{
  "geometry": {
    "type": "Point",
    "coordinates": [
      -84.85,
      32.8167
    ]
  },
  "type": "Feature",
  "properties": {
    "hierarchy": [
      "tgn:2184421",
      "tgn:1000001",
      "tgn:7012149",
      "tgn:2000363",
      "tgn:7007248",
      "tgn:7029392"
    ],
    "placetype": [
      "aat:300006191"
    ],
    "id": 2184421,
    "name:xx": "Bobolink Lake"
  }
}
