{
  "type": "FeatureCollection",
  "features": [
    {
      "geometry": {
        "type": "Point",
        "coordinates": [
          -97.2,
          36.25
        ]
      },
      "type": "Feature",
      "properties": {
        "hierarchy": [
          "tgn:2774050",
          "tgn:1000001",
          "tgn:7012149",
          "tgn:2001674",
          "tgn:7007707",
          "tgn:7029392"
        ],
        "placetype": [
          "aat:300008706"
        ],
        "id": 2774050,
        "name:xx": "Willow Creek"
      }
    },
    {
      "geometry": {
        "type": "Point",
        "coordinates": [
          -95.2167,
          36.8667
        ]
      },
      "type": "Feature",
      "properties": {
        "hierarchy": [
          "tgn:2774051",
          "tgn:1000001",
          "tgn:2001640",
          "tgn:7012149",
          "tgn:7007707",
          "tgn:7029392"
        ],
        "placetype": [
          "aat:300008706"
        ],
        "id": 2774051,
        "name:xx": "Willow Creek"
      }
    },
    {
      "geometry": {
        "type": "Point",
        "coordinates": [
          -97.9333,
          34.5333
        ]
      },
      "type": "Feature",
      "properties": {
        "hierarchy": [
          "tgn:2774052",
          "tgn:1000001",
          "tgn:7012149",
          "tgn:2001691",
          "tgn:7007707",
          "tgn:7029392"
        ],
        "placetype": [
          "aat:300008706"
        ],
        "id": 2774052,
        "name:xx": "Willow Creek"
      }
    },
    {
      "geometry": {
        "type": "Point",
        "coordinates": [
          -97.2667,
          35.0667
        ]
      },
      "type": "Feature",
      "properties": {
        "hierarchy": [
          "tgn:2774053",
          "tgn:1000001",
          "tgn:2001636",
          "tgn:7012149",
          "tgn:7007707",
          "tgn:7029392"
        ],
        "placetype": [
          "aat:300008706"
        ],
        "id": 2774053,
        "name:xx": "Willow Creek"
      }
    },
    {
      "geometry": {
        "type": "Point",
        "coordinates": [
          -99.8333,
          36.1667
        ]
      },
      "type": "Feature",
      "properties": {
        "hierarchy": [
          "tgn:2774054",
          "tgn:1000001",
          "tgn:2001645",
          "tgn:7012149",
          "tgn:7007707",
          "tgn:7029392"
        ],
        "placetype": [
          "aat:300008706"
        ],
        "id": 2774054,
        "name:xx": "Willow Creek"
      }
    },
    {
      "geometry": {
        "type": "Point",
        "coordinates": [
          -100.75,
          36.6167
        ]
      },
      "type": "Feature",
      "properties": {
        "hierarchy": [
          "tgn:2774055",
          "tgn:2001626",
          "tgn:1000001",
          "tgn:7012149",
          "tgn:7007707",
          "tgn:7029392"
        ],
        "placetype": [
          "aat:300008706"
        ],
        "id": 2774055,
        "name:xx": "Willow Creek"
      }
    },
    {
      "geometry": {
        "type": "Point",
        "coordinates": [
          -102.9167,
          36.7833
        ]
      },
      "type": "Feature",
      "properties": {
        "hierarchy": [
          "tgn:2774056",
          "tgn:1000001",
          "tgn:2001635",
          "tgn:7012149",
          "tgn:7007707",
          "tgn:7029392"
        ],
        "placetype": [
          "aat:300008706"
        ],
        "id": 2774056,
        "name:xx": "Willow Creek"
      }
    },
    {
      "geometry": {
        "type": "Point",
        "coordinates": [
          -98.4333,
          35.35
        ]
      },
      "type": "Feature",
      "properties": {
        "hierarchy": [
          "tgn:2774057",
          "tgn:1000001",
          "tgn:2001630",
          "tgn:7012149",
          "tgn:7007707",
          "tgn:7029392"
        ],
        "placetype": [
          "aat:300008706"
        ],
        "id": 2774057,
        "name:xx": "Willow Creek"
      }
    },
    {
      "geometry": {
        "type": "Point",
        "coordinates": [
          -124.15,
          42.0833
        ]
      },
      "type": "Feature",
      "properties": {
        "hierarchy": [
          "tgn:2774058",
          "tgn:1000001",
          "tgn:2001704",
          "tgn:7012149",
          "tgn:7007708",
          "tgn:7029392"
        ],
        "placetype": [
          "aat:300008706"
        ],
        "id": 2774058,
        "name:xx": "Willow Creek"
      }
    },
    {
      "geometry": {
        "type": "Point",
        "coordinates": [
          -120.2333,
          42.0667
        ]
      },
      "type": "Feature",
      "properties": {
        "hierarchy": [
          "tgn:2774059",
          "tgn:1000001",
          "tgn:7012149",
          "tgn:2001715",
          "tgn:7007708",
          "tgn:7029392"
        ],
        "placetype": [
          "aat:300008706"
        ],
        "id": 2774059,
        "name:xx": "Willow Creek"
      }
    }
  ]
}
