{
  "geometry": {
    "type": "Point",
    "coordinates": [
      -87.45,
      46.0667
    ]
  },
  "type": "Feature",
  "properties": {
    "hierarchy": [
      "tgn:2407101",
      "tgn:1000001",
      "tgn:7012149",
      "tgn:7007520",
      "tgn:7029392"
    ],
    "placetype": [
      "aat:300008699"
    ],
    "id": 2407101,
    "name:xx": "Hunters Brook"
  }
}
