{
  "geometry": {
    "type": "Point",
    "coordinates": [
      27.7333,
      64.8333
    ]
  },
  "type": "Feature",
  "properties": {
    "hierarchy": [
      "tgn:1031519",
      "tgn:1001475",
      "tgn:1000003",
      "tgn:1000069",
      "tgn:7029392"
    ],
    "placetype": [
      "aat:300008347"
    ],
    "id": 1031519,
    "name:xx": "Puolanka"
  }
}
