{
  "geometry": {
    "type": "Point",
    "coordinates": [
      77.99227,
      21.728704
    ]
  },
  "type": "Feature",
  "properties": {
    "hierarchy": [
      "tgn:7545911",
      "tgn:1000004",
      "tgn:7000198",
      "tgn:1001894",
      "tgn:7029392"
    ],
    "placetype": [
      "aat:300008347"
    ],
    "name:en": "Bārvi",
    "id": 7545911
  }
}
