{
  "geometry": {
    "type": "Point",
    "coordinates": [
      -105.9333,
      35.7167
    ]
  },
  "type": "Feature",
  "properties": {
    "hierarchy": [
      "tgn:2341123",
      "tgn:1000001",
      "tgn:7012149",
      "tgn:2001454",
      "tgn:7007566",
      "tgn:7029392"
    ],
    "placetype": [
      "aat:300008701"
    ],
    "id": 2341123,
    "name:xx": "Frijoles, Arroyo de los"
  }
}
