{
  "geometry": {
    "type": "Point",
    "coordinates": [
      -86.9833,
      41.0667
    ]
  },
  "type": "Feature",
  "properties": {
    "hierarchy": [
      "tgn:2030983",
      "tgn:1000001",
      "tgn:7012149",
      "tgn:1002512",
      "tgn:7007252",
      "tgn:7029392"
    ],
    "placetype": [
      "aat:300008347",
      "aat:300387210"
    ],
    "id": 2030983,
    "name:xx": "Baileys Corner"
  }
}
