{
  "geometry": {
    "type": "Point",
    "coordinates": [
      31.497,
      -29.225
    ]
  },
  "type": "Feature",
  "properties": {
    "hierarchy": [
      "tgn:1131079",
      "tgn:7001242",
      "tgn:7016749",
      "tgn:1000193",
      "tgn:7029392"
    ],
    "placetype": [
      "aat:300008707"
    ],
    "id": 1131079,
    "name:xx": "Tugela"
  }
}
