{
  "geometry": {
    "type": "Point",
    "coordinates": [
      45.8333,
      -24.4167
    ]
  },
  "type": "Feature",
  "properties": {
    "hierarchy": [
      "tgn:1090907",
      "tgn:7001242",
      "tgn:1001575",
      "tgn:1000173",
      "tgn:7029392"
    ],
    "placetype": [
      "aat:300008347"
    ],
    "id": 1090907,
    "name:xx": "Imanombo"
  }
}
