{
  "geometry": {
    "type": "Point",
    "coordinates": [
      -84.5667,
      35.45
    ]
  },
  "type": "Feature",
  "properties": {
    "hierarchy": [
      "tgn:2412819",
      "tgn:1000001",
      "tgn:7012149",
      "tgn:7022542",
      "tgn:7007825",
      "tgn:7029392"
    ],
    "placetype": [
      "aat:300008697"
    ],
    "id": 2412819,
    "name:xx": "Ingleside Spring"
  }
}
