{
  "geometry": {
    "type": "Point",
    "coordinates": [
      -96.3167,
      50.6333
    ]
  },
  "type": "Feature",
  "properties": {
    "hierarchy": [
      "tgn:1131835",
      "tgn:7005685",
      "tgn:1000001",
      "tgn:7029392"
    ],
    "placetype": [
      "aat:300008707"
    ],
    "id": 1131835,
    "name:xx": "Winnipeg"
  }
}
