{
  "type": "FeatureCollection",
  "features": [
    {
      "geometry": {
        "type": "Point",
        "coordinates": [
          -100.783333,
          27.733333
        ]
      },
      "type": "Feature",
      "properties": {
        "hierarchy": [
          "tgn:7391650",
          "tgn:1001853",
          "tgn:1000001",
          "tgn:7005560",
          "tgn:7029392"
        ],
        "placetype": [
          "aat:300008347"
        ],
        "id": 7391650,
        "name:xx": "Rancho Tanque Herradur"
      }
    },
    {
      "geometry": {
        "type": "Point",
        "coordinates": [
          -101.466667,
          26.4
        ]
      },
      "type": "Feature",
      "properties": {
        "hierarchy": [
          "tgn:7391651",
          "tgn:1001853",
          "tgn:1000001",
          "tgn:7005560",
          "tgn:7029392"
        ],
        "placetype": [
          "aat:300008347"
        ],
        "id": 7391651,
        "name:xx": "Rancho Tanque Favorite"
      }
    },
    {
      "geometry": {
        "type": "Point",
        "coordinates": [
          -100.65,
          27.733333
        ]
      },
      "type": "Feature",
      "properties": {
        "hierarchy": [
          "tgn:7391652",
          "tgn:1001853",
          "tgn:1000001",
          "tgn:7005560",
          "tgn:7029392"
        ],
        "placetype": [
          "aat:300008347"
        ],
        "id": 7391652,
        "name:xx": "Rancho Tanque El Indio"
      }
    },
    {
      "geometry": {
        "type": "Point",
        "coordinates": [
          -101.383333,
          24.2
        ]
      },
      "type": "Feature",
      "properties": {
        "hierarchy": [
          "tgn:7391653",
          "tgn:1000001",
          "tgn:7005601",
          "tgn:7005560",
          "tgn:7029392"
        ],
        "placetype": [
          "aat:300008347"
        ],
        "id": 7391653,
        "name:xx": "Rancho Tanque de San Angel"
      }
    },
    {
      "geometry": {
        "type": "Point",
        "coordinates": [
          -102.583333,
          24.433333
        ]
      },
      "type": "Feature",
      "properties": {
        "hierarchy": [
          "tgn:7391654",
          "tgn:7005583",
          "tgn:1000001",
          "tgn:7005560",
          "tgn:7029392"
        ],
        "placetype": [
          "aat:300008347"
        ],
        "id": 7391654,
        "name:xx": "Rancho Tanque del Alambre"
      }
    },
    {
      "geometry": {
        "type": "Point",
        "coordinates": [
          -99.1,
          24.9
        ]
      },
      "type": "Feature",
      "properties": {
        "hierarchy": [
          "tgn:7391655",
          "tgn:1000001",
          "tgn:7005597",
          "tgn:7005560",
          "tgn:7029392"
        ],
        "placetype": [
          "aat:300008347"
        ],
        "id": 7391655,
        "name:xx": "Rancho Tanque de Flores"
      }
    },
    {
      "geometry": {
        "type": "Point",
        "coordinates": [
          -100.8,
          25.033333
        ]
      },
      "type": "Feature",
      "properties": {
        "hierarchy": [
          "tgn:7391656",
          "tgn:1000001",
          "tgn:7005589",
          "tgn:7005560",
          "tgn:7029392"
        ],
        "placetype": [
          "aat:300008347"
        ],
        "id": 7391656,
        "name:xx": "Rancho Tanque Colorado"
      }
    },
    {
      "geometry": {
        "type": "Point",
        "coordinates": [
          -100.1,
          27.833333
        ]
      },
      "type": "Feature",
      "properties": {
        "hierarchy": [
          "tgn:7391657",
          "tgn:1001853",
          "tgn:1000001",
          "tgn:7005560",
          "tgn:7029392"
        ],
        "placetype": [
          "aat:300008347"
        ],
        "id": 7391657,
        "name:xx": "Rancho Tanquecillos"
      }
    },
    {
      "geometry": {
        "type": "Point",
        "coordinates": [
          -102.566667,
          27.2
        ]
      },
      "type": "Feature",
      "properties": {
        "hierarchy": [
          "tgn:7391658",
          "tgn:1001853",
          "tgn:1000001",
          "tgn:7005560",
          "tgn:7029392"
        ],
        "placetype": [
          "aat:300008347"
        ],
        "id": 7391658,
        "name:xx": "Rancho Tanquecillos"
      }
    },
    {
      "geometry": {
        "type": "Point",
        "coordinates": [
          -97.983333,
          24.1
        ]
      },
      "type": "Feature",
      "properties": {
        "hierarchy": [
          "tgn:7391659",
          "tgn:1000001",
          "tgn:7005597",
          "tgn:7005560",
          "tgn:7029392"
        ],
        "placetype": [
          "aat:300008347"
        ],
        "id": 7391659,
        "name:xx": "Rancho Tangumba"
      }
    }
  ]
}
