{
  "geometry": {
    "type": "Point",
    "coordinates": [
      -83.6667,
      35.0667
    ]
  },
  "type": "Feature",
  "properties": {
    "hierarchy": [
      "tgn:2407972",
      "tgn:1000001",
      "tgn:2001483",
      "tgn:7012149",
      "tgn:7007709",
      "tgn:7029392"
    ],
    "placetype": [
      "aat:300008706"
    ],
    "id": 2407972,
    "name:xx": "Hurricane Creek"
  }
}
