{
  "geometry": {
    "type": "Point",
    "coordinates": [
      -108.3167,
      31.4167
    ]
  },
  "type": "Feature",
  "properties": {
    "hierarchy": [
      "tgn:2258711",
      "tgn:1000001",
      "tgn:7012149",
      "tgn:2001440",
      "tgn:7007566",
      "tgn:7029392"
    ],
    "placetype": [
      "aat:300008761"
    ],
    "id": 2258711,
    "name:xx": "Cottonwood Canyon"
  }
}
