{
  "geometry": {
    "type": "Point",
    "coordinates": [
      12.25,
      49.75
    ]
  },
  "type": "Feature",
  "properties": {
    "hierarchy": [
      "tgn:7164794",
      "tgn:7003669",
      "tgn:1000003",
      "tgn:7000084",
      "tgn:7029392"
    ],
    "placetype": [
      "aat:300008777"
    ],
    "id": 7164794,
    "name:xx": "Hundsrück"
  }
}
