{
  "geometry": {
    "type": "Point",
    "coordinates": [
      -93.9667,
      36.4667
    ]
  },
  "type": "Feature",
  "properties": {
    "hierarchy": [
      "tgn:2344309",
      "tgn:1000001",
      "tgn:2000108",
      "tgn:7016172",
      "tgn:7012149",
      "tgn:7029392"
    ],
    "placetype": [
      "aat:300266640"
    ],
    "id": 2344309,
    "name:xx": "Gann Ridge"
  }
}
