{
  "geometry": {
    "type": "Point",
    "coordinates": [
      -80.85,
      35.5167
    ]
  },
  "type": "Feature",
  "properties": {
    "hierarchy": [
      "tgn:2276682",
      "tgn:1000001",
      "tgn:7012149",
      "tgn:7007709",
      "tgn:7029392"
    ],
    "placetype": [
      "aat:300008706"
    ],
    "id": 2276682,
    "name:xx": "Davidson Creek"
  }
}
