{
  "type": "FeatureCollection",
  "features": [
    {
      "geometry": {
        "type": "Point",
        "coordinates": [
          -106.0667,
          40.4
        ]
      },
      "type": "Feature",
      "properties": {
        "hierarchy": [
          "tgn:2230270",
          "tgn:1000001",
          "tgn:7012149",
          "tgn:2000226",
          "tgn:7007158",
          "tgn:7029392"
        ],
        "placetype": [
          "aat:300006191"
        ],
        "id": 2230270,
        "name:xx": "Cemetery Lake"
      }
    },
    {
      "geometry": {
        "type": "Point",
        "coordinates": [
          -81.9333,
          29.2
        ]
      },
      "type": "Feature",
      "properties": {
        "hierarchy": [
          "tgn:2230271",
          "tgn:1000001",
          "tgn:7012149",
          "tgn:1002631",
          "tgn:7007240",
          "tgn:7029392"
        ],
        "placetype": [
          "aat:300008680"
        ],
        "id": 2230271,
        "name:xx": "Cemetery Lake"
      }
    },
    {
      "geometry": {
        "type": "Point",
        "coordinates": [
          -83,
          29.7833
        ]
      },
      "type": "Feature",
      "properties": {
        "hierarchy": [
          "tgn:2230272",
          "tgn:1000001",
          "tgn:2000263",
          "tgn:7012149",
          "tgn:7007240",
          "tgn:7029392"
        ],
        "placetype": [
          "aat:300008680"
        ],
        "id": 2230272,
        "name:xx": "Cemetery Lake"
      }
    },
    {
      "geometry": {
        "type": "Point",
        "coordinates": [
          -85.0333,
          41.95
        ]
      },
      "type": "Feature",
      "properties": {
        "hierarchy": [
          "tgn:2230273",
          "tgn:1000001",
          "tgn:1002195",
          "tgn:7012149",
          "tgn:7007520",
          "tgn:7029392"
        ],
        "placetype": [
          "aat:300008680"
        ],
        "id": 2230273,
        "name:xx": "Cemetery Lake"
      }
    },
    {
      "geometry": {
        "type": "Point",
        "coordinates": [
          -88.4667,
          46.2333
        ]
      },
      "type": "Feature",
      "properties": {
        "hierarchy": [
          "tgn:2230274",
          "tgn:1000001",
          "tgn:7012149",
          "tgn:2000966",
          "tgn:7007520",
          "tgn:7029392"
        ],
        "placetype": [
          "aat:300008680"
        ],
        "id": 2230274,
        "name:xx": "Cemetery Lake"
      }
    },
    {
      "geometry": {
        "type": "Point",
        "coordinates": [
          -88.9,
          46.85
        ]
      },
      "type": "Feature",
      "properties": {
        "hierarchy": [
          "tgn:2230275",
          "tgn:1000001",
          "tgn:7012149",
          "tgn:2000963",
          "tgn:7007520",
          "tgn:7029392"
        ],
        "placetype": [
          "aat:300008680"
        ],
        "id": 2230275,
        "name:xx": "Cemetery Lake"
      }
    },
    {
      "geometry": {
        "type": "Point",
        "coordinates": [
          -92.8833,
          46.25
        ]
      },
      "type": "Feature",
      "properties": {
        "hierarchy": [
          "tgn:2230276",
          "tgn:1000001",
          "tgn:7012149",
          "tgn:2001056",
          "tgn:7007521",
          "tgn:7029392"
        ],
        "placetype": [
          "aat:300008680"
        ],
        "id": 2230276,
        "name:xx": "Cemetery Lake"
      }
    },
    {
      "geometry": {
        "type": "Point",
        "coordinates": [
          -93.6333,
          47.7333
        ]
      },
      "type": "Feature",
      "properties": {
        "hierarchy": [
          "tgn:2230277",
          "tgn:1000001",
          "tgn:7012149",
          "tgn:2001029",
          "tgn:7007521",
          "tgn:7029392"
        ],
        "placetype": [
          "aat:300008680"
        ],
        "id": 2230277,
        "name:xx": "Cemetery Lake"
      }
    },
    {
      "geometry": {
        "type": "Point",
        "coordinates": [
          -123.9333,
          46.15
        ]
      },
      "type": "Feature",
      "properties": {
        "hierarchy": [
          "tgn:2230278",
          "tgn:1000001",
          "tgn:1002276",
          "tgn:7012149",
          "tgn:7007708",
          "tgn:7029392"
        ],
        "placetype": [
          "aat:300008680"
        ],
        "id": 2230278,
        "name:xx": "Cemetery Lake"
      }
    },
    {
      "geometry": {
        "type": "Point",
        "coordinates": [
          -94.8167,
          32.4833
        ]
      },
      "type": "Feature",
      "properties": {
        "hierarchy": [
          "tgn:2230279",
          "tgn:1000001",
          "tgn:7012149",
          "tgn:1002427",
          "tgn:7007826",
          "tgn:7029392"
        ],
        "placetype": [
          "aat:300006191"
        ],
        "id": 2230279,
        "name:xx": "Cemetery Lake"
      }
    }
  ]
}
