{
  "geometry": {
    "type": "Point",
    "coordinates": [
      75.60166,
      25.96688
    ]
  },
  "type": "Feature",
  "properties": {
    "hierarchy": [
      "tgn:7570103",
      "tgn:1000004",
      "tgn:7000198",
      "tgn:7016788",
      "tgn:7029392"
    ],
    "placetype": [
      "aat:300008347"
    ],
    "name:en": "Karesya ki Dhāni",
    "id": 7570103
  }
}
