{
  "geometry": {
    "type": "Point",
    "coordinates": [
      -104.4167,
      37.2667
    ]
  },
  "type": "Feature",
  "properties": {
    "hierarchy": [
      "tgn:2424125",
      "tgn:1000001",
      "tgn:7012149",
      "tgn:2000227",
      "tgn:7007158",
      "tgn:7029392"
    ],
    "placetype": [
      "aat:300008680"
    ],
    "id": 2424125,
    "name:xx": "Johns Lake"
  }
}
