{
  "geometry": {
    "type": "Point",
    "coordinates": [
      -94.8667,
      36.55
    ]
  },
  "type": "Feature",
  "properties": {
    "hierarchy": [
      "tgn:2696991",
      "tgn:1000001",
      "tgn:2001643",
      "tgn:7012149",
      "tgn:7007707",
      "tgn:7029392"
    ],
    "placetype": [
      "aat:300008850"
    ],
    "id": 2696991,
    "name:xx": "Stoney Point"
  }
}
