{
  "geometry": {
    "type": "Point",
    "coordinates": [
      116.9333,
      38.8667
    ]
  },
  "type": "Feature",
  "properties": {
    "hierarchy": [
      "tgn:1139632",
      "tgn:1000004",
      "tgn:1000960",
      "tgn:1000111",
      "tgn:7029392"
    ],
    "placetype": [
      "aat:300008347"
    ],
    "id": 1139632,
    "name:xx": "Shuangtang"
  }
}
