{
  "type": "FeatureCollection",
  "features": [
    {
      "geometry": {
        "type": "Point",
        "coordinates": [
          -124.2,
          43.0333
        ]
      },
      "type": "Feature",
      "properties": {
        "hierarchy": [
          "tgn:2261610",
          "tgn:1000001",
          "tgn:2001702",
          "tgn:7012149",
          "tgn:7007708",
          "tgn:7029392"
        ],
        "placetype": [
          "aat:300008706"
        ],
        "id": 2261610,
        "name:xx": "Cove Creek"
      }
    },
    {
      "geometry": {
        "type": "Point",
        "coordinates": [
          -122.8,
          43.55
        ]
      },
      "type": "Feature",
      "properties": {
        "hierarchy": [
          "tgn:2261611",
          "tgn:1000001",
          "tgn:7012149",
          "tgn:2001716",
          "tgn:7007708",
          "tgn:7029392"
        ],
        "placetype": [
          "aat:300008706"
        ],
        "id": 2261611,
        "name:xx": "Cove Creek"
      }
    },
    {
      "geometry": {
        "type": "Point",
        "coordinates": [
          -123.6667,
          44.4167
        ]
      },
      "type": "Feature",
      "properties": {
        "hierarchy": [
          "tgn:2261612",
          "tgn:1000001",
          "tgn:7012149",
          "tgn:7007708",
          "tgn:7029392"
        ],
        "placetype": [
          "aat:300008706"
        ],
        "id": 2261612,
        "name:xx": "Cove Creek"
      }
    },
    {
      "geometry": {
        "type": "Point",
        "coordinates": [
          -118.2167,
          45.1167
        ]
      },
      "type": "Feature",
      "properties": {
        "hierarchy": [
          "tgn:2261613",
          "tgn:1000001",
          "tgn:7012149",
          "tgn:2001721",
          "tgn:7007708",
          "tgn:7029392"
        ],
        "placetype": [
          "aat:300008706"
        ],
        "id": 2261613,
        "name:xx": "Cove Creek"
      }
    },
    {
      "geometry": {
        "type": "Point",
        "coordinates": [
          -116.5833,
          45.5667
        ]
      },
      "type": "Feature",
      "properties": {
        "hierarchy": [
          "tgn:2261614",
          "tgn:1000001",
          "tgn:7012149",
          "tgn:2001722",
          "tgn:7007708",
          "tgn:7029392"
        ],
        "placetype": [
          "aat:300008706"
        ],
        "id": 2261614,
        "name:xx": "Cove Creek"
      }
    },
    {
      "geometry": {
        "type": "Point",
        "coordinates": [
          -122.5167,
          42.2
        ]
      },
      "type": "Feature",
      "properties": {
        "hierarchy": [
          "tgn:2261615",
          "tgn:1000001",
          "tgn:7012149",
          "tgn:2001711",
          "tgn:7007708",
          "tgn:7029392"
        ],
        "placetype": [
          "aat:300008706"
        ],
        "id": 2261615,
        "name:xx": "Cove Creek"
      }
    },
    {
      "geometry": {
        "type": "Point",
        "coordinates": [
          -117.25,
          43.2167
        ]
      },
      "type": "Feature",
      "properties": {
        "hierarchy": [
          "tgn:2261616",
          "tgn:1000001",
          "tgn:7012149",
          "tgn:2001718",
          "tgn:7007708",
          "tgn:7029392"
        ],
        "placetype": [
          "aat:300008706"
        ],
        "id": 2261616,
        "name:xx": "Cove Creek"
      }
    },
    {
      "geometry": {
        "type": "Point",
        "coordinates": [
          -120.3833,
          44.9667
        ]
      },
      "type": "Feature",
      "properties": {
        "hierarchy": [
          "tgn:2261617",
          "tgn:1000001",
          "tgn:7012149",
          "tgn:2001723",
          "tgn:7007708",
          "tgn:7029392"
        ],
        "placetype": [
          "aat:300008706"
        ],
        "id": 2261617,
        "name:xx": "Cove Creek"
      }
    },
    {
      "geometry": {
        "type": "Point",
        "coordinates": [
          -120.9833,
          44.9667
        ]
      },
      "type": "Feature",
      "properties": {
        "hierarchy": [
          "tgn:2261618",
          "tgn:1000001",
          "tgn:7012149",
          "tgn:1002990",
          "tgn:7007708",
          "tgn:7029392"
        ],
        "placetype": [
          "aat:300008706"
        ],
        "id": 2261618,
        "name:xx": "Cove Creek"
      }
    },
    {
      "geometry": {
        "type": "Point",
        "coordinates": [
          -77.0833,
          40.3333
        ]
      },
      "type": "Feature",
      "properties": {
        "hierarchy": [
          "tgn:2261619",
          "tgn:1000001",
          "tgn:7012149",
          "tgn:1002779",
          "tgn:7007710",
          "tgn:7029392"
        ],
        "placetype": [
          "aat:300008706"
        ],
        "id": 2261619,
        "name:xx": "Cove Creek"
      }
    }
  ]
}
