{
  "geometry": {
    "type": "Point",
    "coordinates": [
      -119.0833,
      44.6833
    ]
  },
  "type": "Feature",
  "properties": {
    "hierarchy": [
      "tgn:2467187",
      "tgn:1000001",
      "tgn:7012149",
      "tgn:2001708",
      "tgn:7007708",
      "tgn:7029392"
    ],
    "placetype": [
      "aat:300386845"
    ],
    "id": 2467187,
    "name:xx": "Long Creek Municipal Watershed"
  }
}
