{
  "geometry": {
    "type": "Point",
    "coordinates": [
      -88.7167,
      37.9167
    ]
  },
  "type": "Feature",
  "properties": {
    "hierarchy": [
      "tgn:2373206",
      "tgn:1000001",
      "tgn:7012149",
      "tgn:7007251",
      "tgn:7029392"
    ],
    "placetype": [
      "aat:300008706"
    ],
    "id": 2373206,
    "name:xx": "Halltown Creek"
  }
}
