{
  "geometry": {
    "type": "Point",
    "coordinates": [
      79.933487,
      28.376154
    ]
  },
  "type": "Feature",
  "properties": {
    "hierarchy": [
      "tgn:7548468",
      "tgn:1000004",
      "tgn:7000198",
      "tgn:7016722",
      "tgn:7029392"
    ],
    "placetype": [
      "aat:300008347"
    ],
    "name:en": "Deoria Kalān",
    "id": 7548468
  }
}
