{
  "geometry": {
    "type": "Point",
    "coordinates": [
      33.3333,
      50.2667
    ]
  },
  "type": "Feature",
  "properties": {
    "hierarchy": [
      "tgn:1059323",
      "tgn:1000003",
      "tgn:7011666",
      "tgn:7006660",
      "tgn:7029392"
    ],
    "placetype": [
      "aat:300008347"
    ],
    "id": 1059323,
    "name:xx": "Sencha"
  }
}
