{
  "geometry": {
    "type": "Point",
    "coordinates": [
      -75.9833,
      37.95
    ]
  },
  "type": "Feature",
  "properties": {
    "hierarchy": [
      "tgn:7022193",
      "tgn:1000001",
      "tgn:1002902",
      "tgn:7012149",
      "tgn:7007516",
      "tgn:7029392"
    ],
    "placetype": [
      "aat:300008791"
    ],
    "id": 7022193,
    "name:xx": "Horse Hammock"
  }
}
