{
  "geometry": {
    "type": "Point",
    "coordinates": [
      -96.0333,
      31.3833
    ]
  },
  "type": "Feature",
  "properties": {
    "hierarchy": [
      "tgn:2611764",
      "tgn:1000001",
      "tgn:7012149",
      "tgn:1002590",
      "tgn:7007826",
      "tgn:7029392"
    ],
    "placetype": [
      "aat:300006191"
    ],
    "id": 2611764,
    "name:xx": "Red Oak Lake"
  }
}
