{
  "geometry": {
    "type": "Point",
    "coordinates": [
      5.95,
      51.75
    ]
  },
  "type": "Feature",
  "properties": {
    "hierarchy": [
      "tgn:7270774",
      "tgn:7003619",
      "tgn:1000003",
      "tgn:7016845",
      "tgn:7029392"
    ],
    "placetype": [
      "aat:300008777"
    ],
    "name:nl": "Sint Jansberg",
    "id": 7270774
  }
}
