{
  "geometry": {
    "type": "Point",
    "coordinates": [
      -76.5833,
      41.2833
    ]
  },
  "type": "Feature",
  "properties": {
    "hierarchy": [
      "tgn:2142570",
      "tgn:1000001",
      "tgn:7012149",
      "tgn:1002613",
      "tgn:7007710",
      "tgn:7029392"
    ],
    "placetype": [
      "aat:300008798"
    ],
    "id": 2142570,
    "name:xx": "Bad Hill"
  }
}
