{
  "type": "FeatureCollection",
  "features": [
    {
      "geometry": {
        "type": "Point",
        "coordinates": [
          -102.75,
          19.133333
        ]
      },
      "type": "Feature",
      "properties": {
        "hierarchy": [
          "tgn:7372730",
          "tgn:1000001",
          "tgn:7005590",
          "tgn:7005560",
          "tgn:7029392"
        ],
        "placetype": [
          "aat:300000241"
        ],
        "id": 7372730,
        "name:xx": "La Ordeñita"
      }
    },
    {
      "geometry": {
        "type": "Point",
        "coordinates": [
          -101.616667,
          20.483333
        ]
      },
      "type": "Feature",
      "properties": {
        "hierarchy": [
          "tgn:7372731",
          "tgn:7005584",
          "tgn:1000001",
          "tgn:7005560",
          "tgn:7029392"
        ],
        "placetype": [
          "aat:300008347"
        ],
        "id": 7372731,
        "name:xx": "La Ordeña de Parajes"
      }
    },
    {
      "geometry": {
        "type": "Point",
        "coordinates": [
          -102.1,
          20.833333
        ]
      },
      "type": "Feature",
      "properties": {
        "hierarchy": [
          "tgn:7372732",
          "tgn:7005586",
          "tgn:1000001",
          "tgn:7005560",
          "tgn:7029392"
        ],
        "placetype": [
          "aat:300006191"
        ],
        "id": 7372732,
        "name:xx": "La Ordeña"
      }
    },
    {
      "geometry": {
        "type": "Point",
        "coordinates": [
          -104.183333,
          25.4
        ]
      },
      "type": "Feature",
      "properties": {
        "hierarchy": [
          "tgn:7372733",
          "tgn:7005583",
          "tgn:1000001",
          "tgn:7005560",
          "tgn:7029392"
        ],
        "placetype": [
          "aat:300008347"
        ],
        "id": 7372733,
        "name:xx": "La Ordeña"
      }
    },
    {
      "geometry": {
        "type": "Point",
        "coordinates": [
          -102.933333,
          22.9
        ]
      },
      "type": "Feature",
      "properties": {
        "hierarchy": [
          "tgn:7372734",
          "tgn:1000001",
          "tgn:7005601",
          "tgn:7005560",
          "tgn:7029392"
        ],
        "placetype": [
          "aat:300008347"
        ],
        "id": 7372734,
        "name:xx": "La Ordeña"
      }
    },
    {
      "geometry": {
        "type": "Point",
        "coordinates": [
          -102.533333,
          22.083333
        ]
      },
      "type": "Feature",
      "properties": {
        "hierarchy": [
          "tgn:7372735",
          "tgn:7005579",
          "tgn:1000001",
          "tgn:7005560",
          "tgn:7029392"
        ],
        "placetype": [
          "aat:300008347"
        ],
        "id": 7372735,
        "name:xx": "La Ordeña"
      }
    },
    {
      "geometry": {
        "type": "Point",
        "coordinates": [
          -102.716667,
          22
        ]
      },
      "type": "Feature",
      "properties": {
        "hierarchy": [
          "tgn:7372736",
          "tgn:7005579",
          "tgn:1000001",
          "tgn:7005560",
          "tgn:7029392"
        ],
        "placetype": [
          "aat:300008347"
        ],
        "id": 7372736,
        "name:xx": "La Ordeña"
      }
    },
    {
      "geometry": {
        "type": "Point",
        "coordinates": [
          -102.166667,
          21.95
        ]
      },
      "type": "Feature",
      "properties": {
        "hierarchy": [
          "tgn:7372737",
          "tgn:7005579",
          "tgn:1000001",
          "tgn:7005560",
          "tgn:7029392"
        ],
        "placetype": [
          "aat:300008347"
        ],
        "id": 7372737,
        "name:xx": "La Ordeña"
      }
    },
    {
      "geometry": {
        "type": "Point",
        "coordinates": [
          -100.633333,
          21.883333
        ]
      },
      "type": "Feature",
      "properties": {
        "hierarchy": [
          "tgn:7372738",
          "tgn:1000001",
          "tgn:7005594",
          "tgn:7005560",
          "tgn:7029392"
        ],
        "placetype": [
          "aat:300008347"
        ],
        "id": 7372738,
        "name:xx": "La Ordeña"
      }
    },
    {
      "geometry": {
        "type": "Point",
        "coordinates": [
          -100.116667,
          21.316667
        ]
      },
      "type": "Feature",
      "properties": {
        "hierarchy": [
          "tgn:7372739",
          "tgn:7005584",
          "tgn:1000001",
          "tgn:7005560",
          "tgn:7029392"
        ],
        "placetype": [
          "aat:300008347"
        ],
        "id": 7372739,
        "name:xx": "La Ordeña"
      }
    }
  ]
}
