{
  "geometry": {
    "type": "Point",
    "coordinates": [
      -89.4167,
      45.75
    ]
  },
  "type": "Feature",
  "properties": {
    "hierarchy": [
      "tgn:2461097",
      "tgn:1000001",
      "tgn:7012149",
      "tgn:2002342",
      "tgn:7007922",
      "tgn:7029392"
    ],
    "placetype": [
      "aat:300008680"
    ],
    "id": 2461097,
    "name:xx": "Little Spider Lake"
  }
}
