{
  "geometry": {
    "type": "Point",
    "coordinates": [
      -85.4833,
      41.3667
    ]
  },
  "type": "Feature",
  "properties": {
    "hierarchy": [
      "tgn:2634231",
      "tgn:1000001",
      "tgn:7012149",
      "tgn:1002723",
      "tgn:7007252",
      "tgn:7029392"
    ],
    "placetype": [
      "aat:300008680"
    ],
    "id": 2634231,
    "name:xx": "Russell Lake"
  }
}
