{
  "geometry": {
    "type": "Point",
    "coordinates": [
      -87.0333,
      30.55
    ]
  },
  "type": "Feature",
  "properties": {
    "hierarchy": [
      "tgn:2128047",
      "tgn:1000001",
      "tgn:7012149",
      "tgn:2000285",
      "tgn:7007240",
      "tgn:7029392"
    ],
    "placetype": [
      "aat:300008680"
    ],
    "id": 2128047,
    "name:xx": "Albert Gordon Pond"
  }
}
