{
  "geometry": {
    "type": "Point",
    "coordinates": [
      78.727001,
      29.874785
    ]
  },
  "type": "Feature",
  "properties": {
    "hierarchy": [
      "tgn:7566965",
      "tgn:1000004",
      "tgn:7000198",
      "tgn:7031786",
      "tgn:7029392"
    ],
    "placetype": [
      "aat:300008347"
    ],
    "name:en": "Kāndākhāl",
    "id": 7566965
  }
}
