{
  "geometry": {
    "type": "Point",
    "coordinates": [
      -114.6167,
      33.4833
    ]
  },
  "type": "Feature",
  "properties": {
    "hierarchy": [
      "tgn:2188125",
      "tgn:1000001",
      "tgn:7012149",
      "tgn:7007157",
      "tgn:7029392"
    ],
    "placetype": [
      "aat:300006075"
    ],
    "id": 2188125,
    "name:xx": "Borrow Pit Drain"
  }
}
