{
  "geometry": {
    "type": "Point",
    "coordinates": [
      32.440512,
      29.480263
    ]
  },
  "type": "Feature",
  "properties": {
    "hierarchy": [
      "tgn:7532939",
      "tgn:7001242",
      "tgn:7016833",
      "tgn:1001110",
      "tgn:7029392"
    ],
    "placetype": [
      "aat:300379998"
    ],
    "name:en": "Abū Daraj, Wādī",
    "id": 7532939
  }
}
