{
  "geometry": {
    "type": "Point",
    "coordinates": [
      71.505814,
      27.319776
    ]
  },
  "type": "Feature",
  "properties": {
    "hierarchy": [
      "tgn:7565417",
      "tgn:1000004",
      "tgn:7000198",
      "tgn:7016788",
      "tgn:7029392"
    ],
    "placetype": [
      "aat:300008347"
    ],
    "name:en": "Jodheri Nādi",
    "id": 7565417
  }
}
