{
  "geometry": {
    "type": "Point",
    "coordinates": [
      11.7167,
      51.1167
    ]
  },
  "type": "Feature",
  "properties": {
    "hierarchy": [
      "tgn:1100341",
      "tgn:1000003",
      "tgn:7003687",
      "tgn:7000084",
      "tgn:7029392"
    ],
    "placetype": [
      "aat:300006891"
    ],
    "id": 1100341,
    "name:xx": "Rudelsburg"
  }
}
