{
  "geometry": {
    "type": "Point",
    "coordinates": [
      113.55,
      22.127
    ]
  },
  "type": "Feature",
  "properties": {
    "hierarchy": [
      "tgn:7031807",
      "tgn:1000004",
      "tgn:7005019",
      "tgn:7029392"
    ],
    "placetype": [
      "aat:300132316"
    ],
    "id": 7031807,
    "name:xx": "Tai Van, Baía de"
  }
}
