{
  "geometry": {
    "type": "Point",
    "coordinates": [
      -120.0333,
      38.8333
    ]
  },
  "type": "Feature",
  "properties": {
    "hierarchy": [
      "tgn:2011159",
      "tgn:1000001",
      "tgn:7012149",
      "tgn:1002350",
      "tgn:7007157",
      "tgn:7029392"
    ],
    "placetype": [
      "aat:300008347"
    ],
    "id": 2011159,
    "name:xx": "Echo Lake"
  }
}
