{
  "geometry": {
    "type": "Point",
    "coordinates": [
      -2.65,
      40.55
    ]
  },
  "type": "Feature",
  "properties": {
    "hierarchy": [
      "tgn:7298065",
      "tgn:7002822",
      "tgn:1001647",
      "tgn:1000003",
      "tgn:1000095",
      "tgn:7029392"
    ],
    "placetype": [
      "aat:300008699"
    ],
    "id": 7298065,
    "name:xx": "Solana, Arroyo de la"
  }
}
