{
  "geometry": {
    "type": "Point",
    "coordinates": [
      11.5833,
      49.45
    ]
  },
  "type": "Feature",
  "properties": {
    "hierarchy": [
      "tgn:7004326",
      "tgn:7003669",
      "tgn:1000003",
      "tgn:7000084",
      "tgn:7029392"
    ],
    "placetype": [
      "aat:300008347",
      "aat:300387218",
      "aat:300008389",
      "aat:300387222",
      "aat:300005135"
    ],
    "id": 7004326,
    "name:de": "Bayreuth"
  }
}
