{
  "geometry": {
    "type": "Point",
    "coordinates": [
      -93.2167,
      42.1833
    ]
  },
  "type": "Feature",
  "properties": {
    "hierarchy": [
      "tgn:2409823",
      "tgn:1000001",
      "tgn:7012149",
      "tgn:2000624",
      "tgn:7007253",
      "tgn:7029392"
    ],
    "placetype": [
      "aat:300008347"
    ],
    "id": 2409823,
    "name:xx": "Illinois Grove"
  }
}
