{
  "geometry": {
    "type": "Point",
    "coordinates": [
      -91.5667,
      43.0833
    ]
  },
  "type": "Feature",
  "properties": {
    "hierarchy": [
      "tgn:2035487",
      "tgn:2000563",
      "tgn:1000001",
      "tgn:7012149",
      "tgn:7007253",
      "tgn:7029392"
    ],
    "placetype": [
      "aat:300008347"
    ],
    "id": 2035487,
    "name:xx": "Postville"
  }
}
