{
  "geometry": {
    "type": "Point",
    "coordinates": [
      6.9667,
      51.0833
    ]
  },
  "type": "Feature",
  "properties": {
    "hierarchy": [
      "tgn:1039183",
      "tgn:1000003",
      "tgn:7003677",
      "tgn:7000084",
      "tgn:7029392"
    ],
    "placetype": [
      "aat:300008347"
    ],
    "id": 1039183,
    "name:xx": "Galkhausen"
  }
}
