{
  "geometry": {
    "type": "Point",
    "coordinates": [
      -118.9833,
      35.4833
    ]
  },
  "type": "Feature",
  "properties": {
    "hierarchy": [
      "tgn:2762062",
      "tgn:1000001",
      "tgn:7012149",
      "tgn:1002545",
      "tgn:7007157",
      "tgn:7029392"
    ],
    "placetype": [
      "aat:300008761"
    ],
    "id": 2762062,
    "name:xx": "West Shore Gulch"
  }
}
