{
  "type": "FeatureCollection",
  "features": [
    {
      "geometry": {
        "type": "Point",
        "coordinates": [
          -83.3667,
          37.85
        ]
      },
      "type": "Feature",
      "properties": {
        "hierarchy": [
          "tgn:2360530",
          "tgn:1000001",
          "tgn:7012149",
          "tgn:2000831",
          "tgn:7007255",
          "tgn:7029392"
        ],
        "placetype": [
          "aat:300008706"
        ],
        "id": 2360530,
        "name:xx": "Grassy Creek"
      }
    },
    {
      "geometry": {
        "type": "Point",
        "coordinates": [
          -83.1667,
          38.45
        ]
      },
      "type": "Feature",
      "properties": {
        "hierarchy": [
          "tgn:2360531",
          "tgn:1000001",
          "tgn:1002240",
          "tgn:7012149",
          "tgn:7007255",
          "tgn:7029392"
        ],
        "placetype": [
          "aat:300008706"
        ],
        "id": 2360531,
        "name:xx": "Grassy Creek"
      }
    },
    {
      "geometry": {
        "type": "Point",
        "coordinates": [
          -86.5667,
          46.2167
        ]
      },
      "type": "Feature",
      "properties": {
        "hierarchy": [
          "tgn:2360532",
          "tgn:1000001",
          "tgn:7012149",
          "tgn:2000996",
          "tgn:7007520",
          "tgn:7029392"
        ],
        "placetype": [
          "aat:300008706"
        ],
        "id": 2360532,
        "name:xx": "Grassy Creek"
      }
    },
    {
      "geometry": {
        "type": "Point",
        "coordinates": [
          -91.4,
          37.2
        ]
      },
      "type": "Feature",
      "properties": {
        "hierarchy": [
          "tgn:2360533",
          "tgn:1000001",
          "tgn:7012149",
          "tgn:2001247",
          "tgn:7007523",
          "tgn:7029392"
        ],
        "placetype": [
          "aat:300008706"
        ],
        "id": 2360533,
        "name:xx": "Grassy Creek"
      }
    },
    {
      "geometry": {
        "type": "Point",
        "coordinates": [
          -90.1,
          37.2833
        ]
      },
      "type": "Feature",
      "properties": {
        "hierarchy": [
          "tgn:2360534",
          "tgn:1000001",
          "tgn:2001174",
          "tgn:7012149",
          "tgn:7007523",
          "tgn:7029392"
        ],
        "placetype": [
          "aat:300008706"
        ],
        "id": 2360534,
        "name:xx": "Grassy Creek"
      }
    },
    {
      "geometry": {
        "type": "Point",
        "coordinates": [
          -91.2,
          39.4
        ]
      },
      "type": "Feature",
      "properties": {
        "hierarchy": [
          "tgn:2360535",
          "tgn:1000001",
          "tgn:7012149",
          "tgn:1002787",
          "tgn:7007523",
          "tgn:7029392"
        ],
        "placetype": [
          "aat:300008706"
        ],
        "id": 2360535,
        "name:xx": "Grassy Creek"
      }
    },
    {
      "geometry": {
        "type": "Point",
        "coordinates": [
          -93.4833,
          39.9333
        ]
      },
      "type": "Feature",
      "properties": {
        "hierarchy": [
          "tgn:2360536",
          "tgn:1000001",
          "tgn:7012149",
          "tgn:2001215",
          "tgn:7007523",
          "tgn:7029392"
        ],
        "placetype": [
          "aat:300008706"
        ],
        "id": 2360536,
        "name:xx": "Grassy Creek"
      }
    },
    {
      "geometry": {
        "type": "Point",
        "coordinates": [
          -91.75,
          38.6167
        ]
      },
      "type": "Feature",
      "properties": {
        "hierarchy": [
          "tgn:2360537",
          "tgn:1000001",
          "tgn:7012149",
          "tgn:1002755",
          "tgn:7007523",
          "tgn:7029392"
        ],
        "placetype": [
          "aat:300008706"
        ],
        "id": 2360537,
        "name:xx": "Grassy Creek"
      }
    },
    {
      "geometry": {
        "type": "Point",
        "coordinates": [
          -90.6667,
          37.15
        ]
      },
      "type": "Feature",
      "properties": {
        "hierarchy": [
          "tgn:2360538",
          "tgn:1000001",
          "tgn:7012149",
          "tgn:2001255",
          "tgn:7007523",
          "tgn:7029392"
        ],
        "placetype": [
          "aat:300008706"
        ],
        "id": 2360538,
        "name:xx": "Grassy Creek"
      }
    },
    {
      "geometry": {
        "type": "Point",
        "coordinates": [
          -110.2167,
          45.05
        ]
      },
      "type": "Feature",
      "properties": {
        "hierarchy": [
          "tgn:2360539",
          "tgn:1000001",
          "tgn:7012149",
          "tgn:2001293",
          "tgn:7007524",
          "tgn:7029392"
        ],
        "placetype": [
          "aat:300008706"
        ],
        "id": 2360539,
        "name:xx": "Grassy Creek"
      }
    }
  ]
}
