{
  "geometry": {
    "type": "Point",
    "coordinates": [
      -104.8667,
      38.4833
    ]
  },
  "type": "Feature",
  "properties": {
    "hierarchy": [
      "tgn:2187689",
      "tgn:1000001",
      "tgn:7012149",
      "tgn:7007158",
      "tgn:2000242",
      "tgn:7029392"
    ],
    "placetype": [
      "aat:300008798"
    ],
    "id": 2187689,
    "name:xx": "Booth Mountain"
  }
}
