{
  "geometry": {
    "type": "Point",
    "coordinates": [
      20.0833,
      -33.9167
    ]
  },
  "type": "Feature",
  "properties": {
    "hierarchy": [
      "tgn:1092901",
      "tgn:7001242",
      "tgn:7017584",
      "tgn:1000193",
      "tgn:7029392"
    ],
    "placetype": [
      "aat:300008347"
    ],
    "id": 1092901,
    "name:xx": "Bonnievale"
  }
}
