{
  "geometry": {
    "type": "Point",
    "coordinates": [
      -72.65,
      41.7167
    ]
  },
  "type": "Feature",
  "properties": {
    "hierarchy": [
      "tgn:2157080",
      "tgn:1000001",
      "tgn:1002664",
      "tgn:7012149",
      "tgn:7007159",
      "tgn:7029392"
    ],
    "placetype": [
      "aat:300008699"
    ],
    "id": 2157080,
    "name:xx": "Beaver Brook"
  }
}
