{
  "geometry": {
    "type": "Point",
    "coordinates": [
      2.35,
      48.1833
    ]
  },
  "type": "Feature",
  "properties": {
    "hierarchy": [
      "tgn:1128016",
      "tgn:1000003",
      "tgn:7002877",
      "tgn:1000070",
      "tgn:7029392"
    ],
    "placetype": [
      "aat:300008707"
    ],
    "id": 1128016,
    "name:xx": "Oeuf"
  }
}
