{
  "geometry": {
    "type": "Point",
    "coordinates": [
      -89.0333,
      42.8833
    ]
  },
  "type": "Feature",
  "properties": {
    "hierarchy": [
      "tgn:2707423",
      "tgn:1000001",
      "tgn:1002316",
      "tgn:7012149",
      "tgn:7007922",
      "tgn:7029392"
    ],
    "placetype": [
      "aat:300008905"
    ],
    "id": 2707423,
    "name:xx": "Sweet Lake"
  }
}
