{
  "geometry": {
    "type": "Point",
    "coordinates": [
      -99.95,
      29.8833
    ]
  },
  "type": "Feature",
  "properties": {
    "hierarchy": [
      "tgn:2246504",
      "tgn:1000001",
      "tgn:7012149",
      "tgn:7007826",
      "tgn:7029392"
    ],
    "placetype": [
      "aat:300008761"
    ],
    "id": 2246504,
    "name:xx": "Cobb Hollow"
  }
}
