{
  "type": "FeatureCollection",
  "features": [
    {
      "geometry": {
        "type": "Point",
        "coordinates": [
          -109.7833,
          45.05
        ]
      },
      "type": "Feature",
      "properties": {
        "hierarchy": [
          "tgn:2634240",
          "tgn:1000001",
          "tgn:2001264",
          "tgn:7012149",
          "tgn:7007524",
          "tgn:7029392"
        ],
        "placetype": [
          "aat:300008680"
        ],
        "id": 2634240,
        "name:xx": "Russell Lake"
      }
    },
    {
      "geometry": {
        "type": "Point",
        "coordinates": [
          -75.3,
          42.05
        ]
      },
      "type": "Feature",
      "properties": {
        "hierarchy": [
          "tgn:2634241",
          "tgn:1000001",
          "tgn:1002328",
          "tgn:7012149",
          "tgn:7007568",
          "tgn:7029392"
        ],
        "placetype": [
          "aat:300008680"
        ],
        "id": 2634241,
        "name:xx": "Russell Lake"
      }
    },
    {
      "geometry": {
        "type": "Point",
        "coordinates": [
          -74.4833,
          42.7167
        ]
      },
      "type": "Feature",
      "properties": {
        "hierarchy": [
          "tgn:2634242",
          "tgn:1000001",
          "tgn:7012149",
          "tgn:1002873",
          "tgn:7007568",
          "tgn:7029392"
        ],
        "placetype": [
          "aat:300008680"
        ],
        "id": 2634242,
        "name:xx": "Russell Lake"
      }
    },
    {
      "geometry": {
        "type": "Point",
        "coordinates": [
          -99.15,
          47.3667
        ]
      },
      "type": "Feature",
      "properties": {
        "hierarchy": [
          "tgn:2634243",
          "tgn:1000001",
          "tgn:2001572",
          "tgn:7012149",
          "tgn:7007705",
          "tgn:7029392"
        ],
        "placetype": [
          "aat:300008680"
        ],
        "id": 2634243,
        "name:xx": "Russell Lake"
      }
    },
    {
      "geometry": {
        "type": "Point",
        "coordinates": [
          -121.7833,
          44.7
        ]
      },
      "type": "Feature",
      "properties": {
        "hierarchy": [
          "tgn:2634244",
          "tgn:1000001",
          "tgn:7012149",
          "tgn:7007708",
          "tgn:7029392"
        ],
        "placetype": [
          "aat:300008680"
        ],
        "id": 2634244,
        "name:xx": "Russell Lake"
      }
    },
    {
      "geometry": {
        "type": "Point",
        "coordinates": [
          -79.5333,
          39.8167
        ]
      },
      "type": "Feature",
      "properties": {
        "hierarchy": [
          "tgn:2634245",
          "tgn:1000001",
          "tgn:7012149",
          "tgn:7014185",
          "tgn:7007710",
          "tgn:7029392"
        ],
        "placetype": [
          "aat:300006191"
        ],
        "id": 2634245,
        "name:xx": "Russell Lake"
      }
    },
    {
      "geometry": {
        "type": "Point",
        "coordinates": [
          -99.7833,
          33.2667
        ]
      },
      "type": "Feature",
      "properties": {
        "hierarchy": [
          "tgn:2634246",
          "tgn:1000001",
          "tgn:7012149",
          "tgn:2002000",
          "tgn:7007826",
          "tgn:7029392"
        ],
        "placetype": [
          "aat:300008680"
        ],
        "id": 2634246,
        "name:xx": "Russell Lake"
      }
    },
    {
      "geometry": {
        "type": "Point",
        "coordinates": [
          -94.9,
          33.5333
        ]
      },
      "type": "Feature",
      "properties": {
        "hierarchy": [
          "tgn:2634247",
          "tgn:1000001",
          "tgn:7012149",
          "tgn:2002061",
          "tgn:7007826",
          "tgn:7029392"
        ],
        "placetype": [
          "aat:300006191"
        ],
        "id": 2634247,
        "name:xx": "Russell Lake"
      }
    },
    {
      "geometry": {
        "type": "Point",
        "coordinates": [
          -91.4667,
          46.5333
        ]
      },
      "type": "Feature",
      "properties": {
        "hierarchy": [
          "tgn:2634248",
          "tgn:2002308",
          "tgn:1000001",
          "tgn:7012149",
          "tgn:7007922",
          "tgn:7029392"
        ],
        "placetype": [
          "aat:300008680"
        ],
        "id": 2634248,
        "name:xx": "Russell Lake"
      }
    },
    {
      "geometry": {
        "type": "Point",
        "coordinates": [
          -105.9333,
          41.2333
        ]
      },
      "type": "Feature",
      "properties": {
        "hierarchy": [
          "tgn:2634249",
          "tgn:2002365",
          "tgn:1000001",
          "tgn:7012149",
          "tgn:7007923",
          "tgn:7029392"
        ],
        "placetype": [
          "aat:300008680"
        ],
        "id": 2634249,
        "name:xx": "Russell Lake"
      }
    }
  ]
}
