{
  "type": "FeatureCollection",
  "features": [
    {
      "geometry": {
        "type": "Point",
        "coordinates": [
          10.866667,
          53.983333
        ]
      },
      "type": "Feature",
      "properties": {
        "hierarchy": [
          "tgn:7202680",
          "tgn:1000003",
          "tgn:7003688",
          "tgn:7000084",
          "tgn:7029392"
        ],
        "placetype": [
          "aat:300008347"
        ],
        "id": 7202680,
        "name:xx": "Brodten"
      }
    },
    {
      "geometry": {
        "type": "Point",
        "coordinates": [
          10.6,
          49.266667
        ]
      },
      "type": "Feature",
      "properties": {
        "hierarchy": [
          "tgn:7202681",
          "tgn:7003669",
          "tgn:1000003",
          "tgn:7000084",
          "tgn:7029392"
        ],
        "placetype": [
          "aat:300008347"
        ],
        "id": 7202681,
        "name:xx": "Brodswinden"
      }
    },
    {
      "geometry": {
        "type": "Point",
        "coordinates": [
          12.7,
          48.15
        ]
      },
      "type": "Feature",
      "properties": {
        "hierarchy": [
          "tgn:7202682",
          "tgn:7003669",
          "tgn:1000003",
          "tgn:7000084",
          "tgn:7029392"
        ],
        "placetype": [
          "aat:300000206"
        ],
        "id": 7202682,
        "name:xx": "Brodstrumm"
      }
    },
    {
      "geometry": {
        "type": "Point",
        "coordinates": [
          13.95,
          52.9
        ]
      },
      "type": "Feature",
      "properties": {
        "hierarchy": [
          "tgn:7202683",
          "tgn:7000096",
          "tgn:1000003",
          "tgn:7000084",
          "tgn:7029392"
        ],
        "placetype": [
          "aat:300008680"
        ],
        "id": 7202683,
        "name:xx": "Brodowin-See"
      }
    },
    {
      "geometry": {
        "type": "Point",
        "coordinates": [
          13.95,
          52.916667
        ]
      },
      "type": "Feature",
      "properties": {
        "hierarchy": [
          "tgn:7202684",
          "tgn:7000096",
          "tgn:1000003",
          "tgn:7000084",
          "tgn:7029392"
        ],
        "placetype": [
          "aat:300008347"
        ],
        "id": 7202684,
        "name:xx": "Brodowin"
      }
    },
    {
      "geometry": {
        "type": "Point",
        "coordinates": [
          9.9,
          54.65
        ]
      },
      "type": "Feature",
      "properties": {
        "hierarchy": [
          "tgn:7202685",
          "tgn:1000003",
          "tgn:7003688",
          "tgn:7000084",
          "tgn:7029392"
        ],
        "placetype": [
          "aat:300000206"
        ],
        "id": 7202685,
        "name:xx": "Brodlos"
      }
    },
    {
      "geometry": {
        "type": "Point",
        "coordinates": [
          12.116667,
          51.1
        ]
      },
      "type": "Feature",
      "properties": {
        "hierarchy": [
          "tgn:7202686",
          "tgn:1000003",
          "tgn:7003687",
          "tgn:7000084",
          "tgn:7029392"
        ],
        "placetype": [
          "aat:300008347"
        ],
        "id": 7202686,
        "name:xx": "Bröditz"
      }
    },
    {
      "geometry": {
        "type": "Point",
        "coordinates": [
          11.966667,
          47.8
        ]
      },
      "type": "Feature",
      "properties": {
        "hierarchy": [
          "tgn:7202687",
          "tgn:7003669",
          "tgn:1000003",
          "tgn:7000084",
          "tgn:7029392"
        ],
        "placetype": [
          "aat:300008347"
        ],
        "id": 7202687,
        "name:xx": "Brodhub"
      }
    },
    {
      "geometry": {
        "type": "Point",
        "coordinates": [
          12.95,
          47.85
        ]
      },
      "type": "Feature",
      "properties": {
        "hierarchy": [
          "tgn:7202688",
          "tgn:7003669",
          "tgn:1000003",
          "tgn:7000084",
          "tgn:7029392"
        ],
        "placetype": [
          "aat:300008347"
        ],
        "id": 7202688,
        "name:xx": "Brodhausen"
      }
    },
    {
      "geometry": {
        "type": "Point",
        "coordinates": [
          11.85,
          54.1
        ]
      },
      "type": "Feature",
      "properties": {
        "hierarchy": [
          "tgn:7202689",
          "tgn:1000003",
          "tgn:7000094",
          "tgn:7000084",
          "tgn:7029392"
        ],
        "placetype": [
          "aat:300008347"
        ],
        "id": 7202689,
        "name:xx": "Brodhagen"
      }
    }
  ]
}
