{
  "geometry": {
    "type": "Point",
    "coordinates": [
      -82.1167,
      36.4333
    ]
  },
  "type": "Feature",
  "properties": {
    "hierarchy": [
      "tgn:2396464",
      "tgn:1000001",
      "tgn:7012149",
      "tgn:2001846",
      "tgn:7007825",
      "tgn:7029392"
    ],
    "placetype": [
      "aat:300008850"
    ],
    "id": 2396464,
    "name:xx": "Holston High Point"
  }
}
