{
  "geometry": {
    "type": "Point",
    "coordinates": [
      -93.5667,
      40.8333
    ]
  },
  "type": "Feature",
  "properties": {
    "hierarchy": [
      "tgn:2692724",
      "tgn:1000001",
      "tgn:7012149",
      "tgn:7007253",
      "tgn:7029392"
    ],
    "placetype": [
      "aat:300008706"
    ],
    "id": 2692724,
    "name:xx": "Steel Creek"
  }
}
