{
  "geometry": {
    "type": "Point",
    "coordinates": [
      121.40337,
      23.466701
    ]
  },
  "type": "Feature",
  "properties": {
    "hierarchy": [
      "tgn:7499326",
      "tgn:7001010",
      "tgn:1000004",
      "tgn:1000141",
      "tgn:7029392"
    ],
    "placetype": [
      "aat:300007836"
    ],
    "id": 7499326,
    "name:xx": "Nengya Qiao"
  }
}
