{
  "geometry": {
    "type": "Point",
    "coordinates": [
      130.6667,
      42.3333
    ]
  },
  "type": "Feature",
  "properties": {
    "hierarchy": [
      "tgn:7017965",
      "tgn:1000004",
      "tgn:7029392"
    ],
    "placetype": [
      "aat:300008707"
    ],
    "id": 7017965,
    "name:xx": "Tumen"
  }
}
