{
  "geometry": {
    "type": "Point",
    "coordinates": [
      -71.8667,
      44.1167
    ]
  },
  "type": "Feature",
  "properties": {
    "hierarchy": [
      "tgn:2280128",
      "tgn:1000001",
      "tgn:2001424",
      "tgn:7012149",
      "tgn:7007564",
      "tgn:7029392"
    ],
    "placetype": [
      "aat:300008699"
    ],
    "id": 2280128,
    "name:xx": "Dearth Brook"
  }
}
