{
  "geometry": {
    "type": "Point",
    "coordinates": [
      -91.346,
      15.416
    ]
  },
  "type": "Feature",
  "properties": {
    "hierarchy": [
      "tgn:1108936",
      "tgn:1000001",
      "tgn:7005493",
      "tgn:7029392"
    ],
    "placetype": [
      "aat:300008795"
    ],
    "id": 1108936,
    "name:xx": "Cuchumatanes, Sierra de los"
  }
}
