{
  "geometry": {
    "type": "Point",
    "coordinates": [
      34.9167,
      32.4167
    ]
  },
  "type": "Feature",
  "properties": {
    "hierarchy": [
      "tgn:1120903",
      "tgn:1000004",
      "tgn:7029392"
    ],
    "placetype": [
      "aat:300008707"
    ],
    "id": 1120903,
    "name:xx": "H̲adera"
  }
}
