{
  "geometry": {
    "type": "Point",
    "coordinates": [
      -111.95,
      34.5667
    ]
  },
  "type": "Feature",
  "properties": {
    "hierarchy": [
      "tgn:2366125",
      "tgn:1000001",
      "tgn:7006451",
      "tgn:7012149",
      "tgn:2000103",
      "tgn:7029392"
    ],
    "placetype": [
      "aat:300008699"
    ],
    "id": 2366125,
    "name:xx": "Grief Hill Wash"
  }
}
