{
  "geometry": {
    "type": "Point",
    "coordinates": [
      -122.6667,
      40.1667
    ]
  },
  "type": "Feature",
  "properties": {
    "hierarchy": [
      "tgn:2010787",
      "tgn:1000001",
      "tgn:7012149",
      "tgn:7007157",
      "tgn:2000190",
      "tgn:7029392"
    ],
    "placetype": [
      "aat:300008347",
      "aat:300387210"
    ],
    "id": 2010787,
    "name:xx": "Cold Fork"
  }
}
