{
  "geometry": {
    "type": "Point",
    "coordinates": [
      -150.7167,
      60.4667
    ]
  },
  "type": "Feature",
  "properties": {
    "hierarchy": [
      "tgn:2198486",
      "tgn:7006450",
      "tgn:1000001",
      "tgn:7019698",
      "tgn:7012149",
      "tgn:7029392"
    ],
    "placetype": [
      "aat:300008680"
    ],
    "id": 2198486,
    "name:xx": "Browns Lake"
  }
}
