{
  "geometry": {
    "type": "Point",
    "coordinates": [
      -58.7833,
      -34.7167
    ]
  },
  "type": "Feature",
  "properties": {
    "hierarchy": [
      "tgn:1019747",
      "tgn:1001160",
      "tgn:7006477",
      "tgn:1000002",
      "tgn:7029392"
    ],
    "placetype": [
      "aat:300008347"
    ],
    "id": 1019747,
    "name:xx": "Mariano Acosta"
  }
}
