{
  "geometry": {
    "type": "Point",
    "coordinates": [
      -82.75,
      32.9833
    ]
  },
  "type": "Feature",
  "properties": {
    "hierarchy": [
      "tgn:2547541",
      "tgn:1000001",
      "tgn:7012149",
      "tgn:2000441",
      "tgn:7007248",
      "tgn:7029392"
    ],
    "placetype": [
      "aat:300008706"
    ],
    "id": 2547541,
    "name:xx": "North Fork Sun Hill Creek"
  }
}
