{
  "geometry": {
    "type": "Point",
    "coordinates": [
      -106.5667,
      37.6333
    ]
  },
  "type": "Feature",
  "properties": {
    "hierarchy": [
      "tgn:2348122",
      "tgn:1000001",
      "tgn:7012149",
      "tgn:7007158",
      "tgn:2000244",
      "tgn:7029392"
    ],
    "placetype": [
      "aat:300008761"
    ],
    "id": 2348122,
    "name:xx": "Gerrard Gulch"
  }
}
