{
  "geometry": {
    "type": "Point",
    "coordinates": [
      31.516667,
      26.65
    ]
  },
  "type": "Feature",
  "properties": {
    "hierarchy": [
      "tgn:7540049",
      "tgn:7001242",
      "tgn:7016833",
      "tgn:7000124",
      "tgn:7029392"
    ],
    "placetype": [
      "aat:300008347"
    ],
    "name:en": "Nag' Ghazâli",
    "id": 7540049
  }
}
