{
  "geometry": {
    "type": "Point",
    "coordinates": [
      -150.2833,
      63.3667
    ]
  },
  "type": "Feature",
  "properties": {
    "hierarchy": [
      "tgn:2253103",
      "tgn:7006450",
      "tgn:1000001",
      "tgn:7030547",
      "tgn:7012149",
      "tgn:7029392"
    ],
    "placetype": [
      "aat:300008706"
    ],
    "id": 2253103,
    "name:xx": "Contact Creek"
  }
}
