{
  "type": "FeatureCollection",
  "features": [
    {
      "geometry": {
        "type": "Point",
        "coordinates": [
          -120.4667,
          36.3667
        ]
      },
      "type": "Feature",
      "properties": {
        "hierarchy": [
          "tgn:2608800",
          "tgn:1000001",
          "tgn:7012149",
          "tgn:1002392",
          "tgn:7007157",
          "tgn:7029392"
        ],
        "placetype": [
          "aat:300008697"
        ],
        "id": 2608800,
        "name:xx": "Rattlesnake Spring"
      }
    },
    {
      "geometry": {
        "type": "Point",
        "coordinates": [
          -114.2667,
          42.0333
        ]
      },
      "type": "Feature",
      "properties": {
        "hierarchy": [
          "tgn:2608801",
          "tgn:1000001",
          "tgn:2000467",
          "tgn:7012149",
          "tgn:7007250",
          "tgn:7029392"
        ],
        "placetype": [
          "aat:300008697"
        ],
        "id": 2608801,
        "name:xx": "Rattlesnake Spring"
      }
    },
    {
      "geometry": {
        "type": "Point",
        "coordinates": [
          -112.1333,
          42.2667
        ]
      },
      "type": "Feature",
      "properties": {
        "hierarchy": [
          "tgn:2608802",
          "tgn:1000001",
          "tgn:7012149",
          "tgn:2000487",
          "tgn:7007250",
          "tgn:7029392"
        ],
        "placetype": [
          "aat:300008697"
        ],
        "id": 2608802,
        "name:xx": "Rattlesnake Spring"
      }
    },
    {
      "geometry": {
        "type": "Point",
        "coordinates": [
          -114.6,
          43.15
        ]
      },
      "type": "Feature",
      "properties": {
        "hierarchy": [
          "tgn:2608804",
          "tgn:1000001",
          "tgn:7012149",
          "tgn:2000475",
          "tgn:7007250",
          "tgn:7029392"
        ],
        "placetype": [
          "aat:300008697"
        ],
        "id": 2608804,
        "name:xx": "Rattlesnake Spring"
      }
    },
    {
      "geometry": {
        "type": "Point",
        "coordinates": [
          -113.9,
          44.4333
        ]
      },
      "type": "Feature",
      "properties": {
        "hierarchy": [
          "tgn:2608806",
          "tgn:1000001",
          "tgn:2000470",
          "tgn:7012149",
          "tgn:7007250",
          "tgn:7029392"
        ],
        "placetype": [
          "aat:300008697"
        ],
        "id": 2608806,
        "name:xx": "Rattlesnake Spring"
      }
    },
    {
      "geometry": {
        "type": "Point",
        "coordinates": [
          -116.3833,
          45.2667
        ]
      },
      "type": "Feature",
      "properties": {
        "hierarchy": [
          "tgn:2608807",
          "tgn:1000001",
          "tgn:7012149",
          "tgn:2000476",
          "tgn:7007250",
          "tgn:7029392"
        ],
        "placetype": [
          "aat:300008697"
        ],
        "id": 2608807,
        "name:xx": "Rattlesnake Spring"
      }
    },
    {
      "geometry": {
        "type": "Point",
        "coordinates": [
          -92.1167,
          36.5167
        ]
      },
      "type": "Feature",
      "properties": {
        "hierarchy": [
          "tgn:2608808",
          "tgn:1000001",
          "tgn:7012149",
          "tgn:2001206",
          "tgn:7007523",
          "tgn:7029392"
        ],
        "placetype": [
          "aat:300008697"
        ],
        "id": 2608808,
        "name:xx": "Rattlesnake Spring"
      }
    },
    {
      "geometry": {
        "type": "Point",
        "coordinates": [
          -90.5333,
          37.9833
        ]
      },
      "type": "Feature",
      "properties": {
        "hierarchy": [
          "tgn:2608809",
          "tgn:1000001",
          "tgn:7012149",
          "tgn:2001241",
          "tgn:7007523",
          "tgn:7029392"
        ],
        "placetype": [
          "aat:300008697"
        ],
        "id": 2608809,
        "name:xx": "Rattlesnake Spring"
      }
    }
  ]
}
