{
  "geometry": {
    "type": "Point",
    "coordinates": [
      -94.0167,
      42.2833
    ]
  },
  "type": "Feature",
  "properties": {
    "hierarchy": [
      "tgn:2129945",
      "tgn:1000001",
      "tgn:7012149",
      "tgn:2000654",
      "tgn:7007253",
      "tgn:7029392"
    ],
    "placetype": [
      "aat:300008706"
    ],
    "id": 2129945,
    "name:xx": "Allen Creek"
  }
}
