{
  "geometry": {
    "type": "Point",
    "coordinates": [
      -84.1833,
      32.1667
    ]
  },
  "type": "Feature",
  "properties": {
    "hierarchy": [
      "tgn:2778645",
      "tgn:1000001",
      "tgn:7012149",
      "tgn:2000414",
      "tgn:7007248",
      "tgn:7029392"
    ],
    "placetype": [
      "aat:300006191"
    ],
    "id": 2778645,
    "name:xx": "Wohlwender Lake"
  }
}
