{
  "geometry": {
    "type": "Point",
    "coordinates": [
      -118.1667,
      48.5667
    ]
  },
  "type": "Feature",
  "properties": {
    "hierarchy": [
      "tgn:2628717",
      "tgn:1000001",
      "tgn:2002243",
      "tgn:7012149",
      "tgn:7007920",
      "tgn:7029392"
    ],
    "placetype": [
      "aat:300008706"
    ],
    "id": 2628717,
    "name:xx": "Roper Creek"
  }
}
