{
  "geometry": {
    "type": "Point",
    "coordinates": [
      -78.5667,
      34.1167
    ]
  },
  "type": "Feature",
  "properties": {
    "hierarchy": [
      "tgn:2394039",
      "tgn:1000001",
      "tgn:2001485",
      "tgn:7012149",
      "tgn:7007709",
      "tgn:7029392"
    ],
    "placetype": [
      "aat:300008905"
    ],
    "id": 2394039,
    "name:xx": "Hog Swamp"
  }
}
