{
  "geometry": {
    "type": "Point",
    "coordinates": [
      -83.0333,
      35.4833
    ]
  },
  "type": "Feature",
  "properties": {
    "hierarchy": [
      "tgn:2304122",
      "tgn:1000001",
      "tgn:7012149",
      "tgn:2001503",
      "tgn:7007709",
      "tgn:7029392"
    ],
    "placetype": [
      "aat:300008798"
    ],
    "id": 2304122,
    "name:xx": "Eaglenest Mountain"
  }
}
