{
  "geometry": {
    "type": "Point",
    "coordinates": [
      -104.65,
      39.4167
    ]
  },
  "type": "Feature",
  "properties": {
    "hierarchy": [
      "tgn:2385504",
      "tgn:1000001",
      "tgn:7012149",
      "tgn:2000211",
      "tgn:7007158",
      "tgn:7029392"
    ],
    "placetype": [
      "aat:300008761"
    ],
    "id": 2385504,
    "name:xx": "Henderson Gulch"
  }
}
