{
  "type": "FeatureCollection",
  "features": [
    {
      "geometry": {
        "type": "Point",
        "coordinates": [
          -98.633333,
          21.5
        ]
      },
      "type": "Feature",
      "properties": {
        "hierarchy": [
          "tgn:7437270",
          "tgn:1000001",
          "tgn:7005594",
          "tgn:7005560",
          "tgn:7029392"
        ],
        "placetype": [
          "aat:300008347"
        ],
        "id": 7437270,
        "name:xx": "Tepemiche"
      }
    },
    {
      "geometry": {
        "type": "Point",
        "coordinates": [
          -105.083333,
          19.95
        ]
      },
      "type": "Feature",
      "properties": {
        "hierarchy": [
          "tgn:7437271",
          "tgn:7005586",
          "tgn:1000001",
          "tgn:7005560",
          "tgn:7029392"
        ],
        "placetype": [
          "aat:300008795"
        ],
        "id": 7437271,
        "name:xx": "Tepemezquite, Cerro el"
      }
    },
    {
      "geometry": {
        "type": "Point",
        "coordinates": [
          -106.35,
          23.7
        ]
      },
      "type": "Feature",
      "properties": {
        "hierarchy": [
          "tgn:7437272",
          "tgn:1000001",
          "tgn:7005595",
          "tgn:7005560",
          "tgn:7029392"
        ],
        "placetype": [
          "aat:300008347"
        ],
        "id": 7437272,
        "name:xx": "Tepemezquite"
      }
    },
    {
      "geometry": {
        "type": "Point",
        "coordinates": [
          -102.95,
          19.05
        ]
      },
      "type": "Feature",
      "properties": {
        "hierarchy": [
          "tgn:7437273",
          "tgn:1000001",
          "tgn:7005590",
          "tgn:7005560",
          "tgn:7029392"
        ],
        "placetype": [
          "aat:300008347"
        ],
        "id": 7437273,
        "name:xx": "Tepemesquite"
      }
    },
    {
      "geometry": {
        "type": "Point",
        "coordinates": [
          -98.4,
          18.816667
        ]
      },
      "type": "Feature",
      "properties": {
        "hierarchy": [
          "tgn:7437274",
          "tgn:1000001",
          "tgn:7005592",
          "tgn:7005560",
          "tgn:7029392"
        ],
        "placetype": [
          "aat:300008795"
        ],
        "id": 7437274,
        "name:xx": "Tepemecate, Loma"
      }
    },
    {
      "geometry": {
        "type": "Point",
        "coordinates": [
          -97.266667,
          17.9
        ]
      },
      "type": "Feature",
      "properties": {
        "hierarchy": [
          "tgn:7437276",
          "tgn:1000001",
          "tgn:7005591",
          "tgn:7005560",
          "tgn:7029392"
        ],
        "placetype": [
          "aat:300008347"
        ],
        "id": 7437276,
        "name:xx": "Río Tepelmeme"
      }
    },
    {
      "geometry": {
        "type": "Point",
        "coordinates": [
          -95.333333,
          17.516667
        ]
      },
      "type": "Feature",
      "properties": {
        "hierarchy": [
          "tgn:7437277",
          "tgn:1000001",
          "tgn:7005591",
          "tgn:7005560",
          "tgn:7029392"
        ],
        "placetype": [
          "aat:300008347"
        ],
        "id": 7437277,
        "name:xx": "Tepejilotal"
      }
    },
    {
      "geometry": {
        "type": "Point",
        "coordinates": [
          -97.933333,
          20.05
        ]
      },
      "type": "Feature",
      "properties": {
        "hierarchy": [
          "tgn:7437279",
          "tgn:1000001",
          "tgn:7005592",
          "tgn:7005560",
          "tgn:7029392"
        ],
        "placetype": [
          "aat:300008347"
        ],
        "id": 7437279,
        "name:xx": "Tepeixco"
      }
    }
  ]
}
