{
  "geometry": {
    "type": "Point",
    "coordinates": [
      -100.7333,
      44.2667
    ]
  },
  "type": "Feature",
  "properties": {
    "hierarchy": [
      "tgn:2532848",
      "tgn:1000001",
      "tgn:7012149",
      "tgn:2001828",
      "tgn:7007713",
      "tgn:7029392"
    ],
    "placetype": [
      "aat:300008798"
    ],
    "id": 2532848,
    "name:xx": "Murray Butte"
  }
}
