{
  "geometry": {
    "type": "Point",
    "coordinates": [
      14.75,
      56.1833
    ]
  },
  "type": "Feature",
  "properties": {
    "hierarchy": [
      "tgn:1063359",
      "tgn:7003767",
      "tgn:1000003",
      "tgn:1000097",
      "tgn:7029392"
    ],
    "placetype": [
      "aat:300008347"
    ],
    "id": 1063359,
    "name:xx": "Mörrum"
  }
}
