{
  "geometry": {
    "type": "Point",
    "coordinates": [
      -80.1333,
      26.2167
    ]
  },
  "type": "Feature",
  "properties": {
    "hierarchy": [
      "tgn:2591510",
      "tgn:1000001",
      "tgn:1002207",
      "tgn:7012149",
      "tgn:7007240",
      "tgn:7029392"
    ],
    "placetype": [
      "aat:300006075"
    ],
    "id": 2591510,
    "name:xx": "Pompano Canal"
  }
}
