{
  "type": "FeatureCollection",
  "features": [
    {
      "geometry": {
        "type": "Point",
        "coordinates": [
          -9.2833,
          52.5667
        ]
      },
      "type": "Feature",
      "properties": {
        "hierarchy": [
          "tgn:1042820",
          "tgn:7003499",
          "tgn:7001201",
          "tgn:1000003",
          "tgn:1000078",
          "tgn:7029392"
        ],
        "placetype": [
          "aat:300008347"
        ],
        "id": 1042820,
        "name:xx": "Glin"
      }
    },
    {
      "geometry": {
        "type": "Point",
        "coordinates": [
          -7.9667,
          52.5
        ]
      },
      "type": "Feature",
      "properties": {
        "hierarchy": [
          "tgn:1042821",
          "tgn:7593749",
          "tgn:7001201",
          "tgn:1000003",
          "tgn:1000078",
          "tgn:7029392"
        ],
        "placetype": [
          "aat:300008347"
        ],
        "id": 1042821,
        "name:xx": "Golden"
      }
    },
    {
      "geometry": {
        "type": "Point",
        "coordinates": [
          -9.7167,
          51.4667
        ]
      },
      "type": "Feature",
      "properties": {
        "hierarchy": [
          "tgn:1042822",
          "tgn:7003497",
          "tgn:7001201",
          "tgn:1000003",
          "tgn:1000078",
          "tgn:7029392"
        ],
        "placetype": [
          "aat:300008347"
        ],
        "id": 1042822,
        "name:xx": "Goleen"
      }
    },
    {
      "geometry": {
        "type": "Point",
        "coordinates": [
          -6.3,
          52.6667
        ]
      },
      "type": "Feature",
      "properties": {
        "hierarchy": [
          "tgn:1042823",
          "tgn:7001199",
          "tgn:7003494",
          "tgn:1000003",
          "tgn:1000078",
          "tgn:7029392"
        ],
        "placetype": [
          "aat:300008347"
        ],
        "id": 1042823,
        "name:xx": "Gorey"
      }
    },
    {
      "geometry": {
        "type": "Point",
        "coordinates": [
          -8.8333,
          53.0667
        ]
      },
      "type": "Feature",
      "properties": {
        "hierarchy": [
          "tgn:1042824",
          "tgn:7003479",
          "tgn:7001198",
          "tgn:1000003",
          "tgn:1000078",
          "tgn:7029392"
        ],
        "placetype": [
          "aat:300008347"
        ],
        "id": 1042824,
        "name:xx": "Gort"
      }
    },
    {
      "geometry": {
        "type": "Point",
        "coordinates": [
          -8.15,
          55.1333
        ]
      },
      "type": "Feature",
      "properties": {
        "hierarchy": [
          "tgn:1042825",
          "tgn:7003502",
          "tgn:7003478",
          "tgn:1000003",
          "tgn:1000078",
          "tgn:7029392"
        ],
        "placetype": [
          "aat:300008347"
        ],
        "id": 1042825,
        "name:xx": "Gortahork"
      }
    },
    {
      "geometry": {
        "type": "Point",
        "coordinates": [
          -7.5,
          53.7833
        ]
      },
      "type": "Feature",
      "properties": {
        "hierarchy": [
          "tgn:1042827",
          "tgn:7003490",
          "tgn:7001199",
          "tgn:1000003",
          "tgn:1000078",
          "tgn:7029392"
        ],
        "placetype": [
          "aat:300008347"
        ],
        "id": 1042827,
        "name:xx": "Granard"
      }
    },
    {
      "geometry": {
        "type": "Point",
        "coordinates": [
          -6.9833,
          55.2
        ]
      },
      "type": "Feature",
      "properties": {
        "hierarchy": [
          "tgn:1042828",
          "tgn:7003502",
          "tgn:7003478",
          "tgn:1000003",
          "tgn:1000078",
          "tgn:7029392"
        ],
        "placetype": [
          "aat:300008347"
        ],
        "id": 1042828,
        "name:xx": "Greencastle"
      }
    },
    {
      "geometry": {
        "type": "Point",
        "coordinates": [
          -8.6167,
          52
        ]
      },
      "type": "Feature",
      "properties": {
        "hierarchy": [
          "tgn:1042829",
          "tgn:7003497",
          "tgn:7001201",
          "tgn:1000003",
          "tgn:1000078",
          "tgn:7029392"
        ],
        "placetype": [
          "aat:300008347"
        ],
        "id": 1042829,
        "name:xx": "Grenagh"
      }
    }
  ]
}
