{
  "type": "FeatureCollection",
  "features": [
    {
      "geometry": {
        "type": "Point",
        "coordinates": [
          -120.7667,
          39.5667
        ]
      },
      "type": "Feature",
      "properties": {
        "hierarchy": [
          "tgn:2519100",
          "tgn:1000001",
          "tgn:7012149",
          "tgn:7007157",
          "tgn:1002894",
          "tgn:7029392"
        ],
        "placetype": [
          "aat:300008761"
        ],
        "id": 2519100,
        "name:xx": "Mobile Ravine"
      }
    },
    {
      "geometry": {
        "type": "Point",
        "coordinates": [
          -91.2667,
          30.6
        ]
      },
      "type": "Feature",
      "properties": {
        "hierarchy": [
          "tgn:2519101",
          "tgn:1000001",
          "tgn:2000870",
          "tgn:7012149",
          "tgn:7007256",
          "tgn:7029392"
        ],
        "placetype": [
          "aat:300266640"
        ],
        "id": 2519101,
        "name:xx": "Mobile Ridge"
      }
    },
    {
      "geometry": {
        "type": "Point",
        "coordinates": [
          -85.6,
          30.55
        ]
      },
      "type": "Feature",
      "properties": {
        "hierarchy": [
          "tgn:2519102",
          "tgn:1000001",
          "tgn:7012149",
          "tgn:2000291",
          "tgn:7007240",
          "tgn:7029392"
        ],
        "placetype": [
          "aat:300008905"
        ],
        "id": 2519102,
        "name:xx": "Mobile Swamp"
      }
    },
    {
      "geometry": {
        "type": "Point",
        "coordinates": [
          -88.0333,
          30.7
        ]
      },
      "type": "Feature",
      "properties": {
        "hierarchy": [
          "tgn:2519103",
          "tgn:7002659",
          "tgn:1000001",
          "tgn:7012149",
          "tgn:2000048",
          "tgn:7029392"
        ],
        "placetype": [
          "aat:300006075"
        ],
        "id": 2519103,
        "name:xx": "Mobile Turning Basin"
      }
    },
    {
      "geometry": {
        "type": "Point",
        "coordinates": [
          -112.2667,
          33
        ]
      },
      "type": "Feature",
      "properties": {
        "hierarchy": [
          "tgn:2519104",
          "tgn:1000001",
          "tgn:7006451",
          "tgn:7012149",
          "tgn:2000097",
          "tgn:7029392"
        ],
        "placetype": [
          "aat:300008761"
        ],
        "id": 2519104,
        "name:xx": "Mobile Valley"
      }
    },
    {
      "geometry": {
        "type": "Point",
        "coordinates": [
          -81.35,
          28.6667
        ]
      },
      "type": "Feature",
      "properties": {
        "hierarchy": [
          "tgn:2519105",
          "tgn:1000001",
          "tgn:7012149",
          "tgn:1002881",
          "tgn:7007240",
          "tgn:7029392"
        ],
        "placetype": [
          "aat:300008680"
        ],
        "id": 2519105,
        "name:xx": "Mobile, Lake"
      }
    },
    {
      "geometry": {
        "type": "Point",
        "coordinates": [
          -91.4333,
          35.9
        ]
      },
      "type": "Feature",
      "properties": {
        "hierarchy": [
          "tgn:2519106",
          "tgn:1000001",
          "tgn:7016172",
          "tgn:7012149",
          "tgn:2000172",
          "tgn:7029392"
        ],
        "placetype": [
          "aat:300008347"
        ],
        "id": 2519106,
        "name:xx": "Mobley"
      }
    },
    {
      "geometry": {
        "type": "Point",
        "coordinates": [
          -88,
          36.4333
        ]
      },
      "type": "Feature",
      "properties": {
        "hierarchy": [
          "tgn:2519107",
          "tgn:1000001",
          "tgn:7012149",
          "tgn:2001917",
          "tgn:7007825",
          "tgn:7029392"
        ],
        "placetype": [
          "aat:300008347"
        ],
        "id": 2519107,
        "name:xx": "Mobley"
      }
    },
    {
      "geometry": {
        "type": "Point",
        "coordinates": [
          -81.6167,
          32.6
        ]
      },
      "type": "Feature",
      "properties": {
        "hierarchy": [
          "tgn:2519108",
          "tgn:1000001",
          "tgn:7012149",
          "tgn:2000415",
          "tgn:7007248",
          "tgn:7029392"
        ],
        "placetype": [
          "aat:300008905"
        ],
        "id": 2519108,
        "name:xx": "Mobley Bay"
      }
    },
    {
      "geometry": {
        "type": "Point",
        "coordinates": [
          -82.9833,
          31.75
        ]
      },
      "type": "Feature",
      "properties": {
        "hierarchy": [
          "tgn:2519109",
          "tgn:1000001",
          "tgn:7012149",
          "tgn:7007248",
          "tgn:7029392"
        ],
        "placetype": [
          "aat:300008706"
        ],
        "id": 2519109,
        "name:xx": "Mobley Bluff Creek"
      }
    }
  ]
}
