{
  "geometry": {
    "type": "Point",
    "coordinates": [
      -82.4167,
      34.7333
    ]
  },
  "type": "Feature",
  "properties": {
    "hierarchy": [
      "tgn:2367755",
      "tgn:1000001",
      "tgn:7012149",
      "tgn:7007712",
      "tgn:7029392"
    ],
    "placetype": [
      "aat:300008706"
    ],
    "id": 2367755,
    "name:xx": "Grove Creek"
  }
}
