{
  "geometry": {
    "type": "Point",
    "coordinates": [
      28.522,
      -33.267
    ]
  },
  "type": "Feature",
  "properties": {
    "hierarchy": [
      "tgn:1123596",
      "tgn:7001242",
      "tgn:7017584",
      "tgn:1000193",
      "tgn:7029392"
    ],
    "placetype": [
      "aat:300008707"
    ],
    "id": 1123596,
    "name:xx": "Dwyka"
  }
}
