{
  "type": "FeatureCollection",
  "features": [
    {
      "geometry": {
        "type": "Point",
        "coordinates": [
          -80.8167,
          40.2
        ]
      },
      "type": "Feature",
      "properties": {
        "hierarchy": [
          "tgn:2079952",
          "tgn:1000001",
          "tgn:7012149",
          "tgn:1002519",
          "tgn:7007706",
          "tgn:7029392"
        ],
        "placetype": [
          "aat:300387016"
        ],
        "id": 2079952,
        "name:xx": "Herrick"
      }
    },
    {
      "geometry": {
        "type": "Point",
        "coordinates": [
          -83.2333,
          41.4
        ]
      },
      "type": "Feature",
      "properties": {
        "hierarchy": [
          "tgn:2079953",
          "tgn:1000001",
          "tgn:7012149",
          "tgn:1002865",
          "tgn:7007706",
          "tgn:7029392"
        ],
        "placetype": [
          "aat:300008347"
        ],
        "id": 2079953,
        "name:xx": "Hessville"
      }
    },
    {
      "geometry": {
        "type": "Point",
        "coordinates": [
          -82.3,
          40.1333
        ]
      },
      "type": "Feature",
      "properties": {
        "hierarchy": [
          "tgn:2079954",
          "tgn:1000001",
          "tgn:7012149",
          "tgn:1002596",
          "tgn:7007706",
          "tgn:7029392"
        ],
        "placetype": [
          "aat:300008347",
          "aat:300387210"
        ],
        "id": 2079954,
        "name:xx": "Hickman"
      }
    },
    {
      "geometry": {
        "type": "Point",
        "coordinates": [
          -84.75,
          41.2833
        ]
      },
      "type": "Feature",
      "properties": {
        "hierarchy": [
          "tgn:2079955",
          "tgn:1000001",
          "tgn:1002326",
          "tgn:7012149",
          "tgn:7007706",
          "tgn:7029392"
        ],
        "placetype": [
          "aat:300008347"
        ],
        "id": 2079955,
        "name:xx": "Hicksville"
      }
    },
    {
      "geometry": {
        "type": "Point",
        "coordinates": [
          -83.7167,
          38.7167
        ]
      },
      "type": "Feature",
      "properties": {
        "hierarchy": [
          "tgn:2079957",
          "tgn:1000001",
          "tgn:1002210",
          "tgn:7012149",
          "tgn:7007706",
          "tgn:7029392"
        ],
        "placetype": [
          "aat:300008347",
          "aat:300387210"
        ],
        "id": 2079957,
        "name:xx": "Hiett"
      }
    },
    {
      "geometry": {
        "type": "Point",
        "coordinates": [
          -83.9667,
          38.7833
        ]
      },
      "type": "Feature",
      "properties": {
        "hierarchy": [
          "tgn:2079958",
          "tgn:1000001",
          "tgn:1002210",
          "tgn:7012149",
          "tgn:7007706",
          "tgn:7029392"
        ],
        "placetype": [
          "aat:300008347"
        ],
        "id": 2079958,
        "name:xx": "Higginsport"
      }
    }
  ]
}
