{
  "geometry": {
    "type": "Point",
    "coordinates": [
      -89.8833,
      38.3667
    ]
  },
  "type": "Feature",
  "properties": {
    "hierarchy": [
      "tgn:2160750",
      "tgn:1000001",
      "tgn:7012149",
      "tgn:7016022",
      "tgn:7007251",
      "tgn:7029392"
    ],
    "placetype": [
      "aat:300266640"
    ],
    "id": 2160750,
    "name:xx": "Belcher Ridge"
  }
}
