{
  "geometry": {
    "type": "Point",
    "coordinates": [
      -86.95,
      32.3667
    ]
  },
  "type": "Feature",
  "properties": {
    "hierarchy": [
      "tgn:2711996",
      "tgn:7002659",
      "tgn:1000001",
      "tgn:7012149",
      "tgn:2000023",
      "tgn:7029392"
    ],
    "placetype": [
      "aat:300132348"
    ],
    "id": 2711996,
    "name:xx": "Tarver Bar"
  }
}
