{
  "geometry": {
    "type": "Point",
    "coordinates": [
      -82.5833,
      28.1667
    ]
  },
  "type": "Feature",
  "properties": {
    "hierarchy": [
      "tgn:2368629",
      "tgn:1000001",
      "tgn:7012149",
      "tgn:1002773",
      "tgn:7007240",
      "tgn:7029392"
    ],
    "placetype": [
      "aat:300008347"
    ],
    "id": 2368629,
    "name:xx": "Gulf Pine"
  }
}
