{
  "geometry": {
    "type": "Point",
    "coordinates": [
      1.5833,
      50.8667
    ]
  },
  "type": "Feature",
  "properties": {
    "hierarchy": [
      "tgn:1010747",
      "tgn:1000003",
      "tgn:7001097",
      "tgn:1000070",
      "tgn:7029392"
    ],
    "placetype": [
      "aat:300008850"
    ],
    "id": 1010747,
    "name:xx": "Gris-Nez, Cap"
  }
}
