{
  "geometry": {
    "type": "Point",
    "coordinates": [
      -74.85,
      44.0667
    ]
  },
  "type": "Feature",
  "properties": {
    "hierarchy": [
      "tgn:2669281",
      "tgn:1000001",
      "tgn:7012149",
      "tgn:7016021",
      "tgn:7007568",
      "tgn:7029392"
    ],
    "placetype": [
      "aat:300008680"
    ],
    "id": 2669281,
    "name:xx": "Slender Pond"
  }
}
