{
  "type": "FeatureCollection",
  "features": [
    {
      "geometry": {
        "type": "Point",
        "coordinates": [
          -85.65,
          35.4833
        ]
      },
      "type": "Feature",
      "properties": {
        "hierarchy": [
          "tgn:2357680",
          "tgn:1000001",
          "tgn:7012149",
          "tgn:2001867",
          "tgn:7007825",
          "tgn:7029392"
        ],
        "placetype": [
          "aat:300008746"
        ],
        "id": 2357680,
        "name:xx": "Grace Chapel Cave"
      }
    },
    {
      "geometry": {
        "type": "Point",
        "coordinates": [
          -103.4833,
          43.7833
        ]
      },
      "type": "Feature",
      "properties": {
        "hierarchy": [
          "tgn:2357681",
          "tgn:1000001",
          "tgn:2001786",
          "tgn:7012149",
          "tgn:7007713",
          "tgn:7029392"
        ],
        "placetype": [
          "aat:300008706"
        ],
        "id": 2357681,
        "name:xx": "Grace Coolidge Creek"
      }
    },
    {
      "geometry": {
        "type": "Point",
        "coordinates": [
          -71.5833,
          41.1833
        ]
      },
      "type": "Feature",
      "properties": {
        "hierarchy": [
          "tgn:2357683",
          "tgn:1002996",
          "tgn:1000001",
          "tgn:7012149",
          "tgn:7007711",
          "tgn:7029392"
        ],
        "placetype": [
          "aat:300132316"
        ],
        "id": 2357683,
        "name:xx": "Grace Cove"
      }
    },
    {
      "geometry": {
        "type": "Point",
        "coordinates": [
          -141.35,
          64.1833
        ]
      },
      "type": "Feature",
      "properties": {
        "hierarchy": [
          "tgn:2357684",
          "tgn:7006450",
          "tgn:1000001",
          "tgn:7012149",
          "tgn:2000085",
          "tgn:7029392"
        ],
        "placetype": [
          "aat:300008706"
        ],
        "id": 2357684,
        "name:xx": "Grace Creek"
      }
    },
    {
      "geometry": {
        "type": "Point",
        "coordinates": [
          -131.1333,
          55.65
        ]
      },
      "type": "Feature",
      "properties": {
        "hierarchy": [
          "tgn:2357685",
          "tgn:7006450",
          "tgn:1000001",
          "tgn:2124076",
          "tgn:7012149",
          "tgn:7029392"
        ],
        "placetype": [
          "aat:300008706"
        ],
        "id": 2357685,
        "name:xx": "Grace Creek"
      }
    },
    {
      "geometry": {
        "type": "Point",
        "coordinates": [
          -93.1,
          34.9833
        ]
      },
      "type": "Feature",
      "properties": {
        "hierarchy": [
          "tgn:2357686",
          "tgn:1000001",
          "tgn:7016172",
          "tgn:7012149",
          "tgn:2000157",
          "tgn:7029392"
        ],
        "placetype": [
          "aat:300008706"
        ],
        "id": 2357686,
        "name:xx": "Grace Creek"
      }
    },
    {
      "geometry": {
        "type": "Point",
        "coordinates": [
          -123.4667,
          40.3833
        ]
      },
      "type": "Feature",
      "properties": {
        "hierarchy": [
          "tgn:2357687",
          "tgn:1000001",
          "tgn:7012149",
          "tgn:7007157",
          "tgn:2000191",
          "tgn:7029392"
        ],
        "placetype": [
          "aat:300008706"
        ],
        "id": 2357687,
        "name:xx": "Grace Creek"
      }
    },
    {
      "geometry": {
        "type": "Point",
        "coordinates": [
          -106.0333,
          40.9
        ]
      },
      "type": "Feature",
      "properties": {
        "hierarchy": [
          "tgn:2357688",
          "tgn:1000001",
          "tgn:7012149",
          "tgn:2000226",
          "tgn:7007158",
          "tgn:7029392"
        ],
        "placetype": [
          "aat:300008706"
        ],
        "id": 2357688,
        "name:xx": "Grace Creek"
      }
    },
    {
      "geometry": {
        "type": "Point",
        "coordinates": [
          -88.0667,
          36.8
        ]
      },
      "type": "Feature",
      "properties": {
        "hierarchy": [
          "tgn:2357689",
          "tgn:1000001",
          "tgn:7012149",
          "tgn:2000846",
          "tgn:7007255",
          "tgn:7029392"
        ],
        "placetype": [
          "aat:300008706"
        ],
        "id": 2357689,
        "name:xx": "Grace Creek"
      }
    }
  ]
}
