{
  "geometry": {
    "type": "Point",
    "coordinates": [
      -74.9333,
      40.95
    ]
  },
  "type": "Feature",
  "properties": {
    "hierarchy": [
      "tgn:2752624",
      "tgn:1000001",
      "tgn:1002985",
      "tgn:7012149",
      "tgn:7007565",
      "tgn:7029392"
    ],
    "placetype": [
      "aat:300006191"
    ],
    "id": 2752624,
    "name:xx": "Wasigan, Lake"
  }
}
