{
  "geometry": {
    "type": "Point",
    "coordinates": [
      30.666389,
      31.4325
    ]
  },
  "type": "Feature",
  "properties": {
    "hierarchy": [
      "tgn:7527914",
      "tgn:7001242",
      "tgn:7016833",
      "tgn:1001335",
      "tgn:7029392"
    ],
    "placetype": [
      "aat:300008791"
    ],
    "name:en": "Umm 'Âmir, Gezîret",
    "id": 7527914
  }
}
