{
  "geometry": {
    "type": "Point",
    "coordinates": [
      -75.75,
      36.1667
    ]
  },
  "type": "Feature",
  "properties": {
    "hierarchy": [
      "tgn:2152560",
      "tgn:1000001",
      "tgn:7012149",
      "tgn:2001488",
      "tgn:7007709",
      "tgn:7029392"
    ],
    "placetype": [
      "aat:300008347"
    ],
    "id": 2152560,
    "name:xx": "Bayberry Bluffs"
  }
}
