{
  "geometry": {
    "type": "Point",
    "coordinates": [
      -82.2667,
      38.9667
    ]
  },
  "type": "Feature",
  "properties": {
    "hierarchy": [
      "tgn:2080853",
      "tgn:1000001",
      "tgn:7012149",
      "tgn:2001612",
      "tgn:7007706",
      "tgn:7029392"
    ],
    "placetype": [
      "aat:300008347",
      "aat:300387210"
    ],
    "id": 2080853,
    "name:xx": "Morgan Center"
  }
}
