{
  "geometry": {
    "type": "Point",
    "coordinates": [
      -107.95,
      39.0333
    ]
  },
  "type": "Feature",
  "properties": {
    "hierarchy": [
      "tgn:2691386",
      "tgn:1000001",
      "tgn:7012149",
      "tgn:2000206",
      "tgn:7007158",
      "tgn:7029392"
    ],
    "placetype": [
      "aat:300006191"
    ],
    "id": 2691386,
    "name:xx": "Star Lake"
  }
}
