{
  "geometry": {
    "type": "Point",
    "coordinates": [
      -92.65,
      29.8667
    ]
  },
  "type": "Feature",
  "properties": {
    "hierarchy": [
      "tgn:2630985",
      "tgn:1000001",
      "tgn:7020676",
      "tgn:7012149",
      "tgn:7007256",
      "tgn:7029392"
    ],
    "placetype": [
      "aat:300006075"
    ],
    "id": 2630985,
    "name:xx": "Round Lake Canal"
  }
}
