{
  "geometry": {
    "type": "Point",
    "coordinates": [
      41.2167,
      53.0833
    ]
  },
  "type": "Feature",
  "properties": {
    "hierarchy": [
      "tgn:1059810",
      "tgn:1000004",
      "tgn:1003417",
      "tgn:7018214",
      "tgn:7002435",
      "tgn:7029392"
    ],
    "placetype": [
      "aat:300008347"
    ],
    "id": 1059810,
    "name:xx": "Stëzhki"
  }
}
