{
  "geometry": {
    "type": "Point",
    "coordinates": [
      -84.6833,
      36.85
    ]
  },
  "type": "Feature",
  "properties": {
    "hierarchy": [
      "tgn:2264473",
      "tgn:1000001",
      "tgn:7012149",
      "tgn:2000850",
      "tgn:7007255",
      "tgn:7029392"
    ],
    "placetype": [
      "aat:300008699"
    ],
    "id": 2264473,
    "name:xx": "Crabtree Branch"
  }
}
