{
  "geometry": {
    "type": "Point",
    "coordinates": [
      -1.5833,
      43.4333
    ]
  },
  "type": "Feature",
  "properties": {
    "hierarchy": [
      "tgn:4001501",
      "tgn:7002878",
      "tgn:1000003",
      "tgn:1000070",
      "tgn:7029392"
    ],
    "placetype": [
      "aat:300008347"
    ],
    "id": 4001501,
    "name:xx": "Bidart"
  }
}
