{
  "geometry": {
    "type": "Point",
    "coordinates": [
      -103.9333,
      48.1667
    ]
  },
  "type": "Feature",
  "properties": {
    "hierarchy": [
      "tgn:2312375",
      "tgn:1000001",
      "tgn:7012149",
      "tgn:2001609",
      "tgn:7007705",
      "tgn:7029392"
    ],
    "placetype": [
      "aat:300008706"
    ],
    "id": 2312375,
    "name:xx": "Eightmile Creek"
  }
}
