{
  "geometry": {
    "type": "Point",
    "coordinates": [
      -81.65,
      30.0167
    ]
  },
  "type": "Feature",
  "properties": {
    "hierarchy": [
      "tgn:2373014",
      "tgn:1000001",
      "tgn:7012149",
      "tgn:2000283",
      "tgn:7007240",
      "tgn:7029392"
    ],
    "placetype": [
      "aat:300132316"
    ],
    "id": 2373014,
    "name:xx": "Hallowes Cove"
  }
}
