{
  "geometry": {
    "type": "Point",
    "coordinates": [
      -107.55,
      44.6167
    ]
  },
  "type": "Feature",
  "properties": {
    "hierarchy": [
      "tgn:2297585",
      "tgn:1000001",
      "tgn:2002366",
      "tgn:7012149",
      "tgn:7007923",
      "tgn:7029392"
    ],
    "placetype": [
      "aat:300008706"
    ],
    "id": 2297585,
    "name:xx": "Dry Fork Granite Creek"
  }
}
