{
  "geometry": {
    "type": "Point",
    "coordinates": [
      18.0833,
      44.5333
    ]
  },
  "type": "Feature",
  "properties": {
    "hierarchy": [
      "tgn:1065115",
      "tgn:7018774",
      "tgn:1000003",
      "tgn:7006664",
      "tgn:7029392"
    ],
    "placetype": [
      "aat:300008347"
    ],
    "id": 1065115,
    "name:xx": "Maglaj"
  }
}
