{
  "geometry": {
    "type": "Point",
    "coordinates": [
      -98.625,
      19.025
    ]
  },
  "type": "Feature",
  "properties": {
    "hierarchy": [
      "tgn:1107733",
      "tgn:1000001",
      "tgn:7005592",
      "tgn:7005560",
      "tgn:7029392"
    ],
    "placetype": [
      "aat:300008795",
      "aat:300132325"
    ],
    "id": 1107733,
    "name:xx": "Popocatépetl, Volcán"
  }
}
