{
  "type": "FeatureCollection",
  "features": [
    {
      "geometry": {
        "type": "Point",
        "coordinates": [
          -108.8,
          27.883333
        ]
      },
      "type": "Feature",
      "properties": {
        "hierarchy": [
          "tgn:7348940",
          "tgn:7005581",
          "tgn:1000001",
          "tgn:7005560",
          "tgn:7029392"
        ],
        "placetype": [
          "aat:300008347"
        ],
        "id": 7348940,
        "name:xx": "Agua Caliente"
      }
    },
    {
      "geometry": {
        "type": "Point",
        "coordinates": [
          -108.433333,
          27.883333
        ]
      },
      "type": "Feature",
      "properties": {
        "hierarchy": [
          "tgn:7348941",
          "tgn:7005581",
          "tgn:1000001",
          "tgn:7005560",
          "tgn:7029392"
        ],
        "placetype": [
          "aat:300008347"
        ],
        "id": 7348941,
        "name:xx": "Agua Caliente"
      }
    },
    {
      "geometry": {
        "type": "Point",
        "coordinates": [
          -106.2,
          27.866667
        ]
      },
      "type": "Feature",
      "properties": {
        "hierarchy": [
          "tgn:7348942",
          "tgn:7005581",
          "tgn:1000001",
          "tgn:7005560",
          "tgn:7029392"
        ],
        "placetype": [
          "aat:300008347"
        ],
        "id": 7348942,
        "name:xx": "Agua Caliente"
      }
    },
    {
      "geometry": {
        "type": "Point",
        "coordinates": [
          -108.466667,
          27.583333
        ]
      },
      "type": "Feature",
      "properties": {
        "hierarchy": [
          "tgn:7348943",
          "tgn:7005581",
          "tgn:1000001",
          "tgn:7005560",
          "tgn:7029392"
        ],
        "placetype": [
          "aat:300008347"
        ],
        "id": 7348943,
        "name:xx": "Agua Caliente"
      }
    },
    {
      "geometry": {
        "type": "Point",
        "coordinates": [
          -106.966667,
          27.583333
        ]
      },
      "type": "Feature",
      "properties": {
        "hierarchy": [
          "tgn:7348944",
          "tgn:7005581",
          "tgn:1000001",
          "tgn:7005560",
          "tgn:7029392"
        ],
        "placetype": [
          "aat:300008347"
        ],
        "id": 7348944,
        "name:xx": "Agua Caliente"
      }
    },
    {
      "geometry": {
        "type": "Point",
        "coordinates": [
          -106.716667,
          27.5
        ]
      },
      "type": "Feature",
      "properties": {
        "hierarchy": [
          "tgn:7348945",
          "tgn:7005581",
          "tgn:1000001",
          "tgn:7005560",
          "tgn:7029392"
        ],
        "placetype": [
          "aat:300008347"
        ],
        "id": 7348945,
        "name:xx": "Agua Caliente"
      }
    },
    {
      "geometry": {
        "type": "Point",
        "coordinates": [
          -108.533333,
          27.266667
        ]
      },
      "type": "Feature",
      "properties": {
        "hierarchy": [
          "tgn:7348946",
          "tgn:7005581",
          "tgn:1000001",
          "tgn:7005560",
          "tgn:7029392"
        ],
        "placetype": [
          "aat:300008347"
        ],
        "id": 7348946,
        "name:xx": "Agua Caliente"
      }
    },
    {
      "geometry": {
        "type": "Point",
        "coordinates": [
          -109.066667,
          27.216667
        ]
      },
      "type": "Feature",
      "properties": {
        "hierarchy": [
          "tgn:7348947",
          "tgn:1000001",
          "tgn:1001960",
          "tgn:7005560",
          "tgn:7029392"
        ],
        "placetype": [
          "aat:300008347"
        ],
        "id": 7348947,
        "name:xx": "Agua Caliente"
      }
    },
    {
      "geometry": {
        "type": "Point",
        "coordinates": [
          -106.216667,
          26.883333
        ]
      },
      "type": "Feature",
      "properties": {
        "hierarchy": [
          "tgn:7348948",
          "tgn:7005581",
          "tgn:1000001",
          "tgn:7005560",
          "tgn:7029392"
        ],
        "placetype": [
          "aat:300008347"
        ],
        "id": 7348948,
        "name:xx": "Agua Caliente"
      }
    },
    {
      "geometry": {
        "type": "Point",
        "coordinates": [
          -105.983333,
          26.883333
        ]
      },
      "type": "Feature",
      "properties": {
        "hierarchy": [
          "tgn:7348949",
          "tgn:7005581",
          "tgn:1000001",
          "tgn:7005560",
          "tgn:7029392"
        ],
        "placetype": [
          "aat:300008347"
        ],
        "id": 7348949,
        "name:xx": "Agua Caliente"
      }
    }
  ]
}
