{
  "geometry": {
    "type": "Point",
    "coordinates": [
      -105.0167,
      41.0167
    ]
  },
  "type": "Feature",
  "properties": {
    "hierarchy": [
      "tgn:2199593",
      "tgn:1000001",
      "tgn:7012149",
      "tgn:2002375",
      "tgn:7007923",
      "tgn:7029392"
    ],
    "placetype": [
      "aat:300008706"
    ],
    "id": 2199593,
    "name:xx": "Brush Creek"
  }
}
