{
  "geometry": {
    "type": "Point",
    "coordinates": [
      -92.0833,
      45.1333
    ]
  },
  "type": "Feature",
  "properties": {
    "hierarchy": [
      "tgn:2120977",
      "tgn:1000001",
      "tgn:2002319",
      "tgn:7012149",
      "tgn:7007922",
      "tgn:7029392"
    ],
    "placetype": [
      "aat:300008347"
    ],
    "id": 2120977,
    "name:xx": "Connorsville"
  }
}
