{
  "geometry": {
    "type": "Point",
    "coordinates": [
      -165.9667,
      54.05
    ]
  },
  "type": "Feature",
  "properties": {
    "hierarchy": [
      "tgn:2224261",
      "tgn:7030515",
      "tgn:7006450",
      "tgn:1000001",
      "tgn:7012149",
      "tgn:7029392"
    ],
    "placetype": [
      "aat:300132316"
    ],
    "id": 2224261,
    "name:xx": "Cascade Bight"
  }
}
