{
  "geometry": {
    "type": "Point",
    "coordinates": [
      -99.4667,
      35.45
    ]
  },
  "type": "Feature",
  "properties": {
    "hierarchy": [
      "tgn:2758826",
      "tgn:2001627",
      "tgn:1000001",
      "tgn:7012149",
      "tgn:7007707",
      "tgn:7029392"
    ],
    "placetype": [
      "aat:300008706"
    ],
    "id": 2758826,
    "name:xx": "West Elk Creek"
  }
}
