{
  "geometry": {
    "type": "Point",
    "coordinates": [
      23.95,
      -1.5833
    ]
  },
  "type": "Feature",
  "properties": {
    "hierarchy": [
      "tgn:1089360",
      "tgn:7001242",
      "tgn:7016654",
      "tgn:1000159",
      "tgn:7029392"
    ],
    "placetype": [
      "aat:300008347"
    ],
    "id": 1089360,
    "name:xx": "Moma"
  }
}
