{
  "geometry": {
    "type": "Point",
    "coordinates": [
      -81.8167,
      37.8167
    ]
  },
  "type": "Feature",
  "properties": {
    "hierarchy": [
      "tgn:2270767",
      "tgn:1000001",
      "tgn:7012149",
      "tgn:2002273",
      "tgn:7013961",
      "tgn:7029392"
    ],
    "placetype": [
      "aat:300008699"
    ],
    "id": 2270767,
    "name:xx": "Cub Branch"
  }
}
