{
  "geometry": {
    "type": "Point",
    "coordinates": [
      -119.6667,
      33.9667
    ]
  },
  "type": "Feature",
  "properties": {
    "hierarchy": [
      "tgn:2181018",
      "tgn:1000001",
      "tgn:7012149",
      "tgn:1009002",
      "tgn:7007157",
      "tgn:1002867",
      "tgn:7029392"
    ],
    "placetype": [
      "aat:300008678"
    ],
    "id": 2181018,
    "name:xx": "Blue Banks Anchorage"
  }
}
