{
  "geometry": {
    "type": "Point",
    "coordinates": [
      -74.5833,
      9.3167
    ]
  },
  "type": "Feature",
  "properties": {
    "hierarchy": [
      "tgn:1023998",
      "tgn:1000050",
      "tgn:1000682",
      "tgn:1000002",
      "tgn:7029392"
    ],
    "placetype": [
      "aat:300008347"
    ],
    "id": 1023998,
    "name:xx": "Santa Ana"
  }
}
