{
  "type": "FeatureCollection",
  "features": [
    {
      "geometry": {
        "type": "Point",
        "coordinates": [
          -38.9833,
          -8.7833
        ]
      },
      "type": "Feature",
      "properties": {
        "hierarchy": [
          "tgn:1126600",
          "tgn:1001834",
          "tgn:1000047",
          "tgn:7002455",
          "tgn:1000002",
          "tgn:7029392"
        ],
        "placetype": [
          "aat:300008707"
        ],
        "id": 1126600,
        "name:xx": "Maçururé"
      }
    },
    {
      "geometry": {
        "type": "Point",
        "coordinates": [
          17.8768,
          50.719433
        ]
      },
      "type": "Feature",
      "properties": {
        "hierarchy": [
          "tgn:1126601",
          "tgn:1000003",
          "tgn:7006366",
          "tgn:7029392"
        ],
        "placetype": [
          "aat:300008707"
        ],
        "id": 1126601,
        "name:xx": "Mała Panew"
      }
    },
    {
      "geometry": {
        "type": "Point",
        "coordinates": [
          103.9667,
          29.1333
        ]
      },
      "type": "Feature",
      "properties": {
        "hierarchy": [
          "tgn:1126604",
          "tgn:1000004",
          "tgn:7002087",
          "tgn:1000111",
          "tgn:7029392"
        ],
        "placetype": [
          "aat:300008707"
        ],
        "id": 1126604,
        "name:xx": "Mabian"
      }
    },
    {
      "geometry": {
        "type": "Point",
        "coordinates": [
          -12.75,
          9
        ]
      },
      "type": "Feature",
      "properties": {
        "hierarchy": [
          "tgn:1126605",
          "tgn:7001242",
          "tgn:1001460",
          "tgn:1000191",
          "tgn:7029392"
        ],
        "placetype": [
          "aat:300008707"
        ],
        "id": 1126605,
        "name:xx": "Mabole"
      }
    },
    {
      "geometry": {
        "type": "Point",
        "coordinates": [
          -107.9667,
          59.2
        ]
      },
      "type": "Feature",
      "properties": {
        "hierarchy": [
          "tgn:1126606",
          "tgn:7005685",
          "tgn:1000001",
          "tgn:7005805",
          "tgn:7029392"
        ],
        "placetype": [
          "aat:300008707"
        ],
        "id": 1126606,
        "name:xx": "MacFarlane"
      }
    },
    {
      "geometry": {
        "type": "Point",
        "coordinates": [
          -43.0333,
          -22.7
        ]
      },
      "type": "Feature",
      "properties": {
        "hierarchy": [
          "tgn:1126608",
          "tgn:1001942",
          "tgn:1000047",
          "tgn:7002457",
          "tgn:1000002",
          "tgn:7029392"
        ],
        "placetype": [
          "aat:300008707"
        ],
        "id": 1126608,
        "name:xx": "Macacu"
      }
    }
  ]
}
