{
  "geometry": {
    "type": "Point",
    "coordinates": [
      -154.7167,
      63.2667
    ]
  },
  "type": "Feature",
  "properties": {
    "hierarchy": [
      "tgn:2690706",
      "tgn:7006450",
      "tgn:1000001",
      "tgn:7012149",
      "tgn:2000089",
      "tgn:7029392"
    ],
    "placetype": [
      "aat:300008798"
    ],
    "id": 2690706,
    "name:xx": "Strand Peak"
  }
}
