{
  "geometry": {
    "type": "Point",
    "coordinates": [
      -74.5667,
      43.4833
    ]
  },
  "type": "Feature",
  "properties": {
    "hierarchy": [
      "tgn:2677238",
      "tgn:1000001",
      "tgn:7012149",
      "tgn:7007568",
      "tgn:7029392"
    ],
    "placetype": [
      "aat:300008706"
    ],
    "id": 2677238,
    "name:xx": "South Branch West Canada Creek"
  }
}
