{
  "type": "FeatureCollection",
  "features": [
    {
      "geometry": {
        "type": "Point",
        "coordinates": [
          -121.8833,
          45.5
        ]
      },
      "type": "Feature",
      "properties": {
        "hierarchy": [
          "tgn:2709300",
          "tgn:1000001",
          "tgn:7012149",
          "tgn:7007708",
          "tgn:7029392"
        ],
        "placetype": [
          "aat:300008798"
        ],
        "id": 2709300,
        "name:xx": "Table Mountain"
      }
    },
    {
      "geometry": {
        "type": "Point",
        "coordinates": [
          -117.1833,
          43.1167
        ]
      },
      "type": "Feature",
      "properties": {
        "hierarchy": [
          "tgn:2709301",
          "tgn:1000001",
          "tgn:7012149",
          "tgn:2001718",
          "tgn:7007708",
          "tgn:7029392"
        ],
        "placetype": [
          "aat:300008798"
        ],
        "id": 2709301,
        "name:xx": "Table Mountain"
      }
    },
    {
      "geometry": {
        "type": "Point",
        "coordinates": [
          -103.65,
          45.8833
        ]
      },
      "type": "Feature",
      "properties": {
        "hierarchy": [
          "tgn:2709302",
          "tgn:1000001",
          "tgn:2001801",
          "tgn:7012149",
          "tgn:7007713",
          "tgn:7029392"
        ],
        "placetype": [
          "aat:300008798"
        ],
        "id": 2709302,
        "name:xx": "Table Mountain"
      }
    },
    {
      "geometry": {
        "type": "Point",
        "coordinates": [
          -99.8167,
          32.0167
        ]
      },
      "type": "Feature",
      "properties": {
        "hierarchy": [
          "tgn:2709303",
          "tgn:1000001",
          "tgn:7012149",
          "tgn:2002065",
          "tgn:7007826",
          "tgn:7029392"
        ],
        "placetype": [
          "aat:300008798"
        ],
        "id": 2709303,
        "name:xx": "Table Mountain"
      }
    },
    {
      "geometry": {
        "type": "Point",
        "coordinates": [
          -112.3,
          37.3167
        ]
      },
      "type": "Feature",
      "properties": {
        "hierarchy": [
          "tgn:2709304",
          "tgn:1000001",
          "tgn:7012149",
          "tgn:2002113",
          "tgn:7007827",
          "tgn:7029392"
        ],
        "placetype": [
          "aat:300008798"
        ],
        "id": 2709304,
        "name:xx": "Table Mountain"
      }
    },
    {
      "geometry": {
        "type": "Point",
        "coordinates": [
          -110.8333,
          38.15
        ]
      },
      "type": "Feature",
      "properties": {
        "hierarchy": [
          "tgn:2709305",
          "tgn:1000001",
          "tgn:7012149",
          "tgn:2002128",
          "tgn:7007827",
          "tgn:7029392"
        ],
        "placetype": [
          "aat:300008798"
        ],
        "id": 2709305,
        "name:xx": "Table Mountain"
      }
    },
    {
      "geometry": {
        "type": "Point",
        "coordinates": [
          -113.5167,
          38.8
        ]
      },
      "type": "Feature",
      "properties": {
        "hierarchy": [
          "tgn:2709306",
          "tgn:1000001",
          "tgn:7012149",
          "tgn:2002114",
          "tgn:7007827",
          "tgn:7029392"
        ],
        "placetype": [
          "aat:300008798"
        ],
        "id": 2709306,
        "name:xx": "Table Mountain"
      }
    },
    {
      "geometry": {
        "type": "Point",
        "coordinates": [
          -112.1,
          38.8167
        ]
      },
      "type": "Feature",
      "properties": {
        "hierarchy": [
          "tgn:2709307",
          "tgn:1000001",
          "tgn:7012149",
          "tgn:2002121",
          "tgn:7007827",
          "tgn:7029392"
        ],
        "placetype": [
          "aat:300008798"
        ],
        "id": 2709307,
        "name:xx": "Table Mountain"
      }
    },
    {
      "geometry": {
        "type": "Point",
        "coordinates": [
          -112.8833,
          39.9333
        ]
      },
      "type": "Feature",
      "properties": {
        "hierarchy": [
          "tgn:2709308",
          "tgn:1000001",
          "tgn:7012149",
          "tgn:2002123",
          "tgn:7007827",
          "tgn:7029392"
        ],
        "placetype": [
          "aat:300008798"
        ],
        "id": 2709308,
        "name:xx": "Table Mountain"
      }
    },
    {
      "geometry": {
        "type": "Point",
        "coordinates": [
          -111.2,
          41.3
        ]
      },
      "type": "Feature",
      "properties": {
        "hierarchy": [
          "tgn:2709309",
          "tgn:1000001",
          "tgn:7012149",
          "tgn:2002117",
          "tgn:7007827",
          "tgn:7029392"
        ],
        "placetype": [
          "aat:300008798"
        ],
        "id": 2709309,
        "name:xx": "Table Mountain"
      }
    }
  ]
}
