{
  "geometry": {
    "type": "Point",
    "coordinates": [
      30.24238,
      30.43148
    ]
  },
  "type": "Feature",
  "properties": {
    "hierarchy": [
      "tgn:7537062",
      "tgn:7001242",
      "tgn:1001075",
      "tgn:7016833",
      "tgn:7029392"
    ],
    "placetype": [
      "aat:300008680"
    ],
    "name:en": "Bayḑah, Buḩayrat al",
    "id": 7537062
  }
}
