{
  "geometry": {
    "type": "Point",
    "coordinates": [
      -89.7667,
      33.8167
    ]
  },
  "type": "Feature",
  "properties": {
    "hierarchy": [
      "tgn:2365818",
      "tgn:1000001",
      "tgn:7012149",
      "tgn:7007522",
      "tgn:7029392"
    ],
    "placetype": [
      "aat:300006191"
    ],
    "id": 2365818,
    "name:xx": "Grenada Lake"
  }
}
