{
  "geometry": {
    "type": "Point",
    "coordinates": [
      79.7821,
      27.2276
    ]
  },
  "type": "Feature",
  "properties": {
    "hierarchy": [
      "tgn:7562032",
      "tgn:1000004",
      "tgn:7000198",
      "tgn:7016722",
      "tgn:7029392"
    ],
    "placetype": [
      "aat:300008347"
    ],
    "name:en": "Khimal ki Marhaiyān",
    "id": 7562032
  }
}
