{
  "geometry": {
    "type": "Point",
    "coordinates": [
      -74.75,
      44.1667
    ]
  },
  "type": "Feature",
  "properties": {
    "hierarchy": [
      "tgn:2308539",
      "tgn:1000001",
      "tgn:7012149",
      "tgn:7016021",
      "tgn:7007568",
      "tgn:7029392"
    ],
    "placetype": [
      "aat:300008798"
    ],
    "id": 2308539,
    "name:xx": "East Mountain"
  }
}
