{
  "geometry": {
    "type": "Point",
    "coordinates": [
      52.0833,
      49.8333
    ]
  },
  "type": "Feature",
  "properties": {
    "hierarchy": [
      "tgn:1128069",
      "tgn:1000004",
      "tgn:7011457",
      "tgn:7014786",
      "tgn:7029392"
    ],
    "placetype": [
      "aat:300008707"
    ],
    "id": 1128069,
    "name:xx": "Olenty"
  }
}
