{
  "geometry": {
    "type": "Point",
    "coordinates": [
      -151.05,
      60.7667
    ]
  },
  "type": "Feature",
  "properties": {
    "hierarchy": [
      "tgn:2697851",
      "tgn:7006450",
      "tgn:1000001",
      "tgn:7019698",
      "tgn:7012149",
      "tgn:7029392"
    ],
    "placetype": [
      "aat:300008680"
    ],
    "id": 2697851,
    "name:xx": "Stormy Lake"
  }
}
