{
  "geometry": {
    "type": "Point",
    "coordinates": [
      -82.7167,
      28.85
    ]
  },
  "type": "Feature",
  "properties": {
    "hierarchy": [
      "tgn:2468398",
      "tgn:1000001",
      "tgn:1002269",
      "tgn:7012149",
      "tgn:7007240",
      "tgn:7029392"
    ],
    "placetype": [
      "aat:300008850"
    ],
    "id": 2468398,
    "name:xx": "Long Point"
  }
}
