{
  "geometry": {
    "type": "Point",
    "coordinates": [
      -59.1167,
      -34.5667
    ]
  },
  "type": "Feature",
  "properties": {
    "hierarchy": [
      "tgn:1136444",
      "tgn:1001160",
      "tgn:7006477",
      "tgn:1000002",
      "tgn:7029392"
    ],
    "placetype": [
      "aat:300008347"
    ],
    "id": 1136444,
    "name:xx": "Luján"
  }
}
