{
  "type": "FeatureCollection",
  "features": [
    {
      "geometry": {
        "type": "Point",
        "coordinates": [
          -2.633333,
          39.3
        ]
      },
      "type": "Feature",
      "properties": {
        "hierarchy": [
          "tgn:7344130",
          "tgn:7002803",
          "tgn:1001647",
          "tgn:1000003",
          "tgn:1000095",
          "tgn:7029392"
        ],
        "placetype": [
          "aat:300008347"
        ],
        "id": 7344130,
        "name:xx": "Casa Madres"
      }
    },
    {
      "geometry": {
        "type": "Point",
        "coordinates": [
          -1.6,
          38.5
        ]
      },
      "type": "Feature",
      "properties": {
        "hierarchy": [
          "tgn:7344131",
          "tgn:7002803",
          "tgn:1001647",
          "tgn:1000003",
          "tgn:1000095",
          "tgn:7029392"
        ],
        "placetype": [
          "aat:300266554",
          "aat:300008699"
        ],
        "id": 7344131,
        "name:xx": "Casalta, Barranco de la"
      }
    },
    {
      "geometry": {
        "type": "Point",
        "coordinates": [
          -0.15,
          40.266667
        ]
      },
      "type": "Feature",
      "properties": {
        "hierarchy": [
          "tgn:7344132",
          "tgn:7002815",
          "tgn:1000003",
          "tgn:7002793",
          "tgn:1000095",
          "tgn:7029392"
        ],
        "placetype": [
          "aat:300008347"
        ],
        "id": 7344132,
        "name:xx": "Casa-Lluna"
      }
    },
    {
      "geometry": {
        "type": "Point",
        "coordinates": [
          -0.7,
          38.816667
        ]
      },
      "type": "Feature",
      "properties": {
        "hierarchy": [
          "tgn:7344133",
          "tgn:7001165",
          "tgn:1000003",
          "tgn:7002793",
          "tgn:1000095",
          "tgn:7029392"
        ],
        "placetype": [
          "aat:300008347"
        ],
        "id": 7344133,
        "name:xx": "Casa Lloma Rasa"
      }
    },
    {
      "geometry": {
        "type": "Point",
        "coordinates": [
          -6.45,
          41.1
        ]
      },
      "type": "Feature",
      "properties": {
        "hierarchy": [
          "tgn:7344135",
          "tgn:7002835",
          "tgn:7001158",
          "tgn:1000003",
          "tgn:1000095",
          "tgn:7029392"
        ],
        "placetype": [
          "aat:300008699"
        ],
        "id": 7344135,
        "name:xx": "Casales, Rivera de los"
      }
    },
    {
      "geometry": {
        "type": "Point",
        "coordinates": [
          -2.909937,
          42.549114
        ]
      },
      "type": "Feature",
      "properties": {
        "hierarchy": [
          "tgn:7344136",
          "tgn:7002827",
          "tgn:1000003",
          "tgn:7002789",
          "tgn:1000095",
          "tgn:7029392"
        ],
        "placetype": [
          "aat:300008347"
        ],
        "id": 7344136,
        "name:xx": "Casalarreina"
      }
    },
    {
      "geometry": {
        "type": "Point",
        "coordinates": [
          -8.116667,
          41.916667
        ]
      },
      "type": "Feature",
      "properties": {
        "hierarchy": [
          "tgn:7344137",
          "tgn:7002831",
          "tgn:1000003",
          "tgn:7002786",
          "tgn:1000095",
          "tgn:7029392"
        ],
        "placetype": [
          "aat:300008699"
        ],
        "id": 7344137,
        "name:xx": "Casal, Río de"
      }
    },
    {
      "geometry": {
        "type": "Point",
        "coordinates": [
          -5.933333,
          41.833333
        ]
      },
      "type": "Feature",
      "properties": {
        "hierarchy": [
          "tgn:7344138",
          "tgn:7001158",
          "tgn:7002850",
          "tgn:1000003",
          "tgn:1000095",
          "tgn:7029392"
        ],
        "placetype": [
          "aat:300008699"
        ],
        "id": 7344138,
        "name:xx": "Casal, Arroyo del"
      }
    },
    {
      "geometry": {
        "type": "Point",
        "coordinates": [
          -7,
          43.5
        ]
      },
      "type": "Feature",
      "properties": {
        "hierarchy": [
          "tgn:7344139",
          "tgn:7008911",
          "tgn:1000003",
          "tgn:7002763",
          "tgn:1000095",
          "tgn:7029392"
        ],
        "placetype": [
          "aat:300008347"
        ],
        "id": 7344139,
        "name:xx": "Casal"
      }
    }
  ]
}
