{
  "type": "FeatureCollection",
  "features": [
    {
      "geometry": {
        "type": "Point",
        "coordinates": [
          -7,
          41.983333
        ]
      },
      "type": "Feature",
      "properties": {
        "hierarchy": [
          "tgn:7343430",
          "tgn:7002831",
          "tgn:1000003",
          "tgn:7002786",
          "tgn:1000095",
          "tgn:7029392"
        ],
        "placetype": [
          "aat:300008347"
        ],
        "id": 7343430,
        "name:xx": "Cádavos"
      }
    },
    {
      "geometry": {
        "type": "Point",
        "coordinates": [
          -6.383333,
          43.55
        ]
      },
      "type": "Feature",
      "properties": {
        "hierarchy": [
          "tgn:7343431",
          "tgn:7008911",
          "tgn:1000003",
          "tgn:7002763",
          "tgn:1000095",
          "tgn:7029392"
        ],
        "placetype": [
          "aat:300008347"
        ],
        "id": 7343431,
        "name:xx": "Cadavedo"
      }
    },
    {
      "geometry": {
        "type": "Point",
        "coordinates": [
          -8.9,
          42.7
        ]
      },
      "type": "Feature",
      "properties": {
        "hierarchy": [
          "tgn:7343432",
          "tgn:7002824",
          "tgn:1000003",
          "tgn:7002786",
          "tgn:1000095",
          "tgn:7029392"
        ],
        "placetype": [
          "aat:300008347"
        ],
        "id": 7343432,
        "name:xx": "Cadarnojo"
      }
    },
    {
      "geometry": {
        "type": "Point",
        "coordinates": [
          -5.416667,
          43.316667
        ]
      },
      "type": "Feature",
      "properties": {
        "hierarchy": [
          "tgn:7343434",
          "tgn:7008911",
          "tgn:1000003",
          "tgn:7002763",
          "tgn:1000095",
          "tgn:7029392"
        ],
        "placetype": [
          "aat:300008347"
        ],
        "id": 7343434,
        "name:xx": "Cadapereda"
      }
    },
    {
      "geometry": {
        "type": "Point",
        "coordinates": [
          -5.333333,
          43.383333
        ]
      },
      "type": "Feature",
      "properties": {
        "hierarchy": [
          "tgn:7343435",
          "tgn:7008911",
          "tgn:1000003",
          "tgn:7002763",
          "tgn:1000095",
          "tgn:7029392"
        ],
        "placetype": [
          "aat:300008347"
        ],
        "id": 7343435,
        "name:xx": "Cadanes"
      }
    },
    {
      "geometry": {
        "type": "Point",
        "coordinates": [
          -6.5,
          38.733333
        ]
      },
      "type": "Feature",
      "properties": {
        "hierarchy": [
          "tgn:7343436",
          "tgn:7002807",
          "tgn:1000003",
          "tgn:7003837",
          "tgn:1000095",
          "tgn:7029392"
        ],
        "placetype": [
          "aat:300008347"
        ],
        "id": 7343436,
        "name:xx": "Casas Marqués de la Encomienda"
      }
    },
    {
      "geometry": {
        "type": "Point",
        "coordinates": [
          -0.85,
          38.8
        ]
      },
      "type": "Feature",
      "properties": {
        "hierarchy": [
          "tgn:7343437",
          "tgn:7001165",
          "tgn:1000003",
          "tgn:7002793",
          "tgn:1000095",
          "tgn:7029392"
        ],
        "placetype": [
          "aat:300008347"
        ],
        "id": 7343437,
        "name:xx": "Casas Los Collados"
      }
    },
    {
      "geometry": {
        "type": "Point",
        "coordinates": [
          -1.066667,
          37.6
        ]
      },
      "type": "Feature",
      "properties": {
        "hierarchy": [
          "tgn:7343438",
          "tgn:1001439",
          "tgn:1000003",
          "tgn:7002797",
          "tgn:1000095",
          "tgn:7029392"
        ],
        "placetype": [
          "aat:300008347"
        ],
        "id": 7343438,
        "name:xx": "Casas las Escarihuelas"
      }
    },
    {
      "geometry": {
        "type": "Point",
        "coordinates": [
          -0.2,
          39.05
        ]
      },
      "type": "Feature",
      "properties": {
        "hierarchy": [
          "tgn:7343439",
          "tgn:7001165",
          "tgn:1000003",
          "tgn:7002793",
          "tgn:1000095",
          "tgn:7029392"
        ],
        "placetype": [
          "aat:300008347"
        ],
        "id": 7343439,
        "name:xx": "Casas Las Basas"
      }
    }
  ]
}
