{
  "geometry": {
    "type": "Point",
    "coordinates": [
      -81.9833,
      36.0833
    ]
  },
  "type": "Feature",
  "properties": {
    "hierarchy": [
      "tgn:2356265",
      "tgn:2001468",
      "tgn:1000001",
      "tgn:7012149",
      "tgn:7007709",
      "tgn:7029392"
    ],
    "placetype": [
      "aat:300008699"
    ],
    "id": 2356265,
    "name:xx": "Gooseneck Branch"
  }
}
