{
  "type": "FeatureCollection",
  "features": [
    {
      "geometry": {
        "type": "Point",
        "coordinates": [
          -121.7833,
          36.8
        ]
      },
      "type": "Feature",
      "properties": {
        "hierarchy": [
          "tgn:7015372",
          "tgn:1000001",
          "tgn:7012149",
          "tgn:7007157",
          "tgn:1002684",
          "tgn:7029392"
        ],
        "placetype": [
          "aat:300008347"
        ],
        "id": 7015372,
        "name:xx": "Moss Landing"
      }
    },
    {
      "geometry": {
        "type": "Point",
        "coordinates": [
          -122.4,
          37.8
        ]
      },
      "type": "Feature",
      "properties": {
        "hierarchy": [
          "tgn:7015373",
          "tgn:1000001",
          "tgn:7014456",
          "tgn:7012149",
          "tgn:7007157",
          "tgn:1002859",
          "tgn:7029392"
        ],
        "placetype": [
          "aat:300000745"
        ],
        "id": 7015373,
        "name:xx": "North Beach"
      }
    },
    {
      "geometry": {
        "type": "Point",
        "coordinates": [
          -117.8167,
          33.6667
        ]
      },
      "type": "Feature",
      "properties": {
        "hierarchy": [
          "tgn:7015377",
          "tgn:1000001",
          "tgn:7012149",
          "tgn:7007157",
          "tgn:1002748",
          "tgn:7029392"
        ],
        "placetype": [
          "aat:300008347"
        ],
        "id": 7015377,
        "name:xx": "Irvine"
      }
    },
    {
      "geometry": {
        "type": "Point",
        "coordinates": [
          -117.7,
          33.6
        ]
      },
      "type": "Feature",
      "properties": {
        "hierarchy": [
          "tgn:7015378",
          "tgn:1000001",
          "tgn:7012149",
          "tgn:7007157",
          "tgn:1002748",
          "tgn:7029392"
        ],
        "placetype": [
          "aat:300008347"
        ],
        "id": 7015378,
        "name:xx": "Laguna Hills"
      }
    }
  ]
}
