{
  "type": "FeatureCollection",
  "features": [
    {
      "geometry": {
        "type": "Point",
        "coordinates": [
          -83.85,
          41.6333
        ]
      },
      "type": "Feature",
      "properties": {
        "hierarchy": [
          "tgn:2338860",
          "tgn:1000001",
          "tgn:7012149",
          "tgn:1002611",
          "tgn:7007706",
          "tgn:7029392"
        ],
        "placetype": [
          "aat:300008347"
        ],
        "id": 2338860,
        "name:xx": "Frankfort"
      }
    },
    {
      "geometry": {
        "type": "Point",
        "coordinates": [
          -96.6667,
          36.9667
        ]
      },
      "type": "Feature",
      "properties": {
        "hierarchy": [
          "tgn:2338862",
          "tgn:1000001",
          "tgn:7012149",
          "tgn:2001679",
          "tgn:7007707",
          "tgn:7029392"
        ],
        "placetype": [
          "aat:300008347"
        ],
        "id": 2338862,
        "name:xx": "Frankfort"
      }
    },
    {
      "geometry": {
        "type": "Point",
        "coordinates": [
          -123.75,
          46.2667
        ]
      },
      "type": "Feature",
      "properties": {
        "hierarchy": [
          "tgn:2338863",
          "tgn:1000001",
          "tgn:7012149",
          "tgn:1002767",
          "tgn:7007920",
          "tgn:7029392"
        ],
        "placetype": [
          "aat:300008347"
        ],
        "id": 2338863,
        "name:xx": "Frankfort"
      }
    },
    {
      "geometry": {
        "type": "Point",
        "coordinates": [
          -81.8,
          24.5667
        ]
      },
      "type": "Feature",
      "properties": {
        "hierarchy": [
          "tgn:2338864",
          "tgn:1000001",
          "tgn:7012149",
          "tgn:1002676",
          "tgn:7007240",
          "tgn:7029392"
        ],
        "placetype": [
          "aat:300132348"
        ],
        "id": 2338864,
        "name:xx": "Frankfort Bank"
      }
    },
    {
      "geometry": {
        "type": "Point",
        "coordinates": [
          -83.85,
          41.6333
        ]
      },
      "type": "Feature",
      "properties": {
        "hierarchy": [
          "tgn:2338865",
          "tgn:1000001",
          "tgn:7012149",
          "tgn:7007706",
          "tgn:7029392"
        ],
        "placetype": [
          "aat:300006075"
        ],
        "id": 2338865,
        "name:xx": "Frankfort Ditch"
      }
    },
    {
      "geometry": {
        "type": "Point",
        "coordinates": [
          -75.1667,
          43
        ]
      },
      "type": "Feature",
      "properties": {
        "hierarchy": [
          "tgn:2338866",
          "tgn:1000001",
          "tgn:7012149",
          "tgn:1002472",
          "tgn:7007568",
          "tgn:7029392"
        ],
        "placetype": [
          "aat:300008761"
        ],
        "id": 2338866,
        "name:xx": "Frankfort Gorge"
      }
    },
    {
      "geometry": {
        "type": "Point",
        "coordinates": [
          -70.8,
          43.1
        ]
      },
      "type": "Feature",
      "properties": {
        "hierarchy": [
          "tgn:2338867",
          "tgn:1000001",
          "tgn:7012149",
          "tgn:2000933",
          "tgn:7007515",
          "tgn:7029392"
        ],
        "placetype": [
          "aat:300008791"
        ],
        "id": 2338867,
        "name:xx": "Frankfort Island"
      }
    },
    {
      "geometry": {
        "type": "Point",
        "coordinates": [
          -80.4167,
          40.4833
        ]
      },
      "type": "Feature",
      "properties": {
        "hierarchy": [
          "tgn:2338869",
          "tgn:1002171",
          "tgn:1000001",
          "tgn:7012149",
          "tgn:7007710",
          "tgn:7029392"
        ],
        "placetype": [
          "aat:300008697"
        ],
        "id": 2338869,
        "name:xx": "Frankfort Springs"
      }
    }
  ]
}
