{
  "geometry": {
    "type": "Point",
    "coordinates": [
      -75.9667,
      41.15
    ]
  },
  "type": "Feature",
  "properties": {
    "hierarchy": [
      "tgn:2551152",
      "tgn:1000001",
      "tgn:7012149",
      "tgn:1002612",
      "tgn:7007710",
      "tgn:7029392"
    ],
    "placetype": [
      "aat:300008699"
    ],
    "id": 2551152,
    "name:xx": "Nuangola Outlet"
  }
}
