{
  "geometry": {
    "type": "Point",
    "coordinates": [
      1.6667,
      45.1833
    ]
  },
  "type": "Feature",
  "properties": {
    "hierarchy": [
      "tgn:7008388",
      "tgn:1000003",
      "tgn:7001095",
      "tgn:1000070",
      "tgn:7029392"
    ],
    "placetype": [
      "aat:300008347"
    ],
    "id": 7008388,
    "name:xx": "Aubazines"
  }
}
