{
  "geometry": {
    "type": "Point",
    "coordinates": [
      -113.4333,
      48.4833
    ]
  },
  "type": "Feature",
  "properties": {
    "hierarchy": [
      "tgn:2172139",
      "tgn:1000001",
      "tgn:7012149",
      "tgn:2001277",
      "tgn:7007524",
      "tgn:7029392"
    ],
    "placetype": [
      "aat:300386845"
    ],
    "id": 2172139,
    "name:xx": "Bighorn Basin"
  }
}
