{
  "geometry": {
    "type": "Point",
    "coordinates": [
      -82.8167,
      37.6167
    ]
  },
  "type": "Feature",
  "properties": {
    "hierarchy": [
      "tgn:2159764",
      "tgn:1000001",
      "tgn:7012149",
      "tgn:2000789",
      "tgn:7007255",
      "tgn:7029392"
    ],
    "placetype": [
      "aat:300008699"
    ],
    "id": 2159764,
    "name:xx": "Beech Branch"
  }
}
