{
  "geometry": {
    "type": "Point",
    "coordinates": [
      111.5667,
      36.1333
    ]
  },
  "type": "Feature",
  "properties": {
    "hierarchy": [
      "tgn:1069846",
      "tgn:1000004",
      "tgn:7002086",
      "tgn:1000111",
      "tgn:7029392"
    ],
    "placetype": [
      "aat:300008347"
    ],
    "id": 1069846,
    "name:xx": "Linfen"
  }
}
