{
  "geometry": {
    "type": "Point",
    "coordinates": [
      -92.4833,
      34.7167
    ]
  },
  "type": "Feature",
  "properties": {
    "hierarchy": [
      "tgn:2156871",
      "tgn:1000001",
      "tgn:7016172",
      "tgn:7012149",
      "tgn:2000164",
      "tgn:7029392"
    ],
    "placetype": [
      "aat:300008699"
    ],
    "id": 2156871,
    "name:xx": "Beauchamp Branch"
  }
}
