{
  "geometry": {
    "type": "Point",
    "coordinates": [
      12.55,
      49.05
    ]
  },
  "type": "Feature",
  "properties": {
    "hierarchy": [
      "tgn:7145630",
      "tgn:7003669",
      "tgn:1000003",
      "tgn:7000084",
      "tgn:7029392"
    ],
    "placetype": [
      "aat:300000206"
    ],
    "id": 7145630,
    "name:xx": "Kleinviecht"
  }
}
