{
  "geometry": {
    "type": "Point",
    "coordinates": [
      -109.0833,
      43.5167
    ]
  },
  "type": "Feature",
  "properties": {
    "hierarchy": [
      "tgn:2250234",
      "tgn:1000001",
      "tgn:7012149",
      "tgn:2002371",
      "tgn:7007923",
      "tgn:7029392"
    ],
    "placetype": [
      "aat:300008347"
    ],
    "id": 2250234,
    "name:xx": "Collins Place"
  }
}
