{
  "geometry": {
    "type": "Point",
    "coordinates": [
      -90.4833,
      38.9333
    ]
  },
  "type": "Feature",
  "properties": {
    "hierarchy": [
      "tgn:2689487",
      "tgn:1000001",
      "tgn:1002221",
      "tgn:7012149",
      "tgn:7007251",
      "tgn:7029392"
    ],
    "placetype": [
      "aat:300008791"
    ],
    "id": 2689487,
    "name:xx": "Squaw Island"
  }
}
