{
  "geometry": {
    "type": "Point",
    "coordinates": [
      -95.65,
      32.35
    ]
  },
  "type": "Feature",
  "properties": {
    "hierarchy": [
      "tgn:2598407",
      "tgn:1000001",
      "tgn:7012149",
      "tgn:7007826",
      "tgn:7029392"
    ],
    "placetype": [
      "aat:300008699"
    ],
    "id": 2598407,
    "name:xx": "Price Branch"
  }
}
