{
  "geometry": {
    "type": "Point",
    "coordinates": [
      -122.8833,
      41.2167
    ]
  },
  "type": "Feature",
  "properties": {
    "hierarchy": [
      "tgn:2223753",
      "tgn:1000001",
      "tgn:7012149",
      "tgn:7007157",
      "tgn:2000189",
      "tgn:7029392"
    ],
    "placetype": [
      "aat:300008798"
    ],
    "id": 2223753,
    "name:xx": "Carter Meadows Summit"
  }
}
