{
  "type": "FeatureCollection",
  "features": [
    {
      "geometry": {
        "type": "Point",
        "coordinates": [
          22.857079,
          37.250396
        ]
      },
      "type": "Feature",
      "properties": {
        "hierarchy": [
          "tgn:7218710",
          "tgn:7002735",
          "tgn:7017076",
          "tgn:1000003",
          "tgn:1000074",
          "tgn:7029392"
        ],
        "placetype": [
          "aat:300008347"
        ],
        "id": 7218710,
        "name:xx": "Tyrós"
      }
    },
    {
      "geometry": {
        "type": "Point",
        "coordinates": [
          20.533333,
          39.666667
        ]
      },
      "type": "Feature",
      "properties": {
        "hierarchy": [
          "tgn:7218713",
          "tgn:7002707",
          "tgn:7002705",
          "tgn:1000003",
          "tgn:1000074",
          "tgn:7029392"
        ],
        "placetype": [
          "aat:300008699"
        ],
        "id": 7218713,
        "name:xx": "Tíria Réma"
      }
    },
    {
      "geometry": {
        "type": "Point",
        "coordinates": [
          20.4,
          38.2
        ]
      },
      "type": "Feature",
      "properties": {
        "hierarchy": [
          "tgn:7218714",
          "tgn:7011167",
          "tgn:7001338",
          "tgn:1000003",
          "tgn:1000074",
          "tgn:7029392"
        ],
        "placetype": [
          "aat:300008347"
        ],
        "id": 7218714,
        "name:xx": "Tipaldháta"
      }
    },
    {
      "geometry": {
        "type": "Point",
        "coordinates": [
          25.15,
          37.533333
        ]
      },
      "type": "Feature",
      "properties": {
        "hierarchy": [
          "tgn:7218715",
          "tgn:7011270",
          "tgn:7002674",
          "tgn:1000003",
          "tgn:1000074",
          "tgn:7029392"
        ],
        "placetype": [
          "aat:300008678"
        ],
        "id": 7218715,
        "name:xx": "Tínou, Limín"
      }
    },
    {
      "geometry": {
        "type": "Point",
        "coordinates": [
          24.2,
          41.233333
        ]
      },
      "type": "Feature",
      "properties": {
        "hierarchy": [
          "tgn:7218718",
          "tgn:7011170",
          "tgn:7002715",
          "tgn:1000003",
          "tgn:1000074",
          "tgn:7029392"
        ],
        "placetype": [
          "aat:300008347"
        ],
        "id": 7218718,
        "name:xx": "Timótheos"
      }
    },
    {
      "geometry": {
        "type": "Point",
        "coordinates": [
          19.65,
          39.716667
        ]
      },
      "type": "Feature",
      "properties": {
        "hierarchy": [
          "tgn:7218719",
          "tgn:7002711",
          "tgn:7001338",
          "tgn:1000003",
          "tgn:1000074",
          "tgn:7029392"
        ],
        "placetype": [
          "aat:300132316"
        ],
        "id": 7218719,
        "name:xx": "Timóni, Pórto"
      }
    }
  ]
}
