{
  "geometry": {
    "type": "Point",
    "coordinates": [
      -5.05,
      37.95
    ]
  },
  "type": "Feature",
  "properties": {
    "hierarchy": [
      "tgn:7333704",
      "tgn:7002758",
      "tgn:7002817",
      "tgn:1000003",
      "tgn:1000095",
      "tgn:7029392"
    ],
    "placetype": [
      "aat:300008777"
    ],
    "id": 7333704,
    "name:xx": "Escoboso, Cerro"
  }
}
