{
  "geometry": {
    "type": "Point",
    "coordinates": [
      -85.9833,
      36.55
    ]
  },
  "type": "Feature",
  "properties": {
    "hierarchy": [
      "tgn:2768024",
      "tgn:1000001",
      "tgn:7012149",
      "tgn:2001892",
      "tgn:7007825",
      "tgn:7029392"
    ],
    "placetype": [
      "aat:300008746"
    ],
    "id": 2768024,
    "name:xx": "Whiteoak Saltpeter Cave"
  }
}
