{
  "geometry": {
    "type": "Point",
    "coordinates": [
      -103.9167,
      44.35
    ]
  },
  "type": "Feature",
  "properties": {
    "hierarchy": [
      "tgn:2097524",
      "tgn:1000001",
      "tgn:2001810",
      "tgn:7012149",
      "tgn:7007713",
      "tgn:7029392"
    ],
    "placetype": [
      "aat:300008347",
      "aat:300387247"
    ],
    "id": 2097524,
    "name:xx": "Savoy"
  }
}
