{
  "geometry": {
    "type": "Point",
    "coordinates": [
      -86.2167,
      34.4667
    ]
  },
  "type": "Feature",
  "properties": {
    "hierarchy": [
      "tgn:2512390",
      "tgn:7002659",
      "tgn:1000001",
      "tgn:7012149",
      "tgn:2000047",
      "tgn:7029392"
    ],
    "placetype": [
      "aat:300132316"
    ],
    "id": 2512390,
    "name:xx": "Mill Creek"
  }
}
