{
  "type": "FeatureCollection",
  "features": [
    {
      "geometry": {
        "type": "Point",
        "coordinates": [
          -111.083333,
          29.383333
        ]
      },
      "type": "Feature",
      "properties": {
        "hierarchy": [
          "tgn:7358820",
          "tgn:1000001",
          "tgn:1001960",
          "tgn:7005560",
          "tgn:7029392"
        ],
        "placetype": [
          "aat:300008795"
        ],
        "id": 7358820,
        "name:xx": "Colorado, Cerro"
      }
    },
    {
      "geometry": {
        "type": "Point",
        "coordinates": [
          -111.033333,
          29.183333
        ]
      },
      "type": "Feature",
      "properties": {
        "hierarchy": [
          "tgn:7358821",
          "tgn:1000001",
          "tgn:1001960",
          "tgn:7005560",
          "tgn:7029392"
        ],
        "placetype": [
          "aat:300008795"
        ],
        "id": 7358821,
        "name:xx": "Colorado, Cerro"
      }
    },
    {
      "geometry": {
        "type": "Point",
        "coordinates": [
          -107.766667,
          29.1
        ]
      },
      "type": "Feature",
      "properties": {
        "hierarchy": [
          "tgn:7358822",
          "tgn:7005581",
          "tgn:1000001",
          "tgn:7005560",
          "tgn:7029392"
        ],
        "placetype": [
          "aat:300008795"
        ],
        "id": 7358822,
        "name:xx": "Colorado, Cerro"
      }
    },
    {
      "geometry": {
        "type": "Point",
        "coordinates": [
          -110.566667,
          28.816667
        ]
      },
      "type": "Feature",
      "properties": {
        "hierarchy": [
          "tgn:7358823",
          "tgn:1000001",
          "tgn:1001960",
          "tgn:7005560",
          "tgn:7029392"
        ],
        "placetype": [
          "aat:300008795"
        ],
        "id": 7358823,
        "name:xx": "Colorado, Cerro"
      }
    },
    {
      "geometry": {
        "type": "Point",
        "coordinates": [
          -105.866667,
          28.7
        ]
      },
      "type": "Feature",
      "properties": {
        "hierarchy": [
          "tgn:7358824",
          "tgn:7005581",
          "tgn:1000001",
          "tgn:7005560",
          "tgn:7029392"
        ],
        "placetype": [
          "aat:300008795"
        ],
        "id": 7358824,
        "name:xx": "Colorado, Cerro"
      }
    },
    {
      "geometry": {
        "type": "Point",
        "coordinates": [
          -103.383333,
          28.633333
        ]
      },
      "type": "Feature",
      "properties": {
        "hierarchy": [
          "tgn:7358825",
          "tgn:1001853",
          "tgn:1000001",
          "tgn:7005560",
          "tgn:7029392"
        ],
        "placetype": [
          "aat:300008795"
        ],
        "id": 7358825,
        "name:xx": "Colorado, Cerro"
      }
    },
    {
      "geometry": {
        "type": "Point",
        "coordinates": [
          -109.916667,
          28.416667
        ]
      },
      "type": "Feature",
      "properties": {
        "hierarchy": [
          "tgn:7358826",
          "tgn:1000001",
          "tgn:1001960",
          "tgn:7005560",
          "tgn:7029392"
        ],
        "placetype": [
          "aat:300008795"
        ],
        "id": 7358826,
        "name:xx": "Colorado, Cerro"
      }
    },
    {
      "geometry": {
        "type": "Point",
        "coordinates": [
          -107.333333,
          28.366667
        ]
      },
      "type": "Feature",
      "properties": {
        "hierarchy": [
          "tgn:7358827",
          "tgn:7005581",
          "tgn:1000001",
          "tgn:7005560",
          "tgn:7029392"
        ],
        "placetype": [
          "aat:300008795"
        ],
        "id": 7358827,
        "name:xx": "Colorado, Cerro"
      }
    },
    {
      "geometry": {
        "type": "Point",
        "coordinates": [
          -110.8,
          28.083333
        ]
      },
      "type": "Feature",
      "properties": {
        "hierarchy": [
          "tgn:7358828",
          "tgn:1000001",
          "tgn:1001960",
          "tgn:7005560",
          "tgn:7029392"
        ],
        "placetype": [
          "aat:300008795"
        ],
        "id": 7358828,
        "name:xx": "Colorado, Cerro"
      }
    },
    {
      "geometry": {
        "type": "Point",
        "coordinates": [
          -105.55,
          27.733333
        ]
      },
      "type": "Feature",
      "properties": {
        "hierarchy": [
          "tgn:7358829",
          "tgn:7005581",
          "tgn:1000001",
          "tgn:7005560",
          "tgn:7029392"
        ],
        "placetype": [
          "aat:300008795"
        ],
        "id": 7358829,
        "name:xx": "Colorado, Cerro"
      }
    }
  ]
}
