{
  "geometry": {
    "type": "Point",
    "coordinates": [
      -123.6333,
      45.5667
    ]
  },
  "type": "Feature",
  "properties": {
    "hierarchy": [
      "tgn:2458578",
      "tgn:1000001",
      "tgn:7012149",
      "tgn:1002943",
      "tgn:7007708",
      "tgn:7029392"
    ],
    "placetype": [
      "aat:300008707"
    ],
    "id": 2458578,
    "name:xx": "Little North Fork Wilson River"
  }
}
