{
  "geometry": {
    "type": "Point",
    "coordinates": [
      -68.85,
      46.2667
    ]
  },
  "type": "Feature",
  "properties": {
    "hierarchy": [
      "tgn:2158173",
      "tgn:1000001",
      "tgn:7012149",
      "tgn:2000928",
      "tgn:7007515",
      "tgn:7029392"
    ],
    "placetype": [
      "aat:300266640"
    ],
    "id": 2158173,
    "name:xx": "Beaver Pond Ridge"
  }
}
