{
  "geometry": {
    "type": "Point",
    "coordinates": [
      -83.4333,
      44.4333
    ]
  },
  "type": "Feature",
  "properties": {
    "hierarchy": [
      "tgn:2333740",
      "tgn:1000001",
      "tgn:7012149",
      "tgn:2000965",
      "tgn:7007520",
      "tgn:7029392"
    ],
    "placetype": [
      "aat:300006191"
    ],
    "id": 2333740,
    "name:xx": "Foote Dam Pond"
  }
}
