{
  "geometry": {
    "type": "Point",
    "coordinates": [
      24.5167,
      46.1333
    ]
  },
  "type": "Feature",
  "properties": {
    "hierarchy": [
      "tgn:4001508",
      "tgn:1000003",
      "tgn:1000443",
      "tgn:1000091",
      "tgn:7029392"
    ],
    "placetype": [
      "aat:300008347"
    ],
    "id": 4001508,
    "name:xx": "Biertan"
  }
}
