{
  "geometry": {
    "type": "Point",
    "coordinates": [
      -82.6167,
      40.65
    ]
  },
  "type": "Feature",
  "properties": {
    "hierarchy": [
      "tgn:2438286",
      "tgn:1000001",
      "tgn:7012149",
      "tgn:1002697",
      "tgn:7007706",
      "tgn:7029392"
    ],
    "placetype": [
      "aat:300008347"
    ],
    "id": 2438286,
    "name:xx": "Kings Corners"
  }
}
