{
  "geometry": {
    "type": "Point",
    "coordinates": [
      79.287875,
      21.57904
    ]
  },
  "type": "Feature",
  "properties": {
    "hierarchy": [
      "tgn:7581280",
      "tgn:1000004",
      "tgn:7000198",
      "tgn:1001894",
      "tgn:7029392"
    ],
    "placetype": [
      "aat:300008347"
    ],
    "name:en": "Silāri",
    "id": 7581280
  }
}
