{
  "geometry": {
    "type": "Point",
    "coordinates": [
      -82.2333,
      36.0833
    ]
  },
  "type": "Feature",
  "properties": {
    "hierarchy": [
      "tgn:2124451",
      "tgn:1000001",
      "tgn:7012149",
      "tgn:2001519",
      "tgn:7007709",
      "tgn:7029392"
    ],
    "placetype": [
      "aat:300008699"
    ],
    "id": 2124451,
    "name:xx": "Aaron Branch"
  }
}
