{
  "geometry": {
    "type": "Point",
    "coordinates": [
      89.8728,
      26.292687
    ]
  },
  "type": "Feature",
  "properties": {
    "hierarchy": [
      "tgn:7566585",
      "tgn:1000004",
      "tgn:1001832",
      "tgn:7000198",
      "tgn:7029392"
    ],
    "placetype": [
      "aat:300008347"
    ],
    "name:en": "Petla Ujān",
    "id": 7566585
  }
}
