{
  "geometry": {
    "type": "Point",
    "coordinates": [
      -107.85,
      37.9833
    ]
  },
  "type": "Feature",
  "properties": {
    "hierarchy": [
      "tgn:2414172",
      "tgn:1000001",
      "tgn:7012149",
      "tgn:7007158",
      "tgn:2000248",
      "tgn:7029392"
    ],
    "placetype": [
      "aat:300008798"
    ],
    "id": 2414172,
    "name:xx": "Iron Mountain"
  }
}
