{
  "geometry": {
    "type": "Point",
    "coordinates": [
      13.0833,
      55.65
    ]
  },
  "type": "Feature",
  "properties": {
    "hierarchy": [
      "tgn:1062780",
      "tgn:1000003",
      "tgn:7024622",
      "tgn:1000097",
      "tgn:7029392"
    ],
    "placetype": [
      "aat:300008347"
    ],
    "id": 1062780,
    "name:xx": "Arlöv"
  }
}
