{
  "type": "FeatureCollection",
  "features": [
    {
      "geometry": {
        "type": "Point",
        "coordinates": [
          -103.416667,
          28.283333
        ]
      },
      "type": "Feature",
      "properties": {
        "hierarchy": [
          "tgn:7355970",
          "tgn:1001853",
          "tgn:1000001",
          "tgn:7005560",
          "tgn:7029392"
        ],
        "placetype": [
          "aat:300000241"
        ],
        "id": 7355970,
        "name:xx": "Hacienda Cerro Blanco"
      }
    },
    {
      "geometry": {
        "type": "Point",
        "coordinates": [
          -110.85,
          30.833333
        ]
      },
      "type": "Feature",
      "properties": {
        "hierarchy": [
          "tgn:7355971",
          "tgn:1001835",
          "tgn:1000001",
          "tgn:7005560",
          "tgn:7029392"
        ],
        "placetype": [
          "aat:300007783"
        ],
        "id": 7355971,
        "name:xx": "Cerro Blanco"
      }
    },
    {
      "geometry": {
        "type": "Point",
        "coordinates": [
          -102.366667,
          20.65
        ]
      },
      "type": "Feature",
      "properties": {
        "hierarchy": [
          "tgn:7355972",
          "tgn:7005586",
          "tgn:1000001",
          "tgn:7005560",
          "tgn:7029392"
        ],
        "placetype": [
          "aat:300000241"
        ],
        "id": 7355972,
        "name:xx": "Cerro Blanco"
      }
    },
    {
      "geometry": {
        "type": "Point",
        "coordinates": [
          -116.283333,
          32.55
        ]
      },
      "type": "Feature",
      "properties": {
        "hierarchy": [
          "tgn:7355973",
          "tgn:1001835",
          "tgn:1000001",
          "tgn:7005560",
          "tgn:7029392"
        ],
        "placetype": [
          "aat:300008347"
        ],
        "id": 7355973,
        "name:xx": "Cerro Blanco"
      }
    },
    {
      "geometry": {
        "type": "Point",
        "coordinates": [
          -104.666667,
          26.883333
        ]
      },
      "type": "Feature",
      "properties": {
        "hierarchy": [
          "tgn:7355974",
          "tgn:7005581",
          "tgn:1000001",
          "tgn:7005560",
          "tgn:7029392"
        ],
        "placetype": [
          "aat:300008347"
        ],
        "id": 7355974,
        "name:xx": "Cerro Blanco"
      }
    },
    {
      "geometry": {
        "type": "Point",
        "coordinates": [
          -104.25,
          25.35
        ]
      },
      "type": "Feature",
      "properties": {
        "hierarchy": [
          "tgn:7355975",
          "tgn:7005583",
          "tgn:1000001",
          "tgn:7005560",
          "tgn:7029392"
        ],
        "placetype": [
          "aat:300008347"
        ],
        "id": 7355975,
        "name:xx": "Cerro Blanco"
      }
    },
    {
      "geometry": {
        "type": "Point",
        "coordinates": [
          -104.616667,
          21.366667
        ]
      },
      "type": "Feature",
      "properties": {
        "hierarchy": [
          "tgn:7355976",
          "tgn:1000001",
          "tgn:1001906",
          "tgn:7005560",
          "tgn:7029392"
        ],
        "placetype": [
          "aat:300008347"
        ],
        "id": 7355976,
        "name:xx": "Cerro Blanco"
      }
    },
    {
      "geometry": {
        "type": "Point",
        "coordinates": [
          -100.75,
          20.683333
        ]
      },
      "type": "Feature",
      "properties": {
        "hierarchy": [
          "tgn:7355977",
          "tgn:7005584",
          "tgn:1000001",
          "tgn:7005560",
          "tgn:7029392"
        ],
        "placetype": [
          "aat:300008347"
        ],
        "id": 7355977,
        "name:xx": "Cerro Blanco"
      }
    },
    {
      "geometry": {
        "type": "Point",
        "coordinates": [
          -97.75,
          20.333333
        ]
      },
      "type": "Feature",
      "properties": {
        "hierarchy": [
          "tgn:7355979",
          "tgn:1000001",
          "tgn:7005592",
          "tgn:7005560",
          "tgn:7029392"
        ],
        "placetype": [
          "aat:300008347"
        ],
        "id": 7355979,
        "name:xx": "Cerro Azul"
      }
    }
  ]
}
