{
  "type": "FeatureCollection",
  "features": [
    {
      "geometry": {
        "type": "Point",
        "coordinates": [
          -89.7333,
          36.2667
        ]
      },
      "type": "Feature",
      "properties": {
        "hierarchy": [
          "tgn:2288780",
          "tgn:1000001",
          "tgn:7012149",
          "tgn:7007523",
          "tgn:7029392"
        ],
        "placetype": [
          "aat:300006075"
        ],
        "id": 2288780,
        "name:xx": "Ditch Number 25"
      }
    },
    {
      "geometry": {
        "type": "Point",
        "coordinates": [
          -89.9167,
          36.3167
        ]
      },
      "type": "Feature",
      "properties": {
        "hierarchy": [
          "tgn:2288781",
          "tgn:1000001",
          "tgn:7012149",
          "tgn:7007523",
          "tgn:7029392"
        ],
        "placetype": [
          "aat:300006075"
        ],
        "id": 2288781,
        "name:xx": "Ditch Number 251"
      }
    },
    {
      "geometry": {
        "type": "Point",
        "coordinates": [
          -89.8,
          36.45
        ]
      },
      "type": "Feature",
      "properties": {
        "hierarchy": [
          "tgn:2288782",
          "tgn:1000001",
          "tgn:7012149",
          "tgn:2001222",
          "tgn:7007523",
          "tgn:7029392"
        ],
        "placetype": [
          "aat:300006075"
        ],
        "id": 2288782,
        "name:xx": "Ditch Number 256"
      }
    },
    {
      "geometry": {
        "type": "Point",
        "coordinates": [
          -89.8667,
          36.3833
        ]
      },
      "type": "Feature",
      "properties": {
        "hierarchy": [
          "tgn:2288783",
          "tgn:1000001",
          "tgn:7012149",
          "tgn:7007523",
          "tgn:7029392"
        ],
        "placetype": [
          "aat:300006075"
        ],
        "id": 2288783,
        "name:xx": "Ditch Number 258"
      }
    },
    {
      "geometry": {
        "type": "Point",
        "coordinates": [
          -90.0333,
          36.1167
        ]
      },
      "type": "Feature",
      "properties": {
        "hierarchy": [
          "tgn:2288784",
          "tgn:1000001",
          "tgn:7012149",
          "tgn:2001197",
          "tgn:7007523",
          "tgn:7029392"
        ],
        "placetype": [
          "aat:300006075"
        ],
        "id": 2288784,
        "name:xx": "Ditch Number 259"
      }
    },
    {
      "geometry": {
        "type": "Point",
        "coordinates": [
          -93.6833,
          42.45
        ]
      },
      "type": "Feature",
      "properties": {
        "hierarchy": [
          "tgn:2288785",
          "tgn:1000001",
          "tgn:2000600",
          "tgn:7012149",
          "tgn:7007253",
          "tgn:7029392"
        ],
        "placetype": [
          "aat:300006075"
        ],
        "id": 2288785,
        "name:xx": "Ditch Number 265"
      }
    },
    {
      "geometry": {
        "type": "Point",
        "coordinates": [
          -93.6833,
          42.4
        ]
      },
      "type": "Feature",
      "properties": {
        "hierarchy": [
          "tgn:2288786",
          "tgn:1000001",
          "tgn:2000600",
          "tgn:7012149",
          "tgn:7007253",
          "tgn:7029392"
        ],
        "placetype": [
          "aat:300006075"
        ],
        "id": 2288786,
        "name:xx": "Ditch Number 266"
      }
    },
    {
      "geometry": {
        "type": "Point",
        "coordinates": [
          -90.05,
          36.1333
        ]
      },
      "type": "Feature",
      "properties": {
        "hierarchy": [
          "tgn:2288787",
          "tgn:1000001",
          "tgn:7012149",
          "tgn:2001197",
          "tgn:7007523",
          "tgn:7029392"
        ],
        "placetype": [
          "aat:300006075"
        ],
        "id": 2288787,
        "name:xx": "Ditch Number 27"
      }
    },
    {
      "geometry": {
        "type": "Point",
        "coordinates": [
          -94.45,
          42.2167
        ]
      },
      "type": "Feature",
      "properties": {
        "hierarchy": [
          "tgn:2288788",
          "tgn:1000001",
          "tgn:7012149",
          "tgn:7007253",
          "tgn:7029392"
        ],
        "placetype": [
          "aat:300006075"
        ],
        "id": 2288788,
        "name:xx": "Ditch Number 28"
      }
    },
    {
      "geometry": {
        "type": "Point",
        "coordinates": [
          -94.7667,
          43.45
        ]
      },
      "type": "Feature",
      "properties": {
        "hierarchy": [
          "tgn:2288789",
          "tgn:1000001",
          "tgn:2000592",
          "tgn:7012149",
          "tgn:7007253",
          "tgn:7029392"
        ],
        "placetype": [
          "aat:300006075"
        ],
        "id": 2288789,
        "name:xx": "Ditch Number 29"
      }
    }
  ]
}
