{
  "type": "FeatureCollection",
  "features": [
    {
      "geometry": {
        "type": "Point",
        "coordinates": [
          -71.2333,
          42.2833
        ]
      },
      "type": "Feature",
      "properties": {
        "hierarchy": [
          "tgn:2050190",
          "tgn:1000001",
          "tgn:1002724",
          "tgn:7012149",
          "tgn:7007517",
          "tgn:7029392"
        ],
        "placetype": [
          "aat:300008347"
        ],
        "id": 2050190,
        "name:xx": "Needham"
      }
    },
    {
      "geometry": {
        "type": "Point",
        "coordinates": [
          -71.2333,
          42.2833
        ]
      },
      "type": "Feature",
      "properties": {
        "hierarchy": [
          "tgn:2050192",
          "tgn:1000001",
          "tgn:1002724",
          "tgn:7012149",
          "tgn:2050190",
          "tgn:7007517",
          "tgn:7029392"
        ],
        "placetype": [
          "aat:300000745"
        ],
        "id": 2050192,
        "name:xx": "Needham Heights"
      }
    },
    {
      "geometry": {
        "type": "Point",
        "coordinates": [
          -70.9333,
          41.8167
        ]
      },
      "type": "Feature",
      "properties": {
        "hierarchy": [
          "tgn:2050193",
          "tgn:1000001",
          "tgn:7014423",
          "tgn:7012149",
          "tgn:7007517",
          "tgn:7029392"
        ],
        "placetype": [
          "aat:300008347"
        ],
        "id": 2050193,
        "name:xx": "Nelsons Shores"
      }
    },
    {
      "geometry": {
        "type": "Point",
        "coordinates": [
          -73.2333,
          42.6
        ]
      },
      "type": "Feature",
      "properties": {
        "hierarchy": [
          "tgn:2050194",
          "tgn:7013388",
          "tgn:1000001",
          "tgn:7012149",
          "tgn:7007517",
          "tgn:7029392"
        ],
        "placetype": [
          "aat:300008347"
        ],
        "id": 2050194,
        "name:xx": "New Ashford"
      }
    }
  ]
}
