{
  "geometry": {
    "type": "Point",
    "coordinates": [
      -62.6667,
      8.05
    ]
  },
  "type": "Feature",
  "properties": {
    "hierarchy": [
      "tgn:1025117",
      "tgn:1001843",
      "tgn:1000002",
      "tgn:1000059",
      "tgn:7029392"
    ],
    "placetype": [
      "aat:300008347"
    ],
    "id": 1025117,
    "name:xx": "El Pao"
  }
}
