{
  "geometry": {
    "type": "Point",
    "coordinates": [
      -124.0667,
      40.3333
    ]
  },
  "type": "Feature",
  "properties": {
    "hierarchy": [
      "tgn:2168526",
      "tgn:1000001",
      "tgn:7012149",
      "tgn:2000181",
      "tgn:7007157",
      "tgn:7029392"
    ],
    "placetype": [
      "aat:300008798"
    ],
    "id": 2168526,
    "name:xx": "Big Hill"
  }
}
