{
  "type": "FeatureCollection",
  "features": [
    {
      "geometry": {
        "type": "Point",
        "coordinates": [
          -2.45,
          54.55
        ]
      },
      "type": "Feature",
      "properties": {
        "hierarchy": [
          "tgn:7453900",
          "tgn:7002445",
          "tgn:1000003",
          "tgn:7008117",
          "tgn:7008591",
          "tgn:7029392"
        ],
        "placetype": [
          "aat:300008347"
        ],
        "name:en": "Coupland",
        "id": 7453900
      }
    },
    {
      "geometry": {
        "type": "Point",
        "coordinates": [
          -0.5,
          52.766667
        ]
      },
      "type": "Feature",
      "properties": {
        "hierarchy": [
          "tgn:7453903",
          "tgn:7002445",
          "tgn:1000003",
          "tgn:7008157",
          "tgn:7008591",
          "tgn:7029392"
        ],
        "placetype": [
          "aat:300008347"
        ],
        "name:en": "Counthorpe",
        "id": 7453903
      }
    },
    {
      "geometry": {
        "type": "Point",
        "coordinates": [
          -3.483333,
          50.7
        ]
      },
      "type": "Feature",
      "properties": {
        "hierarchy": [
          "tgn:7453905",
          "tgn:7002445",
          "tgn:1000003",
          "tgn:7012077",
          "tgn:7008591",
          "tgn:7029392"
        ],
        "placetype": [
          "aat:300008347"
        ],
        "name:en": "Countess Wear",
        "id": 7453905
      }
    },
    {
      "geometry": {
        "type": "Point",
        "coordinates": [
          -0.233333,
          52.766667
        ]
      },
      "type": "Feature",
      "properties": {
        "hierarchy": [
          "tgn:7453906",
          "tgn:7002445",
          "tgn:1000003",
          "tgn:7008157",
          "tgn:7008591",
          "tgn:7029392"
        ],
        "placetype": [
          "aat:300007783"
        ],
        "name:en": "Counter Drain Station",
        "id": 7453906
      }
    },
    {
      "geometry": {
        "type": "Point",
        "coordinates": [
          -1.533333,
          52.433333
        ]
      },
      "type": "Feature",
      "properties": {
        "hierarchy": [
          "tgn:7453908",
          "tgn:7019026",
          "tgn:7002445",
          "tgn:1000003",
          "tgn:7029506",
          "tgn:7008591",
          "tgn:7029392"
        ],
        "placetype": [
          "aat:300008347"
        ],
        "name:en": "Coundon",
        "id": 7453908
      }
    },
    {
      "geometry": {
        "type": "Point",
        "coordinates": [
          -2.65,
          52.633333
        ]
      },
      "type": "Feature",
      "properties": {
        "hierarchy": [
          "tgn:7453909",
          "tgn:7002445",
          "tgn:1000003",
          "tgn:7012034",
          "tgn:7008591",
          "tgn:7029392"
        ],
        "placetype": [
          "aat:300008347"
        ],
        "name:en": "Cound",
        "id": 7453909
      }
    }
  ]
}
