{
  "type": "FeatureCollection",
  "features": [
    {
      "geometry": {
        "type": "Point",
        "coordinates": [
          23.05,
          37.5
        ]
      },
      "type": "Feature",
      "properties": {
        "hierarchy": [
          "tgn:7231460",
          "tgn:7002739",
          "tgn:7017076",
          "tgn:1000003",
          "tgn:1000074",
          "tgn:7029392"
        ],
        "placetype": [
          "aat:300008347"
        ],
        "id": 7231460,
        "name:xx": "Mantzavraíika"
      }
    },
    {
      "geometry": {
        "type": "Point",
        "coordinates": [
          20.4,
          38.183333
        ]
      },
      "type": "Feature",
      "properties": {
        "hierarchy": [
          "tgn:7231461",
          "tgn:7011167",
          "tgn:7001338",
          "tgn:1000003",
          "tgn:1000074",
          "tgn:7029392"
        ],
        "placetype": [
          "aat:300008347"
        ],
        "id": 7231461,
        "name:xx": "Mantzavináta"
      }
    },
    {
      "geometry": {
        "type": "Point",
        "coordinates": [
          21.966667,
          37.266667
        ]
      },
      "type": "Feature",
      "properties": {
        "hierarchy": [
          "tgn:7231462",
          "tgn:7002735",
          "tgn:7017076",
          "tgn:1000003",
          "tgn:1000074",
          "tgn:7029392"
        ],
        "placetype": [
          "aat:300008347"
        ],
        "id": 7231462,
        "name:xx": "Mantzárion"
      }
    },
    {
      "geometry": {
        "type": "Point",
        "coordinates": [
          22.4,
          37.416667
        ]
      },
      "type": "Feature",
      "properties": {
        "hierarchy": [
          "tgn:7231463",
          "tgn:7002739",
          "tgn:7017076",
          "tgn:1000003",
          "tgn:1000074",
          "tgn:7029392"
        ],
        "placetype": [
          "aat:300008347"
        ],
        "id": 7231463,
        "name:xx": "Manthiréa"
      }
    },
    {
      "geometry": {
        "type": "Point",
        "coordinates": [
          25.283333,
          39.216667
        ]
      },
      "type": "Feature",
      "properties": {
        "hierarchy": [
          "tgn:7231464",
          "tgn:7011163",
          "tgn:7002674",
          "tgn:1000003",
          "tgn:1000074",
          "tgn:7029392"
        ],
        "placetype": [
          "aat:300386970"
        ],
        "id": 7231464,
        "name:xx": "Mánsel, Ífalos"
      }
    },
    {
      "geometry": {
        "type": "Point",
        "coordinates": [
          21.2,
          40.85
        ]
      },
      "type": "Feature",
      "properties": {
        "hierarchy": [
          "tgn:7231465",
          "tgn:7002724",
          "tgn:7002715",
          "tgn:1000003",
          "tgn:1000074",
          "tgn:7029392"
        ],
        "placetype": [
          "aat:300266640"
        ],
        "id": 7231465,
        "name:xx": "Mánou Rákhi"
      }
    },
    {
      "geometry": {
        "type": "Point",
        "coordinates": [
          24.6,
          36.766667
        ]
      },
      "type": "Feature",
      "properties": {
        "hierarchy": [
          "tgn:7231466",
          "tgn:7011270",
          "tgn:7002674",
          "tgn:1000003",
          "tgn:1000074",
          "tgn:7029392"
        ],
        "placetype": [
          "aat:300008791"
        ],
        "id": 7231466,
        "name:xx": "Manolás, Nisís"
      }
    },
    {
      "geometry": {
        "type": "Point",
        "coordinates": [
          23.433333,
          37.7
        ]
      },
      "type": "Feature",
      "properties": {
        "hierarchy": [
          "tgn:7231467",
          "tgn:7002681",
          "tgn:7001395",
          "tgn:1000003",
          "tgn:1000074",
          "tgn:7029392"
        ],
        "placetype": [
          "aat:300008850"
        ],
        "id": 7231467,
        "name:xx": "Manólis, Ákra"
      }
    },
    {
      "geometry": {
        "type": "Point",
        "coordinates": [
          23.85,
          35.466667
        ]
      },
      "type": "Feature",
      "properties": {
        "hierarchy": [
          "tgn:7231468",
          "tgn:7002690",
          "tgn:7012056",
          "tgn:1000003",
          "tgn:1000074",
          "tgn:7029392"
        ],
        "placetype": [
          "aat:300008347"
        ],
        "id": 7231468,
        "name:xx": "Manoliópoulon"
      }
    },
    {
      "geometry": {
        "type": "Point",
        "coordinates": [
          23.866667,
          38.383333
        ]
      },
      "type": "Feature",
      "properties": {
        "hierarchy": [
          "tgn:7231469",
          "tgn:7002681",
          "tgn:7001395",
          "tgn:1000003",
          "tgn:1000074",
          "tgn:7029392"
        ],
        "placetype": [
          "aat:300008850"
        ],
        "id": 7231469,
        "name:xx": "Manóli Míti, Ákra"
      }
    }
  ]
}
