{
  "geometry": {
    "type": "Point",
    "coordinates": [
      -74.6167,
      43.8667
    ]
  },
  "type": "Feature",
  "properties": {
    "hierarchy": [
      "tgn:2160122",
      "tgn:1000001",
      "tgn:7012149",
      "tgn:1002440",
      "tgn:7007568",
      "tgn:7029392"
    ],
    "placetype": [
      "aat:300008791"
    ],
    "id": 2160122,
    "name:xx": "Beecher Island"
  }
}
