{
  "geometry": {
    "type": "Point",
    "coordinates": [
      -106.2667,
      44.1333
    ]
  },
  "type": "Feature",
  "properties": {
    "hierarchy": [
      "tgn:2411108",
      "tgn:1000001",
      "tgn:7012149",
      "tgn:2002374",
      "tgn:7007923",
      "tgn:7029392"
    ],
    "placetype": [
      "aat:300266640"
    ],
    "id": 2411108,
    "name:xx": "Indian Creek Divide"
  }
}
