{
  "geometry": {
    "type": "Point",
    "coordinates": [
      -110.7667,
      44.4667
    ]
  },
  "type": "Feature",
  "properties": {
    "hierarchy": [
      "tgn:2489514",
      "tgn:1000001",
      "tgn:7012149",
      "tgn:2002384",
      "tgn:7007923",
      "tgn:7029392"
    ],
    "placetype": [
      "aat:300008706"
    ],
    "id": 2489514,
    "name:xx": "Mallard Creek"
  }
}
