{
  "geometry": {
    "type": "Point",
    "coordinates": [
      100.4833,
      14.05
    ]
  },
  "type": "Feature",
  "properties": {
    "hierarchy": [
      "tgn:1085620",
      "tgn:7005192",
      "tgn:1000004",
      "tgn:7000937",
      "tgn:1000142",
      "tgn:7029392"
    ],
    "placetype": [
      "aat:300008347"
    ],
    "id": 1085620,
    "name:xx": "Pathum Thani"
  }
}
