{
  "geometry": {
    "type": "Point",
    "coordinates": [
      34.893855,
      29.491056
    ]
  },
  "type": "Feature",
  "properties": {
    "hierarchy": [
      "tgn:7528968",
      "tgn:7001242",
      "tgn:7016833",
      "tgn:7001336",
      "tgn:7029392"
    ],
    "placetype": [
      "aat:300006207"
    ],
    "name:en": "Abār Ţābā",
    "id": 7528968
  }
}
