{
  "geometry": {
    "type": "Point",
    "coordinates": [
      -89.9167,
      29.9333
    ]
  },
  "type": "Feature",
  "properties": {
    "hierarchy": [
      "tgn:7022968",
      "tgn:1000001",
      "tgn:7012149",
      "tgn:7007256",
      "tgn:7029392"
    ],
    "placetype": [
      "aat:300006075"
    ],
    "id": 7022968,
    "name:xx": "Forty Arpent Canal"
  }
}
