{
  "geometry": {
    "type": "Point",
    "coordinates": [
      -166.4667,
      53.7167
    ]
  },
  "type": "Feature",
  "properties": {
    "hierarchy": [
      "tgn:2710745",
      "tgn:7030516",
      "tgn:7006450",
      "tgn:1000001",
      "tgn:7012149",
      "tgn:7029392"
    ],
    "placetype": [
      "aat:300132316"
    ],
    "id": 2710745,
    "name:xx": "Tanaskan Bay"
  }
}
