{
  "geometry": {
    "type": "Point",
    "coordinates": [
      -88.8833,
      44.15
    ]
  },
  "type": "Feature",
  "properties": {
    "hierarchy": [
      "tgn:2122572",
      "tgn:1000001",
      "tgn:7012149",
      "tgn:2002362",
      "tgn:7007922",
      "tgn:7029392"
    ],
    "placetype": [
      "aat:300008347"
    ],
    "id": 2122572,
    "name:xx": "Tustin"
  }
}
