{
  "geometry": {
    "type": "Point",
    "coordinates": [
      -90.6167,
      36.9333
    ]
  },
  "type": "Feature",
  "properties": {
    "hierarchy": [
      "tgn:2739239",
      "tgn:1000001",
      "tgn:7012149",
      "tgn:2001255",
      "tgn:7007523",
      "tgn:7029392"
    ],
    "placetype": [
      "aat:300006191"
    ],
    "id": 2739239,
    "name:xx": "Upalika Pond"
  }
}
