{
  "geometry": {
    "type": "Point",
    "coordinates": [
      -88.25,
      39.3667
    ]
  },
  "type": "Feature",
  "properties": {
    "hierarchy": [
      "tgn:2342228",
      "tgn:1000001",
      "tgn:7012149",
      "tgn:7007251",
      "tgn:7029392"
    ],
    "placetype": [
      "aat:300008699"
    ],
    "id": 2342228,
    "name:xx": "Fulfer Branch"
  }
}
