{
  "geometry": {
    "type": "Point",
    "coordinates": [
      -106.3333,
      36.0167
    ]
  },
  "type": "Feature",
  "properties": {
    "hierarchy": [
      "tgn:2607088",
      "tgn:1000001",
      "tgn:7012149",
      "tgn:2001449",
      "tgn:7007566",
      "tgn:7029392"
    ],
    "placetype": [
      "aat:300008761"
    ],
    "id": 2607088,
    "name:xx": "Ranchos, Cañoncito de los"
  }
}
