{
  "geometry": {
    "type": "Point",
    "coordinates": [
      -91.0833,
      39.5167
    ]
  },
  "type": "Feature",
  "properties": {
    "hierarchy": [
      "tgn:7023586",
      "tgn:1000001",
      "tgn:7012149",
      "tgn:7029392"
    ],
    "placetype": [
      "aat:300008791"
    ],
    "id": 7023586,
    "name:xx": "North Fritz Island"
  }
}
