{
  "type": "FeatureCollection",
  "features": [
    {
      "geometry": {
        "type": "Point",
        "coordinates": [
          -83.7167,
          41.6
        ]
      },
      "type": "Feature",
      "properties": {
        "hierarchy": [
          "tgn:2082010",
          "tgn:1000001",
          "tgn:7012149",
          "tgn:1002611",
          "tgn:7007706",
          "tgn:7029392"
        ],
        "placetype": [
          "aat:300008347"
        ],
        "id": 2082010,
        "name:xx": "Spring Valley"
      }
    },
    {
      "geometry": {
        "type": "Point",
        "coordinates": [
          -84,
          39.6
        ]
      },
      "type": "Feature",
      "properties": {
        "hierarchy": [
          "tgn:2082011",
          "tgn:1000001",
          "tgn:7012149",
          "tgn:1002424",
          "tgn:7007706",
          "tgn:7029392"
        ],
        "placetype": [
          "aat:300008347"
        ],
        "id": 2082011,
        "name:xx": "Spring Valley"
      }
    },
    {
      "geometry": {
        "type": "Point",
        "coordinates": [
          -82.0167,
          40.7333
        ]
      },
      "type": "Feature",
      "properties": {
        "hierarchy": [
          "tgn:2082012",
          "tgn:1000001",
          "tgn:7012149",
          "tgn:1003007",
          "tgn:7007706",
          "tgn:7029392"
        ],
        "placetype": [
          "aat:300008347"
        ],
        "id": 2082012,
        "name:xx": "Springville"
      }
    },
    {
      "geometry": {
        "type": "Point",
        "coordinates": [
          -83.3833,
          41
        ]
      },
      "type": "Feature",
      "properties": {
        "hierarchy": [
          "tgn:2082013",
          "tgn:1000001",
          "tgn:7012149",
          "tgn:1002883",
          "tgn:7007706",
          "tgn:7029392"
        ],
        "placetype": [
          "aat:300008347"
        ],
        "id": 2082013,
        "name:xx": "Springville"
      }
    },
    {
      "geometry": {
        "type": "Point",
        "coordinates": [
          -83.3667,
          38.6833
        ]
      },
      "type": "Feature",
      "properties": {
        "hierarchy": [
          "tgn:2082015",
          "tgn:1002136",
          "tgn:1000001",
          "tgn:7012149",
          "tgn:7007706",
          "tgn:7029392"
        ],
        "placetype": [
          "aat:300008347"
        ],
        "id": 2082015,
        "name:xx": "Squirrel Town"
      }
    },
    {
      "geometry": {
        "type": "Point",
        "coordinates": [
          -81.2667,
          39.7
        ]
      },
      "type": "Feature",
      "properties": {
        "hierarchy": [
          "tgn:2082016",
          "tgn:1000001",
          "tgn:7012149",
          "tgn:2001617",
          "tgn:7007706",
          "tgn:7029392"
        ],
        "placetype": [
          "aat:300008347"
        ],
        "id": 2082016,
        "name:xx": "Stafford"
      }
    },
    {
      "geometry": {
        "type": "Point",
        "coordinates": [
          -82.7,
          41.2167
        ]
      },
      "type": "Feature",
      "properties": {
        "hierarchy": [
          "tgn:2082017",
          "tgn:1000001",
          "tgn:7012149",
          "tgn:1002497",
          "tgn:7007706",
          "tgn:7029392"
        ],
        "placetype": [
          "aat:300008347",
          "aat:300387210"
        ],
        "id": 2082017,
        "name:xx": "Standardsburg"
      }
    },
    {
      "geometry": {
        "type": "Point",
        "coordinates": [
          -84.2167,
          41.2667
        ]
      },
      "type": "Feature",
      "properties": {
        "hierarchy": [
          "tgn:2082018",
          "tgn:1000001",
          "tgn:7012149",
          "tgn:1002470",
          "tgn:7007706",
          "tgn:7029392"
        ],
        "placetype": [
          "aat:300008347"
        ],
        "id": 2082018,
        "name:xx": "Standley"
      }
    },
    {
      "geometry": {
        "type": "Point",
        "coordinates": [
          -81.4,
          39.4667
        ]
      },
      "type": "Feature",
      "properties": {
        "hierarchy": [
          "tgn:2082019",
          "tgn:1000001",
          "tgn:7012149",
          "tgn:2001622",
          "tgn:7007706",
          "tgn:7029392"
        ],
        "placetype": [
          "aat:300008347"
        ],
        "id": 2082019,
        "name:xx": "Stanleyville"
      }
    }
  ]
}
