{
  "geometry": {
    "type": "Point",
    "coordinates": [
      -99.3833,
      37.8167
    ]
  },
  "type": "Feature",
  "properties": {
    "hierarchy": [
      "tgn:2393075",
      "tgn:1000001",
      "tgn:2000683",
      "tgn:7012149",
      "tgn:7007254",
      "tgn:7029392"
    ],
    "placetype": [
      "aat:300008347"
    ],
    "id": 2393075,
    "name:xx": "Hodges"
  }
}
