{
  "geometry": {
    "type": "Point",
    "coordinates": [
      33.3333,
      35.3333
    ]
  },
  "type": "Feature",
  "properties": {
    "hierarchy": [
      "tgn:7002364",
      "tgn:1000004",
      "tgn:1000113",
      "tgn:7029392"
    ],
    "placetype": [
      "aat:300387064",
      "aat:300387081"
    ],
    "id": 7002364,
    "name:xx": "Lefkoşa"
  }
}
