{
  "geometry": {
    "type": "Point",
    "coordinates": [
      -106.6333,
      38.6333
    ]
  },
  "type": "Feature",
  "properties": {
    "hierarchy": [
      "tgn:2306025",
      "tgn:1000001",
      "tgn:7012149",
      "tgn:2000217",
      "tgn:7007158",
      "tgn:7029392"
    ],
    "placetype": [
      "aat:300008706"
    ],
    "id": 2306025,
    "name:xx": "East Fork Alder Creek"
  }
}
