{
  "geometry": {
    "type": "Point",
    "coordinates": [
      -120.1833,
      39.05
    ]
  },
  "type": "Feature",
  "properties": {
    "hierarchy": [
      "tgn:2202113",
      "tgn:1000001",
      "tgn:7012149",
      "tgn:7007157",
      "tgn:1002791",
      "tgn:7029392"
    ],
    "placetype": [
      "aat:300008680"
    ],
    "id": 2202113,
    "name:xx": "Buck Lake"
  }
}
