{
  "geometry": {
    "type": "Point",
    "coordinates": [
      -81.85,
      32.85
    ]
  },
  "type": "Feature",
  "properties": {
    "hierarchy": [
      "tgn:2510109",
      "tgn:1000001",
      "tgn:7012149",
      "tgn:2000373",
      "tgn:7007248",
      "tgn:7029392"
    ],
    "placetype": [
      "aat:300008699"
    ],
    "id": 2510109,
    "name:xx": "Middle Pond"
  }
}
