{
  "geometry": {
    "type": "Point",
    "coordinates": [
      -88.6667,
      45.75
    ]
  },
  "type": "Feature",
  "properties": {
    "hierarchy": [
      "tgn:2677095",
      "tgn:1000001",
      "tgn:7012149",
      "tgn:7007922",
      "tgn:7029392"
    ],
    "placetype": [
      "aat:300008707"
    ],
    "id": 2677095,
    "name:xx": "South Branch Popple River"
  }
}
