{
  "geometry": {
    "type": "Point",
    "coordinates": [
      -76.1833,
      43.5333
    ]
  },
  "type": "Feature",
  "properties": {
    "hierarchy": [
      "tgn:2278111",
      "tgn:1000001",
      "tgn:7012149",
      "tgn:1002758",
      "tgn:7007568",
      "tgn:7029392"
    ],
    "placetype": [
      "aat:300008347"
    ],
    "id": 2278111,
    "name:xx": "Daysville Corner"
  }
}
