{
  "type": "FeatureCollection",
  "features": [
    {
      "geometry": {
        "type": "Point",
        "coordinates": [
          -73.6,
          -37.366667
        ]
      },
      "type": "Feature",
      "properties": {
        "hierarchy": [
          "tgn:7283730",
          "tgn:1001637",
          "tgn:1000049",
          "tgn:1000002",
          "tgn:7029392"
        ],
        "placetype": [
          "aat:300266554",
          "aat:300008699"
        ],
        "id": 7283730,
        "name:xx": "Paillacahue, Río"
      }
    },
    {
      "geometry": {
        "type": "Point",
        "coordinates": [
          -71.766667,
          -34.266667
        ]
      },
      "type": "Feature",
      "properties": {
        "hierarchy": [
          "tgn:7283731",
          "tgn:1001695",
          "tgn:1000049",
          "tgn:1000002",
          "tgn:7029392"
        ],
        "placetype": [
          "aat:300000206"
        ],
        "id": 7283731,
        "name:xx": "Pailimo Chico"
      }
    },
    {
      "geometry": {
        "type": "Point",
        "coordinates": [
          -71.816667,
          -34.2
        ]
      },
      "type": "Feature",
      "properties": {
        "hierarchy": [
          "tgn:7283732",
          "tgn:1001695",
          "tgn:1000049",
          "tgn:1000002",
          "tgn:7029392"
        ],
        "placetype": [
          "aat:300008699"
        ],
        "id": 7283732,
        "name:xx": "Pailimo, Estero"
      }
    },
    {
      "geometry": {
        "type": "Point",
        "coordinates": [
          -71.766667,
          -34.3
        ]
      },
      "type": "Feature",
      "properties": {
        "hierarchy": [
          "tgn:7283733",
          "tgn:1001695",
          "tgn:1000049",
          "tgn:1000002",
          "tgn:7029392"
        ],
        "placetype": [
          "aat:300006191"
        ],
        "id": 7283733,
        "name:xx": "Embalse Pailimo"
      }
    },
    {
      "geometry": {
        "type": "Point",
        "coordinates": [
          -71.766667,
          -34.35
        ]
      },
      "type": "Feature",
      "properties": {
        "hierarchy": [
          "tgn:7283734",
          "tgn:1001695",
          "tgn:1000049",
          "tgn:1000002",
          "tgn:7029392"
        ],
        "placetype": [
          "aat:300387200"
        ],
        "id": 7283734,
        "name:xx": "Pailimo"
      }
    },
    {
      "geometry": {
        "type": "Point",
        "coordinates": [
          -71.8,
          -34.216667
        ]
      },
      "type": "Feature",
      "properties": {
        "hierarchy": [
          "tgn:7283735",
          "tgn:1001695",
          "tgn:1000049",
          "tgn:1000002",
          "tgn:7029392"
        ],
        "placetype": [
          "aat:300000206"
        ],
        "id": 7283735,
        "name:xx": "Pailimo"
      }
    },
    {
      "geometry": {
        "type": "Point",
        "coordinates": [
          -71.6,
          -38.916667
        ]
      },
      "type": "Feature",
      "properties": {
        "hierarchy": [
          "tgn:7283737",
          "tgn:1001692",
          "tgn:1000049",
          "tgn:1000002",
          "tgn:7029392"
        ],
        "placetype": [
          "aat:300008795"
        ],
        "id": 7283737,
        "name:xx": "Pailepaile, Cerros"
      }
    },
    {
      "geometry": {
        "type": "Point",
        "coordinates": [
          -73.609167,
          -42.836389
        ]
      },
      "type": "Feature",
      "properties": {
        "hierarchy": [
          "tgn:7283738",
          "tgn:1001699",
          "tgn:1000049",
          "tgn:1000002",
          "tgn:7029392"
        ],
        "placetype": [
          "aat:300008676"
        ],
        "id": 7283738,
        "name:xx": "Paildad, Estero"
      }
    },
    {
      "geometry": {
        "type": "Point",
        "coordinates": [
          -73.62,
          -42.850278
        ]
      },
      "type": "Feature",
      "properties": {
        "hierarchy": [
          "tgn:7283739",
          "tgn:1001699",
          "tgn:1000049",
          "tgn:1000002",
          "tgn:7029392"
        ],
        "placetype": [
          "aat:300008347"
        ],
        "id": 7283739,
        "name:xx": "Paildad"
      }
    }
  ]
}
