{
  "geometry": {
    "type": "Point",
    "coordinates": [
      98.5667,
      18.1167
    ]
  },
  "type": "Feature",
  "properties": {
    "hierarchy": [
      "tgn:1085537",
      "tgn:7000915",
      "tgn:7005194",
      "tgn:1000004",
      "tgn:1000142",
      "tgn:7029392"
    ],
    "placetype": [
      "aat:300008347"
    ],
    "id": 1085537,
    "name:xx": "Hot"
  }
}
