{
  "geometry": {
    "type": "Point",
    "coordinates": [
      -115.6167,
      33.0333
    ]
  },
  "type": "Feature",
  "properties": {
    "hierarchy": [
      "tgn:2014924",
      "tgn:1000001",
      "tgn:7012149",
      "tgn:2000182",
      "tgn:7007157",
      "tgn:7029392"
    ],
    "placetype": [
      "aat:300008347"
    ],
    "id": 2014924,
    "name:xx": "Westmorland"
  }
}
