{
  "type": "FeatureCollection",
  "features": [
    {
      "geometry": {
        "type": "Point",
        "coordinates": [
          -46.66,
          -20.133
        ]
      },
      "type": "Feature",
      "properties": {
        "hierarchy": [
          "tgn:7031980",
          "tgn:7006237",
          "tgn:1000047",
          "tgn:7002457",
          "tgn:1000002",
          "tgn:7029392"
        ],
        "placetype": [
          "aat:300008347"
        ],
        "id": 7031980,
        "name:xx": "Serra da Canastra"
      }
    },
    {
      "geometry": {
        "type": "Point",
        "coordinates": [
          -43.288,
          -22.95
        ]
      },
      "type": "Feature",
      "properties": {
        "hierarchy": [
          "tgn:7031981",
          "tgn:1001942",
          "tgn:1000047",
          "tgn:7002457",
          "tgn:1000002",
          "tgn:7029392"
        ],
        "placetype": [
          "aat:300008189"
        ],
        "id": 7031981,
        "name:xx": "Tijuca, Parque Nacional da"
      }
    },
    {
      "geometry": {
        "type": "Point",
        "coordinates": [
          -55.491,
          2.166
        ]
      },
      "type": "Feature",
      "properties": {
        "hierarchy": [
          "tgn:7031982",
          "tgn:7006247",
          "tgn:1000047",
          "tgn:7002456",
          "tgn:1000002",
          "tgn:7029392"
        ],
        "placetype": [
          "aat:300008865"
        ],
        "id": 7031982,
        "name:xx": "Tumucumaque, Reserva Florestal"
      }
    },
    {
      "geometry": {
        "type": "Point",
        "coordinates": [
          -54,
          -12
        ]
      },
      "type": "Feature",
      "properties": {
        "hierarchy": [
          "tgn:7031983",
          "tgn:7006260",
          "tgn:7002454",
          "tgn:1000047",
          "tgn:1000002",
          "tgn:7029392"
        ],
        "placetype": [
          "aat:300008189"
        ],
        "id": 7031983,
        "name:xx": "Xingu, Parque Nacional do"
      }
    },
    {
      "geometry": {
        "type": "Point",
        "coordinates": [
          -68.508,
          -13.166
        ]
      },
      "type": "Feature",
      "properties": {
        "hierarchy": [
          "tgn:7031984",
          "tgn:1000662",
          "tgn:1000046",
          "tgn:1000002",
          "tgn:7029392"
        ],
        "placetype": [
          "aat:300008189"
        ],
        "id": 7031984,
        "name:xx": "Madidi, Parque Nacional"
      }
    }
  ]
}
