{
  "geometry": {
    "type": "Point",
    "coordinates": [
      31.013906,
      31.199115
    ]
  },
  "type": "Feature",
  "properties": {
    "hierarchy": [
      "tgn:7530718",
      "tgn:7001242",
      "tgn:7016833",
      "tgn:1001335",
      "tgn:7029392"
    ],
    "placetype": [
      "aat:300006075"
    ],
    "name:en": "Tir'at al Muḩīţ",
    "id": 7530718
  }
}
