{
  "geometry": {
    "type": "Point",
    "coordinates": [
      -86.2167,
      40.1833
    ]
  },
  "type": "Feature",
  "properties": {
    "hierarchy": [
      "tgn:2572854",
      "tgn:1000001",
      "tgn:7012149",
      "tgn:1002439",
      "tgn:7007252",
      "tgn:7029392"
    ],
    "placetype": [
      "aat:300006075"
    ],
    "id": 2572854,
    "name:xx": "Pearce Ditch"
  }
}
