{
  "type": "FeatureCollection",
  "features": [
    {
      "geometry": {
        "type": "Point",
        "coordinates": [
          -85,
          35.1333
        ]
      },
      "type": "Feature",
      "properties": {
        "hierarchy": [
          "tgn:2563450",
          "tgn:1000001",
          "tgn:2001842",
          "tgn:7012149",
          "tgn:7007825",
          "tgn:7029392"
        ],
        "placetype": [
          "aat:300008761"
        ],
        "id": 2563450,
        "name:xx": "Owl Hollow"
      }
    },
    {
      "geometry": {
        "type": "Point",
        "coordinates": [
          -86.2,
          35.2
        ]
      },
      "type": "Feature",
      "properties": {
        "hierarchy": [
          "tgn:2563451",
          "tgn:1000001",
          "tgn:7012149",
          "tgn:2001862",
          "tgn:7007825",
          "tgn:7029392"
        ],
        "placetype": [
          "aat:300008761"
        ],
        "id": 2563451,
        "name:xx": "Owl Hollow"
      }
    },
    {
      "geometry": {
        "type": "Point",
        "coordinates": [
          -85.5333,
          35.2
        ]
      },
      "type": "Feature",
      "properties": {
        "hierarchy": [
          "tgn:2563452",
          "tgn:1000001",
          "tgn:7012149",
          "tgn:2001894",
          "tgn:7007825",
          "tgn:7029392"
        ],
        "placetype": [
          "aat:300008761"
        ],
        "id": 2563452,
        "name:xx": "Owl Hollow"
      }
    },
    {
      "geometry": {
        "type": "Point",
        "coordinates": [
          -87.5167,
          35.2833
        ]
      },
      "type": "Feature",
      "properties": {
        "hierarchy": [
          "tgn:2563453",
          "tgn:1000001",
          "tgn:7012149",
          "tgn:2001886",
          "tgn:7007825",
          "tgn:7029392"
        ],
        "placetype": [
          "aat:300008761"
        ],
        "id": 2563453,
        "name:xx": "Owl Hollow"
      }
    },
    {
      "geometry": {
        "type": "Point",
        "coordinates": [
          -88,
          35.35
        ]
      },
      "type": "Feature",
      "properties": {
        "hierarchy": [
          "tgn:2563454",
          "tgn:1000001",
          "tgn:7012149",
          "tgn:2001872",
          "tgn:7007825",
          "tgn:7029392"
        ],
        "placetype": [
          "aat:300008761"
        ],
        "id": 2563454,
        "name:xx": "Owl Hollow"
      }
    },
    {
      "geometry": {
        "type": "Point",
        "coordinates": [
          -87.5667,
          35.4167
        ]
      },
      "type": "Feature",
      "properties": {
        "hierarchy": [
          "tgn:2563455",
          "tgn:1000001",
          "tgn:7012149",
          "tgn:2001887",
          "tgn:7007825",
          "tgn:7029392"
        ],
        "placetype": [
          "aat:300008761"
        ],
        "id": 2563455,
        "name:xx": "Owl Hollow"
      }
    },
    {
      "geometry": {
        "type": "Point",
        "coordinates": [
          -87.9667,
          35.7
        ]
      },
      "type": "Feature",
      "properties": {
        "hierarchy": [
          "tgn:2563456",
          "tgn:1000001",
          "tgn:7012149",
          "tgn:2001904",
          "tgn:7007825",
          "tgn:7029392"
        ],
        "placetype": [
          "aat:300008761"
        ],
        "id": 2563456,
        "name:xx": "Owl Hollow"
      }
    },
    {
      "geometry": {
        "type": "Point",
        "coordinates": [
          -87.7,
          36.2833
        ]
      },
      "type": "Feature",
      "properties": {
        "hierarchy": [
          "tgn:2563457",
          "tgn:1000001",
          "tgn:7012149",
          "tgn:2001878",
          "tgn:7007825",
          "tgn:7029392"
        ],
        "placetype": [
          "aat:300008761"
        ],
        "id": 2563457,
        "name:xx": "Owl Hollow"
      }
    },
    {
      "geometry": {
        "type": "Point",
        "coordinates": [
          -83.4333,
          36.35
        ]
      },
      "type": "Feature",
      "properties": {
        "hierarchy": [
          "tgn:2563458",
          "tgn:1000001",
          "tgn:7012149",
          "tgn:2001865",
          "tgn:7007825",
          "tgn:7029392"
        ],
        "placetype": [
          "aat:300008761"
        ],
        "id": 2563458,
        "name:xx": "Owl Hollow"
      }
    },
    {
      "geometry": {
        "type": "Point",
        "coordinates": [
          -83.6,
          36.4
        ]
      },
      "type": "Feature",
      "properties": {
        "hierarchy": [
          "tgn:2563459",
          "tgn:1000001",
          "tgn:7012149",
          "tgn:2001849",
          "tgn:7007825",
          "tgn:7029392"
        ],
        "placetype": [
          "aat:300008761"
        ],
        "id": 2563459,
        "name:xx": "Owl Hollow"
      }
    }
  ]
}
