{
  "type": "FeatureCollection",
  "features": [
    {
      "geometry": {
        "type": "Point",
        "coordinates": [
          80.614402,
          22.770543
        ]
      },
      "type": "Feature",
      "properties": {
        "hierarchy": [
          "tgn:7555560",
          "tgn:1000004",
          "tgn:7000198",
          "tgn:1001894",
          "tgn:7029392"
        ],
        "placetype": [
          "aat:300008347"
        ],
        "name:en": "Mohgaon",
        "id": 7555560
      }
    },
    {
      "geometry": {
        "type": "Point",
        "coordinates": [
          81.121334,
          22.511761
        ]
      },
      "type": "Feature",
      "properties": {
        "hierarchy": [
          "tgn:7555561",
          "tgn:1000004",
          "tgn:7000198",
          "tgn:1001894",
          "tgn:7029392"
        ],
        "placetype": [
          "aat:300008347"
        ],
        "name:en": "Mohgaon",
        "id": 7555561
      }
    },
    {
      "geometry": {
        "type": "Point",
        "coordinates": [
          80.163694,
          22.268559
        ]
      },
      "type": "Feature",
      "properties": {
        "hierarchy": [
          "tgn:7555562",
          "tgn:1000004",
          "tgn:7000198",
          "tgn:1001894",
          "tgn:7029392"
        ],
        "placetype": [
          "aat:300008347"
        ],
        "name:en": "Mohgaon",
        "id": 7555562
      }
    },
    {
      "geometry": {
        "type": "Point",
        "coordinates": [
          80.678818,
          22.0554
        ]
      },
      "type": "Feature",
      "properties": {
        "hierarchy": [
          "tgn:7555563",
          "tgn:1000004",
          "tgn:7000198",
          "tgn:1001894",
          "tgn:7029392"
        ],
        "placetype": [
          "aat:300008347"
        ],
        "name:en": "Mohgaon",
        "id": 7555563
      }
    },
    {
      "geometry": {
        "type": "Point",
        "coordinates": [
          79.9,
          21.733333
        ]
      },
      "type": "Feature",
      "properties": {
        "hierarchy": [
          "tgn:7555564",
          "tgn:1000004",
          "tgn:7000198",
          "tgn:1001894",
          "tgn:7029392"
        ],
        "placetype": [
          "aat:300008347"
        ],
        "name:en": "Mohgaon",
        "id": 7555564
      }
    },
    {
      "geometry": {
        "type": "Point",
        "coordinates": [
          80.957111,
          21.707777
        ]
      },
      "type": "Feature",
      "properties": {
        "hierarchy": [
          "tgn:7555565",
          "tgn:1000004",
          "tgn:7031781",
          "tgn:7000198",
          "tgn:7029392"
        ],
        "placetype": [
          "aat:300008347"
        ],
        "name:en": "Mohgaon",
        "id": 7555565
      }
    },
    {
      "geometry": {
        "type": "Point",
        "coordinates": [
          78.736164,
          21.639467
        ]
      },
      "type": "Feature",
      "properties": {
        "hierarchy": [
          "tgn:7555566",
          "tgn:1000004",
          "tgn:7000198",
          "tgn:1001894",
          "tgn:7029392"
        ],
        "placetype": [
          "aat:300008347"
        ],
        "name:en": "Mohgaon",
        "id": 7555566
      }
    },
    {
      "geometry": {
        "type": "Point",
        "coordinates": [
          81.998333,
          20.666944
        ]
      },
      "type": "Feature",
      "properties": {
        "hierarchy": [
          "tgn:7555567",
          "tgn:1000004",
          "tgn:7031781",
          "tgn:7000198",
          "tgn:7029392"
        ],
        "placetype": [
          "aat:300008347"
        ],
        "name:en": "Mohera",
        "id": 7555567
      }
    },
    {
      "geometry": {
        "type": "Point",
        "coordinates": [
          77.444984,
          28.223385
        ]
      },
      "type": "Feature",
      "properties": {
        "hierarchy": [
          "tgn:7555568",
          "tgn:1000004",
          "tgn:1001871",
          "tgn:7000198",
          "tgn:7029392"
        ],
        "placetype": [
          "aat:300008347"
        ],
        "name:en": "Mohena",
        "id": 7555568
      }
    },
    {
      "geometry": {
        "type": "Point",
        "coordinates": [
          79.133333,
          18.4
        ]
      },
      "type": "Feature",
      "properties": {
        "hierarchy": [
          "tgn:7555569",
          "tgn:1001828",
          "tgn:1000004",
          "tgn:7000198",
          "tgn:7029392"
        ],
        "placetype": [
          "aat:300008699"
        ],
        "name:en": "Mohedamada River",
        "id": 7555569
      }
    }
  ]
}
