{
  "type": "FeatureCollection",
  "features": [
    {
      "geometry": {
        "type": "Point",
        "coordinates": [
          -77.9,
          34.0833
        ]
      },
      "type": "Feature",
      "properties": {
        "hierarchy": [
          "tgn:2470290",
          "tgn:1000001",
          "tgn:7012149",
          "tgn:2001523",
          "tgn:7007709",
          "tgn:7029392"
        ],
        "placetype": [
          "aat:300008706"
        ],
        "id": 2470290,
        "name:xx": "Lords Creek"
      }
    },
    {
      "geometry": {
        "type": "Point",
        "coordinates": [
          -75,
          41.4333
        ]
      },
      "type": "Feature",
      "properties": {
        "hierarchy": [
          "tgn:2470291",
          "tgn:1000001",
          "tgn:7012149",
          "tgn:1002789",
          "tgn:7007710",
          "tgn:7029392"
        ],
        "placetype": [
          "aat:300008706"
        ],
        "id": 2470291,
        "name:xx": "Lords Creek"
      }
    },
    {
      "geometry": {
        "type": "Point",
        "coordinates": [
          -72.3167,
          44.7
        ]
      },
      "type": "Feature",
      "properties": {
        "hierarchy": [
          "tgn:2470292",
          "tgn:1000001",
          "tgn:1002753",
          "tgn:7012149",
          "tgn:7007828",
          "tgn:7029392"
        ],
        "placetype": [
          "aat:300008706"
        ],
        "id": 2470292,
        "name:xx": "Lords Creek"
      }
    },
    {
      "geometry": {
        "type": "Point",
        "coordinates": [
          -118.1667,
          47.5333
        ]
      },
      "type": "Feature",
      "properties": {
        "hierarchy": [
          "tgn:2470293",
          "tgn:1000001",
          "tgn:7012149",
          "tgn:2002247",
          "tgn:7007920",
          "tgn:7029392"
        ],
        "placetype": [
          "aat:300008706"
        ],
        "id": 2470293,
        "name:xx": "Lords Creek"
      }
    },
    {
      "geometry": {
        "type": "Point",
        "coordinates": [
          -83.4833,
          42.1
        ]
      },
      "type": "Feature",
      "properties": {
        "hierarchy": [
          "tgn:2470294",
          "tgn:1000001",
          "tgn:7012149",
          "tgn:1003005",
          "tgn:7007520",
          "tgn:7029392"
        ],
        "placetype": [
          "aat:300008699"
        ],
        "id": 2470294,
        "name:xx": "Lords Drain"
      }
    },
    {
      "geometry": {
        "type": "Point",
        "coordinates": [
          -69.6167,
          44.95
        ]
      },
      "type": "Feature",
      "properties": {
        "hierarchy": [
          "tgn:2470295",
          "tgn:1000001",
          "tgn:7012149",
          "tgn:2000930",
          "tgn:7007515",
          "tgn:7029392"
        ],
        "placetype": [
          "aat:300008798"
        ],
        "id": 2470295,
        "name:xx": "Lords Hill"
      }
    },
    {
      "geometry": {
        "type": "Point",
        "coordinates": [
          -70.9,
          42.5833
        ]
      },
      "type": "Feature",
      "properties": {
        "hierarchy": [
          "tgn:2470296",
          "tgn:1000001",
          "tgn:1002359",
          "tgn:7012149",
          "tgn:7007517",
          "tgn:7029392"
        ],
        "placetype": [
          "aat:300008798"
        ],
        "id": 2470296,
        "name:xx": "Lords Hill"
      }
    },
    {
      "geometry": {
        "type": "Point",
        "coordinates": [
          -72.2,
          43.7167
        ]
      },
      "type": "Feature",
      "properties": {
        "hierarchy": [
          "tgn:2470297",
          "tgn:1000001",
          "tgn:2001424",
          "tgn:7012149",
          "tgn:7007564",
          "tgn:7029392"
        ],
        "placetype": [
          "aat:300008798"
        ],
        "id": 2470297,
        "name:xx": "Lords Hill"
      }
    },
    {
      "geometry": {
        "type": "Point",
        "coordinates": [
          -76.2167,
          42.9
        ]
      },
      "type": "Feature",
      "properties": {
        "hierarchy": [
          "tgn:2470298",
          "tgn:1000001",
          "tgn:7012149",
          "tgn:1002746",
          "tgn:7007568",
          "tgn:7029392"
        ],
        "placetype": [
          "aat:300008798"
        ],
        "id": 2470298,
        "name:xx": "Lords Hill"
      }
    },
    {
      "geometry": {
        "type": "Point",
        "coordinates": [
          -72.35,
          44.3
        ]
      },
      "type": "Feature",
      "properties": {
        "hierarchy": [
          "tgn:2470299",
          "tgn:1000001",
          "tgn:2002135",
          "tgn:7012149",
          "tgn:7007828",
          "tgn:7029392"
        ],
        "placetype": [
          "aat:300008798"
        ],
        "id": 2470299,
        "name:xx": "Lords Hill"
      }
    }
  ]
}
