{
  "geometry": {
    "type": "Point",
    "coordinates": [
      -8.683,
      39.2333
    ]
  },
  "type": "Feature",
  "properties": {
    "hierarchy": [
      "tgn:7011005",
      "tgn:1000003",
      "tgn:1000926",
      "tgn:1000090",
      "tgn:7029392"
    ],
    "placetype": [
      "aat:300008347",
      "aat:300008389",
      "aat:300387222"
    ],
    "id": 7011005,
    "name:xx": "Santarém"
  }
}
