{
  "geometry": {
    "type": "Point",
    "coordinates": [
      -61.15,
      14.8667
    ]
  },
  "type": "Feature",
  "properties": {
    "hierarchy": [
      "tgn:1012129",
      "tgn:7015035",
      "tgn:1000001",
      "tgn:7005870",
      "tgn:7029392"
    ],
    "placetype": [
      "aat:300386846"
    ],
    "id": 1012129,
    "name:xx": "Macouba, Pointe de"
  }
}
