{
  "geometry": {
    "type": "Point",
    "coordinates": [
      -83.5167,
      41.8333
    ]
  },
  "type": "Feature",
  "properties": {
    "hierarchy": [
      "tgn:2784450",
      "tgn:1000001",
      "tgn:7012149",
      "tgn:1002679",
      "tgn:7007520",
      "tgn:7029392"
    ],
    "placetype": [
      "aat:300006075"
    ],
    "id": 2784450,
    "name:xx": "Yarger Drain"
  }
}
