{
  "geometry": {
    "type": "Point",
    "coordinates": [
      -100.9167,
      32.7167
    ]
  },
  "type": "Feature",
  "properties": {
    "hierarchy": [
      "tgn:2107732",
      "tgn:1000001",
      "tgn:7012149",
      "tgn:2002071",
      "tgn:7007826",
      "tgn:7029392"
    ],
    "placetype": [
      "aat:300008347"
    ],
    "id": 2107732,
    "name:xx": "Snyder"
  }
}
