{
  "geometry": {
    "type": "Point",
    "coordinates": [
      -92.4333,
      36.8833
    ]
  },
  "type": "Feature",
  "properties": {
    "hierarchy": [
      "tgn:2258481",
      "tgn:1000001",
      "tgn:7012149",
      "tgn:2001196",
      "tgn:7007523",
      "tgn:7029392"
    ],
    "placetype": [
      "aat:300008761"
    ],
    "id": 2258481,
    "name:xx": "Cotton Patch Hollow"
  }
}
