{
  "geometry": {
    "type": "Point",
    "coordinates": [
      36.05,
      31.5833
    ]
  },
  "type": "Feature",
  "properties": {
    "hierarchy": [
      "tgn:1099879",
      "tgn:1002055",
      "tgn:1000004",
      "tgn:1000121",
      "tgn:7029392"
    ],
    "placetype": [
      "aat:300008347",
      "aat:300167671"
    ],
    "id": 1099879,
    "name:xx": "Qaṣr Ḍabʻah"
  }
}
