{
  "geometry": {
    "type": "Point",
    "coordinates": [
      76.7333,
      42.0833
    ]
  },
  "type": "Feature",
  "properties": {
    "hierarchy": [
      "tgn:1060344",
      "tgn:1000004",
      "tgn:7011479",
      "tgn:7006655",
      "tgn:7029392"
    ],
    "placetype": [
      "aat:300008347"
    ],
    "id": 1060344,
    "name:xx": "Toguzbulak"
  }
}
