{
  "geometry": {
    "type": "Point",
    "coordinates": [
      22.2833,
      43.2167
    ]
  },
  "type": "Feature",
  "properties": {
    "hierarchy": [
      "tgn:1064917",
      "tgn:1000003",
      "tgn:7006669",
      "tgn:7029392"
    ],
    "placetype": [
      "aat:300008347"
    ],
    "id": 1064917,
    "name:xx": "Bela Palanka"
  }
}
