{
  "geometry": {
    "type": "Point",
    "coordinates": [
      -72.2333,
      9.0667
    ]
  },
  "type": "Feature",
  "properties": {
    "hierarchy": [
      "tgn:1025134",
      "tgn:1001985",
      "tgn:1000002",
      "tgn:1000059",
      "tgn:7029392"
    ],
    "placetype": [
      "aat:300008347"
    ],
    "id": 1025134,
    "name:xx": "Encontrados"
  }
}
