{
  "geometry": {
    "type": "Point",
    "coordinates": [
      -8.85,
      42.55
    ]
  },
  "type": "Feature",
  "properties": {
    "hierarchy": [
      "tgn:7298726",
      "tgn:7002824",
      "tgn:1000003",
      "tgn:7002786",
      "tgn:1000095",
      "tgn:7029392"
    ],
    "placetype": [
      "aat:300386846"
    ],
    "id": 7298726,
    "name:xx": "Vado, Punta del"
  }
}
