{
  "geometry": {
    "type": "Point",
    "coordinates": [
      28.0333,
      -26.1167
    ]
  },
  "type": "Feature",
  "properties": {
    "hierarchy": [
      "tgn:1093544",
      "tgn:7001242",
      "tgn:7017576",
      "tgn:1000193",
      "tgn:7029392"
    ],
    "placetype": [
      "aat:300008347",
      "aat:300000879",
      "aat:300008375"
    ],
    "id": 1093544,
    "name:xx": "Randburg"
  }
}
