{
  "geometry": {
    "type": "Point",
    "coordinates": [
      -82.2167,
      39.15
    ]
  },
  "type": "Feature",
  "properties": {
    "hierarchy": [
      "tgn:2078744",
      "tgn:1000001",
      "tgn:7012149",
      "tgn:2001616",
      "tgn:7007706",
      "tgn:7029392"
    ],
    "placetype": [
      "aat:300008347"
    ],
    "id": 2078744,
    "name:xx": "Carpenter"
  }
}
