{
  "geometry": {
    "type": "Point",
    "coordinates": [
      -88.7167,
      34.2667
    ]
  },
  "type": "Feature",
  "properties": {
    "hierarchy": [
      "tgn:2554643",
      "tgn:1000001",
      "tgn:7012149",
      "tgn:2001126",
      "tgn:7007522",
      "tgn:7029392"
    ],
    "placetype": [
      "aat:300008347"
    ],
    "id": 2554643,
    "name:xx": "Oakridge"
  }
}
