{
  "geometry": {
    "type": "Point",
    "coordinates": [
      -121.6333,
      48.0833
    ]
  },
  "type": "Feature",
  "properties": {
    "hierarchy": [
      "tgn:2356575",
      "tgn:1000001",
      "tgn:7012149",
      "tgn:1002899",
      "tgn:7007920",
      "tgn:7029392"
    ],
    "placetype": [
      "aat:300266640"
    ],
    "id": 2356575,
    "name:xx": "Gordon Ridge"
  }
}
