{
  "geometry": {
    "type": "Point",
    "coordinates": [
      -89.5333,
      37.8167
    ]
  },
  "type": "Feature",
  "properties": {
    "hierarchy": [
      "tgn:2424564",
      "tgn:1000001",
      "tgn:7012149",
      "tgn:2000512",
      "tgn:7007251",
      "tgn:7029392"
    ],
    "placetype": [
      "aat:300008706"
    ],
    "id": 2424564,
    "name:xx": "Johnson Creek"
  }
}
