{
  "type": "FeatureCollection",
  "features": [
    {
      "geometry": {
        "type": "Point",
        "coordinates": [
          -47.75,
          -15.75
        ]
      },
      "type": "Feature",
      "properties": {
        "hierarchy": [
          "tgn:1000841",
          "tgn:7002454",
          "tgn:1000047",
          "tgn:1000002",
          "tgn:7029392"
        ],
        "placetype": [
          "aat:300387064",
          "aat:300387081"
        ],
        "id": 1000841,
        "name:xx": "Distrito Federal"
      }
    },
    {
      "geometry": {
        "type": "Point",
        "coordinates": [
          -66.9167,
          10.5
        ]
      },
      "type": "Feature",
      "properties": {
        "hierarchy": [
          "tgn:1000842",
          "tgn:1000002",
          "tgn:1000059",
          "tgn:7029392"
        ],
        "placetype": [
          "aat:300387064",
          "aat:300387081"
        ],
        "id": 1000842,
        "name:xx": "Distrito Capital"
      }
    },
    {
      "geometry": {
        "type": "Point",
        "coordinates": [
          152,
          6
        ]
      },
      "type": "Feature",
      "properties": {
        "hierarchy": [
          "tgn:1000846",
          "tgn:7006160",
          "tgn:1000006",
          "tgn:7029392"
        ],
        "placetype": [
          "aat:300387064",
          "aat:300000774"
        ],
        "id": 1000846,
        "name:xx": "East New Britain"
      }
    },
    {
      "geometry": {
        "type": "Point",
        "coordinates": [
          143.75,
          -4
        ]
      },
      "type": "Feature",
      "properties": {
        "hierarchy": [
          "tgn:1000847",
          "tgn:7006160",
          "tgn:1000006",
          "tgn:7029392"
        ],
        "placetype": [
          "aat:300387064",
          "aat:300000774"
        ],
        "id": 1000847,
        "name:xx": "East Sepik"
      }
    },
    {
      "geometry": {
        "type": "Point",
        "coordinates": [
          33.8333,
          1.4167
        ]
      },
      "type": "Feature",
      "properties": {
        "hierarchy": [
          "tgn:1000848",
          "tgn:7001242",
          "tgn:1000206",
          "tgn:7029392"
        ],
        "placetype": [
          "aat:300387064",
          "aat:300000774"
        ],
        "id": 1000848,
        "name:xx": "Eastern"
      }
    },
    {
      "geometry": {
        "type": "Point",
        "coordinates": [
          180,
          -18.5
        ]
      },
      "type": "Feature",
      "properties": {
        "hierarchy": [
          "tgn:1000849",
          "tgn:7000493",
          "tgn:1000006",
          "tgn:7029392"
        ],
        "placetype": [
          "aat:300387064",
          "aat:300387082"
        ],
        "id": 1000849,
        "name:xx": "Eastern Division"
      }
    }
  ]
}
