{
  "geometry": {
    "type": "Point",
    "coordinates": [
      -114.6333,
      56.15
    ]
  },
  "type": "Feature",
  "properties": {
    "hierarchy": [
      "tgn:1117412",
      "tgn:7005694",
      "tgn:7005685",
      "tgn:1000001",
      "tgn:7029392"
    ],
    "placetype": [
      "aat:300008680"
    ],
    "id": 1117412,
    "name:xx": "Muskwa Lake"
  }
}
