{
  "geometry": {
    "type": "Point",
    "coordinates": [
      -95.9167,
      37.4333
    ]
  },
  "type": "Feature",
  "properties": {
    "hierarchy": [
      "tgn:2036136",
      "tgn:1000001",
      "tgn:7012149",
      "tgn:2000762",
      "tgn:7007254",
      "tgn:7029392"
    ],
    "placetype": [
      "aat:300008347",
      "aat:300387210"
    ],
    "id": 2036136,
    "name:xx": "Buxton"
  }
}
