{
  "geometry": {
    "type": "Point",
    "coordinates": [
      -87.0833,
      40.4833
    ]
  },
  "type": "Feature",
  "properties": {
    "hierarchy": [
      "tgn:2033208",
      "tgn:1002177",
      "tgn:1000001",
      "tgn:7012149",
      "tgn:7007252",
      "tgn:7029392"
    ],
    "placetype": [
      "aat:300008347"
    ],
    "id": 2033208,
    "name:xx": "Otterbein"
  }
}
