{
  "geometry": {
    "type": "Point",
    "coordinates": [
      -98.9333,
      35.1667
    ]
  },
  "type": "Feature",
  "properties": {
    "hierarchy": [
      "tgn:2553497",
      "tgn:1000001",
      "tgn:7012149",
      "tgn:2001697",
      "tgn:7007707",
      "tgn:7029392"
    ],
    "placetype": [
      "aat:300008706"
    ],
    "id": 2553497,
    "name:xx": "Oak Creek"
  }
}
