{
  "geometry": {
    "type": "Point",
    "coordinates": [
      -114.1333,
      46.6833
    ]
  },
  "type": "Feature",
  "properties": {
    "hierarchy": [
      "tgn:2491313",
      "tgn:1000001",
      "tgn:7012149",
      "tgn:2001291",
      "tgn:7007524",
      "tgn:7029392"
    ],
    "placetype": [
      "aat:300008706"
    ],
    "id": 2491313,
    "name:xx": "Maple Creek"
  }
}
