{
  "geometry": {
    "type": "Point",
    "coordinates": [
      -75.5333,
      35.25
    ]
  },
  "type": "Feature",
  "properties": {
    "hierarchy": [
      "tgn:7020224",
      "tgn:1000001",
      "tgn:7012149",
      "tgn:2001488",
      "tgn:7007709",
      "tgn:7029392"
    ],
    "placetype": [
      "aat:300008905"
    ],
    "id": 7020224,
    "name:xx": "Jeanette Sedge"
  }
}
