{
  "geometry": {
    "type": "Point",
    "coordinates": [
      -83.85,
      33.3667
    ]
  },
  "type": "Feature",
  "properties": {
    "hierarchy": [
      "tgn:2588697",
      "tgn:1000001",
      "tgn:7012149",
      "tgn:2000398",
      "tgn:7007248",
      "tgn:7029392"
    ],
    "placetype": [
      "aat:300132316"
    ],
    "id": 2588697,
    "name:xx": "Plunkett Neck"
  }
}
