{
  "geometry": {
    "type": "Point",
    "coordinates": [
      -2.4667,
      47.5667
    ]
  },
  "type": "Feature",
  "properties": {
    "hierarchy": [
      "tgn:1034602",
      "tgn:1000003",
      "tgn:7012216",
      "tgn:1000070",
      "tgn:7029392"
    ],
    "placetype": [
      "aat:300008347"
    ],
    "id": 1034602,
    "name:xx": "Muzillac"
  }
}
