{
  "geometry": {
    "type": "Point",
    "coordinates": [
      23.723,
      38.03
    ]
  },
  "type": "Feature",
  "properties": {
    "hierarchy": [
      "tgn:1041939",
      "tgn:7002681",
      "tgn:7001395",
      "tgn:1000003",
      "tgn:1000074",
      "tgn:7029392"
    ],
    "placetype": [
      "aat:300008347"
    ],
    "id": 1041939,
    "name:xx": "Ágioi Anárgyroi"
  }
}
