{
  "geometry": {
    "type": "Point",
    "coordinates": [
      -104.0333,
      34.4833
    ]
  },
  "type": "Feature",
  "properties": {
    "hierarchy": [
      "tgn:2466941",
      "tgn:1000001",
      "tgn:7019560",
      "tgn:7012149",
      "tgn:7007566",
      "tgn:7029392"
    ],
    "placetype": [
      "aat:300008761"
    ],
    "id": 2466941,
    "name:xx": "Long Canyon"
  }
}
