{
  "geometry": {
    "type": "Point",
    "coordinates": [
      74.72039,
      28.259897
    ]
  },
  "type": "Feature",
  "properties": {
    "hierarchy": [
      "tgn:7568421",
      "tgn:1000004",
      "tgn:7000198",
      "tgn:7016788",
      "tgn:7029392"
    ],
    "placetype": [
      "aat:300008347"
    ],
    "name:en": "Jāsāsar",
    "id": 7568421
  }
}
