{
  "geometry": {
    "type": "Point",
    "coordinates": [
      114.9667,
      25.45
    ]
  },
  "type": "Feature",
  "properties": {
    "hierarchy": [
      "tgn:1139872",
      "tgn:1000004",
      "tgn:7002082",
      "tgn:1000111",
      "tgn:7029392"
    ],
    "placetype": [
      "aat:300008347"
    ],
    "id": 1139872,
    "name:xx": "Xinfeng"
  }
}
