{
  "geometry": {
    "type": "Point",
    "coordinates": [
      32.0925,
      31.027778
    ]
  },
  "type": "Feature",
  "properties": {
    "hierarchy": [
      "tgn:7525317",
      "tgn:7001242",
      "tgn:7016833",
      "tgn:1001123",
      "tgn:7029392"
    ],
    "placetype": [
      "aat:300008791"
    ],
    "id": 7525317,
    "name:xx": "Dâkhlet el-Ghâla"
  }
}
