{
  "geometry": {
    "type": "Point",
    "coordinates": [
      -91.2333,
      45.9167
    ]
  },
  "type": "Feature",
  "properties": {
    "hierarchy": [
      "tgn:2511678",
      "tgn:1000001",
      "tgn:7012149",
      "tgn:2002353",
      "tgn:7007922",
      "tgn:7029392"
    ],
    "placetype": [
      "aat:300008850"
    ],
    "id": 2511678,
    "name:xx": "Miles Point"
  }
}
