{
  "geometry": {
    "type": "Point",
    "coordinates": [
      -117.75,
      33.5167
    ]
  },
  "type": "Feature",
  "properties": {
    "hierarchy": [
      "tgn:2701986",
      "tgn:1000001",
      "tgn:7012149",
      "tgn:7007157",
      "tgn:1002748",
      "tgn:7029392"
    ],
    "placetype": [
      "aat:300008850"
    ],
    "id": 2701986,
    "name:xx": "Sugarloaf Point"
  }
}
