{
  "geometry": {
    "type": "Point",
    "coordinates": [
      -93.35,
      37.8833
    ]
  },
  "type": "Feature",
  "properties": {
    "hierarchy": [
      "tgn:2058854",
      "tgn:1000001",
      "tgn:7012149",
      "tgn:2001203",
      "tgn:7007523",
      "tgn:7029392"
    ],
    "placetype": [
      "aat:300008347"
    ],
    "id": 2058854,
    "name:xx": "Galmey"
  }
}
