{
  "geometry": {
    "type": "Point",
    "coordinates": [
      81.95,
      55.2167
    ]
  },
  "type": "Feature",
  "properties": {
    "hierarchy": [
      "tgn:1138040",
      "tgn:1000004",
      "tgn:7011589",
      "tgn:7018214",
      "tgn:7002435",
      "tgn:7029392"
    ],
    "placetype": [
      "aat:300008347"
    ],
    "id": 1138040,
    "name:xx": "Novomichajlovka"
  }
}
