{
  "geometry": {
    "type": "Point",
    "coordinates": [
      -114.0167,
      34.4167
    ]
  },
  "type": "Feature",
  "properties": {
    "hierarchy": [
      "tgn:2519635",
      "tgn:1000001",
      "tgn:7006451",
      "tgn:7012149",
      "tgn:2000098",
      "tgn:7029392"
    ],
    "placetype": [
      "aat:300006191"
    ],
    "id": 2519635,
    "name:xx": "Mohave Tank"
  }
}
