{
  "geometry": {
    "type": "Point",
    "coordinates": [
      42.3167,
      8.1667
    ]
  },
  "type": "Feature",
  "properties": {
    "hierarchy": [
      "tgn:1089805",
      "tgn:7001242",
      "tgn:1001286",
      "tgn:7000489",
      "tgn:7029392"
    ],
    "placetype": [
      "aat:300008347"
    ],
    "id": 1089805,
    "name:xx": "Fik'"
  }
}
