{
  "geometry": {
    "type": "Point",
    "coordinates": [
      -106.8333,
      42.9167
    ]
  },
  "type": "Feature",
  "properties": {
    "hierarchy": [
      "tgn:2181207",
      "tgn:1000001",
      "tgn:7012149",
      "tgn:2002377",
      "tgn:7007923",
      "tgn:7029392"
    ],
    "placetype": [
      "aat:300008761"
    ],
    "id": 2181207,
    "name:xx": "Blue Canyon"
  }
}
