{
  "geometry": {
    "type": "Point",
    "coordinates": [
      -82.5833,
      35.7333
    ]
  },
  "type": "Feature",
  "properties": {
    "hierarchy": [
      "tgn:2658495",
      "tgn:1000001",
      "tgn:2001473",
      "tgn:7012149",
      "tgn:7007709",
      "tgn:7029392"
    ],
    "placetype": [
      "aat:300008699"
    ],
    "id": 2658495,
    "name:xx": "Sheppard Branch"
  }
}
