{
  "geometry": {
    "type": "Point",
    "coordinates": [
      -106.5333,
      39.5333
    ]
  },
  "type": "Feature",
  "properties": {
    "hierarchy": [
      "tgn:2785780",
      "tgn:1000001",
      "tgn:7012149",
      "tgn:2000210",
      "tgn:7007158",
      "tgn:7029392"
    ],
    "placetype": [
      "aat:300008706"
    ],
    "id": 2785780,
    "name:xx": "York Creek"
  }
}
