{
  "geometry": {
    "type": "Point",
    "coordinates": [
      -98.5333,
      32.9333
    ]
  },
  "type": "Feature",
  "properties": {
    "hierarchy": [
      "tgn:2579285",
      "tgn:1000001",
      "tgn:7012149",
      "tgn:7007826",
      "tgn:7029392"
    ],
    "placetype": [
      "aat:300008706"
    ],
    "id": 2579285,
    "name:xx": "Pickard Creek"
  }
}
