{
  "geometry": {
    "type": "Point",
    "coordinates": [
      46.0667,
      40.5333
    ]
  },
  "type": "Feature",
  "properties": {
    "hierarchy": [
      "tgn:1052144",
      "tgn:7011438",
      "tgn:1000004",
      "tgn:7006646",
      "tgn:7029392"
    ],
    "placetype": [
      "aat:300008347"
    ],
    "id": 1052144,
    "name:xx": "Alunitdag"
  }
}
