{
  "geometry": {
    "type": "Point",
    "coordinates": [
      120.2088,
      23.3417
    ]
  },
  "type": "Feature",
  "properties": {
    "hierarchy": [
      "tgn:7486563",
      "tgn:7468018",
      "tgn:1000004",
      "tgn:1000141",
      "tgn:7029392"
    ],
    "placetype": [
      "aat:300008347"
    ],
    "id": 7486563,
    "name:xx": "Kanglanggang"
  }
}
