{
  "geometry": {
    "type": "Point",
    "coordinates": [
      -121.1667,
      48.0333
    ]
  },
  "type": "Feature",
  "properties": {
    "hierarchy": [
      "tgn:2594098",
      "tgn:1000001",
      "tgn:7012149",
      "tgn:1002899",
      "tgn:7007920",
      "tgn:7029392"
    ],
    "placetype": [
      "aat:300008798"
    ],
    "id": 2594098,
    "name:xx": "Portal Peak"
  }
}
