{
  "geometry": {
    "type": "Point",
    "coordinates": [
      -72.5833,
      -49.5833
    ]
  },
  "type": "Feature",
  "properties": {
    "hierarchy": [
      "tgn:1118580",
      "tgn:7006477",
      "tgn:1001522",
      "tgn:1000002",
      "tgn:7029392"
    ],
    "placetype": [
      "aat:300008680"
    ],
    "id": 1118580,
    "name:xx": "Viedma, Lago"
  }
}
