{
  "geometry": {
    "type": "Point",
    "coordinates": [
      -76.5833,
      35.1333
    ]
  },
  "type": "Feature",
  "properties": {
    "hierarchy": [
      "tgn:2200750",
      "tgn:1000001",
      "tgn:7012149",
      "tgn:2001526",
      "tgn:7007709",
      "tgn:7029392"
    ],
    "placetype": [
      "aat:300008706"
    ],
    "id": 2200750,
    "name:xx": "Bryan Creek"
  }
}
