{
  "geometry": {
    "type": "Point",
    "coordinates": [
      -83.6167,
      35.4833
    ]
  },
  "type": "Feature",
  "properties": {
    "hierarchy": [
      "tgn:2759253",
      "tgn:1000001",
      "tgn:7012149",
      "tgn:2001543",
      "tgn:7007709",
      "tgn:7029392"
    ],
    "placetype": [
      "aat:300008706"
    ],
    "id": 2759253,
    "name:xx": "West Fork Chambers Creek"
  }
}
