{
  "geometry": {
    "type": "Point",
    "coordinates": [
      37.9667,
      54.5667
    ]
  },
  "type": "Feature",
  "properties": {
    "hierarchy": [
      "tgn:1057091",
      "tgn:1000004",
      "tgn:1003418",
      "tgn:7018214",
      "tgn:7002435",
      "tgn:7029392"
    ],
    "placetype": [
      "aat:300008347"
    ],
    "id": 1057091,
    "name:xx": "Mokryy Kor"
  }
}
