{
  "geometry": {
    "type": "Point",
    "coordinates": [
      -108.0833,
      46.3667
    ]
  },
  "type": "Feature",
  "properties": {
    "hierarchy": [
      "tgn:2328250",
      "tgn:1000001",
      "tgn:7012149",
      "tgn:2001292",
      "tgn:7007524",
      "tgn:7029392"
    ],
    "placetype": [
      "aat:300008706"
    ],
    "id": 2328250,
    "name:xx": "Fishel Creek"
  }
}
