{
  "geometry": {
    "type": "Point",
    "coordinates": [
      -116.55,
      31.75
    ]
  },
  "type": "Feature",
  "properties": {
    "hierarchy": [
      "tgn:7430131",
      "tgn:1001835",
      "tgn:1000001",
      "tgn:7005560",
      "tgn:7029392"
    ],
    "placetype": [
      "aat:300008347"
    ],
    "id": 7430131,
    "name:xx": "Tres Palmas"
  }
}
