{
  "geometry": {
    "type": "Point",
    "coordinates": [
      -105.3667,
      33.5333
    ]
  },
  "type": "Feature",
  "properties": {
    "hierarchy": [
      "tgn:2233999",
      "tgn:1000001",
      "tgn:7012149",
      "tgn:2001442",
      "tgn:7007566",
      "tgn:7029392"
    ],
    "placetype": [
      "aat:300008761"
    ],
    "id": 2233999,
    "name:xx": "Chavez Canyon"
  }
}
