{
  "geometry": {
    "type": "Point",
    "coordinates": [
      -115.55,
      45.4333
    ]
  },
  "type": "Feature",
  "properties": {
    "hierarchy": [
      "tgn:2519200",
      "tgn:1000001",
      "tgn:7012149",
      "tgn:2000476",
      "tgn:7007250",
      "tgn:7029392"
    ],
    "placetype": [
      "aat:300008706"
    ],
    "id": 2519200,
    "name:xx": "Moccasin Creek"
  }
}
