{
  "type": "FeatureCollection",
  "features": [
    {
      "geometry": {
        "type": "Point",
        "coordinates": [
          30.566667,
          25.166667
        ]
      },
      "type": "Feature",
      "properties": {
        "hierarchy": [
          "tgn:7522590",
          "tgn:7001242",
          "tgn:7016833",
          "tgn:7001334",
          "tgn:7029392"
        ],
        "placetype": [
          "aat:300008697"
        ],
        "name:en": "Dhakar, 'Ayn adh",
        "id": 7522590
      }
    },
    {
      "geometry": {
        "type": "Point",
        "coordinates": [
          29.016667,
          30.783333
        ]
      },
      "type": "Feature",
      "properties": {
        "hierarchy": [
          "tgn:7522591",
          "tgn:7001242",
          "tgn:7016833",
          "tgn:1001418",
          "tgn:7029392"
        ],
        "placetype": [
          "aat:300008777"
        ],
        "name:en": "Dhakar, 'Alam adh",
        "id": 7522591
      }
    },
    {
      "geometry": {
        "type": "Point",
        "coordinates": [
          32,
          31.2
        ]
      },
      "type": "Feature",
      "properties": {
        "hierarchy": [
          "tgn:7522592",
          "tgn:7001242",
          "tgn:7016833",
          "tgn:1001123",
          "tgn:7029392"
        ],
        "placetype": [
          "aat:300008777"
        ],
        "id": 7522592,
        "name:xx": "Dhahā'ibah, Tall adh"
      }
    },
    {
      "geometry": {
        "type": "Point",
        "coordinates": [
          31.648875,
          30.978402
        ]
      },
      "type": "Feature",
      "properties": {
        "hierarchy": [
          "tgn:7522593",
          "tgn:7001242",
          "tgn:1001059",
          "tgn:7016833",
          "tgn:7029392"
        ],
        "placetype": [
          "aat:300008777"
        ],
        "id": 7522593,
        "name:xx": "Dhahab, Tall adh"
      }
    },
    {
      "geometry": {
        "type": "Point",
        "coordinates": [
          33.226821,
          22.334466
        ]
      },
      "type": "Feature",
      "properties": {
        "hierarchy": [
          "tgn:7522594",
          "tgn:7001242",
          "tgn:7001311",
          "tgn:7016833",
          "tgn:7029392"
        ],
        "placetype": [
          "aat:300379998"
        ],
        "name:en": "Dhahab, Rawḑ adh",
        "id": 7522594
      }
    },
    {
      "geometry": {
        "type": "Point",
        "coordinates": [
          30.438202,
          27.470895
        ]
      },
      "type": "Feature",
      "properties": {
        "hierarchy": [
          "tgn:7522595",
          "tgn:7001242",
          "tgn:7016833",
          "tgn:7001334",
          "tgn:7029392"
        ],
        "placetype": [
          "aat:300008777"
        ],
        "name:en": "Dhahab, Qārat adh",
        "id": 7522595
      }
    },
    {
      "geometry": {
        "type": "Point",
        "coordinates": [
          30.327222,
          30.967778
        ]
      },
      "type": "Feature",
      "properties": {
        "hierarchy": [
          "tgn:7522596",
          "tgn:7001242",
          "tgn:1001075",
          "tgn:7016833",
          "tgn:7029392"
        ],
        "placetype": [
          "aat:300008777"
        ],
        "name:en": "Dhahab, Kawm adh",
        "id": 7522596
      }
    },
    {
      "geometry": {
        "type": "Point",
        "coordinates": [
          30.553333,
          31.205833
        ]
      },
      "type": "Feature",
      "properties": {
        "hierarchy": [
          "tgn:7522597",
          "tgn:7001242",
          "tgn:7016833",
          "tgn:1001335",
          "tgn:7029392"
        ],
        "placetype": [
          "aat:300008791"
        ],
        "name:en": "Dhahab, Jazīrat adh",
        "id": 7522597
      }
    },
    {
      "geometry": {
        "type": "Point",
        "coordinates": [
          31.216667,
          29.983333
        ]
      },
      "type": "Feature",
      "properties": {
        "hierarchy": [
          "tgn:7522598",
          "tgn:7001242",
          "tgn:7016833",
          "tgn:1001083",
          "tgn:7029392"
        ],
        "placetype": [
          "aat:300008791"
        ],
        "name:en": "Dhahab, Jazīrat adh",
        "id": 7522598
      }
    },
    {
      "geometry": {
        "type": "Point",
        "coordinates": [
          30.15,
          31.233333
        ]
      },
      "type": "Feature",
      "properties": {
        "hierarchy": [
          "tgn:7522599",
          "tgn:7001242",
          "tgn:1001075",
          "tgn:7016833",
          "tgn:7029392"
        ],
        "placetype": [
          "aat:300266559"
        ],
        "name:en": "Dhahab, Bāb adh",
        "id": 7522599
      }
    }
  ]
}
