{
  "geometry": {
    "type": "Point",
    "coordinates": [
      127.3333,
      40.8667
    ]
  },
  "type": "Feature",
  "properties": {
    "hierarchy": [
      "tgn:1081985",
      "tgn:1001196",
      "tgn:1000004",
      "tgn:1000122",
      "tgn:7029392"
    ],
    "placetype": [
      "aat:300008347"
    ],
    "id": 1081985,
    "name:xx": "Chunggang-ni"
  }
}
