{
  "geometry": {
    "type": "Point",
    "coordinates": [
      -76.75,
      40.7833
    ]
  },
  "type": "Feature",
  "properties": {
    "hierarchy": [
      "tgn:2373017",
      "tgn:1000001",
      "tgn:7012149",
      "tgn:1002732",
      "tgn:7007710",
      "tgn:7029392"
    ],
    "placetype": [
      "aat:300008699"
    ],
    "id": 2373017,
    "name:xx": "Hallowing Run"
  }
}
