{
  "geometry": {
    "type": "Point",
    "coordinates": [
      -82.0333,
      38.0833
    ]
  },
  "type": "Feature",
  "properties": {
    "hierarchy": [
      "tgn:2595212",
      "tgn:1000001",
      "tgn:7012149",
      "tgn:2002272",
      "tgn:7013961",
      "tgn:7029392"
    ],
    "placetype": [
      "aat:300008699"
    ],
    "id": 2595212,
    "name:xx": "Pot Fork"
  }
}
