{
  "geometry": {
    "type": "Point",
    "coordinates": [
      -98.55,
      30.6667
    ]
  },
  "type": "Feature",
  "properties": {
    "hierarchy": [
      "tgn:2626207",
      "tgn:1000001",
      "tgn:7012149",
      "tgn:2002030",
      "tgn:7007826",
      "tgn:7029392"
    ],
    "placetype": [
      "aat:300008706"
    ],
    "id": 2626207,
    "name:xx": "Rocky Creek"
  }
}
