{
  "type": "FeatureCollection",
  "features": [
    {
      "geometry": {
        "type": "Point",
        "coordinates": [
          42.3,
          39
        ]
      },
      "type": "Feature",
      "properties": {
        "hierarchy": [
          "tgn:1116541",
          "tgn:1001437",
          "tgn:1000004",
          "tgn:7018455",
          "tgn:1000144",
          "tgn:7029392"
        ],
        "placetype": [
          "aat:300008680"
        ],
        "id": 1116541,
        "name:xx": "Hacli Golu"
      }
    },
    {
      "geometry": {
        "type": "Point",
        "coordinates": [
          25.35,
          65.166667
        ]
      },
      "type": "Feature",
      "properties": {
        "hierarchy": [
          "tgn:1116542",
          "tgn:7594392",
          "tgn:1000003",
          "tgn:1000069",
          "tgn:7029392"
        ],
        "placetype": [
          "aat:300008680"
        ],
        "id": 1116542,
        "name:xx": "Haapajärvi"
      }
    },
    {
      "geometry": {
        "type": "Point",
        "coordinates": [
          -121.5,
          51.8333
        ]
      },
      "type": "Feature",
      "properties": {
        "hierarchy": [
          "tgn:1116543",
          "tgn:7005735",
          "tgn:7005685",
          "tgn:1000001",
          "tgn:7029392"
        ],
        "placetype": [
          "aat:300008680"
        ],
        "id": 1116543,
        "name:xx": "Hache, Lac la"
      }
    },
    {
      "geometry": {
        "type": "Point",
        "coordinates": [
          -98.4167,
          55.0667
        ]
      },
      "type": "Feature",
      "properties": {
        "hierarchy": [
          "tgn:1116547",
          "tgn:7005685",
          "tgn:1000001",
          "tgn:7005734",
          "tgn:7029392"
        ],
        "placetype": [
          "aat:300008680"
        ],
        "id": 1116547,
        "name:xx": "Halfway Lake"
      }
    },
    {
      "geometry": {
        "type": "Point",
        "coordinates": [
          -78.4,
          45.2
        ]
      },
      "type": "Feature",
      "properties": {
        "hierarchy": [
          "tgn:1116548",
          "tgn:7005685",
          "tgn:1000001",
          "tgn:7013154",
          "tgn:7029392"
        ],
        "placetype": [
          "aat:300008680"
        ],
        "id": 1116548,
        "name:xx": "Haliburton Lake"
      }
    },
    {
      "geometry": {
        "type": "Point",
        "coordinates": [
          -82.3333,
          68.6667
        ]
      },
      "type": "Feature",
      "properties": {
        "hierarchy": [
          "tgn:1116549",
          "tgn:7005685",
          "tgn:1000001",
          "tgn:7024197",
          "tgn:7029392"
        ],
        "placetype": [
          "aat:300008680"
        ],
        "id": 1116549,
        "name:xx": "Hall Lake"
      }
    }
  ]
}
