{
  "geometry": {
    "type": "Point",
    "coordinates": [
      7.833333,
      53.65
    ]
  },
  "type": "Feature",
  "properties": {
    "hierarchy": [
      "tgn:7147224",
      "tgn:1000003",
      "tgn:7003676",
      "tgn:7000084",
      "tgn:7029392"
    ],
    "placetype": [
      "aat:300000206"
    ],
    "id": 7147224,
    "name:xx": "Klein Münchhausen"
  }
}
