{
  "geometry": {
    "type": "Point",
    "coordinates": [
      -80.6333,
      38.5667
    ]
  },
  "type": "Feature",
  "properties": {
    "hierarchy": [
      "tgn:2487931",
      "tgn:1000001",
      "tgn:2002256",
      "tgn:7012149",
      "tgn:7013961",
      "tgn:7029392"
    ],
    "placetype": [
      "aat:300008706"
    ],
    "id": 2487931,
    "name:xx": "Left Fork Wolf Creek"
  }
}
