{
  "geometry": {
    "type": "Point",
    "coordinates": [
      -148.3167,
      70.4833
    ]
  },
  "type": "Feature",
  "properties": {
    "hierarchy": [
      "tgn:2614532",
      "tgn:7006450",
      "tgn:1000001",
      "tgn:7012149",
      "tgn:2124005",
      "tgn:7029392"
    ],
    "placetype": [
      "aat:300008791"
    ],
    "id": 2614532,
    "name:xx": "Reindeer Island"
  }
}
