{
  "type": "FeatureCollection",
  "features": [
    {
      "geometry": {
        "type": "Point",
        "coordinates": [
          -120.1167,
          39.0333
        ]
      },
      "type": "Feature",
      "properties": {
        "hierarchy": [
          "tgn:2012650",
          "tgn:1000001",
          "tgn:7012149",
          "tgn:1002350",
          "tgn:7007157",
          "tgn:7029392"
        ],
        "placetype": [
          "aat:300008347"
        ],
        "id": 2012650,
        "name:xx": "Meeks Bay"
      }
    },
    {
      "geometry": {
        "type": "Point",
        "coordinates": [
          -123.6333,
          39.2833
        ]
      },
      "type": "Feature",
      "properties": {
        "hierarchy": [
          "tgn:2012653",
          "tgn:1000001",
          "tgn:7012149",
          "tgn:7007157",
          "tgn:2000185",
          "tgn:7029392"
        ],
        "placetype": [
          "aat:300008347",
          "aat:300387210"
        ],
        "id": 2012653,
        "name:xx": "Melbourne"
      }
    },
    {
      "geometry": {
        "type": "Point",
        "coordinates": [
          -120.75,
          38.35
        ]
      },
      "type": "Feature",
      "properties": {
        "hierarchy": [
          "tgn:2012654",
          "tgn:1002146",
          "tgn:1000001",
          "tgn:7012149",
          "tgn:7007157",
          "tgn:7029392"
        ],
        "placetype": [
          "aat:300008347"
        ],
        "id": 2012654,
        "name:xx": "Bonnefoy"
      }
    },
    {
      "geometry": {
        "type": "Point",
        "coordinates": [
          -115.4333,
          32.8
        ]
      },
      "type": "Feature",
      "properties": {
        "hierarchy": [
          "tgn:2012655",
          "tgn:1000001",
          "tgn:7012149",
          "tgn:2000182",
          "tgn:7007157",
          "tgn:7029392"
        ],
        "placetype": [
          "aat:300008347",
          "aat:300387210"
        ],
        "id": 2012655,
        "name:xx": "Meloland"
      }
    },
    {
      "geometry": {
        "type": "Point",
        "coordinates": [
          -120.7,
          38.6
        ]
      },
      "type": "Feature",
      "properties": {
        "hierarchy": [
          "tgn:2012656",
          "tgn:1000001",
          "tgn:7012149",
          "tgn:1002350",
          "tgn:7007157",
          "tgn:7029392"
        ],
        "placetype": [
          "aat:300008347",
          "aat:300387210"
        ],
        "id": 2012656,
        "name:xx": "Melsons Corner"
      }
    },
    {
      "geometry": {
        "type": "Point",
        "coordinates": [
          -120.3667,
          36.75
        ]
      },
      "type": "Feature",
      "properties": {
        "hierarchy": [
          "tgn:2012659",
          "tgn:1000001",
          "tgn:7012149",
          "tgn:1002392",
          "tgn:7007157",
          "tgn:7029392"
        ],
        "placetype": [
          "aat:300008347"
        ],
        "id": 2012659,
        "name:xx": "Mendota"
      }
    }
  ]
}
