{
  "geometry": {
    "type": "Point",
    "coordinates": [
      -74.8667,
      44.0167
    ]
  },
  "type": "Feature",
  "properties": {
    "hierarchy": [
      "tgn:2454865",
      "tgn:1000001",
      "tgn:7012149",
      "tgn:1002472",
      "tgn:7007568",
      "tgn:7029392"
    ],
    "placetype": [
      "aat:300008680"
    ],
    "id": 2454865,
    "name:xx": "Little Duck Pond"
  }
}
