{
  "geometry": {
    "type": "Point",
    "coordinates": [
      79.807,
      27.1424
    ]
  },
  "type": "Feature",
  "properties": {
    "hierarchy": [
      "tgn:7562463",
      "tgn:1000004",
      "tgn:7000198",
      "tgn:7016722",
      "tgn:7029392"
    ],
    "placetype": [
      "aat:300008347"
    ],
    "name:en": "Tārāpur",
    "id": 7562463
  }
}
