{
  "geometry": {
    "type": "Point",
    "coordinates": [
      -80.2833,
      40.3333
    ]
  },
  "type": "Feature",
  "properties": {
    "hierarchy": [
      "tgn:1133869",
      "tgn:1000001",
      "tgn:7012149",
      "tgn:7007710",
      "tgn:7029392"
    ],
    "placetype": [
      "aat:300008706"
    ],
    "id": 1133869,
    "name:xx": "Millers Run"
  }
}
