{
  "geometry": {
    "type": "Point",
    "coordinates": [
      -78.6833,
      41.8833
    ]
  },
  "type": "Feature",
  "properties": {
    "hierarchy": [
      "tgn:2439638",
      "tgn:1000001",
      "tgn:7012149",
      "tgn:7016020",
      "tgn:7007710",
      "tgn:7029392"
    ],
    "placetype": [
      "aat:300008699"
    ],
    "id": 2439638,
    "name:xx": "Kissem Run"
  }
}
