{
  "geometry": {
    "type": "Point",
    "coordinates": [
      26.1167,
      3.5667
    ]
  },
  "type": "Feature",
  "properties": {
    "hierarchy": [
      "tgn:1088782",
      "tgn:7001242",
      "tgn:7016755",
      "tgn:1000159",
      "tgn:7029392"
    ],
    "placetype": [
      "aat:300008347"
    ],
    "id": 1088782,
    "name:xx": "Bambili"
  }
}
