{
  "geometry": {
    "type": "Point",
    "coordinates": [
      18.1667,
      60.3667
    ]
  },
  "type": "Feature",
  "properties": {
    "hierarchy": [
      "tgn:1062981",
      "tgn:1000003",
      "tgn:1000462",
      "tgn:1000097",
      "tgn:7029392"
    ],
    "placetype": [
      "aat:300008347"
    ],
    "id": 1062981,
    "name:xx": "Forsmark"
  }
}
