{
  "geometry": {
    "type": "Point",
    "coordinates": [
      -87.15,
      40.35
    ]
  },
  "type": "Feature",
  "properties": {
    "hierarchy": [
      "tgn:2146981",
      "tgn:1000001",
      "tgn:7012149",
      "tgn:1002983",
      "tgn:7007252",
      "tgn:7029392"
    ],
    "placetype": [
      "aat:300008347"
    ],
    "id": 2146981,
    "name:xx": "Banning Corner"
  }
}
