{
  "geometry": {
    "type": "Point",
    "coordinates": [
      29.8333,
      50.9833
    ]
  },
  "type": "Feature",
  "properties": {
    "hierarchy": [
      "tgn:1054456",
      "tgn:1000003",
      "tgn:7011661",
      "tgn:7006660",
      "tgn:7029392"
    ],
    "placetype": [
      "aat:300008347"
    ],
    "id": 1054456,
    "name:xx": "Ivankov"
  }
}
