{
  "type": "FeatureCollection",
  "features": [
    {
      "geometry": {
        "type": "Point",
        "coordinates": [
          13.733333,
          43.033333
        ]
      },
      "type": "Feature",
      "properties": {
        "hierarchy": [
          "tgn:4007421",
          "tgn:1003432",
          "tgn:1000003",
          "tgn:7003240",
          "tgn:1000080",
          "tgn:7029392"
        ],
        "placetype": [
          "aat:300008347"
        ],
        "id": 4007421,
        "name:xx": "Montefiore dell'Aso"
      }
    },
    {
      "geometry": {
        "type": "Point",
        "coordinates": [
          12.933333,
          43.533333
        ]
      },
      "type": "Feature",
      "properties": {
        "hierarchy": [
          "tgn:4007422",
          "tgn:1003429",
          "tgn:1000003",
          "tgn:7003240",
          "tgn:1000080",
          "tgn:7029392"
        ],
        "placetype": [
          "aat:300008347"
        ],
        "id": 4007422,
        "name:xx": "Montefortino"
      }
    },
    {
      "geometry": {
        "type": "Point",
        "coordinates": [
          10.35,
          43.916667
        ]
      },
      "type": "Feature",
      "properties": {
        "hierarchy": [
          "tgn:4007428",
          "tgn:7003165",
          "tgn:1000003",
          "tgn:7009760",
          "tgn:1000080",
          "tgn:7029392"
        ],
        "placetype": [
          "aat:300008347"
        ],
        "id": 4007428,
        "name:xx": "Montemagno"
      }
    }
  ]
}
