{
  "geometry": {
    "type": "Point",
    "coordinates": [
      117.2167,
      41.15
    ]
  },
  "type": "Feature",
  "properties": {
    "hierarchy": [
      "tgn:1072841",
      "tgn:1000004",
      "tgn:7002077",
      "tgn:1000111",
      "tgn:7029392"
    ],
    "placetype": [
      "aat:300008347"
    ],
    "id": 1072841,
    "name:xx": "Xiaohuying"
  }
}
