{
  "geometry": {
    "type": "Point",
    "coordinates": [
      -159.1333,
      61.6667
    ]
  },
  "type": "Feature",
  "properties": {
    "hierarchy": [
      "tgn:2246401",
      "tgn:7006450",
      "tgn:2000069",
      "tgn:1000001",
      "tgn:7012149",
      "tgn:7029392"
    ],
    "placetype": [
      "aat:300008706"
    ],
    "id": 2246401,
    "name:xx": "Cobalt Creek"
  }
}
