{
  "geometry": {
    "type": "Point",
    "coordinates": [
      -116.7167,
      34.4833
    ]
  },
  "type": "Feature",
  "properties": {
    "hierarchy": [
      "tgn:2364309",
      "tgn:1000001",
      "tgn:7012149",
      "tgn:7007157",
      "tgn:1002857",
      "tgn:7029392"
    ],
    "placetype": [
      "aat:300000390"
    ],
    "id": 2364309,
    "name:xx": "Green Rock Mine"
  }
}
