{
  "geometry": {
    "type": "Point",
    "coordinates": [
      -83.6667,
      43.45
    ]
  },
  "type": "Feature",
  "properties": {
    "hierarchy": [
      "tgn:2647132",
      "tgn:1000001",
      "tgn:7012149",
      "tgn:2000997",
      "tgn:7007520",
      "tgn:7029392"
    ],
    "placetype": [
      "aat:300006075"
    ],
    "id": 2647132,
    "name:xx": "Schemn Drain"
  }
}
