{
  "geometry": {
    "type": "Point",
    "coordinates": [
      -91.8833,
      44.6833
    ]
  },
  "type": "Feature",
  "properties": {
    "hierarchy": [
      "tgn:2198125",
      "tgn:1000001",
      "tgn:2002319",
      "tgn:7012149",
      "tgn:7007922",
      "tgn:7029392"
    ],
    "placetype": [
      "aat:300132316"
    ],
    "id": 2198125,
    "name:xx": "Browning Lake"
  }
}
