{
  "geometry": {
    "type": "Point",
    "coordinates": [
      -78.6333,
      41.6833
    ]
  },
  "type": "Feature",
  "properties": {
    "hierarchy": [
      "tgn:2662110",
      "tgn:1000001",
      "tgn:7012149",
      "tgn:7016020",
      "tgn:7007710",
      "tgn:7029392"
    ],
    "placetype": [
      "aat:300008699"
    ],
    "id": 2662110,
    "name:xx": "Sicily Run"
  }
}
