{
  "geometry": {
    "type": "Point",
    "coordinates": [
      -88.2167,
      34.8833
    ]
  },
  "type": "Feature",
  "properties": {
    "hierarchy": [
      "tgn:2260288",
      "tgn:1000001",
      "tgn:7012149",
      "tgn:2001156",
      "tgn:7007522",
      "tgn:7029392"
    ],
    "placetype": [
      "aat:300008699"
    ],
    "id": 2260288,
    "name:xx": "Counts Branch"
  }
}
