{
  "geometry": {
    "type": "Point",
    "coordinates": [
      -47.8833,
      -24.7167
    ]
  },
  "type": "Feature",
  "properties": {
    "hierarchy": [
      "tgn:1022361",
      "tgn:1001945",
      "tgn:1000047",
      "tgn:7002457",
      "tgn:1000002",
      "tgn:7029392"
    ],
    "placetype": [
      "aat:300008347"
    ],
    "id": 1022361,
    "name:xx": "Pariquera-Açu"
  }
}
