{
  "geometry": {
    "type": "Point",
    "coordinates": [
      -123.3167,
      48.0167
    ]
  },
  "type": "Feature",
  "properties": {
    "hierarchy": [
      "tgn:2489430",
      "tgn:1000001",
      "tgn:1002271",
      "tgn:7012149",
      "tgn:7007920",
      "tgn:7029392"
    ],
    "placetype": [
      "aat:300008798"
    ],
    "id": 2489430,
    "name:xx": "Maletti Hill"
  }
}
