{
  "geometry": {
    "type": "Point",
    "coordinates": [
      -89.8167,
      36.4333
    ]
  },
  "type": "Feature",
  "properties": {
    "hierarchy": [
      "tgn:2288852",
      "tgn:1000001",
      "tgn:7012149",
      "tgn:2001222",
      "tgn:7007523",
      "tgn:7029392"
    ],
    "placetype": [
      "aat:300006075"
    ],
    "id": 2288852,
    "name:xx": "Ditch Number 57"
  }
}
