{
  "geometry": {
    "type": "Point",
    "coordinates": [
      -118.8667,
      37.45
    ]
  },
  "type": "Feature",
  "properties": {
    "hierarchy": [
      "tgn:2546832",
      "tgn:1000001",
      "tgn:7012149",
      "tgn:1002392",
      "tgn:7007157",
      "tgn:7029392"
    ],
    "placetype": [
      "aat:300008706"
    ],
    "id": 2546832,
    "name:xx": "North Fork Mono Creek"
  }
}
