{
  "geometry": {
    "type": "Point",
    "coordinates": [
      132.4333,
      35.0667
    ]
  },
  "type": "Feature",
  "properties": {
    "hierarchy": [
      "tgn:1103588",
      "tgn:7016808",
      "tgn:7000897",
      "tgn:1000004",
      "tgn:1000120",
      "tgn:7029392"
    ],
    "placetype": [
      "aat:300008795"
    ],
    "id": 1103588,
    "name:xx": "Ōetaka-yama"
  }
}
