{
  "geometry": {
    "type": "Point",
    "coordinates": [
      -111.35,
      34.3667
    ]
  },
  "type": "Feature",
  "properties": {
    "hierarchy": [
      "tgn:2348101",
      "tgn:1000001",
      "tgn:7006451",
      "tgn:2000093",
      "tgn:7012149",
      "tgn:7029392"
    ],
    "placetype": [
      "aat:300008347"
    ],
    "id": 2348101,
    "name:xx": "Geronimo Estates Subdivision"
  }
}
