{
  "geometry": {
    "type": "Point",
    "coordinates": [
      -107.6667,
      35.8667
    ]
  },
  "type": "Feature",
  "properties": {
    "hierarchy": [
      "tgn:2208544",
      "tgn:1000001",
      "tgn:7012149",
      "tgn:7019676",
      "tgn:7007566",
      "tgn:7029392"
    ],
    "placetype": [
      "aat:300008699"
    ],
    "id": 2208544,
    "name:xx": "Burning Bridge Wash"
  }
}
