{
  "geometry": {
    "type": "Point",
    "coordinates": [
      -81.9333,
      26.45
    ]
  },
  "type": "Feature",
  "properties": {
    "hierarchy": [
      "tgn:2640289",
      "tgn:1000001",
      "tgn:7012149",
      "tgn:1002582",
      "tgn:7007240",
      "tgn:7029392"
    ],
    "placetype": [
      "aat:300008791"
    ],
    "id": 2640289,
    "name:xx": "San Carlos Island"
  }
}
