{
  "geometry": {
    "type": "Point",
    "coordinates": [
      81.1667,
      55.6667
    ]
  },
  "type": "Feature",
  "properties": {
    "hierarchy": [
      "tgn:4001047",
      "tgn:1000003",
      "tgn:7594009",
      "tgn:1000066",
      "tgn:7029392"
    ],
    "placetype": [
      "aat:300008347"
    ],
    "id": 4001047,
    "name:xx": "Børsmose"
  }
}
