{
  "geometry": {
    "type": "Point",
    "coordinates": [
      -50.0333,
      -15.1833
    ]
  },
  "type": "Feature",
  "properties": {
    "hierarchy": [
      "tgn:1023296",
      "tgn:7012827",
      "tgn:7002454",
      "tgn:1000047",
      "tgn:1000002",
      "tgn:7029392"
    ],
    "placetype": [
      "aat:300008347"
    ],
    "id": 1023296,
    "name:xx": "Valdelândia"
  }
}
