{
  "geometry": {
    "type": "Point",
    "coordinates": [
      -104.25,
      32.3333
    ]
  },
  "type": "Feature",
  "properties": {
    "hierarchy": [
      "tgn:2221764",
      "tgn:1000001",
      "tgn:2001436",
      "tgn:7012149",
      "tgn:7007566",
      "tgn:7029392"
    ],
    "placetype": [
      "aat:300000390"
    ],
    "id": 2221764,
    "name:xx": "Carlsbad Pit"
  }
}
