{
  "type": "FeatureCollection",
  "features": [
    {
      "geometry": {
        "type": "Point",
        "coordinates": [
          -92.6833,
          31.4
        ]
      },
      "type": "Feature",
      "properties": {
        "hierarchy": [
          "tgn:2513560",
          "tgn:1000001",
          "tgn:7012149",
          "tgn:2000893",
          "tgn:7007256",
          "tgn:7029392"
        ],
        "placetype": [
          "aat:300008680"
        ],
        "id": 2513560,
        "name:xx": "Mill Pond"
      }
    },
    {
      "geometry": {
        "type": "Point",
        "coordinates": [
          -92.2167,
          31.9167
        ]
      },
      "type": "Feature",
      "properties": {
        "hierarchy": [
          "tgn:2513561",
          "tgn:1000001",
          "tgn:7012149",
          "tgn:2000883",
          "tgn:7007256",
          "tgn:7029392"
        ],
        "placetype": [
          "aat:300006191"
        ],
        "id": 2513561,
        "name:xx": "Mill Pond"
      }
    },
    {
      "geometry": {
        "type": "Point",
        "coordinates": [
          -68.7,
          44.2
        ]
      },
      "type": "Feature",
      "properties": {
        "hierarchy": [
          "tgn:2513562",
          "tgn:1000001",
          "tgn:2000922",
          "tgn:7012149",
          "tgn:7007515",
          "tgn:7029392"
        ],
        "placetype": [
          "aat:300132316"
        ],
        "id": 2513562,
        "name:xx": "Mill Pond"
      }
    },
    {
      "geometry": {
        "type": "Point",
        "coordinates": [
          -67.6167,
          44.5167
        ]
      },
      "type": "Feature",
      "properties": {
        "hierarchy": [
          "tgn:2513563",
          "tgn:1000001",
          "tgn:7012149",
          "tgn:7014589",
          "tgn:7007515",
          "tgn:7029392"
        ],
        "placetype": [
          "aat:300132316"
        ],
        "id": 2513563,
        "name:xx": "Mill Pond"
      }
    },
    {
      "geometry": {
        "type": "Point",
        "coordinates": [
          -69.8,
          43.7833
        ]
      },
      "type": "Feature",
      "properties": {
        "hierarchy": [
          "tgn:2513564",
          "tgn:1000001",
          "tgn:7012149",
          "tgn:2000929",
          "tgn:7007515",
          "tgn:7029392"
        ],
        "placetype": [
          "aat:300008680"
        ],
        "id": 2513564,
        "name:xx": "Mill Pond"
      }
    },
    {
      "geometry": {
        "type": "Point",
        "coordinates": [
          -70.4167,
          43.8333
        ]
      },
      "type": "Feature",
      "properties": {
        "hierarchy": [
          "tgn:2513565",
          "tgn:1000001",
          "tgn:2000920",
          "tgn:7012149",
          "tgn:7007515",
          "tgn:7029392"
        ],
        "placetype": [
          "aat:300008680"
        ],
        "id": 2513565,
        "name:xx": "Mill Pond"
      }
    },
    {
      "geometry": {
        "type": "Point",
        "coordinates": [
          -69.2167,
          44.2833
        ]
      },
      "type": "Feature",
      "properties": {
        "hierarchy": [
          "tgn:2513566",
          "tgn:1000001",
          "tgn:2000924",
          "tgn:7012149",
          "tgn:7007515",
          "tgn:7029392"
        ],
        "placetype": [
          "aat:300008680"
        ],
        "id": 2513566,
        "name:xx": "Mill Pond"
      }
    },
    {
      "geometry": {
        "type": "Point",
        "coordinates": [
          -68.75,
          44.35
        ]
      },
      "type": "Feature",
      "properties": {
        "hierarchy": [
          "tgn:2513567",
          "tgn:1000001",
          "tgn:2000922",
          "tgn:7012149",
          "tgn:7007515",
          "tgn:7029392"
        ],
        "placetype": [
          "aat:300008680"
        ],
        "id": 2513567,
        "name:xx": "Mill Pond"
      }
    },
    {
      "geometry": {
        "type": "Point",
        "coordinates": [
          -69.9167,
          44.3667
        ]
      },
      "type": "Feature",
      "properties": {
        "hierarchy": [
          "tgn:2513568",
          "tgn:1000001",
          "tgn:2000923",
          "tgn:7012149",
          "tgn:7007515",
          "tgn:7029392"
        ],
        "placetype": [
          "aat:300008680"
        ],
        "id": 2513568,
        "name:xx": "Mill Pond"
      }
    },
    {
      "geometry": {
        "type": "Point",
        "coordinates": [
          -68.9167,
          44.45
        ]
      },
      "type": "Feature",
      "properties": {
        "hierarchy": [
          "tgn:2513569",
          "tgn:1000001",
          "tgn:7012149",
          "tgn:2000931",
          "tgn:7007515",
          "tgn:7029392"
        ],
        "placetype": [
          "aat:300008680"
        ],
        "id": 2513569,
        "name:xx": "Mill Pond"
      }
    }
  ]
}
