{
  "geometry": {
    "type": "Point",
    "coordinates": [
      -78.4333,
      34.0167
    ]
  },
  "type": "Feature",
  "properties": {
    "hierarchy": [
      "tgn:2512115",
      "tgn:1000001",
      "tgn:2001472",
      "tgn:7012149",
      "tgn:7007709",
      "tgn:7029392"
    ],
    "placetype": [
      "aat:300008699"
    ],
    "id": 2512115,
    "name:xx": "Mill Branch"
  }
}
