{
  "type": "FeatureCollection",
  "features": [
    {
      "geometry": {
        "type": "Point",
        "coordinates": [
          -94.5667,
          43.5667
        ]
      },
      "type": "Feature",
      "properties": {
        "hierarchy": [
          "tgn:2529930",
          "tgn:1000001",
          "tgn:7012149",
          "tgn:2001044",
          "tgn:7007521",
          "tgn:7029392"
        ],
        "placetype": [
          "aat:300008680"
        ],
        "id": 2529930,
        "name:xx": "Mud Slough"
      }
    },
    {
      "geometry": {
        "type": "Point",
        "coordinates": [
          -89.75,
          36.9667
        ]
      },
      "type": "Feature",
      "properties": {
        "hierarchy": [
          "tgn:2529931",
          "tgn:1000001",
          "tgn:7012149",
          "tgn:2001248",
          "tgn:7007523",
          "tgn:7029392"
        ],
        "placetype": [
          "aat:300008699"
        ],
        "id": 2529931,
        "name:xx": "Mud Slough"
      }
    },
    {
      "geometry": {
        "type": "Point",
        "coordinates": [
          -94.5,
          35.3167
        ]
      },
      "type": "Feature",
      "properties": {
        "hierarchy": [
          "tgn:2529932",
          "tgn:1000001",
          "tgn:7012149",
          "tgn:2001690",
          "tgn:7007707",
          "tgn:7029392"
        ],
        "placetype": [
          "aat:300008699"
        ],
        "id": 2529932,
        "name:xx": "Mud Slough"
      }
    },
    {
      "geometry": {
        "type": "Point",
        "coordinates": [
          -88,
          35.4167
        ]
      },
      "type": "Feature",
      "properties": {
        "hierarchy": [
          "tgn:2529933",
          "tgn:1000001",
          "tgn:7012149",
          "tgn:2001904",
          "tgn:7007825",
          "tgn:7029392"
        ],
        "placetype": [
          "aat:300008699"
        ],
        "id": 2529933,
        "name:xx": "Mud Slough"
      }
    },
    {
      "geometry": {
        "type": "Point",
        "coordinates": [
          -120.7667,
          37.0333
        ]
      },
      "type": "Feature",
      "properties": {
        "hierarchy": [
          "tgn:2529934",
          "tgn:1000001",
          "tgn:7012149",
          "tgn:7007157",
          "tgn:1002656",
          "tgn:7029392"
        ],
        "placetype": [
          "aat:300006075"
        ],
        "id": 2529934,
        "name:xx": "Mud Slough Bypass"
      }
    },
    {
      "geometry": {
        "type": "Point",
        "coordinates": [
          -83.75,
          38.3333
        ]
      },
      "type": "Feature",
      "properties": {
        "hierarchy": [
          "tgn:2529938",
          "tgn:1000001",
          "tgn:7012149",
          "tgn:1002375",
          "tgn:7007255",
          "tgn:7029392"
        ],
        "placetype": [
          "aat:300008699"
        ],
        "id": 2529938,
        "name:xx": "Mud Sock Branch"
      }
    },
    {
      "geometry": {
        "type": "Point",
        "coordinates": [
          -113.6667,
          37.4833
        ]
      },
      "type": "Feature",
      "properties": {
        "hierarchy": [
          "tgn:2529939",
          "tgn:1000001",
          "tgn:7012149",
          "tgn:2002127",
          "tgn:7007827",
          "tgn:7029392"
        ],
        "placetype": [
          "aat:300008697"
        ],
        "id": 2529939,
        "name:xx": "Mud Sprin"
      }
    }
  ]
}
