{
  "geometry": {
    "type": "Point",
    "coordinates": [
      -110.0333,
      45.4167
    ]
  },
  "type": "Feature",
  "properties": {
    "hierarchy": [
      "tgn:2681356",
      "tgn:1000001",
      "tgn:7012149",
      "tgn:2001308",
      "tgn:7007524",
      "tgn:7029392"
    ],
    "placetype": [
      "aat:300008680"
    ],
    "id": 2681356,
    "name:xx": "South Picket Pin Lake"
  }
}
