{
  "type": "FeatureCollection",
  "features": [
    {
      "geometry": {
        "type": "Point",
        "coordinates": [
          7.55,
          44
        ]
      },
      "type": "Feature",
      "properties": {
        "hierarchy": [
          "tgn:1033141",
          "tgn:1000003",
          "tgn:1000070",
          "tgn:7002895",
          "tgn:7029392"
        ],
        "placetype": [
          "aat:300008347"
        ],
        "id": 1033141,
        "name:xx": "Fontan"
      }
    },
    {
      "geometry": {
        "type": "Point",
        "coordinates": [
          1.75,
          49.0333
        ]
      },
      "type": "Feature",
      "properties": {
        "hierarchy": [
          "tgn:1033142",
          "tgn:1000003",
          "tgn:7002883",
          "tgn:1000070",
          "tgn:7029392"
        ],
        "placetype": [
          "aat:300008347"
        ],
        "id": 1033142,
        "name:xx": "Fontenay-Saint-Père"
      }
    },
    {
      "geometry": {
        "type": "Point",
        "coordinates": [
          2.8833,
          48.7
        ]
      },
      "type": "Feature",
      "properties": {
        "hierarchy": [
          "tgn:1033143",
          "tgn:1000003",
          "tgn:7002883",
          "tgn:1000070",
          "tgn:7029392"
        ],
        "placetype": [
          "aat:300008347"
        ],
        "id": 1033143,
        "name:xx": "Fontenay-Triésigny"
      }
    },
    {
      "geometry": {
        "type": "Point",
        "coordinates": [
          2.3,
          48.7833
        ]
      },
      "type": "Feature",
      "properties": {
        "hierarchy": [
          "tgn:1033144",
          "tgn:1000003",
          "tgn:7002883",
          "tgn:1000070",
          "tgn:7029392"
        ],
        "placetype": [
          "aat:300008347"
        ],
        "id": 1033144,
        "name:xx": "Fontenay-aux-Roses"
      }
    },
    {
      "geometry": {
        "type": "Point",
        "coordinates": [
          2.45,
          49.05
        ]
      },
      "type": "Feature",
      "properties": {
        "hierarchy": [
          "tgn:1033145",
          "tgn:1000003",
          "tgn:7002883",
          "tgn:1000070",
          "tgn:7029392"
        ],
        "placetype": [
          "aat:300008347"
        ],
        "id": 1033145,
        "name:xx": "Fontenay-en-Parisis"
      }
    },
    {
      "geometry": {
        "type": "Point",
        "coordinates": [
          2.15,
          48.6167
        ]
      },
      "type": "Feature",
      "properties": {
        "hierarchy": [
          "tgn:1033146",
          "tgn:1000003",
          "tgn:7002883",
          "tgn:1000070",
          "tgn:7029392"
        ],
        "placetype": [
          "aat:300008347"
        ],
        "id": 1033146,
        "name:xx": "Fontenay-lès-Briis"
      }
    },
    {
      "geometry": {
        "type": "Point",
        "coordinates": [
          -0.8,
          46.4667
        ]
      },
      "type": "Feature",
      "properties": {
        "hierarchy": [
          "tgn:1033147",
          "tgn:1000003",
          "tgn:7002893",
          "tgn:1000070",
          "tgn:7029392"
        ],
        "placetype": [
          "aat:300008347"
        ],
        "id": 1033147,
        "name:xx": "Fontenay-le-Comte"
      }
    },
    {
      "geometry": {
        "type": "Point",
        "coordinates": [
          2.05,
          48.8167
        ]
      },
      "type": "Feature",
      "properties": {
        "hierarchy": [
          "tgn:1033148",
          "tgn:1000003",
          "tgn:7002883",
          "tgn:1000070",
          "tgn:7029392"
        ],
        "placetype": [
          "aat:300008347"
        ],
        "id": 1033148,
        "name:xx": "Fontenay-le-Fleury"
      }
    },
    {
      "geometry": {
        "type": "Point",
        "coordinates": [
          2.4,
          48.55
        ]
      },
      "type": "Feature",
      "properties": {
        "hierarchy": [
          "tgn:1033149",
          "tgn:1000003",
          "tgn:7002883",
          "tgn:1000070",
          "tgn:7029392"
        ],
        "placetype": [
          "aat:300008347"
        ],
        "id": 1033149,
        "name:xx": "Fontenay-le-Vicomte"
      }
    }
  ]
}
