{
  "type": "FeatureCollection",
  "features": [
    {
      "geometry": {
        "type": "Point",
        "coordinates": [
          6.2167,
          59.15
        ]
      },
      "type": "Feature",
      "properties": {
        "hierarchy": [
          "tgn:4000314",
          "tgn:7003652",
          "tgn:1000003",
          "tgn:1000088",
          "tgn:7029392"
        ],
        "placetype": [
          "aat:300008347"
        ],
        "id": 4000314,
        "name:xx": "Årdal"
      }
    },
    {
      "geometry": {
        "type": "Point",
        "coordinates": [
          15.15,
          55.1
        ]
      },
      "type": "Feature",
      "properties": {
        "hierarchy": [
          "tgn:4000318",
          "tgn:7594005",
          "tgn:1000003",
          "tgn:1000066",
          "tgn:7029392"
        ],
        "placetype": [
          "aat:300008347"
        ],
        "id": 4000318,
        "name:xx": "Årsdale"
      }
    },
    {
      "geometry": {
        "type": "Point",
        "coordinates": [
          6.2833,
          58.3333
        ]
      },
      "type": "Feature",
      "properties": {
        "hierarchy": [
          "tgn:4000319",
          "tgn:7003652",
          "tgn:1000003",
          "tgn:1000088",
          "tgn:7029392"
        ],
        "placetype": [
          "aat:300008347"
        ],
        "id": 4000319,
        "name:xx": "Årstad"
      }
    }
  ]
}
