{
  "geometry": {
    "type": "Point",
    "coordinates": [
      -105.1667,
      39.9667
    ]
  },
  "type": "Feature",
  "properties": {
    "hierarchy": [
      "tgn:2016101",
      "tgn:1000001",
      "tgn:2000198",
      "tgn:7012149",
      "tgn:7007158",
      "tgn:7029392"
    ],
    "placetype": [
      "aat:300008347"
    ],
    "id": 2016101,
    "name:xx": "Paragon Estates"
  }
}
