{
  "type": "FeatureCollection",
  "features": [
    {
      "geometry": {
        "type": "Point",
        "coordinates": [
          12.966667,
          41.433333
        ]
      },
      "type": "Feature",
      "properties": {
        "hierarchy": [
          "tgn:7041320",
          "tgn:7003136",
          "tgn:1000003",
          "tgn:7003080",
          "tgn:1000080",
          "tgn:7029392"
        ],
        "placetype": [
          "aat:300008347"
        ],
        "id": 7041320,
        "name:xx": "San Michele"
      }
    },
    {
      "geometry": {
        "type": "Point",
        "coordinates": [
          13.75,
          45.6
        ]
      },
      "type": "Feature",
      "properties": {
        "hierarchy": [
          "tgn:7041321",
          "tgn:1003505",
          "tgn:1000003",
          "tgn:7002993",
          "tgn:1000080",
          "tgn:7029392"
        ],
        "placetype": [
          "aat:300008795"
        ],
        "id": 7041321,
        "name:xx": "San Michele"
      }
    },
    {
      "geometry": {
        "type": "Point",
        "coordinates": [
          14.25,
          40.566667
        ]
      },
      "type": "Feature",
      "properties": {
        "hierarchy": [
          "tgn:7041323",
          "tgn:7003013",
          "tgn:7003005",
          "tgn:1000003",
          "tgn:1000080",
          "tgn:7029392"
        ],
        "placetype": [
          "aat:300006909"
        ],
        "id": 7041323,
        "name:xx": "San Michele"
      }
    },
    {
      "geometry": {
        "type": "Point",
        "coordinates": [
          16.266667,
          39.033333
        ]
      },
      "type": "Feature",
      "properties": {
        "hierarchy": [
          "tgn:7041324",
          "tgn:1003447",
          "tgn:7007850",
          "tgn:1000003",
          "tgn:1000080",
          "tgn:7029392"
        ],
        "placetype": [
          "aat:300008347"
        ],
        "id": 7041324,
        "name:xx": "San Mazzeo"
      }
    }
  ]
}
