{
  "geometry": {
    "type": "Point",
    "coordinates": [
      123.65,
      41.7833
    ]
  },
  "type": "Feature",
  "properties": {
    "hierarchy": [
      "tgn:1071612",
      "tgn:1000004",
      "tgn:1001390",
      "tgn:1000111",
      "tgn:7029392"
    ],
    "placetype": [
      "aat:300008347"
    ],
    "id": 1071612,
    "name:xx": "Shenjingzi"
  }
}
