{
  "geometry": {
    "type": "Point",
    "coordinates": [
      -83.6167,
      33.6667
    ]
  },
  "type": "Feature",
  "properties": {
    "hierarchy": [
      "tgn:2198140",
      "tgn:1000001",
      "tgn:7012149",
      "tgn:2000438",
      "tgn:7007248",
      "tgn:7029392"
    ],
    "placetype": [
      "aat:300132348"
    ],
    "id": 2198140,
    "name:xx": "Browning Shoals"
  }
}
