{
  "geometry": {
    "type": "Point",
    "coordinates": [
      -112.95,
      47.5167
    ]
  },
  "type": "Feature",
  "properties": {
    "hierarchy": [
      "tgn:2279469",
      "tgn:1000001",
      "tgn:7012149",
      "tgn:2001284",
      "tgn:7007524",
      "tgn:7029392"
    ],
    "placetype": [
      "aat:300008798"
    ],
    "id": 2279469,
    "name:xx": "Deadman Hill"
  }
}
