{
  "type": "FeatureCollection",
  "features": [
    {
      "geometry": {
        "type": "Point",
        "coordinates": [
          -86.3167,
          33.2
        ]
      },
      "type": "Feature",
      "properties": {
        "hierarchy": [
          "tgn:2228210",
          "tgn:7002659",
          "tgn:1000001",
          "tgn:7012149",
          "tgn:2000060",
          "tgn:7029392"
        ],
        "placetype": [
          "aat:300008706"
        ],
        "id": 2228210,
        "name:xx": "Cedar Creek"
      }
    },
    {
      "geometry": {
        "type": "Point",
        "coordinates": [
          -87.2667,
          33.5833
        ]
      },
      "type": "Feature",
      "properties": {
        "hierarchy": [
          "tgn:2228211",
          "tgn:7002659",
          "tgn:1000001",
          "tgn:7012149",
          "tgn:2000063",
          "tgn:7029392"
        ],
        "placetype": [
          "aat:300008706"
        ],
        "id": 2228211,
        "name:xx": "Cedar Creek"
      }
    },
    {
      "geometry": {
        "type": "Point",
        "coordinates": [
          -86.8167,
          34.4
        ]
      },
      "type": "Feature",
      "properties": {
        "hierarchy": [
          "tgn:2228212",
          "tgn:7002659",
          "tgn:1000001",
          "tgn:7012149",
          "tgn:2000051",
          "tgn:7029392"
        ],
        "placetype": [
          "aat:300008706"
        ],
        "id": 2228212,
        "name:xx": "Cedar Creek"
      }
    },
    {
      "geometry": {
        "type": "Point",
        "coordinates": [
          -87.1833,
          34.5
        ]
      },
      "type": "Feature",
      "properties": {
        "hierarchy": [
          "tgn:2228213",
          "tgn:7002659",
          "tgn:1000001",
          "tgn:7012149",
          "tgn:2000039",
          "tgn:7029392"
        ],
        "placetype": [
          "aat:300008706"
        ],
        "id": 2228213,
        "name:xx": "Cedar Creek"
      }
    },
    {
      "geometry": {
        "type": "Point",
        "coordinates": [
          -88.1167,
          34.6333
        ]
      },
      "type": "Feature",
      "properties": {
        "hierarchy": [
          "tgn:2228214",
          "tgn:1000001",
          "tgn:7012149",
          "tgn:7029392"
        ],
        "placetype": [
          "aat:300008706"
        ],
        "id": 2228214,
        "name:xx": "Cedar Creek"
      }
    },
    {
      "geometry": {
        "type": "Point",
        "coordinates": [
          -145.95,
          60.5333
        ]
      },
      "type": "Feature",
      "properties": {
        "hierarchy": [
          "tgn:2228215",
          "tgn:7006450",
          "tgn:1000001",
          "tgn:7012149",
          "tgn:2000086",
          "tgn:7029392"
        ],
        "placetype": [
          "aat:300008706"
        ],
        "id": 2228215,
        "name:xx": "Cedar Creek"
      }
    },
    {
      "geometry": {
        "type": "Point",
        "coordinates": [
          -143.05,
          64.0333
        ]
      },
      "type": "Feature",
      "properties": {
        "hierarchy": [
          "tgn:2228216",
          "tgn:7006450",
          "tgn:1000001",
          "tgn:7012149",
          "tgn:2000085",
          "tgn:7029392"
        ],
        "placetype": [
          "aat:300008706"
        ],
        "id": 2228216,
        "name:xx": "Cedar Creek"
      }
    },
    {
      "geometry": {
        "type": "Point",
        "coordinates": [
          -110.1667,
          33.8833
        ]
      },
      "type": "Feature",
      "properties": {
        "hierarchy": [
          "tgn:2228217",
          "tgn:1000001",
          "tgn:7006451",
          "tgn:2000093",
          "tgn:7012149",
          "tgn:7029392"
        ],
        "placetype": [
          "aat:300008706"
        ],
        "id": 2228217,
        "name:xx": "Cedar Creek"
      }
    },
    {
      "geometry": {
        "type": "Point",
        "coordinates": [
          -112.2833,
          34.3667
        ]
      },
      "type": "Feature",
      "properties": {
        "hierarchy": [
          "tgn:2228218",
          "tgn:1000001",
          "tgn:7006451",
          "tgn:7012149",
          "tgn:2000103",
          "tgn:7029392"
        ],
        "placetype": [
          "aat:300008706"
        ],
        "id": 2228218,
        "name:xx": "Cedar Creek"
      }
    },
    {
      "geometry": {
        "type": "Point",
        "coordinates": [
          -92.5333,
          35.3167
        ]
      },
      "type": "Feature",
      "properties": {
        "hierarchy": [
          "tgn:2228219",
          "tgn:1000001",
          "tgn:7016172",
          "tgn:2000119",
          "tgn:7012149",
          "tgn:7029392"
        ],
        "placetype": [
          "aat:300008347"
        ],
        "id": 2228219,
        "name:xx": "Cedar Creek"
      }
    }
  ]
}
