{
  "geometry": {
    "type": "Point",
    "coordinates": [
      -108.5333,
      36.7833
    ]
  },
  "type": "Feature",
  "properties": {
    "hierarchy": [
      "tgn:2639289",
      "tgn:1000001",
      "tgn:7012149",
      "tgn:2001452",
      "tgn:7007566",
      "tgn:7029392"
    ],
    "placetype": [
      "aat:300008697"
    ],
    "id": 2639289,
    "name:xx": "Salt Spring"
  }
}
