{
  "geometry": {
    "type": "Point",
    "coordinates": [
      78.474444,
      17.7825
    ]
  },
  "type": "Feature",
  "properties": {
    "hierarchy": [
      "tgn:7567742",
      "tgn:1001828",
      "tgn:1000004",
      "tgn:7000198",
      "tgn:7029392"
    ],
    "placetype": [
      "aat:300008347"
    ],
    "name:en": "Rāmayapalli",
    "id": 7567742
  }
}
