{
  "geometry": {
    "type": "Point",
    "coordinates": [
      -98.7667,
      31.3667
    ]
  },
  "type": "Feature",
  "properties": {
    "hierarchy": [
      "tgn:2607990",
      "tgn:1000001",
      "tgn:7012149",
      "tgn:2002042",
      "tgn:7007826",
      "tgn:7029392"
    ],
    "placetype": [
      "aat:300008347"
    ],
    "id": 2607990,
    "name:xx": "Ratler"
  }
}
