{
  "geometry": {
    "type": "Point",
    "coordinates": [
      -112.4333,
      37.85
    ]
  },
  "type": "Feature",
  "properties": {
    "hierarchy": [
      "tgn:2758751",
      "tgn:1000001",
      "tgn:2002109",
      "tgn:7012149",
      "tgn:7007827",
      "tgn:7029392"
    ],
    "placetype": [
      "aat:300006075"
    ],
    "id": 2758751,
    "name:xx": "West Ditch"
  }
}
