{
  "geometry": {
    "type": "Point",
    "coordinates": [
      27.900763,
      31.107147
    ]
  },
  "type": "Feature",
  "properties": {
    "hierarchy": [
      "tgn:7539636",
      "tgn:7001242",
      "tgn:7016833",
      "tgn:1001418",
      "tgn:7029392"
    ],
    "placetype": [
      "aat:300006207"
    ],
    "name:en": "Sāniyat Şāliḩ al Jāhil",
    "id": 7539636
  }
}
