{
  "geometry": {
    "type": "Point",
    "coordinates": [
      -104.8667,
      38.7833
    ]
  },
  "type": "Feature",
  "properties": {
    "hierarchy": [
      "tgn:2353314",
      "tgn:1000001",
      "tgn:7012149",
      "tgn:7014097",
      "tgn:7007158",
      "tgn:7029392"
    ],
    "placetype": [
      "aat:300006191"
    ],
    "id": 2353314,
    "name:xx": "Gold Camp Reservoir"
  }
}
