{
  "geometry": {
    "type": "Point",
    "coordinates": [
      34.0833,
      13.3333
    ]
  },
  "type": "Feature",
  "properties": {
    "hierarchy": [
      "tgn:1094149",
      "tgn:7001242",
      "tgn:1000201",
      "tgn:7593696",
      "tgn:7029392"
    ],
    "placetype": [
      "aat:300008347"
    ],
    "id": 1094149,
    "name:xx": "Al-Quwaysī"
  }
}
