{
  "geometry": {
    "type": "Point",
    "coordinates": [
      79.248783,
      27.207116
    ]
  },
  "type": "Feature",
  "properties": {
    "hierarchy": [
      "tgn:7560007",
      "tgn:1000004",
      "tgn:7000198",
      "tgn:7016722",
      "tgn:7029392"
    ],
    "placetype": [
      "aat:300008347"
    ],
    "name:en": "Kaua Tānda",
    "id": 7560007
  }
}
