{
  "geometry": {
    "type": "Point",
    "coordinates": [
      -88.7833,
      39.0167
    ]
  },
  "type": "Feature",
  "properties": {
    "hierarchy": [
      "tgn:2167470",
      "tgn:1000001",
      "tgn:1002349",
      "tgn:7012149",
      "tgn:7007251",
      "tgn:7029392"
    ],
    "placetype": [
      "aat:300008706"
    ],
    "id": 2167470,
    "name:xx": "Big Creek"
  }
}
