{
  "geometry": {
    "type": "Point",
    "coordinates": [
      -141.2833,
      -19.15
    ]
  },
  "type": "Feature",
  "properties": {
    "hierarchy": [
      "tgn:1006059",
      "tgn:1010365",
      "tgn:1000216",
      "tgn:1000006",
      "tgn:7029392"
    ],
    "placetype": [
      "aat:300008793"
    ],
    "id": 1006059,
    "name:xx": "Manuhangi"
  }
}
