{
  "geometry": {
    "type": "Point",
    "coordinates": [
      -83.8333,
      22.5833
    ]
  },
  "type": "Feature",
  "properties": {
    "hierarchy": [
      "tgn:1109088",
      "tgn:1001488",
      "tgn:1000001",
      "tgn:7004624",
      "tgn:7029392"
    ],
    "placetype": [
      "aat:300386831"
    ],
    "id": 1109088,
    "name:xx": "Guaniguanico, Cordillera de"
  }
}
