{
  "type": "FeatureCollection",
  "features": [
    {
      "geometry": {
        "type": "Point",
        "coordinates": [
          -72.483333,
          -35.75
        ]
      },
      "type": "Feature",
      "properties": {
        "hierarchy": [
          "tgn:7288690",
          "tgn:1001705",
          "tgn:1000049",
          "tgn:1000002",
          "tgn:7029392"
        ],
        "placetype": [
          "aat:300008347"
        ],
        "id": 7288690,
        "name:xx": "Lagunillas"
      }
    },
    {
      "geometry": {
        "type": "Point",
        "coordinates": [
          -71.466667,
          -33.433333
        ]
      },
      "type": "Feature",
      "properties": {
        "hierarchy": [
          "tgn:7288691",
          "tgn:1001768",
          "tgn:1000049",
          "tgn:1000002",
          "tgn:7029392"
        ],
        "placetype": [
          "aat:300008347"
        ],
        "id": 7288691,
        "name:xx": "Lagunillas"
      }
    },
    {
      "geometry": {
        "type": "Point",
        "coordinates": [
          -71.166667,
          -30.533333
        ]
      },
      "type": "Feature",
      "properties": {
        "hierarchy": [
          "tgn:7288692",
          "tgn:1001657",
          "tgn:1000049",
          "tgn:1000002",
          "tgn:7029392"
        ],
        "placetype": [
          "aat:300008347"
        ],
        "id": 7288692,
        "name:xx": "Lagunillas"
      }
    },
    {
      "geometry": {
        "type": "Point",
        "coordinates": [
          -69.3,
          -18.1
        ]
      },
      "type": "Feature",
      "properties": {
        "hierarchy": [
          "tgn:7288693",
          "tgn:7002464",
          "tgn:1000049",
          "tgn:1000002",
          "tgn:7029392"
        ],
        "placetype": [
          "aat:300008680"
        ],
        "id": 7288693,
        "name:xx": "Lagunillas"
      }
    },
    {
      "geometry": {
        "type": "Point",
        "coordinates": [
          -71.633333,
          -34.6
        ]
      },
      "type": "Feature",
      "properties": {
        "hierarchy": [
          "tgn:7288694",
          "tgn:1001695",
          "tgn:1000049",
          "tgn:1000002",
          "tgn:7029392"
        ],
        "placetype": [
          "aat:300387200"
        ],
        "id": 7288694,
        "name:xx": "Lagunillas"
      }
    },
    {
      "geometry": {
        "type": "Point",
        "coordinates": [
          -71.333333,
          -30.15
        ]
      },
      "type": "Feature",
      "properties": {
        "hierarchy": [
          "tgn:7288695",
          "tgn:1001657",
          "tgn:1000049",
          "tgn:1000002",
          "tgn:7029392"
        ],
        "placetype": [
          "aat:300387200"
        ],
        "id": 7288695,
        "name:xx": "Lagunillas"
      }
    },
    {
      "geometry": {
        "type": "Point",
        "coordinates": [
          -71.95,
          -34.65
        ]
      },
      "type": "Feature",
      "properties": {
        "hierarchy": [
          "tgn:7288696",
          "tgn:1001695",
          "tgn:1000049",
          "tgn:1000002",
          "tgn:7029392"
        ],
        "placetype": [
          "aat:300008777"
        ],
        "id": 7288696,
        "name:xx": "Lagunillas"
      }
    },
    {
      "geometry": {
        "type": "Point",
        "coordinates": [
          -71.883333,
          -33.966667
        ]
      },
      "type": "Feature",
      "properties": {
        "hierarchy": [
          "tgn:7288697",
          "tgn:1001708",
          "tgn:1000049",
          "tgn:1000002",
          "tgn:7029392"
        ],
        "placetype": [
          "aat:300008777"
        ],
        "id": 7288697,
        "name:xx": "Lagunillas"
      }
    },
    {
      "geometry": {
        "type": "Point",
        "coordinates": [
          -68.833333,
          -19.916667
        ]
      },
      "type": "Feature",
      "properties": {
        "hierarchy": [
          "tgn:7288698",
          "tgn:7002464",
          "tgn:1000049",
          "tgn:1000002",
          "tgn:7029392"
        ],
        "placetype": [
          "aat:300008805"
        ],
        "id": 7288698,
        "name:xx": "Lagunilla, Pampa"
      }
    },
    {
      "geometry": {
        "type": "Point",
        "coordinates": [
          -68.85,
          -19.933333
        ]
      },
      "type": "Feature",
      "properties": {
        "hierarchy": [
          "tgn:7288699",
          "tgn:7002464",
          "tgn:1000049",
          "tgn:1000002",
          "tgn:7029392"
        ],
        "placetype": [
          "aat:300008680"
        ],
        "id": 7288699,
        "name:xx": "Lagunilla, Laguna"
      }
    }
  ]
}
