{
  "geometry": {
    "type": "Point",
    "coordinates": [
      167.85,
      -46.35
    ]
  },
  "type": "Feature",
  "properties": {
    "hierarchy": [
      "tgn:7513564",
      "tgn:1009227",
      "tgn:1000226",
      "tgn:7016822",
      "tgn:1000006",
      "tgn:7029392"
    ],
    "placetype": [
      "aat:300008680"
    ],
    "name:en": "George, Lake",
    "id": 7513564
  }
}
