{
  "geometry": {
    "type": "Point",
    "coordinates": [
      31.255116,
      30.115506
    ]
  },
  "type": "Feature",
  "properties": {
    "hierarchy": [
      "tgn:7531684",
      "tgn:7001242",
      "tgn:7016833",
      "tgn:1001092",
      "tgn:7029392"
    ],
    "placetype": [
      "aat:300004792"
    ],
    "id": 7531684,
    "name:xx": "Mashr큰' Wirash wa Makh훮zin Mitr큰 al Anf훮q"
  }
}
