{
  "geometry": {
    "type": "Point",
    "coordinates": [
      -105.9833,
      35.9833
    ]
  },
  "type": "Feature",
  "properties": {
    "hierarchy": [
      "tgn:2443917",
      "tgn:1000001",
      "tgn:7012149",
      "tgn:2001454",
      "tgn:7007566",
      "tgn:7029392"
    ],
    "placetype": [
      "aat:300006075"
    ],
    "id": 2443917,
    "name:xx": "La Puebla Ditch"
  }
}
