{
  "geometry": {
    "type": "Point",
    "coordinates": [
      -77.9667,
      41.1667
    ]
  },
  "type": "Feature",
  "properties": {
    "hierarchy": [
      "tgn:2735670",
      "tgn:1000001",
      "tgn:1002249",
      "tgn:7012149",
      "tgn:7007710",
      "tgn:7029392"
    ],
    "placetype": [
      "aat:300008347"
    ],
    "id": 2735670,
    "name:xx": "Twin Hollows"
  }
}
