{
  "geometry": {
    "type": "Point",
    "coordinates": [
      -94.8333,
      33.25
    ]
  },
  "type": "Feature",
  "properties": {
    "hierarchy": [
      "tgn:2712789",
      "tgn:1000001",
      "tgn:7012149",
      "tgn:1002948",
      "tgn:7007826",
      "tgn:7029392"
    ],
    "placetype": [
      "aat:300008706"
    ],
    "id": 2712789,
    "name:xx": "Taylor Creek"
  }
}
