{
  "geometry": {
    "type": "Point",
    "coordinates": [
      -91.65,
      35.4167
    ]
  },
  "type": "Feature",
  "properties": {
    "hierarchy": [
      "tgn:2194577",
      "tgn:1000001",
      "tgn:7016172",
      "tgn:7012149",
      "tgn:2000177",
      "tgn:7029392"
    ],
    "placetype": [
      "aat:300006191"
    ],
    "id": 2194577,
    "name:xx": "Bridges Lake"
  }
}
