{
  "geometry": {
    "type": "Point",
    "coordinates": [
      -80.5667,
      37.0667
    ]
  },
  "type": "Feature",
  "properties": {
    "hierarchy": [
      "tgn:2459880",
      "tgn:1000001",
      "tgn:7012149",
      "tgn:2002174",
      "tgn:7007919",
      "tgn:7029392"
    ],
    "placetype": [
      "aat:300006191"
    ],
    "id": 2459880,
    "name:xx": "Little River Reservoir"
  }
}
