{
  "geometry": {
    "type": "Point",
    "coordinates": [
      -108.4833,
      39.6833
    ]
  },
  "type": "Feature",
  "properties": {
    "hierarchy": [
      "tgn:2309615",
      "tgn:1000001",
      "tgn:7012149",
      "tgn:2000214",
      "tgn:7007158",
      "tgn:7029392"
    ],
    "placetype": [
      "aat:300008706"
    ],
    "id": 2309615,
    "name:xx": "East Willow Creek"
  }
}
