{
  "geometry": {
    "type": "Point",
    "coordinates": [
      -95.85,
      36.9667
    ]
  },
  "type": "Feature",
  "properties": {
    "hierarchy": [
      "tgn:2258516",
      "tgn:1000001",
      "tgn:7012149",
      "tgn:2001696",
      "tgn:7007707",
      "tgn:7029392"
    ],
    "placetype": [
      "aat:300008347"
    ],
    "id": 2258516,
    "name:xx": "Cotton Valley"
  }
}
