{
  "geometry": {
    "type": "Point",
    "coordinates": [
      -81.65,
      39.1333
    ]
  },
  "type": "Feature",
  "properties": {
    "hierarchy": [
      "tgn:2363896",
      "tgn:1000001",
      "tgn:7012149",
      "tgn:2002303",
      "tgn:7013961",
      "tgn:7029392"
    ],
    "placetype": [
      "aat:300008699"
    ],
    "id": 2363896,
    "name:xx": "Green Lick"
  }
}
