{
  "geometry": {
    "type": "Point",
    "coordinates": [
      -79.85,
      36.7333
    ]
  },
  "type": "Feature",
  "properties": {
    "hierarchy": [
      "tgn:2451868",
      "tgn:1000001",
      "tgn:7012149",
      "tgn:2002167",
      "tgn:7007919",
      "tgn:7029392"
    ],
    "placetype": [
      "aat:300008706"
    ],
    "id": 2451868,
    "name:xx": "Little Beaver Creek"
  }
}
