{
  "geometry": {
    "type": "Point",
    "coordinates": [
      17.15,
      50.4667
    ]
  },
  "type": "Feature",
  "properties": {
    "hierarchy": [
      "tgn:1049338",
      "tgn:1000003",
      "tgn:7024124",
      "tgn:7006366",
      "tgn:7029392"
    ],
    "placetype": [
      "aat:300008347"
    ],
    "id": 1049338,
    "name:xx": "Otmuchów"
  }
}
