{
  "geometry": {
    "type": "Point",
    "coordinates": [
      30.04642,
      31.270467
    ]
  },
  "type": "Feature",
  "properties": {
    "hierarchy": [
      "tgn:7530477",
      "tgn:7001242",
      "tgn:7016833",
      "tgn:1001079",
      "tgn:7029392"
    ],
    "placetype": [
      "aat:300008347"
    ],
    "name:en": "Manshīyat al Awqāf",
    "id": 7530477
  }
}
