{
  "geometry": {
    "type": "Point",
    "coordinates": [
      -87.75,
      35.7167
    ]
  },
  "type": "Feature",
  "properties": {
    "hierarchy": [
      "tgn:2208692",
      "tgn:1000001",
      "tgn:7012149",
      "tgn:2001904",
      "tgn:7007825",
      "tgn:7029392"
    ],
    "placetype": [
      "aat:300008761"
    ],
    "id": 2208692,
    "name:xx": "Burns Hollow"
  }
}
