{
  "geometry": {
    "type": "Point",
    "coordinates": [
      -122.6667,
      48.15
    ]
  },
  "type": "Feature",
  "properties": {
    "hierarchy": [
      "tgn:2436179",
      "tgn:1000001",
      "tgn:7012149",
      "tgn:1002505",
      "tgn:7007920",
      "tgn:7029392"
    ],
    "placetype": [
      "aat:300132316"
    ],
    "id": 2436179,
    "name:xx": "Keystone Harbor"
  }
}
