{
  "type": "FeatureCollection",
  "features": [
    {
      "geometry": {
        "type": "Point",
        "coordinates": [
          -76.9833,
          39.05
        ]
      },
      "type": "Feature",
      "properties": {
        "hierarchy": [
          "tgn:2046932",
          "tgn:1000001",
          "tgn:7016104",
          "tgn:7012149",
          "tgn:7007516",
          "tgn:7029392"
        ],
        "placetype": [
          "aat:300008347"
        ],
        "id": 2046932,
        "name:xx": "East Springbrook"
      }
    },
    {
      "geometry": {
        "type": "Point",
        "coordinates": [
          -76.9333,
          39.5
        ]
      },
      "type": "Feature",
      "properties": {
        "hierarchy": [
          "tgn:2046933",
          "tgn:1002238",
          "tgn:1000001",
          "tgn:7012149",
          "tgn:7007516",
          "tgn:7029392"
        ],
        "placetype": [
          "aat:300008347"
        ],
        "id": 2046933,
        "name:xx": "Eastview"
      }
    },
    {
      "geometry": {
        "type": "Point",
        "coordinates": [
          -78.8833,
          39.65
        ]
      },
      "type": "Feature",
      "properties": {
        "hierarchy": [
          "tgn:2046935",
          "tgn:2000934",
          "tgn:1000001",
          "tgn:7012149",
          "tgn:7007516",
          "tgn:7029392"
        ],
        "placetype": [
          "aat:300000390"
        ],
        "id": 2046935,
        "name:xx": "Eckhart Mines"
      }
    },
    {
      "geometry": {
        "type": "Point",
        "coordinates": [
          -75.65,
          38.2667
        ]
      },
      "type": "Feature",
      "properties": {
        "hierarchy": [
          "tgn:2046936",
          "tgn:1000001",
          "tgn:1002902",
          "tgn:7012149",
          "tgn:7007516",
          "tgn:7029392"
        ],
        "placetype": [
          "aat:300008347"
        ],
        "id": 2046936,
        "name:xx": "Eden"
      }
    },
    {
      "geometry": {
        "type": "Point",
        "coordinates": [
          -75.9,
          39.6167
        ]
      },
      "type": "Feature",
      "properties": {
        "hierarchy": [
          "tgn:2046937",
          "tgn:1002247",
          "tgn:1000001",
          "tgn:7012149",
          "tgn:7007516",
          "tgn:7029392"
        ],
        "placetype": [
          "aat:300387016"
        ],
        "id": 2046937,
        "name:xx": "Eder"
      }
    },
    {
      "geometry": {
        "type": "Point",
        "coordinates": [
          -76.2,
          39.15
        ]
      },
      "type": "Feature",
      "properties": {
        "hierarchy": [
          "tgn:2046938",
          "tgn:1000001",
          "tgn:1002539",
          "tgn:7012149",
          "tgn:7007516",
          "tgn:7029392"
        ],
        "placetype": [
          "aat:300008347"
        ],
        "id": 2046938,
        "name:xx": "Edesville"
      }
    }
  ]
}
