{
  "geometry": {
    "type": "Point",
    "coordinates": [
      -85.4167,
      35.2167
    ]
  },
  "type": "Feature",
  "properties": {
    "hierarchy": [
      "tgn:2549671",
      "tgn:1000001",
      "tgn:7012149",
      "tgn:7007825",
      "tgn:7029392"
    ],
    "placetype": [
      "aat:300008706"
    ],
    "id": 2549671,
    "name:xx": "North Suck Creek"
  }
}
