{
  "geometry": {
    "type": "Point",
    "coordinates": [
      -111.8333,
      36.9333
    ]
  },
  "type": "Feature",
  "properties": {
    "hierarchy": [
      "tgn:2395111",
      "tgn:1000001",
      "tgn:7006451",
      "tgn:2000092",
      "tgn:7012149",
      "tgn:7029392"
    ],
    "placetype": [
      "aat:300386837"
    ],
    "id": 2395111,
    "name:xx": "Hole in the Rock"
  }
}
