{
  "type": "FeatureCollection",
  "features": [
    {
      "geometry": {
        "type": "Point",
        "coordinates": [
          -87.0833,
          31.1333
        ]
      },
      "type": "Feature",
      "properties": {
        "hierarchy": [
          "tgn:2623000",
          "tgn:7002659",
          "tgn:1000001",
          "tgn:7012149",
          "tgn:2000026",
          "tgn:7029392"
        ],
        "placetype": [
          "aat:300006191"
        ],
        "id": 2623000,
        "name:xx": "Robinsons Lake"
      }
    },
    {
      "geometry": {
        "type": "Point",
        "coordinates": [
          -86.55,
          32.2333
        ]
      },
      "type": "Feature",
      "properties": {
        "hierarchy": [
          "tgn:2623001",
          "tgn:7002659",
          "tgn:1000001",
          "tgn:7012149",
          "tgn:2000042",
          "tgn:7029392"
        ],
        "placetype": [
          "aat:300006191"
        ],
        "id": 2623001,
        "name:xx": "Robinsons Lake"
      }
    },
    {
      "geometry": {
        "type": "Point",
        "coordinates": [
          -92.5833,
          38.9167
        ]
      },
      "type": "Feature",
      "properties": {
        "hierarchy": [
          "tgn:2623002",
          "tgn:1000001",
          "tgn:7012149",
          "tgn:2001189",
          "tgn:7007523",
          "tgn:7029392"
        ],
        "placetype": [
          "aat:300006191"
        ],
        "id": 2623002,
        "name:xx": "Robinsons Lake"
      }
    },
    {
      "geometry": {
        "type": "Point",
        "coordinates": [
          -81.2,
          35.3667
        ]
      },
      "type": "Feature",
      "properties": {
        "hierarchy": [
          "tgn:2623003",
          "tgn:1000001",
          "tgn:7012149",
          "tgn:2001496",
          "tgn:7007709",
          "tgn:7029392"
        ],
        "placetype": [
          "aat:300006191"
        ],
        "id": 2623003,
        "name:xx": "Robinsons Lake"
      }
    },
    {
      "geometry": {
        "type": "Point",
        "coordinates": [
          -86.45,
          32.0333
        ]
      },
      "type": "Feature",
      "properties": {
        "hierarchy": [
          "tgn:2623004",
          "tgn:7002659",
          "tgn:1000001",
          "tgn:7012149",
          "tgn:2000042",
          "tgn:7029392"
        ],
        "placetype": [
          "aat:300006191"
        ],
        "id": 2623004,
        "name:xx": "Robinsons Pond"
      }
    },
    {
      "geometry": {
        "type": "Point",
        "coordinates": [
          -77.8167,
          36.3833
        ]
      },
      "type": "Feature",
      "properties": {
        "hierarchy": [
          "tgn:2623005",
          "tgn:1000001",
          "tgn:7012149",
          "tgn:2001501",
          "tgn:7007709",
          "tgn:7029392"
        ],
        "placetype": [
          "aat:300006191"
        ],
        "id": 2623005,
        "name:xx": "Robinsons Pond"
      }
    },
    {
      "geometry": {
        "type": "Point",
        "coordinates": [
          -75.1833,
          38.7
        ]
      },
      "type": "Feature",
      "properties": {
        "hierarchy": [
          "tgn:2623006",
          "tgn:1002933",
          "tgn:1000001",
          "tgn:7012149",
          "tgn:7007239",
          "tgn:7029392"
        ],
        "placetype": [
          "aat:300008347"
        ],
        "id": 2623006,
        "name:xx": "Robinsonville"
      }
    },
    {
      "geometry": {
        "type": "Point",
        "coordinates": [
          -71.2667,
          42
        ]
      },
      "type": "Feature",
      "properties": {
        "hierarchy": [
          "tgn:2623007",
          "tgn:1002201",
          "tgn:1000001",
          "tgn:7012149",
          "tgn:7007517",
          "tgn:7029392"
        ],
        "placetype": [
          "aat:300008347"
        ],
        "id": 2623007,
        "name:xx": "Robinsonville"
      }
    },
    {
      "geometry": {
        "type": "Point",
        "coordinates": [
          -118.4833,
          44.7
        ]
      },
      "type": "Feature",
      "properties": {
        "hierarchy": [
          "tgn:2623008",
          "tgn:1000001",
          "tgn:7012149",
          "tgn:2001708",
          "tgn:7007708",
          "tgn:7029392"
        ],
        "placetype": [
          "aat:300008347"
        ],
        "id": 2623008,
        "name:xx": "Robinsonville"
      }
    },
    {
      "geometry": {
        "type": "Point",
        "coordinates": [
          -78.3333,
          39.8
        ]
      },
      "type": "Feature",
      "properties": {
        "hierarchy": [
          "tgn:2623009",
          "tgn:1002172",
          "tgn:1000001",
          "tgn:7012149",
          "tgn:7007710",
          "tgn:7029392"
        ],
        "placetype": [
          "aat:300008347"
        ],
        "id": 2623009,
        "name:xx": "Robinsonville"
      }
    }
  ]
}
