{
  "geometry": {
    "type": "Point",
    "coordinates": [
      -85.3333,
      35.6833
    ]
  },
  "type": "Feature",
  "properties": {
    "hierarchy": [
      "tgn:2422790",
      "tgn:1000001",
      "tgn:7012149",
      "tgn:2001924",
      "tgn:7007825",
      "tgn:7029392"
    ],
    "placetype": [
      "aat:300008699"
    ],
    "id": 2422790,
    "name:xx": "Joe Branch"
  }
}
