{
  "geometry": {
    "type": "Point",
    "coordinates": [
      -46.2833,
      -23.6667
    ]
  },
  "type": "Feature",
  "properties": {
    "hierarchy": [
      "tgn:1132826",
      "tgn:1001945",
      "tgn:1000047",
      "tgn:7002457",
      "tgn:1000002",
      "tgn:7029392"
    ],
    "placetype": [
      "aat:300008706"
    ],
    "id": 1132826,
    "name:xx": "Claro, Ribeirão"
  }
}
