{
  "geometry": {
    "type": "Point",
    "coordinates": [
      -111.4667,
      37.6667
    ]
  },
  "type": "Feature",
  "properties": {
    "hierarchy": [
      "tgn:2714932",
      "tgn:1000001",
      "tgn:2002109",
      "tgn:7012149",
      "tgn:7007827",
      "tgn:7029392"
    ],
    "placetype": [
      "aat:300008697"
    ],
    "id": 2714932,
    "name:xx": "Tenmile Spring"
  }
}
