{
  "geometry": {
    "type": "Point",
    "coordinates": [
      31.248121,
      30.09698
    ]
  },
  "type": "Feature",
  "properties": {
    "hierarchy": [
      "tgn:7531132",
      "tgn:7001242",
      "tgn:7016833",
      "tgn:1001091",
      "tgn:7029392"
    ],
    "placetype": [
      "aat:300007466"
    ],
    "id": 7531132,
    "name:xx": "Kanīsat al 'Adhrā' wa al Malāk Mīkhā'īl"
  }
}
