{
  "geometry": {
    "type": "Point",
    "coordinates": [
      -97.7167,
      32.8667
    ]
  },
  "type": "Feature",
  "properties": {
    "hierarchy": [
      "tgn:2552244",
      "tgn:1000001",
      "tgn:7012149",
      "tgn:1002771",
      "tgn:7007826",
      "tgn:7029392"
    ],
    "placetype": [
      "aat:300006191"
    ],
    "id": 2552244,
    "name:xx": "Number Sixteen, Reservoir"
  }
}
