{
  "type": "FeatureCollection",
  "features": [
    {
      "geometry": {
        "type": "Point",
        "coordinates": [
          31.612234,
          30.953379
        ]
      },
      "type": "Feature",
      "properties": {
        "hierarchy": [
          "tgn:7543450",
          "tgn:7001242",
          "tgn:1001059",
          "tgn:7016833",
          "tgn:7029392"
        ],
        "placetype": [
          "aat:300008347"
        ],
        "id": 7543450,
        "name:xx": "'Izbat Manşūr"
      }
    },
    {
      "geometry": {
        "type": "Point",
        "coordinates": [
          31.690321,
          30.953784
        ]
      },
      "type": "Feature",
      "properties": {
        "hierarchy": [
          "tgn:7543451",
          "tgn:7001242",
          "tgn:7016833",
          "tgn:1001113",
          "tgn:7029392"
        ],
        "placetype": [
          "aat:300008347"
        ],
        "id": 7543451,
        "name:xx": "'Izbat ad Duktūr Ibrāhīm"
      }
    },
    {
      "geometry": {
        "type": "Point",
        "coordinates": [
          31.6637,
          30.929375
        ]
      },
      "type": "Feature",
      "properties": {
        "hierarchy": [
          "tgn:7543452",
          "tgn:7001242",
          "tgn:1001059",
          "tgn:7016833",
          "tgn:7029392"
        ],
        "placetype": [
          "aat:300008347"
        ],
        "id": 7543452,
        "name:xx": "Al Ma'alwah"
      }
    },
    {
      "geometry": {
        "type": "Point",
        "coordinates": [
          31.545666,
          30.972888
        ]
      },
      "type": "Feature",
      "properties": {
        "hierarchy": [
          "tgn:7543453",
          "tgn:7001242",
          "tgn:1001059",
          "tgn:7016833",
          "tgn:7029392"
        ],
        "placetype": [
          "aat:300008347"
        ],
        "id": 7543453,
        "name:xx": "'Izbat ash Shaykh Yūsif"
      }
    },
    {
      "geometry": {
        "type": "Point",
        "coordinates": [
          31.730286,
          30.994935
        ]
      },
      "type": "Feature",
      "properties": {
        "hierarchy": [
          "tgn:7543454",
          "tgn:7001242",
          "tgn:7016833",
          "tgn:1001113",
          "tgn:7029392"
        ],
        "placetype": [
          "aat:300008347"
        ],
        "id": 7543454,
        "name:xx": "Qaşşāşīn al Azhār"
      }
    },
    {
      "geometry": {
        "type": "Point",
        "coordinates": [
          31.71737,
          30.998196
        ]
      },
      "type": "Feature",
      "properties": {
        "hierarchy": [
          "tgn:7543455",
          "tgn:7001242",
          "tgn:1001059",
          "tgn:7016833",
          "tgn:7029392"
        ],
        "placetype": [
          "aat:300008347"
        ],
        "id": 7543455,
        "name:xx": "'Izbat al Bāz"
      }
    },
    {
      "geometry": {
        "type": "Point",
        "coordinates": [
          31.610938,
          30.9388
        ]
      },
      "type": "Feature",
      "properties": {
        "hierarchy": [
          "tgn:7543456",
          "tgn:7001242",
          "tgn:1001059",
          "tgn:7016833",
          "tgn:7029392"
        ],
        "placetype": [
          "aat:300008347"
        ],
        "id": 7543456,
        "name:xx": "'Izbat Ḩusayn Āghā"
      }
    },
    {
      "geometry": {
        "type": "Point",
        "coordinates": [
          31.647529,
          30.954152
        ]
      },
      "type": "Feature",
      "properties": {
        "hierarchy": [
          "tgn:7543457",
          "tgn:7001242",
          "tgn:1001059",
          "tgn:7016833",
          "tgn:7029392"
        ],
        "placetype": [
          "aat:300008347"
        ],
        "id": 7543457,
        "name:xx": "'Izbat ash Shurafā"
      }
    },
    {
      "geometry": {
        "type": "Point",
        "coordinates": [
          31.701119,
          30.979628
        ]
      },
      "type": "Feature",
      "properties": {
        "hierarchy": [
          "tgn:7543458",
          "tgn:7001242",
          "tgn:7016833",
          "tgn:1001113",
          "tgn:7029392"
        ],
        "placetype": [
          "aat:300008347"
        ],
        "id": 7543458,
        "name:xx": "'Izbat ash Shalābwah"
      }
    },
    {
      "geometry": {
        "type": "Point",
        "coordinates": [
          31.628866,
          30.801327
        ]
      },
      "type": "Feature",
      "properties": {
        "hierarchy": [
          "tgn:7543459",
          "tgn:7001242",
          "tgn:7016833",
          "tgn:1001113",
          "tgn:7029392"
        ],
        "placetype": [
          "aat:300008347"
        ],
        "id": 7543459,
        "name:xx": "Kafr 'Uthmān"
      }
    }
  ]
}
