{
  "geometry": {
    "type": "Point",
    "coordinates": [
      -88.0333,
      46.8667
    ]
  },
  "type": "Feature",
  "properties": {
    "hierarchy": [
      "tgn:2145133",
      "tgn:1000001",
      "tgn:7012149",
      "tgn:2000975",
      "tgn:7007520",
      "tgn:7029392"
    ],
    "placetype": [
      "aat:300008798"
    ],
    "id": 2145133,
    "name:xx": "Bald Mountain"
  }
}
