{
  "geometry": {
    "type": "Point",
    "coordinates": [
      47.25,
      5.75
    ]
  },
  "type": "Feature",
  "properties": {
    "hierarchy": [
      "tgn:1092617",
      "tgn:7001242",
      "tgn:1001673",
      "tgn:1000192",
      "tgn:7029392"
    ],
    "placetype": [
      "aat:300008347"
    ],
    "id": 1092617,
    "name:xx": "Baxdo"
  }
}
