{
  "type": "FeatureCollection",
  "features": [
    {
      "geometry": {
        "type": "Point",
        "coordinates": [
          -85.3833,
          43.0833
        ]
      },
      "type": "Feature",
      "properties": {
        "hierarchy": [
          "tgn:2779450",
          "tgn:1000001",
          "tgn:7012149",
          "tgn:1002540",
          "tgn:7007520",
          "tgn:7029392"
        ],
        "placetype": [
          "aat:300008680"
        ],
        "id": 2779450,
        "name:xx": "Wolf Lake"
      }
    },
    {
      "geometry": {
        "type": "Point",
        "coordinates": [
          -86.1,
          43.25
        ]
      },
      "type": "Feature",
      "properties": {
        "hierarchy": [
          "tgn:2779451",
          "tgn:1000001",
          "tgn:7012149",
          "tgn:1002700",
          "tgn:7007520",
          "tgn:7029392"
        ],
        "placetype": [
          "aat:300008680"
        ],
        "id": 2779451,
        "name:xx": "Wolf Lake"
      }
    },
    {
      "geometry": {
        "type": "Point",
        "coordinates": [
          -85.1667,
          43.4333
        ]
      },
      "type": "Feature",
      "properties": {
        "hierarchy": [
          "tgn:2779452",
          "tgn:1000001",
          "tgn:7012149",
          "tgn:2000981",
          "tgn:7007520",
          "tgn:7029392"
        ],
        "placetype": [
          "aat:300008680"
        ],
        "id": 2779452,
        "name:xx": "Wolf Lake"
      }
    },
    {
      "geometry": {
        "type": "Point",
        "coordinates": [
          -84.6,
          43.9167
        ]
      },
      "type": "Feature",
      "properties": {
        "hierarchy": [
          "tgn:2779453",
          "tgn:1000001",
          "tgn:7012149",
          "tgn:7007520",
          "tgn:7029392"
        ],
        "placetype": [
          "aat:300008680"
        ],
        "id": 2779453,
        "name:xx": "Wolf Lake"
      }
    },
    {
      "geometry": {
        "type": "Point",
        "coordinates": [
          -86.5167,
          46.05
        ]
      },
      "type": "Feature",
      "properties": {
        "hierarchy": [
          "tgn:2779454",
          "tgn:1000001",
          "tgn:2000955",
          "tgn:7012149",
          "tgn:7007520",
          "tgn:7029392"
        ],
        "placetype": [
          "aat:300008680"
        ],
        "id": 2779454,
        "name:xx": "Wolf Lake"
      }
    },
    {
      "geometry": {
        "type": "Point",
        "coordinates": [
          -88.65,
          46.3167
        ]
      },
      "type": "Feature",
      "properties": {
        "hierarchy": [
          "tgn:2779455",
          "tgn:1000001",
          "tgn:7012149",
          "tgn:2000966",
          "tgn:7007520",
          "tgn:7029392"
        ],
        "placetype": [
          "aat:300008680"
        ],
        "id": 2779455,
        "name:xx": "Wolf Lake"
      }
    },
    {
      "geometry": {
        "type": "Point",
        "coordinates": [
          -85.7333,
          46.4833
        ]
      },
      "type": "Feature",
      "properties": {
        "hierarchy": [
          "tgn:2779456",
          "tgn:1000001",
          "tgn:7012149",
          "tgn:2000972",
          "tgn:7007520",
          "tgn:7029392"
        ],
        "placetype": [
          "aat:300008680"
        ],
        "id": 2779456,
        "name:xx": "Wolf Lake"
      }
    },
    {
      "geometry": {
        "type": "Point",
        "coordinates": [
          -86.2333,
          46.5167
        ]
      },
      "type": "Feature",
      "properties": {
        "hierarchy": [
          "tgn:2779457",
          "tgn:2000943",
          "tgn:1000001",
          "tgn:7012149",
          "tgn:7007520",
          "tgn:7029392"
        ],
        "placetype": [
          "aat:300008680"
        ],
        "id": 2779457,
        "name:xx": "Wolf Lake"
      }
    },
    {
      "geometry": {
        "type": "Point",
        "coordinates": [
          -87.8833,
          46.5833
        ]
      },
      "type": "Feature",
      "properties": {
        "hierarchy": [
          "tgn:2779458",
          "tgn:1000001",
          "tgn:7012149",
          "tgn:2000975",
          "tgn:7007520",
          "tgn:7029392"
        ],
        "placetype": [
          "aat:300008680"
        ],
        "id": 2779458,
        "name:xx": "Wolf Lake"
      }
    },
    {
      "geometry": {
        "type": "Point",
        "coordinates": [
          -84.1833,
          42.05
        ]
      },
      "type": "Feature",
      "properties": {
        "hierarchy": [
          "tgn:2779459",
          "tgn:1000001",
          "tgn:7012149",
          "tgn:1002588",
          "tgn:7007520",
          "tgn:7029392"
        ],
        "placetype": [
          "aat:300008680"
        ],
        "id": 2779459,
        "name:xx": "Wolf Lake"
      }
    }
  ]
}
