{
  "geometry": {
    "type": "Point",
    "coordinates": [
      -111.1833,
      52.9333
    ]
  },
  "type": "Feature",
  "properties": {
    "hierarchy": [
      "tgn:1013207",
      "tgn:7005694",
      "tgn:7005685",
      "tgn:1000001",
      "tgn:7029392"
    ],
    "placetype": [
      "aat:300008347"
    ],
    "id": 1013207,
    "name:xx": "Irma"
  }
}
