{
  "geometry": {
    "type": "Point",
    "coordinates": [
      24.833,
      -17.55
    ]
  },
  "type": "Feature",
  "properties": {
    "hierarchy": [
      "tgn:7593205",
      "tgn:7001242",
      "tgn:7030582",
      "tgn:1000198",
      "tgn:7029392"
    ],
    "placetype": [
      "aat:300008347"
    ],
    "id": 7593205,
    "name:xx": "Luhonono"
  }
}
