{
  "geometry": {
    "type": "Point",
    "coordinates": [
      -105.5667,
      40.7833
    ]
  },
  "type": "Feature",
  "properties": {
    "hierarchy": [
      "tgn:2673091",
      "tgn:1000001",
      "tgn:7012149",
      "tgn:2000226",
      "tgn:7007158",
      "tgn:7029392"
    ],
    "placetype": [
      "aat:300006191"
    ],
    "id": 2673091,
    "name:xx": "Snake Lake"
  }
}
