{
  "geometry": {
    "type": "Point",
    "coordinates": [
      -94.8167,
      34.1833
    ]
  },
  "type": "Feature",
  "properties": {
    "hierarchy": [
      "tgn:2677473",
      "tgn:1000001",
      "tgn:7012149",
      "tgn:2001667",
      "tgn:7007707",
      "tgn:7029392"
    ],
    "placetype": [
      "aat:300008706"
    ],
    "id": 2677473,
    "name:xx": "South Cedar Creek"
  }
}
