{
  "geometry": {
    "type": "Point",
    "coordinates": [
      30.983333,
      27.25
    ]
  },
  "type": "Feature",
  "properties": {
    "hierarchy": [
      "tgn:7527545",
      "tgn:7001242",
      "tgn:7016833",
      "tgn:1001114",
      "tgn:7029392"
    ],
    "placetype": [
      "aat:300005926"
    ],
    "name:en": "Sīdī Sulţān",
    "id": 7527545
  }
}
