{
  "geometry": {
    "type": "Point",
    "coordinates": [
      -82.4667,
      37.85
    ]
  },
  "type": "Feature",
  "properties": {
    "hierarchy": [
      "tgn:2168055",
      "tgn:1000001",
      "tgn:7012149",
      "tgn:2000824",
      "tgn:7007255",
      "tgn:7029392"
    ],
    "placetype": [
      "aat:300008706"
    ],
    "id": 2168055,
    "name:xx": "Big Elk Creek"
  }
}
