{
  "type": "FeatureCollection",
  "features": [
    {
      "geometry": {
        "type": "Point",
        "coordinates": [
          6.9,
          49.883333
        ]
      },
      "type": "Feature",
      "properties": {
        "hierarchy": [
          "tgn:7192530",
          "tgn:1000003",
          "tgn:7003682",
          "tgn:7000084",
          "tgn:7029392"
        ],
        "placetype": [
          "aat:300008347"
        ],
        "id": 7192530,
        "name:xx": "Ferres"
      }
    },
    {
      "geometry": {
        "type": "Point",
        "coordinates": [
          10.333333,
          54.416667
        ]
      },
      "type": "Feature",
      "properties": {
        "hierarchy": [
          "tgn:7192531",
          "tgn:1000003",
          "tgn:7003688",
          "tgn:7000084",
          "tgn:7029392"
        ],
        "placetype": [
          "aat:300000206"
        ],
        "id": 7192531,
        "name:xx": "Fernwisch"
      }
    },
    {
      "geometry": {
        "type": "Point",
        "coordinates": [
          7.45,
          50.6
        ]
      },
      "type": "Feature",
      "properties": {
        "hierarchy": [
          "tgn:7192532",
          "tgn:1000003",
          "tgn:7003682",
          "tgn:7000084",
          "tgn:7029392"
        ],
        "placetype": [
          "aat:300008347"
        ],
        "id": 7192532,
        "name:xx": "Fernthal"
      }
    },
    {
      "geometry": {
        "type": "Point",
        "coordinates": [
          10.2,
          53.583333
        ]
      },
      "type": "Feature",
      "properties": {
        "hierarchy": [
          "tgn:7192533",
          "tgn:1000003",
          "tgn:7003673",
          "tgn:7000084",
          "tgn:7029392"
        ],
        "placetype": [
          "aat:300008347"
        ],
        "id": 7192533,
        "name:xx": "Fernsicht"
      }
    },
    {
      "geometry": {
        "type": "Point",
        "coordinates": [
          9.7,
          53.95
        ]
      },
      "type": "Feature",
      "properties": {
        "hierarchy": [
          "tgn:7192534",
          "tgn:1000003",
          "tgn:7003688",
          "tgn:7000084",
          "tgn:7029392"
        ],
        "placetype": [
          "aat:300000206"
        ],
        "id": 7192534,
        "name:xx": "Fernsicht"
      }
    },
    {
      "geometry": {
        "type": "Point",
        "coordinates": [
          12.05,
          51.7
        ]
      },
      "type": "Feature",
      "properties": {
        "hierarchy": [
          "tgn:7192535",
          "tgn:1000003",
          "tgn:7003687",
          "tgn:7000084",
          "tgn:7029392"
        ],
        "placetype": [
          "aat:300008347"
        ],
        "id": 7192535,
        "name:xx": "Fernsdorf"
      }
    },
    {
      "geometry": {
        "type": "Point",
        "coordinates": [
          12.966667,
          49.033333
        ]
      },
      "type": "Feature",
      "properties": {
        "hierarchy": [
          "tgn:7192536",
          "tgn:7003669",
          "tgn:1000003",
          "tgn:7000084",
          "tgn:7029392"
        ],
        "placetype": [
          "aat:300008347"
        ],
        "id": 7192536,
        "name:xx": "Fernsdorf"
      }
    },
    {
      "geometry": {
        "type": "Point",
        "coordinates": [
          12.583333,
          48.1
        ]
      },
      "type": "Feature",
      "properties": {
        "hierarchy": [
          "tgn:7192537",
          "tgn:7003669",
          "tgn:1000003",
          "tgn:7000084",
          "tgn:7029392"
        ],
        "placetype": [
          "aat:300000206"
        ],
        "id": 7192537,
        "name:xx": "Fernschachen"
      }
    },
    {
      "geometry": {
        "type": "Point",
        "coordinates": [
          7.583333,
          52.283333
        ]
      },
      "type": "Feature",
      "properties": {
        "hierarchy": [
          "tgn:7192538",
          "tgn:1000003",
          "tgn:7003677",
          "tgn:7000084",
          "tgn:7029392"
        ],
        "placetype": [
          "aat:300008347"
        ],
        "id": 7192538,
        "name:xx": "Fernrodde"
      }
    },
    {
      "geometry": {
        "type": "Point",
        "coordinates": [
          11.333333,
          49.95
        ]
      },
      "type": "Feature",
      "properties": {
        "hierarchy": [
          "tgn:7192539",
          "tgn:7003669",
          "tgn:1000003",
          "tgn:7000084",
          "tgn:7029392"
        ],
        "placetype": [
          "aat:300008347"
        ],
        "id": 7192539,
        "name:xx": "Fernreuth"
      }
    }
  ]
}
