{
  "geometry": {
    "type": "Point",
    "coordinates": [
      21.95,
      47.6833
    ]
  },
  "type": "Feature",
  "properties": {
    "hierarchy": [
      "tgn:1042423",
      "tgn:1000385",
      "tgn:1000003",
      "tgn:7006278",
      "tgn:7029392"
    ],
    "placetype": [
      "aat:300008347"
    ],
    "id": 1042423,
    "name:xx": "Nyíradony"
  }
}
