{
  "geometry": {
    "type": "Point",
    "coordinates": [
      -94.85,
      49.3167
    ]
  },
  "type": "Feature",
  "properties": {
    "hierarchy": [
      "tgn:2211477",
      "tgn:1000001",
      "tgn:7012149",
      "tgn:7021313",
      "tgn:7007521",
      "tgn:7029392"
    ],
    "placetype": [
      "aat:300008678"
    ],
    "id": 2211477,
    "name:xx": "Butterfield Harbor"
  }
}
