{
  "geometry": {
    "type": "Point",
    "coordinates": [
      -114.7833,
      42.9333
    ]
  },
  "type": "Feature",
  "properties": {
    "hierarchy": [
      "tgn:2489318",
      "tgn:1000001",
      "tgn:7012149",
      "tgn:2000475",
      "tgn:7007250",
      "tgn:7029392"
    ],
    "placetype": [
      "aat:300008707"
    ],
    "id": 2489318,
    "name:xx": "Malad River"
  }
}
