{
  "geometry": {
    "type": "Point",
    "coordinates": [
      -105.85,
      36.0833
    ]
  },
  "type": "Feature",
  "properties": {
    "hierarchy": [
      "tgn:2135679",
      "tgn:1000001",
      "tgn:7012149",
      "tgn:2001449",
      "tgn:7007566",
      "tgn:7029392"
    ],
    "placetype": [
      "aat:300008699"
    ],
    "id": 2135679,
    "name:xx": "Apache del Ojito, Cañada del"
  }
}
