{
  "type": "FeatureCollection",
  "features": [
    {
      "geometry": {
        "type": "Point",
        "coordinates": [
          -72.6833,
          43.65
        ]
      },
      "type": "Feature",
      "properties": {
        "hierarchy": [
          "tgn:2233830",
          "tgn:1000001",
          "tgn:2002136",
          "tgn:7012149",
          "tgn:7007828",
          "tgn:7029392"
        ],
        "placetype": [
          "aat:300008347"
        ],
        "id": 2233830,
        "name:xx": "Chateauguay"
      }
    },
    {
      "geometry": {
        "type": "Point",
        "coordinates": [
          -83.8333,
          34.5833
        ]
      },
      "type": "Feature",
      "properties": {
        "hierarchy": [
          "tgn:2233831",
          "tgn:1000001",
          "tgn:7012149",
          "tgn:2000445",
          "tgn:7007248",
          "tgn:7029392"
        ],
        "placetype": [
          "aat:300008706"
        ],
        "id": 2233831,
        "name:xx": "Chateen Creek"
      }
    },
    {
      "geometry": {
        "type": "Point",
        "coordinates": [
          -150.2667,
          60.5
        ]
      },
      "type": "Feature",
      "properties": {
        "hierarchy": [
          "tgn:2233832",
          "tgn:7006450",
          "tgn:1000001",
          "tgn:7019698",
          "tgn:7012149",
          "tgn:7029392"
        ],
        "placetype": [
          "aat:300008680"
        ],
        "id": 2233832,
        "name:xx": "Chatelain Lake"
      }
    },
    {
      "geometry": {
        "type": "Point",
        "coordinates": [
          -82.85,
          33.9
        ]
      },
      "type": "Feature",
      "properties": {
        "hierarchy": [
          "tgn:2233833",
          "tgn:1000001",
          "tgn:7012149",
          "tgn:2000448",
          "tgn:7007248",
          "tgn:7029392"
        ],
        "placetype": [
          "aat:300008347"
        ],
        "id": 2233833,
        "name:xx": "Chatfield"
      }
    },
    {
      "geometry": {
        "type": "Point",
        "coordinates": [
          -75.1333,
          39.4167
        ]
      },
      "type": "Feature",
      "properties": {
        "hierarchy": [
          "tgn:2233834",
          "tgn:1002309",
          "tgn:1000001",
          "tgn:7012149",
          "tgn:7007565",
          "tgn:7029392"
        ],
        "placetype": [
          "aat:300008699"
        ],
        "id": 2233834,
        "name:xx": "Chatfield Branch"
      }
    },
    {
      "geometry": {
        "type": "Point",
        "coordinates": [
          -105.4667,
          32.5333
        ]
      },
      "type": "Feature",
      "properties": {
        "hierarchy": [
          "tgn:2233835",
          "tgn:1000001",
          "tgn:7012149",
          "tgn:2001447",
          "tgn:7007566",
          "tgn:7029392"
        ],
        "placetype": [
          "aat:300008761"
        ],
        "id": 2233835,
        "name:xx": "Chatfield Canyon"
      }
    },
    {
      "geometry": {
        "type": "Point",
        "coordinates": [
          -73.9333,
          43.1
        ]
      },
      "type": "Feature",
      "properties": {
        "hierarchy": [
          "tgn:2233836",
          "tgn:1000001",
          "tgn:7012149",
          "tgn:1002871",
          "tgn:7007568",
          "tgn:7029392"
        ],
        "placetype": [
          "aat:300008347"
        ],
        "id": 2233836,
        "name:xx": "Chatfield Corner"
      }
    },
    {
      "geometry": {
        "type": "Point",
        "coordinates": [
          -116.6,
          47.5333
        ]
      },
      "type": "Feature",
      "properties": {
        "hierarchy": [
          "tgn:2233837",
          "tgn:1000001",
          "tgn:7012149",
          "tgn:2000479",
          "tgn:7007250",
          "tgn:7029392"
        ],
        "placetype": [
          "aat:300008706"
        ],
        "id": 2233837,
        "name:xx": "Chatfield Creek"
      }
    },
    {
      "geometry": {
        "type": "Point",
        "coordinates": [
          -72.6,
          41.3833
        ]
      },
      "type": "Feature",
      "properties": {
        "hierarchy": [
          "tgn:2233838",
          "tgn:1000001",
          "tgn:1002664",
          "tgn:7012149",
          "tgn:7007159",
          "tgn:7029392"
        ],
        "placetype": [
          "aat:300008699"
        ],
        "id": 2233838,
        "name:xx": "Chatfield Hollow Brook"
      }
    }
  ]
}
