{
  "geometry": {
    "type": "Point",
    "coordinates": [
      120.2686,
      23.1686
    ]
  },
  "type": "Feature",
  "properties": {
    "hierarchy": [
      "tgn:7487401",
      "tgn:1000004",
      "tgn:7490934",
      "tgn:1000141",
      "tgn:7029392"
    ],
    "placetype": [
      "aat:300008347"
    ],
    "id": 7487401,
    "name:xx": "Xidiliao"
  }
}
