{
  "geometry": {
    "type": "Point",
    "coordinates": [
      12.75,
      51.25
    ]
  },
  "type": "Feature",
  "properties": {
    "hierarchy": [
      "tgn:7215007",
      "tgn:1000003",
      "tgn:7003685",
      "tgn:7000084",
      "tgn:7029392"
    ],
    "placetype": [
      "aat:300008347"
    ],
    "id": 7215007,
    "name:xx": "Böhlen"
  }
}
