{
  "geometry": {
    "type": "Point",
    "coordinates": [
      -109.6167,
      45.4833
    ]
  },
  "type": "Feature",
  "properties": {
    "hierarchy": [
      "tgn:2276680",
      "tgn:1000001",
      "tgn:7012149",
      "tgn:2001307",
      "tgn:7007524",
      "tgn:7029392"
    ],
    "placetype": [
      "aat:300008706"
    ],
    "id": 2276680,
    "name:xx": "Davidson Creek"
  }
}
