{
  "type": "FeatureCollection",
  "features": [
    {
      "geometry": {
        "type": "Point",
        "coordinates": [
          -107.05,
          30.783333
        ]
      },
      "type": "Feature",
      "properties": {
        "hierarchy": [
          "tgn:7433851",
          "tgn:7005581",
          "tgn:1000001",
          "tgn:7005560",
          "tgn:7029392"
        ],
        "placetype": [
          "aat:300000241"
        ],
        "id": 7433851,
        "name:xx": "Rancho Veracruz"
      }
    },
    {
      "geometry": {
        "type": "Point",
        "coordinates": [
          -100.716667,
          25.25
        ]
      },
      "type": "Feature",
      "properties": {
        "hierarchy": [
          "tgn:7433852",
          "tgn:1001853",
          "tgn:1000001",
          "tgn:7005560",
          "tgn:7029392"
        ],
        "placetype": [
          "aat:300000241"
        ],
        "id": 7433852,
        "name:xx": "Rancho Veracruz"
      }
    },
    {
      "geometry": {
        "type": "Point",
        "coordinates": [
          -107.05,
          30.75
        ]
      },
      "type": "Feature",
      "properties": {
        "hierarchy": [
          "tgn:7433853",
          "tgn:7005581",
          "tgn:1000001",
          "tgn:7005560",
          "tgn:7029392"
        ],
        "placetype": [
          "aat:300008795"
        ],
        "id": 7433853,
        "name:xx": "Veracruz, Cerro de"
      }
    },
    {
      "geometry": {
        "type": "Point",
        "coordinates": [
          -112.358056,
          31.447222
        ]
      },
      "type": "Feature",
      "properties": {
        "hierarchy": [
          "tgn:7433854",
          "tgn:1000001",
          "tgn:1001960",
          "tgn:7005560",
          "tgn:7029392"
        ],
        "placetype": [
          "aat:300008347"
        ],
        "id": 7433854,
        "name:xx": "El Veracruz"
      }
    },
    {
      "geometry": {
        "type": "Point",
        "coordinates": [
          -97.966667,
          26.033333
        ]
      },
      "type": "Feature",
      "properties": {
        "hierarchy": [
          "tgn:7433855",
          "tgn:1000001",
          "tgn:7005597",
          "tgn:7005560",
          "tgn:7029392"
        ],
        "placetype": [
          "aat:300008347"
        ],
        "id": 7433855,
        "name:xx": "Veracruz"
      }
    },
    {
      "geometry": {
        "type": "Point",
        "coordinates": [
          -103.921111,
          24.0175
        ]
      },
      "type": "Feature",
      "properties": {
        "hierarchy": [
          "tgn:7433856",
          "tgn:7005583",
          "tgn:1000001",
          "tgn:7005560",
          "tgn:7029392"
        ],
        "placetype": [
          "aat:300008347"
        ],
        "id": 7433856,
        "name:xx": "Veracruz"
      }
    },
    {
      "geometry": {
        "type": "Point",
        "coordinates": [
          -98.733333,
          23.433333
        ]
      },
      "type": "Feature",
      "properties": {
        "hierarchy": [
          "tgn:7433857",
          "tgn:1000001",
          "tgn:7005597",
          "tgn:7005560",
          "tgn:7029392"
        ],
        "placetype": [
          "aat:300008347"
        ],
        "id": 7433857,
        "name:xx": "Veracruz"
      }
    },
    {
      "geometry": {
        "type": "Point",
        "coordinates": [
          -92.5,
          15.3
        ]
      },
      "type": "Feature",
      "properties": {
        "hierarchy": [
          "tgn:7433859",
          "tgn:7005580",
          "tgn:1000001",
          "tgn:7005560",
          "tgn:7029392"
        ],
        "placetype": [
          "aat:300008347"
        ],
        "id": 7433859,
        "name:xx": "Veracruz"
      }
    }
  ]
}
