{
  "geometry": {
    "type": "Point",
    "coordinates": [
      78.326111,
      17.943611
    ]
  },
  "type": "Feature",
  "properties": {
    "hierarchy": [
      "tgn:7567743",
      "tgn:1001828",
      "tgn:1000004",
      "tgn:7000198",
      "tgn:7029392"
    ],
    "placetype": [
      "aat:300008347"
    ],
    "name:en": "Rāmāyanpalli",
    "id": 7567743
  }
}
