{
  "type": "FeatureCollection",
  "features": [
    {
      "geometry": {
        "type": "Point",
        "coordinates": [
          -105.516667,
          23.066667
        ]
      },
      "type": "Feature",
      "properties": {
        "hierarchy": [
          "tgn:7396340",
          "tgn:1000001",
          "tgn:7005595",
          "tgn:7005560",
          "tgn:7029392"
        ],
        "placetype": [
          "aat:300008347"
        ],
        "id": 7396340,
        "name:xx": "Santa Rita"
      }
    },
    {
      "geometry": {
        "type": "Point",
        "coordinates": [
          -99.033333,
          22.566667
        ]
      },
      "type": "Feature",
      "properties": {
        "hierarchy": [
          "tgn:7396341",
          "tgn:1000001",
          "tgn:7005597",
          "tgn:7005560",
          "tgn:7029392"
        ],
        "placetype": [
          "aat:300008347"
        ],
        "id": 7396341,
        "name:xx": "Santa Rita"
      }
    },
    {
      "geometry": {
        "type": "Point",
        "coordinates": [
          -100.85,
          22.116667
        ]
      },
      "type": "Feature",
      "properties": {
        "hierarchy": [
          "tgn:7396342",
          "tgn:1000001",
          "tgn:7005594",
          "tgn:7005560",
          "tgn:7029392"
        ],
        "placetype": [
          "aat:300008347"
        ],
        "id": 7396342,
        "name:xx": "Santa Rita"
      }
    },
    {
      "geometry": {
        "type": "Point",
        "coordinates": [
          -99.85,
          21.983333
        ]
      },
      "type": "Feature",
      "properties": {
        "hierarchy": [
          "tgn:7396343",
          "tgn:1000001",
          "tgn:7005594",
          "tgn:7005560",
          "tgn:7029392"
        ],
        "placetype": [
          "aat:300008347"
        ],
        "id": 7396343,
        "name:xx": "Santa Rita"
      }
    },
    {
      "geometry": {
        "type": "Point",
        "coordinates": [
          -103.516667,
          21.916667
        ]
      },
      "type": "Feature",
      "properties": {
        "hierarchy": [
          "tgn:7396344",
          "tgn:7005586",
          "tgn:1000001",
          "tgn:7005560",
          "tgn:7029392"
        ],
        "placetype": [
          "aat:300008347"
        ],
        "id": 7396344,
        "name:xx": "Santa Rita"
      }
    },
    {
      "geometry": {
        "type": "Point",
        "coordinates": [
          -98.866667,
          21.866667
        ]
      },
      "type": "Feature",
      "properties": {
        "hierarchy": [
          "tgn:7396345",
          "tgn:1000001",
          "tgn:7005594",
          "tgn:7005560",
          "tgn:7029392"
        ],
        "placetype": [
          "aat:300008347"
        ],
        "id": 7396345,
        "name:xx": "Santa Rita"
      }
    },
    {
      "geometry": {
        "type": "Point",
        "coordinates": [
          -88.966667,
          21.15
        ]
      },
      "type": "Feature",
      "properties": {
        "hierarchy": [
          "tgn:7396346",
          "tgn:1000001",
          "tgn:7005600",
          "tgn:7005560",
          "tgn:7029392"
        ],
        "placetype": [
          "aat:300008347"
        ],
        "id": 7396346,
        "name:xx": "Santa Rita"
      }
    },
    {
      "geometry": {
        "type": "Point",
        "coordinates": [
          -89.233333,
          21.016667
        ]
      },
      "type": "Feature",
      "properties": {
        "hierarchy": [
          "tgn:7396347",
          "tgn:1000001",
          "tgn:7005600",
          "tgn:7005560",
          "tgn:7029392"
        ],
        "placetype": [
          "aat:300008347"
        ],
        "id": 7396347,
        "name:xx": "Santa Rita"
      }
    },
    {
      "geometry": {
        "type": "Point",
        "coordinates": [
          -89.9,
          20.983333
        ]
      },
      "type": "Feature",
      "properties": {
        "hierarchy": [
          "tgn:7396348",
          "tgn:1000001",
          "tgn:7005600",
          "tgn:7005560",
          "tgn:7029392"
        ],
        "placetype": [
          "aat:300008347"
        ],
        "id": 7396348,
        "name:xx": "Santa Rita"
      }
    },
    {
      "geometry": {
        "type": "Point",
        "coordinates": [
          -101.716667,
          20.933333
        ]
      },
      "type": "Feature",
      "properties": {
        "hierarchy": [
          "tgn:7396349",
          "tgn:7005584",
          "tgn:1000001",
          "tgn:7005560",
          "tgn:7029392"
        ],
        "placetype": [
          "aat:300008347"
        ],
        "id": 7396349,
        "name:xx": "Santa Rita"
      }
    }
  ]
}
