{
  "geometry": {
    "type": "Point",
    "coordinates": [
      -91.8167,
      36.4833
    ]
  },
  "type": "Feature",
  "properties": {
    "hierarchy": [
      "tgn:2540061",
      "tgn:1000001",
      "tgn:7016172",
      "tgn:7012149",
      "tgn:2000129",
      "tgn:7029392"
    ],
    "placetype": [
      "aat:300008699"
    ],
    "id": 2540061,
    "name:xx": "Newcomb Branch"
  }
}
