{
  "geometry": {
    "type": "Point",
    "coordinates": [
      122.3167,
      14.2667
    ]
  },
  "type": "Feature",
  "properties": {
    "hierarchy": [
      "tgn:1112652",
      "tgn:1000004",
      "tgn:7016720",
      "tgn:1000135",
      "tgn:7029392"
    ],
    "placetype": [
      "aat:300132316"
    ],
    "id": 1112652,
    "name:xx": "Basiad Bay"
  }
}
