{
  "geometry": {
    "type": "Point",
    "coordinates": [
      42.766,
      38.55
    ]
  },
  "type": "Feature",
  "properties": {
    "hierarchy": [
      "tgn:7593986",
      "tgn:1000004",
      "tgn:7029392"
    ],
    "placetype": [
      "aat:300387356",
      "aat:300235096"
    ],
    "id": 7593986,
    "name:xx": "Urartu"
  }
}
