{
  "geometry": {
    "type": "Point",
    "coordinates": [
      -86.9667,
      40.0167
    ]
  },
  "type": "Feature",
  "properties": {
    "hierarchy": [
      "tgn:2034226",
      "tgn:1000001",
      "tgn:7012149",
      "tgn:2000547",
      "tgn:7007252",
      "tgn:7029392"
    ],
    "placetype": [
      "aat:300008347"
    ],
    "id": 2034226,
    "name:xx": "Yountsville"
  }
}
