{
  "geometry": {
    "type": "Point",
    "coordinates": [
      -76.75,
      45.2667
    ]
  },
  "type": "Feature",
  "properties": {
    "hierarchy": [
      "tgn:1115765",
      "tgn:7005685",
      "tgn:1000001",
      "tgn:7013154",
      "tgn:7029392"
    ],
    "placetype": [
      "aat:300008680"
    ],
    "id": 1115765,
    "name:xx": "Calabogie Lake"
  }
}
