{
  "geometry": {
    "type": "Point",
    "coordinates": [
      -150.1833,
      67.4667
    ]
  },
  "type": "Feature",
  "properties": {
    "hierarchy": [
      "tgn:2352792",
      "tgn:7006450",
      "tgn:1000001",
      "tgn:7012149",
      "tgn:2124014",
      "tgn:7029392"
    ],
    "placetype": [
      "aat:300008798"
    ],
    "id": 2352792,
    "name:xx": "Gobblers Knob"
  }
}
