{
  "geometry": {
    "type": "Point",
    "coordinates": [
      -120.8333,
      39.7167
    ]
  },
  "type": "Feature",
  "properties": {
    "hierarchy": [
      "tgn:2393649",
      "tgn:1000001",
      "tgn:7012149",
      "tgn:7007157",
      "tgn:1002894",
      "tgn:7029392"
    ],
    "placetype": [
      "aat:300008761"
    ],
    "id": 2393649,
    "name:xx": "Hog Gulch"
  }
}
