{
  "geometry": {
    "type": "Point",
    "coordinates": [
      -111.3333,
      35.0167
    ]
  },
  "type": "Feature",
  "properties": {
    "hierarchy": [
      "tgn:2172810",
      "tgn:1000001",
      "tgn:7006451",
      "tgn:2000092",
      "tgn:7012149",
      "tgn:7029392"
    ],
    "placetype": [
      "aat:300008697"
    ],
    "id": 2172810,
    "name:xx": "Billy Back Spring"
  }
}
