{
  "type": "FeatureCollection",
  "features": [
    {
      "geometry": {
        "type": "Point",
        "coordinates": [
          -89.8333,
          41.3667
        ]
      },
      "type": "Feature",
      "properties": {
        "hierarchy": [
          "tgn:2029101",
          "tgn:1000001",
          "tgn:2000497",
          "tgn:7012149",
          "tgn:7007251",
          "tgn:7029392"
        ],
        "placetype": [
          "aat:300008347"
        ],
        "id": 2029101,
        "name:xx": "Mineral"
      }
    },
    {
      "geometry": {
        "type": "Point",
        "coordinates": [
          -89.3,
          40.4333
        ]
      },
      "type": "Feature",
      "properties": {
        "hierarchy": [
          "tgn:2029102",
          "tgn:1000001",
          "tgn:7012149",
          "tgn:2000533",
          "tgn:7007251",
          "tgn:7029392"
        ],
        "placetype": [
          "aat:300008347"
        ],
        "id": 2029102,
        "name:xx": "Minier"
      }
    },
    {
      "geometry": {
        "type": "Point",
        "coordinates": [
          -89.0333,
          40.9
        ]
      },
      "type": "Feature",
      "properties": {
        "hierarchy": [
          "tgn:2029103",
          "tgn:1000001",
          "tgn:7012149",
          "tgn:1003035",
          "tgn:7007251",
          "tgn:7029392"
        ],
        "placetype": [
          "aat:300008347"
        ],
        "id": 2029103,
        "name:xx": "Minonk"
      }
    },
    {
      "geometry": {
        "type": "Point",
        "coordinates": [
          -88.25,
          41.45
        ]
      },
      "type": "Feature",
      "properties": {
        "hierarchy": [
          "tgn:2029104",
          "tgn:1000001",
          "tgn:7012149",
          "tgn:1002430",
          "tgn:7007251",
          "tgn:7029392"
        ],
        "placetype": [
          "aat:300008347"
        ],
        "id": 2029104,
        "name:xx": "Minooka"
      }
    },
    {
      "geometry": {
        "type": "Point",
        "coordinates": [
          -88.15,
          40.0833
        ]
      },
      "type": "Feature",
      "properties": {
        "hierarchy": [
          "tgn:2029105",
          "tgn:1000001",
          "tgn:1002253",
          "tgn:7012149",
          "tgn:7007251",
          "tgn:7029392"
        ],
        "placetype": [
          "aat:300387016"
        ],
        "id": 2029105,
        "name:xx": "Mira"
      }
    },
    {
      "geometry": {
        "type": "Point",
        "coordinates": [
          -90.0833,
          38.75
        ]
      },
      "type": "Feature",
      "properties": {
        "hierarchy": [
          "tgn:2029108",
          "tgn:1000001",
          "tgn:7012149",
          "tgn:1002622",
          "tgn:7007251",
          "tgn:7029392"
        ],
        "placetype": [
          "aat:300008347"
        ],
        "id": 2029108,
        "name:xx": "Mitchell"
      }
    }
  ]
}
