{
  "geometry": {
    "type": "Point",
    "coordinates": [
      -87.9333,
      42.1667
    ]
  },
  "type": "Feature",
  "properties": {
    "hierarchy": [
      "tgn:2026351",
      "tgn:1000001",
      "tgn:7012149",
      "tgn:7013855",
      "tgn:7007251",
      "tgn:7029392"
    ],
    "placetype": [
      "aat:300008347"
    ],
    "id": 2026351,
    "name:xx": "Aptakisic"
  }
}
