{
  "type": "FeatureCollection",
  "features": [
    {
      "geometry": {
        "type": "Point",
        "coordinates": [
          -69.45,
          -18.833333
        ]
      },
      "type": "Feature",
      "properties": {
        "hierarchy": [
          "tgn:7281640",
          "tgn:7002464",
          "tgn:1000049",
          "tgn:1000002",
          "tgn:7029392"
        ],
        "placetype": [
          "aat:300008347"
        ],
        "id": 7281640,
        "name:xx": "Sucuna"
      }
    },
    {
      "geometry": {
        "type": "Point",
        "coordinates": [
          -70.083333,
          -54.366667
        ]
      },
      "type": "Feature",
      "properties": {
        "hierarchy": [
          "tgn:7281641",
          "tgn:1001702",
          "tgn:1000049",
          "tgn:1000002",
          "tgn:7029392"
        ],
        "placetype": [
          "aat:300008676"
        ],
        "id": 7281641,
        "name:xx": "Sucio, Seno"
      }
    },
    {
      "geometry": {
        "type": "Point",
        "coordinates": [
          -72.616667,
          -43.45
        ]
      },
      "type": "Feature",
      "properties": {
        "hierarchy": [
          "tgn:7281642",
          "tgn:1001699",
          "tgn:1000049",
          "tgn:1000002",
          "tgn:7029392"
        ],
        "placetype": [
          "aat:300008699"
        ],
        "id": 7281642,
        "name:xx": "Sucio, Río"
      }
    },
    {
      "geometry": {
        "type": "Point",
        "coordinates": [
          -74.883333,
          -45.633333
        ]
      },
      "type": "Feature",
      "properties": {
        "hierarchy": [
          "tgn:7281643",
          "tgn:1001623",
          "tgn:1000049",
          "tgn:1000002",
          "tgn:7029392"
        ],
        "placetype": [
          "aat:300387026"
        ],
        "id": 7281643,
        "name:xx": "Sucio, Paso"
      }
    },
    {
      "geometry": {
        "type": "Point",
        "coordinates": [
          -72.316667,
          -48.216667
        ]
      },
      "type": "Feature",
      "properties": {
        "hierarchy": [
          "tgn:7281644",
          "tgn:1001623",
          "tgn:1000049",
          "tgn:1000002",
          "tgn:7029392"
        ],
        "placetype": [
          "aat:300008699"
        ],
        "id": 7281644,
        "name:xx": "Sucio, Arroyo"
      }
    },
    {
      "geometry": {
        "type": "Point",
        "coordinates": [
          -69.783333,
          -19.266667
        ]
      },
      "type": "Feature",
      "properties": {
        "hierarchy": [
          "tgn:7281645",
          "tgn:7002464",
          "tgn:1000049",
          "tgn:1000002",
          "tgn:7029392"
        ],
        "placetype": [
          "aat:300008347"
        ],
        "id": 7281645,
        "name:xx": "Suca Alto"
      }
    },
    {
      "geometry": {
        "type": "Point",
        "coordinates": [
          -70,
          -19.2
        ]
      },
      "type": "Feature",
      "properties": {
        "hierarchy": [
          "tgn:7281646",
          "tgn:7002464",
          "tgn:1000049",
          "tgn:1000002",
          "tgn:7029392"
        ],
        "placetype": [
          "aat:300266554",
          "aat:300008699"
        ],
        "id": 7281646,
        "name:xx": "Suca, Quebrada de"
      }
    },
    {
      "geometry": {
        "type": "Point",
        "coordinates": [
          -69.833333,
          -19.2
        ]
      },
      "type": "Feature",
      "properties": {
        "hierarchy": [
          "tgn:7281647",
          "tgn:7002464",
          "tgn:1000049",
          "tgn:1000002",
          "tgn:7029392"
        ],
        "placetype": [
          "aat:300008805"
        ],
        "id": 7281647,
        "name:xx": "Suca, Pampa de"
      }
    },
    {
      "geometry": {
        "type": "Point",
        "coordinates": [
          -69.8,
          -19.3
        ]
      },
      "type": "Feature",
      "properties": {
        "hierarchy": [
          "tgn:7281648",
          "tgn:7002464",
          "tgn:1000049",
          "tgn:1000002",
          "tgn:7029392"
        ],
        "placetype": [
          "aat:300387033"
        ],
        "id": 7281648,
        "name:xx": "Suca"
      }
    },
    {
      "geometry": {
        "type": "Point",
        "coordinates": [
          -69.85,
          -19.25
        ]
      },
      "type": "Feature",
      "properties": {
        "hierarchy": [
          "tgn:7281649",
          "tgn:7002464",
          "tgn:1000049",
          "tgn:1000002",
          "tgn:7029392"
        ],
        "placetype": [
          "aat:300008347",
          "aat:300387200"
        ],
        "id": 7281649,
        "name:xx": "Suca"
      }
    }
  ]
}
