{
  "geometry": {
    "type": "Point",
    "coordinates": [
      115.25,
      4.9167
    ]
  },
  "type": "Feature",
  "properties": {
    "hierarchy": [
      "tgn:1082967",
      "tgn:7000316",
      "tgn:1001952",
      "tgn:1000004",
      "tgn:1000128",
      "tgn:7029392"
    ],
    "placetype": [
      "aat:300008347"
    ],
    "id": 1082967,
    "name:xx": "Sundar"
  }
}
