{
  "geometry": {
    "type": "Point",
    "coordinates": [
      -146.5833,
      62.1833
    ]
  },
  "type": "Feature",
  "properties": {
    "hierarchy": [
      "tgn:2469926",
      "tgn:7006450",
      "tgn:1000001",
      "tgn:7012149",
      "tgn:2000086",
      "tgn:7029392"
    ],
    "placetype": [
      "aat:300008680"
    ],
    "id": 2469926,
    "name:xx": "Loon Lake"
  }
}
