{
  "geometry": {
    "type": "Point",
    "coordinates": [
      26.721667,
      37.34
    ]
  },
  "type": "Feature",
  "properties": {
    "hierarchy": [
      "tgn:7231471",
      "tgn:7011330",
      "tgn:7002674",
      "tgn:1000003",
      "tgn:1000074",
      "tgn:7029392"
    ],
    "placetype": [
      "aat:300008791"
    ],
    "id": 7231471,
    "name:xx": "Manóli, Vrachonisídes"
  }
}
