{
  "geometry": {
    "type": "Point",
    "coordinates": [
      -115.6333,
      32.95
    ]
  },
  "type": "Feature",
  "properties": {
    "hierarchy": [
      "tgn:2619102",
      "tgn:1000001",
      "tgn:7012149",
      "tgn:2000182",
      "tgn:7007157",
      "tgn:7029392"
    ],
    "placetype": [
      "aat:300006075"
    ],
    "id": 2619102,
    "name:xx": "Riley Canal"
  }
}
