{
  "geometry": {
    "type": "Point",
    "coordinates": [
      -114.9333,
      43.1833
    ]
  },
  "type": "Feature",
  "properties": {
    "hierarchy": [
      "tgn:2676287",
      "tgn:1000001",
      "tgn:7012149",
      "tgn:2000475",
      "tgn:7007250",
      "tgn:7029392"
    ],
    "placetype": [
      "aat:300008706"
    ],
    "id": 2676287,
    "name:xx": "Sourdough Creek"
  }
}
