{
  "geometry": {
    "type": "Point",
    "coordinates": [
      -95.75,
      43.0167
    ]
  },
  "type": "Feature",
  "properties": {
    "hierarchy": [
      "tgn:2424569",
      "tgn:1000001",
      "tgn:7012149",
      "tgn:2000631",
      "tgn:7007253",
      "tgn:7029392"
    ],
    "placetype": [
      "aat:300008706"
    ],
    "id": 2424569,
    "name:xx": "Johnson Creek"
  }
}
