{
  "geometry": {
    "type": "Point",
    "coordinates": [
      -85.9833,
      38.4167
    ]
  },
  "type": "Feature",
  "properties": {
    "hierarchy": [
      "tgn:2154119",
      "tgn:1000001",
      "tgn:7012149",
      "tgn:1002992",
      "tgn:7007252",
      "tgn:7029392"
    ],
    "placetype": [
      "aat:300008706"
    ],
    "id": 2154119,
    "name:xx": "Bear Creek"
  }
}
