{
  "geometry": {
    "type": "Point",
    "coordinates": [
      137.8667,
      36.1667
    ]
  },
  "type": "Feature",
  "properties": {
    "hierarchy": [
      "tgn:1081740",
      "tgn:7000895",
      "tgn:1000004",
      "tgn:1001010",
      "tgn:1000120",
      "tgn:7029392"
    ],
    "placetype": [
      "aat:300008347",
      "aat:300387220"
    ],
    "id": 1081740,
    "name:xx": "Yamagata"
  }
}
