{
  "geometry": {
    "type": "Point",
    "coordinates": [
      76.058445,
      32.547961
    ]
  },
  "type": "Feature",
  "properties": {
    "hierarchy": [
      "tgn:7575673",
      "tgn:1000004",
      "tgn:7000198",
      "tgn:1001996",
      "tgn:7029392"
    ],
    "placetype": [
      "aat:300008347"
    ],
    "name:en": "Lāhri",
    "id": 7575673
  }
}
