{
  "geometry": {
    "type": "Point",
    "coordinates": [
      -134.8333,
      56.4833
    ]
  },
  "type": "Feature",
  "properties": {
    "hierarchy": [
      "tgn:2135322",
      "tgn:7006450",
      "tgn:1000001",
      "tgn:7012149",
      "tgn:2124002",
      "tgn:7029392"
    ],
    "placetype": [
      "aat:300008680"
    ],
    "id": 2135322,
    "name:xx": "Antipatr Lake"
  }
}
