{
  "geometry": {
    "type": "Point",
    "coordinates": [
      79.8841,
      27.0279
    ]
  },
  "type": "Feature",
  "properties": {
    "hierarchy": [
      "tgn:7563180",
      "tgn:1000004",
      "tgn:7000198",
      "tgn:7016722",
      "tgn:7029392"
    ],
    "placetype": [
      "aat:300008347"
    ],
    "name:en": "Gangdharāpur",
    "id": 7563180
  }
}
