{
  "geometry": {
    "type": "Point",
    "coordinates": [
      23.0333,
      43.9167
    ]
  },
  "type": "Feature",
  "properties": {
    "hierarchy": [
      "tgn:1050233",
      "tgn:1000003",
      "tgn:1000364",
      "tgn:1000091",
      "tgn:7029392"
    ],
    "placetype": [
      "aat:300008347"
    ],
    "id": 1050233,
    "name:xx": "Poiana Mare"
  }
}
