{
  "geometry": {
    "type": "Point",
    "coordinates": [
      -83.95,
      40.8333
    ]
  },
  "type": "Feature",
  "properties": {
    "hierarchy": [
      "tgn:2497586",
      "tgn:1002144",
      "tgn:1000001",
      "tgn:7012149",
      "tgn:7007706",
      "tgn:7029392"
    ],
    "placetype": [
      "aat:300006075"
    ],
    "id": 2497586,
    "name:xx": "May Ditch"
  }
}
