{
  "geometry": {
    "type": "Point",
    "coordinates": [
      1.9333,
      49.0667
    ]
  },
  "type": "Feature",
  "properties": {
    "hierarchy": [
      "tgn:1034099",
      "tgn:1000003",
      "tgn:7002883",
      "tgn:1000070",
      "tgn:7029392"
    ],
    "placetype": [
      "aat:300008347"
    ],
    "id": 1034099,
    "name:xx": "Longuesse"
  }
}
