{
  "geometry": {
    "type": "Point",
    "coordinates": [
      -76.2667,
      38.7333
    ]
  },
  "type": "Feature",
  "properties": {
    "hierarchy": [
      "tgn:2178969",
      "tgn:1000001",
      "tgn:2000939",
      "tgn:7012149",
      "tgn:7007516",
      "tgn:7029392"
    ],
    "placetype": [
      "aat:300008850"
    ],
    "id": 2178969,
    "name:xx": "Blades Point"
  }
}
