{
  "type": "FeatureCollection",
  "features": [
    {
      "geometry": {
        "type": "Point",
        "coordinates": [
          9.95,
          49.833333
        ]
      },
      "type": "Feature",
      "properties": {
        "hierarchy": [
          "tgn:7124491",
          "tgn:7003669",
          "tgn:1000003",
          "tgn:7000084",
          "tgn:7029392"
        ],
        "placetype": [
          "aat:300008777"
        ],
        "id": 7124491,
        "name:xx": "Neuberg"
      }
    },
    {
      "geometry": {
        "type": "Point",
        "coordinates": [
          8.216667,
          49.783333
        ]
      },
      "type": "Feature",
      "properties": {
        "hierarchy": [
          "tgn:7124494",
          "tgn:1000003",
          "tgn:7003682",
          "tgn:7000084",
          "tgn:7029392"
        ],
        "placetype": [
          "aat:300008777"
        ],
        "id": 7124494,
        "name:xx": "Neuberg"
      }
    },
    {
      "geometry": {
        "type": "Point",
        "coordinates": [
          10.533333,
          49.633333
        ]
      },
      "type": "Feature",
      "properties": {
        "hierarchy": [
          "tgn:7124495",
          "tgn:7003669",
          "tgn:1000003",
          "tgn:7000084",
          "tgn:7029392"
        ],
        "placetype": [
          "aat:300008777"
        ],
        "id": 7124495,
        "name:xx": "Neuberg"
      }
    },
    {
      "geometry": {
        "type": "Point",
        "coordinates": [
          9.883333,
          49.516667
        ]
      },
      "type": "Feature",
      "properties": {
        "hierarchy": [
          "tgn:7124496",
          "tgn:7003692",
          "tgn:1000003",
          "tgn:7000084",
          "tgn:7029392"
        ],
        "placetype": [
          "aat:300008777"
        ],
        "id": 7124496,
        "name:xx": "Neu-Berg"
      }
    },
    {
      "geometry": {
        "type": "Point",
        "coordinates": [
          9.733333,
          49.133333
        ]
      },
      "type": "Feature",
      "properties": {
        "hierarchy": [
          "tgn:7124497",
          "tgn:7003692",
          "tgn:1000003",
          "tgn:7000084",
          "tgn:7029392"
        ],
        "placetype": [
          "aat:300008777"
        ],
        "id": 7124497,
        "name:xx": "Neuberg"
      }
    },
    {
      "geometry": {
        "type": "Point",
        "coordinates": [
          8.516667,
          48.95
        ]
      },
      "type": "Feature",
      "properties": {
        "hierarchy": [
          "tgn:7124498",
          "tgn:7003692",
          "tgn:1000003",
          "tgn:7000084",
          "tgn:7029392"
        ],
        "placetype": [
          "aat:300008777"
        ],
        "id": 7124498,
        "name:xx": "Neuberg"
      }
    },
    {
      "geometry": {
        "type": "Point",
        "coordinates": [
          8.033333,
          48.533333
        ]
      },
      "type": "Feature",
      "properties": {
        "hierarchy": [
          "tgn:7124499",
          "tgn:7003692",
          "tgn:1000003",
          "tgn:7000084",
          "tgn:7029392"
        ],
        "placetype": [
          "aat:300000206"
        ],
        "id": 7124499,
        "name:xx": "Neuberg"
      }
    }
  ]
}
