{
  "geometry": {
    "type": "Point",
    "coordinates": [
      -105.1333,
      45.8333
    ]
  },
  "type": "Feature",
  "properties": {
    "hierarchy": [
      "tgn:2503867",
      "tgn:1000001",
      "tgn:2001268",
      "tgn:7012149",
      "tgn:7007524",
      "tgn:7029392"
    ],
    "placetype": [
      "aat:300008706"
    ],
    "id": 2503867,
    "name:xx": "Meadow Creek"
  }
}
