{
  "geometry": {
    "type": "Point",
    "coordinates": [
      -80.3167,
      35.0833
    ]
  },
  "type": "Feature",
  "properties": {
    "hierarchy": [
      "tgn:2462316",
      "tgn:1000001",
      "tgn:7012149",
      "tgn:2001546",
      "tgn:7007709",
      "tgn:7029392"
    ],
    "placetype": [
      "aat:300008699"
    ],
    "id": 2462316,
    "name:xx": "Little Water Branch"
  }
}
