{
  "geometry": {
    "type": "Point",
    "coordinates": [
      -80.4667,
      38.8167
    ]
  },
  "type": "Feature",
  "properties": {
    "hierarchy": [
      "tgn:2440563",
      "tgn:1000001",
      "tgn:2002256",
      "tgn:7012149",
      "tgn:7013961",
      "tgn:7029392"
    ],
    "placetype": [
      "aat:300008706"
    ],
    "id": 2440563,
    "name:xx": "Knawl Creek"
  }
}
