{
  "geometry": {
    "type": "Point",
    "coordinates": [
      -93.85,
      39.0167
    ]
  },
  "type": "Feature",
  "properties": {
    "hierarchy": [
      "tgn:2709467",
      "tgn:1000001",
      "tgn:7012149",
      "tgn:2001212",
      "tgn:7007523",
      "tgn:7029392"
    ],
    "placetype": [
      "aat:300008706"
    ],
    "id": 2709467,
    "name:xx": "Tabo Creek"
  }
}
