{
  "geometry": {
    "type": "Point",
    "coordinates": [
      -159.45,
      61.05
    ]
  },
  "type": "Feature",
  "properties": {
    "hierarchy": [
      "tgn:2572923",
      "tgn:7006450",
      "tgn:2000069",
      "tgn:1000001",
      "tgn:7012149",
      "tgn:7029392"
    ],
    "placetype": [
      "aat:300008706"
    ],
    "id": 2572923,
    "name:xx": "Pearl Creek"
  }
}
