{
  "geometry": {
    "type": "Point",
    "coordinates": [
      5.3333,
      51.1667
    ]
  },
  "type": "Feature",
  "properties": {
    "hierarchy": [
      "tgn:7008882",
      "tgn:1000003",
      "tgn:1000063",
      "tgn:7029392"
    ],
    "placetype": [
      "aat:300387346",
      "aat:300132339"
    ],
    "id": 7008882,
    "name:xx": "Kempen"
  }
}
