{
  "geometry": {
    "type": "Point",
    "coordinates": [
      -92.9333,
      31.1333
    ]
  },
  "type": "Feature",
  "properties": {
    "hierarchy": [
      "tgn:2296818",
      "tgn:1000001",
      "tgn:7012149",
      "tgn:2000911",
      "tgn:7007256",
      "tgn:7029392"
    ],
    "placetype": [
      "aat:300008706"
    ],
    "id": 2296818,
    "name:xx": "Dry Creek"
  }
}
