{
  "geometry": {
    "type": "Point",
    "coordinates": [
      30.566667,
      31.109532
    ]
  },
  "type": "Feature",
  "properties": {
    "hierarchy": [
      "tgn:7538682",
      "tgn:7001242",
      "tgn:1001075",
      "tgn:7016833",
      "tgn:7029392"
    ],
    "placetype": [
      "aat:300008347"
    ],
    "name:en": "Niz̧ārat Samādīs",
    "id": 7538682
  }
}
