{
  "geometry": {
    "type": "Point",
    "coordinates": [
      35.0167,
      -17.4333
    ]
  },
  "type": "Feature",
  "properties": {
    "hierarchy": [
      "tgn:7000398",
      "tgn:7001242",
      "tgn:7000400",
      "tgn:1000180",
      "tgn:7029392"
    ],
    "placetype": [
      "aat:300008347"
    ],
    "id": 7000398,
    "name:xx": "Sena"
  }
}
