{
  "geometry": {
    "type": "Point",
    "coordinates": [
      -87.7167,
      36.1833
    ]
  },
  "type": "Feature",
  "properties": {
    "hierarchy": [
      "tgn:2729620",
      "tgn:1000001",
      "tgn:7012149",
      "tgn:2001879",
      "tgn:7007825",
      "tgn:7029392"
    ],
    "placetype": [
      "aat:300008761"
    ],
    "id": 2729620,
    "name:xx": "Trotter Hollow"
  }
}
