{
  "geometry": {
    "type": "Point",
    "coordinates": [
      -99.8667,
      35.3333
    ]
  },
  "type": "Feature",
  "properties": {
    "hierarchy": [
      "tgn:2083587",
      "tgn:2001627",
      "tgn:1000001",
      "tgn:7012149",
      "tgn:7007707",
      "tgn:7029392"
    ],
    "placetype": [
      "aat:300008347"
    ],
    "id": 2083587,
    "name:xx": "Mayfield"
  }
}
