{
  "geometry": {
    "type": "Point",
    "coordinates": [
      -92.2667,
      33.2833
    ]
  },
  "type": "Feature",
  "properties": {
    "hierarchy": [
      "tgn:2363764",
      "tgn:1000001",
      "tgn:7016172",
      "tgn:2000110",
      "tgn:7012149",
      "tgn:7029392"
    ],
    "placetype": [
      "aat:300008680"
    ],
    "id": 2363764,
    "name:xx": "Green Lake"
  }
}
