{
  "geometry": {
    "type": "Point",
    "coordinates": [
      -93.2167,
      44.55
    ]
  },
  "type": "Feature",
  "properties": {
    "hierarchy": [
      "tgn:2239088",
      "tgn:1000001",
      "tgn:2001017",
      "tgn:7012149",
      "tgn:7007521",
      "tgn:7029392"
    ],
    "placetype": [
      "aat:300008680"
    ],
    "id": 2239088,
    "name:xx": "Chub Lake"
  }
}
