{
  "geometry": {
    "type": "Point",
    "coordinates": [
      -62.25,
      -40.25
    ]
  },
  "type": "Feature",
  "properties": {
    "hierarchy": [
      "tgn:1112582",
      "tgn:1001160",
      "tgn:7006477",
      "tgn:1000002",
      "tgn:7029392"
    ],
    "placetype": [
      "aat:300132316"
    ],
    "id": 1112582,
    "name:xx": "Anegada, Bahía"
  }
}
