{
  "geometry": {
    "type": "Point",
    "coordinates": [
      -56.85,
      -33.9167
    ]
  },
  "type": "Feature",
  "properties": {
    "hierarchy": [
      "tgn:1134210",
      "tgn:1000610",
      "tgn:1000002",
      "tgn:1000058",
      "tgn:7029392"
    ],
    "placetype": [
      "aat:300008706"
    ],
    "id": 1134210,
    "name:xx": "Pintos, Arroyo de"
  }
}
