{
  "geometry": {
    "type": "Point",
    "coordinates": [
      -0.2667,
      29.0167
    ]
  },
  "type": "Feature",
  "properties": {
    "hierarchy": [
      "tgn:1087412",
      "tgn:1000486",
      "tgn:7001242",
      "tgn:7016752",
      "tgn:7029392"
    ],
    "placetype": [
      "aat:300008347"
    ],
    "id": 1087412,
    "name:xx": "Charouïne"
  }
}
