{
  "type": "FeatureCollection",
  "features": [
    {
      "geometry": {
        "type": "Point",
        "coordinates": [
          -71.3833,
          43.6167
        ]
      },
      "type": "Feature",
      "properties": {
        "hierarchy": [
          "tgn:2517070",
          "tgn:2001422",
          "tgn:1000001",
          "tgn:7012149",
          "tgn:7007564",
          "tgn:7029392"
        ],
        "placetype": [
          "aat:300008791"
        ],
        "id": 2517070,
        "name:xx": "Mink Island"
      }
    },
    {
      "geometry": {
        "type": "Point",
        "coordinates": [
          -71.5333,
          43.75
        ]
      },
      "type": "Feature",
      "properties": {
        "hierarchy": [
          "tgn:2517071",
          "tgn:1000001",
          "tgn:2001424",
          "tgn:7012149",
          "tgn:7007564",
          "tgn:7029392"
        ],
        "placetype": [
          "aat:300008791"
        ],
        "id": 2517071,
        "name:xx": "Mink Island"
      }
    },
    {
      "geometry": {
        "type": "Point",
        "coordinates": [
          -75.7833,
          44.4
        ]
      },
      "type": "Feature",
      "properties": {
        "hierarchy": [
          "tgn:2517072",
          "tgn:1000001",
          "tgn:7012149",
          "tgn:7016021",
          "tgn:7007568",
          "tgn:7029392"
        ],
        "placetype": [
          "aat:300008791"
        ],
        "id": 2517072,
        "name:xx": "Mink Island"
      }
    },
    {
      "geometry": {
        "type": "Point",
        "coordinates": [
          -78.5667,
          33.85
        ]
      },
      "type": "Feature",
      "properties": {
        "hierarchy": [
          "tgn:2517073",
          "tgn:1000001",
          "tgn:7012149",
          "tgn:2001750",
          "tgn:7007712",
          "tgn:7029392"
        ],
        "placetype": [
          "aat:300008791"
        ],
        "id": 2517073,
        "name:xx": "Mink Island"
      }
    },
    {
      "geometry": {
        "type": "Point",
        "coordinates": [
          -75.8167,
          37.1833
        ]
      },
      "type": "Feature",
      "properties": {
        "hierarchy": [
          "tgn:2517074",
          "tgn:1000001",
          "tgn:7012149",
          "tgn:1002730",
          "tgn:7007919",
          "tgn:7029392"
        ],
        "placetype": [
          "aat:300008791"
        ],
        "id": 2517074,
        "name:xx": "Mink Island"
      }
    },
    {
      "geometry": {
        "type": "Point",
        "coordinates": [
          -75.8333,
          37.1667
        ]
      },
      "type": "Feature",
      "properties": {
        "hierarchy": [
          "tgn:2517075",
          "tgn:1000001",
          "tgn:7012149",
          "tgn:1002730",
          "tgn:7007919",
          "tgn:7029392"
        ],
        "placetype": [
          "aat:300132316"
        ],
        "id": 2517075,
        "name:xx": "Mink Island Bay"
      }
    },
    {
      "geometry": {
        "type": "Point",
        "coordinates": [
          -133.3833,
          55.75
        ]
      },
      "type": "Feature",
      "properties": {
        "hierarchy": [
          "tgn:2517076",
          "tgn:7006450",
          "tgn:1000001",
          "tgn:7012149",
          "tgn:2000082",
          "tgn:7029392"
        ],
        "placetype": [
          "aat:300008680"
        ],
        "id": 2517076,
        "name:xx": "Mink Lake"
      }
    },
    {
      "geometry": {
        "type": "Point",
        "coordinates": [
          -143.5667,
          67.1
        ]
      },
      "type": "Feature",
      "properties": {
        "hierarchy": [
          "tgn:2517077",
          "tgn:7006450",
          "tgn:1000001",
          "tgn:7012149",
          "tgn:2000089",
          "tgn:7029392"
        ],
        "placetype": [
          "aat:300008680"
        ],
        "id": 2517077,
        "name:xx": "Mink Lake"
      }
    },
    {
      "geometry": {
        "type": "Point",
        "coordinates": [
          -90.1833,
          35.4333
        ]
      },
      "type": "Feature",
      "properties": {
        "hierarchy": [
          "tgn:2517078",
          "tgn:1000001",
          "tgn:7016172",
          "tgn:7012149",
          "tgn:2000151",
          "tgn:7029392"
        ],
        "placetype": [
          "aat:300008680"
        ],
        "id": 2517078,
        "name:xx": "Mink Lake"
      }
    },
    {
      "geometry": {
        "type": "Point",
        "coordinates": [
          -85.0667,
          41.6
        ]
      },
      "type": "Feature",
      "properties": {
        "hierarchy": [
          "tgn:2517079",
          "tgn:1000001",
          "tgn:7012149",
          "tgn:1002919",
          "tgn:7007252",
          "tgn:7029392"
        ],
        "placetype": [
          "aat:300008680"
        ],
        "id": 2517079,
        "name:xx": "Mink Lake"
      }
    }
  ]
}
