{
  "geometry": {
    "type": "Point",
    "coordinates": [
      3.6167,
      45.8167
    ]
  },
  "type": "Feature",
  "properties": {
    "hierarchy": [
      "tgn:1035561",
      "tgn:7002871",
      "tgn:1000003",
      "tgn:1000070",
      "tgn:7029392"
    ],
    "placetype": [
      "aat:300008347"
    ],
    "id": 1035561,
    "name:xx": "Sainte-Agathe"
  }
}
