{
  "geometry": {
    "type": "Point",
    "coordinates": [
      -119.45,
      37.8167
    ]
  },
  "type": "Feature",
  "properties": {
    "hierarchy": [
      "tgn:2714674",
      "tgn:1000001",
      "tgn:7012149",
      "tgn:7007157",
      "tgn:7014004",
      "tgn:7029392"
    ],
    "placetype": [
      "aat:300008680"
    ],
    "id": 2714674,
    "name:xx": "Tenaya Lake"
  }
}
