{
  "geometry": {
    "type": "Point",
    "coordinates": [
      -73.8167,
      44.0167
    ]
  },
  "type": "Feature",
  "properties": {
    "hierarchy": [
      "tgn:2299218",
      "tgn:1000001",
      "tgn:7012149",
      "tgn:2001461",
      "tgn:7007568",
      "tgn:7029392"
    ],
    "placetype": [
      "aat:300132316"
    ],
    "id": 2299218,
    "name:xx": "Duck Hole"
  }
}
