{
  "geometry": {
    "type": "Point",
    "coordinates": [
      -96.1667,
      35.8167
    ]
  },
  "type": "Feature",
  "properties": {
    "hierarchy": [
      "tgn:2319557",
      "tgn:1000001",
      "tgn:7012149",
      "tgn:7007707",
      "tgn:7029392"
    ],
    "placetype": [
      "aat:300008706"
    ],
    "id": 2319557,
    "name:xx": "Euchee Creek"
  }
}
