{
  "type": "FeatureCollection",
  "features": [
    {
      "geometry": {
        "type": "Point",
        "coordinates": [
          -99.8,
          29.55
        ]
      },
      "type": "Feature",
      "properties": {
        "hierarchy": [
          "tgn:2200150",
          "tgn:1000001",
          "tgn:7012149",
          "tgn:2002087",
          "tgn:7007826",
          "tgn:7029392"
        ],
        "placetype": [
          "aat:300008706"
        ],
        "id": 2200150,
        "name:xx": "Brushy Creek"
      }
    },
    {
      "geometry": {
        "type": "Point",
        "coordinates": [
          -98.9333,
          29.6167
        ]
      },
      "type": "Feature",
      "properties": {
        "hierarchy": [
          "tgn:2200151",
          "tgn:1000001",
          "tgn:2001938",
          "tgn:7012149",
          "tgn:7007826",
          "tgn:7029392"
        ],
        "placetype": [
          "aat:300008706"
        ],
        "id": 2200151,
        "name:xx": "Brushy Creek"
      }
    },
    {
      "geometry": {
        "type": "Point",
        "coordinates": [
          -97.5833,
          29.9833
        ]
      },
      "type": "Feature",
      "properties": {
        "hierarchy": [
          "tgn:2200152",
          "tgn:1000001",
          "tgn:7012149",
          "tgn:1002220",
          "tgn:7007826",
          "tgn:7029392"
        ],
        "placetype": [
          "aat:300008706"
        ],
        "id": 2200152,
        "name:xx": "Brushy Creek"
      }
    },
    {
      "geometry": {
        "type": "Point",
        "coordinates": [
          -99.0667,
          32.6833
        ]
      },
      "type": "Feature",
      "properties": {
        "hierarchy": [
          "tgn:2200153",
          "tgn:1000001",
          "tgn:7012149",
          "tgn:2002076",
          "tgn:7007826",
          "tgn:7029392"
        ],
        "placetype": [
          "aat:300008706"
        ],
        "id": 2200153,
        "name:xx": "Brushy Creek"
      }
    },
    {
      "geometry": {
        "type": "Point",
        "coordinates": [
          -96.9,
          29.4833
        ]
      },
      "type": "Feature",
      "properties": {
        "hierarchy": [
          "tgn:2200154",
          "tgn:1000001",
          "tgn:7012149",
          "tgn:1002578",
          "tgn:7007826",
          "tgn:7029392"
        ],
        "placetype": [
          "aat:300008706"
        ],
        "id": 2200154,
        "name:xx": "Brushy Creek"
      }
    },
    {
      "geometry": {
        "type": "Point",
        "coordinates": [
          -97.0333,
          29.6667
        ]
      },
      "type": "Feature",
      "properties": {
        "hierarchy": [
          "tgn:2200155",
          "tgn:1000001",
          "tgn:7012149",
          "tgn:1002374",
          "tgn:7007826",
          "tgn:7029392"
        ],
        "placetype": [
          "aat:300008706"
        ],
        "id": 2200155,
        "name:xx": "Brushy Creek"
      }
    },
    {
      "geometry": {
        "type": "Point",
        "coordinates": [
          -97.8667,
          29.6833
        ]
      },
      "type": "Feature",
      "properties": {
        "hierarchy": [
          "tgn:2200156",
          "tgn:1000001",
          "tgn:7012149",
          "tgn:1002431",
          "tgn:7007826",
          "tgn:7029392"
        ],
        "placetype": [
          "aat:300008706"
        ],
        "id": 2200156,
        "name:xx": "Brushy Creek"
      }
    },
    {
      "geometry": {
        "type": "Point",
        "coordinates": [
          -96.4833,
          29.8167
        ]
      },
      "type": "Feature",
      "properties": {
        "hierarchy": [
          "tgn:2200157",
          "tgn:1000001",
          "tgn:7012149",
          "tgn:1002291",
          "tgn:7007826",
          "tgn:7029392"
        ],
        "placetype": [
          "aat:300008706"
        ],
        "id": 2200157,
        "name:xx": "Brushy Creek"
      }
    },
    {
      "geometry": {
        "type": "Point",
        "coordinates": [
          -96.9833,
          31.8833
        ]
      },
      "type": "Feature",
      "properties": {
        "hierarchy": [
          "tgn:2200158",
          "tgn:1000001",
          "tgn:7012149",
          "tgn:1002478",
          "tgn:7007826",
          "tgn:7029392"
        ],
        "placetype": [
          "aat:300008706"
        ],
        "id": 2200158,
        "name:xx": "Brushy Creek"
      }
    },
    {
      "geometry": {
        "type": "Point",
        "coordinates": [
          -95.2667,
          32.0167
        ]
      },
      "type": "Feature",
      "properties": {
        "hierarchy": [
          "tgn:2200159",
          "tgn:1000001",
          "tgn:7012149",
          "tgn:1002263",
          "tgn:7007826",
          "tgn:7029392"
        ],
        "placetype": [
          "aat:300008706"
        ],
        "id": 2200159,
        "name:xx": "Brushy Creek"
      }
    }
  ]
}
