{
  "geometry": {
    "type": "Point",
    "coordinates": [
      -86.3333,
      39.6667
    ]
  },
  "type": "Feature",
  "properties": {
    "hierarchy": [
      "tgn:2368416",
      "tgn:1000001",
      "tgn:7012149",
      "tgn:1002465",
      "tgn:7007252",
      "tgn:7029392"
    ],
    "placetype": [
      "aat:300008699"
    ],
    "id": 2368416,
    "name:xx": "Guilford Branch"
  }
}
