{
  "geometry": {
    "type": "Point",
    "coordinates": [
      48.7333,
      51.1167
    ]
  },
  "type": "Feature",
  "properties": {
    "hierarchy": [
      "tgn:1052132",
      "tgn:1000004",
      "tgn:1003408",
      "tgn:7018214",
      "tgn:7002435",
      "tgn:7029392"
    ],
    "placetype": [
      "aat:300008347"
    ],
    "id": 1052132,
    "name:xx": "Altata"
  }
}
