{
  "geometry": {
    "type": "Point",
    "coordinates": [
      34.153056,
      30.6575
    ]
  },
  "type": "Feature",
  "properties": {
    "hierarchy": [
      "tgn:7541902",
      "tgn:7001242",
      "tgn:7016833",
      "tgn:7001335",
      "tgn:7029392"
    ],
    "placetype": [
      "aat:300379998"
    ],
    "id": 7541902,
    "name:xx": "Mazīra'a, Wādī al"
  }
}
