{
  "geometry": {
    "type": "Point",
    "coordinates": [
      79.9819,
      27.1413
    ]
  },
  "type": "Feature",
  "properties": {
    "hierarchy": [
      "tgn:7562023",
      "tgn:1000004",
      "tgn:7000198",
      "tgn:7016722",
      "tgn:7029392"
    ],
    "placetype": [
      "aat:300008347"
    ],
    "name:en": "Karehka",
    "id": 7562023
  }
}
