{
  "geometry": {
    "type": "Point",
    "coordinates": [
      -111.7833,
      39.4667
    ]
  },
  "type": "Feature",
  "properties": {
    "hierarchy": [
      "tgn:2281967",
      "tgn:1000001",
      "tgn:7012149",
      "tgn:2002112",
      "tgn:7007827",
      "tgn:7029392"
    ],
    "placetype": [
      "aat:300008761"
    ],
    "id": 2281967,
    "name:xx": "Deer Gulch"
  }
}
