{
  "geometry": {
    "type": "Point",
    "coordinates": [
      -137.5167,
      61.5667
    ]
  },
  "type": "Feature",
  "properties": {
    "hierarchy": [
      "tgn:1016180",
      "tgn:7005685",
      "tgn:1000001",
      "tgn:7005806",
      "tgn:7029392"
    ],
    "placetype": [
      "aat:300008347"
    ],
    "id": 1016180,
    "name:xx": "Aishihik Lake"
  }
}
