{
  "type": "FeatureCollection",
  "features": [
    {
      "geometry": {
        "type": "Point",
        "coordinates": [
          -66,
          -34
        ]
      },
      "type": "Feature",
      "properties": {
        "hierarchy": [
          "tgn:1001520",
          "tgn:7006477",
          "tgn:1000002",
          "tgn:7029392"
        ],
        "placetype": [
          "aat:300387064",
          "aat:300000774"
        ],
        "id": 1001520,
        "name:xx": "San Luis"
      }
    },
    {
      "geometry": {
        "type": "Point",
        "coordinates": [
          -79.25,
          22
        ]
      },
      "type": "Feature",
      "properties": {
        "hierarchy": [
          "tgn:1001521",
          "tgn:1000001",
          "tgn:7004624",
          "tgn:7029392"
        ],
        "placetype": [
          "aat:300008631",
          "aat:300387064",
          "aat:300387302",
          "aat:300000774"
        ],
        "id": 1001521,
        "name:xx": "Sancti-Spíritus"
      }
    },
    {
      "geometry": {
        "type": "Point",
        "coordinates": [
          -70,
          -49
        ]
      },
      "type": "Feature",
      "properties": {
        "hierarchy": [
          "tgn:1001522",
          "tgn:7006477",
          "tgn:1000002",
          "tgn:7029392"
        ],
        "placetype": [
          "aat:300387064",
          "aat:300000774"
        ],
        "id": 1001522,
        "name:xx": "Santa Cruz"
      }
    },
    {
      "geometry": {
        "type": "Point",
        "coordinates": [
          -61,
          -31
        ]
      },
      "type": "Feature",
      "properties": {
        "hierarchy": [
          "tgn:1001524",
          "tgn:7006477",
          "tgn:1000002",
          "tgn:7029392"
        ],
        "placetype": [
          "aat:300387064",
          "aat:300000774"
        ],
        "id": 1001524,
        "name:xx": "Santa Fe"
      }
    },
    {
      "geometry": {
        "type": "Point",
        "coordinates": [
          -76,
          20.25
        ]
      },
      "type": "Feature",
      "properties": {
        "hierarchy": [
          "tgn:1001525",
          "tgn:1000001",
          "tgn:7004624",
          "tgn:7029392"
        ],
        "placetype": [
          "aat:300008631",
          "aat:300387064",
          "aat:300000774"
        ],
        "id": 1001525,
        "name:xx": "Santiago de Cuba"
      }
    },
    {
      "geometry": {
        "type": "Point",
        "coordinates": [
          -63.5,
          -28
        ]
      },
      "type": "Feature",
      "properties": {
        "hierarchy": [
          "tgn:1001526",
          "tgn:7006477",
          "tgn:1000002",
          "tgn:7029392"
        ],
        "placetype": [
          "aat:300387064",
          "aat:300000774"
        ],
        "id": 1001526,
        "name:xx": "Santiago del Estero"
      }
    },
    {
      "geometry": {
        "type": "Point",
        "coordinates": [
          106.416,
          49.666
        ]
      },
      "type": "Feature",
      "properties": {
        "hierarchy": [
          "tgn:1001527",
          "tgn:1000004",
          "tgn:7029379",
          "tgn:7029392"
        ],
        "placetype": [
          "aat:300387064",
          "aat:300000774"
        ],
        "id": 1001527,
        "name:xx": "Selenge"
      }
    },
    {
      "geometry": {
        "type": "Point",
        "coordinates": [
          53.4167,
          35.5
        ]
      },
      "type": "Feature",
      "properties": {
        "hierarchy": [
          "tgn:1001528",
          "tgn:1000004",
          "tgn:7000231",
          "tgn:7029392"
        ],
        "placetype": [
          "aat:300387064",
          "aat:300000774"
        ],
        "id": 1001528,
        "name:xx": "Semnān"
      }
    },
    {
      "geometry": {
        "type": "Point",
        "coordinates": [
          -7.416,
          33.0833
        ]
      },
      "type": "Feature",
      "properties": {
        "hierarchy": [
          "tgn:1001529",
          "tgn:7593667",
          "tgn:7001242",
          "tgn:1000179",
          "tgn:7029392"
        ],
        "placetype": [
          "aat:300387064",
          "aat:300387145",
          "aat:300000774"
        ],
        "id": 1001529,
        "name:xx": "Settat, Province de"
      }
    }
  ]
}
