{
  "geometry": {
    "type": "Point",
    "coordinates": [
      27.920195,
      30.382873
    ]
  },
  "type": "Feature",
  "properties": {
    "hierarchy": [
      "tgn:7527262",
      "tgn:7001242",
      "tgn:7016833",
      "tgn:1001418",
      "tgn:7029392"
    ],
    "placetype": [
      "aat:300008749"
    ],
    "name:en": "Z̧ahr al Ḩimār, Minqār",
    "id": 7527262
  }
}
