{
  "geometry": {
    "type": "Point",
    "coordinates": [
      -115.4833,
      35.8333
    ]
  },
  "type": "Feature",
  "properties": {
    "hierarchy": [
      "tgn:2634631",
      "tgn:1000001",
      "tgn:2001410",
      "tgn:7012149",
      "tgn:7007526",
      "tgn:7029392"
    ],
    "placetype": [
      "aat:300000390"
    ],
    "id": 2634631,
    "name:xx": "Ruth Mine"
  }
}
