{
  "geometry": {
    "type": "Point",
    "coordinates": [
      -84.7333,
      32.9167
    ]
  },
  "type": "Feature",
  "properties": {
    "hierarchy": [
      "tgn:2702560",
      "tgn:1000001",
      "tgn:7012149",
      "tgn:7007248",
      "tgn:7029392"
    ],
    "placetype": [
      "aat:300008706"
    ],
    "id": 2702560,
    "name:xx": "Sulphur Creek"
  }
}
