{
  "geometry": {
    "type": "Point",
    "coordinates": [
      120.6501,
      24.1191
    ]
  },
  "type": "Feature",
  "properties": {
    "hierarchy": [
      "tgn:7471344",
      "tgn:1000004",
      "tgn:7001009",
      "tgn:1000141",
      "tgn:7029392"
    ],
    "placetype": [
      "aat:300008347"
    ],
    "id": 7471344,
    "name:xx": "Fanpo"
  }
}
