{
  "geometry": {
    "type": "Point",
    "coordinates": [
      -106.8667,
      40.0667
    ]
  },
  "type": "Feature",
  "properties": {
    "hierarchy": [
      "tgn:2540588",
      "tgn:1000001",
      "tgn:7012149",
      "tgn:7007158",
      "tgn:2000245",
      "tgn:7029392"
    ],
    "placetype": [
      "aat:300006191"
    ],
    "id": 2540588,
    "name:xx": "Newton Gulch Reservoir"
  }
}
