{
  "geometry": {
    "type": "Point",
    "coordinates": [
      -80.4833,
      37.0167
    ]
  },
  "type": "Feature",
  "properties": {
    "hierarchy": [
      "tgn:2214826",
      "tgn:1000001",
      "tgn:7012149",
      "tgn:2002174",
      "tgn:7007919",
      "tgn:7029392"
    ],
    "placetype": [
      "aat:300008798"
    ],
    "id": 2214826,
    "name:xx": "Calfee Knob"
  }
}
