{
  "geometry": {
    "type": "Point",
    "coordinates": [
      -98.4167,
      30.7333
    ]
  },
  "type": "Feature",
  "properties": {
    "hierarchy": [
      "tgn:2201223",
      "tgn:1000001",
      "tgn:7012149",
      "tgn:2002005",
      "tgn:7007826",
      "tgn:7029392"
    ],
    "placetype": [
      "aat:300008347"
    ],
    "id": 2201223,
    "name:xx": "Buchanan Dam"
  }
}
