{
  "geometry": {
    "type": "Point",
    "coordinates": [
      -123.5667,
      39.45
    ]
  },
  "type": "Feature",
  "properties": {
    "hierarchy": [
      "tgn:2491954",
      "tgn:1000001",
      "tgn:7012149",
      "tgn:7007157",
      "tgn:2000185",
      "tgn:7029392"
    ],
    "placetype": [
      "aat:300008347"
    ],
    "id": 2491954,
    "name:xx": "Marble Place"
  }
}
