{
  "geometry": {
    "type": "Point",
    "coordinates": [
      30.562,
      30.937
    ]
  },
  "type": "Feature",
  "properties": {
    "hierarchy": [
      "tgn:1095124",
      "tgn:7001242",
      "tgn:1001075",
      "tgn:7016833",
      "tgn:7029392"
    ],
    "placetype": [
      "aat:300008347"
    ],
    "name:en": "Şafţ al Mulūk",
    "id": 1095124
  }
}
