{
  "geometry": {
    "type": "Point",
    "coordinates": [
      -75.7333,
      35.65
    ]
  },
  "type": "Feature",
  "properties": {
    "hierarchy": [
      "tgn:2770106",
      "tgn:1000001",
      "tgn:7012149",
      "tgn:2001488",
      "tgn:7007709",
      "tgn:7029392"
    ],
    "placetype": [
      "aat:300008850"
    ],
    "id": 2770106,
    "name:xx": "Wild Boar Point"
  }
}
