{
  "geometry": {
    "type": "Point",
    "coordinates": [
      -86.4833,
      34.65
    ]
  },
  "type": "Feature",
  "properties": {
    "hierarchy": [
      "tgn:2458092",
      "tgn:7002659",
      "tgn:1000001",
      "tgn:7012149",
      "tgn:2000044",
      "tgn:7029392"
    ],
    "placetype": [
      "aat:300008798"
    ],
    "id": 2458092,
    "name:xx": "Little Mountain"
  }
}
