{
  "geometry": {
    "type": "Point",
    "coordinates": [
      -121.3167,
      47.6667
    ]
  },
  "type": "Feature",
  "properties": {
    "hierarchy": [
      "tgn:2674795",
      "tgn:1000001",
      "tgn:7012149",
      "tgn:7018871",
      "tgn:7007920",
      "tgn:7029392"
    ],
    "placetype": [
      "aat:300008798"
    ],
    "id": 2674795,
    "name:xx": "Sobieski Mountain"
  }
}
