{
  "type": "FeatureCollection",
  "features": [
    {
      "geometry": {
        "type": "Point",
        "coordinates": [
          -121.65,
          43.25
        ]
      },
      "type": "Feature",
      "properties": {
        "hierarchy": [
          "tgn:2667490",
          "tgn:1000001",
          "tgn:7012149",
          "tgn:2001714",
          "tgn:7007708",
          "tgn:7029392"
        ],
        "placetype": [
          "aat:300008798"
        ],
        "id": 2667490,
        "name:xx": "Skookum Butte"
      }
    },
    {
      "geometry": {
        "type": "Point",
        "coordinates": [
          -115.6833,
          47.2167
        ]
      },
      "type": "Feature",
      "properties": {
        "hierarchy": [
          "tgn:2667491",
          "tgn:1000001",
          "tgn:7012149",
          "tgn:2000491",
          "tgn:7007250",
          "tgn:7029392"
        ],
        "placetype": [
          "aat:300008761"
        ],
        "id": 2667491,
        "name:xx": "Skookum Canyon"
      }
    },
    {
      "geometry": {
        "type": "Point",
        "coordinates": [
          -118.4833,
          44.05
        ]
      },
      "type": "Feature",
      "properties": {
        "hierarchy": [
          "tgn:2667492",
          "tgn:1000001",
          "tgn:7012149",
          "tgn:7007708",
          "tgn:7029392"
        ],
        "placetype": [
          "aat:300008761"
        ],
        "id": 2667492,
        "name:xx": "Skookum Canyon"
      }
    },
    {
      "geometry": {
        "type": "Point",
        "coordinates": [
          -121.2,
          45.9
        ]
      },
      "type": "Feature",
      "properties": {
        "hierarchy": [
          "tgn:2667493",
          "tgn:1000001",
          "tgn:7012149",
          "tgn:1002554",
          "tgn:7007920",
          "tgn:7029392"
        ],
        "placetype": [
          "aat:300008761"
        ],
        "id": 2667493,
        "name:xx": "Skookum Canyon"
      }
    },
    {
      "geometry": {
        "type": "Point",
        "coordinates": [
          -118.3833,
          46.65
        ]
      },
      "type": "Feature",
      "properties": {
        "hierarchy": [
          "tgn:2667494",
          "tgn:1000001",
          "tgn:2002244",
          "tgn:7012149",
          "tgn:7007920",
          "tgn:7029392"
        ],
        "placetype": [
          "aat:300008761"
        ],
        "id": 2667494,
        "name:xx": "Skookum Canyon"
      }
    },
    {
      "geometry": {
        "type": "Point",
        "coordinates": [
          -117.0833,
          44.6667
        ]
      },
      "type": "Feature",
      "properties": {
        "hierarchy": [
          "tgn:2667495",
          "tgn:7013349",
          "tgn:1000001",
          "tgn:7012149",
          "tgn:7007708",
          "tgn:7029392"
        ],
        "placetype": [
          "aat:300008706"
        ],
        "id": 2667495,
        "name:xx": "Skookum Chuck Creek"
      }
    },
    {
      "geometry": {
        "type": "Point",
        "coordinates": [
          -141.8333,
          62.1
        ]
      },
      "type": "Feature",
      "properties": {
        "hierarchy": [
          "tgn:2667496",
          "tgn:7006450",
          "tgn:1000001",
          "tgn:7012149",
          "tgn:2000086",
          "tgn:7029392"
        ],
        "placetype": [
          "aat:300008706"
        ],
        "id": 2667496,
        "name:xx": "Skookum Creek"
      }
    },
    {
      "geometry": {
        "type": "Point",
        "coordinates": [
          -154.9,
          63.1333
        ]
      },
      "type": "Feature",
      "properties": {
        "hierarchy": [
          "tgn:2667497",
          "tgn:7006450",
          "tgn:1000001",
          "tgn:7012149",
          "tgn:2000089",
          "tgn:7029392"
        ],
        "placetype": [
          "aat:300008706"
        ],
        "id": 2667497,
        "name:xx": "Skookum Creek"
      }
    },
    {
      "geometry": {
        "type": "Point",
        "coordinates": [
          -165.2167,
          64.6667
        ]
      },
      "type": "Feature",
      "properties": {
        "hierarchy": [
          "tgn:2667498",
          "tgn:7006450",
          "tgn:1000001",
          "tgn:7012149",
          "tgn:2000079",
          "tgn:7029392"
        ],
        "placetype": [
          "aat:300008706"
        ],
        "id": 2667498,
        "name:xx": "Skookum Creek"
      }
    },
    {
      "geometry": {
        "type": "Point",
        "coordinates": [
          -130.0167,
          56
        ]
      },
      "type": "Feature",
      "properties": {
        "hierarchy": [
          "tgn:2667499",
          "tgn:7006450",
          "tgn:1000001",
          "tgn:7012149",
          "tgn:2000082",
          "tgn:7029392"
        ],
        "placetype": [
          "aat:300008706"
        ],
        "id": 2667499,
        "name:xx": "Skookum Creek"
      }
    }
  ]
}
