{
  "type": "FeatureCollection",
  "features": [
    {
      "geometry": {
        "type": "Point",
        "coordinates": [
          -84.5333,
          37.0167
        ]
      },
      "type": "Feature",
      "properties": {
        "hierarchy": [
          "tgn:2213380",
          "tgn:1000001",
          "tgn:7012149",
          "tgn:2000839",
          "tgn:7007255",
          "tgn:7029392"
        ],
        "placetype": [
          "aat:300008761"
        ],
        "id": 2213380,
        "name:xx": "Cabin Hollow"
      }
    },
    {
      "geometry": {
        "type": "Point",
        "coordinates": [
          -84.2833,
          37.0667
        ]
      },
      "type": "Feature",
      "properties": {
        "hierarchy": [
          "tgn:2213381",
          "tgn:1000001",
          "tgn:7012149",
          "tgn:7007255",
          "tgn:7029392"
        ],
        "placetype": [
          "aat:300008761"
        ],
        "id": 2213381,
        "name:xx": "Cabin Hollow"
      }
    },
    {
      "geometry": {
        "type": "Point",
        "coordinates": [
          -83.8333,
          36.5667
        ]
      },
      "type": "Feature",
      "properties": {
        "hierarchy": [
          "tgn:2213382",
          "tgn:1000001",
          "tgn:7012149",
          "tgn:7029392"
        ],
        "placetype": [
          "aat:300008761"
        ],
        "id": 2213382,
        "name:xx": "Cabin Hollow"
      }
    },
    {
      "geometry": {
        "type": "Point",
        "coordinates": [
          -91.9333,
          36.5333
        ]
      },
      "type": "Feature",
      "properties": {
        "hierarchy": [
          "tgn:2213383",
          "tgn:1000001",
          "tgn:7012149",
          "tgn:2001206",
          "tgn:7007523",
          "tgn:7029392"
        ],
        "placetype": [
          "aat:300008761"
        ],
        "id": 2213383,
        "name:xx": "Cabin Hollow"
      }
    },
    {
      "geometry": {
        "type": "Point",
        "coordinates": [
          -91.1167,
          37.0667
        ]
      },
      "type": "Feature",
      "properties": {
        "hierarchy": [
          "tgn:2213384",
          "tgn:1000001",
          "tgn:7012149",
          "tgn:7007523",
          "tgn:7029392"
        ],
        "placetype": [
          "aat:300008761"
        ],
        "id": 2213384,
        "name:xx": "Cabin Hollow"
      }
    },
    {
      "geometry": {
        "type": "Point",
        "coordinates": [
          -91.3167,
          37.25
        ]
      },
      "type": "Feature",
      "properties": {
        "hierarchy": [
          "tgn:2213385",
          "tgn:1000001",
          "tgn:7012149",
          "tgn:2001247",
          "tgn:7007523",
          "tgn:7029392"
        ],
        "placetype": [
          "aat:300008761"
        ],
        "id": 2213385,
        "name:xx": "Cabin Hollow"
      }
    },
    {
      "geometry": {
        "type": "Point",
        "coordinates": [
          -111.3,
          40.3333
        ]
      },
      "type": "Feature",
      "properties": {
        "hierarchy": [
          "tgn:2213386",
          "tgn:1000001",
          "tgn:7012149",
          "tgn:2002126",
          "tgn:7007827",
          "tgn:7029392"
        ],
        "placetype": [
          "aat:300008761"
        ],
        "id": 2213386,
        "name:xx": "Cabin Hollow"
      }
    },
    {
      "geometry": {
        "type": "Point",
        "coordinates": [
          -111.5333,
          41.1
        ]
      },
      "type": "Feature",
      "properties": {
        "hierarchy": [
          "tgn:2213387",
          "tgn:1000001",
          "tgn:7012149",
          "tgn:2002115",
          "tgn:7007827",
          "tgn:7029392"
        ],
        "placetype": [
          "aat:300008761"
        ],
        "id": 2213387,
        "name:xx": "Cabin Hollow"
      }
    },
    {
      "geometry": {
        "type": "Point",
        "coordinates": [
          -112.2333,
          37.7333
        ]
      },
      "type": "Feature",
      "properties": {
        "hierarchy": [
          "tgn:2213388",
          "tgn:1000001",
          "tgn:2002109",
          "tgn:7012149",
          "tgn:7007827",
          "tgn:7029392"
        ],
        "placetype": [
          "aat:300008761"
        ],
        "id": 2213388,
        "name:xx": "Cabin Hollow"
      }
    },
    {
      "geometry": {
        "type": "Point",
        "coordinates": [
          -111.1667,
          41.3667
        ]
      },
      "type": "Feature",
      "properties": {
        "hierarchy": [
          "tgn:2213389",
          "tgn:1000001",
          "tgn:7012149",
          "tgn:2002117",
          "tgn:7007827",
          "tgn:7029392"
        ],
        "placetype": [
          "aat:300008761"
        ],
        "id": 2213389,
        "name:xx": "Cabin Hollow"
      }
    }
  ]
}
