{
  "geometry": {
    "type": "Point",
    "coordinates": [
      73.5667,
      31.7167
    ]
  },
  "type": "Feature",
  "properties": {
    "hierarchy": [
      "tgn:1083431",
      "tgn:1000004",
      "tgn:1001490",
      "tgn:1000133",
      "tgn:7029392"
    ],
    "placetype": [
      "aat:300008347"
    ],
    "id": 1083431,
    "name:xx": "Dhabān Singh"
  }
}
