{
  "geometry": {
    "type": "Point",
    "coordinates": [
      -123.3667,
      43.15
    ]
  },
  "type": "Feature",
  "properties": {
    "hierarchy": [
      "tgn:2319610",
      "tgn:1000001",
      "tgn:7012149",
      "tgn:2001706",
      "tgn:7007708",
      "tgn:7029392"
    ],
    "placetype": [
      "aat:300006191"
    ],
    "id": 2319610,
    "name:xx": "Eugene Log Pond"
  }
}
