{
  "geometry": {
    "type": "Point",
    "coordinates": [
      -120.1167,
      48.85
    ]
  },
  "type": "Feature",
  "properties": {
    "hierarchy": [
      "tgn:2504106",
      "tgn:1000001",
      "tgn:7012149",
      "tgn:1002742",
      "tgn:7007920",
      "tgn:7029392"
    ],
    "placetype": [
      "aat:300008680"
    ],
    "id": 2504106,
    "name:xx": "Meadow Lake"
  }
}
