{
  "geometry": {
    "type": "Point",
    "coordinates": [
      9.8333,
      47.5167
    ]
  },
  "type": "Feature",
  "properties": {
    "hierarchy": [
      "tgn:1106038",
      "tgn:7018001",
      "tgn:1000003",
      "tgn:1000062",
      "tgn:7029392"
    ],
    "placetype": [
      "aat:300008795"
    ],
    "id": 1106038,
    "name:xx": "Pfänder"
  }
}
