{
  "geometry": {
    "type": "Point",
    "coordinates": [
      -109.5667,
      39.1167
    ]
  },
  "type": "Feature",
  "properties": {
    "hierarchy": [
      "tgn:2214702",
      "tgn:1000001",
      "tgn:7012149",
      "tgn:2002110",
      "tgn:7007827",
      "tgn:7029392"
    ],
    "placetype": [
      "aat:300008761"
    ],
    "id": 2214702,
    "name:xx": "Calf Canyon"
  }
}
