{
  "geometry": {
    "type": "Point",
    "coordinates": [
      -102.2833,
      30.8833
    ]
  },
  "type": "Feature",
  "properties": {
    "hierarchy": [
      "tgn:2102548",
      "tgn:1000001",
      "tgn:7012149",
      "tgn:2002055",
      "tgn:7007826",
      "tgn:7029392"
    ],
    "placetype": [
      "aat:300008347",
      "aat:300387210"
    ],
    "id": 2102548,
    "name:xx": "Bakersfield"
  }
}
