{
  "geometry": {
    "type": "Point",
    "coordinates": [
      -159.9333,
      22.0167
    ]
  },
  "type": "Feature",
  "properties": {
    "hierarchy": [
      "tgn:1114170",
      "tgn:1002534",
      "tgn:1000001",
      "tgn:7012149",
      "tgn:7007249",
      "tgn:7029392"
    ],
    "placetype": [
      "aat:300008713"
    ],
    "id": 1114170,
    "name:xx": "Kaulakahi Channel"
  }
}
