{
  "geometry": {
    "type": "Point",
    "coordinates": [
      -78.15,
      36.0833
    ]
  },
  "type": "Feature",
  "properties": {
    "hierarchy": [
      "tgn:2169920",
      "tgn:1000001",
      "tgn:7012149",
      "tgn:7007709",
      "tgn:7029392"
    ],
    "placetype": [
      "aat:300008706"
    ],
    "id": 2169920,
    "name:xx": "Big Peachtree Creek"
  }
}
