{
  "geometry": {
    "type": "Point",
    "coordinates": [
      -110.8833,
      37.05
    ]
  },
  "type": "Feature",
  "properties": {
    "hierarchy": [
      "tgn:2553436",
      "tgn:1000001",
      "tgn:7012149",
      "tgn:2002119",
      "tgn:7007827",
      "tgn:7029392"
    ],
    "placetype": [
      "aat:300008761"
    ],
    "id": 2553436,
    "name:xx": "Oak Canyon"
  }
}
