{
  "geometry": {
    "type": "Point",
    "coordinates": [
      -122.8667,
      43.35
    ]
  },
  "type": "Feature",
  "properties": {
    "hierarchy": [
      "tgn:2322094",
      "tgn:1000001",
      "tgn:7012149",
      "tgn:2001706",
      "tgn:7007708",
      "tgn:7029392"
    ],
    "placetype": [
      "aat:300008706"
    ],
    "id": 2322094,
    "name:xx": "Fall Creek"
  }
}
