{
  "geometry": {
    "type": "Point",
    "coordinates": [
      -139.4167,
      59.7833
    ]
  },
  "type": "Feature",
  "properties": {
    "hierarchy": [
      "tgn:2607723",
      "tgn:7006450",
      "tgn:1000001",
      "tgn:7012149",
      "tgn:7030574",
      "tgn:7029392"
    ],
    "placetype": [
      "aat:300008798"
    ],
    "id": 2607723,
    "name:xx": "Rasmuson, Mount"
  }
}
