{
  "geometry": {
    "type": "Point",
    "coordinates": [
      -77.35,
      38.6667
    ]
  },
  "type": "Feature",
  "properties": {
    "hierarchy": [
      "tgn:2392596",
      "tgn:1000001",
      "tgn:7012149",
      "tgn:7015778",
      "tgn:7007919",
      "tgn:7029392"
    ],
    "placetype": [
      "aat:300008699"
    ],
    "id": 2392596,
    "name:xx": "Hoadly Run"
  }
}
