{
  "geometry": {
    "type": "Point",
    "coordinates": [
      -112.4833,
      46.45
    ]
  },
  "type": "Feature",
  "properties": {
    "hierarchy": [
      "tgn:2448823",
      "tgn:1000001",
      "tgn:7012149",
      "tgn:2001298",
      "tgn:7007524",
      "tgn:7029392"
    ],
    "placetype": [
      "aat:300008697"
    ],
    "id": 2448823,
    "name:xx": "Limburger Spring"
  }
}
