{
  "geometry": {
    "type": "Point",
    "coordinates": [
      -87.15,
      37.7167
    ]
  },
  "type": "Feature",
  "properties": {
    "hierarchy": [
      "tgn:2167856",
      "tgn:1000001",
      "tgn:7012149",
      "tgn:2000786",
      "tgn:7007255",
      "tgn:7029392"
    ],
    "placetype": [
      "aat:300006075"
    ],
    "id": 2167856,
    "name:xx": "Big Ditch"
  }
}
