{
  "geometry": {
    "type": "Point",
    "coordinates": [
      12.383333,
      47.85
    ]
  },
  "type": "Feature",
  "properties": {
    "hierarchy": [
      "tgn:7076373",
      "tgn:7003669",
      "tgn:1000003",
      "tgn:7000084",
      "tgn:7029392"
    ],
    "placetype": [
      "aat:300006891"
    ],
    "id": 7076373,
    "name:xx": "Schloß Herrenchiemsee"
  }
}
