{
  "geometry": {
    "type": "Point",
    "coordinates": [
      -89.3833,
      45.65
    ]
  },
  "type": "Feature",
  "properties": {
    "hierarchy": [
      "tgn:2720442",
      "tgn:1000001",
      "tgn:7012149",
      "tgn:2002342",
      "tgn:7007922",
      "tgn:7029392"
    ],
    "placetype": [
      "aat:300008680"
    ],
    "id": 2720442,
    "name:xx": "Thunder Lake"
  }
}
