{
  "geometry": {
    "type": "Point",
    "coordinates": [
      -91.3167,
      41.1833
    ]
  },
  "type": "Feature",
  "properties": {
    "hierarchy": [
      "tgn:2034429",
      "tgn:1000001",
      "tgn:7012149",
      "tgn:2000618",
      "tgn:7007253",
      "tgn:7029392"
    ],
    "placetype": [
      "aat:300008347"
    ],
    "id": 2034429,
    "name:xx": "Cairo"
  }
}
