{
  "geometry": {
    "type": "Point",
    "coordinates": [
      -87.2833,
      36.0167
    ]
  },
  "type": "Feature",
  "properties": {
    "hierarchy": [
      "tgn:2427527",
      "tgn:1000001",
      "tgn:7012149",
      "tgn:2001858",
      "tgn:7007825",
      "tgn:7029392"
    ],
    "placetype": [
      "aat:300008761"
    ],
    "id": 2427527,
    "name:xx": "Jordon Hollow"
  }
}
