{
  "geometry": {
    "type": "Point",
    "coordinates": [
      -108.9833,
      33.0667
    ]
  },
  "type": "Feature",
  "properties": {
    "hierarchy": [
      "tgn:2309563",
      "tgn:1000001",
      "tgn:7012149",
      "tgn:2001437",
      "tgn:7007566",
      "tgn:7029392"
    ],
    "placetype": [
      "aat:300006191"
    ],
    "id": 2309563,
    "name:xx": "East Walnut Tank"
  }
}
