{
  "geometry": {
    "type": "Point",
    "coordinates": [
      -91.3333,
      40.1833
    ]
  },
  "type": "Feature",
  "properties": {
    "hierarchy": [
      "tgn:2447152",
      "tgn:1002134",
      "tgn:1000001",
      "tgn:7012149",
      "tgn:7007251",
      "tgn:7029392"
    ],
    "placetype": [
      "aat:300008699"
    ],
    "id": 2447152,
    "name:xx": "Lick Branch"
  }
}
