{
  "geometry": {
    "type": "Point",
    "coordinates": [
      -122.8667,
      40.4667
    ]
  },
  "type": "Feature",
  "properties": {
    "hierarchy": [
      "tgn:2288690",
      "tgn:1000001",
      "tgn:7012149",
      "tgn:7007157",
      "tgn:2000188",
      "tgn:7029392"
    ],
    "placetype": [
      "aat:300008706"
    ],
    "id": 2288690,
    "name:xx": "Ditch Fork Duncan Creek"
  }
}
