{
  "geometry": {
    "type": "Point",
    "coordinates": [
      121.2333,
      42.4333
    ]
  },
  "type": "Feature",
  "properties": {
    "hierarchy": [
      "tgn:1070010",
      "tgn:1000004",
      "tgn:1001390",
      "tgn:1000111",
      "tgn:7029392"
    ],
    "placetype": [
      "aat:300008347"
    ],
    "id": 1070010,
    "name:xx": "Liushudixia"
  }
}
