{
  "geometry": {
    "type": "Point",
    "coordinates": [
      -120.15,
      45.1667
    ]
  },
  "type": "Feature",
  "properties": {
    "hierarchy": [
      "tgn:2717355",
      "tgn:1000001",
      "tgn:7012149",
      "tgn:2001707",
      "tgn:7007708",
      "tgn:7029392"
    ],
    "placetype": [
      "aat:300008347"
    ],
    "id": 2717355,
    "name:xx": "Thirtymile"
  }
}
