{
  "geometry": {
    "type": "Point",
    "coordinates": [
      -66.6667,
      45.9667
    ]
  },
  "type": "Feature",
  "properties": {
    "hierarchy": [
      "tgn:1014094",
      "tgn:7005685",
      "tgn:1000001",
      "tgn:7005799",
      "tgn:7029392"
    ],
    "placetype": [
      "aat:300008347"
    ],
    "id": 1014094,
    "name:xx": "Nashwaaksis"
  }
}
