{
  "type": "FeatureCollection",
  "features": [
    {
      "geometry": {
        "type": "Point",
        "coordinates": [
          -87.4667,
          39.5
        ]
      },
      "type": "Feature",
      "properties": {
        "hierarchy": [
          "tgn:2033550",
          "tgn:1000001",
          "tgn:7012149",
          "tgn:2000559",
          "tgn:7007252",
          "tgn:7029392"
        ],
        "placetype": [
          "aat:300008347"
        ],
        "id": 2033550,
        "name:xx": "Saint Mary-of-the-Woods"
      }
    },
    {
      "geometry": {
        "type": "Point",
        "coordinates": [
          -85.85,
          38.35
        ]
      },
      "type": "Feature",
      "properties": {
        "hierarchy": [
          "tgn:2033552",
          "tgn:1000001",
          "tgn:7012149",
          "tgn:1002376",
          "tgn:7007252",
          "tgn:7029392"
        ],
        "placetype": [
          "aat:300008347",
          "aat:300387210"
        ],
        "id": 2033552,
        "name:xx": "Saint Marys"
      }
    },
    {
      "geometry": {
        "type": "Point",
        "coordinates": [
          -85.3333,
          39.35
        ]
      },
      "type": "Feature",
      "properties": {
        "hierarchy": [
          "tgn:2033553",
          "tgn:1000001",
          "tgn:1002325",
          "tgn:7012149",
          "tgn:7007252",
          "tgn:7029392"
        ],
        "placetype": [
          "aat:300008347"
        ],
        "id": 2033553,
        "name:xx": "Saint Maurice"
      }
    },
    {
      "geometry": {
        "type": "Point",
        "coordinates": [
          -86.8,
          38.1667
        ]
      },
      "type": "Feature",
      "properties": {
        "hierarchy": [
          "tgn:2033554",
          "tgn:1000001",
          "tgn:7012149",
          "tgn:2000555",
          "tgn:7007252",
          "tgn:7029392"
        ],
        "placetype": [
          "aat:300008347"
        ],
        "id": 2033554,
        "name:xx": "Saint Meinrad"
      }
    },
    {
      "geometry": {
        "type": "Point",
        "coordinates": [
          -85.5833,
          39.4333
        ]
      },
      "type": "Feature",
      "properties": {
        "hierarchy": [
          "tgn:2033555",
          "tgn:1000001",
          "tgn:1002325",
          "tgn:7012149",
          "tgn:7007252",
          "tgn:7029392"
        ],
        "placetype": [
          "aat:300008347"
        ],
        "id": 2033555,
        "name:xx": "Saint Omer"
      }
    },
    {
      "geometry": {
        "type": "Point",
        "coordinates": [
          -85.6167,
          39.4167
        ]
      },
      "type": "Feature",
      "properties": {
        "hierarchy": [
          "tgn:2033556",
          "tgn:1000001",
          "tgn:1002325",
          "tgn:7012149",
          "tgn:7007252",
          "tgn:7029392"
        ],
        "placetype": [
          "aat:300008347"
        ],
        "id": 2033556,
        "name:xx": "Saint Paul"
      }
    }
  ]
}
