{
  "geometry": {
    "type": "Point",
    "coordinates": [
      -108.6833,
      31.5833
    ]
  },
  "type": "Feature",
  "properties": {
    "hierarchy": [
      "tgn:2568576",
      "tgn:1000001",
      "tgn:7012149",
      "tgn:2001440",
      "tgn:7007566",
      "tgn:7029392"
    ],
    "placetype": [
      "aat:300006191"
    ],
    "id": 2568576,
    "name:xx": "Park Tank"
  }
}
