{
  "geometry": {
    "type": "Point",
    "coordinates": [
      59.4667,
      51.55
    ]
  },
  "type": "Feature",
  "properties": {
    "hierarchy": [
      "tgn:1060262",
      "tgn:1000004",
      "tgn:1003398",
      "tgn:7018214",
      "tgn:7002435",
      "tgn:7029392"
    ],
    "placetype": [
      "aat:300008347"
    ],
    "id": 1060262,
    "name:xx": "Terensay"
  }
}
