{
  "type": "FeatureCollection",
  "features": [
    {
      "geometry": {
        "type": "Point",
        "coordinates": [
          -103.266667,
          24.95
        ]
      },
      "type": "Feature",
      "properties": {
        "hierarchy": [
          "tgn:7368650",
          "tgn:7005583",
          "tgn:1000001",
          "tgn:7005560",
          "tgn:7029392"
        ],
        "placetype": [
          "aat:300000241"
        ],
        "id": 7368650,
        "name:xx": "Rancho Infiernillo"
      }
    },
    {
      "geometry": {
        "type": "Point",
        "coordinates": [
          -99.941667,
          24.518056
        ]
      },
      "type": "Feature",
      "properties": {
        "hierarchy": [
          "tgn:7368652",
          "tgn:1000001",
          "tgn:7005589",
          "tgn:7005560",
          "tgn:7029392"
        ],
        "placetype": [
          "aat:300008795"
        ],
        "id": 7368652,
        "name:xx": "Infiernillo, Cerro"
      }
    },
    {
      "geometry": {
        "type": "Point",
        "coordinates": [
          -112.183333,
          28.966667
        ]
      },
      "type": "Feature",
      "properties": {
        "hierarchy": [
          "tgn:7368653",
          "tgn:1000001",
          "tgn:1001960",
          "tgn:7005560",
          "tgn:7029392"
        ],
        "placetype": [
          "aat:300387026"
        ],
        "id": 7368653,
        "name:xx": "Infiernillo, Canel del"
      }
    },
    {
      "geometry": {
        "type": "Point",
        "coordinates": [
          -101.766667,
          25.633333
        ]
      },
      "type": "Feature",
      "properties": {
        "hierarchy": [
          "tgn:7368655",
          "tgn:1001853",
          "tgn:1000001",
          "tgn:7005560",
          "tgn:7029392"
        ],
        "placetype": [
          "aat:300266554",
          "aat:300008699"
        ],
        "id": 7368655,
        "name:xx": "Infiernillo, Arroyo del"
      }
    },
    {
      "geometry": {
        "type": "Point",
        "coordinates": [
          -102.15,
          18.15
        ]
      },
      "type": "Feature",
      "properties": {
        "hierarchy": [
          "tgn:7368656",
          "tgn:7005585",
          "tgn:1000001",
          "tgn:7005560",
          "tgn:7029392"
        ],
        "placetype": [
          "aat:300008347"
        ],
        "id": 7368656,
        "name:xx": "Infiernillo"
      }
    },
    {
      "geometry": {
        "type": "Point",
        "coordinates": [
          -95.25,
          18.033333
        ]
      },
      "type": "Feature",
      "properties": {
        "hierarchy": [
          "tgn:7368657",
          "tgn:1000001",
          "tgn:7005599",
          "tgn:7005560",
          "tgn:7029392"
        ],
        "placetype": [
          "aat:300008347"
        ],
        "id": 7368657,
        "name:xx": "Infiernillo"
      }
    },
    {
      "geometry": {
        "type": "Point",
        "coordinates": [
          -101.6,
          17.733333
        ]
      },
      "type": "Feature",
      "properties": {
        "hierarchy": [
          "tgn:7368658",
          "tgn:7005585",
          "tgn:1000001",
          "tgn:7005560",
          "tgn:7029392"
        ],
        "placetype": [
          "aat:300008347"
        ],
        "id": 7368658,
        "name:xx": "Infiernillo"
      }
    }
  ]
}
