{
  "geometry": {
    "type": "Point",
    "coordinates": [
      31.316818,
      31.05032
    ]
  },
  "type": "Feature",
  "properties": {
    "hierarchy": [
      "tgn:7540421",
      "tgn:7001242",
      "tgn:1001059",
      "tgn:7016833",
      "tgn:7029392"
    ],
    "placetype": [
      "aat:300008347"
    ],
    "name:en": "Minshāt al Badawī",
    "id": 7540421
  }
}
