{
  "geometry": {
    "type": "Point",
    "coordinates": [
      93.43116,
      25.84341
    ]
  },
  "type": "Feature",
  "properties": {
    "hierarchy": [
      "tgn:7551179",
      "tgn:1000004",
      "tgn:1001832",
      "tgn:7000198",
      "tgn:7029392"
    ],
    "placetype": [
      "aat:300008347"
    ],
    "name:en": "Diphu",
    "id": 7551179
  }
}
