{
  "geometry": {
    "type": "Point",
    "coordinates": [
      -78.3333,
      42.3833
    ]
  },
  "type": "Feature",
  "properties": {
    "hierarchy": [
      "tgn:2210325",
      "tgn:1000001",
      "tgn:1002245",
      "tgn:7012149",
      "tgn:7007568",
      "tgn:7029392"
    ],
    "placetype": [
      "aat:300008798"
    ],
    "id": 2210325,
    "name:xx": "Bush Hill"
  }
}
