{
  "geometry": {
    "type": "Point",
    "coordinates": [
      -84.2833,
      33.2667
    ]
  },
  "type": "Feature",
  "properties": {
    "hierarchy": [
      "tgn:2000417",
      "tgn:1000001",
      "tgn:7012149",
      "tgn:7007248",
      "tgn:7029392"
    ],
    "placetype": [
      "aat:300387145",
      "aat:300000771"
    ],
    "id": 2000417,
    "name:xx": "Spalding"
  }
}
