{
  "geometry": {
    "type": "Point",
    "coordinates": [
      -92.0333,
      34.35
    ]
  },
  "type": "Feature",
  "properties": {
    "hierarchy": [
      "tgn:2009182",
      "tgn:1000001",
      "tgn:7016172",
      "tgn:7012149",
      "tgn:2000139",
      "tgn:7029392"
    ],
    "placetype": [
      "aat:300008347",
      "aat:300387210"
    ],
    "id": 2009182,
    "name:xx": "Pastoria"
  }
}
