{
  "geometry": {
    "type": "Point",
    "coordinates": [
      -114.7167,
      36.0167
    ]
  },
  "type": "Feature",
  "properties": {
    "hierarchy": [
      "tgn:2175403",
      "tgn:1000001",
      "tgn:7012149",
      "tgn:7029392"
    ],
    "placetype": [
      "aat:300008761"
    ],
    "id": 2175403,
    "name:xx": "Black Canyon"
  }
}
