{
  "geometry": {
    "type": "Point",
    "coordinates": [
      -99.6275,
      19.355
    ]
  },
  "type": "Feature",
  "properties": {
    "hierarchy": [
      "tgn:7398801",
      "tgn:1000001",
      "tgn:1001893",
      "tgn:7005560",
      "tgn:7029392"
    ],
    "placetype": [
      "aat:300008347"
    ],
    "id": 7398801,
    "name:xx": "San Andrés Cuexcontitlán"
  }
}
