{
  "geometry": {
    "type": "Point",
    "coordinates": [
      -86.4833,
      39.2333
    ]
  },
  "type": "Feature",
  "properties": {
    "hierarchy": [
      "tgn:2031618",
      "tgn:1000001",
      "tgn:7012149",
      "tgn:1002678",
      "tgn:7007252",
      "tgn:7029392"
    ],
    "placetype": [
      "aat:300008347"
    ],
    "id": 2031618,
    "name:xx": "Dolan"
  }
}
