{
  "geometry": {
    "type": "Point",
    "coordinates": [
      87.5667,
      22.5667
    ]
  },
  "type": "Feature",
  "properties": {
    "hierarchy": [
      "tgn:1076104",
      "tgn:1000004",
      "tgn:7000198",
      "tgn:1001977",
      "tgn:7029392"
    ],
    "placetype": [
      "aat:300008347"
    ],
    "id": 1076104,
    "name:xx": "Magara"
  }
}
