{
  "geometry": {
    "type": "Point",
    "coordinates": [
      -120.2833,
      48.0833
    ]
  },
  "type": "Feature",
  "properties": {
    "hierarchy": [
      "tgn:2264053",
      "tgn:1000001",
      "tgn:1002260",
      "tgn:7012149",
      "tgn:7007920",
      "tgn:7029392"
    ],
    "placetype": [
      "aat:300266640"
    ],
    "id": 2264053,
    "name:xx": "Coyote Ridge"
  }
}
