{
  "type": "FeatureCollection",
  "features": [
    {
      "geometry": {
        "type": "Point",
        "coordinates": [
          -99.533333,
          23
        ]
      },
      "type": "Feature",
      "properties": {
        "hierarchy": [
          "tgn:7377210",
          "tgn:1000001",
          "tgn:7005597",
          "tgn:7005560",
          "tgn:7029392"
        ],
        "placetype": [
          "aat:300008347"
        ],
        "id": 7377210,
        "name:xx": "La Unión"
      }
    },
    {
      "geometry": {
        "type": "Point",
        "coordinates": [
          -96.85,
          20.066667
        ]
      },
      "type": "Feature",
      "properties": {
        "hierarchy": [
          "tgn:7377211",
          "tgn:1000001",
          "tgn:7005599",
          "tgn:7005560",
          "tgn:7029392"
        ],
        "placetype": [
          "aat:300008347"
        ],
        "id": 7377211,
        "name:xx": "La Unión"
      }
    },
    {
      "geometry": {
        "type": "Point",
        "coordinates": [
          -99.966667,
          18.833333
        ]
      },
      "type": "Feature",
      "properties": {
        "hierarchy": [
          "tgn:7377212",
          "tgn:1000001",
          "tgn:1001893",
          "tgn:7005560",
          "tgn:7029392"
        ],
        "placetype": [
          "aat:300008347"
        ],
        "id": 7377212,
        "name:xx": "La Unión"
      }
    },
    {
      "geometry": {
        "type": "Point",
        "coordinates": [
          -93.35,
          17.9
        ]
      },
      "type": "Feature",
      "properties": {
        "hierarchy": [
          "tgn:7377214",
          "tgn:1000001",
          "tgn:7005596",
          "tgn:7005560",
          "tgn:7029392"
        ],
        "placetype": [
          "aat:300008347"
        ],
        "id": 7377214,
        "name:xx": "La Unión"
      }
    },
    {
      "geometry": {
        "type": "Point",
        "coordinates": [
          -91.233333,
          17.616667
        ]
      },
      "type": "Feature",
      "properties": {
        "hierarchy": [
          "tgn:7377215",
          "tgn:1000001",
          "tgn:7005596",
          "tgn:7005560",
          "tgn:7029392"
        ],
        "placetype": [
          "aat:300008347"
        ],
        "id": 7377215,
        "name:xx": "La Unión"
      }
    },
    {
      "geometry": {
        "type": "Point",
        "coordinates": [
          -93.25,
          17.366667
        ]
      },
      "type": "Feature",
      "properties": {
        "hierarchy": [
          "tgn:7377216",
          "tgn:7005580",
          "tgn:1000001",
          "tgn:7005560",
          "tgn:7029392"
        ],
        "placetype": [
          "aat:300008347"
        ],
        "id": 7377216,
        "name:xx": "La Unión"
      }
    },
    {
      "geometry": {
        "type": "Point",
        "coordinates": [
          -93.883333,
          16.733333
        ]
      },
      "type": "Feature",
      "properties": {
        "hierarchy": [
          "tgn:7377217",
          "tgn:7005580",
          "tgn:1000001",
          "tgn:7005560",
          "tgn:7029392"
        ],
        "placetype": [
          "aat:300008347"
        ],
        "id": 7377217,
        "name:xx": "La Unión"
      }
    },
    {
      "geometry": {
        "type": "Point",
        "coordinates": [
          -93.416667,
          16.683333
        ]
      },
      "type": "Feature",
      "properties": {
        "hierarchy": [
          "tgn:7377218",
          "tgn:7005580",
          "tgn:1000001",
          "tgn:7005560",
          "tgn:7029392"
        ],
        "placetype": [
          "aat:300008347"
        ],
        "id": 7377218,
        "name:xx": "La Unión"
      }
    },
    {
      "geometry": {
        "type": "Point",
        "coordinates": [
          -93.933333,
          16.533333
        ]
      },
      "type": "Feature",
      "properties": {
        "hierarchy": [
          "tgn:7377219",
          "tgn:7005580",
          "tgn:1000001",
          "tgn:7005560",
          "tgn:7029392"
        ],
        "placetype": [
          "aat:300008347"
        ],
        "id": 7377219,
        "name:xx": "La Unión"
      }
    }
  ]
}
