{
  "type": "FeatureCollection",
  "features": [
    {
      "geometry": {
        "type": "Point",
        "coordinates": [
          -95.7667,
          40.6167
        ]
      },
      "type": "Feature",
      "properties": {
        "hierarchy": [
          "tgn:2336910",
          "tgn:1000001",
          "tgn:7012149",
          "tgn:2001381",
          "tgn:7007525",
          "tgn:7029392"
        ],
        "placetype": [
          "aat:300008706"
        ],
        "id": 2336910,
        "name:xx": "Fourmile Creek"
      }
    },
    {
      "geometry": {
        "type": "Point",
        "coordinates": [
          -96,
          40.9167
        ]
      },
      "type": "Feature",
      "properties": {
        "hierarchy": [
          "tgn:2336911",
          "tgn:1000001",
          "tgn:2001328",
          "tgn:7012149",
          "tgn:7007525",
          "tgn:7029392"
        ],
        "placetype": [
          "aat:300008706"
        ],
        "id": 2336911,
        "name:xx": "Fourmile Creek"
      }
    },
    {
      "geometry": {
        "type": "Point",
        "coordinates": [
          -115.85,
          41.55
        ]
      },
      "type": "Feature",
      "properties": {
        "hierarchy": [
          "tgn:2336912",
          "tgn:1000001",
          "tgn:2001411",
          "tgn:7012149",
          "tgn:7007526",
          "tgn:7029392"
        ],
        "placetype": [
          "aat:300008706"
        ],
        "id": 2336912,
        "name:xx": "Fourmile Creek"
      }
    },
    {
      "geometry": {
        "type": "Point",
        "coordinates": [
          -78.5,
          42
        ]
      },
      "type": "Feature",
      "properties": {
        "hierarchy": [
          "tgn:2336913",
          "tgn:1000001",
          "tgn:1002245",
          "tgn:7012149",
          "tgn:7007568",
          "tgn:7029392"
        ],
        "placetype": [
          "aat:300008706"
        ],
        "id": 2336913,
        "name:xx": "Fourmile Creek"
      }
    },
    {
      "geometry": {
        "type": "Point",
        "coordinates": [
          -79.0167,
          43.1667
        ]
      },
      "type": "Feature",
      "properties": {
        "hierarchy": [
          "tgn:2336914",
          "tgn:1000001",
          "tgn:7012149",
          "tgn:1002718",
          "tgn:7007568",
          "tgn:7029392"
        ],
        "placetype": [
          "aat:300008706"
        ],
        "id": 2336914,
        "name:xx": "Fourmile Creek"
      }
    },
    {
      "geometry": {
        "type": "Point",
        "coordinates": [
          -80.6833,
          35.1
        ]
      },
      "type": "Feature",
      "properties": {
        "hierarchy": [
          "tgn:2336915",
          "tgn:1000001",
          "tgn:7012149",
          "tgn:7014021",
          "tgn:7007709",
          "tgn:7029392"
        ],
        "placetype": [
          "aat:300008706"
        ],
        "id": 2336915,
        "name:xx": "Fourmile Creek"
      }
    },
    {
      "geometry": {
        "type": "Point",
        "coordinates": [
          -100.8167,
          46.1
        ]
      },
      "type": "Feature",
      "properties": {
        "hierarchy": [
          "tgn:2336916",
          "tgn:1000001",
          "tgn:2001599",
          "tgn:7012149",
          "tgn:7007705",
          "tgn:7029392"
        ],
        "placetype": [
          "aat:300008706"
        ],
        "id": 2336916,
        "name:xx": "Fourmile Creek"
      }
    },
    {
      "geometry": {
        "type": "Point",
        "coordinates": [
          -82.35,
          38.4667
        ]
      },
      "type": "Feature",
      "properties": {
        "hierarchy": [
          "tgn:2336917",
          "tgn:1000001",
          "tgn:7012149",
          "tgn:2001615",
          "tgn:7007706",
          "tgn:7029392"
        ],
        "placetype": [
          "aat:300008706"
        ],
        "id": 2336917,
        "name:xx": "Fourmile Creek"
      }
    },
    {
      "geometry": {
        "type": "Point",
        "coordinates": [
          -84.3667,
          39.0667
        ]
      },
      "type": "Feature",
      "properties": {
        "hierarchy": [
          "tgn:2336918",
          "tgn:1000001",
          "tgn:7012149",
          "tgn:1002441",
          "tgn:7007706",
          "tgn:7029392"
        ],
        "placetype": [
          "aat:300008706"
        ],
        "id": 2336918,
        "name:xx": "Fourmile Creek"
      }
    },
    {
      "geometry": {
        "type": "Point",
        "coordinates": [
          -81.8667,
          39.2
        ]
      },
      "type": "Feature",
      "properties": {
        "hierarchy": [
          "tgn:2336919",
          "tgn:2001610",
          "tgn:1000001",
          "tgn:7012149",
          "tgn:7007706",
          "tgn:7029392"
        ],
        "placetype": [
          "aat:300008706"
        ],
        "id": 2336919,
        "name:xx": "Fourmile Creek"
      }
    }
  ]
}
