{
  "type": "FeatureCollection",
  "features": [
    {
      "geometry": {
        "type": "Point",
        "coordinates": [
          -83.2,
          31.6333
        ]
      },
      "type": "Feature",
      "properties": {
        "hierarchy": [
          "tgn:2277330",
          "tgn:1000001",
          "tgn:7012149",
          "tgn:2000368",
          "tgn:7007248",
          "tgn:7029392"
        ],
        "placetype": [
          "aat:300006191"
        ],
        "id": 2277330,
        "name:xx": "Davis Lake"
      }
    },
    {
      "geometry": {
        "type": "Point",
        "coordinates": [
          -111.7833,
          43.9667
        ]
      },
      "type": "Feature",
      "properties": {
        "hierarchy": [
          "tgn:2277331",
          "tgn:1000001",
          "tgn:7012149",
          "tgn:2000473",
          "tgn:7007250",
          "tgn:7029392"
        ],
        "placetype": [
          "aat:300008680"
        ],
        "id": 2277331,
        "name:xx": "Davis Lake"
      }
    },
    {
      "geometry": {
        "type": "Point",
        "coordinates": [
          -85.5833,
          41.4167
        ]
      },
      "type": "Feature",
      "properties": {
        "hierarchy": [
          "tgn:2277332",
          "tgn:1000001",
          "tgn:7012149",
          "tgn:1002723",
          "tgn:7007252",
          "tgn:7029392"
        ],
        "placetype": [
          "aat:300008680"
        ],
        "id": 2277332,
        "name:xx": "Davis Lake"
      }
    },
    {
      "geometry": {
        "type": "Point",
        "coordinates": [
          -92.0667,
          32.1333
        ]
      },
      "type": "Feature",
      "properties": {
        "hierarchy": [
          "tgn:2277333",
          "tgn:1000001",
          "tgn:2000864",
          "tgn:7012149",
          "tgn:7007256",
          "tgn:7029392"
        ],
        "placetype": [
          "aat:300008680"
        ],
        "id": 2277333,
        "name:xx": "Davis Lake"
      }
    },
    {
      "geometry": {
        "type": "Point",
        "coordinates": [
          -91.45,
          30.7667
        ]
      },
      "type": "Feature",
      "properties": {
        "hierarchy": [
          "tgn:2277334",
          "tgn:1000001",
          "tgn:7012149",
          "tgn:2000916",
          "tgn:7007256",
          "tgn:7029392"
        ],
        "placetype": [
          "aat:300008905"
        ],
        "id": 2277334,
        "name:xx": "Davis Lake"
      }
    },
    {
      "geometry": {
        "type": "Point",
        "coordinates": [
          -86.0167,
          41.8167
        ]
      },
      "type": "Feature",
      "properties": {
        "hierarchy": [
          "tgn:2277335",
          "tgn:1000001",
          "tgn:1002243",
          "tgn:7012149",
          "tgn:7007520",
          "tgn:7029392"
        ],
        "placetype": [
          "aat:300008680"
        ],
        "id": 2277335,
        "name:xx": "Davis Lake"
      }
    },
    {
      "geometry": {
        "type": "Point",
        "coordinates": [
          -85.9167,
          42.2667
        ]
      },
      "type": "Feature",
      "properties": {
        "hierarchy": [
          "tgn:2277336",
          "tgn:1000001",
          "tgn:7012149",
          "tgn:1002967",
          "tgn:7007520",
          "tgn:7029392"
        ],
        "placetype": [
          "aat:300008680"
        ],
        "id": 2277336,
        "name:xx": "Davis Lake"
      }
    },
    {
      "geometry": {
        "type": "Point",
        "coordinates": [
          -83.2833,
          42.8167
        ]
      },
      "type": "Feature",
      "properties": {
        "hierarchy": [
          "tgn:2277337",
          "tgn:1000001",
          "tgn:7012149",
          "tgn:1002737",
          "tgn:7007520",
          "tgn:7029392"
        ],
        "placetype": [
          "aat:300008680"
        ],
        "id": 2277337,
        "name:xx": "Davis Lake"
      }
    },
    {
      "geometry": {
        "type": "Point",
        "coordinates": [
          -85.4167,
          43.1333
        ]
      },
      "type": "Feature",
      "properties": {
        "hierarchy": [
          "tgn:2277338",
          "tgn:1000001",
          "tgn:7012149",
          "tgn:1002540",
          "tgn:7007520",
          "tgn:7029392"
        ],
        "placetype": [
          "aat:300008680"
        ],
        "id": 2277338,
        "name:xx": "Davis Lake"
      }
    },
    {
      "geometry": {
        "type": "Point",
        "coordinates": [
          -85.85,
          44.7667
        ]
      },
      "type": "Feature",
      "properties": {
        "hierarchy": [
          "tgn:2277339",
          "tgn:1000001",
          "tgn:7012149",
          "tgn:2000971",
          "tgn:7007520",
          "tgn:7029392"
        ],
        "placetype": [
          "aat:300008680"
        ],
        "id": 2277339,
        "name:xx": "Davis Lake"
      }
    }
  ]
}
