{
  "geometry": {
    "type": "Point",
    "coordinates": [
      -112.7167,
      36.7667
    ]
  },
  "type": "Feature",
  "properties": {
    "hierarchy": [
      "tgn:2649431",
      "tgn:1000001",
      "tgn:7006451",
      "tgn:7012149",
      "tgn:2000098",
      "tgn:7029392"
    ],
    "placetype": [
      "aat:300386845"
    ],
    "id": 2649431,
    "name:xx": "Scotts Hole"
  }
}
