{
  "geometry": {
    "type": "Point",
    "coordinates": [
      -105.7167,
      40.8333
    ]
  },
  "type": "Feature",
  "properties": {
    "hierarchy": [
      "tgn:2572924",
      "tgn:1000001",
      "tgn:7012149",
      "tgn:2000226",
      "tgn:7007158",
      "tgn:7029392"
    ],
    "placetype": [
      "aat:300008706"
    ],
    "id": 2572924,
    "name:xx": "Pearl Creek"
  }
}
