{
  "geometry": {
    "type": "Point",
    "coordinates": [
      -39.3333,
      -5.2667
    ]
  },
  "type": "Feature",
  "properties": {
    "hierarchy": [
      "tgn:1022635",
      "tgn:7006064",
      "tgn:1000047",
      "tgn:7002455",
      "tgn:1000002",
      "tgn:7029392"
    ],
    "placetype": [
      "aat:300008347"
    ],
    "id": 1022635,
    "name:xx": "Quixeramobim"
  }
}
