{
  "geometry": {
    "type": "Point",
    "coordinates": [
      -81.95,
      26.4833
    ]
  },
  "type": "Feature",
  "properties": {
    "hierarchy": [
      "tgn:2360940",
      "tgn:1000001",
      "tgn:7012149",
      "tgn:1002582",
      "tgn:7007240",
      "tgn:7029392"
    ],
    "placetype": [
      "aat:300008680"
    ],
    "id": 2360940,
    "name:xx": "Grassy Pond"
  }
}
