{
  "geometry": {
    "type": "Point",
    "coordinates": [
      -0.406,
      52.618
    ]
  },
  "type": "Feature",
  "properties": {
    "hierarchy": [
      "tgn:7030767",
      "tgn:7002445",
      "tgn:1000003",
      "tgn:7026520",
      "tgn:7008591",
      "tgn:7029392"
    ],
    "placetype": [
      "aat:300008347",
      "aat:300008372"
    ],
    "id": 7030767,
    "name:xx": "Barnack"
  }
}
