{
  "geometry": {
    "type": "Point",
    "coordinates": [
      -81.3333,
      8.7833
    ]
  },
  "type": "Feature",
  "properties": {
    "hierarchy": [
      "tgn:1018893",
      "tgn:7593354",
      "tgn:1000001",
      "tgn:7005565",
      "tgn:7029392"
    ],
    "placetype": [
      "aat:300008347"
    ],
    "id": 1018893,
    "name:xx": "Santa Catalina"
  }
}
