{
  "geometry": {
    "type": "Point",
    "coordinates": [
      13.8333,
      64.25
    ]
  },
  "type": "Feature",
  "properties": {
    "hierarchy": [
      "tgn:1048728",
      "tgn:7003645",
      "tgn:1000003",
      "tgn:1000088",
      "tgn:7029392"
    ],
    "placetype": [
      "aat:300008347"
    ],
    "id": 1048728,
    "name:xx": "Sørli"
  }
}
