{
  "geometry": {
    "type": "Point",
    "coordinates": [
      -88.4167,
      37.8167
    ]
  },
  "type": "Feature",
  "properties": {
    "hierarchy": [
      "tgn:2766541",
      "tgn:1000001",
      "tgn:7012149",
      "tgn:7007251",
      "tgn:7029392"
    ],
    "placetype": [
      "aat:300008706"
    ],
    "id": 2766541,
    "name:xx": "White Oak Creek"
  }
}
