{
  "geometry": {
    "type": "Point",
    "coordinates": [
      90.6167,
      22.25
    ]
  },
  "type": "Feature",
  "properties": {
    "hierarchy": [
      "tgn:1135809",
      "tgn:1000004",
      "tgn:7000190",
      "tgn:1000105",
      "tgn:7029392"
    ],
    "placetype": [
      "aat:300387055"
    ],
    "id": 1135809,
    "name:xx": "Tetulia"
  }
}
