{
  "geometry": {
    "type": "Point",
    "coordinates": [
      -111.8833,
      45.7667
    ]
  },
  "type": "Feature",
  "properties": {
    "hierarchy": [
      "tgn:2061763",
      "tgn:1000001",
      "tgn:7012149",
      "tgn:2001288",
      "tgn:7007524",
      "tgn:7029392"
    ],
    "placetype": [
      "aat:300008347",
      "aat:300387210"
    ],
    "id": 2061763,
    "name:xx": "Summit Valley"
  }
}
