{
  "geometry": {
    "type": "Point",
    "coordinates": [
      38.2833,
      55.55
    ]
  },
  "type": "Feature",
  "properties": {
    "hierarchy": [
      "tgn:1138344",
      "tgn:1000004",
      "tgn:7011573",
      "tgn:7018214",
      "tgn:7002435",
      "tgn:7029392"
    ],
    "placetype": [
      "aat:300008347"
    ],
    "id": 1138344,
    "name:xx": "Safonovo"
  }
}
