{
  "geometry": {
    "type": "Point",
    "coordinates": [
      140.4333,
      35.6833
    ]
  },
  "type": "Feature",
  "properties": {
    "hierarchy": [
      "tgn:1081276",
      "tgn:1000971",
      "tgn:1000004",
      "tgn:7000894",
      "tgn:1000120",
      "tgn:7029392"
    ],
    "placetype": [
      "aat:300008347"
    ],
    "id": 1081276,
    "name:xx": "Shibayama"
  }
}
