{
  "geometry": {
    "type": "Point",
    "coordinates": [
      -86.5333,
      41.9667
    ]
  },
  "type": "Feature",
  "properties": {
    "hierarchy": [
      "tgn:2463131",
      "tgn:1000001",
      "tgn:1002182",
      "tgn:7012149",
      "tgn:7007520",
      "tgn:7029392"
    ],
    "placetype": [
      "aat:300008347"
    ],
    "id": 2463131,
    "name:xx": "Livingston"
  }
}
