{
  "geometry": {
    "type": "Point",
    "coordinates": [
      -113.35,
      45.1333
    ]
  },
  "type": "Feature",
  "properties": {
    "hierarchy": [
      "tgn:2660960",
      "tgn:1000001",
      "tgn:2001260",
      "tgn:7012149",
      "tgn:7007524",
      "tgn:7029392"
    ],
    "placetype": [
      "aat:300008706"
    ],
    "id": 2660960,
    "name:xx": "Short Creek"
  }
}
