{
  "geometry": {
    "type": "Point",
    "coordinates": [
      -103.7667,
      30.9667
    ]
  },
  "type": "Feature",
  "properties": {
    "hierarchy": [
      "tgn:2488845",
      "tgn:1000001",
      "tgn:7012149",
      "tgn:2002062",
      "tgn:7007826",
      "tgn:7029392"
    ],
    "placetype": [
      "aat:300006075"
    ],
    "id": 2488845,
    "name:xx": "Main Canal"
  }
}
