{
  "geometry": {
    "type": "Point",
    "coordinates": [
      34.755197,
      29.324214
    ]
  },
  "type": "Feature",
  "properties": {
    "hierarchy": [
      "tgn:7534199",
      "tgn:7001242",
      "tgn:7016833",
      "tgn:7001336",
      "tgn:7029392"
    ],
    "placetype": [
      "aat:300386968"
    ],
    "name:en": "Marsá Maḩash al Aa'lá",
    "id": 7534199
  }
}
