{
  "geometry": {
    "type": "Point",
    "coordinates": [
      -82.8167,
      29.6833
    ]
  },
  "type": "Feature",
  "properties": {
    "hierarchy": [
      "tgn:2211858",
      "tgn:1000001",
      "tgn:2000269",
      "tgn:7012149",
      "tgn:7007240",
      "tgn:7029392"
    ],
    "placetype": [
      "aat:300008680"
    ],
    "id": 2211858,
    "name:xx": "Buttonwood Pond"
  }
}
