{
  "geometry": {
    "type": "Point",
    "coordinates": [
      120.34843,
      23.00883
    ]
  },
  "type": "Feature",
  "properties": {
    "hierarchy": [
      "tgn:7470989",
      "tgn:1000004",
      "tgn:7490934",
      "tgn:1000141",
      "tgn:7029392"
    ],
    "placetype": [
      "aat:300008347"
    ],
    "id": 7470989,
    "name:xx": "Houliao"
  }
}
