{
  "geometry": {
    "type": "Point",
    "coordinates": [
      -80.3167,
      40.9167
    ]
  },
  "type": "Feature",
  "properties": {
    "hierarchy": [
      "tgn:2732944",
      "tgn:1000001",
      "tgn:7012149",
      "tgn:1002580",
      "tgn:7007710",
      "tgn:7029392"
    ],
    "placetype": [
      "aat:300008798"
    ],
    "id": 2732944,
    "name:xx": "Turkey Hill"
  }
}
