{
  "geometry": {
    "type": "Point",
    "coordinates": [
      -120.7833,
      44.7333
    ]
  },
  "type": "Feature",
  "properties": {
    "hierarchy": [
      "tgn:2427564",
      "tgn:1000001",
      "tgn:7012149",
      "tgn:2001712",
      "tgn:7007708",
      "tgn:7029392"
    ],
    "placetype": [
      "aat:300386845"
    ],
    "id": 2427564,
    "name:xx": "Jory Basin"
  }
}
