{
  "geometry": {
    "type": "Point",
    "coordinates": [
      135.7167,
      34.4167
    ]
  },
  "type": "Feature",
  "properties": {
    "hierarchy": [
      "tgn:1081577",
      "tgn:1000004",
      "tgn:1001012",
      "tgn:7000896",
      "tgn:1000120",
      "tgn:7029392"
    ],
    "placetype": [
      "aat:300008347"
    ],
    "id": 1081577,
    "name:xx": "Toriido"
  }
}
