{
  "geometry": {
    "type": "Point",
    "coordinates": [
      -116.1833,
      48.0667
    ]
  },
  "type": "Feature",
  "properties": {
    "hierarchy": [
      "tgn:2547686",
      "tgn:1000001",
      "tgn:2000460",
      "tgn:7012149",
      "tgn:7007250",
      "tgn:7029392"
    ],
    "placetype": [
      "aat:300008706"
    ],
    "id": 2547686,
    "name:xx": "North Fork Twin Creek"
  }
}
