{
  "geometry": {
    "type": "Point",
    "coordinates": [
      -92.9833,
      38.2333
    ]
  },
  "type": "Feature",
  "properties": {
    "hierarchy": [
      "tgn:2299931",
      "tgn:1000001",
      "tgn:7012149",
      "tgn:2001221",
      "tgn:7007523",
      "tgn:7029392"
    ],
    "placetype": [
      "aat:300008761"
    ],
    "id": 2299931,
    "name:xx": "Duffer Hollow"
  }
}
