{
  "geometry": {
    "type": "Point",
    "coordinates": [
      -105.5333,
      32.85
    ]
  },
  "type": "Feature",
  "properties": {
    "hierarchy": [
      "tgn:2474528",
      "tgn:1000001",
      "tgn:7012149",
      "tgn:2001447",
      "tgn:7007566",
      "tgn:7029392"
    ],
    "placetype": [
      "aat:300008697"
    ],
    "id": 2474528,
    "name:xx": "Lower Robinson Canyon Spring"
  }
}
