{
  "type": "FeatureCollection",
  "features": [
    {
      "geometry": {
        "type": "Point",
        "coordinates": [
          8.326,
          44.161
        ]
      },
      "type": "Feature",
      "properties": {
        "hierarchy": [
          "tgn:6000380",
          "tgn:1000003",
          "tgn:7003236",
          "tgn:1000080",
          "tgn:7029392"
        ],
        "placetype": [
          "aat:300008347",
          "aat:300000810",
          "aat:300048808",
          "aat:300167671",
          "aat:300019271",
          "aat:300008746"
        ],
        "id": 6000380,
        "name:xx": "Arene Candide"
      }
    },
    {
      "geometry": {
        "type": "Point",
        "coordinates": [
          22.354646,
          39.635357
        ]
      },
      "type": "Feature",
      "properties": {
        "hierarchy": [
          "tgn:6000387",
          "tgn:7002715",
          "tgn:7002731",
          "tgn:1000003",
          "tgn:1000074",
          "tgn:7029392"
        ],
        "placetype": [
          "aat:300008347",
          "aat:300000810",
          "aat:300167671",
          "aat:300008545"
        ],
        "id": 6000387,
        "name:xx": "Argissa"
      }
    }
  ]
}
