{
  "geometry": {
    "type": "Point",
    "coordinates": [
      73.966667,
      20.05
    ]
  },
  "type": "Feature",
  "properties": {
    "hierarchy": [
      "tgn:7577458",
      "tgn:1000004",
      "tgn:7000198",
      "tgn:1001895",
      "tgn:7029392"
    ],
    "placetype": [
      "aat:300008347"
    ],
    "name:en": "Khervādi",
    "id": 7577458
  }
}
