{
  "geometry": {
    "type": "Point",
    "coordinates": [
      14.8333,
      44.2167
    ]
  },
  "type": "Feature",
  "properties": {
    "hierarchy": [
      "tgn:1008189",
      "tgn:1000003",
      "tgn:7017304",
      "tgn:7006663",
      "tgn:7029392"
    ],
    "placetype": [
      "aat:300008791"
    ],
    "id": 1008189,
    "name:xx": "Molat"
  }
}
