{
  "geometry": {
    "type": "Point",
    "coordinates": [
      -117.8167,
      45.1167
    ]
  },
  "type": "Feature",
  "properties": {
    "hierarchy": [
      "tgn:2602327",
      "tgn:1000001",
      "tgn:7012149",
      "tgn:2001721",
      "tgn:7007708",
      "tgn:7029392"
    ],
    "placetype": [
      "aat:300008761"
    ],
    "id": 2602327,
    "name:xx": "Pyles Canyon"
  }
}
