{
  "geometry": {
    "type": "Point",
    "coordinates": [
      30.583658,
      29.22759
    ]
  },
  "type": "Feature",
  "properties": {
    "hierarchy": [
      "tgn:7540891",
      "tgn:7001242",
      "tgn:7001105",
      "tgn:7016833",
      "tgn:7029392"
    ],
    "placetype": [
      "aat:300008777"
    ],
    "name:en": "Madīnat al Ju'rān, Jabal",
    "id": 7540891
  }
}
