{
  "geometry": {
    "type": "Point",
    "coordinates": [
      -98.225,
      21.823611
    ]
  },
  "type": "Feature",
  "properties": {
    "hierarchy": [
      "tgn:7401329",
      "tgn:1000001",
      "tgn:7005599",
      "tgn:7005560",
      "tgn:7029392"
    ],
    "placetype": [
      "aat:300008347"
    ],
    "id": 7401329,
    "name:xx": "Bernabé Sánchez Fuentes"
  }
}
