{
  "geometry": {
    "type": "Point",
    "coordinates": [
      -110.0833,
      45.2667
    ]
  },
  "type": "Feature",
  "properties": {
    "hierarchy": [
      "tgn:2760450",
      "tgn:1000001",
      "tgn:7012149",
      "tgn:7007524",
      "tgn:7029392"
    ],
    "placetype": [
      "aat:300008707"
    ],
    "id": 2760450,
    "name:xx": "West Fork Stillwater River"
  }
}
