{
  "geometry": {
    "type": "Point",
    "coordinates": [
      34.3333,
      31.4167
    ]
  },
  "type": "Feature",
  "properties": {
    "hierarchy": [
      "tgn:7001390",
      "tgn:1000004",
      "tgn:1000119",
      "tgn:7029392"
    ],
    "placetype": [
      "aat:300387054",
      "aat:300387130",
      "aat:300387064",
      "aat:300387139"
    ],
    "name:en": "Gaza Strip",
    "id": 7001390,
    "name:xx": "Reẕuʻat ʻAzza"
  }
}
