{
  "geometry": {
    "type": "Point",
    "coordinates": [
      -79.4667,
      21.9167
    ]
  },
  "type": "Feature",
  "properties": {
    "hierarchy": [
      "tgn:1016431",
      "tgn:1001521",
      "tgn:1000001",
      "tgn:7004624",
      "tgn:7029392"
    ],
    "placetype": [
      "aat:300008347",
      "aat:300008389",
      "aat:300387512",
      "aat:300387223"
    ],
    "id": 1016431,
    "name:xx": "Sancti-Spíritus"
  }
}
