{
  "geometry": {
    "type": "Point",
    "coordinates": [
      -45.2833,
      -23.8833
    ]
  },
  "type": "Feature",
  "properties": {
    "hierarchy": [
      "tgn:1008853",
      "tgn:1001945",
      "tgn:1000047",
      "tgn:7002457",
      "tgn:1000002",
      "tgn:7029392"
    ],
    "placetype": [
      "aat:300008791"
    ],
    "id": 1008853,
    "name:xx": "São Sebastião, Ilha de"
  }
}
