{
  "type": "FeatureCollection",
  "features": [
    {
      "geometry": {
        "type": "Point",
        "coordinates": [
          31.510656,
          31.214082
        ]
      },
      "type": "Feature",
      "properties": {
        "hierarchy": [
          "tgn:7542360",
          "tgn:7001242",
          "tgn:1001059",
          "tgn:7016833",
          "tgn:7029392"
        ],
        "placetype": [
          "aat:300008347"
        ],
        "name:en": "'Izbat Ḩasan Madkūr",
        "id": 7542360
      }
    },
    {
      "geometry": {
        "type": "Point",
        "coordinates": [
          31.746575,
          31.221264
        ]
      },
      "type": "Feature",
      "properties": {
        "hierarchy": [
          "tgn:7542361",
          "tgn:7001242",
          "tgn:7016833",
          "tgn:1001225",
          "tgn:7029392"
        ],
        "placetype": [
          "aat:300000206"
        ],
        "name:en": "'Izbat Diyāb Mabrūk",
        "id": 7542361
      }
    },
    {
      "geometry": {
        "type": "Point",
        "coordinates": [
          31.742555,
          31.226819
        ]
      },
      "type": "Feature",
      "properties": {
        "hierarchy": [
          "tgn:7542362",
          "tgn:7001242",
          "tgn:7016833",
          "tgn:1001225",
          "tgn:7029392"
        ],
        "placetype": [
          "aat:300000206"
        ],
        "name:en": "'Izbat Wizārat az Zirā'ah",
        "id": 7542362
      }
    },
    {
      "geometry": {
        "type": "Point",
        "coordinates": [
          31.730208,
          31.222953
        ]
      },
      "type": "Feature",
      "properties": {
        "hierarchy": [
          "tgn:7542363",
          "tgn:7001242",
          "tgn:7016833",
          "tgn:1001225",
          "tgn:7029392"
        ],
        "placetype": [
          "aat:300000206"
        ],
        "name:en": "'Izbat Isḩāq",
        "id": 7542363
      }
    },
    {
      "geometry": {
        "type": "Point",
        "coordinates": [
          33.906349,
          30.364671
        ]
      },
      "type": "Feature",
      "properties": {
        "hierarchy": [
          "tgn:7542364",
          "tgn:7001242",
          "tgn:7016833",
          "tgn:7001335",
          "tgn:7029392"
        ],
        "placetype": [
          "aat:300008777"
        ],
        "name:en": "'Ubayd, Ra's",
        "id": 7542364
      }
    },
    {
      "geometry": {
        "type": "Point",
        "coordinates": [
          33.935556,
          30.415556
        ]
      },
      "type": "Feature",
      "properties": {
        "hierarchy": [
          "tgn:7542365",
          "tgn:7001242",
          "tgn:7016833",
          "tgn:7001335",
          "tgn:7029392"
        ],
        "placetype": [
          "aat:300006207"
        ],
        "name:en": "Bi'r ar Rashāydah",
        "id": 7542365
      }
    },
    {
      "geometry": {
        "type": "Point",
        "coordinates": [
          33.997916,
          30.219477
        ]
      },
      "type": "Feature",
      "properties": {
        "hierarchy": [
          "tgn:7542366",
          "tgn:7001242",
          "tgn:7016833",
          "tgn:7001335",
          "tgn:7029392"
        ],
        "placetype": [
          "aat:300379998"
        ],
        "name:en": "Fahdī, Wādī al",
        "id": 7542366
      }
    },
    {
      "geometry": {
        "type": "Point",
        "coordinates": [
          33.747795,
          30.386629
        ]
      },
      "type": "Feature",
      "properties": {
        "hierarchy": [
          "tgn:7542367",
          "tgn:7001242",
          "tgn:7016833",
          "tgn:7001335",
          "tgn:7029392"
        ],
        "placetype": [
          "aat:300008777"
        ],
        "name:en": "Şafrat al Ḩasanah",
        "id": 7542367
      }
    },
    {
      "geometry": {
        "type": "Point",
        "coordinates": [
          33.731654,
          30.236958
        ]
      },
      "type": "Feature",
      "properties": {
        "hierarchy": [
          "tgn:7542368",
          "tgn:7001242",
          "tgn:7016833",
          "tgn:7001335",
          "tgn:7029392"
        ],
        "placetype": [
          "aat:300379998"
        ],
        "name:en": "Shiyyāḩ, Wādī ash",
        "id": 7542368
      }
    },
    {
      "geometry": {
        "type": "Point",
        "coordinates": [
          33.696128,
          30.225847
        ]
      },
      "type": "Feature",
      "properties": {
        "hierarchy": [
          "tgn:7542369",
          "tgn:7001242",
          "tgn:7016833",
          "tgn:7001335",
          "tgn:7029392"
        ],
        "placetype": [
          "aat:300379998"
        ],
        "name:en": "Jidāl ad Dawkh, Wādī",
        "id": 7542369
      }
    }
  ]
}
