{
  "geometry": {
    "type": "Point",
    "coordinates": [
      67.4167,
      48.9167
    ]
  },
  "type": "Feature",
  "properties": {
    "hierarchy": [
      "tgn:1058325",
      "tgn:1000004",
      "tgn:1003363",
      "tgn:7014786",
      "tgn:7029392"
    ],
    "placetype": [
      "aat:300008347"
    ],
    "id": 1058325,
    "name:xx": "Pervaja Maja"
  }
}
