{
  "type": "FeatureCollection",
  "features": [
    {
      "geometry": {
        "type": "Point",
        "coordinates": [
          -2.833333,
          59.25
        ]
      },
      "type": "Feature",
      "properties": {
        "hierarchy": [
          "tgn:7445310",
          "tgn:7002444",
          "tgn:1000003",
          "tgn:7009907",
          "tgn:7008591",
          "tgn:7029392"
        ],
        "placetype": [
          "aat:300266558"
        ],
        "name:en": "Weatherness Sound",
        "id": 7445310
      }
    },
    {
      "geometry": {
        "type": "Point",
        "coordinates": [
          -2.833333,
          59.25
        ]
      },
      "type": "Feature",
      "properties": {
        "hierarchy": [
          "tgn:7445311",
          "tgn:7002444",
          "tgn:1000003",
          "tgn:7009907",
          "tgn:7008591",
          "tgn:7029392"
        ],
        "placetype": [
          "aat:300386846"
        ],
        "name:en": "Weather Ness",
        "id": 7445311
      }
    },
    {
      "geometry": {
        "type": "Point",
        "coordinates": [
          -2.4,
          54.183333
        ]
      },
      "type": "Feature",
      "properties": {
        "hierarchy": [
          "tgn:7445312",
          "tgn:7002445",
          "tgn:1000003",
          "tgn:7008166",
          "tgn:7008591",
          "tgn:7029392"
        ],
        "placetype": [
          "aat:300008347"
        ],
        "name:en": "Weathercote",
        "id": 7445312
      }
    },
    {
      "geometry": {
        "type": "Point",
        "coordinates": [
          -2.3,
          53.483333
        ]
      },
      "type": "Feature",
      "properties": {
        "hierarchy": [
          "tgn:7445313",
          "tgn:7002445",
          "tgn:1003640",
          "tgn:1000003",
          "tgn:7026570",
          "tgn:7008591",
          "tgn:7029392"
        ],
        "placetype": [
          "aat:300000745"
        ],
        "name:en": "Weaste",
        "id": 7445313
      }
    },
    {
      "geometry": {
        "type": "Point",
        "coordinates": [
          0.75,
          52.766667
        ]
      },
      "type": "Feature",
      "properties": {
        "hierarchy": [
          "tgn:7445315",
          "tgn:7002445",
          "tgn:1000003",
          "tgn:7008160",
          "tgn:7008591",
          "tgn:7029392"
        ],
        "placetype": [
          "aat:300008347"
        ],
        "name:en": "Weasenham",
        "id": 7445315
      }
    },
    {
      "geometry": {
        "type": "Point",
        "coordinates": [
          -2.839167,
          51.270833
        ]
      },
      "type": "Feature",
      "properties": {
        "hierarchy": [
          "tgn:7445319",
          "tgn:7002445",
          "tgn:1000003",
          "tgn:7012032",
          "tgn:7008591",
          "tgn:7029392"
        ],
        "placetype": [
          "aat:300008347"
        ],
        "name:en": "Weare",
        "id": 7445319
      }
    }
  ]
}
