{
  "geometry": {
    "type": "Point",
    "coordinates": [
      168.1667,
      -15.4167
    ]
  },
  "type": "Feature",
  "properties": {
    "hierarchy": [
      "tgn:1114887",
      "tgn:1000225",
      "tgn:1000006",
      "tgn:7029392"
    ],
    "placetype": [
      "aat:300387217"
    ],
    "id": 1114887,
    "name:xx": "Lolvavana, Passage"
  }
}
