{
  "geometry": {
    "type": "Point",
    "coordinates": [
      -86.0833,
      37.4833
    ]
  },
  "type": "Feature",
  "properties": {
    "hierarchy": [
      "tgn:2039753",
      "tgn:1000001",
      "tgn:7012149",
      "tgn:2000793",
      "tgn:7007255",
      "tgn:7029392"
    ],
    "placetype": [
      "aat:300008347",
      "aat:300387210"
    ],
    "id": 2039753,
    "name:xx": "Lacon"
  }
}
