{
  "geometry": {
    "type": "Point",
    "coordinates": [
      -55.0667,
      5.0833
    ]
  },
  "type": "Feature",
  "properties": {
    "hierarchy": [
      "tgn:1024826",
      "tgn:1000818",
      "tgn:1000002",
      "tgn:7015386",
      "tgn:7029392"
    ],
    "placetype": [
      "aat:300008347",
      "aat:300387222",
      "aat:300008375"
    ],
    "id": 1024826,
    "name:xx": "Brokopondo"
  }
}
