{
  "geometry": {
    "type": "Point",
    "coordinates": [
      -97.6167,
      44.0333
    ]
  },
  "type": "Feature",
  "properties": {
    "hierarchy": [
      "tgn:2001818",
      "tgn:1000001",
      "tgn:7012149",
      "tgn:7007713",
      "tgn:7029392"
    ],
    "placetype": [
      "aat:300387145",
      "aat:300000771"
    ],
    "id": 2001818,
    "name:xx": "Miner"
  }
}
