{
  "geometry": {
    "type": "Point",
    "coordinates": [
      32.4167,
      50.1167
    ]
  },
  "type": "Feature",
  "properties": {
    "hierarchy": [
      "tgn:1054156",
      "tgn:1000003",
      "tgn:7011666",
      "tgn:7006660",
      "tgn:7029392"
    ],
    "placetype": [
      "aat:300008347"
    ],
    "id": 1054156,
    "name:xx": "Grebenka"
  }
}
