{
  "geometry": {
    "type": "Point",
    "coordinates": [
      -85.2667,
      40.9167
    ]
  },
  "type": "Feature",
  "properties": {
    "hierarchy": [
      "tgn:2034228",
      "tgn:1000001",
      "tgn:7012149",
      "tgn:1003010",
      "tgn:7007252",
      "tgn:7029392"
    ],
    "placetype": [
      "aat:300008347"
    ],
    "id": 2034228,
    "name:xx": "Zanesville"
  }
}
