{
  "geometry": {
    "type": "Point",
    "coordinates": [
      -117.05,
      45.8833
    ]
  },
  "type": "Feature",
  "properties": {
    "hierarchy": [
      "tgn:2759003",
      "tgn:1000001",
      "tgn:7012149",
      "tgn:2001722",
      "tgn:7007708",
      "tgn:7029392"
    ],
    "placetype": [
      "aat:300008706"
    ],
    "id": 2759003,
    "name:xx": "West Fork Basin Creek"
  }
}
