{
  "geometry": {
    "type": "Point",
    "coordinates": [
      -118.3833,
      47.7833
    ]
  },
  "type": "Feature",
  "properties": {
    "hierarchy": [
      "tgn:2738501",
      "tgn:1000001",
      "tgn:7012149",
      "tgn:2002247",
      "tgn:7007920",
      "tgn:7029392"
    ],
    "placetype": [
      "aat:300008761"
    ],
    "id": 2738501,
    "name:xx": "Underwood Canyon"
  }
}
