{
  "geometry": {
    "type": "Point",
    "coordinates": [
      72.866667,
      21.25
    ]
  },
  "type": "Feature",
  "properties": {
    "hierarchy": [
      "tgn:7580120",
      "tgn:1000004",
      "tgn:1001869",
      "tgn:7000198",
      "tgn:7029392"
    ],
    "placetype": [
      "aat:300007783"
    ],
    "name:en": "Utrān",
    "id": 7580120
  }
}
