{
  "type": "FeatureCollection",
  "features": [
    {
      "geometry": {
        "type": "Point",
        "coordinates": [
          -121.9667,
          37.15
        ]
      },
      "type": "Feature",
      "properties": {
        "hierarchy": [
          "tgn:7015460",
          "tgn:1000001",
          "tgn:7012149",
          "tgn:7007157",
          "tgn:7014475",
          "tgn:7029392"
        ],
        "placetype": [
          "aat:300008347"
        ],
        "id": 7015460,
        "name:xx": "Chemeketa Park"
      }
    },
    {
      "geometry": {
        "type": "Point",
        "coordinates": [
          -122.4833,
          38.3167
        ]
      },
      "type": "Feature",
      "properties": {
        "hierarchy": [
          "tgn:7015467",
          "tgn:1000001",
          "tgn:7012149",
          "tgn:7007157",
          "tgn:7014516",
          "tgn:7029392"
        ],
        "placetype": [
          "aat:300008347"
        ],
        "id": 7015467,
        "name:xx": "Fetters Hot Springs"
      }
    },
    {
      "geometry": {
        "type": "Point",
        "coordinates": [
          -118.2833,
          34.25
        ]
      },
      "type": "Feature",
      "properties": {
        "hierarchy": [
          "tgn:7015468",
          "tgn:1000001",
          "tgn:7012149",
          "tgn:7007157",
          "tgn:7023900",
          "tgn:1002608",
          "tgn:7029392"
        ],
        "placetype": [
          "aat:300000745"
        ],
        "id": 7015468,
        "name:xx": "Tujunga"
      }
    }
  ]
}
