{
  "geometry": {
    "type": "Point",
    "coordinates": [
      16.446,
      -10.347
    ]
  },
  "type": "Feature",
  "properties": {
    "hierarchy": [
      "tgn:1126420",
      "tgn:7001242",
      "tgn:1000149",
      "tgn:7029392"
    ],
    "placetype": [
      "aat:300008707"
    ],
    "id": 1126420,
    "name:xx": "Luando"
  }
}
