{
  "geometry": {
    "type": "Point",
    "coordinates": [
      -77.2167,
      39.8333
    ]
  },
  "type": "Feature",
  "properties": {
    "hierarchy": [
      "tgn:2148285",
      "tgn:1002137",
      "tgn:1000001",
      "tgn:7012149",
      "tgn:7007710",
      "tgn:7029392"
    ],
    "placetype": [
      "aat:300008347"
    ],
    "id": 2148285,
    "name:xx": "Barlow Knoll"
  }
}
