{
  "type": "FeatureCollection",
  "features": [
    {
      "geometry": {
        "type": "Point",
        "coordinates": [
          -71,
          42.8
        ]
      },
      "type": "Feature",
      "properties": {
        "hierarchy": [
          "tgn:2049890",
          "tgn:1000001",
          "tgn:1002359",
          "tgn:7012149",
          "tgn:2049885",
          "tgn:7007517",
          "tgn:7029392"
        ],
        "placetype": [
          "aat:300000745"
        ],
        "id": 2049890,
        "name:xx": "Rock Village"
      }
    },
    {
      "geometry": {
        "type": "Point",
        "coordinates": [
          -72.8667,
          42.55
        ]
      },
      "type": "Feature",
      "properties": {
        "hierarchy": [
          "tgn:2049892",
          "tgn:1000001",
          "tgn:7013942",
          "tgn:7012149",
          "tgn:7007517",
          "tgn:7029392"
        ],
        "placetype": [
          "aat:300008347"
        ],
        "id": 2049892,
        "name:xx": "Hawley"
      }
    },
    {
      "geometry": {
        "type": "Point",
        "coordinates": [
          -72.7,
          42.3667
        ]
      },
      "type": "Feature",
      "properties": {
        "hierarchy": [
          "tgn:2049893",
          "tgn:1000001",
          "tgn:7013686",
          "tgn:7012149",
          "tgn:7007517",
          "tgn:7029392"
        ],
        "placetype": [
          "aat:300008347"
        ],
        "id": 2049893,
        "name:xx": "Haydenville"
      }
    },
    {
      "geometry": {
        "type": "Point",
        "coordinates": [
          -71.05,
          41.6167
        ]
      },
      "type": "Feature",
      "properties": {
        "hierarchy": [
          "tgn:2049894",
          "tgn:1002201",
          "tgn:1000001",
          "tgn:7012149",
          "tgn:7007517",
          "tgn:7029392"
        ],
        "placetype": [
          "aat:300008347"
        ],
        "id": 2049894,
        "name:xx": "Head of Westport"
      }
    },
    {
      "geometry": {
        "type": "Point",
        "coordinates": [
          -72.8167,
          42.6667
        ]
      },
      "type": "Feature",
      "properties": {
        "hierarchy": [
          "tgn:2049895",
          "tgn:1000001",
          "tgn:7013942",
          "tgn:7012149",
          "tgn:7007517",
          "tgn:7029392"
        ],
        "placetype": [
          "aat:300008347"
        ],
        "id": 2049895,
        "name:xx": "Heath"
      }
    },
    {
      "geometry": {
        "type": "Point",
        "coordinates": [
          -70.95,
          41.7833
        ]
      },
      "type": "Feature",
      "properties": {
        "hierarchy": [
          "tgn:2049896",
          "tgn:1002201",
          "tgn:1000001",
          "tgn:7012149",
          "tgn:7007517",
          "tgn:7029392"
        ],
        "placetype": [
          "aat:300008347"
        ],
        "id": 2049896,
        "name:xx": "Heaven Heights"
      }
    },
    {
      "geometry": {
        "type": "Point",
        "coordinates": [
          -70.9333,
          41.8
        ]
      },
      "type": "Feature",
      "properties": {
        "hierarchy": [
          "tgn:2049897",
          "tgn:1000001",
          "tgn:7014423",
          "tgn:7012149",
          "tgn:7007517",
          "tgn:7029392"
        ],
        "placetype": [
          "aat:300008347"
        ],
        "id": 2049897,
        "name:xx": "Hemlocks"
      }
    },
    {
      "geometry": {
        "type": "Point",
        "coordinates": [
          -71.7,
          42.6
        ]
      },
      "type": "Feature",
      "properties": {
        "hierarchy": [
          "tgn:2049898",
          "tgn:1000001",
          "tgn:7012149",
          "tgn:1003038",
          "tgn:7007517",
          "tgn:7029392"
        ],
        "placetype": [
          "aat:300006191"
        ],
        "id": 2049898,
        "name:xx": "Hickory Hills Lake"
      }
    }
  ]
}
