{
  "geometry": {
    "type": "Point",
    "coordinates": [
      138.9333,
      34.9833
    ]
  },
  "type": "Feature",
  "properties": {
    "hierarchy": [
      "tgn:1079678",
      "tgn:7000895",
      "tgn:1000004",
      "tgn:1001031",
      "tgn:1000120",
      "tgn:7029392"
    ],
    "placetype": [
      "aat:300008347"
    ],
    "id": 1079678,
    "name:xx": "Ōhito"
  }
}
