{
  "geometry": {
    "type": "Point",
    "coordinates": [
      13.55,
      46.3333
    ]
  },
  "type": "Feature",
  "properties": {
    "hierarchy": [
      "tgn:1064947",
      "tgn:1000003",
      "tgn:7015085",
      "tgn:7006670",
      "tgn:7029392"
    ],
    "placetype": [
      "aat:300008347"
    ],
    "id": 1064947,
    "name:xx": "Bovec"
  }
}
