{
  "geometry": {
    "type": "Point",
    "coordinates": [
      -86.3667,
      38.6667
    ]
  },
  "type": "Feature",
  "properties": {
    "hierarchy": [
      "tgn:2032597",
      "tgn:1000001",
      "tgn:7012149",
      "tgn:1002750",
      "tgn:7007252",
      "tgn:7029392"
    ],
    "placetype": [
      "aat:300008347"
    ],
    "id": 2032597,
    "name:xx": "Leipsic"
  }
}
