{
  "geometry": {
    "type": "Point",
    "coordinates": [
      12.5167,
      49.8333
    ]
  },
  "type": "Feature",
  "properties": {
    "hierarchy": [
      "tgn:1027103",
      "tgn:7593919",
      "tgn:1000003",
      "tgn:1001780",
      "tgn:7029392"
    ],
    "placetype": [
      "aat:300008347"
    ],
    "id": 1027103,
    "name:xx": "Branka"
  }
}
