{
  "geometry": {
    "type": "Point",
    "coordinates": [
      -112.2667,
      33.9833
    ]
  },
  "type": "Feature",
  "properties": {
    "hierarchy": [
      "tgn:2298711",
      "tgn:1000001",
      "tgn:7006451",
      "tgn:7012149",
      "tgn:2000103",
      "tgn:7029392"
    ],
    "placetype": [
      "aat:300008699"
    ],
    "id": 2298711,
    "name:xx": "Dry Wash"
  }
}
