{
  "geometry": {
    "type": "Point",
    "coordinates": [
      -79.3833,
      42.2167
    ]
  },
  "type": "Feature",
  "properties": {
    "hierarchy": [
      "tgn:2753496",
      "tgn:1000001",
      "tgn:1002259",
      "tgn:7012149",
      "tgn:7007568",
      "tgn:7029392"
    ],
    "placetype": [
      "aat:300008347"
    ],
    "id": 2753496,
    "name:xx": "Waterman Corner"
  }
}
