{
  "type": "FeatureCollection",
  "features": [
    {
      "geometry": {
        "type": "Point",
        "coordinates": [
          28.7,
          48.05
        ]
      },
      "type": "Feature",
      "properties": {
        "hierarchy": [
          "tgn:1137590",
          "tgn:1000003",
          "tgn:7594267",
          "tgn:7006656",
          "tgn:7029392"
        ],
        "placetype": [
          "aat:300008347"
        ],
        "id": 1137590,
        "name:xx": "Camenca"
      }
    },
    {
      "geometry": {
        "type": "Point",
        "coordinates": [
          32.1,
          49.05
        ]
      },
      "type": "Feature",
      "properties": {
        "hierarchy": [
          "tgn:1137591",
          "tgn:6001332",
          "tgn:1000003",
          "tgn:7006660",
          "tgn:7029392"
        ],
        "placetype": [
          "aat:300008347"
        ],
        "id": 1137591,
        "name:xx": "Kamenka"
      }
    },
    {
      "geometry": {
        "type": "Point",
        "coordinates": [
          37.3,
          49.1167
        ]
      },
      "type": "Feature",
      "properties": {
        "hierarchy": [
          "tgn:1137592",
          "tgn:1003361",
          "tgn:1000003",
          "tgn:7006660",
          "tgn:7029392"
        ],
        "placetype": [
          "aat:300008347"
        ],
        "id": 1137592,
        "name:xx": "Kam'yanka"
      }
    },
    {
      "geometry": {
        "type": "Point",
        "coordinates": [
          39.3667,
          49.6167
        ]
      },
      "type": "Feature",
      "properties": {
        "hierarchy": [
          "tgn:1137593",
          "tgn:1000003",
          "tgn:7012067",
          "tgn:7006660",
          "tgn:7029392"
        ],
        "placetype": [
          "aat:300008347"
        ],
        "id": 1137593,
        "name:xx": "Kamenka"
      }
    },
    {
      "geometry": {
        "type": "Point",
        "coordinates": [
          39.4167,
          50.7167
        ]
      },
      "type": "Feature",
      "properties": {
        "hierarchy": [
          "tgn:1137594",
          "tgn:1000004",
          "tgn:1003424",
          "tgn:7018214",
          "tgn:7002435",
          "tgn:7029392"
        ],
        "placetype": [
          "aat:300008347"
        ],
        "id": 1137594,
        "name:xx": "Kamenka"
      }
    },
    {
      "geometry": {
        "type": "Point",
        "coordinates": [
          50.3333,
          51.1667
        ]
      },
      "type": "Feature",
      "properties": {
        "hierarchy": [
          "tgn:1137595",
          "tgn:1000004",
          "tgn:7011457",
          "tgn:7014786",
          "tgn:7029392"
        ],
        "placetype": [
          "aat:300008347"
        ],
        "id": 1137595,
        "name:xx": "Kamenka"
      }
    },
    {
      "geometry": {
        "type": "Point",
        "coordinates": [
          41.8167,
          52.0667
        ]
      },
      "type": "Feature",
      "properties": {
        "hierarchy": [
          "tgn:1137596",
          "tgn:1000004",
          "tgn:1003417",
          "tgn:7018214",
          "tgn:7002435",
          "tgn:7029392"
        ],
        "placetype": [
          "aat:300008347"
        ],
        "id": 1137596,
        "name:xx": "Kamenka"
      }
    },
    {
      "geometry": {
        "type": "Point",
        "coordinates": [
          69.0667,
          52.3667
        ]
      },
      "type": "Feature",
      "properties": {
        "hierarchy": [
          "tgn:1137597",
          "tgn:7012935",
          "tgn:1000004",
          "tgn:7014786",
          "tgn:7029392"
        ],
        "placetype": [
          "aat:300008347"
        ],
        "id": 1137597,
        "name:xx": "Kamenka"
      }
    },
    {
      "geometry": {
        "type": "Point",
        "coordinates": [
          44.0833,
          53.1667
        ]
      },
      "type": "Feature",
      "properties": {
        "hierarchy": [
          "tgn:1137598",
          "tgn:1000004",
          "tgn:1003399",
          "tgn:7018214",
          "tgn:7002435",
          "tgn:7029392"
        ],
        "placetype": [
          "aat:300008347"
        ],
        "id": 1137598,
        "name:xx": "Kamenka"
      }
    },
    {
      "geometry": {
        "type": "Point",
        "coordinates": [
          38.3333,
          54.6833
        ]
      },
      "type": "Feature",
      "properties": {
        "hierarchy": [
          "tgn:1137599",
          "tgn:1000004",
          "tgn:7011573",
          "tgn:7018214",
          "tgn:7002435",
          "tgn:7029392"
        ],
        "placetype": [
          "aat:300008347"
        ],
        "id": 1137599,
        "name:xx": "Kamenka"
      }
    }
  ]
}
