{
  "geometry": {
    "type": "Point",
    "coordinates": [
      76.184,
      20.529
    ]
  },
  "type": "Feature",
  "properties": {
    "hierarchy": [
      "tgn:1074885",
      "tgn:1000004",
      "tgn:7000198",
      "tgn:1001895",
      "tgn:7029392"
    ],
    "placetype": [
      "aat:300008347"
    ],
    "name:en": "Buldāna",
    "id": 1074885
  }
}
