{
  "type": "FeatureCollection",
  "features": [
    {
      "geometry": {
        "type": "Point",
        "coordinates": [
          12.283333,
          51.883333
        ]
      },
      "type": "Feature",
      "properties": {
        "hierarchy": [
          "tgn:7062690",
          "tgn:1000003",
          "tgn:7003687",
          "tgn:7000084",
          "tgn:7029392"
        ],
        "placetype": [
          "aat:300008777"
        ],
        "id": 7062690,
        "name:xx": "Au-Berg"
      }
    },
    {
      "geometry": {
        "type": "Point",
        "coordinates": [
          6.883333,
          51.383333
        ]
      },
      "type": "Feature",
      "properties": {
        "hierarchy": [
          "tgn:7062692",
          "tgn:1000003",
          "tgn:7003677",
          "tgn:7000084",
          "tgn:7029392"
        ],
        "placetype": [
          "aat:300008777"
        ],
        "id": 7062692,
        "name:xx": "Auberg"
      }
    },
    {
      "geometry": {
        "type": "Point",
        "coordinates": [
          10.116667,
          47.983333
        ]
      },
      "type": "Feature",
      "properties": {
        "hierarchy": [
          "tgn:7062693",
          "tgn:7003692",
          "tgn:1000003",
          "tgn:7000084",
          "tgn:7029392"
        ],
        "placetype": [
          "aat:300008347"
        ],
        "id": 7062693,
        "name:xx": "Arlach"
      }
    },
    {
      "geometry": {
        "type": "Point",
        "coordinates": [
          9.2,
          54.5
        ]
      },
      "type": "Feature",
      "properties": {
        "hierarchy": [
          "tgn:7062694",
          "tgn:1000003",
          "tgn:7003688",
          "tgn:7000084",
          "tgn:7029392"
        ],
        "placetype": [
          "aat:300000206"
        ],
        "id": 7062694,
        "name:xx": "Arl"
      }
    },
    {
      "geometry": {
        "type": "Point",
        "coordinates": [
          7.5,
          50.266667
        ]
      },
      "type": "Feature",
      "properties": {
        "hierarchy": [
          "tgn:7062697",
          "tgn:1000003",
          "tgn:7003682",
          "tgn:7000084",
          "tgn:7029392"
        ],
        "placetype": [
          "aat:300000206"
        ],
        "id": 7062697,
        "name:xx": "Arkenwälderhof"
      }
    },
    {
      "geometry": {
        "type": "Point",
        "coordinates": [
          12.75,
          52.45
        ]
      },
      "type": "Feature",
      "properties": {
        "hierarchy": [
          "tgn:7062698",
          "tgn:7000096",
          "tgn:1000003",
          "tgn:7000084",
          "tgn:7029392"
        ],
        "placetype": [
          "aat:300008791"
        ],
        "id": 7062698,
        "name:xx": "Arkenbude"
      }
    }
  ]
}
