{
  "type": "FeatureCollection",
  "features": [
    {
      "geometry": {
        "type": "Point",
        "coordinates": [
          -5.3,
          42.383333
        ]
      },
      "type": "Feature",
      "properties": {
        "hierarchy": [
          "tgn:7298771",
          "tgn:7002826",
          "tgn:7001158",
          "tgn:1000003",
          "tgn:1000095",
          "tgn:7029392"
        ],
        "placetype": [
          "aat:300266554",
          "aat:300008699"
        ],
        "id": 7298771,
        "name:xx": "Utielga, Valle de"
      }
    },
    {
      "geometry": {
        "type": "Point",
        "coordinates": [
          -1.133333,
          39.6
        ]
      },
      "type": "Feature",
      "properties": {
        "hierarchy": [
          "tgn:7298772",
          "tgn:7001165",
          "tgn:1000003",
          "tgn:7002793",
          "tgn:1000095",
          "tgn:7029392"
        ],
        "placetype": [
          "aat:300008795"
        ],
        "id": 7298772,
        "name:xx": "Utiel, Sierra de"
      }
    },
    {
      "geometry": {
        "type": "Point",
        "coordinates": [
          -1.75,
          42.7
        ]
      },
      "type": "Feature",
      "properties": {
        "hierarchy": [
          "tgn:7298774",
          "tgn:7001155",
          "tgn:1000003",
          "tgn:7002790",
          "tgn:1000095",
          "tgn:7029392"
        ],
        "placetype": [
          "aat:300008347"
        ],
        "id": 7298774,
        "name:xx": "Uterga"
      }
    },
    {
      "geometry": {
        "type": "Point",
        "coordinates": [
          -1,
          41.716667
        ]
      },
      "type": "Feature",
      "properties": {
        "hierarchy": [
          "tgn:7298775",
          "tgn:7002759",
          "tgn:7002845",
          "tgn:1000003",
          "tgn:1000095",
          "tgn:7029392"
        ],
        "placetype": [
          "aat:300008347"
        ],
        "id": 7298775,
        "name:xx": "Utebo"
      }
    },
    {
      "geometry": {
        "type": "Point",
        "coordinates": [
          -2.916667,
          40.833333
        ]
      },
      "type": "Feature",
      "properties": {
        "hierarchy": [
          "tgn:7298776",
          "tgn:7002822",
          "tgn:1001647",
          "tgn:1000003",
          "tgn:1000095",
          "tgn:7029392"
        ],
        "placetype": [
          "aat:300008347"
        ],
        "id": 7298776,
        "name:xx": "Utande"
      }
    },
    {
      "geometry": {
        "type": "Point",
        "coordinates": [
          -2.05,
          43.266667
        ]
      },
      "type": "Feature",
      "properties": {
        "hierarchy": [
          "tgn:7298777",
          "tgn:7007780",
          "tgn:1000003",
          "tgn:7009604",
          "tgn:1000095",
          "tgn:7029392"
        ],
        "placetype": [
          "aat:300008347"
        ],
        "id": 7298777,
        "name:xx": "Usúrbil"
      }
    },
    {
      "geometry": {
        "type": "Point",
        "coordinates": [
          -8.333333,
          43.166667
        ]
      },
      "type": "Feature",
      "properties": {
        "hierarchy": [
          "tgn:7298778",
          "tgn:7002824",
          "tgn:1000003",
          "tgn:7002786",
          "tgn:1000095",
          "tgn:7029392"
        ],
        "placetype": [
          "aat:300008347"
        ],
        "id": 7298778,
        "name:xx": "Traviesas"
      }
    },
    {
      "geometry": {
        "type": "Point",
        "coordinates": [
          -6.766667,
          39.333333
        ]
      },
      "type": "Feature",
      "properties": {
        "hierarchy": [
          "tgn:7298779",
          "tgn:7002807",
          "tgn:1000003",
          "tgn:7003837",
          "tgn:1000095",
          "tgn:7029392"
        ],
        "placetype": [
          "aat:300266640"
        ],
        "id": 7298779,
        "name:xx": "Traviesa, Sierra"
      }
    }
  ]
}
