{
  "geometry": {
    "type": "Point",
    "coordinates": [
      -111.4333,
      34.4833
    ]
  },
  "type": "Feature",
  "properties": {
    "hierarchy": [
      "tgn:2735130",
      "tgn:1000001",
      "tgn:7006451",
      "tgn:2000092",
      "tgn:7012149",
      "tgn:7029392"
    ],
    "placetype": [
      "aat:300008798"
    ],
    "id": 2735130,
    "name:xx": "Twentynine Mile Butte"
  }
}
