{
  "geometry": {
    "type": "Point",
    "coordinates": [
      -95.9333,
      33.5833
    ]
  },
  "type": "Feature",
  "properties": {
    "hierarchy": [
      "tgn:2130321",
      "tgn:1000001",
      "tgn:7012149",
      "tgn:2001983",
      "tgn:7007826",
      "tgn:7029392"
    ],
    "placetype": [
      "aat:300008706"
    ],
    "id": 2130321,
    "name:xx": "Allens Creek"
  }
}
