{
  "geometry": {
    "type": "Point",
    "coordinates": [
      68.95,
      34.5833
    ]
  },
  "type": "Feature",
  "properties": {
    "hierarchy": [
      "tgn:1065491",
      "tgn:7016612",
      "tgn:1000004",
      "tgn:1001331",
      "tgn:7029392"
    ],
    "placetype": [
      "aat:300008347"
    ],
    "id": 1065491,
    "name:xx": "Paghman"
  }
}
