{
  "geometry": {
    "type": "Point",
    "coordinates": [
      -82.4833,
      32.3667
    ]
  },
  "type": "Feature",
  "properties": {
    "hierarchy": [
      "tgn:2534919",
      "tgn:1000001",
      "tgn:7012149",
      "tgn:7007248",
      "tgn:7029392"
    ],
    "placetype": [
      "aat:300008706"
    ],
    "id": 2534919,
    "name:xx": "Naked Creek"
  }
}
