{
  "geometry": {
    "type": "Point",
    "coordinates": [
      12.45,
      52.85
    ]
  },
  "type": "Feature",
  "properties": {
    "hierarchy": [
      "tgn:1037023",
      "tgn:7000096",
      "tgn:1000003",
      "tgn:7000084",
      "tgn:7029392"
    ],
    "placetype": [
      "aat:300008347"
    ],
    "id": 1037023,
    "name:xx": "Köritz"
  }
}
