{
  "geometry": {
    "type": "Point",
    "coordinates": [
      -78.8167,
      40.7667
    ]
  },
  "type": "Feature",
  "properties": {
    "hierarchy": [
      "tgn:2661679",
      "tgn:1000001",
      "tgn:7012149",
      "tgn:7007710",
      "tgn:7029392"
    ],
    "placetype": [
      "aat:300008699"
    ],
    "id": 2661679,
    "name:xx": "Shryock Run"
  }
}
