{
  "geometry": {
    "type": "Point",
    "coordinates": [
      -69.1833,
      45.75
    ]
  },
  "type": "Feature",
  "properties": {
    "hierarchy": [
      "tgn:2591382",
      "tgn:1000001",
      "tgn:7012149",
      "tgn:2000928",
      "tgn:7007515",
      "tgn:7029392"
    ],
    "placetype": [
      "aat:300008699"
    ],
    "id": 2591382,
    "name:xx": "Pollywog Stream"
  }
}
