{
  "geometry": {
    "type": "Point",
    "coordinates": [
      -109.7333,
      37.8333
    ]
  },
  "type": "Feature",
  "properties": {
    "hierarchy": [
      "tgn:2259041",
      "tgn:1000001",
      "tgn:7012149",
      "tgn:2002119",
      "tgn:7007827",
      "tgn:7029392"
    ],
    "placetype": [
      "aat:300008706"
    ],
    "id": 2259041,
    "name:xx": "Cottonwood Creek"
  }
}
