{
  "geometry": {
    "type": "Point",
    "coordinates": [
      -113.3167,
      39.4667
    ]
  },
  "type": "Feature",
  "properties": {
    "hierarchy": [
      "tgn:2544632",
      "tgn:1000001",
      "tgn:7012149",
      "tgn:2002114",
      "tgn:7007827",
      "tgn:7029392"
    ],
    "placetype": [
      "aat:300008697"
    ],
    "id": 2544632,
    "name:xx": "North Canyon Spring"
  }
}
