{
  "geometry": {
    "type": "Point",
    "coordinates": [
      -90.5833,
      39.4833
    ]
  },
  "type": "Feature",
  "properties": {
    "hierarchy": [
      "tgn:2203277",
      "tgn:1000001",
      "tgn:7012149",
      "tgn:1002422",
      "tgn:7007251",
      "tgn:7029392"
    ],
    "placetype": [
      "aat:300008791"
    ],
    "id": 2203277,
    "name:xx": "Buckhorn Island"
  }
}
