{
  "geometry": {
    "type": "Point",
    "coordinates": [
      -82.3333,
      39.2667
    ]
  },
  "type": "Feature",
  "properties": {
    "hierarchy": [
      "tgn:2426565",
      "tgn:1000001",
      "tgn:7012149",
      "tgn:2001621",
      "tgn:7007706",
      "tgn:7029392"
    ],
    "placetype": [
      "aat:300008761"
    ],
    "id": 2426565,
    "name:xx": "Jones Hollow"
  }
}
