{
  "geometry": {
    "type": "Point",
    "coordinates": [
      -111.7333,
      33.4167
    ]
  },
  "type": "Feature",
  "properties": {
    "hierarchy": [
      "tgn:2520196",
      "tgn:1000001",
      "tgn:7006451",
      "tgn:7012149",
      "tgn:2000097",
      "tgn:7029392"
    ],
    "placetype": [
      "aat:300008347"
    ],
    "id": 2520196,
    "name:xx": "MonDak Mobile Home Park"
  }
}
