{
  "type": "FeatureCollection",
  "features": [
    {
      "geometry": {
        "type": "Point",
        "coordinates": [
          4.3833,
          44.6333
        ]
      },
      "type": "Feature",
      "properties": {
        "hierarchy": [
          "tgn:1033730",
          "tgn:1000003",
          "tgn:1000070",
          "tgn:7002897",
          "tgn:7029392"
        ],
        "placetype": [
          "aat:300008347"
        ],
        "id": 1033730,
        "name:xx": "Labégude"
      }
    },
    {
      "geometry": {
        "type": "Point",
        "coordinates": [
          1.55,
          44.65
        ]
      },
      "type": "Feature",
      "properties": {
        "hierarchy": [
          "tgn:1033731",
          "tgn:1000003",
          "tgn:7002889",
          "tgn:1000070",
          "tgn:7029392"
        ],
        "placetype": [
          "aat:300008347"
        ],
        "id": 1033731,
        "name:xx": "Labastide-Murat"
      }
    },
    {
      "geometry": {
        "type": "Point",
        "coordinates": [
          -0.5333,
          44.1
        ]
      },
      "type": "Feature",
      "properties": {
        "hierarchy": [
          "tgn:1033734",
          "tgn:7002878",
          "tgn:1000003",
          "tgn:1000070",
          "tgn:7029392"
        ],
        "placetype": [
          "aat:300008347"
        ],
        "id": 1033734,
        "name:xx": "Labrit"
      }
    },
    {
      "geometry": {
        "type": "Point",
        "coordinates": [
          2,
          50.2833
        ]
      },
      "type": "Feature",
      "properties": {
        "hierarchy": [
          "tgn:1033735",
          "tgn:1000003",
          "tgn:7001097",
          "tgn:1000070",
          "tgn:7029392"
        ],
        "placetype": [
          "aat:300008347"
        ],
        "id": 1033735,
        "name:xx": "Labroye"
      }
    },
    {
      "geometry": {
        "type": "Point",
        "coordinates": [
          5.8667,
          49.1667
        ]
      },
      "type": "Feature",
      "properties": {
        "hierarchy": [
          "tgn:1033736",
          "tgn:1000003",
          "tgn:7002888",
          "tgn:1000070",
          "tgn:7029392"
        ],
        "placetype": [
          "aat:300008347"
        ],
        "id": 1033736,
        "name:xx": "Labry"
      }
    },
    {
      "geometry": {
        "type": "Point",
        "coordinates": [
          -1.0833,
          44.9833
        ]
      },
      "type": "Feature",
      "properties": {
        "hierarchy": [
          "tgn:1033737",
          "tgn:7002878",
          "tgn:1000003",
          "tgn:1000070",
          "tgn:7029392"
        ],
        "placetype": [
          "aat:300008347"
        ],
        "id": 1033737,
        "name:xx": "Lacanau"
      }
    },
    {
      "geometry": {
        "type": "Point",
        "coordinates": [
          1.9,
          44.7333
        ]
      },
      "type": "Feature",
      "properties": {
        "hierarchy": [
          "tgn:1033738",
          "tgn:1000003",
          "tgn:7002889",
          "tgn:1000070",
          "tgn:7029392"
        ],
        "placetype": [
          "aat:300008347"
        ],
        "id": 1033738,
        "name:xx": "Lacapelle-Marival"
      }
    },
    {
      "geometry": {
        "type": "Point",
        "coordinates": [
          2.6833,
          43.7
        ]
      },
      "type": "Feature",
      "properties": {
        "hierarchy": [
          "tgn:1033739",
          "tgn:1000003",
          "tgn:7002889",
          "tgn:1000070",
          "tgn:7029392"
        ],
        "placetype": [
          "aat:300008347"
        ],
        "id": 1033739,
        "name:xx": "Lacaune"
      }
    }
  ]
}
