{
  "geometry": {
    "type": "Point",
    "coordinates": [
      -91.7167,
      30.8333
    ]
  },
  "type": "Feature",
  "properties": {
    "hierarchy": [
      "tgn:2241935",
      "tgn:1000001",
      "tgn:7012149",
      "tgn:2000892",
      "tgn:7007256",
      "tgn:7029392"
    ],
    "placetype": [
      "aat:300006075"
    ],
    "id": 2241935,
    "name:xx": "Clay Bayou"
  }
}
