{
  "geometry": {
    "type": "Point",
    "coordinates": [
      -86.25,
      34.7167
    ]
  },
  "type": "Feature",
  "properties": {
    "hierarchy": [
      "tgn:2349708",
      "tgn:7002659",
      "tgn:1000001",
      "tgn:7012149",
      "tgn:2000035",
      "tgn:7029392"
    ],
    "placetype": [
      "aat:300008697"
    ],
    "id": 2349708,
    "name:xx": "Gilliam Spring"
  }
}
