{
  "geometry": {
    "type": "Point",
    "coordinates": [
      -91.975,
      17.975
    ]
  },
  "type": "Feature",
  "properties": {
    "hierarchy": [
      "tgn:7406953",
      "tgn:7005578",
      "tgn:1000001",
      "tgn:7005560",
      "tgn:7029392"
    ],
    "placetype": [
      "aat:300008680"
    ],
    "id": 7406953,
    "name:xx": "Campo Nuevo, Laguna"
  }
}
