{
  "geometry": {
    "type": "Point",
    "coordinates": [
      -94.8833,
      33.1167
    ]
  },
  "type": "Feature",
  "properties": {
    "hierarchy": [
      "tgn:2597242",
      "tgn:1000001",
      "tgn:7012149",
      "tgn:1002948",
      "tgn:7007826",
      "tgn:7029392"
    ],
    "placetype": [
      "aat:300008699"
    ],
    "id": 2597242,
    "name:xx": "Prairie Branch"
  }
}
