{
  "geometry": {
    "type": "Point",
    "coordinates": [
      -93.7833,
      37.1833
    ]
  },
  "type": "Feature",
  "properties": {
    "hierarchy": [
      "tgn:2690409",
      "tgn:1000001",
      "tgn:7012149",
      "tgn:2001213",
      "tgn:7007523",
      "tgn:7029392"
    ],
    "placetype": [
      "aat:300008706"
    ],
    "id": 2690409,
    "name:xx": "Stahl Creek"
  }
}
