{
  "geometry": {
    "type": "Point",
    "coordinates": [
      24.966,
      55.8333
    ]
  },
  "type": "Feature",
  "properties": {
    "hierarchy": [
      "tgn:7006567",
      "tgn:1000003",
      "tgn:7006542",
      "tgn:7029392"
    ],
    "placetype": [
      "aat:300387064",
      "aat:300265612",
      "aat:300387081"
    ],
    "id": 7006567,
    "name:xx": "Kupiškis"
  }
}
