{
  "geometry": {
    "type": "Point",
    "coordinates": [
      -117.85,
      46.5167
    ]
  },
  "type": "Feature",
  "properties": {
    "hierarchy": [
      "tgn:2233023",
      "tgn:1000001",
      "tgn:2002241",
      "tgn:7012149",
      "tgn:7007920",
      "tgn:7029392"
    ],
    "placetype": [
      "aat:300008761"
    ],
    "id": 2233023,
    "name:xx": "Chard Gulch"
  }
}
