{
  "geometry": {
    "type": "Point",
    "coordinates": [
      -118.7833,
      37.2667
    ]
  },
  "type": "Feature",
  "properties": {
    "hierarchy": [
      "tgn:2169654",
      "tgn:1000001",
      "tgn:7012149",
      "tgn:1002392",
      "tgn:7007157",
      "tgn:7029392"
    ],
    "placetype": [
      "aat:300008680"
    ],
    "id": 2169654,
    "name:xx": "Big Moccasin Lake"
  }
}
