{
  "geometry": {
    "type": "Point",
    "coordinates": [
      -76.2833,
      42.3667
    ]
  },
  "type": "Feature",
  "properties": {
    "hierarchy": [
      "tgn:2068361",
      "tgn:1000001",
      "tgn:7012149",
      "tgn:1002950",
      "tgn:7007568",
      "tgn:7029392"
    ],
    "placetype": [
      "aat:300008347"
    ],
    "id": 2068361,
    "name:xx": "Caroline"
  }
}
