{
  "geometry": {
    "type": "Point",
    "coordinates": [
      -73.6167,
      44.8667
    ]
  },
  "type": "Feature",
  "properties": {
    "hierarchy": [
      "tgn:2150607",
      "tgn:1000001",
      "tgn:1002284",
      "tgn:7012149",
      "tgn:7007568",
      "tgn:7029392"
    ],
    "placetype": [
      "aat:300386845"
    ],
    "id": 2150607,
    "name:xx": "Basin,the"
  }
}
