{
  "geometry": {
    "type": "Point",
    "coordinates": [
      -71.8667,
      44.0833
    ]
  },
  "type": "Feature",
  "properties": {
    "hierarchy": [
      "tgn:2189435",
      "tgn:1000001",
      "tgn:2001424",
      "tgn:7012149",
      "tgn:7007564",
      "tgn:7029392"
    ],
    "placetype": [
      "aat:300008347"
    ],
    "id": 2189435,
    "name:xx": "Boutin Corner"
  }
}
