{
  "geometry": {
    "type": "Point",
    "coordinates": [
      -82.45,
      28.2167
    ]
  },
  "type": "Feature",
  "properties": {
    "hierarchy": [
      "tgn:2481661",
      "tgn:1000001",
      "tgn:7012149",
      "tgn:1002773",
      "tgn:7007240",
      "tgn:7029392"
    ],
    "placetype": [
      "aat:300008347"
    ],
    "id": 2481661,
    "name:xx": "Land O' Lakes"
  }
}
