{
  "geometry": {
    "type": "Point",
    "coordinates": [
      -82.7167,
      36.8333
    ]
  },
  "type": "Feature",
  "properties": {
    "hierarchy": [
      "tgn:2524966",
      "tgn:1000001",
      "tgn:7012149",
      "tgn:2002195",
      "tgn:7007919",
      "tgn:7029392"
    ],
    "placetype": [
      "aat:300008746"
    ],
    "id": 2524966,
    "name:xx": "Morris Butt Cave"
  }
}
