{
  "type": "FeatureCollection",
  "features": [
    {
      "geometry": {
        "type": "Point",
        "coordinates": [
          -76.5833,
          42.1
        ]
      },
      "type": "Feature",
      "properties": {
        "hierarchy": [
          "tgn:2489650",
          "tgn:1000001",
          "tgn:1002261",
          "tgn:7012149",
          "tgn:7007568",
          "tgn:7029392"
        ],
        "placetype": [
          "aat:300008706"
        ],
        "id": 2489650,
        "name:xx": "Mallory Creek"
      }
    },
    {
      "geometry": {
        "type": "Point",
        "coordinates": [
          -78.0167,
          34.1667
        ]
      },
      "type": "Feature",
      "properties": {
        "hierarchy": [
          "tgn:2489651",
          "tgn:1000001",
          "tgn:2001472",
          "tgn:7012149",
          "tgn:7007709",
          "tgn:7029392"
        ],
        "placetype": [
          "aat:300008706"
        ],
        "id": 2489651,
        "name:xx": "Mallory Creek"
      }
    },
    {
      "geometry": {
        "type": "Point",
        "coordinates": [
          -119.3,
          45.1333
        ]
      },
      "type": "Feature",
      "properties": {
        "hierarchy": [
          "tgn:2489652",
          "tgn:1000001",
          "tgn:7012149",
          "tgn:7007708",
          "tgn:7029392"
        ],
        "placetype": [
          "aat:300008706"
        ],
        "id": 2489652,
        "name:xx": "Mallory Creek"
      }
    },
    {
      "geometry": {
        "type": "Point",
        "coordinates": [
          -76.4667,
          41.9167
        ]
      },
      "type": "Feature",
      "properties": {
        "hierarchy": [
          "tgn:2489653",
          "tgn:1000001",
          "tgn:1002194",
          "tgn:7012149",
          "tgn:7007710",
          "tgn:7029392"
        ],
        "placetype": [
          "aat:300008706"
        ],
        "id": 2489653,
        "name:xx": "Mallory Creek"
      }
    },
    {
      "geometry": {
        "type": "Point",
        "coordinates": [
          -95.6667,
          33.6
        ]
      },
      "type": "Feature",
      "properties": {
        "hierarchy": [
          "tgn:2489654",
          "tgn:1000001",
          "tgn:7012149",
          "tgn:7007826",
          "tgn:7029392"
        ],
        "placetype": [
          "aat:300008706"
        ],
        "id": 2489654,
        "name:xx": "Mallory Creek"
      }
    },
    {
      "geometry": {
        "type": "Point",
        "coordinates": [
          -78.85,
          37.9333
        ]
      },
      "type": "Feature",
      "properties": {
        "hierarchy": [
          "tgn:2489655",
          "tgn:1000001",
          "tgn:7012149",
          "tgn:2002175",
          "tgn:7007919",
          "tgn:7029392"
        ],
        "placetype": [
          "aat:300008706"
        ],
        "id": 2489655,
        "name:xx": "Mallory Creek"
      }
    },
    {
      "geometry": {
        "type": "Point",
        "coordinates": [
          -77.0167,
          37.65
        ]
      },
      "type": "Feature",
      "properties": {
        "hierarchy": [
          "tgn:2489656",
          "tgn:1000001",
          "tgn:7012149",
          "tgn:1002548",
          "tgn:7007919",
          "tgn:7029392"
        ],
        "placetype": [
          "aat:300008706"
        ],
        "id": 2489656,
        "name:xx": "Mallory Creek"
      }
    },
    {
      "geometry": {
        "type": "Point",
        "coordinates": [
          -82.5667,
          42.95
        ]
      },
      "type": "Feature",
      "properties": {
        "hierarchy": [
          "tgn:2489657",
          "tgn:1000001",
          "tgn:7012149",
          "tgn:7016056",
          "tgn:7007520",
          "tgn:7029392"
        ],
        "placetype": [
          "aat:300006075"
        ],
        "id": 2489657,
        "name:xx": "Mallory Drain"
      }
    },
    {
      "geometry": {
        "type": "Point",
        "coordinates": [
          -109.55,
          34.1667
        ]
      },
      "type": "Feature",
      "properties": {
        "hierarchy": [
          "tgn:2489658",
          "tgn:2000090",
          "tgn:1000001",
          "tgn:7006451",
          "tgn:7012149",
          "tgn:7029392"
        ],
        "placetype": [
          "aat:300008761"
        ],
        "id": 2489658,
        "name:xx": "Mallory Draw"
      }
    },
    {
      "geometry": {
        "type": "Point",
        "coordinates": [
          -102.7667,
          45.45
        ]
      },
      "type": "Feature",
      "properties": {
        "hierarchy": [
          "tgn:2489659",
          "tgn:1000001",
          "tgn:7012149",
          "tgn:2001822",
          "tgn:7007713",
          "tgn:7029392"
        ],
        "placetype": [
          "aat:300008761"
        ],
        "id": 2489659,
        "name:xx": "Mallory Draw"
      }
    }
  ]
}
