{
  "geometry": {
    "type": "Point",
    "coordinates": [
      -91.25,
      36.0833
    ]
  },
  "type": "Feature",
  "properties": {
    "hierarchy": [
      "tgn:2453935",
      "tgn:1000001",
      "tgn:7016172",
      "tgn:7012149",
      "tgn:2000142",
      "tgn:7029392"
    ],
    "placetype": [
      "aat:300008706"
    ],
    "id": 2453935,
    "name:xx": "Little Creek"
  }
}
