{
  "geometry": {
    "type": "Point",
    "coordinates": [
      -123.6333,
      41.9833
    ]
  },
  "type": "Feature",
  "properties": {
    "hierarchy": [
      "tgn:2212400",
      "tgn:1000001",
      "tgn:7012149",
      "tgn:2000180",
      "tgn:7007157",
      "tgn:7029392"
    ],
    "placetype": [
      "aat:300008761"
    ],
    "id": 2212400,
    "name:xx": "Bybee Gulch"
  }
}
