{
  "geometry": {
    "type": "Point",
    "coordinates": [
      75.35,
      40.4667
    ]
  },
  "type": "Feature",
  "properties": {
    "hierarchy": [
      "tgn:1072361",
      "tgn:1000004",
      "tgn:7001745",
      "tgn:1000111",
      "tgn:7029392"
    ],
    "placetype": [
      "aat:300008347"
    ],
    "id": 1072361,
    "name:xx": "Tuergate"
  }
}
