{
  "geometry": {
    "type": "Point",
    "coordinates": [
      -95.3333,
      35.5833
    ]
  },
  "type": "Feature",
  "properties": {
    "hierarchy": [
      "tgn:2001673",
      "tgn:1000001",
      "tgn:7012149",
      "tgn:7007707",
      "tgn:7029392"
    ],
    "placetype": [
      "aat:300387145",
      "aat:300000771"
    ],
    "id": 2001673,
    "name:xx": "Muskogee"
  }
}
