{
  "geometry": {
    "type": "Point",
    "coordinates": [
      -103.6833,
      37.0833
    ]
  },
  "type": "Feature",
  "properties": {
    "hierarchy": [
      "tgn:2378925",
      "tgn:1000001",
      "tgn:7012149",
      "tgn:2000227",
      "tgn:7007158",
      "tgn:7029392"
    ],
    "placetype": [
      "aat:300008697"
    ],
    "id": 2378925,
    "name:xx": "Hart Spring"
  }
}
