{
  "geometry": {
    "type": "Point",
    "coordinates": [
      -122.2167,
      37.05
    ]
  },
  "type": "Feature",
  "properties": {
    "hierarchy": [
      "tgn:2014522",
      "tgn:1000001",
      "tgn:7012149",
      "tgn:7007157",
      "tgn:1002869",
      "tgn:7029392"
    ],
    "placetype": [
      "aat:300008347",
      "aat:300387210"
    ],
    "id": 2014522,
    "name:xx": "Swanton"
  }
}
