{
  "geometry": {
    "type": "Point",
    "coordinates": [
      -90.95,
      47.8833
    ]
  },
  "type": "Feature",
  "properties": {
    "hierarchy": [
      "tgn:2488005",
      "tgn:1000001",
      "tgn:2001014",
      "tgn:7012149",
      "tgn:7007521",
      "tgn:7029392"
    ],
    "placetype": [
      "aat:300008680"
    ],
    "id": 2488005,
    "name:xx": "Magic Lake"
  }
}
