{
  "type": "FeatureCollection",
  "features": [
    {
      "geometry": {
        "type": "Point",
        "coordinates": [
          7.2,
          50.15
        ]
      },
      "type": "Feature",
      "properties": {
        "hierarchy": [
          "tgn:7093760",
          "tgn:1000003",
          "tgn:7003682",
          "tgn:7000084",
          "tgn:7029392"
        ],
        "placetype": [
          "aat:300000206"
        ],
        "id": 7093760,
        "name:xx": "Schuwerackerhof"
      }
    },
    {
      "geometry": {
        "type": "Point",
        "coordinates": [
          8.033333,
          49.383333
        ]
      },
      "type": "Feature",
      "properties": {
        "hierarchy": [
          "tgn:7093761",
          "tgn:1000003",
          "tgn:7003682",
          "tgn:7000084",
          "tgn:7029392"
        ],
        "placetype": [
          "aat:300008777"
        ],
        "id": 7093761,
        "name:xx": "Schützler-Berg"
      }
    },
    {
      "geometry": {
        "type": "Point",
        "coordinates": [
          7.1,
          49.566667
        ]
      },
      "type": "Feature",
      "properties": {
        "hierarchy": [
          "tgn:7093762",
          "tgn:1000003",
          "tgn:7003684",
          "tgn:7000084",
          "tgn:7029392"
        ],
        "placetype": [
          "aat:300008777"
        ],
        "id": 7093762,
        "name:xx": "Schoos-Berg"
      }
    },
    {
      "geometry": {
        "type": "Point",
        "coordinates": [
          14.85,
          51.216667
        ]
      },
      "type": "Feature",
      "properties": {
        "hierarchy": [
          "tgn:7093763",
          "tgn:1000003",
          "tgn:7003685",
          "tgn:7000084",
          "tgn:7029392"
        ],
        "placetype": [
          "aat:300008777"
        ],
        "id": 7093763,
        "name:xx": "Schoorstein"
      }
    },
    {
      "geometry": {
        "type": "Point",
        "coordinates": [
          7.166667,
          53.5
        ]
      },
      "type": "Feature",
      "properties": {
        "hierarchy": [
          "tgn:7093764",
          "tgn:1000003",
          "tgn:7003676",
          "tgn:7000084",
          "tgn:7029392"
        ],
        "placetype": [
          "aat:300006163"
        ],
        "id": 7093764,
        "name:xx": "Schoonorther Polder"
      }
    },
    {
      "geometry": {
        "type": "Point",
        "coordinates": [
          7.2,
          53.5
        ]
      },
      "type": "Feature",
      "properties": {
        "hierarchy": [
          "tgn:7093765",
          "tgn:1000003",
          "tgn:7003676",
          "tgn:7000084",
          "tgn:7029392"
        ],
        "placetype": [
          "aat:300006163"
        ],
        "id": 7093765,
        "name:xx": "Schoonorth"
      }
    },
    {
      "geometry": {
        "type": "Point",
        "coordinates": [
          7.183333,
          53.5
        ]
      },
      "type": "Feature",
      "properties": {
        "hierarchy": [
          "tgn:7093766",
          "tgn:1000003",
          "tgn:7003676",
          "tgn:7000084",
          "tgn:7029392"
        ],
        "placetype": [
          "aat:300000206"
        ],
        "id": 7093766,
        "name:xx": "Schoonorth"
      }
    },
    {
      "geometry": {
        "type": "Point",
        "coordinates": [
          10.666667,
          54.25
        ]
      },
      "type": "Feature",
      "properties": {
        "hierarchy": [
          "tgn:7093767",
          "tgn:1000003",
          "tgn:7003688",
          "tgn:7000084",
          "tgn:7029392"
        ],
        "placetype": [
          "aat:300000206"
        ],
        "id": 7093767,
        "name:xx": "Schoolbrook"
      }
    },
    {
      "geometry": {
        "type": "Point",
        "coordinates": [
          9.733333,
          54.5
        ]
      },
      "type": "Feature",
      "properties": {
        "hierarchy": [
          "tgn:7093768",
          "tgn:1000003",
          "tgn:7003688",
          "tgn:7000084",
          "tgn:7029392"
        ],
        "placetype": [
          "aat:300000206"
        ],
        "id": 7093768,
        "name:xx": "Schoolbek"
      }
    },
    {
      "geometry": {
        "type": "Point",
        "coordinates": [
          7.566667,
          53.6
        ]
      },
      "type": "Feature",
      "properties": {
        "hierarchy": [
          "tgn:7093769",
          "tgn:1000003",
          "tgn:7003676",
          "tgn:7000084",
          "tgn:7029392"
        ],
        "placetype": [
          "aat:300004792"
        ],
        "id": 7093769,
        "name:xx": "Försterei Schoo"
      }
    }
  ]
}
