{
  "geometry": {
    "type": "Point",
    "coordinates": [
      -84.0167,
      41.9667
    ]
  },
  "type": "Feature",
  "properties": {
    "hierarchy": [
      "tgn:2668706",
      "tgn:1000001",
      "tgn:7012149",
      "tgn:1002588",
      "tgn:7007520",
      "tgn:7029392"
    ],
    "placetype": [
      "aat:300008706"
    ],
    "id": 2668706,
    "name:xx": "Slater Creek"
  }
}
