{
  "geometry": {
    "type": "Point",
    "coordinates": [
      31.066667,
      27.216667
    ]
  },
  "type": "Feature",
  "properties": {
    "hierarchy": [
      "tgn:7522527",
      "tgn:7001242",
      "tgn:7016833",
      "tgn:1001114",
      "tgn:7029392"
    ],
    "placetype": [
      "aat:300343519"
    ],
    "name:en": "Banī Ḩusayn al Gharbī, Ḩawḑ",
    "id": 7522527
  }
}
