{
  "geometry": {
    "type": "Point",
    "coordinates": [
      116.0833,
      38.2333
    ]
  },
  "type": "Feature",
  "properties": {
    "hierarchy": [
      "tgn:1124775",
      "tgn:1000004",
      "tgn:1000111",
      "tgn:7029392"
    ],
    "placetype": [
      "aat:300008707"
    ],
    "id": 1124775,
    "name:xx": "Hutuo He"
  }
}
