{
  "geometry": {
    "type": "Point",
    "coordinates": [
      18.1667,
      50.0833
    ]
  },
  "type": "Feature",
  "properties": {
    "hierarchy": [
      "tgn:1049401",
      "tgn:1000003",
      "tgn:7024125",
      "tgn:7006366",
      "tgn:7029392"
    ],
    "placetype": [
      "aat:300008347",
      "aat:300008389",
      "aat:300387302"
    ],
    "id": 1049401,
    "name:xx": "Racibórz"
  }
}
