{
  "geometry": {
    "type": "Point",
    "coordinates": [
      -79.1333,
      33.5833
    ]
  },
  "type": "Feature",
  "properties": {
    "hierarchy": [
      "tgn:2452783",
      "tgn:1000001",
      "tgn:2001746",
      "tgn:7012149",
      "tgn:7007712",
      "tgn:7029392"
    ],
    "placetype": [
      "aat:300008706"
    ],
    "id": 2452783,
    "name:xx": "Little Bull Creek"
  }
}
