{
  "type": "FeatureCollection",
  "features": [
    {
      "geometry": {
        "type": "Point",
        "coordinates": [
          -104.75,
          20.5
        ]
      },
      "type": "Feature",
      "properties": {
        "hierarchy": [
          "tgn:7386570",
          "tgn:7005586",
          "tgn:1000001",
          "tgn:7005560",
          "tgn:7029392"
        ],
        "placetype": [
          "aat:300008699"
        ],
        "id": 7386570,
        "name:xx": "Plan Verde"
      }
    },
    {
      "geometry": {
        "type": "Point",
        "coordinates": [
          -102.533333,
          22
        ]
      },
      "type": "Feature",
      "properties": {
        "hierarchy": [
          "tgn:7386571",
          "tgn:7005579",
          "tgn:1000001",
          "tgn:7005560",
          "tgn:7029392"
        ],
        "placetype": [
          "aat:300008347"
        ],
        "id": 7386571,
        "name:xx": "Plan Valdez"
      }
    },
    {
      "geometry": {
        "type": "Point",
        "coordinates": [
          -110.583333,
          31.3
        ]
      },
      "type": "Feature",
      "properties": {
        "hierarchy": [
          "tgn:7386572",
          "tgn:1000001",
          "tgn:1001960",
          "tgn:7005560",
          "tgn:7029392"
        ],
        "placetype": [
          "aat:300008347"
        ],
        "id": 7386572,
        "name:xx": "Planta de Bombas"
      }
    },
    {
      "geometry": {
        "type": "Point",
        "coordinates": [
          -104.25,
          21.216667
        ]
      },
      "type": "Feature",
      "properties": {
        "hierarchy": [
          "tgn:7386573",
          "tgn:7005586",
          "tgn:1000001",
          "tgn:7005560",
          "tgn:7029392"
        ],
        "placetype": [
          "aat:300008347"
        ],
        "id": 7386573,
        "name:xx": "Planta"
      }
    },
    {
      "geometry": {
        "type": "Point",
        "coordinates": [
          -97.133333,
          16.3
        ]
      },
      "type": "Feature",
      "properties": {
        "hierarchy": [
          "tgn:7386574",
          "tgn:1000001",
          "tgn:7005591",
          "tgn:7005560",
          "tgn:7029392"
        ],
        "placetype": [
          "aat:300008347"
        ],
        "id": 7386574,
        "name:xx": "Plan Minas"
      }
    },
    {
      "geometry": {
        "type": "Point",
        "coordinates": [
          -94.65,
          17.85
        ]
      },
      "type": "Feature",
      "properties": {
        "hierarchy": [
          "tgn:7386575",
          "tgn:1000001",
          "tgn:7005599",
          "tgn:7005560",
          "tgn:7029392"
        ],
        "placetype": [
          "aat:300008347"
        ],
        "id": 7386575,
        "name:xx": "Plan Mariscal"
      }
    },
    {
      "geometry": {
        "type": "Point",
        "coordinates": [
          -100.883333,
          25.333333
        ]
      },
      "type": "Feature",
      "properties": {
        "hierarchy": [
          "tgn:7386577",
          "tgn:1001853",
          "tgn:1000001",
          "tgn:7005560",
          "tgn:7029392"
        ],
        "placetype": [
          "aat:300008795"
        ],
        "id": 7386577,
        "name:xx": "Penitente, Cerro"
      }
    },
    {
      "geometry": {
        "type": "Point",
        "coordinates": [
          -109.483333,
          30.6
        ]
      },
      "type": "Feature",
      "properties": {
        "hierarchy": [
          "tgn:7386578",
          "tgn:1000001",
          "tgn:1001960",
          "tgn:7005560",
          "tgn:7029392"
        ],
        "placetype": [
          "aat:300008795"
        ],
        "id": 7386578,
        "name:xx": "Peñitas, Sierra"
      }
    },
    {
      "geometry": {
        "type": "Point",
        "coordinates": [
          -99.883333,
          26.4
        ]
      },
      "type": "Feature",
      "properties": {
        "hierarchy": [
          "tgn:7386579",
          "tgn:1000001",
          "tgn:7005589",
          "tgn:7005560",
          "tgn:7029392"
        ],
        "placetype": [
          "aat:300000241"
        ],
        "id": 7386579,
        "name:xx": "Rancho Peñitas"
      }
    }
  ]
}
