{
  "geometry": {
    "type": "Point",
    "coordinates": [
      -80.15,
      41.15
    ]
  },
  "type": "Feature",
  "properties": {
    "hierarchy": [
      "tgn:2513785",
      "tgn:1000001",
      "tgn:7012149",
      "tgn:1002659",
      "tgn:7007710",
      "tgn:7029392"
    ],
    "placetype": [
      "aat:300008699"
    ],
    "id": 2513785,
    "name:xx": "Mill Run"
  }
}
