{
  "geometry": {
    "type": "Point",
    "coordinates": [
      -70.3667,
      44.9333
    ]
  },
  "type": "Feature",
  "properties": {
    "hierarchy": [
      "tgn:2504587",
      "tgn:1000001",
      "tgn:2000921",
      "tgn:7012149",
      "tgn:7007515",
      "tgn:7029392"
    ],
    "placetype": [
      "aat:300008798"
    ],
    "id": 2504587,
    "name:xx": "Mecham Hill"
  }
}
