{
  "geometry": {
    "type": "Point",
    "coordinates": [
      -75.9667,
      43.2333
    ]
  },
  "type": "Feature",
  "properties": {
    "hierarchy": [
      "tgn:2274315",
      "tgn:1000001",
      "tgn:7012149",
      "tgn:1002758",
      "tgn:7007568",
      "tgn:7029392"
    ],
    "placetype": [
      "aat:300132316"
    ],
    "id": 2274315,
    "name:xx": "Dakin Bay"
  }
}
