{
  "geometry": {
    "type": "Point",
    "coordinates": [
      -114.0333,
      42.15
    ]
  },
  "type": "Feature",
  "properties": {
    "hierarchy": [
      "tgn:2173627",
      "tgn:1000001",
      "tgn:2000467",
      "tgn:7012149",
      "tgn:7007250",
      "tgn:7029392"
    ],
    "placetype": [
      "aat:300008697"
    ],
    "id": 2173627,
    "name:xx": "Birch Spring"
  }
}
