{
  "geometry": {
    "type": "Point",
    "coordinates": [
      -91.3333,
      39.6833
    ]
  },
  "type": "Feature",
  "properties": {
    "hierarchy": [
      "tgn:2322075",
      "tgn:1000001",
      "tgn:7012149",
      "tgn:1002634",
      "tgn:7007523",
      "tgn:7029392"
    ],
    "placetype": [
      "aat:300008706"
    ],
    "id": 2322075,
    "name:xx": "Fall Creek"
  }
}
