{
  "type": "FeatureCollection",
  "features": [
    {
      "geometry": {
        "type": "Point",
        "coordinates": [
          30.885494,
          29.346712
        ]
      },
      "type": "Feature",
      "properties": {
        "hierarchy": [
          "tgn:7541130",
          "tgn:7001242",
          "tgn:7001105",
          "tgn:7016833",
          "tgn:7029392"
        ],
        "placetype": [
          "aat:300008347"
        ],
        "name:en": "'Izbat 'Abd an Nabī Ḩusayn",
        "id": 7541130
      }
    },
    {
      "geometry": {
        "type": "Point",
        "coordinates": [
          30.837615,
          29.362401
        ]
      },
      "type": "Feature",
      "properties": {
        "hierarchy": [
          "tgn:7541131",
          "tgn:7001242",
          "tgn:7001105",
          "tgn:7016833",
          "tgn:7029392"
        ],
        "placetype": [
          "aat:300008347"
        ],
        "name:en": "'Izbat Ḩarfūsh",
        "id": 7541131
      }
    },
    {
      "geometry": {
        "type": "Point",
        "coordinates": [
          30.868629,
          29.315613
        ]
      },
      "type": "Feature",
      "properties": {
        "hierarchy": [
          "tgn:7541132",
          "tgn:7001242",
          "tgn:7001105",
          "tgn:7016833",
          "tgn:7029392"
        ],
        "placetype": [
          "aat:300008347"
        ],
        "name:en": "'Izbat Muḩmmad Khamīs az Zamlūţī",
        "id": 7541132
      }
    },
    {
      "geometry": {
        "type": "Point",
        "coordinates": [
          30.862849,
          29.350267
        ]
      },
      "type": "Feature",
      "properties": {
        "hierarchy": [
          "tgn:7541133",
          "tgn:7001242",
          "tgn:7001105",
          "tgn:7016833",
          "tgn:7029392"
        ],
        "placetype": [
          "aat:300008347"
        ],
        "name:en": "'Izbat al Gharīb",
        "id": 7541133
      }
    },
    {
      "geometry": {
        "type": "Point",
        "coordinates": [
          30.896451,
          29.288004
        ]
      },
      "type": "Feature",
      "properties": {
        "hierarchy": [
          "tgn:7541134",
          "tgn:7001242",
          "tgn:7001105",
          "tgn:7016833",
          "tgn:7029392"
        ],
        "placetype": [
          "aat:300008347"
        ],
        "name:en": "'Izbat Sa'd Abū Diyāb",
        "id": 7541134
      }
    },
    {
      "geometry": {
        "type": "Point",
        "coordinates": [
          30.842825,
          29.291238
        ]
      },
      "type": "Feature",
      "properties": {
        "hierarchy": [
          "tgn:7541135",
          "tgn:7001242",
          "tgn:7001105",
          "tgn:7016833",
          "tgn:7029392"
        ],
        "placetype": [
          "aat:300008347"
        ],
        "name:en": "Minsha'at Abū Khalaf",
        "id": 7541135
      }
    },
    {
      "geometry": {
        "type": "Point",
        "coordinates": [
          30.856758,
          29.290035
        ]
      },
      "type": "Feature",
      "properties": {
        "hierarchy": [
          "tgn:7541136",
          "tgn:7001242",
          "tgn:7001105",
          "tgn:7016833",
          "tgn:7029392"
        ],
        "placetype": [
          "aat:300008347"
        ],
        "name:en": "'Izbat Junaydī",
        "id": 7541136
      }
    },
    {
      "geometry": {
        "type": "Point",
        "coordinates": [
          30.855464,
          29.279803
        ]
      },
      "type": "Feature",
      "properties": {
        "hierarchy": [
          "tgn:7541137",
          "tgn:7001242",
          "tgn:7001105",
          "tgn:7016833",
          "tgn:7029392"
        ],
        "placetype": [
          "aat:300008347"
        ],
        "name:en": "'Izbat Sunūfar",
        "id": 7541137
      }
    },
    {
      "geometry": {
        "type": "Point",
        "coordinates": [
          30.722563,
          29.212213
        ]
      },
      "type": "Feature",
      "properties": {
        "hierarchy": [
          "tgn:7541138",
          "tgn:7001242",
          "tgn:7001105",
          "tgn:7016833",
          "tgn:7029392"
        ],
        "placetype": [
          "aat:300006075"
        ],
        "name:en": "Tur'at an Nazlah",
        "id": 7541138
      }
    },
    {
      "geometry": {
        "type": "Point",
        "coordinates": [
          30.828304,
          29.255386
        ]
      },
      "type": "Feature",
      "properties": {
        "hierarchy": [
          "tgn:7541139",
          "tgn:7001242",
          "tgn:7001105",
          "tgn:7016833",
          "tgn:7029392"
        ],
        "placetype": [
          "aat:300008347"
        ],
        "name:en": "Kafr al Jubb",
        "id": 7541139
      }
    }
  ]
}
