{
  "geometry": {
    "type": "Point",
    "coordinates": [
      -122.8833,
      42.0167
    ]
  },
  "type": "Feature",
  "properties": {
    "hierarchy": [
      "tgn:2435856",
      "tgn:1000001",
      "tgn:7012149",
      "tgn:2001711",
      "tgn:7007708",
      "tgn:7029392"
    ],
    "placetype": [
      "aat:300008680"
    ],
    "id": 2435856,
    "name:xx": "Kettle Lake"
  }
}
