{
  "geometry": {
    "type": "Point",
    "coordinates": [
      39.3833,
      47.5833
    ]
  },
  "type": "Feature",
  "properties": {
    "hierarchy": [
      "tgn:1125747",
      "tgn:1000003",
      "tgn:7029392"
    ],
    "placetype": [
      "aat:300008707"
    ],
    "id": 1125747,
    "name:xx": "Krepkaya"
  }
}
