{
  "type": "FeatureCollection",
  "features": [
    {
      "geometry": {
        "type": "Point",
        "coordinates": [
          -81.3833,
          32.2
        ]
      },
      "type": "Feature",
      "properties": {
        "hierarchy": [
          "tgn:2293020",
          "tgn:1000001",
          "tgn:7012149",
          "tgn:2000342",
          "tgn:7007248",
          "tgn:7029392"
        ],
        "placetype": [
          "aat:300008347"
        ],
        "id": 2293020,
        "name:xx": "Doswell"
      }
    },
    {
      "geometry": {
        "type": "Point",
        "coordinates": [
          -120.3333,
          45.8667
        ]
      },
      "type": "Feature",
      "properties": {
        "hierarchy": [
          "tgn:2293021",
          "tgn:1000001",
          "tgn:7012149",
          "tgn:1002554",
          "tgn:7007920",
          "tgn:7029392"
        ],
        "placetype": [
          "aat:300008347"
        ],
        "id": 2293021,
        "name:xx": "Dot"
      }
    },
    {
      "geometry": {
        "type": "Point",
        "coordinates": [
          -123.4667,
          41.1
        ]
      },
      "type": "Feature",
      "properties": {
        "hierarchy": [
          "tgn:2293022",
          "tgn:1000001",
          "tgn:7012149",
          "tgn:2000181",
          "tgn:7007157",
          "tgn:7029392"
        ],
        "placetype": [
          "aat:300008706"
        ],
        "id": 2293022,
        "name:xx": "Dot Creek"
      }
    },
    {
      "geometry": {
        "type": "Point",
        "coordinates": [
          -116.1,
          47.4167
        ]
      },
      "type": "Feature",
      "properties": {
        "hierarchy": [
          "tgn:2293023",
          "tgn:1000001",
          "tgn:7012149",
          "tgn:2000491",
          "tgn:7007250",
          "tgn:7029392"
        ],
        "placetype": [
          "aat:300008706"
        ],
        "id": 2293023,
        "name:xx": "Dot Creek"
      }
    },
    {
      "geometry": {
        "type": "Point",
        "coordinates": [
          -120.4833,
          47.2333
        ]
      },
      "type": "Feature",
      "properties": {
        "hierarchy": [
          "tgn:2293024",
          "tgn:1000001",
          "tgn:7012149",
          "tgn:1002553",
          "tgn:7007920",
          "tgn:7029392"
        ],
        "placetype": [
          "aat:300008706"
        ],
        "id": 2293024,
        "name:xx": "Dot Creek"
      }
    },
    {
      "geometry": {
        "type": "Point",
        "coordinates": [
          -120.5167,
          48.8333
        ]
      },
      "type": "Feature",
      "properties": {
        "hierarchy": [
          "tgn:2293025",
          "tgn:1000001",
          "tgn:7012149",
          "tgn:1002742",
          "tgn:7007920",
          "tgn:7029392"
        ],
        "placetype": [
          "aat:300008706"
        ],
        "id": 2293025,
        "name:xx": "Dot Creek"
      }
    },
    {
      "geometry": {
        "type": "Point",
        "coordinates": [
          -91.8167,
          36
        ]
      },
      "type": "Feature",
      "properties": {
        "hierarchy": [
          "tgn:2293026",
          "tgn:1000001",
          "tgn:7016172",
          "tgn:7012149",
          "tgn:2000137",
          "tgn:7029392"
        ],
        "placetype": [
          "aat:300008680"
        ],
        "id": 2293026,
        "name:xx": "Dot Hole"
      }
    },
    {
      "geometry": {
        "type": "Point",
        "coordinates": [
          -83.1,
          37.45
        ]
      },
      "type": "Feature",
      "properties": {
        "hierarchy": [
          "tgn:2293027",
          "tgn:1000001",
          "tgn:7012149",
          "tgn:2000805",
          "tgn:7007255",
          "tgn:7029392"
        ],
        "placetype": [
          "aat:300008761"
        ],
        "id": 2293027,
        "name:xx": "Dot Hollow"
      }
    },
    {
      "geometry": {
        "type": "Point",
        "coordinates": [
          -133.3167,
          55.9
        ]
      },
      "type": "Feature",
      "properties": {
        "hierarchy": [
          "tgn:2293028",
          "tgn:7006450",
          "tgn:1000001",
          "tgn:7012149",
          "tgn:2000082",
          "tgn:7029392"
        ],
        "placetype": [
          "aat:300008791"
        ],
        "id": 2293028,
        "name:xx": "Dot Island"
      }
    },
    {
      "geometry": {
        "type": "Point",
        "coordinates": [
          -152.75,
          58.05
        ]
      },
      "type": "Feature",
      "properties": {
        "hierarchy": [
          "tgn:2293029",
          "tgn:7006450",
          "tgn:1000001",
          "tgn:2124012",
          "tgn:7012149",
          "tgn:7029392"
        ],
        "placetype": [
          "aat:300008791"
        ],
        "id": 2293029,
        "name:xx": "Dot Island"
      }
    }
  ]
}
