{
  "geometry": {
    "type": "Point",
    "coordinates": [
      -91.15,
      30.85
    ]
  },
  "type": "Feature",
  "properties": {
    "hierarchy": [
      "tgn:2678050",
      "tgn:1000001",
      "tgn:2000872",
      "tgn:7012149",
      "tgn:7007256",
      "tgn:7029392"
    ],
    "placetype": [
      "aat:300008706"
    ],
    "id": 2678050,
    "name:xx": "South Fork Beaver Creek"
  }
}
