{
  "geometry": {
    "type": "Point",
    "coordinates": [
      -79.9667,
      8.4833
    ]
  },
  "type": "Feature",
  "properties": {
    "hierarchy": [
      "tgn:1018890",
      "tgn:1001483",
      "tgn:1000001",
      "tgn:7005565",
      "tgn:7029392"
    ],
    "placetype": [
      "aat:300008347"
    ],
    "id": 1018890,
    "name:xx": "San Carlos"
  }
}
