{
  "geometry": {
    "type": "Point",
    "coordinates": [
      -0.45,
      40.65
    ]
  },
  "type": "Feature",
  "properties": {
    "hierarchy": [
      "tgn:7342352",
      "tgn:7002759",
      "tgn:7002843",
      "tgn:1000003",
      "tgn:1000095",
      "tgn:7029392"
    ],
    "placetype": [
      "aat:300008777"
    ],
    "id": 7342352,
    "name:xx": "Carrascosa, Sierra"
  }
}
