{
  "geometry": {
    "type": "Point",
    "coordinates": [
      79.6667,
      25.0333
    ]
  },
  "type": "Feature",
  "properties": {
    "hierarchy": [
      "tgn:1075314",
      "tgn:1000004",
      "tgn:7000198",
      "tgn:1001894",
      "tgn:7029392"
    ],
    "placetype": [
      "aat:300008347"
    ],
    "id": 1075314,
    "name:xx": "Garhi Malehra"
  }
}
