{
  "type": "FeatureCollection",
  "features": [
    {
      "geometry": {
        "type": "Point",
        "coordinates": [
          -72,
          42.7
        ]
      },
      "type": "Feature",
      "properties": {
        "hierarchy": [
          "tgn:7022180",
          "tgn:7019618",
          "tgn:1000001",
          "tgn:7012149",
          "tgn:7007564",
          "tgn:7029392"
        ],
        "placetype": [
          "aat:300008791"
        ],
        "id": 7022180,
        "name:xx": "Blueberry Island"
      }
    },
    {
      "geometry": {
        "type": "Point",
        "coordinates": [
          -91.15,
          32.6667
        ]
      },
      "type": "Feature",
      "properties": {
        "hierarchy": [
          "tgn:7022181",
          "tgn:1000001",
          "tgn:2000871",
          "tgn:7012149",
          "tgn:7007256",
          "tgn:7029392"
        ],
        "placetype": [
          "aat:300132348"
        ],
        "id": 7022181,
        "name:xx": "Atherton Towhead"
      }
    },
    {
      "geometry": {
        "type": "Point",
        "coordinates": [
          -119.65,
          45.8667
        ]
      },
      "type": "Feature",
      "properties": {
        "hierarchy": [
          "tgn:7022182",
          "tgn:1000001",
          "tgn:7012149",
          "tgn:2001719",
          "tgn:7007708",
          "tgn:7029392"
        ],
        "placetype": [
          "aat:300386851",
          "aat:300008791"
        ],
        "id": 7022182,
        "name:xx": "Coyote Island"
      }
    },
    {
      "geometry": {
        "type": "Point",
        "coordinates": [
          -75.0833,
          40.8
        ]
      },
      "type": "Feature",
      "properties": {
        "hierarchy": [
          "tgn:7022183",
          "tgn:1000001",
          "tgn:7012149",
          "tgn:1002729",
          "tgn:7007710",
          "tgn:7029392"
        ],
        "placetype": [
          "aat:300386853"
        ],
        "id": 7022183,
        "name:xx": "Foul Rift Islands"
      }
    },
    {
      "geometry": {
        "type": "Point",
        "coordinates": [
          -106,
          32.25
        ]
      },
      "type": "Feature",
      "properties": {
        "hierarchy": [
          "tgn:7022184",
          "tgn:1000001",
          "tgn:2001435",
          "tgn:7012149",
          "tgn:7007566",
          "tgn:7029392"
        ],
        "placetype": [
          "aat:300386994"
        ],
        "id": 7022184,
        "name:xx": "Fort Bliss"
      }
    },
    {
      "geometry": {
        "type": "Point",
        "coordinates": [
          -107,
          36.6667
        ]
      },
      "type": "Feature",
      "properties": {
        "hierarchy": [
          "tgn:7022187",
          "tgn:1000001",
          "tgn:7012149",
          "tgn:2001449",
          "tgn:7007566",
          "tgn:7029392"
        ],
        "placetype": [
          "aat:300008347",
          "aat:300387324"
        ],
        "id": 7022187,
        "name:xx": "Jicarilla Apache Indian Reservation"
      }
    },
    {
      "geometry": {
        "type": "Point",
        "coordinates": [
          -107.3333,
          35
        ]
      },
      "type": "Feature",
      "properties": {
        "hierarchy": [
          "tgn:7022188",
          "tgn:1000001",
          "tgn:2001431",
          "tgn:7012149",
          "tgn:7007566",
          "tgn:7029392"
        ],
        "placetype": [
          "aat:300008347",
          "aat:300387324"
        ],
        "id": 7022188,
        "name:xx": "Laguna Indian Reservation"
      }
    },
    {
      "geometry": {
        "type": "Point",
        "coordinates": [
          -108.4167,
          34.8333
        ]
      },
      "type": "Feature",
      "properties": {
        "hierarchy": [
          "tgn:7022189",
          "tgn:1000001",
          "tgn:2001431",
          "tgn:7012149",
          "tgn:7007566",
          "tgn:7029392"
        ],
        "placetype": [
          "aat:300008347",
          "aat:300387324"
        ],
        "id": 7022189,
        "name:xx": "Ramah Navajo Indian Reservation"
      }
    }
  ]
}
