{
  "geometry": {
    "type": "Point",
    "coordinates": [
      -132.3333,
      57.3667
    ]
  },
  "type": "Feature",
  "properties": {
    "hierarchy": [
      "tgn:1106168",
      "tgn:7005735",
      "tgn:7005685",
      "tgn:1000001",
      "tgn:7029392"
    ],
    "placetype": [
      "aat:300008795"
    ],
    "id": 1106168,
    "name:xx": "Ratz, Mount"
  }
}
