{
  "geometry": {
    "type": "Point",
    "coordinates": [
      -78.7167,
      41.2833
    ]
  },
  "type": "Feature",
  "properties": {
    "hierarchy": [
      "tgn:2402321",
      "tgn:1000001",
      "tgn:7012149",
      "tgn:1002352",
      "tgn:7007710",
      "tgn:7029392"
    ],
    "placetype": [
      "aat:300008347"
    ],
    "id": 2402321,
    "name:xx": "Horton City"
  }
}
