{
  "geometry": {
    "type": "Point",
    "coordinates": [
      35.2667,
      51.75
    ]
  },
  "type": "Feature",
  "properties": {
    "hierarchy": [
      "tgn:1056819",
      "tgn:1000004",
      "tgn:1003382",
      "tgn:7018214",
      "tgn:7002435",
      "tgn:7029392"
    ],
    "placetype": [
      "aat:300008347"
    ],
    "id": 1056819,
    "name:xx": "Maritsa"
  }
}
