{
  "geometry": {
    "type": "Point",
    "coordinates": [
      136.1167,
      35.9833
    ]
  },
  "type": "Feature",
  "properties": {
    "hierarchy": [
      "tgn:1140325",
      "tgn:7000895",
      "tgn:1000004",
      "tgn:1000974",
      "tgn:1000120",
      "tgn:7029392"
    ],
    "placetype": [
      "aat:300008347"
    ],
    "id": 1140325,
    "name:xx": "Asahi"
  }
}
