{
  "geometry": {
    "type": "Point",
    "coordinates": [
      -82.4333,
      27.6833
    ]
  },
  "type": "Feature",
  "properties": {
    "hierarchy": [
      "tgn:2381891",
      "tgn:1000001",
      "tgn:1002479",
      "tgn:7012149",
      "tgn:7007240",
      "tgn:7029392"
    ],
    "placetype": [
      "aat:300132316"
    ],
    "id": 2381891,
    "name:xx": "Hayes Bayou"
  }
}
