{
  "geometry": {
    "type": "Point",
    "coordinates": [
      123.8667,
      42.3167
    ]
  },
  "type": "Feature",
  "properties": {
    "hierarchy": [
      "tgn:1072268",
      "tgn:1000004",
      "tgn:1001390",
      "tgn:1000111",
      "tgn:7029392"
    ],
    "placetype": [
      "aat:300008347"
    ],
    "id": 1072268,
    "name:xx": "Tieling"
  }
}
