{
  "geometry": {
    "type": "Point",
    "coordinates": [
      -98.0667,
      38.5167
    ]
  },
  "type": "Feature",
  "properties": {
    "hierarchy": [
      "tgn:2400071",
      "tgn:1000001",
      "tgn:7012149",
      "tgn:7007254",
      "tgn:7029392"
    ],
    "placetype": [
      "aat:300008706"
    ],
    "id": 2400071,
    "name:xx": "Horse Creek"
  }
}
