{
  "geometry": {
    "type": "Point",
    "coordinates": [
      120.875,
      22.11
    ]
  },
  "type": "Feature",
  "properties": {
    "hierarchy": [
      "tgn:7501833",
      "tgn:1000004",
      "tgn:7492971",
      "tgn:1000141",
      "tgn:7029392"
    ],
    "placetype": [
      "aat:300007836"
    ],
    "id": 7501833,
    "name:xx": "Jiupeng Yihao Qiao"
  }
}
