{
  "geometry": {
    "type": "Point",
    "coordinates": [
      -111.5667,
      35.0167
    ]
  },
  "type": "Feature",
  "properties": {
    "hierarchy": [
      "tgn:2479417",
      "tgn:1000001",
      "tgn:7006451",
      "tgn:2000092",
      "tgn:7012149",
      "tgn:7029392"
    ],
    "placetype": [
      "aat:300006191"
    ],
    "id": 2479417,
    "name:xx": "Lagunita Tank"
  }
}
