{
  "geometry": {
    "type": "Point",
    "coordinates": [
      -108.95,
      32.9833
    ]
  },
  "type": "Feature",
  "properties": {
    "hierarchy": [
      "tgn:2135587",
      "tgn:1000001",
      "tgn:7012149",
      "tgn:2001437",
      "tgn:7007566",
      "tgn:7029392"
    ],
    "placetype": [
      "aat:300006191"
    ],
    "id": 2135587,
    "name:xx": "Apache Creek Trick Tank"
  }
}
