{
  "geometry": {
    "type": "Point",
    "coordinates": [
      77.367,
      20.732
    ]
  },
  "type": "Feature",
  "properties": {
    "hierarchy": [
      "tgn:1076287",
      "tgn:1000004",
      "tgn:7000198",
      "tgn:1001895",
      "tgn:7029392"
    ],
    "placetype": [
      "aat:300008347"
    ],
    "name:en": "Murtajāpur",
    "id": 1076287
  }
}
