{
  "type": "FeatureCollection",
  "features": [
    {
      "geometry": {
        "type": "Point",
        "coordinates": [
          -78.8667,
          39.9
        ]
      },
      "type": "Feature",
      "properties": {
        "hierarchy": [
          "tgn:2751161",
          "tgn:1000001",
          "tgn:7012149",
          "tgn:1002904",
          "tgn:7007710",
          "tgn:7029392"
        ],
        "placetype": [
          "aat:300008699"
        ],
        "id": 2751161,
        "name:xx": "Ware Run"
      }
    },
    {
      "geometry": {
        "type": "Point",
        "coordinates": [
          -82.2333,
          34.4
        ]
      },
      "type": "Feature",
      "properties": {
        "hierarchy": [
          "tgn:2751162",
          "tgn:1000001",
          "tgn:7012149",
          "tgn:2001754",
          "tgn:7007712",
          "tgn:7029392"
        ],
        "placetype": [
          "aat:300006191"
        ],
        "id": 2751162,
        "name:xx": "Ware Shoals Reservoir"
      }
    },
    {
      "geometry": {
        "type": "Point",
        "coordinates": [
          -110.6667,
          39.25
        ]
      },
      "type": "Feature",
      "properties": {
        "hierarchy": [
          "tgn:2751163",
          "tgn:1000001",
          "tgn:2002108",
          "tgn:7012149",
          "tgn:7007827",
          "tgn:7029392"
        ],
        "placetype": [
          "aat:300008697"
        ],
        "id": 2751163,
        "name:xx": "Ware Spring"
      }
    },
    {
      "geometry": {
        "type": "Point",
        "coordinates": [
          -76.3167,
          37.1333
        ]
      },
      "type": "Feature",
      "properties": {
        "hierarchy": [
          "tgn:2751164",
          "tgn:1000001",
          "tgn:7012149",
          "tgn:7022208",
          "tgn:7007919",
          "tgn:7029392"
        ],
        "placetype": [
          "aat:300008850"
        ],
        "id": 2751164,
        "name:xx": "Ware Stick Point"
      }
    },
    {
      "geometry": {
        "type": "Point",
        "coordinates": [
          -107.5833,
          39.55
        ]
      },
      "type": "Feature",
      "properties": {
        "hierarchy": [
          "tgn:2751165",
          "tgn:1000001",
          "tgn:7012149",
          "tgn:2000214",
          "tgn:7007158",
          "tgn:7029392"
        ],
        "placetype": [
          "aat:300006075"
        ],
        "id": 2751165,
        "name:xx": "Ware and Hinds Ditch"
      }
    },
    {
      "geometry": {
        "type": "Point",
        "coordinates": [
          -85.6833,
          30.1667
        ]
      },
      "type": "Feature",
      "properties": {
        "hierarchy": [
          "tgn:2751166",
          "tgn:2000258",
          "tgn:1000001",
          "tgn:7012149",
          "tgn:7007240",
          "tgn:7029392"
        ],
        "placetype": [
          "aat:300008680"
        ],
        "id": 2751166,
        "name:xx": "Ware, Lake"
      }
    },
    {
      "geometry": {
        "type": "Point",
        "coordinates": [
          -70.7,
          41.75
        ]
      },
      "type": "Feature",
      "properties": {
        "hierarchy": [
          "tgn:2751167",
          "tgn:1000001",
          "tgn:7014423",
          "tgn:7012149",
          "tgn:7007517",
          "tgn:7029392"
        ],
        "placetype": [
          "aat:300055621"
        ],
        "id": 2751167,
        "name:xx": "Wareham Narrows"
      }
    },
    {
      "geometry": {
        "type": "Point",
        "coordinates": [
          -70.7,
          41.7333
        ]
      },
      "type": "Feature",
      "properties": {
        "hierarchy": [
          "tgn:2751168",
          "tgn:1000001",
          "tgn:7014423",
          "tgn:7012149",
          "tgn:7007517",
          "tgn:7029392"
        ],
        "placetype": [
          "aat:300008850"
        ],
        "id": 2751168,
        "name:xx": "Wareham Neck"
      }
    },
    {
      "geometry": {
        "type": "Point",
        "coordinates": [
          -70.7,
          41.75
        ]
      },
      "type": "Feature",
      "properties": {
        "hierarchy": [
          "tgn:2751169",
          "tgn:1000001",
          "tgn:7014423",
          "tgn:7012149",
          "tgn:7007517",
          "tgn:7029392"
        ],
        "placetype": [
          "aat:300008707"
        ],
        "id": 2751169,
        "name:xx": "Wareham River"
      }
    }
  ]
}
