{
  "geometry": {
    "type": "Point",
    "coordinates": [
      -83.4667,
      44.3333
    ]
  },
  "type": "Feature",
  "properties": {
    "hierarchy": [
      "tgn:2734705",
      "tgn:1000001",
      "tgn:7012149",
      "tgn:2000965",
      "tgn:7007520",
      "tgn:7029392"
    ],
    "placetype": [
      "aat:300006075"
    ],
    "id": 2734705,
    "name:xx": "Tuttle Ditch"
  }
}
