{
  "geometry": {
    "type": "Point",
    "coordinates": [
      40.0333,
      -1.4833
    ]
  },
  "type": "Feature",
  "properties": {
    "hierarchy": [
      "tgn:1090450",
      "tgn:7001242",
      "tgn:7593796",
      "tgn:1000169",
      "tgn:7029392"
    ],
    "placetype": [
      "aat:300008347"
    ],
    "id": 1090450,
    "name:xx": "Hola"
  }
}
