{
  "geometry": {
    "type": "Point",
    "coordinates": [
      -88.8167,
      32.6667
    ]
  },
  "type": "Feature",
  "properties": {
    "hierarchy": [
      "tgn:2574799",
      "tgn:1000001",
      "tgn:7012149",
      "tgn:7007522",
      "tgn:7029392"
    ],
    "placetype": [
      "aat:300008706"
    ],
    "id": 2574799,
    "name:xx": "Penders Creek"
  }
}
