{
  "geometry": {
    "type": "Point",
    "coordinates": [
      -123.9167,
      43.2667
    ]
  },
  "type": "Feature",
  "properties": {
    "hierarchy": [
      "tgn:2522175",
      "tgn:1000001",
      "tgn:2001702",
      "tgn:7012149",
      "tgn:7007708",
      "tgn:7029392"
    ],
    "placetype": [
      "aat:300008706"
    ],
    "id": 2522175,
    "name:xx": "Moon Creek"
  }
}
