{
  "geometry": {
    "type": "Point",
    "coordinates": [
      -98.75,
      20.033333
    ]
  },
  "type": "Feature",
  "properties": {
    "hierarchy": [
      "tgn:7436302",
      "tgn:7005587",
      "tgn:1000001",
      "tgn:7005560",
      "tgn:7029392"
    ],
    "placetype": [
      "aat:300007783"
    ],
    "id": 7436302,
    "name:xx": "Soledad"
  }
}
