{
  "geometry": {
    "type": "Point",
    "coordinates": [
      -83.1667,
      43.75
    ]
  },
  "type": "Feature",
  "properties": {
    "hierarchy": [
      "tgn:2156865",
      "tgn:1000001",
      "tgn:7012149",
      "tgn:2000964",
      "tgn:7007520",
      "tgn:7029392"
    ],
    "placetype": [
      "aat:300006075"
    ],
    "id": 2156865,
    "name:xx": "Beaubien Drain"
  }
}
