{
  "geometry": {
    "type": "Point",
    "coordinates": [
      -79.65,
      39.65
    ]
  },
  "type": "Feature",
  "properties": {
    "hierarchy": [
      "tgn:2750971",
      "tgn:1000001",
      "tgn:7012149",
      "tgn:2002288",
      "tgn:7013961",
      "tgn:7029392"
    ],
    "placetype": [
      "aat:300008697"
    ],
    "id": 2750971,
    "name:xx": "Ward Thompson Spring"
  }
}
