{
  "geometry": {
    "type": "Point",
    "coordinates": [
      82.732831,
      25.69844
    ]
  },
  "type": "Feature",
  "properties": {
    "hierarchy": [
      "tgn:7584624",
      "tgn:1000004",
      "tgn:7000198",
      "tgn:7016722",
      "tgn:7029392"
    ],
    "placetype": [
      "aat:300008347"
    ],
    "name:en": "Zafarābād",
    "id": 7584624
  }
}
