{
  "type": "FeatureCollection",
  "features": [
    {
      "geometry": {
        "type": "Point",
        "coordinates": [
          14.398,
          40.989
        ]
      },
      "type": "Feature",
      "properties": {
        "hierarchy": [
          "tgn:5004315",
          "tgn:7003013",
          "tgn:7003005",
          "tgn:1000003",
          "tgn:1000080",
          "tgn:7029392"
        ],
        "placetype": [
          "aat:300008347",
          "aat:300000810",
          "aat:300167671"
        ],
        "id": 5004315,
        "name:xx": "Suéssula"
      }
    },
    {
      "geometry": {
        "type": "Point",
        "coordinates": [
          12.283333,
          42.983333
        ]
      },
      "type": "Feature",
      "properties": {
        "hierarchy": [
          "tgn:5004318",
          "tgn:7003128",
          "tgn:1000003",
          "tgn:7008516",
          "tgn:1000080",
          "tgn:7029392"
        ],
        "placetype": [
          "aat:300008347",
          "aat:300000810",
          "aat:300167671"
        ],
        "id": 5004318,
        "name:xx": "Spina"
      }
    }
  ]
}
