{
  "geometry": {
    "type": "Point",
    "coordinates": [
      -110.1667,
      40.55
    ]
  },
  "type": "Feature",
  "properties": {
    "hierarchy": [
      "tgn:2685943",
      "tgn:1000001",
      "tgn:2002107",
      "tgn:7012149",
      "tgn:7007827",
      "tgn:7029392"
    ],
    "placetype": [
      "aat:300008706"
    ],
    "id": 2685943,
    "name:xx": "Spring Branch Creek"
  }
}
