{
  "geometry": {
    "type": "Point",
    "coordinates": [
      42.95,
      42.5667
    ]
  },
  "type": "Feature",
  "properties": {
    "hierarchy": [
      "tgn:1056294",
      "tgn:1000004",
      "tgn:7012215",
      "tgn:7006653",
      "tgn:7029392"
    ],
    "placetype": [
      "aat:300008347"
    ],
    "id": 1056294,
    "name:xx": "Ladzhanurges"
  }
}
