{
  "geometry": {
    "type": "Point",
    "coordinates": [
      -46.3167,
      -14.05
    ]
  },
  "type": "Feature",
  "properties": {
    "hierarchy": [
      "tgn:1022583",
      "tgn:7012827",
      "tgn:7002454",
      "tgn:1000047",
      "tgn:1000002",
      "tgn:7029392"
    ],
    "placetype": [
      "aat:300008347"
    ],
    "id": 1022583,
    "name:xx": "Posse"
  }
}
