{
  "geometry": {
    "type": "Point",
    "coordinates": [
      -86.8167,
      40.7167
    ]
  },
  "type": "Feature",
  "properties": {
    "hierarchy": [
      "tgn:2673805",
      "tgn:1000001",
      "tgn:7012149",
      "tgn:1003021",
      "tgn:7007252",
      "tgn:7029392"
    ],
    "placetype": [
      "aat:300006075"
    ],
    "id": 2673805,
    "name:xx": "Snow Ditch"
  }
}
