{
  "geometry": {
    "type": "Point",
    "coordinates": [
      -88.8833,
      33.0333
    ]
  },
  "type": "Feature",
  "properties": {
    "hierarchy": [
      "tgn:2521993",
      "tgn:1000001",
      "tgn:7012149",
      "tgn:7007522",
      "tgn:7029392"
    ],
    "placetype": [
      "aat:300008706"
    ],
    "id": 2521993,
    "name:xx": "Moody Creek"
  }
}
