{
  "type": "FeatureCollection",
  "features": [
    {
      "geometry": {
        "type": "Point",
        "coordinates": [
          -111.983333,
          26.9
        ]
      },
      "type": "Feature",
      "properties": {
        "hierarchy": [
          "tgn:7386000",
          "tgn:1001836",
          "tgn:1000001",
          "tgn:7005560",
          "tgn:7029392"
        ],
        "placetype": [
          "aat:300386846"
        ],
        "id": 7386000,
        "name:xx": "Prieta, Punta"
      }
    },
    {
      "geometry": {
        "type": "Point",
        "coordinates": [
          -110.333333,
          24.233333
        ]
      },
      "type": "Feature",
      "properties": {
        "hierarchy": [
          "tgn:7386001",
          "tgn:1001836",
          "tgn:1000001",
          "tgn:7005560",
          "tgn:7029392"
        ],
        "placetype": [
          "aat:300386846"
        ],
        "id": 7386001,
        "name:xx": "Prieta, Punta"
      }
    },
    {
      "geometry": {
        "type": "Point",
        "coordinates": [
          -100.6,
          24.6
        ]
      },
      "type": "Feature",
      "properties": {
        "hierarchy": [
          "tgn:7386002",
          "tgn:1000001",
          "tgn:7005589",
          "tgn:7005560",
          "tgn:7029392"
        ],
        "placetype": [
          "aat:300259572"
        ],
        "id": 7386002,
        "name:xx": "Prieta, Puerto"
      }
    },
    {
      "geometry": {
        "type": "Point",
        "coordinates": [
          -105.516667,
          28.516667
        ]
      },
      "type": "Feature",
      "properties": {
        "hierarchy": [
          "tgn:7386003",
          "tgn:7005581",
          "tgn:1000001",
          "tgn:7005560",
          "tgn:7029392"
        ],
        "placetype": [
          "aat:300008795"
        ],
        "id": 7386003,
        "name:xx": "Prieta, Loma"
      }
    },
    {
      "geometry": {
        "type": "Point",
        "coordinates": [
          -102.166667,
          28.45
        ]
      },
      "type": "Feature",
      "properties": {
        "hierarchy": [
          "tgn:7386004",
          "tgn:7005581",
          "tgn:1000001",
          "tgn:7005560",
          "tgn:7029392"
        ],
        "placetype": [
          "aat:300008795"
        ],
        "id": 7386004,
        "name:xx": "Prieta, Loma"
      }
    },
    {
      "geometry": {
        "type": "Point",
        "coordinates": [
          -102.283333,
          27.166667
        ]
      },
      "type": "Feature",
      "properties": {
        "hierarchy": [
          "tgn:7386005",
          "tgn:1001853",
          "tgn:1000001",
          "tgn:7005560",
          "tgn:7029392"
        ],
        "placetype": [
          "aat:300008777"
        ],
        "id": 7386005,
        "name:xx": "Prieta, Loma"
      }
    },
    {
      "geometry": {
        "type": "Point",
        "coordinates": [
          -98.233333,
          24.733333
        ]
      },
      "type": "Feature",
      "properties": {
        "hierarchy": [
          "tgn:7386006",
          "tgn:1000001",
          "tgn:7005597",
          "tgn:7005560",
          "tgn:7029392"
        ],
        "placetype": [
          "aat:300008777"
        ],
        "id": 7386006,
        "name:xx": "Prieta, Loma"
      }
    },
    {
      "geometry": {
        "type": "Point",
        "coordinates": [
          -114.55,
          32.3
        ]
      },
      "type": "Feature",
      "properties": {
        "hierarchy": [
          "tgn:7386007",
          "tgn:1000001",
          "tgn:1001960",
          "tgn:7005560",
          "tgn:7029392"
        ],
        "placetype": [
          "aat:300387087"
        ],
        "id": 7386007,
        "name:xx": "Prieta, Laguna"
      }
    },
    {
      "geometry": {
        "type": "Point",
        "coordinates": [
          -107.733333,
          30.366667
        ]
      },
      "type": "Feature",
      "properties": {
        "hierarchy": [
          "tgn:7386008",
          "tgn:7005581",
          "tgn:1000001",
          "tgn:7005560",
          "tgn:7029392"
        ],
        "placetype": [
          "aat:300387087"
        ],
        "id": 7386008,
        "name:xx": "Prieta, Laguna"
      }
    },
    {
      "geometry": {
        "type": "Point",
        "coordinates": [
          -97.666667,
          24.983333
        ]
      },
      "type": "Feature",
      "properties": {
        "hierarchy": [
          "tgn:7386009",
          "tgn:1000001",
          "tgn:7005597",
          "tgn:7005560",
          "tgn:7029392"
        ],
        "placetype": [
          "aat:300008791"
        ],
        "id": 7386009,
        "name:xx": "Prieta, Isla"
      }
    }
  ]
}
