{
  "geometry": {
    "type": "Point",
    "coordinates": [
      -104.3167,
      41.75
    ]
  },
  "type": "Feature",
  "properties": {
    "hierarchy": [
      "tgn:2404096",
      "tgn:1000001",
      "tgn:7012149",
      "tgn:2002372",
      "tgn:7007923",
      "tgn:7029392"
    ],
    "placetype": [
      "aat:300006191"
    ],
    "id": 2404096,
    "name:xx": "Howery Reservoir"
  }
}
