{
  "type": "FeatureCollection",
  "features": [
    {
      "geometry": {
        "type": "Point",
        "coordinates": [
          -72.7,
          -47.3
        ]
      },
      "type": "Feature",
      "properties": {
        "hierarchy": [
          "tgn:7282080",
          "tgn:1001623",
          "tgn:1000049",
          "tgn:1000002",
          "tgn:7029392"
        ],
        "placetype": [
          "aat:300008699"
        ],
        "id": 7282080,
        "name:xx": "Salto, Río del"
      }
    },
    {
      "geometry": {
        "type": "Point",
        "coordinates": [
          -72.416667,
          -41.283333
        ]
      },
      "type": "Feature",
      "properties": {
        "hierarchy": [
          "tgn:7282081",
          "tgn:1001699",
          "tgn:1000049",
          "tgn:1000002",
          "tgn:7029392"
        ],
        "placetype": [
          "aat:300008699"
        ],
        "id": 7282081,
        "name:xx": "Salto, Río del"
      }
    },
    {
      "geometry": {
        "type": "Point",
        "coordinates": [
          -73.055,
          -43.4025
        ]
      },
      "type": "Feature",
      "properties": {
        "hierarchy": [
          "tgn:7282082",
          "tgn:1001699",
          "tgn:1000049",
          "tgn:1000002",
          "tgn:7029392"
        ],
        "placetype": [
          "aat:300008699"
        ],
        "id": 7282082,
        "name:xx": "Río Salto"
      }
    },
    {
      "geometry": {
        "type": "Point",
        "coordinates": [
          -70.916667,
          -33.15
        ]
      },
      "type": "Feature",
      "properties": {
        "hierarchy": [
          "tgn:7282083",
          "tgn:1001708",
          "tgn:1000049",
          "tgn:1000002",
          "tgn:7029392"
        ],
        "placetype": [
          "aat:300266554",
          "aat:300008699"
        ],
        "id": 7282083,
        "name:xx": "Salto, Quebrada del"
      }
    },
    {
      "geometry": {
        "type": "Point",
        "coordinates": [
          -69.733333,
          -26.7
        ]
      },
      "type": "Feature",
      "properties": {
        "hierarchy": [
          "tgn:7282084",
          "tgn:1001630",
          "tgn:1000049",
          "tgn:1000002",
          "tgn:7029392"
        ],
        "placetype": [
          "aat:300266554",
          "aat:300008699"
        ],
        "id": 7282084,
        "name:xx": "Salto, Quebrada del"
      }
    },
    {
      "geometry": {
        "type": "Point",
        "coordinates": [
          -72.616667,
          -48.366667
        ]
      },
      "type": "Feature",
      "properties": {
        "hierarchy": [
          "tgn:7282085",
          "tgn:1001623",
          "tgn:1000049",
          "tgn:1000002",
          "tgn:7029392"
        ],
        "placetype": [
          "aat:300008680"
        ],
        "id": 7282085,
        "name:xx": "Salto, Lago"
      }
    },
    {
      "geometry": {
        "type": "Point",
        "coordinates": [
          -72.633333,
          -41.216667
        ]
      },
      "type": "Feature",
      "properties": {
        "hierarchy": [
          "tgn:7282086",
          "tgn:1001699",
          "tgn:1000049",
          "tgn:1000002",
          "tgn:7029392"
        ],
        "placetype": [
          "aat:300008699"
        ],
        "id": 7282086,
        "name:xx": "Salto, Estero del"
      }
    },
    {
      "geometry": {
        "type": "Point",
        "coordinates": [
          -71.366667,
          -38.483333
        ]
      },
      "type": "Feature",
      "properties": {
        "hierarchy": [
          "tgn:7282087",
          "tgn:1001692",
          "tgn:1000049",
          "tgn:1000002",
          "tgn:7029392"
        ],
        "placetype": [
          "aat:300008699"
        ],
        "id": 7282087,
        "name:xx": "Salto, Estero del"
      }
    },
    {
      "geometry": {
        "type": "Point",
        "coordinates": [
          -72.533333,
          -38.35
        ]
      },
      "type": "Feature",
      "properties": {
        "hierarchy": [
          "tgn:7282088",
          "tgn:1001692",
          "tgn:1000049",
          "tgn:1000002",
          "tgn:7029392"
        ],
        "placetype": [
          "aat:300008699"
        ],
        "id": 7282088,
        "name:xx": "Salto, Estero del"
      }
    },
    {
      "geometry": {
        "type": "Point",
        "coordinates": [
          -75.5,
          -49.733333
        ]
      },
      "type": "Feature",
      "properties": {
        "hierarchy": [
          "tgn:7282089",
          "tgn:1001702",
          "tgn:1000049",
          "tgn:1000002",
          "tgn:7029392"
        ],
        "placetype": [
          "aat:300132316"
        ],
        "id": 7282089,
        "name:xx": "Spartan, Bahía"
      }
    }
  ]
}
