{
  "geometry": {
    "type": "Point",
    "coordinates": [
      79.95,
      18.233333
    ]
  },
  "type": "Feature",
  "properties": {
    "hierarchy": [
      "tgn:7556759",
      "tgn:1001828",
      "tgn:1000004",
      "tgn:7000198",
      "tgn:7029392"
    ],
    "placetype": [
      "aat:300008680"
    ],
    "name:en": "Rāmappa Cheruvu",
    "id": 7556759
  }
}
