{
  "type": "FeatureCollection",
  "features": [
    {
      "geometry": {
        "type": "Point",
        "coordinates": [
          -72.1,
          42.1667
        ]
      },
      "type": "Feature",
      "properties": {
        "hierarchy": [
          "tgn:2779850",
          "tgn:1000001",
          "tgn:7012149",
          "tgn:1003038",
          "tgn:7007517",
          "tgn:7029392"
        ],
        "placetype": [
          "aat:300008905"
        ],
        "id": 2779850,
        "name:xx": "Wolf Swamp"
      }
    },
    {
      "geometry": {
        "type": "Point",
        "coordinates": [
          -71.6833,
          42.6833
        ]
      },
      "type": "Feature",
      "properties": {
        "hierarchy": [
          "tgn:2779851",
          "tgn:1000001",
          "tgn:1002665",
          "tgn:7012149",
          "tgn:7007517",
          "tgn:7029392"
        ],
        "placetype": [
          "aat:300008905"
        ],
        "id": 2779851,
        "name:xx": "Wolf Swamp"
      }
    },
    {
      "geometry": {
        "type": "Point",
        "coordinates": [
          -77.0333,
          34.7667
        ]
      },
      "type": "Feature",
      "properties": {
        "hierarchy": [
          "tgn:2779852",
          "tgn:1000001",
          "tgn:2001477",
          "tgn:7012149",
          "tgn:7007709",
          "tgn:7029392"
        ],
        "placetype": [
          "aat:300008699"
        ],
        "id": 2779852,
        "name:xx": "Wolf Swamp"
      }
    },
    {
      "geometry": {
        "type": "Point",
        "coordinates": [
          -77.3667,
          34.8167
        ]
      },
      "type": "Feature",
      "properties": {
        "hierarchy": [
          "tgn:2779853",
          "tgn:1000001",
          "tgn:7012149",
          "tgn:2001524",
          "tgn:7007709",
          "tgn:7029392"
        ],
        "placetype": [
          "aat:300008699"
        ],
        "id": 2779853,
        "name:xx": "Wolf Swamp"
      }
    },
    {
      "geometry": {
        "type": "Point",
        "coordinates": [
          -78.7333,
          39.8667
        ]
      },
      "type": "Feature",
      "properties": {
        "hierarchy": [
          "tgn:2779854",
          "tgn:1002172",
          "tgn:1000001",
          "tgn:7012149",
          "tgn:7007710",
          "tgn:7029392"
        ],
        "placetype": [
          "aat:300008905"
        ],
        "id": 2779854,
        "name:xx": "Wolf Swamp"
      }
    },
    {
      "geometry": {
        "type": "Point",
        "coordinates": [
          -75.0667,
          41.25
        ]
      },
      "type": "Feature",
      "properties": {
        "hierarchy": [
          "tgn:2779855",
          "tgn:1000001",
          "tgn:7012149",
          "tgn:1002789",
          "tgn:7007710",
          "tgn:7029392"
        ],
        "placetype": [
          "aat:300008905"
        ],
        "id": 2779855,
        "name:xx": "Wolf Swamp"
      }
    },
    {
      "geometry": {
        "type": "Point",
        "coordinates": [
          -76.7,
          41.6
        ]
      },
      "type": "Feature",
      "properties": {
        "hierarchy": [
          "tgn:2779856",
          "tgn:1000001",
          "tgn:1002194",
          "tgn:7012149",
          "tgn:7007710",
          "tgn:7029392"
        ],
        "placetype": [
          "aat:300008905"
        ],
        "id": 2779856,
        "name:xx": "Wolf Swamp"
      }
    },
    {
      "geometry": {
        "type": "Point",
        "coordinates": [
          -77.65,
          37.8
        ]
      },
      "type": "Feature",
      "properties": {
        "hierarchy": [
          "tgn:2779857",
          "tgn:1000001",
          "tgn:7012149",
          "tgn:1002451",
          "tgn:7007919",
          "tgn:7029392"
        ],
        "placetype": [
          "aat:300008699"
        ],
        "id": 2779857,
        "name:xx": "Wolf Swamp"
      }
    },
    {
      "geometry": {
        "type": "Point",
        "coordinates": [
          -75.3833,
          41.0333
        ]
      },
      "type": "Feature",
      "properties": {
        "hierarchy": [
          "tgn:2779858",
          "tgn:1000001",
          "tgn:7012149",
          "tgn:1002682",
          "tgn:7007710",
          "tgn:7029392"
        ],
        "placetype": [
          "aat:300008699"
        ],
        "id": 2779858,
        "name:xx": "Wolf Swamp Run"
      }
    },
    {
      "geometry": {
        "type": "Point",
        "coordinates": [
          -112.9667,
          35.1
        ]
      },
      "type": "Feature",
      "properties": {
        "hierarchy": [
          "tgn:2779859",
          "tgn:1000001",
          "tgn:7006451",
          "tgn:7012149",
          "tgn:2000103",
          "tgn:7029392"
        ],
        "placetype": [
          "aat:300006191"
        ],
        "id": 2779859,
        "name:xx": "Wolf Tank"
      }
    }
  ]
}
