{
  "geometry": {
    "type": "Point",
    "coordinates": [
      14.4667,
      49.2833
    ]
  },
  "type": "Feature",
  "properties": {
    "hierarchy": [
      "tgn:7011356",
      "tgn:7011506",
      "tgn:1000003",
      "tgn:1001780",
      "tgn:7029392"
    ],
    "placetype": [
      "aat:300008347"
    ],
    "id": 7011356,
    "name:xx": "Bechyně"
  }
}
