{
  "geometry": {
    "type": "Point",
    "coordinates": [
      -112.3167,
      46.4167
    ]
  },
  "type": "Feature",
  "properties": {
    "hierarchy": [
      "tgn:2559515",
      "tgn:1000001",
      "tgn:7012149",
      "tgn:7007524",
      "tgn:7029392"
    ],
    "placetype": [
      "aat:300008706"
    ],
    "id": 2559515,
    "name:xx": "Ontario Creek"
  }
}
