{
  "geometry": {
    "type": "Point",
    "coordinates": [
      -119.2167,
      34.1167
    ]
  },
  "type": "Feature",
  "properties": {
    "hierarchy": [
      "tgn:2405148",
      "tgn:1000001",
      "tgn:7012149",
      "tgn:7007157",
      "tgn:1002972",
      "tgn:7029392"
    ],
    "placetype": [
      "aat:300132348"
    ],
    "id": 2405148,
    "name:xx": "Hueneme Canyon"
  }
}
