{
  "geometry": {
    "type": "Point",
    "coordinates": [
      -122.9333,
      42.0167
    ]
  },
  "type": "Feature",
  "properties": {
    "hierarchy": [
      "tgn:2785354",
      "tgn:1000001",
      "tgn:7012149",
      "tgn:2001711",
      "tgn:7007708",
      "tgn:7029392"
    ],
    "placetype": [
      "aat:300008798"
    ],
    "id": 2785354,
    "name:xx": "Yellowjacket Mountain"
  }
}
