{
  "geometry": {
    "type": "Point",
    "coordinates": [
      127.1167,
      43.3333
    ]
  },
  "type": "Feature",
  "properties": {
    "hierarchy": [
      "tgn:1118195",
      "tgn:1000004",
      "tgn:7002372",
      "tgn:1000111",
      "tgn:7029392"
    ],
    "placetype": [
      "aat:300008680"
    ],
    "id": 1118195,
    "name:xx": "Songhuahu"
  }
}
