{
  "geometry": {
    "type": "Point",
    "coordinates": [
      88.309644,
      22.87698
    ]
  },
  "type": "Feature",
  "properties": {
    "hierarchy": [
      "tgn:7574536",
      "tgn:1000004",
      "tgn:7000198",
      "tgn:1001977",
      "tgn:7029392"
    ],
    "placetype": [
      "aat:300008699"
    ],
    "name:en": "Kunti Nadī",
    "id": 7574536
  }
}
