{
  "geometry": {
    "type": "Point",
    "coordinates": [
      -83.0167,
      35.7667
    ]
  },
  "type": "Feature",
  "properties": {
    "hierarchy": [
      "tgn:2367408",
      "tgn:1000001",
      "tgn:7012149",
      "tgn:2001503",
      "tgn:7007709",
      "tgn:7029392"
    ],
    "placetype": [
      "aat:300008706"
    ],
    "id": 2367408,
    "name:xx": "Groundhog Creek"
  }
}
