{
  "geometry": {
    "type": "Point",
    "coordinates": [
      -76.5333,
      39.3833
    ]
  },
  "type": "Feature",
  "properties": {
    "hierarchy": [
      "tgn:1135052",
      "tgn:7016099",
      "tgn:1000001",
      "tgn:7012149",
      "tgn:7007516",
      "tgn:7029392"
    ],
    "placetype": [
      "aat:300008706"
    ],
    "id": 1135052,
    "name:xx": "Whitemarsh Run"
  }
}
