{
  "type": "FeatureCollection",
  "features": [
    {
      "geometry": {
        "type": "Point",
        "coordinates": [
          12.566667,
          51.216667
        ]
      },
      "type": "Feature",
      "properties": {
        "hierarchy": [
          "tgn:7112050",
          "tgn:1000003",
          "tgn:7003685",
          "tgn:7000084",
          "tgn:7029392"
        ],
        "placetype": [
          "aat:300008347"
        ],
        "id": 7112050,
        "name:xx": "Rohrbach"
      }
    },
    {
      "geometry": {
        "type": "Point",
        "coordinates": [
          11.4,
          51.066667
        ]
      },
      "type": "Feature",
      "properties": {
        "hierarchy": [
          "tgn:7112051",
          "tgn:1000003",
          "tgn:7003689",
          "tgn:7000084",
          "tgn:7029392"
        ],
        "placetype": [
          "aat:300008347"
        ],
        "id": 7112051,
        "name:xx": "Rohrbach"
      }
    },
    {
      "geometry": {
        "type": "Point",
        "coordinates": [
          9.7,
          50.916667
        ]
      },
      "type": "Feature",
      "properties": {
        "hierarchy": [
          "tgn:7112052",
          "tgn:1000003",
          "tgn:7003678",
          "tgn:7000084",
          "tgn:7029392"
        ],
        "placetype": [
          "aat:300008347"
        ],
        "id": 7112052,
        "name:xx": "Rohrbach"
      }
    },
    {
      "geometry": {
        "type": "Point",
        "coordinates": [
          11.216667,
          50.6
        ]
      },
      "type": "Feature",
      "properties": {
        "hierarchy": [
          "tgn:7112053",
          "tgn:1000003",
          "tgn:7003689",
          "tgn:7000084",
          "tgn:7029392"
        ],
        "placetype": [
          "aat:300008347"
        ],
        "id": 7112053,
        "name:xx": "Rohrbach"
      }
    },
    {
      "geometry": {
        "type": "Point",
        "coordinates": [
          9.05,
          50.316667
        ]
      },
      "type": "Feature",
      "properties": {
        "hierarchy": [
          "tgn:7112054",
          "tgn:1000003",
          "tgn:7003678",
          "tgn:7000084",
          "tgn:7029392"
        ],
        "placetype": [
          "aat:300008347"
        ],
        "id": 7112054,
        "name:xx": "Rohrbach"
      }
    },
    {
      "geometry": {
        "type": "Point",
        "coordinates": [
          11.033333,
          50.25
        ]
      },
      "type": "Feature",
      "properties": {
        "hierarchy": [
          "tgn:7112055",
          "tgn:7003669",
          "tgn:1000003",
          "tgn:7000084",
          "tgn:7029392"
        ],
        "placetype": [
          "aat:300008347"
        ],
        "id": 7112055,
        "name:xx": "Rohrbach"
      }
    },
    {
      "geometry": {
        "type": "Point",
        "coordinates": [
          9.699167,
          49.969167
        ]
      },
      "type": "Feature",
      "properties": {
        "hierarchy": [
          "tgn:7112056",
          "tgn:7003669",
          "tgn:1000003",
          "tgn:7000084",
          "tgn:7029392"
        ],
        "placetype": [
          "aat:300008347"
        ],
        "id": 7112056,
        "name:xx": "Rohrbach"
      }
    },
    {
      "geometry": {
        "type": "Point",
        "coordinates": [
          6.35,
          49.9
        ]
      },
      "type": "Feature",
      "properties": {
        "hierarchy": [
          "tgn:7112057",
          "tgn:1000003",
          "tgn:7003682",
          "tgn:7000084",
          "tgn:7029392"
        ],
        "placetype": [
          "aat:300008347"
        ],
        "id": 7112057,
        "name:xx": "Rohrbach"
      }
    },
    {
      "geometry": {
        "type": "Point",
        "coordinates": [
          7.416667,
          49.883333
        ]
      },
      "type": "Feature",
      "properties": {
        "hierarchy": [
          "tgn:7112058",
          "tgn:1000003",
          "tgn:7003682",
          "tgn:7000084",
          "tgn:7029392"
        ],
        "placetype": [
          "aat:300008347"
        ],
        "id": 7112058,
        "name:xx": "Rohrbach"
      }
    },
    {
      "geometry": {
        "type": "Point",
        "coordinates": [
          8.763889,
          49.8
        ]
      },
      "type": "Feature",
      "properties": {
        "hierarchy": [
          "tgn:7112059",
          "tgn:1000003",
          "tgn:7003678",
          "tgn:7000084",
          "tgn:7029392"
        ],
        "placetype": [
          "aat:300008347"
        ],
        "id": 7112059,
        "name:xx": "Rohrbach"
      }
    }
  ]
}
