{
  "geometry": {
    "type": "Point",
    "coordinates": [
      79.157678,
      26.92436
    ]
  },
  "type": "Feature",
  "properties": {
    "hierarchy": [
      "tgn:7561194",
      "tgn:1000004",
      "tgn:7000198",
      "tgn:7016722",
      "tgn:7029392"
    ],
    "placetype": [
      "aat:300008347"
    ],
    "name:en": "Bhojpur Ramāin",
    "id": 7561194
  }
}
