{
  "geometry": {
    "type": "Point",
    "coordinates": [
      27.0167,
      47.75
    ]
  },
  "type": "Feature",
  "properties": {
    "hierarchy": [
      "tgn:1050312",
      "tgn:1000349",
      "tgn:1000003",
      "tgn:1000091",
      "tgn:7029392"
    ],
    "placetype": [
      "aat:300008347"
    ],
    "id": 1050312,
    "name:xx": "Trușești"
  }
}
