{
  "geometry": {
    "type": "Point",
    "coordinates": [
      -72.8167,
      44.35
    ]
  },
  "type": "Feature",
  "properties": {
    "hierarchy": [
      "tgn:2109864",
      "tgn:1000001",
      "tgn:2002135",
      "tgn:7012149",
      "tgn:7007828",
      "tgn:7029392"
    ],
    "placetype": [
      "aat:300008347",
      "aat:300387210"
    ],
    "id": 2109864,
    "name:xx": "North Duxbury"
  }
}
