{
  "geometry": {
    "type": "Point",
    "coordinates": [
      100.45,
      26.8333
    ]
  },
  "type": "Feature",
  "properties": {
    "hierarchy": [
      "tgn:1074200",
      "tgn:1000004",
      "tgn:7018118",
      "tgn:1000111",
      "tgn:7029392"
    ],
    "placetype": [
      "aat:300008347"
    ],
    "id": 1074200,
    "name:xx": "Zili"
  }
}
