{
  "geometry": {
    "type": "Point",
    "coordinates": [
      -0.6667,
      45.05
    ]
  },
  "type": "Feature",
  "properties": {
    "hierarchy": [
      "tgn:4006908",
      "tgn:7002878",
      "tgn:1000003",
      "tgn:1000070",
      "tgn:7029392"
    ],
    "placetype": [
      "aat:300008347"
    ],
    "id": 4006908,
    "name:xx": "Margaux"
  }
}
