{
  "geometry": {
    "type": "Point",
    "coordinates": [
      -112.6833,
      42.55
    ]
  },
  "type": "Feature",
  "properties": {
    "hierarchy": [
      "tgn:2741055",
      "tgn:1000001",
      "tgn:7012149",
      "tgn:2000490",
      "tgn:7007250",
      "tgn:7029392"
    ],
    "placetype": [
      "aat:300006191"
    ],
    "id": 2741055,
    "name:xx": "Upper Stump Canyon Reservoir"
  }
}
