{
  "geometry": {
    "type": "Point",
    "coordinates": [
      35.5833,
      33.5667
    ]
  },
  "type": "Feature",
  "properties": {
    "hierarchy": [
      "tgn:1082612",
      "tgn:1001084",
      "tgn:1000004",
      "tgn:1000126",
      "tgn:7029392"
    ],
    "placetype": [
      "aat:300008347"
    ],
    "id": 1082612,
    "name:xx": "Bkāsīn"
  }
}
