{
  "geometry": {
    "type": "Point",
    "coordinates": [
      28.8333,
      -1.4167
    ]
  },
  "type": "Feature",
  "properties": {
    "hierarchy": [
      "tgn:1089317",
      "tgn:7001242",
      "tgn:7016707",
      "tgn:1000159",
      "tgn:7029392"
    ],
    "placetype": [
      "aat:300008347"
    ],
    "id": 1089317,
    "name:xx": "Masisi"
  }
}
