{
  "geometry": {
    "type": "Point",
    "coordinates": [
      -87.3167,
      38.6333
    ]
  },
  "type": "Feature",
  "properties": {
    "hierarchy": [
      "tgn:2435630",
      "tgn:1000001",
      "tgn:7012149",
      "tgn:2000545",
      "tgn:7007252",
      "tgn:7029392"
    ],
    "placetype": [
      "aat:300006075"
    ],
    "id": 2435630,
    "name:xx": "Kessinger Ditch"
  }
}
