{
  "geometry": {
    "type": "Point",
    "coordinates": [
      -116.9333,
      43.0333
    ]
  },
  "type": "Feature",
  "properties": {
    "hierarchy": [
      "tgn:2708173",
      "tgn:1000001",
      "tgn:7012149",
      "tgn:2000488",
      "tgn:7007250",
      "tgn:7029392"
    ],
    "placetype": [
      "aat:300266640"
    ],
    "id": 2708173,
    "name:xx": "Swisher Ridge"
  }
}
