{
  "geometry": {
    "type": "Point",
    "coordinates": [
      32.052119,
      28.978627
    ]
  },
  "type": "Feature",
  "properties": {
    "hierarchy": [
      "tgn:7534486",
      "tgn:7001242",
      "tgn:7016833",
      "tgn:1001110",
      "tgn:7029392"
    ],
    "placetype": [
      "aat:300379998"
    ],
    "name:en": "Mijallī, Wādī",
    "id": 7534486
  }
}
