{
  "geometry": {
    "type": "Point",
    "coordinates": [
      -73.3167,
      44.2167
    ]
  },
  "type": "Feature",
  "properties": {
    "hierarchy": [
      "tgn:2594127",
      "tgn:2002130",
      "tgn:1000001",
      "tgn:7012149",
      "tgn:7007828",
      "tgn:7029392"
    ],
    "placetype": [
      "aat:300132316"
    ],
    "id": 2594127,
    "name:xx": "Porter Bay"
  }
}
