{
  "geometry": {
    "type": "Point",
    "coordinates": [
      -87.001,
      12.705
    ]
  },
  "type": "Feature",
  "properties": {
    "hierarchy": [
      "tgn:1107739",
      "tgn:1000566",
      "tgn:1000001",
      "tgn:7005562",
      "tgn:7029392"
    ],
    "placetype": [
      "aat:300132325"
    ],
    "id": 1107739,
    "name:xx": "San Cristóbal, Volcán"
  }
}
