{
  "geometry": {
    "type": "Point",
    "coordinates": [
      22.474,
      58.982
    ]
  },
  "type": "Feature",
  "properties": {
    "hierarchy": [
      "tgn:1054813",
      "tgn:7006625",
      "tgn:7006632",
      "tgn:1000003",
      "tgn:7006540",
      "tgn:7029392"
    ],
    "placetype": [
      "aat:300008347"
    ],
    "id": 1054813,
    "name:xx": "Kõrgessaare"
  }
}
