{
  "geometry": {
    "type": "Point",
    "coordinates": [
      -133.75,
      59.3333
    ]
  },
  "type": "Feature",
  "properties": {
    "hierarchy": [
      "tgn:1115477",
      "tgn:7005685",
      "tgn:1000001",
      "tgn:7029392"
    ],
    "placetype": [
      "aat:300008680"
    ],
    "id": 1115477,
    "name:xx": "Atlin Lake"
  }
}
