{
  "type": "FeatureCollection",
  "features": [
    {
      "geometry": {
        "type": "Point",
        "coordinates": [
          -99.233333,
          19.5
        ]
      },
      "type": "Feature",
      "properties": {
        "hierarchy": [
          "tgn:7373050",
          "tgn:1000001",
          "tgn:1001893",
          "tgn:7005560",
          "tgn:7029392"
        ],
        "placetype": [
          "aat:300000745"
        ],
        "id": 7373050,
        "name:xx": "La Florida"
      }
    },
    {
      "geometry": {
        "type": "Point",
        "coordinates": [
          -98.466667,
          25.983333
        ]
      },
      "type": "Feature",
      "properties": {
        "hierarchy": [
          "tgn:7373051",
          "tgn:1000001",
          "tgn:7005597",
          "tgn:7005560",
          "tgn:7029392"
        ],
        "placetype": [
          "aat:300008347"
        ],
        "id": 7373051,
        "name:xx": "La Florida"
      }
    },
    {
      "geometry": {
        "type": "Point",
        "coordinates": [
          -109.2,
          25.933333
        ]
      },
      "type": "Feature",
      "properties": {
        "hierarchy": [
          "tgn:7373052",
          "tgn:1000001",
          "tgn:7005595",
          "tgn:7005560",
          "tgn:7029392"
        ],
        "placetype": [
          "aat:300008347"
        ],
        "id": 7373052,
        "name:xx": "La Florida"
      }
    },
    {
      "geometry": {
        "type": "Point",
        "coordinates": [
          -108.566667,
          25.633333
        ]
      },
      "type": "Feature",
      "properties": {
        "hierarchy": [
          "tgn:7373053",
          "tgn:1000001",
          "tgn:7005595",
          "tgn:7005560",
          "tgn:7029392"
        ],
        "placetype": [
          "aat:300008347"
        ],
        "id": 7373053,
        "name:xx": "La Florida"
      }
    },
    {
      "geometry": {
        "type": "Point",
        "coordinates": [
          -97.616667,
          25.616667
        ]
      },
      "type": "Feature",
      "properties": {
        "hierarchy": [
          "tgn:7373054",
          "tgn:1000001",
          "tgn:7005597",
          "tgn:7005560",
          "tgn:7029392"
        ],
        "placetype": [
          "aat:300008347"
        ],
        "id": 7373054,
        "name:xx": "La Florida"
      }
    },
    {
      "geometry": {
        "type": "Point",
        "coordinates": [
          -108.466667,
          25.583333
        ]
      },
      "type": "Feature",
      "properties": {
        "hierarchy": [
          "tgn:7373055",
          "tgn:1000001",
          "tgn:7005595",
          "tgn:7005560",
          "tgn:7029392"
        ],
        "placetype": [
          "aat:300008347"
        ],
        "id": 7373055,
        "name:xx": "La Florida"
      }
    },
    {
      "geometry": {
        "type": "Point",
        "coordinates": [
          -99.933333,
          25.466667
        ]
      },
      "type": "Feature",
      "properties": {
        "hierarchy": [
          "tgn:7373056",
          "tgn:1000001",
          "tgn:7005589",
          "tgn:7005560",
          "tgn:7029392"
        ],
        "placetype": [
          "aat:300008347"
        ],
        "id": 7373056,
        "name:xx": "La Florida"
      }
    },
    {
      "geometry": {
        "type": "Point",
        "coordinates": [
          -99.433333,
          18.766667
        ]
      },
      "type": "Feature",
      "properties": {
        "hierarchy": [
          "tgn:7373057",
          "tgn:1000001",
          "tgn:7005588",
          "tgn:7005560",
          "tgn:7029392"
        ],
        "placetype": [
          "aat:300008347"
        ],
        "id": 7373057,
        "name:xx": "La Chía"
      }
    },
    {
      "geometry": {
        "type": "Point",
        "coordinates": [
          -100.866667,
          26.55
        ]
      },
      "type": "Feature",
      "properties": {
        "hierarchy": [
          "tgn:7373058",
          "tgn:1000001",
          "tgn:7005589",
          "tgn:7005560",
          "tgn:7029392"
        ],
        "placetype": [
          "aat:300000241"
        ],
        "id": 7373058,
        "name:xx": "Rancho La Chena"
      }
    },
    {
      "geometry": {
        "type": "Point",
        "coordinates": [
          -101.85,
          26.65
        ]
      },
      "type": "Feature",
      "properties": {
        "hierarchy": [
          "tgn:7373059",
          "tgn:7005581",
          "tgn:1000001",
          "tgn:7005560",
          "tgn:7029392"
        ],
        "placetype": [
          "aat:300008347"
        ],
        "id": 7373059,
        "name:xx": "La Chata"
      }
    }
  ]
}
