{
  "type": "FeatureCollection",
  "features": [
    {
      "geometry": {
        "type": "Point",
        "coordinates": [
          -74.85,
          41.2667
        ]
      },
      "type": "Feature",
      "properties": {
        "hierarchy": [
          "tgn:2296390",
          "tgn:1000001",
          "tgn:7012149",
          "tgn:1002789",
          "tgn:7007710",
          "tgn:7029392"
        ],
        "placetype": [
          "aat:300008699"
        ],
        "id": 2296390,
        "name:xx": "Dry Brook"
      }
    },
    {
      "geometry": {
        "type": "Point",
        "coordinates": [
          -78.8167,
          41.9333
        ]
      },
      "type": "Feature",
      "properties": {
        "hierarchy": [
          "tgn:2296391",
          "tgn:1000001",
          "tgn:7012149",
          "tgn:7016020",
          "tgn:7007710",
          "tgn:7029392"
        ],
        "placetype": [
          "aat:300008699"
        ],
        "id": 2296391,
        "name:xx": "Dry Brook"
      }
    },
    {
      "geometry": {
        "type": "Point",
        "coordinates": [
          -71.5333,
          41.8167
        ]
      },
      "type": "Feature",
      "properties": {
        "hierarchy": [
          "tgn:2296392",
          "tgn:1002808",
          "tgn:1000001",
          "tgn:7012149",
          "tgn:7007711",
          "tgn:7029392"
        ],
        "placetype": [
          "aat:300008699"
        ],
        "id": 2296392,
        "name:xx": "Dry Brook"
      }
    },
    {
      "geometry": {
        "type": "Point",
        "coordinates": [
          -73.2,
          43.05
        ]
      },
      "type": "Feature",
      "properties": {
        "hierarchy": [
          "tgn:2296393",
          "tgn:1002176",
          "tgn:1000001",
          "tgn:7012149",
          "tgn:7007828",
          "tgn:7029392"
        ],
        "placetype": [
          "aat:300008699"
        ],
        "id": 2296393,
        "name:xx": "Dry Brook"
      }
    },
    {
      "geometry": {
        "type": "Point",
        "coordinates": [
          -73.2,
          43.35
        ]
      },
      "type": "Feature",
      "properties": {
        "hierarchy": [
          "tgn:2296394",
          "tgn:1000001",
          "tgn:1002840",
          "tgn:7012149",
          "tgn:7007828",
          "tgn:7029392"
        ],
        "placetype": [
          "aat:300008699"
        ],
        "id": 2296394,
        "name:xx": "Dry Brook"
      }
    },
    {
      "geometry": {
        "type": "Point",
        "coordinates": [
          -72.5833,
          42.2667
        ]
      },
      "type": "Feature",
      "properties": {
        "hierarchy": [
          "tgn:2296395",
          "tgn:1000001",
          "tgn:7013686",
          "tgn:7012149",
          "tgn:7007517",
          "tgn:7029392"
        ],
        "placetype": [
          "aat:300008798"
        ],
        "id": 2296395,
        "name:xx": "Dry Brook Hill"
      }
    },
    {
      "geometry": {
        "type": "Point",
        "coordinates": [
          -73.2,
          43.05
        ]
      },
      "type": "Feature",
      "properties": {
        "hierarchy": [
          "tgn:2296396",
          "tgn:1002176",
          "tgn:1000001",
          "tgn:7012149",
          "tgn:7007828",
          "tgn:7029392"
        ],
        "placetype": [
          "aat:300008761"
        ],
        "id": 2296396,
        "name:xx": "Dry Brook Hollow"
      }
    },
    {
      "geometry": {
        "type": "Point",
        "coordinates": [
          -74.5833,
          42.1
        ]
      },
      "type": "Feature",
      "properties": {
        "hierarchy": [
          "tgn:2296397",
          "tgn:1000001",
          "tgn:1002328",
          "tgn:7012149",
          "tgn:7007568",
          "tgn:7029392"
        ],
        "placetype": [
          "aat:300266640"
        ],
        "id": 2296397,
        "name:xx": "Dry Brook Ridge"
      }
    },
    {
      "geometry": {
        "type": "Point",
        "coordinates": [
          -97.35,
          30.4
        ]
      },
      "type": "Feature",
      "properties": {
        "hierarchy": [
          "tgn:2296398",
          "tgn:1000001",
          "tgn:7012149",
          "tgn:7007826",
          "tgn:7029392"
        ],
        "placetype": [
          "aat:300008706"
        ],
        "id": 2296398,
        "name:xx": "Dry Brushy Creek"
      }
    },
    {
      "geometry": {
        "type": "Point",
        "coordinates": [
          -97.0833,
          30.6
        ]
      },
      "type": "Feature",
      "properties": {
        "hierarchy": [
          "tgn:2296399",
          "tgn:1000001",
          "tgn:7012149",
          "tgn:1002670",
          "tgn:7007826",
          "tgn:7029392"
        ],
        "placetype": [
          "aat:300008706"
        ],
        "id": 2296399,
        "name:xx": "Dry Brushy Creek"
      }
    }
  ]
}
