{
  "geometry": {
    "type": "Point",
    "coordinates": [
      -97.4167,
      33.5833
    ]
  },
  "type": "Feature",
  "properties": {
    "hierarchy": [
      "tgn:2772685",
      "tgn:1000001",
      "tgn:7012149",
      "tgn:2001964",
      "tgn:7007826",
      "tgn:7029392"
    ],
    "placetype": [
      "aat:300008706"
    ],
    "id": 2772685,
    "name:xx": "Williams Creek"
  }
}
