{
  "geometry": {
    "type": "Point",
    "coordinates": [
      -113.4833,
      35.65
    ]
  },
  "type": "Feature",
  "properties": {
    "hierarchy": [
      "tgn:2471605",
      "tgn:1000001",
      "tgn:7006451",
      "tgn:7012149",
      "tgn:2000098",
      "tgn:7029392"
    ],
    "placetype": [
      "aat:300008706"
    ],
    "id": 2471605,
    "name:xx": "Lost Man Creek"
  }
}
