{
  "geometry": {
    "type": "Point",
    "coordinates": [
      75.275696,
      28.245901
    ]
  },
  "type": "Feature",
  "properties": {
    "hierarchy": [
      "tgn:7584349",
      "tgn:1000004",
      "tgn:7000198",
      "tgn:7016788",
      "tgn:7029392"
    ],
    "placetype": [
      "aat:300008347"
    ],
    "name:en": "Gy훮n훮r훮m ki Dh훮ni",
    "id": 7584349
  }
}
