{
  "geometry": {
    "type": "Point",
    "coordinates": [
      -80.4167,
      37.2167
    ]
  },
  "type": "Feature",
  "properties": {
    "hierarchy": [
      "tgn:2114880",
      "tgn:1000001",
      "tgn:7012149",
      "tgn:2002174",
      "tgn:7007919",
      "tgn:7029392"
    ],
    "placetype": [
      "aat:300132384"
    ],
    "id": 2114880,
    "name:xx": "Virginia Polytechnic Institute"
  }
}
