{
  "geometry": {
    "type": "Point",
    "coordinates": [
      -100.55,
      39.9667
    ]
  },
  "type": "Feature",
  "properties": {
    "hierarchy": [
      "tgn:2036167",
      "tgn:1000001",
      "tgn:2000679",
      "tgn:7012149",
      "tgn:7007254",
      "tgn:7029392"
    ],
    "placetype": [
      "aat:300008347"
    ],
    "id": 2036167,
    "name:xx": "Cedar Bluffs"
  }
}
