{
  "geometry": {
    "type": "Point",
    "coordinates": [
      99.8333,
      2.2667
    ]
  },
  "type": "Feature",
  "properties": {
    "hierarchy": [
      "tgn:1140246",
      "tgn:1000004",
      "tgn:1001555",
      "tgn:1000116",
      "tgn:7029392"
    ],
    "placetype": [
      "aat:300008347"
    ],
    "id": 1140246,
    "name:xx": "Merbau"
  }
}
