{
  "geometry": {
    "type": "Point",
    "coordinates": [
      -67.6667,
      44.4667
    ]
  },
  "type": "Feature",
  "properties": {
    "hierarchy": [
      "tgn:2413154",
      "tgn:1000001",
      "tgn:7012149",
      "tgn:7014589",
      "tgn:7007515",
      "tgn:7029392"
    ],
    "placetype": [
      "aat:300008791"
    ],
    "id": 2413154,
    "name:xx": "Inner Sand Island"
  }
}
