{
  "type": "FeatureCollection",
  "features": [
    {
      "geometry": {
        "type": "Point",
        "coordinates": [
          -82.9,
          42.75
        ]
      },
      "type": "Feature",
      "properties": {
        "hierarchy": [
          "tgn:2053112",
          "tgn:1000001",
          "tgn:7012149",
          "tgn:1002617",
          "tgn:7007520",
          "tgn:7029392"
        ],
        "placetype": [
          "aat:300008347"
        ],
        "id": 2053112,
        "name:xx": "Ray Center"
      }
    },
    {
      "geometry": {
        "type": "Point",
        "coordinates": [
          -85.5667,
          44.0167
        ]
      },
      "type": "Feature",
      "properties": {
        "hierarchy": [
          "tgn:2053113",
          "tgn:1000001",
          "tgn:7012149",
          "tgn:2000970",
          "tgn:7007520",
          "tgn:7029392"
        ],
        "placetype": [
          "aat:300008347",
          "aat:300387210"
        ],
        "id": 2053113,
        "name:xx": "Raymond Corners"
      }
    },
    {
      "geometry": {
        "type": "Point",
        "coordinates": [
          -84.7333,
          41.8333
        ]
      },
      "type": "Feature",
      "properties": {
        "hierarchy": [
          "tgn:2053115",
          "tgn:1000001",
          "tgn:7012149",
          "tgn:1002481",
          "tgn:7007520",
          "tgn:7029392"
        ],
        "placetype": [
          "aat:300008347"
        ],
        "id": 2053115,
        "name:xx": "Reading"
      }
    }
  ]
}
