{
  "type": "FeatureCollection",
  "features": [
    {
      "geometry": {
        "type": "Point",
        "coordinates": [
          -91.3,
          30.7833
        ]
      },
      "type": "Feature",
      "properties": {
        "hierarchy": [
          "tgn:2484470",
          "tgn:1000001",
          "tgn:7012149",
          "tgn:2000916",
          "tgn:7007256",
          "tgn:7029392"
        ],
        "placetype": [
          "aat:300008699"
        ],
        "id": 2484470,
        "name:xx": "Laurel Fork"
      }
    },
    {
      "geometry": {
        "type": "Point",
        "coordinates": [
          -82.85,
          35.2667
        ]
      },
      "type": "Feature",
      "properties": {
        "hierarchy": [
          "tgn:2484471",
          "tgn:1000001",
          "tgn:7012149",
          "tgn:2001544",
          "tgn:7007709",
          "tgn:7029392"
        ],
        "placetype": [
          "aat:300008699"
        ],
        "id": 2484471,
        "name:xx": "Laurel Fork"
      }
    },
    {
      "geometry": {
        "type": "Point",
        "coordinates": [
          -82.4333,
          35.6833
        ]
      },
      "type": "Feature",
      "properties": {
        "hierarchy": [
          "tgn:2484472",
          "tgn:1000001",
          "tgn:2001473",
          "tgn:7012149",
          "tgn:7007709",
          "tgn:7029392"
        ],
        "placetype": [
          "aat:300008699"
        ],
        "id": 2484472,
        "name:xx": "Laurel Fork"
      }
    },
    {
      "geometry": {
        "type": "Point",
        "coordinates": [
          -81.6167,
          36.0167
        ]
      },
      "type": "Feature",
      "properties": {
        "hierarchy": [
          "tgn:2484473",
          "tgn:1000001",
          "tgn:2001476",
          "tgn:7012149",
          "tgn:7007709",
          "tgn:7029392"
        ],
        "placetype": [
          "aat:300008699"
        ],
        "id": 2484473,
        "name:xx": "Laurel Fork"
      }
    },
    {
      "geometry": {
        "type": "Point",
        "coordinates": [
          -81.7167,
          36.1833
        ]
      },
      "type": "Feature",
      "properties": {
        "hierarchy": [
          "tgn:2484474",
          "tgn:1000001",
          "tgn:7012149",
          "tgn:2001551",
          "tgn:7007709",
          "tgn:7029392"
        ],
        "placetype": [
          "aat:300008699"
        ],
        "id": 2484474,
        "name:xx": "Laurel Fork"
      }
    },
    {
      "geometry": {
        "type": "Point",
        "coordinates": [
          -81.2333,
          36.3667
        ]
      },
      "type": "Feature",
      "properties": {
        "hierarchy": [
          "tgn:2484475",
          "tgn:1000001",
          "tgn:7012149",
          "tgn:7007709",
          "tgn:7029392"
        ],
        "placetype": [
          "aat:300008699"
        ],
        "id": 2484475,
        "name:xx": "Laurel Fork"
      }
    },
    {
      "geometry": {
        "type": "Point",
        "coordinates": [
          -82.65,
          38.8667
        ]
      },
      "type": "Feature",
      "properties": {
        "hierarchy": [
          "tgn:2484476",
          "tgn:1000001",
          "tgn:7012149",
          "tgn:2001614",
          "tgn:7007706",
          "tgn:7029392"
        ],
        "placetype": [
          "aat:300008699"
        ],
        "id": 2484476,
        "name:xx": "Laurel Fork"
      }
    },
    {
      "geometry": {
        "type": "Point",
        "coordinates": [
          -83.2333,
          38.8833
        ]
      },
      "type": "Feature",
      "properties": {
        "hierarchy": [
          "tgn:2484477",
          "tgn:1000001",
          "tgn:7012149",
          "tgn:1002877",
          "tgn:7007706",
          "tgn:7029392"
        ],
        "placetype": [
          "aat:300008699"
        ],
        "id": 2484477,
        "name:xx": "Laurel Fork"
      }
    },
    {
      "geometry": {
        "type": "Point",
        "coordinates": [
          -78.1833,
          40.1
        ]
      },
      "type": "Feature",
      "properties": {
        "hierarchy": [
          "tgn:2484478",
          "tgn:1000001",
          "tgn:7012149",
          "tgn:7007710",
          "tgn:7029392"
        ],
        "placetype": [
          "aat:300008699"
        ],
        "id": 2484478,
        "name:xx": "Laurel Fork"
      }
    },
    {
      "geometry": {
        "type": "Point",
        "coordinates": [
          -77.6,
          41.4333
        ]
      },
      "type": "Feature",
      "properties": {
        "hierarchy": [
          "tgn:2484479",
          "tgn:1000001",
          "tgn:1002286",
          "tgn:7012149",
          "tgn:7007710",
          "tgn:7029392"
        ],
        "placetype": [
          "aat:300008699"
        ],
        "id": 2484479,
        "name:xx": "Laurel Fork"
      }
    }
  ]
}
