{
  "geometry": {
    "type": "Point",
    "coordinates": [
      -83.05,
      37.5833
    ]
  },
  "type": "Feature",
  "properties": {
    "hierarchy": [
      "tgn:2592891",
      "tgn:1000001",
      "tgn:2000772",
      "tgn:7012149",
      "tgn:7007255",
      "tgn:7029392"
    ],
    "placetype": [
      "aat:300008699"
    ],
    "id": 2592891,
    "name:xx": "Poplar Branch"
  }
}
