{
  "geometry": {
    "type": "Point",
    "coordinates": [
      -83.6333,
      40.45
    ]
  },
  "type": "Feature",
  "properties": {
    "hierarchy": [
      "tgn:1133859",
      "tgn:1000001",
      "tgn:7012149",
      "tgn:7007706",
      "tgn:7029392"
    ],
    "placetype": [
      "aat:300008706"
    ],
    "id": 1133859,
    "name:xx": "Mill Creek"
  }
}
