{
  "geometry": {
    "type": "Point",
    "coordinates": [
      -164.25,
      65.3333
    ]
  },
  "type": "Feature",
  "properties": {
    "hierarchy": [
      "tgn:2653714",
      "tgn:7006450",
      "tgn:1000001",
      "tgn:7012149",
      "tgn:7029392"
    ],
    "placetype": [
      "aat:300008850"
    ],
    "id": 2653714,
    "name:xx": "Seward Peninsula"
  }
}
