{
  "geometry": {
    "type": "Point",
    "coordinates": [
      -91.1667,
      33.9833
    ]
  },
  "type": "Feature",
  "properties": {
    "hierarchy": [
      "tgn:2443666",
      "tgn:2000105",
      "tgn:1000001",
      "tgn:7016172",
      "tgn:7012149",
      "tgn:7029392"
    ],
    "placetype": [
      "aat:300008905"
    ],
    "id": 2443666,
    "name:xx": "La Grues Lake"
  }
}
