{
  "geometry": {
    "type": "Point",
    "coordinates": [
      -120.1167,
      48.9833
    ]
  },
  "type": "Feature",
  "properties": {
    "hierarchy": [
      "tgn:2780124",
      "tgn:1000001",
      "tgn:7012149",
      "tgn:1002742",
      "tgn:7007920",
      "tgn:7029392"
    ],
    "placetype": [
      "aat:300008798"
    ],
    "id": 2780124,
    "name:xx": "Wolframite Mountain"
  }
}
