{
  "geometry": {
    "type": "Point",
    "coordinates": [
      -75.8667,
      38.6167
    ]
  },
  "type": "Feature",
  "properties": {
    "hierarchy": [
      "tgn:2213252",
      "tgn:1002338",
      "tgn:1000001",
      "tgn:7012149",
      "tgn:7007516",
      "tgn:7029392"
    ],
    "placetype": [
      "aat:300008706"
    ],
    "id": 2213252,
    "name:xx": "Cabin Creek"
  }
}
