{
  "geometry": {
    "type": "Point",
    "coordinates": [
      -93.091667,
      17.95
    ]
  },
  "type": "Feature",
  "properties": {
    "hierarchy": [
      "tgn:7412093",
      "tgn:1000001",
      "tgn:7005596",
      "tgn:7005560",
      "tgn:7029392"
    ],
    "placetype": [
      "aat:300008347"
    ],
    "id": 7412093,
    "name:es": "Buenavista Río Nuevo Cuarta Sección"
  }
}
