{
  "geometry": {
    "type": "Point",
    "coordinates": [
      7.55,
      47.55
    ]
  },
  "type": "Feature",
  "properties": {
    "hierarchy": [
      "tgn:1063888",
      "tgn:7003740",
      "tgn:1000003",
      "tgn:7011731",
      "tgn:7029392"
    ],
    "placetype": [
      "aat:300008347"
    ],
    "id": 1063888,
    "name:xx": "Allschwil"
  }
}
