{
  "type": "FeatureCollection",
  "features": [
    {
      "geometry": {
        "type": "Point",
        "coordinates": [
          -85.4333,
          36.0167
        ]
      },
      "type": "Feature",
      "properties": {
        "hierarchy": [
          "tgn:2234810",
          "tgn:1000001",
          "tgn:7012149",
          "tgn:2001929",
          "tgn:7007825",
          "tgn:7029392"
        ],
        "placetype": [
          "aat:300008347"
        ],
        "id": 2234810,
        "name:xx": "Cherry Creek"
      }
    },
    {
      "geometry": {
        "type": "Point",
        "coordinates": [
          -99.4,
          30.0167
        ]
      },
      "type": "Feature",
      "properties": {
        "hierarchy": [
          "tgn:2234811",
          "tgn:1000001",
          "tgn:7012149",
          "tgn:2002018",
          "tgn:7007826",
          "tgn:7029392"
        ],
        "placetype": [
          "aat:300008706"
        ],
        "id": 2234811,
        "name:xx": "Cherry Creek"
      }
    },
    {
      "geometry": {
        "type": "Point",
        "coordinates": [
          -100.3167,
          29.7
        ]
      },
      "type": "Feature",
      "properties": {
        "hierarchy": [
          "tgn:2234812",
          "tgn:1000001",
          "tgn:7012149",
          "tgn:2001980",
          "tgn:7007826",
          "tgn:7029392"
        ],
        "placetype": [
          "aat:300008706"
        ],
        "id": 2234812,
        "name:xx": "Cherry Creek"
      }
    },
    {
      "geometry": {
        "type": "Point",
        "coordinates": [
          -94.95,
          30.4167
        ]
      },
      "type": "Feature",
      "properties": {
        "hierarchy": [
          "tgn:2234813",
          "tgn:1000001",
          "tgn:7012149",
          "tgn:1002595",
          "tgn:7007826",
          "tgn:7029392"
        ],
        "placetype": [
          "aat:300008706"
        ],
        "id": 2234813,
        "name:xx": "Cherry Creek"
      }
    },
    {
      "geometry": {
        "type": "Point",
        "coordinates": [
          -104.1,
          31.0167
        ]
      },
      "type": "Feature",
      "properties": {
        "hierarchy": [
          "tgn:2234814",
          "tgn:1000001",
          "tgn:7012149",
          "tgn:2002010",
          "tgn:7007826",
          "tgn:7029392"
        ],
        "placetype": [
          "aat:300008706"
        ],
        "id": 2234814,
        "name:xx": "Cherry Creek"
      }
    },
    {
      "geometry": {
        "type": "Point",
        "coordinates": [
          -98.3833,
          29.9
        ]
      },
      "type": "Feature",
      "properties": {
        "hierarchy": [
          "tgn:2234815",
          "tgn:1000001",
          "tgn:7012149",
          "tgn:2001961",
          "tgn:7007826",
          "tgn:7029392"
        ],
        "placetype": [
          "aat:300008706"
        ],
        "id": 2234815,
        "name:xx": "Cherry Creek"
      }
    },
    {
      "geometry": {
        "type": "Point",
        "coordinates": [
          -98.9667,
          29.3667
        ]
      },
      "type": "Feature",
      "properties": {
        "hierarchy": [
          "tgn:2234816",
          "tgn:1000001",
          "tgn:7012149",
          "tgn:2002039",
          "tgn:7007826",
          "tgn:7029392"
        ],
        "placetype": [
          "aat:300008706"
        ],
        "id": 2234816,
        "name:xx": "Cherry Creek"
      }
    },
    {
      "geometry": {
        "type": "Point",
        "coordinates": [
          -111.8667,
          37.75
        ]
      },
      "type": "Feature",
      "properties": {
        "hierarchy": [
          "tgn:2234817",
          "tgn:1000001",
          "tgn:2002109",
          "tgn:7012149",
          "tgn:7007827",
          "tgn:7029392"
        ],
        "placetype": [
          "aat:300008706"
        ],
        "id": 2234817,
        "name:xx": "Cherry Creek"
      }
    },
    {
      "geometry": {
        "type": "Point",
        "coordinates": [
          -112.85,
          38.3
        ]
      },
      "type": "Feature",
      "properties": {
        "hierarchy": [
          "tgn:2234818",
          "tgn:2002101",
          "tgn:1000001",
          "tgn:7012149",
          "tgn:7007827",
          "tgn:7029392"
        ],
        "placetype": [
          "aat:300008706"
        ],
        "id": 2234818,
        "name:xx": "Cherry Creek"
      }
    },
    {
      "geometry": {
        "type": "Point",
        "coordinates": [
          -112.2833,
          38.7667
        ]
      },
      "type": "Feature",
      "properties": {
        "hierarchy": [
          "tgn:2234819",
          "tgn:1000001",
          "tgn:7012149",
          "tgn:2002114",
          "tgn:7007827",
          "tgn:7029392"
        ],
        "placetype": [
          "aat:300008706"
        ],
        "id": 2234819,
        "name:xx": "Cherry Creek"
      }
    }
  ]
}
