{
  "geometry": {
    "type": "Point",
    "coordinates": [
      -83.0833,
      40.7667
    ]
  },
  "type": "Feature",
  "properties": {
    "hierarchy": [
      "tgn:2361899",
      "tgn:1000001",
      "tgn:7012149",
      "tgn:7007706",
      "tgn:7029392"
    ],
    "placetype": [
      "aat:300008699"
    ],
    "id": 2361899,
    "name:xx": "Gray Eye Run"
  }
}
