{
  "geometry": {
    "type": "Point",
    "coordinates": [
      105.3667,
      16.0833
    ]
  },
  "type": "Feature",
  "properties": {
    "hierarchy": [
      "tgn:1082441",
      "tgn:1000004",
      "tgn:7000850",
      "tgn:1000125",
      "tgn:7029392"
    ],
    "placetype": [
      "aat:300008347"
    ],
    "id": 1082441,
    "name:xx": "Ban Kèngtangan"
  }
}
