{
  "geometry": {
    "type": "Point",
    "coordinates": [
      -80.35,
      39.4833
    ]
  },
  "type": "Feature",
  "properties": {
    "hierarchy": [
      "tgn:2452023",
      "tgn:1000001",
      "tgn:7012149",
      "tgn:2002275",
      "tgn:7013961",
      "tgn:7029392"
    ],
    "placetype": [
      "aat:300008706"
    ],
    "id": 2452023,
    "name:xx": "Little Bingamon Creek"
  }
}
