{
  "geometry": {
    "type": "Point",
    "coordinates": [
      -88.4833,
      46.6667
    ]
  },
  "type": "Feature",
  "properties": {
    "hierarchy": [
      "tgn:2417936",
      "tgn:2000947",
      "tgn:1000001",
      "tgn:7012149",
      "tgn:7007520",
      "tgn:7029392"
    ],
    "placetype": [
      "aat:300008680"
    ],
    "id": 2417936,
    "name:xx": "Jackson Lakes"
  }
}
