{
  "geometry": {
    "type": "Point",
    "coordinates": [
      -102.7167,
      35.4667
    ]
  },
  "type": "Feature",
  "properties": {
    "hierarchy": [
      "tgn:2347499",
      "tgn:1000001",
      "tgn:7012149",
      "tgn:2002051",
      "tgn:7007826",
      "tgn:7029392"
    ],
    "placetype": [
      "aat:300006191"
    ],
    "id": 2347499,
    "name:xx": "George Spring Tank"
  }
}
