{
  "geometry": {
    "type": "Point",
    "coordinates": [
      -111.7333,
      39.75
    ]
  },
  "type": "Feature",
  "properties": {
    "hierarchy": [
      "tgn:2491644",
      "tgn:1000001",
      "tgn:7012149",
      "tgn:2002112",
      "tgn:7007827",
      "tgn:7029392"
    ],
    "placetype": [
      "aat:300008697"
    ],
    "id": 2491644,
    "name:xx": "Maple Spring"
  }
}
