{
  "geometry": {
    "type": "Point",
    "coordinates": [
      -118.25,
      34.0667
    ]
  },
  "type": "Feature",
  "properties": {
    "hierarchy": [
      "tgn:2012361",
      "tgn:1000001",
      "tgn:7012149",
      "tgn:7007157",
      "tgn:7023900",
      "tgn:1002608",
      "tgn:7029392"
    ],
    "placetype": [
      "aat:300000745"
    ],
    "id": 2012361,
    "name:xx": "Echo Park"
  }
}
