{
  "geometry": {
    "type": "Point",
    "coordinates": [
      -90.0667,
      35.1833
    ]
  },
  "type": "Feature",
  "properties": {
    "hierarchy": [
      "tgn:2470120",
      "tgn:1000001",
      "tgn:7012149",
      "tgn:2001915",
      "tgn:7007825",
      "tgn:7029392"
    ],
    "placetype": [
      "aat:300132348"
    ],
    "id": 2470120,
    "name:xx": "Loosahatchie Bar"
  }
}
