{
  "type": "FeatureCollection",
  "features": [
    {
      "geometry": {
        "type": "Point",
        "coordinates": [
          -95.1,
          32.5833
        ]
      },
      "type": "Feature",
      "properties": {
        "hierarchy": [
          "tgn:2102741",
          "tgn:1000001",
          "tgn:7012149",
          "tgn:1002966",
          "tgn:7007826",
          "tgn:7029392"
        ],
        "placetype": [
          "aat:300008347"
        ],
        "id": 2102741,
        "name:xx": "Big Sandy"
      }
    },
    {
      "geometry": {
        "type": "Point",
        "coordinates": [
          -101.4667,
          32.25
        ]
      },
      "type": "Feature",
      "properties": {
        "hierarchy": [
          "tgn:2102742",
          "tgn:1000001",
          "tgn:7012149",
          "tgn:2002004",
          "tgn:7007826",
          "tgn:7029392"
        ],
        "placetype": [
          "aat:300008347"
        ],
        "id": 2102742,
        "name:xx": "Big Spring"
      }
    },
    {
      "geometry": {
        "type": "Point",
        "coordinates": [
          -99.5667,
          28.5667
        ]
      },
      "type": "Feature",
      "properties": {
        "hierarchy": [
          "tgn:2102746",
          "tgn:1000001",
          "tgn:7012149",
          "tgn:2001975",
          "tgn:7007826",
          "tgn:7029392"
        ],
        "placetype": [
          "aat:300008347"
        ],
        "id": 2102746,
        "name:xx": "Big Wells"
      }
    },
    {
      "geometry": {
        "type": "Point",
        "coordinates": [
          -96.6667,
          30.3667
        ]
      },
      "type": "Feature",
      "properties": {
        "hierarchy": [
          "tgn:2102749",
          "tgn:1000001",
          "tgn:7012149",
          "tgn:1002214",
          "tgn:7007826",
          "tgn:7029392"
        ],
        "placetype": [
          "aat:300008347",
          "aat:300387210"
        ],
        "id": 2102749,
        "name:xx": "Birch"
      }
    }
  ]
}
