{
  "geometry": {
    "type": "Point",
    "coordinates": [
      103.2667,
      -1.8667
    ]
  },
  "type": "Feature",
  "properties": {
    "hierarchy": [
      "tgn:1077497",
      "tgn:1001319",
      "tgn:1000004",
      "tgn:1000116",
      "tgn:7029392"
    ],
    "placetype": [
      "aat:300008347"
    ],
    "id": 1077497,
    "name:xx": "Betung"
  }
}
