{
  "geometry": {
    "type": "Point",
    "coordinates": [
      -85.9833,
      36.2667
    ]
  },
  "type": "Feature",
  "properties": {
    "hierarchy": [
      "tgn:2223889",
      "tgn:1000001",
      "tgn:7012149",
      "tgn:2001916",
      "tgn:7007825",
      "tgn:7029392"
    ],
    "placetype": [
      "aat:300008791"
    ],
    "id": 2223889,
    "name:xx": "Carters Island"
  }
}
