{
  "geometry": {
    "type": "Point",
    "coordinates": [
      37.55,
      15.4833
    ]
  },
  "type": "Feature",
  "properties": {
    "hierarchy": [
      "tgn:1089746",
      "tgn:7001242",
      "tgn:7017565",
      "tgn:7001658",
      "tgn:7029392"
    ],
    "placetype": [
      "aat:300008347"
    ],
    "id": 1089746,
    "name:xx": "Bīsha"
  }
}
