{
  "geometry": {
    "type": "Point",
    "coordinates": [
      -78.95,
      35.35
    ]
  },
  "type": "Feature",
  "properties": {
    "hierarchy": [
      "tgn:2628690",
      "tgn:1000001",
      "tgn:7012149",
      "tgn:2001502",
      "tgn:7007709",
      "tgn:7029392"
    ],
    "placetype": [
      "aat:300008699"
    ],
    "id": 2628690,
    "name:xx": "Rooty Branch"
  }
}
