{
  "geometry": {
    "type": "Point",
    "coordinates": [
      -106.7333,
      32.1667
    ]
  },
  "type": "Feature",
  "properties": {
    "hierarchy": [
      "tgn:2067521",
      "tgn:1000001",
      "tgn:2001435",
      "tgn:7012149",
      "tgn:7007566",
      "tgn:7029392"
    ],
    "placetype": [
      "aat:300008347"
    ],
    "id": 2067521,
    "name:xx": "Santo Tomas"
  }
}
