{
  "geometry": {
    "type": "Point",
    "coordinates": [
      120.4061,
      22.6095
    ]
  },
  "type": "Feature",
  "properties": {
    "hierarchy": [
      "tgn:7488476",
      "tgn:7001004",
      "tgn:1000004",
      "tgn:1000141",
      "tgn:7029392"
    ],
    "placetype": [
      "aat:300008347"
    ],
    "id": 7488476,
    "name:xx": "Hongcuocheng"
  }
}
