{
  "geometry": {
    "type": "Point",
    "coordinates": [
      -108.7167,
      42.5667
    ]
  },
  "type": "Feature",
  "properties": {
    "hierarchy": [
      "tgn:2449333",
      "tgn:1000001",
      "tgn:7012149",
      "tgn:2002371",
      "tgn:7007923",
      "tgn:7029392"
    ],
    "placetype": [
      "aat:300008798"
    ],
    "id": 2449333,
    "name:xx": "Limestone Mountain"
  }
}
