{
  "geometry": {
    "type": "Point",
    "coordinates": [
      -92.85,
      37.7333
    ]
  },
  "type": "Feature",
  "properties": {
    "hierarchy": [
      "tgn:2642293",
      "tgn:1000001",
      "tgn:7012149",
      "tgn:2001192",
      "tgn:7007523",
      "tgn:7029392"
    ],
    "placetype": [
      "aat:300008697"
    ],
    "id": 2642293,
    "name:xx": "Sand Spring"
  }
}
