{
  "geometry": {
    "type": "Point",
    "coordinates": [
      125.9167,
      38.05
    ]
  },
  "type": "Feature",
  "properties": {
    "hierarchy": [
      "tgn:1082023",
      "tgn:1001301",
      "tgn:1000004",
      "tgn:1000122",
      "tgn:7029392"
    ],
    "placetype": [
      "aat:300008347"
    ],
    "id": 1082023,
    "name:xx": "Kamsu-ri"
  }
}
