{
  "geometry": {
    "type": "Point",
    "coordinates": [
      125.25,
      6.1167
    ]
  },
  "type": "Feature",
  "properties": {
    "hierarchy": [
      "tgn:1084060",
      "tgn:1000004",
      "tgn:1001541",
      "tgn:1000135",
      "tgn:7029392"
    ],
    "placetype": [
      "aat:300008347"
    ],
    "id": 1084060,
    "name:xx": "Buayan"
  }
}
