{
  "geometry": {
    "type": "Point",
    "coordinates": [
      -121.3833,
      37.3333
    ]
  },
  "type": "Feature",
  "properties": {
    "hierarchy": [
      "tgn:2356162",
      "tgn:1000001",
      "tgn:7012149",
      "tgn:7007157",
      "tgn:1002915",
      "tgn:7029392"
    ],
    "placetype": [
      "aat:300008761"
    ],
    "id": 2356162,
    "name:xx": "Gooseberry Canyon"
  }
}
