{
  "type": "FeatureCollection",
  "features": [
    {
      "geometry": {
        "type": "Point",
        "coordinates": [
          -102.3,
          43.4833
        ]
      },
      "type": "Feature",
      "properties": {
        "hierarchy": [
          "tgn:2566040",
          "tgn:1000001",
          "tgn:7012149",
          "tgn:2001826",
          "tgn:7007713",
          "tgn:7029392"
        ],
        "placetype": [
          "aat:300008706"
        ],
        "id": 2566040,
        "name:xx": "Palmer Creek"
      }
    },
    {
      "geometry": {
        "type": "Point",
        "coordinates": [
          -83.1,
          36.0667
        ]
      },
      "type": "Feature",
      "properties": {
        "hierarchy": [
          "tgn:2566041",
          "tgn:1000001",
          "tgn:7012149",
          "tgn:2001851",
          "tgn:7007825",
          "tgn:7029392"
        ],
        "placetype": [
          "aat:300008706"
        ],
        "id": 2566041,
        "name:xx": "Palmer Creek"
      }
    },
    {
      "geometry": {
        "type": "Point",
        "coordinates": [
          -99.2167,
          29.9
        ]
      },
      "type": "Feature",
      "properties": {
        "hierarchy": [
          "tgn:2566042",
          "tgn:1000001",
          "tgn:7012149",
          "tgn:7007826",
          "tgn:7029392"
        ],
        "placetype": [
          "aat:300008706"
        ],
        "id": 2566042,
        "name:xx": "Palmer Creek"
      }
    },
    {
      "geometry": {
        "type": "Point",
        "coordinates": [
          -117.5333,
          48.3167
        ]
      },
      "type": "Feature",
      "properties": {
        "hierarchy": [
          "tgn:2566043",
          "tgn:1000001",
          "tgn:7012149",
          "tgn:2002250",
          "tgn:7007920",
          "tgn:7029392"
        ],
        "placetype": [
          "aat:300008706"
        ],
        "id": 2566043,
        "name:xx": "Palmer Creek"
      }
    },
    {
      "geometry": {
        "type": "Point",
        "coordinates": [
          -121.4333,
          48.0167
        ]
      },
      "type": "Feature",
      "properties": {
        "hierarchy": [
          "tgn:2566044",
          "tgn:1000001",
          "tgn:7012149",
          "tgn:1002899",
          "tgn:7007920",
          "tgn:7029392"
        ],
        "placetype": [
          "aat:300008706"
        ],
        "id": 2566044,
        "name:xx": "Palmer Creek"
      }
    },
    {
      "geometry": {
        "type": "Point",
        "coordinates": [
          -119.6333,
          48.9
        ]
      },
      "type": "Feature",
      "properties": {
        "hierarchy": [
          "tgn:2566045",
          "tgn:1000001",
          "tgn:7012149",
          "tgn:1002742",
          "tgn:7007920",
          "tgn:7029392"
        ],
        "placetype": [
          "aat:300008706"
        ],
        "id": 2566045,
        "name:xx": "Palmer Creek"
      }
    },
    {
      "geometry": {
        "type": "Point",
        "coordinates": [
          -88.25,
          42.5667
        ]
      },
      "type": "Feature",
      "properties": {
        "hierarchy": [
          "tgn:2566046",
          "tgn:1000001",
          "tgn:7012149",
          "tgn:1002537",
          "tgn:7007922",
          "tgn:7029392"
        ],
        "placetype": [
          "aat:300008706"
        ],
        "id": 2566046,
        "name:xx": "Palmer Creek"
      }
    },
    {
      "geometry": {
        "type": "Point",
        "coordinates": [
          -110.7167,
          43.2833
        ]
      },
      "type": "Feature",
      "properties": {
        "hierarchy": [
          "tgn:2566047",
          "tgn:1000001",
          "tgn:7012149",
          "tgn:2002384",
          "tgn:7007923",
          "tgn:7029392"
        ],
        "placetype": [
          "aat:300008706"
        ],
        "id": 2566047,
        "name:xx": "Palmer Creek"
      }
    },
    {
      "geometry": {
        "type": "Point",
        "coordinates": [
          -68.05,
          45.7
        ]
      },
      "type": "Feature",
      "properties": {
        "hierarchy": [
          "tgn:2566048",
          "tgn:2000919",
          "tgn:1000001",
          "tgn:7012149",
          "tgn:7007515",
          "tgn:7029392"
        ],
        "placetype": [
          "aat:300008905"
        ],
        "id": 2566048,
        "name:xx": "Palmer Deadwater"
      }
    },
    {
      "geometry": {
        "type": "Point",
        "coordinates": [
          -85.35,
          40.7
        ]
      },
      "type": "Feature",
      "properties": {
        "hierarchy": [
          "tgn:2566049",
          "tgn:1000001",
          "tgn:7012149",
          "tgn:1002496",
          "tgn:7007252",
          "tgn:7029392"
        ],
        "placetype": [
          "aat:300006075"
        ],
        "id": 2566049,
        "name:xx": "Palmer Ditch"
      }
    }
  ]
}
