{
  "geometry": {
    "type": "Point",
    "coordinates": [
      66.8167,
      39.0833
    ]
  },
  "type": "Feature",
  "properties": {
    "hierarchy": [
      "tgn:1051509",
      "tgn:1000004",
      "tgn:7012259",
      "tgn:7006661",
      "tgn:7029392"
    ],
    "placetype": [
      "aat:300008347"
    ],
    "id": 1051509,
    "name:xx": "Shakhrisabz"
  }
}
