{
  "geometry": {
    "type": "Point",
    "coordinates": [
      -82.9167,
      35.15
    ]
  },
  "type": "Feature",
  "properties": {
    "hierarchy": [
      "tgn:2546197",
      "tgn:1000001",
      "tgn:7012149",
      "tgn:2001544",
      "tgn:7007709",
      "tgn:7029392"
    ],
    "placetype": [
      "aat:300008706"
    ],
    "id": 2546197,
    "name:xx": "North Fork Flat Creek"
  }
}
