{
  "type": "FeatureCollection",
  "features": [
    {
      "geometry": {
        "type": "Point",
        "coordinates": [
          74.816667,
          14.866667
        ]
      },
      "type": "Feature",
      "properties": {
        "hierarchy": [
          "tgn:7555240",
          "tgn:1000004",
          "tgn:7000198",
          "tgn:1001882",
          "tgn:7029392"
        ],
        "placetype": [
          "aat:300008347"
        ],
        "name:en": "Manchikeri",
        "id": 7555240
      }
    },
    {
      "geometry": {
        "type": "Point",
        "coordinates": [
          85.844854,
          20.32178
        ]
      },
      "type": "Feature",
      "properties": {
        "hierarchy": [
          "tgn:7555241",
          "tgn:1000004",
          "tgn:7000198",
          "tgn:7016694",
          "tgn:7029392"
        ],
        "placetype": [
          "aat:300007783"
        ],
        "name:en": "Mancheshwar",
        "id": 7555241
      }
    },
    {
      "geometry": {
        "type": "Point",
        "coordinates": [
          73.933333,
          19
        ]
      },
      "type": "Feature",
      "properties": {
        "hierarchy": [
          "tgn:7555243",
          "tgn:1000004",
          "tgn:7000198",
          "tgn:1001895",
          "tgn:7029392"
        ],
        "placetype": [
          "aat:300008347"
        ],
        "name:en": "Manchar",
        "id": 7555243
      }
    },
    {
      "geometry": {
        "type": "Point",
        "coordinates": [
          74.499294,
          32.732243
        ]
      },
      "type": "Feature",
      "properties": {
        "hierarchy": [
          "tgn:7555245",
          "tgn:1000004",
          "tgn:7000198",
          "tgn:7000799",
          "tgn:7029392"
        ],
        "placetype": [
          "aat:300008699"
        ],
        "name:en": "Manﾄ『ar Tawi River",
        "id": 7555245
      }
    },
    {
      "geometry": {
        "type": "Point",
        "coordinates": [
          78.216667,
          10.916667
        ]
      },
      "type": "Feature",
      "properties": {
        "hierarchy": [
          "tgn:7555247",
          "tgn:1000004",
          "tgn:7000198",
          "tgn:7001797",
          "tgn:7029392"
        ],
        "placetype": [
          "aat:300007783"
        ],
        "name:en": "Manavﾄ《i",
        "id": 7555247
      }
    },
    {
      "geometry": {
        "type": "Point",
        "coordinates": [
          77.3,
          8.133333
        ]
      },
      "type": "Feature",
      "properties": {
        "hierarchy": [
          "tgn:7555248",
          "tgn:1000004",
          "tgn:7000198",
          "tgn:7001797",
          "tgn:7029392"
        ],
        "placetype": [
          "aat:300008347"
        ],
        "name:en": "Manavalakurichi",
        "id": 7555248
      }
    },
    {
      "geometry": {
        "type": "Point",
        "coordinates": [
          70.133333,
          21.5
        ]
      },
      "type": "Feature",
      "properties": {
        "hierarchy": [
          "tgn:7555249",
          "tgn:1000004",
          "tgn:1001869",
          "tgn:7000198",
          "tgn:7029392"
        ],
        "placetype": [
          "aat:300008347"
        ],
        "name:en": "Mﾄ］ﾄ」adar",
        "id": 7555249
      }
    }
  ]
}
