{
  "geometry": {
    "type": "Point",
    "coordinates": [
      31.145809,
      31.00216
    ]
  },
  "type": "Feature",
  "properties": {
    "hierarchy": [
      "tgn:7542512",
      "tgn:7001242",
      "tgn:7016833",
      "tgn:7001312",
      "tgn:7029392"
    ],
    "placetype": [
      "aat:300006075"
    ],
    "name:en": "Tir'at Sāmūl",
    "id": 7542512
  }
}
