{
  "geometry": {
    "type": "Point",
    "coordinates": [
      138.1833,
      34.6333
    ]
  },
  "type": "Feature",
  "properties": {
    "hierarchy": [
      "tgn:1081171",
      "tgn:7000895",
      "tgn:1000004",
      "tgn:1001031",
      "tgn:1000120",
      "tgn:7029392"
    ],
    "placetype": [
      "aat:300008347"
    ],
    "id": 1081171,
    "name:xx": "Sagara"
  }
}
