{
  "type": "FeatureCollection",
  "features": [
    {
      "geometry": {
        "type": "Point",
        "coordinates": [
          -3.233333,
          55.933333
        ]
      },
      "type": "Feature",
      "properties": {
        "hierarchy": [
          "tgn:7452573",
          "tgn:7002444",
          "tgn:1000003",
          "tgn:7019109",
          "tgn:7008591",
          "tgn:7029392"
        ],
        "placetype": [
          "aat:300000745"
        ],
        "name:en": "Gorgie",
        "id": 7452573
      }
    },
    {
      "geometry": {
        "type": "Point",
        "coordinates": [
          0.1,
          52.683333
        ]
      },
      "type": "Feature",
      "properties": {
        "hierarchy": [
          "tgn:7452574",
          "tgn:7002445",
          "tgn:7011980",
          "tgn:1000003",
          "tgn:7008591",
          "tgn:7029392"
        ],
        "placetype": [
          "aat:300008347"
        ],
        "name:en": "Gorfield",
        "id": 7452574
      }
    },
    {
      "geometry": {
        "type": "Point",
        "coordinates": [
          -3.063333,
          51.256111
        ]
      },
      "type": "Feature",
      "properties": {
        "hierarchy": [
          "tgn:7452575",
          "tgn:7002445",
          "tgn:1000003",
          "tgn:7012032",
          "tgn:7008591",
          "tgn:7029392"
        ],
        "placetype": [
          "aat:300386885"
        ],
        "name:en": "Gore Sand",
        "id": 7452575
      }
    },
    {
      "geometry": {
        "type": "Point",
        "coordinates": [
          0.55,
          52.966667
        ]
      },
      "type": "Feature",
      "properties": {
        "hierarchy": [
          "tgn:7452576",
          "tgn:7002445",
          "tgn:1000003",
          "tgn:7008160",
          "tgn:7008591",
          "tgn:7029392"
        ],
        "placetype": [
          "aat:300386846"
        ],
        "name:en": "Gore Point",
        "id": 7452576
      }
    },
    {
      "geometry": {
        "type": "Point",
        "coordinates": [
          0.55,
          53
        ]
      },
      "type": "Feature",
      "properties": {
        "hierarchy": [
          "tgn:7452577",
          "tgn:7002445",
          "tgn:1000003",
          "tgn:7008160",
          "tgn:7008591",
          "tgn:7029392"
        ],
        "placetype": [
          "aat:300386970"
        ],
        "name:en": "Gore Middle",
        "id": 7452577
      }
    },
    {
      "geometry": {
        "type": "Point",
        "coordinates": [
          -4.183333,
          53.216667
        ]
      },
      "type": "Feature",
      "properties": {
        "hierarchy": [
          "tgn:7452578",
          "tgn:7002443",
          "tgn:1000003",
          "tgn:7029493",
          "tgn:7008591",
          "tgn:7029392"
        ],
        "placetype": [
          "aat:300008791"
        ],
        "name:en": "Gorad Goch, Ynys",
        "id": 7452578
      }
    }
  ]
}
