{
  "geometry": {
    "type": "Point",
    "coordinates": [
      -1.15,
      41.25
    ]
  },
  "type": "Feature",
  "properties": {
    "hierarchy": [
      "tgn:7348100",
      "tgn:7002759",
      "tgn:7002845",
      "tgn:1000003",
      "tgn:1000095",
      "tgn:7029392"
    ],
    "placetype": [
      "aat:300008347"
    ],
    "id": 7348100,
    "name:xx": "Aladrén"
  }
}
