{
  "geometry": {
    "type": "Point",
    "coordinates": [
      -84.5333,
      40.5333
    ]
  },
  "type": "Feature",
  "properties": {
    "hierarchy": [
      "tgn:2376107",
      "tgn:1000001",
      "tgn:7012149",
      "tgn:1002658",
      "tgn:7007706",
      "tgn:7029392"
    ],
    "placetype": [
      "aat:300008850"
    ],
    "id": 2376107,
    "name:xx": "Harbor Point"
  }
}
