{
  "geometry": {
    "type": "Point",
    "coordinates": [
      30.735034,
      28.662498
    ]
  },
  "type": "Feature",
  "properties": {
    "hierarchy": [
      "tgn:7525803",
      "tgn:7001242",
      "tgn:7016833",
      "tgn:1001088",
      "tgn:7029392"
    ],
    "placetype": [
      "aat:300008347"
    ],
    "name:en": "Banī 'Āmir",
    "id": 7525803
  }
}
