{
  "type": "FeatureCollection",
  "features": [
    {
      "geometry": {
        "type": "Point",
        "coordinates": [
          -85.3833,
          36.6667
        ]
      },
      "type": "Feature",
      "properties": {
        "hierarchy": [
          "tgn:2572150",
          "tgn:1000001",
          "tgn:7012149",
          "tgn:2000785",
          "tgn:7007255",
          "tgn:7029392"
        ],
        "placetype": [
          "aat:300266640"
        ],
        "id": 2572150,
        "name:xx": "Pea Ridge"
      }
    },
    {
      "geometry": {
        "type": "Point",
        "coordinates": [
          -86.0833,
          36.7667
        ]
      },
      "type": "Feature",
      "properties": {
        "hierarchy": [
          "tgn:2572151",
          "tgn:2000766",
          "tgn:1000001",
          "tgn:7012149",
          "tgn:7007255",
          "tgn:7029392"
        ],
        "placetype": [
          "aat:300266640"
        ],
        "id": 2572151,
        "name:xx": "Pea Ridge"
      }
    },
    {
      "geometry": {
        "type": "Point",
        "coordinates": [
          -86.6,
          37.2
        ]
      },
      "type": "Feature",
      "properties": {
        "hierarchy": [
          "tgn:2572152",
          "tgn:1000001",
          "tgn:2000775",
          "tgn:7012149",
          "tgn:7007255",
          "tgn:7029392"
        ],
        "placetype": [
          "aat:300266640"
        ],
        "id": 2572152,
        "name:xx": "Pea Ridge"
      }
    },
    {
      "geometry": {
        "type": "Point",
        "coordinates": [
          -84.0167,
          37.6833
        ]
      },
      "type": "Feature",
      "properties": {
        "hierarchy": [
          "tgn:2572153",
          "tgn:1000001",
          "tgn:7012149",
          "tgn:2000788",
          "tgn:7007255",
          "tgn:7029392"
        ],
        "placetype": [
          "aat:300266640"
        ],
        "id": 2572153,
        "name:xx": "Pea Ridge"
      }
    },
    {
      "geometry": {
        "type": "Point",
        "coordinates": [
          -84.9333,
          38.1667
        ]
      },
      "type": "Feature",
      "properties": {
        "hierarchy": [
          "tgn:2572154",
          "tgn:1000001",
          "tgn:7012149",
          "tgn:1002382",
          "tgn:7007255",
          "tgn:7029392"
        ],
        "placetype": [
          "aat:300266640"
        ],
        "id": 2572154,
        "name:xx": "Pea Ridge"
      }
    },
    {
      "geometry": {
        "type": "Point",
        "coordinates": [
          -84.7167,
          38.2333
        ]
      },
      "type": "Feature",
      "properties": {
        "hierarchy": [
          "tgn:2572155",
          "tgn:1000001",
          "tgn:7012149",
          "tgn:1002880",
          "tgn:7007255",
          "tgn:7029392"
        ],
        "placetype": [
          "aat:300266640"
        ],
        "id": 2572155,
        "name:xx": "Pea Ridge"
      }
    },
    {
      "geometry": {
        "type": "Point",
        "coordinates": [
          -84.4,
          37.1
        ]
      },
      "type": "Feature",
      "properties": {
        "hierarchy": [
          "tgn:2572156",
          "tgn:1000001",
          "tgn:7012149",
          "tgn:2000839",
          "tgn:7007255",
          "tgn:7029392"
        ],
        "placetype": [
          "aat:300266640"
        ],
        "id": 2572156,
        "name:xx": "Pea Ridge"
      }
    },
    {
      "geometry": {
        "type": "Point",
        "coordinates": [
          -86.6667,
          37.3667
        ]
      },
      "type": "Feature",
      "properties": {
        "hierarchy": [
          "tgn:2572157",
          "tgn:1000001",
          "tgn:7012149",
          "tgn:7007255",
          "tgn:7029392"
        ],
        "placetype": [
          "aat:300266640"
        ],
        "id": 2572157,
        "name:xx": "Pea Ridge"
      }
    },
    {
      "geometry": {
        "type": "Point",
        "coordinates": [
          -85.1167,
          38.0833
        ]
      },
      "type": "Feature",
      "properties": {
        "hierarchy": [
          "tgn:2572158",
          "tgn:1000001",
          "tgn:7012149",
          "tgn:1002887",
          "tgn:7007255",
          "tgn:7029392"
        ],
        "placetype": [
          "aat:300266640"
        ],
        "id": 2572158,
        "name:xx": "Pea Ridge"
      }
    },
    {
      "geometry": {
        "type": "Point",
        "coordinates": [
          -79.0333,
          39.6333
        ]
      },
      "type": "Feature",
      "properties": {
        "hierarchy": [
          "tgn:2572159",
          "tgn:1000001",
          "tgn:2000935",
          "tgn:7012149",
          "tgn:7007516",
          "tgn:7029392"
        ],
        "placetype": [
          "aat:300266640"
        ],
        "id": 2572159,
        "name:xx": "Pea Ridge"
      }
    }
  ]
}
