{
  "geometry": {
    "type": "Point",
    "coordinates": [
      -82.85,
      43.05
    ]
  },
  "type": "Feature",
  "properties": {
    "hierarchy": [
      "tgn:2162928",
      "tgn:1000001",
      "tgn:7012149",
      "tgn:7016056",
      "tgn:7007520",
      "tgn:7029392"
    ],
    "placetype": [
      "aat:300006075"
    ],
    "id": 2162928,
    "name:xx": "Benke Drain"
  }
}
