{
  "geometry": {
    "type": "Point",
    "coordinates": [
      -81.5167,
      38.7667
    ]
  },
  "type": "Feature",
  "properties": {
    "hierarchy": [
      "tgn:2493570",
      "tgn:1000001",
      "tgn:7012149",
      "tgn:2002293",
      "tgn:7013961",
      "tgn:7029392"
    ],
    "placetype": [
      "aat:300008798"
    ],
    "id": 2493570,
    "name:xx": "Marsh Hart Knob"
  }
}
