{
  "geometry": {
    "type": "Point",
    "coordinates": [
      145.25,
      -37.8167
    ]
  },
  "type": "Feature",
  "properties": {
    "hierarchy": [
      "tgn:1098057",
      "tgn:7000490",
      "tgn:1000006",
      "tgn:7006238",
      "tgn:7029392"
    ],
    "placetype": [
      "aat:300008347"
    ],
    "id": 1098057,
    "name:xx": "Ringwood"
  }
}
