{
  "geometry": {
    "type": "Point",
    "coordinates": [
      -123.0833,
      41.4667
    ]
  },
  "type": "Feature",
  "properties": {
    "hierarchy": [
      "tgn:2618929",
      "tgn:1000001",
      "tgn:7012149",
      "tgn:7007157",
      "tgn:2000189",
      "tgn:7029392"
    ],
    "placetype": [
      "aat:300008707"
    ],
    "id": 2618929,
    "name:xx": "Right Hand North Fork Salmon River"
  }
}
