{
  "geometry": {
    "type": "Point",
    "coordinates": [
      -115.9333,
      40.7333
    ]
  },
  "type": "Feature",
  "properties": {
    "hierarchy": [
      "tgn:2063021",
      "tgn:1000001",
      "tgn:2001411",
      "tgn:7012149",
      "tgn:7007526",
      "tgn:7029392"
    ],
    "placetype": [
      "aat:300387016"
    ],
    "id": 2063021,
    "name:xx": "Moleen"
  }
}
