{
  "type": "FeatureCollection",
  "features": [
    {
      "geometry": {
        "type": "Point",
        "coordinates": [
          -1.366667,
          51.2
        ]
      },
      "type": "Feature",
      "properties": {
        "hierarchy": [
          "tgn:4005203",
          "tgn:7002445",
          "tgn:1000003",
          "tgn:7008139",
          "tgn:7008591",
          "tgn:7029392"
        ],
        "placetype": [
          "aat:300008347",
          "aat:300008372"
        ],
        "name:en": "Hurstbourne Priors",
        "id": 4005203
      }
    },
    {
      "geometry": {
        "type": "Point",
        "coordinates": [
          -0.916667,
          54.283333
        ]
      },
      "type": "Feature",
      "properties": {
        "hierarchy": [
          "tgn:4005206",
          "tgn:7002445",
          "tgn:1000003",
          "tgn:7008166",
          "tgn:7008591",
          "tgn:7029392"
        ],
        "placetype": [
          "aat:300008347",
          "aat:300008372"
        ],
        "id": 4005206,
        "name:xx": "Hutton-le-Hole"
      }
    },
    {
      "geometry": {
        "type": "Point",
        "coordinates": [
          11,
          51.966667
        ]
      },
      "type": "Feature",
      "properties": {
        "hierarchy": [
          "tgn:4005207",
          "tgn:1000003",
          "tgn:7003687",
          "tgn:7000084",
          "tgn:7029392"
        ],
        "placetype": [
          "aat:300008347"
        ],
        "id": 4005207,
        "name:xx": "Huysburg"
      }
    },
    {
      "geometry": {
        "type": "Point",
        "coordinates": [
          10.0556,
          56.006486
        ]
      },
      "type": "Feature",
      "properties": {
        "hierarchy": [
          "tgn:4005209",
          "tgn:7594006",
          "tgn:1000003",
          "tgn:1000066",
          "tgn:7029392"
        ],
        "placetype": [
          "aat:300008347"
        ],
        "id": 4005209,
        "name:xx": "Hvilsted"
      }
    }
  ]
}
