{
  "geometry": {
    "type": "Point",
    "coordinates": [
      -83.6667,
      34.8167
    ]
  },
  "type": "Feature",
  "properties": {
    "hierarchy": [
      "tgn:2237812",
      "tgn:1000001",
      "tgn:7012149",
      "tgn:2000430",
      "tgn:7007248",
      "tgn:7029392"
    ],
    "placetype": [
      "aat:300266640"
    ],
    "id": 2237812,
    "name:xx": "Chinquapin Ridge"
  }
}
