{
  "geometry": {
    "type": "Point",
    "coordinates": [
      -121.15,
      46.9667
    ]
  },
  "type": "Feature",
  "properties": {
    "hierarchy": [
      "tgn:2229787",
      "tgn:1000001",
      "tgn:7012149",
      "tgn:1003042",
      "tgn:7007920",
      "tgn:7029392"
    ],
    "placetype": [
      "aat:300008697"
    ],
    "id": 2229787,
    "name:xx": "Cedar Springs"
  }
}
