{
  "geometry": {
    "type": "Point",
    "coordinates": [
      -85.55,
      30.9667
    ]
  },
  "type": "Feature",
  "properties": {
    "hierarchy": [
      "tgn:2160957",
      "tgn:1000001",
      "tgn:2000272",
      "tgn:7012149",
      "tgn:7007240",
      "tgn:7029392"
    ],
    "placetype": [
      "aat:300008699"
    ],
    "id": 2160957,
    "name:xx": "Bell Branch"
  }
}
