{
  "geometry": {
    "type": "Point",
    "coordinates": [
      -109.55,
      38.7333
    ]
  },
  "type": "Feature",
  "properties": {
    "hierarchy": [
      "tgn:2755299",
      "tgn:1000001",
      "tgn:7012149",
      "tgn:2002110",
      "tgn:7007827",
      "tgn:7029392"
    ],
    "placetype": [
      "aat:300386837"
    ],
    "id": 2755299,
    "name:xx": "Webbing Arch"
  }
}
