{
  "type": "FeatureCollection",
  "features": [
    {
      "geometry": {
        "type": "Point",
        "coordinates": [
          95.75,
          52.6667
        ]
      },
      "type": "Feature",
      "properties": {
        "hierarchy": [
          "tgn:1122670",
          "tgn:1000004",
          "tgn:7002435",
          "tgn:7014829",
          "tgn:7029392"
        ],
        "placetype": [
          "aat:300008707"
        ],
        "id": 1122670,
        "name:xx": "Khamsara"
      }
    },
    {
      "geometry": {
        "type": "Point",
        "coordinates": [
          107.2333,
          55
        ]
      },
      "type": "Feature",
      "properties": {
        "hierarchy": [
          "tgn:1122672",
          "tgn:1003373",
          "tgn:1000004",
          "tgn:7018214",
          "tgn:7002435",
          "tgn:7029392"
        ],
        "placetype": [
          "aat:300008707"
        ],
        "id": 1122672,
        "name:xx": "Khanda"
      }
    },
    {
      "geometry": {
        "type": "Point",
        "coordinates": [
          -148.2833,
          67.1667
        ]
      },
      "type": "Feature",
      "properties": {
        "hierarchy": [
          "tgn:1122673",
          "tgn:7006450",
          "tgn:1000001",
          "tgn:7012149",
          "tgn:2000089",
          "tgn:7029392"
        ],
        "placetype": [
          "aat:300008707"
        ],
        "id": 1122673,
        "name:xx": "Chandalar"
      }
    },
    {
      "geometry": {
        "type": "Point",
        "coordinates": [
          -152.4833,
          68.1333
        ]
      },
      "type": "Feature",
      "properties": {
        "hierarchy": [
          "tgn:1122677",
          "tgn:7006450",
          "tgn:1000001",
          "tgn:7012149",
          "tgn:2124005",
          "tgn:7029392"
        ],
        "placetype": [
          "aat:300008707"
        ],
        "id": 1122677,
        "name:xx": "Chandler"
      }
    },
    {
      "geometry": {
        "type": "Point",
        "coordinates": [
          -70,
          -9.1667
        ]
      },
      "type": "Feature",
      "properties": {
        "hierarchy": [
          "tgn:1122678",
          "tgn:1000002",
          "tgn:7029392"
        ],
        "placetype": [
          "aat:300008707"
        ],
        "id": 1122678,
        "name:xx": "Chandless"
      }
    },
    {
      "geometry": {
        "type": "Point",
        "coordinates": [
          121.1667,
          31.8
        ]
      },
      "type": "Feature",
      "properties": {
        "hierarchy": [
          "tgn:1122679",
          "tgn:1000004",
          "tgn:1000111",
          "tgn:7029392"
        ],
        "placetype": [
          "aat:300008707"
        ],
        "name:en": "Yangtze River",
        "id": 1122679
      }
    }
  ]
}
