{
  "geometry": {
    "type": "Point",
    "coordinates": [
      111.0333,
      33.7667
    ]
  },
  "type": "Feature",
  "properties": {
    "hierarchy": [
      "tgn:1072655",
      "tgn:1000004",
      "tgn:7016672",
      "tgn:1000111",
      "tgn:7029392"
    ],
    "placetype": [
      "aat:300008347"
    ],
    "id": 1072655,
    "name:xx": "Wulichuan"
  }
}
