{
  "geometry": {
    "type": "Point",
    "coordinates": [
      -80.3167,
      35.8333
    ]
  },
  "type": "Feature",
  "properties": {
    "hierarchy": [
      "tgn:2287108",
      "tgn:1000001",
      "tgn:7012149",
      "tgn:2001489",
      "tgn:7007709",
      "tgn:7029392"
    ],
    "placetype": [
      "aat:300008347"
    ],
    "id": 2287108,
    "name:xx": "Dickerson Estates"
  }
}
