{
  "geometry": {
    "type": "Point",
    "coordinates": [
      30.95,
      40.85
    ]
  },
  "type": "Feature",
  "properties": {
    "hierarchy": [
      "tgn:1086469",
      "tgn:7593737",
      "tgn:1000004",
      "tgn:7018454",
      "tgn:1000144",
      "tgn:7029392"
    ],
    "placetype": [
      "aat:300008347"
    ],
    "id": 1086469,
    "name:xx": "Gümüşova"
  }
}
