{
  "type": "FeatureCollection",
  "features": [
    {
      "geometry": {
        "type": "Point",
        "coordinates": [
          139.2833,
          35.8
        ]
      },
      "type": "Feature",
      "properties": {
        "hierarchy": [
          "tgn:1079700",
          "tgn:1000004",
          "tgn:7000894",
          "tgn:1001032",
          "tgn:1000120",
          "tgn:7029392"
        ],
        "placetype": [
          "aat:300008347"
        ],
        "id": 1079700,
        "name:xx": "Ōme"
      }
    },
    {
      "geometry": {
        "type": "Point",
        "coordinates": [
          136.4,
          35.3333
        ]
      },
      "type": "Feature",
      "properties": {
        "hierarchy": [
          "tgn:1079701",
          "tgn:1000004",
          "tgn:7000896",
          "tgn:7000277",
          "tgn:1000120",
          "tgn:7029392"
        ],
        "placetype": [
          "aat:300008347"
        ],
        "id": 1079701,
        "name:xx": "Ōmi"
      }
    },
    {
      "geometry": {
        "type": "Point",
        "coordinates": [
          136.8333,
          35.1167
        ]
      },
      "type": "Feature",
      "properties": {
        "hierarchy": [
          "tgn:1079702",
          "tgn:1000004",
          "tgn:7000896",
          "tgn:7000277",
          "tgn:1000120",
          "tgn:7029392"
        ],
        "placetype": [
          "aat:300008347"
        ],
        "id": 1079702,
        "name:xx": "Ōmi-hachiman"
      }
    },
    {
      "geometry": {
        "type": "Point",
        "coordinates": [
          135.55,
          34.5333
        ]
      },
      "type": "Feature",
      "properties": {
        "hierarchy": [
          "tgn:1079703",
          "tgn:1000004",
          "tgn:1000962",
          "tgn:7000896",
          "tgn:1000120",
          "tgn:7029392"
        ],
        "placetype": [
          "aat:300008347"
        ],
        "id": 1079703,
        "name:xx": "Ōmino"
      }
    },
    {
      "geometry": {
        "type": "Point",
        "coordinates": [
          135.1,
          35.5833
        ]
      },
      "type": "Feature",
      "properties": {
        "hierarchy": [
          "tgn:1079704",
          "tgn:1000004",
          "tgn:1000998",
          "tgn:7000896",
          "tgn:1000120",
          "tgn:7029392"
        ],
        "placetype": [
          "aat:300008347"
        ],
        "id": 1079704,
        "name:xx": "Ōmiya"
      }
    },
    {
      "geometry": {
        "type": "Point",
        "coordinates": [
          143,
          44.5667
        ]
      },
      "type": "Feature",
      "properties": {
        "hierarchy": [
          "tgn:1079705",
          "tgn:1000985",
          "tgn:7016529",
          "tgn:7016531",
          "tgn:1000004",
          "tgn:1000120",
          "tgn:7029392"
        ],
        "placetype": [
          "aat:300008347"
        ],
        "id": 1079705,
        "name:xx": "Ōmu"
      }
    },
    {
      "geometry": {
        "type": "Point",
        "coordinates": [
          139.9667,
          35.9
        ]
      },
      "type": "Feature",
      "properties": {
        "hierarchy": [
          "tgn:1079707",
          "tgn:1000971",
          "tgn:1000004",
          "tgn:7000894",
          "tgn:1000120",
          "tgn:7029392"
        ],
        "placetype": [
          "aat:300008347"
        ],
        "id": 1079707,
        "name:xx": "Ōmuro"
      }
    },
    {
      "geometry": {
        "type": "Point",
        "coordinates": [
          130.4333,
          33.0333
        ]
      },
      "type": "Feature",
      "properties": {
        "hierarchy": [
          "tgn:1079708",
          "tgn:1000975",
          "tgn:1000004",
          "tgn:7000901",
          "tgn:1000120",
          "tgn:7029392"
        ],
        "placetype": [
          "aat:300008347"
        ],
        "id": 1079708,
        "name:xx": "Ōmuta"
      }
    },
    {
      "geometry": {
        "type": "Point",
        "coordinates": [
          139.6167,
          35.9167
        ]
      },
      "type": "Feature",
      "properties": {
        "hierarchy": [
          "tgn:1079709",
          "tgn:1000004",
          "tgn:7000894",
          "tgn:7016797",
          "tgn:1000120",
          "tgn:7029392"
        ],
        "placetype": [
          "aat:300008347"
        ],
        "id": 1079709,
        "name:xx": "Ōnari"
      }
    }
  ]
}
