{
  "geometry": {
    "type": "Point",
    "coordinates": [
      -110.6667,
      46.8333
    ]
  },
  "type": "Feature",
  "properties": {
    "hierarchy": [
      "tgn:2754840",
      "tgn:1000001",
      "tgn:7012149",
      "tgn:7007524",
      "tgn:7029392"
    ],
    "placetype": [
      "aat:300008706"
    ],
    "id": 2754840,
    "name:xx": "Weatherwax Creek"
  }
}
