{
  "geometry": {
    "type": "Point",
    "coordinates": [
      -85.75,
      46.2833
    ]
  },
  "type": "Feature",
  "properties": {
    "hierarchy": [
      "tgn:2222526",
      "tgn:1000001",
      "tgn:7012149",
      "tgn:2000972",
      "tgn:7007520",
      "tgn:7029392"
    ],
    "placetype": [
      "aat:300008347"
    ],
    "id": 2222526,
    "name:xx": "Carpenter Landing"
  }
}
