{
  "geometry": {
    "type": "Point",
    "coordinates": [
      -84.1667,
      38.3833
    ]
  },
  "type": "Feature",
  "properties": {
    "hierarchy": [
      "tgn:2530900",
      "tgn:1000001",
      "tgn:7012149",
      "tgn:1002458",
      "tgn:7007255",
      "tgn:7029392"
    ],
    "placetype": [
      "aat:300008706"
    ],
    "id": 2530900,
    "name:xx": "Mudlick Creek"
  }
}
