{
  "geometry": {
    "type": "Point",
    "coordinates": [
      -72.15,
      41.35
    ]
  },
  "type": "Feature",
  "properties": {
    "hierarchy": [
      "tgn:2490483",
      "tgn:1000001",
      "tgn:1002714",
      "tgn:7012149",
      "tgn:7007159",
      "tgn:7029392"
    ],
    "placetype": [
      "aat:300008697"
    ],
    "id": 2490483,
    "name:xx": "Manitock Spring"
  }
}
