{
  "geometry": {
    "type": "Point",
    "coordinates": [
      -120.25,
      47.6667
    ]
  },
  "type": "Feature",
  "properties": {
    "hierarchy": [
      "tgn:2374487",
      "tgn:1000001",
      "tgn:1002260",
      "tgn:7012149",
      "tgn:7007920",
      "tgn:7029392"
    ],
    "placetype": [
      "aat:300008761"
    ],
    "id": 2374487,
    "name:xx": "Hanan Canyon"
  }
}
