{
  "geometry": {
    "type": "Point",
    "coordinates": [
      -79.8667,
      33.8167
    ]
  },
  "type": "Feature",
  "properties": {
    "hierarchy": [
      "tgn:2240792",
      "tgn:1000001",
      "tgn:7012149",
      "tgn:2001769",
      "tgn:7007712",
      "tgn:7029392"
    ],
    "placetype": [
      "aat:300008699"
    ],
    "id": 2240792,
    "name:xx": "Clapp Swamp"
  }
}
