{
  "geometry": {
    "type": "Point",
    "coordinates": [
      -76.3333,
      36.9167
    ]
  },
  "type": "Feature",
  "properties": {
    "hierarchy": [
      "tgn:2265635",
      "tgn:1000001",
      "tgn:7012149",
      "tgn:7022210",
      "tgn:7007919",
      "tgn:7029392"
    ],
    "placetype": [
      "aat:300132348"
    ],
    "id": 2265635,
    "name:xx": "Craney Island Flats"
  }
}
