{
  "geometry": {
    "type": "Point",
    "coordinates": [
      30.75,
      29.166667
    ]
  },
  "type": "Feature",
  "properties": {
    "hierarchy": [
      "tgn:7537864",
      "tgn:7001242",
      "tgn:7001105",
      "tgn:7016833",
      "tgn:7029392"
    ],
    "placetype": [
      "aat:300008916"
    ],
    "name:en": "Shaykh Faraj, Ḩamrāyat ash",
    "id": 7537864
  }
}
