{
  "geometry": {
    "type": "Point",
    "coordinates": [
      -81.2833,
      38.9167
    ]
  },
  "type": "Feature",
  "properties": {
    "hierarchy": [
      "tgn:2564467",
      "tgn:1000001",
      "tgn:7012149",
      "tgn:2002302",
      "tgn:7013961",
      "tgn:7029392"
    ],
    "placetype": [
      "aat:300008699"
    ],
    "id": 2564467,
    "name:xx": "Pack Saddle Run"
  }
}
