{
  "geometry": {
    "type": "Point",
    "coordinates": [
      92.28842,
      24.570637
    ]
  },
  "type": "Feature",
  "properties": {
    "hierarchy": [
      "tgn:7579643",
      "tgn:1000004",
      "tgn:1001832",
      "tgn:7000198",
      "tgn:7029392"
    ],
    "placetype": [
      "aat:300008347"
    ],
    "name:en": "Sonākhira",
    "id": 7579643
  }
}
