{
  "geometry": {
    "type": "Point",
    "coordinates": [
      -85.0167,
      37.0667
    ]
  },
  "type": "Feature",
  "properties": {
    "hierarchy": [
      "tgn:2242899",
      "tgn:1000001",
      "tgn:7012149",
      "tgn:2000841",
      "tgn:7007255",
      "tgn:7029392"
    ],
    "placetype": [
      "aat:300008699"
    ],
    "id": 2242899,
    "name:xx": "Clear Fork"
  }
}
