{
  "geometry": {
    "type": "Point",
    "coordinates": [
      -164.9833,
      64.4667
    ]
  },
  "type": "Feature",
  "properties": {
    "hierarchy": [
      "tgn:2614529",
      "tgn:7006450",
      "tgn:1000001",
      "tgn:7012149",
      "tgn:2000079",
      "tgn:7029392"
    ],
    "placetype": [
      "aat:300008798"
    ],
    "id": 2614529,
    "name:xx": "Reindeer Hill"
  }
}
