{
  "geometry": {
    "type": "Point",
    "coordinates": [
      -70.0833,
      44.2333
    ]
  },
  "type": "Feature",
  "properties": {
    "hierarchy": [
      "tgn:2415392",
      "tgn:2000918",
      "tgn:1000001",
      "tgn:7012149",
      "tgn:7007515",
      "tgn:7029392"
    ],
    "placetype": [
      "aat:300008680"
    ],
    "id": 2415392,
    "name:xx": "Island Pond"
  }
}
