{
  "geometry": {
    "type": "Point",
    "coordinates": [
      75.6667,
      30.1667
    ]
  },
  "type": "Feature",
  "properties": {
    "hierarchy": [
      "tgn:1121068",
      "tgn:1000004",
      "tgn:7000198",
      "tgn:7029392"
    ],
    "placetype": [
      "aat:300008707"
    ],
    "id": 1121068,
    "name:xx": "Alaknanda"
  }
}
