{
  "geometry": {
    "type": "Point",
    "coordinates": [
      -110.2667,
      34.3333
    ]
  },
  "type": "Feature",
  "properties": {
    "hierarchy": [
      "tgn:2576101",
      "tgn:1000001",
      "tgn:7006451",
      "tgn:7012149",
      "tgn:2000099",
      "tgn:7029392"
    ],
    "placetype": [
      "aat:300008697"
    ],
    "id": 2576101,
    "name:xx": "Perkins Spring"
  }
}
