{
  "geometry": {
    "type": "Point",
    "coordinates": [
      -88.45,
      48.1333
    ]
  },
  "type": "Feature",
  "properties": {
    "hierarchy": [
      "tgn:2151150",
      "tgn:1000001",
      "tgn:7012149",
      "tgn:2000969",
      "tgn:7007520",
      "tgn:7029392"
    ],
    "placetype": [
      "aat:300008791"
    ],
    "id": 2151150,
    "name:xx": "Bat Island"
  }
}
