{
  "geometry": {
    "type": "Point",
    "coordinates": [
      76.761287,
      30.73304
    ]
  },
  "type": "Feature",
  "properties": {
    "hierarchy": [
      "tgn:7584944",
      "tgn:1000004",
      "tgn:7000200",
      "tgn:7000198",
      "tgn:7029392"
    ],
    "placetype": [
      "aat:300008347"
    ],
    "name:en": "Bajwāra",
    "id": 7584944
  }
}
