{
  "geometry": {
    "type": "Point",
    "coordinates": [
      -107.1333,
      36.0667
    ]
  },
  "type": "Feature",
  "properties": {
    "hierarchy": [
      "tgn:2640440",
      "tgn:1000001",
      "tgn:7012149",
      "tgn:2001451",
      "tgn:7007566",
      "tgn:7029392"
    ],
    "placetype": [
      "aat:300008699"
    ],
    "id": 2640440,
    "name:xx": "San Isidro Wash"
  }
}
