{
  "geometry": {
    "type": "Point",
    "coordinates": [
      106.0833,
      52.5333
    ]
  },
  "type": "Feature",
  "properties": {
    "hierarchy": [
      "tgn:1053126",
      "tgn:1003373",
      "tgn:1000004",
      "tgn:7018214",
      "tgn:7002435",
      "tgn:7029392"
    ],
    "placetype": [
      "aat:300008347"
    ],
    "id": 1053126,
    "name:xx": "Buguldeyka"
  }
}
