{
  "type": "FeatureCollection",
  "features": [
    {
      "geometry": {
        "type": "Point",
        "coordinates": [
          -85.7333,
          41.3
        ]
      },
      "type": "Feature",
      "properties": {
        "hierarchy": [
          "tgn:2660370",
          "tgn:1000001",
          "tgn:7012149",
          "tgn:1002557",
          "tgn:7007252",
          "tgn:7029392"
        ],
        "placetype": [
          "aat:300008680"
        ],
        "id": 2660370,
        "name:xx": "Shoe Lake"
      }
    },
    {
      "geometry": {
        "type": "Point",
        "coordinates": [
          -83.1833,
          42.7833
        ]
      },
      "type": "Feature",
      "properties": {
        "hierarchy": [
          "tgn:2660371",
          "tgn:1000001",
          "tgn:7012149",
          "tgn:1002737",
          "tgn:7007520",
          "tgn:7029392"
        ],
        "placetype": [
          "aat:300008680"
        ],
        "id": 2660371,
        "name:xx": "Shoe Lake"
      }
    },
    {
      "geometry": {
        "type": "Point",
        "coordinates": [
          -96.1667,
          46.8167
        ]
      },
      "type": "Feature",
      "properties": {
        "hierarchy": [
          "tgn:2660372",
          "tgn:2001001",
          "tgn:1000001",
          "tgn:7012149",
          "tgn:7007521",
          "tgn:7029392"
        ],
        "placetype": [
          "aat:300008680"
        ],
        "id": 2660372,
        "name:xx": "Shoe Lake"
      }
    },
    {
      "geometry": {
        "type": "Point",
        "coordinates": [
          -90.2333,
          48
        ]
      },
      "type": "Feature",
      "properties": {
        "hierarchy": [
          "tgn:2660373",
          "tgn:1000001",
          "tgn:2001014",
          "tgn:7012149",
          "tgn:7007521",
          "tgn:7029392"
        ],
        "placetype": [
          "aat:300008680"
        ],
        "id": 2660373,
        "name:xx": "Shoe Lake"
      }
    },
    {
      "geometry": {
        "type": "Point",
        "coordinates": [
          -80.5833,
          33.7667
        ]
      },
      "type": "Feature",
      "properties": {
        "hierarchy": [
          "tgn:2660374",
          "tgn:1000001",
          "tgn:7012149",
          "tgn:2001767",
          "tgn:7007712",
          "tgn:7029392"
        ],
        "placetype": [
          "aat:300008680"
        ],
        "id": 2660374,
        "name:xx": "Shoe Lake"
      }
    },
    {
      "geometry": {
        "type": "Point",
        "coordinates": [
          -121.3833,
          46.5833
        ]
      },
      "type": "Feature",
      "properties": {
        "hierarchy": [
          "tgn:2660375",
          "tgn:1000001",
          "tgn:7012149",
          "tgn:1003042",
          "tgn:7007920",
          "tgn:7029392"
        ],
        "placetype": [
          "aat:300008680"
        ],
        "id": 2660375,
        "name:xx": "Shoe Lake"
      }
    },
    {
      "geometry": {
        "type": "Point",
        "coordinates": [
          -123,
          47.4333
        ]
      },
      "type": "Feature",
      "properties": {
        "hierarchy": [
          "tgn:2660376",
          "tgn:1000001",
          "tgn:7012149",
          "tgn:1002645",
          "tgn:7007920",
          "tgn:7029392"
        ],
        "placetype": [
          "aat:300008680"
        ],
        "id": 2660376,
        "name:xx": "Shoe Lake"
      }
    },
    {
      "geometry": {
        "type": "Point",
        "coordinates": [
          -87.9833,
          43.9333
        ]
      },
      "type": "Feature",
      "properties": {
        "hierarchy": [
          "tgn:2660377",
          "tgn:1000001",
          "tgn:7012149",
          "tgn:2002335",
          "tgn:7007922",
          "tgn:7029392"
        ],
        "placetype": [
          "aat:300008680"
        ],
        "id": 2660377,
        "name:xx": "Shoe Lake"
      }
    },
    {
      "geometry": {
        "type": "Point",
        "coordinates": [
          -88.75,
          45.4167
        ]
      },
      "type": "Feature",
      "properties": {
        "hierarchy": [
          "tgn:2660378",
          "tgn:1000001",
          "tgn:2002323",
          "tgn:7012149",
          "tgn:7007922",
          "tgn:7029392"
        ],
        "placetype": [
          "aat:300008680"
        ],
        "id": 2660378,
        "name:xx": "Shoe Lake"
      }
    },
    {
      "geometry": {
        "type": "Point",
        "coordinates": [
          -109.1167,
          42.9
        ]
      },
      "type": "Feature",
      "properties": {
        "hierarchy": [
          "tgn:2660379",
          "tgn:1000001",
          "tgn:7012149",
          "tgn:2002371",
          "tgn:7007923",
          "tgn:7029392"
        ],
        "placetype": [
          "aat:300008680"
        ],
        "id": 2660379,
        "name:xx": "Shoe Lake"
      }
    }
  ]
}
