{
  "geometry": {
    "type": "Point",
    "coordinates": [
      88.238292,
      22.199556
    ]
  },
  "type": "Feature",
  "properties": {
    "hierarchy": [
      "tgn:7587415",
      "tgn:1000004",
      "tgn:7000198",
      "tgn:1001977",
      "tgn:7029392"
    ],
    "placetype": [
      "aat:300008347"
    ],
    "name:en": "Basuldānga",
    "id": 7587415
  }
}
