{
  "geometry": {
    "type": "Point",
    "coordinates": [
      -85.5333,
      34.9667
    ]
  },
  "type": "Feature",
  "properties": {
    "hierarchy": [
      "tgn:2130423",
      "tgn:1000001",
      "tgn:7012149",
      "tgn:7029392"
    ],
    "placetype": [
      "aat:300008761"
    ],
    "id": 2130423,
    "name:xx": "Alley Gulf"
  }
}
