{
  "geometry": {
    "type": "Point",
    "coordinates": [
      117.1833,
      39.8167
    ]
  },
  "type": "Feature",
  "properties": {
    "hierarchy": [
      "tgn:1068353",
      "tgn:1000004",
      "tgn:1000960",
      "tgn:1000111",
      "tgn:7029392"
    ],
    "placetype": [
      "aat:300008347"
    ],
    "id": 1068353,
    "name:xx": "Goutou"
  }
}
