{
  "geometry": {
    "type": "Point",
    "coordinates": [
      -110.3667,
      38.0833
    ]
  },
  "type": "Feature",
  "properties": {
    "hierarchy": [
      "tgn:2202688",
      "tgn:1000001",
      "tgn:2002109",
      "tgn:7012149",
      "tgn:7007827",
      "tgn:7029392"
    ],
    "placetype": [
      "aat:300008850"
    ],
    "id": 2202688,
    "name:xx": "Buckacre Point"
  }
}
