{
  "geometry": {
    "type": "Point",
    "coordinates": [
      -109.95,
      32.8167
    ]
  },
  "type": "Feature",
  "properties": {
    "hierarchy": [
      "tgn:2695933",
      "tgn:1000001",
      "tgn:7006451",
      "tgn:2000094",
      "tgn:7012149",
      "tgn:7029392"
    ],
    "placetype": [
      "aat:300006191"
    ],
    "id": 2695933,
    "name:xx": "Stockpond Tank"
  }
}
