{
  "geometry": {
    "type": "Point",
    "coordinates": [
      -76.8333,
      38.4833
    ]
  },
  "type": "Feature",
  "properties": {
    "hierarchy": [
      "tgn:2349237",
      "tgn:7016100",
      "tgn:1000001",
      "tgn:7012149",
      "tgn:7007516",
      "tgn:7029392"
    ],
    "placetype": [
      "aat:300008699"
    ],
    "id": 2349237,
    "name:xx": "Gilbert Swamp Run"
  }
}
