{
  "geometry": {
    "type": "Point",
    "coordinates": [
      -82.75,
      32.0833
    ]
  },
  "type": "Feature",
  "properties": {
    "hierarchy": [
      "tgn:2310850",
      "tgn:1000001",
      "tgn:7012149",
      "tgn:2000444",
      "tgn:7007248",
      "tgn:7029392"
    ],
    "placetype": [
      "aat:300008706"
    ],
    "id": 2310850,
    "name:xx": "Eddards Creek"
  }
}
