{
  "geometry": {
    "type": "Point",
    "coordinates": [
      -74.1667,
      42.0167
    ]
  },
  "type": "Feature",
  "properties": {
    "hierarchy": [
      "tgn:2125424",
      "tgn:1000001",
      "tgn:7012149",
      "tgn:1002961",
      "tgn:7007568",
      "tgn:7029392"
    ],
    "placetype": [
      "aat:300008798"
    ],
    "id": 2125424,
    "name:xx": "Acorn Hill"
  }
}
