{
  "geometry": {
    "type": "Point",
    "coordinates": [
      -105.3667,
      39.1333
    ]
  },
  "type": "Feature",
  "properties": {
    "hierarchy": [
      "tgn:2770763",
      "tgn:1000001",
      "tgn:7012149",
      "tgn:2000221",
      "tgn:7007158",
      "tgn:7029392"
    ],
    "placetype": [
      "aat:300008706"
    ],
    "id": 2770763,
    "name:xx": "Wildcat Creek"
  }
}
