{
  "geometry": {
    "type": "Point",
    "coordinates": [
      73.5333,
      45.9833
    ]
  },
  "type": "Feature",
  "properties": {
    "hierarchy": [
      "tgn:1055489",
      "tgn:1000004",
      "tgn:1003363",
      "tgn:7014786",
      "tgn:7029392"
    ],
    "placetype": [
      "aat:300008347",
      "aat:300008375"
    ],
    "id": 1055489,
    "name:xx": "Koktas"
  }
}
