{
  "geometry": {
    "type": "Point",
    "coordinates": [
      -76.75,
      42.0333
    ]
  },
  "type": "Feature",
  "properties": {
    "hierarchy": [
      "tgn:2651630",
      "tgn:1000001",
      "tgn:7012149",
      "tgn:7029392"
    ],
    "placetype": [
      "aat:300008706"
    ],
    "id": 2651630,
    "name:xx": "Seeley Creek"
  }
}
