{
  "geometry": {
    "type": "Point",
    "coordinates": [
      21.25,
      44.75
    ]
  },
  "type": "Feature",
  "properties": {
    "hierarchy": [
      "tgn:1127232",
      "tgn:1000003",
      "tgn:7006669",
      "tgn:7029392"
    ],
    "placetype": [
      "aat:300008707"
    ],
    "id": 1127232,
    "name:xx": "Mlava"
  }
}
