{
  "geometry": {
    "type": "Point",
    "coordinates": [
      -78.3833,
      42.65
    ]
  },
  "type": "Feature",
  "properties": {
    "hierarchy": [
      "tgn:2069915",
      "tgn:1000001",
      "tgn:7012149",
      "tgn:1003040",
      "tgn:7007568",
      "tgn:7029392"
    ],
    "placetype": [
      "aat:300008347"
    ],
    "id": 2069915,
    "name:xx": "Java Center"
  }
}
