{
  "type": "FeatureCollection",
  "features": [
    {
      "geometry": {
        "type": "Point",
        "coordinates": [
          -78.5167,
          35.2833
        ]
      },
      "type": "Feature",
      "properties": {
        "hierarchy": [
          "tgn:2428981",
          "tgn:1000001",
          "tgn:7012149",
          "tgn:2001509",
          "tgn:7007709",
          "tgn:7029392"
        ],
        "placetype": [
          "aat:300008699"
        ],
        "id": 2428981,
        "name:xx": "Jumping Run"
      }
    },
    {
      "geometry": {
        "type": "Point",
        "coordinates": [
          -78.2167,
          36.05
        ]
      },
      "type": "Feature",
      "properties": {
        "hierarchy": [
          "tgn:2428982",
          "tgn:1000001",
          "tgn:7012149",
          "tgn:7013940",
          "tgn:7007709",
          "tgn:7029392"
        ],
        "placetype": [
          "aat:300008699"
        ],
        "id": 2428982,
        "name:xx": "Jumping Run"
      }
    },
    {
      "geometry": {
        "type": "Point",
        "coordinates": [
          -78,
          36.0833
        ]
      },
      "type": "Feature",
      "properties": {
        "hierarchy": [
          "tgn:2428983",
          "tgn:1000001",
          "tgn:7012149",
          "tgn:2001522",
          "tgn:7007709",
          "tgn:7029392"
        ],
        "placetype": [
          "aat:300008699"
        ],
        "id": 2428983,
        "name:xx": "Jumping Run"
      }
    },
    {
      "geometry": {
        "type": "Point",
        "coordinates": [
          -83.5667,
          40.1
        ]
      },
      "type": "Feature",
      "properties": {
        "hierarchy": [
          "tgn:2428984",
          "tgn:1000001",
          "tgn:1002254",
          "tgn:7012149",
          "tgn:7007706",
          "tgn:7029392"
        ],
        "placetype": [
          "aat:300008699"
        ],
        "id": 2428984,
        "name:xx": "Jumping Run"
      }
    },
    {
      "geometry": {
        "type": "Point",
        "coordinates": [
          -79.65,
          33.5
        ]
      },
      "type": "Feature",
      "properties": {
        "hierarchy": [
          "tgn:2428985",
          "tgn:1000001",
          "tgn:7012149",
          "tgn:2001769",
          "tgn:7007712",
          "tgn:7029392"
        ],
        "placetype": [
          "aat:300008699"
        ],
        "id": 2428985,
        "name:xx": "Jumping Run"
      }
    },
    {
      "geometry": {
        "type": "Point",
        "coordinates": [
          -79.6833,
          37.2333
        ]
      },
      "type": "Feature",
      "properties": {
        "hierarchy": [
          "tgn:2428986",
          "tgn:1000001",
          "tgn:2002144",
          "tgn:7012149",
          "tgn:7007919",
          "tgn:7029392"
        ],
        "placetype": [
          "aat:300008699"
        ],
        "id": 2428986,
        "name:xx": "Jumping Run"
      }
    },
    {
      "geometry": {
        "type": "Point",
        "coordinates": [
          -78.0667,
          34.45
        ]
      },
      "type": "Feature",
      "properties": {
        "hierarchy": [
          "tgn:2428987",
          "tgn:1000001",
          "tgn:7012149",
          "tgn:2001527",
          "tgn:7007709",
          "tgn:7029392"
        ],
        "placetype": [
          "aat:300008699"
        ],
        "id": 2428987,
        "name:xx": "Jumping Run Branch"
      }
    },
    {
      "geometry": {
        "type": "Point",
        "coordinates": [
          -77.95,
          35.2
        ]
      },
      "type": "Feature",
      "properties": {
        "hierarchy": [
          "tgn:2428988",
          "tgn:1000001",
          "tgn:7012149",
          "tgn:2001552",
          "tgn:7007709",
          "tgn:7029392"
        ],
        "placetype": [
          "aat:300008699"
        ],
        "id": 2428988,
        "name:xx": "Jumping Run Branch"
      }
    },
    {
      "geometry": {
        "type": "Point",
        "coordinates": [
          -79.1333,
          35.1167
        ]
      },
      "type": "Feature",
      "properties": {
        "hierarchy": [
          "tgn:2428989",
          "tgn:1000001",
          "tgn:7012149",
          "tgn:7007709",
          "tgn:7029392"
        ],
        "placetype": [
          "aat:300008706"
        ],
        "id": 2428989,
        "name:xx": "Jumping Run Creek"
      }
    }
  ]
}
