{
  "geometry": {
    "type": "Point",
    "coordinates": [
      -99.7167,
      39.9667
    ]
  },
  "type": "Feature",
  "properties": {
    "hierarchy": [
      "tgn:2491306",
      "tgn:1000001",
      "tgn:7012149",
      "tgn:7029392"
    ],
    "placetype": [
      "aat:300008706"
    ],
    "id": 2491306,
    "name:xx": "Maple Creek"
  }
}
