{
  "geometry": {
    "type": "Point",
    "coordinates": [
      -88.5333,
      37.1833
    ]
  },
  "type": "Feature",
  "properties": {
    "hierarchy": [
      "tgn:2290724",
      "tgn:1000001",
      "tgn:7012149",
      "tgn:7007251",
      "tgn:7029392"
    ],
    "placetype": [
      "aat:300008706"
    ],
    "id": 2290724,
    "name:xx": "Dog Creek"
  }
}
