{
  "type": "FeatureCollection",
  "features": [
    {
      "geometry": {
        "type": "Point",
        "coordinates": [
          -89.7667,
          30.35
        ]
      },
      "type": "Feature",
      "properties": {
        "hierarchy": [
          "tgn:2745280",
          "tgn:1000001",
          "tgn:7012149",
          "tgn:2000905",
          "tgn:7007256",
          "tgn:7029392"
        ],
        "placetype": [
          "aat:300008699"
        ],
        "id": 2745280,
        "name:xx": "Vincent, Bayou"
      }
    },
    {
      "geometry": {
        "type": "Point",
        "coordinates": [
          -74.25,
          40.8
        ]
      },
      "type": "Feature",
      "properties": {
        "hierarchy": [
          "tgn:2745281",
          "tgn:1000001",
          "tgn:1002360",
          "tgn:7012149",
          "tgn:7007565",
          "tgn:7029392"
        ],
        "placetype": [
          "aat:300008680"
        ],
        "id": 2745281,
        "name:xx": "Vincent, Lake"
      }
    },
    {
      "geometry": {
        "type": "Point",
        "coordinates": [
          -135.8667,
          57.4
        ]
      },
      "type": "Feature",
      "properties": {
        "hierarchy": [
          "tgn:2745282",
          "tgn:7006450",
          "tgn:1000001",
          "tgn:7012149",
          "tgn:2124002",
          "tgn:7029392"
        ],
        "placetype": [
          "aat:300008850"
        ],
        "id": 2745282,
        "name:xx": "Vincent, Point"
      }
    },
    {
      "geometry": {
        "type": "Point",
        "coordinates": [
          -115.8,
          41.8667
        ]
      },
      "type": "Feature",
      "properties": {
        "hierarchy": [
          "tgn:2745283",
          "tgn:1000001",
          "tgn:2001411",
          "tgn:7012149",
          "tgn:7007526",
          "tgn:7029392"
        ],
        "placetype": [
          "aat:300008761"
        ],
        "id": 2745283,
        "name:xx": "Vincenti Canyon"
      }
    },
    {
      "geometry": {
        "type": "Point",
        "coordinates": [
          -74.75,
          39.9333
        ]
      },
      "type": "Feature",
      "properties": {
        "hierarchy": [
          "tgn:2745284",
          "tgn:1002215",
          "tgn:1000001",
          "tgn:7012149",
          "tgn:7007565",
          "tgn:7029392"
        ],
        "placetype": [
          "aat:300006191"
        ],
        "id": 2745284,
        "name:xx": "Vincentown Millpond"
      }
    },
    {
      "geometry": {
        "type": "Point",
        "coordinates": [
          -84.4833,
          31.6
        ]
      },
      "type": "Feature",
      "properties": {
        "hierarchy": [
          "tgn:2745285",
          "tgn:1000001",
          "tgn:2000310",
          "tgn:7012149",
          "tgn:7007248",
          "tgn:7029392"
        ],
        "placetype": [
          "aat:300008699"
        ],
        "id": 2745285,
        "name:xx": "Vincey Branch"
      }
    },
    {
      "geometry": {
        "type": "Point",
        "coordinates": [
          -90.0667,
          36.15
        ]
      },
      "type": "Feature",
      "properties": {
        "hierarchy": [
          "tgn:2745288",
          "tgn:1000001",
          "tgn:7012149",
          "tgn:2001197",
          "tgn:7007523",
          "tgn:7029392"
        ],
        "placetype": [
          "aat:300008347"
        ],
        "id": 2745288,
        "name:xx": "Vincit"
      }
    },
    {
      "geometry": {
        "type": "Point",
        "coordinates": [
          -107.2,
          34.1
        ]
      },
      "type": "Feature",
      "properties": {
        "hierarchy": [
          "tgn:2745289",
          "tgn:1000001",
          "tgn:7012149",
          "tgn:2001456",
          "tgn:7007566",
          "tgn:7029392"
        ],
        "placetype": [
          "aat:300000390"
        ],
        "id": 2745289,
        "name:xx": "Vindicator"
      }
    }
  ]
}
