{
  "geometry": {
    "type": "Point",
    "coordinates": [
      -98.4333,
      31.05
    ]
  },
  "type": "Feature",
  "properties": {
    "hierarchy": [
      "tgn:2407671",
      "tgn:1000001",
      "tgn:7012149",
      "tgn:7007826",
      "tgn:7029392"
    ],
    "placetype": [
      "aat:300008761"
    ],
    "id": 2407671,
    "name:xx": "Hurley Hollow"
  }
}
