{
  "geometry": {
    "type": "Point",
    "coordinates": [
      7.2667,
      47.3333
    ]
  },
  "type": "Feature",
  "properties": {
    "hierarchy": [
      "tgn:1063927",
      "tgn:7003749",
      "tgn:1000003",
      "tgn:7011731",
      "tgn:7029392"
    ],
    "placetype": [
      "aat:300008347"
    ],
    "id": 1063927,
    "name:xx": "Bassecourt"
  }
}
