{
  "geometry": {
    "type": "Point",
    "coordinates": [
      7.7167,
      12.6833
    ]
  },
  "type": "Feature",
  "properties": {
    "hierarchy": [
      "tgn:1091927",
      "tgn:7001242",
      "tgn:7015580",
      "tgn:1000182",
      "tgn:7029392"
    ],
    "placetype": [
      "aat:300008347"
    ],
    "id": 1091927,
    "name:xx": "Cheranchi"
  }
}
