{
  "type": "FeatureCollection",
  "features": [
    {
      "geometry": {
        "type": "Point",
        "coordinates": [
          -90.9167,
          38.1667
        ]
      },
      "type": "Feature",
      "properties": {
        "hierarchy": [
          "tgn:2215010",
          "tgn:1000001",
          "tgn:7012149",
          "tgn:7007523",
          "tgn:7029392"
        ],
        "placetype": [
          "aat:300008699"
        ],
        "id": 2215010,
        "name:xx": "California Branch"
      }
    },
    {
      "geometry": {
        "type": "Point",
        "coordinates": [
          -81.9833,
          35.5333
        ]
      },
      "type": "Feature",
      "properties": {
        "hierarchy": [
          "tgn:2215011",
          "tgn:1000001",
          "tgn:7012149",
          "tgn:2001537",
          "tgn:7007709",
          "tgn:7029392"
        ],
        "placetype": [
          "aat:300008699"
        ],
        "id": 2215011,
        "name:xx": "California Branch"
      }
    },
    {
      "geometry": {
        "type": "Point",
        "coordinates": [
          -82.6833,
          39.4667
        ]
      },
      "type": "Feature",
      "properties": {
        "hierarchy": [
          "tgn:2215012",
          "tgn:1000001",
          "tgn:7012149",
          "tgn:2001613",
          "tgn:7007706",
          "tgn:7029392"
        ],
        "placetype": [
          "aat:300008699"
        ],
        "id": 2215012,
        "name:xx": "California Branch"
      }
    },
    {
      "geometry": {
        "type": "Point",
        "coordinates": [
          -82.8,
          34.9333
        ]
      },
      "type": "Feature",
      "properties": {
        "hierarchy": [
          "tgn:2215013",
          "tgn:1000001",
          "tgn:7012149",
          "tgn:2001763",
          "tgn:7007712",
          "tgn:7029392"
        ],
        "placetype": [
          "aat:300008699"
        ],
        "id": 2215013,
        "name:xx": "California Branch"
      }
    },
    {
      "geometry": {
        "type": "Point",
        "coordinates": [
          -80.0333,
          33.1667
        ]
      },
      "type": "Feature",
      "properties": {
        "hierarchy": [
          "tgn:2215014",
          "tgn:2001732",
          "tgn:1000001",
          "tgn:7012149",
          "tgn:7007712",
          "tgn:7029392"
        ],
        "placetype": [
          "aat:300008699"
        ],
        "id": 2215014,
        "name:xx": "California Branch"
      }
    },
    {
      "geometry": {
        "type": "Point",
        "coordinates": [
          -87.6167,
          35.15
        ]
      },
      "type": "Feature",
      "properties": {
        "hierarchy": [
          "tgn:2215015",
          "tgn:1000001",
          "tgn:7012149",
          "tgn:7007825",
          "tgn:7029392"
        ],
        "placetype": [
          "aat:300008699"
        ],
        "id": 2215015,
        "name:xx": "California Branch"
      }
    },
    {
      "geometry": {
        "type": "Point",
        "coordinates": [
          -68.4667,
          47.1333
        ]
      },
      "type": "Feature",
      "properties": {
        "hierarchy": [
          "tgn:2215016",
          "tgn:2000919",
          "tgn:1000001",
          "tgn:7012149",
          "tgn:7007515",
          "tgn:7029392"
        ],
        "placetype": [
          "aat:300008699"
        ],
        "id": 2215016,
        "name:xx": "California Brook"
      }
    },
    {
      "geometry": {
        "type": "Point",
        "coordinates": [
          -72.3667,
          42.9
        ]
      },
      "type": "Feature",
      "properties": {
        "hierarchy": [
          "tgn:2215017",
          "tgn:7019618",
          "tgn:1000001",
          "tgn:7012149",
          "tgn:7007564",
          "tgn:7029392"
        ],
        "placetype": [
          "aat:300008699"
        ],
        "id": 2215017,
        "name:xx": "California Brook"
      }
    },
    {
      "geometry": {
        "type": "Point",
        "coordinates": [
          -77.5667,
          41.9667
        ]
      },
      "type": "Feature",
      "properties": {
        "hierarchy": [
          "tgn:2215018",
          "tgn:1000001",
          "tgn:7012149",
          "tgn:1002945",
          "tgn:7007710",
          "tgn:7029392"
        ],
        "placetype": [
          "aat:300008699"
        ],
        "id": 2215018,
        "name:xx": "California Brook"
      }
    },
    {
      "geometry": {
        "type": "Point",
        "coordinates": [
          -73.65,
          40.5833
        ]
      },
      "type": "Feature",
      "properties": {
        "hierarchy": [
          "tgn:2215019",
          "tgn:1000001",
          "tgn:7012149",
          "tgn:1002708",
          "tgn:7007568",
          "tgn:7029392"
        ],
        "placetype": [
          "aat:300006075"
        ],
        "id": 2215019,
        "name:xx": "California Canal"
      }
    }
  ]
}
