{
  "geometry": {
    "type": "Point",
    "coordinates": [
      -84.4167,
      34.0167
    ]
  },
  "type": "Feature",
  "properties": {
    "hierarchy": [
      "tgn:2518662",
      "tgn:1000001",
      "tgn:2000324",
      "tgn:7012149",
      "tgn:7007248",
      "tgn:7029392"
    ],
    "placetype": [
      "aat:300006191"
    ],
    "id": 2518662,
    "name:xx": "Mitchell Lake"
  }
}
