{
  "geometry": {
    "type": "Point",
    "coordinates": [
      -91.1667,
      35.95
    ]
  },
  "type": "Feature",
  "properties": {
    "hierarchy": [
      "tgn:2659974",
      "tgn:1000001",
      "tgn:7016172",
      "tgn:7012149",
      "tgn:2000142",
      "tgn:7029392"
    ],
    "placetype": [
      "aat:300132316"
    ],
    "id": 2659974,
    "name:xx": "Shirey Bay"
  }
}
