{
  "type": "FeatureCollection",
  "features": [
    {
      "geometry": {
        "type": "Point",
        "coordinates": [
          69.1667,
          46.9333
        ]
      },
      "type": "Feature",
      "properties": {
        "hierarchy": [
          "tgn:1107851",
          "tgn:1000004",
          "tgn:1003363",
          "tgn:7014786",
          "tgn:7029392"
        ],
        "placetype": [
          "aat:300008777"
        ],
        "id": 1107851,
        "name:xx": "Azat, Gora"
      }
    },
    {
      "geometry": {
        "type": "Point",
        "coordinates": [
          7.316667,
          51.383333
        ]
      },
      "type": "Feature",
      "properties": {
        "hierarchy": [
          "tgn:1107852",
          "tgn:1000003",
          "tgn:7003677",
          "tgn:7000084",
          "tgn:7029392"
        ],
        "placetype": [
          "aat:300008777"
        ],
        "id": 1107852,
        "name:xx": "Böll Berg"
      }
    },
    {
      "geometry": {
        "type": "Point",
        "coordinates": [
          12.9,
          52.333333
        ]
      },
      "type": "Feature",
      "properties": {
        "hierarchy": [
          "tgn:1107854",
          "tgn:7000096",
          "tgn:1000003",
          "tgn:7000084",
          "tgn:7029392"
        ],
        "placetype": [
          "aat:300008777"
        ],
        "id": 1107854,
        "name:xx": "Bachten-Berg"
      }
    },
    {
      "geometry": {
        "type": "Point",
        "coordinates": [
          13.116667,
          54.6
        ]
      },
      "type": "Feature",
      "properties": {
        "hierarchy": [
          "tgn:1107855",
          "tgn:1000003",
          "tgn:7000094",
          "tgn:7000084",
          "tgn:7029392"
        ],
        "placetype": [
          "aat:300008777"
        ],
        "id": 1107855,
        "name:xx": "Bakenberg"
      }
    }
  ]
}
