{
  "geometry": {
    "type": "Point",
    "coordinates": [
      5.8833,
      59.35
    ]
  },
  "type": "Feature",
  "properties": {
    "hierarchy": [
      "tgn:1048672",
      "tgn:7003652",
      "tgn:1000003",
      "tgn:1000088",
      "tgn:7029392"
    ],
    "placetype": [
      "aat:300008347"
    ],
    "id": 1048672,
    "name:xx": "Nedstrand"
  }
}
