{
  "type": "FeatureCollection",
  "features": [
    {
      "geometry": {
        "type": "Point",
        "coordinates": [
          -103.45,
          20.7
        ]
      },
      "type": "Feature",
      "properties": {
        "hierarchy": [
          "tgn:7384270",
          "tgn:7005586",
          "tgn:1000001",
          "tgn:7005560",
          "tgn:7029392"
        ],
        "placetype": [
          "aat:300007783"
        ],
        "id": 7384270,
        "name:xx": "Ocotán"
      }
    },
    {
      "geometry": {
        "type": "Point",
        "coordinates": [
          -94.833333,
          18.283333
        ]
      },
      "type": "Feature",
      "properties": {
        "hierarchy": [
          "tgn:7384271",
          "tgn:1000001",
          "tgn:7005599",
          "tgn:7005560",
          "tgn:7029392"
        ],
        "placetype": [
          "aat:300008347"
        ],
        "id": 7384271,
        "name:xx": "Ocotal Grande"
      }
    },
    {
      "geometry": {
        "type": "Point",
        "coordinates": [
          -94.8,
          18.3
        ]
      },
      "type": "Feature",
      "properties": {
        "hierarchy": [
          "tgn:7384272",
          "tgn:1000001",
          "tgn:7005599",
          "tgn:7005560",
          "tgn:7029392"
        ],
        "placetype": [
          "aat:300008347"
        ],
        "id": 7384272,
        "name:xx": "Ocotal Chico"
      }
    },
    {
      "geometry": {
        "type": "Point",
        "coordinates": [
          -91.45,
          16.816667
        ]
      },
      "type": "Feature",
      "properties": {
        "hierarchy": [
          "tgn:7384273",
          "tgn:7005580",
          "tgn:1000001",
          "tgn:7005560",
          "tgn:7029392"
        ],
        "placetype": [
          "aat:300008680"
        ],
        "id": 7384273,
        "name:xx": "Ocotal, Laguna"
      }
    },
    {
      "geometry": {
        "type": "Point",
        "coordinates": [
          -98.5,
          22.9
        ]
      },
      "type": "Feature",
      "properties": {
        "hierarchy": [
          "tgn:7384274",
          "tgn:1000001",
          "tgn:7005597",
          "tgn:7005560",
          "tgn:7029392"
        ],
        "placetype": [
          "aat:300008347"
        ],
        "id": 7384274,
        "name:xx": "Ocotal"
      }
    },
    {
      "geometry": {
        "type": "Point",
        "coordinates": [
          -98.316667,
          20.6
        ]
      },
      "type": "Feature",
      "properties": {
        "hierarchy": [
          "tgn:7384275",
          "tgn:1000001",
          "tgn:7005599",
          "tgn:7005560",
          "tgn:7029392"
        ],
        "placetype": [
          "aat:300008347"
        ],
        "id": 7384275,
        "name:xx": "Ocotal"
      }
    },
    {
      "geometry": {
        "type": "Point",
        "coordinates": [
          -95.166667,
          16.783333
        ]
      },
      "type": "Feature",
      "properties": {
        "hierarchy": [
          "tgn:7384276",
          "tgn:1000001",
          "tgn:7005591",
          "tgn:7005560",
          "tgn:7029392"
        ],
        "placetype": [
          "aat:300008347"
        ],
        "id": 7384276,
        "name:xx": "Ocotal"
      }
    },
    {
      "geometry": {
        "type": "Point",
        "coordinates": [
          -94.65,
          16.633333
        ]
      },
      "type": "Feature",
      "properties": {
        "hierarchy": [
          "tgn:7384277",
          "tgn:1000001",
          "tgn:7005591",
          "tgn:7005560",
          "tgn:7029392"
        ],
        "placetype": [
          "aat:300008347"
        ],
        "id": 7384277,
        "name:xx": "Ocotal"
      }
    },
    {
      "geometry": {
        "type": "Point",
        "coordinates": [
          -96.15,
          16.116667
        ]
      },
      "type": "Feature",
      "properties": {
        "hierarchy": [
          "tgn:7384279",
          "tgn:1000001",
          "tgn:7005591",
          "tgn:7005560",
          "tgn:7029392"
        ],
        "placetype": [
          "aat:300008347"
        ],
        "id": 7384279,
        "name:xx": "Ocotal"
      }
    }
  ]
}
