{
  "geometry": {
    "type": "Point",
    "coordinates": [
      -93.7333,
      45.4333
    ]
  },
  "type": "Feature",
  "properties": {
    "hierarchy": [
      "tgn:2055180",
      "tgn:1000001",
      "tgn:7012149",
      "tgn:2001069",
      "tgn:7007521",
      "tgn:7029392"
    ],
    "placetype": [
      "aat:300008347"
    ],
    "id": 2055180,
    "name:xx": "Orrock"
  }
}
