{
  "type": "FeatureCollection",
  "features": [
    {
      "geometry": {
        "type": "Point",
        "coordinates": [
          -88.2667,
          38.5333
        ]
      },
      "type": "Feature",
      "properties": {
        "hierarchy": [
          "tgn:2317280",
          "tgn:1000001",
          "tgn:7012149",
          "tgn:1003003",
          "tgn:7007251",
          "tgn:7029392"
        ],
        "placetype": [
          "aat:300008706"
        ],
        "id": 2317280,
        "name:xx": "Emmons Creek"
      }
    },
    {
      "geometry": {
        "type": "Point",
        "coordinates": [
          -96.4,
          39.0833
        ]
      },
      "type": "Feature",
      "properties": {
        "hierarchy": [
          "tgn:2317281",
          "tgn:1000001",
          "tgn:7012149",
          "tgn:7007254",
          "tgn:7029392"
        ],
        "placetype": [
          "aat:300008706"
        ],
        "id": 2317281,
        "name:xx": "Emmons Creek"
      }
    },
    {
      "geometry": {
        "type": "Point",
        "coordinates": [
          -114.35,
          48.0167
        ]
      },
      "type": "Feature",
      "properties": {
        "hierarchy": [
          "tgn:2317282",
          "tgn:1000001",
          "tgn:7012149",
          "tgn:2001274",
          "tgn:7007524",
          "tgn:7029392"
        ],
        "placetype": [
          "aat:300008706"
        ],
        "id": 2317282,
        "name:xx": "Emmons Creek"
      }
    },
    {
      "geometry": {
        "type": "Point",
        "coordinates": [
          -89.25,
          44.3
        ]
      },
      "type": "Feature",
      "properties": {
        "hierarchy": [
          "tgn:2317283",
          "tgn:1000001",
          "tgn:7012149",
          "tgn:7007922",
          "tgn:7029392"
        ],
        "placetype": [
          "aat:300008706"
        ],
        "id": 2317283,
        "name:xx": "Emmons Creek"
      }
    },
    {
      "geometry": {
        "type": "Point",
        "coordinates": [
          -83.3833,
          42.0167
        ]
      },
      "type": "Feature",
      "properties": {
        "hierarchy": [
          "tgn:2317284",
          "tgn:1000001",
          "tgn:7012149",
          "tgn:1002679",
          "tgn:7007520",
          "tgn:7029392"
        ],
        "placetype": [
          "aat:300008699"
        ],
        "id": 2317284,
        "name:xx": "Emmons Drain"
      }
    },
    {
      "geometry": {
        "type": "Point",
        "coordinates": [
          -121.7,
          46.85
        ]
      },
      "type": "Feature",
      "properties": {
        "hierarchy": [
          "tgn:2317285",
          "tgn:1000001",
          "tgn:7012149",
          "tgn:1002785",
          "tgn:7007920",
          "tgn:7029392"
        ],
        "placetype": [
          "aat:300008835"
        ],
        "id": 2317285,
        "name:xx": "Emmons Glacier"
      }
    },
    {
      "geometry": {
        "type": "Point",
        "coordinates": [
          -88.5,
          35.1667
        ]
      },
      "type": "Feature",
      "properties": {
        "hierarchy": [
          "tgn:2317286",
          "tgn:1000001",
          "tgn:7012149",
          "tgn:7022544",
          "tgn:7007825",
          "tgn:7029392"
        ],
        "placetype": [
          "aat:300008761"
        ],
        "id": 2317286,
        "name:xx": "Emmons Hollow"
      }
    },
    {
      "geometry": {
        "type": "Point",
        "coordinates": [
          -135.5333,
          57.6
        ]
      },
      "type": "Feature",
      "properties": {
        "hierarchy": [
          "tgn:2317287",
          "tgn:7006450",
          "tgn:1000001",
          "tgn:7012149",
          "tgn:2124002",
          "tgn:7029392"
        ],
        "placetype": [
          "aat:300008791"
        ],
        "id": 2317287,
        "name:xx": "Emmons Island"
      }
    },
    {
      "geometry": {
        "type": "Point",
        "coordinates": [
          -162.0833,
          55.3
        ]
      },
      "type": "Feature",
      "properties": {
        "hierarchy": [
          "tgn:2317288",
          "tgn:7030515",
          "tgn:7006450",
          "tgn:1000001",
          "tgn:7012149",
          "tgn:7029392"
        ],
        "placetype": [
          "aat:300008680"
        ],
        "id": 2317288,
        "name:xx": "Emmons Lake"
      }
    },
    {
      "geometry": {
        "type": "Point",
        "coordinates": [
          -85.5,
          42.7833
        ]
      },
      "type": "Feature",
      "properties": {
        "hierarchy": [
          "tgn:2317289",
          "tgn:1000001",
          "tgn:7012149",
          "tgn:1002540",
          "tgn:7007520",
          "tgn:7029392"
        ],
        "placetype": [
          "aat:300008680"
        ],
        "id": 2317289,
        "name:xx": "Emmons Lake"
      }
    }
  ]
}
