{
  "geometry": {
    "type": "Point",
    "coordinates": [
      -76.5333,
      43.3167
    ]
  },
  "type": "Feature",
  "properties": {
    "hierarchy": [
      "tgn:2312374",
      "tgn:1000001",
      "tgn:7012149",
      "tgn:7007568",
      "tgn:7029392"
    ],
    "placetype": [
      "aat:300008706"
    ],
    "id": 2312374,
    "name:xx": "Eightmile Creek"
  }
}
