{
  "geometry": {
    "type": "Point",
    "coordinates": [
      120.6041,
      23.9284
    ]
  },
  "type": "Feature",
  "properties": {
    "hierarchy": [
      "tgn:7470390",
      "tgn:7488858",
      "tgn:1000004",
      "tgn:1000141",
      "tgn:7029392"
    ],
    "placetype": [
      "aat:300008347"
    ],
    "id": 7470390,
    "name:xx": "Qizitou"
  }
}
