{
  "geometry": {
    "type": "Point",
    "coordinates": [
      -72.0833,
      44.4167
    ]
  },
  "type": "Feature",
  "properties": {
    "hierarchy": [
      "tgn:2600901",
      "tgn:2002131",
      "tgn:1000001",
      "tgn:7012149",
      "tgn:7007828",
      "tgn:7029392"
    ],
    "placetype": [
      "aat:300008798"
    ],
    "id": 2600901,
    "name:xx": "Pumpkin Hill"
  }
}
