{
  "geometry": {
    "type": "Point",
    "coordinates": [
      -101.2333,
      35.0167
    ]
  },
  "type": "Feature",
  "properties": {
    "hierarchy": [
      "tgn:2500204",
      "tgn:1000001",
      "tgn:7012149",
      "tgn:7007826",
      "tgn:7029392"
    ],
    "placetype": [
      "aat:300008706"
    ],
    "id": 2500204,
    "name:xx": "McCullum Creek"
  }
}
