{
  "geometry": {
    "type": "Point",
    "coordinates": [
      -76.7167,
      35.3333
    ]
  },
  "type": "Feature",
  "properties": {
    "hierarchy": [
      "tgn:2708975",
      "tgn:1000001",
      "tgn:7013368",
      "tgn:7012149",
      "tgn:7007709",
      "tgn:7029392"
    ],
    "placetype": [
      "aat:300006191"
    ],
    "id": 2708975,
    "name:xx": "T G Slimes Pond Number One"
  }
}
