{
  "geometry": {
    "type": "Point",
    "coordinates": [
      -60.5167,
      -38.9333
    ]
  },
  "type": "Feature",
  "properties": {
    "hierarchy": [
      "tgn:1128923",
      "tgn:1001160",
      "tgn:7006477",
      "tgn:1000002",
      "tgn:7029392"
    ],
    "placetype": [
      "aat:300008707"
    ],
    "id": 1128923,
    "name:xx": "Quequén Salado, Río"
  }
}
