{
  "geometry": {
    "type": "Point",
    "coordinates": [
      -116.3333,
      32.6833
    ]
  },
  "type": "Feature",
  "properties": {
    "hierarchy": [
      "tgn:2012238",
      "tgn:1000001",
      "tgn:7012149",
      "tgn:7007157",
      "tgn:1002858",
      "tgn:7029392"
    ],
    "placetype": [
      "aat:300008347"
    ],
    "id": 2012238,
    "name:xx": "Live Oak Springs"
  }
}
