{
  "geometry": {
    "type": "Point",
    "coordinates": [
      -81.9167,
      37.9667
    ]
  },
  "type": "Feature",
  "properties": {
    "hierarchy": [
      "tgn:2371400",
      "tgn:1000001",
      "tgn:7012149",
      "tgn:2002273",
      "tgn:7013961",
      "tgn:7029392"
    ],
    "placetype": [
      "aat:300008699"
    ],
    "id": 2371400,
    "name:xx": "Hainer Branch"
  }
}
