{
  "geometry": {
    "type": "Point",
    "coordinates": [
      -123.65,
      48.8667
    ]
  },
  "type": "Feature",
  "properties": {
    "hierarchy": [
      "tgn:1013465",
      "tgn:7005735",
      "tgn:7005685",
      "tgn:1000001",
      "tgn:7013409",
      "tgn:7029392"
    ],
    "placetype": [
      "aat:300008347"
    ],
    "id": 1013465,
    "name:xx": "Crofton"
  }
}
