{
  "geometry": {
    "type": "Point",
    "coordinates": [
      -118.8167,
      35.4833
    ]
  },
  "type": "Feature",
  "properties": {
    "hierarchy": [
      "tgn:2602378",
      "tgn:1000001",
      "tgn:7012149",
      "tgn:1002545",
      "tgn:7007157",
      "tgn:7029392"
    ],
    "placetype": [
      "aat:300266640"
    ],
    "id": 2602378,
    "name:xx": "Pyramid Hill"
  }
}
