{
  "geometry": {
    "type": "Point",
    "coordinates": [
      -109.15,
      33.95
    ]
  },
  "type": "Feature",
  "properties": {
    "hierarchy": [
      "tgn:2762030",
      "tgn:2000090",
      "tgn:1000001",
      "tgn:7006451",
      "tgn:7012149",
      "tgn:7029392"
    ],
    "placetype": [
      "aat:300006191"
    ],
    "id": 2762030,
    "name:xx": "West Section Thirty-five Tank"
  }
}
