{
  "geometry": {
    "type": "Point",
    "coordinates": [
      -72.0667,
      41.4333
    ]
  },
  "type": "Feature",
  "properties": {
    "hierarchy": [
      "tgn:2497981",
      "tgn:1000001",
      "tgn:1002714",
      "tgn:7012149",
      "tgn:7007159",
      "tgn:7029392"
    ],
    "placetype": [
      "aat:300008798"
    ],
    "id": 2497981,
    "name:xx": "Maynard Hill"
  }
}
