{
  "geometry": {
    "type": "Point",
    "coordinates": [
      -82.8667,
      35.1167
    ]
  },
  "type": "Feature",
  "properties": {
    "hierarchy": [
      "tgn:2341812",
      "tgn:1000001",
      "tgn:7012149",
      "tgn:2001544",
      "tgn:7007709",
      "tgn:7029392"
    ],
    "placetype": [
      "aat:300008706"
    ],
    "id": 2341812,
    "name:xx": "Frozen Creek"
  }
}
