{
  "geometry": {
    "type": "Point",
    "coordinates": [
      -106.25,
      43.5167
    ]
  },
  "type": "Feature",
  "properties": {
    "hierarchy": [
      "tgn:2276911",
      "tgn:1000001",
      "tgn:7012149",
      "tgn:2002374",
      "tgn:7007923",
      "tgn:7029392"
    ],
    "placetype": [
      "aat:300008699"
    ],
    "id": 2276911,
    "name:xx": "Davis Branch"
  }
}
