{
  "geometry": {
    "type": "Point",
    "coordinates": [
      -113.6833,
      48.55
    ]
  },
  "type": "Feature",
  "properties": {
    "hierarchy": [
      "tgn:2718201",
      "tgn:1000001",
      "tgn:7012149",
      "tgn:2001274",
      "tgn:7007524",
      "tgn:7029392"
    ],
    "placetype": [
      "aat:300008706"
    ],
    "id": 2718201,
    "name:xx": "Thompson Creek"
  }
}
