{
  "type": "FeatureCollection",
  "features": [
    {
      "geometry": {
        "type": "Point",
        "coordinates": [
          94.1833,
          19.1
        ]
      },
      "type": "Feature",
      "properties": {
        "hierarchy": [
          "tgn:1066261",
          "tgn:7002212",
          "tgn:1000004",
          "tgn:1000108",
          "tgn:7029392"
        ],
        "placetype": [
          "aat:300008347"
        ],
        "id": 1066261,
        "name:xx": "Sabyin"
      }
    },
    {
      "geometry": {
        "type": "Point",
        "coordinates": [
          95.9333,
          21.9167
        ]
      },
      "type": "Feature",
      "properties": {
        "hierarchy": [
          "tgn:1066262",
          "tgn:1000004",
          "tgn:1002109",
          "tgn:1000108",
          "tgn:7029392"
        ],
        "placetype": [
          "aat:300008347",
          "aat:300387219",
          "aat:300387220",
          "aat:300008375",
          "aat:300120599"
        ],
        "id": 1066262,
        "name:xx": "Sagaing"
      }
    },
    {
      "geometry": {
        "type": "Point",
        "coordinates": [
          94.6667,
          20.5
        ]
      },
      "type": "Feature",
      "properties": {
        "hierarchy": [
          "tgn:1066263",
          "tgn:1000004",
          "tgn:1002093",
          "tgn:1000108",
          "tgn:7029392"
        ],
        "placetype": [
          "aat:300008347"
        ],
        "id": 1066263,
        "name:xx": "Salin"
      }
    },
    {
      "geometry": {
        "type": "Point",
        "coordinates": [
          95.1167,
          21.9667
        ]
      },
      "type": "Feature",
      "properties": {
        "hierarchy": [
          "tgn:1066264",
          "tgn:1000004",
          "tgn:1002109",
          "tgn:1000108",
          "tgn:7029392"
        ],
        "placetype": [
          "aat:300008347"
        ],
        "id": 1066264,
        "name:xx": "Salingyi"
      }
    },
    {
      "geometry": {
        "type": "Point",
        "coordinates": [
          96.9667,
          20.1167
        ]
      },
      "type": "Feature",
      "properties": {
        "hierarchy": [
          "tgn:1066265",
          "tgn:1000004",
          "tgn:7002190",
          "tgn:1000108",
          "tgn:7029392"
        ],
        "placetype": [
          "aat:300008347"
        ],
        "id": 1066265,
        "name:xx": "Samka"
      }
    },
    {
      "geometry": {
        "type": "Point",
        "coordinates": [
          94.3333,
          18.4667
        ]
      },
      "type": "Feature",
      "properties": {
        "hierarchy": [
          "tgn:1066266",
          "tgn:7002212",
          "tgn:1000004",
          "tgn:1000108",
          "tgn:7029392"
        ],
        "placetype": [
          "aat:300008347"
        ],
        "id": 1066266,
        "name:xx": "Sandoway"
      }
    },
    {
      "geometry": {
        "type": "Point",
        "coordinates": [
          94.5,
          17.7667
        ]
      },
      "type": "Feature",
      "properties": {
        "hierarchy": [
          "tgn:1066267",
          "tgn:7002212",
          "tgn:1000004",
          "tgn:1000108",
          "tgn:7029392"
        ],
        "placetype": [
          "aat:300008347"
        ],
        "id": 1066267,
        "name:xx": "Satthwa"
      }
    },
    {
      "geometry": {
        "type": "Point",
        "coordinates": [
          96.3167,
          24.5
        ]
      },
      "type": "Feature",
      "properties": {
        "hierarchy": [
          "tgn:1066268",
          "tgn:7002185",
          "tgn:1000004",
          "tgn:1000108",
          "tgn:7029392"
        ],
        "placetype": [
          "aat:300008347"
        ],
        "id": 1066268,
        "name:xx": "Sawan"
      }
    },
    {
      "geometry": {
        "type": "Point",
        "coordinates": [
          94.8,
          20.85
        ]
      },
      "type": "Feature",
      "properties": {
        "hierarchy": [
          "tgn:1066269",
          "tgn:1000004",
          "tgn:1002093",
          "tgn:1000108",
          "tgn:7029392"
        ],
        "placetype": [
          "aat:300008347"
        ],
        "id": 1066269,
        "name:xx": "Seikpyu"
      }
    }
  ]
}
