{
  "geometry": {
    "type": "Point",
    "coordinates": [
      78.375906,
      24.084094
    ]
  },
  "type": "Feature",
  "properties": {
    "hierarchy": [
      "tgn:7582942",
      "tgn:1000004",
      "tgn:7000198",
      "tgn:1001894",
      "tgn:7029392"
    ],
    "placetype": [
      "aat:300008347"
    ],
    "name:en": "Gabhīriya Buzurg",
    "id": 7582942
  }
}
