{
  "geometry": {
    "type": "Point",
    "coordinates": [
      -155.15,
      58.8667
    ]
  },
  "type": "Feature",
  "properties": {
    "hierarchy": [
      "tgn:2132018",
      "tgn:7006450",
      "tgn:1000001",
      "tgn:7030517",
      "tgn:7012149",
      "tgn:7029392"
    ],
    "placetype": [
      "aat:300008706"
    ],
    "id": 2132018,
    "name:xx": "American Creek"
  }
}
