{
  "geometry": {
    "type": "Point",
    "coordinates": [
      16.1167,
      -12.2167
    ]
  },
  "type": "Feature",
  "properties": {
    "hierarchy": [
      "tgn:1087871",
      "tgn:7001242",
      "tgn:1000149",
      "tgn:1000868",
      "tgn:7029392"
    ],
    "placetype": [
      "aat:300008347"
    ],
    "id": 1087871,
    "name:xx": "Lunge"
  }
}
