{
  "geometry": {
    "type": "Point",
    "coordinates": [
      -104.45,
      37.6667
    ]
  },
  "type": "Feature",
  "properties": {
    "hierarchy": [
      "tgn:2256690",
      "tgn:1000001",
      "tgn:7012149",
      "tgn:2000227",
      "tgn:7007158",
      "tgn:7029392"
    ],
    "placetype": [
      "aat:300006191"
    ],
    "id": 2256690,
    "name:xx": "Cordova Tank"
  }
}
