{
  "geometry": {
    "type": "Point",
    "coordinates": [
      -103.4667,
      30.2167
    ]
  },
  "type": "Feature",
  "properties": {
    "hierarchy": [
      "tgn:1133777",
      "tgn:1000001",
      "tgn:2001945",
      "tgn:7012149",
      "tgn:7007826",
      "tgn:7029392"
    ],
    "placetype": [
      "aat:300008706"
    ],
    "id": 1133777,
    "name:xx": "Maravillas Creek"
  }
}
