{
  "geometry": {
    "type": "Point",
    "coordinates": [
      -71.5833,
      44.2833
    ]
  },
  "type": "Feature",
  "properties": {
    "hierarchy": [
      "tgn:2159940",
      "tgn:1002300",
      "tgn:1000001",
      "tgn:7012149",
      "tgn:7007564",
      "tgn:7029392"
    ],
    "placetype": [
      "aat:300008798"
    ],
    "id": 2159940,
    "name:xx": "Beech Hill"
  }
}
