{
  "geometry": {
    "type": "Point",
    "coordinates": [
      -112.1333,
      37.6667
    ]
  },
  "type": "Feature",
  "properties": {
    "hierarchy": [
      "tgn:2729579",
      "tgn:1000001",
      "tgn:2002109",
      "tgn:7012149",
      "tgn:7007827",
      "tgn:7029392"
    ],
    "placetype": [
      "aat:300008761"
    ],
    "id": 2729579,
    "name:xx": "Tropic Canyon"
  }
}
