{
  "geometry": {
    "type": "Point",
    "coordinates": [
      -81.3167,
      37.2833
    ]
  },
  "type": "Feature",
  "properties": {
    "hierarchy": [
      "tgn:2124685",
      "tgn:1000001",
      "tgn:7012149",
      "tgn:2002278",
      "tgn:7013961",
      "tgn:7029392"
    ],
    "placetype": [
      "aat:300008746"
    ],
    "id": 2124685,
    "name:xx": "Abbs Valley Cave"
  }
}
