{
  "geometry": {
    "type": "Point",
    "coordinates": [
      -71.8167,
      41.0667
    ]
  },
  "type": "Feature",
  "properties": {
    "hierarchy": [
      "tgn:2578442",
      "tgn:1000001",
      "tgn:7012149",
      "tgn:1002924",
      "tgn:7007568",
      "tgn:7029392"
    ],
    "placetype": [
      "aat:300132348"
    ],
    "id": 2578442,
    "name:xx": "Phelps Ledge"
  }
}
