{
  "geometry": {
    "type": "Point",
    "coordinates": [
      -105.85,
      33.05
    ]
  },
  "type": "Feature",
  "properties": {
    "hierarchy": [
      "tgn:7022492",
      "tgn:1000001",
      "tgn:7012149",
      "tgn:2001447",
      "tgn:7007566",
      "tgn:7029392"
    ],
    "placetype": [
      "aat:300008761"
    ],
    "id": 7022492,
    "name:xx": "Ysletaño Canyon"
  }
}
