{
  "geometry": {
    "type": "Point",
    "coordinates": [
      -103.55,
      36.0833
    ]
  },
  "type": "Feature",
  "properties": {
    "hierarchy": [
      "tgn:2511137",
      "tgn:1000001",
      "tgn:7012149",
      "tgn:2001459",
      "tgn:7007566",
      "tgn:7029392"
    ],
    "placetype": [
      "aat:300008347"
    ],
    "id": 2511137,
    "name:xx": "Miera"
  }
}
