{
  "geometry": {
    "type": "Point",
    "coordinates": [
      128.9333,
      44.4667
    ]
  },
  "type": "Feature",
  "properties": {
    "hierarchy": [
      "tgn:1138823",
      "tgn:1000004",
      "tgn:1001290",
      "tgn:1000111",
      "tgn:7029392"
    ],
    "placetype": [
      "aat:300008347"
    ],
    "id": 1138823,
    "name:xx": "Changting"
  }
}
