{
  "type": "FeatureCollection",
  "features": [
    {
      "geometry": {
        "type": "Point",
        "coordinates": [
          -114.1833,
          34.35
        ]
      },
      "type": "Feature",
      "properties": {
        "hierarchy": [
          "tgn:2010280",
          "tgn:1000001",
          "tgn:7012149",
          "tgn:7007157",
          "tgn:1002857",
          "tgn:7029392"
        ],
        "placetype": [
          "aat:300008347"
        ],
        "id": 2010280,
        "name:xx": "Black Meadow Landing"
      }
    },
    {
      "geometry": {
        "type": "Point",
        "coordinates": [
          -122.5,
          38.1
        ]
      },
      "type": "Feature",
      "properties": {
        "hierarchy": [
          "tgn:2010281",
          "tgn:1000001",
          "tgn:7012149",
          "tgn:7007157",
          "tgn:7014005",
          "tgn:7029392"
        ],
        "placetype": [
          "aat:300008347"
        ],
        "id": 2010281,
        "name:xx": "Black Point"
      }
    },
    {
      "geometry": {
        "type": "Point",
        "coordinates": [
          -119.8667,
          35.6
        ]
      },
      "type": "Feature",
      "properties": {
        "hierarchy": [
          "tgn:2010283",
          "tgn:1000001",
          "tgn:7012149",
          "tgn:1002545",
          "tgn:7007157",
          "tgn:7029392"
        ],
        "placetype": [
          "aat:300008347",
          "aat:300387210"
        ],
        "id": 2010283,
        "name:xx": "Blackwells Corner"
      }
    },
    {
      "geometry": {
        "type": "Point",
        "coordinates": [
          -120.6,
          39.7667
        ]
      },
      "type": "Feature",
      "properties": {
        "hierarchy": [
          "tgn:2010284",
          "tgn:1000001",
          "tgn:7012149",
          "tgn:7007157",
          "tgn:2000187",
          "tgn:7029392"
        ],
        "placetype": [
          "aat:300008347"
        ],
        "id": 2010284,
        "name:xx": "Blairsden"
      }
    },
    {
      "geometry": {
        "type": "Point",
        "coordinates": [
          -119.5,
          36.0333
        ]
      },
      "type": "Feature",
      "properties": {
        "hierarchy": [
          "tgn:2010285",
          "tgn:1000001",
          "tgn:7012149",
          "tgn:7007157",
          "tgn:1002956",
          "tgn:7029392"
        ],
        "placetype": [
          "aat:300387016"
        ],
        "id": 2010285,
        "name:xx": "Blanco"
      }
    },
    {
      "geometry": {
        "type": "Point",
        "coordinates": [
          -121.7333,
          36.6667
        ]
      },
      "type": "Feature",
      "properties": {
        "hierarchy": [
          "tgn:2010286",
          "tgn:1000001",
          "tgn:7012149",
          "tgn:7007157",
          "tgn:1002684",
          "tgn:7029392"
        ],
        "placetype": [
          "aat:300008347",
          "aat:300387210"
        ],
        "id": 2010286,
        "name:xx": "Blanco"
      }
    },
    {
      "geometry": {
        "type": "Point",
        "coordinates": [
          -123.6333,
          40.2667
        ]
      },
      "type": "Feature",
      "properties": {
        "hierarchy": [
          "tgn:2010287",
          "tgn:1000001",
          "tgn:7012149",
          "tgn:2000181",
          "tgn:7007157",
          "tgn:7029392"
        ],
        "placetype": [
          "aat:300008347"
        ],
        "id": 2010287,
        "name:xx": "Blocksburg"
      }
    },
    {
      "geometry": {
        "type": "Point",
        "coordinates": [
          -122.85,
          38.3
        ]
      },
      "type": "Feature",
      "properties": {
        "hierarchy": [
          "tgn:2010288",
          "tgn:1000001",
          "tgn:7012149",
          "tgn:7007157",
          "tgn:7014516",
          "tgn:7029392"
        ],
        "placetype": [
          "aat:300008347"
        ],
        "id": 2010288,
        "name:xx": "Bloomfield"
      }
    },
    {
      "geometry": {
        "type": "Point",
        "coordinates": [
          -117.3833,
          34.0667
        ]
      },
      "type": "Feature",
      "properties": {
        "hierarchy": [
          "tgn:2010289",
          "tgn:1000001",
          "tgn:7012149",
          "tgn:7007157",
          "tgn:1002857",
          "tgn:7029392"
        ],
        "placetype": [
          "aat:300008347"
        ],
        "id": 2010289,
        "name:xx": "Bloomington"
      }
    }
  ]
}
