{
  "geometry": {
    "type": "Point",
    "coordinates": [
      -82.85,
      35.35
    ]
  },
  "type": "Feature",
  "properties": {
    "hierarchy": [
      "tgn:2332701",
      "tgn:1000001",
      "tgn:7012149",
      "tgn:2001503",
      "tgn:7007709",
      "tgn:7029392"
    ],
    "placetype": [
      "aat:300008798"
    ],
    "id": 2332701,
    "name:xx": "Flower Knob"
  }
}
