{
  "geometry": {
    "type": "Point",
    "coordinates": [
      -89.3833,
      43.5167
    ]
  },
  "type": "Feature",
  "properties": {
    "hierarchy": [
      "tgn:2347588",
      "tgn:1000001",
      "tgn:2002315",
      "tgn:7012149",
      "tgn:7007922",
      "tgn:7029392"
    ],
    "placetype": [
      "aat:300008680"
    ],
    "id": 2347588,
    "name:xx": "George, Lake"
  }
}
