{
  "geometry": {
    "type": "Point",
    "coordinates": [
      -102.8833,
      30.9167
    ]
  },
  "type": "Feature",
  "properties": {
    "hierarchy": [
      "tgn:2390626",
      "tgn:1000001",
      "tgn:7012149",
      "tgn:2002055",
      "tgn:7007826",
      "tgn:7029392"
    ],
    "placetype": [
      "aat:300006075"
    ],
    "id": 2390626,
    "name:xx": "Highline Ditch"
  }
}
