{
  "geometry": {
    "type": "Point",
    "coordinates": [
      -136.1667,
      59.3333
    ]
  },
  "type": "Feature",
  "properties": {
    "hierarchy": [
      "tgn:2703353",
      "tgn:7006450",
      "tgn:1000001",
      "tgn:7012149",
      "tgn:7029392"
    ],
    "placetype": [
      "aat:300008706"
    ],
    "id": 2703353,
    "name:xx": "Summit Creek"
  }
}
