{
  "geometry": {
    "type": "Point",
    "coordinates": [
      -67.7333,
      45.4833
    ]
  },
  "type": "Feature",
  "properties": {
    "hierarchy": [
      "tgn:2211456",
      "tgn:1000001",
      "tgn:7012149",
      "tgn:7014589",
      "tgn:7007515",
      "tgn:7029392"
    ],
    "placetype": [
      "aat:300008699"
    ],
    "id": 2211456,
    "name:xx": "Butterfield Brook"
  }
}
