{
  "geometry": {
    "type": "Point",
    "coordinates": [
      -96.0667,
      44.2167
    ]
  },
  "type": "Feature",
  "properties": {
    "hierarchy": [
      "tgn:2428328",
      "tgn:1000001",
      "tgn:7012149",
      "tgn:7007521",
      "tgn:7029392"
    ],
    "placetype": [
      "aat:300006075"
    ],
    "id": 2428328,
    "name:xx": "Judicial Ditch Number Thirteen"
  }
}
