{
  "geometry": {
    "type": "Point",
    "coordinates": [
      -78.55,
      39.4833
    ]
  },
  "type": "Feature",
  "properties": {
    "hierarchy": [
      "tgn:2118931",
      "tgn:1000001",
      "tgn:7012149",
      "tgn:2002265",
      "tgn:7013961",
      "tgn:7029392"
    ],
    "placetype": [
      "aat:300008347"
    ],
    "id": 2118931,
    "name:xx": "Levels"
  }
}
