{
  "geometry": {
    "type": "Point",
    "coordinates": [
      -84.3667,
      37.0167
    ]
  },
  "type": "Feature",
  "properties": {
    "hierarchy": [
      "tgn:2741167",
      "tgn:1000001",
      "tgn:7012149",
      "tgn:2000839",
      "tgn:7007255",
      "tgn:7029392"
    ],
    "placetype": [
      "aat:300008706"
    ],
    "id": 2741167,
    "name:xx": "Upper Troublesome Creek"
  }
}
