{
  "geometry": {
    "type": "Point",
    "coordinates": [
      -61.0667,
      13.8833
    ]
  },
  "type": "Feature",
  "properties": {
    "hierarchy": [
      "tgn:1019064",
      "tgn:7015077",
      "tgn:1000001",
      "tgn:7004772",
      "tgn:7029392"
    ],
    "placetype": [
      "aat:300008347",
      "aat:300387220",
      "aat:300008375"
    ],
    "id": 1019064,
    "name:xx": "Soufrière"
  }
}
