{
  "geometry": {
    "type": "Point",
    "coordinates": [
      84.75,
      20.15
    ]
  },
  "type": "Feature",
  "properties": {
    "hierarchy": [
      "tgn:7572784",
      "tgn:1000004",
      "tgn:7000198",
      "tgn:7016694",
      "tgn:7029392"
    ],
    "placetype": [
      "aat:300008347"
    ],
    "name:en": "Goyāgonda",
    "id": 7572784
  }
}
