{
  "geometry": {
    "type": "Point",
    "coordinates": [
      -93.6833,
      41.1833
    ]
  },
  "type": "Feature",
  "properties": {
    "hierarchy": [
      "tgn:2567539",
      "tgn:1000001",
      "tgn:7012149",
      "tgn:2000651",
      "tgn:7007253",
      "tgn:7029392"
    ],
    "placetype": [
      "aat:300008706"
    ],
    "id": 2567539,
    "name:xx": "Papoose Creek"
  }
}
