{
  "type": "FeatureCollection",
  "features": [
    {
      "geometry": {
        "type": "Point",
        "coordinates": [
          -85.9333,
          30.6
        ]
      },
      "type": "Feature",
      "properties": {
        "hierarchy": [
          "tgn:2406940",
          "tgn:1000001",
          "tgn:7012149",
          "tgn:2000290",
          "tgn:7007240",
          "tgn:7029392"
        ],
        "placetype": [
          "aat:300008798"
        ],
        "id": 2406940,
        "name:xx": "Hunter Hill"
      }
    },
    {
      "geometry": {
        "type": "Point",
        "coordinates": [
          -120.7833,
          42.8333
        ]
      },
      "type": "Feature",
      "properties": {
        "hierarchy": [
          "tgn:2406941",
          "tgn:1000001",
          "tgn:7012149",
          "tgn:2001715",
          "tgn:7007708",
          "tgn:7029392"
        ],
        "placetype": [
          "aat:300008798"
        ],
        "id": 2406941,
        "name:xx": "Hunter Hill"
      }
    },
    {
      "geometry": {
        "type": "Point",
        "coordinates": [
          -80.85,
          33.5167
        ]
      },
      "type": "Feature",
      "properties": {
        "hierarchy": [
          "tgn:2406942",
          "tgn:1000001",
          "tgn:7012149",
          "tgn:2001762",
          "tgn:7007712",
          "tgn:7029392"
        ],
        "placetype": [
          "aat:300008347"
        ],
        "id": 2406942,
        "name:xx": "Hunter Hill"
      }
    },
    {
      "geometry": {
        "type": "Point",
        "coordinates": [
          -103.6333,
          43.0167
        ]
      },
      "type": "Feature",
      "properties": {
        "hierarchy": [
          "tgn:2406943",
          "tgn:1000001",
          "tgn:2001793",
          "tgn:7012149",
          "tgn:7007713",
          "tgn:7029392"
        ],
        "placetype": [
          "aat:300008798"
        ],
        "id": 2406943,
        "name:xx": "Hunter Hill"
      }
    },
    {
      "geometry": {
        "type": "Point",
        "coordinates": [
          -86.9167,
          35.6333
        ]
      },
      "type": "Feature",
      "properties": {
        "hierarchy": [
          "tgn:2406944",
          "tgn:1000001",
          "tgn:7012149",
          "tgn:2001896",
          "tgn:7007825",
          "tgn:7029392"
        ],
        "placetype": [
          "aat:300008798"
        ],
        "id": 2406944,
        "name:xx": "Hunter Hill"
      }
    },
    {
      "geometry": {
        "type": "Point",
        "coordinates": [
          -81.4167,
          39.3667
        ]
      },
      "type": "Feature",
      "properties": {
        "hierarchy": [
          "tgn:2406945",
          "tgn:1000001",
          "tgn:7012149",
          "tgn:2002303",
          "tgn:7013961",
          "tgn:7029392"
        ],
        "placetype": [
          "aat:300008798"
        ],
        "id": 2406945,
        "name:xx": "Hunter Hill"
      }
    },
    {
      "geometry": {
        "type": "Point",
        "coordinates": [
          -111.95,
          41.2333
        ]
      },
      "type": "Feature",
      "properties": {
        "hierarchy": [
          "tgn:2406946",
          "tgn:1000001",
          "tgn:7012149",
          "tgn:2002129",
          "tgn:7007827",
          "tgn:7029392"
        ],
        "placetype": [
          "aat:300008347"
        ],
        "id": 2406946,
        "name:xx": "Hunter Hill Addition"
      }
    },
    {
      "geometry": {
        "type": "Point",
        "coordinates": [
          -79.85,
          36.05
        ]
      },
      "type": "Feature",
      "properties": {
        "hierarchy": [
          "tgn:2406947",
          "tgn:1000001",
          "tgn:7012149",
          "tgn:2001500",
          "tgn:7007709",
          "tgn:7029392"
        ],
        "placetype": [
          "aat:300008347"
        ],
        "id": 2406947,
        "name:xx": "Hunter Hills"
      }
    },
    {
      "geometry": {
        "type": "Point",
        "coordinates": [
          -82.1333,
          36.5667
        ]
      },
      "type": "Feature",
      "properties": {
        "hierarchy": [
          "tgn:2406948",
          "tgn:1000001",
          "tgn:7012149",
          "tgn:2001918",
          "tgn:7007825",
          "tgn:7029392"
        ],
        "placetype": [
          "aat:300008347"
        ],
        "id": 2406948,
        "name:xx": "Hunter Hills"
      }
    },
    {
      "geometry": {
        "type": "Point",
        "coordinates": [
          -112,
          40.6667
        ]
      },
      "type": "Feature",
      "properties": {
        "hierarchy": [
          "tgn:2406949",
          "tgn:1000001",
          "tgn:7012149",
          "tgn:2002118",
          "tgn:7007827",
          "tgn:7029392"
        ],
        "placetype": [
          "aat:300008347"
        ],
        "id": 2406949,
        "name:xx": "Hunter Hills"
      }
    }
  ]
}
