{
  "geometry": {
    "type": "Point",
    "coordinates": [
      -107.15,
      28.35
    ]
  },
  "type": "Feature",
  "properties": {
    "hierarchy": [
      "tgn:7386037",
      "tgn:7005581",
      "tgn:1000001",
      "tgn:7005560",
      "tgn:7029392"
    ],
    "placetype": [
      "aat:300008777"
    ],
    "id": 7386037,
    "name:xx": "Pelon, Cerro"
  }
}
