{
  "geometry": {
    "type": "Point",
    "coordinates": [
      -94.7333,
      35.7333
    ]
  },
  "type": "Feature",
  "properties": {
    "hierarchy": [
      "tgn:2477480",
      "tgn:2001623",
      "tgn:1000001",
      "tgn:7012149",
      "tgn:7007707",
      "tgn:7029392"
    ],
    "placetype": [
      "aat:300008798"
    ],
    "id": 2477480,
    "name:xx": "Lyons Mountain"
  }
}
