{
  "geometry": {
    "type": "Point",
    "coordinates": [
      -120.95,
      36.4833
    ]
  },
  "type": "Feature",
  "properties": {
    "hierarchy": [
      "tgn:2259334",
      "tgn:1000001",
      "tgn:7012149",
      "tgn:7007157",
      "tgn:1002856",
      "tgn:7029392"
    ],
    "placetype": [
      "aat:300266640"
    ],
    "id": 2259334,
    "name:xx": "Cottonwood Ridge"
  }
}
