{
  "geometry": {
    "type": "Point",
    "coordinates": [
      -85.45,
      32.2833
    ]
  },
  "type": "Feature",
  "properties": {
    "hierarchy": [
      "tgn:2613541",
      "tgn:7002659",
      "tgn:1000001",
      "tgn:7012149",
      "tgn:7029392"
    ],
    "placetype": [
      "aat:300008699"
    ],
    "id": 2613541,
    "name:xx": "Reeder Branch"
  }
}
