{
  "geometry": {
    "type": "Point",
    "coordinates": [
      -88.8833,
      36.8833
    ]
  },
  "type": "Feature",
  "properties": {
    "hierarchy": [
      "tgn:2384023",
      "tgn:1000001",
      "tgn:2000778",
      "tgn:7012149",
      "tgn:7007255",
      "tgn:7029392"
    ],
    "placetype": [
      "aat:300008706"
    ],
    "id": 2384023,
    "name:xx": "Heflin Creek"
  }
}
