{
  "geometry": {
    "type": "Point",
    "coordinates": [
      -80.95,
      33.6667
    ]
  },
  "type": "Feature",
  "properties": {
    "hierarchy": [
      "tgn:2192120",
      "tgn:1000001",
      "tgn:2001733",
      "tgn:7012149",
      "tgn:7007712",
      "tgn:7029392"
    ],
    "placetype": [
      "aat:300006191"
    ],
    "id": 2192120,
    "name:xx": "Brakefield Pond"
  }
}
