{
  "geometry": {
    "type": "Point",
    "coordinates": [
      79.10636,
      24.748249
    ]
  },
  "type": "Feature",
  "properties": {
    "hierarchy": [
      "tgn:7565463",
      "tgn:1000004",
      "tgn:7000198",
      "tgn:1001894",
      "tgn:7029392"
    ],
    "placetype": [
      "aat:300008795"
    ],
    "name:en": "Mansūkra Pahār",
    "id": 7565463
  }
}
