{
  "geometry": {
    "type": "Point",
    "coordinates": [
      -109.0167,
      33.9833
    ]
  },
  "type": "Feature",
  "properties": {
    "hierarchy": [
      "tgn:2420467",
      "tgn:1000001",
      "tgn:2001429",
      "tgn:7012149",
      "tgn:7007566",
      "tgn:7029392"
    ],
    "placetype": [
      "aat:300008706"
    ],
    "id": 2420467,
    "name:xx": "Jenkins Creek"
  }
}
