{
  "geometry": {
    "type": "Point",
    "coordinates": [
      -110.0167,
      45.5167
    ]
  },
  "type": "Feature",
  "properties": {
    "hierarchy": [
      "tgn:2244928",
      "tgn:1000001",
      "tgn:7012149",
      "tgn:2001308",
      "tgn:7007524",
      "tgn:7029392"
    ],
    "placetype": [
      "aat:300386845"
    ],
    "id": 2244928,
    "name:xx": "Clover Basin"
  }
}
