{
  "geometry": {
    "type": "Point",
    "coordinates": [
      -87.566,
      12.981
    ]
  },
  "type": "Feature",
  "properties": {
    "hierarchy": [
      "tgn:1107679",
      "tgn:1000566",
      "tgn:1000001",
      "tgn:7005562",
      "tgn:7029392"
    ],
    "placetype": [
      "aat:300132325"
    ],
    "id": 1107679,
    "name:xx": "Cosigüina, Volcán"
  }
}
