{
  "geometry": {
    "type": "Point",
    "coordinates": [
      13.883333,
      54.05
    ]
  },
  "type": "Feature",
  "properties": {
    "hierarchy": [
      "tgn:7176265",
      "tgn:1000003",
      "tgn:7000094",
      "tgn:7000084",
      "tgn:7029392"
    ],
    "placetype": [
      "aat:300185707"
    ],
    "id": 7176265,
    "name:xx": "Groß Strummin-See"
  }
}
