{
  "geometry": {
    "type": "Point",
    "coordinates": [
      -79.1167,
      35.7667
    ]
  },
  "type": "Feature",
  "properties": {
    "hierarchy": [
      "tgn:2481287",
      "tgn:1000001",
      "tgn:2001480",
      "tgn:7012149",
      "tgn:7007709",
      "tgn:7029392"
    ],
    "placetype": [
      "aat:300008798"
    ],
    "id": 2481287,
    "name:xx": "Lambeth Mountain"
  }
}
