{
  "type": "FeatureCollection",
  "features": [
    {
      "geometry": {
        "type": "Point",
        "coordinates": [
          -3.65,
          55.933333
        ]
      },
      "type": "Feature",
      "properties": {
        "hierarchy": [
          "tgn:4011271",
          "tgn:7002444",
          "tgn:1000003",
          "tgn:7019121",
          "tgn:7008591",
          "tgn:7029392"
        ],
        "placetype": [
          "aat:300008347"
        ],
        "name:en": "Torphichen",
        "id": 4011271
      }
    },
    {
      "geometry": {
        "type": "Point",
        "coordinates": [
          9.7,
          45.716667
        ]
      },
      "type": "Feature",
      "properties": {
        "hierarchy": [
          "tgn:4011275",
          "tgn:7005023",
          "tgn:1000003",
          "tgn:7003237",
          "tgn:1000080",
          "tgn:7029392"
        ],
        "placetype": [
          "aat:300008347"
        ],
        "id": 4011275,
        "name:xx": "Torre Boldone"
      }
    },
    {
      "geometry": {
        "type": "Point",
        "coordinates": [
          8.8,
          44.9
        ]
      },
      "type": "Feature",
      "properties": {
        "hierarchy": [
          "tgn:4011276",
          "tgn:1003428",
          "tgn:1000003",
          "tgn:7003120",
          "tgn:1000080",
          "tgn:7029392"
        ],
        "placetype": [
          "aat:300008347"
        ],
        "id": 4011276,
        "name:xx": "Torre Garofoli"
      }
    }
  ]
}
