{
  "geometry": {
    "type": "Point",
    "coordinates": [
      -105.1667,
      45.4833
    ]
  },
  "type": "Feature",
  "properties": {
    "hierarchy": [
      "tgn:2699397",
      "tgn:1000001",
      "tgn:7012149",
      "tgn:2001297",
      "tgn:7007524",
      "tgn:7029392"
    ],
    "placetype": [
      "aat:300008761"
    ],
    "id": 2699397,
    "name:xx": "Strock Draw"
  }
}
