{
  "geometry": {
    "type": "Point",
    "coordinates": [
      -135.3667,
      59.1833
    ]
  },
  "type": "Feature",
  "properties": {
    "hierarchy": [
      "tgn:2236946",
      "tgn:7006450",
      "tgn:1000001",
      "tgn:2124077",
      "tgn:7012149",
      "tgn:7029392"
    ],
    "placetype": [
      "aat:300008850"
    ],
    "id": 2236946,
    "name:xx": "Chilkat Peninsula"
  }
}
