{
  "geometry": {
    "type": "Point",
    "coordinates": [
      -58.8667,
      -34.6333
    ]
  },
  "type": "Feature",
  "properties": {
    "hierarchy": [
      "tgn:1019471",
      "tgn:1001160",
      "tgn:7006477",
      "tgn:1000002",
      "tgn:7029392"
    ],
    "placetype": [
      "aat:300008347"
    ],
    "id": 1019471,
    "name:xx": "Francisco Álvarez"
  }
}
