{
  "type": "FeatureCollection",
  "features": [
    {
      "geometry": {
        "type": "Point",
        "coordinates": [
          -1.55,
          54.483333
        ]
      },
      "type": "Feature",
      "properties": {
        "hierarchy": [
          "tgn:1130081",
          "tgn:7002445",
          "tgn:1000003",
          "tgn:7008127",
          "tgn:7008591",
          "tgn:7029392"
        ],
        "placetype": [
          "aat:300008707",
          "aat:300008699"
        ],
        "name:en": "Skerne",
        "id": 1130081
      }
    },
    {
      "geometry": {
        "type": "Point",
        "coordinates": [
          -88.7167,
          38.8
        ]
      },
      "type": "Feature",
      "properties": {
        "hierarchy": [
          "tgn:1130082",
          "tgn:1000001",
          "tgn:7012149",
          "tgn:7007251",
          "tgn:7029392"
        ],
        "placetype": [
          "aat:300008707"
        ],
        "id": 1130082,
        "name:xx": "Skillet Fork"
      }
    },
    {
      "geometry": {
        "type": "Point",
        "coordinates": [
          -2.033333,
          54.1
        ]
      },
      "type": "Feature",
      "properties": {
        "hierarchy": [
          "tgn:1130083",
          "tgn:7002445",
          "tgn:1000003",
          "tgn:7008166",
          "tgn:7008591",
          "tgn:7029392"
        ],
        "placetype": [
          "aat:300008707",
          "aat:300008699"
        ],
        "name:en": "Skirfare",
        "id": 1130083
      }
    },
    {
      "geometry": {
        "type": "Point",
        "coordinates": [
          -17.6333,
          65.95
        ]
      },
      "type": "Feature",
      "properties": {
        "hierarchy": [
          "tgn:1130084",
          "tgn:7594017",
          "tgn:1000003",
          "tgn:1000077",
          "tgn:7029392"
        ],
        "placetype": [
          "aat:300008707"
        ],
        "id": 1130084,
        "name:xx": "Skjalfandafljot"
      }
    },
    {
      "geometry": {
        "type": "Point",
        "coordinates": [
          -87.8667,
          42.3
        ]
      },
      "type": "Feature",
      "properties": {
        "hierarchy": [
          "tgn:1130087",
          "tgn:1000001",
          "tgn:7012149",
          "tgn:7007251",
          "tgn:7029392"
        ],
        "placetype": [
          "aat:300008707"
        ],
        "id": 1130087,
        "name:xx": "Skokie"
      }
    }
  ]
}
