{
  "geometry": {
    "type": "Point",
    "coordinates": [
      -86.3667,
      39.3167
    ]
  },
  "type": "Feature",
  "properties": {
    "hierarchy": [
      "tgn:2204005",
      "tgn:1000001",
      "tgn:7012149",
      "tgn:7007252",
      "tgn:7029392"
    ],
    "placetype": [
      "aat:300008761"
    ],
    "id": 2204005,
    "name:xx": "Bud Davis Hollow"
  }
}
