{
  "type": "FeatureCollection",
  "features": [
    {
      "geometry": {
        "type": "Point",
        "coordinates": [
          -82.8167,
          35.7333
        ]
      },
      "type": "Feature",
      "properties": {
        "hierarchy": [
          "tgn:2694070",
          "tgn:1000001",
          "tgn:7012149",
          "tgn:2001516",
          "tgn:7007709",
          "tgn:7029392"
        ],
        "placetype": [
          "aat:300008761"
        ],
        "id": 2694070,
        "name:xx": "Stevens Cove"
      }
    },
    {
      "geometry": {
        "type": "Point",
        "coordinates": [
          -71.6,
          41.1667
        ]
      },
      "type": "Feature",
      "properties": {
        "hierarchy": [
          "tgn:2694071",
          "tgn:1002996",
          "tgn:1000001",
          "tgn:7012149",
          "tgn:7007711",
          "tgn:7029392"
        ],
        "placetype": [
          "aat:300132316"
        ],
        "id": 2694071,
        "name:xx": "Stevens Cove"
      }
    },
    {
      "geometry": {
        "type": "Point",
        "coordinates": [
          -78.8833,
          37.7667
        ]
      },
      "type": "Feature",
      "properties": {
        "hierarchy": [
          "tgn:2694072",
          "tgn:1000001",
          "tgn:7012149",
          "tgn:2002175",
          "tgn:7007919",
          "tgn:7029392"
        ],
        "placetype": [
          "aat:300008761"
        ],
        "id": 2694072,
        "name:xx": "Stevens Cove"
      }
    },
    {
      "geometry": {
        "type": "Point",
        "coordinates": [
          -87.95,
          34.2
        ]
      },
      "type": "Feature",
      "properties": {
        "hierarchy": [
          "tgn:2694073",
          "tgn:7002659",
          "tgn:1000001",
          "tgn:7012149",
          "tgn:2000046",
          "tgn:7029392"
        ],
        "placetype": [
          "aat:300008706"
        ],
        "id": 2694073,
        "name:xx": "Stevens Creek"
      }
    },
    {
      "geometry": {
        "type": "Point",
        "coordinates": [
          -157.3333,
          60.9333
        ]
      },
      "type": "Feature",
      "properties": {
        "hierarchy": [
          "tgn:2694074",
          "tgn:7006450",
          "tgn:2000069",
          "tgn:1000001",
          "tgn:7012149",
          "tgn:7029392"
        ],
        "placetype": [
          "aat:300008706"
        ],
        "id": 2694074,
        "name:xx": "Stevens Creek"
      }
    },
    {
      "geometry": {
        "type": "Point",
        "coordinates": [
          -150.8167,
          65.1833
        ]
      },
      "type": "Feature",
      "properties": {
        "hierarchy": [
          "tgn:2694075",
          "tgn:7006450",
          "tgn:1000001",
          "tgn:7012149",
          "tgn:2000089",
          "tgn:7029392"
        ],
        "placetype": [
          "aat:300008706"
        ],
        "id": 2694075,
        "name:xx": "Stevens Creek"
      }
    },
    {
      "geometry": {
        "type": "Point",
        "coordinates": [
          -91.5333,
          35.4
        ]
      },
      "type": "Feature",
      "properties": {
        "hierarchy": [
          "tgn:2694076",
          "tgn:1000001",
          "tgn:7016172",
          "tgn:7012149",
          "tgn:2000177",
          "tgn:7029392"
        ],
        "placetype": [
          "aat:300008706"
        ],
        "id": 2694076,
        "name:xx": "Stevens Creek"
      }
    },
    {
      "geometry": {
        "type": "Point",
        "coordinates": [
          -106.75,
          40.8667
        ]
      },
      "type": "Feature",
      "properties": {
        "hierarchy": [
          "tgn:2694077",
          "tgn:1000001",
          "tgn:7012149",
          "tgn:7007158",
          "tgn:2000245",
          "tgn:7029392"
        ],
        "placetype": [
          "aat:300008706"
        ],
        "id": 2694077,
        "name:xx": "Stevens Creek"
      }
    },
    {
      "geometry": {
        "type": "Point",
        "coordinates": [
          -107.7333,
          37.4
        ]
      },
      "type": "Feature",
      "properties": {
        "hierarchy": [
          "tgn:2694078",
          "tgn:1000001",
          "tgn:7012149",
          "tgn:2000225",
          "tgn:7007158",
          "tgn:7029392"
        ],
        "placetype": [
          "aat:300008706"
        ],
        "id": 2694078,
        "name:xx": "Stevens Creek"
      }
    },
    {
      "geometry": {
        "type": "Point",
        "coordinates": [
          -107.1333,
          38.6
        ]
      },
      "type": "Feature",
      "properties": {
        "hierarchy": [
          "tgn:2694079",
          "tgn:1000001",
          "tgn:7012149",
          "tgn:2000217",
          "tgn:7007158",
          "tgn:7029392"
        ],
        "placetype": [
          "aat:300008706"
        ],
        "id": 2694079,
        "name:xx": "Stevens Creek"
      }
    }
  ]
}
