{
  "geometry": {
    "type": "Point",
    "coordinates": [
      -91.1167,
      30.1667
    ]
  },
  "type": "Feature",
  "properties": {
    "hierarchy": [
      "tgn:2129214",
      "tgn:1000001",
      "tgn:7012149",
      "tgn:2000877",
      "tgn:7007256",
      "tgn:7029392"
    ],
    "placetype": [
      "aat:300008347"
    ],
    "id": 2129214,
    "name:xx": "Alhambra"
  }
}
