{
  "geometry": {
    "type": "Point",
    "coordinates": [
      -68.5167,
      44.8833
    ]
  },
  "type": "Feature",
  "properties": {
    "hierarchy": [
      "tgn:2552369",
      "tgn:1000001",
      "tgn:7012149",
      "tgn:2000927",
      "tgn:7007515",
      "tgn:7029392"
    ],
    "placetype": [
      "aat:300008905"
    ],
    "id": 2552369,
    "name:xx": "Number Twenty-six Swamp"
  }
}
