{
  "geometry": {
    "type": "Point",
    "coordinates": [
      -79.3833,
      38.45
    ]
  },
  "type": "Feature",
  "properties": {
    "hierarchy": [
      "tgn:2342010",
      "tgn:1000001",
      "tgn:7012149",
      "tgn:7014398",
      "tgn:7013961",
      "tgn:7029392"
    ],
    "placetype": [
      "aat:300008798"
    ],
    "id": 2342010,
    "name:xx": "Frye Knob"
  }
}
