{
  "geometry": {
    "type": "Point",
    "coordinates": [
      55.0667,
      45.2667
    ]
  },
  "type": "Feature",
  "properties": {
    "hierarchy": [
      "tgn:1052613",
      "tgn:1000004",
      "tgn:7012911",
      "tgn:7014786",
      "tgn:7029392"
    ],
    "placetype": [
      "aat:300008347"
    ],
    "id": 1052613,
    "name:xx": "Beyneu"
  }
}
