{
  "geometry": {
    "type": "Point",
    "coordinates": [
      30.842156,
      30.998684
    ]
  },
  "type": "Feature",
  "properties": {
    "hierarchy": [
      "tgn:7536800",
      "tgn:7001242",
      "tgn:7016833",
      "tgn:1001335",
      "tgn:7029392"
    ],
    "placetype": [
      "aat:300008347"
    ],
    "name:en": "Kunayyisat Shubrā Ţū",
    "id": 7536800
  }
}
