{
  "geometry": {
    "type": "Point",
    "coordinates": [
      -122.0833,
      37.65
    ]
  },
  "type": "Feature",
  "properties": {
    "hierarchy": [
      "tgn:2702549",
      "tgn:1002138",
      "tgn:1000001",
      "tgn:7012149",
      "tgn:7007157",
      "tgn:7029392"
    ],
    "placetype": [
      "aat:300008706"
    ],
    "id": 2702549,
    "name:xx": "Sulphur Creek"
  }
}
