{
  "geometry": {
    "type": "Point",
    "coordinates": [
      -87.8333,
      33.65
    ]
  },
  "type": "Feature",
  "properties": {
    "hierarchy": [
      "tgn:2214234",
      "tgn:7002659",
      "tgn:1000001",
      "tgn:7012149",
      "tgn:2000028",
      "tgn:7029392"
    ],
    "placetype": [
      "aat:300006191"
    ],
    "id": 2214234,
    "name:xx": "Cains Ridge Lake"
  }
}
