{
  "geometry": {
    "type": "Point",
    "coordinates": [
      -105.9167,
      46.0333
    ]
  },
  "type": "Feature",
  "properties": {
    "hierarchy": [
      "tgn:2061343",
      "tgn:1000001",
      "tgn:2001268",
      "tgn:7012149",
      "tgn:7007524",
      "tgn:7029392"
    ],
    "placetype": [
      "aat:300008347",
      "aat:300387210"
    ],
    "id": 2061343,
    "name:xx": "Garland"
  }
}
