{
  "type": "FeatureCollection",
  "features": [
    {
      "geometry": {
        "type": "Point",
        "coordinates": [
          -110.8333,
          31.5833
        ]
      },
      "type": "Feature",
      "properties": {
        "hierarchy": [
          "tgn:2138500",
          "tgn:1000001",
          "tgn:7006451",
          "tgn:7012149",
          "tgn:2000102",
          "tgn:7029392"
        ],
        "placetype": [
          "aat:300008761"
        ],
        "id": 2138500,
        "name:xx": "Ash Canyon"
      }
    },
    {
      "geometry": {
        "type": "Point",
        "coordinates": [
          -99.6833,
          41.7167
        ]
      },
      "type": "Feature",
      "properties": {
        "hierarchy": [
          "tgn:2138501",
          "tgn:1000001",
          "tgn:2001336",
          "tgn:7012149",
          "tgn:7007525",
          "tgn:7029392"
        ],
        "placetype": [
          "aat:300008761"
        ],
        "id": 2138501,
        "name:xx": "Ash Canyon"
      }
    },
    {
      "geometry": {
        "type": "Point",
        "coordinates": [
          -114.4667,
          37.4667
        ]
      },
      "type": "Feature",
      "properties": {
        "hierarchy": [
          "tgn:2138502",
          "tgn:1000001",
          "tgn:2001416",
          "tgn:7012149",
          "tgn:7007526",
          "tgn:7029392"
        ],
        "placetype": [
          "aat:300008761"
        ],
        "id": 2138502,
        "name:xx": "Ash Canyon"
      }
    },
    {
      "geometry": {
        "type": "Point",
        "coordinates": [
          -119.8833,
          39.15
        ]
      },
      "type": "Feature",
      "properties": {
        "hierarchy": [
          "tgn:2138503",
          "tgn:1000001",
          "tgn:7012149",
          "tgn:7007526",
          "tgn:7029392"
        ],
        "placetype": [
          "aat:300008761"
        ],
        "id": 2138503,
        "name:xx": "Ash Canyon"
      }
    },
    {
      "geometry": {
        "type": "Point",
        "coordinates": [
          -107.25,
          32.9667
        ]
      },
      "type": "Feature",
      "properties": {
        "hierarchy": [
          "tgn:2138504",
          "tgn:1000001",
          "tgn:7012149",
          "tgn:2001455",
          "tgn:7007566",
          "tgn:7029392"
        ],
        "placetype": [
          "aat:300008761"
        ],
        "id": 2138504,
        "name:xx": "Ash Canyon"
      }
    },
    {
      "geometry": {
        "type": "Point",
        "coordinates": [
          -106.5,
          32.3333
        ]
      },
      "type": "Feature",
      "properties": {
        "hierarchy": [
          "tgn:2138505",
          "tgn:1000001",
          "tgn:2001435",
          "tgn:7012149",
          "tgn:7007566",
          "tgn:7029392"
        ],
        "placetype": [
          "aat:300008761"
        ],
        "id": 2138505,
        "name:xx": "Ash Canyon"
      }
    },
    {
      "geometry": {
        "type": "Point",
        "coordinates": [
          -106.5167,
          32.6167
        ]
      },
      "type": "Feature",
      "properties": {
        "hierarchy": [
          "tgn:2138506",
          "tgn:1000001",
          "tgn:2001435",
          "tgn:7012149",
          "tgn:7007566",
          "tgn:7029392"
        ],
        "placetype": [
          "aat:300000390"
        ],
        "id": 2138506,
        "name:xx": "Ash Canyon"
      }
    },
    {
      "geometry": {
        "type": "Point",
        "coordinates": [
          -119.8833,
          39.15
        ]
      },
      "type": "Feature",
      "properties": {
        "hierarchy": [
          "tgn:2138507",
          "tgn:1000001",
          "tgn:7012149",
          "tgn:7007526",
          "tgn:7029392"
        ],
        "placetype": [
          "aat:300008706"
        ],
        "id": 2138507,
        "name:xx": "Ash Canyon Creek"
      }
    },
    {
      "geometry": {
        "type": "Point",
        "coordinates": [
          -112.1333,
          34.65
        ]
      },
      "type": "Feature",
      "properties": {
        "hierarchy": [
          "tgn:2138508",
          "tgn:1000001",
          "tgn:7006451",
          "tgn:7012149",
          "tgn:2000103",
          "tgn:7029392"
        ],
        "placetype": [
          "aat:300008697"
        ],
        "id": 2138508,
        "name:xx": "Ash Canyon Spring"
      }
    }
  ]
}
