{
  "geometry": {
    "type": "Point",
    "coordinates": [
      -121.8833,
      47.3333
    ]
  },
  "type": "Feature",
  "properties": {
    "hierarchy": [
      "tgn:2301821",
      "tgn:1000001",
      "tgn:7012149",
      "tgn:7018871",
      "tgn:7007920",
      "tgn:7029392"
    ],
    "placetype": [
      "aat:300008347"
    ],
    "id": 2301821,
    "name:xx": "Durham"
  }
}
