{
  "geometry": {
    "type": "Point",
    "coordinates": [
      -92.05,
      34.4833
    ]
  },
  "type": "Feature",
  "properties": {
    "hierarchy": [
      "tgn:2276821",
      "tgn:1000001",
      "tgn:7016172",
      "tgn:7012149",
      "tgn:2000139",
      "tgn:7029392"
    ],
    "placetype": [
      "aat:300008699"
    ],
    "id": 2276821,
    "name:xx": "Davis Bayou"
  }
}
