{
  "geometry": {
    "type": "Point",
    "coordinates": [
      -124.3333,
      42.1833
    ]
  },
  "type": "Feature",
  "properties": {
    "hierarchy": [
      "tgn:2516369",
      "tgn:1000001",
      "tgn:2001704",
      "tgn:7012149",
      "tgn:7007708",
      "tgn:7029392"
    ],
    "placetype": [
      "aat:300008761"
    ],
    "id": 2516369,
    "name:xx": "Miner Gulch"
  }
}
