{
  "geometry": {
    "type": "Point",
    "coordinates": [
      -73.5333,
      41.2333
    ]
  },
  "type": "Feature",
  "properties": {
    "hierarchy": [
      "tgn:2439698",
      "tgn:1000001",
      "tgn:7012149",
      "tgn:7014612",
      "tgn:7007568",
      "tgn:7029392"
    ],
    "placetype": [
      "aat:300008680"
    ],
    "id": 2439698,
    "name:xx": "Kitchawan, Lake"
  }
}
