{
  "geometry": {
    "type": "Point",
    "coordinates": [
      -141.45,
      64.1167
    ]
  },
  "type": "Feature",
  "properties": {
    "hierarchy": [
      "tgn:2747893",
      "tgn:7006450",
      "tgn:1000001",
      "tgn:7012149",
      "tgn:2000085",
      "tgn:7029392"
    ],
    "placetype": [
      "aat:300008706"
    ],
    "id": 2747893,
    "name:xx": "Walby Creek"
  }
}
