{
  "geometry": {
    "type": "Point",
    "coordinates": [
      -157.9833,
      61.9167
    ]
  },
  "type": "Feature",
  "properties": {
    "hierarchy": [
      "tgn:2230770",
      "tgn:7006450",
      "tgn:2000069",
      "tgn:1000001",
      "tgn:7012149",
      "tgn:7029392"
    ],
    "placetype": [
      "aat:300008706"
    ],
    "id": 2230770,
    "name:xx": "Central Creek"
  }
}
