{
  "geometry": {
    "type": "Point",
    "coordinates": [
      -85.8333,
      35.3333
    ]
  },
  "type": "Feature",
  "properties": {
    "hierarchy": [
      "tgn:2644760",
      "tgn:1000001",
      "tgn:7012149",
      "tgn:2001867",
      "tgn:7007825",
      "tgn:7029392"
    ],
    "placetype": [
      "aat:300008697"
    ],
    "id": 2644760,
    "name:xx": "Sartain Spring"
  }
}
