{
  "geometry": {
    "type": "Point",
    "coordinates": [
      -81.0833,
      41.2833
    ]
  },
  "type": "Feature",
  "properties": {
    "hierarchy": [
      "tgn:2079699",
      "tgn:1000001",
      "tgn:7012149",
      "tgn:1002797",
      "tgn:7007706",
      "tgn:7029392"
    ],
    "placetype": [
      "aat:300008347"
    ],
    "id": 2079699,
    "name:xx": "Garrettsville"
  }
}
