{
  "geometry": {
    "type": "Point",
    "coordinates": [
      145.6167,
      -20.3333
    ]
  },
  "type": "Feature",
  "properties": {
    "hierarchy": [
      "tgn:1097128",
      "tgn:7000490",
      "tgn:1000006",
      "tgn:7001830",
      "tgn:7029392"
    ],
    "placetype": [
      "aat:300008347"
    ],
    "id": 1097128,
    "name:xx": "Homestead"
  }
}
