{
  "geometry": {
    "type": "Point",
    "coordinates": [
      -111.6833,
      42.1833
    ]
  },
  "type": "Feature",
  "properties": {
    "hierarchy": [
      "tgn:2692187",
      "tgn:1000001",
      "tgn:7012149",
      "tgn:2000472",
      "tgn:7007250",
      "tgn:7029392"
    ],
    "placetype": [
      "aat:300008706"
    ],
    "id": 2692187,
    "name:xx": "Station Creek"
  }
}
