{
  "type": "FeatureCollection",
  "features": [
    {
      "geometry": {
        "type": "Point",
        "coordinates": [
          -123.0833,
          43.4833
        ]
      },
      "type": "Feature",
      "properties": {
        "hierarchy": [
          "tgn:2722240",
          "tgn:1000001",
          "tgn:7012149",
          "tgn:2001706",
          "tgn:7007708",
          "tgn:7029392"
        ],
        "placetype": [
          "aat:300008706"
        ],
        "id": 2722240,
        "name:xx": "Timothy Creek"
      }
    },
    {
      "geometry": {
        "type": "Point",
        "coordinates": [
          -121.3,
          43.25
        ]
      },
      "type": "Feature",
      "properties": {
        "hierarchy": [
          "tgn:2722241",
          "tgn:1000001",
          "tgn:7012149",
          "tgn:2001715",
          "tgn:7007708",
          "tgn:7029392"
        ],
        "placetype": [
          "aat:300008706"
        ],
        "id": 2722241,
        "name:xx": "Timothy Creek"
      }
    },
    {
      "geometry": {
        "type": "Point",
        "coordinates": [
          -81.55,
          34.2167
        ]
      },
      "type": "Feature",
      "properties": {
        "hierarchy": [
          "tgn:2722242",
          "tgn:1000001",
          "tgn:7012149",
          "tgn:2001760",
          "tgn:7007712",
          "tgn:7029392"
        ],
        "placetype": [
          "aat:300008706"
        ],
        "id": 2722242,
        "name:xx": "Timothy Creek"
      }
    },
    {
      "geometry": {
        "type": "Point",
        "coordinates": [
          -80.3,
          33.15
        ]
      },
      "type": "Feature",
      "properties": {
        "hierarchy": [
          "tgn:2722243",
          "tgn:1000001",
          "tgn:7012149",
          "tgn:7007712",
          "tgn:7029392"
        ],
        "placetype": [
          "aat:300008706"
        ],
        "id": 2722243,
        "name:xx": "Timothy Creek"
      }
    },
    {
      "geometry": {
        "type": "Point",
        "coordinates": [
          -83.3333,
          35.7167
        ]
      },
      "type": "Feature",
      "properties": {
        "hierarchy": [
          "tgn:2722244",
          "tgn:1000001",
          "tgn:7012149",
          "tgn:2001914",
          "tgn:7007825",
          "tgn:7029392"
        ],
        "placetype": [
          "aat:300008706"
        ],
        "id": 2722244,
        "name:xx": "Timothy Creek"
      }
    },
    {
      "geometry": {
        "type": "Point",
        "coordinates": [
          -110.2833,
          40.6167
        ]
      },
      "type": "Feature",
      "properties": {
        "hierarchy": [
          "tgn:2722245",
          "tgn:1000001",
          "tgn:2002107",
          "tgn:7012149",
          "tgn:7007827",
          "tgn:7029392"
        ],
        "placetype": [
          "aat:300008706"
        ],
        "id": 2722245,
        "name:xx": "Timothy Creek"
      }
    },
    {
      "geometry": {
        "type": "Point",
        "coordinates": [
          -119.8667,
          48.75
        ]
      },
      "type": "Feature",
      "properties": {
        "hierarchy": [
          "tgn:2722246",
          "tgn:1000001",
          "tgn:7012149",
          "tgn:1002742",
          "tgn:7007920",
          "tgn:7029392"
        ],
        "placetype": [
          "aat:300008706"
        ],
        "id": 2722246,
        "name:xx": "Timothy Creek"
      }
    },
    {
      "geometry": {
        "type": "Point",
        "coordinates": [
          -110.1833,
          44.7167
        ]
      },
      "type": "Feature",
      "properties": {
        "hierarchy": [
          "tgn:2722247",
          "tgn:1000001",
          "tgn:7012149",
          "tgn:2002379",
          "tgn:7007923",
          "tgn:7029392"
        ],
        "placetype": [
          "aat:300008706"
        ],
        "id": 2722247,
        "name:xx": "Timothy Creek"
      }
    },
    {
      "geometry": {
        "type": "Point",
        "coordinates": [
          -110.2667,
          40.55
        ]
      },
      "type": "Feature",
      "properties": {
        "hierarchy": [
          "tgn:2722248",
          "tgn:1000001",
          "tgn:2002107",
          "tgn:7012149",
          "tgn:7007827",
          "tgn:7029392"
        ],
        "placetype": [
          "aat:300006191"
        ],
        "id": 2722248,
        "name:xx": "Timothy Creek Reservoir"
      }
    },
    {
      "geometry": {
        "type": "Point",
        "coordinates": [
          -105.8833,
          40.85
        ]
      },
      "type": "Feature",
      "properties": {
        "hierarchy": [
          "tgn:2722249",
          "tgn:1000001",
          "tgn:7012149",
          "tgn:2000226",
          "tgn:7007158",
          "tgn:7029392"
        ],
        "placetype": [
          "aat:300006075"
        ],
        "id": 2722249,
        "name:xx": "Timothy Ditch"
      }
    }
  ]
}
