{
  "geometry": {
    "type": "Point",
    "coordinates": [
      -76.6833,
      37.2667
    ]
  },
  "type": "Feature",
  "properties": {
    "hierarchy": [
      "tgn:2567475",
      "tgn:1000001",
      "tgn:7012149",
      "tgn:7007919",
      "tgn:7029392"
    ],
    "placetype": [
      "aat:300008706"
    ],
    "id": 2567475,
    "name:xx": "Paper Mill Creek"
  }
}
