{
  "geometry": {
    "type": "Point",
    "coordinates": [
      -81.7333,
      37.7667
    ]
  },
  "type": "Feature",
  "properties": {
    "hierarchy": [
      "tgn:2223983",
      "tgn:1000001",
      "tgn:7012149",
      "tgn:2002273",
      "tgn:7013961",
      "tgn:7029392"
    ],
    "placetype": [
      "aat:300008699"
    ],
    "id": 2223983,
    "name:xx": "Cartwright Branch"
  }
}
