{
  "type": "FeatureCollection",
  "features": [
    {
      "geometry": {
        "type": "Point",
        "coordinates": [
          -170.35,
          63.6833
        ]
      },
      "type": "Feature",
      "properties": {
        "hierarchy": [
          "tgn:2601170",
          "tgn:7006450",
          "tgn:1000001",
          "tgn:7012149",
          "tgn:2000079",
          "tgn:7029392"
        ],
        "placetype": [
          "aat:300132316"
        ],
        "id": 2601170,
        "name:xx": "Punelok Bay"
      }
    },
    {
      "geometry": {
        "type": "Point",
        "coordinates": [
          -109.2333,
          33.25
        ]
      },
      "type": "Feature",
      "properties": {
        "hierarchy": [
          "tgn:2601171",
          "tgn:1000001",
          "tgn:7006451",
          "tgn:2000095",
          "tgn:7012149",
          "tgn:7029392"
        ],
        "placetype": [
          "aat:300008697"
        ],
        "id": 2601171,
        "name:xx": "Pungent Spring"
      }
    },
    {
      "geometry": {
        "type": "Point",
        "coordinates": [
          -76.0167,
          38.1
        ]
      },
      "type": "Feature",
      "properties": {
        "hierarchy": [
          "tgn:2601172",
          "tgn:1000001",
          "tgn:1002902",
          "tgn:7012149",
          "tgn:7007516",
          "tgn:7029392"
        ],
        "placetype": [
          "aat:300132316"
        ],
        "id": 2601172,
        "name:xx": "Pungers Cove"
      }
    },
    {
      "geometry": {
        "type": "Point",
        "coordinates": [
          -76.0167,
          38.1
        ]
      },
      "type": "Feature",
      "properties": {
        "hierarchy": [
          "tgn:2601173",
          "tgn:1000001",
          "tgn:1002902",
          "tgn:7012149",
          "tgn:7007516",
          "tgn:7029392"
        ],
        "placetype": [
          "aat:300132316"
        ],
        "id": 2601173,
        "name:xx": "Pungers Creek"
      }
    },
    {
      "geometry": {
        "type": "Point",
        "coordinates": [
          -76.0167,
          38.1
        ]
      },
      "type": "Feature",
      "properties": {
        "hierarchy": [
          "tgn:2601174",
          "tgn:1000001",
          "tgn:1002902",
          "tgn:7012149",
          "tgn:7007516",
          "tgn:7029392"
        ],
        "placetype": [
          "aat:300008850"
        ],
        "id": 2601174,
        "name:xx": "Pungers Point"
      }
    },
    {
      "geometry": {
        "type": "Point",
        "coordinates": [
          -115.3333,
          44.0333
        ]
      },
      "type": "Feature",
      "properties": {
        "hierarchy": [
          "tgn:2601175",
          "tgn:1000001",
          "tgn:2000459",
          "tgn:7012149",
          "tgn:7007250",
          "tgn:7029392"
        ],
        "placetype": [
          "aat:300008706"
        ],
        "id": 2601175,
        "name:xx": "Pungo Creek"
      }
    },
    {
      "geometry": {
        "type": "Point",
        "coordinates": [
          -115.0167,
          44.8
        ]
      },
      "type": "Feature",
      "properties": {
        "hierarchy": [
          "tgn:2601176",
          "tgn:1000001",
          "tgn:7012149",
          "tgn:2000494",
          "tgn:7007250",
          "tgn:7029392"
        ],
        "placetype": [
          "aat:300008706"
        ],
        "id": 2601176,
        "name:xx": "Pungo Creek"
      }
    },
    {
      "geometry": {
        "type": "Point",
        "coordinates": [
          -76.7333,
          35.5333
        ]
      },
      "type": "Feature",
      "properties": {
        "hierarchy": [
          "tgn:2601177",
          "tgn:1000001",
          "tgn:7013368",
          "tgn:7012149",
          "tgn:7007709",
          "tgn:7029392"
        ],
        "placetype": [
          "aat:300008706"
        ],
        "id": 2601177,
        "name:xx": "Pungo Creek"
      }
    },
    {
      "geometry": {
        "type": "Point",
        "coordinates": [
          -76.0333,
          36.6
        ]
      },
      "type": "Feature",
      "properties": {
        "hierarchy": [
          "tgn:2601178",
          "tgn:1000001",
          "tgn:7012149",
          "tgn:7022218",
          "tgn:7007919",
          "tgn:7029392"
        ],
        "placetype": [
          "aat:300008347"
        ],
        "id": 2601178,
        "name:xx": "Pungo Ferry"
      }
    },
    {
      "geometry": {
        "type": "Point",
        "coordinates": [
          -76.55,
          35.7
        ]
      },
      "type": "Feature",
      "properties": {
        "hierarchy": [
          "tgn:2601179",
          "tgn:1000001",
          "tgn:7012149",
          "tgn:2001550",
          "tgn:7007709",
          "tgn:7029392"
        ],
        "placetype": [
          "aat:300008680"
        ],
        "id": 2601179,
        "name:xx": "Pungo Lake"
      }
    }
  ]
}
