{
  "geometry": {
    "type": "Point",
    "coordinates": [
      -79.3167,
      37.9833
    ]
  },
  "type": "Feature",
  "properties": {
    "hierarchy": [
      "tgn:2356611",
      "tgn:1000001",
      "tgn:7012149",
      "tgn:2002186",
      "tgn:7007919",
      "tgn:7029392"
    ],
    "placetype": [
      "aat:300008746"
    ],
    "id": 2356611,
    "name:xx": "Gordons Cave"
  }
}
