{
  "geometry": {
    "type": "Point",
    "coordinates": [
      -121.4833,
      37.3333
    ]
  },
  "type": "Feature",
  "properties": {
    "hierarchy": [
      "tgn:2185954",
      "tgn:1000001",
      "tgn:7012149",
      "tgn:7007157",
      "tgn:7014475",
      "tgn:7029392"
    ],
    "placetype": [
      "aat:300008761"
    ],
    "id": 2185954,
    "name:xx": "Bollinger Canyon"
  }
}
