{
  "geometry": {
    "type": "Point",
    "coordinates": [
      119.15,
      -2.1833
    ]
  },
  "type": "Feature",
  "properties": {
    "hierarchy": [
      "tgn:1078046",
      "tgn:1000004",
      "tgn:1001547",
      "tgn:1000116",
      "tgn:7029392"
    ],
    "placetype": [
      "aat:300008347"
    ],
    "id": 1078046,
    "name:xx": "Lumu"
  }
}
