{
  "geometry": {
    "type": "Point",
    "coordinates": [
      -77.7667,
      42.9167
    ]
  },
  "type": "Feature",
  "properties": {
    "hierarchy": [
      "tgn:2068336",
      "tgn:1000001",
      "tgn:7012149",
      "tgn:1002604",
      "tgn:7007568",
      "tgn:7029392"
    ],
    "placetype": [
      "aat:300008347",
      "aat:300387210"
    ],
    "id": 2068336,
    "name:xx": "Canawaugus"
  }
}
