{
  "geometry": {
    "type": "Point",
    "coordinates": [
      -75.5333,
      39.4167
    ]
  },
  "type": "Feature",
  "properties": {
    "hierarchy": [
      "tgn:2450924",
      "tgn:7014201",
      "tgn:1000001",
      "tgn:7012149",
      "tgn:7007239",
      "tgn:7029392"
    ],
    "placetype": [
      "aat:300008850"
    ],
    "id": 2450924,
    "name:xx": "Liston Point"
  }
}
