{
  "geometry": {
    "type": "Point",
    "coordinates": [
      -98.95,
      20.808333
    ]
  },
  "type": "Feature",
  "properties": {
    "hierarchy": [
      "tgn:7411372",
      "tgn:7005587",
      "tgn:1000001",
      "tgn:7005560",
      "tgn:7029392"
    ],
    "placetype": [
      "aat:300008699"
    ],
    "id": 7411372,
    "name:es": "Amajac, Río"
  }
}
