{
  "geometry": {
    "type": "Point",
    "coordinates": [
      -78.4833,
      42.4333
    ]
  },
  "type": "Feature",
  "properties": {
    "hierarchy": [
      "tgn:2475704",
      "tgn:1000001",
      "tgn:1002245",
      "tgn:7012149",
      "tgn:7007568",
      "tgn:7029392"
    ],
    "placetype": [
      "aat:300008680"
    ],
    "id": 2475704,
    "name:xx": "Lucky Lakes"
  }
}
