{
  "type": "FeatureCollection",
  "features": [
    {
      "geometry": {
        "type": "Point",
        "coordinates": [
          50.55,
          26
        ]
      },
      "type": "Feature",
      "properties": {
        "hierarchy": [
          "tgn:7000182",
          "tgn:1000004",
          "tgn:7016770",
          "tgn:7029392"
        ],
        "placetype": [
          "aat:300008791"
        ],
        "id": 7000182,
        "name:xx": "Al-Baḥrayn"
      }
    },
    {
      "geometry": {
        "type": "Point",
        "coordinates": [
          50.6167,
          26.2667
        ]
      },
      "type": "Feature",
      "properties": {
        "hierarchy": [
          "tgn:7000183",
          "tgn:1000004",
          "tgn:7016770",
          "tgn:7029392"
        ],
        "placetype": [
          "aat:300008791"
        ],
        "id": 7000183,
        "name:xx": "Al-Muḥarraq, Jazīrat al"
      }
    },
    {
      "geometry": {
        "type": "Point",
        "coordinates": [
          50.6667,
          26.1
        ]
      },
      "type": "Feature",
      "properties": {
        "hierarchy": [
          "tgn:7000185",
          "tgn:1000004",
          "tgn:7016770",
          "tgn:7029392"
        ],
        "placetype": [
          "aat:300008791"
        ],
        "id": 7000185,
        "name:xx": "Sitrah"
      }
    },
    {
      "geometry": {
        "type": "Point",
        "coordinates": [
          91.8333,
          22.3333
        ]
      },
      "type": "Feature",
      "properties": {
        "hierarchy": [
          "tgn:7000188",
          "tgn:1000004",
          "tgn:1000105",
          "tgn:7029392"
        ],
        "placetype": [
          "aat:300387064",
          "aat:300387082"
        ],
        "id": 7000188,
        "name:xx": "Chittagong"
      }
    },
    {
      "geometry": {
        "type": "Point",
        "coordinates": [
          90.4167,
          23.7167
        ]
      },
      "type": "Feature",
      "properties": {
        "hierarchy": [
          "tgn:7000189",
          "tgn:1000004",
          "tgn:1000105",
          "tgn:7029392"
        ],
        "placetype": [
          "aat:300387064",
          "aat:300387082"
        ],
        "id": 7000189,
        "name:xx": "Dhaka"
      }
    }
  ]
}
