{
  "geometry": {
    "type": "Point",
    "coordinates": [
      -95.0833,
      36.5167
    ]
  },
  "type": "Feature",
  "properties": {
    "hierarchy": [
      "tgn:2556347",
      "tgn:1000001",
      "tgn:2001640",
      "tgn:7012149",
      "tgn:7007707",
      "tgn:7029392"
    ],
    "placetype": [
      "aat:300008347"
    ],
    "id": 2556347,
    "name:xx": "Okoee"
  }
}
