{
  "type": "FeatureCollection",
  "features": [
    {
      "geometry": {
        "type": "Point",
        "coordinates": [
          -100.516667,
          23.833333
        ]
      },
      "type": "Feature",
      "properties": {
        "hierarchy": [
          "tgn:7376330",
          "tgn:1000001",
          "tgn:7005589",
          "tgn:7005560",
          "tgn:7029392"
        ],
        "placetype": [
          "aat:300008347"
        ],
        "id": 7376330,
        "name:xx": "La Tapona"
      }
    },
    {
      "geometry": {
        "type": "Point",
        "coordinates": [
          -100.483333,
          23.5
        ]
      },
      "type": "Feature",
      "properties": {
        "hierarchy": [
          "tgn:7376331",
          "tgn:1000001",
          "tgn:7005589",
          "tgn:7005560",
          "tgn:7029392"
        ],
        "placetype": [
          "aat:300008347"
        ],
        "id": 7376331,
        "name:xx": "La Tapona"
      }
    },
    {
      "geometry": {
        "type": "Point",
        "coordinates": [
          -99.983333,
          23.133333
        ]
      },
      "type": "Feature",
      "properties": {
        "hierarchy": [
          "tgn:7376332",
          "tgn:1000001",
          "tgn:7005597",
          "tgn:7005560",
          "tgn:7029392"
        ],
        "placetype": [
          "aat:300008347"
        ],
        "id": 7376332,
        "name:xx": "La Tapona"
      }
    },
    {
      "geometry": {
        "type": "Point",
        "coordinates": [
          -101.233333,
          22.25
        ]
      },
      "type": "Feature",
      "properties": {
        "hierarchy": [
          "tgn:7376335",
          "tgn:1000001",
          "tgn:7005594",
          "tgn:7005560",
          "tgn:7029392"
        ],
        "placetype": [
          "aat:300008347"
        ],
        "id": 7376335,
        "name:xx": "La Tapona"
      }
    },
    {
      "geometry": {
        "type": "Point",
        "coordinates": [
          -101.916667,
          21.216667
        ]
      },
      "type": "Feature",
      "properties": {
        "hierarchy": [
          "tgn:7376336",
          "tgn:7005586",
          "tgn:1000001",
          "tgn:7005560",
          "tgn:7029392"
        ],
        "placetype": [
          "aat:300008347"
        ],
        "id": 7376336,
        "name:xx": "La Tapona"
      }
    },
    {
      "geometry": {
        "type": "Point",
        "coordinates": [
          -102.8,
          25.333333
        ]
      },
      "type": "Feature",
      "properties": {
        "hierarchy": [
          "tgn:7376337",
          "tgn:1001853",
          "tgn:1000001",
          "tgn:7005560",
          "tgn:7029392"
        ],
        "placetype": [
          "aat:300008347"
        ],
        "id": 7376337,
        "name:xx": "La Tapatía"
      }
    },
    {
      "geometry": {
        "type": "Point",
        "coordinates": [
          -92.066667,
          15.866667
        ]
      },
      "type": "Feature",
      "properties": {
        "hierarchy": [
          "tgn:7376338",
          "tgn:7005580",
          "tgn:1000001",
          "tgn:7005560",
          "tgn:7029392"
        ],
        "placetype": [
          "aat:300266554",
          "aat:300008699"
        ],
        "id": 7376338,
        "name:xx": "La Tapadera"
      }
    },
    {
      "geometry": {
        "type": "Point",
        "coordinates": [
          -100.685556,
          20.991944
        ]
      },
      "type": "Feature",
      "properties": {
        "hierarchy": [
          "tgn:7376339",
          "tgn:7005584",
          "tgn:1000001",
          "tgn:7005560",
          "tgn:7029392"
        ],
        "placetype": [
          "aat:300008347"
        ],
        "id": 7376339,
        "name:xx": "La Talega"
      }
    }
  ]
}
