{
  "geometry": {
    "type": "Point",
    "coordinates": [
      -78.4333,
      37.8833
    ]
  },
  "type": "Feature",
  "properties": {
    "hierarchy": [
      "tgn:2733322",
      "tgn:2002137",
      "tgn:1000001",
      "tgn:7012149",
      "tgn:7007919",
      "tgn:7029392"
    ],
    "placetype": [
      "aat:300008699"
    ],
    "id": 2733322,
    "name:xx": "Turkey Run"
  }
}
