{
  "geometry": {
    "type": "Point",
    "coordinates": [
      -82.6167,
      36.95
    ]
  },
  "type": "Feature",
  "properties": {
    "hierarchy": [
      "tgn:2756609",
      "tgn:1000001",
      "tgn:7012149",
      "tgn:2002195",
      "tgn:7007919",
      "tgn:7029392"
    ],
    "placetype": [
      "aat:300008347"
    ],
    "id": 2756609,
    "name:xx": "Wells"
  }
}
