{
  "geometry": {
    "type": "Point",
    "coordinates": [
      -97.35,
      17.85
    ]
  },
  "type": "Feature",
  "properties": {
    "hierarchy": [
      "tgn:1018455",
      "tgn:1000001",
      "tgn:7005591",
      "tgn:7005560",
      "tgn:7029392"
    ],
    "placetype": [
      "aat:300008347"
    ],
    "id": 1018455,
    "name:es": "Tepelmeme de Morelos"
  }
}
