{
  "type": "FeatureCollection",
  "features": [
    {
      "geometry": {
        "type": "Point",
        "coordinates": [
          -117.1833,
          34.25
        ]
      },
      "type": "Feature",
      "properties": {
        "hierarchy": [
          "tgn:2543710",
          "tgn:1000001",
          "tgn:7012149",
          "tgn:7007157",
          "tgn:1002857",
          "tgn:7029392"
        ],
        "placetype": [
          "aat:300132316"
        ],
        "id": 2543710,
        "name:xx": "North Bay"
      }
    },
    {
      "geometry": {
        "type": "Point",
        "coordinates": [
          -73.2,
          41.7
        ]
      },
      "type": "Feature",
      "properties": {
        "hierarchy": [
          "tgn:2543711",
          "tgn:1000001",
          "tgn:1002601",
          "tgn:7012149",
          "tgn:7007159",
          "tgn:7029392"
        ],
        "placetype": [
          "aat:300132316"
        ],
        "id": 2543711,
        "name:xx": "North Bay"
      }
    },
    {
      "geometry": {
        "type": "Point",
        "coordinates": [
          -85.6667,
          30.25
        ]
      },
      "type": "Feature",
      "properties": {
        "hierarchy": [
          "tgn:2543712",
          "tgn:2000258",
          "tgn:1000001",
          "tgn:7012149",
          "tgn:7007240",
          "tgn:7029392"
        ],
        "placetype": [
          "aat:300132316"
        ],
        "id": 2543712,
        "name:xx": "North Bay"
      }
    },
    {
      "geometry": {
        "type": "Point",
        "coordinates": [
          -69.8167,
          44.5667
        ]
      },
      "type": "Feature",
      "properties": {
        "hierarchy": [
          "tgn:2543713",
          "tgn:1000001",
          "tgn:2000923",
          "tgn:7012149",
          "tgn:7007515",
          "tgn:7029392"
        ],
        "placetype": [
          "aat:300132316"
        ],
        "id": 2543713,
        "name:xx": "North Bay"
      }
    },
    {
      "geometry": {
        "type": "Point",
        "coordinates": [
          -69.75,
          45.75
        ]
      },
      "type": "Feature",
      "properties": {
        "hierarchy": [
          "tgn:2543714",
          "tgn:1000001",
          "tgn:7012149",
          "tgn:2000928",
          "tgn:7007515",
          "tgn:7029392"
        ],
        "placetype": [
          "aat:300132316"
        ],
        "id": 2543714,
        "name:xx": "North Bay"
      }
    },
    {
      "geometry": {
        "type": "Point",
        "coordinates": [
          -70.4,
          41.6333
        ]
      },
      "type": "Feature",
      "properties": {
        "hierarchy": [
          "tgn:2543715",
          "tgn:1002165",
          "tgn:1000001",
          "tgn:7012149",
          "tgn:7007517",
          "tgn:7029392"
        ],
        "placetype": [
          "aat:300132316"
        ],
        "id": 2543715,
        "name:xx": "North Bay"
      }
    },
    {
      "geometry": {
        "type": "Point",
        "coordinates": [
          -83.5833,
          44.85
        ]
      },
      "type": "Feature",
      "properties": {
        "hierarchy": [
          "tgn:2543716",
          "tgn:2000942",
          "tgn:1000001",
          "tgn:7012149",
          "tgn:7007520",
          "tgn:7029392"
        ],
        "placetype": [
          "aat:300132316"
        ],
        "id": 2543716,
        "name:xx": "North Bay"
      }
    },
    {
      "geometry": {
        "type": "Point",
        "coordinates": [
          -87.6333,
          47.4167
        ]
      },
      "type": "Feature",
      "properties": {
        "hierarchy": [
          "tgn:2543717",
          "tgn:1000001",
          "tgn:7012149",
          "tgn:2000969",
          "tgn:7007520",
          "tgn:7029392"
        ],
        "placetype": [
          "aat:300132316"
        ],
        "id": 2543717,
        "name:xx": "North Bay"
      }
    },
    {
      "geometry": {
        "type": "Point",
        "coordinates": [
          -83.5,
          45.35
        ]
      },
      "type": "Feature",
      "properties": {
        "hierarchy": [
          "tgn:2543718",
          "tgn:1000001",
          "tgn:7012149",
          "tgn:2000990",
          "tgn:7007520",
          "tgn:7029392"
        ],
        "placetype": [
          "aat:300132316"
        ],
        "id": 2543718,
        "name:xx": "North Bay"
      }
    },
    {
      "geometry": {
        "type": "Point",
        "coordinates": [
          -90.6333,
          47.95
        ]
      },
      "type": "Feature",
      "properties": {
        "hierarchy": [
          "tgn:2543719",
          "tgn:1000001",
          "tgn:2001014",
          "tgn:7012149",
          "tgn:7007521",
          "tgn:7029392"
        ],
        "placetype": [
          "aat:300132316"
        ],
        "id": 2543719,
        "name:xx": "North Bay"
      }
    }
  ]
}
