{
  "geometry": {
    "type": "Point",
    "coordinates": [
      -79.1833,
      37.8167
    ]
  },
  "type": "Feature",
  "properties": {
    "hierarchy": [
      "tgn:2538649",
      "tgn:1000001",
      "tgn:7012149",
      "tgn:2002186",
      "tgn:7007919",
      "tgn:7029392"
    ],
    "placetype": [
      "aat:300008798"
    ],
    "id": 2538649,
    "name:xx": "Nettle Mountain"
  }
}
