{
  "geometry": {
    "type": "Point",
    "coordinates": [
      -73.3333,
      41.7833
    ]
  },
  "type": "Feature",
  "properties": {
    "hierarchy": [
      "tgn:2369521",
      "tgn:1000001",
      "tgn:1002601",
      "tgn:7012149",
      "tgn:7007159",
      "tgn:7029392"
    ],
    "placetype": [
      "aat:300008699"
    ],
    "id": 2369521,
    "name:xx": "Gunn Brook"
  }
}
