{
  "geometry": {
    "type": "Point",
    "coordinates": [
      -83.2833,
      37.55
    ]
  },
  "type": "Feature",
  "properties": {
    "hierarchy": [
      "tgn:2772778",
      "tgn:1000001",
      "tgn:2000772",
      "tgn:7012149",
      "tgn:7007255",
      "tgn:7029392"
    ],
    "placetype": [
      "aat:300008798"
    ],
    "id": 2772778,
    "name:xx": "Williams Hill"
  }
}
