{
  "geometry": {
    "type": "Point",
    "coordinates": [
      68.5333,
      43.1667
    ]
  },
  "type": "Feature",
  "properties": {
    "hierarchy": [
      "tgn:1053847",
      "tgn:1000004",
      "tgn:7012947",
      "tgn:7014786",
      "tgn:7029392"
    ],
    "placetype": [
      "aat:300008347"
    ],
    "id": 1053847,
    "name:xx": "Staryy Ikan"
  }
}
