{
  "geometry": {
    "type": "Point",
    "coordinates": [
      -82.3667,
      27.8167
    ]
  },
  "type": "Feature",
  "properties": {
    "hierarchy": [
      "tgn:2614696",
      "tgn:1000001",
      "tgn:1002479",
      "tgn:7012149",
      "tgn:7007240",
      "tgn:7029392"
    ],
    "placetype": [
      "aat:300008347"
    ],
    "id": 2614696,
    "name:xx": "Remlap"
  }
}
