{
  "geometry": {
    "type": "Point",
    "coordinates": [
      -119.85,
      34.0667
    ]
  },
  "type": "Feature",
  "properties": {
    "hierarchy": [
      "tgn:2565401",
      "tgn:1000001",
      "tgn:7012149",
      "tgn:1009002",
      "tgn:7007157",
      "tgn:1002867",
      "tgn:7029392"
    ],
    "placetype": [
      "aat:300008746"
    ],
    "id": 2565401,
    "name:xx": "Painted Cave"
  }
}
