{
  "geometry": {
    "type": "Point",
    "coordinates": [
      -90.0333,
      39.4833
    ]
  },
  "type": "Feature",
  "properties": {
    "hierarchy": [
      "tgn:2733776",
      "tgn:1000001",
      "tgn:7012149",
      "tgn:7007251",
      "tgn:7029392"
    ],
    "placetype": [
      "aat:300008706"
    ],
    "id": 2733776,
    "name:xx": "Turner Creek"
  }
}
