{
  "geometry": {
    "type": "Point",
    "coordinates": [
      -97.0333,
      31.8167
    ]
  },
  "type": "Feature",
  "properties": {
    "hierarchy": [
      "tgn:2258590",
      "tgn:1000001",
      "tgn:7012149",
      "tgn:7021748",
      "tgn:7007826",
      "tgn:7029392"
    ],
    "placetype": [
      "aat:300008347"
    ],
    "id": 2258590,
    "name:xx": "Cottonwood"
  }
}
