{
  "geometry": {
    "type": "Point",
    "coordinates": [
      5.95,
      52.25
    ]
  },
  "type": "Feature",
  "properties": {
    "hierarchy": [
      "tgn:7273223",
      "tgn:7003619",
      "tgn:1000003",
      "tgn:7016845",
      "tgn:7029392"
    ],
    "placetype": [
      "aat:300008347"
    ],
    "name:nl": "Wenum",
    "id": 7273223
  }
}
