{
  "geometry": {
    "type": "Point",
    "coordinates": [
      146.2667,
      -41.15
    ]
  },
  "type": "Feature",
  "properties": {
    "hierarchy": [
      "tgn:1096751",
      "tgn:7000490",
      "tgn:1000006",
      "tgn:7001992",
      "tgn:7029392"
    ],
    "placetype": [
      "aat:300008347",
      "aat:300387308",
      "aat:300008375"
    ],
    "id": 1096751,
    "name:xx": "Devonport"
  }
}
