{
  "geometry": {
    "type": "Point",
    "coordinates": [
      -78.4667,
      35.3333
    ]
  },
  "type": "Feature",
  "properties": {
    "hierarchy": [
      "tgn:2454635",
      "tgn:1000001",
      "tgn:7012149",
      "tgn:2001509",
      "tgn:7007709",
      "tgn:7029392"
    ],
    "placetype": [
      "aat:300008905"
    ],
    "id": 2454635,
    "name:xx": "Little Dismal Swamp"
  }
}
