{
  "geometry": {
    "type": "Point",
    "coordinates": [
      146.3167,
      -35.35
    ]
  },
  "type": "Feature",
  "properties": {
    "hierarchy": [
      "tgn:1098401",
      "tgn:7000490",
      "tgn:1000006",
      "tgn:7001828",
      "tgn:7029392"
    ],
    "placetype": [
      "aat:300008347"
    ],
    "id": 1098401,
    "name:xx": "Urana"
  }
}
