{
  "type": "FeatureCollection",
  "features": [
    {
      "geometry": {
        "type": "Point",
        "coordinates": [
          10.3,
          51.466667
        ]
      },
      "type": "Feature",
      "properties": {
        "hierarchy": [
          "tgn:7143060",
          "tgn:1000003",
          "tgn:7003689",
          "tgn:7000084",
          "tgn:7029392"
        ],
        "placetype": [
          "aat:300008777"
        ],
        "id": 7143060,
        "name:xx": "Linden-Berg"
      }
    },
    {
      "geometry": {
        "type": "Point",
        "coordinates": [
          11.533333,
          51.366667
        ]
      },
      "type": "Feature",
      "properties": {
        "hierarchy": [
          "tgn:7143061",
          "tgn:1000003",
          "tgn:7003687",
          "tgn:7000084",
          "tgn:7029392"
        ],
        "placetype": [
          "aat:300008777"
        ],
        "id": 7143061,
        "name:xx": "Linden-Berg"
      }
    },
    {
      "geometry": {
        "type": "Point",
        "coordinates": [
          10.866667,
          51.35
        ]
      },
      "type": "Feature",
      "properties": {
        "hierarchy": [
          "tgn:7143062",
          "tgn:1000003",
          "tgn:7003689",
          "tgn:7000084",
          "tgn:7029392"
        ],
        "placetype": [
          "aat:300008777"
        ],
        "id": 7143062,
        "name:xx": "Linden-Berg"
      }
    },
    {
      "geometry": {
        "type": "Point",
        "coordinates": [
          14.1,
          51.316667
        ]
      },
      "type": "Feature",
      "properties": {
        "hierarchy": [
          "tgn:7143063",
          "tgn:1000003",
          "tgn:7003685",
          "tgn:7000084",
          "tgn:7029392"
        ],
        "placetype": [
          "aat:300008777"
        ],
        "id": 7143063,
        "name:xx": "Linden-Berg"
      }
    },
    {
      "geometry": {
        "type": "Point",
        "coordinates": [
          9.316667,
          51.3
        ]
      },
      "type": "Feature",
      "properties": {
        "hierarchy": [
          "tgn:7143064",
          "tgn:1000003",
          "tgn:7003678",
          "tgn:7000084",
          "tgn:7029392"
        ],
        "placetype": [
          "aat:300008777"
        ],
        "id": 7143064,
        "name:xx": "Linden-Berg"
      }
    },
    {
      "geometry": {
        "type": "Point",
        "coordinates": [
          13.916667,
          51.283333
        ]
      },
      "type": "Feature",
      "properties": {
        "hierarchy": [
          "tgn:7143065",
          "tgn:1000003",
          "tgn:7003685",
          "tgn:7000084",
          "tgn:7029392"
        ],
        "placetype": [
          "aat:300008777"
        ],
        "id": 7143065,
        "name:xx": "Linden-Berg"
      }
    },
    {
      "geometry": {
        "type": "Point",
        "coordinates": [
          9.566667,
          51.283333
        ]
      },
      "type": "Feature",
      "properties": {
        "hierarchy": [
          "tgn:7143067",
          "tgn:1000003",
          "tgn:7003678",
          "tgn:7000084",
          "tgn:7029392"
        ],
        "placetype": [
          "aat:300008777"
        ],
        "id": 7143067,
        "name:xx": "Lindenberg"
      }
    },
    {
      "geometry": {
        "type": "Point",
        "coordinates": [
          13.633333,
          51.233333
        ]
      },
      "type": "Feature",
      "properties": {
        "hierarchy": [
          "tgn:7143068",
          "tgn:1000003",
          "tgn:7003685",
          "tgn:7000084",
          "tgn:7029392"
        ],
        "placetype": [
          "aat:300008777"
        ],
        "id": 7143068,
        "name:xx": "Linden-Berg"
      }
    }
  ]
}
