{
  "type": "FeatureCollection",
  "features": [
    {
      "geometry": {
        "type": "Point",
        "coordinates": [
          -83.3333,
          30.3
        ]
      },
      "type": "Feature",
      "properties": {
        "hierarchy": [
          "tgn:2583000",
          "tgn:1000001",
          "tgn:7012149",
          "tgn:2000279",
          "tgn:7007240",
          "tgn:7029392"
        ],
        "placetype": [
          "aat:300008680"
        ],
        "id": 2583000,
        "name:xx": "Pine Lake"
      }
    },
    {
      "geometry": {
        "type": "Point",
        "coordinates": [
          -86.4667,
          30.5
        ]
      },
      "type": "Feature",
      "properties": {
        "hierarchy": [
          "tgn:2583001",
          "tgn:1000001",
          "tgn:7012149",
          "tgn:2000281",
          "tgn:7007240",
          "tgn:7029392"
        ],
        "placetype": [
          "aat:300008680"
        ],
        "id": 2583001,
        "name:xx": "Pine Lake"
      }
    },
    {
      "geometry": {
        "type": "Point",
        "coordinates": [
          -81.8167,
          26.45
        ]
      },
      "type": "Feature",
      "properties": {
        "hierarchy": [
          "tgn:2583002",
          "tgn:1000001",
          "tgn:7012149",
          "tgn:1002582",
          "tgn:7007240",
          "tgn:7029392"
        ],
        "placetype": [
          "aat:300008680"
        ],
        "id": 2583002,
        "name:xx": "Pine Lake"
      }
    },
    {
      "geometry": {
        "type": "Point",
        "coordinates": [
          -84.1833,
          31.5833
        ]
      },
      "type": "Feature",
      "properties": {
        "hierarchy": [
          "tgn:2583003",
          "tgn:1000001",
          "tgn:7012149",
          "tgn:2000338",
          "tgn:7007248",
          "tgn:7029392"
        ],
        "placetype": [
          "aat:300008680"
        ],
        "id": 2583003,
        "name:xx": "Pine Lake"
      }
    },
    {
      "geometry": {
        "type": "Point",
        "coordinates": [
          -85.05,
          32.8
        ]
      },
      "type": "Feature",
      "properties": {
        "hierarchy": [
          "tgn:2583004",
          "tgn:1000001",
          "tgn:7012149",
          "tgn:2000363",
          "tgn:7007248",
          "tgn:7029392"
        ],
        "placetype": [
          "aat:300006191"
        ],
        "id": 2583004,
        "name:xx": "Pine Lake"
      }
    },
    {
      "geometry": {
        "type": "Point",
        "coordinates": [
          -84.2,
          33.7833
        ]
      },
      "type": "Feature",
      "properties": {
        "hierarchy": [
          "tgn:2583005",
          "tgn:1000001",
          "tgn:7012149",
          "tgn:2124023",
          "tgn:7007248",
          "tgn:7029392"
        ],
        "placetype": [
          "aat:300006191"
        ],
        "id": 2583005,
        "name:xx": "Pine Lake"
      }
    },
    {
      "geometry": {
        "type": "Point",
        "coordinates": [
          -83.9167,
          34.3833
        ]
      },
      "type": "Feature",
      "properties": {
        "hierarchy": [
          "tgn:2583006",
          "tgn:1000001",
          "tgn:7012149",
          "tgn:2000360",
          "tgn:7007248",
          "tgn:7029392"
        ],
        "placetype": [
          "aat:300006191"
        ],
        "id": 2583006,
        "name:xx": "Pine Lake"
      }
    },
    {
      "geometry": {
        "type": "Point",
        "coordinates": [
          -84.15,
          34.2
        ]
      },
      "type": "Feature",
      "properties": {
        "hierarchy": [
          "tgn:2583007",
          "tgn:1000001",
          "tgn:7012149",
          "tgn:2000349",
          "tgn:7007248",
          "tgn:7029392"
        ],
        "placetype": [
          "aat:300006191"
        ],
        "id": 2583007,
        "name:xx": "Pine Lake"
      }
    },
    {
      "geometry": {
        "type": "Point",
        "coordinates": [
          -84.2333,
          34.2
        ]
      },
      "type": "Feature",
      "properties": {
        "hierarchy": [
          "tgn:2583008",
          "tgn:1000001",
          "tgn:7012149",
          "tgn:2000349",
          "tgn:7007248",
          "tgn:7029392"
        ],
        "placetype": [
          "aat:300008680"
        ],
        "id": 2583008,
        "name:xx": "Pine Lake"
      }
    },
    {
      "geometry": {
        "type": "Point",
        "coordinates": [
          -85.05,
          32.8
        ]
      },
      "type": "Feature",
      "properties": {
        "hierarchy": [
          "tgn:2583009",
          "tgn:1000001",
          "tgn:7012149",
          "tgn:2000363",
          "tgn:7007248",
          "tgn:7029392"
        ],
        "placetype": [
          "aat:300008347"
        ],
        "id": 2583009,
        "name:xx": "Pine Lake"
      }
    }
  ]
}
