{
  "geometry": {
    "type": "Point",
    "coordinates": [
      6.4833,
      35.15
    ]
  },
  "type": "Feature",
  "properties": {
    "hierarchy": [
      "tgn:1108741",
      "tgn:7001242",
      "tgn:1000523",
      "tgn:7016752",
      "tgn:7029392"
    ],
    "placetype": [
      "aat:300008795"
    ],
    "id": 1108741,
    "name:xx": "Aurès"
  }
}
