{
  "geometry": {
    "type": "Point",
    "coordinates": [
      98.5833,
      8.8833
    ]
  },
  "type": "Feature",
  "properties": {
    "hierarchy": [
      "tgn:1085489",
      "tgn:7005195",
      "tgn:1000004",
      "tgn:7000967",
      "tgn:1000142",
      "tgn:7029392"
    ],
    "placetype": [
      "aat:300008347"
    ],
    "id": 1085489,
    "name:xx": "Ban Ya Plong"
  }
}
