{
  "geometry": {
    "type": "Point",
    "coordinates": [
      91.582254,
      25.29847
    ]
  },
  "type": "Feature",
  "properties": {
    "hierarchy": [
      "tgn:7554201",
      "tgn:1000004",
      "tgn:7000198",
      "tgn:1003539",
      "tgn:7029392"
    ],
    "placetype": [
      "aat:300008347"
    ],
    "name:en": "Mawsynrām",
    "id": 7554201
  }
}
