{
  "type": "FeatureCollection",
  "features": [
    {
      "geometry": {
        "type": "Point",
        "coordinates": [
          0.033333,
          51.816667
        ]
      },
      "type": "Feature",
      "properties": {
        "hierarchy": [
          "tgn:7024354",
          "tgn:7002445",
          "tgn:1000003",
          "tgn:7008145",
          "tgn:7008591",
          "tgn:7029392"
        ],
        "placetype": [
          "aat:300008347",
          "aat:300008372"
        ],
        "name:en": "Widford",
        "id": 7024354
      }
    },
    {
      "geometry": {
        "type": "Point",
        "coordinates": [
          23.675,
          38.412
        ]
      },
      "type": "Feature",
      "properties": {
        "hierarchy": [
          "tgn:7024356",
          "tgn:7011171",
          "tgn:7001395",
          "tgn:1000003",
          "tgn:7002677",
          "tgn:1000074",
          "tgn:7029392"
        ],
        "placetype": [
          "aat:300008347",
          "aat:300008372",
          "aat:300391489"
        ],
        "id": 7024356,
        "name:xx": "Lefkandi"
      }
    },
    {
      "geometry": {
        "type": "Point",
        "coordinates": [
          23.666,
          34.4
        ]
      },
      "type": "Feature",
      "properties": {
        "hierarchy": [
          "tgn:7024357",
          "tgn:7011171",
          "tgn:7001395",
          "tgn:1000003",
          "tgn:7002677",
          "tgn:1000074",
          "tgn:7029392"
        ],
        "placetype": [
          "aat:300008347",
          "aat:300000810",
          "aat:300167671"
        ],
        "id": 7024357,
        "name:xx": "Xeropolis"
      }
    }
  ]
}
