{
  "geometry": {
    "type": "Point",
    "coordinates": [
      38.3667,
      54.1167
    ]
  },
  "type": "Feature",
  "properties": {
    "hierarchy": [
      "tgn:1053049",
      "tgn:1000004",
      "tgn:1003418",
      "tgn:7018214",
      "tgn:7002435",
      "tgn:7029392"
    ],
    "placetype": [
      "aat:300008347"
    ],
    "id": 1053049,
    "name:xx": "Borozdino"
  }
}
