{
  "type": "FeatureCollection",
  "features": [
    {
      "geometry": {
        "type": "Point",
        "coordinates": [
          -56.2,
          46.7833
        ]
      },
      "type": "Feature",
      "properties": {
        "hierarchy": [
          "tgn:1008910",
          "tgn:1000001",
          "tgn:7005663",
          "tgn:7029392"
        ],
        "placetype": [
          "aat:300008791"
        ],
        "id": 1008910,
        "name:xx": "Saint-Pierre"
      }
    },
    {
      "geometry": {
        "type": "Point",
        "coordinates": [
          -73.25,
          45.3667
        ]
      },
      "type": "Feature",
      "properties": {
        "hierarchy": [
          "tgn:1008912",
          "tgn:7005685",
          "tgn:1000001",
          "tgn:7005804",
          "tgn:7029392"
        ],
        "placetype": [
          "aat:300008791"
        ],
        "id": 1008912,
        "name:xx": "Sainte-Thérèse, Île"
      }
    },
    {
      "geometry": {
        "type": "Point",
        "coordinates": [
          41.9,
          16.8667
        ]
      },
      "type": "Feature",
      "properties": {
        "hierarchy": [
          "tgn:1008914",
          "tgn:7000682",
          "tgn:7003875",
          "tgn:1000004",
          "tgn:1000137",
          "tgn:7029392"
        ],
        "placetype": [
          "aat:300008791"
        ],
        "id": 1008914,
        "name:xx": "Sajīd"
      }
    },
    {
      "geometry": {
        "type": "Point",
        "coordinates": [
          103.85,
          1.2167
        ]
      },
      "type": "Feature",
      "properties": {
        "hierarchy": [
          "tgn:1008917",
          "tgn:1000004",
          "tgn:7000381",
          "tgn:7029392"
        ],
        "placetype": [
          "aat:300008791"
        ],
        "id": 1008917,
        "name:xx": "Sakijang Bendera, Pulau"
      }
    },
    {
      "geometry": {
        "type": "Point",
        "coordinates": [
          103.8667,
          1.2167
        ]
      },
      "type": "Feature",
      "properties": {
        "hierarchy": [
          "tgn:1008918",
          "tgn:1000004",
          "tgn:7000381",
          "tgn:7029392"
        ],
        "placetype": [
          "aat:300008791"
        ],
        "id": 1008918,
        "name:xx": "Sakijang Pelepah, Pulau"
      }
    },
    {
      "geometry": {
        "type": "Point",
        "coordinates": [
          103.7,
          1.2667
        ]
      },
      "type": "Feature",
      "properties": {
        "hierarchy": [
          "tgn:1008919",
          "tgn:1000004",
          "tgn:7000381",
          "tgn:7029392"
        ],
        "placetype": [
          "aat:300008791"
        ],
        "id": 1008919,
        "name:xx": "Sakra, Pulau"
      }
    }
  ]
}
