{
  "geometry": {
    "type": "Point",
    "coordinates": [
      51.2167,
      24.95
    ]
  },
  "type": "Feature",
  "properties": {
    "hierarchy": [
      "tgn:1107825",
      "tgn:7594193",
      "tgn:1000004",
      "tgn:1000136",
      "tgn:7029392"
    ],
    "placetype": [
      "aat:300008777"
    ],
    "id": 1107825,
    "name:xx": "Abā al-Bawl, Qurayn"
  }
}
