{
  "type": "FeatureCollection",
  "features": [
    {
      "geometry": {
        "type": "Point",
        "coordinates": [
          8.466667,
          50.9
        ]
      },
      "type": "Feature",
      "properties": {
        "hierarchy": [
          "tgn:1038640",
          "tgn:1000003",
          "tgn:7003678",
          "tgn:7000084",
          "tgn:7029392"
        ],
        "placetype": [
          "aat:300008347"
        ],
        "id": 1038640,
        "name:xx": "Breidenstein"
      }
    },
    {
      "geometry": {
        "type": "Point",
        "coordinates": [
          10.633333,
          53.6
        ]
      },
      "type": "Feature",
      "properties": {
        "hierarchy": [
          "tgn:1038642",
          "tgn:1000003",
          "tgn:7003688",
          "tgn:7000084",
          "tgn:7029392"
        ],
        "placetype": [
          "aat:300008347"
        ],
        "id": 1038642,
        "name:xx": "Breitenfelde"
      }
    },
    {
      "geometry": {
        "type": "Point",
        "coordinates": [
          10.9,
          49.9667
        ]
      },
      "type": "Feature",
      "properties": {
        "hierarchy": [
          "tgn:1038643",
          "tgn:7003669",
          "tgn:1000003",
          "tgn:7000084",
          "tgn:7029392"
        ],
        "placetype": [
          "aat:300008347"
        ],
        "id": 1038643,
        "name:xx": "Breitengüssbach"
      }
    },
    {
      "geometry": {
        "type": "Point",
        "coordinates": [
          8.2,
          50.683333
        ]
      },
      "type": "Feature",
      "properties": {
        "hierarchy": [
          "tgn:1038644",
          "tgn:1000003",
          "tgn:7003678",
          "tgn:7000084",
          "tgn:7029392"
        ],
        "placetype": [
          "aat:300008347"
        ],
        "id": 1038644,
        "name:xx": "Breitscheid"
      }
    },
    {
      "geometry": {
        "type": "Point",
        "coordinates": [
          10.083333,
          53.016667
        ]
      },
      "type": "Feature",
      "properties": {
        "hierarchy": [
          "tgn:1038645",
          "tgn:1000003",
          "tgn:7003676",
          "tgn:7000084",
          "tgn:7029392"
        ],
        "placetype": [
          "aat:300008347"
        ],
        "id": 1038645,
        "name:xx": "Breloh"
      }
    },
    {
      "geometry": {
        "type": "Point",
        "coordinates": [
          9.533333,
          48.333333
        ]
      },
      "type": "Feature",
      "properties": {
        "hierarchy": [
          "tgn:1038646",
          "tgn:7003692",
          "tgn:1000003",
          "tgn:7000084",
          "tgn:7029392"
        ],
        "placetype": [
          "aat:300008347"
        ],
        "id": 1038646,
        "name:xx": "Bremelau"
      }
    },
    {
      "geometry": {
        "type": "Point",
        "coordinates": [
          9.133333,
          53.483333
        ]
      },
      "type": "Feature",
      "properties": {
        "hierarchy": [
          "tgn:1038649",
          "tgn:1000003",
          "tgn:7003676",
          "tgn:7000084",
          "tgn:7029392"
        ],
        "placetype": [
          "aat:300008347"
        ],
        "id": 1038649,
        "name:xx": "Bremervörde"
      }
    }
  ]
}
