{
  "geometry": {
    "type": "Point",
    "coordinates": [
      -95.5333,
      29.5333
    ]
  },
  "type": "Feature",
  "properties": {
    "hierarchy": [
      "tgn:2330307",
      "tgn:1000001",
      "tgn:7012149",
      "tgn:1002379",
      "tgn:7007826",
      "tgn:7029392"
    ],
    "placetype": [
      "aat:300008706"
    ],
    "id": 2330307,
    "name:xx": "Flat Bank Creek"
  }
}
