{
  "geometry": {
    "type": "Point",
    "coordinates": [
      -123.3167,
      42.2333
    ]
  },
  "type": "Feature",
  "properties": {
    "hierarchy": [
      "tgn:2612166",
      "tgn:1000001",
      "tgn:7012149",
      "tgn:2001713",
      "tgn:7007708",
      "tgn:7029392"
    ],
    "placetype": [
      "aat:300000390"
    ],
    "id": 2612166,
    "name:xx": "Red Rose Mine"
  }
}
