{
  "geometry": {
    "type": "Point",
    "coordinates": [
      -104.8333,
      36.4667
    ]
  },
  "type": "Feature",
  "properties": {
    "hierarchy": [
      "tgn:2500307",
      "tgn:1000001",
      "tgn:2001432",
      "tgn:7012149",
      "tgn:7007566",
      "tgn:7029392"
    ],
    "placetype": [
      "aat:300008347"
    ],
    "id": 2500307,
    "name:xx": "McDaniel Cimarron Place"
  }
}
