{
  "geometry": {
    "type": "Point",
    "coordinates": [
      126.7333,
      35.7333
    ]
  },
  "type": "Feature",
  "properties": {
    "hierarchy": [
      "tgn:1082336",
      "tgn:1001194",
      "tgn:1000004",
      "tgn:7000299",
      "tgn:7029392"
    ],
    "placetype": [
      "aat:300008347"
    ],
    "id": 1082336,
    "name:xx": "Puan"
  }
}
