{
  "geometry": {
    "type": "Point",
    "coordinates": [
      78.48117,
      23.97428
    ]
  },
  "type": "Feature",
  "properties": {
    "hierarchy": [
      "tgn:7571935",
      "tgn:1000004",
      "tgn:7000198",
      "tgn:1001894",
      "tgn:7029392"
    ],
    "placetype": [
      "aat:300008347"
    ],
    "name:en": "Jeruwakhera",
    "id": 7571935
  }
}
