{
  "type": "FeatureCollection",
  "features": [
    {
      "geometry": {
        "type": "Point",
        "coordinates": [
          -5.4,
          40.416667
        ]
      },
      "type": "Feature",
      "properties": {
        "hierarchy": [
          "tgn:7332740",
          "tgn:7002806",
          "tgn:7001158",
          "tgn:1000003",
          "tgn:1000095",
          "tgn:7029392"
        ],
        "placetype": [
          "aat:300008347"
        ],
        "id": 7332740,
        "name:xx": "La Aldehuela"
      }
    },
    {
      "geometry": {
        "type": "Point",
        "coordinates": [
          -3.266667,
          42.7
        ]
      },
      "type": "Feature",
      "properties": {
        "hierarchy": [
          "tgn:7332743",
          "tgn:7002810",
          "tgn:7001158",
          "tgn:1000003",
          "tgn:1000095",
          "tgn:7029392"
        ],
        "placetype": [
          "aat:300008347"
        ],
        "id": 7332743,
        "name:xx": "La Aldea del Portillo de Busto"
      }
    },
    {
      "geometry": {
        "type": "Point",
        "coordinates": [
          -3.533333,
          42.9
        ]
      },
      "type": "Feature",
      "properties": {
        "hierarchy": [
          "tgn:7332744",
          "tgn:7002810",
          "tgn:7001158",
          "tgn:1000003",
          "tgn:1000095",
          "tgn:7029392"
        ],
        "placetype": [
          "aat:300008347"
        ],
        "id": 7332744,
        "name:xx": "La Aldea"
      }
    },
    {
      "geometry": {
        "type": "Point",
        "coordinates": [
          -6.283333,
          37.733333
        ]
      },
      "type": "Feature",
      "properties": {
        "hierarchy": [
          "tgn:7332745",
          "tgn:7002758",
          "tgn:7002841",
          "tgn:1000003",
          "tgn:1000095",
          "tgn:7029392"
        ],
        "placetype": [
          "aat:300008347"
        ],
        "id": 7332745,
        "name:xx": "La Alcornocosa"
      }
    },
    {
      "geometry": {
        "type": "Point",
        "coordinates": [
          -3.083333,
          36.75
        ]
      },
      "type": "Feature",
      "properties": {
        "hierarchy": [
          "tgn:7332746",
          "tgn:7002758",
          "tgn:7002821",
          "tgn:1000003",
          "tgn:1000095",
          "tgn:7029392"
        ],
        "placetype": [
          "aat:300008347"
        ],
        "id": 7332746,
        "name:xx": "La Alcazaba"
      }
    },
    {
      "geometry": {
        "type": "Point",
        "coordinates": [
          -2.75,
          40.516667
        ]
      },
      "type": "Feature",
      "properties": {
        "hierarchy": [
          "tgn:7332747",
          "tgn:7002822",
          "tgn:1001647",
          "tgn:1000003",
          "tgn:1000095",
          "tgn:7029392"
        ],
        "placetype": [
          "aat:300386856"
        ],
        "id": 7332747,
        "name:xx": "Alcarria, Páramos de la"
      }
    },
    {
      "geometry": {
        "type": "Point",
        "coordinates": [
          -1.866667,
          38.383333
        ]
      },
      "type": "Feature",
      "properties": {
        "hierarchy": [
          "tgn:7332748",
          "tgn:7002803",
          "tgn:1001647",
          "tgn:1000003",
          "tgn:1000095",
          "tgn:7029392"
        ],
        "placetype": [
          "aat:300008347"
        ],
        "id": 7332748,
        "name:xx": "La Alcantarilla"
      }
    }
  ]
}
