{
  "geometry": {
    "type": "Point",
    "coordinates": [
      -79.85,
      38.3167
    ]
  },
  "type": "Feature",
  "properties": {
    "hierarchy": [
      "tgn:2238273",
      "tgn:1000001",
      "tgn:7012149",
      "tgn:2002287",
      "tgn:7013961",
      "tgn:7029392"
    ],
    "placetype": [
      "aat:300008697"
    ],
    "id": 2238273,
    "name:xx": "Chocklett Spring"
  }
}
