{
  "geometry": {
    "type": "Point",
    "coordinates": [
      -109.7667,
      40.2833
    ]
  },
  "type": "Feature",
  "properties": {
    "hierarchy": [
      "tgn:2562491",
      "tgn:1000001",
      "tgn:7012149",
      "tgn:2002124",
      "tgn:7007827",
      "tgn:7029392"
    ],
    "placetype": [
      "aat:300006075"
    ],
    "id": 2562491,
    "name:xx": "Ouray Park Canal"
  }
}
