{
  "geometry": {
    "type": "Point",
    "coordinates": [
      -77.8333,
      38.7833
    ]
  },
  "type": "Feature",
  "properties": {
    "hierarchy": [
      "tgn:2607652",
      "tgn:1000001",
      "tgn:7012149",
      "tgn:1002368",
      "tgn:7007919",
      "tgn:7029392"
    ],
    "placetype": [
      "aat:300008798"
    ],
    "id": 2607652,
    "name:xx": "Rappahannock Mountain"
  }
}
