{
  "geometry": {
    "type": "Point",
    "coordinates": [
      -90.35,
      31.65
    ]
  },
  "type": "Feature",
  "properties": {
    "hierarchy": [
      "tgn:2342895",
      "tgn:1000001",
      "tgn:7012149",
      "tgn:2001128",
      "tgn:7007522",
      "tgn:7029392"
    ],
    "placetype": [
      "aat:300008699"
    ],
    "id": 2342895,
    "name:xx": "Furr Branch"
  }
}
