{
  "geometry": {
    "type": "Point",
    "coordinates": [
      -105.8167,
      36.2333
    ]
  },
  "type": "Feature",
  "properties": {
    "hierarchy": [
      "tgn:2560920",
      "tgn:1000001",
      "tgn:7012149",
      "tgn:2001457",
      "tgn:7007566",
      "tgn:7029392"
    ],
    "placetype": [
      "aat:300000390"
    ],
    "id": 2560920,
    "name:xx": "Oro Grande Company of Pennsylvania"
  }
}
