{
  "type": "FeatureCollection",
  "features": [
    {
      "geometry": {
        "type": "Point",
        "coordinates": [
          -92.75,
          46.2167
        ]
      },
      "type": "Feature",
      "properties": {
        "hierarchy": [
          "tgn:2218600",
          "tgn:1000001",
          "tgn:7012149",
          "tgn:2001056",
          "tgn:7007521",
          "tgn:7029392"
        ],
        "placetype": [
          "aat:300008706"
        ],
        "id": 2218600,
        "name:xx": "Cane Creek"
      }
    },
    {
      "geometry": {
        "type": "Point",
        "coordinates": [
          -90.25,
          32.5667
        ]
      },
      "type": "Feature",
      "properties": {
        "hierarchy": [
          "tgn:2218601",
          "tgn:1000001",
          "tgn:7012149",
          "tgn:2001130",
          "tgn:7007522",
          "tgn:7029392"
        ],
        "placetype": [
          "aat:300008706"
        ],
        "id": 2218601,
        "name:xx": "Cane Creek"
      }
    },
    {
      "geometry": {
        "type": "Point",
        "coordinates": [
          -88.5167,
          33.7333
        ]
      },
      "type": "Feature",
      "properties": {
        "hierarchy": [
          "tgn:2218602",
          "tgn:1000001",
          "tgn:7012149",
          "tgn:7007522",
          "tgn:7029392"
        ],
        "placetype": [
          "aat:300008706"
        ],
        "id": 2218602,
        "name:xx": "Cane Creek"
      }
    },
    {
      "geometry": {
        "type": "Point",
        "coordinates": [
          -89.1667,
          34.25
        ]
      },
      "type": "Feature",
      "properties": {
        "hierarchy": [
          "tgn:2218603",
          "tgn:1000001",
          "tgn:7012149",
          "tgn:2001143",
          "tgn:7007522",
          "tgn:7029392"
        ],
        "placetype": [
          "aat:300008706"
        ],
        "id": 2218603,
        "name:xx": "Cane Creek"
      }
    },
    {
      "geometry": {
        "type": "Point",
        "coordinates": [
          -88.8833,
          31.9833
        ]
      },
      "type": "Feature",
      "properties": {
        "hierarchy": [
          "tgn:2218604",
          "tgn:1000001",
          "tgn:2001097",
          "tgn:7012149",
          "tgn:7007522",
          "tgn:7029392"
        ],
        "placetype": [
          "aat:300008706"
        ],
        "id": 2218604,
        "name:xx": "Cane Creek"
      }
    },
    {
      "geometry": {
        "type": "Point",
        "coordinates": [
          -89.8833,
          32.4667
        ]
      },
      "type": "Feature",
      "properties": {
        "hierarchy": [
          "tgn:2218605",
          "tgn:1000001",
          "tgn:7012149",
          "tgn:2001146",
          "tgn:7007522",
          "tgn:7029392"
        ],
        "placetype": [
          "aat:300008706"
        ],
        "id": 2218605,
        "name:xx": "Cane Creek"
      }
    },
    {
      "geometry": {
        "type": "Point",
        "coordinates": [
          -89.8667,
          33.7
        ]
      },
      "type": "Feature",
      "properties": {
        "hierarchy": [
          "tgn:2218606",
          "tgn:1000001",
          "tgn:7012149",
          "tgn:2001107",
          "tgn:7007522",
          "tgn:7029392"
        ],
        "placetype": [
          "aat:300008706"
        ],
        "id": 2218606,
        "name:xx": "Cane Creek"
      }
    },
    {
      "geometry": {
        "type": "Point",
        "coordinates": [
          -89.1667,
          34
        ]
      },
      "type": "Feature",
      "properties": {
        "hierarchy": [
          "tgn:2218607",
          "tgn:1000001",
          "tgn:2001092",
          "tgn:7012149",
          "tgn:7007522",
          "tgn:7029392"
        ],
        "placetype": [
          "aat:300008706"
        ],
        "id": 2218607,
        "name:xx": "Cane Creek"
      }
    },
    {
      "geometry": {
        "type": "Point",
        "coordinates": [
          -88.8167,
          34.0333
        ]
      },
      "type": "Feature",
      "properties": {
        "hierarchy": [
          "tgn:2218608",
          "tgn:1000001",
          "tgn:2001094",
          "tgn:7012149",
          "tgn:7007522",
          "tgn:7029392"
        ],
        "placetype": [
          "aat:300008706"
        ],
        "id": 2218608,
        "name:xx": "Cane Creek"
      }
    },
    {
      "geometry": {
        "type": "Point",
        "coordinates": [
          -89.15,
          34.5333
        ]
      },
      "type": "Feature",
      "properties": {
        "hierarchy": [
          "tgn:2218609",
          "tgn:1000001",
          "tgn:7012149",
          "tgn:2001158",
          "tgn:7007522",
          "tgn:7029392"
        ],
        "placetype": [
          "aat:300008706"
        ],
        "id": 2218609,
        "name:xx": "Cane Creek"
      }
    }
  ]
}
