{
  "geometry": {
    "type": "Point",
    "coordinates": [
      -117.85,
      43.3333
    ]
  },
  "type": "Feature",
  "properties": {
    "hierarchy": [
      "tgn:2733670",
      "tgn:1000001",
      "tgn:7012149",
      "tgn:2001718",
      "tgn:7007708",
      "tgn:7029392"
    ],
    "placetype": [
      "aat:300008798"
    ],
    "id": 2733670,
    "name:xx": "Turnbull Mountain"
  }
}
