{
  "geometry": {
    "type": "Point",
    "coordinates": [
      -105.1667,
      38.9667
    ]
  },
  "type": "Feature",
  "properties": {
    "hierarchy": [
      "tgn:2266304",
      "tgn:1000001",
      "tgn:7012149",
      "tgn:7007158",
      "tgn:2000251",
      "tgn:7029392"
    ],
    "placetype": [
      "aat:300008761"
    ],
    "id": 2266304,
    "name:xx": "Crazy Gulch"
  }
}
