{
  "geometry": {
    "type": "Point",
    "coordinates": [
      -91.05,
      31.9167
    ]
  },
  "type": "Feature",
  "properties": {
    "hierarchy": [
      "tgn:2426300",
      "tgn:1000001",
      "tgn:2001096",
      "tgn:7012149",
      "tgn:7007522",
      "tgn:7029392"
    ],
    "placetype": [
      "aat:300008706"
    ],
    "id": 2426300,
    "name:xx": "Jones Creek"
  }
}
