{
  "geometry": {
    "type": "Point",
    "coordinates": [
      121.6562,
      24.1537
    ]
  },
  "type": "Feature",
  "properties": {
    "hierarchy": [
      "tgn:7469843",
      "tgn:7001010",
      "tgn:1000004",
      "tgn:1000141",
      "tgn:7029392"
    ],
    "placetype": [
      "aat:300387173"
    ],
    "id": 7469843,
    "name:xx": "Chongde Cun"
  }
}
