{
  "geometry": {
    "type": "Point",
    "coordinates": [
      -81.4667,
      40.4833
    ]
  },
  "type": "Feature",
  "properties": {
    "hierarchy": [
      "tgn:2182945",
      "tgn:1000001",
      "tgn:7012149",
      "tgn:1002958",
      "tgn:7007706",
      "tgn:7029392"
    ],
    "placetype": [
      "aat:300008791"
    ],
    "id": 2182945,
    "name:xx": "Bluebell Island"
  }
}
