{
  "geometry": {
    "type": "Point",
    "coordinates": [
      -102.8333,
      45.4167
    ]
  },
  "type": "Feature",
  "properties": {
    "hierarchy": [
      "tgn:2184803",
      "tgn:1000001",
      "tgn:7012149",
      "tgn:2001822",
      "tgn:7007713",
      "tgn:7029392"
    ],
    "placetype": [
      "aat:300008706"
    ],
    "id": 2184803,
    "name:xx": "Bog Creek"
  }
}
