{
  "geometry": {
    "type": "Point",
    "coordinates": [
      -68.4333,
      44.9167
    ]
  },
  "type": "Feature",
  "properties": {
    "hierarchy": [
      "tgn:2723091",
      "tgn:1000001",
      "tgn:2000922",
      "tgn:7012149",
      "tgn:7007515",
      "tgn:7029392"
    ],
    "placetype": [
      "aat:300008680"
    ],
    "id": 2723091,
    "name:xx": "Titcomb Pond"
  }
}
