{
  "type": "FeatureCollection",
  "features": [
    {
      "geometry": {
        "type": "Point",
        "coordinates": [
          12.066667,
          42.766667
        ]
      },
      "type": "Feature",
      "properties": {
        "hierarchy": [
          "tgn:7042631",
          "tgn:7003171",
          "tgn:1000003",
          "tgn:7003125",
          "tgn:1000080",
          "tgn:7029392"
        ],
        "placetype": [
          "aat:300008699"
        ],
        "id": 7042631,
        "name:xx": "Sala, Fosso della"
      }
    },
    {
      "geometry": {
        "type": "Point",
        "coordinates": [
          9.25,
          44.783333
        ]
      },
      "type": "Feature",
      "properties": {
        "hierarchy": [
          "tgn:7042632",
          "tgn:7003132",
          "tgn:1000003",
          "tgn:7008516",
          "tgn:1000080",
          "tgn:7029392"
        ],
        "placetype": [
          "aat:300008347"
        ],
        "id": 7042632,
        "name:xx": "Sala"
      }
    },
    {
      "geometry": {
        "type": "Point",
        "coordinates": [
          10.3,
          44.183333
        ]
      },
      "type": "Feature",
      "properties": {
        "hierarchy": [
          "tgn:7042633",
          "tgn:7003165",
          "tgn:1000003",
          "tgn:7009760",
          "tgn:1000080",
          "tgn:7029392"
        ],
        "placetype": [
          "aat:300008347"
        ],
        "id": 7042633,
        "name:xx": "Sala"
      }
    },
    {
      "geometry": {
        "type": "Point",
        "coordinates": [
          13.033333,
          42.583333
        ]
      },
      "type": "Feature",
      "properties": {
        "hierarchy": [
          "tgn:7042634",
          "tgn:7003170",
          "tgn:1000003",
          "tgn:7003125",
          "tgn:1000080",
          "tgn:7029392"
        ],
        "placetype": [
          "aat:300008347"
        ],
        "id": 7042634,
        "name:xx": "Sala"
      }
    },
    {
      "geometry": {
        "type": "Point",
        "coordinates": [
          12.9,
          42.35
        ]
      },
      "type": "Feature",
      "properties": {
        "hierarchy": [
          "tgn:7042635",
          "tgn:7003171",
          "tgn:1000003",
          "tgn:7003125",
          "tgn:1000080",
          "tgn:7029392"
        ],
        "placetype": [
          "aat:300008347"
        ],
        "id": 7042635,
        "name:xx": "Sala"
      }
    },
    {
      "geometry": {
        "type": "Point",
        "coordinates": [
          14.316667,
          41.083333
        ]
      },
      "type": "Feature",
      "properties": {
        "hierarchy": [
          "tgn:7042636",
          "tgn:7003011",
          "tgn:7003005",
          "tgn:1000003",
          "tgn:1000080",
          "tgn:7029392"
        ],
        "placetype": [
          "aat:300008347"
        ],
        "id": 7042636,
        "name:xx": "Sala"
      }
    },
    {
      "geometry": {
        "type": "Point",
        "coordinates": [
          9.033333,
          45.133333
        ]
      },
      "type": "Feature",
      "properties": {
        "hierarchy": [
          "tgn:7042637",
          "tgn:1000003",
          "tgn:7003151",
          "tgn:7003237",
          "tgn:1000080",
          "tgn:7029392"
        ],
        "placetype": [
          "aat:300008347"
        ],
        "id": 7042637,
        "name:xx": "Sairano"
      }
    },
    {
      "geometry": {
        "type": "Point",
        "coordinates": [
          11.116667,
          43.2
        ]
      },
      "type": "Feature",
      "properties": {
        "hierarchy": [
          "tgn:7042638",
          "tgn:7003168",
          "tgn:1000003",
          "tgn:7009760",
          "tgn:1000080",
          "tgn:7029392"
        ],
        "placetype": [
          "aat:300008699"
        ],
        "id": 7042638,
        "name:xx": "Saio, Torrente"
      }
    }
  ]
}
