{
  "type": "FeatureCollection",
  "features": [
    {
      "geometry": {
        "type": "Point",
        "coordinates": [
          -119.2,
          37.8833
        ]
      },
      "type": "Feature",
      "properties": {
        "hierarchy": [
          "tgn:2348510",
          "tgn:1000001",
          "tgn:7012149",
          "tgn:7007157",
          "tgn:1002675",
          "tgn:7029392"
        ],
        "placetype": [
          "aat:300008761"
        ],
        "id": 2348510,
        "name:xx": "Gibbs Canyon"
      }
    },
    {
      "geometry": {
        "type": "Point",
        "coordinates": [
          -88.7,
          46.2167
        ]
      },
      "type": "Feature",
      "properties": {
        "hierarchy": [
          "tgn:2348511",
          "tgn:1000001",
          "tgn:7012149",
          "tgn:2000966",
          "tgn:7007520",
          "tgn:7029392"
        ],
        "placetype": [
          "aat:300008347"
        ],
        "id": 2348511,
        "name:xx": "Gibbs City"
      }
    },
    {
      "geometry": {
        "type": "Point",
        "coordinates": [
          -108.0167,
          47.3
        ]
      },
      "type": "Feature",
      "properties": {
        "hierarchy": [
          "tgn:2348512",
          "tgn:1000001",
          "tgn:7012149",
          "tgn:2001294",
          "tgn:7007524",
          "tgn:7029392"
        ],
        "placetype": [
          "aat:300008761"
        ],
        "id": 2348512,
        "name:xx": "Gibbs Coulee"
      }
    },
    {
      "geometry": {
        "type": "Point",
        "coordinates": [
          -91.5,
          35.7833
        ]
      },
      "type": "Feature",
      "properties": {
        "hierarchy": [
          "tgn:2348513",
          "tgn:1000001",
          "tgn:7016172",
          "tgn:7012149",
          "tgn:2000136",
          "tgn:7029392"
        ],
        "placetype": [
          "aat:300008706"
        ],
        "id": 2348513,
        "name:xx": "Gibbs Creek"
      }
    },
    {
      "geometry": {
        "type": "Point",
        "coordinates": [
          -106.8,
          37.4833
        ]
      },
      "type": "Feature",
      "properties": {
        "hierarchy": [
          "tgn:2348514",
          "tgn:1000001",
          "tgn:7012149",
          "tgn:2000231",
          "tgn:7007158",
          "tgn:7029392"
        ],
        "placetype": [
          "aat:300008706"
        ],
        "id": 2348514,
        "name:xx": "Gibbs Creek"
      }
    },
    {
      "geometry": {
        "type": "Point",
        "coordinates": [
          -114.3833,
          45.4
        ]
      },
      "type": "Feature",
      "properties": {
        "hierarchy": [
          "tgn:2348515",
          "tgn:1000001",
          "tgn:7012149",
          "tgn:2000481",
          "tgn:7007250",
          "tgn:7029392"
        ],
        "placetype": [
          "aat:300008706"
        ],
        "id": 2348515,
        "name:xx": "Gibbs Creek"
      }
    },
    {
      "geometry": {
        "type": "Point",
        "coordinates": [
          -89.1667,
          38.6667
        ]
      },
      "type": "Feature",
      "properties": {
        "hierarchy": [
          "tgn:2348516",
          "tgn:1000001",
          "tgn:1002281",
          "tgn:7012149",
          "tgn:7007251",
          "tgn:7029392"
        ],
        "placetype": [
          "aat:300008706"
        ],
        "id": 2348516,
        "name:xx": "Gibbs Creek"
      }
    },
    {
      "geometry": {
        "type": "Point",
        "coordinates": [
          -89.75,
          33.7667
        ]
      },
      "type": "Feature",
      "properties": {
        "hierarchy": [
          "tgn:2348517",
          "tgn:1000001",
          "tgn:7012149",
          "tgn:2001107",
          "tgn:7007522",
          "tgn:7029392"
        ],
        "placetype": [
          "aat:300008706"
        ],
        "id": 2348517,
        "name:xx": "Gibbs Creek"
      }
    },
    {
      "geometry": {
        "type": "Point",
        "coordinates": [
          -89.65,
          32.6
        ]
      },
      "type": "Feature",
      "properties": {
        "hierarchy": [
          "tgn:2348518",
          "tgn:1000001",
          "tgn:7012149",
          "tgn:2001125",
          "tgn:7007522",
          "tgn:7029392"
        ],
        "placetype": [
          "aat:300008706"
        ],
        "id": 2348518,
        "name:xx": "Gibbs Creek"
      }
    },
    {
      "geometry": {
        "type": "Point",
        "coordinates": [
          -106.2667,
          47.3
        ]
      },
      "type": "Feature",
      "properties": {
        "hierarchy": [
          "tgn:2348519",
          "tgn:1000001",
          "tgn:7012149",
          "tgn:2001276",
          "tgn:7007524",
          "tgn:7029392"
        ],
        "placetype": [
          "aat:300008706"
        ],
        "id": 2348519,
        "name:xx": "Gibbs Creek"
      }
    }
  ]
}
