{
  "geometry": {
    "type": "Point",
    "coordinates": [
      -164.8667,
      61.7333
    ]
  },
  "type": "Feature",
  "properties": {
    "hierarchy": [
      "tgn:2436749",
      "tgn:7006450",
      "tgn:1000001",
      "tgn:7012149",
      "tgn:2000087",
      "tgn:7029392"
    ],
    "placetype": [
      "aat:300008707"
    ],
    "id": 2436749,
    "name:xx": "Kikneak River"
  }
}
