{
  "type": "FeatureCollection",
  "features": [
    {
      "geometry": {
        "type": "Point",
        "coordinates": [
          -84.1333,
          44.5167
        ]
      },
      "type": "Feature",
      "properties": {
        "hierarchy": [
          "tgn:2735760",
          "tgn:1000001",
          "tgn:7012149",
          "tgn:2000988",
          "tgn:7007520",
          "tgn:7029392"
        ],
        "placetype": [
          "aat:300008680"
        ],
        "id": 2735760,
        "name:xx": "Twin Lake"
      }
    },
    {
      "geometry": {
        "type": "Point",
        "coordinates": [
          -83.7333,
          44.55
        ]
      },
      "type": "Feature",
      "properties": {
        "hierarchy": [
          "tgn:2735761",
          "tgn:2000942",
          "tgn:1000001",
          "tgn:7012149",
          "tgn:7007520",
          "tgn:7029392"
        ],
        "placetype": [
          "aat:300008680"
        ],
        "id": 2735761,
        "name:xx": "Twin Lake"
      }
    },
    {
      "geometry": {
        "type": "Point",
        "coordinates": [
          -85.8167,
          44.5667
        ]
      },
      "type": "Feature",
      "properties": {
        "hierarchy": [
          "tgn:2735762",
          "tgn:1000001",
          "tgn:2000949",
          "tgn:7012149",
          "tgn:7007520",
          "tgn:7029392"
        ],
        "placetype": [
          "aat:300008680"
        ],
        "id": 2735762,
        "name:xx": "Twin Lake"
      }
    },
    {
      "geometry": {
        "type": "Point",
        "coordinates": [
          -85.3833,
          44.6667
        ]
      },
      "type": "Feature",
      "properties": {
        "hierarchy": [
          "tgn:2735763",
          "tgn:1000001",
          "tgn:7012149",
          "tgn:2000961",
          "tgn:7007520",
          "tgn:7029392"
        ],
        "placetype": [
          "aat:300008680"
        ],
        "id": 2735763,
        "name:xx": "Twin Lake"
      }
    },
    {
      "geometry": {
        "type": "Point",
        "coordinates": [
          -84.95,
          44.8167
        ]
      },
      "type": "Feature",
      "properties": {
        "hierarchy": [
          "tgn:2735764",
          "tgn:1000001",
          "tgn:7012149",
          "tgn:2000968",
          "tgn:7007520",
          "tgn:7029392"
        ],
        "placetype": [
          "aat:300008680"
        ],
        "id": 2735764,
        "name:xx": "Twin Lake"
      }
    },
    {
      "geometry": {
        "type": "Point",
        "coordinates": [
          -84.1167,
          45
        ]
      },
      "type": "Feature",
      "properties": {
        "hierarchy": [
          "tgn:2735765",
          "tgn:1000001",
          "tgn:7012149",
          "tgn:2000982",
          "tgn:7007520",
          "tgn:7029392"
        ],
        "placetype": [
          "aat:300008680"
        ],
        "id": 2735765,
        "name:xx": "Twin Lake"
      }
    },
    {
      "geometry": {
        "type": "Point",
        "coordinates": [
          -84.7167,
          45.7
        ]
      },
      "type": "Feature",
      "properties": {
        "hierarchy": [
          "tgn:2735766",
          "tgn:1000001",
          "tgn:2000951",
          "tgn:7012149",
          "tgn:7007520",
          "tgn:7029392"
        ],
        "placetype": [
          "aat:300008680"
        ],
        "id": 2735766,
        "name:xx": "Twin Lake"
      }
    },
    {
      "geometry": {
        "type": "Point",
        "coordinates": [
          -87.9833,
          46.45
        ]
      },
      "type": "Feature",
      "properties": {
        "hierarchy": [
          "tgn:2735767",
          "tgn:1000001",
          "tgn:7012149",
          "tgn:2000975",
          "tgn:7007520",
          "tgn:7029392"
        ],
        "placetype": [
          "aat:300008680"
        ],
        "id": 2735767,
        "name:xx": "Twin Lake"
      }
    },
    {
      "geometry": {
        "type": "Point",
        "coordinates": [
          -93.0833,
          45.0333
        ]
      },
      "type": "Feature",
      "properties": {
        "hierarchy": [
          "tgn:2735769",
          "tgn:1000001",
          "tgn:7012149",
          "tgn:2001060",
          "tgn:7007521",
          "tgn:7029392"
        ],
        "placetype": [
          "aat:300008680"
        ],
        "id": 2735769,
        "name:xx": "Twin Lake"
      }
    }
  ]
}
