{
  "geometry": {
    "type": "Point",
    "coordinates": [
      -117.2833,
      38.9333
    ]
  },
  "type": "Feature",
  "properties": {
    "hierarchy": [
      "tgn:2559849",
      "tgn:1000001",
      "tgn:2001418",
      "tgn:7012149",
      "tgn:7007526",
      "tgn:7029392"
    ],
    "placetype": [
      "aat:300000390"
    ],
    "id": 2559849,
    "name:xx": "Ophir Mine"
  }
}
