{
  "type": "FeatureCollection",
  "features": [
    {
      "geometry": {
        "type": "Point",
        "coordinates": [
          6.783333,
          51.783333
        ]
      },
      "type": "Feature",
      "properties": {
        "hierarchy": [
          "tgn:7080870",
          "tgn:1000003",
          "tgn:7003677",
          "tgn:7000084",
          "tgn:7029392"
        ],
        "placetype": [
          "aat:300000206"
        ],
        "id": 7080870,
        "name:xx": "Winkelschulte"
      }
    },
    {
      "geometry": {
        "type": "Point",
        "coordinates": [
          6.366667,
          51.583333
        ]
      },
      "type": "Feature",
      "properties": {
        "hierarchy": [
          "tgn:7080871",
          "tgn:1000003",
          "tgn:7003677",
          "tgn:7000084",
          "tgn:7029392"
        ],
        "placetype": [
          "aat:300008863"
        ],
        "id": 7080871,
        "name:xx": "Winkelscher-Busch"
      }
    },
    {
      "geometry": {
        "type": "Point",
        "coordinates": [
          10.55,
          47.6
        ]
      },
      "type": "Feature",
      "properties": {
        "hierarchy": [
          "tgn:7080872",
          "tgn:7003669",
          "tgn:1000003",
          "tgn:7000084",
          "tgn:7029392"
        ],
        "placetype": [
          "aat:300008699"
        ],
        "id": 7080872,
        "name:xx": "Winkels Bach"
      }
    },
    {
      "geometry": {
        "type": "Point",
        "coordinates": [
          11.95,
          48.6
        ]
      },
      "type": "Feature",
      "properties": {
        "hierarchy": [
          "tgn:7080873",
          "tgn:7003669",
          "tgn:1000003",
          "tgn:7000084",
          "tgn:7029392"
        ],
        "placetype": [
          "aat:300000206"
        ],
        "id": 7080873,
        "name:xx": "Winkelsbach"
      }
    },
    {
      "geometry": {
        "type": "Point",
        "coordinates": [
          8.183333,
          50.55
        ]
      },
      "type": "Feature",
      "properties": {
        "hierarchy": [
          "tgn:7080874",
          "tgn:1000003",
          "tgn:7003678",
          "tgn:7000084",
          "tgn:7029392"
        ],
        "placetype": [
          "aat:300008347"
        ],
        "id": 7080874,
        "name:xx": "Winkels"
      }
    },
    {
      "geometry": {
        "type": "Point",
        "coordinates": [
          10.1,
          50.2
        ]
      },
      "type": "Feature",
      "properties": {
        "hierarchy": [
          "tgn:7080875",
          "tgn:7003669",
          "tgn:1000003",
          "tgn:7000084",
          "tgn:7029392"
        ],
        "placetype": [
          "aat:300008347"
        ],
        "id": 7080875,
        "name:xx": "Winkels"
      }
    },
    {
      "geometry": {
        "type": "Point",
        "coordinates": [
          10.25,
          47.8
        ]
      },
      "type": "Feature",
      "properties": {
        "hierarchy": [
          "tgn:7080876",
          "tgn:7003669",
          "tgn:1000003",
          "tgn:7000084",
          "tgn:7029392"
        ],
        "placetype": [
          "aat:300008347"
        ],
        "id": 7080876,
        "name:xx": "Winkels"
      }
    },
    {
      "geometry": {
        "type": "Point",
        "coordinates": [
          13.333333,
          48.883333
        ]
      },
      "type": "Feature",
      "properties": {
        "hierarchy": [
          "tgn:7080877",
          "tgn:7003669",
          "tgn:1000003",
          "tgn:7000084",
          "tgn:7029392"
        ],
        "placetype": [
          "aat:300000206"
        ],
        "id": 7080877,
        "name:xx": "Winkelreuth"
      }
    },
    {
      "geometry": {
        "type": "Point",
        "coordinates": [
          7.6,
          51.266667
        ]
      },
      "type": "Feature",
      "properties": {
        "hierarchy": [
          "tgn:7080878",
          "tgn:1000003",
          "tgn:7003677",
          "tgn:7000084",
          "tgn:7029392"
        ],
        "placetype": [
          "aat:300008347"
        ],
        "id": 7080878,
        "name:xx": "Winkeln"
      }
    },
    {
      "geometry": {
        "type": "Point",
        "coordinates": [
          6.366667,
          51.2
        ]
      },
      "type": "Feature",
      "properties": {
        "hierarchy": [
          "tgn:7080879",
          "tgn:1000003",
          "tgn:7003677",
          "tgn:7000084",
          "tgn:7029392"
        ],
        "placetype": [
          "aat:300008347"
        ],
        "id": 7080879,
        "name:xx": "Winkeln"
      }
    }
  ]
}
