{
  "geometry": {
    "type": "Point",
    "coordinates": [
      -122.9167,
      39.4833
    ]
  },
  "type": "Feature",
  "properties": {
    "hierarchy": [
      "tgn:2183887",
      "tgn:1000001",
      "tgn:7012149",
      "tgn:7007157",
      "tgn:7029392"
    ],
    "placetype": [
      "aat:300266640"
    ],
    "id": 2183887,
    "name:xx": "Boardman Ridge"
  }
}
