{
  "type": "FeatureCollection",
  "features": [
    {
      "geometry": {
        "type": "Point",
        "coordinates": [
          -118.5167,
          41.2
        ]
      },
      "type": "Feature",
      "properties": {
        "hierarchy": [
          "tgn:2610230",
          "tgn:1000001",
          "tgn:2001414",
          "tgn:7012149",
          "tgn:7007526",
          "tgn:7029392"
        ],
        "placetype": [
          "aat:300000390"
        ],
        "id": 2610230,
        "name:xx": "Red Boy Mine"
      }
    },
    {
      "geometry": {
        "type": "Point",
        "coordinates": [
          -118.4667,
          44.7833
        ]
      },
      "type": "Feature",
      "properties": {
        "hierarchy": [
          "tgn:2610231",
          "tgn:1000001",
          "tgn:7012149",
          "tgn:2001708",
          "tgn:7007708",
          "tgn:7029392"
        ],
        "placetype": [
          "aat:300000390"
        ],
        "id": 2610231,
        "name:xx": "Red Boy Mine"
      }
    },
    {
      "geometry": {
        "type": "Point",
        "coordinates": [
          -111.2,
          31.85
        ]
      },
      "type": "Feature",
      "properties": {
        "hierarchy": [
          "tgn:2610232",
          "tgn:1000001",
          "tgn:7006451",
          "tgn:7012149",
          "tgn:2000100",
          "tgn:7029392"
        ],
        "placetype": [
          "aat:300008798"
        ],
        "id": 2610232,
        "name:xx": "Red Boy Peak"
      }
    },
    {
      "geometry": {
        "type": "Point",
        "coordinates": [
          -87.25,
          34.6167
        ]
      },
      "type": "Feature",
      "properties": {
        "hierarchy": [
          "tgn:2610233",
          "tgn:7002659",
          "tgn:1000001",
          "tgn:7012149",
          "tgn:2000039",
          "tgn:7029392"
        ],
        "placetype": [
          "aat:300008699"
        ],
        "id": 2610233,
        "name:xx": "Red Branch"
      }
    },
    {
      "geometry": {
        "type": "Point",
        "coordinates": [
          -87.0833,
          30.9833
        ]
      },
      "type": "Feature",
      "properties": {
        "hierarchy": [
          "tgn:2610234",
          "tgn:1000001",
          "tgn:7012149",
          "tgn:7029392"
        ],
        "placetype": [
          "aat:300008699"
        ],
        "id": 2610234,
        "name:xx": "Red Branch"
      }
    },
    {
      "geometry": {
        "type": "Point",
        "coordinates": [
          -93.5333,
          33.3167
        ]
      },
      "type": "Feature",
      "properties": {
        "hierarchy": [
          "tgn:2610235",
          "tgn:1000001",
          "tgn:7016172",
          "tgn:7012149",
          "tgn:2000141",
          "tgn:7029392"
        ],
        "placetype": [
          "aat:300008699"
        ],
        "id": 2610235,
        "name:xx": "Red Branch"
      }
    },
    {
      "geometry": {
        "type": "Point",
        "coordinates": [
          -94.0833,
          33.5833
        ]
      },
      "type": "Feature",
      "properties": {
        "hierarchy": [
          "tgn:2610236",
          "tgn:1000001",
          "tgn:7016172",
          "tgn:7012149",
          "tgn:2000145",
          "tgn:7029392"
        ],
        "placetype": [
          "aat:300008699"
        ],
        "id": 2610236,
        "name:xx": "Red Branch"
      }
    },
    {
      "geometry": {
        "type": "Point",
        "coordinates": [
          -93.9167,
          34.1167
        ]
      },
      "type": "Feature",
      "properties": {
        "hierarchy": [
          "tgn:2610237",
          "tgn:1000001",
          "tgn:7016172",
          "tgn:7012149",
          "tgn:2000135",
          "tgn:7029392"
        ],
        "placetype": [
          "aat:300008699"
        ],
        "id": 2610237,
        "name:xx": "Red Branch"
      }
    },
    {
      "geometry": {
        "type": "Point",
        "coordinates": [
          -93.4333,
          34.5
        ]
      },
      "type": "Feature",
      "properties": {
        "hierarchy": [
          "tgn:2610238",
          "tgn:1000001",
          "tgn:7016172",
          "tgn:7012149",
          "tgn:7029392"
        ],
        "placetype": [
          "aat:300008699"
        ],
        "id": 2610238,
        "name:xx": "Red Branch"
      }
    },
    {
      "geometry": {
        "type": "Point",
        "coordinates": [
          -92.6,
          33.9667
        ]
      },
      "type": "Feature",
      "properties": {
        "hierarchy": [
          "tgn:2610239",
          "tgn:1000001",
          "tgn:7016172",
          "tgn:7012149",
          "tgn:2000124",
          "tgn:7029392"
        ],
        "placetype": [
          "aat:300008699"
        ],
        "id": 2610239,
        "name:xx": "Red Branch"
      }
    }
  ]
}
