{
  "geometry": {
    "type": "Point",
    "coordinates": [
      -112.1833,
      40.4167
    ]
  },
  "type": "Feature",
  "properties": {
    "hierarchy": [
      "tgn:2491275",
      "tgn:1000001",
      "tgn:7012149",
      "tgn:2002125",
      "tgn:7007827",
      "tgn:7029392"
    ],
    "placetype": [
      "aat:300008761"
    ],
    "id": 2491275,
    "name:xx": "Maple Canyon"
  }
}
