{
  "geometry": {
    "type": "Point",
    "coordinates": [
      -100.5667,
      35.55
    ]
  },
  "type": "Feature",
  "properties": {
    "hierarchy": [
      "tgn:2262857",
      "tgn:1000001",
      "tgn:7012149",
      "tgn:7007826",
      "tgn:7029392"
    ],
    "placetype": [
      "aat:300008706"
    ],
    "id": 2262857,
    "name:xx": "Cowboy Creek"
  }
}
