{
  "type": "FeatureCollection",
  "features": [
    {
      "geometry": {
        "type": "Point",
        "coordinates": [
          30.895668,
          31.311731
        ]
      },
      "type": "Feature",
      "properties": {
        "hierarchy": [
          "tgn:7530430",
          "tgn:7001242",
          "tgn:7016833",
          "tgn:1001335",
          "tgn:7029392"
        ],
        "placetype": [
          "aat:300008347"
        ],
        "name:en": "'Izbat al 'Ishrīn",
        "id": 7530430
      }
    },
    {
      "geometry": {
        "type": "Point",
        "coordinates": [
          30.853953,
          31.303514
        ]
      },
      "type": "Feature",
      "properties": {
        "hierarchy": [
          "tgn:7530431",
          "tgn:7001242",
          "tgn:7016833",
          "tgn:1001335",
          "tgn:7029392"
        ],
        "placetype": [
          "aat:300008347"
        ],
        "name:en": "'Izbat Abū al 'Azāyim",
        "id": 7530431
      }
    },
    {
      "geometry": {
        "type": "Point",
        "coordinates": [
          30.883702,
          31.306947
        ]
      },
      "type": "Feature",
      "properties": {
        "hierarchy": [
          "tgn:7530432",
          "tgn:7001242",
          "tgn:7016833",
          "tgn:1001335",
          "tgn:7029392"
        ],
        "placetype": [
          "aat:300008347"
        ],
        "name:en": "Al Manshīyah al Jadīdah",
        "id": 7530432
      }
    },
    {
      "geometry": {
        "type": "Point",
        "coordinates": [
          30.926885,
          31.289824
        ]
      },
      "type": "Feature",
      "properties": {
        "hierarchy": [
          "tgn:7530433",
          "tgn:7001242",
          "tgn:7016833",
          "tgn:1001335",
          "tgn:7029392"
        ],
        "placetype": [
          "aat:300008347"
        ],
        "name:en": "'Izbat as Sayyid Khalīl",
        "id": 7530433
      }
    },
    {
      "geometry": {
        "type": "Point",
        "coordinates": [
          30.924517,
          31.279861
        ]
      },
      "type": "Feature",
      "properties": {
        "hierarchy": [
          "tgn:7530434",
          "tgn:7001242",
          "tgn:7016833",
          "tgn:1001335",
          "tgn:7029392"
        ],
        "placetype": [
          "aat:300008347"
        ],
        "name:en": "'Izbat Biltājī al Fiqī",
        "id": 7530434
      }
    },
    {
      "geometry": {
        "type": "Point",
        "coordinates": [
          30.936259,
          31.322698
        ]
      },
      "type": "Feature",
      "properties": {
        "hierarchy": [
          "tgn:7530435",
          "tgn:7001242",
          "tgn:7016833",
          "tgn:1001335",
          "tgn:7029392"
        ],
        "placetype": [
          "aat:300008347"
        ],
        "name:en": "'Izbat Abū Jayyid",
        "id": 7530435
      }
    },
    {
      "geometry": {
        "type": "Point",
        "coordinates": [
          30.938619,
          31.285586
        ]
      },
      "type": "Feature",
      "properties": {
        "hierarchy": [
          "tgn:7530436",
          "tgn:7001242",
          "tgn:7016833",
          "tgn:1001335",
          "tgn:7029392"
        ],
        "placetype": [
          "aat:300008347"
        ],
        "name:en": "'Izbat Sa'd Abū 'Alī",
        "id": 7530436
      }
    },
    {
      "geometry": {
        "type": "Point",
        "coordinates": [
          30.916493,
          31.305679
        ]
      },
      "type": "Feature",
      "properties": {
        "hierarchy": [
          "tgn:7530437",
          "tgn:7001242",
          "tgn:7016833",
          "tgn:1001335",
          "tgn:7029392"
        ],
        "placetype": [
          "aat:300008347"
        ],
        "name:en": "'Izbat Makhālī",
        "id": 7530437
      }
    },
    {
      "geometry": {
        "type": "Point",
        "coordinates": [
          30.812778,
          31.278889
        ]
      },
      "type": "Feature",
      "properties": {
        "hierarchy": [
          "tgn:7530438",
          "tgn:7001242",
          "tgn:7016833",
          "tgn:1001335",
          "tgn:7029392"
        ],
        "placetype": [
          "aat:300008347"
        ],
        "name:en": "'Izbat Abū Aḩmad",
        "id": 7530438
      }
    },
    {
      "geometry": {
        "type": "Point",
        "coordinates": [
          30.839072,
          31.296154
        ]
      },
      "type": "Feature",
      "properties": {
        "hierarchy": [
          "tgn:7530439",
          "tgn:7001242",
          "tgn:7016833",
          "tgn:1001335",
          "tgn:7029392"
        ],
        "placetype": [
          "aat:300008347"
        ],
        "name:en": "'Izbat al 'Umdah al Ghannām",
        "id": 7530439
      }
    }
  ]
}
