{
  "geometry": {
    "type": "Point",
    "coordinates": [
      82.0167,
      30.6833
    ]
  },
  "type": "Feature",
  "properties": {
    "hierarchy": [
      "tgn:1070757",
      "tgn:1000004",
      "tgn:7001319",
      "tgn:1000111",
      "tgn:7029392"
    ],
    "placetype": [
      "aat:300008347"
    ],
    "id": 1070757,
    "name:xx": "Niuke"
  }
}
