{
  "geometry": {
    "type": "Point",
    "coordinates": [
      9.3667,
      51.65
    ]
  },
  "type": "Feature",
  "properties": {
    "hierarchy": [
      "tgn:1040050",
      "tgn:1000003",
      "tgn:7003676",
      "tgn:7000084",
      "tgn:7029392"
    ],
    "placetype": [
      "aat:300008347"
    ],
    "id": 1040050,
    "name:xx": "Lauenförde"
  }
}
