{
  "geometry": {
    "type": "Point",
    "coordinates": [
      -80.5333,
      32.9167
    ]
  },
  "type": "Feature",
  "properties": {
    "hierarchy": [
      "tgn:2277231",
      "tgn:1000001",
      "tgn:2001739",
      "tgn:7012149",
      "tgn:7007712",
      "tgn:7029392"
    ],
    "placetype": [
      "aat:300008347"
    ],
    "id": 2277231,
    "name:xx": "Davis Hill"
  }
}
