{
  "geometry": {
    "type": "Point",
    "coordinates": [
      -54.7833,
      5.8667
    ]
  },
  "type": "Feature",
  "properties": {
    "hierarchy": [
      "tgn:1024827",
      "tgn:1000830",
      "tgn:1000002",
      "tgn:7015386",
      "tgn:7029392"
    ],
    "placetype": [
      "aat:300008347"
    ],
    "id": 1024827,
    "name:xx": "Charlottenburg"
  }
}
