{
  "geometry": {
    "type": "Point",
    "coordinates": [
      -109.3333,
      40.9667
    ]
  },
  "type": "Feature",
  "properties": {
    "hierarchy": [
      "tgn:2366765",
      "tgn:1000001",
      "tgn:2002105",
      "tgn:7012149",
      "tgn:7007827",
      "tgn:7029392"
    ],
    "placetype": [
      "aat:300008761"
    ],
    "id": 2366765,
    "name:xx": "Grindstone Wash"
  }
}
