{
  "geometry": {
    "type": "Point",
    "coordinates": [
      -104.6833,
      35.65
    ]
  },
  "type": "Feature",
  "properties": {
    "hierarchy": [
      "tgn:2682749",
      "tgn:1000001",
      "tgn:7012149",
      "tgn:2001453",
      "tgn:7007566",
      "tgn:7029392"
    ],
    "placetype": [
      "aat:300000390"
    ],
    "id": 2682749,
    "name:xx": "Southwest 1 Conchas"
  }
}
