{
  "geometry": {
    "type": "Point",
    "coordinates": [
      31.083333,
      29.05
    ]
  },
  "type": "Feature",
  "properties": {
    "hierarchy": [
      "tgn:7522702",
      "tgn:7001242",
      "tgn:7016833",
      "tgn:1001142",
      "tgn:7029392"
    ],
    "placetype": [
      "aat:300008777"
    ],
    "name:en": "Aşfar, At Tall al",
    "id": 7522702
  }
}
