{
  "geometry": {
    "type": "Point",
    "coordinates": [
      14.9667,
      48.5833
    ]
  },
  "type": "Feature",
  "properties": {
    "hierarchy": [
      "tgn:1025606",
      "tgn:7003025",
      "tgn:1000003",
      "tgn:1000062",
      "tgn:7029392"
    ],
    "placetype": [
      "aat:300008347"
    ],
    "id": 1025606,
    "name:xx": "Gross Gerungs"
  }
}
