{
  "geometry": {
    "type": "Point",
    "coordinates": [
      -82.8833,
      35.0167
    ]
  },
  "type": "Feature",
  "properties": {
    "hierarchy": [
      "tgn:2285618",
      "tgn:1000001",
      "tgn:7012149",
      "tgn:2001763",
      "tgn:7007712",
      "tgn:7029392"
    ],
    "placetype": [
      "aat:300008706"
    ],
    "id": 2285618,
    "name:xx": "Devils Hole Creek"
  }
}
