{
  "geometry": {
    "type": "Point",
    "coordinates": [
      -97.4833,
      25.9167
    ]
  },
  "type": "Feature",
  "properties": {
    "hierarchy": [
      "tgn:2726730",
      "tgn:1000001",
      "tgn:7012149",
      "tgn:2001952",
      "tgn:7007826",
      "tgn:7029392"
    ],
    "placetype": [
      "aat:300008680"
    ],
    "id": 2726730,
    "name:xx": "Town Resaca"
  }
}
