{
  "type": "FeatureCollection",
  "features": [
    {
      "geometry": {
        "type": "Point",
        "coordinates": [
          -86.65,
          46.55
        ]
      },
      "type": "Feature",
      "properties": {
        "hierarchy": [
          "tgn:2550160",
          "tgn:2000943",
          "tgn:1000001",
          "tgn:7012149",
          "tgn:7007520",
          "tgn:7029392"
        ],
        "placetype": [
          "aat:300008850"
        ],
        "id": 2550160,
        "name:xx": "Northeast Point"
      }
    },
    {
      "geometry": {
        "type": "Point",
        "coordinates": [
          -71.3167,
          41.6167
        ]
      },
      "type": "Feature",
      "properties": {
        "hierarchy": [
          "tgn:2550161",
          "tgn:1002716",
          "tgn:1000001",
          "tgn:7012149",
          "tgn:7007711",
          "tgn:7029392"
        ],
        "placetype": [
          "aat:300008850"
        ],
        "id": 2550161,
        "name:xx": "Northeast Point"
      }
    },
    {
      "geometry": {
        "type": "Point",
        "coordinates": [
          -79.5667,
          32.9333
        ]
      },
      "type": "Feature",
      "properties": {
        "hierarchy": [
          "tgn:2550162",
          "tgn:1000001",
          "tgn:2001734",
          "tgn:7012149",
          "tgn:7007712",
          "tgn:7029392"
        ],
        "placetype": [
          "aat:300008850"
        ],
        "id": 2550162,
        "name:xx": "Northeast Point"
      }
    },
    {
      "geometry": {
        "type": "Point",
        "coordinates": [
          -69.3833,
          44
        ]
      },
      "type": "Feature",
      "properties": {
        "hierarchy": [
          "tgn:2550163",
          "tgn:1000001",
          "tgn:2000925",
          "tgn:7012149",
          "tgn:7007515",
          "tgn:7029392"
        ],
        "placetype": [
          "aat:300132348"
        ],
        "id": 2550163,
        "name:xx": "Northeast Point Ledges"
      }
    },
    {
      "geometry": {
        "type": "Point",
        "coordinates": [
          -69.3167,
          43.95
        ]
      },
      "type": "Feature",
      "properties": {
        "hierarchy": [
          "tgn:2550164",
          "tgn:1000001",
          "tgn:2000924",
          "tgn:7012149",
          "tgn:7007515",
          "tgn:7029392"
        ],
        "placetype": [
          "aat:300132348"
        ],
        "id": 2550164,
        "name:xx": "Northeast Point Reef"
      }
    },
    {
      "geometry": {
        "type": "Point",
        "coordinates": [
          -70.35,
          44.3333
        ]
      },
      "type": "Feature",
      "properties": {
        "hierarchy": [
          "tgn:2550165",
          "tgn:1000001",
          "tgn:7012149",
          "tgn:2000926",
          "tgn:7007515",
          "tgn:7029392"
        ],
        "placetype": [
          "aat:300008680"
        ],
        "id": 2550165,
        "name:xx": "Northeast Pond"
      }
    },
    {
      "geometry": {
        "type": "Point",
        "coordinates": [
          -70.95,
          43.4333
        ]
      },
      "type": "Feature",
      "properties": {
        "hierarchy": [
          "tgn:2550166",
          "tgn:1000001",
          "tgn:7012149",
          "tgn:7029392"
        ],
        "placetype": [
          "aat:300008680"
        ],
        "id": 2550166,
        "name:xx": "Northeast Pond"
      }
    },
    {
      "geometry": {
        "type": "Point",
        "coordinates": [
          -69.9833,
          41.9333
        ]
      },
      "type": "Feature",
      "properties": {
        "hierarchy": [
          "tgn:2550167",
          "tgn:1002165",
          "tgn:1000001",
          "tgn:7012149",
          "tgn:7007517",
          "tgn:7029392"
        ],
        "placetype": [
          "aat:300008680"
        ],
        "id": 2550167,
        "name:xx": "Northeast Pond"
      }
    },
    {
      "geometry": {
        "type": "Point",
        "coordinates": [
          -75.8333,
          36.3167
        ]
      },
      "type": "Feature",
      "properties": {
        "hierarchy": [
          "tgn:2550168",
          "tgn:1000001",
          "tgn:7012149",
          "tgn:1002312",
          "tgn:7007709",
          "tgn:7029392"
        ],
        "placetype": [
          "aat:300008680"
        ],
        "id": 2550168,
        "name:xx": "Northeast Pond"
      }
    },
    {
      "geometry": {
        "type": "Point",
        "coordinates": [
          -98.2833,
          34.7667
        ]
      },
      "type": "Feature",
      "properties": {
        "hierarchy": [
          "tgn:2550169",
          "tgn:1000001",
          "tgn:2001638",
          "tgn:7012149",
          "tgn:7007707",
          "tgn:7029392"
        ],
        "placetype": [
          "aat:300008680"
        ],
        "id": 2550169,
        "name:xx": "Northeast Pond"
      }
    }
  ]
}
