{
  "geometry": {
    "type": "Point",
    "coordinates": [
      -82.8833,
      31.1333
    ]
  },
  "type": "Feature",
  "properties": {
    "hierarchy": [
      "tgn:2136163",
      "tgn:1000001",
      "tgn:2000323",
      "tgn:7012149",
      "tgn:7007248",
      "tgn:7029392"
    ],
    "placetype": [
      "aat:300008905"
    ],
    "id": 2136163,
    "name:xx": "Arabia Swamp"
  }
}
