{
  "geometry": {
    "type": "Point",
    "coordinates": [
      -97.55,
      30.8667
    ]
  },
  "type": "Feature",
  "properties": {
    "hierarchy": [
      "tgn:2677737",
      "tgn:1000001",
      "tgn:1002174",
      "tgn:7012149",
      "tgn:7007826",
      "tgn:7029392"
    ],
    "placetype": [
      "aat:300008706"
    ],
    "id": 2677737,
    "name:xx": "South Darrs Creek"
  }
}
