{
  "geometry": {
    "type": "Point",
    "coordinates": [
      -105.5333,
      40.2833
    ]
  },
  "type": "Feature",
  "properties": {
    "hierarchy": [
      "tgn:2709809",
      "tgn:1000001",
      "tgn:7012149",
      "tgn:7007158",
      "tgn:7029392"
    ],
    "placetype": [
      "aat:300008761"
    ],
    "id": 2709809,
    "name:xx": "Tahosa Valley"
  }
}
