{
  "geometry": {
    "type": "Point",
    "coordinates": [
      77.144722,
      21.466667
    ]
  },
  "type": "Feature",
  "properties": {
    "hierarchy": [
      "tgn:7579255",
      "tgn:1000004",
      "tgn:7000198",
      "tgn:1001895",
      "tgn:7029392"
    ],
    "placetype": [
      "aat:300008347"
    ],
    "name:en": "Tārubānda",
    "id": 7579255
  }
}
