{
  "geometry": {
    "type": "Point",
    "coordinates": [
      120.6167,
      40.9167
    ]
  },
  "type": "Feature",
  "properties": {
    "hierarchy": [
      "tgn:1068324",
      "tgn:1000004",
      "tgn:1001390",
      "tgn:1000111",
      "tgn:7029392"
    ],
    "placetype": [
      "aat:300008347"
    ],
    "id": 1068324,
    "name:xx": "Gongjiatun"
  }
}
