{
  "type": "FeatureCollection",
  "features": [
    {
      "geometry": {
        "type": "Point",
        "coordinates": [
          -84.4667,
          35
        ]
      },
      "type": "Feature",
      "properties": {
        "hierarchy": [
          "tgn:2202850",
          "tgn:1000001",
          "tgn:7012149",
          "tgn:2001906",
          "tgn:7007825",
          "tgn:7029392"
        ],
        "placetype": [
          "aat:300008761"
        ],
        "id": 2202850,
        "name:xx": "Buckeye Cove"
      }
    },
    {
      "geometry": {
        "type": "Point",
        "coordinates": [
          -83.6,
          35.5833
        ]
      },
      "type": "Feature",
      "properties": {
        "hierarchy": [
          "tgn:2202851",
          "tgn:1000001",
          "tgn:7012149",
          "tgn:2001914",
          "tgn:7007825",
          "tgn:7029392"
        ],
        "placetype": [
          "aat:300008761"
        ],
        "id": 2202851,
        "name:xx": "Buckeye Cove"
      }
    },
    {
      "geometry": {
        "type": "Point",
        "coordinates": [
          -87.8167,
          32.2333
        ]
      },
      "type": "Feature",
      "properties": {
        "hierarchy": [
          "tgn:2202852",
          "tgn:7002659",
          "tgn:1000001",
          "tgn:7012149",
          "tgn:2000045",
          "tgn:7029392"
        ],
        "placetype": [
          "aat:300008706"
        ],
        "id": 2202852,
        "name:xx": "Buckeye Creek"
      }
    },
    {
      "geometry": {
        "type": "Point",
        "coordinates": [
          -146.2333,
          64.35
        ]
      },
      "type": "Feature",
      "properties": {
        "hierarchy": [
          "tgn:2202853",
          "tgn:7006450",
          "tgn:1000001",
          "tgn:7019674",
          "tgn:7012149",
          "tgn:7029392"
        ],
        "placetype": [
          "aat:300008706"
        ],
        "id": 2202853,
        "name:xx": "Buckeye Creek"
      }
    },
    {
      "geometry": {
        "type": "Point",
        "coordinates": [
          -149.5333,
          65.3667
        ]
      },
      "type": "Feature",
      "properties": {
        "hierarchy": [
          "tgn:2202854",
          "tgn:7006450",
          "tgn:1000001",
          "tgn:7012149",
          "tgn:2000089",
          "tgn:7029392"
        ],
        "placetype": [
          "aat:300008706"
        ],
        "id": 2202854,
        "name:xx": "Buckeye Creek"
      }
    },
    {
      "geometry": {
        "type": "Point",
        "coordinates": [
          -141.1167,
          64.7
        ]
      },
      "type": "Feature",
      "properties": {
        "hierarchy": [
          "tgn:2202855",
          "tgn:7006450",
          "tgn:1000001",
          "tgn:7012149",
          "tgn:2000085",
          "tgn:7029392"
        ],
        "placetype": [
          "aat:300008706"
        ],
        "id": 2202855,
        "name:xx": "Buckeye Creek"
      }
    },
    {
      "geometry": {
        "type": "Point",
        "coordinates": [
          -119.0833,
          36.5833
        ]
      },
      "type": "Feature",
      "properties": {
        "hierarchy": [
          "tgn:2202856",
          "tgn:1000001",
          "tgn:7012149",
          "tgn:7007157",
          "tgn:1002956",
          "tgn:7029392"
        ],
        "placetype": [
          "aat:300008706"
        ],
        "id": 2202856,
        "name:xx": "Buckeye Creek"
      }
    },
    {
      "geometry": {
        "type": "Point",
        "coordinates": [
          -119.9667,
          37.4667
        ]
      },
      "type": "Feature",
      "properties": {
        "hierarchy": [
          "tgn:2202857",
          "tgn:1000001",
          "tgn:7012149",
          "tgn:7007157",
          "tgn:7014004",
          "tgn:7029392"
        ],
        "placetype": [
          "aat:300008706"
        ],
        "id": 2202857,
        "name:xx": "Buckeye Creek"
      }
    },
    {
      "geometry": {
        "type": "Point",
        "coordinates": [
          -121.2333,
          39.6
        ]
      },
      "type": "Feature",
      "properties": {
        "hierarchy": [
          "tgn:2202858",
          "tgn:1000001",
          "tgn:1002218",
          "tgn:7012149",
          "tgn:7007157",
          "tgn:7029392"
        ],
        "placetype": [
          "aat:300008706"
        ],
        "id": 2202858,
        "name:xx": "Buckeye Creek"
      }
    },
    {
      "geometry": {
        "type": "Point",
        "coordinates": [
          -122.8667,
          40.8
        ]
      },
      "type": "Feature",
      "properties": {
        "hierarchy": [
          "tgn:2202859",
          "tgn:1000001",
          "tgn:7012149",
          "tgn:7007157",
          "tgn:2000191",
          "tgn:7029392"
        ],
        "placetype": [
          "aat:300008706"
        ],
        "id": 2202859,
        "name:xx": "Buckeye Creek"
      }
    }
  ]
}
