{
  "geometry": {
    "type": "Point",
    "coordinates": [
      -94.45,
      32.1167
    ]
  },
  "type": "Feature",
  "properties": {
    "hierarchy": [
      "tgn:2276905",
      "tgn:1000001",
      "tgn:7012149",
      "tgn:1002769",
      "tgn:7007826",
      "tgn:7029392"
    ],
    "placetype": [
      "aat:300008699"
    ],
    "id": 2276905,
    "name:xx": "Davis Branch"
  }
}
