{
  "geometry": {
    "type": "Point",
    "coordinates": [
      -81.2167,
      36.65
    ]
  },
  "type": "Feature",
  "properties": {
    "hierarchy": [
      "tgn:2002164",
      "tgn:1000001",
      "tgn:7012149",
      "tgn:7007919",
      "tgn:7029392"
    ],
    "placetype": [
      "aat:300387145",
      "aat:300000771"
    ],
    "id": 2002164,
    "name:xx": "Grayson"
  }
}
