{
  "geometry": {
    "type": "Point",
    "coordinates": [
      43.5833,
      -22.95
    ]
  },
  "type": "Feature",
  "properties": {
    "hierarchy": [
      "tgn:1090815",
      "tgn:7001242",
      "tgn:1001575",
      "tgn:1000173",
      "tgn:7029392"
    ],
    "placetype": [
      "aat:300008347"
    ],
    "id": 1090815,
    "name:xx": "Ankilimalinika"
  }
}
