{
  "geometry": {
    "type": "Point",
    "coordinates": [
      43.6833,
      -23.3333
    ]
  },
  "type": "Feature",
  "properties": {
    "hierarchy": [
      "tgn:1091015",
      "tgn:7001242",
      "tgn:1001575",
      "tgn:1000173",
      "tgn:7029392"
    ],
    "placetype": [
      "aat:300008347",
      "aat:300387223",
      "aat:300008375",
      "aat:300120599"
    ],
    "id": 1091015,
    "name:xx": "Toliara"
  }
}
