{
  "geometry": {
    "type": "Point",
    "coordinates": [
      -76.75,
      39.8167
    ]
  },
  "type": "Feature",
  "properties": {
    "hierarchy": [
      "tgn:2092897",
      "tgn:1000001",
      "tgn:7012149",
      "tgn:1003047",
      "tgn:7007710",
      "tgn:7029392"
    ],
    "placetype": [
      "aat:300008347"
    ],
    "id": 2092897,
    "name:xx": "Seitzville"
  }
}
