{
  "geometry": {
    "type": "Point",
    "coordinates": [
      29.1667,
      39.6833
    ]
  },
  "type": "Feature",
  "properties": {
    "hierarchy": [
      "tgn:1085784",
      "tgn:1001167",
      "tgn:1000004",
      "tgn:7018450",
      "tgn:1000144",
      "tgn:7029392"
    ],
    "placetype": [
      "aat:300008347"
    ],
    "id": 1085784,
    "name:xx": "Harmancık"
  }
}
