{
  "geometry": {
    "type": "Point",
    "coordinates": [
      -73.8333,
      41.0333
    ]
  },
  "type": "Feature",
  "properties": {
    "hierarchy": [
      "tgn:2148869",
      "tgn:1000001",
      "tgn:7012149",
      "tgn:7014612",
      "tgn:7007568",
      "tgn:7029392"
    ],
    "placetype": [
      "aat:300008699"
    ],
    "id": 2148869,
    "name:xx": "Barney Brook"
  }
}
