{
  "type": "FeatureCollection",
  "features": [
    {
      "geometry": {
        "type": "Point",
        "coordinates": [
          -71.083333,
          -29.3
        ]
      },
      "type": "Feature",
      "properties": {
        "hierarchy": [
          "tgn:7318720",
          "tgn:1001657",
          "tgn:1000049",
          "tgn:1000002",
          "tgn:7029392"
        ],
        "placetype": [
          "aat:300008795"
        ],
        "id": 7318720,
        "name:xx": "Cachiyuyo, Cerro"
      }
    },
    {
      "geometry": {
        "type": "Point",
        "coordinates": [
          -70.033333,
          -27.083333
        ]
      },
      "type": "Feature",
      "properties": {
        "hierarchy": [
          "tgn:7318721",
          "tgn:1001630",
          "tgn:1000049",
          "tgn:1000002",
          "tgn:7029392"
        ],
        "placetype": [
          "aat:300008795"
        ],
        "id": 7318721,
        "name:xx": "Cachiyuyo, Cerro"
      }
    },
    {
      "geometry": {
        "type": "Point",
        "coordinates": [
          -70.716667,
          -29.083333
        ]
      },
      "type": "Feature",
      "properties": {
        "hierarchy": [
          "tgn:7318722",
          "tgn:1001630",
          "tgn:1000049",
          "tgn:1000002",
          "tgn:7029392"
        ],
        "placetype": [
          "aat:300008697"
        ],
        "id": 7318722,
        "name:xx": "Cachiyuyo, Aguada"
      }
    },
    {
      "geometry": {
        "type": "Point",
        "coordinates": [
          -70.866667,
          -29.916667
        ]
      },
      "type": "Feature",
      "properties": {
        "hierarchy": [
          "tgn:7318723",
          "tgn:1001657",
          "tgn:1000049",
          "tgn:1000002",
          "tgn:7029392"
        ],
        "placetype": [
          "aat:300008697"
        ],
        "id": 7318723,
        "name:xx": "Cachiyuyo"
      }
    },
    {
      "geometry": {
        "type": "Point",
        "coordinates": [
          -69.7,
          -27.35
        ]
      },
      "type": "Feature",
      "properties": {
        "hierarchy": [
          "tgn:7318724",
          "tgn:1001630",
          "tgn:1000049",
          "tgn:1000002",
          "tgn:7029392"
        ],
        "placetype": [
          "aat:300008697"
        ],
        "id": 7318724,
        "name:xx": "Cachiyuyo"
      }
    },
    {
      "geometry": {
        "type": "Point",
        "coordinates": [
          -69.816667,
          -26.65
        ]
      },
      "type": "Feature",
      "properties": {
        "hierarchy": [
          "tgn:7318725",
          "tgn:1001630",
          "tgn:1000049",
          "tgn:1000002",
          "tgn:7029392"
        ],
        "placetype": [
          "aat:300008697"
        ],
        "id": 7318725,
        "name:xx": "Cachiyuyo"
      }
    },
    {
      "geometry": {
        "type": "Point",
        "coordinates": [
          -70.9,
          -29.033333
        ]
      },
      "type": "Feature",
      "properties": {
        "hierarchy": [
          "tgn:7318726",
          "tgn:1001630",
          "tgn:1000049",
          "tgn:1000002",
          "tgn:7029392"
        ],
        "placetype": [
          "aat:300008347"
        ],
        "id": 7318726,
        "name:xx": "Cachiyuyo"
      }
    },
    {
      "geometry": {
        "type": "Point",
        "coordinates": [
          -70.233333,
          -27.9
        ]
      },
      "type": "Feature",
      "properties": {
        "hierarchy": [
          "tgn:7318727",
          "tgn:1001630",
          "tgn:1000049",
          "tgn:1000002",
          "tgn:7029392"
        ],
        "placetype": [
          "aat:300387200"
        ],
        "id": 7318727,
        "name:xx": "Cachiyuyo"
      }
    },
    {
      "geometry": {
        "type": "Point",
        "coordinates": [
          -69.366667,
          -26.416667
        ]
      },
      "type": "Feature",
      "properties": {
        "hierarchy": [
          "tgn:7318728",
          "tgn:1001630",
          "tgn:1000049",
          "tgn:1000002",
          "tgn:7029392"
        ],
        "placetype": [
          "aat:300004792"
        ],
        "id": 7318728,
        "name:xx": "Cachiyuyo"
      }
    },
    {
      "geometry": {
        "type": "Point",
        "coordinates": [
          -69.583333,
          -26.166667
        ]
      },
      "type": "Feature",
      "properties": {
        "hierarchy": [
          "tgn:7318729",
          "tgn:1001630",
          "tgn:1000049",
          "tgn:1000002",
          "tgn:7029392"
        ],
        "placetype": [
          "aat:300004792"
        ],
        "id": 7318729,
        "name:xx": "Cachiyuyo"
      }
    }
  ]
}
