{
  "geometry": {
    "type": "Point",
    "coordinates": [
      15.2333,
      2.05
    ]
  },
  "type": "Feature",
  "properties": {
    "hierarchy": [
      "tgn:1088246",
      "tgn:1001245",
      "tgn:7001242",
      "tgn:1000153",
      "tgn:7029392"
    ],
    "placetype": [
      "aat:300008347"
    ],
    "id": 1088246,
    "name:xx": "Moloundou"
  }
}
