{
  "geometry": {
    "type": "Point",
    "coordinates": [
      -94.3167,
      40.2167
    ]
  },
  "type": "Feature",
  "properties": {
    "hierarchy": [
      "tgn:2272322",
      "tgn:1000001",
      "tgn:7012149",
      "tgn:2001198",
      "tgn:7007523",
      "tgn:7029392"
    ],
    "placetype": [
      "aat:300006191"
    ],
    "id": 2272322,
    "name:xx": "Curt Lee Lake"
  }
}
