{
  "geometry": {
    "type": "Point",
    "coordinates": [
      125.2333,
      38.8833
    ]
  },
  "type": "Feature",
  "properties": {
    "hierarchy": [
      "tgn:1082171",
      "tgn:1000004",
      "tgn:1001477",
      "tgn:1000122",
      "tgn:7029392"
    ],
    "placetype": [
      "aat:300008347"
    ],
    "id": 1082171,
    "name:xx": "Yonggang-Onch'ŏn"
  }
}
