{
  "geometry": {
    "type": "Point",
    "coordinates": [
      -121.1167,
      45.75
    ]
  },
  "type": "Feature",
  "properties": {
    "hierarchy": [
      "tgn:2424446",
      "tgn:1000001",
      "tgn:7012149",
      "tgn:1002554",
      "tgn:7007920",
      "tgn:7029392"
    ],
    "placetype": [
      "aat:300008761"
    ],
    "id": 2424446,
    "name:xx": "Johnson Canyon"
  }
}
