{
  "geometry": {
    "type": "Point",
    "coordinates": [
      -104.5167,
      42.7333
    ]
  },
  "type": "Feature",
  "properties": {
    "hierarchy": [
      "tgn:2544325",
      "tgn:1000001",
      "tgn:7012149",
      "tgn:2002378",
      "tgn:7007923",
      "tgn:7029392"
    ],
    "placetype": [
      "aat:300008706"
    ],
    "id": 2544325,
    "name:xx": "North Branch Silver Springs Creek"
  }
}
