{
  "geometry": {
    "type": "Point",
    "coordinates": [
      -83.95,
      33.1833
    ]
  },
  "type": "Feature",
  "properties": {
    "hierarchy": [
      "tgn:2312353",
      "tgn:1000001",
      "tgn:7012149",
      "tgn:2000393",
      "tgn:7007248",
      "tgn:7029392"
    ],
    "placetype": [
      "aat:300008706"
    ],
    "id": 2312353,
    "name:xx": "Eightmile Creek"
  }
}
