{
  "geometry": {
    "type": "Point",
    "coordinates": [
      -82.8667,
      32.7667
    ]
  },
  "type": "Feature",
  "properties": {
    "hierarchy": [
      "tgn:2349217",
      "tgn:1000001",
      "tgn:7012149",
      "tgn:2000374",
      "tgn:7007248",
      "tgn:7029392"
    ],
    "placetype": [
      "aat:300008680"
    ],
    "id": 2349217,
    "name:xx": "Gilbert Pond"
  }
}
