{
  "geometry": {
    "type": "Point",
    "coordinates": [
      119.0167,
      27.3667
    ]
  },
  "type": "Feature",
  "properties": {
    "hierarchy": [
      "tgn:1072939",
      "tgn:1000004",
      "tgn:7001796",
      "tgn:1000111",
      "tgn:7029392"
    ],
    "placetype": [
      "aat:300008347"
    ],
    "id": 1072939,
    "name:xx": "Xiazhuang"
  }
}
