{
  "geometry": {
    "type": "Point",
    "coordinates": [
      -90.0167,
      35.2667
    ]
  },
  "type": "Feature",
  "properties": {
    "hierarchy": [
      "tgn:2216972",
      "tgn:1000001",
      "tgn:7012149",
      "tgn:2001915",
      "tgn:7007825",
      "tgn:7029392"
    ],
    "placetype": [
      "aat:300006191"
    ],
    "id": 2216972,
    "name:xx": "Camp Lake Number One"
  }
}
