{
  "geometry": {
    "type": "Point",
    "coordinates": [
      -75.5833,
      42.4333
    ]
  },
  "type": "Feature",
  "properties": {
    "hierarchy": [
      "tgn:2071534",
      "tgn:1000001",
      "tgn:1002262",
      "tgn:7012149",
      "tgn:7007568",
      "tgn:7029392"
    ],
    "placetype": [
      "aat:300008347"
    ],
    "id": 2071534,
    "name:xx": "Oxford"
  }
}
