{
  "geometry": {
    "type": "Point",
    "coordinates": [
      -106.5333,
      46.65
    ]
  },
  "type": "Feature",
  "properties": {
    "hierarchy": [
      "tgn:2630235",
      "tgn:1000001",
      "tgn:7012149",
      "tgn:2001303",
      "tgn:7007524",
      "tgn:7029392"
    ],
    "placetype": [
      "aat:300008706"
    ],
    "id": 2630235,
    "name:xx": "Rough Creek"
  }
}
