{
  "geometry": {
    "type": "Point",
    "coordinates": [
      -78.7667,
      34.4833
    ]
  },
  "type": "Feature",
  "properties": {
    "hierarchy": [
      "tgn:2401385",
      "tgn:1000001",
      "tgn:2001471",
      "tgn:7012149",
      "tgn:7007709",
      "tgn:7029392"
    ],
    "placetype": [
      "aat:300008905"
    ],
    "id": 2401385,
    "name:xx": "Horsepen Swamp"
  }
}
