{
  "geometry": {
    "type": "Point",
    "coordinates": [
      -87.2333,
      33.5333
    ]
  },
  "type": "Feature",
  "properties": {
    "hierarchy": [
      "tgn:2002971",
      "tgn:7002659",
      "tgn:1000001",
      "tgn:7012149",
      "tgn:2000036",
      "tgn:7029392"
    ],
    "placetype": [
      "aat:300008347"
    ],
    "id": 2002971,
    "name:xx": "Camp Oliver"
  }
}
