{
  "geometry": {
    "type": "Point",
    "coordinates": [
      -79.2167,
      36.0333
    ]
  },
  "type": "Feature",
  "properties": {
    "hierarchy": [
      "tgn:2653355",
      "tgn:1000001",
      "tgn:7012149",
      "tgn:2001525",
      "tgn:7007709",
      "tgn:7029392"
    ],
    "placetype": [
      "aat:300008706"
    ],
    "id": 2653355,
    "name:xx": "Sevenmile Creek"
  }
}
