{
  "geometry": {
    "type": "Point",
    "coordinates": [
      46.65,
      41.6333
    ]
  },
  "type": "Feature",
  "properties": {
    "hierarchy": [
      "tgn:7010329",
      "tgn:7011438",
      "tgn:1000004",
      "tgn:7006646",
      "tgn:7029392"
    ],
    "placetype": [
      "aat:300008347"
    ],
    "id": 7010329,
    "name:xx": "Zakataly"
  }
}
