{
  "geometry": {
    "type": "Point",
    "coordinates": [
      -88.4833,
      43.2167
    ]
  },
  "type": "Feature",
  "properties": {
    "hierarchy": [
      "tgn:2277700",
      "tgn:1000001",
      "tgn:1002337",
      "tgn:7012149",
      "tgn:7007922",
      "tgn:7029392"
    ],
    "placetype": [
      "aat:300008706"
    ],
    "id": 2277700,
    "name:xx": "Davy Creek"
  }
}
