{
  "geometry": {
    "type": "Point",
    "coordinates": [
      -76.4333,
      39.3833
    ]
  },
  "type": "Feature",
  "properties": {
    "hierarchy": [
      "tgn:2664308",
      "tgn:7016099",
      "tgn:1000001",
      "tgn:7012149",
      "tgn:7007516",
      "tgn:7029392"
    ],
    "placetype": [
      "aat:300008347"
    ],
    "id": 2664308,
    "name:xx": "Silver Woods"
  }
}
