{
  "geometry": {
    "type": "Point",
    "coordinates": [
      74.6625,
      34.033333
    ]
  },
  "type": "Feature",
  "properties": {
    "hierarchy": [
      "tgn:7588314",
      "tgn:1000004",
      "tgn:7000198",
      "tgn:7000799",
      "tgn:7029392"
    ],
    "placetype": [
      "aat:300008347"
    ],
    "name:en": "Sāratpur",
    "id": 7588314
  }
}
