{
  "geometry": {
    "type": "Point",
    "coordinates": [
      117.0167,
      39.7833
    ]
  },
  "type": "Feature",
  "properties": {
    "hierarchy": [
      "tgn:1072772",
      "tgn:1000004",
      "tgn:7002077",
      "tgn:1000111",
      "tgn:7029392"
    ],
    "placetype": [
      "aat:300008347"
    ],
    "id": 1072772,
    "name:xx": "Xianghe"
  }
}
