{
  "geometry": {
    "type": "Point",
    "coordinates": [
      13.35,
      51.666667
    ]
  },
  "type": "Feature",
  "properties": {
    "hierarchy": [
      "tgn:7173753",
      "tgn:7000096",
      "tgn:1000003",
      "tgn:7000084",
      "tgn:7029392"
    ],
    "placetype": [
      "aat:300008777"
    ],
    "id": 7173753,
    "name:xx": "Groß-Berg"
  }
}
