{
  "geometry": {
    "type": "Point",
    "coordinates": [
      -91.05,
      48.1333
    ]
  },
  "type": "Feature",
  "properties": {
    "hierarchy": [
      "tgn:2349025",
      "tgn:1000001",
      "tgn:7012149",
      "tgn:2001036",
      "tgn:7007521",
      "tgn:7029392"
    ],
    "placetype": [
      "aat:300008680"
    ],
    "id": 2349025,
    "name:xx": "Gift Lake"
  }
}
