{
  "geometry": {
    "type": "Point",
    "coordinates": [
      -94.7667,
      29.7833
    ]
  },
  "type": "Feature",
  "properties": {
    "hierarchy": [
      "tgn:2617938",
      "tgn:1000001",
      "tgn:7012149",
      "tgn:1002251",
      "tgn:7007826",
      "tgn:7029392"
    ],
    "placetype": [
      "aat:300266640"
    ],
    "id": 2617938,
    "name:xx": "Ridge, The"
  }
}
