{
  "geometry": {
    "type": "Point",
    "coordinates": [
      -83.5333,
      44.8667
    ]
  },
  "type": "Feature",
  "properties": {
    "hierarchy": [
      "tgn:2544081",
      "tgn:1000001",
      "tgn:7012149",
      "tgn:7007520",
      "tgn:7029392"
    ],
    "placetype": [
      "aat:300008706"
    ],
    "id": 2544081,
    "name:xx": "North Branch Holcomb Creek"
  }
}
