{
  "geometry": {
    "type": "Point",
    "coordinates": [
      -80.1333,
      40.2667
    ]
  },
  "type": "Feature",
  "properties": {
    "hierarchy": [
      "tgn:1115798",
      "tgn:1000001",
      "tgn:7012149",
      "tgn:1002995",
      "tgn:7007710",
      "tgn:7029392"
    ],
    "placetype": [
      "aat:300008680"
    ],
    "id": 1115798,
    "name:xx": "Canonsburg Lake"
  }
}
