{
  "geometry": {
    "type": "Point",
    "coordinates": [
      -77.6833,
      42.3667
    ]
  },
  "type": "Feature",
  "properties": {
    "hierarchy": [
      "tgn:2493551",
      "tgn:1000001",
      "tgn:7012149",
      "tgn:1002920",
      "tgn:7007568",
      "tgn:7029392"
    ],
    "placetype": [
      "aat:300006075"
    ],
    "id": 2493551,
    "name:xx": "Marsh Ditch"
  }
}
