{
  "geometry": {
    "type": "Point",
    "coordinates": [
      -90.1667,
      46.0833
    ]
  },
  "type": "Feature",
  "properties": {
    "hierarchy": [
      "tgn:2328649",
      "tgn:1000001",
      "tgn:7012149",
      "tgn:2002327",
      "tgn:7007922",
      "tgn:7029392"
    ],
    "placetype": [
      "aat:300008347"
    ],
    "id": 2328649,
    "name:xx": "Fishermans Landing"
  }
}
