{
  "geometry": {
    "type": "Point",
    "coordinates": [
      -85.3333,
      41.9333
    ]
  },
  "type": "Feature",
  "properties": {
    "hierarchy": [
      "tgn:2323528",
      "tgn:1000001",
      "tgn:7012149",
      "tgn:7016057",
      "tgn:7007520",
      "tgn:7029392"
    ],
    "placetype": [
      "aat:300008680"
    ],
    "id": 2323528,
    "name:xx": "Farrand Lake"
  }
}
