{
  "geometry": {
    "type": "Point",
    "coordinates": [
      33.646371,
      30.305921
    ]
  },
  "type": "Feature",
  "properties": {
    "hierarchy": [
      "tgn:7522145",
      "tgn:7001242",
      "tgn:7016833",
      "tgn:7001335",
      "tgn:7029392"
    ],
    "placetype": [
      "aat:300379998"
    ],
    "name:en": "Abū Rujm, Wādī",
    "id": 7522145
  }
}
