{
  "geometry": {
    "type": "Point",
    "coordinates": [
      81.7333,
      43.1667
    ]
  },
  "type": "Feature",
  "properties": {
    "hierarchy": [
      "tgn:1072205",
      "tgn:1000004",
      "tgn:7001745",
      "tgn:1000111",
      "tgn:7029392"
    ],
    "placetype": [
      "aat:300008347"
    ],
    "id": 1072205,
    "name:xx": "Tekes"
  }
}
