{
  "geometry": {
    "type": "Point",
    "coordinates": [
      -89.1667,
      35.8667
    ]
  },
  "type": "Feature",
  "properties": {
    "hierarchy": [
      "tgn:2098689",
      "tgn:1000001",
      "tgn:7012149",
      "tgn:2001853",
      "tgn:7007825",
      "tgn:7029392"
    ],
    "placetype": [
      "aat:300008347"
    ],
    "id": 2098689,
    "name:xx": "Crockett Mills"
  }
}
