{
  "geometry": {
    "type": "Point",
    "coordinates": [
      -112.5333,
      38.4667
    ]
  },
  "type": "Feature",
  "properties": {
    "hierarchy": [
      "tgn:2679645",
      "tgn:1000001",
      "tgn:7012149",
      "tgn:7007827",
      "tgn:7029392"
    ],
    "placetype": [
      "aat:300008706"
    ],
    "id": 2679645,
    "name:xx": "South Fork Pine Creek"
  }
}
