{
  "geometry": {
    "type": "Point",
    "coordinates": [
      -114.55,
      46.65
    ]
  },
  "type": "Feature",
  "properties": {
    "hierarchy": [
      "tgn:2747133",
      "tgn:1000001",
      "tgn:7012149",
      "tgn:2001291",
      "tgn:7007524",
      "tgn:7029392"
    ],
    "placetype": [
      "aat:300008798"
    ],
    "id": 2747133,
    "name:xx": "Wagon Mountain"
  }
}
