{
  "geometry": {
    "type": "Point",
    "coordinates": [
      -113.1833,
      43.65
    ]
  },
  "type": "Feature",
  "properties": {
    "hierarchy": [
      "tgn:2192107",
      "tgn:1000001",
      "tgn:2000463",
      "tgn:7012149",
      "tgn:7007250",
      "tgn:7029392"
    ],
    "placetype": [
      "aat:300008761"
    ],
    "id": 2192107,
    "name:xx": "Braithwaite Canyon"
  }
}
