{
  "geometry": {
    "type": "Point",
    "coordinates": [
      -79.15,
      40.4333
    ]
  },
  "type": "Feature",
  "properties": {
    "hierarchy": [
      "tgn:2621532",
      "tgn:1000001",
      "tgn:7012149",
      "tgn:1002501",
      "tgn:7007710",
      "tgn:7029392"
    ],
    "placetype": [
      "aat:300008699"
    ],
    "id": 2621532,
    "name:xx": "Roaring Run"
  }
}
