{
  "geometry": {
    "type": "Point",
    "coordinates": [
      -95.95,
      44.3167
    ]
  },
  "type": "Feature",
  "properties": {
    "hierarchy": [
      "tgn:2243067",
      "tgn:1000001",
      "tgn:7012149",
      "tgn:2001040",
      "tgn:7007521",
      "tgn:7029392"
    ],
    "placetype": [
      "aat:300008680"
    ],
    "id": 2243067,
    "name:xx": "Clear Lake"
  }
}
