{
  "geometry": {
    "type": "Point",
    "coordinates": [
      -85.2167,
      40.3833
    ]
  },
  "type": "Feature",
  "properties": {
    "hierarchy": [
      "tgn:2162239",
      "tgn:1000001",
      "tgn:1002184",
      "tgn:7012149",
      "tgn:7007252",
      "tgn:7029392"
    ],
    "placetype": [
      "aat:300008699"
    ],
    "id": 2162239,
    "name:xx": "Belt Run"
  }
}
