{
  "geometry": {
    "type": "Point",
    "coordinates": [
      -109.4833,
      44.55
    ]
  },
  "type": "Feature",
  "properties": {
    "hierarchy": [
      "tgn:2306159",
      "tgn:1000001",
      "tgn:7012149",
      "tgn:2002379",
      "tgn:7007923",
      "tgn:7029392"
    ],
    "placetype": [
      "aat:300008706"
    ],
    "id": 2306159,
    "name:xx": "East Fork Big Creek"
  }
}
