{
  "geometry": {
    "type": "Point",
    "coordinates": [
      128.7833,
      36.0333
    ]
  },
  "type": "Feature",
  "properties": {
    "hierarchy": [
      "tgn:1082363",
      "tgn:1000004",
      "tgn:1001372",
      "tgn:7000299",
      "tgn:7029392"
    ],
    "placetype": [
      "aat:300008347"
    ],
    "id": 1082363,
    "name:xx": "Sinnyŏng"
  }
}
