{
  "type": "FeatureCollection",
  "features": [
    {
      "geometry": {
        "type": "Point",
        "coordinates": [
          -82.7,
          40.0333
        ]
      },
      "type": "Feature",
      "properties": {
        "hierarchy": [
          "tgn:2345110",
          "tgn:1000001",
          "tgn:7012149",
          "tgn:1002596",
          "tgn:7007706",
          "tgn:7029392"
        ],
        "placetype": [
          "aat:300006191"
        ],
        "id": 2345110,
        "name:xx": "Gardner Pond"
      }
    },
    {
      "geometry": {
        "type": "Point",
        "coordinates": [
          -81.05,
          33.65
        ]
      },
      "type": "Feature",
      "properties": {
        "hierarchy": [
          "tgn:2345111",
          "tgn:1000001",
          "tgn:7012149",
          "tgn:2001762",
          "tgn:7007712",
          "tgn:7029392"
        ],
        "placetype": [
          "aat:300006191"
        ],
        "id": 2345111,
        "name:xx": "Gardner Pond"
      }
    },
    {
      "geometry": {
        "type": "Point",
        "coordinates": [
          -86.2833,
          40.8333
        ]
      },
      "type": "Feature",
      "properties": {
        "hierarchy": [
          "tgn:2345112",
          "tgn:1000001",
          "tgn:1002242",
          "tgn:7012149",
          "tgn:7007252",
          "tgn:7029392"
        ],
        "placetype": [
          "aat:300006075"
        ],
        "id": 2345112,
        "name:xx": "Gardner Powell Ditch"
      }
    },
    {
      "geometry": {
        "type": "Point",
        "coordinates": [
          -108.4667,
          32.6167
        ]
      },
      "type": "Feature",
      "properties": {
        "hierarchy": [
          "tgn:2345113",
          "tgn:1000001",
          "tgn:7012149",
          "tgn:2001437",
          "tgn:7007566",
          "tgn:7029392"
        ],
        "placetype": [
          "aat:300000390"
        ],
        "id": 2345113,
        "name:xx": "Gardner Prospect"
      }
    },
    {
      "geometry": {
        "type": "Point",
        "coordinates": [
          -83.6833,
          36.5
        ]
      },
      "type": "Feature",
      "properties": {
        "hierarchy": [
          "tgn:2345114",
          "tgn:1000001",
          "tgn:7012149",
          "tgn:2001849",
          "tgn:7007825",
          "tgn:7029392"
        ],
        "placetype": [
          "aat:300000390"
        ],
        "id": 2345114,
        "name:xx": "Gardner Prospect"
      }
    },
    {
      "geometry": {
        "type": "Point",
        "coordinates": [
          -113.6167,
          36.3333
        ]
      },
      "type": "Feature",
      "properties": {
        "hierarchy": [
          "tgn:2345116",
          "tgn:1000001",
          "tgn:7006451",
          "tgn:7012149",
          "tgn:2000098",
          "tgn:7029392"
        ],
        "placetype": [
          "aat:300006191"
        ],
        "id": 2345116,
        "name:xx": "Gardner Reservoir"
      }
    },
    {
      "geometry": {
        "type": "Point",
        "coordinates": [
          -108.5333,
          37.6167
        ]
      },
      "type": "Feature",
      "properties": {
        "hierarchy": [
          "tgn:2345117",
          "tgn:1000001",
          "tgn:7012149",
          "tgn:2000233",
          "tgn:7007158",
          "tgn:7029392"
        ],
        "placetype": [
          "aat:300006191"
        ],
        "id": 2345117,
        "name:xx": "Gardner Reservoir"
      }
    },
    {
      "geometry": {
        "type": "Point",
        "coordinates": [
          -104.1333,
          41.05
        ]
      },
      "type": "Feature",
      "properties": {
        "hierarchy": [
          "tgn:2345118",
          "tgn:1000001",
          "tgn:7012149",
          "tgn:2002375",
          "tgn:7007923",
          "tgn:7029392"
        ],
        "placetype": [
          "aat:300006191"
        ],
        "id": 2345118,
        "name:xx": "Gardner Reservoir"
      }
    },
    {
      "geometry": {
        "type": "Point",
        "coordinates": [
          -107.75,
          43.6
        ]
      },
      "type": "Feature",
      "properties": {
        "hierarchy": [
          "tgn:2345119",
          "tgn:1000001",
          "tgn:7012149",
          "tgn:2002373",
          "tgn:7007923",
          "tgn:7029392"
        ],
        "placetype": [
          "aat:300006191"
        ],
        "id": 2345119,
        "name:xx": "Gardner Reservoir"
      }
    }
  ]
}
