{
  "geometry": {
    "type": "Point",
    "coordinates": [
      79.698254,
      27.68035
    ]
  },
  "type": "Feature",
  "properties": {
    "hierarchy": [
      "tgn:7559972",
      "tgn:1000004",
      "tgn:7000198",
      "tgn:7016722",
      "tgn:7029392"
    ],
    "placetype": [
      "aat:300008347"
    ],
    "name:en": "Chorān",
    "id": 7559972
  }
}
