{
  "geometry": {
    "type": "Point",
    "coordinates": [
      -114.8167,
      47.0167
    ]
  },
  "type": "Feature",
  "properties": {
    "hierarchy": [
      "tgn:2754932",
      "tgn:1000001",
      "tgn:7012149",
      "tgn:2001290",
      "tgn:7007524",
      "tgn:7029392"
    ],
    "placetype": [
      "aat:300008761"
    ],
    "id": 2754932,
    "name:xx": "Weaver Gulch"
  }
}
