{
  "geometry": {
    "type": "Point",
    "coordinates": [
      -78.3167,
      41.2333
    ]
  },
  "type": "Feature",
  "properties": {
    "hierarchy": [
      "tgn:1133913",
      "tgn:1000001",
      "tgn:7012149",
      "tgn:7007710",
      "tgn:7029392"
    ],
    "placetype": [
      "aat:300008706"
    ],
    "id": 1133913,
    "name:xx": "Mosquito Creek"
  }
}
