{
  "geometry": {
    "type": "Point",
    "coordinates": [
      -100.5833,
      36.0833
    ]
  },
  "type": "Feature",
  "properties": {
    "hierarchy": [
      "tgn:2150052",
      "tgn:1000001",
      "tgn:7012149",
      "tgn:7007826",
      "tgn:7029392"
    ],
    "placetype": [
      "aat:300008706"
    ],
    "id": 2150052,
    "name:xx": "Barton Creek"
  }
}
