{
  "geometry": {
    "type": "Point",
    "coordinates": [
      -3.2333,
      53.2667
    ]
  },
  "type": "Feature",
  "properties": {
    "hierarchy": [
      "tgn:1064599",
      "tgn:7002443",
      "tgn:7026278",
      "tgn:1000003",
      "tgn:7008591",
      "tgn:7029392"
    ],
    "placetype": [
      "aat:300008347"
    ],
    "id": 1064599,
    "name:xx": "Brynford"
  }
}
