{
  "type": "FeatureCollection",
  "features": [
    {
      "geometry": {
        "type": "Point",
        "coordinates": [
          -108.4333,
          44.6833
        ]
      },
      "type": "Feature",
      "properties": {
        "hierarchy": [
          "tgn:2416640",
          "tgn:1000001",
          "tgn:2002366",
          "tgn:7012149",
          "tgn:7007923",
          "tgn:7029392"
        ],
        "placetype": [
          "aat:300006191"
        ],
        "id": 2416640,
        "name:xx": "Jack Horner Reservoir"
      }
    },
    {
      "geometry": {
        "type": "Point",
        "coordinates": [
          -82.5,
          36.8167
        ]
      },
      "type": "Feature",
      "properties": {
        "hierarchy": [
          "tgn:2416641",
          "tgn:1000001",
          "tgn:7012149",
          "tgn:2002189",
          "tgn:7007919",
          "tgn:7029392"
        ],
        "placetype": [
          "aat:300008746"
        ],
        "id": 2416641,
        "name:xx": "Jack Horse Pit"
      }
    },
    {
      "geometry": {
        "type": "Point",
        "coordinates": [
          -77.85,
          36.1833
        ]
      },
      "type": "Feature",
      "properties": {
        "hierarchy": [
          "tgn:2416642",
          "tgn:1000001",
          "tgn:7012149",
          "tgn:2001501",
          "tgn:7007709",
          "tgn:7029392"
        ],
        "placetype": [
          "aat:300008699"
        ],
        "id": 2416642,
        "name:xx": "Jack Horse Swamp"
      }
    },
    {
      "geometry": {
        "type": "Point",
        "coordinates": [
          -94.0333,
          33.7167
        ]
      },
      "type": "Feature",
      "properties": {
        "hierarchy": [
          "tgn:2416643",
          "tgn:1000001",
          "tgn:7016172",
          "tgn:7012149",
          "tgn:2000145",
          "tgn:7029392"
        ],
        "placetype": [
          "aat:300008791"
        ],
        "id": 2416643,
        "name:xx": "Jack Island"
      }
    },
    {
      "geometry": {
        "type": "Point",
        "coordinates": [
          -73.5333,
          41.0167
        ]
      },
      "type": "Feature",
      "properties": {
        "hierarchy": [
          "tgn:2416644",
          "tgn:1002366",
          "tgn:1000001",
          "tgn:7012149",
          "tgn:7007159",
          "tgn:7029392"
        ],
        "placetype": [
          "aat:300008791"
        ],
        "id": 2416644,
        "name:xx": "Jack Island"
      }
    },
    {
      "geometry": {
        "type": "Point",
        "coordinates": [
          -80.3,
          27.4833
        ]
      },
      "type": "Feature",
      "properties": {
        "hierarchy": [
          "tgn:2416645",
          "tgn:1000001",
          "tgn:7012149",
          "tgn:7016124",
          "tgn:7007240",
          "tgn:7029392"
        ],
        "placetype": [
          "aat:300008791"
        ],
        "id": 2416645,
        "name:xx": "Jack Island"
      }
    },
    {
      "geometry": {
        "type": "Point",
        "coordinates": [
          -82.4,
          30.75
        ]
      },
      "type": "Feature",
      "properties": {
        "hierarchy": [
          "tgn:2416646",
          "tgn:1000001",
          "tgn:7012149",
          "tgn:2000439",
          "tgn:7007248",
          "tgn:7029392"
        ],
        "placetype": [
          "aat:300008791"
        ],
        "id": 2416646,
        "name:xx": "Jack Island"
      }
    },
    {
      "geometry": {
        "type": "Point",
        "coordinates": [
          -90.5667,
          30.3667
        ]
      },
      "type": "Feature",
      "properties": {
        "hierarchy": [
          "tgn:2416647",
          "tgn:1000001",
          "tgn:7012149",
          "tgn:2000885",
          "tgn:7007256",
          "tgn:7029392"
        ],
        "placetype": [
          "aat:300008791"
        ],
        "id": 2416647,
        "name:xx": "Jack Island"
      }
    },
    {
      "geometry": {
        "type": "Point",
        "coordinates": [
          -91.5,
          30.15
        ]
      },
      "type": "Feature",
      "properties": {
        "hierarchy": [
          "tgn:2416648",
          "tgn:1000001",
          "tgn:7012149",
          "tgn:2000903",
          "tgn:7007256",
          "tgn:7029392"
        ],
        "placetype": [
          "aat:300008791"
        ],
        "id": 2416648,
        "name:xx": "Jack Island"
      }
    }
  ]
}
