{
  "geometry": {
    "type": "Point",
    "coordinates": [
      -84.6333,
      45.4333
    ]
  },
  "type": "Feature",
  "properties": {
    "hierarchy": [
      "tgn:2754298",
      "tgn:1000001",
      "tgn:2000951",
      "tgn:7012149",
      "tgn:7007520",
      "tgn:7029392"
    ],
    "placetype": [
      "aat:300008347"
    ],
    "id": 2754298,
    "name:xx": "Wauban Beach"
  }
}
