{
  "geometry": {
    "type": "Point",
    "coordinates": [
      -108.7667,
      33.8833
    ]
  },
  "type": "Feature",
  "properties": {
    "hierarchy": [
      "tgn:2326974",
      "tgn:1000001",
      "tgn:2001429",
      "tgn:7012149",
      "tgn:7007566",
      "tgn:7029392"
    ],
    "placetype": [
      "aat:300008761"
    ],
    "id": 2326974,
    "name:xx": "Firebox Canyon"
  }
}
