{
  "geometry": {
    "type": "Point",
    "coordinates": [
      -75.0833,
      40.8167
    ]
  },
  "type": "Feature",
  "properties": {
    "hierarchy": [
      "tgn:2500772",
      "tgn:1000001",
      "tgn:7012149",
      "tgn:1002729",
      "tgn:7007710",
      "tgn:7029392"
    ],
    "placetype": [
      "aat:300008791"
    ],
    "id": 2500772,
    "name:xx": "McElhaneys Island"
  }
}
