{
  "geometry": {
    "type": "Point",
    "coordinates": [
      9.0333,
      55.8167
    ]
  },
  "type": "Feature",
  "properties": {
    "hierarchy": [
      "tgn:1027802",
      "tgn:1000003",
      "tgn:7594009",
      "tgn:1000066",
      "tgn:7029392"
    ],
    "placetype": [
      "aat:300008347"
    ],
    "id": 1027802,
    "name:xx": "Filskov"
  }
}
