{
  "geometry": {
    "type": "Point",
    "coordinates": [
      -107.6167,
      48.9833
    ]
  },
  "type": "Feature",
  "properties": {
    "hierarchy": [
      "tgn:2441672",
      "tgn:1000001",
      "tgn:7012149",
      "tgn:2001295",
      "tgn:7007524",
      "tgn:7029392"
    ],
    "placetype": [
      "aat:300006191"
    ],
    "id": 2441672,
    "name:xx": "Kohola Reservoir"
  }
}
