{
  "geometry": {
    "type": "Point",
    "coordinates": [
      -122.7833,
      41.9667
    ]
  },
  "type": "Feature",
  "properties": {
    "hierarchy": [
      "tgn:2460972",
      "tgn:1000001",
      "tgn:7012149",
      "tgn:7007157",
      "tgn:2000189",
      "tgn:7029392"
    ],
    "placetype": [
      "aat:300008706"
    ],
    "id": 2460972,
    "name:xx": "Little Smoky Creek"
  }
}
