{
  "geometry": {
    "type": "Point",
    "coordinates": [
      -75.3333,
      39.8167
    ]
  },
  "type": "Feature",
  "properties": {
    "hierarchy": [
      "tgn:2556651",
      "tgn:1000001",
      "tgn:1002410",
      "tgn:7012149",
      "tgn:7007565",
      "tgn:7029392"
    ],
    "placetype": [
      "aat:300006075"
    ],
    "id": 2556651,
    "name:xx": "Old Canal"
  }
}
