{
  "geometry": {
    "type": "Point",
    "coordinates": [
      -81.4833,
      40.0667
    ]
  },
  "type": "Feature",
  "properties": {
    "hierarchy": [
      "tgn:2751917",
      "tgn:1000001",
      "tgn:7012149",
      "tgn:1002432",
      "tgn:7007706",
      "tgn:7029392"
    ],
    "placetype": [
      "aat:300008347"
    ],
    "id": 2751917,
    "name:xx": "Warrentown"
  }
}
