{
  "geometry": {
    "type": "Point",
    "coordinates": [
      -121.0333,
      45.25
    ]
  },
  "type": "Feature",
  "properties": {
    "hierarchy": [
      "tgn:2085518",
      "tgn:1000001",
      "tgn:7012149",
      "tgn:1002990",
      "tgn:7007708",
      "tgn:7029392"
    ],
    "placetype": [
      "aat:300387016"
    ],
    "id": 2085518,
    "name:xx": "Sherar"
  }
}
