{
  "type": "FeatureCollection",
  "features": [
    {
      "geometry": {
        "type": "Point",
        "coordinates": [
          -91.1833,
          35.9667
        ]
      },
      "type": "Feature",
      "properties": {
        "hierarchy": [
          "tgn:2273280",
          "tgn:1000001",
          "tgn:7016172",
          "tgn:7012149",
          "tgn:2000142",
          "tgn:7029392"
        ],
        "placetype": [
          "aat:300008706"
        ],
        "id": 2273280,
        "name:xx": "Cypress Creek"
      }
    },
    {
      "geometry": {
        "type": "Point",
        "coordinates": [
          -93.3167,
          33.5833
        ]
      },
      "type": "Feature",
      "properties": {
        "hierarchy": [
          "tgn:2273281",
          "tgn:1000001",
          "tgn:7016172",
          "tgn:7012149",
          "tgn:2000154",
          "tgn:7029392"
        ],
        "placetype": [
          "aat:300008706"
        ],
        "id": 2273281,
        "name:xx": "Cypress Creek"
      }
    },
    {
      "geometry": {
        "type": "Point",
        "coordinates": [
          -93.0167,
          33.85
        ]
      },
      "type": "Feature",
      "properties": {
        "hierarchy": [
          "tgn:2273282",
          "tgn:1000001",
          "tgn:7016172",
          "tgn:2000114",
          "tgn:7012149",
          "tgn:7029392"
        ],
        "placetype": [
          "aat:300008706"
        ],
        "id": 2273282,
        "name:xx": "Cypress Creek"
      }
    },
    {
      "geometry": {
        "type": "Point",
        "coordinates": [
          -91.0167,
          35.0833
        ]
      },
      "type": "Feature",
      "properties": {
        "hierarchy": [
          "tgn:2273283",
          "tgn:1000001",
          "tgn:7016172",
          "tgn:7012149",
          "tgn:2000166",
          "tgn:7029392"
        ],
        "placetype": [
          "aat:300008706"
        ],
        "id": 2273283,
        "name:xx": "Cypress Creek"
      }
    },
    {
      "geometry": {
        "type": "Point",
        "coordinates": [
          -92.8167,
          35.05
        ]
      },
      "type": "Feature",
      "properties": {
        "hierarchy": [
          "tgn:2273284",
          "tgn:1000001",
          "tgn:7016172",
          "tgn:7012149",
          "tgn:2000157",
          "tgn:7029392"
        ],
        "placetype": [
          "aat:300008706"
        ],
        "id": 2273284,
        "name:xx": "Cypress Creek"
      }
    },
    {
      "geometry": {
        "type": "Point",
        "coordinates": [
          -92.4333,
          35.1167
        ]
      },
      "type": "Feature",
      "properties": {
        "hierarchy": [
          "tgn:2273285",
          "tgn:1000001",
          "tgn:7016172",
          "tgn:7012149",
          "tgn:2000127",
          "tgn:7029392"
        ],
        "placetype": [
          "aat:300008706"
        ],
        "id": 2273285,
        "name:xx": "Cypress Creek"
      }
    },
    {
      "geometry": {
        "type": "Point",
        "coordinates": [
          -91.7167,
          35.5
        ]
      },
      "type": "Feature",
      "properties": {
        "hierarchy": [
          "tgn:2273286",
          "tgn:1000001",
          "tgn:7016172",
          "tgn:7012149",
          "tgn:2000177",
          "tgn:7029392"
        ],
        "placetype": [
          "aat:300008706"
        ],
        "id": 2273286,
        "name:xx": "Cypress Creek"
      }
    },
    {
      "geometry": {
        "type": "Point",
        "coordinates": [
          -82.7833,
          30.5667
        ]
      },
      "type": "Feature",
      "properties": {
        "hierarchy": [
          "tgn:2273287",
          "tgn:1000001",
          "tgn:2000271",
          "tgn:7012149",
          "tgn:7007240",
          "tgn:7029392"
        ],
        "placetype": [
          "aat:300008347"
        ],
        "id": 2273287,
        "name:xx": "Cypress Creek"
      }
    },
    {
      "geometry": {
        "type": "Point",
        "coordinates": [
          -80.1833,
          26.95
        ]
      },
      "type": "Feature",
      "properties": {
        "hierarchy": [
          "tgn:2273288",
          "tgn:1000001",
          "tgn:7012149",
          "tgn:1002641",
          "tgn:7007240",
          "tgn:7029392"
        ],
        "placetype": [
          "aat:300008706"
        ],
        "id": 2273288,
        "name:xx": "Cypress Creek"
      }
    },
    {
      "geometry": {
        "type": "Point",
        "coordinates": [
          -80.7,
          27.3
        ]
      },
      "type": "Feature",
      "properties": {
        "hierarchy": [
          "tgn:2273289",
          "tgn:1000001",
          "tgn:7012149",
          "tgn:7007240",
          "tgn:7029392"
        ],
        "placetype": [
          "aat:300008706"
        ],
        "id": 2273289,
        "name:xx": "Cypress Creek"
      }
    }
  ]
}
