{
  "type": "FeatureCollection",
  "features": [
    {
      "geometry": {
        "type": "Point",
        "coordinates": [
          -84.9167,
          33.65
        ]
      },
      "type": "Feature",
      "properties": {
        "hierarchy": [
          "tgn:2328860",
          "tgn:1000001",
          "tgn:2000313",
          "tgn:7012149",
          "tgn:7007248",
          "tgn:7029392"
        ],
        "placetype": [
          "aat:300006191"
        ],
        "id": 2328860,
        "name:xx": "Fishing Lake"
      }
    },
    {
      "geometry": {
        "type": "Point",
        "coordinates": [
          -91.4667,
          38.4167
        ]
      },
      "type": "Feature",
      "properties": {
        "hierarchy": [
          "tgn:2328861",
          "tgn:1000001",
          "tgn:7012149",
          "tgn:1002402",
          "tgn:7007523",
          "tgn:7029392"
        ],
        "placetype": [
          "aat:300006191"
        ],
        "id": 2328861,
        "name:xx": "Fishing Lake"
      }
    },
    {
      "geometry": {
        "type": "Point",
        "coordinates": [
          -92.1333,
          47.7333
        ]
      },
      "type": "Feature",
      "properties": {
        "hierarchy": [
          "tgn:2328862",
          "tgn:1000001",
          "tgn:7012149",
          "tgn:2001067",
          "tgn:7007521",
          "tgn:7029392"
        ],
        "placetype": [
          "aat:300008680"
        ],
        "id": 2328862,
        "name:xx": "Fishing Lakes"
      }
    },
    {
      "geometry": {
        "type": "Point",
        "coordinates": [
          -70.3,
          41.9333
        ]
      },
      "type": "Feature",
      "properties": {
        "hierarchy": [
          "tgn:2328863",
          "tgn:1002165",
          "tgn:1000001",
          "tgn:7012149",
          "tgn:7007517",
          "tgn:7029392"
        ],
        "placetype": [
          "aat:300011692"
        ],
        "id": 2328863,
        "name:xx": "Fishing Ledge"
      }
    },
    {
      "geometry": {
        "type": "Point",
        "coordinates": [
          -75.25,
          38.5833
        ]
      },
      "type": "Feature",
      "properties": {
        "hierarchy": [
          "tgn:2328864",
          "tgn:1002933",
          "tgn:1000001",
          "tgn:7012149",
          "tgn:7007239",
          "tgn:7029392"
        ],
        "placetype": [
          "aat:300008850"
        ],
        "id": 2328864,
        "name:xx": "Fishing Point"
      }
    },
    {
      "geometry": {
        "type": "Point",
        "coordinates": [
          -91.2833,
          29.3167
        ]
      },
      "type": "Feature",
      "properties": {
        "hierarchy": [
          "tgn:2328865",
          "tgn:1000001",
          "tgn:7012149",
          "tgn:2000908",
          "tgn:7007256",
          "tgn:7029392"
        ],
        "placetype": [
          "aat:300008850"
        ],
        "id": 2328865,
        "name:xx": "Fishing Point"
      }
    },
    {
      "geometry": {
        "type": "Point",
        "coordinates": [
          -76,
          38.0333
        ]
      },
      "type": "Feature",
      "properties": {
        "hierarchy": [
          "tgn:2328866",
          "tgn:1000001",
          "tgn:1002902",
          "tgn:7012149",
          "tgn:7007516",
          "tgn:7029392"
        ],
        "placetype": [
          "aat:300008850"
        ],
        "id": 2328866,
        "name:xx": "Fishing Point"
      }
    },
    {
      "geometry": {
        "type": "Point",
        "coordinates": [
          -76.15,
          38.2333
        ]
      },
      "type": "Feature",
      "properties": {
        "hierarchy": [
          "tgn:2328867",
          "tgn:1002338",
          "tgn:1000001",
          "tgn:7012149",
          "tgn:7007516",
          "tgn:7029392"
        ],
        "placetype": [
          "aat:300008850"
        ],
        "id": 2328867,
        "name:xx": "Fishing Point"
      }
    },
    {
      "geometry": {
        "type": "Point",
        "coordinates": [
          -76.4167,
          38.3
        ]
      },
      "type": "Feature",
      "properties": {
        "hierarchy": [
          "tgn:2328868",
          "tgn:1000001",
          "tgn:7016098",
          "tgn:7012149",
          "tgn:7007516",
          "tgn:7029392"
        ],
        "placetype": [
          "aat:300008850"
        ],
        "id": 2328868,
        "name:xx": "Fishing Point"
      }
    },
    {
      "geometry": {
        "type": "Point",
        "coordinates": [
          -76.55,
          39.2167
        ]
      },
      "type": "Feature",
      "properties": {
        "hierarchy": [
          "tgn:2328869",
          "tgn:7021987",
          "tgn:1000001",
          "tgn:7012149",
          "tgn:7007516",
          "tgn:7029392"
        ],
        "placetype": [
          "aat:300008850"
        ],
        "id": 2328869,
        "name:xx": "Fishing Point"
      }
    }
  ]
}
