{
  "geometry": {
    "type": "Point",
    "coordinates": [
      -105.6167,
      43.7333
    ]
  },
  "type": "Feature",
  "properties": {
    "hierarchy": [
      "tgn:2625999",
      "tgn:1000001",
      "tgn:2002367",
      "tgn:7012149",
      "tgn:7007923",
      "tgn:7029392"
    ],
    "placetype": [
      "aat:300008761"
    ],
    "id": 2625999,
    "name:xx": "Rocky Butte Gulch"
  }
}
