{
  "geometry": {
    "type": "Point",
    "coordinates": [
      -94.2167,
      42.2667
    ]
  },
  "type": "Feature",
  "properties": {
    "hierarchy": [
      "tgn:2288832",
      "tgn:1000001",
      "tgn:7012149",
      "tgn:2000654",
      "tgn:7007253",
      "tgn:7029392"
    ],
    "placetype": [
      "aat:300006075"
    ],
    "id": 2288832,
    "name:xx": "Ditch Number 48"
  }
}
