{
  "geometry": {
    "type": "Point",
    "coordinates": [
      32.533333,
      23.583333
    ]
  },
  "type": "Feature",
  "properties": {
    "hierarchy": [
      "tgn:7540013",
      "tgn:7001242",
      "tgn:7016833",
      "tgn:7001334",
      "tgn:7029392"
    ],
    "placetype": [
      "aat:300379998"
    ],
    "name:en": "Sanā, Wādī as",
    "id": 7540013
  }
}
