{
  "geometry": {
    "type": "Point",
    "coordinates": [
      -85.3333,
      35.1833
    ]
  },
  "type": "Feature",
  "properties": {
    "hierarchy": [
      "tgn:2493842",
      "tgn:1000001",
      "tgn:7012149",
      "tgn:2001869",
      "tgn:7007825",
      "tgn:7029392"
    ],
    "placetype": [
      "aat:300008706"
    ],
    "id": 2493842,
    "name:xx": "Marshall Creek"
  }
}
