{
  "geometry": {
    "type": "Point",
    "coordinates": [
      -108.85,
      31.6167
    ]
  },
  "type": "Feature",
  "properties": {
    "hierarchy": [
      "tgn:2173677",
      "tgn:1000001",
      "tgn:7012149",
      "tgn:2001440",
      "tgn:7007566",
      "tgn:7029392"
    ],
    "placetype": [
      "aat:300008347"
    ],
    "id": 2173677,
    "name:xx": "Birchfield"
  }
}
