{
  "geometry": {
    "type": "Point",
    "coordinates": [
      25.383333,
      37.45
    ]
  },
  "type": "Feature",
  "properties": {
    "hierarchy": [
      "tgn:1007946",
      "tgn:7011270",
      "tgn:7002674",
      "tgn:1000003",
      "tgn:1000074",
      "tgn:7029392"
    ],
    "placetype": [
      "aat:300008791"
    ],
    "name:en": "Mýkonos, Nísos",
    "id": 1007946
  }
}
