{
  "geometry": {
    "type": "Point",
    "coordinates": [
      -82.8167,
      34.4333
    ]
  },
  "type": "Feature",
  "properties": {
    "hierarchy": [
      "tgn:2636353",
      "tgn:2001728",
      "tgn:1000001",
      "tgn:7012149",
      "tgn:7007712",
      "tgn:7029392"
    ],
    "placetype": [
      "aat:300008347"
    ],
    "id": 2636353,
    "name:xx": "Sadler"
  }
}
