{
  "geometry": {
    "type": "Point",
    "coordinates": [
      -76.3833,
      35.3333
    ]
  },
  "type": "Feature",
  "properties": {
    "hierarchy": [
      "tgn:2280691",
      "tgn:1000001",
      "tgn:7012149",
      "tgn:2001506",
      "tgn:7007709",
      "tgn:7029392"
    ],
    "placetype": [
      "aat:300132316"
    ],
    "id": 2280691,
    "name:xx": "Deep Cove"
  }
}
