{
  "type": "FeatureCollection",
  "features": [
    {
      "geometry": {
        "type": "Point",
        "coordinates": [
          -92.8167,
          43.6
        ]
      },
      "type": "Feature",
      "properties": {
        "hierarchy": [
          "tgn:2055360",
          "tgn:1000001",
          "tgn:7012149",
          "tgn:2001048",
          "tgn:7007521",
          "tgn:7029392"
        ],
        "placetype": [
          "aat:300008347"
        ],
        "id": 2055360,
        "name:xx": "Rose Creek"
      }
    },
    {
      "geometry": {
        "type": "Point",
        "coordinates": [
          -95.1,
          44.9333
        ]
      },
      "type": "Feature",
      "properties": {
        "hierarchy": [
          "tgn:2055362",
          "tgn:1000001",
          "tgn:7012149",
          "tgn:2001032",
          "tgn:7007521",
          "tgn:7029392"
        ],
        "placetype": [
          "aat:300008347"
        ],
        "id": 2055362,
        "name:xx": "Roseland"
      }
    },
    {
      "geometry": {
        "type": "Point",
        "coordinates": [
          -93.1167,
          44.7333
        ]
      },
      "type": "Feature",
      "properties": {
        "hierarchy": [
          "tgn:2055363",
          "tgn:1000001",
          "tgn:2001017",
          "tgn:7012149",
          "tgn:7007521",
          "tgn:7029392"
        ],
        "placetype": [
          "aat:300008347"
        ],
        "id": 2055363,
        "name:xx": "Rosemount"
      }
    },
    {
      "geometry": {
        "type": "Point",
        "coordinates": [
          -96.4,
          45.15
        ]
      },
      "type": "Feature",
      "properties": {
        "hierarchy": [
          "tgn:2055367",
          "tgn:1000001",
          "tgn:7012149",
          "tgn:7021314",
          "tgn:7007521",
          "tgn:7029392"
        ],
        "placetype": [
          "aat:300008347"
        ],
        "id": 2055367,
        "name:xx": "Rosen"
      }
    },
    {
      "geometry": {
        "type": "Point",
        "coordinates": [
          -94.7,
          45.0333
        ]
      },
      "type": "Feature",
      "properties": {
        "hierarchy": [
          "tgn:2055368",
          "tgn:1000001",
          "tgn:7012149",
          "tgn:2001045",
          "tgn:7007521",
          "tgn:7029392"
        ],
        "placetype": [
          "aat:300008347",
          "aat:300387210"
        ],
        "id": 2055368,
        "name:xx": "Rosendale"
      }
    },
    {
      "geometry": {
        "type": "Point",
        "coordinates": [
          -93.15,
          45
        ]
      },
      "type": "Feature",
      "properties": {
        "hierarchy": [
          "tgn:2055369",
          "tgn:1000001",
          "tgn:7012149",
          "tgn:2001060",
          "tgn:7007521",
          "tgn:7029392"
        ],
        "placetype": [
          "aat:300008347"
        ],
        "id": 2055369,
        "name:xx": "Roseville"
      }
    }
  ]
}
