{
  "geometry": {
    "type": "Point",
    "coordinates": [
      -81.4833,
      29.9667
    ]
  },
  "type": "Feature",
  "properties": {
    "hierarchy": [
      "tgn:2512518",
      "tgn:1000001",
      "tgn:7012149",
      "tgn:2000283",
      "tgn:7007240",
      "tgn:7029392"
    ],
    "placetype": [
      "aat:300008706"
    ],
    "id": 2512518,
    "name:xx": "Mill Creek"
  }
}
