{
  "geometry": {
    "type": "Point",
    "coordinates": [
      -89.0667,
      40.4833
    ]
  },
  "type": "Feature",
  "properties": {
    "hierarchy": [
      "tgn:2735609",
      "tgn:1000001",
      "tgn:7012149",
      "tgn:7019015",
      "tgn:7007251",
      "tgn:7029392"
    ],
    "placetype": [
      "aat:300008347"
    ],
    "id": 2735609,
    "name:xx": "Twin Grove"
  }
}
