{
  "geometry": {
    "type": "Point",
    "coordinates": [
      -108.5333,
      40.3167
    ]
  },
  "type": "Feature",
  "properties": {
    "hierarchy": [
      "tgn:2509549",
      "tgn:1000001",
      "tgn:7012149",
      "tgn:7007158",
      "tgn:7029392"
    ],
    "placetype": [
      "aat:300008706"
    ],
    "id": 2509549,
    "name:xx": "Middle Fork Wolf Creek"
  }
}
