{
  "type": "FeatureCollection",
  "features": [
    {
      "geometry": {
        "type": "Point",
        "coordinates": [
          -1.133333,
          52.4
        ]
      },
      "type": "Feature",
      "properties": {
        "hierarchy": [
          "tgn:4010730",
          "tgn:7002445",
          "tgn:1000003",
          "tgn:7012031",
          "tgn:7008591",
          "tgn:7029392"
        ],
        "placetype": [
          "aat:300008347",
          "aat:300008372"
        ],
        "name:en": "Stanford on Avon",
        "id": 4010730
      }
    },
    {
      "geometry": {
        "type": "Point",
        "coordinates": [
          -1.183333,
          52.783333
        ]
      },
      "type": "Feature",
      "properties": {
        "hierarchy": [
          "tgn:4010731",
          "tgn:7002445",
          "tgn:1000003",
          "tgn:7008167",
          "tgn:7008591",
          "tgn:7029392"
        ],
        "placetype": [
          "aat:300008347",
          "aat:300008372"
        ],
        "name:en": "Stanford on Soar",
        "id": 4010731
      }
    },
    {
      "geometry": {
        "type": "Point",
        "coordinates": [
          -1.4,
          51.733333
        ]
      },
      "type": "Feature",
      "properties": {
        "hierarchy": [
          "tgn:4010734",
          "tgn:7002445",
          "tgn:1000003",
          "tgn:7008168",
          "tgn:7008591",
          "tgn:7029392"
        ],
        "placetype": [
          "aat:300008347",
          "aat:300008372"
        ],
        "name:en": "Stanton Harcourt",
        "id": 4010734
      }
    },
    {
      "geometry": {
        "type": "Point",
        "coordinates": [
          -0.683333,
          53.1
        ]
      },
      "type": "Feature",
      "properties": {
        "hierarchy": [
          "tgn:4010735",
          "tgn:7002445",
          "tgn:7011980",
          "tgn:1000003",
          "tgn:7008591",
          "tgn:7029392"
        ],
        "placetype": [
          "aat:300008347"
        ],
        "id": 4010735,
        "name:ang": "Stapleforde"
      }
    },
    {
      "geometry": {
        "type": "Point",
        "coordinates": [
          -0.8,
          52.733333
        ]
      },
      "type": "Feature",
      "properties": {
        "hierarchy": [
          "tgn:4010736",
          "tgn:7002445",
          "tgn:1000003",
          "tgn:7008155",
          "tgn:7008591",
          "tgn:7029392"
        ],
        "placetype": [
          "aat:300008347"
        ],
        "name:en": "Stapleford",
        "id": 4010736
      }
    },
    {
      "geometry": {
        "type": "Point",
        "coordinates": [
          17.437993,
          49.076493
        ]
      },
      "type": "Feature",
      "properties": {
        "hierarchy": [
          "tgn:4010738",
          "tgn:7593922",
          "tgn:1000003",
          "tgn:1001780",
          "tgn:7029392"
        ],
        "placetype": [
          "aat:300008347"
        ],
        "id": 4010738,
        "name:xx": "Staré Město"
      }
    },
    {
      "geometry": {
        "type": "Point",
        "coordinates": [
          20.4,
          49.6667
        ]
      },
      "type": "Feature",
      "properties": {
        "hierarchy": [
          "tgn:4010739",
          "tgn:1000003",
          "tgn:7024127",
          "tgn:7006366",
          "tgn:7029392"
        ],
        "placetype": [
          "aat:300008347"
        ],
        "id": 4010739,
        "name:xx": "Stara Wieś"
      }
    }
  ]
}
