{
  "geometry": {
    "type": "Point",
    "coordinates": [
      -122.2667,
      47.4833
    ]
  },
  "type": "Feature",
  "properties": {
    "hierarchy": [
      "tgn:2116808",
      "tgn:1000001",
      "tgn:7012149",
      "tgn:7018871",
      "tgn:7015617",
      "tgn:7007920",
      "tgn:7029392"
    ],
    "placetype": [
      "aat:300000745"
    ],
    "id": 2116808,
    "name:xx": "Allentown"
  }
}
