{
  "geometry": {
    "type": "Point",
    "coordinates": [
      108.9333,
      34.6667
    ]
  },
  "type": "Feature",
  "properties": {
    "hierarchy": [
      "tgn:1071367",
      "tgn:1000004",
      "tgn:7002084",
      "tgn:1000111",
      "tgn:7029392"
    ],
    "placetype": [
      "aat:300008347"
    ],
    "id": 1071367,
    "name:xx": "Sanyuan"
  }
}
