{
  "geometry": {
    "type": "Point",
    "coordinates": [
      -121.5667,
      45.85
    ]
  },
  "type": "Feature",
  "properties": {
    "hierarchy": [
      "tgn:2201745",
      "tgn:1000001",
      "tgn:7012149",
      "tgn:1002554",
      "tgn:7007920",
      "tgn:7029392"
    ],
    "placetype": [
      "aat:300008706"
    ],
    "id": 2201745,
    "name:xx": "Buck Creek"
  }
}
