{
  "geometry": {
    "type": "Point",
    "coordinates": [
      -118.15,
      45.4667
    ]
  },
  "type": "Feature",
  "properties": {
    "hierarchy": [
      "tgn:2364019",
      "tgn:1000001",
      "tgn:7012149",
      "tgn:2001720",
      "tgn:7007708",
      "tgn:7029392"
    ],
    "placetype": [
      "aat:300008798"
    ],
    "id": 2364019,
    "name:xx": "Green Mountain"
  }
}
