{
  "geometry": {
    "type": "Point",
    "coordinates": [
      -80.0167,
      36.7833
    ]
  },
  "type": "Feature",
  "properties": {
    "hierarchy": [
      "tgn:2578948",
      "tgn:1000001",
      "tgn:7012149",
      "tgn:2002167",
      "tgn:7007919",
      "tgn:7029392"
    ],
    "placetype": [
      "aat:300006191"
    ],
    "id": 2578948,
    "name:xx": "Philpott Lake"
  }
}
