{
  "geometry": {
    "type": "Point",
    "coordinates": [
      -177.1333,
      51.8833
    ]
  },
  "type": "Feature",
  "properties": {
    "hierarchy": [
      "tgn:2430942",
      "tgn:7030516",
      "tgn:7006450",
      "tgn:1000001",
      "tgn:7012149",
      "tgn:7029392"
    ],
    "placetype": [
      "aat:300266640"
    ],
    "id": 2430942,
    "name:xx": "Kanaton Ridge"
  }
}
