{
  "geometry": {
    "type": "Point",
    "coordinates": [
      -121.1167,
      46.1167
    ]
  },
  "type": "Feature",
  "properties": {
    "hierarchy": [
      "tgn:2553820",
      "tgn:1000001",
      "tgn:7012149",
      "tgn:1003042",
      "tgn:7007920",
      "tgn:7029392"
    ],
    "placetype": [
      "aat:300008798"
    ],
    "id": 2553820,
    "name:xx": "Oak Hill"
  }
}
