{
  "geometry": {
    "type": "Point",
    "coordinates": [
      -111.9167,
      50.4167
    ]
  },
  "type": "Feature",
  "properties": {
    "hierarchy": [
      "tgn:1117482",
      "tgn:7005694",
      "tgn:7005685",
      "tgn:1000001",
      "tgn:7029392"
    ],
    "placetype": [
      "aat:300008680"
    ],
    "id": 1117482,
    "name:xx": "Newell, Lake"
  }
}
