{
  "geometry": {
    "type": "Point",
    "coordinates": [
      -81.2833,
      37.15
    ]
  },
  "type": "Feature",
  "properties": {
    "hierarchy": [
      "tgn:2385338",
      "tgn:1000001",
      "tgn:2002145",
      "tgn:7012149",
      "tgn:7007919",
      "tgn:7029392"
    ],
    "placetype": [
      "aat:300008699"
    ],
    "id": 2385338,
    "name:xx": "Hemppatch Branch"
  }
}
