{
  "geometry": {
    "type": "Point",
    "coordinates": [
      5.85,
      58.7667
    ]
  },
  "type": "Feature",
  "properties": {
    "hierarchy": [
      "tgn:1048443",
      "tgn:7003652",
      "tgn:1000003",
      "tgn:1000088",
      "tgn:7029392"
    ],
    "placetype": [
      "aat:300008347"
    ],
    "id": 1048443,
    "name:xx": "Ålgård"
  }
}
