{
  "type": "FeatureCollection",
  "features": [
    {
      "geometry": {
        "type": "Point",
        "coordinates": [
          -122.7667,
          47.5
        ]
      },
      "type": "Feature",
      "properties": {
        "hierarchy": [
          "tgn:2115300",
          "tgn:1000001",
          "tgn:7012149",
          "tgn:1002552",
          "tgn:7007920",
          "tgn:7029392"
        ],
        "placetype": [
          "aat:300008347"
        ],
        "id": 2115300,
        "name:xx": "Belfair"
      }
    },
    {
      "geometry": {
        "type": "Point",
        "coordinates": [
          -122.1167,
          47.6167
        ]
      },
      "type": "Feature",
      "properties": {
        "hierarchy": [
          "tgn:2115305",
          "tgn:1000001",
          "tgn:7013374",
          "tgn:7012149",
          "tgn:7018871",
          "tgn:7007920",
          "tgn:7029392"
        ],
        "placetype": [
          "aat:300000745"
        ],
        "id": 2115305,
        "name:xx": "Crossroads"
      }
    },
    {
      "geometry": {
        "type": "Point",
        "coordinates": [
          -122.1167,
          47.6
        ]
      },
      "type": "Feature",
      "properties": {
        "hierarchy": [
          "tgn:2115308",
          "tgn:1000001",
          "tgn:7013374",
          "tgn:7012149",
          "tgn:7018871",
          "tgn:7007920",
          "tgn:7029392"
        ],
        "placetype": [
          "aat:300000745"
        ],
        "id": 2115308,
        "name:xx": "Lake Hills"
      }
    }
  ]
}
