{
  "geometry": {
    "type": "Point",
    "coordinates": [
      -88.7167,
      36.8167
    ]
  },
  "type": "Feature",
  "properties": {
    "hierarchy": [
      "tgn:2349126",
      "tgn:1000001",
      "tgn:7012149",
      "tgn:2000792",
      "tgn:7007255",
      "tgn:7029392"
    ],
    "placetype": [
      "aat:300008706"
    ],
    "id": 2349126,
    "name:xx": "Gilbert Creek"
  }
}
