{
  "geometry": {
    "type": "Point",
    "coordinates": [
      -112.4333,
      43.8333
    ]
  },
  "type": "Feature",
  "properties": {
    "hierarchy": [
      "tgn:2026177",
      "tgn:1000001",
      "tgn:7012149",
      "tgn:2000477",
      "tgn:7007250",
      "tgn:7029392"
    ],
    "placetype": [
      "aat:300008347"
    ],
    "id": 2026177,
    "name:xx": "Terreton"
  }
}
