{
  "geometry": {
    "type": "Point",
    "coordinates": [
      -133.0833,
      55.55
    ]
  },
  "type": "Feature",
  "properties": {
    "hierarchy": [
      "tgn:7016126",
      "tgn:7006450",
      "tgn:1000001",
      "tgn:7012149",
      "tgn:2000082",
      "tgn:7019648",
      "tgn:7029392"
    ],
    "placetype": [
      "aat:300008347"
    ],
    "id": 7016126,
    "name:xx": "Klawock"
  }
}
