{
  "type": "FeatureCollection",
  "features": [
    {
      "geometry": {
        "type": "Point",
        "coordinates": [
          -103.866667,
          27.066667
        ]
      },
      "type": "Feature",
      "properties": {
        "hierarchy": [
          "tgn:7377040",
          "tgn:7005581",
          "tgn:1000001",
          "tgn:7005560",
          "tgn:7029392"
        ],
        "placetype": [
          "aat:300000241"
        ],
        "id": 7377040,
        "name:xx": "Rancho La Trinidad"
      }
    },
    {
      "geometry": {
        "type": "Point",
        "coordinates": [
          -98.816667,
          24.65
        ]
      },
      "type": "Feature",
      "properties": {
        "hierarchy": [
          "tgn:7377041",
          "tgn:1000001",
          "tgn:7005597",
          "tgn:7005560",
          "tgn:7029392"
        ],
        "placetype": [
          "aat:300000241"
        ],
        "id": 7377041,
        "name:xx": "Rancho La Trinidad"
      }
    },
    {
      "geometry": {
        "type": "Point",
        "coordinates": [
          -109.333333,
          28.183333
        ]
      },
      "type": "Feature",
      "properties": {
        "hierarchy": [
          "tgn:7377042",
          "tgn:1000001",
          "tgn:1001960",
          "tgn:7005560",
          "tgn:7029392"
        ],
        "placetype": [
          "aat:300008699"
        ],
        "id": 7377042,
        "name:xx": "La Trinidad, Arroyo"
      }
    },
    {
      "geometry": {
        "type": "Point",
        "coordinates": [
          -98.7,
          19.95
        ]
      },
      "type": "Feature",
      "properties": {
        "hierarchy": [
          "tgn:7377043",
          "tgn:7005587",
          "tgn:1000001",
          "tgn:7005560",
          "tgn:7029392"
        ],
        "placetype": [
          "aat:300007783"
        ],
        "id": 7377043,
        "name:xx": "La Trinidad"
      }
    },
    {
      "geometry": {
        "type": "Point",
        "coordinates": [
          -102.45,
          20.95
        ]
      },
      "type": "Feature",
      "properties": {
        "hierarchy": [
          "tgn:7377044",
          "tgn:7005586",
          "tgn:1000001",
          "tgn:7005560",
          "tgn:7029392"
        ],
        "placetype": [
          "aat:300000241"
        ],
        "id": 7377044,
        "name:xx": "La Trinidad"
      }
    },
    {
      "geometry": {
        "type": "Point",
        "coordinates": [
          -102.05,
          20.816667
        ]
      },
      "type": "Feature",
      "properties": {
        "hierarchy": [
          "tgn:7377045",
          "tgn:7005586",
          "tgn:1000001",
          "tgn:7005560",
          "tgn:7029392"
        ],
        "placetype": [
          "aat:300000241"
        ],
        "id": 7377045,
        "name:xx": "La Trinidad"
      }
    },
    {
      "geometry": {
        "type": "Point",
        "coordinates": [
          -102.466667,
          20.666667
        ]
      },
      "type": "Feature",
      "properties": {
        "hierarchy": [
          "tgn:7377046",
          "tgn:7005586",
          "tgn:1000001",
          "tgn:7005560",
          "tgn:7029392"
        ],
        "placetype": [
          "aat:300000241"
        ],
        "id": 7377046,
        "name:xx": "La Trinidad"
      }
    },
    {
      "geometry": {
        "type": "Point",
        "coordinates": [
          -111.45,
          28.616667
        ]
      },
      "type": "Feature",
      "properties": {
        "hierarchy": [
          "tgn:7377047",
          "tgn:1000001",
          "tgn:1001960",
          "tgn:7005560",
          "tgn:7029392"
        ],
        "placetype": [
          "aat:300008347"
        ],
        "id": 7377047,
        "name:xx": "La Trinidad"
      }
    },
    {
      "geometry": {
        "type": "Point",
        "coordinates": [
          -109.266667,
          28.366667
        ]
      },
      "type": "Feature",
      "properties": {
        "hierarchy": [
          "tgn:7377048",
          "tgn:1000001",
          "tgn:1001960",
          "tgn:7005560",
          "tgn:7029392"
        ],
        "placetype": [
          "aat:300008347"
        ],
        "id": 7377048,
        "name:xx": "La Trinidad"
      }
    },
    {
      "geometry": {
        "type": "Point",
        "coordinates": [
          -99.95,
          27.016667
        ]
      },
      "type": "Feature",
      "properties": {
        "hierarchy": [
          "tgn:7377049",
          "tgn:1000001",
          "tgn:7005589",
          "tgn:7005560",
          "tgn:7029392"
        ],
        "placetype": [
          "aat:300008347"
        ],
        "id": 7377049,
        "name:xx": "La Trinidad"
      }
    }
  ]
}
