{
  "geometry": {
    "type": "Point",
    "coordinates": [
      -83.6333,
      34.95
    ]
  },
  "type": "Feature",
  "properties": {
    "hierarchy": [
      "tgn:2372659",
      "tgn:1000001",
      "tgn:7012149",
      "tgn:2000430",
      "tgn:7007248",
      "tgn:7029392"
    ],
    "placetype": [
      "aat:300006191"
    ],
    "id": 2372659,
    "name:xx": "Hall Creek Watershed Number 25 Lake"
  }
}
