{
  "geometry": {
    "type": "Point",
    "coordinates": [
      140.3667,
      38.3667
    ]
  },
  "type": "Feature",
  "properties": {
    "hierarchy": [
      "tgn:1081530",
      "tgn:1000004",
      "tgn:7000274",
      "tgn:7000893",
      "tgn:1000120",
      "tgn:7029392"
    ],
    "placetype": [
      "aat:300008347"
    ],
    "id": 1081530,
    "name:xx": "Tendō"
  }
}
