{
  "geometry": {
    "type": "Point",
    "coordinates": [
      12.6167,
      37.8833
    ]
  },
  "type": "Feature",
  "properties": {
    "hierarchy": [
      "tgn:1122130",
      "tgn:1000003",
      "tgn:7003122",
      "tgn:1001762",
      "tgn:1000080",
      "tgn:7029392"
    ],
    "placetype": [
      "aat:300008707"
    ],
    "id": 1122130,
    "name:xx": "Bordino, Fiume di"
  }
}
