{
  "geometry": {
    "type": "Point",
    "coordinates": [
      111.5833,
      50.9833
    ]
  },
  "type": "Feature",
  "properties": {
    "hierarchy": [
      "tgn:1057733",
      "tgn:1003351",
      "tgn:1000004",
      "tgn:7018214",
      "tgn:7002435",
      "tgn:7029392"
    ],
    "placetype": [
      "aat:300008347"
    ],
    "id": 1057733,
    "name:xx": "Novopavlovskoye"
  }
}
