{
  "geometry": {
    "type": "Point",
    "coordinates": [
      -79.4167,
      35.6667
    ]
  },
  "type": "Feature",
  "properties": {
    "hierarchy": [
      "tgn:2075812",
      "tgn:1000001",
      "tgn:2001480",
      "tgn:7012149",
      "tgn:7007709",
      "tgn:7029392"
    ],
    "placetype": [
      "aat:300008347"
    ],
    "id": 2075812,
    "name:xx": "Mount Vernon Springs"
  }
}
