{
  "type": "FeatureCollection",
  "features": [
    {
      "geometry": {
        "type": "Point",
        "coordinates": [
          -70.5333,
          41.7833
        ]
      },
      "type": "Feature",
      "properties": {
        "hierarchy": [
          "tgn:2689700",
          "tgn:1000001",
          "tgn:7014423",
          "tgn:7012149",
          "tgn:7007517",
          "tgn:7029392"
        ],
        "placetype": [
          "aat:300008905"
        ],
        "id": 2689700,
        "name:xx": "Squaw Swamp"
      }
    },
    {
      "geometry": {
        "type": "Point",
        "coordinates": [
          -73.4833,
          42.5333
        ]
      },
      "type": "Feature",
      "properties": {
        "hierarchy": [
          "tgn:2689701",
          "tgn:1000001",
          "tgn:7012149",
          "tgn:1002821",
          "tgn:7007568",
          "tgn:7029392"
        ],
        "placetype": [
          "aat:300008905"
        ],
        "id": 2689701,
        "name:xx": "Squaw Swamp"
      }
    },
    {
      "geometry": {
        "type": "Point",
        "coordinates": [
          -109.9833,
          32.8333
        ]
      },
      "type": "Feature",
      "properties": {
        "hierarchy": [
          "tgn:2689702",
          "tgn:1000001",
          "tgn:7006451",
          "tgn:2000094",
          "tgn:7012149",
          "tgn:7029392"
        ],
        "placetype": [
          "aat:300006191"
        ],
        "id": 2689702,
        "name:xx": "Squaw Tank"
      }
    },
    {
      "geometry": {
        "type": "Point",
        "coordinates": [
          -110.5833,
          34.5833
        ]
      },
      "type": "Feature",
      "properties": {
        "hierarchy": [
          "tgn:2689703",
          "tgn:1000001",
          "tgn:7006451",
          "tgn:7012149",
          "tgn:2000099",
          "tgn:7029392"
        ],
        "placetype": [
          "aat:300006191"
        ],
        "id": 2689703,
        "name:xx": "Squaw Tank"
      }
    },
    {
      "geometry": {
        "type": "Point",
        "coordinates": [
          -113.75,
          36.35
        ]
      },
      "type": "Feature",
      "properties": {
        "hierarchy": [
          "tgn:2689704",
          "tgn:1000001",
          "tgn:7006451",
          "tgn:7012149",
          "tgn:2000098",
          "tgn:7029392"
        ],
        "placetype": [
          "aat:300006191"
        ],
        "id": 2689704,
        "name:xx": "Squaw Tank"
      }
    },
    {
      "geometry": {
        "type": "Point",
        "coordinates": [
          -111.3667,
          35.1
        ]
      },
      "type": "Feature",
      "properties": {
        "hierarchy": [
          "tgn:2689705",
          "tgn:1000001",
          "tgn:7006451",
          "tgn:2000092",
          "tgn:7012149",
          "tgn:7029392"
        ],
        "placetype": [
          "aat:300006191"
        ],
        "id": 2689705,
        "name:xx": "Squaw Tank"
      }
    },
    {
      "geometry": {
        "type": "Point",
        "coordinates": [
          -110.9333,
          34
        ]
      },
      "type": "Feature",
      "properties": {
        "hierarchy": [
          "tgn:2689706",
          "tgn:1000001",
          "tgn:7006451",
          "tgn:2000093",
          "tgn:7012149",
          "tgn:7029392"
        ],
        "placetype": [
          "aat:300006191"
        ],
        "id": 2689706,
        "name:xx": "Squaw Tank"
      }
    },
    {
      "geometry": {
        "type": "Point",
        "coordinates": [
          -116.0667,
          33.9167
        ]
      },
      "type": "Feature",
      "properties": {
        "hierarchy": [
          "tgn:2689707",
          "tgn:1000001",
          "tgn:7012149",
          "tgn:7007157",
          "tgn:1002828",
          "tgn:7029392"
        ],
        "placetype": [
          "aat:300006191"
        ],
        "id": 2689707,
        "name:xx": "Squaw Tank"
      }
    },
    {
      "geometry": {
        "type": "Point",
        "coordinates": [
          -106.05,
          32.6667
        ]
      },
      "type": "Feature",
      "properties": {
        "hierarchy": [
          "tgn:2689708",
          "tgn:1000001",
          "tgn:7012149",
          "tgn:2001447",
          "tgn:7007566",
          "tgn:7029392"
        ],
        "placetype": [
          "aat:300006191"
        ],
        "id": 2689708,
        "name:xx": "Squaw Tank"
      }
    },
    {
      "geometry": {
        "type": "Point",
        "coordinates": [
          -110.5833,
          34.5833
        ]
      },
      "type": "Feature",
      "properties": {
        "hierarchy": [
          "tgn:2689709",
          "tgn:1000001",
          "tgn:7006451",
          "tgn:7012149",
          "tgn:2000099",
          "tgn:7029392"
        ],
        "placetype": [
          "aat:300006191"
        ],
        "id": 2689709,
        "name:xx": "Squaw Tank South"
      }
    }
  ]
}
