{
  "geometry": {
    "type": "Point",
    "coordinates": [
      -89.9667,
      32.4167
    ]
  },
  "type": "Feature",
  "properties": {
    "hierarchy": [
      "tgn:2539139",
      "tgn:1000001",
      "tgn:7012149",
      "tgn:2001146",
      "tgn:7007522",
      "tgn:7029392"
    ],
    "placetype": [
      "aat:300008347"
    ],
    "id": 2539139,
    "name:xx": "New Fannin"
  }
}
