{
  "type": "FeatureCollection",
  "features": [
    {
      "geometry": {
        "type": "Point",
        "coordinates": [
          -87.1333,
          33.4
        ]
      },
      "type": "Feature",
      "properties": {
        "hierarchy": [
          "tgn:2604650",
          "tgn:7002659",
          "tgn:1000001",
          "tgn:7012149",
          "tgn:2000036",
          "tgn:7029392"
        ],
        "placetype": [
          "aat:300008699"
        ],
        "id": 2604650,
        "name:xx": "Raccoon Branch"
      }
    },
    {
      "geometry": {
        "type": "Point",
        "coordinates": [
          -81.4667,
          31.9333
        ]
      },
      "type": "Feature",
      "properties": {
        "hierarchy": [
          "tgn:2604651",
          "tgn:1000001",
          "tgn:7012149",
          "tgn:7007248",
          "tgn:7029392"
        ],
        "placetype": [
          "aat:300008699"
        ],
        "id": 2604651,
        "name:xx": "Raccoon Branch"
      }
    },
    {
      "geometry": {
        "type": "Point",
        "coordinates": [
          -84.6667,
          34.5333
        ]
      },
      "type": "Feature",
      "properties": {
        "hierarchy": [
          "tgn:2604652",
          "tgn:1000001",
          "tgn:7012149",
          "tgn:2000355",
          "tgn:7007248",
          "tgn:7029392"
        ],
        "placetype": [
          "aat:300008699"
        ],
        "id": 2604652,
        "name:xx": "Raccoon Branch"
      }
    },
    {
      "geometry": {
        "type": "Point",
        "coordinates": [
          -86,
          38.25
        ]
      },
      "type": "Feature",
      "properties": {
        "hierarchy": [
          "tgn:2604653",
          "tgn:1000001",
          "tgn:7012149",
          "tgn:1002457",
          "tgn:7007252",
          "tgn:7029392"
        ],
        "placetype": [
          "aat:300008699"
        ],
        "id": 2604653,
        "name:xx": "Raccoon Branch"
      }
    },
    {
      "geometry": {
        "type": "Point",
        "coordinates": [
          -85.7667,
          36.9667
        ]
      },
      "type": "Feature",
      "properties": {
        "hierarchy": [
          "tgn:2604654",
          "tgn:2000768",
          "tgn:1000001",
          "tgn:7012149",
          "tgn:7007255",
          "tgn:7029392"
        ],
        "placetype": [
          "aat:300008699"
        ],
        "id": 2604654,
        "name:xx": "Raccoon Branch"
      }
    },
    {
      "geometry": {
        "type": "Point",
        "coordinates": [
          -82.5667,
          37.4333
        ]
      },
      "type": "Feature",
      "properties": {
        "hierarchy": [
          "tgn:2604655",
          "tgn:1000001",
          "tgn:7012149",
          "tgn:2000837",
          "tgn:7007255",
          "tgn:7029392"
        ],
        "placetype": [
          "aat:300008699"
        ],
        "id": 2604655,
        "name:xx": "Raccoon Branch"
      }
    },
    {
      "geometry": {
        "type": "Point",
        "coordinates": [
          -85.0833,
          37.9667
        ]
      },
      "type": "Feature",
      "properties": {
        "hierarchy": [
          "tgn:2604656",
          "tgn:1002147",
          "tgn:1000001",
          "tgn:7012149",
          "tgn:7007255",
          "tgn:7029392"
        ],
        "placetype": [
          "aat:300008699"
        ],
        "id": 2604656,
        "name:xx": "Raccoon Branch"
      }
    },
    {
      "geometry": {
        "type": "Point",
        "coordinates": [
          -83.3,
          38.3667
        ]
      },
      "type": "Feature",
      "properties": {
        "hierarchy": [
          "tgn:2604657",
          "tgn:1000001",
          "tgn:7012149",
          "tgn:1002591",
          "tgn:7007255",
          "tgn:7029392"
        ],
        "placetype": [
          "aat:300008699"
        ],
        "id": 2604657,
        "name:xx": "Raccoon Branch"
      }
    },
    {
      "geometry": {
        "type": "Point",
        "coordinates": [
          -84.9,
          38.4
        ]
      },
      "type": "Feature",
      "properties": {
        "hierarchy": [
          "tgn:2604658",
          "tgn:1000001",
          "tgn:7012149",
          "tgn:1002469",
          "tgn:7007255",
          "tgn:7029392"
        ],
        "placetype": [
          "aat:300008699"
        ],
        "id": 2604658,
        "name:xx": "Raccoon Branch"
      }
    },
    {
      "geometry": {
        "type": "Point",
        "coordinates": [
          -83.2667,
          36.75
        ]
      },
      "type": "Feature",
      "properties": {
        "hierarchy": [
          "tgn:2604659",
          "tgn:1000001",
          "tgn:7012149",
          "tgn:2000797",
          "tgn:7007255",
          "tgn:7029392"
        ],
        "placetype": [
          "aat:300008699"
        ],
        "id": 2604659,
        "name:xx": "Raccoon Branch"
      }
    }
  ]
}
