{
  "geometry": {
    "type": "Point",
    "coordinates": [
      -77.5667,
      43.0167
    ]
  },
  "type": "Feature",
  "properties": {
    "hierarchy": [
      "tgn:2285172",
      "tgn:1000001",
      "tgn:7012149",
      "tgn:1002681",
      "tgn:7007568",
      "tgn:7029392"
    ],
    "placetype": [
      "aat:300008680"
    ],
    "id": 2285172,
    "name:xx": "Devils Bathtub"
  }
}
