{
  "geometry": {
    "type": "Point",
    "coordinates": [
      -84.9167,
      35.8833
    ]
  },
  "type": "Feature",
  "properties": {
    "hierarchy": [
      "tgn:2506029",
      "tgn:1000001",
      "tgn:7012149",
      "tgn:2001854",
      "tgn:7007825",
      "tgn:7029392"
    ],
    "placetype": [
      "aat:300008347"
    ],
    "id": 2506029,
    "name:xx": "Meridian"
  }
}
