{
  "geometry": {
    "type": "Point",
    "coordinates": [
      166.6333,
      19.3167
    ]
  },
  "type": "Feature",
  "properties": {
    "hierarchy": [
      "tgn:1008557",
      "tgn:1000001",
      "tgn:7012149",
      "tgn:7006050",
      "tgn:7029392"
    ],
    "placetype": [
      "aat:300008791"
    ],
    "id": 1008557,
    "name:xx": "Peale Island"
  }
}
