{
  "geometry": {
    "type": "Point",
    "coordinates": [
      -84.3167,
      44.05
    ]
  },
  "type": "Feature",
  "properties": {
    "hierarchy": [
      "tgn:2482143",
      "tgn:1000001",
      "tgn:7012149",
      "tgn:2000959",
      "tgn:7007520",
      "tgn:7029392"
    ],
    "placetype": [
      "aat:300006075"
    ],
    "id": 2482143,
    "name:xx": "Lang Drain"
  }
}
