{
  "geometry": {
    "type": "Point",
    "coordinates": [
      -107.45,
      41.6167
    ]
  },
  "type": "Feature",
  "properties": {
    "hierarchy": [
      "tgn:2666702",
      "tgn:1000001",
      "tgn:2002368",
      "tgn:7012149",
      "tgn:7007923",
      "tgn:7029392"
    ],
    "placetype": [
      "aat:300006191"
    ],
    "id": 2666702,
    "name:xx": "Sixteenmile Reservoir"
  }
}
