{
  "geometry": {
    "type": "Point",
    "coordinates": [
      -152.45,
      57.6667
    ]
  },
  "type": "Feature",
  "properties": {
    "hierarchy": [
      "tgn:2507980",
      "tgn:7006450",
      "tgn:1000001",
      "tgn:2124012",
      "tgn:7012149",
      "tgn:7029392"
    ],
    "placetype": [
      "aat:300132316"
    ],
    "id": 2507980,
    "name:xx": "Middle Bay"
  }
}
