{
  "geometry": {
    "type": "Point",
    "coordinates": [
      -76.5833,
      41.3333
    ]
  },
  "type": "Feature",
  "properties": {
    "hierarchy": [
      "tgn:2091063",
      "tgn:1000001",
      "tgn:7012149",
      "tgn:1002927",
      "tgn:7007710",
      "tgn:7029392"
    ],
    "placetype": [
      "aat:300008347"
    ],
    "id": 2091063,
    "name:xx": "Muncy Valley"
  }
}
