{
  "geometry": {
    "type": "Point",
    "coordinates": [
      -110.9167,
      42.8167
    ]
  },
  "type": "Feature",
  "properties": {
    "hierarchy": [
      "tgn:2191819",
      "tgn:1000001",
      "tgn:7012149",
      "tgn:2002376",
      "tgn:7007923",
      "tgn:7029392"
    ],
    "placetype": [
      "aat:300008761"
    ],
    "id": 2191819,
    "name:xx": "Bradshaw Canyon"
  }
}
