{
  "type": "FeatureCollection",
  "features": [
    {
      "geometry": {
        "type": "Point",
        "coordinates": [
          -71.766667,
          -34
        ]
      },
      "type": "Feature",
      "properties": {
        "hierarchy": [
          "tgn:7315810",
          "tgn:1001708",
          "tgn:1000049",
          "tgn:1000002",
          "tgn:7029392"
        ],
        "placetype": [
          "aat:300387200"
        ],
        "id": 7315810,
        "name:xx": "Centinela de Rapel"
      }
    },
    {
      "geometry": {
        "type": "Point",
        "coordinates": [
          -74.233333,
          -43.433333
        ]
      },
      "type": "Feature",
      "properties": {
        "hierarchy": [
          "tgn:7315811",
          "tgn:1001699",
          "tgn:1000049",
          "tgn:1000002",
          "tgn:7029392"
        ],
        "placetype": [
          "aat:300386846"
        ],
        "id": 7315811,
        "name:xx": "Centinela, Punta"
      }
    },
    {
      "geometry": {
        "type": "Point",
        "coordinates": [
          -73.322222,
          -43.005
        ]
      },
      "type": "Feature",
      "properties": {
        "hierarchy": [
          "tgn:7315812",
          "tgn:1001699",
          "tgn:1000049",
          "tgn:1000002",
          "tgn:7029392"
        ],
        "placetype": [
          "aat:300386846"
        ],
        "id": 7315812,
        "name:xx": "Punta Centinela"
      }
    },
    {
      "geometry": {
        "type": "Point",
        "coordinates": [
          -73.031667,
          -41.860278
        ]
      },
      "type": "Feature",
      "properties": {
        "hierarchy": [
          "tgn:7315813",
          "tgn:1001699",
          "tgn:1000049",
          "tgn:1000002",
          "tgn:7029392"
        ],
        "placetype": [
          "aat:300386846"
        ],
        "id": 7315813,
        "name:xx": "Centinela, Punta"
      }
    },
    {
      "geometry": {
        "type": "Point",
        "coordinates": [
          -72.866667,
          -40.983333
        ]
      },
      "type": "Feature",
      "properties": {
        "hierarchy": [
          "tgn:7315814",
          "tgn:1001699",
          "tgn:1000049",
          "tgn:1000002",
          "tgn:7029392"
        ],
        "placetype": [
          "aat:300386846"
        ],
        "id": 7315814,
        "name:xx": "Centinela, Punta"
      }
    },
    {
      "geometry": {
        "type": "Point",
        "coordinates": [
          -71.983333,
          -34.25
        ]
      },
      "type": "Feature",
      "properties": {
        "hierarchy": [
          "tgn:7315815",
          "tgn:1001695",
          "tgn:1000049",
          "tgn:1000002",
          "tgn:7029392"
        ],
        "placetype": [
          "aat:300386846"
        ],
        "id": 7315815,
        "name:xx": "Centinela, Punta"
      }
    },
    {
      "geometry": {
        "type": "Point",
        "coordinates": [
          -71.283333,
          -33.516667
        ]
      },
      "type": "Feature",
      "properties": {
        "hierarchy": [
          "tgn:7315816",
          "tgn:1001708",
          "tgn:1000049",
          "tgn:1000002",
          "tgn:7029392"
        ],
        "placetype": [
          "aat:300008777"
        ],
        "id": 7315816,
        "name:xx": "Centinela, Morro"
      }
    },
    {
      "geometry": {
        "type": "Point",
        "coordinates": [
          -72.416667,
          -42.533333
        ]
      },
      "type": "Feature",
      "properties": {
        "hierarchy": [
          "tgn:7315817",
          "tgn:1001699",
          "tgn:1000049",
          "tgn:1000002",
          "tgn:7029392"
        ],
        "placetype": [
          "aat:300008795"
        ],
        "id": 7315817,
        "name:xx": "Centinela, Monte"
      }
    },
    {
      "geometry": {
        "type": "Point",
        "coordinates": [
          -69.983333,
          -55.066667
        ]
      },
      "type": "Feature",
      "properties": {
        "hierarchy": [
          "tgn:7315818",
          "tgn:1001702",
          "tgn:1000049",
          "tgn:1000002",
          "tgn:7029392"
        ],
        "placetype": [
          "aat:300008791"
        ],
        "id": 7315818,
        "name:xx": "Centinela, Islote"
      }
    },
    {
      "geometry": {
        "type": "Point",
        "coordinates": [
          -73.6,
          -53.066667
        ]
      },
      "type": "Feature",
      "properties": {
        "hierarchy": [
          "tgn:7315819",
          "tgn:1001702",
          "tgn:1000049",
          "tgn:1000002",
          "tgn:7029392"
        ],
        "placetype": [
          "aat:300008791"
        ],
        "id": 7315819,
        "name:xx": "Centinela, Isla"
      }
    }
  ]
}
