{
  "geometry": {
    "type": "Point",
    "coordinates": [
      -42.2333,
      -8.35
    ]
  },
  "type": "Feature",
  "properties": {
    "hierarchy": [
      "tgn:1022817",
      "tgn:7006252",
      "tgn:1000047",
      "tgn:7002455",
      "tgn:1000002",
      "tgn:7029392"
    ],
    "placetype": [
      "aat:300008347"
    ],
    "id": 1022817,
    "name:xx": "São João do Piauí"
  }
}
