{
  "geometry": {
    "type": "Point",
    "coordinates": [
      -67.95,
      44.9167
    ]
  },
  "type": "Feature",
  "properties": {
    "hierarchy": [
      "tgn:2739687",
      "tgn:1000001",
      "tgn:7012149",
      "tgn:7014589",
      "tgn:7007515",
      "tgn:7029392"
    ],
    "placetype": [
      "aat:300008680"
    ],
    "id": 2739687,
    "name:xx": "Upper Cranberry Lake"
  }
}
