{
  "geometry": {
    "type": "Point",
    "coordinates": [
      -87.8333,
      45.4167
    ]
  },
  "type": "Feature",
  "properties": {
    "hierarchy": [
      "tgn:2201878",
      "tgn:1000001",
      "tgn:7012149",
      "tgn:2000978",
      "tgn:7007520",
      "tgn:7029392"
    ],
    "placetype": [
      "aat:300008798"
    ],
    "id": 2201878,
    "name:xx": "Buck Hill"
  }
}
