{
  "geometry": {
    "type": "Point",
    "coordinates": [
      -100.05,
      20.133333
    ]
  },
  "type": "Feature",
  "properties": {
    "hierarchy": [
      "tgn:7399265",
      "tgn:1000001",
      "tgn:7005593",
      "tgn:7005560",
      "tgn:7029392"
    ],
    "placetype": [
      "aat:300008697"
    ],
    "id": 7399265,
    "name:xx": "El Capulín, Poza"
  }
}
