{
  "geometry": {
    "type": "Point",
    "coordinates": [
      -89.5667,
      32.65
    ]
  },
  "type": "Feature",
  "properties": {
    "hierarchy": [
      "tgn:2731298",
      "tgn:1000001",
      "tgn:7012149",
      "tgn:2001125",
      "tgn:7007522",
      "tgn:7029392"
    ],
    "placetype": [
      "aat:300008347"
    ],
    "id": 2731298,
    "name:xx": "Tuckers Crossing"
  }
}
