{
  "type": "FeatureCollection",
  "features": [
    {
      "geometry": {
        "type": "Point",
        "coordinates": [
          -103.45,
          47.0833
        ]
      },
      "type": "Feature",
      "properties": {
        "hierarchy": [
          "tgn:2779270",
          "tgn:2001560",
          "tgn:1000001",
          "tgn:7012149",
          "tgn:7007705",
          "tgn:7029392"
        ],
        "placetype": [
          "aat:300008761"
        ],
        "id": 2779270,
        "name:xx": "Wolf Draw"
      }
    },
    {
      "geometry": {
        "type": "Point",
        "coordinates": [
          -103.8667,
          43.85
        ]
      },
      "type": "Feature",
      "properties": {
        "hierarchy": [
          "tgn:2779271",
          "tgn:1000001",
          "tgn:7012149",
          "tgn:7007713",
          "tgn:7029392"
        ],
        "placetype": [
          "aat:300008761"
        ],
        "id": 2779271,
        "name:xx": "Wolf Draw"
      }
    },
    {
      "geometry": {
        "type": "Point",
        "coordinates": [
          -100.15,
          32.25
        ]
      },
      "type": "Feature",
      "properties": {
        "hierarchy": [
          "tgn:2779272",
          "tgn:1000001",
          "tgn:7012149",
          "tgn:2002048",
          "tgn:7007826",
          "tgn:7029392"
        ],
        "placetype": [
          "aat:300008761"
        ],
        "id": 2779272,
        "name:xx": "Wolf Draw"
      }
    },
    {
      "geometry": {
        "type": "Point",
        "coordinates": [
          -99.3167,
          30.4667
        ]
      },
      "type": "Feature",
      "properties": {
        "hierarchy": [
          "tgn:2779273",
          "tgn:1000001",
          "tgn:7012149",
          "tgn:2002019",
          "tgn:7007826",
          "tgn:7029392"
        ],
        "placetype": [
          "aat:300008761"
        ],
        "id": 2779273,
        "name:xx": "Wolf Draw"
      }
    },
    {
      "geometry": {
        "type": "Point",
        "coordinates": [
          -119.8167,
          47.75
        ]
      },
      "type": "Feature",
      "properties": {
        "hierarchy": [
          "tgn:2779274",
          "tgn:1000001",
          "tgn:2002242",
          "tgn:7012149",
          "tgn:7007920",
          "tgn:7029392"
        ],
        "placetype": [
          "aat:300008761"
        ],
        "id": 2779274,
        "name:xx": "Wolf Draw"
      }
    },
    {
      "geometry": {
        "type": "Point",
        "coordinates": [
          -105.0333,
          44.4667
        ]
      },
      "type": "Feature",
      "properties": {
        "hierarchy": [
          "tgn:2779275",
          "tgn:1000001",
          "tgn:7012149",
          "tgn:7007923",
          "tgn:7029392"
        ],
        "placetype": [
          "aat:300008761"
        ],
        "id": 2779275,
        "name:xx": "Wolf Draw"
      }
    },
    {
      "geometry": {
        "type": "Point",
        "coordinates": [
          -107.0333,
          44.7333
        ]
      },
      "type": "Feature",
      "properties": {
        "hierarchy": [
          "tgn:2779276",
          "tgn:1000001",
          "tgn:7012149",
          "tgn:2002381",
          "tgn:7007923",
          "tgn:7029392"
        ],
        "placetype": [
          "aat:300008761"
        ],
        "id": 2779276,
        "name:xx": "Wolf Draw"
      }
    },
    {
      "geometry": {
        "type": "Point",
        "coordinates": [
          -92.4,
          35.4833
        ]
      },
      "type": "Feature",
      "properties": {
        "hierarchy": [
          "tgn:2779277",
          "tgn:1000001",
          "tgn:7016172",
          "tgn:7012149",
          "tgn:2000175",
          "tgn:7029392"
        ],
        "placetype": [
          "aat:300008761"
        ],
        "id": 2779277,
        "name:xx": "Wolf Fall Hollow"
      }
    },
    {
      "geometry": {
        "type": "Point",
        "coordinates": [
          -115.4,
          45.1667
        ]
      },
      "type": "Feature",
      "properties": {
        "hierarchy": [
          "tgn:2779278",
          "tgn:1000001",
          "tgn:7012149",
          "tgn:7007250",
          "tgn:7029392"
        ],
        "placetype": [
          "aat:300008706"
        ],
        "id": 2779278,
        "name:xx": "Wolf Fang Creek"
      }
    },
    {
      "geometry": {
        "type": "Point",
        "coordinates": [
          -115.4,
          45.1667
        ]
      },
      "type": "Feature",
      "properties": {
        "hierarchy": [
          "tgn:2779279",
          "tgn:1000001",
          "tgn:7012149",
          "tgn:2000494",
          "tgn:7007250",
          "tgn:7029392"
        ],
        "placetype": [
          "aat:300008798"
        ],
        "id": 2779279,
        "name:xx": "Wolf Fang Peak"
      }
    }
  ]
}
