{
  "geometry": {
    "type": "Point",
    "coordinates": [
      -74.75,
      9.114
    ]
  },
  "type": "Feature",
  "properties": {
    "hierarchy": [
      "tgn:1129554",
      "tgn:1000050",
      "tgn:1000002",
      "tgn:7029392"
    ],
    "placetype": [
      "aat:300008707"
    ],
    "id": 1129554,
    "name:xx": "San Jorge, Río"
  }
}
