{
  "geometry": {
    "type": "Point",
    "coordinates": [
      -104.35,
      32.0167
    ]
  },
  "type": "Feature",
  "properties": {
    "hierarchy": [
      "tgn:2752507",
      "tgn:1000001",
      "tgn:2001436",
      "tgn:7012149",
      "tgn:7007566",
      "tgn:7029392"
    ],
    "placetype": [
      "aat:300008697"
    ],
    "id": 2752507,
    "name:xx": "Washington Spring"
  }
}
