{
  "geometry": {
    "type": "Point",
    "coordinates": [
      -75.9667,
      36.4833
    ]
  },
  "type": "Feature",
  "properties": {
    "hierarchy": [
      "tgn:2202037",
      "tgn:1000001",
      "tgn:7012149",
      "tgn:1002312",
      "tgn:7007709",
      "tgn:7029392"
    ],
    "placetype": [
      "aat:300132316"
    ],
    "id": 2202037,
    "name:xx": "Buck Island Bay"
  }
}
