{
  "geometry": {
    "type": "Point",
    "coordinates": [
      -114.25,
      42.25
    ]
  },
  "type": "Feature",
  "properties": {
    "hierarchy": [
      "tgn:2488227",
      "tgn:1000001",
      "tgn:2000467",
      "tgn:7012149",
      "tgn:7007250",
      "tgn:7029392"
    ],
    "placetype": [
      "aat:300386845"
    ],
    "id": 2488227,
    "name:xx": "Magpie Basin"
  }
}
