{
  "geometry": {
    "type": "Point",
    "coordinates": [
      80.604126,
      23.996345
    ]
  },
  "type": "Feature",
  "properties": {
    "hierarchy": [
      "tgn:7549745",
      "tgn:1000004",
      "tgn:7000198",
      "tgn:1001894",
      "tgn:7029392"
    ],
    "placetype": [
      "aat:300008347"
    ],
    "name:en": "Bijerāghogarh",
    "id": 7549745
  }
}
