{
  "geometry": {
    "type": "Point",
    "coordinates": [
      -71.1333,
      42.35
    ]
  },
  "type": "Feature",
  "properties": {
    "hierarchy": [
      "tgn:2049479",
      "tgn:7013445",
      "tgn:1000001",
      "tgn:1002923",
      "tgn:7012149",
      "tgn:7007517",
      "tgn:7029392"
    ],
    "placetype": [
      "aat:300000745"
    ],
    "id": 2049479,
    "name:xx": "North Brighton"
  }
}
