{
  "geometry": {
    "type": "Point",
    "coordinates": [
      -62.5333,
      5.9167
    ]
  },
  "type": "Feature",
  "properties": {
    "hierarchy": [
      "tgn:1107798",
      "tgn:1001843",
      "tgn:1000002",
      "tgn:1000059",
      "tgn:7029392"
    ],
    "placetype": [
      "aat:300008811"
    ],
    "id": 1107798,
    "name:xx": "Auyán Tepuy"
  }
}
