{
  "geometry": {
    "type": "Point",
    "coordinates": [
      -82.2833,
      35.3167
    ]
  },
  "type": "Feature",
  "properties": {
    "hierarchy": [
      "tgn:2500035",
      "tgn:1000001",
      "tgn:7012149",
      "tgn:2001531",
      "tgn:7007709",
      "tgn:7029392"
    ],
    "placetype": [
      "aat:300008798"
    ],
    "id": 2500035,
    "name:xx": "McCraw Mountain"
  }
}
