{
  "type": "FeatureCollection",
  "features": [
    {
      "geometry": {
        "type": "Point",
        "coordinates": [
          16.8333,
          -27.1667
        ]
      },
      "type": "Feature",
      "properties": {
        "hierarchy": [
          "tgn:1110300",
          "tgn:7001242",
          "tgn:1000198",
          "tgn:7029392"
        ],
        "placetype": [
          "aat:300132339"
        ],
        "id": 1110300,
        "name:xx": "Huib-Hoch Plateau"
      }
    },
    {
      "geometry": {
        "type": "Point",
        "coordinates": [
          46,
          41.3333
        ]
      },
      "type": "Feature",
      "properties": {
        "hierarchy": [
          "tgn:1110301",
          "tgn:1000004",
          "tgn:7029392"
        ],
        "placetype": [
          "aat:300132339"
        ],
        "id": 1110301,
        "name:xx": "Iorskoje ploskogorje"
      }
    },
    {
      "geometry": {
        "type": "Point",
        "coordinates": [
          132.5,
          35
        ]
      },
      "type": "Feature",
      "properties": {
        "hierarchy": [
          "tgn:1110302",
          "tgn:7016808",
          "tgn:7000897",
          "tgn:1000004",
          "tgn:1000120",
          "tgn:7029392"
        ],
        "placetype": [
          "aat:300132339"
        ],
        "id": 1110302,
        "name:xx": "Iwami-kōgen"
      }
    },
    {
      "geometry": {
        "type": "Point",
        "coordinates": [
          29,
          19
        ]
      },
      "type": "Feature",
      "properties": {
        "hierarchy": [
          "tgn:1110303",
          "tgn:7001242",
          "tgn:1001112",
          "tgn:1000201",
          "tgn:7029392"
        ],
        "placetype": [
          "aat:300132339"
        ],
        "id": 1110303,
        "name:xx": "Jabal Abyad Plateau"
      }
    },
    {
      "geometry": {
        "type": "Point",
        "coordinates": [
          9.5,
          1
        ]
      },
      "type": "Feature",
      "properties": {
        "hierarchy": [
          "tgn:1110304",
          "tgn:7001242",
          "tgn:1000182",
          "tgn:7029392"
        ],
        "placetype": [
          "aat:300132339"
        ],
        "id": 1110304,
        "name:xx": "Jos Plateau"
      }
    },
    {
      "geometry": {
        "type": "Point",
        "coordinates": [
          23.95,
          -28.3333
        ]
      },
      "type": "Feature",
      "properties": {
        "hierarchy": [
          "tgn:1110305",
          "tgn:7001242",
          "tgn:7029392"
        ],
        "placetype": [
          "aat:300132339"
        ],
        "id": 1110305,
        "name:xx": "Kaap Plato"
      }
    }
  ]
}
