{
  "geometry": {
    "type": "Point",
    "coordinates": [
      -83.4833,
      38.5333
    ]
  },
  "type": "Feature",
  "properties": {
    "hierarchy": [
      "tgn:2329095",
      "tgn:1000001",
      "tgn:7012149",
      "tgn:1002591",
      "tgn:7007255",
      "tgn:7029392"
    ],
    "placetype": [
      "aat:300008761"
    ],
    "id": 2329095,
    "name:xx": "Fite Hollow"
  }
}
