{
  "geometry": {
    "type": "Point",
    "coordinates": [
      -85.0667,
      40.4833
    ]
  },
  "type": "Feature",
  "properties": {
    "hierarchy": [
      "tgn:2592249",
      "tgn:1000001",
      "tgn:7012149",
      "tgn:1002513",
      "tgn:7007252",
      "tgn:7029392"
    ],
    "placetype": [
      "aat:300008699"
    ],
    "id": 2592249,
    "name:xx": "Pony Run"
  }
}
