{
  "geometry": {
    "type": "Point",
    "coordinates": [
      -77.0833,
      38.15
    ]
  },
  "type": "Feature",
  "properties": {
    "hierarchy": [
      "tgn:2252119",
      "tgn:1000001",
      "tgn:7012149",
      "tgn:1002362",
      "tgn:7007919",
      "tgn:7029392"
    ],
    "placetype": [
      "aat:300008706"
    ],
    "id": 2252119,
    "name:xx": "Cone Creek"
  }
}
