{
  "geometry": {
    "type": "Point",
    "coordinates": [
      -118.1333,
      46.55
    ]
  },
  "type": "Feature",
  "properties": {
    "hierarchy": [
      "tgn:2238387",
      "tgn:1000001",
      "tgn:2002241",
      "tgn:7012149",
      "tgn:7007920",
      "tgn:7029392"
    ],
    "placetype": [
      "aat:300008697"
    ],
    "id": 2238387,
    "name:xx": "Choke Cherry Spring"
  }
}
