{
  "geometry": {
    "type": "Point",
    "coordinates": [
      120.35,
      40.35
    ]
  },
  "type": "Feature",
  "properties": {
    "hierarchy": [
      "tgn:1072008",
      "tgn:1000004",
      "tgn:1001390",
      "tgn:1000111",
      "tgn:7029392"
    ],
    "placetype": [
      "aat:300008347"
    ],
    "id": 1072008,
    "name:xx": "Suizhong"
  }
}
