{
  "geometry": {
    "type": "Point",
    "coordinates": [
      -81.0667,
      38.65
    ]
  },
  "type": "Feature",
  "properties": {
    "hierarchy": [
      "tgn:2120073",
      "tgn:1000001",
      "tgn:2002258",
      "tgn:7012149",
      "tgn:7013961",
      "tgn:7029392"
    ],
    "placetype": [
      "aat:300008347",
      "aat:300387210"
    ],
    "id": 2120073,
    "name:xx": "Stinson"
  }
}
