{
  "type": "FeatureCollection",
  "features": [
    {
      "geometry": {
        "type": "Point",
        "coordinates": [
          7.4,
          51.266667
        ]
      },
      "type": "Feature",
      "properties": {
        "hierarchy": [
          "tgn:7130200",
          "tgn:1000003",
          "tgn:7003677",
          "tgn:7000084",
          "tgn:7029392"
        ],
        "placetype": [
          "aat:300000206"
        ],
        "id": 7130200,
        "name:xx": "Mitten Hesterberg"
      }
    },
    {
      "geometry": {
        "type": "Point",
        "coordinates": [
          11.566667,
          48.266667
        ]
      },
      "type": "Feature",
      "properties": {
        "hierarchy": [
          "tgn:7130201",
          "tgn:7003669",
          "tgn:1000003",
          "tgn:7000084",
          "tgn:7029392"
        ],
        "placetype": [
          "aat:300008347"
        ],
        "id": 7130201,
        "name:xx": "Mittenheim"
      }
    },
    {
      "geometry": {
        "type": "Point",
        "coordinates": [
          9.533333,
          48.233333
        ]
      },
      "type": "Feature",
      "properties": {
        "hierarchy": [
          "tgn:7130202",
          "tgn:7003692",
          "tgn:1000003",
          "tgn:7000084",
          "tgn:7029392"
        ],
        "placetype": [
          "aat:300008347"
        ],
        "id": 7130202,
        "name:xx": "Mittenhausen"
      }
    },
    {
      "geometry": {
        "type": "Point",
        "coordinates": [
          8.433333,
          53.416667
        ]
      },
      "type": "Feature",
      "properties": {
        "hierarchy": [
          "tgn:7130203",
          "tgn:1000003",
          "tgn:7003676",
          "tgn:7000084",
          "tgn:7029392"
        ],
        "placetype": [
          "aat:300000206"
        ],
        "id": 7130203,
        "name:xx": "Mittenfelde"
      }
    },
    {
      "geometry": {
        "type": "Point",
        "coordinates": [
          8,
          52
        ]
      },
      "type": "Feature",
      "properties": {
        "hierarchy": [
          "tgn:7130204",
          "tgn:1000003",
          "tgn:7003677",
          "tgn:7000084",
          "tgn:7029392"
        ],
        "placetype": [
          "aat:300000206"
        ],
        "id": 7130204,
        "name:xx": "Mittendorf"
      }
    },
    {
      "geometry": {
        "type": "Point",
        "coordinates": [
          8.5,
          48.133333
        ]
      },
      "type": "Feature",
      "properties": {
        "hierarchy": [
          "tgn:7130205",
          "tgn:7003692",
          "tgn:1000003",
          "tgn:7000084",
          "tgn:7029392"
        ],
        "placetype": [
          "aat:300000206"
        ],
        "id": 7130205,
        "name:xx": "Mittendorf"
      }
    },
    {
      "geometry": {
        "type": "Point",
        "coordinates": [
          8.383333,
          50.7
        ]
      },
      "type": "Feature",
      "properties": {
        "hierarchy": [
          "tgn:7130206",
          "tgn:1000003",
          "tgn:7003678",
          "tgn:7000084",
          "tgn:7029392"
        ],
        "placetype": [
          "aat:300008347"
        ],
        "id": 7130206,
        "name:xx": "Mittenaar"
      }
    },
    {
      "geometry": {
        "type": "Point",
        "coordinates": [
          9.633333,
          47.566667
        ]
      },
      "type": "Feature",
      "properties": {
        "hierarchy": [
          "tgn:7130207",
          "tgn:7003669",
          "tgn:1000003",
          "tgn:7000084",
          "tgn:7029392"
        ],
        "placetype": [
          "aat:300008347"
        ],
        "id": 7130207,
        "name:xx": "Mitten"
      }
    },
    {
      "geometry": {
        "type": "Point",
        "coordinates": [
          9.066667,
          47.7
        ]
      },
      "type": "Feature",
      "properties": {
        "hierarchy": [
          "tgn:7130208",
          "tgn:7003692",
          "tgn:1000003",
          "tgn:7000084",
          "tgn:7029392"
        ],
        "placetype": [
          "aat:300008347"
        ],
        "id": 7130208,
        "name:xx": "Mittelzell"
      }
    },
    {
      "geometry": {
        "type": "Point",
        "coordinates": [
          7.9,
          47.75
        ]
      },
      "type": "Feature",
      "properties": {
        "hierarchy": [
          "tgn:7130209",
          "tgn:7003692",
          "tgn:1000003",
          "tgn:7000084",
          "tgn:7029392"
        ],
        "placetype": [
          "aat:300000206"
        ],
        "id": 7130209,
        "name:xx": "Mittelwühre"
      }
    }
  ]
}
