{
  "geometry": {
    "type": "Point",
    "coordinates": [
      -75.9833,
      37.8167
    ]
  },
  "type": "Feature",
  "properties": {
    "hierarchy": [
      "tgn:2488773",
      "tgn:1000001",
      "tgn:7012149",
      "tgn:1002548",
      "tgn:7007919",
      "tgn:7029392"
    ],
    "placetype": [
      "aat:300132316"
    ],
    "id": 2488773,
    "name:xx": "Mailboat Harbor"
  }
}
