{
  "geometry": {
    "type": "Point",
    "coordinates": [
      -65.3667,
      -10.3667
    ]
  },
  "type": "Feature",
  "properties": {
    "hierarchy": [
      "tgn:1020459",
      "tgn:1000525",
      "tgn:1000046",
      "tgn:1000002",
      "tgn:7029392"
    ],
    "placetype": [
      "aat:300008347"
    ],
    "id": 1020459,
    "name:xx": "Villa Bella"
  }
}
