{
  "geometry": {
    "type": "Point",
    "coordinates": [
      -110.45,
      39.3833
    ]
  },
  "type": "Feature",
  "properties": {
    "hierarchy": [
      "tgn:2108754",
      "tgn:1000001",
      "tgn:2002108",
      "tgn:7012149",
      "tgn:7007827",
      "tgn:7029392"
    ],
    "placetype": [
      "aat:300387016"
    ],
    "id": 2108754,
    "name:xx": "Cedar"
  }
}
