{
  "geometry": {
    "type": "Point",
    "coordinates": [
      35.6667,
      33.916
    ]
  },
  "type": "Feature",
  "properties": {
    "hierarchy": [
      "tgn:1001317",
      "tgn:1000004",
      "tgn:1000126",
      "tgn:7029392"
    ],
    "placetype": [
      "aat:300387064",
      "aat:300235093"
    ],
    "id": 1001317,
    "name:xx": "Mont-Liban, Mohafazat"
  }
}
