{
  "geometry": {
    "type": "Point",
    "coordinates": [
      -123.0333,
      47.8333
    ]
  },
  "type": "Feature",
  "properties": {
    "hierarchy": [
      "tgn:2763364",
      "tgn:1000001",
      "tgn:7012149",
      "tgn:1002521",
      "tgn:7007920",
      "tgn:7029392"
    ],
    "placetype": [
      "aat:300008706"
    ],
    "id": 2763364,
    "name:xx": "Wet Weather Creek"
  }
}
