{
  "geometry": {
    "type": "Point",
    "coordinates": [
      20.25,
      -11.0667
    ]
  },
  "type": "Feature",
  "properties": {
    "hierarchy": [
      "tgn:7000388",
      "tgn:7001242",
      "tgn:1000149",
      "tgn:1000885",
      "tgn:7029392"
    ],
    "placetype": [
      "aat:300008347"
    ],
    "id": 7000388,
    "name:xx": "Dala"
  }
}
