{
  "type": "FeatureCollection",
  "features": [
    {
      "geometry": {
        "type": "Point",
        "coordinates": [
          -106.866667,
          30.583333
        ]
      },
      "type": "Feature",
      "properties": {
        "hierarchy": [
          "tgn:7355900",
          "tgn:7005581",
          "tgn:1000001",
          "tgn:7005560",
          "tgn:7029392"
        ],
        "placetype": [
          "aat:300008697"
        ],
        "id": 7355900,
        "name:xx": "Carbonero, Ojo"
      }
    },
    {
      "geometry": {
        "type": "Point",
        "coordinates": [
          -101.766667,
          25.25
        ]
      },
      "type": "Feature",
      "properties": {
        "hierarchy": [
          "tgn:7355901",
          "tgn:1001853",
          "tgn:1000001",
          "tgn:7005560",
          "tgn:7029392"
        ],
        "placetype": [
          "aat:300008795"
        ],
        "id": 7355901,
        "name:xx": "Carbonero, Cerro del"
      }
    },
    {
      "geometry": {
        "type": "Point",
        "coordinates": [
          -101.783333,
          25.283333
        ]
      },
      "type": "Feature",
      "properties": {
        "hierarchy": [
          "tgn:7355902",
          "tgn:1001853",
          "tgn:1000001",
          "tgn:7005560",
          "tgn:7029392"
        ],
        "placetype": [
          "aat:300008763"
        ],
        "id": 7355902,
        "name:xx": "Carbonero, Cañón del"
      }
    },
    {
      "geometry": {
        "type": "Point",
        "coordinates": [
          -106.483333,
          31.1
        ]
      },
      "type": "Feature",
      "properties": {
        "hierarchy": [
          "tgn:7355903",
          "tgn:7005581",
          "tgn:1000001",
          "tgn:7005560",
          "tgn:7029392"
        ],
        "placetype": [
          "aat:300007783"
        ],
        "id": 7355903,
        "name:xx": "Carbonero"
      }
    },
    {
      "geometry": {
        "type": "Point",
        "coordinates": [
          -99.166667,
          23.916667
        ]
      },
      "type": "Feature",
      "properties": {
        "hierarchy": [
          "tgn:7355904",
          "tgn:1000001",
          "tgn:7005597",
          "tgn:7005560",
          "tgn:7029392"
        ],
        "placetype": [
          "aat:300007783"
        ],
        "id": 7355904,
        "name:xx": "Carbonero"
      }
    },
    {
      "geometry": {
        "type": "Point",
        "coordinates": [
          -106.866667,
          30.583333
        ]
      },
      "type": "Feature",
      "properties": {
        "hierarchy": [
          "tgn:7355905",
          "tgn:7005581",
          "tgn:1000001",
          "tgn:7005560",
          "tgn:7029392"
        ],
        "placetype": [
          "aat:300008347"
        ],
        "id": 7355905,
        "name:xx": "Carbonero"
      }
    },
    {
      "geometry": {
        "type": "Point",
        "coordinates": [
          -103.961111,
          24.191111
        ]
      },
      "type": "Feature",
      "properties": {
        "hierarchy": [
          "tgn:7355906",
          "tgn:7005583",
          "tgn:1000001",
          "tgn:7005560",
          "tgn:7029392"
        ],
        "placetype": [
          "aat:300008347"
        ],
        "id": 7355906,
        "name:xx": "Carboneras"
      }
    },
    {
      "geometry": {
        "type": "Point",
        "coordinates": [
          -107.248333,
          24.775
        ]
      },
      "type": "Feature",
      "properties": {
        "hierarchy": [
          "tgn:7355907",
          "tgn:1000001",
          "tgn:7005595",
          "tgn:7005560",
          "tgn:7029392"
        ],
        "placetype": [
          "aat:300008347"
        ],
        "id": 7355907,
        "name:xx": "Carboneras de Imala"
      }
    },
    {
      "geometry": {
        "type": "Point",
        "coordinates": [
          -104.666667,
          24.433333
        ]
      },
      "type": "Feature",
      "properties": {
        "hierarchy": [
          "tgn:7355908",
          "tgn:7005583",
          "tgn:1000001",
          "tgn:7005560",
          "tgn:7029392"
        ],
        "placetype": [
          "aat:300266554",
          "aat:300008699"
        ],
        "id": 7355908,
        "name:xx": "Carboneras, Arroyo"
      }
    },
    {
      "geometry": {
        "type": "Point",
        "coordinates": [
          -105.133333,
          20.866667
        ]
      },
      "type": "Feature",
      "properties": {
        "hierarchy": [
          "tgn:7355909",
          "tgn:7005586",
          "tgn:1000001",
          "tgn:7005560",
          "tgn:7029392"
        ],
        "placetype": [
          "aat:300008699"
        ],
        "id": 7355909,
        "name:xx": "Carboneras"
      }
    }
  ]
}
