{
  "geometry": {
    "type": "Point",
    "coordinates": [
      -118.6333,
      37.3167
    ]
  },
  "type": "Feature",
  "properties": {
    "hierarchy": [
      "tgn:2675867",
      "tgn:1000001",
      "tgn:7012149",
      "tgn:2000183",
      "tgn:7007157",
      "tgn:7029392"
    ],
    "placetype": [
      "aat:300000390"
    ],
    "id": 2675867,
    "name:xx": "Sonny Boy Prospect"
  }
}
