{
  "geometry": {
    "type": "Point",
    "coordinates": [
      -73.085,
      -43.928333
    ]
  },
  "type": "Feature",
  "properties": {
    "hierarchy": [
      "tgn:7277701",
      "tgn:1001623",
      "tgn:1000049",
      "tgn:1000002",
      "tgn:7029392"
    ],
    "placetype": [
      "aat:300008699"
    ],
    "id": 7277701,
    "name:xx": "Río Santo Domingo"
  }
}
