{
  "geometry": {
    "type": "Point",
    "coordinates": [
      -81.6167,
      28.3167
    ]
  },
  "type": "Feature",
  "properties": {
    "hierarchy": [
      "tgn:2328681",
      "tgn:1000001",
      "tgn:7012149",
      "tgn:1002756",
      "tgn:7007240",
      "tgn:7029392"
    ],
    "placetype": [
      "aat:300008791"
    ],
    "id": 2328681,
    "name:xx": "Fishers Island"
  }
}
