{
  "geometry": {
    "type": "Point",
    "coordinates": [
      -81.4333,
      36.1833
    ]
  },
  "type": "Feature",
  "properties": {
    "hierarchy": [
      "tgn:2512836",
      "tgn:1000001",
      "tgn:7012149",
      "tgn:2001553",
      "tgn:7007709",
      "tgn:7029392"
    ],
    "placetype": [
      "aat:300008706"
    ],
    "id": 2512836,
    "name:xx": "Mill Creek"
  }
}
