{
  "geometry": {
    "type": "Point",
    "coordinates": [
      -113.2833,
      41.9167
    ]
  },
  "type": "Feature",
  "properties": {
    "hierarchy": [
      "tgn:2616404",
      "tgn:1000001",
      "tgn:7012149",
      "tgn:7029392"
    ],
    "placetype": [
      "aat:300008706"
    ],
    "id": 2616404,
    "name:xx": "Rice Creek"
  }
}
