{
  "geometry": {
    "type": "Point",
    "coordinates": [
      -109.6333,
      40.75
    ]
  },
  "type": "Feature",
  "properties": {
    "hierarchy": [
      "tgn:2357357",
      "tgn:1000001",
      "tgn:7012149",
      "tgn:2002124",
      "tgn:7007827",
      "tgn:7029392"
    ],
    "placetype": [
      "aat:300008706"
    ],
    "id": 2357357,
    "name:xx": "Government Creek"
  }
}
