{
  "geometry": {
    "type": "Point",
    "coordinates": [
      -112.8667,
      35.3167
    ]
  },
  "type": "Feature",
  "properties": {
    "hierarchy": [
      "tgn:2007322",
      "tgn:1000001",
      "tgn:7006451",
      "tgn:7012149",
      "tgn:2000103",
      "tgn:7029392"
    ],
    "placetype": [
      "aat:300008347"
    ],
    "id": 2007322,
    "name:xx": "Seligman"
  }
}
