{
  "geometry": {
    "type": "Point",
    "coordinates": [
      -122.7833,
      38.9333
    ]
  },
  "type": "Feature",
  "properties": {
    "hierarchy": [
      "tgn:2655773",
      "tgn:1000001",
      "tgn:7012149",
      "tgn:7007157",
      "tgn:1002566",
      "tgn:7029392"
    ],
    "placetype": [
      "aat:300386845"
    ],
    "id": 2655773,
    "name:xx": "Shaul Valley"
  }
}
