{
  "geometry": {
    "type": "Point",
    "coordinates": [
      -68.6667,
      46.65
    ]
  },
  "type": "Feature",
  "properties": {
    "hierarchy": [
      "tgn:2499641",
      "tgn:2000919",
      "tgn:1000001",
      "tgn:7012149",
      "tgn:7007515",
      "tgn:7029392"
    ],
    "placetype": [
      "aat:300008699"
    ],
    "id": 2499641,
    "name:xx": "McConnell Brook"
  }
}
