{
  "geometry": {
    "type": "Point",
    "coordinates": [
      -111.9333,
      41.3667
    ]
  },
  "type": "Feature",
  "properties": {
    "hierarchy": [
      "tgn:2248150",
      "tgn:1000001",
      "tgn:7012149",
      "tgn:2002129",
      "tgn:7007827",
      "tgn:7029392"
    ],
    "placetype": [
      "aat:300008761"
    ],
    "id": 2248150,
    "name:xx": "Cold Canyon"
  }
}
