{
  "geometry": {
    "type": "Point",
    "coordinates": [
      -89.6375,
      21.05
    ]
  },
  "type": "Feature",
  "properties": {
    "hierarchy": [
      "tgn:7401995",
      "tgn:1000001",
      "tgn:7005600",
      "tgn:7005560",
      "tgn:7029392"
    ],
    "placetype": [
      "aat:300007783"
    ],
    "id": 7401995,
    "name:xx": "Estación Cordemex"
  }
}
