{
  "geometry": {
    "type": "Point",
    "coordinates": [
      21.3167,
      53.8833
    ]
  },
  "type": "Feature",
  "properties": {
    "hierarchy": [
      "tgn:1049267",
      "tgn:1000003",
      "tgn:7024118",
      "tgn:7006366",
      "tgn:7029392"
    ],
    "placetype": [
      "aat:300008347"
    ],
    "id": 1049267,
    "name:xx": "MraÌœgowo"
  }
}
