{
  "type": "FeatureCollection",
  "features": [
    {
      "geometry": {
        "type": "Point",
        "coordinates": [
          -91.8167,
          31.6167
        ]
      },
      "type": "Feature",
      "properties": {
        "hierarchy": [
          "tgn:2043110",
          "tgn:1000001",
          "tgn:2000866",
          "tgn:7012149",
          "tgn:7007256",
          "tgn:7029392"
        ],
        "placetype": [
          "aat:300008347"
        ],
        "id": 2043110,
        "name:xx": "Jonesville"
      }
    },
    {
      "geometry": {
        "type": "Point",
        "coordinates": [
          -92.5167,
          31.85
        ]
      },
      "type": "Feature",
      "properties": {
        "hierarchy": [
          "tgn:2043111",
          "tgn:1000001",
          "tgn:7012149",
          "tgn:2000917",
          "tgn:7007256",
          "tgn:7029392"
        ],
        "placetype": [
          "aat:300008347"
        ],
        "id": 2043111,
        "name:xx": "Jordan Hill"
      }
    },
    {
      "geometry": {
        "type": "Point",
        "coordinates": [
          -92.5833,
          31.9333
        ]
      },
      "type": "Feature",
      "properties": {
        "hierarchy": [
          "tgn:2043112",
          "tgn:1000001",
          "tgn:7012149",
          "tgn:2000917",
          "tgn:7007256",
          "tgn:7029392"
        ],
        "placetype": [
          "aat:300008347"
        ],
        "id": 2043112,
        "name:xx": "Joyce"
      }
    },
    {
      "geometry": {
        "type": "Point",
        "coordinates": [
          -93.5,
          30.8333
        ]
      },
      "type": "Feature",
      "properties": {
        "hierarchy": [
          "tgn:2043113",
          "tgn:1000001",
          "tgn:2000859",
          "tgn:7012149",
          "tgn:7007256",
          "tgn:7029392"
        ],
        "placetype": [
          "aat:300008347",
          "aat:300387210"
        ],
        "id": 2043113,
        "name:xx": "Junction"
      }
    },
    {
      "geometry": {
        "type": "Point",
        "coordinates": [
          -92.9,
          31.7
        ]
      },
      "type": "Feature",
      "properties": {
        "hierarchy": [
          "tgn:2043115",
          "tgn:1000001",
          "tgn:7012149",
          "tgn:2000875",
          "tgn:7007256",
          "tgn:7029392"
        ],
        "placetype": [
          "aat:300008347",
          "aat:300387210"
        ],
        "id": 2043115,
        "name:xx": "Kadesh"
      }
    },
    {
      "geometry": {
        "type": "Point",
        "coordinates": [
          -92.2833,
          29.9833
        ]
      },
      "type": "Feature",
      "properties": {
        "hierarchy": [
          "tgn:2043116",
          "tgn:1000001",
          "tgn:7012149",
          "tgn:2000910",
          "tgn:7007256",
          "tgn:7029392"
        ],
        "placetype": [
          "aat:300008347"
        ],
        "id": 2043116,
        "name:xx": "Kaplan"
      }
    },
    {
      "geometry": {
        "type": "Point",
        "coordinates": [
          -91.5,
          29.8167
        ]
      },
      "type": "Feature",
      "properties": {
        "hierarchy": [
          "tgn:2043117",
          "tgn:1000001",
          "tgn:7012149",
          "tgn:2000904",
          "tgn:7007256",
          "tgn:7029392"
        ],
        "placetype": [
          "aat:300008347",
          "aat:300387210"
        ],
        "id": 2043117,
        "name:xx": "Katy"
      }
    },
    {
      "geometry": {
        "type": "Point",
        "coordinates": [
          -93.9,
          32.1833
        ]
      },
      "type": "Feature",
      "properties": {
        "hierarchy": [
          "tgn:2043118",
          "tgn:1000001",
          "tgn:7020680",
          "tgn:7012149",
          "tgn:7007256",
          "tgn:7029392"
        ],
        "placetype": [
          "aat:300008347"
        ],
        "id": 2043118,
        "name:xx": "Keatchie"
      }
    }
  ]
}
