{
  "type": "FeatureCollection",
  "features": [
    {
      "geometry": {
        "type": "Point",
        "coordinates": [
          -84.1167,
          38.2167
        ]
      },
      "type": "Feature",
      "properties": {
        "hierarchy": [
          "tgn:2178520",
          "tgn:1000001",
          "tgn:1002192",
          "tgn:7012149",
          "tgn:7007255",
          "tgn:7029392"
        ],
        "placetype": [
          "aat:300008706"
        ],
        "id": 2178520,
        "name:xx": "Blacks Creek"
      }
    },
    {
      "geometry": {
        "type": "Point",
        "coordinates": [
          -70.9833,
          42.2667
        ]
      },
      "type": "Feature",
      "properties": {
        "hierarchy": [
          "tgn:2178521",
          "tgn:1000001",
          "tgn:1002724",
          "tgn:7012149",
          "tgn:7007517",
          "tgn:7029392"
        ],
        "placetype": [
          "aat:300132316"
        ],
        "id": 2178521,
        "name:xx": "Blacks Creek"
      }
    },
    {
      "geometry": {
        "type": "Point",
        "coordinates": [
          -80.4333,
          36.0833
        ]
      },
      "type": "Feature",
      "properties": {
        "hierarchy": [
          "tgn:2178522",
          "tgn:1000001",
          "tgn:7012149",
          "tgn:2001494",
          "tgn:7007709",
          "tgn:7029392"
        ],
        "placetype": [
          "aat:300008706"
        ],
        "id": 2178522,
        "name:xx": "Blacks Creek"
      }
    },
    {
      "geometry": {
        "type": "Point",
        "coordinates": [
          -124.1,
          43.6333
        ]
      },
      "type": "Feature",
      "properties": {
        "hierarchy": [
          "tgn:2178523",
          "tgn:1000001",
          "tgn:7012149",
          "tgn:2001706",
          "tgn:7007708",
          "tgn:7029392"
        ],
        "placetype": [
          "aat:300008706"
        ],
        "id": 2178523,
        "name:xx": "Blacks Creek"
      }
    },
    {
      "geometry": {
        "type": "Point",
        "coordinates": [
          -80.4167,
          39.8167
        ]
      },
      "type": "Feature",
      "properties": {
        "hierarchy": [
          "tgn:2178524",
          "tgn:1000001",
          "tgn:7012149",
          "tgn:2001724",
          "tgn:7007710",
          "tgn:7029392"
        ],
        "placetype": [
          "aat:300008706"
        ],
        "id": 2178524,
        "name:xx": "Blacks Creek"
      }
    },
    {
      "geometry": {
        "type": "Point",
        "coordinates": [
          -79.9167,
          41.1667
        ]
      },
      "type": "Feature",
      "properties": {
        "hierarchy": [
          "tgn:2178525",
          "tgn:1000001",
          "tgn:7012149",
          "tgn:7007710",
          "tgn:7029392"
        ],
        "placetype": [
          "aat:300008706"
        ],
        "id": 2178525,
        "name:xx": "Blacks Creek"
      }
    },
    {
      "geometry": {
        "type": "Point",
        "coordinates": [
          -82.5333,
          34.3
        ]
      },
      "type": "Feature",
      "properties": {
        "hierarchy": [
          "tgn:2178526",
          "tgn:2001725",
          "tgn:1000001",
          "tgn:7012149",
          "tgn:7007712",
          "tgn:7029392"
        ],
        "placetype": [
          "aat:300008706"
        ],
        "id": 2178526,
        "name:xx": "Blacks Creek"
      }
    },
    {
      "geometry": {
        "type": "Point",
        "coordinates": [
          -79.1667,
          36.9667
        ]
      },
      "type": "Feature",
      "properties": {
        "hierarchy": [
          "tgn:2178528",
          "tgn:1000001",
          "tgn:7012149",
          "tgn:2002180",
          "tgn:7007919",
          "tgn:7029392"
        ],
        "placetype": [
          "aat:300008706"
        ],
        "id": 2178528,
        "name:xx": "Blacks Creek"
      }
    },
    {
      "geometry": {
        "type": "Point",
        "coordinates": [
          -79.6667,
          37.7333
        ]
      },
      "type": "Feature",
      "properties": {
        "hierarchy": [
          "tgn:2178529",
          "tgn:1000001",
          "tgn:7012149",
          "tgn:2002186",
          "tgn:7007919",
          "tgn:7029392"
        ],
        "placetype": [
          "aat:300008706"
        ],
        "id": 2178529,
        "name:xx": "Blacks Creek"
      }
    }
  ]
}
