{
  "geometry": {
    "type": "Point",
    "coordinates": [
      -157.0167,
      20.9167
    ]
  },
  "type": "Feature",
  "properties": {
    "hierarchy": [
      "tgn:2430044",
      "tgn:1002648",
      "tgn:1000001",
      "tgn:1007799",
      "tgn:7012149",
      "tgn:7007249",
      "tgn:7029392"
    ],
    "placetype": [
      "aat:300008798"
    ],
    "id": 2430044,
    "name:xx": "Kaena"
  }
}
