{
  "geometry": {
    "type": "Point",
    "coordinates": [
      -88.3667,
      46.4833
    ]
  },
  "type": "Feature",
  "properties": {
    "hierarchy": [
      "tgn:2519580",
      "tgn:2000947",
      "tgn:1000001",
      "tgn:7012149",
      "tgn:7007520",
      "tgn:7029392"
    ],
    "placetype": [
      "aat:300008680"
    ],
    "id": 2519580,
    "name:xx": "Mogans Lake"
  }
}
