{
  "geometry": {
    "type": "Point",
    "coordinates": [
      -81.6833,
      33.0667
    ]
  },
  "type": "Feature",
  "properties": {
    "hierarchy": [
      "tgn:2495640",
      "tgn:1000001",
      "tgn:2000308",
      "tgn:7012149",
      "tgn:7007248",
      "tgn:7029392"
    ],
    "placetype": [
      "aat:300006191"
    ],
    "id": 2495640,
    "name:xx": "Mash Pond"
  }
}
