{
  "geometry": {
    "type": "Point",
    "coordinates": [
      141.5167,
      39.3333
    ]
  },
  "type": "Feature",
  "properties": {
    "hierarchy": [
      "tgn:1081418",
      "tgn:7016687",
      "tgn:1000004",
      "tgn:7000893",
      "tgn:1000120",
      "tgn:7029392"
    ],
    "placetype": [
      "aat:300008347"
    ],
    "id": 1081418,
    "name:xx": "Tōno"
  }
}
