{
  "geometry": {
    "type": "Point",
    "coordinates": [
      34.648819,
      30.00845
    ]
  },
  "type": "Feature",
  "properties": {
    "hierarchy": [
      "tgn:7535717",
      "tgn:7001242",
      "tgn:7016833",
      "tgn:7001335",
      "tgn:7029392"
    ],
    "placetype": [
      "aat:300379998"
    ],
    "name:en": "Ghuba, Wâdî el-",
    "id": 7535717
  }
}
