{
  "geometry": {
    "type": "Point",
    "coordinates": [
      -89.6167,
      43.7833
    ]
  },
  "type": "Feature",
  "properties": {
    "hierarchy": [
      "tgn:2500678",
      "tgn:2002305",
      "tgn:1000001",
      "tgn:7012149",
      "tgn:7007922",
      "tgn:7029392"
    ],
    "placetype": [
      "aat:300008680"
    ],
    "id": 2500678,
    "name:xx": "McDougall Lake"
  }
}
