{
  "geometry": {
    "type": "Point",
    "coordinates": [
      -90.95,
      29.6167
    ]
  },
  "type": "Feature",
  "properties": {
    "hierarchy": [
      "tgn:2657756",
      "tgn:1000001",
      "tgn:7012149",
      "tgn:2000908",
      "tgn:7007256",
      "tgn:7029392"
    ],
    "placetype": [
      "aat:300006075"
    ],
    "id": 2657756,
    "name:xx": "Shell Canal"
  }
}
