{
  "geometry": {
    "type": "Point",
    "coordinates": [
      2.8667,
      47.5333
    ]
  },
  "type": "Feature",
  "properties": {
    "hierarchy": [
      "tgn:1034659",
      "tgn:1000003",
      "tgn:7002875",
      "tgn:1000070",
      "tgn:7029392"
    ],
    "placetype": [
      "aat:300008347"
    ],
    "id": 1034659,
    "name:xx": "Neuvy-sur-Loire"
  }
}
