{
  "geometry": {
    "type": "Point",
    "coordinates": [
      -92.85,
      35.3667
    ]
  },
  "type": "Feature",
  "properties": {
    "hierarchy": [
      "tgn:2210612",
      "tgn:1000001",
      "tgn:7016172",
      "tgn:7012149",
      "tgn:7029392"
    ],
    "placetype": [
      "aat:300008798"
    ],
    "id": 2210612,
    "name:xx": "Busted Mountain"
  }
}
