{
  "geometry": {
    "type": "Point",
    "coordinates": [
      -104.8167,
      40.5167
    ]
  },
  "type": "Feature",
  "properties": {
    "hierarchy": [
      "tgn:2706856",
      "tgn:1000001",
      "tgn:7012149",
      "tgn:7007158",
      "tgn:2000253",
      "tgn:7029392"
    ],
    "placetype": [
      "aat:300006191"
    ],
    "id": 2706856,
    "name:xx": "Swanson Lake"
  }
}
