{
  "geometry": {
    "type": "Point",
    "coordinates": [
      -91.55,
      34.9833
    ]
  },
  "type": "Feature",
  "properties": {
    "hierarchy": [
      "tgn:2712242",
      "tgn:1000001",
      "tgn:7016172",
      "tgn:7012149",
      "tgn:2000163",
      "tgn:7029392"
    ],
    "placetype": [
      "aat:300006191"
    ],
    "id": 2712242,
    "name:xx": "Tates Reservoir"
  }
}
