{
  "geometry": {
    "type": "Point",
    "coordinates": [
      -81.2333,
      41.1167
    ]
  },
  "type": "Feature",
  "properties": {
    "hierarchy": [
      "tgn:2555761",
      "tgn:1000001",
      "tgn:7012149",
      "tgn:1002797",
      "tgn:7007706",
      "tgn:7029392"
    ],
    "placetype": [
      "aat:300006191"
    ],
    "id": 2555761,
    "name:xx": "Ohio Farmettes Lake"
  }
}
