{
  "geometry": {
    "type": "Point",
    "coordinates": [
      -73.5833,
      41.7167
    ]
  },
  "type": "Feature",
  "properties": {
    "hierarchy": [
      "tgn:2470678",
      "tgn:1000001",
      "tgn:1002347",
      "tgn:7012149",
      "tgn:7007568",
      "tgn:7029392"
    ],
    "placetype": [
      "aat:300008798"
    ],
    "id": 2470678,
    "name:xx": "Lossing Hill"
  }
}
