{
  "geometry": {
    "type": "Point",
    "coordinates": [
      11.3167,
      53.1833
    ]
  },
  "type": "Feature",
  "properties": {
    "hierarchy": [
      "tgn:1037343",
      "tgn:1000003",
      "tgn:7000094",
      "tgn:7000084",
      "tgn:7029392"
    ],
    "placetype": [
      "aat:300008347"
    ],
    "id": 1037343,
    "name:xx": "Neu Kaliss"
  }
}
