{
  "geometry": {
    "type": "Point",
    "coordinates": [
      11.3333,
      32.0167
    ]
  },
  "type": "Feature",
  "properties": {
    "hierarchy": [
      "tgn:1090711",
      "tgn:7001242",
      "tgn:7000612",
      "tgn:1000172",
      "tgn:7029392"
    ],
    "placetype": [
      "aat:300008347"
    ],
    "id": 1090711,
    "name:xx": "Tījī"
  }
}
