{
  "geometry": {
    "type": "Point",
    "coordinates": [
      -70.0167,
      41.55
    ]
  },
  "type": "Feature",
  "properties": {
    "hierarchy": [
      "tgn:2627333",
      "tgn:1002165",
      "tgn:1000001",
      "tgn:7012149",
      "tgn:7007517",
      "tgn:7029392"
    ],
    "placetype": [
      "aat:300132348"
    ],
    "id": 2627333,
    "name:xx": "Rodgers Shoal"
  }
}
