{
  "type": "FeatureCollection",
  "features": [
    {
      "geometry": {
        "type": "Point",
        "coordinates": [
          -69.589722,
          -17.986389
        ]
      },
      "type": "Feature",
      "properties": {
        "hierarchy": [
          "tgn:7317700",
          "tgn:7002464",
          "tgn:1000049",
          "tgn:1000002",
          "tgn:7029392"
        ],
        "placetype": [
          "aat:300008699"
        ],
        "id": 7317700,
        "name:xx": "Colpitas, Quebrada"
      }
    },
    {
      "geometry": {
        "type": "Point",
        "coordinates": [
          -69.366667,
          -17.966667
        ]
      },
      "type": "Feature",
      "properties": {
        "hierarchy": [
          "tgn:7317701",
          "tgn:7002464",
          "tgn:1000049",
          "tgn:1000002",
          "tgn:7029392"
        ],
        "placetype": [
          "aat:300008795"
        ],
        "id": 7317701,
        "name:xx": "Colpitas, Cerro"
      }
    },
    {
      "geometry": {
        "type": "Point",
        "coordinates": [
          -68.966667,
          -21.966667
        ]
      },
      "type": "Feature",
      "properties": {
        "hierarchy": [
          "tgn:7317702",
          "tgn:7016598",
          "tgn:1000049",
          "tgn:1000002",
          "tgn:7029392"
        ],
        "placetype": [
          "aat:300008697"
        ],
        "id": 7317702,
        "name:xx": "Colpita"
      }
    },
    {
      "geometry": {
        "type": "Point",
        "coordinates": [
          -69.233333,
          -18.05
        ]
      },
      "type": "Feature",
      "properties": {
        "hierarchy": [
          "tgn:7317703",
          "tgn:7002464",
          "tgn:1000049",
          "tgn:1000002",
          "tgn:7029392"
        ],
        "placetype": [
          "aat:300008347"
        ],
        "id": 7317703,
        "name:xx": "Colpita"
      }
    },
    {
      "geometry": {
        "type": "Point",
        "coordinates": [
          -69.45,
          -17.966667
        ]
      },
      "type": "Feature",
      "properties": {
        "hierarchy": [
          "tgn:7317704",
          "tgn:7002464",
          "tgn:1000049",
          "tgn:1000002",
          "tgn:7029392"
        ],
        "placetype": [
          "aat:300008347"
        ],
        "id": 7317704,
        "name:xx": "Colpita"
      }
    },
    {
      "geometry": {
        "type": "Point",
        "coordinates": [
          -72.9,
          -38.35
        ]
      },
      "type": "Feature",
      "properties": {
        "hierarchy": [
          "tgn:7317705",
          "tgn:1001692",
          "tgn:1000049",
          "tgn:1000002",
          "tgn:7029392"
        ],
        "placetype": [
          "aat:300008699"
        ],
        "id": 7317705,
        "name:xx": "Colpi, Río"
      }
    },
    {
      "geometry": {
        "type": "Point",
        "coordinates": [
          -70.433333,
          -23.766667
        ]
      },
      "type": "Feature",
      "properties": {
        "hierarchy": [
          "tgn:7317706",
          "tgn:7016598",
          "tgn:1000049",
          "tgn:1000002",
          "tgn:7029392"
        ],
        "placetype": [
          "aat:300266554",
          "aat:300008699"
        ],
        "id": 7317706,
        "name:xx": "Coloso, Quebrada"
      }
    },
    {
      "geometry": {
        "type": "Point",
        "coordinates": [
          -70.466667,
          -23.75
        ]
      },
      "type": "Feature",
      "properties": {
        "hierarchy": [
          "tgn:7317707",
          "tgn:7016598",
          "tgn:1000049",
          "tgn:1000002",
          "tgn:7029392"
        ],
        "placetype": [
          "aat:300386846"
        ],
        "id": 7317707,
        "name:xx": "Coloso, Punta"
      }
    },
    {
      "geometry": {
        "type": "Point",
        "coordinates": [
          -70.483333,
          -23.8
        ]
      },
      "type": "Feature",
      "properties": {
        "hierarchy": [
          "tgn:7317708",
          "tgn:7016598",
          "tgn:1000049",
          "tgn:1000002",
          "tgn:7029392"
        ],
        "placetype": [
          "aat:300008795"
        ],
        "id": 7317708,
        "name:xx": "Coloso, Cerro"
      }
    },
    {
      "geometry": {
        "type": "Point",
        "coordinates": [
          -70.466667,
          -23.75
        ]
      },
      "type": "Feature",
      "properties": {
        "hierarchy": [
          "tgn:7317709",
          "tgn:7016598",
          "tgn:1000049",
          "tgn:1000002",
          "tgn:7029392"
        ],
        "placetype": [
          "aat:300132317"
        ],
        "id": 7317709,
        "name:xx": "Coloso, Caleta"
      }
    }
  ]
}
