{
  "geometry": {
    "type": "Point",
    "coordinates": [
      -91.1667,
      43.6167
    ]
  },
  "type": "Feature",
  "properties": {
    "hierarchy": [
      "tgn:2554144",
      "tgn:1000001",
      "tgn:7012149",
      "tgn:2002358",
      "tgn:7007922",
      "tgn:7029392"
    ],
    "placetype": [
      "aat:300266640"
    ],
    "id": 2554144,
    "name:xx": "Oak Ridge"
  }
}
