{
  "geometry": {
    "type": "Point",
    "coordinates": [
      -122.8833,
      48.4333
    ]
  },
  "type": "Feature",
  "properties": {
    "hierarchy": [
      "tgn:2425990",
      "tgn:1000001",
      "tgn:7012149",
      "tgn:1002862",
      "tgn:7007920",
      "tgn:7029392"
    ],
    "placetype": [
      "aat:300132316"
    ],
    "id": 2425990,
    "name:xx": "Jones Bay"
  }
}
