{
  "geometry": {
    "type": "Point",
    "coordinates": [
      -85.2833,
      45.1667
    ]
  },
  "type": "Feature",
  "properties": {
    "hierarchy": [
      "tgn:2437720",
      "tgn:2000945",
      "tgn:1000001",
      "tgn:7012149",
      "tgn:7007520",
      "tgn:7029392"
    ],
    "placetype": [
      "aat:300008706"
    ],
    "id": 2437720,
    "name:xx": "King Creek"
  }
}
