{
  "geometry": {
    "type": "Point",
    "coordinates": [
      -121.9333,
      45.3333
    ]
  },
  "type": "Feature",
  "properties": {
    "hierarchy": [
      "tgn:2085820",
      "tgn:1000001",
      "tgn:1002270",
      "tgn:7012149",
      "tgn:7007708",
      "tgn:7029392"
    ],
    "placetype": [
      "aat:300008347"
    ],
    "id": 2085820,
    "name:xx": "Zigzag"
  }
}
