{
  "type": "FeatureCollection",
  "features": [
    {
      "geometry": {
        "type": "Point",
        "coordinates": [
          -91.3,
          46.3833
        ]
      },
      "type": "Feature",
      "properties": {
        "hierarchy": [
          "tgn:2298740",
          "tgn:2002308",
          "tgn:1000001",
          "tgn:7012149",
          "tgn:7007922",
          "tgn:7029392"
        ],
        "placetype": [
          "aat:300008680"
        ],
        "id": 2298740,
        "name:xx": "Dry Well Lake"
      }
    },
    {
      "geometry": {
        "type": "Point",
        "coordinates": [
          -107.7167,
          42.1833
        ]
      },
      "type": "Feature",
      "properties": {
        "hierarchy": [
          "tgn:2298741",
          "tgn:1000001",
          "tgn:7012149",
          "tgn:2002383",
          "tgn:7007923",
          "tgn:7029392"
        ],
        "placetype": [
          "aat:300006191"
        ],
        "id": 2298741,
        "name:xx": "Dry Well Reservoir"
      }
    },
    {
      "geometry": {
        "type": "Point",
        "coordinates": [
          -119.3833,
          43.9
        ]
      },
      "type": "Feature",
      "properties": {
        "hierarchy": [
          "tgn:2298742",
          "tgn:1000001",
          "tgn:7012149",
          "tgn:2001709",
          "tgn:7007708",
          "tgn:7029392"
        ],
        "placetype": [
          "aat:300008697"
        ],
        "id": 2298742,
        "name:xx": "Dry Well Spring"
      }
    },
    {
      "geometry": {
        "type": "Point",
        "coordinates": [
          -103.45,
          40.6833
        ]
      },
      "type": "Feature",
      "properties": {
        "hierarchy": [
          "tgn:2298743",
          "tgn:1000001",
          "tgn:7012149",
          "tgn:2000229",
          "tgn:7007158",
          "tgn:7029392"
        ],
        "placetype": [
          "aat:300008680"
        ],
        "id": 2298743,
        "name:xx": "Dry Wild Horse Lake"
      }
    },
    {
      "geometry": {
        "type": "Point",
        "coordinates": [
          -102.15,
          39.9333
        ]
      },
      "type": "Feature",
      "properties": {
        "hierarchy": [
          "tgn:2298744",
          "tgn:1000001",
          "tgn:7012149",
          "tgn:7007158",
          "tgn:2000254",
          "tgn:7029392"
        ],
        "placetype": [
          "aat:300008706"
        ],
        "id": 2298744,
        "name:xx": "Dry Willow Creek"
      }
    },
    {
      "geometry": {
        "type": "Point",
        "coordinates": [
          -105.85,
          43.7
        ]
      },
      "type": "Feature",
      "properties": {
        "hierarchy": [
          "tgn:2298745",
          "tgn:1000001",
          "tgn:2002367",
          "tgn:7012149",
          "tgn:7007923",
          "tgn:7029392"
        ],
        "placetype": [
          "aat:300008706"
        ],
        "id": 2298745,
        "name:xx": "Dry Willow Creek"
      }
    },
    {
      "geometry": {
        "type": "Point",
        "coordinates": [
          -112.9833,
          38.1
        ]
      },
      "type": "Feature",
      "properties": {
        "hierarchy": [
          "tgn:2298746",
          "tgn:1000001",
          "tgn:7012149",
          "tgn:2002111",
          "tgn:7007827",
          "tgn:7029392"
        ],
        "placetype": [
          "aat:300008798"
        ],
        "id": 2298746,
        "name:xx": "Dry Willow Peak"
      }
    },
    {
      "geometry": {
        "type": "Point",
        "coordinates": [
          -113,
          38.1167
        ]
      },
      "type": "Feature",
      "properties": {
        "hierarchy": [
          "tgn:2298747",
          "tgn:1000001",
          "tgn:7012149",
          "tgn:2002111",
          "tgn:7007827",
          "tgn:7029392"
        ],
        "placetype": [
          "aat:300008697"
        ],
        "id": 2298747,
        "name:xx": "Dry Willow Spring"
      }
    },
    {
      "geometry": {
        "type": "Point",
        "coordinates": [
          -110.6,
          46.9333
        ]
      },
      "type": "Feature",
      "properties": {
        "hierarchy": [
          "tgn:2298748",
          "tgn:1000001",
          "tgn:7012149",
          "tgn:2001282",
          "tgn:7007524",
          "tgn:7029392"
        ],
        "placetype": [
          "aat:300008706"
        ],
        "id": 2298748,
        "name:xx": "Dry Wolf Creek"
      }
    },
    {
      "geometry": {
        "type": "Point",
        "coordinates": [
          -110.1333,
          47.15
        ]
      },
      "type": "Feature",
      "properties": {
        "hierarchy": [
          "tgn:2298749",
          "tgn:1000001",
          "tgn:7012149",
          "tgn:7007524",
          "tgn:7029392"
        ],
        "placetype": [
          "aat:300008706"
        ],
        "id": 2298749,
        "name:xx": "Dry Wolf Creek"
      }
    }
  ]
}
