{
  "geometry": {
    "type": "Point",
    "coordinates": [
      9.05,
      54.116667
    ]
  },
  "type": "Feature",
  "properties": {
    "hierarchy": [
      "tgn:7189224",
      "tgn:1000003",
      "tgn:7003688",
      "tgn:7000084",
      "tgn:7029392"
    ],
    "placetype": [
      "aat:300008347"
    ],
    "id": 7189224,
    "name:xx": "Epenwöhrden"
  }
}
