{
  "geometry": {
    "type": "Point",
    "coordinates": [
      104.7833,
      28.75
    ]
  },
  "type": "Feature",
  "properties": {
    "hierarchy": [
      "tgn:1070045",
      "tgn:1000004",
      "tgn:7002087",
      "tgn:1000111",
      "tgn:7029392"
    ],
    "placetype": [
      "aat:300008347"
    ],
    "id": 1070045,
    "name:xx": "Lizhuang"
  }
}
