{
  "type": "FeatureCollection",
  "features": [
    {
      "geometry": {
        "type": "Point",
        "coordinates": [
          -3.683333,
          52.683333
        ]
      },
      "type": "Feature",
      "properties": {
        "hierarchy": [
          "tgn:7458195",
          "tgn:7002443",
          "tgn:1000003",
          "tgn:7008050",
          "tgn:7008591",
          "tgn:7029392"
        ],
        "placetype": [
          "aat:300008347"
        ],
        "name:en": "Mallwyd",
        "id": 7458195
      }
    },
    {
      "geometry": {
        "type": "Point",
        "coordinates": [
          -3.266667,
          58.95
        ]
      },
      "type": "Feature",
      "properties": {
        "hierarchy": [
          "tgn:7458196",
          "tgn:7002444",
          "tgn:1000003",
          "tgn:7009907",
          "tgn:7008591",
          "tgn:7029392"
        ],
        "placetype": [
          "aat:300386970"
        ],
        "name:en": "Mallow Bank",
        "id": 7458196
      }
    },
    {
      "geometry": {
        "type": "Point",
        "coordinates": [
          0.416667,
          51.283333
        ]
      },
      "type": "Feature",
      "properties": {
        "hierarchy": [
          "tgn:7458197",
          "tgn:7002445",
          "tgn:1000003",
          "tgn:7008153",
          "tgn:7008591",
          "tgn:7029392"
        ],
        "placetype": [
          "aat:300387173"
        ],
        "name:en": "Malling",
        "id": 7458197
      }
    },
    {
      "geometry": {
        "type": "Point",
        "coordinates": [
          -4.983333,
          56.95
        ]
      },
      "type": "Feature",
      "properties": {
        "hierarchy": [
          "tgn:7458198",
          "tgn:7002444",
          "tgn:1000003",
          "tgn:7008082",
          "tgn:7008591",
          "tgn:7029392"
        ],
        "placetype": [
          "aat:300008699"
        ],
        "name:en": "Mallie, River",
        "id": 7458198
      }
    },
    {
      "geometry": {
        "type": "Point",
        "coordinates": [
          -5.166667,
          56.95
        ]
      },
      "type": "Feature",
      "properties": {
        "hierarchy": [
          "tgn:7458199",
          "tgn:7002444",
          "tgn:1000003",
          "tgn:7008082",
          "tgn:7008591",
          "tgn:7029392"
        ],
        "placetype": [
          "aat:300008761"
        ],
        "name:en": "Mallie, Glen",
        "id": 7458199
      }
    }
  ]
}
