{
  "geometry": {
    "type": "Point",
    "coordinates": [
      31.656667,
      30.52531
    ]
  },
  "type": "Feature",
  "properties": {
    "hierarchy": [
      "tgn:7538292",
      "tgn:7001242",
      "tgn:7016833",
      "tgn:1001113",
      "tgn:7029392"
    ],
    "placetype": [
      "aat:300008347"
    ],
    "id": 7538292,
    "name:xx": "Shinbārat aţ Ţaffāfāt"
  }
}
