{
  "type": "FeatureCollection",
  "features": [
    {
      "geometry": {
        "type": "Point",
        "coordinates": [
          -83.7333,
          44.1833
        ]
      },
      "type": "Feature",
      "properties": {
        "hierarchy": [
          "tgn:2734241",
          "tgn:1000001",
          "tgn:7012149",
          "tgn:2000965",
          "tgn:7007520",
          "tgn:7029392"
        ],
        "placetype": [
          "aat:300008347"
        ],
        "id": 2734241,
        "name:xx": "Turtle"
      }
    },
    {
      "geometry": {
        "type": "Point",
        "coordinates": [
          -83.55,
          37.7667
        ]
      },
      "type": "Feature",
      "properties": {
        "hierarchy": [
          "tgn:2734242",
          "tgn:1000001",
          "tgn:7012149",
          "tgn:2000853",
          "tgn:7007255",
          "tgn:7029392"
        ],
        "placetype": [
          "aat:300386837"
        ],
        "id": 2734242,
        "name:xx": "Turtle Back Arch"
      }
    },
    {
      "geometry": {
        "type": "Point",
        "coordinates": [
          -82.1667,
          26.7833
        ]
      },
      "type": "Feature",
      "properties": {
        "hierarchy": [
          "tgn:2734243",
          "tgn:1000001",
          "tgn:1002258",
          "tgn:7012149",
          "tgn:7007240",
          "tgn:7029392"
        ],
        "placetype": [
          "aat:300132316"
        ],
        "id": 2734243,
        "name:xx": "Turtle Bay"
      }
    },
    {
      "geometry": {
        "type": "Point",
        "coordinates": [
          -82.5667,
          30.3167
        ]
      },
      "type": "Feature",
      "properties": {
        "hierarchy": [
          "tgn:2734244",
          "tgn:1000001",
          "tgn:2000262",
          "tgn:7012149",
          "tgn:7007240",
          "tgn:7029392"
        ],
        "placetype": [
          "aat:300008905"
        ],
        "id": 2734244,
        "name:xx": "Turtle Bay"
      }
    },
    {
      "geometry": {
        "type": "Point",
        "coordinates": [
          -81.5333,
          25.8667
        ]
      },
      "type": "Feature",
      "properties": {
        "hierarchy": [
          "tgn:2734245",
          "tgn:1000001",
          "tgn:1002289",
          "tgn:7012149",
          "tgn:7007240",
          "tgn:7029392"
        ],
        "placetype": [
          "aat:300132316"
        ],
        "id": 2734245,
        "name:xx": "Turtle Bay"
      }
    },
    {
      "geometry": {
        "type": "Point",
        "coordinates": [
          -90.1167,
          29.5333
        ]
      },
      "type": "Feature",
      "properties": {
        "hierarchy": [
          "tgn:2734246",
          "tgn:1000001",
          "tgn:7012149",
          "tgn:2000879",
          "tgn:7007256",
          "tgn:7029392"
        ],
        "placetype": [
          "aat:300132316"
        ],
        "id": 2734246,
        "name:xx": "Turtle Bay"
      }
    },
    {
      "geometry": {
        "type": "Point",
        "coordinates": [
          -93.6,
          47.2333
        ]
      },
      "type": "Feature",
      "properties": {
        "hierarchy": [
          "tgn:2734247",
          "tgn:1000001",
          "tgn:7012149",
          "tgn:2001029",
          "tgn:7007521",
          "tgn:7029392"
        ],
        "placetype": [
          "aat:300132316"
        ],
        "id": 2734247,
        "name:xx": "Turtle Bay"
      }
    },
    {
      "geometry": {
        "type": "Point",
        "coordinates": [
          -96.2667,
          28.6667
        ]
      },
      "type": "Feature",
      "properties": {
        "hierarchy": [
          "tgn:2734248",
          "tgn:1000001",
          "tgn:7012149",
          "tgn:1002646",
          "tgn:7007826",
          "tgn:7029392"
        ],
        "placetype": [
          "aat:300132316"
        ],
        "id": 2734248,
        "name:xx": "Turtle Bay"
      }
    },
    {
      "geometry": {
        "type": "Point",
        "coordinates": [
          -88.0167,
          43.8167
        ]
      },
      "type": "Feature",
      "properties": {
        "hierarchy": [
          "tgn:2734249",
          "tgn:1000001",
          "tgn:7012149",
          "tgn:2002355",
          "tgn:7007922",
          "tgn:7029392"
        ],
        "placetype": [
          "aat:300132316"
        ],
        "id": 2734249,
        "name:xx": "Turtle Bay"
      }
    }
  ]
}
