{
  "geometry": {
    "type": "Point",
    "coordinates": [
      -99.75,
      46.8667
    ]
  },
  "type": "Feature",
  "properties": {
    "hierarchy": [
      "tgn:2077530",
      "tgn:1000001",
      "tgn:2001578",
      "tgn:7012149",
      "tgn:7007705",
      "tgn:7029392"
    ],
    "placetype": [
      "aat:300008347"
    ],
    "id": 2077530,
    "name:xx": "Dawson"
  }
}
