{
  "geometry": {
    "type": "Point",
    "coordinates": [
      80.323333,
      13.235
    ]
  },
  "type": "Feature",
  "properties": {
    "hierarchy": [
      "tgn:7567541",
      "tgn:1000004",
      "tgn:7000198",
      "tgn:7001797",
      "tgn:7029392"
    ],
    "placetype": [
      "aat:300008347"
    ],
    "name:en": "Mukhdwāram",
    "id": 7567541
  }
}
