{
  "geometry": {
    "type": "Point",
    "coordinates": [
      -80.423,
      -0.598
    ]
  },
  "type": "Feature",
  "properties": {
    "hierarchy": [
      "tgn:1024085",
      "tgn:1001411",
      "tgn:7002560",
      "tgn:1000051",
      "tgn:1000002",
      "tgn:7029392"
    ],
    "placetype": [
      "aat:300008347"
    ],
    "id": 1024085,
    "name:xx": "Bahía de Caráquez"
  }
}
