{
  "geometry": {
    "type": "Point",
    "coordinates": [
      -104.0333,
      39.6833
    ]
  },
  "type": "Feature",
  "properties": {
    "hierarchy": [
      "tgn:2465977",
      "tgn:1000001",
      "tgn:7012149",
      "tgn:7007158",
      "tgn:7029392"
    ],
    "placetype": [
      "aat:300008761"
    ],
    "id": 2465977,
    "name:xx": "Lone Tree Gulch"
  }
}
