{
  "geometry": {
    "type": "Point",
    "coordinates": [
      -90.35,
      42.7667
    ]
  },
  "type": "Feature",
  "properties": {
    "hierarchy": [
      "tgn:2445847",
      "tgn:1000001",
      "tgn:7012149",
      "tgn:2002332",
      "tgn:7007922",
      "tgn:7029392"
    ],
    "placetype": [
      "aat:300008347"
    ],
    "id": 2445847,
    "name:xx": "Leslie"
  }
}
