{
  "type": "FeatureCollection",
  "features": [
    {
      "geometry": {
        "type": "Point",
        "coordinates": [
          2.599714,
          51.043718
        ]
      },
      "type": "Feature",
      "properties": {
        "hierarchy": [
          "tgn:7247992",
          "tgn:7003458",
          "tgn:1000003",
          "tgn:1000063",
          "tgn:7018236",
          "tgn:7029392"
        ],
        "placetype": [
          "aat:300008347"
        ],
        "id": 7247992,
        "name:xx": "De Moeren"
      }
    },
    {
      "geometry": {
        "type": "Point",
        "coordinates": [
          5.15,
          51.316667
        ]
      },
      "type": "Feature",
      "properties": {
        "hierarchy": [
          "tgn:7247993",
          "tgn:7003456",
          "tgn:1000003",
          "tgn:1000063",
          "tgn:7018236",
          "tgn:7029392"
        ],
        "placetype": [
          "aat:300008903"
        ],
        "id": 7247993,
        "name:xx": "De Moeren"
      }
    },
    {
      "geometry": {
        "type": "Point",
        "coordinates": [
          4.316667,
          51.083333
        ]
      },
      "type": "Feature",
      "properties": {
        "hierarchy": [
          "tgn:7247994",
          "tgn:7003456",
          "tgn:1000003",
          "tgn:1000063",
          "tgn:7018236",
          "tgn:7029392"
        ],
        "placetype": [
          "aat:300008903"
        ],
        "id": 7247994,
        "name:xx": "De Moeren"
      }
    },
    {
      "geometry": {
        "type": "Point",
        "coordinates": [
          3.566667,
          51.15
        ]
      },
      "type": "Feature",
      "properties": {
        "hierarchy": [
          "tgn:7247996",
          "tgn:7003457",
          "tgn:1000003",
          "tgn:1000063",
          "tgn:7018236",
          "tgn:7029392"
        ],
        "placetype": [
          "aat:300008863"
        ],
        "id": 7247996,
        "name:xx": "De Moer"
      }
    },
    {
      "geometry": {
        "type": "Point",
        "coordinates": [
          4.483333,
          51.116667
        ]
      },
      "type": "Feature",
      "properties": {
        "hierarchy": [
          "tgn:7247997",
          "tgn:7003456",
          "tgn:1000003",
          "tgn:1000063",
          "tgn:7018236",
          "tgn:7029392"
        ],
        "placetype": [
          "aat:300000206"
        ],
        "id": 7247997,
        "name:xx": "De Moeder"
      }
    },
    {
      "geometry": {
        "type": "Point",
        "coordinates": [
          3.604061,
          51.131946
        ]
      },
      "type": "Feature",
      "properties": {
        "hierarchy": [
          "tgn:7247999",
          "tgn:7003457",
          "tgn:1000003",
          "tgn:1000063",
          "tgn:7018236",
          "tgn:7029392"
        ],
        "placetype": [
          "aat:300008347"
        ],
        "id": 7247999,
        "name:xx": "Beke"
      }
    }
  ]
}
