{
  "geometry": {
    "type": "Point",
    "coordinates": [
      83.35,
      20.616667
    ]
  },
  "type": "Feature",
  "properties": {
    "hierarchy": [
      "tgn:7550445",
      "tgn:1000004",
      "tgn:7000198",
      "tgn:7016694",
      "tgn:7029392"
    ],
    "placetype": [
      "aat:300008347"
    ],
    "name:en": "Bhutyābāhāl",
    "id": 7550445
  }
}
