{
  "geometry": {
    "type": "Point",
    "coordinates": [
      -122.0333,
      43.5167
    ]
  },
  "type": "Feature",
  "properties": {
    "hierarchy": [
      "tgn:2480829",
      "tgn:1000001",
      "tgn:7012149",
      "tgn:2001714",
      "tgn:7007708",
      "tgn:7029392"
    ],
    "placetype": [
      "aat:300008798"
    ],
    "id": 2480829,
    "name:xx": "Lakeview Mountain"
  }
}
