{
  "geometry": {
    "type": "Point",
    "coordinates": [
      -89.65,
      43.4167
    ]
  },
  "type": "Feature",
  "properties": {
    "hierarchy": [
      "tgn:2645080",
      "tgn:1000001",
      "tgn:7012149",
      "tgn:2002352",
      "tgn:7007922",
      "tgn:7029392"
    ],
    "placetype": [
      "aat:300008798"
    ],
    "id": 2645080,
    "name:xx": "Sauk Point"
  }
}
