{
  "geometry": {
    "type": "Point",
    "coordinates": [
      -81.1333,
      39.4333
    ]
  },
  "type": "Feature",
  "properties": {
    "hierarchy": [
      "tgn:2657514",
      "tgn:1000001",
      "tgn:7012149",
      "tgn:2001622",
      "tgn:7007706",
      "tgn:7029392"
    ],
    "placetype": [
      "aat:300132348"
    ],
    "id": 2657514,
    "name:xx": "Sheets Ripple"
  }
}
