{
  "geometry": {
    "type": "Point",
    "coordinates": [
      -110.85,
      45.55
    ]
  },
  "type": "Feature",
  "properties": {
    "hierarchy": [
      "tgn:2155179",
      "tgn:1000001",
      "tgn:7012149",
      "tgn:2001275",
      "tgn:7007524",
      "tgn:7029392"
    ],
    "placetype": [
      "aat:300008680"
    ],
    "id": 2155179,
    "name:xx": "Bear Lakes"
  }
}
