{
  "geometry": {
    "type": "Point",
    "coordinates": [
      5.25,
      52.55
    ]
  },
  "type": "Feature",
  "properties": {
    "hierarchy": [
      "tgn:1117221",
      "tgn:1000003",
      "tgn:7016845",
      "tgn:7029392"
    ],
    "placetype": [
      "aat:300008680"
    ],
    "id": 1117221,
    "name:xx": "Markermeer"
  }
}
