{
  "geometry": {
    "type": "Point",
    "coordinates": [
      13.1667,
      65.8333
    ]
  },
  "type": "Feature",
  "properties": {
    "hierarchy": [
      "tgn:1048665",
      "tgn:7003644",
      "tgn:1000003",
      "tgn:1000088",
      "tgn:7029392"
    ],
    "placetype": [
      "aat:300008347"
    ],
    "id": 1048665,
    "name:xx": "Mosjøen"
  }
}
