{
  "geometry": {
    "type": "Point",
    "coordinates": [
      -79.6333,
      32.9167
    ]
  },
  "type": "Feature",
  "properties": {
    "hierarchy": [
      "tgn:2387913",
      "tgn:1000001",
      "tgn:2001734",
      "tgn:7012149",
      "tgn:7007712",
      "tgn:7029392"
    ],
    "placetype": [
      "aat:300132316"
    ],
    "id": 2387913,
    "name:xx": "Hickory Bay"
  }
}
