{
  "geometry": {
    "type": "Point",
    "coordinates": [
      -85.9167,
      35.7333
    ]
  },
  "type": "Feature",
  "properties": {
    "hierarchy": [
      "tgn:2365770",
      "tgn:1000001",
      "tgn:7012149",
      "tgn:2001925",
      "tgn:7007825",
      "tgn:7029392"
    ],
    "placetype": [
      "aat:300008697"
    ],
    "id": 2365770,
    "name:xx": "Gregory Spring"
  }
}
