{
  "geometry": {
    "type": "Point",
    "coordinates": [
      -113.4167,
      36.8667
    ]
  },
  "type": "Feature",
  "properties": {
    "hierarchy": [
      "tgn:2179257",
      "tgn:1000001",
      "tgn:7006451",
      "tgn:7012149",
      "tgn:2000098",
      "tgn:7029392"
    ],
    "placetype": [
      "aat:300008680"
    ],
    "id": 2179257,
    "name:xx": "Blake Pond"
  }
}
