{
  "geometry": {
    "type": "Point",
    "coordinates": [
      -121.7667,
      46.35
    ]
  },
  "type": "Feature",
  "properties": {
    "hierarchy": [
      "tgn:2216637",
      "tgn:1000001",
      "tgn:7012149",
      "tgn:1002897",
      "tgn:7007920",
      "tgn:7029392"
    ],
    "placetype": [
      "aat:300008706"
    ],
    "id": 2216637,
    "name:xx": "Camp Creek"
  }
}
