{
  "geometry": {
    "type": "Point",
    "coordinates": [
      -115.55,
      33.3333
    ]
  },
  "type": "Feature",
  "properties": {
    "hierarchy": [
      "tgn:1135879",
      "tgn:1000001",
      "tgn:7012149",
      "tgn:7007157",
      "tgn:7029392"
    ],
    "placetype": [
      "aat:300006075"
    ],
    "id": 1135879,
    "name:xx": "Coachella Canal"
  }
}
