{
  "type": "FeatureCollection",
  "features": [
    {
      "geometry": {
        "type": "Point",
        "coordinates": [
          0.316667,
          51.433333
        ]
      },
      "type": "Feature",
      "properties": {
        "hierarchy": [
          "tgn:7011620",
          "tgn:7002445",
          "tgn:1000003",
          "tgn:7008153",
          "tgn:7008591",
          "tgn:7029392"
        ],
        "placetype": [
          "aat:300008347",
          "aat:300000810",
          "aat:300008372",
          "aat:300387302"
        ],
        "name:en": "Swanscombe",
        "id": 7011620
      }
    },
    {
      "geometry": {
        "type": "Point",
        "coordinates": [
          15.1833,
          50.0333
        ]
      },
      "type": "Feature",
      "properties": {
        "hierarchy": [
          "tgn:7011624",
          "tgn:1003530",
          "tgn:1000003",
          "tgn:1001780",
          "tgn:7029392"
        ],
        "placetype": [
          "aat:300008347"
        ],
        "id": 7011624,
        "name:xx": "Kolín"
      }
    },
    {
      "geometry": {
        "type": "Point",
        "coordinates": [
          72,
          36.75
        ]
      },
      "type": "Feature",
      "properties": {
        "hierarchy": [
          "tgn:7011625",
          "tgn:7016612",
          "tgn:1000004",
          "tgn:7029392"
        ],
        "placetype": [
          "aat:300387064",
          "aat:300000774"
        ],
        "id": 7011625,
        "name:xx": "Badakhshan"
      }
    },
    {
      "geometry": {
        "type": "Point",
        "coordinates": [
          73,
          38
        ]
      },
      "type": "Feature",
      "properties": {
        "hierarchy": [
          "tgn:7011626",
          "tgn:1000004",
          "tgn:7014835",
          "tgn:7029392"
        ],
        "placetype": [
          "aat:300387064",
          "aat:300387107",
          "aat:300387110"
        ],
        "name:en": "Gorno-Badakhshan",
        "id": 7011626
      }
    },
    {
      "geometry": {
        "type": "Point",
        "coordinates": [
          69,
          40
        ]
      },
      "type": "Feature",
      "properties": {
        "hierarchy": [
          "tgn:7011628",
          "tgn:1000004",
          "tgn:7014835",
          "tgn:7029392"
        ],
        "placetype": [
          "aat:300387064",
          "aat:300236112"
        ],
        "id": 7011628,
        "name:xx": "Sughd"
      }
    },
    {
      "geometry": {
        "type": "Point",
        "coordinates": [
          69.75,
          37.75
        ]
      },
      "type": "Feature",
      "properties": {
        "hierarchy": [
          "tgn:7011629",
          "tgn:1000004",
          "tgn:7014835",
          "tgn:7029392"
        ],
        "placetype": [
          "aat:300387179"
        ],
        "id": 7011629,
        "name:xx": "Kŭlob"
      }
    }
  ]
}
