{
  "geometry": {
    "type": "Point",
    "coordinates": [
      25.301165,
      31.083003
    ]
  },
  "type": "Feature",
  "properties": {
    "hierarchy": [
      "tgn:7533554",
      "tgn:7001242",
      "tgn:7016833",
      "tgn:1001418",
      "tgn:7029392"
    ],
    "placetype": [
      "aat:300008777"
    ],
    "name:en": "拷빠mr캐', Al Q캐r캐t al",
    "id": 7533554
  }
}
