{
  "type": "FeatureCollection",
  "features": [
    {
      "geometry": {
        "type": "Point",
        "coordinates": [
          -107.9833,
          37.6167
        ]
      },
      "type": "Feature",
      "properties": {
        "hierarchy": [
          "tgn:2257701",
          "tgn:1000001",
          "tgn:7012149",
          "tgn:2000225",
          "tgn:7007158",
          "tgn:7029392"
        ],
        "placetype": [
          "aat:300008761"
        ],
        "id": 2257701,
        "name:xx": "Corral Draw"
      }
    },
    {
      "geometry": {
        "type": "Point",
        "coordinates": [
          -103.95,
          47.6
        ]
      },
      "type": "Feature",
      "properties": {
        "hierarchy": [
          "tgn:2257702",
          "tgn:1000001",
          "tgn:2001583",
          "tgn:7012149",
          "tgn:7007705",
          "tgn:7029392"
        ],
        "placetype": [
          "aat:300008761"
        ],
        "id": 2257702,
        "name:xx": "Corral Draw"
      }
    },
    {
      "geometry": {
        "type": "Point",
        "coordinates": [
          -121.9167,
          43.9667
        ]
      },
      "type": "Feature",
      "properties": {
        "hierarchy": [
          "tgn:2257703",
          "tgn:1000001",
          "tgn:7012149",
          "tgn:2001716",
          "tgn:7007708",
          "tgn:7029392"
        ],
        "placetype": [
          "aat:300008761"
        ],
        "id": 2257703,
        "name:xx": "Corral Draw"
      }
    },
    {
      "geometry": {
        "type": "Point",
        "coordinates": [
          -101.7833,
          34.9
        ]
      },
      "type": "Feature",
      "properties": {
        "hierarchy": [
          "tgn:2257704",
          "tgn:1000001",
          "tgn:7012149",
          "tgn:2002058",
          "tgn:7007826",
          "tgn:7029392"
        ],
        "placetype": [
          "aat:300008761"
        ],
        "id": 2257704,
        "name:xx": "Corral Draw"
      }
    },
    {
      "geometry": {
        "type": "Point",
        "coordinates": [
          -107.65,
          42.95
        ]
      },
      "type": "Feature",
      "properties": {
        "hierarchy": [
          "tgn:2257705",
          "tgn:1000001",
          "tgn:7012149",
          "tgn:2002371",
          "tgn:7007923",
          "tgn:7029392"
        ],
        "placetype": [
          "aat:300008761"
        ],
        "id": 2257705,
        "name:xx": "Corral Draw"
      }
    },
    {
      "geometry": {
        "type": "Point",
        "coordinates": [
          -112.1167,
          38.1333
        ]
      },
      "type": "Feature",
      "properties": {
        "hierarchy": [
          "tgn:2257706",
          "tgn:1000001",
          "tgn:2002109",
          "tgn:7012149",
          "tgn:7007827",
          "tgn:7029392"
        ],
        "placetype": [
          "aat:300006191"
        ],
        "id": 2257706,
        "name:xx": "Corral Flat Reservoir"
      }
    },
    {
      "geometry": {
        "type": "Point",
        "coordinates": [
          -108.7667,
          38.7
        ]
      },
      "type": "Feature",
      "properties": {
        "hierarchy": [
          "tgn:2257709",
          "tgn:1000001",
          "tgn:7012149",
          "tgn:2000230",
          "tgn:7007158",
          "tgn:7029392"
        ],
        "placetype": [
          "aat:300008706"
        ],
        "id": 2257709,
        "name:xx": "Corral Fork Little Creek"
      }
    }
  ]
}
