{
  "type": "FeatureCollection",
  "features": [
    {
      "geometry": {
        "type": "Point",
        "coordinates": [
          11.35,
          46.9
        ]
      },
      "type": "Feature",
      "properties": {
        "hierarchy": [
          "tgn:4006903",
          "tgn:1003440",
          "tgn:1000003",
          "tgn:7003124",
          "tgn:1000080",
          "tgn:7029392"
        ],
        "placetype": [
          "aat:300008347"
        ],
        "id": 4006903,
        "name:xx": "Mareta"
      }
    },
    {
      "geometry": {
        "type": "Point",
        "coordinates": [
          -2.9333,
          53.1
        ]
      },
      "type": "Feature",
      "properties": {
        "hierarchy": [
          "tgn:4006905",
          "tgn:7002443",
          "tgn:1000003",
          "tgn:7019007",
          "tgn:7008591",
          "tgn:7029392"
        ],
        "placetype": [
          "aat:300008347"
        ],
        "id": 4006905,
        "name:xx": "Marford"
      }
    },
    {
      "geometry": {
        "type": "Point",
        "coordinates": [
          -0.6667,
          45.05
        ]
      },
      "type": "Feature",
      "properties": {
        "hierarchy": [
          "tgn:4006908",
          "tgn:7002878",
          "tgn:1000003",
          "tgn:1000070",
          "tgn:7029392"
        ],
        "placetype": [
          "aat:300008347"
        ],
        "id": 4006908,
        "name:xx": "Margaux"
      }
    },
    {
      "geometry": {
        "type": "Point",
        "coordinates": [
          22.2667,
          45.8333
        ]
      },
      "type": "Feature",
      "properties": {
        "hierarchy": [
          "tgn:4006909",
          "tgn:1000003",
          "tgn:7002701",
          "tgn:1000091",
          "tgn:7029392"
        ],
        "placetype": [
          "aat:300008347"
        ],
        "id": 4006909,
        "name:xx": "Margina"
      }
    }
  ]
}
