{
  "geometry": {
    "type": "Point",
    "coordinates": [
      -111.95,
      43.2833
    ]
  },
  "type": "Feature",
  "properties": {
    "hierarchy": [
      "tgn:2645480",
      "tgn:1000001",
      "tgn:2000457",
      "tgn:7012149",
      "tgn:7007250",
      "tgn:7029392"
    ],
    "placetype": [
      "aat:300386845"
    ],
    "id": 2645480,
    "name:xx": "Saw Log Basin"
  }
}
