{
  "geometry": {
    "type": "Point",
    "coordinates": [
      21.75,
      38.15
    ]
  },
  "type": "Feature",
  "properties": {
    "hierarchy": [
      "tgn:7231048",
      "tgn:7002743",
      "tgn:7017076",
      "tgn:1000003",
      "tgn:1000074",
      "tgn:7029392"
    ],
    "placetype": [
      "aat:300008347"
    ],
    "id": 7231048,
    "name:xx": "Kallithéa"
  }
}
