{
  "geometry": {
    "type": "Point",
    "coordinates": [
      -93.7167,
      31.9167
    ]
  },
  "type": "Feature",
  "properties": {
    "hierarchy": [
      "tgn:2300293",
      "tgn:1000001",
      "tgn:7020680",
      "tgn:7012149",
      "tgn:7007256",
      "tgn:7029392"
    ],
    "placetype": [
      "aat:300008699"
    ],
    "id": 2300293,
    "name:xx": "Duke Bayou"
  }
}
