{
  "geometry": {
    "type": "Point",
    "coordinates": [
      -76.4667,
      37.3167
    ]
  },
  "type": "Feature",
  "properties": {
    "hierarchy": [
      "tgn:2192956",
      "tgn:1000001",
      "tgn:7012149",
      "tgn:1002411",
      "tgn:7007919",
      "tgn:7029392"
    ],
    "placetype": [
      "aat:300008347"
    ],
    "id": 2192956,
    "name:xx": "Brays Landing"
  }
}
