{
  "geometry": {
    "type": "Point",
    "coordinates": [
      15.3167,
      48.2333
    ]
  },
  "type": "Feature",
  "properties": {
    "hierarchy": [
      "tgn:1127056",
      "tgn:7003025",
      "tgn:1000003",
      "tgn:1000062",
      "tgn:7029392"
    ],
    "placetype": [
      "aat:300008707"
    ],
    "id": 1127056,
    "name:xx": "Melk"
  }
}
