{
  "geometry": {
    "type": "Point",
    "coordinates": [
      -85.85,
      38.45
    ]
  },
  "type": "Feature",
  "properties": {
    "hierarchy": [
      "tgn:1119684",
      "tgn:1000001",
      "tgn:1002273",
      "tgn:7012149",
      "tgn:7007252",
      "tgn:7029392"
    ],
    "placetype": [
      "aat:300006191"
    ],
    "id": 1119684,
    "name:xx": "Deam Lake"
  }
}
