{
  "geometry": {
    "type": "Point",
    "coordinates": [
      -84.9167,
      32.4667
    ]
  },
  "type": "Feature",
  "properties": {
    "hierarchy": [
      "tgn:2351311",
      "tgn:1000001",
      "tgn:7012149",
      "tgn:2000397",
      "tgn:7007248",
      "tgn:7029392"
    ],
    "placetype": [
      "aat:300008347"
    ],
    "id": 2351311,
    "name:xx": "Glen Arden"
  }
}
