{
  "geometry": {
    "type": "Point",
    "coordinates": [
      42.0333,
      41.9167
    ]
  },
  "type": "Feature",
  "properties": {
    "hierarchy": [
      "tgn:1056640",
      "tgn:1000004",
      "tgn:7012215",
      "tgn:7006653",
      "tgn:7029392"
    ],
    "placetype": [
      "aat:300008347"
    ],
    "id": 1056640,
    "name:xx": "Ozurgety"
  }
}
