{
  "type": "FeatureCollection",
  "features": [
    {
      "geometry": {
        "type": "Point",
        "coordinates": [
          -70.05,
          44.1833
        ]
      },
      "type": "Feature",
      "properties": {
        "hierarchy": [
          "tgn:2045790",
          "tgn:2000918",
          "tgn:1000001",
          "tgn:7012149",
          "tgn:7007515",
          "tgn:7029392"
        ],
        "placetype": [
          "aat:300008347"
        ],
        "id": 2045790,
        "name:xx": "Wales Corner"
      }
    },
    {
      "geometry": {
        "type": "Point",
        "coordinates": [
          -68.5833,
          47.1167
        ]
      },
      "type": "Feature",
      "properties": {
        "hierarchy": [
          "tgn:2045792",
          "tgn:2000919",
          "tgn:1000001",
          "tgn:7012149",
          "tgn:7007515",
          "tgn:7029392"
        ],
        "placetype": [
          "aat:300387016"
        ],
        "id": 2045792,
        "name:xx": "Wallagrass"
      }
    },
    {
      "geometry": {
        "type": "Point",
        "coordinates": [
          -70.2333,
          43.8167
        ]
      },
      "type": "Feature",
      "properties": {
        "hierarchy": [
          "tgn:2045794",
          "tgn:1000001",
          "tgn:2000920",
          "tgn:7012149",
          "tgn:7007515",
          "tgn:7029392"
        ],
        "placetype": [
          "aat:300008347"
        ],
        "id": 2045794,
        "name:xx": "Walnut Hill"
      }
    },
    {
      "geometry": {
        "type": "Point",
        "coordinates": [
          -69.55,
          43.95
        ]
      },
      "type": "Feature",
      "properties": {
        "hierarchy": [
          "tgn:2045795",
          "tgn:1000001",
          "tgn:2000925",
          "tgn:7012149",
          "tgn:7007515",
          "tgn:7029392"
        ],
        "placetype": [
          "aat:300008347"
        ],
        "id": 2045795,
        "name:xx": "Walpole"
      }
    },
    {
      "geometry": {
        "type": "Point",
        "coordinates": [
          -68.3333,
          44.7
        ]
      },
      "type": "Feature",
      "properties": {
        "hierarchy": [
          "tgn:2045796",
          "tgn:1000001",
          "tgn:2000922",
          "tgn:7012149",
          "tgn:7007515",
          "tgn:7029392"
        ],
        "placetype": [
          "aat:300008347"
        ],
        "id": 2045796,
        "name:xx": "Waltham"
      }
    },
    {
      "geometry": {
        "type": "Point",
        "coordinates": [
          -70.6,
          43.8167
        ]
      },
      "type": "Feature",
      "properties": {
        "hierarchy": [
          "tgn:2045797",
          "tgn:1000001",
          "tgn:2000920",
          "tgn:7012149",
          "tgn:7007515",
          "tgn:7029392"
        ],
        "placetype": [
          "aat:300008347"
        ],
        "id": 2045797,
        "name:xx": "Wards Cove"
      }
    }
  ]
}
