{
  "geometry": {
    "type": "Point",
    "coordinates": [
      -83.25,
      43.9667
    ]
  },
  "type": "Feature",
  "properties": {
    "hierarchy": [
      "tgn:2554051",
      "tgn:1000001",
      "tgn:7012149",
      "tgn:2000964",
      "tgn:7007520",
      "tgn:7029392"
    ],
    "placetype": [
      "aat:300008850"
    ],
    "id": 2554051,
    "name:xx": "Oak Point"
  }
}
