{
  "geometry": {
    "type": "Point",
    "coordinates": [
      -75.35,
      39.3333
    ]
  },
  "type": "Feature",
  "properties": {
    "hierarchy": [
      "tgn:2247761",
      "tgn:1002309",
      "tgn:1000001",
      "tgn:7012149",
      "tgn:7007565",
      "tgn:7029392"
    ],
    "placetype": [
      "aat:300008850"
    ],
    "id": 2247761,
    "name:xx": "Cohansey Point"
  }
}
