{
  "geometry": {
    "type": "Point",
    "coordinates": [
      31.252573,
      30.073029
    ]
  },
  "type": "Feature",
  "properties": {
    "hierarchy": [
      "tgn:7531916",
      "tgn:7001242",
      "tgn:7016833",
      "tgn:1001091",
      "tgn:7029392"
    ],
    "placetype": [
      "aat:300006676"
    ],
    "id": 7531916,
    "name:xx": "Mustashfá Shubrā al 'Āmm"
  }
}
