{
  "type": "FeatureCollection",
  "features": [
    {
      "geometry": {
        "type": "Point",
        "coordinates": [
          -81.1167,
          38.3667
        ]
      },
      "type": "Feature",
      "properties": {
        "hierarchy": [
          "tgn:2561350",
          "tgn:1000001",
          "tgn:2002259",
          "tgn:7012149",
          "tgn:7013961",
          "tgn:7029392"
        ],
        "placetype": [
          "aat:300008699"
        ],
        "id": 2561350,
        "name:xx": "Osborne Fork"
      }
    },
    {
      "geometry": {
        "type": "Point",
        "coordinates": [
          -121.0333,
          39.1833
        ]
      },
      "type": "Feature",
      "properties": {
        "hierarchy": [
          "tgn:2561351",
          "tgn:1000001",
          "tgn:7012149",
          "tgn:7007157",
          "tgn:1002710",
          "tgn:7029392"
        ],
        "placetype": [
          "aat:300008798"
        ],
        "id": 2561351,
        "name:xx": "Osborne Hill"
      }
    },
    {
      "geometry": {
        "type": "Point",
        "coordinates": [
          -73.25,
          41.15
        ]
      },
      "type": "Feature",
      "properties": {
        "hierarchy": [
          "tgn:2561352",
          "tgn:1002366",
          "tgn:1000001",
          "tgn:7012149",
          "tgn:7007159",
          "tgn:7029392"
        ],
        "placetype": [
          "aat:300008798"
        ],
        "id": 2561352,
        "name:xx": "Osborne Hill"
      }
    },
    {
      "geometry": {
        "type": "Point",
        "coordinates": [
          -73.9,
          41.5333
        ]
      },
      "type": "Feature",
      "properties": {
        "hierarchy": [
          "tgn:2561353",
          "tgn:1000001",
          "tgn:1002347",
          "tgn:7012149",
          "tgn:7007568",
          "tgn:7029392"
        ],
        "placetype": [
          "aat:300008798"
        ],
        "id": 2561353,
        "name:xx": "Osborne Hill"
      }
    },
    {
      "geometry": {
        "type": "Point",
        "coordinates": [
          -75.0167,
          43.0833
        ]
      },
      "type": "Feature",
      "properties": {
        "hierarchy": [
          "tgn:2561354",
          "tgn:1000001",
          "tgn:7012149",
          "tgn:1002472",
          "tgn:7007568",
          "tgn:7029392"
        ],
        "placetype": [
          "aat:300008798"
        ],
        "id": 2561354,
        "name:xx": "Osborne Hill"
      }
    },
    {
      "geometry": {
        "type": "Point",
        "coordinates": [
          -75.6,
          39.9167
        ]
      },
      "type": "Feature",
      "properties": {
        "hierarchy": [
          "tgn:2561355",
          "tgn:1000001",
          "tgn:1002266",
          "tgn:7012149",
          "tgn:7007710",
          "tgn:7029392"
        ],
        "placetype": [
          "aat:300008798"
        ],
        "id": 2561355,
        "name:xx": "Osborne Hill"
      }
    },
    {
      "geometry": {
        "type": "Point",
        "coordinates": [
          -92.7167,
          36.05
        ]
      },
      "type": "Feature",
      "properties": {
        "hierarchy": [
          "tgn:2561356",
          "tgn:1000001",
          "tgn:7016172",
          "tgn:7012149",
          "tgn:2000169",
          "tgn:7029392"
        ],
        "placetype": [
          "aat:300008761"
        ],
        "id": 2561356,
        "name:xx": "Osborne Hollow"
      }
    },
    {
      "geometry": {
        "type": "Point",
        "coordinates": [
          -84.55,
          37.2833
        ]
      },
      "type": "Feature",
      "properties": {
        "hierarchy": [
          "tgn:2561357",
          "tgn:1000001",
          "tgn:7012149",
          "tgn:2000839",
          "tgn:7007255",
          "tgn:7029392"
        ],
        "placetype": [
          "aat:300008761"
        ],
        "id": 2561357,
        "name:xx": "Osborne Hollow"
      }
    },
    {
      "geometry": {
        "type": "Point",
        "coordinates": [
          -82.3333,
          36.8333
        ]
      },
      "type": "Feature",
      "properties": {
        "hierarchy": [
          "tgn:2561358",
          "tgn:1000001",
          "tgn:7012149",
          "tgn:2002188",
          "tgn:7007919",
          "tgn:7029392"
        ],
        "placetype": [
          "aat:300008761"
        ],
        "id": 2561358,
        "name:xx": "Osborne Hollow"
      }
    },
    {
      "geometry": {
        "type": "Point",
        "coordinates": [
          -81.85,
          37.2
        ]
      },
      "type": "Feature",
      "properties": {
        "hierarchy": [
          "tgn:2561359",
          "tgn:1000001",
          "tgn:2002148",
          "tgn:7012149",
          "tgn:7007919",
          "tgn:7029392"
        ],
        "placetype": [
          "aat:300008761"
        ],
        "id": 2561359,
        "name:xx": "Osborne Hollow"
      }
    }
  ]
}
