{
  "type": "FeatureCollection",
  "features": [
    {
      "geometry": {
        "type": "Point",
        "coordinates": [
          5.033333,
          49.9
        ]
      },
      "type": "Feature",
      "properties": {
        "hierarchy": [
          "tgn:7242600",
          "tgn:7003466",
          "tgn:1000003",
          "tgn:1000063",
          "tgn:4012014",
          "tgn:7029392"
        ],
        "placetype": [
          "aat:300008347"
        ],
        "id": 7242600,
        "name:xx": "Le Rot"
      }
    },
    {
      "geometry": {
        "type": "Point",
        "coordinates": [
          4.201997,
          50.659524
        ]
      },
      "type": "Feature",
      "properties": {
        "hierarchy": [
          "tgn:7242601",
          "tgn:7007877",
          "tgn:1000003",
          "tgn:1000063",
          "tgn:4012014",
          "tgn:7029392"
        ],
        "placetype": [
          "aat:300008347"
        ],
        "id": 7242601,
        "name:xx": "Le Rossignol"
      }
    },
    {
      "geometry": {
        "type": "Point",
        "coordinates": [
          4.016231,
          50.685586
        ]
      },
      "type": "Feature",
      "properties": {
        "hierarchy": [
          "tgn:7242602",
          "tgn:7007877",
          "tgn:1000003",
          "tgn:1000063",
          "tgn:4012014",
          "tgn:7029392"
        ],
        "placetype": [
          "aat:300008347"
        ],
        "id": 7242602,
        "name:xx": "Le Roo"
      }
    },
    {
      "geometry": {
        "type": "Point",
        "coordinates": [
          5.183333,
          50.133333
        ]
      },
      "type": "Feature",
      "properties": {
        "hierarchy": [
          "tgn:7242603",
          "tgn:7003466",
          "tgn:1000003",
          "tgn:1000063",
          "tgn:4012014",
          "tgn:7029392"
        ],
        "placetype": [
          "aat:300008347"
        ],
        "id": 7242603,
        "name:xx": "Le Rond Tienne"
      }
    },
    {
      "geometry": {
        "type": "Point",
        "coordinates": [
          5.283333,
          49.8
        ]
      },
      "type": "Feature",
      "properties": {
        "hierarchy": [
          "tgn:7242604",
          "tgn:7003465",
          "tgn:1000003",
          "tgn:1000063",
          "tgn:4012014",
          "tgn:7029392"
        ],
        "placetype": [
          "aat:300008347"
        ],
        "id": 7242604,
        "name:xx": "L'Ermite"
      }
    },
    {
      "geometry": {
        "type": "Point",
        "coordinates": [
          4.283333,
          50.666667
        ]
      },
      "type": "Feature",
      "properties": {
        "hierarchy": [
          "tgn:7242605",
          "tgn:7007877",
          "tgn:1000003",
          "tgn:1000063",
          "tgn:4012014",
          "tgn:7029392"
        ],
        "placetype": [
          "aat:300008347"
        ],
        "id": 7242605,
        "name:xx": "L'Ermitage"
      }
    },
    {
      "geometry": {
        "type": "Point",
        "coordinates": [
          4.3,
          50.166667
        ]
      },
      "type": "Feature",
      "properties": {
        "hierarchy": [
          "tgn:7242606",
          "tgn:7007877",
          "tgn:1000003",
          "tgn:1000063",
          "tgn:4012014",
          "tgn:7029392"
        ],
        "placetype": [
          "aat:300008347"
        ],
        "id": 7242606,
        "name:xx": "L'Ermitage"
      }
    },
    {
      "geometry": {
        "type": "Point",
        "coordinates": [
          4.55,
          50
        ]
      },
      "type": "Feature",
      "properties": {
        "hierarchy": [
          "tgn:7242608",
          "tgn:7003466",
          "tgn:1000003",
          "tgn:1000063",
          "tgn:4012014",
          "tgn:7029392"
        ],
        "placetype": [
          "aat:300008347"
        ],
        "id": 7242608,
        "name:xx": "L'Ermitage"
      }
    },
    {
      "geometry": {
        "type": "Point",
        "coordinates": [
          5.716667,
          49.8
        ]
      },
      "type": "Feature",
      "properties": {
        "hierarchy": [
          "tgn:7242609",
          "tgn:7003465",
          "tgn:1000003",
          "tgn:1000063",
          "tgn:4012014",
          "tgn:7029392"
        ],
        "placetype": [
          "aat:300008863"
        ],
        "id": 7242609,
        "name:xx": "L'Ermitage"
      }
    }
  ]
}
