{
  "type": "FeatureCollection",
  "features": [
    {
      "geometry": {
        "type": "Point",
        "coordinates": [
          138.9167,
          36.6833
        ]
      },
      "type": "Feature",
      "properties": {
        "hierarchy": [
          "tgn:1081010",
          "tgn:1000980",
          "tgn:1000004",
          "tgn:7000894",
          "tgn:1000120",
          "tgn:7029392"
        ],
        "placetype": [
          "aat:300008347"
        ],
        "id": 1081010,
        "name:xx": "Niiharu"
      }
    },
    {
      "geometry": {
        "type": "Point",
        "coordinates": [
          133.4667,
          34.9833
        ]
      },
      "type": "Feature",
      "properties": {
        "hierarchy": [
          "tgn:1081011",
          "tgn:1001015",
          "tgn:7000897",
          "tgn:1000004",
          "tgn:1000120",
          "tgn:7029392"
        ],
        "placetype": [
          "aat:300008347"
        ],
        "id": 1081011,
        "name:xx": "Niimi"
      }
    },
    {
      "geometry": {
        "type": "Point",
        "coordinates": [
          139.15,
          37.8
        ]
      },
      "type": "Feature",
      "properties": {
        "hierarchy": [
          "tgn:1081012",
          "tgn:7000895",
          "tgn:1000004",
          "tgn:1001014",
          "tgn:1000120",
          "tgn:7029392"
        ],
        "placetype": [
          "aat:300008347"
        ],
        "id": 1081012,
        "name:xx": "Niitsu"
      }
    },
    {
      "geometry": {
        "type": "Point",
        "coordinates": [
          139.55,
          35.7833
        ]
      },
      "type": "Feature",
      "properties": {
        "hierarchy": [
          "tgn:1081013",
          "tgn:1000004",
          "tgn:7000894",
          "tgn:7016797",
          "tgn:1000120",
          "tgn:7029392"
        ],
        "placetype": [
          "aat:300008347"
        ],
        "id": 1081013,
        "name:xx": "Niiza"
      }
    },
    {
      "geometry": {
        "type": "Point",
        "coordinates": [
          132.4,
          35.15
        ]
      },
      "type": "Feature",
      "properties": {
        "hierarchy": [
          "tgn:1081015",
          "tgn:7016808",
          "tgn:7000897",
          "tgn:1000004",
          "tgn:1000120",
          "tgn:7029392"
        ],
        "placetype": [
          "aat:300008347"
        ],
        "id": 1081015,
        "name:xx": "Nima"
      }
    },
    {
      "geometry": {
        "type": "Point",
        "coordinates": [
          141.3,
          40.2667
        ]
      },
      "type": "Feature",
      "properties": {
        "hierarchy": [
          "tgn:1081016",
          "tgn:7016687",
          "tgn:1000004",
          "tgn:7000893",
          "tgn:1000120",
          "tgn:7029392"
        ],
        "placetype": [
          "aat:300008347"
        ],
        "id": 1081016,
        "name:xx": "Ninohe"
      }
    },
    {
      "geometry": {
        "type": "Point",
        "coordinates": [
          139.2667,
          35.3
        ]
      },
      "type": "Feature",
      "properties": {
        "hierarchy": [
          "tgn:1081017",
          "tgn:7016696",
          "tgn:1000004",
          "tgn:7000894",
          "tgn:1000120",
          "tgn:7029392"
        ],
        "placetype": [
          "aat:300008347"
        ],
        "id": 1081017,
        "name:xx": "Ninomiya"
      }
    },
    {
      "geometry": {
        "type": "Point",
        "coordinates": [
          133.6333,
          34.2
        ]
      },
      "type": "Feature",
      "properties": {
        "hierarchy": [
          "tgn:1081018",
          "tgn:1000992",
          "tgn:1000004",
          "tgn:7000903",
          "tgn:1000120",
          "tgn:7029392"
        ],
        "placetype": [
          "aat:300008347"
        ],
        "id": 1081018,
        "name:xx": "Nio"
      }
    },
    {
      "geometry": {
        "type": "Point",
        "coordinates": [
          138.45,
          35.75
        ]
      },
      "type": "Feature",
      "properties": {
        "hierarchy": [
          "tgn:1081019",
          "tgn:7000895",
          "tgn:1000004",
          "tgn:7016854",
          "tgn:1000120",
          "tgn:7029392"
        ],
        "placetype": [
          "aat:300008347"
        ],
        "id": 1081019,
        "name:xx": "Nirasaki"
      }
    }
  ]
}
