{
  "geometry": {
    "type": "Point",
    "coordinates": [
      17.166,
      49.75
    ]
  },
  "type": "Feature",
  "properties": {
    "hierarchy": [
      "tgn:7593917",
      "tgn:1000003",
      "tgn:1001780",
      "tgn:7029392"
    ],
    "placetype": [
      "aat:300387064",
      "aat:300236112"
    ],
    "id": 7593917,
    "name:xx": "Olomoucký Kraj"
  }
}
