{
  "type": "FeatureCollection",
  "features": [
    {
      "geometry": {
        "type": "Point",
        "coordinates": [
          8.05,
          49.983333
        ]
      },
      "type": "Feature",
      "properties": {
        "hierarchy": [
          "tgn:7124850",
          "tgn:1000003",
          "tgn:7003682",
          "tgn:7000084",
          "tgn:7029392"
        ],
        "placetype": [
          "aat:300008347"
        ],
        "id": 7124850,
        "name:xx": "Neumühle"
      }
    },
    {
      "geometry": {
        "type": "Point",
        "coordinates": [
          10.983333,
          49.433333
        ]
      },
      "type": "Feature",
      "properties": {
        "hierarchy": [
          "tgn:7124852",
          "tgn:7003669",
          "tgn:1000003",
          "tgn:7000084",
          "tgn:7029392"
        ],
        "placetype": [
          "aat:300008347"
        ],
        "id": 7124852,
        "name:xx": "Neumühle"
      }
    },
    {
      "geometry": {
        "type": "Point",
        "coordinates": [
          7.566667,
          49.333333
        ]
      },
      "type": "Feature",
      "properties": {
        "hierarchy": [
          "tgn:7124853",
          "tgn:1000003",
          "tgn:7003682",
          "tgn:7000084",
          "tgn:7029392"
        ],
        "placetype": [
          "aat:300008347"
        ],
        "id": 7124853,
        "name:xx": "Neumühle"
      }
    },
    {
      "geometry": {
        "type": "Point",
        "coordinates": [
          12.766667,
          48.266667
        ]
      },
      "type": "Feature",
      "properties": {
        "hierarchy": [
          "tgn:7124854",
          "tgn:7003669",
          "tgn:1000003",
          "tgn:7000084",
          "tgn:7029392"
        ],
        "placetype": [
          "aat:300008347"
        ],
        "id": 7124854,
        "name:xx": "Neumühle"
      }
    },
    {
      "geometry": {
        "type": "Point",
        "coordinates": [
          11.8,
          47.8
        ]
      },
      "type": "Feature",
      "properties": {
        "hierarchy": [
          "tgn:7124855",
          "tgn:7003669",
          "tgn:1000003",
          "tgn:7000084",
          "tgn:7029392"
        ],
        "placetype": [
          "aat:300008347"
        ],
        "id": 7124855,
        "name:xx": "Neumühle"
      }
    },
    {
      "geometry": {
        "type": "Point",
        "coordinates": [
          10.616667,
          54.15
        ]
      },
      "type": "Feature",
      "properties": {
        "hierarchy": [
          "tgn:7124856",
          "tgn:1000003",
          "tgn:7003688",
          "tgn:7000084",
          "tgn:7029392"
        ],
        "placetype": [
          "aat:300000206"
        ],
        "id": 7124856,
        "name:xx": "Neumühle"
      }
    },
    {
      "geometry": {
        "type": "Point",
        "coordinates": [
          7.883333,
          49.533333
        ]
      },
      "type": "Feature",
      "properties": {
        "hierarchy": [
          "tgn:7124857",
          "tgn:1000003",
          "tgn:7003682",
          "tgn:7000084",
          "tgn:7029392"
        ],
        "placetype": [
          "aat:300000206"
        ],
        "id": 7124857,
        "name:xx": "Neumühle"
      }
    },
    {
      "geometry": {
        "type": "Point",
        "coordinates": [
          11.166667,
          49.866667
        ]
      },
      "type": "Feature",
      "properties": {
        "hierarchy": [
          "tgn:7124858",
          "tgn:7003669",
          "tgn:1000003",
          "tgn:7000084",
          "tgn:7029392"
        ],
        "placetype": [
          "aat:300008699"
        ],
        "id": 7124858,
        "name:xx": "Neumühlbach"
      }
    },
    {
      "geometry": {
        "type": "Point",
        "coordinates": [
          13.433333,
          52.683333
        ]
      },
      "type": "Feature",
      "properties": {
        "hierarchy": [
          "tgn:7124859",
          "tgn:7000096",
          "tgn:1000003",
          "tgn:7000084",
          "tgn:7029392"
        ],
        "placetype": [
          "aat:300004792"
        ],
        "id": 7124859,
        "name:xx": "Försterei Neumühl"
      }
    }
  ]
}
