{
  "type": "FeatureCollection",
  "features": [
    {
      "geometry": {
        "type": "Point",
        "coordinates": [
          -82.9667,
          38.3833
        ]
      },
      "type": "Feature",
      "properties": {
        "hierarchy": [
          "tgn:2321930",
          "tgn:1000001",
          "tgn:7012149",
          "tgn:7007255",
          "tgn:7029392"
        ],
        "placetype": [
          "aat:300008699"
        ],
        "id": 2321930,
        "name:xx": "Fall Branch"
      }
    },
    {
      "geometry": {
        "type": "Point",
        "coordinates": [
          -83.9833,
          35.1
        ]
      },
      "type": "Feature",
      "properties": {
        "hierarchy": [
          "tgn:2321931",
          "tgn:1000001",
          "tgn:2001481",
          "tgn:7012149",
          "tgn:7007709",
          "tgn:7029392"
        ],
        "placetype": [
          "aat:300008699"
        ],
        "id": 2321931,
        "name:xx": "Fall Branch"
      }
    },
    {
      "geometry": {
        "type": "Point",
        "coordinates": [
          -82.2667,
          35.6333
        ]
      },
      "type": "Feature",
      "properties": {
        "hierarchy": [
          "tgn:2321933",
          "tgn:1000001",
          "tgn:7012149",
          "tgn:2001514",
          "tgn:7007709",
          "tgn:7029392"
        ],
        "placetype": [
          "aat:300008699"
        ],
        "id": 2321933,
        "name:xx": "Fall Branch"
      }
    },
    {
      "geometry": {
        "type": "Point",
        "coordinates": [
          -82.8167,
          35.7167
        ]
      },
      "type": "Feature",
      "properties": {
        "hierarchy": [
          "tgn:2321934",
          "tgn:1000001",
          "tgn:7012149",
          "tgn:2001516",
          "tgn:7007709",
          "tgn:7029392"
        ],
        "placetype": [
          "aat:300008699"
        ],
        "id": 2321934,
        "name:xx": "Fall Branch"
      }
    },
    {
      "geometry": {
        "type": "Point",
        "coordinates": [
          -82.95,
          35.75
        ]
      },
      "type": "Feature",
      "properties": {
        "hierarchy": [
          "tgn:2321935",
          "tgn:1000001",
          "tgn:7012149",
          "tgn:2001503",
          "tgn:7007709",
          "tgn:7029392"
        ],
        "placetype": [
          "aat:300008699"
        ],
        "id": 2321935,
        "name:xx": "Fall Branch"
      }
    },
    {
      "geometry": {
        "type": "Point",
        "coordinates": [
          -81.9667,
          36.0333
        ]
      },
      "type": "Feature",
      "properties": {
        "hierarchy": [
          "tgn:2321936",
          "tgn:2001468",
          "tgn:1000001",
          "tgn:7012149",
          "tgn:7007709",
          "tgn:7029392"
        ],
        "placetype": [
          "aat:300008699"
        ],
        "id": 2321936,
        "name:xx": "Fall Branch"
      }
    },
    {
      "geometry": {
        "type": "Point",
        "coordinates": [
          -82.3667,
          35.65
        ]
      },
      "type": "Feature",
      "properties": {
        "hierarchy": [
          "tgn:2321939",
          "tgn:1000001",
          "tgn:2001473",
          "tgn:7012149",
          "tgn:7007709",
          "tgn:7029392"
        ],
        "placetype": [
          "aat:300008699"
        ],
        "id": 2321939,
        "name:xx": "Fall Branch"
      }
    }
  ]
}
