{
  "geometry": {
    "type": "Point",
    "coordinates": [
      -85.8833,
      30.85
    ]
  },
  "type": "Feature",
  "properties": {
    "hierarchy": [
      "tgn:2182595",
      "tgn:1000001",
      "tgn:2000272",
      "tgn:7012149",
      "tgn:7007240",
      "tgn:7029392"
    ],
    "placetype": [
      "aat:300008697"
    ],
    "id": 2182595,
    "name:xx": "Blue Spring"
  }
}
