{
  "geometry": {
    "type": "Point",
    "coordinates": [
      -123.0833,
      44.8833
    ]
  },
  "type": "Feature",
  "properties": {
    "hierarchy": [
      "tgn:2267667",
      "tgn:1000001",
      "tgn:7012149",
      "tgn:1002636",
      "tgn:7007708",
      "tgn:7029392"
    ],
    "placetype": [
      "aat:300266640"
    ],
    "id": 2267667,
    "name:xx": "Croisan Ridge"
  }
}
