{
  "geometry": {
    "type": "Point",
    "coordinates": [
      -82.4167,
      36.25
    ]
  },
  "type": "Feature",
  "properties": {
    "hierarchy": [
      "tgn:2365419",
      "tgn:1000001",
      "tgn:7012149",
      "tgn:2001926",
      "tgn:7007825",
      "tgn:7029392"
    ],
    "placetype": [
      "aat:300008347"
    ],
    "id": 2365419,
    "name:xx": "Greenwood"
  }
}
