{
  "geometry": {
    "type": "Point",
    "coordinates": [
      -99.9333,
      29.9333
    ]
  },
  "type": "Feature",
  "properties": {
    "hierarchy": [
      "tgn:2228134",
      "tgn:1000001",
      "tgn:7012149",
      "tgn:2002060",
      "tgn:7007826",
      "tgn:7029392"
    ],
    "placetype": [
      "aat:300008761"
    ],
    "id": 2228134,
    "name:xx": "Cedar Canyon"
  }
}
