{
  "geometry": {
    "type": "Point",
    "coordinates": [
      -96.1667,
      33.4833
    ]
  },
  "type": "Feature",
  "properties": {
    "hierarchy": [
      "tgn:2673853",
      "tgn:1000001",
      "tgn:7012149",
      "tgn:2001983",
      "tgn:7007826",
      "tgn:7029392"
    ],
    "placetype": [
      "aat:300008798"
    ],
    "id": 2673853,
    "name:xx": "Snow Hill"
  }
}
