{
  "geometry": {
    "type": "Point",
    "coordinates": [
      -70.1667,
      -31.9833
    ]
  },
  "type": "Feature",
  "properties": {
    "hierarchy": [
      "tgn:1105613",
      "tgn:7006477",
      "tgn:1001519",
      "tgn:1000002",
      "tgn:7029392"
    ],
    "placetype": [
      "aat:300008795"
    ],
    "id": 1105613,
    "name:xx": "Mercedario, Cerro"
  }
}
