{
  "type": "FeatureCollection",
  "features": [
    {
      "geometry": {
        "type": "Point",
        "coordinates": [
          -91.6333,
          34.6333
        ]
      },
      "type": "Feature",
      "properties": {
        "hierarchy": [
          "tgn:2369290",
          "tgn:1000001",
          "tgn:7016172",
          "tgn:7012149",
          "tgn:7029392"
        ],
        "placetype": [
          "aat:300008905"
        ],
        "id": 2369290,
        "name:xx": "Gum Swamp"
      }
    },
    {
      "geometry": {
        "type": "Point",
        "coordinates": [
          -81.1833,
          26.3333
        ]
      },
      "type": "Feature",
      "properties": {
        "hierarchy": [
          "tgn:2369291",
          "tgn:1000001",
          "tgn:1002466",
          "tgn:7012149",
          "tgn:7007240",
          "tgn:7029392"
        ],
        "placetype": [
          "aat:300008905"
        ],
        "id": 2369291,
        "name:xx": "Gum Swamp"
      }
    },
    {
      "geometry": {
        "type": "Point",
        "coordinates": [
          -84.0833,
          30.15
        ]
      },
      "type": "Feature",
      "properties": {
        "hierarchy": [
          "tgn:2369292",
          "tgn:1000001",
          "tgn:7012149",
          "tgn:2000289",
          "tgn:7007240",
          "tgn:7029392"
        ],
        "placetype": [
          "aat:300008905"
        ],
        "id": 2369292,
        "name:xx": "Gum Swamp"
      }
    },
    {
      "geometry": {
        "type": "Point",
        "coordinates": [
          -81.5333,
          30.2167
        ]
      },
      "type": "Feature",
      "properties": {
        "hierarchy": [
          "tgn:2369293",
          "tgn:1000001",
          "tgn:2000264",
          "tgn:7012149",
          "tgn:7007240",
          "tgn:7029392"
        ],
        "placetype": [
          "aat:300008905"
        ],
        "id": 2369293,
        "name:xx": "Gum Swamp"
      }
    },
    {
      "geometry": {
        "type": "Point",
        "coordinates": [
          -84.35,
          30.45
        ]
      },
      "type": "Feature",
      "properties": {
        "hierarchy": [
          "tgn:2369294",
          "tgn:1000001",
          "tgn:7012149",
          "tgn:2000276",
          "tgn:7007240",
          "tgn:7029392"
        ],
        "placetype": [
          "aat:300008905"
        ],
        "id": 2369294,
        "name:xx": "Gum Swamp"
      }
    },
    {
      "geometry": {
        "type": "Point",
        "coordinates": [
          -82.2333,
          28.95
        ]
      },
      "type": "Feature",
      "properties": {
        "hierarchy": [
          "tgn:2369295",
          "tgn:1000001",
          "tgn:7012149",
          "tgn:7007240",
          "tgn:7029392"
        ],
        "placetype": [
          "aat:300008905"
        ],
        "id": 2369295,
        "name:xx": "Gum Swamp"
      }
    },
    {
      "geometry": {
        "type": "Point",
        "coordinates": [
          -82.1833,
          27.45
        ]
      },
      "type": "Feature",
      "properties": {
        "hierarchy": [
          "tgn:2369296",
          "tgn:1000001",
          "tgn:7012149",
          "tgn:1002628",
          "tgn:7007240",
          "tgn:7029392"
        ],
        "placetype": [
          "aat:300008905"
        ],
        "id": 2369296,
        "name:xx": "Gum Swamp"
      }
    },
    {
      "geometry": {
        "type": "Point",
        "coordinates": [
          -82.4,
          31.1167
        ]
      },
      "type": "Feature",
      "properties": {
        "hierarchy": [
          "tgn:2369297",
          "tgn:1000001",
          "tgn:7012149",
          "tgn:2000439",
          "tgn:7007248",
          "tgn:7029392"
        ],
        "placetype": [
          "aat:300008699"
        ],
        "id": 2369297,
        "name:xx": "Gum Swamp"
      }
    },
    {
      "geometry": {
        "type": "Point",
        "coordinates": [
          -90.6833,
          30.4
        ]
      },
      "type": "Feature",
      "properties": {
        "hierarchy": [
          "tgn:2369298",
          "tgn:1000001",
          "tgn:7012149",
          "tgn:2000885",
          "tgn:7007256",
          "tgn:7029392"
        ],
        "placetype": [
          "aat:300008905"
        ],
        "id": 2369298,
        "name:xx": "Gum Swamp"
      }
    },
    {
      "geometry": {
        "type": "Point",
        "coordinates": [
          -89.9333,
          30.4833
        ]
      },
      "type": "Feature",
      "properties": {
        "hierarchy": [
          "tgn:2369299",
          "tgn:1000001",
          "tgn:7012149",
          "tgn:2000905",
          "tgn:7007256",
          "tgn:7029392"
        ],
        "placetype": [
          "aat:300008905"
        ],
        "id": 2369299,
        "name:xx": "Gum Swamp"
      }
    }
  ]
}
