{
  "geometry": {
    "type": "Point",
    "coordinates": [
      -90.7833,
      31.6333
    ]
  },
  "type": "Feature",
  "properties": {
    "hierarchy": [
      "tgn:2693098",
      "tgn:1000001",
      "tgn:7012149",
      "tgn:7007522",
      "tgn:7029392"
    ],
    "placetype": [
      "aat:300008706"
    ],
    "id": 2693098,
    "name:xx": "Steep Hill Creek"
  }
}
