{
  "geometry": {
    "type": "Point",
    "coordinates": [
      -113.3833,
      43.9833
    ]
  },
  "type": "Feature",
  "properties": {
    "hierarchy": [
      "tgn:1110068",
      "tgn:1000001",
      "tgn:7012149",
      "tgn:7007250",
      "tgn:7029392"
    ],
    "placetype": [
      "aat:300386831"
    ],
    "id": 1110068,
    "name:xx": "Lost River Range"
  }
}
