{
  "type": "FeatureCollection",
  "features": [
    {
      "geometry": {
        "type": "Point",
        "coordinates": [
          -78.2333,
          39.8833
        ]
      },
      "type": "Feature",
      "properties": {
        "hierarchy": [
          "tgn:2771020",
          "tgn:1000001",
          "tgn:7012149",
          "tgn:1002399",
          "tgn:7007710",
          "tgn:7029392"
        ],
        "placetype": [
          "aat:300008761"
        ],
        "id": 2771020,
        "name:xx": "Wildcat Hollow"
      }
    },
    {
      "geometry": {
        "type": "Point",
        "coordinates": [
          -88.1333,
          35.05
        ]
      },
      "type": "Feature",
      "properties": {
        "hierarchy": [
          "tgn:2771021",
          "tgn:1000001",
          "tgn:7012149",
          "tgn:2001872",
          "tgn:7007825",
          "tgn:7029392"
        ],
        "placetype": [
          "aat:300008761"
        ],
        "id": 2771021,
        "name:xx": "Wildcat Hollow"
      }
    },
    {
      "geometry": {
        "type": "Point",
        "coordinates": [
          -87.7667,
          35.35
        ]
      },
      "type": "Feature",
      "properties": {
        "hierarchy": [
          "tgn:2771022",
          "tgn:1000001",
          "tgn:7012149",
          "tgn:2001927",
          "tgn:7007825",
          "tgn:7029392"
        ],
        "placetype": [
          "aat:300008761"
        ],
        "id": 2771022,
        "name:xx": "Wildcat Hollow"
      }
    },
    {
      "geometry": {
        "type": "Point",
        "coordinates": [
          -85.0833,
          35.4667
        ]
      },
      "type": "Feature",
      "properties": {
        "hierarchy": [
          "tgn:2771023",
          "tgn:1000001",
          "tgn:7012149",
          "tgn:2001908",
          "tgn:7007825",
          "tgn:7029392"
        ],
        "placetype": [
          "aat:300008761"
        ],
        "id": 2771023,
        "name:xx": "Wildcat Hollow"
      }
    },
    {
      "geometry": {
        "type": "Point",
        "coordinates": [
          -86.1667,
          35.5
        ]
      },
      "type": "Feature",
      "properties": {
        "hierarchy": [
          "tgn:2771024",
          "tgn:1000001",
          "tgn:7012149",
          "tgn:2001852",
          "tgn:7007825",
          "tgn:7029392"
        ],
        "placetype": [
          "aat:300008761"
        ],
        "id": 2771024,
        "name:xx": "Wildcat Hollow"
      }
    },
    {
      "geometry": {
        "type": "Point",
        "coordinates": [
          -87.6,
          35.5333
        ]
      },
      "type": "Feature",
      "properties": {
        "hierarchy": [
          "tgn:2771025",
          "tgn:1000001",
          "tgn:7012149",
          "tgn:2001887",
          "tgn:7007825",
          "tgn:7029392"
        ],
        "placetype": [
          "aat:300008761"
        ],
        "id": 2771025,
        "name:xx": "Wildcat Hollow"
      }
    },
    {
      "geometry": {
        "type": "Point",
        "coordinates": [
          -83.7,
          35.7
        ]
      },
      "type": "Feature",
      "properties": {
        "hierarchy": [
          "tgn:2771026",
          "tgn:1000001",
          "tgn:7012149",
          "tgn:2001914",
          "tgn:7007825",
          "tgn:7029392"
        ],
        "placetype": [
          "aat:300008761"
        ],
        "id": 2771026,
        "name:xx": "Wildcat Hollow"
      }
    },
    {
      "geometry": {
        "type": "Point",
        "coordinates": [
          -87.3667,
          35.8167
        ]
      },
      "type": "Feature",
      "properties": {
        "hierarchy": [
          "tgn:2771027",
          "tgn:1000001",
          "tgn:7012149",
          "tgn:7015666",
          "tgn:7007825",
          "tgn:7029392"
        ],
        "placetype": [
          "aat:300008761"
        ],
        "id": 2771027,
        "name:xx": "Wildcat Hollow"
      }
    },
    {
      "geometry": {
        "type": "Point",
        "coordinates": [
          -84.8,
          35.8167
        ]
      },
      "type": "Feature",
      "properties": {
        "hierarchy": [
          "tgn:2771028",
          "tgn:1000001",
          "tgn:7012149",
          "tgn:7007825",
          "tgn:7029392"
        ],
        "placetype": [
          "aat:300008761"
        ],
        "id": 2771028,
        "name:xx": "Wildcat Hollow"
      }
    },
    {
      "geometry": {
        "type": "Point",
        "coordinates": [
          -87.1667,
          35.8167
        ]
      },
      "type": "Feature",
      "properties": {
        "hierarchy": [
          "tgn:2771029",
          "tgn:1000001",
          "tgn:7012149",
          "tgn:2001896",
          "tgn:7007825",
          "tgn:7029392"
        ],
        "placetype": [
          "aat:300008761"
        ],
        "id": 2771029,
        "name:xx": "Wildcat Hollow"
      }
    }
  ]
}
