{
  "geometry": {
    "type": "Point",
    "coordinates": [
      -144.85,
      61.4833
    ]
  },
  "type": "Feature",
  "properties": {
    "hierarchy": [
      "tgn:2371867",
      "tgn:7006450",
      "tgn:1000001",
      "tgn:7012149",
      "tgn:2000086",
      "tgn:7029392"
    ],
    "placetype": [
      "aat:300008706"
    ],
    "id": 2371867,
    "name:xx": "Haley Creek"
  }
}
