{
  "geometry": {
    "type": "Point",
    "coordinates": [
      -113.3833,
      45.2333
    ]
  },
  "type": "Feature",
  "properties": {
    "hierarchy": [
      "tgn:2301197",
      "tgn:1000001",
      "tgn:2001260",
      "tgn:7012149",
      "tgn:7007524",
      "tgn:7029392"
    ],
    "placetype": [
      "aat:300008905"
    ],
    "id": 2301197,
    "name:xx": "Dunkwaden Flats"
  }
}
