{
  "type": "FeatureCollection",
  "features": [
    {
      "geometry": {
        "type": "Point",
        "coordinates": [
          9.5833,
          37.0833
        ]
      },
      "type": "Feature",
      "properties": {
        "hierarchy": [
          "tgn:1002070",
          "tgn:7001242",
          "tgn:1000205",
          "tgn:7029392"
        ],
        "placetype": [
          "aat:300387064",
          "aat:300235093"
        ],
        "id": 1002070,
        "name:xx": "Bizerte"
      }
    },
    {
      "geometry": {
        "type": "Point",
        "coordinates": [
          -74,
          1
        ]
      },
      "type": "Feature",
      "properties": {
        "hierarchy": [
          "tgn:1002071",
          "tgn:1000050",
          "tgn:1000002",
          "tgn:7029392"
        ],
        "placetype": [
          "aat:300387064",
          "aat:300000772"
        ],
        "id": 1002071,
        "name:xx": "Caquetá"
      }
    },
    {
      "geometry": {
        "type": "Point",
        "coordinates": [
          -52.5,
          4
        ]
      },
      "type": "Feature",
      "properties": {
        "hierarchy": [
          "tgn:1002072",
          "tgn:1000053",
          "tgn:1000002",
          "tgn:7029392"
        ],
        "placetype": [
          "aat:300000759",
          "aat:300387064"
        ],
        "id": 1002072,
        "name:xx": "Cayenne"
      }
    },
    {
      "geometry": {
        "type": "Point",
        "coordinates": [
          36.216,
          32.85
        ]
      },
      "type": "Feature",
      "properties": {
        "hierarchy": [
          "tgn:1002074",
          "tgn:1000004",
          "tgn:1000140",
          "tgn:7029392"
        ],
        "placetype": [
          "aat:300387064",
          "aat:300235093"
        ],
        "id": 1002074,
        "name:xx": "Dar‘ā, Muḩāfaz̧at"
      }
    },
    {
      "geometry": {
        "type": "Point",
        "coordinates": [
          40.283,
          35.166
        ]
      },
      "type": "Feature",
      "properties": {
        "hierarchy": [
          "tgn:1002075",
          "tgn:1000004",
          "tgn:1000140",
          "tgn:7029392"
        ],
        "placetype": [
          "aat:300387064",
          "aat:300235093"
        ],
        "id": 1002075,
        "name:xx": "Dayr az Zawr"
      }
    },
    {
      "geometry": {
        "type": "Point",
        "coordinates": [
          36.283,
          33.516
        ]
      },
      "type": "Feature",
      "properties": {
        "hierarchy": [
          "tgn:1002076",
          "tgn:1000004",
          "tgn:1000140",
          "tgn:7029392"
        ],
        "placetype": [
          "aat:300387064",
          "aat:300235093"
        ],
        "id": 1002076,
        "name:xx": "Dimashq"
      }
    },
    {
      "geometry": {
        "type": "Point",
        "coordinates": [
          9,
          36
        ]
      },
      "type": "Feature",
      "properties": {
        "hierarchy": [
          "tgn:1002078",
          "tgn:7001242",
          "tgn:1000205",
          "tgn:7029392"
        ],
        "placetype": [
          "aat:300387064",
          "aat:300235093"
        ],
        "id": 1002078,
        "name:xx": "El Kef"
      }
    }
  ]
}
