{
  "type": "FeatureCollection",
  "features": [
    {
      "geometry": {
        "type": "Point",
        "coordinates": [
          -94.55,
          36.5167
        ]
      },
      "type": "Feature",
      "properties": {
        "hierarchy": [
          "tgn:2227501",
          "tgn:1000001",
          "tgn:7012149",
          "tgn:7029392"
        ],
        "placetype": [
          "aat:300008699"
        ],
        "id": 2227501,
        "name:xx": "Cave Springs Branch"
      }
    },
    {
      "geometry": {
        "type": "Point",
        "coordinates": [
          -82.9667,
          36.5167
        ]
      },
      "type": "Feature",
      "properties": {
        "hierarchy": [
          "tgn:2227502",
          "tgn:1000001",
          "tgn:7012149",
          "tgn:2001873",
          "tgn:7007825",
          "tgn:7029392"
        ],
        "placetype": [
          "aat:300008699"
        ],
        "id": 2227502,
        "name:xx": "Cave Springs Branch"
      }
    },
    {
      "geometry": {
        "type": "Point",
        "coordinates": [
          -87.1333,
          34.7833
        ]
      },
      "type": "Feature",
      "properties": {
        "hierarchy": [
          "tgn:2227503",
          "tgn:7002659",
          "tgn:1000001",
          "tgn:7012149",
          "tgn:2000038",
          "tgn:7029392"
        ],
        "placetype": [
          "aat:300008746"
        ],
        "id": 2227503,
        "name:xx": "Cave Springs Cave"
      }
    },
    {
      "geometry": {
        "type": "Point",
        "coordinates": [
          -94.2167,
          36.25
        ]
      },
      "type": "Feature",
      "properties": {
        "hierarchy": [
          "tgn:2227504",
          "tgn:1000001",
          "tgn:2000108",
          "tgn:7016172",
          "tgn:7012149",
          "tgn:7029392"
        ],
        "placetype": [
          "aat:300008746"
        ],
        "id": 2227504,
        "name:xx": "Cave Springs Cave"
      }
    },
    {
      "geometry": {
        "type": "Point",
        "coordinates": [
          -87.0333,
          36.1
        ]
      },
      "type": "Feature",
      "properties": {
        "hierarchy": [
          "tgn:2227505",
          "tgn:1000001",
          "tgn:7012149",
          "tgn:2001847",
          "tgn:7007825",
          "tgn:7029392"
        ],
        "placetype": [
          "aat:300008746"
        ],
        "id": 2227505,
        "name:xx": "Cave Springs Cave"
      }
    },
    {
      "geometry": {
        "type": "Point",
        "coordinates": [
          -85.55,
          35.7
        ]
      },
      "type": "Feature",
      "properties": {
        "hierarchy": [
          "tgn:2227506",
          "tgn:1000001",
          "tgn:7012149",
          "tgn:2001924",
          "tgn:7007825",
          "tgn:7029392"
        ],
        "placetype": [
          "aat:300008746"
        ],
        "id": 2227506,
        "name:xx": "Cave Springs Cave"
      }
    },
    {
      "geometry": {
        "type": "Point",
        "coordinates": [
          -85.2167,
          35.1833
        ]
      },
      "type": "Feature",
      "properties": {
        "hierarchy": [
          "tgn:2227507",
          "tgn:1000001",
          "tgn:7012149",
          "tgn:2001869",
          "tgn:7007825",
          "tgn:7029392"
        ],
        "placetype": [
          "aat:300008746"
        ],
        "id": 2227507,
        "name:xx": "Cave Springs Cave"
      }
    },
    {
      "geometry": {
        "type": "Point",
        "coordinates": [
          -81.5667,
          37.0833
        ]
      },
      "type": "Feature",
      "properties": {
        "hierarchy": [
          "tgn:2227508",
          "tgn:1000001",
          "tgn:7012149",
          "tgn:2002192",
          "tgn:7007919",
          "tgn:7029392"
        ],
        "placetype": [
          "aat:300008746"
        ],
        "id": 2227508,
        "name:xx": "Cave Springs Cave"
      }
    },
    {
      "geometry": {
        "type": "Point",
        "coordinates": [
          -82.9167,
          36.8
        ]
      },
      "type": "Feature",
      "properties": {
        "hierarchy": [
          "tgn:2227509",
          "tgn:1000001",
          "tgn:7012149",
          "tgn:2002169",
          "tgn:7007919",
          "tgn:7029392"
        ],
        "placetype": [
          "aat:300008746"
        ],
        "id": 2227509,
        "name:xx": "Cave Springs Cave"
      }
    }
  ]
}
