{
  "geometry": {
    "type": "Point",
    "coordinates": [
      -114.7833,
      46.65
    ]
  },
  "type": "Feature",
  "properties": {
    "hierarchy": [
      "tgn:2772989",
      "tgn:1000001",
      "tgn:2000469",
      "tgn:7012149",
      "tgn:7007250",
      "tgn:7029392"
    ],
    "placetype": [
      "aat:300008798"
    ],
    "id": 2772989,
    "name:xx": "Williams Peak"
  }
}
