{
  "geometry": {
    "type": "Point",
    "coordinates": [
      -133.2167,
      57.1167
    ]
  },
  "type": "Feature",
  "properties": {
    "hierarchy": [
      "tgn:2323519",
      "tgn:7006450",
      "tgn:1000001",
      "tgn:7012149",
      "tgn:2000088",
      "tgn:7029392"
    ],
    "placetype": [
      "aat:300132316"
    ],
    "id": 2323519,
    "name:xx": "Farragut Bay"
  }
}
