{
  "geometry": {
    "type": "Point",
    "coordinates": [
      86.6667,
      26.9167
    ]
  },
  "type": "Feature",
  "properties": {
    "hierarchy": [
      "tgn:1083327",
      "tgn:7001423",
      "tgn:7001416",
      "tgn:1000004",
      "tgn:1000132",
      "tgn:7029392"
    ],
    "placetype": [
      "aat:300008347"
    ],
    "id": 1083327,
    "name:xx": "Udaypur"
  }
}
