{
  "geometry": {
    "type": "Point",
    "coordinates": [
      34.15,
      24.05
    ]
  },
  "type": "Feature",
  "properties": {
    "hierarchy": [
      "tgn:7540715",
      "tgn:7001242",
      "tgn:7001311",
      "tgn:7016833",
      "tgn:7029392"
    ],
    "placetype": [
      "aat:300379998"
    ],
    "name:en": "Shabana, Rôd",
    "id": 7540715
  }
}
