{
  "geometry": {
    "type": "Point",
    "coordinates": [
      5.25,
      50.05
    ]
  },
  "type": "Feature",
  "properties": {
    "hierarchy": [
      "tgn:7254584",
      "tgn:7003465",
      "tgn:1000003",
      "tgn:1000063",
      "tgn:4012014",
      "tgn:7029392"
    ],
    "placetype": [
      "aat:300008863"
    ],
    "id": 7254584,
    "name:xx": "Thiry, Bois"
  }
}
