{
  "geometry": {
    "type": "Point",
    "coordinates": [
      -107.0833,
      49.4167
    ]
  },
  "type": "Feature",
  "properties": {
    "hierarchy": [
      "tgn:1016012",
      "tgn:7005685",
      "tgn:1000001",
      "tgn:7005805",
      "tgn:7029392"
    ],
    "placetype": [
      "aat:300008347"
    ],
    "id": 1016012,
    "name:xx": "Mankota"
  }
}
