{
  "type": "FeatureCollection",
  "features": [
    {
      "geometry": {
        "type": "Point",
        "coordinates": [
          -148.05,
          -17.8667
        ]
      },
      "type": "Feature",
      "properties": {
        "hierarchy": [
          "tgn:1008116",
          "tgn:7006218",
          "tgn:1000216",
          "tgn:1000006",
          "tgn:7029392"
        ],
        "placetype": [
          "aat:300008791"
        ],
        "id": 1008116,
        "name:xx": "Mehetia"
      }
    },
    {
      "geometry": {
        "type": "Point",
        "coordinates": [
          -43.2833,
          -23.0333
        ]
      },
      "type": "Feature",
      "properties": {
        "hierarchy": [
          "tgn:1008117",
          "tgn:1001942",
          "tgn:1000047",
          "tgn:7002457",
          "tgn:1000002",
          "tgn:7029392"
        ],
        "placetype": [
          "aat:300008791"
        ],
        "id": 1008117,
        "name:xx": "Meio, Ilha do"
      }
    },
    {
      "geometry": {
        "type": "Point",
        "coordinates": [
          119.1167,
          25.0667
        ]
      },
      "type": "Feature",
      "properties": {
        "hierarchy": [
          "tgn:1008118",
          "tgn:1000004",
          "tgn:7001796",
          "tgn:1000111",
          "tgn:7029392"
        ],
        "placetype": [
          "aat:300008791"
        ],
        "id": 1008118,
        "name:xx": "Meizhou Dao"
      }
    }
  ]
}
