{
  "geometry": {
    "type": "Point",
    "coordinates": [
      -95.0333,
      37.0833
    ]
  },
  "type": "Feature",
  "properties": {
    "hierarchy": [
      "tgn:2404552",
      "tgn:1000001",
      "tgn:2000670",
      "tgn:7012149",
      "tgn:7007254",
      "tgn:7029392"
    ],
    "placetype": [
      "aat:300008680"
    ],
    "id": 2404552,
    "name:xx": "Hubbell Lake"
  }
}
