{
  "geometry": {
    "type": "Point",
    "coordinates": [
      -68.9167,
      45.9167
    ]
  },
  "type": "Feature",
  "properties": {
    "hierarchy": [
      "tgn:2373900",
      "tgn:1000001",
      "tgn:7012149",
      "tgn:2000928",
      "tgn:7007515",
      "tgn:7029392"
    ],
    "placetype": [
      "aat:300266640"
    ],
    "id": 2373900,
    "name:xx": "Hamlin Ridge"
  }
}
