{
  "geometry": {
    "type": "Point",
    "coordinates": [
      -108.0833,
      37.4167
    ]
  },
  "type": "Feature",
  "properties": {
    "hierarchy": [
      "tgn:2308400",
      "tgn:1000001",
      "tgn:7012149",
      "tgn:2000233",
      "tgn:7007158",
      "tgn:7029392"
    ],
    "placetype": [
      "aat:300008699"
    ],
    "id": 2308400,
    "name:xx": "East Mancos River"
  }
}
