{
  "geometry": {
    "type": "Point",
    "coordinates": [
      -105.55,
      39.9333
    ]
  },
  "type": "Feature",
  "properties": {
    "hierarchy": [
      "tgn:2715008",
      "tgn:1000001",
      "tgn:7012149",
      "tgn:7007158",
      "tgn:7029392"
    ],
    "placetype": [
      "aat:300008798"
    ],
    "id": 2715008,
    "name:xx": "Tennessee Mountain"
  }
}
