{
  "geometry": {
    "type": "Point",
    "coordinates": [
      -89.7833,
      30.4667
    ]
  },
  "type": "Feature",
  "properties": {
    "hierarchy": [
      "tgn:2573023",
      "tgn:1000001",
      "tgn:7012149",
      "tgn:2000905",
      "tgn:7007256",
      "tgn:7029392"
    ],
    "placetype": [
      "aat:300006075"
    ],
    "id": 2573023,
    "name:xx": "Pearl River Canal"
  }
}
