{
  "geometry": {
    "type": "Point",
    "coordinates": [
      -110.2333,
      42.8833
    ]
  },
  "type": "Feature",
  "properties": {
    "hierarchy": [
      "tgn:2635130",
      "tgn:1000001",
      "tgn:7012149",
      "tgn:2002382",
      "tgn:7007923",
      "tgn:7029392"
    ],
    "placetype": [
      "aat:300008761"
    ],
    "id": 2635130,
    "name:xx": "Ryegrass Draw"
  }
}
