{
  "geometry": {
    "type": "Point",
    "coordinates": [
      -99.75,
      29.7333
    ]
  },
  "type": "Feature",
  "properties": {
    "hierarchy": [
      "tgn:1124028",
      "tgn:1000001",
      "tgn:7012149",
      "tgn:7007826",
      "tgn:7029392"
    ],
    "placetype": [
      "aat:300008707"
    ],
    "id": 1124028,
    "name:xx": "Frio"
  }
}
