{
  "geometry": {
    "type": "Point",
    "coordinates": [
      -114.0167,
      35.7667
    ]
  },
  "type": "Feature",
  "properties": {
    "hierarchy": [
      "tgn:2608787",
      "tgn:1000001",
      "tgn:7006451",
      "tgn:7012149",
      "tgn:2000098",
      "tgn:7029392"
    ],
    "placetype": [
      "aat:300008697"
    ],
    "id": 2608787,
    "name:xx": "Rattlesnake Spring"
  }
}
