{
  "type": "FeatureCollection",
  "features": [
    {
      "geometry": {
        "type": "Point",
        "coordinates": [
          -1.9,
          53.483333
        ]
      },
      "type": "Feature",
      "properties": {
        "hierarchy": [
          "tgn:7463440",
          "tgn:7002445",
          "tgn:1000003",
          "tgn:7008118",
          "tgn:7008591",
          "tgn:7029392"
        ],
        "placetype": [
          "aat:300006191"
        ],
        "name:en": "Longdendale Reservoirs",
        "id": 7463440
      }
    },
    {
      "geometry": {
        "type": "Point",
        "coordinates": [
          -0.583333,
          51.366667
        ]
      },
      "type": "Feature",
      "properties": {
        "hierarchy": [
          "tgn:7463443",
          "tgn:7002445",
          "tgn:1000003",
          "tgn:7008175",
          "tgn:7008591",
          "tgn:7029392"
        ],
        "placetype": [
          "aat:300008347"
        ],
        "name:en": "Longcross",
        "id": 7463443
      }
    },
    {
      "geometry": {
        "type": "Point",
        "coordinates": [
          -5.116667,
          56.683333
        ]
      },
      "type": "Feature",
      "properties": {
        "hierarchy": [
          "tgn:7463446",
          "tgn:7002444",
          "tgn:1000003",
          "tgn:7008082",
          "tgn:7008591",
          "tgn:7029392"
        ],
        "placetype": [
          "aat:300008680"
        ],
        "name:en": "Leven, Loch",
        "id": 7463446
      }
    }
  ]
}
