{
  "geometry": {
    "type": "Point",
    "coordinates": [
      -106.9833,
      43.8167
    ]
  },
  "type": "Feature",
  "properties": {
    "hierarchy": [
      "tgn:2779243",
      "tgn:1000001",
      "tgn:7012149",
      "tgn:2002374",
      "tgn:7007923",
      "tgn:7029392"
    ],
    "placetype": [
      "aat:300008761"
    ],
    "id": 2779243,
    "name:xx": "Wolf Den Draw"
  }
}
