{
  "geometry": {
    "type": "Point",
    "coordinates": [
      -6.9833,
      52.7333
    ]
  },
  "type": "Feature",
  "properties": {
    "hierarchy": [
      "tgn:1042896",
      "tgn:7003485",
      "tgn:7001199",
      "tgn:1000003",
      "tgn:1000078",
      "tgn:7029392"
    ],
    "placetype": [
      "aat:300008347"
    ],
    "id": 1042896,
    "name:xx": "Leighlinbridge"
  }
}
