{
  "type": "FeatureCollection",
  "features": [
    {
      "geometry": {
        "type": "Point",
        "coordinates": [
          -109.8167,
          45.35
        ]
      },
      "type": "Feature",
      "properties": {
        "hierarchy": [
          "tgn:2332940",
          "tgn:1000001",
          "tgn:7012149",
          "tgn:2001307",
          "tgn:7007524",
          "tgn:7029392"
        ],
        "placetype": [
          "aat:300008706"
        ],
        "id": 2332940,
        "name:xx": "Flume Creek"
      }
    },
    {
      "geometry": {
        "type": "Point",
        "coordinates": [
          -121.6333,
          45.6667
        ]
      },
      "type": "Feature",
      "properties": {
        "hierarchy": [
          "tgn:2332941",
          "tgn:1000001",
          "tgn:7012149",
          "tgn:2001710",
          "tgn:7007708",
          "tgn:7029392"
        ],
        "placetype": [
          "aat:300008706"
        ],
        "id": 2332941,
        "name:xx": "Flume Creek"
      }
    },
    {
      "geometry": {
        "type": "Point",
        "coordinates": [
          -123.0833,
          46.1333
        ]
      },
      "type": "Feature",
      "properties": {
        "hierarchy": [
          "tgn:2332942",
          "tgn:1000001",
          "tgn:1002293",
          "tgn:7012149",
          "tgn:7007708",
          "tgn:7029392"
        ],
        "placetype": [
          "aat:300008706"
        ],
        "id": 2332942,
        "name:xx": "Flume Creek"
      }
    },
    {
      "geometry": {
        "type": "Point",
        "coordinates": [
          -122.7,
          45.7667
        ]
      },
      "type": "Feature",
      "properties": {
        "hierarchy": [
          "tgn:2332943",
          "tgn:1000001",
          "tgn:1002275",
          "tgn:7012149",
          "tgn:7007920",
          "tgn:7029392"
        ],
        "placetype": [
          "aat:300008706"
        ],
        "id": 2332943,
        "name:xx": "Flume Creek"
      }
    },
    {
      "geometry": {
        "type": "Point",
        "coordinates": [
          -121.5833,
          48.4167
        ]
      },
      "type": "Feature",
      "properties": {
        "hierarchy": [
          "tgn:2332944",
          "tgn:1000001",
          "tgn:7012149",
          "tgn:7014510",
          "tgn:7007920",
          "tgn:7029392"
        ],
        "placetype": [
          "aat:300008706"
        ],
        "id": 2332944,
        "name:xx": "Flume Creek"
      }
    },
    {
      "geometry": {
        "type": "Point",
        "coordinates": [
          -117.3833,
          48.9333
        ]
      },
      "type": "Feature",
      "properties": {
        "hierarchy": [
          "tgn:2332945",
          "tgn:1000001",
          "tgn:7012149",
          "tgn:7007920",
          "tgn:7029392"
        ],
        "placetype": [
          "aat:300008706"
        ],
        "id": 2332945,
        "name:xx": "Flume Creek"
      }
    },
    {
      "geometry": {
        "type": "Point",
        "coordinates": [
          -89.3333,
          44.7
        ]
      },
      "type": "Feature",
      "properties": {
        "hierarchy": [
          "tgn:2332946",
          "tgn:1000001",
          "tgn:7012149",
          "tgn:7007922",
          "tgn:7029392"
        ],
        "placetype": [
          "aat:300008706"
        ],
        "id": 2332946,
        "name:xx": "Flume Creek"
      }
    },
    {
      "geometry": {
        "type": "Point",
        "coordinates": [
          -106.3,
          41.15
        ]
      },
      "type": "Feature",
      "properties": {
        "hierarchy": [
          "tgn:2332947",
          "tgn:2002365",
          "tgn:1000001",
          "tgn:7012149",
          "tgn:7007923",
          "tgn:7029392"
        ],
        "placetype": [
          "aat:300008706"
        ],
        "id": 2332947,
        "name:xx": "Flume Creek"
      }
    },
    {
      "geometry": {
        "type": "Point",
        "coordinates": [
          -105.5,
          42.6667
        ]
      },
      "type": "Feature",
      "properties": {
        "hierarchy": [
          "tgn:2332948",
          "tgn:1000001",
          "tgn:2002369",
          "tgn:7012149",
          "tgn:7007923",
          "tgn:7029392"
        ],
        "placetype": [
          "aat:300008706"
        ],
        "id": 2332948,
        "name:xx": "Flume Creek"
      }
    },
    {
      "geometry": {
        "type": "Point",
        "coordinates": [
          -117.3833,
          48.8667
        ]
      },
      "type": "Feature",
      "properties": {
        "hierarchy": [
          "tgn:2332949",
          "tgn:1000001",
          "tgn:7012149",
          "tgn:2002248",
          "tgn:7007920",
          "tgn:7029392"
        ],
        "placetype": [
          "aat:300006191"
        ],
        "id": 2332949,
        "name:xx": "Flume Creek Reservoir"
      }
    }
  ]
}
