{
  "type": "FeatureCollection",
  "features": [
    {
      "geometry": {
        "type": "Point",
        "coordinates": [
          4.766667,
          51.433333
        ]
      },
      "type": "Feature",
      "properties": {
        "hierarchy": [
          "tgn:7259001",
          "tgn:7003456",
          "tgn:1000003",
          "tgn:1000063",
          "tgn:7018236",
          "tgn:7029392"
        ],
        "placetype": [
          "aat:300008347"
        ],
        "id": 7259001,
        "name:xx": "Vijfhuizen"
      }
    },
    {
      "geometry": {
        "type": "Point",
        "coordinates": [
          4.233333,
          51.133333
        ]
      },
      "type": "Feature",
      "properties": {
        "hierarchy": [
          "tgn:7259002",
          "tgn:7003457",
          "tgn:1000003",
          "tgn:1000063",
          "tgn:7018236",
          "tgn:7029392"
        ],
        "placetype": [
          "aat:300008347"
        ],
        "id": 7259002,
        "name:xx": "Vijfhuizen"
      }
    },
    {
      "geometry": {
        "type": "Point",
        "coordinates": [
          3.916667,
          51.133333
        ]
      },
      "type": "Feature",
      "properties": {
        "hierarchy": [
          "tgn:7259003",
          "tgn:7003457",
          "tgn:1000003",
          "tgn:1000063",
          "tgn:7018236",
          "tgn:7029392"
        ],
        "placetype": [
          "aat:300008347"
        ],
        "id": 7259003,
        "name:xx": "Vijfhuizen"
      }
    },
    {
      "geometry": {
        "type": "Point",
        "coordinates": [
          4.866667,
          51.1
        ]
      },
      "type": "Feature",
      "properties": {
        "hierarchy": [
          "tgn:7259004",
          "tgn:7003456",
          "tgn:1000003",
          "tgn:1000063",
          "tgn:7018236",
          "tgn:7029392"
        ],
        "placetype": [
          "aat:300008347"
        ],
        "id": 7259004,
        "name:xx": "Vijfhuizen"
      }
    },
    {
      "geometry": {
        "type": "Point",
        "coordinates": [
          2.8465,
          50.984041
        ]
      },
      "type": "Feature",
      "properties": {
        "hierarchy": [
          "tgn:7259005",
          "tgn:7003458",
          "tgn:1000003",
          "tgn:1000063",
          "tgn:7018236",
          "tgn:7029392"
        ],
        "placetype": [
          "aat:300008347"
        ],
        "id": 7259005,
        "name:xx": "Vijfhuizen"
      }
    },
    {
      "geometry": {
        "type": "Point",
        "coordinates": [
          3.993115,
          50.942539
        ]
      },
      "type": "Feature",
      "properties": {
        "hierarchy": [
          "tgn:7259006",
          "tgn:7003457",
          "tgn:1000003",
          "tgn:1000063",
          "tgn:7018236",
          "tgn:7029392"
        ],
        "placetype": [
          "aat:300008347"
        ],
        "id": 7259006,
        "name:xx": "Vijfhuizen"
      }
    },
    {
      "geometry": {
        "type": "Point",
        "coordinates": [
          3.074454,
          51.043983
        ]
      },
      "type": "Feature",
      "properties": {
        "hierarchy": [
          "tgn:7259007",
          "tgn:7003458",
          "tgn:1000003",
          "tgn:1000063",
          "tgn:7018236",
          "tgn:7029392"
        ],
        "placetype": [
          "aat:300008347"
        ],
        "id": 7259007,
        "name:xx": "Vijfhuishoek"
      }
    },
    {
      "geometry": {
        "type": "Point",
        "coordinates": [
          3.783333,
          51.25
        ]
      },
      "type": "Feature",
      "properties": {
        "hierarchy": [
          "tgn:7259008",
          "tgn:7003457",
          "tgn:1000003",
          "tgn:1000063",
          "tgn:7018236",
          "tgn:7029392"
        ],
        "placetype": [
          "aat:300008699"
        ],
        "id": 7259008,
        "name:xx": "Vijfhonderd Gemetenbeek"
      }
    },
    {
      "geometry": {
        "type": "Point",
        "coordinates": [
          3.781128,
          51.232056
        ]
      },
      "type": "Feature",
      "properties": {
        "hierarchy": [
          "tgn:7259009",
          "tgn:7003457",
          "tgn:1000003",
          "tgn:1000063",
          "tgn:7018236",
          "tgn:7029392"
        ],
        "placetype": [
          "aat:300008347"
        ],
        "id": 7259009,
        "name:xx": "Vijfhonderd Gemeten"
      }
    }
  ]
}
