{
  "geometry": {
    "type": "Point",
    "coordinates": [
      -123.6667,
      42.8333
    ]
  },
  "type": "Feature",
  "properties": {
    "hierarchy": [
      "tgn:2382039",
      "tgn:1000001",
      "tgn:7012149",
      "tgn:2001706",
      "tgn:7007708",
      "tgn:7029392"
    ],
    "placetype": [
      "aat:300266640"
    ],
    "id": 2382039,
    "name:xx": "Hayes Ridge"
  }
}
