{
  "type": "FeatureCollection",
  "features": [
    {
      "geometry": {
        "type": "Point",
        "coordinates": [
          -105.6667,
          32.75
        ]
      },
      "type": "Feature",
      "properties": {
        "hierarchy": [
          "tgn:2575500",
          "tgn:1000001",
          "tgn:7012149",
          "tgn:2001447",
          "tgn:7007566",
          "tgn:7029392"
        ],
        "placetype": [
          "aat:300008761"
        ],
        "id": 2575500,
        "name:xx": "Pepper Canyon"
      }
    },
    {
      "geometry": {
        "type": "Point",
        "coordinates": [
          -120.3833,
          44.9833
        ]
      },
      "type": "Feature",
      "properties": {
        "hierarchy": [
          "tgn:2575501",
          "tgn:1000001",
          "tgn:7012149",
          "tgn:2001723",
          "tgn:7007708",
          "tgn:7029392"
        ],
        "placetype": [
          "aat:300008761"
        ],
        "id": 2575501,
        "name:xx": "Pepper Canyon"
      }
    },
    {
      "geometry": {
        "type": "Point",
        "coordinates": [
          -117.5333,
          33.85
        ]
      },
      "type": "Feature",
      "properties": {
        "hierarchy": [
          "tgn:2575502",
          "tgn:1000001",
          "tgn:7012149",
          "tgn:7007157",
          "tgn:1002828",
          "tgn:7029392"
        ],
        "placetype": [
          "aat:300008347"
        ],
        "id": 2575502,
        "name:xx": "Pepper Corner"
      }
    },
    {
      "geometry": {
        "type": "Point",
        "coordinates": [
          -80.4667,
          27.9
        ]
      },
      "type": "Feature",
      "properties": {
        "hierarchy": [
          "tgn:2575503",
          "tgn:1000001",
          "tgn:1002200",
          "tgn:7012149",
          "tgn:7007240",
          "tgn:7029392"
        ],
        "placetype": [
          "aat:300132316"
        ],
        "id": 2575503,
        "name:xx": "Pepper Cove"
      }
    },
    {
      "geometry": {
        "type": "Point",
        "coordinates": [
          -94.2833,
          34.1167
        ]
      },
      "type": "Feature",
      "properties": {
        "hierarchy": [
          "tgn:2575504",
          "tgn:1000001",
          "tgn:7016172",
          "tgn:7012149",
          "tgn:2000171",
          "tgn:7029392"
        ],
        "placetype": [
          "aat:300008706"
        ],
        "id": 2575504,
        "name:xx": "Pepper Creek"
      }
    },
    {
      "geometry": {
        "type": "Point",
        "coordinates": [
          -75.2833,
          38.5333
        ]
      },
      "type": "Feature",
      "properties": {
        "hierarchy": [
          "tgn:2575505",
          "tgn:1002933",
          "tgn:1000001",
          "tgn:7012149",
          "tgn:7007239",
          "tgn:7029392"
        ],
        "placetype": [
          "aat:300008706"
        ],
        "id": 2575505,
        "name:xx": "Pepper Creek"
      }
    },
    {
      "geometry": {
        "type": "Point",
        "coordinates": [
          -84.1,
          33.0667
        ]
      },
      "type": "Feature",
      "properties": {
        "hierarchy": [
          "tgn:2575506",
          "tgn:1000001",
          "tgn:7012149",
          "tgn:2000376",
          "tgn:7007248",
          "tgn:7029392"
        ],
        "placetype": [
          "aat:300008706"
        ],
        "id": 2575506,
        "name:xx": "Pepper Creek"
      }
    },
    {
      "geometry": {
        "type": "Point",
        "coordinates": [
          -114.8833,
          43.5333
        ]
      },
      "type": "Feature",
      "properties": {
        "hierarchy": [
          "tgn:2575507",
          "tgn:1000001",
          "tgn:2000464",
          "tgn:7012149",
          "tgn:7007250",
          "tgn:7029392"
        ],
        "placetype": [
          "aat:300008706"
        ],
        "id": 2575507,
        "name:xx": "Pepper Creek"
      }
    },
    {
      "geometry": {
        "type": "Point",
        "coordinates": [
          -114.1333,
          45.0167
        ]
      },
      "type": "Feature",
      "properties": {
        "hierarchy": [
          "tgn:2575508",
          "tgn:1000001",
          "tgn:7012149",
          "tgn:2000481",
          "tgn:7007250",
          "tgn:7029392"
        ],
        "placetype": [
          "aat:300008706"
        ],
        "id": 2575508,
        "name:xx": "Pepper Creek"
      }
    },
    {
      "geometry": {
        "type": "Point",
        "coordinates": [
          -115.3667,
          44.9
        ]
      },
      "type": "Feature",
      "properties": {
        "hierarchy": [
          "tgn:2575509",
          "tgn:1000001",
          "tgn:7012149",
          "tgn:2000494",
          "tgn:7007250",
          "tgn:7029392"
        ],
        "placetype": [
          "aat:300008706"
        ],
        "id": 2575509,
        "name:xx": "Pepper Creek"
      }
    }
  ]
}
