{
  "geometry": {
    "type": "Point",
    "coordinates": [
      -82.5667,
      32.7167
    ]
  },
  "type": "Feature",
  "properties": {
    "hierarchy": [
      "tgn:2335631",
      "tgn:1000001",
      "tgn:7012149",
      "tgn:2000369",
      "tgn:7007248",
      "tgn:7029392"
    ],
    "placetype": [
      "aat:300006191"
    ],
    "id": 2335631,
    "name:xx": "Fortner Pond"
  }
}
