{
  "geometry": {
    "type": "Point",
    "coordinates": [
      -96.5333,
      31.7333
    ]
  },
  "type": "Feature",
  "properties": {
    "hierarchy": [
      "tgn:2107971",
      "tgn:1000001",
      "tgn:7012149",
      "tgn:1002597",
      "tgn:7007826",
      "tgn:7029392"
    ],
    "placetype": [
      "aat:300008347"
    ],
    "id": 2107971,
    "name:xx": "Tehuacana"
  }
}
