{
  "type": "FeatureCollection",
  "features": [
    {
      "geometry": {
        "type": "Point",
        "coordinates": [
          -98.1,
          25.6
        ]
      },
      "type": "Feature",
      "properties": {
        "hierarchy": [
          "tgn:7381430",
          "tgn:1000001",
          "tgn:7005597",
          "tgn:7005560",
          "tgn:7029392"
        ],
        "placetype": [
          "aat:300008347"
        ],
        "id": 7381430,
        "name:xx": "Los Mirasoles"
      }
    },
    {
      "geometry": {
        "type": "Point",
        "coordinates": [
          -105.783333,
          25.85
        ]
      },
      "type": "Feature",
      "properties": {
        "hierarchy": [
          "tgn:7381431",
          "tgn:7005583",
          "tgn:1000001",
          "tgn:7005560",
          "tgn:7029392"
        ],
        "placetype": [
          "aat:300008795"
        ],
        "id": 7381431,
        "name:xx": "Los Minbres, Sierra de"
      }
    },
    {
      "geometry": {
        "type": "Point",
        "coordinates": [
          -107.433333,
          25.333333
        ]
      },
      "type": "Feature",
      "properties": {
        "hierarchy": [
          "tgn:7381432",
          "tgn:1000001",
          "tgn:7005595",
          "tgn:7005560",
          "tgn:7029392"
        ],
        "placetype": [
          "aat:300000241"
        ],
        "id": 7381432,
        "name:xx": "Rancho Los Mimbres"
      }
    },
    {
      "geometry": {
        "type": "Point",
        "coordinates": [
          -99.421389,
          24.097222
        ]
      },
      "type": "Feature",
      "properties": {
        "hierarchy": [
          "tgn:7381433",
          "tgn:1000001",
          "tgn:7005597",
          "tgn:7005560",
          "tgn:7029392"
        ],
        "placetype": [
          "aat:300008763"
        ],
        "id": 7381433,
        "name:xx": "Los Mimbres, Cañón de"
      }
    },
    {
      "geometry": {
        "type": "Point",
        "coordinates": [
          -109.616667,
          29.583333
        ]
      },
      "type": "Feature",
      "properties": {
        "hierarchy": [
          "tgn:7381434",
          "tgn:1000001",
          "tgn:1001960",
          "tgn:7005560",
          "tgn:7029392"
        ],
        "placetype": [
          "aat:300266554",
          "aat:300008699"
        ],
        "id": 7381434,
        "name:xx": "Los Mimbres, Arroyo"
      }
    },
    {
      "geometry": {
        "type": "Point",
        "coordinates": [
          -109.183333,
          27.416667
        ]
      },
      "type": "Feature",
      "properties": {
        "hierarchy": [
          "tgn:7381435",
          "tgn:1000001",
          "tgn:1001960",
          "tgn:7005560",
          "tgn:7029392"
        ],
        "placetype": [
          "aat:300266554",
          "aat:300008699"
        ],
        "id": 7381435,
        "name:xx": "Los Mimbres, Arroyo"
      }
    },
    {
      "geometry": {
        "type": "Point",
        "coordinates": [
          -99.483333,
          23.45
        ]
      },
      "type": "Feature",
      "properties": {
        "hierarchy": [
          "tgn:7381436",
          "tgn:1000001",
          "tgn:7005597",
          "tgn:7005560",
          "tgn:7029392"
        ],
        "placetype": [
          "aat:300008699"
        ],
        "id": 7381436,
        "name:xx": "Los Mimbres"
      }
    },
    {
      "geometry": {
        "type": "Point",
        "coordinates": [
          -100.25,
          24.966667
        ]
      },
      "type": "Feature",
      "properties": {
        "hierarchy": [
          "tgn:7381437",
          "tgn:1000001",
          "tgn:7005589",
          "tgn:7005560",
          "tgn:7029392"
        ],
        "placetype": [
          "aat:300008347"
        ],
        "id": 7381437,
        "name:xx": "Los Mimbres"
      }
    },
    {
      "geometry": {
        "type": "Point",
        "coordinates": [
          -106.953611,
          24.635833
        ]
      },
      "type": "Feature",
      "properties": {
        "hierarchy": [
          "tgn:7381438",
          "tgn:1000001",
          "tgn:7005595",
          "tgn:7005560",
          "tgn:7029392"
        ],
        "placetype": [
          "aat:300008347"
        ],
        "id": 7381438,
        "name:xx": "Los Mimbres"
      }
    },
    {
      "geometry": {
        "type": "Point",
        "coordinates": [
          -99.533333,
          24.566667
        ]
      },
      "type": "Feature",
      "properties": {
        "hierarchy": [
          "tgn:7381439",
          "tgn:1000001",
          "tgn:7005597",
          "tgn:7005560",
          "tgn:7029392"
        ],
        "placetype": [
          "aat:300008347"
        ],
        "id": 7381439,
        "name:xx": "Los Mimbres"
      }
    }
  ]
}
