{
  "type": "FeatureCollection",
  "features": [
    {
      "geometry": {
        "type": "Point",
        "coordinates": [
          -98.1833,
          39.9667
        ]
      },
      "type": "Feature",
      "properties": {
        "hierarchy": [
          "tgn:2712720",
          "tgn:1000001",
          "tgn:2000704",
          "tgn:7012149",
          "tgn:7007254",
          "tgn:7029392"
        ],
        "placetype": [
          "aat:300008706"
        ],
        "id": 2712720,
        "name:xx": "Taylor Creek"
      }
    },
    {
      "geometry": {
        "type": "Point",
        "coordinates": [
          -96.1,
          38.5167
        ]
      },
      "type": "Feature",
      "properties": {
        "hierarchy": [
          "tgn:2712721",
          "tgn:1000001",
          "tgn:7012149",
          "tgn:2000715",
          "tgn:7007254",
          "tgn:7029392"
        ],
        "placetype": [
          "aat:300008706"
        ],
        "id": 2712721,
        "name:xx": "Taylor Creek"
      }
    },
    {
      "geometry": {
        "type": "Point",
        "coordinates": [
          -88.05,
          36.8667
        ]
      },
      "type": "Feature",
      "properties": {
        "hierarchy": [
          "tgn:2712722",
          "tgn:1000001",
          "tgn:7012149",
          "tgn:2000846",
          "tgn:7007255",
          "tgn:7029392"
        ],
        "placetype": [
          "aat:300008706"
        ],
        "id": 2712722,
        "name:xx": "Taylor Creek"
      }
    },
    {
      "geometry": {
        "type": "Point",
        "coordinates": [
          -88.2833,
          36.9667
        ]
      },
      "type": "Feature",
      "properties": {
        "hierarchy": [
          "tgn:2712723",
          "tgn:1000001",
          "tgn:7012149",
          "tgn:2000823",
          "tgn:7007255",
          "tgn:7029392"
        ],
        "placetype": [
          "aat:300008706"
        ],
        "id": 2712723,
        "name:xx": "Taylor Creek"
      }
    },
    {
      "geometry": {
        "type": "Point",
        "coordinates": [
          -85.5333,
          38.4167
        ]
      },
      "type": "Feature",
      "properties": {
        "hierarchy": [
          "tgn:2712724",
          "tgn:1000001",
          "tgn:7012149",
          "tgn:1002744",
          "tgn:7007255",
          "tgn:7029392"
        ],
        "placetype": [
          "aat:300008706"
        ],
        "id": 2712724,
        "name:xx": "Taylor Creek"
      }
    },
    {
      "geometry": {
        "type": "Point",
        "coordinates": [
          -84.8167,
          39.05
        ]
      },
      "type": "Feature",
      "properties": {
        "hierarchy": [
          "tgn:2712725",
          "tgn:1000001",
          "tgn:1002189",
          "tgn:7012149",
          "tgn:7007255",
          "tgn:7029392"
        ],
        "placetype": [
          "aat:300008706"
        ],
        "id": 2712725,
        "name:xx": "Taylor Creek"
      }
    },
    {
      "geometry": {
        "type": "Point",
        "coordinates": [
          -90.3,
          30.8
        ]
      },
      "type": "Feature",
      "properties": {
        "hierarchy": [
          "tgn:2712726",
          "tgn:1000001",
          "tgn:7012149",
          "tgn:7007256",
          "tgn:7029392"
        ],
        "placetype": [
          "aat:300008706"
        ],
        "id": 2712726,
        "name:xx": "Taylor Creek"
      }
    },
    {
      "geometry": {
        "type": "Point",
        "coordinates": [
          -90.6,
          30.9
        ]
      },
      "type": "Feature",
      "properties": {
        "hierarchy": [
          "tgn:2712727",
          "tgn:1000001",
          "tgn:7012149",
          "tgn:2000899",
          "tgn:7007256",
          "tgn:7029392"
        ],
        "placetype": [
          "aat:300008706"
        ],
        "id": 2712727,
        "name:xx": "Taylor Creek"
      }
    },
    {
      "geometry": {
        "type": "Point",
        "coordinates": [
          -85.2167,
          44.2667
        ]
      },
      "type": "Feature",
      "properties": {
        "hierarchy": [
          "tgn:2712728",
          "tgn:1000001",
          "tgn:7012149",
          "tgn:2000980",
          "tgn:7007520",
          "tgn:7029392"
        ],
        "placetype": [
          "aat:300008706"
        ],
        "id": 2712728,
        "name:xx": "Taylor Creek"
      }
    },
    {
      "geometry": {
        "type": "Point",
        "coordinates": [
          -85.25,
          44.65
        ]
      },
      "type": "Feature",
      "properties": {
        "hierarchy": [
          "tgn:2712729",
          "tgn:1000001",
          "tgn:7012149",
          "tgn:7007520",
          "tgn:7029392"
        ],
        "placetype": [
          "aat:300008706"
        ],
        "id": 2712729,
        "name:xx": "Taylor Creek"
      }
    }
  ]
}
