{
  "geometry": {
    "type": "Point",
    "coordinates": [
      -119.3667,
      43.4833
    ]
  },
  "type": "Feature",
  "properties": {
    "hierarchy": [
      "tgn:2624327",
      "tgn:1000001",
      "tgn:7012149",
      "tgn:2001709",
      "tgn:7007708",
      "tgn:7029392"
    ],
    "placetype": [
      "aat:300008680"
    ],
    "id": 2624327,
    "name:xx": "Rock Lake"
  }
}
