{
  "geometry": {
    "type": "Point",
    "coordinates": [
      -90.5167,
      44.3333
    ]
  },
  "type": "Feature",
  "properties": {
    "hierarchy": [
      "tgn:2425182",
      "tgn:1000001",
      "tgn:7012149",
      "tgn:2002328",
      "tgn:7007922",
      "tgn:7029392"
    ],
    "placetype": [
      "aat:300008905"
    ],
    "id": 2425182,
    "name:xx": "Johnson Marsh"
  }
}
