{
  "type": "FeatureCollection",
  "features": [
    {
      "geometry": {
        "type": "Point",
        "coordinates": [
          3.919637,
          50.619637
        ]
      },
      "type": "Feature",
      "properties": {
        "hierarchy": [
          "tgn:7237680",
          "tgn:7007877",
          "tgn:1000003",
          "tgn:1000063",
          "tgn:4012014",
          "tgn:7029392"
        ],
        "placetype": [
          "aat:300008347"
        ],
        "id": 7237680,
        "name:xx": "Fouleng"
      }
    },
    {
      "geometry": {
        "type": "Point",
        "coordinates": [
          5.7,
          49.666667
        ]
      },
      "type": "Feature",
      "properties": {
        "hierarchy": [
          "tgn:7237682",
          "tgn:7003465",
          "tgn:1000003",
          "tgn:1000063",
          "tgn:4012014",
          "tgn:7029392"
        ],
        "placetype": [
          "aat:300008863"
        ],
        "id": 7237682,
        "name:xx": "Fouches, Bois de"
      }
    },
    {
      "geometry": {
        "type": "Point",
        "coordinates": [
          5.716667,
          49.7
        ]
      },
      "type": "Feature",
      "properties": {
        "hierarchy": [
          "tgn:7237683",
          "tgn:7003465",
          "tgn:1000003",
          "tgn:1000063",
          "tgn:4012014",
          "tgn:7029392"
        ],
        "placetype": [
          "aat:300008347"
        ],
        "id": 7237683,
        "name:xx": "Fouches"
      }
    },
    {
      "geometry": {
        "type": "Point",
        "coordinates": [
          3.713493,
          50.634664
        ]
      },
      "type": "Feature",
      "properties": {
        "hierarchy": [
          "tgn:7237684",
          "tgn:7007877",
          "tgn:1000003",
          "tgn:1000063",
          "tgn:4012014",
          "tgn:7029392"
        ],
        "placetype": [
          "aat:300008347"
        ],
        "id": 7237684,
        "name:xx": "Foucaumont"
      }
    },
    {
      "geometry": {
        "type": "Point",
        "coordinates": [
          3.470421,
          50.54236
        ]
      },
      "type": "Feature",
      "properties": {
        "hierarchy": [
          "tgn:7237685",
          "tgn:7007877",
          "tgn:1000003",
          "tgn:1000063",
          "tgn:4012014",
          "tgn:7029392"
        ],
        "placetype": [
          "aat:300008863"
        ],
        "id": 7237685,
        "name:xx": "Fouages, Bois de"
      }
    },
    {
      "geometry": {
        "type": "Point",
        "coordinates": [
          4.5,
          50.6
        ]
      },
      "type": "Feature",
      "properties": {
        "hierarchy": [
          "tgn:7237686",
          "tgn:7018238",
          "tgn:1000003",
          "tgn:1000063",
          "tgn:4012014",
          "tgn:7029392"
        ],
        "placetype": [
          "aat:300008347"
        ],
        "id": 7237686,
        "name:xx": "Fosty"
      }
    },
    {
      "geometry": {
        "type": "Point",
        "coordinates": [
          4.030952,
          50.612827
        ]
      },
      "type": "Feature",
      "properties": {
        "hierarchy": [
          "tgn:7237687",
          "tgn:7007877",
          "tgn:1000003",
          "tgn:1000063",
          "tgn:4012014",
          "tgn:7029392"
        ],
        "placetype": [
          "aat:300008347"
        ],
        "id": 7237687,
        "name:xx": "Fostrée"
      }
    },
    {
      "geometry": {
        "type": "Point",
        "coordinates": [
          4.25,
          50.3
        ]
      },
      "type": "Feature",
      "properties": {
        "hierarchy": [
          "tgn:7237688",
          "tgn:7007877",
          "tgn:1000003",
          "tgn:1000063",
          "tgn:4012014",
          "tgn:7029392"
        ],
        "placetype": [
          "aat:300005567"
        ],
        "id": 7237688,
        "name:xx": "Château de Fosteau"
      }
    },
    {
      "geometry": {
        "type": "Point",
        "coordinates": [
          4.3,
          50.316667
        ]
      },
      "type": "Feature",
      "properties": {
        "hierarchy": [
          "tgn:7237689",
          "tgn:7007877",
          "tgn:1000003",
          "tgn:1000063",
          "tgn:4012014",
          "tgn:7029392"
        ],
        "placetype": [
          "aat:300008347"
        ],
        "id": 7237689,
        "name:xx": "Fostaille"
      }
    }
  ]
}
