{
  "type": "FeatureCollection",
  "features": [
    {
      "geometry": {
        "type": "Point",
        "coordinates": [
          4.189324,
          50.542242
        ]
      },
      "type": "Feature",
      "properties": {
        "hierarchy": [
          "tgn:7242843",
          "tgn:7007877",
          "tgn:1000003",
          "tgn:1000063",
          "tgn:4012014",
          "tgn:7029392"
        ],
        "placetype": [
          "aat:300008347"
        ],
        "id": 7242843,
        "name:xx": "Loussérie"
      }
    },
    {
      "geometry": {
        "type": "Point",
        "coordinates": [
          4.466667,
          50.716667
        ]
      },
      "type": "Feature",
      "properties": {
        "hierarchy": [
          "tgn:7242844",
          "tgn:7018238",
          "tgn:1000003",
          "tgn:1000063",
          "tgn:4012014",
          "tgn:7029392"
        ],
        "placetype": [
          "aat:300000206"
        ],
        "id": 7242844,
        "name:xx": "Ferme des Loups"
      }
    },
    {
      "geometry": {
        "type": "Point",
        "coordinates": [
          3.643432,
          50.771225
        ]
      },
      "type": "Feature",
      "properties": {
        "hierarchy": [
          "tgn:7242847",
          "tgn:7003457",
          "tgn:1000003",
          "tgn:1000063",
          "tgn:7018236",
          "tgn:7029392"
        ],
        "placetype": [
          "aat:300008347"
        ],
        "id": 7242847,
        "name:xx": "Louise Marie"
      }
    },
    {
      "geometry": {
        "type": "Point",
        "coordinates": [
          5.633333,
          49.783333
        ]
      },
      "type": "Feature",
      "properties": {
        "hierarchy": [
          "tgn:7242848",
          "tgn:7003465",
          "tgn:1000003",
          "tgn:1000063",
          "tgn:4012014",
          "tgn:7029392"
        ],
        "placetype": [
          "aat:300008347"
        ],
        "id": 7242848,
        "name:xx": "Louftémont"
      }
    },
    {
      "geometry": {
        "type": "Point",
        "coordinates": [
          4.9,
          49.966667
        ]
      },
      "type": "Feature",
      "properties": {
        "hierarchy": [
          "tgn:7242849",
          "tgn:7003466",
          "tgn:1000003",
          "tgn:1000063",
          "tgn:4012014",
          "tgn:7029392"
        ],
        "placetype": [
          "aat:300008863"
        ],
        "id": 7242849,
        "name:xx": "Louette-Saint-Pierre, Bois de"
      }
    }
  ]
}
