{
  "geometry": {
    "type": "Point",
    "coordinates": [
      -115.8333,
      39.3833
    ]
  },
  "type": "Feature",
  "properties": {
    "hierarchy": [
      "tgn:2249295",
      "tgn:1000001",
      "tgn:7012149",
      "tgn:2001420",
      "tgn:7007526",
      "tgn:7029392"
    ],
    "placetype": [
      "aat:300000390"
    ],
    "id": 2249295,
    "name:xx": "Cole and Johnson Mine"
  }
}
