{
  "geometry": {
    "type": "Point",
    "coordinates": [
      30.4333,
      50.3333
    ]
  },
  "type": "Feature",
  "properties": {
    "hierarchy": [
      "tgn:1052863",
      "tgn:1000003",
      "tgn:7011661",
      "tgn:7006660",
      "tgn:7029392"
    ],
    "placetype": [
      "aat:300008347"
    ],
    "id": 1052863,
    "name:xx": "Boyarka"
  }
}
