{
  "geometry": {
    "type": "Point",
    "coordinates": [
      -100.0167,
      32.95
    ]
  },
  "type": "Feature",
  "properties": {
    "hierarchy": [
      "tgn:2570192",
      "tgn:1000001",
      "tgn:7012149",
      "tgn:2002014",
      "tgn:7007826",
      "tgn:7029392"
    ],
    "placetype": [
      "aat:300008347"
    ],
    "id": 2570192,
    "name:xx": "Pastura"
  }
}
