{
  "geometry": {
    "type": "Point",
    "coordinates": [
      -80.55,
      27.7667
    ]
  },
  "type": "Feature",
  "properties": {
    "hierarchy": [
      "tgn:2196926",
      "tgn:1000001",
      "tgn:1002500",
      "tgn:7012149",
      "tgn:7007240",
      "tgn:7029392"
    ],
    "placetype": [
      "aat:300008347"
    ],
    "id": 2196926,
    "name:xx": "Brookside"
  }
}
