{
  "geometry": {
    "type": "Point",
    "coordinates": [
      16.8333,
      53.8833
    ]
  },
  "type": "Feature",
  "properties": {
    "hierarchy": [
      "tgn:1048921",
      "tgn:1000003",
      "tgn:7024114",
      "tgn:7006366",
      "tgn:7029392"
    ],
    "placetype": [
      "aat:300008347"
    ],
    "id": 1048921,
    "name:xx": "Biały Bór"
  }
}
