{
  "geometry": {
    "type": "Point",
    "coordinates": [
      34.617827,
      24.419751
    ]
  },
  "type": "Feature",
  "properties": {
    "hierarchy": [
      "tgn:7533315",
      "tgn:7001242",
      "tgn:7001311",
      "tgn:7016833",
      "tgn:7029392"
    ],
    "placetype": [
      "aat:300379998"
    ],
    "name:en": "Ḩalūz, Wādī",
    "id": 7533315
  }
}
