{
  "geometry": {
    "type": "Point",
    "coordinates": [
      74.825,
      32.877778
    ]
  },
  "type": "Feature",
  "properties": {
    "hierarchy": [
      "tgn:7592792",
      "tgn:1000004",
      "tgn:7000198",
      "tgn:7000799",
      "tgn:7029392"
    ],
    "placetype": [
      "aat:300008347"
    ],
    "name:en": "Nadhuwāl",
    "id": 7592792
  }
}
