{
  "geometry": {
    "type": "Point",
    "coordinates": [
      -74.7333,
      43.0167
    ]
  },
  "type": "Feature",
  "properties": {
    "hierarchy": [
      "tgn:2305508",
      "tgn:1000001",
      "tgn:7012149",
      "tgn:7007568",
      "tgn:7029392"
    ],
    "placetype": [
      "aat:300006191"
    ],
    "id": 2305508,
    "name:xx": "East Canada Lake"
  }
}
