{
  "geometry": {
    "type": "Point",
    "coordinates": [
      -4.2833,
      50.8167
    ]
  },
  "type": "Feature",
  "properties": {
    "hierarchy": [
      "tgn:7025511",
      "tgn:7002445",
      "tgn:1000003",
      "tgn:7012077",
      "tgn:7008591",
      "tgn:7029392"
    ],
    "placetype": [
      "aat:300008347"
    ],
    "id": 7025511,
    "name:xx": "Cookbury Wick"
  }
}
