{
  "geometry": {
    "type": "Point",
    "coordinates": [
      -123.35,
      40.3333
    ]
  },
  "type": "Feature",
  "properties": {
    "hierarchy": [
      "tgn:2579591",
      "tgn:1000001",
      "tgn:7012149",
      "tgn:7007157",
      "tgn:2000191",
      "tgn:7029392"
    ],
    "placetype": [
      "aat:300008798"
    ],
    "id": 2579591,
    "name:xx": "Pickett Peak"
  }
}
