{
  "geometry": {
    "type": "Point",
    "coordinates": [
      -122.9167,
      45.0167
    ]
  },
  "type": "Feature",
  "properties": {
    "hierarchy": [
      "tgn:2480090",
      "tgn:1000001",
      "tgn:7012149",
      "tgn:1002636",
      "tgn:7007708",
      "tgn:7029392"
    ],
    "placetype": [
      "aat:300006075"
    ],
    "id": 2480090,
    "name:xx": "Lake Labish Ditch"
  }
}
