{
  "geometry": {
    "type": "Point",
    "coordinates": [
      -76.65,
      39.4333
    ]
  },
  "type": "Feature",
  "properties": {
    "hierarchy": [
      "tgn:2355296",
      "tgn:7016099",
      "tgn:1000001",
      "tgn:7012149",
      "tgn:7007516",
      "tgn:7029392"
    ],
    "placetype": [
      "aat:300008699"
    ],
    "id": 2355296,
    "name:xx": "Goodwin Run"
  }
}
