{
  "type": "FeatureCollection",
  "features": [
    {
      "geometry": {
        "type": "Point",
        "coordinates": [
          -68.933333,
          -26.016667
        ]
      },
      "type": "Feature",
      "properties": {
        "hierarchy": [
          "tgn:7319310",
          "tgn:1001630",
          "tgn:1000049",
          "tgn:1000002",
          "tgn:7029392"
        ],
        "placetype": [
          "aat:300008795"
        ],
        "id": 7319310,
        "name:xx": "Anaranjado, Cerro"
      }
    },
    {
      "geometry": {
        "type": "Point",
        "coordinates": [
          -69.4,
          -18.566667
        ]
      },
      "type": "Feature",
      "properties": {
        "hierarchy": [
          "tgn:7319311",
          "tgn:7002464",
          "tgn:1000049",
          "tgn:1000002",
          "tgn:7029392"
        ],
        "placetype": [
          "aat:300008795"
        ],
        "id": 7319311,
        "name:xx": "Anarabe, Cerro"
      }
    },
    {
      "geometry": {
        "type": "Point",
        "coordinates": [
          -69.35,
          -17.733333
        ]
      },
      "type": "Feature",
      "properties": {
        "hierarchy": [
          "tgn:7319312",
          "tgn:7002464",
          "tgn:1000049",
          "tgn:1000002",
          "tgn:7029392"
        ],
        "placetype": [
          "aat:300008347"
        ],
        "id": 7319312,
        "name:xx": "Anantocollo"
      }
    },
    {
      "geometry": {
        "type": "Point",
        "coordinates": [
          -74.7,
          -45.466667
        ]
      },
      "type": "Feature",
      "properties": {
        "hierarchy": [
          "tgn:7319313",
          "tgn:1001623",
          "tgn:1000049",
          "tgn:1000002",
          "tgn:7029392"
        ],
        "placetype": [
          "aat:300008791"
        ],
        "id": 7319313,
        "name:xx": "Analao, Isla"
      }
    },
    {
      "geometry": {
        "type": "Point",
        "coordinates": [
          -68.666667,
          -19.6
        ]
      },
      "type": "Feature",
      "properties": {
        "hierarchy": [
          "tgn:7319315",
          "tgn:7002464",
          "tgn:1000049",
          "tgn:1000002",
          "tgn:7029392"
        ],
        "placetype": [
          "aat:300008347"
        ],
        "id": 7319315,
        "name:xx": "Añaguani"
      }
    },
    {
      "geometry": {
        "type": "Point",
        "coordinates": [
          -69.3,
          -18.9
        ]
      },
      "type": "Feature",
      "properties": {
        "hierarchy": [
          "tgn:7319316",
          "tgn:7002464",
          "tgn:1000049",
          "tgn:1000002",
          "tgn:7029392"
        ],
        "placetype": [
          "aat:300008795"
        ],
        "id": 7319316,
        "name:xx": "Anacopata, Cerro"
      }
    },
    {
      "geometry": {
        "type": "Point",
        "coordinates": [
          -71.016667,
          -27.333333
        ]
      },
      "type": "Feature",
      "properties": {
        "hierarchy": [
          "tgn:7319317",
          "tgn:1001630",
          "tgn:1000049",
          "tgn:1000002",
          "tgn:7029392"
        ],
        "placetype": [
          "aat:300011692"
        ],
        "id": 7319317,
        "name:xx": "Anacachi, Roca"
      }
    },
    {
      "geometry": {
        "type": "Point",
        "coordinates": [
          -75.316667,
          -50
        ]
      },
      "type": "Feature",
      "properties": {
        "hierarchy": [
          "tgn:7319318",
          "tgn:1001702",
          "tgn:1000049",
          "tgn:1000002",
          "tgn:7029392"
        ],
        "placetype": [
          "aat:300011692"
        ],
        "id": 7319318,
        "name:xx": "Ana, Rompiente"
      }
    },
    {
      "geometry": {
        "type": "Point",
        "coordinates": [
          -69.8,
          -53.666667
        ]
      },
      "type": "Feature",
      "properties": {
        "hierarchy": [
          "tgn:7319319",
          "tgn:1001702",
          "tgn:1000049",
          "tgn:1000002",
          "tgn:7029392"
        ],
        "placetype": [
          "aat:300008699"
        ],
        "id": 7319319,
        "name:xx": "Ana, Río"
      }
    }
  ]
}
