{
  "geometry": {
    "type": "Point",
    "coordinates": [
      -98.8833,
      32.7667
    ]
  },
  "type": "Feature",
  "properties": {
    "hierarchy": [
      "tgn:2292270",
      "tgn:1000001",
      "tgn:7012149",
      "tgn:2002076",
      "tgn:7007826",
      "tgn:7029392"
    ],
    "placetype": [
      "aat:300008798"
    ],
    "id": 2292270,
    "name:xx": "Donkey Mountain"
  }
}
