{
  "geometry": {
    "type": "Point",
    "coordinates": [
      -116.8167,
      34.75
    ]
  },
  "type": "Feature",
  "properties": {
    "hierarchy": [
      "tgn:2273985",
      "tgn:1000001",
      "tgn:7012149",
      "tgn:7007157",
      "tgn:1002857",
      "tgn:7029392"
    ],
    "placetype": [
      "aat:300008699"
    ],
    "id": 2273985,
    "name:xx": "Daggett Wash"
  }
}
