{
  "geometry": {
    "type": "Point",
    "coordinates": [
      -74.3833,
      40.9667
    ]
  },
  "type": "Feature",
  "properties": {
    "hierarchy": [
      "tgn:2624453",
      "tgn:1000001",
      "tgn:1002695",
      "tgn:7012149",
      "tgn:7007565",
      "tgn:7029392"
    ],
    "placetype": [
      "aat:300008798"
    ],
    "id": 2624453,
    "name:xx": "Rock Peon Mountain"
  }
}
