{
  "type": "FeatureCollection",
  "features": [
    {
      "geometry": {
        "type": "Point",
        "coordinates": [
          -91.05,
          40.7333
        ]
      },
      "type": "Feature",
      "properties": {
        "hierarchy": [
          "tgn:2026870",
          "tgn:1000001",
          "tgn:7012149",
          "tgn:2000510",
          "tgn:7007251",
          "tgn:7029392"
        ],
        "placetype": [
          "aat:300008347"
        ],
        "id": 2026870,
        "name:xx": "Carman"
      }
    },
    {
      "geometry": {
        "type": "Point",
        "coordinates": [
          -88.15,
          38.0833
        ]
      },
      "type": "Feature",
      "properties": {
        "hierarchy": [
          "tgn:2026871",
          "tgn:1000001",
          "tgn:7012149",
          "tgn:2000537",
          "tgn:7007251",
          "tgn:7029392"
        ],
        "placetype": [
          "aat:300008347"
        ],
        "id": 2026871,
        "name:xx": "Carmi"
      }
    },
    {
      "geometry": {
        "type": "Point",
        "coordinates": [
          -88.1333,
          41.9
        ]
      },
      "type": "Feature",
      "properties": {
        "hierarchy": [
          "tgn:2026872",
          "tgn:1000001",
          "tgn:7019013",
          "tgn:7012149",
          "tgn:7007251",
          "tgn:7029392"
        ],
        "placetype": [
          "aat:300008347"
        ],
        "id": 2026872,
        "name:xx": "Carol Stream"
      }
    },
    {
      "geometry": {
        "type": "Point",
        "coordinates": [
          -89.8833,
          38.8833
        ]
      },
      "type": "Feature",
      "properties": {
        "hierarchy": [
          "tgn:2026879",
          "tgn:1000001",
          "tgn:7012149",
          "tgn:1002622",
          "tgn:7007251",
          "tgn:7029392"
        ],
        "placetype": [
          "aat:300008347"
        ],
        "id": 2026879,
        "name:xx": "Carpenter"
      }
    }
  ]
}
