{
  "geometry": {
    "type": "Point",
    "coordinates": [
      -109.7167,
      32.5667
    ]
  },
  "type": "Feature",
  "properties": {
    "hierarchy": [
      "tgn:2349595",
      "tgn:1000001",
      "tgn:7006451",
      "tgn:2000094",
      "tgn:7012149",
      "tgn:7029392"
    ],
    "placetype": [
      "aat:300008798"
    ],
    "id": 2349595,
    "name:xx": "Gillespie Mountain"
  }
}
