{
  "type": "FeatureCollection",
  "features": [
    {
      "geometry": {
        "type": "Point",
        "coordinates": [
          10.45,
          53.816667
        ]
      },
      "type": "Feature",
      "properties": {
        "hierarchy": [
          "tgn:7065220",
          "tgn:1000003",
          "tgn:7003688",
          "tgn:7000084",
          "tgn:7029392"
        ],
        "placetype": [
          "aat:300000206"
        ],
        "id": 7065220,
        "name:xx": "Kaffee Hof"
      }
    },
    {
      "geometry": {
        "type": "Point",
        "coordinates": [
          10.45,
          52.316667
        ]
      },
      "type": "Feature",
      "properties": {
        "hierarchy": [
          "tgn:7065221",
          "tgn:1000003",
          "tgn:7003676",
          "tgn:7000084",
          "tgn:7029392"
        ],
        "placetype": [
          "aat:300000206"
        ],
        "id": 7065221,
        "name:xx": "Steinhof"
      }
    },
    {
      "geometry": {
        "type": "Point",
        "coordinates": [
          7.85,
          51.816667
        ]
      },
      "type": "Feature",
      "properties": {
        "hierarchy": [
          "tgn:7065222",
          "tgn:1000003",
          "tgn:7003677",
          "tgn:7000084",
          "tgn:7029392"
        ],
        "placetype": [
          "aat:300000206"
        ],
        "id": 7065222,
        "name:xx": "Steinhof"
      }
    },
    {
      "geometry": {
        "type": "Point",
        "coordinates": [
          7.95,
          51.733333
        ]
      },
      "type": "Feature",
      "properties": {
        "hierarchy": [
          "tgn:7065223",
          "tgn:1000003",
          "tgn:7003677",
          "tgn:7000084",
          "tgn:7029392"
        ],
        "placetype": [
          "aat:300000206"
        ],
        "id": 7065223,
        "name:xx": "Steinhof"
      }
    },
    {
      "geometry": {
        "type": "Point",
        "coordinates": [
          10.816667,
          49.3
        ]
      },
      "type": "Feature",
      "properties": {
        "hierarchy": [
          "tgn:7065224",
          "tgn:7003669",
          "tgn:1000003",
          "tgn:7000084",
          "tgn:7029392"
        ],
        "placetype": [
          "aat:300000206"
        ],
        "id": 7065224,
        "name:xx": "Steinhof"
      }
    },
    {
      "geometry": {
        "type": "Point",
        "coordinates": [
          12.1,
          49.183333
        ]
      },
      "type": "Feature",
      "properties": {
        "hierarchy": [
          "tgn:7065225",
          "tgn:7003669",
          "tgn:1000003",
          "tgn:7000084",
          "tgn:7029392"
        ],
        "placetype": [
          "aat:300000206"
        ],
        "id": 7065225,
        "name:xx": "Steinhof"
      }
    },
    {
      "geometry": {
        "type": "Point",
        "coordinates": [
          12.266667,
          49.166667
        ]
      },
      "type": "Feature",
      "properties": {
        "hierarchy": [
          "tgn:7065226",
          "tgn:7003669",
          "tgn:1000003",
          "tgn:7000084",
          "tgn:7029392"
        ],
        "placetype": [
          "aat:300000206"
        ],
        "id": 7065226,
        "name:xx": "Steinhof"
      }
    },
    {
      "geometry": {
        "type": "Point",
        "coordinates": [
          12.45,
          49.15
        ]
      },
      "type": "Feature",
      "properties": {
        "hierarchy": [
          "tgn:7065227",
          "tgn:7003669",
          "tgn:1000003",
          "tgn:7000084",
          "tgn:7029392"
        ],
        "placetype": [
          "aat:300000206"
        ],
        "id": 7065227,
        "name:xx": "Steinhof"
      }
    },
    {
      "geometry": {
        "type": "Point",
        "coordinates": [
          12.033333,
          49.066667
        ]
      },
      "type": "Feature",
      "properties": {
        "hierarchy": [
          "tgn:7065228",
          "tgn:7003669",
          "tgn:1000003",
          "tgn:7000084",
          "tgn:7029392"
        ],
        "placetype": [
          "aat:300000206"
        ],
        "id": 7065228,
        "name:xx": "Steinhof"
      }
    },
    {
      "geometry": {
        "type": "Point",
        "coordinates": [
          13.25,
          48.766667
        ]
      },
      "type": "Feature",
      "properties": {
        "hierarchy": [
          "tgn:7065229",
          "tgn:7003669",
          "tgn:1000003",
          "tgn:7000084",
          "tgn:7029392"
        ],
        "placetype": [
          "aat:300000206"
        ],
        "id": 7065229,
        "name:xx": "Steinhof"
      }
    }
  ]
}
