{
  "geometry": {
    "type": "Point",
    "coordinates": [
      -97.7833,
      31.85
    ]
  },
  "type": "Feature",
  "properties": {
    "hierarchy": [
      "tgn:2694883",
      "tgn:1000001",
      "tgn:1002191",
      "tgn:7012149",
      "tgn:7007826",
      "tgn:7029392"
    ],
    "placetype": [
      "aat:300008761"
    ],
    "id": 2694883,
    "name:xx": "Stiffy Hollow"
  }
}
