{
  "geometry": {
    "type": "Point",
    "coordinates": [
      -80.1167,
      25.85
    ]
  },
  "type": "Feature",
  "properties": {
    "hierarchy": [
      "tgn:2568589",
      "tgn:1000001",
      "tgn:7012149",
      "tgn:1002314",
      "tgn:7007240",
      "tgn:7029392"
    ],
    "placetype": [
      "aat:300008791"
    ],
    "id": 2568589,
    "name:xx": "Park View Island"
  }
}
