{
  "geometry": {
    "type": "Point",
    "coordinates": [
      -85.4167,
      31.6167
    ]
  },
  "type": "Feature",
  "properties": {
    "hierarchy": [
      "tgn:2481183",
      "tgn:7002659",
      "tgn:1000001",
      "tgn:7012149",
      "tgn:7029392"
    ],
    "placetype": [
      "aat:300008699"
    ],
    "id": 2481183,
    "name:xx": "Lambert Branch"
  }
}
