{
  "geometry": {
    "type": "Point",
    "coordinates": [
      76.114444,
      28.028889
    ]
  },
  "type": "Feature",
  "properties": {
    "hierarchy": [
      "tgn:7567335",
      "tgn:1000004",
      "tgn:1001871",
      "tgn:7000198",
      "tgn:7029392"
    ],
    "placetype": [
      "aat:300008347"
    ],
    "name:en": "Lāl Pahāri",
    "id": 7567335
  }
}
