{
  "geometry": {
    "type": "Point",
    "coordinates": [
      -80.9667,
      34.5667
    ]
  },
  "type": "Feature",
  "properties": {
    "hierarchy": [
      "tgn:2214538",
      "tgn:1000001",
      "tgn:2001736",
      "tgn:7012149",
      "tgn:7007712",
      "tgn:7029392"
    ],
    "placetype": [
      "aat:300008347"
    ],
    "id": 2214538,
    "name:xx": "Caldwell Crossroad"
  }
}
