{
  "geometry": {
    "type": "Point",
    "coordinates": [
      -86.0167,
      37.6167
    ]
  },
  "type": "Feature",
  "properties": {
    "hierarchy": [
      "tgn:2693703",
      "tgn:1000001",
      "tgn:7012149",
      "tgn:2000796",
      "tgn:7007255",
      "tgn:7029392"
    ],
    "placetype": [
      "aat:300006191"
    ],
    "id": 2693703,
    "name:xx": "Stephensburg Lake"
  }
}
