{
  "geometry": {
    "type": "Point",
    "coordinates": [
      -109.5167,
      43.4833
    ]
  },
  "type": "Feature",
  "properties": {
    "hierarchy": [
      "tgn:2286494",
      "tgn:1000001",
      "tgn:7012149",
      "tgn:2002371",
      "tgn:7007923",
      "tgn:7029392"
    ],
    "placetype": [
      "aat:300006075"
    ],
    "id": 2286494,
    "name:xx": "Diamond Ditch"
  }
}
