{
  "geometry": {
    "type": "Point",
    "coordinates": [
      -115.8667,
      44.4167
    ]
  },
  "type": "Feature",
  "properties": {
    "hierarchy": [
      "tgn:2367380",
      "tgn:1000001",
      "tgn:7012149",
      "tgn:2000494",
      "tgn:7007250",
      "tgn:7029392"
    ],
    "placetype": [
      "aat:300008706"
    ],
    "id": 2367380,
    "name:xx": "Ground Hog Creek"
  }
}
