{
  "type": "FeatureCollection",
  "features": [
    {
      "geometry": {
        "type": "Point",
        "coordinates": [
          -0.85,
          53.8
        ]
      },
      "type": "Feature",
      "properties": {
        "hierarchy": [
          "tgn:7029360",
          "tgn:7002445",
          "tgn:1000003",
          "tgn:7019057",
          "tgn:7008591",
          "tgn:7029392"
        ],
        "placetype": [
          "aat:300008347",
          "aat:300008372"
        ],
        "name:en": "Spaldington",
        "id": 7029360
      }
    },
    {
      "geometry": {
        "type": "Point",
        "coordinates": [
          -0.233333,
          54.15
        ]
      },
      "type": "Feature",
      "properties": {
        "hierarchy": [
          "tgn:7029361",
          "tgn:7002445",
          "tgn:1000003",
          "tgn:7008166",
          "tgn:7008591",
          "tgn:7029392"
        ],
        "placetype": [
          "aat:300008347",
          "aat:300008372"
        ],
        "id": 7029361,
        "name:xx": "Speeton"
      }
    },
    {
      "geometry": {
        "type": "Point",
        "coordinates": [
          -0.183333,
          53.783333
        ]
      },
      "type": "Feature",
      "properties": {
        "hierarchy": [
          "tgn:7029362",
          "tgn:7002445",
          "tgn:1000003",
          "tgn:7019057",
          "tgn:7008591",
          "tgn:7029392"
        ],
        "placetype": [
          "aat:300008347",
          "aat:300008372"
        ],
        "name:en": "Sproatley",
        "id": 7029362
      }
    },
    {
      "geometry": {
        "type": "Point",
        "coordinates": [
          -0.44,
          54.2
        ]
      },
      "type": "Feature",
      "properties": {
        "hierarchy": [
          "tgn:7029363",
          "tgn:7002445",
          "tgn:1000003",
          "tgn:7008166",
          "tgn:7008591",
          "tgn:7029392"
        ],
        "placetype": [
          "aat:300008347",
          "aat:300019279",
          "aat:300008372"
        ],
        "id": 7029363,
        "name:xx": "Staxton"
      }
    },
    {
      "geometry": {
        "type": "Point",
        "coordinates": [
          -171.0833,
          -3.1333
        ]
      },
      "type": "Feature",
      "properties": {
        "hierarchy": [
          "tgn:7029365",
          "tgn:1010215",
          "tgn:1000217",
          "tgn:1000006",
          "tgn:7029392"
        ],
        "placetype": [
          "aat:300008793"
        ],
        "id": 7029365,
        "name:xx": "Enderbury Atoll"
      }
    },
    {
      "geometry": {
        "type": "Point",
        "coordinates": [
          -171.6667,
          -2.8333
        ]
      },
      "type": "Feature",
      "properties": {
        "hierarchy": [
          "tgn:7029366",
          "tgn:1010215",
          "tgn:1000217",
          "tgn:1000006",
          "tgn:7029392"
        ],
        "placetype": [
          "aat:300008791",
          "aat:300387275"
        ],
        "id": 7029366,
        "name:xx": "Kanton"
      }
    }
  ]
}
