{
  "type": "FeatureCollection",
  "features": [
    {
      "geometry": {
        "type": "Point",
        "coordinates": [
          -112.05,
          40.85
        ]
      },
      "type": "Feature",
      "properties": {
        "hierarchy": [
          "tgn:2261980",
          "tgn:1000001",
          "tgn:7012149",
          "tgn:2002118",
          "tgn:7007827",
          "tgn:7029392"
        ],
        "placetype": [
          "aat:300008798"
        ],
        "id": 2261980,
        "name:xx": "Cow Bay Knoll"
      }
    },
    {
      "geometry": {
        "type": "Point",
        "coordinates": [
          -90.7167,
          34.8667
        ]
      },
      "type": "Feature",
      "properties": {
        "hierarchy": [
          "tgn:2261981",
          "tgn:1000001",
          "tgn:7016172",
          "tgn:7012149",
          "tgn:2000143",
          "tgn:7029392"
        ],
        "placetype": [
          "aat:300008699"
        ],
        "id": 2261981,
        "name:xx": "Cow Bayou"
      }
    },
    {
      "geometry": {
        "type": "Point",
        "coordinates": [
          -93.7167,
          31.9667
        ]
      },
      "type": "Feature",
      "properties": {
        "hierarchy": [
          "tgn:2261982",
          "tgn:1000001",
          "tgn:7012149",
          "tgn:7007256",
          "tgn:7029392"
        ],
        "placetype": [
          "aat:300008699"
        ],
        "id": 2261982,
        "name:xx": "Cow Bayou"
      }
    },
    {
      "geometry": {
        "type": "Point",
        "coordinates": [
          -91.5167,
          30.15
        ]
      },
      "type": "Feature",
      "properties": {
        "hierarchy": [
          "tgn:2261983",
          "tgn:1000001",
          "tgn:7012149",
          "tgn:2000903",
          "tgn:7007256",
          "tgn:7029392"
        ],
        "placetype": [
          "aat:300008699"
        ],
        "id": 2261983,
        "name:xx": "Cow Bayou"
      }
    },
    {
      "geometry": {
        "type": "Point",
        "coordinates": [
          -91.5833,
          30.2667
        ]
      },
      "type": "Feature",
      "properties": {
        "hierarchy": [
          "tgn:2261984",
          "tgn:1000001",
          "tgn:7012149",
          "tgn:2000877",
          "tgn:7007256",
          "tgn:7029392"
        ],
        "placetype": [
          "aat:300008699"
        ],
        "id": 2261984,
        "name:xx": "Cow Bayou"
      }
    },
    {
      "geometry": {
        "type": "Point",
        "coordinates": [
          -92.9,
          30.4333
        ]
      },
      "type": "Feature",
      "properties": {
        "hierarchy": [
          "tgn:2261985",
          "tgn:1000001",
          "tgn:7012149",
          "tgn:2000880",
          "tgn:7007256",
          "tgn:7029392"
        ],
        "placetype": [
          "aat:300008699"
        ],
        "id": 2261985,
        "name:xx": "Cow Bayou"
      }
    },
    {
      "geometry": {
        "type": "Point",
        "coordinates": [
          -89.8167,
          30.6
        ]
      },
      "type": "Feature",
      "properties": {
        "hierarchy": [
          "tgn:2261986",
          "tgn:1000001",
          "tgn:7012149",
          "tgn:2000905",
          "tgn:7007256",
          "tgn:7029392"
        ],
        "placetype": [
          "aat:300008699"
        ],
        "id": 2261986,
        "name:xx": "Cow Bayou"
      }
    },
    {
      "geometry": {
        "type": "Point",
        "coordinates": [
          -91.85,
          30.7167
        ]
      },
      "type": "Feature",
      "properties": {
        "hierarchy": [
          "tgn:2261987",
          "tgn:1000001",
          "tgn:7012149",
          "tgn:2000902",
          "tgn:7007256",
          "tgn:7029392"
        ],
        "placetype": [
          "aat:300008699"
        ],
        "id": 2261987,
        "name:xx": "Cow Bayou"
      }
    },
    {
      "geometry": {
        "type": "Point",
        "coordinates": [
          -91.45,
          32.4833
        ]
      },
      "type": "Feature",
      "properties": {
        "hierarchy": [
          "tgn:2261988",
          "tgn:1000001",
          "tgn:7012149",
          "tgn:2000886",
          "tgn:7007256",
          "tgn:7029392"
        ],
        "placetype": [
          "aat:300008699"
        ],
        "id": 2261988,
        "name:xx": "Cow Bayou"
      }
    },
    {
      "geometry": {
        "type": "Point",
        "coordinates": [
          -91.7,
          32.5833
        ]
      },
      "type": "Feature",
      "properties": {
        "hierarchy": [
          "tgn:2261989",
          "tgn:1000001",
          "tgn:7012149",
          "tgn:2000895",
          "tgn:7007256",
          "tgn:7029392"
        ],
        "placetype": [
          "aat:300008699"
        ],
        "id": 2261989,
        "name:xx": "Cow Bayou"
      }
    }
  ]
}
