{
  "geometry": {
    "type": "Point",
    "coordinates": [
      26.077947,
      28.87452
    ]
  },
  "type": "Feature",
  "properties": {
    "hierarchy": [
      "tgn:7523462",
      "tgn:7001242",
      "tgn:7016833",
      "tgn:1001418",
      "tgn:7029392"
    ],
    "placetype": [
      "aat:300008777"
    ],
    "name:en": "Duyūr, Qārat ad",
    "id": 7523462
  }
}
