{
  "geometry": {
    "type": "Point",
    "coordinates": [
      -113.7333,
      46.3833
    ]
  },
  "type": "Feature",
  "properties": {
    "hierarchy": [
      "tgn:2566459",
      "tgn:1000001",
      "tgn:7012149",
      "tgn:2001279",
      "tgn:7007524",
      "tgn:7029392"
    ],
    "placetype": [
      "aat:300008761"
    ],
    "id": 2566459,
    "name:xx": "Palouse Gulch"
  }
}
