{
  "geometry": {
    "type": "Point",
    "coordinates": [
      121.4333,
      42.0667
    ]
  },
  "type": "Feature",
  "properties": {
    "hierarchy": [
      "tgn:1070986",
      "tgn:1000004",
      "tgn:1001390",
      "tgn:1000111",
      "tgn:7029392"
    ],
    "placetype": [
      "aat:300008347"
    ],
    "id": 1070986,
    "name:xx": "Qianyamen"
  }
}
