{
  "geometry": {
    "type": "Point",
    "coordinates": [
      78.546111,
      17.769444
    ]
  },
  "type": "Feature",
  "properties": {
    "hierarchy": [
      "tgn:7567480",
      "tgn:1001828",
      "tgn:1000004",
      "tgn:7000198",
      "tgn:7029392"
    ],
    "placetype": [
      "aat:300008347"
    ],
    "name:en": "Minājīpet",
    "id": 7567480
  }
}
