{
  "geometry": {
    "type": "Point",
    "coordinates": [
      -84.1667,
      34.0833
    ]
  },
  "type": "Feature",
  "properties": {
    "hierarchy": [
      "tgn:2022275",
      "tgn:1000001",
      "tgn:7012149",
      "tgn:2000349",
      "tgn:7007248",
      "tgn:7029392"
    ],
    "placetype": [
      "aat:300008347",
      "aat:300387210"
    ],
    "id": 2022275,
    "name:xx": "Brookwood"
  }
}
