{
  "geometry": {
    "type": "Point",
    "coordinates": [
      -121.6667,
      38.6667
    ]
  },
  "type": "Feature",
  "properties": {
    "hierarchy": [
      "tgn:2010813",
      "tgn:1000001",
      "tgn:7012149",
      "tgn:7007157",
      "tgn:1003046",
      "tgn:7029392"
    ],
    "placetype": [
      "aat:300387016"
    ],
    "id": 2010813,
    "name:xx": "Conaway"
  }
}
