{
  "geometry": {
    "type": "Point",
    "coordinates": [
      -108.4667,
      37.7667
    ]
  },
  "type": "Feature",
  "properties": {
    "hierarchy": [
      "tgn:2465498",
      "tgn:1000001",
      "tgn:7012149",
      "tgn:2000208",
      "tgn:7007158",
      "tgn:7029392"
    ],
    "placetype": [
      "aat:300008697"
    ],
    "id": 2465498,
    "name:xx": "Lone Mesa Spring Number 1"
  }
}
