{
  "type": "FeatureCollection",
  "features": [
    {
      "geometry": {
        "type": "Point",
        "coordinates": [
          7.166667,
          50.933333
        ]
      },
      "type": "Feature",
      "properties": {
        "hierarchy": [
          "tgn:7162170",
          "tgn:1000003",
          "tgn:7003677",
          "tgn:7000084",
          "tgn:7029392"
        ],
        "placetype": [
          "aat:300008347"
        ],
        "id": 7162170,
        "name:xx": "Holzmarkt"
      }
    },
    {
      "geometry": {
        "type": "Point",
        "coordinates": [
          11.75,
          48.65
        ]
      },
      "type": "Feature",
      "properties": {
        "hierarchy": [
          "tgn:7162171",
          "tgn:7003669",
          "tgn:1000003",
          "tgn:7000084",
          "tgn:7029392"
        ],
        "placetype": [
          "aat:300008347"
        ],
        "id": 7162171,
        "name:xx": "Holzmannshausen"
      }
    },
    {
      "geometry": {
        "type": "Point",
        "coordinates": [
          10.566667,
          47.7
        ]
      },
      "type": "Feature",
      "properties": {
        "hierarchy": [
          "tgn:7162172",
          "tgn:7003669",
          "tgn:1000003",
          "tgn:7000084",
          "tgn:7029392"
        ],
        "placetype": [
          "aat:300008347"
        ],
        "id": 7162172,
        "name:xx": "Holzmanns"
      }
    },
    {
      "geometry": {
        "type": "Point",
        "coordinates": [
          12.2,
          47.75
        ]
      },
      "type": "Feature",
      "properties": {
        "hierarchy": [
          "tgn:7162173",
          "tgn:7003669",
          "tgn:1000003",
          "tgn:7000084",
          "tgn:7029392"
        ],
        "placetype": [
          "aat:300008347"
        ],
        "id": 7162173,
        "name:xx": "Holzmann"
      }
    },
    {
      "geometry": {
        "type": "Point",
        "coordinates": [
          12.916667,
          48.616667
        ]
      },
      "type": "Feature",
      "properties": {
        "hierarchy": [
          "tgn:7162174",
          "tgn:7003669",
          "tgn:1000003",
          "tgn:7000084",
          "tgn:7029392"
        ],
        "placetype": [
          "aat:300000206"
        ],
        "id": 7162174,
        "name:xx": "Holzmann"
      }
    },
    {
      "geometry": {
        "type": "Point",
        "coordinates": [
          12.5,
          48.55
        ]
      },
      "type": "Feature",
      "properties": {
        "hierarchy": [
          "tgn:7162175",
          "tgn:7003669",
          "tgn:1000003",
          "tgn:7000084",
          "tgn:7029392"
        ],
        "placetype": [
          "aat:300000206"
        ],
        "id": 7162175,
        "name:xx": "Holzmann"
      }
    },
    {
      "geometry": {
        "type": "Point",
        "coordinates": [
          12.883333,
          48.533333
        ]
      },
      "type": "Feature",
      "properties": {
        "hierarchy": [
          "tgn:7162176",
          "tgn:7003669",
          "tgn:1000003",
          "tgn:7000084",
          "tgn:7029392"
        ],
        "placetype": [
          "aat:300000206"
        ],
        "id": 7162176,
        "name:xx": "Holzmann"
      }
    },
    {
      "geometry": {
        "type": "Point",
        "coordinates": [
          12.716667,
          48.516667
        ]
      },
      "type": "Feature",
      "properties": {
        "hierarchy": [
          "tgn:7162177",
          "tgn:7003669",
          "tgn:1000003",
          "tgn:7000084",
          "tgn:7029392"
        ],
        "placetype": [
          "aat:300000206"
        ],
        "id": 7162177,
        "name:xx": "Holzmann"
      }
    },
    {
      "geometry": {
        "type": "Point",
        "coordinates": [
          12.783333,
          48.25
        ]
      },
      "type": "Feature",
      "properties": {
        "hierarchy": [
          "tgn:7162178",
          "tgn:7003669",
          "tgn:1000003",
          "tgn:7000084",
          "tgn:7029392"
        ],
        "placetype": [
          "aat:300000206"
        ],
        "id": 7162178,
        "name:xx": "Holzmann"
      }
    },
    {
      "geometry": {
        "type": "Point",
        "coordinates": [
          12.483333,
          48.15
        ]
      },
      "type": "Feature",
      "properties": {
        "hierarchy": [
          "tgn:7162179",
          "tgn:7003669",
          "tgn:1000003",
          "tgn:7000084",
          "tgn:7029392"
        ],
        "placetype": [
          "aat:300000206"
        ],
        "id": 7162179,
        "name:xx": "Holzmann"
      }
    }
  ]
}
