{
  "type": "FeatureCollection",
  "features": [
    {
      "geometry": {
        "type": "Point",
        "coordinates": [
          -3.733333,
          38.833333
        ]
      },
      "type": "Feature",
      "properties": {
        "hierarchy": [
          "tgn:7335270",
          "tgn:7002816",
          "tgn:1001647",
          "tgn:1000003",
          "tgn:1000095",
          "tgn:7029392"
        ],
        "placetype": [
          "aat:300008777"
        ],
        "id": 7335270,
        "name:xx": "Gordo, Cerro"
      }
    },
    {
      "geometry": {
        "type": "Point",
        "coordinates": [
          -4.666667,
          38.083333
        ]
      },
      "type": "Feature",
      "properties": {
        "hierarchy": [
          "tgn:7335271",
          "tgn:7002758",
          "tgn:7002817",
          "tgn:1000003",
          "tgn:1000095",
          "tgn:7029392"
        ],
        "placetype": [
          "aat:300008777"
        ],
        "id": 7335271,
        "name:xx": "Gordo, Cerro"
      }
    },
    {
      "geometry": {
        "type": "Point",
        "coordinates": [
          -5.333333,
          37.35
        ]
      },
      "type": "Feature",
      "properties": {
        "hierarchy": [
          "tgn:7335272",
          "tgn:7002758",
          "tgn:7002841",
          "tgn:1000003",
          "tgn:1000095",
          "tgn:7029392"
        ],
        "placetype": [
          "aat:300008777"
        ],
        "id": 7335272,
        "name:xx": "Gordo, Cerro"
      }
    },
    {
      "geometry": {
        "type": "Point",
        "coordinates": [
          -6.016667,
          37.05
        ]
      },
      "type": "Feature",
      "properties": {
        "hierarchy": [
          "tgn:7335273",
          "tgn:7002758",
          "tgn:7002841",
          "tgn:1000003",
          "tgn:1000095",
          "tgn:7029392"
        ],
        "placetype": [
          "aat:300387088"
        ],
        "id": 7335273,
        "name:xx": "Gordo, Caño"
      }
    },
    {
      "geometry": {
        "type": "Point",
        "coordinates": [
          -6.2,
          36.916667
        ]
      },
      "type": "Feature",
      "properties": {
        "hierarchy": [
          "tgn:7335274",
          "tgn:7002758",
          "tgn:7002841",
          "tgn:1000003",
          "tgn:1000095",
          "tgn:7029392"
        ],
        "placetype": [
          "aat:300387088"
        ],
        "id": 7335274,
        "name:xx": "Gordo, Caño"
      }
    },
    {
      "geometry": {
        "type": "Point",
        "coordinates": [
          -0.9,
          37.8
        ]
      },
      "type": "Feature",
      "properties": {
        "hierarchy": [
          "tgn:7335275",
          "tgn:1001439",
          "tgn:1000003",
          "tgn:7002797",
          "tgn:1000095",
          "tgn:7029392"
        ],
        "placetype": [
          "aat:300266640"
        ],
        "id": 7335275,
        "name:xx": "Gordo, Cabezo"
      }
    },
    {
      "geometry": {
        "type": "Point",
        "coordinates": [
          -2.25,
          39.833333
        ]
      },
      "type": "Feature",
      "properties": {
        "hierarchy": [
          "tgn:7335276",
          "tgn:7002818",
          "tgn:1001647",
          "tgn:1000003",
          "tgn:1000095",
          "tgn:7029392"
        ],
        "placetype": [
          "aat:300008777"
        ],
        "id": 7335276,
        "name:xx": "Gordo, Cabezo"
      }
    },
    {
      "geometry": {
        "type": "Point",
        "coordinates": [
          -7.2,
          37.316667
        ]
      },
      "type": "Feature",
      "properties": {
        "hierarchy": [
          "tgn:7335277",
          "tgn:7002758",
          "tgn:7002823",
          "tgn:1000003",
          "tgn:1000095",
          "tgn:7029392"
        ],
        "placetype": [
          "aat:300008699"
        ],
        "id": 7335277,
        "name:xx": "Gordo, Arroyo"
      }
    },
    {
      "geometry": {
        "type": "Point",
        "coordinates": [
          -3.066667,
          43.183333
        ]
      },
      "type": "Feature",
      "properties": {
        "hierarchy": [
          "tgn:7335278",
          "tgn:7002849",
          "tgn:1000003",
          "tgn:7009604",
          "tgn:1000095",
          "tgn:7029392"
        ],
        "placetype": [
          "aat:300387173"
        ],
        "id": 7335278,
        "name:xx": "Gordejuela"
      }
    },
    {
      "geometry": {
        "type": "Point",
        "coordinates": [
          -17.983333,
          28.75
        ]
      },
      "type": "Feature",
      "properties": {
        "hierarchy": [
          "tgn:7335279",
          "tgn:7002836",
          "tgn:7016622",
          "tgn:1000003",
          "tgn:1000095",
          "tgn:7029392"
        ],
        "placetype": [
          "aat:300011692"
        ],
        "id": 7335279,
        "name:xx": "Gordas, Rocas"
      }
    }
  ]
}
