{
  "geometry": {
    "type": "Point",
    "coordinates": [
      -110.9833,
      48.8833
    ]
  },
  "type": "Feature",
  "properties": {
    "hierarchy": [
      "tgn:2156369",
      "tgn:1000001",
      "tgn:7012149",
      "tgn:2001285",
      "tgn:7007524",
      "tgn:7029392"
    ],
    "placetype": [
      "aat:300386845"
    ],
    "id": 2156369,
    "name:xx": "Bears Den"
  }
}
