{
  "geometry": {
    "type": "Point",
    "coordinates": [
      131.9833,
      47.25
    ]
  },
  "type": "Feature",
  "properties": {
    "hierarchy": [
      "tgn:1068109",
      "tgn:1000004",
      "tgn:1001290",
      "tgn:1000111",
      "tgn:7029392"
    ],
    "placetype": [
      "aat:300008347"
    ],
    "id": 1068109,
    "name:xx": "Fujin"
  }
}
