{
  "geometry": {
    "type": "Point",
    "coordinates": [
      -98.4833,
      30.1667
    ]
  },
  "type": "Feature",
  "properties": {
    "hierarchy": [
      "tgn:2307395",
      "tgn:1000001",
      "tgn:7012149",
      "tgn:7007826",
      "tgn:7029392"
    ],
    "placetype": [
      "aat:300008706"
    ],
    "id": 2307395,
    "name:xx": "East Fork Rocky Creek"
  }
}
