{
  "geometry": {
    "type": "Point",
    "coordinates": [
      -110.9167,
      43.1667
    ]
  },
  "type": "Feature",
  "properties": {
    "hierarchy": [
      "tgn:2586760",
      "tgn:1000001",
      "tgn:7012149",
      "tgn:2002376",
      "tgn:7007923",
      "tgn:7029392"
    ],
    "placetype": [
      "aat:300008706"
    ],
    "id": 2586760,
    "name:xx": "Placer Creek"
  }
}
