{
  "geometry": {
    "type": "Point",
    "coordinates": [
      -118.6833,
      38.0833
    ]
  },
  "type": "Feature",
  "properties": {
    "hierarchy": [
      "tgn:2407449",
      "tgn:1000001",
      "tgn:7012149",
      "tgn:7029392"
    ],
    "placetype": [
      "aat:300008706"
    ],
    "id": 2407449,
    "name:xx": "Huntoon Creek"
  }
}
