{
  "geometry": {
    "type": "Point",
    "coordinates": [
      -95.3667,
      32.4667
    ]
  },
  "type": "Feature",
  "properties": {
    "hierarchy": [
      "tgn:2253801",
      "tgn:1000001",
      "tgn:7012149",
      "tgn:1002898",
      "tgn:7007826",
      "tgn:7029392"
    ],
    "placetype": [
      "aat:300008706"
    ],
    "id": 2253801,
    "name:xx": "Cooks Creek"
  }
}
