{
  "geometry": {
    "type": "Point",
    "coordinates": [
      -109.3333,
      33.15
    ]
  },
  "type": "Feature",
  "properties": {
    "hierarchy": [
      "tgn:2437698",
      "tgn:1000001",
      "tgn:7006451",
      "tgn:2000095",
      "tgn:7012149",
      "tgn:7029392"
    ],
    "placetype": [
      "aat:300008706"
    ],
    "id": 2437698,
    "name:xx": "King Creek"
  }
}
