{
  "geometry": {
    "type": "Point",
    "coordinates": [
      51.65,
      56.55
    ]
  },
  "type": "Feature",
  "properties": {
    "hierarchy": [
      "tgn:1054254",
      "tgn:1000004",
      "tgn:7002435",
      "tgn:7011526",
      "tgn:7029392"
    ],
    "placetype": [
      "aat:300008347"
    ],
    "id": 1054254,
    "name:xx": "Gybdan"
  }
}
