{
  "geometry": {
    "type": "Point",
    "coordinates": [
      -111.1667,
      34.5333
    ]
  },
  "type": "Feature",
  "properties": {
    "hierarchy": [
      "tgn:2378908",
      "tgn:1000001",
      "tgn:7006451",
      "tgn:2000092",
      "tgn:7012149",
      "tgn:7029392"
    ],
    "placetype": [
      "aat:300008798"
    ],
    "id": 2378908,
    "name:xx": "Hart Point"
  }
}
