{
  "geometry": {
    "type": "Point",
    "coordinates": [
      -79.8333,
      35.0333
    ]
  },
  "type": "Feature",
  "properties": {
    "hierarchy": [
      "tgn:2534924",
      "tgn:1000001",
      "tgn:7012149",
      "tgn:7007709",
      "tgn:7029392"
    ],
    "placetype": [
      "aat:300008706"
    ],
    "id": 2534924,
    "name:xx": "Naked Creek"
  }
}
