{
  "geometry": {
    "type": "Point",
    "coordinates": [
      -119.7833,
      44.3333
    ]
  },
  "type": "Feature",
  "properties": {
    "hierarchy": [
      "tgn:2689342",
      "tgn:1000001",
      "tgn:7012149",
      "tgn:2001723",
      "tgn:7007708",
      "tgn:7029392"
    ],
    "placetype": [
      "aat:300008706"
    ],
    "id": 2689342,
    "name:xx": "Squaw Creek"
  }
}
