{
  "geometry": {
    "type": "Point",
    "coordinates": [
      -99.9333,
      29.4667
    ]
  },
  "type": "Feature",
  "properties": {
    "hierarchy": [
      "tgn:2708536",
      "tgn:1000001",
      "tgn:7012149",
      "tgn:2002087",
      "tgn:7007826",
      "tgn:7029392"
    ],
    "placetype": [
      "aat:300008798"
    ],
    "id": 2708536,
    "name:xx": "Sycamore Mountain"
  }
}
