{
  "geometry": {
    "type": "Point",
    "coordinates": [
      -114.95,
      41.7167
    ]
  },
  "type": "Feature",
  "properties": {
    "hierarchy": [
      "tgn:2445516",
      "tgn:1000001",
      "tgn:2001411",
      "tgn:7012149",
      "tgn:7007526",
      "tgn:7029392"
    ],
    "placetype": [
      "aat:300008697"
    ],
    "id": 2445516,
    "name:xx": "Leo Spring"
  }
}
