{
  "geometry": {
    "type": "Point",
    "coordinates": [
      -91.1667,
      43.25
    ]
  },
  "type": "Feature",
  "properties": {
    "hierarchy": [
      "tgn:2555986",
      "tgn:2000563",
      "tgn:1000001",
      "tgn:7012149",
      "tgn:7007253",
      "tgn:7029392"
    ],
    "placetype": [
      "aat:300008706"
    ],
    "id": 2555986,
    "name:xx": "Oil Spring Creek"
  }
}
