{
  "geometry": {
    "type": "Point",
    "coordinates": [
      104.9167,
      11.55
    ]
  },
  "type": "Feature",
  "properties": {
    "hierarchy": [
      "tgn:7018242",
      "tgn:1000004",
      "tgn:1000109",
      "tgn:7029392"
    ],
    "placetype": [
      "aat:300387064",
      "aat:300265612"
    ],
    "id": 7018242,
    "name:xx": "Phnum Pénh"
  }
}
