{
  "geometry": {
    "type": "Point",
    "coordinates": [
      -76.0833,
      35.65
    ]
  },
  "type": "Feature",
  "properties": {
    "hierarchy": [
      "tgn:2777465",
      "tgn:1000001",
      "tgn:7012149",
      "tgn:2001506",
      "tgn:7007709",
      "tgn:7029392"
    ],
    "placetype": [
      "aat:300132316"
    ],
    "id": 2777465,
    "name:xx": "Winn Bay"
  }
}
