{
  "geometry": {
    "type": "Point",
    "coordinates": [
      -124.6667,
      48.5667
    ]
  },
  "type": "Feature",
  "properties": {
    "hierarchy": [
      "tgn:1134976",
      "tgn:7005735",
      "tgn:7005685",
      "tgn:1000001",
      "tgn:7013409",
      "tgn:7029392"
    ],
    "placetype": [
      "aat:300008706"
    ],
    "id": 1134976,
    "name:xx": "Walbran Creek"
  }
}
