{
  "geometry": {
    "type": "Point",
    "coordinates": [
      -3.15,
      36.75
    ]
  },
  "type": "Feature",
  "properties": {
    "hierarchy": [
      "tgn:7334749",
      "tgn:7002758",
      "tgn:7002821",
      "tgn:1000003",
      "tgn:1000095",
      "tgn:7029392"
    ],
    "placetype": [
      "aat:300008347"
    ],
    "id": 7334749,
    "name:xx": "El Pozuelo"
  }
}
