{
  "geometry": {
    "type": "Point",
    "coordinates": [
      -111.2167,
      41.9167
    ]
  },
  "type": "Feature",
  "properties": {
    "hierarchy": [
      "tgn:2677841",
      "tgn:1000001",
      "tgn:7012149",
      "tgn:2002117",
      "tgn:7007827",
      "tgn:7029392"
    ],
    "placetype": [
      "aat:300006191"
    ],
    "id": 2677841,
    "name:xx": "South Eden Reservoir"
  }
}
