{
  "geometry": {
    "type": "Point",
    "coordinates": [
      -72.9333,
      44.1167
    ]
  },
  "type": "Feature",
  "properties": {
    "hierarchy": [
      "tgn:2125006",
      "tgn:2002130",
      "tgn:1000001",
      "tgn:7012149",
      "tgn:7007828",
      "tgn:7029392"
    ],
    "placetype": [
      "aat:300008798"
    ],
    "id": 2125006,
    "name:xx": "Abraham, Mount"
  }
}
