{
  "type": "FeatureCollection",
  "features": [
    {
      "geometry": {
        "type": "Point",
        "coordinates": [
          -80.9,
          39.4
        ]
      },
      "type": "Feature",
      "properties": {
        "hierarchy": [
          "tgn:2117371",
          "tgn:1000001",
          "tgn:7012149",
          "tgn:2002297",
          "tgn:7013961",
          "tgn:7029392"
        ],
        "placetype": [
          "aat:300008347",
          "aat:300387210"
        ],
        "id": 2117371,
        "name:xx": "Bearsville"
      }
    },
    {
      "geometry": {
        "type": "Point",
        "coordinates": [
          -81.1333,
          39.0833
        ]
      },
      "type": "Feature",
      "properties": {
        "hierarchy": [
          "tgn:2117373",
          "tgn:1000001",
          "tgn:7012149",
          "tgn:2002292",
          "tgn:7013961",
          "tgn:7029392"
        ],
        "placetype": [
          "aat:300008347",
          "aat:300387210"
        ],
        "id": 2117373,
        "name:xx": "Beatrice"
      }
    },
    {
      "geometry": {
        "type": "Point",
        "coordinates": [
          -81.1333,
          37.7333
        ]
      },
      "type": "Feature",
      "properties": {
        "hierarchy": [
          "tgn:2117375",
          "tgn:1000001",
          "tgn:7012149",
          "tgn:2002290",
          "tgn:7013961",
          "tgn:7029392"
        ],
        "placetype": [
          "aat:300008347"
        ],
        "id": 2117375,
        "name:xx": "Beaver"
      }
    },
    {
      "geometry": {
        "type": "Point",
        "coordinates": [
          -80.7167,
          39.65
        ]
      },
      "type": "Feature",
      "properties": {
        "hierarchy": [
          "tgn:2117376",
          "tgn:1000001",
          "tgn:7012149",
          "tgn:2002301",
          "tgn:7013961",
          "tgn:7029392"
        ],
        "placetype": [
          "aat:300008347",
          "aat:300387210"
        ],
        "id": 2117376,
        "name:xx": "Bebee"
      }
    },
    {
      "geometry": {
        "type": "Point",
        "coordinates": [
          -81.1833,
          37.7667
        ]
      },
      "type": "Feature",
      "properties": {
        "hierarchy": [
          "tgn:2117377",
          "tgn:1000001",
          "tgn:7012149",
          "tgn:2002290",
          "tgn:7013961",
          "tgn:7029392"
        ],
        "placetype": [
          "aat:300008347"
        ],
        "id": 2117377,
        "name:xx": "Beckley"
      }
    }
  ]
}
