{
  "geometry": {
    "type": "Point",
    "coordinates": [
      78.052373,
      27.59621
    ]
  },
  "type": "Feature",
  "properties": {
    "hierarchy": [
      "tgn:1075429",
      "tgn:1000004",
      "tgn:7000198",
      "tgn:7016722",
      "tgn:7029392"
    ],
    "placetype": [
      "aat:300008347"
    ],
    "name:en": "Hāthras",
    "id": 1075429
  }
}
