{
  "geometry": {
    "type": "Point",
    "coordinates": [
      -111.8667,
      34.0667
    ]
  },
  "type": "Feature",
  "properties": {
    "hierarchy": [
      "tgn:2259500",
      "tgn:1000001",
      "tgn:7006451",
      "tgn:7012149",
      "tgn:2000103",
      "tgn:7029392"
    ],
    "placetype": [
      "aat:300006191"
    ],
    "id": 2259500,
    "name:xx": "Cottonwood Tank"
  }
}
