{
  "geometry": {
    "type": "Point",
    "coordinates": [
      78.942225,
      27.301951
    ]
  },
  "type": "Feature",
  "properties": {
    "hierarchy": [
      "tgn:7588104",
      "tgn:1000004",
      "tgn:7000198",
      "tgn:7016722",
      "tgn:7029392"
    ],
    "placetype": [
      "aat:300008347"
    ],
    "name:en": "Khoriā",
    "id": 7588104
  }
}
