{
  "geometry": {
    "type": "Point",
    "coordinates": [
      -81.4167,
      29.8833
    ]
  },
  "type": "Feature",
  "properties": {
    "hierarchy": [
      "tgn:2000283",
      "tgn:1000001",
      "tgn:7012149",
      "tgn:7007240",
      "tgn:7029392"
    ],
    "placetype": [
      "aat:300387145",
      "aat:300000771"
    ],
    "id": 2000283,
    "name:xx": "Saint Johns"
  }
}
