{
  "geometry": {
    "type": "Point",
    "coordinates": [
      -93.8833,
      47.6667
    ]
  },
  "type": "Feature",
  "properties": {
    "hierarchy": [
      "tgn:2336676",
      "tgn:1000001",
      "tgn:7012149",
      "tgn:2001029",
      "tgn:7007521",
      "tgn:7029392"
    ],
    "placetype": [
      "aat:300008680"
    ],
    "id": 2336676,
    "name:xx": "Four Town Lake"
  }
}
