{
  "geometry": {
    "type": "Point",
    "coordinates": [
      31.909727,
      30.120812
    ]
  },
  "type": "Feature",
  "properties": {
    "hierarchy": [
      "tgn:7528321",
      "tgn:7001242",
      "tgn:7016833",
      "tgn:1001110",
      "tgn:7029392"
    ],
    "placetype": [
      "aat:300379998"
    ],
    "name:en": "Umm Jarfān, Wādī",
    "id": 7528321
  }
}
