{
  "geometry": {
    "type": "Point",
    "coordinates": [
      -90.3167,
      42.55
    ]
  },
  "type": "Feature",
  "properties": {
    "hierarchy": [
      "tgn:2319454",
      "tgn:1000001",
      "tgn:7012149",
      "tgn:2002332",
      "tgn:7007922",
      "tgn:7029392"
    ],
    "placetype": [
      "aat:300008347"
    ],
    "id": 2319454,
    "name:xx": "Etna"
  }
}
