{
  "geometry": {
    "type": "Point",
    "coordinates": [
      31.236062,
      30.028417
    ]
  },
  "type": "Feature",
  "properties": {
    "hierarchy": [
      "tgn:7533244",
      "tgn:7001242",
      "tgn:7016833",
      "tgn:1001091",
      "tgn:7029392"
    ],
    "placetype": [
      "aat:300007836"
    ],
    "id": 7533244,
    "name:xx": "K큰br카 Ab큰 ar R카sh"
  }
}
