{
  "geometry": {
    "type": "Point",
    "coordinates": [
      31.316667,
      30.866667
    ]
  },
  "type": "Feature",
  "properties": {
    "hierarchy": [
      "tgn:7529142",
      "tgn:7001242",
      "tgn:1001059",
      "tgn:7016833",
      "tgn:7029392"
    ],
    "placetype": [
      "aat:300005926"
    ],
    "name:en": "Manāmat Sīdī al Maghāribī",
    "id": 7529142
  }
}
