{
  "geometry": {
    "type": "Point",
    "coordinates": [
      -114.45,
      48.35
    ]
  },
  "type": "Feature",
  "properties": {
    "hierarchy": [
      "tgn:2375597",
      "tgn:1000001",
      "tgn:7012149",
      "tgn:2001274",
      "tgn:7007524",
      "tgn:7029392"
    ],
    "placetype": [
      "aat:300008680"
    ],
    "id": 2375597,
    "name:xx": "Hanson-Doyle Lake"
  }
}
