{
  "geometry": {
    "type": "Point",
    "coordinates": [
      -75.7833,
      40.35
    ]
  },
  "type": "Feature",
  "properties": {
    "hierarchy": [
      "tgn:2449092",
      "tgn:1000001",
      "tgn:7013387",
      "tgn:7012149",
      "tgn:7007710",
      "tgn:7029392"
    ],
    "placetype": [
      "aat:300008706"
    ],
    "id": 2449092,
    "name:xx": "Limekiln Creek"
  }
}
