{
  "geometry": {
    "type": "Point",
    "coordinates": [
      -110.4333,
      32.1667
    ]
  },
  "type": "Feature",
  "properties": {
    "hierarchy": [
      "tgn:2295622",
      "tgn:1000001",
      "tgn:7006451",
      "tgn:2000091",
      "tgn:7012149",
      "tgn:7029392"
    ],
    "placetype": [
      "aat:300008798"
    ],
    "id": 2295622,
    "name:xx": "Driscoll Mountain"
  }
}
