{
  "geometry": {
    "type": "Point",
    "coordinates": [
      70.497376,
      26.070952
    ]
  },
  "type": "Feature",
  "properties": {
    "hierarchy": [
      "tgn:7553460",
      "tgn:1000004",
      "tgn:7000198",
      "tgn:7016788",
      "tgn:7029392"
    ],
    "placetype": [
      "aat:300008347"
    ],
    "name:en": "Mūngiāsar",
    "id": 7553460
  }
}
