{
  "geometry": {
    "type": "Point",
    "coordinates": [
      108.35,
      37.4167
    ]
  },
  "type": "Feature",
  "properties": {
    "hierarchy": [
      "tgn:1069295",
      "tgn:1000004",
      "tgn:7002084",
      "tgn:1000111",
      "tgn:7029392"
    ],
    "placetype": [
      "aat:300008347"
    ],
    "id": 1069295,
    "name:xx": "Jingbian"
  }
}
