{
  "geometry": {
    "type": "Point",
    "coordinates": [
      -105.9833,
      39.9167
    ]
  },
  "type": "Feature",
  "properties": {
    "hierarchy": [
      "tgn:2664958",
      "tgn:1000001",
      "tgn:7012149",
      "tgn:2000216",
      "tgn:7007158",
      "tgn:7029392"
    ],
    "placetype": [
      "aat:300008706"
    ],
    "id": 2664958,
    "name:xx": "Simpson Creek"
  }
}
