{
  "geometry": {
    "type": "Point",
    "coordinates": [
      -88.0667,
      31.9333
    ]
  },
  "type": "Feature",
  "properties": {
    "hierarchy": [
      "tgn:2781734",
      "tgn:7002659",
      "tgn:1000001",
      "tgn:7012149",
      "tgn:7029392"
    ],
    "placetype": [
      "aat:300132348"
    ],
    "id": 2781734,
    "name:xx": "Woods Bluff Shoal"
  }
}
