{
  "geometry": {
    "type": "Point",
    "coordinates": [
      -83.8167,
      35.15
    ]
  },
  "type": "Feature",
  "properties": {
    "hierarchy": [
      "tgn:2247281",
      "tgn:1000001",
      "tgn:2001481",
      "tgn:7012149",
      "tgn:7007709",
      "tgn:7029392"
    ],
    "placetype": [
      "aat:300008699"
    ],
    "id": 2247281,
    "name:xx": "Coefield Branch"
  }
}
