{
  "type": "FeatureCollection",
  "features": [
    {
      "geometry": {
        "type": "Point",
        "coordinates": [
          -68.35,
          45.9
        ]
      },
      "type": "Feature",
      "properties": {
        "hierarchy": [
          "tgn:2187610",
          "tgn:2000919",
          "tgn:1000001",
          "tgn:7012149",
          "tgn:7007515",
          "tgn:7029392"
        ],
        "placetype": [
          "aat:300008699"
        ],
        "id": 2187610,
        "name:xx": "Boot Swamp Brook"
      }
    },
    {
      "geometry": {
        "type": "Point",
        "coordinates": [
          -111.3333,
          34.9667
        ]
      },
      "type": "Feature",
      "properties": {
        "hierarchy": [
          "tgn:2187611",
          "tgn:1000001",
          "tgn:7006451",
          "tgn:2000092",
          "tgn:7012149",
          "tgn:7029392"
        ],
        "placetype": [
          "aat:300006191"
        ],
        "id": 2187611,
        "name:xx": "Boot Tank"
      }
    },
    {
      "geometry": {
        "type": "Point",
        "coordinates": [
          -80.3,
          27.4667
        ]
      },
      "type": "Feature",
      "properties": {
        "hierarchy": [
          "tgn:2187612",
          "tgn:1000001",
          "tgn:7012149",
          "tgn:7016124",
          "tgn:7007240",
          "tgn:7029392"
        ],
        "placetype": [
          "aat:300008850"
        ],
        "id": 2187612,
        "name:xx": "Boot Toe Point"
      }
    },
    {
      "geometry": {
        "type": "Point",
        "coordinates": [
          -122.1833,
          46.2
        ]
      },
      "type": "Feature",
      "properties": {
        "hierarchy": [
          "tgn:2187613",
          "tgn:1000001",
          "tgn:7012149",
          "tgn:1002897",
          "tgn:7007920",
          "tgn:7029392"
        ],
        "placetype": [
          "aat:300266640"
        ],
        "id": 2187613,
        "name:xx": "Boot, The"
      }
    },
    {
      "geometry": {
        "type": "Point",
        "coordinates": [
          -121,
          45.05
        ]
      },
      "type": "Feature",
      "properties": {
        "hierarchy": [
          "tgn:2187614",
          "tgn:1000001",
          "tgn:7012149",
          "tgn:1002990",
          "tgn:7007708",
          "tgn:7029392"
        ],
        "placetype": [
          "aat:300008706"
        ],
        "id": 2187614,
        "name:xx": "Booten Creek"
      }
    },
    {
      "geometry": {
        "type": "Point",
        "coordinates": [
          -82.3,
          38.35
        ]
      },
      "type": "Feature",
      "properties": {
        "hierarchy": [
          "tgn:2187615",
          "tgn:1000001",
          "tgn:2002257",
          "tgn:7012149",
          "tgn:7013961",
          "tgn:7029392"
        ],
        "placetype": [
          "aat:300008706"
        ],
        "id": 2187615,
        "name:xx": "Booten Creek"
      }
    },
    {
      "geometry": {
        "type": "Point",
        "coordinates": [
          -78.4167,
          38.4333
        ]
      },
      "type": "Feature",
      "properties": {
        "hierarchy": [
          "tgn:2187616",
          "tgn:1000001",
          "tgn:7012149",
          "tgn:7007919",
          "tgn:7029392"
        ],
        "placetype": [
          "aat:300008699"
        ],
        "id": 2187616,
        "name:xx": "Bootens Run"
      }
    },
    {
      "geometry": {
        "type": "Point",
        "coordinates": [
          -83.6167,
          37.6833
        ]
      },
      "type": "Feature",
      "properties": {
        "hierarchy": [
          "tgn:2187617",
          "tgn:1000001",
          "tgn:7012149",
          "tgn:2000853",
          "tgn:7007255",
          "tgn:7029392"
        ],
        "placetype": [
          "aat:300008347"
        ],
        "id": 2187617,
        "name:xx": "Booth"
      }
    },
    {
      "geometry": {
        "type": "Point",
        "coordinates": [
          -85.75,
          37.8
        ]
      },
      "type": "Feature",
      "properties": {
        "hierarchy": [
          "tgn:2187618",
          "tgn:1000001",
          "tgn:7012149",
          "tgn:2000796",
          "tgn:7007255",
          "tgn:7029392"
        ],
        "placetype": [
          "aat:300008347"
        ],
        "id": 2187618,
        "name:xx": "Booth"
      }
    },
    {
      "geometry": {
        "type": "Point",
        "coordinates": [
          -90.9167,
          32.95
        ]
      },
      "type": "Feature",
      "properties": {
        "hierarchy": [
          "tgn:2187619",
          "tgn:1000001",
          "tgn:7012149",
          "tgn:2001113",
          "tgn:7007522",
          "tgn:7029392"
        ],
        "placetype": [
          "aat:300008347"
        ],
        "id": 2187619,
        "name:xx": "Booth"
      }
    }
  ]
}
