{
  "geometry": {
    "type": "Point",
    "coordinates": [
      -120.0667,
      37.4667
    ]
  },
  "type": "Feature",
  "properties": {
    "hierarchy": [
      "tgn:1134079",
      "tgn:1000001",
      "tgn:7012149",
      "tgn:7007157",
      "tgn:7029392"
    ],
    "placetype": [
      "aat:300008706"
    ],
    "id": 1134079,
    "name:xx": "Owens Creek"
  }
}
