{
  "geometry": {
    "type": "Point",
    "coordinates": [
      -112.2667,
      34.0333
    ]
  },
  "type": "Feature",
  "properties": {
    "hierarchy": [
      "tgn:2731534",
      "tgn:1000001",
      "tgn:7006451",
      "tgn:7012149",
      "tgn:2000103",
      "tgn:7029392"
    ],
    "placetype": [
      "aat:300008706"
    ],
    "id": 2731534,
    "name:xx": "Tule Creek"
  }
}
