{
  "geometry": {
    "type": "Point",
    "coordinates": [
      -117.8333,
      45.8833
    ]
  },
  "type": "Feature",
  "properties": {
    "hierarchy": [
      "tgn:2259661",
      "tgn:1000001",
      "tgn:7012149",
      "tgn:2001722",
      "tgn:7007708",
      "tgn:7029392"
    ],
    "placetype": [
      "aat:300008761"
    ],
    "id": 2259661,
    "name:xx": "Cougar Canyon"
  }
}
