{
  "type": "FeatureCollection",
  "features": [
    {
      "geometry": {
        "type": "Point",
        "coordinates": [
          -7.463,
          40.767
        ]
      },
      "type": "Feature",
      "properties": {
        "hierarchy": [
          "tgn:6001164",
          "tgn:7003823",
          "tgn:1000003",
          "tgn:1000090",
          "tgn:7029392"
        ],
        "placetype": [
          "aat:300008347",
          "aat:300008375",
          "aat:300387005"
        ],
        "id": 6001164,
        "name:xx": "Carapito"
      }
    },
    {
      "geometry": {
        "type": "Point",
        "coordinates": [
          38,
          36.916
        ]
      },
      "type": "Feature",
      "properties": {
        "hierarchy": [
          "tgn:6001165",
          "tgn:1001262",
          "tgn:1000004",
          "tgn:7018456",
          "tgn:1000144",
          "tgn:7029392"
        ],
        "placetype": [
          "aat:300008347",
          "aat:300167671",
          "aat:300008389",
          "aat:300387006"
        ],
        "name:la": "Carchemish",
        "id": 6001165
      }
    }
  ]
}
