{
  "geometry": {
    "type": "Point",
    "coordinates": [
      28.0333,
      39.5167
    ]
  },
  "type": "Feature",
  "properties": {
    "hierarchy": [
      "tgn:1085764",
      "tgn:1001135",
      "tgn:1000004",
      "tgn:7018450",
      "tgn:1000144",
      "tgn:7029392"
    ],
    "placetype": [
      "aat:300008347"
    ],
    "id": 1085764,
    "name:xx": "Çağış"
  }
}
