{
  "geometry": {
    "type": "Point",
    "coordinates": [
      -112.9667,
      47.95
    ]
  },
  "type": "Feature",
  "properties": {
    "hierarchy": [
      "tgn:2333627",
      "tgn:1000001",
      "tgn:7012149",
      "tgn:7007524",
      "tgn:7029392"
    ],
    "placetype": [
      "aat:300008706"
    ],
    "id": 2333627,
    "name:xx": "Fool Creek"
  }
}
