{
  "geometry": {
    "type": "Point",
    "coordinates": [
      138.4667,
      35.5667
    ]
  },
  "type": "Feature",
  "properties": {
    "hierarchy": [
      "tgn:1080730",
      "tgn:7000895",
      "tgn:1000004",
      "tgn:7016854",
      "tgn:1000120",
      "tgn:7029392"
    ],
    "placetype": [
      "aat:300008347"
    ],
    "id": 1080730,
    "name:xx": "Masuho"
  }
}
