{
  "geometry": {
    "type": "Point",
    "coordinates": [
      -81.4333,
      31.9333
    ]
  },
  "type": "Feature",
  "properties": {
    "hierarchy": [
      "tgn:2527161",
      "tgn:1000001",
      "tgn:7012149",
      "tgn:7007248",
      "tgn:7029392"
    ],
    "placetype": [
      "aat:300008706"
    ],
    "id": 2527161,
    "name:xx": "Mount Hope Creek"
  }
}
