{
  "geometry": {
    "type": "Point",
    "coordinates": [
      -120.6833,
      41.9833
    ]
  },
  "type": "Feature",
  "properties": {
    "hierarchy": [
      "tgn:7023516",
      "tgn:1000001",
      "tgn:7012149",
      "tgn:7029392"
    ],
    "placetype": [
      "aat:300008798"
    ],
    "id": 7023516,
    "name:xx": "Muldoon Mountain"
  }
}
