{
  "geometry": {
    "type": "Point",
    "coordinates": [
      -78.75,
      36.25
    ]
  },
  "type": "Feature",
  "properties": {
    "hierarchy": [
      "tgn:2287040",
      "tgn:1000001",
      "tgn:7012149",
      "tgn:7014128",
      "tgn:7007709",
      "tgn:7029392"
    ],
    "placetype": [
      "aat:300008706"
    ],
    "id": 2287040,
    "name:xx": "Dickens Creek"
  }
}
