{
  "geometry": {
    "type": "Point",
    "coordinates": [
      -76.7667,
      36.4667
    ]
  },
  "type": "Feature",
  "properties": {
    "hierarchy": [
      "tgn:2249104",
      "tgn:1000001",
      "tgn:7012149",
      "tgn:1002403",
      "tgn:7007709",
      "tgn:7029392"
    ],
    "placetype": [
      "aat:300008706"
    ],
    "id": 2249104,
    "name:xx": "Cole Creek"
  }
}
