{
  "type": "FeatureCollection",
  "features": [
    {
      "geometry": {
        "type": "Point",
        "coordinates": [
          16.333333,
          39.2
        ]
      },
      "type": "Feature",
      "properties": {
        "hierarchy": [
          "tgn:1045220",
          "tgn:1003450",
          "tgn:7007850",
          "tgn:1000003",
          "tgn:1000080",
          "tgn:7029392"
        ],
        "placetype": [
          "aat:300008347"
        ],
        "id": 1045220,
        "name:xx": "Mangone"
      }
    },
    {
      "geometry": {
        "type": "Point",
        "coordinates": [
          8.3833,
          40.8333
        ]
      },
      "type": "Feature",
      "properties": {
        "hierarchy": [
          "tgn:1045222",
          "tgn:1001641",
          "tgn:1000003",
          "tgn:7003121",
          "tgn:1000080",
          "tgn:7029392"
        ],
        "placetype": [
          "aat:300008347"
        ],
        "id": 1045222,
        "name:xx": "Mannu"
      }
    },
    {
      "geometry": {
        "type": "Point",
        "coordinates": [
          13.383889,
          45.991667
        ]
      },
      "type": "Feature",
      "properties": {
        "hierarchy": [
          "tgn:1045226",
          "tgn:1003506",
          "tgn:1000003",
          "tgn:7002993",
          "tgn:1000080",
          "tgn:7029392"
        ],
        "placetype": [
          "aat:300008347"
        ],
        "id": 1045226,
        "name:xx": "Manzano"
      }
    },
    {
      "geometry": {
        "type": "Point",
        "coordinates": [
          9.2275,
          39.287222
        ]
      },
      "type": "Feature",
      "properties": {
        "hierarchy": [
          "tgn:1045228",
          "tgn:1001641",
          "tgn:1000003",
          "tgn:7003121",
          "tgn:1000080",
          "tgn:7029392"
        ],
        "placetype": [
          "aat:300008347"
        ],
        "id": 1045228,
        "name:xx": "Maracalagonis"
      }
    },
    {
      "geometry": {
        "type": "Point",
        "coordinates": [
          10.866667,
          44.533333
        ]
      },
      "type": "Feature",
      "properties": {
        "hierarchy": [
          "tgn:1045229",
          "tgn:7004597",
          "tgn:1000003",
          "tgn:7008516",
          "tgn:1000080",
          "tgn:7029392"
        ],
        "placetype": [
          "aat:300008347"
        ],
        "id": 1045229,
        "name:xx": "Maranello"
      }
    }
  ]
}
