{
  "geometry": {
    "type": "Point",
    "coordinates": [
      -69.8833,
      -14.8667
    ]
  },
  "type": "Feature",
  "properties": {
    "hierarchy": [
      "tgn:1024713",
      "tgn:1000731",
      "tgn:1000002",
      "tgn:1000056",
      "tgn:7029392"
    ],
    "placetype": [
      "aat:300008347"
    ],
    "id": 1024713,
    "name:xx": "Putina"
  }
}
