{
  "geometry": {
    "type": "Point",
    "coordinates": [
      79.677509,
      26.91118
    ]
  },
  "type": "Feature",
  "properties": {
    "hierarchy": [
      "tgn:7564852",
      "tgn:1000004",
      "tgn:7000198",
      "tgn:7016722",
      "tgn:7029392"
    ],
    "placetype": [
      "aat:300008347"
    ],
    "name:en": "Purwa Kahārān",
    "id": 7564852
  }
}
