{
  "geometry": {
    "type": "Point",
    "coordinates": [
      -99.8667,
      34.1333
    ]
  },
  "type": "Feature",
  "properties": {
    "hierarchy": [
      "tgn:2452928",
      "tgn:1000001",
      "tgn:7012149",
      "tgn:7007826",
      "tgn:7029392"
    ],
    "placetype": [
      "aat:300008706"
    ],
    "id": 2452928,
    "name:xx": "Little Cactus Creek"
  }
}
