{
  "geometry": {
    "type": "Point",
    "coordinates": [
      -87.8333,
      41.85
    ]
  },
  "type": "Feature",
  "properties": {
    "hierarchy": [
      "tgn:2028336",
      "tgn:1000001",
      "tgn:7013649",
      "tgn:7012149",
      "tgn:7007251",
      "tgn:7029392"
    ],
    "placetype": [
      "aat:300387016"
    ],
    "id": 2028336,
    "name:xx": "Hines"
  }
}
