{
  "geometry": {
    "type": "Point",
    "coordinates": [
      -115.4167,
      41.9333
    ]
  },
  "type": "Feature",
  "properties": {
    "hierarchy": [
      "tgn:2281875",
      "tgn:1000001",
      "tgn:2001411",
      "tgn:7012149",
      "tgn:7007526",
      "tgn:7029392"
    ],
    "placetype": [
      "aat:300008746"
    ],
    "id": 2281875,
    "name:xx": "Deer Creek Cave"
  }
}
