{
  "geometry": {
    "type": "Point",
    "coordinates": [
      -77.2667,
      38.2333
    ]
  },
  "type": "Feature",
  "properties": {
    "hierarchy": [
      "tgn:2667255",
      "tgn:1000001",
      "tgn:1002235",
      "tgn:7012149",
      "tgn:7007919",
      "tgn:7029392"
    ],
    "placetype": [
      "aat:300008706"
    ],
    "id": 2667255,
    "name:xx": "Skinkers Creek"
  }
}
