{
  "geometry": {
    "type": "Point",
    "coordinates": [
      -75.0667,
      41.4167
    ]
  },
  "type": "Feature",
  "properties": {
    "hierarchy": [
      "tgn:2692419",
      "tgn:1000001",
      "tgn:7012149",
      "tgn:1002789",
      "tgn:7007710",
      "tgn:7029392"
    ],
    "placetype": [
      "aat:300008699"
    ],
    "id": 2692419,
    "name:xx": "Steam Mill Run"
  }
}
