{
  "geometry": {
    "type": "Point",
    "coordinates": [
      -78.4833,
      39.3333
    ]
  },
  "type": "Feature",
  "properties": {
    "hierarchy": [
      "tgn:2609055",
      "tgn:1000001",
      "tgn:7012149",
      "tgn:2002265",
      "tgn:7013961",
      "tgn:7029392"
    ],
    "placetype": [
      "aat:300008798"
    ],
    "id": 2609055,
    "name:xx": "Raven Rocks"
  }
}
