{
  "geometry": {
    "type": "Point",
    "coordinates": [
      79.893769,
      24.35799
    ]
  },
  "type": "Feature",
  "properties": {
    "hierarchy": [
      "tgn:7588527",
      "tgn:1000004",
      "tgn:7000198",
      "tgn:1001894",
      "tgn:7029392"
    ],
    "placetype": [
      "aat:300008347"
    ],
    "name:en": "Sunwāni Kalan",
    "id": 7588527
  }
}
