{
  "geometry": {
    "type": "Point",
    "coordinates": [
      4.8667,
      6.75
    ]
  },
  "type": "Feature",
  "properties": {
    "hierarchy": [
      "tgn:1092234",
      "tgn:7001242",
      "tgn:1001919",
      "tgn:1000182",
      "tgn:7029392"
    ],
    "placetype": [
      "aat:300008347"
    ],
    "id": 1092234,
    "name:xx": "Ore"
  }
}
