{
  "geometry": {
    "type": "Point",
    "coordinates": [
      -56.15,
      -31.8333
    ]
  },
  "type": "Feature",
  "properties": {
    "hierarchy": [
      "tgn:1024999",
      "tgn:7002644",
      "tgn:1000002",
      "tgn:1000058",
      "tgn:7029392"
    ],
    "placetype": [
      "aat:300008347"
    ],
    "id": 1024999,
    "name:xx": "Valle Edén"
  }
}
