{
  "geometry": {
    "type": "Point",
    "coordinates": [
      -92.0167,
      35.1167
    ]
  },
  "type": "Feature",
  "properties": {
    "hierarchy": [
      "tgn:2378768",
      "tgn:1000001",
      "tgn:7016172",
      "tgn:7012149",
      "tgn:2000177",
      "tgn:7029392"
    ],
    "placetype": [
      "aat:300008699"
    ],
    "id": 2378768,
    "name:xx": "Harston Branch"
  }
}
