{
  "geometry": {
    "type": "Point",
    "coordinates": [
      -95.6333,
      33.0833
    ]
  },
  "type": "Feature",
  "properties": {
    "hierarchy": [
      "tgn:2217981",
      "tgn:1000001",
      "tgn:7012149",
      "tgn:1002485",
      "tgn:7007826",
      "tgn:7029392"
    ],
    "placetype": [
      "aat:300006191"
    ],
    "id": 2217981,
    "name:xx": "Camps Lake"
  }
}
