{
  "geometry": {
    "type": "Point",
    "coordinates": [
      -81.2167,
      44.9667
    ]
  },
  "type": "Feature",
  "properties": {
    "hierarchy": [
      "tgn:1112650",
      "tgn:7005685",
      "tgn:1000001",
      "tgn:7013154",
      "tgn:7029392"
    ],
    "placetype": [
      "aat:300132316"
    ],
    "id": 1112650,
    "name:xx": "Barrow Bay"
  }
}
