{
  "geometry": {
    "type": "Point",
    "coordinates": [
      -116.748333,
      32.02
    ]
  },
  "type": "Feature",
  "properties": {
    "hierarchy": [
      "tgn:7418588",
      "tgn:1001835",
      "tgn:1000001",
      "tgn:7005560",
      "tgn:7029392"
    ],
    "placetype": [
      "aat:300266554",
      "aat:300008699"
    ],
    "id": 7418588,
    "name:xx": "Matajanal, Cañón"
  }
}
