{
  "type": "FeatureCollection",
  "features": [
    {
      "geometry": {
        "type": "Point",
        "coordinates": [
          75.642301,
          27.427151
        ]
      },
      "type": "Feature",
      "properties": {
        "hierarchy": [
          "tgn:7553920",
          "tgn:1000004",
          "tgn:7000198",
          "tgn:7016788",
          "tgn:7029392"
        ],
        "placetype": [
          "aat:300008347"
        ],
        "name:en": "Mau",
        "id": 7553920
      }
    },
    {
      "geometry": {
        "type": "Point",
        "coordinates": [
          77.009902,
          26.821404
        ]
      },
      "type": "Feature",
      "properties": {
        "hierarchy": [
          "tgn:7553921",
          "tgn:1000004",
          "tgn:7000198",
          "tgn:7016788",
          "tgn:7029392"
        ],
        "placetype": [
          "aat:300008347"
        ],
        "name:en": "Mau",
        "id": 7553921
      }
    },
    {
      "geometry": {
        "type": "Point",
        "coordinates": [
          78.671083,
          26.265837
        ]
      },
      "type": "Feature",
      "properties": {
        "hierarchy": [
          "tgn:7553922",
          "tgn:1000004",
          "tgn:7000198",
          "tgn:1001894",
          "tgn:7029392"
        ],
        "placetype": [
          "aat:300008347"
        ],
        "name:en": "Mau",
        "id": 7553922
      }
    },
    {
      "geometry": {
        "type": "Point",
        "coordinates": [
          78.183333,
          26.266667
        ]
      },
      "type": "Feature",
      "properties": {
        "hierarchy": [
          "tgn:7553923",
          "tgn:1000004",
          "tgn:7000198",
          "tgn:1001894",
          "tgn:7029392"
        ],
        "placetype": [
          "aat:300008347"
        ],
        "name:en": "Mau",
        "id": 7553923
      }
    },
    {
      "geometry": {
        "type": "Point",
        "coordinates": [
          80.871954,
          25.612103
        ]
      },
      "type": "Feature",
      "properties": {
        "hierarchy": [
          "tgn:7553925",
          "tgn:1000004",
          "tgn:7000198",
          "tgn:7016722",
          "tgn:7029392"
        ],
        "placetype": [
          "aat:300008347"
        ],
        "name:en": "Mau",
        "id": 7553925
      }
    },
    {
      "geometry": {
        "type": "Point",
        "coordinates": [
          76.516667,
          25.366667
        ]
      },
      "type": "Feature",
      "properties": {
        "hierarchy": [
          "tgn:7553926",
          "tgn:1000004",
          "tgn:7000198",
          "tgn:7016788",
          "tgn:7029392"
        ],
        "placetype": [
          "aat:300008347"
        ],
        "name:en": "Maū",
        "id": 7553926
      }
    },
    {
      "geometry": {
        "type": "Point",
        "coordinates": [
          84.812109,
          25.005069
        ]
      },
      "type": "Feature",
      "properties": {
        "hierarchy": [
          "tgn:7553928",
          "tgn:1000004",
          "tgn:1001842",
          "tgn:7000198",
          "tgn:7029392"
        ],
        "placetype": [
          "aat:300008347"
        ],
        "name:en": "Mau",
        "id": 7553928
      }
    },
    {
      "geometry": {
        "type": "Point",
        "coordinates": [
          76.342326,
          24.567361
        ]
      },
      "type": "Feature",
      "properties": {
        "hierarchy": [
          "tgn:7553929",
          "tgn:1000004",
          "tgn:7000198",
          "tgn:7016788",
          "tgn:7029392"
        ],
        "placetype": [
          "aat:300008347"
        ],
        "name:en": "Mau",
        "id": 7553929
      }
    }
  ]
}
