{
  "geometry": {
    "type": "Point",
    "coordinates": [
      19.0833,
      -17.8333
    ]
  },
  "type": "Feature",
  "properties": {
    "hierarchy": [
      "tgn:1093963",
      "tgn:7001242",
      "tgn:7030582",
      "tgn:1000198",
      "tgn:7029392"
    ],
    "placetype": [
      "aat:300055621",
      "aat:300008347"
    ],
    "id": 1093963,
    "name:xx": "Lupala"
  }
}
