{
  "geometry": {
    "type": "Point",
    "coordinates": [
      1.55,
      34.8167
    ]
  },
  "type": "Feature",
  "properties": {
    "hierarchy": [
      "tgn:1087341",
      "tgn:7001242",
      "tgn:7016752",
      "tgn:1000781",
      "tgn:7029392"
    ],
    "placetype": [
      "aat:300008347"
    ],
    "id": 1087341,
    "name:xx": "Aïn Deheb"
  }
}
