{
  "geometry": {
    "type": "Point",
    "coordinates": [
      -111.15,
      33.9167
    ]
  },
  "type": "Feature",
  "properties": {
    "hierarchy": [
      "tgn:2518346",
      "tgn:1000001",
      "tgn:7006451",
      "tgn:2000093",
      "tgn:7012149",
      "tgn:7029392"
    ],
    "placetype": [
      "aat:300008798"
    ],
    "id": 2518346,
    "name:xx": "Mistake Peak"
  }
}
