{
  "geometry": {
    "type": "Point",
    "coordinates": [
      98.5167,
      27.4833
    ]
  },
  "type": "Feature",
  "properties": {
    "hierarchy": [
      "tgn:1066007",
      "tgn:7002185",
      "tgn:1000004",
      "tgn:1000108",
      "tgn:7029392"
    ],
    "placetype": [
      "aat:300008347"
    ],
    "id": 1066007,
    "name:xx": "Chakwadām"
  }
}
