{
  "geometry": {
    "type": "Point",
    "coordinates": [
      -108.55,
      39.9167
    ]
  },
  "type": "Feature",
  "properties": {
    "hierarchy": [
      "tgn:2278789",
      "tgn:1000001",
      "tgn:7012149",
      "tgn:7007158",
      "tgn:2000243",
      "tgn:7029392"
    ],
    "placetype": [
      "aat:300266640"
    ],
    "id": 2278789,
    "name:xx": "Dead Horse Ridge"
  }
}
