{
  "type": "FeatureCollection",
  "features": [
    {
      "geometry": {
        "type": "Point",
        "coordinates": [
          -93.916667,
          17.75
        ]
      },
      "type": "Feature",
      "properties": {
        "hierarchy": [
          "tgn:7352590",
          "tgn:1000001",
          "tgn:7005596",
          "tgn:7005560",
          "tgn:7029392"
        ],
        "placetype": [
          "aat:300008347"
        ],
        "id": 7352590,
        "name:xx": "Buenavista"
      }
    },
    {
      "geometry": {
        "type": "Point",
        "coordinates": [
          -91.733333,
          17.75
        ]
      },
      "type": "Feature",
      "properties": {
        "hierarchy": [
          "tgn:7352591",
          "tgn:1000001",
          "tgn:7005596",
          "tgn:7005560",
          "tgn:7029392"
        ],
        "placetype": [
          "aat:300008347"
        ],
        "id": 7352591,
        "name:xx": "Buenavista"
      }
    },
    {
      "geometry": {
        "type": "Point",
        "coordinates": [
          -91.375,
          17.770833
        ]
      },
      "type": "Feature",
      "properties": {
        "hierarchy": [
          "tgn:7352592",
          "tgn:1000001",
          "tgn:7005596",
          "tgn:7005560",
          "tgn:7029392"
        ],
        "placetype": [
          "aat:300008347"
        ],
        "id": 7352592,
        "name:xx": "Buenavista"
      }
    },
    {
      "geometry": {
        "type": "Point",
        "coordinates": [
          -93.75,
          17.666667
        ]
      },
      "type": "Feature",
      "properties": {
        "hierarchy": [
          "tgn:7352593",
          "tgn:1000001",
          "tgn:7005599",
          "tgn:7005560",
          "tgn:7029392"
        ],
        "placetype": [
          "aat:300008347"
        ],
        "id": 7352593,
        "name:xx": "Buenavista"
      }
    },
    {
      "geometry": {
        "type": "Point",
        "coordinates": [
          -95.216667,
          17.633333
        ]
      },
      "type": "Feature",
      "properties": {
        "hierarchy": [
          "tgn:7352594",
          "tgn:1000001",
          "tgn:7005599",
          "tgn:7005560",
          "tgn:7029392"
        ],
        "placetype": [
          "aat:300008347"
        ],
        "id": 7352594,
        "name:xx": "Buenavista"
      }
    },
    {
      "geometry": {
        "type": "Point",
        "coordinates": [
          -93.933333,
          17.633333
        ]
      },
      "type": "Feature",
      "properties": {
        "hierarchy": [
          "tgn:7352595",
          "tgn:1000001",
          "tgn:7005599",
          "tgn:7005560",
          "tgn:7029392"
        ],
        "placetype": [
          "aat:300008347"
        ],
        "id": 7352595,
        "name:xx": "Buenavista"
      }
    },
    {
      "geometry": {
        "type": "Point",
        "coordinates": [
          -91.3,
          17.6
        ]
      },
      "type": "Feature",
      "properties": {
        "hierarchy": [
          "tgn:7352596",
          "tgn:1000001",
          "tgn:7005596",
          "tgn:7005560",
          "tgn:7029392"
        ],
        "placetype": [
          "aat:300008347"
        ],
        "id": 7352596,
        "name:xx": "Buenavista"
      }
    },
    {
      "geometry": {
        "type": "Point",
        "coordinates": [
          -91,
          17.55
        ]
      },
      "type": "Feature",
      "properties": {
        "hierarchy": [
          "tgn:7352597",
          "tgn:1000001",
          "tgn:7005596",
          "tgn:7005560",
          "tgn:7029392"
        ],
        "placetype": [
          "aat:300008347"
        ],
        "id": 7352597,
        "name:xx": "Buenavista"
      }
    },
    {
      "geometry": {
        "type": "Point",
        "coordinates": [
          -96.816667,
          17.333333
        ]
      },
      "type": "Feature",
      "properties": {
        "hierarchy": [
          "tgn:7352598",
          "tgn:1000001",
          "tgn:7005591",
          "tgn:7005560",
          "tgn:7029392"
        ],
        "placetype": [
          "aat:300008347"
        ],
        "id": 7352598,
        "name:xx": "Buenavista"
      }
    },
    {
      "geometry": {
        "type": "Point",
        "coordinates": [
          -93.233333,
          17.283333
        ]
      },
      "type": "Feature",
      "properties": {
        "hierarchy": [
          "tgn:7352599",
          "tgn:7005580",
          "tgn:1000001",
          "tgn:7005560",
          "tgn:7029392"
        ],
        "placetype": [
          "aat:300008347"
        ],
        "id": 7352599,
        "name:xx": "Buenavista"
      }
    }
  ]
}
