{
  "geometry": {
    "type": "Point",
    "coordinates": [
      -120.8667,
      38.2667
    ]
  },
  "type": "Feature",
  "properties": {
    "hierarchy": [
      "tgn:2442381",
      "tgn:1002146",
      "tgn:1000001",
      "tgn:7012149",
      "tgn:7007157",
      "tgn:7029392"
    ],
    "placetype": [
      "aat:300006075"
    ],
    "id": 2442381,
    "name:xx": "Kreth Ditch"
  }
}
