{
  "geometry": {
    "type": "Point",
    "coordinates": [
      -108.5167,
      37.9667
    ]
  },
  "type": "Feature",
  "properties": {
    "hierarchy": [
      "tgn:2278694",
      "tgn:1000001",
      "tgn:7012149",
      "tgn:7007158",
      "tgn:2000248",
      "tgn:7029392"
    ],
    "placetype": [
      "aat:300008706"
    ],
    "id": 2278694,
    "name:xx": "Dead Horse Creek"
  }
}
