{
  "geometry": {
    "type": "Point",
    "coordinates": [
      25.383333,
      36.65
    ]
  },
  "type": "Feature",
  "properties": {
    "hierarchy": [
      "tgn:7224130",
      "tgn:7011270",
      "tgn:7002674",
      "tgn:1000003",
      "tgn:1000074",
      "tgn:7029392"
    ],
    "placetype": [
      "aat:300008850"
    ],
    "id": 7224130,
    "name:xx": "Pirgári, Ákra"
  }
}
