{
  "geometry": {
    "type": "Point",
    "coordinates": [
      -120.5833,
      44.4833
    ]
  },
  "type": "Feature",
  "properties": {
    "hierarchy": [
      "tgn:2421483",
      "tgn:1000001",
      "tgn:2001703",
      "tgn:7012149",
      "tgn:7007708",
      "tgn:7029392"
    ],
    "placetype": [
      "aat:300008697"
    ],
    "id": 2421483,
    "name:xx": "Jesse Spring"
  }
}
