{
  "geometry": {
    "type": "Point",
    "coordinates": [
      -120.5833,
      39.6167
    ]
  },
  "type": "Feature",
  "properties": {
    "hierarchy": [
      "tgn:2586777",
      "tgn:1000001",
      "tgn:7012149",
      "tgn:7007157",
      "tgn:1002894",
      "tgn:7029392"
    ],
    "placetype": [
      "aat:300000390"
    ],
    "id": 2586777,
    "name:xx": "Placer Mine"
  }
}
