{
  "geometry": {
    "type": "Point",
    "coordinates": [
      74.594444,
      32.888889
    ]
  },
  "type": "Feature",
  "properties": {
    "hierarchy": [
      "tgn:7590764",
      "tgn:1000004",
      "tgn:7000198",
      "tgn:7000799",
      "tgn:7029392"
    ],
    "placetype": [
      "aat:300266554",
      "aat:300008699"
    ],
    "name:en": "Gopīwāla Nāla",
    "id": 7590764
  }
}
