{
  "geometry": {
    "type": "Point",
    "coordinates": [
      -82.0667,
      28.6833
    ]
  },
  "type": "Feature",
  "properties": {
    "hierarchy": [
      "tgn:2428919",
      "tgn:1000001",
      "tgn:7012149",
      "tgn:1002929",
      "tgn:7007240",
      "tgn:7029392"
    ],
    "placetype": [
      "aat:300006075"
    ],
    "id": 2428919,
    "name:xx": "Jumper Creek Canal"
  }
}
