{
  "geometry": {
    "type": "Point",
    "coordinates": [
      -119.1333,
      41.1333
    ]
  },
  "type": "Feature",
  "properties": {
    "hierarchy": [
      "tgn:2747036",
      "tgn:1000001",
      "tgn:2001414",
      "tgn:7012149",
      "tgn:7007526",
      "tgn:7029392"
    ],
    "placetype": [
      "aat:300008697"
    ],
    "id": 2747036,
    "name:xx": "Wagner Springs"
  }
}
