{
  "geometry": {
    "type": "Point",
    "coordinates": [
      74.11182,
      34.323674
    ]
  },
  "type": "Feature",
  "properties": {
    "hierarchy": [
      "tgn:7585786",
      "tgn:1000004",
      "tgn:7000198",
      "tgn:7000799",
      "tgn:7029392"
    ],
    "placetype": [
      "aat:300008347"
    ],
    "name:en": "Ahadio",
    "id": 7585786
  }
}
