{
  "geometry": {
    "type": "Point",
    "coordinates": [
      -114.2833,
      48.5333
    ]
  },
  "type": "Feature",
  "properties": {
    "hierarchy": [
      "tgn:2438906",
      "tgn:1000001",
      "tgn:7012149",
      "tgn:2001274",
      "tgn:7007524",
      "tgn:7029392"
    ],
    "placetype": [
      "aat:300008706"
    ],
    "id": 2438906,
    "name:xx": "Kinnimiki Creek"
  }
}
