{
  "geometry": {
    "type": "Point",
    "coordinates": [
      104.0167,
      1.4167
    ]
  },
  "type": "Feature",
  "properties": {
    "hierarchy": [
      "tgn:1009401",
      "tgn:1000004",
      "tgn:7000381",
      "tgn:7029392"
    ],
    "placetype": [
      "aat:300008791"
    ],
    "id": 1009401,
    "name:xx": "Tekong Kechil, Pulau"
  }
}
