{
  "type": "FeatureCollection",
  "features": [
    {
      "geometry": {
        "type": "Point",
        "coordinates": [
          0.85,
          52.45
        ]
      },
      "type": "Feature",
      "properties": {
        "hierarchy": [
          "tgn:7448731",
          "tgn:7002445",
          "tgn:1000003",
          "tgn:7008160",
          "tgn:7008591",
          "tgn:7029392"
        ],
        "placetype": [
          "aat:300386887"
        ],
        "name:en": "Roudham Heath",
        "id": 7448731
      }
    },
    {
      "geometry": {
        "type": "Point",
        "coordinates": [
          0.9,
          52.45
        ]
      },
      "type": "Feature",
      "properties": {
        "hierarchy": [
          "tgn:7448732",
          "tgn:7002445",
          "tgn:1000003",
          "tgn:7008160",
          "tgn:7008591",
          "tgn:7029392"
        ],
        "placetype": [
          "aat:300008347"
        ],
        "name:en": "Roudham",
        "id": 7448732
      }
    },
    {
      "geometry": {
        "type": "Point",
        "coordinates": [
          -4.1,
          55.833333
        ]
      },
      "type": "Feature",
      "properties": {
        "hierarchy": [
          "tgn:7448734",
          "tgn:7002444",
          "tgn:1000003",
          "tgn:7019100",
          "tgn:7008591",
          "tgn:7029392"
        ],
        "placetype": [
          "aat:300008699"
        ],
        "name:en": "Rotten Calder",
        "id": 7448734
      }
    }
  ]
}
