{
  "geometry": {
    "type": "Point",
    "coordinates": [
      -104.15,
      43.35
    ]
  },
  "type": "Feature",
  "properties": {
    "hierarchy": [
      "tgn:2397177",
      "tgn:1000001",
      "tgn:7012149",
      "tgn:2002378",
      "tgn:7007923",
      "tgn:7029392"
    ],
    "placetype": [
      "aat:300008706"
    ],
    "id": 2397177,
    "name:xx": "Hon Creek"
  }
}
