{
  "geometry": {
    "type": "Point",
    "coordinates": [
      -118.9167,
      44.35
    ]
  },
  "type": "Feature",
  "properties": {
    "hierarchy": [
      "tgn:2219936",
      "tgn:1000001",
      "tgn:7012149",
      "tgn:2001708",
      "tgn:7007708",
      "tgn:7029392"
    ],
    "placetype": [
      "aat:300386845"
    ],
    "id": 2219936,
    "name:xx": "Canyon City Municipal Watershed"
  }
}
