{
  "geometry": {
    "type": "Point",
    "coordinates": [
      -23.1667,
      15.25
    ]
  },
  "type": "Feature",
  "properties": {
    "hierarchy": [
      "tgn:1007985",
      "tgn:7001635",
      "tgn:7001242",
      "tgn:7001632",
      "tgn:7029392"
    ],
    "placetype": [
      "aat:300387145",
      "aat:300008791",
      "aat:300000771"
    ],
    "id": 1007985,
    "name:xx": "Maio"
  }
}
