{
  "geometry": {
    "type": "Point",
    "coordinates": [
      -115.4833,
      45.55
    ]
  },
  "type": "Feature",
  "properties": {
    "hierarchy": [
      "tgn:2725807",
      "tgn:1000001",
      "tgn:7012149",
      "tgn:2000476",
      "tgn:7007250",
      "tgn:7029392"
    ],
    "placetype": [
      "aat:300000390"
    ],
    "id": 2725807,
    "name:xx": "Toropah Mine"
  }
}
