{
  "geometry": {
    "type": "Point",
    "coordinates": [
      -93.7333,
      43.6333
    ]
  },
  "type": "Feature",
  "properties": {
    "hierarchy": [
      "tgn:2616531",
      "tgn:1000001",
      "tgn:2001020",
      "tgn:7012149",
      "tgn:7007521",
      "tgn:7029392"
    ],
    "placetype": [
      "aat:300008680"
    ],
    "id": 2616531,
    "name:xx": "Rice Lake"
  }
}
