{
  "type": "FeatureCollection",
  "features": [
    {
      "geometry": {
        "type": "Point",
        "coordinates": [
          -117.55,
          42.4167
        ]
      },
      "type": "Feature",
      "properties": {
        "hierarchy": [
          "tgn:2237120",
          "tgn:1000001",
          "tgn:7012149",
          "tgn:2001718",
          "tgn:7007708",
          "tgn:7029392"
        ],
        "placetype": [
          "aat:300008706"
        ],
        "id": 2237120,
        "name:xx": "Chimney Creek"
      }
    },
    {
      "geometry": {
        "type": "Point",
        "coordinates": [
          -101.35,
          32.1667
        ]
      },
      "type": "Feature",
      "properties": {
        "hierarchy": [
          "tgn:2237121",
          "tgn:1000001",
          "tgn:7012149",
          "tgn:2002004",
          "tgn:7007826",
          "tgn:7029392"
        ],
        "placetype": [
          "aat:300008706"
        ],
        "id": 2237121,
        "name:xx": "Chimney Creek"
      }
    },
    {
      "geometry": {
        "type": "Point",
        "coordinates": [
          -101.0833,
          32.7167
        ]
      },
      "type": "Feature",
      "properties": {
        "hierarchy": [
          "tgn:2237122",
          "tgn:1000001",
          "tgn:7012149",
          "tgn:2002071",
          "tgn:7007826",
          "tgn:7029392"
        ],
        "placetype": [
          "aat:300008706"
        ],
        "id": 2237122,
        "name:xx": "Chimney Creek"
      }
    },
    {
      "geometry": {
        "type": "Point",
        "coordinates": [
          -99.55,
          32.75
        ]
      },
      "type": "Feature",
      "properties": {
        "hierarchy": [
          "tgn:2237123",
          "tgn:1000001",
          "tgn:7012149",
          "tgn:7007826",
          "tgn:7029392"
        ],
        "placetype": [
          "aat:300008706"
        ],
        "id": 2237123,
        "name:xx": "Chimney Creek"
      }
    },
    {
      "geometry": {
        "type": "Point",
        "coordinates": [
          -101.1167,
          33.3667
        ]
      },
      "type": "Feature",
      "properties": {
        "hierarchy": [
          "tgn:2237124",
          "tgn:1000001",
          "tgn:7012149",
          "tgn:2001989",
          "tgn:7007826",
          "tgn:7029392"
        ],
        "placetype": [
          "aat:300008706"
        ],
        "id": 2237124,
        "name:xx": "Chimney Creek"
      }
    },
    {
      "geometry": {
        "type": "Point",
        "coordinates": [
          -99.3667,
          32.6833
        ]
      },
      "type": "Feature",
      "properties": {
        "hierarchy": [
          "tgn:2237125",
          "tgn:1000001",
          "tgn:7012149",
          "tgn:2002072",
          "tgn:7007826",
          "tgn:7029392"
        ],
        "placetype": [
          "aat:300008706"
        ],
        "id": 2237125,
        "name:xx": "Chimney Creek"
      }
    },
    {
      "geometry": {
        "type": "Point",
        "coordinates": [
          -121.4667,
          46.5667
        ]
      },
      "type": "Feature",
      "properties": {
        "hierarchy": [
          "tgn:2237126",
          "tgn:1000001",
          "tgn:7012149",
          "tgn:1002594",
          "tgn:7007920",
          "tgn:7029392"
        ],
        "placetype": [
          "aat:300008706"
        ],
        "id": 2237126,
        "name:xx": "Chimney Creek"
      }
    },
    {
      "geometry": {
        "type": "Point",
        "coordinates": [
          -108.45,
          42.45
        ]
      },
      "type": "Feature",
      "properties": {
        "hierarchy": [
          "tgn:2237127",
          "tgn:1000001",
          "tgn:7012149",
          "tgn:2002371",
          "tgn:7007923",
          "tgn:7029392"
        ],
        "placetype": [
          "aat:300008706"
        ],
        "id": 2237127,
        "name:xx": "Chimney Creek"
      }
    },
    {
      "geometry": {
        "type": "Point",
        "coordinates": [
          -109.0667,
          43.8167
        ]
      },
      "type": "Feature",
      "properties": {
        "hierarchy": [
          "tgn:2237128",
          "tgn:1000001",
          "tgn:7012149",
          "tgn:7007923",
          "tgn:7029392"
        ],
        "placetype": [
          "aat:300008706"
        ],
        "id": 2237128,
        "name:xx": "Chimney Creek"
      }
    },
    {
      "geometry": {
        "type": "Point",
        "coordinates": [
          -109.8,
          44.4667
        ]
      },
      "type": "Feature",
      "properties": {
        "hierarchy": [
          "tgn:2237129",
          "tgn:1000001",
          "tgn:7012149",
          "tgn:2002379",
          "tgn:7007923",
          "tgn:7029392"
        ],
        "placetype": [
          "aat:300008706"
        ],
        "id": 2237129,
        "name:xx": "Chimney Creek"
      }
    }
  ]
}
