{
  "type": "FeatureCollection",
  "features": [
    {
      "geometry": {
        "type": "Point",
        "coordinates": [
          -89.0833,
          30.4
        ]
      },
      "type": "Feature",
      "properties": {
        "hierarchy": [
          "tgn:2057760",
          "tgn:1000001",
          "tgn:7012149",
          "tgn:2001109",
          "tgn:7007522",
          "tgn:7029392"
        ],
        "placetype": [
          "aat:300008347"
        ],
        "id": 2057760,
        "name:xx": "West Gulfport"
      }
    },
    {
      "geometry": {
        "type": "Point",
        "coordinates": [
          -89.9,
          33.1
        ]
      },
      "type": "Feature",
      "properties": {
        "hierarchy": [
          "tgn:2057761",
          "tgn:1000001",
          "tgn:7012149",
          "tgn:2001111",
          "tgn:7007522",
          "tgn:7029392"
        ],
        "placetype": [
          "aat:300008347",
          "aat:300387210"
        ],
        "id": 2057761,
        "name:xx": "West Hill"
      }
    },
    {
      "geometry": {
        "type": "Point",
        "coordinates": [
          -90.5667,
          31.4833
        ]
      },
      "type": "Feature",
      "properties": {
        "hierarchy": [
          "tgn:2057762",
          "tgn:1000001",
          "tgn:7012149",
          "tgn:2001128",
          "tgn:7007522",
          "tgn:7029392"
        ],
        "placetype": [
          "aat:300008347",
          "aat:300387210"
        ],
        "id": 2057762,
        "name:xx": "West Lincoln"
      }
    },
    {
      "geometry": {
        "type": "Point",
        "coordinates": [
          -90.3,
          34.25
        ]
      },
      "type": "Feature",
      "properties": {
        "hierarchy": [
          "tgn:2057764",
          "tgn:1000001",
          "tgn:7012149",
          "tgn:2001145",
          "tgn:7007522",
          "tgn:7029392"
        ],
        "placetype": [
          "aat:300008347"
        ],
        "id": 2057764,
        "name:xx": "West Marks"
      }
    },
    {
      "geometry": {
        "type": "Point",
        "coordinates": [
          -88.65,
          33.6
        ]
      },
      "type": "Feature",
      "properties": {
        "hierarchy": [
          "tgn:2057765",
          "tgn:1000001",
          "tgn:2001098",
          "tgn:7012149",
          "tgn:7007522",
          "tgn:7029392"
        ],
        "placetype": [
          "aat:300008347",
          "aat:300008416"
        ],
        "id": 2057765,
        "name:xx": "West Point"
      }
    },
    {
      "geometry": {
        "type": "Point",
        "coordinates": [
          -89.5667,
          30.8333
        ]
      },
      "type": "Feature",
      "properties": {
        "hierarchy": [
          "tgn:2057766",
          "tgn:1000001",
          "tgn:7012149",
          "tgn:2001140",
          "tgn:7007522",
          "tgn:7029392"
        ],
        "placetype": [
          "aat:300008347"
        ],
        "id": 2057766,
        "name:xx": "West Poplarville"
      }
    },
    {
      "geometry": {
        "type": "Point",
        "coordinates": [
          -91.1167,
          31.9
        ]
      },
      "type": "Feature",
      "properties": {
        "hierarchy": [
          "tgn:2057767",
          "tgn:1000001",
          "tgn:2001096",
          "tgn:7012149",
          "tgn:7007522",
          "tgn:7029392"
        ],
        "placetype": [
          "aat:300008347",
          "aat:300387210"
        ],
        "id": 2057767,
        "name:xx": "Westside"
      }
    },
    {
      "geometry": {
        "type": "Point",
        "coordinates": [
          -88.6,
          34.5667
        ]
      },
      "type": "Feature",
      "properties": {
        "hierarchy": [
          "tgn:2057768",
          "tgn:1000001",
          "tgn:7012149",
          "tgn:2001144",
          "tgn:7007522",
          "tgn:7029392"
        ],
        "placetype": [
          "aat:300008347"
        ],
        "id": 2057768,
        "name:xx": "Wheeler"
      }
    }
  ]
}
