{
  "geometry": {
    "type": "Point",
    "coordinates": [
      -122.0833,
      37.0833
    ]
  },
  "type": "Feature",
  "properties": {
    "hierarchy": [
      "tgn:2010212",
      "tgn:1000001",
      "tgn:7012149",
      "tgn:7007157",
      "tgn:1002869",
      "tgn:7029392"
    ],
    "placetype": [
      "aat:300008347"
    ],
    "id": 2010212,
    "name:xx": "Ben Lomond"
  }
}
