{
  "geometry": {
    "type": "Point",
    "coordinates": [
      9.95,
      47.5833
    ]
  },
  "type": "Feature",
  "properties": {
    "hierarchy": [
      "tgn:1041233",
      "tgn:7003669",
      "tgn:1000003",
      "tgn:7000084",
      "tgn:7029392"
    ],
    "placetype": [
      "aat:300008347"
    ],
    "id": 1041233,
    "name:xx": "Simmerberg"
  }
}
