{
  "geometry": {
    "type": "Point",
    "coordinates": [
      -88.0333,
      42.4833
    ]
  },
  "type": "Feature",
  "properties": {
    "hierarchy": [
      "tgn:2282107",
      "tgn:1000001",
      "tgn:7012149",
      "tgn:7013855",
      "tgn:7007251",
      "tgn:7029392"
    ],
    "placetype": [
      "aat:300008680"
    ],
    "id": 2282107,
    "name:xx": "Deer Lake"
  }
}
