{
  "geometry": {
    "type": "Point",
    "coordinates": [
      -82.4167,
      37.1167
    ]
  },
  "type": "Feature",
  "properties": {
    "hierarchy": [
      "tgn:2235313",
      "tgn:1000001",
      "tgn:7012149",
      "tgn:2002157",
      "tgn:7007919",
      "tgn:7029392"
    ],
    "placetype": [
      "aat:300008761"
    ],
    "id": 2235313,
    "name:xx": "Cherrytree Hollow"
  }
}
