{
  "geometry": {
    "type": "Point",
    "coordinates": [
      -70.4333,
      41.7333
    ]
  },
  "type": "Feature",
  "properties": {
    "hierarchy": [
      "tgn:2588162",
      "tgn:1002165",
      "tgn:1000001",
      "tgn:7012149",
      "tgn:7007517",
      "tgn:7029392"
    ],
    "placetype": [
      "aat:300008347"
    ],
    "id": 2588162,
    "name:xx": "Plowed Neck"
  }
}
