{
  "geometry": {
    "type": "Point",
    "coordinates": [
      -83.8667,
      35.4833
    ]
  },
  "type": "Feature",
  "properties": {
    "hierarchy": [
      "tgn:2779707",
      "tgn:1000001",
      "tgn:7012149",
      "tgn:2001543",
      "tgn:7007709",
      "tgn:7029392"
    ],
    "placetype": [
      "aat:300266640"
    ],
    "id": 2779707,
    "name:xx": "Wolf Ridge"
  }
}
