{
  "type": "FeatureCollection",
  "features": [
    {
      "geometry": {
        "type": "Point",
        "coordinates": [
          -84.5833,
          22.1333
        ]
      },
      "type": "Feature",
      "properties": {
        "hierarchy": [
          "tgn:1112390",
          "tgn:1001488",
          "tgn:1000001",
          "tgn:7004624",
          "tgn:7029392"
        ],
        "placetype": [
          "aat:300132315"
        ],
        "id": 1112390,
        "name:xx": "Guanahacabibes, Golfo de"
      }
    },
    {
      "geometry": {
        "type": "Point",
        "coordinates": [
          -80.5,
          -3
        ]
      },
      "type": "Feature",
      "properties": {
        "hierarchy": [
          "tgn:1112391",
          "tgn:1000002",
          "tgn:7029392"
        ],
        "placetype": [
          "aat:300132315"
        ],
        "id": 1112391,
        "name:xx": "Guayaquil, Golfo de"
      }
    },
    {
      "geometry": {
        "type": "Point",
        "coordinates": [
          2.5,
          2
        ]
      },
      "type": "Feature",
      "properties": {
        "hierarchy": [
          "tgn:1112392",
          "tgn:7001242",
          "tgn:7029392"
        ],
        "placetype": [
          "aat:300132315"
        ],
        "id": 1112392,
        "name:xx": "Guinea, Gulf of"
      }
    },
    {
      "geometry": {
        "type": "Point",
        "coordinates": [
          10.6667,
          36.0833
        ]
      },
      "type": "Feature",
      "properties": {
        "hierarchy": [
          "tgn:1112393",
          "tgn:7001242",
          "tgn:1000205",
          "tgn:7029392"
        ],
        "placetype": [
          "aat:300132315"
        ],
        "id": 1112393,
        "name:xx": "Hammamet, Golfe de"
      }
    },
    {
      "geometry": {
        "type": "Point",
        "coordinates": [
          175.083333,
          -36.333333
        ]
      },
      "type": "Feature",
      "properties": {
        "hierarchy": [
          "tgn:1112394",
          "tgn:1008380",
          "tgn:1000226",
          "tgn:1000006",
          "tgn:7029392"
        ],
        "placetype": [
          "aat:300132315"
        ],
        "name:en": "Hauraki Gulf",
        "id": 1112394
      }
    },
    {
      "geometry": {
        "type": "Point",
        "coordinates": [
          -88,
          16.3333
        ]
      },
      "type": "Feature",
      "properties": {
        "hierarchy": [
          "tgn:1112395",
          "tgn:1000001",
          "tgn:7029392"
        ],
        "placetype": [
          "aat:300132315"
        ],
        "id": 1112395,
        "name:xx": "Gulfo de Honduras"
      }
    },
    {
      "geometry": {
        "type": "Point",
        "coordinates": [
          136,
          71.8333
        ]
      },
      "type": "Feature",
      "properties": {
        "hierarchy": [
          "tgn:1112398",
          "tgn:1000004",
          "tgn:7011528",
          "tgn:7002435",
          "tgn:7029392"
        ],
        "placetype": [
          "aat:300132315"
        ],
        "id": 1112398,
        "name:xx": "Yanskiy Zaliv"
      }
    },
    {
      "geometry": {
        "type": "Point",
        "coordinates": [
          80,
          72.5
        ]
      },
      "type": "Feature",
      "properties": {
        "hierarchy": [
          "tgn:1112399",
          "tgn:1000004",
          "tgn:7017024",
          "tgn:7018214",
          "tgn:7002435",
          "tgn:7029392"
        ],
        "placetype": [
          "aat:300132315"
        ],
        "id": 1112399,
        "name:xx": "Yeniseyskiy Zaliv"
      }
    }
  ]
}
