{
  "geometry": {
    "type": "Point",
    "coordinates": [
      -89.9167,
      36.8833
    ]
  },
  "type": "Feature",
  "properties": {
    "hierarchy": [
      "tgn:2180679",
      "tgn:1000001",
      "tgn:2001180",
      "tgn:7012149",
      "tgn:7007523",
      "tgn:7029392"
    ],
    "placetype": [
      "aat:300008347"
    ],
    "id": 2180679,
    "name:xx": "Bloomfield"
  }
}
