{
  "geometry": {
    "type": "Point",
    "coordinates": [
      -99.15,
      30.15
    ]
  },
  "type": "Feature",
  "properties": {
    "hierarchy": [
      "tgn:2410360",
      "tgn:1000001",
      "tgn:7012149",
      "tgn:7007826",
      "tgn:7029392"
    ],
    "placetype": [
      "aat:300008699"
    ],
    "id": 2410360,
    "name:xx": "Indian Branch"
  }
}
