{
  "geometry": {
    "type": "Point",
    "coordinates": [
      -117.0333,
      39.4833
    ]
  },
  "type": "Feature",
  "properties": {
    "hierarchy": [
      "tgn:2599377",
      "tgn:1000001",
      "tgn:2001415",
      "tgn:7012149",
      "tgn:7007526",
      "tgn:7029392"
    ],
    "placetype": [
      "aat:300008798"
    ],
    "id": 2599377,
    "name:xx": "Prometheus, Mount"
  }
}
