{
  "geometry": {
    "type": "Point",
    "coordinates": [
      -94.6167,
      46.1667
    ]
  },
  "type": "Feature",
  "properties": {
    "hierarchy": [
      "tgn:2257157",
      "tgn:1000001",
      "tgn:7012149",
      "tgn:2001047",
      "tgn:7007521",
      "tgn:7029392"
    ],
    "placetype": [
      "aat:300008680"
    ],
    "id": 2257157,
    "name:xx": "Corner Lake"
  }
}
