{
  "geometry": {
    "type": "Point",
    "coordinates": [
      10.7833,
      55.1333
    ]
  },
  "type": "Feature",
  "properties": {
    "hierarchy": [
      "tgn:1028006",
      "tgn:1000003",
      "tgn:7594009",
      "tgn:1000066",
      "tgn:7029392"
    ],
    "placetype": [
      "aat:300008347"
    ],
    "id": 1028006,
    "name:xx": "Lundeborg"
  }
}
