{
  "geometry": {
    "type": "Point",
    "coordinates": [
      78.1833,
      52.5167
    ]
  },
  "type": "Feature",
  "properties": {
    "hierarchy": [
      "tgn:1051482",
      "tgn:1000004",
      "tgn:7011458",
      "tgn:7014786",
      "tgn:7029392"
    ],
    "placetype": [
      "aat:300008347"
    ],
    "id": 1051482,
    "name:xx": "Shcherbakty"
  }
}
