{
  "type": "FeatureCollection",
  "features": [
    {
      "geometry": {
        "type": "Point",
        "coordinates": [
          -2.243056,
          51.378611
        ]
      },
      "type": "Feature",
      "properties": {
        "hierarchy": [
          "tgn:7448850",
          "tgn:7002445",
          "tgn:1000003",
          "tgn:7008180",
          "tgn:7008591",
          "tgn:7029392"
        ],
        "placetype": [
          "aat:300008347"
        ],
        "name:en": "South Wraxall",
        "id": 7448850
      }
    },
    {
      "geometry": {
        "type": "Point",
        "coordinates": [
          1.683333,
          52.316667
        ]
      },
      "type": "Feature",
      "properties": {
        "hierarchy": [
          "tgn:7448852",
          "tgn:7002445",
          "tgn:1000003",
          "tgn:7008185",
          "tgn:7008591",
          "tgn:7029392"
        ],
        "placetype": [
          "aat:300008678"
        ],
        "name:en": "Southwold Harbour",
        "id": 7448852
      }
    },
    {
      "geometry": {
        "type": "Point",
        "coordinates": [
          -2.6025,
          51.3075
        ]
      },
      "type": "Feature",
      "properties": {
        "hierarchy": [
          "tgn:7448857",
          "tgn:7002445",
          "tgn:7019021",
          "tgn:1000003",
          "tgn:7008591",
          "tgn:7029392"
        ],
        "placetype": [
          "aat:300008347"
        ],
        "name:en": "South Widcombe",
        "id": 7448857
      }
    },
    {
      "geometry": {
        "type": "Point",
        "coordinates": [
          -3.783333,
          54.95
        ]
      },
      "type": "Feature",
      "properties": {
        "hierarchy": [
          "tgn:7448858",
          "tgn:7002444",
          "tgn:7008074",
          "tgn:1000003",
          "tgn:7008591",
          "tgn:7029392"
        ],
        "placetype": [
          "aat:300007783"
        ],
        "name:en": "Southwick Station",
        "id": 7448858
      }
    },
    {
      "geometry": {
        "type": "Point",
        "coordinates": [
          -3.666667,
          54.9
        ]
      },
      "type": "Feature",
      "properties": {
        "hierarchy": [
          "tgn:7448859",
          "tgn:7002444",
          "tgn:7008074",
          "tgn:1000003",
          "tgn:7008591",
          "tgn:7029392"
        ],
        "placetype": [
          "aat:300387502"
        ],
        "name:en": "Southwick House",
        "id": 7448859
      }
    }
  ]
}
