{
  "geometry": {
    "type": "Point",
    "coordinates": [
      -88.85,
      32.4333
    ]
  },
  "type": "Feature",
  "properties": {
    "hierarchy": [
      "tgn:2377511",
      "tgn:1000001",
      "tgn:7012149",
      "tgn:2001123",
      "tgn:7007522",
      "tgn:7029392"
    ],
    "placetype": [
      "aat:300008706"
    ],
    "id": 2377511,
    "name:xx": "Harper Creek"
  }
}
