{
  "geometry": {
    "type": "Point",
    "coordinates": [
      -80.1667,
      33.3833
    ]
  },
  "type": "Feature",
  "properties": {
    "hierarchy": [
      "tgn:2234902",
      "tgn:2001732",
      "tgn:1000001",
      "tgn:7012149",
      "tgn:7007712",
      "tgn:7029392"
    ],
    "placetype": [
      "aat:300387099",
      "aat:300008905"
    ],
    "id": 2234902,
    "name:xx": "Cherry Grove Swamp"
  }
}
