{
  "geometry": {
    "type": "Point",
    "coordinates": [
      -108.0167,
      35.6833
    ]
  },
  "type": "Feature",
  "properties": {
    "hierarchy": [
      "tgn:2383403",
      "tgn:1000001",
      "tgn:7012149",
      "tgn:7019676",
      "tgn:7007566",
      "tgn:7029392"
    ],
    "placetype": [
      "aat:300008798"
    ],
    "id": 2383403,
    "name:xx": "Heart Rock"
  }
}
