{
  "geometry": {
    "type": "Point",
    "coordinates": [
      -115.2333,
      43.6167
    ]
  },
  "type": "Feature",
  "properties": {
    "hierarchy": [
      "tgn:2751360",
      "tgn:1000001",
      "tgn:7012149",
      "tgn:2000471",
      "tgn:7007250",
      "tgn:7029392"
    ],
    "placetype": [
      "aat:300008761"
    ],
    "id": 2751360,
    "name:xx": "Warm Spring Gulch"
  }
}
