{
  "geometry": {
    "type": "Point",
    "coordinates": [
      -96.1667,
      36.4833
    ]
  },
  "type": "Feature",
  "properties": {
    "hierarchy": [
      "tgn:2205478",
      "tgn:1000001",
      "tgn:7012149",
      "tgn:2001679",
      "tgn:7007707",
      "tgn:7029392"
    ],
    "placetype": [
      "aat:300008706"
    ],
    "id": 2205478,
    "name:xx": "Bull Creek"
  }
}
