{
  "geometry": {
    "type": "Point",
    "coordinates": [
      106.203,
      35.659
    ]
  },
  "type": "Feature",
  "properties": {
    "hierarchy": [
      "tgn:1109277",
      "tgn:1000004",
      "tgn:1000111",
      "tgn:7029392"
    ],
    "placetype": [
      "aat:300386831"
    ],
    "id": 1109277,
    "name:xx": "Liupan Shan"
  }
}
