{
  "geometry": {
    "type": "Point",
    "coordinates": [
      -96.5667,
      39.8667
    ]
  },
  "type": "Feature",
  "properties": {
    "hierarchy": [
      "tgn:2180373",
      "tgn:1000001",
      "tgn:7012149",
      "tgn:2000718",
      "tgn:7007254",
      "tgn:7029392"
    ],
    "placetype": [
      "aat:300008706"
    ],
    "id": 2180373,
    "name:xx": "Blodgett Creek"
  }
}
