{
  "geometry": {
    "type": "Point",
    "coordinates": [
      -80.9167,
      27.2667
    ]
  },
  "type": "Feature",
  "properties": {
    "hierarchy": [
      "tgn:2592729",
      "tgn:1000001",
      "tgn:7012149",
      "tgn:1002743",
      "tgn:7007240",
      "tgn:7029392"
    ],
    "placetype": [
      "aat:300008699"
    ],
    "id": 2592729,
    "name:xx": "Popash Slough"
  }
}
