{
  "geometry": {
    "type": "Point",
    "coordinates": [
      -87.8667,
      31.8667
    ]
  },
  "type": "Feature",
  "properties": {
    "hierarchy": [
      "tgn:2339144",
      "tgn:7002659",
      "tgn:1000001",
      "tgn:2000012",
      "tgn:7012149",
      "tgn:7029392"
    ],
    "placetype": [
      "aat:300008706"
    ],
    "id": 2339144,
    "name:xx": "Franks Creek"
  }
}
