{
  "geometry": {
    "type": "Point",
    "coordinates": [
      -74.8167,
      40.0833
    ]
  },
  "type": "Feature",
  "properties": {
    "hierarchy": [
      "tgn:2066258",
      "tgn:1002215",
      "tgn:1000001",
      "tgn:7012149",
      "tgn:7007565",
      "tgn:7029392"
    ],
    "placetype": [
      "aat:300008347"
    ],
    "id": 2066258,
    "name:xx": "Stevens"
  }
}
