{
  "geometry": {
    "type": "Point",
    "coordinates": [
      42.2167,
      46.75
    ]
  },
  "type": "Feature",
  "properties": {
    "hierarchy": [
      "tgn:1058075",
      "tgn:1000004",
      "tgn:1003405",
      "tgn:7018214",
      "tgn:7002435",
      "tgn:7029392"
    ],
    "placetype": [
      "aat:300008347"
    ],
    "id": 1058075,
    "name:xx": "Ostrov'anskij"
  }
}
