{
  "geometry": {
    "type": "Point",
    "coordinates": [
      -117.7333,
      46.1167
    ]
  },
  "type": "Feature",
  "properties": {
    "hierarchy": [
      "tgn:2364261",
      "tgn:1000001",
      "tgn:2002241",
      "tgn:7012149",
      "tgn:7007920",
      "tgn:7029392"
    ],
    "placetype": [
      "aat:300266640"
    ],
    "id": 2364261,
    "name:xx": "Green Ridge"
  }
}
