{
  "type": "FeatureCollection",
  "features": [
    {
      "geometry": {
        "type": "Point",
        "coordinates": [
          168.116667,
          -44.6
        ]
      },
      "type": "Feature",
      "properties": {
        "hierarchy": [
          "tgn:7513510",
          "tgn:1009227",
          "tgn:1000226",
          "tgn:7016822",
          "tgn:1000006",
          "tgn:7029392"
        ],
        "placetype": [
          "aat:300008699"
        ],
        "name:en": "Glacier Creek",
        "id": 7513510
      }
    },
    {
      "geometry": {
        "type": "Point",
        "coordinates": [
          171.433333,
          -43.033333
        ]
      },
      "type": "Feature",
      "properties": {
        "hierarchy": [
          "tgn:7513511",
          "tgn:1009227",
          "tgn:7001866",
          "tgn:1000226",
          "tgn:1000006",
          "tgn:7029392"
        ],
        "placetype": [
          "aat:300008795"
        ],
        "name:en": "Gizeh, Mount",
        "id": 7513511
      }
    },
    {
      "geometry": {
        "type": "Point",
        "coordinates": [
          175.433333,
          -40.8
        ]
      },
      "type": "Feature",
      "properties": {
        "hierarchy": [
          "tgn:7513515",
          "tgn:1008380",
          "tgn:7520093",
          "tgn:1000226",
          "tgn:1000006",
          "tgn:7029392"
        ],
        "placetype": [
          "aat:300008795"
        ],
        "name:en": "Girdlestone",
        "id": 7513515
      }
    },
    {
      "geometry": {
        "type": "Point",
        "coordinates": [
          170,
          -45.183333
        ]
      },
      "type": "Feature",
      "properties": {
        "hierarchy": [
          "tgn:7513517",
          "tgn:1009227",
          "tgn:1000226",
          "tgn:7018437",
          "tgn:1000006",
          "tgn:7029392"
        ],
        "placetype": [
          "aat:300008699"
        ],
        "name:en": "Gimmerburn",
        "id": 7513517
      }
    },
    {
      "geometry": {
        "type": "Point",
        "coordinates": [
          170,
          -45.166667
        ]
      },
      "type": "Feature",
      "properties": {
        "hierarchy": [
          "tgn:7513518",
          "tgn:1009227",
          "tgn:1000226",
          "tgn:7018437",
          "tgn:1000006",
          "tgn:7029392"
        ],
        "placetype": [
          "aat:300008347"
        ],
        "name:en": "Gimmerburn",
        "id": 7513518
      }
    },
    {
      "geometry": {
        "type": "Point",
        "coordinates": [
          166.233333,
          -50.883333
        ]
      },
      "type": "Feature",
      "properties": {
        "hierarchy": [
          "tgn:7513519",
          "tgn:1009227",
          "tgn:1000226",
          "tgn:7016822",
          "tgn:1000006",
          "tgn:7029392"
        ],
        "placetype": [
          "aat:300008850"
        ],
        "name:en": "Gilroy Head",
        "id": 7513519
      }
    }
  ]
}
