{
  "type": "FeatureCollection",
  "features": [
    {
      "geometry": {
        "type": "Point",
        "coordinates": [
          -3.4,
          55.533333
        ]
      },
      "type": "Feature",
      "properties": {
        "hierarchy": [
          "tgn:7460082",
          "tgn:7002444",
          "tgn:1000003",
          "tgn:7008072",
          "tgn:7008591",
          "tgn:7029392"
        ],
        "placetype": [
          "aat:300008699"
        ],
        "name:en": "Polmood Burn",
        "id": 7460082
      }
    },
    {
      "geometry": {
        "type": "Point",
        "coordinates": [
          -3.4,
          55.533333
        ]
      },
      "type": "Feature",
      "properties": {
        "hierarchy": [
          "tgn:7460083",
          "tgn:7002444",
          "tgn:1000003",
          "tgn:7008072",
          "tgn:7008591",
          "tgn:7029392"
        ],
        "placetype": [
          "aat:300008347"
        ],
        "name:en": "Polmood",
        "id": 7460083
      }
    },
    {
      "geometry": {
        "type": "Point",
        "coordinates": [
          -4.233333,
          55.816667
        ]
      },
      "type": "Feature",
      "properties": {
        "hierarchy": [
          "tgn:7460085",
          "tgn:7002444",
          "tgn:1000003",
          "tgn:7019097",
          "tgn:7008591",
          "tgn:7029392"
        ],
        "placetype": [
          "aat:300000745"
        ],
        "name:en": "Polmadie",
        "id": 7460085
      }
    },
    {
      "geometry": {
        "type": "Point",
        "coordinates": [
          -4.2,
          55.166667
        ]
      },
      "type": "Feature",
      "properties": {
        "hierarchy": [
          "tgn:7460086",
          "tgn:7002444",
          "tgn:7008074",
          "tgn:1000003",
          "tgn:7008591",
          "tgn:7029392"
        ],
        "placetype": [
          "aat:300008699"
        ],
        "name:en": "Polmaddy Burn",
        "id": 7460086
      }
    },
    {
      "geometry": {
        "type": "Point",
        "coordinates": [
          -4.633333,
          55.183333
        ]
      },
      "type": "Feature",
      "properties": {
        "hierarchy": [
          "tgn:7460087",
          "tgn:7002444",
          "tgn:1000003",
          "tgn:7019085",
          "tgn:7008591",
          "tgn:7029392"
        ],
        "placetype": [
          "aat:300008795"
        ],
        "name:en": "Polmaddie Hill",
        "id": 7460087
      }
    },
    {
      "geometry": {
        "type": "Point",
        "coordinates": [
          -5.283333,
          58.066667
        ]
      },
      "type": "Feature",
      "properties": {
        "hierarchy": [
          "tgn:7460088",
          "tgn:7002444",
          "tgn:1000003",
          "tgn:7008082",
          "tgn:7008591",
          "tgn:7029392"
        ],
        "placetype": [
          "aat:300132316"
        ],
        "name:en": "Polly, Loch",
        "id": 7460088
      }
    },
    {
      "geometry": {
        "type": "Point",
        "coordinates": [
          -5.283333,
          58.066667
        ]
      },
      "type": "Feature",
      "properties": {
        "hierarchy": [
          "tgn:7460089",
          "tgn:7002444",
          "tgn:1000003",
          "tgn:7008082",
          "tgn:7008591",
          "tgn:7029392"
        ],
        "placetype": [
          "aat:300008699"
        ],
        "name:en": "Polly, River",
        "id": 7460089
      }
    }
  ]
}
