{
  "geometry": {
    "type": "Point",
    "coordinates": [
      116.65,
      29.9833
    ]
  },
  "type": "Feature",
  "properties": {
    "hierarchy": [
      "tgn:1070269",
      "tgn:1000004",
      "tgn:7002082",
      "tgn:1000111",
      "tgn:7029392"
    ],
    "placetype": [
      "aat:300008347"
    ],
    "id": 1070269,
    "name:xx": "Madang"
  }
}
