{
  "geometry": {
    "type": "Point",
    "coordinates": [
      -60.666,
      11.25
    ]
  },
  "type": "Feature",
  "properties": {
    "hierarchy": [
      "tgn:7593622",
      "tgn:1000001",
      "tgn:7004787",
      "tgn:7029392"
    ],
    "placetype": [
      "aat:300387064"
    ],
    "id": 7593622,
    "name:xx": "Tobago"
  }
}
