{
  "geometry": {
    "type": "Point",
    "coordinates": [
      -93.3833,
      36.8667
    ]
  },
  "type": "Feature",
  "properties": {
    "hierarchy": [
      "tgn:2765587",
      "tgn:1000001",
      "tgn:7012149",
      "tgn:2001249",
      "tgn:7007523",
      "tgn:7029392"
    ],
    "placetype": [
      "aat:300008347"
    ],
    "id": 2765587,
    "name:xx": "White City"
  }
}
