{
  "geometry": {
    "type": "Point",
    "coordinates": [
      -83.9167,
      35.0333
    ]
  },
  "type": "Feature",
  "properties": {
    "hierarchy": [
      "tgn:2201203",
      "tgn:1000001",
      "tgn:2001483",
      "tgn:7012149",
      "tgn:7007709",
      "tgn:7029392"
    ],
    "placetype": [
      "aat:300008699"
    ],
    "id": 2201203,
    "name:xx": "Buchanan Branch"
  }
}
