{
  "geometry": {
    "type": "Point",
    "coordinates": [
      -89.1667,
      41.45
    ]
  },
  "type": "Feature",
  "properties": {
    "hierarchy": [
      "tgn:2537261",
      "tgn:1000001",
      "tgn:2000497",
      "tgn:7012149",
      "tgn:7007251",
      "tgn:7029392"
    ],
    "placetype": [
      "aat:300008706"
    ],
    "id": 2537261,
    "name:xx": "Negro Creek"
  }
}
