{
  "geometry": {
    "type": "Point",
    "coordinates": [
      -121.3833,
      45.55
    ]
  },
  "type": "Feature",
  "properties": {
    "hierarchy": [
      "tgn:2657691",
      "tgn:1000001",
      "tgn:7012149",
      "tgn:1002990",
      "tgn:7007708",
      "tgn:7029392"
    ],
    "placetype": [
      "aat:300266640"
    ],
    "id": 2657691,
    "name:xx": "Sheldon Ridge"
  }
}
