{
  "geometry": {
    "type": "Point",
    "coordinates": [
      -122.9833,
      44.9333
    ]
  },
  "type": "Feature",
  "properties": {
    "hierarchy": [
      "tgn:2518498",
      "tgn:1000001",
      "tgn:7012149",
      "tgn:1002636",
      "tgn:7007708",
      "tgn:7029392"
    ],
    "placetype": [
      "aat:300008347"
    ],
    "id": 2518498,
    "name:xx": "Mitchell Corner"
  }
}
