{
  "geometry": {
    "type": "Point",
    "coordinates": [
      30.918056,
      31.529167
    ]
  },
  "type": "Feature",
  "properties": {
    "hierarchy": [
      "tgn:7525087",
      "tgn:7001242",
      "tgn:7016833",
      "tgn:1001335",
      "tgn:7029392"
    ],
    "placetype": [
      "aat:300008791"
    ],
    "name:en": "Bāb ash Shīshah, Jazīrat",
    "id": 7525087
  }
}
