{
  "geometry": {
    "type": "Point",
    "coordinates": [
      -113.3333,
      46.1167
    ]
  },
  "type": "Feature",
  "properties": {
    "hierarchy": [
      "tgn:2180380",
      "tgn:1000001",
      "tgn:7012149",
      "tgn:2001279",
      "tgn:7007524",
      "tgn:7029392"
    ],
    "placetype": [
      "aat:300008761"
    ],
    "id": 2180380,
    "name:xx": "Blodgett Gulch"
  }
}
