{
  "geometry": {
    "type": "Point",
    "coordinates": [
      -75.05,
      38.4833
    ]
  },
  "type": "Feature",
  "properties": {
    "hierarchy": [
      "tgn:2355988",
      "tgn:1002933",
      "tgn:1000001",
      "tgn:7012149",
      "tgn:7007239",
      "tgn:7029392"
    ],
    "placetype": [
      "aat:300008680"
    ],
    "id": 2355988,
    "name:xx": "Goose Pond"
  }
}
