{
  "geometry": {
    "type": "Point",
    "coordinates": [
      -81.2833,
      38.95
    ]
  },
  "type": "Feature",
  "properties": {
    "hierarchy": [
      "tgn:2738290",
      "tgn:1000001",
      "tgn:7012149",
      "tgn:2002302",
      "tgn:7013961",
      "tgn:7029392"
    ],
    "placetype": [
      "aat:300266640"
    ],
    "id": 2738290,
    "name:xx": "Umpsted Ridge"
  }
}
