{
  "geometry": {
    "type": "Point",
    "coordinates": [
      -121.0833,
      43.0833
    ]
  },
  "type": "Feature",
  "properties": {
    "hierarchy": [
      "tgn:2208326",
      "tgn:1000001",
      "tgn:7012149",
      "tgn:2001715",
      "tgn:7007708",
      "tgn:7029392"
    ],
    "placetype": [
      "aat:300006191"
    ],
    "id": 2208326,
    "name:xx": "Burn Waterhole"
  }
}
