{
  "geometry": {
    "type": "Point",
    "coordinates": [
      -83.3833,
      44.7333
    ]
  },
  "type": "Feature",
  "properties": {
    "hierarchy": [
      "tgn:2515327",
      "tgn:2000942",
      "tgn:1000001",
      "tgn:7012149",
      "tgn:7007520",
      "tgn:7029392"
    ],
    "placetype": [
      "aat:300008680"
    ],
    "id": 2515327,
    "name:xx": "Millikin Lake"
  }
}
