{
  "geometry": {
    "type": "Point",
    "coordinates": [
      77.536451,
      31.54969
    ]
  },
  "type": "Feature",
  "properties": {
    "hierarchy": [
      "tgn:7558623",
      "tgn:1000004",
      "tgn:7000198",
      "tgn:1001996",
      "tgn:7029392"
    ],
    "placetype": [
      "aat:300008347"
    ],
    "name:en": "Sarāhan",
    "id": 7558623
  }
}
