{
  "geometry": {
    "type": "Point",
    "coordinates": [
      -91.1667,
      40.4667
    ]
  },
  "type": "Feature",
  "properties": {
    "hierarchy": [
      "tgn:2623547",
      "tgn:1000001",
      "tgn:7012149",
      "tgn:1002446",
      "tgn:7007251",
      "tgn:7029392"
    ],
    "placetype": [
      "aat:300008706"
    ],
    "id": 2623547,
    "name:xx": "Rock Creek"
  }
}
