{
  "type": "FeatureCollection",
  "features": [
    {
      "geometry": {
        "type": "Point",
        "coordinates": [
          -102.366667,
          19.216667
        ]
      },
      "type": "Feature",
      "properties": {
        "hierarchy": [
          "tgn:7357080",
          "tgn:1000001",
          "tgn:7005590",
          "tgn:7005560",
          "tgn:7029392"
        ],
        "placetype": [
          "aat:300000241"
        ],
        "id": 7357080,
        "name:xx": "Carrizal"
      }
    },
    {
      "geometry": {
        "type": "Point",
        "coordinates": [
          -106.65,
          30.566667
        ]
      },
      "type": "Feature",
      "properties": {
        "hierarchy": [
          "tgn:7357081",
          "tgn:7005581",
          "tgn:1000001",
          "tgn:7005560",
          "tgn:7029392"
        ],
        "placetype": [
          "aat:300008347"
        ],
        "id": 7357081,
        "name:xx": "Carrizal"
      }
    },
    {
      "geometry": {
        "type": "Point",
        "coordinates": [
          -106.783333,
          30.383333
        ]
      },
      "type": "Feature",
      "properties": {
        "hierarchy": [
          "tgn:7357082",
          "tgn:7005581",
          "tgn:1000001",
          "tgn:7005560",
          "tgn:7029392"
        ],
        "placetype": [
          "aat:300008347"
        ],
        "id": 7357082,
        "name:xx": "Carrizal"
      }
    },
    {
      "geometry": {
        "type": "Point",
        "coordinates": [
          -109.616667,
          29.266667
        ]
      },
      "type": "Feature",
      "properties": {
        "hierarchy": [
          "tgn:7357083",
          "tgn:1000001",
          "tgn:1001960",
          "tgn:7005560",
          "tgn:7029392"
        ],
        "placetype": [
          "aat:300008347"
        ],
        "id": 7357083,
        "name:xx": "Carrizal"
      }
    },
    {
      "geometry": {
        "type": "Point",
        "coordinates": [
          -110.583333,
          28.6
        ]
      },
      "type": "Feature",
      "properties": {
        "hierarchy": [
          "tgn:7357084",
          "tgn:1000001",
          "tgn:1001960",
          "tgn:7005560",
          "tgn:7029392"
        ],
        "placetype": [
          "aat:300008347"
        ],
        "id": 7357084,
        "name:xx": "Carrizal"
      }
    },
    {
      "geometry": {
        "type": "Point",
        "coordinates": [
          -109.25,
          28.433333
        ]
      },
      "type": "Feature",
      "properties": {
        "hierarchy": [
          "tgn:7357085",
          "tgn:1000001",
          "tgn:1001960",
          "tgn:7005560",
          "tgn:7029392"
        ],
        "placetype": [
          "aat:300008347"
        ],
        "id": 7357085,
        "name:xx": "Carrizal"
      }
    },
    {
      "geometry": {
        "type": "Point",
        "coordinates": [
          -105.933333,
          27.366667
        ]
      },
      "type": "Feature",
      "properties": {
        "hierarchy": [
          "tgn:7357087",
          "tgn:7005581",
          "tgn:1000001",
          "tgn:7005560",
          "tgn:7029392"
        ],
        "placetype": [
          "aat:300008347"
        ],
        "id": 7357087,
        "name:xx": "Carrizal"
      }
    },
    {
      "geometry": {
        "type": "Point",
        "coordinates": [
          -109.05,
          27.083333
        ]
      },
      "type": "Feature",
      "properties": {
        "hierarchy": [
          "tgn:7357088",
          "tgn:1000001",
          "tgn:1001960",
          "tgn:7005560",
          "tgn:7029392"
        ],
        "placetype": [
          "aat:300008347"
        ],
        "id": 7357088,
        "name:xx": "Carrizal"
      }
    },
    {
      "geometry": {
        "type": "Point",
        "coordinates": [
          -102.183333,
          26.966667
        ]
      },
      "type": "Feature",
      "properties": {
        "hierarchy": [
          "tgn:7357089",
          "tgn:1001853",
          "tgn:1000001",
          "tgn:7005560",
          "tgn:7029392"
        ],
        "placetype": [
          "aat:300008347"
        ],
        "id": 7357089,
        "name:xx": "Carrizal"
      }
    }
  ]
}
