{
  "geometry": {
    "type": "Point",
    "coordinates": [
      -80.3833,
      38.1833
    ]
  },
  "type": "Feature",
  "properties": {
    "hierarchy": [
      "tgn:2334768",
      "tgn:1000001",
      "tgn:7012149",
      "tgn:2002264",
      "tgn:7013961",
      "tgn:7029392"
    ],
    "placetype": [
      "aat:300008798"
    ],
    "id": 2334768,
    "name:xx": "Fork Mountain"
  }
}
