{
  "geometry": {
    "type": "Point",
    "coordinates": [
      -117.8167,
      37.7167
    ]
  },
  "type": "Feature",
  "properties": {
    "hierarchy": [
      "tgn:2413075",
      "tgn:1000001",
      "tgn:2001412",
      "tgn:7012149",
      "tgn:7007526",
      "tgn:7029392"
    ],
    "placetype": [
      "aat:300000390"
    ],
    "id": 2413075,
    "name:xx": "Inman Group Mine"
  }
}
