{
  "geometry": {
    "type": "Point",
    "coordinates": [
      -109.9167,
      34.25
    ]
  },
  "type": "Feature",
  "properties": {
    "hierarchy": [
      "tgn:2125175",
      "tgn:1000001",
      "tgn:7006451",
      "tgn:7012149",
      "tgn:2000099",
      "tgn:7029392"
    ],
    "placetype": [
      "aat:300006191"
    ],
    "id": 2125175,
    "name:xx": "Accord Tank"
  }
}
