{
  "geometry": {
    "type": "Point",
    "coordinates": [
      -85.0667,
      31.6333
    ]
  },
  "type": "Feature",
  "properties": {
    "hierarchy": [
      "tgn:2556302",
      "tgn:1000001",
      "tgn:2000321",
      "tgn:7012149",
      "tgn:7007248",
      "tgn:7029392"
    ],
    "placetype": [
      "aat:300008347",
      "aat:300167671"
    ],
    "id": 2556302,
    "name:xx": "Oketeyeconne"
  }
}
