{
  "geometry": {
    "type": "Point",
    "coordinates": [
      39.3167,
      38.8833
    ]
  },
  "type": "Feature",
  "properties": {
    "hierarchy": [
      "tgn:1086783",
      "tgn:1000004",
      "tgn:1001581",
      "tgn:7018455",
      "tgn:1000144",
      "tgn:7029392"
    ],
    "placetype": [
      "aat:300008347"
    ],
    "id": 1086783,
    "name:xx": "Pertek"
  }
}
