{
  "geometry": {
    "type": "Point",
    "coordinates": [
      79.064307,
      26.772569
    ]
  },
  "type": "Feature",
  "properties": {
    "hierarchy": [
      "tgn:7561645",
      "tgn:1000004",
      "tgn:7000198",
      "tgn:7016722",
      "tgn:7029392"
    ],
    "placetype": [
      "aat:300008347"
    ],
    "name:en": "Rāmpur Nāoli",
    "id": 7561645
  }
}
