{
  "geometry": {
    "type": "Point",
    "coordinates": [
      -71.7667,
      41.5333
    ]
  },
  "type": "Feature",
  "properties": {
    "hierarchy": [
      "tgn:2525707",
      "tgn:1002996",
      "tgn:1000001",
      "tgn:7012149",
      "tgn:7007711",
      "tgn:7029392"
    ],
    "placetype": [
      "aat:300008699"
    ],
    "id": 2525707,
    "name:xx": "Moscow Brook"
  }
}
