{
  "geometry": {
    "type": "Point",
    "coordinates": [
      -95.4167,
      42.3667
    ]
  },
  "type": "Feature",
  "properties": {
    "hierarchy": [
      "tgn:2231251",
      "tgn:1000001",
      "tgn:7012149",
      "tgn:2000632",
      "tgn:7007253",
      "tgn:7029392"
    ],
    "placetype": [
      "aat:300008680"
    ],
    "id": 2231251,
    "name:xx": "Chain Lake"
  }
}
