{
  "geometry": {
    "type": "Point",
    "coordinates": [
      25.55,
      56.8333
    ]
  },
  "type": "Feature",
  "properties": {
    "hierarchy": [
      "tgn:1051879",
      "tgn:7012152",
      "tgn:1000003",
      "tgn:7006541",
      "tgn:7029392"
    ],
    "placetype": [
      "aat:300008347"
    ],
    "id": 1051879,
    "name:xx": "Ērgļi"
  }
}
