{
  "geometry": {
    "type": "Point",
    "coordinates": [
      -89.3667,
      37.55
    ]
  },
  "type": "Feature",
  "properties": {
    "hierarchy": [
      "tgn:2606932",
      "tgn:1000001",
      "tgn:7012149",
      "tgn:7007251",
      "tgn:7029392"
    ],
    "placetype": [
      "aat:300008761"
    ],
    "id": 2606932,
    "name:xx": "Ranbarger Hollow"
  }
}
