{
  "type": "FeatureCollection",
  "features": [
    {
      "geometry": {
        "type": "Point",
        "coordinates": [
          -93.2,
          31.65
        ]
      },
      "type": "Feature",
      "properties": {
        "hierarchy": [
          "tgn:2043812",
          "tgn:1000001",
          "tgn:7012149",
          "tgn:2000888",
          "tgn:7007256",
          "tgn:7029392"
        ],
        "placetype": [
          "aat:300008347"
        ],
        "id": 2043812,
        "name:xx": "Provencal"
      }
    },
    {
      "geometry": {
        "type": "Point",
        "coordinates": [
          -91.0333,
          30.5667
        ]
      },
      "type": "Feature",
      "properties": {
        "hierarchy": [
          "tgn:2043814",
          "tgn:1000001",
          "tgn:2000870",
          "tgn:7012149",
          "tgn:7007256",
          "tgn:7029392"
        ],
        "placetype": [
          "aat:300008347",
          "aat:300387210"
        ],
        "id": 2043814,
        "name:xx": "Puckett"
      }
    },
    {
      "geometry": {
        "type": "Point",
        "coordinates": [
          -90.5333,
          30.45
        ]
      },
      "type": "Feature",
      "properties": {
        "hierarchy": [
          "tgn:2043816",
          "tgn:1000001",
          "tgn:7012149",
          "tgn:2000906",
          "tgn:7007256",
          "tgn:7029392"
        ],
        "placetype": [
          "aat:300008347"
        ],
        "id": 2043816,
        "name:xx": "Pumpkin Center"
      }
    },
    {
      "geometry": {
        "type": "Point",
        "coordinates": [
          -92.7,
          32.3
        ]
      },
      "type": "Feature",
      "properties": {
        "hierarchy": [
          "tgn:2043817",
          "tgn:1000001",
          "tgn:7012149",
          "tgn:2000878",
          "tgn:7007256",
          "tgn:7029392"
        ],
        "placetype": [
          "aat:300008347",
          "aat:300387210"
        ],
        "id": 2043817,
        "name:xx": "Punkin Center"
      }
    },
    {
      "geometry": {
        "type": "Point",
        "coordinates": [
          -91.8,
          31.6667
        ]
      },
      "type": "Feature",
      "properties": {
        "hierarchy": [
          "tgn:2043818",
          "tgn:1000001",
          "tgn:2000866",
          "tgn:7012149",
          "tgn:7007256",
          "tgn:7029392"
        ],
        "placetype": [
          "aat:300008347",
          "aat:300387210"
        ],
        "id": 2043818,
        "name:xx": "Quaid"
      }
    },
    {
      "geometry": {
        "type": "Point",
        "coordinates": [
          -91.2,
          32.2333
        ]
      },
      "type": "Feature",
      "properties": {
        "hierarchy": [
          "tgn:2043819",
          "tgn:1000001",
          "tgn:7012149",
          "tgn:2000886",
          "tgn:7007256",
          "tgn:7029392"
        ],
        "placetype": [
          "aat:300008347",
          "aat:300387210"
        ],
        "id": 2043819,
        "name:xx": "Quimby"
      }
    }
  ]
}
