{
  "geometry": {
    "type": "Point",
    "coordinates": [
      76.82604,
      30.123261
    ]
  },
  "type": "Feature",
  "properties": {
    "hierarchy": [
      "tgn:7582997",
      "tgn:1000004",
      "tgn:1001871",
      "tgn:7000198",
      "tgn:7029392"
    ],
    "placetype": [
      "aat:300008347"
    ],
    "name:en": "Tigri",
    "id": 7582997
  }
}
