{
  "geometry": {
    "type": "Point",
    "coordinates": [
      48.5833,
      34.7667
    ]
  },
  "type": "Feature",
  "properties": {
    "hierarchy": [
      "tgn:7002115",
      "tgn:1000004",
      "tgn:1001283",
      "tgn:7000231",
      "tgn:7029392"
    ],
    "placetype": [
      "aat:300008347",
      "aat:300387218",
      "aat:300008389",
      "aat:300387223",
      "aat:300343603",
      "aat:300387286"
    ],
    "id": 7002115,
    "name:xx": "Hamadān"
  }
}
