{
  "geometry": {
    "type": "Point",
    "coordinates": [
      -134.6667,
      59.1833
    ]
  },
  "type": "Feature",
  "properties": {
    "hierarchy": [
      "tgn:2189234",
      "tgn:7006450",
      "tgn:1000001",
      "tgn:2124077",
      "tgn:7012149",
      "tgn:7029392"
    ],
    "placetype": [
      "aat:300008798"
    ],
    "id": 2189234,
    "name:xx": "Boundary Peak 104"
  }
}
