{
  "geometry": {
    "type": "Point",
    "coordinates": [
      -81.9667,
      31.2833
    ]
  },
  "type": "Feature",
  "properties": {
    "hierarchy": [
      "tgn:2186961",
      "tgn:1000001",
      "tgn:2000304",
      "tgn:7012149",
      "tgn:7007248",
      "tgn:7029392"
    ],
    "placetype": [
      "aat:300008680"
    ],
    "id": 2186961,
    "name:xx": "Bonnet Lake"
  }
}
