{
  "geometry": {
    "type": "Point",
    "coordinates": [
      -108.1333,
      36.9667
    ]
  },
  "type": "Feature",
  "properties": {
    "hierarchy": [
      "tgn:7022536",
      "tgn:1000001",
      "tgn:7012149",
      "tgn:7029392"
    ],
    "placetype": [
      "aat:300008761"
    ],
    "id": 7022536,
    "name:xx": "Cinder Gulch"
  }
}
