{
  "geometry": {
    "type": "Point",
    "coordinates": [
      121.38861,
      23.46168
    ]
  },
  "type": "Feature",
  "properties": {
    "hierarchy": [
      "tgn:7499512",
      "tgn:7001010",
      "tgn:1000004",
      "tgn:1000141",
      "tgn:7029392"
    ],
    "placetype": [
      "aat:300008347"
    ],
    "id": 7499512,
    "name:xx": "Shennong"
  }
}
