{
  "geometry": {
    "type": "Point",
    "coordinates": [
      -89.3833,
      41.2833
    ]
  },
  "type": "Feature",
  "properties": {
    "hierarchy": [
      "tgn:2556688",
      "tgn:1000001",
      "tgn:2000497",
      "tgn:7012149",
      "tgn:7007251",
      "tgn:7029392"
    ],
    "placetype": [
      "aat:300008706"
    ],
    "id": 2556688,
    "name:xx": "Old Channel Big Bureau Creek"
  }
}
