{
  "geometry": {
    "type": "Point",
    "coordinates": [
      -75.6667,
      42.8833
    ]
  },
  "type": "Feature",
  "properties": {
    "hierarchy": [
      "tgn:2772543",
      "tgn:1000001",
      "tgn:7012149",
      "tgn:1002624",
      "tgn:7007568",
      "tgn:7029392"
    ],
    "placetype": [
      "aat:300008347"
    ],
    "id": 2772543,
    "name:xx": "Williams Corners"
  }
}
