{
  "geometry": {
    "type": "Point",
    "coordinates": [
      -78.4833,
      42.25
    ]
  },
  "type": "Feature",
  "properties": {
    "hierarchy": [
      "tgn:2548127",
      "tgn:1000001",
      "tgn:1002245",
      "tgn:7012149",
      "tgn:7007568",
      "tgn:7029392"
    ],
    "placetype": [
      "aat:300008761"
    ],
    "id": 2548127,
    "name:xx": "North Hollow"
  }
}
