{
  "geometry": {
    "type": "Point",
    "coordinates": [
      -2.05,
      34.0833
    ]
  },
  "type": "Feature",
  "properties": {
    "hierarchy": [
      "tgn:1111128",
      "tgn:7001242",
      "tgn:1000179",
      "tgn:7593681",
      "tgn:7029392"
    ],
    "placetype": [
      "aat:300387091"
    ],
    "id": 1111128,
    "name:xx": "Charef, Oued"
  }
}
