{
  "geometry": {
    "type": "Point",
    "coordinates": [
      -103.1667,
      48.2167
    ]
  },
  "type": "Feature",
  "properties": {
    "hierarchy": [
      "tgn:2371930",
      "tgn:1000001",
      "tgn:7012149",
      "tgn:2001609",
      "tgn:7007705",
      "tgn:7029392"
    ],
    "placetype": [
      "aat:300008761"
    ],
    "id": 2371930,
    "name:xx": "Half Breed Coulee"
  }
}
