{
  "geometry": {
    "type": "Point",
    "coordinates": [
      -78.2667,
      41.4833
    ]
  },
  "type": "Feature",
  "properties": {
    "hierarchy": [
      "tgn:2094314",
      "tgn:1000001",
      "tgn:1002229",
      "tgn:7012149",
      "tgn:7007710",
      "tgn:7029392"
    ],
    "placetype": [
      "aat:300008347",
      "aat:300387210"
    ],
    "id": 2094314,
    "name:xx": "West Creek"
  }
}
