{
  "geometry": {
    "type": "Point",
    "coordinates": [
      -105.6667,
      39.8833
    ]
  },
  "type": "Feature",
  "properties": {
    "hierarchy": [
      "tgn:2265833",
      "tgn:1000001",
      "tgn:7012149",
      "tgn:2000215",
      "tgn:7007158",
      "tgn:7029392"
    ],
    "placetype": [
      "aat:300008680"
    ],
    "id": 2265833,
    "name:xx": "Crater Lakes"
  }
}
