{
  "geometry": {
    "type": "Point",
    "coordinates": [
      14.2333,
      46.1667
    ]
  },
  "type": "Feature",
  "properties": {
    "hierarchy": [
      "tgn:7015136",
      "tgn:1000003",
      "tgn:7006670",
      "tgn:7029392"
    ],
    "placetype": [
      "aat:300387064",
      "aat:300387081"
    ],
    "id": 7015136,
    "name:xx": "Škofja Loka, Občina"
  }
}
