{
  "geometry": {
    "type": "Point",
    "coordinates": [
      -112.0167,
      40.65
    ]
  },
  "type": "Feature",
  "properties": {
    "hierarchy": [
      "tgn:2233822",
      "tgn:1000001",
      "tgn:7012149",
      "tgn:2002118",
      "tgn:7007827",
      "tgn:7029392"
    ],
    "placetype": [
      "aat:300008347"
    ],
    "id": 2233822,
    "name:xx": "Chateau Village"
  }
}
