{
  "geometry": {
    "type": "Point",
    "coordinates": [
      -80.9667,
      38.4833
    ]
  },
  "type": "Feature",
  "properties": {
    "hierarchy": [
      "tgn:2169201",
      "tgn:1000001",
      "tgn:2002259",
      "tgn:7012149",
      "tgn:7013961",
      "tgn:7029392"
    ],
    "placetype": [
      "aat:300008798"
    ],
    "id": 2169201,
    "name:xx": "Big Knob"
  }
}
