{
  "geometry": {
    "type": "Point",
    "coordinates": [
      -82.0167,
      40.8667
    ]
  },
  "type": "Feature",
  "properties": {
    "hierarchy": [
      "tgn:2078769",
      "tgn:1000001",
      "tgn:7012149",
      "tgn:1003007",
      "tgn:7007706",
      "tgn:7029392"
    ],
    "placetype": [
      "aat:300008347"
    ],
    "id": 2078769,
    "name:xx": "Cedar Valley"
  }
}
