{
  "geometry": {
    "type": "Point",
    "coordinates": [
      -82.2667,
      34.7167
    ]
  },
  "type": "Feature",
  "properties": {
    "hierarchy": [
      "tgn:2193508",
      "tgn:1000001",
      "tgn:2001747",
      "tgn:7012149",
      "tgn:7007712",
      "tgn:7029392"
    ],
    "placetype": [
      "aat:300008347"
    ],
    "id": 2193508,
    "name:xx": "Brentwood"
  }
}
