{
  "geometry": {
    "type": "Point",
    "coordinates": [
      -76.8167,
      35.2667
    ]
  },
  "type": "Feature",
  "properties": {
    "hierarchy": [
      "tgn:2273556",
      "tgn:1000001",
      "tgn:7013368",
      "tgn:7012149",
      "tgn:7007709",
      "tgn:7029392"
    ],
    "placetype": [
      "aat:300008699"
    ],
    "id": 2273556,
    "name:xx": "Cypress Run"
  }
}
