{
  "geometry": {
    "type": "Point",
    "coordinates": [
      -90.2167,
      46.4667
    ]
  },
  "type": "Feature",
  "properties": {
    "hierarchy": [
      "tgn:2429959",
      "tgn:1000001",
      "tgn:7012149",
      "tgn:2002327",
      "tgn:7007922",
      "tgn:7029392"
    ],
    "placetype": [
      "aat:300008706"
    ],
    "id": 2429959,
    "name:xx": "Kaari Creek"
  }
}
