{
  "geometry": {
    "type": "Point",
    "coordinates": [
      14.15,
      51.75
    ]
  },
  "type": "Feature",
  "properties": {
    "hierarchy": [
      "tgn:7150973",
      "tgn:7000096",
      "tgn:1000003",
      "tgn:7000084",
      "tgn:7029392"
    ],
    "placetype": [
      "aat:300008347"
    ],
    "id": 7150973,
    "name:xx": "Krieschow Wiesendorf"
  }
}
