{
  "geometry": {
    "type": "Point",
    "coordinates": [
      30.969722,
      31.4325
    ]
  },
  "type": "Feature",
  "properties": {
    "hierarchy": [
      "tgn:7526561",
      "tgn:7001242",
      "tgn:7016833",
      "tgn:1001335",
      "tgn:7029392"
    ],
    "placetype": [
      "aat:300008699"
    ],
    "name:en": "Waḩḩāl, Khalīj al",
    "id": 7526561
  }
}
