{
  "geometry": {
    "type": "Point",
    "coordinates": [
      -93.95,
      37.3333
    ]
  },
  "type": "Feature",
  "properties": {
    "hierarchy": [
      "tgn:2400092",
      "tgn:1000001",
      "tgn:7012149",
      "tgn:7007523",
      "tgn:7029392"
    ],
    "placetype": [
      "aat:300008706"
    ],
    "id": 2400092,
    "name:xx": "Horse Creek"
  }
}
