{
  "geometry": {
    "type": "Point",
    "coordinates": [
      33.720833,
      29.204167
    ]
  },
  "type": "Feature",
  "properties": {
    "hierarchy": [
      "tgn:7544136",
      "tgn:7001242",
      "tgn:7016833",
      "tgn:7001336",
      "tgn:7029392"
    ],
    "placetype": [
      "aat:300379998"
    ],
    "id": 7544136,
    "name:xx": "Washūāshī, Wādī"
  }
}
