{
  "geometry": {
    "type": "Point",
    "coordinates": [
      -77.2833,
      40.5667
    ]
  },
  "type": "Feature",
  "properties": {
    "hierarchy": [
      "tgn:2094071",
      "tgn:1000001",
      "tgn:7012149",
      "tgn:1002528",
      "tgn:7007710",
      "tgn:7029392"
    ],
    "placetype": [
      "aat:300008347"
    ],
    "id": 2094071,
    "name:xx": "Van Wert"
  }
}
