{
  "geometry": {
    "type": "Point",
    "coordinates": [
      -95.55,
      47.3167
    ]
  },
  "type": "Feature",
  "properties": {
    "hierarchy": [
      "tgn:2055380",
      "tgn:1000001",
      "tgn:2001013",
      "tgn:7012149",
      "tgn:7007521",
      "tgn:7029392"
    ],
    "placetype": [
      "aat:300008347"
    ],
    "id": 2055380,
    "name:xx": "Roy Lake"
  }
}
