{
  "geometry": {
    "type": "Point",
    "coordinates": [
      -89.05,
      33.7667
    ]
  },
  "type": "Feature",
  "properties": {
    "hierarchy": [
      "tgn:2057809",
      "tgn:1000001",
      "tgn:2001094",
      "tgn:7012149",
      "tgn:7007522",
      "tgn:7029392"
    ],
    "placetype": [
      "aat:300008347"
    ],
    "id": 2057809,
    "name:xx": "Woodland"
  }
}
