{
  "type": "FeatureCollection",
  "features": [
    {
      "geometry": {
        "type": "Point",
        "coordinates": [
          5.583333,
          50.816667
        ]
      },
      "type": "Feature",
      "properties": {
        "hierarchy": [
          "tgn:7254881",
          "tgn:7003461",
          "tgn:1000003",
          "tgn:1000063",
          "tgn:7018236",
          "tgn:7029392"
        ],
        "placetype": [
          "aat:300008347"
        ],
        "id": 7254881,
        "name:xx": "Siberg"
      }
    },
    {
      "geometry": {
        "type": "Point",
        "coordinates": [
          4.816667,
          50.966667
        ]
      },
      "type": "Feature",
      "properties": {
        "hierarchy": [
          "tgn:7254882",
          "tgn:7003456",
          "tgn:1000003",
          "tgn:1000063",
          "tgn:7018236",
          "tgn:7029392"
        ],
        "placetype": [
          "aat:300008863"
        ],
        "id": 7254882,
        "name:xx": "'s Hertogenbos"
      }
    },
    {
      "geometry": {
        "type": "Point",
        "coordinates": [
          5.066667,
          51.216667
        ]
      },
      "type": "Feature",
      "properties": {
        "hierarchy": [
          "tgn:7254883",
          "tgn:7003456",
          "tgn:1000003",
          "tgn:1000063",
          "tgn:7018236",
          "tgn:7029392"
        ],
        "placetype": [
          "aat:300008863"
        ],
        "id": 7254883,
        "name:xx": "'s Herenhei"
      }
    },
    {
      "geometry": {
        "type": "Point",
        "coordinates": [
          5.500672,
          50.808815
        ]
      },
      "type": "Feature",
      "properties": {
        "hierarchy": [
          "tgn:7254884",
          "tgn:7003461",
          "tgn:1000003",
          "tgn:1000063",
          "tgn:7018236",
          "tgn:7029392"
        ],
        "placetype": [
          "aat:300008347"
        ],
        "id": 7254884,
        "name:xx": "'s-Herenelderen"
      }
    },
    {
      "geometry": {
        "type": "Point",
        "coordinates": [
          4.733333,
          51.283333
        ]
      },
      "type": "Feature",
      "properties": {
        "hierarchy": [
          "tgn:7254886",
          "tgn:7003456",
          "tgn:1000003",
          "tgn:1000063",
          "tgn:7018236",
          "tgn:7029392"
        ],
        "placetype": [
          "aat:300008863"
        ],
        "id": 7254886,
        "name:xx": "'s Herenbos"
      }
    },
    {
      "geometry": {
        "type": "Point",
        "coordinates": [
          2.753498,
          51.068985
        ]
      },
      "type": "Feature",
      "properties": {
        "hierarchy": [
          "tgn:7254887",
          "tgn:7003458",
          "tgn:1000003",
          "tgn:1000063",
          "tgn:7018236",
          "tgn:7029392"
        ],
        "placetype": [
          "aat:300008347"
        ],
        "id": 7254887,
        "name:xx": "'s Heerwillemskapelle"
      }
    },
    {
      "geometry": {
        "type": "Point",
        "coordinates": [
          4.554093,
          51.258672
        ]
      },
      "type": "Feature",
      "properties": {
        "hierarchy": [
          "tgn:7254888",
          "tgn:7003456",
          "tgn:1000003",
          "tgn:1000063",
          "tgn:7018236",
          "tgn:7029392"
        ],
        "placetype": [
          "aat:300008347"
        ],
        "id": 7254888,
        "name:xx": "'s-Gravenwezel"
      }
    }
  ]
}
