{
  "geometry": {
    "type": "Point",
    "coordinates": [
      -85.9667,
      44.05
    ]
  },
  "type": "Feature",
  "properties": {
    "hierarchy": [
      "tgn:2383336",
      "tgn:1000001",
      "tgn:7012149",
      "tgn:2000970",
      "tgn:7007520",
      "tgn:7029392"
    ],
    "placetype": [
      "aat:300008680"
    ],
    "id": 2383336,
    "name:xx": "Heart Lake"
  }
}
