{
  "geometry": {
    "type": "Point",
    "coordinates": [
      -81.2833,
      25.6667
    ]
  },
  "type": "Feature",
  "properties": {
    "hierarchy": [
      "tgn:2524677",
      "tgn:1000001",
      "tgn:2000275",
      "tgn:7012149",
      "tgn:7007240",
      "tgn:7029392"
    ],
    "placetype": [
      "aat:300008791"
    ],
    "id": 2524677,
    "name:xx": "Mormon Key"
  }
}
