{
  "type": "FeatureCollection",
  "features": [
    {
      "geometry": {
        "type": "Point",
        "coordinates": [
          -79.2,
          40.3667
        ]
      },
      "type": "Feature",
      "properties": {
        "hierarchy": [
          "tgn:2298480",
          "tgn:1000001",
          "tgn:7012149",
          "tgn:1003017",
          "tgn:7007710",
          "tgn:7029392"
        ],
        "placetype": [
          "aat:300008699"
        ],
        "id": 2298480,
        "name:xx": "Dry Run"
      }
    },
    {
      "geometry": {
        "type": "Point",
        "coordinates": [
          -76.7167,
          40.5333
        ]
      },
      "type": "Feature",
      "properties": {
        "hierarchy": [
          "tgn:2298481",
          "tgn:1000001",
          "tgn:1002318",
          "tgn:7012149",
          "tgn:7007710",
          "tgn:7029392"
        ],
        "placetype": [
          "aat:300008699"
        ],
        "id": 2298481,
        "name:xx": "Dry Run"
      }
    },
    {
      "geometry": {
        "type": "Point",
        "coordinates": [
          -75.4667,
          40.7
        ]
      },
      "type": "Feature",
      "properties": {
        "hierarchy": [
          "tgn:2298482",
          "tgn:1000001",
          "tgn:7012149",
          "tgn:1002729",
          "tgn:7007710",
          "tgn:7029392"
        ],
        "placetype": [
          "aat:300008699"
        ],
        "id": 2298482,
        "name:xx": "Dry Run"
      }
    },
    {
      "geometry": {
        "type": "Point",
        "coordinates": [
          -76.9833,
          40.7667
        ]
      },
      "type": "Feature",
      "properties": {
        "hierarchy": [
          "tgn:2298483",
          "tgn:1000001",
          "tgn:7012149",
          "tgn:1002900",
          "tgn:7007710",
          "tgn:7029392"
        ],
        "placetype": [
          "aat:300008699"
        ],
        "id": 2298483,
        "name:xx": "Dry Run"
      }
    },
    {
      "geometry": {
        "type": "Point",
        "coordinates": [
          -77.9,
          41.2333
        ]
      },
      "type": "Feature",
      "properties": {
        "hierarchy": [
          "tgn:2298484",
          "tgn:1000001",
          "tgn:1002286",
          "tgn:7012149",
          "tgn:7007710",
          "tgn:7029392"
        ],
        "placetype": [
          "aat:300008699"
        ],
        "id": 2298484,
        "name:xx": "Dry Run"
      }
    },
    {
      "geometry": {
        "type": "Point",
        "coordinates": [
          -79.05,
          41.3
        ]
      },
      "type": "Feature",
      "properties": {
        "hierarchy": [
          "tgn:2298485",
          "tgn:1000001",
          "tgn:7012149",
          "tgn:1002520",
          "tgn:7007710",
          "tgn:7029392"
        ],
        "placetype": [
          "aat:300008699"
        ],
        "id": 2298485,
        "name:xx": "Dry Run"
      }
    },
    {
      "geometry": {
        "type": "Point",
        "coordinates": [
          -77.3833,
          41.35
        ]
      },
      "type": "Feature",
      "properties": {
        "hierarchy": [
          "tgn:2298486",
          "tgn:1000001",
          "tgn:7012149",
          "tgn:1002613",
          "tgn:7007710",
          "tgn:7029392"
        ],
        "placetype": [
          "aat:300008699"
        ],
        "id": 2298486,
        "name:xx": "Dry Run"
      }
    },
    {
      "geometry": {
        "type": "Point",
        "coordinates": [
          -79.1,
          41.4167
        ]
      },
      "type": "Feature",
      "properties": {
        "hierarchy": [
          "tgn:2298487",
          "tgn:1000001",
          "tgn:7012149",
          "tgn:1002378",
          "tgn:7007710",
          "tgn:7029392"
        ],
        "placetype": [
          "aat:300008699"
        ],
        "id": 2298487,
        "name:xx": "Dry Run"
      }
    },
    {
      "geometry": {
        "type": "Point",
        "coordinates": [
          -76.6333,
          41.4333
        ]
      },
      "type": "Feature",
      "properties": {
        "hierarchy": [
          "tgn:2298488",
          "tgn:1000001",
          "tgn:7012149",
          "tgn:1002927",
          "tgn:7007710",
          "tgn:7029392"
        ],
        "placetype": [
          "aat:300008699"
        ],
        "id": 2298488,
        "name:xx": "Dry Run"
      }
    },
    {
      "geometry": {
        "type": "Point",
        "coordinates": [
          -78.0667,
          41.6667
        ]
      },
      "type": "Feature",
      "properties": {
        "hierarchy": [
          "tgn:2298489",
          "tgn:1000001",
          "tgn:7012149",
          "tgn:1002800",
          "tgn:7007710",
          "tgn:7029392"
        ],
        "placetype": [
          "aat:300008699"
        ],
        "id": 2298489,
        "name:xx": "Dry Run"
      }
    }
  ]
}
