{
  "geometry": {
    "type": "Point",
    "coordinates": [
      -116.6667,
      33.4667
    ]
  },
  "type": "Feature",
  "properties": {
    "hierarchy": [
      "tgn:2301714",
      "tgn:1000001",
      "tgn:7012149",
      "tgn:7007157",
      "tgn:1002828",
      "tgn:7029392"
    ],
    "placetype": [
      "aat:300008761"
    ],
    "id": 2301714,
    "name:xx": "Durasno Valley"
  }
}
