{
  "type": "FeatureCollection",
  "features": [
    {
      "geometry": {
        "type": "Point",
        "coordinates": [
          12.833333,
          42.966667
        ]
      },
      "type": "Feature",
      "properties": {
        "hierarchy": [
          "tgn:1043950",
          "tgn:7003170",
          "tgn:1000003",
          "tgn:7003125",
          "tgn:1000080",
          "tgn:7029392"
        ],
        "placetype": [
          "aat:300008347"
        ],
        "id": 1043950,
        "name:xx": "Casenove"
      }
    },
    {
      "geometry": {
        "type": "Point",
        "coordinates": [
          8.7,
          45.6333
        ]
      },
      "type": "Feature",
      "properties": {
        "hierarchy": [
          "tgn:1043951",
          "tgn:1000003",
          "tgn:1003508",
          "tgn:7003237",
          "tgn:1000080",
          "tgn:7029392"
        ],
        "placetype": [
          "aat:300008347"
        ],
        "id": 1043951,
        "name:xx": "Casenuove"
      }
    },
    {
      "geometry": {
        "type": "Point",
        "coordinates": [
          10.5,
          44.516667
        ]
      },
      "type": "Feature",
      "properties": {
        "hierarchy": [
          "tgn:1043953",
          "tgn:7003134",
          "tgn:1000003",
          "tgn:7008516",
          "tgn:1000080",
          "tgn:7029392"
        ],
        "placetype": [
          "aat:300008347"
        ],
        "id": 1043953,
        "name:xx": "Casina"
      }
    },
    {
      "geometry": {
        "type": "Point",
        "coordinates": [
          11.616667,
          44.216667
        ]
      },
      "type": "Feature",
      "properties": {
        "hierarchy": [
          "tgn:1043954",
          "tgn:7003133",
          "tgn:1000003",
          "tgn:7008516",
          "tgn:1000080",
          "tgn:7029392"
        ],
        "placetype": [
          "aat:300008347"
        ],
        "id": 1043954,
        "name:xx": "Casola Valsenio"
      }
    },
    {
      "geometry": {
        "type": "Point",
        "coordinates": [
          10.2,
          44.2
        ]
      },
      "type": "Feature",
      "properties": {
        "hierarchy": [
          "tgn:1043955",
          "tgn:1003473",
          "tgn:1000003",
          "tgn:7009760",
          "tgn:1000080",
          "tgn:7029392"
        ],
        "placetype": [
          "aat:300008347"
        ],
        "id": 1043955,
        "name:xx": "Casola in Lunigiana"
      }
    },
    {
      "geometry": {
        "type": "Point",
        "coordinates": [
          14.3,
          42.116667
        ]
      },
      "type": "Feature",
      "properties": {
        "hierarchy": [
          "tgn:1043957",
          "tgn:7009084",
          "tgn:7003000",
          "tgn:1000003",
          "tgn:1000080",
          "tgn:7029392"
        ],
        "placetype": [
          "aat:300008347"
        ],
        "id": 1043957,
        "name:xx": "Casoli"
      }
    },
    {
      "geometry": {
        "type": "Point",
        "coordinates": [
          8.733333,
          45.666667
        ]
      },
      "type": "Feature",
      "properties": {
        "hierarchy": [
          "tgn:1043959",
          "tgn:1000003",
          "tgn:1003508",
          "tgn:7003237",
          "tgn:1000080",
          "tgn:7029392"
        ],
        "placetype": [
          "aat:300008347"
        ],
        "id": 1043959,
        "name:xx": "Casorate Sempione"
      }
    }
  ]
}
