{
  "type": "FeatureCollection",
  "features": [
    {
      "geometry": {
        "type": "Point",
        "coordinates": [
          -110.5167,
          46.2833
        ]
      },
      "type": "Feature",
      "properties": {
        "hierarchy": [
          "tgn:2190320",
          "tgn:1000001",
          "tgn:7012149",
          "tgn:2001289",
          "tgn:7007524",
          "tgn:7029392"
        ],
        "placetype": [
          "aat:300008761"
        ],
        "id": 2190320,
        "name:xx": "Box Canyon"
      }
    },
    {
      "geometry": {
        "type": "Point",
        "coordinates": [
          -112.4167,
          45.6333
        ]
      },
      "type": "Feature",
      "properties": {
        "hierarchy": [
          "tgn:2190321",
          "tgn:1000001",
          "tgn:7012149",
          "tgn:2001288",
          "tgn:7007524",
          "tgn:7029392"
        ],
        "placetype": [
          "aat:300008761"
        ],
        "id": 2190321,
        "name:xx": "Box Canyon"
      }
    },
    {
      "geometry": {
        "type": "Point",
        "coordinates": [
          -109.6333,
          45.4333
        ]
      },
      "type": "Feature",
      "properties": {
        "hierarchy": [
          "tgn:2190322",
          "tgn:1000001",
          "tgn:7012149",
          "tgn:2001307",
          "tgn:7007524",
          "tgn:7029392"
        ],
        "placetype": [
          "aat:300008761"
        ],
        "id": 2190322,
        "name:xx": "Box Canyon"
      }
    },
    {
      "geometry": {
        "type": "Point",
        "coordinates": [
          -109.95,
          45.5667
        ]
      },
      "type": "Feature",
      "properties": {
        "hierarchy": [
          "tgn:2190323",
          "tgn:1000001",
          "tgn:7012149",
          "tgn:2001308",
          "tgn:7007524",
          "tgn:7029392"
        ],
        "placetype": [
          "aat:300008761"
        ],
        "id": 2190323,
        "name:xx": "Box Canyon"
      }
    },
    {
      "geometry": {
        "type": "Point",
        "coordinates": [
          -116.8333,
          36.9167
        ]
      },
      "type": "Feature",
      "properties": {
        "hierarchy": [
          "tgn:2190324",
          "tgn:1000001",
          "tgn:2001418",
          "tgn:7012149",
          "tgn:7007526",
          "tgn:7029392"
        ],
        "placetype": [
          "aat:300008761"
        ],
        "id": 2190324,
        "name:xx": "Box Canyon"
      }
    },
    {
      "geometry": {
        "type": "Point",
        "coordinates": [
          -114.9833,
          38.7167
        ]
      },
      "type": "Feature",
      "properties": {
        "hierarchy": [
          "tgn:2190325",
          "tgn:1000001",
          "tgn:7012149",
          "tgn:2001420",
          "tgn:7007526",
          "tgn:7029392"
        ],
        "placetype": [
          "aat:300008761"
        ],
        "id": 2190325,
        "name:xx": "Box Canyon"
      }
    },
    {
      "geometry": {
        "type": "Point",
        "coordinates": [
          -117.1167,
          40.5167
        ]
      },
      "type": "Feature",
      "properties": {
        "hierarchy": [
          "tgn:2190326",
          "tgn:1000001",
          "tgn:2001415",
          "tgn:7012149",
          "tgn:7007526",
          "tgn:7029392"
        ],
        "placetype": [
          "aat:300008761"
        ],
        "id": 2190326,
        "name:xx": "Box Canyon"
      }
    },
    {
      "geometry": {
        "type": "Point",
        "coordinates": [
          -117.4333,
          41.1833
        ]
      },
      "type": "Feature",
      "properties": {
        "hierarchy": [
          "tgn:2190327",
          "tgn:1000001",
          "tgn:2001414",
          "tgn:7012149",
          "tgn:7007526",
          "tgn:7029392"
        ],
        "placetype": [
          "aat:300008761"
        ],
        "id": 2190327,
        "name:xx": "Box Canyon"
      }
    },
    {
      "geometry": {
        "type": "Point",
        "coordinates": [
          -115.3833,
          36.2167
        ]
      },
      "type": "Feature",
      "properties": {
        "hierarchy": [
          "tgn:2190328",
          "tgn:1000001",
          "tgn:2001410",
          "tgn:7012149",
          "tgn:7007526",
          "tgn:7029392"
        ],
        "placetype": [
          "aat:300008761"
        ],
        "id": 2190328,
        "name:xx": "Box Canyon"
      }
    },
    {
      "geometry": {
        "type": "Point",
        "coordinates": [
          -118.6667,
          38.2333
        ]
      },
      "type": "Feature",
      "properties": {
        "hierarchy": [
          "tgn:2190329",
          "tgn:1000001",
          "tgn:2001417",
          "tgn:7012149",
          "tgn:7007526",
          "tgn:7029392"
        ],
        "placetype": [
          "aat:300008761"
        ],
        "id": 2190329,
        "name:xx": "Box Canyon"
      }
    }
  ]
}
