{
  "geometry": {
    "type": "Point",
    "coordinates": [
      -67.95,
      44.75
    ]
  },
  "type": "Feature",
  "properties": {
    "hierarchy": [
      "tgn:2506379",
      "tgn:1000001",
      "tgn:7012149",
      "tgn:7014589",
      "tgn:7007515",
      "tgn:7029392"
    ],
    "placetype": [
      "aat:300008699"
    ],
    "id": 2506379,
    "name:xx": "Merrit Brook"
  }
}
