{
  "geometry": {
    "type": "Point",
    "coordinates": [
      -92.9333,
      33.6167
    ]
  },
  "type": "Feature",
  "properties": {
    "hierarchy": [
      "tgn:2445919",
      "tgn:1000001",
      "tgn:7016172",
      "tgn:7012149",
      "tgn:2000156",
      "tgn:7029392"
    ],
    "placetype": [
      "aat:300008347"
    ],
    "id": 2445919,
    "name:xx": "Lester Junction"
  }
}
