{
  "type": "FeatureCollection",
  "features": [
    {
      "geometry": {
        "type": "Point",
        "coordinates": [
          -56.3,
          -4.7167
        ]
      },
      "type": "Feature",
      "properties": {
        "hierarchy": [
          "tgn:1125110",
          "tgn:7006247",
          "tgn:1000047",
          "tgn:7002456",
          "tgn:1000002",
          "tgn:7029392"
        ],
        "placetype": [
          "aat:300008707"
        ],
        "id": 1125110,
        "name:xx": "Jamanxim"
      }
    },
    {
      "geometry": {
        "type": "Point",
        "coordinates": [
          -63.5,
          -8.45
        ]
      },
      "type": "Feature",
      "properties": {
        "hierarchy": [
          "tgn:1125111",
          "tgn:1001944",
          "tgn:1000047",
          "tgn:7002456",
          "tgn:1000002",
          "tgn:7029392"
        ],
        "placetype": [
          "aat:300008707"
        ],
        "id": 1125111,
        "name:xx": "Jamari"
      }
    },
    {
      "geometry": {
        "type": "Point",
        "coordinates": [
          -92.7167,
          37.2167
        ]
      },
      "type": "Feature",
      "properties": {
        "hierarchy": [
          "tgn:1125113",
          "tgn:1000001",
          "tgn:7012149",
          "tgn:7007523",
          "tgn:7029392"
        ],
        "placetype": [
          "aat:300008707"
        ],
        "id": 1125113,
        "name:xx": "James"
      }
    },
    {
      "geometry": {
        "type": "Point",
        "coordinates": [
          -79.7667,
          37.7833
        ]
      },
      "type": "Feature",
      "properties": {
        "hierarchy": [
          "tgn:1125114",
          "tgn:1000001",
          "tgn:7012149",
          "tgn:7007919",
          "tgn:7029392"
        ],
        "placetype": [
          "aat:300008707"
        ],
        "id": 1125114,
        "name:xx": "James"
      }
    },
    {
      "geometry": {
        "type": "Point",
        "coordinates": [
          -114.5667,
          51.9167
        ]
      },
      "type": "Feature",
      "properties": {
        "hierarchy": [
          "tgn:1125115",
          "tgn:7005694",
          "tgn:7005685",
          "tgn:1000001",
          "tgn:7029392"
        ],
        "placetype": [
          "aat:300008707"
        ],
        "id": 1125115,
        "name:xx": "James"
      }
    },
    {
      "geometry": {
        "type": "Point",
        "coordinates": [
          -70.9833,
          -9.3333
        ]
      },
      "type": "Feature",
      "properties": {
        "hierarchy": [
          "tgn:1125119",
          "tgn:1001822",
          "tgn:1000047",
          "tgn:7002456",
          "tgn:1000002",
          "tgn:7029392"
        ],
        "placetype": [
          "aat:300008707"
        ],
        "id": 1125119,
        "name:xx": "Jaminauá"
      }
    }
  ]
}
