{
  "geometry": {
    "type": "Point",
    "coordinates": [
      -98.1667,
      28.7333
    ]
  },
  "type": "Feature",
  "properties": {
    "hierarchy": [
      "tgn:2106673",
      "tgn:1000001",
      "tgn:2001936",
      "tgn:7012149",
      "tgn:7007826",
      "tgn:7029392"
    ],
    "placetype": [
      "aat:300008347"
    ],
    "id": 2106673,
    "name:xx": "Peggy"
  }
}
