{
  "geometry": {
    "type": "Point",
    "coordinates": [
      -108.8167,
      39.5833
    ]
  },
  "type": "Feature",
  "properties": {
    "hierarchy": [
      "tgn:2727371",
      "tgn:1000001",
      "tgn:7012149",
      "tgn:2000214",
      "tgn:7007158",
      "tgn:7029392"
    ],
    "placetype": [
      "aat:300008761"
    ],
    "id": 2727371,
    "name:xx": "Trail Canyon"
  }
}
