{
  "type": "FeatureCollection",
  "features": [
    {
      "geometry": {
        "type": "Point",
        "coordinates": [
          -101.1833,
          33.8
        ]
      },
      "type": "Feature",
      "properties": {
        "hierarchy": [
          "tgn:2106161",
          "tgn:1000001",
          "tgn:7012149",
          "tgn:2001968",
          "tgn:7007826",
          "tgn:7029392"
        ],
        "placetype": [
          "aat:300008347",
          "aat:300387210"
        ],
        "id": 2106161,
        "name:xx": "Mount Blanco"
      }
    },
    {
      "geometry": {
        "type": "Point",
        "coordinates": [
          -96.8667,
          31.75
        ]
      },
      "type": "Feature",
      "properties": {
        "hierarchy": [
          "tgn:2106162",
          "tgn:1000001",
          "tgn:7012149",
          "tgn:1002478",
          "tgn:7007826",
          "tgn:7029392"
        ],
        "placetype": [
          "aat:300008347"
        ],
        "id": 2106162,
        "name:xx": "Mount Calm"
      }
    },
    {
      "geometry": {
        "type": "Point",
        "coordinates": [
          -94.6667,
          31.9167
        ]
      },
      "type": "Feature",
      "properties": {
        "hierarchy": [
          "tgn:2106164",
          "tgn:1000001",
          "tgn:7012149",
          "tgn:1002839",
          "tgn:7007826",
          "tgn:7029392"
        ],
        "placetype": [
          "aat:300008347"
        ],
        "id": 2106164,
        "name:xx": "Mount Enterprise"
      }
    },
    {
      "geometry": {
        "type": "Point",
        "coordinates": [
          -95.4667,
          32.7333
        ]
      },
      "type": "Feature",
      "properties": {
        "hierarchy": [
          "tgn:2106165",
          "tgn:1000001",
          "tgn:7012149",
          "tgn:1003034",
          "tgn:7007826",
          "tgn:7029392"
        ],
        "placetype": [
          "aat:300008347",
          "aat:300387210"
        ],
        "id": 2106165,
        "name:xx": "Mount Enterprise"
      }
    },
    {
      "geometry": {
        "type": "Point",
        "coordinates": [
          -95.3,
          29.8833
        ]
      },
      "type": "Feature",
      "properties": {
        "hierarchy": [
          "tgn:2106167",
          "tgn:1000001",
          "tgn:7012149",
          "tgn:1002456",
          "tgn:7007826",
          "tgn:7029392"
        ],
        "placetype": [
          "aat:300008347"
        ],
        "id": 2106167,
        "name:xx": "Mount Houston"
      }
    }
  ]
}
