{
  "geometry": {
    "type": "Point",
    "coordinates": [
      -114.1667,
      45.7333
    ]
  },
  "type": "Feature",
  "properties": {
    "hierarchy": [
      "tgn:2657723",
      "tgn:1000001",
      "tgn:7012149",
      "tgn:2001300",
      "tgn:7007524",
      "tgn:7029392"
    ],
    "placetype": [
      "aat:300008680"
    ],
    "id": 2657723,
    "name:xx": "Shelf Lake"
  }
}
