{
  "geometry": {
    "type": "Point",
    "coordinates": [
      -82.7833,
      41.5667
    ]
  },
  "type": "Feature",
  "properties": {
    "hierarchy": [
      "tgn:2509642",
      "tgn:1000001",
      "tgn:7012149",
      "tgn:1002761",
      "tgn:7007706",
      "tgn:7029392"
    ],
    "placetype": [
      "aat:300132348"
    ],
    "id": 2509642,
    "name:xx": "Middle Harbor Shoal"
  }
}
