{
  "geometry": {
    "type": "Point",
    "coordinates": [
      -82.4167,
      30.3667
    ]
  },
  "type": "Feature",
  "properties": {
    "hierarchy": [
      "tgn:2510172",
      "tgn:2000257",
      "tgn:1000001",
      "tgn:7012149",
      "tgn:7007240",
      "tgn:7029392"
    ],
    "placetype": [
      "aat:300008707"
    ],
    "id": 2510172,
    "name:xx": "Middle Prong Saint Marys River"
  }
}
