{
  "geometry": {
    "type": "Point",
    "coordinates": [
      -78.45,
      42.0167
    ]
  },
  "type": "Feature",
  "properties": {
    "hierarchy": [
      "tgn:2336580",
      "tgn:1000001",
      "tgn:1002245",
      "tgn:7012149",
      "tgn:7007568",
      "tgn:7029392"
    ],
    "placetype": [
      "aat:300008347"
    ],
    "id": 2336580,
    "name:xx": "Four Mile"
  }
}
