{
  "geometry": {
    "type": "Point",
    "coordinates": [
      -111.75,
      39.3833
    ]
  },
  "type": "Feature",
  "properties": {
    "hierarchy": [
      "tgn:2166002",
      "tgn:1000001",
      "tgn:7012149",
      "tgn:2002112",
      "tgn:7007827",
      "tgn:7029392"
    ],
    "placetype": [
      "aat:300008798"
    ],
    "id": 2166002,
    "name:xx": "Big Baldy"
  }
}
