{
  "geometry": {
    "type": "Point",
    "coordinates": [
      112.4833,
      51.8667
    ]
  },
  "type": "Feature",
  "properties": {
    "hierarchy": [
      "tgn:1059553",
      "tgn:1003351",
      "tgn:1000004",
      "tgn:7018214",
      "tgn:7002435",
      "tgn:7029392"
    ],
    "placetype": [
      "aat:300008347"
    ],
    "id": 1059553,
    "name:xx": "Sokhonda"
  }
}
