{
  "type": "FeatureCollection",
  "features": [
    {
      "geometry": {
        "type": "Point",
        "coordinates": [
          -74.05,
          -52.983333
        ]
      },
      "type": "Feature",
      "properties": {
        "hierarchy": [
          "tgn:7288140",
          "tgn:1001702",
          "tgn:1000049",
          "tgn:1000002",
          "tgn:7029392"
        ],
        "placetype": [
          "aat:300008804"
        ],
        "id": 7288140,
        "name:xx": "Jorge, Península"
      }
    },
    {
      "geometry": {
        "type": "Point",
        "coordinates": [
          -72.6,
          -51.816667
        ]
      },
      "type": "Feature",
      "properties": {
        "hierarchy": [
          "tgn:7288141",
          "tgn:1001702",
          "tgn:1000049",
          "tgn:1000002",
          "tgn:7029392"
        ],
        "placetype": [
          "aat:300386846"
        ],
        "id": 7288141,
        "name:xx": "Jorge, Morro"
      }
    },
    {
      "geometry": {
        "type": "Point",
        "coordinates": [
          -72.9,
          -53.2
        ]
      },
      "type": "Feature",
      "properties": {
        "hierarchy": [
          "tgn:7288142",
          "tgn:1001702",
          "tgn:1000049",
          "tgn:1000002",
          "tgn:7029392"
        ],
        "placetype": [
          "aat:300008795"
        ],
        "id": 7288142,
        "name:xx": "Jorge, Monte"
      }
    },
    {
      "geometry": {
        "type": "Point",
        "coordinates": [
          -67.066667,
          -55.016667
        ]
      },
      "type": "Feature",
      "properties": {
        "hierarchy": [
          "tgn:7288143",
          "tgn:1001702",
          "tgn:1000049",
          "tgn:1000002",
          "tgn:7029392"
        ],
        "placetype": [
          "aat:300008791"
        ],
        "id": 7288143,
        "name:xx": "Jorge, Islote"
      }
    },
    {
      "geometry": {
        "type": "Point",
        "coordinates": [
          -73.016667,
          -42.75
        ]
      },
      "type": "Feature",
      "properties": {
        "hierarchy": [
          "tgn:7288144",
          "tgn:1001699",
          "tgn:1000049",
          "tgn:1000002",
          "tgn:7029392"
        ],
        "placetype": [
          "aat:300008791"
        ],
        "id": 7288144,
        "name:xx": "Jorge, Islote"
      }
    },
    {
      "geometry": {
        "type": "Point",
        "coordinates": [
          -70.866667,
          -27.083333
        ]
      },
      "type": "Feature",
      "properties": {
        "hierarchy": [
          "tgn:7288145",
          "tgn:1001630",
          "tgn:1000049",
          "tgn:1000002",
          "tgn:7029392"
        ],
        "placetype": [
          "aat:300008791"
        ],
        "id": 7288145,
        "name:xx": "Jorge, Islote"
      }
    },
    {
      "geometry": {
        "type": "Point",
        "coordinates": [
          -70.783333,
          -55.116667
        ]
      },
      "type": "Feature",
      "properties": {
        "hierarchy": [
          "tgn:7288146",
          "tgn:1001702",
          "tgn:1000049",
          "tgn:1000002",
          "tgn:7029392"
        ],
        "placetype": [
          "aat:300008791"
        ],
        "id": 7288146,
        "name:xx": "Jorge, Isla"
      }
    },
    {
      "geometry": {
        "type": "Point",
        "coordinates": [
          -72.316667,
          -54.016667
        ]
      },
      "type": "Feature",
      "properties": {
        "hierarchy": [
          "tgn:7288147",
          "tgn:1001702",
          "tgn:1000049",
          "tgn:1000002",
          "tgn:7029392"
        ],
        "placetype": [
          "aat:300008791"
        ],
        "id": 7288147,
        "name:xx": "Jorge, Isla"
      }
    },
    {
      "geometry": {
        "type": "Point",
        "coordinates": [
          -74.7,
          -50.233333
        ]
      },
      "type": "Feature",
      "properties": {
        "hierarchy": [
          "tgn:7288148",
          "tgn:1001702",
          "tgn:1000049",
          "tgn:1000002",
          "tgn:7029392"
        ],
        "placetype": [
          "aat:300008791"
        ],
        "id": 7288148,
        "name:xx": "Jorge, Isla"
      }
    },
    {
      "geometry": {
        "type": "Point",
        "coordinates": [
          -74.033333,
          -44.816667
        ]
      },
      "type": "Feature",
      "properties": {
        "hierarchy": [
          "tgn:7288149",
          "tgn:1001623",
          "tgn:1000049",
          "tgn:1000002",
          "tgn:7029392"
        ],
        "placetype": [
          "aat:300008791"
        ],
        "id": 7288149,
        "name:xx": "Jorge, Isla"
      }
    }
  ]
}
