{
  "geometry": {
    "type": "Point",
    "coordinates": [
      83.05,
      20.566667
    ]
  },
  "type": "Feature",
  "properties": {
    "hierarchy": [
      "tgn:7557975",
      "tgn:1000004",
      "tgn:7000198",
      "tgn:7016694",
      "tgn:7029392"
    ],
    "placetype": [
      "aat:300008347"
    ],
    "name:en": "Rarbāhāl",
    "id": 7557975
  }
}
