{
  "geometry": {
    "type": "Point",
    "coordinates": [
      -75.6333,
      43.4667
    ]
  },
  "type": "Feature",
  "properties": {
    "hierarchy": [
      "tgn:2499034",
      "tgn:1000001",
      "tgn:7012149",
      "tgn:1002593",
      "tgn:7007568",
      "tgn:7029392"
    ],
    "placetype": [
      "aat:300008680"
    ],
    "id": 2499034,
    "name:xx": "McCarthys Lake"
  }
}
