{
  "geometry": {
    "type": "Point",
    "coordinates": [
      -122.3833,
      37.5167
    ]
  },
  "type": "Feature",
  "properties": {
    "hierarchy": [
      "tgn:2214108",
      "tgn:1000001",
      "tgn:7012149",
      "tgn:7007157",
      "tgn:1002864",
      "tgn:7029392"
    ],
    "placetype": [
      "aat:300266640"
    ],
    "id": 2214108,
    "name:xx": "Cahill Ridge"
  }
}
