{
  "type": "FeatureCollection",
  "features": [
    {
      "geometry": {
        "type": "Point",
        "coordinates": [
          -83.95,
          35.85
        ]
      },
      "type": "Feature",
      "properties": {
        "hierarchy": [
          "tgn:2099970",
          "tgn:1000001",
          "tgn:2001841",
          "tgn:7012149",
          "tgn:7007825",
          "tgn:7029392"
        ],
        "placetype": [
          "aat:300008347"
        ],
        "id": 2099970,
        "name:xx": "Lakemont"
      }
    },
    {
      "geometry": {
        "type": "Point",
        "coordinates": [
          -83.1667,
          36.35
        ]
      },
      "type": "Feature",
      "properties": {
        "hierarchy": [
          "tgn:2099971",
          "tgn:1000001",
          "tgn:7012149",
          "tgn:2001873",
          "tgn:7007825",
          "tgn:7029392"
        ],
        "placetype": [
          "aat:300008347"
        ],
        "id": 2099971,
        "name:xx": "Lakemont Cabin Area"
      }
    },
    {
      "geometry": {
        "type": "Point",
        "coordinates": [
          -85.15,
          35.1167
        ]
      },
      "type": "Feature",
      "properties": {
        "hierarchy": [
          "tgn:2099974",
          "tgn:1000001",
          "tgn:7012149",
          "tgn:2001869",
          "tgn:7007825",
          "tgn:7029392"
        ],
        "placetype": [
          "aat:300008347"
        ],
        "id": 2099974,
        "name:xx": "Lakeshore Estates"
      }
    },
    {
      "geometry": {
        "type": "Point",
        "coordinates": [
          -84.2667,
          35.6
        ]
      },
      "type": "Feature",
      "properties": {
        "hierarchy": [
          "tgn:2099975",
          "tgn:1000001",
          "tgn:7012149",
          "tgn:2001898",
          "tgn:7007825",
          "tgn:7029392"
        ],
        "placetype": [
          "aat:300008347",
          "aat:300387210"
        ],
        "id": 2099975,
        "name:xx": "Lakeside"
      }
    },
    {
      "geometry": {
        "type": "Point",
        "coordinates": [
          -85.1167,
          35.2
        ]
      },
      "type": "Feature",
      "properties": {
        "hierarchy": [
          "tgn:2099978",
          "tgn:1000001",
          "tgn:7012149",
          "tgn:2001869",
          "tgn:7007825",
          "tgn:7029392"
        ],
        "placetype": [
          "aat:300008347"
        ],
        "id": 2099978,
        "name:xx": "Lakesite"
      }
    },
    {
      "geometry": {
        "type": "Point",
        "coordinates": [
          -85.0333,
          35.8833
        ]
      },
      "type": "Feature",
      "properties": {
        "hierarchy": [
          "tgn:2099979",
          "tgn:1000001",
          "tgn:7012149",
          "tgn:2001854",
          "tgn:7007825",
          "tgn:7029392"
        ],
        "placetype": [
          "aat:300008347"
        ],
        "id": 2099979,
        "name:xx": "Lake Tansi Village"
      }
    }
  ]
}
