{
  "geometry": {
    "type": "Point",
    "coordinates": [
      -103.2167,
      43.1667
    ]
  },
  "type": "Feature",
  "properties": {
    "hierarchy": [
      "tgn:2097414",
      "tgn:1000001",
      "tgn:2001793",
      "tgn:7012149",
      "tgn:7007713",
      "tgn:7029392"
    ],
    "placetype": [
      "aat:300008347"
    ],
    "id": 2097414,
    "name:xx": "Oelrichs"
  }
}
