{
  "geometry": {
    "type": "Point",
    "coordinates": [
      64.8333,
      32.0833
    ]
  },
  "type": "Feature",
  "properties": {
    "hierarchy": [
      "tgn:1126594",
      "tgn:7016612",
      "tgn:1000004",
      "tgn:1001291",
      "tgn:7029392"
    ],
    "placetype": [
      "aat:300008707"
    ],
    "id": 1126594,
    "name:xx": "Musa Qaleh"
  }
}
