{
  "geometry": {
    "type": "Point",
    "coordinates": [
      -113.55,
      35.9667
    ]
  },
  "type": "Feature",
  "properties": {
    "hierarchy": [
      "tgn:2705368",
      "tgn:1000001",
      "tgn:7006451",
      "tgn:7012149",
      "tgn:2000098",
      "tgn:7029392"
    ],
    "placetype": [
      "aat:300008761"
    ],
    "id": 2705368,
    "name:xx": "Surprise Canyon"
  }
}
