{
  "geometry": {
    "type": "Point",
    "coordinates": [
      34.8167,
      32.0667
    ]
  },
  "type": "Feature",
  "properties": {
    "hierarchy": [
      "tgn:1079521",
      "tgn:1000004",
      "tgn:1000939",
      "tgn:1000119",
      "tgn:7029392"
    ],
    "placetype": [
      "aat:300008347",
      "aat:300008389",
      "aat:300387302"
    ],
    "id": 1079521,
    "name:xx": "Givʻatayim"
  }
}
