{
  "geometry": {
    "type": "Point",
    "coordinates": [
      -71.2833,
      41.9167
    ]
  },
  "type": "Feature",
  "properties": {
    "hierarchy": [
      "tgn:2290320",
      "tgn:1002201",
      "tgn:1000001",
      "tgn:7012149",
      "tgn:7007517",
      "tgn:7029392"
    ],
    "placetype": [
      "aat:300006191"
    ],
    "id": 2290320,
    "name:xx": "Dodgeville Pond"
  }
}
