{
  "geometry": {
    "type": "Point",
    "coordinates": [
      -82.2167,
      28.45
    ]
  },
  "type": "Feature",
  "properties": {
    "hierarchy": [
      "tgn:2180296",
      "tgn:1000001",
      "tgn:7012149",
      "tgn:1002773",
      "tgn:7007240",
      "tgn:7029392"
    ],
    "placetype": [
      "aat:300008680"
    ],
    "id": 2180296,
    "name:xx": "Block Pond"
  }
}
