{
  "geometry": {
    "type": "Point",
    "coordinates": [
      2.4167,
      48.9667
    ]
  },
  "type": "Feature",
  "properties": {
    "hierarchy": [
      "tgn:1135369",
      "tgn:1000003",
      "tgn:7002883",
      "tgn:1000070",
      "tgn:7029392"
    ],
    "placetype": [
      "aat:300008703"
    ],
    "id": 1135369,
    "name:xx": "Rosne, Ruisseau le"
  }
}
