{
  "geometry": {
    "type": "Point",
    "coordinates": [
      29.46737,
      28.549371
    ]
  },
  "type": "Feature",
  "properties": {
    "hierarchy": [
      "tgn:7525436",
      "tgn:7001242",
      "tgn:7016833",
      "tgn:7029392"
    ],
    "placetype": [
      "aat:300379998"
    ],
    "name:en": "Baḩr, Wādī al",
    "id": 7525436
  }
}
