{
  "type": "FeatureCollection",
  "features": [
    {
      "geometry": {
        "type": "Point",
        "coordinates": [
          4.050406,
          50.919046
        ]
      },
      "type": "Feature",
      "properties": {
        "hierarchy": [
          "tgn:7240441",
          "tgn:7003457",
          "tgn:1000003",
          "tgn:1000063",
          "tgn:7018236",
          "tgn:7029392"
        ],
        "placetype": [
          "aat:300008347"
        ],
        "id": 7240441,
        "name:xx": "Erembodegem"
      }
    },
    {
      "geometry": {
        "type": "Point",
        "coordinates": [
          5.255209,
          50.470821
        ]
      },
      "type": "Feature",
      "properties": {
        "hierarchy": [
          "tgn:7240443",
          "tgn:7003460",
          "tgn:1000003",
          "tgn:1000063",
          "tgn:4012014",
          "tgn:7029392"
        ],
        "placetype": [
          "aat:300008347"
        ],
        "id": 7240443,
        "name:xx": "Ereffe"
      }
    },
    {
      "geometry": {
        "type": "Point",
        "coordinates": [
          3.36765,
          50.58226
        ]
      },
      "type": "Feature",
      "properties": {
        "hierarchy": [
          "tgn:7240444",
          "tgn:7007877",
          "tgn:1000003",
          "tgn:1000063",
          "tgn:4012014",
          "tgn:7029392"
        ],
        "placetype": [
          "aat:300008347"
        ],
        "id": 7240444,
        "name:xx": "Ere"
      }
    },
    {
      "geometry": {
        "type": "Point",
        "coordinates": [
          3.8,
          50.933333
        ]
      },
      "type": "Feature",
      "properties": {
        "hierarchy": [
          "tgn:7240446",
          "tgn:7003457",
          "tgn:1000003",
          "tgn:1000063",
          "tgn:7018236",
          "tgn:7029392"
        ],
        "placetype": [
          "aat:300008347"
        ],
        "id": 7240446,
        "name:xx": "Ettinge"
      }
    },
    {
      "geometry": {
        "type": "Point",
        "coordinates": [
          4.373668,
          51.310433
        ]
      },
      "type": "Feature",
      "properties": {
        "hierarchy": [
          "tgn:7240449",
          "tgn:7003456",
          "tgn:1000003",
          "tgn:1000063",
          "tgn:7018236",
          "tgn:7029392"
        ],
        "placetype": [
          "aat:300006163"
        ],
        "id": 7240449,
        "name:xx": "Ettenhovense Polder"
      }
    }
  ]
}
