{
  "geometry": {
    "type": "Point",
    "coordinates": [
      -87.9667,
      32.75
    ]
  },
  "type": "Feature",
  "properties": {
    "hierarchy": [
      "tgn:2382353",
      "tgn:7002659",
      "tgn:1000001",
      "tgn:7012149",
      "tgn:2000031",
      "tgn:7029392"
    ],
    "placetype": [
      "aat:300008798"
    ],
    "id": 2382353,
    "name:xx": "Hays Mount"
  }
}
