{
  "geometry": {
    "type": "Point",
    "coordinates": [
      62.5833,
      44.1167
    ]
  },
  "type": "Feature",
  "properties": {
    "hierarchy": [
      "tgn:1099909",
      "tgn:1000004",
      "tgn:1003384",
      "tgn:7014786",
      "tgn:7029392"
    ],
    "placetype": [
      "aat:300008347",
      "aat:300167671"
    ],
    "id": 1099909,
    "name:xx": "Sirykrabet"
  }
}
