{
  "geometry": {
    "type": "Point",
    "coordinates": [
      32.766667,
      26.816667
    ]
  },
  "type": "Feature",
  "properties": {
    "hierarchy": [
      "tgn:7528322",
      "tgn:7001242",
      "tgn:7001311",
      "tgn:7016833",
      "tgn:7029392"
    ],
    "placetype": [
      "aat:300379998"
    ],
    "name:en": "Umm Gilu, Wâdi",
    "id": 7528322
  }
}
