{
  "type": "FeatureCollection",
  "features": [
    {
      "geometry": {
        "type": "Point",
        "coordinates": [
          -79.1833,
          38.55
        ]
      },
      "type": "Feature",
      "properties": {
        "hierarchy": [
          "tgn:2398620",
          "tgn:1000001",
          "tgn:7012149",
          "tgn:7014398",
          "tgn:7013961",
          "tgn:7029392"
        ],
        "placetype": [
          "aat:300266640"
        ],
        "id": 2398620,
        "name:xx": "Hoovers Ridge"
      }
    },
    {
      "geometry": {
        "type": "Point",
        "coordinates": [
          -84.2833,
          39.4667
        ]
      },
      "type": "Feature",
      "properties": {
        "hierarchy": [
          "tgn:2398621",
          "tgn:1000001",
          "tgn:7012149",
          "tgn:1002987",
          "tgn:7007706",
          "tgn:7029392"
        ],
        "placetype": [
          "aat:300008699"
        ],
        "id": 2398621,
        "name:xx": "Hoovers Run"
      }
    },
    {
      "geometry": {
        "type": "Point",
        "coordinates": [
          -80.3,
          39.8
        ]
      },
      "type": "Feature",
      "properties": {
        "hierarchy": [
          "tgn:2398622",
          "tgn:1000001",
          "tgn:7012149",
          "tgn:2001724",
          "tgn:7007710",
          "tgn:7029392"
        ],
        "placetype": [
          "aat:300008699"
        ],
        "id": 2398622,
        "name:xx": "Hoovers Run"
      }
    },
    {
      "geometry": {
        "type": "Point",
        "coordinates": [
          -98.3833,
          30.7
        ]
      },
      "type": "Feature",
      "properties": {
        "hierarchy": [
          "tgn:2398623",
          "tgn:1000001",
          "tgn:7012149",
          "tgn:2001949",
          "tgn:7007826",
          "tgn:7029392"
        ],
        "placetype": [
          "aat:300386845"
        ],
        "id": 2398623,
        "name:xx": "Hoovers Valley"
      }
    },
    {
      "geometry": {
        "type": "Point",
        "coordinates": [
          -75.3167,
          40.1333
        ]
      },
      "type": "Feature",
      "properties": {
        "hierarchy": [
          "tgn:2398624",
          "tgn:1000001",
          "tgn:7012149",
          "tgn:1002690",
          "tgn:7007710",
          "tgn:7029392"
        ],
        "placetype": [
          "aat:300008347"
        ],
        "id": 2398624,
        "name:xx": "Hooverton"
      }
    },
    {
      "geometry": {
        "type": "Point",
        "coordinates": [
          -78.5833,
          41.2
        ]
      },
      "type": "Feature",
      "properties": {
        "hierarchy": [
          "tgn:2398625",
          "tgn:1000001",
          "tgn:1002278",
          "tgn:7012149",
          "tgn:7007710",
          "tgn:7029392"
        ],
        "placetype": [
          "aat:300008347"
        ],
        "id": 2398625,
        "name:xx": "Hoovertown"
      }
    },
    {
      "geometry": {
        "type": "Point",
        "coordinates": [
          -79.0167,
          40.4
        ]
      },
      "type": "Feature",
      "properties": {
        "hierarchy": [
          "tgn:2398626",
          "tgn:1000001",
          "tgn:7012149",
          "tgn:1003017",
          "tgn:7007710",
          "tgn:7029392"
        ],
        "placetype": [
          "aat:300008347"
        ],
        "id": 2398626,
        "name:xx": "Hooverville"
      }
    },
    {
      "geometry": {
        "type": "Point",
        "coordinates": [
          -109.3167,
          31.9
        ]
      },
      "type": "Feature",
      "properties": {
        "hierarchy": [
          "tgn:2398627",
          "tgn:1000001",
          "tgn:7006451",
          "tgn:2000091",
          "tgn:7012149",
          "tgn:7029392"
        ],
        "placetype": [
          "aat:300008761"
        ],
        "id": 2398627,
        "name:xx": "Hoovey Canyon"
      }
    },
    {
      "geometry": {
        "type": "Point",
        "coordinates": [
          -84.7667,
          36.9
        ]
      },
      "type": "Feature",
      "properties": {
        "hierarchy": [
          "tgn:2398628",
          "tgn:1000001",
          "tgn:7012149",
          "tgn:2000850",
          "tgn:7007255",
          "tgn:7029392"
        ],
        "placetype": [
          "aat:300008798"
        ],
        "id": 2398628,
        "name:xx": "Hoozer Hill"
      }
    },
    {
      "geometry": {
        "type": "Point",
        "coordinates": [
          -75.7833,
          41.85
        ]
      },
      "type": "Feature",
      "properties": {
        "hierarchy": [
          "tgn:2398629",
          "tgn:1000001",
          "tgn:7012149",
          "tgn:1002932",
          "tgn:7007710",
          "tgn:7029392"
        ],
        "placetype": [
          "aat:300008706"
        ],
        "id": 2398629,
        "name:xx": "Hop Bottom Creek"
      }
    }
  ]
}
