{
  "geometry": {
    "type": "Point",
    "coordinates": [
      -112.8167,
      36.4833
    ]
  },
  "type": "Feature",
  "properties": {
    "hierarchy": [
      "tgn:2169083",
      "tgn:1000001",
      "tgn:7006451",
      "tgn:7012149",
      "tgn:2000098",
      "tgn:7029392"
    ],
    "placetype": [
      "aat:300006191"
    ],
    "id": 2169083,
    "name:xx": "Big Jackson Tank"
  }
}
