{
  "geometry": {
    "type": "Point",
    "coordinates": [
      57.9833,
      58.3667
    ]
  },
  "type": "Feature",
  "properties": {
    "hierarchy": [
      "tgn:1059457",
      "tgn:1000004",
      "tgn:7013412",
      "tgn:7018214",
      "tgn:7002435",
      "tgn:7029392"
    ],
    "placetype": [
      "aat:300008347"
    ],
    "id": 1059457,
    "name:xx": "Skal'nyy"
  }
}
