{
  "geometry": {
    "type": "Point",
    "coordinates": [
      -75.2333,
      20.6333
    ]
  },
  "type": "Feature",
  "properties": {
    "hierarchy": [
      "tgn:1016422",
      "tgn:1001296",
      "tgn:1000001",
      "tgn:7004624",
      "tgn:7029392"
    ],
    "placetype": [
      "aat:300008347"
    ],
    "id": 1016422,
    "name:xx": "Sagua de Tánamo"
  }
}
