{
  "geometry": {
    "type": "Point",
    "coordinates": [
      -80.5833,
      41.1833
    ]
  },
  "type": "Feature",
  "properties": {
    "hierarchy": [
      "tgn:2246193",
      "tgn:1000001",
      "tgn:7012149",
      "tgn:1002955",
      "tgn:7007706",
      "tgn:7029392"
    ],
    "placetype": [
      "aat:300006191"
    ],
    "id": 2246193,
    "name:xx": "Coalburg Lake"
  }
}
