{
  "geometry": {
    "type": "Point",
    "coordinates": [
      -5.25,
      5.1833
    ]
  },
  "type": "Feature",
  "properties": {
    "hierarchy": [
      "tgn:1114840",
      "tgn:7001242",
      "tgn:1000168",
      "tgn:7029392"
    ],
    "placetype": [
      "aat:300008679"
    ],
    "id": 1114840,
    "name:xx": "Tadio, Lagune"
  }
}
