{
  "geometry": {
    "type": "Point",
    "coordinates": [
      9.3333,
      0.3833
    ]
  },
  "type": "Feature",
  "properties": {
    "hierarchy": [
      "tgn:1012334",
      "tgn:1001668",
      "tgn:7001242",
      "tgn:1000164",
      "tgn:7029392"
    ],
    "placetype": [
      "aat:300386846"
    ],
    "id": 1012334,
    "name:xx": "Pongara, Pointe"
  }
}
