{
  "geometry": {
    "type": "Point",
    "coordinates": [
      -93.0333,
      30.8667
    ]
  },
  "type": "Feature",
  "properties": {
    "hierarchy": [
      "tgn:2281307",
      "tgn:1000001",
      "tgn:7012149",
      "tgn:7007256",
      "tgn:7029392"
    ],
    "placetype": [
      "aat:300008699"
    ],
    "id": 2281307,
    "name:xx": "Deep Slough"
  }
}
