{
  "geometry": {
    "type": "Point",
    "coordinates": [
      -121.6333,
      46.5833
    ]
  },
  "type": "Feature",
  "properties": {
    "hierarchy": [
      "tgn:2674485",
      "tgn:1000001",
      "tgn:7012149",
      "tgn:1002594",
      "tgn:7007920",
      "tgn:7029392"
    ],
    "placetype": [
      "aat:300008706"
    ],
    "id": 2674485,
    "name:xx": "Snyder Creek"
  }
}
