{
  "geometry": {
    "type": "Point",
    "coordinates": [
      -93.7167,
      33.15
    ]
  },
  "type": "Feature",
  "properties": {
    "hierarchy": [
      "tgn:2595152",
      "tgn:1000001",
      "tgn:7012149",
      "tgn:7029392"
    ],
    "placetype": [
      "aat:300008699"
    ],
    "id": 2595152,
    "name:xx": "Posten Bayou"
  }
}
