{
  "type": "FeatureCollection",
  "features": [
    {
      "geometry": {
        "type": "Point",
        "coordinates": [
          -69,
          -55.25
        ]
      },
      "type": "Feature",
      "properties": {
        "hierarchy": [
          "tgn:1007440",
          "tgn:1001702",
          "tgn:1000049",
          "tgn:1000002",
          "tgn:7029392"
        ],
        "placetype": [
          "aat:300008791"
        ],
        "id": 1007440,
        "name:xx": "Hoste, Isla"
      }
    },
    {
      "geometry": {
        "type": "Point",
        "coordinates": [
          -2.9667,
          47.4
        ]
      },
      "type": "Feature",
      "properties": {
        "hierarchy": [
          "tgn:1007441",
          "tgn:1000003",
          "tgn:7012216",
          "tgn:1000070",
          "tgn:7029392"
        ],
        "placetype": [
          "aat:300008791"
        ],
        "id": 1007441,
        "name:xx": "Houat"
      }
    },
    {
      "geometry": {
        "type": "Point",
        "coordinates": [
          21.3667,
          60.2
        ]
      },
      "type": "Feature",
      "properties": {
        "hierarchy": [
          "tgn:1007442",
          "tgn:7024077",
          "tgn:1000003",
          "tgn:1000069",
          "tgn:7029392"
        ],
        "placetype": [
          "aat:300008791"
        ],
        "id": 1007442,
        "name:xx": "Houtskär"
      }
    },
    {
      "geometry": {
        "type": "Point",
        "coordinates": [
          40.2667,
          15.1667
        ]
      },
      "type": "Feature",
      "properties": {
        "hierarchy": [
          "tgn:1007443",
          "tgn:7001242",
          "tgn:7017570",
          "tgn:7001658",
          "tgn:7029392"
        ],
        "placetype": [
          "aat:300008791"
        ],
        "id": 1007443,
        "name:xx": "Howakil"
      }
    },
    {
      "geometry": {
        "type": "Point",
        "coordinates": [
          -76.25,
          44.2833
        ]
      },
      "type": "Feature",
      "properties": {
        "hierarchy": [
          "tgn:1007445",
          "tgn:7005685",
          "tgn:1000001",
          "tgn:7013154",
          "tgn:7029392"
        ],
        "placetype": [
          "aat:300008791"
        ],
        "id": 1007445,
        "name:xx": "Howe Island"
      }
    },
    {
      "geometry": {
        "type": "Point",
        "coordinates": [
          -90.7,
          38.65
        ]
      },
      "type": "Feature",
      "properties": {
        "hierarchy": [
          "tgn:1007446",
          "tgn:1000001",
          "tgn:7012149",
          "tgn:7016166",
          "tgn:7007523",
          "tgn:7029392"
        ],
        "placetype": [
          "aat:300008791"
        ],
        "id": 1007446,
        "name:xx": "Howell Island"
      }
    },
    {
      "geometry": {
        "type": "Point",
        "coordinates": [
          -176.643,
          0.801
        ]
      },
      "type": "Feature",
      "properties": {
        "hierarchy": [
          "tgn:1007447",
          "tgn:1000001",
          "tgn:7012149",
          "tgn:7029392"
        ],
        "placetype": [
          "aat:300387054",
          "aat:300387064",
          "aat:300008791",
          "aat:300235118",
          "aat:300387118"
        ],
        "id": 1007447,
        "name:xx": "Howland Island"
      }
    },
    {
      "geometry": {
        "type": "Point",
        "coordinates": [
          121.61,
          21.948889
        ]
      },
      "type": "Feature",
      "properties": {
        "hierarchy": [
          "tgn:1007449",
          "tgn:1000004",
          "tgn:7492971",
          "tgn:1000141",
          "tgn:7029392"
        ],
        "placetype": [
          "aat:300008791"
        ],
        "id": 1007449,
        "name:xx": "Hsiao-hung-t'ou Yü"
      }
    }
  ]
}
