{
  "geometry": {
    "type": "Point",
    "coordinates": [
      79.8493,
      27.0599
    ]
  },
  "type": "Feature",
  "properties": {
    "hierarchy": [
      "tgn:7562999",
      "tgn:1000004",
      "tgn:7000198",
      "tgn:7016722",
      "tgn:7029392"
    ],
    "placetype": [
      "aat:300008347"
    ],
    "name:en": "Basīrāpur Bhāt",
    "id": 7562999
  }
}
