{
  "geometry": {
    "type": "Point",
    "coordinates": [
      58.7167,
      48.45
    ]
  },
  "type": "Feature",
  "properties": {
    "hierarchy": [
      "tgn:1052720",
      "tgn:7011450",
      "tgn:1000004",
      "tgn:7014786",
      "tgn:7029392"
    ],
    "placetype": [
      "aat:300008347"
    ],
    "id": 1052720,
    "name:xx": "Berchogur"
  }
}
