{
  "geometry": {
    "type": "Point",
    "coordinates": [
      -82.2333,
      38.9667
    ]
  },
  "type": "Feature",
  "properties": {
    "hierarchy": [
      "tgn:2318035",
      "tgn:1000001",
      "tgn:7012149",
      "tgn:2001612",
      "tgn:7007706",
      "tgn:7029392"
    ],
    "placetype": [
      "aat:300008347"
    ],
    "id": 2318035,
    "name:xx": "Eno"
  }
}
