{
  "geometry": {
    "type": "Point",
    "coordinates": [
      -79.5333,
      43.8667
    ]
  },
  "type": "Feature",
  "properties": {
    "hierarchy": [
      "tgn:1015154",
      "tgn:7005685",
      "tgn:1000001",
      "tgn:7013154",
      "tgn:7029392"
    ],
    "placetype": [
      "aat:300008347"
    ],
    "id": 1015154,
    "name:xx": "Teston"
  }
}
