{
  "geometry": {
    "type": "Point",
    "coordinates": [
      114.5667,
      35.65
    ]
  },
  "type": "Feature",
  "properties": {
    "hierarchy": [
      "tgn:1073265",
      "tgn:1000004",
      "tgn:7016672",
      "tgn:1000111",
      "tgn:7029392"
    ],
    "placetype": [
      "aat:300008347"
    ],
    "id": 1073265,
    "name:xx": "Xunxian"
  }
}
