{
  "geometry": {
    "type": "Point",
    "coordinates": [
      16.0833,
      56.25
    ]
  },
  "type": "Feature",
  "properties": {
    "hierarchy": [
      "tgn:1063248",
      "tgn:7003767",
      "tgn:1000003",
      "tgn:1000097",
      "tgn:7029392"
    ],
    "placetype": [
      "aat:300008347"
    ],
    "id": 1063248,
    "name:xx": "Kristianopel"
  }
}
