{
  "type": "FeatureCollection",
  "features": [
    {
      "geometry": {
        "type": "Point",
        "coordinates": [
          -75.4333,
          40.3333
        ]
      },
      "type": "Feature",
      "properties": {
        "hierarchy": [
          "tgn:2479850",
          "tgn:1000001",
          "tgn:7012149",
          "tgn:1002690",
          "tgn:7007710",
          "tgn:7029392"
        ],
        "placetype": [
          "aat:300006191"
        ],
        "id": 2479850,
        "name:xx": "Lake Delmont"
      }
    },
    {
      "geometry": {
        "type": "Point",
        "coordinates": [
          -79.7,
          40.2333
        ]
      },
      "type": "Feature",
      "properties": {
        "hierarchy": [
          "tgn:2479851",
          "tgn:1000001",
          "tgn:7012149",
          "tgn:1003017",
          "tgn:7007710",
          "tgn:7029392"
        ],
        "placetype": [
          "aat:300008347"
        ],
        "id": 2479851,
        "name:xx": "Lake Denise"
      }
    },
    {
      "geometry": {
        "type": "Point",
        "coordinates": [
          -73.9667,
          43.1167
        ]
      },
      "type": "Feature",
      "properties": {
        "hierarchy": [
          "tgn:2479852",
          "tgn:1000001",
          "tgn:7012149",
          "tgn:1002871",
          "tgn:7007568",
          "tgn:7029392"
        ],
        "placetype": [
          "aat:300008347"
        ],
        "id": 2479852,
        "name:xx": "Lake Desolation"
      }
    },
    {
      "geometry": {
        "type": "Point",
        "coordinates": [
          -90.3667,
          36.0167
        ]
      },
      "type": "Feature",
      "properties": {
        "hierarchy": [
          "tgn:2479853",
          "tgn:1000001",
          "tgn:7016172",
          "tgn:7012149",
          "tgn:2000132",
          "tgn:7029392"
        ],
        "placetype": [
          "aat:300006075"
        ],
        "id": 2479853,
        "name:xx": "Lake Ditch"
      }
    },
    {
      "geometry": {
        "type": "Point",
        "coordinates": [
          -105.0667,
          40.35
        ]
      },
      "type": "Feature",
      "properties": {
        "hierarchy": [
          "tgn:2479854",
          "tgn:1000001",
          "tgn:7012149",
          "tgn:2000226",
          "tgn:7007158",
          "tgn:7029392"
        ],
        "placetype": [
          "aat:300006075"
        ],
        "id": 2479854,
        "name:xx": "Lake Ditch"
      }
    },
    {
      "geometry": {
        "type": "Point",
        "coordinates": [
          -105.2667,
          40.15
        ]
      },
      "type": "Feature",
      "properties": {
        "hierarchy": [
          "tgn:2479855",
          "tgn:1000001",
          "tgn:2000198",
          "tgn:7012149",
          "tgn:7007158",
          "tgn:7029392"
        ],
        "placetype": [
          "aat:300006075"
        ],
        "id": 2479855,
        "name:xx": "Lake Ditch"
      }
    },
    {
      "geometry": {
        "type": "Point",
        "coordinates": [
          -86.6,
          39.5333
        ]
      },
      "type": "Feature",
      "properties": {
        "hierarchy": [
          "tgn:2479856",
          "tgn:1000001",
          "tgn:7012149",
          "tgn:7007252",
          "tgn:7029392"
        ],
        "placetype": [
          "aat:300006075"
        ],
        "id": 2479856,
        "name:xx": "Lake Ditch"
      }
    },
    {
      "geometry": {
        "type": "Point",
        "coordinates": [
          -91.8667,
          38.4
        ]
      },
      "type": "Feature",
      "properties": {
        "hierarchy": [
          "tgn:2479857",
          "tgn:1000001",
          "tgn:7012149",
          "tgn:1002755",
          "tgn:7007523",
          "tgn:7029392"
        ],
        "placetype": [
          "aat:300006075"
        ],
        "id": 2479857,
        "name:xx": "Lake Ditch"
      }
    },
    {
      "geometry": {
        "type": "Point",
        "coordinates": [
          -119.85,
          39.5
        ]
      },
      "type": "Feature",
      "properties": {
        "hierarchy": [
          "tgn:2479858",
          "tgn:1000001",
          "tgn:7012149",
          "tgn:1002999",
          "tgn:7007526",
          "tgn:7029392"
        ],
        "placetype": [
          "aat:300006075"
        ],
        "id": 2479858,
        "name:xx": "Lake Ditch"
      }
    }
  ]
}
