{
  "geometry": {
    "type": "Point",
    "coordinates": [
      -103.5833,
      36.8833
    ]
  },
  "type": "Feature",
  "properties": {
    "hierarchy": [
      "tgn:2767124",
      "tgn:1000001",
      "tgn:7012149",
      "tgn:2001459",
      "tgn:7007566",
      "tgn:7029392"
    ],
    "placetype": [
      "aat:300008761"
    ],
    "id": 2767124,
    "name:xx": "White Rock Canyon"
  }
}
