{
  "type": "FeatureCollection",
  "features": [
    {
      "geometry": {
        "type": "Point",
        "coordinates": [
          12.966667,
          49.016667
        ]
      },
      "type": "Feature",
      "properties": {
        "hierarchy": [
          "tgn:7143310",
          "tgn:7003669",
          "tgn:1000003",
          "tgn:7000084",
          "tgn:7029392"
        ],
        "placetype": [
          "aat:300008347"
        ],
        "id": 7143310,
        "name:xx": "Linden"
      }
    },
    {
      "geometry": {
        "type": "Point",
        "coordinates": [
          13.566667,
          48.816667
        ]
      },
      "type": "Feature",
      "properties": {
        "hierarchy": [
          "tgn:7143311",
          "tgn:7003669",
          "tgn:1000003",
          "tgn:7000084",
          "tgn:7029392"
        ],
        "placetype": [
          "aat:300008347"
        ],
        "id": 7143311,
        "name:xx": "Linden"
      }
    },
    {
      "geometry": {
        "type": "Point",
        "coordinates": [
          11.266667,
          48.6
        ]
      },
      "type": "Feature",
      "properties": {
        "hierarchy": [
          "tgn:7143312",
          "tgn:7003669",
          "tgn:1000003",
          "tgn:7000084",
          "tgn:7029392"
        ],
        "placetype": [
          "aat:300008347"
        ],
        "id": 7143312,
        "name:xx": "Linden"
      }
    },
    {
      "geometry": {
        "type": "Point",
        "coordinates": [
          12.066667,
          48.583333
        ]
      },
      "type": "Feature",
      "properties": {
        "hierarchy": [
          "tgn:7143313",
          "tgn:7003669",
          "tgn:1000003",
          "tgn:7000084",
          "tgn:7029392"
        ],
        "placetype": [
          "aat:300008347"
        ],
        "id": 7143313,
        "name:xx": "Linden"
      }
    },
    {
      "geometry": {
        "type": "Point",
        "coordinates": [
          13.733333,
          48.533333
        ]
      },
      "type": "Feature",
      "properties": {
        "hierarchy": [
          "tgn:7143314",
          "tgn:7003669",
          "tgn:1000003",
          "tgn:7000084",
          "tgn:7029392"
        ],
        "placetype": [
          "aat:300008347"
        ],
        "id": 7143314,
        "name:xx": "Linden"
      }
    },
    {
      "geometry": {
        "type": "Point",
        "coordinates": [
          12.833333,
          48.416667
        ]
      },
      "type": "Feature",
      "properties": {
        "hierarchy": [
          "tgn:7143315",
          "tgn:7003669",
          "tgn:1000003",
          "tgn:7000084",
          "tgn:7029392"
        ],
        "placetype": [
          "aat:300008347"
        ],
        "id": 7143315,
        "name:xx": "Linden"
      }
    },
    {
      "geometry": {
        "type": "Point",
        "coordinates": [
          9.766667,
          48.016667
        ]
      },
      "type": "Feature",
      "properties": {
        "hierarchy": [
          "tgn:7143316",
          "tgn:7003692",
          "tgn:1000003",
          "tgn:7000084",
          "tgn:7029392"
        ],
        "placetype": [
          "aat:300008347"
        ],
        "id": 7143316,
        "name:xx": "Linden"
      }
    },
    {
      "geometry": {
        "type": "Point",
        "coordinates": [
          12.083333,
          47.916667
        ]
      },
      "type": "Feature",
      "properties": {
        "hierarchy": [
          "tgn:7143317",
          "tgn:7003669",
          "tgn:1000003",
          "tgn:7000084",
          "tgn:7029392"
        ],
        "placetype": [
          "aat:300008347"
        ],
        "id": 7143317,
        "name:xx": "Linden"
      }
    },
    {
      "geometry": {
        "type": "Point",
        "coordinates": [
          10,
          47.916667
        ]
      },
      "type": "Feature",
      "properties": {
        "hierarchy": [
          "tgn:7143318",
          "tgn:7003692",
          "tgn:1000003",
          "tgn:7000084",
          "tgn:7029392"
        ],
        "placetype": [
          "aat:300008347"
        ],
        "id": 7143318,
        "name:xx": "Linden"
      }
    },
    {
      "geometry": {
        "type": "Point",
        "coordinates": [
          10.7,
          47.9
        ]
      },
      "type": "Feature",
      "properties": {
        "hierarchy": [
          "tgn:7143319",
          "tgn:7003669",
          "tgn:1000003",
          "tgn:7000084",
          "tgn:7029392"
        ],
        "placetype": [
          "aat:300008347"
        ],
        "id": 7143319,
        "name:xx": "Linden"
      }
    }
  ]
}
