{
  "geometry": {
    "type": "Point",
    "coordinates": [
      -77.7167,
      39.7833
    ]
  },
  "type": "Feature",
  "properties": {
    "hierarchy": [
      "tgn:2526470",
      "tgn:1000001",
      "tgn:7012149",
      "tgn:1002387",
      "tgn:7007710",
      "tgn:7029392"
    ],
    "placetype": [
      "aat:300008697"
    ],
    "id": 2526470,
    "name:xx": "Moss Spring"
  }
}
