{
  "geometry": {
    "type": "Point",
    "coordinates": [
      -37.7667,
      -6.15
    ]
  },
  "type": "Feature",
  "properties": {
    "hierarchy": [
      "tgn:1020562",
      "tgn:7006257",
      "tgn:1000047",
      "tgn:7002455",
      "tgn:1000002",
      "tgn:7029392"
    ],
    "placetype": [
      "aat:300008347"
    ],
    "id": 1020562,
    "name:xx": "Almino Afonso"
  }
}
