{
  "geometry": {
    "type": "Point",
    "coordinates": [
      -67.0333,
      -22.6667
    ]
  },
  "type": "Feature",
  "properties": {
    "hierarchy": [
      "tgn:1106745",
      "tgn:1000002",
      "tgn:7029392"
    ],
    "placetype": [
      "aat:300008795"
    ],
    "id": 1106745,
    "name:xx": "Tinte, Cerro"
  }
}
