{
  "geometry": {
    "type": "Point",
    "coordinates": [
      25.766667,
      31.583333
    ]
  },
  "type": "Feature",
  "properties": {
    "hierarchy": [
      "tgn:7533404",
      "tgn:7001242",
      "tgn:7016833",
      "tgn:1001418",
      "tgn:7029392"
    ],
    "placetype": [
      "aat:300008777"
    ],
    "name:en": "Ḩāmid, 'Alam",
    "id": 7533404
  }
}
