{
  "type": "FeatureCollection",
  "features": [
    {
      "geometry": {
        "type": "Point",
        "coordinates": [
          7,
          46.1167
        ]
      },
      "type": "Feature",
      "properties": {
        "hierarchy": [
          "tgn:1064190",
          "tgn:1000003",
          "tgn:7003762",
          "tgn:7011731",
          "tgn:7029392"
        ],
        "placetype": [
          "aat:300008347"
        ],
        "id": 1064190,
        "name:xx": "Les Marécottes"
      }
    },
    {
      "geometry": {
        "type": "Point",
        "coordinates": [
          7.1167,
          46.4
        ]
      },
      "type": "Feature",
      "properties": {
        "hierarchy": [
          "tgn:1064191",
          "tgn:1000003",
          "tgn:7003763",
          "tgn:7011731",
          "tgn:7029392"
        ],
        "placetype": [
          "aat:300008347"
        ],
        "id": 1064191,
        "name:xx": "Les Mosses"
      }
    },
    {
      "geometry": {
        "type": "Point",
        "coordinates": [
          6.6833,
          46.9
        ]
      },
      "type": "Feature",
      "properties": {
        "hierarchy": [
          "tgn:1064192",
          "tgn:1000003",
          "tgn:7003751",
          "tgn:7011731",
          "tgn:7029392"
        ],
        "placetype": [
          "aat:300008347"
        ],
        "id": 1064192,
        "name:xx": "Les Ponts-de-Martel"
      }
    },
    {
      "geometry": {
        "type": "Point",
        "coordinates": [
          6.5,
          46.9
        ]
      },
      "type": "Feature",
      "properties": {
        "hierarchy": [
          "tgn:1064193",
          "tgn:1000003",
          "tgn:7003751",
          "tgn:7011731",
          "tgn:7029392"
        ],
        "placetype": [
          "aat:300008347"
        ],
        "id": 1064193,
        "name:xx": "Les Verrières"
      }
    },
    {
      "geometry": {
        "type": "Point",
        "coordinates": [
          7.6333,
          46.3833
        ]
      },
      "type": "Feature",
      "properties": {
        "hierarchy": [
          "tgn:1064195",
          "tgn:1000003",
          "tgn:7003762",
          "tgn:7011731",
          "tgn:7029392"
        ],
        "placetype": [
          "aat:300008347"
        ],
        "id": 1064195,
        "name:xx": "Leukerbad"
      }
    },
    {
      "geometry": {
        "type": "Point",
        "coordinates": [
          7.0167,
          46.35
        ]
      },
      "type": "Feature",
      "properties": {
        "hierarchy": [
          "tgn:1064196",
          "tgn:1000003",
          "tgn:7003763",
          "tgn:7011731",
          "tgn:7029392"
        ],
        "placetype": [
          "aat:300008347"
        ],
        "id": 1064196,
        "name:xx": "Leysin"
      }
    },
    {
      "geometry": {
        "type": "Point",
        "coordinates": [
          9.1,
          47.3333
        ]
      },
      "type": "Feature",
      "properties": {
        "hierarchy": [
          "tgn:1064197",
          "tgn:1000003",
          "tgn:7003755",
          "tgn:7011731",
          "tgn:7029392"
        ],
        "placetype": [
          "aat:300008347"
        ],
        "id": 1064197,
        "name:xx": "Lichtensteig"
      }
    },
    {
      "geometry": {
        "type": "Point",
        "coordinates": [
          9,
          46.9167
        ]
      },
      "type": "Feature",
      "properties": {
        "hierarchy": [
          "tgn:1064199",
          "tgn:7003747",
          "tgn:1000003",
          "tgn:7011731",
          "tgn:7029392"
        ],
        "placetype": [
          "aat:300008347"
        ],
        "id": 1064199,
        "name:xx": "Linthal"
      }
    }
  ]
}
