{
  "geometry": {
    "type": "Point",
    "coordinates": [
      -121.3333,
      35.8167
    ]
  },
  "type": "Feature",
  "properties": {
    "hierarchy": [
      "tgn:2302543",
      "tgn:1000001",
      "tgn:7012149",
      "tgn:7007157",
      "tgn:1002684",
      "tgn:7029392"
    ],
    "placetype": [
      "aat:300008706"
    ],
    "id": 2302543,
    "name:xx": "Dutra Creek"
  }
}
