{
  "geometry": {
    "type": "Point",
    "coordinates": [
      -74.3667,
      42.8167
    ]
  },
  "type": "Feature",
  "properties": {
    "hierarchy": [
      "tgn:2784578",
      "tgn:1000001",
      "tgn:7012149",
      "tgn:1002688",
      "tgn:7007568",
      "tgn:7029392"
    ],
    "placetype": [
      "aat:300008706"
    ],
    "id": 2784578,
    "name:xx": "Yatesville Creek"
  }
}
