{
  "type": "FeatureCollection",
  "features": [
    {
      "geometry": {
        "type": "Point",
        "coordinates": [
          18.9667,
          47.4
        ]
      },
      "type": "Feature",
      "properties": {
        "hierarchy": [
          "tgn:1005150",
          "tgn:7010547",
          "tgn:7006280",
          "tgn:7017994",
          "tgn:1000003",
          "tgn:7006278",
          "tgn:7029392"
        ],
        "placetype": [
          "aat:300000745"
        ],
        "id": 1005150,
        "name:xx": "Nagytétény"
      }
    },
    {
      "geometry": {
        "type": "Point",
        "coordinates": [
          77.1167,
          28.7
        ]
      },
      "type": "Feature",
      "properties": {
        "hierarchy": [
          "tgn:1005151",
          "tgn:1000004",
          "tgn:7000201",
          "tgn:7000198",
          "tgn:7029392"
        ],
        "placetype": [
          "aat:300000745"
        ],
        "id": 1005151,
        "name:xx": "Naharpur"
      }
    },
    {
      "geometry": {
        "type": "Point",
        "coordinates": [
          76.9833,
          28.611
        ]
      },
      "type": "Feature",
      "properties": {
        "hierarchy": [
          "tgn:1005152",
          "tgn:1000004",
          "tgn:7000201",
          "tgn:7000198",
          "tgn:7029392"
        ],
        "placetype": [
          "aat:300008347",
          "aat:300000745"
        ],
        "name:en": "Najafgarh",
        "id": 1005152
      }
    },
    {
      "geometry": {
        "type": "Point",
        "coordinates": [
          139.6667,
          35.4333
        ]
      },
      "type": "Feature",
      "properties": {
        "hierarchy": [
          "tgn:1005153",
          "tgn:7016696",
          "tgn:1000004",
          "tgn:7000894",
          "tgn:7004836",
          "tgn:1000120",
          "tgn:7029392"
        ],
        "placetype": [
          "aat:300000745"
        ],
        "id": 1005153,
        "name:xx": "Naka"
      }
    },
    {
      "geometry": {
        "type": "Point",
        "coordinates": [
          135.1833,
          34.85
        ]
      },
      "type": "Feature",
      "properties": {
        "hierarchy": [
          "tgn:1005154",
          "tgn:7016675",
          "tgn:1000004",
          "tgn:7000896",
          "tgn:7004560",
          "tgn:1000120",
          "tgn:7029392"
        ],
        "placetype": [
          "aat:300000745"
        ],
        "id": 1005154,
        "name:xx": "Nakaōzō"
      }
    },
    {
      "geometry": {
        "type": "Point",
        "coordinates": [
          135.75,
          35
        ]
      },
      "type": "Feature",
      "properties": {
        "hierarchy": [
          "tgn:1005156",
          "tgn:1000004",
          "tgn:1000998",
          "tgn:7000896",
          "tgn:7004603",
          "tgn:1000120",
          "tgn:7029392"
        ],
        "placetype": [
          "aat:300000745"
        ],
        "id": 1005156,
        "name:xx": "Nakagyō"
      }
    },
    {
      "geometry": {
        "type": "Point",
        "coordinates": [
          139.7,
          35.7
        ]
      },
      "type": "Feature",
      "properties": {
        "hierarchy": [
          "tgn:1005157",
          "tgn:1000004",
          "tgn:7000894",
          "tgn:1001032",
          "tgn:7004472",
          "tgn:1000120",
          "tgn:7029392"
        ],
        "placetype": [
          "aat:300000745"
        ],
        "id": 1005157,
        "name:xx": "Nakano"
      }
    },
    {
      "geometry": {
        "type": "Point",
        "coordinates": [
          139.7167,
          35.6
        ]
      },
      "type": "Feature",
      "properties": {
        "hierarchy": [
          "tgn:1005158",
          "tgn:1000004",
          "tgn:7000894",
          "tgn:1001032",
          "tgn:7004472",
          "tgn:1000120",
          "tgn:7029392"
        ],
        "placetype": [
          "aat:300000745"
        ],
        "id": 1005158,
        "name:xx": "Nakanobu"
      }
    },
    {
      "geometry": {
        "type": "Point",
        "coordinates": [
          139.6833,
          35.4833
        ]
      },
      "type": "Feature",
      "properties": {
        "hierarchy": [
          "tgn:1005159",
          "tgn:7016696",
          "tgn:1000004",
          "tgn:7000894",
          "tgn:7004836",
          "tgn:1000120",
          "tgn:7029392"
        ],
        "placetype": [
          "aat:300000745"
        ],
        "id": 1005159,
        "name:xx": "Namamugichō"
      }
    }
  ]
}
