{
  "geometry": {
    "type": "Point",
    "coordinates": [
      -120.3833,
      34.4667
    ]
  },
  "type": "Feature",
  "properties": {
    "hierarchy": [
      "tgn:2230202",
      "tgn:1000001",
      "tgn:7012149",
      "tgn:7007157",
      "tgn:1002867",
      "tgn:7029392"
    ],
    "placetype": [
      "aat:300008761"
    ],
    "id": 2230202,
    "name:xx": "Cementerio, Ca4ñada Del"
  }
}
