{
  "geometry": {
    "type": "Point",
    "coordinates": [
      30.126667,
      30.750556
    ]
  },
  "type": "Feature",
  "properties": {
    "hierarchy": [
      "tgn:7539639",
      "tgn:7001242",
      "tgn:1001075",
      "tgn:7016833",
      "tgn:7029392"
    ],
    "placetype": [
      "aat:300005926"
    ],
    "name:en": "Qabr Şāliḩ",
    "id": 7539639
  }
}
