{
  "geometry": {
    "type": "Point",
    "coordinates": [
      38.3333,
      37.3833
    ]
  },
  "type": "Feature",
  "properties": {
    "hierarchy": [
      "tgn:1086996",
      "tgn:1001586",
      "tgn:1000004",
      "tgn:7018456",
      "tgn:1000144",
      "tgn:7029392"
    ],
    "placetype": [
      "aat:300008347"
    ],
    "id": 1086996,
    "name:xx": "Yaylak"
  }
}
