{
  "geometry": {
    "type": "Point",
    "coordinates": [
      -115.8667,
      41.2833
    ]
  },
  "type": "Feature",
  "properties": {
    "hierarchy": [
      "tgn:2339150",
      "tgn:1000001",
      "tgn:2001411",
      "tgn:7012149",
      "tgn:7007526",
      "tgn:7029392"
    ],
    "placetype": [
      "aat:300008706"
    ],
    "id": 2339150,
    "name:xx": "Franks Creek"
  }
}
