{
  "geometry": {
    "type": "Point",
    "coordinates": [
      -110.35,
      33.8667
    ]
  },
  "type": "Feature",
  "properties": {
    "hierarchy": [
      "tgn:2449413",
      "tgn:1000001",
      "tgn:7006451",
      "tgn:2000093",
      "tgn:7012149",
      "tgn:7029392"
    ],
    "placetype": [
      "aat:300006191"
    ],
    "id": 2449413,
    "name:xx": "Limestone Tank"
  }
}
