{
  "geometry": {
    "type": "Point",
    "coordinates": [
      -133.8833,
      57.4833
    ]
  },
  "type": "Feature",
  "properties": {
    "hierarchy": [
      "tgn:2354750",
      "tgn:7006450",
      "tgn:1000001",
      "tgn:7012149",
      "tgn:7019760",
      "tgn:7029392"
    ],
    "placetype": [
      "aat:300008791"
    ],
    "id": 2354750,
    "name:xx": "Good Island"
  }
}
