{
  "geometry": {
    "type": "Point",
    "coordinates": [
      125.15,
      10.0667
    ]
  },
  "type": "Feature",
  "properties": {
    "hierarchy": [
      "tgn:1140756",
      "tgn:1008514",
      "tgn:1000004",
      "tgn:1001545",
      "tgn:1000135",
      "tgn:7029392"
    ],
    "placetype": [
      "aat:300008347"
    ],
    "id": 1140756,
    "name:xx": "San Francisco"
  }
}
