{
  "geometry": {
    "type": "Point",
    "coordinates": [
      -83.3333,
      37.0833
    ]
  },
  "type": "Feature",
  "properties": {
    "hierarchy": [
      "tgn:2386265",
      "tgn:1000001",
      "tgn:7012149",
      "tgn:2000811",
      "tgn:7007255",
      "tgn:7029392"
    ],
    "placetype": [
      "aat:300008699"
    ],
    "id": 2386265,
    "name:xx": "Hensley Branch"
  }
}
