{
  "type": "FeatureCollection",
  "features": [
    {
      "geometry": {
        "type": "Point",
        "coordinates": [
          79.5,
          17.966667
        ]
      },
      "type": "Feature",
      "properties": {
        "hierarchy": [
          "tgn:7575120",
          "tgn:1001828",
          "tgn:1000004",
          "tgn:7000198",
          "tgn:7029392"
        ],
        "placetype": [
          "aat:300008347"
        ],
        "name:en": "Kāzīpet",
        "id": 7575120
      }
    },
    {
      "geometry": {
        "type": "Point",
        "coordinates": [
          76.9,
          8.566667
        ]
      },
      "type": "Feature",
      "properties": {
        "hierarchy": [
          "tgn:7575121",
          "tgn:1000004",
          "tgn:7000198",
          "tgn:1001886",
          "tgn:7029392"
        ],
        "placetype": [
          "aat:300008347"
        ],
        "name:en": "Kazhakuttam",
        "id": 7575121
      }
    },
    {
      "geometry": {
        "type": "Point",
        "coordinates": [
          94.680521,
          28.411562
        ]
      },
      "type": "Feature",
      "properties": {
        "hierarchy": [
          "tgn:7575122",
          "tgn:7001819",
          "tgn:1000004",
          "tgn:7000198",
          "tgn:7029392"
        ],
        "placetype": [
          "aat:300008347"
        ],
        "name:en": "Kāying",
        "id": 7575122
      }
    },
    {
      "geometry": {
        "type": "Point",
        "coordinates": [
          77.8,
          8.95
        ]
      },
      "type": "Feature",
      "properties": {
        "hierarchy": [
          "tgn:7575123",
          "tgn:1000004",
          "tgn:7000198",
          "tgn:7001797",
          "tgn:7029392"
        ],
        "placetype": [
          "aat:300008347"
        ],
        "name:en": "Kayattār",
        "id": 7575123
      }
    },
    {
      "geometry": {
        "type": "Point",
        "coordinates": [
          78.9,
          19.9
        ]
      },
      "type": "Feature",
      "properties": {
        "hierarchy": [
          "tgn:7575124",
          "tgn:1000004",
          "tgn:7000198",
          "tgn:1001895",
          "tgn:7029392"
        ],
        "placetype": [
          "aat:300008347"
        ],
        "name:en": "Kāyar",
        "id": 7575124
      }
    },
    {
      "geometry": {
        "type": "Point",
        "coordinates": [
          76.5,
          9.15
        ]
      },
      "type": "Feature",
      "properties": {
        "hierarchy": [
          "tgn:7575125",
          "tgn:1000004",
          "tgn:7000198",
          "tgn:1001886",
          "tgn:7029392"
        ],
        "placetype": [
          "aat:300185707"
        ],
        "name:en": "Kāyankulam Kāyal",
        "id": 7575125
      }
    },
    {
      "geometry": {
        "type": "Point",
        "coordinates": [
          96.566667,
          28.816667
        ]
      },
      "type": "Feature",
      "properties": {
        "hierarchy": [
          "tgn:7575128",
          "tgn:7001819",
          "tgn:1000004",
          "tgn:7000198",
          "tgn:7029392"
        ],
        "placetype": [
          "aat:300259572"
        ],
        "name:en": "Chia-ya Shan-k'ou",
        "id": 7575128
      }
    },
    {
      "geometry": {
        "type": "Point",
        "coordinates": [
          77.383333,
          18.8
        ]
      },
      "type": "Feature",
      "properties": {
        "hierarchy": [
          "tgn:7575129",
          "tgn:1000004",
          "tgn:7000198",
          "tgn:1001895",
          "tgn:7029392"
        ],
        "placetype": [
          "aat:300008347"
        ],
        "name:en": "Kawta",
        "id": 7575129
      }
    }
  ]
}
