{
  "geometry": {
    "type": "Point",
    "coordinates": [
      -90.75,
      37.9333
    ]
  },
  "type": "Feature",
  "properties": {
    "hierarchy": [
      "tgn:2537487",
      "tgn:1000001",
      "tgn:7012149",
      "tgn:2001254",
      "tgn:7007523",
      "tgn:7029392"
    ],
    "placetype": [
      "aat:300000390"
    ],
    "id": 2537487,
    "name:xx": "Negro Lead Diggings"
  }
}
