{
  "geometry": {
    "type": "Point",
    "coordinates": [
      -73.4167,
      42.85
    ]
  },
  "type": "Feature",
  "properties": {
    "hierarchy": [
      "tgn:2470436",
      "tgn:1000001",
      "tgn:7012149",
      "tgn:1002821",
      "tgn:7007568",
      "tgn:7029392"
    ],
    "placetype": [
      "aat:300008680"
    ],
    "id": 2470436,
    "name:xx": "Lorraine, Lake"
  }
}
