{
  "geometry": {
    "type": "Point",
    "coordinates": [
      -87.6333,
      44.1667
    ]
  },
  "type": "Feature",
  "properties": {
    "hierarchy": [
      "tgn:2122390",
      "tgn:1000001",
      "tgn:7012149",
      "tgn:2002335",
      "tgn:7007922",
      "tgn:7029392"
    ],
    "placetype": [
      "aat:300008347"
    ],
    "id": 2122390,
    "name:xx": "Shoto"
  }
}
