{
  "geometry": {
    "type": "Point",
    "coordinates": [
      -74.5667,
      43.0167
    ]
  },
  "type": "Feature",
  "properties": {
    "hierarchy": [
      "tgn:2335450",
      "tgn:1000001",
      "tgn:7012149",
      "tgn:1002397",
      "tgn:7007568",
      "tgn:7029392"
    ],
    "placetype": [
      "aat:300006191"
    ],
    "id": 2335450,
    "name:xx": "Fort Plain Reservoir"
  }
}
