{
  "geometry": {
    "type": "Point",
    "coordinates": [
      -88.5833,
      46.3333
    ]
  },
  "type": "Feature",
  "properties": {
    "hierarchy": [
      "tgn:2570049",
      "tgn:1000001",
      "tgn:7012149",
      "tgn:2000966",
      "tgn:7007520",
      "tgn:7029392"
    ],
    "placetype": [
      "aat:300008706"
    ],
    "id": 2570049,
    "name:xx": "Pass Creek"
  }
}
