{
  "geometry": {
    "type": "Point",
    "coordinates": [
      -82.0833,
      30.7833
    ]
  },
  "type": "Feature",
  "properties": {
    "hierarchy": [
      "tgn:2466432",
      "tgn:1000001",
      "tgn:2000315",
      "tgn:7012149",
      "tgn:7007248",
      "tgn:7029392"
    ],
    "placetype": [
      "aat:300008699"
    ],
    "id": 2466432,
    "name:xx": "Long Branch"
  }
}
