{
  "geometry": {
    "type": "Point",
    "coordinates": [
      39.0167,
      47.2833
    ]
  },
  "type": "Feature",
  "properties": {
    "hierarchy": [
      "tgn:1060943",
      "tgn:1000004",
      "tgn:1003405",
      "tgn:7018214",
      "tgn:7002435",
      "tgn:7029392"
    ],
    "placetype": [
      "aat:300008347"
    ],
    "id": 1060943,
    "name:xx": "Varenovka"
  }
}
