{
  "geometry": {
    "type": "Point",
    "coordinates": [
      -115.3333,
      45.7333
    ]
  },
  "type": "Feature",
  "properties": {
    "hierarchy": [
      "tgn:2179509",
      "tgn:1000001",
      "tgn:7012149",
      "tgn:2000476",
      "tgn:7007250",
      "tgn:7029392"
    ],
    "placetype": [
      "aat:300008706"
    ],
    "id": 2179509,
    "name:xx": "Blanco Creek"
  }
}
