{
  "geometry": {
    "type": "Point",
    "coordinates": [
      -75.3833,
      43.1833
    ]
  },
  "type": "Feature",
  "properties": {
    "hierarchy": [
      "tgn:2556906",
      "tgn:1000001",
      "tgn:7012149",
      "tgn:7007568",
      "tgn:7029392"
    ],
    "placetype": [
      "aat:300006075"
    ],
    "id": 2556906,
    "name:xx": "Old Erie Canal"
  }
}
