{
  "geometry": {
    "type": "Point",
    "coordinates": [
      -88.9333,
      31.4167
    ]
  },
  "type": "Feature",
  "properties": {
    "hierarchy": [
      "tgn:2583169",
      "tgn:1000001",
      "tgn:7012149",
      "tgn:2001141",
      "tgn:7007522",
      "tgn:7029392"
    ],
    "placetype": [
      "aat:300008699"
    ],
    "id": 2583169,
    "name:xx": "Pine Log Branch"
  }
}
