{
  "geometry": {
    "type": "Point",
    "coordinates": [
      -75.3333,
      42.4333
    ]
  },
  "type": "Feature",
  "properties": {
    "hierarchy": [
      "tgn:2255644",
      "tgn:1000001",
      "tgn:7012149",
      "tgn:7014318",
      "tgn:7007568",
      "tgn:7029392"
    ],
    "placetype": [
      "aat:300008347"
    ],
    "id": 2255644,
    "name:xx": "Copes Corner"
  }
}
