{
  "geometry": {
    "type": "Point",
    "coordinates": [
      -146.9667,
      64.8333
    ]
  },
  "type": "Feature",
  "properties": {
    "hierarchy": [
      "tgn:2531736",
      "tgn:7006450",
      "tgn:1000001",
      "tgn:7019674",
      "tgn:7012149",
      "tgn:7029392"
    ],
    "placetype": [
      "aat:300008699"
    ],
    "id": 2531736,
    "name:xx": "Mullen Slough"
  }
}
