{
  "type": "FeatureCollection",
  "features": [
    {
      "geometry": {
        "type": "Point",
        "coordinates": [
          12.081667,
          46.074444
        ]
      },
      "type": "Feature",
      "properties": {
        "hierarchy": [
          "tgn:7045511",
          "tgn:7002991",
          "tgn:1000003",
          "tgn:7002997",
          "tgn:1000080",
          "tgn:7029392"
        ],
        "placetype": [
          "aat:300008699"
        ],
        "id": 7045511,
        "name:xx": "Cordevole, Torrente"
      }
    },
    {
      "geometry": {
        "type": "Point",
        "coordinates": [
          12.05,
          46.016667
        ]
      },
      "type": "Feature",
      "properties": {
        "hierarchy": [
          "tgn:7045513",
          "tgn:7002991",
          "tgn:1000003",
          "tgn:7002997",
          "tgn:1000080",
          "tgn:7029392"
        ],
        "placetype": [
          "aat:300008347"
        ],
        "id": 7045513,
        "name:xx": "Cordellon"
      }
    },
    {
      "geometry": {
        "type": "Point",
        "coordinates": [
          8.394722,
          40.468333
        ]
      },
      "type": "Feature",
      "properties": {
        "hierarchy": [
          "tgn:7045515",
          "tgn:7015163",
          "tgn:1000003",
          "tgn:7003121",
          "tgn:1000080",
          "tgn:7029392"
        ],
        "placetype": [
          "aat:300008795"
        ],
        "id": 7045515,
        "name:xx": "Corcorija, Punta sa"
      }
    },
    {
      "geometry": {
        "type": "Point",
        "coordinates": [
          12.783333,
          43.2
        ]
      },
      "type": "Feature",
      "properties": {
        "hierarchy": [
          "tgn:7045518",
          "tgn:7003170",
          "tgn:1000003",
          "tgn:7003125",
          "tgn:1000080",
          "tgn:7029392"
        ],
        "placetype": [
          "aat:300008347"
        ],
        "id": 7045518,
        "name:xx": "Corcia"
      }
    }
  ]
}
