{
  "geometry": {
    "type": "Point",
    "coordinates": [
      -81.5333,
      28.7833
    ]
  },
  "type": "Feature",
  "properties": {
    "hierarchy": [
      "tgn:2475461",
      "tgn:1000001",
      "tgn:7012149",
      "tgn:7007240",
      "tgn:7029392"
    ],
    "placetype": [
      "aat:300008680"
    ],
    "id": 2475461,
    "name:xx": "Lucie, Lake"
  }
}
