{
  "geometry": {
    "type": "Point",
    "coordinates": [
      17.4667,
      21.75
    ]
  },
  "type": "Feature",
  "properties": {
    "hierarchy": [
      "tgn:1088462",
      "tgn:7001242",
      "tgn:1000968",
      "tgn:1000156",
      "tgn:7029392"
    ],
    "placetype": [
      "aat:300008347"
    ],
    "id": 1088462,
    "name:xx": "Aozou"
  }
}
