{
  "geometry": {
    "type": "Point",
    "coordinates": [
      -108.3667,
      35.7167
    ]
  },
  "type": "Feature",
  "properties": {
    "hierarchy": [
      "tgn:2624769",
      "tgn:1000001",
      "tgn:7012149",
      "tgn:7019676",
      "tgn:7007566",
      "tgn:7029392"
    ],
    "placetype": [
      "aat:300008697"
    ],
    "id": 2624769,
    "name:xx": "Rock Spring"
  }
}
