{
  "geometry": {
    "type": "Point",
    "coordinates": [
      -122.1667,
      38.4833
    ]
  },
  "type": "Feature",
  "properties": {
    "hierarchy": [
      "tgn:2249351",
      "tgn:1000001",
      "tgn:7012149",
      "tgn:7007157",
      "tgn:1002706",
      "tgn:7029392"
    ],
    "placetype": [
      "aat:300008761"
    ],
    "id": 2249351,
    "name:xx": "Coleman Canyon"
  }
}
