{
  "geometry": {
    "type": "Point",
    "coordinates": [
      -121.55,
      48.9167
    ]
  },
  "type": "Feature",
  "properties": {
    "hierarchy": [
      "tgn:2666830",
      "tgn:1000001",
      "tgn:7012149",
      "tgn:1003020",
      "tgn:7007920",
      "tgn:7029392"
    ],
    "placetype": [
      "aat:300386831"
    ],
    "id": 2666830,
    "name:xx": "Skagit Range"
  }
}
