{
  "geometry": {
    "type": "Point",
    "coordinates": [
      77.773439,
      30.39204
    ]
  },
  "type": "Feature",
  "properties": {
    "hierarchy": [
      "tgn:7591688",
      "tgn:1000004",
      "tgn:7000198",
      "tgn:7031786",
      "tgn:7029392"
    ],
    "placetype": [
      "aat:300008699"
    ],
    "name:en": "Bānswāli Rao",
    "id": 7591688
  }
}
