{
  "geometry": {
    "type": "Point",
    "coordinates": [
      -113.4167,
      37.35
    ]
  },
  "type": "Feature",
  "properties": {
    "hierarchy": [
      "tgn:2398645",
      "tgn:1000001",
      "tgn:7012149",
      "tgn:2002127",
      "tgn:7007827",
      "tgn:7029392"
    ],
    "placetype": [
      "aat:300008761"
    ],
    "id": 2398645,
    "name:xx": "Hop Canyon"
  }
}
