{
  "geometry": {
    "type": "Point",
    "coordinates": [
      -109.6333,
      45.2167
    ]
  },
  "type": "Feature",
  "properties": {
    "hierarchy": [
      "tgn:2719812",
      "tgn:1000001",
      "tgn:2001264",
      "tgn:7012149",
      "tgn:7007524",
      "tgn:7029392"
    ],
    "placetype": [
      "aat:300008798"
    ],
    "id": 2719812,
    "name:xx": "Three Sisters"
  }
}
