{
  "geometry": {
    "type": "Point",
    "coordinates": [
      -98.4833,
      36.6833
    ]
  },
  "type": "Feature",
  "properties": {
    "hierarchy": [
      "tgn:2258946",
      "tgn:2001624",
      "tgn:1000001",
      "tgn:7012149",
      "tgn:7007707",
      "tgn:7029392"
    ],
    "placetype": [
      "aat:300008706"
    ],
    "id": 2258946,
    "name:xx": "Cottonwood Creek"
  }
}
