{
  "type": "FeatureCollection",
  "features": [
    {
      "geometry": {
        "type": "Point",
        "coordinates": [
          16.3,
          39.816667
        ]
      },
      "type": "Feature",
      "properties": {
        "hierarchy": [
          "tgn:1044280",
          "tgn:1003450",
          "tgn:7007850",
          "tgn:1000003",
          "tgn:1000080",
          "tgn:7029392"
        ],
        "placetype": [
          "aat:300008347"
        ],
        "id": 1044280,
        "name:xx": "Civita"
      }
    },
    {
      "geometry": {
        "type": "Point",
        "coordinates": [
          13.4333,
          42.3
        ]
      },
      "type": "Feature",
      "properties": {
        "hierarchy": [
          "tgn:1044282",
          "tgn:7009084",
          "tgn:7004154",
          "tgn:1000003",
          "tgn:1000080",
          "tgn:7029392"
        ],
        "placetype": [
          "aat:300008347"
        ],
        "id": 1044282,
        "name:xx": "Civita di Bagno"
      }
    },
    {
      "geometry": {
        "type": "Point",
        "coordinates": [
          14.683333,
          41.783333
        ]
      },
      "type": "Feature",
      "properties": {
        "hierarchy": [
          "tgn:1044283",
          "tgn:1003444",
          "tgn:1000003",
          "tgn:7003241",
          "tgn:1000080",
          "tgn:7029392"
        ],
        "placetype": [
          "aat:300008347"
        ],
        "id": 1044283,
        "name:xx": "Civitacampomarano"
      }
    },
    {
      "geometry": {
        "type": "Point",
        "coordinates": [
          13.666667,
          43.316667
        ]
      },
      "type": "Feature",
      "properties": {
        "hierarchy": [
          "tgn:1044284",
          "tgn:1003471",
          "tgn:1000003",
          "tgn:7003240",
          "tgn:1000080",
          "tgn:7029392"
        ],
        "placetype": [
          "aat:300008347"
        ],
        "id": 1044284,
        "name:xx": "Civitanova Alta"
      }
    },
    {
      "geometry": {
        "type": "Point",
        "coordinates": [
          14.4,
          41.666667
        ]
      },
      "type": "Feature",
      "properties": {
        "hierarchy": [
          "tgn:1044286",
          "tgn:1003464",
          "tgn:1000003",
          "tgn:7003241",
          "tgn:1000080",
          "tgn:7029392"
        ],
        "placetype": [
          "aat:300008347"
        ],
        "id": 1044286,
        "name:xx": "Civitanova del Sannio"
      }
    },
    {
      "geometry": {
        "type": "Point",
        "coordinates": [
          11.283333,
          43
        ]
      },
      "type": "Feature",
      "properties": {
        "hierarchy": [
          "tgn:1044289",
          "tgn:1003460",
          "tgn:1000003",
          "tgn:7009760",
          "tgn:1000080",
          "tgn:7029392"
        ],
        "placetype": [
          "aat:300008347"
        ],
        "id": 1044289,
        "name:xx": "Civitella Marittima"
      }
    }
  ]
}
