{
  "geometry": {
    "type": "Point",
    "coordinates": [
      -74.5833,
      44.0333
    ]
  },
  "type": "Feature",
  "properties": {
    "hierarchy": [
      "tgn:2461938",
      "tgn:1000001",
      "tgn:7012149",
      "tgn:1002440",
      "tgn:7007568",
      "tgn:7029392"
    ],
    "placetype": [
      "aat:300008680"
    ],
    "id": 2461938,
    "name:xx": "Little Tupper Lake"
  }
}
