{
  "geometry": {
    "type": "Point",
    "coordinates": [
      -110.7667,
      34.4833
    ]
  },
  "type": "Feature",
  "properties": {
    "hierarchy": [
      "tgn:2651337",
      "tgn:1000001",
      "tgn:7006451",
      "tgn:2000092",
      "tgn:7012149",
      "tgn:7029392"
    ],
    "placetype": [
      "aat:300006191"
    ],
    "id": 2651337,
    "name:xx": "Section Tank"
  }
}
