{
  "geometry": {
    "type": "Point",
    "coordinates": [
      18.2167,
      59.25
    ]
  },
  "type": "Feature",
  "properties": {
    "hierarchy": [
      "tgn:1062845",
      "tgn:1000003",
      "tgn:7003777",
      "tgn:1000097",
      "tgn:7029392"
    ],
    "placetype": [
      "aat:300008347"
    ],
    "id": 1062845,
    "name:xx": "Bollmora"
  }
}
