{
  "geometry": {
    "type": "Point",
    "coordinates": [
      -89.5833,
      43.65
    ]
  },
  "type": "Feature",
  "properties": {
    "hierarchy": [
      "tgn:2495878",
      "tgn:1000001",
      "tgn:7012149",
      "tgn:7007922",
      "tgn:7029392"
    ],
    "placetype": [
      "aat:300006191"
    ],
    "id": 2495878,
    "name:xx": "Mason Lake"
  }
}
