{
  "geometry": {
    "type": "Point",
    "coordinates": [
      -91.65,
      33.0667
    ]
  },
  "type": "Feature",
  "properties": {
    "hierarchy": [
      "tgn:2331059",
      "tgn:2000106",
      "tgn:1000001",
      "tgn:7016172",
      "tgn:7012149",
      "tgn:7029392"
    ],
    "placetype": [
      "aat:300008905"
    ],
    "id": 2331059,
    "name:xx": "Flat Slough"
  }
}
