{
  "geometry": {
    "type": "Point",
    "coordinates": [
      -87.9333,
      41.7833
    ]
  },
  "type": "Feature",
  "properties": {
    "hierarchy": [
      "tgn:2425420",
      "tgn:1000001",
      "tgn:7019013",
      "tgn:7012149",
      "tgn:7007251",
      "tgn:7029392"
    ],
    "placetype": [
      "aat:300008680"
    ],
    "id": 2425420,
    "name:xx": "Johnson Slough"
  }
}
