{
  "geometry": {
    "type": "Point",
    "coordinates": [
      -91.85,
      42.8667
    ]
  },
  "type": "Feature",
  "properties": {
    "hierarchy": [
      "tgn:2000593",
      "tgn:1000001",
      "tgn:7012149",
      "tgn:7007253",
      "tgn:7029392"
    ],
    "placetype": [
      "aat:300387145",
      "aat:300000771"
    ],
    "id": 2000593,
    "name:xx": "Fayette"
  }
}
