{
  "type": "FeatureCollection",
  "features": [
    {
      "geometry": {
        "type": "Point",
        "coordinates": [
          -5.966667,
          56.6
        ]
      },
      "type": "Feature",
      "properties": {
        "hierarchy": [
          "tgn:7465500",
          "tgn:7002444",
          "tgn:1000003",
          "tgn:7008082",
          "tgn:7008591",
          "tgn:7029392"
        ],
        "placetype": [
          "aat:300008347"
        ],
        "name:en": "Bonnavoulin",
        "id": 7465500
      }
    },
    {
      "geometry": {
        "type": "Point",
        "coordinates": [
          -2.55,
          55.5
        ]
      },
      "type": "Feature",
      "properties": {
        "hierarchy": [
          "tgn:7465501",
          "tgn:7002444",
          "tgn:1000003",
          "tgn:7008072",
          "tgn:7008591",
          "tgn:7029392"
        ],
        "placetype": [
          "aat:300387502"
        ],
        "name:en": "Bonjedward House",
        "id": 7465501
      }
    },
    {
      "geometry": {
        "type": "Point",
        "coordinates": [
          -4.566667,
          55.983333
        ]
      },
      "type": "Feature",
      "properties": {
        "hierarchy": [
          "tgn:7465502",
          "tgn:7002444",
          "tgn:1000003",
          "tgn:7019098",
          "tgn:7008591",
          "tgn:7029392"
        ],
        "placetype": [
          "aat:300008347"
        ],
        "name:en": "Bonhill",
        "id": 7465502
      }
    },
    {
      "geometry": {
        "type": "Point",
        "coordinates": [
          -6.85,
          54.316667
        ]
      },
      "type": "Feature",
      "properties": {
        "hierarchy": [
          "tgn:7465504",
          "tgn:7008696",
          "tgn:7002448",
          "tgn:1000003",
          "tgn:7008591",
          "tgn:7029392"
        ],
        "placetype": [
          "aat:300008347"
        ],
        "name:en": "Bondville",
        "id": 7465504
      }
    },
    {
      "geometry": {
        "type": "Point",
        "coordinates": [
          -1.516667,
          55.316667
        ]
      },
      "type": "Feature",
      "properties": {
        "hierarchy": [
          "tgn:7465505",
          "tgn:7002445",
          "tgn:1000003",
          "tgn:7008165",
          "tgn:7008591",
          "tgn:7029392"
        ],
        "placetype": [
          "aat:300008808"
        ],
        "name:en": "Bondicarr Bush",
        "id": 7465505
      }
    },
    {
      "geometry": {
        "type": "Point",
        "coordinates": [
          -4.616667,
          52
        ]
      },
      "type": "Feature",
      "properties": {
        "hierarchy": [
          "tgn:7465508",
          "tgn:7002443",
          "tgn:1000003",
          "tgn:7018993",
          "tgn:7008591",
          "tgn:7029392"
        ],
        "placetype": [
          "aat:300008347"
        ],
        "name:en": "Boncath",
        "id": 7465508
      }
    }
  ]
}
