{
  "geometry": {
    "type": "Point",
    "coordinates": [
      -54.5667,
      -25.5667
    ]
  },
  "type": "Feature",
  "properties": {
    "hierarchy": [
      "tgn:1019891",
      "tgn:7006477",
      "tgn:1001434",
      "tgn:1000002",
      "tgn:7029392"
    ],
    "placetype": [
      "aat:300008347"
    ],
    "id": 1019891,
    "name:xx": "Puerto Iguazú"
  }
}
