{
  "geometry": {
    "type": "Point",
    "coordinates": [
      -83.4833,
      35.5667
    ]
  },
  "type": "Feature",
  "properties": {
    "hierarchy": [
      "tgn:2472617",
      "tgn:1000001",
      "tgn:7012149",
      "tgn:7029392"
    ],
    "placetype": [
      "aat:300008798"
    ],
    "id": 2472617,
    "name:xx": "Love, Mount"
  }
}
