{
  "geometry": {
    "type": "Point",
    "coordinates": [
      -118.2167,
      34.4333
    ]
  },
  "type": "Feature",
  "properties": {
    "hierarchy": [
      "tgn:2013526",
      "tgn:1000001",
      "tgn:7012149",
      "tgn:7007157",
      "tgn:1002608",
      "tgn:7029392"
    ],
    "placetype": [
      "aat:300387016"
    ],
    "id": 2013526,
    "name:xx": "Ravenna"
  }
}
