{
  "geometry": {
    "type": "Point",
    "coordinates": [
      -64.1167,
      44.9667
    ]
  },
  "type": "Feature",
  "properties": {
    "hierarchy": [
      "tgn:1014523",
      "tgn:7005685",
      "tgn:1000001",
      "tgn:7005802",
      "tgn:7029392"
    ],
    "placetype": [
      "aat:300008347"
    ],
    "id": 1014523,
    "name:xx": "Three Mile Plains"
  }
}
