{
  "geometry": {
    "type": "Point",
    "coordinates": [
      -67.55,
      10.1833
    ]
  },
  "type": "Feature",
  "properties": {
    "hierarchy": [
      "tgn:1025224",
      "tgn:1001831",
      "tgn:1000002",
      "tgn:1000059",
      "tgn:7029392"
    ],
    "placetype": [
      "aat:300008347"
    ],
    "id": 1025224,
    "name:xx": "Palo Negro"
  }
}
