{
  "geometry": {
    "type": "Point",
    "coordinates": [
      -106.9333,
      45.0833
    ]
  },
  "type": "Feature",
  "properties": {
    "hierarchy": [
      "tgn:2573090",
      "tgn:1000001",
      "tgn:2001261",
      "tgn:7012149",
      "tgn:7007524",
      "tgn:7029392"
    ],
    "placetype": [
      "aat:300008706"
    ],
    "id": 2573090,
    "name:xx": "Pearson Creek"
  }
}
