{
  "geometry": {
    "type": "Point",
    "coordinates": [
      -82.85,
      32.85
    ]
  },
  "type": "Feature",
  "properties": {
    "hierarchy": [
      "tgn:2561094",
      "tgn:1000001",
      "tgn:7012149",
      "tgn:2000441",
      "tgn:7007248",
      "tgn:7029392"
    ],
    "placetype": [
      "aat:300008680"
    ],
    "id": 2561094,
    "name:xx": "Orrs Pond"
  }
}
