{
  "geometry": {
    "type": "Point",
    "coordinates": [
      -104.75,
      44.8667
    ]
  },
  "type": "Feature",
  "properties": {
    "hierarchy": [
      "tgn:2210409",
      "tgn:1000001",
      "tgn:2002370",
      "tgn:7012149",
      "tgn:7007923",
      "tgn:7029392"
    ],
    "placetype": [
      "aat:300006191"
    ],
    "id": 2210409,
    "name:xx": "Bush Reservoir"
  }
}
