{
  "geometry": {
    "type": "Point",
    "coordinates": [
      35.4833,
      -16.0833
    ]
  },
  "type": "Feature",
  "properties": {
    "hierarchy": [
      "tgn:1091076",
      "tgn:7001242",
      "tgn:1001542",
      "tgn:7000726",
      "tgn:7029392"
    ],
    "placetype": [
      "aat:300008347"
    ],
    "id": 1091076,
    "name:xx": "Mulanje"
  }
}
