{
  "geometry": {
    "type": "Point",
    "coordinates": [
      77.6333,
      41.0833
    ]
  },
  "type": "Feature",
  "properties": {
    "hierarchy": [
      "tgn:1107210",
      "tgn:1000004",
      "tgn:1003394",
      "tgn:7006655",
      "tgn:7029392"
    ],
    "placetype": [
      "aat:300008798"
    ],
    "id": 1107210,
    "name:xx": "Dankova, Pik"
  }
}
