{
  "geometry": {
    "type": "Point",
    "coordinates": [
      -106.0167,
      42.1667
    ]
  },
  "type": "Feature",
  "properties": {
    "hierarchy": [
      "tgn:2167184",
      "tgn:2002365",
      "tgn:1000001",
      "tgn:7012149",
      "tgn:7007923",
      "tgn:7029392"
    ],
    "placetype": [
      "aat:300008680"
    ],
    "id": 2167184,
    "name:xx": "Big Charlie Lakes"
  }
}
