{
  "geometry": {
    "type": "Point",
    "coordinates": [
      -83.75,
      33.9167
    ]
  },
  "type": "Feature",
  "properties": {
    "hierarchy": [
      "tgn:2465079",
      "tgn:1000001",
      "tgn:2000298",
      "tgn:7012149",
      "tgn:7007248",
      "tgn:7029392"
    ],
    "placetype": [
      "aat:300006191"
    ],
    "id": 2465079,
    "name:xx": "Lokeys Lake"
  }
}
