{
  "geometry": {
    "type": "Point",
    "coordinates": [
      -114.0833,
      39.7667
    ]
  },
  "type": "Feature",
  "properties": {
    "hierarchy": [
      "tgn:2361169",
      "tgn:1000001",
      "tgn:7012149",
      "tgn:2001420",
      "tgn:7007526",
      "tgn:7029392"
    ],
    "placetype": [
      "aat:300008761"
    ],
    "id": 2361169,
    "name:xx": "Gravel Canyon"
  }
}
