{
  "geometry": {
    "type": "Point",
    "coordinates": [
      -79.2167,
      40.1167
    ]
  },
  "type": "Feature",
  "properties": {
    "hierarchy": [
      "tgn:2624633",
      "tgn:1000001",
      "tgn:7012149",
      "tgn:1003017",
      "tgn:7007710",
      "tgn:7029392"
    ],
    "placetype": [
      "aat:300008699"
    ],
    "id": 2624633,
    "name:xx": "Rock Run"
  }
}
