{
  "geometry": {
    "type": "Point",
    "coordinates": [
      71.1333,
      34.8667
    ]
  },
  "type": "Feature",
  "properties": {
    "hierarchy": [
      "tgn:1065376",
      "tgn:7016612",
      "tgn:1000004",
      "tgn:1001362",
      "tgn:7029392"
    ],
    "placetype": [
      "aat:300008347",
      "aat:300387223",
      "aat:300008375"
    ],
    "id": 1065376,
    "name:xx": "Asadābād"
  }
}
