{
  "geometry": {
    "type": "Point",
    "coordinates": [
      -81.7167,
      38.2667
    ]
  },
  "type": "Feature",
  "properties": {
    "hierarchy": [
      "tgn:2487465",
      "tgn:1000001",
      "tgn:7012149",
      "tgn:2002270",
      "tgn:7013961",
      "tgn:7029392"
    ],
    "placetype": [
      "aat:300008706"
    ],
    "id": 2487465,
    "name:xx": "Left Fork Brier Creek"
  }
}
