{
  "geometry": {
    "type": "Point",
    "coordinates": [
      -85.5167,
      33.1833
    ]
  },
  "type": "Feature",
  "properties": {
    "hierarchy": [
      "tgn:2542285",
      "tgn:7002659",
      "tgn:1000001",
      "tgn:7012149",
      "tgn:2000055",
      "tgn:7029392"
    ],
    "placetype": [
      "aat:300008706"
    ],
    "id": 2542285,
    "name:xx": "No Business Creek"
  }
}
