{
  "geometry": {
    "type": "Point",
    "coordinates": [
      -90.35,
      37.4333
    ]
  },
  "type": "Feature",
  "properties": {
    "hierarchy": [
      "tgn:2255131",
      "tgn:1000001",
      "tgn:7012149",
      "tgn:2001217",
      "tgn:7007523",
      "tgn:7029392"
    ],
    "placetype": [
      "aat:300008761"
    ],
    "id": 2255131,
    "name:xx": "Cooper Hollow"
  }
}
