{
  "type": "FeatureCollection",
  "features": [
    {
      "geometry": {
        "type": "Point",
        "coordinates": [
          -109.2667,
          34.0667
        ]
      },
      "type": "Feature",
      "properties": {
        "hierarchy": [
          "tgn:2622340",
          "tgn:2000090",
          "tgn:1000001",
          "tgn:7006451",
          "tgn:7012149",
          "tgn:7029392"
        ],
        "placetype": [
          "aat:300006191"
        ],
        "id": 2622340,
        "name:xx": "Robertson Tank"
      }
    },
    {
      "geometry": {
        "type": "Point",
        "coordinates": [
          -105.4167,
          32.5833
        ]
      },
      "type": "Feature",
      "properties": {
        "hierarchy": [
          "tgn:2622341",
          "tgn:1000001",
          "tgn:7012149",
          "tgn:2001447",
          "tgn:7007566",
          "tgn:7029392"
        ],
        "placetype": [
          "aat:300006191"
        ],
        "id": 2622341,
        "name:xx": "Robertson Tank"
      }
    },
    {
      "geometry": {
        "type": "Point",
        "coordinates": [
          -108.6667,
          32.8833
        ]
      },
      "type": "Feature",
      "properties": {
        "hierarchy": [
          "tgn:2622342",
          "tgn:1000001",
          "tgn:7012149",
          "tgn:2001437",
          "tgn:7007566",
          "tgn:7029392"
        ],
        "placetype": [
          "aat:300006191"
        ],
        "id": 2622342,
        "name:xx": "Robertson Tank"
      }
    },
    {
      "geometry": {
        "type": "Point",
        "coordinates": [
          -104.8,
          34.1167
        ]
      },
      "type": "Feature",
      "properties": {
        "hierarchy": [
          "tgn:2622343",
          "tgn:1000001",
          "tgn:7019560",
          "tgn:7012149",
          "tgn:7007566",
          "tgn:7029392"
        ],
        "placetype": [
          "aat:300006191"
        ],
        "id": 2622343,
        "name:xx": "Robertson Tank"
      }
    },
    {
      "geometry": {
        "type": "Point",
        "coordinates": [
          -108.7167,
          31.3667
        ]
      },
      "type": "Feature",
      "properties": {
        "hierarchy": [
          "tgn:2622344",
          "tgn:1000001",
          "tgn:7012149",
          "tgn:2001440",
          "tgn:7007566",
          "tgn:7029392"
        ],
        "placetype": [
          "aat:300006191"
        ],
        "id": 2622344,
        "name:xx": "Robertson Tank"
      }
    },
    {
      "geometry": {
        "type": "Point",
        "coordinates": [
          -109.8833,
          31.7833
        ]
      },
      "type": "Feature",
      "properties": {
        "hierarchy": [
          "tgn:2622346",
          "tgn:1000001",
          "tgn:7006451",
          "tgn:2000091",
          "tgn:7012149",
          "tgn:7029392"
        ],
        "placetype": [
          "aat:300008699"
        ],
        "id": 2622346,
        "name:xx": "Robertson Wash"
      }
    },
    {
      "geometry": {
        "type": "Point",
        "coordinates": [
          -103.9167,
          33.6833
        ]
      },
      "type": "Feature",
      "properties": {
        "hierarchy": [
          "tgn:2622347",
          "tgn:1000001",
          "tgn:2001430",
          "tgn:7012149",
          "tgn:7007566",
          "tgn:7029392"
        ],
        "placetype": [
          "aat:300008347"
        ],
        "id": 2622347,
        "name:xx": "Robertson Wells"
      }
    },
    {
      "geometry": {
        "type": "Point",
        "coordinates": [
          -86.2167,
          33.5667
        ]
      },
      "type": "Feature",
      "properties": {
        "hierarchy": [
          "tgn:2622349",
          "tgn:7002659",
          "tgn:1000001",
          "tgn:7012149",
          "tgn:2000060",
          "tgn:7029392"
        ],
        "placetype": [
          "aat:300386851",
          "aat:300008791"
        ],
        "id": 2622349,
        "name:xx": "Robertsons Island"
      }
    }
  ]
}
