{
  "geometry": {
    "type": "Point",
    "coordinates": [
      -89.3833,
      31.6667
    ]
  },
  "type": "Feature",
  "properties": {
    "hierarchy": [
      "tgn:2649892",
      "tgn:1000001",
      "tgn:7012149",
      "tgn:2001119",
      "tgn:7007522",
      "tgn:7029392"
    ],
    "placetype": [
      "aat:300008680"
    ],
    "id": 2649892,
    "name:xx": "Scruggs Lake"
  }
}
