{
  "type": "FeatureCollection",
  "features": [
    {
      "geometry": {
        "type": "Point",
        "coordinates": [
          -106.8333,
          39.8667
        ]
      },
      "type": "Feature",
      "properties": {
        "hierarchy": [
          "tgn:2181550",
          "tgn:1000001",
          "tgn:7012149",
          "tgn:2000210",
          "tgn:7007158",
          "tgn:7029392"
        ],
        "placetype": [
          "aat:300008798"
        ],
        "id": 2181550,
        "name:xx": "Blue Hill"
      }
    },
    {
      "geometry": {
        "type": "Point",
        "coordinates": [
          -104.3167,
          37.7833
        ]
      },
      "type": "Feature",
      "properties": {
        "hierarchy": [
          "tgn:2181551",
          "tgn:1000001",
          "tgn:7012149",
          "tgn:2000227",
          "tgn:7007158",
          "tgn:7029392"
        ],
        "placetype": [
          "aat:300008798"
        ],
        "id": 2181551,
        "name:xx": "Blue Hill"
      }
    },
    {
      "geometry": {
        "type": "Point",
        "coordinates": [
          -72.1667,
          41.5833
        ]
      },
      "type": "Feature",
      "properties": {
        "hierarchy": [
          "tgn:2181552",
          "tgn:1000001",
          "tgn:1002714",
          "tgn:7012149",
          "tgn:7007159",
          "tgn:7029392"
        ],
        "placetype": [
          "aat:300008798"
        ],
        "id": 2181552,
        "name:xx": "Blue Hill"
      }
    },
    {
      "geometry": {
        "type": "Point",
        "coordinates": [
          -81.65,
          25.9
        ]
      },
      "type": "Feature",
      "properties": {
        "hierarchy": [
          "tgn:2181553",
          "tgn:1000001",
          "tgn:1002289",
          "tgn:7012149",
          "tgn:7007240",
          "tgn:7029392"
        ],
        "placetype": [
          "aat:300008798"
        ],
        "id": 2181553,
        "name:xx": "Blue Hill"
      }
    },
    {
      "geometry": {
        "type": "Point",
        "coordinates": [
          -113.9333,
          42.05
        ]
      },
      "type": "Feature",
      "properties": {
        "hierarchy": [
          "tgn:2181554",
          "tgn:1000001",
          "tgn:2000467",
          "tgn:7012149",
          "tgn:7007250",
          "tgn:7029392"
        ],
        "placetype": [
          "aat:300008798"
        ],
        "id": 2181554,
        "name:xx": "Blue Hill"
      }
    },
    {
      "geometry": {
        "type": "Point",
        "coordinates": [
          -98.35,
          39.3
        ]
      },
      "type": "Feature",
      "properties": {
        "hierarchy": [
          "tgn:2181555",
          "tgn:1000001",
          "tgn:7012149",
          "tgn:2000721",
          "tgn:7007254",
          "tgn:7029392"
        ],
        "placetype": [
          "aat:300008347"
        ],
        "id": 2181555,
        "name:xx": "Blue Hill"
      }
    },
    {
      "geometry": {
        "type": "Point",
        "coordinates": [
          -68.5833,
          44.4333
        ]
      },
      "type": "Feature",
      "properties": {
        "hierarchy": [
          "tgn:2181556",
          "tgn:1000001",
          "tgn:2000922",
          "tgn:7012149",
          "tgn:7007515",
          "tgn:7029392"
        ],
        "placetype": [
          "aat:300008798"
        ],
        "id": 2181556,
        "name:xx": "Blue Hill"
      }
    },
    {
      "geometry": {
        "type": "Point",
        "coordinates": [
          -93.7,
          45.4833
        ]
      },
      "type": "Feature",
      "properties": {
        "hierarchy": [
          "tgn:2181557",
          "tgn:1000001",
          "tgn:7012149",
          "tgn:2001069",
          "tgn:7007521",
          "tgn:7029392"
        ],
        "placetype": [
          "aat:300008798"
        ],
        "id": 2181557,
        "name:xx": "Blue Hill"
      }
    },
    {
      "geometry": {
        "type": "Point",
        "coordinates": [
          -90.85,
          31.75
        ]
      },
      "type": "Feature",
      "properties": {
        "hierarchy": [
          "tgn:2181558",
          "tgn:1000001",
          "tgn:7012149",
          "tgn:2001117",
          "tgn:7007522",
          "tgn:7029392"
        ],
        "placetype": [
          "aat:300008347"
        ],
        "id": 2181558,
        "name:xx": "Blue Hill"
      }
    },
    {
      "geometry": {
        "type": "Point",
        "coordinates": [
          -90.8833,
          31.75
        ]
      },
      "type": "Feature",
      "properties": {
        "hierarchy": [
          "tgn:2181559",
          "tgn:1000001",
          "tgn:7012149",
          "tgn:2001117",
          "tgn:7007522",
          "tgn:7029392"
        ],
        "placetype": [
          "aat:300008798"
        ],
        "id": 2181559,
        "name:xx": "Blue Hill"
      }
    }
  ]
}
