{
  "geometry": {
    "type": "Point",
    "coordinates": [
      -75.0667,
      42.2667
    ]
  },
  "type": "Feature",
  "properties": {
    "hierarchy": [
      "tgn:2757783",
      "tgn:1000001",
      "tgn:1002328",
      "tgn:7012149",
      "tgn:7007568",
      "tgn:7029392"
    ],
    "placetype": [
      "aat:300008699"
    ],
    "id": 2757783,
    "name:xx": "West Branch Handsome Brook"
  }
}
