{
  "geometry": {
    "type": "Point",
    "coordinates": [
      -120.5667,
      37.35
    ]
  },
  "type": "Feature",
  "properties": {
    "hierarchy": [
      "tgn:2270932",
      "tgn:1000001",
      "tgn:7012149",
      "tgn:7007157",
      "tgn:1002656",
      "tgn:7029392"
    ],
    "placetype": [
      "aat:300008347"
    ],
    "id": 2270932,
    "name:xx": "Cuba"
  }
}
