{
  "geometry": {
    "type": "Point",
    "coordinates": [
      -45.1833,
      -10.4833
    ]
  },
  "type": "Feature",
  "properties": {
    "hierarchy": [
      "tgn:1021245",
      "tgn:7006252",
      "tgn:1000047",
      "tgn:7002455",
      "tgn:1000002",
      "tgn:7029392"
    ],
    "placetype": [
      "aat:300008347"
    ],
    "id": 1021245,
    "name:xx": "Corrente"
  }
}
