{
  "geometry": {
    "type": "Point",
    "coordinates": [
      -102.9833,
      29.1833
    ]
  },
  "type": "Feature",
  "properties": {
    "hierarchy": [
      "tgn:2402770",
      "tgn:1000001",
      "tgn:2001945",
      "tgn:7012149",
      "tgn:7007826",
      "tgn:7029392"
    ],
    "placetype": [
      "aat:300008761"
    ],
    "id": 2402770,
    "name:xx": "Hot Springs Canyon"
  }
}
