{
  "type": "FeatureCollection",
  "features": [
    {
      "geometry": {
        "type": "Point",
        "coordinates": [
          -85.5,
          36.9667
        ]
      },
      "type": "Feature",
      "properties": {
        "hierarchy": [
          "tgn:2525680",
          "tgn:1000001",
          "tgn:7012149",
          "tgn:2000828",
          "tgn:7007255",
          "tgn:7029392"
        ],
        "placetype": [
          "aat:300266640"
        ],
        "id": 2525680,
        "name:xx": "Mosby Ridge"
      }
    },
    {
      "geometry": {
        "type": "Point",
        "coordinates": [
          -109.85,
          40.6167
        ]
      },
      "type": "Feature",
      "properties": {
        "hierarchy": [
          "tgn:2525681",
          "tgn:1000001",
          "tgn:7012149",
          "tgn:2002124",
          "tgn:7007827",
          "tgn:7029392"
        ],
        "placetype": [
          "aat:300386845"
        ],
        "id": 2525681,
        "name:xx": "Mosby Sink"
      }
    },
    {
      "geometry": {
        "type": "Point",
        "coordinates": [
          -107.7,
          34.5833
        ]
      },
      "type": "Feature",
      "properties": {
        "hierarchy": [
          "tgn:2525683",
          "tgn:1000001",
          "tgn:2001431",
          "tgn:7012149",
          "tgn:7007566",
          "tgn:7029392"
        ],
        "placetype": [
          "aat:300008761"
        ],
        "id": 2525683,
        "name:xx": "Mosca, Cañon de la"
      }
    },
    {
      "geometry": {
        "type": "Point",
        "coordinates": [
          -107.4,
          37.45
        ]
      },
      "type": "Feature",
      "properties": {
        "hierarchy": [
          "tgn:2525684",
          "tgn:1000001",
          "tgn:7012149",
          "tgn:7007158",
          "tgn:7029392"
        ],
        "placetype": [
          "aat:300008706"
        ],
        "id": 2525684,
        "name:xx": "Mosca Creek"
      }
    },
    {
      "geometry": {
        "type": "Point",
        "coordinates": [
          -105.45,
          37.7333
        ]
      },
      "type": "Feature",
      "properties": {
        "hierarchy": [
          "tgn:2525685",
          "tgn:2000193",
          "tgn:1000001",
          "tgn:7012149",
          "tgn:7007158",
          "tgn:7029392"
        ],
        "placetype": [
          "aat:300008706"
        ],
        "id": 2525685,
        "name:xx": "Mosca Creek"
      }
    },
    {
      "geometry": {
        "type": "Point",
        "coordinates": [
          -106.4,
          34.8
        ]
      },
      "type": "Feature",
      "properties": {
        "hierarchy": [
          "tgn:2525686",
          "tgn:1000001",
          "tgn:7012149",
          "tgn:2001458",
          "tgn:7007566",
          "tgn:7029392"
        ],
        "placetype": [
          "aat:300008798"
        ],
        "id": 2525686,
        "name:xx": "Mosca Peak"
      }
    },
    {
      "geometry": {
        "type": "Point",
        "coordinates": [
          -105.5,
          37.7333
        ]
      },
      "type": "Feature",
      "properties": {
        "hierarchy": [
          "tgn:2525687",
          "tgn:2000193",
          "tgn:1000001",
          "tgn:7012149",
          "tgn:7007158",
          "tgn:7029392"
        ],
        "placetype": [
          "aat:300008697"
        ],
        "id": 2525687,
        "name:xx": "Mosca Spring"
      }
    },
    {
      "geometry": {
        "type": "Point",
        "coordinates": [
          -111.4333,
          31.7167
        ]
      },
      "type": "Feature",
      "properties": {
        "hierarchy": [
          "tgn:2525688",
          "tgn:1000001",
          "tgn:7006451",
          "tgn:7012149",
          "tgn:2000100",
          "tgn:7029392"
        ],
        "placetype": [
          "aat:300006191"
        ],
        "id": 2525688,
        "name:xx": "Mosca Tank"
      }
    },
    {
      "geometry": {
        "type": "Point",
        "coordinates": [
          -107.6833,
          34.6167
        ]
      },
      "type": "Feature",
      "properties": {
        "hierarchy": [
          "tgn:2525689",
          "tgn:1000001",
          "tgn:2001431",
          "tgn:7012149",
          "tgn:7007566",
          "tgn:7029392"
        ],
        "placetype": [
          "aat:300008697"
        ],
        "id": 2525689,
        "name:xx": "Mosca, Ojo de la"
      }
    }
  ]
}
