{
  "geometry": {
    "type": "Point",
    "coordinates": [
      -115.55,
      34.8667
    ]
  },
  "type": "Feature",
  "properties": {
    "hierarchy": [
      "tgn:2777765",
      "tgn:1000001",
      "tgn:7012149",
      "tgn:7007157",
      "tgn:1002857",
      "tgn:7029392"
    ],
    "placetype": [
      "aat:300008699"
    ],
    "id": 2777765,
    "name:xx": "Winston Wash"
  }
}
