{
  "geometry": {
    "type": "Point",
    "coordinates": [
      -98.3167,
      30.4667
    ]
  },
  "type": "Feature",
  "properties": {
    "hierarchy": [
      "tgn:2533620",
      "tgn:1000001",
      "tgn:2001942",
      "tgn:7012149",
      "tgn:7007826",
      "tgn:7029392"
    ],
    "placetype": [
      "aat:300008680"
    ],
    "id": 2533620,
    "name:xx": "Mustang Lake"
  }
}
