{
  "geometry": {
    "type": "Point",
    "coordinates": [
      -113.5667,
      45.15
    ]
  },
  "type": "Feature",
  "properties": {
    "hierarchy": [
      "tgn:2275977",
      "tgn:1000001",
      "tgn:7012149",
      "tgn:7029392"
    ],
    "placetype": [
      "aat:300008680"
    ],
    "id": 2275977,
    "name:xx": "Darkhorse Lake"
  }
}
