{
  "geometry": {
    "type": "Point",
    "coordinates": [
      -73.7667,
      40.8167
    ]
  },
  "type": "Feature",
  "properties": {
    "hierarchy": [
      "tgn:2693762",
      "tgn:1000001",
      "tgn:7012149",
      "tgn:1002708",
      "tgn:7007568",
      "tgn:7029392"
    ],
    "placetype": [
      "aat:300132348"
    ],
    "id": 2693762,
    "name:xx": "Stepping Stones"
  }
}
