{
  "geometry": {
    "type": "Point",
    "coordinates": [
      -158.8333,
      55.9167
    ]
  },
  "type": "Feature",
  "properties": {
    "hierarchy": [
      "tgn:2197090",
      "tgn:7006450",
      "tgn:1000001",
      "tgn:7030517",
      "tgn:7012149",
      "tgn:7029392"
    ],
    "placetype": [
      "aat:300386853"
    ],
    "id": 2197090,
    "name:xx": "Brother Islands"
  }
}
