{
  "type": "FeatureCollection",
  "features": [
    {
      "geometry": {
        "type": "Point",
        "coordinates": [
          -104.8,
          30.3
        ]
      },
      "type": "Feature",
      "properties": {
        "hierarchy": [
          "tgn:7353290",
          "tgn:7005581",
          "tgn:1000001",
          "tgn:7005560",
          "tgn:7029392"
        ],
        "placetype": [
          "aat:300008347"
        ],
        "id": 7353290,
        "name:xx": "Buenavista"
      }
    },
    {
      "geometry": {
        "type": "Point",
        "coordinates": [
          -109.333333,
          29.866667
        ]
      },
      "type": "Feature",
      "properties": {
        "hierarchy": [
          "tgn:7353291",
          "tgn:1000001",
          "tgn:1001960",
          "tgn:7005560",
          "tgn:7029392"
        ],
        "placetype": [
          "aat:300008347"
        ],
        "id": 7353291,
        "name:xx": "Buenavista"
      }
    },
    {
      "geometry": {
        "type": "Point",
        "coordinates": [
          -104.55,
          29.7
        ]
      },
      "type": "Feature",
      "properties": {
        "hierarchy": [
          "tgn:7353292",
          "tgn:7005581",
          "tgn:1000001",
          "tgn:7005560",
          "tgn:7029392"
        ],
        "placetype": [
          "aat:300008347"
        ],
        "id": 7353292,
        "name:xx": "Buenavista"
      }
    },
    {
      "geometry": {
        "type": "Point",
        "coordinates": [
          -108.983333,
          29.616667
        ]
      },
      "type": "Feature",
      "properties": {
        "hierarchy": [
          "tgn:7353293",
          "tgn:1000001",
          "tgn:1001960",
          "tgn:7005560",
          "tgn:7029392"
        ],
        "placetype": [
          "aat:300008347"
        ],
        "id": 7353293,
        "name:xx": "Buena Vista"
      }
    },
    {
      "geometry": {
        "type": "Point",
        "coordinates": [
          -107.283333,
          28.85
        ]
      },
      "type": "Feature",
      "properties": {
        "hierarchy": [
          "tgn:7353294",
          "tgn:7005581",
          "tgn:1000001",
          "tgn:7005560",
          "tgn:7029392"
        ],
        "placetype": [
          "aat:300008347"
        ],
        "id": 7353294,
        "name:xx": "Buena Vista"
      }
    },
    {
      "geometry": {
        "type": "Point",
        "coordinates": [
          -105.6,
          28.666667
        ]
      },
      "type": "Feature",
      "properties": {
        "hierarchy": [
          "tgn:7353295",
          "tgn:7005581",
          "tgn:1000001",
          "tgn:7005560",
          "tgn:7029392"
        ],
        "placetype": [
          "aat:300008347"
        ],
        "id": 7353295,
        "name:xx": "Buena Vista"
      }
    },
    {
      "geometry": {
        "type": "Point",
        "coordinates": [
          -101.75,
          28.033333
        ]
      },
      "type": "Feature",
      "properties": {
        "hierarchy": [
          "tgn:7353296",
          "tgn:1001853",
          "tgn:1000001",
          "tgn:7005560",
          "tgn:7029392"
        ],
        "placetype": [
          "aat:300008347"
        ],
        "id": 7353296,
        "name:xx": "Buenavista"
      }
    },
    {
      "geometry": {
        "type": "Point",
        "coordinates": [
          -106.133333,
          28
        ]
      },
      "type": "Feature",
      "properties": {
        "hierarchy": [
          "tgn:7353297",
          "tgn:7005581",
          "tgn:1000001",
          "tgn:7005560",
          "tgn:7029392"
        ],
        "placetype": [
          "aat:300008347"
        ],
        "id": 7353297,
        "name:xx": "Buena Vista"
      }
    },
    {
      "geometry": {
        "type": "Point",
        "coordinates": [
          -109.9,
          27.783333
        ]
      },
      "type": "Feature",
      "properties": {
        "hierarchy": [
          "tgn:7353298",
          "tgn:1000001",
          "tgn:1001960",
          "tgn:7005560",
          "tgn:7029392"
        ],
        "placetype": [
          "aat:300008347"
        ],
        "id": 7353298,
        "name:xx": "Buenavista"
      }
    }
  ]
}
