{
  "type": "FeatureCollection",
  "features": [
    {
      "geometry": {
        "type": "Point",
        "coordinates": [
          -71.4,
          -32.316667
        ]
      },
      "type": "Feature",
      "properties": {
        "hierarchy": [
          "tgn:7281770",
          "tgn:1001768",
          "tgn:1000049",
          "tgn:1000002",
          "tgn:7029392"
        ],
        "placetype": [
          "aat:300387200"
        ],
        "id": 7281770,
        "name:xx": "San Ramón"
      }
    },
    {
      "geometry": {
        "type": "Point",
        "coordinates": [
          -71.8,
          -36
        ]
      },
      "type": "Feature",
      "properties": {
        "hierarchy": [
          "tgn:7281771",
          "tgn:1001705",
          "tgn:1000049",
          "tgn:1000002",
          "tgn:7029392"
        ],
        "placetype": [
          "aat:300000206"
        ],
        "id": 7281771,
        "name:xx": "San Ramón"
      }
    },
    {
      "geometry": {
        "type": "Point",
        "coordinates": [
          -71.65,
          -35.166667
        ]
      },
      "type": "Feature",
      "properties": {
        "hierarchy": [
          "tgn:7281772",
          "tgn:1001705",
          "tgn:1000049",
          "tgn:1000002",
          "tgn:7029392"
        ],
        "placetype": [
          "aat:300000206"
        ],
        "id": 7281772,
        "name:xx": "San Ramón"
      }
    },
    {
      "geometry": {
        "type": "Point",
        "coordinates": [
          -71.233333,
          -34.75
        ]
      },
      "type": "Feature",
      "properties": {
        "hierarchy": [
          "tgn:7281773",
          "tgn:1001695",
          "tgn:1000049",
          "tgn:1000002",
          "tgn:7029392"
        ],
        "placetype": [
          "aat:300000206"
        ],
        "id": 7281773,
        "name:xx": "San Ramón"
      }
    },
    {
      "geometry": {
        "type": "Point",
        "coordinates": [
          -71.533333,
          -34.166667
        ]
      },
      "type": "Feature",
      "properties": {
        "hierarchy": [
          "tgn:7281775",
          "tgn:1001708",
          "tgn:1000049",
          "tgn:1000002",
          "tgn:7029392"
        ],
        "placetype": [
          "aat:300008805"
        ],
        "id": 7281775,
        "name:xx": "San Rafael, Llano"
      }
    },
    {
      "geometry": {
        "type": "Point",
        "coordinates": [
          -70.933333,
          -34.483333
        ]
      },
      "type": "Feature",
      "properties": {
        "hierarchy": [
          "tgn:7281777",
          "tgn:1001695",
          "tgn:1000049",
          "tgn:1000002",
          "tgn:7029392"
        ],
        "placetype": [
          "aat:300008795"
        ],
        "id": 7281777,
        "name:xx": "San Rafael, Cerro"
      }
    },
    {
      "geometry": {
        "type": "Point",
        "coordinates": [
          -71.5,
          -34.233333
        ]
      },
      "type": "Feature",
      "properties": {
        "hierarchy": [
          "tgn:7281778",
          "tgn:1001695",
          "tgn:1000049",
          "tgn:1000002",
          "tgn:7029392"
        ],
        "placetype": [
          "aat:300008777"
        ],
        "id": 7281778,
        "name:xx": "San Rafael, Cerro"
      }
    },
    {
      "geometry": {
        "type": "Point",
        "coordinates": [
          -73.916667,
          -46.55
        ]
      },
      "type": "Feature",
      "properties": {
        "hierarchy": [
          "tgn:7281779",
          "tgn:1001623",
          "tgn:1000049",
          "tgn:1000002",
          "tgn:7029392"
        ],
        "placetype": [
          "aat:300132316"
        ],
        "id": 7281779,
        "name:xx": "San Rafael, Bahía"
      }
    }
  ]
}
