{
  "geometry": {
    "type": "Point",
    "coordinates": [
      -98.5167,
      28.6667
    ]
  },
  "type": "Feature",
  "properties": {
    "hierarchy": [
      "tgn:2606870",
      "tgn:1000001",
      "tgn:2001936",
      "tgn:7012149",
      "tgn:7007826",
      "tgn:7029392"
    ],
    "placetype": [
      "aat:300006191"
    ],
    "id": 2606870,
    "name:xx": "Ramsey Tank"
  }
}
