{
  "geometry": {
    "type": "Point",
    "coordinates": [
      -82.5833,
      36.7833
    ]
  },
  "type": "Feature",
  "properties": {
    "hierarchy": [
      "tgn:2194094",
      "tgn:1000001",
      "tgn:7012149",
      "tgn:2002189",
      "tgn:7007919",
      "tgn:7029392"
    ],
    "placetype": [
      "aat:300008697"
    ],
    "id": 2194094,
    "name:xx": "Brickey Spring"
  }
}
