{
  "geometry": {
    "type": "Point",
    "coordinates": [
      -112.4167,
      34.6833
    ]
  },
  "type": "Feature",
  "properties": {
    "hierarchy": [
      "tgn:2237736",
      "tgn:1000001",
      "tgn:7006451",
      "tgn:7012149",
      "tgn:2000103",
      "tgn:7029392"
    ],
    "placetype": [
      "aat:300006075"
    ],
    "id": 2237736,
    "name:xx": "Chino Valley Irrigation Ditch"
  }
}
