{
  "geometry": {
    "type": "Point",
    "coordinates": [
      -2.0333,
      51.7167
    ]
  },
  "type": "Feature",
  "properties": {
    "hierarchy": [
      "tgn:7026699",
      "tgn:7002445",
      "tgn:1000003",
      "tgn:7008132",
      "tgn:7008591",
      "tgn:7029392"
    ],
    "placetype": [
      "aat:300008863"
    ],
    "id": 7026699,
    "name:xx": "Oakley Wood"
  }
}
