{
  "geometry": {
    "type": "Point",
    "coordinates": [
      74.851951,
      27.053585
    ]
  },
  "type": "Feature",
  "properties": {
    "hierarchy": [
      "tgn:7577368",
      "tgn:1000004",
      "tgn:7000198",
      "tgn:7016788",
      "tgn:7029392"
    ],
    "placetype": [
      "aat:300007783"
    ],
    "name:en": "Kuchāman City Railroad Station",
    "id": 7577368
  }
}
