{
  "geometry": {
    "type": "Point",
    "coordinates": [
      -104.7333,
      30.4833
    ]
  },
  "type": "Feature",
  "properties": {
    "hierarchy": [
      "tgn:2352383",
      "tgn:1000001",
      "tgn:7012149",
      "tgn:2002057",
      "tgn:7007826",
      "tgn:7029392"
    ],
    "placetype": [
      "aat:300006191"
    ],
    "id": 2352383,
    "name:xx": "Goat Herd Tank"
  }
}
