{
  "geometry": {
    "type": "Point",
    "coordinates": [
      -85.85,
      45.2833
    ]
  },
  "type": "Feature",
  "properties": {
    "hierarchy": [
      "tgn:7023357",
      "tgn:1000001",
      "tgn:7012149",
      "tgn:7007520",
      "tgn:7029392"
    ],
    "placetype": [
      "aat:300132348"
    ],
    "id": 7023357,
    "name:xx": "South Fox Island Shoals"
  }
}
