{
  "geometry": {
    "type": "Point",
    "coordinates": [
      2.3833,
      49.0167
    ]
  },
  "type": "Feature",
  "properties": {
    "hierarchy": [
      "tgn:1100220",
      "tgn:1000003",
      "tgn:7002883",
      "tgn:1000070",
      "tgn:7029392"
    ],
    "placetype": [
      "aat:300006891"
    ],
    "id": 1100220,
    "name:xx": "Écouen, Château d'"
  }
}
