{
  "geometry": {
    "type": "Point",
    "coordinates": [
      -77.35,
      40.4833
    ]
  },
  "type": "Feature",
  "properties": {
    "hierarchy": [
      "tgn:2734573",
      "tgn:1000001",
      "tgn:7012149",
      "tgn:7007710",
      "tgn:7029392"
    ],
    "placetype": [
      "aat:300055621"
    ],
    "id": 2734573,
    "name:xx": "Tuscarora Wild Area"
  }
}
