{
  "geometry": {
    "type": "Point",
    "coordinates": [
      -87.1333,
      36.25
    ]
  },
  "type": "Feature",
  "properties": {
    "hierarchy": [
      "tgn:2451994",
      "tgn:1000001",
      "tgn:7012149",
      "tgn:2001847",
      "tgn:7007825",
      "tgn:7029392"
    ],
    "placetype": [
      "aat:300008706"
    ],
    "id": 2451994,
    "name:xx": "Little Bethany Creek"
  }
}
