{
  "geometry": {
    "type": "Point",
    "coordinates": [
      -71.35,
      -54.75
    ]
  },
  "type": "Feature",
  "properties": {
    "hierarchy": [
      "tgn:7310695",
      "tgn:1001702",
      "tgn:1000049",
      "tgn:1000002",
      "tgn:7029392"
    ],
    "placetype": [
      "aat:300008791"
    ],
    "id": 7310695,
    "name:xx": "Morritos, Islote"
  }
}
