{
  "geometry": {
    "type": "Point",
    "coordinates": [
      -99.0333,
      30.4833
    ]
  },
  "type": "Feature",
  "properties": {
    "hierarchy": [
      "tgn:2348147",
      "tgn:1000001",
      "tgn:7012149",
      "tgn:7007826",
      "tgn:7029392"
    ],
    "placetype": [
      "aat:300008706"
    ],
    "id": 2348147,
    "name:xx": "Gersdorf Creek"
  }
}
