{
  "geometry": {
    "type": "Point",
    "coordinates": [
      -92.1667,
      35.5333
    ]
  },
  "type": "Feature",
  "properties": {
    "hierarchy": [
      "tgn:2407742",
      "tgn:1000001",
      "tgn:7016172",
      "tgn:2000116",
      "tgn:7012149",
      "tgn:7029392"
    ],
    "placetype": [
      "aat:300132316"
    ],
    "id": 2407742,
    "name:xx": "Hurricane Bay"
  }
}
