{
  "type": "FeatureCollection",
  "features": [
    {
      "geometry": {
        "type": "Point",
        "coordinates": [
          12.35,
          43.75
        ]
      },
      "type": "Feature",
      "properties": {
        "hierarchy": [
          "tgn:5002670",
          "tgn:1003483",
          "tgn:1000003",
          "tgn:7003240",
          "tgn:1000080",
          "tgn:7029392"
        ],
        "placetype": [
          "aat:300000635",
          "aat:300000641"
        ],
        "id": 5002670,
        "name:xx": "Montefiorentino"
      }
    },
    {
      "geometry": {
        "type": "Point",
        "coordinates": [
          12.416667,
          43.716667
        ]
      },
      "type": "Feature",
      "properties": {
        "hierarchy": [
          "tgn:5002673",
          "tgn:1003483",
          "tgn:1000003",
          "tgn:7003240",
          "tgn:1000080",
          "tgn:7029392"
        ],
        "placetype": [
          "aat:300008347"
        ],
        "id": 5002673,
        "name:xx": "Piandimeleto"
      }
    },
    {
      "geometry": {
        "type": "Point",
        "coordinates": [
          12.283333,
          43.9
        ]
      },
      "type": "Feature",
      "properties": {
        "hierarchy": [
          "tgn:5002677",
          "tgn:1003483",
          "tgn:1000003",
          "tgn:7003240",
          "tgn:1000080",
          "tgn:7029392"
        ],
        "placetype": [
          "aat:300008347"
        ],
        "id": 5002677,
        "name:xx": "Talamello"
      }
    }
  ]
}
