{
  "geometry": {
    "type": "Point",
    "coordinates": [
      -72.9667,
      42.7333
    ]
  },
  "type": "Feature",
  "properties": {
    "hierarchy": [
      "tgn:2776871",
      "tgn:7013388",
      "tgn:1000001",
      "tgn:7012149",
      "tgn:7007517",
      "tgn:7029392"
    ],
    "placetype": [
      "aat:300008680"
    ],
    "id": 2776871,
    "name:xx": "Windsor Pond"
  }
}
