{
  "geometry": {
    "type": "Point",
    "coordinates": [
      79.481444,
      27.819425
    ]
  },
  "type": "Feature",
  "properties": {
    "hierarchy": [
      "tgn:7559715",
      "tgn:1000004",
      "tgn:7000198",
      "tgn:7016722",
      "tgn:7029392"
    ],
    "placetype": [
      "aat:300008347"
    ],
    "name:en": "Golāganj",
    "id": 7559715
  }
}
