{
  "geometry": {
    "type": "Point",
    "coordinates": [
      -92.4167,
      41.0167
    ]
  },
  "type": "Feature",
  "properties": {
    "hierarchy": [
      "tgn:2733017",
      "tgn:1000001",
      "tgn:7012149",
      "tgn:2000650",
      "tgn:7007253",
      "tgn:7029392"
    ],
    "placetype": [
      "aat:300008791"
    ],
    "id": 2733017,
    "name:xx": "Turkey Island"
  }
}
