{
  "geometry": {
    "type": "Point",
    "coordinates": [
      -109.75,
      27.55
    ]
  },
  "type": "Feature",
  "properties": {
    "hierarchy": [
      "tgn:7393026",
      "tgn:1000001",
      "tgn:1001960",
      "tgn:7005560",
      "tgn:7029392"
    ],
    "placetype": [
      "aat:300000241"
    ],
    "id": 7393026,
    "name:xx": "Rancho San Joaquín"
  }
}
