{
  "geometry": {
    "type": "Point",
    "coordinates": [
      -92.9333,
      36.8833
    ]
  },
  "type": "Feature",
  "properties": {
    "hierarchy": [
      "tgn:2241214",
      "tgn:1000001",
      "tgn:2001185",
      "tgn:7012149",
      "tgn:7007523",
      "tgn:7029392"
    ],
    "placetype": [
      "aat:300008761"
    ],
    "id": 2241214,
    "name:xx": "Clark Hollow"
  }
}
