{
  "geometry": {
    "type": "Point",
    "coordinates": [
      -111.0333,
      41.95
    ]
  },
  "type": "Feature",
  "properties": {
    "hierarchy": [
      "tgn:2611283",
      "tgn:1000001",
      "tgn:7012149",
      "tgn:7029392"
    ],
    "placetype": [
      "aat:300008798"
    ],
    "id": 2611283,
    "name:xx": "Red Knoll"
  }
}
