{
  "geometry": {
    "type": "Point",
    "coordinates": [
      -97.1833,
      28.0167
    ]
  },
  "type": "Feature",
  "properties": {
    "hierarchy": [
      "tgn:2340725",
      "tgn:7013313",
      "tgn:1000001",
      "tgn:7012149",
      "tgn:7007826",
      "tgn:7029392"
    ],
    "placetype": [
      "aat:300008680"
    ],
    "id": 2340725,
    "name:xx": "Fresh Water Lake"
  }
}
