{
  "type": "FeatureCollection",
  "features": [
    {
      "geometry": {
        "type": "Point",
        "coordinates": [
          -73.7833,
          41.4167
        ]
      },
      "type": "Feature",
      "properties": {
        "hierarchy": [
          "tgn:2523460",
          "tgn:1000001",
          "tgn:7012149",
          "tgn:1002810",
          "tgn:7007568",
          "tgn:7029392"
        ],
        "placetype": [
          "aat:300008798"
        ],
        "id": 2523460,
        "name:xx": "Moose Hill"
      }
    },
    {
      "geometry": {
        "type": "Point",
        "coordinates": [
          -79.05,
          40.5667
        ]
      },
      "type": "Feature",
      "properties": {
        "hierarchy": [
          "tgn:2523461",
          "tgn:1000001",
          "tgn:7012149",
          "tgn:1002501",
          "tgn:7007710",
          "tgn:7029392"
        ],
        "placetype": [
          "aat:300008798"
        ],
        "id": 2523461,
        "name:xx": "Moose Hill"
      }
    },
    {
      "geometry": {
        "type": "Point",
        "coordinates": [
          -70.1333,
          44.45
        ]
      },
      "type": "Feature",
      "properties": {
        "hierarchy": [
          "tgn:2523462",
          "tgn:2000918",
          "tgn:1000001",
          "tgn:7012149",
          "tgn:7007515",
          "tgn:7029392"
        ],
        "placetype": [
          "aat:300008680"
        ],
        "id": 2523462,
        "name:xx": "Moose Hill Pond"
      }
    },
    {
      "geometry": {
        "type": "Point",
        "coordinates": [
          -92.6,
          46.6667
        ]
      },
      "type": "Feature",
      "properties": {
        "hierarchy": [
          "tgn:2523464",
          "tgn:1000001",
          "tgn:2001007",
          "tgn:7012149",
          "tgn:7007521",
          "tgn:7029392"
        ],
        "placetype": [
          "aat:300008707"
        ],
        "id": 2523464,
        "name:xx": "Moose Horn River"
      }
    },
    {
      "geometry": {
        "type": "Point",
        "coordinates": [
          -152.3167,
          63.85
        ]
      },
      "type": "Feature",
      "properties": {
        "hierarchy": [
          "tgn:2523465",
          "tgn:7006450",
          "tgn:1000001",
          "tgn:7012149",
          "tgn:2000089",
          "tgn:7029392"
        ],
        "placetype": [
          "aat:300008791"
        ],
        "id": 2523465,
        "name:xx": "Moose Island"
      }
    },
    {
      "geometry": {
        "type": "Point",
        "coordinates": [
          -88.2167,
          41.4
        ]
      },
      "type": "Feature",
      "properties": {
        "hierarchy": [
          "tgn:2523466",
          "tgn:1000001",
          "tgn:7012149",
          "tgn:1003024",
          "tgn:7007251",
          "tgn:7029392"
        ],
        "placetype": [
          "aat:300008791"
        ],
        "id": 2523466,
        "name:xx": "Moose Island"
      }
    },
    {
      "geometry": {
        "type": "Point",
        "coordinates": [
          -68.6833,
          44.1333
        ]
      },
      "type": "Feature",
      "properties": {
        "hierarchy": [
          "tgn:2523467",
          "tgn:1000001",
          "tgn:2000922",
          "tgn:7012149",
          "tgn:7007515",
          "tgn:7029392"
        ],
        "placetype": [
          "aat:300008791"
        ],
        "id": 2523467,
        "name:xx": "Moose Island"
      }
    },
    {
      "geometry": {
        "type": "Point",
        "coordinates": [
          -68.7667,
          44.9
        ]
      },
      "type": "Feature",
      "properties": {
        "hierarchy": [
          "tgn:2523468",
          "tgn:1000001",
          "tgn:7012149",
          "tgn:2000927",
          "tgn:7007515",
          "tgn:7029392"
        ],
        "placetype": [
          "aat:300008791"
        ],
        "id": 2523468,
        "name:xx": "Moose Island"
      }
    },
    {
      "geometry": {
        "type": "Point",
        "coordinates": [
          -68.95,
          45.7167
        ]
      },
      "type": "Feature",
      "properties": {
        "hierarchy": [
          "tgn:2523469",
          "tgn:1000001",
          "tgn:7012149",
          "tgn:2000928",
          "tgn:7007515",
          "tgn:7029392"
        ],
        "placetype": [
          "aat:300008791"
        ],
        "id": 2523469,
        "name:xx": "Moose Island"
      }
    }
  ]
}
