{
  "geometry": {
    "type": "Point",
    "coordinates": [
      13.2667,
      -20.4667
    ]
  },
  "type": "Feature",
  "properties": {
    "hierarchy": [
      "tgn:1012275",
      "tgn:7001242",
      "tgn:7030587",
      "tgn:1000198",
      "tgn:7029392"
    ],
    "placetype": [
      "aat:300386846"
    ],
    "id": 1012275,
    "name:xx": "Palgrave Point"
  }
}
