{
  "geometry": {
    "type": "Point",
    "coordinates": [
      -81.7667,
      28.4833
    ]
  },
  "type": "Feature",
  "properties": {
    "hierarchy": [
      "tgn:2457210",
      "tgn:1000001",
      "tgn:7012149",
      "tgn:1002567",
      "tgn:7007240",
      "tgn:7029392"
    ],
    "placetype": [
      "aat:300008680"
    ],
    "id": 2457210,
    "name:xx": "Little Lake Nellie"
  }
}
