{
  "geometry": {
    "type": "Point",
    "coordinates": [
      -85.2333,
      46.6333
    ]
  },
  "type": "Feature",
  "properties": {
    "hierarchy": [
      "tgn:2657992",
      "tgn:1000001",
      "tgn:2000952",
      "tgn:7012149",
      "tgn:7007520",
      "tgn:7029392"
    ],
    "placetype": [
      "aat:300008707"
    ],
    "id": 2657992,
    "name:xx": "Shelldrake River"
  }
}
