{
  "geometry": {
    "type": "Point",
    "coordinates": [
      -91.3167,
      43.3667
    ]
  },
  "type": "Feature",
  "properties": {
    "hierarchy": [
      "tgn:2241076",
      "tgn:2000563",
      "tgn:1000001",
      "tgn:7012149",
      "tgn:7007253",
      "tgn:7029392"
    ],
    "placetype": [
      "aat:300008706"
    ],
    "id": 2241076,
    "name:xx": "Clark Creek"
  }
}
