{
  "geometry": {
    "type": "Point",
    "coordinates": [
      -113.9333,
      37.3167
    ]
  },
  "type": "Feature",
  "properties": {
    "hierarchy": [
      "tgn:2163673",
      "tgn:1000001",
      "tgn:7012149",
      "tgn:2002127",
      "tgn:7007827",
      "tgn:7029392"
    ],
    "placetype": [
      "aat:300008761"
    ],
    "id": 2163673,
    "name:xx": "Bentley Wash"
  }
}
