{
  "geometry": {
    "type": "Point",
    "coordinates": [
      -81.4833,
      35.9167
    ]
  },
  "type": "Feature",
  "properties": {
    "hierarchy": [
      "tgn:2387713",
      "tgn:1000001",
      "tgn:2001476",
      "tgn:7012149",
      "tgn:7007709",
      "tgn:7029392"
    ],
    "placetype": [
      "aat:300008347"
    ],
    "id": 2387713,
    "name:xx": "Hibriten"
  }
}
