{
  "geometry": {
    "type": "Point",
    "coordinates": [
      -7.4833,
      7.0167
    ]
  },
  "type": "Feature",
  "properties": {
    "hierarchy": [
      "tgn:1090314",
      "tgn:7001242",
      "tgn:7018266",
      "tgn:1000168",
      "tgn:7029392"
    ],
    "placetype": [
      "aat:300008347"
    ],
    "id": 1090314,
    "name:xx": "Bangolo"
  }
}
