{
  "type": "FeatureCollection",
  "features": [
    {
      "geometry": {
        "type": "Point",
        "coordinates": [
          2.1833,
          42.4167
        ]
      },
      "type": "Feature",
      "properties": {
        "hierarchy": [
          "tgn:1035020",
          "tgn:1000003",
          "tgn:7002885",
          "tgn:1000070",
          "tgn:7029392"
        ],
        "placetype": [
          "aat:300008347"
        ],
        "id": 1035020,
        "name:xx": "Quillan"
      }
    },
    {
      "geometry": {
        "type": "Point",
        "coordinates": [
          1.1833,
          49.5167
        ]
      },
      "type": "Feature",
      "properties": {
        "hierarchy": [
          "tgn:1035024",
          "tgn:1000003",
          "tgn:7002882",
          "tgn:1000070",
          "tgn:7029392"
        ],
        "placetype": [
          "aat:300008347"
        ],
        "id": 1035024,
        "name:xx": "Quincampoix"
      }
    },
    {
      "geometry": {
        "type": "Point",
        "coordinates": [
          2.8833,
          48.9
        ]
      },
      "type": "Feature",
      "properties": {
        "hierarchy": [
          "tgn:1035025",
          "tgn:1000003",
          "tgn:7002883",
          "tgn:1000070",
          "tgn:7029392"
        ],
        "placetype": [
          "aat:300008347"
        ],
        "id": 1035025,
        "name:xx": "Quincy-Voisins"
      }
    },
    {
      "geometry": {
        "type": "Point",
        "coordinates": [
          2.5333,
          48.6667
        ]
      },
      "type": "Feature",
      "properties": {
        "hierarchy": [
          "tgn:1035026",
          "tgn:1000003",
          "tgn:7002883",
          "tgn:1000070",
          "tgn:7029392"
        ],
        "placetype": [
          "aat:300008347"
        ],
        "id": 1035026,
        "name:xx": "Quincy-sous-Sénart"
      }
    },
    {
      "geometry": {
        "type": "Point",
        "coordinates": [
          5.8833,
          47.1
        ]
      },
      "type": "Feature",
      "properties": {
        "hierarchy": [
          "tgn:1035027",
          "tgn:1000003",
          "tgn:7002881",
          "tgn:1000070",
          "tgn:7029392"
        ],
        "placetype": [
          "aat:300008347"
        ],
        "id": 1035027,
        "name:xx": "Quingey"
      }
    },
    {
      "geometry": {
        "type": "Point",
        "coordinates": [
          6.05,
          43.7
        ]
      },
      "type": "Feature",
      "properties": {
        "hierarchy": [
          "tgn:1035028",
          "tgn:1000003",
          "tgn:1000070",
          "tgn:7002895",
          "tgn:7029392"
        ],
        "placetype": [
          "aat:300008347"
        ],
        "id": 1035028,
        "name:xx": "Quinson"
      }
    },
    {
      "geometry": {
        "type": "Point",
        "coordinates": [
          -2.9167,
          48.4
        ]
      },
      "type": "Feature",
      "properties": {
        "hierarchy": [
          "tgn:1035029",
          "tgn:1000003",
          "tgn:7012216",
          "tgn:1000070",
          "tgn:7029392"
        ],
        "placetype": [
          "aat:300008347"
        ],
        "id": 1035029,
        "name:xx": "Quintin"
      }
    }
  ]
}
