{
  "geometry": {
    "type": "Point",
    "coordinates": [
      -64.0833,
      -10.4833
    ]
  },
  "type": "Feature",
  "properties": {
    "hierarchy": [
      "tgn:1135712",
      "tgn:1001944",
      "tgn:1000047",
      "tgn:7002456",
      "tgn:1000002",
      "tgn:7029392"
    ],
    "placetype": [
      "aat:300008736"
    ],
    "id": 1135712,
    "name:xx": "Tracajá, Cachoeira"
  }
}
