{
  "geometry": {
    "type": "Point",
    "coordinates": [
      -98.2833,
      34.7667
    ]
  },
  "type": "Feature",
  "properties": {
    "hierarchy": [
      "tgn:2550169",
      "tgn:1000001",
      "tgn:2001638",
      "tgn:7012149",
      "tgn:7007707",
      "tgn:7029392"
    ],
    "placetype": [
      "aat:300008680"
    ],
    "id": 2550169,
    "name:xx": "Northeast Pond"
  }
}
