{
  "geometry": {
    "type": "Point",
    "coordinates": [
      -96.35,
      33.15
    ]
  },
  "type": "Feature",
  "properties": {
    "hierarchy": [
      "tgn:2548342",
      "tgn:1000001",
      "tgn:7012149",
      "tgn:1002290",
      "tgn:7007826",
      "tgn:7029392"
    ],
    "placetype": [
      "aat:300006191"
    ],
    "id": 2548342,
    "name:xx": "North Lake"
  }
}
