{
  "geometry": {
    "type": "Point",
    "coordinates": [
      120.8667,
      41.3833
    ]
  },
  "type": "Feature",
  "properties": {
    "hierarchy": [
      "tgn:1070090",
      "tgn:1000004",
      "tgn:1001390",
      "tgn:1000111",
      "tgn:7029392"
    ],
    "placetype": [
      "aat:300008347"
    ],
    "id": 1070090,
    "name:xx": "Longqiantai"
  }
}
