{
  "type": "FeatureCollection",
  "features": [
    {
      "geometry": {
        "type": "Point",
        "coordinates": [
          31.085619,
          30.102501
        ]
      },
      "type": "Feature",
      "properties": {
        "hierarchy": [
          "tgn:7541060",
          "tgn:7001242",
          "tgn:7016833",
          "tgn:1001083",
          "tgn:7029392"
        ],
        "placetype": [
          "aat:300008347"
        ],
        "id": 7541060,
        "name:xx": "'Izbat Māhir"
      }
    },
    {
      "geometry": {
        "type": "Point",
        "coordinates": [
          31.069029,
          30.09799
        ]
      },
      "type": "Feature",
      "properties": {
        "hierarchy": [
          "tgn:7541061",
          "tgn:7001242",
          "tgn:7016833",
          "tgn:7029392"
        ],
        "placetype": [
          "aat:300006075"
        ],
        "id": 7541061,
        "name:xx": "Tur'at Kafr Ḩakīm"
      }
    },
    {
      "geometry": {
        "type": "Point",
        "coordinates": [
          30.086389,
          30.086389
        ]
      },
      "type": "Feature",
      "properties": {
        "hierarchy": [
          "tgn:7541062",
          "tgn:7001242",
          "tgn:7016833",
          "tgn:1001083",
          "tgn:7029392"
        ],
        "placetype": [
          "aat:300008347"
        ],
        "name:en": "'Izbat aş Şafīḩ",
        "id": 7541062
      }
    },
    {
      "geometry": {
        "type": "Point",
        "coordinates": [
          31.095886,
          30.080562
        ]
      },
      "type": "Feature",
      "properties": {
        "hierarchy": [
          "tgn:7541063",
          "tgn:7001242",
          "tgn:7016833",
          "tgn:7029392"
        ],
        "placetype": [
          "aat:300006075"
        ],
        "id": 7541063,
        "name:xx": "Tur'at al Ḩamāmi"
      }
    },
    {
      "geometry": {
        "type": "Point",
        "coordinates": [
          31.103895,
          30.083136
        ]
      },
      "type": "Feature",
      "properties": {
        "hierarchy": [
          "tgn:7541064",
          "tgn:7001242",
          "tgn:7016833",
          "tgn:7029392"
        ],
        "placetype": [
          "aat:300006075"
        ],
        "id": 7541064,
        "name:xx": "Far' ash Shihīmī"
      }
    },
    {
      "geometry": {
        "type": "Point",
        "coordinates": [
          31.109355,
          30.116377
        ]
      },
      "type": "Feature",
      "properties": {
        "hierarchy": [
          "tgn:7541065",
          "tgn:7001242",
          "tgn:7016833",
          "tgn:7029392"
        ],
        "placetype": [
          "aat:300006075"
        ],
        "id": 7541065,
        "name:xx": "Tur'at al Barājil"
      }
    },
    {
      "geometry": {
        "type": "Point",
        "coordinates": [
          31.237677,
          30.062938
        ]
      },
      "type": "Feature",
      "properties": {
        "hierarchy": [
          "tgn:7541066",
          "tgn:7001242",
          "tgn:7016833",
          "tgn:1001091",
          "tgn:7029392"
        ],
        "placetype": [
          "aat:300008347"
        ],
        "id": 7541066,
        "name:xx": "As Sabtīyah"
      }
    },
    {
      "geometry": {
        "type": "Point",
        "coordinates": [
          31.20385,
          30.000334
        ]
      },
      "type": "Feature",
      "properties": {
        "hierarchy": [
          "tgn:7541067",
          "tgn:7001242",
          "tgn:7016833",
          "tgn:7029392"
        ],
        "placetype": [
          "aat:300006075"
        ],
        "id": 7541067,
        "name:xx": "Tur'at az Zumur"
      }
    },
    {
      "geometry": {
        "type": "Point",
        "coordinates": [
          31.095756,
          30.053405
        ]
      },
      "type": "Feature",
      "properties": {
        "hierarchy": [
          "tgn:7541069",
          "tgn:7001242",
          "tgn:7016833",
          "tgn:7029392"
        ],
        "placetype": [
          "aat:300006075"
        ],
        "id": 7541069,
        "name:xx": "Far' al Birinsīsah"
      }
    }
  ]
}
