{
  "geometry": {
    "type": "Point",
    "coordinates": [
      -150.3833,
      60.85
    ]
  },
  "type": "Feature",
  "properties": {
    "hierarchy": [
      "tgn:2477329",
      "tgn:7006450",
      "tgn:1000001",
      "tgn:7019698",
      "tgn:7012149",
      "tgn:7029392"
    ],
    "placetype": [
      "aat:300008680"
    ],
    "id": 2477329,
    "name:xx": "Lynx Lake"
  }
}
