{
  "geometry": {
    "type": "Point",
    "coordinates": [
      -113.8833,
      47.3333
    ]
  },
  "type": "Feature",
  "properties": {
    "hierarchy": [
      "tgn:2344896",
      "tgn:1000001",
      "tgn:7012149",
      "tgn:7007524",
      "tgn:7029392"
    ],
    "placetype": [
      "aat:300266640"
    ],
    "id": 2344896,
    "name:xx": "Garden Wall, The"
  }
}
