{
  "geometry": {
    "type": "Point",
    "coordinates": [
      -72.4167,
      42.5667
    ]
  },
  "type": "Feature",
  "properties": {
    "hierarchy": [
      "tgn:2756956",
      "tgn:1000001",
      "tgn:7013942",
      "tgn:7012149",
      "tgn:7007517",
      "tgn:7029392"
    ],
    "placetype": [
      "aat:300008863"
    ],
    "id": 2756956,
    "name:xx": "Wendell State Forest"
  }
}
