{
  "geometry": {
    "type": "Point",
    "coordinates": [
      113.546,
      22.199
    ]
  },
  "type": "Feature",
  "properties": {
    "hierarchy": [
      "tgn:7031811",
      "tgn:1000004",
      "tgn:7005019",
      "tgn:7029392"
    ],
    "placetype": [
      "aat:300008791"
    ],
    "name:pt": "Macau, Ilha de",
    "name:en": "Macau Island",
    "id": 7031811
  }
}
