{
  "geometry": {
    "type": "Point",
    "coordinates": [
      -71.4167,
      41.4667
    ]
  },
  "type": "Feature",
  "properties": {
    "hierarchy": [
      "tgn:2412135",
      "tgn:1002996",
      "tgn:1000001",
      "tgn:7012149",
      "tgn:7007711",
      "tgn:7029392"
    ],
    "placetype": [
      "aat:300008699"
    ],
    "id": 2412135,
    "name:xx": "Indian Run"
  }
}
