{
  "geometry": {
    "type": "Point",
    "coordinates": [
      -81.3333,
      29.2167
    ]
  },
  "type": "Feature",
  "properties": {
    "hierarchy": [
      "tgn:2280733",
      "tgn:1000001",
      "tgn:7012149",
      "tgn:1002977",
      "tgn:7007240",
      "tgn:7029392"
    ],
    "placetype": [
      "aat:300008706"
    ],
    "id": 2280733,
    "name:xx": "Deep Creek"
  }
}
