{
  "geometry": {
    "type": "Point",
    "coordinates": [
      -108.6167,
      37.9833
    ]
  },
  "type": "Feature",
  "properties": {
    "hierarchy": [
      "tgn:2133724",
      "tgn:1000001",
      "tgn:7012149",
      "tgn:7007158",
      "tgn:2000248",
      "tgn:7029392"
    ],
    "placetype": [
      "aat:300008761"
    ],
    "id": 2133724,
    "name:xx": "Andy Draw"
  }
}
