{
  "geometry": {
    "type": "Point",
    "coordinates": [
      -75.1333,
      38.45
    ]
  },
  "type": "Feature",
  "properties": {
    "hierarchy": [
      "tgn:2632275",
      "tgn:1002933",
      "tgn:1000001",
      "tgn:7012149",
      "tgn:7007239",
      "tgn:7029392"
    ],
    "placetype": [
      "aat:300008706"
    ],
    "id": 2632275,
    "name:xx": "Roy Creek"
  }
}
