{
  "geometry": {
    "type": "Point",
    "coordinates": [
      -158.65,
      56.5333
    ]
  },
  "type": "Feature",
  "properties": {
    "hierarchy": [
      "tgn:2784776",
      "tgn:7006450",
      "tgn:1000001",
      "tgn:7030517",
      "tgn:7012149",
      "tgn:7029392"
    ],
    "placetype": [
      "aat:300008706"
    ],
    "id": 2784776,
    "name:xx": "Yellow Bluff Creek"
  }
}
