{
  "type": "FeatureCollection",
  "features": [
    {
      "geometry": {
        "type": "Point",
        "coordinates": [
          87.266,
          25.316
        ]
      },
      "type": "Feature",
      "properties": {
        "hierarchy": [
          "tgn:7593820",
          "tgn:1000004",
          "tgn:1001842",
          "tgn:7000198",
          "tgn:7029392"
        ],
        "placetype": [
          "aat:300008347",
          "aat:300000810",
          "aat:300073738",
          "aat:300008372"
        ],
        "id": 7593820,
        "name:xx": "Antichak"
      }
    },
    {
      "geometry": {
        "type": "Point",
        "coordinates": [
          74.7,
          19.516
        ]
      },
      "type": "Feature",
      "properties": {
        "hierarchy": [
          "tgn:7593821",
          "tgn:1000004",
          "tgn:7000198",
          "tgn:1001895",
          "tgn:7029392"
        ],
        "placetype": [
          "aat:300008347",
          "aat:300000810",
          "aat:300167671"
        ],
        "id": 7593821,
        "name:xx": "Daimabad"
      }
    },
    {
      "geometry": {
        "type": "Point",
        "coordinates": [
          76.783,
          30.283
        ]
      },
      "type": "Feature",
      "properties": {
        "hierarchy": [
          "tgn:7593823",
          "tgn:1000004",
          "tgn:7000198",
          "tgn:7016883",
          "tgn:7029392"
        ],
        "placetype": [
          "aat:300008347",
          "aat:300000810",
          "aat:300008372"
        ],
        "id": 7593823,
        "name:xx": "Bara"
      }
    },
    {
      "geometry": {
        "type": "Point",
        "coordinates": [
          74.25,
          25.016
        ]
      },
      "type": "Feature",
      "properties": {
        "hierarchy": [
          "tgn:7593824",
          "tgn:1000004",
          "tgn:7000198",
          "tgn:7016788",
          "tgn:7029392"
        ],
        "placetype": [
          "aat:300019273",
          "aat:300008347",
          "aat:300000810",
          "aat:300008372",
          "aat:300000833"
        ],
        "id": 7593824,
        "name:xx": "Gilund"
      }
    },
    {
      "geometry": {
        "type": "Point",
        "coordinates": [
          -16.5,
          32.5
        ]
      },
      "type": "Feature",
      "properties": {
        "hierarchy": [
          "tgn:7593826",
          "tgn:7023836",
          "tgn:7003831",
          "tgn:1000003",
          "tgn:1000090",
          "tgn:7029392"
        ],
        "placetype": [
          "aat:300008791"
        ],
        "id": 7593826,
        "name:xx": "Deserta Grande"
      }
    },
    {
      "geometry": {
        "type": "Point",
        "coordinates": [
          -4.315,
          48.425
        ]
      },
      "type": "Feature",
      "properties": {
        "hierarchy": [
          "tgn:7593828",
          "tgn:1000003",
          "tgn:7012216",
          "tgn:1000070",
          "tgn:7029392"
        ],
        "placetype": [
          "aat:300008347"
        ],
        "id": 7593828,
        "name:xx": "La Forest-Landerneau"
      }
    },
    {
      "geometry": {
        "type": "Point",
        "coordinates": [
          -3.8,
          48.333
        ]
      },
      "type": "Feature",
      "properties": {
        "hierarchy": [
          "tgn:7593829",
          "tgn:1000003",
          "tgn:7012216",
          "tgn:1000070",
          "tgn:7029392"
        ],
        "placetype": [
          "aat:300008347"
        ],
        "id": 7593829,
        "name:xx": "Saint-Herbot"
      }
    }
  ]
}
