{
  "geometry": {
    "type": "Point",
    "coordinates": [
      -86.2833,
      34.75
    ]
  },
  "type": "Feature",
  "properties": {
    "hierarchy": [
      "tgn:2193676",
      "tgn:7002659",
      "tgn:1000001",
      "tgn:7012149",
      "tgn:2000035",
      "tgn:7029392"
    ],
    "placetype": [
      "aat:300008697"
    ],
    "id": 2193676,
    "name:xx": "Brewer Spring"
  }
}
