{
  "geometry": {
    "type": "Point",
    "coordinates": [
      119.4833,
      25.2167
    ]
  },
  "type": "Feature",
  "properties": {
    "hierarchy": [
      "tgn:1008290",
      "tgn:1000004",
      "tgn:7001796",
      "tgn:1000111",
      "tgn:7029392"
    ],
    "placetype": [
      "aat:300008791"
    ],
    "id": 1008290,
    "name:xx": "Nanri Dao"
  }
}
