{
  "geometry": {
    "type": "Point",
    "coordinates": [
      -99.35,
      27.0167
    ]
  },
  "type": "Feature",
  "properties": {
    "hierarchy": [
      "tgn:2614228",
      "tgn:1000001",
      "tgn:7012149",
      "tgn:2002099",
      "tgn:7007826",
      "tgn:7029392"
    ],
    "placetype": [
      "aat:300006191"
    ],
    "id": 2614228,
    "name:xx": "Refugio Ramirez Tank"
  }
}
