{
  "geometry": {
    "type": "Point",
    "coordinates": [
      -131.3833,
      55.2667
    ]
  },
  "type": "Feature",
  "properties": {
    "hierarchy": [
      "tgn:2176757",
      "tgn:7006450",
      "tgn:1000001",
      "tgn:2124076",
      "tgn:7012149",
      "tgn:7029392"
    ],
    "placetype": [
      "aat:300008798"
    ],
    "id": 2176757,
    "name:xx": "Black Mountain"
  }
}
