{
  "geometry": {
    "type": "Point",
    "coordinates": [
      58.25,
      51.25
    ]
  },
  "type": "Feature",
  "properties": {
    "hierarchy": [
      "tgn:1052014",
      "tgn:1000004",
      "tgn:1003398",
      "tgn:7018214",
      "tgn:7002435",
      "tgn:7029392"
    ],
    "placetype": [
      "aat:300008347"
    ],
    "id": 1052014,
    "name:xx": "Akkermanovka"
  }
}
