{
  "geometry": {
    "type": "Point",
    "coordinates": [
      -95.45,
      29.3333
    ]
  },
  "type": "Feature",
  "properties": {
    "hierarchy": [
      "tgn:2629579",
      "tgn:1000001",
      "tgn:1002198",
      "tgn:7012149",
      "tgn:7007826",
      "tgn:7029392"
    ],
    "placetype": [
      "aat:300006075"
    ],
    "id": 2629579,
    "name:xx": "Rosharon Lateral"
  }
}
