{
  "geometry": {
    "type": "Point",
    "coordinates": [
      -97.6333,
      31.5333
    ]
  },
  "type": "Feature",
  "properties": {
    "hierarchy": [
      "tgn:2606074",
      "tgn:1000001",
      "tgn:7012149",
      "tgn:7007826",
      "tgn:7029392"
    ],
    "placetype": [
      "aat:300008706"
    ],
    "id": 2606074,
    "name:xx": "Rainey Creek"
  }
}
