{
  "type": "FeatureCollection",
  "features": [
    {
      "geometry": {
        "type": "Point",
        "coordinates": [
          -80.3333,
          27.3
        ]
      },
      "type": "Feature",
      "properties": {
        "hierarchy": [
          "tgn:2021051",
          "tgn:1000001",
          "tgn:7012149",
          "tgn:7016124",
          "tgn:7007240",
          "tgn:7029392"
        ],
        "placetype": [
          "aat:300008347"
        ],
        "id": 2021051,
        "name:xx": "River Park"
      }
    },
    {
      "geometry": {
        "type": "Point",
        "coordinates": [
          -87.1833,
          30.5333
        ]
      },
      "type": "Feature",
      "properties": {
        "hierarchy": [
          "tgn:2021057",
          "tgn:1000001",
          "tgn:2000265",
          "tgn:7012149",
          "tgn:7007240",
          "tgn:7029392"
        ],
        "placetype": [
          "aat:300008347"
        ],
        "id": 2021057,
        "name:xx": "Riverview"
      }
    },
    {
      "geometry": {
        "type": "Point",
        "coordinates": [
          -82.3167,
          27.85
        ]
      },
      "type": "Feature",
      "properties": {
        "hierarchy": [
          "tgn:2021058",
          "tgn:1000001",
          "tgn:1002479",
          "tgn:7012149",
          "tgn:7007240",
          "tgn:7029392"
        ],
        "placetype": [
          "aat:300008347"
        ],
        "id": 2021058,
        "name:xx": "Riverview"
      }
    },
    {
      "geometry": {
        "type": "Point",
        "coordinates": [
          -80.05,
          26.7667
        ]
      },
      "type": "Feature",
      "properties": {
        "hierarchy": [
          "tgn:2021059",
          "tgn:1000001",
          "tgn:7012149",
          "tgn:1002768",
          "tgn:7007240",
          "tgn:7029392"
        ],
        "placetype": [
          "aat:300008347"
        ],
        "id": 2021059,
        "name:xx": "Riviera Beach"
      }
    }
  ]
}
