{
  "geometry": {
    "type": "Point",
    "coordinates": [
      120.90944,
      24.20916
    ]
  },
  "type": "Feature",
  "properties": {
    "hierarchy": [
      "tgn:7490761",
      "tgn:1000004",
      "tgn:1000141",
      "tgn:7029392"
    ],
    "placetype": [
      "aat:300387179"
    ],
    "id": 7490761,
    "name:xx": "Taizhong Xian"
  }
}
