{
  "geometry": {
    "type": "Point",
    "coordinates": [
      -117.0667,
      46.7167
    ]
  },
  "type": "Feature",
  "properties": {
    "hierarchy": [
      "tgn:2705060",
      "tgn:1000001",
      "tgn:7012149",
      "tgn:2002252",
      "tgn:7007920",
      "tgn:7029392"
    ],
    "placetype": [
      "aat:300008706"
    ],
    "id": 2705060,
    "name:xx": "Sunshine Creek"
  }
}
