{
  "geometry": {
    "type": "Point",
    "coordinates": [
      -105.6167,
      37.95
    ]
  },
  "type": "Feature",
  "properties": {
    "hierarchy": [
      "tgn:2681960",
      "tgn:1000001",
      "tgn:7012149",
      "tgn:7007158",
      "tgn:2000246",
      "tgn:7029392"
    ],
    "placetype": [
      "aat:300008706"
    ],
    "id": 2681960,
    "name:xx": "South Spanish Creek"
  }
}
