{
  "geometry": {
    "type": "Point",
    "coordinates": [
      -97.8333,
      32.5667
    ]
  },
  "type": "Feature",
  "properties": {
    "hierarchy": [
      "tgn:2217632",
      "tgn:1000001",
      "tgn:7012149",
      "tgn:1002771",
      "tgn:7007826",
      "tgn:7029392"
    ],
    "placetype": [
      "aat:300008791"
    ],
    "id": 2217632,
    "name:xx": "Campbell Island"
  }
}
