{
  "type": "FeatureCollection",
  "features": [
    {
      "geometry": {
        "type": "Point",
        "coordinates": [
          3.876164,
          50.551229
        ]
      },
      "type": "Feature",
      "properties": {
        "hierarchy": [
          "tgn:7238161",
          "tgn:7007877",
          "tgn:1000003",
          "tgn:1000063",
          "tgn:4012014",
          "tgn:7029392"
        ],
        "placetype": [
          "aat:300008347"
        ],
        "id": 7238161,
        "name:xx": "Grand Hameau"
      }
    },
    {
      "geometry": {
        "type": "Point",
        "coordinates": [
          5.035865,
          50.695305
        ]
      },
      "type": "Feature",
      "properties": {
        "hierarchy": [
          "tgn:7238164",
          "tgn:7003460",
          "tgn:1000003",
          "tgn:1000063",
          "tgn:4012014",
          "tgn:7029392"
        ],
        "placetype": [
          "aat:300008347"
        ],
        "id": 7238164,
        "name:xx": "Grand-Hallet"
      }
    },
    {
      "geometry": {
        "type": "Point",
        "coordinates": [
          6.166667,
          50.533333
        ]
      },
      "type": "Feature",
      "properties": {
        "hierarchy": [
          "tgn:7238166",
          "tgn:7003460",
          "tgn:1000003",
          "tgn:1000063",
          "tgn:4012014",
          "tgn:7029392"
        ],
        "placetype": [
          "aat:300008863"
        ],
        "id": 7238166,
        "name:xx": "Grand Haard"
      }
    },
    {
      "geometry": {
        "type": "Point",
        "coordinates": [
          5.7,
          50.283333
        ]
      },
      "type": "Feature",
      "properties": {
        "hierarchy": [
          "tgn:7238167",
          "tgn:7003465",
          "tgn:1000003",
          "tgn:1000063",
          "tgn:4012014",
          "tgn:7029392"
        ],
        "placetype": [
          "aat:300008347"
        ],
        "id": 7238167,
        "name:xx": "Grand Gotta"
      }
    },
    {
      "geometry": {
        "type": "Point",
        "coordinates": [
          3.695756,
          50.505184
        ]
      },
      "type": "Feature",
      "properties": {
        "hierarchy": [
          "tgn:7238168",
          "tgn:7007877",
          "tgn:1000003",
          "tgn:1000063",
          "tgn:4012014",
          "tgn:7029392"
        ],
        "placetype": [
          "aat:300008347"
        ],
        "id": 7238168,
        "name:xx": "Grandglise"
      }
    }
  ]
}
