{
  "geometry": {
    "type": "Point",
    "coordinates": [
      31.284447,
      30.019098
    ]
  },
  "type": "Feature",
  "properties": {
    "hierarchy": [
      "tgn:7526173",
      "tgn:7001242",
      "tgn:7016833",
      "tgn:1001091",
      "tgn:7029392"
    ],
    "placetype": [
      "aat:300000641"
    ],
    "id": 7526173,
    "name:xx": "Dayr as Sayyidah al 'Adhr훮' lil Ruhb훮n al Farans카sk훮n"
  }
}
