{
  "geometry": {
    "type": "Point",
    "coordinates": [
      13.95,
      52.65
    ]
  },
  "type": "Feature",
  "properties": {
    "hierarchy": [
      "tgn:7097642",
      "tgn:7000096",
      "tgn:1000003",
      "tgn:7000084",
      "tgn:7029392"
    ],
    "placetype": [
      "aat:300008777"
    ],
    "id": 7097642,
    "name:xx": "Spring-Berge"
  }
}
