{
  "geometry": {
    "type": "Point",
    "coordinates": [
      -91.8333,
      37.4333
    ]
  },
  "type": "Feature",
  "properties": {
    "hierarchy": [
      "tgn:2162724",
      "tgn:1000001",
      "tgn:7012149",
      "tgn:2001252",
      "tgn:7007523",
      "tgn:7029392"
    ],
    "placetype": [
      "aat:300008706"
    ],
    "id": 2162724,
    "name:xx": "Bender Creek"
  }
}
