{
  "geometry": {
    "type": "Point",
    "coordinates": [
      -113.9167,
      33.6167
    ]
  },
  "type": "Feature",
  "properties": {
    "hierarchy": [
      "tgn:2615015",
      "tgn:1000001",
      "tgn:7006451",
      "tgn:7012149",
      "tgn:2000104",
      "tgn:7029392"
    ],
    "placetype": [
      "aat:300000390"
    ],
    "id": 2615015,
    "name:xx": "Republic Mine"
  }
}
