{
  "geometry": {
    "type": "Point",
    "coordinates": [
      -123.1833,
      47.0833
    ]
  },
  "type": "Feature",
  "properties": {
    "hierarchy": [
      "tgn:2307782",
      "tgn:1000001",
      "tgn:7012149",
      "tgn:1002418",
      "tgn:7007920",
      "tgn:7029392"
    ],
    "placetype": [
      "aat:300008706"
    ],
    "id": 2307782,
    "name:xx": "East Fork Wildcat Creek"
  }
}
