{
  "geometry": {
    "type": "Point",
    "coordinates": [
      -85.9667,
      46.6667
    ]
  },
  "type": "Feature",
  "properties": {
    "hierarchy": [
      "tgn:2757389",
      "tgn:2000943",
      "tgn:1000001",
      "tgn:7012149",
      "tgn:7007520",
      "tgn:7029392"
    ],
    "placetype": [
      "aat:300132316"
    ],
    "id": 2757389,
    "name:xx": "West Bay"
  }
}
