{
  "geometry": {
    "type": "Point",
    "coordinates": [
      55.95,
      37.8833
    ]
  },
  "type": "Feature",
  "properties": {
    "hierarchy": [
      "tgn:1079192",
      "tgn:1000004",
      "tgn:1001403",
      "tgn:7000231",
      "tgn:7029392"
    ],
    "placetype": [
      "aat:300008347"
    ],
    "id": 1079192,
    "name:xx": "Marāveh Tappeh"
  }
}
