{
  "geometry": {
    "type": "Point",
    "coordinates": [
      130.9167,
      33.3167
    ]
  },
  "type": "Feature",
  "properties": {
    "hierarchy": [
      "tgn:1080144",
      "tgn:1000961",
      "tgn:1000004",
      "tgn:7000901",
      "tgn:1000120",
      "tgn:7029392"
    ],
    "placetype": [
      "aat:300008347"
    ],
    "id": 1080144,
    "name:xx": "Hita"
  }
}
