{
  "geometry": {
    "type": "Point",
    "coordinates": [
      -122.05,
      37.85
    ]
  },
  "type": "Feature",
  "properties": {
    "hierarchy": [
      "tgn:2225208",
      "tgn:1000001",
      "tgn:7012149",
      "tgn:1002298",
      "tgn:7007157",
      "tgn:7029392"
    ],
    "placetype": [
      "aat:300008798"
    ],
    "id": 2225208,
    "name:xx": "Castle Hill"
  }
}
