{
  "geometry": {
    "type": "Point",
    "coordinates": [
      -71.2667,
      42.15
    ]
  },
  "type": "Feature",
  "properties": {
    "hierarchy": [
      "tgn:2333217",
      "tgn:1000001",
      "tgn:1002724",
      "tgn:7012149",
      "tgn:7007517",
      "tgn:7029392"
    ],
    "placetype": [
      "aat:300008680"
    ],
    "id": 2333217,
    "name:xx": "Flynns Pond"
  }
}
