{
  "type": "FeatureCollection",
  "features": [
    {
      "geometry": {
        "type": "Point",
        "coordinates": [
          -92.166667,
          15.933333
        ]
      },
      "type": "Feature",
      "properties": {
        "hierarchy": [
          "tgn:7396840",
          "tgn:1000001",
          "tgn:1001893",
          "tgn:7005560",
          "tgn:7029392"
        ],
        "placetype": [
          "aat:300008699"
        ],
        "id": 7396840,
        "name:xx": "Cuilco, Río"
      }
    },
    {
      "geometry": {
        "type": "Point",
        "coordinates": [
          -105.4,
          30.883333
        ]
      },
      "type": "Feature",
      "properties": {
        "hierarchy": [
          "tgn:7396841",
          "tgn:7005581",
          "tgn:1000001",
          "tgn:7005560",
          "tgn:7029392"
        ],
        "placetype": [
          "aat:300000241"
        ],
        "id": 7396841,
        "name:xx": "Rancho San Miguel"
      }
    },
    {
      "geometry": {
        "type": "Point",
        "coordinates": [
          -115.866667,
          30.733333
        ]
      },
      "type": "Feature",
      "properties": {
        "hierarchy": [
          "tgn:7396842",
          "tgn:1001835",
          "tgn:1000001",
          "tgn:7005560",
          "tgn:7029392"
        ],
        "placetype": [
          "aat:300000241"
        ],
        "id": 7396842,
        "name:xx": "Rancho San Miguel"
      }
    },
    {
      "geometry": {
        "type": "Point",
        "coordinates": [
          -108.733333,
          28.4
        ]
      },
      "type": "Feature",
      "properties": {
        "hierarchy": [
          "tgn:7396843",
          "tgn:1000001",
          "tgn:1001960",
          "tgn:7005560",
          "tgn:7029392"
        ],
        "placetype": [
          "aat:300000241"
        ],
        "id": 7396843,
        "name:xx": "Rancho San Miguel"
      }
    },
    {
      "geometry": {
        "type": "Point",
        "coordinates": [
          -105.7,
          28.066667
        ]
      },
      "type": "Feature",
      "properties": {
        "hierarchy": [
          "tgn:7396844",
          "tgn:7005581",
          "tgn:1000001",
          "tgn:7005560",
          "tgn:7029392"
        ],
        "placetype": [
          "aat:300000241"
        ],
        "id": 7396844,
        "name:xx": "Rancho San Miguel"
      }
    },
    {
      "geometry": {
        "type": "Point",
        "coordinates": [
          -107.816667,
          27.683333
        ]
      },
      "type": "Feature",
      "properties": {
        "hierarchy": [
          "tgn:7396845",
          "tgn:7005581",
          "tgn:1000001",
          "tgn:7005560",
          "tgn:7029392"
        ],
        "placetype": [
          "aat:300000241"
        ],
        "id": 7396845,
        "name:xx": "Rancho San Miguel"
      }
    },
    {
      "geometry": {
        "type": "Point",
        "coordinates": [
          -104.95,
          27.6
        ]
      },
      "type": "Feature",
      "properties": {
        "hierarchy": [
          "tgn:7396846",
          "tgn:7005581",
          "tgn:1000001",
          "tgn:7005560",
          "tgn:7029392"
        ],
        "placetype": [
          "aat:300000241"
        ],
        "id": 7396846,
        "name:xx": "Rancho San Miguel"
      }
    },
    {
      "geometry": {
        "type": "Point",
        "coordinates": [
          -104.616667,
          27.4
        ]
      },
      "type": "Feature",
      "properties": {
        "hierarchy": [
          "tgn:7396847",
          "tgn:7005581",
          "tgn:1000001",
          "tgn:7005560",
          "tgn:7029392"
        ],
        "placetype": [
          "aat:300000241"
        ],
        "id": 7396847,
        "name:xx": "Rancho San Miguel"
      }
    },
    {
      "geometry": {
        "type": "Point",
        "coordinates": [
          -102.366667,
          27.216667
        ]
      },
      "type": "Feature",
      "properties": {
        "hierarchy": [
          "tgn:7396848",
          "tgn:1001853",
          "tgn:1000001",
          "tgn:7005560",
          "tgn:7029392"
        ],
        "placetype": [
          "aat:300000241"
        ],
        "id": 7396848,
        "name:xx": "Rancho San Miguel"
      }
    },
    {
      "geometry": {
        "type": "Point",
        "coordinates": [
          -104.9,
          27.15
        ]
      },
      "type": "Feature",
      "properties": {
        "hierarchy": [
          "tgn:7396849",
          "tgn:7005581",
          "tgn:1000001",
          "tgn:7005560",
          "tgn:7029392"
        ],
        "placetype": [
          "aat:300000241"
        ],
        "id": 7396849,
        "name:xx": "Rancho San Miguel"
      }
    }
  ]
}
