{
  "geometry": {
    "type": "Point",
    "coordinates": [
      -116.6833,
      48.4667
    ]
  },
  "type": "Feature",
  "properties": {
    "hierarchy": [
      "tgn:2384718",
      "tgn:1000001",
      "tgn:2000460",
      "tgn:7012149",
      "tgn:7007250",
      "tgn:7029392"
    ],
    "placetype": [
      "aat:300008706"
    ],
    "id": 2384718,
    "name:xx": "Hellroaring Creek"
  }
}
