{
  "type": "FeatureCollection",
  "features": [
    {
      "geometry": {
        "type": "Point",
        "coordinates": [
          -162.3,
          55.0667
        ]
      },
      "type": "Feature",
      "properties": {
        "hierarchy": [
          "tgn:2437690",
          "tgn:7030515",
          "tgn:7006450",
          "tgn:1000001",
          "tgn:7012149",
          "tgn:7029392"
        ],
        "placetype": [
          "aat:300132316"
        ],
        "id": 2437690,
        "name:xx": "King Cove Lagoon"
      }
    },
    {
      "geometry": {
        "type": "Point",
        "coordinates": [
          -74.9,
          39.0667
        ]
      },
      "type": "Feature",
      "properties": {
        "hierarchy": [
          "tgn:2437691",
          "tgn:1002232",
          "tgn:1000001",
          "tgn:7012149",
          "tgn:7007565",
          "tgn:7029392"
        ],
        "placetype": [
          "aat:300008347"
        ],
        "id": 2437691,
        "name:xx": "King Crab Landing"
      }
    },
    {
      "geometry": {
        "type": "Point",
        "coordinates": [
          -86.8833,
          33.15
        ]
      },
      "type": "Feature",
      "properties": {
        "hierarchy": [
          "tgn:2437692",
          "tgn:7002659",
          "tgn:1000001",
          "tgn:7012149",
          "tgn:2000058",
          "tgn:7029392"
        ],
        "placetype": [
          "aat:300008706"
        ],
        "id": 2437692,
        "name:xx": "King Creek"
      }
    },
    {
      "geometry": {
        "type": "Point",
        "coordinates": [
          -130.7,
          55.8
        ]
      },
      "type": "Feature",
      "properties": {
        "hierarchy": [
          "tgn:2437693",
          "tgn:7006450",
          "tgn:1000001",
          "tgn:7012149",
          "tgn:2000082",
          "tgn:7029392"
        ],
        "placetype": [
          "aat:300008706"
        ],
        "id": 2437693,
        "name:xx": "King Creek"
      }
    },
    {
      "geometry": {
        "type": "Point",
        "coordinates": [
          -161.8,
          61.8833
        ]
      },
      "type": "Feature",
      "properties": {
        "hierarchy": [
          "tgn:2437694",
          "tgn:7006450",
          "tgn:1000001",
          "tgn:7012149",
          "tgn:2000087",
          "tgn:7029392"
        ],
        "placetype": [
          "aat:300008706"
        ],
        "id": 2437694,
        "name:xx": "King Creek"
      }
    },
    {
      "geometry": {
        "type": "Point",
        "coordinates": [
          -153.9,
          63.4833
        ]
      },
      "type": "Feature",
      "properties": {
        "hierarchy": [
          "tgn:2437695",
          "tgn:7006450",
          "tgn:1000001",
          "tgn:7012149",
          "tgn:2000089",
          "tgn:7029392"
        ],
        "placetype": [
          "aat:300008706"
        ],
        "id": 2437695,
        "name:xx": "King Creek"
      }
    },
    {
      "geometry": {
        "type": "Point",
        "coordinates": [
          -144.2167,
          64.3333
        ]
      },
      "type": "Feature",
      "properties": {
        "hierarchy": [
          "tgn:2437696",
          "tgn:7006450",
          "tgn:1000001",
          "tgn:7012149",
          "tgn:2000085",
          "tgn:7029392"
        ],
        "placetype": [
          "aat:300008706"
        ],
        "id": 2437696,
        "name:xx": "King Creek"
      }
    },
    {
      "geometry": {
        "type": "Point",
        "coordinates": [
          -145.95,
          65.1833
        ]
      },
      "type": "Feature",
      "properties": {
        "hierarchy": [
          "tgn:2437697",
          "tgn:7006450",
          "tgn:1000001",
          "tgn:7019674",
          "tgn:7012149",
          "tgn:7029392"
        ],
        "placetype": [
          "aat:300008706"
        ],
        "id": 2437697,
        "name:xx": "King Creek"
      }
    },
    {
      "geometry": {
        "type": "Point",
        "coordinates": [
          -109.3333,
          33.15
        ]
      },
      "type": "Feature",
      "properties": {
        "hierarchy": [
          "tgn:2437698",
          "tgn:1000001",
          "tgn:7006451",
          "tgn:2000095",
          "tgn:7012149",
          "tgn:7029392"
        ],
        "placetype": [
          "aat:300008706"
        ],
        "id": 2437698,
        "name:xx": "King Creek"
      }
    },
    {
      "geometry": {
        "type": "Point",
        "coordinates": [
          -123.3833,
          41.5833
        ]
      },
      "type": "Feature",
      "properties": {
        "hierarchy": [
          "tgn:2437699",
          "tgn:1000001",
          "tgn:7012149",
          "tgn:7007157",
          "tgn:2000189",
          "tgn:7029392"
        ],
        "placetype": [
          "aat:300008706"
        ],
        "id": 2437699,
        "name:xx": "King Creek"
      }
    }
  ]
}
