{
  "geometry": {
    "type": "Point",
    "coordinates": [
      75.016667,
      14.55
    ]
  },
  "type": "Feature",
  "properties": {
    "hierarchy": [
      "tgn:7547321",
      "tgn:1000004",
      "tgn:7000198",
      "tgn:1001882",
      "tgn:7029392"
    ],
    "placetype": [
      "aat:300008347"
    ],
    "name:en": "Banavāsi",
    "id": 7547321
  }
}
