{
  "geometry": {
    "type": "Point",
    "coordinates": [
      114.9167,
      36.8167
    ]
  },
  "type": "Feature",
  "properties": {
    "hierarchy": [
      "tgn:1071199",
      "tgn:1000004",
      "tgn:7002077",
      "tgn:1000111",
      "tgn:7029392"
    ],
    "placetype": [
      "aat:300008347"
    ],
    "id": 1071199,
    "name:xx": "Quzhou"
  }
}
