{
  "type": "FeatureCollection",
  "features": [
    {
      "geometry": {
        "type": "Point",
        "coordinates": [
          -134.7833,
          58.05
        ]
      },
      "type": "Feature",
      "properties": {
        "hierarchy": [
          "tgn:2344140",
          "tgn:7006450",
          "tgn:1000001",
          "tgn:7012149",
          "tgn:7019760",
          "tgn:7029392"
        ],
        "placetype": [
          "aat:300132316"
        ],
        "id": 2344140,
        "name:xx": "Game Cove"
      }
    },
    {
      "geometry": {
        "type": "Point",
        "coordinates": [
          -164.4167,
          64.9
        ]
      },
      "type": "Feature",
      "properties": {
        "hierarchy": [
          "tgn:2344141",
          "tgn:7006450",
          "tgn:1000001",
          "tgn:7012149",
          "tgn:2000079",
          "tgn:7029392"
        ],
        "placetype": [
          "aat:300008706"
        ],
        "id": 2344141,
        "name:xx": "Game Creek"
      }
    },
    {
      "geometry": {
        "type": "Point",
        "coordinates": [
          -135.4167,
          57.95
        ]
      },
      "type": "Feature",
      "properties": {
        "hierarchy": [
          "tgn:2344142",
          "tgn:7006450",
          "tgn:1000001",
          "tgn:7012149",
          "tgn:7019760",
          "tgn:7029392"
        ],
        "placetype": [
          "aat:300008706"
        ],
        "id": 2344142,
        "name:xx": "Game Creek"
      }
    },
    {
      "geometry": {
        "type": "Point",
        "coordinates": [
          -106.3667,
          39.6
        ]
      },
      "type": "Feature",
      "properties": {
        "hierarchy": [
          "tgn:2344143",
          "tgn:1000001",
          "tgn:7012149",
          "tgn:2000210",
          "tgn:7007158",
          "tgn:7029392"
        ],
        "placetype": [
          "aat:300008706"
        ],
        "id": 2344143,
        "name:xx": "Game Creek"
      }
    },
    {
      "geometry": {
        "type": "Point",
        "coordinates": [
          -82.6,
          28.8167
        ]
      },
      "type": "Feature",
      "properties": {
        "hierarchy": [
          "tgn:2344144",
          "tgn:1000001",
          "tgn:1002269",
          "tgn:7012149",
          "tgn:7007240",
          "tgn:7029392"
        ],
        "placetype": [
          "aat:300008706"
        ],
        "id": 2344144,
        "name:xx": "Game Creek"
      }
    },
    {
      "geometry": {
        "type": "Point",
        "coordinates": [
          -83.4333,
          32.75
        ]
      },
      "type": "Feature",
      "properties": {
        "hierarchy": [
          "tgn:2344145",
          "tgn:1000001",
          "tgn:7012149",
          "tgn:2000434",
          "tgn:7007248",
          "tgn:7029392"
        ],
        "placetype": [
          "aat:300008706"
        ],
        "id": 2344145,
        "name:xx": "Game Creek"
      }
    },
    {
      "geometry": {
        "type": "Point",
        "coordinates": [
          -115.15,
          46.85
        ]
      },
      "type": "Feature",
      "properties": {
        "hierarchy": [
          "tgn:2344146",
          "tgn:1000001",
          "tgn:2000469",
          "tgn:7012149",
          "tgn:7007250",
          "tgn:7029392"
        ],
        "placetype": [
          "aat:300008706"
        ],
        "id": 2344146,
        "name:xx": "Game Creek"
      }
    },
    {
      "geometry": {
        "type": "Point",
        "coordinates": [
          -115.3333,
          47
        ]
      },
      "type": "Feature",
      "properties": {
        "hierarchy": [
          "tgn:2344147",
          "tgn:1000001",
          "tgn:7012149",
          "tgn:2000491",
          "tgn:7007250",
          "tgn:7029392"
        ],
        "placetype": [
          "aat:300008706"
        ],
        "id": 2344147,
        "name:xx": "Game Creek"
      }
    },
    {
      "geometry": {
        "type": "Point",
        "coordinates": [
          -115.2667,
          45.4
        ]
      },
      "type": "Feature",
      "properties": {
        "hierarchy": [
          "tgn:2344148",
          "tgn:1000001",
          "tgn:7012149",
          "tgn:2000476",
          "tgn:7007250",
          "tgn:7029392"
        ],
        "placetype": [
          "aat:300008706"
        ],
        "id": 2344148,
        "name:xx": "Game Creek"
      }
    },
    {
      "geometry": {
        "type": "Point",
        "coordinates": [
          -111.0667,
          43.5667
        ]
      },
      "type": "Feature",
      "properties": {
        "hierarchy": [
          "tgn:2344149",
          "tgn:1000001",
          "tgn:7012149",
          "tgn:7029392"
        ],
        "placetype": [
          "aat:300008706"
        ],
        "id": 2344149,
        "name:xx": "Game Creek"
      }
    }
  ]
}
