{
  "geometry": {
    "type": "Point",
    "coordinates": [
      137.25,
      36.45
    ]
  },
  "type": "Feature",
  "properties": {
    "hierarchy": [
      "tgn:1130544",
      "tgn:7000895",
      "tgn:1000004",
      "tgn:1000977",
      "tgn:1000120",
      "tgn:7029392"
    ],
    "placetype": [
      "aat:300008707"
    ],
    "id": 1130544,
    "name:xx": "Takahara-gawa"
  }
}
