{
  "geometry": {
    "type": "Point",
    "coordinates": [
      -113.3833,
      45.95
    ]
  },
  "type": "Feature",
  "properties": {
    "hierarchy": [
      "tgn:2760731",
      "tgn:1000001",
      "tgn:7012149",
      "tgn:7020792",
      "tgn:7007524",
      "tgn:7029392"
    ],
    "placetype": [
      "aat:300008798"
    ],
    "id": 2760731,
    "name:xx": "West Goat Peak"
  }
}
