{
  "geometry": {
    "type": "Point",
    "coordinates": [
      -104.5833,
      42.3333
    ]
  },
  "type": "Feature",
  "properties": {
    "hierarchy": [
      "tgn:2782348",
      "tgn:1000001",
      "tgn:7012149",
      "tgn:2002372",
      "tgn:7007923",
      "tgn:7029392"
    ],
    "placetype": [
      "aat:300008697"
    ],
    "id": 2782348,
    "name:xx": "Woodworth Spring"
  }
}
