{
  "geometry": {
    "type": "Point",
    "coordinates": [
      -79.1333,
      37.9833
    ]
  },
  "type": "Feature",
  "properties": {
    "hierarchy": [
      "tgn:2248483",
      "tgn:2002142",
      "tgn:1000001",
      "tgn:7012149",
      "tgn:7007919",
      "tgn:7029392"
    ],
    "placetype": [
      "aat:300008347"
    ],
    "id": 2248483,
    "name:xx": "Cold Spring"
  }
}
