{
  "geometry": {
    "type": "Point",
    "coordinates": [
      -102.0833,
      41.7333
    ]
  },
  "type": "Feature",
  "properties": {
    "hierarchy": [
      "tgn:2756470",
      "tgn:1000001",
      "tgn:7012149",
      "tgn:7007525",
      "tgn:7029392"
    ],
    "placetype": [
      "aat:300386845"
    ],
    "id": 2756470,
    "name:xx": "Well Valley"
  }
}
