{
  "geometry": {
    "type": "Point",
    "coordinates": [
      100.15,
      25.55
    ]
  },
  "type": "Feature",
  "properties": {
    "hierarchy": [
      "tgn:7018866",
      "tgn:1000004",
      "tgn:7018118",
      "tgn:1000111",
      "tgn:7029392"
    ],
    "placetype": [
      "aat:300008347"
    ],
    "id": 7018866,
    "name:xx": "Dali"
  }
}
