{
  "geometry": {
    "type": "Point",
    "coordinates": [
      -76.2333,
      39.8833
    ]
  },
  "type": "Feature",
  "properties": {
    "hierarchy": [
      "tgn:2404607",
      "tgn:1000001",
      "tgn:7012149",
      "tgn:7013867",
      "tgn:7007710",
      "tgn:7029392"
    ],
    "placetype": [
      "aat:300008699"
    ],
    "id": 2404607,
    "name:xx": "Huber Run"
  }
}
