{
  "geometry": {
    "type": "Point",
    "coordinates": [
      -86.9833,
      34.5167
    ]
  },
  "type": "Feature",
  "properties": {
    "hierarchy": [
      "tgn:2378223",
      "tgn:7002659",
      "tgn:1000001",
      "tgn:7012149",
      "tgn:2000051",
      "tgn:7029392"
    ],
    "placetype": [
      "aat:300008798"
    ],
    "id": 2378223,
    "name:xx": "Harris Mountain"
  }
}
