{
  "geometry": {
    "type": "Point",
    "coordinates": [
      -111.2833,
      33.8667
    ]
  },
  "type": "Feature",
  "properties": {
    "hierarchy": [
      "tgn:2607050",
      "tgn:1000001",
      "tgn:7006451",
      "tgn:2000093",
      "tgn:7012149",
      "tgn:7029392"
    ],
    "placetype": [
      "aat:300008347"
    ],
    "id": 2607050,
    "name:xx": "Rancho Del Escondido"
  }
}
