{
  "geometry": {
    "type": "Point",
    "coordinates": [
      -78.8167,
      39.2667
    ]
  },
  "type": "Feature",
  "properties": {
    "hierarchy": [
      "tgn:2118755",
      "tgn:1000001",
      "tgn:7012149",
      "tgn:2002265",
      "tgn:7013961",
      "tgn:7029392"
    ],
    "placetype": [
      "aat:300387016"
    ],
    "id": 2118755,
    "name:xx": "Johnson"
  }
}
