{
  "geometry": {
    "type": "Point",
    "coordinates": [
      -104.5667,
      32.3333
    ]
  },
  "type": "Feature",
  "properties": {
    "hierarchy": [
      "tgn:2635800",
      "tgn:1000001",
      "tgn:2001436",
      "tgn:7012149",
      "tgn:7007566",
      "tgn:7029392"
    ],
    "placetype": [
      "aat:300008761"
    ],
    "id": 2635800,
    "name:xx": "Sacahuiste Draw"
  }
}
