{
  "geometry": {
    "type": "Point",
    "coordinates": [
      -2.5667,
      49.4667
    ]
  },
  "type": "Feature",
  "properties": {
    "hierarchy": [
      "tgn:1042258",
      "tgn:7005240",
      "tgn:1000003",
      "tgn:7005237",
      "tgn:7029392"
    ],
    "placetype": [
      "aat:300008347"
    ],
    "id": 1042258,
    "name:xx": "Catel"
  }
}
