{
  "geometry": {
    "type": "Point",
    "coordinates": [
      -88.0833,
      35.2833
    ]
  },
  "type": "Feature",
  "properties": {
    "hierarchy": [
      "tgn:2478868",
      "tgn:1000001",
      "tgn:7012149",
      "tgn:2001872",
      "tgn:7007825",
      "tgn:7029392"
    ],
    "placetype": [
      "aat:300008761"
    ],
    "id": 2478868,
    "name:xx": "Mag Hollow"
  }
}
