{
  "type": "FeatureCollection",
  "features": [
    {
      "geometry": {
        "type": "Point",
        "coordinates": [
          -122.4,
          37.5667
        ]
      },
      "type": "Feature",
      "properties": {
        "hierarchy": [
          "tgn:1118020",
          "tgn:1000001",
          "tgn:7012149",
          "tgn:7007157",
          "tgn:1002864",
          "tgn:7029392"
        ],
        "placetype": [
          "aat:300008680"
        ],
        "id": 1118020,
        "name:xx": "San Andreas Lake"
      }
    },
    {
      "geometry": {
        "type": "Point",
        "coordinates": [
          16.5,
          40.6167
        ]
      },
      "type": "Feature",
      "properties": {
        "hierarchy": [
          "tgn:1118021",
          "tgn:1003474",
          "tgn:7004610",
          "tgn:1000003",
          "tgn:1000080",
          "tgn:7029392"
        ],
        "placetype": [
          "aat:300008680"
        ],
        "id": 1118021,
        "name:xx": "San Giuliano, Lago di"
      }
    },
    {
      "geometry": {
        "type": "Point",
        "coordinates": [
          -113.216667,
          26.9
        ]
      },
      "type": "Feature",
      "properties": {
        "hierarchy": [
          "tgn:1118022",
          "tgn:1001836",
          "tgn:1000001",
          "tgn:7005560",
          "tgn:7029392"
        ],
        "placetype": [
          "aat:300008680"
        ],
        "id": 1118022,
        "name:xx": "San Ignacio, Laguna"
      }
    },
    {
      "geometry": {
        "type": "Point",
        "coordinates": [
          -64,
          -13.75
        ]
      },
      "type": "Feature",
      "properties": {
        "hierarchy": [
          "tgn:1118023",
          "tgn:1000525",
          "tgn:1000046",
          "tgn:1000002",
          "tgn:7029392"
        ],
        "placetype": [
          "aat:300008680"
        ],
        "id": 1118023,
        "name:xx": "San Luis, Laguna"
      }
    },
    {
      "geometry": {
        "type": "Point",
        "coordinates": [
          -91.708333,
          17.7375
        ]
      },
      "type": "Feature",
      "properties": {
        "hierarchy": [
          "tgn:1118024",
          "tgn:7005586",
          "tgn:1000001",
          "tgn:7005560",
          "tgn:7029392"
        ],
        "placetype": [
          "aat:300008680"
        ],
        "id": 1118024,
        "name:es": "San Marcos, Laguna"
      }
    },
    {
      "geometry": {
        "type": "Point",
        "coordinates": [
          -76.25,
          44.5667
        ]
      },
      "type": "Feature",
      "properties": {
        "hierarchy": [
          "tgn:1118026",
          "tgn:7005685",
          "tgn:1000001",
          "tgn:7013154",
          "tgn:7029392"
        ],
        "placetype": [
          "aat:300008680"
        ],
        "id": 1118026,
        "name:xx": "Sand Lake"
      }
    },
    {
      "geometry": {
        "type": "Point",
        "coordinates": [
          -57,
          49.2833
        ]
      },
      "type": "Feature",
      "properties": {
        "hierarchy": [
          "tgn:1118028",
          "tgn:7005685",
          "tgn:7005807",
          "tgn:1000001",
          "tgn:7005801",
          "tgn:7029392"
        ],
        "placetype": [
          "aat:300008680"
        ],
        "id": 1118028,
        "name:xx": "Sandy Lake"
      }
    },
    {
      "geometry": {
        "type": "Point",
        "coordinates": [
          -78.4,
          44.55
        ]
      },
      "type": "Feature",
      "properties": {
        "hierarchy": [
          "tgn:1118029",
          "tgn:7005685",
          "tgn:1000001",
          "tgn:7013154",
          "tgn:7029392"
        ],
        "placetype": [
          "aat:300008680"
        ],
        "id": 1118029,
        "name:xx": "Sandy Lake"
      }
    }
  ]
}
