{
  "geometry": {
    "type": "Point",
    "coordinates": [
      104.0333,
      34.4333
    ]
  },
  "type": "Feature",
  "properties": {
    "hierarchy": [
      "tgn:1070500",
      "tgn:1000004",
      "tgn:1001261",
      "tgn:1000111",
      "tgn:7029392"
    ],
    "placetype": [
      "aat:300008347"
    ],
    "id": 1070500,
    "name:xx": "Minxian"
  }
}
