{
  "geometry": {
    "type": "Point",
    "coordinates": [
      -116.6333,
      34.3333
    ]
  },
  "type": "Feature",
  "properties": {
    "hierarchy": [
      "tgn:2559109",
      "tgn:1000001",
      "tgn:7012149",
      "tgn:7007157",
      "tgn:1002857",
      "tgn:7029392"
    ],
    "placetype": [
      "aat:300008697"
    ],
    "id": 2559109,
    "name:xx": "One Hole Spring"
  }
}
