{
  "geometry": {
    "type": "Point",
    "coordinates": [
      -114.1833,
      43.1833
    ]
  },
  "type": "Feature",
  "properties": {
    "hierarchy": [
      "tgn:2425344",
      "tgn:1000001",
      "tgn:7012149",
      "tgn:2000483",
      "tgn:7007250",
      "tgn:7029392"
    ],
    "placetype": [
      "aat:300006191"
    ],
    "id": 2425344,
    "name:xx": "Johnson Reservoir"
  }
}
