{
  "geometry": {
    "type": "Point",
    "coordinates": [
      -113.0167,
      47.8667
    ]
  },
  "type": "Feature",
  "properties": {
    "hierarchy": [
      "tgn:2522480",
      "tgn:1000001",
      "tgn:7012149",
      "tgn:2001284",
      "tgn:7007524",
      "tgn:7029392"
    ],
    "placetype": [
      "aat:300008798"
    ],
    "id": 2522480,
    "name:xx": "Moonlight Peak"
  }
}
