{
  "geometry": {
    "type": "Point",
    "coordinates": [
      74.625064,
      32.857111
    ]
  },
  "type": "Feature",
  "properties": {
    "hierarchy": [
      "tgn:7590770",
      "tgn:1000004",
      "tgn:7000198",
      "tgn:7000799",
      "tgn:7029392"
    ],
    "placetype": [
      "aat:300008347"
    ],
    "name:en": "Dābra",
    "id": 7590770
  }
}
