{
  "geometry": {
    "type": "Point",
    "coordinates": [
      -80.15,
      41.4833
    ]
  },
  "type": "Feature",
  "properties": {
    "hierarchy": [
      "tgn:2623733",
      "tgn:1000001",
      "tgn:1002308",
      "tgn:7012149",
      "tgn:7007710",
      "tgn:7029392"
    ],
    "placetype": [
      "aat:300008706"
    ],
    "id": 2623733,
    "name:xx": "Rock Creek"
  }
}
