{
  "type": "FeatureCollection",
  "features": [
    {
      "geometry": {
        "type": "Point",
        "coordinates": [
          -106.1333,
          39.9667
        ]
      },
      "type": "Feature",
      "properties": {
        "hierarchy": [
          "tgn:2272490",
          "tgn:1000001",
          "tgn:7012149",
          "tgn:2000216",
          "tgn:7007158",
          "tgn:7029392"
        ],
        "placetype": [
          "aat:300266640"
        ],
        "id": 2272490,
        "name:xx": "Curtis Ridge"
      }
    },
    {
      "geometry": {
        "type": "Point",
        "coordinates": [
          -81.3167,
          39.75
        ]
      },
      "type": "Feature",
      "properties": {
        "hierarchy": [
          "tgn:2272491",
          "tgn:1000001",
          "tgn:7012149",
          "tgn:2001619",
          "tgn:7007706",
          "tgn:7029392"
        ],
        "placetype": [
          "aat:300266640"
        ],
        "id": 2272491,
        "name:xx": "Curtis Ridge"
      }
    },
    {
      "geometry": {
        "type": "Point",
        "coordinates": [
          -111.4833,
          41.6
        ]
      },
      "type": "Feature",
      "properties": {
        "hierarchy": [
          "tgn:2272492",
          "tgn:1000001",
          "tgn:2002103",
          "tgn:7012149",
          "tgn:7007827",
          "tgn:7029392"
        ],
        "placetype": [
          "aat:300266640"
        ],
        "id": 2272492,
        "name:xx": "Curtis Ridge"
      }
    },
    {
      "geometry": {
        "type": "Point",
        "coordinates": [
          -121.75,
          46.8667
        ]
      },
      "type": "Feature",
      "properties": {
        "hierarchy": [
          "tgn:2272493",
          "tgn:1000001",
          "tgn:7012149",
          "tgn:1002785",
          "tgn:7007920",
          "tgn:7029392"
        ],
        "placetype": [
          "aat:300266640"
        ],
        "id": 2272493,
        "name:xx": "Curtis Ridge"
      }
    },
    {
      "geometry": {
        "type": "Point",
        "coordinates": [
          -78.3833,
          40.7167
        ]
      },
      "type": "Feature",
      "properties": {
        "hierarchy": [
          "tgn:2272495",
          "tgn:1000001",
          "tgn:1002225",
          "tgn:7012149",
          "tgn:7007710",
          "tgn:7029392"
        ],
        "placetype": [
          "aat:300008699"
        ],
        "id": 2272495,
        "name:xx": "Curtis Run"
      }
    },
    {
      "geometry": {
        "type": "Point",
        "coordinates": [
          -80.4,
          38.9833
        ]
      },
      "type": "Feature",
      "properties": {
        "hierarchy": [
          "tgn:2272496",
          "tgn:1000001",
          "tgn:7012149",
          "tgn:2002271",
          "tgn:7013961",
          "tgn:7029392"
        ],
        "placetype": [
          "aat:300008699"
        ],
        "id": 2272496,
        "name:xx": "Curtis Run"
      }
    },
    {
      "geometry": {
        "type": "Point",
        "coordinates": [
          -80.5333,
          40.1333
        ]
      },
      "type": "Feature",
      "properties": {
        "hierarchy": [
          "tgn:2272497",
          "tgn:1000001",
          "tgn:7012149",
          "tgn:1002741",
          "tgn:7013961",
          "tgn:7029392"
        ],
        "placetype": [
          "aat:300008699"
        ],
        "id": 2272497,
        "name:xx": "Curtis Run"
      }
    },
    {
      "geometry": {
        "type": "Point",
        "coordinates": [
          -117.05,
          39.4833
        ]
      },
      "type": "Feature",
      "properties": {
        "hierarchy": [
          "tgn:2272498",
          "tgn:1000001",
          "tgn:2001415",
          "tgn:7012149",
          "tgn:7007526",
          "tgn:7029392"
        ],
        "placetype": [
          "aat:300000390"
        ],
        "id": 2272498,
        "name:xx": "Curtis Shaft"
      }
    },
    {
      "geometry": {
        "type": "Point",
        "coordinates": [
          -144.0167,
          66.8
        ]
      },
      "type": "Feature",
      "properties": {
        "hierarchy": [
          "tgn:2272499",
          "tgn:7006450",
          "tgn:1000001",
          "tgn:7012149",
          "tgn:2000089",
          "tgn:7029392"
        ],
        "placetype": [
          "aat:300008699"
        ],
        "id": 2272499,
        "name:xx": "Curtis Slough"
      }
    }
  ]
}
