{
  "type": "FeatureCollection",
  "features": [
    {
      "geometry": {
        "type": "Point",
        "coordinates": [
          -105.116667,
          20.75
        ]
      },
      "type": "Feature",
      "properties": {
        "hierarchy": [
          "tgn:7389100",
          "tgn:7005586",
          "tgn:1000001",
          "tgn:7005560",
          "tgn:7029392"
        ],
        "placetype": [
          "aat:300266554",
          "aat:300008699"
        ],
        "id": 7389100,
        "name:xx": "Quelitán"
      }
    },
    {
      "geometry": {
        "type": "Point",
        "coordinates": [
          -103.2,
          20.966667
        ]
      },
      "type": "Feature",
      "properties": {
        "hierarchy": [
          "tgn:7389101",
          "tgn:7005586",
          "tgn:1000001",
          "tgn:7005560",
          "tgn:7029392"
        ],
        "placetype": [
          "aat:300008347"
        ],
        "id": 7389101,
        "name:xx": "Quelitán"
      }
    },
    {
      "geometry": {
        "type": "Point",
        "coordinates": [
          -104.833333,
          19.783333
        ]
      },
      "type": "Feature",
      "properties": {
        "hierarchy": [
          "tgn:7389102",
          "tgn:7005586",
          "tgn:1000001",
          "tgn:7005560",
          "tgn:7029392"
        ],
        "placetype": [
          "aat:300008347"
        ],
        "id": 7389102,
        "name:xx": "Quelitán"
      }
    },
    {
      "geometry": {
        "type": "Point",
        "coordinates": [
          -110.85,
          30.883333
        ]
      },
      "type": "Feature",
      "properties": {
        "hierarchy": [
          "tgn:7389103",
          "tgn:1000001",
          "tgn:1001960",
          "tgn:7005560",
          "tgn:7029392"
        ],
        "placetype": [
          "aat:300008347"
        ],
        "id": 7389103,
        "name:xx": "Quelital"
      }
    },
    {
      "geometry": {
        "type": "Point",
        "coordinates": [
          -104.633333,
          23.683333
        ]
      },
      "type": "Feature",
      "properties": {
        "hierarchy": [
          "tgn:7389104",
          "tgn:7005583",
          "tgn:1000001",
          "tgn:7005560",
          "tgn:7029392"
        ],
        "placetype": [
          "aat:300008347"
        ],
        "id": 7389104,
        "name:xx": "Quelital"
      }
    },
    {
      "geometry": {
        "type": "Point",
        "coordinates": [
          -100.2,
          22.55
        ]
      },
      "type": "Feature",
      "properties": {
        "hierarchy": [
          "tgn:7389105",
          "tgn:1000001",
          "tgn:7005594",
          "tgn:7005560",
          "tgn:7029392"
        ],
        "placetype": [
          "aat:300008347"
        ],
        "id": 7389105,
        "name:xx": "Quelital"
      }
    },
    {
      "geometry": {
        "type": "Point",
        "coordinates": [
          -107.266667,
          25.066667
        ]
      },
      "type": "Feature",
      "properties": {
        "hierarchy": [
          "tgn:7389106",
          "tgn:7005583",
          "tgn:1000001",
          "tgn:7005560",
          "tgn:7029392"
        ],
        "placetype": [
          "aat:300008347"
        ],
        "id": 7389106,
        "name:xx": "Quelele"
      }
    },
    {
      "geometry": {
        "type": "Point",
        "coordinates": [
          -107.833333,
          24.783333
        ]
      },
      "type": "Feature",
      "properties": {
        "hierarchy": [
          "tgn:7389107",
          "tgn:1000001",
          "tgn:7005595",
          "tgn:7005560",
          "tgn:7029392"
        ],
        "placetype": [
          "aat:300008347"
        ],
        "id": 7389107,
        "name:xx": "Quelele"
      }
    },
    {
      "geometry": {
        "type": "Point",
        "coordinates": [
          -105.5,
          22.35
        ]
      },
      "type": "Feature",
      "properties": {
        "hierarchy": [
          "tgn:7389108",
          "tgn:1000001",
          "tgn:1001906",
          "tgn:7005560",
          "tgn:7029392"
        ],
        "placetype": [
          "aat:300008347"
        ],
        "id": 7389108,
        "name:xx": "Quelele"
      }
    }
  ]
}
