{
  "type": "FeatureCollection",
  "features": [
    {
      "geometry": {
        "type": "Point",
        "coordinates": [
          -107.066667,
          25.216667
        ]
      },
      "type": "Feature",
      "properties": {
        "hierarchy": [
          "tgn:7393720",
          "tgn:7005583",
          "tgn:1000001",
          "tgn:7005560",
          "tgn:7029392"
        ],
        "placetype": [
          "aat:300008347"
        ],
        "id": 7393720,
        "name:xx": "San José"
      }
    },
    {
      "geometry": {
        "type": "Point",
        "coordinates": [
          -99.933333,
          25.2
        ]
      },
      "type": "Feature",
      "properties": {
        "hierarchy": [
          "tgn:7393721",
          "tgn:1000001",
          "tgn:7005589",
          "tgn:7005560",
          "tgn:7029392"
        ],
        "placetype": [
          "aat:300008347"
        ],
        "id": 7393721,
        "name:xx": "San José"
      }
    },
    {
      "geometry": {
        "type": "Point",
        "coordinates": [
          -106.366667,
          25.166667
        ]
      },
      "type": "Feature",
      "properties": {
        "hierarchy": [
          "tgn:7393722",
          "tgn:7005583",
          "tgn:1000001",
          "tgn:7005560",
          "tgn:7029392"
        ],
        "placetype": [
          "aat:300008347"
        ],
        "id": 7393722,
        "name:xx": "San José"
      }
    },
    {
      "geometry": {
        "type": "Point",
        "coordinates": [
          -98.533333,
          25.116667
        ]
      },
      "type": "Feature",
      "properties": {
        "hierarchy": [
          "tgn:7393723",
          "tgn:1000001",
          "tgn:7005597",
          "tgn:7005560",
          "tgn:7029392"
        ],
        "placetype": [
          "aat:300008347"
        ],
        "id": 7393723,
        "name:xx": "San José"
      }
    },
    {
      "geometry": {
        "type": "Point",
        "coordinates": [
          -103.883333,
          24.966667
        ]
      },
      "type": "Feature",
      "properties": {
        "hierarchy": [
          "tgn:7393724",
          "tgn:7005583",
          "tgn:1000001",
          "tgn:7005560",
          "tgn:7029392"
        ],
        "placetype": [
          "aat:300008347"
        ],
        "id": 7393724,
        "name:xx": "San José"
      }
    },
    {
      "geometry": {
        "type": "Point",
        "coordinates": [
          -105.05,
          24.916667
        ]
      },
      "type": "Feature",
      "properties": {
        "hierarchy": [
          "tgn:7393725",
          "tgn:7005583",
          "tgn:1000001",
          "tgn:7005560",
          "tgn:7029392"
        ],
        "placetype": [
          "aat:300008347"
        ],
        "id": 7393725,
        "name:xx": "San José"
      }
    },
    {
      "geometry": {
        "type": "Point",
        "coordinates": [
          -100.8,
          24.883333
        ]
      },
      "type": "Feature",
      "properties": {
        "hierarchy": [
          "tgn:7393726",
          "tgn:1001853",
          "tgn:1000001",
          "tgn:7005560",
          "tgn:7029392"
        ],
        "placetype": [
          "aat:300008347"
        ],
        "id": 7393726,
        "name:xx": "San José"
      }
    },
    {
      "geometry": {
        "type": "Point",
        "coordinates": [
          -99.75,
          24.883333
        ]
      },
      "type": "Feature",
      "properties": {
        "hierarchy": [
          "tgn:7393727",
          "tgn:1000001",
          "tgn:7005589",
          "tgn:7005560",
          "tgn:7029392"
        ],
        "placetype": [
          "aat:300008347"
        ],
        "id": 7393727,
        "name:xx": "San José"
      }
    },
    {
      "geometry": {
        "type": "Point",
        "coordinates": [
          -104.163611,
          24.870833
        ]
      },
      "type": "Feature",
      "properties": {
        "hierarchy": [
          "tgn:7393728",
          "tgn:7005583",
          "tgn:1000001",
          "tgn:7005560",
          "tgn:7029392"
        ],
        "placetype": [
          "aat:300008347"
        ],
        "id": 7393728,
        "name:xx": "San José"
      }
    },
    {
      "geometry": {
        "type": "Point",
        "coordinates": [
          -103.633333,
          24.733333
        ]
      },
      "type": "Feature",
      "properties": {
        "hierarchy": [
          "tgn:7393729",
          "tgn:7005583",
          "tgn:1000001",
          "tgn:7005560",
          "tgn:7029392"
        ],
        "placetype": [
          "aat:300008347"
        ],
        "id": 7393729,
        "name:xx": "San José"
      }
    }
  ]
}
