{
  "geometry": {
    "type": "Point",
    "coordinates": [
      -122.9833,
      45.45
    ]
  },
  "type": "Feature",
  "properties": {
    "hierarchy": [
      "tgn:2615374",
      "tgn:1000001",
      "tgn:7012149",
      "tgn:1002994",
      "tgn:7007708",
      "tgn:7029392"
    ],
    "placetype": [
      "aat:300006191"
    ],
    "id": 2615374,
    "name:xx": "Reservoir Number Two"
  }
}
