{
  "geometry": {
    "type": "Point",
    "coordinates": [
      -79.2833,
      35.4833
    ]
  },
  "type": "Feature",
  "properties": {
    "hierarchy": [
      "tgn:2222256",
      "tgn:1000001",
      "tgn:7012149",
      "tgn:2001511",
      "tgn:7007709",
      "tgn:7029392"
    ],
    "placetype": [
      "aat:300006191"
    ],
    "id": 2222256,
    "name:xx": "Carolina Forest Lake"
  }
}
