{
  "geometry": {
    "type": "Point",
    "coordinates": [
      -74.0667,
      41.95
    ]
  },
  "type": "Feature",
  "properties": {
    "hierarchy": [
      "tgn:2343861",
      "tgn:1000001",
      "tgn:7012149",
      "tgn:1002961",
      "tgn:7007568",
      "tgn:7029392"
    ],
    "placetype": [
      "aat:300008798"
    ],
    "id": 2343861,
    "name:xx": "Gallis Hill"
  }
}
