{
  "type": "FeatureCollection",
  "features": [
    {
      "geometry": {
        "type": "Point",
        "coordinates": [
          121.66931,
          24.723895
        ]
      },
      "type": "Feature",
      "properties": {
        "hierarchy": [
          "tgn:7489880",
          "tgn:1000004",
          "tgn:7489179",
          "tgn:1000141",
          "tgn:7029392"
        ],
        "placetype": [
          "aat:300008798"
        ],
        "id": 7489880,
        "name:xx": "Da'anpi Shan"
      }
    },
    {
      "geometry": {
        "type": "Point",
        "coordinates": [
          120.580833,
          24.380278
        ]
      },
      "type": "Feature",
      "properties": {
        "hierarchy": [
          "tgn:7489881",
          "tgn:1000004",
          "tgn:7001009",
          "tgn:1000141",
          "tgn:7029392"
        ],
        "placetype": [
          "aat:300386968"
        ],
        "id": 7489881,
        "name:xx": "Da'an Gang"
      }
    },
    {
      "geometry": {
        "type": "Point",
        "coordinates": [
          120.583333,
          24.366667
        ]
      },
      "type": "Feature",
      "properties": {
        "hierarchy": [
          "tgn:7489882",
          "tgn:1000004",
          "tgn:7001009",
          "tgn:1000141",
          "tgn:7029392"
        ],
        "placetype": [
          "aat:300387173"
        ],
        "id": 7489882,
        "name:xx": "Da'an Xiang"
      }
    },
    {
      "geometry": {
        "type": "Point",
        "coordinates": [
          120.596111,
          24.408056
        ]
      },
      "type": "Feature",
      "properties": {
        "hierarchy": [
          "tgn:7489883",
          "tgn:1000004",
          "tgn:7001009",
          "tgn:1000141",
          "tgn:7029392"
        ],
        "placetype": [
          "aat:300008699"
        ],
        "id": 7489883,
        "name:xx": "Da'an Xi"
      }
    },
    {
      "geometry": {
        "type": "Point",
        "coordinates": [
          121.533333,
          25.033333
        ]
      },
      "type": "Feature",
      "properties": {
        "hierarchy": [
          "tgn:7489884",
          "tgn:1000004",
          "tgn:1000959",
          "tgn:1000141",
          "tgn:7029392"
        ],
        "placetype": [
          "aat:300387173"
        ],
        "id": 7489884,
        "name:xx": "Da'an Qu"
      }
    },
    {
      "geometry": {
        "type": "Point",
        "coordinates": [
          121.53104,
          25.026945
        ]
      },
      "type": "Feature",
      "properties": {
        "hierarchy": [
          "tgn:7489885",
          "tgn:1000004",
          "tgn:1000959",
          "tgn:1000141",
          "tgn:7029392"
        ],
        "placetype": [
          "aat:300000745"
        ],
        "id": 7489885,
        "name:xx": "Da'an"
      }
    },
    {
      "geometry": {
        "type": "Point",
        "coordinates": [
          121.431833,
          24.964947
        ]
      },
      "type": "Feature",
      "properties": {
        "hierarchy": [
          "tgn:7489886",
          "tgn:1000004",
          "tgn:1000454",
          "tgn:1000141",
          "tgn:7029392"
        ],
        "placetype": [
          "aat:300008347"
        ],
        "id": 7489886,
        "name:xx": "Da'anliao"
      }
    },
    {
      "geometry": {
        "type": "Point",
        "coordinates": [
          121.296389,
          24.611667
        ]
      },
      "type": "Feature",
      "properties": {
        "hierarchy": [
          "tgn:7489887",
          "tgn:1000004",
          "tgn:7471332",
          "tgn:1000141",
          "tgn:7029392"
        ],
        "placetype": [
          "aat:300008347"
        ],
        "id": 7489887,
        "name:xx": "Taigang"
      }
    },
    {
      "geometry": {
        "type": "Point",
        "coordinates": [
          120.749722,
          24.323333
        ]
      },
      "type": "Feature",
      "properties": {
        "hierarchy": [
          "tgn:7489888",
          "tgn:7487020",
          "tgn:1000004",
          "tgn:1000141",
          "tgn:7029392"
        ],
        "placetype": [
          "aat:300008347"
        ],
        "id": 7489888,
        "name:xx": "Qikuaicuo"
      }
    },
    {
      "geometry": {
        "type": "Point",
        "coordinates": [
          120.187222,
          23.209167
        ]
      },
      "type": "Feature",
      "properties": {
        "hierarchy": [
          "tgn:7489889",
          "tgn:1000004",
          "tgn:7490934",
          "tgn:1000141",
          "tgn:7029392"
        ],
        "placetype": [
          "aat:300008347"
        ],
        "id": 7489889,
        "name:xx": "Dawan"
      }
    }
  ]
}
