{
  "geometry": {
    "type": "Point",
    "coordinates": [
      -106.2167,
      38.45
    ]
  },
  "type": "Feature",
  "properties": {
    "hierarchy": [
      "tgn:2570086",
      "tgn:1000001",
      "tgn:2000199",
      "tgn:7012149",
      "tgn:7007158",
      "tgn:7029392"
    ],
    "placetype": [
      "aat:300008680"
    ],
    "id": 2570086,
    "name:xx": "Pass Creek Lake"
  }
}
