{
  "type": "FeatureCollection",
  "features": [
    {
      "geometry": {
        "type": "Point",
        "coordinates": [
          -76.8167,
          42.3833
        ]
      },
      "type": "Feature",
      "properties": {
        "hierarchy": [
          "tgn:2320670",
          "tgn:1000001",
          "tgn:7012149",
          "tgn:1002875",
          "tgn:7007568",
          "tgn:7029392"
        ],
        "placetype": [
          "aat:300008761"
        ],
        "id": 2320670,
        "name:xx": "Excelsior Glen"
      }
    },
    {
      "geometry": {
        "type": "Point",
        "coordinates": [
          -75.8833,
          44.3667
        ]
      },
      "type": "Feature",
      "properties": {
        "hierarchy": [
          "tgn:2320671",
          "tgn:1000001",
          "tgn:7012149",
          "tgn:1002518",
          "tgn:7007568",
          "tgn:7029392"
        ],
        "placetype": [
          "aat:300008791"
        ],
        "id": 2320671,
        "name:xx": "Excelsior Group"
      }
    },
    {
      "geometry": {
        "type": "Point",
        "coordinates": [
          -106.65,
          38.8
        ]
      },
      "type": "Feature",
      "properties": {
        "hierarchy": [
          "tgn:2320672",
          "tgn:1000001",
          "tgn:7012149",
          "tgn:2000217",
          "tgn:7007158",
          "tgn:7029392"
        ],
        "placetype": [
          "aat:300008761"
        ],
        "id": 2320672,
        "name:xx": "Excelsior Gulch"
      }
    },
    {
      "geometry": {
        "type": "Point",
        "coordinates": [
          -117.4167,
          44.9833
        ]
      },
      "type": "Feature",
      "properties": {
        "hierarchy": [
          "tgn:2320673",
          "tgn:7013349",
          "tgn:1000001",
          "tgn:7012149",
          "tgn:7007708",
          "tgn:7029392"
        ],
        "placetype": [
          "aat:300008761"
        ],
        "id": 2320673,
        "name:xx": "Excelsior Gulch"
      }
    },
    {
      "geometry": {
        "type": "Point",
        "coordinates": [
          -148.6833,
          60.0333
        ]
      },
      "type": "Feature",
      "properties": {
        "hierarchy": [
          "tgn:2320674",
          "tgn:7006450",
          "tgn:1000001",
          "tgn:7019698",
          "tgn:7012149",
          "tgn:7029392"
        ],
        "placetype": [
          "aat:300008680"
        ],
        "id": 2320674,
        "name:xx": "Excelsior Lake"
      }
    },
    {
      "geometry": {
        "type": "Point",
        "coordinates": [
          -91.5333,
          31.3
        ]
      },
      "type": "Feature",
      "properties": {
        "hierarchy": [
          "tgn:2320675",
          "tgn:1000001",
          "tgn:2000868",
          "tgn:7012149",
          "tgn:7007256",
          "tgn:7029392"
        ],
        "placetype": [
          "aat:300008680"
        ],
        "id": 2320675,
        "name:xx": "Excelsior Lake"
      }
    },
    {
      "geometry": {
        "type": "Point",
        "coordinates": [
          -108.75,
          32.3
        ]
      },
      "type": "Feature",
      "properties": {
        "hierarchy": [
          "tgn:2320676",
          "tgn:1000001",
          "tgn:7012149",
          "tgn:2001440",
          "tgn:7007566",
          "tgn:7029392"
        ],
        "placetype": [
          "aat:300000390"
        ],
        "id": 2320676,
        "name:xx": "Excelsior Lode"
      }
    },
    {
      "geometry": {
        "type": "Point",
        "coordinates": [
          -114.1833,
          35.8
        ]
      },
      "type": "Feature",
      "properties": {
        "hierarchy": [
          "tgn:2320678",
          "tgn:1000001",
          "tgn:7006451",
          "tgn:7012149",
          "tgn:2000098",
          "tgn:7029392"
        ],
        "placetype": [
          "aat:300000390"
        ],
        "id": 2320678,
        "name:xx": "Excelsior Mine"
      }
    },
    {
      "geometry": {
        "type": "Point",
        "coordinates": [
          -120.5,
          39.3833
        ]
      },
      "type": "Feature",
      "properties": {
        "hierarchy": [
          "tgn:2320679",
          "tgn:1000001",
          "tgn:7012149",
          "tgn:7007157",
          "tgn:1002710",
          "tgn:7029392"
        ],
        "placetype": [
          "aat:300000390"
        ],
        "id": 2320679,
        "name:xx": "Excelsior Mine"
      }
    }
  ]
}
