{
  "geometry": {
    "type": "Point",
    "coordinates": [
      -92.0167,
      44.5833
    ]
  },
  "type": "Feature",
  "properties": {
    "hierarchy": [
      "tgn:2663030",
      "tgn:1000001",
      "tgn:7012149",
      "tgn:2002344",
      "tgn:7007922",
      "tgn:7029392"
    ],
    "placetype": [
      "aat:300008680"
    ],
    "id": 2663030,
    "name:xx": "Silver Birch Lake"
  }
}
