{
  "geometry": {
    "type": "Point",
    "coordinates": [
      4.4833,
      48.2333
    ]
  },
  "type": "Feature",
  "properties": {
    "hierarchy": [
      "tgn:1036049",
      "tgn:1000003",
      "tgn:7002880",
      "tgn:1000070",
      "tgn:7029392"
    ],
    "placetype": [
      "aat:300008347"
    ],
    "id": 1036049,
    "name:xx": "Vendeuvre-sur-Barse"
  }
}
