{
  "geometry": {
    "type": "Point",
    "coordinates": [
      -120.8667,
      37.6833
    ]
  },
  "type": "Feature",
  "properties": {
    "hierarchy": [
      "tgn:2718486",
      "tgn:1000001",
      "tgn:7012149",
      "tgn:7007157",
      "tgn:1002915",
      "tgn:7029392"
    ],
    "placetype": [
      "aat:300006075"
    ],
    "id": 2718486,
    "name:xx": "Thompson Lateral"
  }
}
