{
  "geometry": {
    "type": "Point",
    "coordinates": [
      40.4333,
      35.1667
    ]
  },
  "type": "Feature",
  "properties": {
    "hierarchy": [
      "tgn:1085118",
      "tgn:1002075",
      "tgn:1000004",
      "tgn:1000140",
      "tgn:7029392"
    ],
    "placetype": [
      "aat:300008347"
    ],
    "id": 1085118,
    "name:xx": "Buṣayrah"
  }
}
