{
  "geometry": {
    "type": "Point",
    "coordinates": [
      116.05,
      -33.1333
    ]
  },
  "type": "Feature",
  "properties": {
    "hierarchy": [
      "tgn:1120517",
      "tgn:7000490",
      "tgn:1000006",
      "tgn:7001834",
      "tgn:7029392"
    ],
    "placetype": [
      "aat:300006191"
    ],
    "id": 1120517,
    "name:xx": "Stirling Reservoir"
  }
}
