{
  "geometry": {
    "type": "Point",
    "coordinates": [
      -86.75,
      38.6833
    ]
  },
  "type": "Feature",
  "properties": {
    "hierarchy": [
      "tgn:2403240",
      "tgn:1000001",
      "tgn:7012149",
      "tgn:2000546",
      "tgn:7007252",
      "tgn:7029392"
    ],
    "placetype": [
      "aat:300008699"
    ],
    "id": 2403240,
    "name:xx": "House Rock Branch"
  }
}
