{
  "type": "FeatureCollection",
  "features": [
    {
      "geometry": {
        "type": "Point",
        "coordinates": [
          -71.8833,
          41.3167
        ]
      },
      "type": "Feature",
      "properties": {
        "hierarchy": [
          "tgn:2643520",
          "tgn:1000001",
          "tgn:1002714",
          "tgn:7012149",
          "tgn:7007159",
          "tgn:7029392"
        ],
        "placetype": [
          "aat:300008791"
        ],
        "id": 2643520,
        "name:xx": "Sandy Point"
      }
    },
    {
      "geometry": {
        "type": "Point",
        "coordinates": [
          -75.3667,
          39.0333
        ]
      },
      "type": "Feature",
      "properties": {
        "hierarchy": [
          "tgn:2643521",
          "tgn:1002538",
          "tgn:1000001",
          "tgn:7012149",
          "tgn:7007239",
          "tgn:7029392"
        ],
        "placetype": [
          "aat:300008850"
        ],
        "id": 2643521,
        "name:xx": "Sandy Point"
      }
    },
    {
      "geometry": {
        "type": "Point",
        "coordinates": [
          -81.0167,
          24.7
        ]
      },
      "type": "Feature",
      "properties": {
        "hierarchy": [
          "tgn:2643522",
          "tgn:1000001",
          "tgn:7012149",
          "tgn:1002676",
          "tgn:7007240",
          "tgn:7029392"
        ],
        "placetype": [
          "aat:300008850"
        ],
        "id": 2643522,
        "name:xx": "Sandy Point"
      }
    },
    {
      "geometry": {
        "type": "Point",
        "coordinates": [
          -82.7,
          28.0833
        ]
      },
      "type": "Feature",
      "properties": {
        "hierarchy": [
          "tgn:2643523",
          "tgn:1000001",
          "tgn:7012149",
          "tgn:1002790",
          "tgn:7007240",
          "tgn:7029392"
        ],
        "placetype": [
          "aat:300008850"
        ],
        "id": 2643523,
        "name:xx": "Sandy Point"
      }
    },
    {
      "geometry": {
        "type": "Point",
        "coordinates": [
          -82.85,
          29.9
        ]
      },
      "type": "Feature",
      "properties": {
        "hierarchy": [
          "tgn:2643524",
          "tgn:1000001",
          "tgn:7012149",
          "tgn:2000286",
          "tgn:7007240",
          "tgn:7029392"
        ],
        "placetype": [
          "aat:300008347"
        ],
        "id": 2643524,
        "name:xx": "Sandy Point"
      }
    },
    {
      "geometry": {
        "type": "Point",
        "coordinates": [
          -83.9333,
          32.7667
        ]
      },
      "type": "Feature",
      "properties": {
        "hierarchy": [
          "tgn:2643525",
          "tgn:1000001",
          "tgn:7012149",
          "tgn:2000330",
          "tgn:7007248",
          "tgn:7029392"
        ],
        "placetype": [
          "aat:300008347"
        ],
        "id": 2643525,
        "name:xx": "Sandy Point"
      }
    },
    {
      "geometry": {
        "type": "Point",
        "coordinates": [
          -89.4833,
          29.2
        ]
      },
      "type": "Feature",
      "properties": {
        "hierarchy": [
          "tgn:2643526",
          "tgn:1000001",
          "tgn:7012149",
          "tgn:2000891",
          "tgn:7007256",
          "tgn:7029392"
        ],
        "placetype": [
          "aat:300008850"
        ],
        "id": 2643526,
        "name:xx": "Sandy Point"
      }
    },
    {
      "geometry": {
        "type": "Point",
        "coordinates": [
          -91.6,
          29.9833
        ]
      },
      "type": "Feature",
      "properties": {
        "hierarchy": [
          "tgn:2643527",
          "tgn:1000001",
          "tgn:7012149",
          "tgn:2000876",
          "tgn:7007256",
          "tgn:7029392"
        ],
        "placetype": [
          "aat:300008850"
        ],
        "id": 2643527,
        "name:xx": "Sandy Point"
      }
    },
    {
      "geometry": {
        "type": "Point",
        "coordinates": [
          -93.0167,
          31.9333
        ]
      },
      "type": "Feature",
      "properties": {
        "hierarchy": [
          "tgn:2643528",
          "tgn:1000001",
          "tgn:7012149",
          "tgn:2000888",
          "tgn:7007256",
          "tgn:7029392"
        ],
        "placetype": [
          "aat:300008850"
        ],
        "id": 2643528,
        "name:xx": "Sandy Point"
      }
    },
    {
      "geometry": {
        "type": "Point",
        "coordinates": [
          -70.1333,
          43.7667
        ]
      },
      "type": "Feature",
      "properties": {
        "hierarchy": [
          "tgn:2643529",
          "tgn:1000001",
          "tgn:2000920",
          "tgn:7012149",
          "tgn:7007515",
          "tgn:7029392"
        ],
        "placetype": [
          "aat:300008850"
        ],
        "id": 2643529,
        "name:xx": "Sandy Point"
      }
    }
  ]
}
