{
  "type": "FeatureCollection",
  "features": [
    {
      "geometry": {
        "type": "Point",
        "coordinates": [
          3.230344,
          50.923802
        ]
      },
      "type": "Feature",
      "properties": {
        "hierarchy": [
          "tgn:7240260",
          "tgn:7003458",
          "tgn:1000003",
          "tgn:1000063",
          "tgn:7018236",
          "tgn:7029392"
        ],
        "placetype": [
          "aat:300008347"
        ],
        "id": 7240260,
        "name:xx": "Emelgem"
      }
    },
    {
      "geometry": {
        "type": "Point",
        "coordinates": [
          5.816667,
          50.316667
        ]
      },
      "type": "Feature",
      "properties": {
        "hierarchy": [
          "tgn:7240262",
          "tgn:7003465",
          "tgn:1000003",
          "tgn:1000063",
          "tgn:4012014",
          "tgn:7029392"
        ],
        "placetype": [
          "aat:300008347"
        ],
        "id": 7240262,
        "name:xx": "Emcômont"
      }
    },
    {
      "geometry": {
        "type": "Point",
        "coordinates": [
          5.616667,
          50.583333
        ]
      },
      "type": "Feature",
      "properties": {
        "hierarchy": [
          "tgn:7240263",
          "tgn:7003460",
          "tgn:1000003",
          "tgn:1000063",
          "tgn:4012014",
          "tgn:7029392"
        ],
        "placetype": [
          "aat:300006909"
        ],
        "id": 7240263,
        "name:xx": "Fort d' Embourg"
      }
    },
    {
      "geometry": {
        "type": "Point",
        "coordinates": [
          5.6,
          50.583333
        ]
      },
      "type": "Feature",
      "properties": {
        "hierarchy": [
          "tgn:7240264",
          "tgn:7003460",
          "tgn:1000003",
          "tgn:1000063",
          "tgn:4012014",
          "tgn:7029392"
        ],
        "placetype": [
          "aat:300008863"
        ],
        "id": 7240264,
        "name:xx": "Embourg, Bois d'"
      }
    },
    {
      "geometry": {
        "type": "Point",
        "coordinates": [
          5.6,
          50.6
        ]
      },
      "type": "Feature",
      "properties": {
        "hierarchy": [
          "tgn:7240265",
          "tgn:7003460",
          "tgn:1000003",
          "tgn:1000063",
          "tgn:4012014",
          "tgn:7029392"
        ],
        "placetype": [
          "aat:300008347"
        ],
        "id": 7240265,
        "name:xx": "Embourg"
      }
    },
    {
      "geometry": {
        "type": "Point",
        "coordinates": [
          5.1,
          50.333333
        ]
      },
      "type": "Feature",
      "properties": {
        "hierarchy": [
          "tgn:7240267",
          "tgn:7003466",
          "tgn:1000003",
          "tgn:1000063",
          "tgn:4012014",
          "tgn:7029392"
        ],
        "placetype": [
          "aat:300008347"
        ],
        "id": 7240267,
        "name:xx": "Emblinne"
      }
    },
    {
      "geometry": {
        "type": "Point",
        "coordinates": [
          4.604854,
          51.162384
        ]
      },
      "type": "Feature",
      "properties": {
        "hierarchy": [
          "tgn:7240268",
          "tgn:7003456",
          "tgn:1000003",
          "tgn:1000063",
          "tgn:7018236",
          "tgn:7029392"
        ],
        "placetype": [
          "aat:300008347"
        ],
        "id": 7240268,
        "name:xx": "Emblem"
      }
    }
  ]
}
