{
  "geometry": {
    "type": "Point",
    "coordinates": [
      -122.8167,
      48.9333
    ]
  },
  "type": "Feature",
  "properties": {
    "hierarchy": [
      "tgn:2173589",
      "tgn:1000001",
      "tgn:7012149",
      "tgn:1003020",
      "tgn:7007920",
      "tgn:7029392"
    ],
    "placetype": [
      "aat:300008850"
    ],
    "id": 2173589,
    "name:xx": "Birch Point"
  }
}
