{
  "type": "FeatureCollection",
  "features": [
    {
      "geometry": {
        "type": "Point",
        "coordinates": [
          -85.5667,
          32.85
        ]
      },
      "type": "Feature",
      "properties": {
        "hierarchy": [
          "tgn:2263410",
          "tgn:7002659",
          "tgn:1000001",
          "tgn:2000008",
          "tgn:7012149",
          "tgn:7029392"
        ],
        "placetype": [
          "aat:300006191"
        ],
        "id": 2263410,
        "name:xx": "Cox Lake"
      }
    },
    {
      "geometry": {
        "type": "Point",
        "coordinates": [
          -92.6333,
          35.1167
        ]
      },
      "type": "Feature",
      "properties": {
        "hierarchy": [
          "tgn:2263411",
          "tgn:1000001",
          "tgn:7016172",
          "tgn:2000119",
          "tgn:7012149",
          "tgn:7029392"
        ],
        "placetype": [
          "aat:300008905"
        ],
        "id": 2263411,
        "name:xx": "Cox Lake"
      }
    },
    {
      "geometry": {
        "type": "Point",
        "coordinates": [
          -93.95,
          33.4833
        ]
      },
      "type": "Feature",
      "properties": {
        "hierarchy": [
          "tgn:2263412",
          "tgn:1000001",
          "tgn:7016172",
          "tgn:7012149",
          "tgn:2000150",
          "tgn:7029392"
        ],
        "placetype": [
          "aat:300006191"
        ],
        "id": 2263412,
        "name:xx": "Cox Lake"
      }
    },
    {
      "geometry": {
        "type": "Point",
        "coordinates": [
          -81.4667,
          26.25
        ]
      },
      "type": "Feature",
      "properties": {
        "hierarchy": [
          "tgn:2263415",
          "tgn:1000001",
          "tgn:1002289",
          "tgn:7012149",
          "tgn:7007240",
          "tgn:7029392"
        ],
        "placetype": [
          "aat:300008680"
        ],
        "id": 2263415,
        "name:xx": "Cox Lake"
      }
    },
    {
      "geometry": {
        "type": "Point",
        "coordinates": [
          -84.2833,
          34.4167
        ]
      },
      "type": "Feature",
      "properties": {
        "hierarchy": [
          "tgn:2263416",
          "tgn:1000001",
          "tgn:7012149",
          "tgn:2000403",
          "tgn:7007248",
          "tgn:7029392"
        ],
        "placetype": [
          "aat:300008680"
        ],
        "id": 2263416,
        "name:xx": "Cox Lake"
      }
    },
    {
      "geometry": {
        "type": "Point",
        "coordinates": [
          -84.7,
          33.3333
        ]
      },
      "type": "Feature",
      "properties": {
        "hierarchy": [
          "tgn:2263417",
          "tgn:1000001",
          "tgn:7012149",
          "tgn:2000329",
          "tgn:7007248",
          "tgn:7029392"
        ],
        "placetype": [
          "aat:300006191"
        ],
        "id": 2263417,
        "name:xx": "Cox Lake"
      }
    },
    {
      "geometry": {
        "type": "Point",
        "coordinates": [
          -83.3833,
          34.9
        ]
      },
      "type": "Feature",
      "properties": {
        "hierarchy": [
          "tgn:2263418",
          "tgn:1000001",
          "tgn:7012149",
          "tgn:2000410",
          "tgn:7007248",
          "tgn:7029392"
        ],
        "placetype": [
          "aat:300006191"
        ],
        "id": 2263418,
        "name:xx": "Cox Lake"
      }
    },
    {
      "geometry": {
        "type": "Point",
        "coordinates": [
          -84.2833,
          34.4167
        ]
      },
      "type": "Feature",
      "properties": {
        "hierarchy": [
          "tgn:2263419",
          "tgn:1000001",
          "tgn:7012149",
          "tgn:2000403",
          "tgn:7007248",
          "tgn:7029392"
        ],
        "placetype": [
          "aat:300006191"
        ],
        "id": 2263419,
        "name:xx": "Cox Lake"
      }
    }
  ]
}
