{
  "geometry": {
    "type": "Point",
    "coordinates": [
      -116.9667,
      45.7167
    ]
  },
  "type": "Feature",
  "properties": {
    "hierarchy": [
      "tgn:2227767",
      "tgn:1000001",
      "tgn:7012149",
      "tgn:2001722",
      "tgn:7007708",
      "tgn:7029392"
    ],
    "placetype": [
      "aat:300266640"
    ],
    "id": 2227767,
    "name:xx": "Cayuse Ridge"
  }
}
