{
  "geometry": {
    "type": "Point",
    "coordinates": [
      -90.85,
      39.4833
    ]
  },
  "type": "Feature",
  "properties": {
    "hierarchy": [
      "tgn:2297369",
      "tgn:1000001",
      "tgn:7012149",
      "tgn:1002786",
      "tgn:7007251",
      "tgn:7029392"
    ],
    "placetype": [
      "aat:300008699"
    ],
    "id": 2297369,
    "name:xx": "Dry Fork"
  }
}
