{
  "geometry": {
    "type": "Point",
    "coordinates": [
      -106.6833,
      36.0167
    ]
  },
  "type": "Feature",
  "properties": {
    "hierarchy": [
      "tgn:2574682",
      "tgn:1000001",
      "tgn:7012149",
      "tgn:7007566",
      "tgn:7029392"
    ],
    "placetype": [
      "aat:300008699"
    ],
    "id": 2574682,
    "name:xx": "Peñas Negras, Rito"
  }
}
