{
  "type": "FeatureCollection",
  "features": [
    {
      "geometry": {
        "type": "Point",
        "coordinates": [
          11.766667,
          53.883333
        ]
      },
      "type": "Feature",
      "properties": {
        "hierarchy": [
          "tgn:7161720",
          "tgn:1000003",
          "tgn:7000094",
          "tgn:7000084",
          "tgn:7029392"
        ],
        "placetype": [
          "aat:300008777"
        ],
        "id": 7161720,
        "name:xx": "Hohe Berg"
      }
    },
    {
      "geometry": {
        "type": "Point",
        "coordinates": [
          11.716667,
          53.483333
        ]
      },
      "type": "Feature",
      "properties": {
        "hierarchy": [
          "tgn:7161721",
          "tgn:1000003",
          "tgn:7000094",
          "tgn:7000084",
          "tgn:7029392"
        ],
        "placetype": [
          "aat:300008777"
        ],
        "id": 7161721,
        "name:xx": "Hohe Berg"
      }
    },
    {
      "geometry": {
        "type": "Point",
        "coordinates": [
          13.2,
          53.45
        ]
      },
      "type": "Feature",
      "properties": {
        "hierarchy": [
          "tgn:7161722",
          "tgn:1000003",
          "tgn:7000094",
          "tgn:7000084",
          "tgn:7029392"
        ],
        "placetype": [
          "aat:300008777"
        ],
        "id": 7161722,
        "name:xx": "Hohe-Berg"
      }
    },
    {
      "geometry": {
        "type": "Point",
        "coordinates": [
          13.966667,
          53.25
        ]
      },
      "type": "Feature",
      "properties": {
        "hierarchy": [
          "tgn:7161723",
          "tgn:7000096",
          "tgn:1000003",
          "tgn:7000084",
          "tgn:7029392"
        ],
        "placetype": [
          "aat:300008777"
        ],
        "id": 7161723,
        "name:xx": "Hohe Berg"
      }
    },
    {
      "geometry": {
        "type": "Point",
        "coordinates": [
          13.3,
          52.916667
        ]
      },
      "type": "Feature",
      "properties": {
        "hierarchy": [
          "tgn:7161724",
          "tgn:7000096",
          "tgn:1000003",
          "tgn:7000084",
          "tgn:7029392"
        ],
        "placetype": [
          "aat:300008777"
        ],
        "id": 7161724,
        "name:xx": "Hohe-Berg"
      }
    },
    {
      "geometry": {
        "type": "Point",
        "coordinates": [
          7.416667,
          51.95
        ]
      },
      "type": "Feature",
      "properties": {
        "hierarchy": [
          "tgn:7161725",
          "tgn:1000003",
          "tgn:7003677",
          "tgn:7000084",
          "tgn:7029392"
        ],
        "placetype": [
          "aat:300008777"
        ],
        "id": 7161725,
        "name:xx": "Hohe Berg"
      }
    },
    {
      "geometry": {
        "type": "Point",
        "coordinates": [
          9.866667,
          51.633333
        ]
      },
      "type": "Feature",
      "properties": {
        "hierarchy": [
          "tgn:7161726",
          "tgn:1000003",
          "tgn:7003676",
          "tgn:7000084",
          "tgn:7029392"
        ],
        "placetype": [
          "aat:300008777"
        ],
        "id": 7161726,
        "name:xx": "Höhe-Berg"
      }
    },
    {
      "geometry": {
        "type": "Point",
        "coordinates": [
          9.233333,
          51.15
        ]
      },
      "type": "Feature",
      "properties": {
        "hierarchy": [
          "tgn:7161727",
          "tgn:1000003",
          "tgn:7003678",
          "tgn:7000084",
          "tgn:7029392"
        ],
        "placetype": [
          "aat:300008777"
        ],
        "id": 7161727,
        "name:xx": "Hohe Berg"
      }
    },
    {
      "geometry": {
        "type": "Point",
        "coordinates": [
          9.166667,
          51
        ]
      },
      "type": "Feature",
      "properties": {
        "hierarchy": [
          "tgn:7161729",
          "tgn:1000003",
          "tgn:7003678",
          "tgn:7000084",
          "tgn:7029392"
        ],
        "placetype": [
          "aat:300008777"
        ],
        "id": 7161729,
        "name:xx": "Hohe Berg"
      }
    }
  ]
}
