{
  "type": "FeatureCollection",
  "features": [
    {
      "geometry": {
        "type": "Point",
        "coordinates": [
          -79.3833,
          39.65
        ]
      },
      "type": "Feature",
      "properties": {
        "hierarchy": [
          "tgn:2361210",
          "tgn:1000001",
          "tgn:2000935",
          "tgn:7012149",
          "tgn:7007516",
          "tgn:7029392"
        ],
        "placetype": [
          "aat:300008347"
        ],
        "id": 2361210,
        "name:xx": "Gravel Hill"
      }
    },
    {
      "geometry": {
        "type": "Point",
        "coordinates": [
          -78.9667,
          39.7
        ]
      },
      "type": "Feature",
      "properties": {
        "hierarchy": [
          "tgn:2361211",
          "tgn:1000001",
          "tgn:2000935",
          "tgn:7012149",
          "tgn:7007516",
          "tgn:7029392"
        ],
        "placetype": [
          "aat:300008798"
        ],
        "id": 2361211,
        "name:xx": "Gravel Hill"
      }
    },
    {
      "geometry": {
        "type": "Point",
        "coordinates": [
          -89.8333,
          37.35
        ]
      },
      "type": "Feature",
      "properties": {
        "hierarchy": [
          "tgn:2361212",
          "tgn:1000001",
          "tgn:2001179",
          "tgn:7012149",
          "tgn:7007523",
          "tgn:7029392"
        ],
        "placetype": [
          "aat:300008347"
        ],
        "id": 2361212,
        "name:xx": "Gravel Hill"
      }
    },
    {
      "geometry": {
        "type": "Point",
        "coordinates": [
          -105.6667,
          46.2
        ]
      },
      "type": "Feature",
      "properties": {
        "hierarchy": [
          "tgn:2361213",
          "tgn:1000001",
          "tgn:2001268",
          "tgn:7012149",
          "tgn:7007524",
          "tgn:7029392"
        ],
        "placetype": [
          "aat:300008798"
        ],
        "id": 2361213,
        "name:xx": "Gravel Hill"
      }
    },
    {
      "geometry": {
        "type": "Point",
        "coordinates": [
          -75.1333,
          40.5833
        ]
      },
      "type": "Feature",
      "properties": {
        "hierarchy": [
          "tgn:2361214",
          "tgn:1000001",
          "tgn:1002493",
          "tgn:7012149",
          "tgn:7007565",
          "tgn:7029392"
        ],
        "placetype": [
          "aat:300008798"
        ],
        "id": 2361214,
        "name:xx": "Gravel Hill"
      }
    },
    {
      "geometry": {
        "type": "Point",
        "coordinates": [
          -82.8667,
          38.9667
        ]
      },
      "type": "Feature",
      "properties": {
        "hierarchy": [
          "tgn:2361215",
          "tgn:1000001",
          "tgn:7012149",
          "tgn:1002788",
          "tgn:7007706",
          "tgn:7029392"
        ],
        "placetype": [
          "aat:300008798"
        ],
        "id": 2361215,
        "name:xx": "Gravel Hill"
      }
    },
    {
      "geometry": {
        "type": "Point",
        "coordinates": [
          -79.1667,
          40.2333
        ]
      },
      "type": "Feature",
      "properties": {
        "hierarchy": [
          "tgn:2361216",
          "tgn:1000001",
          "tgn:7012149",
          "tgn:1003017",
          "tgn:7007710",
          "tgn:7029392"
        ],
        "placetype": [
          "aat:300008798"
        ],
        "id": 2361216,
        "name:xx": "Gravel Hill"
      }
    },
    {
      "geometry": {
        "type": "Point",
        "coordinates": [
          -76.6,
          40.3167
        ]
      },
      "type": "Feature",
      "properties": {
        "hierarchy": [
          "tgn:2361217",
          "tgn:1000001",
          "tgn:7012149",
          "tgn:1002581",
          "tgn:7007710",
          "tgn:7029392"
        ],
        "placetype": [
          "aat:300008347"
        ],
        "id": 2361217,
        "name:xx": "Gravel Hill"
      }
    },
    {
      "geometry": {
        "type": "Point",
        "coordinates": [
          -80.9667,
          33.4667
        ]
      },
      "type": "Feature",
      "properties": {
        "hierarchy": [
          "tgn:2361218",
          "tgn:1000001",
          "tgn:7012149",
          "tgn:2001762",
          "tgn:7007712",
          "tgn:7029392"
        ],
        "placetype": [
          "aat:300008347"
        ],
        "id": 2361218,
        "name:xx": "Gravel Hill"
      }
    },
    {
      "geometry": {
        "type": "Point",
        "coordinates": [
          -81.3667,
          32.95
        ]
      },
      "type": "Feature",
      "properties": {
        "hierarchy": [
          "tgn:2361219",
          "tgn:2001727",
          "tgn:1000001",
          "tgn:7012149",
          "tgn:7007712",
          "tgn:7029392"
        ],
        "placetype": [
          "aat:300008798"
        ],
        "id": 2361219,
        "name:xx": "Gravel Hill"
      }
    }
  ]
}
