{
  "geometry": {
    "type": "Point",
    "coordinates": [
      -99.5833,
      37.1667
    ]
  },
  "type": "Feature",
  "properties": {
    "hierarchy": [
      "tgn:2701707",
      "tgn:1000001",
      "tgn:2000672",
      "tgn:7012149",
      "tgn:7007254",
      "tgn:7029392"
    ],
    "placetype": [
      "aat:300008798"
    ],
    "id": 2701707,
    "name:xx": "Sugarloaf"
  }
}
