{
  "geometry": {
    "type": "Point",
    "coordinates": [
      -96.6667,
      47.2667
    ]
  },
  "type": "Feature",
  "properties": {
    "hierarchy": [
      "tgn:2260974",
      "tgn:1000001",
      "tgn:7012149",
      "tgn:2001052",
      "tgn:7007521",
      "tgn:7029392"
    ],
    "placetype": [
      "aat:300006075"
    ],
    "id": 2260974,
    "name:xx": "County Ditch Number Thirtyone"
  }
}
