{
  "geometry": {
    "type": "Point",
    "coordinates": [
      -147.1167,
      61.4167
    ]
  },
  "type": "Feature",
  "properties": {
    "hierarchy": [
      "tgn:2316504",
      "tgn:7006450",
      "tgn:1000001",
      "tgn:7012149",
      "tgn:2000086",
      "tgn:7029392"
    ],
    "placetype": [
      "aat:300008798"
    ],
    "id": 2316504,
    "name:xx": "Elusive, Mount"
  }
}
