{
  "geometry": {
    "type": "Point",
    "coordinates": [
      -71.3167,
      41.8833
    ]
  },
  "type": "Feature",
  "properties": {
    "hierarchy": [
      "tgn:2714617",
      "tgn:1002201",
      "tgn:1000001",
      "tgn:7012149",
      "tgn:7007517",
      "tgn:7029392"
    ],
    "placetype": [
      "aat:300006191"
    ],
    "id": 2714617,
    "name:xx": "Ten Mile River Reservoir"
  }
}
