{
  "geometry": {
    "type": "Point",
    "coordinates": [
      152.7667,
      -25.3167
    ]
  },
  "type": "Feature",
  "properties": {
    "hierarchy": [
      "tgn:1098403",
      "tgn:7000490",
      "tgn:1000006",
      "tgn:7001830",
      "tgn:7029392"
    ],
    "placetype": [
      "aat:300008347"
    ],
    "id": 1098403,
    "name:xx": "Urangan"
  }
}
