{
  "geometry": {
    "type": "Point",
    "coordinates": [
      -111.15,
      39.1833
    ]
  },
  "type": "Feature",
  "properties": {
    "hierarchy": [
      "tgn:2437058",
      "tgn:1000001",
      "tgn:2002108",
      "tgn:7012149",
      "tgn:7007827",
      "tgn:7029392"
    ],
    "placetype": [
      "aat:300000390"
    ],
    "id": 2437058,
    "name:xx": "Killpack Mine"
  }
}
