{
  "type": "FeatureCollection",
  "features": [
    {
      "geometry": {
        "type": "Point",
        "coordinates": [
          -79.1833,
          40.2
        ]
      },
      "type": "Feature",
      "properties": {
        "hierarchy": [
          "tgn:2089991",
          "tgn:1000001",
          "tgn:7012149",
          "tgn:1003017",
          "tgn:7007710",
          "tgn:7029392"
        ],
        "placetype": [
          "aat:300008347"
        ],
        "id": 2089991,
        "name:xx": "Laughlintown"
      }
    },
    {
      "geometry": {
        "type": "Point",
        "coordinates": [
          -76.5,
          39.8167
        ]
      },
      "type": "Feature",
      "properties": {
        "hierarchy": [
          "tgn:2089993",
          "tgn:1000001",
          "tgn:7012149",
          "tgn:1003047",
          "tgn:7007710",
          "tgn:7029392"
        ],
        "placetype": [
          "aat:300008347"
        ],
        "id": 2089993,
        "name:xx": "Laurel"
      }
    },
    {
      "geometry": {
        "type": "Point",
        "coordinates": [
          -75.9167,
          40.3833
        ]
      },
      "type": "Feature",
      "properties": {
        "hierarchy": [
          "tgn:2089994",
          "tgn:1000001",
          "tgn:7013387",
          "tgn:7012149",
          "tgn:7007710",
          "tgn:7029392"
        ],
        "placetype": [
          "aat:300008347"
        ],
        "id": 2089994,
        "name:xx": "Laureldale"
      }
    },
    {
      "geometry": {
        "type": "Point",
        "coordinates": [
          -79.1167,
          39.8167
        ]
      },
      "type": "Feature",
      "properties": {
        "hierarchy": [
          "tgn:2089995",
          "tgn:1000001",
          "tgn:7012149",
          "tgn:1002904",
          "tgn:7007710",
          "tgn:7029392"
        ],
        "placetype": [
          "aat:300008347"
        ],
        "id": 2089995,
        "name:xx": "Laurel Falls"
      }
    },
    {
      "geometry": {
        "type": "Point",
        "coordinates": [
          -79.7,
          39.9667
        ]
      },
      "type": "Feature",
      "properties": {
        "hierarchy": [
          "tgn:2089996",
          "tgn:1000001",
          "tgn:7012149",
          "tgn:7014185",
          "tgn:7007710",
          "tgn:7029392"
        ],
        "placetype": [
          "aat:300008347",
          "aat:300387210"
        ],
        "id": 2089996,
        "name:xx": "Laurel Hill"
      }
    },
    {
      "geometry": {
        "type": "Point",
        "coordinates": [
          -75.9167,
          41.95
        ]
      },
      "type": "Feature",
      "properties": {
        "hierarchy": [
          "tgn:2089998",
          "tgn:1000001",
          "tgn:7012149",
          "tgn:1002932",
          "tgn:7007710",
          "tgn:7029392"
        ],
        "placetype": [
          "aat:300008347"
        ],
        "id": 2089998,
        "name:xx": "Laurel Lake"
      }
    }
  ]
}
