{
  "geometry": {
    "type": "Point",
    "coordinates": [
      31.413713,
      31.026895
    ]
  },
  "type": "Feature",
  "properties": {
    "hierarchy": [
      "tgn:7537471",
      "tgn:7001242",
      "tgn:1001059",
      "tgn:7016833",
      "tgn:7029392"
    ],
    "placetype": [
      "aat:300008347"
    ],
    "name:en": "Mīt aş Şārim",
    "id": 7537471
  }
}
