{
  "geometry": {
    "type": "Point",
    "coordinates": [
      -70.6833,
      42.5833
    ]
  },
  "type": "Feature",
  "properties": {
    "hierarchy": [
      "tgn:2533481",
      "tgn:1000001",
      "tgn:1002359",
      "tgn:7012149",
      "tgn:7007517",
      "tgn:7029392"
    ],
    "placetype": [
      "aat:300008850"
    ],
    "id": 2533481,
    "name:xx": "Mussel Point"
  }
}
