{
  "geometry": {
    "type": "Point",
    "coordinates": [
      76.65,
      9.95
    ]
  },
  "type": "Feature",
  "properties": {
    "hierarchy": [
      "tgn:7581217",
      "tgn:1000004",
      "tgn:7000198",
      "tgn:1001886",
      "tgn:7029392"
    ],
    "placetype": [
      "aat:300008347"
    ],
    "name:en": "Vāzhākulam",
    "id": 7581217
  }
}
