{
  "geometry": {
    "type": "Point",
    "coordinates": [
      -82.6333,
      45.9167
    ]
  },
  "type": "Feature",
  "properties": {
    "hierarchy": [
      "tgn:1006431",
      "tgn:7005685",
      "tgn:1000001",
      "tgn:7013154",
      "tgn:7029392"
    ],
    "placetype": [
      "aat:300008791"
    ],
    "id": 1006431,
    "name:xx": "Barrie Island"
  }
}
