{
  "geometry": {
    "type": "Point",
    "coordinates": [
      -106.5833,
      35.65
    ]
  },
  "type": "Feature",
  "properties": {
    "hierarchy": [
      "tgn:2188085",
      "tgn:1000001",
      "tgn:7012149",
      "tgn:2001451",
      "tgn:7007566",
      "tgn:7029392"
    ],
    "placetype": [
      "aat:300008761"
    ],
    "id": 2188085,
    "name:xx": "Borrego Canyon"
  }
}
