{
  "geometry": {
    "type": "Point",
    "coordinates": [
      -89.9667,
      33.05
    ]
  },
  "type": "Feature",
  "properties": {
    "hierarchy": [
      "tgn:2167752",
      "tgn:1000001",
      "tgn:7012149",
      "tgn:7007522",
      "tgn:7029392"
    ],
    "placetype": [
      "aat:300008706"
    ],
    "id": 2167752,
    "name:xx": "Big Cypress Creek"
  }
}
