{
  "type": "FeatureCollection",
  "features": [
    {
      "geometry": {
        "type": "Point",
        "coordinates": [
          -109.3,
          29.85
        ]
      },
      "type": "Feature",
      "properties": {
        "hierarchy": [
          "tgn:7371240",
          "tgn:1000001",
          "tgn:1001960",
          "tgn:7005560",
          "tgn:7029392"
        ],
        "placetype": [
          "aat:300008347"
        ],
        "id": 7371240,
        "name:xx": "Granados"
      }
    },
    {
      "geometry": {
        "type": "Point",
        "coordinates": [
          -109.316667,
          29.75
        ]
      },
      "type": "Feature",
      "properties": {
        "hierarchy": [
          "tgn:7371241",
          "tgn:1000001",
          "tgn:1001960",
          "tgn:7005560",
          "tgn:7029392"
        ],
        "placetype": [
          "aat:300008347"
        ],
        "id": 7371241,
        "name:xx": "Granados"
      }
    },
    {
      "geometry": {
        "type": "Point",
        "coordinates": [
          -100.216667,
          20.333333
        ]
      },
      "type": "Feature",
      "properties": {
        "hierarchy": [
          "tgn:7371242",
          "tgn:1000001",
          "tgn:7005593",
          "tgn:7005560",
          "tgn:7029392"
        ],
        "placetype": [
          "aat:300008347"
        ],
        "id": 7371242,
        "name:xx": "Granados"
      }
    },
    {
      "geometry": {
        "type": "Point",
        "coordinates": [
          -102.333333,
          19.233333
        ]
      },
      "type": "Feature",
      "properties": {
        "hierarchy": [
          "tgn:7371243",
          "tgn:1000001",
          "tgn:7005590",
          "tgn:7005560",
          "tgn:7029392"
        ],
        "placetype": [
          "aat:300008347"
        ],
        "id": 7371243,
        "name:xx": "Granados"
      }
    },
    {
      "geometry": {
        "type": "Point",
        "coordinates": [
          -96.233333,
          19.266667
        ]
      },
      "type": "Feature",
      "properties": {
        "hierarchy": [
          "tgn:7371244",
          "tgn:1000001",
          "tgn:7005599",
          "tgn:7005560",
          "tgn:7029392"
        ],
        "placetype": [
          "aat:300008699"
        ],
        "id": 7371244,
        "name:xx": "Granado, Río"
      }
    },
    {
      "geometry": {
        "type": "Point",
        "coordinates": [
          -97.6,
          19.816667
        ]
      },
      "type": "Feature",
      "properties": {
        "hierarchy": [
          "tgn:7371245",
          "tgn:1000001",
          "tgn:7005592",
          "tgn:7005560",
          "tgn:7029392"
        ],
        "placetype": [
          "aat:300008347"
        ],
        "id": 7371245,
        "name:xx": "Jilotepec"
      }
    },
    {
      "geometry": {
        "type": "Point",
        "coordinates": [
          -96.933333,
          19.6
        ]
      },
      "type": "Feature",
      "properties": {
        "hierarchy": [
          "tgn:7371246",
          "tgn:1000001",
          "tgn:7005599",
          "tgn:7005560",
          "tgn:7029392"
        ],
        "placetype": [
          "aat:300008347"
        ],
        "id": 7371246,
        "name:xx": "Jilotepec"
      }
    },
    {
      "geometry": {
        "type": "Point",
        "coordinates": [
          -95.766667,
          16.633333
        ]
      },
      "type": "Feature",
      "properties": {
        "hierarchy": [
          "tgn:7371247",
          "tgn:1000001",
          "tgn:7005591",
          "tgn:7005560",
          "tgn:7029392"
        ],
        "placetype": [
          "aat:300008347"
        ],
        "id": 7371247,
        "name:xx": "Jilotepec"
      }
    },
    {
      "geometry": {
        "type": "Point",
        "coordinates": [
          -109.983333,
          28.7
        ]
      },
      "type": "Feature",
      "properties": {
        "hierarchy": [
          "tgn:7371249",
          "tgn:1000001",
          "tgn:1001960",
          "tgn:7005560",
          "tgn:7029392"
        ],
        "placetype": [
          "aat:300008347"
        ],
        "id": 7371249,
        "name:xx": "Iglesia"
      }
    }
  ]
}
