{
  "geometry": {
    "type": "Point",
    "coordinates": [
      -87.8167,
      38.3333
    ]
  },
  "type": "Feature",
  "properties": {
    "hierarchy": [
      "tgn:2029897",
      "tgn:1000001",
      "tgn:7012149",
      "tgn:2000535",
      "tgn:7007251",
      "tgn:7029392"
    ],
    "placetype": [
      "aat:300008347",
      "aat:300387210"
    ],
    "id": 2029897,
    "name:xx": "Rochester"
  }
}
