{
  "geometry": {
    "type": "Point",
    "coordinates": [
      -75.1667,
      -14.0167
    ]
  },
  "type": "Feature",
  "properties": {
    "hierarchy": [
      "tgn:1024392",
      "tgn:1000638",
      "tgn:1000002",
      "tgn:1000056",
      "tgn:7029392"
    ],
    "placetype": [
      "aat:300008347"
    ],
    "id": 1024392,
    "name:xx": "Córdova"
  }
}
