{
  "type": "FeatureCollection",
  "features": [
    {
      "geometry": {
        "type": "Point",
        "coordinates": [
          -86.0167,
          34.5333
        ]
      },
      "type": "Feature",
      "properties": {
        "hierarchy": [
          "tgn:2277680",
          "tgn:7002659",
          "tgn:1000001",
          "tgn:7012149",
          "tgn:2000035",
          "tgn:7029392"
        ],
        "placetype": [
          "aat:300008347"
        ],
        "id": 2277680,
        "name:xx": "Davistown"
      }
    },
    {
      "geometry": {
        "type": "Point",
        "coordinates": [
          -79.5167,
          34.0167
        ]
      },
      "type": "Feature",
      "properties": {
        "hierarchy": [
          "tgn:2277681",
          "tgn:1000001",
          "tgn:2001745",
          "tgn:7012149",
          "tgn:7007712",
          "tgn:7029392"
        ],
        "placetype": [
          "aat:300008347"
        ],
        "id": 2277681,
        "name:xx": "Davistown"
      }
    },
    {
      "geometry": {
        "type": "Point",
        "coordinates": [
          -82.8167,
          37.9667
        ]
      },
      "type": "Feature",
      "properties": {
        "hierarchy": [
          "tgn:2277682",
          "tgn:1000001",
          "tgn:7012149",
          "tgn:2000809",
          "tgn:7007255",
          "tgn:7029392"
        ],
        "placetype": [
          "aat:300008347"
        ],
        "id": 2277682,
        "name:xx": "Davisville"
      }
    },
    {
      "geometry": {
        "type": "Point",
        "coordinates": [
          -88.9667,
          31.95
        ]
      },
      "type": "Feature",
      "properties": {
        "hierarchy": [
          "tgn:2277683",
          "tgn:1000001",
          "tgn:7012149",
          "tgn:2001116",
          "tgn:7007522",
          "tgn:7029392"
        ],
        "placetype": [
          "aat:300008347"
        ],
        "id": 2277683,
        "name:xx": "Davisville"
      }
    },
    {
      "geometry": {
        "type": "Point",
        "coordinates": [
          -71.7833,
          42.85
        ]
      },
      "type": "Feature",
      "properties": {
        "hierarchy": [
          "tgn:2277684",
          "tgn:1000001",
          "tgn:1002480",
          "tgn:7012149",
          "tgn:7007564",
          "tgn:7029392"
        ],
        "placetype": [
          "aat:300008347"
        ],
        "id": 2277684,
        "name:xx": "Davisville"
      }
    },
    {
      "geometry": {
        "type": "Point",
        "coordinates": [
          -75.0333,
          39.7833
        ]
      },
      "type": "Feature",
      "properties": {
        "hierarchy": [
          "tgn:2277685",
          "tgn:1002227",
          "tgn:1000001",
          "tgn:7012149",
          "tgn:7007565",
          "tgn:7029392"
        ],
        "placetype": [
          "aat:300008347"
        ],
        "id": 2277685,
        "name:xx": "Davisville"
      }
    },
    {
      "geometry": {
        "type": "Point",
        "coordinates": [
          -74.6167,
          40.1
        ]
      },
      "type": "Feature",
      "properties": {
        "hierarchy": [
          "tgn:2277686",
          "tgn:1002215",
          "tgn:1000001",
          "tgn:7012149",
          "tgn:7007565",
          "tgn:7029392"
        ],
        "placetype": [
          "aat:300008347"
        ],
        "id": 2277686,
        "name:xx": "Davisville"
      }
    },
    {
      "geometry": {
        "type": "Point",
        "coordinates": [
          -75.05,
          40.1667
        ]
      },
      "type": "Feature",
      "properties": {
        "hierarchy": [
          "tgn:2277687",
          "tgn:1000001",
          "tgn:1002213",
          "tgn:7012149",
          "tgn:7007710",
          "tgn:7029392"
        ],
        "placetype": [
          "aat:300008347"
        ],
        "id": 2277687,
        "name:xx": "Davisville"
      }
    },
    {
      "geometry": {
        "type": "Point",
        "coordinates": [
          -91.2167,
          37.7667
        ]
      },
      "type": "Feature",
      "properties": {
        "hierarchy": [
          "tgn:2277688",
          "tgn:1000001",
          "tgn:7012149",
          "tgn:2001190",
          "tgn:7007523",
          "tgn:7029392"
        ],
        "placetype": [
          "aat:300008761"
        ],
        "id": 2277688,
        "name:xx": "Davisville Hollow"
      }
    },
    {
      "geometry": {
        "type": "Point",
        "coordinates": [
          -71.7333,
          43.2333
        ]
      },
      "type": "Feature",
      "properties": {
        "hierarchy": [
          "tgn:2277689",
          "tgn:1000001",
          "tgn:2001425",
          "tgn:7012149",
          "tgn:7007564",
          "tgn:7029392"
        ],
        "placetype": [
          "aat:300008863"
        ],
        "id": 2277689,
        "name:xx": "Davisville State Forest"
      }
    }
  ]
}
