{
  "geometry": {
    "type": "Point",
    "coordinates": [
      78.016667,
      8.833333
    ]
  },
  "type": "Feature",
  "properties": {
    "hierarchy": [
      "tgn:7579431",
      "tgn:1000004",
      "tgn:7000198",
      "tgn:7001797",
      "tgn:7029392"
    ],
    "placetype": [
      "aat:300007783"
    ],
    "name:en": "Tattappārai",
    "id": 7579431
  }
}
