{
  "geometry": {
    "type": "Point",
    "coordinates": [
      -68.0333,
      46.4167
    ]
  },
  "type": "Feature",
  "properties": {
    "hierarchy": [
      "tgn:2552045",
      "tgn:2000919",
      "tgn:1000001",
      "tgn:7012149",
      "tgn:7007515",
      "tgn:7029392"
    ],
    "placetype": [
      "aat:300008680"
    ],
    "id": 2552045,
    "name:xx": "Number Nine Lake"
  }
}
