{
  "geometry": {
    "type": "Point",
    "coordinates": [
      -104.0667,
      44.35
    ]
  },
  "type": "Feature",
  "properties": {
    "hierarchy": [
      "tgn:2230168",
      "tgn:1000001",
      "tgn:2002370",
      "tgn:7012149",
      "tgn:7007923",
      "tgn:7029392"
    ],
    "placetype": [
      "aat:300266640"
    ],
    "id": 2230168,
    "name:xx": "Cement Ridge"
  }
}
