{
  "geometry": {
    "type": "Point",
    "coordinates": [
      -82.2667,
      29.4667
    ]
  },
  "type": "Feature",
  "properties": {
    "hierarchy": [
      "tgn:2272562",
      "tgn:1000001",
      "tgn:7012149",
      "tgn:1002631",
      "tgn:7007240",
      "tgn:7029392"
    ],
    "placetype": [
      "aat:300008347",
      "aat:300167671"
    ],
    "id": 2272562,
    "name:xx": "Cuscowilla"
  }
}
