{
  "type": "FeatureCollection",
  "features": [
    {
      "geometry": {
        "type": "Point",
        "coordinates": [
          24.433333,
          37.483333
        ]
      },
      "type": "Feature",
      "properties": {
        "hierarchy": [
          "tgn:7232070",
          "tgn:7002681",
          "tgn:7001395",
          "tgn:1000003",
          "tgn:1000074",
          "tgn:7029392"
        ],
        "placetype": [
          "aat:300008850"
        ],
        "id": 7232070,
        "name:xx": "Kéfalos, Ákra"
      }
    },
    {
      "geometry": {
        "type": "Point",
        "coordinates": [
          25.283333,
          37.066667
        ]
      },
      "type": "Feature",
      "properties": {
        "hierarchy": [
          "tgn:7232071",
          "tgn:7011270",
          "tgn:7002674",
          "tgn:1000003",
          "tgn:1000074",
          "tgn:7029392"
        ],
        "placetype": [
          "aat:300008850"
        ],
        "id": 7232071,
        "name:xx": "Kéfalos, Ákra"
      }
    },
    {
      "geometry": {
        "type": "Point",
        "coordinates": [
          27.516667,
          36.233333
        ]
      },
      "type": "Feature",
      "properties": {
        "hierarchy": [
          "tgn:7232072",
          "tgn:7011330",
          "tgn:7002674",
          "tgn:1000003",
          "tgn:1000074",
          "tgn:7029392"
        ],
        "placetype": [
          "aat:300008850"
        ],
        "id": 7232072,
        "name:xx": "Kéfalos, Ákra"
      }
    },
    {
      "geometry": {
        "type": "Point",
        "coordinates": [
          25.266667,
          37.066667
        ]
      },
      "type": "Feature",
      "properties": {
        "hierarchy": [
          "tgn:7232074",
          "tgn:7011270",
          "tgn:7002674",
          "tgn:1000003",
          "tgn:1000074",
          "tgn:7029392"
        ],
        "placetype": [
          "aat:300008777"
        ],
        "id": 7232074,
        "name:xx": "Kéfalos"
      }
    },
    {
      "geometry": {
        "type": "Point",
        "coordinates": [
          23.283333,
          40.983333
        ]
      },
      "type": "Feature",
      "properties": {
        "hierarchy": [
          "tgn:7232075",
          "tgn:7002725",
          "tgn:7002715",
          "tgn:1000003",
          "tgn:1000074",
          "tgn:7029392"
        ],
        "placetype": [
          "aat:300008347"
        ],
        "id": 7232075,
        "name:xx": "Kefalokhórion"
      }
    },
    {
      "geometry": {
        "type": "Point",
        "coordinates": [
          22.365278,
          40.568333
        ]
      },
      "type": "Feature",
      "properties": {
        "hierarchy": [
          "tgn:7232076",
          "tgn:7002718",
          "tgn:7002715",
          "tgn:1000003",
          "tgn:1000074",
          "tgn:7029392"
        ],
        "placetype": [
          "aat:300008347"
        ],
        "id": 7232076,
        "name:xx": "Kefalochórion"
      }
    },
    {
      "geometry": {
        "type": "Point",
        "coordinates": [
          23.683333,
          35.3
        ]
      },
      "type": "Feature",
      "properties": {
        "hierarchy": [
          "tgn:7232079",
          "tgn:7002690",
          "tgn:7012056",
          "tgn:1000003",
          "tgn:1000074",
          "tgn:7029392"
        ],
        "placetype": [
          "aat:300008347"
        ],
        "id": 7232079,
        "name:xx": "Kefálion"
      }
    }
  ]
}
