{
  "type": "FeatureCollection",
  "features": [
    {
      "geometry": {
        "type": "Point",
        "coordinates": [
          20.75,
          41
        ]
      },
      "type": "Feature",
      "properties": {
        "hierarchy": [
          "tgn:1117570",
          "tgn:1000003",
          "tgn:7029392"
        ],
        "placetype": [
          "aat:300008680"
        ],
        "id": 1117570,
        "name:xx": "Ohridsko ezero"
      }
    },
    {
      "geometry": {
        "type": "Point",
        "coordinates": [
          -119.5,
          49.9167
        ]
      },
      "type": "Feature",
      "properties": {
        "hierarchy": [
          "tgn:1117572",
          "tgn:7005735",
          "tgn:7005685",
          "tgn:1000001",
          "tgn:7029392"
        ],
        "placetype": [
          "aat:300008680"
        ],
        "id": 1117572,
        "name:xx": "Okanagan Lake"
      }
    },
    {
      "geometry": {
        "type": "Point",
        "coordinates": [
          -88.4333,
          43.1
        ]
      },
      "type": "Feature",
      "properties": {
        "hierarchy": [
          "tgn:1117573",
          "tgn:1000001",
          "tgn:7012149",
          "tgn:1003002",
          "tgn:7007922",
          "tgn:7029392"
        ],
        "placetype": [
          "aat:300008680"
        ],
        "id": 1117573,
        "name:xx": "Okauchee Lake"
      }
    },
    {
      "geometry": {
        "type": "Point",
        "coordinates": [
          139.0333,
          35.7833
        ]
      },
      "type": "Feature",
      "properties": {
        "hierarchy": [
          "tgn:1117575",
          "tgn:1000004",
          "tgn:7000894",
          "tgn:1001032",
          "tgn:1000120",
          "tgn:7029392"
        ],
        "placetype": [
          "aat:300008680"
        ],
        "id": 1117575,
        "name:xx": "Okutama-ko"
      }
    },
    {
      "geometry": {
        "type": "Point",
        "coordinates": [
          -103.3667,
          56.9333
        ]
      },
      "type": "Feature",
      "properties": {
        "hierarchy": [
          "tgn:1117577",
          "tgn:7005685",
          "tgn:1000001",
          "tgn:7005805",
          "tgn:7029392"
        ],
        "placetype": [
          "aat:300008680"
        ],
        "id": 1117577,
        "name:xx": "Oliver Lake"
      }
    },
    {
      "geometry": {
        "type": "Point",
        "coordinates": [
          -88.0667,
          13.3167
        ]
      },
      "type": "Feature",
      "properties": {
        "hierarchy": [
          "tgn:1117578",
          "tgn:7005462",
          "tgn:1000001",
          "tgn:7005441",
          "tgn:7029392"
        ],
        "placetype": [
          "aat:300008680"
        ],
        "id": 1117578,
        "name:xx": "Olomega, Laguna"
      }
    },
    {
      "geometry": {
        "type": "Point",
        "coordinates": [
          -119.3833,
          48.2667
        ]
      },
      "type": "Feature",
      "properties": {
        "hierarchy": [
          "tgn:1117579",
          "tgn:1000001",
          "tgn:7012149",
          "tgn:1002742",
          "tgn:7007920",
          "tgn:7029392"
        ],
        "placetype": [
          "aat:300008680"
        ],
        "id": 1117579,
        "name:xx": "Omak Lake"
      }
    }
  ]
}
