{
  "geometry": {
    "type": "Point",
    "coordinates": [
      120.4303,
      22.727
    ]
  },
  "type": "Feature",
  "properties": {
    "hierarchy": [
      "tgn:7487339",
      "tgn:7001004",
      "tgn:1000004",
      "tgn:1000141",
      "tgn:7029392"
    ],
    "placetype": [
      "aat:300008347"
    ],
    "id": 7487339,
    "name:xx": "Neikengnei"
  }
}
