{
  "geometry": {
    "type": "Point",
    "coordinates": [
      -6.683333,
      37.45
    ]
  },
  "type": "Feature",
  "properties": {
    "hierarchy": [
      "tgn:7340773",
      "tgn:7002758",
      "tgn:7002823",
      "tgn:1000003",
      "tgn:1000095",
      "tgn:7029392"
    ],
    "placetype": [
      "aat:300008699"
    ],
    "id": 7340773,
    "name:xx": "Caballón, Arroyo"
  }
}
