{
  "geometry": {
    "type": "Point",
    "coordinates": [
      89.781728,
      26.30318
    ]
  },
  "type": "Feature",
  "properties": {
    "hierarchy": [
      "tgn:7566417",
      "tgn:1000004",
      "tgn:7000198",
      "tgn:1001977",
      "tgn:7029392"
    ],
    "placetype": [
      "aat:300008347"
    ],
    "name:en": "Nātabāri",
    "id": 7566417
  }
}
