{
  "geometry": {
    "type": "Point",
    "coordinates": [
      -89.225,
      19.875
    ]
  },
  "type": "Feature",
  "properties": {
    "hierarchy": [
      "tgn:7402009",
      "tgn:1000001",
      "tgn:7005600",
      "tgn:7005560",
      "tgn:7029392"
    ],
    "placetype": [
      "aat:300008347"
    ],
    "id": 7402009,
    "name:xx": "Becanchén"
  }
}
