{
  "geometry": {
    "type": "Point",
    "coordinates": [
      -72.4667,
      42.4667
    ]
  },
  "type": "Feature",
  "properties": {
    "hierarchy": [
      "tgn:2527669",
      "tgn:1000001",
      "tgn:7013942",
      "tgn:7012149",
      "tgn:7007517",
      "tgn:7029392"
    ],
    "placetype": [
      "aat:300008699"
    ],
    "id": 2527669,
    "name:xx": "Mountain Brook"
  }
}
