{
  "geometry": {
    "type": "Point",
    "coordinates": [
      -111.8667,
      43.7167
    ]
  },
  "type": "Feature",
  "properties": {
    "hierarchy": [
      "tgn:2025841",
      "tgn:1000001",
      "tgn:7012149",
      "tgn:2000477",
      "tgn:7007250",
      "tgn:7029392"
    ],
    "placetype": [
      "aat:300008347"
    ],
    "id": 2025841,
    "name:xx": "Lorenzo"
  }
}
