{
  "geometry": {
    "type": "Point",
    "coordinates": [
      73.89,
      17.952
    ]
  },
  "type": "Feature",
  "properties": {
    "hierarchy": [
      "tgn:1077307",
      "tgn:1000004",
      "tgn:7000198",
      "tgn:1001895",
      "tgn:7029392"
    ],
    "placetype": [
      "aat:300008347"
    ],
    "name:en": "Wai",
    "id": 1077307
  }
}
