{
  "geometry": {
    "type": "Point",
    "coordinates": [
      -70.65,
      42.5833
    ]
  },
  "type": "Feature",
  "properties": {
    "hierarchy": [
      "tgn:1119298",
      "tgn:1000001",
      "tgn:1002359",
      "tgn:7012149",
      "tgn:7007517",
      "tgn:7029392"
    ],
    "placetype": [
      "aat:300008688"
    ],
    "id": 1119298,
    "name:xx": "Niles Pond"
  }
}
