{
  "geometry": {
    "type": "Point",
    "coordinates": [
      -119.5833,
      47.6333
    ]
  },
  "type": "Feature",
  "properties": {
    "hierarchy": [
      "tgn:1133811",
      "tgn:1000001",
      "tgn:2002242",
      "tgn:7012149",
      "tgn:7007920",
      "tgn:7029392"
    ],
    "placetype": [
      "aat:300008706"
    ],
    "id": 1133811,
    "name:xx": "McCarteney Creek"
  }
}
