{
  "geometry": {
    "type": "Point",
    "coordinates": [
      31.930348,
      31.288294
    ]
  },
  "type": "Feature",
  "properties": {
    "hierarchy": [
      "tgn:7524879",
      "tgn:7001242",
      "tgn:1001059",
      "tgn:7016833",
      "tgn:7029392"
    ],
    "placetype": [
      "aat:300008791"
    ],
    "name:en": "Buţūnī al Kabīrah, 'Alāwī al",
    "id": 7524879
  }
}
