{
  "geometry": {
    "type": "Point",
    "coordinates": [
      -108.1167,
      37.3667
    ]
  },
  "type": "Feature",
  "properties": {
    "hierarchy": [
      "tgn:2307937",
      "tgn:1000001",
      "tgn:7012149",
      "tgn:2000233",
      "tgn:7007158",
      "tgn:7029392"
    ],
    "placetype": [
      "aat:300008761"
    ],
    "id": 2307937,
    "name:xx": "East Gulch"
  }
}
