{
  "geometry": {
    "type": "Point",
    "coordinates": [
      -82.4333,
      28.4667
    ]
  },
  "type": "Feature",
  "properties": {
    "hierarchy": [
      "tgn:2019424",
      "tgn:1000001",
      "tgn:1002473",
      "tgn:7012149",
      "tgn:7007240",
      "tgn:7029392"
    ],
    "placetype": [
      "aat:300008347"
    ],
    "id": 2019424,
    "name:xx": "Garden Grove"
  }
}
