{
  "type": "FeatureCollection",
  "features": [
    {
      "geometry": {
        "type": "Point",
        "coordinates": [
          115.5667,
          28.15
        ]
      },
      "type": "Feature",
      "properties": {
        "hierarchy": [
          "tgn:1132102",
          "tgn:1000004",
          "tgn:7002082",
          "tgn:1000111",
          "tgn:7029392"
        ],
        "placetype": [
          "aat:300008707"
        ],
        "id": 1132102,
        "name:xx": "Yuan"
      }
    },
    {
      "geometry": {
        "type": "Point",
        "coordinates": [
          -121.1333,
          39.3667
        ]
      },
      "type": "Feature",
      "properties": {
        "hierarchy": [
          "tgn:1132104",
          "tgn:1000001",
          "tgn:7012149",
          "tgn:7007157",
          "tgn:7029392"
        ],
        "placetype": [
          "aat:300008707"
        ],
        "id": 1132104,
        "name:xx": "Yuba"
      }
    },
    {
      "geometry": {
        "type": "Point",
        "coordinates": [
          118.2833,
          -20.6833
        ]
      },
      "type": "Feature",
      "properties": {
        "hierarchy": [
          "tgn:1132108",
          "tgn:7000490",
          "tgn:1000006",
          "tgn:7001834",
          "tgn:7029392"
        ],
        "placetype": [
          "aat:300008707"
        ],
        "id": 1132108,
        "name:xx": "Yule River"
      }
    },
    {
      "geometry": {
        "type": "Point",
        "coordinates": [
          79.9167,
          37
        ]
      },
      "type": "Feature",
      "properties": {
        "hierarchy": [
          "tgn:1132109",
          "tgn:1000004",
          "tgn:7001745",
          "tgn:1000111",
          "tgn:7029392"
        ],
        "placetype": [
          "aat:300008707"
        ],
        "id": 1132109,
        "name:xx": "Yulongkashihe"
      }
    }
  ]
}
