{
  "geometry": {
    "type": "Point",
    "coordinates": [
      -122.0167,
      42.6333
    ]
  },
  "type": "Feature",
  "properties": {
    "hierarchy": [
      "tgn:2230762",
      "tgn:1000001",
      "tgn:7012149",
      "tgn:2001714",
      "tgn:7007708",
      "tgn:7029392"
    ],
    "placetype": [
      "aat:300006075"
    ],
    "id": 2230762,
    "name:xx": "Central Canal"
  }
}
