{
  "geometry": {
    "type": "Point",
    "coordinates": [
      19.1667,
      48.6667
    ]
  },
  "type": "Feature",
  "properties": {
    "hierarchy": [
      "tgn:7006468",
      "tgn:1000003",
      "tgn:7011765",
      "tgn:7029392"
    ],
    "placetype": [
      "aat:300387179",
      "aat:300236112"
    ],
    "id": 7006468,
    "name:xx": "Stredoslovenský Kraj"
  }
}
