{
  "geometry": {
    "type": "Point",
    "coordinates": [
      -121.3167,
      41.4833
    ]
  },
  "type": "Feature",
  "properties": {
    "hierarchy": [
      "tgn:2171917",
      "tgn:1000001",
      "tgn:7012149",
      "tgn:7007157",
      "tgn:2000186",
      "tgn:7029392"
    ],
    "placetype": [
      "aat:300008680"
    ],
    "id": 2171917,
    "name:xx": "Big Waterhole"
  }
}
