{
  "geometry": {
    "type": "Point",
    "coordinates": [
      100.2333,
      13.8167
    ]
  },
  "type": "Feature",
  "properties": {
    "hierarchy": [
      "tgn:1135987",
      "tgn:1000004",
      "tgn:1000142",
      "tgn:7029392"
    ],
    "placetype": [
      "aat:300006075"
    ],
    "id": 1135987,
    "name:xx": "Maha Sawat, Khlong"
  }
}
