{
  "geometry": {
    "type": "Point",
    "coordinates": [
      -91.8833,
      52.8833
    ]
  },
  "type": "Feature",
  "properties": {
    "hierarchy": [
      "tgn:1117496",
      "tgn:7005685",
      "tgn:1000001",
      "tgn:7013154",
      "tgn:7029392"
    ],
    "placetype": [
      "aat:300008680"
    ],
    "id": 1117496,
    "name:xx": "Nikip Lake"
  }
}
