{
  "geometry": {
    "type": "Point",
    "coordinates": [
      -106.2167,
      45.3333
    ]
  },
  "type": "Feature",
  "properties": {
    "hierarchy": [
      "tgn:2664828",
      "tgn:1000001",
      "tgn:7012149",
      "tgn:2001297",
      "tgn:7007524",
      "tgn:7029392"
    ],
    "placetype": [
      "aat:300006191"
    ],
    "id": 2664828,
    "name:xx": "Simon Reservoir"
  }
}
