{
  "geometry": {
    "type": "Point",
    "coordinates": [
      -88.95,
      40.85
    ]
  },
  "type": "Feature",
  "properties": {
    "hierarchy": [
      "tgn:2519951",
      "tgn:1000001",
      "tgn:7012149",
      "tgn:7007251",
      "tgn:7029392"
    ],
    "placetype": [
      "aat:300008706"
    ],
    "id": 2519951,
    "name:xx": "Mole Creek"
  }
}
