{
  "geometry": {
    "type": "Point",
    "coordinates": [
      -70.3833,
      43.7333
    ]
  },
  "type": "Feature",
  "properties": {
    "hierarchy": [
      "tgn:2218100",
      "tgn:1000001",
      "tgn:2000920",
      "tgn:7012149",
      "tgn:7007515",
      "tgn:7029392"
    ],
    "placetype": [
      "aat:300008798"
    ],
    "id": 2218100,
    "name:xx": "Canada Hill"
  }
}
