{
  "type": "FeatureCollection",
  "features": [
    {
      "geometry": {
        "type": "Point",
        "coordinates": [
          -71.8,
          -52.966667
        ]
      },
      "type": "Feature",
      "properties": {
        "hierarchy": [
          "tgn:7292760",
          "tgn:1001702",
          "tgn:1000049",
          "tgn:1000002",
          "tgn:7029392"
        ],
        "placetype": [
          "aat:300386846"
        ],
        "id": 7292760,
        "name:xx": "Eugenio, Punta"
      }
    },
    {
      "geometry": {
        "type": "Point",
        "coordinates": [
          -74.183333,
          -45.616667
        ]
      },
      "type": "Feature",
      "properties": {
        "hierarchy": [
          "tgn:7292761",
          "tgn:1001623",
          "tgn:1000049",
          "tgn:1000002",
          "tgn:7029392"
        ],
        "placetype": [
          "aat:300386846"
        ],
        "id": 7292761,
        "name:xx": "Eugenio, Punta"
      }
    },
    {
      "geometry": {
        "type": "Point",
        "coordinates": [
          -73.516667,
          -45.166667
        ]
      },
      "type": "Feature",
      "properties": {
        "hierarchy": [
          "tgn:7292762",
          "tgn:1001623",
          "tgn:1000049",
          "tgn:1000002",
          "tgn:7029392"
        ],
        "placetype": [
          "aat:300008791"
        ],
        "id": 7292762,
        "name:xx": "Eugenio, Islote"
      }
    },
    {
      "geometry": {
        "type": "Point",
        "coordinates": [
          -67.283333,
          -54.916667
        ]
      },
      "type": "Feature",
      "properties": {
        "hierarchy": [
          "tgn:7292763",
          "tgn:1001702",
          "tgn:1000049",
          "tgn:1000002",
          "tgn:7029392"
        ],
        "placetype": [
          "aat:300386846"
        ],
        "id": 7292763,
        "name:xx": "Eugenia, Punta"
      }
    },
    {
      "geometry": {
        "type": "Point",
        "coordinates": [
          -67.3,
          -54.916667
        ]
      },
      "type": "Feature",
      "properties": {
        "hierarchy": [
          "tgn:7292764",
          "tgn:1001702",
          "tgn:1000049",
          "tgn:1000002",
          "tgn:7029392"
        ],
        "placetype": [
          "aat:300132317"
        ],
        "id": 7292764,
        "name:xx": "Eugenia, Puerto"
      }
    },
    {
      "geometry": {
        "type": "Point",
        "coordinates": [
          -67.283333,
          -54.916667
        ]
      },
      "type": "Feature",
      "properties": {
        "hierarchy": [
          "tgn:7292765",
          "tgn:1001702",
          "tgn:1000049",
          "tgn:1000002",
          "tgn:7029392"
        ],
        "placetype": [
          "aat:300008791"
        ],
        "id": 7292765,
        "name:xx": "Eugenia, Islotes"
      }
    },
    {
      "geometry": {
        "type": "Point",
        "coordinates": [
          -73.483333,
          -44.983333
        ]
      },
      "type": "Feature",
      "properties": {
        "hierarchy": [
          "tgn:7292766",
          "tgn:1001623",
          "tgn:1000049",
          "tgn:1000002",
          "tgn:7029392"
        ],
        "placetype": [
          "aat:300008791"
        ],
        "id": 7292766,
        "name:xx": "Eugenia, Islote"
      }
    },
    {
      "geometry": {
        "type": "Point",
        "coordinates": [
          -69.95,
          -24.116667
        ]
      },
      "type": "Feature",
      "properties": {
        "hierarchy": [
          "tgn:7292767",
          "tgn:7016598",
          "tgn:1000049",
          "tgn:1000002",
          "tgn:7029392"
        ],
        "placetype": [
          "aat:300387033"
        ],
        "id": 7292767,
        "name:xx": "Eugenia"
      }
    },
    {
      "geometry": {
        "type": "Point",
        "coordinates": [
          -70.8,
          -27.2
        ]
      },
      "type": "Feature",
      "properties": {
        "hierarchy": [
          "tgn:7292768",
          "tgn:1001630",
          "tgn:1000049",
          "tgn:1000002",
          "tgn:7029392"
        ],
        "placetype": [
          "aat:300008777"
        ],
        "id": 7292768,
        "name:xx": "Eucalipto, Alto del"
      }
    },
    {
      "geometry": {
        "type": "Point",
        "coordinates": [
          -73.8,
          -52.916667
        ]
      },
      "type": "Feature",
      "properties": {
        "hierarchy": [
          "tgn:7292769",
          "tgn:1001702",
          "tgn:1000049",
          "tgn:1000002",
          "tgn:7029392"
        ],
        "placetype": [
          "aat:300011692"
        ],
        "id": 7292769,
        "name:xx": "Estribor, Roca"
      }
    }
  ]
}
