{
  "geometry": {
    "type": "Point",
    "coordinates": [
      -111.6333,
      39.8667
    ]
  },
  "type": "Feature",
  "properties": {
    "hierarchy": [
      "tgn:2347186",
      "tgn:1000001",
      "tgn:7012149",
      "tgn:2002125",
      "tgn:7007827",
      "tgn:7029392"
    ],
    "placetype": [
      "aat:300266640"
    ],
    "id": 2347186,
    "name:xx": "Gentle Band Ridge"
  }
}
