{
  "geometry": {
    "type": "Point",
    "coordinates": [
      -85.4833,
      30.4667
    ]
  },
  "type": "Feature",
  "properties": {
    "hierarchy": [
      "tgn:2518711",
      "tgn:1000001",
      "tgn:7012149",
      "tgn:2000291",
      "tgn:7007240",
      "tgn:7029392"
    ],
    "placetype": [
      "aat:300008706"
    ],
    "id": 2518711,
    "name:xx": "Mitchell Mill Creek"
  }
}
