{
  "type": "FeatureCollection",
  "features": [
    {
      "geometry": {
        "type": "Point",
        "coordinates": [
          -106.85,
          37.5833
        ]
      },
      "type": "Feature",
      "properties": {
        "hierarchy": [
          "tgn:2479930",
          "tgn:1000001",
          "tgn:7012149",
          "tgn:2000231",
          "tgn:7007158",
          "tgn:7029392"
        ],
        "placetype": [
          "aat:300008699"
        ],
        "id": 2479930,
        "name:xx": "Lake Fork"
      }
    },
    {
      "geometry": {
        "type": "Point",
        "coordinates": [
          -106.55,
          37.3167
        ]
      },
      "type": "Feature",
      "properties": {
        "hierarchy": [
          "tgn:2479931",
          "tgn:1000001",
          "tgn:2000202",
          "tgn:7012149",
          "tgn:7007158",
          "tgn:7029392"
        ],
        "placetype": [
          "aat:300008699"
        ],
        "id": 2479931,
        "name:xx": "Lake Fork"
      }
    },
    {
      "geometry": {
        "type": "Point",
        "coordinates": [
          -115.9333,
          44.9167
        ]
      },
      "type": "Feature",
      "properties": {
        "hierarchy": [
          "tgn:2479932",
          "tgn:1000001",
          "tgn:7012149",
          "tgn:2000494",
          "tgn:7007250",
          "tgn:7029392"
        ],
        "placetype": [
          "aat:300008699"
        ],
        "id": 2479932,
        "name:xx": "Lake Fork"
      }
    },
    {
      "geometry": {
        "type": "Point",
        "coordinates": [
          -116.55,
          45.1833
        ]
      },
      "type": "Feature",
      "properties": {
        "hierarchy": [
          "tgn:2479933",
          "tgn:2000453",
          "tgn:1000001",
          "tgn:7012149",
          "tgn:7007250",
          "tgn:7029392"
        ],
        "placetype": [
          "aat:300008699"
        ],
        "id": 2479933,
        "name:xx": "Lake Fork"
      }
    },
    {
      "geometry": {
        "type": "Point",
        "coordinates": [
          -113.0333,
          42.4
        ]
      },
      "type": "Feature",
      "properties": {
        "hierarchy": [
          "tgn:2479934",
          "tgn:1000001",
          "tgn:2000467",
          "tgn:7012149",
          "tgn:7007250",
          "tgn:7029392"
        ],
        "placetype": [
          "aat:300008699"
        ],
        "id": 2479934,
        "name:xx": "Lake Fork"
      }
    },
    {
      "geometry": {
        "type": "Point",
        "coordinates": [
          -113.5333,
          44.55
        ]
      },
      "type": "Feature",
      "properties": {
        "hierarchy": [
          "tgn:2479935",
          "tgn:1000001",
          "tgn:7012149",
          "tgn:2000481",
          "tgn:7007250",
          "tgn:7029392"
        ],
        "placetype": [
          "aat:300008699"
        ],
        "id": 2479935,
        "name:xx": "Lake Fork"
      }
    },
    {
      "geometry": {
        "type": "Point",
        "coordinates": [
          -89,
          39.5
        ]
      },
      "type": "Feature",
      "properties": {
        "hierarchy": [
          "tgn:2479936",
          "tgn:1000001",
          "tgn:7012149",
          "tgn:1002885",
          "tgn:7007251",
          "tgn:7029392"
        ],
        "placetype": [
          "aat:300008699"
        ],
        "id": 2479936,
        "name:xx": "Lake Fork"
      }
    },
    {
      "geometry": {
        "type": "Point",
        "coordinates": [
          -89.7167,
          38.7167
        ]
      },
      "type": "Feature",
      "properties": {
        "hierarchy": [
          "tgn:2479937",
          "tgn:1000001",
          "tgn:7012149",
          "tgn:1002622",
          "tgn:7007251",
          "tgn:7029392"
        ],
        "placetype": [
          "aat:300008699"
        ],
        "id": 2479937,
        "name:xx": "Lake Fork"
      }
    },
    {
      "geometry": {
        "type": "Point",
        "coordinates": [
          -89.2333,
          39.9333
        ]
      },
      "type": "Feature",
      "properties": {
        "hierarchy": [
          "tgn:2479938",
          "tgn:1000001",
          "tgn:7012149",
          "tgn:1002605",
          "tgn:7007251",
          "tgn:7029392"
        ],
        "placetype": [
          "aat:300008699"
        ],
        "id": 2479938,
        "name:xx": "Lake Fork"
      }
    },
    {
      "geometry": {
        "type": "Point",
        "coordinates": [
          -109.6,
          45.05
        ]
      },
      "type": "Feature",
      "properties": {
        "hierarchy": [
          "tgn:2479939",
          "tgn:1000001",
          "tgn:2001264",
          "tgn:7012149",
          "tgn:7007524",
          "tgn:7029392"
        ],
        "placetype": [
          "aat:300008699"
        ],
        "id": 2479939,
        "name:xx": "Lake Fork"
      }
    }
  ]
}
