{
  "type": "FeatureCollection",
  "features": [
    {
      "geometry": {
        "type": "Point",
        "coordinates": [
          -83.3833,
          38.1167
        ]
      },
      "type": "Feature",
      "properties": {
        "hierarchy": [
          "tgn:2700790",
          "tgn:1000001",
          "tgn:7012149",
          "tgn:1002837",
          "tgn:7007255",
          "tgn:7029392"
        ],
        "placetype": [
          "aat:300008699"
        ],
        "id": 2700790,
        "name:xx": "Sugar Branch"
      }
    },
    {
      "geometry": {
        "type": "Point",
        "coordinates": [
          -83.3333,
          37.3667
        ]
      },
      "type": "Feature",
      "properties": {
        "hierarchy": [
          "tgn:2700791",
          "tgn:1000001",
          "tgn:2000772",
          "tgn:7012149",
          "tgn:7007255",
          "tgn:7029392"
        ],
        "placetype": [
          "aat:300008699"
        ],
        "id": 2700791,
        "name:xx": "Sugar Branch"
      }
    },
    {
      "geometry": {
        "type": "Point",
        "coordinates": [
          -82.8333,
          37.1833
        ]
      },
      "type": "Feature",
      "properties": {
        "hierarchy": [
          "tgn:2700792",
          "tgn:1000001",
          "tgn:7012149",
          "tgn:2000812",
          "tgn:7007255",
          "tgn:7029392"
        ],
        "placetype": [
          "aat:300008699"
        ],
        "id": 2700792,
        "name:xx": "Sugar Branch"
      }
    },
    {
      "geometry": {
        "type": "Point",
        "coordinates": [
          -92.4333,
          31.5167
        ]
      },
      "type": "Feature",
      "properties": {
        "hierarchy": [
          "tgn:2700793",
          "tgn:1000001",
          "tgn:7012149",
          "tgn:2000875",
          "tgn:7007256",
          "tgn:7029392"
        ],
        "placetype": [
          "aat:300008699"
        ],
        "id": 2700793,
        "name:xx": "Sugar Branch"
      }
    },
    {
      "geometry": {
        "type": "Point",
        "coordinates": [
          -92.4833,
          38.9833
        ]
      },
      "type": "Feature",
      "properties": {
        "hierarchy": [
          "tgn:2700794",
          "tgn:1000001",
          "tgn:1002190",
          "tgn:7012149",
          "tgn:7007523",
          "tgn:7029392"
        ],
        "placetype": [
          "aat:300008699"
        ],
        "id": 2700794,
        "name:xx": "Sugar Branch"
      }
    },
    {
      "geometry": {
        "type": "Point",
        "coordinates": [
          -83.3,
          35.2667
        ]
      },
      "type": "Feature",
      "properties": {
        "hierarchy": [
          "tgn:2700795",
          "tgn:1000001",
          "tgn:7012149",
          "tgn:2001508",
          "tgn:7007709",
          "tgn:7029392"
        ],
        "placetype": [
          "aat:300008699"
        ],
        "id": 2700795,
        "name:xx": "Sugar Branch"
      }
    },
    {
      "geometry": {
        "type": "Point",
        "coordinates": [
          -81.6,
          35.2667
        ]
      },
      "type": "Feature",
      "properties": {
        "hierarchy": [
          "tgn:2700796",
          "tgn:1000001",
          "tgn:2001484",
          "tgn:7012149",
          "tgn:7007709",
          "tgn:7029392"
        ],
        "placetype": [
          "aat:300008699"
        ],
        "id": 2700796,
        "name:xx": "Sugar Branch"
      }
    },
    {
      "geometry": {
        "type": "Point",
        "coordinates": [
          -89.2167,
          35.55
        ]
      },
      "type": "Feature",
      "properties": {
        "hierarchy": [
          "tgn:2700797",
          "tgn:1000001",
          "tgn:7012149",
          "tgn:2001874",
          "tgn:7007825",
          "tgn:7029392"
        ],
        "placetype": [
          "aat:300008699"
        ],
        "id": 2700797,
        "name:xx": "Sugar Branch"
      }
    },
    {
      "geometry": {
        "type": "Point",
        "coordinates": [
          -81.3833,
          36.6833
        ]
      },
      "type": "Feature",
      "properties": {
        "hierarchy": [
          "tgn:2700799",
          "tgn:1000001",
          "tgn:7012149",
          "tgn:2002164",
          "tgn:7007919",
          "tgn:7029392"
        ],
        "placetype": [
          "aat:300008699"
        ],
        "id": 2700799,
        "name:xx": "Sugar Branch"
      }
    }
  ]
}
