{
  "type": "FeatureCollection",
  "features": [
    {
      "geometry": {
        "type": "Point",
        "coordinates": [
          104.6667,
          29.9667
        ]
      },
      "type": "Feature",
      "properties": {
        "hierarchy": [
          "tgn:1128910",
          "tgn:1000004",
          "tgn:7002087",
          "tgn:1000111",
          "tgn:7029392"
        ],
        "placetype": [
          "aat:300008707"
        ],
        "id": 1128910,
        "name:xx": "Qiuxi"
      }
    },
    {
      "geometry": {
        "type": "Point",
        "coordinates": [
          50.95,
          34.65
        ]
      },
      "type": "Feature",
      "properties": {
        "hierarchy": [
          "tgn:1128911",
          "tgn:1000004",
          "tgn:7000231",
          "tgn:7029392"
        ],
        "placetype": [
          "aat:300008707"
        ],
        "id": 1128911,
        "name:xx": "Qom"
      }
    },
    {
      "geometry": {
        "type": "Point",
        "coordinates": [
          68.2667,
          37
        ]
      },
      "type": "Feature",
      "properties": {
        "hierarchy": [
          "tgn:1128912",
          "tgn:7016612",
          "tgn:1000004",
          "tgn:7029392"
        ],
        "placetype": [
          "aat:300008707"
        ],
        "id": 1128912,
        "name:xx": "Qondūz"
      }
    },
    {
      "geometry": {
        "type": "Point",
        "coordinates": [
          119.45,
          29.2
        ]
      },
      "type": "Feature",
      "properties": {
        "hierarchy": [
          "tgn:1128913",
          "tgn:1000004",
          "tgn:7002076",
          "tgn:1000111",
          "tgn:7029392"
        ],
        "placetype": [
          "aat:300008707"
        ],
        "id": 1128913,
        "name:xx": "Qu"
      }
    },
    {
      "geometry": {
        "type": "Point",
        "coordinates": [
          -101.3167,
          50.45
        ]
      },
      "type": "Feature",
      "properties": {
        "hierarchy": [
          "tgn:1128914",
          "tgn:7005685",
          "tgn:1000001",
          "tgn:7029392"
        ],
        "placetype": [
          "aat:300008707"
        ],
        "id": 1128914,
        "name:xx": "Qu'Appelle River"
      }
    },
    {
      "geometry": {
        "type": "Point",
        "coordinates": [
          15.05,
          -14.7
        ]
      },
      "type": "Feature",
      "properties": {
        "hierarchy": [
          "tgn:1128915",
          "tgn:7001242",
          "tgn:1000149",
          "tgn:1000867",
          "tgn:7029392"
        ],
        "placetype": [
          "aat:300008707"
        ],
        "id": 1128915,
        "name:xx": "Quê"
      }
    },
    {
      "geometry": {
        "type": "Point",
        "coordinates": [
          -47.6333,
          -19.15
        ]
      },
      "type": "Feature",
      "properties": {
        "hierarchy": [
          "tgn:1128918",
          "tgn:7006237",
          "tgn:1000047",
          "tgn:7002457",
          "tgn:1000002",
          "tgn:7029392"
        ],
        "placetype": [
          "aat:300008707"
        ],
        "id": 1128918,
        "name:xx": "Quebra-Anzol"
      }
    },
    {
      "geometry": {
        "type": "Point",
        "coordinates": [
          -123.6,
          47.7833
        ]
      },
      "type": "Feature",
      "properties": {
        "hierarchy": [
          "tgn:1128919",
          "tgn:1000001",
          "tgn:7012149",
          "tgn:1002418",
          "tgn:7007920",
          "tgn:7029392"
        ],
        "placetype": [
          "aat:300008707"
        ],
        "id": 1128919,
        "name:xx": "Queets"
      }
    }
  ]
}
