{
  "geometry": {
    "type": "Point",
    "coordinates": [
      -97.3333,
      34.7167
    ]
  },
  "type": "Feature",
  "properties": {
    "hierarchy": [
      "tgn:2001647",
      "tgn:1000001",
      "tgn:7012149",
      "tgn:7007707",
      "tgn:7029392"
    ],
    "placetype": [
      "aat:300387145",
      "aat:300000771"
    ],
    "id": 2001647,
    "name:xx": "Garvin"
  }
}
