{
  "geometry": {
    "type": "Point",
    "coordinates": [
      -93.75,
      44.4833
    ]
  },
  "type": "Feature",
  "properties": {
    "hierarchy": [
      "tgn:2717760",
      "tgn:1000001",
      "tgn:7012149",
      "tgn:2001038",
      "tgn:7007521",
      "tgn:7029392"
    ],
    "placetype": [
      "aat:300008680"
    ],
    "id": 2717760,
    "name:xx": "Thomas Lake"
  }
}
