{
  "geometry": {
    "type": "Point",
    "coordinates": [
      -89.0333,
      33.7667
    ]
  },
  "type": "Feature",
  "properties": {
    "hierarchy": [
      "tgn:2597335",
      "tgn:1000001",
      "tgn:7012149",
      "tgn:7007522",
      "tgn:7029392"
    ],
    "placetype": [
      "aat:300008706"
    ],
    "id": 2597335,
    "name:xx": "Prairie Creek"
  }
}
