{
  "type": "FeatureCollection",
  "features": [
    {
      "geometry": {
        "type": "Point",
        "coordinates": [
          6,
          50.783333
        ]
      },
      "type": "Feature",
      "properties": {
        "hierarchy": [
          "tgn:4005091",
          "tgn:1000003",
          "tgn:7003622",
          "tgn:7016845",
          "tgn:7029392"
        ],
        "placetype": [
          "aat:300008347"
        ],
        "name:nl": "Holset",
        "id": 4005091
      }
    },
    {
      "geometry": {
        "type": "Point",
        "coordinates": [
          6.883333,
          53.35
        ]
      },
      "type": "Feature",
      "properties": {
        "hierarchy": [
          "tgn:4005096",
          "tgn:1000003",
          "tgn:7003613",
          "tgn:7016845",
          "tgn:7029392"
        ],
        "placetype": [
          "aat:300008347"
        ],
        "name:nl": "Holwierde",
        "id": 4005096
      }
    }
  ]
}
