{
  "geometry": {
    "type": "Point",
    "coordinates": [
      88.5167,
      28.0167
    ]
  },
  "type": "Feature",
  "properties": {
    "hierarchy": [
      "tgn:1104227",
      "tgn:1000004",
      "tgn:7029392"
    ],
    "placetype": [
      "aat:300008795"
    ],
    "id": 1104227,
    "name:xx": "Chomiomo"
  }
}
