{
  "geometry": {
    "type": "Point",
    "coordinates": [
      -85.75,
      38.4333
    ]
  },
  "type": "Feature",
  "properties": {
    "hierarchy": [
      "tgn:2668676",
      "tgn:1000001",
      "tgn:1002273",
      "tgn:7012149",
      "tgn:7007252",
      "tgn:7029392"
    ],
    "placetype": [
      "aat:300008347"
    ],
    "id": 2668676,
    "name:xx": "Slatecut"
  }
}
