{
  "geometry": {
    "type": "Point",
    "coordinates": [
      -109.5333,
      33.0167
    ]
  },
  "type": "Feature",
  "properties": {
    "hierarchy": [
      "tgn:2323568",
      "tgn:1000001",
      "tgn:7006451",
      "tgn:2000094",
      "tgn:7012149",
      "tgn:7029392"
    ],
    "placetype": [
      "aat:300008697"
    ],
    "id": 2323568,
    "name:xx": "Farrell Spring"
  }
}
