{
  "type": "FeatureCollection",
  "features": [
    {
      "geometry": {
        "type": "Point",
        "coordinates": [
          -95.7,
          18
        ]
      },
      "type": "Feature",
      "properties": {
        "hierarchy": [
          "tgn:7396080",
          "tgn:1000001",
          "tgn:7005599",
          "tgn:7005560",
          "tgn:7029392"
        ],
        "placetype": [
          "aat:300008347"
        ],
        "id": 7396080,
        "name:xx": "San Jerónimo"
      }
    },
    {
      "geometry": {
        "type": "Point",
        "coordinates": [
          -101.95,
          17.966667
        ]
      },
      "type": "Feature",
      "properties": {
        "hierarchy": [
          "tgn:7396081",
          "tgn:7005585",
          "tgn:1000001",
          "tgn:7005560",
          "tgn:7029392"
        ],
        "placetype": [
          "aat:300008347"
        ],
        "id": 7396081,
        "name:xx": "San Jerónimo"
      }
    },
    {
      "geometry": {
        "type": "Point",
        "coordinates": [
          -91.883333,
          17.95
        ]
      },
      "type": "Feature",
      "properties": {
        "hierarchy": [
          "tgn:7396082",
          "tgn:1000001",
          "tgn:7005596",
          "tgn:7005560",
          "tgn:7029392"
        ],
        "placetype": [
          "aat:300008347"
        ],
        "id": 7396082,
        "name:xx": "San Jerónimo"
      }
    },
    {
      "geometry": {
        "type": "Point",
        "coordinates": [
          -92.416667,
          17.866667
        ]
      },
      "type": "Feature",
      "properties": {
        "hierarchy": [
          "tgn:7396083",
          "tgn:1000001",
          "tgn:7005596",
          "tgn:7005560",
          "tgn:7029392"
        ],
        "placetype": [
          "aat:300008347"
        ],
        "id": 7396083,
        "name:xx": "San Jerónimo"
      }
    },
    {
      "geometry": {
        "type": "Point",
        "coordinates": [
          -93.266667,
          17.616667
        ]
      },
      "type": "Feature",
      "properties": {
        "hierarchy": [
          "tgn:7396084",
          "tgn:7005580",
          "tgn:1000001",
          "tgn:7005560",
          "tgn:7029392"
        ],
        "placetype": [
          "aat:300008347"
        ],
        "id": 7396084,
        "name:xx": "San Jerónimo"
      }
    },
    {
      "geometry": {
        "type": "Point",
        "coordinates": [
          -96.583333,
          17.25
        ]
      },
      "type": "Feature",
      "properties": {
        "hierarchy": [
          "tgn:7396085",
          "tgn:1000001",
          "tgn:7005591",
          "tgn:7005560",
          "tgn:7029392"
        ],
        "placetype": [
          "aat:300008347"
        ],
        "id": 7396085,
        "name:xx": "San Jerónimo"
      }
    },
    {
      "geometry": {
        "type": "Point",
        "coordinates": [
          -92.816667,
          17.15
        ]
      },
      "type": "Feature",
      "properties": {
        "hierarchy": [
          "tgn:7396086",
          "tgn:7005580",
          "tgn:1000001",
          "tgn:7005560",
          "tgn:7029392"
        ],
        "placetype": [
          "aat:300008347"
        ],
        "id": 7396086,
        "name:xx": "San Jerónimo"
      }
    },
    {
      "geometry": {
        "type": "Point",
        "coordinates": [
          -92.2,
          15.683333
        ]
      },
      "type": "Feature",
      "properties": {
        "hierarchy": [
          "tgn:7396087",
          "tgn:7005580",
          "tgn:1000001",
          "tgn:7005560",
          "tgn:7029392"
        ],
        "placetype": [
          "aat:300008347"
        ],
        "id": 7396087,
        "name:xx": "San Jerónimo"
      }
    },
    {
      "geometry": {
        "type": "Point",
        "coordinates": [
          -92.383333,
          15.3
        ]
      },
      "type": "Feature",
      "properties": {
        "hierarchy": [
          "tgn:7396088",
          "tgn:7005580",
          "tgn:1000001",
          "tgn:7005560",
          "tgn:7029392"
        ],
        "placetype": [
          "aat:300008347"
        ],
        "id": 7396088,
        "name:xx": "San Jerónimo"
      }
    },
    {
      "geometry": {
        "type": "Point",
        "coordinates": [
          -92.133333,
          15.05
        ]
      },
      "type": "Feature",
      "properties": {
        "hierarchy": [
          "tgn:7396089",
          "tgn:7005580",
          "tgn:1000001",
          "tgn:7005560",
          "tgn:7029392"
        ],
        "placetype": [
          "aat:300008347"
        ],
        "id": 7396089,
        "name:xx": "San Jerónimo"
      }
    }
  ]
}
