{
  "geometry": {
    "type": "Point",
    "coordinates": [
      -87.5333,
      38.65
    ]
  },
  "type": "Feature",
  "properties": {
    "hierarchy": [
      "tgn:2207230",
      "tgn:1000001",
      "tgn:7012149",
      "tgn:2000545",
      "tgn:7007252",
      "tgn:7029392"
    ],
    "placetype": [
      "aat:300008798"
    ],
    "id": 2207230,
    "name:xx": "Bunker Hill"
  }
}
