{
  "geometry": {
    "type": "Point",
    "coordinates": [
      -120.85,
      47.6333
    ]
  },
  "type": "Feature",
  "properties": {
    "hierarchy": [
      "tgn:2409321",
      "tgn:1000001",
      "tgn:1002260",
      "tgn:7012149",
      "tgn:7007920",
      "tgn:7029392"
    ],
    "placetype": [
      "aat:300008706"
    ],
    "id": 2409321,
    "name:xx": "Ida Creek"
  }
}
