{
  "geometry": {
    "type": "Point",
    "coordinates": [
      21.65,
      -26.9333
    ]
  },
  "type": "Feature",
  "properties": {
    "hierarchy": [
      "tgn:1125819",
      "tgn:7001242",
      "tgn:7029392"
    ],
    "placetype": [
      "aat:300008707"
    ],
    "id": 1125819,
    "name:xx": "Kuruman"
  }
}
