{
  "geometry": {
    "type": "Point",
    "coordinates": [
      23.533333,
      35.35
    ]
  },
  "type": "Feature",
  "properties": {
    "hierarchy": [
      "tgn:7218611",
      "tgn:7002690",
      "tgn:7012056",
      "tgn:1000003",
      "tgn:1000074",
      "tgn:7029392"
    ],
    "placetype": [
      "aat:300386846"
    ],
    "id": 7218611,
    "name:xx": "Xekoftó, Ákra"
  }
}
