{
  "geometry": {
    "type": "Point",
    "coordinates": [
      32.353,
      29.775
    ]
  },
  "type": "Feature",
  "properties": {
    "hierarchy": [
      "tgn:1111432",
      "tgn:7001242",
      "tgn:7016833",
      "tgn:1001110",
      "tgn:7029392"
    ],
    "placetype": [
      "aat:300008773",
      "aat:300379998"
    ],
    "id": 1111432,
    "name:xx": "Ḥammād, Wādī"
  }
}
