{
  "geometry": {
    "type": "Point",
    "coordinates": [
      -116.1667,
      34.6167
    ]
  },
  "type": "Feature",
  "properties": {
    "hierarchy": [
      "tgn:2692662",
      "tgn:1000001",
      "tgn:7012149",
      "tgn:7007157",
      "tgn:1002857",
      "tgn:7029392"
    ],
    "placetype": [
      "aat:300008347"
    ],
    "id": 2692662,
    "name:xx": "Stedman"
  }
}
