{
  "geometry": {
    "type": "Point",
    "coordinates": [
      -85.35,
      43.2667
    ]
  },
  "type": "Feature",
  "properties": {
    "hierarchy": [
      "tgn:2229153",
      "tgn:1000001",
      "tgn:7012149",
      "tgn:1002540",
      "tgn:7007520",
      "tgn:7029392"
    ],
    "placetype": [
      "aat:300008680"
    ],
    "id": 2229153,
    "name:xx": "Cedar Lake"
  }
}
