{
  "geometry": {
    "type": "Point",
    "coordinates": [
      -78.9333,
      37.9333
    ]
  },
  "type": "Feature",
  "properties": {
    "hierarchy": [
      "tgn:2295464",
      "tgn:1000001",
      "tgn:7012149",
      "tgn:7007919",
      "tgn:7029392"
    ],
    "placetype": [
      "aat:300008798"
    ],
    "id": 2295464,
    "name:xx": "Dripping Rock"
  }
}
