{
  "geometry": {
    "type": "Point",
    "coordinates": [
      -117.5667,
      45.1667
    ]
  },
  "type": "Feature",
  "properties": {
    "hierarchy": [
      "tgn:2689196",
      "tgn:1000001",
      "tgn:7012149",
      "tgn:2001721",
      "tgn:7007708",
      "tgn:7029392"
    ],
    "placetype": [
      "aat:300008798"
    ],
    "id": 2689196,
    "name:xx": "Squaw Butte"
  }
}
