{
  "geometry": {
    "type": "Point",
    "coordinates": [
      -92.0167,
      45.5167
    ]
  },
  "type": "Feature",
  "properties": {
    "hierarchy": [
      "tgn:2121008",
      "tgn:2002307",
      "tgn:1000001",
      "tgn:7012149",
      "tgn:7007922",
      "tgn:7029392"
    ],
    "placetype": [
      "aat:300008347"
    ],
    "id": 2121008,
    "name:xx": "Cumberland"
  }
}
