{
  "geometry": {
    "type": "Point",
    "coordinates": [
      -80.4667,
      40.6333
    ]
  },
  "type": "Feature",
  "properties": {
    "hierarchy": [
      "tgn:2347749",
      "tgn:1002171",
      "tgn:1000001",
      "tgn:7012149",
      "tgn:7007710",
      "tgn:7029392"
    ],
    "placetype": [
      "aat:300008791"
    ],
    "id": 2347749,
    "name:xx": "Georgetown Island"
  }
}
