{
  "geometry": {
    "type": "Point",
    "coordinates": [
      -91.3167,
      46.0167
    ]
  },
  "type": "Feature",
  "properties": {
    "hierarchy": [
      "tgn:2392250",
      "tgn:1000001",
      "tgn:7012149",
      "tgn:2002353",
      "tgn:7007922",
      "tgn:7029392"
    ],
    "placetype": [
      "aat:300132316"
    ],
    "id": 2392250,
    "name:xx": "Hinton Bay"
  }
}
