{
  "type": "FeatureCollection",
  "features": [
    {
      "geometry": {
        "type": "Point",
        "coordinates": [
          -123.1333,
          45.2167
        ]
      },
      "type": "Feature",
      "properties": {
        "hierarchy": [
          "tgn:1131991",
          "tgn:1000001",
          "tgn:7012149",
          "tgn:1003044",
          "tgn:7007708",
          "tgn:7029392"
        ],
        "placetype": [
          "aat:300008707"
        ],
        "id": 1131991,
        "name:xx": "Yamhill"
      }
    },
    {
      "geometry": {
        "type": "Point",
        "coordinates": [
          -106.8833,
          40.15
        ]
      },
      "type": "Feature",
      "properties": {
        "hierarchy": [
          "tgn:1131992",
          "tgn:1000001",
          "tgn:7012149",
          "tgn:7007158",
          "tgn:7029392"
        ],
        "placetype": [
          "aat:300008707"
        ],
        "id": 1131992,
        "name:xx": "Yampa"
      }
    },
    {
      "geometry": {
        "type": "Point",
        "coordinates": [
          81.75,
          25.5
        ]
      },
      "type": "Feature",
      "properties": {
        "hierarchy": [
          "tgn:1131993",
          "tgn:1000004",
          "tgn:7000198",
          "tgn:7029392"
        ],
        "placetype": [
          "aat:300008707"
        ],
        "id": 1131993,
        "name:xx": "Yamuna"
      }
    },
    {
      "geometry": {
        "type": "Point",
        "coordinates": [
          81.0167,
          8.9167
        ]
      },
      "type": "Feature",
      "properties": {
        "hierarchy": [
          "tgn:1131994",
          "tgn:1000004",
          "tgn:1000110",
          "tgn:7029392"
        ],
        "placetype": [
          "aat:300008707"
        ],
        "id": 1131994,
        "name:xx": "Yan Oya"
      }
    },
    {
      "geometry": {
        "type": "Point",
        "coordinates": [
          115.3,
          40.4
        ]
      },
      "type": "Feature",
      "properties": {
        "hierarchy": [
          "tgn:1131996",
          "tgn:1000004",
          "tgn:1000111",
          "tgn:7029392"
        ],
        "placetype": [
          "aat:300008707"
        ],
        "id": 1131996,
        "name:xx": "Yang He"
      }
    },
    {
      "geometry": {
        "type": "Point",
        "coordinates": [
          104.7,
          30.0667
        ]
      },
      "type": "Feature",
      "properties": {
        "hierarchy": [
          "tgn:1131998",
          "tgn:1000004",
          "tgn:7002087",
          "tgn:1000111",
          "tgn:7029392"
        ],
        "placetype": [
          "aat:300008707"
        ],
        "id": 1131998,
        "name:xx": "Yanghua He"
      }
    },
    {
      "geometry": {
        "type": "Point",
        "coordinates": [
          123,
          42.0667
        ]
      },
      "type": "Feature",
      "properties": {
        "hierarchy": [
          "tgn:1131999",
          "tgn:1000004",
          "tgn:1001390",
          "tgn:1000111",
          "tgn:7029392"
        ],
        "placetype": [
          "aat:300008707"
        ],
        "id": 1131999,
        "name:xx": "Yangximu He"
      }
    }
  ]
}
