{
  "geometry": {
    "type": "Point",
    "coordinates": [
      -113.65,
      48.9333
    ]
  },
  "type": "Feature",
  "properties": {
    "hierarchy": [
      "tgn:2487035",
      "tgn:1000001",
      "tgn:7012149",
      "tgn:2001277",
      "tgn:7007524",
      "tgn:7029392"
    ],
    "placetype": [
      "aat:300266640"
    ],
    "id": 2487035,
    "name:xx": "Lee Ridge"
  }
}
