{
  "type": "FeatureCollection",
  "features": [
    {
      "geometry": {
        "type": "Point",
        "coordinates": [
          10.066667,
          43.9
        ]
      },
      "type": "Feature",
      "properties": {
        "hierarchy": [
          "tgn:7042770",
          "tgn:7003165",
          "tgn:1000003",
          "tgn:7009760",
          "tgn:1000080",
          "tgn:7029392"
        ],
        "placetype": [
          "aat:300008734"
        ],
        "id": 7042770,
        "name:xx": "Riviera della Versilia"
      }
    },
    {
      "geometry": {
        "type": "Point",
        "coordinates": [
          10.366667,
          44.666667
        ]
      },
      "type": "Feature",
      "properties": {
        "hierarchy": [
          "tgn:7042771",
          "tgn:7003131",
          "tgn:1000003",
          "tgn:7008516",
          "tgn:1000080",
          "tgn:7029392"
        ],
        "placetype": [
          "aat:300008347"
        ],
        "id": 7042771,
        "name:xx": "Riviera"
      }
    },
    {
      "geometry": {
        "type": "Point",
        "coordinates": [
          7.5,
          43.75
        ]
      },
      "type": "Feature",
      "properties": {
        "hierarchy": [
          "tgn:7042772",
          "tgn:1000003",
          "tgn:7003236",
          "tgn:1000080",
          "tgn:7029392"
        ],
        "placetype": [
          "aat:300008734"
        ],
        "id": 7042772,
        "name:xx": "Ponente, Riviera di"
      }
    },
    {
      "geometry": {
        "type": "Point",
        "coordinates": [
          13,
          45.883333
        ]
      },
      "type": "Feature",
      "properties": {
        "hierarchy": [
          "tgn:7042773",
          "tgn:1003506",
          "tgn:1000003",
          "tgn:7002993",
          "tgn:1000080",
          "tgn:7029392"
        ],
        "placetype": [
          "aat:300008347"
        ],
        "id": 7042773,
        "name:xx": "Rividischia"
      }
    },
    {
      "geometry": {
        "type": "Point",
        "coordinates": [
          7.4,
          45.116667
        ]
      },
      "type": "Feature",
      "properties": {
        "hierarchy": [
          "tgn:7042775",
          "tgn:7003154",
          "tgn:1000003",
          "tgn:7003120",
          "tgn:1000080",
          "tgn:7029392"
        ],
        "placetype": [
          "aat:300008347"
        ],
        "id": 7042775,
        "name:xx": "Rivera"
      }
    },
    {
      "geometry": {
        "type": "Point",
        "coordinates": [
          8.416667,
          45.216667
        ]
      },
      "type": "Feature",
      "properties": {
        "hierarchy": [
          "tgn:7042778",
          "tgn:1003428",
          "tgn:1000003",
          "tgn:7003120",
          "tgn:1000080",
          "tgn:7029392"
        ],
        "placetype": [
          "aat:300008347"
        ],
        "id": 7042778,
        "name:xx": "Rive"
      }
    },
    {
      "geometry": {
        "type": "Point",
        "coordinates": [
          9.433333,
          44.266667
        ]
      },
      "type": "Feature",
      "properties": {
        "hierarchy": [
          "tgn:7042779",
          "tgn:1000003",
          "tgn:7003236",
          "tgn:1000080",
          "tgn:7029392"
        ],
        "placetype": [
          "aat:300007783"
        ],
        "id": 7042779,
        "name:xx": "Stazione Riva-Trigoso"
      }
    }
  ]
}
