{
  "geometry": {
    "type": "Point",
    "coordinates": [
      -91.3833,
      45.0167
    ]
  },
  "type": "Feature",
  "properties": {
    "hierarchy": [
      "tgn:2121093",
      "tgn:1000001",
      "tgn:2002313",
      "tgn:7012149",
      "tgn:7007922",
      "tgn:7029392"
    ],
    "placetype": [
      "aat:300387016"
    ],
    "id": 2121093,
    "name:xx": "Eagle Point"
  }
}
