{
  "geometry": {
    "type": "Point",
    "coordinates": [
      -152.9167,
      65.3667
    ]
  },
  "type": "Feature",
  "properties": {
    "hierarchy": [
      "tgn:2505409",
      "tgn:7006450",
      "tgn:1000001",
      "tgn:7012149",
      "tgn:2000089",
      "tgn:7029392"
    ],
    "placetype": [
      "aat:300008706"
    ],
    "id": 2505409,
    "name:xx": "Melozimoran Creek"
  }
}
