{
  "type": "FeatureCollection",
  "features": [
    {
      "geometry": {
        "type": "Point",
        "coordinates": [
          -102.9167,
          42.6667
        ]
      },
      "type": "Feature",
      "properties": {
        "hierarchy": [
          "tgn:2166440",
          "tgn:1000001",
          "tgn:2001338",
          "tgn:7012149",
          "tgn:7007525",
          "tgn:7029392"
        ],
        "placetype": [
          "aat:300008706"
        ],
        "id": 2166440,
        "name:xx": "Big Bordeaux Creek"
      }
    },
    {
      "geometry": {
        "type": "Point",
        "coordinates": [
          -87.0333,
          38.3667
        ]
      },
      "type": "Feature",
      "properties": {
        "hierarchy": [
          "tgn:2166441",
          "tgn:1000001",
          "tgn:7013619",
          "tgn:7012149",
          "tgn:7007252",
          "tgn:7029392"
        ],
        "placetype": [
          "aat:300008905"
        ],
        "id": 2166441,
        "name:xx": "Big Bottom"
      }
    },
    {
      "geometry": {
        "type": "Point",
        "coordinates": [
          -122.1,
          46.4667
        ]
      },
      "type": "Feature",
      "properties": {
        "hierarchy": [
          "tgn:2166444",
          "tgn:1000001",
          "tgn:7012149",
          "tgn:1002594",
          "tgn:7007920",
          "tgn:7029392"
        ],
        "placetype": [
          "aat:300008761"
        ],
        "id": 2166444,
        "name:xx": "Big Bottom"
      }
    },
    {
      "geometry": {
        "type": "Point",
        "coordinates": [
          -82.9,
          37.0833
        ]
      },
      "type": "Feature",
      "properties": {
        "hierarchy": [
          "tgn:2166445",
          "tgn:1000001",
          "tgn:7012149",
          "tgn:2000812",
          "tgn:7007255",
          "tgn:7029392"
        ],
        "placetype": [
          "aat:300008699"
        ],
        "id": 2166445,
        "name:xx": "Big Bottom Branch"
      }
    },
    {
      "geometry": {
        "type": "Point",
        "coordinates": [
          -85.75,
          35.5167
        ]
      },
      "type": "Feature",
      "properties": {
        "hierarchy": [
          "tgn:2166446",
          "tgn:1000001",
          "tgn:7012149",
          "tgn:2001925",
          "tgn:7007825",
          "tgn:7029392"
        ],
        "placetype": [
          "aat:300008746"
        ],
        "id": 2166446,
        "name:xx": "Big Bottom Cave"
      }
    },
    {
      "geometry": {
        "type": "Point",
        "coordinates": [
          -90.2,
          37.9167
        ]
      },
      "type": "Feature",
      "properties": {
        "hierarchy": [
          "tgn:2166447",
          "tgn:1000001",
          "tgn:7012149",
          "tgn:2001240",
          "tgn:7007523",
          "tgn:7029392"
        ],
        "placetype": [
          "aat:300008706"
        ],
        "id": 2166447,
        "name:xx": "Big Bottom Creek"
      }
    },
    {
      "geometry": {
        "type": "Point",
        "coordinates": [
          -91.2833,
          36.7333
        ]
      },
      "type": "Feature",
      "properties": {
        "hierarchy": [
          "tgn:2166448",
          "tgn:1000001",
          "tgn:7012149",
          "tgn:2001225",
          "tgn:7007523",
          "tgn:7029392"
        ],
        "placetype": [
          "aat:300008761"
        ],
        "id": 2166448,
        "name:xx": "Big Bottom Hollow"
      }
    },
    {
      "geometry": {
        "type": "Point",
        "coordinates": [
          -81.5,
          38.35
        ]
      },
      "type": "Feature",
      "properties": {
        "hierarchy": [
          "tgn:2166449",
          "tgn:1000001",
          "tgn:7012149",
          "tgn:2002270",
          "tgn:7013961",
          "tgn:7029392"
        ],
        "placetype": [
          "aat:300008761"
        ],
        "id": 2166449,
        "name:xx": "Big Bottom Hollow"
      }
    }
  ]
}
