{
  "type": "FeatureCollection",
  "features": [
    {
      "geometry": {
        "type": "Point",
        "coordinates": [
          -37.9167,
          -9.2833
        ]
      },
      "type": "Feature",
      "properties": {
        "hierarchy": [
          "tgn:1136490",
          "tgn:7016581",
          "tgn:1000047",
          "tgn:7002455",
          "tgn:1000002",
          "tgn:7029392"
        ],
        "placetype": [
          "aat:300008347"
        ],
        "id": 1136490,
        "name:xx": "Água Branca"
      }
    },
    {
      "geometry": {
        "type": "Point",
        "coordinates": [
          -45.6667,
          -21.9
        ]
      },
      "type": "Feature",
      "properties": {
        "hierarchy": [
          "tgn:1136491",
          "tgn:7006237",
          "tgn:1000047",
          "tgn:7002457",
          "tgn:1000002",
          "tgn:7029392"
        ],
        "placetype": [
          "aat:300008347"
        ],
        "id": 1136491,
        "name:xx": "Água Comprida"
      }
    },
    {
      "geometry": {
        "type": "Point",
        "coordinates": [
          -46.6,
          -22.8167
        ]
      },
      "type": "Feature",
      "properties": {
        "hierarchy": [
          "tgn:1136492",
          "tgn:1001945",
          "tgn:1000047",
          "tgn:7002457",
          "tgn:1000002",
          "tgn:7029392"
        ],
        "placetype": [
          "aat:300008347",
          "aat:300008389"
        ],
        "id": 1136492,
        "name:xx": "Araras"
      }
    },
    {
      "geometry": {
        "type": "Point",
        "coordinates": [
          -43.4167,
          -22.7333
        ]
      },
      "type": "Feature",
      "properties": {
        "hierarchy": [
          "tgn:1136493",
          "tgn:1001942",
          "tgn:1000047",
          "tgn:7002457",
          "tgn:1000002",
          "tgn:7029392"
        ],
        "placetype": [
          "aat:300008347"
        ],
        "id": 1136493,
        "name:xx": "Areia Branca"
      }
    },
    {
      "geometry": {
        "type": "Point",
        "coordinates": [
          -46.85,
          -22.8
        ]
      },
      "type": "Feature",
      "properties": {
        "hierarchy": [
          "tgn:1136494",
          "tgn:1001945",
          "tgn:1000047",
          "tgn:7002457",
          "tgn:1000002",
          "tgn:7029392"
        ],
        "placetype": [
          "aat:300008347"
        ],
        "id": 1136494,
        "name:xx": "Areia Branca"
      }
    },
    {
      "geometry": {
        "type": "Point",
        "coordinates": [
          -43.4,
          -22.7667
        ]
      },
      "type": "Feature",
      "properties": {
        "hierarchy": [
          "tgn:1136495",
          "tgn:1001942",
          "tgn:1000047",
          "tgn:7002457",
          "tgn:1000002",
          "tgn:7029392"
        ],
        "placetype": [
          "aat:300008347"
        ],
        "id": 1136495,
        "name:xx": "Aurora"
      }
    },
    {
      "geometry": {
        "type": "Point",
        "coordinates": [
          -54.3833,
          -19.8833
        ]
      },
      "type": "Feature",
      "properties": {
        "hierarchy": [
          "tgn:1136496",
          "tgn:1001898",
          "tgn:7002454",
          "tgn:1000047",
          "tgn:1000002",
          "tgn:7029392"
        ],
        "placetype": [
          "aat:300008347"
        ],
        "id": 1136496,
        "name:xx": "Bandeirantes"
      }
    },
    {
      "geometry": {
        "type": "Point",
        "coordinates": [
          -50.4,
          -23.1
        ]
      },
      "type": "Feature",
      "properties": {
        "hierarchy": [
          "tgn:1136497",
          "tgn:1001925",
          "tgn:1000047",
          "tgn:7002458",
          "tgn:1000002",
          "tgn:7029392"
        ],
        "placetype": [
          "aat:300008347"
        ],
        "id": 1136497,
        "name:xx": "Bandeirantes"
      }
    },
    {
      "geometry": {
        "type": "Point",
        "coordinates": [
          -37.1333,
          -9.6833
        ]
      },
      "type": "Feature",
      "properties": {
        "hierarchy": [
          "tgn:1136498",
          "tgn:7016581",
          "tgn:1000047",
          "tgn:7002455",
          "tgn:1000002",
          "tgn:7029392"
        ],
        "placetype": [
          "aat:300008347"
        ],
        "id": 1136498,
        "name:xx": "Batalha"
      }
    },
    {
      "geometry": {
        "type": "Point",
        "coordinates": [
          -42.5667,
          -22.8
        ]
      },
      "type": "Feature",
      "properties": {
        "hierarchy": [
          "tgn:1136499",
          "tgn:1001942",
          "tgn:1000047",
          "tgn:7002457",
          "tgn:1000002",
          "tgn:7029392"
        ],
        "placetype": [
          "aat:300008347"
        ],
        "id": 1136499,
        "name:xx": "Boa Esperança"
      }
    }
  ]
}
