{
  "geometry": {
    "type": "Point",
    "coordinates": [
      -106.4667,
      40.9833
    ]
  },
  "type": "Feature",
  "properties": {
    "hierarchy": [
      "tgn:2396432",
      "tgn:1000001",
      "tgn:7012149",
      "tgn:7029392"
    ],
    "placetype": [
      "aat:300008706"
    ],
    "id": 2396432,
    "name:xx": "Holroyd Creek"
  }
}
