{
  "geometry": {
    "type": "Point",
    "coordinates": [
      -103.555556,
      19.1875
    ]
  },
  "type": "Feature",
  "properties": {
    "hierarchy": [
      "tgn:7405225",
      "tgn:7016644",
      "tgn:1000001",
      "tgn:7005560",
      "tgn:7029392"
    ],
    "placetype": [
      "aat:300008347"
    ],
    "id": 7405225,
    "name:xx": "El Astillero de Arriba"
  }
}
