{
  "geometry": {
    "type": "Point",
    "coordinates": [
      -70.8333,
      42.9167
    ]
  },
  "type": "Feature",
  "properties": {
    "hierarchy": [
      "tgn:2481752",
      "tgn:1000001",
      "tgn:7014352",
      "tgn:7012149",
      "tgn:7007564",
      "tgn:7029392"
    ],
    "placetype": [
      "aat:300008699"
    ],
    "id": 2481752,
    "name:xx": "Landing Brook"
  }
}
