{
  "geometry": {
    "type": "Point",
    "coordinates": [
      9.55,
      9.8833
    ]
  },
  "type": "Feature",
  "properties": {
    "hierarchy": [
      "tgn:1090270",
      "tgn:7001242",
      "tgn:7000792",
      "tgn:1000167",
      "tgn:7029392"
    ],
    "placetype": [
      "aat:300008347"
    ],
    "id": 1090270,
    "name:xx": "Moribaya"
  }
}
