{
  "geometry": {
    "type": "Point",
    "coordinates": [
      -92.7667,
      29.9167
    ]
  },
  "type": "Feature",
  "properties": {
    "hierarchy": [
      "tgn:2360919",
      "tgn:1000001",
      "tgn:7020676",
      "tgn:7012149",
      "tgn:7007256",
      "tgn:7029392"
    ],
    "placetype": [
      "aat:300008850"
    ],
    "id": 2360919,
    "name:xx": "Grassy Point"
  }
}
