{
  "geometry": {
    "type": "Point",
    "coordinates": [
      -110.7667,
      34.4667
    ]
  },
  "type": "Feature",
  "properties": {
    "hierarchy": [
      "tgn:2402923",
      "tgn:1000001",
      "tgn:7006451",
      "tgn:2000092",
      "tgn:7012149",
      "tgn:7029392"
    ],
    "placetype": [
      "aat:300008761"
    ],
    "id": 2402923,
    "name:xx": "Houck Draw"
  }
}
