{
  "type": "FeatureCollection",
  "features": [
    {
      "geometry": {
        "type": "Point",
        "coordinates": [
          -119.0833,
          37.7333
        ]
      },
      "type": "Feature",
      "properties": {
        "hierarchy": [
          "tgn:2785950",
          "tgn:1000001",
          "tgn:7012149",
          "tgn:7007157",
          "tgn:1002675",
          "tgn:7029392"
        ],
        "placetype": [
          "aat:300008680"
        ],
        "id": 2785950,
        "name:xx": "Yost Lake"
      }
    },
    {
      "geometry": {
        "type": "Point",
        "coordinates": [
          -97,
          36.1833
        ]
      },
      "type": "Feature",
      "properties": {
        "hierarchy": [
          "tgn:2785951",
          "tgn:1000001",
          "tgn:7012149",
          "tgn:2001682",
          "tgn:7007707",
          "tgn:7029392"
        ],
        "placetype": [
          "aat:300006191"
        ],
        "id": 2785951,
        "name:xx": "Yost Reservoir"
      }
    },
    {
      "geometry": {
        "type": "Point",
        "coordinates": [
          -80.8333,
          39.8
        ]
      },
      "type": "Feature",
      "properties": {
        "hierarchy": [
          "tgn:2785952",
          "tgn:1000001",
          "tgn:7012149",
          "tgn:2001617",
          "tgn:7007706",
          "tgn:7029392"
        ],
        "placetype": [
          "aat:300008699"
        ],
        "id": 2785952,
        "name:xx": "Yost Run"
      }
    },
    {
      "geometry": {
        "type": "Point",
        "coordinates": [
          -75.5667,
          41
        ]
      },
      "type": "Feature",
      "properties": {
        "hierarchy": [
          "tgn:2785953",
          "tgn:1000001",
          "tgn:1002233",
          "tgn:7012149",
          "tgn:7007710",
          "tgn:7029392"
        ],
        "placetype": [
          "aat:300008905"
        ],
        "id": 2785953,
        "name:xx": "Yost Swamp"
      }
    },
    {
      "geometry": {
        "type": "Point",
        "coordinates": [
          -120.8833,
          39.2
        ]
      },
      "type": "Feature",
      "properties": {
        "hierarchy": [
          "tgn:2785954",
          "tgn:1000001",
          "tgn:7012149",
          "tgn:7007157",
          "tgn:1002710",
          "tgn:7029392"
        ],
        "placetype": [
          "aat:300008347"
        ],
        "id": 2785954,
        "name:xx": "You Bet"
      }
    },
    {
      "geometry": {
        "type": "Point",
        "coordinates": [
          -141.1167,
          68.7167
        ]
      },
      "type": "Feature",
      "properties": {
        "hierarchy": [
          "tgn:2785955",
          "tgn:7006450",
          "tgn:1000001",
          "tgn:7012149",
          "tgn:2124005",
          "tgn:7029392"
        ],
        "placetype": [
          "aat:300008706"
        ],
        "id": 2785955,
        "name:xx": "You Creek"
      }
    },
    {
      "geometry": {
        "type": "Point",
        "coordinates": [
          -89.3167,
          37.35
        ]
      },
      "type": "Feature",
      "properties": {
        "hierarchy": [
          "tgn:2785956",
          "tgn:1000001",
          "tgn:7012149",
          "tgn:2000534",
          "tgn:7007251",
          "tgn:7029392"
        ],
        "placetype": [
          "aat:300008761"
        ],
        "id": 2785956,
        "name:xx": "You-Be Hollow"
      }
    },
    {
      "geometry": {
        "type": "Point",
        "coordinates": [
          -81.7333,
          39.2
        ]
      },
      "type": "Feature",
      "properties": {
        "hierarchy": [
          "tgn:2785957",
          "tgn:2001610",
          "tgn:1000001",
          "tgn:7012149",
          "tgn:7007706",
          "tgn:7029392"
        ],
        "placetype": [
          "aat:300008347"
        ],
        "id": 2785957,
        "name:xx": "Youba"
      }
    },
    {
      "geometry": {
        "type": "Point",
        "coordinates": [
          -81.7333,
          39.2167
        ]
      },
      "type": "Feature",
      "properties": {
        "hierarchy": [
          "tgn:2785958",
          "tgn:2001610",
          "tgn:1000001",
          "tgn:7012149",
          "tgn:7007706",
          "tgn:7029392"
        ],
        "placetype": [
          "aat:300266640"
        ],
        "id": 2785958,
        "name:xx": "Youba Ridge"
      }
    },
    {
      "geometry": {
        "type": "Point",
        "coordinates": [
          -77.3,
          38.3833
        ]
      },
      "type": "Feature",
      "properties": {
        "hierarchy": [
          "tgn:2785959",
          "tgn:1000001",
          "tgn:7012149",
          "tgn:1002913",
          "tgn:7007919",
          "tgn:7029392"
        ],
        "placetype": [
          "aat:300008347"
        ],
        "id": 2785959,
        "name:xx": "Youbedamn Landing"
      }
    }
  ]
}
