{
  "geometry": {
    "type": "Point",
    "coordinates": [
      79.63871,
      26.963167
    ]
  },
  "type": "Feature",
  "properties": {
    "hierarchy": [
      "tgn:7564247",
      "tgn:1000004",
      "tgn:7000198",
      "tgn:7016722",
      "tgn:7029392"
    ],
    "placetype": [
      "aat:300008347"
    ],
    "name:en": "Dera Banjārān",
    "id": 7564247
  }
}
