{
  "geometry": {
    "type": "Point",
    "coordinates": [
      31.933333,
      29.15
    ]
  },
  "type": "Feature",
  "properties": {
    "hierarchy": [
      "tgn:7522133",
      "tgn:7001242",
      "tgn:7016833",
      "tgn:1001110",
      "tgn:7029392"
    ],
    "placetype": [
      "aat:300379998"
    ],
    "name:en": "Abu Rîsha, Wâdi",
    "id": 7522133
  }
}
