{
  "geometry": {
    "type": "Point",
    "coordinates": [
      74.751389,
      34.348611
    ]
  },
  "type": "Feature",
  "properties": {
    "hierarchy": [
      "tgn:7586142",
      "tgn:1000004",
      "tgn:7000198",
      "tgn:7000799",
      "tgn:7029392"
    ],
    "placetype": [
      "aat:300008347"
    ],
    "name:en": "Dātiwās",
    "id": 7586142
  }
}
