{
  "geometry": {
    "type": "Point",
    "coordinates": [
      -119.3833,
      36.5333
    ]
  },
  "type": "Feature",
  "properties": {
    "hierarchy": [
      "tgn:2011053",
      "tgn:1000001",
      "tgn:7012149",
      "tgn:7007157",
      "tgn:1002956",
      "tgn:7029392"
    ],
    "placetype": [
      "aat:300008347"
    ],
    "id": 2011053,
    "name:xx": "Dinuba"
  }
}
