{
  "geometry": {
    "type": "Point",
    "coordinates": [
      -75.8833,
      38.1667
    ]
  },
  "type": "Feature",
  "properties": {
    "hierarchy": [
      "tgn:2274777",
      "tgn:1000001",
      "tgn:1002902",
      "tgn:7012149",
      "tgn:7007516",
      "tgn:7029392"
    ],
    "placetype": [
      "aat:300008905"
    ],
    "id": 2274777,
    "name:xx": "Dames Quarter Marsh"
  }
}
