{
  "geometry": {
    "type": "Point",
    "coordinates": [
      -83.9833,
      39.8333
    ]
  },
  "type": "Feature",
  "properties": {
    "hierarchy": [
      "tgn:2385856",
      "tgn:1000001",
      "tgn:7012149",
      "tgn:1002424",
      "tgn:7007706",
      "tgn:7029392"
    ],
    "placetype": [
      "aat:300008347"
    ],
    "id": 2385856,
    "name:xx": "Hennessee"
  }
}
