{
  "type": "FeatureCollection",
  "features": [
    {
      "geometry": {
        "type": "Point",
        "coordinates": [
          30.333333,
          31
        ]
      },
      "type": "Feature",
      "properties": {
        "hierarchy": [
          "tgn:7526260",
          "tgn:7001242",
          "tgn:1001075",
          "tgn:7016833",
          "tgn:7029392"
        ],
        "placetype": [
          "aat:300000206"
        ],
        "name:en": "'Izbat 'Uthmān Hāshim",
        "id": 7526260
      }
    },
    {
      "geometry": {
        "type": "Point",
        "coordinates": [
          30.15,
          31.183333
        ]
      },
      "type": "Feature",
      "properties": {
        "hierarchy": [
          "tgn:7526261",
          "tgn:7001242",
          "tgn:1001075",
          "tgn:7016833",
          "tgn:7029392"
        ],
        "placetype": [
          "aat:300000206"
        ],
        "name:en": "'Izbat 'Uthmān Bey Murtaḑá",
        "id": 7526261
      }
    },
    {
      "geometry": {
        "type": "Point",
        "coordinates": [
          30.133333,
          31.083333
        ]
      },
      "type": "Feature",
      "properties": {
        "hierarchy": [
          "tgn:7526262",
          "tgn:7001242",
          "tgn:1001075",
          "tgn:7016833",
          "tgn:7029392"
        ],
        "placetype": [
          "aat:300000206"
        ],
        "name:en": "'Izbat 'Uthmān Aḩmad",
        "id": 7526262
      }
    },
    {
      "geometry": {
        "type": "Point",
        "coordinates": [
          33.733333,
          30.75
        ]
      },
      "type": "Feature",
      "properties": {
        "hierarchy": [
          "tgn:7526263",
          "tgn:7001242",
          "tgn:7016833",
          "tgn:7001335",
          "tgn:7029392"
        ],
        "placetype": [
          "aat:300379998"
        ],
        "name:en": "Uthaylī, Wādī al",
        "id": 7526263
      }
    },
    {
      "geometry": {
        "type": "Point",
        "coordinates": [
          27.903571,
          29.951136
        ]
      },
      "type": "Feature",
      "properties": {
        "hierarchy": [
          "tgn:7526264",
          "tgn:7001242",
          "tgn:7016833",
          "tgn:1001418",
          "tgn:7029392"
        ],
        "placetype": [
          "aat:300379998"
        ],
        "name:en": "Uthaylah, Wādī",
        "id": 7526264
      }
    },
    {
      "geometry": {
        "type": "Point",
        "coordinates": [
          33.048889,
          29.715556
        ]
      },
      "type": "Feature",
      "properties": {
        "hierarchy": [
          "tgn:7526265",
          "tgn:7001242",
          "tgn:7016833",
          "tgn:7001336",
          "tgn:7029392"
        ],
        "placetype": [
          "aat:300379998"
        ],
        "name:en": "Uthami, Wâdi el-",
        "id": 7526265
      }
    },
    {
      "geometry": {
        "type": "Point",
        "coordinates": [
          31.290833,
          29.538611
        ]
      },
      "type": "Feature",
      "properties": {
        "hierarchy": [
          "tgn:7526266",
          "tgn:7001242",
          "tgn:7016833",
          "tgn:1001083",
          "tgn:7029392"
        ],
        "placetype": [
          "aat:300008347"
        ],
        "name:en": "Askur",
        "id": 7526266
      }
    },
    {
      "geometry": {
        "type": "Point",
        "coordinates": [
          33.7,
          25.683333
        ]
      },
      "type": "Feature",
      "properties": {
        "hierarchy": [
          "tgn:7526267",
          "tgn:7001242",
          "tgn:7001311",
          "tgn:7016833",
          "tgn:7029392"
        ],
        "placetype": [
          "aat:300379998"
        ],
        "name:en": "'Ushsh, Wādī al",
        "id": 7526267
      }
    },
    {
      "geometry": {
        "type": "Point",
        "coordinates": [
          33.611862,
          27.48641
        ]
      },
      "type": "Feature",
      "properties": {
        "hierarchy": [
          "tgn:7526268",
          "tgn:7001242",
          "tgn:7001311",
          "tgn:7016833",
          "tgn:7029392"
        ],
        "placetype": [
          "aat:300379998"
        ],
        "name:en": "'Ushsh, Wādī",
        "id": 7526268
      }
    },
    {
      "geometry": {
        "type": "Point",
        "coordinates": [
          33.559582,
          27.886482
        ]
      },
      "type": "Feature",
      "properties": {
        "hierarchy": [
          "tgn:7526269",
          "tgn:7001242",
          "tgn:7001311",
          "tgn:7016833",
          "tgn:7029392"
        ],
        "placetype": [
          "aat:300386846"
        ],
        "name:en": "'Ushsh, Ra's al",
        "id": 7526269
      }
    }
  ]
}
