{
  "geometry": {
    "type": "Point",
    "coordinates": [
      82.7833,
      37.0333
    ]
  },
  "type": "Feature",
  "properties": {
    "hierarchy": [
      "tgn:1070479",
      "tgn:1000004",
      "tgn:7001745",
      "tgn:1000111",
      "tgn:7029392"
    ],
    "placetype": [
      "aat:300008347"
    ],
    "id": 1070479,
    "name:xx": "Minfeng"
  }
}
