{
  "geometry": {
    "type": "Point",
    "coordinates": [
      -87.15,
      41.5333
    ]
  },
  "type": "Feature",
  "properties": {
    "hierarchy": [
      "tgn:2689884",
      "tgn:1000001",
      "tgn:7012149",
      "tgn:1002798",
      "tgn:7007252",
      "tgn:7029392"
    ],
    "placetype": [
      "aat:300008706"
    ],
    "id": 2689884,
    "name:xx": "Squirrel Creek"
  }
}
