{
  "geometry": {
    "type": "Point",
    "coordinates": [
      -85.5667,
      30.6667
    ]
  },
  "type": "Feature",
  "properties": {
    "hierarchy": [
      "tgn:2343380",
      "tgn:1000001",
      "tgn:7012149",
      "tgn:2000291",
      "tgn:7007240",
      "tgn:7029392"
    ],
    "placetype": [
      "aat:300008905"
    ],
    "id": 2343380,
    "name:xx": "Gainer Lake"
  }
}
