{
  "geometry": {
    "type": "Point",
    "coordinates": [
      -85.05,
      34.5833
    ]
  },
  "type": "Feature",
  "properties": {
    "hierarchy": [
      "tgn:2399380",
      "tgn:1000001",
      "tgn:7012149",
      "tgn:7007248",
      "tgn:7029392"
    ],
    "placetype": [
      "aat:300008798"
    ],
    "id": 2399380,
    "name:xx": "Horn Mountain"
  }
}
