{
  "type": "FeatureCollection",
  "features": [
    {
      "geometry": {
        "type": "Point",
        "coordinates": [
          -3.083333,
          52.483333
        ]
      },
      "type": "Feature",
      "properties": {
        "hierarchy": [
          "tgn:7458220",
          "tgn:7002445",
          "tgn:1000003",
          "tgn:7012034",
          "tgn:7008591",
          "tgn:7029392"
        ],
        "placetype": [
          "aat:300008347"
        ],
        "name:en": "Mainstone",
        "id": 7458220
      }
    },
    {
      "geometry": {
        "type": "Point",
        "coordinates": [
          -3.65,
          54.883333
        ]
      },
      "type": "Feature",
      "properties": {
        "hierarchy": [
          "tgn:7458221",
          "tgn:7002444",
          "tgn:7008074",
          "tgn:1000003",
          "tgn:7008591",
          "tgn:7029392"
        ],
        "placetype": [
          "aat:300008347"
        ],
        "name:en": "Mainsriddle",
        "id": 7458221
      }
    },
    {
      "geometry": {
        "type": "Point",
        "coordinates": [
          -3.483333,
          57.35
        ]
      },
      "type": "Feature",
      "properties": {
        "hierarchy": [
          "tgn:7458222",
          "tgn:7002444",
          "tgn:1000003",
          "tgn:7008082",
          "tgn:7008591",
          "tgn:7029392"
        ],
        "placetype": [
          "aat:300008347"
        ],
        "name:en": "Mains of Dalvey",
        "id": 7458222
      }
    }
  ]
}
