{
  "geometry": {
    "type": "Point",
    "coordinates": [
      -121.8333,
      46.7833
    ]
  },
  "type": "Feature",
  "properties": {
    "hierarchy": [
      "tgn:2411369",
      "tgn:1000001",
      "tgn:7012149",
      "tgn:1002785",
      "tgn:7007920",
      "tgn:7029392"
    ],
    "placetype": [
      "aat:300055621"
    ],
    "id": 2411369,
    "name:xx": "Indian Henrys Hunting Ground"
  }
}
