{
  "geometry": {
    "type": "Point",
    "coordinates": [
      -94.9667,
      34.9667
    ]
  },
  "type": "Feature",
  "properties": {
    "hierarchy": [
      "tgn:2572327",
      "tgn:1000001",
      "tgn:7012149",
      "tgn:7007707",
      "tgn:7029392"
    ],
    "placetype": [
      "aat:300008706"
    ],
    "id": 2572327,
    "name:xx": "Peach Creek"
  }
}
