{
  "type": "FeatureCollection",
  "features": [
    {
      "geometry": {
        "type": "Point",
        "coordinates": [
          -83.6667,
          40.3333
        ]
      },
      "type": "Feature",
      "properties": {
        "hierarchy": [
          "tgn:2082741",
          "tgn:1000001",
          "tgn:7012149",
          "tgn:1002606",
          "tgn:7007706",
          "tgn:7029392"
        ],
        "placetype": [
          "aat:300008347"
        ],
        "id": 2082741,
        "name:xx": "Zanesfield"
      }
    },
    {
      "geometry": {
        "type": "Point",
        "coordinates": [
          -84.7,
          40.3667
        ]
      },
      "type": "Feature",
      "properties": {
        "hierarchy": [
          "tgn:2082746",
          "tgn:1000001",
          "tgn:7012149",
          "tgn:1002658",
          "tgn:7007706",
          "tgn:7029392"
        ],
        "placetype": [
          "aat:300008347"
        ],
        "id": 2082746,
        "name:xx": "Sharpsburg"
      }
    },
    {
      "geometry": {
        "type": "Point",
        "coordinates": [
          -82.35,
          39.85
        ]
      },
      "type": "Feature",
      "properties": {
        "hierarchy": [
          "tgn:2082748",
          "tgn:1000001",
          "tgn:7012149",
          "tgn:2001620",
          "tgn:7007706",
          "tgn:7029392"
        ],
        "placetype": [
          "aat:300008347"
        ],
        "id": 2082748,
        "name:xx": "Ziontown"
      }
    },
    {
      "geometry": {
        "type": "Point",
        "coordinates": [
          -84.1833,
          39.35
        ]
      },
      "type": "Feature",
      "properties": {
        "hierarchy": [
          "tgn:2082749",
          "tgn:1000001",
          "tgn:7012149",
          "tgn:1002987",
          "tgn:7007706",
          "tgn:7029392"
        ],
        "placetype": [
          "aat:300008347"
        ],
        "id": 2082749,
        "name:xx": "Zoar"
      }
    }
  ]
}
