{
  "geometry": {
    "type": "Point",
    "coordinates": [
      -122.35,
      37.35
    ]
  },
  "type": "Feature",
  "properties": {
    "hierarchy": [
      "tgn:2263752",
      "tgn:1000001",
      "tgn:7012149",
      "tgn:7007157",
      "tgn:1002864",
      "tgn:7029392"
    ],
    "placetype": [
      "aat:300008706"
    ],
    "id": 2263752,
    "name:xx": "Coyote Creek"
  }
}
