{
  "geometry": {
    "type": "Point",
    "coordinates": [
      -97.0333,
      28.0333
    ]
  },
  "type": "Feature",
  "properties": {
    "hierarchy": [
      "tgn:2219586",
      "tgn:7013313",
      "tgn:1000001",
      "tgn:7012149",
      "tgn:7007826",
      "tgn:7029392"
    ],
    "placetype": [
      "aat:300008680"
    ],
    "id": 2219586,
    "name:xx": "Canoe Lake"
  }
}
