{
  "geometry": {
    "type": "Point",
    "coordinates": [
      -112.8667,
      46.7167
    ]
  },
  "type": "Feature",
  "properties": {
    "hierarchy": [
      "tgn:2337329",
      "tgn:1000001",
      "tgn:7012149",
      "tgn:2001298",
      "tgn:7007524",
      "tgn:7029392"
    ],
    "placetype": [
      "aat:300266640"
    ],
    "id": 2337329,
    "name:xx": "Fourth of July Ridge"
  }
}
