{
  "geometry": {
    "type": "Point",
    "coordinates": [
      -9.254,
      38.756
    ]
  },
  "type": "Feature",
  "properties": {
    "hierarchy": [
      "tgn:7010996",
      "tgn:1000882",
      "tgn:1000003",
      "tgn:1000090",
      "tgn:7029392"
    ],
    "placetype": [
      "aat:300008347"
    ],
    "id": 7010996,
    "name:xx": "Queluz"
  }
}
