{
  "geometry": {
    "type": "Point",
    "coordinates": [
      -78.7667,
      36.8667
    ]
  },
  "type": "Feature",
  "properties": {
    "hierarchy": [
      "tgn:2494931",
      "tgn:1000001",
      "tgn:7012149",
      "tgn:2002166",
      "tgn:7007919",
      "tgn:7029392"
    ],
    "placetype": [
      "aat:300008699"
    ],
    "id": 2494931,
    "name:xx": "Martins Branch"
  }
}
