{
  "geometry": {
    "type": "Point",
    "coordinates": [
      -83.85,
      37.9167
    ]
  },
  "type": "Feature",
  "properties": {
    "hierarchy": [
      "tgn:2460162",
      "tgn:1000001",
      "tgn:7012149",
      "tgn:2000803",
      "tgn:7007255",
      "tgn:7029392"
    ],
    "placetype": [
      "aat:300008798"
    ],
    "id": 2460162,
    "name:xx": "Little Round Mountain"
  }
}
