{
  "geometry": {
    "type": "Point",
    "coordinates": [
      -90.3333,
      35.0333
    ]
  },
  "type": "Feature",
  "properties": {
    "hierarchy": [
      "tgn:2158282",
      "tgn:1000001",
      "tgn:7016172",
      "tgn:2000122",
      "tgn:7012149",
      "tgn:7029392"
    ],
    "placetype": [
      "aat:300008699"
    ],
    "id": 2158282,
    "name:xx": "Beaver Slu"
  }
}
