{
  "type": "FeatureCollection",
  "features": [
    {
      "geometry": {
        "type": "Point",
        "coordinates": [
          15.583333,
          40
        ]
      },
      "type": "Feature",
      "properties": {
        "hierarchy": [
          "tgn:1112451",
          "tgn:7003005",
          "tgn:7003014",
          "tgn:1000003",
          "tgn:1000080",
          "tgn:7029392"
        ],
        "placetype": [
          "aat:300132315"
        ],
        "id": 1112451,
        "name:xx": "Policastro, Golfo di"
      }
    },
    {
      "geometry": {
        "type": "Point",
        "coordinates": [
          8.5833,
          42.25
        ]
      },
      "type": "Feature",
      "properties": {
        "hierarchy": [
          "tgn:1112452",
          "tgn:1000003",
          "tgn:7594273",
          "tgn:1000070",
          "tgn:7029392"
        ],
        "placetype": [
          "aat:300132315"
        ],
        "id": 1112452,
        "name:xx": "Porto, Golfe de"
      }
    },
    {
      "geometry": {
        "type": "Point",
        "coordinates": [
          9.4833,
          41.4667
        ]
      },
      "type": "Feature",
      "properties": {
        "hierarchy": [
          "tgn:1112453",
          "tgn:1000003",
          "tgn:7594273",
          "tgn:1000070",
          "tgn:7029392"
        ],
        "placetype": [
          "aat:300132315"
        ],
        "id": 1112453,
        "name:xx": "Porto-Vecchio, Golfe de"
      }
    },
    {
      "geometry": {
        "type": "Point",
        "coordinates": [
          14.116667,
          40.8
        ]
      },
      "type": "Feature",
      "properties": {
        "hierarchy": [
          "tgn:1112454",
          "tgn:7003013",
          "tgn:7003005",
          "tgn:1000003",
          "tgn:1000080",
          "tgn:7029392"
        ],
        "placetype": [
          "aat:300132315"
        ],
        "id": 1112454,
        "name:xx": "Pozzuoli, Golfo di"
      }
    },
    {
      "geometry": {
        "type": "Point",
        "coordinates": [
          -102.5,
          68.4167
        ]
      },
      "type": "Feature",
      "properties": {
        "hierarchy": [
          "tgn:1112455",
          "tgn:7005685",
          "tgn:1000001",
          "tgn:7024197",
          "tgn:7029392"
        ],
        "placetype": [
          "aat:300132315"
        ],
        "id": 1112455,
        "name:xx": "Queen Maud Gulf"
      }
    },
    {
      "geometry": {
        "type": "Point",
        "coordinates": [
          122.75,
          13.5
        ]
      },
      "type": "Feature",
      "properties": {
        "hierarchy": [
          "tgn:1112456",
          "tgn:1000004",
          "tgn:1000135",
          "tgn:7029392"
        ],
        "placetype": [
          "aat:300132315"
        ],
        "id": 1112456,
        "name:xx": "Ragay Gulf"
      }
    },
    {
      "geometry": {
        "type": "Point",
        "coordinates": [
          23.5833,
          57.5
        ]
      },
      "type": "Feature",
      "properties": {
        "hierarchy": [
          "tgn:1112457",
          "tgn:1000003",
          "tgn:7029392"
        ],
        "placetype": [
          "aat:300132315"
        ],
        "name:en": "Riga, Gulf of",
        "id": 1112457,
        "name:xx": "Rizhskiy Zaliv"
      }
    },
    {
      "geometry": {
        "type": "Point",
        "coordinates": [
          3.25,
          42.166667
        ]
      },
      "type": "Feature",
      "properties": {
        "hierarchy": [
          "tgn:1112458",
          "tgn:7002820",
          "tgn:7030216",
          "tgn:1000003",
          "tgn:1000095",
          "tgn:7029392"
        ],
        "placetype": [
          "aat:300132315"
        ],
        "id": 1112458,
        "name:xx": "Rosas, Golfo de"
      }
    }
  ]
}
