{
  "geometry": {
    "type": "Point",
    "coordinates": [
      26.901007,
      30.74715
    ]
  },
  "type": "Feature",
  "properties": {
    "hierarchy": [
      "tgn:7537383",
      "tgn:7001242",
      "tgn:7016833",
      "tgn:1001418",
      "tgn:7029392"
    ],
    "placetype": [
      "aat:300008749"
    ],
    "name:en": "Quşayr, Minqār al",
    "id": 7537383
  }
}
