{
  "geometry": {
    "type": "Point",
    "coordinates": [
      -87.7167,
      31.3333
    ]
  },
  "type": "Feature",
  "properties": {
    "hierarchy": [
      "tgn:2527405",
      "tgn:7002659",
      "tgn:1000001",
      "tgn:7012149",
      "tgn:2000049",
      "tgn:7029392"
    ],
    "placetype": [
      "aat:300008347"
    ],
    "id": 2527405,
    "name:xx": "Mount Pleasant Landing"
  }
}
