{
  "geometry": {
    "type": "Point",
    "coordinates": [
      -156.6167,
      63.0667
    ]
  },
  "type": "Feature",
  "properties": {
    "hierarchy": [
      "tgn:2290220",
      "tgn:7006450",
      "tgn:1000001",
      "tgn:7012149",
      "tgn:2000089",
      "tgn:7029392"
    ],
    "placetype": [
      "aat:300008706"
    ],
    "id": 2290220,
    "name:xx": "Dodge Creek"
  }
}
