{
  "geometry": {
    "type": "Point",
    "coordinates": [
      -75.3833,
      39.35
    ]
  },
  "type": "Feature",
  "properties": {
    "hierarchy": [
      "tgn:2301196",
      "tgn:1002309",
      "tgn:1000001",
      "tgn:7012149",
      "tgn:7007565",
      "tgn:7029392"
    ],
    "placetype": [
      "aat:300008850"
    ],
    "id": 2301196,
    "name:xx": "Dunks Point"
  }
}
