{
  "geometry": {
    "type": "Point",
    "coordinates": [
      -104.8833,
      39.9833
    ]
  },
  "type": "Feature",
  "properties": {
    "hierarchy": [
      "tgn:2662655",
      "tgn:2000192",
      "tgn:1000001",
      "tgn:7012149",
      "tgn:7007158",
      "tgn:7029392"
    ],
    "placetype": [
      "aat:300006191"
    ],
    "id": 2662655,
    "name:xx": "Signal Reservoir Number 1"
  }
}
