{
  "geometry": {
    "type": "Point",
    "coordinates": [
      -81.2833,
      41.2333
    ]
  },
  "type": "Feature",
  "properties": {
    "hierarchy": [
      "tgn:2339742",
      "tgn:1000001",
      "tgn:7012149",
      "tgn:1002797",
      "tgn:7007706",
      "tgn:7029392"
    ],
    "placetype": [
      "aat:300008347"
    ],
    "id": 2339742,
    "name:xx": "Freedom Dam"
  }
}
