{
  "geometry": {
    "type": "Point",
    "coordinates": [
      34.654287,
      29.54022
    ]
  },
  "type": "Feature",
  "properties": {
    "hierarchy": [
      "tgn:7541366",
      "tgn:7001242",
      "tgn:7016833",
      "tgn:7001336",
      "tgn:7029392"
    ],
    "placetype": [
      "aat:300379998"
    ],
    "name:en": "Biyār, Wādī",
    "id": 7541366
  }
}
