{
  "geometry": {
    "type": "Point",
    "coordinates": [
      21.35,
      37.816667
    ]
  },
  "type": "Feature",
  "properties": {
    "hierarchy": [
      "tgn:7236795",
      "tgn:7002743",
      "tgn:7017076",
      "tgn:1000003",
      "tgn:1000074",
      "tgn:7029392"
    ],
    "placetype": [
      "aat:300008347"
    ],
    "id": 7236795,
    "name:xx": "Áyios Ioánnis"
  }
}
