{
  "geometry": {
    "type": "Point",
    "coordinates": [
      -76.35,
      -6.3667
    ]
  },
  "type": "Feature",
  "properties": {
    "hierarchy": [
      "tgn:1024736",
      "tgn:1000749",
      "tgn:1000002",
      "tgn:1000056",
      "tgn:7029392"
    ],
    "placetype": [
      "aat:300008347"
    ],
    "id": 1024736,
    "name:xx": "San Antonio"
  }
}
