{
  "type": "FeatureCollection",
  "features": [
    {
      "geometry": {
        "type": "Point",
        "coordinates": [
          -3.1,
          53.383333
        ]
      },
      "type": "Feature",
      "properties": {
        "hierarchy": [
          "tgn:1136760",
          "tgn:7002445",
          "tgn:1003666",
          "tgn:1000003",
          "tgn:7029504",
          "tgn:7008591",
          "tgn:7029392"
        ],
        "placetype": [
          "aat:300008347"
        ],
        "name:en": "Upton",
        "id": 1136760
      }
    },
    {
      "geometry": {
        "type": "Point",
        "coordinates": [
          -2.766667,
          54.133333
        ]
      },
      "type": "Feature",
      "properties": {
        "hierarchy": [
          "tgn:1136763",
          "tgn:7002445",
          "tgn:1000003",
          "tgn:7008154",
          "tgn:7008591",
          "tgn:7029392"
        ],
        "placetype": [
          "aat:300008347",
          "aat:300008372"
        ],
        "name:en": "Warton",
        "id": 1136763
      }
    },
    {
      "geometry": {
        "type": "Point",
        "coordinates": [
          -2.516667,
          52.7
        ]
      },
      "type": "Feature",
      "properties": {
        "hierarchy": [
          "tgn:1136764",
          "tgn:7002445",
          "tgn:1000003",
          "tgn:7012034",
          "tgn:7008591",
          "tgn:7029392"
        ],
        "placetype": [
          "aat:300008347"
        ],
        "name:en": "Wellington",
        "id": 1136764
      }
    },
    {
      "geometry": {
        "type": "Point",
        "coordinates": [
          -0.0667,
          51.7333
        ]
      },
      "type": "Feature",
      "properties": {
        "hierarchy": [
          "tgn:1136765",
          "tgn:7002445",
          "tgn:1000003",
          "tgn:7008145",
          "tgn:7008591",
          "tgn:7029392"
        ],
        "placetype": [
          "aat:300008347"
        ],
        "id": 1136765,
        "name:xx": "West End"
      }
    },
    {
      "geometry": {
        "type": "Point",
        "coordinates": [
          -2.95,
          52.683333
        ]
      },
      "type": "Feature",
      "properties": {
        "hierarchy": [
          "tgn:1136766",
          "tgn:7002445",
          "tgn:1000003",
          "tgn:7012034",
          "tgn:7008591",
          "tgn:7029392"
        ],
        "placetype": [
          "aat:300008347"
        ],
        "name:en": "Westbury",
        "id": 1136766
      }
    },
    {
      "geometry": {
        "type": "Point",
        "coordinates": [
          -0.833333,
          51.883333
        ]
      },
      "type": "Feature",
      "properties": {
        "hierarchy": [
          "tgn:1136769",
          "tgn:7002445",
          "tgn:7008104",
          "tgn:1000003",
          "tgn:7008591",
          "tgn:7029392"
        ],
        "placetype": [
          "aat:300008347"
        ],
        "id": 1136769,
        "name:ang": "Wicherce"
      }
    }
  ]
}
