{
  "geometry": {
    "type": "Point",
    "coordinates": [
      -87.5833,
      34.5667
    ]
  },
  "type": "Feature",
  "properties": {
    "hierarchy": [
      "tgn:2592958",
      "tgn:7002659",
      "tgn:1000001",
      "tgn:2000016",
      "tgn:7012149",
      "tgn:7029392"
    ],
    "placetype": [
      "aat:300008706"
    ],
    "id": 2592958,
    "name:xx": "Poplar Creek"
  }
}
