{
  "geometry": {
    "type": "Point",
    "coordinates": [
      -62.9833,
      -35.0167
    ]
  },
  "type": "Feature",
  "properties": {
    "hierarchy": [
      "tgn:1019518",
      "tgn:1001160",
      "tgn:7006477",
      "tgn:1000002",
      "tgn:7029392"
    ],
    "placetype": [
      "aat:300008347"
    ],
    "id": 1019518,
    "name:xx": "General Villegas"
  }
}
