{
  "type": "FeatureCollection",
  "features": [
    {
      "geometry": {
        "type": "Point",
        "coordinates": [
          -103.383333,
          29
        ]
      },
      "type": "Feature",
      "properties": {
        "hierarchy": [
          "tgn:7356760",
          "tgn:7005581",
          "tgn:1000001",
          "tgn:7005560",
          "tgn:7029392"
        ],
        "placetype": [
          "aat:300008777"
        ],
        "id": 7356760,
        "name:xx": "Chino, Cerro del"
      }
    },
    {
      "geometry": {
        "type": "Point",
        "coordinates": [
          -107.066667,
          30.983333
        ]
      },
      "type": "Feature",
      "properties": {
        "hierarchy": [
          "tgn:7356761",
          "tgn:7005581",
          "tgn:1000001",
          "tgn:7005560",
          "tgn:7029392"
        ],
        "placetype": [
          "aat:300008795"
        ],
        "id": 7356761,
        "name:xx": "Chino, Cerro"
      }
    },
    {
      "geometry": {
        "type": "Point",
        "coordinates": [
          -106.9,
          30.8
        ]
      },
      "type": "Feature",
      "properties": {
        "hierarchy": [
          "tgn:7356762",
          "tgn:7005581",
          "tgn:1000001",
          "tgn:7005560",
          "tgn:7029392"
        ],
        "placetype": [
          "aat:300008795"
        ],
        "id": 7356762,
        "name:xx": "Chino, Cerro"
      }
    },
    {
      "geometry": {
        "type": "Point",
        "coordinates": [
          -111.966667,
          30.483333
        ]
      },
      "type": "Feature",
      "properties": {
        "hierarchy": [
          "tgn:7356763",
          "tgn:1000001",
          "tgn:1001960",
          "tgn:7005560",
          "tgn:7029392"
        ],
        "placetype": [
          "aat:300008795"
        ],
        "id": 7356763,
        "name:xx": "Chino, Cerro"
      }
    },
    {
      "geometry": {
        "type": "Point",
        "coordinates": [
          -104.7,
          29.483333
        ]
      },
      "type": "Feature",
      "properties": {
        "hierarchy": [
          "tgn:7356764",
          "tgn:7005581",
          "tgn:1000001",
          "tgn:7005560",
          "tgn:7029392"
        ],
        "placetype": [
          "aat:300008777"
        ],
        "id": 7356764,
        "name:xx": "Chino, Cerro"
      }
    },
    {
      "geometry": {
        "type": "Point",
        "coordinates": [
          -111.15,
          29.433333
        ]
      },
      "type": "Feature",
      "properties": {
        "hierarchy": [
          "tgn:7356765",
          "tgn:1000001",
          "tgn:1001960",
          "tgn:7005560",
          "tgn:7029392"
        ],
        "placetype": [
          "aat:300008347"
        ],
        "id": 7356765,
        "name:xx": "Chino"
      }
    },
    {
      "geometry": {
        "type": "Point",
        "coordinates": [
          -104.15,
          29.383333
        ]
      },
      "type": "Feature",
      "properties": {
        "hierarchy": [
          "tgn:7356766",
          "tgn:7005581",
          "tgn:1000001",
          "tgn:7005560",
          "tgn:7029392"
        ],
        "placetype": [
          "aat:300008347"
        ],
        "id": 7356766,
        "name:xx": "Chino"
      }
    },
    {
      "geometry": {
        "type": "Point",
        "coordinates": [
          -89.4,
          20.683333
        ]
      },
      "type": "Feature",
      "properties": {
        "hierarchy": [
          "tgn:7356767",
          "tgn:1000001",
          "tgn:7005600",
          "tgn:7005560",
          "tgn:7029392"
        ],
        "placetype": [
          "aat:300008347"
        ],
        "id": 7356767,
        "name:xx": "Chinkilá"
      }
    }
  ]
}
