{
  "geometry": {
    "type": "Point",
    "coordinates": [
      -105.1667,
      32.0833
    ]
  },
  "type": "Feature",
  "properties": {
    "hierarchy": [
      "tgn:2471718",
      "tgn:1000001",
      "tgn:7012149",
      "tgn:2001447",
      "tgn:7007566",
      "tgn:7029392"
    ],
    "placetype": [
      "aat:300008680"
    ],
    "id": 2471718,
    "name:xx": "Lost Pond"
  }
}
