{
  "geometry": {
    "type": "Point",
    "coordinates": [
      -101.05,
      33.6167
    ]
  },
  "type": "Feature",
  "properties": {
    "hierarchy": [
      "tgn:2576894",
      "tgn:1000001",
      "tgn:7012149",
      "tgn:2001968",
      "tgn:7007826",
      "tgn:7029392"
    ],
    "placetype": [
      "aat:300008706"
    ],
    "id": 2576894,
    "name:xx": "Pete Creek"
  }
}
