{
  "geometry": {
    "type": "Point",
    "coordinates": [
      -69.5833,
      45.5167
    ]
  },
  "type": "Feature",
  "properties": {
    "hierarchy": [
      "tgn:2186047",
      "tgn:1000001",
      "tgn:7012149",
      "tgn:2000928",
      "tgn:7007515",
      "tgn:7029392"
    ],
    "placetype": [
      "aat:300132316"
    ],
    "id": 2186047,
    "name:xx": "Bolton Cove"
  }
}
