{
  "geometry": {
    "type": "Point",
    "coordinates": [
      -96.4667,
      42.1667
    ]
  },
  "type": "Feature",
  "properties": {
    "hierarchy": [
      "tgn:2558950",
      "tgn:1000001",
      "tgn:7012149",
      "tgn:7007525",
      "tgn:7029392"
    ],
    "placetype": [
      "aat:300008706"
    ],
    "id": 2558950,
    "name:xx": "Omaha Creek"
  }
}
