{
  "geometry": {
    "type": "Point",
    "coordinates": [
      128.1167,
      26.55
    ]
  },
  "type": "Feature",
  "properties": {
    "hierarchy": [
      "tgn:1080512",
      "tgn:1010195",
      "tgn:7004299",
      "tgn:1000004",
      "tgn:7000902",
      "tgn:1001016",
      "tgn:1000120",
      "tgn:7029392"
    ],
    "placetype": [
      "aat:300008347"
    ],
    "id": 1080512,
    "name:xx": "Kayō"
  }
}
