{
  "geometry": {
    "type": "Point",
    "coordinates": [
      -2.45,
      53.4833
    ]
  },
  "type": "Feature",
  "properties": {
    "hierarchy": [
      "tgn:1028352",
      "tgn:7002445",
      "tgn:1003664",
      "tgn:1000003",
      "tgn:7026570",
      "tgn:7008591",
      "tgn:7029392"
    ],
    "placetype": [
      "aat:300008347"
    ],
    "id": 1028352,
    "name:xx": "Astley Green"
  }
}
