{
  "geometry": {
    "type": "Point",
    "coordinates": [
      -76.0667,
      42.4833
    ]
  },
  "type": "Feature",
  "properties": {
    "hierarchy": [
      "tgn:2070525",
      "tgn:1000001",
      "tgn:1002302",
      "tgn:7012149",
      "tgn:7007568",
      "tgn:7029392"
    ],
    "placetype": [
      "aat:300008347",
      "aat:300387210"
    ],
    "id": 2070525,
    "name:xx": "Messengerville"
  }
}
