{
  "geometry": {
    "type": "Point",
    "coordinates": [
      -69.7167,
      44.5333
    ]
  },
  "type": "Feature",
  "properties": {
    "hierarchy": [
      "tgn:2506948",
      "tgn:1000001",
      "tgn:2000923",
      "tgn:7012149",
      "tgn:7007515",
      "tgn:7029392"
    ],
    "placetype": [
      "aat:300008699"
    ],
    "id": 2506948,
    "name:xx": "Messalonskee Stream"
  }
}
