{
  "geometry": {
    "type": "Point",
    "coordinates": [
      -89.2833,
      39.55
    ]
  },
  "type": "Feature",
  "properties": {
    "hierarchy": [
      "tgn:1002268",
      "tgn:1000001",
      "tgn:7012149",
      "tgn:7007251",
      "tgn:7029392"
    ],
    "placetype": [
      "aat:300387145",
      "aat:300000771"
    ],
    "id": 1002268,
    "name:xx": "Christian"
  }
}
