{
  "geometry": {
    "type": "Point",
    "coordinates": [
      82.45,
      20.35
    ]
  },
  "type": "Feature",
  "properties": {
    "hierarchy": [
      "tgn:7557728",
      "tgn:1000004",
      "tgn:7000198",
      "tgn:7016694",
      "tgn:7029392"
    ],
    "placetype": [
      "aat:300008347"
    ],
    "name:en": "Pātdarha",
    "id": 7557728
  }
}
