{
  "geometry": {
    "type": "Point",
    "coordinates": [
      -3.2333,
      51.7167
    ]
  },
  "type": "Feature",
  "properties": {
    "hierarchy": [
      "tgn:4009236",
      "tgn:7002443",
      "tgn:1000003",
      "tgn:7018974",
      "tgn:7008591",
      "tgn:7029392"
    ],
    "placetype": [
      "aat:300008347"
    ],
    "id": 4009236,
    "name:xx": "Rheola"
  }
}
