{
  "geometry": {
    "type": "Point",
    "coordinates": [
      15.6667,
      -0.0167
    ]
  },
  "type": "Feature",
  "properties": {
    "hierarchy": [
      "tgn:1088682",
      "tgn:7001242",
      "tgn:1000972",
      "tgn:1000158",
      "tgn:7029392"
    ],
    "placetype": [
      "aat:300008347"
    ],
    "id": 1088682,
    "name:xx": "Makoua"
  }
}
