{
  "geometry": {
    "type": "Point",
    "coordinates": [
      129.7167,
      -19.9667
    ]
  },
  "type": "Feature",
  "properties": {
    "hierarchy": [
      "tgn:1098269",
      "tgn:7000490",
      "tgn:1000006",
      "tgn:7001829",
      "tgn:7029392"
    ],
    "placetype": [
      "aat:300008347"
    ],
    "id": 1098269,
    "name:xx": "Tanami"
  }
}
