{
  "geometry": {
    "type": "Point",
    "coordinates": [
      -89.45,
      39.85
    ]
  },
  "type": "Feature",
  "properties": {
    "hierarchy": [
      "tgn:2027416",
      "tgn:1000001",
      "tgn:7012149",
      "tgn:1002866",
      "tgn:7007251",
      "tgn:7029392"
    ],
    "placetype": [
      "aat:300008347"
    ],
    "id": 2027416,
    "name:xx": "Dawson"
  }
}
