{
  "geometry": {
    "type": "Point",
    "coordinates": [
      33.282222,
      29.55
    ]
  },
  "type": "Feature",
  "properties": {
    "hierarchy": [
      "tgn:7535861",
      "tgn:7001242",
      "tgn:7016833",
      "tgn:7001336",
      "tgn:7029392"
    ],
    "placetype": [
      "aat:300379998"
    ],
    "id": 7535861,
    "name:xx": "Fawqīyah, Wādī al"
  }
}
