{
  "geometry": {
    "type": "Point",
    "coordinates": [
      -82.1333,
      28.6667
    ]
  },
  "type": "Feature",
  "properties": {
    "hierarchy": [
      "tgn:2438007",
      "tgn:1000001",
      "tgn:7012149",
      "tgn:1002929",
      "tgn:7007240",
      "tgn:7029392"
    ],
    "placetype": [
      "aat:300008680"
    ],
    "id": 2438007,
    "name:xx": "King Pond"
  }
}
