{
  "geometry": {
    "type": "Point",
    "coordinates": [
      -108.4333,
      42.55
    ]
  },
  "type": "Feature",
  "properties": {
    "hierarchy": [
      "tgn:2514969",
      "tgn:1000001",
      "tgn:7012149",
      "tgn:2002371",
      "tgn:7007923",
      "tgn:7029392"
    ],
    "placetype": [
      "aat:300008697"
    ],
    "id": 2514969,
    "name:xx": "Miller Spring"
  }
}
