{
  "geometry": {
    "type": "Point",
    "coordinates": [
      30.28192,
      30.913156
    ]
  },
  "type": "Feature",
  "properties": {
    "hierarchy": [
      "tgn:7521943",
      "tgn:7001242",
      "tgn:1001075",
      "tgn:7016833",
      "tgn:7029392"
    ],
    "placetype": [
      "aat:300008347"
    ],
    "name:en": "Al Būţah",
    "id": 7521943
  }
}
