{
  "type": "FeatureCollection",
  "features": [
    {
      "geometry": {
        "type": "Point",
        "coordinates": [
          -78.75,
          38.15
        ]
      },
      "type": "Feature",
      "properties": {
        "hierarchy": [
          "tgn:2591920",
          "tgn:2002137",
          "tgn:1000001",
          "tgn:7012149",
          "tgn:7007919",
          "tgn:7029392"
        ],
        "placetype": [
          "aat:300266640"
        ],
        "id": 2591920,
        "name:xx": "Pond Ridge"
      }
    },
    {
      "geometry": {
        "type": "Point",
        "coordinates": [
          -79.0333,
          38.5667
        ]
      },
      "type": "Feature",
      "properties": {
        "hierarchy": [
          "tgn:2591921",
          "tgn:1000001",
          "tgn:7012149",
          "tgn:2002187",
          "tgn:7007919",
          "tgn:7029392"
        ],
        "placetype": [
          "aat:300266640"
        ],
        "id": 2591921,
        "name:xx": "Pond Ridge"
      }
    },
    {
      "geometry": {
        "type": "Point",
        "coordinates": [
          -81,
          37.4833
        ]
      },
      "type": "Feature",
      "properties": {
        "hierarchy": [
          "tgn:2591922",
          "tgn:1000001",
          "tgn:7012149",
          "tgn:2002278",
          "tgn:7013961",
          "tgn:7029392"
        ],
        "placetype": [
          "aat:300266640"
        ],
        "id": 2591922,
        "name:xx": "Pond Ridge"
      }
    },
    {
      "geometry": {
        "type": "Point",
        "coordinates": [
          -80.1667,
          38.0667
        ]
      },
      "type": "Feature",
      "properties": {
        "hierarchy": [
          "tgn:2591923",
          "tgn:1000001",
          "tgn:7012149",
          "tgn:2002287",
          "tgn:7013961",
          "tgn:7029392"
        ],
        "placetype": [
          "aat:300266640"
        ],
        "id": 2591923,
        "name:xx": "Pond Ridge"
      }
    },
    {
      "geometry": {
        "type": "Point",
        "coordinates": [
          -80.8667,
          38.4667
        ]
      },
      "type": "Feature",
      "properties": {
        "hierarchy": [
          "tgn:2591924",
          "tgn:1000001",
          "tgn:2002259",
          "tgn:7012149",
          "tgn:7013961",
          "tgn:7029392"
        ],
        "placetype": [
          "aat:300266640"
        ],
        "id": 2591924,
        "name:xx": "Pond Ridge"
      }
    },
    {
      "geometry": {
        "type": "Point",
        "coordinates": [
          -78.7667,
          38.15
        ]
      },
      "type": "Feature",
      "properties": {
        "hierarchy": [
          "tgn:2591925",
          "tgn:2002137",
          "tgn:1000001",
          "tgn:7012149",
          "tgn:7007919",
          "tgn:7029392"
        ],
        "placetype": [
          "aat:300008699"
        ],
        "id": 2591925,
        "name:xx": "Pond Ridge Branch"
      }
    },
    {
      "geometry": {
        "type": "Point",
        "coordinates": [
          -70.5833,
          43.2
        ]
      },
      "type": "Feature",
      "properties": {
        "hierarchy": [
          "tgn:2591926",
          "tgn:1000001",
          "tgn:7012149",
          "tgn:2000933",
          "tgn:7007515",
          "tgn:7029392"
        ],
        "placetype": [
          "aat:300132348"
        ],
        "id": 2591926,
        "name:xx": "Pond Rocks"
      }
    },
    {
      "geometry": {
        "type": "Point",
        "coordinates": [
          -93.8167,
          33.95
        ]
      },
      "type": "Feature",
      "properties": {
        "hierarchy": [
          "tgn:2591927",
          "tgn:1000001",
          "tgn:7016172",
          "tgn:7012149",
          "tgn:7029392"
        ],
        "placetype": [
          "aat:300008699"
        ],
        "id": 2591927,
        "name:xx": "Pond Run"
      }
    },
    {
      "geometry": {
        "type": "Point",
        "coordinates": [
          -86.6167,
          37.85
        ]
      },
      "type": "Feature",
      "properties": {
        "hierarchy": [
          "tgn:2591928",
          "tgn:1000001",
          "tgn:7012149",
          "tgn:2000550",
          "tgn:7007252",
          "tgn:7029392"
        ],
        "placetype": [
          "aat:300008699"
        ],
        "id": 2591928,
        "name:xx": "Pond Run"
      }
    },
    {
      "geometry": {
        "type": "Point",
        "coordinates": [
          -86.9167,
          37.3
        ]
      },
      "type": "Feature",
      "properties": {
        "hierarchy": [
          "tgn:2591929",
          "tgn:1000001",
          "tgn:7012149",
          "tgn:2000834",
          "tgn:7007255",
          "tgn:7029392"
        ],
        "placetype": [
          "aat:300008699"
        ],
        "id": 2591929,
        "name:xx": "Pond Run"
      }
    }
  ]
}
