{
  "geometry": {
    "type": "Point",
    "coordinates": [
      -119.3333,
      34.55
    ]
  },
  "type": "Feature",
  "properties": {
    "hierarchy": [
      "tgn:2731536",
      "tgn:1000001",
      "tgn:7012149",
      "tgn:7007157",
      "tgn:1002972",
      "tgn:7029392"
    ],
    "placetype": [
      "aat:300008706"
    ],
    "id": 2731536,
    "name:xx": "Tule Creek"
  }
}
