{
  "geometry": {
    "type": "Point",
    "coordinates": [
      52.5833,
      34.5333
    ]
  },
  "type": "Feature",
  "properties": {
    "hierarchy": [
      "tgn:1079209",
      "tgn:1000004",
      "tgn:1001528",
      "tgn:7000231",
      "tgn:7029392"
    ],
    "placetype": [
      "aat:300008347"
    ],
    "id": 1079209,
    "name:xx": "Molkābād"
  }
}
