{
  "geometry": {
    "type": "Point",
    "coordinates": [
      31.230965,
      30.129754
    ]
  },
  "type": "Feature",
  "properties": {
    "hierarchy": [
      "tgn:7532357",
      "tgn:7001242",
      "tgn:7016833",
      "tgn:1001092",
      "tgn:7029392"
    ],
    "placetype": [
      "aat:300006676"
    ],
    "id": 7532357,
    "name:xx": "Mustashfá Shubrā al Khaymah al Markazī"
  }
}
