{
  "geometry": {
    "type": "Point",
    "coordinates": [
      -149.6333,
      60.9167
    ]
  },
  "type": "Feature",
  "properties": {
    "hierarchy": [
      "tgn:2006120",
      "tgn:7006450",
      "tgn:1000001",
      "tgn:7019698",
      "tgn:7012149",
      "tgn:7029392"
    ],
    "placetype": [
      "aat:300008347"
    ],
    "id": 2006120,
    "name:xx": "Hope"
  }
}
