{
  "geometry": {
    "type": "Point",
    "coordinates": [
      -85.4667,
      30.2833
    ]
  },
  "type": "Feature",
  "properties": {
    "hierarchy": [
      "tgn:2242589",
      "tgn:2000258",
      "tgn:1000001",
      "tgn:7012149",
      "tgn:7007240",
      "tgn:7029392"
    ],
    "placetype": [
      "aat:300008706"
    ],
    "id": 2242589,
    "name:xx": "Clear Creek"
  }
}
