{
  "type": "FeatureCollection",
  "features": [
    {
      "geometry": {
        "type": "Point",
        "coordinates": [
          -100.65,
          23.683333
        ]
      },
      "type": "Feature",
      "properties": {
        "hierarchy": [
          "tgn:7385130",
          "tgn:1000001",
          "tgn:7005594",
          "tgn:7005560",
          "tgn:7029392"
        ],
        "placetype": [
          "aat:300008347"
        ],
        "id": 7385130,
        "name:xx": "Ojo de Agua"
      }
    },
    {
      "geometry": {
        "type": "Point",
        "coordinates": [
          -102.8,
          23.266667
        ]
      },
      "type": "Feature",
      "properties": {
        "hierarchy": [
          "tgn:7385131",
          "tgn:1000001",
          "tgn:7005601",
          "tgn:7005560",
          "tgn:7029392"
        ],
        "placetype": [
          "aat:300008347"
        ],
        "id": 7385131,
        "name:xx": "Ojo de Agua"
      }
    },
    {
      "geometry": {
        "type": "Point",
        "coordinates": [
          -102.816667,
          23.116667
        ]
      },
      "type": "Feature",
      "properties": {
        "hierarchy": [
          "tgn:7385132",
          "tgn:1000001",
          "tgn:7005601",
          "tgn:7005560",
          "tgn:7029392"
        ],
        "placetype": [
          "aat:300008347"
        ],
        "id": 7385132,
        "name:xx": "Ojo de Agua"
      }
    },
    {
      "geometry": {
        "type": "Point",
        "coordinates": [
          -102.666667,
          23.116667
        ]
      },
      "type": "Feature",
      "properties": {
        "hierarchy": [
          "tgn:7385133",
          "tgn:1000001",
          "tgn:7005601",
          "tgn:7005560",
          "tgn:7029392"
        ],
        "placetype": [
          "aat:300008347"
        ],
        "id": 7385133,
        "name:xx": "Ojo de Agua"
      }
    },
    {
      "geometry": {
        "type": "Point",
        "coordinates": [
          -105.7,
          23.1
        ]
      },
      "type": "Feature",
      "properties": {
        "hierarchy": [
          "tgn:7385134",
          "tgn:1000001",
          "tgn:7005595",
          "tgn:7005560",
          "tgn:7029392"
        ],
        "placetype": [
          "aat:300008347"
        ],
        "id": 7385134,
        "name:xx": "Ojo de Agua"
      }
    },
    {
      "geometry": {
        "type": "Point",
        "coordinates": [
          -102.833333,
          22.933333
        ]
      },
      "type": "Feature",
      "properties": {
        "hierarchy": [
          "tgn:7385135",
          "tgn:1000001",
          "tgn:7005601",
          "tgn:7005560",
          "tgn:7029392"
        ],
        "placetype": [
          "aat:300008347"
        ],
        "id": 7385135,
        "name:xx": "Ojo de Agua"
      }
    },
    {
      "geometry": {
        "type": "Point",
        "coordinates": [
          -108.416667,
          25.633333
        ]
      },
      "type": "Feature",
      "properties": {
        "hierarchy": [
          "tgn:7385136",
          "tgn:1000001",
          "tgn:7005595",
          "tgn:7005560",
          "tgn:7029392"
        ],
        "placetype": [
          "aat:300008347"
        ],
        "id": 7385136,
        "name:xx": "Nío"
      }
    },
    {
      "geometry": {
        "type": "Point",
        "coordinates": [
          -99.583333,
          20.45
        ]
      },
      "type": "Feature",
      "properties": {
        "hierarchy": [
          "tgn:7385137",
          "tgn:7005587",
          "tgn:1000001",
          "tgn:7005560",
          "tgn:7029392"
        ],
        "placetype": [
          "aat:300008347"
        ],
        "id": 7385137,
        "name:xx": "Ninthí"
      }
    },
    {
      "geometry": {
        "type": "Point",
        "coordinates": [
          -91.433333,
          16.983333
        ]
      },
      "type": "Feature",
      "properties": {
        "hierarchy": [
          "tgn:7385138",
          "tgn:7005580",
          "tgn:1000001",
          "tgn:7005560",
          "tgn:7029392"
        ],
        "placetype": [
          "aat:300008347"
        ],
        "id": 7385138,
        "name:xx": "Niños Héroes"
      }
    },
    {
      "geometry": {
        "type": "Point",
        "coordinates": [
          -91.316667,
          16.216667
        ]
      },
      "type": "Feature",
      "properties": {
        "hierarchy": [
          "tgn:7385139",
          "tgn:7005580",
          "tgn:1000001",
          "tgn:7005560",
          "tgn:7029392"
        ],
        "placetype": [
          "aat:300008347"
        ],
        "id": 7385139,
        "name:xx": "Niños Héroes"
      }
    }
  ]
}
