{
  "geometry": {
    "type": "Point",
    "coordinates": [
      38.7667,
      -3.5667
    ]
  },
  "type": "Feature",
  "properties": {
    "hierarchy": [
      "tgn:1090508",
      "tgn:7001242",
      "tgn:7593795",
      "tgn:1000169",
      "tgn:7029392"
    ],
    "placetype": [
      "aat:300008347"
    ],
    "id": 1090508,
    "name:xx": "Maungu"
  }
}
