{
  "geometry": {
    "type": "Point",
    "coordinates": [
      -151.25,
      65.25
    ]
  },
  "type": "Feature",
  "properties": {
    "hierarchy": [
      "tgn:2523629",
      "tgn:7006450",
      "tgn:1000001",
      "tgn:7012149",
      "tgn:2000089",
      "tgn:7029392"
    ],
    "placetype": [
      "aat:300008798"
    ],
    "id": 2523629,
    "name:xx": "Moosehead Rack"
  }
}
