{
  "geometry": {
    "type": "Point",
    "coordinates": [
      -116.6333,
      42.4833
    ]
  },
  "type": "Feature",
  "properties": {
    "hierarchy": [
      "tgn:2189737",
      "tgn:1000001",
      "tgn:7012149",
      "tgn:2000488",
      "tgn:7007250",
      "tgn:7029392"
    ],
    "placetype": [
      "aat:300006191"
    ],
    "id": 2189737,
    "name:xx": "Bower Reservoir"
  }
}
