{
  "geometry": {
    "type": "Point",
    "coordinates": [
      -90.6333,
      46.35
    ]
  },
  "type": "Feature",
  "properties": {
    "hierarchy": [
      "tgn:2469998",
      "tgn:2002306",
      "tgn:1000001",
      "tgn:7012149",
      "tgn:7007922",
      "tgn:7029392"
    ],
    "placetype": [
      "aat:300008680"
    ],
    "id": 2469998,
    "name:xx": "Loon Lake"
  }
}
