{
  "geometry": {
    "type": "Point",
    "coordinates": [
      -86.1833,
      36.5333
    ]
  },
  "type": "Feature",
  "properties": {
    "hierarchy": [
      "tgn:2725411",
      "tgn:1000001",
      "tgn:7012149",
      "tgn:2001892",
      "tgn:7007825",
      "tgn:7029392"
    ],
    "placetype": [
      "aat:300008699"
    ],
    "id": 2725411,
    "name:xx": "Tooley Branch"
  }
}
