{
  "geometry": {
    "type": "Point",
    "coordinates": [
      -97.6667,
      31.15
    ]
  },
  "type": "Feature",
  "properties": {
    "hierarchy": [
      "tgn:2548650",
      "tgn:1000001",
      "tgn:1002174",
      "tgn:7012149",
      "tgn:7007826",
      "tgn:7029392"
    ],
    "placetype": [
      "aat:300008706"
    ],
    "id": 2548650,
    "name:xx": "North Nolan Creek"
  }
}
