{
  "geometry": {
    "type": "Point",
    "coordinates": [
      -145.8833,
      66.65
    ]
  },
  "type": "Feature",
  "properties": {
    "hierarchy": [
      "tgn:2272950",
      "tgn:7006450",
      "tgn:1000001",
      "tgn:7012149",
      "tgn:2000089",
      "tgn:7029392"
    ],
    "placetype": [
      "aat:300008699"
    ],
    "id": 2272950,
    "name:xx": "Cutoff Slough"
  }
}
