{
  "geometry": {
    "type": "Point",
    "coordinates": [
      -76.65,
      37.9667
    ]
  },
  "type": "Feature",
  "properties": {
    "hierarchy": [
      "tgn:2113967",
      "tgn:1000001",
      "tgn:7012149",
      "tgn:7014334",
      "tgn:7007919",
      "tgn:7029392"
    ],
    "placetype": [
      "aat:300008347",
      "aat:300387210"
    ],
    "id": 2113967,
    "name:xx": "Rich Neck"
  }
}
