{
  "type": "FeatureCollection",
  "features": [
    {
      "geometry": {
        "type": "Point",
        "coordinates": [
          -104,
          21.016667
        ]
      },
      "type": "Feature",
      "properties": {
        "hierarchy": [
          "tgn:7372590",
          "tgn:7005586",
          "tgn:1000001",
          "tgn:7005560",
          "tgn:7029392"
        ],
        "placetype": [
          "aat:300006191"
        ],
        "id": 7372590,
        "name:xx": "La Estanzuela"
      }
    },
    {
      "geometry": {
        "type": "Point",
        "coordinates": [
          -105.95,
          27.133333
        ]
      },
      "type": "Feature",
      "properties": {
        "hierarchy": [
          "tgn:7372591",
          "tgn:7005581",
          "tgn:1000001",
          "tgn:7005560",
          "tgn:7029392"
        ],
        "placetype": [
          "aat:300008347"
        ],
        "id": 7372591,
        "name:xx": "La Estanzuela"
      }
    },
    {
      "geometry": {
        "type": "Point",
        "coordinates": [
          -102.25,
          21.6
        ]
      },
      "type": "Feature",
      "properties": {
        "hierarchy": [
          "tgn:7372592",
          "tgn:7005586",
          "tgn:1000001",
          "tgn:7005560",
          "tgn:7029392"
        ],
        "placetype": [
          "aat:300008347"
        ],
        "id": 7372592,
        "name:xx": "La Estanzuela"
      }
    },
    {
      "geometry": {
        "type": "Point",
        "coordinates": [
          -104.466667,
          21.266667
        ]
      },
      "type": "Feature",
      "properties": {
        "hierarchy": [
          "tgn:7372593",
          "tgn:1000001",
          "tgn:1001906",
          "tgn:7005560",
          "tgn:7029392"
        ],
        "placetype": [
          "aat:300008347"
        ],
        "id": 7372593,
        "name:xx": "La Estanzuela"
      }
    },
    {
      "geometry": {
        "type": "Point",
        "coordinates": [
          -103.983333,
          21.033333
        ]
      },
      "type": "Feature",
      "properties": {
        "hierarchy": [
          "tgn:7372594",
          "tgn:7005586",
          "tgn:1000001",
          "tgn:7005560",
          "tgn:7029392"
        ],
        "placetype": [
          "aat:300008347"
        ],
        "id": 7372594,
        "name:xx": "La Estanzuela"
      }
    },
    {
      "geometry": {
        "type": "Point",
        "coordinates": [
          -99.433333,
          20.7
        ]
      },
      "type": "Feature",
      "properties": {
        "hierarchy": [
          "tgn:7372595",
          "tgn:7005587",
          "tgn:1000001",
          "tgn:7005560",
          "tgn:7029392"
        ],
        "placetype": [
          "aat:300008347"
        ],
        "id": 7372595,
        "name:xx": "La Estanzuela"
      }
    },
    {
      "geometry": {
        "type": "Point",
        "coordinates": [
          -102.566667,
          20.633333
        ]
      },
      "type": "Feature",
      "properties": {
        "hierarchy": [
          "tgn:7372596",
          "tgn:7005586",
          "tgn:1000001",
          "tgn:7005560",
          "tgn:7029392"
        ],
        "placetype": [
          "aat:300008347"
        ],
        "id": 7372596,
        "name:xx": "La Estanzuela"
      }
    },
    {
      "geometry": {
        "type": "Point",
        "coordinates": [
          -103.85,
          20.466667
        ]
      },
      "type": "Feature",
      "properties": {
        "hierarchy": [
          "tgn:7372597",
          "tgn:7005586",
          "tgn:1000001",
          "tgn:7005560",
          "tgn:7029392"
        ],
        "placetype": [
          "aat:300008347"
        ],
        "id": 7372597,
        "name:xx": "La Estanzuela"
      }
    },
    {
      "geometry": {
        "type": "Point",
        "coordinates": [
          -102.366667,
          20.116667
        ]
      },
      "type": "Feature",
      "properties": {
        "hierarchy": [
          "tgn:7372598",
          "tgn:1000001",
          "tgn:7005590",
          "tgn:7005560",
          "tgn:7029392"
        ],
        "placetype": [
          "aat:300008347"
        ],
        "id": 7372598,
        "name:xx": "La Estanzuela"
      }
    },
    {
      "geometry": {
        "type": "Point",
        "coordinates": [
          -102.966667,
          19.183333
        ]
      },
      "type": "Feature",
      "properties": {
        "hierarchy": [
          "tgn:7372599",
          "tgn:1000001",
          "tgn:1001893",
          "tgn:7005560",
          "tgn:7029392"
        ],
        "placetype": [
          "aat:300008347"
        ],
        "id": 7372599,
        "name:xx": "La Estanzuela"
      }
    }
  ]
}
