{
  "geometry": {
    "type": "Point",
    "coordinates": [
      -147.1833,
      68.3667
    ]
  },
  "type": "Feature",
  "properties": {
    "hierarchy": [
      "tgn:2672311",
      "tgn:7006450",
      "tgn:1000001",
      "tgn:7012149",
      "tgn:7029392"
    ],
    "placetype": [
      "aat:300008706"
    ],
    "id": 2672311,
    "name:xx": "Smoke Creek"
  }
}
