{
  "geometry": {
    "type": "Point",
    "coordinates": [
      -116.7333,
      40.3667
    ]
  },
  "type": "Feature",
  "properties": {
    "hierarchy": [
      "tgn:2206587",
      "tgn:1000001",
      "tgn:2001415",
      "tgn:7012149",
      "tgn:7007526",
      "tgn:7029392"
    ],
    "placetype": [
      "aat:300008798"
    ],
    "id": 2206587,
    "name:xx": "Bullion Mountain"
  }
}
