{
  "geometry": {
    "type": "Point",
    "coordinates": [
      -76.1167,
      36.2333
    ]
  },
  "type": "Feature",
  "properties": {
    "hierarchy": [
      "tgn:2592472",
      "tgn:1000001",
      "tgn:7012149",
      "tgn:1002774",
      "tgn:7007709",
      "tgn:7029392"
    ],
    "placetype": [
      "aat:300008347"
    ],
    "id": 2592472,
    "name:xx": "Poolville"
  }
}
