{
  "type": "FeatureCollection",
  "features": [
    {
      "geometry": {
        "type": "Point",
        "coordinates": [
          -72.6,
          42.0667
        ]
      },
      "type": "Feature",
      "properties": {
        "hierarchy": [
          "tgn:2049310",
          "tgn:1000001",
          "tgn:7019982",
          "tgn:7012149",
          "tgn:7007517",
          "tgn:7029392"
        ],
        "placetype": [
          "aat:300008347"
        ],
        "id": 2049310,
        "name:xx": "Agawam"
      }
    },
    {
      "geometry": {
        "type": "Point",
        "coordinates": [
          -73.4,
          42.2333
        ]
      },
      "type": "Feature",
      "properties": {
        "hierarchy": [
          "tgn:2049314",
          "tgn:7013388",
          "tgn:1000001",
          "tgn:7012149",
          "tgn:7007517",
          "tgn:7029392"
        ],
        "placetype": [
          "aat:300008347"
        ],
        "id": 2049314,
        "name:xx": "Alford"
      }
    },
    {
      "geometry": {
        "type": "Point",
        "coordinates": [
          -70.9167,
          42.85
        ]
      },
      "type": "Feature",
      "properties": {
        "hierarchy": [
          "tgn:2049316",
          "tgn:1000001",
          "tgn:1002359",
          "tgn:7012149",
          "tgn:7007517",
          "tgn:7029392"
        ],
        "placetype": [
          "aat:300008347"
        ],
        "id": 2049316,
        "name:xx": "Amesbury"
      }
    }
  ]
}
