{
  "geometry": {
    "type": "Point",
    "coordinates": [
      -73.4667,
      44.1167
    ]
  },
  "type": "Feature",
  "properties": {
    "hierarchy": [
      "tgn:2696009",
      "tgn:1000001",
      "tgn:7012149",
      "tgn:2001461",
      "tgn:7007568",
      "tgn:7029392"
    ],
    "placetype": [
      "aat:300008798"
    ],
    "id": 2696009,
    "name:xx": "Stockwell Mountain"
  }
}
