{
  "geometry": {
    "type": "Point",
    "coordinates": [
      -135.3833,
      57.2333
    ]
  },
  "type": "Feature",
  "properties": {
    "hierarchy": [
      "tgn:2129723",
      "tgn:7006450",
      "tgn:1000001",
      "tgn:7012149",
      "tgn:2124002",
      "tgn:7029392"
    ],
    "placetype": [
      "aat:300008850"
    ],
    "id": 2129723,
    "name:xx": "Allan Point"
  }
}
