{
  "geometry": {
    "type": "Point",
    "coordinates": [
      -119.7167,
      43.8667
    ]
  },
  "type": "Feature",
  "properties": {
    "hierarchy": [
      "tgn:2395551",
      "tgn:1000001",
      "tgn:7012149",
      "tgn:2001709",
      "tgn:7007708",
      "tgn:7029392"
    ],
    "placetype": [
      "aat:300008697"
    ],
    "id": 2395551,
    "name:xx": "Hollenbeck Spring"
  }
}
