{
  "geometry": {
    "type": "Point",
    "coordinates": [
      -148.55,
      66.9667
    ]
  },
  "type": "Feature",
  "properties": {
    "hierarchy": [
      "tgn:2586386",
      "tgn:7006450",
      "tgn:1000001",
      "tgn:7012149",
      "tgn:2000089",
      "tgn:7029392"
    ],
    "placetype": [
      "aat:300008707"
    ],
    "id": 2586386,
    "name:xx": "Pitka Fork Hodzana River"
  }
}
