{
  "geometry": {
    "type": "Point",
    "coordinates": [
      -93.9167,
      50.9667
    ]
  },
  "type": "Feature",
  "properties": {
    "hierarchy": [
      "tgn:1014895",
      "tgn:7005685",
      "tgn:1000001",
      "tgn:7013154",
      "tgn:7029392"
    ],
    "placetype": [
      "aat:300008347"
    ],
    "id": 1014895,
    "name:xx": "Madsen"
  }
}
