{
  "geometry": {
    "type": "Point",
    "coordinates": [
      13.55,
      48.95
    ]
  },
  "type": "Feature",
  "properties": {
    "hierarchy": [
      "tgn:7191647",
      "tgn:7003669",
      "tgn:1000003",
      "tgn:7000084",
      "tgn:7029392"
    ],
    "placetype": [
      "aat:300008795"
    ],
    "id": 7191647,
    "name:xx": "Farren Berg"
  }
}
