{
  "geometry": {
    "type": "Point",
    "coordinates": [
      22.0333,
      4.2333
    ]
  },
  "type": "Feature",
  "properties": {
    "hierarchy": [
      "tgn:1125718",
      "tgn:7001242",
      "tgn:1000155",
      "tgn:7029392"
    ],
    "placetype": [
      "aat:300008707"
    ],
    "id": 1125718,
    "name:xx": "Kotto"
  }
}
