{
  "geometry": {
    "type": "Point",
    "coordinates": [
      -0.3333,
      53.75
    ]
  },
  "type": "Feature",
  "properties": {
    "hierarchy": [
      "tgn:7019056",
      "tgn:7002445",
      "tgn:1000003",
      "tgn:7008591",
      "tgn:7029392"
    ],
    "placetype": [
      "aat:300387064",
      "aat:300387145",
      "aat:300387071"
    ],
    "name:en": "Kingston upon Hull",
    "id": 7019056
  }
}
