{
  "geometry": {
    "type": "Point",
    "coordinates": [
      -96.5833,
      30.5167
    ]
  },
  "type": "Feature",
  "properties": {
    "hierarchy": [
      "tgn:2222938",
      "tgn:1000001",
      "tgn:7012149",
      "tgn:1002214",
      "tgn:7007826",
      "tgn:7029392"
    ],
    "placetype": [
      "aat:300008706"
    ],
    "id": 2222938,
    "name:xx": "Carrington Creek"
  }
}
