{
  "geometry": {
    "type": "Point",
    "coordinates": [
      75.52767,
      25.821591
    ]
  },
  "type": "Feature",
  "properties": {
    "hierarchy": [
      "tgn:7570378",
      "tgn:1000004",
      "tgn:7000198",
      "tgn:7016788",
      "tgn:7029392"
    ],
    "placetype": [
      "aat:300008347"
    ],
    "name:en": "Shrīnagar",
    "id": 7570378
  }
}
