{
  "geometry": {
    "type": "Point",
    "coordinates": [
      -72.3667,
      42.6167
    ]
  },
  "type": "Feature",
  "properties": {
    "hierarchy": [
      "tgn:2318726",
      "tgn:1000001",
      "tgn:7013942",
      "tgn:7012149",
      "tgn:7007517",
      "tgn:7029392"
    ],
    "placetype": [
      "aat:300008863"
    ],
    "id": 2318726,
    "name:xx": "Erving State Forest"
  }
}
