{
  "geometry": {
    "type": "Point",
    "coordinates": [
      29.815,
      31.084
    ]
  },
  "type": "Feature",
  "properties": {
    "hierarchy": [
      "tgn:1118974",
      "tgn:7001242",
      "tgn:7016833",
      "tgn:1001079",
      "tgn:7029392"
    ],
    "placetype": [
      "aat:300008680",
      "aat:300266556"
    ],
    "id": 1118974,
    "name:xx": "Maryūţ, Buḩayrat"
  }
}
