{
  "geometry": {
    "type": "Point",
    "coordinates": [
      -90.35,
      42.65
    ]
  },
  "type": "Feature",
  "properties": {
    "hierarchy": [
      "tgn:2445518",
      "tgn:1000001",
      "tgn:7012149",
      "tgn:2002332",
      "tgn:7007922",
      "tgn:7029392"
    ],
    "placetype": [
      "aat:300000390"
    ],
    "id": 2445518,
    "name:xx": "Leo V Mine"
  }
}
