{
  "type": "FeatureCollection",
  "features": [
    {
      "geometry": {
        "type": "Point",
        "coordinates": [
          29.5,
          -24
        ]
      },
      "type": "Feature",
      "properties": {
        "hierarchy": [
          "tgn:7017573",
          "tgn:7001242",
          "tgn:1000193",
          "tgn:7029392"
        ],
        "placetype": [
          "aat:300387064",
          "aat:300000774"
        ],
        "id": 7017573,
        "name:xx": "Limpopo"
      }
    },
    {
      "geometry": {
        "type": "Point",
        "coordinates": [
          30,
          -26
        ]
      },
      "type": "Feature",
      "properties": {
        "hierarchy": [
          "tgn:7017574",
          "tgn:7001242",
          "tgn:1000193",
          "tgn:7029392"
        ],
        "placetype": [
          "aat:300387064",
          "aat:300000774"
        ],
        "id": 7017574,
        "name:xx": "Mpumalanga"
      }
    },
    {
      "geometry": {
        "type": "Point",
        "coordinates": [
          28.25,
          -26.0833
        ]
      },
      "type": "Feature",
      "properties": {
        "hierarchy": [
          "tgn:7017576",
          "tgn:7001242",
          "tgn:1000193",
          "tgn:7029392"
        ],
        "placetype": [
          "aat:300387064",
          "aat:300000774"
        ],
        "id": 7017576,
        "name:xx": "Gauteng"
      }
    },
    {
      "geometry": {
        "type": "Point",
        "coordinates": [
          26,
          -26.5
        ]
      },
      "type": "Feature",
      "properties": {
        "hierarchy": [
          "tgn:7017577",
          "tgn:7001242",
          "tgn:1000193",
          "tgn:7029392"
        ],
        "placetype": [
          "aat:300387064",
          "aat:300000774"
        ],
        "id": 7017577,
        "name:xx": "North West"
      }
    }
  ]
}
