{
  "geometry": {
    "type": "Point",
    "coordinates": [
      -91.95,
      40.5833
    ]
  },
  "type": "Feature",
  "properties": {
    "hierarchy": [
      "tgn:2209398",
      "tgn:1000001",
      "tgn:7012149",
      "tgn:7007523",
      "tgn:7029392"
    ],
    "placetype": [
      "aat:300008699"
    ],
    "id": 2209398,
    "name:xx": "Burnt Shirt Branch"
  }
}
