{
  "geometry": {
    "type": "Point",
    "coordinates": [
      13.6667,
      -8.9333
    ]
  },
  "type": "Feature",
  "properties": {
    "hierarchy": [
      "tgn:1087649",
      "tgn:1000811",
      "tgn:7001242",
      "tgn:1000149",
      "tgn:7029392"
    ],
    "placetype": [
      "aat:300008347"
    ],
    "id": 1087649,
    "name:xx": "Cabiri"
  }
}
