{
  "geometry": {
    "type": "Point",
    "coordinates": [
      25.146851,
      31.13377
    ]
  },
  "type": "Feature",
  "properties": {
    "hierarchy": [
      "tgn:7524899",
      "tgn:7001242",
      "tgn:7016833",
      "tgn:1001418",
      "tgn:7029392"
    ],
    "placetype": [
      "aat:300386860"
    ],
    "name:en": "Burūq, Dayr al",
    "id": 7524899
  }
}
