{
  "geometry": {
    "type": "Point",
    "coordinates": [
      20.3333,
      53.1333
    ]
  },
  "type": "Feature",
  "properties": {
    "hierarchy": [
      "tgn:1049230",
      "tgn:1000003",
      "tgn:7024122",
      "tgn:7006366",
      "tgn:7029392"
    ],
    "placetype": [
      "aat:300008347"
    ],
    "id": 1049230,
    "name:xx": "Mława"
  }
}
