{
  "type": "FeatureCollection",
  "features": [
    {
      "geometry": {
        "type": "Point",
        "coordinates": [
          -97.6167,
          31.5333
        ]
      },
      "type": "Feature",
      "properties": {
        "hierarchy": [
          "tgn:2103474",
          "tgn:1000001",
          "tgn:7012149",
          "tgn:1002303",
          "tgn:7007826",
          "tgn:7029392"
        ],
        "placetype": [
          "aat:300008347"
        ],
        "id": 2103474,
        "name:xx": "Coryell"
      }
    },
    {
      "geometry": {
        "type": "Point",
        "coordinates": [
          -97.5167,
          29.4333
        ]
      },
      "type": "Feature",
      "properties": {
        "hierarchy": [
          "tgn:2103475",
          "tgn:1000001",
          "tgn:7012149",
          "tgn:1002414",
          "tgn:7007826",
          "tgn:7029392"
        ],
        "placetype": [
          "aat:300008347"
        ],
        "id": 2103475,
        "name:xx": "Cost"
      }
    },
    {
      "geometry": {
        "type": "Point",
        "coordinates": [
          -101.9833,
          33.9833
        ]
      },
      "type": "Feature",
      "properties": {
        "hierarchy": [
          "tgn:2103476",
          "tgn:1000001",
          "tgn:7012149",
          "tgn:2001994",
          "tgn:7007826",
          "tgn:7029392"
        ],
        "placetype": [
          "aat:300008347"
        ],
        "id": 2103476,
        "name:xx": "Cotton Center"
      }
    },
    {
      "geometry": {
        "type": "Point",
        "coordinates": [
          -96.1167,
          33.5
        ]
      },
      "type": "Feature",
      "properties": {
        "hierarchy": [
          "tgn:2103477",
          "tgn:1000001",
          "tgn:7012149",
          "tgn:2001983",
          "tgn:7007826",
          "tgn:7029392"
        ],
        "placetype": [
          "aat:300008347",
          "aat:300387210"
        ],
        "id": 2103477,
        "name:xx": "Cotton Center"
      }
    },
    {
      "geometry": {
        "type": "Point",
        "coordinates": [
          -97.7,
          33.05
        ]
      },
      "type": "Feature",
      "properties": {
        "hierarchy": [
          "tgn:2103478",
          "tgn:1000001",
          "tgn:7012149",
          "tgn:1003031",
          "tgn:7007826",
          "tgn:7029392"
        ],
        "placetype": [
          "aat:300008347"
        ],
        "id": 2103478,
        "name:xx": "Cottondale"
      }
    },
    {
      "geometry": {
        "type": "Point",
        "coordinates": [
          -102.05,
          31.9167
        ]
      },
      "type": "Feature",
      "properties": {
        "hierarchy": [
          "tgn:2103479",
          "tgn:1000001",
          "tgn:7012149",
          "tgn:2002041",
          "tgn:7007826",
          "tgn:7029392"
        ],
        "placetype": [
          "aat:300008347",
          "aat:300387210"
        ],
        "id": 2103479,
        "name:xx": "Cotton Flat"
      }
    }
  ]
}
