{
  "geometry": {
    "type": "Point",
    "coordinates": [
      -96.1167,
      41.4333
    ]
  },
  "type": "Feature",
  "properties": {
    "hierarchy": [
      "tgn:2467110",
      "tgn:1000001",
      "tgn:7012149",
      "tgn:2001404",
      "tgn:7007525",
      "tgn:7029392"
    ],
    "placetype": [
      "aat:300008706"
    ],
    "id": 2467110,
    "name:xx": "Long Creek"
  }
}
