{
  "geometry": {
    "type": "Point",
    "coordinates": [
      120.476728,
      23.10697
    ]
  },
  "type": "Feature",
  "properties": {
    "hierarchy": [
      "tgn:7479568",
      "tgn:1000004",
      "tgn:7490934",
      "tgn:1000141",
      "tgn:7029392"
    ],
    "placetype": [
      "aat:300008699"
    ],
    "id": 7479568,
    "name:xx": "Kengnei Gou"
  }
}
