{
  "geometry": {
    "type": "Point",
    "coordinates": [
      -86.7833,
      35.3167
    ]
  },
  "type": "Feature",
  "properties": {
    "hierarchy": [
      "tgn:2100888",
      "tgn:1000001",
      "tgn:7012149",
      "tgn:2001895",
      "tgn:7007825",
      "tgn:7029392"
    ],
    "placetype": [
      "aat:300008347"
    ],
    "id": 2100888,
    "name:xx": "Ostella"
  }
}
