{
  "geometry": {
    "type": "Point",
    "coordinates": [
      -87.2333,
      32.0667
    ]
  },
  "type": "Feature",
  "properties": {
    "hierarchy": [
      "tgn:2238340",
      "tgn:7002659",
      "tgn:1000001",
      "tgn:2000011",
      "tgn:7012149",
      "tgn:7029392"
    ],
    "placetype": [
      "aat:300006191"
    ],
    "id": 2238340,
    "name:xx": "Choctaw County School Lake"
  }
}
