{
  "geometry": {
    "type": "Point",
    "coordinates": [
      -74.1167,
      40.5833
    ]
  },
  "type": "Feature",
  "properties": {
    "hierarchy": [
      "tgn:2700049",
      "tgn:1000001",
      "tgn:7012149",
      "tgn:7015817",
      "tgn:7007568",
      "tgn:7029392"
    ],
    "placetype": [
      "aat:300008680"
    ],
    "id": 2700049,
    "name:xx": "Stump Pond"
  }
}
