{
  "geometry": {
    "type": "Point",
    "coordinates": [
      -88.3833,
      35.2667
    ]
  },
  "type": "Feature",
  "properties": {
    "hierarchy": [
      "tgn:2291526",
      "tgn:1000001",
      "tgn:7012149",
      "tgn:7007825",
      "tgn:7029392"
    ],
    "placetype": [
      "aat:300008706"
    ],
    "id": 2291526,
    "name:xx": "Dollar Creek"
  }
}
