{
  "geometry": {
    "type": "Point",
    "coordinates": [
      -3.35,
      42.65
    ]
  },
  "type": "Feature",
  "properties": {
    "hierarchy": [
      "tgn:7344240",
      "tgn:7002810",
      "tgn:7001158",
      "tgn:1000003",
      "tgn:1000095",
      "tgn:7029392"
    ],
    "placetype": [
      "aat:300008347"
    ],
    "id": 7344240,
    "name:xx": "Barrio de Díaz Ruiz"
  }
}
