{
  "type": "FeatureCollection",
  "features": [
    {
      "geometry": {
        "type": "Point",
        "coordinates": [
          -149.25,
          64.1167
        ]
      },
      "type": "Feature",
      "properties": {
        "hierarchy": [
          "tgn:2429170",
          "tgn:7006450",
          "tgn:1000001",
          "tgn:7030547",
          "tgn:7012149",
          "tgn:7029392"
        ],
        "placetype": [
          "aat:300008706"
        ],
        "id": 2429170,
        "name:xx": "June Creek"
      }
    },
    {
      "geometry": {
        "type": "Point",
        "coordinates": [
          -166.2333,
          65.15
        ]
      },
      "type": "Feature",
      "properties": {
        "hierarchy": [
          "tgn:2429171",
          "tgn:7006450",
          "tgn:1000001",
          "tgn:7012149",
          "tgn:2000079",
          "tgn:7029392"
        ],
        "placetype": [
          "aat:300008706"
        ],
        "id": 2429171,
        "name:xx": "June Creek"
      }
    },
    {
      "geometry": {
        "type": "Point",
        "coordinates": [
          -163.15,
          65.7833
        ]
      },
      "type": "Feature",
      "properties": {
        "hierarchy": [
          "tgn:2429172",
          "tgn:7006450",
          "tgn:1000001",
          "tgn:7012149",
          "tgn:2124014",
          "tgn:7029392"
        ],
        "placetype": [
          "aat:300008706"
        ],
        "id": 2429172,
        "name:xx": "June Creek"
      }
    },
    {
      "geometry": {
        "type": "Point",
        "coordinates": [
          -107.5167,
          39.3833
        ]
      },
      "type": "Feature",
      "properties": {
        "hierarchy": [
          "tgn:2429173",
          "tgn:1000001",
          "tgn:7012149",
          "tgn:2000214",
          "tgn:7007158",
          "tgn:7029392"
        ],
        "placetype": [
          "aat:300008706"
        ],
        "id": 2429173,
        "name:xx": "June Creek"
      }
    },
    {
      "geometry": {
        "type": "Point",
        "coordinates": [
          -107.5,
          39.2
        ]
      },
      "type": "Feature",
      "properties": {
        "hierarchy": [
          "tgn:2429174",
          "tgn:1000001",
          "tgn:7012149",
          "tgn:7007158",
          "tgn:7029392"
        ],
        "placetype": [
          "aat:300008706"
        ],
        "id": 2429174,
        "name:xx": "June Creek"
      }
    },
    {
      "geometry": {
        "type": "Point",
        "coordinates": [
          -106.5167,
          39.7
        ]
      },
      "type": "Feature",
      "properties": {
        "hierarchy": [
          "tgn:2429175",
          "tgn:1000001",
          "tgn:7012149",
          "tgn:2000210",
          "tgn:7007158",
          "tgn:7029392"
        ],
        "placetype": [
          "aat:300008706"
        ],
        "id": 2429175,
        "name:xx": "June Creek"
      }
    },
    {
      "geometry": {
        "type": "Point",
        "coordinates": [
          -116.7667,
          44.8333
        ]
      },
      "type": "Feature",
      "properties": {
        "hierarchy": [
          "tgn:2429176",
          "tgn:2000453",
          "tgn:1000001",
          "tgn:7012149",
          "tgn:7007250",
          "tgn:7029392"
        ],
        "placetype": [
          "aat:300008706"
        ],
        "id": 2429176,
        "name:xx": "June Creek"
      }
    },
    {
      "geometry": {
        "type": "Point",
        "coordinates": [
          -115.55,
          46.8
        ]
      },
      "type": "Feature",
      "properties": {
        "hierarchy": [
          "tgn:2429177",
          "tgn:1000001",
          "tgn:2000469",
          "tgn:7012149",
          "tgn:7007250",
          "tgn:7029392"
        ],
        "placetype": [
          "aat:300008706"
        ],
        "id": 2429177,
        "name:xx": "June Creek"
      }
    },
    {
      "geometry": {
        "type": "Point",
        "coordinates": [
          -116.1833,
          47.7167
        ]
      },
      "type": "Feature",
      "properties": {
        "hierarchy": [
          "tgn:2429178",
          "tgn:1000001",
          "tgn:7012149",
          "tgn:2000491",
          "tgn:7007250",
          "tgn:7029392"
        ],
        "placetype": [
          "aat:300008706"
        ],
        "id": 2429178,
        "name:xx": "June Creek"
      }
    },
    {
      "geometry": {
        "type": "Point",
        "coordinates": [
          -111.55,
          43.3333
        ]
      },
      "type": "Feature",
      "properties": {
        "hierarchy": [
          "tgn:2429179",
          "tgn:1000001",
          "tgn:2000461",
          "tgn:7012149",
          "tgn:7007250",
          "tgn:7029392"
        ],
        "placetype": [
          "aat:300008706"
        ],
        "id": 2429179,
        "name:xx": "June Creek"
      }
    }
  ]
}
