{
  "geometry": {
    "type": "Point",
    "coordinates": [
      -100.7333,
      35.7833
    ]
  },
  "type": "Feature",
  "properties": {
    "hierarchy": [
      "tgn:2719425",
      "tgn:1000001",
      "tgn:7012149",
      "tgn:2002064",
      "tgn:7007826",
      "tgn:7029392"
    ],
    "placetype": [
      "aat:300008706"
    ],
    "id": 2719425,
    "name:xx": "Three Corrals Creek"
  }
}
