{
  "geometry": {
    "type": "Point",
    "coordinates": [
      -79.5333,
      40.5833
    ]
  },
  "type": "Feature",
  "properties": {
    "hierarchy": [
      "tgn:2701199",
      "tgn:1002153",
      "tgn:1000001",
      "tgn:7012149",
      "tgn:7007710",
      "tgn:7029392"
    ],
    "placetype": [
      "aat:300008761"
    ],
    "id": 2701199,
    "name:xx": "Sugar Hollow"
  }
}
