{
  "geometry": {
    "type": "Point",
    "coordinates": [
      -84.9167,
      36.2667
    ]
  },
  "type": "Feature",
  "properties": {
    "hierarchy": [
      "tgn:2549053",
      "tgn:1000001",
      "tgn:7012149",
      "tgn:2001861",
      "tgn:7007825",
      "tgn:7029392"
    ],
    "placetype": [
      "aat:300008706"
    ],
    "id": 2549053,
    "name:xx": "North Prong Horse Creek"
  }
}
