{
  "geometry": {
    "type": "Point",
    "coordinates": [
      -122.7167,
      48.55
    ]
  },
  "type": "Feature",
  "properties": {
    "hierarchy": [
      "tgn:2698773",
      "tgn:1000001",
      "tgn:7012149",
      "tgn:7014510",
      "tgn:7007920",
      "tgn:7029392"
    ],
    "placetype": [
      "aat:300132316"
    ],
    "id": 2698773,
    "name:xx": "Strawberry Bay"
  }
}
