{
  "geometry": {
    "type": "Point",
    "coordinates": [
      -70.7667,
      42.1833
    ]
  },
  "type": "Feature",
  "properties": {
    "hierarchy": [
      "tgn:2658736",
      "tgn:1000001",
      "tgn:7014423",
      "tgn:7012149",
      "tgn:7007517",
      "tgn:7029392"
    ],
    "placetype": [
      "aat:300008347"
    ],
    "id": 2658736,
    "name:xx": "Sherman Corner"
  }
}
