{
  "geometry": {
    "type": "Point",
    "coordinates": [
      -76.2667,
      40.8833
    ]
  },
  "type": "Feature",
  "properties": {
    "hierarchy": [
      "tgn:2268401",
      "tgn:1000001",
      "tgn:7012149",
      "tgn:1002876",
      "tgn:7007710",
      "tgn:7029392"
    ],
    "placetype": [
      "aat:300008699"
    ],
    "id": 2268401,
    "name:xx": "Crooked Run"
  }
}
