{
  "geometry": {
    "type": "Point",
    "coordinates": [
      -106.1833,
      38.2333
    ]
  },
  "type": "Feature",
  "properties": {
    "hierarchy": [
      "tgn:2333926",
      "tgn:1000001",
      "tgn:7012149",
      "tgn:7007158",
      "tgn:2000246",
      "tgn:7029392"
    ],
    "placetype": [
      "aat:300008706"
    ],
    "id": 2333926,
    "name:xx": "Ford Creek"
  }
}
