{
  "geometry": {
    "type": "Point",
    "coordinates": [
      20.9167,
      47.8333
    ]
  },
  "type": "Feature",
  "properties": {
    "hierarchy": [
      "tgn:7010490",
      "tgn:1000348",
      "tgn:1000003",
      "tgn:7006278",
      "tgn:7029392"
    ],
    "placetype": [
      "aat:300008347"
    ],
    "id": 7010490,
    "name:xx": "Mezőcsát"
  }
}
