{
  "geometry": {
    "type": "Point",
    "coordinates": [
      -81.3667,
      41.65
    ]
  },
  "type": "Feature",
  "properties": {
    "hierarchy": [
      "tgn:2615785",
      "tgn:1000001",
      "tgn:7012149",
      "tgn:1002570",
      "tgn:7007706",
      "tgn:7029392"
    ],
    "placetype": [
      "aat:300008347"
    ],
    "id": 2615785,
    "name:xx": "Reynolds"
  }
}
