{
  "geometry": {
    "type": "Point",
    "coordinates": [
      -71.3667,
      44.6667
    ]
  },
  "type": "Feature",
  "properties": {
    "hierarchy": [
      "tgn:2468289",
      "tgn:1002300",
      "tgn:1000001",
      "tgn:7012149",
      "tgn:7007564",
      "tgn:7029392"
    ],
    "placetype": [
      "aat:300266640"
    ],
    "id": 2468289,
    "name:xx": "Long Mountain"
  }
}
