{
  "geometry": {
    "type": "Point",
    "coordinates": [
      -104.3167,
      32.75
    ]
  },
  "type": "Feature",
  "properties": {
    "hierarchy": [
      "tgn:2192088",
      "tgn:1000001",
      "tgn:2001436",
      "tgn:7012149",
      "tgn:7007566",
      "tgn:7029392"
    ],
    "placetype": [
      "aat:300008680"
    ],
    "id": 2192088,
    "name:xx": "Brainard Lake"
  }
}
