{
  "geometry": {
    "type": "Point",
    "coordinates": [
      79.486002,
      26.385457
    ]
  },
  "type": "Feature",
  "properties": {
    "hierarchy": [
      "tgn:7565932",
      "tgn:1000004",
      "tgn:7000198",
      "tgn:7016722",
      "tgn:7029392"
    ],
    "placetype": [
      "aat:300008699"
    ],
    "name:en": "Dhāsak Nāla",
    "id": 7565932
  }
}
