{
  "geometry": {
    "type": "Point",
    "coordinates": [
      -58.2167,
      49.3167
    ]
  },
  "type": "Feature",
  "properties": {
    "hierarchy": [
      "tgn:1106277",
      "tgn:7005685",
      "tgn:7005807",
      "tgn:1000001",
      "tgn:7005801",
      "tgn:7029392"
    ],
    "placetype": [
      "aat:300008795"
    ],
    "id": 1106277,
    "name:xx": "Saint Gregory, Mount"
  }
}
