{
  "geometry": {
    "type": "Point",
    "coordinates": [
      -86.4333,
      43.5333
    ]
  },
  "type": "Feature",
  "properties": {
    "hierarchy": [
      "tgn:2418708",
      "tgn:1000001",
      "tgn:7012149",
      "tgn:2000984",
      "tgn:7007520",
      "tgn:7029392"
    ],
    "placetype": [
      "aat:300008680"
    ],
    "id": 2418708,
    "name:xx": "Jakes Lake"
  }
}
