{
  "geometry": {
    "type": "Point",
    "coordinates": [
      -101.95,
      44.7167
    ]
  },
  "type": "Feature",
  "properties": {
    "hierarchy": [
      "tgn:2278733",
      "tgn:1000001",
      "tgn:7012149",
      "tgn:2001836",
      "tgn:7007713",
      "tgn:7029392"
    ],
    "placetype": [
      "aat:300008761"
    ],
    "id": 2278733,
    "name:xx": "Dead Horse Draw"
  }
}
