{
  "geometry": {
    "type": "Point",
    "coordinates": [
      33.466097,
      25.35154
    ]
  },
  "type": "Feature",
  "properties": {
    "hierarchy": [
      "tgn:7521462",
      "tgn:7001242",
      "tgn:7001311",
      "tgn:7016833",
      "tgn:7029392"
    ],
    "placetype": [
      "aat:300379998"
    ],
    "name:en": "Abu Heita, Wâdi",
    "id": 7521462
  }
}
