{
  "geometry": {
    "type": "Point",
    "coordinates": [
      79.9279,
      27.0704
    ]
  },
  "type": "Feature",
  "properties": {
    "hierarchy": [
      "tgn:7563285",
      "tgn:1000004",
      "tgn:7000198",
      "tgn:7016722",
      "tgn:7029392"
    ],
    "placetype": [
      "aat:300008347"
    ],
    "name:en": "Kandrauli Kachhoha",
    "id": 7563285
  }
}
