{
  "type": "FeatureCollection",
  "features": [
    {
      "geometry": {
        "type": "Point",
        "coordinates": [
          -170.5833,
          -14.25
        ]
      },
      "type": "Feature",
      "properties": {
        "hierarchy": [
          "tgn:1010931",
          "tgn:7005667",
          "tgn:1009538",
          "tgn:1000006",
          "tgn:7029392"
        ],
        "placetype": [
          "aat:300008850"
        ],
        "id": 1010931,
        "name:xx": "Matatula, Cape"
      }
    },
    {
      "geometry": {
        "type": "Point",
        "coordinates": [
          8.166667,
          43.95
        ]
      },
      "type": "Feature",
      "properties": {
        "hierarchy": [
          "tgn:1010935",
          "tgn:1000003",
          "tgn:7003236",
          "tgn:7003144",
          "tgn:1000080",
          "tgn:7029392"
        ],
        "placetype": [
          "aat:300008850",
          "aat:300386846"
        ],
        "id": 1010935,
        "name:xx": "Mele, Capo"
      }
    },
    {
      "geometry": {
        "type": "Point",
        "coordinates": [
          117.0167,
          7.9333
        ]
      },
      "type": "Feature",
      "properties": {
        "hierarchy": [
          "tgn:1010936",
          "tgn:1006388",
          "tgn:1000004",
          "tgn:1001481",
          "tgn:1000135",
          "tgn:7029392"
        ],
        "placetype": [
          "aat:300008850"
        ],
        "id": 1010936,
        "name:xx": "Melville, Cape"
      }
    }
  ]
}
