{
  "geometry": {
    "type": "Point",
    "coordinates": [
      -106.8833,
      35.6667
    ]
  },
  "type": "Feature",
  "properties": {
    "hierarchy": [
      "tgn:2250219",
      "tgn:1000001",
      "tgn:7012149",
      "tgn:2001451",
      "tgn:7007566",
      "tgn:7029392"
    ],
    "placetype": [
      "aat:300000390"
    ],
    "id": 2250219,
    "name:xx": "Collins Mine"
  }
}
