{
  "geometry": {
    "type": "Point",
    "coordinates": [
      -111.2167,
      40.15
    ]
  },
  "type": "Feature",
  "properties": {
    "hierarchy": [
      "tgn:2666737",
      "tgn:1000001",
      "tgn:7012149",
      "tgn:2002125",
      "tgn:7007827",
      "tgn:7029392"
    ],
    "placetype": [
      "aat:300008706"
    ],
    "id": 2666737,
    "name:xx": "Sixth Water Creek"
  }
}
