{
  "geometry": {
    "type": "Point",
    "coordinates": [
      18.8167,
      45.2667
    ]
  },
  "type": "Feature",
  "properties": {
    "hierarchy": [
      "tgn:1065324",
      "tgn:1000003",
      "tgn:7017307",
      "tgn:7006663",
      "tgn:7029392"
    ],
    "placetype": [
      "aat:300008347",
      "aat:300008375"
    ],
    "id": 1065324,
    "name:xx": "Vinkovci"
  }
}
