{
  "geometry": {
    "type": "Point",
    "coordinates": [
      -96.0333,
      46.25
    ]
  },
  "type": "Feature",
  "properties": {
    "hierarchy": [
      "tgn:2573406",
      "tgn:1000001",
      "tgn:7012149",
      "tgn:2001054",
      "tgn:7007521",
      "tgn:7029392"
    ],
    "placetype": [
      "aat:300008680"
    ],
    "id": 2573406,
    "name:xx": "Pebble Lake"
  }
}
