{
  "geometry": {
    "type": "Point",
    "coordinates": [
      -115.4333,
      41.6833
    ]
  },
  "type": "Feature",
  "properties": {
    "hierarchy": [
      "tgn:2455379",
      "tgn:1000001",
      "tgn:2001411",
      "tgn:7012149",
      "tgn:7007526",
      "tgn:7029392"
    ],
    "placetype": [
      "aat:300008706"
    ],
    "id": 2455379,
    "name:xx": "Little Fork Willow Creek"
  }
}
