{
  "geometry": {
    "type": "Point",
    "coordinates": [
      -82.55,
      34.8167
    ]
  },
  "type": "Feature",
  "properties": {
    "hierarchy": [
      "tgn:2231150",
      "tgn:1000001",
      "tgn:7012149",
      "tgn:2001763",
      "tgn:7007712",
      "tgn:7029392"
    ],
    "placetype": [
      "aat:300008347"
    ],
    "id": 2231150,
    "name:xx": "Chadwick"
  }
}
