{
  "geometry": {
    "type": "Point",
    "coordinates": [
      -90.0833,
      35.65
    ]
  },
  "type": "Feature",
  "properties": {
    "hierarchy": [
      "tgn:2632258",
      "tgn:1000001",
      "tgn:7016172",
      "tgn:7012149",
      "tgn:2000151",
      "tgn:7029392"
    ],
    "placetype": [
      "aat:300008347"
    ],
    "id": 2632258,
    "name:xx": "Roy"
  }
}
