{
  "geometry": {
    "type": "Point",
    "coordinates": [
      -98.1833,
      42.7167
    ]
  },
  "type": "Feature",
  "properties": {
    "hierarchy": [
      "tgn:2586157",
      "tgn:1000001",
      "tgn:2001369",
      "tgn:7012149",
      "tgn:7007525",
      "tgn:7029392"
    ],
    "placetype": [
      "aat:300008791"
    ],
    "id": 2586157,
    "name:xx": "Pishelville Island"
  }
}
