{
  "geometry": {
    "type": "Point",
    "coordinates": [
      -113.0167,
      44.4833
    ]
  },
  "type": "Feature",
  "properties": {
    "hierarchy": [
      "tgn:2570045",
      "tgn:1000001",
      "tgn:7012149",
      "tgn:2000481",
      "tgn:7007250",
      "tgn:7029392"
    ],
    "placetype": [
      "aat:300008706"
    ],
    "id": 2570045,
    "name:xx": "Pass Creek"
  }
}
