{
  "geometry": {
    "type": "Point",
    "coordinates": [
      81.32063,
      22.97924
    ]
  },
  "type": "Feature",
  "properties": {
    "hierarchy": [
      "tgn:7576157",
      "tgn:1000004",
      "tgn:7000198",
      "tgn:1001894",
      "tgn:7029392"
    ],
    "placetype": [
      "aat:300008347"
    ],
    "name:en": "Karanpathār",
    "id": 7576157
  }
}
