{
  "geometry": {
    "type": "Point",
    "coordinates": [
      -88.0167,
      33.8833
    ]
  },
  "type": "Feature",
  "properties": {
    "hierarchy": [
      "tgn:2137323",
      "tgn:7002659",
      "tgn:1000001",
      "tgn:7012149",
      "tgn:2000037",
      "tgn:7029392"
    ],
    "placetype": [
      "aat:300008699"
    ],
    "id": 2137323,
    "name:xx": "Armstrong Branch"
  }
}
