{
  "type": "FeatureCollection",
  "features": [
    {
      "geometry": {
        "type": "Point",
        "coordinates": [
          10.266667,
          47.8
        ]
      },
      "type": "Feature",
      "properties": {
        "hierarchy": [
          "tgn:7186690",
          "tgn:7003669",
          "tgn:1000003",
          "tgn:7000084",
          "tgn:7029392"
        ],
        "placetype": [
          "aat:300008347"
        ],
        "id": 7186690,
        "name:xx": "Graben"
      }
    },
    {
      "geometry": {
        "type": "Point",
        "coordinates": [
          10.866667,
          47.683333
        ]
      },
      "type": "Feature",
      "properties": {
        "hierarchy": [
          "tgn:7186691",
          "tgn:7003669",
          "tgn:1000003",
          "tgn:7000084",
          "tgn:7029392"
        ],
        "placetype": [
          "aat:300008347"
        ],
        "id": 7186691,
        "name:xx": "Graben"
      }
    },
    {
      "geometry": {
        "type": "Point",
        "coordinates": [
          11.583333,
          47.65
        ]
      },
      "type": "Feature",
      "properties": {
        "hierarchy": [
          "tgn:7186692",
          "tgn:7003669",
          "tgn:1000003",
          "tgn:7000084",
          "tgn:7029392"
        ],
        "placetype": [
          "aat:300008347"
        ],
        "id": 7186692,
        "name:xx": "Graben"
      }
    },
    {
      "geometry": {
        "type": "Point",
        "coordinates": [
          7.2,
          51.216667
        ]
      },
      "type": "Feature",
      "properties": {
        "hierarchy": [
          "tgn:7186693",
          "tgn:1000003",
          "tgn:7003677",
          "tgn:7000084",
          "tgn:7029392"
        ],
        "placetype": [
          "aat:300000206"
        ],
        "id": 7186693,
        "name:xx": "Graben"
      }
    },
    {
      "geometry": {
        "type": "Point",
        "coordinates": [
          11.583333,
          49.35
        ]
      },
      "type": "Feature",
      "properties": {
        "hierarchy": [
          "tgn:7186694",
          "tgn:7003669",
          "tgn:1000003",
          "tgn:7000084",
          "tgn:7029392"
        ],
        "placetype": [
          "aat:300000206"
        ],
        "id": 7186694,
        "name:xx": "Graben"
      }
    },
    {
      "geometry": {
        "type": "Point",
        "coordinates": [
          12.8,
          48.983333
        ]
      },
      "type": "Feature",
      "properties": {
        "hierarchy": [
          "tgn:7186695",
          "tgn:7003669",
          "tgn:1000003",
          "tgn:7000084",
          "tgn:7029392"
        ],
        "placetype": [
          "aat:300000206"
        ],
        "id": 7186695,
        "name:xx": "Graben"
      }
    },
    {
      "geometry": {
        "type": "Point",
        "coordinates": [
          13.016667,
          48.816667
        ]
      },
      "type": "Feature",
      "properties": {
        "hierarchy": [
          "tgn:7186696",
          "tgn:7003669",
          "tgn:1000003",
          "tgn:7000084",
          "tgn:7029392"
        ],
        "placetype": [
          "aat:300000206"
        ],
        "id": 7186696,
        "name:xx": "Graben"
      }
    },
    {
      "geometry": {
        "type": "Point",
        "coordinates": [
          10.166667,
          51.583333
        ]
      },
      "type": "Feature",
      "properties": {
        "hierarchy": [
          "tgn:7186697",
          "tgn:1000003",
          "tgn:7003676",
          "tgn:7000084",
          "tgn:7029392"
        ],
        "placetype": [
          "aat:300055621"
        ],
        "id": 7186697,
        "name:xx": "Goldene Mark"
      }
    },
    {
      "geometry": {
        "type": "Point",
        "coordinates": [
          7.816667,
          53.7
        ]
      },
      "type": "Feature",
      "properties": {
        "hierarchy": [
          "tgn:7186698",
          "tgn:1000003",
          "tgn:7003676",
          "tgn:7000084",
          "tgn:7029392"
        ],
        "placetype": [
          "aat:300008347"
        ],
        "id": 7186698,
        "name:xx": "Goldene Linie"
      }
    },
    {
      "geometry": {
        "type": "Point",
        "coordinates": [
          13.733333,
          50.983333
        ]
      },
      "type": "Feature",
      "properties": {
        "hierarchy": [
          "tgn:7186699",
          "tgn:1000003",
          "tgn:7003685",
          "tgn:7000084",
          "tgn:7029392"
        ],
        "placetype": [
          "aat:300000206"
        ],
        "id": 7186699,
        "name:xx": "Goldene Höhe"
      }
    }
  ]
}
