{
  "geometry": {
    "type": "Point",
    "coordinates": [
      9.526,
      47.145
    ]
  },
  "type": "Feature",
  "properties": {
    "hierarchy": [
      "tgn:7032088",
      "tgn:1000003",
      "tgn:7003515",
      "tgn:7029392"
    ],
    "placetype": [
      "aat:300387064",
      "aat:300387330"
    ],
    "id": 7032088,
    "name:xx": "Vaduz"
  }
}
