{
  "geometry": {
    "type": "Point",
    "coordinates": [
      120.5791,
      23.9695
    ]
  },
  "type": "Feature",
  "properties": {
    "hierarchy": [
      "tgn:7475446",
      "tgn:1000004",
      "tgn:7467799",
      "tgn:1000141",
      "tgn:7029392"
    ],
    "placetype": [
      "aat:300000745"
    ],
    "id": 7475446,
    "name:xx": "Liujiahu"
  }
}
