{
  "geometry": {
    "type": "Point",
    "coordinates": [
      38.0667,
      -5.4167
    ]
  },
  "type": "Feature",
  "properties": {
    "hierarchy": [
      "tgn:1094583",
      "tgn:7001242",
      "tgn:1001756",
      "tgn:1000203",
      "tgn:7029392"
    ],
    "placetype": [
      "aat:300008347"
    ],
    "id": 1094583,
    "name:xx": "Handeni"
  }
}
