{
  "geometry": {
    "type": "Point",
    "coordinates": [
      -99.8167,
      37.3167
    ]
  },
  "type": "Feature",
  "properties": {
    "hierarchy": [
      "tgn:2304794",
      "tgn:1000001",
      "tgn:2000672",
      "tgn:7012149",
      "tgn:7007254",
      "tgn:7029392"
    ],
    "placetype": [
      "aat:300008706"
    ],
    "id": 2304794,
    "name:xx": "East Branch Bear Creek"
  }
}
