{
  "geometry": {
    "type": "Point",
    "coordinates": [
      -106.8333,
      47.9667
    ]
  },
  "type": "Feature",
  "properties": {
    "hierarchy": [
      "tgn:2771395",
      "tgn:1000001",
      "tgn:7012149",
      "tgn:2001312",
      "tgn:7007524",
      "tgn:7029392"
    ],
    "placetype": [
      "aat:300006191"
    ],
    "id": 2771395,
    "name:xx": "Wilderness Reservoir"
  }
}
