{
  "geometry": {
    "type": "Point",
    "coordinates": [
      -81.4833,
      41.3667
    ]
  },
  "type": "Feature",
  "properties": {
    "hierarchy": [
      "tgn:2262781",
      "tgn:1000001",
      "tgn:1002313",
      "tgn:7012149",
      "tgn:7007706",
      "tgn:7029392"
    ],
    "placetype": [
      "aat:300008347"
    ],
    "id": 2262781,
    "name:xx": "Cowans"
  }
}
