{
  "geometry": {
    "type": "Point",
    "coordinates": [
      -83.3667,
      32.5833
    ]
  },
  "type": "Feature",
  "properties": {
    "hierarchy": [
      "tgn:2424300",
      "tgn:1000001",
      "tgn:7012149",
      "tgn:2000434",
      "tgn:7007248",
      "tgn:7029392"
    ],
    "placetype": [
      "aat:300008699"
    ],
    "id": 2424300,
    "name:xx": "Johnson Branch"
  }
}
