{
  "geometry": {
    "type": "Point",
    "coordinates": [
      28.8333,
      61.2333
    ]
  },
  "type": "Feature",
  "properties": {
    "hierarchy": [
      "tgn:1031312",
      "tgn:7594379",
      "tgn:1000003",
      "tgn:1000069",
      "tgn:7029392"
    ],
    "placetype": [
      "aat:300008347"
    ],
    "id": 1031312,
    "name:xx": "Imatra"
  }
}
