{
  "geometry": {
    "type": "Point",
    "coordinates": [
      -143.65,
      63.0167
    ]
  },
  "type": "Feature",
  "properties": {
    "hierarchy": [
      "tgn:2721749",
      "tgn:7006450",
      "tgn:1000001",
      "tgn:7012149",
      "tgn:2000085",
      "tgn:7029392"
    ],
    "placetype": [
      "aat:300008706"
    ],
    "id": 2721749,
    "name:xx": "Timber Creek"
  }
}
