{
  "type": "FeatureCollection",
  "features": [
    {
      "geometry": {
        "type": "Point",
        "coordinates": [
          12,
          42.75
        ]
      },
      "type": "Feature",
      "properties": {
        "hierarchy": [
          "tgn:1043992",
          "tgn:7003171",
          "tgn:1000003",
          "tgn:7003125",
          "tgn:1000080",
          "tgn:7029392"
        ],
        "placetype": [
          "aat:300008347"
        ],
        "id": 1043992,
        "name:xx": "Castel Viscardo"
      }
    },
    {
      "geometry": {
        "type": "Point",
        "coordinates": [
          10.966667,
          45.183333
        ]
      },
      "type": "Feature",
      "properties": {
        "hierarchy": [
          "tgn:1043994",
          "tgn:7005880",
          "tgn:1000003",
          "tgn:7003237",
          "tgn:1000080",
          "tgn:7029392"
        ],
        "placetype": [
          "aat:300008347"
        ],
        "id": 1043994,
        "name:xx": "Castel d'Ario"
      }
    },
    {
      "geometry": {
        "type": "Point",
        "coordinates": [
          11.533333,
          42.883333
        ]
      },
      "type": "Feature",
      "properties": {
        "hierarchy": [
          "tgn:1043996",
          "tgn:1003460",
          "tgn:1000003",
          "tgn:7009760",
          "tgn:1000080",
          "tgn:7029392"
        ],
        "placetype": [
          "aat:300008347"
        ],
        "id": 1043996,
        "name:xx": "Castel del Piano"
      }
    },
    {
      "geometry": {
        "type": "Point",
        "coordinates": [
          13.733333,
          42.1
        ]
      },
      "type": "Feature",
      "properties": {
        "hierarchy": [
          "tgn:1043998",
          "tgn:7009084",
          "tgn:7004154",
          "tgn:1000003",
          "tgn:1000080",
          "tgn:7029392"
        ],
        "placetype": [
          "aat:300008347"
        ],
        "id": 1043998,
        "name:xx": "Castel di Ieri"
      }
    },
    {
      "geometry": {
        "type": "Point",
        "coordinates": [
          14.316667,
          37.883333
        ]
      },
      "type": "Feature",
      "properties": {
        "hierarchy": [
          "tgn:1043999",
          "tgn:1000003",
          "tgn:7003122",
          "tgn:7003157",
          "tgn:1000080",
          "tgn:7029392"
        ],
        "placetype": [
          "aat:300008347"
        ],
        "id": 1043999,
        "name:xx": "Castel di Lucio"
      }
    }
  ]
}
