{
  "type": "FeatureCollection",
  "features": [
    {
      "geometry": {
        "type": "Point",
        "coordinates": [
          -85.5,
          36.85
        ]
      },
      "type": "Feature",
      "properties": {
        "hierarchy": [
          "tgn:2600910",
          "tgn:1000001",
          "tgn:7012149",
          "tgn:2000785",
          "tgn:7007255",
          "tgn:7029392"
        ],
        "placetype": [
          "aat:300008761"
        ],
        "id": 2600910,
        "name:xx": "Pumpkin Hollow"
      }
    },
    {
      "geometry": {
        "type": "Point",
        "coordinates": [
          -91.05,
          37.1833
        ]
      },
      "type": "Feature",
      "properties": {
        "hierarchy": [
          "tgn:2600911",
          "tgn:1000001",
          "tgn:7012149",
          "tgn:2001236",
          "tgn:7007523",
          "tgn:7029392"
        ],
        "placetype": [
          "aat:300008761"
        ],
        "id": 2600911,
        "name:xx": "Pumpkin Hollow"
      }
    },
    {
      "geometry": {
        "type": "Point",
        "coordinates": [
          -118.9167,
          38.8
        ]
      },
      "type": "Feature",
      "properties": {
        "hierarchy": [
          "tgn:2600913",
          "tgn:1000001",
          "tgn:7012149",
          "tgn:7007526",
          "tgn:7029392"
        ],
        "placetype": [
          "aat:300008761"
        ],
        "id": 2600913,
        "name:xx": "Pumpkin Hollow"
      }
    },
    {
      "geometry": {
        "type": "Point",
        "coordinates": [
          -74.25,
          43.35
        ]
      },
      "type": "Feature",
      "properties": {
        "hierarchy": [
          "tgn:2600914",
          "tgn:1000001",
          "tgn:7012149",
          "tgn:1002440",
          "tgn:7007568",
          "tgn:7029392"
        ],
        "placetype": [
          "aat:300008347"
        ],
        "id": 2600914,
        "name:xx": "Pumpkin Hollow"
      }
    },
    {
      "geometry": {
        "type": "Point",
        "coordinates": [
          -73.55,
          42.2167
        ]
      },
      "type": "Feature",
      "properties": {
        "hierarchy": [
          "tgn:2600915",
          "tgn:1000001",
          "tgn:7013638",
          "tgn:7012149",
          "tgn:7007568",
          "tgn:7029392"
        ],
        "placetype": [
          "aat:300008798"
        ],
        "id": 2600915,
        "name:xx": "Pumpkin Hollow"
      }
    },
    {
      "geometry": {
        "type": "Point",
        "coordinates": [
          -78.5333,
          42.1667
        ]
      },
      "type": "Feature",
      "properties": {
        "hierarchy": [
          "tgn:2600916",
          "tgn:1000001",
          "tgn:1002245",
          "tgn:7012149",
          "tgn:7007568",
          "tgn:7029392"
        ],
        "placetype": [
          "aat:300008761"
        ],
        "id": 2600916,
        "name:xx": "Pumpkin Hollow"
      }
    },
    {
      "geometry": {
        "type": "Point",
        "coordinates": [
          -74.9,
          42.4167
        ]
      },
      "type": "Feature",
      "properties": {
        "hierarchy": [
          "tgn:2600917",
          "tgn:1000001",
          "tgn:1002328",
          "tgn:7012149",
          "tgn:7007568",
          "tgn:7029392"
        ],
        "placetype": [
          "aat:300008761"
        ],
        "id": 2600917,
        "name:xx": "Pumpkin Hollow"
      }
    },
    {
      "geometry": {
        "type": "Point",
        "coordinates": [
          -76.25,
          42.9667
        ]
      },
      "type": "Feature",
      "properties": {
        "hierarchy": [
          "tgn:2600918",
          "tgn:1000001",
          "tgn:7012149",
          "tgn:1002746",
          "tgn:7007568",
          "tgn:7029392"
        ],
        "placetype": [
          "aat:300008761"
        ],
        "id": 2600918,
        "name:xx": "Pumpkin Hollow"
      }
    },
    {
      "geometry": {
        "type": "Point",
        "coordinates": [
          -94.7833,
          36.05
        ]
      },
      "type": "Feature",
      "properties": {
        "hierarchy": [
          "tgn:2600919",
          "tgn:1000001",
          "tgn:7012149",
          "tgn:7007707",
          "tgn:7029392"
        ],
        "placetype": [
          "aat:300008761"
        ],
        "id": 2600919,
        "name:xx": "Pumpkin Hollow"
      }
    }
  ]
}
