{
  "geometry": {
    "type": "Point",
    "coordinates": [
      0.9167,
      42.7833
    ]
  },
  "type": "Feature",
  "properties": {
    "hierarchy": [
      "tgn:1107392",
      "tgn:1000003",
      "tgn:7029392"
    ],
    "placetype": [
      "aat:300008798"
    ],
    "name:fr": "Maubermé, Pic de",
    "id": 1107392,
    "name:es": "Mauberme, Pico"
  }
}
