{
  "type": "FeatureCollection",
  "features": [
    {
      "geometry": {
        "type": "Point",
        "coordinates": [
          -67.3333,
          -17.15
        ]
      },
      "type": "Feature",
      "properties": {
        "hierarchy": [
          "tgn:1020470",
          "tgn:1000662",
          "tgn:1000046",
          "tgn:1000002",
          "tgn:7029392"
        ],
        "placetype": [
          "aat:300008347"
        ],
        "id": 1020470,
        "name:xx": "Yaco"
      }
    },
    {
      "geometry": {
        "type": "Point",
        "coordinates": [
          -63.7167,
          -22
        ]
      },
      "type": "Feature",
      "properties": {
        "hierarchy": [
          "tgn:1020471",
          "tgn:1000776",
          "tgn:1000046",
          "tgn:1000002",
          "tgn:7029392"
        ],
        "placetype": [
          "aat:300008347"
        ],
        "id": 1020471,
        "name:xx": "Yacuiba"
      }
    },
    {
      "geometry": {
        "type": "Point",
        "coordinates": [
          -65.1667,
          -19.2
        ]
      },
      "type": "Feature",
      "properties": {
        "hierarchy": [
          "tgn:1020472",
          "tgn:1000571",
          "tgn:1000046",
          "tgn:1000002",
          "tgn:7029392"
        ],
        "placetype": [
          "aat:300008347"
        ],
        "id": 1020472,
        "name:xx": "Yamparáez"
      }
    },
    {
      "geometry": {
        "type": "Point",
        "coordinates": [
          -67.7333,
          -16.3833
        ]
      },
      "type": "Feature",
      "properties": {
        "hierarchy": [
          "tgn:1020473",
          "tgn:1000662",
          "tgn:1000046",
          "tgn:1000002",
          "tgn:7029392"
        ],
        "placetype": [
          "aat:300008347"
        ],
        "id": 1020473,
        "name:xx": "Yanacachi"
      }
    },
    {
      "geometry": {
        "type": "Point",
        "coordinates": [
          -64.3,
          -16.75
        ]
      },
      "type": "Feature",
      "properties": {
        "hierarchy": [
          "tgn:1020474",
          "tgn:1000752",
          "tgn:1000046",
          "tgn:1000002",
          "tgn:7029392"
        ],
        "placetype": [
          "aat:300008347"
        ],
        "id": 1020474,
        "name:xx": "Yapacaní"
      }
    },
    {
      "geometry": {
        "type": "Point",
        "coordinates": [
          -66.4167,
          -13.5
        ]
      },
      "type": "Feature",
      "properties": {
        "hierarchy": [
          "tgn:1020475",
          "tgn:1000525",
          "tgn:1000046",
          "tgn:1000002",
          "tgn:7029392"
        ],
        "placetype": [
          "aat:300008347"
        ],
        "id": 1020475,
        "name:xx": "Yata"
      }
    },
    {
      "geometry": {
        "type": "Point",
        "coordinates": [
          -63.0333,
          -16.0833
        ]
      },
      "type": "Feature",
      "properties": {
        "hierarchy": [
          "tgn:1020476",
          "tgn:1000752",
          "tgn:1000046",
          "tgn:1000002",
          "tgn:7029392"
        ],
        "placetype": [
          "aat:300008347"
        ],
        "id": 1020476,
        "name:xx": "Yotau"
      }
    },
    {
      "geometry": {
        "type": "Point",
        "coordinates": [
          -65.2667,
          -19.2
        ]
      },
      "type": "Feature",
      "properties": {
        "hierarchy": [
          "tgn:1020477",
          "tgn:1000571",
          "tgn:1000046",
          "tgn:1000002",
          "tgn:7029392"
        ],
        "placetype": [
          "aat:300008347"
        ],
        "id": 1020477,
        "name:xx": "Villa Oropeza"
      }
    },
    {
      "geometry": {
        "type": "Point",
        "coordinates": [
          -64.75,
          -19.0833
        ]
      },
      "type": "Feature",
      "properties": {
        "hierarchy": [
          "tgn:1020478",
          "tgn:1000571",
          "tgn:1000046",
          "tgn:1000002",
          "tgn:7029392"
        ],
        "placetype": [
          "aat:300008347"
        ],
        "id": 1020478,
        "name:xx": "Zudañez"
      }
    },
    {
      "geometry": {
        "type": "Point",
        "coordinates": [
          -42.4,
          -17.9833
        ]
      },
      "type": "Feature",
      "properties": {
        "hierarchy": [
          "tgn:1020479",
          "tgn:7006237",
          "tgn:1000047",
          "tgn:7002457",
          "tgn:1000002",
          "tgn:7029392"
        ],
        "placetype": [
          "aat:300008347"
        ],
        "id": 1020479,
        "name:xx": "Água Boa"
      }
    }
  ]
}
