{
  "geometry": {
    "type": "Point",
    "coordinates": [
      -70.6667,
      41.8167
    ]
  },
  "type": "Feature",
  "properties": {
    "hierarchy": [
      "tgn:2324163",
      "tgn:1000001",
      "tgn:7014423",
      "tgn:7012149",
      "tgn:7007517",
      "tgn:7029392"
    ],
    "placetype": [
      "aat:300008680"
    ],
    "id": 2324163,
    "name:xx": "Fearing Pond"
  }
}
