{
  "type": "FeatureCollection",
  "features": [
    {
      "geometry": {
        "type": "Point",
        "coordinates": [
          -77.8,
          41.1667
        ]
      },
      "type": "Feature",
      "properties": {
        "hierarchy": [
          "tgn:2451750",
          "tgn:1000001",
          "tgn:7012149",
          "tgn:7007710",
          "tgn:7029392"
        ],
        "placetype": [
          "aat:300008699"
        ],
        "id": 2451750,
        "name:xx": "Little Bear Run"
      }
    },
    {
      "geometry": {
        "type": "Point",
        "coordinates": [
          -78.2833,
          41.3667
        ]
      },
      "type": "Feature",
      "properties": {
        "hierarchy": [
          "tgn:2451751",
          "tgn:1000001",
          "tgn:7012149",
          "tgn:1002352",
          "tgn:7007710",
          "tgn:7029392"
        ],
        "placetype": [
          "aat:300008699"
        ],
        "id": 2451751,
        "name:xx": "Little Bear Run"
      }
    },
    {
      "geometry": {
        "type": "Point",
        "coordinates": [
          -104.0167,
          43.9833
        ]
      },
      "type": "Feature",
      "properties": {
        "hierarchy": [
          "tgn:2451752",
          "tgn:1000001",
          "tgn:7012149",
          "tgn:7029392"
        ],
        "placetype": [
          "aat:300008699"
        ],
        "id": 2451752,
        "name:xx": "Little Bear Run"
      }
    },
    {
      "geometry": {
        "type": "Point",
        "coordinates": [
          -105.4333,
          45.2
        ]
      },
      "type": "Feature",
      "properties": {
        "hierarchy": [
          "tgn:2451753",
          "tgn:1000001",
          "tgn:7012149",
          "tgn:2001297",
          "tgn:7007524",
          "tgn:7029392"
        ],
        "placetype": [
          "aat:300008706"
        ],
        "id": 2451753,
        "name:xx": "Little Bear Skull Creek"
      }
    },
    {
      "geometry": {
        "type": "Point",
        "coordinates": [
          -116.9667,
          34.2833
        ]
      },
      "type": "Feature",
      "properties": {
        "hierarchy": [
          "tgn:2451754",
          "tgn:1000001",
          "tgn:7012149",
          "tgn:7007157",
          "tgn:1002857",
          "tgn:7029392"
        ],
        "placetype": [
          "aat:300008697"
        ],
        "id": 2451754,
        "name:xx": "Little Bear Spring"
      }
    },
    {
      "geometry": {
        "type": "Point",
        "coordinates": [
          -116.6,
          45.1167
        ]
      },
      "type": "Feature",
      "properties": {
        "hierarchy": [
          "tgn:2451755",
          "tgn:2000453",
          "tgn:1000001",
          "tgn:7012149",
          "tgn:7007250",
          "tgn:7029392"
        ],
        "placetype": [
          "aat:300008697"
        ],
        "id": 2451755,
        "name:xx": "Little Bear Spring"
      }
    },
    {
      "geometry": {
        "type": "Point",
        "coordinates": [
          -105.6333,
          32.7833
        ]
      },
      "type": "Feature",
      "properties": {
        "hierarchy": [
          "tgn:2451756",
          "tgn:1000001",
          "tgn:7012149",
          "tgn:2001447",
          "tgn:7007566",
          "tgn:7029392"
        ],
        "placetype": [
          "aat:300008697"
        ],
        "id": 2451756,
        "name:xx": "Little Bear Spring"
      }
    },
    {
      "geometry": {
        "type": "Point",
        "coordinates": [
          -107.3,
          34.3167
        ]
      },
      "type": "Feature",
      "properties": {
        "hierarchy": [
          "tgn:2451757",
          "tgn:1000001",
          "tgn:7012149",
          "tgn:2001456",
          "tgn:7007566",
          "tgn:7029392"
        ],
        "placetype": [
          "aat:300008697"
        ],
        "id": 2451757,
        "name:xx": "Little Bear Spring"
      }
    },
    {
      "geometry": {
        "type": "Point",
        "coordinates": [
          -108.6,
          35.3667
        ]
      },
      "type": "Feature",
      "properties": {
        "hierarchy": [
          "tgn:2451758",
          "tgn:1000001",
          "tgn:7012149",
          "tgn:7019676",
          "tgn:7007566",
          "tgn:7029392"
        ],
        "placetype": [
          "aat:300008697"
        ],
        "id": 2451758,
        "name:xx": "Little Bear Spring"
      }
    },
    {
      "geometry": {
        "type": "Point",
        "coordinates": [
          -108.0333,
          32.9
        ]
      },
      "type": "Feature",
      "properties": {
        "hierarchy": [
          "tgn:2451759",
          "tgn:1000001",
          "tgn:7012149",
          "tgn:2001437",
          "tgn:7007566",
          "tgn:7029392"
        ],
        "placetype": [
          "aat:300008697"
        ],
        "id": 2451759,
        "name:xx": "Little Bear Spring"
      }
    }
  ]
}
