{
  "type": "FeatureCollection",
  "features": [
    {
      "geometry": {
        "type": "Point",
        "coordinates": [
          -63.15,
          46.2
        ]
      },
      "type": "Feature",
      "properties": {
        "hierarchy": [
          "tgn:1101982",
          "tgn:7005685",
          "tgn:1000001",
          "tgn:7005803",
          "tgn:7029392"
        ],
        "placetype": [
          "aat:300386977"
        ],
        "id": 1101982,
        "name:xx": "Fort Amherst National Historic Park"
      }
    },
    {
      "geometry": {
        "type": "Point",
        "coordinates": [
          -65.4333,
          44.7333
        ]
      },
      "type": "Feature",
      "properties": {
        "hierarchy": [
          "tgn:1101983",
          "tgn:7005685",
          "tgn:1000001",
          "tgn:7005802",
          "tgn:7029392"
        ],
        "placetype": [
          "aat:300386977"
        ],
        "id": 1101983,
        "name:xx": "Fort Anne National Historic Park"
      }
    },
    {
      "geometry": {
        "type": "Point",
        "coordinates": [
          -108.25,
          52.7
        ]
      },
      "type": "Feature",
      "properties": {
        "hierarchy": [
          "tgn:1101984",
          "tgn:7005685",
          "tgn:1000001",
          "tgn:7005805",
          "tgn:7029392"
        ],
        "placetype": [
          "aat:300386977"
        ],
        "id": 1101984,
        "name:xx": "Fort Battleford Historic Park"
      }
    },
    {
      "geometry": {
        "type": "Point",
        "coordinates": [
          -73.2833,
          45.45
        ]
      },
      "type": "Feature",
      "properties": {
        "hierarchy": [
          "tgn:1101986",
          "tgn:7005685",
          "tgn:1000001",
          "tgn:7005804",
          "tgn:7029392"
        ],
        "placetype": [
          "aat:300386977"
        ],
        "id": 1101986,
        "name:xx": "Fort Chambly National Historic Park"
      }
    },
    {
      "geometry": {
        "type": "Point",
        "coordinates": [
          -122.5833,
          49.1667
        ]
      },
      "type": "Feature",
      "properties": {
        "hierarchy": [
          "tgn:1101987",
          "tgn:7005735",
          "tgn:7005685",
          "tgn:1000001",
          "tgn:7029392"
        ],
        "placetype": [
          "aat:300386977"
        ],
        "id": 1101987,
        "name:xx": "Fort Langley National Historic Park"
      }
    },
    {
      "geometry": {
        "type": "Point",
        "coordinates": [
          -73.2667,
          45.1
        ]
      },
      "type": "Feature",
      "properties": {
        "hierarchy": [
          "tgn:1101989",
          "tgn:7005685",
          "tgn:1000001",
          "tgn:7005804",
          "tgn:7029392"
        ],
        "placetype": [
          "aat:300386977"
        ],
        "id": 1101989,
        "name:xx": "Fort Lennox National Historic Park"
      }
    }
  ]
}
