{
  "geometry": {
    "type": "Point",
    "coordinates": [
      -67.45,
      -55.75
    ]
  },
  "type": "Feature",
  "properties": {
    "hierarchy": [
      "tgn:7287975",
      "tgn:1001702",
      "tgn:1000049",
      "tgn:1000002",
      "tgn:7029392"
    ],
    "placetype": [
      "aat:300386968"
    ],
    "id": 7287975,
    "name:xx": "Fondeadero Hyde"
  }
}
