{
  "type": "FeatureCollection",
  "features": [
    {
      "geometry": {
        "type": "Point",
        "coordinates": [
          -86.6,
          33.95
        ]
      },
      "type": "Feature",
      "properties": {
        "hierarchy": [
          "tgn:2493461",
          "tgn:7002659",
          "tgn:1000001",
          "tgn:2000004",
          "tgn:7012149",
          "tgn:7029392"
        ],
        "placetype": [
          "aat:300008699"
        ],
        "id": 2493461,
        "name:xx": "Marsh Branch"
      }
    },
    {
      "geometry": {
        "type": "Point",
        "coordinates": [
          -85.9167,
          31.4
        ]
      },
      "type": "Feature",
      "properties": {
        "hierarchy": [
          "tgn:2493462",
          "tgn:7002659",
          "tgn:1000001",
          "tgn:2000015",
          "tgn:7012149",
          "tgn:7029392"
        ],
        "placetype": [
          "aat:300008699"
        ],
        "id": 2493462,
        "name:xx": "Marsh Branch"
      }
    },
    {
      "geometry": {
        "type": "Point",
        "coordinates": [
          -82.4,
          27.6833
        ]
      },
      "type": "Feature",
      "properties": {
        "hierarchy": [
          "tgn:2493463",
          "tgn:1000001",
          "tgn:1002479",
          "tgn:7012149",
          "tgn:7007240",
          "tgn:7029392"
        ],
        "placetype": [
          "aat:300008699"
        ],
        "id": 2493463,
        "name:xx": "Marsh Branch"
      }
    },
    {
      "geometry": {
        "type": "Point",
        "coordinates": [
          -84.2333,
          37.0167
        ]
      },
      "type": "Feature",
      "properties": {
        "hierarchy": [
          "tgn:2493464",
          "tgn:1000001",
          "tgn:7012149",
          "tgn:2000808",
          "tgn:7007255",
          "tgn:7029392"
        ],
        "placetype": [
          "aat:300008699"
        ],
        "id": 2493464,
        "name:xx": "Marsh Branch"
      }
    },
    {
      "geometry": {
        "type": "Point",
        "coordinates": [
          -78.35,
          34.5667
        ]
      },
      "type": "Feature",
      "properties": {
        "hierarchy": [
          "tgn:2493465",
          "tgn:1000001",
          "tgn:2001471",
          "tgn:7012149",
          "tgn:7007709",
          "tgn:7029392"
        ],
        "placetype": [
          "aat:300008699"
        ],
        "id": 2493465,
        "name:xx": "Marsh Branch"
      }
    },
    {
      "geometry": {
        "type": "Point",
        "coordinates": [
          -78.0333,
          34.9667
        ]
      },
      "type": "Feature",
      "properties": {
        "hierarchy": [
          "tgn:2493466",
          "tgn:1000001",
          "tgn:7012149",
          "tgn:2001491",
          "tgn:7007709",
          "tgn:7029392"
        ],
        "placetype": [
          "aat:300008699"
        ],
        "id": 2493466,
        "name:xx": "Marsh Branch"
      }
    },
    {
      "geometry": {
        "type": "Point",
        "coordinates": [
          -94.9667,
          30.4
        ]
      },
      "type": "Feature",
      "properties": {
        "hierarchy": [
          "tgn:2493467",
          "tgn:1000001",
          "tgn:7012149",
          "tgn:1002595",
          "tgn:7007826",
          "tgn:7029392"
        ],
        "placetype": [
          "aat:300008699"
        ],
        "id": 2493467,
        "name:xx": "Marsh Branch"
      }
    },
    {
      "geometry": {
        "type": "Point",
        "coordinates": [
          -72.4333,
          41.8833
        ]
      },
      "type": "Feature",
      "properties": {
        "hierarchy": [
          "tgn:2493468",
          "tgn:1000001",
          "tgn:1002949",
          "tgn:7012149",
          "tgn:7007159",
          "tgn:7029392"
        ],
        "placetype": [
          "aat:300008699"
        ],
        "id": 2493468,
        "name:xx": "Marsh Brook"
      }
    },
    {
      "geometry": {
        "type": "Point",
        "coordinates": [
          -72.9833,
          41.7167
        ]
      },
      "type": "Feature",
      "properties": {
        "hierarchy": [
          "tgn:2493469",
          "tgn:1000001",
          "tgn:7012149",
          "tgn:7007159",
          "tgn:7029392"
        ],
        "placetype": [
          "aat:300008699"
        ],
        "id": 2493469,
        "name:xx": "Marsh Brook"
      }
    }
  ]
}
