{
  "type": "FeatureCollection",
  "features": [
    {
      "geometry": {
        "type": "Point",
        "coordinates": [
          78.916667,
          13.2
        ]
      },
      "type": "Feature",
      "properties": {
        "hierarchy": [
          "tgn:7581670",
          "tgn:1001828",
          "tgn:1000004",
          "tgn:7000198",
          "tgn:7029392"
        ],
        "placetype": [
          "aat:300008347"
        ],
        "name:en": "Venkatagiri",
        "id": 7581670
      }
    },
    {
      "geometry": {
        "type": "Point",
        "coordinates": [
          79.916667,
          14.316667
        ]
      },
      "type": "Feature",
      "properties": {
        "hierarchy": [
          "tgn:7581671",
          "tgn:1001828",
          "tgn:1000004",
          "tgn:7000198",
          "tgn:7029392"
        ],
        "placetype": [
          "aat:300008347"
        ],
        "name:en": "Venkatachelam",
        "id": 7581671
      }
    },
    {
      "geometry": {
        "type": "Point",
        "coordinates": [
          76.9,
          8.683333
        ]
      },
      "type": "Feature",
      "properties": {
        "hierarchy": [
          "tgn:7581672",
          "tgn:1000004",
          "tgn:7000198",
          "tgn:1001886",
          "tgn:7029392"
        ],
        "placetype": [
          "aat:300008347"
        ],
        "name:en": "Venjāramūdu",
        "id": 7581672
      }
    },
    {
      "geometry": {
        "type": "Point",
        "coordinates": [
          73.483333,
          15.983333
        ]
      },
      "type": "Feature",
      "properties": {
        "hierarchy": [
          "tgn:7581673",
          "tgn:1000004",
          "tgn:7018318",
          "tgn:7000198",
          "tgn:7029392"
        ],
        "placetype": [
          "aat:300011692"
        ],
        "name:en": "Vengurla Rocks",
        "id": 7581673
      }
    },
    {
      "geometry": {
        "type": "Point",
        "coordinates": [
          72.7,
          21.683333
        ]
      },
      "type": "Feature",
      "properties": {
        "hierarchy": [
          "tgn:7581675",
          "tgn:1000004",
          "tgn:1001869",
          "tgn:7000198",
          "tgn:7029392"
        ],
        "placetype": [
          "aat:300008347"
        ],
        "name:en": "Vengni",
        "id": 7581675
      }
    },
    {
      "geometry": {
        "type": "Point",
        "coordinates": [
          69.1,
          22.9
        ]
      },
      "type": "Feature",
      "properties": {
        "hierarchy": [
          "tgn:7581676",
          "tgn:1000004",
          "tgn:1001869",
          "tgn:7000198",
          "tgn:7029392"
        ],
        "placetype": [
          "aat:300008699"
        ],
        "name:en": "Vengdi Nadi",
        "id": 7581676
      }
    },
    {
      "geometry": {
        "type": "Point",
        "coordinates": [
          80.5,
          17.416667
        ]
      },
      "type": "Feature",
      "properties": {
        "hierarchy": [
          "tgn:7581677",
          "tgn:1001828",
          "tgn:1000004",
          "tgn:7000198",
          "tgn:7029392"
        ],
        "placetype": [
          "aat:300008347"
        ],
        "name:en": "Vengannapālem",
        "id": 7581677
      }
    },
    {
      "geometry": {
        "type": "Point",
        "coordinates": [
          80.012778,
          13.249722
        ]
      },
      "type": "Feature",
      "properties": {
        "hierarchy": [
          "tgn:7581678",
          "tgn:1000004",
          "tgn:7000198",
          "tgn:7001797",
          "tgn:7029392"
        ],
        "placetype": [
          "aat:300008347"
        ],
        "name:en": "Vengal",
        "id": 7581678
      }
    },
    {
      "geometry": {
        "type": "Point",
        "coordinates": [
          76.283333,
          9.95
        ]
      },
      "type": "Feature",
      "properties": {
        "hierarchy": [
          "tgn:7581679",
          "tgn:1000004",
          "tgn:7000198",
          "tgn:1001886",
          "tgn:7029392"
        ],
        "placetype": [
          "aat:300008791"
        ],
        "name:en": "Venduruthi Island",
        "id": 7581679
      }
    }
  ]
}
