{
  "geometry": {
    "type": "Point",
    "coordinates": [
      -87.4833,
      35.4833
    ]
  },
  "type": "Feature",
  "properties": {
    "hierarchy": [
      "tgn:2407829",
      "tgn:1000001",
      "tgn:7012149",
      "tgn:2001887",
      "tgn:7007825",
      "tgn:7029392"
    ],
    "placetype": [
      "aat:300008699"
    ],
    "id": 2407829,
    "name:xx": "Hurricane Branch"
  }
}
