{
  "geometry": {
    "type": "Point",
    "coordinates": [
      -82.1833,
      35.3333
    ]
  },
  "type": "Feature",
  "properties": {
    "hierarchy": [
      "tgn:2126224",
      "tgn:1000001",
      "tgn:7012149",
      "tgn:2001531",
      "tgn:7007709",
      "tgn:7029392"
    ],
    "placetype": [
      "aat:300006191"
    ],
    "id": 2126224,
    "name:xx": "Adger, Lake"
  }
}
