{
  "geometry": {
    "type": "Point",
    "coordinates": [
      31.340389,
      30.86167
    ]
  },
  "type": "Feature",
  "properties": {
    "hierarchy": [
      "tgn:7537395",
      "tgn:7001242",
      "tgn:1001059",
      "tgn:7016833",
      "tgn:7029392"
    ],
    "placetype": [
      "aat:300008347"
    ],
    "name:en": "Mīt Abū al Ḩusayn",
    "id": 7537395
  }
}
