{
  "type": "FeatureCollection",
  "features": [
    {
      "geometry": {
        "type": "Point",
        "coordinates": [
          8.3833,
          46.9167
        ]
      },
      "type": "Feature",
      "properties": {
        "hierarchy": [
          "tgn:4003140",
          "tgn:1000003",
          "tgn:7003753",
          "tgn:7011731",
          "tgn:7029392"
        ],
        "placetype": [
          "aat:300008347"
        ],
        "id": 4003140,
        "name:xx": "Dallenwil"
      }
    },
    {
      "geometry": {
        "type": "Point",
        "coordinates": [
          -3.383333,
          55.966667
        ]
      },
      "type": "Feature",
      "properties": {
        "hierarchy": [
          "tgn:4003142",
          "tgn:7002444",
          "tgn:1000003",
          "tgn:7019109",
          "tgn:7008591",
          "tgn:7029392"
        ],
        "placetype": [
          "aat:300008347"
        ],
        "name:en": "Dalmeny",
        "id": 4003142
      }
    },
    {
      "geometry": {
        "type": "Point",
        "coordinates": [
          1.9667,
          43.65
        ]
      },
      "type": "Feature",
      "properties": {
        "hierarchy": [
          "tgn:4003145",
          "tgn:1000003",
          "tgn:7002889",
          "tgn:1000070",
          "tgn:7029392"
        ],
        "placetype": [
          "aat:300008347"
        ],
        "id": 4003145,
        "name:xx": "Damiatte"
      }
    },
    {
      "geometry": {
        "type": "Point",
        "coordinates": [
          9.983333,
          54.583333
        ]
      },
      "type": "Feature",
      "properties": {
        "hierarchy": [
          "tgn:4003148",
          "tgn:1000003",
          "tgn:7003688",
          "tgn:7000084",
          "tgn:7029392"
        ],
        "placetype": [
          "aat:300008347"
        ],
        "id": 4003148,
        "name:xx": "Damp"
      }
    }
  ]
}
