{
  "geometry": {
    "type": "Point",
    "coordinates": [
      -91.0667,
      34.2667
    ]
  },
  "type": "Feature",
  "properties": {
    "hierarchy": [
      "tgn:2466094",
      "tgn:1000001",
      "tgn:7016172",
      "tgn:7012149",
      "tgn:2000158",
      "tgn:7029392"
    ],
    "placetype": [
      "aat:300008850"
    ],
    "id": 2466094,
    "name:xx": "Lone Willow Point"
  }
}
