{
  "type": "FeatureCollection",
  "features": [
    {
      "geometry": {
        "type": "Point",
        "coordinates": [
          33.766186,
          27.594086
        ]
      },
      "type": "Feature",
      "properties": {
        "hierarchy": [
          "tgn:1009820",
          "tgn:7001242",
          "tgn:7001311",
          "tgn:7016833",
          "tgn:7029392"
        ],
        "placetype": [
          "aat:300008791"
        ],
        "id": 1009820,
        "name:xx": "Ṭawīlah, Juzur"
      }
    },
    {
      "geometry": {
        "type": "Point",
        "coordinates": [
          56.6167,
          -10.4
        ]
      },
      "type": "Feature",
      "properties": {
        "hierarchy": [
          "tgn:1009823",
          "tgn:7001242",
          "tgn:1000177",
          "tgn:7029392"
        ],
        "placetype": [
          "aat:300235114",
          "aat:300387064",
          "aat:300386853"
        ],
        "id": 1009823,
        "name:xx": "Agalega"
      }
    },
    {
      "geometry": {
        "type": "Point",
        "coordinates": [
          53.1667,
          12.1333
        ]
      },
      "type": "Feature",
      "properties": {
        "hierarchy": [
          "tgn:1009825",
          "tgn:1000139",
          "tgn:7004345",
          "tgn:1000004",
          "tgn:7000261",
          "tgn:7029392"
        ],
        "placetype": [
          "aat:300008791"
        ],
        "id": 1009825,
        "name:xx": "Al-Ikhwān"
      }
    },
    {
      "geometry": {
        "type": "Point",
        "coordinates": [
          -81.8333,
          12.1667
        ]
      },
      "type": "Feature",
      "properties": {
        "hierarchy": [
          "tgn:1009826",
          "tgn:1000050",
          "tgn:1002111",
          "tgn:1000002",
          "tgn:7029392"
        ],
        "placetype": [
          "aat:300386853"
        ],
        "id": 1009826,
        "name:xx": "Albuquerque, Cayos de"
      }
    }
  ]
}
