{
  "geometry": {
    "type": "Point",
    "coordinates": [
      -95.5167,
      29.35
    ]
  },
  "type": "Feature",
  "properties": {
    "hierarchy": [
      "tgn:2463676",
      "tgn:1000001",
      "tgn:1002198",
      "tgn:7012149",
      "tgn:7007826",
      "tgn:7029392"
    ],
    "placetype": [
      "aat:300008347"
    ],
    "id": 2463676,
    "name:xx": "Lochridge"
  }
}
