{
  "geometry": {
    "type": "Point",
    "coordinates": [
      -98.7667,
      42.45
    ]
  },
  "type": "Feature",
  "properties": {
    "hierarchy": [
      "tgn:2001360",
      "tgn:1000001",
      "tgn:7012149",
      "tgn:7007525",
      "tgn:7029392"
    ],
    "placetype": [
      "aat:300387145",
      "aat:300000771"
    ],
    "id": 2001360,
    "name:xx": "Holt"
  }
}
