{
  "type": "FeatureCollection",
  "features": [
    {
      "geometry": {
        "type": "Point",
        "coordinates": [
          -87.1833,
          30.55
        ]
      },
      "type": "Feature",
      "properties": {
        "hierarchy": [
          "tgn:2645130",
          "tgn:1000001",
          "tgn:7012149",
          "tgn:2000285",
          "tgn:7007240",
          "tgn:7029392"
        ],
        "placetype": [
          "aat:300132316"
        ],
        "id": 2645130,
        "name:xx": "Saultsman Cove"
      }
    },
    {
      "geometry": {
        "type": "Point",
        "coordinates": [
          -122.75,
          45.3333
        ]
      },
      "type": "Feature",
      "properties": {
        "hierarchy": [
          "tgn:2645131",
          "tgn:1000001",
          "tgn:7012149",
          "tgn:7007708",
          "tgn:7029392"
        ],
        "placetype": [
          "aat:300008706"
        ],
        "id": 2645131,
        "name:xx": "Saum Creek"
      }
    },
    {
      "geometry": {
        "type": "Point",
        "coordinates": [
          -88.6167,
          46.5
        ]
      },
      "type": "Feature",
      "properties": {
        "hierarchy": [
          "tgn:2645132",
          "tgn:2000947",
          "tgn:1000001",
          "tgn:7012149",
          "tgn:7007520",
          "tgn:7029392"
        ],
        "placetype": [
          "aat:300008706"
        ],
        "id": 2645132,
        "name:xx": "Sauna Creek"
      }
    },
    {
      "geometry": {
        "type": "Point",
        "coordinates": [
          -91.7333,
          48.1333
        ]
      },
      "type": "Feature",
      "properties": {
        "hierarchy": [
          "tgn:2645133",
          "tgn:1000001",
          "tgn:7012149",
          "tgn:2001036",
          "tgn:7007521",
          "tgn:7029392"
        ],
        "placetype": [
          "aat:300008680"
        ],
        "id": 2645133,
        "name:xx": "Sauna Lake"
      }
    },
    {
      "geometry": {
        "type": "Point",
        "coordinates": [
          -88.75,
          46.55
        ]
      },
      "type": "Feature",
      "properties": {
        "hierarchy": [
          "tgn:2645134",
          "tgn:1000001",
          "tgn:7012149",
          "tgn:2000963",
          "tgn:7007520",
          "tgn:7029392"
        ],
        "placetype": [
          "aat:300008680"
        ],
        "id": 2645134,
        "name:xx": "Saunder Lake"
      }
    },
    {
      "geometry": {
        "type": "Point",
        "coordinates": [
          -108,
          38.75
        ]
      },
      "type": "Feature",
      "properties": {
        "hierarchy": [
          "tgn:2645135",
          "tgn:1000001",
          "tgn:7012149",
          "tgn:2000206",
          "tgn:7007158",
          "tgn:7029392"
        ],
        "placetype": [
          "aat:300008347"
        ],
        "id": 2645135,
        "name:xx": "Saunders"
      }
    },
    {
      "geometry": {
        "type": "Point",
        "coordinates": [
          -83.05,
          32.2
        ]
      },
      "type": "Feature",
      "properties": {
        "hierarchy": [
          "tgn:2645136",
          "tgn:1000001",
          "tgn:7012149",
          "tgn:2000336",
          "tgn:7007248",
          "tgn:7029392"
        ],
        "placetype": [
          "aat:300008347"
        ],
        "id": 2645136,
        "name:xx": "Saunders"
      }
    },
    {
      "geometry": {
        "type": "Point",
        "coordinates": [
          -89.3,
          39.85
        ]
      },
      "type": "Feature",
      "properties": {
        "hierarchy": [
          "tgn:2645137",
          "tgn:1000001",
          "tgn:7012149",
          "tgn:1002866",
          "tgn:7007251",
          "tgn:7029392"
        ],
        "placetype": [
          "aat:300008347"
        ],
        "id": 2645137,
        "name:xx": "Saunders"
      }
    },
    {
      "geometry": {
        "type": "Point",
        "coordinates": [
          -93.1,
          36.8667
        ]
      },
      "type": "Feature",
      "properties": {
        "hierarchy": [
          "tgn:2645138",
          "tgn:1000001",
          "tgn:2001185",
          "tgn:7012149",
          "tgn:7007523",
          "tgn:7029392"
        ],
        "placetype": [
          "aat:300008347"
        ],
        "id": 2645138,
        "name:xx": "Saunders"
      }
    },
    {
      "geometry": {
        "type": "Point",
        "coordinates": [
          -111.95,
          41.2
        ]
      },
      "type": "Feature",
      "properties": {
        "hierarchy": [
          "tgn:2645139",
          "tgn:1000001",
          "tgn:7012149",
          "tgn:2002129",
          "tgn:7007827",
          "tgn:7029392"
        ],
        "placetype": [
          "aat:300008347"
        ],
        "id": 2645139,
        "name:xx": "Saunders"
      }
    }
  ]
}
