{
  "geometry": {
    "type": "Point",
    "coordinates": [
      82.5167,
      50.1333
    ]
  },
  "type": "Feature",
  "properties": {
    "hierarchy": [
      "tgn:1137258",
      "tgn:1000004",
      "tgn:7012943",
      "tgn:7014786",
      "tgn:7029392"
    ],
    "placetype": [
      "aat:300008347"
    ],
    "id": 1137258,
    "name:xx": "Belousovka"
  }
}
