{
  "type": "FeatureCollection",
  "features": [
    {
      "geometry": {
        "type": "Point",
        "coordinates": [
          -105.3167,
          39.6333
        ]
      },
      "type": "Feature",
      "properties": {
        "hierarchy": [
          "tgn:7015740",
          "tgn:1000001",
          "tgn:7012149",
          "tgn:2000221",
          "tgn:7007158",
          "tgn:7029392"
        ],
        "placetype": [
          "aat:300008347"
        ],
        "id": 7015740,
        "name:xx": "Evergreen"
      }
    },
    {
      "geometry": {
        "type": "Point",
        "coordinates": [
          -106.9833,
          39.3167
        ]
      },
      "type": "Feature",
      "properties": {
        "hierarchy": [
          "tgn:7015742",
          "tgn:1000001",
          "tgn:7012149",
          "tgn:7007158",
          "tgn:2000240",
          "tgn:7029392"
        ],
        "placetype": [
          "aat:300008347"
        ],
        "id": 7015742,
        "name:xx": "Snowmass"
      }
    },
    {
      "geometry": {
        "type": "Point",
        "coordinates": [
          -97.95,
          32.7
        ]
      },
      "type": "Feature",
      "properties": {
        "hierarchy": [
          "tgn:7015745",
          "tgn:1000001",
          "tgn:7012149",
          "tgn:1002771",
          "tgn:7007826",
          "tgn:7029392"
        ],
        "placetype": [
          "aat:300008347",
          "aat:300387210"
        ],
        "id": 7015745,
        "name:xx": "Brock Junction"
      }
    },
    {
      "geometry": {
        "type": "Point",
        "coordinates": [
          -156.9667,
          21.2167
        ]
      },
      "type": "Feature",
      "properties": {
        "hierarchy": [
          "tgn:7015746",
          "tgn:1002648",
          "tgn:1000001",
          "tgn:1002530",
          "tgn:1008191",
          "tgn:7012149",
          "tgn:7007249",
          "tgn:7029392"
        ],
        "placetype": [
          "aat:300386846"
        ],
        "id": 7015746,
        "name:xx": "Kahiu Point"
      }
    },
    {
      "geometry": {
        "type": "Point",
        "coordinates": [
          -157.8333,
          21.4333
        ]
      },
      "type": "Feature",
      "properties": {
        "hierarchy": [
          "tgn:7015747",
          "tgn:1002483",
          "tgn:7019080",
          "tgn:1000001",
          "tgn:7012149",
          "tgn:7007249",
          "tgn:7029392"
        ],
        "placetype": [
          "aat:300008347"
        ],
        "id": 7015747,
        "name:xx": "Ahuimanu"
      }
    }
  ]
}
