{
  "type": "FeatureCollection",
  "features": [
    {
      "geometry": {
        "type": "Point",
        "coordinates": [
          -85.034,
          13.768
        ]
      },
      "type": "Feature",
      "properties": {
        "hierarchy": [
          "tgn:1106351",
          "tgn:1000001",
          "tgn:7005562",
          "tgn:7029392"
        ],
        "placetype": [
          "aat:300008795"
        ],
        "id": 1106351,
        "name:xx": "Saslaya, Cerro"
      }
    },
    {
      "geometry": {
        "type": "Point",
        "coordinates": [
          -82.7667,
          35.05
        ]
      },
      "type": "Feature",
      "properties": {
        "hierarchy": [
          "tgn:1106352",
          "tgn:1000001",
          "tgn:7012149",
          "tgn:7029392"
        ],
        "placetype": [
          "aat:300008795"
        ],
        "id": 1106352,
        "name:xx": "Sassafras Mountain"
      }
    },
    {
      "geometry": {
        "type": "Point",
        "coordinates": [
          -124.7,
          52.4667
        ]
      },
      "type": "Feature",
      "properties": {
        "hierarchy": [
          "tgn:1106353",
          "tgn:7005735",
          "tgn:7005685",
          "tgn:1000001",
          "tgn:7029392"
        ],
        "placetype": [
          "aat:300008795"
        ],
        "id": 1106353,
        "name:xx": "Satah Mountain"
      }
    },
    {
      "geometry": {
        "type": "Point",
        "coordinates": [
          -126.4833,
          52.2667
        ]
      },
      "type": "Feature",
      "properties": {
        "hierarchy": [
          "tgn:1106354",
          "tgn:7005735",
          "tgn:7005685",
          "tgn:1000001",
          "tgn:7029392"
        ],
        "placetype": [
          "aat:300008795"
        ],
        "id": 1106354,
        "name:xx": "Saugstad, Mount"
      }
    },
    {
      "geometry": {
        "type": "Point",
        "coordinates": [
          36.1167,
          34.3
        ]
      },
      "type": "Feature",
      "properties": {
        "hierarchy": [
          "tgn:1106356",
          "tgn:1001111",
          "tgn:1000004",
          "tgn:1000126",
          "tgn:7029392"
        ],
        "placetype": [
          "aat:300008795"
        ],
        "id": 1106356,
        "name:xx": "Sawdā', Qurnat as-"
      }
    },
    {
      "geometry": {
        "type": "Point",
        "coordinates": [
          -7.033333,
          54.816667
        ]
      },
      "type": "Feature",
      "properties": {
        "hierarchy": [
          "tgn:1106357",
          "tgn:7002448",
          "tgn:1000003",
          "tgn:7008591",
          "tgn:7029392"
        ],
        "placetype": [
          "aat:300008795"
        ],
        "name:en": "Sawel Mountain",
        "id": 1106357
      }
    },
    {
      "geometry": {
        "type": "Point",
        "coordinates": [
          -112.8167,
          47.3
        ]
      },
      "type": "Feature",
      "properties": {
        "hierarchy": [
          "tgn:1106359",
          "tgn:1000001",
          "tgn:7012149",
          "tgn:2001284",
          "tgn:7007524",
          "tgn:7029392"
        ],
        "placetype": [
          "aat:300008795"
        ],
        "id": 1106359,
        "name:xx": "Scapegoat Mountain"
      }
    }
  ]
}
