{
  "geometry": {
    "type": "Point",
    "coordinates": [
      34.75,
      47.75
    ]
  },
  "type": "Feature",
  "properties": {
    "hierarchy": [
      "tgn:1057033",
      "tgn:7011648",
      "tgn:1000003",
      "tgn:7006660",
      "tgn:7029392"
    ],
    "placetype": [
      "aat:300008347"
    ],
    "id": 1057033,
    "name:xx": "Mirove"
  }
}
