{
  "geometry": {
    "type": "Point",
    "coordinates": [
      -84.6833,
      33.6333
    ]
  },
  "type": "Feature",
  "properties": {
    "hierarchy": [
      "tgn:2670313",
      "tgn:1000001",
      "tgn:7012149",
      "tgn:2000351",
      "tgn:7007248",
      "tgn:7029392"
    ],
    "placetype": [
      "aat:300006191"
    ],
    "id": 2670313,
    "name:xx": "Small Browns Lake"
  }
}
