{
  "geometry": {
    "type": "Point",
    "coordinates": [
      -87.1167,
      35.45
    ]
  },
  "type": "Feature",
  "properties": {
    "hierarchy": [
      "tgn:2330246",
      "tgn:1000001",
      "tgn:7012149",
      "tgn:2001896",
      "tgn:7007825",
      "tgn:7029392"
    ],
    "placetype": [
      "aat:300008798"
    ],
    "id": 2330246,
    "name:xx": "Flanigan Hill"
  }
}
