{
  "geometry": {
    "type": "Point",
    "coordinates": [
      -99.7667,
      39.4667
    ]
  },
  "type": "Feature",
  "properties": {
    "hierarchy": [
      "tgn:2628842",
      "tgn:1000001",
      "tgn:2000692",
      "tgn:7012149",
      "tgn:7007254",
      "tgn:7029392"
    ],
    "placetype": [
      "aat:300008347"
    ],
    "id": 2628842,
    "name:xx": "Roscoe"
  }
}
