{
  "geometry": {
    "type": "Point",
    "coordinates": [
      -81.2667,
      29.8667
    ]
  },
  "type": "Feature",
  "properties": {
    "hierarchy": [
      "tgn:2173883",
      "tgn:1000001",
      "tgn:7012149",
      "tgn:2000283",
      "tgn:7007240",
      "tgn:7029392"
    ],
    "placetype": [
      "aat:300008791"
    ],
    "id": 2173883,
    "name:xx": "Bird Island"
  }
}
