{
  "type": "FeatureCollection",
  "features": [
    {
      "geometry": {
        "type": "Point",
        "coordinates": [
          72.5,
          43.6667
        ]
      },
      "type": "Feature",
      "properties": {
        "hierarchy": [
          "tgn:1103410",
          "tgn:1000004",
          "tgn:1003362",
          "tgn:7014786",
          "tgn:7029392"
        ],
        "placetype": [
          "aat:300008916"
        ],
        "id": 1103410,
        "name:xx": "Muyunkum, Peski"
      }
    },
    {
      "geometry": {
        "type": "Point",
        "coordinates": [
          57.7333,
          34.75
        ]
      },
      "type": "Feature",
      "properties": {
        "hierarchy": [
          "tgn:1103411",
          "tgn:1000004",
          "tgn:7016768",
          "tgn:7000231",
          "tgn:7029392"
        ],
        "placetype": [
          "aat:300008916"
        ],
        "id": 1103411,
        "name:xx": "Namak, Kavīr-e"
      }
    },
    {
      "geometry": {
        "type": "Point",
        "coordinates": [
          12,
          -18
        ]
      },
      "type": "Feature",
      "properties": {
        "hierarchy": [
          "tgn:1103412",
          "tgn:7001242",
          "tgn:1000198",
          "tgn:7029392"
        ],
        "placetype": [
          "aat:300008916"
        ],
        "id": 1103412,
        "name:xx": "Namib Desert"
      }
    },
    {
      "geometry": {
        "type": "Point",
        "coordinates": [
          33,
          20.5
        ]
      },
      "type": "Feature",
      "properties": {
        "hierarchy": [
          "tgn:1103413",
          "tgn:7001242",
          "tgn:1000201",
          "tgn:1001097",
          "tgn:7029392"
        ],
        "placetype": [
          "aat:300008916"
        ],
        "id": 1103413,
        "name:xx": "Nubian Desert"
      }
    },
    {
      "geometry": {
        "type": "Point",
        "coordinates": [
          63.5,
          47
        ]
      },
      "type": "Feature",
      "properties": {
        "hierarchy": [
          "tgn:1103415",
          "tgn:1000004",
          "tgn:7014786",
          "tgn:7029392"
        ],
        "placetype": [
          "aat:300008916"
        ],
        "id": 1103415,
        "name:xx": "Priaralskiye Karakumy, Peski"
      }
    },
    {
      "geometry": {
        "type": "Point",
        "coordinates": [
          21,
          24.5
        ]
      },
      "type": "Feature",
      "properties": {
        "hierarchy": [
          "tgn:1103416",
          "tgn:7001242",
          "tgn:7000604",
          "tgn:1000172",
          "tgn:7029392"
        ],
        "placetype": [
          "aat:300008916"
        ],
        "id": 1103416,
        "name:xx": "Rabyānah, Ramlat"
      }
    },
    {
      "geometry": {
        "type": "Point",
        "coordinates": [
          2.75,
          29.25
        ]
      },
      "type": "Feature",
      "properties": {
        "hierarchy": [
          "tgn:1103417",
          "tgn:7001242",
          "tgn:1000519",
          "tgn:7016752",
          "tgn:7029392"
        ],
        "placetype": [
          "aat:300008916"
        ],
        "id": 1103417,
        "name:xx": "Raoui, 'Erg er"
      }
    },
    {
      "geometry": {
        "type": "Point",
        "coordinates": [
          49,
          48.4167
        ]
      },
      "type": "Feature",
      "properties": {
        "hierarchy": [
          "tgn:1103418",
          "tgn:1000004",
          "tgn:7014786",
          "tgn:7029392"
        ],
        "placetype": [
          "aat:300008916"
        ],
        "id": 1103418,
        "name:xx": "Ryn Peski"
      }
    }
  ]
}
