{
  "geometry": {
    "type": "Point",
    "coordinates": [
      74.35,
      33.225
    ]
  },
  "type": "Feature",
  "properties": {
    "hierarchy": [
      "tgn:7589416",
      "tgn:1000004",
      "tgn:7000198",
      "tgn:7000799",
      "tgn:7029392"
    ],
    "placetype": [
      "aat:300008347"
    ],
    "name:en": "Kākadan",
    "id": 7589416
  }
}
