{
  "geometry": {
    "type": "Point",
    "coordinates": [
      -80.6667,
      28.3333
    ]
  },
  "type": "Feature",
  "properties": {
    "hierarchy": [
      "tgn:2600662",
      "tgn:1000001",
      "tgn:1002200",
      "tgn:7012149",
      "tgn:7007240",
      "tgn:7029392"
    ],
    "placetype": [
      "aat:300008850"
    ],
    "id": 2600662,
    "name:xx": "Pullman Point"
  }
}
