{
  "geometry": {
    "type": "Point",
    "coordinates": [
      -83.0667,
      37.3667
    ]
  },
  "type": "Feature",
  "properties": {
    "hierarchy": [
      "tgn:2037642",
      "tgn:1000001",
      "tgn:7012149",
      "tgn:2000806",
      "tgn:7007255",
      "tgn:7029392"
    ],
    "placetype": [
      "aat:300008347"
    ],
    "id": 2037642,
    "name:xx": "Bearville"
  }
}
