{
  "geometry": {
    "type": "Point",
    "coordinates": [
      -118.8167,
      34.0833
    ]
  },
  "type": "Feature",
  "properties": {
    "hierarchy": [
      "tgn:2636197",
      "tgn:1000001",
      "tgn:7012149",
      "tgn:7007157",
      "tgn:1002608",
      "tgn:7029392"
    ],
    "placetype": [
      "aat:300008798"
    ],
    "id": 2636197,
    "name:xx": "Saddle Rock"
  }
}
