{
  "geometry": {
    "type": "Point",
    "coordinates": [
      79.460868,
      26.171249
    ]
  },
  "type": "Feature",
  "properties": {
    "hierarchy": [
      "tgn:7544857",
      "tgn:1000004",
      "tgn:7000198",
      "tgn:7016722",
      "tgn:7029392"
    ],
    "placetype": [
      "aat:300008347"
    ],
    "name:en": "Bābai",
    "id": 7544857
  }
}
