{
  "geometry": {
    "type": "Point",
    "coordinates": [
      -93.6833,
      42.7833
    ]
  },
  "type": "Feature",
  "properties": {
    "hierarchy": [
      "tgn:2257056",
      "tgn:1000001",
      "tgn:7012149",
      "tgn:2000659",
      "tgn:7007253",
      "tgn:7029392"
    ],
    "placetype": [
      "aat:300008680"
    ],
    "id": 2257056,
    "name:xx": "Cornelia, Lake"
  }
}
