{
  "geometry": {
    "type": "Point",
    "coordinates": [
      24.5667,
      -31.8667
    ]
  },
  "type": "Feature",
  "properties": {
    "hierarchy": [
      "tgn:1093434",
      "tgn:7001242",
      "tgn:7017583",
      "tgn:1000193",
      "tgn:7029392"
    ],
    "placetype": [
      "aat:300008347"
    ],
    "id": 1093434,
    "name:xx": "Nieu Bethesda"
  }
}
