{
  "geometry": {
    "type": "Point",
    "coordinates": [
      -115.6667,
      47.55
    ]
  },
  "type": "Feature",
  "properties": {
    "hierarchy": [
      "tgn:2351936",
      "tgn:1000001",
      "tgn:7012149",
      "tgn:2001304",
      "tgn:7007524",
      "tgn:7029392"
    ],
    "placetype": [
      "aat:300266640"
    ],
    "id": 2351936,
    "name:xx": "Glidden Ridge"
  }
}
