{
  "type": "FeatureCollection",
  "features": [
    {
      "geometry": {
        "type": "Point",
        "coordinates": [
          -75.9833,
          39.4167
        ]
      },
      "type": "Feature",
      "properties": {
        "hierarchy": [
          "tgn:2049150",
          "tgn:1002247",
          "tgn:1000001",
          "tgn:7012149",
          "tgn:7007516",
          "tgn:7029392"
        ],
        "placetype": [
          "aat:300008347"
        ],
        "id": 2049150,
        "name:xx": "West View Shores"
      }
    },
    {
      "geometry": {
        "type": "Point",
        "coordinates": [
          -79.2,
          39.4167
        ]
      },
      "type": "Feature",
      "properties": {
        "hierarchy": [
          "tgn:2049151",
          "tgn:1000001",
          "tgn:2000935",
          "tgn:7012149",
          "tgn:7007516",
          "tgn:7029392"
        ],
        "placetype": [
          "aat:300008347",
          "aat:300387210"
        ],
        "id": 2049151,
        "name:xx": "West Vindex"
      }
    },
    {
      "geometry": {
        "type": "Point",
        "coordinates": [
          -76.7333,
          38.65
        ]
      },
      "type": "Feature",
      "properties": {
        "hierarchy": [
          "tgn:2049152",
          "tgn:1000001",
          "tgn:2124001",
          "tgn:7012149",
          "tgn:7007516",
          "tgn:7029392"
        ],
        "placetype": [
          "aat:300008347"
        ],
        "id": 2049152,
        "name:xx": "Westwood"
      }
    },
    {
      "geometry": {
        "type": "Point",
        "coordinates": [
          -75.8333,
          38.3333
        ]
      },
      "type": "Feature",
      "properties": {
        "hierarchy": [
          "tgn:2049154",
          "tgn:1000001",
          "tgn:1003023",
          "tgn:7012149",
          "tgn:7007516",
          "tgn:7029392"
        ],
        "placetype": [
          "aat:300008347"
        ],
        "id": 2049154,
        "name:xx": "Wetipquin"
      }
    },
    {
      "geometry": {
        "type": "Point",
        "coordinates": [
          -75.3,
          38.3833
        ]
      },
      "type": "Feature",
      "properties": {
        "hierarchy": [
          "tgn:2049157",
          "tgn:1000001",
          "tgn:1003037",
          "tgn:7012149",
          "tgn:7007516",
          "tgn:7029392"
        ],
        "placetype": [
          "aat:300008347"
        ],
        "id": 2049157,
        "name:xx": "Whaleysville"
      }
    },
    {
      "geometry": {
        "type": "Point",
        "coordinates": [
          -77.05,
          39.0333
        ]
      },
      "type": "Feature",
      "properties": {
        "hierarchy": [
          "tgn:2049158",
          "tgn:1000001",
          "tgn:7016104",
          "tgn:7012149",
          "tgn:7007516",
          "tgn:7029392"
        ],
        "placetype": [
          "aat:300008347"
        ],
        "id": 2049158,
        "name:xx": "Wheaton"
      }
    }
  ]
}
