{
  "geometry": {
    "type": "Point",
    "coordinates": [
      13.05,
      48.85
    ]
  },
  "type": "Feature",
  "properties": {
    "hierarchy": [
      "tgn:7199762",
      "tgn:7003669",
      "tgn:1000003",
      "tgn:7000084",
      "tgn:7029392"
    ],
    "placetype": [
      "aat:300000206"
    ],
    "id": 7199762,
    "name:xx": "Edhof"
  }
}
