{
  "geometry": {
    "type": "Point",
    "coordinates": [
      73.293785,
      26.593128
    ]
  },
  "type": "Feature",
  "properties": {
    "hierarchy": [
      "tgn:7550717",
      "tgn:1000004",
      "tgn:7000198",
      "tgn:7016788",
      "tgn:7029392"
    ],
    "placetype": [
      "aat:300008347"
    ],
    "name:en": "Bīrāi",
    "id": 7550717
  }
}
