{
  "geometry": {
    "type": "Point",
    "coordinates": [
      31.169799,
      28.55628
    ]
  },
  "type": "Feature",
  "properties": {
    "hierarchy": [
      "tgn:7529122",
      "tgn:7001242",
      "tgn:7001311",
      "tgn:7016833",
      "tgn:7029392"
    ],
    "placetype": [
      "aat:300379998"
    ],
    "name:en": "Umm Rutaymah, Wādī",
    "id": 7529122
  }
}
