{
  "geometry": {
    "type": "Point",
    "coordinates": [
      -90.55,
      35.6833
    ]
  },
  "type": "Feature",
  "properties": {
    "hierarchy": [
      "tgn:2551456",
      "tgn:1000001",
      "tgn:7016172",
      "tgn:7012149",
      "tgn:2000160",
      "tgn:7029392"
    ],
    "placetype": [
      "aat:300006075"
    ],
    "id": 2551456,
    "name:xx": "Number 14, Ditch"
  }
}
