{
  "geometry": {
    "type": "Point",
    "coordinates": [
      115.0667,
      -1.9833
    ]
  },
  "type": "Feature",
  "properties": {
    "hierarchy": [
      "tgn:1077624",
      "tgn:1000004",
      "tgn:1001338",
      "tgn:1000116",
      "tgn:7029392"
    ],
    "placetype": [
      "aat:300008347"
    ],
    "id": 1077624,
    "name:xx": "Dayu"
  }
}
