{
  "geometry": {
    "type": "Point",
    "coordinates": [
      -58.3167,
      -3.1167
    ]
  },
  "type": "Feature",
  "properties": {
    "hierarchy": [
      "tgn:1009107",
      "tgn:7006247",
      "tgn:1000047",
      "tgn:7002456",
      "tgn:1000002",
      "tgn:7029392"
    ],
    "placetype": [
      "aat:300008791"
    ],
    "id": 1009107,
    "name:xx": "Serpa, Ilha da"
  }
}
