{
  "type": "FeatureCollection",
  "features": [
    {
      "geometry": {
        "type": "Point",
        "coordinates": [
          -91.45,
          17.333333
        ]
      },
      "type": "Feature",
      "properties": {
        "hierarchy": [
          "tgn:7433190",
          "tgn:7005580",
          "tgn:1000001",
          "tgn:7005560",
          "tgn:7029392"
        ],
        "placetype": [
          "aat:300008347"
        ],
        "id": 7433190,
        "name:xx": "Victorico Grajales"
      }
    },
    {
      "geometry": {
        "type": "Point",
        "coordinates": [
          -99.033333,
          26.35
        ]
      },
      "type": "Feature",
      "properties": {
        "hierarchy": [
          "tgn:7433191",
          "tgn:1000001",
          "tgn:7005597",
          "tgn:7005560",
          "tgn:7029392"
        ],
        "placetype": [
          "aat:300008347"
        ],
        "id": 7433191,
        "name:xx": "Victoriano"
      }
    },
    {
      "geometry": {
        "type": "Point",
        "coordinates": [
          -112.103333,
          31.001111
        ]
      },
      "type": "Feature",
      "properties": {
        "hierarchy": [
          "tgn:7433192",
          "tgn:1000001",
          "tgn:1001960",
          "tgn:7005560",
          "tgn:7029392"
        ],
        "placetype": [
          "aat:300008347"
        ],
        "id": 7433192,
        "name:xx": "Victoria"
      }
    },
    {
      "geometry": {
        "type": "Point",
        "coordinates": [
          -107.233333,
          30.083333
        ]
      },
      "type": "Feature",
      "properties": {
        "hierarchy": [
          "tgn:7433193",
          "tgn:7005581",
          "tgn:1000001",
          "tgn:7005560",
          "tgn:7029392"
        ],
        "placetype": [
          "aat:300008680"
        ],
        "id": 7433193,
        "name:xx": "Victoria, Laguna de"
      }
    },
    {
      "geometry": {
        "type": "Point",
        "coordinates": [
          -115.106944,
          32.284722
        ]
      },
      "type": "Feature",
      "properties": {
        "hierarchy": [
          "tgn:7433194",
          "tgn:1001835",
          "tgn:1000001",
          "tgn:7005560",
          "tgn:7029392"
        ],
        "placetype": [
          "aat:300007783"
        ],
        "id": 7433194,
        "name:xx": "Estación Victoria"
      }
    },
    {
      "geometry": {
        "type": "Point",
        "coordinates": [
          -106.383333,
          28.95
        ]
      },
      "type": "Feature",
      "properties": {
        "hierarchy": [
          "tgn:7433195",
          "tgn:7005581",
          "tgn:1000001",
          "tgn:7005560",
          "tgn:7029392"
        ],
        "placetype": [
          "aat:300008795"
        ],
        "id": 7433195,
        "name:xx": "Victoria, Cerro"
      }
    },
    {
      "geometry": {
        "type": "Point",
        "coordinates": [
          -106.483333,
          28.916667
        ]
      },
      "type": "Feature",
      "properties": {
        "hierarchy": [
          "tgn:7433196",
          "tgn:7005581",
          "tgn:1000001",
          "tgn:7005560",
          "tgn:7029392"
        ],
        "placetype": [
          "aat:300008795"
        ],
        "id": 7433196,
        "name:xx": "Victoria, Cerro"
      }
    },
    {
      "geometry": {
        "type": "Point",
        "coordinates": [
          -100.766667,
          28.95
        ]
      },
      "type": "Feature",
      "properties": {
        "hierarchy": [
          "tgn:7433197",
          "tgn:1001853",
          "tgn:1000001",
          "tgn:7005560",
          "tgn:7029392"
        ],
        "placetype": [
          "aat:300008347"
        ],
        "id": 7433197,
        "name:xx": "Victoria"
      }
    },
    {
      "geometry": {
        "type": "Point",
        "coordinates": [
          -104.266667,
          28.033333
        ]
      },
      "type": "Feature",
      "properties": {
        "hierarchy": [
          "tgn:7433198",
          "tgn:7005581",
          "tgn:1000001",
          "tgn:7005560",
          "tgn:7029392"
        ],
        "placetype": [
          "aat:300008347"
        ],
        "id": 7433198,
        "name:xx": "Victoria"
      }
    },
    {
      "geometry": {
        "type": "Point",
        "coordinates": [
          -99.95,
          25.75
        ]
      },
      "type": "Feature",
      "properties": {
        "hierarchy": [
          "tgn:7433199",
          "tgn:1000001",
          "tgn:7005589",
          "tgn:7005560",
          "tgn:7029392"
        ],
        "placetype": [
          "aat:300008347"
        ],
        "id": 7433199,
        "name:xx": "Victoria"
      }
    }
  ]
}
