{
  "geometry": {
    "type": "Point",
    "coordinates": [
      -122.3833,
      48.8833
    ]
  },
  "type": "Feature",
  "properties": {
    "hierarchy": [
      "tgn:2336953",
      "tgn:1000001",
      "tgn:7012149",
      "tgn:1003020",
      "tgn:7007920",
      "tgn:7029392"
    ],
    "placetype": [
      "aat:300008706"
    ],
    "id": 2336953,
    "name:xx": "Fourmile Creek"
  }
}
