{
  "geometry": {
    "type": "Point",
    "coordinates": [
      -96.3667,
      39.0333
    ]
  },
  "type": "Feature",
  "properties": {
    "hierarchy": [
      "tgn:2578714",
      "tgn:1000001",
      "tgn:7012149",
      "tgn:2000758",
      "tgn:7007254",
      "tgn:7029392"
    ],
    "placetype": [
      "aat:300008706"
    ],
    "id": 2578714,
    "name:xx": "Phillips Creek"
  }
}
