{
  "geometry": {
    "type": "Point",
    "coordinates": [
      14.0167,
      -12.9667
    ]
  },
  "type": "Feature",
  "properties": {
    "hierarchy": [
      "tgn:1087665",
      "tgn:1000812",
      "tgn:7001242",
      "tgn:1000149",
      "tgn:7029392"
    ],
    "placetype": [
      "aat:300008347"
    ],
    "id": 1087665,
    "name:xx": "Caimbambo"
  }
}
