{
  "geometry": {
    "type": "Point",
    "coordinates": [
      -116.6833,
      33.45
    ]
  },
  "type": "Feature",
  "properties": {
    "hierarchy": [
      "tgn:2710327",
      "tgn:1000001",
      "tgn:7012149",
      "tgn:7007157",
      "tgn:7029392"
    ],
    "placetype": [
      "aat:300008761"
    ],
    "id": 2710327,
    "name:xx": "Talmadge Canyon"
  }
}
