{
  "geometry": {
    "type": "Point",
    "coordinates": [
      88.359,
      22.504
    ]
  },
  "type": "Feature",
  "properties": {
    "hierarchy": [
      "tgn:1005741",
      "tgn:1000004",
      "tgn:7000198",
      "tgn:1001977",
      "tgn:7030776",
      "tgn:7029392"
    ],
    "placetype": [
      "aat:300008347",
      "aat:300000745"
    ],
    "name:en": "Taliganja",
    "id": 1005741
  }
}
