{
  "geometry": {
    "type": "Point",
    "coordinates": [
      -83.2667,
      35.2667
    ]
  },
  "type": "Feature",
  "properties": {
    "hierarchy": [
      "tgn:2167355",
      "tgn:1000001",
      "tgn:7012149",
      "tgn:2001508",
      "tgn:7007709",
      "tgn:7029392"
    ],
    "placetype": [
      "aat:300008761"
    ],
    "id": 2167355,
    "name:xx": "Big Cove"
  }
}
