{
  "type": "FeatureCollection",
  "features": [
    {
      "geometry": {
        "type": "Point",
        "coordinates": [
          -88.1167,
          30.7
        ]
      },
      "type": "Feature",
      "properties": {
        "hierarchy": [
          "tgn:2582430",
          "tgn:7002659",
          "tgn:1000001",
          "tgn:7012149",
          "tgn:2000048",
          "tgn:7029392"
        ],
        "placetype": [
          "aat:300008347"
        ],
        "id": 2582430,
        "name:xx": "Pine Grove"
      }
    },
    {
      "geometry": {
        "type": "Point",
        "coordinates": [
          -88.2167,
          33.3333
        ]
      },
      "type": "Feature",
      "properties": {
        "hierarchy": [
          "tgn:2582431",
          "tgn:7002659",
          "tgn:1000001",
          "tgn:7012149",
          "tgn:2000053",
          "tgn:7029392"
        ],
        "placetype": [
          "aat:300008347"
        ],
        "id": 2582431,
        "name:xx": "Pine Grove"
      }
    },
    {
      "geometry": {
        "type": "Point",
        "coordinates": [
          -86.25,
          34.0833
        ]
      },
      "type": "Feature",
      "properties": {
        "hierarchy": [
          "tgn:2582432",
          "tgn:7002659",
          "tgn:1000001",
          "tgn:7012149",
          "tgn:2000027",
          "tgn:7029392"
        ],
        "placetype": [
          "aat:300008347"
        ],
        "id": 2582432,
        "name:xx": "Pine Grove"
      }
    },
    {
      "geometry": {
        "type": "Point",
        "coordinates": [
          -94.1,
          34.6
        ]
      },
      "type": "Feature",
      "properties": {
        "hierarchy": [
          "tgn:2582433",
          "tgn:1000001",
          "tgn:7016172",
          "tgn:7012149",
          "tgn:2000161",
          "tgn:7029392"
        ],
        "placetype": [
          "aat:300008347"
        ],
        "id": 2582433,
        "name:xx": "Pine Grove"
      }
    },
    {
      "geometry": {
        "type": "Point",
        "coordinates": [
          -116.7,
          32.9333
        ]
      },
      "type": "Feature",
      "properties": {
        "hierarchy": [
          "tgn:2582434",
          "tgn:1000001",
          "tgn:7012149",
          "tgn:7007157",
          "tgn:1002858",
          "tgn:7029392"
        ],
        "placetype": [
          "aat:300008347"
        ],
        "id": 2582434,
        "name:xx": "Pine Grove"
      }
    },
    {
      "geometry": {
        "type": "Point",
        "coordinates": [
          -75.1167,
          38.5333
        ]
      },
      "type": "Feature",
      "properties": {
        "hierarchy": [
          "tgn:2582435",
          "tgn:1002933",
          "tgn:1000001",
          "tgn:7012149",
          "tgn:7007239",
          "tgn:7029392"
        ],
        "placetype": [
          "aat:300008347"
        ],
        "id": 2582435,
        "name:xx": "Pine Grove"
      }
    },
    {
      "geometry": {
        "type": "Point",
        "coordinates": [
          -111.85,
          42.9
        ]
      },
      "type": "Feature",
      "properties": {
        "hierarchy": [
          "tgn:2582436",
          "tgn:1000001",
          "tgn:2000466",
          "tgn:7012149",
          "tgn:7007250",
          "tgn:7029392"
        ],
        "placetype": [
          "aat:300132451"
        ],
        "id": 2582436,
        "name:xx": "Pine Grove"
      }
    },
    {
      "geometry": {
        "type": "Point",
        "coordinates": [
          -93.05,
          32.2
        ]
      },
      "type": "Feature",
      "properties": {
        "hierarchy": [
          "tgn:2582437",
          "tgn:1000001",
          "tgn:2000860",
          "tgn:7012149",
          "tgn:7007256",
          "tgn:7029392"
        ],
        "placetype": [
          "aat:300008347"
        ],
        "id": 2582437,
        "name:xx": "Pine Grove"
      }
    },
    {
      "geometry": {
        "type": "Point",
        "coordinates": [
          -70.9167,
          42.15
        ]
      },
      "type": "Feature",
      "properties": {
        "hierarchy": [
          "tgn:2582438",
          "tgn:1000001",
          "tgn:1002724",
          "tgn:7012149",
          "tgn:7007517",
          "tgn:7029392"
        ],
        "placetype": [
          "aat:300008347"
        ],
        "id": 2582438,
        "name:xx": "Pine Grove"
      }
    },
    {
      "geometry": {
        "type": "Point",
        "coordinates": [
          -89.1667,
          31.2667
        ]
      },
      "type": "Feature",
      "properties": {
        "hierarchy": [
          "tgn:2582439",
          "tgn:1000001",
          "tgn:7012149",
          "tgn:2001103",
          "tgn:7007522",
          "tgn:7029392"
        ],
        "placetype": [
          "aat:300008347"
        ],
        "id": 2582439,
        "name:xx": "Pine Grove"
      }
    }
  ]
}
