{
  "geometry": {
    "type": "Point",
    "coordinates": [
      79.127922,
      24.736714
    ]
  },
  "type": "Feature",
  "properties": {
    "hierarchy": [
      "tgn:7565533",
      "tgn:1000004",
      "tgn:7000198",
      "tgn:1001894",
      "tgn:7029392"
    ],
    "placetype": [
      "aat:300008795"
    ],
    "name:en": "Ghurājan Pahār",
    "id": 7565533
  }
}
