{
  "geometry": {
    "type": "Point",
    "coordinates": [
      -89.2833,
      38.95
    ]
  },
  "type": "Feature",
  "properties": {
    "hierarchy": [
      "tgn:2563296",
      "tgn:1000001",
      "tgn:7012149",
      "tgn:7007251",
      "tgn:7029392"
    ],
    "placetype": [
      "aat:300008706"
    ],
    "id": 2563296,
    "name:xx": "Owl Creek"
  }
}
