{
  "geometry": {
    "type": "Point",
    "coordinates": [
      33.65,
      -14.85
    ]
  },
  "type": "Feature",
  "properties": {
    "hierarchy": [
      "tgn:1091527",
      "tgn:7001242",
      "tgn:1000940",
      "tgn:1000180",
      "tgn:7029392"
    ],
    "placetype": [
      "aat:300008347"
    ],
    "id": 1091527,
    "name:xx": "Furancungo"
  }
}
