{
  "type": "FeatureCollection",
  "features": [
    {
      "geometry": {
        "type": "Point",
        "coordinates": [
          -6.25,
          54.566667
        ]
      },
      "type": "Feature",
      "properties": {
        "hierarchy": [
          "tgn:7466840",
          "tgn:7002448",
          "tgn:7019187",
          "tgn:1000003",
          "tgn:7008591",
          "tgn:7029392"
        ],
        "placetype": [
          "aat:300008347"
        ],
        "name:en": "Ballymacrevan",
        "id": 7466840
      }
    },
    {
      "geometry": {
        "type": "Point",
        "coordinates": [
          -6.516667,
          54.966667
        ]
      },
      "type": "Feature",
      "properties": {
        "hierarchy": [
          "tgn:7466841",
          "tgn:7019163",
          "tgn:7002448",
          "tgn:1000003",
          "tgn:7008591",
          "tgn:7029392"
        ],
        "placetype": [
          "aat:300008347"
        ],
        "name:en": "Ballymaconnelly",
        "id": 7466841
      }
    },
    {
      "geometry": {
        "type": "Point",
        "coordinates": [
          -5.9,
          54.6
        ]
      },
      "type": "Feature",
      "properties": {
        "hierarchy": [
          "tgn:7466842",
          "tgn:7002448",
          "tgn:7019168",
          "tgn:1000003",
          "tgn:7008591",
          "tgn:7029392"
        ],
        "placetype": [
          "aat:300008347"
        ],
        "name:en": "Ballymacarret",
        "id": 7466842
      }
    },
    {
      "geometry": {
        "type": "Point",
        "coordinates": [
          -5.783333,
          54.833333
        ]
      },
      "type": "Feature",
      "properties": {
        "hierarchy": [
          "tgn:7466843",
          "tgn:7002448",
          "tgn:7019159",
          "tgn:1000003",
          "tgn:7008591",
          "tgn:7029392"
        ],
        "placetype": [
          "aat:300008347"
        ],
        "name:en": "Ballylumford",
        "id": 7466843
      }
    },
    {
      "geometry": {
        "type": "Point",
        "coordinates": [
          -6.5,
          55.166667
        ]
      },
      "type": "Feature",
      "properties": {
        "hierarchy": [
          "tgn:7466844",
          "tgn:7002448",
          "tgn:7019157",
          "tgn:1000003",
          "tgn:7008591",
          "tgn:7029392"
        ],
        "placetype": [
          "aat:300387502"
        ],
        "name:en": "Ballylough House",
        "id": 7466844
      }
    },
    {
      "geometry": {
        "type": "Point",
        "coordinates": [
          -5.8,
          54.25
        ]
      },
      "type": "Feature",
      "properties": {
        "hierarchy": [
          "tgn:7466845",
          "tgn:7002448",
          "tgn:7008698",
          "tgn:1000003",
          "tgn:7008591",
          "tgn:7029392"
        ],
        "placetype": [
          "aat:300008347"
        ],
        "name:en": "Ballykinler",
        "id": 7466845
      }
    },
    {
      "geometry": {
        "type": "Point",
        "coordinates": [
          -7.016667,
          55.05
        ]
      },
      "type": "Feature",
      "properties": {
        "hierarchy": [
          "tgn:7466846",
          "tgn:7002448",
          "tgn:7019215",
          "tgn:1000003",
          "tgn:7008591",
          "tgn:7029392"
        ],
        "placetype": [
          "aat:300008347"
        ],
        "name:en": "Ballykelly",
        "id": 7466846
      }
    },
    {
      "geometry": {
        "type": "Point",
        "coordinates": [
          -5.55,
          54.3
        ]
      },
      "type": "Feature",
      "properties": {
        "hierarchy": [
          "tgn:7466847",
          "tgn:7002448",
          "tgn:7008698",
          "tgn:1000003",
          "tgn:7008591",
          "tgn:7029392"
        ],
        "placetype": [
          "aat:300132316"
        ],
        "name:en": "Ballyhornan Bay",
        "id": 7466847
      }
    },
    {
      "geometry": {
        "type": "Point",
        "coordinates": [
          -5.55,
          54.3
        ]
      },
      "type": "Feature",
      "properties": {
        "hierarchy": [
          "tgn:7466848",
          "tgn:7002448",
          "tgn:7008698",
          "tgn:1000003",
          "tgn:7008591",
          "tgn:7029392"
        ],
        "placetype": [
          "aat:300008347"
        ],
        "name:en": "Ballyhornan",
        "id": 7466848
      }
    }
  ]
}
