{
  "geometry": {
    "type": "Point",
    "coordinates": [
      -108.8167,
      32.9167
    ]
  },
  "type": "Feature",
  "properties": {
    "hierarchy": [
      "tgn:2693126",
      "tgn:1000001",
      "tgn:7012149",
      "tgn:2001437",
      "tgn:7007566",
      "tgn:7029392"
    ],
    "placetype": [
      "aat:300006191"
    ],
    "id": 2693126,
    "name:xx": "Steep Hollow Tank"
  }
}
