{
  "geometry": {
    "type": "Point",
    "coordinates": [
      -109.0833,
      33.0167
    ]
  },
  "type": "Feature",
  "properties": {
    "hierarchy": [
      "tgn:2212704",
      "tgn:1000001",
      "tgn:7006451",
      "tgn:2000095",
      "tgn:7012149",
      "tgn:7029392"
    ],
    "placetype": [
      "aat:300008706"
    ],
    "id": 2212704,
    "name:xx": "C A Bar Creek"
  }
}
