{
  "geometry": {
    "type": "Point",
    "coordinates": [
      -162.8167,
      68.0167
    ]
  },
  "type": "Feature",
  "properties": {
    "hierarchy": [
      "tgn:2135526",
      "tgn:7006450",
      "tgn:1000001",
      "tgn:7012149",
      "tgn:2124005",
      "tgn:7029392"
    ],
    "placetype": [
      "aat:300266640"
    ],
    "id": 2135526,
    "name:xx": "Anxiety Ridge"
  }
}
