{
  "geometry": {
    "type": "Point",
    "coordinates": [
      -119.25,
      47.8833
    ]
  },
  "type": "Feature",
  "properties": {
    "hierarchy": [
      "tgn:2307842",
      "tgn:1000001",
      "tgn:2002242",
      "tgn:7012149",
      "tgn:7007920",
      "tgn:7029392"
    ],
    "placetype": [
      "aat:300008706"
    ],
    "id": 2307842,
    "name:xx": "East Foster Creek"
  }
}
