{
  "geometry": {
    "type": "Point",
    "coordinates": [
      31.833,
      41.25
    ]
  },
  "type": "Feature",
  "properties": {
    "hierarchy": [
      "tgn:1001616",
      "tgn:1000004",
      "tgn:7018454",
      "tgn:1000144",
      "tgn:7029392"
    ],
    "placetype": [
      "aat:300387064",
      "aat:300000774"
    ],
    "id": 1001616,
    "name:xx": "Zonguldak"
  }
}
