{
  "geometry": {
    "type": "Point",
    "coordinates": [
      22.816667,
      38.533333
    ]
  },
  "type": "Feature",
  "properties": {
    "hierarchy": [
      "tgn:7234185",
      "tgn:7002741",
      "tgn:7017076",
      "tgn:1000003",
      "tgn:1000074",
      "tgn:7029392"
    ],
    "placetype": [
      "aat:300007783"
    ],
    "id": 7234185,
    "name:xx": "Sidhirodhromikós Stathmós Dhavlías"
  }
}
