{
  "geometry": {
    "type": "Point",
    "coordinates": [
      -83.4667,
      40.1833
    ]
  },
  "type": "Feature",
  "properties": {
    "hierarchy": [
      "tgn:2265565",
      "tgn:1000001",
      "tgn:7012149",
      "tgn:1002964",
      "tgn:7007706",
      "tgn:7029392"
    ],
    "placetype": [
      "aat:300008905"
    ],
    "id": 2265565,
    "name:xx": "Crane Swamp"
  }
}
