{
  "geometry": {
    "type": "Point",
    "coordinates": [
      -121.2167,
      36.8167
    ]
  },
  "type": "Feature",
  "properties": {
    "hierarchy": [
      "tgn:2239725",
      "tgn:1000001",
      "tgn:7012149",
      "tgn:7007157",
      "tgn:1002856",
      "tgn:7029392"
    ],
    "placetype": [
      "aat:300008798"
    ],
    "id": 2239725,
    "name:xx": "Cibo Peak"
  }
}
