{
  "geometry": {
    "type": "Point",
    "coordinates": [
      1.847,
      9.166
    ]
  },
  "type": "Feature",
  "properties": {
    "hierarchy": [
      "tgn:7032094",
      "tgn:7001242",
      "tgn:1000160",
      "tgn:7029392"
    ],
    "placetype": [
      "aat:300387064",
      "aat:300000772"
    ],
    "id": 7032094,
    "name:xx": "Donga"
  }
}
