{
  "geometry": {
    "type": "Point",
    "coordinates": [
      6.4333,
      44.4167
    ]
  },
  "type": "Feature",
  "properties": {
    "hierarchy": [
      "tgn:1033878",
      "tgn:1000003",
      "tgn:1000070",
      "tgn:7002895",
      "tgn:7029392"
    ],
    "placetype": [
      "aat:300008347"
    ],
    "id": 1033878,
    "name:xx": "Lauzet-Ubaye"
  }
}
