{
  "geometry": {
    "type": "Point",
    "coordinates": [
      -83.8167,
      41.4667
    ]
  },
  "type": "Feature",
  "properties": {
    "hierarchy": [
      "tgn:2378093",
      "tgn:1000001",
      "tgn:7012149",
      "tgn:7007706",
      "tgn:7029392"
    ],
    "placetype": [
      "aat:300006075"
    ],
    "id": 2378093,
    "name:xx": "Harris Ditch"
  }
}
