{
  "type": "FeatureCollection",
  "features": [
    {
      "geometry": {
        "type": "Point",
        "coordinates": [
          -86.05,
          37.2
        ]
      },
      "type": "Feature",
      "properties": {
        "hierarchy": [
          "tgn:2270180",
          "tgn:1000001",
          "tgn:7012149",
          "tgn:2000787",
          "tgn:7007255",
          "tgn:7029392"
        ],
        "placetype": [
          "aat:300008746"
        ],
        "id": 2270180,
        "name:xx": "Crystal Cave"
      }
    },
    {
      "geometry": {
        "type": "Point",
        "coordinates": [
          -93.25,
          37.3167
        ]
      },
      "type": "Feature",
      "properties": {
        "hierarchy": [
          "tgn:2270181",
          "tgn:1000001",
          "tgn:7012149",
          "tgn:2001199",
          "tgn:7007523",
          "tgn:7029392"
        ],
        "placetype": [
          "aat:300008746"
        ],
        "id": 2270181,
        "name:xx": "Crystal Cave"
      }
    },
    {
      "geometry": {
        "type": "Point",
        "coordinates": [
          -110.4167,
          45.3333
        ]
      },
      "type": "Feature",
      "properties": {
        "hierarchy": [
          "tgn:2270182",
          "tgn:1000001",
          "tgn:7012149",
          "tgn:2001293",
          "tgn:7007524",
          "tgn:7029392"
        ],
        "placetype": [
          "aat:300008746"
        ],
        "id": 2270182,
        "name:xx": "Crystal Cave"
      }
    },
    {
      "geometry": {
        "type": "Point",
        "coordinates": [
          -94.8,
          35.6167
        ]
      },
      "type": "Feature",
      "properties": {
        "hierarchy": [
          "tgn:2270183",
          "tgn:1000001",
          "tgn:7012149",
          "tgn:2001690",
          "tgn:7007707",
          "tgn:7029392"
        ],
        "placetype": [
          "aat:300008746"
        ],
        "id": 2270183,
        "name:xx": "Crystal Cave"
      }
    },
    {
      "geometry": {
        "type": "Point",
        "coordinates": [
          -103.3,
          43.95
        ]
      },
      "type": "Feature",
      "properties": {
        "hierarchy": [
          "tgn:2270184",
          "tgn:1000001",
          "tgn:7012149",
          "tgn:2001821",
          "tgn:7007713",
          "tgn:7029392"
        ],
        "placetype": [
          "aat:300008746"
        ],
        "id": 2270184,
        "name:xx": "Crystal Cave"
      }
    },
    {
      "geometry": {
        "type": "Point",
        "coordinates": [
          -85.4,
          35.0167
        ]
      },
      "type": "Feature",
      "properties": {
        "hierarchy": [
          "tgn:2270185",
          "tgn:1000001",
          "tgn:7012149",
          "tgn:2001869",
          "tgn:7007825",
          "tgn:7029392"
        ],
        "placetype": [
          "aat:300008746"
        ],
        "id": 2270185,
        "name:xx": "Crystal Cave"
      }
    },
    {
      "geometry": {
        "type": "Point",
        "coordinates": [
          -85.85,
          35.2667
        ]
      },
      "type": "Feature",
      "properties": {
        "hierarchy": [
          "tgn:2270186",
          "tgn:1000001",
          "tgn:7012149",
          "tgn:2001867",
          "tgn:7007825",
          "tgn:7029392"
        ],
        "placetype": [
          "aat:300008746"
        ],
        "id": 2270186,
        "name:xx": "Crystal Cave"
      }
    },
    {
      "geometry": {
        "type": "Point",
        "coordinates": [
          -114.0167,
          41.2833
        ]
      },
      "type": "Feature",
      "properties": {
        "hierarchy": [
          "tgn:2270187",
          "tgn:1000001",
          "tgn:2002102",
          "tgn:7012149",
          "tgn:7007827",
          "tgn:7029392"
        ],
        "placetype": [
          "aat:300008746"
        ],
        "id": 2270187,
        "name:xx": "Crystal Cave"
      }
    },
    {
      "geometry": {
        "type": "Point",
        "coordinates": [
          -92.25,
          44.8167
        ]
      },
      "type": "Feature",
      "properties": {
        "hierarchy": [
          "tgn:2270188",
          "tgn:1000001",
          "tgn:7012149",
          "tgn:2002345",
          "tgn:7007922",
          "tgn:7029392"
        ],
        "placetype": [
          "aat:300008746"
        ],
        "id": 2270188,
        "name:xx": "Crystal Cave"
      }
    },
    {
      "geometry": {
        "type": "Point",
        "coordinates": [
          -108.0167,
          45.1
        ]
      },
      "type": "Feature",
      "properties": {
        "hierarchy": [
          "tgn:2270189",
          "tgn:1000001",
          "tgn:2001261",
          "tgn:7012149",
          "tgn:7007524",
          "tgn:7029392"
        ],
        "placetype": [
          "aat:300008697"
        ],
        "id": 2270189,
        "name:xx": "Crystal Cave Spring"
      }
    }
  ]
}
