{
  "type": "FeatureCollection",
  "features": [
    {
      "geometry": {
        "type": "Point",
        "coordinates": [
          11.716667,
          53.9
        ]
      },
      "type": "Feature",
      "properties": {
        "hierarchy": [
          "tgn:7121830",
          "tgn:1000003",
          "tgn:7000094",
          "tgn:7000084",
          "tgn:7029392"
        ],
        "placetype": [
          "aat:300008347"
        ],
        "id": 7121830,
        "name:xx": "Pinnowhof"
      }
    },
    {
      "geometry": {
        "type": "Point",
        "coordinates": [
          13.133333,
          53.6
        ]
      },
      "type": "Feature",
      "properties": {
        "hierarchy": [
          "tgn:7121831",
          "tgn:1000003",
          "tgn:7000094",
          "tgn:7000084",
          "tgn:7029392"
        ],
        "placetype": [
          "aat:300008863"
        ],
        "id": 7121831,
        "name:xx": "Pinnower Wald"
      }
    },
    {
      "geometry": {
        "type": "Point",
        "coordinates": [
          11.533333,
          53.6
        ]
      },
      "type": "Feature",
      "properties": {
        "hierarchy": [
          "tgn:7121832",
          "tgn:1000003",
          "tgn:7000094",
          "tgn:7000084",
          "tgn:7029392"
        ],
        "placetype": [
          "aat:300008680"
        ],
        "id": 7121832,
        "name:xx": "Pinnower See"
      }
    },
    {
      "geometry": {
        "type": "Point",
        "coordinates": [
          13.8,
          53.216667
        ]
      },
      "type": "Feature",
      "properties": {
        "hierarchy": [
          "tgn:7121833",
          "tgn:7000096",
          "tgn:1000003",
          "tgn:7000084",
          "tgn:7029392"
        ],
        "placetype": [
          "aat:300008680"
        ],
        "id": 7121833,
        "name:xx": "Pinnower See"
      }
    },
    {
      "geometry": {
        "type": "Point",
        "coordinates": [
          13.25,
          52.716667
        ]
      },
      "type": "Feature",
      "properties": {
        "hierarchy": [
          "tgn:7121834",
          "tgn:7000096",
          "tgn:1000003",
          "tgn:7000084",
          "tgn:7029392"
        ],
        "placetype": [
          "aat:300008680"
        ],
        "id": 7121834,
        "name:xx": "Pinnower See"
      }
    },
    {
      "geometry": {
        "type": "Point",
        "coordinates": [
          14.533333,
          51.966667
        ]
      },
      "type": "Feature",
      "properties": {
        "hierarchy": [
          "tgn:7121835",
          "tgn:7000096",
          "tgn:1000003",
          "tgn:7000084",
          "tgn:7029392"
        ],
        "placetype": [
          "aat:300008680"
        ],
        "id": 7121835,
        "name:xx": "Pinnower See"
      }
    },
    {
      "geometry": {
        "type": "Point",
        "coordinates": [
          13.25,
          52.716667
        ]
      },
      "type": "Feature",
      "properties": {
        "hierarchy": [
          "tgn:7121836",
          "tgn:7000096",
          "tgn:1000003",
          "tgn:7000084",
          "tgn:7029392"
        ],
        "placetype": [
          "aat:300008347"
        ],
        "id": 7121836,
        "name:xx": "Pinnower Schleuse"
      }
    },
    {
      "geometry": {
        "type": "Point",
        "coordinates": [
          13.8,
          53.883333
        ]
      },
      "type": "Feature",
      "properties": {
        "hierarchy": [
          "tgn:7121837",
          "tgn:1000003",
          "tgn:7000094",
          "tgn:7000084",
          "tgn:7029392"
        ],
        "placetype": [
          "aat:300008863"
        ],
        "id": 7121837,
        "name:xx": "Pinnower Forst"
      }
    },
    {
      "geometry": {
        "type": "Point",
        "coordinates": [
          13.8,
          53.9
        ]
      },
      "type": "Feature",
      "properties": {
        "hierarchy": [
          "tgn:7121838",
          "tgn:1000003",
          "tgn:7000094",
          "tgn:7000084",
          "tgn:7029392"
        ],
        "placetype": [
          "aat:300008347"
        ],
        "id": 7121838,
        "name:xx": "Pinnow"
      }
    },
    {
      "geometry": {
        "type": "Point",
        "coordinates": [
          12.816667,
          53.666667
        ]
      },
      "type": "Feature",
      "properties": {
        "hierarchy": [
          "tgn:7121839",
          "tgn:1000003",
          "tgn:7000094",
          "tgn:7000084",
          "tgn:7029392"
        ],
        "placetype": [
          "aat:300008347"
        ],
        "id": 7121839,
        "name:xx": "Pinnow"
      }
    }
  ]
}
