{
  "geometry": {
    "type": "Point",
    "coordinates": [
      -84.5333,
      36.2333
    ]
  },
  "type": "Feature",
  "properties": {
    "hierarchy": [
      "tgn:2366405",
      "tgn:1000001",
      "tgn:7012149",
      "tgn:2001912",
      "tgn:7007825",
      "tgn:7029392"
    ],
    "placetype": [
      "aat:300008798"
    ],
    "id": 2366405,
    "name:xx": "Griffith Mountain"
  }
}
