{
  "geometry": {
    "type": "Point",
    "coordinates": [
      -83.1167,
      36.4833
    ]
  },
  "type": "Feature",
  "properties": {
    "hierarchy": [
      "tgn:2510270",
      "tgn:1000001",
      "tgn:7012149",
      "tgn:2001873",
      "tgn:7007825",
      "tgn:7029392"
    ],
    "placetype": [
      "aat:300266640"
    ],
    "id": 2510270,
    "name:xx": "Middle Ridge"
  }
}
