{
  "type": "FeatureCollection",
  "features": [
    {
      "geometry": {
        "type": "Point",
        "coordinates": [
          -117.9,
          35.8
        ]
      },
      "type": "Feature",
      "properties": {
        "hierarchy": [
          "tgn:2261260",
          "tgn:1000001",
          "tgn:7012149",
          "tgn:7007157",
          "tgn:7029392"
        ],
        "placetype": [
          "aat:300008761"
        ],
        "id": 2261260,
        "name:xx": "County Line Canyon"
      }
    },
    {
      "geometry": {
        "type": "Point",
        "coordinates": [
          -124.1667,
          42.8
        ]
      },
      "type": "Feature",
      "properties": {
        "hierarchy": [
          "tgn:2261261",
          "tgn:1000001",
          "tgn:2001704",
          "tgn:7012149",
          "tgn:7007708",
          "tgn:7029392"
        ],
        "placetype": [
          "aat:300008761"
        ],
        "id": 2261261,
        "name:xx": "County Line Canyon"
      }
    },
    {
      "geometry": {
        "type": "Point",
        "coordinates": [
          -86.8833,
          35.4833
        ]
      },
      "type": "Feature",
      "properties": {
        "hierarchy": [
          "tgn:2261262",
          "tgn:1000001",
          "tgn:7012149",
          "tgn:2001896",
          "tgn:7007825",
          "tgn:7029392"
        ],
        "placetype": [
          "aat:300008746"
        ],
        "id": 2261262,
        "name:xx": "County Line Cave"
      }
    },
    {
      "geometry": {
        "type": "Point",
        "coordinates": [
          -87.5333,
          32.25
        ]
      },
      "type": "Feature",
      "properties": {
        "hierarchy": [
          "tgn:2261263",
          "tgn:7002659",
          "tgn:1000001",
          "tgn:7012149",
          "tgn:7029392"
        ],
        "placetype": [
          "aat:300008706"
        ],
        "id": 2261263,
        "name:xx": "County Line Creek"
      }
    },
    {
      "geometry": {
        "type": "Point",
        "coordinates": [
          -123.5167,
          40.5
        ]
      },
      "type": "Feature",
      "properties": {
        "hierarchy": [
          "tgn:2261264",
          "tgn:1000001",
          "tgn:7012149",
          "tgn:7007157",
          "tgn:7029392"
        ],
        "placetype": [
          "aat:300008706"
        ],
        "id": 2261264,
        "name:xx": "County Line Creek"
      }
    },
    {
      "geometry": {
        "type": "Point",
        "coordinates": [
          -100.15,
          39.3167
        ]
      },
      "type": "Feature",
      "properties": {
        "hierarchy": [
          "tgn:2261265",
          "tgn:1000001",
          "tgn:2000692",
          "tgn:7012149",
          "tgn:7007254",
          "tgn:7029392"
        ],
        "placetype": [
          "aat:300008706"
        ],
        "id": 2261265,
        "name:xx": "County Line Creek"
      }
    },
    {
      "geometry": {
        "type": "Point",
        "coordinates": [
          -76.7667,
          38.6167
        ]
      },
      "type": "Feature",
      "properties": {
        "hierarchy": [
          "tgn:2261266",
          "tgn:1000001",
          "tgn:7012149",
          "tgn:7007516",
          "tgn:7029392"
        ],
        "placetype": [
          "aat:300008706"
        ],
        "id": 2261266,
        "name:xx": "County Line Creek"
      }
    },
    {
      "geometry": {
        "type": "Point",
        "coordinates": [
          -88.4667,
          46.4333
        ]
      },
      "type": "Feature",
      "properties": {
        "hierarchy": [
          "tgn:2261267",
          "tgn:1000001",
          "tgn:7012149",
          "tgn:7007520",
          "tgn:7029392"
        ],
        "placetype": [
          "aat:300008706"
        ],
        "id": 2261267,
        "name:xx": "County Line Creek"
      }
    },
    {
      "geometry": {
        "type": "Point",
        "coordinates": [
          -82.7667,
          43.65
        ]
      },
      "type": "Feature",
      "properties": {
        "hierarchy": [
          "tgn:2261268",
          "tgn:1000001",
          "tgn:7012149",
          "tgn:2000995",
          "tgn:7007520",
          "tgn:7029392"
        ],
        "placetype": [
          "aat:300008706"
        ],
        "id": 2261268,
        "name:xx": "County Line Creek"
      }
    },
    {
      "geometry": {
        "type": "Point",
        "coordinates": [
          -98.1,
          35.0333
        ]
      },
      "type": "Feature",
      "properties": {
        "hierarchy": [
          "tgn:2261269",
          "tgn:1000001",
          "tgn:7012149",
          "tgn:7007707",
          "tgn:7029392"
        ],
        "placetype": [
          "aat:300008706"
        ],
        "id": 2261269,
        "name:xx": "County Line Creek"
      }
    }
  ]
}
