{
  "geometry": {
    "type": "Point",
    "coordinates": [
      -118.3833,
      44.1833
    ]
  },
  "type": "Feature",
  "properties": {
    "hierarchy": [
      "tgn:2381135",
      "tgn:1000001",
      "tgn:7012149",
      "tgn:2001708",
      "tgn:7007708",
      "tgn:7029392"
    ],
    "placetype": [
      "aat:300008697"
    ],
    "id": 2381135,
    "name:xx": "Hawkins Spring"
  }
}
