{
  "type": "FeatureCollection",
  "features": [
    {
      "geometry": {
        "type": "Point",
        "coordinates": [
          -0.633333,
          51.4
        ]
      },
      "type": "Feature",
      "properties": {
        "hierarchy": [
          "tgn:7445821",
          "tgn:7002445",
          "tgn:1000003",
          "tgn:7026243",
          "tgn:7008591",
          "tgn:7029392"
        ],
        "placetype": [
          "aat:300387502"
        ],
        "name:en": "Sunningdale Park",
        "id": 7445821
      }
    },
    {
      "geometry": {
        "type": "Point",
        "coordinates": [
          -2.466667,
          55.55
        ]
      },
      "type": "Feature",
      "properties": {
        "hierarchy": [
          "tgn:7445823",
          "tgn:7002444",
          "tgn:1000003",
          "tgn:7008072",
          "tgn:7008591",
          "tgn:7029392"
        ],
        "placetype": [
          "aat:300387502"
        ],
        "name:en": "Sunlaws",
        "id": 7445823
      }
    },
    {
      "geometry": {
        "type": "Point",
        "coordinates": [
          -0.083333,
          53.65
        ]
      },
      "type": "Feature",
      "properties": {
        "hierarchy": [
          "tgn:7445824",
          "tgn:7002445",
          "tgn:1000003",
          "tgn:7019057",
          "tgn:7008591",
          "tgn:7029392"
        ],
        "placetype": [
          "aat:300008347"
        ],
        "name:en": "Sunk Island",
        "id": 7445824
      }
    },
    {
      "geometry": {
        "type": "Point",
        "coordinates": [
          -0.066667,
          53.65
        ]
      },
      "type": "Feature",
      "properties": {
        "hierarchy": [
          "tgn:7445825",
          "tgn:7002445",
          "tgn:1000003",
          "tgn:7019057",
          "tgn:7008591",
          "tgn:7029392"
        ],
        "placetype": [
          "aat:300008791"
        ],
        "name:en": "Sunk Island",
        "id": 7445825
      }
    },
    {
      "geometry": {
        "type": "Point",
        "coordinates": [
          -6.283333,
          56.6
        ]
      },
      "type": "Feature",
      "properties": {
        "hierarchy": [
          "tgn:7445826",
          "tgn:7019094",
          "tgn:7002444",
          "tgn:1000003",
          "tgn:7008591",
          "tgn:7029392"
        ],
        "placetype": [
          "aat:300008347"
        ],
        "name:en": "Sunipol",
        "id": 7445826
      }
    },
    {
      "geometry": {
        "type": "Point",
        "coordinates": [
          -2.7,
          52.733333
        ]
      },
      "type": "Feature",
      "properties": {
        "hierarchy": [
          "tgn:7445828",
          "tgn:7002445",
          "tgn:1000003",
          "tgn:7012034",
          "tgn:7008591",
          "tgn:7029392"
        ],
        "placetype": [
          "aat:300387502"
        ],
        "name:en": "Sundorne Castle",
        "id": 7445828
      }
    },
    {
      "geometry": {
        "type": "Point",
        "coordinates": [
          -0.466667,
          51.916667
        ]
      },
      "type": "Feature",
      "properties": {
        "hierarchy": [
          "tgn:7445829",
          "tgn:7002445",
          "tgn:1000003",
          "tgn:7026516",
          "tgn:7008591",
          "tgn:7029392"
        ],
        "placetype": [
          "aat:300008347"
        ],
        "name:en": "Sundon",
        "id": 7445829
      }
    }
  ]
}
