{
  "geometry": {
    "type": "Point",
    "coordinates": [
      31.238773,
      30.066982
    ]
  },
  "type": "Feature",
  "properties": {
    "hierarchy": [
      "tgn:7533069",
      "tgn:7001242",
      "tgn:7016833",
      "tgn:1001091",
      "tgn:7029392"
    ],
    "placetype": [
      "aat:300006036"
    ],
    "id": 7533069,
    "name:xx": "Barīd Jazīrat Badrān"
  }
}
