{
  "geometry": {
    "type": "Point",
    "coordinates": [
      -116.4833,
      42.8333
    ]
  },
  "type": "Feature",
  "properties": {
    "hierarchy": [
      "tgn:2401020",
      "tgn:1000001",
      "tgn:7012149",
      "tgn:2000488",
      "tgn:7007250",
      "tgn:7029392"
    ],
    "placetype": [
      "aat:300008706"
    ],
    "id": 2401020,
    "name:xx": "Horse Thief Creek"
  }
}
