{
  "geometry": {
    "type": "Point",
    "coordinates": [
      -142.1833,
      69.8667
    ]
  },
  "type": "Feature",
  "properties": {
    "hierarchy": [
      "tgn:2156900",
      "tgn:7006450",
      "tgn:1000001",
      "tgn:7012149",
      "tgn:2124005",
      "tgn:7029392"
    ],
    "placetype": [
      "aat:300132316"
    ],
    "id": 2156900,
    "name:xx": "Beaufort Lagoon"
  }
}
