{
  "geometry": {
    "type": "Point",
    "coordinates": [
      172.8167,
      52.85
    ]
  },
  "type": "Feature",
  "properties": {
    "hierarchy": [
      "tgn:2538854",
      "tgn:7030516",
      "tgn:7006450",
      "tgn:1000001",
      "tgn:7012149",
      "tgn:7029392"
    ],
    "placetype": [
      "aat:300008707"
    ],
    "id": 2538854,
    "name:xx": "Nevidiskov River"
  }
}
