{
  "geometry": {
    "type": "Point",
    "coordinates": [
      -73.5833,
      42.35
    ]
  },
  "type": "Feature",
  "properties": {
    "hierarchy": [
      "tgn:2068456",
      "tgn:1000001",
      "tgn:7013638",
      "tgn:7012149",
      "tgn:7007568",
      "tgn:7029392"
    ],
    "placetype": [
      "aat:300008347"
    ],
    "id": 2068456,
    "name:xx": "Chatham"
  }
}
