{
  "geometry": {
    "type": "Point",
    "coordinates": [
      -111.8333,
      33.3333
    ]
  },
  "type": "Feature",
  "properties": {
    "hierarchy": [
      "tgn:2131869",
      "tgn:1000001",
      "tgn:7006451",
      "tgn:7012149",
      "tgn:2000097",
      "tgn:7029392"
    ],
    "placetype": [
      "aat:300008347"
    ],
    "id": 2131869,
    "name:xx": "Amberwood II"
  }
}
