{
  "geometry": {
    "type": "Point",
    "coordinates": [
      -80.8833,
      41.8667
    ]
  },
  "type": "Feature",
  "properties": {
    "hierarchy": [
      "tgn:2646510",
      "tgn:1002156",
      "tgn:1000001",
      "tgn:7012149",
      "tgn:7007706",
      "tgn:7029392"
    ],
    "placetype": [
      "aat:300008347"
    ],
    "id": 2646510,
    "name:xx": "Saybrook-on-the-lake"
  }
}
