{
  "geometry": {
    "type": "Point",
    "coordinates": [
      -79.2833,
      38.25
    ]
  },
  "type": "Feature",
  "properties": {
    "hierarchy": [
      "tgn:2246261",
      "tgn:2002142",
      "tgn:1000001",
      "tgn:7012149",
      "tgn:7007919",
      "tgn:7029392"
    ],
    "placetype": [
      "aat:300008798"
    ],
    "id": 2246261,
    "name:xx": "Coalpit Knob"
  }
}
