{
  "geometry": {
    "type": "Point",
    "coordinates": [
      -112.25,
      35.5167
    ]
  },
  "type": "Feature",
  "properties": {
    "hierarchy": [
      "tgn:2457408",
      "tgn:1000001",
      "tgn:7006451",
      "tgn:2000092",
      "tgn:7012149",
      "tgn:7029392"
    ],
    "placetype": [
      "aat:300006191"
    ],
    "id": 2457408,
    "name:xx": "Little Lo Tank"
  }
}
