{
  "geometry": {
    "type": "Point",
    "coordinates": [
      -165.55,
      65.8333
    ]
  },
  "type": "Feature",
  "properties": {
    "hierarchy": [
      "tgn:2674235",
      "tgn:7006450",
      "tgn:1000001",
      "tgn:7012149",
      "tgn:2000079",
      "tgn:7029392"
    ],
    "placetype": [
      "aat:300008706"
    ],
    "id": 2674235,
    "name:xx": "Snowshoe Creek"
  }
}
