{
  "geometry": {
    "type": "Point",
    "coordinates": [
      -103.5667,
      29.7333
    ]
  },
  "type": "Feature",
  "properties": {
    "hierarchy": [
      "tgn:2286098",
      "tgn:1000001",
      "tgn:2001945",
      "tgn:7012149",
      "tgn:7007826",
      "tgn:7029392"
    ],
    "placetype": [
      "aat:300006191"
    ],
    "id": 2286098,
    "name:xx": "Dewees Tank"
  }
}
