{
  "geometry": {
    "type": "Point",
    "coordinates": [
      -80.9667,
      35.1167
    ]
  },
  "type": "Feature",
  "properties": {
    "hierarchy": [
      "tgn:2536409",
      "tgn:1000001",
      "tgn:7012149",
      "tgn:7014021",
      "tgn:7007709",
      "tgn:7029392"
    ],
    "placetype": [
      "aat:300008699"
    ],
    "id": 2536409,
    "name:xx": "Neal Branch"
  }
}
