{
  "geometry": {
    "type": "Point",
    "coordinates": [
      -84.3833,
      37.0167
    ]
  },
  "type": "Feature",
  "properties": {
    "hierarchy": [
      "tgn:2664389",
      "tgn:1000001",
      "tgn:7012149",
      "tgn:2000839",
      "tgn:7007255",
      "tgn:7029392"
    ],
    "placetype": [
      "aat:300008761"
    ],
    "id": 2664389,
    "name:xx": "Silvers Hollow"
  }
}
