{
  "geometry": {
    "type": "Point",
    "coordinates": [
      -75.95,
      39.7167
    ]
  },
  "type": "Feature",
  "properties": {
    "hierarchy": [
      "tgn:2149337",
      "tgn:1000001",
      "tgn:1002266",
      "tgn:7012149",
      "tgn:7007710",
      "tgn:7029392"
    ],
    "placetype": [
      "aat:300008699"
    ],
    "id": 2149337,
    "name:xx": "Barren Brook"
  }
}
