{
  "geometry": {
    "type": "Point",
    "coordinates": [
      -116.4833,
      45.3667
    ]
  },
  "type": "Feature",
  "properties": {
    "hierarchy": [
      "tgn:2150123",
      "tgn:1000001",
      "tgn:7012149",
      "tgn:2000476",
      "tgn:7007250",
      "tgn:7029392"
    ],
    "placetype": [
      "aat:300008697"
    ],
    "id": 2150123,
    "name:xx": "Barton Spring"
  }
}
