{
  "geometry": {
    "type": "Point",
    "coordinates": [
      -84.0333,
      38.05
    ]
  },
  "type": "Feature",
  "properties": {
    "hierarchy": [
      "tgn:2360856",
      "tgn:1000001",
      "tgn:7012149",
      "tgn:7007255",
      "tgn:7029392"
    ],
    "placetype": [
      "aat:300008706"
    ],
    "id": 2360856,
    "name:xx": "Grassy Lick Creek"
  }
}
