{
  "geometry": {
    "type": "Point",
    "coordinates": [
      17.3333,
      -10.0167
    ]
  },
  "type": "Feature",
  "properties": {
    "hierarchy": [
      "tgn:1087926",
      "tgn:7001242",
      "tgn:1000149",
      "tgn:1000888",
      "tgn:7029392"
    ],
    "placetype": [
      "aat:300008347"
    ],
    "id": 1087926,
    "name:xx": "Mussolo"
  }
}
