{
  "geometry": {
    "type": "Point",
    "coordinates": [
      -107.45,
      40.4333
    ]
  },
  "type": "Feature",
  "properties": {
    "hierarchy": [
      "tgn:2202361",
      "tgn:1000001",
      "tgn:7012149",
      "tgn:2000232",
      "tgn:7007158",
      "tgn:7029392"
    ],
    "placetype": [
      "aat:300008798"
    ],
    "id": 2202361,
    "name:xx": "Buck Peak"
  }
}
