{
  "geometry": {
    "type": "Point",
    "coordinates": [
      -81.5333,
      40.6833
    ]
  },
  "type": "Feature",
  "properties": {
    "hierarchy": [
      "tgn:2338114",
      "tgn:1000001",
      "tgn:7012149",
      "tgn:1002917",
      "tgn:7007706",
      "tgn:7029392"
    ],
    "placetype": [
      "aat:300000390"
    ],
    "id": 2338114,
    "name:xx": "Fox Mine"
  }
}
