{
  "geometry": {
    "type": "Point",
    "coordinates": [
      -76.9833,
      42.15
    ]
  },
  "type": "Feature",
  "properties": {
    "hierarchy": [
      "tgn:2777255",
      "tgn:1000001",
      "tgn:7012149",
      "tgn:1002920",
      "tgn:7007568",
      "tgn:7029392"
    ],
    "placetype": [
      "aat:300008706"
    ],
    "id": 2777255,
    "name:xx": "Winfield Creek"
  }
}
