{
  "geometry": {
    "type": "Point",
    "coordinates": [
      -81.55,
      38.2667
    ]
  },
  "type": "Feature",
  "properties": {
    "hierarchy": [
      "tgn:2119704",
      "tgn:1000001",
      "tgn:7012149",
      "tgn:2002270",
      "tgn:7013961",
      "tgn:7029392"
    ],
    "placetype": [
      "aat:300008347"
    ],
    "id": 2119704,
    "name:xx": "Rand"
  }
}
