{
  "geometry": {
    "type": "Point",
    "coordinates": [
      -115.0667,
      38.2333
    ]
  },
  "type": "Feature",
  "properties": {
    "hierarchy": [
      "tgn:2344482",
      "tgn:1000001",
      "tgn:2001418",
      "tgn:7012149",
      "tgn:7007526",
      "tgn:7029392"
    ],
    "placetype": [
      "aat:300386831"
    ],
    "id": 2344482,
    "name:xx": "Gap Mountains"
  }
}
