{
  "geometry": {
    "type": "Point",
    "coordinates": [
      -108.3333,
      46.2167
    ]
  },
  "type": "Feature",
  "properties": {
    "hierarchy": [
      "tgn:2591535",
      "tgn:1000001",
      "tgn:7012149",
      "tgn:2001315",
      "tgn:7007524",
      "tgn:7029392"
    ],
    "placetype": [
      "aat:300008706"
    ],
    "id": 2591535,
    "name:xx": "Pompeys Pillar Creek"
  }
}
