{
  "geometry": {
    "type": "Point",
    "coordinates": [
      -99.6333,
      43.45
    ]
  },
  "type": "Feature",
  "properties": {
    "hierarchy": [
      "tgn:2542371",
      "tgn:1000001",
      "tgn:7012149",
      "tgn:2001831",
      "tgn:7007713",
      "tgn:7029392"
    ],
    "placetype": [
      "aat:300008706"
    ],
    "id": 2542371,
    "name:xx": "No Moccasin Creek"
  }
}
