{
  "geometry": {
    "type": "Point",
    "coordinates": [
      -111.9667,
      41.5167
    ]
  },
  "type": "Feature",
  "properties": {
    "hierarchy": [
      "tgn:2189541",
      "tgn:1000001",
      "tgn:2002102",
      "tgn:7012149",
      "tgn:7007827",
      "tgn:7029392"
    ],
    "placetype": [
      "aat:300008761"
    ],
    "id": 2189541,
    "name:xx": "Bowden Canyon"
  }
}
