{
  "geometry": {
    "type": "Point",
    "coordinates": [
      36.0333,
      32.8333
    ]
  },
  "type": "Feature",
  "properties": {
    "hierarchy": [
      "tgn:1085108",
      "tgn:1002074",
      "tgn:1000004",
      "tgn:1000140",
      "tgn:7029392"
    ],
    "placetype": [
      "aat:300008347"
    ],
    "id": 1085108,
    "name:xx": "Ash Shaykh Saʻd"
  }
}
