{
  "geometry": {
    "type": "Point",
    "coordinates": [
      -109.0667,
      40.1833
    ]
  },
  "type": "Feature",
  "properties": {
    "hierarchy": [
      "tgn:2673077",
      "tgn:1000001",
      "tgn:7012149",
      "tgn:2002124",
      "tgn:7007827",
      "tgn:7029392"
    ],
    "placetype": [
      "aat:300008761"
    ],
    "id": 2673077,
    "name:xx": "Snake John Wash"
  }
}
