{
  "type": "FeatureCollection",
  "features": [
    {
      "geometry": {
        "type": "Point",
        "coordinates": [
          -93.8,
          44.2
        ]
      },
      "type": "Feature",
      "properties": {
        "hierarchy": [
          "tgn:2054920",
          "tgn:1000001",
          "tgn:2001005",
          "tgn:7012149",
          "tgn:7007521",
          "tgn:7029392"
        ],
        "placetype": [
          "aat:300008347"
        ],
        "id": 2054920,
        "name:xx": "Madison Lake"
      }
    },
    {
      "geometry": {
        "type": "Point",
        "coordinates": [
          -96.0667,
          43.6333
        ]
      },
      "type": "Feature",
      "properties": {
        "hierarchy": [
          "tgn:2054921",
          "tgn:1000001",
          "tgn:7012149",
          "tgn:2001065",
          "tgn:7007521",
          "tgn:7029392"
        ],
        "placetype": [
          "aat:300008347"
        ],
        "id": 2054921,
        "name:xx": "Magnolia"
      }
    },
    {
      "geometry": {
        "type": "Point",
        "coordinates": [
          -95.6,
          47.3167
        ]
      },
      "type": "Feature",
      "properties": {
        "hierarchy": [
          "tgn:2054922",
          "tgn:1000001",
          "tgn:7012149",
          "tgn:2001042",
          "tgn:7007521",
          "tgn:7029392"
        ],
        "placetype": [
          "aat:300008347",
          "aat:300387210"
        ],
        "id": 2054922,
        "name:xx": "Mahkonce"
      }
    },
    {
      "geometry": {
        "type": "Point",
        "coordinates": [
          -95.9667,
          47.3
        ]
      },
      "type": "Feature",
      "properties": {
        "hierarchy": [
          "tgn:2054923",
          "tgn:1000001",
          "tgn:7012149",
          "tgn:2001042",
          "tgn:7007521",
          "tgn:7029392"
        ],
        "placetype": [
          "aat:300008347"
        ],
        "id": 2054923,
        "name:xx": "Mahnomen"
      }
    },
    {
      "geometry": {
        "type": "Point",
        "coordinates": [
          -92.95,
          45.0667
        ]
      },
      "type": "Feature",
      "properties": {
        "hierarchy": [
          "tgn:2054924",
          "tgn:1000001",
          "tgn:7012149",
          "tgn:2001080",
          "tgn:7007521",
          "tgn:7029392"
        ],
        "placetype": [
          "aat:300008347"
        ],
        "id": 2054924,
        "name:xx": "Mahtomedi"
      }
    },
    {
      "geometry": {
        "type": "Point",
        "coordinates": [
          -92.6167,
          46.5667
        ]
      },
      "type": "Feature",
      "properties": {
        "hierarchy": [
          "tgn:2054925",
          "tgn:1000001",
          "tgn:2001007",
          "tgn:7012149",
          "tgn:7007521",
          "tgn:7029392"
        ],
        "placetype": [
          "aat:300008347"
        ],
        "id": 2054925,
        "name:xx": "Mahtowa"
      }
    },
    {
      "geometry": {
        "type": "Point",
        "coordinates": [
          -95.8167,
          46.4
        ]
      },
      "type": "Feature",
      "properties": {
        "hierarchy": [
          "tgn:2054926",
          "tgn:1000001",
          "tgn:7012149",
          "tgn:2001054",
          "tgn:7007521",
          "tgn:7029392"
        ],
        "placetype": [
          "aat:300008347",
          "aat:300387210"
        ],
        "id": 2054926,
        "name:xx": "Maine"
      }
    },
    {
      "geometry": {
        "type": "Point",
        "coordinates": [
          -92.3667,
          47.35
        ]
      },
      "type": "Feature",
      "properties": {
        "hierarchy": [
          "tgn:2054928",
          "tgn:1000001",
          "tgn:7012149",
          "tgn:2001067",
          "tgn:7007521",
          "tgn:7029392"
        ],
        "placetype": [
          "aat:300008347"
        ],
        "id": 2054928,
        "name:xx": "Makinen"
      }
    },
    {
      "geometry": {
        "type": "Point",
        "coordinates": [
          -96.9,
          47.8667
        ]
      },
      "type": "Feature",
      "properties": {
        "hierarchy": [
          "tgn:2054929",
          "tgn:1000001",
          "tgn:7012149",
          "tgn:2001058",
          "tgn:7007521",
          "tgn:7029392"
        ],
        "placetype": [
          "aat:300387016"
        ],
        "id": 2054929,
        "name:xx": "Mallory"
      }
    }
  ]
}
