{
  "geometry": {
    "type": "Point",
    "coordinates": [
      116.5667,
      41.1167
    ]
  },
  "type": "Feature",
  "properties": {
    "hierarchy": [
      "tgn:1107064",
      "tgn:1000004",
      "tgn:7002077",
      "tgn:1000111",
      "tgn:7029392"
    ],
    "placetype": [
      "aat:300008795"
    ],
    "id": 1107064,
    "name:xx": "Yunwu Shan"
  }
}
