{
  "geometry": {
    "type": "Point",
    "coordinates": [
      -89.4667,
      40.75
    ]
  },
  "type": "Feature",
  "properties": {
    "hierarchy": [
      "tgn:2027995",
      "tgn:1000001",
      "tgn:7012149",
      "tgn:1003035",
      "tgn:7007251",
      "tgn:7029392"
    ],
    "placetype": [
      "aat:300008347"
    ],
    "id": 2027995,
    "name:xx": "Germantown Hills"
  }
}
