{
  "geometry": {
    "type": "Point",
    "coordinates": [
      -95.1167,
      46.1667
    ]
  },
  "type": "Feature",
  "properties": {
    "hierarchy": [
      "tgn:2574784",
      "tgn:1000001",
      "tgn:7012149",
      "tgn:2001075",
      "tgn:7007521",
      "tgn:7029392"
    ],
    "placetype": [
      "aat:300008680"
    ],
    "id": 2574784,
    "name:xx": "Pendergast Lake"
  }
}
