{
  "geometry": {
    "type": "Point",
    "coordinates": [
      -83.3333,
      38.7667
    ]
  },
  "type": "Feature",
  "properties": {
    "hierarchy": [
      "tgn:2679927",
      "tgn:1000001",
      "tgn:7012149",
      "tgn:7007706",
      "tgn:7029392"
    ],
    "placetype": [
      "aat:300008706"
    ],
    "id": 2679927,
    "name:xx": "South Fork Scioto Brush Creek"
  }
}
