{
  "geometry": {
    "type": "Point",
    "coordinates": [
      -144.35,
      69.0167
    ]
  },
  "type": "Feature",
  "properties": {
    "hierarchy": [
      "tgn:2415738",
      "tgn:7006450",
      "tgn:1000001",
      "tgn:7012149",
      "tgn:2124005",
      "tgn:7029392"
    ],
    "placetype": [
      "aat:300008706"
    ],
    "id": 2415738,
    "name:xx": "Itkillik Creek"
  }
}
