{
  "geometry": {
    "type": "Point",
    "coordinates": [
      -116.55,
      33.15
    ]
  },
  "type": "Feature",
  "properties": {
    "hierarchy": [
      "tgn:2569478",
      "tgn:1000001",
      "tgn:7012149",
      "tgn:7007157",
      "tgn:1002858",
      "tgn:7029392"
    ],
    "placetype": [
      "aat:300008697"
    ],
    "id": 2569478,
    "name:xx": "Paroli Spring"
  }
}
