{
  "geometry": {
    "type": "Point",
    "coordinates": [
      -112.0667,
      46.55
    ]
  },
  "type": "Feature",
  "properties": {
    "hierarchy": [
      "tgn:2635528",
      "tgn:1000001",
      "tgn:7012149",
      "tgn:2001284",
      "tgn:7007524",
      "tgn:7029392"
    ],
    "placetype": [
      "aat:300000390"
    ],
    "id": 2635528,
    "name:xx": "SW NW Section 11 Mine"
  }
}
