{
  "type": "FeatureCollection",
  "features": [
    {
      "geometry": {
        "type": "Point",
        "coordinates": [
          -121.3833,
          47.5
        ]
      },
      "type": "Feature",
      "properties": {
        "hierarchy": [
          "tgn:2387330",
          "tgn:1000001",
          "tgn:7012149",
          "tgn:7018871",
          "tgn:7007920",
          "tgn:7029392"
        ],
        "placetype": [
          "aat:300008680"
        ],
        "id": 2387330,
        "name:xx": "Hester Lake"
      }
    },
    {
      "geometry": {
        "type": "Point",
        "coordinates": [
          -92.4833,
          30.95
        ]
      },
      "type": "Feature",
      "properties": {
        "hierarchy": [
          "tgn:2387331",
          "tgn:1000001",
          "tgn:7012149",
          "tgn:2000893",
          "tgn:7007256",
          "tgn:7029392"
        ],
        "placetype": [
          "aat:300008347"
        ],
        "id": 2387331,
        "name:xx": "Hester Landing"
      }
    },
    {
      "geometry": {
        "type": "Point",
        "coordinates": [
          -78.8,
          34.6167
        ]
      },
      "type": "Feature",
      "properties": {
        "hierarchy": [
          "tgn:2387332",
          "tgn:1000001",
          "tgn:2001471",
          "tgn:7012149",
          "tgn:7007709",
          "tgn:7029392"
        ],
        "placetype": [
          "aat:300006191"
        ],
        "id": 2387332,
        "name:xx": "Hester Millpond"
      }
    },
    {
      "geometry": {
        "type": "Point",
        "coordinates": [
          -82.9833,
          35
        ]
      },
      "type": "Feature",
      "properties": {
        "hierarchy": [
          "tgn:2387333",
          "tgn:1000001",
          "tgn:7012149",
          "tgn:2001761",
          "tgn:7007712",
          "tgn:7029392"
        ],
        "placetype": [
          "aat:300008798"
        ],
        "id": 2387333,
        "name:xx": "Hester Mountain"
      }
    },
    {
      "geometry": {
        "type": "Point",
        "coordinates": [
          -78.3167,
          35.7833
        ]
      },
      "type": "Feature",
      "properties": {
        "hierarchy": [
          "tgn:2387334",
          "tgn:1000001",
          "tgn:7012149",
          "tgn:2001548",
          "tgn:7007709",
          "tgn:7029392"
        ],
        "placetype": [
          "aat:300006191"
        ],
        "id": 2387334,
        "name:xx": "Hester Pond"
      }
    },
    {
      "geometry": {
        "type": "Point",
        "coordinates": [
          -74.3,
          39.55
        ]
      },
      "type": "Feature",
      "properties": {
        "hierarchy": [
          "tgn:2387335",
          "tgn:1000001",
          "tgn:1002738",
          "tgn:7012149",
          "tgn:7007565",
          "tgn:7029392"
        ],
        "placetype": [
          "aat:300008791"
        ],
        "id": 2387335,
        "name:xx": "Hester Sedge"
      }
    },
    {
      "geometry": {
        "type": "Point",
        "coordinates": [
          -75.6833,
          40
        ]
      },
      "type": "Feature",
      "properties": {
        "hierarchy": [
          "tgn:2387336",
          "tgn:1000001",
          "tgn:1002266",
          "tgn:7012149",
          "tgn:7007710",
          "tgn:7029392"
        ],
        "placetype": [
          "aat:300386845"
        ],
        "id": 2387336,
        "name:xx": "Hester Valley"
      }
    },
    {
      "geometry": {
        "type": "Point",
        "coordinates": [
          -81.6333,
          28.1
        ]
      },
      "type": "Feature",
      "properties": {
        "hierarchy": [
          "tgn:2387337",
          "tgn:1000001",
          "tgn:7012149",
          "tgn:1002793",
          "tgn:7007240",
          "tgn:7029392"
        ],
        "placetype": [
          "aat:300008680"
        ],
        "id": 2387337,
        "name:xx": "Hester, Lake"
      }
    },
    {
      "geometry": {
        "type": "Point",
        "coordinates": [
          -100.75,
          48.05
        ]
      },
      "type": "Feature",
      "properties": {
        "hierarchy": [
          "tgn:2387338",
          "tgn:1000001",
          "tgn:2001581",
          "tgn:7012149",
          "tgn:7007705",
          "tgn:7029392"
        ],
        "placetype": [
          "aat:300008680"
        ],
        "id": 2387338,
        "name:xx": "Hester, Lake"
      }
    },
    {
      "geometry": {
        "type": "Point",
        "coordinates": [
          -90.1833,
          38.25
        ]
      },
      "type": "Feature",
      "properties": {
        "hierarchy": [
          "tgn:2387339",
          "tgn:1000001",
          "tgn:7012149",
          "tgn:1002677",
          "tgn:7007251",
          "tgn:7029392"
        ],
        "placetype": [
          "aat:300008706"
        ],
        "id": 2387339,
        "name:xx": "Hesterburg Creek"
      }
    }
  ]
}
