{
  "geometry": {
    "type": "Point",
    "coordinates": [
      -159.9833,
      70.3667
    ]
  },
  "type": "Feature",
  "properties": {
    "hierarchy": [
      "tgn:2536399",
      "tgn:7006450",
      "tgn:1000001",
      "tgn:7012149",
      "tgn:2124005",
      "tgn:7029392"
    ],
    "placetype": [
      "aat:300008791"
    ],
    "id": 2536399,
    "name:xx": "Neakok Island"
  }
}
