{
  "geometry": {
    "type": "Point",
    "coordinates": [
      -114.2833,
      41.3833
    ]
  },
  "type": "Feature",
  "properties": {
    "hierarchy": [
      "tgn:2734862",
      "tgn:1000001",
      "tgn:2001411",
      "tgn:7012149",
      "tgn:7007526",
      "tgn:7029392"
    ],
    "placetype": [
      "aat:300008761"
    ],
    "id": 2734862,
    "name:xx": "Twelvemile Canyon"
  }
}
