{
  "geometry": {
    "type": "Point",
    "coordinates": [
      -106.9833,
      39.0333
    ]
  },
  "type": "Feature",
  "properties": {
    "hierarchy": [
      "tgn:2161792",
      "tgn:1000001",
      "tgn:7012149",
      "tgn:7007158",
      "tgn:7029392"
    ],
    "placetype": [
      "aat:300008798"
    ],
    "id": 2161792,
    "name:xx": "Belleview Mountain"
  }
}
