{
  "type": "FeatureCollection",
  "features": [
    {
      "geometry": {
        "type": "Point",
        "coordinates": [
          12.816667,
          48.466667
        ]
      },
      "type": "Feature",
      "properties": {
        "hierarchy": [
          "tgn:7207550",
          "tgn:7003669",
          "tgn:1000003",
          "tgn:7000084",
          "tgn:7029392"
        ],
        "placetype": [
          "aat:300008347"
        ],
        "id": 7207550,
        "name:xx": "Burg"
      }
    },
    {
      "geometry": {
        "type": "Point",
        "coordinates": [
          9.066667,
          48.45
        ]
      },
      "type": "Feature",
      "properties": {
        "hierarchy": [
          "tgn:7207551",
          "tgn:7003692",
          "tgn:1000003",
          "tgn:7000084",
          "tgn:7029392"
        ],
        "placetype": [
          "aat:300008347"
        ],
        "id": 7207551,
        "name:xx": "Burg"
      }
    },
    {
      "geometry": {
        "type": "Point",
        "coordinates": [
          12.316667,
          48.433333
        ]
      },
      "type": "Feature",
      "properties": {
        "hierarchy": [
          "tgn:7207552",
          "tgn:7003669",
          "tgn:1000003",
          "tgn:7000084",
          "tgn:7029392"
        ],
        "placetype": [
          "aat:300008347"
        ],
        "id": 7207552,
        "name:xx": "Bürg"
      }
    },
    {
      "geometry": {
        "type": "Point",
        "coordinates": [
          12.683333,
          48.266667
        ]
      },
      "type": "Feature",
      "properties": {
        "hierarchy": [
          "tgn:7207553",
          "tgn:7003669",
          "tgn:1000003",
          "tgn:7000084",
          "tgn:7029392"
        ],
        "placetype": [
          "aat:300008347"
        ],
        "id": 7207553,
        "name:xx": "Burg"
      }
    },
    {
      "geometry": {
        "type": "Point",
        "coordinates": [
          10.5,
          48.25
        ]
      },
      "type": "Feature",
      "properties": {
        "hierarchy": [
          "tgn:7207554",
          "tgn:7003669",
          "tgn:1000003",
          "tgn:7000084",
          "tgn:7029392"
        ],
        "placetype": [
          "aat:300008347"
        ],
        "id": 7207554,
        "name:xx": "Burg"
      }
    },
    {
      "geometry": {
        "type": "Point",
        "coordinates": [
          12.3,
          48.216667
        ]
      },
      "type": "Feature",
      "properties": {
        "hierarchy": [
          "tgn:7207555",
          "tgn:7003669",
          "tgn:1000003",
          "tgn:7000084",
          "tgn:7029392"
        ],
        "placetype": [
          "aat:300008347"
        ],
        "id": 7207555,
        "name:xx": "Bürg"
      }
    },
    {
      "geometry": {
        "type": "Point",
        "coordinates": [
          12.716667,
          47.983333
        ]
      },
      "type": "Feature",
      "properties": {
        "hierarchy": [
          "tgn:7207556",
          "tgn:7003669",
          "tgn:1000003",
          "tgn:7000084",
          "tgn:7029392"
        ],
        "placetype": [
          "aat:300008347"
        ],
        "id": 7207556,
        "name:xx": "Burg"
      }
    },
    {
      "geometry": {
        "type": "Point",
        "coordinates": [
          7.983333,
          47.966667
        ]
      },
      "type": "Feature",
      "properties": {
        "hierarchy": [
          "tgn:7207557",
          "tgn:7003692",
          "tgn:1000003",
          "tgn:7000084",
          "tgn:7029392"
        ],
        "placetype": [
          "aat:300008347"
        ],
        "id": 7207557,
        "name:xx": "Burg"
      }
    },
    {
      "geometry": {
        "type": "Point",
        "coordinates": [
          10.433333,
          47.866667
        ]
      },
      "type": "Feature",
      "properties": {
        "hierarchy": [
          "tgn:7207558",
          "tgn:7003669",
          "tgn:1000003",
          "tgn:7000084",
          "tgn:7029392"
        ],
        "placetype": [
          "aat:300008347"
        ],
        "id": 7207558,
        "name:xx": "Burg"
      }
    },
    {
      "geometry": {
        "type": "Point",
        "coordinates": [
          9.45,
          47.8
        ]
      },
      "type": "Feature",
      "properties": {
        "hierarchy": [
          "tgn:7207559",
          "tgn:7003692",
          "tgn:1000003",
          "tgn:7000084",
          "tgn:7029392"
        ],
        "placetype": [
          "aat:300008347"
        ],
        "id": 7207559,
        "name:xx": "Burg"
      }
    }
  ]
}
