{
  "geometry": {
    "type": "Point",
    "coordinates": [
      -82.8667,
      34.9333
    ]
  },
  "type": "Feature",
  "properties": {
    "hierarchy": [
      "tgn:2502323",
      "tgn:1000001",
      "tgn:7012149",
      "tgn:2001761",
      "tgn:7007712",
      "tgn:7029392"
    ],
    "placetype": [
      "aat:300008798"
    ],
    "id": 2502323,
    "name:xx": "McKinney Mountain"
  }
}
