{
  "type": "FeatureCollection",
  "features": [
    {
      "geometry": {
        "type": "Point",
        "coordinates": [
          -65.6,
          -17.9833
        ]
      },
      "type": "Feature",
      "properties": {
        "hierarchy": [
          "tgn:1020460",
          "tgn:1000572",
          "tgn:1000046",
          "tgn:1000002",
          "tgn:7029392"
        ],
        "placetype": [
          "aat:300008347"
        ],
        "id": 1020460,
        "name:xx": "Villa Eufronio Viscarra"
      }
    },
    {
      "geometry": {
        "type": "Point",
        "coordinates": [
          -67.75,
          -20.7667
        ]
      },
      "type": "Feature",
      "properties": {
        "hierarchy": [
          "tgn:1020461",
          "tgn:1000729",
          "tgn:1000046",
          "tgn:1000002",
          "tgn:7029392"
        ],
        "placetype": [
          "aat:300008347"
        ],
        "id": 1020461,
        "name:xx": "Villa Martín"
      }
    },
    {
      "geometry": {
        "type": "Point",
        "coordinates": [
          -63.5,
          -22.25
        ]
      },
      "type": "Feature",
      "properties": {
        "hierarchy": [
          "tgn:1020462",
          "tgn:1000776",
          "tgn:1000046",
          "tgn:1000002",
          "tgn:7029392"
        ],
        "placetype": [
          "aat:300008347"
        ],
        "id": 1020462,
        "name:xx": "Villa Montes"
      }
    },
    {
      "geometry": {
        "type": "Point",
        "coordinates": [
          -65.8,
          -17.6167
        ]
      },
      "type": "Feature",
      "properties": {
        "hierarchy": [
          "tgn:1020463",
          "tgn:1000572",
          "tgn:1000046",
          "tgn:1000002",
          "tgn:7029392"
        ],
        "placetype": [
          "aat:300008347"
        ],
        "id": 1020463,
        "name:xx": "Villa Rivero"
      }
    },
    {
      "geometry": {
        "type": "Point",
        "coordinates": [
          -64.3833,
          -19.1
        ]
      },
      "type": "Feature",
      "properties": {
        "hierarchy": [
          "tgn:1020464",
          "tgn:1000571",
          "tgn:1000046",
          "tgn:1000002",
          "tgn:7029392"
        ],
        "placetype": [
          "aat:300008347"
        ],
        "id": 1020464,
        "name:xx": "Villa Serrano"
      }
    },
    {
      "geometry": {
        "type": "Point",
        "coordinates": [
          -65.3667,
          16.9167
        ]
      },
      "type": "Feature",
      "properties": {
        "hierarchy": [
          "tgn:1020465",
          "tgn:1000572",
          "tgn:1000046",
          "tgn:1000002",
          "tgn:7029392"
        ],
        "placetype": [
          "aat:300008347"
        ],
        "id": 1020465,
        "name:xx": "Villa Tunari"
      }
    },
    {
      "geometry": {
        "type": "Point",
        "coordinates": [
          -63.8,
          -19.9
        ]
      },
      "type": "Feature",
      "properties": {
        "hierarchy": [
          "tgn:1020466",
          "tgn:1000571",
          "tgn:1000046",
          "tgn:1000002",
          "tgn:7029392"
        ],
        "placetype": [
          "aat:300008347"
        ],
        "id": 1020466,
        "name:xx": "Villa Vaca Guzmán"
      }
    },
    {
      "geometry": {
        "type": "Point",
        "coordinates": [
          -65.5833,
          -22.0833
        ]
      },
      "type": "Feature",
      "properties": {
        "hierarchy": [
          "tgn:1020467",
          "tgn:1000729",
          "tgn:1000046",
          "tgn:1000002",
          "tgn:7029392"
        ],
        "placetype": [
          "aat:300008347"
        ],
        "id": 1020467,
        "name:xx": "Villazon"
      }
    },
    {
      "geometry": {
        "type": "Point",
        "coordinates": [
          -65.3667,
          -20.2333
        ]
      },
      "type": "Feature",
      "properties": {
        "hierarchy": [
          "tgn:1020468",
          "tgn:1000729",
          "tgn:1000046",
          "tgn:1000002",
          "tgn:7029392"
        ],
        "placetype": [
          "aat:300008347"
        ],
        "id": 1020468,
        "name:xx": "Vitichi"
      }
    },
    {
      "geometry": {
        "type": "Point",
        "coordinates": [
          -63.1833,
          -17.5
        ]
      },
      "type": "Feature",
      "properties": {
        "hierarchy": [
          "tgn:1020469",
          "tgn:1000752",
          "tgn:1000046",
          "tgn:1000002",
          "tgn:7029392"
        ],
        "placetype": [
          "aat:300008347"
        ],
        "id": 1020469,
        "name:xx": "Warnes"
      }
    }
  ]
}
