{
  "geometry": {
    "type": "Point",
    "coordinates": [
      -106.6333,
      36.2333
    ]
  },
  "type": "Feature",
  "properties": {
    "hierarchy": [
      "tgn:2595830",
      "tgn:1000001",
      "tgn:7012149",
      "tgn:2001449",
      "tgn:7007566",
      "tgn:7029392"
    ],
    "placetype": [
      "aat:300008699"
    ],
    "id": 2595830,
    "name:xx": "Potrero, Cañada del"
  }
}
