{
  "geometry": {
    "type": "Point",
    "coordinates": [
      17.45,
      59.7333
    ]
  },
  "type": "Feature",
  "properties": {
    "hierarchy": [
      "tgn:1100364",
      "tgn:1000003",
      "tgn:1000462",
      "tgn:1000097",
      "tgn:7029392"
    ],
    "placetype": [
      "aat:300006891"
    ],
    "id": 1100364,
    "name:xx": "Vik"
  }
}
