{
  "type": "FeatureCollection",
  "features": [
    {
      "geometry": {
        "type": "Point",
        "coordinates": [
          10.45,
          44.816667
        ]
      },
      "type": "Feature",
      "properties": {
        "hierarchy": [
          "tgn:7046291",
          "tgn:7003134",
          "tgn:1000003",
          "tgn:7008516",
          "tgn:1000080",
          "tgn:7029392"
        ],
        "placetype": [
          "aat:300008347"
        ],
        "id": 7046291,
        "name:xx": "Fiesso"
      }
    },
    {
      "geometry": {
        "type": "Point",
        "coordinates": [
          10.316667,
          45.233333
        ]
      },
      "type": "Feature",
      "properties": {
        "hierarchy": [
          "tgn:7046292",
          "tgn:7005765",
          "tgn:1000003",
          "tgn:7003237",
          "tgn:1000080",
          "tgn:7029392"
        ],
        "placetype": [
          "aat:300008347"
        ],
        "id": 7046292,
        "name:xx": "Fiesse"
      }
    },
    {
      "geometry": {
        "type": "Point",
        "coordinates": [
          7.716667,
          45.866667
        ]
      },
      "type": "Feature",
      "properties": {
        "hierarchy": [
          "tgn:7046294",
          "tgn:1003430",
          "tgn:1000003",
          "tgn:7003126",
          "tgn:1000080",
          "tgn:7029392"
        ],
        "placetype": [
          "aat:300008347"
        ],
        "id": 7046294,
        "name:xx": "Fiery"
      }
    },
    {
      "geometry": {
        "type": "Point",
        "coordinates": [
          16.833333,
          41.133333
        ]
      },
      "type": "Feature",
      "properties": {
        "hierarchy": [
          "tgn:7046296",
          "tgn:7003248",
          "tgn:1000003",
          "tgn:7010380",
          "tgn:1000080",
          "tgn:7029392"
        ],
        "placetype": [
          "aat:300387200"
        ],
        "id": 7046296,
        "name:xx": "Fiera del Levante"
      }
    },
    {
      "geometry": {
        "type": "Point",
        "coordinates": [
          8.7,
          45.766667
        ]
      },
      "type": "Feature",
      "properties": {
        "hierarchy": [
          "tgn:7046299",
          "tgn:1000003",
          "tgn:1003508",
          "tgn:7003237",
          "tgn:1000080",
          "tgn:7029392"
        ],
        "placetype": [
          "aat:300008680"
        ],
        "id": 7046299,
        "name:xx": "Comabbio, Lago di"
      }
    }
  ]
}
