{
  "type": "FeatureCollection",
  "features": [
    {
      "geometry": {
        "type": "Point",
        "coordinates": [
          11.65,
          49.616667
        ]
      },
      "type": "Feature",
      "properties": {
        "hierarchy": [
          "tgn:7140090",
          "tgn:7003669",
          "tgn:1000003",
          "tgn:7000084",
          "tgn:7029392"
        ],
        "placetype": [
          "aat:300008347"
        ],
        "id": 7140090,
        "name:xx": "Loch"
      }
    },
    {
      "geometry": {
        "type": "Point",
        "coordinates": [
          11.533333,
          49.566667
        ]
      },
      "type": "Feature",
      "properties": {
        "hierarchy": [
          "tgn:7140091",
          "tgn:7003669",
          "tgn:1000003",
          "tgn:7000084",
          "tgn:7029392"
        ],
        "placetype": [
          "aat:300008347"
        ],
        "id": 7140091,
        "name:xx": "Loch"
      }
    },
    {
      "geometry": {
        "type": "Point",
        "coordinates": [
          10.966667,
          49.4
        ]
      },
      "type": "Feature",
      "properties": {
        "hierarchy": [
          "tgn:7140092",
          "tgn:7003669",
          "tgn:1000003",
          "tgn:7000084",
          "tgn:7029392"
        ],
        "placetype": [
          "aat:300008347"
        ],
        "id": 7140092,
        "name:xx": "Loch"
      }
    },
    {
      "geometry": {
        "type": "Point",
        "coordinates": [
          12.066667,
          49.1
        ]
      },
      "type": "Feature",
      "properties": {
        "hierarchy": [
          "tgn:7140093",
          "tgn:7003669",
          "tgn:1000003",
          "tgn:7000084",
          "tgn:7029392"
        ],
        "placetype": [
          "aat:300008347"
        ],
        "id": 7140093,
        "name:xx": "Loch"
      }
    },
    {
      "geometry": {
        "type": "Point",
        "coordinates": [
          11.933333,
          49.016667
        ]
      },
      "type": "Feature",
      "properties": {
        "hierarchy": [
          "tgn:7140094",
          "tgn:7003669",
          "tgn:1000003",
          "tgn:7000084",
          "tgn:7029392"
        ],
        "placetype": [
          "aat:300008347"
        ],
        "id": 7140094,
        "name:xx": "Loch"
      }
    },
    {
      "geometry": {
        "type": "Point",
        "coordinates": [
          11.366667,
          48.566667
        ]
      },
      "type": "Feature",
      "properties": {
        "hierarchy": [
          "tgn:7140095",
          "tgn:7003669",
          "tgn:1000003",
          "tgn:7000084",
          "tgn:7029392"
        ],
        "placetype": [
          "aat:300008347"
        ],
        "id": 7140095,
        "name:xx": "Loch"
      }
    },
    {
      "geometry": {
        "type": "Point",
        "coordinates": [
          8.383333,
          48.5
        ]
      },
      "type": "Feature",
      "properties": {
        "hierarchy": [
          "tgn:7140096",
          "tgn:7003692",
          "tgn:1000003",
          "tgn:7000084",
          "tgn:7029392"
        ],
        "placetype": [
          "aat:300008347"
        ],
        "id": 7140096,
        "name:xx": "Loch"
      }
    },
    {
      "geometry": {
        "type": "Point",
        "coordinates": [
          8.166667,
          47.783333
        ]
      },
      "type": "Feature",
      "properties": {
        "hierarchy": [
          "tgn:7140097",
          "tgn:7003692",
          "tgn:1000003",
          "tgn:7000084",
          "tgn:7029392"
        ],
        "placetype": [
          "aat:300008347"
        ],
        "id": 7140097,
        "name:xx": "Loch"
      }
    },
    {
      "geometry": {
        "type": "Point",
        "coordinates": [
          8.066667,
          47.566667
        ]
      },
      "type": "Feature",
      "properties": {
        "hierarchy": [
          "tgn:7140098",
          "tgn:7003692",
          "tgn:1000003",
          "tgn:7000084",
          "tgn:7029392"
        ],
        "placetype": [
          "aat:300008347"
        ],
        "id": 7140098,
        "name:xx": "Loch"
      }
    },
    {
      "geometry": {
        "type": "Point",
        "coordinates": [
          9.833333,
          54.6
        ]
      },
      "type": "Feature",
      "properties": {
        "hierarchy": [
          "tgn:7140099",
          "tgn:1000003",
          "tgn:7003688",
          "tgn:7000084",
          "tgn:7029392"
        ],
        "placetype": [
          "aat:300008347"
        ],
        "id": 7140099,
        "name:xx": "Lindaunis"
      }
    }
  ]
}
