{
  "geometry": {
    "type": "Point",
    "coordinates": [
      -148.55,
      60.1667
    ]
  },
  "type": "Feature",
  "properties": {
    "hierarchy": [
      "tgn:2721270",
      "tgn:7006450",
      "tgn:1000001",
      "tgn:7012149",
      "tgn:2000086",
      "tgn:7029392"
    ],
    "placetype": [
      "aat:300008835"
    ],
    "id": 2721270,
    "name:xx": "Tiger Glacier"
  }
}
