{
  "geometry": {
    "type": "Point",
    "coordinates": [
      -90.7833,
      34.4333
    ]
  },
  "type": "Feature",
  "properties": {
    "hierarchy": [
      "tgn:2157029",
      "tgn:1000001",
      "tgn:7016172",
      "tgn:7012149",
      "tgn:2000158",
      "tgn:7029392"
    ],
    "placetype": [
      "aat:300006075"
    ],
    "id": 2157029,
    "name:xx": "Beaver Bayou Ditch"
  }
}
