{
  "geometry": {
    "type": "Point",
    "coordinates": [
      -89.8667,
      37.1167
    ]
  },
  "type": "Feature",
  "properties": {
    "hierarchy": [
      "tgn:2187716",
      "tgn:1000001",
      "tgn:7012149",
      "tgn:7007523",
      "tgn:7029392"
    ],
    "placetype": [
      "aat:300055621"
    ],
    "id": 2187716,
    "name:xx": "Bootheel Planning Region"
  }
}
