{
  "geometry": {
    "type": "Point",
    "coordinates": [
      -98.0333,
      35.4833
    ]
  },
  "type": "Feature",
  "properties": {
    "hierarchy": [
      "tgn:2711767",
      "tgn:1000001",
      "tgn:2001631",
      "tgn:7012149",
      "tgn:7007707",
      "tgn:7029392"
    ],
    "placetype": [
      "aat:300008706"
    ],
    "id": 2711767,
    "name:xx": "Target Creek"
  }
}
