{
  "geometry": {
    "type": "Point",
    "coordinates": [
      -77.35,
      41.1667
    ]
  },
  "type": "Feature",
  "properties": {
    "hierarchy": [
      "tgn:2087130",
      "tgn:1000001",
      "tgn:1002286",
      "tgn:7012149",
      "tgn:7007710",
      "tgn:7029392"
    ],
    "placetype": [
      "aat:300008347"
    ],
    "id": 2087130,
    "name:xx": "Charlton"
  }
}
