{
  "geometry": {
    "type": "Point",
    "coordinates": [
      -123.35,
      45.3167
    ]
  },
  "type": "Feature",
  "properties": {
    "hierarchy": [
      "tgn:2443061",
      "tgn:1000001",
      "tgn:7012149",
      "tgn:1003044",
      "tgn:7007708",
      "tgn:7029392"
    ],
    "placetype": [
      "aat:300008706"
    ],
    "id": 2443061,
    "name:xx": "Kutch Creek"
  }
}
