{
  "geometry": {
    "type": "Point",
    "coordinates": [
      30.15,
      31.133333
    ]
  },
  "type": "Feature",
  "properties": {
    "hierarchy": [
      "tgn:7540150",
      "tgn:7001242",
      "tgn:1001075",
      "tgn:7016833",
      "tgn:7029392"
    ],
    "placetype": [
      "aat:300006075"
    ],
    "name:en": "Jann훮b카yat as Sa'r훮n카yah",
    "id": 7540150
  }
}
