{
  "geometry": {
    "type": "Point",
    "coordinates": [
      -119.2167,
      34.5333
    ]
  },
  "type": "Feature",
  "properties": {
    "hierarchy": [
      "tgn:2546734",
      "tgn:1000001",
      "tgn:7012149",
      "tgn:7007157",
      "tgn:1002972",
      "tgn:7029392"
    ],
    "placetype": [
      "aat:300008706"
    ],
    "id": 2546734,
    "name:xx": "North Fork Matilija Creek"
  }
}
