{
  "geometry": {
    "type": "Point",
    "coordinates": [
      -86.6667,
      38.65
    ]
  },
  "type": "Feature",
  "properties": {
    "hierarchy": [
      "tgn:2646838",
      "tgn:1000001",
      "tgn:7012149",
      "tgn:1002750",
      "tgn:7007252",
      "tgn:7029392"
    ],
    "placetype": [
      "aat:300008347"
    ],
    "id": 2646838,
    "name:xx": "Scarlet"
  }
}
