{
  "geometry": {
    "type": "Point",
    "coordinates": [
      -85.0833,
      37.9333
    ]
  },
  "type": "Feature",
  "properties": {
    "hierarchy": [
      "tgn:2529672",
      "tgn:1002147",
      "tgn:1000001",
      "tgn:7012149",
      "tgn:7007255",
      "tgn:7029392"
    ],
    "placetype": [
      "aat:300008699"
    ],
    "id": 2529672,
    "name:xx": "Mud Lick"
  }
}
