{
  "type": "FeatureCollection",
  "features": [
    {
      "geometry": {
        "type": "Point",
        "coordinates": [
          10.033333,
          49.966667
        ]
      },
      "type": "Feature",
      "properties": {
        "hierarchy": [
          "tgn:7163190",
          "tgn:7003669",
          "tgn:1000003",
          "tgn:7000084",
          "tgn:7029392"
        ],
        "placetype": [
          "aat:300008777"
        ],
        "id": 7163190,
        "name:xx": "Hühner-Berg"
      }
    },
    {
      "geometry": {
        "type": "Point",
        "coordinates": [
          9.316667,
          49.35
        ]
      },
      "type": "Feature",
      "properties": {
        "hierarchy": [
          "tgn:7163191",
          "tgn:7003692",
          "tgn:1000003",
          "tgn:7000084",
          "tgn:7029392"
        ],
        "placetype": [
          "aat:300008777"
        ],
        "id": 7163191,
        "name:xx": "Hühnerberg"
      }
    },
    {
      "geometry": {
        "type": "Point",
        "coordinates": [
          8.966667,
          49.233333
        ]
      },
      "type": "Feature",
      "properties": {
        "hierarchy": [
          "tgn:7163193",
          "tgn:7003692",
          "tgn:1000003",
          "tgn:7000084",
          "tgn:7029392"
        ],
        "placetype": [
          "aat:300008777"
        ],
        "id": 7163193,
        "name:xx": "Hühnerberg"
      }
    },
    {
      "geometry": {
        "type": "Point",
        "coordinates": [
          8.933333,
          48.85
        ]
      },
      "type": "Feature",
      "properties": {
        "hierarchy": [
          "tgn:7163194",
          "tgn:7003692",
          "tgn:1000003",
          "tgn:7000084",
          "tgn:7029392"
        ],
        "placetype": [
          "aat:300008777"
        ],
        "id": 7163194,
        "name:xx": "Hühnerberg"
      }
    },
    {
      "geometry": {
        "type": "Point",
        "coordinates": [
          10.666667,
          48.783333
        ]
      },
      "type": "Feature",
      "properties": {
        "hierarchy": [
          "tgn:7163195",
          "tgn:7003669",
          "tgn:1000003",
          "tgn:7000084",
          "tgn:7029392"
        ],
        "placetype": [
          "aat:300008777"
        ],
        "id": 7163195,
        "name:xx": "Hühnerberg"
      }
    },
    {
      "geometry": {
        "type": "Point",
        "coordinates": [
          10.616667,
          48.666667
        ]
      },
      "type": "Feature",
      "properties": {
        "hierarchy": [
          "tgn:7163196",
          "tgn:7003669",
          "tgn:1000003",
          "tgn:7000084",
          "tgn:7029392"
        ],
        "placetype": [
          "aat:300008777"
        ],
        "id": 7163196,
        "name:xx": "Hühnerberg"
      }
    },
    {
      "geometry": {
        "type": "Point",
        "coordinates": [
          10.366667,
          48.466667
        ]
      },
      "type": "Feature",
      "properties": {
        "hierarchy": [
          "tgn:7163197",
          "tgn:7003669",
          "tgn:1000003",
          "tgn:7000084",
          "tgn:7029392"
        ],
        "placetype": [
          "aat:300008777"
        ],
        "id": 7163197,
        "name:xx": "Hühnerberg"
      }
    },
    {
      "geometry": {
        "type": "Point",
        "coordinates": [
          7.683333,
          50.316667
        ]
      },
      "type": "Feature",
      "properties": {
        "hierarchy": [
          "tgn:7163198",
          "tgn:1000003",
          "tgn:7003682",
          "tgn:7000084",
          "tgn:7029392"
        ],
        "placetype": [
          "aat:300000206"
        ],
        "id": 7163198,
        "name:xx": "Hühnerberg"
      }
    },
    {
      "geometry": {
        "type": "Point",
        "coordinates": [
          10.733333,
          47.983333
        ]
      },
      "type": "Feature",
      "properties": {
        "hierarchy": [
          "tgn:7163199",
          "tgn:7003669",
          "tgn:1000003",
          "tgn:7000084",
          "tgn:7029392"
        ],
        "placetype": [
          "aat:300008699"
        ],
        "id": 7163199,
        "name:xx": "Hühnerbach"
      }
    }
  ]
}
