{
  "geometry": {
    "type": "Point",
    "coordinates": [
      74.953402,
      32.49228
    ]
  },
  "type": "Feature",
  "properties": {
    "hierarchy": [
      "tgn:7564981",
      "tgn:1000004",
      "tgn:7000198",
      "tgn:7000799",
      "tgn:7029392"
    ],
    "placetype": [
      "aat:300008347"
    ],
    "name:en": "Mandliāl",
    "id": 7564981
  }
}
