{
  "geometry": {
    "type": "Point",
    "coordinates": [
      -76.6167,
      40.9333
    ]
  },
  "type": "Feature",
  "properties": {
    "hierarchy": [
      "tgn:2439179",
      "tgn:1000001",
      "tgn:7012149",
      "tgn:1002732",
      "tgn:7007710",
      "tgn:7029392"
    ],
    "placetype": [
      "aat:300008699"
    ],
    "id": 2439179,
    "name:xx": "Kipps Run"
  }
}
