{
  "type": "FeatureCollection",
  "features": [
    {
      "geometry": {
        "type": "Point",
        "coordinates": [
          -124.1333,
          42.7167
        ]
      },
      "type": "Feature",
      "properties": {
        "hierarchy": [
          "tgn:2596380",
          "tgn:1000001",
          "tgn:7012149",
          "tgn:7007708",
          "tgn:7029392"
        ],
        "placetype": [
          "aat:300008761"
        ],
        "id": 2596380,
        "name:xx": "Poverty Gulch"
      }
    },
    {
      "geometry": {
        "type": "Point",
        "coordinates": [
          -103.7167,
          44.0833
        ]
      },
      "type": "Feature",
      "properties": {
        "hierarchy": [
          "tgn:2596381",
          "tgn:1000001",
          "tgn:7012149",
          "tgn:2001821",
          "tgn:7007713",
          "tgn:7029392"
        ],
        "placetype": [
          "aat:300008761"
        ],
        "id": 2596381,
        "name:xx": "Poverty Gulch"
      }
    },
    {
      "geometry": {
        "type": "Point",
        "coordinates": [
          -121,
          39.6167
        ]
      },
      "type": "Feature",
      "properties": {
        "hierarchy": [
          "tgn:2596382",
          "tgn:1000001",
          "tgn:7012149",
          "tgn:7007157",
          "tgn:1002894",
          "tgn:7029392"
        ],
        "placetype": [
          "aat:300008347"
        ],
        "id": 2596382,
        "name:xx": "Poverty Hill"
      }
    },
    {
      "geometry": {
        "type": "Point",
        "coordinates": [
          -120.9667,
          39.6167
        ]
      },
      "type": "Feature",
      "properties": {
        "hierarchy": [
          "tgn:2596383",
          "tgn:1000001",
          "tgn:7012149",
          "tgn:7007157",
          "tgn:1002894",
          "tgn:7029392"
        ],
        "placetype": [
          "aat:300008798"
        ],
        "id": 2596383,
        "name:xx": "Poverty Hill"
      }
    },
    {
      "geometry": {
        "type": "Point",
        "coordinates": [
          -72.1833,
          42.35
        ]
      },
      "type": "Feature",
      "properties": {
        "hierarchy": [
          "tgn:2596384",
          "tgn:1000001",
          "tgn:7012149",
          "tgn:1003038",
          "tgn:7007517",
          "tgn:7029392"
        ],
        "placetype": [
          "aat:300008798"
        ],
        "id": 2596384,
        "name:xx": "Poverty Hill"
      }
    },
    {
      "geometry": {
        "type": "Point",
        "coordinates": [
          -95.7833,
          44.0833
        ]
      },
      "type": "Feature",
      "properties": {
        "hierarchy": [
          "tgn:2596385",
          "tgn:1000001",
          "tgn:7012149",
          "tgn:2001049",
          "tgn:7007521",
          "tgn:7029392"
        ],
        "placetype": [
          "aat:300008798"
        ],
        "id": 2596385,
        "name:xx": "Poverty Hill"
      }
    },
    {
      "geometry": {
        "type": "Point",
        "coordinates": [
          -78.6833,
          42.3
        ]
      },
      "type": "Feature",
      "properties": {
        "hierarchy": [
          "tgn:2596386",
          "tgn:1000001",
          "tgn:1002245",
          "tgn:7012149",
          "tgn:7007568",
          "tgn:7029392"
        ],
        "placetype": [
          "aat:300008798"
        ],
        "id": 2596386,
        "name:xx": "Poverty Hill"
      }
    },
    {
      "geometry": {
        "type": "Point",
        "coordinates": [
          -122.55,
          42.4333
        ]
      },
      "type": "Feature",
      "properties": {
        "hierarchy": [
          "tgn:2596387",
          "tgn:1000001",
          "tgn:7012149",
          "tgn:2001711",
          "tgn:7007708",
          "tgn:7029392"
        ],
        "placetype": [
          "aat:300008798"
        ],
        "id": 2596387,
        "name:xx": "Poverty Hill"
      }
    },
    {
      "geometry": {
        "type": "Point",
        "coordinates": [
          -82,
          33.55
        ]
      },
      "type": "Feature",
      "properties": {
        "hierarchy": [
          "tgn:2596388",
          "tgn:1000001",
          "tgn:7013677",
          "tgn:7012149",
          "tgn:7007712",
          "tgn:7029392"
        ],
        "placetype": [
          "aat:300008347"
        ],
        "id": 2596388,
        "name:xx": "Poverty Hill"
      }
    },
    {
      "geometry": {
        "type": "Point",
        "coordinates": [
          -82,
          33.55
        ]
      },
      "type": "Feature",
      "properties": {
        "hierarchy": [
          "tgn:2596389",
          "tgn:1000001",
          "tgn:7013677",
          "tgn:7012149",
          "tgn:7007712",
          "tgn:7029392"
        ],
        "placetype": [
          "aat:300008798"
        ],
        "id": 2596389,
        "name:xx": "Poverty Hill"
      }
    }
  ]
}
