{
  "geometry": {
    "type": "Point",
    "coordinates": [
      -155.8667,
      19.9333
    ]
  },
  "type": "Feature",
  "properties": {
    "hierarchy": [
      "tgn:2490785",
      "tgn:7023902",
      "tgn:1000001",
      "tgn:7012149",
      "tgn:7007249",
      "tgn:7029392"
    ],
    "placetype": [
      "aat:300008680"
    ],
    "id": 2490785,
    "name:xx": "Manoku Fishpond"
  }
}
