{
  "geometry": {
    "type": "Point",
    "coordinates": [
      -84.8333,
      33.9333
    ]
  },
  "type": "Feature",
  "properties": {
    "hierarchy": [
      "tgn:2246486",
      "tgn:1000001",
      "tgn:7012149",
      "tgn:2000401",
      "tgn:7007248",
      "tgn:7029392"
    ],
    "placetype": [
      "aat:300008347"
    ],
    "id": 2246486,
    "name:xx": "Cobb Estates"
  }
}
