{
  "geometry": {
    "type": "Point",
    "coordinates": [
      -86.0833,
      32.3333
    ]
  },
  "type": "Feature",
  "properties": {
    "hierarchy": [
      "tgn:2004430",
      "tgn:7002659",
      "tgn:1000001",
      "tgn:7012149",
      "tgn:2000050",
      "tgn:7029392"
    ],
    "placetype": [
      "aat:300008347",
      "aat:300387210"
    ],
    "id": 2004430,
    "name:xx": "Merry"
  }
}
