{
  "geometry": {
    "type": "Point",
    "coordinates": [
      -75.1167,
      41.75
    ]
  },
  "type": "Feature",
  "properties": {
    "hierarchy": [
      "tgn:2085852",
      "tgn:1000001",
      "tgn:7012149",
      "tgn:1003008",
      "tgn:7007710",
      "tgn:7029392"
    ],
    "placetype": [
      "aat:300008347",
      "aat:300387210"
    ],
    "id": 2085852,
    "name:xx": "Abrahamsville"
  }
}
