{
  "geometry": {
    "type": "Point",
    "coordinates": [
      -104.0167,
      40.4167
    ]
  },
  "type": "Feature",
  "properties": {
    "hierarchy": [
      "tgn:2215733",
      "tgn:1000001",
      "tgn:7012149",
      "tgn:2000235",
      "tgn:7007158",
      "tgn:7029392"
    ],
    "placetype": [
      "aat:300006191"
    ],
    "id": 2215733,
    "name:xx": "Camden Reservoir"
  }
}
