{
  "geometry": {
    "type": "Point",
    "coordinates": [
      -119.6667,
      48.8333
    ]
  },
  "type": "Feature",
  "properties": {
    "hierarchy": [
      "tgn:2608415",
      "tgn:1000001",
      "tgn:7012149",
      "tgn:1002742",
      "tgn:7007920",
      "tgn:7029392"
    ],
    "placetype": [
      "aat:300008761"
    ],
    "id": 2608415,
    "name:xx": "Rattlesnake Draw"
  }
}
