{
  "geometry": {
    "type": "Point",
    "coordinates": [
      -97.9833,
      37.3833
    ]
  },
  "type": "Feature",
  "properties": {
    "hierarchy": [
      "tgn:2686364",
      "tgn:1000001",
      "tgn:2000698",
      "tgn:7012149",
      "tgn:7007254",
      "tgn:7029392"
    ],
    "placetype": [
      "aat:300008706"
    ],
    "id": 2686364,
    "name:xx": "Spring Creek"
  }
}
