{
  "geometry": {
    "type": "Point",
    "coordinates": [
      -88.0333,
      38.15
    ]
  },
  "type": "Feature",
  "properties": {
    "hierarchy": [
      "tgn:2267975",
      "tgn:1000001",
      "tgn:7012149",
      "tgn:2000537",
      "tgn:7007251",
      "tgn:7029392"
    ],
    "placetype": [
      "aat:300008706"
    ],
    "id": 2267975,
    "name:xx": "Crooked Creek"
  }
}
