{
  "type": "FeatureCollection",
  "features": [
    {
      "geometry": {
        "type": "Point",
        "coordinates": [
          -83.3,
          41.1833
        ]
      },
      "type": "Feature",
      "properties": {
        "hierarchy": [
          "tgn:2658580",
          "tgn:1000001",
          "tgn:7012149",
          "tgn:1002883",
          "tgn:7007706",
          "tgn:7029392"
        ],
        "placetype": [
          "aat:300006075"
        ],
        "id": 2658580,
        "name:xx": "Sherger Ditch"
      }
    },
    {
      "geometry": {
        "type": "Point",
        "coordinates": [
          -83.3167,
          30.85
        ]
      },
      "type": "Feature",
      "properties": {
        "hierarchy": [
          "tgn:2658581",
          "tgn:1000001",
          "tgn:7012149",
          "tgn:2000383",
          "tgn:7007248",
          "tgn:7029392"
        ],
        "placetype": [
          "aat:300006191"
        ],
        "id": 2658581,
        "name:xx": "Sheri, Lake"
      }
    },
    {
      "geometry": {
        "type": "Point",
        "coordinates": [
          -123.0333,
          38.45
        ]
      },
      "type": "Feature",
      "properties": {
        "hierarchy": [
          "tgn:2658582",
          "tgn:1000001",
          "tgn:7012149",
          "tgn:7007157",
          "tgn:7014516",
          "tgn:7029392"
        ],
        "placetype": [
          "aat:300008347"
        ],
        "id": 2658582,
        "name:xx": "Sheridan"
      }
    },
    {
      "geometry": {
        "type": "Point",
        "coordinates": [
          -105.2333,
          35.4833
        ]
      },
      "type": "Feature",
      "properties": {
        "hierarchy": [
          "tgn:2658583",
          "tgn:1000001",
          "tgn:7012149",
          "tgn:2001453",
          "tgn:7007566",
          "tgn:7029392"
        ],
        "placetype": [
          "aat:300008347"
        ],
        "id": 2658583,
        "name:xx": "Sheridan"
      }
    },
    {
      "geometry": {
        "type": "Point",
        "coordinates": [
          -105.25,
          36.6167
        ]
      },
      "type": "Feature",
      "properties": {
        "hierarchy": [
          "tgn:2658584",
          "tgn:1000001",
          "tgn:2001432",
          "tgn:7012149",
          "tgn:7007566",
          "tgn:7029392"
        ],
        "placetype": [
          "aat:300000390"
        ],
        "id": 2658584,
        "name:xx": "Sheridan"
      }
    },
    {
      "geometry": {
        "type": "Point",
        "coordinates": [
          -103.4667,
          43.9667
        ]
      },
      "type": "Feature",
      "properties": {
        "hierarchy": [
          "tgn:2658585",
          "tgn:1000001",
          "tgn:7012149",
          "tgn:2001821",
          "tgn:7007713",
          "tgn:7029392"
        ],
        "placetype": [
          "aat:300008347"
        ],
        "id": 2658585,
        "name:xx": "Sheridan"
      }
    },
    {
      "geometry": {
        "type": "Point",
        "coordinates": [
          -111.8667,
          40.9
        ]
      },
      "type": "Feature",
      "properties": {
        "hierarchy": [
          "tgn:2658586",
          "tgn:1000001",
          "tgn:2002106",
          "tgn:7012149",
          "tgn:7007827",
          "tgn:7029392"
        ],
        "placetype": [
          "aat:300008347"
        ],
        "id": 2658586,
        "name:xx": "Sheridan"
      }
    },
    {
      "geometry": {
        "type": "Point",
        "coordinates": [
          -122.6333,
          47.5833
        ]
      },
      "type": "Feature",
      "properties": {
        "hierarchy": [
          "tgn:2658587",
          "tgn:1000001",
          "tgn:7012149",
          "tgn:1002552",
          "tgn:7007920",
          "tgn:7029392"
        ],
        "placetype": [
          "aat:300008347"
        ],
        "id": 2658587,
        "name:xx": "Sheridan"
      }
    },
    {
      "geometry": {
        "type": "Point",
        "coordinates": [
          -88.1667,
          37.5
        ]
      },
      "type": "Feature",
      "properties": {
        "hierarchy": [
          "tgn:2658588",
          "tgn:1000001",
          "tgn:7012149",
          "tgn:2000509",
          "tgn:7007251",
          "tgn:7029392"
        ],
        "placetype": [
          "aat:300008699"
        ],
        "id": 2658588,
        "name:xx": "Sheridan Branch"
      }
    },
    {
      "geometry": {
        "type": "Point",
        "coordinates": [
          -95.3333,
          31.5167
        ]
      },
      "type": "Feature",
      "properties": {
        "hierarchy": [
          "tgn:2658589",
          "tgn:1000001",
          "tgn:7012149",
          "tgn:1002486",
          "tgn:7007826",
          "tgn:7029392"
        ],
        "placetype": [
          "aat:300008699"
        ],
        "id": 2658589,
        "name:xx": "Sheridan Branch"
      }
    }
  ]
}
