{
  "geometry": {
    "type": "Point",
    "coordinates": [
      85.333264,
      20.813669
    ]
  },
  "type": "Feature",
  "properties": {
    "hierarchy": [
      "tgn:7553508",
      "tgn:1000004",
      "tgn:7000198",
      "tgn:7016694",
      "tgn:7029392"
    ],
    "placetype": [
      "aat:300008699"
    ],
    "name:en": "Nigrā Nadī",
    "id": 7553508
  }
}
