{
  "geometry": {
    "type": "Point",
    "coordinates": [
      -74.25,
      -49.55
    ]
  },
  "type": "Feature",
  "properties": {
    "hierarchy": [
      "tgn:7291219",
      "tgn:1001702",
      "tgn:1000049",
      "tgn:1000002",
      "tgn:7029392"
    ],
    "placetype": [
      "aat:300387499"
    ],
    "id": 7291219,
    "name:xx": "Escarpado, Morro"
  }
}
