{
  "geometry": {
    "type": "Point",
    "coordinates": [
      -108.6667,
      33.9167
    ]
  },
  "type": "Feature",
  "properties": {
    "hierarchy": [
      "tgn:2487046",
      "tgn:1000001",
      "tgn:2001429",
      "tgn:7012149",
      "tgn:7007566",
      "tgn:7029392"
    ],
    "placetype": [
      "aat:300008697"
    ],
    "id": 2487046,
    "name:xx": "Lee Russell Spring"
  }
}
