{
  "geometry": {
    "type": "Point",
    "coordinates": [
      -77.85,
      40.7167
    ]
  },
  "type": "Feature",
  "properties": {
    "hierarchy": [
      "tgn:2655799",
      "tgn:1000001",
      "tgn:7012149",
      "tgn:1002494",
      "tgn:7007710",
      "tgn:7029392"
    ],
    "placetype": [
      "aat:300008706"
    ],
    "id": 2655799,
    "name:xx": "Shaver Creek"
  }
}
