{
  "geometry": {
    "type": "Point",
    "coordinates": [
      -93.65,
      32.3333
    ]
  },
  "type": "Feature",
  "properties": {
    "hierarchy": [
      "tgn:2536348",
      "tgn:1000001",
      "tgn:2000862",
      "tgn:7012149",
      "tgn:7007256",
      "tgn:7029392"
    ],
    "placetype": [
      "aat:300008347"
    ],
    "id": 2536348,
    "name:xx": "Naylor"
  }
}
