{
  "geometry": {
    "type": "Point",
    "coordinates": [
      -71.9667,
      44.5833
    ]
  },
  "type": "Feature",
  "properties": {
    "hierarchy": [
      "tgn:2333524",
      "tgn:2002131",
      "tgn:1000001",
      "tgn:7012149",
      "tgn:7007828",
      "tgn:7029392"
    ],
    "placetype": [
      "aat:300008347"
    ],
    "id": 2333524,
    "name:xx": "Folsom"
  }
}
