{
  "geometry": {
    "type": "Point",
    "coordinates": [
      37.2167,
      40.7333
    ]
  },
  "type": "Feature",
  "properties": {
    "hierarchy": [
      "tgn:1086608",
      "tgn:1001471",
      "tgn:1000004",
      "tgn:7018454",
      "tgn:1000144",
      "tgn:7029392"
    ],
    "placetype": [
      "aat:300008347"
    ],
    "id": 1086608,
    "name:xx": "Korgan"
  }
}
