{
  "geometry": {
    "type": "Point",
    "coordinates": [
      -112.8167,
      42.2833
    ]
  },
  "type": "Feature",
  "properties": {
    "hierarchy": [
      "tgn:2443022",
      "tgn:1000001",
      "tgn:7012149",
      "tgn:2000487",
      "tgn:7007250",
      "tgn:7029392"
    ],
    "placetype": [
      "aat:300008697"
    ],
    "id": 2443022,
    "name:xx": "Kurtz Spring"
  }
}
