{
  "type": "FeatureCollection",
  "features": [
    {
      "geometry": {
        "type": "Point",
        "coordinates": [
          -77.5833,
          41.5333
        ]
      },
      "type": "Feature",
      "properties": {
        "hierarchy": [
          "tgn:2428550",
          "tgn:1000001",
          "tgn:7012149",
          "tgn:1002613",
          "tgn:7007710",
          "tgn:7029392"
        ],
        "placetype": [
          "aat:300008761"
        ],
        "id": 2428550,
        "name:xx": "Jug Hollow"
      }
    },
    {
      "geometry": {
        "type": "Point",
        "coordinates": [
          -87.0167,
          33.3833
        ]
      },
      "type": "Feature",
      "properties": {
        "hierarchy": [
          "tgn:2428551",
          "tgn:7002659",
          "tgn:1000001",
          "tgn:7012149",
          "tgn:2000036",
          "tgn:7029392"
        ],
        "placetype": [
          "aat:300006191"
        ],
        "id": 2428551,
        "name:xx": "Jug Hollow Lake"
      }
    },
    {
      "geometry": {
        "type": "Point",
        "coordinates": [
          -135.4167,
          56.7833
        ]
      },
      "type": "Feature",
      "properties": {
        "hierarchy": [
          "tgn:2428552",
          "tgn:7006450",
          "tgn:1000001",
          "tgn:7012149",
          "tgn:2124002",
          "tgn:7029392"
        ],
        "placetype": [
          "aat:300008791"
        ],
        "id": 2428552,
        "name:xx": "Jug Island"
      }
    },
    {
      "geometry": {
        "type": "Point",
        "coordinates": [
          -152.4167,
          57.6333
        ]
      },
      "type": "Feature",
      "properties": {
        "hierarchy": [
          "tgn:2428553",
          "tgn:7006450",
          "tgn:1000001",
          "tgn:2124012",
          "tgn:7012149",
          "tgn:7029392"
        ],
        "placetype": [
          "aat:300008791"
        ],
        "id": 2428553,
        "name:xx": "Jug Island"
      }
    },
    {
      "geometry": {
        "type": "Point",
        "coordinates": [
          -80.8,
          27.9667
        ]
      },
      "type": "Feature",
      "properties": {
        "hierarchy": [
          "tgn:2428554",
          "tgn:1000001",
          "tgn:1002200",
          "tgn:7012149",
          "tgn:7007240",
          "tgn:7029392"
        ],
        "placetype": [
          "aat:300008791"
        ],
        "id": 2428554,
        "name:xx": "Jug Island"
      }
    },
    {
      "geometry": {
        "type": "Point",
        "coordinates": [
          -92.65,
          48.4167
        ]
      },
      "type": "Feature",
      "properties": {
        "hierarchy": [
          "tgn:2428555",
          "tgn:1000001",
          "tgn:7012149",
          "tgn:2001067",
          "tgn:7007521",
          "tgn:7029392"
        ],
        "placetype": [
          "aat:300008791"
        ],
        "id": 2428555,
        "name:xx": "Jug Island"
      }
    },
    {
      "geometry": {
        "type": "Point",
        "coordinates": [
          -75.8167,
          44.4167
        ]
      },
      "type": "Feature",
      "properties": {
        "hierarchy": [
          "tgn:2428556",
          "tgn:1000001",
          "tgn:7012149",
          "tgn:7016021",
          "tgn:7007568",
          "tgn:7029392"
        ],
        "placetype": [
          "aat:300008791"
        ],
        "id": 2428556,
        "name:xx": "Jug Island"
      }
    },
    {
      "geometry": {
        "type": "Point",
        "coordinates": [
          -81.9,
          28.9167
        ]
      },
      "type": "Feature",
      "properties": {
        "hierarchy": [
          "tgn:2428557",
          "tgn:1000001",
          "tgn:7012149",
          "tgn:1002567",
          "tgn:7007240",
          "tgn:7029392"
        ],
        "placetype": [
          "aat:300008680"
        ],
        "id": 2428557,
        "name:xx": "Jug Lake"
      }
    },
    {
      "geometry": {
        "type": "Point",
        "coordinates": [
          -81.6,
          31.4333
        ]
      },
      "type": "Feature",
      "properties": {
        "hierarchy": [
          "tgn:2428558",
          "tgn:1000001",
          "tgn:7012149",
          "tgn:2000386",
          "tgn:7007248",
          "tgn:7029392"
        ],
        "placetype": [
          "aat:300008680"
        ],
        "id": 2428558,
        "name:xx": "Jug Lake"
      }
    },
    {
      "geometry": {
        "type": "Point",
        "coordinates": [
          -90.9333,
          29.3667
        ]
      },
      "type": "Feature",
      "properties": {
        "hierarchy": [
          "tgn:2428559",
          "tgn:1000001",
          "tgn:7012149",
          "tgn:2000908",
          "tgn:7007256",
          "tgn:7029392"
        ],
        "placetype": [
          "aat:300008680"
        ],
        "id": 2428559,
        "name:xx": "Jug Lake"
      }
    }
  ]
}
