{
  "geometry": {
    "type": "Point",
    "coordinates": [
      -120.1333,
      34.8833
    ]
  },
  "type": "Feature",
  "properties": {
    "hierarchy": [
      "tgn:2287522",
      "tgn:1000001",
      "tgn:7012149",
      "tgn:7007157",
      "tgn:1002867",
      "tgn:7029392"
    ],
    "placetype": [
      "aat:300008697"
    ],
    "id": 2287522,
    "name:xx": "Difficult Spring"
  }
}
