{
  "geometry": {
    "type": "Point",
    "coordinates": [
      -79.6667,
      39.0167
    ]
  },
  "type": "Feature",
  "properties": {
    "hierarchy": [
      "tgn:2219613",
      "tgn:1000001",
      "tgn:7012149",
      "tgn:2002296",
      "tgn:7013961",
      "tgn:7029392"
    ],
    "placetype": [
      "aat:300008699"
    ],
    "id": 2219613,
    "name:xx": "Canoe Run"
  }
}
