{
  "geometry": {
    "type": "Point",
    "coordinates": [
      17.7667,
      60.4667
    ]
  },
  "type": "Feature",
  "properties": {
    "hierarchy": [
      "tgn:1063586",
      "tgn:1000003",
      "tgn:1000462",
      "tgn:1000097",
      "tgn:7029392"
    ],
    "placetype": [
      "aat:300008347"
    ],
    "id": 1063586,
    "name:xx": "Skärplinge"
  }
}
