{
  "geometry": {
    "type": "Point",
    "coordinates": [
      -117.5333,
      48.7667
    ]
  },
  "type": "Feature",
  "properties": {
    "hierarchy": [
      "tgn:2458364",
      "tgn:1000001",
      "tgn:7012149",
      "tgn:2002248",
      "tgn:7007920",
      "tgn:7029392"
    ],
    "placetype": [
      "aat:300008706"
    ],
    "id": 2458364,
    "name:xx": "Little Muddy Creek"
  }
}
