{
  "geometry": {
    "type": "Point",
    "coordinates": [
      -84.7667,
      40.1667
    ]
  },
  "type": "Feature",
  "properties": {
    "hierarchy": [
      "tgn:2079978",
      "tgn:1000001",
      "tgn:1002317",
      "tgn:7012149",
      "tgn:7007706",
      "tgn:7029392"
    ],
    "placetype": [
      "aat:300008347"
    ],
    "id": 2079978,
    "name:xx": "Hill Grove"
  }
}
