{
  "geometry": {
    "type": "Point",
    "coordinates": [
      -91.891667,
      18.35
    ]
  },
  "type": "Feature",
  "properties": {
    "hierarchy": [
      "tgn:7407155",
      "tgn:7005578",
      "tgn:1000001",
      "tgn:7005560",
      "tgn:7029392"
    ],
    "placetype": [
      "aat:300008680"
    ],
    "id": 7407155,
    "name:xx": "Lagón Dulce, Laguna"
  }
}
