{
  "geometry": {
    "type": "Point",
    "coordinates": [
      -86.5833,
      31.35
    ]
  },
  "type": "Feature",
  "properties": {
    "hierarchy": [
      "tgn:2594668",
      "tgn:7002659",
      "tgn:1000001",
      "tgn:2000019",
      "tgn:7012149",
      "tgn:7029392"
    ],
    "placetype": [
      "aat:300006191"
    ],
    "id": 2594668,
    "name:xx": "Posey Pond"
  }
}
