{
  "geometry": {
    "type": "Point",
    "coordinates": [
      -5.65,
      40.15
    ]
  },
  "type": "Feature",
  "properties": {
    "hierarchy": [
      "tgn:7330631",
      "tgn:7002811",
      "tgn:1000003",
      "tgn:7003837",
      "tgn:1000095",
      "tgn:7029392"
    ],
    "placetype": [
      "aat:300008347"
    ],
    "id": 7330631,
    "name:xx": "Guijo de Santa Bárbara"
  }
}
