{
  "geometry": {
    "type": "Point",
    "coordinates": [
      -121.55,
      48.05
    ]
  },
  "type": "Feature",
  "properties": {
    "hierarchy": [
      "tgn:2491953",
      "tgn:1000001",
      "tgn:7012149",
      "tgn:1002899",
      "tgn:7007920",
      "tgn:7029392"
    ],
    "placetype": [
      "aat:300008798"
    ],
    "id": 2491953,
    "name:xx": "Marble Peak"
  }
}
