{
  "geometry": {
    "type": "Point",
    "coordinates": [
      -107.0333,
      39.8833
    ]
  },
  "type": "Feature",
  "properties": {
    "hierarchy": [
      "tgn:2281573",
      "tgn:1000001",
      "tgn:7012149",
      "tgn:2000210",
      "tgn:7007158",
      "tgn:7029392"
    ],
    "placetype": [
      "aat:300008706"
    ],
    "id": 2281573,
    "name:xx": "Deer Creek"
  }
}
