{
  "geometry": {
    "type": "Point",
    "coordinates": [
      -121.15,
      47.3167
    ]
  },
  "type": "Feature",
  "properties": {
    "hierarchy": [
      "tgn:2340601",
      "tgn:1000001",
      "tgn:7012149",
      "tgn:1002553",
      "tgn:7007920",
      "tgn:7029392"
    ],
    "placetype": [
      "aat:300008798"
    ],
    "id": 2340601,
    "name:xx": "Frenchman Mountain"
  }
}
