{
  "geometry": {
    "type": "Point",
    "coordinates": [
      118.1667,
      51.3667
    ]
  },
  "type": "Feature",
  "properties": {
    "hierarchy": [
      "tgn:1055169",
      "tgn:1003351",
      "tgn:1000004",
      "tgn:7018214",
      "tgn:7002435",
      "tgn:7029392"
    ],
    "placetype": [
      "aat:300008347"
    ],
    "id": 1055169,
    "name:xx": "Kavykuči-Gazimurskije"
  }
}
