{
  "type": "FeatureCollection",
  "features": [
    {
      "geometry": {
        "type": "Point",
        "coordinates": [
          -80.85,
          36.0167
        ]
      },
      "type": "Feature",
      "properties": {
        "hierarchy": [
          "tgn:2077000",
          "tgn:1000001",
          "tgn:7012149",
          "tgn:2001507",
          "tgn:7007709",
          "tgn:7029392"
        ],
        "placetype": [
          "aat:300008347"
        ],
        "id": 2077000,
        "name:xx": "Union Grove"
      }
    },
    {
      "geometry": {
        "type": "Point",
        "coordinates": [
          -80.4667,
          36.2333
        ]
      },
      "type": "Feature",
      "properties": {
        "hierarchy": [
          "tgn:2077002",
          "tgn:1000001",
          "tgn:7012149",
          "tgn:2001555",
          "tgn:7007709",
          "tgn:7029392"
        ],
        "placetype": [
          "aat:300008347",
          "aat:300387210"
        ],
        "id": 2077002,
        "name:xx": "Union Hill"
      }
    },
    {
      "geometry": {
        "type": "Point",
        "coordinates": [
          -81.95,
          35.4833
        ]
      },
      "type": "Feature",
      "properties": {
        "hierarchy": [
          "tgn:2077003",
          "tgn:1000001",
          "tgn:7012149",
          "tgn:2001537",
          "tgn:7007709",
          "tgn:7029392"
        ],
        "placetype": [
          "aat:300008347"
        ],
        "id": 2077003,
        "name:xx": "Union Mills"
      }
    },
    {
      "geometry": {
        "type": "Point",
        "coordinates": [
          -79.4,
          36.2
        ]
      },
      "type": "Feature",
      "properties": {
        "hierarchy": [
          "tgn:2077004",
          "tgn:2001463",
          "tgn:1000001",
          "tgn:7012149",
          "tgn:7007709",
          "tgn:7029392"
        ],
        "placetype": [
          "aat:300008347",
          "aat:300387210"
        ],
        "id": 2077004,
        "name:xx": "Union Ridge"
      }
    },
    {
      "geometry": {
        "type": "Point",
        "coordinates": [
          -80.5,
          35.0833
        ]
      },
      "type": "Feature",
      "properties": {
        "hierarchy": [
          "tgn:2077005",
          "tgn:1000001",
          "tgn:7012149",
          "tgn:2001546",
          "tgn:7007709",
          "tgn:7029392"
        ],
        "placetype": [
          "aat:300008347"
        ],
        "id": 2077005,
        "name:xx": "Unionville"
      }
    },
    {
      "geometry": {
        "type": "Point",
        "coordinates": [
          -79.7,
          36.3833
        ]
      },
      "type": "Feature",
      "properties": {
        "hierarchy": [
          "tgn:2077006",
          "tgn:1000001",
          "tgn:7012149",
          "tgn:2001535",
          "tgn:7007709",
          "tgn:7029392"
        ],
        "placetype": [
          "aat:300008347"
        ],
        "id": 2077006,
        "name:xx": "University Estates"
      }
    },
    {
      "geometry": {
        "type": "Point",
        "coordinates": [
          -78.9167,
          35.1
        ]
      },
      "type": "Feature",
      "properties": {
        "hierarchy": [
          "tgn:2077007",
          "tgn:1000001",
          "tgn:7012149",
          "tgn:2001487",
          "tgn:7007709",
          "tgn:7029392"
        ],
        "placetype": [
          "aat:300008347"
        ],
        "id": 2077007,
        "name:xx": "University Estates"
      }
    },
    {
      "geometry": {
        "type": "Point",
        "coordinates": [
          -78.85,
          35.7833
        ]
      },
      "type": "Feature",
      "properties": {
        "hierarchy": [
          "tgn:2077008",
          "tgn:1000001",
          "tgn:7012149",
          "tgn:2001548",
          "tgn:7007709",
          "tgn:7029392"
        ],
        "placetype": [
          "aat:300008347",
          "aat:300387210"
        ],
        "id": 2077008,
        "name:xx": "Upchurch"
      }
    },
    {
      "geometry": {
        "type": "Point",
        "coordinates": [
          -83.9,
          35.1
        ]
      },
      "type": "Feature",
      "properties": {
        "hierarchy": [
          "tgn:2077009",
          "tgn:1000001",
          "tgn:2001481",
          "tgn:7012149",
          "tgn:7007709",
          "tgn:7029392"
        ],
        "placetype": [
          "aat:300008347",
          "aat:300387210"
        ],
        "id": 2077009,
        "name:xx": "Upper Peachtree"
      }
    }
  ]
}
