{
  "geometry": {
    "type": "Point",
    "coordinates": [
      -122.95,
      49.3833
    ]
  },
  "type": "Feature",
  "properties": {
    "hierarchy": [
      "tgn:1102599",
      "tgn:7005735",
      "tgn:7005685",
      "tgn:1000001",
      "tgn:7029392"
    ],
    "placetype": [
      "aat:300008195"
    ],
    "id": 1102599,
    "name:xx": "Mount Seymour Provincial Park"
  }
}
