{
  "geometry": {
    "type": "Point",
    "coordinates": [
      -119.3833,
      37.2167
    ]
  },
  "type": "Feature",
  "properties": {
    "hierarchy": [
      "tgn:2243420",
      "tgn:1000001",
      "tgn:7012149",
      "tgn:7007157",
      "tgn:1002621",
      "tgn:7029392"
    ],
    "placetype": [
      "aat:300008706"
    ],
    "id": 2243420,
    "name:xx": "Clearwater Creek"
  }
}
