{
  "type": "FeatureCollection",
  "features": [
    {
      "geometry": {
        "type": "Point",
        "coordinates": [
          169.033333,
          -46.6
        ]
      },
      "type": "Feature",
      "properties": {
        "hierarchy": [
          "tgn:7514791",
          "tgn:1009227",
          "tgn:1000226",
          "tgn:7016822",
          "tgn:1000006",
          "tgn:7029392"
        ],
        "placetype": [
          "aat:300008795"
        ],
        "name:en": "Darby, Mount",
        "id": 7514791
      }
    },
    {
      "geometry": {
        "type": "Point",
        "coordinates": [
          167.616667,
          -45.216667
        ]
      },
      "type": "Feature",
      "properties": {
        "hierarchy": [
          "tgn:7514792",
          "tgn:1009227",
          "tgn:1000226",
          "tgn:7016822",
          "tgn:1000006",
          "tgn:7029392"
        ],
        "placetype": [
          "aat:300008798"
        ],
        "name:en": "Dara Peaks",
        "id": 7514792
      }
    },
    {
      "geometry": {
        "type": "Point",
        "coordinates": [
          166.566667,
          -48
        ]
      },
      "type": "Feature",
      "properties": {
        "hierarchy": [
          "tgn:7514793",
          "tgn:1009227",
          "tgn:1000226",
          "tgn:7016822",
          "tgn:1000006",
          "tgn:7029392"
        ],
        "placetype": [
          "aat:300011692"
        ],
        "name:en": "Daption Rocks",
        "id": 7514793
      }
    },
    {
      "geometry": {
        "type": "Point",
        "coordinates": [
          170.366667,
          -44.95
        ]
      },
      "type": "Feature",
      "properties": {
        "hierarchy": [
          "tgn:7514794",
          "tgn:1009227",
          "tgn:1000226",
          "tgn:7018437",
          "tgn:1000006",
          "tgn:7029392"
        ],
        "placetype": [
          "aat:300259572"
        ],
        "name:en": "Dansey Pass",
        "id": 7514794
      }
    },
    {
      "geometry": {
        "type": "Point",
        "coordinates": [
          170.416667,
          -44.95
        ]
      },
      "type": "Feature",
      "properties": {
        "hierarchy": [
          "tgn:7514795",
          "tgn:1009227",
          "tgn:1000226",
          "tgn:7018437",
          "tgn:1000006",
          "tgn:7029392"
        ],
        "placetype": [
          "aat:300008699"
        ],
        "name:en": "Dansey Creek",
        "id": 7514795
      }
    },
    {
      "geometry": {
        "type": "Point",
        "coordinates": [
          172.616667,
          -42.316667
        ]
      },
      "type": "Feature",
      "properties": {
        "hierarchy": [
          "tgn:7514796",
          "tgn:1009227",
          "tgn:7001866",
          "tgn:1000226",
          "tgn:1000006",
          "tgn:7029392"
        ],
        "placetype": [
          "aat:300008699"
        ],
        "name:en": "Danns Stream",
        "id": 7514796
      }
    }
  ]
}
