{
  "type": "FeatureCollection",
  "features": [
    {
      "geometry": {
        "type": "Point",
        "coordinates": [
          138.8,
          36.3167
        ]
      },
      "type": "Feature",
      "properties": {
        "hierarchy": [
          "tgn:1080740",
          "tgn:1000980",
          "tgn:1000004",
          "tgn:7000894",
          "tgn:1000120",
          "tgn:7029392"
        ],
        "placetype": [
          "aat:300008347"
        ],
        "id": 1080740,
        "name:xx": "Matsuida"
      }
    },
    {
      "geometry": {
        "type": "Point",
        "coordinates": [
          137.9167,
          35.6
        ]
      },
      "type": "Feature",
      "properties": {
        "hierarchy": [
          "tgn:1080741",
          "tgn:7000895",
          "tgn:1000004",
          "tgn:1001010",
          "tgn:1000120",
          "tgn:7029392"
        ],
        "placetype": [
          "aat:300008347"
        ],
        "id": 1080741,
        "name:xx": "Matsukawa"
      }
    },
    {
      "geometry": {
        "type": "Point",
        "coordinates": [
          132.7,
          33.2167
        ]
      },
      "type": "Feature",
      "properties": {
        "hierarchy": [
          "tgn:1080744",
          "tgn:7004473",
          "tgn:1000004",
          "tgn:7000903",
          "tgn:1000120",
          "tgn:7029392"
        ],
        "placetype": [
          "aat:300008347"
        ],
        "id": 1080744,
        "name:xx": "Matsuno"
      }
    },
    {
      "geometry": {
        "type": "Point",
        "coordinates": [
          138.6167,
          37.0833
        ]
      },
      "type": "Feature",
      "properties": {
        "hierarchy": [
          "tgn:1080745",
          "tgn:7000895",
          "tgn:1000004",
          "tgn:1001014",
          "tgn:1000120",
          "tgn:7029392"
        ],
        "placetype": [
          "aat:300008347"
        ],
        "id": 1080745,
        "name:xx": "Matsunoyama"
      }
    },
    {
      "geometry": {
        "type": "Point",
        "coordinates": [
          140.4667,
          35.6333
        ]
      },
      "type": "Feature",
      "properties": {
        "hierarchy": [
          "tgn:1080746",
          "tgn:1000971",
          "tgn:1000004",
          "tgn:7000894",
          "tgn:1000120",
          "tgn:7029392"
        ],
        "placetype": [
          "aat:300008347"
        ],
        "id": 1080746,
        "name:xx": "Matsuo"
      }
    },
    {
      "geometry": {
        "type": "Point",
        "coordinates": [
          136.3,
          36.0833
        ]
      },
      "type": "Feature",
      "properties": {
        "hierarchy": [
          "tgn:1080747",
          "tgn:7000895",
          "tgn:1000004",
          "tgn:1000974",
          "tgn:1000120",
          "tgn:7029392"
        ],
        "placetype": [
          "aat:300008347"
        ],
        "id": 1080747,
        "name:xx": "Matsuoka"
      }
    },
    {
      "geometry": {
        "type": "Point",
        "coordinates": [
          136.5333,
          34.5667
        ]
      },
      "type": "Feature",
      "properties": {
        "hierarchy": [
          "tgn:1080748",
          "tgn:1000004",
          "tgn:1001007",
          "tgn:7000896",
          "tgn:1000120",
          "tgn:7029392"
        ],
        "placetype": [
          "aat:300008347"
        ],
        "id": 1080748,
        "name:xx": "Matsusaka"
      }
    },
    {
      "geometry": {
        "type": "Point",
        "coordinates": [
          141.0667,
          38.3667
        ]
      },
      "type": "Feature",
      "properties": {
        "hierarchy": [
          "tgn:1080749",
          "tgn:7016745",
          "tgn:1000004",
          "tgn:7000893",
          "tgn:1000120",
          "tgn:7029392"
        ],
        "placetype": [
          "aat:300008347"
        ],
        "id": 1080749,
        "name:xx": "Matsushima"
      }
    }
  ]
}
