{
  "geometry": {
    "type": "Point",
    "coordinates": [
      -106.75,
      37.8833
    ]
  },
  "type": "Feature",
  "properties": {
    "hierarchy": [
      "tgn:2679863",
      "tgn:1000001",
      "tgn:7012149",
      "tgn:7007158",
      "tgn:2000246",
      "tgn:7029392"
    ],
    "placetype": [
      "aat:300008706"
    ],
    "id": 2679863,
    "name:xx": "South Fork Saguache Creek"
  }
}
