{
  "geometry": {
    "type": "Point",
    "coordinates": [
      -75.6667,
      44.5667
    ]
  },
  "type": "Feature",
  "properties": {
    "hierarchy": [
      "tgn:2396371",
      "tgn:1000001",
      "tgn:7012149",
      "tgn:7016021",
      "tgn:7007568",
      "tgn:7029392"
    ],
    "placetype": [
      "aat:300008850"
    ],
    "id": 2396371,
    "name:xx": "Holmes Point"
  }
}
