{
  "geometry": {
    "type": "Point",
    "coordinates": [
      21.95,
      38.783333
    ]
  },
  "type": "Feature",
  "properties": {
    "hierarchy": [
      "tgn:7223429",
      "tgn:4003773",
      "tgn:7001395",
      "tgn:1000003",
      "tgn:1000074",
      "tgn:7029392"
    ],
    "placetype": [
      "aat:300008795"
    ],
    "id": 7223429,
    "name:xx": "Oxiá Óros"
  }
}
