{
  "geometry": {
    "type": "Point",
    "coordinates": [
      -135.5833,
      57.5667
    ]
  },
  "type": "Feature",
  "properties": {
    "hierarchy": [
      "tgn:2741574",
      "tgn:7006450",
      "tgn:1000001",
      "tgn:7012149",
      "tgn:2124002",
      "tgn:7029392"
    ],
    "placetype": [
      "aat:300008850"
    ],
    "id": 2741574,
    "name:xx": "Ushk Point"
  }
}
