{
  "geometry": {
    "type": "Point",
    "coordinates": [
      30.904238,
      28.850226
    ]
  },
  "type": "Feature",
  "properties": {
    "hierarchy": [
      "tgn:7533830",
      "tgn:7001242",
      "tgn:7016833",
      "tgn:1001142",
      "tgn:7029392"
    ],
    "placetype": [
      "aat:300008347"
    ],
    "name:en": "Ḩannā",
    "id": 7533830
  }
}
