{
  "type": "FeatureCollection",
  "features": [
    {
      "geometry": {
        "type": "Point",
        "coordinates": [
          -122.7333,
          45.3167
        ]
      },
      "type": "Feature",
      "properties": {
        "hierarchy": [
          "tgn:2341500",
          "tgn:1000001",
          "tgn:1002270",
          "tgn:7012149",
          "tgn:7007708",
          "tgn:7029392"
        ],
        "placetype": [
          "aat:300008347"
        ],
        "id": 2341500,
        "name:xx": "Frog Pond"
      }
    },
    {
      "geometry": {
        "type": "Point",
        "coordinates": [
          -79.65,
          40.2667
        ]
      },
      "type": "Feature",
      "properties": {
        "hierarchy": [
          "tgn:2341501",
          "tgn:1000001",
          "tgn:7012149",
          "tgn:1003017",
          "tgn:7007710",
          "tgn:7029392"
        ],
        "placetype": [
          "aat:300006191"
        ],
        "id": 2341501,
        "name:xx": "Frog Pond"
      }
    },
    {
      "geometry": {
        "type": "Point",
        "coordinates": [
          -87.2167,
          36.1167
        ]
      },
      "type": "Feature",
      "properties": {
        "hierarchy": [
          "tgn:2341502",
          "tgn:1000001",
          "tgn:7012149",
          "tgn:2001858",
          "tgn:7007825",
          "tgn:7029392"
        ],
        "placetype": [
          "aat:300008347"
        ],
        "id": 2341502,
        "name:xx": "Frog Pond"
      }
    },
    {
      "geometry": {
        "type": "Point",
        "coordinates": [
          -85.9667,
          36.5333
        ]
      },
      "type": "Feature",
      "properties": {
        "hierarchy": [
          "tgn:2341503",
          "tgn:1000001",
          "tgn:7012149",
          "tgn:2001892",
          "tgn:7007825",
          "tgn:7029392"
        ],
        "placetype": [
          "aat:300008347"
        ],
        "id": 2341503,
        "name:xx": "Frog Pond"
      }
    },
    {
      "geometry": {
        "type": "Point",
        "coordinates": [
          -95.3333,
          30.2
        ]
      },
      "type": "Feature",
      "properties": {
        "hierarchy": [
          "tgn:2341504",
          "tgn:1000001",
          "tgn:7012149",
          "tgn:1002691",
          "tgn:7007826",
          "tgn:7029392"
        ],
        "placetype": [
          "aat:300008905"
        ],
        "id": 2341504,
        "name:xx": "Frog Pond"
      }
    },
    {
      "geometry": {
        "type": "Point",
        "coordinates": [
          -80.4167,
          39.6167
        ]
      },
      "type": "Feature",
      "properties": {
        "hierarchy": [
          "tgn:2341505",
          "tgn:1000001",
          "tgn:7012149",
          "tgn:2002275",
          "tgn:7013961",
          "tgn:7029392"
        ],
        "placetype": [
          "aat:300006191"
        ],
        "id": 2341505,
        "name:xx": "Frog Pond"
      }
    },
    {
      "geometry": {
        "type": "Point",
        "coordinates": [
          -106.6333,
          44.2333
        ]
      },
      "type": "Feature",
      "properties": {
        "hierarchy": [
          "tgn:2341506",
          "tgn:1000001",
          "tgn:7012149",
          "tgn:2002374",
          "tgn:7007923",
          "tgn:7029392"
        ],
        "placetype": [
          "aat:300008680"
        ],
        "id": 2341506,
        "name:xx": "Frog Pond"
      }
    },
    {
      "geometry": {
        "type": "Point",
        "coordinates": [
          -116.9167,
          45.8833
        ]
      },
      "type": "Feature",
      "properties": {
        "hierarchy": [
          "tgn:2341507",
          "tgn:1000001",
          "tgn:7012149",
          "tgn:2001722",
          "tgn:7007708",
          "tgn:7029392"
        ],
        "placetype": [
          "aat:300008798"
        ],
        "id": 2341507,
        "name:xx": "Frog Pond Butte"
      }
    },
    {
      "geometry": {
        "type": "Point",
        "coordinates": [
          -77.95,
          39.45
        ]
      },
      "type": "Feature",
      "properties": {
        "hierarchy": [
          "tgn:2341508",
          "tgn:1000001",
          "tgn:2002254",
          "tgn:7012149",
          "tgn:7013961",
          "tgn:7029392"
        ],
        "placetype": [
          "aat:300008746"
        ],
        "id": 2341508,
        "name:xx": "Frog Pond Cave"
      }
    },
    {
      "geometry": {
        "type": "Point",
        "coordinates": [
          -100.0167,
          31.1833
        ]
      },
      "type": "Feature",
      "properties": {
        "hierarchy": [
          "tgn:2341509",
          "tgn:1000001",
          "tgn:7012149",
          "tgn:2001963",
          "tgn:7007826",
          "tgn:7029392"
        ],
        "placetype": [
          "aat:300008706"
        ],
        "id": 2341509,
        "name:xx": "Frog Pond Creek"
      }
    }
  ]
}
