{
  "geometry": {
    "type": "Point",
    "coordinates": [
      -61.3667,
      15.2167
    ]
  },
  "type": "Feature",
  "properties": {
    "hierarchy": [
      "tgn:1113845",
      "tgn:7014982",
      "tgn:1000001",
      "tgn:7004641",
      "tgn:7029392"
    ],
    "placetype": [
      "aat:300132316"
    ],
    "id": 1113845,
    "name:xx": "Soufrière Bay"
  }
}
