{
  "geometry": {
    "type": "Point",
    "coordinates": [
      -121.2667,
      48.95
    ]
  },
  "type": "Feature",
  "properties": {
    "hierarchy": [
      "tgn:2284318",
      "tgn:1000001",
      "tgn:7012149",
      "tgn:1003020",
      "tgn:7007920",
      "tgn:7029392"
    ],
    "placetype": [
      "aat:300008706"
    ],
    "id": 2284318,
    "name:xx": "Depot Creek"
  }
}
