{
  "geometry": {
    "type": "Point",
    "coordinates": [
      -113.2667,
      38.4667
    ]
  },
  "type": "Feature",
  "properties": {
    "hierarchy": [
      "tgn:2341201",
      "tgn:2002101",
      "tgn:1000001",
      "tgn:7012149",
      "tgn:7007827",
      "tgn:7029392"
    ],
    "placetype": [
      "aat:300000390"
    ],
    "id": 2341201,
    "name:xx": "Frisco Contact Mine"
  }
}
