{
  "geometry": {
    "type": "Point",
    "coordinates": [
      -80.95,
      38.2833
    ]
  },
  "type": "Feature",
  "properties": {
    "hierarchy": [
      "tgn:2120561",
      "tgn:1000001",
      "tgn:7012149",
      "tgn:2002284",
      "tgn:7013961",
      "tgn:7029392"
    ],
    "placetype": [
      "aat:300008347",
      "aat:300387210"
    ],
    "id": 2120561,
    "name:xx": "Zela"
  }
}
