{
  "geometry": {
    "type": "Point",
    "coordinates": [
      -76.1333,
      44.2333
    ]
  },
  "type": "Feature",
  "properties": {
    "hierarchy": [
      "tgn:2567567",
      "tgn:1000001",
      "tgn:7012149",
      "tgn:1002518",
      "tgn:7007568",
      "tgn:7029392"
    ],
    "placetype": [
      "aat:300008791"
    ],
    "id": 2567567,
    "name:xx": "Papoose Island"
  }
}
