{
  "geometry": {
    "type": "Point",
    "coordinates": [
      -74.85,
      42.1833
    ]
  },
  "type": "Feature",
  "properties": {
    "hierarchy": [
      "tgn:2667253",
      "tgn:1000001",
      "tgn:1002328",
      "tgn:7012149",
      "tgn:7007568",
      "tgn:7029392"
    ],
    "placetype": [
      "aat:300008761"
    ],
    "id": 2667253,
    "name:xx": "Skink Hollow"
  }
}
