{
  "type": "FeatureCollection",
  "features": [
    {
      "geometry": {
        "type": "Point",
        "coordinates": [
          14.95,
          -26.1167
        ]
      },
      "type": "Feature",
      "properties": {
        "hierarchy": [
          "tgn:1113151",
          "tgn:7001242",
          "tgn:7030585",
          "tgn:1000198",
          "tgn:7029392"
        ],
        "placetype": [
          "aat:300132316"
        ],
        "id": 1113151,
        "name:xx": "Hottentotsbaai"
      }
    },
    {
      "geometry": {
        "type": "Point",
        "coordinates": [
          -5.6,
          57.133333
        ]
      },
      "type": "Feature",
      "properties": {
        "hierarchy": [
          "tgn:1113152",
          "tgn:7002444",
          "tgn:1000003",
          "tgn:7008082",
          "tgn:7008591",
          "tgn:7029392"
        ],
        "placetype": [
          "aat:300132316"
        ],
        "name:en": "Hourn, Loch",
        "id": 1113152
      }
    },
    {
      "geometry": {
        "type": "Point",
        "coordinates": [
          -70.9,
          42.2833
        ]
      },
      "type": "Feature",
      "properties": {
        "hierarchy": [
          "tgn:1113154",
          "tgn:1000001",
          "tgn:7014423",
          "tgn:7012149",
          "tgn:7007517",
          "tgn:7029392"
        ],
        "placetype": [
          "aat:300132316"
        ],
        "id": 1113154,
        "name:xx": "Hull Bay"
      }
    },
    {
      "geometry": {
        "type": "Point",
        "coordinates": [
          -124.2,
          40.75
        ]
      },
      "type": "Feature",
      "properties": {
        "hierarchy": [
          "tgn:1113156",
          "tgn:1000001",
          "tgn:7012149",
          "tgn:2000181",
          "tgn:7007157",
          "tgn:7029392"
        ],
        "placetype": [
          "aat:300132316"
        ],
        "id": 1113156,
        "name:xx": "Humboldt Bay"
      }
    },
    {
      "geometry": {
        "type": "Point",
        "coordinates": [
          -73.4167,
          40.9167
        ]
      },
      "type": "Feature",
      "properties": {
        "hierarchy": [
          "tgn:1113158",
          "tgn:1000001",
          "tgn:7012149",
          "tgn:1002924",
          "tgn:7007568",
          "tgn:7029392"
        ],
        "placetype": [
          "aat:300132316"
        ],
        "id": 1113158,
        "name:xx": "Huntington Bay"
      }
    },
    {
      "geometry": {
        "type": "Point",
        "coordinates": [
          -6.866667,
          56.483333
        ]
      },
      "type": "Feature",
      "properties": {
        "hierarchy": [
          "tgn:1113159",
          "tgn:7019094",
          "tgn:7002444",
          "tgn:1000003",
          "tgn:7008591",
          "tgn:7009076",
          "tgn:7029392"
        ],
        "placetype": [
          "aat:300132316"
        ],
        "name:en": "Hynish Bay",
        "id": 1113159
      }
    }
  ]
}
