{
  "geometry": {
    "type": "Point",
    "coordinates": [
      79.9489,
      27.011
    ]
  },
  "type": "Feature",
  "properties": {
    "hierarchy": [
      "tgn:7559606",
      "tgn:1000004",
      "tgn:7000198",
      "tgn:7016722",
      "tgn:7029392"
    ],
    "placetype": [
      "aat:300008347"
    ],
    "name:en": "Bahādurpur Ujena",
    "id": 7559606
  }
}
