{
  "geometry": {
    "type": "Point",
    "coordinates": [
      -97.85,
      30.65
    ]
  },
  "type": "Feature",
  "properties": {
    "hierarchy": [
      "tgn:2682951",
      "tgn:1000001",
      "tgn:7012149",
      "tgn:1003026",
      "tgn:7007826",
      "tgn:7029392"
    ],
    "placetype": [
      "aat:300008699"
    ],
    "id": 2682951,
    "name:xx": "Sowes Branch"
  }
}
