{
  "geometry": {
    "type": "Point",
    "coordinates": [
      133.05,
      35.0667
    ]
  },
  "type": "Feature",
  "properties": {
    "hierarchy": [
      "tgn:1104493",
      "tgn:7016674",
      "tgn:1000004",
      "tgn:1000120",
      "tgn:7029392"
    ],
    "placetype": [
      "aat:300008795"
    ],
    "id": 1104493,
    "name:xx": "Eboshi-yama"
  }
}
