{
  "geometry": {
    "type": "Point",
    "coordinates": [
      -110.1167,
      43.6833
    ]
  },
  "type": "Feature",
  "properties": {
    "hierarchy": [
      "tgn:2156984",
      "tgn:1000001",
      "tgn:7012149",
      "tgn:2002384",
      "tgn:7007923",
      "tgn:7029392"
    ],
    "placetype": [
      "aat:300008706"
    ],
    "id": 2156984,
    "name:xx": "Beauty Park Creek"
  }
}
