{
  "geometry": {
    "type": "Point",
    "coordinates": [
      -77.0833,
      41.4667
    ]
  },
  "type": "Feature",
  "properties": {
    "hierarchy": [
      "tgn:2785608",
      "tgn:1000001",
      "tgn:7012149",
      "tgn:1002613",
      "tgn:7007710",
      "tgn:7029392"
    ],
    "placetype": [
      "aat:300008761"
    ],
    "id": 2785608,
    "name:xx": "Yoder Hollow"
  }
}
