{
  "geometry": {
    "type": "Point",
    "coordinates": [
      -103.8167,
      44.2833
    ]
  },
  "type": "Feature",
  "properties": {
    "hierarchy": [
      "tgn:2409230",
      "tgn:1000001",
      "tgn:2001810",
      "tgn:7012149",
      "tgn:7007713",
      "tgn:7029392"
    ],
    "placetype": [
      "aat:300008761"
    ],
    "id": 2409230,
    "name:xx": "Icebox Gulch"
  }
}
