{
  "geometry": {
    "type": "Point",
    "coordinates": [
      31.83352,
      31.433226
    ]
  },
  "type": "Feature",
  "properties": {
    "hierarchy": [
      "tgn:7537586",
      "tgn:7001242",
      "tgn:1001059",
      "tgn:7016833",
      "tgn:7029392"
    ],
    "placetype": [
      "aat:300008347"
    ],
    "name:en": "Shaṭṭ Gireiba",
    "id": 7537586
  }
}
