{
  "geometry": {
    "type": "Point",
    "coordinates": [
      10.15,
      47.65
    ]
  },
  "type": "Feature",
  "properties": {
    "hierarchy": [
      "tgn:7115745",
      "tgn:7003669",
      "tgn:1000003",
      "tgn:7000084",
      "tgn:7029392"
    ],
    "placetype": [
      "aat:300008699"
    ],
    "id": 7115745,
    "name:xx": "Osterbach"
  }
}
