{
  "type": "FeatureCollection",
  "features": [
    {
      "geometry": {
        "type": "Point",
        "coordinates": [
          -7.3,
          43.366667
        ]
      },
      "type": "Feature",
      "properties": {
        "hierarchy": [
          "tgn:7337350",
          "tgn:7002829",
          "tgn:1000003",
          "tgn:7002786",
          "tgn:1000095",
          "tgn:7029392"
        ],
        "placetype": [
          "aat:300008347"
        ],
        "id": 7337350,
        "name:xx": "Cima de Vila de Santalla"
      }
    },
    {
      "geometry": {
        "type": "Point",
        "coordinates": [
          -7.2,
          43.433333
        ]
      },
      "type": "Feature",
      "properties": {
        "hierarchy": [
          "tgn:7337351",
          "tgn:7002829",
          "tgn:1000003",
          "tgn:7002786",
          "tgn:1000095",
          "tgn:7029392"
        ],
        "placetype": [
          "aat:300008347"
        ],
        "id": 7337351,
        "name:xx": "Cima de Vila"
      }
    },
    {
      "geometry": {
        "type": "Point",
        "coordinates": [
          -7.216667,
          42.3
        ]
      },
      "type": "Feature",
      "properties": {
        "hierarchy": [
          "tgn:7337352",
          "tgn:7002831",
          "tgn:1000003",
          "tgn:7002786",
          "tgn:1000095",
          "tgn:7029392"
        ],
        "placetype": [
          "aat:300008347"
        ],
        "id": 7337352,
        "name:xx": "Cimadevila"
      }
    },
    {
      "geometry": {
        "type": "Point",
        "coordinates": [
          -7.766667,
          42
        ]
      },
      "type": "Feature",
      "properties": {
        "hierarchy": [
          "tgn:7337353",
          "tgn:7002831",
          "tgn:1000003",
          "tgn:7002786",
          "tgn:1000095",
          "tgn:7029392"
        ],
        "placetype": [
          "aat:300008347"
        ],
        "id": 7337353,
        "name:xx": "Cima de Ribeira"
      }
    },
    {
      "geometry": {
        "type": "Point",
        "coordinates": [
          -1.466667,
          42.983333
        ]
      },
      "type": "Feature",
      "properties": {
        "hierarchy": [
          "tgn:7337354",
          "tgn:7001155",
          "tgn:1000003",
          "tgn:7002790",
          "tgn:1000095",
          "tgn:7029392"
        ],
        "placetype": [
          "aat:300008347"
        ],
        "id": 7337354,
        "name:xx": "Cilveti"
      }
    },
    {
      "geometry": {
        "type": "Point",
        "coordinates": [
          -3,
          42.333333
        ]
      },
      "type": "Feature",
      "properties": {
        "hierarchy": [
          "tgn:7337355",
          "tgn:7002827",
          "tgn:1000003",
          "tgn:7002789",
          "tgn:1000095",
          "tgn:7029392"
        ],
        "placetype": [
          "aat:300008699"
        ],
        "id": 7337355,
        "name:xx": "Ciloria, Río"
      }
    },
    {
      "geometry": {
        "type": "Point",
        "coordinates": [
          -5.466667,
          40.916667
        ]
      },
      "type": "Feature",
      "properties": {
        "hierarchy": [
          "tgn:7337356",
          "tgn:7002835",
          "tgn:7001158",
          "tgn:1000003",
          "tgn:1000095",
          "tgn:7029392"
        ],
        "placetype": [
          "aat:300008347"
        ],
        "id": 7337356,
        "name:xx": "Cilloruelo"
      }
    },
    {
      "geometry": {
        "type": "Point",
        "coordinates": [
          -3.566667,
          41.433333
        ]
      },
      "type": "Feature",
      "properties": {
        "hierarchy": [
          "tgn:7337357",
          "tgn:7002839",
          "tgn:7001158",
          "tgn:1000003",
          "tgn:1000095",
          "tgn:7029392"
        ],
        "placetype": [
          "aat:300008347"
        ],
        "id": 7337357,
        "name:xx": "Cilleruelo de San Mamés"
      }
    },
    {
      "geometry": {
        "type": "Point",
        "coordinates": [
          -3.85,
          42.9
        ]
      },
      "type": "Feature",
      "properties": {
        "hierarchy": [
          "tgn:7337358",
          "tgn:7002810",
          "tgn:7001158",
          "tgn:1000003",
          "tgn:1000095",
          "tgn:7029392"
        ],
        "placetype": [
          "aat:300008347"
        ],
        "id": 7337358,
        "name:xx": "Cilleruelo de Bricia"
      }
    }
  ]
}
