{
  "type": "FeatureCollection",
  "features": [
    {
      "geometry": {
        "type": "Point",
        "coordinates": [
          35,
          38
        ]
      },
      "type": "Feature",
      "properties": {
        "hierarchy": [
          "tgn:1003720",
          "tgn:1000004",
          "tgn:1000144",
          "tgn:7029392"
        ],
        "placetype": [
          "aat:300387346"
        ],
        "id": 1003720,
        "name:xx": "Cataonia"
      }
    },
    {
      "geometry": {
        "type": "Point",
        "coordinates": [
          9.728,
          44.106
        ]
      },
      "type": "Feature",
      "properties": {
        "hierarchy": [
          "tgn:1003723",
          "tgn:1000003",
          "tgn:7003143",
          "tgn:7003236",
          "tgn:1000080",
          "tgn:7029392"
        ],
        "placetype": [
          "aat:300008189",
          "aat:300387346",
          "aat:300263063"
        ],
        "id": 1003723,
        "name:xx": "Cinque Terre"
      }
    },
    {
      "geometry": {
        "type": "Point",
        "coordinates": [
          5,
          50.333
        ]
      },
      "type": "Feature",
      "properties": {
        "hierarchy": [
          "tgn:1003725",
          "tgn:7003466",
          "tgn:1000003",
          "tgn:1000063",
          "tgn:4012014",
          "tgn:7029392"
        ],
        "placetype": [
          "aat:300387346"
        ],
        "id": 1003725,
        "name:xx": "Condroz"
      }
    },
    {
      "geometry": {
        "type": "Point",
        "coordinates": [
          -4.5,
          55.6667
        ]
      },
      "type": "Feature",
      "properties": {
        "hierarchy": [
          "tgn:1003727",
          "tgn:7002444",
          "tgn:1000003",
          "tgn:7008591",
          "tgn:7029392"
        ],
        "placetype": [
          "aat:300387346"
        ],
        "id": 1003727,
        "name:xx": "Cunningham"
      }
    }
  ]
}
