{
  "geometry": {
    "type": "Point",
    "coordinates": [
      27.25,
      35.816667
    ]
  },
  "type": "Feature",
  "properties": {
    "hierarchy": [
      "tgn:7226736",
      "tgn:7011330",
      "tgn:7002674",
      "tgn:1000003",
      "tgn:1000074",
      "tgn:7029392"
    ],
    "placetype": [
      "aat:300008850"
    ],
    "id": 7226736,
    "name:xx": "Monakhoú, Ákra"
  }
}
