{
  "geometry": {
    "type": "Point",
    "coordinates": [
      -82.0833,
      35.8333
    ]
  },
  "type": "Feature",
  "properties": {
    "hierarchy": [
      "tgn:2719676",
      "tgn:1000001",
      "tgn:7012149",
      "tgn:2001514",
      "tgn:7007709",
      "tgn:7029392"
    ],
    "placetype": [
      "aat:300008706"
    ],
    "id": 2719676,
    "name:xx": "Three Mile Creek"
  }
}
