{
  "geometry": {
    "type": "Point",
    "coordinates": [
      -122.8833,
      48.5667
    ]
  },
  "type": "Feature",
  "properties": {
    "hierarchy": [
      "tgn:2741358",
      "tgn:1000001",
      "tgn:7012149",
      "tgn:1002862",
      "tgn:7007920",
      "tgn:7029392"
    ],
    "placetype": [
      "aat:300008798"
    ],
    "id": 2741358,
    "name:xx": "Upright Head"
  }
}
