{
  "geometry": {
    "type": "Point",
    "coordinates": [
      -74.8333,
      41.2667
    ]
  },
  "type": "Feature",
  "properties": {
    "hierarchy": [
      "tgn:2251890",
      "tgn:1000001",
      "tgn:7012149",
      "tgn:1002789",
      "tgn:7007710",
      "tgn:7029392"
    ],
    "placetype": [
      "aat:300008347"
    ],
    "id": 2251890,
    "name:xx": "Conashaugh"
  }
}
