{
  "geometry": {
    "type": "Point",
    "coordinates": [
      -91.3167,
      45.0833
    ]
  },
  "type": "Feature",
  "properties": {
    "hierarchy": [
      "tgn:2187587",
      "tgn:1000001",
      "tgn:2002313",
      "tgn:7012149",
      "tgn:7007922",
      "tgn:7029392"
    ],
    "placetype": [
      "aat:300008680"
    ],
    "id": 2187587,
    "name:xx": "Boot Lake"
  }
}
