{
  "geometry": {
    "type": "Point",
    "coordinates": [
      -109.4333,
      31.4333
    ]
  },
  "type": "Feature",
  "properties": {
    "hierarchy": [
      "tgn:2393477",
      "tgn:1000001",
      "tgn:7006451",
      "tgn:2000091",
      "tgn:7012149",
      "tgn:7029392"
    ],
    "placetype": [
      "aat:300008761"
    ],
    "id": 2393477,
    "name:xx": "Hog Canyon"
  }
}
