{
  "geometry": {
    "type": "Point",
    "coordinates": [
      -107.3667,
      48.2667
    ]
  },
  "type": "Feature",
  "properties": {
    "hierarchy": [
      "tgn:2254284",
      "tgn:1000001",
      "tgn:7012149",
      "tgn:7007524",
      "tgn:7029392"
    ],
    "placetype": [
      "aat:300008761"
    ],
    "id": 2254284,
    "name:xx": "Coon Coulee"
  }
}
