{
  "geometry": {
    "type": "Point",
    "coordinates": [
      -74.5667,
      39.7667
    ]
  },
  "type": "Feature",
  "properties": {
    "hierarchy": [
      "tgn:2303192",
      "tgn:1002215",
      "tgn:1000001",
      "tgn:7012149",
      "tgn:7007565",
      "tgn:7029392"
    ],
    "placetype": [
      "aat:300008347"
    ],
    "id": 2303192,
    "name:xx": "Eagle"
  }
}
