{
  "geometry": {
    "type": "Point",
    "coordinates": [
      -108.1167,
      37.3833
    ]
  },
  "type": "Feature",
  "properties": {
    "hierarchy": [
      "tgn:2726880",
      "tgn:1000001",
      "tgn:7012149",
      "tgn:2000233",
      "tgn:7007158",
      "tgn:7029392"
    ],
    "placetype": [
      "aat:300386845"
    ],
    "id": 2726880,
    "name:xx": "Townsend Basin"
  }
}
