{
  "geometry": {
    "type": "Point",
    "coordinates": [
      77.916667,
      8.85
    ]
  },
  "type": "Feature",
  "properties": {
    "hierarchy": [
      "tgn:7552441",
      "tgn:1000004",
      "tgn:7000198",
      "tgn:7001797",
      "tgn:7029392"
    ],
    "placetype": [
      "aat:300008347"
    ],
    "name:en": "Maniyāchchi",
    "id": 7552441
  }
}
