{
  "geometry": {
    "type": "Point",
    "coordinates": [
      -80.1167,
      26.6667
    ]
  },
  "type": "Feature",
  "properties": {
    "hierarchy": [
      "tgn:2761544",
      "tgn:1000001",
      "tgn:7012149",
      "tgn:1002768",
      "tgn:7007240",
      "tgn:7029392"
    ],
    "placetype": [
      "aat:300008347"
    ],
    "id": 2761544,
    "name:xx": "West Palm Beach Farms"
  }
}
