{
  "geometry": {
    "type": "Point",
    "coordinates": [
      -118.7167,
      36.35
    ]
  },
  "type": "Feature",
  "properties": {
    "hierarchy": [
      "tgn:2678923",
      "tgn:1000001",
      "tgn:7012149",
      "tgn:7007157",
      "tgn:1002956",
      "tgn:7029392"
    ],
    "placetype": [
      "aat:300132451"
    ],
    "id": 2678923,
    "name:xx": "South Fork Grove"
  }
}
