{
  "geometry": {
    "type": "Point",
    "coordinates": [
      -130.6333,
      54.8667
    ]
  },
  "type": "Feature",
  "properties": {
    "hierarchy": [
      "tgn:2534915",
      "tgn:7006450",
      "tgn:1000001",
      "tgn:7012149",
      "tgn:2000082",
      "tgn:7029392"
    ],
    "placetype": [
      "aat:300008798"
    ],
    "id": 2534915,
    "name:xx": "Nakat Mountain"
  }
}
