{
  "geometry": {
    "type": "Point",
    "coordinates": [
      27.65,
      52.85
    ]
  },
  "type": "Feature",
  "properties": {
    "hierarchy": [
      "tgn:1058513",
      "tgn:1003391",
      "tgn:1000003",
      "tgn:7006657",
      "tgn:7029392"
    ],
    "placetype": [
      "aat:300008347",
      "aat:300008375"
    ],
    "id": 1058513,
    "name:xx": "Pogost"
  }
}
