{
  "geometry": {
    "type": "Point",
    "coordinates": [
      -75.3833,
      41.05
    ]
  },
  "type": "Feature",
  "properties": {
    "hierarchy": [
      "tgn:2160306",
      "tgn:1000001",
      "tgn:7012149",
      "tgn:1002682",
      "tgn:7007710",
      "tgn:7029392"
    ],
    "placetype": [
      "aat:300008798"
    ],
    "id": 2160306,
    "name:xx": "Beehive"
  }
}
