{
  "type": "FeatureCollection",
  "features": [
    {
      "geometry": {
        "type": "Point",
        "coordinates": [
          -100.933333,
          20.233333
        ]
      },
      "type": "Feature",
      "properties": {
        "hierarchy": [
          "tgn:7436120",
          "tgn:7005584",
          "tgn:1000001",
          "tgn:7005560",
          "tgn:7029392"
        ],
        "placetype": [
          "aat:300008347"
        ],
        "id": 7436120,
        "name:xx": "Santo Tomás"
      }
    },
    {
      "geometry": {
        "type": "Point",
        "coordinates": [
          -98.566667,
          19.9
        ]
      },
      "type": "Feature",
      "properties": {
        "hierarchy": [
          "tgn:7436121",
          "tgn:7005587",
          "tgn:1000001",
          "tgn:7005560",
          "tgn:7029392"
        ],
        "placetype": [
          "aat:300008347"
        ],
        "id": 7436121,
        "name:xx": "Santo Tomás"
      }
    },
    {
      "geometry": {
        "type": "Point",
        "coordinates": [
          -102.1,
          19.85
        ]
      },
      "type": "Feature",
      "properties": {
        "hierarchy": [
          "tgn:7436122",
          "tgn:1000001",
          "tgn:7005590",
          "tgn:7005560",
          "tgn:7029392"
        ],
        "placetype": [
          "aat:300008347"
        ],
        "id": 7436122,
        "name:xx": "Santo Tomás"
      }
    },
    {
      "geometry": {
        "type": "Point",
        "coordinates": [
          -92.783333,
          17.583333
        ]
      },
      "type": "Feature",
      "properties": {
        "hierarchy": [
          "tgn:7436123",
          "tgn:1000001",
          "tgn:7005596",
          "tgn:7005560",
          "tgn:7029392"
        ],
        "placetype": [
          "aat:300008347"
        ],
        "id": 7436123,
        "name:xx": "Santo Tomás"
      }
    },
    {
      "geometry": {
        "type": "Point",
        "coordinates": [
          -91.316667,
          17.3
        ]
      },
      "type": "Feature",
      "properties": {
        "hierarchy": [
          "tgn:7436124",
          "tgn:1000001",
          "tgn:7005596",
          "tgn:7005560",
          "tgn:7029392"
        ],
        "placetype": [
          "aat:300008347"
        ],
        "id": 7436124,
        "name:xx": "Santo Tomás"
      }
    },
    {
      "geometry": {
        "type": "Point",
        "coordinates": [
          -92.083333,
          17.033333
        ]
      },
      "type": "Feature",
      "properties": {
        "hierarchy": [
          "tgn:7436126",
          "tgn:7005580",
          "tgn:1000001",
          "tgn:7005560",
          "tgn:7029392"
        ],
        "placetype": [
          "aat:300008347"
        ],
        "id": 7436126,
        "name:xx": "Santo Tomás"
      }
    },
    {
      "geometry": {
        "type": "Point",
        "coordinates": [
          -92.783333,
          16.733333
        ]
      },
      "type": "Feature",
      "properties": {
        "hierarchy": [
          "tgn:7436127",
          "tgn:7005580",
          "tgn:1000001",
          "tgn:7005560",
          "tgn:7029392"
        ],
        "placetype": [
          "aat:300008347"
        ],
        "id": 7436127,
        "name:xx": "Santo Tomás"
      }
    },
    {
      "geometry": {
        "type": "Point",
        "coordinates": [
          -96.733333,
          16.066667
        ]
      },
      "type": "Feature",
      "properties": {
        "hierarchy": [
          "tgn:7436128",
          "tgn:1000001",
          "tgn:7005591",
          "tgn:7005560",
          "tgn:7029392"
        ],
        "placetype": [
          "aat:300008347"
        ],
        "id": 7436128,
        "name:xx": "Santo Tomás"
      }
    }
  ]
}
