{
  "geometry": {
    "type": "Point",
    "coordinates": [
      74.6375,
      34.238889
    ]
  },
  "type": "Feature",
  "properties": {
    "hierarchy": [
      "tgn:7587218",
      "tgn:1000004",
      "tgn:7000198",
      "tgn:7000799",
      "tgn:7029392"
    ],
    "placetype": [
      "aat:300008347"
    ],
    "name:en": "Sonāwāri",
    "id": 7587218
  }
}
