{
  "geometry": {
    "type": "Point",
    "coordinates": [
      -91.8667,
      33.1167
    ]
  },
  "type": "Feature",
  "properties": {
    "hierarchy": [
      "tgn:2627950",
      "tgn:2000106",
      "tgn:1000001",
      "tgn:7016172",
      "tgn:7012149",
      "tgn:7029392"
    ],
    "placetype": [
      "aat:300008347"
    ],
    "id": 2627950,
    "name:xx": "Rolfe Junction"
  }
}
