{
  "geometry": {
    "type": "Point",
    "coordinates": [
      27.65,
      2.1667
    ]
  },
  "type": "Feature",
  "properties": {
    "hierarchy": [
      "tgn:1088764",
      "tgn:7001242",
      "tgn:7016755",
      "tgn:1000159",
      "tgn:7029392"
    ],
    "placetype": [
      "aat:300008347"
    ],
    "id": 1088764,
    "name:xx": "Bafwabaka"
  }
}
