{
  "geometry": {
    "type": "Point",
    "coordinates": [
      -117.55,
      41.7333
    ]
  },
  "type": "Feature",
  "properties": {
    "hierarchy": [
      "tgn:2545573",
      "tgn:1000001",
      "tgn:2001414",
      "tgn:7012149",
      "tgn:7007526",
      "tgn:7029392"
    ],
    "placetype": [
      "aat:300008706"
    ],
    "id": 2545573,
    "name:xx": "North Fork Cabin Creek"
  }
}
