{
  "geometry": {
    "type": "Point",
    "coordinates": [
      -81.65,
      39.8333
    ]
  },
  "type": "Feature",
  "properties": {
    "hierarchy": [
      "tgn:2204547",
      "tgn:1000001",
      "tgn:7012149",
      "tgn:1002432",
      "tgn:7007706",
      "tgn:7029392"
    ],
    "placetype": [
      "aat:300008699"
    ],
    "id": 2204547,
    "name:xx": "Buffalo Fork"
  }
}
