{
  "geometry": {
    "type": "Point",
    "coordinates": [
      -93.0333,
      32.3333
    ]
  },
  "type": "Feature",
  "properties": {
    "hierarchy": [
      "tgn:2754217",
      "tgn:1000001",
      "tgn:2000860",
      "tgn:7012149",
      "tgn:7007256",
      "tgn:7029392"
    ],
    "placetype": [
      "aat:300008699"
    ],
    "id": 2754217,
    "name:xx": "Watts Branch"
  }
}
