{
  "geometry": {
    "type": "Point",
    "coordinates": [
      -93.7667,
      39.4667
    ]
  },
  "type": "Feature",
  "properties": {
    "hierarchy": [
      "tgn:2387936",
      "tgn:1000001",
      "tgn:7012149",
      "tgn:7007523",
      "tgn:7029392"
    ],
    "placetype": [
      "aat:300008699"
    ],
    "id": 2387936,
    "name:xx": "Hickory Branch"
  }
}
