{
  "geometry": {
    "type": "Point",
    "coordinates": [
      -111.2667,
      46.5167
    ]
  },
  "type": "Feature",
  "properties": {
    "hierarchy": [
      "tgn:2299113",
      "tgn:1000001",
      "tgn:2001263",
      "tgn:7012149",
      "tgn:7007524",
      "tgn:7029392"
    ],
    "placetype": [
      "aat:300008706"
    ],
    "id": 2299113,
    "name:xx": "Duck Creek"
  }
}
