{
  "type": "FeatureCollection",
  "features": [
    {
      "geometry": {
        "type": "Point",
        "coordinates": [
          -111.05,
          33.6
        ]
      },
      "type": "Feature",
      "properties": {
        "hierarchy": [
          "tgn:2700410",
          "tgn:1000001",
          "tgn:7006451",
          "tgn:2000093",
          "tgn:7012149",
          "tgn:7029392"
        ],
        "placetype": [
          "aat:300006191"
        ],
        "id": 2700410,
        "name:xx": "Substitute Tank"
      }
    },
    {
      "geometry": {
        "type": "Point",
        "coordinates": [
          -108.1667,
          33.3
        ]
      },
      "type": "Feature",
      "properties": {
        "hierarchy": [
          "tgn:2700411",
          "tgn:1000001",
          "tgn:2001429",
          "tgn:7012149",
          "tgn:7007566",
          "tgn:7029392"
        ],
        "placetype": [
          "aat:300006191"
        ],
        "id": 2700411,
        "name:xx": "Substitute Tank"
      }
    },
    {
      "geometry": {
        "type": "Point",
        "coordinates": [
          -119.9833,
          39.4167
        ]
      },
      "type": "Feature",
      "properties": {
        "hierarchy": [
          "tgn:2700412",
          "tgn:1000001",
          "tgn:7012149",
          "tgn:7029392"
        ],
        "placetype": [
          "aat:300008706"
        ],
        "id": 2700412,
        "name:xx": "Subterranean Creek"
      }
    },
    {
      "geometry": {
        "type": "Point",
        "coordinates": [
          -78.1333,
          34
        ]
      },
      "type": "Feature",
      "properties": {
        "hierarchy": [
          "tgn:2700413",
          "tgn:1000001",
          "tgn:2001472",
          "tgn:7012149",
          "tgn:7007709",
          "tgn:7029392"
        ],
        "placetype": [
          "aat:300008347"
        ],
        "id": 2700413,
        "name:xx": "Suburb"
      }
    },
    {
      "geometry": {
        "type": "Point",
        "coordinates": [
          -88.6,
          34.2667
        ]
      },
      "type": "Feature",
      "properties": {
        "hierarchy": [
          "tgn:2700414",
          "tgn:1000001",
          "tgn:7012149",
          "tgn:2001126",
          "tgn:7007522",
          "tgn:7029392"
        ],
        "placetype": [
          "aat:300008347"
        ],
        "id": 2700414,
        "name:xx": "Suburban Acres"
      }
    },
    {
      "geometry": {
        "type": "Point",
        "coordinates": [
          -76.25,
          36.9
        ]
      },
      "type": "Feature",
      "properties": {
        "hierarchy": [
          "tgn:2700415",
          "tgn:1000001",
          "tgn:7012149",
          "tgn:7022201",
          "tgn:7007919",
          "tgn:7029392"
        ],
        "placetype": [
          "aat:300008347"
        ],
        "id": 2700415,
        "name:xx": "Suburban Acres"
      }
    },
    {
      "geometry": {
        "type": "Point",
        "coordinates": [
          -90.1667,
          30
        ]
      },
      "type": "Feature",
      "properties": {
        "hierarchy": [
          "tgn:2700416",
          "tgn:1000001",
          "tgn:7012149",
          "tgn:2000879",
          "tgn:7007256",
          "tgn:7029392"
        ],
        "placetype": [
          "aat:300006075"
        ],
        "id": 2700416,
        "name:xx": "Suburban Canal"
      }
    },
    {
      "geometry": {
        "type": "Point",
        "coordinates": [
          -101,
          41.1833
        ]
      },
      "type": "Feature",
      "properties": {
        "hierarchy": [
          "tgn:2700417",
          "tgn:1000001",
          "tgn:7012149",
          "tgn:2001371",
          "tgn:7007525",
          "tgn:7029392"
        ],
        "placetype": [
          "aat:300006075"
        ],
        "id": 2700417,
        "name:xx": "Suburban Canal"
      }
    },
    {
      "geometry": {
        "type": "Point",
        "coordinates": [
          -108.55,
          45.7333
        ]
      },
      "type": "Feature",
      "properties": {
        "hierarchy": [
          "tgn:2700418",
          "tgn:1000001",
          "tgn:7012149",
          "tgn:2001315",
          "tgn:7007524",
          "tgn:7029392"
        ],
        "placetype": [
          "aat:300006075"
        ],
        "id": 2700418,
        "name:xx": "Suburban Ditch"
      }
    },
    {
      "geometry": {
        "type": "Point",
        "coordinates": [
          -85.0167,
          33.8167
        ]
      },
      "type": "Feature",
      "properties": {
        "hierarchy": [
          "tgn:2700419",
          "tgn:1000001",
          "tgn:7012149",
          "tgn:2000401",
          "tgn:7007248",
          "tgn:7029392"
        ],
        "placetype": [
          "aat:300008347"
        ],
        "id": 2700419,
        "name:xx": "Suburban Estates"
      }
    }
  ]
}
