{
  "geometry": {
    "type": "Point",
    "coordinates": [
      -71.2167,
      42.15
    ]
  },
  "type": "Feature",
  "properties": {
    "hierarchy": [
      "tgn:2588093",
      "tgn:1000001",
      "tgn:1002724",
      "tgn:7012149",
      "tgn:7007517",
      "tgn:7029392"
    ],
    "placetype": [
      "aat:300006191"
    ],
    "id": 2588093,
    "name:xx": "Plimpton Pond"
  }
}
