{
  "geometry": {
    "type": "Point",
    "coordinates": [
      -110.7833,
      31.6333
    ]
  },
  "type": "Feature",
  "properties": {
    "hierarchy": [
      "tgn:2453141",
      "tgn:1000001",
      "tgn:7006451",
      "tgn:7012149",
      "tgn:2000102",
      "tgn:7029392"
    ],
    "placetype": [
      "aat:300008761"
    ],
    "id": 2453141,
    "name:xx": "Little Casa Blanca Canyon"
  }
}
