{
  "type": "FeatureCollection",
  "features": [
    {
      "geometry": {
        "type": "Point",
        "coordinates": [
          23.25,
          62.5
        ]
      },
      "type": "Feature",
      "properties": {
        "hierarchy": [
          "tgn:7594380",
          "tgn:1000003",
          "tgn:1000069",
          "tgn:7029392"
        ],
        "placetype": [
          "aat:300387064",
          "aat:300236112"
        ],
        "id": 7594380,
        "name:fi": "Etelä-Pohjanmaa"
      }
    },
    {
      "geometry": {
        "type": "Point",
        "coordinates": [
          27.833333,
          61.75
        ]
      },
      "type": "Feature",
      "properties": {
        "hierarchy": [
          "tgn:7594381",
          "tgn:1000003",
          "tgn:1000069",
          "tgn:7029392"
        ],
        "placetype": [
          "aat:300387064",
          "aat:300236112"
        ],
        "id": 7594381,
        "name:fi": "Etelä-Savo"
      }
    },
    {
      "geometry": {
        "type": "Point",
        "coordinates": [
          24.25,
          60.833333
        ]
      },
      "type": "Feature",
      "properties": {
        "hierarchy": [
          "tgn:7594382",
          "tgn:1000003",
          "tgn:1000069",
          "tgn:7029392"
        ],
        "placetype": [
          "aat:300387064",
          "aat:300236112"
        ],
        "id": 7594382,
        "name:fi": "Kanta-Häme"
      }
    },
    {
      "geometry": {
        "type": "Point",
        "coordinates": [
          28,
          64.5
        ]
      },
      "type": "Feature",
      "properties": {
        "hierarchy": [
          "tgn:7594383",
          "tgn:1000003",
          "tgn:1000069",
          "tgn:7029392"
        ],
        "placetype": [
          "aat:300387064",
          "aat:300236112"
        ],
        "id": 7594383,
        "name:fi": "Kainuu"
      }
    },
    {
      "geometry": {
        "type": "Point",
        "coordinates": [
          24,
          63.5
        ]
      },
      "type": "Feature",
      "properties": {
        "hierarchy": [
          "tgn:7594384",
          "tgn:1000003",
          "tgn:1000069",
          "tgn:7029392"
        ],
        "placetype": [
          "aat:300387064",
          "aat:300236112"
        ],
        "id": 7594384,
        "name:fi": "Keski-Pohjanmaa"
      }
    },
    {
      "geometry": {
        "type": "Point",
        "coordinates": [
          25.5,
          62.5
        ]
      },
      "type": "Feature",
      "properties": {
        "hierarchy": [
          "tgn:7594385",
          "tgn:1000003",
          "tgn:1000069",
          "tgn:7029392"
        ],
        "placetype": [
          "aat:300387064",
          "aat:300236112"
        ],
        "id": 7594385,
        "name:fi": "Keski-Suomi"
      }
    },
    {
      "geometry": {
        "type": "Point",
        "coordinates": [
          27,
          60.5
        ]
      },
      "type": "Feature",
      "properties": {
        "hierarchy": [
          "tgn:7594386",
          "tgn:1000003",
          "tgn:1000069",
          "tgn:7029392"
        ],
        "placetype": [
          "aat:300387064",
          "aat:300236112"
        ],
        "id": 7594386,
        "name:fi": "Kymenlaakso"
      }
    },
    {
      "geometry": {
        "type": "Point",
        "coordinates": [
          27,
          68
        ]
      },
      "type": "Feature",
      "properties": {
        "hierarchy": [
          "tgn:7594387",
          "tgn:1000003",
          "tgn:1000069",
          "tgn:7029392"
        ],
        "placetype": [
          "aat:300387064",
          "aat:300236112"
        ],
        "id": 7594387,
        "name:fi": "Lappi"
      }
    },
    {
      "geometry": {
        "type": "Point",
        "coordinates": [
          25.833333,
          61.25
        ]
      },
      "type": "Feature",
      "properties": {
        "hierarchy": [
          "tgn:7594388",
          "tgn:1000003",
          "tgn:1000069",
          "tgn:7029392"
        ],
        "placetype": [
          "aat:300387064",
          "aat:300236112"
        ],
        "id": 7594388,
        "name:fi": "Päijät-Häme"
      }
    },
    {
      "geometry": {
        "type": "Point",
        "coordinates": [
          23.716667,
          61.7
        ]
      },
      "type": "Feature",
      "properties": {
        "hierarchy": [
          "tgn:7594389",
          "tgn:1000003",
          "tgn:1000069",
          "tgn:7029392"
        ],
        "placetype": [
          "aat:300387064",
          "aat:300236112"
        ],
        "id": 7594389,
        "name:fi": "Pirkanmaa"
      }
    }
  ]
}
