{
  "geometry": {
    "type": "Point",
    "coordinates": [
      -68.05,
      44.4667
    ]
  },
  "type": "Feature",
  "properties": {
    "hierarchy": [
      "tgn:2287984",
      "tgn:1000001",
      "tgn:2000922",
      "tgn:7012149",
      "tgn:7007515",
      "tgn:7029392"
    ],
    "placetype": [
      "aat:300008905"
    ],
    "id": 2287984,
    "name:xx": "Dingle Meadow Heath"
  }
}
