{
  "geometry": {
    "type": "Point",
    "coordinates": [
      -77.45,
      37.7667
    ]
  },
  "type": "Feature",
  "properties": {
    "hierarchy": [
      "tgn:2669027",
      "tgn:1000001",
      "tgn:7012149",
      "tgn:1002451",
      "tgn:7007919",
      "tgn:7029392"
    ],
    "placetype": [
      "aat:300008706"
    ],
    "id": 2669027,
    "name:xx": "Slayden Creek"
  }
}
