{
  "geometry": {
    "type": "Point",
    "coordinates": [
      -82.2167,
      26.65
    ]
  },
  "type": "Feature",
  "properties": {
    "hierarchy": [
      "tgn:2213078",
      "tgn:1000001",
      "tgn:7012149",
      "tgn:1002582",
      "tgn:7007240",
      "tgn:7029392"
    ],
    "placetype": [
      "aat:300008791"
    ],
    "id": 2213078,
    "name:xx": "Cabbage Key"
  }
}
