{
  "geometry": {
    "type": "Point",
    "coordinates": [
      -84.95,
      37.1667
    ]
  },
  "type": "Feature",
  "properties": {
    "hierarchy": [
      "tgn:2591339",
      "tgn:1000001",
      "tgn:2000779",
      "tgn:7012149",
      "tgn:7007255",
      "tgn:7029392"
    ],
    "placetype": [
      "aat:300266640"
    ],
    "id": 2591339,
    "name:xx": "Polly Ridge"
  }
}
