{
  "type": "FeatureCollection",
  "features": [
    {
      "geometry": {
        "type": "Point",
        "coordinates": [
          -81.1,
          28.6
        ]
      },
      "type": "Feature",
      "properties": {
        "hierarchy": [
          "tgn:1117730",
          "tgn:1000001",
          "tgn:7012149",
          "tgn:7007240",
          "tgn:7029392"
        ],
        "placetype": [
          "aat:300008680"
        ],
        "id": 1117730,
        "name:xx": "Pickett, Lake"
      }
    },
    {
      "geometry": {
        "type": "Point",
        "coordinates": [
          26.583333,
          63.3
        ]
      },
      "type": "Feature",
      "properties": {
        "hierarchy": [
          "tgn:1117731",
          "tgn:7594394",
          "tgn:1000003",
          "tgn:1000069",
          "tgn:7029392"
        ],
        "placetype": [
          "aat:300008680"
        ],
        "id": 1117731,
        "name:xx": "Pielavesi"
      }
    },
    {
      "geometry": {
        "type": "Point",
        "coordinates": [
          29.666667,
          63.25
        ]
      },
      "type": "Feature",
      "properties": {
        "hierarchy": [
          "tgn:1117732",
          "tgn:7594391",
          "tgn:1000003",
          "tgn:1000069",
          "tgn:7029392"
        ],
        "placetype": [
          "aat:300008680"
        ],
        "id": 1117732,
        "name:xx": "Pielinen"
      }
    },
    {
      "geometry": {
        "type": "Point",
        "coordinates": [
          -92.9667,
          54.1667
        ]
      },
      "type": "Feature",
      "properties": {
        "hierarchy": [
          "tgn:1117733",
          "tgn:7005685",
          "tgn:1000001",
          "tgn:7029392"
        ],
        "placetype": [
          "aat:300008680"
        ],
        "id": 1117733,
        "name:xx": "Pierce Lake"
      }
    },
    {
      "geometry": {
        "type": "Point",
        "coordinates": [
          -109.7,
          54.5
        ]
      },
      "type": "Feature",
      "properties": {
        "hierarchy": [
          "tgn:1117734",
          "tgn:7005685",
          "tgn:1000001",
          "tgn:7005805",
          "tgn:1102586",
          "tgn:7029392"
        ],
        "placetype": [
          "aat:300008680"
        ],
        "id": 1117734,
        "name:xx": "Pierce Lake"
      }
    },
    {
      "geometry": {
        "type": "Point",
        "coordinates": [
          -81.5167,
          27.9667
        ]
      },
      "type": "Feature",
      "properties": {
        "hierarchy": [
          "tgn:1117735",
          "tgn:1000001",
          "tgn:7012149",
          "tgn:1002793",
          "tgn:7007240",
          "tgn:7029392"
        ],
        "placetype": [
          "aat:300008680"
        ],
        "id": 1117735,
        "name:xx": "Pierce, Lake"
      }
    },
    {
      "geometry": {
        "type": "Point",
        "coordinates": [
          15.983333,
          40.283333
        ]
      },
      "type": "Feature",
      "properties": {
        "hierarchy": [
          "tgn:1117737",
          "tgn:1003489",
          "tgn:7004610",
          "tgn:1000003",
          "tgn:1000080",
          "tgn:7029392"
        ],
        "placetype": [
          "aat:300008680"
        ],
        "id": 1117737,
        "name:xx": "Pietra del Pertusillo, Lago di"
      }
    },
    {
      "geometry": {
        "type": "Point",
        "coordinates": [
          -114,
          53
        ]
      },
      "type": "Feature",
      "properties": {
        "hierarchy": [
          "tgn:1117738",
          "tgn:7005694",
          "tgn:7005685",
          "tgn:1000001",
          "tgn:7029392"
        ],
        "placetype": [
          "aat:300008680"
        ],
        "id": 1117738,
        "name:xx": "Pigeon Lake"
      }
    }
  ]
}
