{
  "geometry": {
    "type": "Point",
    "coordinates": [
      -94.9833,
      45.2167
    ]
  },
  "type": "Feature",
  "properties": {
    "hierarchy": [
      "tgn:2385544",
      "tgn:1000001",
      "tgn:7012149",
      "tgn:2001032",
      "tgn:7007521",
      "tgn:7029392"
    ],
    "placetype": [
      "aat:300008680"
    ],
    "id": 2385544,
    "name:xx": "Henderson Lake"
  }
}
