{
  "geometry": {
    "type": "Point",
    "coordinates": [
      15.4833,
      -3.75
    ]
  },
  "type": "Feature",
  "properties": {
    "hierarchy": [
      "tgn:1088686",
      "tgn:7001242",
      "tgn:1001023",
      "tgn:1000158",
      "tgn:7029392"
    ],
    "placetype": [
      "aat:300008347"
    ],
    "id": 1088686,
    "name:xx": "Masa"
  }
}
