{
  "geometry": {
    "type": "Point",
    "coordinates": [
      -111.6167,
      33.7667
    ]
  },
  "type": "Feature",
  "properties": {
    "hierarchy": [
      "tgn:2159530",
      "tgn:1000001",
      "tgn:7006451",
      "tgn:7012149",
      "tgn:2000097",
      "tgn:7029392"
    ],
    "placetype": [
      "aat:300008798"
    ],
    "id": 2159530,
    "name:xx": "Bee Mountain"
  }
}
