{
  "geometry": {
    "type": "Point",
    "coordinates": [
      120.4991,
      23.8554
    ]
  },
  "type": "Feature",
  "properties": {
    "hierarchy": [
      "tgn:7475405",
      "tgn:1000004",
      "tgn:7467799",
      "tgn:1000141",
      "tgn:7029392"
    ],
    "placetype": [
      "aat:300387173"
    ],
    "id": 7475405,
    "name:xx": "Weicuo Cun"
  }
}
