{
  "geometry": {
    "type": "Point",
    "coordinates": [
      79.563356,
      29.34447
    ]
  },
  "type": "Feature",
  "properties": {
    "hierarchy": [
      "tgn:7545514",
      "tgn:1000004",
      "tgn:7000198",
      "tgn:7031786",
      "tgn:7029392"
    ],
    "placetype": [
      "aat:300008347"
    ],
    "name:en": "Bhīm Tāl",
    "id": 7545514
  }
}
