{
  "type": "FeatureCollection",
  "features": [
    {
      "geometry": {
        "type": "Point",
        "coordinates": [
          9.5,
          49.5
        ]
      },
      "type": "Feature",
      "properties": {
        "hierarchy": [
          "tgn:7088970",
          "tgn:7003692",
          "tgn:1000003",
          "tgn:7000084",
          "tgn:7029392"
        ],
        "placetype": [
          "aat:300008699"
        ],
        "id": 7088970,
        "name:xx": "Wasserleitung"
      }
    },
    {
      "geometry": {
        "type": "Point",
        "coordinates": [
          7.683333,
          47.733333
        ]
      },
      "type": "Feature",
      "properties": {
        "hierarchy": [
          "tgn:7088971",
          "tgn:7003692",
          "tgn:1000003",
          "tgn:7000084",
          "tgn:7029392"
        ],
        "placetype": [
          "aat:300000206"
        ],
        "id": 7088971,
        "name:xx": "Wässerlehof"
      }
    },
    {
      "geometry": {
        "type": "Point",
        "coordinates": [
          10.754167,
          51.93
        ]
      },
      "type": "Feature",
      "properties": {
        "hierarchy": [
          "tgn:7088972",
          "tgn:1000003",
          "tgn:7003687",
          "tgn:7000084",
          "tgn:7029392"
        ],
        "placetype": [
          "aat:300007783"
        ],
        "id": 7088972,
        "name:xx": "Bahnhof Wasserleben"
      }
    },
    {
      "geometry": {
        "type": "Point",
        "coordinates": [
          9.95,
          50.5
        ]
      },
      "type": "Feature",
      "properties": {
        "hierarchy": [
          "tgn:7088975",
          "tgn:1000003",
          "tgn:7003689",
          "tgn:7000084",
          "tgn:7029392"
        ],
        "placetype": [
          "aat:300008347"
        ],
        "id": 7088975,
        "name:xx": "Wasserkuppe"
      }
    },
    {
      "geometry": {
        "type": "Point",
        "coordinates": [
          9.333333,
          53.666667
        ]
      },
      "type": "Feature",
      "properties": {
        "hierarchy": [
          "tgn:7088977",
          "tgn:1000003",
          "tgn:7003676",
          "tgn:7000084",
          "tgn:7029392"
        ],
        "placetype": [
          "aat:300000206"
        ],
        "id": 7088977,
        "name:xx": "Wasserkrug"
      }
    },
    {
      "geometry": {
        "type": "Point",
        "coordinates": [
          11.566667,
          49.85
        ]
      },
      "type": "Feature",
      "properties": {
        "hierarchy": [
          "tgn:7088978",
          "tgn:7003669",
          "tgn:1000003",
          "tgn:7000084",
          "tgn:7029392"
        ],
        "placetype": [
          "aat:300008347"
        ],
        "id": 7088978,
        "name:xx": "Wasserkraut"
      }
    }
  ]
}
