{
  "geometry": {
    "type": "Point",
    "coordinates": [
      -90.3833,
      35.5833
    ]
  },
  "type": "Feature",
  "properties": {
    "hierarchy": [
      "tgn:2551695",
      "tgn:1000001",
      "tgn:7016172",
      "tgn:7012149",
      "tgn:7029392"
    ],
    "placetype": [
      "aat:300006075"
    ],
    "id": 2551695,
    "name:xx": "Number 45, Ditch"
  }
}
