{
  "geometry": {
    "type": "Point",
    "coordinates": [
      76.983333,
      20.25
    ]
  },
  "type": "Feature",
  "properties": {
    "hierarchy": [
      "tgn:7553880",
      "tgn:1000004",
      "tgn:7000198",
      "tgn:1001895",
      "tgn:7029392"
    ],
    "placetype": [
      "aat:300008347"
    ],
    "name:en": "Mālegaon",
    "id": 7553880
  }
}
