{
  "geometry": {
    "type": "Point",
    "coordinates": [
      11.7167,
      -16.5167
    ]
  },
  "type": "Feature",
  "properties": {
    "hierarchy": [
      "tgn:1012152",
      "tgn:7001242",
      "tgn:1000149",
      "tgn:7000392",
      "tgn:7029392"
    ],
    "placetype": [
      "aat:300386846"
    ],
    "id": 1012152,
    "name:xx": "Marca, Ponta da"
  }
}
