{
  "geometry": {
    "type": "Point",
    "coordinates": [
      79.8183,
      27.151
    ]
  },
  "type": "Feature",
  "properties": {
    "hierarchy": [
      "tgn:7562478",
      "tgn:1000004",
      "tgn:7000198",
      "tgn:7016722",
      "tgn:7029392"
    ],
    "placetype": [
      "aat:300008347"
    ],
    "name:en": "Badnādpur",
    "id": 7562478
  }
}
