{
  "geometry": {
    "type": "Point",
    "coordinates": [
      -100.0167,
      37.75
    ]
  },
  "type": "Feature",
  "properties": {
    "hierarchy": [
      "tgn:2187546",
      "tgn:1000001",
      "tgn:2000688",
      "tgn:7012149",
      "tgn:7007254",
      "tgn:7029392"
    ],
    "placetype": [
      "aat:300008798"
    ],
    "id": 2187546,
    "name:xx": "Boot Hill"
  }
}
