{
  "geometry": {
    "type": "Point",
    "coordinates": [
      -86.65,
      36.8833
    ]
  },
  "type": "Feature",
  "properties": {
    "hierarchy": [
      "tgn:2242937",
      "tgn:1000001",
      "tgn:7012149",
      "tgn:7007255",
      "tgn:7029392"
    ],
    "placetype": [
      "aat:300008706"
    ],
    "id": 2242937,
    "name:xx": "Clear Fork Creek"
  }
}
