{
  "geometry": {
    "type": "Point",
    "coordinates": [
      79.45962,
      26.066901
    ]
  },
  "type": "Feature",
  "properties": {
    "hierarchy": [
      "tgn:7565783",
      "tgn:1000004",
      "tgn:7000198",
      "tgn:7016722",
      "tgn:7029392"
    ],
    "placetype": [
      "aat:300008347"
    ],
    "name:en": "Lahūra",
    "id": 7565783
  }
}
