{
  "geometry": {
    "type": "Point",
    "coordinates": [
      -91.6333,
      34.8333
    ]
  },
  "type": "Feature",
  "properties": {
    "hierarchy": [
      "tgn:2505353",
      "tgn:1000001",
      "tgn:7016172",
      "tgn:7012149",
      "tgn:2000163",
      "tgn:7029392"
    ],
    "placetype": [
      "aat:300008699"
    ],
    "id": 2505353,
    "name:xx": "Mellon Branch"
  }
}
