{
  "geometry": {
    "type": "Point",
    "coordinates": [
      81.3333,
      30.95
    ]
  },
  "type": "Feature",
  "properties": {
    "hierarchy": [
      "tgn:1072190",
      "tgn:1000004",
      "tgn:7001319",
      "tgn:1000111",
      "tgn:7029392"
    ],
    "placetype": [
      "aat:300008347"
    ],
    "id": 1072190,
    "name:xx": "Taqin"
  }
}
