{
  "geometry": {
    "type": "Point",
    "coordinates": [
      -87.6167,
      46.4333
    ]
  },
  "type": "Feature",
  "properties": {
    "hierarchy": [
      "tgn:2566092",
      "tgn:1000001",
      "tgn:7012149",
      "tgn:2000975",
      "tgn:7007520",
      "tgn:7029392"
    ],
    "placetype": [
      "aat:300008680"
    ],
    "id": 2566092,
    "name:xx": "Palmer Lake"
  }
}
