{
  "geometry": {
    "type": "Point",
    "coordinates": [
      -137.8833,
      59.0333
    ]
  },
  "type": "Feature",
  "properties": {
    "hierarchy": [
      "tgn:2358394",
      "tgn:7006450",
      "tgn:1000001",
      "tgn:7012149",
      "tgn:7030574",
      "tgn:7029392"
    ],
    "placetype": [
      "aat:300008835"
    ],
    "id": 2358394,
    "name:xx": "Grand Plateau Glacier"
  }
}
