{
  "geometry": {
    "type": "Point",
    "coordinates": [
      -80.2667,
      40.9167
    ]
  },
  "type": "Feature",
  "properties": {
    "hierarchy": [
      "tgn:2501942",
      "tgn:1000001",
      "tgn:7012149",
      "tgn:1002580",
      "tgn:7007710",
      "tgn:7029392"
    ],
    "placetype": [
      "aat:300008699"
    ],
    "id": 2501942,
    "name:xx": "McKee Run"
  }
}
