{
  "type": "FeatureCollection",
  "features": [
    {
      "geometry": {
        "type": "Point",
        "coordinates": [
          31.574374,
          31.003041
        ]
      },
      "type": "Feature",
      "properties": {
        "hierarchy": [
          "tgn:7544300",
          "tgn:7001242",
          "tgn:1001059",
          "tgn:7016833",
          "tgn:7029392"
        ],
        "placetype": [
          "aat:300000206"
        ],
        "name:en": "'Izbat Ḩamzah al 'Adl",
        "id": 7544300
      }
    },
    {
      "geometry": {
        "type": "Point",
        "coordinates": [
          31.550621,
          31.004477
        ]
      },
      "type": "Feature",
      "properties": {
        "hierarchy": [
          "tgn:7544301",
          "tgn:7001242",
          "tgn:1001059",
          "tgn:7016833",
          "tgn:7029392"
        ],
        "placetype": [
          "aat:300000206"
        ],
        "name:en": "'Izbat 'Abduh al Jayyār",
        "id": 7544301
      }
    },
    {
      "geometry": {
        "type": "Point",
        "coordinates": [
          31.535333,
          31.00556
        ]
      },
      "type": "Feature",
      "properties": {
        "hierarchy": [
          "tgn:7544302",
          "tgn:7001242",
          "tgn:1001059",
          "tgn:7016833",
          "tgn:7029392"
        ],
        "placetype": [
          "aat:300008347"
        ],
        "name:en": "'Izbat Muḩammad Tawfīq",
        "id": 7544302
      }
    },
    {
      "geometry": {
        "type": "Point",
        "coordinates": [
          30.214781,
          30.893043
        ]
      },
      "type": "Feature",
      "properties": {
        "hierarchy": [
          "tgn:7544303",
          "tgn:7001242",
          "tgn:1001075",
          "tgn:7016833",
          "tgn:7029392"
        ],
        "placetype": [
          "aat:300008347"
        ],
        "name:en": "'Izbat al 'Inānī",
        "id": 7544303
      }
    },
    {
      "geometry": {
        "type": "Point",
        "coordinates": [
          30.231178,
          30.873749
        ]
      },
      "type": "Feature",
      "properties": {
        "hierarchy": [
          "tgn:7544304",
          "tgn:7001242",
          "tgn:1001075",
          "tgn:7016833",
          "tgn:7029392"
        ],
        "placetype": [
          "aat:300008347"
        ],
        "name:en": "'Izbat Nūbār",
        "id": 7544304
      }
    },
    {
      "geometry": {
        "type": "Point",
        "coordinates": [
          30.097689,
          30.867576
        ]
      },
      "type": "Feature",
      "properties": {
        "hierarchy": [
          "tgn:7544305",
          "tgn:7001242",
          "tgn:1001075",
          "tgn:7016833",
          "tgn:7029392"
        ],
        "placetype": [
          "aat:300008347"
        ],
        "name:en": "Naj' ar Ruzz",
        "id": 7544305
      }
    },
    {
      "geometry": {
        "type": "Point",
        "coordinates": [
          30.233225,
          30.84401
        ]
      },
      "type": "Feature",
      "properties": {
        "hierarchy": [
          "tgn:7544306",
          "tgn:7001242",
          "tgn:1001075",
          "tgn:7016833",
          "tgn:7029392"
        ],
        "placetype": [
          "aat:300008347"
        ],
        "name:en": "'Izbat Būghūş Nūbār ash Sharqīyah",
        "id": 7544306
      }
    },
    {
      "geometry": {
        "type": "Point",
        "coordinates": [
          30.223971,
          30.843681
        ]
      },
      "type": "Feature",
      "properties": {
        "hierarchy": [
          "tgn:7544307",
          "tgn:7001242",
          "tgn:1001075",
          "tgn:7016833",
          "tgn:7029392"
        ],
        "placetype": [
          "aat:300008347"
        ],
        "name:en": "'Izbat Būghūş Nūbār al Baḩarīyah",
        "id": 7544307
      }
    },
    {
      "geometry": {
        "type": "Point",
        "coordinates": [
          30.170253,
          30.839555
        ]
      },
      "type": "Feature",
      "properties": {
        "hierarchy": [
          "tgn:7544308",
          "tgn:7001242",
          "tgn:1001075",
          "tgn:7016833",
          "tgn:7029392"
        ],
        "placetype": [
          "aat:300008347"
        ],
        "name:en": "Naj' Sallām",
        "id": 7544308
      }
    },
    {
      "geometry": {
        "type": "Point",
        "coordinates": [
          30.200695,
          30.83219
        ]
      },
      "type": "Feature",
      "properties": {
        "hierarchy": [
          "tgn:7544309",
          "tgn:7001242",
          "tgn:1001075",
          "tgn:7016833",
          "tgn:7029392"
        ],
        "placetype": [
          "aat:300008347"
        ],
        "name:en": "Minshāt Jalāwah",
        "id": 7544309
      }
    }
  ]
}
