{
  "geometry": {
    "type": "Point",
    "coordinates": [
      5.3333,
      43.2167
    ]
  },
  "type": "Feature",
  "properties": {
    "hierarchy": [
      "tgn:1010615",
      "tgn:1000003",
      "tgn:1000070",
      "tgn:7002895",
      "tgn:7029392"
    ],
    "placetype": [
      "aat:300008850"
    ],
    "id": 1010615,
    "name:xx": "Croisette, Cap"
  }
}
