{
  "geometry": {
    "type": "Point",
    "coordinates": [
      -80.2667,
      36.3833
    ]
  },
  "type": "Feature",
  "properties": {
    "hierarchy": [
      "tgn:2779729",
      "tgn:1000001",
      "tgn:7012149",
      "tgn:2001541",
      "tgn:7007709",
      "tgn:7029392"
    ],
    "placetype": [
      "aat:300008798"
    ],
    "id": 2779729,
    "name:xx": "Wolf Rock"
  }
}
