{
  "geometry": {
    "type": "Point",
    "coordinates": [
      -96.7833,
      44.4167
    ]
  },
  "type": "Feature",
  "properties": {
    "hierarchy": [
      "tgn:2547976",
      "tgn:1000001",
      "tgn:2001775",
      "tgn:7012149",
      "tgn:7007713",
      "tgn:7029392"
    ],
    "placetype": [
      "aat:300008347"
    ],
    "id": 2547976,
    "name:xx": "North Grove Addition"
  }
}
