{
  "geometry": {
    "type": "Point",
    "coordinates": [
      74.492472,
      28.36027
    ]
  },
  "type": "Feature",
  "properties": {
    "hierarchy": [
      "tgn:7564183",
      "tgn:1000004",
      "tgn:7000198",
      "tgn:7016788",
      "tgn:7029392"
    ],
    "placetype": [
      "aat:300008347"
    ],
    "name:en": "Udāsar",
    "id": 7564183
  }
}
