{
  "geometry": {
    "type": "Point",
    "coordinates": [
      -112.2333,
      33.3167
    ]
  },
  "type": "Feature",
  "properties": {
    "hierarchy": [
      "tgn:1129637",
      "tgn:1000001",
      "tgn:7029392"
    ],
    "placetype": [
      "aat:300008707"
    ],
    "id": 1129637,
    "name:xx": "Santa Cruz, Río de"
  }
}
