{
  "geometry": {
    "type": "Point",
    "coordinates": [
      87.1333,
      23.6667
    ]
  },
  "type": "Feature",
  "properties": {
    "hierarchy": [
      "tgn:1077130",
      "tgn:1000004",
      "tgn:7000198",
      "tgn:1001977",
      "tgn:7029392"
    ],
    "placetype": [
      "aat:300008347"
    ],
    "id": 1077130,
    "name:xx": "Tapasi"
  }
}
