{
  "geometry": {
    "type": "Point",
    "coordinates": [
      -76.2333,
      38.3667
    ]
  },
  "type": "Feature",
  "properties": {
    "hierarchy": [
      "tgn:2595256",
      "tgn:1002338",
      "tgn:1000001",
      "tgn:7012149",
      "tgn:7007516",
      "tgn:7029392"
    ],
    "placetype": [
      "aat:300008706"
    ],
    "id": 2595256,
    "name:xx": "Pot Island Creek"
  }
}
