{
  "geometry": {
    "type": "Point",
    "coordinates": [
      -70.4333,
      -40.55
    ]
  },
  "type": "Feature",
  "properties": {
    "hierarchy": [
      "tgn:1019833",
      "tgn:7006477",
      "tgn:7006348",
      "tgn:1000002",
      "tgn:7029392"
    ],
    "placetype": [
      "aat:300008347"
    ],
    "id": 1019833,
    "name:xx": "Paso Limay"
  }
}
