{
  "geometry": {
    "type": "Point",
    "coordinates": [
      -83.5667,
      29.7667
    ]
  },
  "type": "Feature",
  "properties": {
    "hierarchy": [
      "tgn:2371136",
      "tgn:1000001",
      "tgn:7012149",
      "tgn:2000287",
      "tgn:7007240",
      "tgn:7029392"
    ],
    "placetype": [
      "aat:300132316"
    ],
    "id": 2371136,
    "name:xx": "Hagens Cove"
  }
}
