{
  "geometry": {
    "type": "Point",
    "coordinates": [
      -118.4167,
      46.55
    ]
  },
  "type": "Feature",
  "properties": {
    "hierarchy": [
      "tgn:2261976",
      "tgn:1000001",
      "tgn:7012149",
      "tgn:2002251",
      "tgn:7007920",
      "tgn:7029392"
    ],
    "placetype": [
      "aat:300008761"
    ],
    "id": 2261976,
    "name:xx": "Cow Bar Canyon"
  }
}
