{
  "geometry": {
    "type": "Point",
    "coordinates": [
      -111.2167,
      39.75
    ]
  },
  "type": "Feature",
  "properties": {
    "hierarchy": [
      "tgn:2529851",
      "tgn:1000001",
      "tgn:2002104",
      "tgn:7012149",
      "tgn:7007827",
      "tgn:7029392"
    ],
    "placetype": [
      "aat:300266640"
    ],
    "id": 2529851,
    "name:xx": "Mud Ridge"
  }
}
