{
  "type": "FeatureCollection",
  "features": [
    {
      "geometry": {
        "type": "Point",
        "coordinates": [
          -120.8333,
          42.2
        ]
      },
      "type": "Feature",
      "properties": {
        "hierarchy": [
          "tgn:2775570",
          "tgn:1000001",
          "tgn:7012149",
          "tgn:2001715",
          "tgn:7007708",
          "tgn:7029392"
        ],
        "placetype": [
          "aat:300008706"
        ],
        "id": 2775570,
        "name:xx": "Wilson Creek"
      }
    },
    {
      "geometry": {
        "type": "Point",
        "coordinates": [
          -119.5667,
          44.1167
        ]
      },
      "type": "Feature",
      "properties": {
        "hierarchy": [
          "tgn:2775571",
          "tgn:1000001",
          "tgn:7012149",
          "tgn:2001708",
          "tgn:7007708",
          "tgn:7029392"
        ],
        "placetype": [
          "aat:300008706"
        ],
        "id": 2775571,
        "name:xx": "Wilson Creek"
      }
    },
    {
      "geometry": {
        "type": "Point",
        "coordinates": [
          -75.2167,
          41.2833
        ]
      },
      "type": "Feature",
      "properties": {
        "hierarchy": [
          "tgn:2775572",
          "tgn:1000001",
          "tgn:7012149",
          "tgn:1002789",
          "tgn:7007710",
          "tgn:7029392"
        ],
        "placetype": [
          "aat:300008706"
        ],
        "id": 2775572,
        "name:xx": "Wilson Creek"
      }
    },
    {
      "geometry": {
        "type": "Point",
        "coordinates": [
          -77.0333,
          41.7167
        ]
      },
      "type": "Feature",
      "properties": {
        "hierarchy": [
          "tgn:2775573",
          "tgn:1000001",
          "tgn:7012149",
          "tgn:1002945",
          "tgn:7007710",
          "tgn:7029392"
        ],
        "placetype": [
          "aat:300008706"
        ],
        "id": 2775573,
        "name:xx": "Wilson Creek"
      }
    },
    {
      "geometry": {
        "type": "Point",
        "coordinates": [
          -79.0333,
          39.9333
        ]
      },
      "type": "Feature",
      "properties": {
        "hierarchy": [
          "tgn:2775574",
          "tgn:1000001",
          "tgn:7012149",
          "tgn:1002904",
          "tgn:7007710",
          "tgn:7029392"
        ],
        "placetype": [
          "aat:300008706"
        ],
        "id": 2775574,
        "name:xx": "Wilson Creek"
      }
    },
    {
      "geometry": {
        "type": "Point",
        "coordinates": [
          -75.5,
          41.6333
        ]
      },
      "type": "Feature",
      "properties": {
        "hierarchy": [
          "tgn:2775575",
          "tgn:1000001",
          "tgn:7012149",
          "tgn:1002564",
          "tgn:7007710",
          "tgn:7029392"
        ],
        "placetype": [
          "aat:300008706"
        ],
        "id": 2775575,
        "name:xx": "Wilson Creek"
      }
    },
    {
      "geometry": {
        "type": "Point",
        "coordinates": [
          -82.1833,
          34.6833
        ]
      },
      "type": "Feature",
      "properties": {
        "hierarchy": [
          "tgn:2775576",
          "tgn:1000001",
          "tgn:7012149",
          "tgn:7007712",
          "tgn:7029392"
        ],
        "placetype": [
          "aat:300008706"
        ],
        "id": 2775576,
        "name:xx": "Wilson Creek"
      }
    },
    {
      "geometry": {
        "type": "Point",
        "coordinates": [
          -83.0333,
          34.9833
        ]
      },
      "type": "Feature",
      "properties": {
        "hierarchy": [
          "tgn:2775577",
          "tgn:1000001",
          "tgn:7012149",
          "tgn:2001761",
          "tgn:7007712",
          "tgn:7029392"
        ],
        "placetype": [
          "aat:300008706"
        ],
        "id": 2775577,
        "name:xx": "Wilson Creek"
      }
    },
    {
      "geometry": {
        "type": "Point",
        "coordinates": [
          -81.9333,
          34.1833
        ]
      },
      "type": "Feature",
      "properties": {
        "hierarchy": [
          "tgn:2775578",
          "tgn:1000001",
          "tgn:2001748",
          "tgn:7012149",
          "tgn:7007712",
          "tgn:7029392"
        ],
        "placetype": [
          "aat:300008706"
        ],
        "id": 2775578,
        "name:xx": "Wilson Creek"
      }
    },
    {
      "geometry": {
        "type": "Point",
        "coordinates": [
          -88.6667,
          35.2167
        ]
      },
      "type": "Feature",
      "properties": {
        "hierarchy": [
          "tgn:2775579",
          "tgn:1000001",
          "tgn:7012149",
          "tgn:7022544",
          "tgn:7007825",
          "tgn:7029392"
        ],
        "placetype": [
          "aat:300008706"
        ],
        "id": 2775579,
        "name:xx": "Wilson Creek"
      }
    }
  ]
}
