{
  "geometry": {
    "type": "Point",
    "coordinates": [
      -96.9333,
      38.6667
    ]
  },
  "type": "Feature",
  "properties": {
    "hierarchy": [
      "tgn:2036493",
      "tgn:1000001",
      "tgn:2000680",
      "tgn:7012149",
      "tgn:7007254",
      "tgn:7029392"
    ],
    "placetype": [
      "aat:300008347"
    ],
    "id": 2036493,
    "name:xx": "Herington"
  }
}
