{
  "type": "FeatureCollection",
  "features": [
    {
      "geometry": {
        "type": "Point",
        "coordinates": [
          -88.95,
          34.9833
        ]
      },
      "type": "Feature",
      "properties": {
        "hierarchy": [
          "tgn:2296840",
          "tgn:1000001",
          "tgn:7012149",
          "tgn:2001155",
          "tgn:7007522",
          "tgn:7029392"
        ],
        "placetype": [
          "aat:300008706"
        ],
        "id": 2296840,
        "name:xx": "Dry Creek"
      }
    },
    {
      "geometry": {
        "type": "Point",
        "coordinates": [
          -89.5833,
          31.05
        ]
      },
      "type": "Feature",
      "properties": {
        "hierarchy": [
          "tgn:2296841",
          "tgn:1000001",
          "tgn:7012149",
          "tgn:2001122",
          "tgn:7007522",
          "tgn:7029392"
        ],
        "placetype": [
          "aat:300008706"
        ],
        "id": 2296841,
        "name:xx": "Dry Creek"
      }
    },
    {
      "geometry": {
        "type": "Point",
        "coordinates": [
          -90.1833,
          31.1833
        ]
      },
      "type": "Feature",
      "properties": {
        "hierarchy": [
          "tgn:2296842",
          "tgn:1000001",
          "tgn:7012149",
          "tgn:2001159",
          "tgn:7007522",
          "tgn:7029392"
        ],
        "placetype": [
          "aat:300008706"
        ],
        "id": 2296842,
        "name:xx": "Dry Creek"
      }
    },
    {
      "geometry": {
        "type": "Point",
        "coordinates": [
          -91,
          31.45
        ]
      },
      "type": "Feature",
      "properties": {
        "hierarchy": [
          "tgn:2296843",
          "tgn:1000001",
          "tgn:7012149",
          "tgn:2001104",
          "tgn:7007522",
          "tgn:7029392"
        ],
        "placetype": [
          "aat:300008706"
        ],
        "id": 2296843,
        "name:xx": "Dry Creek"
      }
    },
    {
      "geometry": {
        "type": "Point",
        "coordinates": [
          -89.1333,
          31.55
        ]
      },
      "type": "Feature",
      "properties": {
        "hierarchy": [
          "tgn:2296844",
          "tgn:1000001",
          "tgn:7012149",
          "tgn:2001119",
          "tgn:7007522",
          "tgn:7029392"
        ],
        "placetype": [
          "aat:300008706"
        ],
        "id": 2296844,
        "name:xx": "Dry Creek"
      }
    },
    {
      "geometry": {
        "type": "Point",
        "coordinates": [
          -89.8833,
          32.1167
        ]
      },
      "type": "Feature",
      "properties": {
        "hierarchy": [
          "tgn:2296845",
          "tgn:1000001",
          "tgn:7012149",
          "tgn:2001146",
          "tgn:7007522",
          "tgn:7029392"
        ],
        "placetype": [
          "aat:300008706"
        ],
        "id": 2296845,
        "name:xx": "Dry Creek"
      }
    },
    {
      "geometry": {
        "type": "Point",
        "coordinates": [
          -88.9667,
          32.75
        ]
      },
      "type": "Feature",
      "properties": {
        "hierarchy": [
          "tgn:2296846",
          "tgn:1000001",
          "tgn:7012149",
          "tgn:2001135",
          "tgn:7007522",
          "tgn:7029392"
        ],
        "placetype": [
          "aat:300008706"
        ],
        "id": 2296846,
        "name:xx": "Dry Creek"
      }
    },
    {
      "geometry": {
        "type": "Point",
        "coordinates": [
          -89.85,
          32.6
        ]
      },
      "type": "Feature",
      "properties": {
        "hierarchy": [
          "tgn:2296847",
          "tgn:1000001",
          "tgn:7012149",
          "tgn:2001130",
          "tgn:7007522",
          "tgn:7029392"
        ],
        "placetype": [
          "aat:300008706"
        ],
        "id": 2296847,
        "name:xx": "Dry Creek"
      }
    },
    {
      "geometry": {
        "type": "Point",
        "coordinates": [
          -89.2,
          33.0333
        ]
      },
      "type": "Feature",
      "properties": {
        "hierarchy": [
          "tgn:2296848",
          "tgn:1000001",
          "tgn:7012149",
          "tgn:2001165",
          "tgn:7007522",
          "tgn:7029392"
        ],
        "placetype": [
          "aat:300008706"
        ],
        "id": 2296848,
        "name:xx": "Dry Creek"
      }
    },
    {
      "geometry": {
        "type": "Point",
        "coordinates": [
          -88.65,
          33.0833
        ]
      },
      "type": "Feature",
      "properties": {
        "hierarchy": [
          "tgn:2296849",
          "tgn:1000001",
          "tgn:7012149",
          "tgn:2001137",
          "tgn:7007522",
          "tgn:7029392"
        ],
        "placetype": [
          "aat:300008706"
        ],
        "id": 2296849,
        "name:xx": "Dry Creek"
      }
    }
  ]
}
