{
  "geometry": {
    "type": "Point",
    "coordinates": [
      29.2833,
      61.9167
    ]
  },
  "type": "Feature",
  "properties": {
    "hierarchy": [
      "tgn:1031370",
      "tgn:7594381",
      "tgn:1000003",
      "tgn:1000069",
      "tgn:7029392"
    ],
    "placetype": [
      "aat:300008347"
    ],
    "id": 1031370,
    "name:xx": "Kerimäki"
  }
}
