{
  "geometry": {
    "type": "Point",
    "coordinates": [
      -81.6167,
      25.9333
    ]
  },
  "type": "Feature",
  "properties": {
    "hierarchy": [
      "tgn:2448032",
      "tgn:1000001",
      "tgn:1002289",
      "tgn:7012149",
      "tgn:7007240",
      "tgn:7029392"
    ],
    "placetype": [
      "aat:300132316"
    ],
    "id": 2448032,
    "name:xx": "Lighter Bay"
  }
}
