{
  "geometry": {
    "type": "Point",
    "coordinates": [
      -73.4333,
      41.35
    ]
  },
  "type": "Feature",
  "properties": {
    "hierarchy": [
      "tgn:2527985",
      "tgn:1002366",
      "tgn:1000001",
      "tgn:7012149",
      "tgn:7007159",
      "tgn:7029392"
    ],
    "placetype": [
      "aat:300006191"
    ],
    "id": 2527985,
    "name:xx": "Mountain Pond"
  }
}
