{
  "geometry": {
    "type": "Point",
    "coordinates": [
      -87.15,
      35.5667
    ]
  },
  "type": "Feature",
  "properties": {
    "hierarchy": [
      "tgn:2217665",
      "tgn:1000001",
      "tgn:7012149",
      "tgn:2001896",
      "tgn:7007825",
      "tgn:7029392"
    ],
    "placetype": [
      "aat:300006191"
    ],
    "id": 2217665,
    "name:xx": "Campbell Lake"
  }
}
