{
  "type": "FeatureCollection",
  "features": [
    {
      "geometry": {
        "type": "Point",
        "coordinates": [
          -107.7833,
          37.05
        ]
      },
      "type": "Feature",
      "properties": {
        "hierarchy": [
          "tgn:2757260",
          "tgn:1000001",
          "tgn:7012149",
          "tgn:2000225",
          "tgn:7007158",
          "tgn:7029392"
        ],
        "placetype": [
          "aat:300008761"
        ],
        "id": 2757260,
        "name:xx": "West Alamo Canyon"
      }
    },
    {
      "geometry": {
        "type": "Point",
        "coordinates": [
          -102.5,
          35.4
        ]
      },
      "type": "Feature",
      "properties": {
        "hierarchy": [
          "tgn:2757261",
          "tgn:1000001",
          "tgn:7012149",
          "tgn:2002051",
          "tgn:7007826",
          "tgn:7029392"
        ],
        "placetype": [
          "aat:300008706"
        ],
        "id": 2757261,
        "name:xx": "West Alamosa Creek"
      }
    },
    {
      "geometry": {
        "type": "Point",
        "coordinates": [
          -150.85,
          68.1333
        ]
      },
      "type": "Feature",
      "properties": {
        "hierarchy": [
          "tgn:2757262",
          "tgn:7006450",
          "tgn:1000001",
          "tgn:7012149",
          "tgn:2124005",
          "tgn:7029392"
        ],
        "placetype": [
          "aat:300008835"
        ],
        "id": 2757262,
        "name:xx": "West Alapah Glacier"
      }
    },
    {
      "geometry": {
        "type": "Point",
        "coordinates": [
          -87.5,
          44.5333
        ]
      },
      "type": "Feature",
      "properties": {
        "hierarchy": [
          "tgn:2757263",
          "tgn:1000001",
          "tgn:7012149",
          "tgn:2002330",
          "tgn:7007922",
          "tgn:7029392"
        ],
        "placetype": [
          "aat:300008680"
        ],
        "id": 2757263,
        "name:xx": "West Alaska Lake"
      }
    },
    {
      "geometry": {
        "type": "Point",
        "coordinates": [
          -78.5167,
          42.8833
        ]
      },
      "type": "Feature",
      "properties": {
        "hierarchy": [
          "tgn:2757264",
          "tgn:1000001",
          "tgn:7012149",
          "tgn:1002356",
          "tgn:7007568",
          "tgn:7029392"
        ],
        "placetype": [
          "aat:300008347"
        ],
        "id": 2757264,
        "name:xx": "West Alden"
      }
    },
    {
      "geometry": {
        "type": "Point",
        "coordinates": [
          -106.7167,
          37.8
        ]
      },
      "type": "Feature",
      "properties": {
        "hierarchy": [
          "tgn:2757265",
          "tgn:1000001",
          "tgn:7012149",
          "tgn:7007158",
          "tgn:7029392"
        ],
        "placetype": [
          "aat:300008706"
        ],
        "id": 2757265,
        "name:xx": "West Alder Creek"
      }
    },
    {
      "geometry": {
        "type": "Point",
        "coordinates": [
          -108.2167,
          48.2
        ]
      },
      "type": "Feature",
      "properties": {
        "hierarchy": [
          "tgn:2757266",
          "tgn:1000001",
          "tgn:7012149",
          "tgn:2001295",
          "tgn:7007524",
          "tgn:7029392"
        ],
        "placetype": [
          "aat:300008706"
        ],
        "id": 2757266,
        "name:xx": "West Alkali Creek"
      }
    },
    {
      "geometry": {
        "type": "Point",
        "coordinates": [
          -108.4,
          42.25
        ]
      },
      "type": "Feature",
      "properties": {
        "hierarchy": [
          "tgn:2757267",
          "tgn:1000001",
          "tgn:7012149",
          "tgn:7007923",
          "tgn:7029392"
        ],
        "placetype": [
          "aat:300008706"
        ],
        "id": 2757267,
        "name:xx": "West Alkali Creek"
      }
    },
    {
      "geometry": {
        "type": "Point",
        "coordinates": [
          -108.1333,
          37.2667
        ]
      },
      "type": "Feature",
      "properties": {
        "hierarchy": [
          "tgn:2757268",
          "tgn:1000001",
          "tgn:7012149",
          "tgn:2000225",
          "tgn:7007158",
          "tgn:7029392"
        ],
        "placetype": [
          "aat:300008761"
        ],
        "id": 2757268,
        "name:xx": "West Alkali Gulch"
      }
    },
    {
      "geometry": {
        "type": "Point",
        "coordinates": [
          -108.0667,
          48.2
        ]
      },
      "type": "Feature",
      "properties": {
        "hierarchy": [
          "tgn:2757269",
          "tgn:1000001",
          "tgn:7012149",
          "tgn:2001295",
          "tgn:7007524",
          "tgn:7029392"
        ],
        "placetype": [
          "aat:300006191"
        ],
        "id": 2757269,
        "name:xx": "West Alkali Reservoir"
      }
    }
  ]
}
