{
  "type": "FeatureCollection",
  "features": [
    {
      "geometry": {
        "type": "Point",
        "coordinates": [
          -98.0333,
          31.5167
        ]
      },
      "type": "Feature",
      "properties": {
        "hierarchy": [
          "tgn:2297470",
          "tgn:1000001",
          "tgn:7012149",
          "tgn:1002303",
          "tgn:7007826",
          "tgn:7029392"
        ],
        "placetype": [
          "aat:300008699"
        ],
        "id": 2297470,
        "name:xx": "Dry Fork"
      }
    },
    {
      "geometry": {
        "type": "Point",
        "coordinates": [
          -93.8667,
          31.6667
        ]
      },
      "type": "Feature",
      "properties": {
        "hierarchy": [
          "tgn:2297471",
          "tgn:1000001",
          "tgn:7012149",
          "tgn:2002073",
          "tgn:7007826",
          "tgn:7029392"
        ],
        "placetype": [
          "aat:300008699"
        ],
        "id": 2297471,
        "name:xx": "Dry Fork"
      }
    },
    {
      "geometry": {
        "type": "Point",
        "coordinates": [
          -96.1167,
          33.75
        ]
      },
      "type": "Feature",
      "properties": {
        "hierarchy": [
          "tgn:2297472",
          "tgn:1000001",
          "tgn:7012149",
          "tgn:2001983",
          "tgn:7007826",
          "tgn:7029392"
        ],
        "placetype": [
          "aat:300008699"
        ],
        "id": 2297472,
        "name:xx": "Dry Fork"
      }
    },
    {
      "geometry": {
        "type": "Point",
        "coordinates": [
          -98.4667,
          32.2667
        ]
      },
      "type": "Feature",
      "properties": {
        "hierarchy": [
          "tgn:2297473",
          "tgn:1000001",
          "tgn:7012149",
          "tgn:7007826",
          "tgn:7029392"
        ],
        "placetype": [
          "aat:300008699"
        ],
        "id": 2297473,
        "name:xx": "Dry Fork"
      }
    },
    {
      "geometry": {
        "type": "Point",
        "coordinates": [
          -113.45,
          37.35
        ]
      },
      "type": "Feature",
      "properties": {
        "hierarchy": [
          "tgn:2297474",
          "tgn:1000001",
          "tgn:7012149",
          "tgn:2002127",
          "tgn:7007827",
          "tgn:7029392"
        ],
        "placetype": [
          "aat:300008699"
        ],
        "id": 2297474,
        "name:xx": "Dry Fork"
      }
    },
    {
      "geometry": {
        "type": "Point",
        "coordinates": [
          -112.3833,
          37.4333
        ]
      },
      "type": "Feature",
      "properties": {
        "hierarchy": [
          "tgn:2297475",
          "tgn:1000001",
          "tgn:7012149",
          "tgn:2002113",
          "tgn:7007827",
          "tgn:7029392"
        ],
        "placetype": [
          "aat:300008699"
        ],
        "id": 2297475,
        "name:xx": "Dry Fork"
      }
    },
    {
      "geometry": {
        "type": "Point",
        "coordinates": [
          -112.65,
          37.75
        ]
      },
      "type": "Feature",
      "properties": {
        "hierarchy": [
          "tgn:2297476",
          "tgn:1000001",
          "tgn:2002109",
          "tgn:7012149",
          "tgn:7007827",
          "tgn:7029392"
        ],
        "placetype": [
          "aat:300008699"
        ],
        "id": 2297476,
        "name:xx": "Dry Fork"
      }
    },
    {
      "geometry": {
        "type": "Point",
        "coordinates": [
          -109.7333,
          38.55
        ]
      },
      "type": "Feature",
      "properties": {
        "hierarchy": [
          "tgn:2297477",
          "tgn:1000001",
          "tgn:7012149",
          "tgn:2002110",
          "tgn:7007827",
          "tgn:7029392"
        ],
        "placetype": [
          "aat:300008699"
        ],
        "id": 2297477,
        "name:xx": "Dry Fork"
      }
    },
    {
      "geometry": {
        "type": "Point",
        "coordinates": [
          -111.3333,
          38.95
        ]
      },
      "type": "Feature",
      "properties": {
        "hierarchy": [
          "tgn:2297478",
          "tgn:1000001",
          "tgn:7012149",
          "tgn:2002121",
          "tgn:7007827",
          "tgn:7029392"
        ],
        "placetype": [
          "aat:300008699"
        ],
        "id": 2297478,
        "name:xx": "Dry Fork"
      }
    },
    {
      "geometry": {
        "type": "Point",
        "coordinates": [
          -111.7667,
          39.3167
        ]
      },
      "type": "Feature",
      "properties": {
        "hierarchy": [
          "tgn:2297479",
          "tgn:1000001",
          "tgn:7012149",
          "tgn:2002120",
          "tgn:7007827",
          "tgn:7029392"
        ],
        "placetype": [
          "aat:300008699"
        ],
        "id": 2297479,
        "name:xx": "Dry Fork"
      }
    }
  ]
}
