{
  "type": "FeatureCollection",
  "features": [
    {
      "geometry": {
        "type": "Point",
        "coordinates": [
          14.15,
          48.7833
        ]
      },
      "type": "Feature",
      "properties": {
        "hierarchy": [
          "tgn:6002832",
          "tgn:7011506",
          "tgn:1000003",
          "tgn:1001780",
          "tgn:7029392"
        ],
        "placetype": [
          "aat:300008347",
          "aat:300000835",
          "aat:300008375"
        ],
        "id": 6002832,
        "name:xx": "Jankau"
      }
    },
    {
      "geometry": {
        "type": "Point",
        "coordinates": [
          44.9167,
          35.5667
        ]
      },
      "type": "Feature",
      "properties": {
        "hierarchy": [
          "tgn:6002834",
          "tgn:1001115",
          "tgn:1000004",
          "tgn:1000118",
          "tgn:7029392"
        ],
        "placetype": [
          "aat:300008347",
          "aat:300000810",
          "aat:300167671"
        ],
        "id": 6002834,
        "name:xx": "Jarmo"
      }
    }
  ]
}
