{
  "geometry": {
    "type": "Point",
    "coordinates": [
      -85.7167,
      34.5667
    ]
  },
  "type": "Feature",
  "properties": {
    "hierarchy": [
      "tgn:2173096",
      "tgn:7002659",
      "tgn:1000001",
      "tgn:7012149",
      "tgn:7021514",
      "tgn:7029392"
    ],
    "placetype": [
      "aat:300008699"
    ],
    "id": 2173096,
    "name:xx": "Bing Branch"
  }
}
