{
  "geometry": {
    "type": "Point",
    "coordinates": [
      79.363657,
      26.066822
    ]
  },
  "type": "Feature",
  "properties": {
    "hierarchy": [
      "tgn:7565775",
      "tgn:1000004",
      "tgn:7000198",
      "tgn:7016722",
      "tgn:7029392"
    ],
    "placetype": [
      "aat:300008347"
    ],
    "name:en": "Rūra Mallu",
    "id": 7565775
  }
}
