{
  "geometry": {
    "type": "Point",
    "coordinates": [
      -81.15,
      34.0333
    ]
  },
  "type": "Feature",
  "properties": {
    "hierarchy": [
      "tgn:2256902",
      "tgn:1000001",
      "tgn:7012149",
      "tgn:2001756",
      "tgn:7007712",
      "tgn:7029392"
    ],
    "placetype": [
      "aat:300006191"
    ],
    "id": 2256902,
    "name:xx": "Corley Millpond"
  }
}
