{
  "type": "FeatureCollection",
  "features": [
    {
      "geometry": {
        "type": "Point",
        "coordinates": [
          13.383333,
          50.883333
        ]
      },
      "type": "Feature",
      "properties": {
        "hierarchy": [
          "tgn:7112460",
          "tgn:1000003",
          "tgn:7003685",
          "tgn:7000084",
          "tgn:7029392"
        ],
        "placetype": [
          "aat:300000206"
        ],
        "id": 7112460,
        "name:xx": "Rosinhäuschen"
      }
    },
    {
      "geometry": {
        "type": "Point",
        "coordinates": [
          6.75,
          51.866667
        ]
      },
      "type": "Feature",
      "properties": {
        "hierarchy": [
          "tgn:7112461",
          "tgn:1000003",
          "tgn:7003677",
          "tgn:7000084",
          "tgn:7029392"
        ],
        "placetype": [
          "aat:300008863"
        ],
        "id": 7112461,
        "name:xx": "Rösing Busch"
      }
    },
    {
      "geometry": {
        "type": "Point",
        "coordinates": [
          7.55,
          52.1
        ]
      },
      "type": "Feature",
      "properties": {
        "hierarchy": [
          "tgn:7112462",
          "tgn:1000003",
          "tgn:7003677",
          "tgn:7000084",
          "tgn:7029392"
        ],
        "placetype": [
          "aat:300008699"
        ],
        "id": 7112462,
        "name:xx": "Rösing-Bach"
      }
    },
    {
      "geometry": {
        "type": "Point",
        "coordinates": [
          11.233333,
          48.7
        ]
      },
      "type": "Feature",
      "properties": {
        "hierarchy": [
          "tgn:7112464",
          "tgn:7003669",
          "tgn:1000003",
          "tgn:7000084",
          "tgn:7029392"
        ],
        "placetype": [
          "aat:300008347"
        ],
        "id": 7112464,
        "name:xx": "Rosing"
      }
    },
    {
      "geometry": {
        "type": "Point",
        "coordinates": [
          10.5,
          53.95
        ]
      },
      "type": "Feature",
      "properties": {
        "hierarchy": [
          "tgn:7112465",
          "tgn:1000003",
          "tgn:7003688",
          "tgn:7000084",
          "tgn:7029392"
        ],
        "placetype": [
          "aat:300000206"
        ],
        "id": 7112465,
        "name:xx": "Rösing"
      }
    },
    {
      "geometry": {
        "type": "Point",
        "coordinates": [
          8.366667,
          50.4
        ]
      },
      "type": "Feature",
      "properties": {
        "hierarchy": [
          "tgn:7112466",
          "tgn:1000003",
          "tgn:7003678",
          "tgn:7000084",
          "tgn:7029392"
        ],
        "placetype": [
          "aat:300008347"
        ],
        "id": 7112466,
        "name:xx": "Rohnstadt"
      }
    },
    {
      "geometry": {
        "type": "Point",
        "coordinates": [
          7.95,
          51.366667
        ]
      },
      "type": "Feature",
      "properties": {
        "hierarchy": [
          "tgn:7112467",
          "tgn:1000003",
          "tgn:7003677",
          "tgn:7000084",
          "tgn:7029392"
        ],
        "placetype": [
          "aat:300008863"
        ],
        "id": 7112467,
        "name:xx": "Rohnscheid"
      }
    },
    {
      "geometry": {
        "type": "Point",
        "coordinates": [
          9.866667,
          51.933333
        ]
      },
      "type": "Feature",
      "properties": {
        "hierarchy": [
          "tgn:7112468",
          "tgn:1000003",
          "tgn:7003676",
          "tgn:7000084",
          "tgn:7029392"
        ],
        "placetype": [
          "aat:300000206"
        ],
        "id": 7112468,
        "name:xx": "Röhnkrug"
      }
    },
    {
      "geometry": {
        "type": "Point",
        "coordinates": [
          9.1,
          47.75
        ]
      },
      "type": "Feature",
      "properties": {
        "hierarchy": [
          "tgn:7112469",
          "tgn:7003692",
          "tgn:1000003",
          "tgn:7000084",
          "tgn:7029392"
        ],
        "placetype": [
          "aat:300000206"
        ],
        "id": 7112469,
        "name:xx": "Rohnhausen"
      }
    }
  ]
}
