{
  "geometry": {
    "type": "Point",
    "coordinates": [
      -74.4167,
      41.3333
    ]
  },
  "type": "Feature",
  "properties": {
    "hierarchy": [
      "tgn:2301915",
      "tgn:1000001",
      "tgn:7012149",
      "tgn:1002751",
      "tgn:7007568",
      "tgn:7029392"
    ],
    "placetype": [
      "aat:300006075"
    ],
    "id": 2301915,
    "name:xx": "Durlandville Ditch"
  }
}
