{
  "geometry": {
    "type": "Point",
    "coordinates": [
      -80.7167,
      39.15
    ]
  },
  "type": "Feature",
  "properties": {
    "hierarchy": [
      "tgn:2726450",
      "tgn:1000001",
      "tgn:2002260",
      "tgn:7012149",
      "tgn:7013961",
      "tgn:7029392"
    ],
    "placetype": [
      "aat:300008699"
    ],
    "id": 2726450,
    "name:xx": "Town Camp Run"
  }
}
