{
  "geometry": {
    "type": "Point",
    "coordinates": [
      -81.8667,
      35.5833
    ]
  },
  "type": "Feature",
  "properties": {
    "hierarchy": [
      "tgn:2530607",
      "tgn:1000001",
      "tgn:7012149",
      "tgn:2001514",
      "tgn:7007709",
      "tgn:7029392"
    ],
    "placetype": [
      "aat:300006191"
    ],
    "id": 2530607,
    "name:xx": "Muddy Creek B S A Lake"
  }
}
