{
  "type": "FeatureCollection",
  "features": [
    {
      "geometry": {
        "type": "Point",
        "coordinates": [
          22.766667,
          39.15
        ]
      },
      "type": "Feature",
      "properties": {
        "hierarchy": [
          "tgn:7223040",
          "tgn:7002751",
          "tgn:7001399",
          "tgn:1000003",
          "tgn:1000074",
          "tgn:7029392"
        ],
        "placetype": [
          "aat:300008347"
        ],
        "id": 7223040,
        "name:xx": "Plátanos"
      }
    },
    {
      "geometry": {
        "type": "Point",
        "coordinates": [
          21.835,
          39.085556
        ]
      },
      "type": "Feature",
      "properties": {
        "hierarchy": [
          "tgn:7223041",
          "tgn:4003773",
          "tgn:7001395",
          "tgn:1000003",
          "tgn:1000074",
          "tgn:7029392"
        ],
        "placetype": [
          "aat:300008347"
        ],
        "id": 7223041,
        "name:xx": "Plátanos"
      }
    },
    {
      "geometry": {
        "type": "Point",
        "coordinates": [
          21.8,
          38.6
        ]
      },
      "type": "Feature",
      "properties": {
        "hierarchy": [
          "tgn:7223042",
          "tgn:4003773",
          "tgn:7001395",
          "tgn:1000003",
          "tgn:1000074",
          "tgn:7029392"
        ],
        "placetype": [
          "aat:300008347"
        ],
        "id": 7223042,
        "name:xx": "Plátanos"
      }
    },
    {
      "geometry": {
        "type": "Point",
        "coordinates": [
          21.316667,
          38.6
        ]
      },
      "type": "Feature",
      "properties": {
        "hierarchy": [
          "tgn:7223043",
          "tgn:7002680",
          "tgn:7001395",
          "tgn:1000003",
          "tgn:1000074",
          "tgn:7029392"
        ],
        "placetype": [
          "aat:300008347"
        ],
        "id": 7223043,
        "name:xx": "Plátanos"
      }
    },
    {
      "geometry": {
        "type": "Point",
        "coordinates": [
          22.266667,
          38.166667
        ]
      },
      "type": "Feature",
      "properties": {
        "hierarchy": [
          "tgn:7223044",
          "tgn:7002741",
          "tgn:7017076",
          "tgn:1000003",
          "tgn:1000074",
          "tgn:7029392"
        ],
        "placetype": [
          "aat:300008347"
        ],
        "id": 7223044,
        "name:xx": "Plátanos"
      }
    },
    {
      "geometry": {
        "type": "Point",
        "coordinates": [
          21.866667,
          38.05
        ]
      },
      "type": "Feature",
      "properties": {
        "hierarchy": [
          "tgn:7223045",
          "tgn:7002743",
          "tgn:7017076",
          "tgn:1000003",
          "tgn:1000074",
          "tgn:7029392"
        ],
        "placetype": [
          "aat:300008347"
        ],
        "id": 7223045,
        "name:xx": "Plátanos"
      }
    },
    {
      "geometry": {
        "type": "Point",
        "coordinates": [
          21.616667,
          37.666667
        ]
      },
      "type": "Feature",
      "properties": {
        "hierarchy": [
          "tgn:7223046",
          "tgn:7002743",
          "tgn:7017076",
          "tgn:1000003",
          "tgn:1000074",
          "tgn:7029392"
        ],
        "placetype": [
          "aat:300008347"
        ],
        "id": 7223046,
        "name:xx": "Plátanos"
      }
    },
    {
      "geometry": {
        "type": "Point",
        "coordinates": [
          22.65,
          37.316667
        ]
      },
      "type": "Feature",
      "properties": {
        "hierarchy": [
          "tgn:7223047",
          "tgn:7002739",
          "tgn:7017076",
          "tgn:1000003",
          "tgn:1000074",
          "tgn:7029392"
        ],
        "placetype": [
          "aat:300008347"
        ],
        "id": 7223047,
        "name:xx": "Plátanos"
      }
    },
    {
      "geometry": {
        "type": "Point",
        "coordinates": [
          21.733333,
          37.016667
        ]
      },
      "type": "Feature",
      "properties": {
        "hierarchy": [
          "tgn:7223048",
          "tgn:7011369",
          "tgn:7017076",
          "tgn:1000003",
          "tgn:1000074",
          "tgn:7029392"
        ],
        "placetype": [
          "aat:300008347"
        ],
        "id": 7223048,
        "name:xx": "Plátanos"
      }
    },
    {
      "geometry": {
        "type": "Point",
        "coordinates": [
          22.333333,
          36.783333
        ]
      },
      "type": "Feature",
      "properties": {
        "hierarchy": [
          "tgn:7223049",
          "tgn:7002745",
          "tgn:7017076",
          "tgn:1000003",
          "tgn:1000074",
          "tgn:7029392"
        ],
        "placetype": [
          "aat:300008347"
        ],
        "id": 7223049,
        "name:xx": "Plátanos"
      }
    }
  ]
}
