{
  "geometry": {
    "type": "Point",
    "coordinates": [
      35.23629,
      23.372297
    ]
  },
  "type": "Feature",
  "properties": {
    "hierarchy": [
      "tgn:7535227",
      "tgn:7001242",
      "tgn:7001311",
      "tgn:7016833",
      "tgn:7029392"
    ],
    "placetype": [
      "aat:300379998"
    ],
    "name:en": "Hutit, Wâdi",
    "id": 7535227
  }
}
