{
  "geometry": {
    "type": "Point",
    "coordinates": [
      -121.15,
      39.7667
    ]
  },
  "type": "Feature",
  "properties": {
    "hierarchy": [
      "tgn:2379078",
      "tgn:1000001",
      "tgn:7012149",
      "tgn:7007157",
      "tgn:2000187",
      "tgn:7029392"
    ],
    "placetype": [
      "aat:300132348"
    ],
    "id": 2379078,
    "name:xx": "Hartman Bar"
  }
}
