{
  "geometry": {
    "type": "Point",
    "coordinates": [
      -66.5167,
      -40.5167
    ]
  },
  "type": "Feature",
  "properties": {
    "hierarchy": [
      "tgn:1019789",
      "tgn:7006477",
      "tgn:7006348",
      "tgn:1000002",
      "tgn:7029392"
    ],
    "placetype": [
      "aat:300008347"
    ],
    "id": 1019789,
    "name:xx": "Nahuel Niyeu"
  }
}
