{
  "type": "FeatureCollection",
  "features": [
    {
      "geometry": {
        "type": "Point",
        "coordinates": [
          -75.25,
          40.65
        ]
      },
      "type": "Feature",
      "properties": {
        "hierarchy": [
          "tgn:2089301",
          "tgn:1000001",
          "tgn:7012149",
          "tgn:1002729",
          "tgn:7007710",
          "tgn:7029392"
        ],
        "placetype": [
          "aat:300008347"
        ],
        "id": 2089301,
        "name:xx": "Highland Park"
      }
    },
    {
      "geometry": {
        "type": "Point",
        "coordinates": [
          -77.5667,
          40.6167
        ]
      },
      "type": "Feature",
      "properties": {
        "hierarchy": [
          "tgn:2089302",
          "tgn:1000001",
          "tgn:7012149",
          "tgn:1002669",
          "tgn:7007710",
          "tgn:7029392"
        ],
        "placetype": [
          "aat:300008347"
        ],
        "id": 2089302,
        "name:xx": "Highland Park"
      }
    },
    {
      "geometry": {
        "type": "Point",
        "coordinates": [
          -76.9,
          40.2167
        ]
      },
      "type": "Feature",
      "properties": {
        "hierarchy": [
          "tgn:2089304",
          "tgn:1000001",
          "tgn:1002310",
          "tgn:7012149",
          "tgn:7007710",
          "tgn:7029392"
        ],
        "placetype": [
          "aat:300008347"
        ],
        "id": 2089304,
        "name:xx": "Highland Park"
      }
    },
    {
      "geometry": {
        "type": "Point",
        "coordinates": [
          -76.5667,
          40.0167
        ]
      },
      "type": "Feature",
      "properties": {
        "hierarchy": [
          "tgn:2089306",
          "tgn:1000001",
          "tgn:7012149",
          "tgn:1003047",
          "tgn:7007710",
          "tgn:7029392"
        ],
        "placetype": [
          "aat:300008347"
        ],
        "id": 2089306,
        "name:xx": "Highmount"
      }
    },
    {
      "geometry": {
        "type": "Point",
        "coordinates": [
          -76.4667,
          39.8
        ]
      },
      "type": "Feature",
      "properties": {
        "hierarchy": [
          "tgn:2089307",
          "tgn:1000001",
          "tgn:7012149",
          "tgn:1003047",
          "tgn:7007710",
          "tgn:7029392"
        ],
        "placetype": [
          "aat:300008347",
          "aat:300387210"
        ],
        "id": 2089307,
        "name:xx": "Highrock"
      }
    },
    {
      "geometry": {
        "type": "Point",
        "coordinates": [
          -76.7833,
          40.2
        ]
      },
      "type": "Feature",
      "properties": {
        "hierarchy": [
          "tgn:2089308",
          "tgn:1000001",
          "tgn:1002318",
          "tgn:7012149",
          "tgn:7007710",
          "tgn:7029392"
        ],
        "placetype": [
          "aat:300008347"
        ],
        "id": 2089308,
        "name:xx": "Highspire"
      }
    },
    {
      "geometry": {
        "type": "Point",
        "coordinates": [
          -76.4167,
          39.9333
        ]
      },
      "type": "Feature",
      "properties": {
        "hierarchy": [
          "tgn:2089309",
          "tgn:1000001",
          "tgn:7012149",
          "tgn:7013867",
          "tgn:7007710",
          "tgn:7029392"
        ],
        "placetype": [
          "aat:300008347"
        ],
        "id": 2089309,
        "name:xx": "Highville"
      }
    }
  ]
}
