{
  "geometry": {
    "type": "Point",
    "coordinates": [
      31.312168,
      31.132913
    ]
  },
  "type": "Feature",
  "properties": {
    "hierarchy": [
      "tgn:7524298",
      "tgn:7001242",
      "tgn:1001059",
      "tgn:7016833",
      "tgn:7029392"
    ],
    "placetype": [
      "aat:300008347"
    ],
    "name:en": "Aţ Ţayyibah",
    "id": 7524298
  }
}
