{
  "geometry": {
    "type": "Point",
    "coordinates": [
      -114.75,
      43.4667
    ]
  },
  "type": "Feature",
  "properties": {
    "hierarchy": [
      "tgn:2756810",
      "tgn:1000001",
      "tgn:2000464",
      "tgn:7012149",
      "tgn:7007250",
      "tgn:7029392"
    ],
    "placetype": [
      "aat:300008798"
    ],
    "id": 2756810,
    "name:xx": "Wells Summit"
  }
}
