{
  "type": "FeatureCollection",
  "features": [
    {
      "geometry": {
        "type": "Point",
        "coordinates": [
          -80.0333,
          35.8667
        ]
      },
      "type": "Feature",
      "properties": {
        "hierarchy": [
          "tgn:2740260",
          "tgn:1000001",
          "tgn:7012149",
          "tgn:2001532",
          "tgn:7007709",
          "tgn:7029392"
        ],
        "placetype": [
          "aat:300006191"
        ],
        "id": 2740260,
        "name:xx": "Upper Lake"
      }
    },
    {
      "geometry": {
        "type": "Point",
        "coordinates": [
          -121.8,
          44.7833
        ]
      },
      "type": "Feature",
      "properties": {
        "hierarchy": [
          "tgn:2740261",
          "tgn:1000001",
          "tgn:7012149",
          "tgn:2001712",
          "tgn:7007708",
          "tgn:7029392"
        ],
        "placetype": [
          "aat:300008680"
        ],
        "id": 2740261,
        "name:xx": "Upper Lake"
      }
    },
    {
      "geometry": {
        "type": "Point",
        "coordinates": [
          -117.3167,
          45.1667
        ]
      },
      "type": "Feature",
      "properties": {
        "hierarchy": [
          "tgn:2740262",
          "tgn:1000001",
          "tgn:7012149",
          "tgn:2001722",
          "tgn:7007708",
          "tgn:7029392"
        ],
        "placetype": [
          "aat:300008680"
        ],
        "id": 2740262,
        "name:xx": "Upper Lake"
      }
    },
    {
      "geometry": {
        "type": "Point",
        "coordinates": [
          -75.75,
          41.8167
        ]
      },
      "type": "Feature",
      "properties": {
        "hierarchy": [
          "tgn:2740263",
          "tgn:1000001",
          "tgn:7012149",
          "tgn:1002932",
          "tgn:7007710",
          "tgn:7029392"
        ],
        "placetype": [
          "aat:300008680"
        ],
        "id": 2740263,
        "name:xx": "Upper Lake"
      }
    },
    {
      "geometry": {
        "type": "Point",
        "coordinates": [
          -95.0833,
          31.5
        ]
      },
      "type": "Feature",
      "properties": {
        "hierarchy": [
          "tgn:2740264",
          "tgn:1000001",
          "tgn:7012149",
          "tgn:1002486",
          "tgn:7007826",
          "tgn:7029392"
        ],
        "placetype": [
          "aat:300008680"
        ],
        "id": 2740264,
        "name:xx": "Upper Lake"
      }
    },
    {
      "geometry": {
        "type": "Point",
        "coordinates": [
          -78.1,
          38.3333
        ]
      },
      "type": "Feature",
      "properties": {
        "hierarchy": [
          "tgn:2740265",
          "tgn:1000001",
          "tgn:7012149",
          "tgn:2002172",
          "tgn:7007919",
          "tgn:7029392"
        ],
        "placetype": [
          "aat:300006191"
        ],
        "id": 2740265,
        "name:xx": "Upper Lake"
      }
    },
    {
      "geometry": {
        "type": "Point",
        "coordinates": [
          -88,
          45.55
        ]
      },
      "type": "Feature",
      "properties": {
        "hierarchy": [
          "tgn:2740266",
          "tgn:1000001",
          "tgn:7012149",
          "tgn:2002337",
          "tgn:7007922",
          "tgn:7029392"
        ],
        "placetype": [
          "aat:300008680"
        ],
        "id": 2740266,
        "name:xx": "Upper Lake"
      }
    },
    {
      "geometry": {
        "type": "Point",
        "coordinates": [
          -91.55,
          35.95
        ]
      },
      "type": "Feature",
      "properties": {
        "hierarchy": [
          "tgn:2740267",
          "tgn:1000001",
          "tgn:7016172",
          "tgn:7012149",
          "tgn:2000172",
          "tgn:7029392"
        ],
        "placetype": [
          "aat:300006191"
        ],
        "id": 2740267,
        "name:xx": "Upper Lake - Green Acres Estates"
      }
    },
    {
      "geometry": {
        "type": "Point",
        "coordinates": [
          -77.5667,
          37.45
        ]
      },
      "type": "Feature",
      "properties": {
        "hierarchy": [
          "tgn:2740268",
          "tgn:1000001",
          "tgn:1002267",
          "tgn:7012149",
          "tgn:7007919",
          "tgn:7029392"
        ],
        "placetype": [
          "aat:300006191"
        ],
        "id": 2740268,
        "name:xx": "Upper Lake Bexley"
      }
    },
    {
      "geometry": {
        "type": "Point",
        "coordinates": [
          -121.6,
          47.5667
        ]
      },
      "type": "Feature",
      "properties": {
        "hierarchy": [
          "tgn:2740269",
          "tgn:1000001",
          "tgn:7012149",
          "tgn:7018871",
          "tgn:7007920",
          "tgn:7029392"
        ],
        "placetype": [
          "aat:300008680"
        ],
        "id": 2740269,
        "name:xx": "Upper Lake Blethen"
      }
    }
  ]
}
