{
  "geometry": {
    "type": "Point",
    "coordinates": [
      -80.9167,
      40.0833
    ]
  },
  "type": "Feature",
  "properties": {
    "hierarchy": [
      "tgn:2428574",
      "tgn:1002175",
      "tgn:1000001",
      "tgn:7012149",
      "tgn:7007706",
      "tgn:7029392"
    ],
    "placetype": [
      "aat:300008699"
    ],
    "id": 2428574,
    "name:xx": "Jug Run"
  }
}
