{
  "geometry": {
    "type": "Point",
    "coordinates": [
      -82.9333,
      41.0333
    ]
  },
  "type": "Feature",
  "properties": {
    "hierarchy": [
      "tgn:2127114",
      "tgn:1000001",
      "tgn:7012149",
      "tgn:1002883",
      "tgn:7007706",
      "tgn:7029392"
    ],
    "placetype": [
      "aat:300006075"
    ],
    "id": 2127114,
    "name:xx": "Aichholz Ditch"
  }
}
