{
  "geometry": {
    "type": "Point",
    "coordinates": [
      -112.8667,
      36.5167
    ]
  },
  "type": "Feature",
  "properties": {
    "hierarchy": [
      "tgn:2736701",
      "tgn:1000001",
      "tgn:7006451",
      "tgn:7012149",
      "tgn:2000098",
      "tgn:7029392"
    ],
    "placetype": [
      "aat:300006191"
    ],
    "id": 2736701,
    "name:xx": "Twin Tanks"
  }
}
