{
  "geometry": {
    "type": "Point",
    "coordinates": [
      -81.5333,
      41.05
    ]
  },
  "type": "Feature",
  "properties": {
    "hierarchy": [
      "tgn:2490731",
      "tgn:1000001",
      "tgn:7012149",
      "tgn:1002928",
      "tgn:7007706",
      "tgn:7029392"
    ],
    "placetype": [
      "aat:300008680"
    ],
    "id": 2490731,
    "name:xx": "Mannings Pond"
  }
}
