{
  "geometry": {
    "type": "Point",
    "coordinates": [
      -94.6667,
      75.7333
    ]
  },
  "type": "Feature",
  "properties": {
    "hierarchy": [
      "tgn:1114197",
      "tgn:7005685",
      "tgn:1000001",
      "tgn:1000296",
      "tgn:7029392"
    ],
    "placetype": [
      "aat:300008713"
    ],
    "id": 1114197,
    "name:xx": "Maury Channel"
  }
}
