{
  "geometry": {
    "type": "Point",
    "coordinates": [
      120.6678,
      23.9418
    ]
  },
  "type": "Feature",
  "properties": {
    "hierarchy": [
      "tgn:7494437",
      "tgn:7488858",
      "tgn:1000004",
      "tgn:1000141",
      "tgn:7029392"
    ],
    "placetype": [
      "aat:300007836"
    ],
    "id": 7494437,
    "name:xx": "Yongfeng Qiao"
  }
}
