{
  "type": "FeatureCollection",
  "features": [
    {
      "geometry": {
        "type": "Point",
        "coordinates": [
          -79.85,
          41.4
        ]
      },
      "type": "Feature",
      "properties": {
        "hierarchy": [
          "tgn:2336020",
          "tgn:1000001",
          "tgn:7012149",
          "tgn:1002971",
          "tgn:7007710",
          "tgn:7029392"
        ],
        "placetype": [
          "aat:300008347"
        ],
        "id": 2336020,
        "name:xx": "Foster Corner"
      }
    },
    {
      "geometry": {
        "type": "Point",
        "coordinates": [
          -79.4167,
          33.3167
        ]
      },
      "type": "Feature",
      "properties": {
        "hierarchy": [
          "tgn:2336021",
          "tgn:1000001",
          "tgn:2001746",
          "tgn:7012149",
          "tgn:7007712",
          "tgn:7029392"
        ],
        "placetype": [
          "aat:300008347"
        ],
        "id": 2336021,
        "name:xx": "Foster Corner"
      }
    },
    {
      "geometry": {
        "type": "Point",
        "coordinates": [
          -71.2,
          42.7667
        ]
      },
      "type": "Feature",
      "properties": {
        "hierarchy": [
          "tgn:2336022",
          "tgn:1000001",
          "tgn:7014352",
          "tgn:7012149",
          "tgn:7007564",
          "tgn:7029392"
        ],
        "placetype": [
          "aat:300008347"
        ],
        "id": 2336022,
        "name:xx": "Foster Corners"
      }
    },
    {
      "geometry": {
        "type": "Point",
        "coordinates": [
          -119.2333,
          47.8667
        ]
      },
      "type": "Feature",
      "properties": {
        "hierarchy": [
          "tgn:2336023",
          "tgn:1000001",
          "tgn:2002242",
          "tgn:7012149",
          "tgn:7007920",
          "tgn:7029392"
        ],
        "placetype": [
          "aat:300008761"
        ],
        "id": 2336023,
        "name:xx": "Foster Coulee"
      }
    },
    {
      "geometry": {
        "type": "Point",
        "coordinates": [
          -83.8,
          35.4
        ]
      },
      "type": "Feature",
      "properties": {
        "hierarchy": [
          "tgn:2336024",
          "tgn:1000001",
          "tgn:7012149",
          "tgn:2001497",
          "tgn:7007709",
          "tgn:7029392"
        ],
        "placetype": [
          "aat:300386845"
        ],
        "id": 2336024,
        "name:xx": "Foster Cove"
      }
    },
    {
      "geometry": {
        "type": "Point",
        "coordinates": [
          -71.85,
          41.3
        ]
      },
      "type": "Feature",
      "properties": {
        "hierarchy": [
          "tgn:2336025",
          "tgn:1002996",
          "tgn:1000001",
          "tgn:7012149",
          "tgn:7007711",
          "tgn:7029392"
        ],
        "placetype": [
          "aat:300132316"
        ],
        "id": 2336025,
        "name:xx": "Foster Cove"
      }
    },
    {
      "geometry": {
        "type": "Point",
        "coordinates": [
          -87.3667,
          32.2
        ]
      },
      "type": "Feature",
      "properties": {
        "hierarchy": [
          "tgn:2336026",
          "tgn:7002659",
          "tgn:1000001",
          "tgn:7012149",
          "tgn:2000065",
          "tgn:7029392"
        ],
        "placetype": [
          "aat:300008706"
        ],
        "id": 2336026,
        "name:xx": "Foster Creek"
      }
    },
    {
      "geometry": {
        "type": "Point",
        "coordinates": [
          -85.1833,
          31.4333
        ]
      },
      "type": "Feature",
      "properties": {
        "hierarchy": [
          "tgn:2336027",
          "tgn:1000001",
          "tgn:7012149",
          "tgn:7029392"
        ],
        "placetype": [
          "aat:300008706"
        ],
        "id": 2336027,
        "name:xx": "Foster Creek"
      }
    },
    {
      "geometry": {
        "type": "Point",
        "coordinates": [
          -160.6667,
          55.6
        ]
      },
      "type": "Feature",
      "properties": {
        "hierarchy": [
          "tgn:2336028",
          "tgn:7030515",
          "tgn:7006450",
          "tgn:1000001",
          "tgn:7012149",
          "tgn:7029392"
        ],
        "placetype": [
          "aat:300008706"
        ],
        "id": 2336028,
        "name:xx": "Foster Creek"
      }
    },
    {
      "geometry": {
        "type": "Point",
        "coordinates": [
          -164,
          64.8833
        ]
      },
      "type": "Feature",
      "properties": {
        "hierarchy": [
          "tgn:2336029",
          "tgn:7006450",
          "tgn:1000001",
          "tgn:7012149",
          "tgn:2000079",
          "tgn:7029392"
        ],
        "placetype": [
          "aat:300008706"
        ],
        "id": 2336029,
        "name:xx": "Foster Creek"
      }
    }
  ]
}
