{
  "geometry": {
    "type": "Point",
    "coordinates": [
      -6.573,
      32.862
    ]
  },
  "type": "Feature",
  "properties": {
    "hierarchy": [
      "tgn:1091417",
      "tgn:7593667",
      "tgn:7001242",
      "tgn:1000179",
      "tgn:7029392"
    ],
    "placetype": [
      "aat:300008347",
      "aat:300008375"
    ],
    "id": 1091417,
    "name:xx": "Oued Zem"
  }
}
