{
  "geometry": {
    "type": "Point",
    "coordinates": [
      -108.6833,
      37.65
    ]
  },
  "type": "Feature",
  "properties": {
    "hierarchy": [
      "tgn:2234053",
      "tgn:1000001",
      "tgn:7012149",
      "tgn:2000208",
      "tgn:7007158",
      "tgn:7029392"
    ],
    "placetype": [
      "aat:300006191"
    ],
    "id": 2234053,
    "name:xx": "Cheap Reservoir"
  }
}
