{
  "geometry": {
    "type": "Point",
    "coordinates": [
      -76.6167,
      41.1167
    ]
  },
  "type": "Feature",
  "properties": {
    "hierarchy": [
      "tgn:2765897",
      "tgn:1000001",
      "tgn:7012149",
      "tgn:7007710",
      "tgn:7029392"
    ],
    "placetype": [
      "aat:300008706"
    ],
    "id": 2765897,
    "name:xx": "White Hall Creek"
  }
}
