{
  "geometry": {
    "type": "Point",
    "coordinates": [
      31.085826,
      30.95304
    ]
  },
  "type": "Feature",
  "properties": {
    "hierarchy": [
      "tgn:7521370",
      "tgn:7001242",
      "tgn:7016833",
      "tgn:7001312",
      "tgn:7029392"
    ],
    "placetype": [
      "aat:300008347"
    ],
    "name:en": "Al Abshīţ",
    "id": 7521370
  }
}
