{
  "geometry": {
    "type": "Point",
    "coordinates": [
      -82.1333,
      30.8667
    ]
  },
  "type": "Feature",
  "properties": {
    "hierarchy": [
      "tgn:2372002",
      "tgn:1000001",
      "tgn:2000315",
      "tgn:7012149",
      "tgn:7007248",
      "tgn:7029392"
    ],
    "placetype": [
      "aat:300008680"
    ],
    "id": 2372002,
    "name:xx": "Half Moon Lake"
  }
}
