{
  "geometry": {
    "type": "Point",
    "coordinates": [
      -87.0667,
      34.4833
    ]
  },
  "type": "Feature",
  "properties": {
    "hierarchy": [
      "tgn:2537020",
      "tgn:7002659",
      "tgn:1000001",
      "tgn:7012149",
      "tgn:2000051",
      "tgn:7029392"
    ],
    "placetype": [
      "aat:300008706"
    ],
    "id": 2537020,
    "name:xx": "Neel Creek"
  }
}
