{
  "geometry": {
    "type": "Point",
    "coordinates": [
      8.2167,
      62.9333
    ]
  },
  "type": "Feature",
  "properties": {
    "hierarchy": [
      "tgn:1048795",
      "tgn:7003647",
      "tgn:1000003",
      "tgn:1000088",
      "tgn:7029392"
    ],
    "placetype": [
      "aat:300008347"
    ],
    "id": 1048795,
    "name:xx": "Tingvoll"
  }
}
