{
  "geometry": {
    "type": "Point",
    "coordinates": [
      -86.3833,
      41.25
    ]
  },
  "type": "Feature",
  "properties": {
    "hierarchy": [
      "tgn:2032166",
      "tgn:1000001",
      "tgn:7012149",
      "tgn:1002640",
      "tgn:7007252",
      "tgn:7029392"
    ],
    "placetype": [
      "aat:300008347"
    ],
    "id": 2032166,
    "name:xx": "Hibbard"
  }
}
