{
  "type": "FeatureCollection",
  "features": [
    {
      "geometry": {
        "type": "Point",
        "coordinates": [
          -96.05,
          33.2167
        ]
      },
      "type": "Feature",
      "properties": {
        "hierarchy": [
          "tgn:2105210",
          "tgn:1000001",
          "tgn:7012149",
          "tgn:1002492",
          "tgn:7007826",
          "tgn:7029392"
        ],
        "placetype": [
          "aat:300008347"
        ],
        "id": 2105210,
        "name:xx": "Jacobia"
      }
    },
    {
      "geometry": {
        "type": "Point",
        "coordinates": [
          -100.2,
          34.0667
        ]
      },
      "type": "Feature",
      "properties": {
        "hierarchy": [
          "tgn:2105211",
          "tgn:1000001",
          "tgn:7012149",
          "tgn:1002839",
          "tgn:7007826",
          "tgn:7029392"
        ],
        "placetype": [
          "aat:300008347"
        ],
        "id": 2105211,
        "name:xx": "Jacobs"
      }
    },
    {
      "geometry": {
        "type": "Point",
        "coordinates": [
          -94.1,
          31.85
        ]
      },
      "type": "Feature",
      "properties": {
        "hierarchy": [
          "tgn:2105215",
          "tgn:1000001",
          "tgn:7012149",
          "tgn:2002073",
          "tgn:7007826",
          "tgn:7029392"
        ],
        "placetype": [
          "aat:300008347",
          "aat:300387210"
        ],
        "id": 2105215,
        "name:xx": "James"
      }
    },
    {
      "geometry": {
        "type": "Point",
        "coordinates": [
          -95.5833,
          32.5833
        ]
      },
      "type": "Feature",
      "properties": {
        "hierarchy": [
          "tgn:2105216",
          "tgn:1000001",
          "tgn:7012149",
          "tgn:1002898",
          "tgn:7007826",
          "tgn:7029392"
        ],
        "placetype": [
          "aat:300008347"
        ],
        "id": 2105216,
        "name:xx": "Jamestown"
      }
    },
    {
      "geometry": {
        "type": "Point",
        "coordinates": [
          -93.8167,
          30.9167
        ]
      },
      "type": "Feature",
      "properties": {
        "hierarchy": [
          "tgn:2105217",
          "tgn:1000001",
          "tgn:7012149",
          "tgn:2002047",
          "tgn:7007826",
          "tgn:7029392"
        ],
        "placetype": [
          "aat:300008347"
        ],
        "id": 2105217,
        "name:xx": "Jamestown"
      }
    },
    {
      "geometry": {
        "type": "Point",
        "coordinates": [
          -95.9167,
          33.3167
        ]
      },
      "type": "Feature",
      "properties": {
        "hierarchy": [
          "tgn:2105219",
          "tgn:1000001",
          "tgn:7012149",
          "tgn:1002492",
          "tgn:7007826",
          "tgn:7029392"
        ],
        "placetype": [
          "aat:300008347",
          "aat:300387210"
        ],
        "id": 2105219,
        "name:xx": "Jardin"
      }
    }
  ]
}
