{
  "geometry": {
    "type": "Point",
    "coordinates": [
      -77.2167,
      42.5833
    ]
  },
  "type": "Feature",
  "properties": {
    "hierarchy": [
      "tgn:2428074",
      "tgn:1000001",
      "tgn:7012149",
      "tgn:1003045",
      "tgn:7007568",
      "tgn:7029392"
    ],
    "placetype": [
      "aat:300008905"
    ],
    "id": 2428074,
    "name:xx": "Jubertown Swamp"
  }
}
