{
  "type": "FeatureCollection",
  "features": [
    {
      "geometry": {
        "type": "Point",
        "coordinates": [
          -88.5,
          40.7333
        ]
      },
      "type": "Feature",
      "properties": {
        "hierarchy": [
          "tgn:2027780",
          "tgn:1000001",
          "tgn:7012149",
          "tgn:1002602",
          "tgn:7007251",
          "tgn:7029392"
        ],
        "placetype": [
          "aat:300008347"
        ],
        "id": 2027780,
        "name:xx": "Fairbury"
      }
    },
    {
      "geometry": {
        "type": "Point",
        "coordinates": [
          -88.9167,
          42.1
        ]
      },
      "type": "Feature",
      "properties": {
        "hierarchy": [
          "tgn:2027781",
          "tgn:1000001",
          "tgn:7019012",
          "tgn:7012149",
          "tgn:7007251",
          "tgn:7029392"
        ],
        "placetype": [
          "aat:300008347"
        ],
        "id": 2027781,
        "name:xx": "Fairdale"
      }
    },
    {
      "geometry": {
        "type": "Point",
        "coordinates": [
          -88.35,
          38.3667
        ]
      },
      "type": "Feature",
      "properties": {
        "hierarchy": [
          "tgn:2027782",
          "tgn:1000001",
          "tgn:7012149",
          "tgn:1003003",
          "tgn:7007251",
          "tgn:7029392"
        ],
        "placetype": [
          "aat:300008347"
        ],
        "id": 2027782,
        "name:xx": "Fairfield"
      }
    },
    {
      "geometry": {
        "type": "Point",
        "coordinates": [
          -88.1667,
          39.5667
        ]
      },
      "type": "Feature",
      "properties": {
        "hierarchy": [
          "tgn:2027787",
          "tgn:1000001",
          "tgn:2000500",
          "tgn:7012149",
          "tgn:7007251",
          "tgn:7029392"
        ],
        "placetype": [
          "aat:300008347"
        ],
        "id": 2027787,
        "name:xx": "Fairgrange"
      }
    },
    {
      "geometry": {
        "type": "Point",
        "coordinates": [
          -89.9167,
          41.9333
        ]
      },
      "type": "Feature",
      "properties": {
        "hierarchy": [
          "tgn:2027788",
          "tgn:1000001",
          "tgn:2000498",
          "tgn:7012149",
          "tgn:7007251",
          "tgn:7029392"
        ],
        "placetype": [
          "aat:300008347"
        ],
        "id": 2027788,
        "name:xx": "Fair Haven"
      }
    },
    {
      "geometry": {
        "type": "Point",
        "coordinates": [
          -88.1,
          39.8667
        ]
      },
      "type": "Feature",
      "properties": {
        "hierarchy": [
          "tgn:2027789",
          "tgn:1000001",
          "tgn:2000503",
          "tgn:7012149",
          "tgn:7007251",
          "tgn:7029392"
        ],
        "placetype": [
          "aat:300008347"
        ],
        "id": 2027789,
        "name:xx": "Fairland"
      }
    }
  ]
}
