{
  "geometry": {
    "type": "Point",
    "coordinates": [
      8.7833,
      35.9667
    ]
  },
  "type": "Feature",
  "properties": {
    "hierarchy": [
      "tgn:1094918",
      "tgn:7001242",
      "tgn:1002078",
      "tgn:1000205",
      "tgn:7029392"
    ],
    "placetype": [
      "aat:300008347"
    ],
    "id": 1094918,
    "name:xx": "Dahmani"
  }
}
