{
  "geometry": {
    "type": "Point",
    "coordinates": [
      74.486895,
      27.825854
    ]
  },
  "type": "Feature",
  "properties": {
    "hierarchy": [
      "tgn:7578326",
      "tgn:1000004",
      "tgn:7000198",
      "tgn:7016788",
      "tgn:7029392"
    ],
    "placetype": [
      "aat:300007783"
    ],
    "name:en": "Tālchhāpar",
    "id": 7578326
  }
}
