{
  "geometry": {
    "type": "Point",
    "coordinates": [
      -110.9333,
      46.7167
    ]
  },
  "type": "Feature",
  "properties": {
    "hierarchy": [
      "tgn:2636688",
      "tgn:1000001",
      "tgn:7012149",
      "tgn:2001289",
      "tgn:7007524",
      "tgn:7029392"
    ],
    "placetype": [
      "aat:300008697"
    ],
    "id": 2636688,
    "name:xx": "Sage Spring"
  }
}
