{
  "geometry": {
    "type": "Point",
    "coordinates": [
      -83.0167,
      29.8167
    ]
  },
  "type": "Feature",
  "properties": {
    "hierarchy": [
      "tgn:2183800",
      "tgn:1000001",
      "tgn:2000275",
      "tgn:7012149",
      "tgn:7007240",
      "tgn:7029392"
    ],
    "placetype": [
      "aat:300008905"
    ],
    "id": 2183800,
    "name:xx": "Board Pile Bay"
  }
}
