{
  "geometry": {
    "type": "Point",
    "coordinates": [
      121.7333,
      40.9333
    ]
  },
  "type": "Feature",
  "properties": {
    "hierarchy": [
      "tgn:1123288",
      "tgn:1000004",
      "tgn:1001390",
      "tgn:1000111",
      "tgn:7029392"
    ],
    "placetype": [
      "aat:300008707"
    ],
    "id": 1123288,
    "name:xx": "Daling"
  }
}
