{
  "geometry": {
    "type": "Point",
    "coordinates": [
      -11.7333,
      7.5333
    ]
  },
  "type": "Feature",
  "properties": {
    "hierarchy": [
      "tgn:1092592",
      "tgn:7001242",
      "tgn:1001543",
      "tgn:1000191",
      "tgn:7029392"
    ],
    "placetype": [
      "aat:300008347"
    ],
    "id": 1092592,
    "name:xx": "Pujehun"
  }
}
