{
  "type": "FeatureCollection",
  "features": [
    {
      "geometry": {
        "type": "Point",
        "coordinates": [
          -2.716667,
          52.516667
        ]
      },
      "type": "Feature",
      "properties": {
        "hierarchy": [
          "tgn:7448090",
          "tgn:7002445",
          "tgn:1000003",
          "tgn:7012034",
          "tgn:7008591",
          "tgn:7029392"
        ],
        "placetype": [
          "aat:300008347"
        ],
        "name:en": "Rushbury",
        "id": 7448090
      }
    },
    {
      "geometry": {
        "type": "Point",
        "coordinates": [
          0.766667,
          52.216667
        ]
      },
      "type": "Feature",
      "properties": {
        "hierarchy": [
          "tgn:7448091",
          "tgn:7002445",
          "tgn:1000003",
          "tgn:7008185",
          "tgn:7008591",
          "tgn:7029392"
        ],
        "placetype": [
          "aat:300008347"
        ],
        "name:en": "Rushbrooke",
        "id": 7448091
      }
    },
    {
      "geometry": {
        "type": "Point",
        "coordinates": [
          -6.15,
          56.4
        ]
      },
      "type": "Feature",
      "properties": {
        "hierarchy": [
          "tgn:7448096",
          "tgn:7019094",
          "tgn:7002444",
          "tgn:1000003",
          "tgn:7008591",
          "tgn:7029392"
        ],
        "placetype": [
          "aat:300004792"
        ],
        "name:en": "Tavool House",
        "id": 7448096
      }
    },
    {
      "geometry": {
        "type": "Point",
        "coordinates": [
          -4.641111,
          51.781944
        ]
      },
      "type": "Feature",
      "properties": {
        "hierarchy": [
          "tgn:7448098",
          "tgn:7002443",
          "tgn:5000552",
          "tgn:1000003",
          "tgn:7008591",
          "tgn:7029392"
        ],
        "placetype": [
          "aat:300008347"
        ],
        "name:en": "Tavernspite",
        "id": 7448098
      }
    },
    {
      "geometry": {
        "type": "Point",
        "coordinates": [
          -6.383333,
          58.116667
        ]
      },
      "type": "Feature",
      "properties": {
        "hierarchy": [
          "tgn:7448099",
          "tgn:7002444",
          "tgn:1000003",
          "tgn:7008094",
          "tgn:7008591",
          "tgn:7029392"
        ],
        "placetype": [
          "aat:300008791"
        ],
        "name:en": "Tavay More",
        "id": 7448099
      }
    }
  ]
}
