{
  "geometry": {
    "type": "Point",
    "coordinates": [
      12.35,
      53.75
    ]
  },
  "type": "Feature",
  "properties": {
    "hierarchy": [
      "tgn:7069225",
      "tgn:1000003",
      "tgn:7000094",
      "tgn:7000084",
      "tgn:7029392"
    ],
    "placetype": [
      "aat:300008680"
    ],
    "id": 7069225,
    "name:xx": "Tiefer Ziest"
  }
}
