{
  "type": "FeatureCollection",
  "features": [
    {
      "geometry": {
        "type": "Point",
        "coordinates": [
          -104.75,
          26.15
        ]
      },
      "type": "Feature",
      "properties": {
        "hierarchy": [
          "tgn:7374750",
          "tgn:7005583",
          "tgn:1000001",
          "tgn:7005560",
          "tgn:7029392"
        ],
        "placetype": [
          "aat:300000241"
        ],
        "id": 7374750,
        "name:xx": "Rancho La Boquilla de Patos"
      }
    },
    {
      "geometry": {
        "type": "Point",
        "coordinates": [
          -106.5,
          30.266667
        ]
      },
      "type": "Feature",
      "properties": {
        "hierarchy": [
          "tgn:7374751",
          "tgn:7005581",
          "tgn:1000001",
          "tgn:7005560",
          "tgn:7029392"
        ],
        "placetype": [
          "aat:300008777"
        ],
        "id": 7374751,
        "name:xx": "La Boquilla de Palo Blanco, Cerro"
      }
    },
    {
      "geometry": {
        "type": "Point",
        "coordinates": [
          -105.4,
          27.55
        ]
      },
      "type": "Feature",
      "properties": {
        "hierarchy": [
          "tgn:7374752",
          "tgn:7005581",
          "tgn:1000001",
          "tgn:7005560",
          "tgn:7029392"
        ],
        "placetype": [
          "aat:300008347"
        ],
        "id": 7374752,
        "name:xx": "La Boquilla del Conchos"
      }
    },
    {
      "geometry": {
        "type": "Point",
        "coordinates": [
          -108,
          30.8
        ]
      },
      "type": "Feature",
      "properties": {
        "hierarchy": [
          "tgn:7374753",
          "tgn:7005581",
          "tgn:1000001",
          "tgn:7005560",
          "tgn:7029392"
        ],
        "placetype": [
          "aat:300000241"
        ],
        "id": 7374753,
        "name:xx": "Rancho La Boquilla"
      }
    },
    {
      "geometry": {
        "type": "Point",
        "coordinates": [
          -105.05,
          30.666667
        ]
      },
      "type": "Feature",
      "properties": {
        "hierarchy": [
          "tgn:7374754",
          "tgn:7005581",
          "tgn:1000001",
          "tgn:7005560",
          "tgn:7029392"
        ],
        "placetype": [
          "aat:300000241"
        ],
        "id": 7374754,
        "name:xx": "Rancho La Boquilla"
      }
    },
    {
      "geometry": {
        "type": "Point",
        "coordinates": [
          -106.216667,
          28.483333
        ]
      },
      "type": "Feature",
      "properties": {
        "hierarchy": [
          "tgn:7374755",
          "tgn:7005581",
          "tgn:1000001",
          "tgn:7005560",
          "tgn:7029392"
        ],
        "placetype": [
          "aat:300000241"
        ],
        "id": 7374755,
        "name:xx": "Rancho La Boquilla"
      }
    },
    {
      "geometry": {
        "type": "Point",
        "coordinates": [
          -107.15,
          28.133333
        ]
      },
      "type": "Feature",
      "properties": {
        "hierarchy": [
          "tgn:7374756",
          "tgn:7005581",
          "tgn:1000001",
          "tgn:7005560",
          "tgn:7029392"
        ],
        "placetype": [
          "aat:300000241"
        ],
        "id": 7374756,
        "name:xx": "Rancho La Boquilla"
      }
    },
    {
      "geometry": {
        "type": "Point",
        "coordinates": [
          -102.3,
          27.533333
        ]
      },
      "type": "Feature",
      "properties": {
        "hierarchy": [
          "tgn:7374757",
          "tgn:1001853",
          "tgn:1000001",
          "tgn:7005560",
          "tgn:7029392"
        ],
        "placetype": [
          "aat:300000241"
        ],
        "id": 7374757,
        "name:xx": "Rancho La Boquilla"
      }
    },
    {
      "geometry": {
        "type": "Point",
        "coordinates": [
          -105.611389,
          24.611111
        ]
      },
      "type": "Feature",
      "properties": {
        "hierarchy": [
          "tgn:7374758",
          "tgn:7005583",
          "tgn:1000001",
          "tgn:7005560",
          "tgn:7029392"
        ],
        "placetype": [
          "aat:300000241"
        ],
        "id": 7374758,
        "name:xx": "Rancho La Boquilla"
      }
    },
    {
      "geometry": {
        "type": "Point",
        "coordinates": [
          -99.729722,
          24.465
        ]
      },
      "type": "Feature",
      "properties": {
        "hierarchy": [
          "tgn:7374759",
          "tgn:1000001",
          "tgn:7005589",
          "tgn:7005560",
          "tgn:7029392"
        ],
        "placetype": [
          "aat:300000241"
        ],
        "id": 7374759,
        "name:xx": "Rancho La Boquilla"
      }
    }
  ]
}
