{
  "type": "FeatureCollection",
  "features": [
    {
      "geometry": {
        "type": "Point",
        "coordinates": [
          -90.016667,
          20.983333
        ]
      },
      "type": "Feature",
      "properties": {
        "hierarchy": [
          "tgn:7396690",
          "tgn:1000001",
          "tgn:7005600",
          "tgn:7005560",
          "tgn:7029392"
        ],
        "placetype": [
          "aat:300387007"
        ],
        "id": 7396690,
        "name:xx": "Santa Elena"
      }
    },
    {
      "geometry": {
        "type": "Point",
        "coordinates": [
          -106.483333,
          24.95
        ]
      },
      "type": "Feature",
      "properties": {
        "hierarchy": [
          "tgn:7396691",
          "tgn:7005583",
          "tgn:1000001",
          "tgn:7005560",
          "tgn:7029392"
        ],
        "placetype": [
          "aat:300008347"
        ],
        "id": 7396691,
        "name:xx": "Santa Efigenia"
      }
    },
    {
      "geometry": {
        "type": "Point",
        "coordinates": [
          -101.883333,
          23.716667
        ]
      },
      "type": "Feature",
      "properties": {
        "hierarchy": [
          "tgn:7396692",
          "tgn:1000001",
          "tgn:7005601",
          "tgn:7005560",
          "tgn:7029392"
        ],
        "placetype": [
          "aat:300008347"
        ],
        "id": 7396692,
        "name:xx": "Santa Efigenia"
      }
    },
    {
      "geometry": {
        "type": "Point",
        "coordinates": [
          -99.75,
          23.483333
        ]
      },
      "type": "Feature",
      "properties": {
        "hierarchy": [
          "tgn:7396693",
          "tgn:1000001",
          "tgn:7005597",
          "tgn:7005560",
          "tgn:7029392"
        ],
        "placetype": [
          "aat:300008347"
        ],
        "id": 7396693,
        "name:xx": "Santa Efigenia"
      }
    },
    {
      "geometry": {
        "type": "Point",
        "coordinates": [
          -101.583333,
          23.416667
        ]
      },
      "type": "Feature",
      "properties": {
        "hierarchy": [
          "tgn:7396694",
          "tgn:1000001",
          "tgn:7005594",
          "tgn:7005560",
          "tgn:7029392"
        ],
        "placetype": [
          "aat:300008347"
        ],
        "id": 7396694,
        "name:xx": "Santa Efigenia"
      }
    },
    {
      "geometry": {
        "type": "Point",
        "coordinates": [
          -100.45,
          21.983333
        ]
      },
      "type": "Feature",
      "properties": {
        "hierarchy": [
          "tgn:7396695",
          "tgn:1000001",
          "tgn:7005594",
          "tgn:7005560",
          "tgn:7029392"
        ],
        "placetype": [
          "aat:300008347"
        ],
        "id": 7396695,
        "name:xx": "Santa Efigenia"
      }
    },
    {
      "geometry": {
        "type": "Point",
        "coordinates": [
          -94.2,
          16.45
        ]
      },
      "type": "Feature",
      "properties": {
        "hierarchy": [
          "tgn:7396696",
          "tgn:1000001",
          "tgn:7005591",
          "tgn:7005560",
          "tgn:7029392"
        ],
        "placetype": [
          "aat:300008347"
        ],
        "id": 7396696,
        "name:xx": "Santa Efigenia"
      }
    },
    {
      "geometry": {
        "type": "Point",
        "coordinates": [
          -90.033333,
          20.533333
        ]
      },
      "type": "Feature",
      "properties": {
        "hierarchy": [
          "tgn:7396697",
          "tgn:1000001",
          "tgn:7005600",
          "tgn:7005560",
          "tgn:7029392"
        ],
        "placetype": [
          "aat:300008347"
        ],
        "id": 7396697,
        "name:xx": "Santa Eduwigis"
      }
    },
    {
      "geometry": {
        "type": "Point",
        "coordinates": [
          -115.2,
          31.05
        ]
      },
      "type": "Feature",
      "properties": {
        "hierarchy": [
          "tgn:7396698",
          "tgn:1001835",
          "tgn:1000001",
          "tgn:7005560",
          "tgn:7029392"
        ],
        "placetype": [
          "aat:300000241"
        ],
        "id": 7396698,
        "name:xx": "Rancho Santa Eduwiges"
      }
    },
    {
      "geometry": {
        "type": "Point",
        "coordinates": [
          -109.833333,
          27.5
        ]
      },
      "type": "Feature",
      "properties": {
        "hierarchy": [
          "tgn:7396699",
          "tgn:1000001",
          "tgn:1001960",
          "tgn:7005560",
          "tgn:7029392"
        ],
        "placetype": [
          "aat:300000241"
        ],
        "id": 7396699,
        "name:xx": "Rancho Santa Eduwiges"
      }
    }
  ]
}
