{
  "geometry": {
    "type": "Point",
    "coordinates": [
      -81.4333,
      36.3833
    ]
  },
  "type": "Feature",
  "properties": {
    "hierarchy": [
      "tgn:2458435",
      "tgn:2001467",
      "tgn:1000001",
      "tgn:7012149",
      "tgn:7007709",
      "tgn:7029392"
    ],
    "placetype": [
      "aat:300008706"
    ],
    "id": 2458435,
    "name:xx": "Little Naked Creek"
  }
}
