{
  "geometry": {
    "type": "Point",
    "coordinates": [
      -101.1833,
      43.4667
    ]
  },
  "type": "Feature",
  "properties": {
    "hierarchy": [
      "tgn:2097404",
      "tgn:1000001",
      "tgn:2001817",
      "tgn:7012149",
      "tgn:7007713",
      "tgn:7029392"
    ],
    "placetype": [
      "aat:300008347"
    ],
    "id": 2097404,
    "name:xx": "Norris"
  }
}
