{
  "type": "FeatureCollection",
  "features": [
    {
      "geometry": {
        "type": "Point",
        "coordinates": [
          31.037277,
          30.202651
        ]
      },
      "type": "Feature",
      "properties": {
        "hierarchy": [
          "tgn:7541250",
          "tgn:7001242",
          "tgn:7016833",
          "tgn:7029392"
        ],
        "placetype": [
          "aat:300006075"
        ],
        "id": 7541250,
        "name:xx": "Tur'at Jazīrah Umm Dīnār"
      }
    },
    {
      "geometry": {
        "type": "Point",
        "coordinates": [
          31.04829,
          30.187454
        ]
      },
      "type": "Feature",
      "properties": {
        "hierarchy": [
          "tgn:7541251",
          "tgn:7001242",
          "tgn:7016833",
          "tgn:7029392"
        ],
        "placetype": [
          "aat:300006075"
        ],
        "id": 7541251,
        "name:xx": "Tur'at Umm Dīnār"
      }
    },
    {
      "geometry": {
        "type": "Point",
        "coordinates": [
          31.120127,
          30.185977
        ]
      },
      "type": "Feature",
      "properties": {
        "hierarchy": [
          "tgn:7541252",
          "tgn:7001242",
          "tgn:7016833",
          "tgn:1001087",
          "tgn:7029392"
        ],
        "placetype": [
          "aat:300006075"
        ],
        "id": 7541252,
        "name:xx": "Tur'at an Najāyil"
      }
    },
    {
      "geometry": {
        "type": "Point",
        "coordinates": [
          31.32123,
          30.50253
        ]
      },
      "type": "Feature",
      "properties": {
        "hierarchy": [
          "tgn:7541253",
          "tgn:7001242",
          "tgn:7016833",
          "tgn:1001113",
          "tgn:7029392"
        ],
        "placetype": [
          "aat:300008347"
        ],
        "id": 7541253,
        "name:xx": "Kafr aş Şa'īdī"
      }
    },
    {
      "geometry": {
        "type": "Point",
        "coordinates": [
          31.422646,
          30.503678
        ]
      },
      "type": "Feature",
      "properties": {
        "hierarchy": [
          "tgn:7541254",
          "tgn:7001242",
          "tgn:7016833",
          "tgn:1001113",
          "tgn:7029392"
        ],
        "placetype": [
          "aat:300008347"
        ],
        "id": 7541254,
        "name:xx": "'Izbat Abū Fayyāḑ"
      }
    },
    {
      "geometry": {
        "type": "Point",
        "coordinates": [
          31.270497,
          30.520932
        ]
      },
      "type": "Feature",
      "properties": {
        "hierarchy": [
          "tgn:7541255",
          "tgn:7001242",
          "tgn:7016833",
          "tgn:1001092",
          "tgn:7029392"
        ],
        "placetype": [
          "aat:300008347"
        ],
        "id": 7541255,
        "name:xx": "'Izbat 'Uthmān Aḩmad"
      }
    },
    {
      "geometry": {
        "type": "Point",
        "coordinates": [
          31.326377,
          30.50062
        ]
      },
      "type": "Feature",
      "properties": {
        "hierarchy": [
          "tgn:7541256",
          "tgn:7001242",
          "tgn:7016833",
          "tgn:1001113",
          "tgn:7029392"
        ],
        "placetype": [
          "aat:300008347"
        ],
        "id": 7541256,
        "name:xx": "'Izbat aţ Ţārūţī"
      }
    },
    {
      "geometry": {
        "type": "Point",
        "coordinates": [
          31.46413,
          30.516376
        ]
      },
      "type": "Feature",
      "properties": {
        "hierarchy": [
          "tgn:7541257",
          "tgn:7001242",
          "tgn:7016833",
          "tgn:1001113",
          "tgn:7029392"
        ],
        "placetype": [
          "aat:300008347"
        ],
        "id": 7541257,
        "name:xx": "Kafr al Jundī"
      }
    },
    {
      "geometry": {
        "type": "Point",
        "coordinates": [
          31.273611,
          30
        ]
      },
      "type": "Feature",
      "properties": {
        "hierarchy": [
          "tgn:7541258",
          "tgn:7001242",
          "tgn:7016833",
          "tgn:1001091",
          "tgn:7029392"
        ],
        "placetype": [
          "aat:300000206"
        ],
        "name:en": "'Izbat Zakarīyā Muḩyī ad Dīn",
        "id": 7541258
      }
    },
    {
      "geometry": {
        "type": "Point",
        "coordinates": [
          31.466667,
          30.502778
        ]
      },
      "type": "Feature",
      "properties": {
        "hierarchy": [
          "tgn:7541259",
          "tgn:7001242",
          "tgn:7016833",
          "tgn:1001113",
          "tgn:7029392"
        ],
        "placetype": [
          "aat:300008347"
        ],
        "id": 7541259,
        "name:xx": "'Izbat Taymūr"
      }
    }
  ]
}
