{
  "geometry": {
    "type": "Point",
    "coordinates": [
      -83.7167,
      38.2333
    ]
  },
  "type": "Feature",
  "properties": {
    "hierarchy": [
      "tgn:2554456",
      "tgn:1002169",
      "tgn:1000001",
      "tgn:7012149",
      "tgn:7007255",
      "tgn:7029392"
    ],
    "placetype": [
      "aat:300008347"
    ],
    "id": 2554456,
    "name:xx": "Oakla"
  }
}
