{
  "geometry": {
    "type": "Point",
    "coordinates": [
      14.0167,
      59.6667
    ]
  },
  "type": "Feature",
  "properties": {
    "hierarchy": [
      "tgn:1062865",
      "tgn:1000003",
      "tgn:7010031",
      "tgn:1000097",
      "tgn:7029392"
    ],
    "placetype": [
      "aat:300008347"
    ],
    "id": 1062865,
    "name:xx": "Brattfors"
  }
}
