{
  "geometry": {
    "type": "Point",
    "coordinates": [
      -76.3667,
      37.2667
    ]
  },
  "type": "Feature",
  "properties": {
    "hierarchy": [
      "tgn:2169039",
      "tgn:1000001",
      "tgn:7012149",
      "tgn:1002411",
      "tgn:7007919",
      "tgn:7029392"
    ],
    "placetype": [
      "aat:300008791"
    ],
    "id": 2169039,
    "name:xx": "Big Island"
  }
}
