{
  "geometry": {
    "type": "Point",
    "coordinates": [
      -117.9333,
      43.9667
    ]
  },
  "type": "Feature",
  "properties": {
    "hierarchy": [
      "tgn:2740012",
      "tgn:1000001",
      "tgn:7012149",
      "tgn:2001718",
      "tgn:7007708",
      "tgn:7029392"
    ],
    "placetype": [
      "aat:300006191"
    ],
    "id": 2740012,
    "name:xx": "Upper Gregory Creek Reservoir"
  }
}
