{
  "type": "FeatureCollection",
  "features": [
    {
      "geometry": {
        "type": "Point",
        "coordinates": [
          -82.7833,
          43.7
        ]
      },
      "type": "Feature",
      "properties": {
        "hierarchy": [
          "tgn:2315920",
          "tgn:1000001",
          "tgn:7012149",
          "tgn:2000964",
          "tgn:7007520",
          "tgn:7029392"
        ],
        "placetype": [
          "aat:300008706"
        ],
        "id": 2315920,
        "name:xx": "Elm Creek"
      }
    },
    {
      "geometry": {
        "type": "Point",
        "coordinates": [
          -84.9333,
          43.8667
        ]
      },
      "type": "Feature",
      "properties": {
        "hierarchy": [
          "tgn:2315921",
          "tgn:1000001",
          "tgn:2000953",
          "tgn:7012149",
          "tgn:7007520",
          "tgn:7029392"
        ],
        "placetype": [
          "aat:300008706"
        ],
        "id": 2315921,
        "name:xx": "Elm Creek"
      }
    },
    {
      "geometry": {
        "type": "Point",
        "coordinates": [
          -83.75,
          44.2667
        ]
      },
      "type": "Feature",
      "properties": {
        "hierarchy": [
          "tgn:2315922",
          "tgn:1000001",
          "tgn:7012149",
          "tgn:2000965",
          "tgn:7007520",
          "tgn:7029392"
        ],
        "placetype": [
          "aat:300008706"
        ],
        "id": 2315922,
        "name:xx": "Elm Creek"
      }
    },
    {
      "geometry": {
        "type": "Point",
        "coordinates": [
          -87.0667,
          46.0833
        ]
      },
      "type": "Feature",
      "properties": {
        "hierarchy": [
          "tgn:2315923",
          "tgn:1000001",
          "tgn:2000955",
          "tgn:7012149",
          "tgn:7007520",
          "tgn:7029392"
        ],
        "placetype": [
          "aat:300008706"
        ],
        "id": 2315923,
        "name:xx": "Elm Creek"
      }
    },
    {
      "geometry": {
        "type": "Point",
        "coordinates": [
          -87.9,
          46.8167
        ]
      },
      "type": "Feature",
      "properties": {
        "hierarchy": [
          "tgn:2315924",
          "tgn:1000001",
          "tgn:7012149",
          "tgn:2000975",
          "tgn:7007520",
          "tgn:7029392"
        ],
        "placetype": [
          "aat:300008706"
        ],
        "id": 2315924,
        "name:xx": "Elm Creek"
      }
    },
    {
      "geometry": {
        "type": "Point",
        "coordinates": [
          -94.4333,
          44.0667
        ]
      },
      "type": "Feature",
      "properties": {
        "hierarchy": [
          "tgn:2315925",
          "tgn:1000001",
          "tgn:7012149",
          "tgn:2001081",
          "tgn:7007521",
          "tgn:7029392"
        ],
        "placetype": [
          "aat:300008706"
        ],
        "id": 2315925,
        "name:xx": "Elm Creek"
      }
    },
    {
      "geometry": {
        "type": "Point",
        "coordinates": [
          -92.9167,
          48.0167
        ]
      },
      "type": "Feature",
      "properties": {
        "hierarchy": [
          "tgn:2315926",
          "tgn:1000001",
          "tgn:7012149",
          "tgn:2001067",
          "tgn:7007521",
          "tgn:7029392"
        ],
        "placetype": [
          "aat:300008706"
        ],
        "id": 2315926,
        "name:xx": "Elm Creek"
      }
    },
    {
      "geometry": {
        "type": "Point",
        "coordinates": [
          -93.55,
          45.0167
        ]
      },
      "type": "Feature",
      "properties": {
        "hierarchy": [
          "tgn:2315927",
          "tgn:1000001",
          "tgn:2001025",
          "tgn:7012149",
          "tgn:7007521",
          "tgn:7029392"
        ],
        "placetype": [
          "aat:300008706"
        ],
        "id": 2315927,
        "name:xx": "Elm Creek"
      }
    },
    {
      "geometry": {
        "type": "Point",
        "coordinates": [
          -94.3,
          47.9333
        ]
      },
      "type": "Feature",
      "properties": {
        "hierarchy": [
          "tgn:2315928",
          "tgn:1000001",
          "tgn:7012149",
          "tgn:2001034",
          "tgn:7007521",
          "tgn:7029392"
        ],
        "placetype": [
          "aat:300008706"
        ],
        "id": 2315928,
        "name:xx": "Elm Creek"
      }
    },
    {
      "geometry": {
        "type": "Point",
        "coordinates": [
          -91.8833,
          37.6667
        ]
      },
      "type": "Feature",
      "properties": {
        "hierarchy": [
          "tgn:2315929",
          "tgn:1000001",
          "tgn:7012149",
          "tgn:2001230",
          "tgn:7007523",
          "tgn:7029392"
        ],
        "placetype": [
          "aat:300008706"
        ],
        "id": 2315929,
        "name:xx": "Elm Creek"
      }
    }
  ]
}
