{
  "geometry": {
    "type": "Point",
    "coordinates": [
      79.65,
      13.116667
    ]
  },
  "type": "Feature",
  "properties": {
    "hierarchy": [
      "tgn:7573128",
      "tgn:1000004",
      "tgn:7000198",
      "tgn:7001797",
      "tgn:7029392"
    ],
    "placetype": [
      "aat:300008347"
    ],
    "name:en": "Ichchiputtūr",
    "id": 7573128
  }
}
