{
  "geometry": {
    "type": "Point",
    "coordinates": [
      86.65,
      23.4167
    ]
  },
  "type": "Feature",
  "properties": {
    "hierarchy": [
      "tgn:1075162",
      "tgn:1000004",
      "tgn:7000198",
      "tgn:1001977",
      "tgn:7029392"
    ],
    "placetype": [
      "aat:300008347"
    ],
    "id": 1075162,
    "name:xx": "Dhanera"
  }
}
