{
  "geometry": {
    "type": "Point",
    "coordinates": [
      -59.5833,
      -51.3167
    ]
  },
  "type": "Feature",
  "properties": {
    "hierarchy": [
      "tgn:1008559",
      "tgn:7005151",
      "tgn:7005152",
      "tgn:1000002",
      "tgn:7029392"
    ],
    "placetype": [
      "aat:300008791"
    ],
    "id": 1008559,
    "name:xx": "Pebble Island"
  }
}
