{
  "geometry": {
    "type": "Point",
    "coordinates": [
      -116.7833,
      39.6833
    ]
  },
  "type": "Feature",
  "properties": {
    "hierarchy": [
      "tgn:2360283",
      "tgn:1000001",
      "tgn:2001415",
      "tgn:7012149",
      "tgn:7007526",
      "tgn:7029392"
    ],
    "placetype": [
      "aat:300008347"
    ],
    "id": 2360283,
    "name:xx": "Grass Valley"
  }
}
