{
  "geometry": {
    "type": "Point",
    "coordinates": [
      -49.85,
      -1.9667
    ]
  },
  "type": "Feature",
  "properties": {
    "hierarchy": [
      "tgn:1022254",
      "tgn:7006247",
      "tgn:1000047",
      "tgn:7002456",
      "tgn:1000002",
      "tgn:7029392"
    ],
    "placetype": [
      "aat:300008347"
    ],
    "id": 1022254,
    "name:xx": "Oeiras do Pará"
  }
}
