{
  "geometry": {
    "type": "Point",
    "coordinates": [
      25.033,
      58.648
    ]
  },
  "type": "Feature",
  "properties": {
    "hierarchy": [
      "tgn:1060889",
      "tgn:7006638",
      "tgn:1000003",
      "tgn:7006540",
      "tgn:7029392"
    ],
    "placetype": [
      "aat:300008347"
    ],
    "name:en": "Vändra",
    "id": 1060889
  }
}
