{
  "geometry": {
    "type": "Point",
    "coordinates": [
      -80.5667,
      37.9333
    ]
  },
  "type": "Feature",
  "properties": {
    "hierarchy": [
      "tgn:2405440",
      "tgn:1000001",
      "tgn:7012149",
      "tgn:2002264",
      "tgn:7013961",
      "tgn:7029392"
    ],
    "placetype": [
      "aat:300008706"
    ],
    "id": 2405440,
    "name:xx": "Hughart Creek"
  }
}
