{
  "type": "FeatureCollection",
  "features": [
    {
      "geometry": {
        "type": "Point",
        "coordinates": [
          168.7,
          -44.05
        ]
      },
      "type": "Feature",
      "properties": {
        "hierarchy": [
          "tgn:7511470",
          "tgn:1009227",
          "tgn:1000226",
          "tgn:7018437",
          "tgn:1000006",
          "tgn:7029392"
        ],
        "placetype": [
          "aat:300008680"
        ],
        "name:en": "Mary, Lake",
        "id": 7511470
      }
    },
    {
      "geometry": {
        "type": "Point",
        "coordinates": [
          172.333333,
          -42.383333
        ]
      },
      "type": "Feature",
      "properties": {
        "hierarchy": [
          "tgn:7511471",
          "tgn:1009227",
          "tgn:7001866",
          "tgn:1000226",
          "tgn:1000006",
          "tgn:7029392"
        ],
        "placetype": [
          "aat:300008347"
        ],
        "name:en": "Maruia Springs",
        "id": 7511471
      }
    },
    {
      "geometry": {
        "type": "Point",
        "coordinates": [
          174.366667,
          -35.566667
        ]
      },
      "type": "Feature",
      "properties": {
        "hierarchy": [
          "tgn:7511474",
          "tgn:1008380",
          "tgn:7000507",
          "tgn:1000226",
          "tgn:1000006",
          "tgn:7029392"
        ],
        "placetype": [
          "aat:300008347"
        ],
        "name:en": "Marua",
        "id": 7511474
      }
    },
    {
      "geometry": {
        "type": "Point",
        "coordinates": [
          168.516667,
          -44.1
        ]
      },
      "type": "Feature",
      "properties": {
        "hierarchy": [
          "tgn:7511475",
          "tgn:1009227",
          "tgn:1000226",
          "tgn:7018437",
          "tgn:1000006",
          "tgn:7029392"
        ],
        "placetype": [
          "aat:300008699"
        ],
        "name:en": "Martyr River",
        "id": 7511475
      }
    },
    {
      "geometry": {
        "type": "Point",
        "coordinates": [
          168.533333,
          -44.183333
        ]
      },
      "type": "Feature",
      "properties": {
        "hierarchy": [
          "tgn:7511476",
          "tgn:1009227",
          "tgn:1000226",
          "tgn:7018437",
          "tgn:1000006",
          "tgn:7029392"
        ],
        "placetype": [
          "aat:300008777"
        ],
        "name:en": "Martyr Hill",
        "id": 7511476
      }
    },
    {
      "geometry": {
        "type": "Point",
        "coordinates": [
          167.966667,
          -44.366667
        ]
      },
      "type": "Feature",
      "properties": {
        "hierarchy": [
          "tgn:7511479",
          "tgn:1009227",
          "tgn:1000226",
          "tgn:7016822",
          "tgn:1000006",
          "tgn:7029392"
        ],
        "placetype": [
          "aat:300132316"
        ],
        "name:en": "Martins Bay",
        "id": 7511479
      }
    }
  ]
}
