{
  "geometry": {
    "type": "Point",
    "coordinates": [
      -90.8167,
      38.9333
    ]
  },
  "type": "Feature",
  "properties": {
    "hierarchy": [
      "tgn:2058698",
      "tgn:1000001",
      "tgn:7012149",
      "tgn:1002598",
      "tgn:7007523",
      "tgn:7029392"
    ],
    "placetype": [
      "aat:300008347"
    ],
    "id": 2058698,
    "name:xx": "Ethlyn"
  }
}
