{
  "geometry": {
    "type": "Point",
    "coordinates": [
      -91.65,
      47.7667
    ]
  },
  "type": "Feature",
  "properties": {
    "hierarchy": [
      "tgn:2383342",
      "tgn:1000001",
      "tgn:7012149",
      "tgn:2001036",
      "tgn:7007521",
      "tgn:7029392"
    ],
    "placetype": [
      "aat:300008680"
    ],
    "id": 2383342,
    "name:xx": "Heart Lake"
  }
}
