{
  "geometry": {
    "type": "Point",
    "coordinates": [
      106.15,
      30.35
    ]
  },
  "type": "Feature",
  "properties": {
    "hierarchy": [
      "tgn:1073055",
      "tgn:1000004",
      "tgn:7024355",
      "tgn:1000111",
      "tgn:7029392"
    ],
    "placetype": [
      "aat:300008347"
    ],
    "id": 1073055,
    "name:xx": "Xinglong"
  }
}
