{
  "type": "FeatureCollection",
  "features": [
    {
      "geometry": {
        "type": "Point",
        "coordinates": [
          -0.083333,
          51.433333
        ]
      },
      "type": "Feature",
      "properties": {
        "hierarchy": [
          "tgn:7448800",
          "tgn:7002445",
          "tgn:7018929",
          "tgn:7011781",
          "tgn:1000003",
          "tgn:7008136",
          "tgn:7008591",
          "tgn:7029392"
        ],
        "placetype": [
          "aat:300007783"
        ],
        "name:en": "Sydenham Hill Station",
        "id": 7448800
      }
    },
    {
      "geometry": {
        "type": "Point",
        "coordinates": [
          -5.883333,
          54.6
        ]
      },
      "type": "Feature",
      "properties": {
        "hierarchy": [
          "tgn:7448802",
          "tgn:7002448",
          "tgn:7019168",
          "tgn:1000003",
          "tgn:7008591",
          "tgn:7029392"
        ],
        "placetype": [
          "aat:300008347"
        ],
        "name:en": "Sydenham",
        "id": 7448802
      }
    },
    {
      "geometry": {
        "type": "Point",
        "coordinates": [
          -3.383333,
          52.883333
        ]
      },
      "type": "Feature",
      "properties": {
        "hierarchy": [
          "tgn:7448804",
          "tgn:7002443",
          "tgn:5000555",
          "tgn:1000003",
          "tgn:7008591",
          "tgn:7029392"
        ],
        "placetype": [
          "aat:300008795"
        ],
        "name:en": "Sych, Moel",
        "id": 7448804
      }
    },
    {
      "geometry": {
        "type": "Point",
        "coordinates": [
          -2.216667,
          52.916667
        ]
      },
      "type": "Feature",
      "properties": {
        "hierarchy": [
          "tgn:7448806",
          "tgn:7002445",
          "tgn:1000003",
          "tgn:7008174",
          "tgn:7008591",
          "tgn:7029392"
        ],
        "placetype": [
          "aat:300008347"
        ],
        "name:en": "Swynnerton",
        "id": 7448806
      }
    },
    {
      "geometry": {
        "type": "Point",
        "coordinates": [
          -1,
          51.6
        ]
      },
      "type": "Feature",
      "properties": {
        "hierarchy": [
          "tgn:7448807",
          "tgn:7002445",
          "tgn:1000003",
          "tgn:7008168",
          "tgn:7008591",
          "tgn:7029392"
        ],
        "placetype": [
          "aat:300387502"
        ],
        "name:en": "Swyncombe House",
        "id": 7448807
      }
    },
    {
      "geometry": {
        "type": "Point",
        "coordinates": [
          -6.266667,
          58.183333
        ]
      },
      "type": "Feature",
      "properties": {
        "hierarchy": [
          "tgn:7448808",
          "tgn:7002444",
          "tgn:1000003",
          "tgn:7008094",
          "tgn:7008591",
          "tgn:7029392"
        ],
        "placetype": [
          "aat:300008347"
        ],
        "name:en": "Swordale",
        "id": 7448808
      }
    }
  ]
}
