{
  "geometry": {
    "type": "Point",
    "coordinates": [
      -122.1167,
      38.65
    ]
  },
  "type": "Feature",
  "properties": {
    "hierarchy": [
      "tgn:2504712",
      "tgn:1000001",
      "tgn:7012149",
      "tgn:7007157",
      "tgn:1003046",
      "tgn:7029392"
    ],
    "placetype": [
      "aat:300008697"
    ],
    "id": 2504712,
    "name:xx": "Medical Spring"
  }
}
