{
  "geometry": {
    "type": "Point",
    "coordinates": [
      -111.4167,
      33.8667
    ]
  },
  "type": "Feature",
  "properties": {
    "hierarchy": [
      "tgn:2454415",
      "tgn:1000001",
      "tgn:7006451",
      "tgn:7012149",
      "tgn:2000097",
      "tgn:7029392"
    ],
    "placetype": [
      "aat:300000390"
    ],
    "id": 2454415,
    "name:xx": "Little Daisy Mine"
  }
}
