{
  "geometry": {
    "type": "Point",
    "coordinates": [
      16.9667,
      48.1833
    ]
  },
  "type": "Feature",
  "properties": {
    "hierarchy": [
      "tgn:1135371",
      "tgn:7003025",
      "tgn:1000003",
      "tgn:1000062",
      "tgn:7029392"
    ],
    "placetype": [
      "aat:300008703"
    ],
    "id": 1135371,
    "name:xx": "Russbach"
  }
}
