{
  "geometry": {
    "type": "Point",
    "coordinates": [
      -78.3333,
      35.7333
    ]
  },
  "type": "Feature",
  "properties": {
    "hierarchy": [
      "tgn:2226699",
      "tgn:1000001",
      "tgn:7012149",
      "tgn:2001509",
      "tgn:7007709",
      "tgn:7029392"
    ],
    "placetype": [
      "aat:300008706"
    ],
    "id": 2226699,
    "name:xx": "Cattail Creek"
  }
}
