{
  "type": "FeatureCollection",
  "features": [
    {
      "geometry": {
        "type": "Point",
        "coordinates": [
          119.9167,
          30.2667
        ]
      },
      "type": "Feature",
      "properties": {
        "hierarchy": [
          "tgn:1069440",
          "tgn:1000004",
          "tgn:7002076",
          "tgn:1000111",
          "tgn:7029392"
        ],
        "placetype": [
          "aat:300008347"
        ],
        "id": 1069440,
        "name:xx": "Jiuyuhang"
      }
    },
    {
      "geometry": {
        "type": "Point",
        "coordinates": [
          88.0833,
          44.2
        ]
      },
      "type": "Feature",
      "properties": {
        "hierarchy": [
          "tgn:1069441",
          "tgn:1000004",
          "tgn:7001745",
          "tgn:1000111",
          "tgn:7029392"
        ],
        "placetype": [
          "aat:300008347"
        ],
        "id": 1069441,
        "name:xx": "Jiuyunjie"
      }
    },
    {
      "geometry": {
        "type": "Point",
        "coordinates": [
          116.55,
          39.5
        ]
      },
      "type": "Feature",
      "properties": {
        "hierarchy": [
          "tgn:1069444",
          "tgn:1000004",
          "tgn:7002077",
          "tgn:1000111",
          "tgn:7029392"
        ],
        "placetype": [
          "aat:300008347"
        ],
        "id": 1069444,
        "name:xx": "Jiuzhou"
      }
    },
    {
      "geometry": {
        "type": "Point",
        "coordinates": [
          115.6167,
          40.2
        ]
      },
      "type": "Feature",
      "properties": {
        "hierarchy": [
          "tgn:1069445",
          "tgn:1000004",
          "tgn:7002077",
          "tgn:1000111",
          "tgn:7029392"
        ],
        "placetype": [
          "aat:300008347"
        ],
        "id": 1069445,
        "name:xx": "Jiuzhuangwo"
      }
    },
    {
      "geometry": {
        "type": "Point",
        "coordinates": [
          121.2667,
          31.2333
        ]
      },
      "type": "Feature",
      "properties": {
        "hierarchy": [
          "tgn:1069446",
          "tgn:1000004",
          "tgn:1000958",
          "tgn:1000111",
          "tgn:7029392"
        ],
        "placetype": [
          "aat:300008347"
        ],
        "id": 1069446,
        "name:xx": "Jiwangmiao"
      }
    },
    {
      "geometry": {
        "type": "Point",
        "coordinates": [
          122.9667,
          41.0333
        ]
      },
      "type": "Feature",
      "properties": {
        "hierarchy": [
          "tgn:1069447",
          "tgn:1000004",
          "tgn:1001390",
          "tgn:1000111",
          "tgn:7029392"
        ],
        "placetype": [
          "aat:300008347"
        ],
        "id": 1069447,
        "name:xx": "Jiwangtun"
      }
    },
    {
      "geometry": {
        "type": "Point",
        "coordinates": [
          123.1333,
          50.7
        ]
      },
      "type": "Feature",
      "properties": {
        "hierarchy": [
          "tgn:1069448",
          "tgn:1000004",
          "tgn:7001838",
          "tgn:1000111",
          "tgn:7029392"
        ],
        "placetype": [
          "aat:300008347"
        ],
        "id": 1069448,
        "name:xx": "Jiwen"
      }
    },
    {
      "geometry": {
        "type": "Point",
        "coordinates": [
          118.5667,
          30.0833
        ]
      },
      "type": "Feature",
      "properties": {
        "hierarchy": [
          "tgn:1069449",
          "tgn:7002075",
          "tgn:1000004",
          "tgn:1000111",
          "tgn:7029392"
        ],
        "placetype": [
          "aat:300008347"
        ],
        "id": 1069449,
        "name:xx": "Jixi"
      }
    }
  ]
}
