{
  "type": "FeatureCollection",
  "features": [
    {
      "geometry": {
        "type": "Point",
        "coordinates": [
          -86.7,
          37.8667
        ]
      },
      "type": "Feature",
      "properties": {
        "hierarchy": [
          "tgn:2411640",
          "tgn:1000001",
          "tgn:7012149",
          "tgn:2000795",
          "tgn:7007255",
          "tgn:7029392"
        ],
        "placetype": [
          "aat:300006191"
        ],
        "id": 2411640,
        "name:xx": "Indian Lake"
      }
    },
    {
      "geometry": {
        "type": "Point",
        "coordinates": [
          -91.9167,
          30.8167
        ]
      },
      "type": "Feature",
      "properties": {
        "hierarchy": [
          "tgn:2411641",
          "tgn:1000001",
          "tgn:7012149",
          "tgn:2000902",
          "tgn:7007256",
          "tgn:7029392"
        ],
        "placetype": [
          "aat:300008680"
        ],
        "id": 2411641,
        "name:xx": "Indian Lake"
      }
    },
    {
      "geometry": {
        "type": "Point",
        "coordinates": [
          -91.45,
          32.2667
        ]
      },
      "type": "Feature",
      "properties": {
        "hierarchy": [
          "tgn:2411642",
          "tgn:1000001",
          "tgn:7012149",
          "tgn:2000886",
          "tgn:7007256",
          "tgn:7029392"
        ],
        "placetype": [
          "aat:300008680"
        ],
        "id": 2411642,
        "name:xx": "Indian Lake"
      }
    },
    {
      "geometry": {
        "type": "Point",
        "coordinates": [
          -92.2333,
          30.7833
        ]
      },
      "type": "Feature",
      "properties": {
        "hierarchy": [
          "tgn:2411643",
          "tgn:1000001",
          "tgn:2000873",
          "tgn:7012149",
          "tgn:7007256",
          "tgn:7029392"
        ],
        "placetype": [
          "aat:300006191"
        ],
        "id": 2411643,
        "name:xx": "Indian Lake"
      }
    },
    {
      "geometry": {
        "type": "Point",
        "coordinates": [
          -67.6,
          44.9667
        ]
      },
      "type": "Feature",
      "properties": {
        "hierarchy": [
          "tgn:2411644",
          "tgn:1000001",
          "tgn:7012149",
          "tgn:7014589",
          "tgn:7007515",
          "tgn:7029392"
        ],
        "placetype": [
          "aat:300008680"
        ],
        "id": 2411644,
        "name:xx": "Indian Lake"
      }
    },
    {
      "geometry": {
        "type": "Point",
        "coordinates": [
          -71.8,
          42.3
        ]
      },
      "type": "Feature",
      "properties": {
        "hierarchy": [
          "tgn:2411645",
          "tgn:1000001",
          "tgn:7012149",
          "tgn:1003038",
          "tgn:7007517",
          "tgn:7029392"
        ],
        "placetype": [
          "aat:300006191"
        ],
        "id": 2411645,
        "name:xx": "Indian Lake"
      }
    },
    {
      "geometry": {
        "type": "Point",
        "coordinates": [
          -86.4333,
          41.8333
        ]
      },
      "type": "Feature",
      "properties": {
        "hierarchy": [
          "tgn:2411646",
          "tgn:1000001",
          "tgn:1002182",
          "tgn:7012149",
          "tgn:7007520",
          "tgn:7029392"
        ],
        "placetype": [
          "aat:300008680"
        ],
        "id": 2411646,
        "name:xx": "Indian Lake"
      }
    },
    {
      "geometry": {
        "type": "Point",
        "coordinates": [
          -85.4667,
          42.4333
        ]
      },
      "type": "Feature",
      "properties": {
        "hierarchy": [
          "tgn:2411647",
          "tgn:1002166",
          "tgn:1000001",
          "tgn:7012149",
          "tgn:7007520",
          "tgn:7029392"
        ],
        "placetype": [
          "aat:300008680"
        ],
        "id": 2411647,
        "name:xx": "Indian Lake"
      }
    },
    {
      "geometry": {
        "type": "Point",
        "coordinates": [
          -83.8833,
          42.7333
        ]
      },
      "type": "Feature",
      "properties": {
        "hierarchy": [
          "tgn:2411648",
          "tgn:1000001",
          "tgn:7012149",
          "tgn:1002603",
          "tgn:7007520",
          "tgn:7029392"
        ],
        "placetype": [
          "aat:300008680"
        ],
        "id": 2411648,
        "name:xx": "Indian Lake"
      }
    },
    {
      "geometry": {
        "type": "Point",
        "coordinates": [
          -83.2,
          42.7833
        ]
      },
      "type": "Feature",
      "properties": {
        "hierarchy": [
          "tgn:2411649",
          "tgn:1000001",
          "tgn:7012149",
          "tgn:1002737",
          "tgn:7007520",
          "tgn:7029392"
        ],
        "placetype": [
          "aat:300008680"
        ],
        "id": 2411649,
        "name:xx": "Indian Lake"
      }
    }
  ]
}
