{
  "geometry": {
    "type": "Point",
    "coordinates": [
      10.3333,
      23.3333
    ]
  },
  "type": "Feature",
  "properties": {
    "hierarchy": [
      "tgn:1111310",
      "tgn:7001242",
      "tgn:7029392"
    ],
    "placetype": [
      "aat:300387091"
    ],
    "id": 1111310,
    "name:xx": "Tourndo, Oued"
  }
}
