{
  "geometry": {
    "type": "Point",
    "coordinates": [
      -91.4167,
      39.7667
    ]
  },
  "type": "Feature",
  "properties": {
    "hierarchy": [
      "tgn:2059060",
      "tgn:1000001",
      "tgn:7012149",
      "tgn:1002634",
      "tgn:7007523",
      "tgn:7029392"
    ],
    "placetype": [
      "aat:300387016"
    ],
    "id": 2059060,
    "name:xx": "Helton"
  }
}
