{
  "geometry": {
    "type": "Point",
    "coordinates": [
      23.0667,
      -0.6667
    ]
  },
  "type": "Feature",
  "properties": {
    "hierarchy": [
      "tgn:1089592",
      "tgn:7001242",
      "tgn:7016654",
      "tgn:1000159",
      "tgn:7029392"
    ],
    "placetype": [
      "aat:300008347"
    ],
    "id": 1089592,
    "name:xx": "Yokolo"
  }
}
