{
  "type": "FeatureCollection",
  "features": [
    {
      "geometry": {
        "type": "Point",
        "coordinates": [
          -124.2333,
          43.2
        ]
      },
      "type": "Feature",
      "properties": {
        "hierarchy": [
          "tgn:2084540",
          "tgn:1000001",
          "tgn:2001702",
          "tgn:7012149",
          "tgn:7007708",
          "tgn:7029392"
        ],
        "placetype": [
          "aat:300387016"
        ],
        "id": 2084540,
        "name:xx": "Chrome"
      }
    },
    {
      "geometry": {
        "type": "Point",
        "coordinates": [
          -122.8,
          45.3667
        ]
      },
      "type": "Feature",
      "properties": {
        "hierarchy": [
          "tgn:2084541",
          "tgn:1000001",
          "tgn:7012149",
          "tgn:1002994",
          "tgn:7007708",
          "tgn:7029392"
        ],
        "placetype": [
          "aat:300387016"
        ],
        "id": 2084541,
        "name:xx": "Cipole"
      }
    },
    {
      "geometry": {
        "type": "Point",
        "coordinates": [
          -118.4333,
          43.35
        ]
      },
      "type": "Feature",
      "properties": {
        "hierarchy": [
          "tgn:2084542",
          "tgn:1000001",
          "tgn:7012149",
          "tgn:2001709",
          "tgn:7007708",
          "tgn:7029392"
        ],
        "placetype": [
          "aat:300387016"
        ],
        "id": 2084542,
        "name:xx": "Circle Bar"
      }
    },
    {
      "geometry": {
        "type": "Point",
        "coordinates": [
          -120.2333,
          45.2833
        ]
      },
      "type": "Feature",
      "properties": {
        "hierarchy": [
          "tgn:2084543",
          "tgn:1000001",
          "tgn:7012149",
          "tgn:2001707",
          "tgn:7007708",
          "tgn:7029392"
        ],
        "placetype": [
          "aat:300008347",
          "aat:300387210"
        ],
        "id": 2084543,
        "name:xx": "City Farm"
      }
    },
    {
      "geometry": {
        "type": "Point",
        "coordinates": [
          -122.5667,
          45.4
        ]
      },
      "type": "Feature",
      "properties": {
        "hierarchy": [
          "tgn:2084544",
          "tgn:1000001",
          "tgn:1002270",
          "tgn:7012149",
          "tgn:7007708",
          "tgn:7029392"
        ],
        "placetype": [
          "aat:300008347"
        ],
        "id": 2084544,
        "name:xx": "Clackamas"
      }
    },
    {
      "geometry": {
        "type": "Point",
        "coordinates": [
          -122.5667,
          45.3667
        ]
      },
      "type": "Feature",
      "properties": {
        "hierarchy": [
          "tgn:2084545",
          "tgn:1000001",
          "tgn:1002270",
          "tgn:7012149",
          "tgn:7007708",
          "tgn:7029392"
        ],
        "placetype": [
          "aat:300008347"
        ],
        "id": 2084545,
        "name:xx": "Clackamas Heights"
      }
    },
    {
      "geometry": {
        "type": "Point",
        "coordinates": [
          -119.5833,
          45.8333
        ]
      },
      "type": "Feature",
      "properties": {
        "hierarchy": [
          "tgn:2084547",
          "tgn:1000001",
          "tgn:7012149",
          "tgn:2001719",
          "tgn:7007708",
          "tgn:7029392"
        ],
        "placetype": [
          "aat:300387016"
        ],
        "id": 2084547,
        "name:xx": "Clarke"
      }
    },
    {
      "geometry": {
        "type": "Point",
        "coordinates": [
          -122.4667,
          45.2
        ]
      },
      "type": "Feature",
      "properties": {
        "hierarchy": [
          "tgn:2084548",
          "tgn:1000001",
          "tgn:1002270",
          "tgn:7012149",
          "tgn:7007708",
          "tgn:7029392"
        ],
        "placetype": [
          "aat:300008347",
          "aat:300387210"
        ],
        "id": 2084548,
        "name:xx": "Clarkes"
      }
    },
    {
      "geometry": {
        "type": "Point",
        "coordinates": [
          -120.4667,
          44.9
        ]
      },
      "type": "Feature",
      "properties": {
        "hierarchy": [
          "tgn:2084549",
          "tgn:1000001",
          "tgn:7012149",
          "tgn:1002990",
          "tgn:7007708",
          "tgn:7029392"
        ],
        "placetype": [
          "aat:300008347",
          "aat:300387210"
        ],
        "id": 2084549,
        "name:xx": "Clarno"
      }
    }
  ]
}
