{
  "type": "FeatureCollection",
  "features": [
    {
      "geometry": {
        "type": "Point",
        "coordinates": [
          -106.45,
          38.3167
        ]
      },
      "type": "Feature",
      "properties": {
        "hierarchy": [
          "tgn:2479600",
          "tgn:1000001",
          "tgn:7012149",
          "tgn:7007158",
          "tgn:2000246",
          "tgn:7029392"
        ],
        "placetype": [
          "aat:300008699"
        ],
        "id": 2479600,
        "name:xx": "Lake Branch"
      }
    },
    {
      "geometry": {
        "type": "Point",
        "coordinates": [
          -82.05,
          27.7833
        ]
      },
      "type": "Feature",
      "properties": {
        "hierarchy": [
          "tgn:2479601",
          "tgn:1000001",
          "tgn:7012149",
          "tgn:7007240",
          "tgn:7029392"
        ],
        "placetype": [
          "aat:300008699"
        ],
        "id": 2479601,
        "name:xx": "Lake Branch"
      }
    },
    {
      "geometry": {
        "type": "Point",
        "coordinates": [
          -89.55,
          38.6667
        ]
      },
      "type": "Feature",
      "properties": {
        "hierarchy": [
          "tgn:2479602",
          "tgn:1000001",
          "tgn:1002281",
          "tgn:7012149",
          "tgn:7007251",
          "tgn:7029392"
        ],
        "placetype": [
          "aat:300008699"
        ],
        "id": 2479602,
        "name:xx": "Lake Branch"
      }
    },
    {
      "geometry": {
        "type": "Point",
        "coordinates": [
          -86.2833,
          39.6333
        ]
      },
      "type": "Feature",
      "properties": {
        "hierarchy": [
          "tgn:2479603",
          "tgn:1000001",
          "tgn:7012149",
          "tgn:1002633",
          "tgn:7007252",
          "tgn:7029392"
        ],
        "placetype": [
          "aat:300008699"
        ],
        "id": 2479603,
        "name:xx": "Lake Branch"
      }
    },
    {
      "geometry": {
        "type": "Point",
        "coordinates": [
          -85.4,
          40
        ]
      },
      "type": "Feature",
      "properties": {
        "hierarchy": [
          "tgn:2479604",
          "tgn:1000001",
          "tgn:7012149",
          "tgn:1002468",
          "tgn:7007252",
          "tgn:7029392"
        ],
        "placetype": [
          "aat:300008699"
        ],
        "id": 2479604,
        "name:xx": "Lake Branch"
      }
    },
    {
      "geometry": {
        "type": "Point",
        "coordinates": [
          -85.4667,
          40.4167
        ]
      },
      "type": "Feature",
      "properties": {
        "hierarchy": [
          "tgn:2479605",
          "tgn:1000001",
          "tgn:7012149",
          "tgn:1002416",
          "tgn:7007252",
          "tgn:7029392"
        ],
        "placetype": [
          "aat:300008699"
        ],
        "id": 2479605,
        "name:xx": "Lake Branch"
      }
    },
    {
      "geometry": {
        "type": "Point",
        "coordinates": [
          -84.55,
          38.65
        ]
      },
      "type": "Feature",
      "properties": {
        "hierarchy": [
          "tgn:2479606",
          "tgn:1000001",
          "tgn:7012149",
          "tgn:1002417",
          "tgn:7007255",
          "tgn:7029392"
        ],
        "placetype": [
          "aat:300008699"
        ],
        "id": 2479606,
        "name:xx": "Lake Branch"
      }
    },
    {
      "geometry": {
        "type": "Point",
        "coordinates": [
          -83.3167,
          43.3833
        ]
      },
      "type": "Feature",
      "properties": {
        "hierarchy": [
          "tgn:2479607",
          "tgn:1000001",
          "tgn:7012149",
          "tgn:2000997",
          "tgn:7007520",
          "tgn:7029392"
        ],
        "placetype": [
          "aat:300006075"
        ],
        "id": 2479607,
        "name:xx": "Lake Branch"
      }
    },
    {
      "geometry": {
        "type": "Point",
        "coordinates": [
          -91.9,
          38.7333
        ]
      },
      "type": "Feature",
      "properties": {
        "hierarchy": [
          "tgn:2479608",
          "tgn:1000001",
          "tgn:1002223",
          "tgn:7012149",
          "tgn:7007523",
          "tgn:7029392"
        ],
        "placetype": [
          "aat:300008699"
        ],
        "id": 2479608,
        "name:xx": "Lake Branch"
      }
    },
    {
      "geometry": {
        "type": "Point",
        "coordinates": [
          -92.7333,
          39.4
        ]
      },
      "type": "Feature",
      "properties": {
        "hierarchy": [
          "tgn:2479609",
          "tgn:1000001",
          "tgn:2001184",
          "tgn:7012149",
          "tgn:7007523",
          "tgn:7029392"
        ],
        "placetype": [
          "aat:300008699"
        ],
        "id": 2479609,
        "name:xx": "Lake Branch"
      }
    }
  ]
}
