{
  "geometry": {
    "type": "Point",
    "coordinates": [
      -72.7833,
      41.7833
    ]
  },
  "type": "Feature",
  "properties": {
    "hierarchy": [
      "tgn:2756514",
      "tgn:1000001",
      "tgn:1002461",
      "tgn:7012149",
      "tgn:7007159",
      "tgn:7029392"
    ],
    "placetype": [
      "aat:300008680"
    ],
    "id": 2756514,
    "name:xx": "Welles Pond"
  }
}
