{
  "geometry": {
    "type": "Point",
    "coordinates": [
      -83.9333,
      35.2667
    ]
  },
  "type": "Feature",
  "properties": {
    "hierarchy": [
      "tgn:2160792",
      "tgn:1000001",
      "tgn:7012149",
      "tgn:2001497",
      "tgn:7007709",
      "tgn:7029392"
    ],
    "placetype": [
      "aat:300008699"
    ],
    "id": 2160792,
    "name:xx": "Belding House Branch"
  }
}
