{
  "geometry": {
    "type": "Point",
    "coordinates": [
      105.8167,
      -6.4167
    ]
  },
  "type": "Feature",
  "properties": {
    "hierarchy": [
      "tgn:1077937",
      "tgn:1001321",
      "tgn:1000004",
      "tgn:1000116",
      "tgn:7029392"
    ],
    "placetype": [
      "aat:300008347"
    ],
    "id": 1077937,
    "name:xx": "Labuhan"
  }
}
