{
  "geometry": {
    "type": "Point",
    "coordinates": [
      30.4032,
      29.455288
    ]
  },
  "type": "Feature",
  "properties": {
    "hierarchy": [
      "tgn:7534797",
      "tgn:7001242",
      "tgn:7001105",
      "tgn:7016833",
      "tgn:7029392"
    ],
    "placetype": [
      "aat:300132316"
    ],
    "name:en": "Ḩītān, Būrat al",
    "id": 7534797
  }
}
