{
  "geometry": {
    "type": "Point",
    "coordinates": [
      79.9312,
      27.0762
    ]
  },
  "type": "Feature",
  "properties": {
    "hierarchy": [
      "tgn:7563288",
      "tgn:1000004",
      "tgn:7000198",
      "tgn:7016722",
      "tgn:7029392"
    ],
    "placetype": [
      "aat:300008347"
    ],
    "name:en": "Jalālpur Amra",
    "id": 7563288
  }
}
