{
  "geometry": {
    "type": "Point",
    "coordinates": [
      -123.9833,
      42.1833
    ]
  },
  "type": "Feature",
  "properties": {
    "hierarchy": [
      "tgn:2611661",
      "tgn:1000001",
      "tgn:2001704",
      "tgn:7012149",
      "tgn:7007708",
      "tgn:7029392"
    ],
    "placetype": [
      "aat:300008706"
    ],
    "id": 2611661,
    "name:xx": "Red Mountain Creek"
  }
}
