{
  "geometry": {
    "type": "Point",
    "coordinates": [
      -103.4833,
      46.9167
    ]
  },
  "type": "Feature",
  "properties": {
    "hierarchy": [
      "tgn:2648682",
      "tgn:2001560",
      "tgn:1000001",
      "tgn:7012149",
      "tgn:7007705",
      "tgn:7029392"
    ],
    "placetype": [
      "aat:300008347"
    ],
    "id": 2648682,
    "name:xx": "Scoria Point"
  }
}
