{
  "type": "FeatureCollection",
  "features": [
    {
      "geometry": {
        "type": "Point",
        "coordinates": [
          -110.716667,
          28.283333
        ]
      },
      "type": "Feature",
      "properties": {
        "hierarchy": [
          "tgn:7383370",
          "tgn:1000001",
          "tgn:1001960",
          "tgn:7005560",
          "tgn:7029392"
        ],
        "placetype": [
          "aat:300007783"
        ],
        "id": 7383370,
        "name:xx": "Ortiz"
      }
    },
    {
      "geometry": {
        "type": "Point",
        "coordinates": [
          -105.516667,
          28.25
        ]
      },
      "type": "Feature",
      "properties": {
        "hierarchy": [
          "tgn:7383371",
          "tgn:7005581",
          "tgn:1000001",
          "tgn:7005560",
          "tgn:7029392"
        ],
        "placetype": [
          "aat:300007783"
        ],
        "id": 7383371,
        "name:xx": "Ortiz"
      }
    },
    {
      "geometry": {
        "type": "Point",
        "coordinates": [
          -108.45,
          30.05
        ]
      },
      "type": "Feature",
      "properties": {
        "hierarchy": [
          "tgn:7383372",
          "tgn:7005581",
          "tgn:1000001",
          "tgn:7005560",
          "tgn:7029392"
        ],
        "placetype": [
          "aat:300000241"
        ],
        "id": 7383372,
        "name:xx": "Rancho Nuevo"
      }
    },
    {
      "geometry": {
        "type": "Point",
        "coordinates": [
          -106.583333,
          29.933333
        ]
      },
      "type": "Feature",
      "properties": {
        "hierarchy": [
          "tgn:7383373",
          "tgn:7005581",
          "tgn:1000001",
          "tgn:7005560",
          "tgn:7029392"
        ],
        "placetype": [
          "aat:300000241"
        ],
        "id": 7383373,
        "name:xx": "Rancho Nuevo"
      }
    },
    {
      "geometry": {
        "type": "Point",
        "coordinates": [
          -109.483333,
          29.816667
        ]
      },
      "type": "Feature",
      "properties": {
        "hierarchy": [
          "tgn:7383374",
          "tgn:1000001",
          "tgn:1001960",
          "tgn:7005560",
          "tgn:7029392"
        ],
        "placetype": [
          "aat:300000241"
        ],
        "id": 7383374,
        "name:xx": "Rancho Nuevo"
      }
    },
    {
      "geometry": {
        "type": "Point",
        "coordinates": [
          -105.35,
          29.8
        ]
      },
      "type": "Feature",
      "properties": {
        "hierarchy": [
          "tgn:7383375",
          "tgn:7005581",
          "tgn:1000001",
          "tgn:7005560",
          "tgn:7029392"
        ],
        "placetype": [
          "aat:300000241"
        ],
        "id": 7383375,
        "name:xx": "Rancho Nuevo"
      }
    },
    {
      "geometry": {
        "type": "Point",
        "coordinates": [
          -105,
          29.65
        ]
      },
      "type": "Feature",
      "properties": {
        "hierarchy": [
          "tgn:7383376",
          "tgn:7005581",
          "tgn:1000001",
          "tgn:7005560",
          "tgn:7029392"
        ],
        "placetype": [
          "aat:300000241"
        ],
        "id": 7383376,
        "name:xx": "Rancho Nuevo"
      }
    },
    {
      "geometry": {
        "type": "Point",
        "coordinates": [
          -102.566667,
          29.45
        ]
      },
      "type": "Feature",
      "properties": {
        "hierarchy": [
          "tgn:7383377",
          "tgn:1001853",
          "tgn:1000001",
          "tgn:7005560",
          "tgn:7029392"
        ],
        "placetype": [
          "aat:300000241"
        ],
        "id": 7383377,
        "name:xx": "Rancho Nuevo"
      }
    },
    {
      "geometry": {
        "type": "Point",
        "coordinates": [
          -111.433333,
          29.066667
        ]
      },
      "type": "Feature",
      "properties": {
        "hierarchy": [
          "tgn:7383378",
          "tgn:1000001",
          "tgn:1001960",
          "tgn:7005560",
          "tgn:7029392"
        ],
        "placetype": [
          "aat:300000241"
        ],
        "id": 7383378,
        "name:xx": "Rancho Nuevo"
      }
    },
    {
      "geometry": {
        "type": "Point",
        "coordinates": [
          -100.283333,
          28.233333
        ]
      },
      "type": "Feature",
      "properties": {
        "hierarchy": [
          "tgn:7383379",
          "tgn:1001853",
          "tgn:1000001",
          "tgn:7005560",
          "tgn:7029392"
        ],
        "placetype": [
          "aat:300000241"
        ],
        "id": 7383379,
        "name:xx": "Rancho Nuevo"
      }
    }
  ]
}
