{
  "geometry": {
    "type": "Point",
    "coordinates": [
      -89.2833,
      46.0833
    ]
  },
  "type": "Feature",
  "properties": {
    "hierarchy": [
      "tgn:2614600",
      "tgn:1000001",
      "tgn:7012149",
      "tgn:2002359",
      "tgn:7007922",
      "tgn:7029392"
    ],
    "placetype": [
      "aat:300008680"
    ],
    "id": 2614600,
    "name:xx": "Reiter Lake"
  }
}
