{
  "geometry": {
    "type": "Point",
    "coordinates": [
      -104.65,
      30.4333
    ]
  },
  "type": "Feature",
  "properties": {
    "hierarchy": [
      "tgn:2748361",
      "tgn:1000001",
      "tgn:7012149",
      "tgn:2002057",
      "tgn:7007826",
      "tgn:7029392"
    ],
    "placetype": [
      "aat:300008706"
    ],
    "id": 2748361,
    "name:xx": "Walker Creek"
  }
}
