{
  "type": "FeatureCollection",
  "features": [
    {
      "geometry": {
        "type": "Point",
        "coordinates": [
          -156.1167,
          20.65
        ]
      },
      "type": "Feature",
      "properties": {
        "hierarchy": [
          "tgn:2371760",
          "tgn:1002648",
          "tgn:1000001",
          "tgn:7019158",
          "tgn:7012149",
          "tgn:7007249",
          "tgn:7029392"
        ],
        "placetype": [
          "aat:300008347"
        ],
        "id": 2371760,
        "name:xx": "Hale o Kane Heiau"
      }
    },
    {
      "geometry": {
        "type": "Point",
        "coordinates": [
          -156.0167,
          19.6667
        ]
      },
      "type": "Feature",
      "properties": {
        "hierarchy": [
          "tgn:2371761",
          "tgn:7023902",
          "tgn:1000001",
          "tgn:7012149",
          "tgn:7007249",
          "tgn:7029392"
        ],
        "placetype": [
          "aat:300008347"
        ],
        "id": 2371761,
        "name:xx": "Hale o Lono Heiau"
      }
    },
    {
      "geometry": {
        "type": "Point",
        "coordinates": [
          -156.0167,
          19.6667
        ]
      },
      "type": "Feature",
      "properties": {
        "hierarchy": [
          "tgn:2371762",
          "tgn:7023902",
          "tgn:1000001",
          "tgn:7012149",
          "tgn:7007249",
          "tgn:7029392"
        ],
        "placetype": [
          "aat:300008347"
        ],
        "id": 2371762,
        "name:xx": "Hale o Mano Heiau"
      }
    },
    {
      "geometry": {
        "type": "Point",
        "coordinates": [
          -118.3,
          36.5833
        ]
      },
      "type": "Feature",
      "properties": {
        "hierarchy": [
          "tgn:2371763",
          "tgn:1000001",
          "tgn:7012149",
          "tgn:7007157",
          "tgn:1002956",
          "tgn:7029392"
        ],
        "placetype": [
          "aat:300008798"
        ],
        "id": 2371763,
        "name:xx": "Hale, Mount"
      }
    },
    {
      "geometry": {
        "type": "Point",
        "coordinates": [
          -71.5,
          44.2167
        ]
      },
      "type": "Feature",
      "properties": {
        "hierarchy": [
          "tgn:2371764",
          "tgn:1000001",
          "tgn:2001424",
          "tgn:7012149",
          "tgn:7007564",
          "tgn:7029392"
        ],
        "placetype": [
          "aat:300008798"
        ],
        "id": 2371764,
        "name:xx": "Hale, Mount"
      }
    },
    {
      "geometry": {
        "type": "Point",
        "coordinates": [
          -155.6833,
          20.05
        ]
      },
      "type": "Feature",
      "properties": {
        "hierarchy": [
          "tgn:2371765",
          "tgn:7023902",
          "tgn:1000001",
          "tgn:7012149",
          "tgn:7007249",
          "tgn:7029392"
        ],
        "placetype": [
          "aat:300008761"
        ],
        "id": 2371765,
        "name:xx": "Haleaha Gulch"
      }
    },
    {
      "geometry": {
        "type": "Point",
        "coordinates": [
          -156.1667,
          20.7
        ]
      },
      "type": "Feature",
      "properties": {
        "hierarchy": [
          "tgn:2371766",
          "tgn:1002648",
          "tgn:1000001",
          "tgn:7019158",
          "tgn:7012149",
          "tgn:7007249",
          "tgn:7029392"
        ],
        "placetype": [
          "aat:300008798"
        ],
        "id": 2371766,
        "name:xx": "Haleakala"
      }
    },
    {
      "geometry": {
        "type": "Point",
        "coordinates": [
          -158.1333,
          21.5
        ]
      },
      "type": "Feature",
      "properties": {
        "hierarchy": [
          "tgn:2371769",
          "tgn:1002483",
          "tgn:7019080",
          "tgn:1000001",
          "tgn:7012149",
          "tgn:7007249",
          "tgn:7029392"
        ],
        "placetype": [
          "aat:300008761"
        ],
        "id": 2371769,
        "name:xx": "Haleanau Gulch"
      }
    }
  ]
}
