{
  "geometry": {
    "type": "Point",
    "coordinates": [
      -86.9833,
      34.9167
    ]
  },
  "type": "Feature",
  "properties": {
    "hierarchy": [
      "tgn:2276830",
      "tgn:7002659",
      "tgn:1000001",
      "tgn:7012149",
      "tgn:2000041",
      "tgn:7029392"
    ],
    "placetype": [
      "aat:300008699"
    ],
    "id": 2276830,
    "name:xx": "Davis Branch"
  }
}
