{
  "geometry": {
    "type": "Point",
    "coordinates": [
      -3.1667,
      53.2667
    ]
  },
  "type": "Feature",
  "properties": {
    "hierarchy": [
      "tgn:1136678",
      "tgn:7002445",
      "tgn:7008114",
      "tgn:1000003",
      "tgn:7008591",
      "tgn:7029392"
    ],
    "placetype": [
      "aat:300008347"
    ],
    "id": 1136678,
    "name:ang": "Burtone"
  }
}
