{
  "geometry": {
    "type": "Point",
    "coordinates": [
      74.886111,
      32.6875
    ]
  },
  "type": "Feature",
  "properties": {
    "hierarchy": [
      "tgn:7591895",
      "tgn:1000004",
      "tgn:7000198",
      "tgn:7000799",
      "tgn:7029392"
    ],
    "placetype": [
      "aat:300008347"
    ],
    "name:en": "Chhanni Kamāl",
    "id": 7591895
  }
}
