{
  "geometry": {
    "type": "Point",
    "coordinates": [
      -80.75,
      38.7333
    ]
  },
  "type": "Feature",
  "properties": {
    "hierarchy": [
      "tgn:2618448",
      "tgn:1000001",
      "tgn:2002256",
      "tgn:7012149",
      "tgn:7013961",
      "tgn:7029392"
    ],
    "placetype": [
      "aat:300008706"
    ],
    "id": 2618448,
    "name:xx": "Right Fork Cedar Creek"
  }
}
