{
  "type": "FeatureCollection",
  "features": [
    {
      "geometry": {
        "type": "Point",
        "coordinates": [
          -82.2,
          34.9
        ]
      },
      "type": "Feature",
      "properties": {
        "hierarchy": [
          "tgn:2287670",
          "tgn:1000001",
          "tgn:7012149",
          "tgn:7007712",
          "tgn:7029392"
        ],
        "placetype": [
          "aat:300008706"
        ],
        "id": 2287670,
        "name:xx": "Dillard Creek"
      }
    },
    {
      "geometry": {
        "type": "Point",
        "coordinates": [
          -85.8167,
          36.2
        ]
      },
      "type": "Feature",
      "properties": {
        "hierarchy": [
          "tgn:2287671",
          "tgn:1000001",
          "tgn:7012149",
          "tgn:2001916",
          "tgn:7007825",
          "tgn:7029392"
        ],
        "placetype": [
          "aat:300008706"
        ],
        "id": 2287671,
        "name:xx": "Dillard Creek"
      }
    },
    {
      "geometry": {
        "type": "Point",
        "coordinates": [
          -89.15,
          36.2167
        ]
      },
      "type": "Feature",
      "properties": {
        "hierarchy": [
          "tgn:2287672",
          "tgn:1000001",
          "tgn:7012149",
          "tgn:2001902",
          "tgn:7007825",
          "tgn:7029392"
        ],
        "placetype": [
          "aat:300008706"
        ],
        "id": 2287672,
        "name:xx": "Dillard Creek"
      }
    },
    {
      "geometry": {
        "type": "Point",
        "coordinates": [
          -89.0833,
          36.1667
        ]
      },
      "type": "Feature",
      "properties": {
        "hierarchy": [
          "tgn:2287673",
          "tgn:1000001",
          "tgn:7012149",
          "tgn:7007825",
          "tgn:7029392"
        ],
        "placetype": [
          "aat:300008706"
        ],
        "id": 2287673,
        "name:xx": "Dillard Creek"
      }
    },
    {
      "geometry": {
        "type": "Point",
        "coordinates": [
          -95.4833,
          31.0333
        ]
      },
      "type": "Feature",
      "properties": {
        "hierarchy": [
          "tgn:2287674",
          "tgn:1000001",
          "tgn:7012149",
          "tgn:7007826",
          "tgn:7029392"
        ],
        "placetype": [
          "aat:300008706"
        ],
        "id": 2287674,
        "name:xx": "Dillard Creek"
      }
    },
    {
      "geometry": {
        "type": "Point",
        "coordinates": [
          -94.3833,
          32.2833
        ]
      },
      "type": "Feature",
      "properties": {
        "hierarchy": [
          "tgn:2287675",
          "tgn:1000001",
          "tgn:7012149",
          "tgn:1002769",
          "tgn:7007826",
          "tgn:7029392"
        ],
        "placetype": [
          "aat:300008706"
        ],
        "id": 2287675,
        "name:xx": "Dillard Creek"
      }
    },
    {
      "geometry": {
        "type": "Point",
        "coordinates": [
          -94.7833,
          33.5
        ]
      },
      "type": "Feature",
      "properties": {
        "hierarchy": [
          "tgn:2287676",
          "tgn:1000001",
          "tgn:7012149",
          "tgn:2002061",
          "tgn:7007826",
          "tgn:7029392"
        ],
        "placetype": [
          "aat:300008706"
        ],
        "id": 2287676,
        "name:xx": "Dillard Creek"
      }
    },
    {
      "geometry": {
        "type": "Point",
        "coordinates": [
          -78.8833,
          37.7833
        ]
      },
      "type": "Feature",
      "properties": {
        "hierarchy": [
          "tgn:2287677",
          "tgn:1000001",
          "tgn:7012149",
          "tgn:2002175",
          "tgn:7007919",
          "tgn:7029392"
        ],
        "placetype": [
          "aat:300008706"
        ],
        "id": 2287677,
        "name:xx": "Dillard Creek"
      }
    },
    {
      "geometry": {
        "type": "Point",
        "coordinates": [
          -121.7833,
          48.7167
        ]
      },
      "type": "Feature",
      "properties": {
        "hierarchy": [
          "tgn:2287678",
          "tgn:1000001",
          "tgn:7012149",
          "tgn:1003020",
          "tgn:7007920",
          "tgn:7029392"
        ],
        "placetype": [
          "aat:300008706"
        ],
        "id": 2287678,
        "name:xx": "Dillard Creek"
      }
    },
    {
      "geometry": {
        "type": "Point",
        "coordinates": [
          -82.0833,
          34.8167
        ]
      },
      "type": "Feature",
      "properties": {
        "hierarchy": [
          "tgn:2287679",
          "tgn:1000001",
          "tgn:7012149",
          "tgn:2001766",
          "tgn:7007712",
          "tgn:7029392"
        ],
        "placetype": [
          "aat:300008347"
        ],
        "id": 2287679,
        "name:xx": "Dillard Crossroads"
      }
    }
  ]
}
