{
  "type": "FeatureCollection",
  "features": [
    {
      "geometry": {
        "type": "Point",
        "coordinates": [
          -120.5333,
          39.4333
        ]
      },
      "type": "Feature",
      "properties": {
        "hierarchy": [
          "tgn:2340230",
          "tgn:1000001",
          "tgn:7012149",
          "tgn:7007157",
          "tgn:1002710",
          "tgn:7029392"
        ],
        "placetype": [
          "aat:300008706"
        ],
        "id": 2340230,
        "name:xx": "French Creek"
      }
    },
    {
      "geometry": {
        "type": "Point",
        "coordinates": [
          -121.0167,
          39.45
        ]
      },
      "type": "Feature",
      "properties": {
        "hierarchy": [
          "tgn:2340231",
          "tgn:1000001",
          "tgn:7012149",
          "tgn:7007157",
          "tgn:7029392"
        ],
        "placetype": [
          "aat:300008706"
        ],
        "id": 2340231,
        "name:xx": "French Creek"
      }
    },
    {
      "geometry": {
        "type": "Point",
        "coordinates": [
          -121.1667,
          40.0833
        ]
      },
      "type": "Feature",
      "properties": {
        "hierarchy": [
          "tgn:2340232",
          "tgn:1000001",
          "tgn:7012149",
          "tgn:7007157",
          "tgn:2000187",
          "tgn:7029392"
        ],
        "placetype": [
          "aat:300008706"
        ],
        "id": 2340232,
        "name:xx": "French Creek"
      }
    },
    {
      "geometry": {
        "type": "Point",
        "coordinates": [
          -120.8833,
          38.65
        ]
      },
      "type": "Feature",
      "properties": {
        "hierarchy": [
          "tgn:2340233",
          "tgn:1000001",
          "tgn:7012149",
          "tgn:1002350",
          "tgn:7007157",
          "tgn:7029392"
        ],
        "placetype": [
          "aat:300008706"
        ],
        "id": 2340233,
        "name:xx": "French Creek"
      }
    },
    {
      "geometry": {
        "type": "Point",
        "coordinates": [
          -122.8333,
          39.2333
        ]
      },
      "type": "Feature",
      "properties": {
        "hierarchy": [
          "tgn:2340234",
          "tgn:1000001",
          "tgn:7012149",
          "tgn:7007157",
          "tgn:1002566",
          "tgn:7029392"
        ],
        "placetype": [
          "aat:300008706"
        ],
        "id": 2340234,
        "name:xx": "French Creek"
      }
    },
    {
      "geometry": {
        "type": "Point",
        "coordinates": [
          -122.45,
          39.6667
        ]
      },
      "type": "Feature",
      "properties": {
        "hierarchy": [
          "tgn:2340235",
          "tgn:1000001",
          "tgn:7012149",
          "tgn:1002409",
          "tgn:7007157",
          "tgn:7029392"
        ],
        "placetype": [
          "aat:300008706"
        ],
        "id": 2340235,
        "name:xx": "French Creek"
      }
    },
    {
      "geometry": {
        "type": "Point",
        "coordinates": [
          -121.35,
          39.7667
        ]
      },
      "type": "Feature",
      "properties": {
        "hierarchy": [
          "tgn:2340236",
          "tgn:1000001",
          "tgn:1002218",
          "tgn:7012149",
          "tgn:7007157",
          "tgn:7029392"
        ],
        "placetype": [
          "aat:300008706"
        ],
        "id": 2340236,
        "name:xx": "French Creek"
      }
    },
    {
      "geometry": {
        "type": "Point",
        "coordinates": [
          -124.0167,
          40.1333
        ]
      },
      "type": "Feature",
      "properties": {
        "hierarchy": [
          "tgn:2340237",
          "tgn:1000001",
          "tgn:7012149",
          "tgn:2000181",
          "tgn:7007157",
          "tgn:7029392"
        ],
        "placetype": [
          "aat:300008706"
        ],
        "id": 2340237,
        "name:xx": "French Creek"
      }
    },
    {
      "geometry": {
        "type": "Point",
        "coordinates": [
          -122.9167,
          41.3
        ]
      },
      "type": "Feature",
      "properties": {
        "hierarchy": [
          "tgn:2340238",
          "tgn:1000001",
          "tgn:7012149",
          "tgn:7007157",
          "tgn:2000189",
          "tgn:7029392"
        ],
        "placetype": [
          "aat:300008706"
        ],
        "id": 2340238,
        "name:xx": "French Creek"
      }
    },
    {
      "geometry": {
        "type": "Point",
        "coordinates": [
          -122.1167,
          40.65
        ]
      },
      "type": "Feature",
      "properties": {
        "hierarchy": [
          "tgn:2340239",
          "tgn:1000001",
          "tgn:7012149",
          "tgn:7007157",
          "tgn:2000188",
          "tgn:7029392"
        ],
        "placetype": [
          "aat:300008706"
        ],
        "id": 2340239,
        "name:xx": "French Creek"
      }
    }
  ]
}
