{
  "geometry": {
    "type": "Point",
    "coordinates": [
      32.95,
      24.666667
    ]
  },
  "type": "Feature",
  "properties": {
    "hierarchy": [
      "tgn:7534579",
      "tgn:7001242",
      "tgn:7016833",
      "tgn:7000122",
      "tgn:7029392"
    ],
    "placetype": [
      "aat:300007783"
    ],
    "name:en": "Kājūj",
    "id": 7534579
  }
}
