{
  "geometry": {
    "type": "Point",
    "coordinates": [
      46.8167,
      41.3667
    ]
  },
  "type": "Feature",
  "properties": {
    "hierarchy": [
      "tgn:1052116",
      "tgn:7011438",
      "tgn:1000004",
      "tgn:7006646",
      "tgn:7029392"
    ],
    "placetype": [
      "aat:300008347"
    ],
    "id": 1052116,
    "name:xx": "Alibeyli"
  }
}
