{
  "geometry": {
    "type": "Point",
    "coordinates": [
      -72.4667,
      43.5833
    ]
  },
  "type": "Feature",
  "properties": {
    "hierarchy": [
      "tgn:2270586",
      "tgn:1000001",
      "tgn:2002136",
      "tgn:7012149",
      "tgn:7007828",
      "tgn:7029392"
    ],
    "placetype": [
      "aat:300008680"
    ],
    "id": 2270586,
    "name:xx": "Crystal Pond"
  }
}
