{
  "geometry": {
    "type": "Point",
    "coordinates": [
      -110.6333,
      44.6167
    ]
  },
  "type": "Feature",
  "properties": {
    "hierarchy": [
      "tgn:2495345",
      "tgn:1000001",
      "tgn:7012149",
      "tgn:7007923",
      "tgn:7029392"
    ],
    "placetype": [
      "aat:300008798"
    ],
    "id": 2495345,
    "name:xx": "Mary Mountain"
  }
}
