{
  "geometry": {
    "type": "Point",
    "coordinates": [
      -108.8833,
      43.4833
    ]
  },
  "type": "Feature",
  "properties": {
    "hierarchy": [
      "tgn:2407665",
      "tgn:1000001",
      "tgn:7012149",
      "tgn:2002371",
      "tgn:7007923",
      "tgn:7029392"
    ],
    "placetype": [
      "aat:300008761"
    ],
    "id": 2407665,
    "name:xx": "Hurley Draw"
  }
}
