{
  "geometry": {
    "type": "Point",
    "coordinates": [
      -78.85,
      37.4167
    ]
  },
  "type": "Feature",
  "properties": {
    "hierarchy": [
      "tgn:2113481",
      "tgn:2002141",
      "tgn:1000001",
      "tgn:7012149",
      "tgn:7007919",
      "tgn:7029392"
    ],
    "placetype": [
      "aat:300008347"
    ],
    "id": 2113481,
    "name:xx": "Oakville"
  }
}
