{
  "geometry": {
    "type": "Point",
    "coordinates": [
      -85.6167,
      34.0667
    ]
  },
  "type": "Feature",
  "properties": {
    "hierarchy": [
      "tgn:2003156",
      "tgn:7002659",
      "tgn:1000001",
      "tgn:2000009",
      "tgn:7012149",
      "tgn:7029392"
    ],
    "placetype": [
      "aat:300008347",
      "aat:300387210"
    ],
    "id": 2003156,
    "name:xx": "Coloma"
  }
}
