{
  "type": "FeatureCollection",
  "features": [
    {
      "geometry": {
        "type": "Point",
        "coordinates": [
          5.1,
          52.016667
        ]
      },
      "type": "Feature",
      "properties": {
        "hierarchy": [
          "tgn:7267880",
          "tgn:1000003",
          "tgn:7003627",
          "tgn:7016845",
          "tgn:7029392"
        ],
        "placetype": [
          "aat:300006163"
        ],
        "name:nl": "Rijnhuizen, Polder",
        "id": 7267880
      }
    },
    {
      "geometry": {
        "type": "Point",
        "coordinates": [
          5.1,
          52.033333
        ]
      },
      "type": "Feature",
      "properties": {
        "hierarchy": [
          "tgn:7267881",
          "tgn:1000003",
          "tgn:7003627",
          "tgn:7016845",
          "tgn:7029392"
        ],
        "placetype": [
          "aat:300006891"
        ],
        "name:nl": "Rijnhuizen",
        "id": 7267881
      }
    },
    {
      "geometry": {
        "type": "Point",
        "coordinates": [
          4.483333,
          51.9
        ]
      },
      "type": "Feature",
      "properties": {
        "hierarchy": [
          "tgn:7267882",
          "tgn:1000003",
          "tgn:7003632",
          "tgn:7016845",
          "tgn:7029392"
        ],
        "placetype": [
          "aat:300120801"
        ],
        "name:nl": "Rijnhaven",
        "id": 7267882
      }
    },
    {
      "geometry": {
        "type": "Point",
        "coordinates": [
          4.683333,
          52.083333
        ]
      },
      "type": "Feature",
      "properties": {
        "hierarchy": [
          "tgn:7267883",
          "tgn:1000003",
          "tgn:7003632",
          "tgn:7016845",
          "tgn:7029392"
        ],
        "placetype": [
          "aat:300006163"
        ],
        "name:nl": "Rijneveld, Polder",
        "id": 7267883
      }
    },
    {
      "geometry": {
        "type": "Point",
        "coordinates": [
          5.316667,
          52
        ]
      },
      "type": "Feature",
      "properties": {
        "hierarchy": [
          "tgn:7267884",
          "tgn:1000003",
          "tgn:7003627",
          "tgn:7016845",
          "tgn:7029392"
        ],
        "placetype": [
          "aat:300006891"
        ],
        "name:nl": "Rijnestein",
        "id": 7267884
      }
    },
    {
      "geometry": {
        "type": "Point",
        "coordinates": [
          4.6,
          52.116667
        ]
      },
      "type": "Feature",
      "properties": {
        "hierarchy": [
          "tgn:7267885",
          "tgn:1000003",
          "tgn:7003632",
          "tgn:7016845",
          "tgn:7029392"
        ],
        "placetype": [
          "aat:300006163"
        ],
        "name:nl": "Rijnenburgerpolder",
        "id": 7267885
      }
    },
    {
      "geometry": {
        "type": "Point",
        "coordinates": [
          4.45,
          52.15
        ]
      },
      "type": "Feature",
      "properties": {
        "hierarchy": [
          "tgn:7267886",
          "tgn:1000003",
          "tgn:7003632",
          "tgn:7016845",
          "tgn:7029392"
        ],
        "placetype": [
          "aat:300008347"
        ],
        "name:nl": "Rijndijk",
        "id": 7267886
      }
    },
    {
      "geometry": {
        "type": "Point",
        "coordinates": [
          4.683333,
          52.116667
        ]
      },
      "type": "Feature",
      "properties": {
        "hierarchy": [
          "tgn:7267887",
          "tgn:1000003",
          "tgn:7003632",
          "tgn:7016845",
          "tgn:7029392"
        ],
        "placetype": [
          "aat:300007836"
        ],
        "name:nl": "Rijnbrug",
        "id": 7267887
      }
    },
    {
      "geometry": {
        "type": "Point",
        "coordinates": [
          5.9,
          51.983333
        ]
      },
      "type": "Feature",
      "properties": {
        "hierarchy": [
          "tgn:7267888",
          "tgn:7003619",
          "tgn:1000003",
          "tgn:7016845",
          "tgn:7029392"
        ],
        "placetype": [
          "aat:300007836"
        ],
        "name:nl": "Rijnbrug",
        "id": 7267888
      }
    },
    {
      "geometry": {
        "type": "Point",
        "coordinates": [
          4.1,
          51.5
        ]
      },
      "type": "Feature",
      "properties": {
        "hierarchy": [
          "tgn:7267889",
          "tgn:1000003",
          "tgn:7003635",
          "tgn:7016845",
          "tgn:7029392"
        ],
        "placetype": [
          "aat:300387026"
        ],
        "name:nl": "Rijn",
        "id": 7267889
      }
    }
  ]
}
