{
  "type": "FeatureCollection",
  "features": [
    {
      "geometry": {
        "type": "Point",
        "coordinates": [
          16.516667,
          39.6
        ]
      },
      "type": "Feature",
      "properties": {
        "hierarchy": [
          "tgn:1044381",
          "tgn:1003450",
          "tgn:7007850",
          "tgn:1000003",
          "tgn:1000080",
          "tgn:7029392"
        ],
        "placetype": [
          "aat:300008347"
        ],
        "id": 1044381,
        "name:xx": "Corigliano Calabro"
      }
    },
    {
      "geometry": {
        "type": "Point",
        "coordinates": [
          13.3,
          37.816667
        ]
      },
      "type": "Feature",
      "properties": {
        "hierarchy": [
          "tgn:1044384",
          "tgn:1000003",
          "tgn:7003122",
          "tgn:1001732",
          "tgn:1000080",
          "tgn:7029392"
        ],
        "placetype": [
          "aat:300008347"
        ],
        "id": 1044384,
        "name:xx": "Corleone"
      }
    },
    {
      "geometry": {
        "type": "Point",
        "coordinates": [
          16.033333,
          40.383333
        ]
      },
      "type": "Feature",
      "properties": {
        "hierarchy": [
          "tgn:1044385",
          "tgn:1003489",
          "tgn:7004610",
          "tgn:1000003",
          "tgn:1000080",
          "tgn:7029392"
        ],
        "placetype": [
          "aat:300008347"
        ],
        "id": 1044385,
        "name:xx": "Corleto Perticara"
      }
    },
    {
      "geometry": {
        "type": "Point",
        "coordinates": [
          9.166667,
          45.533333
        ]
      },
      "type": "Feature",
      "properties": {
        "hierarchy": [
          "tgn:1044386",
          "tgn:7003150",
          "tgn:1000003",
          "tgn:7003237",
          "tgn:1000080",
          "tgn:7029392"
        ],
        "placetype": [
          "aat:300008347"
        ],
        "id": 1044386,
        "name:xx": "Cormano"
      }
    },
    {
      "geometry": {
        "type": "Point",
        "coordinates": [
          13.472222,
          45.960556
        ]
      },
      "type": "Feature",
      "properties": {
        "hierarchy": [
          "tgn:1044387",
          "tgn:1003459",
          "tgn:1000003",
          "tgn:7002993",
          "tgn:1000080",
          "tgn:7029392"
        ],
        "placetype": [
          "aat:300008347"
        ],
        "id": 1044387,
        "name:xx": "Cormons"
      }
    },
    {
      "geometry": {
        "type": "Point",
        "coordinates": [
          10.166667,
          45.883333
        ]
      },
      "type": "Feature",
      "properties": {
        "hierarchy": [
          "tgn:1044388",
          "tgn:7005023",
          "tgn:1000003",
          "tgn:7003237",
          "tgn:1000080",
          "tgn:7029392"
        ],
        "placetype": [
          "aat:300008347"
        ],
        "id": 1044388,
        "name:xx": "Corna"
      }
    },
    {
      "geometry": {
        "type": "Point",
        "coordinates": [
          9.016667,
          45.5
        ]
      },
      "type": "Feature",
      "properties": {
        "hierarchy": [
          "tgn:1044389",
          "tgn:7003150",
          "tgn:1000003",
          "tgn:7003237",
          "tgn:1000080",
          "tgn:7029392"
        ],
        "placetype": [
          "aat:300008347"
        ],
        "id": 1044389,
        "name:xx": "Cornaredo"
      }
    }
  ]
}
