{
  "geometry": {
    "type": "Point",
    "coordinates": [
      30.083333,
      29.033333
    ]
  },
  "type": "Feature",
  "properties": {
    "hierarchy": [
      "tgn:7537369",
      "tgn:7001242",
      "tgn:7016833",
      "tgn:1001142",
      "tgn:7029392"
    ],
    "placetype": [
      "aat:300008777"
    ],
    "name:en": "Quşūr al 'Arab, Qārat",
    "id": 7537369
  }
}
