{
  "geometry": {
    "type": "Point",
    "coordinates": [
      -72.8333,
      46.0667
    ]
  },
  "type": "Feature",
  "properties": {
    "hierarchy": [
      "tgn:1015652",
      "tgn:7005685",
      "tgn:1000001",
      "tgn:7005804",
      "tgn:7029392"
    ],
    "placetype": [
      "aat:300008347"
    ],
    "id": 1015652,
    "name:xx": "Saint-François-du-Lac"
  }
}
