{
  "geometry": {
    "type": "Point",
    "coordinates": [
      -73.95,
      42.5667
    ]
  },
  "type": "Feature",
  "properties": {
    "hierarchy": [
      "tgn:2068529",
      "tgn:1002139",
      "tgn:1000001",
      "tgn:7012149",
      "tgn:7007568",
      "tgn:7029392"
    ],
    "placetype": [
      "aat:300008347"
    ],
    "id": 2068529,
    "name:xx": "Clarksville"
  }
}
