{
  "geometry": {
    "type": "Point",
    "coordinates": [
      75.4781,
      28.8549
    ]
  },
  "type": "Feature",
  "properties": {
    "hierarchy": [
      "tgn:7584160",
      "tgn:1000004",
      "tgn:7000198",
      "tgn:7016788",
      "tgn:7029392"
    ],
    "placetype": [
      "aat:300008688"
    ],
    "name:en": "Dholpāliya Johri",
    "id": 7584160
  }
}
