{
  "geometry": {
    "type": "Point",
    "coordinates": [
      -87.3333,
      46.3333
    ]
  },
  "type": "Feature",
  "properties": {
    "hierarchy": [
      "tgn:2757644",
      "tgn:1000001",
      "tgn:7012149",
      "tgn:2000975",
      "tgn:7007520",
      "tgn:7029392"
    ],
    "placetype": [
      "aat:300008707"
    ],
    "id": 2757644,
    "name:xx": "West Branch Chocolay River"
  }
}
