{
  "type": "FeatureCollection",
  "features": [
    {
      "geometry": {
        "type": "Point",
        "coordinates": [
          -85.1167,
          41.9
        ]
      },
      "type": "Feature",
      "properties": {
        "hierarchy": [
          "tgn:2415210",
          "tgn:1000001",
          "tgn:1002195",
          "tgn:7012149",
          "tgn:7007520",
          "tgn:7029392"
        ],
        "placetype": [
          "aat:300008680"
        ],
        "id": 2415210,
        "name:xx": "Island Lake"
      }
    },
    {
      "geometry": {
        "type": "Point",
        "coordinates": [
          -96,
          44.3667
        ]
      },
      "type": "Feature",
      "properties": {
        "hierarchy": [
          "tgn:2415211",
          "tgn:1000001",
          "tgn:7012149",
          "tgn:2001040",
          "tgn:7007521",
          "tgn:7029392"
        ],
        "placetype": [
          "aat:300008680"
        ],
        "id": 2415211,
        "name:xx": "Island Lake"
      }
    },
    {
      "geometry": {
        "type": "Point",
        "coordinates": [
          -93.1333,
          45.05
        ]
      },
      "type": "Feature",
      "properties": {
        "hierarchy": [
          "tgn:2415212",
          "tgn:1000001",
          "tgn:7012149",
          "tgn:2001060",
          "tgn:7007521",
          "tgn:7029392"
        ],
        "placetype": [
          "aat:300008680"
        ],
        "id": 2415212,
        "name:xx": "Island Lake"
      }
    },
    {
      "geometry": {
        "type": "Point",
        "coordinates": [
          -93.0833,
          45.3667
        ]
      },
      "type": "Feature",
      "properties": {
        "hierarchy": [
          "tgn:2415213",
          "tgn:2001000",
          "tgn:1000001",
          "tgn:7012149",
          "tgn:7007521",
          "tgn:7029392"
        ],
        "placetype": [
          "aat:300008680"
        ],
        "id": 2415213,
        "name:xx": "Island Lake"
      }
    },
    {
      "geometry": {
        "type": "Point",
        "coordinates": [
          -94.3833,
          45.55
        ]
      },
      "type": "Feature",
      "properties": {
        "hierarchy": [
          "tgn:2415214",
          "tgn:1000001",
          "tgn:7012149",
          "tgn:2001071",
          "tgn:7007521",
          "tgn:7029392"
        ],
        "placetype": [
          "aat:300008680"
        ],
        "id": 2415214,
        "name:xx": "Island Lake"
      }
    },
    {
      "geometry": {
        "type": "Point",
        "coordinates": [
          -95.9667,
          45.9667
        ]
      },
      "type": "Feature",
      "properties": {
        "hierarchy": [
          "tgn:2415215",
          "tgn:1000001",
          "tgn:2001024",
          "tgn:7012149",
          "tgn:7007521",
          "tgn:7029392"
        ],
        "placetype": [
          "aat:300008680"
        ],
        "id": 2415215,
        "name:xx": "Island Lake"
      }
    },
    {
      "geometry": {
        "type": "Point",
        "coordinates": [
          -94.3,
          46.3
        ]
      },
      "type": "Feature",
      "properties": {
        "hierarchy": [
          "tgn:2415216",
          "tgn:1000001",
          "tgn:2001016",
          "tgn:7012149",
          "tgn:7007521",
          "tgn:7029392"
        ],
        "placetype": [
          "aat:300008680"
        ],
        "id": 2415216,
        "name:xx": "Island Lake"
      }
    },
    {
      "geometry": {
        "type": "Point",
        "coordinates": [
          -93.1833,
          46.7333
        ]
      },
      "type": "Feature",
      "properties": {
        "hierarchy": [
          "tgn:2415217",
          "tgn:2000999",
          "tgn:1000001",
          "tgn:7012149",
          "tgn:7007521",
          "tgn:7029392"
        ],
        "placetype": [
          "aat:300008680"
        ],
        "id": 2415217,
        "name:xx": "Island Lake"
      }
    },
    {
      "geometry": {
        "type": "Point",
        "coordinates": [
          -95.3,
          46.8333
        ]
      },
      "type": "Feature",
      "properties": {
        "hierarchy": [
          "tgn:2415218",
          "tgn:2001001",
          "tgn:1000001",
          "tgn:7012149",
          "tgn:7007521",
          "tgn:7029392"
        ],
        "placetype": [
          "aat:300008680"
        ],
        "id": 2415218,
        "name:xx": "Island Lake"
      }
    },
    {
      "geometry": {
        "type": "Point",
        "coordinates": [
          -94.5167,
          46.85
        ]
      },
      "type": "Feature",
      "properties": {
        "hierarchy": [
          "tgn:2415219",
          "tgn:1000001",
          "tgn:2001009",
          "tgn:7012149",
          "tgn:7007521",
          "tgn:7029392"
        ],
        "placetype": [
          "aat:300008680"
        ],
        "id": 2415219,
        "name:xx": "Island Lake"
      }
    }
  ]
}
