{
  "type": "FeatureCollection",
  "features": [
    {
      "geometry": {
        "type": "Point",
        "coordinates": [
          -158,
          21.4667
        ]
      },
      "type": "Feature",
      "properties": {
        "hierarchy": [
          "tgn:2025310",
          "tgn:1002483",
          "tgn:7019080",
          "tgn:1000001",
          "tgn:7012149",
          "tgn:7007249",
          "tgn:7029392"
        ],
        "placetype": [
          "aat:300008347"
        ],
        "id": 2025310,
        "name:xx": "Waipio Acres"
      }
    },
    {
      "geometry": {
        "type": "Point",
        "coordinates": [
          -158.0167,
          21.5
        ]
      },
      "type": "Feature",
      "properties": {
        "hierarchy": [
          "tgn:2025312",
          "tgn:1002483",
          "tgn:7019080",
          "tgn:1000001",
          "tgn:7012149",
          "tgn:7007249",
          "tgn:7029392"
        ],
        "placetype": [
          "aat:300008347"
        ],
        "id": 2025312,
        "name:xx": "Whitmore Village"
      }
    },
    {
      "geometry": {
        "type": "Point",
        "coordinates": [
          -155.4833,
          19.2667
        ]
      },
      "type": "Feature",
      "properties": {
        "hierarchy": [
          "tgn:2025313",
          "tgn:7023902",
          "tgn:1000001",
          "tgn:7012149",
          "tgn:7007249",
          "tgn:7029392"
        ],
        "placetype": [
          "aat:300008347",
          "aat:300387210"
        ],
        "id": 2025313,
        "name:xx": "Wood Valley Homesteads"
      }
    },
    {
      "geometry": {
        "type": "Point",
        "coordinates": [
          -112.8333,
          42.9333
        ]
      },
      "type": "Feature",
      "properties": {
        "hierarchy": [
          "tgn:2025314",
          "tgn:1000001",
          "tgn:2000457",
          "tgn:7012149",
          "tgn:7007250",
          "tgn:7029392"
        ],
        "placetype": [
          "aat:300008347"
        ],
        "id": 2025314,
        "name:xx": "Aberdeen"
      }
    },
    {
      "geometry": {
        "type": "Point",
        "coordinates": [
          -112.4667,
          43.2167
        ]
      },
      "type": "Feature",
      "properties": {
        "hierarchy": [
          "tgn:2025315",
          "tgn:1000001",
          "tgn:2000457",
          "tgn:7012149",
          "tgn:7007250",
          "tgn:7029392"
        ],
        "placetype": [
          "aat:300387016"
        ],
        "id": 2025315,
        "name:xx": "Aberdeen Junction"
      }
    },
    {
      "geometry": {
        "type": "Point",
        "coordinates": [
          -113.5833,
          42.6667
        ]
      },
      "type": "Feature",
      "properties": {
        "hierarchy": [
          "tgn:2025316",
          "tgn:1000001",
          "tgn:7012149",
          "tgn:2000485",
          "tgn:7007250",
          "tgn:7029392"
        ],
        "placetype": [
          "aat:300008347"
        ],
        "id": 2025316,
        "name:xx": "Acequia"
      }
    },
    {
      "geometry": {
        "type": "Point",
        "coordinates": [
          -113.7167,
          42.8
        ]
      },
      "type": "Feature",
      "properties": {
        "hierarchy": [
          "tgn:2025317",
          "tgn:1000001",
          "tgn:7012149",
          "tgn:2000485",
          "tgn:7007250",
          "tgn:7029392"
        ],
        "placetype": [
          "aat:300387016"
        ],
        "id": 2025317,
        "name:xx": "Adelaide"
      }
    },
    {
      "geometry": {
        "type": "Point",
        "coordinates": [
          -116.3167,
          46.5
        ]
      },
      "type": "Feature",
      "properties": {
        "hierarchy": [
          "tgn:2025318",
          "tgn:1000001",
          "tgn:2000469",
          "tgn:7012149",
          "tgn:7007250",
          "tgn:7029392"
        ],
        "placetype": [
          "aat:300008347"
        ],
        "id": 2025318,
        "name:xx": "Ahsahka"
      }
    },
    {
      "geometry": {
        "type": "Point",
        "coordinates": [
          -112.4,
          43.2
        ]
      },
      "type": "Feature",
      "properties": {
        "hierarchy": [
          "tgn:2025319",
          "tgn:1000001",
          "tgn:2000457",
          "tgn:7012149",
          "tgn:7007250",
          "tgn:7029392"
        ],
        "placetype": [
          "aat:300387016"
        ],
        "id": 2025319,
        "name:xx": "Aiken"
      }
    }
  ]
}
