{
  "geometry": {
    "type": "Point",
    "coordinates": [
      -149.5667,
      60.4667
    ]
  },
  "type": "Feature",
  "properties": {
    "hierarchy": [
      "tgn:2266716",
      "tgn:7006450",
      "tgn:1000001",
      "tgn:7019698",
      "tgn:7012149",
      "tgn:7029392"
    ],
    "placetype": [
      "aat:300008706"
    ],
    "id": 2266716,
    "name:xx": "Crescent Creek"
  }
}
