{
  "geometry": {
    "type": "Point",
    "coordinates": [
      -161.7833,
      61.8833
    ]
  },
  "type": "Feature",
  "properties": {
    "hierarchy": [
      "tgn:2693442",
      "tgn:7006450",
      "tgn:1000001",
      "tgn:7012149",
      "tgn:2000087",
      "tgn:7029392"
    ],
    "placetype": [
      "aat:300008706"
    ],
    "id": 2693442,
    "name:xx": "Stella Creek"
  }
}
