{
  "geometry": {
    "type": "Point",
    "coordinates": [
      -82.6833,
      38.0833
    ]
  },
  "type": "Feature",
  "properties": {
    "hierarchy": [
      "tgn:2223497",
      "tgn:1000001",
      "tgn:7012149",
      "tgn:2000809",
      "tgn:7007255",
      "tgn:7029392"
    ],
    "placetype": [
      "aat:300008699"
    ],
    "id": 2223497,
    "name:xx": "Carter Branch"
  }
}
