{
  "geometry": {
    "type": "Point",
    "coordinates": [
      -76.85,
      38.1333
    ]
  },
  "type": "Feature",
  "properties": {
    "hierarchy": [
      "tgn:2169593",
      "tgn:1000001",
      "tgn:7012149",
      "tgn:1003018",
      "tgn:7007919",
      "tgn:7029392"
    ],
    "placetype": [
      "aat:300008699"
    ],
    "id": 2169593,
    "name:xx": "Big Meadow Run"
  }
}
