{
  "geometry": {
    "type": "Point",
    "coordinates": [
      -91.15,
      45.4167
    ]
  },
  "type": "Feature",
  "properties": {
    "hierarchy": [
      "tgn:2593808",
      "tgn:1000001",
      "tgn:7012149",
      "tgn:2002350",
      "tgn:7007922",
      "tgn:7029392"
    ],
    "placetype": [
      "aat:300008347"
    ],
    "id": 2593808,
    "name:xx": "Port Arthur"
  }
}
