{
  "geometry": {
    "type": "Point",
    "coordinates": [
      -105.5833,
      44.8333
    ]
  },
  "type": "Feature",
  "properties": {
    "hierarchy": [
      "tgn:2231578",
      "tgn:1000001",
      "tgn:2002367",
      "tgn:7012149",
      "tgn:7007923",
      "tgn:7029392"
    ],
    "placetype": [
      "aat:300008699"
    ],
    "id": 2231578,
    "name:xx": "Chalk Prong"
  }
}
