{
  "geometry": {
    "type": "Point",
    "coordinates": [
      -88.9333,
      34.7333
    ]
  },
  "type": "Feature",
  "properties": {
    "hierarchy": [
      "tgn:2726519",
      "tgn:1000001",
      "tgn:7012149",
      "tgn:2001155",
      "tgn:7007522",
      "tgn:7029392"
    ],
    "placetype": [
      "aat:300008706"
    ],
    "id": 2726519,
    "name:xx": "Town Creek"
  }
}
