{
  "geometry": {
    "type": "Point",
    "coordinates": [
      -110.95,
      39.55
    ]
  },
  "type": "Feature",
  "properties": {
    "hierarchy": [
      "tgn:2585098",
      "tgn:1000001",
      "tgn:2002104",
      "tgn:7012149",
      "tgn:7007827",
      "tgn:7029392"
    ],
    "placetype": [
      "aat:300008699"
    ],
    "id": 2585098,
    "name:xx": "Pinnacle Wash"
  }
}
