{
  "geometry": {
    "type": "Point",
    "coordinates": [
      -116.2667,
      40.7333
    ]
  },
  "type": "Feature",
  "properties": {
    "hierarchy": [
      "tgn:2418889",
      "tgn:1000001",
      "tgn:2001413",
      "tgn:7012149",
      "tgn:7007526",
      "tgn:7029392"
    ],
    "placetype": [
      "aat:300008706"
    ],
    "id": 2418889,
    "name:xx": "James Creek"
  }
}
