{
  "type": "FeatureCollection",
  "features": [
    {
      "geometry": {
        "type": "Point",
        "coordinates": [
          -2.883333,
          43
        ]
      },
      "type": "Feature",
      "properties": {
        "hierarchy": [
          "tgn:7303020",
          "tgn:7001155",
          "tgn:1000003",
          "tgn:7002790",
          "tgn:1000095",
          "tgn:7029392"
        ],
        "placetype": [
          "aat:300008347"
        ],
        "id": 7303020,
        "name:xx": "Muguiro"
      }
    },
    {
      "geometry": {
        "type": "Point",
        "coordinates": [
          -1.133333,
          38.933333
        ]
      },
      "type": "Feature",
      "properties": {
        "hierarchy": [
          "tgn:7303021",
          "tgn:7002803",
          "tgn:1001647",
          "tgn:1000003",
          "tgn:1000095",
          "tgn:7029392"
        ],
        "placetype": [
          "aat:300008795"
        ],
        "id": 7303021,
        "name:xx": "Mugrón, Sierra del"
      }
    },
    {
      "geometry": {
        "type": "Point",
        "coordinates": [
          -9.216667,
          43.1
        ]
      },
      "type": "Feature",
      "properties": {
        "hierarchy": [
          "tgn:7303022",
          "tgn:7002824",
          "tgn:1000003",
          "tgn:7002786",
          "tgn:1000095",
          "tgn:7029392"
        ],
        "placetype": [
          "aat:300008347"
        ],
        "id": 7303022,
        "name:xx": "Mugia"
      }
    },
    {
      "geometry": {
        "type": "Point",
        "coordinates": [
          -8.25,
          43.466667
        ]
      },
      "type": "Feature",
      "properties": {
        "hierarchy": [
          "tgn:7303024",
          "tgn:7002824",
          "tgn:1000003",
          "tgn:7002786",
          "tgn:1000095",
          "tgn:7029392"
        ],
        "placetype": [
          "aat:300008347"
        ],
        "id": 7303024,
        "name:xx": "Mugardos"
      }
    },
    {
      "geometry": {
        "type": "Point",
        "coordinates": [
          -1.6,
          43.133333
        ]
      },
      "type": "Feature",
      "properties": {
        "hierarchy": [
          "tgn:7303025",
          "tgn:7001155",
          "tgn:1000003",
          "tgn:7002790",
          "tgn:1000095",
          "tgn:7029392"
        ],
        "placetype": [
          "aat:300008347"
        ],
        "id": 7303025,
        "name:xx": "Mugaire de Oronoz"
      }
    },
    {
      "geometry": {
        "type": "Point",
        "coordinates": [
          -6.2,
          41.383333
        ]
      },
      "type": "Feature",
      "properties": {
        "hierarchy": [
          "tgn:7303026",
          "tgn:7001158",
          "tgn:7002850",
          "tgn:1000003",
          "tgn:1000095",
          "tgn:7029392"
        ],
        "placetype": [
          "aat:300008347"
        ],
        "id": 7303026,
        "name:xx": "Muga de Sayago"
      }
    },
    {
      "geometry": {
        "type": "Point",
        "coordinates": [
          -6.033333,
          41.666667
        ]
      },
      "type": "Feature",
      "properties": {
        "hierarchy": [
          "tgn:7303027",
          "tgn:7001158",
          "tgn:7002850",
          "tgn:1000003",
          "tgn:1000095",
          "tgn:7029392"
        ],
        "placetype": [
          "aat:300008347"
        ],
        "id": 7303027,
        "name:xx": "Muga de Alba"
      }
    },
    {
      "geometry": {
        "type": "Point",
        "coordinates": [
          3.133333,
          42.233333
        ]
      },
      "type": "Feature",
      "properties": {
        "hierarchy": [
          "tgn:7303028",
          "tgn:7002820",
          "tgn:7030216",
          "tgn:1000003",
          "tgn:1000095",
          "tgn:7029392"
        ],
        "placetype": [
          "aat:300008699"
        ],
        "id": 7303028,
        "name:xx": "Muga, Río"
      }
    },
    {
      "geometry": {
        "type": "Point",
        "coordinates": [
          2.6,
          42.35
        ]
      },
      "type": "Feature",
      "properties": {
        "hierarchy": [
          "tgn:7303029",
          "tgn:7002820",
          "tgn:7030216",
          "tgn:1000003",
          "tgn:1000095",
          "tgn:7029392"
        ],
        "placetype": [
          "aat:300259572"
        ],
        "id": 7303029,
        "name:xx": "Mouga, Col de la"
      }
    }
  ]
}
