{
  "geometry": {
    "type": "Point",
    "coordinates": [
      31.384737,
      27.08663
    ]
  },
  "type": "Feature",
  "properties": {
    "hierarchy": [
      "tgn:7520929",
      "tgn:7001242",
      "tgn:7001311",
      "tgn:7016833",
      "tgn:7029392"
    ],
    "placetype": [
      "aat:300008347"
    ],
    "name:en": "Al Khawālid",
    "id": 7520929
  }
}
