{
  "geometry": {
    "type": "Point",
    "coordinates": [
      -112.1667,
      40.6667
    ]
  },
  "type": "Feature",
  "properties": {
    "hierarchy": [
      "tgn:2475922",
      "tgn:1000001",
      "tgn:7012149",
      "tgn:2002118",
      "tgn:7007827",
      "tgn:7029392"
    ],
    "placetype": [
      "aat:300008761"
    ],
    "id": 2475922,
    "name:xx": "Ludson Hollow"
  }
}
