{
  "geometry": {
    "type": "Point",
    "coordinates": [
      -73.0833,
      41.4833
    ]
  },
  "type": "Feature",
  "properties": {
    "hierarchy": [
      "tgn:2688259",
      "tgn:1000001",
      "tgn:1002712",
      "tgn:7012149",
      "tgn:7007159",
      "tgn:7029392"
    ],
    "placetype": [
      "aat:300008699"
    ],
    "id": 2688259,
    "name:xx": "Spruce Brook"
  }
}
