{
  "geometry": {
    "type": "Point",
    "coordinates": [
      -92.0833,
      35.5167
    ]
  },
  "type": "Feature",
  "properties": {
    "hierarchy": [
      "tgn:2352423",
      "tgn:1000001",
      "tgn:7016172",
      "tgn:2000116",
      "tgn:7012149",
      "tgn:7029392"
    ],
    "placetype": [
      "aat:300008791"
    ],
    "id": 2352423,
    "name:xx": "Goat Island"
  }
}
