{
  "geometry": {
    "type": "Point",
    "coordinates": [
      -73.1833,
      42.7333
    ]
  },
  "type": "Feature",
  "properties": {
    "hierarchy": [
      "tgn:2217031",
      "tgn:7013388",
      "tgn:1000001",
      "tgn:7012149",
      "tgn:7007517",
      "tgn:7029392"
    ],
    "placetype": [
      "aat:300008347"
    ],
    "id": 2217031,
    "name:xx": "Camp Muriel Flagg"
  }
}
