{
  "geometry": {
    "type": "Point",
    "coordinates": [
      -77.5333,
      41.9167
    ]
  },
  "type": "Feature",
  "properties": {
    "hierarchy": [
      "tgn:2094330",
      "tgn:1000001",
      "tgn:7012149",
      "tgn:1002945",
      "tgn:7007710",
      "tgn:7029392"
    ],
    "placetype": [
      "aat:300008347"
    ],
    "id": 2094330,
    "name:xx": "Westfield"
  }
}
