{
  "geometry": {
    "type": "Point",
    "coordinates": [
      -96.4333,
      33.2833
    ]
  },
  "type": "Feature",
  "properties": {
    "hierarchy": [
      "tgn:2447276",
      "tgn:1000001",
      "tgn:7012149",
      "tgn:1002290",
      "tgn:7007826",
      "tgn:7029392"
    ],
    "placetype": [
      "aat:300008699"
    ],
    "id": 2447276,
    "name:xx": "Lick Branch"
  }
}
