{
  "geometry": {
    "type": "Point",
    "coordinates": [
      -116.0667,
      48.3333
    ]
  },
  "type": "Feature",
  "properties": {
    "hierarchy": [
      "tgn:2759783",
      "tgn:1000001",
      "tgn:7012149",
      "tgn:7029392"
    ],
    "placetype": [
      "aat:300008706"
    ],
    "id": 2759783,
    "name:xx": "West Fork Keeler Creek"
  }
}
