{
  "geometry": {
    "type": "Point",
    "coordinates": [
      76.595224,
      30.178771
    ]
  },
  "type": "Feature",
  "properties": {
    "hierarchy": [
      "tgn:7584237",
      "tgn:1000004",
      "tgn:7000198",
      "tgn:7016883",
      "tgn:7029392"
    ],
    "placetype": [
      "aat:300008347"
    ],
    "name:en": "Alīpur Wazīr Sāhib",
    "id": 7584237
  }
}
