{
  "geometry": {
    "type": "Point",
    "coordinates": [
      -77.4333,
      36.5667
    ]
  },
  "type": "Feature",
  "properties": {
    "hierarchy": [
      "tgn:2201029",
      "tgn:1000001",
      "tgn:7012149",
      "tgn:1002425",
      "tgn:7007919",
      "tgn:7029392"
    ],
    "placetype": [
      "aat:300006191"
    ],
    "id": 2201029,
    "name:xx": "Bryants Millpond"
  }
}
