{
  "geometry": {
    "type": "Point",
    "coordinates": [
      -90.0667,
      33.8667
    ]
  },
  "type": "Feature",
  "properties": {
    "hierarchy": [
      "tgn:2056814",
      "tgn:1000001",
      "tgn:7012149",
      "tgn:2001153",
      "tgn:7007522",
      "tgn:7029392"
    ],
    "placetype": [
      "aat:300008347",
      "aat:300387210"
    ],
    "id": 2056814,
    "name:xx": "Leverett"
  }
}
