{
  "type": "FeatureCollection",
  "features": [
    {
      "geometry": {
        "type": "Point",
        "coordinates": [
          -70.783333,
          -35.25
        ]
      },
      "type": "Feature",
      "properties": {
        "hierarchy": [
          "tgn:7311790",
          "tgn:1001705",
          "tgn:1000049",
          "tgn:1000002",
          "tgn:7029392"
        ],
        "placetype": [
          "aat:300008795"
        ],
        "id": 7311790,
        "name:xx": "Las Mulas, Serranía"
      }
    },
    {
      "geometry": {
        "type": "Point",
        "coordinates": [
          -71.083333,
          -33.283333
        ]
      },
      "type": "Feature",
      "properties": {
        "hierarchy": [
          "tgn:7311791",
          "tgn:1001708",
          "tgn:1000049",
          "tgn:1000002",
          "tgn:7029392"
        ],
        "placetype": [
          "aat:300008699"
        ],
        "id": 7311791,
        "name:xx": "Las Mulas, Quebrada de"
      }
    },
    {
      "geometry": {
        "type": "Point",
        "coordinates": [
          -71.2,
          -30.783333
        ]
      },
      "type": "Feature",
      "properties": {
        "hierarchy": [
          "tgn:7311792",
          "tgn:1001657",
          "tgn:1000049",
          "tgn:1000002",
          "tgn:7029392"
        ],
        "placetype": [
          "aat:300008777"
        ],
        "id": 7311792,
        "name:xx": "Las Mulas, Loma"
      }
    },
    {
      "geometry": {
        "type": "Point",
        "coordinates": [
          -69.25,
          -25.116667
        ]
      },
      "type": "Feature",
      "properties": {
        "hierarchy": [
          "tgn:7311793",
          "tgn:7016598",
          "tgn:1000049",
          "tgn:1000002",
          "tgn:7029392"
        ],
        "placetype": [
          "aat:300008697"
        ],
        "id": 7311793,
        "name:xx": "Las Mulas, Agua de"
      }
    },
    {
      "geometry": {
        "type": "Point",
        "coordinates": [
          -70.35,
          -33.566667
        ]
      },
      "type": "Feature",
      "properties": {
        "hierarchy": [
          "tgn:7311794",
          "tgn:1001708",
          "tgn:1000049",
          "tgn:1000002",
          "tgn:7029392"
        ],
        "placetype": [
          "aat:300008699"
        ],
        "id": 7311794,
        "name:xx": "Las Monjas, Estero"
      }
    },
    {
      "geometry": {
        "type": "Point",
        "coordinates": [
          -71.166667,
          -33.516667
        ]
      },
      "type": "Feature",
      "properties": {
        "hierarchy": [
          "tgn:7311795",
          "tgn:1001708",
          "tgn:1000049",
          "tgn:1000002",
          "tgn:7029392"
        ],
        "placetype": [
          "aat:300387200"
        ],
        "id": 7311795,
        "name:xx": "Las Monjas"
      }
    },
    {
      "geometry": {
        "type": "Point",
        "coordinates": [
          -70.783333,
          -30.166667
        ]
      },
      "type": "Feature",
      "properties": {
        "hierarchy": [
          "tgn:7311796",
          "tgn:1001657",
          "tgn:1000049",
          "tgn:1000002",
          "tgn:7029392"
        ],
        "placetype": [
          "aat:300008699"
        ],
        "id": 7311796,
        "name:xx": "Las Mollacas, Quebrada"
      }
    },
    {
      "geometry": {
        "type": "Point",
        "coordinates": [
          -70.683333,
          -30.75
        ]
      },
      "type": "Feature",
      "properties": {
        "hierarchy": [
          "tgn:7311797",
          "tgn:1001657",
          "tgn:1000049",
          "tgn:1000002",
          "tgn:7029392"
        ],
        "placetype": [
          "aat:300008347"
        ],
        "id": 7311797,
        "name:xx": "Las Mollacas"
      }
    },
    {
      "geometry": {
        "type": "Point",
        "coordinates": [
          -70.916667,
          -30.35
        ]
      },
      "type": "Feature",
      "properties": {
        "hierarchy": [
          "tgn:7311798",
          "tgn:1001657",
          "tgn:1000049",
          "tgn:1000002",
          "tgn:7029392"
        ],
        "placetype": [
          "aat:300008347"
        ],
        "id": 7311798,
        "name:xx": "Las Mollacas"
      }
    },
    {
      "geometry": {
        "type": "Point",
        "coordinates": [
          -70.733333,
          -30.916667
        ]
      },
      "type": "Feature",
      "properties": {
        "hierarchy": [
          "tgn:7311799",
          "tgn:1001657",
          "tgn:1000049",
          "tgn:1000002",
          "tgn:7029392"
        ],
        "placetype": [
          "aat:300387200"
        ],
        "id": 7311799,
        "name:xx": "Las Mollacas"
      }
    }
  ]
}
