{
  "geometry": {
    "type": "Point",
    "coordinates": [
      -79.8167,
      40.5167
    ]
  },
  "type": "Feature",
  "properties": {
    "hierarchy": [
      "tgn:2322383",
      "tgn:7013272",
      "tgn:1000001",
      "tgn:7012149",
      "tgn:7007710",
      "tgn:7029392"
    ],
    "placetype": [
      "aat:300008699"
    ],
    "id": 2322383,
    "name:xx": "Falling Springs Run"
  }
}
