{
  "geometry": {
    "type": "Point",
    "coordinates": [
      -110.1667,
      45.2667
    ]
  },
  "type": "Feature",
  "properties": {
    "hierarchy": [
      "tgn:2401809",
      "tgn:1000001",
      "tgn:7012149",
      "tgn:2001308",
      "tgn:7007524",
      "tgn:7029392"
    ],
    "placetype": [
      "aat:300008680"
    ],
    "id": 2401809,
    "name:xx": "Horseshoe Lake"
  }
}
