{
  "geometry": {
    "type": "Point",
    "coordinates": [
      -75.3833,
      44.05
    ]
  },
  "type": "Feature",
  "properties": {
    "hierarchy": [
      "tgn:2570427",
      "tgn:1000001",
      "tgn:7012149",
      "tgn:1002593",
      "tgn:7007568",
      "tgn:7029392"
    ],
    "placetype": [
      "aat:300008905"
    ],
    "id": 2570427,
    "name:xx": "Patchin Swamp"
  }
}
