{
  "geometry": {
    "type": "Point",
    "coordinates": [
      -81.1167,
      32.2333
    ]
  },
  "type": "Feature",
  "properties": {
    "hierarchy": [
      "tgn:2738715",
      "tgn:1000001",
      "tgn:7012149",
      "tgn:7029392"
    ],
    "placetype": [
      "aat:300008706"
    ],
    "id": 2738715,
    "name:xx": "Union Creek"
  }
}
