{
  "geometry": {
    "type": "Point",
    "coordinates": [
      -83.6167,
      42.1333
    ]
  },
  "type": "Feature",
  "properties": {
    "hierarchy": [
      "tgn:2543877",
      "tgn:1000001",
      "tgn:7012149",
      "tgn:1003000",
      "tgn:7007520",
      "tgn:7029392"
    ],
    "placetype": [
      "aat:300006075"
    ],
    "id": 2543877,
    "name:xx": "North Branch"
  }
}
