{
  "geometry": {
    "type": "Point",
    "coordinates": [
      -87.4167,
      36.0833
    ]
  },
  "type": "Feature",
  "properties": {
    "hierarchy": [
      "tgn:2771031",
      "tgn:1000001",
      "tgn:7012149",
      "tgn:2001858",
      "tgn:7007825",
      "tgn:7029392"
    ],
    "placetype": [
      "aat:300008761"
    ],
    "id": 2771031,
    "name:xx": "Wildcat Hollow"
  }
}
