{
  "geometry": {
    "type": "Point",
    "coordinates": [
      35.95,
      29.5333
    ]
  },
  "type": "Feature",
  "properties": {
    "hierarchy": [
      "tgn:1081919",
      "tgn:1000004",
      "tgn:1000121",
      "tgn:1002092",
      "tgn:7029392"
    ],
    "placetype": [
      "aat:300008347"
    ],
    "id": 1081919,
    "name:xx": "Maḥaṭṭat ar-Ramlah"
  }
}
