{
  "geometry": {
    "type": "Point",
    "coordinates": [
      -87.8333,
      36.9833
    ]
  },
  "type": "Feature",
  "properties": {
    "hierarchy": [
      "tgn:2039448",
      "tgn:1000001",
      "tgn:2000776",
      "tgn:7012149",
      "tgn:7007255",
      "tgn:7029392"
    ],
    "placetype": [
      "aat:300008347",
      "aat:300387210"
    ],
    "id": 2039448,
    "name:xx": "Hopson"
  }
}
