{
  "type": "FeatureCollection",
  "features": [
    {
      "geometry": {
        "type": "Point",
        "coordinates": [
          -94.8,
          32.25
        ]
      },
      "type": "Feature",
      "properties": {
        "hierarchy": [
          "tgn:2224860",
          "tgn:1000001",
          "tgn:7012149",
          "tgn:1002839",
          "tgn:7007826",
          "tgn:7029392"
        ],
        "placetype": [
          "aat:300008699"
        ],
        "id": 2224860,
        "name:xx": "Cass Branch"
      }
    },
    {
      "geometry": {
        "type": "Point",
        "coordinates": [
          -72.3833,
          44.5833
        ]
      },
      "type": "Feature",
      "properties": {
        "hierarchy": [
          "tgn:2224861",
          "tgn:1000001",
          "tgn:7012149",
          "tgn:7007828",
          "tgn:7029392"
        ],
        "placetype": [
          "aat:300008699"
        ],
        "id": 2224861,
        "name:xx": "Cass Brook"
      }
    },
    {
      "geometry": {
        "type": "Point",
        "coordinates": [
          -79.95,
          38.3833
        ]
      },
      "type": "Feature",
      "properties": {
        "hierarchy": [
          "tgn:2224862",
          "tgn:1000001",
          "tgn:7012149",
          "tgn:2002287",
          "tgn:7013961",
          "tgn:7029392"
        ],
        "placetype": [
          "aat:300008746"
        ],
        "id": 2224862,
        "name:xx": "Cass Cave"
      }
    },
    {
      "geometry": {
        "type": "Point",
        "coordinates": [
          -69.6833,
          44.9
        ]
      },
      "type": "Feature",
      "properties": {
        "hierarchy": [
          "tgn:2224863",
          "tgn:1000001",
          "tgn:7012149",
          "tgn:2000930",
          "tgn:7007515",
          "tgn:7029392"
        ],
        "placetype": [
          "aat:300008347"
        ],
        "id": 2224863,
        "name:xx": "Cass Corner"
      }
    },
    {
      "geometry": {
        "type": "Point",
        "coordinates": [
          -94.6333,
          46.2333
        ]
      },
      "type": "Feature",
      "properties": {
        "hierarchy": [
          "tgn:2224865",
          "tgn:1000001",
          "tgn:7012149",
          "tgn:7007521",
          "tgn:7029392"
        ],
        "placetype": [
          "aat:300008680"
        ],
        "id": 2224865,
        "name:xx": "Cass County Lake"
      }
    },
    {
      "geometry": {
        "type": "Point",
        "coordinates": [
          -67.6833,
          45.2
        ]
      },
      "type": "Feature",
      "properties": {
        "hierarchy": [
          "tgn:2224866",
          "tgn:1000001",
          "tgn:7012149",
          "tgn:7014589",
          "tgn:7007515",
          "tgn:7029392"
        ],
        "placetype": [
          "aat:300132316"
        ],
        "id": 2224866,
        "name:xx": "Cass Cove"
      }
    },
    {
      "geometry": {
        "type": "Point",
        "coordinates": [
          -94.2833,
          41.7
        ]
      },
      "type": "Feature",
      "properties": {
        "hierarchy": [
          "tgn:2224867",
          "tgn:1000001",
          "tgn:7012149",
          "tgn:7007253",
          "tgn:7029392"
        ],
        "placetype": [
          "aat:300008706"
        ],
        "id": 2224867,
        "name:xx": "Cass Creek"
      }
    },
    {
      "geometry": {
        "type": "Point",
        "coordinates": [
          -110.7,
          37.9
        ]
      },
      "type": "Feature",
      "properties": {
        "hierarchy": [
          "tgn:2224868",
          "tgn:1000001",
          "tgn:2002109",
          "tgn:7012149",
          "tgn:7007827",
          "tgn:7029392"
        ],
        "placetype": [
          "aat:300008706"
        ],
        "id": 2224868,
        "name:xx": "Cass Creek"
      }
    },
    {
      "geometry": {
        "type": "Point",
        "coordinates": [
          -110.7,
          37.9
        ]
      },
      "type": "Feature",
      "properties": {
        "hierarchy": [
          "tgn:2224869",
          "tgn:1000001",
          "tgn:2002109",
          "tgn:7012149",
          "tgn:7007827",
          "tgn:7029392"
        ],
        "placetype": [
          "aat:300008798"
        ],
        "id": 2224869,
        "name:xx": "Cass Creek Peak"
      }
    }
  ]
}
