{
  "geometry": {
    "type": "Point",
    "coordinates": [
      -50.4833,
      -15.3667
    ]
  },
  "type": "Feature",
  "properties": {
    "hierarchy": [
      "tgn:1021867",
      "tgn:7012827",
      "tgn:7002454",
      "tgn:1000047",
      "tgn:1000002",
      "tgn:7029392"
    ],
    "placetype": [
      "aat:300008347"
    ],
    "id": 1021867,
    "name:xx": "Jeroaguara"
  }
}
