{
  "geometry": {
    "type": "Point",
    "coordinates": [
      -120.65,
      39.3667
    ]
  },
  "type": "Feature",
  "properties": {
    "hierarchy": [
      "tgn:2674167",
      "tgn:1000001",
      "tgn:7012149",
      "tgn:7007157",
      "tgn:1002710",
      "tgn:7029392"
    ],
    "placetype": [
      "aat:300000390"
    ],
    "id": 2674167,
    "name:xx": "Snowflower Mine"
  }
}
