{
  "geometry": {
    "type": "Point",
    "coordinates": [
      -94.15,
      40.3333
    ]
  },
  "type": "Feature",
  "properties": {
    "hierarchy": [
      "tgn:2592159",
      "tgn:1000001",
      "tgn:7012149",
      "tgn:2001201",
      "tgn:7007523",
      "tgn:7029392"
    ],
    "placetype": [
      "aat:300008699"
    ],
    "id": 2592159,
    "name:xx": "Pony Branch"
  }
}
