{
  "geometry": {
    "type": "Point",
    "coordinates": [
      -85.5833,
      40.4667
    ]
  },
  "type": "Feature",
  "properties": {
    "hierarchy": [
      "tgn:2657958",
      "tgn:1000001",
      "tgn:7012149",
      "tgn:1002416",
      "tgn:7007252",
      "tgn:7029392"
    ],
    "placetype": [
      "aat:300008699"
    ],
    "id": 2657958,
    "name:xx": "Shell Run"
  }
}
