{
  "geometry": {
    "type": "Point",
    "coordinates": [
      -119.8167,
      43.2333
    ]
  },
  "type": "Feature",
  "properties": {
    "hierarchy": [
      "tgn:2461612",
      "tgn:1000001",
      "tgn:7012149",
      "tgn:2001709",
      "tgn:7007708",
      "tgn:7029392"
    ],
    "placetype": [
      "aat:300008761"
    ],
    "id": 2461612,
    "name:xx": "Little Tank Canyon"
  }
}
