{
  "geometry": {
    "type": "Point",
    "coordinates": [
      -78.3167,
      40.25
    ]
  },
  "type": "Feature",
  "properties": {
    "hierarchy": [
      "tgn:2387919",
      "tgn:1000001",
      "tgn:7012149",
      "tgn:7007710",
      "tgn:7029392"
    ],
    "placetype": [
      "aat:300008706"
    ],
    "id": 2387919,
    "name:xx": "Hickory Bottom Creek"
  }
}
