{
  "geometry": {
    "type": "Point",
    "coordinates": [
      -91.2333,
      31.4833
    ]
  },
  "type": "Feature",
  "properties": {
    "hierarchy": [
      "tgn:2420008",
      "tgn:2001086",
      "tgn:1000001",
      "tgn:7012149",
      "tgn:7007522",
      "tgn:7029392"
    ],
    "placetype": [
      "aat:300008347"
    ],
    "id": 2420008,
    "name:xx": "Jeannette"
  }
}
