{
  "geometry": {
    "type": "Point",
    "coordinates": [
      88.48144,
      26.677083
    ]
  },
  "type": "Feature",
  "properties": {
    "hierarchy": [
      "tgn:7550735",
      "tgn:1000004",
      "tgn:7000198",
      "tgn:1001977",
      "tgn:7029392"
    ],
    "placetype": [
      "aat:300008347"
    ],
    "name:en": "Binnāguri",
    "id": 7550735
  }
}
