{
  "geometry": {
    "type": "Point",
    "coordinates": [
      -119.6667,
      42.4333
    ]
  },
  "type": "Feature",
  "properties": {
    "hierarchy": [
      "tgn:2257651",
      "tgn:1000001",
      "tgn:7012149",
      "tgn:2001715",
      "tgn:7007708",
      "tgn:7029392"
    ],
    "placetype": [
      "aat:300008706"
    ],
    "id": 2257651,
    "name:xx": "Corral Creek"
  }
}
