{
  "geometry": {
    "type": "Point",
    "coordinates": [
      -121.7833,
      38.8833
    ]
  },
  "type": "Feature",
  "properties": {
    "hierarchy": [
      "tgn:2387602",
      "tgn:1000001",
      "tgn:7012149",
      "tgn:7007157",
      "tgn:1002937",
      "tgn:7029392"
    ],
    "placetype": [
      "aat:300008680"
    ],
    "id": 2387602,
    "name:xx": "Hiatt Lake"
  }
}
