{
  "geometry": {
    "type": "Point",
    "coordinates": [
      -123.3667,
      46.2667
    ]
  },
  "type": "Feature",
  "properties": {
    "hierarchy": [
      "tgn:2620085",
      "tgn:1000001",
      "tgn:7012149",
      "tgn:1002979",
      "tgn:7007920",
      "tgn:7029392"
    ],
    "placetype": [
      "aat:300008706"
    ],
    "id": 2620085,
    "name:xx": "Risk Creek"
  }
}
