{
  "geometry": {
    "type": "Point",
    "coordinates": [
      -107.5833,
      43.9333
    ]
  },
  "type": "Feature",
  "properties": {
    "hierarchy": [
      "tgn:2235412",
      "tgn:1000001",
      "tgn:7012149",
      "tgn:2002386",
      "tgn:7007923",
      "tgn:7029392"
    ],
    "placetype": [
      "aat:300006191"
    ],
    "id": 2235412,
    "name:xx": "Chess Reservoir"
  }
}
