{
  "geometry": {
    "type": "Point",
    "coordinates": [
      -100.1167,
      30.8167
    ]
  },
  "type": "Feature",
  "properties": {
    "hierarchy": [
      "tgn:2710036",
      "tgn:1000001",
      "tgn:7012149",
      "tgn:2002070",
      "tgn:7007826",
      "tgn:7029392"
    ],
    "placetype": [
      "aat:300008680"
    ],
    "id": 2710036,
    "name:xx": "Talbot Lake"
  }
}
