{
  "geometry": {
    "type": "Point",
    "coordinates": [
      29.35,
      -28.7333
    ]
  },
  "type": "Feature",
  "properties": {
    "hierarchy": [
      "tgn:1092868",
      "tgn:7001242",
      "tgn:7016749",
      "tgn:1000193",
      "tgn:7029392"
    ],
    "placetype": [
      "aat:300008347"
    ],
    "id": 1092868,
    "name:xx": "Bergville"
  }
}
