{
  "geometry": {
    "type": "Point",
    "coordinates": [
      -60.9667,
      13.8833
    ]
  },
  "type": "Feature",
  "properties": {
    "name:en": "Saint Lucia",
    "hierarchy": [
      "tgn:7004772",
      "tgn:1000001",
      "tgn:7029392"
    ],
    "name:ar": "ساهت وًس اَ",
    "placetype": [
      "aat:300387054",
      "aat:300235115",
      "aat:300387062",
      "aat:300128207",
      "aat:300387174"
    ],
    "name:fr": "Santa Lucía",
    "name:ru": "Сент-Люсия",
    "name:zh": "圣卢西亚",
    "id": 7004772,
    "name:es": "Sainte-Lucie"
  }
}
