{
  "geometry": {
    "type": "Point",
    "coordinates": [
      -111.0833,
      34.5833
    ]
  },
  "type": "Feature",
  "properties": {
    "hierarchy": [
      "tgn:2223459",
      "tgn:1000001",
      "tgn:7006451",
      "tgn:2000092",
      "tgn:7012149",
      "tgn:7029392"
    ],
    "placetype": [
      "aat:300266640"
    ],
    "id": 2223459,
    "name:xx": "Cart Ridge"
  }
}
