{
  "geometry": {
    "type": "Point",
    "coordinates": [
      -168.8833,
      52.9833
    ]
  },
  "type": "Feature",
  "properties": {
    "hierarchy": [
      "tgn:2312217",
      "tgn:7030516",
      "tgn:7006450",
      "tgn:1000001",
      "tgn:7012149",
      "tgn:7029392"
    ],
    "placetype": [
      "aat:300008791"
    ],
    "id": 2312217,
    "name:xx": "Eider Rock"
  }
}
