{
  "geometry": {
    "type": "Point",
    "coordinates": [
      46.8667,
      -20.8667
    ]
  },
  "type": "Feature",
  "properties": {
    "hierarchy": [
      "tgn:1140896",
      "tgn:7001242",
      "tgn:7000556",
      "tgn:1000173",
      "tgn:7029392"
    ],
    "placetype": [
      "aat:300008347"
    ],
    "id": 1140896,
    "name:xx": "Fenoarivo"
  }
}
