{
  "geometry": {
    "type": "Point",
    "coordinates": [
      -74.2333,
      41.7167
    ]
  },
  "type": "Feature",
  "properties": {
    "hierarchy": [
      "tgn:2517261",
      "tgn:1000001",
      "tgn:7012149",
      "tgn:1002961",
      "tgn:7007568",
      "tgn:7029392"
    ],
    "placetype": [
      "aat:300008680"
    ],
    "id": 2517261,
    "name:xx": "Minnewaska, Lake"
  }
}
