{
  "type": "FeatureCollection",
  "features": [
    {
      "geometry": {
        "type": "Point",
        "coordinates": [
          4.15,
          35.1667
        ]
      },
      "type": "Feature",
      "properties": {
        "hierarchy": [
          "tgn:7032011",
          "tgn:7001242",
          "tgn:7016752",
          "tgn:1000679",
          "tgn:7029392"
        ],
        "placetype": [
          "aat:300008347",
          "aat:300008686",
          "aat:300008375",
          "aat:300387285"
        ],
        "name:en": "Bou Saâda",
        "id": 7032011
      }
    },
    {
      "geometry": {
        "type": "Point",
        "coordinates": [
          12.2166,
          -14.9
        ]
      },
      "type": "Feature",
      "properties": {
        "hierarchy": [
          "tgn:7032012",
          "tgn:7001242",
          "tgn:1000149",
          "tgn:7000392",
          "tgn:7029392"
        ],
        "placetype": [
          "aat:300008347"
        ],
        "name:en": "Mucuio",
        "id": 7032012
      }
    },
    {
      "geometry": {
        "type": "Point",
        "coordinates": [
          2.1333,
          48.6333
        ]
      },
      "type": "Feature",
      "properties": {
        "hierarchy": [
          "tgn:7032015",
          "tgn:1000003",
          "tgn:7012216",
          "tgn:1000070",
          "tgn:7029392"
        ],
        "placetype": [
          "aat:300008347"
        ],
        "name:fr": "Saint-Briac-Sur-Mer",
        "id": 7032015
      }
    },
    {
      "geometry": {
        "type": "Point",
        "coordinates": [
          35.5,
          32.9667
        ]
      },
      "type": "Feature",
      "properties": {
        "hierarchy": [
          "tgn:7032018",
          "tgn:7000249",
          "tgn:1000004",
          "tgn:1000119",
          "tgn:7029392"
        ],
        "placetype": [
          "aat:300008347",
          "aat:300008375"
        ],
        "name:en": "Safad",
        "id": 7032018,
        "name:xx": "Tsefat"
      }
    },
    {
      "geometry": {
        "type": "Point",
        "coordinates": [
          -2.1166,
          48.6333
        ]
      },
      "type": "Feature",
      "properties": {
        "hierarchy": [
          "tgn:7032019",
          "tgn:1000003",
          "tgn:7012216",
          "tgn:1000070",
          "tgn:7029392"
        ],
        "placetype": [
          "aat:300008347"
        ],
        "name:fr": "Saint-Lunaire",
        "id": 7032019
      }
    }
  ]
}
