{
  "geometry": {
    "type": "Point",
    "coordinates": [
      -90.8333,
      38.5667
    ]
  },
  "type": "Feature",
  "properties": {
    "hierarchy": [
      "tgn:2059403",
      "tgn:1000001",
      "tgn:7012149",
      "tgn:7016166",
      "tgn:7007523",
      "tgn:7029392"
    ],
    "placetype": [
      "aat:300387016"
    ],
    "id": 2059403,
    "name:xx": "Klondike"
  }
}
