{
  "geometry": {
    "type": "Point",
    "coordinates": [
      -89.2167,
      33.0667
    ]
  },
  "type": "Feature",
  "properties": {
    "hierarchy": [
      "tgn:2434268",
      "tgn:1000001",
      "tgn:7012149",
      "tgn:2001165",
      "tgn:7007522",
      "tgn:7029392"
    ],
    "placetype": [
      "aat:300006191"
    ],
    "id": 2434268,
    "name:xx": "Kemps Pond"
  }
}
