{
  "geometry": {
    "type": "Point",
    "coordinates": [
      -95.9833,
      31.6667
    ]
  },
  "type": "Feature",
  "properties": {
    "hierarchy": [
      "tgn:2376450",
      "tgn:1000001",
      "tgn:7012149",
      "tgn:1002391",
      "tgn:7007826",
      "tgn:7029392"
    ],
    "placetype": [
      "aat:300006191"
    ],
    "id": 2376450,
    "name:xx": "Harding Lake"
  }
}
