{
  "type": "FeatureCollection",
  "features": [
    {
      "geometry": {
        "type": "Point",
        "coordinates": [
          -1.5,
          50.85
        ]
      },
      "type": "Feature",
      "properties": {
        "hierarchy": [
          "tgn:7465324",
          "tgn:7002445",
          "tgn:1000003",
          "tgn:7008139",
          "tgn:7008591",
          "tgn:7029392"
        ],
        "placetype": [
          "aat:300007783"
        ],
        "name:en": "Beaulieu Road Station",
        "id": 7465324
      }
    },
    {
      "geometry": {
        "type": "Point",
        "coordinates": [
          -1.4,
          50.766667
        ]
      },
      "type": "Feature",
      "properties": {
        "hierarchy": [
          "tgn:7465325",
          "tgn:7002445",
          "tgn:1000003",
          "tgn:7008139",
          "tgn:7008591",
          "tgn:7029392"
        ],
        "placetype": [
          "aat:300008699"
        ],
        "name:en": "Beaulieu River",
        "id": 7465325
      }
    },
    {
      "geometry": {
        "type": "Point",
        "coordinates": [
          -5.233333,
          54.716667
        ]
      },
      "type": "Feature",
      "properties": {
        "hierarchy": [
          "tgn:7465327",
          "tgn:7002444",
          "tgn:7008074",
          "tgn:1000003",
          "tgn:7008591",
          "tgn:7029392"
        ],
        "placetype": [
          "aat:300386938"
        ],
        "name:en": "Beaufort's Dyke",
        "id": 7465327
      }
    },
    {
      "geometry": {
        "type": "Point",
        "coordinates": [
          -4.5,
          57.45
        ]
      },
      "type": "Feature",
      "properties": {
        "hierarchy": [
          "tgn:7465328",
          "tgn:7002444",
          "tgn:1000003",
          "tgn:7008082",
          "tgn:7008591",
          "tgn:7029392"
        ],
        "placetype": [
          "aat:300387502"
        ],
        "name:en": "Beaufort Castle",
        "id": 7465328
      }
    },
    {
      "geometry": {
        "type": "Point",
        "coordinates": [
          -1.25,
          60.55
        ]
      },
      "type": "Feature",
      "properties": {
        "hierarchy": [
          "tgn:7465329",
          "tgn:7002444",
          "tgn:1000003",
          "tgn:7029508",
          "tgn:7008591",
          "tgn:7029392"
        ],
        "placetype": [
          "aat:300386970"
        ],
        "name:en": "Beaufort Bank",
        "id": 7465329
      }
    }
  ]
}
