{
  "geometry": {
    "type": "Point",
    "coordinates": [
      -75.1667,
      41.1667
    ]
  },
  "type": "Feature",
  "properties": {
    "hierarchy": [
      "tgn:2275062",
      "tgn:1000001",
      "tgn:7012149",
      "tgn:1002682",
      "tgn:7007710",
      "tgn:7029392"
    ],
    "placetype": [
      "aat:300266640"
    ],
    "id": 2275062,
    "name:xx": "Dancing Ridge"
  }
}
