{
  "geometry": {
    "type": "Point",
    "coordinates": [
      -111.8167,
      33.45
    ]
  },
  "type": "Feature",
  "properties": {
    "hierarchy": [
      "tgn:2587704",
      "tgn:1000001",
      "tgn:7006451",
      "tgn:7012149",
      "tgn:2000097",
      "tgn:7029392"
    ],
    "placetype": [
      "aat:300006191"
    ],
    "id": 2587704,
    "name:xx": "Pleasant Shadows Subdivision Water Retention Basin"
  }
}
