{
  "geometry": {
    "type": "Point",
    "coordinates": [
      24.75,
      43.683
    ]
  },
  "type": "Feature",
  "properties": {
    "hierarchy": [
      "tgn:1131501",
      "tgn:7593867",
      "tgn:1000003",
      "tgn:7006413",
      "tgn:7029392"
    ],
    "placetype": [
      "aat:300008707"
    ],
    "id": 1131501,
    "name:xx": "Vit"
  }
}
