{
  "type": "FeatureCollection",
  "features": [
    {
      "geometry": {
        "type": "Point",
        "coordinates": [
          11.8,
          52.966667
        ]
      },
      "type": "Feature",
      "properties": {
        "hierarchy": [
          "tgn:7103770",
          "tgn:7000096",
          "tgn:1000003",
          "tgn:7000084",
          "tgn:7029392"
        ],
        "placetype": [
          "aat:300008347"
        ],
        "id": 7103770,
        "name:xx": "Schadebeuster"
      }
    },
    {
      "geometry": {
        "type": "Point",
        "coordinates": [
          10.5,
          51.2
        ]
      },
      "type": "Feature",
      "properties": {
        "hierarchy": [
          "tgn:7103771",
          "tgn:1000003",
          "tgn:7003689",
          "tgn:7000084",
          "tgn:7029392"
        ],
        "placetype": [
          "aat:300008777"
        ],
        "id": 7103771,
        "name:xx": "Schade-Berg"
      }
    },
    {
      "geometry": {
        "type": "Point",
        "coordinates": [
          10.85,
          52.766667
        ]
      },
      "type": "Feature",
      "properties": {
        "hierarchy": [
          "tgn:7103772",
          "tgn:1000003",
          "tgn:7003687",
          "tgn:7000084",
          "tgn:7029392"
        ],
        "placetype": [
          "aat:300387173"
        ],
        "id": 7103772,
        "name:xx": "Schadeberg"
      }
    },
    {
      "geometry": {
        "type": "Point",
        "coordinates": [
          12.483333,
          51.533333
        ]
      },
      "type": "Feature",
      "properties": {
        "hierarchy": [
          "tgn:7103773",
          "tgn:1000003",
          "tgn:7003685",
          "tgn:7000084",
          "tgn:7029392"
        ],
        "placetype": [
          "aat:300008699"
        ],
        "id": 7103773,
        "name:xx": "Schade-Bach"
      }
    },
    {
      "geometry": {
        "type": "Point",
        "coordinates": [
          11.416667,
          50.733333
        ]
      },
      "type": "Feature",
      "properties": {
        "hierarchy": [
          "tgn:7103774",
          "tgn:1000003",
          "tgn:7003689",
          "tgn:7000084",
          "tgn:7029392"
        ],
        "placetype": [
          "aat:300008699"
        ],
        "id": 7103774,
        "name:xx": "Schade-Bach"
      }
    },
    {
      "geometry": {
        "type": "Point",
        "coordinates": [
          10.966667,
          53.75
        ]
      },
      "type": "Feature",
      "properties": {
        "hierarchy": [
          "tgn:7103775",
          "tgn:1000003",
          "tgn:7000094",
          "tgn:7000084",
          "tgn:7029392"
        ],
        "placetype": [
          "aat:300008347"
        ],
        "id": 7103775,
        "name:xx": "Schaddingsdorf"
      }
    },
    {
      "geometry": {
        "type": "Point",
        "coordinates": [
          6.2,
          51.633333
        ]
      },
      "type": "Feature",
      "properties": {
        "hierarchy": [
          "tgn:7103776",
          "tgn:1000003",
          "tgn:7003677",
          "tgn:7000084",
          "tgn:7029392"
        ],
        "placetype": [
          "aat:300000206"
        ],
        "id": 7103776,
        "name:xx": "Schaddenhof"
      }
    },
    {
      "geometry": {
        "type": "Point",
        "coordinates": [
          12.75,
          51.2
        ]
      },
      "type": "Feature",
      "properties": {
        "hierarchy": [
          "tgn:7103777",
          "tgn:1000003",
          "tgn:7003685",
          "tgn:7000084",
          "tgn:7029392"
        ],
        "placetype": [
          "aat:300008347"
        ],
        "id": 7103777,
        "name:xx": "Großbothen-Schaddel"
      }
    },
    {
      "geometry": {
        "type": "Point",
        "coordinates": [
          6.466667,
          51.4
        ]
      },
      "type": "Feature",
      "properties": {
        "hierarchy": [
          "tgn:7103778",
          "tgn:1000003",
          "tgn:7003677",
          "tgn:7000084",
          "tgn:7029392"
        ],
        "placetype": [
          "aat:300055621"
        ],
        "id": 7103778,
        "name:xx": "Schadbruch"
      }
    },
    {
      "geometry": {
        "type": "Point",
        "coordinates": [
          9.683333,
          48.9
        ]
      },
      "type": "Feature",
      "properties": {
        "hierarchy": [
          "tgn:7103779",
          "tgn:7003692",
          "tgn:1000003",
          "tgn:7000084",
          "tgn:7029392"
        ],
        "placetype": [
          "aat:300008347"
        ],
        "id": 7103779,
        "name:xx": "Schadberg"
      }
    }
  ]
}
