{
  "geometry": {
    "type": "Point",
    "coordinates": [
      29.55,
      30.483333
    ]
  },
  "type": "Feature",
  "properties": {
    "hierarchy": [
      "tgn:7520909",
      "tgn:7001242",
      "tgn:7016833",
      "tgn:1001418",
      "tgn:7029392"
    ],
    "placetype": [
      "aat:300008777"
    ],
    "name:en": "Al Khuwaymāt",
    "id": 7520909
  }
}
