{
  "geometry": {
    "type": "Point",
    "coordinates": [
      -119.7333,
      48.7667
    ]
  },
  "type": "Feature",
  "properties": {
    "hierarchy": [
      "tgn:2719520",
      "tgn:1000001",
      "tgn:7012149",
      "tgn:1002742",
      "tgn:7007920",
      "tgn:7029392"
    ],
    "placetype": [
      "aat:300008699"
    ],
    "id": 2719520,
    "name:xx": "Three Forks"
  }
}
