{
  "geometry": {
    "type": "Point",
    "coordinates": [
      -110.7833,
      41.7667
    ]
  },
  "type": "Feature",
  "properties": {
    "hierarchy": [
      "tgn:2335962",
      "tgn:1000001",
      "tgn:7012149",
      "tgn:7007923",
      "tgn:7029392"
    ],
    "placetype": [
      "aat:300266640"
    ],
    "id": 2335962,
    "name:xx": "Fossil Ridge"
  }
}
