{
  "geometry": {
    "type": "Point",
    "coordinates": [
      -106.5167,
      38.1333
    ]
  },
  "type": "Feature",
  "properties": {
    "hierarchy": [
      "tgn:2604329",
      "tgn:1000001",
      "tgn:7012149",
      "tgn:7007158",
      "tgn:2000246",
      "tgn:7029392"
    ],
    "placetype": [
      "aat:300008761"
    ],
    "id": 2604329,
    "name:xx": "Rabbit Canyon"
  }
}
