{
  "type": "FeatureCollection",
  "features": [
    {
      "geometry": {
        "type": "Point",
        "coordinates": [
          -71.35,
          42.1667
        ]
      },
      "type": "Feature",
      "properties": {
        "hierarchy": [
          "tgn:7017830",
          "tgn:1000001",
          "tgn:1002724",
          "tgn:7012149",
          "tgn:7007517",
          "tgn:7029392"
        ],
        "placetype": [
          "aat:300008347"
        ],
        "id": 7017830,
        "name:xx": "Clicquot"
      }
    },
    {
      "geometry": {
        "type": "Point",
        "coordinates": [
          -82,
          37.8333
        ]
      },
      "type": "Feature",
      "properties": {
        "hierarchy": [
          "tgn:7017831",
          "tgn:1000001",
          "tgn:7012149",
          "tgn:2002273",
          "tgn:7013961",
          "tgn:7029392"
        ],
        "placetype": [
          "aat:300008347"
        ],
        "id": 7017831,
        "name:xx": "Mount Gay"
      }
    },
    {
      "geometry": {
        "type": "Point",
        "coordinates": [
          -74.4,
          41.4
        ]
      },
      "type": "Feature",
      "properties": {
        "hierarchy": [
          "tgn:7017833",
          "tgn:1000001",
          "tgn:7012149",
          "tgn:1002751",
          "tgn:7007568",
          "tgn:7029392"
        ],
        "placetype": [
          "aat:300008347"
        ],
        "id": 7017833,
        "name:xx": "New Hampton"
      }
    },
    {
      "geometry": {
        "type": "Point",
        "coordinates": [
          -79.8333,
          39.9167
        ]
      },
      "type": "Feature",
      "properties": {
        "hierarchy": [
          "tgn:7017835",
          "tgn:1000001",
          "tgn:7012149",
          "tgn:7014185",
          "tgn:7007710",
          "tgn:7029392"
        ],
        "placetype": [
          "aat:300008347"
        ],
        "id": 7017835,
        "name:xx": "New Salem"
      }
    },
    {
      "geometry": {
        "type": "Point",
        "coordinates": [
          -79.55,
          40.6
        ]
      },
      "type": "Feature",
      "properties": {
        "hierarchy": [
          "tgn:7017836",
          "tgn:1002153",
          "tgn:1000001",
          "tgn:7012149",
          "tgn:7007710",
          "tgn:7029392"
        ],
        "placetype": [
          "aat:300008347"
        ],
        "id": 7017836,
        "name:xx": "North Vandergrift"
      }
    },
    {
      "geometry": {
        "type": "Point",
        "coordinates": [
          -70.65,
          42.0833
        ]
      },
      "type": "Feature",
      "properties": {
        "hierarchy": [
          "tgn:7017837",
          "tgn:1000001",
          "tgn:7014423",
          "tgn:7012149",
          "tgn:2050079",
          "tgn:7007517",
          "tgn:7029392"
        ],
        "placetype": [
          "aat:300000745"
        ],
        "id": 7017837,
        "name:xx": "Ocean Bluff"
      }
    },
    {
      "geometry": {
        "type": "Point",
        "coordinates": [
          -78.8,
          39.6
        ]
      },
      "type": "Feature",
      "properties": {
        "hierarchy": [
          "tgn:7017839",
          "tgn:2000934",
          "tgn:1000001",
          "tgn:7012149",
          "tgn:7007516",
          "tgn:7029392"
        ],
        "placetype": [
          "aat:300008347"
        ],
        "id": 7017839,
        "name:xx": "Potomac Park"
      }
    }
  ]
}
