{
  "geometry": {
    "type": "Point",
    "coordinates": [
      -82.15,
      39.45
    ]
  },
  "type": "Feature",
  "properties": {
    "hierarchy": [
      "tgn:2165984",
      "tgn:2001610",
      "tgn:1000001",
      "tgn:7012149",
      "tgn:7007706",
      "tgn:7029392"
    ],
    "placetype": [
      "aat:300008699"
    ],
    "id": 2165984,
    "name:xx": "Big Bailey Run"
  }
}
