{
  "geometry": {
    "type": "Point",
    "coordinates": [
      9.2833,
      8.9333
    ]
  },
  "type": "Feature",
  "properties": {
    "hierarchy": [
      "tgn:1092136",
      "tgn:7001242",
      "tgn:1001931",
      "tgn:1000182",
      "tgn:7029392"
    ],
    "placetype": [
      "aat:300008347"
    ],
    "id": 1092136,
    "name:xx": "Kwolla"
  }
}
