{
  "type": "FeatureCollection",
  "features": [
    {
      "geometry": {
        "type": "Point",
        "coordinates": [
          -68.9,
          45.8833
        ]
      },
      "type": "Feature",
      "properties": {
        "hierarchy": [
          "tgn:2633280",
          "tgn:1000001",
          "tgn:7012149",
          "tgn:2000928",
          "tgn:7007515",
          "tgn:7029392"
        ],
        "placetype": [
          "aat:300008798"
        ],
        "id": 2633280,
        "name:xx": "Rum Mountain"
      }
    },
    {
      "geometry": {
        "type": "Point",
        "coordinates": [
          -75.15,
          38.2333
        ]
      },
      "type": "Feature",
      "properties": {
        "hierarchy": [
          "tgn:2633281",
          "tgn:1000001",
          "tgn:1003037",
          "tgn:7012149",
          "tgn:7007516",
          "tgn:7029392"
        ],
        "placetype": [
          "aat:300008850"
        ],
        "id": 2633281,
        "name:xx": "Rum Point"
      }
    },
    {
      "geometry": {
        "type": "Point",
        "coordinates": [
          -77.1833,
          38.55
        ]
      },
      "type": "Feature",
      "properties": {
        "hierarchy": [
          "tgn:2633282",
          "tgn:7016100",
          "tgn:1000001",
          "tgn:7012149",
          "tgn:7007516",
          "tgn:7029392"
        ],
        "placetype": [
          "aat:300008850"
        ],
        "id": 2633282,
        "name:xx": "Rum Point"
      }
    },
    {
      "geometry": {
        "type": "Point",
        "coordinates": [
          -71.2667,
          43.5333
        ]
      },
      "type": "Feature",
      "properties": {
        "hierarchy": [
          "tgn:2633283",
          "tgn:2001422",
          "tgn:1000001",
          "tgn:7012149",
          "tgn:7007564",
          "tgn:7029392"
        ],
        "placetype": [
          "aat:300008850"
        ],
        "id": 2633283,
        "name:xx": "Rum Point"
      }
    },
    {
      "geometry": {
        "type": "Point",
        "coordinates": [
          -74.4167,
          39.3833
        ]
      },
      "type": "Feature",
      "properties": {
        "hierarchy": [
          "tgn:2633284",
          "tgn:1002157",
          "tgn:1000001",
          "tgn:7012149",
          "tgn:7007565",
          "tgn:7029392"
        ],
        "placetype": [
          "aat:300008850"
        ],
        "id": 2633284,
        "name:xx": "Rum Point"
      }
    },
    {
      "geometry": {
        "type": "Point",
        "coordinates": [
          -76,
          37.8667
        ]
      },
      "type": "Feature",
      "properties": {
        "hierarchy": [
          "tgn:2633285",
          "tgn:1000001",
          "tgn:7012149",
          "tgn:1002548",
          "tgn:7007919",
          "tgn:7029392"
        ],
        "placetype": [
          "aat:300008850"
        ],
        "id": 2633285,
        "name:xx": "Rum Point"
      }
    },
    {
      "geometry": {
        "type": "Point",
        "coordinates": [
          -85.4167,
          30.8833
        ]
      },
      "type": "Feature",
      "properties": {
        "hierarchy": [
          "tgn:2633286",
          "tgn:1000001",
          "tgn:2000273",
          "tgn:7012149",
          "tgn:7007240",
          "tgn:7029392"
        ],
        "placetype": [
          "aat:300008905"
        ],
        "id": 2633286,
        "name:xx": "Rum Pond"
      }
    },
    {
      "geometry": {
        "type": "Point",
        "coordinates": [
          -68.8833,
          45.8333
        ]
      },
      "type": "Feature",
      "properties": {
        "hierarchy": [
          "tgn:2633287",
          "tgn:1000001",
          "tgn:7012149",
          "tgn:2000928",
          "tgn:7007515",
          "tgn:7029392"
        ],
        "placetype": [
          "aat:300008680"
        ],
        "id": 2633287,
        "name:xx": "Rum Pond"
      }
    },
    {
      "geometry": {
        "type": "Point",
        "coordinates": [
          -121.1333,
          42.4
        ]
      },
      "type": "Feature",
      "properties": {
        "hierarchy": [
          "tgn:2633288",
          "tgn:1000001",
          "tgn:7012149",
          "tgn:2001714",
          "tgn:7007708",
          "tgn:7029392"
        ],
        "placetype": [
          "aat:300006191"
        ],
        "id": 2633288,
        "name:xx": "Rum Pond"
      }
    },
    {
      "geometry": {
        "type": "Point",
        "coordinates": [
          -71.5167,
          41.4167
        ]
      },
      "type": "Feature",
      "properties": {
        "hierarchy": [
          "tgn:2633289",
          "tgn:1002996",
          "tgn:1000001",
          "tgn:7012149",
          "tgn:7007711",
          "tgn:7029392"
        ],
        "placetype": [
          "aat:300008680"
        ],
        "id": 2633289,
        "name:xx": "Rum Pond"
      }
    }
  ]
}
