{
  "geometry": {
    "type": "Point",
    "coordinates": [
      -13.6667,
      9.9167
    ]
  },
  "type": "Feature",
  "properties": {
    "hierarchy": [
      "tgn:1125701",
      "tgn:7001242",
      "tgn:1000167",
      "tgn:7029392"
    ],
    "placetype": [
      "aat:300008707"
    ],
    "id": 1125701,
    "name:xx": "Konkouré"
  }
}
