{
  "geometry": {
    "type": "Point",
    "coordinates": [
      -86.7833,
      39.8667
    ]
  },
  "type": "Feature",
  "properties": {
    "hierarchy": [
      "tgn:2525313",
      "tgn:1000001",
      "tgn:7012149",
      "tgn:2000547",
      "tgn:7007252",
      "tgn:7029392"
    ],
    "placetype": [
      "aat:300008680"
    ],
    "id": 2525313,
    "name:xx": "Morrison Lake"
  }
}
