{
  "geometry": {
    "type": "Point",
    "coordinates": [
      -71.25,
      42.6833
    ]
  },
  "type": "Feature",
  "properties": {
    "hierarchy": [
      "tgn:2366209",
      "tgn:1000001",
      "tgn:7012149",
      "tgn:7007517",
      "tgn:7029392"
    ],
    "placetype": [
      "aat:300008699"
    ],
    "id": 2366209,
    "name:xx": "Griffin Brook"
  }
}
