{
  "geometry": {
    "type": "Point",
    "coordinates": [
      -101.3333,
      45.9167
    ]
  },
  "type": "Feature",
  "properties": {
    "hierarchy": [
      "tgn:2501709",
      "tgn:1000001",
      "tgn:2001785",
      "tgn:7012149",
      "tgn:7007713",
      "tgn:7029392"
    ],
    "placetype": [
      "aat:300006191"
    ],
    "id": 2501709,
    "name:xx": "McIntosh Lake"
  }
}
