{
  "geometry": {
    "type": "Point",
    "coordinates": [
      -88.5833,
      41.8667
    ]
  },
  "type": "Feature",
  "properties": {
    "hierarchy": [
      "tgn:2304811",
      "tgn:1000001",
      "tgn:7012149",
      "tgn:1002531",
      "tgn:7007251",
      "tgn:7029392"
    ],
    "placetype": [
      "aat:300008706"
    ],
    "id": 2304811,
    "name:xx": "East Branch Big Rock Creek"
  }
}
