{
  "geometry": {
    "type": "Point",
    "coordinates": [
      -68.6833,
      45.7833
    ]
  },
  "type": "Feature",
  "properties": {
    "hierarchy": [
      "tgn:2458257",
      "tgn:1000001",
      "tgn:7012149",
      "tgn:2000927",
      "tgn:7007515",
      "tgn:7029392"
    ],
    "placetype": [
      "aat:300008699"
    ],
    "id": 2458257,
    "name:xx": "Little Mud Brook"
  }
}
