{
  "geometry": {
    "type": "Point",
    "coordinates": [
      -79.2833,
      38.8333
    ]
  },
  "type": "Feature",
  "properties": {
    "hierarchy": [
      "tgn:2672324",
      "tgn:1000001",
      "tgn:7012149",
      "tgn:7014398",
      "tgn:7013961",
      "tgn:7029392"
    ],
    "placetype": [
      "aat:300008746"
    ],
    "id": 2672324,
    "name:xx": "Smoke Hole Cave"
  }
}
