{
  "type": "FeatureCollection",
  "features": [
    {
      "geometry": {
        "type": "Point",
        "coordinates": [
          175.983333,
          -39.783333
        ]
      },
      "type": "Feature",
      "properties": {
        "hierarchy": [
          "tgn:7512700",
          "tgn:1008380",
          "tgn:7520093",
          "tgn:1000226",
          "tgn:1000006",
          "tgn:7029392"
        ],
        "placetype": [
          "aat:300008699"
        ],
        "name:en": "Hikurangi Stream",
        "id": 7512700
      }
    },
    {
      "geometry": {
        "type": "Point",
        "coordinates": [
          174.033333,
          -35.683333
        ]
      },
      "type": "Feature",
      "properties": {
        "hierarchy": [
          "tgn:7512701",
          "tgn:1008380",
          "tgn:7000507",
          "tgn:1000226",
          "tgn:1000006",
          "tgn:7029392"
        ],
        "placetype": [
          "aat:300008699"
        ],
        "name:en": "Hikurangi River",
        "id": 7512701
      }
    },
    {
      "geometry": {
        "type": "Point",
        "coordinates": [
          176.083333,
          -39.8
        ]
      },
      "type": "Feature",
      "properties": {
        "hierarchy": [
          "tgn:7512702",
          "tgn:1008380",
          "tgn:7520093",
          "tgn:1000226",
          "tgn:1000006",
          "tgn:7029392"
        ],
        "placetype": [
          "aat:300008795"
        ],
        "name:en": "Hikurangi",
        "id": 7512702
      }
    },
    {
      "geometry": {
        "type": "Point",
        "coordinates": [
          176.85,
          -38.35
        ]
      },
      "type": "Feature",
      "properties": {
        "hierarchy": [
          "tgn:7512703",
          "tgn:7000509",
          "tgn:1008380",
          "tgn:1000226",
          "tgn:1000006",
          "tgn:7029392"
        ],
        "placetype": [
          "aat:300008795"
        ],
        "name:en": "Hikurangi",
        "id": 7512703
      }
    },
    {
      "geometry": {
        "type": "Point",
        "coordinates": [
          178.216667,
          -38.283333
        ]
      },
      "type": "Feature",
      "properties": {
        "hierarchy": [
          "tgn:7512704",
          "tgn:7520092",
          "tgn:1008380",
          "tgn:1000226",
          "tgn:1000006",
          "tgn:7029392"
        ],
        "placetype": [
          "aat:300008795"
        ],
        "name:en": "Hikurangi",
        "id": 7512704
      }
    },
    {
      "geometry": {
        "type": "Point",
        "coordinates": [
          175.9,
          -37.483333
        ]
      },
      "type": "Feature",
      "properties": {
        "hierarchy": [
          "tgn:7512706",
          "tgn:1008380",
          "tgn:1000226",
          "tgn:7018426",
          "tgn:1000006",
          "tgn:7029392"
        ],
        "placetype": [
          "aat:300008795"
        ],
        "name:en": "Hikurangi, Mount",
        "id": 7512706
      }
    },
    {
      "geometry": {
        "type": "Point",
        "coordinates": [
          174.283333,
          -35.6
        ]
      },
      "type": "Feature",
      "properties": {
        "hierarchy": [
          "tgn:7512707",
          "tgn:1008380",
          "tgn:7000507",
          "tgn:1000226",
          "tgn:1000006",
          "tgn:7029392"
        ],
        "placetype": [
          "aat:300008795"
        ],
        "name:en": "Hikurangi",
        "id": 7512707
      }
    },
    {
      "geometry": {
        "type": "Point",
        "coordinates": [
          173.916667,
          -35.533333
        ]
      },
      "type": "Feature",
      "properties": {
        "hierarchy": [
          "tgn:7512708",
          "tgn:1008380",
          "tgn:7000507",
          "tgn:1000226",
          "tgn:1000006",
          "tgn:7029392"
        ],
        "placetype": [
          "aat:300008795"
        ],
        "name:en": "Hikurangi",
        "id": 7512708
      }
    },
    {
      "geometry": {
        "type": "Point",
        "coordinates": [
          175.1,
          -38.1
        ]
      },
      "type": "Feature",
      "properties": {
        "hierarchy": [
          "tgn:7512709",
          "tgn:1008380",
          "tgn:1000226",
          "tgn:7018426",
          "tgn:1000006",
          "tgn:7029392"
        ],
        "placetype": [
          "aat:300008777"
        ],
        "name:en": "Hikurangi",
        "id": 7512709
      }
    }
  ]
}
