{
  "geometry": {
    "type": "Point",
    "coordinates": [
      -81.2333,
      29.45
    ]
  },
  "type": "Feature",
  "properties": {
    "hierarchy": [
      "tgn:2175195",
      "tgn:1000001",
      "tgn:2000266",
      "tgn:7012149",
      "tgn:7007240",
      "tgn:7029392"
    ],
    "placetype": [
      "aat:300008905"
    ],
    "id": 2175195,
    "name:xx": "Black Branch Swamp"
  }
}
