{
  "geometry": {
    "type": "Point",
    "coordinates": [
      27.780422,
      28.599022
    ]
  },
  "type": "Feature",
  "properties": {
    "hierarchy": [
      "tgn:7528443",
      "tgn:7001242",
      "tgn:7016833",
      "tgn:7029392"
    ],
    "placetype": [
      "aat:300008777"
    ],
    "name:en": "Shūshat al Khādim",
    "id": 7528443
  }
}
