{
  "geometry": {
    "type": "Point",
    "coordinates": [
      87.431,
      21.691
    ]
  },
  "type": "Feature",
  "properties": {
    "hierarchy": [
      "tgn:1075113",
      "tgn:1000004",
      "tgn:7000198",
      "tgn:7016694",
      "tgn:7029392"
    ],
    "placetype": [
      "aat:300008347"
    ],
    "name:en": "Dehūrda",
    "id": 1075113
  }
}
