{
  "geometry": {
    "type": "Point",
    "coordinates": [
      89.7167,
      24.45
    ]
  },
  "type": "Feature",
  "properties": {
    "hierarchy": [
      "tgn:1065945",
      "tgn:1000004",
      "tgn:7000191",
      "tgn:1000105",
      "tgn:7029392"
    ],
    "placetype": [
      "aat:300008347",
      "aat:300387316",
      "aat:300008375",
      "aat:300120599"
    ],
    "id": 1065945,
    "name:xx": "Sirājganj"
  }
}
