{
  "geometry": {
    "type": "Point",
    "coordinates": [
      -81.45,
      37.8167
    ]
  },
  "type": "Feature",
  "properties": {
    "hierarchy": [
      "tgn:2572523",
      "tgn:1000001",
      "tgn:7012149",
      "tgn:2002290",
      "tgn:7013961",
      "tgn:7029392"
    ],
    "placetype": [
      "aat:300266640"
    ],
    "id": 2572523,
    "name:xx": "Peachtree Ridge"
  }
}
