{
  "geometry": {
    "type": "Point",
    "coordinates": [
      -96.4667,
      33.75
    ]
  },
  "type": "Feature",
  "properties": {
    "hierarchy": [
      "tgn:2671134",
      "tgn:1000001",
      "tgn:7012149",
      "tgn:2001993",
      "tgn:7007826",
      "tgn:7029392"
    ],
    "placetype": [
      "aat:300008706"
    ],
    "id": 2671134,
    "name:xx": "Smith Creek"
  }
}
