{
  "geometry": {
    "type": "Point",
    "coordinates": [
      -112.7167,
      48.55
    ]
  },
  "type": "Feature",
  "properties": {
    "hierarchy": [
      "tgn:2368211",
      "tgn:1000001",
      "tgn:7012149",
      "tgn:2001277",
      "tgn:7007524",
      "tgn:7029392"
    ],
    "placetype": [
      "aat:300008680"
    ],
    "id": 2368211,
    "name:xx": "Guardipee Lake"
  }
}
