{
  "geometry": {
    "type": "Point",
    "coordinates": [
      74.485146,
      26.679043
    ]
  },
  "type": "Feature",
  "properties": {
    "hierarchy": [
      "tgn:7552336",
      "tgn:1000004",
      "tgn:7000198",
      "tgn:7016788",
      "tgn:7029392"
    ],
    "placetype": [
      "aat:300008347"
    ],
    "name:en": "Mori Kalān",
    "id": 7552336
  }
}
