{
  "geometry": {
    "type": "Point",
    "coordinates": [
      -99.6167,
      30.7833
    ]
  },
  "type": "Feature",
  "properties": {
    "hierarchy": [
      "tgn:2338965",
      "tgn:1000001",
      "tgn:7012149",
      "tgn:2002040",
      "tgn:7007826",
      "tgn:7029392"
    ],
    "placetype": [
      "aat:300008761"
    ],
    "id": 2338965,
    "name:xx": "Franklin Draw"
  }
}
