{
  "geometry": {
    "type": "Point",
    "coordinates": [
      44.4833,
      51.5333
    ]
  },
  "type": "Feature",
  "properties": {
    "hierarchy": [
      "tgn:1137578",
      "tgn:1000004",
      "tgn:1003408",
      "tgn:7018214",
      "tgn:7002435",
      "tgn:7029392"
    ],
    "placetype": [
      "aat:300008347"
    ],
    "id": 1137578,
    "name:xx": "Kalininsk"
  }
}
