{
  "geometry": {
    "type": "Point",
    "coordinates": [
      -151.0167,
      62.55
    ]
  },
  "type": "Feature",
  "properties": {
    "hierarchy": [
      "tgn:2322506",
      "tgn:7006450",
      "tgn:1000001",
      "tgn:2124053",
      "tgn:7012149",
      "tgn:7029392"
    ],
    "placetype": [
      "aat:300008706"
    ],
    "id": 2322506,
    "name:xx": "Falls Creek"
  }
}
