{
  "geometry": {
    "type": "Point",
    "coordinates": [
      -89.8167,
      43.0167
    ]
  },
  "type": "Feature",
  "properties": {
    "hierarchy": [
      "tgn:2588052",
      "tgn:1000001",
      "tgn:1002316",
      "tgn:7012149",
      "tgn:7007922",
      "tgn:7029392"
    ],
    "placetype": [
      "aat:300008761"
    ],
    "id": 2588052,
    "name:xx": "Pleasure Valley"
  }
}
