{
  "type": "FeatureCollection",
  "features": [
    {
      "geometry": {
        "type": "Point",
        "coordinates": [
          -105.45,
          20.783333
        ]
      },
      "type": "Feature",
      "properties": {
        "hierarchy": [
          "tgn:7368550",
          "tgn:1000001",
          "tgn:1001906",
          "tgn:7005560",
          "tgn:7029392"
        ],
        "placetype": [
          "aat:300008347"
        ],
        "id": 7368550,
        "name:xx": "Higuera Blanca"
      }
    },
    {
      "geometry": {
        "type": "Point",
        "coordinates": [
          -109.65,
          27.4
        ]
      },
      "type": "Feature",
      "properties": {
        "hierarchy": [
          "tgn:7368552",
          "tgn:1000001",
          "tgn:1001960",
          "tgn:7005560",
          "tgn:7029392"
        ],
        "placetype": [
          "aat:300008699"
        ],
        "id": 7368552,
        "name:xx": "Higuera, Río"
      }
    },
    {
      "geometry": {
        "type": "Point",
        "coordinates": [
          -110.433333,
          29.8
        ]
      },
      "type": "Feature",
      "properties": {
        "hierarchy": [
          "tgn:7368553",
          "tgn:1000001",
          "tgn:1001960",
          "tgn:7005560",
          "tgn:7029392"
        ],
        "placetype": [
          "aat:300000241"
        ],
        "id": 7368553,
        "name:xx": "Rancho Higuera"
      }
    },
    {
      "geometry": {
        "type": "Point",
        "coordinates": [
          -109.5,
          28.1
        ]
      },
      "type": "Feature",
      "properties": {
        "hierarchy": [
          "tgn:7368554",
          "tgn:1000001",
          "tgn:1001960",
          "tgn:7005560",
          "tgn:7029392"
        ],
        "placetype": [
          "aat:300000241"
        ],
        "id": 7368554,
        "name:xx": "Rancho Higuera"
      }
    },
    {
      "geometry": {
        "type": "Point",
        "coordinates": [
          -108.403333,
          26.653889
        ]
      },
      "type": "Feature",
      "properties": {
        "hierarchy": [
          "tgn:7368555",
          "tgn:1000001",
          "tgn:7005595",
          "tgn:7005560",
          "tgn:7029392"
        ],
        "placetype": [
          "aat:300008795"
        ],
        "id": 7368555,
        "name:xx": "Higuera, Cerro la"
      }
    },
    {
      "geometry": {
        "type": "Point",
        "coordinates": [
          -97.166667,
          20.65
        ]
      },
      "type": "Feature",
      "properties": {
        "hierarchy": [
          "tgn:7368556",
          "tgn:1000001",
          "tgn:7005599",
          "tgn:7005560",
          "tgn:7029392"
        ],
        "placetype": [
          "aat:300387057"
        ],
        "id": 7368556,
        "name:xx": "Higuera, Boca"
      }
    },
    {
      "geometry": {
        "type": "Point",
        "coordinates": [
          -103.466667,
          19.433333
        ]
      },
      "type": "Feature",
      "properties": {
        "hierarchy": [
          "tgn:7368557",
          "tgn:7005586",
          "tgn:1000001",
          "tgn:7005560",
          "tgn:7029392"
        ],
        "placetype": [
          "aat:300007783"
        ],
        "id": 7368557,
        "name:xx": "Higuera"
      }
    },
    {
      "geometry": {
        "type": "Point",
        "coordinates": [
          -109.45,
          28.116667
        ]
      },
      "type": "Feature",
      "properties": {
        "hierarchy": [
          "tgn:7368558",
          "tgn:1000001",
          "tgn:1001960",
          "tgn:7005560",
          "tgn:7029392"
        ],
        "placetype": [
          "aat:300008347"
        ],
        "id": 7368558,
        "name:xx": "Higuera"
      }
    },
    {
      "geometry": {
        "type": "Point",
        "coordinates": [
          -107.127222,
          24.775833
        ]
      },
      "type": "Feature",
      "properties": {
        "hierarchy": [
          "tgn:7368559",
          "tgn:1000001",
          "tgn:7005595",
          "tgn:7005560",
          "tgn:7029392"
        ],
        "placetype": [
          "aat:300008347"
        ],
        "id": 7368559,
        "name:xx": "Higuera"
      }
    }
  ]
}
