{
  "geometry": {
    "type": "Point",
    "coordinates": [
      31.350396,
      30.098516
    ]
  },
  "type": "Feature",
  "properties": {
    "hierarchy": [
      "tgn:7532434",
      "tgn:7001242",
      "tgn:7016833",
      "tgn:1001091",
      "tgn:7029392"
    ],
    "placetype": [
      "aat:300006676"
    ],
    "id": 7532434,
    "name:xx": "Mustashfá al Jalā' lil 'Ā'ilāt"
  }
}
