{
  "type": "FeatureCollection",
  "features": [
    {
      "geometry": {
        "type": "Point",
        "coordinates": [
          -68.2,
          44.75
        ]
      },
      "type": "Feature",
      "properties": {
        "hierarchy": [
          "tgn:2683770",
          "tgn:1000001",
          "tgn:2000922",
          "tgn:7012149",
          "tgn:7007515",
          "tgn:7029392"
        ],
        "placetype": [
          "aat:300008680"
        ],
        "id": 2683770,
        "name:xx": "Spectacle Pond"
      }
    },
    {
      "geometry": {
        "type": "Point",
        "coordinates": [
          -68.7333,
          46.5333
        ]
      },
      "type": "Feature",
      "properties": {
        "hierarchy": [
          "tgn:2683771",
          "tgn:2000919",
          "tgn:1000001",
          "tgn:7012149",
          "tgn:7007515",
          "tgn:7029392"
        ],
        "placetype": [
          "aat:300008680"
        ],
        "id": 2683771,
        "name:xx": "Spectacle Pond"
      }
    },
    {
      "geometry": {
        "type": "Point",
        "coordinates": [
          -71.6833,
          42.5
        ]
      },
      "type": "Feature",
      "properties": {
        "hierarchy": [
          "tgn:2683772",
          "tgn:1000001",
          "tgn:7012149",
          "tgn:1003038",
          "tgn:7007517",
          "tgn:7029392"
        ],
        "placetype": [
          "aat:300008680"
        ],
        "id": 2683772,
        "name:xx": "Spectacle Pond"
      }
    },
    {
      "geometry": {
        "type": "Point",
        "coordinates": [
          -71.5167,
          42.55
        ]
      },
      "type": "Feature",
      "properties": {
        "hierarchy": [
          "tgn:2683773",
          "tgn:1000001",
          "tgn:7012149",
          "tgn:7007517",
          "tgn:7029392"
        ],
        "placetype": [
          "aat:300008680"
        ],
        "id": 2683773,
        "name:xx": "Spectacle Pond"
      }
    },
    {
      "geometry": {
        "type": "Point",
        "coordinates": [
          -70.65,
          41.7667
        ]
      },
      "type": "Feature",
      "properties": {
        "hierarchy": [
          "tgn:2683774",
          "tgn:1000001",
          "tgn:7014423",
          "tgn:7012149",
          "tgn:7007517",
          "tgn:7029392"
        ],
        "placetype": [
          "aat:300008680"
        ],
        "id": 2683774,
        "name:xx": "Spectacle Pond"
      }
    },
    {
      "geometry": {
        "type": "Point",
        "coordinates": [
          -70.5833,
          41.5833
        ]
      },
      "type": "Feature",
      "properties": {
        "hierarchy": [
          "tgn:2683775",
          "tgn:1002165",
          "tgn:1000001",
          "tgn:7012149",
          "tgn:7007517",
          "tgn:7029392"
        ],
        "placetype": [
          "aat:300008680"
        ],
        "id": 2683775,
        "name:xx": "Spectacle Pond"
      }
    },
    {
      "geometry": {
        "type": "Point",
        "coordinates": [
          -72.4167,
          42.1333
        ]
      },
      "type": "Feature",
      "properties": {
        "hierarchy": [
          "tgn:2683776",
          "tgn:1000001",
          "tgn:7019982",
          "tgn:7012149",
          "tgn:7007517",
          "tgn:7029392"
        ],
        "placetype": [
          "aat:300008680"
        ],
        "id": 2683776,
        "name:xx": "Spectacle Pond"
      }
    },
    {
      "geometry": {
        "type": "Point",
        "coordinates": [
          -72.1833,
          42.9167
        ]
      },
      "type": "Feature",
      "properties": {
        "hierarchy": [
          "tgn:2683777",
          "tgn:7019618",
          "tgn:1000001",
          "tgn:7012149",
          "tgn:7007564",
          "tgn:7029392"
        ],
        "placetype": [
          "aat:300008680"
        ],
        "id": 2683777,
        "name:xx": "Spectacle Pond"
      }
    },
    {
      "geometry": {
        "type": "Point",
        "coordinates": [
          -72.0167,
          43.6
        ]
      },
      "type": "Feature",
      "properties": {
        "hierarchy": [
          "tgn:2683778",
          "tgn:1000001",
          "tgn:2001424",
          "tgn:7012149",
          "tgn:7007564",
          "tgn:7029392"
        ],
        "placetype": [
          "aat:300008680"
        ],
        "id": 2683778,
        "name:xx": "Spectacle Pond"
      }
    },
    {
      "geometry": {
        "type": "Point",
        "coordinates": [
          -71.6167,
          43.5833
        ]
      },
      "type": "Feature",
      "properties": {
        "hierarchy": [
          "tgn:2683779",
          "tgn:2001422",
          "tgn:1000001",
          "tgn:7012149",
          "tgn:7007564",
          "tgn:7029392"
        ],
        "placetype": [
          "aat:300008680"
        ],
        "id": 2683779,
        "name:xx": "Spectacle Pond"
      }
    }
  ]
}
