{
  "geometry": {
    "type": "Point",
    "coordinates": [
      -94.0167,
      40.2833
    ]
  },
  "type": "Feature",
  "properties": {
    "hierarchy": [
      "tgn:2165001",
      "tgn:1000001",
      "tgn:7012149",
      "tgn:2001201",
      "tgn:7007523",
      "tgn:7029392"
    ],
    "placetype": [
      "aat:300006191"
    ],
    "id": 2165001,
    "name:xx": "Bethany Reservoir"
  }
}
