{
  "geometry": {
    "type": "Point",
    "coordinates": [
      -78.7667,
      39.7167
    ]
  },
  "type": "Feature",
  "properties": {
    "hierarchy": [
      "tgn:2046988",
      "tgn:2000934",
      "tgn:1000001",
      "tgn:7012149",
      "tgn:7007516",
      "tgn:7029392"
    ],
    "placetype": [
      "aat:300008347"
    ],
    "id": 2046988,
    "name:xx": "Ellerslie"
  }
}
