{
  "type": "FeatureCollection",
  "features": [
    {
      "geometry": {
        "type": "Point",
        "coordinates": [
          -110.9667,
          34.4167
        ]
      },
      "type": "Feature",
      "properties": {
        "hierarchy": [
          "tgn:2378790",
          "tgn:1000001",
          "tgn:7006451",
          "tgn:2000092",
          "tgn:7012149",
          "tgn:7029392"
        ],
        "placetype": [
          "aat:300008761"
        ],
        "id": 2378790,
        "name:xx": "Hart Canyon"
      }
    },
    {
      "geometry": {
        "type": "Point",
        "coordinates": [
          -118.3,
          35.3667
        ]
      },
      "type": "Feature",
      "properties": {
        "hierarchy": [
          "tgn:2378791",
          "tgn:1000001",
          "tgn:7012149",
          "tgn:1002545",
          "tgn:7007157",
          "tgn:7029392"
        ],
        "placetype": [
          "aat:300008761"
        ],
        "id": 2378791,
        "name:xx": "Hart Canyon"
      }
    },
    {
      "geometry": {
        "type": "Point",
        "coordinates": [
          -103.6667,
          37.0833
        ]
      },
      "type": "Feature",
      "properties": {
        "hierarchy": [
          "tgn:2378792",
          "tgn:1000001",
          "tgn:7012149",
          "tgn:2000227",
          "tgn:7007158",
          "tgn:7029392"
        ],
        "placetype": [
          "aat:300008761"
        ],
        "id": 2378792,
        "name:xx": "Hart Canyon"
      }
    },
    {
      "geometry": {
        "type": "Point",
        "coordinates": [
          -106.6667,
          36.4333
        ]
      },
      "type": "Feature",
      "properties": {
        "hierarchy": [
          "tgn:2378793",
          "tgn:1000001",
          "tgn:7012149",
          "tgn:2001449",
          "tgn:7007566",
          "tgn:7029392"
        ],
        "placetype": [
          "aat:300008761"
        ],
        "id": 2378793,
        "name:xx": "Hart Canyon"
      }
    },
    {
      "geometry": {
        "type": "Point",
        "coordinates": [
          -105.0833,
          36.8
        ]
      },
      "type": "Feature",
      "properties": {
        "hierarchy": [
          "tgn:2378794",
          "tgn:1000001",
          "tgn:2001432",
          "tgn:7012149",
          "tgn:7007566",
          "tgn:7029392"
        ],
        "placetype": [
          "aat:300008761"
        ],
        "id": 2378794,
        "name:xx": "Hart Canyon"
      }
    },
    {
      "geometry": {
        "type": "Point",
        "coordinates": [
          -104.1667,
          32.8167
        ]
      },
      "type": "Feature",
      "properties": {
        "hierarchy": [
          "tgn:2378795",
          "tgn:1000001",
          "tgn:2001436",
          "tgn:7012149",
          "tgn:7007566",
          "tgn:7029392"
        ],
        "placetype": [
          "aat:300008761"
        ],
        "id": 2378795,
        "name:xx": "Hart Canyon"
      }
    },
    {
      "geometry": {
        "type": "Point",
        "coordinates": [
          -107.8167,
          36.85
        ]
      },
      "type": "Feature",
      "properties": {
        "hierarchy": [
          "tgn:2378796",
          "tgn:1000001",
          "tgn:7012149",
          "tgn:2001452",
          "tgn:7007566",
          "tgn:7029392"
        ],
        "placetype": [
          "aat:300008761"
        ],
        "id": 2378796,
        "name:xx": "Hart Canyon"
      }
    },
    {
      "geometry": {
        "type": "Point",
        "coordinates": [
          -119.75,
          42.4333
        ]
      },
      "type": "Feature",
      "properties": {
        "hierarchy": [
          "tgn:2378797",
          "tgn:1000001",
          "tgn:7012149",
          "tgn:2001715",
          "tgn:7007708",
          "tgn:7029392"
        ],
        "placetype": [
          "aat:300008761"
        ],
        "id": 2378797,
        "name:xx": "Hart Canyon"
      }
    },
    {
      "geometry": {
        "type": "Point",
        "coordinates": [
          -84.8333,
          33.9167
        ]
      },
      "type": "Feature",
      "properties": {
        "hierarchy": [
          "tgn:2378798",
          "tgn:1000001",
          "tgn:7012149",
          "tgn:2000401",
          "tgn:7007248",
          "tgn:7029392"
        ],
        "placetype": [
          "aat:300008347"
        ],
        "id": 2378798,
        "name:xx": "Hart Circle"
      }
    },
    {
      "geometry": {
        "type": "Point",
        "coordinates": [
          -106.7,
          33.8667
        ]
      },
      "type": "Feature",
      "properties": {
        "hierarchy": [
          "tgn:2378799",
          "tgn:1000001",
          "tgn:7012149",
          "tgn:2001456",
          "tgn:7007566",
          "tgn:7029392"
        ],
        "placetype": [
          "aat:300000390"
        ],
        "id": 2378799,
        "name:xx": "Hart Coal Mine"
      }
    }
  ]
}
