{
  "geometry": {
    "type": "Point",
    "coordinates": [
      -83.95,
      34.0167
    ]
  },
  "type": "Feature",
  "properties": {
    "hierarchy": [
      "tgn:2269558",
      "tgn:1000001",
      "tgn:7012149",
      "tgn:2000358",
      "tgn:7007248",
      "tgn:7029392"
    ],
    "placetype": [
      "aat:300006191"
    ],
    "id": 2269558,
    "name:xx": "Crowe Lake"
  }
}
