{
  "geometry": {
    "type": "Point",
    "coordinates": [
      -109.9167,
      38.1167
    ]
  },
  "type": "Feature",
  "properties": {
    "hierarchy": [
      "tgn:2760556",
      "tgn:1000001",
      "tgn:7012149",
      "tgn:2002119",
      "tgn:7007827",
      "tgn:7029392"
    ],
    "placetype": [
      "aat:300008761"
    ],
    "id": 2760556,
    "name:xx": "West Fork Twin Canyon"
  }
}
