{
  "type": "FeatureCollection",
  "features": [
    {
      "geometry": {
        "type": "Point",
        "coordinates": [
          -79.85,
          36.6
        ]
      },
      "type": "Feature",
      "properties": {
        "hierarchy": [
          "tgn:2112920",
          "tgn:1000001",
          "tgn:7012149",
          "tgn:2002167",
          "tgn:7007919",
          "tgn:7029392"
        ],
        "placetype": [
          "aat:300008347"
        ],
        "id": 2112920,
        "name:xx": "Marrowbone Heights"
      }
    },
    {
      "geometry": {
        "type": "Point",
        "coordinates": [
          -77.85,
          38.85
        ]
      },
      "type": "Feature",
      "properties": {
        "hierarchy": [
          "tgn:2112921",
          "tgn:1000001",
          "tgn:7012149",
          "tgn:1002368",
          "tgn:7007919",
          "tgn:7029392"
        ],
        "placetype": [
          "aat:300008347"
        ],
        "id": 2112921,
        "name:xx": "Marshall"
      }
    },
    {
      "geometry": {
        "type": "Point",
        "coordinates": [
          -76.4833,
          37.2667
        ]
      },
      "type": "Feature",
      "properties": {
        "hierarchy": [
          "tgn:2112922",
          "tgn:1000001",
          "tgn:7012149",
          "tgn:1002411",
          "tgn:7007919",
          "tgn:7029392"
        ],
        "placetype": [
          "aat:300008347"
        ],
        "id": 2112922,
        "name:xx": "Marshall Heights"
      }
    },
    {
      "geometry": {
        "type": "Point",
        "coordinates": [
          -82.2833,
          37.1833
        ]
      },
      "type": "Feature",
      "properties": {
        "hierarchy": [
          "tgn:2112923",
          "tgn:1000001",
          "tgn:7012149",
          "tgn:2002157",
          "tgn:7007919",
          "tgn:7029392"
        ],
        "placetype": [
          "aat:300008347",
          "aat:300387210"
        ],
        "id": 2112923,
        "name:xx": "Martha Gap"
      }
    },
    {
      "geometry": {
        "type": "Point",
        "coordinates": [
          -79.8667,
          36.6833
        ]
      },
      "type": "Feature",
      "properties": {
        "hierarchy": [
          "tgn:2112927",
          "tgn:1000001",
          "tgn:7012149",
          "tgn:2002220",
          "tgn:7007919",
          "tgn:7029392"
        ],
        "placetype": [
          "aat:300387277",
          "aat:300008347",
          "aat:300008416",
          "aat:300008389",
          "aat:300387308"
        ],
        "id": 2112927,
        "name:xx": "Martinsville"
      }
    }
  ]
}
