{
  "geometry": {
    "type": "Point",
    "coordinates": [
      13.75,
      48.55
    ]
  },
  "type": "Feature",
  "properties": {
    "hierarchy": [
      "tgn:7171641",
      "tgn:7003669",
      "tgn:1000003",
      "tgn:7000084",
      "tgn:7029392"
    ],
    "placetype": [
      "aat:300000206"
    ],
    "id": 7171641,
    "name:xx": "Herrnwies"
  }
}
