{
  "geometry": {
    "type": "Point",
    "coordinates": [
      -95.159,
      17.83
    ]
  },
  "type": "Feature",
  "properties": {
    "hierarchy": [
      "tgn:1125956",
      "tgn:1000001",
      "tgn:7005560",
      "tgn:7029392"
    ],
    "placetype": [
      "aat:300008707",
      "aat:300008699"
    ],
    "id": 1125956,
    "name:xx": "Lana, Río de la"
  }
}
