{
  "geometry": {
    "type": "Point",
    "coordinates": [
      -96.6667,
      31.3667
    ]
  },
  "type": "Feature",
  "properties": {
    "hierarchy": [
      "tgn:2103357",
      "tgn:1000001",
      "tgn:7012149",
      "tgn:1002597",
      "tgn:7007826",
      "tgn:7029392"
    ],
    "placetype": [
      "aat:300008347",
      "aat:300387210"
    ],
    "id": 2103357,
    "name:xx": "Coit"
  }
}
