{
  "geometry": {
    "type": "Point",
    "coordinates": [
      -97.6167,
      31.1667
    ]
  },
  "type": "Feature",
  "properties": {
    "hierarchy": [
      "tgn:2196626",
      "tgn:1000001",
      "tgn:1002174",
      "tgn:7012149",
      "tgn:7007826",
      "tgn:7029392"
    ],
    "placetype": [
      "aat:300008347"
    ],
    "id": 2196626,
    "name:xx": "Brookhaven"
  }
}
