{
  "geometry": {
    "type": "Point",
    "coordinates": [
      -122.9167,
      47.15
    ]
  },
  "type": "Feature",
  "properties": {
    "hierarchy": [
      "tgn:2619030",
      "tgn:1000001",
      "tgn:7012149",
      "tgn:1002942",
      "tgn:7007920",
      "tgn:7029392"
    ],
    "placetype": [
      "aat:300008347"
    ],
    "id": 2619030,
    "name:xx": "Rignall"
  }
}
