{
  "geometry": {
    "type": "Point",
    "coordinates": [
      -91.2333,
      29.6167
    ]
  },
  "type": "Feature",
  "properties": {
    "hierarchy": [
      "tgn:2397481",
      "tgn:1000001",
      "tgn:7012149",
      "tgn:2000904",
      "tgn:7007256",
      "tgn:7029392"
    ],
    "placetype": [
      "aat:300008791"
    ],
    "id": 2397481,
    "name:xx": "Honey Island"
  }
}
