{
  "type": "FeatureCollection",
  "features": [
    {
      "geometry": {
        "type": "Point",
        "coordinates": [
          30.6,
          28.9
        ]
      },
      "type": "Feature",
      "properties": {
        "hierarchy": [
          "tgn:1001142",
          "tgn:7001242",
          "tgn:7016833",
          "tgn:7029392"
        ],
        "placetype": [
          "aat:300387064",
          "aat:300235093"
        ],
        "id": 1001142,
        "name:xx": "Muḩāfaz̧at Banī Suwayf"
      }
    },
    {
      "geometry": {
        "type": "Point",
        "coordinates": [
          18,
          -4
        ]
      },
      "type": "Feature",
      "properties": {
        "hierarchy": [
          "tgn:1001143",
          "tgn:7001242",
          "tgn:1000159",
          "tgn:7029392"
        ],
        "placetype": [
          "aat:300387064",
          "aat:300000774"
        ],
        "id": 1001143,
        "name:xx": "Bandundu"
      }
    },
    {
      "geometry": {
        "type": "Point",
        "coordinates": [
          14.5,
          -5.5
        ]
      },
      "type": "Feature",
      "properties": {
        "hierarchy": [
          "tgn:1001144",
          "tgn:7001242",
          "tgn:1000159",
          "tgn:7029392"
        ],
        "placetype": [
          "aat:300387064",
          "aat:300000774"
        ],
        "id": 1001144,
        "name:xx": "Bas-Congo"
      }
    },
    {
      "geometry": {
        "type": "Point",
        "coordinates": [
          122.05,
          6.5667
        ]
      },
      "type": "Feature",
      "properties": {
        "hierarchy": [
          "tgn:1001145",
          "tgn:1000004",
          "tgn:1000135",
          "tgn:7029392"
        ],
        "placetype": [
          "aat:300387064",
          "aat:300000774"
        ],
        "id": 1001145,
        "name:xx": "Basilan"
      }
    },
    {
      "geometry": {
        "type": "Point",
        "coordinates": [
          120.4167,
          14.6667
        ]
      },
      "type": "Feature",
      "properties": {
        "hierarchy": [
          "tgn:1001146",
          "tgn:1000004",
          "tgn:1000135",
          "tgn:7029392"
        ],
        "placetype": [
          "aat:300387064",
          "aat:300000774"
        ],
        "id": 1001146,
        "name:xx": "Bataan"
      }
    },
    {
      "geometry": {
        "type": "Point",
        "coordinates": [
          121.0833,
          13.9167
        ]
      },
      "type": "Feature",
      "properties": {
        "hierarchy": [
          "tgn:1001147",
          "tgn:1000004",
          "tgn:1000135",
          "tgn:7029392"
        ],
        "placetype": [
          "aat:300387064",
          "aat:300000774"
        ],
        "id": 1001147,
        "name:xx": "Batangas"
      }
    },
    {
      "geometry": {
        "type": "Point",
        "coordinates": [
          35.5,
          33.9333
        ]
      },
      "type": "Feature",
      "properties": {
        "hierarchy": [
          "tgn:1001148",
          "tgn:1000004",
          "tgn:1000126",
          "tgn:7029392"
        ],
        "placetype": [
          "aat:300387064",
          "aat:300235093"
        ],
        "id": 1001148,
        "name:xx": "Bayrūt"
      }
    },
    {
      "geometry": {
        "type": "Point",
        "coordinates": [
          -7.1667,
          33.5
        ]
      },
      "type": "Feature",
      "properties": {
        "hierarchy": [
          "tgn:1001149",
          "tgn:7593667",
          "tgn:7001242",
          "tgn:1000179",
          "tgn:7029392"
        ],
        "placetype": [
          "aat:300387064",
          "aat:300387145",
          "aat:300000774"
        ],
        "id": 1001149,
        "name:xx": "Ben Slimane, Province de"
      }
    }
  ]
}
