{
  "type": "FeatureCollection",
  "features": [
    {
      "geometry": {
        "type": "Point",
        "coordinates": [
          12.833333,
          42.2
        ]
      },
      "type": "Feature",
      "properties": {
        "hierarchy": [
          "tgn:7049700",
          "tgn:7003137",
          "tgn:1000003",
          "tgn:7003080",
          "tgn:1000080",
          "tgn:7029392"
        ],
        "placetype": [
          "aat:300008347"
        ],
        "id": 7049700,
        "name:xx": "Cerdomare"
      }
    },
    {
      "geometry": {
        "type": "Point",
        "coordinates": [
          11.016667,
          45.316667
        ]
      },
      "type": "Feature",
      "properties": {
        "hierarchy": [
          "tgn:7049702",
          "tgn:7003007",
          "tgn:1000003",
          "tgn:7002997",
          "tgn:1000080",
          "tgn:7029392"
        ],
        "placetype": [
          "aat:300008347"
        ],
        "id": 7049702,
        "name:xx": "Cercomano"
      }
    },
    {
      "geometry": {
        "type": "Point",
        "coordinates": [
          12.983333,
          48.533333
        ]
      },
      "type": "Feature",
      "properties": {
        "hierarchy": [
          "tgn:7049704",
          "tgn:1003506",
          "tgn:1000003",
          "tgn:7002993",
          "tgn:1000080",
          "tgn:7029392"
        ],
        "placetype": [
          "aat:300008347"
        ],
        "id": 7049704,
        "name:xx": "Cercivento"
      }
    },
    {
      "geometry": {
        "type": "Point",
        "coordinates": [
          9.5,
          46.15
        ]
      },
      "type": "Feature",
      "properties": {
        "hierarchy": [
          "tgn:7049705",
          "tgn:1000003",
          "tgn:7003152",
          "tgn:7003237",
          "tgn:1000080",
          "tgn:7029392"
        ],
        "placetype": [
          "aat:300008347"
        ],
        "id": 7049705,
        "name:xx": "Cercino"
      }
    },
    {
      "geometry": {
        "type": "Point",
        "coordinates": [
          13.766667,
          42.516667
        ]
      },
      "type": "Feature",
      "properties": {
        "hierarchy": [
          "tgn:7049707",
          "tgn:7009084",
          "tgn:7003001",
          "tgn:1000003",
          "tgn:1000080",
          "tgn:7029392"
        ],
        "placetype": [
          "aat:300008699"
        ],
        "id": 7049707,
        "name:xx": "Cerchiola, Torrente"
      }
    },
    {
      "geometry": {
        "type": "Point",
        "coordinates": [
          13.583333,
          42.05
        ]
      },
      "type": "Feature",
      "properties": {
        "hierarchy": [
          "tgn:7049708",
          "tgn:7009084",
          "tgn:7004154",
          "tgn:1000003",
          "tgn:1000080",
          "tgn:7029392"
        ],
        "placetype": [
          "aat:300008347"
        ],
        "id": 7049708,
        "name:xx": "Cerchio"
      }
    }
  ]
}
