{
  "geometry": {
    "type": "Point",
    "coordinates": [
      36.5833,
      32.1333
    ]
  },
  "type": "Feature",
  "properties": {
    "hierarchy": [
      "tgn:1112023",
      "tgn:1000004",
      "tgn:1000121",
      "tgn:7029392"
    ],
    "placetype": [
      "aat:300387346"
    ],
    "id": 1112023,
    "name:xx": "Jabbān, Arḍ al-"
  }
}
