{
  "geometry": {
    "type": "Point",
    "coordinates": [
      -121.1833,
      45.7333
    ]
  },
  "type": "Feature",
  "properties": {
    "hierarchy": [
      "tgn:2363330",
      "tgn:1000001",
      "tgn:7012149",
      "tgn:1002554",
      "tgn:7007920",
      "tgn:7029392"
    ],
    "placetype": [
      "aat:300008761"
    ],
    "id": 2363330,
    "name:xx": "Green Canyon"
  }
}
