{
  "type": "FeatureCollection",
  "features": [
    {
      "geometry": {
        "type": "Point",
        "coordinates": [
          -74.2,
          44.1333
        ]
      },
      "type": "Feature",
      "properties": {
        "hierarchy": [
          "tgn:2317300",
          "tgn:1000001",
          "tgn:7012149",
          "tgn:7013941",
          "tgn:7007568",
          "tgn:7029392"
        ],
        "placetype": [
          "aat:300008798"
        ],
        "id": 2317300,
        "name:xx": "Emmons, Mount"
      }
    },
    {
      "geometry": {
        "type": "Point",
        "coordinates": [
          -110.3,
          40.7
        ]
      },
      "type": "Feature",
      "properties": {
        "hierarchy": [
          "tgn:2317301",
          "tgn:1000001",
          "tgn:2002107",
          "tgn:7012149",
          "tgn:7007827",
          "tgn:7029392"
        ],
        "placetype": [
          "aat:300008798"
        ],
        "id": 2317301,
        "name:xx": "Emmons, Mount"
      }
    },
    {
      "geometry": {
        "type": "Point",
        "coordinates": [
          -74.7,
          43.15
        ]
      },
      "type": "Feature",
      "properties": {
        "hierarchy": [
          "tgn:2317302",
          "tgn:1000001",
          "tgn:7012149",
          "tgn:1002397",
          "tgn:7007568",
          "tgn:7029392"
        ],
        "placetype": [
          "aat:300008347"
        ],
        "id": 2317302,
        "name:xx": "Emmonsburg"
      }
    },
    {
      "geometry": {
        "type": "Point",
        "coordinates": [
          -76.3,
          39.4167
        ]
      },
      "type": "Feature",
      "properties": {
        "hierarchy": [
          "tgn:2317303",
          "tgn:1000001",
          "tgn:7016102",
          "tgn:7012149",
          "tgn:7007516",
          "tgn:7029392"
        ],
        "placetype": [
          "aat:300008699"
        ],
        "id": 2317303,
        "name:xx": "Emmord Branch"
      }
    },
    {
      "geometry": {
        "type": "Point",
        "coordinates": [
          -97.3167,
          27.5
        ]
      },
      "type": "Feature",
      "properties": {
        "hierarchy": [
          "tgn:2317304",
          "tgn:1000001",
          "tgn:7012149",
          "tgn:2002022",
          "tgn:7007826",
          "tgn:7029392"
        ],
        "placetype": [
          "aat:300386845"
        ],
        "id": 2317304,
        "name:xx": "Emmords Hole"
      }
    },
    {
      "geometry": {
        "type": "Point",
        "coordinates": [
          -157.3167,
          68.8
        ]
      },
      "type": "Feature",
      "properties": {
        "hierarchy": [
          "tgn:2317305",
          "tgn:7006450",
          "tgn:1000001",
          "tgn:7012149",
          "tgn:2124005",
          "tgn:7029392"
        ],
        "placetype": [
          "aat:300266640"
        ],
        "id": 2317305,
        "name:xx": "Emnavak Ridge"
      }
    },
    {
      "geometry": {
        "type": "Point",
        "coordinates": [
          -91.5667,
          38.5
        ]
      },
      "type": "Feature",
      "properties": {
        "hierarchy": [
          "tgn:2317306",
          "tgn:1000001",
          "tgn:7012149",
          "tgn:1002402",
          "tgn:7007523",
          "tgn:7029392"
        ],
        "placetype": [
          "aat:300008699"
        ],
        "id": 2317306,
        "name:xx": "Emo Branch"
      }
    },
    {
      "geometry": {
        "type": "Point",
        "coordinates": [
          -93.2333,
          33.35
        ]
      },
      "type": "Feature",
      "properties": {
        "hierarchy": [
          "tgn:2317307",
          "tgn:1000001",
          "tgn:7016172",
          "tgn:2000118",
          "tgn:7012149",
          "tgn:7029392"
        ],
        "placetype": [
          "aat:300008347"
        ],
        "id": 2317307,
        "name:xx": "Emon"
      }
    },
    {
      "geometry": {
        "type": "Point",
        "coordinates": [
          -90.8833,
          39.3833
        ]
      },
      "type": "Feature",
      "properties": {
        "hierarchy": [
          "tgn:2317308",
          "tgn:1000001",
          "tgn:1002221",
          "tgn:7012149",
          "tgn:7007251",
          "tgn:7029392"
        ],
        "placetype": [
          "aat:300008680"
        ],
        "id": 2317308,
        "name:xx": "Emoritt Lake"
      }
    },
    {
      "geometry": {
        "type": "Point",
        "coordinates": [
          -88.45,
          31.8
        ]
      },
      "type": "Feature",
      "properties": {
        "hierarchy": [
          "tgn:2317309",
          "tgn:7002659",
          "tgn:1000001",
          "tgn:2000011",
          "tgn:7012149",
          "tgn:7029392"
        ],
        "placetype": [
          "aat:300008347"
        ],
        "id": 2317309,
        "name:xx": "Emory"
      }
    }
  ]
}
