{
  "geometry": {
    "type": "Point",
    "coordinates": [
      -96.15,
      38.2167
    ]
  },
  "type": "Feature",
  "properties": {
    "hierarchy": [
      "tgn:2433554",
      "tgn:1000001",
      "tgn:7012149",
      "tgn:7007254",
      "tgn:7029392"
    ],
    "placetype": [
      "aat:300008699"
    ],
    "id": 2433554,
    "name:xx": "Kelly Branch"
  }
}
