{
  "geometry": {
    "type": "Point",
    "coordinates": [
      -81.5333,
      28.5333
    ]
  },
  "type": "Feature",
  "properties": {
    "hierarchy": [
      "tgn:2448743",
      "tgn:1000001",
      "tgn:7012149",
      "tgn:1002749",
      "tgn:7007240",
      "tgn:7029392"
    ],
    "placetype": [
      "aat:300008680"
    ],
    "id": 2448743,
    "name:xx": "Lily, Lake"
  }
}
