{
  "type": "FeatureCollection",
  "features": [
    {
      "geometry": {
        "type": "Point",
        "coordinates": [
          -114.65,
          41.7833
        ]
      },
      "type": "Feature",
      "properties": {
        "hierarchy": [
          "tgn:2139420",
          "tgn:1000001",
          "tgn:2001411",
          "tgn:7012149",
          "tgn:7007526",
          "tgn:7029392"
        ],
        "placetype": [
          "aat:300008697"
        ],
        "id": 2139420,
        "name:xx": "Aspen Spring"
      }
    },
    {
      "geometry": {
        "type": "Point",
        "coordinates": [
          -119.45,
          40.8833
        ]
      },
      "type": "Feature",
      "properties": {
        "hierarchy": [
          "tgn:2139421",
          "tgn:1000001",
          "tgn:7012149",
          "tgn:1002999",
          "tgn:7007526",
          "tgn:7029392"
        ],
        "placetype": [
          "aat:300008697"
        ],
        "id": 2139421,
        "name:xx": "Aspen Spring"
      }
    },
    {
      "geometry": {
        "type": "Point",
        "coordinates": [
          -107.9,
          33.1
        ]
      },
      "type": "Feature",
      "properties": {
        "hierarchy": [
          "tgn:2139422",
          "tgn:1000001",
          "tgn:7012149",
          "tgn:2001437",
          "tgn:7007566",
          "tgn:7029392"
        ],
        "placetype": [
          "aat:300008697"
        ],
        "id": 2139422,
        "name:xx": "Aspen Spring"
      }
    },
    {
      "geometry": {
        "type": "Point",
        "coordinates": [
          -107.2167,
          36.6167
        ]
      },
      "type": "Feature",
      "properties": {
        "hierarchy": [
          "tgn:2139423",
          "tgn:1000001",
          "tgn:7012149",
          "tgn:2001449",
          "tgn:7007566",
          "tgn:7029392"
        ],
        "placetype": [
          "aat:300008697"
        ],
        "id": 2139423,
        "name:xx": "Aspen Spring"
      }
    },
    {
      "geometry": {
        "type": "Point",
        "coordinates": [
          -105.4833,
          35.8
        ]
      },
      "type": "Feature",
      "properties": {
        "hierarchy": [
          "tgn:2139424",
          "tgn:1000001",
          "tgn:7012149",
          "tgn:2001453",
          "tgn:7007566",
          "tgn:7029392"
        ],
        "placetype": [
          "aat:300008697"
        ],
        "id": 2139424,
        "name:xx": "Aspen Spring"
      }
    },
    {
      "geometry": {
        "type": "Point",
        "coordinates": [
          -106.3833,
          34.7167
        ]
      },
      "type": "Feature",
      "properties": {
        "hierarchy": [
          "tgn:2139425",
          "tgn:1000001",
          "tgn:7012149",
          "tgn:2001458",
          "tgn:7007566",
          "tgn:7029392"
        ],
        "placetype": [
          "aat:300008697"
        ],
        "id": 2139425,
        "name:xx": "Aspen Spring"
      }
    },
    {
      "geometry": {
        "type": "Point",
        "coordinates": [
          -122.2833,
          42.6333
        ]
      },
      "type": "Feature",
      "properties": {
        "hierarchy": [
          "tgn:2139426",
          "tgn:1000001",
          "tgn:7012149",
          "tgn:2001711",
          "tgn:7007708",
          "tgn:7029392"
        ],
        "placetype": [
          "aat:300008697"
        ],
        "id": 2139426,
        "name:xx": "Aspen Spring"
      }
    },
    {
      "geometry": {
        "type": "Point",
        "coordinates": [
          -120.8667,
          42.8333
        ]
      },
      "type": "Feature",
      "properties": {
        "hierarchy": [
          "tgn:2139427",
          "tgn:1000001",
          "tgn:7012149",
          "tgn:2001715",
          "tgn:7007708",
          "tgn:7029392"
        ],
        "placetype": [
          "aat:300008697"
        ],
        "id": 2139427,
        "name:xx": "Aspen Spring"
      }
    },
    {
      "geometry": {
        "type": "Point",
        "coordinates": [
          -117.9667,
          43.3833
        ]
      },
      "type": "Feature",
      "properties": {
        "hierarchy": [
          "tgn:2139428",
          "tgn:1000001",
          "tgn:7012149",
          "tgn:2001718",
          "tgn:7007708",
          "tgn:7029392"
        ],
        "placetype": [
          "aat:300008697"
        ],
        "id": 2139428,
        "name:xx": "Aspen Spring"
      }
    },
    {
      "geometry": {
        "type": "Point",
        "coordinates": [
          -119,
          43.8833
        ]
      },
      "type": "Feature",
      "properties": {
        "hierarchy": [
          "tgn:2139429",
          "tgn:1000001",
          "tgn:7012149",
          "tgn:2001709",
          "tgn:7007708",
          "tgn:7029392"
        ],
        "placetype": [
          "aat:300008697"
        ],
        "id": 2139429,
        "name:xx": "Aspen Spring"
      }
    }
  ]
}
