{
  "geometry": {
    "type": "Point",
    "coordinates": [
      -87.15,
      36.0167
    ]
  },
  "type": "Feature",
  "properties": {
    "hierarchy": [
      "tgn:2100717",
      "tgn:1000001",
      "tgn:7012149",
      "tgn:2001930",
      "tgn:7007825",
      "tgn:7029392"
    ],
    "placetype": [
      "aat:300008347"
    ],
    "id": 2100717,
    "name:xx": "New Hope"
  }
}
