{
  "geometry": {
    "type": "Point",
    "coordinates": [
      27.15,
      31.266667
    ]
  },
  "type": "Feature",
  "properties": {
    "hierarchy": [
      "tgn:7524263",
      "tgn:7001242",
      "tgn:7016833",
      "tgn:1001418",
      "tgn:7029392"
    ],
    "placetype": [
      "aat:300005926"
    ],
    "name:en": "El Sheikha Mas'ûda",
    "id": 7524263
  }
}
