{
  "geometry": {
    "type": "Point",
    "coordinates": [
      -68.8167,
      46.2667
    ]
  },
  "type": "Feature",
  "properties": {
    "hierarchy": [
      "tgn:2676208",
      "tgn:1000001",
      "tgn:7012149",
      "tgn:2000927",
      "tgn:7007515",
      "tgn:7029392"
    ],
    "placetype": [
      "aat:300008680"
    ],
    "id": 2676208,
    "name:xx": "Soule Pond"
  }
}
