{
  "geometry": {
    "type": "Point",
    "coordinates": [
      -105.9167,
      43.55
    ]
  },
  "type": "Feature",
  "properties": {
    "hierarchy": [
      "tgn:2541768",
      "tgn:1000001",
      "tgn:7012149",
      "tgn:7007923",
      "tgn:7029392"
    ],
    "placetype": [
      "aat:300008706"
    ],
    "id": 2541768,
    "name:xx": "Ninemile Creek"
  }
}
