{
  "geometry": {
    "type": "Point",
    "coordinates": [
      79.55,
      11.55
    ]
  },
  "type": "Feature",
  "properties": {
    "hierarchy": [
      "tgn:7580283",
      "tgn:1000004",
      "tgn:7000198",
      "tgn:7001797",
      "tgn:7029392"
    ],
    "placetype": [
      "aat:300007783"
    ],
    "name:en": "Vadalūr",
    "id": 7580283
  }
}
