{
  "type": "FeatureCollection",
  "features": [
    {
      "geometry": {
        "type": "Point",
        "coordinates": [
          -86.55,
          34.45
        ]
      },
      "type": "Feature",
      "properties": {
        "hierarchy": [
          "tgn:2527270",
          "tgn:7002659",
          "tgn:1000001",
          "tgn:7012149",
          "tgn:2000047",
          "tgn:7029392"
        ],
        "placetype": [
          "aat:300008347"
        ],
        "id": 2527270,
        "name:xx": "Mount Olive"
      }
    },
    {
      "geometry": {
        "type": "Point",
        "coordinates": [
          -86.8333,
          31.5667
        ]
      },
      "type": "Feature",
      "properties": {
        "hierarchy": [
          "tgn:2527271",
          "tgn:7002659",
          "tgn:1000001",
          "tgn:2000006",
          "tgn:7012149",
          "tgn:7029392"
        ],
        "placetype": [
          "aat:300008347"
        ],
        "id": 2527271,
        "name:xx": "Mount Olive"
      }
    },
    {
      "geometry": {
        "type": "Point",
        "coordinates": [
          -85.6167,
          34.8333
        ]
      },
      "type": "Feature",
      "properties": {
        "hierarchy": [
          "tgn:2527272",
          "tgn:7002659",
          "tgn:1000001",
          "tgn:7012149",
          "tgn:7021514",
          "tgn:7029392"
        ],
        "placetype": [
          "aat:300008347"
        ],
        "id": 2527272,
        "name:xx": "Mount Olive"
      }
    },
    {
      "geometry": {
        "type": "Point",
        "coordinates": [
          -87.3167,
          34.8167
        ]
      },
      "type": "Feature",
      "properties": {
        "hierarchy": [
          "tgn:2527273",
          "tgn:7002659",
          "tgn:1000001",
          "tgn:7012149",
          "tgn:2000038",
          "tgn:7029392"
        ],
        "placetype": [
          "aat:300008347"
        ],
        "id": 2527273,
        "name:xx": "Mount Olive"
      }
    },
    {
      "geometry": {
        "type": "Point",
        "coordinates": [
          -86.0833,
          33.7
        ]
      },
      "type": "Feature",
      "properties": {
        "hierarchy": [
          "tgn:2527274",
          "tgn:7002659",
          "tgn:1000001",
          "tgn:2000007",
          "tgn:7012149",
          "tgn:7029392"
        ],
        "placetype": [
          "aat:300008347"
        ],
        "id": 2527274,
        "name:xx": "Mount Olive"
      }
    },
    {
      "geometry": {
        "type": "Point",
        "coordinates": [
          -87.65,
          33.2833
        ]
      },
      "type": "Feature",
      "properties": {
        "hierarchy": [
          "tgn:2527275",
          "tgn:7002659",
          "tgn:1000001",
          "tgn:7012149",
          "tgn:2000062",
          "tgn:7029392"
        ],
        "placetype": [
          "aat:300008347"
        ],
        "id": 2527275,
        "name:xx": "Mount Olive"
      }
    },
    {
      "geometry": {
        "type": "Point",
        "coordinates": [
          -90.4,
          35.4667
        ]
      },
      "type": "Feature",
      "properties": {
        "hierarchy": [
          "tgn:2527276",
          "tgn:1000001",
          "tgn:7016172",
          "tgn:7012149",
          "tgn:2000160",
          "tgn:7029392"
        ],
        "placetype": [
          "aat:300008347"
        ],
        "id": 2527276,
        "name:xx": "Mount Olive"
      }
    },
    {
      "geometry": {
        "type": "Point",
        "coordinates": [
          -91.6667,
          33.3667
        ]
      },
      "type": "Feature",
      "properties": {
        "hierarchy": [
          "tgn:2527277",
          "tgn:2000106",
          "tgn:1000001",
          "tgn:7016172",
          "tgn:7012149",
          "tgn:7029392"
        ],
        "placetype": [
          "aat:300008347"
        ],
        "id": 2527277,
        "name:xx": "Mount Olive"
      }
    },
    {
      "geometry": {
        "type": "Point",
        "coordinates": [
          -93.9,
          33.9333
        ]
      },
      "type": "Feature",
      "properties": {
        "hierarchy": [
          "tgn:2527278",
          "tgn:1000001",
          "tgn:7016172",
          "tgn:7012149",
          "tgn:2000135",
          "tgn:7029392"
        ],
        "placetype": [
          "aat:300008347"
        ],
        "id": 2527278,
        "name:xx": "Mount Olive"
      }
    },
    {
      "geometry": {
        "type": "Point",
        "coordinates": [
          -83.3833,
          32.5833
        ]
      },
      "type": "Feature",
      "properties": {
        "hierarchy": [
          "tgn:2527279",
          "tgn:1000001",
          "tgn:7012149",
          "tgn:2000434",
          "tgn:7007248",
          "tgn:7029392"
        ],
        "placetype": [
          "aat:300008347"
        ],
        "id": 2527279,
        "name:xx": "Mount Olive"
      }
    }
  ]
}
