{
  "type": "FeatureCollection",
  "features": [
    {
      "geometry": {
        "type": "Point",
        "coordinates": [
          2.8333,
          44.9167
        ]
      },
      "type": "Feature",
      "properties": {
        "hierarchy": [
          "tgn:4008650",
          "tgn:7002871",
          "tgn:1000003",
          "tgn:1000070",
          "tgn:7029392"
        ],
        "placetype": [
          "aat:300008347"
        ],
        "id": 4008650,
        "name:xx": "Pierrefort"
      }
    },
    {
      "geometry": {
        "type": "Point",
        "coordinates": [
          10.833333,
          45.116667
        ]
      },
      "type": "Feature",
      "properties": {
        "hierarchy": [
          "tgn:4008652",
          "tgn:7005880",
          "tgn:1000003",
          "tgn:7003237",
          "tgn:1000080",
          "tgn:7029392"
        ],
        "placetype": [
          "aat:300008347"
        ],
        "id": 4008652,
        "name:xx": "Pietole"
      }
    },
    {
      "geometry": {
        "type": "Point",
        "coordinates": [
          9.4167,
          42.8333
        ]
      },
      "type": "Feature",
      "properties": {
        "hierarchy": [
          "tgn:4008653",
          "tgn:1000003",
          "tgn:7594273",
          "tgn:1000070",
          "tgn:7029392"
        ],
        "placetype": [
          "aat:300008347"
        ],
        "id": 4008653,
        "name:xx": "Pietracorbara"
      }
    },
    {
      "geometry": {
        "type": "Point",
        "coordinates": [
          10.216667,
          45.183333
        ]
      },
      "type": "Feature",
      "properties": {
        "hierarchy": [
          "tgn:4008656",
          "tgn:7005869",
          "tgn:1000003",
          "tgn:7003237",
          "tgn:1000080",
          "tgn:7029392"
        ],
        "placetype": [
          "aat:300008347"
        ],
        "id": 4008656,
        "name:xx": "Pieve Terzagni"
      }
    }
  ]
}
