{
  "type": "FeatureCollection",
  "features": [
    {
      "geometry": {
        "type": "Point",
        "coordinates": [
          -105.15,
          38.9
        ]
      },
      "type": "Feature",
      "properties": {
        "hierarchy": [
          "tgn:2727260",
          "tgn:1000001",
          "tgn:7012149",
          "tgn:7007158",
          "tgn:2000251",
          "tgn:7029392"
        ],
        "placetype": [
          "aat:300008798"
        ],
        "id": 2727260,
        "name:xx": "Tracy Hill"
      }
    },
    {
      "geometry": {
        "type": "Point",
        "coordinates": [
          -71.5167,
          41.85
        ]
      },
      "type": "Feature",
      "properties": {
        "hierarchy": [
          "tgn:2727261",
          "tgn:1002808",
          "tgn:1000001",
          "tgn:7012149",
          "tgn:7007711",
          "tgn:7029392"
        ],
        "placetype": [
          "aat:300008798"
        ],
        "id": 2727261,
        "name:xx": "Tracy Hill"
      }
    },
    {
      "geometry": {
        "type": "Point",
        "coordinates": [
          -122.6167,
          47.0333
        ]
      },
      "type": "Feature",
      "properties": {
        "hierarchy": [
          "tgn:2727262",
          "tgn:1000001",
          "tgn:7012149",
          "tgn:1002785",
          "tgn:7007920",
          "tgn:7029392"
        ],
        "placetype": [
          "aat:300008798"
        ],
        "id": 2727262,
        "name:xx": "Tracy Hill"
      }
    },
    {
      "geometry": {
        "type": "Point",
        "coordinates": [
          -121.3833,
          45.7333
        ]
      },
      "type": "Feature",
      "properties": {
        "hierarchy": [
          "tgn:2727263",
          "tgn:1000001",
          "tgn:7012149",
          "tgn:1002554",
          "tgn:7007920",
          "tgn:7029392"
        ],
        "placetype": [
          "aat:300008798"
        ],
        "id": 2727263,
        "name:xx": "Tracy Hill"
      }
    },
    {
      "geometry": {
        "type": "Point",
        "coordinates": [
          -92.2667,
          37.5167
        ]
      },
      "type": "Feature",
      "properties": {
        "hierarchy": [
          "tgn:2727264",
          "tgn:1000001",
          "tgn:7012149",
          "tgn:2001211",
          "tgn:7007523",
          "tgn:7029392"
        ],
        "placetype": [
          "aat:300008761"
        ],
        "id": 2727264,
        "name:xx": "Tracy Hollow"
      }
    },
    {
      "geometry": {
        "type": "Point",
        "coordinates": [
          -91.7333,
          37.1
        ]
      },
      "type": "Feature",
      "properties": {
        "hierarchy": [
          "tgn:2727265",
          "tgn:1000001",
          "tgn:7012149",
          "tgn:2001252",
          "tgn:7007523",
          "tgn:7029392"
        ],
        "placetype": [
          "aat:300008761"
        ],
        "id": 2727265,
        "name:xx": "Tracy Hollow"
      }
    },
    {
      "geometry": {
        "type": "Point",
        "coordinates": [
          -121.3167,
          38.2
        ]
      },
      "type": "Feature",
      "properties": {
        "hierarchy": [
          "tgn:2727266",
          "tgn:1000001",
          "tgn:7012149",
          "tgn:7007157",
          "tgn:1002861",
          "tgn:7029392"
        ],
        "placetype": [
          "aat:300008680"
        ],
        "id": 2727266,
        "name:xx": "Tracy Lake"
      }
    },
    {
      "geometry": {
        "type": "Point",
        "coordinates": [
          -91.5333,
          40.0333
        ]
      },
      "type": "Feature",
      "properties": {
        "hierarchy": [
          "tgn:2727267",
          "tgn:1000001",
          "tgn:7012149",
          "tgn:1002592",
          "tgn:7007523",
          "tgn:7029392"
        ],
        "placetype": [
          "aat:300006191"
        ],
        "id": 2727267,
        "name:xx": "Tracy Lake"
      }
    },
    {
      "geometry": {
        "type": "Point",
        "coordinates": [
          -76.1333,
          42.7833
        ]
      },
      "type": "Feature",
      "properties": {
        "hierarchy": [
          "tgn:2727268",
          "tgn:1000001",
          "tgn:7012149",
          "tgn:1002746",
          "tgn:7007568",
          "tgn:7029392"
        ],
        "placetype": [
          "aat:300008680"
        ],
        "id": 2727268,
        "name:xx": "Tracy Lake"
      }
    },
    {
      "geometry": {
        "type": "Point",
        "coordinates": [
          -90.3167,
          45.9
        ]
      },
      "type": "Feature",
      "properties": {
        "hierarchy": [
          "tgn:2727269",
          "tgn:1000001",
          "tgn:7012149",
          "tgn:2002348",
          "tgn:7007922",
          "tgn:7029392"
        ],
        "placetype": [
          "aat:300008680"
        ],
        "id": 2727269,
        "name:xx": "Tracy Lake"
      }
    }
  ]
}
