{
  "geometry": {
    "type": "Point",
    "coordinates": [
      121.2225,
      24.903333
    ]
  },
  "type": "Feature",
  "properties": {
    "hierarchy": [
      "tgn:7480414",
      "tgn:1000004",
      "tgn:7001013",
      "tgn:1000141",
      "tgn:7029392"
    ],
    "placetype": [
      "aat:300007836"
    ],
    "id": 7480414,
    "name:xx": "Chang'an Qiao"
  }
}
