{
  "geometry": {
    "type": "Point",
    "coordinates": [
      -123.1667,
      46.6333
    ]
  },
  "type": "Feature",
  "properties": {
    "hierarchy": [
      "tgn:2506849",
      "tgn:1000001",
      "tgn:7012149",
      "tgn:1002594",
      "tgn:7007920",
      "tgn:7029392"
    ],
    "placetype": [
      "aat:300008347"
    ],
    "id": 2506849,
    "name:xx": "Meskill"
  }
}
