{
  "type": "FeatureCollection",
  "features": [
    {
      "geometry": {
        "type": "Point",
        "coordinates": [
          11.6833,
          47.3333
        ]
      },
      "type": "Feature",
      "properties": {
        "hierarchy": [
          "tgn:1026190",
          "tgn:7003029",
          "tgn:1000003",
          "tgn:1000062",
          "tgn:7029392"
        ],
        "placetype": [
          "aat:300008347"
        ],
        "id": 1026190,
        "name:xx": "Vomp"
      }
    },
    {
      "geometry": {
        "type": "Point",
        "coordinates": [
          12.2,
          47.2333
        ]
      },
      "type": "Feature",
      "properties": {
        "hierarchy": [
          "tgn:1026193",
          "tgn:7003027",
          "tgn:1000003",
          "tgn:1000062",
          "tgn:7029392"
        ],
        "placetype": [
          "aat:300008347"
        ],
        "id": 1026193,
        "name:xx": "Vorderkrimmi"
      }
    },
    {
      "geometry": {
        "type": "Point",
        "coordinates": [
          16.2167,
          48.3333
        ]
      },
      "type": "Feature",
      "properties": {
        "hierarchy": [
          "tgn:1026195",
          "tgn:7003025",
          "tgn:1000003",
          "tgn:1000062",
          "tgn:7029392"
        ],
        "placetype": [
          "aat:300008347"
        ],
        "id": 1026195,
        "name:xx": "Wördern"
      }
    },
    {
      "geometry": {
        "type": "Point",
        "coordinates": [
          12.0667,
          47.4833
        ]
      },
      "type": "Feature",
      "properties": {
        "hierarchy": [
          "tgn:1026196",
          "tgn:7003029",
          "tgn:1000003",
          "tgn:1000062",
          "tgn:7029392"
        ],
        "placetype": [
          "aat:300008347"
        ],
        "id": 1026196,
        "name:xx": "Wörgl"
      }
    },
    {
      "geometry": {
        "type": "Point",
        "coordinates": [
          15.5667,
          46.7667
        ]
      },
      "type": "Feature",
      "properties": {
        "hierarchy": [
          "tgn:1026197",
          "tgn:7003028",
          "tgn:1000003",
          "tgn:1000062",
          "tgn:7029392"
        ],
        "placetype": [
          "aat:300008347"
        ],
        "id": 1026197,
        "name:xx": "Wagna"
      }
    },
    {
      "geometry": {
        "type": "Point",
        "coordinates": [
          13.3,
          47.3333
        ]
      },
      "type": "Feature",
      "properties": {
        "hierarchy": [
          "tgn:1026198",
          "tgn:7003027",
          "tgn:1000003",
          "tgn:1000062",
          "tgn:7029392"
        ],
        "placetype": [
          "aat:300008347"
        ],
        "id": 1026198,
        "name:xx": "Wagrain"
      }
    }
  ]
}
