{
  "geometry": {
    "type": "Point",
    "coordinates": [
      -89.1167,
      46.7833
    ]
  },
  "type": "Feature",
  "properties": {
    "hierarchy": [
      "tgn:2520380",
      "tgn:1000001",
      "tgn:7012149",
      "tgn:2000986",
      "tgn:7007520",
      "tgn:7029392"
    ],
    "placetype": [
      "aat:300008706"
    ],
    "id": 2520380,
    "name:xx": "Monehan Creek"
  }
}
