{
  "type": "FeatureCollection",
  "features": [
    {
      "geometry": {
        "type": "Point",
        "coordinates": [
          -4.266667,
          51.116667
        ]
      },
      "type": "Feature",
      "properties": {
        "hierarchy": [
          "tgn:7465210",
          "tgn:7002445",
          "tgn:1000003",
          "tgn:7012077",
          "tgn:7008591",
          "tgn:7029392"
        ],
        "placetype": [
          "aat:300011692"
        ],
        "name:en": "Asp Rock",
        "id": 7465210
      }
    },
    {
      "geometry": {
        "type": "Point",
        "coordinates": [
          -0.633333,
          52.016667
        ]
      },
      "type": "Feature",
      "properties": {
        "hierarchy": [
          "tgn:7465211",
          "tgn:7002445",
          "tgn:7008103",
          "tgn:1000003",
          "tgn:7008591",
          "tgn:7029392"
        ],
        "placetype": [
          "aat:300008347"
        ],
        "name:en": "Aspley Guise",
        "id": 7465211
      }
    },
    {
      "geometry": {
        "type": "Point",
        "coordinates": [
          1.166667,
          52.233333
        ]
      },
      "type": "Feature",
      "properties": {
        "hierarchy": [
          "tgn:7465214",
          "tgn:7002445",
          "tgn:1000003",
          "tgn:7008185",
          "tgn:7008591",
          "tgn:7029392"
        ],
        "placetype": [
          "aat:300008347"
        ],
        "name:en": "Aspall",
        "id": 7465214
      }
    },
    {
      "geometry": {
        "type": "Point",
        "coordinates": [
          -5.283333,
          57.2
        ]
      },
      "type": "Feature",
      "properties": {
        "hierarchy": [
          "tgn:7465216",
          "tgn:7002444",
          "tgn:1000003",
          "tgn:7008082",
          "tgn:7008591",
          "tgn:7029392"
        ],
        "placetype": [
          "aat:300008795"
        ],
        "name:en": "Aslak, Ben",
        "id": 7465216
      }
    },
    {
      "geometry": {
        "type": "Point",
        "coordinates": [
          -5.683333,
          57.2
        ]
      },
      "type": "Feature",
      "properties": {
        "hierarchy": [
          "tgn:7465217",
          "tgn:7002444",
          "tgn:1000003",
          "tgn:7008082",
          "tgn:7008591",
          "tgn:7029392"
        ],
        "placetype": [
          "aat:300132316"
        ],
        "name:en": "Aslaig, Port",
        "id": 7465217
      }
    },
    {
      "geometry": {
        "type": "Point",
        "coordinates": [
          -4.633333,
          57.266667
        ]
      },
      "type": "Feature",
      "properties": {
        "hierarchy": [
          "tgn:7465218",
          "tgn:7002444",
          "tgn:1000003",
          "tgn:7008082",
          "tgn:7008591",
          "tgn:7029392"
        ],
        "placetype": [
          "aat:300008680"
        ],
        "name:en": "Aslaich, Loch",
        "id": 7465218
      }
    }
  ]
}
