{
  "geometry": {
    "type": "Point",
    "coordinates": [
      -82.9833,
      38.4667
    ]
  },
  "type": "Feature",
  "properties": {
    "hierarchy": [
      "tgn:2608118",
      "tgn:1000001",
      "tgn:7012149",
      "tgn:1002426",
      "tgn:7007255",
      "tgn:7029392"
    ],
    "placetype": [
      "aat:300008699"
    ],
    "id": 2608118,
    "name:xx": "Rattlesnake Branch"
  }
}
