{
  "geometry": {
    "type": "Point",
    "coordinates": [
      -117.55,
      46.1833
    ]
  },
  "type": "Feature",
  "properties": {
    "hierarchy": [
      "tgn:2293523",
      "tgn:1000001",
      "tgn:2002245",
      "tgn:7012149",
      "tgn:7007920",
      "tgn:7029392"
    ],
    "placetype": [
      "aat:300008697"
    ],
    "id": 2293523,
    "name:xx": "Double Spring"
  }
}
