{
  "type": "FeatureCollection",
  "features": [
    {
      "geometry": {
        "type": "Point",
        "coordinates": [
          -119.8833,
          36.8
        ]
      },
      "type": "Feature",
      "properties": {
        "hierarchy": [
          "tgn:2011765",
          "tgn:1000001",
          "tgn:7012149",
          "tgn:1002392",
          "tgn:7007157",
          "tgn:7029392"
        ],
        "placetype": [
          "aat:300008347"
        ],
        "id": 2011765,
        "name:xx": "Highway City"
      }
    },
    {
      "geometry": {
        "type": "Point",
        "coordinates": [
          -119.1333,
          36.4
        ]
      },
      "type": "Feature",
      "properties": {
        "hierarchy": [
          "tgn:2011767",
          "tgn:1000001",
          "tgn:7012149",
          "tgn:7007157",
          "tgn:1002956",
          "tgn:7029392"
        ],
        "placetype": [
          "aat:300387016"
        ],
        "id": 2011767,
        "name:xx": "Hillmaid"
      }
    },
    {
      "geometry": {
        "type": "Point",
        "coordinates": [
          -122.3667,
          37.5667
        ]
      },
      "type": "Feature",
      "properties": {
        "hierarchy": [
          "tgn:2011768",
          "tgn:1000001",
          "tgn:7012149",
          "tgn:7007157",
          "tgn:1002864",
          "tgn:7029392"
        ],
        "placetype": [
          "aat:300008347"
        ],
        "id": 2011768,
        "name:xx": "Hillsborough"
      }
    },
    {
      "geometry": {
        "type": "Point",
        "coordinates": [
          -121.05,
          39.2167
        ]
      },
      "type": "Feature",
      "properties": {
        "hierarchy": [
          "tgn:2011769",
          "tgn:1000001",
          "tgn:7012149",
          "tgn:7007157",
          "tgn:1002710",
          "tgn:7029392"
        ],
        "placetype": [
          "aat:300008347"
        ],
        "id": 2011769,
        "name:xx": "Hills Flat"
      }
    }
  ]
}
