{
  "geometry": {
    "type": "Point",
    "coordinates": [
      -84.35,
      45.1667
    ]
  },
  "type": "Feature",
  "properties": {
    "hierarchy": [
      "tgn:2694615",
      "tgn:1000001",
      "tgn:7012149",
      "tgn:2000982",
      "tgn:7007520",
      "tgn:7029392"
    ],
    "placetype": [
      "aat:300008680"
    ],
    "id": 2694615,
    "name:xx": "Stewart Lake"
  }
}
