{
  "geometry": {
    "type": "Point",
    "coordinates": [
      -89.2833,
      37.9667
    ]
  },
  "type": "Feature",
  "properties": {
    "hierarchy": [
      "tgn:2786248",
      "tgn:1000001",
      "tgn:7012149",
      "tgn:2000522",
      "tgn:7007251",
      "tgn:7029392"
    ],
    "placetype": [
      "aat:300008706"
    ],
    "id": 2786248,
    "name:xx": "Youngs Creek"
  }
}
