{
  "geometry": {
    "type": "Point",
    "coordinates": [
      -84.5667,
      35.4167
    ]
  },
  "type": "Feature",
  "properties": {
    "hierarchy": [
      "tgn:2705005",
      "tgn:1000001",
      "tgn:7012149",
      "tgn:7022542",
      "tgn:7007825",
      "tgn:7029392"
    ],
    "placetype": [
      "aat:300008347"
    ],
    "id": 2705005,
    "name:xx": "Sunset View"
  }
}
