{
  "type": "FeatureCollection",
  "features": [
    {
      "geometry": {
        "type": "Point",
        "coordinates": [
          -74.7167,
          43.55
        ]
      },
      "type": "Feature",
      "properties": {
        "hierarchy": [
          "tgn:2355860",
          "tgn:1000001",
          "tgn:7012149",
          "tgn:1002440",
          "tgn:7007568",
          "tgn:7029392"
        ],
        "placetype": [
          "aat:300008680"
        ],
        "id": 2355860,
        "name:xx": "Goose Lake"
      }
    },
    {
      "geometry": {
        "type": "Point",
        "coordinates": [
          -98.4,
          46.8833
        ]
      },
      "type": "Feature",
      "properties": {
        "hierarchy": [
          "tgn:2355861",
          "tgn:2001558",
          "tgn:1000001",
          "tgn:7012149",
          "tgn:7007705",
          "tgn:7029392"
        ],
        "placetype": [
          "aat:300008680"
        ],
        "id": 2355861,
        "name:xx": "Goose Lake"
      }
    },
    {
      "geometry": {
        "type": "Point",
        "coordinates": [
          -99.4667,
          47.7833
        ]
      },
      "type": "Feature",
      "properties": {
        "hierarchy": [
          "tgn:2355862",
          "tgn:1000001",
          "tgn:7012149",
          "tgn:2001608",
          "tgn:7007705",
          "tgn:7029392"
        ],
        "placetype": [
          "aat:300008680"
        ],
        "id": 2355862,
        "name:xx": "Goose Lake"
      }
    },
    {
      "geometry": {
        "type": "Point",
        "coordinates": [
          -98.9667,
          47.8167
        ]
      },
      "type": "Feature",
      "properties": {
        "hierarchy": [
          "tgn:2355863",
          "tgn:1000001",
          "tgn:2001570",
          "tgn:7012149",
          "tgn:7007705",
          "tgn:7029392"
        ],
        "placetype": [
          "aat:300008680"
        ],
        "id": 2355863,
        "name:xx": "Goose Lake"
      }
    },
    {
      "geometry": {
        "type": "Point",
        "coordinates": [
          -99.9167,
          48.4167
        ]
      },
      "type": "Feature",
      "properties": {
        "hierarchy": [
          "tgn:2355864",
          "tgn:1000001",
          "tgn:2001591",
          "tgn:7012149",
          "tgn:7007705",
          "tgn:7029392"
        ],
        "placetype": [
          "aat:300008680"
        ],
        "id": 2355864,
        "name:xx": "Goose Lake"
      }
    },
    {
      "geometry": {
        "type": "Point",
        "coordinates": [
          -100,
          46.5333
        ]
      },
      "type": "Feature",
      "properties": {
        "hierarchy": [
          "tgn:2355865",
          "tgn:1000001",
          "tgn:2001571",
          "tgn:7012149",
          "tgn:7007705",
          "tgn:7029392"
        ],
        "placetype": [
          "aat:300008680"
        ],
        "id": 2355865,
        "name:xx": "Goose Lake"
      }
    },
    {
      "geometry": {
        "type": "Point",
        "coordinates": [
          -97.85,
          47.2167
        ]
      },
      "type": "Feature",
      "properties": {
        "hierarchy": [
          "tgn:2355866",
          "tgn:1000001",
          "tgn:7012149",
          "tgn:7007705",
          "tgn:7029392"
        ],
        "placetype": [
          "aat:300008680"
        ],
        "id": 2355866,
        "name:xx": "Goose Lake"
      }
    },
    {
      "geometry": {
        "type": "Point",
        "coordinates": [
          -100.7333,
          48.4167
        ]
      },
      "type": "Feature",
      "properties": {
        "hierarchy": [
          "tgn:2355867",
          "tgn:1000001",
          "tgn:2001581",
          "tgn:7012149",
          "tgn:7007705",
          "tgn:7029392"
        ],
        "placetype": [
          "aat:300008680"
        ],
        "id": 2355867,
        "name:xx": "Goose Lake"
      }
    },
    {
      "geometry": {
        "type": "Point",
        "coordinates": [
          -103.7,
          48.9833
        ]
      },
      "type": "Feature",
      "properties": {
        "hierarchy": [
          "tgn:2355868",
          "tgn:1000001",
          "tgn:2001568",
          "tgn:7012149",
          "tgn:7007705",
          "tgn:7029392"
        ],
        "placetype": [
          "aat:300008680"
        ],
        "id": 2355868,
        "name:xx": "Goose Lake"
      }
    },
    {
      "geometry": {
        "type": "Point",
        "coordinates": [
          -99.4667,
          46.1
        ]
      },
      "type": "Feature",
      "properties": {
        "hierarchy": [
          "tgn:2355869",
          "tgn:1000001",
          "tgn:2001582",
          "tgn:7012149",
          "tgn:7007705",
          "tgn:7029392"
        ],
        "placetype": [
          "aat:300008680"
        ],
        "id": 2355869,
        "name:xx": "Goose Lake"
      }
    }
  ]
}
