{
  "geometry": {
    "type": "Point",
    "coordinates": [
      -104.0833,
      44.6833
    ]
  },
  "type": "Feature",
  "properties": {
    "hierarchy": [
      "tgn:2676889",
      "tgn:1000001",
      "tgn:7012149",
      "tgn:7029392"
    ],
    "placetype": [
      "aat:300008706"
    ],
    "id": 2676889,
    "name:xx": "South Branch Grummit Canyon Creek"
  }
}
