{
  "type": "FeatureCollection",
  "features": [
    {
      "geometry": {
        "type": "Point",
        "coordinates": [
          -1.75,
          54.033333
        ]
      },
      "type": "Feature",
      "properties": {
        "hierarchy": [
          "tgn:7458700",
          "tgn:7002445",
          "tgn:1000003",
          "tgn:7008166",
          "tgn:7008591",
          "tgn:7029392"
        ],
        "placetype": [
          "aat:300008347"
        ],
        "name:en": "Padside",
        "id": 7458700
      }
    },
    {
      "geometry": {
        "type": "Point",
        "coordinates": [
          -2.55,
          53.4
        ]
      },
      "type": "Feature",
      "properties": {
        "hierarchy": [
          "tgn:7458702",
          "tgn:7002445",
          "tgn:1000003",
          "tgn:7026534",
          "tgn:7008591",
          "tgn:7029392"
        ],
        "placetype": [
          "aat:300008347"
        ],
        "name:en": "Padgate",
        "id": 7458702
      }
    },
    {
      "geometry": {
        "type": "Point",
        "coordinates": [
          -3.083333,
          53.15
        ]
      },
      "type": "Feature",
      "properties": {
        "hierarchy": [
          "tgn:7458703",
          "tgn:7002443",
          "tgn:7026278",
          "tgn:1000003",
          "tgn:7008591",
          "tgn:7029392"
        ],
        "placetype": [
          "aat:300008347"
        ],
        "name:en": "Padeswood",
        "id": 7458703
      }
    },
    {
      "geometry": {
        "type": "Point",
        "coordinates": [
          1.133333,
          51.1
        ]
      },
      "type": "Feature",
      "properties": {
        "hierarchy": [
          "tgn:7458705",
          "tgn:7002445",
          "tgn:1000003",
          "tgn:7008153",
          "tgn:7008591",
          "tgn:7029392"
        ],
        "placetype": [
          "aat:300008347"
        ],
        "name:en": "Paddlesworth",
        "id": 7458705
      }
    },
    {
      "geometry": {
        "type": "Point",
        "coordinates": [
          -4.133333,
          53.116667
        ]
      },
      "type": "Feature",
      "properties": {
        "hierarchy": [
          "tgn:7458708",
          "tgn:7002443",
          "tgn:1000003",
          "tgn:7029493",
          "tgn:7008591",
          "tgn:7029392"
        ],
        "placetype": [
          "aat:300008680"
        ],
        "name:en": "Padarn, Llyn",
        "id": 7458708
      }
    },
    {
      "geometry": {
        "type": "Point",
        "coordinates": [
          -1.75,
          52.35
        ]
      },
      "type": "Feature",
      "properties": {
        "hierarchy": [
          "tgn:7458709",
          "tgn:7002445",
          "tgn:1000003",
          "tgn:7008178",
          "tgn:7008591",
          "tgn:7029392"
        ],
        "placetype": [
          "aat:300008347"
        ],
        "name:en": "Packwood",
        "id": 7458709
      }
    }
  ]
}
