{
  "geometry": {
    "type": "Point",
    "coordinates": [
      -89.8167,
      40.3667
    ]
  },
  "type": "Feature",
  "properties": {
    "hierarchy": [
      "tgn:2027880",
      "tgn:1000001",
      "tgn:7012149",
      "tgn:1002643",
      "tgn:7007251",
      "tgn:7029392"
    ],
    "placetype": [
      "aat:300008347"
    ],
    "id": 2027880,
    "name:xx": "Forest City"
  }
}
