{
  "geometry": {
    "type": "Point",
    "coordinates": [
      -112.3333,
      41.9833
    ]
  },
  "type": "Feature",
  "properties": {
    "hierarchy": [
      "tgn:2695013",
      "tgn:1000001",
      "tgn:2002102",
      "tgn:7012149",
      "tgn:7007827",
      "tgn:7029392"
    ],
    "placetype": [
      "aat:300008761"
    ],
    "id": 2695013,
    "name:xx": "Still Hollow"
  }
}
