{
  "geometry": {
    "type": "Point",
    "coordinates": [
      140.3167,
      -34.3333
    ]
  },
  "type": "Feature",
  "properties": {
    "hierarchy": [
      "tgn:1098665",
      "tgn:7000490",
      "tgn:1000006",
      "tgn:7001831",
      "tgn:7029392"
    ],
    "placetype": [
      "aat:300008347"
    ],
    "id": 1098665,
    "name:xx": "Yinkanie"
  }
}
