{
  "geometry": {
    "type": "Point",
    "coordinates": [
      -109.2333,
      38.4833
    ]
  },
  "type": "Feature",
  "properties": {
    "hierarchy": [
      "tgn:2382528",
      "tgn:1000001",
      "tgn:7012149",
      "tgn:7007827",
      "tgn:7029392"
    ],
    "placetype": [
      "aat:300008798"
    ],
    "id": 2382528,
    "name:xx": "Haystack Mountain"
  }
}
