{
  "geometry": {
    "type": "Point",
    "coordinates": [
      -92.6333,
      31.5167
    ]
  },
  "type": "Feature",
  "properties": {
    "hierarchy": [
      "tgn:2476580",
      "tgn:1000001",
      "tgn:7012149",
      "tgn:2000875",
      "tgn:7007256",
      "tgn:7029392"
    ],
    "placetype": [
      "aat:300000390"
    ],
    "id": 2476580,
    "name:xx": "Lutesville Gravel Pit"
  }
}
