{
  "geometry": {
    "type": "Point",
    "coordinates": [
      -96.3333,
      31.15
    ]
  },
  "type": "Feature",
  "properties": {
    "hierarchy": [
      "tgn:2479611",
      "tgn:1000001",
      "tgn:7012149",
      "tgn:1002830",
      "tgn:7007826",
      "tgn:7029392"
    ],
    "placetype": [
      "aat:300008699"
    ],
    "id": 2479611,
    "name:xx": "Lake Branch"
  }
}
