{
  "geometry": {
    "type": "Point",
    "coordinates": [
      -74.4667,
      42.25
    ]
  },
  "type": "Feature",
  "properties": {
    "hierarchy": [
      "tgn:2159056",
      "tgn:1000001",
      "tgn:7012149",
      "tgn:7007568",
      "tgn:7029392"
    ],
    "placetype": [
      "aat:300008761"
    ],
    "id": 2159056,
    "name:xx": "Bed Hollow"
  }
}
