{
  "geometry": {
    "type": "Point",
    "coordinates": [
      -105.05,
      36.4667
    ]
  },
  "type": "Feature",
  "properties": {
    "hierarchy": [
      "tgn:2239906",
      "tgn:1000001",
      "tgn:2001432",
      "tgn:7012149",
      "tgn:7007566",
      "tgn:7029392"
    ],
    "placetype": [
      "aat:300006191"
    ],
    "id": 2239906,
    "name:xx": "Cimarroncito Reservoir"
  }
}
