{
  "geometry": {
    "type": "Point",
    "coordinates": [
      -131.5333,
      55.3333
    ]
  },
  "type": "Feature",
  "properties": {
    "hierarchy": [
      "tgn:2768755",
      "tgn:7006450",
      "tgn:1000001",
      "tgn:2124076",
      "tgn:7012149",
      "tgn:7029392"
    ],
    "placetype": [
      "aat:300008680"
    ],
    "id": 2768755,
    "name:xx": "Whitman Lake"
  }
}
