{
  "geometry": {
    "type": "Point",
    "coordinates": [
      -90.65,
      43.0333
    ]
  },
  "type": "Feature",
  "properties": {
    "hierarchy": [
      "tgn:2268184",
      "tgn:1000001",
      "tgn:2002324",
      "tgn:7012149",
      "tgn:7007922",
      "tgn:7029392"
    ],
    "placetype": [
      "aat:300008706"
    ],
    "id": 2268184,
    "name:xx": "Crooked Creek"
  }
}
