{
  "geometry": {
    "type": "Point",
    "coordinates": [
      -99.3375,
      20.023611
    ]
  },
  "type": "Feature",
  "properties": {
    "hierarchy": [
      "tgn:7412688",
      "tgn:7005587",
      "tgn:1000001",
      "tgn:7005560",
      "tgn:7029392"
    ],
    "placetype": [
      "aat:300007783"
    ],
    "id": 7412688,
    "name:es": "Estación Tolteca"
  }
}
