{
  "geometry": {
    "type": "Point",
    "coordinates": [
      -118.4333,
      34.1833
    ]
  },
  "type": "Feature",
  "properties": {
    "hierarchy": [
      "tgn:7014708",
      "tgn:1000001",
      "tgn:7012149",
      "tgn:7007157",
      "tgn:7023900",
      "tgn:1002608",
      "tgn:7029392"
    ],
    "placetype": [
      "aat:300000745"
    ],
    "id": 7014708,
    "name:xx": "Van Nuys"
  }
}
