{
  "geometry": {
    "type": "Point",
    "coordinates": [
      -122.85,
      41.0333
    ]
  },
  "type": "Feature",
  "properties": {
    "hierarchy": [
      "tgn:2336140",
      "tgn:1000001",
      "tgn:7012149",
      "tgn:7007157",
      "tgn:2000191",
      "tgn:7029392"
    ],
    "placetype": [
      "aat:300008680"
    ],
    "id": 2336140,
    "name:xx": "Foster Lake"
  }
}
