{
  "geometry": {
    "type": "Point",
    "coordinates": [
      61.75,
      51.95
    ]
  },
  "type": "Feature",
  "properties": {
    "hierarchy": [
      "tgn:1054969",
      "tgn:1000004",
      "tgn:7012922",
      "tgn:7014786",
      "tgn:7029392"
    ],
    "placetype": [
      "aat:300008347"
    ],
    "id": 1054969,
    "name:xx": "Kamyshnyy"
  }
}
