{
  "geometry": {
    "type": "Point",
    "coordinates": [
      -83.5667,
      36.7167
    ]
  },
  "type": "Feature",
  "properties": {
    "hierarchy": [
      "tgn:2639758",
      "tgn:1000001",
      "tgn:2000769",
      "tgn:7012149",
      "tgn:7007255",
      "tgn:7029392"
    ],
    "placetype": [
      "aat:300008699"
    ],
    "id": 2639758,
    "name:xx": "Sam Low Branch"
  }
}
