{
  "type": "FeatureCollection",
  "features": [
    {
      "geometry": {
        "type": "Point",
        "coordinates": [
          -3,
          53.4
        ]
      },
      "type": "Feature",
      "properties": {
        "hierarchy": [
          "tgn:1101325",
          "tgn:1003614",
          "tgn:7002445",
          "tgn:1000003",
          "tgn:7029504",
          "tgn:7008591",
          "tgn:7029392"
        ],
        "placetype": [
          "aat:300007899"
        ],
        "id": 1101325,
        "name:xx": "Mersey Tunnel"
      }
    },
    {
      "geometry": {
        "type": "Point",
        "coordinates": [
          6.8833,
          45.8333
        ]
      },
      "type": "Feature",
      "properties": {
        "hierarchy": [
          "tgn:1101326",
          "tgn:1000003",
          "tgn:7029392"
        ],
        "placetype": [
          "aat:300007899"
        ],
        "name:fr": "Mont Blanc, Tunnel du",
        "id": 1101326
      }
    },
    {
      "geometry": {
        "type": "Point",
        "coordinates": [
          13.25,
          41.3333
        ]
      },
      "type": "Feature",
      "properties": {
        "hierarchy": [
          "tgn:1101328",
          "tgn:7003136",
          "tgn:1000003",
          "tgn:7003080",
          "tgn:1000080",
          "tgn:7029392"
        ],
        "placetype": [
          "aat:300007899"
        ],
        "id": 1101328,
        "name:xx": "Mont'Orso, Galleria di"
      }
    },
    {
      "geometry": {
        "type": "Point",
        "coordinates": [
          11.266667,
          44.35
        ]
      },
      "type": "Feature",
      "properties": {
        "hierarchy": [
          "tgn:1101329",
          "tgn:7003127",
          "tgn:1000003",
          "tgn:7008516",
          "tgn:1000080",
          "tgn:7029392"
        ],
        "placetype": [
          "aat:300007899"
        ],
        "id": 1101329,
        "name:xx": "Monte Adone, Galleria di"
      }
    }
  ]
}
