{
  "geometry": {
    "type": "Point",
    "coordinates": [
      -75.5333,
      41.6167
    ]
  },
  "type": "Feature",
  "properties": {
    "hierarchy": [
      "tgn:2540615",
      "tgn:1000001",
      "tgn:7012149",
      "tgn:1002564",
      "tgn:7007710",
      "tgn:7029392"
    ],
    "placetype": [
      "aat:300008680"
    ],
    "id": 2540615,
    "name:xx": "Newton Lake"
  }
}
