{
  "type": "FeatureCollection",
  "features": [
    {
      "geometry": {
        "type": "Point",
        "coordinates": [
          -91.3167,
          44
        ]
      },
      "type": "Feature",
      "properties": {
        "hierarchy": [
          "tgn:2355890",
          "tgn:1000001",
          "tgn:7012149",
          "tgn:2002331",
          "tgn:7007922",
          "tgn:7029392"
        ],
        "placetype": [
          "aat:300008680"
        ],
        "id": 2355890,
        "name:xx": "Goose Lake"
      }
    },
    {
      "geometry": {
        "type": "Point",
        "coordinates": [
          -91.35,
          45.3
        ]
      },
      "type": "Feature",
      "properties": {
        "hierarchy": [
          "tgn:2355891",
          "tgn:1000001",
          "tgn:7012149",
          "tgn:2002350",
          "tgn:7007922",
          "tgn:7029392"
        ],
        "placetype": [
          "aat:300008680"
        ],
        "id": 2355891,
        "name:xx": "Goose Lake"
      }
    },
    {
      "geometry": {
        "type": "Point",
        "coordinates": [
          -92.45,
          45.3
        ]
      },
      "type": "Feature",
      "properties": {
        "hierarchy": [
          "tgn:2355892",
          "tgn:1000001",
          "tgn:7012149",
          "tgn:2002346",
          "tgn:7007922",
          "tgn:7029392"
        ],
        "placetype": [
          "aat:300008680"
        ],
        "id": 2355892,
        "name:xx": "Goose Lake"
      }
    },
    {
      "geometry": {
        "type": "Point",
        "coordinates": [
          -91.6333,
          45.5833
        ]
      },
      "type": "Feature",
      "properties": {
        "hierarchy": [
          "tgn:2355893",
          "tgn:2002307",
          "tgn:1000001",
          "tgn:7012149",
          "tgn:7007922",
          "tgn:7029392"
        ],
        "placetype": [
          "aat:300008680"
        ],
        "id": 2355893,
        "name:xx": "Goose Lake"
      }
    },
    {
      "geometry": {
        "type": "Point",
        "coordinates": [
          -91.9333,
          45.85
        ]
      },
      "type": "Feature",
      "properties": {
        "hierarchy": [
          "tgn:2355894",
          "tgn:1000001",
          "tgn:7012149",
          "tgn:2002360",
          "tgn:7007922",
          "tgn:7029392"
        ],
        "placetype": [
          "aat:300008680"
        ],
        "id": 2355894,
        "name:xx": "Goose Lake"
      }
    },
    {
      "geometry": {
        "type": "Point",
        "coordinates": [
          -91.1,
          45.95
        ]
      },
      "type": "Feature",
      "properties": {
        "hierarchy": [
          "tgn:2355895",
          "tgn:1000001",
          "tgn:7012149",
          "tgn:2002353",
          "tgn:7007922",
          "tgn:7029392"
        ],
        "placetype": [
          "aat:300008680"
        ],
        "id": 2355895,
        "name:xx": "Goose Lake"
      }
    },
    {
      "geometry": {
        "type": "Point",
        "coordinates": [
          -92.0667,
          45.9667
        ]
      },
      "type": "Feature",
      "properties": {
        "hierarchy": [
          "tgn:2355896",
          "tgn:1000001",
          "tgn:2002311",
          "tgn:7012149",
          "tgn:7007922",
          "tgn:7029392"
        ],
        "placetype": [
          "aat:300008680"
        ],
        "id": 2355896,
        "name:xx": "Goose Lake"
      }
    },
    {
      "geometry": {
        "type": "Point",
        "coordinates": [
          -90.0667,
          46.0333
        ]
      },
      "type": "Feature",
      "properties": {
        "hierarchy": [
          "tgn:2355897",
          "tgn:1000001",
          "tgn:7012149",
          "tgn:2002327",
          "tgn:7007922",
          "tgn:7029392"
        ],
        "placetype": [
          "aat:300008680"
        ],
        "id": 2355897,
        "name:xx": "Goose Lake"
      }
    },
    {
      "geometry": {
        "type": "Point",
        "coordinates": [
          -91.6,
          46.2167
        ]
      },
      "type": "Feature",
      "properties": {
        "hierarchy": [
          "tgn:2355898",
          "tgn:1000001",
          "tgn:2002318",
          "tgn:7012149",
          "tgn:7007922",
          "tgn:7029392"
        ],
        "placetype": [
          "aat:300008680"
        ],
        "id": 2355898,
        "name:xx": "Goose Lake"
      }
    },
    {
      "geometry": {
        "type": "Point",
        "coordinates": [
          -89.5,
          44.15
        ]
      },
      "type": "Feature",
      "properties": {
        "hierarchy": [
          "tgn:2355899",
          "tgn:1000001",
          "tgn:7012149",
          "tgn:2002362",
          "tgn:7007922",
          "tgn:7029392"
        ],
        "placetype": [
          "aat:300008905"
        ],
        "id": 2355899,
        "name:xx": "Goose Lake"
      }
    }
  ]
}
