{
  "type": "FeatureCollection",
  "features": [
    {
      "geometry": {
        "type": "Point",
        "coordinates": [
          12.238,
          -4.934
        ]
      },
      "type": "Feature",
      "properties": {
        "hierarchy": [
          "tgn:1000820",
          "tgn:7001242",
          "tgn:1000149",
          "tgn:7029392"
        ],
        "placetype": [
          "aat:300387064",
          "aat:300000774"
        ],
        "id": 1000820,
        "name:xx": "Cabinda"
      }
    },
    {
      "geometry": {
        "type": "Point",
        "coordinates": [
          38.9833,
          -12.5667
        ]
      },
      "type": "Feature",
      "properties": {
        "hierarchy": [
          "tgn:1000821",
          "tgn:7001242",
          "tgn:1000180",
          "tgn:7029392"
        ],
        "placetype": [
          "aat:300387064",
          "aat:300000774"
        ],
        "id": 1000821,
        "name:xx": "Cabo Delgado"
      }
    },
    {
      "geometry": {
        "type": "Point",
        "coordinates": [
          26,
          -22
        ]
      },
      "type": "Feature",
      "properties": {
        "hierarchy": [
          "tgn:1000824",
          "tgn:7001242",
          "tgn:1000150",
          "tgn:7029392"
        ],
        "placetype": [
          "aat:300387064",
          "aat:300387081"
        ],
        "id": 1000824,
        "name:xx": "Central"
      }
    },
    {
      "geometry": {
        "type": "Point",
        "coordinates": [
          32,
          0.1667
        ]
      },
      "type": "Feature",
      "properties": {
        "hierarchy": [
          "tgn:1000825",
          "tgn:7001242",
          "tgn:1000206",
          "tgn:7029392"
        ],
        "placetype": [
          "aat:300387064",
          "aat:300000774"
        ],
        "id": 1000825,
        "name:xx": "Central"
      }
    },
    {
      "geometry": {
        "type": "Point",
        "coordinates": [
          147,
          -9
        ]
      },
      "type": "Feature",
      "properties": {
        "hierarchy": [
          "tgn:1000826",
          "tgn:7006160",
          "tgn:1000006",
          "tgn:7029392"
        ],
        "placetype": [
          "aat:300387064",
          "aat:300000774"
        ],
        "id": 1000826,
        "name:xx": "Central"
      }
    },
    {
      "geometry": {
        "type": "Point",
        "coordinates": [
          178.5,
          -18
        ]
      },
      "type": "Feature",
      "properties": {
        "hierarchy": [
          "tgn:1000827",
          "tgn:7000493",
          "tgn:1000006",
          "tgn:7029392"
        ],
        "placetype": [
          "aat:300387064",
          "aat:300387082"
        ],
        "id": 1000827,
        "name:xx": "Central"
      }
    },
    {
      "geometry": {
        "type": "Point",
        "coordinates": [
          145,
          -6.0833
        ]
      },
      "type": "Feature",
      "properties": {
        "hierarchy": [
          "tgn:1000828",
          "tgn:7006160",
          "tgn:1000006",
          "tgn:7029392"
        ],
        "placetype": [
          "aat:300387064",
          "aat:300000774"
        ],
        "id": 1000828,
        "name:xx": "Chimbu"
      }
    },
    {
      "geometry": {
        "type": "Point",
        "coordinates": [
          24.75,
          -18.5
        ]
      },
      "type": "Feature",
      "properties": {
        "hierarchy": [
          "tgn:1000829",
          "tgn:7001242",
          "tgn:1000150",
          "tgn:7029392"
        ],
        "placetype": [
          "aat:300387064",
          "aat:300387081"
        ],
        "id": 1000829,
        "name:xx": "Chobe"
      }
    }
  ]
}
