{
  "geometry": {
    "type": "Point",
    "coordinates": [
      35.4833,
      8.1667
    ]
  },
  "type": "Feature",
  "properties": {
    "hierarchy": [
      "tgn:1089828",
      "tgn:7001242",
      "tgn:1001308",
      "tgn:7000489",
      "tgn:7029392"
    ],
    "placetype": [
      "aat:300008347",
      "aat:300387220"
    ],
    "id": 1089828,
    "name:xx": "Gorē"
  }
}
