{
  "geometry": {
    "type": "Point",
    "coordinates": [
      -76.2167,
      41.5333
    ]
  },
  "type": "Feature",
  "properties": {
    "hierarchy": [
      "tgn:2631544",
      "tgn:1000001",
      "tgn:7012149",
      "tgn:1003041",
      "tgn:7007710",
      "tgn:7029392"
    ],
    "placetype": [
      "aat:300008798"
    ],
    "id": 2631544,
    "name:xx": "Round Top"
  }
}
