{
  "geometry": {
    "type": "Point",
    "coordinates": [
      31.345162,
      30.11309
    ]
  },
  "type": "Feature",
  "properties": {
    "hierarchy": [
      "tgn:7532414",
      "tgn:7001242",
      "tgn:7016833",
      "tgn:1001091",
      "tgn:7029392"
    ],
    "placetype": [
      "aat:300006676"
    ],
    "id": 7532414,
    "name:xx": "Mustashfá al Ḩijāz"
  }
}
