{
  "geometry": {
    "type": "Point",
    "coordinates": [
      106.0667,
      30.1333
    ]
  },
  "type": "Feature",
  "properties": {
    "hierarchy": [
      "tgn:1072059",
      "tgn:1000004",
      "tgn:7002087",
      "tgn:1000111",
      "tgn:7029392"
    ],
    "placetype": [
      "aat:300008347"
    ],
    "id": 1072059,
    "name:xx": "Taihe"
  }
}
