{
  "geometry": {
    "type": "Point",
    "coordinates": [
      -120.8333,
      47.8833
    ]
  },
  "type": "Feature",
  "properties": {
    "hierarchy": [
      "tgn:2736130",
      "tgn:1000001",
      "tgn:1002260",
      "tgn:7012149",
      "tgn:7007920",
      "tgn:7029392"
    ],
    "placetype": [
      "aat:300008706"
    ],
    "id": 2736130,
    "name:xx": "Twin Lakes Creek"
  }
}
