{
  "type": "FeatureCollection",
  "features": [
    {
      "geometry": {
        "type": "Point",
        "coordinates": [
          -78.05,
          35
        ]
      },
      "type": "Feature",
      "properties": {
        "hierarchy": [
          "tgn:2663810",
          "tgn:1000001",
          "tgn:7012149",
          "tgn:2001491",
          "tgn:7007709",
          "tgn:7029392"
        ],
        "placetype": [
          "aat:300008680"
        ],
        "id": 2663810,
        "name:xx": "Silver Lake"
      }
    },
    {
      "geometry": {
        "type": "Point",
        "coordinates": [
          -75.9833,
          35.1
        ]
      },
      "type": "Feature",
      "properties": {
        "hierarchy": [
          "tgn:2663811",
          "tgn:1000001",
          "tgn:7012149",
          "tgn:2001506",
          "tgn:7007709",
          "tgn:7029392"
        ],
        "placetype": [
          "aat:300008680"
        ],
        "id": 2663811,
        "name:xx": "Silver Lake"
      }
    },
    {
      "geometry": {
        "type": "Point",
        "coordinates": [
          -78.7167,
          35.7333
        ]
      },
      "type": "Feature",
      "properties": {
        "hierarchy": [
          "tgn:2663812",
          "tgn:1000001",
          "tgn:7012149",
          "tgn:2001548",
          "tgn:7007709",
          "tgn:7029392"
        ],
        "placetype": [
          "aat:300006191"
        ],
        "id": 2663812,
        "name:xx": "Silver Lake"
      }
    },
    {
      "geometry": {
        "type": "Point",
        "coordinates": [
          -82.6167,
          35.3667
        ]
      },
      "type": "Feature",
      "properties": {
        "hierarchy": [
          "tgn:2663813",
          "tgn:1000001",
          "tgn:7012149",
          "tgn:2001504",
          "tgn:7007709",
          "tgn:7029392"
        ],
        "placetype": [
          "aat:300006191"
        ],
        "id": 2663813,
        "name:xx": "Silver Lake"
      }
    },
    {
      "geometry": {
        "type": "Point",
        "coordinates": [
          -77.95,
          35.8
        ]
      },
      "type": "Feature",
      "properties": {
        "hierarchy": [
          "tgn:2663814",
          "tgn:1000001",
          "tgn:7012149",
          "tgn:2001554",
          "tgn:7007709",
          "tgn:7029392"
        ],
        "placetype": [
          "aat:300006191"
        ],
        "id": 2663814,
        "name:xx": "Silver Lake"
      }
    },
    {
      "geometry": {
        "type": "Point",
        "coordinates": [
          -78.0333,
          34.0333
        ]
      },
      "type": "Feature",
      "properties": {
        "hierarchy": [
          "tgn:2663815",
          "tgn:1000001",
          "tgn:2001472",
          "tgn:7012149",
          "tgn:7007709",
          "tgn:7029392"
        ],
        "placetype": [
          "aat:300008680"
        ],
        "id": 2663815,
        "name:xx": "Silver Lake"
      }
    },
    {
      "geometry": {
        "type": "Point",
        "coordinates": [
          -99.7833,
          47.3667
        ]
      },
      "type": "Feature",
      "properties": {
        "hierarchy": [
          "tgn:2663816",
          "tgn:1000001",
          "tgn:7012149",
          "tgn:2001608",
          "tgn:7007705",
          "tgn:7029392"
        ],
        "placetype": [
          "aat:300008680"
        ],
        "id": 2663816,
        "name:xx": "Silver Lake"
      }
    },
    {
      "geometry": {
        "type": "Point",
        "coordinates": [
          -97.5667,
          46.0167
        ]
      },
      "type": "Feature",
      "properties": {
        "hierarchy": [
          "tgn:2663817",
          "tgn:1000001",
          "tgn:2001597",
          "tgn:7012149",
          "tgn:7007705",
          "tgn:7029392"
        ],
        "placetype": [
          "aat:300006191"
        ],
        "id": 2663817,
        "name:xx": "Silver Lake"
      }
    },
    {
      "geometry": {
        "type": "Point",
        "coordinates": [
          -99.25,
          48.1833
        ]
      },
      "type": "Feature",
      "properties": {
        "hierarchy": [
          "tgn:2663818",
          "tgn:2001559",
          "tgn:1000001",
          "tgn:7012149",
          "tgn:7007705",
          "tgn:7029392"
        ],
        "placetype": [
          "aat:300008680"
        ],
        "id": 2663818,
        "name:xx": "Silver Lake"
      }
    },
    {
      "geometry": {
        "type": "Point",
        "coordinates": [
          -84.7833,
          39.85
        ]
      },
      "type": "Feature",
      "properties": {
        "hierarchy": [
          "tgn:2663819",
          "tgn:1000001",
          "tgn:7012149",
          "tgn:1002802",
          "tgn:7007706",
          "tgn:7029392"
        ],
        "placetype": [
          "aat:300008680"
        ],
        "id": 2663819,
        "name:xx": "Silver Lake"
      }
    }
  ]
}
