{
  "geometry": {
    "type": "Point",
    "coordinates": [
      -91.0667,
      38.1667
    ]
  },
  "type": "Feature",
  "properties": {
    "hierarchy": [
      "tgn:2373601",
      "tgn:1000001",
      "tgn:7012149",
      "tgn:2001254",
      "tgn:7007523",
      "tgn:7029392"
    ],
    "placetype": [
      "aat:300008746"
    ],
    "id": 2373601,
    "name:xx": "Hamilton Cave"
  }
}
