{
  "type": "FeatureCollection",
  "features": [
    {
      "geometry": {
        "type": "Point",
        "coordinates": [
          -99.9833,
          34.25
        ]
      },
      "type": "Feature",
      "properties": {
        "hierarchy": [
          "tgn:2242800",
          "tgn:1000001",
          "tgn:7012149",
          "tgn:2001998",
          "tgn:7007826",
          "tgn:7029392"
        ],
        "placetype": [
          "aat:300008706"
        ],
        "id": 2242800,
        "name:xx": "Clear Creek"
      }
    },
    {
      "geometry": {
        "type": "Point",
        "coordinates": [
          -96.2333,
          29.8333
        ]
      },
      "type": "Feature",
      "properties": {
        "hierarchy": [
          "tgn:2242801",
          "tgn:1000001",
          "tgn:1002161",
          "tgn:7012149",
          "tgn:7007826",
          "tgn:7029392"
        ],
        "placetype": [
          "aat:300008706"
        ],
        "id": 2242801,
        "name:xx": "Clear Creek"
      }
    },
    {
      "geometry": {
        "type": "Point",
        "coordinates": [
          -96.7833,
          30.0167
        ]
      },
      "type": "Feature",
      "properties": {
        "hierarchy": [
          "tgn:2242802",
          "tgn:1000001",
          "tgn:7012149",
          "tgn:1002374",
          "tgn:7007826",
          "tgn:7029392"
        ],
        "placetype": [
          "aat:300008706"
        ],
        "id": 2242802,
        "name:xx": "Clear Creek"
      }
    },
    {
      "geometry": {
        "type": "Point",
        "coordinates": [
          -97.6333,
          31.5167
        ]
      },
      "type": "Feature",
      "properties": {
        "hierarchy": [
          "tgn:2242803",
          "tgn:1000001",
          "tgn:7012149",
          "tgn:1002303",
          "tgn:7007826",
          "tgn:7029392"
        ],
        "placetype": [
          "aat:300008706"
        ],
        "id": 2242803,
        "name:xx": "Clear Creek"
      }
    },
    {
      "geometry": {
        "type": "Point",
        "coordinates": [
          -110.9167,
          37.2667
        ]
      },
      "type": "Feature",
      "properties": {
        "hierarchy": [
          "tgn:2242804",
          "tgn:1000001",
          "tgn:7012149",
          "tgn:2002113",
          "tgn:7007827",
          "tgn:7029392"
        ],
        "placetype": [
          "aat:300008706"
        ],
        "id": 2242804,
        "name:xx": "Clear Creek"
      }
    },
    {
      "geometry": {
        "type": "Point",
        "coordinates": [
          -112.7333,
          37.7333
        ]
      },
      "type": "Feature",
      "properties": {
        "hierarchy": [
          "tgn:2242805",
          "tgn:1000001",
          "tgn:7012149",
          "tgn:7007827",
          "tgn:7029392"
        ],
        "placetype": [
          "aat:300008706"
        ],
        "id": 2242805,
        "name:xx": "Clear Creek"
      }
    },
    {
      "geometry": {
        "type": "Point",
        "coordinates": [
          -111.6333,
          39.0333
        ]
      },
      "type": "Feature",
      "properties": {
        "hierarchy": [
          "tgn:2242806",
          "tgn:1000001",
          "tgn:7012149",
          "tgn:2002120",
          "tgn:7007827",
          "tgn:7029392"
        ],
        "placetype": [
          "aat:300008706"
        ],
        "id": 2242806,
        "name:xx": "Clear Creek"
      }
    },
    {
      "geometry": {
        "type": "Point",
        "coordinates": [
          -111.2333,
          39.9167
        ]
      },
      "type": "Feature",
      "properties": {
        "hierarchy": [
          "tgn:2242807",
          "tgn:1000001",
          "tgn:7012149",
          "tgn:2002125",
          "tgn:7007827",
          "tgn:7029392"
        ],
        "placetype": [
          "aat:300008706"
        ],
        "id": 2242807,
        "name:xx": "Clear Creek"
      }
    },
    {
      "geometry": {
        "type": "Point",
        "coordinates": [
          -111.65,
          40.8167
        ]
      },
      "type": "Feature",
      "properties": {
        "hierarchy": [
          "tgn:2242808",
          "tgn:1000001",
          "tgn:7012149",
          "tgn:2002118",
          "tgn:7007827",
          "tgn:7029392"
        ],
        "placetype": [
          "aat:300008706"
        ],
        "id": 2242808,
        "name:xx": "Clear Creek"
      }
    },
    {
      "geometry": {
        "type": "Point",
        "coordinates": [
          -112.4833,
          38.5833
        ]
      },
      "type": "Feature",
      "properties": {
        "hierarchy": [
          "tgn:2242809",
          "tgn:1000001",
          "tgn:7012149",
          "tgn:2002121",
          "tgn:7007827",
          "tgn:7029392"
        ],
        "placetype": [
          "aat:300008706"
        ],
        "id": 2242809,
        "name:xx": "Clear Creek"
      }
    }
  ]
}
