{
  "geometry": {
    "type": "Point",
    "coordinates": [
      -83.5833,
      35.75
    ]
  },
  "type": "Feature",
  "properties": {
    "hierarchy": [
      "tgn:2162633",
      "tgn:1000001",
      "tgn:7012149",
      "tgn:2001914",
      "tgn:7007825",
      "tgn:7029392"
    ],
    "placetype": [
      "aat:300008798"
    ],
    "id": 2162633,
    "name:xx": "Bench Mountain"
  }
}
