{
  "geometry": {
    "type": "Point",
    "coordinates": [
      -104.65,
      38.6333
    ]
  },
  "type": "Feature",
  "properties": {
    "hierarchy": [
      "tgn:2215280",
      "tgn:1000001",
      "tgn:7012149",
      "tgn:7014097",
      "tgn:7007158",
      "tgn:7029392"
    ],
    "placetype": [
      "aat:300006191"
    ],
    "id": 2215280,
    "name:xx": "Callahan Reservoir"
  }
}
