{
  "geometry": {
    "type": "Point",
    "coordinates": [
      -109.1167,
      33.3833
    ]
  },
  "type": "Feature",
  "properties": {
    "hierarchy": [
      "tgn:2787307",
      "tgn:1000001",
      "tgn:7006451",
      "tgn:2000095",
      "tgn:7012149",
      "tgn:7029392"
    ],
    "placetype": [
      "aat:300386845"
    ],
    "id": 2787307,
    "name:xx": "Zuni Basin"
  }
}
