{
  "geometry": {
    "type": "Point",
    "coordinates": [
      94.51834,
      26.324799
    ]
  },
  "type": "Feature",
  "properties": {
    "hierarchy": [
      "tgn:1076251",
      "tgn:1000004",
      "tgn:7000198",
      "tgn:1001905",
      "tgn:7029392"
    ],
    "placetype": [
      "aat:300008347"
    ],
    "name:en": "Mokokchūng",
    "id": 1076251
  }
}
