{
  "geometry": {
    "type": "Point",
    "coordinates": [
      -93.35,
      56.9167
    ]
  },
  "type": "Feature",
  "properties": {
    "hierarchy": [
      "tgn:1131673",
      "tgn:7005685",
      "tgn:1000001",
      "tgn:7005734",
      "tgn:7029392"
    ],
    "placetype": [
      "aat:300008707"
    ],
    "id": 1131673,
    "name:xx": "Weir"
  }
}
