{
  "geometry": {
    "type": "Point",
    "coordinates": [
      0.7333,
      14.5833
    ]
  },
  "type": "Feature",
  "properties": {
    "hierarchy": [
      "tgn:1091730",
      "tgn:7001242",
      "tgn:7032820",
      "tgn:1000181",
      "tgn:7029392"
    ],
    "placetype": [
      "aat:300008347"
    ],
    "id": 1091730,
    "name:xx": "Bankilaré"
  }
}
