{
  "geometry": {
    "type": "Point",
    "coordinates": [
      -80.4833,
      41.2167
    ]
  },
  "type": "Feature",
  "properties": {
    "hierarchy": [
      "tgn:7014500",
      "tgn:1000001",
      "tgn:7012149",
      "tgn:1002659",
      "tgn:7007710",
      "tgn:7029392"
    ],
    "placetype": [
      "aat:300008347",
      "aat:300008389"
    ],
    "id": 7014500,
    "name:xx": "Sharon"
  }
}
