{
  "geometry": {
    "type": "Point",
    "coordinates": [
      -83.8667,
      35.85
    ]
  },
  "type": "Feature",
  "properties": {
    "hierarchy": [
      "tgn:2611624",
      "tgn:1000001",
      "tgn:7012149",
      "tgn:2001883",
      "tgn:7007825",
      "tgn:7029392"
    ],
    "placetype": [
      "aat:300008798"
    ],
    "id": 2611624,
    "name:xx": "Red Mountain"
  }
}
