{
  "type": "FeatureCollection",
  "features": [
    {
      "geometry": {
        "type": "Point",
        "coordinates": [
          -91.2167,
          32.1
        ]
      },
      "type": "Feature",
      "properties": {
        "hierarchy": [
          "tgn:2177310",
          "tgn:1000001",
          "tgn:7012149",
          "tgn:2000907",
          "tgn:7007256",
          "tgn:7029392"
        ],
        "placetype": [
          "aat:300008707"
        ],
        "id": 2177310,
        "name:xx": "Black River"
      }
    },
    {
      "geometry": {
        "type": "Point",
        "coordinates": [
          -91.8,
          31.6167
        ]
      },
      "type": "Feature",
      "properties": {
        "hierarchy": [
          "tgn:2177311",
          "tgn:1000001",
          "tgn:7012149",
          "tgn:7007256",
          "tgn:7029392"
        ],
        "placetype": [
          "aat:300008707"
        ],
        "id": 2177311,
        "name:xx": "Black River"
      }
    },
    {
      "geometry": {
        "type": "Point",
        "coordinates": [
          -91.8,
          31.6167
        ]
      },
      "type": "Feature",
      "properties": {
        "hierarchy": [
          "tgn:2177312",
          "tgn:1000001",
          "tgn:2000868",
          "tgn:7012149",
          "tgn:7007256",
          "tgn:7029392"
        ],
        "placetype": [
          "aat:300008347"
        ],
        "id": 2177312,
        "name:xx": "Black River"
      }
    },
    {
      "geometry": {
        "type": "Point",
        "coordinates": [
          -96.4,
          48.1333
        ]
      },
      "type": "Feature",
      "properties": {
        "hierarchy": [
          "tgn:2177313",
          "tgn:1000001",
          "tgn:7012149",
          "tgn:7007521",
          "tgn:7029392"
        ],
        "placetype": [
          "aat:300008707"
        ],
        "id": 2177313,
        "name:xx": "Black River"
      }
    },
    {
      "geometry": {
        "type": "Point",
        "coordinates": [
          -94.2,
          48.3833
        ]
      },
      "type": "Feature",
      "properties": {
        "hierarchy": [
          "tgn:2177314",
          "tgn:1000001",
          "tgn:7012149",
          "tgn:2001034",
          "tgn:7007521",
          "tgn:7029392"
        ],
        "placetype": [
          "aat:300008707"
        ],
        "id": 2177314,
        "name:xx": "Black River"
      }
    },
    {
      "geometry": {
        "type": "Point",
        "coordinates": [
          -82.1,
          41.3667
        ]
      },
      "type": "Feature",
      "properties": {
        "hierarchy": [
          "tgn:2177315",
          "tgn:1000001",
          "tgn:7012149",
          "tgn:1002607",
          "tgn:7007706",
          "tgn:7029392"
        ],
        "placetype": [
          "aat:300008707"
        ],
        "id": 2177315,
        "name:xx": "Black River"
      }
    },
    {
      "geometry": {
        "type": "Point",
        "coordinates": [
          -75.4,
          40.5667
        ]
      },
      "type": "Feature",
      "properties": {
        "hierarchy": [
          "tgn:2177316",
          "tgn:1000001",
          "tgn:7012149",
          "tgn:7007710",
          "tgn:7029392"
        ],
        "placetype": [
          "aat:300008707"
        ],
        "id": 2177316,
        "name:xx": "Black River"
      }
    },
    {
      "geometry": {
        "type": "Point",
        "coordinates": [
          -92.1333,
          46.55
        ]
      },
      "type": "Feature",
      "properties": {
        "hierarchy": [
          "tgn:2177317",
          "tgn:1000001",
          "tgn:2002318",
          "tgn:7012149",
          "tgn:7007922",
          "tgn:7029392"
        ],
        "placetype": [
          "aat:300008347"
        ],
        "id": 2177317,
        "name:xx": "Black River"
      }
    },
    {
      "geometry": {
        "type": "Point",
        "coordinates": [
          -82.4333,
          43.0167
        ]
      },
      "type": "Feature",
      "properties": {
        "hierarchy": [
          "tgn:2177318",
          "tgn:1000001",
          "tgn:7012149",
          "tgn:7016056",
          "tgn:7007520",
          "tgn:7029392"
        ],
        "placetype": [
          "aat:300006075"
        ],
        "id": 2177318,
        "name:xx": "Black River Canal"
      }
    },
    {
      "geometry": {
        "type": "Point",
        "coordinates": [
          -75.4333,
          43.2333
        ]
      },
      "type": "Feature",
      "properties": {
        "hierarchy": [
          "tgn:2177319",
          "tgn:1000001",
          "tgn:7012149",
          "tgn:7014287",
          "tgn:7007568",
          "tgn:7029392"
        ],
        "placetype": [
          "aat:300006075"
        ],
        "id": 2177319,
        "name:xx": "Black River Canal"
      }
    }
  ]
}
