{
  "geometry": {
    "type": "Point",
    "coordinates": [
      16.4333,
      47.5833
    ]
  },
  "type": "Feature",
  "properties": {
    "hierarchy": [
      "tgn:1026224",
      "tgn:7003023",
      "tgn:1000003",
      "tgn:1000062",
      "tgn:7029392"
    ],
    "placetype": [
      "aat:300008347"
    ],
    "id": 1026224,
    "name:xx": "Weppersdorf"
  }
}
