{
  "geometry": {
    "type": "Point",
    "coordinates": [
      121.5835,
      25.0715
    ]
  },
  "type": "Feature",
  "properties": {
    "hierarchy": [
      "tgn:7474852",
      "tgn:1000004",
      "tgn:1000959",
      "tgn:1000141",
      "tgn:7029392"
    ],
    "placetype": [
      "aat:300387173"
    ],
    "id": 7474852,
    "name:xx": "Yongtai Li"
  }
}
