{
  "geometry": {
    "type": "Point",
    "coordinates": [
      -114.7167,
      46.3667
    ]
  },
  "type": "Feature",
  "properties": {
    "hierarchy": [
      "tgn:2706201",
      "tgn:1000001",
      "tgn:7012149",
      "tgn:2000476",
      "tgn:7007250",
      "tgn:7029392"
    ],
    "placetype": [
      "aat:300008706"
    ],
    "id": 2706201,
    "name:xx": "Swamp Creek"
  }
}
