{
  "geometry": {
    "type": "Point",
    "coordinates": [
      86.20038,
      22.769184
    ]
  },
  "type": "Feature",
  "properties": {
    "hierarchy": [
      "tgn:6005841",
      "tgn:1000004",
      "tgn:7000198",
      "tgn:7031783",
      "tgn:7029392"
    ],
    "placetype": [
      "aat:300007783"
    ],
    "name:en": "Tātānagar",
    "id": 6005841
  }
}
