{
  "geometry": {
    "type": "Point",
    "coordinates": [
      78.662085,
      27.02953
    ]
  },
  "type": "Feature",
  "properties": {
    "hierarchy": [
      "tgn:7574838",
      "tgn:1000004",
      "tgn:7000198",
      "tgn:7016722",
      "tgn:7029392"
    ],
    "placetype": [
      "aat:300007783"
    ],
    "name:en": "Kaurāra",
    "id": 7574838
  }
}
