{
  "geometry": {
    "type": "Point",
    "coordinates": [
      -84.0833,
      30.5833
    ]
  },
  "type": "Feature",
  "properties": {
    "hierarchy": [
      "tgn:2642594",
      "tgn:1000001",
      "tgn:7012149",
      "tgn:2000276",
      "tgn:7007240",
      "tgn:7029392"
    ],
    "placetype": [
      "aat:300008680"
    ],
    "id": 2642594,
    "name:xx": "Sanders Hammock Pond"
  }
}
