{
  "geometry": {
    "type": "Point",
    "coordinates": [
      120.5167,
      27.7167
    ]
  },
  "type": "Feature",
  "properties": {
    "hierarchy": [
      "tgn:1070892",
      "tgn:1000004",
      "tgn:7002076",
      "tgn:1000111",
      "tgn:7029392"
    ],
    "placetype": [
      "aat:300008347"
    ],
    "id": 1070892,
    "name:xx": "Pingyang"
  }
}
