{
  "geometry": {
    "type": "Point",
    "coordinates": [
      -82.7333,
      39.7667
    ]
  },
  "type": "Feature",
  "properties": {
    "hierarchy": [
      "tgn:2525518",
      "tgn:1000001",
      "tgn:7012149",
      "tgn:2001611",
      "tgn:7007706",
      "tgn:7029392"
    ],
    "placetype": [
      "aat:300006191"
    ],
    "id": 2525518,
    "name:xx": "Morse Pond"
  }
}
