{
  "geometry": {
    "type": "Point",
    "coordinates": [
      -93.5833,
      44.8667
    ]
  },
  "type": "Feature",
  "properties": {
    "hierarchy": [
      "tgn:2183346",
      "tgn:1000001",
      "tgn:7012149",
      "tgn:7007521",
      "tgn:7029392"
    ],
    "placetype": [
      "aat:300008706"
    ],
    "id": 2183346,
    "name:xx": "Bluff Creek"
  }
}
