{
  "geometry": {
    "type": "Point",
    "coordinates": [
      -75.15,
      41.7667
    ]
  },
  "type": "Feature",
  "properties": {
    "hierarchy": [
      "tgn:2395712",
      "tgn:1000001",
      "tgn:7012149",
      "tgn:1003008",
      "tgn:7007710",
      "tgn:7029392"
    ],
    "placetype": [
      "aat:300008706"
    ],
    "id": 2395712,
    "name:xx": "Hollister Creek"
  }
}
