{
  "type": "FeatureCollection",
  "features": [
    {
      "geometry": {
        "type": "Point",
        "coordinates": [
          -70.95,
          43
        ]
      },
      "type": "Feature",
      "properties": {
        "hierarchy": [
          "tgn:2626470",
          "tgn:1000001",
          "tgn:7014352",
          "tgn:7012149",
          "tgn:7007564",
          "tgn:7029392"
        ],
        "placetype": [
          "aat:300008699"
        ],
        "id": 2626470,
        "name:xx": "Rocky Hill Brook"
      }
    },
    {
      "geometry": {
        "type": "Point",
        "coordinates": [
          -119.75,
          39.3333
        ]
      },
      "type": "Feature",
      "properties": {
        "hierarchy": [
          "tgn:2626471",
          "tgn:1000001",
          "tgn:7012149",
          "tgn:1002999",
          "tgn:7007526",
          "tgn:7029392"
        ],
        "placetype": [
          "aat:300000390"
        ],
        "id": 2626471,
        "name:xx": "Rocky Hill Mine"
      }
    },
    {
      "geometry": {
        "type": "Point",
        "coordinates": [
          -87.35,
          34.6833
        ]
      },
      "type": "Feature",
      "properties": {
        "hierarchy": [
          "tgn:2626472",
          "tgn:7002659",
          "tgn:1000001",
          "tgn:7012149",
          "tgn:2000039",
          "tgn:7029392"
        ],
        "placetype": [
          "aat:300006191"
        ],
        "id": 2626472,
        "name:xx": "Rocky Hill Pond"
      }
    },
    {
      "geometry": {
        "type": "Point",
        "coordinates": [
          -72.65,
          42.3
        ]
      },
      "type": "Feature",
      "properties": {
        "hierarchy": [
          "tgn:2626473",
          "tgn:1000001",
          "tgn:7013686",
          "tgn:7012149",
          "tgn:7007517",
          "tgn:7029392"
        ],
        "placetype": [
          "aat:300006191"
        ],
        "id": 2626473,
        "name:xx": "Rocky Hill Pond"
      }
    },
    {
      "geometry": {
        "type": "Point",
        "coordinates": [
          -71.45,
          42.85
        ]
      },
      "type": "Feature",
      "properties": {
        "hierarchy": [
          "tgn:2626474",
          "tgn:1000001",
          "tgn:1002480",
          "tgn:7012149",
          "tgn:7007564",
          "tgn:7029392"
        ],
        "placetype": [
          "aat:300008680"
        ],
        "id": 2626474,
        "name:xx": "Rocky Hill Pond"
      }
    },
    {
      "geometry": {
        "type": "Point",
        "coordinates": [
          -117.6667,
          43.6
        ]
      },
      "type": "Feature",
      "properties": {
        "hierarchy": [
          "tgn:2626475",
          "tgn:1000001",
          "tgn:7012149",
          "tgn:2001718",
          "tgn:7007708",
          "tgn:7029392"
        ],
        "placetype": [
          "aat:300006191"
        ],
        "id": 2626475,
        "name:xx": "Rocky Hill Reservoir"
      }
    },
    {
      "geometry": {
        "type": "Point",
        "coordinates": [
          -116.4,
          40.0167
        ]
      },
      "type": "Feature",
      "properties": {
        "hierarchy": [
          "tgn:2626476",
          "tgn:1000001",
          "tgn:2001413",
          "tgn:7012149",
          "tgn:7007526",
          "tgn:7029392"
        ],
        "placetype": [
          "aat:300008697"
        ],
        "id": 2626476,
        "name:xx": "Rocky Hill Spring"
      }
    },
    {
      "geometry": {
        "type": "Point",
        "coordinates": [
          -119,
          36.2
        ]
      },
      "type": "Feature",
      "properties": {
        "hierarchy": [
          "tgn:2626477",
          "tgn:1000001",
          "tgn:7012149",
          "tgn:7007157",
          "tgn:1002956",
          "tgn:7029392"
        ],
        "placetype": [
          "aat:300008798"
        ],
        "id": 2626477,
        "name:xx": "Rocky Hills"
      }
    },
    {
      "geometry": {
        "type": "Point",
        "coordinates": [
          -70.7667,
          43.2
        ]
      },
      "type": "Feature",
      "properties": {
        "hierarchy": [
          "tgn:2626478",
          "tgn:1000001",
          "tgn:7012149",
          "tgn:2000933",
          "tgn:7007515",
          "tgn:7029392"
        ],
        "placetype": [
          "aat:300008798"
        ],
        "id": 2626478,
        "name:xx": "Rocky Hills"
      }
    },
    {
      "geometry": {
        "type": "Point",
        "coordinates": [
          -112.9667,
          45.0667
        ]
      },
      "type": "Feature",
      "properties": {
        "hierarchy": [
          "tgn:2626479",
          "tgn:1000001",
          "tgn:2001260",
          "tgn:7012149",
          "tgn:7007524",
          "tgn:7029392"
        ],
        "placetype": [
          "aat:300386831"
        ],
        "id": 2626479,
        "name:xx": "Rocky Hills"
      }
    }
  ]
}
