{
  "geometry": {
    "type": "Point",
    "coordinates": [
      -85.1167,
      35.1833
    ]
  },
  "type": "Feature",
  "properties": {
    "hierarchy": [
      "tgn:2447239",
      "tgn:1000001",
      "tgn:7012149",
      "tgn:2001894",
      "tgn:7007825",
      "tgn:7029392"
    ],
    "placetype": [
      "aat:300008699"
    ],
    "id": 2447239,
    "name:xx": "Lick Branch"
  }
}
