{
  "geometry": {
    "type": "Point",
    "coordinates": [
      -120.9667,
      39.0333
    ]
  },
  "type": "Feature",
  "properties": {
    "hierarchy": [
      "tgn:2200049",
      "tgn:1000001",
      "tgn:7012149",
      "tgn:7007157",
      "tgn:1002791",
      "tgn:7029392"
    ],
    "placetype": [
      "aat:300008706"
    ],
    "id": 2200049,
    "name:xx": "Brushy Creek"
  }
}
