{
  "geometry": {
    "type": "Point",
    "coordinates": [
      120.63128,
      23.80802
    ]
  },
  "type": "Feature",
  "properties": {
    "hierarchy": [
      "tgn:7487858",
      "tgn:1000004",
      "tgn:7467799",
      "tgn:1000141",
      "tgn:7029392"
    ],
    "placetype": [
      "aat:300008347"
    ],
    "id": 7487858,
    "name:xx": "Youshuikeng"
  }
}
