{
  "geometry": {
    "type": "Point",
    "coordinates": [
      -82.3333,
      37.8167
    ]
  },
  "type": "Feature",
  "properties": {
    "hierarchy": [
      "tgn:2569629",
      "tgn:1000001",
      "tgn:7012149",
      "tgn:2002280",
      "tgn:7013961",
      "tgn:7029392"
    ],
    "placetype": [
      "aat:300008699"
    ],
    "id": 2569629,
    "name:xx": "Parsley Big Branch"
  }
}
