{
  "geometry": {
    "type": "Point",
    "coordinates": [
      -123.0667,
      48.5667
    ]
  },
  "type": "Feature",
  "properties": {
    "hierarchy": [
      "tgn:2480556",
      "tgn:1000001",
      "tgn:7012149",
      "tgn:1002862",
      "tgn:7007920",
      "tgn:7029392"
    ],
    "placetype": [
      "aat:300008347"
    ],
    "id": 2480556,
    "name:xx": "Lakedale"
  }
}
