{
  "geometry": {
    "type": "Point",
    "coordinates": [
      30.722975,
      29.525194
    ]
  },
  "type": "Feature",
  "properties": {
    "hierarchy": [
      "tgn:7534673",
      "tgn:7001242",
      "tgn:7001105",
      "tgn:7016833",
      "tgn:7029392"
    ],
    "placetype": [
      "aat:300008777"
    ],
    "name:en": "Kanā'is al Kabīrah, 'Ilwāyat al",
    "id": 7534673
  }
}
