{
  "geometry": {
    "type": "Point",
    "coordinates": [
      87.15,
      27.3667
    ]
  },
  "type": "Feature",
  "properties": {
    "hierarchy": [
      "tgn:1083280",
      "tgn:7001423",
      "tgn:7001416",
      "tgn:1000004",
      "tgn:1000132",
      "tgn:7029392"
    ],
    "placetype": [
      "aat:300008347"
    ],
    "id": 1083280,
    "name:xx": "Dingla"
  }
}
