{
  "geometry": {
    "type": "Point",
    "coordinates": [
      72.946943,
      28.47004
    ]
  },
  "type": "Feature",
  "properties": {
    "hierarchy": [
      "tgn:7581053",
      "tgn:1000004",
      "tgn:7000198",
      "tgn:7016788",
      "tgn:7029392"
    ],
    "placetype": [
      "aat:300008347"
    ],
    "name:en": "Sīasar",
    "id": 7581053
  }
}
