{
  "geometry": {
    "type": "Point",
    "coordinates": [
      -105.65,
      40.1667
    ]
  },
  "type": "Feature",
  "properties": {
    "hierarchy": [
      "tgn:7019184",
      "tgn:1000001",
      "tgn:2000198",
      "tgn:7012149",
      "tgn:7007158",
      "tgn:7029392"
    ],
    "placetype": [
      "aat:300008706"
    ],
    "id": 7019184,
    "name:xx": "Cony Creek"
  }
}
