{
  "geometry": {
    "type": "Point",
    "coordinates": [
      -98.7833,
      31.8167
    ]
  },
  "type": "Feature",
  "properties": {
    "hierarchy": [
      "tgn:2102770",
      "tgn:1000001",
      "tgn:7012149",
      "tgn:2001962",
      "tgn:7007826",
      "tgn:7029392"
    ],
    "placetype": [
      "aat:300008347"
    ],
    "id": 2102770,
    "name:xx": "Blanket"
  }
}
