{
  "geometry": {
    "type": "Point",
    "coordinates": [
      -80.9833,
      35.25
    ]
  },
  "type": "Feature",
  "properties": {
    "hierarchy": [
      "tgn:2431688",
      "tgn:1000001",
      "tgn:7012149",
      "tgn:7014021",
      "tgn:7007709",
      "tgn:7029392"
    ],
    "placetype": [
      "aat:300006191"
    ],
    "id": 2431688,
    "name:xx": "Kathleen, Lake"
  }
}
