{
  "geometry": {
    "type": "Point",
    "coordinates": [
      -122.6833,
      48.2833
    ]
  },
  "type": "Feature",
  "properties": {
    "hierarchy": [
      "tgn:2464395",
      "tgn:1000001",
      "tgn:7012149",
      "tgn:1002505",
      "tgn:7007920",
      "tgn:7029392"
    ],
    "placetype": [
      "aat:300006191"
    ],
    "id": 2464395,
    "name:xx": "Loers Pond"
  }
}
