{
  "geometry": {
    "type": "Point",
    "coordinates": [
      -158.1333,
      21.55
    ]
  },
  "type": "Feature",
  "properties": {
    "hierarchy": [
      "tgn:2775630",
      "tgn:1002483",
      "tgn:7019080",
      "tgn:1000001",
      "tgn:7012149",
      "tgn:7007249",
      "tgn:7029392"
    ],
    "placetype": [
      "aat:300006075"
    ],
    "id": 2775630,
    "name:xx": "Wilson Ditch"
  }
}
