{
  "geometry": {
    "type": "Point",
    "coordinates": [
      -81.55,
      36.95
    ]
  },
  "type": "Feature",
  "properties": {
    "hierarchy": [
      "tgn:2261766",
      "tgn:1000001",
      "tgn:7012149",
      "tgn:2002191",
      "tgn:7007919",
      "tgn:7029392"
    ],
    "placetype": [
      "aat:300266640"
    ],
    "id": 2261766,
    "name:xx": "Cove Ridge"
  }
}
