{
  "geometry": {
    "type": "Point",
    "coordinates": [
      -96.0333,
      38.05
    ]
  },
  "type": "Feature",
  "properties": {
    "hierarchy": [
      "tgn:2391794",
      "tgn:1000001",
      "tgn:2000696",
      "tgn:7012149",
      "tgn:7007254",
      "tgn:7029392"
    ],
    "placetype": [
      "aat:300008347"
    ],
    "id": 2391794,
    "name:xx": "Hilltop"
  }
}
