{
  "geometry": {
    "type": "Point",
    "coordinates": [
      -80.0833,
      36.1667
    ]
  },
  "type": "Feature",
  "properties": {
    "hierarchy": [
      "tgn:2366058",
      "tgn:1000001",
      "tgn:7012149",
      "tgn:2001494",
      "tgn:7007709",
      "tgn:7029392"
    ],
    "placetype": [
      "aat:300008347"
    ],
    "id": 2366058,
    "name:xx": "Greystone Forest"
  }
}
