{
  "geometry": {
    "type": "Point",
    "coordinates": [
      -83.0833,
      37.9833
    ]
  },
  "type": "Feature",
  "properties": {
    "hierarchy": [
      "tgn:2038384",
      "tgn:1000001",
      "tgn:7012149",
      "tgn:2000831",
      "tgn:7007255",
      "tgn:7029392"
    ],
    "placetype": [
      "aat:300008347"
    ],
    "id": 2038384,
    "name:xx": "Crockett"
  }
}
