{
  "geometry": {
    "type": "Point",
    "coordinates": [
      -123.4167,
      46.1667
    ]
  },
  "type": "Feature",
  "properties": {
    "hierarchy": [
      "tgn:2205010",
      "tgn:1000001",
      "tgn:1002276",
      "tgn:7012149",
      "tgn:7007708",
      "tgn:7029392"
    ],
    "placetype": [
      "aat:300386845"
    ],
    "id": 2205010,
    "name:xx": "Bugby Hole"
  }
}
