{
  "geometry": {
    "type": "Point",
    "coordinates": [
      -87.9333,
      31.4333
    ]
  },
  "type": "Feature",
  "properties": {
    "hierarchy": [
      "tgn:2301398",
      "tgn:7002659",
      "tgn:1000001",
      "tgn:7012149",
      "tgn:2000064",
      "tgn:7029392"
    ],
    "placetype": [
      "aat:300008680"
    ],
    "id": 2301398,
    "name:xx": "Dunn Lake"
  }
}
