{
  "geometry": {
    "type": "Point",
    "coordinates": [
      -86.3333,
      35.8167
    ]
  },
  "type": "Feature",
  "properties": {
    "hierarchy": [
      "tgn:2293522",
      "tgn:1000001",
      "tgn:7012149",
      "tgn:2001911",
      "tgn:7007825",
      "tgn:7029392"
    ],
    "placetype": [
      "aat:300008697"
    ],
    "id": 2293522,
    "name:xx": "Double Spring"
  }
}
