{
  "geometry": {
    "type": "Point",
    "coordinates": [
      -95.8833,
      31.7667
    ]
  },
  "type": "Feature",
  "properties": {
    "hierarchy": [
      "tgn:2155127",
      "tgn:1002148",
      "tgn:1000001",
      "tgn:7012149",
      "tgn:7007826",
      "tgn:7029392"
    ],
    "placetype": [
      "aat:300008680"
    ],
    "id": 2155127,
    "name:xx": "Bear Lake"
  }
}
