{
  "geometry": {
    "type": "Point",
    "coordinates": [
      29.65,
      30.183333
    ]
  },
  "type": "Feature",
  "properties": {
    "hierarchy": [
      "tgn:7538584",
      "tgn:7001242",
      "tgn:7016833",
      "tgn:1001418",
      "tgn:7029392"
    ],
    "placetype": [
      "aat:300008750"
    ],
    "name:en": "Mashrūkah, Ghurd al",
    "id": 7538584
  }
}
