{
  "geometry": {
    "type": "Point",
    "coordinates": [
      114.2833,
      31.4167
    ]
  },
  "type": "Feature",
  "properties": {
    "hierarchy": [
      "tgn:1072729",
      "tgn:1000004",
      "tgn:7002078",
      "tgn:1000111",
      "tgn:7029392"
    ],
    "placetype": [
      "aat:300008347"
    ],
    "id": 1072729,
    "name:xx": "Xiadian"
  }
}
