{
  "geometry": {
    "type": "Point",
    "coordinates": [
      -122.4667,
      47.4667
    ]
  },
  "type": "Feature",
  "properties": {
    "hierarchy": [
      "tgn:2325027",
      "tgn:1000001",
      "tgn:7012149",
      "tgn:7018871",
      "tgn:7007920",
      "tgn:7029392"
    ],
    "placetype": [
      "aat:300132316"
    ],
    "id": 2325027,
    "name:xx": "Fern Cove"
  }
}
