{
  "geometry": {
    "type": "Point",
    "coordinates": [
      30.133333,
      28.883333
    ]
  },
  "type": "Feature",
  "properties": {
    "hierarchy": [
      "tgn:1107814",
      "tgn:7001242",
      "tgn:7016833",
      "tgn:1001418",
      "tgn:7029392"
    ],
    "placetype": [
      "aat:300008777"
    ],
    "id": 1107814,
    "name:xx": "ʻAbd al Ḥafīz, Qārat"
  }
}
