{
  "type": "FeatureCollection",
  "features": [
    {
      "geometry": {
        "type": "Point",
        "coordinates": [
          31.402886,
          30.619527
        ]
      },
      "type": "Feature",
      "properties": {
        "hierarchy": [
          "tgn:7541710",
          "tgn:7001242",
          "tgn:7016833",
          "tgn:1001113",
          "tgn:7029392"
        ],
        "placetype": [
          "aat:300008347"
        ],
        "id": 7541710,
        "name:xx": "'Izbat 'Abd al Ḩamīd"
      }
    },
    {
      "geometry": {
        "type": "Point",
        "coordinates": [
          31.278061,
          30.614935
        ]
      },
      "type": "Feature",
      "properties": {
        "hierarchy": [
          "tgn:7541711",
          "tgn:7001242",
          "tgn:1001059",
          "tgn:7016833",
          "tgn:7029392"
        ],
        "placetype": [
          "aat:300006075"
        ],
        "id": 7541711,
        "name:xx": "Tur'at al Qayţūn"
      }
    },
    {
      "geometry": {
        "type": "Point",
        "coordinates": [
          31.492515,
          30.614522
        ]
      },
      "type": "Feature",
      "properties": {
        "hierarchy": [
          "tgn:7541712",
          "tgn:7001242",
          "tgn:7016833",
          "tgn:1001113",
          "tgn:7029392"
        ],
        "placetype": [
          "aat:300008347"
        ],
        "id": 7541712,
        "name:xx": "'Izbat Imām"
      }
    },
    {
      "geometry": {
        "type": "Point",
        "coordinates": [
          31.320816,
          30.613642
        ]
      },
      "type": "Feature",
      "properties": {
        "hierarchy": [
          "tgn:7541713",
          "tgn:7001242",
          "tgn:1001059",
          "tgn:7016833",
          "tgn:7029392"
        ],
        "placetype": [
          "aat:300008347"
        ],
        "id": 7541713,
        "name:xx": "'Izbat Nuşayr"
      }
    },
    {
      "geometry": {
        "type": "Point",
        "coordinates": [
          31.410675,
          30.612794
        ]
      },
      "type": "Feature",
      "properties": {
        "hierarchy": [
          "tgn:7541714",
          "tgn:7001242",
          "tgn:7016833",
          "tgn:1001113",
          "tgn:7029392"
        ],
        "placetype": [
          "aat:300008347"
        ],
        "id": 7541714,
        "name:xx": "'Izbat al Bāblī"
      }
    },
    {
      "geometry": {
        "type": "Point",
        "coordinates": [
          31.350343,
          30.611211
        ]
      },
      "type": "Feature",
      "properties": {
        "hierarchy": [
          "tgn:7541715",
          "tgn:7001242",
          "tgn:7016833",
          "tgn:1001113",
          "tgn:7029392"
        ],
        "placetype": [
          "aat:300008347"
        ],
        "id": 7541715,
        "name:xx": "'Izbat 'Alī Mas'ūd"
      }
    },
    {
      "geometry": {
        "type": "Point",
        "coordinates": [
          31.489262,
          30.611461
        ]
      },
      "type": "Feature",
      "properties": {
        "hierarchy": [
          "tgn:7541716",
          "tgn:7001242",
          "tgn:7016833",
          "tgn:1001113",
          "tgn:7029392"
        ],
        "placetype": [
          "aat:300008347"
        ],
        "id": 7541716,
        "name:xx": "'Izbat Lukshah"
      }
    },
    {
      "geometry": {
        "type": "Point",
        "coordinates": [
          31.398849,
          30.606586
        ]
      },
      "type": "Feature",
      "properties": {
        "hierarchy": [
          "tgn:7541717",
          "tgn:7001242",
          "tgn:7016833",
          "tgn:1001113",
          "tgn:7029392"
        ],
        "placetype": [
          "aat:300008347"
        ],
        "id": 7541717,
        "name:xx": "'Izbat as Sirw"
      }
    },
    {
      "geometry": {
        "type": "Point",
        "coordinates": [
          31.437438,
          30.595765
        ]
      },
      "type": "Feature",
      "properties": {
        "hierarchy": [
          "tgn:7541718",
          "tgn:7001242",
          "tgn:7016833",
          "tgn:1001113",
          "tgn:7029392"
        ],
        "placetype": [
          "aat:300006075"
        ],
        "id": 7541718,
        "name:xx": "Tur'at al Dabābirah"
      }
    },
    {
      "geometry": {
        "type": "Point",
        "coordinates": [
          31.327936,
          30.604236
        ]
      },
      "type": "Feature",
      "properties": {
        "hierarchy": [
          "tgn:7541719",
          "tgn:7001242",
          "tgn:1001059",
          "tgn:7016833",
          "tgn:7029392"
        ],
        "placetype": [
          "aat:300008347"
        ],
        "id": 7541719,
        "name:xx": "'Izbat Nuşayr"
      }
    }
  ]
}
