{
  "geometry": {
    "type": "Point",
    "coordinates": [
      -87.6333,
      31.2667
    ]
  },
  "type": "Feature",
  "properties": {
    "hierarchy": [
      "tgn:2516329",
      "tgn:7002659",
      "tgn:1000001",
      "tgn:7012149",
      "tgn:2000049",
      "tgn:7029392"
    ],
    "placetype": [
      "aat:300008347"
    ],
    "id": 2516329,
    "name:xx": "Mineola"
  }
}
