{
  "geometry": {
    "type": "Point",
    "coordinates": [
      -69.3333,
      45.0667
    ]
  },
  "type": "Feature",
  "properties": {
    "hierarchy": [
      "tgn:2545046",
      "tgn:1000001",
      "tgn:7012149",
      "tgn:2000927",
      "tgn:7007515",
      "tgn:7029392"
    ],
    "placetype": [
      "aat:300008347"
    ],
    "id": 2545046,
    "name:xx": "North Dexter"
  }
}
