{
  "geometry": {
    "type": "Point",
    "coordinates": [
      -91.3167,
      38.85
    ]
  },
  "type": "Feature",
  "properties": {
    "hierarchy": [
      "tgn:2513949",
      "tgn:1000001",
      "tgn:7012149",
      "tgn:7007523",
      "tgn:7029392"
    ],
    "placetype": [
      "aat:300008706"
    ],
    "id": 2513949,
    "name:xx": "Millam Creek"
  }
}
