{
  "type": "FeatureCollection",
  "features": [
    {
      "geometry": {
        "type": "Point",
        "coordinates": [
          -81.8167,
          26.4
        ]
      },
      "type": "Feature",
      "properties": {
        "hierarchy": [
          "tgn:2019210",
          "tgn:1000001",
          "tgn:7012149",
          "tgn:1002582",
          "tgn:7007240",
          "tgn:7029392"
        ],
        "placetype": [
          "aat:300008347"
        ],
        "id": 2019210,
        "name:xx": "El Dorado Acres"
      }
    },
    {
      "geometry": {
        "type": "Point",
        "coordinates": [
          -82.7167,
          28.2
        ]
      },
      "type": "Feature",
      "properties": {
        "hierarchy": [
          "tgn:2019212",
          "tgn:1000001",
          "tgn:7012149",
          "tgn:1002773",
          "tgn:7007240",
          "tgn:7029392"
        ],
        "placetype": [
          "aat:300008347"
        ],
        "id": 2019212,
        "name:xx": "Elfers"
      }
    },
    {
      "geometry": {
        "type": "Point",
        "coordinates": [
          -82.2,
          26.95
        ]
      },
      "type": "Feature",
      "properties": {
        "hierarchy": [
          "tgn:2019213",
          "tgn:1000001",
          "tgn:1002258",
          "tgn:7012149",
          "tgn:7007240",
          "tgn:7029392"
        ],
        "placetype": [
          "aat:300008347"
        ],
        "id": 2019213,
        "name:xx": "El Jobean"
      }
    },
    {
      "geometry": {
        "type": "Point",
        "coordinates": [
          -81.4167,
          29.7667
        ]
      },
      "type": "Feature",
      "properties": {
        "hierarchy": [
          "tgn:2019214",
          "tgn:1000001",
          "tgn:7012149",
          "tgn:2000283",
          "tgn:7007240",
          "tgn:7029392"
        ],
        "placetype": [
          "aat:300008347"
        ],
        "id": 2019214,
        "name:xx": "Elkton"
      }
    },
    {
      "geometry": {
        "type": "Point",
        "coordinates": [
          -85.3667,
          30.9667
        ]
      },
      "type": "Feature",
      "properties": {
        "hierarchy": [
          "tgn:2019215",
          "tgn:1000001",
          "tgn:2000273",
          "tgn:7012149",
          "tgn:7007240",
          "tgn:7029392"
        ],
        "placetype": [
          "aat:300008347",
          "aat:300387210"
        ],
        "id": 2019215,
        "name:xx": "Ellaville"
      }
    },
    {
      "geometry": {
        "type": "Point",
        "coordinates": [
          -83.1667,
          30.3667
        ]
      },
      "type": "Feature",
      "properties": {
        "hierarchy": [
          "tgn:2019216",
          "tgn:1000001",
          "tgn:7012149",
          "tgn:2000286",
          "tgn:7007240",
          "tgn:7029392"
        ],
        "placetype": [
          "aat:300008347",
          "aat:300387210"
        ],
        "id": 2019216,
        "name:xx": "Ellaville"
      }
    },
    {
      "geometry": {
        "type": "Point",
        "coordinates": [
          -82.5167,
          27.5167
        ]
      },
      "type": "Feature",
      "properties": {
        "hierarchy": [
          "tgn:2019217",
          "tgn:1000001",
          "tgn:7012149",
          "tgn:1002628",
          "tgn:7007240",
          "tgn:7029392"
        ],
        "placetype": [
          "aat:300008347"
        ],
        "id": 2019217,
        "name:xx": "Ellenton"
      }
    },
    {
      "geometry": {
        "type": "Point",
        "coordinates": [
          -82.5833,
          30
        ]
      },
      "type": "Feature",
      "properties": {
        "hierarchy": [
          "tgn:2019219",
          "tgn:1000001",
          "tgn:2000262",
          "tgn:7012149",
          "tgn:7007240",
          "tgn:7029392"
        ],
        "placetype": [
          "aat:300008347",
          "aat:300387210"
        ],
        "id": 2019219,
        "name:xx": "Ellisville"
      }
    }
  ]
}
