{
  "type": "FeatureCollection",
  "features": [
    {
      "geometry": {
        "type": "Point",
        "coordinates": [
          -74.4,
          40.2333
        ]
      },
      "type": "Feature",
      "properties": {
        "hierarchy": [
          "tgn:2582590",
          "tgn:1000001",
          "tgn:7014090",
          "tgn:7012149",
          "tgn:7007565",
          "tgn:7029392"
        ],
        "placetype": [
          "aat:300008798"
        ],
        "id": 2582590,
        "name:xx": "Pine Hill"
      }
    },
    {
      "geometry": {
        "type": "Point",
        "coordinates": [
          -76.0667,
          43.8667
        ]
      },
      "type": "Feature",
      "properties": {
        "hierarchy": [
          "tgn:2582591",
          "tgn:1000001",
          "tgn:7012149",
          "tgn:1002518",
          "tgn:7007568",
          "tgn:7029392"
        ],
        "placetype": [
          "aat:300008798"
        ],
        "id": 2582591,
        "name:xx": "Pine Hill"
      }
    },
    {
      "geometry": {
        "type": "Point",
        "coordinates": [
          -74.2167,
          41.1667
        ]
      },
      "type": "Feature",
      "properties": {
        "hierarchy": [
          "tgn:2582592",
          "tgn:1000001",
          "tgn:7012149",
          "tgn:1002751",
          "tgn:7007568",
          "tgn:7029392"
        ],
        "placetype": [
          "aat:300008798"
        ],
        "id": 2582592,
        "name:xx": "Pine Hill"
      }
    },
    {
      "geometry": {
        "type": "Point",
        "coordinates": [
          -78.9833,
          42.1
        ]
      },
      "type": "Feature",
      "properties": {
        "hierarchy": [
          "tgn:2582593",
          "tgn:1000001",
          "tgn:1002245",
          "tgn:7012149",
          "tgn:7007568",
          "tgn:7029392"
        ],
        "placetype": [
          "aat:300008798"
        ],
        "id": 2582593,
        "name:xx": "Pine Hill"
      }
    },
    {
      "geometry": {
        "type": "Point",
        "coordinates": [
          -75.0833,
          42.1833
        ]
      },
      "type": "Feature",
      "properties": {
        "hierarchy": [
          "tgn:2582594",
          "tgn:1000001",
          "tgn:1002328",
          "tgn:7012149",
          "tgn:7007568",
          "tgn:7029392"
        ],
        "placetype": [
          "aat:300008798"
        ],
        "id": 2582594,
        "name:xx": "Pine Hill"
      }
    },
    {
      "geometry": {
        "type": "Point",
        "coordinates": [
          -77.0167,
          42.2
        ]
      },
      "type": "Feature",
      "properties": {
        "hierarchy": [
          "tgn:2582595",
          "tgn:1000001",
          "tgn:7012149",
          "tgn:1002920",
          "tgn:7007568",
          "tgn:7029392"
        ],
        "placetype": [
          "aat:300008798"
        ],
        "id": 2582595,
        "name:xx": "Pine Hill"
      }
    },
    {
      "geometry": {
        "type": "Point",
        "coordinates": [
          -74.7,
          42.5333
        ]
      },
      "type": "Feature",
      "properties": {
        "hierarchy": [
          "tgn:2582596",
          "tgn:1000001",
          "tgn:7012149",
          "tgn:7014318",
          "tgn:7007568",
          "tgn:7029392"
        ],
        "placetype": [
          "aat:300008798"
        ],
        "id": 2582596,
        "name:xx": "Pine Hill"
      }
    },
    {
      "geometry": {
        "type": "Point",
        "coordinates": [
          -74.5833,
          42.7167
        ]
      },
      "type": "Feature",
      "properties": {
        "hierarchy": [
          "tgn:2582597",
          "tgn:1000001",
          "tgn:7012149",
          "tgn:1002873",
          "tgn:7007568",
          "tgn:7029392"
        ],
        "placetype": [
          "aat:300008798"
        ],
        "id": 2582597,
        "name:xx": "Pine Hill"
      }
    },
    {
      "geometry": {
        "type": "Point",
        "coordinates": [
          -78.2667,
          43.1667
        ]
      },
      "type": "Feature",
      "properties": {
        "hierarchy": [
          "tgn:2582598",
          "tgn:1000001",
          "tgn:7012149",
          "tgn:1002752",
          "tgn:7007568",
          "tgn:7029392"
        ],
        "placetype": [
          "aat:300008798"
        ],
        "id": 2582598,
        "name:xx": "Pine Hill"
      }
    },
    {
      "geometry": {
        "type": "Point",
        "coordinates": [
          -77.8333,
          43.2
        ]
      },
      "type": "Feature",
      "properties": {
        "hierarchy": [
          "tgn:2582599",
          "tgn:1000001",
          "tgn:7012149",
          "tgn:1002681",
          "tgn:7007568",
          "tgn:7029392"
        ],
        "placetype": [
          "aat:300008798"
        ],
        "id": 2582599,
        "name:xx": "Pine Hill"
      }
    }
  ]
}
