{
  "geometry": {
    "type": "Point",
    "coordinates": [
      -110.25,
      42.65
    ]
  },
  "type": "Feature",
  "properties": {
    "hierarchy": [
      "tgn:2331747",
      "tgn:1000001",
      "tgn:7012149",
      "tgn:2002382",
      "tgn:7007923",
      "tgn:7029392"
    ],
    "placetype": [
      "aat:300008699"
    ],
    "id": 2331747,
    "name:xx": "Fleming Slough"
  }
}
