{
  "geometry": {
    "type": "Point",
    "coordinates": [
      -92.833333,
      15.35
    ]
  },
  "type": "Feature",
  "properties": {
    "hierarchy": [
      "tgn:7385173",
      "tgn:7005580",
      "tgn:1000001",
      "tgn:7005560",
      "tgn:7029392"
    ],
    "placetype": [
      "aat:300008347"
    ],
    "id": 7385173,
    "name:xx": "Nicolás Bravo Número Dos"
  }
}
