{
  "type": "FeatureCollection",
  "features": [
    {
      "geometry": {
        "type": "Point",
        "coordinates": [
          -69.616667,
          -20.75
        ]
      },
      "type": "Feature",
      "properties": {
        "hierarchy": [
          "tgn:7321560",
          "tgn:7002464",
          "tgn:1000049",
          "tgn:1000002",
          "tgn:7029392"
        ],
        "placetype": [
          "aat:300386871"
        ],
        "id": 7321560,
        "name:xx": "Bella Vista, Salar de"
      }
    },
    {
      "geometry": {
        "type": "Point",
        "coordinates": [
          -70.8,
          -32.716667
        ]
      },
      "type": "Feature",
      "properties": {
        "hierarchy": [
          "tgn:7321561",
          "tgn:1001768",
          "tgn:1000049",
          "tgn:1000002",
          "tgn:7029392"
        ],
        "placetype": [
          "aat:300266554",
          "aat:300008699"
        ],
        "id": 7321561,
        "name:xx": "Bella Vista, Quebrada"
      }
    },
    {
      "geometry": {
        "type": "Point",
        "coordinates": [
          -73.283333,
          -51.466667
        ]
      },
      "type": "Feature",
      "properties": {
        "hierarchy": [
          "tgn:7321562",
          "tgn:1001702",
          "tgn:1000049",
          "tgn:1000002",
          "tgn:7029392"
        ],
        "placetype": [
          "aat:300008678"
        ],
        "id": 7321562,
        "name:xx": "Bellavista, Puerto"
      }
    },
    {
      "geometry": {
        "type": "Point",
        "coordinates": [
          -69.6,
          -20.783333
        ]
      },
      "type": "Feature",
      "properties": {
        "hierarchy": [
          "tgn:7321563",
          "tgn:7002464",
          "tgn:1000049",
          "tgn:1000002",
          "tgn:7029392"
        ],
        "placetype": [
          "aat:300006207"
        ],
        "id": 7321563,
        "name:xx": "Pozo Bellavista"
      }
    },
    {
      "geometry": {
        "type": "Point",
        "coordinates": [
          -70.683333,
          -27.116667
        ]
      },
      "type": "Feature",
      "properties": {
        "hierarchy": [
          "tgn:7321564",
          "tgn:1001630",
          "tgn:1000049",
          "tgn:1000002",
          "tgn:7029392"
        ],
        "placetype": [
          "aat:300008805"
        ],
        "id": 7321564,
        "name:xx": "Bellavista, Pampa"
      }
    },
    {
      "geometry": {
        "type": "Point",
        "coordinates": [
          -69.366667,
          -52.883333
        ]
      },
      "type": "Feature",
      "properties": {
        "hierarchy": [
          "tgn:7321565",
          "tgn:1001702",
          "tgn:1000049",
          "tgn:1000002",
          "tgn:7029392"
        ],
        "placetype": [
          "aat:300008699"
        ],
        "id": 7321565,
        "name:xx": "Bellavista, Estero"
      }
    },
    {
      "geometry": {
        "type": "Point",
        "coordinates": [
          -73.183333,
          -39.616667
        ]
      },
      "type": "Feature",
      "properties": {
        "hierarchy": [
          "tgn:7321566",
          "tgn:1001699",
          "tgn:1000049",
          "tgn:1000002",
          "tgn:7029392"
        ],
        "placetype": [
          "aat:300008699"
        ],
        "id": 7321566,
        "name:xx": "Bellavista, Estero"
      }
    },
    {
      "geometry": {
        "type": "Point",
        "coordinates": [
          -72.95,
          -36.633333
        ]
      },
      "type": "Feature",
      "properties": {
        "hierarchy": [
          "tgn:7321567",
          "tgn:1001637",
          "tgn:1000049",
          "tgn:1000002",
          "tgn:7029392"
        ],
        "placetype": [
          "aat:300008699"
        ],
        "id": 7321567,
        "name:xx": "Bellavista, Estero"
      }
    },
    {
      "geometry": {
        "type": "Point",
        "coordinates": [
          -71.9,
          -38.25
        ]
      },
      "type": "Feature",
      "properties": {
        "hierarchy": [
          "tgn:7321568",
          "tgn:1001692",
          "tgn:1000049",
          "tgn:1000002",
          "tgn:7029392"
        ],
        "placetype": [
          "aat:300008795"
        ],
        "id": 7321568,
        "name:xx": "Bella Vista, Cordillera"
      }
    },
    {
      "geometry": {
        "type": "Point",
        "coordinates": [
          -71.283333,
          -52.416667
        ]
      },
      "type": "Feature",
      "properties": {
        "hierarchy": [
          "tgn:7321569",
          "tgn:1001702",
          "tgn:1000049",
          "tgn:1000002",
          "tgn:7029392"
        ],
        "placetype": [
          "aat:300008699"
        ],
        "id": 7321569,
        "name:xx": "Bellavista, Chorrillo"
      }
    }
  ]
}
