{
  "geometry": {
    "type": "Point",
    "coordinates": [
      -91.05,
      14.0833
    ]
  },
  "type": "Feature",
  "properties": {
    "hierarchy": [
      "tgn:1016671",
      "tgn:1000602",
      "tgn:1000001",
      "tgn:7005493",
      "tgn:7029392"
    ],
    "placetype": [
      "aat:300008347"
    ],
    "id": 1016671,
    "name:xx": "La Gomera"
  }
}
