{
  "geometry": {
    "type": "Point",
    "coordinates": [
      31.168,
      36.831
    ]
  },
  "type": "Feature",
  "properties": {
    "hierarchy": [
      "tgn:1125284",
      "tgn:1001102",
      "tgn:7018452",
      "tgn:1000004",
      "tgn:1000144",
      "tgn:7029392"
    ],
    "placetype": [
      "aat:300000835",
      "aat:300008707",
      "aat:300008699"
    ],
    "id": 1125284,
    "name:xx": "Köprü Irmağı"
  }
}
