{
  "geometry": {
    "type": "Point",
    "coordinates": [
      -82.3667,
      40.5333
    ]
  },
  "type": "Feature",
  "properties": {
    "hierarchy": [
      "tgn:2163929",
      "tgn:1000001",
      "tgn:7012149",
      "tgn:1002556",
      "tgn:7007706",
      "tgn:7029392"
    ],
    "placetype": [
      "aat:300008347"
    ],
    "id": 2163929,
    "name:xx": "Berger"
  }
}
