{
  "geometry": {
    "type": "Point",
    "coordinates": [
      -105.5333,
      36.1667
    ]
  },
  "type": "Feature",
  "properties": {
    "hierarchy": [
      "tgn:2331609",
      "tgn:1000001",
      "tgn:7012149",
      "tgn:2001457",
      "tgn:7007566",
      "tgn:7029392"
    ],
    "placetype": [
      "aat:300008761"
    ],
    "id": 2331609,
    "name:xx": "Flechado Canyon"
  }
}
