{
  "geometry": {
    "type": "Point",
    "coordinates": [
      -119.85,
      44.45
    ]
  },
  "type": "Feature",
  "properties": {
    "hierarchy": [
      "tgn:2247029",
      "tgn:1000001",
      "tgn:7012149",
      "tgn:2001723",
      "tgn:7007708",
      "tgn:7029392"
    ],
    "placetype": [
      "aat:300008706"
    ],
    "id": 2247029,
    "name:xx": "Cockleburr Creek"
  }
}
