{
  "type": "FeatureCollection",
  "features": [
    {
      "geometry": {
        "type": "Point",
        "coordinates": [
          -96.85,
          40.65
        ]
      },
      "type": "Feature",
      "properties": {
        "hierarchy": [
          "tgn:2686510",
          "tgn:1000001",
          "tgn:2001370",
          "tgn:7012149",
          "tgn:7007525",
          "tgn:7029392"
        ],
        "placetype": [
          "aat:300008706"
        ],
        "id": 2686510,
        "name:xx": "Spring Creek"
      }
    },
    {
      "geometry": {
        "type": "Point",
        "coordinates": [
          -100.5333,
          42.9667
        ]
      },
      "type": "Feature",
      "properties": {
        "hierarchy": [
          "tgn:2686511",
          "tgn:1000001",
          "tgn:2001331",
          "tgn:7012149",
          "tgn:7007525",
          "tgn:7029392"
        ],
        "placetype": [
          "aat:300008706"
        ],
        "id": 2686511,
        "name:xx": "Spring Creek"
      }
    },
    {
      "geometry": {
        "type": "Point",
        "coordinates": [
          -98.8333,
          42.8833
        ]
      },
      "type": "Feature",
      "properties": {
        "hierarchy": [
          "tgn:2686512",
          "tgn:1000001",
          "tgn:2001323",
          "tgn:7012149",
          "tgn:7007525",
          "tgn:7029392"
        ],
        "placetype": [
          "aat:300008706"
        ],
        "id": 2686512,
        "name:xx": "Spring Creek"
      }
    },
    {
      "geometry": {
        "type": "Point",
        "coordinates": [
          -99.5333,
          42.7667
        ]
      },
      "type": "Feature",
      "properties": {
        "hierarchy": [
          "tgn:2686513",
          "tgn:1000001",
          "tgn:2001367",
          "tgn:7012149",
          "tgn:7007525",
          "tgn:7029392"
        ],
        "placetype": [
          "aat:300008706"
        ],
        "id": 2686513,
        "name:xx": "Spring Creek"
      }
    },
    {
      "geometry": {
        "type": "Point",
        "coordinates": [
          -98.8333,
          42.6833
        ]
      },
      "type": "Feature",
      "properties": {
        "hierarchy": [
          "tgn:2686514",
          "tgn:1000001",
          "tgn:2001360",
          "tgn:7012149",
          "tgn:7007525",
          "tgn:7029392"
        ],
        "placetype": [
          "aat:300008706"
        ],
        "id": 2686514,
        "name:xx": "Spring Creek"
      }
    },
    {
      "geometry": {
        "type": "Point",
        "coordinates": [
          -98.7833,
          41.65
        ]
      },
      "type": "Feature",
      "properties": {
        "hierarchy": [
          "tgn:2686515",
          "tgn:1000001",
          "tgn:7012149",
          "tgn:2001403",
          "tgn:7007525",
          "tgn:7029392"
        ],
        "placetype": [
          "aat:300008706"
        ],
        "id": 2686515,
        "name:xx": "Spring Creek"
      }
    },
    {
      "geometry": {
        "type": "Point",
        "coordinates": [
          -102.0333,
          40.85
        ]
      },
      "type": "Feature",
      "properties": {
        "hierarchy": [
          "tgn:2686516",
          "tgn:1000001",
          "tgn:7012149",
          "tgn:2001383",
          "tgn:7007525",
          "tgn:7029392"
        ],
        "placetype": [
          "aat:300008706"
        ],
        "id": 2686516,
        "name:xx": "Spring Creek"
      }
    },
    {
      "geometry": {
        "type": "Point",
        "coordinates": [
          -100.5333,
          40.5333
        ]
      },
      "type": "Feature",
      "properties": {
        "hierarchy": [
          "tgn:2686517",
          "tgn:1000001",
          "tgn:2001347",
          "tgn:7012149",
          "tgn:7007525",
          "tgn:7029392"
        ],
        "placetype": [
          "aat:300008706"
        ],
        "id": 2686517,
        "name:xx": "Spring Creek"
      }
    },
    {
      "geometry": {
        "type": "Point",
        "coordinates": [
          -97.1833,
          40.55
        ]
      },
      "type": "Feature",
      "properties": {
        "hierarchy": [
          "tgn:2686518",
          "tgn:1000001",
          "tgn:7012149",
          "tgn:2001391",
          "tgn:7007525",
          "tgn:7029392"
        ],
        "placetype": [
          "aat:300008706"
        ],
        "id": 2686518,
        "name:xx": "Spring Creek"
      }
    },
    {
      "geometry": {
        "type": "Point",
        "coordinates": [
          -95.7667,
          40.1333
        ]
      },
      "type": "Feature",
      "properties": {
        "hierarchy": [
          "tgn:2686519",
          "tgn:1000001",
          "tgn:7012149",
          "tgn:2001389",
          "tgn:7007525",
          "tgn:7029392"
        ],
        "placetype": [
          "aat:300008706"
        ],
        "id": 2686519,
        "name:xx": "Spring Creek"
      }
    }
  ]
}
