{
  "geometry": {
    "type": "Point",
    "coordinates": [
      -93.1167,
      41.2333
    ]
  },
  "type": "Feature",
  "properties": {
    "hierarchy": [
      "tgn:2387995",
      "tgn:1000001",
      "tgn:7012149",
      "tgn:2000623",
      "tgn:7007253",
      "tgn:7029392"
    ],
    "placetype": [
      "aat:300008706"
    ],
    "id": 2387995,
    "name:xx": "Hickory Creek"
  }
}
