{
  "geometry": {
    "type": "Point",
    "coordinates": [
      -81.4333,
      38.6667
    ]
  },
  "type": "Feature",
  "properties": {
    "hierarchy": [
      "tgn:2606063",
      "tgn:1000001",
      "tgn:7012149",
      "tgn:2002293",
      "tgn:7013961",
      "tgn:7029392"
    ],
    "placetype": [
      "aat:300266640"
    ],
    "id": 2606063,
    "name:xx": "Raines Ridge"
  }
}
