{
  "type": "FeatureCollection",
  "features": [
    {
      "geometry": {
        "type": "Point",
        "coordinates": [
          -72.116667,
          -39.466667
        ]
      },
      "type": "Feature",
      "properties": {
        "hierarchy": [
          "tgn:7314951",
          "tgn:1001699",
          "tgn:1000049",
          "tgn:1000002",
          "tgn:7029392"
        ],
        "placetype": [
          "aat:300008347"
        ],
        "id": 7314951,
        "name:xx": "Licanray"
      }
    },
    {
      "geometry": {
        "type": "Point",
        "coordinates": [
          -71.816667,
          -33.916667
        ]
      },
      "type": "Feature",
      "properties": {
        "hierarchy": [
          "tgn:7314952",
          "tgn:1001708",
          "tgn:1000049",
          "tgn:1000002",
          "tgn:7029392"
        ],
        "placetype": [
          "aat:300266554",
          "aat:300008699"
        ],
        "id": 7314952,
        "name:xx": "Licancheo, Estero"
      }
    },
    {
      "geometry": {
        "type": "Point",
        "coordinates": [
          -71.8,
          -33.933333
        ]
      },
      "type": "Feature",
      "properties": {
        "hierarchy": [
          "tgn:7314953",
          "tgn:1001708",
          "tgn:1000049",
          "tgn:1000002",
          "tgn:7029392"
        ],
        "placetype": [
          "aat:300008347"
        ],
        "id": 7314953,
        "name:xx": "Licancheo"
      }
    },
    {
      "geometry": {
        "type": "Point",
        "coordinates": [
          -71.816667,
          -33.933333
        ]
      },
      "type": "Feature",
      "properties": {
        "hierarchy": [
          "tgn:7314954",
          "tgn:1001708",
          "tgn:1000049",
          "tgn:1000002",
          "tgn:7029392"
        ],
        "placetype": [
          "aat:300008777"
        ],
        "id": 7314954,
        "name:xx": "Licancheo"
      }
    },
    {
      "geometry": {
        "type": "Point",
        "coordinates": [
          -72.433333,
          -40.633333
        ]
      },
      "type": "Feature",
      "properties": {
        "hierarchy": [
          "tgn:7314955",
          "tgn:1001699",
          "tgn:1000049",
          "tgn:1000002",
          "tgn:7029392"
        ],
        "placetype": [
          "aat:300008699"
        ],
        "id": 7314955,
        "name:xx": "Licán, Río"
      }
    },
    {
      "geometry": {
        "type": "Point",
        "coordinates": [
          -73.1,
          -39.016667
        ]
      },
      "type": "Feature",
      "properties": {
        "hierarchy": [
          "tgn:7314956",
          "tgn:1001692",
          "tgn:1000049",
          "tgn:1000002",
          "tgn:7029392"
        ],
        "placetype": [
          "aat:300008791"
        ],
        "id": 7314956,
        "name:xx": "Licán, Isla"
      }
    },
    {
      "geometry": {
        "type": "Point",
        "coordinates": [
          -68.233333,
          -22.666667
        ]
      },
      "type": "Feature",
      "properties": {
        "hierarchy": [
          "tgn:7314957",
          "tgn:7016598",
          "tgn:1000049",
          "tgn:1000002",
          "tgn:7029392"
        ],
        "placetype": [
          "aat:300008347"
        ],
        "id": 7314957,
        "name:xx": "Licán"
      }
    },
    {
      "geometry": {
        "type": "Point",
        "coordinates": [
          -72.4,
          -40.6
        ]
      },
      "type": "Feature",
      "properties": {
        "hierarchy": [
          "tgn:7314958",
          "tgn:1001699",
          "tgn:1000049",
          "tgn:1000002",
          "tgn:7029392"
        ],
        "placetype": [
          "aat:300000206"
        ],
        "id": 7314958,
        "name:xx": "Licán"
      }
    },
    {
      "geometry": {
        "type": "Point",
        "coordinates": [
          -69.266667,
          -19.1
        ]
      },
      "type": "Feature",
      "properties": {
        "hierarchy": [
          "tgn:7314959",
          "tgn:7002464",
          "tgn:1000049",
          "tgn:1000002",
          "tgn:7029392"
        ],
        "placetype": [
          "aat:300008795"
        ],
        "id": 7314959,
        "name:xx": "Libunuma, Cerro"
      }
    }
  ]
}
