{
  "geometry": {
    "type": "Point",
    "coordinates": [
      79.800989,
      23.131468
    ]
  },
  "type": "Feature",
  "properties": {
    "hierarchy": [
      "tgn:7545245",
      "tgn:1000004",
      "tgn:7000198",
      "tgn:1001894",
      "tgn:7029392"
    ],
    "placetype": [
      "aat:300008347"
    ],
    "name:en": "Bherāghāt",
    "id": 7545245
  }
}
