{
  "geometry": {
    "type": "Point",
    "coordinates": [
      -79.2167,
      39.7833
    ]
  },
  "type": "Feature",
  "properties": {
    "hierarchy": [
      "tgn:2171126",
      "tgn:1000001",
      "tgn:7012149",
      "tgn:1002904",
      "tgn:7007710",
      "tgn:7029392"
    ],
    "placetype": [
      "aat:300008697"
    ],
    "id": 2171126,
    "name:xx": "Big Spring"
  }
}
