{
  "type": "FeatureCollection",
  "features": [
    {
      "geometry": {
        "type": "Point",
        "coordinates": [
          -80.7833,
          34.15
        ]
      },
      "type": "Feature",
      "properties": {
        "hierarchy": [
          "tgn:2765970",
          "tgn:1000001",
          "tgn:7012149",
          "tgn:2001752",
          "tgn:7007712",
          "tgn:7029392"
        ],
        "placetype": [
          "aat:300008347"
        ],
        "id": 2765970,
        "name:xx": "White Hills"
      }
    },
    {
      "geometry": {
        "type": "Point",
        "coordinates": [
          -113.7,
          37.0833
        ]
      },
      "type": "Feature",
      "properties": {
        "hierarchy": [
          "tgn:2765971",
          "tgn:1000001",
          "tgn:7012149",
          "tgn:2002127",
          "tgn:7007827",
          "tgn:7029392"
        ],
        "placetype": [
          "aat:300008798"
        ],
        "id": 2765971,
        "name:xx": "White Hills"
      }
    },
    {
      "geometry": {
        "type": "Point",
        "coordinates": [
          -112.15,
          38.4833
        ]
      },
      "type": "Feature",
      "properties": {
        "hierarchy": [
          "tgn:2765972",
          "tgn:1000001",
          "tgn:7012149",
          "tgn:2002116",
          "tgn:7007827",
          "tgn:7029392"
        ],
        "placetype": [
          "aat:300008798"
        ],
        "id": 2765972,
        "name:xx": "White Hills"
      }
    },
    {
      "geometry": {
        "type": "Point",
        "coordinates": [
          -111.7333,
          39.1
        ]
      },
      "type": "Feature",
      "properties": {
        "hierarchy": [
          "tgn:2765973",
          "tgn:1000001",
          "tgn:7012149",
          "tgn:7007827",
          "tgn:7029392"
        ],
        "placetype": [
          "aat:300386831"
        ],
        "id": 2765973,
        "name:xx": "White Hills"
      }
    },
    {
      "geometry": {
        "type": "Point",
        "coordinates": [
          -105.0167,
          42.65
        ]
      },
      "type": "Feature",
      "properties": {
        "hierarchy": [
          "tgn:2765974",
          "tgn:1000001",
          "tgn:2002369",
          "tgn:7012149",
          "tgn:7007923",
          "tgn:7029392"
        ],
        "placetype": [
          "aat:300008798"
        ],
        "id": 2765974,
        "name:xx": "White Hills"
      }
    },
    {
      "geometry": {
        "type": "Point",
        "coordinates": [
          -73.15,
          41.35
        ]
      },
      "type": "Feature",
      "properties": {
        "hierarchy": [
          "tgn:2765975",
          "tgn:1000001",
          "tgn:1002712",
          "tgn:7012149",
          "tgn:7007159",
          "tgn:7029392"
        ],
        "placetype": [
          "aat:300008699"
        ],
        "id": 2765975,
        "name:xx": "White Hills Community Brook"
      }
    },
    {
      "geometry": {
        "type": "Point",
        "coordinates": [
          -110.0833,
          32.85
        ]
      },
      "type": "Feature",
      "properties": {
        "hierarchy": [
          "tgn:2765976",
          "tgn:1000001",
          "tgn:7006451",
          "tgn:2000094",
          "tgn:7012149",
          "tgn:7029392"
        ],
        "placetype": [
          "aat:300006191"
        ],
        "id": 2765976,
        "name:xx": "White Hills Tank"
      }
    },
    {
      "geometry": {
        "type": "Point",
        "coordinates": [
          -111.45,
          34.2833
        ]
      },
      "type": "Feature",
      "properties": {
        "hierarchy": [
          "tgn:2765977",
          "tgn:1000001",
          "tgn:7006451",
          "tgn:2000093",
          "tgn:7012149",
          "tgn:7029392"
        ],
        "placetype": [
          "aat:300006191"
        ],
        "id": 2765977,
        "name:xx": "White Hills Tank"
      }
    },
    {
      "geometry": {
        "type": "Point",
        "coordinates": [
          -112.4333,
          34.95
        ]
      },
      "type": "Feature",
      "properties": {
        "hierarchy": [
          "tgn:2765978",
          "tgn:1000001",
          "tgn:7006451",
          "tgn:7012149",
          "tgn:2000103",
          "tgn:7029392"
        ],
        "placetype": [
          "aat:300006191"
        ],
        "id": 2765978,
        "name:xx": "White Hills Tank"
      }
    },
    {
      "geometry": {
        "type": "Point",
        "coordinates": [
          -87.9,
          34.6167
        ]
      },
      "type": "Feature",
      "properties": {
        "hierarchy": [
          "tgn:2765979",
          "tgn:7002659",
          "tgn:1000001",
          "tgn:2000016",
          "tgn:7012149",
          "tgn:7029392"
        ],
        "placetype": [
          "aat:300008761"
        ],
        "id": 2765979,
        "name:xx": "White Hollow"
      }
    }
  ]
}
