{
  "geometry": {
    "type": "Point",
    "coordinates": [
      -112.4833,
      48.5333
    ]
  },
  "type": "Feature",
  "properties": {
    "hierarchy": [
      "tgn:2689207",
      "tgn:1000001",
      "tgn:7012149",
      "tgn:2001277",
      "tgn:7007524",
      "tgn:7029392"
    ],
    "placetype": [
      "aat:300008697"
    ],
    "id": 2689207,
    "name:xx": "Squaw Buttes"
  }
}
