{
  "type": "FeatureCollection",
  "features": [
    {
      "geometry": {
        "type": "Point",
        "coordinates": [
          -93.5,
          41.5667
        ]
      },
      "type": "Feature",
      "properties": {
        "hierarchy": [
          "tgn:2221141",
          "tgn:1000001",
          "tgn:7012149",
          "tgn:2000637",
          "tgn:7007253",
          "tgn:7029392"
        ],
        "placetype": [
          "aat:300008347"
        ],
        "id": 2221141,
        "name:xx": "Carbondale"
      }
    },
    {
      "geometry": {
        "type": "Point",
        "coordinates": [
          -87.6,
          45.2667
        ]
      },
      "type": "Feature",
      "properties": {
        "hierarchy": [
          "tgn:2221142",
          "tgn:1000001",
          "tgn:7012149",
          "tgn:2000978",
          "tgn:7007520",
          "tgn:7029392"
        ],
        "placetype": [
          "aat:300008347"
        ],
        "id": 2221142,
        "name:xx": "Carbondale"
      }
    },
    {
      "geometry": {
        "type": "Point",
        "coordinates": [
          -82.3,
          39.3833
        ]
      },
      "type": "Feature",
      "properties": {
        "hierarchy": [
          "tgn:2221143",
          "tgn:1000001",
          "tgn:7012149",
          "tgn:7007706",
          "tgn:7029392"
        ],
        "placetype": [
          "aat:300008706"
        ],
        "id": 2221143,
        "name:xx": "Carbondale Creek"
      }
    },
    {
      "geometry": {
        "type": "Point",
        "coordinates": [
          -75.45,
          41.5667
        ]
      },
      "type": "Feature",
      "properties": {
        "hierarchy": [
          "tgn:2221144",
          "tgn:1000001",
          "tgn:7012149",
          "tgn:1002564",
          "tgn:7007710",
          "tgn:7029392"
        ],
        "placetype": [
          "aat:300006191"
        ],
        "id": 2221144,
        "name:xx": "Carbondale Number Four Reservoir"
      }
    },
    {
      "geometry": {
        "type": "Point",
        "coordinates": [
          -89.2167,
          37.6833
        ]
      },
      "type": "Feature",
      "properties": {
        "hierarchy": [
          "tgn:2221145",
          "tgn:1000001",
          "tgn:7012149",
          "tgn:2000512",
          "tgn:7007251",
          "tgn:7029392"
        ],
        "placetype": [
          "aat:300006191"
        ],
        "id": 2221145,
        "name:xx": "Carbondale Reservoir"
      }
    },
    {
      "geometry": {
        "type": "Point",
        "coordinates": [
          -108.95,
          39.45
        ]
      },
      "type": "Feature",
      "properties": {
        "hierarchy": [
          "tgn:2221146",
          "tgn:1000001",
          "tgn:7012149",
          "tgn:2000214",
          "tgn:7007158",
          "tgn:7029392"
        ],
        "placetype": [
          "aat:300008347"
        ],
        "id": 2221146,
        "name:xx": "Carbonera"
      }
    },
    {
      "geometry": {
        "type": "Point",
        "coordinates": [
          -121.9667,
          37.0833
        ]
      },
      "type": "Feature",
      "properties": {
        "hierarchy": [
          "tgn:2221147",
          "tgn:1000001",
          "tgn:7012149",
          "tgn:7007157",
          "tgn:1002869",
          "tgn:7029392"
        ],
        "placetype": [
          "aat:300008706"
        ],
        "id": 2221147,
        "name:xx": "Carbonera Creek"
      }
    },
    {
      "geometry": {
        "type": "Point",
        "coordinates": [
          -107.8,
          37.8667
        ]
      },
      "type": "Feature",
      "properties": {
        "hierarchy": [
          "tgn:2221148",
          "tgn:1000001",
          "tgn:7012149",
          "tgn:7007158",
          "tgn:2000248",
          "tgn:7029392"
        ],
        "placetype": [
          "aat:300000390"
        ],
        "id": 2221148,
        "name:xx": "Carbonero Mine"
      }
    },
    {
      "geometry": {
        "type": "Point",
        "coordinates": [
          -103.8,
          35.85
        ]
      },
      "type": "Feature",
      "properties": {
        "hierarchy": [
          "tgn:2221149",
          "tgn:1000001",
          "tgn:7012149",
          "tgn:2001439",
          "tgn:7007566",
          "tgn:7029392"
        ],
        "placetype": [
          "aat:300000390"
        ],
        "id": 2221149,
        "name:xx": "Carbonic Number Five Mitchell"
      }
    }
  ]
}
