{
  "geometry": {
    "type": "Point",
    "coordinates": [
      -94.0833,
      43.1167
    ]
  },
  "type": "Feature",
  "properties": {
    "hierarchy": [
      "tgn:2294851",
      "tgn:1000001",
      "tgn:7012149",
      "tgn:2000615",
      "tgn:7007253",
      "tgn:7029392"
    ],
    "placetype": [
      "aat:300006075"
    ],
    "id": 2294851,
    "name:xx": "Drainage Ditch Number 84"
  }
}
