{
  "geometry": {
    "type": "Point",
    "coordinates": [
      -120.9667,
      39.2667
    ]
  },
  "type": "Feature",
  "properties": {
    "hierarchy": [
      "tgn:2526016",
      "tgn:1000001",
      "tgn:7012149",
      "tgn:7007157",
      "tgn:1002710",
      "tgn:7029392"
    ],
    "placetype": [
      "aat:300008706"
    ],
    "id": 2526016,
    "name:xx": "Mosquito Creek"
  }
}
