{
  "type": "FeatureCollection",
  "features": [
    {
      "geometry": {
        "type": "Point",
        "coordinates": [
          -2.016667,
          53.75
        ]
      },
      "type": "Feature",
      "properties": {
        "hierarchy": [
          "tgn:7010456",
          "tgn:1003573",
          "tgn:7002445",
          "tgn:1000003",
          "tgn:7029507",
          "tgn:7008591",
          "tgn:7029392"
        ],
        "placetype": [
          "aat:300008347",
          "aat:300008372"
        ],
        "id": 7010456,
        "name:xx": "Heptonstall",
        "name:ang": "Crumbetonestun"
      }
    },
    {
      "geometry": {
        "type": "Point",
        "coordinates": [
          -1.916667,
          53.7
        ]
      },
      "type": "Feature",
      "properties": {
        "hierarchy": [
          "tgn:7010457",
          "tgn:1003573",
          "tgn:7002445",
          "tgn:1000003",
          "tgn:7029507",
          "tgn:7008591",
          "tgn:7029392"
        ],
        "placetype": [
          "aat:300008347"
        ],
        "name:en": "Sowerby Bridge",
        "id": 7010457
      }
    },
    {
      "geometry": {
        "type": "Point",
        "coordinates": [
          -2.083333,
          53.716667
        ]
      },
      "type": "Feature",
      "properties": {
        "hierarchy": [
          "tgn:7010458",
          "tgn:1003573",
          "tgn:7002445",
          "tgn:1000003",
          "tgn:7029507",
          "tgn:7008591",
          "tgn:7029392"
        ],
        "placetype": [
          "aat:300008347"
        ],
        "name:en": "Todmorden",
        "id": 7010458
      }
    },
    {
      "geometry": {
        "type": "Point",
        "coordinates": [
          -1.816667,
          53.766667
        ]
      },
      "type": "Feature",
      "properties": {
        "hierarchy": [
          "tgn:7010459",
          "tgn:1003567",
          "tgn:7002445",
          "tgn:1000003",
          "tgn:7029507",
          "tgn:7008591",
          "tgn:7029392"
        ],
        "placetype": [
          "aat:300008347"
        ],
        "id": 7010459,
        "name:xx": "Clayton"
      }
    }
  ]
}
