{
  "type": "FeatureCollection",
  "features": [
    {
      "geometry": {
        "type": "Point",
        "coordinates": [
          -68.1167,
          46.7333
        ]
      },
      "type": "Feature",
      "properties": {
        "hierarchy": [
          "tgn:2685970",
          "tgn:2000919",
          "tgn:1000001",
          "tgn:7012149",
          "tgn:7007515",
          "tgn:7029392"
        ],
        "placetype": [
          "aat:300008699"
        ],
        "id": 2685970,
        "name:xx": "Spring Brook"
      }
    },
    {
      "geometry": {
        "type": "Point",
        "coordinates": [
          -76.55,
          38.3
        ]
      },
      "type": "Feature",
      "properties": {
        "hierarchy": [
          "tgn:2685971",
          "tgn:1000001",
          "tgn:7016098",
          "tgn:7012149",
          "tgn:7007516",
          "tgn:7029392"
        ],
        "placetype": [
          "aat:300008699"
        ],
        "id": 2685971,
        "name:xx": "Spring Brook"
      }
    },
    {
      "geometry": {
        "type": "Point",
        "coordinates": [
          -71.55,
          42.0833
        ]
      },
      "type": "Feature",
      "properties": {
        "hierarchy": [
          "tgn:2685972",
          "tgn:1000001",
          "tgn:7012149",
          "tgn:1003038",
          "tgn:7007517",
          "tgn:7029392"
        ],
        "placetype": [
          "aat:300008699"
        ],
        "id": 2685972,
        "name:xx": "Spring Brook"
      }
    },
    {
      "geometry": {
        "type": "Point",
        "coordinates": [
          -71.2667,
          42.5167
        ]
      },
      "type": "Feature",
      "properties": {
        "hierarchy": [
          "tgn:2685973",
          "tgn:1000001",
          "tgn:1002665",
          "tgn:7012149",
          "tgn:7007517",
          "tgn:7029392"
        ],
        "placetype": [
          "aat:300008699"
        ],
        "id": 2685973,
        "name:xx": "Spring Brook"
      }
    },
    {
      "geometry": {
        "type": "Point",
        "coordinates": [
          -71.2167,
          42.1167
        ]
      },
      "type": "Feature",
      "properties": {
        "hierarchy": [
          "tgn:2685974",
          "tgn:1000001",
          "tgn:1002724",
          "tgn:7012149",
          "tgn:7007517",
          "tgn:7029392"
        ],
        "placetype": [
          "aat:300008699"
        ],
        "id": 2685974,
        "name:xx": "Spring Brook"
      }
    },
    {
      "geometry": {
        "type": "Point",
        "coordinates": [
          -70.9167,
          41.8
        ]
      },
      "type": "Feature",
      "properties": {
        "hierarchy": [
          "tgn:2685975",
          "tgn:1000001",
          "tgn:7014423",
          "tgn:7012149",
          "tgn:7007517",
          "tgn:7029392"
        ],
        "placetype": [
          "aat:300008699"
        ],
        "id": 2685975,
        "name:xx": "Spring Brook"
      }
    },
    {
      "geometry": {
        "type": "Point",
        "coordinates": [
          -70.9833,
          41.85
        ]
      },
      "type": "Feature",
      "properties": {
        "hierarchy": [
          "tgn:2685976",
          "tgn:1002201",
          "tgn:1000001",
          "tgn:7012149",
          "tgn:7007517",
          "tgn:7029392"
        ],
        "placetype": [
          "aat:300008699"
        ],
        "id": 2685976,
        "name:xx": "Spring Brook"
      }
    },
    {
      "geometry": {
        "type": "Point",
        "coordinates": [
          -86,
          42.45
        ]
      },
      "type": "Feature",
      "properties": {
        "hierarchy": [
          "tgn:2685977",
          "tgn:1002140",
          "tgn:1000001",
          "tgn:7012149",
          "tgn:7007520",
          "tgn:7029392"
        ],
        "placetype": [
          "aat:300008699"
        ],
        "id": 2685977,
        "name:xx": "Spring Brook"
      }
    },
    {
      "geometry": {
        "type": "Point",
        "coordinates": [
          -84.2333,
          42.8833
        ]
      },
      "type": "Feature",
      "properties": {
        "hierarchy": [
          "tgn:2685978",
          "tgn:1000001",
          "tgn:7012149",
          "tgn:1002892",
          "tgn:7007520",
          "tgn:7029392"
        ],
        "placetype": [
          "aat:300008699"
        ],
        "id": 2685978,
        "name:xx": "Spring Brook"
      }
    },
    {
      "geometry": {
        "type": "Point",
        "coordinates": [
          -83.6333,
          41.7667
        ]
      },
      "type": "Feature",
      "properties": {
        "hierarchy": [
          "tgn:2685979",
          "tgn:1000001",
          "tgn:7012149",
          "tgn:1002679",
          "tgn:7007520",
          "tgn:7029392"
        ],
        "placetype": [
          "aat:300008699"
        ],
        "id": 2685979,
        "name:xx": "Spring Brook"
      }
    }
  ]
}
