{
  "geometry": {
    "type": "Point",
    "coordinates": [
      72.040142,
      24.800533
    ]
  },
  "type": "Feature",
  "properties": {
    "hierarchy": [
      "tgn:7555855",
      "tgn:1000004",
      "tgn:7000198",
      "tgn:7016788",
      "tgn:7029392"
    ],
    "placetype": [
      "aat:300008347"
    ],
    "name:en": "Mokhātra",
    "id": 7555855
  }
}
