{
  "geometry": {
    "type": "Point",
    "coordinates": [
      -93.55,
      47.1833
    ]
  },
  "type": "Feature",
  "properties": {
    "hierarchy": [
      "tgn:2437593",
      "tgn:1000001",
      "tgn:7012149",
      "tgn:2001029",
      "tgn:7007521",
      "tgn:7029392"
    ],
    "placetype": [
      "aat:300132316"
    ],
    "id": 2437593,
    "name:xx": "King Bay"
  }
}
