{
  "type": "FeatureCollection",
  "features": [
    {
      "geometry": {
        "type": "Point",
        "coordinates": [
          -92.15,
          14.966667
        ]
      },
      "type": "Feature",
      "properties": {
        "hierarchy": [
          "tgn:7365480",
          "tgn:7005580",
          "tgn:1000001",
          "tgn:7005560",
          "tgn:7029392"
        ],
        "placetype": [
          "aat:300008347"
        ],
        "id": 7365480,
        "name:xx": "El Talismán"
      }
    },
    {
      "geometry": {
        "type": "Point",
        "coordinates": [
          -102.766667,
          20.1
        ]
      },
      "type": "Feature",
      "properties": {
        "hierarchy": [
          "tgn:7365481",
          "tgn:1000001",
          "tgn:7005590",
          "tgn:7005560",
          "tgn:7029392"
        ],
        "placetype": [
          "aat:300008795"
        ],
        "id": 7365481,
        "name:xx": "El Talayote, Cerro"
      }
    },
    {
      "geometry": {
        "type": "Point",
        "coordinates": [
          -107.159444,
          24.615556
        ]
      },
      "type": "Feature",
      "properties": {
        "hierarchy": [
          "tgn:7365482",
          "tgn:1000001",
          "tgn:7005595",
          "tgn:7005560",
          "tgn:7029392"
        ],
        "placetype": [
          "aat:300008347"
        ],
        "id": 7365482,
        "name:xx": "El Talayote"
      }
    },
    {
      "geometry": {
        "type": "Point",
        "coordinates": [
          -103.433333,
          20.166667
        ]
      },
      "type": "Feature",
      "properties": {
        "hierarchy": [
          "tgn:7365483",
          "tgn:7005586",
          "tgn:1000001",
          "tgn:7005560",
          "tgn:7029392"
        ],
        "placetype": [
          "aat:300008795"
        ],
        "id": 7365483,
        "name:xx": "El Tajo, Cerro"
      }
    },
    {
      "geometry": {
        "type": "Point",
        "coordinates": [
          -109.65,
          30.516667
        ]
      },
      "type": "Feature",
      "properties": {
        "hierarchy": [
          "tgn:7365484",
          "tgn:1000001",
          "tgn:1001960",
          "tgn:7005560",
          "tgn:7029392"
        ],
        "placetype": [
          "aat:300007783"
        ],
        "id": 7365484,
        "name:xx": "El Tajo"
      }
    },
    {
      "geometry": {
        "type": "Point",
        "coordinates": [
          -100.431389,
          24.376389
        ]
      },
      "type": "Feature",
      "properties": {
        "hierarchy": [
          "tgn:7365485",
          "tgn:1000001",
          "tgn:7005589",
          "tgn:7005560",
          "tgn:7029392"
        ],
        "placetype": [
          "aat:300008347"
        ],
        "id": 7365485,
        "name:es": "El Tajo"
      }
    },
    {
      "geometry": {
        "type": "Point",
        "coordinates": [
          -101.233333,
          20.583333
        ]
      },
      "type": "Feature",
      "properties": {
        "hierarchy": [
          "tgn:7365486",
          "tgn:7005584",
          "tgn:1000001",
          "tgn:7005560",
          "tgn:7029392"
        ],
        "placetype": [
          "aat:300008347"
        ],
        "id": 7365486,
        "name:xx": "El Tajo"
      }
    },
    {
      "geometry": {
        "type": "Point",
        "coordinates": [
          -102.766667,
          19.683333
        ]
      },
      "type": "Feature",
      "properties": {
        "hierarchy": [
          "tgn:7365487",
          "tgn:1000001",
          "tgn:7005590",
          "tgn:7005560",
          "tgn:7029392"
        ],
        "placetype": [
          "aat:300008347"
        ],
        "id": 7365487,
        "name:xx": "El Tajo"
      }
    },
    {
      "geometry": {
        "type": "Point",
        "coordinates": [
          -98.35,
          25.733333
        ]
      },
      "type": "Feature",
      "properties": {
        "hierarchy": [
          "tgn:7365488",
          "tgn:1000001",
          "tgn:7005597",
          "tgn:7005560",
          "tgn:7029392"
        ],
        "placetype": [
          "aat:300008347"
        ],
        "id": 7365488,
        "name:xx": "El Tajito"
      }
    },
    {
      "geometry": {
        "type": "Point",
        "coordinates": [
          -103.416667,
          25.566667
        ]
      },
      "type": "Feature",
      "properties": {
        "hierarchy": [
          "tgn:7365489",
          "tgn:1001853",
          "tgn:1000001",
          "tgn:7005560",
          "tgn:7029392"
        ],
        "placetype": [
          "aat:300008347"
        ],
        "id": 7365489,
        "name:xx": "El Tajito"
      }
    }
  ]
}
