{
  "geometry": {
    "type": "Point",
    "coordinates": [
      -1.6833,
      47.0833
    ]
  },
  "type": "Feature",
  "properties": {
    "hierarchy": [
      "tgn:1122154",
      "tgn:1000003",
      "tgn:1000070",
      "tgn:7029392"
    ],
    "placetype": [
      "aat:300008707"
    ],
    "id": 1122154,
    "name:xx": "Boulogne"
  }
}
