{
  "geometry": {
    "type": "Point",
    "coordinates": [
      -101.05,
      25.05
    ]
  },
  "type": "Feature",
  "properties": {
    "hierarchy": [
      "tgn:7429346",
      "tgn:1001853",
      "tgn:1000001",
      "tgn:7005560",
      "tgn:7029392"
    ],
    "placetype": [
      "aat:300007783"
    ],
    "id": 7429346,
    "name:xx": "Estació Guillermo"
  }
}
