{
  "geometry": {
    "type": "Point",
    "coordinates": [
      -96.0667,
      34.5833
    ]
  },
  "type": "Feature",
  "properties": {
    "hierarchy": [
      "tgn:2578801",
      "tgn:1000001",
      "tgn:7012149",
      "tgn:7007707",
      "tgn:7029392"
    ],
    "placetype": [
      "aat:300008761"
    ],
    "id": 2578801,
    "name:xx": "Phillips Hollow"
  }
}
