{
  "geometry": {
    "type": "Point",
    "coordinates": [
      13.25,
      47.4167
    ]
  },
  "type": "Feature",
  "properties": {
    "hierarchy": [
      "tgn:7003027",
      "tgn:1000003",
      "tgn:1000062",
      "tgn:7029392"
    ],
    "placetype": [
      "aat:300387064",
      "aat:300000776"
    ],
    "id": 7003027,
    "name:xx": "Salzburg"
  }
}
