{
  "geometry": {
    "type": "Point",
    "coordinates": [
      -115.5833,
      45.7667
    ]
  },
  "type": "Feature",
  "properties": {
    "hierarchy": [
      "tgn:2382471",
      "tgn:1000001",
      "tgn:7012149",
      "tgn:2000476",
      "tgn:7007250",
      "tgn:7029392"
    ],
    "placetype": [
      "aat:300000390"
    ],
    "id": 2382471,
    "name:xx": "Haystack Mine"
  }
}
