{
  "geometry": {
    "type": "Point",
    "coordinates": [
      -112.7333,
      51.6667
    ]
  },
  "type": "Feature",
  "properties": {
    "hierarchy": [
      "tgn:1013246",
      "tgn:7005694",
      "tgn:7005685",
      "tgn:1000001",
      "tgn:7029392"
    ],
    "placetype": [
      "aat:300008347"
    ],
    "id": 1013246,
    "name:xx": "Morrin"
  }
}
