{
  "type": "FeatureCollection",
  "features": [
    {
      "geometry": {
        "type": "Point",
        "coordinates": [
          -95.2333,
          32.3667
        ]
      },
      "type": "Feature",
      "properties": {
        "hierarchy": [
          "tgn:2426100",
          "tgn:1000001",
          "tgn:7012149",
          "tgn:1002898",
          "tgn:7007826",
          "tgn:7029392"
        ],
        "placetype": [
          "aat:300008699"
        ],
        "id": 2426100,
        "name:xx": "Jones Branch"
      }
    },
    {
      "geometry": {
        "type": "Point",
        "coordinates": [
          -94.6833,
          31.05
        ]
      },
      "type": "Feature",
      "properties": {
        "hierarchy": [
          "tgn:2426101",
          "tgn:1000001",
          "tgn:7012149",
          "tgn:1002795",
          "tgn:7007826",
          "tgn:7029392"
        ],
        "placetype": [
          "aat:300008699"
        ],
        "id": 2426101,
        "name:xx": "Jones Branch"
      }
    },
    {
      "geometry": {
        "type": "Point",
        "coordinates": [
          -95.8333,
          31.15
        ]
      },
      "type": "Feature",
      "properties": {
        "hierarchy": [
          "tgn:2426102",
          "tgn:1000001",
          "tgn:7012149",
          "tgn:1002590",
          "tgn:7007826",
          "tgn:7029392"
        ],
        "placetype": [
          "aat:300008699"
        ],
        "id": 2426102,
        "name:xx": "Jones Branch"
      }
    },
    {
      "geometry": {
        "type": "Point",
        "coordinates": [
          -95.1833,
          31.6833
        ]
      },
      "type": "Feature",
      "properties": {
        "hierarchy": [
          "tgn:2426103",
          "tgn:1000001",
          "tgn:7012149",
          "tgn:1002263",
          "tgn:7007826",
          "tgn:7029392"
        ],
        "placetype": [
          "aat:300008699"
        ],
        "id": 2426103,
        "name:xx": "Jones Branch"
      }
    },
    {
      "geometry": {
        "type": "Point",
        "coordinates": [
          -94.1833,
          31.8
        ]
      },
      "type": "Feature",
      "properties": {
        "hierarchy": [
          "tgn:2426104",
          "tgn:1000001",
          "tgn:7012149",
          "tgn:2002073",
          "tgn:7007826",
          "tgn:7029392"
        ],
        "placetype": [
          "aat:300008699"
        ],
        "id": 2426104,
        "name:xx": "Jones Branch"
      }
    },
    {
      "geometry": {
        "type": "Point",
        "coordinates": [
          -81.05,
          36.8
        ]
      },
      "type": "Feature",
      "properties": {
        "hierarchy": [
          "tgn:2426105",
          "tgn:1000001",
          "tgn:7012149",
          "tgn:2002164",
          "tgn:7007919",
          "tgn:7029392"
        ],
        "placetype": [
          "aat:300008699"
        ],
        "id": 2426105,
        "name:xx": "Jones Branch"
      }
    },
    {
      "geometry": {
        "type": "Point",
        "coordinates": [
          -79.0167,
          37.2667
        ]
      },
      "type": "Feature",
      "properties": {
        "hierarchy": [
          "tgn:2426106",
          "tgn:1000001",
          "tgn:2002150",
          "tgn:7012149",
          "tgn:7007919",
          "tgn:7029392"
        ],
        "placetype": [
          "aat:300008699"
        ],
        "id": 2426106,
        "name:xx": "Jones Branch"
      }
    },
    {
      "geometry": {
        "type": "Point",
        "coordinates": [
          -80.2167,
          37.5333
        ]
      },
      "type": "Feature",
      "properties": {
        "hierarchy": [
          "tgn:2426107",
          "tgn:1000001",
          "tgn:7012149",
          "tgn:2002154",
          "tgn:7007919",
          "tgn:7029392"
        ],
        "placetype": [
          "aat:300008699"
        ],
        "id": 2426107,
        "name:xx": "Jones Branch"
      }
    },
    {
      "geometry": {
        "type": "Point",
        "coordinates": [
          -76.8167,
          38.05
        ]
      },
      "type": "Feature",
      "properties": {
        "hierarchy": [
          "tgn:2426108",
          "tgn:1000001",
          "tgn:7012149",
          "tgn:7014334",
          "tgn:7007919",
          "tgn:7029392"
        ],
        "placetype": [
          "aat:300008699"
        ],
        "id": 2426108,
        "name:xx": "Jones Branch"
      }
    },
    {
      "geometry": {
        "type": "Point",
        "coordinates": [
          -76.65,
          38.0667
        ]
      },
      "type": "Feature",
      "properties": {
        "hierarchy": [
          "tgn:2426109",
          "tgn:1000001",
          "tgn:7012149",
          "tgn:1003018",
          "tgn:7007919",
          "tgn:7029392"
        ],
        "placetype": [
          "aat:300008699"
        ],
        "id": 2426109,
        "name:xx": "Jones Branch"
      }
    }
  ]
}
