{
  "type": "FeatureCollection",
  "features": [
    {
      "geometry": {
        "type": "Point",
        "coordinates": [
          -76.1,
          38.7333
        ]
      },
      "type": "Feature",
      "properties": {
        "hierarchy": [
          "tgn:2229460",
          "tgn:1000001",
          "tgn:2000939",
          "tgn:7012149",
          "tgn:7007516",
          "tgn:7029392"
        ],
        "placetype": [
          "aat:300008347"
        ],
        "id": 2229460,
        "name:xx": "Cedar Point"
      }
    },
    {
      "geometry": {
        "type": "Point",
        "coordinates": [
          -84.4833,
          46.4333
        ]
      },
      "type": "Feature",
      "properties": {
        "hierarchy": [
          "tgn:2229461",
          "tgn:1000001",
          "tgn:2000952",
          "tgn:7012149",
          "tgn:7007520",
          "tgn:7029392"
        ],
        "placetype": [
          "aat:300008850"
        ],
        "id": 2229461,
        "name:xx": "Cedar Point"
      }
    },
    {
      "geometry": {
        "type": "Point",
        "coordinates": [
          -93.6833,
          44.2
        ]
      },
      "type": "Feature",
      "properties": {
        "hierarchy": [
          "tgn:2229462",
          "tgn:1000001",
          "tgn:7012149",
          "tgn:2001038",
          "tgn:7007521",
          "tgn:7029392"
        ],
        "placetype": [
          "aat:300008850"
        ],
        "id": 2229462,
        "name:xx": "Cedar Point"
      }
    },
    {
      "geometry": {
        "type": "Point",
        "coordinates": [
          -93.65,
          44.9
        ]
      },
      "type": "Feature",
      "properties": {
        "hierarchy": [
          "tgn:2229463",
          "tgn:1000001",
          "tgn:2001025",
          "tgn:7012149",
          "tgn:7007521",
          "tgn:7029392"
        ],
        "placetype": [
          "aat:300008850"
        ],
        "id": 2229463,
        "name:xx": "Cedar Point"
      }
    },
    {
      "geometry": {
        "type": "Point",
        "coordinates": [
          -94.5667,
          47.1333
        ]
      },
      "type": "Feature",
      "properties": {
        "hierarchy": [
          "tgn:2229464",
          "tgn:1000001",
          "tgn:2001009",
          "tgn:7012149",
          "tgn:7007521",
          "tgn:7029392"
        ],
        "placetype": [
          "aat:300008850"
        ],
        "id": 2229464,
        "name:xx": "Cedar Point"
      }
    },
    {
      "geometry": {
        "type": "Point",
        "coordinates": [
          -89.3333,
          30.3333
        ]
      },
      "type": "Feature",
      "properties": {
        "hierarchy": [
          "tgn:2229465",
          "tgn:1000001",
          "tgn:7012149",
          "tgn:2001108",
          "tgn:7007522",
          "tgn:7029392"
        ],
        "placetype": [
          "aat:300008850"
        ],
        "id": 2229465,
        "name:xx": "Cedar Point"
      }
    },
    {
      "geometry": {
        "type": "Point",
        "coordinates": [
          -88.7667,
          30.3833
        ]
      },
      "type": "Feature",
      "properties": {
        "hierarchy": [
          "tgn:2229466",
          "tgn:1000001",
          "tgn:7012149",
          "tgn:2001115",
          "tgn:7007522",
          "tgn:7029392"
        ],
        "placetype": [
          "aat:300008850"
        ],
        "id": 2229466,
        "name:xx": "Cedar Point"
      }
    },
    {
      "geometry": {
        "type": "Point",
        "coordinates": [
          -88.9667,
          30.4167
        ]
      },
      "type": "Feature",
      "properties": {
        "hierarchy": [
          "tgn:2229467",
          "tgn:1000001",
          "tgn:7012149",
          "tgn:2001109",
          "tgn:7007522",
          "tgn:7029392"
        ],
        "placetype": [
          "aat:300008850"
        ],
        "id": 2229467,
        "name:xx": "Cedar Point"
      }
    },
    {
      "geometry": {
        "type": "Point",
        "coordinates": [
          -89.75,
          33.8
        ]
      },
      "type": "Feature",
      "properties": {
        "hierarchy": [
          "tgn:2229468",
          "tgn:1000001",
          "tgn:7012149",
          "tgn:2001107",
          "tgn:7007522",
          "tgn:7029392"
        ],
        "placetype": [
          "aat:300008850"
        ],
        "id": 2229468,
        "name:xx": "Cedar Point"
      }
    },
    {
      "geometry": {
        "type": "Point",
        "coordinates": [
          -88.8333,
          33.4833
        ]
      },
      "type": "Feature",
      "properties": {
        "hierarchy": [
          "tgn:2229469",
          "tgn:1000001",
          "tgn:7012149",
          "tgn:2001138",
          "tgn:7007522",
          "tgn:7029392"
        ],
        "placetype": [
          "aat:300008347"
        ],
        "id": 2229469,
        "name:xx": "Cedar Point"
      }
    }
  ]
}
