{
  "type": "FeatureCollection",
  "features": [
    {
      "geometry": {
        "type": "Point",
        "coordinates": [
          -109.333333,
          28
        ]
      },
      "type": "Feature",
      "properties": {
        "hierarchy": [
          "tgn:7432590",
          "tgn:1000001",
          "tgn:1001960",
          "tgn:7005560",
          "tgn:7029392"
        ],
        "placetype": [
          "aat:300008347"
        ],
        "id": 7432590,
        "name:xx": "Ubalama"
      }
    },
    {
      "geometry": {
        "type": "Point",
        "coordinates": [
          -89.5,
          21.316667
        ]
      },
      "type": "Feature",
      "properties": {
        "hierarchy": [
          "tgn:7432591",
          "tgn:1000001",
          "tgn:7005600",
          "tgn:7005560",
          "tgn:7029392"
        ],
        "placetype": [
          "aat:300008347"
        ],
        "id": 7432591,
        "name:xx": "Uaymitun"
      }
    },
    {
      "geometry": {
        "type": "Point",
        "coordinates": [
          -88.316667,
          20.733333
        ]
      },
      "type": "Feature",
      "properties": {
        "hierarchy": [
          "tgn:7432592",
          "tgn:1000001",
          "tgn:7005600",
          "tgn:7005560",
          "tgn:7029392"
        ],
        "placetype": [
          "aat:300008347"
        ],
        "id": 7432592,
        "name:xx": "Uaymá"
      }
    },
    {
      "geometry": {
        "type": "Point",
        "coordinates": [
          -90.416667,
          19.65
        ]
      },
      "type": "Feature",
      "properties": {
        "hierarchy": [
          "tgn:7432593",
          "tgn:7005578",
          "tgn:1000001",
          "tgn:7005560",
          "tgn:7029392"
        ],
        "placetype": [
          "aat:300007783"
        ],
        "id": 7432593,
        "name:xx": "Uayamón"
      }
    },
    {
      "geometry": {
        "type": "Point",
        "coordinates": [
          -94.1,
          18.133333
        ]
      },
      "type": "Feature",
      "properties": {
        "hierarchy": [
          "tgn:7432594",
          "tgn:1000001",
          "tgn:7005599",
          "tgn:7005560",
          "tgn:7029392"
        ],
        "placetype": [
          "aat:300386885"
        ],
        "id": 7432594,
        "name:xx": "Tonalá, Barra de"
      }
    },
    {
      "geometry": {
        "type": "Point",
        "coordinates": [
          -93.766667,
          16.083333
        ]
      },
      "type": "Feature",
      "properties": {
        "hierarchy": [
          "tgn:7432596",
          "tgn:7005580",
          "tgn:1000001",
          "tgn:7005560",
          "tgn:7029392"
        ],
        "placetype": [
          "aat:300007783"
        ],
        "id": 7432596,
        "name:xx": "Tonalá"
      }
    },
    {
      "geometry": {
        "type": "Point",
        "coordinates": [
          -104,
          23.316667
        ]
      },
      "type": "Feature",
      "properties": {
        "hierarchy": [
          "tgn:7432597",
          "tgn:1000001",
          "tgn:7005601",
          "tgn:7005560",
          "tgn:7029392"
        ],
        "placetype": [
          "aat:300008347"
        ],
        "id": 7432597,
        "name:xx": "Tonalá"
      }
    },
    {
      "geometry": {
        "type": "Point",
        "coordinates": [
          -103.733333,
          22.566667
        ]
      },
      "type": "Feature",
      "properties": {
        "hierarchy": [
          "tgn:7432598",
          "tgn:7005586",
          "tgn:1000001",
          "tgn:7005560",
          "tgn:7029392"
        ],
        "placetype": [
          "aat:300008347"
        ],
        "id": 7432598,
        "name:xx": "Tonalá"
      }
    }
  ]
}
