{
  "geometry": {
    "type": "Point",
    "coordinates": [
      -76.2667,
      38.55
    ]
  },
  "type": "Feature",
  "properties": {
    "hierarchy": [
      "tgn:2391584",
      "tgn:1002338",
      "tgn:1000001",
      "tgn:7012149",
      "tgn:7007516",
      "tgn:7029392"
    ],
    "placetype": [
      "aat:300008850"
    ],
    "id": 2391584,
    "name:xx": "Hills Point Neck"
  }
}
