{
  "geometry": {
    "type": "Point",
    "coordinates": [
      -83.2167,
      38.75
    ]
  },
  "type": "Feature",
  "properties": {
    "hierarchy": [
      "tgn:2779891",
      "tgn:1000001",
      "tgn:7012149",
      "tgn:1002877",
      "tgn:7007706",
      "tgn:7029392"
    ],
    "placetype": [
      "aat:300006191"
    ],
    "id": 2779891,
    "name:xx": "Wolfden Lake"
  }
}
