{
  "geometry": {
    "type": "Point",
    "coordinates": [
      -68.333,
      19.616
    ]
  },
  "type": "Feature",
  "properties": {
    "hierarchy": [
      "tgn:7593422",
      "tgn:7005402",
      "tgn:1000001",
      "tgn:7005388",
      "tgn:7029392"
    ],
    "placetype": [
      "aat:300008347"
    ],
    "id": 7593422,
    "name:xx": "Cabo Engaño"
  }
}
