{
  "geometry": {
    "type": "Point",
    "coordinates": [
      -106.6833,
      44.1833
    ]
  },
  "type": "Feature",
  "properties": {
    "hierarchy": [
      "tgn:2735013",
      "tgn:1000001",
      "tgn:7012149",
      "tgn:2002374",
      "tgn:7007923",
      "tgn:7029392"
    ],
    "placetype": [
      "aat:300006075"
    ],
    "id": 2735013,
    "name:xx": "Twenty and One Half Ditch"
  }
}
