{
  "geometry": {
    "type": "Point",
    "coordinates": [
      -6.1667,
      5.3333
    ]
  },
  "type": "Feature",
  "properties": {
    "hierarchy": [
      "tgn:1000756",
      "tgn:7001242",
      "tgn:1000168",
      "tgn:7029392"
    ],
    "placetype": [
      "aat:300387064",
      "aat:300000772"
    ],
    "id": 1000756,
    "name:xx": "Sassandra, Département de"
  }
}
