{
  "geometry": {
    "type": "Point",
    "coordinates": [
      -73.1167,
      46.0333
    ]
  },
  "type": "Feature",
  "properties": {
    "hierarchy": [
      "tgn:1015678",
      "tgn:7005685",
      "tgn:1000001",
      "tgn:7005804",
      "tgn:7029392"
    ],
    "placetype": [
      "aat:300008347"
    ],
    "id": 1015678,
    "name:xx": "Saint-Joseph-de-Sorel"
  }
}
