{
  "type": "FeatureCollection",
  "features": [
    {
      "geometry": {
        "type": "Point",
        "coordinates": [
          -116.7,
          33.7333
        ]
      },
      "type": "Feature",
      "properties": {
        "hierarchy": [
          "tgn:2296700",
          "tgn:1000001",
          "tgn:7012149",
          "tgn:7007157",
          "tgn:1002828",
          "tgn:7029392"
        ],
        "placetype": [
          "aat:300008706"
        ],
        "id": 2296700,
        "name:xx": "Dry Creek"
      }
    },
    {
      "geometry": {
        "type": "Point",
        "coordinates": [
          -118.95,
          36.3
        ]
      },
      "type": "Feature",
      "properties": {
        "hierarchy": [
          "tgn:2296701",
          "tgn:1000001",
          "tgn:7012149",
          "tgn:7007157",
          "tgn:1002956",
          "tgn:7029392"
        ],
        "placetype": [
          "aat:300008706"
        ],
        "id": 2296701,
        "name:xx": "Dry Creek"
      }
    },
    {
      "geometry": {
        "type": "Point",
        "coordinates": [
          -118.9667,
          34.75
        ]
      },
      "type": "Feature",
      "properties": {
        "hierarchy": [
          "tgn:2296702",
          "tgn:1000001",
          "tgn:7012149",
          "tgn:7007157",
          "tgn:1002972",
          "tgn:7029392"
        ],
        "placetype": [
          "aat:300008706"
        ],
        "id": 2296702,
        "name:xx": "Dry Creek"
      }
    },
    {
      "geometry": {
        "type": "Point",
        "coordinates": [
          -108.4167,
          40.9333
        ]
      },
      "type": "Feature",
      "properties": {
        "hierarchy": [
          "tgn:2296703",
          "tgn:1000001",
          "tgn:7012149",
          "tgn:2000232",
          "tgn:7007158",
          "tgn:7029392"
        ],
        "placetype": [
          "aat:300008706"
        ],
        "id": 2296703,
        "name:xx": "Dry Creek"
      }
    },
    {
      "geometry": {
        "type": "Point",
        "coordinates": [
          -105.1167,
          40.8167
        ]
      },
      "type": "Feature",
      "properties": {
        "hierarchy": [
          "tgn:2296704",
          "tgn:1000001",
          "tgn:7012149",
          "tgn:2000226",
          "tgn:7007158",
          "tgn:7029392"
        ],
        "placetype": [
          "aat:300008706"
        ],
        "id": 2296704,
        "name:xx": "Dry Creek"
      }
    },
    {
      "geometry": {
        "type": "Point",
        "coordinates": [
          -107.25,
          40.3333
        ]
      },
      "type": "Feature",
      "properties": {
        "hierarchy": [
          "tgn:2296705",
          "tgn:1000001",
          "tgn:7012149",
          "tgn:7007158",
          "tgn:2000245",
          "tgn:7029392"
        ],
        "placetype": [
          "aat:300008706"
        ],
        "id": 2296705,
        "name:xx": "Dry Creek"
      }
    },
    {
      "geometry": {
        "type": "Point",
        "coordinates": [
          -105.9833,
          40.6167
        ]
      },
      "type": "Feature",
      "properties": {
        "hierarchy": [
          "tgn:2296706",
          "tgn:1000001",
          "tgn:7012149",
          "tgn:2000220",
          "tgn:7007158",
          "tgn:7029392"
        ],
        "placetype": [
          "aat:300008706"
        ],
        "id": 2296706,
        "name:xx": "Dry Creek"
      }
    },
    {
      "geometry": {
        "type": "Point",
        "coordinates": [
          -107.6667,
          39.8
        ]
      },
      "type": "Feature",
      "properties": {
        "hierarchy": [
          "tgn:2296707",
          "tgn:1000001",
          "tgn:7012149",
          "tgn:7007158",
          "tgn:7029392"
        ],
        "placetype": [
          "aat:300008706"
        ],
        "id": 2296707,
        "name:xx": "Dry Creek"
      }
    },
    {
      "geometry": {
        "type": "Point",
        "coordinates": [
          -107.95,
          39.3667
        ]
      },
      "type": "Feature",
      "properties": {
        "hierarchy": [
          "tgn:2296708",
          "tgn:1000001",
          "tgn:7012149",
          "tgn:2000214",
          "tgn:7007158",
          "tgn:7029392"
        ],
        "placetype": [
          "aat:300008706"
        ],
        "id": 2296708,
        "name:xx": "Dry Creek"
      }
    },
    {
      "geometry": {
        "type": "Point",
        "coordinates": [
          -106.4167,
          40
        ]
      },
      "type": "Feature",
      "properties": {
        "hierarchy": [
          "tgn:2296709",
          "tgn:1000001",
          "tgn:7012149",
          "tgn:2000216",
          "tgn:7007158",
          "tgn:7029392"
        ],
        "placetype": [
          "aat:300008706"
        ],
        "id": 2296709,
        "name:xx": "Dry Creek"
      }
    }
  ]
}
