{
  "geometry": {
    "type": "Point",
    "coordinates": [
      -146.1667,
      61.1333
    ]
  },
  "type": "Feature",
  "properties": {
    "hierarchy": [
      "tgn:2742063",
      "tgn:7006450",
      "tgn:1000001",
      "tgn:7012149",
      "tgn:2000086",
      "tgn:7029392"
    ],
    "placetype": [
      "aat:300008699"
    ],
    "id": 2742063,
    "name:xx": "Valdez Glacier Stream"
  }
}
