{
  "geometry": {
    "type": "Point",
    "coordinates": [
      12.95,
      50.95
    ]
  },
  "type": "Feature",
  "properties": {
    "hierarchy": [
      "tgn:7100922",
      "tgn:1000003",
      "tgn:7003685",
      "tgn:7000084",
      "tgn:7029392"
    ],
    "placetype": [
      "aat:300008777"
    ],
    "id": 7100922,
    "name:xx": "Sand-Berg"
  }
}
