{
  "geometry": {
    "type": "Point",
    "coordinates": [
      -78.7667,
      38.1833
    ]
  },
  "type": "Feature",
  "properties": {
    "hierarchy": [
      "tgn:2237252",
      "tgn:2002142",
      "tgn:1000001",
      "tgn:7012149",
      "tgn:7007919",
      "tgn:7029392"
    ],
    "placetype": [
      "aat:300008798"
    ],
    "id": 2237252,
    "name:xx": "Chimney Rock"
  }
}
