{
  "geometry": {
    "type": "Point",
    "coordinates": [
      79.05,
      18.066667
    ]
  },
  "type": "Feature",
  "properties": {
    "hierarchy": [
      "tgn:7554702",
      "tgn:1001828",
      "tgn:1000004",
      "tgn:7000198",
      "tgn:7029392"
    ],
    "placetype": [
      "aat:300008347"
    ],
    "name:en": "Nāgnūr",
    "id": 7554702
  }
}
