{
  "geometry": {
    "type": "Point",
    "coordinates": [
      33.696128,
      30.225847
    ]
  },
  "type": "Feature",
  "properties": {
    "hierarchy": [
      "tgn:7542369",
      "tgn:7001242",
      "tgn:7016833",
      "tgn:7001335",
      "tgn:7029392"
    ],
    "placetype": [
      "aat:300379998"
    ],
    "name:en": "Jidāl ad Dawkh, Wādī",
    "id": 7542369
  }
}
