{
  "type": "FeatureCollection",
  "features": [
    {
      "geometry": {
        "type": "Point",
        "coordinates": [
          10.15,
          48.466667
        ]
      },
      "type": "Feature",
      "properties": {
        "hierarchy": [
          "tgn:7193830",
          "tgn:7003692",
          "tgn:1000003",
          "tgn:7000084",
          "tgn:7029392"
        ],
        "placetype": [
          "aat:300008347"
        ],
        "id": 7193830,
        "name:xx": "Fischerhöfe"
      }
    },
    {
      "geometry": {
        "type": "Point",
        "coordinates": [
          8.166667,
          48.65
        ]
      },
      "type": "Feature",
      "properties": {
        "hierarchy": [
          "tgn:7193831",
          "tgn:7003692",
          "tgn:1000003",
          "tgn:7000084",
          "tgn:7029392"
        ],
        "placetype": [
          "aat:300000206"
        ],
        "id": 7193831,
        "name:xx": "Fischerhöfe"
      }
    },
    {
      "geometry": {
        "type": "Point",
        "coordinates": [
          9.616667,
          53.483333
        ]
      },
      "type": "Feature",
      "properties": {
        "hierarchy": [
          "tgn:7193832",
          "tgn:1000003",
          "tgn:7003676",
          "tgn:7000084",
          "tgn:7029392"
        ],
        "placetype": [
          "aat:300000206"
        ],
        "id": 7193832,
        "name:xx": "Fischerhof"
      }
    },
    {
      "geometry": {
        "type": "Point",
        "coordinates": [
          10.533333,
          52.983333
        ]
      },
      "type": "Feature",
      "properties": {
        "hierarchy": [
          "tgn:7193833",
          "tgn:1000003",
          "tgn:7003676",
          "tgn:7000084",
          "tgn:7029392"
        ],
        "placetype": [
          "aat:300000206"
        ],
        "id": 7193833,
        "name:xx": "Fischerhof"
      }
    },
    {
      "geometry": {
        "type": "Point",
        "coordinates": [
          14.85,
          51.4
        ]
      },
      "type": "Feature",
      "properties": {
        "hierarchy": [
          "tgn:7193834",
          "tgn:1000003",
          "tgn:7003685",
          "tgn:7000084",
          "tgn:7029392"
        ],
        "placetype": [
          "aat:300000206"
        ],
        "id": 7193834,
        "name:xx": "Feldhäuser"
      }
    },
    {
      "geometry": {
        "type": "Point",
        "coordinates": [
          14.583333,
          51.233333
        ]
      },
      "type": "Feature",
      "properties": {
        "hierarchy": [
          "tgn:7193835",
          "tgn:1000003",
          "tgn:7003685",
          "tgn:7000084",
          "tgn:7029392"
        ],
        "placetype": [
          "aat:300000206"
        ],
        "id": 7193835,
        "name:xx": "Feldhäuser"
      }
    },
    {
      "geometry": {
        "type": "Point",
        "coordinates": [
          14.866667,
          50.95
        ]
      },
      "type": "Feature",
      "properties": {
        "hierarchy": [
          "tgn:7193836",
          "tgn:1000003",
          "tgn:7003685",
          "tgn:7000084",
          "tgn:7029392"
        ],
        "placetype": [
          "aat:300000206"
        ],
        "id": 7193836,
        "name:xx": "Feldhäuser"
      }
    },
    {
      "geometry": {
        "type": "Point",
        "coordinates": [
          12.8,
          50.7
        ]
      },
      "type": "Feature",
      "properties": {
        "hierarchy": [
          "tgn:7193837",
          "tgn:1000003",
          "tgn:7003685",
          "tgn:7000084",
          "tgn:7029392"
        ],
        "placetype": [
          "aat:300000206"
        ],
        "id": 7193837,
        "name:xx": "Feldhäuser"
      }
    },
    {
      "geometry": {
        "type": "Point",
        "coordinates": [
          12.45,
          50.583333
        ]
      },
      "type": "Feature",
      "properties": {
        "hierarchy": [
          "tgn:7193838",
          "tgn:1000003",
          "tgn:7003685",
          "tgn:7000084",
          "tgn:7029392"
        ],
        "placetype": [
          "aat:300000206"
        ],
        "id": 7193838,
        "name:xx": "Feldhäuser"
      }
    },
    {
      "geometry": {
        "type": "Point",
        "coordinates": [
          7.95,
          53.55
        ]
      },
      "type": "Feature",
      "properties": {
        "hierarchy": [
          "tgn:7193839",
          "tgn:1000003",
          "tgn:7003676",
          "tgn:7000084",
          "tgn:7029392"
        ],
        "placetype": [
          "aat:300387200"
        ],
        "id": 7193839,
        "name:xx": "Feldhausen"
      }
    }
  ]
}
