{
  "geometry": {
    "type": "Point",
    "coordinates": [
      -79.6167,
      37.45
    ]
  },
  "type": "Feature",
  "properties": {
    "hierarchy": [
      "tgn:2656742",
      "tgn:1000001",
      "tgn:2002144",
      "tgn:7012149",
      "tgn:7007919",
      "tgn:7029392"
    ],
    "placetype": [
      "aat:300008706"
    ],
    "id": 2656742,
    "name:xx": "Sheep Creek"
  }
}
