{
  "geometry": {
    "type": "Point",
    "coordinates": [
      -68.6667,
      44.5833
    ]
  },
  "type": "Feature",
  "properties": {
    "hierarchy": [
      "tgn:2139754",
      "tgn:1000001",
      "tgn:2000922",
      "tgn:7012149",
      "tgn:7007515",
      "tgn:7029392"
    ],
    "placetype": [
      "aat:300008798"
    ],
    "id": 2139754,
    "name:xx": "Atkins Hill"
  }
}
