{
  "geometry": {
    "type": "Point",
    "coordinates": [
      28.85,
      41.25
    ]
  },
  "type": "Feature",
  "properties": {
    "hierarchy": [
      "tgn:1086450",
      "tgn:1001052",
      "tgn:1000004",
      "tgn:7018450",
      "tgn:1000144",
      "tgn:7029392"
    ],
    "placetype": [
      "aat:300008347"
    ],
    "id": 1086450,
    "name:xx": "Kömürcüpınar"
  }
}
