{
  "type": "FeatureCollection",
  "features": [
    {
      "geometry": {
        "type": "Point",
        "coordinates": [
          -107.383333,
          27.666667
        ]
      },
      "type": "Feature",
      "properties": {
        "hierarchy": [
          "tgn:7383080",
          "tgn:7005581",
          "tgn:1000001",
          "tgn:7005560",
          "tgn:7029392"
        ],
        "placetype": [
          "aat:300008347"
        ],
        "id": 7383080,
        "name:xx": "Panalachic"
      }
    },
    {
      "geometry": {
        "type": "Point",
        "coordinates": [
          -104.866667,
          19.683333
        ]
      },
      "type": "Feature",
      "properties": {
        "hierarchy": [
          "tgn:7383081",
          "tgn:7005586",
          "tgn:1000001",
          "tgn:7005560",
          "tgn:7029392"
        ],
        "placetype": [
          "aat:300008795"
        ],
        "id": 7383081,
        "name:xx": "Panal, Cerro del"
      }
    },
    {
      "geometry": {
        "type": "Point",
        "coordinates": [
          -101.483333,
          26.416667
        ]
      },
      "type": "Feature",
      "properties": {
        "hierarchy": [
          "tgn:7383082",
          "tgn:1001853",
          "tgn:1000001",
          "tgn:7005560",
          "tgn:7029392"
        ],
        "placetype": [
          "aat:300008763"
        ],
        "id": 7383082,
        "name:xx": "Panal, Cañón del"
      }
    },
    {
      "geometry": {
        "type": "Point",
        "coordinates": [
          -99.216667,
          22.4
        ]
      },
      "type": "Feature",
      "properties": {
        "hierarchy": [
          "tgn:7383083",
          "tgn:1000001",
          "tgn:7005594",
          "tgn:7005560",
          "tgn:7029392"
        ],
        "placetype": [
          "aat:300008347"
        ],
        "id": 7383083,
        "name:xx": "Panal"
      }
    },
    {
      "geometry": {
        "type": "Point",
        "coordinates": [
          -89.366667,
          20.533333
        ]
      },
      "type": "Feature",
      "properties": {
        "hierarchy": [
          "tgn:7383084",
          "tgn:1000001",
          "tgn:7005600",
          "tgn:7005560",
          "tgn:7029392"
        ],
        "placetype": [
          "aat:300008347"
        ],
        "id": 7383084,
        "name:xx": "Panabchén"
      }
    },
    {
      "geometry": {
        "type": "Point",
        "coordinates": [
          -89.3,
          20.9
        ]
      },
      "type": "Feature",
      "properties": {
        "hierarchy": [
          "tgn:7383086",
          "tgn:1000001",
          "tgn:7005600",
          "tgn:7005560",
          "tgn:7029392"
        ],
        "placetype": [
          "aat:300008347"
        ],
        "id": 7383086,
        "name:xx": "Panabá"
      }
    },
    {
      "geometry": {
        "type": "Point",
        "coordinates": [
          -103.4,
          26.1
        ]
      },
      "type": "Feature",
      "properties": {
        "hierarchy": [
          "tgn:7383087",
          "tgn:7005583",
          "tgn:1000001",
          "tgn:7005560",
          "tgn:7029392"
        ],
        "placetype": [
          "aat:300008347"
        ],
        "id": 7383087,
        "name:xx": "Pamplona"
      }
    },
    {
      "geometry": {
        "type": "Point",
        "coordinates": [
          -104.75,
          27.4
        ]
      },
      "type": "Feature",
      "properties": {
        "hierarchy": [
          "tgn:7383088",
          "tgn:7005581",
          "tgn:1000001",
          "tgn:7005560",
          "tgn:7029392"
        ],
        "placetype": [
          "aat:300266640"
        ],
        "id": 7383088,
        "name:xx": "Pampas, Sierra de las"
      }
    },
    {
      "geometry": {
        "type": "Point",
        "coordinates": [
          -106.95,
          28.4
        ]
      },
      "type": "Feature",
      "properties": {
        "hierarchy": [
          "tgn:7383089",
          "tgn:7005581",
          "tgn:1000001",
          "tgn:7005560",
          "tgn:7029392"
        ],
        "placetype": [
          "aat:300007783"
        ],
        "id": 7383089,
        "name:xx": "Pampas"
      }
    }
  ]
}
