{
  "geometry": {
    "type": "Point",
    "coordinates": [
      -79.75,
      37.65
    ]
  },
  "type": "Feature",
  "properties": {
    "hierarchy": [
      "tgn:2657511",
      "tgn:1000001",
      "tgn:2002146",
      "tgn:7012149",
      "tgn:7007919",
      "tgn:7029392"
    ],
    "placetype": [
      "aat:300008798"
    ],
    "id": 2657511,
    "name:xx": "Sheets Mountain"
  }
}
