{
  "geometry": {
    "type": "Point",
    "coordinates": [
      15.65,
      44.0333
    ]
  },
  "type": "Feature",
  "properties": {
    "hierarchy": [
      "tgn:1064921",
      "tgn:7017294",
      "tgn:1000003",
      "tgn:7006663",
      "tgn:7029392"
    ],
    "placetype": [
      "aat:300008347"
    ],
    "id": 1064921,
    "name:xx": "Benkovac"
  }
}
