{
  "geometry": {
    "type": "Point",
    "coordinates": [
      -104.95,
      32.15
    ]
  },
  "type": "Feature",
  "properties": {
    "hierarchy": [
      "tgn:2443842",
      "tgn:1000001",
      "tgn:7012149",
      "tgn:2001447",
      "tgn:7007566",
      "tgn:7029392"
    ],
    "placetype": [
      "aat:300008761"
    ],
    "id": 2443842,
    "name:xx": "La Paloma Canyon"
  }
}
