{
  "geometry": {
    "type": "Point",
    "coordinates": [
      -113.55,
      33.9333
    ]
  },
  "type": "Feature",
  "properties": {
    "hierarchy": [
      "tgn:2230921",
      "tgn:1000001",
      "tgn:7006451",
      "tgn:7012149",
      "tgn:2000104",
      "tgn:7029392"
    ],
    "placetype": [
      "aat:300000390"
    ],
    "id": 2230921,
    "name:xx": "Centroid Mine"
  }
}
