{
  "geometry": {
    "type": "Point",
    "coordinates": [
      9.6167,
      36.65
    ]
  },
  "type": "Feature",
  "properties": {
    "hierarchy": [
      "tgn:1094973",
      "tgn:7001242",
      "tgn:1002067",
      "tgn:1000205",
      "tgn:7029392"
    ],
    "placetype": [
      "aat:300008347"
    ],
    "id": 1094973,
    "name:xx": "Mejez El Bab"
  }
}
