{
  "geometry": {
    "type": "Point",
    "coordinates": [
      -114.0833,
      37.45
    ]
  },
  "type": "Feature",
  "properties": {
    "hierarchy": [
      "tgn:2583279",
      "tgn:1000001",
      "tgn:2001416",
      "tgn:7012149",
      "tgn:7007526",
      "tgn:7029392"
    ],
    "placetype": [
      "aat:300008798"
    ],
    "id": 2583279,
    "name:xx": "Pine Mountain"
  }
}
