{
  "geometry": {
    "type": "Point",
    "coordinates": [
      -72.0167,
      44.7167
    ]
  },
  "type": "Feature",
  "properties": {
    "hierarchy": [
      "tgn:2757995",
      "tgn:1000001",
      "tgn:7012149",
      "tgn:7007828",
      "tgn:7029392"
    ],
    "placetype": [
      "aat:300008707"
    ],
    "id": 2757995,
    "name:xx": "West Branch Passumpsic River"
  }
}
