{
  "geometry": {
    "type": "Point",
    "coordinates": [
      11.6167,
      55.9167
    ]
  },
  "type": "Feature",
  "properties": {
    "hierarchy": [
      "tgn:1136653",
      "tgn:7594008",
      "tgn:1000003",
      "tgn:1000066",
      "tgn:7029392"
    ],
    "placetype": [
      "aat:300008347"
    ],
    "id": 1136653,
    "name:xx": "Højby"
  }
}
