{
  "geometry": {
    "type": "Point",
    "coordinates": [
      -75.6333,
      41.6333
    ]
  },
  "type": "Feature",
  "properties": {
    "hierarchy": [
      "tgn:2326680",
      "tgn:1000001",
      "tgn:7012149",
      "tgn:1002564",
      "tgn:7007710",
      "tgn:7029392"
    ],
    "placetype": [
      "aat:300008680"
    ],
    "id": 2326680,
    "name:xx": "Finn Pond"
  }
}
