{
  "geometry": {
    "type": "Point",
    "coordinates": [
      -134.5833,
      57.0167
    ]
  },
  "type": "Feature",
  "properties": {
    "hierarchy": [
      "tgn:2705401",
      "tgn:7006450",
      "tgn:1000001",
      "tgn:7012149",
      "tgn:7019760",
      "tgn:7029392"
    ],
    "placetype": [
      "aat:300132316"
    ],
    "id": 2705401,
    "name:xx": "Surprise Harbor"
  }
}
