{
  "geometry": {
    "type": "Point",
    "coordinates": [
      -95.1167,
      31.4167
    ]
  },
  "type": "Feature",
  "properties": {
    "hierarchy": [
      "tgn:2662700",
      "tgn:1000001",
      "tgn:7012149",
      "tgn:7007826",
      "tgn:7029392"
    ],
    "placetype": [
      "aat:300008706"
    ],
    "id": 2662700,
    "name:xx": "Sikes Creek"
  }
}
