{
  "geometry": {
    "type": "Point",
    "coordinates": [
      13.1167,
      -14.4667
    ]
  },
  "type": "Feature",
  "properties": {
    "hierarchy": [
      "tgn:1087668",
      "tgn:7001242",
      "tgn:1000149",
      "tgn:7000392",
      "tgn:7029392"
    ],
    "placetype": [
      "aat:300008347"
    ],
    "id": 1087668,
    "name:xx": "Caitou"
  }
}
