{
  "geometry": {
    "type": "Point",
    "coordinates": [
      -106.3167,
      40.1833
    ]
  },
  "type": "Feature",
  "properties": {
    "hierarchy": [
      "tgn:2518272",
      "tgn:1000001",
      "tgn:7012149",
      "tgn:2000216",
      "tgn:7007158",
      "tgn:7029392"
    ],
    "placetype": [
      "aat:300006075"
    ],
    "id": 2518272,
    "name:xx": "Missouri Ditch"
  }
}
