{
  "geometry": {
    "type": "Point",
    "coordinates": [
      -105.2333,
      33.4833
    ]
  },
  "type": "Feature",
  "properties": {
    "hierarchy": [
      "tgn:2318826",
      "tgn:1000001",
      "tgn:7012149",
      "tgn:2001442",
      "tgn:7007566",
      "tgn:7029392"
    ],
    "placetype": [
      "aat:300008347"
    ],
    "id": 2318826,
    "name:xx": "Escondido"
  }
}
