{
  "geometry": {
    "type": "Point",
    "coordinates": [
      31.077771,
      27.344026
    ]
  },
  "type": "Feature",
  "properties": {
    "hierarchy": [
      "tgn:7533392",
      "tgn:7001242",
      "tgn:7001311",
      "tgn:7016833",
      "tgn:7029392"
    ],
    "placetype": [
      "aat:300379998"
    ],
    "name:en": "Jabr훮w카, W훮d카 al",
    "id": 7533392
  }
}
