{
  "geometry": {
    "type": "Point",
    "coordinates": [
      -123.8333,
      45.3667
    ]
  },
  "type": "Feature",
  "properties": {
    "hierarchy": [
      "tgn:2422843",
      "tgn:1000001",
      "tgn:7012149",
      "tgn:1002943",
      "tgn:7007708",
      "tgn:7029392"
    ],
    "placetype": [
      "aat:300008706"
    ],
    "id": 2422843,
    "name:xx": "Joe Creek"
  }
}
