{
  "geometry": {
    "type": "Point",
    "coordinates": [
      151.25,
      -33.7333
    ]
  },
  "type": "Feature",
  "properties": {
    "hierarchy": [
      "tgn:1097890",
      "tgn:7000490",
      "tgn:1000006",
      "tgn:7001828",
      "tgn:7029392"
    ],
    "placetype": [
      "aat:300008347"
    ],
    "id": 1097890,
    "name:xx": "Oxford Falls"
  }
}
