{
  "geometry": {
    "type": "Point",
    "coordinates": [
      30.65,
      29.133333
    ]
  },
  "type": "Feature",
  "properties": {
    "hierarchy": [
      "tgn:7540312",
      "tgn:7001242",
      "tgn:7001105",
      "tgn:7016833",
      "tgn:7029392"
    ],
    "placetype": [
      "aat:300008916"
    ],
    "name:en": "Naj' al Ḩajar, Ḩamrāyat",
    "id": 7540312
  }
}
