{
  "geometry": {
    "type": "Point",
    "coordinates": [
      -121.1667,
      42.3333
    ]
  },
  "type": "Feature",
  "properties": {
    "hierarchy": [
      "tgn:2418844",
      "tgn:1000001",
      "tgn:7012149",
      "tgn:2001714",
      "tgn:7007708",
      "tgn:7029392"
    ],
    "placetype": [
      "aat:300008798"
    ],
    "id": 2418844,
    "name:xx": "James Butte"
  }
}
