{
  "geometry": {
    "type": "Point",
    "coordinates": [
      -73.9667,
      43.5333
    ]
  },
  "type": "Feature",
  "properties": {
    "hierarchy": [
      "tgn:2583497",
      "tgn:1000001",
      "tgn:7012149",
      "tgn:1002986",
      "tgn:7007568",
      "tgn:7029392"
    ],
    "placetype": [
      "aat:300266640"
    ],
    "id": 2583497,
    "name:xx": "Pine Ridge"
  }
}
