{
  "geometry": {
    "type": "Point",
    "coordinates": [
      152.9333,
      -29.6667
    ]
  },
  "type": "Feature",
  "properties": {
    "hierarchy": [
      "tgn:7001936",
      "tgn:7000490",
      "tgn:1000006",
      "tgn:7001828",
      "tgn:7029392"
    ],
    "placetype": [
      "aat:300008347"
    ],
    "id": 7001936,
    "name:xx": "Grafton"
  }
}
