{
  "geometry": {
    "type": "Point",
    "coordinates": [
      -74.0667,
      43.2833
    ]
  },
  "type": "Feature",
  "properties": {
    "hierarchy": [
      "tgn:2786313",
      "tgn:1000001",
      "tgn:7012149",
      "tgn:1002871",
      "tgn:7007568",
      "tgn:7029392"
    ],
    "placetype": [
      "aat:300008798"
    ],
    "id": 2786313,
    "name:xx": "Youngs Mountain"
  }
}
