{
  "geometry": {
    "type": "Point",
    "coordinates": [
      -135.2667,
      59.4167
    ]
  },
  "type": "Feature",
  "properties": {
    "hierarchy": [
      "tgn:2285834",
      "tgn:7006450",
      "tgn:1000001",
      "tgn:7012149",
      "tgn:7019760",
      "tgn:7029392"
    ],
    "placetype": [
      "aat:300008680"
    ],
    "id": 2285834,
    "name:xx": "Devils Punch Bowl"
  }
}
