{
  "geometry": {
    "type": "Point",
    "coordinates": [
      -75.8667,
      42.45
    ]
  },
  "type": "Feature",
  "properties": {
    "hierarchy": [
      "tgn:2591641",
      "tgn:1000001",
      "tgn:7012149",
      "tgn:7007568",
      "tgn:7029392"
    ],
    "placetype": [
      "aat:300008699"
    ],
    "id": 2591641,
    "name:xx": "Pond Brook"
  }
}
