{
  "geometry": {
    "type": "Point",
    "coordinates": [
      -81.15,
      33.2167
    ]
  },
  "type": "Feature",
  "properties": {
    "hierarchy": [
      "tgn:2174103",
      "tgn:1000001",
      "tgn:7012149",
      "tgn:7007712",
      "tgn:7029392"
    ],
    "placetype": [
      "aat:300008699"
    ],
    "id": 2174103,
    "name:xx": "Birds Branch"
  }
}
