{
  "type": "FeatureCollection",
  "features": [
    {
      "geometry": {
        "type": "Point",
        "coordinates": [
          75.65,
          14
        ]
      },
      "type": "Feature",
      "properties": {
        "hierarchy": [
          "tgn:7547662",
          "tgn:1000004",
          "tgn:7000198",
          "tgn:1001882",
          "tgn:7029392"
        ],
        "placetype": [
          "aat:300008699"
        ],
        "name:en": "Bhadra River",
        "id": 7547662
      }
    },
    {
      "geometry": {
        "type": "Point",
        "coordinates": [
          79.002927,
          23.965429
        ]
      },
      "type": "Feature",
      "properties": {
        "hierarchy": [
          "tgn:7547663",
          "tgn:1000004",
          "tgn:7000198",
          "tgn:1001894",
          "tgn:7029392"
        ],
        "placetype": [
          "aat:300008347"
        ],
        "name:en": "Bhadrana",
        "id": 7547663
      }
    },
    {
      "geometry": {
        "type": "Point",
        "coordinates": [
          72.9,
          22.366667
        ]
      },
      "type": "Feature",
      "properties": {
        "hierarchy": [
          "tgn:7547664",
          "tgn:1000004",
          "tgn:1001869",
          "tgn:7000198",
          "tgn:7029392"
        ],
        "placetype": [
          "aat:300008347"
        ],
        "name:en": "Bhādran",
        "id": 7547664
      }
    },
    {
      "geometry": {
        "type": "Point",
        "coordinates": [
          72.867451,
          25.597992
        ]
      },
      "type": "Feature",
      "properties": {
        "hierarchy": [
          "tgn:7547666",
          "tgn:1000004",
          "tgn:7000198",
          "tgn:7016788",
          "tgn:7029392"
        ],
        "placetype": [
          "aat:300008347"
        ],
        "name:en": "Bhadrājan",
        "id": 7547666
      }
    },
    {
      "geometry": {
        "type": "Point",
        "coordinates": [
          80.616667,
          17.55
        ]
      },
      "type": "Feature",
      "properties": {
        "hierarchy": [
          "tgn:7547667",
          "tgn:1001828",
          "tgn:1000004",
          "tgn:7000198",
          "tgn:7029392"
        ],
        "placetype": [
          "aat:300007783"
        ],
        "name:en": "Bhadrāchalam Road",
        "id": 7547667
      }
    },
    {
      "geometry": {
        "type": "Point",
        "coordinates": [
          76.483418,
          32.55317
        ]
      },
      "type": "Feature",
      "properties": {
        "hierarchy": [
          "tgn:7547669",
          "tgn:1000004",
          "tgn:7000198",
          "tgn:1001996",
          "tgn:7029392"
        ],
        "placetype": [
          "aat:300008347"
        ],
        "name:en": "Bhadra",
        "id": 7547669
      }
    }
  ]
}
