{
  "geometry": {
    "type": "Point",
    "coordinates": [
      -111.95,
      45.2667
    ]
  },
  "type": "Feature",
  "properties": {
    "hierarchy": [
      "tgn:2430460",
      "tgn:1000001",
      "tgn:7012149",
      "tgn:2001288",
      "tgn:7007524",
      "tgn:7029392"
    ],
    "placetype": [
      "aat:300000390"
    ],
    "id": 2430460,
    "name:xx": "Kakoosta Mine"
  }
}
