{
  "type": "FeatureCollection",
  "features": [
    {
      "geometry": {
        "type": "Point",
        "coordinates": [
          -110.2667,
          46.7
        ]
      },
      "type": "Feature",
      "properties": {
        "hierarchy": [
          "tgn:2298310",
          "tgn:1000001",
          "tgn:7012149",
          "tgn:2001282",
          "tgn:7007524",
          "tgn:7029392"
        ],
        "placetype": [
          "aat:300008761"
        ],
        "id": 2298310,
        "name:xx": "Dry Pole Canyon"
      }
    },
    {
      "geometry": {
        "type": "Point",
        "coordinates": [
          -106.35,
          37.5833
        ]
      },
      "type": "Feature",
      "properties": {
        "hierarchy": [
          "tgn:2298311",
          "tgn:1000001",
          "tgn:7012149",
          "tgn:7007158",
          "tgn:2000244",
          "tgn:7029392"
        ],
        "placetype": [
          "aat:300008706"
        ],
        "id": 2298311,
        "name:xx": "Dry Pole Creek"
      }
    },
    {
      "geometry": {
        "type": "Point",
        "coordinates": [
          -109.5667,
          46.7833
        ]
      },
      "type": "Feature",
      "properties": {
        "hierarchy": [
          "tgn:2298312",
          "tgn:1000001",
          "tgn:7012149",
          "tgn:2001273",
          "tgn:7007524",
          "tgn:7029392"
        ],
        "placetype": [
          "aat:300008706"
        ],
        "id": 2298312,
        "name:xx": "Dry Pole Creek"
      }
    },
    {
      "geometry": {
        "type": "Point",
        "coordinates": [
          -111.3167,
          39.5
        ]
      },
      "type": "Feature",
      "properties": {
        "hierarchy": [
          "tgn:2298313",
          "tgn:1000001",
          "tgn:7012149",
          "tgn:2002120",
          "tgn:7007827",
          "tgn:7029392"
        ],
        "placetype": [
          "aat:300008699"
        ],
        "id": 2298313,
        "name:xx": "Dry Pole Fork"
      }
    },
    {
      "geometry": {
        "type": "Point",
        "coordinates": [
          -111.75,
          41.7
        ]
      },
      "type": "Feature",
      "properties": {
        "hierarchy": [
          "tgn:2298314",
          "tgn:1000001",
          "tgn:2002103",
          "tgn:7012149",
          "tgn:7007827",
          "tgn:7029392"
        ],
        "placetype": [
          "aat:300008761"
        ],
        "id": 2298314,
        "name:xx": "Dry Pole Hollow"
      }
    },
    {
      "geometry": {
        "type": "Point",
        "coordinates": [
          -85.8333,
          34.35
        ]
      },
      "type": "Feature",
      "properties": {
        "hierarchy": [
          "tgn:2298315",
          "tgn:7002659",
          "tgn:1000001",
          "tgn:7012149",
          "tgn:7021514",
          "tgn:7029392"
        ],
        "placetype": [
          "aat:300008680"
        ],
        "id": 2298315,
        "name:xx": "Dry Pond"
      }
    },
    {
      "geometry": {
        "type": "Point",
        "coordinates": [
          -114.9167,
          42.1
        ]
      },
      "type": "Feature",
      "properties": {
        "hierarchy": [
          "tgn:2298316",
          "tgn:1000001",
          "tgn:7012149",
          "tgn:2000493",
          "tgn:7007250",
          "tgn:7029392"
        ],
        "placetype": [
          "aat:300008680"
        ],
        "id": 2298316,
        "name:xx": "Dry Pond"
      }
    },
    {
      "geometry": {
        "type": "Point",
        "coordinates": [
          -68.9,
          45.9167
        ]
      },
      "type": "Feature",
      "properties": {
        "hierarchy": [
          "tgn:2298317",
          "tgn:1000001",
          "tgn:7012149",
          "tgn:2000928",
          "tgn:7007515",
          "tgn:7029392"
        ],
        "placetype": [
          "aat:300008680"
        ],
        "id": 2298317,
        "name:xx": "Dry Pond"
      }
    },
    {
      "geometry": {
        "type": "Point",
        "coordinates": [
          -68.7167,
          47.1333
        ]
      },
      "type": "Feature",
      "properties": {
        "hierarchy": [
          "tgn:2298318",
          "tgn:2000919",
          "tgn:1000001",
          "tgn:7012149",
          "tgn:7007515",
          "tgn:7029392"
        ],
        "placetype": [
          "aat:300008680"
        ],
        "id": 2298318,
        "name:xx": "Dry Pond"
      }
    },
    {
      "geometry": {
        "type": "Point",
        "coordinates": [
          -71.1333,
          42.1
        ]
      },
      "type": "Feature",
      "properties": {
        "hierarchy": [
          "tgn:2298319",
          "tgn:1000001",
          "tgn:1002724",
          "tgn:7012149",
          "tgn:7007517",
          "tgn:7029392"
        ],
        "placetype": [
          "aat:300008680"
        ],
        "id": 2298319,
        "name:xx": "Dry Pond"
      }
    }
  ]
}
