{
  "geometry": {
    "type": "Point",
    "coordinates": [
      -86.8667,
      31.3333
    ]
  },
  "type": "Feature",
  "properties": {
    "hierarchy": [
      "tgn:2453195",
      "tgn:7002659",
      "tgn:1000001",
      "tgn:2000017",
      "tgn:7012149",
      "tgn:7029392"
    ],
    "placetype": [
      "aat:300008706"
    ],
    "id": 2453195,
    "name:xx": "Little Cedar Creek"
  }
}
