{
  "geometry": {
    "type": "Point",
    "coordinates": [
      31.377604,
      30.360563
    ]
  },
  "type": "Feature",
  "properties": {
    "hierarchy": [
      "tgn:1095597",
      "tgn:7001242",
      "tgn:7016833",
      "tgn:1001113",
      "tgn:7029392"
    ],
    "placetype": [
      "aat:300008347"
    ],
    "name:en": "Mashtūl as Sūq",
    "id": 1095597
  }
}
