{
  "type": "FeatureCollection",
  "features": [
    {
      "geometry": {
        "type": "Point",
        "coordinates": [
          -4.05,
          52.533333
        ]
      },
      "type": "Feature",
      "properties": {
        "hierarchy": [
          "tgn:7466032",
          "tgn:7002443",
          "tgn:7017242",
          "tgn:1000003",
          "tgn:7008591",
          "tgn:7029392"
        ],
        "placetype": [
          "aat:300008678"
        ],
        "name:en": "Aberdovey Harbour",
        "id": 7466032
      }
    },
    {
      "geometry": {
        "type": "Point",
        "coordinates": [
          -2.183333,
          57.666667
        ]
      },
      "type": "Feature",
      "properties": {
        "hierarchy": [
          "tgn:7466033",
          "tgn:5000432",
          "tgn:7002444",
          "tgn:1000003",
          "tgn:7008591",
          "tgn:7029392"
        ],
        "placetype": [
          "aat:300132316"
        ],
        "name:en": "Aberdour Bay",
        "id": 7466033
      }
    },
    {
      "geometry": {
        "type": "Point",
        "coordinates": [
          -2.066667,
          57.15
        ]
      },
      "type": "Feature",
      "properties": {
        "hierarchy": [
          "tgn:7466036",
          "tgn:7019141",
          "tgn:7002444",
          "tgn:1000003",
          "tgn:7008591",
          "tgn:7029392"
        ],
        "placetype": [
          "aat:300132316"
        ],
        "name:en": "Aberdeen Bay",
        "id": 7466036
      }
    },
    {
      "geometry": {
        "type": "Point",
        "coordinates": [
          -2.9,
          55.483333
        ]
      },
      "type": "Feature",
      "properties": {
        "hierarchy": [
          "tgn:7466037",
          "tgn:7002444",
          "tgn:1000003",
          "tgn:7008072",
          "tgn:7008591",
          "tgn:7029392"
        ],
        "placetype": [
          "aat:300008699"
        ],
        "name:en": "Blindhaugh Burn",
        "id": 7466037
      }
    }
  ]
}
