{
  "geometry": {
    "type": "Point",
    "coordinates": [
      -119.6333,
      34.6833
    ]
  },
  "type": "Feature",
  "properties": {
    "hierarchy": [
      "tgn:1130063",
      "tgn:1000001",
      "tgn:7012149",
      "tgn:7007157",
      "tgn:1002867",
      "tgn:7029392"
    ],
    "placetype": [
      "aat:300008707"
    ],
    "id": 1130063,
    "name:xx": "Sisquoc"
  }
}
