{
  "type": "FeatureCollection",
  "features": [
    {
      "geometry": {
        "type": "Point",
        "coordinates": [
          9.183333,
          52.233333
        ]
      },
      "type": "Feature",
      "properties": {
        "hierarchy": [
          "tgn:7115250",
          "tgn:1000003",
          "tgn:7003676",
          "tgn:7000084",
          "tgn:7029392"
        ],
        "placetype": [
          "aat:300008347"
        ],
        "id": 7115250,
        "name:xx": "Osterfelde"
      }
    },
    {
      "geometry": {
        "type": "Point",
        "coordinates": [
          8.65,
          52.2
        ]
      },
      "type": "Feature",
      "properties": {
        "hierarchy": [
          "tgn:7115252",
          "tgn:1000003",
          "tgn:7003677",
          "tgn:7000084",
          "tgn:7029392"
        ],
        "placetype": [
          "aat:300387200"
        ],
        "id": 7115252,
        "name:xx": "Osterfeld"
      }
    },
    {
      "geometry": {
        "type": "Point",
        "coordinates": [
          8.65,
          51.05
        ]
      },
      "type": "Feature",
      "properties": {
        "hierarchy": [
          "tgn:7115254",
          "tgn:1000003",
          "tgn:7003678",
          "tgn:7000084",
          "tgn:7029392"
        ],
        "placetype": [
          "aat:300008347"
        ],
        "id": 7115254,
        "name:xx": "Osterfeld"
      }
    },
    {
      "geometry": {
        "type": "Point",
        "coordinates": [
          8.766667,
          54.866667
        ]
      },
      "type": "Feature",
      "properties": {
        "hierarchy": [
          "tgn:7115255",
          "tgn:1000003",
          "tgn:7003688",
          "tgn:7000084",
          "tgn:7029392"
        ],
        "placetype": [
          "aat:300000206"
        ],
        "id": 7115255,
        "name:xx": "Osterfeld"
      }
    },
    {
      "geometry": {
        "type": "Point",
        "coordinates": [
          9.9,
          54.716667
        ]
      },
      "type": "Feature",
      "properties": {
        "hierarchy": [
          "tgn:7115256",
          "tgn:1000003",
          "tgn:7003688",
          "tgn:7000084",
          "tgn:7029392"
        ],
        "placetype": [
          "aat:300000206"
        ],
        "id": 7115256,
        "name:xx": "Osterfeld"
      }
    },
    {
      "geometry": {
        "type": "Point",
        "coordinates": [
          9.916667,
          54.55
        ]
      },
      "type": "Feature",
      "properties": {
        "hierarchy": [
          "tgn:7115257",
          "tgn:1000003",
          "tgn:7003688",
          "tgn:7000084",
          "tgn:7029392"
        ],
        "placetype": [
          "aat:300000206"
        ],
        "id": 7115257,
        "name:xx": "Osterfeld"
      }
    },
    {
      "geometry": {
        "type": "Point",
        "coordinates": [
          7.716667,
          51.1
        ]
      },
      "type": "Feature",
      "properties": {
        "hierarchy": [
          "tgn:7115258",
          "tgn:1000003",
          "tgn:7003677",
          "tgn:7000084",
          "tgn:7029392"
        ],
        "placetype": [
          "aat:300000206"
        ],
        "id": 7115258,
        "name:xx": "Osterfeld"
      }
    },
    {
      "geometry": {
        "type": "Point",
        "coordinates": [
          7.5,
          52.766667
        ]
      },
      "type": "Feature",
      "properties": {
        "hierarchy": [
          "tgn:7115259",
          "tgn:1000003",
          "tgn:7003676",
          "tgn:7000084",
          "tgn:7029392"
        ],
        "placetype": [
          "aat:300055621"
        ],
        "id": 7115259,
        "name:xx": "Osterfeld"
      }
    }
  ]
}
