{
  "geometry": {
    "type": "Point",
    "coordinates": [
      -83.3167,
      37.3333
    ]
  },
  "type": "Feature",
  "properties": {
    "hierarchy": [
      "tgn:2684021",
      "tgn:1000001",
      "tgn:7012149",
      "tgn:2000836",
      "tgn:7007255",
      "tgn:7029392"
    ],
    "placetype": [
      "aat:300008706"
    ],
    "id": 2684021,
    "name:xx": "Spencer Creek"
  }
}
