{
  "geometry": {
    "type": "Point",
    "coordinates": [
      32.733333,
      25.95
    ]
  },
  "type": "Feature",
  "properties": {
    "hierarchy": [
      "tgn:7526902",
      "tgn:7001242",
      "tgn:7016833",
      "tgn:7000123",
      "tgn:7029392"
    ],
    "placetype": [
      "aat:300343519"
    ],
    "name:en": "Ţūkh, Ḩawḑ",
    "id": 7526902
  }
}
