{
  "geometry": {
    "type": "Point",
    "coordinates": [
      -98.8167,
      26.3667
    ]
  },
  "type": "Feature",
  "properties": {
    "hierarchy": [
      "tgn:2107154",
      "tgn:1000001",
      "tgn:7012149",
      "tgn:2002075",
      "tgn:7007826",
      "tgn:7029392"
    ],
    "placetype": [
      "aat:300008347"
    ],
    "id": 2107154,
    "name:xx": "Rio Grande City"
  }
}
