{
  "geometry": {
    "type": "Point",
    "coordinates": [
      -80.7667,
      38.4833
    ]
  },
  "type": "Feature",
  "properties": {
    "hierarchy": [
      "tgn:2685626",
      "tgn:1000001",
      "tgn:7012149",
      "tgn:2002284",
      "tgn:7013961",
      "tgn:7029392"
    ],
    "placetype": [
      "aat:300008699"
    ],
    "id": 2685626,
    "name:xx": "Spring Bottom Run"
  }
}
