{
  "geometry": {
    "type": "Point",
    "coordinates": [
      -107.6833,
      38.5333
    ]
  },
  "type": "Feature",
  "properties": {
    "hierarchy": [
      "tgn:2585276",
      "tgn:1000001",
      "tgn:7012149",
      "tgn:2000234",
      "tgn:7007158",
      "tgn:7029392"
    ],
    "placetype": [
      "aat:300008761"
    ],
    "id": 2585276,
    "name:xx": "Piñon Springs Draw"
  }
}
