{
  "geometry": {
    "type": "Point",
    "coordinates": [
      -84.95,
      35.2667
    ]
  },
  "type": "Feature",
  "properties": {
    "hierarchy": [
      "tgn:2501025",
      "tgn:1000001",
      "tgn:2001842",
      "tgn:7012149",
      "tgn:7007825",
      "tgn:7029392"
    ],
    "placetype": [
      "aat:300008761"
    ],
    "id": 2501025,
    "name:xx": "McGaha Hollow"
  }
}
