{
  "geometry": {
    "type": "Point",
    "coordinates": [
      -79.5667,
      39.3167
    ]
  },
  "type": "Feature",
  "properties": {
    "hierarchy": [
      "tgn:2185611",
      "tgn:1000001",
      "tgn:7012149",
      "tgn:2002288",
      "tgn:7013961",
      "tgn:7029392"
    ],
    "placetype": [
      "aat:300008697"
    ],
    "id": 2185611,
    "name:xx": "Boiling Spring"
  }
}
