{
  "type": "FeatureCollection",
  "features": [
    {
      "geometry": {
        "type": "Point",
        "coordinates": [
          -9.25,
          53.1667
        ]
      },
      "type": "Feature",
      "properties": {
        "hierarchy": [
          "tgn:1113020",
          "tgn:7003479",
          "tgn:7001198",
          "tgn:1000003",
          "tgn:1000078",
          "tgn:7029392"
        ],
        "placetype": [
          "aat:300132316"
        ],
        "id": 1113020,
        "name:xx": "Galway Bay"
      }
    },
    {
      "geometry": {
        "type": "Point",
        "coordinates": [
          125.3167,
          12.35
        ]
      },
      "type": "Feature",
      "properties": {
        "hierarchy": [
          "tgn:1113021",
          "tgn:1000004",
          "tgn:1001462",
          "tgn:1000135",
          "tgn:7029392"
        ],
        "placetype": [
          "aat:300132316"
        ],
        "id": 1113021,
        "name:xx": "Gamay Bay"
      }
    },
    {
      "geometry": {
        "type": "Point",
        "coordinates": [
          -54.4167,
          49.4167
        ]
      },
      "type": "Feature",
      "properties": {
        "hierarchy": [
          "tgn:1113022",
          "tgn:7005685",
          "tgn:7005807",
          "tgn:1000001",
          "tgn:7005801",
          "tgn:7029392"
        ],
        "placetype": [
          "aat:300132316"
        ],
        "id": 1113022,
        "name:xx": "Gander Bay"
      }
    },
    {
      "geometry": {
        "type": "Point",
        "coordinates": [
          -72.1833,
          41.1
        ]
      },
      "type": "Feature",
      "properties": {
        "hierarchy": [
          "tgn:1113024",
          "tgn:1000001",
          "tgn:7012149",
          "tgn:1002924",
          "tgn:7007568",
          "tgn:7029392"
        ],
        "placetype": [
          "aat:300132316"
        ],
        "id": 1113024,
        "name:xx": "Gardiners Bay"
      }
    },
    {
      "geometry": {
        "type": "Point",
        "coordinates": [
          -85.1667,
          69
        ]
      },
      "type": "Feature",
      "properties": {
        "hierarchy": [
          "tgn:1113025",
          "tgn:7005685",
          "tgn:1000001",
          "tgn:7024197",
          "tgn:7029392"
        ],
        "placetype": [
          "aat:300132316"
        ],
        "id": 1113025,
        "name:xx": "Garry Bay"
      }
    },
    {
      "geometry": {
        "type": "Point",
        "coordinates": [
          -64.5,
          48.8333
        ]
      },
      "type": "Feature",
      "properties": {
        "hierarchy": [
          "tgn:1113026",
          "tgn:7005685",
          "tgn:1000001",
          "tgn:7005804",
          "tgn:7029392"
        ],
        "placetype": [
          "aat:300132316"
        ],
        "id": 1113026,
        "name:xx": "Gaspé, Baie de"
      }
    },
    {
      "geometry": {
        "type": "Point",
        "coordinates": [
          34.1667,
          35.25
        ]
      },
      "type": "Feature",
      "properties": {
        "hierarchy": [
          "tgn:1113027",
          "tgn:7001283",
          "tgn:1000004",
          "tgn:1000112",
          "tgn:7029392"
        ],
        "placetype": [
          "aat:300132316"
        ],
        "id": 1113027,
        "name:xx": "Gazimağusa Körfezi"
      }
    }
  ]
}
