{
  "geometry": {
    "type": "Point",
    "coordinates": [
      -78.4167,
      41.4333
    ]
  },
  "type": "Feature",
  "properties": {
    "hierarchy": [
      "tgn:2757793",
      "tgn:1000001",
      "tgn:7012149",
      "tgn:7007710",
      "tgn:7029392"
    ],
    "placetype": [
      "aat:300008699"
    ],
    "id": 2757793,
    "name:xx": "West Branch Hicks Run"
  }
}
