{
  "geometry": {
    "type": "Point",
    "coordinates": [
      -87.0667,
      37.2333
    ]
  },
  "type": "Feature",
  "properties": {
    "hierarchy": [
      "tgn:2037740",
      "tgn:1000001",
      "tgn:7012149",
      "tgn:2000832",
      "tgn:7007255",
      "tgn:7029392"
    ],
    "placetype": [
      "aat:300008347",
      "aat:300387210"
    ],
    "id": 2037740,
    "name:xx": "Bevier"
  }
}
