{
  "type": "FeatureCollection",
  "features": [
    {
      "geometry": {
        "type": "Point",
        "coordinates": [
          4.833899,
          50.829772
        ]
      },
      "type": "Feature",
      "properties": {
        "hierarchy": [
          "tgn:7254830",
          "tgn:7018239",
          "tgn:1000003",
          "tgn:1000063",
          "tgn:7018236",
          "tgn:7029392"
        ],
        "placetype": [
          "aat:300008347"
        ],
        "id": 7254830,
        "name:xx": "Vertrijk"
      }
    },
    {
      "geometry": {
        "type": "Point",
        "coordinates": [
          3.3,
          50.65
        ]
      },
      "type": "Feature",
      "properties": {
        "hierarchy": [
          "tgn:7254832",
          "tgn:7007877",
          "tgn:1000003",
          "tgn:1000063",
          "tgn:4012014",
          "tgn:7029392"
        ],
        "placetype": [
          "aat:300008347"
        ],
        "id": 7254832,
        "name:xx": "Vert Marais"
      }
    },
    {
      "geometry": {
        "type": "Point",
        "coordinates": [
          5.783333,
          50.733333
        ]
      },
      "type": "Feature",
      "properties": {
        "hierarchy": [
          "tgn:7254833",
          "tgn:7003460",
          "tgn:1000003",
          "tgn:1000063",
          "tgn:4012014",
          "tgn:7029392"
        ],
        "placetype": [
          "aat:300008347"
        ],
        "id": 7254833,
        "name:xx": "Verte Haie"
      }
    },
    {
      "geometry": {
        "type": "Point",
        "coordinates": [
          5.783333,
          50.5
        ]
      },
      "type": "Feature",
      "properties": {
        "hierarchy": [
          "tgn:7254834",
          "tgn:7003460",
          "tgn:1000003",
          "tgn:1000063",
          "tgn:4012014",
          "tgn:7029392"
        ],
        "placetype": [
          "aat:300008347"
        ],
        "id": 7254834,
        "name:xx": "Verte Fontaine"
      }
    },
    {
      "geometry": {
        "type": "Point",
        "coordinates": [
          3.95,
          50.583333
        ]
      },
      "type": "Feature",
      "properties": {
        "hierarchy": [
          "tgn:7254835",
          "tgn:7007877",
          "tgn:1000003",
          "tgn:1000063",
          "tgn:4012014",
          "tgn:7029392"
        ],
        "placetype": [
          "aat:300000206"
        ],
        "id": 7254835,
        "name:xx": "Ferme du Vert Denis"
      }
    },
    {
      "geometry": {
        "type": "Point",
        "coordinates": [
          4.416667,
          50.7
        ]
      },
      "type": "Feature",
      "properties": {
        "hierarchy": [
          "tgn:7254836",
          "tgn:7018238",
          "tgn:1000003",
          "tgn:1000063",
          "tgn:4012014",
          "tgn:7029392"
        ],
        "placetype": [
          "aat:300008347"
        ],
        "id": 7254836,
        "name:xx": "Vert Coucou"
      }
    },
    {
      "geometry": {
        "type": "Point",
        "coordinates": [
          4.15,
          50.533333
        ]
      },
      "type": "Feature",
      "properties": {
        "hierarchy": [
          "tgn:7254837",
          "tgn:7007877",
          "tgn:1000003",
          "tgn:1000063",
          "tgn:4012014",
          "tgn:7029392"
        ],
        "placetype": [
          "aat:300008347"
        ],
        "id": 7254837,
        "name:xx": "Vert Coucou"
      }
    },
    {
      "geometry": {
        "type": "Point",
        "coordinates": [
          3.6,
          50.5
        ]
      },
      "type": "Feature",
      "properties": {
        "hierarchy": [
          "tgn:7254838",
          "tgn:7007877",
          "tgn:1000003",
          "tgn:1000063",
          "tgn:4012014",
          "tgn:7029392"
        ],
        "placetype": [
          "aat:300008347"
        ],
        "id": 7254838,
        "name:xx": "Vert Coron"
      }
    },
    {
      "geometry": {
        "type": "Point",
        "coordinates": [
          4.366667,
          50.8
        ]
      },
      "type": "Feature",
      "properties": {
        "hierarchy": [
          "tgn:7254839",
          "tgn:7018237",
          "tgn:1000003",
          "tgn:1000063",
          "tgn:7029392"
        ],
        "placetype": [
          "aat:300008347"
        ],
        "id": 7254839,
        "name:xx": "Vert Chasseur"
      }
    }
  ]
}
