{
  "geometry": {
    "type": "Point",
    "coordinates": [
      -76.75,
      41.4667
    ]
  },
  "type": "Feature",
  "properties": {
    "hierarchy": [
      "tgn:2193787",
      "tgn:1000001",
      "tgn:7012149",
      "tgn:7007710",
      "tgn:7029392"
    ],
    "placetype": [
      "aat:300008699"
    ],
    "id": 2193787,
    "name:xx": "Brian Branch"
  }
}
