{
  "geometry": {
    "type": "Point",
    "coordinates": [
      -118.5167,
      35.7833
    ]
  },
  "type": "Feature",
  "properties": {
    "hierarchy": [
      "tgn:2205997",
      "tgn:1000001",
      "tgn:7012149",
      "tgn:7007157",
      "tgn:1002956",
      "tgn:7029392"
    ],
    "placetype": [
      "aat:300386845"
    ],
    "id": 2205997,
    "name:xx": "Bull Run Basin"
  }
}
