{
  "geometry": {
    "type": "Point",
    "coordinates": [
      -82.5833,
      28.15
    ]
  },
  "type": "Feature",
  "properties": {
    "hierarchy": [
      "tgn:2266774",
      "tgn:1000001",
      "tgn:1002479",
      "tgn:7012149",
      "tgn:7007240",
      "tgn:7029392"
    ],
    "placetype": [
      "aat:300008680"
    ],
    "id": 2266774,
    "name:xx": "Crescent Lake"
  }
}
