{
  "geometry": {
    "type": "Point",
    "coordinates": [
      -78.7167,
      34.3333
    ]
  },
  "type": "Feature",
  "properties": {
    "hierarchy": [
      "tgn:2704992",
      "tgn:1000001",
      "tgn:2001485",
      "tgn:7012149",
      "tgn:7007709",
      "tgn:7029392"
    ],
    "placetype": [
      "aat:300008347"
    ],
    "id": 2704992,
    "name:xx": "Sunset Terrace"
  }
}
