{
  "geometry": {
    "type": "Point",
    "coordinates": [
      34.221053,
      27.871252
    ]
  },
  "type": "Feature",
  "properties": {
    "hierarchy": [
      "tgn:7533761",
      "tgn:7001242",
      "tgn:7016833",
      "tgn:7001336",
      "tgn:7029392"
    ],
    "placetype": [
      "aat:300379998"
    ],
    "name:en": "Madsūs, Wādī",
    "id": 7533761
  }
}
