{
  "type": "FeatureCollection",
  "features": [
    {
      "geometry": {
        "type": "Point",
        "coordinates": [
          -104.45,
          24.316667
        ]
      },
      "type": "Feature",
      "properties": {
        "hierarchy": [
          "tgn:7386170",
          "tgn:7005583",
          "tgn:1000001",
          "tgn:7005560",
          "tgn:7029392"
        ],
        "placetype": [
          "aat:300008795"
        ],
        "id": 7386170,
        "name:xx": "Prieto, Cerro"
      }
    },
    {
      "geometry": {
        "type": "Point",
        "coordinates": [
          -102.916667,
          24.25
        ]
      },
      "type": "Feature",
      "properties": {
        "hierarchy": [
          "tgn:7386171",
          "tgn:1000001",
          "tgn:7005601",
          "tgn:7005560",
          "tgn:7029392"
        ],
        "placetype": [
          "aat:300008795"
        ],
        "id": 7386171,
        "name:xx": "Prieto, Cerro"
      }
    },
    {
      "geometry": {
        "type": "Point",
        "coordinates": [
          -105.266667,
          24.183333
        ]
      },
      "type": "Feature",
      "properties": {
        "hierarchy": [
          "tgn:7386172",
          "tgn:7005583",
          "tgn:1000001",
          "tgn:7005560",
          "tgn:7029392"
        ],
        "placetype": [
          "aat:300008795"
        ],
        "id": 7386172,
        "name:xx": "Prieto, Cerro"
      }
    },
    {
      "geometry": {
        "type": "Point",
        "coordinates": [
          -105.649167,
          24.149444
        ]
      },
      "type": "Feature",
      "properties": {
        "hierarchy": [
          "tgn:7386173",
          "tgn:7005583",
          "tgn:1000001",
          "tgn:7005560",
          "tgn:7029392"
        ],
        "placetype": [
          "aat:300008795"
        ],
        "id": 7386173,
        "name:xx": "Prieto, Cerro"
      }
    },
    {
      "geometry": {
        "type": "Point",
        "coordinates": [
          -101.983333,
          20.016667
        ]
      },
      "type": "Feature",
      "properties": {
        "hierarchy": [
          "tgn:7386174",
          "tgn:1000001",
          "tgn:7005590",
          "tgn:7005560",
          "tgn:7029392"
        ],
        "placetype": [
          "aat:300008795"
        ],
        "id": 7386174,
        "name:xx": "Prieto, Cerro"
      }
    },
    {
      "geometry": {
        "type": "Point",
        "coordinates": [
          -102.35,
          19.933333
        ]
      },
      "type": "Feature",
      "properties": {
        "hierarchy": [
          "tgn:7386175",
          "tgn:1000001",
          "tgn:7005590",
          "tgn:7005560",
          "tgn:7029392"
        ],
        "placetype": [
          "aat:300008795"
        ],
        "id": 7386175,
        "name:xx": "Prieto, Cerro"
      }
    },
    {
      "geometry": {
        "type": "Point",
        "coordinates": [
          -103.25,
          19.866667
        ]
      },
      "type": "Feature",
      "properties": {
        "hierarchy": [
          "tgn:7386176",
          "tgn:7005586",
          "tgn:1000001",
          "tgn:7005560",
          "tgn:7029392"
        ],
        "placetype": [
          "aat:300008795"
        ],
        "id": 7386176,
        "name:xx": "Prieto, Cerro"
      }
    },
    {
      "geometry": {
        "type": "Point",
        "coordinates": [
          -100.083333,
          19.85
        ]
      },
      "type": "Feature",
      "properties": {
        "hierarchy": [
          "tgn:7386177",
          "tgn:1000001",
          "tgn:1001893",
          "tgn:7005560",
          "tgn:7029392"
        ],
        "placetype": [
          "aat:300008795"
        ],
        "id": 7386177,
        "name:xx": "Prieto, Cerro"
      }
    },
    {
      "geometry": {
        "type": "Point",
        "coordinates": [
          -104.616667,
          19.55
        ]
      },
      "type": "Feature",
      "properties": {
        "hierarchy": [
          "tgn:7386178",
          "tgn:7005586",
          "tgn:1000001",
          "tgn:7005560",
          "tgn:7029392"
        ],
        "placetype": [
          "aat:300008795"
        ],
        "id": 7386178,
        "name:xx": "Prieto, Cerro"
      }
    },
    {
      "geometry": {
        "type": "Point",
        "coordinates": [
          -102.216667,
          19.433333
        ]
      },
      "type": "Feature",
      "properties": {
        "hierarchy": [
          "tgn:7386179",
          "tgn:1000001",
          "tgn:7005590",
          "tgn:7005560",
          "tgn:7029392"
        ],
        "placetype": [
          "aat:300008795"
        ],
        "id": 7386179,
        "name:xx": "Prieto, Cerro"
      }
    }
  ]
}
