{
  "geometry": {
    "type": "Point",
    "coordinates": [
      23.6667,
      46.9333
    ]
  },
  "type": "Feature",
  "properties": {
    "hierarchy": [
      "tgn:1050038",
      "tgn:7004278",
      "tgn:1000003",
      "tgn:1000091",
      "tgn:7029392"
    ],
    "placetype": [
      "aat:300008347"
    ],
    "id": 1050038,
    "name:xx": "Borșa"
  }
}
