{
  "geometry": {
    "type": "Point",
    "coordinates": [
      -84.1167,
      41.45
    ]
  },
  "type": "Feature",
  "properties": {
    "hierarchy": [
      "tgn:2441900",
      "tgn:1000001",
      "tgn:7012149",
      "tgn:7007706",
      "tgn:7029392"
    ],
    "placetype": [
      "aat:300006075"
    ],
    "id": 2441900,
    "name:xx": "Konzem Ditch"
  }
}
