{
  "geometry": {
    "type": "Point",
    "coordinates": [
      -82.7333,
      36.8667
    ]
  },
  "type": "Feature",
  "properties": {
    "hierarchy": [
      "tgn:2110663",
      "tgn:1000001",
      "tgn:7012149",
      "tgn:2002195",
      "tgn:7007919",
      "tgn:7029392"
    ],
    "placetype": [
      "aat:300008347"
    ],
    "id": 2110663,
    "name:xx": "Big Stone Gap"
  }
}
