{
  "geometry": {
    "type": "Point",
    "coordinates": [
      -80.5333,
      38.7167
    ]
  },
  "type": "Feature",
  "properties": {
    "hierarchy": [
      "tgn:2377595",
      "tgn:1000001",
      "tgn:2002256",
      "tgn:7012149",
      "tgn:7013961",
      "tgn:7029392"
    ],
    "placetype": [
      "aat:300266640"
    ],
    "id": 2377595,
    "name:xx": "Harper Ridge"
  }
}
