{
  "geometry": {
    "type": "Point",
    "coordinates": [
      -82.4833,
      36.1667
    ]
  },
  "type": "Feature",
  "properties": {
    "hierarchy": [
      "tgn:2316681",
      "tgn:1000001",
      "tgn:7012149",
      "tgn:7007825",
      "tgn:7029392"
    ],
    "placetype": [
      "aat:300266640"
    ],
    "id": 2316681,
    "name:xx": "Embreeville Mountain"
  }
}
