{
  "geometry": {
    "type": "Point",
    "coordinates": [
      -67.7667,
      8.25
    ]
  },
  "type": "Feature",
  "properties": {
    "hierarchy": [
      "tgn:1025171",
      "tgn:1001837",
      "tgn:1000002",
      "tgn:1000059",
      "tgn:7029392"
    ],
    "placetype": [
      "aat:300008347"
    ],
    "id": 1025171,
    "name:xx": "La Unión"
  }
}
