{
  "geometry": {
    "type": "Point",
    "coordinates": [
      -114.5667,
      32.6667
    ]
  },
  "type": "Feature",
  "properties": {
    "hierarchy": [
      "tgn:2006757",
      "tgn:1000001",
      "tgn:7006451",
      "tgn:7012149",
      "tgn:2000104",
      "tgn:7029392"
    ],
    "placetype": [
      "aat:300387016"
    ],
    "id": 2006757,
    "name:xx": "East Yard"
  }
}
