{
  "geometry": {
    "type": "Point",
    "coordinates": [
      -119.55,
      35.0667
    ]
  },
  "type": "Feature",
  "properties": {
    "hierarchy": [
      "tgn:2314912",
      "tgn:1000001",
      "tgn:7012149",
      "tgn:7007157",
      "tgn:1002863",
      "tgn:7029392"
    ],
    "placetype": [
      "aat:300008805"
    ],
    "id": 2314912,
    "name:xx": "Elkhorn Plain"
  }
}
