{
  "geometry": {
    "type": "Point",
    "coordinates": [
      118.0167,
      27.7667
    ]
  },
  "type": "Feature",
  "properties": {
    "hierarchy": [
      "tgn:1067235",
      "tgn:1000004",
      "tgn:7001796",
      "tgn:1000111",
      "tgn:7029392"
    ],
    "placetype": [
      "aat:300008347"
    ],
    "id": 1067235,
    "name:xx": "Chong'an"
  }
}
