{
  "geometry": {
    "type": "Point",
    "coordinates": [
      -8.6833,
      8.3667
    ]
  },
  "type": "Feature",
  "properties": {
    "hierarchy": [
      "tgn:1090223",
      "tgn:7001242",
      "tgn:7000795",
      "tgn:1000167",
      "tgn:7029392"
    ],
    "placetype": [
      "aat:300008347"
    ],
    "id": 1090223,
    "name:xx": "Boola"
  }
}
