{
  "type": "FeatureCollection",
  "features": [
    {
      "geometry": {
        "type": "Point",
        "coordinates": [
          31.149379,
          31.255773
        ]
      },
      "type": "Feature",
      "properties": {
        "hierarchy": [
          "tgn:7540730",
          "tgn:7001242",
          "tgn:7016833",
          "tgn:1001335",
          "tgn:7029392"
        ],
        "placetype": [
          "aat:300008347"
        ],
        "id": 7540730,
        "name:xx": "'Izbat Fawzīyah"
      }
    },
    {
      "geometry": {
        "type": "Point",
        "coordinates": [
          31.149098,
          31.263202
        ]
      },
      "type": "Feature",
      "properties": {
        "hierarchy": [
          "tgn:7540731",
          "tgn:7001242",
          "tgn:7016833",
          "tgn:1001335",
          "tgn:7029392"
        ],
        "placetype": [
          "aat:300008347"
        ],
        "id": 7540731,
        "name:xx": "'Izbat Firyāl"
      }
    },
    {
      "geometry": {
        "type": "Point",
        "coordinates": [
          31.124483,
          31.257556
        ]
      },
      "type": "Feature",
      "properties": {
        "hierarchy": [
          "tgn:7540732",
          "tgn:7001242",
          "tgn:7016833",
          "tgn:1001335",
          "tgn:7029392"
        ],
        "placetype": [
          "aat:300008347"
        ],
        "id": 7540732,
        "name:xx": "'Izbat Artīnah"
      }
    },
    {
      "geometry": {
        "type": "Point",
        "coordinates": [
          31.116881,
          31.262656
        ]
      },
      "type": "Feature",
      "properties": {
        "hierarchy": [
          "tgn:7540733",
          "tgn:7001242",
          "tgn:7016833",
          "tgn:1001335",
          "tgn:7029392"
        ],
        "placetype": [
          "aat:300008347"
        ],
        "id": 7540733,
        "name:xx": "'Izbat al Manāwfah"
      }
    },
    {
      "geometry": {
        "type": "Point",
        "coordinates": [
          31.118875,
          31.25919
        ]
      },
      "type": "Feature",
      "properties": {
        "hierarchy": [
          "tgn:7540734",
          "tgn:7001242",
          "tgn:7016833",
          "tgn:1001335",
          "tgn:7029392"
        ],
        "placetype": [
          "aat:300008347"
        ],
        "id": 7540734,
        "name:xx": "'Izbat 'Abd al Karīm al Qiblīyah"
      }
    },
    {
      "geometry": {
        "type": "Point",
        "coordinates": [
          31.106763,
          31.260082
        ]
      },
      "type": "Feature",
      "properties": {
        "hierarchy": [
          "tgn:7540735",
          "tgn:7001242",
          "tgn:7016833",
          "tgn:1001335",
          "tgn:7029392"
        ],
        "placetype": [
          "aat:300008347"
        ],
        "id": 7540735,
        "name:xx": "'Izbat Maḩmūd Abū Yūsif"
      }
    },
    {
      "geometry": {
        "type": "Point",
        "coordinates": [
          31.039416,
          31.260368
        ]
      },
      "type": "Feature",
      "properties": {
        "hierarchy": [
          "tgn:7540736",
          "tgn:7001242",
          "tgn:7016833",
          "tgn:1001335",
          "tgn:7029392"
        ],
        "placetype": [
          "aat:300008347"
        ],
        "id": 7540736,
        "name:xx": "'Izbat Abū Aḩmad"
      }
    },
    {
      "geometry": {
        "type": "Point",
        "coordinates": [
          31.028607,
          31.260015
        ]
      },
      "type": "Feature",
      "properties": {
        "hierarchy": [
          "tgn:7540737",
          "tgn:7001242",
          "tgn:7016833",
          "tgn:1001335",
          "tgn:7029392"
        ],
        "placetype": [
          "aat:300007836"
        ],
        "id": 7540737,
        "name:xx": "Kūbrī az Zāwiyah"
      }
    },
    {
      "geometry": {
        "type": "Point",
        "coordinates": [
          31.240973,
          31.275483
        ]
      },
      "type": "Feature",
      "properties": {
        "hierarchy": [
          "tgn:7540738",
          "tgn:7001242",
          "tgn:7016833",
          "tgn:1001335",
          "tgn:7029392"
        ],
        "placetype": [
          "aat:300008347"
        ],
        "id": 7540738,
        "name:xx": "'Izbat Siraywah al Kubrá"
      }
    },
    {
      "geometry": {
        "type": "Point",
        "coordinates": [
          31.221555,
          31.277863
        ]
      },
      "type": "Feature",
      "properties": {
        "hierarchy": [
          "tgn:7540739",
          "tgn:7001242",
          "tgn:7016833",
          "tgn:1001335",
          "tgn:7029392"
        ],
        "placetype": [
          "aat:300008347"
        ],
        "id": 7540739,
        "name:xx": "'Izbat at Tarzī"
      }
    }
  ]
}
