{
  "geometry": {
    "type": "Point",
    "coordinates": [
      -77.95,
      40.3667
    ]
  },
  "type": "Feature",
  "properties": {
    "hierarchy": [
      "tgn:2642179",
      "tgn:1000001",
      "tgn:7012149",
      "tgn:1002494",
      "tgn:7007710",
      "tgn:7029392"
    ],
    "placetype": [
      "aat:300266640"
    ],
    "id": 2642179,
    "name:xx": "Sand Ridge"
  }
}
