{
  "geometry": {
    "type": "Point",
    "coordinates": [
      -70.7833,
      41.6833
    ]
  },
  "type": "Feature",
  "properties": {
    "hierarchy": [
      "tgn:2140149",
      "tgn:1000001",
      "tgn:7014423",
      "tgn:7012149",
      "tgn:7007517",
      "tgn:7029392"
    ],
    "placetype": [
      "aat:300008706"
    ],
    "id": 2140149,
    "name:xx": "Aucoot Creek"
  }
}
