{
  "geometry": {
    "type": "Point",
    "coordinates": [
      -110.7667,
      33.2833
    ]
  },
  "type": "Feature",
  "properties": {
    "hierarchy": [
      "tgn:2205303",
      "tgn:1000001",
      "tgn:7006451",
      "tgn:2000093",
      "tgn:7012149",
      "tgn:7029392"
    ],
    "placetype": [
      "aat:300008761"
    ],
    "id": 2205303,
    "name:xx": "Bull Canyon"
  }
}
