{
  "geometry": {
    "type": "Point",
    "coordinates": [
      -92.7333,
      34.4833
    ]
  },
  "type": "Feature",
  "properties": {
    "hierarchy": [
      "tgn:2277835",
      "tgn:1000001",
      "tgn:7016172",
      "tgn:7012149",
      "tgn:2000167",
      "tgn:7029392"
    ],
    "placetype": [
      "aat:300006191"
    ],
    "id": 2277835,
    "name:xx": "Dawson Lake"
  }
}
