{
  "geometry": {
    "type": "Point",
    "coordinates": [
      -83.1667,
      35.75
    ]
  },
  "type": "Feature",
  "properties": {
    "hierarchy": [
      "tgn:2349753",
      "tgn:1000001",
      "tgn:7012149",
      "tgn:2001851",
      "tgn:7007825",
      "tgn:7029392"
    ],
    "placetype": [
      "aat:300008699"
    ],
    "id": 2349753,
    "name:xx": "Gilliland Fork"
  }
}
