{
  "geometry": {
    "type": "Point",
    "coordinates": [
      -54.3167,
      -24.4667
    ]
  },
  "type": "Feature",
  "properties": {
    "hierarchy": [
      "tgn:1022566",
      "tgn:7006247",
      "tgn:1000047",
      "tgn:7002456",
      "tgn:1000002",
      "tgn:7029392"
    ],
    "placetype": [
      "aat:300008347"
    ],
    "id": 1022566,
    "name:xx": "Pôrto Mendes"
  }
}
