{
  "geometry": {
    "type": "Point",
    "coordinates": [
      -95.9333,
      36.45
    ]
  },
  "type": "Feature",
  "properties": {
    "hierarchy": [
      "tgn:2645158",
      "tgn:1000001",
      "tgn:7012149",
      "tgn:2001696",
      "tgn:7007707",
      "tgn:7029392"
    ],
    "placetype": [
      "aat:300008706"
    ],
    "id": 2645158,
    "name:xx": "Saunders Creek"
  }
}
