{
  "type": "FeatureCollection",
  "features": [
    {
      "geometry": {
        "type": "Point",
        "coordinates": [
          177.566667,
          -38.466667
        ]
      },
      "type": "Feature",
      "properties": {
        "hierarchy": [
          "tgn:7511050",
          "tgn:7520092",
          "tgn:1008380",
          "tgn:1000226",
          "tgn:1000006",
          "tgn:7029392"
        ],
        "placetype": [
          "aat:300008795"
        ],
        "name:en": "Taumata a te Kahu",
        "id": 7511050
      }
    },
    {
      "geometry": {
        "type": "Point",
        "coordinates": [
          178.1,
          -37.55
        ]
      },
      "type": "Feature",
      "properties": {
        "hierarchy": [
          "tgn:7511051",
          "tgn:7520092",
          "tgn:1008380",
          "tgn:1000226",
          "tgn:1000006",
          "tgn:7029392"
        ],
        "placetype": [
          "aat:300008795"
        ],
        "name:en": "Taumata a Ruru",
        "id": 7511051
      }
    },
    {
      "geometry": {
        "type": "Point",
        "coordinates": [
          174.8,
          -39.25
        ]
      },
      "type": "Feature",
      "properties": {
        "hierarchy": [
          "tgn:7511052",
          "tgn:1008380",
          "tgn:1000226",
          "tgn:7016827",
          "tgn:1000006",
          "tgn:7029392"
        ],
        "placetype": [
          "aat:300008699"
        ],
        "name:en": "Taumata",
        "id": 7511052
      }
    },
    {
      "geometry": {
        "type": "Point",
        "coordinates": [
          175.183333,
          -39.7
        ]
      },
      "type": "Feature",
      "properties": {
        "hierarchy": [
          "tgn:7511053",
          "tgn:1008380",
          "tgn:7520093",
          "tgn:1000226",
          "tgn:1000006",
          "tgn:7029392"
        ],
        "placetype": [
          "aat:300008795"
        ],
        "name:en": "Taumata",
        "id": 7511053
      }
    },
    {
      "geometry": {
        "type": "Point",
        "coordinates": [
          175.9,
          -39.583333
        ]
      },
      "type": "Feature",
      "properties": {
        "hierarchy": [
          "tgn:7511054",
          "tgn:1008380",
          "tgn:7520093",
          "tgn:1000226",
          "tgn:1000006",
          "tgn:7029392"
        ],
        "placetype": [
          "aat:300008795"
        ],
        "name:en": "Taumata",
        "id": 7511054
      }
    },
    {
      "geometry": {
        "type": "Point",
        "coordinates": [
          173.4,
          -35.066667
        ]
      },
      "type": "Feature",
      "properties": {
        "hierarchy": [
          "tgn:7511055",
          "tgn:1008380",
          "tgn:7000507",
          "tgn:1000226",
          "tgn:1000006",
          "tgn:7029392"
        ],
        "placetype": [
          "aat:300008777"
        ],
        "name:en": "Taumata",
        "id": 7511055
      }
    },
    {
      "geometry": {
        "type": "Point",
        "coordinates": [
          169.466667,
          -46.15
        ]
      },
      "type": "Feature",
      "properties": {
        "hierarchy": [
          "tgn:7511056",
          "tgn:1009227",
          "tgn:1000226",
          "tgn:7018437",
          "tgn:1000006",
          "tgn:7029392"
        ],
        "placetype": [
          "aat:300008347"
        ],
        "name:en": "Taumata",
        "id": 7511056
      }
    }
  ]
}
