{
  "geometry": {
    "type": "Point",
    "coordinates": [
      -121.8833,
      46.9333
    ]
  },
  "type": "Feature",
  "properties": {
    "hierarchy": [
      "tgn:2164516",
      "tgn:1000001",
      "tgn:7012149",
      "tgn:1002785",
      "tgn:7007920",
      "tgn:7029392"
    ],
    "placetype": [
      "aat:300008798"
    ],
    "id": 2164516,
    "name:xx": "Berry Peak"
  }
}
