{
  "geometry": {
    "type": "Point",
    "coordinates": [
      -91.5667,
      38.1667
    ]
  },
  "type": "Feature",
  "properties": {
    "hierarchy": [
      "tgn:2060214",
      "tgn:1000001",
      "tgn:7012149",
      "tgn:1002402",
      "tgn:7007523",
      "tgn:7029392"
    ],
    "placetype": [
      "aat:300008347"
    ],
    "id": 2060214,
    "name:xx": "Redbird"
  }
}
