{
  "geometry": {
    "type": "Point",
    "coordinates": [
      -88.15,
      37.5333
    ]
  },
  "type": "Feature",
  "properties": {
    "hierarchy": [
      "tgn:2516802",
      "tgn:1000001",
      "tgn:7012149",
      "tgn:2000509",
      "tgn:7007251",
      "tgn:7029392"
    ],
    "placetype": [
      "aat:300000390"
    ],
    "id": 2516802,
    "name:xx": "Minerva Mine Number 1"
  }
}
