{
  "geometry": {
    "type": "Point",
    "coordinates": [
      121.4667,
      6.75
    ]
  },
  "type": "Feature",
  "properties": {
    "hierarchy": [
      "tgn:1006920",
      "tgn:1001145",
      "tgn:1010216",
      "tgn:1000004",
      "tgn:1000135",
      "tgn:7029392"
    ],
    "placetype": [
      "aat:300008791"
    ],
    "id": 1006920,
    "name:xx": "Dassalan Island"
  }
}
