{
  "geometry": {
    "type": "Point",
    "coordinates": [
      -16.1667,
      13.4833
    ]
  },
  "type": "Feature",
  "properties": {
    "hierarchy": [
      "tgn:1090072",
      "tgn:7001242",
      "tgn:7017738",
      "tgn:1000165",
      "tgn:7029392"
    ],
    "placetype": [
      "aat:300008347",
      "aat:300387220",
      "aat:300008375"
    ],
    "id": 1090072,
    "name:xx": "Kerewan"
  }
}
