{
  "geometry": {
    "type": "Point",
    "coordinates": [
      -90.7667,
      37.5667
    ]
  },
  "type": "Feature",
  "properties": {
    "hierarchy": [
      "tgn:2599323",
      "tgn:1000001",
      "tgn:7012149",
      "tgn:2001236",
      "tgn:7007523",
      "tgn:7029392"
    ],
    "placetype": [
      "aat:300008798"
    ],
    "id": 2599323,
    "name:xx": "Proffit Mountain"
  }
}
