{
  "geometry": {
    "type": "Point",
    "coordinates": [
      -94.65,
      45.8333
    ]
  },
  "type": "Feature",
  "properties": {
    "hierarchy": [
      "tgn:2520113",
      "tgn:1000001",
      "tgn:7012149",
      "tgn:2001075",
      "tgn:7007521",
      "tgn:7029392"
    ],
    "placetype": [
      "aat:300008680"
    ],
    "id": 2520113,
    "name:xx": "Molly Lake"
  }
}
