{
  "geometry": {
    "type": "Point",
    "coordinates": [
      -86.2667,
      40.95
    ]
  },
  "type": "Feature",
  "properties": {
    "hierarchy": [
      "tgn:2446123",
      "tgn:1000001",
      "tgn:7012149",
      "tgn:1002396",
      "tgn:7007252",
      "tgn:7029392"
    ],
    "placetype": [
      "aat:300006075"
    ],
    "id": 2446123,
    "name:xx": "Levi Rouch Ditch"
  }
}
