{
  "geometry": {
    "type": "Point",
    "coordinates": [
      -87.5667,
      37.9167
    ]
  },
  "type": "Feature",
  "properties": {
    "hierarchy": [
      "tgn:2620457",
      "tgn:1000001",
      "tgn:7012149",
      "tgn:2000799",
      "tgn:7007255",
      "tgn:7029392"
    ],
    "placetype": [
      "aat:300008699"
    ],
    "id": 2620457,
    "name:xx": "River Slough"
  }
}
