{
  "geometry": {
    "type": "Point",
    "coordinates": [
      -62.3333,
      -13.05
    ]
  },
  "type": "Feature",
  "properties": {
    "hierarchy": [
      "tgn:1122997",
      "tgn:1001944",
      "tgn:1000047",
      "tgn:7002456",
      "tgn:1000002",
      "tgn:7029392"
    ],
    "placetype": [
      "aat:300008707"
    ],
    "id": 1122997,
    "name:xx": "Colorado"
  }
}
