{
  "type": "FeatureCollection",
  "features": [
    {
      "geometry": {
        "type": "Point",
        "coordinates": [
          -92.5667,
          35.85
        ]
      },
      "type": "Feature",
      "properties": {
        "hierarchy": [
          "tgn:2145560",
          "tgn:1000001",
          "tgn:7016172",
          "tgn:7012149",
          "tgn:2000169",
          "tgn:7029392"
        ],
        "placetype": [
          "aat:300008798"
        ],
        "id": 2145560,
        "name:xx": "Baldwin Hill"
      }
    },
    {
      "geometry": {
        "type": "Point",
        "coordinates": [
          -72.0667,
          41.3833
        ]
      },
      "type": "Feature",
      "properties": {
        "hierarchy": [
          "tgn:2145561",
          "tgn:1000001",
          "tgn:1002714",
          "tgn:7012149",
          "tgn:7007159",
          "tgn:7029392"
        ],
        "placetype": [
          "aat:300008798"
        ],
        "id": 2145561,
        "name:xx": "Baldwin Hill"
      }
    },
    {
      "geometry": {
        "type": "Point",
        "coordinates": [
          -73.3333,
          41.6667
        ]
      },
      "type": "Feature",
      "properties": {
        "hierarchy": [
          "tgn:2145562",
          "tgn:1000001",
          "tgn:1002601",
          "tgn:7012149",
          "tgn:7007159",
          "tgn:7029392"
        ],
        "placetype": [
          "aat:300008798"
        ],
        "id": 2145562,
        "name:xx": "Baldwin Hill"
      }
    },
    {
      "geometry": {
        "type": "Point",
        "coordinates": [
          -70.0667,
          44.4167
        ]
      },
      "type": "Feature",
      "properties": {
        "hierarchy": [
          "tgn:2145563",
          "tgn:1000001",
          "tgn:2000923",
          "tgn:7012149",
          "tgn:7007515",
          "tgn:7029392"
        ],
        "placetype": [
          "aat:300008798"
        ],
        "id": 2145563,
        "name:xx": "Baldwin Hill"
      }
    },
    {
      "geometry": {
        "type": "Point",
        "coordinates": [
          -73.4333,
          42.1833
        ]
      },
      "type": "Feature",
      "properties": {
        "hierarchy": [
          "tgn:2145564",
          "tgn:7013388",
          "tgn:1000001",
          "tgn:7012149",
          "tgn:7007517",
          "tgn:7029392"
        ],
        "placetype": [
          "aat:300008798"
        ],
        "id": 2145564,
        "name:xx": "Baldwin Hill"
      }
    },
    {
      "geometry": {
        "type": "Point",
        "coordinates": [
          -72.15,
          42.5667
        ]
      },
      "type": "Feature",
      "properties": {
        "hierarchy": [
          "tgn:2145565",
          "tgn:1000001",
          "tgn:7012149",
          "tgn:1003038",
          "tgn:7007517",
          "tgn:7029392"
        ],
        "placetype": [
          "aat:300008798"
        ],
        "id": 2145565,
        "name:xx": "Baldwin Hill"
      }
    },
    {
      "geometry": {
        "type": "Point",
        "coordinates": [
          -73.9167,
          44.3833
        ]
      },
      "type": "Feature",
      "properties": {
        "hierarchy": [
          "tgn:2145566",
          "tgn:1000001",
          "tgn:7012149",
          "tgn:2001461",
          "tgn:7007568",
          "tgn:7029392"
        ],
        "placetype": [
          "aat:300008798"
        ],
        "id": 2145566,
        "name:xx": "Baldwin Hill"
      }
    },
    {
      "geometry": {
        "type": "Point",
        "coordinates": [
          -83.6167,
          36.45
        ]
      },
      "type": "Feature",
      "properties": {
        "hierarchy": [
          "tgn:2145567",
          "tgn:1000001",
          "tgn:7012149",
          "tgn:2001849",
          "tgn:7007825",
          "tgn:7029392"
        ],
        "placetype": [
          "aat:300266640"
        ],
        "id": 2145567,
        "name:xx": "Baldwin Hill"
      }
    },
    {
      "geometry": {
        "type": "Point",
        "coordinates": [
          -71.7,
          44.4833
        ]
      },
      "type": "Feature",
      "properties": {
        "hierarchy": [
          "tgn:2145568",
          "tgn:1000001",
          "tgn:1002361",
          "tgn:7012149",
          "tgn:7007828",
          "tgn:7029392"
        ],
        "placetype": [
          "aat:300008798"
        ],
        "id": 2145568,
        "name:xx": "Baldwin Hill"
      }
    },
    {
      "geometry": {
        "type": "Point",
        "coordinates": [
          -84.8667,
          33.8333
        ]
      },
      "type": "Feature",
      "properties": {
        "hierarchy": [
          "tgn:2145569",
          "tgn:1000001",
          "tgn:7012149",
          "tgn:2000401",
          "tgn:7007248",
          "tgn:7029392"
        ],
        "placetype": [
          "aat:300008347"
        ],
        "id": 2145569,
        "name:xx": "Baldwin Hills"
      }
    }
  ]
}
