{
  "type": "FeatureCollection",
  "features": [
    {
      "geometry": {
        "type": "Point",
        "coordinates": [
          14.25,
          47.5833
        ]
      },
      "type": "Feature",
      "properties": {
        "hierarchy": [
          "tgn:1025791",
          "tgn:7003028",
          "tgn:1000003",
          "tgn:1000062",
          "tgn:7029392"
        ],
        "placetype": [
          "aat:300008347"
        ],
        "id": 1025791,
        "name:xx": "Liezen"
      }
    },
    {
      "geometry": {
        "type": "Point",
        "coordinates": [
          15.2,
          46.9833
        ]
      },
      "type": "Feature",
      "properties": {
        "hierarchy": [
          "tgn:1025792",
          "tgn:7003028",
          "tgn:1000003",
          "tgn:1000062",
          "tgn:7029392"
        ],
        "placetype": [
          "aat:300008347"
        ],
        "id": 1025792,
        "name:xx": "Ligist"
      }
    },
    {
      "geometry": {
        "type": "Point",
        "coordinates": [
          15.0667,
          48.9667
        ]
      },
      "type": "Feature",
      "properties": {
        "hierarchy": [
          "tgn:1025795",
          "tgn:7003025",
          "tgn:1000003",
          "tgn:1000062",
          "tgn:7029392"
        ],
        "placetype": [
          "aat:300008347"
        ],
        "id": 1025795,
        "name:xx": "Litschau"
      }
    },
    {
      "geometry": {
        "type": "Point",
        "coordinates": [
          16.4167,
          47.4
        ]
      },
      "type": "Feature",
      "properties": {
        "hierarchy": [
          "tgn:1025796",
          "tgn:7003023",
          "tgn:1000003",
          "tgn:1000062",
          "tgn:7029392"
        ],
        "placetype": [
          "aat:300008347"
        ],
        "id": 1025796,
        "name:xx": "Lockenhaus"
      }
    },
    {
      "geometry": {
        "type": "Point",
        "coordinates": [
          12.7,
          47.6
        ]
      },
      "type": "Feature",
      "properties": {
        "hierarchy": [
          "tgn:1025797",
          "tgn:7003027",
          "tgn:1000003",
          "tgn:1000062",
          "tgn:7029392"
        ],
        "placetype": [
          "aat:300008347"
        ],
        "id": 1025797,
        "name:xx": "Lofer"
      }
    },
    {
      "geometry": {
        "type": "Point",
        "coordinates": [
          13.3833,
          48.1333
        ]
      },
      "type": "Feature",
      "properties": {
        "hierarchy": [
          "tgn:1025798",
          "tgn:7003026",
          "tgn:1000003",
          "tgn:1000062",
          "tgn:7029392"
        ],
        "placetype": [
          "aat:300008347"
        ],
        "id": 1025798,
        "name:xx": "Lohnsburg"
      }
    },
    {
      "geometry": {
        "type": "Point",
        "coordinates": [
          15.4167,
          48.2167
        ]
      },
      "type": "Feature",
      "properties": {
        "hierarchy": [
          "tgn:1025799",
          "tgn:7003025",
          "tgn:1000003",
          "tgn:1000062",
          "tgn:7029392"
        ],
        "placetype": [
          "aat:300008347"
        ],
        "id": 1025799,
        "name:xx": "Loosdorf"
      }
    }
  ]
}
