{
  "geometry": {
    "type": "Point",
    "coordinates": [
      -97.7333,
      32.3667
    ]
  },
  "type": "Feature",
  "properties": {
    "hierarchy": [
      "tgn:2105894",
      "tgn:1000001",
      "tgn:7012149",
      "tgn:1002484",
      "tgn:7007826",
      "tgn:7029392"
    ],
    "placetype": [
      "aat:300008347",
      "aat:300387210"
    ],
    "id": 2105894,
    "name:xx": "Mambrino"
  }
}
