{
  "geometry": {
    "type": "Point",
    "coordinates": [
      -91.7667,
      36.3167
    ]
  },
  "type": "Feature",
  "properties": {
    "hierarchy": [
      "tgn:2591672",
      "tgn:1000001",
      "tgn:7016172",
      "tgn:7012149",
      "tgn:2000129",
      "tgn:7029392"
    ],
    "placetype": [
      "aat:300008706"
    ],
    "id": 2591672,
    "name:xx": "Pond Creek"
  }
}
