{
  "geometry": {
    "type": "Point",
    "coordinates": [
      -68.8167,
      44.55
    ]
  },
  "type": "Feature",
  "properties": {
    "hierarchy": [
      "tgn:2319849",
      "tgn:1000001",
      "tgn:7012149",
      "tgn:2000931",
      "tgn:7007515",
      "tgn:7029392"
    ],
    "placetype": [
      "aat:300008798"
    ],
    "id": 2319849,
    "name:xx": "Eustis Mountain"
  }
}
