{
  "geometry": {
    "type": "Point",
    "coordinates": [
      5.05,
      52.083333
    ]
  },
  "type": "Feature",
  "properties": {
    "hierarchy": [
      "tgn:7271141",
      "tgn:1000003",
      "tgn:7003627",
      "tgn:7016845",
      "tgn:7029392"
    ],
    "placetype": [
      "aat:300008347"
    ],
    "name:nl": "Stadsdam",
    "id": 7271141
  }
}
