{
  "geometry": {
    "type": "Point",
    "coordinates": [
      125.8333,
      50.7833
    ]
  },
  "type": "Feature",
  "properties": {
    "hierarchy": [
      "tgn:1074074",
      "tgn:1000004",
      "tgn:1001290",
      "tgn:1000111",
      "tgn:7029392"
    ],
    "placetype": [
      "aat:300008347"
    ],
    "id": 1074074,
    "name:xx": "Zhongyaozhan"
  }
}
