{
  "geometry": {
    "type": "Point",
    "coordinates": [
      7.533333,
      51.05
    ]
  },
  "type": "Feature",
  "properties": {
    "hierarchy": [
      "tgn:7144722",
      "tgn:1000003",
      "tgn:7003677",
      "tgn:7000084",
      "tgn:7029392"
    ],
    "placetype": [
      "aat:300000206"
    ],
    "id": 7144722,
    "name:xx": "Kotthauserhöhe"
  }
}
