{
  "geometry": {
    "type": "Point",
    "coordinates": [
      -80.5667,
      40.0167
    ]
  },
  "type": "Feature",
  "properties": {
    "hierarchy": [
      "tgn:2364552",
      "tgn:1000001",
      "tgn:7012149",
      "tgn:2002276",
      "tgn:7013961",
      "tgn:7029392"
    ],
    "placetype": [
      "aat:300006191"
    ],
    "id": 2364552,
    "name:xx": "Green Valley Lakes"
  }
}
