{
  "geometry": {
    "type": "Point",
    "coordinates": [
      -90.6167,
      44.3333
    ]
  },
  "type": "Feature",
  "properties": {
    "hierarchy": [
      "tgn:2726679",
      "tgn:1000001",
      "tgn:7012149",
      "tgn:2002328",
      "tgn:7007922",
      "tgn:7029392"
    ],
    "placetype": [
      "aat:300006191"
    ],
    "id": 2726679,
    "name:xx": "Town Line Flowage"
  }
}
