{
  "type": "FeatureCollection",
  "features": [
    {
      "geometry": {
        "type": "Point",
        "coordinates": [
          -6.033333,
          37.366667
        ]
      },
      "type": "Feature",
      "properties": {
        "hierarchy": [
          "tgn:7322540",
          "tgn:7002758",
          "tgn:7002841",
          "tgn:1000003",
          "tgn:1000095",
          "tgn:7029392"
        ],
        "placetype": [
          "aat:300008347"
        ],
        "id": 7322540,
        "name:xx": "San Juan de Aznalfarache"
      }
    },
    {
      "geometry": {
        "type": "Point",
        "coordinates": [
          -0.433333,
          38.4
        ]
      },
      "type": "Feature",
      "properties": {
        "hierarchy": [
          "tgn:7322541",
          "tgn:7002804",
          "tgn:1000003",
          "tgn:7002793",
          "tgn:1000095",
          "tgn:7029392"
        ],
        "placetype": [
          "aat:300008347"
        ],
        "id": 7322541,
        "name:xx": "San Juan de Alicante"
      }
    },
    {
      "geometry": {
        "type": "Point",
        "coordinates": [
          -4.833333,
          40.833333
        ]
      },
      "type": "Feature",
      "properties": {
        "hierarchy": [
          "tgn:7322542",
          "tgn:7002806",
          "tgn:7001158",
          "tgn:1000003",
          "tgn:1000095",
          "tgn:7029392"
        ],
        "placetype": [
          "aat:300008347"
        ],
        "id": 7322542,
        "name:xx": "San Juan Bautista"
      }
    },
    {
      "geometry": {
        "type": "Point",
        "coordinates": [
          1.7,
          41.216667
        ]
      },
      "type": "Feature",
      "properties": {
        "hierarchy": [
          "tgn:7322544",
          "tgn:7002808",
          "tgn:7030216",
          "tgn:1000003",
          "tgn:1000095",
          "tgn:7029392"
        ],
        "placetype": [
          "aat:300266554",
          "aat:300008699"
        ],
        "id": 7322544,
        "name:xx": "San Juan, Torrente de"
      }
    },
    {
      "geometry": {
        "type": "Point",
        "coordinates": [
          -1.883333,
          38.733333
        ]
      },
      "type": "Feature",
      "properties": {
        "hierarchy": [
          "tgn:7322545",
          "tgn:7002803",
          "tgn:1001647",
          "tgn:1000003",
          "tgn:1000095",
          "tgn:7029392"
        ],
        "placetype": [
          "aat:300266640"
        ],
        "id": 7322545,
        "name:xx": "San Juan, Sierra de"
      }
    },
    {
      "geometry": {
        "type": "Point",
        "coordinates": [
          1.212466,
          42.201986
        ]
      },
      "type": "Feature",
      "properties": {
        "hierarchy": [
          "tgn:7322546",
          "tgn:7008912",
          "tgn:7030216",
          "tgn:1000003",
          "tgn:1000095",
          "tgn:7029392"
        ],
        "placetype": [
          "aat:300008795"
        ],
        "id": 7322546,
        "name:xx": "San Juan, Sierra de"
      }
    },
    {
      "geometry": {
        "type": "Point",
        "coordinates": [
          -4.1,
          37.533333
        ]
      },
      "type": "Feature",
      "properties": {
        "hierarchy": [
          "tgn:7322547",
          "tgn:7002758",
          "tgn:7002817",
          "tgn:1000003",
          "tgn:1000095",
          "tgn:7029392"
        ],
        "placetype": [
          "aat:300008699"
        ],
        "id": 7322547,
        "name:xx": "San Juan, Río de"
      }
    },
    {
      "geometry": {
        "type": "Point",
        "coordinates": [
          -3.85,
          41.3
        ]
      },
      "type": "Feature",
      "properties": {
        "hierarchy": [
          "tgn:7322548",
          "tgn:7002839",
          "tgn:7001158",
          "tgn:1000003",
          "tgn:1000095",
          "tgn:7029392"
        ],
        "placetype": [
          "aat:300008699"
        ],
        "id": 7322548,
        "name:xx": "San Juan, Río"
      }
    },
    {
      "geometry": {
        "type": "Point",
        "coordinates": [
          -16.8,
          28.166667
        ]
      },
      "type": "Feature",
      "properties": {
        "hierarchy": [
          "tgn:7322549",
          "tgn:7002836",
          "tgn:7016622",
          "tgn:1000003",
          "tgn:1000095",
          "tgn:7029392"
        ],
        "placetype": [
          "aat:300386846"
        ],
        "id": 7322549,
        "name:xx": "San Juan, Punta de"
      }
    }
  ]
}
