{
  "geometry": {
    "type": "Point",
    "coordinates": [
      -107.45,
      38.7833
    ]
  },
  "type": "Feature",
  "properties": {
    "hierarchy": [
      "tgn:2735719",
      "tgn:1000001",
      "tgn:7012149",
      "tgn:2000217",
      "tgn:7007158",
      "tgn:7029392"
    ],
    "placetype": [
      "aat:300008798"
    ],
    "id": 2735719,
    "name:xx": "Twin Knobs"
  }
}
