{
  "geometry": {
    "type": "Point",
    "coordinates": [
      -75.8333,
      37.6333
    ]
  },
  "type": "Feature",
  "properties": {
    "hierarchy": [
      "tgn:2370848",
      "tgn:1002132",
      "tgn:1000001",
      "tgn:7012149",
      "tgn:7007919",
      "tgn:7029392"
    ],
    "placetype": [
      "aat:300008850"
    ],
    "id": 2370848,
    "name:xx": "Hacks Neck"
  }
}
