{
  "geometry": {
    "type": "Point",
    "coordinates": [
      -106.3667,
      33.6333
    ]
  },
  "type": "Feature",
  "properties": {
    "hierarchy": [
      "tgn:2561486",
      "tgn:1000001",
      "tgn:7012149",
      "tgn:2001456",
      "tgn:7007566",
      "tgn:7029392"
    ],
    "placetype": [
      "aat:300008798"
    ],
    "id": 2561486,
    "name:xx": "Oscura Peak"
  }
}
