{
  "geometry": {
    "type": "Point",
    "coordinates": [
      121.553,
      24.9797
    ]
  },
  "type": "Feature",
  "properties": {
    "hierarchy": [
      "tgn:7472678",
      "tgn:1000004",
      "tgn:1000959",
      "tgn:1000141",
      "tgn:7029392"
    ],
    "placetype": [
      "aat:300007836"
    ],
    "id": 7472678,
    "name:xx": "Bao Qiao"
  }
}
