{
  "geometry": {
    "type": "Point",
    "coordinates": [
      -82.7833,
      29.8667
    ]
  },
  "type": "Feature",
  "properties": {
    "hierarchy": [
      "tgn:2282417",
      "tgn:1000001",
      "tgn:2000269",
      "tgn:7012149",
      "tgn:7007240",
      "tgn:7029392"
    ],
    "placetype": [
      "aat:300008680"
    ],
    "id": 2282417,
    "name:xx": "Deer Pond"
  }
}
