{
  "geometry": {
    "type": "Point",
    "coordinates": [
      -89.5667,
      32.4167
    ]
  },
  "type": "Feature",
  "properties": {
    "hierarchy": [
      "tgn:2660486",
      "tgn:1000001",
      "tgn:7012149",
      "tgn:2001147",
      "tgn:7007522",
      "tgn:7029392"
    ],
    "placetype": [
      "aat:300008706"
    ],
    "id": 2660486,
    "name:xx": "Shoesole Creek"
  }
}
