{
  "geometry": {
    "type": "Point",
    "coordinates": [
      -87.7833,
      34.05
    ]
  },
  "type": "Feature",
  "properties": {
    "hierarchy": [
      "tgn:1133741",
      "tgn:1000001",
      "tgn:7012149",
      "tgn:7029392"
    ],
    "placetype": [
      "aat:300008706"
    ],
    "id": 1133741,
    "name:xx": "Luxapallila Creek"
  }
}
