{
  "geometry": {
    "type": "Point",
    "coordinates": [
      -95.1667,
      35.8333
    ]
  },
  "type": "Feature",
  "properties": {
    "hierarchy": [
      "tgn:2336777",
      "tgn:1000001",
      "tgn:7012149",
      "tgn:7007707",
      "tgn:7029392"
    ],
    "placetype": [
      "aat:300008699"
    ],
    "id": 2336777,
    "name:xx": "Fourmile Branch"
  }
}
