{
  "geometry": {
    "type": "Point",
    "coordinates": [
      -80.2167,
      36.5333
    ]
  },
  "type": "Feature",
  "properties": {
    "hierarchy": [
      "tgn:2458946",
      "tgn:1000001",
      "tgn:7012149",
      "tgn:7029392"
    ],
    "placetype": [
      "aat:300008706"
    ],
    "id": 2458946,
    "name:xx": "Little Peters Creek"
  }
}
