{
  "geometry": {
    "type": "Point",
    "coordinates": [
      -71.45,
      41.4667
    ]
  },
  "type": "Feature",
  "properties": {
    "hierarchy": [
      "tgn:2094962",
      "tgn:1002996",
      "tgn:1000001",
      "tgn:7012149",
      "tgn:7007711",
      "tgn:7029392"
    ],
    "placetype": [
      "aat:300008347"
    ],
    "id": 2094962,
    "name:xx": "Indian Lake Shores"
  }
}
