{
  "type": "FeatureCollection",
  "features": [
    {
      "geometry": {
        "type": "Point",
        "coordinates": [
          -77.9333,
          38.3333
        ]
      },
      "type": "Feature",
      "properties": {
        "hierarchy": [
          "tgn:2625930",
          "tgn:1000001",
          "tgn:7012149",
          "tgn:7007919",
          "tgn:7029392"
        ],
        "placetype": [
          "aat:300008699"
        ],
        "id": 2625930,
        "name:xx": "Rocky Branch"
      }
    },
    {
      "geometry": {
        "type": "Point",
        "coordinates": [
          -77.2333,
          38.7167
        ]
      },
      "type": "Feature",
      "properties": {
        "hierarchy": [
          "tgn:2625931",
          "tgn:1000001",
          "tgn:7012149",
          "tgn:7014160",
          "tgn:7007919",
          "tgn:7029392"
        ],
        "placetype": [
          "aat:300008699"
        ],
        "id": 2625931,
        "name:xx": "Rocky Branch"
      }
    },
    {
      "geometry": {
        "type": "Point",
        "coordinates": [
          -77.6,
          38.7833
        ]
      },
      "type": "Feature",
      "properties": {
        "hierarchy": [
          "tgn:2625932",
          "tgn:1000001",
          "tgn:7012149",
          "tgn:7015778",
          "tgn:7007919",
          "tgn:7029392"
        ],
        "placetype": [
          "aat:300008699"
        ],
        "id": 2625932,
        "name:xx": "Rocky Branch"
      }
    },
    {
      "geometry": {
        "type": "Point",
        "coordinates": [
          -80.2667,
          36.6
        ]
      },
      "type": "Feature",
      "properties": {
        "hierarchy": [
          "tgn:2625933",
          "tgn:1000001",
          "tgn:7012149",
          "tgn:2002179",
          "tgn:7007919",
          "tgn:7029392"
        ],
        "placetype": [
          "aat:300008699"
        ],
        "id": 2625933,
        "name:xx": "Rocky Branch"
      }
    },
    {
      "geometry": {
        "type": "Point",
        "coordinates": [
          -79.3667,
          37.0333
        ]
      },
      "type": "Feature",
      "properties": {
        "hierarchy": [
          "tgn:2625934",
          "tgn:1000001",
          "tgn:7012149",
          "tgn:2002180",
          "tgn:7007919",
          "tgn:7029392"
        ],
        "placetype": [
          "aat:300008699"
        ],
        "id": 2625934,
        "name:xx": "Rocky Branch"
      }
    },
    {
      "geometry": {
        "type": "Point",
        "coordinates": [
          -79.6167,
          37.25
        ]
      },
      "type": "Feature",
      "properties": {
        "hierarchy": [
          "tgn:2625935",
          "tgn:1000001",
          "tgn:2002144",
          "tgn:7012149",
          "tgn:7007919",
          "tgn:7029392"
        ],
        "placetype": [
          "aat:300008699"
        ],
        "id": 2625935,
        "name:xx": "Rocky Branch"
      }
    },
    {
      "geometry": {
        "type": "Point",
        "coordinates": [
          -78.3167,
          38.6833
        ]
      },
      "type": "Feature",
      "properties": {
        "hierarchy": [
          "tgn:2625936",
          "tgn:1000001",
          "tgn:7012149",
          "tgn:2002178",
          "tgn:7007919",
          "tgn:7029392"
        ],
        "placetype": [
          "aat:300008699"
        ],
        "id": 2625936,
        "name:xx": "Rocky Branch"
      }
    },
    {
      "geometry": {
        "type": "Point",
        "coordinates": [
          -82.5667,
          36.7333
        ]
      },
      "type": "Feature",
      "properties": {
        "hierarchy": [
          "tgn:2625937",
          "tgn:1000001",
          "tgn:7012149",
          "tgn:2002189",
          "tgn:7007919",
          "tgn:7029392"
        ],
        "placetype": [
          "aat:300008699"
        ],
        "id": 2625937,
        "name:xx": "Rocky Branch"
      }
    },
    {
      "geometry": {
        "type": "Point",
        "coordinates": [
          -80.25,
          37.5167
        ]
      },
      "type": "Feature",
      "properties": {
        "hierarchy": [
          "tgn:2625938",
          "tgn:1000001",
          "tgn:7012149",
          "tgn:2002154",
          "tgn:7007919",
          "tgn:7029392"
        ],
        "placetype": [
          "aat:300008699"
        ],
        "id": 2625938,
        "name:xx": "Rocky Branch"
      }
    },
    {
      "geometry": {
        "type": "Point",
        "coordinates": [
          -77.5167,
          37.6167
        ]
      },
      "type": "Feature",
      "properties": {
        "hierarchy": [
          "tgn:2625939",
          "tgn:1000001",
          "tgn:7012149",
          "tgn:1002467",
          "tgn:7007919",
          "tgn:7029392"
        ],
        "placetype": [
          "aat:300008699"
        ],
        "id": 2625939,
        "name:xx": "Rocky Branch"
      }
    }
  ]
}
