{
  "geometry": {
    "type": "Point",
    "coordinates": [
      -93.1333,
      36.9167
    ]
  },
  "type": "Feature",
  "properties": {
    "hierarchy": [
      "tgn:2224713",
      "tgn:1000001",
      "tgn:2001185",
      "tgn:7012149",
      "tgn:7007523",
      "tgn:7029392"
    ],
    "placetype": [
      "aat:300008697"
    ],
    "id": 2224713,
    "name:xx": "Cash Spring"
  }
}
