{
  "geometry": {
    "type": "Point",
    "coordinates": [
      7.4333,
      47.2667
    ]
  },
  "type": "Feature",
  "properties": {
    "hierarchy": [
      "tgn:4003018",
      "tgn:7003742",
      "tgn:1000003",
      "tgn:7011731",
      "tgn:7029392"
    ],
    "placetype": [
      "aat:300008347"
    ],
    "id": 4003018,
    "name:xx": "Crémines"
  }
}
