{
  "geometry": {
    "type": "Point",
    "coordinates": [
      -90.1333,
      37.45
    ]
  },
  "type": "Feature",
  "properties": {
    "hierarchy": [
      "tgn:2767954",
      "tgn:1000001",
      "tgn:7012149",
      "tgn:7007523",
      "tgn:7029392"
    ],
    "placetype": [
      "aat:300008706"
    ],
    "id": 2767954,
    "name:xx": "Whitener Creek"
  }
}
