{
  "geometry": {
    "type": "Point",
    "coordinates": [
      -117.3167,
      33.1833
    ]
  },
  "type": "Feature",
  "properties": {
    "hierarchy": [
      "tgn:2326933",
      "tgn:1000001",
      "tgn:7012149",
      "tgn:7007157",
      "tgn:1002858",
      "tgn:7029392"
    ],
    "placetype": [
      "aat:300008798"
    ],
    "id": 2326933,
    "name:xx": "Fire Mountain"
  }
}
