{
  "type": "FeatureCollection",
  "features": [
    {
      "geometry": {
        "type": "Point",
        "coordinates": [
          -77.8333,
          35.9333
        ]
      },
      "type": "Feature",
      "properties": {
        "hierarchy": [
          "tgn:2338250",
          "tgn:1000001",
          "tgn:7012149",
          "tgn:2001522",
          "tgn:7007709",
          "tgn:7029392"
        ],
        "placetype": [
          "aat:300008347"
        ],
        "id": 2338250,
        "name:xx": "Fox Run"
      }
    },
    {
      "geometry": {
        "type": "Point",
        "coordinates": [
          -80.05,
          36.0833
        ]
      },
      "type": "Feature",
      "properties": {
        "hierarchy": [
          "tgn:2338251",
          "tgn:1000001",
          "tgn:7012149",
          "tgn:2001494",
          "tgn:7007709",
          "tgn:7029392"
        ],
        "placetype": [
          "aat:300008347"
        ],
        "id": 2338251,
        "name:xx": "Fox Run"
      }
    },
    {
      "geometry": {
        "type": "Point",
        "coordinates": [
          -80.75,
          35.1667
        ]
      },
      "type": "Feature",
      "properties": {
        "hierarchy": [
          "tgn:2338252",
          "tgn:1000001",
          "tgn:7012149",
          "tgn:7014021",
          "tgn:7007709",
          "tgn:7029392"
        ],
        "placetype": [
          "aat:300008347"
        ],
        "id": 2338252,
        "name:xx": "Fox Run"
      }
    },
    {
      "geometry": {
        "type": "Point",
        "coordinates": [
          -84.8167,
          39.2
        ]
      },
      "type": "Feature",
      "properties": {
        "hierarchy": [
          "tgn:2338253",
          "tgn:1000001",
          "tgn:7012149",
          "tgn:1002441",
          "tgn:7007706",
          "tgn:7029392"
        ],
        "placetype": [
          "aat:300008699"
        ],
        "id": 2338253,
        "name:xx": "Fox Run"
      }
    },
    {
      "geometry": {
        "type": "Point",
        "coordinates": [
          -81.9,
          39.8167
        ]
      },
      "type": "Feature",
      "properties": {
        "hierarchy": [
          "tgn:2338254",
          "tgn:1000001",
          "tgn:7012149",
          "tgn:1002701",
          "tgn:7007706",
          "tgn:7029392"
        ],
        "placetype": [
          "aat:300008699"
        ],
        "id": 2338254,
        "name:xx": "Fox Run"
      }
    },
    {
      "geometry": {
        "type": "Point",
        "coordinates": [
          -82.1,
          40.8667
        ]
      },
      "type": "Feature",
      "properties": {
        "hierarchy": [
          "tgn:2338255",
          "tgn:1000001",
          "tgn:7012149",
          "tgn:1003007",
          "tgn:7007706",
          "tgn:7029392"
        ],
        "placetype": [
          "aat:300008699"
        ],
        "id": 2338255,
        "name:xx": "Fox Run"
      }
    },
    {
      "geometry": {
        "type": "Point",
        "coordinates": [
          -81.7,
          40.8833
        ]
      },
      "type": "Feature",
      "properties": {
        "hierarchy": [
          "tgn:2338256",
          "tgn:1000001",
          "tgn:7012149",
          "tgn:7007706",
          "tgn:7029392"
        ],
        "placetype": [
          "aat:300008699"
        ],
        "id": 2338256,
        "name:xx": "Fox Run"
      }
    },
    {
      "geometry": {
        "type": "Point",
        "coordinates": [
          -76.85,
          40.0333
        ]
      },
      "type": "Feature",
      "properties": {
        "hierarchy": [
          "tgn:2338257",
          "tgn:1000001",
          "tgn:7012149",
          "tgn:1003047",
          "tgn:7007710",
          "tgn:7029392"
        ],
        "placetype": [
          "aat:300008699"
        ],
        "id": 2338257,
        "name:xx": "Fox Run"
      }
    },
    {
      "geometry": {
        "type": "Point",
        "coordinates": [
          -78.1833,
          40.55
        ]
      },
      "type": "Feature",
      "properties": {
        "hierarchy": [
          "tgn:2338258",
          "tgn:1000001",
          "tgn:7012149",
          "tgn:7007710",
          "tgn:7029392"
        ],
        "placetype": [
          "aat:300008699"
        ],
        "id": 2338258,
        "name:xx": "Fox Run"
      }
    },
    {
      "geometry": {
        "type": "Point",
        "coordinates": [
          -78.5,
          41.1333
        ]
      },
      "type": "Feature",
      "properties": {
        "hierarchy": [
          "tgn:2338259",
          "tgn:1000001",
          "tgn:1002278",
          "tgn:7012149",
          "tgn:7007710",
          "tgn:7029392"
        ],
        "placetype": [
          "aat:300008699"
        ],
        "id": 2338259,
        "name:xx": "Fox Run"
      }
    }
  ]
}
