{
  "geometry": {
    "type": "Point",
    "coordinates": [
      -77.3833,
      41.55
    ]
  },
  "type": "Feature",
  "properties": {
    "hierarchy": [
      "tgn:2648121",
      "tgn:1000001",
      "tgn:7012149",
      "tgn:1002945",
      "tgn:7007710",
      "tgn:7029392"
    ],
    "placetype": [
      "aat:300008699"
    ],
    "id": 2648121,
    "name:xx": "Schoolhouse Run"
  }
}
