{
  "geometry": {
    "type": "Point",
    "coordinates": [
      147.4167,
      -19.5333
    ]
  },
  "type": "Feature",
  "properties": {
    "hierarchy": [
      "tgn:1096148",
      "tgn:7000490",
      "tgn:1000006",
      "tgn:7001830",
      "tgn:7029392"
    ],
    "placetype": [
      "aat:300008347"
    ],
    "id": 1096148,
    "name:xx": "Ayr"
  }
}
