{
  "type": "FeatureCollection",
  "features": [
    {
      "geometry": {
        "type": "Point",
        "coordinates": [
          -90.5333,
          29.6833
        ]
      },
      "type": "Feature",
      "properties": {
        "hierarchy": [
          "tgn:2043410",
          "tgn:1000001",
          "tgn:7012149",
          "tgn:2000882",
          "tgn:7007256",
          "tgn:7029392"
        ],
        "placetype": [
          "aat:300008347"
        ],
        "id": 2043410,
        "name:xx": "Mathews"
      }
    },
    {
      "geometry": {
        "type": "Point",
        "coordinates": [
          -90.65,
          30.2833
        ]
      },
      "type": "Feature",
      "properties": {
        "hierarchy": [
          "tgn:2043411",
          "tgn:1000001",
          "tgn:7012149",
          "tgn:2000885",
          "tgn:7007256",
          "tgn:7029392"
        ],
        "placetype": [
          "aat:300008347"
        ],
        "id": 2043411,
        "name:xx": "Maurepas"
      }
    },
    {
      "geometry": {
        "type": "Point",
        "coordinates": [
          -92.1167,
          30.1
        ]
      },
      "type": "Feature",
      "properties": {
        "hierarchy": [
          "tgn:2043412",
          "tgn:1000001",
          "tgn:7012149",
          "tgn:2000910",
          "tgn:7007256",
          "tgn:7029392"
        ],
        "placetype": [
          "aat:300008347"
        ],
        "id": 2043412,
        "name:xx": "Maurice"
      }
    },
    {
      "geometry": {
        "type": "Point",
        "coordinates": [
          -92.4,
          30.3167
        ]
      },
      "type": "Feature",
      "properties": {
        "hierarchy": [
          "tgn:2043413",
          "tgn:2000854",
          "tgn:1000001",
          "tgn:7012149",
          "tgn:7007256",
          "tgn:7029392"
        ],
        "placetype": [
          "aat:300008347"
        ],
        "id": 2043413,
        "name:xx": "Maxie"
      }
    },
    {
      "geometry": {
        "type": "Point",
        "coordinates": [
          -91.1,
          30.3833
        ]
      },
      "type": "Feature",
      "properties": {
        "hierarchy": [
          "tgn:2043414",
          "tgn:1000001",
          "tgn:2000870",
          "tgn:7012149",
          "tgn:7007256",
          "tgn:7029392"
        ],
        "placetype": [
          "aat:300008347"
        ],
        "id": 2043414,
        "name:xx": "Hillside"
      }
    },
    {
      "geometry": {
        "type": "Point",
        "coordinates": [
          -91.85,
          31.4167
        ]
      },
      "type": "Feature",
      "properties": {
        "hierarchy": [
          "tgn:2043415",
          "tgn:1000001",
          "tgn:2000866",
          "tgn:7012149",
          "tgn:7007256",
          "tgn:7029392"
        ],
        "placetype": [
          "aat:300008347"
        ],
        "id": 2043415,
        "name:xx": "Mayna"
      }
    }
  ]
}
