{
  "geometry": {
    "type": "Point",
    "coordinates": [
      -77.0333,
      42.5333
    ]
  },
  "type": "Feature",
  "properties": {
    "hierarchy": [
      "tgn:2594166",
      "tgn:1000001",
      "tgn:7012149",
      "tgn:1003045",
      "tgn:7007568",
      "tgn:7029392"
    ],
    "placetype": [
      "aat:300008347"
    ],
    "id": 2594166,
    "name:xx": "Porter Corner"
  }
}
