{
  "geometry": {
    "type": "Point",
    "coordinates": [
      -74.6667,
      44.1333
    ]
  },
  "type": "Feature",
  "properties": {
    "hierarchy": [
      "tgn:2644594",
      "tgn:1000001",
      "tgn:7012149",
      "tgn:7016021",
      "tgn:7007568",
      "tgn:7029392"
    ],
    "placetype": [
      "aat:300008680"
    ],
    "id": 2644594,
    "name:xx": "Sardine Pond"
  }
}
