{
  "geometry": {
    "type": "Point",
    "coordinates": [
      -71.4333,
      42.55
    ]
  },
  "type": "Feature",
  "properties": {
    "hierarchy": [
      "tgn:2569151",
      "tgn:1000001",
      "tgn:1002665",
      "tgn:7012149",
      "tgn:7007517",
      "tgn:7029392"
    ],
    "placetype": [
      "aat:300008347"
    ],
    "id": 2569151,
    "name:xx": "Parkerville"
  }
}
