{
  "type": "FeatureCollection",
  "features": [
    {
      "geometry": {
        "type": "Point",
        "coordinates": [
          -92,
          38.4833
        ]
      },
      "type": "Feature",
      "properties": {
        "hierarchy": [
          "tgn:2450900",
          "tgn:1000001",
          "tgn:7012149",
          "tgn:1002755",
          "tgn:7007523",
          "tgn:7029392"
        ],
        "placetype": [
          "aat:300008347"
        ],
        "id": 2450900,
        "name:xx": "Lisletown"
      }
    },
    {
      "geometry": {
        "type": "Point",
        "coordinates": [
          -120.05,
          34.7333
        ]
      },
      "type": "Feature",
      "properties": {
        "hierarchy": [
          "tgn:2450901",
          "tgn:1000001",
          "tgn:7012149",
          "tgn:7007157",
          "tgn:1002867",
          "tgn:7029392"
        ],
        "placetype": [
          "aat:300008706"
        ],
        "id": 2450901,
        "name:xx": "Lisque Creek"
      }
    },
    {
      "geometry": {
        "type": "Point",
        "coordinates": [
          -93.6167,
          34.1667
        ]
      },
      "type": "Feature",
      "properties": {
        "hierarchy": [
          "tgn:2450902",
          "tgn:1000001",
          "tgn:7016172",
          "tgn:7012149",
          "tgn:2000159",
          "tgn:7029392"
        ],
        "placetype": [
          "aat:300008347"
        ],
        "id": 2450902,
        "name:xx": "Lissie"
      }
    },
    {
      "geometry": {
        "type": "Point",
        "coordinates": [
          -87.9833,
          36.45
        ]
      },
      "type": "Feature",
      "properties": {
        "hierarchy": [
          "tgn:2450903",
          "tgn:1000001",
          "tgn:7012149",
          "tgn:2001917",
          "tgn:7007825",
          "tgn:7029392"
        ],
        "placetype": [
          "aat:300008761"
        ],
        "id": 2450903,
        "name:xx": "Lissie Milton Hollow"
      }
    },
    {
      "geometry": {
        "type": "Point",
        "coordinates": [
          -83.3,
          32.25
        ]
      },
      "type": "Feature",
      "properties": {
        "hierarchy": [
          "tgn:2450904",
          "tgn:1000001",
          "tgn:7012149",
          "tgn:2000336",
          "tgn:7007248",
          "tgn:7029392"
        ],
        "placetype": [
          "aat:300006191"
        ],
        "id": 2450904,
        "name:xx": "Lissie, Lake"
      }
    },
    {
      "geometry": {
        "type": "Point",
        "coordinates": [
          -92.7,
          31.1333
        ]
      },
      "type": "Feature",
      "properties": {
        "hierarchy": [
          "tgn:2450905",
          "tgn:1000001",
          "tgn:7012149",
          "tgn:2000893",
          "tgn:7007256",
          "tgn:7029392"
        ],
        "placetype": [
          "aat:300008347"
        ],
        "id": 2450905,
        "name:xx": "Lisso"
      }
    },
    {
      "geometry": {
        "type": "Point",
        "coordinates": [
          -104.3667,
          43.8
        ]
      },
      "type": "Feature",
      "properties": {
        "hierarchy": [
          "tgn:2450906",
          "tgn:1000001",
          "tgn:7012149",
          "tgn:2002387",
          "tgn:7007923",
          "tgn:7029392"
        ],
        "placetype": [
          "aat:300006191"
        ],
        "id": 2450906,
        "name:xx": "Lissolo 9-364-3 Reservoir"
      }
    },
    {
      "geometry": {
        "type": "Point",
        "coordinates": [
          -119.1167,
          36.2667
        ]
      },
      "type": "Feature",
      "properties": {
        "hierarchy": [
          "tgn:2450907",
          "tgn:1000001",
          "tgn:7012149",
          "tgn:7007157",
          "tgn:1002956",
          "tgn:7029392"
        ],
        "placetype": [
          "aat:300008347"
        ],
        "id": 2450907,
        "name:xx": "List"
      }
    },
    {
      "geometry": {
        "type": "Point",
        "coordinates": [
          -83.7167,
          43.3
        ]
      },
      "type": "Feature",
      "properties": {
        "hierarchy": [
          "tgn:2450908",
          "tgn:1000001",
          "tgn:7012149",
          "tgn:2000992",
          "tgn:7007520",
          "tgn:7029392"
        ],
        "placetype": [
          "aat:300006075"
        ],
        "id": 2450908,
        "name:xx": "List Drain"
      }
    },
    {
      "geometry": {
        "type": "Point",
        "coordinates": [
          -86,
          44.1333
        ]
      },
      "type": "Feature",
      "properties": {
        "hierarchy": [
          "tgn:2450909",
          "tgn:1000001",
          "tgn:7012149",
          "tgn:2000970",
          "tgn:7007520",
          "tgn:7029392"
        ],
        "placetype": [
          "aat:300008680"
        ],
        "id": 2450909,
        "name:xx": "List Lake"
      }
    }
  ]
}
