{
  "geometry": {
    "type": "Point",
    "coordinates": [
      -86.1167,
      39.85
    ]
  },
  "type": "Feature",
  "properties": {
    "hierarchy": [
      "tgn:2142503",
      "tgn:1000001",
      "tgn:7012149",
      "tgn:1002633",
      "tgn:7007252",
      "tgn:7029392"
    ],
    "placetype": [
      "aat:300008905"
    ],
    "id": 2142503,
    "name:xx": "Bacon Swamp"
  }
}
