{
  "geometry": {
    "type": "Point",
    "coordinates": [
      -86.3167,
      34.0167
    ]
  },
  "type": "Feature",
  "properties": {
    "hierarchy": [
      "tgn:2002459",
      "tgn:7002659",
      "tgn:1000001",
      "tgn:7012149",
      "tgn:2000027",
      "tgn:7029392"
    ],
    "placetype": [
      "aat:300008347"
    ],
    "id": 2002459,
    "name:xx": "Altoona"
  }
}
