{
  "geometry": {
    "type": "Point",
    "coordinates": [
      -88.7667,
      33.2667
    ]
  },
  "type": "Feature",
  "properties": {
    "hierarchy": [
      "tgn:2183449",
      "tgn:1000001",
      "tgn:7012149",
      "tgn:2001137",
      "tgn:7007522",
      "tgn:7029392"
    ],
    "placetype": [
      "aat:300006191"
    ],
    "id": 2183449,
    "name:xx": "Bluff Lake"
  }
}
