{
  "type": "FeatureCollection",
  "features": [
    {
      "geometry": {
        "type": "Point",
        "coordinates": [
          6.283333,
          52.25
        ]
      },
      "type": "Feature",
      "properties": {
        "hierarchy": [
          "tgn:7257981",
          "tgn:1000003",
          "tgn:7003626",
          "tgn:7016845",
          "tgn:7029392"
        ],
        "placetype": [
          "aat:300008347"
        ],
        "name:nl": "Bathmen",
        "id": 7257981
      }
    },
    {
      "geometry": {
        "type": "Point",
        "coordinates": [
          4.183333,
          51.4
        ]
      },
      "type": "Feature",
      "properties": {
        "hierarchy": [
          "tgn:7257982",
          "tgn:1000003",
          "tgn:7003635",
          "tgn:7016845",
          "tgn:7029392"
        ],
        "placetype": [
          "aat:300387026"
        ],
        "name:nl": "Bath, Nauw van",
        "id": 7257982
      }
    },
    {
      "geometry": {
        "type": "Point",
        "coordinates": [
          4.216667,
          51.4
        ]
      },
      "type": "Feature",
      "properties": {
        "hierarchy": [
          "tgn:7257983",
          "tgn:1000003",
          "tgn:7003635",
          "tgn:7016845",
          "tgn:7029392"
        ],
        "placetype": [
          "aat:300008347"
        ],
        "name:nl": "Bath",
        "id": 7257983
      }
    },
    {
      "geometry": {
        "type": "Point",
        "coordinates": [
          5.4,
          51.5
        ]
      },
      "type": "Feature",
      "properties": {
        "hierarchy": [
          "tgn:7257986",
          "tgn:1000003",
          "tgn:7003624",
          "tgn:7016845",
          "tgn:7029392"
        ],
        "placetype": [
          "aat:300008347"
        ],
        "name:nl": "Batadorp",
        "id": 7257986
      }
    },
    {
      "geometry": {
        "type": "Point",
        "coordinates": [
          6.033333,
          52.816667
        ]
      },
      "type": "Feature",
      "properties": {
        "hierarchy": [
          "tgn:7257987",
          "tgn:1000003",
          "tgn:7003626",
          "tgn:7016845",
          "tgn:7029392"
        ],
        "placetype": [
          "aat:300008347"
        ],
        "name:nl": "Basserveld",
        "id": 7257987
      }
    },
    {
      "geometry": {
        "type": "Point",
        "coordinates": [
          6.033333,
          52.8
        ]
      },
      "type": "Feature",
      "properties": {
        "hierarchy": [
          "tgn:7257988",
          "tgn:1000003",
          "tgn:7003626",
          "tgn:7016845",
          "tgn:7029392"
        ],
        "placetype": [
          "aat:300008347"
        ],
        "name:nl": "Basse",
        "id": 7257988
      }
    },
    {
      "geometry": {
        "type": "Point",
        "coordinates": [
          6.183333,
          52.25
        ]
      },
      "type": "Feature",
      "properties": {
        "hierarchy": [
          "tgn:7257989",
          "tgn:1000003",
          "tgn:7003626",
          "tgn:7016845",
          "tgn:7029392"
        ],
        "placetype": [
          "aat:300006075"
        ],
        "name:nl": "Basiskanaal",
        "id": 7257989
      }
    }
  ]
}
