{
  "geometry": {
    "type": "Point",
    "coordinates": [
      65.7167,
      26.6333
    ]
  },
  "type": "Feature",
  "properties": {
    "hierarchy": [
      "tgn:1083750",
      "tgn:7000360",
      "tgn:1000004",
      "tgn:1000133",
      "tgn:7029392"
    ],
    "placetype": [
      "aat:300008347"
    ],
    "id": 1083750,
    "name:xx": "Rungāni"
  }
}
