{
  "geometry": {
    "type": "Point",
    "coordinates": [
      118.3333,
      49.1667
    ]
  },
  "type": "Feature",
  "properties": {
    "hierarchy": [
      "tgn:1124526",
      "tgn:1000004",
      "tgn:7001838",
      "tgn:1000111",
      "tgn:7029392"
    ],
    "placetype": [
      "aat:300008707"
    ],
    "id": 1124526,
    "name:xx": "Hailar He"
  }
}
