{
  "geometry": {
    "type": "Point",
    "coordinates": [
      105.1333,
      29.2333
    ]
  },
  "type": "Feature",
  "properties": {
    "hierarchy": [
      "tgn:1067402",
      "tgn:1000004",
      "tgn:7002087",
      "tgn:1000111",
      "tgn:7029392"
    ],
    "placetype": [
      "aat:300008347"
    ],
    "id": 1067402,
    "name:xx": "Daisi"
  }
}
