{
  "geometry": {
    "type": "Point",
    "coordinates": [
      73.028579,
      24.81961
    ]
  },
  "type": "Feature",
  "properties": {
    "hierarchy": [
      "tgn:7580200",
      "tgn:1000004",
      "tgn:7000198",
      "tgn:7016788",
      "tgn:7029392"
    ],
    "placetype": [
      "aat:300008347"
    ],
    "name:en": "Jhāroli",
    "id": 7580200
  }
}
