{
  "geometry": {
    "type": "Point",
    "coordinates": [
      17.5667,
      11.3167
    ]
  },
  "type": "Feature",
  "properties": {
    "hierarchy": [
      "tgn:1088573",
      "tgn:7001242",
      "tgn:1000979",
      "tgn:1000156",
      "tgn:7029392"
    ],
    "placetype": [
      "aat:300008347"
    ],
    "id": 1088573,
    "name:xx": "Séssé"
  }
}
