{
  "type": "FeatureCollection",
  "features": [
    {
      "geometry": {
        "type": "Point",
        "coordinates": [
          1.033333,
          52.7
        ]
      },
      "type": "Feature",
      "properties": {
        "hierarchy": [
          "tgn:4003610",
          "tgn:7002445",
          "tgn:1000003",
          "tgn:7008160",
          "tgn:7008591",
          "tgn:7029392"
        ],
        "placetype": [
          "aat:300008347",
          "aat:300008372"
        ],
        "id": 4003610,
        "name:xx": "Elsing"
      }
    },
    {
      "geometry": {
        "type": "Point",
        "coordinates": [
          0.683333,
          52.383333
        ]
      },
      "type": "Feature",
      "properties": {
        "hierarchy": [
          "tgn:4003614",
          "tgn:7002445",
          "tgn:1000003",
          "tgn:7008185",
          "tgn:7008591",
          "tgn:7029392"
        ],
        "placetype": [
          "aat:300008347"
        ],
        "name:en": "Elveden",
        "id": 4003614
      }
    },
    {
      "geometry": {
        "type": "Point",
        "coordinates": [
          -5.35,
          43.516667
        ]
      },
      "type": "Feature",
      "properties": {
        "hierarchy": [
          "tgn:4003615",
          "tgn:7007088",
          "tgn:1000003",
          "tgn:7009604",
          "tgn:1000095",
          "tgn:7029392"
        ],
        "placetype": [
          "aat:300008347"
        ],
        "id": 4003615,
        "name:xx": "Elvillar"
      }
    }
  ]
}
