{
  "geometry": {
    "type": "Point",
    "coordinates": [
      92.3833,
      53.25
    ]
  },
  "type": "Feature",
  "properties": {
    "hierarchy": [
      "tgn:1054721",
      "tgn:1000004",
      "tgn:1003314",
      "tgn:7018214",
      "tgn:7002435",
      "tgn:7029392"
    ],
    "placetype": [
      "aat:300008347"
    ],
    "id": 1054721,
    "name:xx": "Yermakovskoye"
  }
}
