{
  "geometry": {
    "type": "Point",
    "coordinates": [
      -86.9833,
      49.7333
    ]
  },
  "type": "Feature",
  "properties": {
    "hierarchy": [
      "tgn:1014784",
      "tgn:7005685",
      "tgn:1000001",
      "tgn:7013154",
      "tgn:7029392"
    ],
    "placetype": [
      "aat:300008347"
    ],
    "id": 1014784,
    "name:xx": "Geraldton"
  }
}
