{
  "type": "FeatureCollection",
  "features": [
    {
      "geometry": {
        "type": "Point",
        "coordinates": [
          -4,
          57.5
        ]
      },
      "type": "Feature",
      "properties": {
        "hierarchy": [
          "tgn:7452870",
          "tgn:7002444",
          "tgn:1000003",
          "tgn:7008082",
          "tgn:7008591",
          "tgn:7029392"
        ],
        "placetype": [
          "aat:300004792"
        ],
        "name:en": "Cantray House",
        "id": 7452870
      }
    },
    {
      "geometry": {
        "type": "Point",
        "coordinates": [
          -3.116667,
          58.8
        ]
      },
      "type": "Feature",
      "properties": {
        "hierarchy": [
          "tgn:7452873",
          "tgn:7002444",
          "tgn:1000003",
          "tgn:7009907",
          "tgn:7008591",
          "tgn:7029392"
        ],
        "placetype": [
          "aat:300266558"
        ],
        "name:en": "Cantick Sound",
        "id": 7452873
      }
    },
    {
      "geometry": {
        "type": "Point",
        "coordinates": [
          -3.133333,
          58.783333
        ]
      },
      "type": "Feature",
      "properties": {
        "hierarchy": [
          "tgn:7452874",
          "tgn:7002444",
          "tgn:1000003",
          "tgn:7009907",
          "tgn:7008591",
          "tgn:7029392"
        ],
        "placetype": [
          "aat:300008850"
        ],
        "name:en": "Cantick Head",
        "id": 7452874
      }
    },
    {
      "geometry": {
        "type": "Point",
        "coordinates": [
          0.866667,
          51.45
        ]
      },
      "type": "Feature",
      "properties": {
        "hierarchy": [
          "tgn:7452876",
          "tgn:7002445",
          "tgn:1000003",
          "tgn:7008153",
          "tgn:7008591",
          "tgn:7029392"
        ],
        "placetype": [
          "aat:300387036"
        ],
        "name:en": "Cant, The",
        "id": 7452876
      }
    },
    {
      "geometry": {
        "type": "Point",
        "coordinates": [
          -0.082126,
          51.509449
        ]
      },
      "type": "Feature",
      "properties": {
        "hierarchy": [
          "tgn:7452879",
          "tgn:7002445",
          "tgn:7011781",
          "tgn:1000003",
          "tgn:7008136",
          "tgn:7008591",
          "tgn:7029392"
        ],
        "placetype": [
          "aat:300007783"
        ],
        "name:en": "Cannon Street Station",
        "id": 7452879
      }
    }
  ]
}
