{
  "geometry": {
    "type": "Point",
    "coordinates": [
      -84.65,
      34.1833
    ]
  },
  "type": "Feature",
  "properties": {
    "hierarchy": [
      "tgn:2242594",
      "tgn:1000001",
      "tgn:2000299",
      "tgn:7012149",
      "tgn:7007248",
      "tgn:7029392"
    ],
    "placetype": [
      "aat:300008706"
    ],
    "id": 2242594,
    "name:xx": "Clear Creek"
  }
}
