{
  "geometry": {
    "type": "Point",
    "coordinates": [
      -86.6333,
      35.0167
    ]
  },
  "type": "Feature",
  "properties": {
    "hierarchy": [
      "tgn:2768039",
      "tgn:1000001",
      "tgn:7012149",
      "tgn:2001888",
      "tgn:7007825",
      "tgn:7029392"
    ],
    "placetype": [
      "aat:300008905"
    ],
    "id": 2768039,
    "name:xx": "Whiteoak Swamp"
  }
}
