{
  "geometry": {
    "type": "Point",
    "coordinates": [
      -82.4833,
      29.9833
    ]
  },
  "type": "Feature",
  "properties": {
    "hierarchy": [
      "tgn:2198713",
      "tgn:1000001",
      "tgn:7012149",
      "tgn:2000288",
      "tgn:7007240",
      "tgn:7029392"
    ],
    "placetype": [
      "aat:300008347"
    ],
    "id": 2198713,
    "name:xx": "Browns Still"
  }
}
