{
  "geometry": {
    "type": "Point",
    "coordinates": [
      -55.25,
      -34.85
    ]
  },
  "type": "Feature",
  "properties": {
    "hierarchy": [
      "tgn:1024951",
      "tgn:7002649",
      "tgn:1000002",
      "tgn:1000058",
      "tgn:7029392"
    ],
    "placetype": [
      "aat:300008347"
    ],
    "id": 1024951,
    "name:xx": "Piríápolis"
  }
}
