{
  "geometry": {
    "type": "Point",
    "coordinates": [
      -80.8833,
      37.65
    ]
  },
  "type": "Feature",
  "properties": {
    "hierarchy": [
      "tgn:2210434",
      "tgn:1000001",
      "tgn:7012149",
      "tgn:2002294",
      "tgn:7013961",
      "tgn:7029392"
    ],
    "placetype": [
      "aat:300008791"
    ],
    "id": 2210434,
    "name:xx": "Bushes Island"
  }
}
