{
  "type": "FeatureCollection",
  "features": [
    {
      "geometry": {
        "type": "Point",
        "coordinates": [
          10.466667,
          53.233333
        ]
      },
      "type": "Feature",
      "properties": {
        "hierarchy": [
          "tgn:7177630",
          "tgn:1000003",
          "tgn:7003676",
          "tgn:7000084",
          "tgn:7029392"
        ],
        "placetype": [
          "aat:300008347"
        ],
        "id": 7177630,
        "name:xx": "Hagen"
      }
    },
    {
      "geometry": {
        "type": "Point",
        "coordinates": [
          10.733333,
          53.066667
        ]
      },
      "type": "Feature",
      "properties": {
        "hierarchy": [
          "tgn:7177631",
          "tgn:1000003",
          "tgn:7003676",
          "tgn:7000084",
          "tgn:7029392"
        ],
        "placetype": [
          "aat:300008347"
        ],
        "id": 7177631,
        "name:xx": "Hagen"
      }
    },
    {
      "geometry": {
        "type": "Point",
        "coordinates": [
          8.833333,
          53
        ]
      },
      "type": "Feature",
      "properties": {
        "hierarchy": [
          "tgn:7177632",
          "tgn:1000003",
          "tgn:7003676",
          "tgn:7000084",
          "tgn:7029392"
        ],
        "placetype": [
          "aat:300008347"
        ],
        "id": 7177632,
        "name:xx": "Hagen"
      }
    },
    {
      "geometry": {
        "type": "Point",
        "coordinates": [
          9.966667,
          52.833333
        ]
      },
      "type": "Feature",
      "properties": {
        "hierarchy": [
          "tgn:7177633",
          "tgn:1000003",
          "tgn:7003676",
          "tgn:7000084",
          "tgn:7029392"
        ],
        "placetype": [
          "aat:300008347"
        ],
        "id": 7177633,
        "name:xx": "Hagen"
      }
    },
    {
      "geometry": {
        "type": "Point",
        "coordinates": [
          10.45,
          52.766667
        ]
      },
      "type": "Feature",
      "properties": {
        "hierarchy": [
          "tgn:7177634",
          "tgn:1000003",
          "tgn:7003676",
          "tgn:7000084",
          "tgn:7029392"
        ],
        "placetype": [
          "aat:300008347"
        ],
        "id": 7177634,
        "name:xx": "Hagen"
      }
    },
    {
      "geometry": {
        "type": "Point",
        "coordinates": [
          11.166667,
          52.75
        ]
      },
      "type": "Feature",
      "properties": {
        "hierarchy": [
          "tgn:7177635",
          "tgn:1000003",
          "tgn:7003687",
          "tgn:7000084",
          "tgn:7029392"
        ],
        "placetype": [
          "aat:300008347"
        ],
        "id": 7177635,
        "name:xx": "Hagen"
      }
    },
    {
      "geometry": {
        "type": "Point",
        "coordinates": [
          8.283333,
          52.7
        ]
      },
      "type": "Feature",
      "properties": {
        "hierarchy": [
          "tgn:7177636",
          "tgn:1000003",
          "tgn:7003676",
          "tgn:7000084",
          "tgn:7029392"
        ],
        "placetype": [
          "aat:300008347"
        ],
        "id": 7177636,
        "name:xx": "Hagen"
      }
    },
    {
      "geometry": {
        "type": "Point",
        "coordinates": [
          10.733333,
          52.683333
        ]
      },
      "type": "Feature",
      "properties": {
        "hierarchy": [
          "tgn:7177637",
          "tgn:1000003",
          "tgn:7003676",
          "tgn:7000084",
          "tgn:7029392"
        ],
        "placetype": [
          "aat:300008347"
        ],
        "id": 7177637,
        "name:xx": "Hagen"
      }
    },
    {
      "geometry": {
        "type": "Point",
        "coordinates": [
          9.083333,
          52.483333
        ]
      },
      "type": "Feature",
      "properties": {
        "hierarchy": [
          "tgn:7177639",
          "tgn:1000003",
          "tgn:7003676",
          "tgn:7000084",
          "tgn:7029392"
        ],
        "placetype": [
          "aat:300008347"
        ],
        "id": 7177639,
        "name:xx": "Hagen"
      }
    }
  ]
}
