{
  "type": "FeatureCollection",
  "features": [
    {
      "geometry": {
        "type": "Point",
        "coordinates": [
          -4.416667,
          52.5
        ]
      },
      "type": "Feature",
      "properties": {
        "hierarchy": [
          "tgn:7456523",
          "tgn:7002443",
          "tgn:7017242",
          "tgn:1000003",
          "tgn:7008591",
          "tgn:7029392"
        ],
        "placetype": [
          "aat:300132316"
        ],
        "name:en": "Cardigan Bay",
        "id": 7456523
      }
    },
    {
      "geometry": {
        "type": "Point",
        "coordinates": [
          -4.7,
          52.116667
        ]
      },
      "type": "Feature",
      "properties": {
        "hierarchy": [
          "tgn:7456524",
          "tgn:7002443",
          "tgn:1000003",
          "tgn:7018993",
          "tgn:7008591",
          "tgn:7029392"
        ],
        "placetype": [
          "aat:300132316"
        ],
        "name:en": "Cardigan, Port",
        "id": 7456524
      }
    },
    {
      "geometry": {
        "type": "Point",
        "coordinates": [
          -3.133333,
          51.483333
        ]
      },
      "type": "Feature",
      "properties": {
        "hierarchy": [
          "tgn:7456526",
          "tgn:7002443",
          "tgn:7018962",
          "tgn:1000003",
          "tgn:7008591",
          "tgn:7029392"
        ],
        "placetype": [
          "aat:300055621"
        ],
        "name:en": "Cardiff East Moors",
        "id": 7456526
      }
    },
    {
      "geometry": {
        "type": "Point",
        "coordinates": [
          -3.183333,
          51.483333
        ]
      },
      "type": "Feature",
      "properties": {
        "hierarchy": [
          "tgn:7456527",
          "tgn:7002443",
          "tgn:7018962",
          "tgn:1000003",
          "tgn:7008591",
          "tgn:7029392"
        ],
        "placetype": [
          "aat:300006891"
        ],
        "name:en": "Cardiff Castle",
        "id": 7456527
      }
    },
    {
      "geometry": {
        "type": "Point",
        "coordinates": [
          -3.183333,
          51.483333
        ]
      },
      "type": "Feature",
      "properties": {
        "hierarchy": [
          "tgn:7456528",
          "tgn:7002443",
          "tgn:7018962",
          "tgn:1000003",
          "tgn:7008591",
          "tgn:7029392"
        ],
        "placetype": [
          "aat:300008187"
        ],
        "name:en": "Cardiff Arms Park",
        "id": 7456528
      }
    }
  ]
}
