{
  "geometry": {
    "type": "Point",
    "coordinates": [
      -87.2667,
      34.1167
    ]
  },
  "type": "Feature",
  "properties": {
    "hierarchy": [
      "tgn:2129129",
      "tgn:7002659",
      "tgn:1000001",
      "tgn:7012149",
      "tgn:2000066",
      "tgn:7029392"
    ],
    "placetype": [
      "aat:300008699"
    ],
    "id": 2129129,
    "name:xx": "Alford Spring Branch"
  }
}
