{
  "geometry": {
    "type": "Point",
    "coordinates": [
      -78.4333,
      38.25
    ]
  },
  "type": "Feature",
  "properties": {
    "hierarchy": [
      "tgn:2668132",
      "tgn:1000001",
      "tgn:7012149",
      "tgn:2002165",
      "tgn:7007919",
      "tgn:7029392"
    ],
    "placetype": [
      "aat:300006191"
    ],
    "id": 2668132,
    "name:xx": "Skyline, Lake"
  }
}
