{
  "geometry": {
    "type": "Point",
    "coordinates": [
      -75.55,
      9.75
    ]
  },
  "type": "Feature",
  "properties": {
    "hierarchy": [
      "tgn:1023991",
      "tgn:1000050",
      "tgn:1000771",
      "tgn:1000002",
      "tgn:7029392"
    ],
    "placetype": [
      "aat:300008347"
    ],
    "id": 1023991,
    "name:xx": "San Onofre"
  }
}
