{
  "geometry": {
    "type": "Point",
    "coordinates": [
      -97.0833,
      30.7333
    ]
  },
  "type": "Feature",
  "properties": {
    "hierarchy": [
      "tgn:2108090",
      "tgn:1000001",
      "tgn:7012149",
      "tgn:1002670",
      "tgn:7007826",
      "tgn:7029392"
    ],
    "placetype": [
      "aat:300008347",
      "aat:300387210"
    ],
    "id": 2108090,
    "name:xx": "Tracy"
  }
}
