{
  "geometry": {
    "type": "Point",
    "coordinates": [
      10.1833,
      0.25
    ]
  },
  "type": "Feature",
  "properties": {
    "hierarchy": [
      "tgn:1090012",
      "tgn:1001668",
      "tgn:7001242",
      "tgn:1000164",
      "tgn:7029392"
    ],
    "placetype": [
      "aat:300008347"
    ],
    "id": 1090012,
    "name:xx": "Kango"
  }
}
