{
  "geometry": {
    "type": "Point",
    "coordinates": [
      -102.5833,
      29.8167
    ]
  },
  "type": "Feature",
  "properties": {
    "hierarchy": [
      "tgn:2206604",
      "tgn:1000001",
      "tgn:2001945",
      "tgn:7012149",
      "tgn:7007826",
      "tgn:7029392"
    ],
    "placetype": [
      "aat:300006191"
    ],
    "id": 2206604,
    "name:xx": "Bullis Gap Tank"
  }
}
