{
  "geometry": {
    "type": "Point",
    "coordinates": [
      -80.3333,
      37.4833
    ]
  },
  "type": "Feature",
  "properties": {
    "hierarchy": [
      "tgn:2454726",
      "tgn:1000001",
      "tgn:7012149",
      "tgn:2002154",
      "tgn:7007919",
      "tgn:7029392"
    ],
    "placetype": [
      "aat:300008699"
    ],
    "id": 2454726,
    "name:xx": "Little Double Branch"
  }
}
