{
  "geometry": {
    "type": "Point",
    "coordinates": [
      -80.8167,
      38.15
    ]
  },
  "type": "Feature",
  "properties": {
    "hierarchy": [
      "tgn:2728647",
      "tgn:1000001",
      "tgn:7012149",
      "tgn:2002284",
      "tgn:7013961",
      "tgn:7029392"
    ],
    "placetype": [
      "aat:300008699"
    ],
    "id": 2728647,
    "name:xx": "Trent Branch"
  }
}
