{
  "geometry": {
    "type": "Point",
    "coordinates": [
      -111.95,
      34.0333
    ]
  },
  "type": "Feature",
  "properties": {
    "hierarchy": [
      "tgn:2611966",
      "tgn:1000001",
      "tgn:7006451",
      "tgn:7012149",
      "tgn:2000103",
      "tgn:7029392"
    ],
    "placetype": [
      "aat:300006191"
    ],
    "id": 2611966,
    "name:xx": "Red River Tank"
  }
}
