{
  "type": "FeatureCollection",
  "features": [
    {
      "geometry": {
        "type": "Point",
        "coordinates": [
          -16.333333,
          28.55
        ]
      },
      "type": "Feature",
      "properties": {
        "hierarchy": [
          "tgn:7322550",
          "tgn:7002836",
          "tgn:7016622",
          "tgn:1000003",
          "tgn:1000095",
          "tgn:7029392"
        ],
        "placetype": [
          "aat:300386846"
        ],
        "id": 7322550,
        "name:xx": "San Juan, Punta"
      }
    },
    {
      "geometry": {
        "type": "Point",
        "coordinates": [
          -4.55,
          38.583333
        ]
      },
      "type": "Feature",
      "properties": {
        "hierarchy": [
          "tgn:7322551",
          "tgn:7002816",
          "tgn:1001647",
          "tgn:1000003",
          "tgn:1000095",
          "tgn:7029392"
        ],
        "placetype": [
          "aat:300259572"
        ],
        "id": 7322551,
        "name:xx": "San Juan, Puerto de"
      }
    },
    {
      "geometry": {
        "type": "Point",
        "coordinates": [
          -16.8,
          28.166667
        ]
      },
      "type": "Feature",
      "properties": {
        "hierarchy": [
          "tgn:7322552",
          "tgn:7002836",
          "tgn:7016622",
          "tgn:1000003",
          "tgn:1000095",
          "tgn:7029392"
        ],
        "placetype": [
          "aat:300132317"
        ],
        "id": 7322552,
        "name:xx": "San Juan, Puerto"
      }
    },
    {
      "geometry": {
        "type": "Point",
        "coordinates": [
          -0.4,
          38.4
        ]
      },
      "type": "Feature",
      "properties": {
        "hierarchy": [
          "tgn:7322553",
          "tgn:7002804",
          "tgn:1000003",
          "tgn:7002793",
          "tgn:1000095",
          "tgn:7029392"
        ],
        "placetype": [
          "aat:300008816"
        ],
        "id": 7322553,
        "name:xx": "San Juan, Playa de"
      }
    },
    {
      "geometry": {
        "type": "Point",
        "coordinates": [
          -13.566667,
          29.116667
        ]
      },
      "type": "Feature",
      "properties": {
        "hierarchy": [
          "tgn:7322554",
          "tgn:7002825",
          "tgn:7016622",
          "tgn:1000003",
          "tgn:1000095",
          "tgn:7029392"
        ],
        "placetype": [
          "aat:300008816"
        ],
        "id": 7322554,
        "name:xx": "San Juan, Playa de"
      }
    },
    {
      "geometry": {
        "type": "Point",
        "coordinates": [
          -5.94,
          43.597222
        ]
      },
      "type": "Feature",
      "properties": {
        "hierarchy": [
          "tgn:7322555",
          "tgn:7008911",
          "tgn:1000003",
          "tgn:7002763",
          "tgn:1000095",
          "tgn:7029392"
        ],
        "placetype": [
          "aat:300008804"
        ],
        "id": 7322555,
        "name:xx": "San Juan, Península de"
      }
    },
    {
      "geometry": {
        "type": "Point",
        "coordinates": [
          -1.733333,
          40.433333
        ]
      },
      "type": "Feature",
      "properties": {
        "hierarchy": [
          "tgn:7322556",
          "tgn:7002759",
          "tgn:7002843",
          "tgn:1000003",
          "tgn:1000095",
          "tgn:7029392"
        ],
        "placetype": [
          "aat:300266640"
        ],
        "id": 7322556,
        "name:xx": "San Juan, Muela de"
      }
    },
    {
      "geometry": {
        "type": "Point",
        "coordinates": [
          -16.25,
          28.45
        ]
      },
      "type": "Feature",
      "properties": {
        "hierarchy": [
          "tgn:7322557",
          "tgn:7002836",
          "tgn:7016622",
          "tgn:1000003",
          "tgn:1000095",
          "tgn:7029392"
        ],
        "placetype": [
          "aat:300006891"
        ],
        "id": 7322557,
        "name:xx": "Castillo de San Juan"
      }
    },
    {
      "geometry": {
        "type": "Point",
        "coordinates": [
          0.533333,
          41.233333
        ]
      },
      "type": "Feature",
      "properties": {
        "hierarchy": [
          "tgn:7322558",
          "tgn:7002844",
          "tgn:7030216",
          "tgn:1000003",
          "tgn:1000095",
          "tgn:7029392"
        ],
        "placetype": [
          "aat:300266554",
          "aat:300008699"
        ],
        "id": 7322558,
        "name:xx": "San Juan, Barranco de"
      }
    }
  ]
}
