{
  "geometry": {
    "type": "Point",
    "coordinates": [
      -65.4833,
      -24.9667
    ]
  },
  "type": "Feature",
  "properties": {
    "hierarchy": [
      "tgn:1019634",
      "tgn:7006477",
      "tgn:1001514",
      "tgn:1000002",
      "tgn:7029392"
    ],
    "placetype": [
      "aat:300008347"
    ],
    "id": 1019634,
    "name:xx": "La Merced"
  }
}
