{
  "geometry": {
    "type": "Point",
    "coordinates": [
      -86.6167,
      34.0833
    ]
  },
  "type": "Feature",
  "properties": {
    "hierarchy": [
      "tgn:2350151",
      "tgn:7002659",
      "tgn:1000001",
      "tgn:2000004",
      "tgn:7012149",
      "tgn:7029392"
    ],
    "placetype": [
      "aat:300008699"
    ],
    "id": 2350151,
    "name:xx": "Gin Branch"
  }
}
