{
  "geometry": {
    "type": "Point",
    "coordinates": [
      14.1667,
      -5.8667
    ]
  },
  "type": "Feature",
  "properties": {
    "hierarchy": [
      "tgn:1087875",
      "tgn:7001242",
      "tgn:1000149",
      "tgn:1000954",
      "tgn:7029392"
    ],
    "placetype": [
      "aat:300008347"
    ],
    "id": 1087875,
    "name:xx": "Luvo"
  }
}
