{
  "geometry": {
    "type": "Point",
    "coordinates": [
      -116.4833,
      48.7667
    ]
  },
  "type": "Feature",
  "properties": {
    "hierarchy": [
      "tgn:2648747",
      "tgn:1000001",
      "tgn:2000462",
      "tgn:7012149",
      "tgn:7007250",
      "tgn:7029392"
    ],
    "placetype": [
      "aat:300008706"
    ],
    "id": 2648747,
    "name:xx": "Scotch Creek"
  }
}
