{
  "geometry": {
    "type": "Point",
    "coordinates": [
      42.5667,
      15.35
    ]
  },
  "type": "Feature",
  "properties": {
    "hierarchy": [
      "tgn:1007617",
      "tgn:1000139",
      "tgn:7004345",
      "tgn:1000004",
      "tgn:7000261",
      "tgn:7029392"
    ],
    "placetype": [
      "aat:300008791"
    ],
    "id": 1007617,
    "name:xx": "Kamarān"
  }
}
