{
  "geometry": {
    "type": "Point",
    "coordinates": [
      -106.5833,
      34.3333
    ]
  },
  "type": "Feature",
  "properties": {
    "hierarchy": [
      "tgn:2470610",
      "tgn:1000001",
      "tgn:7012149",
      "tgn:2001456",
      "tgn:7007566",
      "tgn:7029392"
    ],
    "placetype": [
      "aat:300266640"
    ],
    "id": 2470610,
    "name:xx": "Los Pinos Mountains"
  }
}
