{
  "geometry": {
    "type": "Point",
    "coordinates": [
      89.2667,
      27.8333
    ]
  },
  "type": "Feature",
  "properties": {
    "hierarchy": [
      "tgn:1104228",
      "tgn:1000004",
      "tgn:7029392"
    ],
    "placetype": [
      "aat:300008795"
    ],
    "id": 1104228,
    "name:xx": "Cho-mo-la-li Shan"
  }
}
