{
  "geometry": {
    "type": "Point",
    "coordinates": [
      -74.3333,
      40.75
    ]
  },
  "type": "Feature",
  "properties": {
    "hierarchy": [
      "tgn:2713017",
      "tgn:1000001",
      "tgn:1002360",
      "tgn:7012149",
      "tgn:7007565",
      "tgn:7029392"
    ],
    "placetype": [
      "aat:300006191"
    ],
    "id": 2713017,
    "name:xx": "Taylor Lake"
  }
}
