{
  "geometry": {
    "type": "Point",
    "coordinates": [
      -77.1333,
      35.05
    ]
  },
  "type": "Feature",
  "properties": {
    "hierarchy": [
      "tgn:2076330",
      "tgn:1000001",
      "tgn:7012149",
      "tgn:2001486",
      "tgn:7007709",
      "tgn:7029392"
    ],
    "placetype": [
      "aat:300008347",
      "aat:300387210"
    ],
    "id": 2076330,
    "name:xx": "Rhems Landing"
  }
}
