{
  "geometry": {
    "type": "Point",
    "coordinates": [
      32.65,
      25.15
    ]
  },
  "type": "Feature",
  "properties": {
    "hierarchy": [
      "tgn:7521864",
      "tgn:7001242",
      "tgn:7016833",
      "tgn:7000123",
      "tgn:7029392"
    ],
    "placetype": [
      "aat:300379998"
    ],
    "name:en": "Abū Misallah, Wādī",
    "id": 7521864
  }
}
