{
  "geometry": {
    "type": "Point",
    "coordinates": [
      -117.4333,
      42.5667
    ]
  },
  "type": "Feature",
  "properties": {
    "hierarchy": [
      "tgn:2227632",
      "tgn:1000001",
      "tgn:7012149",
      "tgn:2001718",
      "tgn:7007708",
      "tgn:7029392"
    ],
    "placetype": [
      "aat:300266640"
    ],
    "id": 2227632,
    "name:xx": "Caviatta Ridge"
  }
}
