{
  "geometry": {
    "type": "Point",
    "coordinates": [
      -85.3167,
      35.7167
    ]
  },
  "type": "Feature",
  "properties": {
    "hierarchy": [
      "tgn:2370053",
      "tgn:1000001",
      "tgn:7012149",
      "tgn:2001924",
      "tgn:7007825",
      "tgn:7029392"
    ],
    "placetype": [
      "aat:300000390"
    ],
    "id": 2370053,
    "name:xx": "Guy Mine"
  }
}
