{
  "geometry": {
    "type": "Point",
    "coordinates": [
      79.84048,
      26.736823
    ]
  },
  "type": "Feature",
  "properties": {
    "hierarchy": [
      "tgn:7566174",
      "tgn:1000004",
      "tgn:7000198",
      "tgn:7016722",
      "tgn:7029392"
    ],
    "placetype": [
      "aat:300008347"
    ],
    "name:en": "Nawāda Shāham",
    "id": 7566174
  }
}
