{
  "geometry": {
    "type": "Point",
    "coordinates": [
      115.3333,
      30.7833
    ]
  },
  "type": "Feature",
  "properties": {
    "hierarchy": [
      "tgn:1070223",
      "tgn:1000004",
      "tgn:7002078",
      "tgn:1000111",
      "tgn:7029392"
    ],
    "placetype": [
      "aat:300008347"
    ],
    "id": 1070223,
    "name:xx": "Luotian"
  }
}
