{
  "geometry": {
    "type": "Point",
    "coordinates": [
      24.8167,
      46.1167
    ]
  },
  "type": "Feature",
  "properties": {
    "hierarchy": [
      "tgn:4000744",
      "tgn:1000003",
      "tgn:1000421",
      "tgn:1000091",
      "tgn:7029392"
    ],
    "placetype": [
      "aat:300008347"
    ],
    "id": 4000744,
    "name:xx": "Apold"
  }
}
