{
  "geometry": {
    "type": "Point",
    "coordinates": [
      -118.7167,
      37.5667
    ]
  },
  "type": "Feature",
  "properties": {
    "hierarchy": [
      "tgn:2680915",
      "tgn:1000001",
      "tgn:7012149",
      "tgn:7007157",
      "tgn:1002675",
      "tgn:7029392"
    ],
    "placetype": [
      "aat:300008347"
    ],
    "id": 2680915,
    "name:xx": "South Landing"
  }
}
