{
  "geometry": {
    "type": "Point",
    "coordinates": [
      -87.9333,
      39.55
    ]
  },
  "type": "Feature",
  "properties": {
    "hierarchy": [
      "tgn:2028537",
      "tgn:1000001",
      "tgn:2000504",
      "tgn:7012149",
      "tgn:7007251",
      "tgn:7029392"
    ],
    "placetype": [
      "aat:300008347"
    ],
    "id": 2028537,
    "name:xx": "Kansas"
  }
}
