{
  "type": "FeatureCollection",
  "features": [
    {
      "geometry": {
        "type": "Point",
        "coordinates": [
          173,
          -41.416667
        ]
      },
      "type": "Feature",
      "properties": {
        "hierarchy": [
          "tgn:7512470",
          "tgn:1009227",
          "tgn:1000226",
          "tgn:7520095",
          "tgn:1000006",
          "tgn:7029392"
        ],
        "placetype": [
          "aat:300008761"
        ],
        "name:en": "Hoult Valley",
        "id": 7512470
      }
    },
    {
      "geometry": {
        "type": "Point",
        "coordinates": [
          172.266667,
          -42.533333
        ]
      },
      "type": "Feature",
      "properties": {
        "hierarchy": [
          "tgn:7512471",
          "tgn:1009227",
          "tgn:7001866",
          "tgn:1000226",
          "tgn:1000006",
          "tgn:7029392"
        ],
        "placetype": [
          "aat:300008699"
        ],
        "name:en": "Hoults Creek",
        "id": 7512471
      }
    },
    {
      "geometry": {
        "type": "Point",
        "coordinates": [
          169.566667,
          -46.483333
        ]
      },
      "type": "Feature",
      "properties": {
        "hierarchy": [
          "tgn:7512472",
          "tgn:1009227",
          "tgn:1000226",
          "tgn:7018437",
          "tgn:1000006",
          "tgn:7029392"
        ],
        "placetype": [
          "aat:300008347"
        ],
        "name:en": "Houipapa",
        "id": 7512472
      }
    },
    {
      "geometry": {
        "type": "Point",
        "coordinates": [
          171,
          -42.7
        ]
      },
      "type": "Feature",
      "properties": {
        "hierarchy": [
          "tgn:7512473",
          "tgn:1009227",
          "tgn:1000226",
          "tgn:1000006",
          "tgn:7016850",
          "tgn:7029392"
        ],
        "placetype": [
          "aat:300008699"
        ],
        "name:en": "Hou Hou Creek",
        "id": 7512473
      }
    },
    {
      "geometry": {
        "type": "Point",
        "coordinates": [
          173.116667,
          -34.8
        ]
      },
      "type": "Feature",
      "properties": {
        "hierarchy": [
          "tgn:7512474",
          "tgn:1008380",
          "tgn:7000507",
          "tgn:1000226",
          "tgn:1000006",
          "tgn:7029392"
        ],
        "placetype": [
          "aat:300008678"
        ],
        "name:en": "Houhora Harbour",
        "id": 7512474
      }
    },
    {
      "geometry": {
        "type": "Point",
        "coordinates": [
          173.166667,
          -34.8
        ]
      },
      "type": "Feature",
      "properties": {
        "hierarchy": [
          "tgn:7512475",
          "tgn:1008380",
          "tgn:7000507",
          "tgn:1000226",
          "tgn:1000006",
          "tgn:7029392"
        ],
        "placetype": [
          "aat:300132316"
        ],
        "name:en": "Houhora Bay",
        "id": 7512475
      }
    },
    {
      "geometry": {
        "type": "Point",
        "coordinates": [
          173.1,
          -34.783333
        ]
      },
      "type": "Feature",
      "properties": {
        "hierarchy": [
          "tgn:7512476",
          "tgn:1008380",
          "tgn:7000507",
          "tgn:1000226",
          "tgn:1000006",
          "tgn:7029392"
        ],
        "placetype": [
          "aat:300008347"
        ],
        "name:en": "Houhora",
        "id": 7512476
      }
    },
    {
      "geometry": {
        "type": "Point",
        "coordinates": [
          174.783333,
          -41.35
        ]
      },
      "type": "Feature",
      "properties": {
        "hierarchy": [
          "tgn:7512477",
          "tgn:1009227",
          "tgn:1000226",
          "tgn:7016729",
          "tgn:1000006",
          "tgn:7029392"
        ],
        "placetype": [
          "aat:300132316"
        ],
        "name:en": "Houghton Bay",
        "id": 7512477
      }
    },
    {
      "geometry": {
        "type": "Point",
        "coordinates": [
          170.65,
          -43.2
        ]
      },
      "type": "Feature",
      "properties": {
        "hierarchy": [
          "tgn:7512478",
          "tgn:1009227",
          "tgn:1000226",
          "tgn:1000006",
          "tgn:7016850",
          "tgn:7029392"
        ],
        "placetype": [
          "aat:300008699"
        ],
        "name:en": "Hot Spring Creek",
        "id": 7512478
      }
    },
    {
      "geometry": {
        "type": "Point",
        "coordinates": [
          172.15,
          -42.6
        ]
      },
      "type": "Feature",
      "properties": {
        "hierarchy": [
          "tgn:7512479",
          "tgn:1009227",
          "tgn:7001866",
          "tgn:1000226",
          "tgn:1000006",
          "tgn:7029392"
        ],
        "placetype": [
          "aat:300008699"
        ],
        "name:en": "Hot Spring Creek",
        "id": 7512479
      }
    }
  ]
}
