{
  "geometry": {
    "type": "Point",
    "coordinates": [
      120.577,
      24.0711
    ]
  },
  "type": "Feature",
  "properties": {
    "hierarchy": [
      "tgn:7475331",
      "tgn:1000004",
      "tgn:7467799",
      "tgn:1000141",
      "tgn:7029392"
    ],
    "placetype": [
      "aat:300008347"
    ],
    "id": 7475331,
    "name:xx": "Lushankeng"
  }
}
