{
  "geometry": {
    "type": "Point",
    "coordinates": [
      -70.3333,
      41.7167
    ]
  },
  "type": "Feature",
  "properties": {
    "hierarchy": [
      "tgn:2756673",
      "tgn:1002165",
      "tgn:1000001",
      "tgn:7012149",
      "tgn:7007517",
      "tgn:7029392"
    ],
    "placetype": [
      "aat:300008706"
    ],
    "id": 2756673,
    "name:xx": "Wells Creek"
  }
}
