{
  "geometry": {
    "type": "Point",
    "coordinates": [
      -85.1333,
      42.0667
    ]
  },
  "type": "Feature",
  "properties": {
    "hierarchy": [
      "tgn:2738695",
      "tgn:1000001",
      "tgn:1002222",
      "tgn:7012149",
      "tgn:7007520",
      "tgn:7029392"
    ],
    "placetype": [
      "aat:300008347"
    ],
    "id": 2738695,
    "name:xx": "Union City"
  }
}
