{
  "geometry": {
    "type": "Point",
    "coordinates": [
      -73.15,
      40.85
    ]
  },
  "type": "Feature",
  "properties": {
    "hierarchy": [
      "tgn:2070726",
      "tgn:1000001",
      "tgn:7012149",
      "tgn:1002924",
      "tgn:7007568",
      "tgn:7029392"
    ],
    "placetype": [
      "aat:300008347"
    ],
    "id": 2070726,
    "name:xx": "Nesconset"
  }
}
