{
  "geometry": {
    "type": "Point",
    "coordinates": [
      -83.4167,
      34.7333
    ]
  },
  "type": "Feature",
  "properties": {
    "hierarchy": [
      "tgn:2710297",
      "tgn:1000001",
      "tgn:7012149",
      "tgn:7007248",
      "tgn:7029392"
    ],
    "placetype": [
      "aat:300008798"
    ],
    "id": 2710297,
    "name:xx": "Tallulah Mountain"
  }
}
