{
  "geometry": {
    "type": "Point",
    "coordinates": [
      -95.2833,
      43.0667
    ]
  },
  "type": "Feature",
  "properties": {
    "hierarchy": [
      "tgn:2686356",
      "tgn:1000001",
      "tgn:2000581",
      "tgn:7012149",
      "tgn:7007253",
      "tgn:7029392"
    ],
    "placetype": [
      "aat:300008706"
    ],
    "id": 2686356,
    "name:xx": "Spring Creek"
  }
}
