{
  "geometry": {
    "type": "Point",
    "coordinates": [
      16.6667,
      40.2167
    ]
  },
  "type": "Feature",
  "properties": {
    "hierarchy": [
      "tgn:7008299",
      "tgn:1003474",
      "tgn:7004610",
      "tgn:1000003",
      "tgn:1000080",
      "tgn:7029392"
    ],
    "placetype": [
      "aat:300008347",
      "aat:300000810",
      "aat:300167671"
    ],
    "id": 7008299,
    "name:xx": "Eraclea"
  }
}
