{
  "geometry": {
    "type": "Point",
    "coordinates": [
      -107.6833,
      39.0833
    ]
  },
  "type": "Feature",
  "properties": {
    "hierarchy": [
      "tgn:2587106",
      "tgn:1000001",
      "tgn:7012149",
      "tgn:2000230",
      "tgn:7007158",
      "tgn:7029392"
    ],
    "placetype": [
      "aat:300008706"
    ],
    "id": 2587106,
    "name:xx": "Plateau Creek"
  }
}
