{
  "geometry": {
    "type": "Point",
    "coordinates": [
      -108.1167,
      38.15
    ]
  },
  "type": "Feature",
  "properties": {
    "hierarchy": [
      "tgn:2352237",
      "tgn:1000001",
      "tgn:7012149",
      "tgn:7007158",
      "tgn:7029392"
    ],
    "placetype": [
      "aat:300006191"
    ],
    "id": 2352237,
    "name:xx": "Go Back Reservoir"
  }
}
