{
  "geometry": {
    "type": "Point",
    "coordinates": [
      -104.85,
      20.466667
    ]
  },
  "type": "Feature",
  "properties": {
    "hierarchy": [
      "tgn:7432847",
      "tgn:7005586",
      "tgn:1000001",
      "tgn:7005560",
      "tgn:7029392"
    ],
    "placetype": [
      "aat:300008699"
    ],
    "id": 7432847,
    "name:xx": "Toledo"
  }
}
