{
  "geometry": {
    "type": "Point",
    "coordinates": [
      -113.1167,
      39.3167
    ]
  },
  "type": "Feature",
  "properties": {
    "hierarchy": [
      "tgn:2674692",
      "tgn:1000001",
      "tgn:7012149",
      "tgn:2002114",
      "tgn:7007827",
      "tgn:7029392"
    ],
    "placetype": [
      "aat:300006191"
    ],
    "id": 2674692,
    "name:xx": "Soap Hollow Reservoir"
  }
}
