{
  "geometry": {
    "type": "Point",
    "coordinates": [
      -111.1833,
      50.2167
    ]
  },
  "type": "Feature",
  "properties": {
    "hierarchy": [
      "tgn:1013312",
      "tgn:7005694",
      "tgn:7005685",
      "tgn:1000001",
      "tgn:7029392"
    ],
    "placetype": [
      "aat:300008347"
    ],
    "id": 1013312,
    "name:xx": "Suffield"
  }
}
