{
  "geometry": {
    "type": "Point",
    "coordinates": [
      -87.2667,
      41.15
    ]
  },
  "type": "Feature",
  "properties": {
    "hierarchy": [
      "tgn:2561839",
      "tgn:1000001",
      "tgn:7012149",
      "tgn:7007252",
      "tgn:7029392"
    ],
    "placetype": [
      "aat:300006075"
    ],
    "id": 2561839,
    "name:xx": "Otis-Boyle Ditch"
  }
}
