{
  "geometry": {
    "type": "Point",
    "coordinates": [
      30.833333,
      28.816667
    ]
  },
  "type": "Feature",
  "properties": {
    "hierarchy": [
      "tgn:7526956",
      "tgn:7001242",
      "tgn:7016833",
      "tgn:1001142",
      "tgn:7029392"
    ],
    "placetype": [
      "aat:300005926"
    ],
    "name:en": "Sīdī Muḩammad al Khayyāţ",
    "id": 7526956
  }
}
