{
  "geometry": {
    "type": "Point",
    "coordinates": [
      -150.4167,
      61.45
    ]
  },
  "type": "Feature",
  "properties": {
    "hierarchy": [
      "tgn:2330701",
      "tgn:7006450",
      "tgn:1000001",
      "tgn:2124053",
      "tgn:7012149",
      "tgn:7029392"
    ],
    "placetype": [
      "aat:300008680"
    ],
    "id": 2330701,
    "name:xx": "Flat Horn Lake"
  }
}
