{
  "geometry": {
    "type": "Point",
    "coordinates": [
      -113.1167,
      47.5833
    ]
  },
  "type": "Feature",
  "properties": {
    "hierarchy": [
      "tgn:2610383",
      "tgn:1000001",
      "tgn:7012149",
      "tgn:2001284",
      "tgn:7007524",
      "tgn:7029392"
    ],
    "placetype": [
      "aat:300008706"
    ],
    "id": 2610383,
    "name:xx": "Red Butte Creek"
  }
}
