{
  "geometry": {
    "type": "Point",
    "coordinates": [
      5.9833,
      36.1167
    ]
  },
  "type": "Feature",
  "properties": {
    "hierarchy": [
      "tgn:1087571",
      "tgn:7001242",
      "tgn:7016752",
      "tgn:7000350",
      "tgn:7029392"
    ],
    "placetype": [
      "aat:300008347"
    ],
    "id": 1087571,
    "name:xx": "Tadjenanet"
  }
}
