{
  "type": "FeatureCollection",
  "features": [
    {
      "geometry": {
        "type": "Point",
        "coordinates": [
          121.78241,
          25.097545
        ]
      },
      "type": "Feature",
      "properties": {
        "hierarchy": [
          "tgn:7491660",
          "tgn:1000004",
          "tgn:1000454",
          "tgn:1000141",
          "tgn:7029392"
        ],
        "placetype": [
          "aat:300008347"
        ],
        "id": 7491660,
        "name:xx": "Daliao"
      }
    },
    {
      "geometry": {
        "type": "Point",
        "coordinates": [
          120.745511,
          24.586337
        ]
      },
      "type": "Feature",
      "properties": {
        "hierarchy": [
          "tgn:7491661",
          "tgn:7487020",
          "tgn:1000004",
          "tgn:1000141",
          "tgn:7029392"
        ],
        "placetype": [
          "aat:300008347"
        ],
        "id": 7491661,
        "name:xx": "Daliao"
      }
    },
    {
      "geometry": {
        "type": "Point",
        "coordinates": [
          120.861231,
          24.417016
        ]
      },
      "type": "Feature",
      "properties": {
        "hierarchy": [
          "tgn:7491662",
          "tgn:7487020",
          "tgn:1000004",
          "tgn:1000141",
          "tgn:7029392"
        ],
        "placetype": [
          "aat:300008347"
        ],
        "id": 7491662,
        "name:xx": "Daliaokeng"
      }
    },
    {
      "geometry": {
        "type": "Point",
        "coordinates": [
          120.186321,
          23.373753
        ]
      },
      "type": "Feature",
      "properties": {
        "hierarchy": [
          "tgn:7491663",
          "tgn:7468018",
          "tgn:1000004",
          "tgn:1000141",
          "tgn:7029392"
        ],
        "placetype": [
          "aat:300008347"
        ],
        "id": 7491663,
        "name:xx": "Daliao"
      }
    },
    {
      "geometry": {
        "type": "Point",
        "coordinates": [
          120.153611,
          23.147222
        ]
      },
      "type": "Feature",
      "properties": {
        "hierarchy": [
          "tgn:7491664",
          "tgn:1000004",
          "tgn:7490934",
          "tgn:1000141",
          "tgn:7029392"
        ],
        "placetype": [
          "aat:300008347"
        ],
        "id": 7491664,
        "name:xx": "Daliao"
      }
    },
    {
      "geometry": {
        "type": "Point",
        "coordinates": [
          120.315278,
          22.776389
        ]
      },
      "type": "Feature",
      "properties": {
        "hierarchy": [
          "tgn:7491665",
          "tgn:7001004",
          "tgn:1000004",
          "tgn:1000141",
          "tgn:7029392"
        ],
        "placetype": [
          "aat:300008347"
        ],
        "id": 7491665,
        "name:xx": "Daliao"
      }
    },
    {
      "geometry": {
        "type": "Point",
        "coordinates": [
          120.417642,
          22.590572
        ]
      },
      "type": "Feature",
      "properties": {
        "hierarchy": [
          "tgn:7491666",
          "tgn:7001004",
          "tgn:1000004",
          "tgn:1000141",
          "tgn:7029392"
        ],
        "placetype": [
          "aat:300008347"
        ],
        "id": 7491666,
        "name:xx": "Daliao"
      }
    },
    {
      "geometry": {
        "type": "Point",
        "coordinates": [
          120.733333,
          22.25
        ]
      },
      "type": "Feature",
      "properties": {
        "hierarchy": [
          "tgn:7491669",
          "tgn:1000004",
          "tgn:7492971",
          "tgn:1000141",
          "tgn:7029392"
        ],
        "placetype": [
          "aat:300008347"
        ],
        "id": 7491669,
        "name:xx": "Taliao"
      }
    }
  ]
}
