{
  "geometry": {
    "type": "Point",
    "coordinates": [
      -107.0167,
      40.05
    ]
  },
  "type": "Feature",
  "properties": {
    "hierarchy": [
      "tgn:2523002",
      "tgn:1000001",
      "tgn:7012149",
      "tgn:7007158",
      "tgn:2000245",
      "tgn:7029392"
    ],
    "placetype": [
      "aat:300008706"
    ],
    "id": 2523002,
    "name:xx": "Moore Park Creek"
  }
}
