{
  "geometry": {
    "type": "Point",
    "coordinates": [
      59.2667,
      45.15
    ]
  },
  "type": "Feature",
  "properties": {
    "hierarchy": [
      "tgn:1054999",
      "tgn:1000004",
      "tgn:7011673",
      "tgn:1009669",
      "tgn:7006661",
      "tgn:7029392"
    ],
    "placetype": [
      "aat:300008347"
    ],
    "id": 1054999,
    "name:xx": "Kantubek"
  }
}
