{
  "geometry": {
    "type": "Point",
    "coordinates": [
      19.65,
      45.8167
    ]
  },
  "type": "Feature",
  "properties": {
    "hierarchy": [
      "tgn:1064904",
      "tgn:1000003",
      "tgn:4011927",
      "tgn:7006669",
      "tgn:7029392"
    ],
    "placetype": [
      "aat:300008347"
    ],
    "id": 1064904,
    "name:xx": "Bačka Topola"
  }
}
