{
  "type": "FeatureCollection",
  "features": [
    {
      "geometry": {
        "type": "Point",
        "coordinates": [
          -70.6,
          -55.066667
        ]
      },
      "type": "Feature",
      "properties": {
        "hierarchy": [
          "tgn:7291190",
          "tgn:1001702",
          "tgn:1000049",
          "tgn:1000002",
          "tgn:7029392"
        ],
        "placetype": [
          "aat:300008676"
        ],
        "id": 7291190,
        "name:xx": "Escondido, Seno"
      }
    },
    {
      "geometry": {
        "type": "Point",
        "coordinates": [
          -74.150278,
          -42.301389
        ]
      },
      "type": "Feature",
      "properties": {
        "hierarchy": [
          "tgn:7291191",
          "tgn:1001699",
          "tgn:1000049",
          "tgn:1000002",
          "tgn:7029392"
        ],
        "placetype": [
          "aat:300008699"
        ],
        "id": 7291191,
        "name:xx": "Escondido, Río"
      }
    },
    {
      "geometry": {
        "type": "Point",
        "coordinates": [
          -74.933333,
          -47.75
        ]
      },
      "type": "Feature",
      "properties": {
        "hierarchy": [
          "tgn:7291192",
          "tgn:1001623",
          "tgn:1000049",
          "tgn:1000002",
          "tgn:7029392"
        ],
        "placetype": [
          "aat:300008678"
        ],
        "id": 7291192,
        "name:xx": "Escondido, Puerto"
      }
    },
    {
      "geometry": {
        "type": "Point",
        "coordinates": [
          -72.885,
          -43.614167
        ]
      },
      "type": "Feature",
      "properties": {
        "hierarchy": [
          "tgn:7291193",
          "tgn:1001699",
          "tgn:1000049",
          "tgn:1000002",
          "tgn:7029392"
        ],
        "placetype": [
          "aat:300132316"
        ],
        "id": 7291193,
        "name:xx": "Escondido, Puerto"
      }
    },
    {
      "geometry": {
        "type": "Point",
        "coordinates": [
          -70.283333,
          -31.933333
        ]
      },
      "type": "Feature",
      "properties": {
        "hierarchy": [
          "tgn:7291194",
          "tgn:1001657",
          "tgn:1000049",
          "tgn:1000002",
          "tgn:7029392"
        ],
        "placetype": [
          "aat:300259572"
        ],
        "id": 7291194,
        "name:xx": "Escondido, Portezuelo"
      }
    },
    {
      "geometry": {
        "type": "Point",
        "coordinates": [
          -74.7,
          -46.816667
        ]
      },
      "type": "Feature",
      "properties": {
        "hierarchy": [
          "tgn:7291195",
          "tgn:1001623",
          "tgn:1000049",
          "tgn:1000002",
          "tgn:7029392"
        ],
        "placetype": [
          "aat:300008676"
        ],
        "id": 7291195,
        "name:xx": "Escondido, Seno"
      }
    },
    {
      "geometry": {
        "type": "Point",
        "coordinates": [
          -72.333333,
          -46.55
        ]
      },
      "type": "Feature",
      "properties": {
        "hierarchy": [
          "tgn:7291196",
          "tgn:1001623",
          "tgn:1000049",
          "tgn:1000002",
          "tgn:7029392"
        ],
        "placetype": [
          "aat:300008699"
        ],
        "id": 7291196,
        "name:xx": "Escondido, Arroyo"
      }
    },
    {
      "geometry": {
        "type": "Point",
        "coordinates": [
          -74.154167,
          -42.297222
        ]
      },
      "type": "Feature",
      "properties": {
        "hierarchy": [
          "tgn:7291197",
          "tgn:1001699",
          "tgn:1000049",
          "tgn:1000002",
          "tgn:7029392"
        ],
        "placetype": [
          "aat:300386846"
        ],
        "id": 7291197,
        "name:xx": "Escondida, Punta"
      }
    },
    {
      "geometry": {
        "type": "Point",
        "coordinates": [
          -72.15,
          -51.916667
        ]
      },
      "type": "Feature",
      "properties": {
        "hierarchy": [
          "tgn:7291198",
          "tgn:1001702",
          "tgn:1000049",
          "tgn:1000002",
          "tgn:7029392"
        ],
        "placetype": [
          "aat:300008680"
        ],
        "id": 7291198,
        "name:xx": "Escondida, Laguna"
      }
    },
    {
      "geometry": {
        "type": "Point",
        "coordinates": [
          -72.716667,
          -48.533333
        ]
      },
      "type": "Feature",
      "properties": {
        "hierarchy": [
          "tgn:7291199",
          "tgn:1001623",
          "tgn:1000049",
          "tgn:1000002",
          "tgn:7029392"
        ],
        "placetype": [
          "aat:300008680"
        ],
        "id": 7291199,
        "name:xx": "Escondida, Laguna"
      }
    }
  ]
}
