{
  "geometry": {
    "type": "Point",
    "coordinates": [
      79.501119,
      21.803273
    ]
  },
  "type": "Feature",
  "properties": {
    "hierarchy": [
      "tgn:7556852",
      "tgn:1000004",
      "tgn:7000198",
      "tgn:1001894",
      "tgn:7029392"
    ],
    "placetype": [
      "aat:300008347"
    ],
    "name:en": "Pindkāpār",
    "id": 7556852
  }
}
