{
  "geometry": {
    "type": "Point",
    "coordinates": [
      -105.4333,
      36.0667
    ]
  },
  "type": "Feature",
  "properties": {
    "hierarchy": [
      "tgn:2744980",
      "tgn:1000001",
      "tgn:7012149",
      "tgn:2001446",
      "tgn:7007566",
      "tgn:7029392"
    ],
    "placetype": [
      "aat:300008761"
    ],
    "id": 2744980,
    "name:xx": "Vigil Canyon"
  }
}
