{
  "geometry": {
    "type": "Point",
    "coordinates": [
      -106.65,
      40.6667
    ]
  },
  "type": "Feature",
  "properties": {
    "hierarchy": [
      "tgn:2610418",
      "tgn:1000001",
      "tgn:7012149",
      "tgn:2000220",
      "tgn:7007158",
      "tgn:7029392"
    ],
    "placetype": [
      "aat:300008761"
    ],
    "id": 2610418,
    "name:xx": "Red Canyon"
  }
}
