{
  "geometry": {
    "type": "Point",
    "coordinates": [
      14.3333,
      56.0667
    ]
  },
  "type": "Feature",
  "properties": {
    "hierarchy": [
      "tgn:4005670",
      "tgn:1000003",
      "tgn:7024622",
      "tgn:1000097",
      "tgn:7029392"
    ],
    "placetype": [
      "aat:300008347"
    ],
    "id": 4005670,
    "name:xx": "Kiaby"
  }
}
