{
  "type": "FeatureCollection",
  "features": [
    {
      "geometry": {
        "type": "Point",
        "coordinates": [
          -148.45,
          65.5167
        ]
      },
      "type": "Feature",
      "properties": {
        "hierarchy": [
          "tgn:2475480",
          "tgn:7006450",
          "tgn:1000001",
          "tgn:7012149",
          "tgn:2000089",
          "tgn:7029392"
        ],
        "placetype": [
          "aat:300008706"
        ],
        "id": 2475480,
        "name:xx": "Lucille Creek"
      }
    },
    {
      "geometry": {
        "type": "Point",
        "coordinates": [
          -89.5667,
          47.95
        ]
      },
      "type": "Feature",
      "properties": {
        "hierarchy": [
          "tgn:2475481",
          "tgn:1000001",
          "tgn:2001014",
          "tgn:7012149",
          "tgn:7007521",
          "tgn:7029392"
        ],
        "placetype": [
          "aat:300008791"
        ],
        "id": 2475481,
        "name:xx": "Lucille Island"
      }
    },
    {
      "geometry": {
        "type": "Point",
        "coordinates": [
          -94.0333,
          47.1333
        ]
      },
      "type": "Feature",
      "properties": {
        "hierarchy": [
          "tgn:2475482",
          "tgn:1000001",
          "tgn:2001009",
          "tgn:7012149",
          "tgn:7007521",
          "tgn:7029392"
        ],
        "placetype": [
          "aat:300008680"
        ],
        "id": 2475482,
        "name:xx": "Lucille Lake"
      }
    },
    {
      "geometry": {
        "type": "Point",
        "coordinates": [
          -92.5667,
          48.3667
        ]
      },
      "type": "Feature",
      "properties": {
        "hierarchy": [
          "tgn:2475483",
          "tgn:1000001",
          "tgn:7012149",
          "tgn:2001067",
          "tgn:7007521",
          "tgn:7029392"
        ],
        "placetype": [
          "aat:300008680"
        ],
        "id": 2475483,
        "name:xx": "Lucille Lake"
      }
    },
    {
      "geometry": {
        "type": "Point",
        "coordinates": [
          -94.15,
          36.0667
        ]
      },
      "type": "Feature",
      "properties": {
        "hierarchy": [
          "tgn:2475484",
          "tgn:1000001",
          "tgn:7016172",
          "tgn:7012149",
          "tgn:2000176",
          "tgn:7029392"
        ],
        "placetype": [
          "aat:300006191"
        ],
        "id": 2475484,
        "name:xx": "Lucille, Lake"
      }
    },
    {
      "geometry": {
        "type": "Point",
        "coordinates": [
          -120.1,
          38.85
        ]
      },
      "type": "Feature",
      "properties": {
        "hierarchy": [
          "tgn:2475485",
          "tgn:1000001",
          "tgn:7012149",
          "tgn:1002350",
          "tgn:7007157",
          "tgn:7029392"
        ],
        "placetype": [
          "aat:300008680"
        ],
        "id": 2475485,
        "name:xx": "Lucille, Lake"
      }
    },
    {
      "geometry": {
        "type": "Point",
        "coordinates": [
          -81.85,
          28.6833
        ]
      },
      "type": "Feature",
      "properties": {
        "hierarchy": [
          "tgn:2475486",
          "tgn:1000001",
          "tgn:7012149",
          "tgn:1002567",
          "tgn:7007240",
          "tgn:7029392"
        ],
        "placetype": [
          "aat:300008680"
        ],
        "id": 2475486,
        "name:xx": "Lucille, Lake"
      }
    },
    {
      "geometry": {
        "type": "Point",
        "coordinates": [
          -93.3333,
          38.7
        ]
      },
      "type": "Feature",
      "properties": {
        "hierarchy": [
          "tgn:2475487",
          "tgn:1000001",
          "tgn:7012149",
          "tgn:2001229",
          "tgn:7007523",
          "tgn:7029392"
        ],
        "placetype": [
          "aat:300006191"
        ],
        "id": 2475487,
        "name:xx": "Lucille, Lake"
      }
    },
    {
      "geometry": {
        "type": "Point",
        "coordinates": [
          -73.9833,
          41.1833
        ]
      },
      "type": "Feature",
      "properties": {
        "hierarchy": [
          "tgn:2475488",
          "tgn:1000001",
          "tgn:7012149",
          "tgn:1002833",
          "tgn:7007568",
          "tgn:7029392"
        ],
        "placetype": [
          "aat:300008680"
        ],
        "id": 2475488,
        "name:xx": "Lucille, Lake"
      }
    },
    {
      "geometry": {
        "type": "Point",
        "coordinates": [
          -89.0833,
          45.5167
        ]
      },
      "type": "Feature",
      "properties": {
        "hierarchy": [
          "tgn:2475489",
          "tgn:1000001",
          "tgn:7012149",
          "tgn:2002342",
          "tgn:7007922",
          "tgn:7029392"
        ],
        "placetype": [
          "aat:300008680"
        ],
        "id": 2475489,
        "name:xx": "Lucille, Lake"
      }
    }
  ]
}
