{
  "geometry": {
    "type": "Point",
    "coordinates": [
      145.15,
      -37.75
    ]
  },
  "type": "Feature",
  "properties": {
    "hierarchy": [
      "tgn:1102932",
      "tgn:7000490",
      "tgn:1000006",
      "tgn:7006238",
      "tgn:7029392"
    ],
    "placetype": [
      "aat:300008187"
    ],
    "id": 1102932,
    "name:xx": "Lower Eltham Park"
  }
}
