{
  "type": "FeatureCollection",
  "features": [
    {
      "geometry": {
        "type": "Point",
        "coordinates": [
          10,
          48.266667
        ]
      },
      "type": "Feature",
      "properties": {
        "hierarchy": [
          "tgn:7070660",
          "tgn:7003692",
          "tgn:1000003",
          "tgn:7000084",
          "tgn:7029392"
        ],
        "placetype": [
          "aat:300008699"
        ],
        "id": 7070660,
        "name:xx": "Steinenbach"
      }
    },
    {
      "geometry": {
        "type": "Point",
        "coordinates": [
          8.15,
          48.483333
        ]
      },
      "type": "Feature",
      "properties": {
        "hierarchy": [
          "tgn:7070661",
          "tgn:7003692",
          "tgn:1000003",
          "tgn:7000084",
          "tgn:7029392"
        ],
        "placetype": [
          "aat:300387200"
        ],
        "id": 7070661,
        "name:xx": "Steinenbach"
      }
    },
    {
      "geometry": {
        "type": "Point",
        "coordinates": [
          8.2,
          48.233333
        ]
      },
      "type": "Feature",
      "properties": {
        "hierarchy": [
          "tgn:7070662",
          "tgn:7003692",
          "tgn:1000003",
          "tgn:7000084",
          "tgn:7029392"
        ],
        "placetype": [
          "aat:300387200"
        ],
        "id": 7070662,
        "name:xx": "Steinenbach"
      }
    },
    {
      "geometry": {
        "type": "Point",
        "coordinates": [
          9.816667,
          48.9
        ]
      },
      "type": "Feature",
      "properties": {
        "hierarchy": [
          "tgn:7070663",
          "tgn:7003692",
          "tgn:1000003",
          "tgn:7000084",
          "tgn:7029392"
        ],
        "placetype": [
          "aat:300008347"
        ],
        "id": 7070663,
        "name:xx": "Steinenbach"
      }
    },
    {
      "geometry": {
        "type": "Point",
        "coordinates": [
          9.616667,
          47.933333
        ]
      },
      "type": "Feature",
      "properties": {
        "hierarchy": [
          "tgn:7070664",
          "tgn:7003692",
          "tgn:1000003",
          "tgn:7000084",
          "tgn:7029392"
        ],
        "placetype": [
          "aat:300008347"
        ],
        "id": 7070664,
        "name:xx": "Steinenbach"
      }
    },
    {
      "geometry": {
        "type": "Point",
        "coordinates": [
          9.683333,
          47.633333
        ]
      },
      "type": "Feature",
      "properties": {
        "hierarchy": [
          "tgn:7070665",
          "tgn:7003692",
          "tgn:1000003",
          "tgn:7000084",
          "tgn:7029392"
        ],
        "placetype": [
          "aat:300008347"
        ],
        "id": 7070665,
        "name:xx": "Steinenbach"
      }
    },
    {
      "geometry": {
        "type": "Point",
        "coordinates": [
          7.816667,
          51.566667
        ]
      },
      "type": "Feature",
      "properties": {
        "hierarchy": [
          "tgn:7070666",
          "tgn:1000003",
          "tgn:7003677",
          "tgn:7000084",
          "tgn:7029392"
        ],
        "placetype": [
          "aat:300008347"
        ],
        "id": 7070666,
        "name:xx": "Steinen"
      }
    },
    {
      "geometry": {
        "type": "Point",
        "coordinates": [
          7.8,
          50.583333
        ]
      },
      "type": "Feature",
      "properties": {
        "hierarchy": [
          "tgn:7070667",
          "tgn:1000003",
          "tgn:7003682",
          "tgn:7000084",
          "tgn:7029392"
        ],
        "placetype": [
          "aat:300008347"
        ],
        "id": 7070667,
        "name:xx": "Steinen"
      }
    },
    {
      "geometry": {
        "type": "Point",
        "coordinates": [
          7.4,
          51.8
        ]
      },
      "type": "Feature",
      "properties": {
        "hierarchy": [
          "tgn:7070669",
          "tgn:1000003",
          "tgn:7003677",
          "tgn:7000084",
          "tgn:7029392"
        ],
        "placetype": [
          "aat:300000206"
        ],
        "id": 7070669,
        "name:xx": "Steinemann"
      }
    }
  ]
}
