{
  "geometry": {
    "type": "Point",
    "coordinates": [
      -107.2167,
      48.9833
    ]
  },
  "type": "Feature",
  "properties": {
    "hierarchy": [
      "tgn:1134635",
      "tgn:1000001",
      "tgn:7012149",
      "tgn:7007524",
      "tgn:7029392"
    ],
    "placetype": [
      "aat:300008706"
    ],
    "id": 1134635,
    "name:xx": "Snake Creek"
  }
}
