{
  "geometry": {
    "type": "Point",
    "coordinates": [
      34.95,
      32.2333
    ]
  },
  "type": "Feature",
  "properties": {
    "hierarchy": [
      "tgn:1079509",
      "tgn:1000862",
      "tgn:1000004",
      "tgn:1000119",
      "tgn:7029392"
    ],
    "placetype": [
      "aat:300008347"
    ],
    "id": 1079509,
    "name:xx": "Eṭ Ṭaiyiba"
  }
}
