{
  "geometry": {
    "type": "Point",
    "coordinates": [
      -122.2667,
      46.6667
    ]
  },
  "type": "Feature",
  "properties": {
    "hierarchy": [
      "tgn:2730004",
      "tgn:1000001",
      "tgn:7012149",
      "tgn:1002594",
      "tgn:7007920",
      "tgn:7029392"
    ],
    "placetype": [
      "aat:300008706"
    ],
    "id": 2730004,
    "name:xx": "Trout Creek"
  }
}
