{
  "geometry": {
    "type": "Point",
    "coordinates": [
      -106.15,
      39.1167
    ]
  },
  "type": "Feature",
  "properties": {
    "hierarchy": [
      "tgn:2227073",
      "tgn:1000001",
      "tgn:7012149",
      "tgn:2000238",
      "tgn:7007158",
      "tgn:7029392"
    ],
    "placetype": [
      "aat:300008706"
    ],
    "id": 2227073,
    "name:xx": "Cave Creek"
  }
}
