{
  "type": "FeatureCollection",
  "features": [
    {
      "geometry": {
        "type": "Point",
        "coordinates": [
          171.183333,
          -42.7
        ]
      },
      "type": "Feature",
      "properties": {
        "hierarchy": [
          "tgn:7511802",
          "tgn:1009227",
          "tgn:1000226",
          "tgn:1000006",
          "tgn:7016850",
          "tgn:7029392"
        ],
        "placetype": [
          "aat:300008699"
        ],
        "name:en": "Kapitea Creek",
        "id": 7511802
      }
    },
    {
      "geometry": {
        "type": "Point",
        "coordinates": [
          171.1,
          -42.6
        ]
      },
      "type": "Feature",
      "properties": {
        "hierarchy": [
          "tgn:7511803",
          "tgn:1009227",
          "tgn:1000226",
          "tgn:1000006",
          "tgn:7016850",
          "tgn:7029392"
        ],
        "placetype": [
          "aat:300008699"
        ],
        "name:en": "Kapitea Creek",
        "id": 7511803
      }
    },
    {
      "geometry": {
        "type": "Point",
        "coordinates": [
          174.733333,
          -37.533333
        ]
      },
      "type": "Feature",
      "properties": {
        "hierarchy": [
          "tgn:7511804",
          "tgn:1008380",
          "tgn:1000226",
          "tgn:7018426",
          "tgn:1000006",
          "tgn:7029392"
        ],
        "placetype": [
          "aat:300011692"
        ],
        "name:en": "Kapiapia Rock",
        "id": 7511804
      }
    },
    {
      "geometry": {
        "type": "Point",
        "coordinates": [
          173.5,
          -35.466667
        ]
      },
      "type": "Feature",
      "properties": {
        "hierarchy": [
          "tgn:7511806",
          "tgn:1008380",
          "tgn:7000507",
          "tgn:1000226",
          "tgn:1000006",
          "tgn:7029392"
        ],
        "placetype": [
          "aat:300008777"
        ],
        "name:en": "Kapeke",
        "id": 7511806
      }
    },
    {
      "geometry": {
        "type": "Point",
        "coordinates": [
          174.716667,
          -39.516667
        ]
      },
      "type": "Feature",
      "properties": {
        "hierarchy": [
          "tgn:7511807",
          "tgn:1008380",
          "tgn:1000226",
          "tgn:7016827",
          "tgn:1000006",
          "tgn:7029392"
        ],
        "placetype": [
          "aat:300008795"
        ],
        "name:en": "Kapara",
        "id": 7511807
      }
    },
    {
      "geometry": {
        "type": "Point",
        "coordinates": [
          174.75,
          -39.533333
        ]
      },
      "type": "Feature",
      "properties": {
        "hierarchy": [
          "tgn:7511808",
          "tgn:1008380",
          "tgn:1000226",
          "tgn:7016827",
          "tgn:1000006",
          "tgn:7029392"
        ],
        "placetype": [
          "aat:300008347"
        ],
        "name:en": "Kapara",
        "id": 7511808
      }
    },
    {
      "geometry": {
        "type": "Point",
        "coordinates": [
          175.166667,
          -40.933333
        ]
      },
      "type": "Feature",
      "properties": {
        "hierarchy": [
          "tgn:7511809",
          "tgn:1008380",
          "tgn:1000226",
          "tgn:7000512",
          "tgn:1000006",
          "tgn:7029392"
        ],
        "placetype": [
          "aat:300008795"
        ],
        "name:en": "Kapakapanui",
        "id": 7511809
      }
    }
  ]
}
