{
  "geometry": {
    "type": "Point",
    "coordinates": [
      51.6667,
      35.3167
    ]
  },
  "type": "Feature",
  "properties": {
    "hierarchy": [
      "tgn:1079349",
      "tgn:1000004",
      "tgn:7002004",
      "tgn:7000231",
      "tgn:7029392"
    ],
    "placetype": [
      "aat:300008347"
    ],
    "id": 1079349,
    "name:xx": "Varāmīn"
  }
}
