{
  "geometry": {
    "type": "Point",
    "coordinates": [
      -2.28113,
      43.068285
    ]
  },
  "type": "Feature",
  "properties": {
    "hierarchy": [
      "tgn:7324748",
      "tgn:7007780",
      "tgn:1000003",
      "tgn:7009604",
      "tgn:1000095",
      "tgn:7029392"
    ],
    "placetype": [
      "aat:300008347"
    ],
    "id": 7324748,
    "name:xx": "Santa Lucía"
  }
}
