{
  "geometry": {
    "type": "Point",
    "coordinates": [
      82.125367,
      25.735804
    ]
  },
  "type": "Feature",
  "properties": {
    "hierarchy": [
      "tgn:7558433",
      "tgn:1000004",
      "tgn:7000198",
      "tgn:7016722",
      "tgn:7029392"
    ],
    "placetype": [
      "aat:300008347"
    ],
    "name:en": "Patihtīā Kalān",
    "id": 7558433
  }
}
