{
  "geometry": {
    "type": "Point",
    "coordinates": [
      -82.2833,
      22.7167
    ]
  },
  "type": "Feature",
  "properties": {
    "hierarchy": [
      "tgn:1016310",
      "tgn:1001374",
      "tgn:1000001",
      "tgn:7004624",
      "tgn:7029392"
    ],
    "placetype": [
      "aat:300008347"
    ],
    "id": 1016310,
    "name:xx": "Batabanó"
  }
}
