{
  "geometry": {
    "type": "Point",
    "coordinates": [
      -87.1167,
      35.6667
    ]
  },
  "type": "Feature",
  "properties": {
    "hierarchy": [
      "tgn:2709867",
      "tgn:1000001",
      "tgn:7012149",
      "tgn:2001896",
      "tgn:7007825",
      "tgn:7029392"
    ],
    "placetype": [
      "aat:300006191"
    ],
    "id": 2709867,
    "name:xx": "Tailings Pond Number Two"
  }
}
