{
  "geometry": {
    "type": "Point",
    "coordinates": [
      -91.3333,
      40.3833
    ]
  },
  "type": "Feature",
  "properties": {
    "hierarchy": [
      "tgn:2028172",
      "tgn:1000001",
      "tgn:7012149",
      "tgn:1002446",
      "tgn:7007251",
      "tgn:7029392"
    ],
    "placetype": [
      "aat:300008347"
    ],
    "id": 2028172,
    "name:xx": "Hamilton"
  }
}
