{
  "type": "FeatureCollection",
  "features": [
    {
      "geometry": {
        "type": "Point",
        "coordinates": [
          -105.466667,
          20.283333
        ]
      },
      "type": "Feature",
      "properties": {
        "hierarchy": [
          "tgn:7374610",
          "tgn:7005586",
          "tgn:1000001",
          "tgn:7005560",
          "tgn:7029392"
        ],
        "placetype": [
          "aat:300266640"
        ],
        "id": 7374610,
        "name:xx": "Lagunillas, Sierra"
      }
    },
    {
      "geometry": {
        "type": "Point",
        "coordinates": [
          -104.266667,
          25.616667
        ]
      },
      "type": "Feature",
      "properties": {
        "hierarchy": [
          "tgn:7374611",
          "tgn:7005583",
          "tgn:1000001",
          "tgn:7005560",
          "tgn:7029392"
        ],
        "placetype": [
          "aat:300000241"
        ],
        "id": 7374611,
        "name:xx": "Rancho Lagunillas"
      }
    },
    {
      "geometry": {
        "type": "Point",
        "coordinates": [
          -103.45,
          26.833333
        ]
      },
      "type": "Feature",
      "properties": {
        "hierarchy": [
          "tgn:7374612",
          "tgn:1001853",
          "tgn:1000001",
          "tgn:7005560",
          "tgn:7029392"
        ],
        "placetype": [
          "aat:300008680"
        ],
        "id": 7374612,
        "name:xx": "Lagunillas, Lago"
      }
    },
    {
      "geometry": {
        "type": "Point",
        "coordinates": [
          -102.866667,
          20.766667
        ]
      },
      "type": "Feature",
      "properties": {
        "hierarchy": [
          "tgn:7374613",
          "tgn:7005586",
          "tgn:1000001",
          "tgn:7005560",
          "tgn:7029392"
        ],
        "placetype": [
          "aat:300006191"
        ],
        "id": 7374613,
        "name:xx": "Lagunillas"
      }
    },
    {
      "geometry": {
        "type": "Point",
        "coordinates": [
          -101.366667,
          19.55
        ]
      },
      "type": "Feature",
      "properties": {
        "hierarchy": [
          "tgn:7374614",
          "tgn:1000001",
          "tgn:7005590",
          "tgn:7005560",
          "tgn:7029392"
        ],
        "placetype": [
          "aat:300007783"
        ],
        "id": 7374614,
        "name:xx": "Lagunillas"
      }
    },
    {
      "geometry": {
        "type": "Point",
        "coordinates": [
          -98.483333,
          19.416667
        ]
      },
      "type": "Feature",
      "properties": {
        "hierarchy": [
          "tgn:7374615",
          "tgn:1000001",
          "tgn:7005598",
          "tgn:7005560",
          "tgn:7029392"
        ],
        "placetype": [
          "aat:300007783"
        ],
        "id": 7374615,
        "name:xx": "Lagunillas"
      }
    },
    {
      "geometry": {
        "type": "Point",
        "coordinates": [
          -102.85,
          20.866667
        ]
      },
      "type": "Feature",
      "properties": {
        "hierarchy": [
          "tgn:7374616",
          "tgn:7005586",
          "tgn:1000001",
          "tgn:7005560",
          "tgn:7029392"
        ],
        "placetype": [
          "aat:300000241"
        ],
        "id": 7374616,
        "name:xx": "Lagunillas"
      }
    },
    {
      "geometry": {
        "type": "Point",
        "coordinates": [
          -99.716667,
          26.3
        ]
      },
      "type": "Feature",
      "properties": {
        "hierarchy": [
          "tgn:7374617",
          "tgn:1000001",
          "tgn:7005589",
          "tgn:7005560",
          "tgn:7029392"
        ],
        "placetype": [
          "aat:300008347"
        ],
        "id": 7374617,
        "name:xx": "Lagunillas"
      }
    },
    {
      "geometry": {
        "type": "Point",
        "coordinates": [
          -111.566667,
          25.05
        ]
      },
      "type": "Feature",
      "properties": {
        "hierarchy": [
          "tgn:7374618",
          "tgn:1001836",
          "tgn:1000001",
          "tgn:7005560",
          "tgn:7029392"
        ],
        "placetype": [
          "aat:300008347"
        ],
        "id": 7374618,
        "name:xx": "Lagunillas"
      }
    },
    {
      "geometry": {
        "type": "Point",
        "coordinates": [
          -110.433333,
          24.033333
        ]
      },
      "type": "Feature",
      "properties": {
        "hierarchy": [
          "tgn:7374619",
          "tgn:1001836",
          "tgn:1000001",
          "tgn:7005560",
          "tgn:7029392"
        ],
        "placetype": [
          "aat:300008347"
        ],
        "id": 7374619,
        "name:xx": "Lagunillas"
      }
    }
  ]
}
