{
  "geometry": {
    "type": "Point",
    "coordinates": [
      9.833333,
      50.55
    ]
  },
  "type": "Feature",
  "properties": {
    "hierarchy": [
      "tgn:7066649",
      "tgn:1000003",
      "tgn:7003678",
      "tgn:7000084",
      "tgn:7029392"
    ],
    "placetype": [
      "aat:300000206"
    ],
    "id": 7066649,
    "name:xx": "Stöckeshof"
  }
}
