{
  "geometry": {
    "type": "Point",
    "coordinates": [
      116.25,
      -30.9667
    ]
  },
  "type": "Feature",
  "properties": {
    "hierarchy": [
      "tgn:1097764",
      "tgn:7000490",
      "tgn:1000006",
      "tgn:7001834",
      "tgn:7029392"
    ],
    "placetype": [
      "aat:300008347"
    ],
    "id": 1097764,
    "name:xx": "New Norcia"
  }
}
