{
  "geometry": {
    "type": "Point",
    "coordinates": [
      -100.25,
      32.5833
    ]
  },
  "type": "Feature",
  "properties": {
    "hierarchy": [
      "tgn:2608990",
      "tgn:1000001",
      "tgn:7012149",
      "tgn:7007826",
      "tgn:7029392"
    ],
    "placetype": [
      "aat:300008706"
    ],
    "id": 2608990,
    "name:xx": "Raven Creek"
  }
}
