{
  "geometry": {
    "type": "Point",
    "coordinates": [
      -107.1833,
      32.3167
    ]
  },
  "type": "Feature",
  "properties": {
    "hierarchy": [
      "tgn:2419032",
      "tgn:1000001",
      "tgn:2001435",
      "tgn:7012149",
      "tgn:7007566",
      "tgn:7029392"
    ],
    "placetype": [
      "aat:300006191"
    ],
    "id": 2419032,
    "name:xx": "James Tank"
  }
}
