{
  "geometry": {
    "type": "Point",
    "coordinates": [
      -82.15,
      36.9833
    ]
  },
  "type": "Feature",
  "properties": {
    "hierarchy": [
      "tgn:2366919",
      "tgn:1000001",
      "tgn:7012149",
      "tgn:2002188",
      "tgn:7007919",
      "tgn:7029392"
    ],
    "placetype": [
      "aat:300008347"
    ],
    "id": 2366919,
    "name:xx": "Grizzle"
  }
}
