{
  "type": "FeatureCollection",
  "features": [
    {
      "geometry": {
        "type": "Point",
        "coordinates": [
          -81.3333,
          27.2333
        ]
      },
      "type": "Feature",
      "properties": {
        "hierarchy": [
          "tgn:2202120",
          "tgn:1000001",
          "tgn:1002477",
          "tgn:7012149",
          "tgn:7007240",
          "tgn:7029392"
        ],
        "placetype": [
          "aat:300008680"
        ],
        "id": 2202120,
        "name:xx": "Buck Lake"
      }
    },
    {
      "geometry": {
        "type": "Point",
        "coordinates": [
          -82.6167,
          28.1
        ]
      },
      "type": "Feature",
      "properties": {
        "hierarchy": [
          "tgn:2202121",
          "tgn:1000001",
          "tgn:1002479",
          "tgn:7012149",
          "tgn:7007240",
          "tgn:7029392"
        ],
        "placetype": [
          "aat:300008680"
        ],
        "id": 2202121,
        "name:xx": "Buck Lake"
      }
    },
    {
      "geometry": {
        "type": "Point",
        "coordinates": [
          -81.15,
          28.2
        ]
      },
      "type": "Feature",
      "properties": {
        "hierarchy": [
          "tgn:2202122",
          "tgn:1000001",
          "tgn:7012149",
          "tgn:1002756",
          "tgn:7007240",
          "tgn:7029392"
        ],
        "placetype": [
          "aat:300008680"
        ],
        "id": 2202122,
        "name:xx": "Buck Lake"
      }
    },
    {
      "geometry": {
        "type": "Point",
        "coordinates": [
          -82.3167,
          28.65
        ]
      },
      "type": "Feature",
      "properties": {
        "hierarchy": [
          "tgn:2202123",
          "tgn:1000001",
          "tgn:1002473",
          "tgn:7012149",
          "tgn:7007240",
          "tgn:7029392"
        ],
        "placetype": [
          "aat:300008680"
        ],
        "id": 2202123,
        "name:xx": "Buck Lake"
      }
    },
    {
      "geometry": {
        "type": "Point",
        "coordinates": [
          -80.95,
          28.6833
        ]
      },
      "type": "Feature",
      "properties": {
        "hierarchy": [
          "tgn:2202124",
          "tgn:1000001",
          "tgn:1002200",
          "tgn:7012149",
          "tgn:7007240",
          "tgn:7029392"
        ],
        "placetype": [
          "aat:300008680"
        ],
        "id": 2202124,
        "name:xx": "Buck Lake"
      }
    },
    {
      "geometry": {
        "type": "Point",
        "coordinates": [
          -81.4333,
          28.9667
        ]
      },
      "type": "Feature",
      "properties": {
        "hierarchy": [
          "tgn:2202125",
          "tgn:1000001",
          "tgn:7012149",
          "tgn:1002567",
          "tgn:7007240",
          "tgn:7029392"
        ],
        "placetype": [
          "aat:300008680"
        ],
        "id": 2202125,
        "name:xx": "Buck Lake"
      }
    },
    {
      "geometry": {
        "type": "Point",
        "coordinates": [
          -82.5167,
          29.0833
        ]
      },
      "type": "Feature",
      "properties": {
        "hierarchy": [
          "tgn:2202126",
          "tgn:1000001",
          "tgn:7012149",
          "tgn:1002631",
          "tgn:7007240",
          "tgn:7029392"
        ],
        "placetype": [
          "aat:300008680"
        ],
        "id": 2202126,
        "name:xx": "Buck Lake"
      }
    },
    {
      "geometry": {
        "type": "Point",
        "coordinates": [
          -84.2,
          30.45
        ]
      },
      "type": "Feature",
      "properties": {
        "hierarchy": [
          "tgn:2202127",
          "tgn:1000001",
          "tgn:7012149",
          "tgn:2000276",
          "tgn:7007240",
          "tgn:7029392"
        ],
        "placetype": [
          "aat:300008680"
        ],
        "id": 2202127,
        "name:xx": "Buck Lake"
      }
    },
    {
      "geometry": {
        "type": "Point",
        "coordinates": [
          -81.2333,
          28.4
        ]
      },
      "type": "Feature",
      "properties": {
        "hierarchy": [
          "tgn:2202128",
          "tgn:1000001",
          "tgn:7012149",
          "tgn:1002749",
          "tgn:7007240",
          "tgn:7029392"
        ],
        "placetype": [
          "aat:300008680"
        ],
        "id": 2202128,
        "name:xx": "Buck Lake"
      }
    },
    {
      "geometry": {
        "type": "Point",
        "coordinates": [
          -81.1167,
          28.7167
        ]
      },
      "type": "Feature",
      "properties": {
        "hierarchy": [
          "tgn:2202129",
          "tgn:1000001",
          "tgn:7012149",
          "tgn:1002881",
          "tgn:7007240",
          "tgn:7029392"
        ],
        "placetype": [
          "aat:300008680"
        ],
        "id": 2202129,
        "name:xx": "Buck Lake"
      }
    }
  ]
}
