{
  "type": "FeatureCollection",
  "features": [
    {
      "geometry": {
        "type": "Point",
        "coordinates": [
          -83,
          42.35
        ]
      },
      "type": "Feature",
      "properties": {
        "hierarchy": [
          "tgn:2051712",
          "tgn:7013547",
          "tgn:1000001",
          "tgn:7012149",
          "tgn:1003005",
          "tgn:7007520",
          "tgn:7029392"
        ],
        "placetype": [
          "aat:300266755"
        ],
        "id": 2051712,
        "name:xx": "Mount Elliott"
      }
    },
    {
      "geometry": {
        "type": "Point",
        "coordinates": [
          -83.2333,
          42.3667
        ]
      },
      "type": "Feature",
      "properties": {
        "hierarchy": [
          "tgn:2051715",
          "tgn:7013547",
          "tgn:1000001",
          "tgn:7012149",
          "tgn:1003005",
          "tgn:7007520",
          "tgn:7029392"
        ],
        "placetype": [
          "aat:300387331"
        ],
        "id": 2051715,
        "name:xx": "Oak"
      }
    }
  ]
}
