{
  "geometry": {
    "type": "Point",
    "coordinates": [
      -94.8333,
      37.0833
    ]
  },
  "type": "Feature",
  "properties": {
    "hierarchy": [
      "tgn:2174712",
      "tgn:1000001",
      "tgn:2000670",
      "tgn:7012149",
      "tgn:7007254",
      "tgn:7029392"
    ],
    "placetype": [
      "aat:300008706"
    ],
    "id": 2174712,
    "name:xx": "Bitter Creek"
  }
}
