{
  "geometry": {
    "type": "Point",
    "coordinates": [
      -79.25,
      41.2333
    ]
  },
  "type": "Feature",
  "properties": {
    "hierarchy": [
      "tgn:2782039",
      "tgn:1000001",
      "tgn:1002272",
      "tgn:7012149",
      "tgn:7007710",
      "tgn:7029392"
    ],
    "placetype": [
      "aat:300008699"
    ],
    "id": 2782039,
    "name:xx": "Woods Run"
  }
}
