{
  "type": "FeatureCollection",
  "features": [
    {
      "geometry": {
        "type": "Point",
        "coordinates": [
          -83.9833,
          44.1833
        ]
      },
      "type": "Feature",
      "properties": {
        "hierarchy": [
          "tgn:2528900",
          "tgn:1000001",
          "tgn:7012149",
          "tgn:2000985",
          "tgn:7007520",
          "tgn:7029392"
        ],
        "placetype": [
          "aat:300008706"
        ],
        "id": 2528900,
        "name:xx": "Mud Creek"
      }
    },
    {
      "geometry": {
        "type": "Point",
        "coordinates": [
          -84.7833,
          45.35
        ]
      },
      "type": "Feature",
      "properties": {
        "hierarchy": [
          "tgn:2528901",
          "tgn:1000001",
          "tgn:2000958",
          "tgn:7012149",
          "tgn:7007520",
          "tgn:7029392"
        ],
        "placetype": [
          "aat:300008706"
        ],
        "id": 2528901,
        "name:xx": "Mud Creek"
      }
    },
    {
      "geometry": {
        "type": "Point",
        "coordinates": [
          -84.95,
          46.1167
        ]
      },
      "type": "Feature",
      "properties": {
        "hierarchy": [
          "tgn:2528902",
          "tgn:1000001",
          "tgn:7012149",
          "tgn:2000973",
          "tgn:7007520",
          "tgn:7029392"
        ],
        "placetype": [
          "aat:300008706"
        ],
        "id": 2528902,
        "name:xx": "Mud Creek"
      }
    },
    {
      "geometry": {
        "type": "Point",
        "coordinates": [
          -90.15,
          46.5333
        ]
      },
      "type": "Feature",
      "properties": {
        "hierarchy": [
          "tgn:2528903",
          "tgn:1000001",
          "tgn:7012149",
          "tgn:2000960",
          "tgn:7007520",
          "tgn:7029392"
        ],
        "placetype": [
          "aat:300008706"
        ],
        "id": 2528903,
        "name:xx": "Mud Creek"
      }
    },
    {
      "geometry": {
        "type": "Point",
        "coordinates": [
          -88.1167,
          47.4333
        ]
      },
      "type": "Feature",
      "properties": {
        "hierarchy": [
          "tgn:2528904",
          "tgn:1000001",
          "tgn:7012149",
          "tgn:2000969",
          "tgn:7007520",
          "tgn:7029392"
        ],
        "placetype": [
          "aat:300008706"
        ],
        "id": 2528904,
        "name:xx": "Mud Creek"
      }
    },
    {
      "geometry": {
        "type": "Point",
        "coordinates": [
          -84.45,
          43.8167
        ]
      },
      "type": "Feature",
      "properties": {
        "hierarchy": [
          "tgn:2528905",
          "tgn:1000001",
          "tgn:7012149",
          "tgn:2000979",
          "tgn:7007520",
          "tgn:7029392"
        ],
        "placetype": [
          "aat:300008706"
        ],
        "id": 2528905,
        "name:xx": "Mud Creek"
      }
    },
    {
      "geometry": {
        "type": "Point",
        "coordinates": [
          -93.1167,
          43.8167
        ]
      },
      "type": "Feature",
      "properties": {
        "hierarchy": [
          "tgn:2528906",
          "tgn:1000001",
          "tgn:2001022",
          "tgn:7012149",
          "tgn:7007521",
          "tgn:7029392"
        ],
        "placetype": [
          "aat:300008706"
        ],
        "id": 2528906,
        "name:xx": "Mud Creek"
      }
    },
    {
      "geometry": {
        "type": "Point",
        "coordinates": [
          -90.3333,
          47.8667
        ]
      },
      "type": "Feature",
      "properties": {
        "hierarchy": [
          "tgn:2528907",
          "tgn:1000001",
          "tgn:2001014",
          "tgn:7012149",
          "tgn:7007521",
          "tgn:7029392"
        ],
        "placetype": [
          "aat:300008706"
        ],
        "id": 2528907,
        "name:xx": "Mud Creek"
      }
    },
    {
      "geometry": {
        "type": "Point",
        "coordinates": [
          -92.05,
          47.8833
        ]
      },
      "type": "Feature",
      "properties": {
        "hierarchy": [
          "tgn:2528908",
          "tgn:1000001",
          "tgn:7012149",
          "tgn:2001067",
          "tgn:7007521",
          "tgn:7029392"
        ],
        "placetype": [
          "aat:300008706"
        ],
        "id": 2528908,
        "name:xx": "Mud Creek"
      }
    },
    {
      "geometry": {
        "type": "Point",
        "coordinates": [
          -93.3167,
          44.15
        ]
      },
      "type": "Feature",
      "properties": {
        "hierarchy": [
          "tgn:2528909",
          "tgn:1000001",
          "tgn:7012149",
          "tgn:7007521",
          "tgn:7029392"
        ],
        "placetype": [
          "aat:300008706"
        ],
        "id": 2528909,
        "name:xx": "Mud Creek"
      }
    }
  ]
}
