{
  "geometry": {
    "type": "Point",
    "coordinates": [
      -78.15,
      36.0833
    ]
  },
  "type": "Feature",
  "properties": {
    "hierarchy": [
      "tgn:2690552",
      "tgn:1000001",
      "tgn:7012149",
      "tgn:7013940",
      "tgn:7007709",
      "tgn:7029392"
    ],
    "placetype": [
      "aat:300008347"
    ],
    "id": 2690552,
    "name:xx": "Stallings Crossroads"
  }
}
