{
  "geometry": {
    "type": "Point",
    "coordinates": [
      -119.6167,
      37.0667
    ]
  },
  "type": "Feature",
  "properties": {
    "hierarchy": [
      "tgn:2267786",
      "tgn:1000001",
      "tgn:7012149",
      "tgn:7007157",
      "tgn:1002621",
      "tgn:7029392"
    ],
    "placetype": [
      "aat:300008798"
    ],
    "id": 2267786,
    "name:xx": "Crook Mountain"
  }
}
