{
  "geometry": {
    "type": "Point",
    "coordinates": [
      79.204157,
      24.740176
    ]
  },
  "type": "Feature",
  "properties": {
    "hierarchy": [
      "tgn:7565540",
      "tgn:1000004",
      "tgn:7000198",
      "tgn:1001894",
      "tgn:7029392"
    ],
    "placetype": [
      "aat:300008347"
    ],
    "name:en": "Monemāto ka Khero",
    "id": 7565540
  }
}
