{
  "geometry": {
    "type": "Point",
    "coordinates": [
      -122.9667,
      39.6833
    ]
  },
  "type": "Feature",
  "properties": {
    "hierarchy": [
      "tgn:2288004",
      "tgn:1000001",
      "tgn:7012149",
      "tgn:7007157",
      "tgn:2000185",
      "tgn:7029392"
    ],
    "placetype": [
      "aat:300008706"
    ],
    "id": 2288004,
    "name:xx": "Dingman Creek"
  }
}
