{
  "type": "FeatureCollection",
  "features": [
    {
      "geometry": {
        "type": "Point",
        "coordinates": [
          98.9167,
          41.3333
        ]
      },
      "type": "Feature",
      "properties": {
        "hierarchy": [
          "tgn:1108820",
          "tgn:1000004",
          "tgn:7001838",
          "tgn:1000111",
          "tgn:7029392"
        ],
        "placetype": [
          "aat:300008795"
        ],
        "id": 1108820,
        "name:xx": "Bor Ul Shan"
      }
    },
    {
      "geometry": {
        "type": "Point",
        "coordinates": [
          117,
          52
        ]
      },
      "type": "Feature",
      "properties": {
        "hierarchy": [
          "tgn:1108821",
          "tgn:1003351",
          "tgn:1000004",
          "tgn:7018214",
          "tgn:7002435",
          "tgn:7029392"
        ],
        "placetype": [
          "aat:300008795"
        ],
        "id": 1108821,
        "name:xx": "Borshchovochnyy Khrebet"
      }
    },
    {
      "geometry": {
        "type": "Point",
        "coordinates": [
          141.0833,
          -3.6667
        ]
      },
      "type": "Feature",
      "properties": {
        "hierarchy": [
          "tgn:1108822",
          "tgn:1000004",
          "tgn:7029392"
        ],
        "placetype": [
          "aat:300386831"
        ],
        "id": 1108822,
        "name:xx": "Border Mountains"
      }
    },
    {
      "geometry": {
        "type": "Point",
        "coordinates": [
          83.1667,
          44.0833
        ]
      },
      "type": "Feature",
      "properties": {
        "hierarchy": [
          "tgn:1108823",
          "tgn:1000004",
          "tgn:7001745",
          "tgn:1000111",
          "tgn:7029392"
        ],
        "placetype": [
          "aat:300008795"
        ],
        "id": 1108823,
        "name:xx": "Borohoro Shan"
      }
    },
    {
      "geometry": {
        "type": "Point",
        "coordinates": [
          -93.3333,
          35.7
        ]
      },
      "type": "Feature",
      "properties": {
        "hierarchy": [
          "tgn:1108824",
          "tgn:1000001",
          "tgn:7016172",
          "tgn:7012149",
          "tgn:7029392"
        ],
        "placetype": [
          "aat:300008795"
        ],
        "id": 1108824,
        "name:xx": "Boston Mountains"
      }
    },
    {
      "geometry": {
        "type": "Point",
        "coordinates": [
          1.122549,
          42.232249
        ]
      },
      "type": "Feature",
      "properties": {
        "hierarchy": [
          "tgn:1108825",
          "tgn:7008912",
          "tgn:7030216",
          "tgn:1000003",
          "tgn:1000095",
          "tgn:7029392"
        ],
        "placetype": [
          "aat:300386831",
          "aat:300008795"
        ],
        "id": 1108825,
        "name:xx": "Boumort, Sierra de"
      }
    }
  ]
}
