{
  "type": "FeatureCollection",
  "features": [
    {
      "geometry": {
        "type": "Point",
        "coordinates": [
          31.062208,
          31.003263
        ]
      },
      "type": "Feature",
      "properties": {
        "hierarchy": [
          "tgn:7530980",
          "tgn:7001242",
          "tgn:7016833",
          "tgn:7001312",
          "tgn:7029392"
        ],
        "placetype": [
          "aat:300006075"
        ],
        "name:en": "Tir'at Nishīl",
        "id": 7530980
      }
    },
    {
      "geometry": {
        "type": "Point",
        "coordinates": [
          31.16353,
          31.041788
        ]
      },
      "type": "Feature",
      "properties": {
        "hierarchy": [
          "tgn:7530981",
          "tgn:7001242",
          "tgn:7016833",
          "tgn:7001312",
          "tgn:7029392"
        ],
        "placetype": [
          "aat:300000206"
        ],
        "name:en": "'Izbat al Manshīyah",
        "id": 7530981
      }
    },
    {
      "geometry": {
        "type": "Point",
        "coordinates": [
          31.163639,
          30.993068
        ]
      },
      "type": "Feature",
      "properties": {
        "hierarchy": [
          "tgn:7530982",
          "tgn:7001242",
          "tgn:7016833",
          "tgn:7001312",
          "tgn:7029392"
        ],
        "placetype": [
          "aat:300006075"
        ],
        "name:en": "Tir'at Mīt al Layt",
        "id": 7530982
      }
    },
    {
      "geometry": {
        "type": "Point",
        "coordinates": [
          31.142699,
          31.03725
        ]
      },
      "type": "Feature",
      "properties": {
        "hierarchy": [
          "tgn:7530983",
          "tgn:7001242",
          "tgn:7016833",
          "tgn:7001312",
          "tgn:7029392"
        ],
        "placetype": [
          "aat:300000206"
        ],
        "name:en": "'Izbat al Khazzān",
        "id": 7530983
      }
    },
    {
      "geometry": {
        "type": "Point",
        "coordinates": [
          31.022787,
          31.035841
        ]
      },
      "type": "Feature",
      "properties": {
        "hierarchy": [
          "tgn:7530984",
          "tgn:7001242",
          "tgn:7016833",
          "tgn:1001335",
          "tgn:7029392"
        ],
        "placetype": [
          "aat:300000206"
        ],
        "name:en": "'Izbat 'Abbās 'Ābdīn",
        "id": 7530984
      }
    },
    {
      "geometry": {
        "type": "Point",
        "coordinates": [
          31.008375,
          31.033908
        ]
      },
      "type": "Feature",
      "properties": {
        "hierarchy": [
          "tgn:7530985",
          "tgn:7001242",
          "tgn:7016833",
          "tgn:1001335",
          "tgn:7029392"
        ],
        "placetype": [
          "aat:300008347"
        ],
        "name:en": "'Izbat 'Abd Allāh Abū as Sayyid",
        "id": 7530985
      }
    },
    {
      "geometry": {
        "type": "Point",
        "coordinates": [
          31.170957,
          31.035283
        ]
      },
      "type": "Feature",
      "properties": {
        "hierarchy": [
          "tgn:7530986",
          "tgn:7001242",
          "tgn:7016833",
          "tgn:7001312",
          "tgn:7029392"
        ],
        "placetype": [
          "aat:300008347"
        ],
        "name:en": "Manshīyat al Umarā'",
        "id": 7530986
      }
    },
    {
      "geometry": {
        "type": "Point",
        "coordinates": [
          31.067307,
          31.032072
        ]
      },
      "type": "Feature",
      "properties": {
        "hierarchy": [
          "tgn:7530987",
          "tgn:7001242",
          "tgn:7016833",
          "tgn:7001312",
          "tgn:7029392"
        ],
        "placetype": [
          "aat:300000206"
        ],
        "name:en": "'Izbat al Işlāḩ",
        "id": 7530987
      }
    },
    {
      "geometry": {
        "type": "Point",
        "coordinates": [
          31.116521,
          31.029448
        ]
      },
      "type": "Feature",
      "properties": {
        "hierarchy": [
          "tgn:7530988",
          "tgn:7001242",
          "tgn:7016833",
          "tgn:7001312",
          "tgn:7029392"
        ],
        "placetype": [
          "aat:300000206"
        ],
        "name:en": "'Izbat Umm Sittīn",
        "id": 7530988
      }
    },
    {
      "geometry": {
        "type": "Point",
        "coordinates": [
          31.011536,
          31.027962
        ]
      },
      "type": "Feature",
      "properties": {
        "hierarchy": [
          "tgn:7530989",
          "tgn:7001242",
          "tgn:7016833",
          "tgn:7001312",
          "tgn:7029392"
        ],
        "placetype": [
          "aat:300000206"
        ],
        "name:en": "'Izbat Ghāzī",
        "id": 7530989
      }
    }
  ]
}
