{
  "geometry": {
    "type": "Point",
    "coordinates": [
      11.8667,
      55.95
    ]
  },
  "type": "Feature",
  "properties": {
    "hierarchy": [
      "tgn:1028008",
      "tgn:7594005",
      "tgn:1000003",
      "tgn:1000066",
      "tgn:7029392"
    ],
    "placetype": [
      "aat:300008347"
    ],
    "id": 1028008,
    "name:xx": "Lynæs"
  }
}
