{
  "geometry": {
    "type": "Point",
    "coordinates": [
      -80.9333,
      26.75
    ]
  },
  "type": "Feature",
  "properties": {
    "hierarchy": [
      "tgn:2018931",
      "tgn:1000001",
      "tgn:1002466",
      "tgn:7012149",
      "tgn:7007240",
      "tgn:7029392"
    ],
    "placetype": [
      "aat:300008347"
    ],
    "id": 2018931,
    "name:xx": "Clewiston"
  }
}
