{
  "geometry": {
    "type": "Point",
    "coordinates": [
      29.55,
      39.2667
    ]
  },
  "type": "Feature",
  "properties": {
    "hierarchy": [
      "tgn:7002309",
      "tgn:7001298",
      "tgn:1000004",
      "tgn:7018451",
      "tgn:1000144",
      "tgn:7029392"
    ],
    "placetype": [
      "aat:300008347",
      "aat:300000810"
    ],
    "id": 7002309,
    "name:xx": "Orencik"
  }
}
