{
  "geometry": {
    "type": "Point",
    "coordinates": [
      79.125389,
      24.900946
    ]
  },
  "type": "Feature",
  "properties": {
    "hierarchy": [
      "tgn:7564930",
      "tgn:1000004",
      "tgn:7000198",
      "tgn:1001894",
      "tgn:7029392"
    ],
    "placetype": [
      "aat:300008777"
    ],
    "name:en": "Hingāi Pahār",
    "id": 7564930
  }
}
