{
  "type": "FeatureCollection",
  "features": [
    {
      "geometry": {
        "type": "Point",
        "coordinates": [
          1.8333,
          46.3333
        ]
      },
      "type": "Feature",
      "properties": {
        "hierarchy": [
          "tgn:4002581",
          "tgn:1000003",
          "tgn:7001095",
          "tgn:1000070",
          "tgn:7029392"
        ],
        "placetype": [
          "aat:300008347"
        ],
        "id": 4002581,
        "name:xx": "Chéniers"
      }
    },
    {
      "geometry": {
        "type": "Point",
        "coordinates": [
          0.3333,
          47.6167
        ]
      },
      "type": "Feature",
      "properties": {
        "hierarchy": [
          "tgn:4002584",
          "tgn:1000003",
          "tgn:7002893",
          "tgn:1000070",
          "tgn:7029392"
        ],
        "placetype": [
          "aat:300008347"
        ],
        "id": 4002584,
        "name:xx": "Chenu"
      }
    }
  ]
}
