{
  "geometry": {
    "type": "Point",
    "coordinates": [
      -91.8333,
      38.3167
    ]
  },
  "type": "Feature",
  "properties": {
    "hierarchy": [
      "tgn:2273987",
      "tgn:1000001",
      "tgn:7012149",
      "tgn:1002755",
      "tgn:7007523",
      "tgn:7029392"
    ],
    "placetype": [
      "aat:300008347"
    ],
    "id": 2273987,
    "name:xx": "Daggetts Ford"
  }
}
