{
  "geometry": {
    "type": "Point",
    "coordinates": [
      -122.9833,
      45.3667
    ]
  },
  "type": "Feature",
  "properties": {
    "hierarchy": [
      "tgn:2203096",
      "tgn:1000001",
      "tgn:7012149",
      "tgn:1002994",
      "tgn:7007708",
      "tgn:7029392"
    ],
    "placetype": [
      "aat:300008347"
    ],
    "id": 2203096,
    "name:xx": "Buckheaven"
  }
}
