{
  "geometry": {
    "type": "Point",
    "coordinates": [
      -121.0333,
      39.5167
    ]
  },
  "type": "Feature",
  "properties": {
    "hierarchy": [
      "tgn:2199107",
      "tgn:1000001",
      "tgn:7012149",
      "tgn:7007157",
      "tgn:7029392"
    ],
    "placetype": [
      "aat:300008761"
    ],
    "id": 2199107,
    "name:xx": "Brummel Ravine"
  }
}
