{
  "type": "FeatureCollection",
  "features": [
    {
      "geometry": {
        "type": "Point",
        "coordinates": [
          10.266667,
          49.4
        ]
      },
      "type": "Feature",
      "properties": {
        "hierarchy": [
          "tgn:7104990",
          "tgn:7003669",
          "tgn:1000003",
          "tgn:7000084",
          "tgn:7029392"
        ],
        "placetype": [
          "aat:300008777"
        ],
        "id": 7104990,
        "name:xx": "Schloßberg"
      }
    },
    {
      "geometry": {
        "type": "Point",
        "coordinates": [
          8.166667,
          49.4
        ]
      },
      "type": "Feature",
      "properties": {
        "hierarchy": [
          "tgn:7104992",
          "tgn:1000003",
          "tgn:7003682",
          "tgn:7000084",
          "tgn:7029392"
        ],
        "placetype": [
          "aat:300008777"
        ],
        "id": 7104992,
        "name:xx": "Schloß-Berg"
      }
    },
    {
      "geometry": {
        "type": "Point",
        "coordinates": [
          7.366667,
          49.316667
        ]
      },
      "type": "Feature",
      "properties": {
        "hierarchy": [
          "tgn:7104994",
          "tgn:1000003",
          "tgn:7003684",
          "tgn:7000084",
          "tgn:7029392"
        ],
        "placetype": [
          "aat:300008777"
        ],
        "id": 7104994,
        "name:xx": "Schloß-Berg"
      }
    },
    {
      "geometry": {
        "type": "Point",
        "coordinates": [
          6.683333,
          49.3
        ]
      },
      "type": "Feature",
      "properties": {
        "hierarchy": [
          "tgn:7104995",
          "tgn:1000003",
          "tgn:7003684",
          "tgn:7000084",
          "tgn:7029392"
        ],
        "placetype": [
          "aat:300008777"
        ],
        "id": 7104995,
        "name:xx": "Schloß-Berg"
      }
    },
    {
      "geometry": {
        "type": "Point",
        "coordinates": [
          8.266667,
          49.266667
        ]
      },
      "type": "Feature",
      "properties": {
        "hierarchy": [
          "tgn:7104996",
          "tgn:1000003",
          "tgn:7003682",
          "tgn:7000084",
          "tgn:7029392"
        ],
        "placetype": [
          "aat:300008777"
        ],
        "id": 7104996,
        "name:xx": "Schloßberg"
      }
    },
    {
      "geometry": {
        "type": "Point",
        "coordinates": [
          10.533333,
          49.25
        ]
      },
      "type": "Feature",
      "properties": {
        "hierarchy": [
          "tgn:7104997",
          "tgn:7003669",
          "tgn:1000003",
          "tgn:7000084",
          "tgn:7029392"
        ],
        "placetype": [
          "aat:300008777"
        ],
        "id": 7104997,
        "name:xx": "Schloßberg"
      }
    },
    {
      "geometry": {
        "type": "Point",
        "coordinates": [
          11.65,
          49.233333
        ]
      },
      "type": "Feature",
      "properties": {
        "hierarchy": [
          "tgn:7104998",
          "tgn:7003669",
          "tgn:1000003",
          "tgn:7000084",
          "tgn:7029392"
        ],
        "placetype": [
          "aat:300008777"
        ],
        "id": 7104998,
        "name:xx": "Schloßberg"
      }
    },
    {
      "geometry": {
        "type": "Point",
        "coordinates": [
          7.866667,
          49.216667
        ]
      },
      "type": "Feature",
      "properties": {
        "hierarchy": [
          "tgn:7104999",
          "tgn:1000003",
          "tgn:7003682",
          "tgn:7000084",
          "tgn:7029392"
        ],
        "placetype": [
          "aat:300008777"
        ],
        "id": 7104999,
        "name:xx": "Schloß-Berg"
      }
    }
  ]
}
