{
  "type": "FeatureCollection",
  "features": [
    {
      "geometry": {
        "type": "Point",
        "coordinates": [
          14.633333,
          40.7
        ]
      },
      "type": "Feature",
      "properties": {
        "hierarchy": [
          "tgn:7054721",
          "tgn:7003005",
          "tgn:7003014",
          "tgn:1000003",
          "tgn:1000080",
          "tgn:7029392"
        ],
        "placetype": [
          "aat:300008347"
        ],
        "id": 7054721,
        "name:xx": "Polvica"
      }
    },
    {
      "geometry": {
        "type": "Point",
        "coordinates": [
          16.416667,
          38.966667
        ]
      },
      "type": "Feature",
      "properties": {
        "hierarchy": [
          "tgn:7054723",
          "tgn:1003447",
          "tgn:7007850",
          "tgn:1000003",
          "tgn:1000080",
          "tgn:7029392"
        ],
        "placetype": [
          "aat:300008347"
        ],
        "id": 7054723,
        "name:xx": "Polverini"
      }
    },
    {
      "geometry": {
        "type": "Point",
        "coordinates": [
          13.116667,
          42.733333
        ]
      },
      "type": "Feature",
      "properties": {
        "hierarchy": [
          "tgn:7054725",
          "tgn:7003170",
          "tgn:1000003",
          "tgn:7003125",
          "tgn:1000080",
          "tgn:7029392"
        ],
        "placetype": [
          "aat:300008347"
        ],
        "id": 7054725,
        "name:xx": "Paganelli"
      }
    },
    {
      "geometry": {
        "type": "Point",
        "coordinates": [
          9.233333,
          44.333333
        ]
      },
      "type": "Feature",
      "properties": {
        "hierarchy": [
          "tgn:7054727",
          "tgn:1000003",
          "tgn:7003236",
          "tgn:1000080",
          "tgn:7029392"
        ],
        "placetype": [
          "aat:300386846"
        ],
        "id": 7054727,
        "name:xx": "Pagana, Punta"
      }
    },
    {
      "geometry": {
        "type": "Point",
        "coordinates": [
          10.9,
          42.35
        ]
      },
      "type": "Feature",
      "properties": {
        "hierarchy": [
          "tgn:7054728",
          "tgn:1003460",
          "tgn:1000003",
          "tgn:7009760",
          "tgn:1000080",
          "tgn:7029392"
        ],
        "placetype": [
          "aat:300008795"
        ],
        "id": 7054728,
        "name:xx": "Pagana, Poggio della"
      }
    },
    {
      "geometry": {
        "type": "Point",
        "coordinates": [
          15,
          40.416667
        ]
      },
      "type": "Feature",
      "properties": {
        "hierarchy": [
          "tgn:7054729",
          "tgn:7003005",
          "tgn:7003014",
          "tgn:1000003",
          "tgn:1000080",
          "tgn:7029392"
        ],
        "placetype": [
          "aat:300007783"
        ],
        "id": 7054729,
        "name:xx": "Stazione di Paestum"
      }
    }
  ]
}
