{
  "geometry": {
    "type": "Point",
    "coordinates": [
      -6.0833,
      13.7333
    ]
  },
  "type": "Feature",
  "properties": {
    "hierarchy": [
      "tgn:1136064",
      "tgn:7001242",
      "tgn:1000175",
      "tgn:7029392"
    ],
    "placetype": [
      "aat:300006075"
    ],
    "id": 1136064,
    "name:xx": "Sahel, Canal du"
  }
}
