{
  "type": "FeatureCollection",
  "features": [
    {
      "geometry": {
        "type": "Point",
        "coordinates": [
          -78.0167,
          40.5333
        ]
      },
      "type": "Feature",
      "properties": {
        "hierarchy": [
          "tgn:2094191",
          "tgn:1000001",
          "tgn:7012149",
          "tgn:1002494",
          "tgn:7007710",
          "tgn:7029392"
        ],
        "placetype": [
          "aat:300008347",
          "aat:300387210"
        ],
        "id": 2094191,
        "name:xx": "Warrior Ridge"
      }
    },
    {
      "geometry": {
        "type": "Point",
        "coordinates": [
          -75.95,
          41.1833
        ]
      },
      "type": "Feature",
      "properties": {
        "hierarchy": [
          "tgn:2094192",
          "tgn:1000001",
          "tgn:7012149",
          "tgn:1002612",
          "tgn:7007710",
          "tgn:7029392"
        ],
        "placetype": [
          "aat:300008347"
        ],
        "id": 2094192,
        "name:xx": "Warrior Run"
      }
    },
    {
      "geometry": {
        "type": "Point",
        "coordinates": [
          -78.1167,
          40.7
        ]
      },
      "type": "Feature",
      "properties": {
        "hierarchy": [
          "tgn:2094193",
          "tgn:1000001",
          "tgn:7012149",
          "tgn:1002494",
          "tgn:7007710",
          "tgn:7029392"
        ],
        "placetype": [
          "aat:300008347"
        ],
        "id": 2094193,
        "name:xx": "Warriors Mark"
      }
    },
    {
      "geometry": {
        "type": "Point",
        "coordinates": [
          -75.7833,
          40.15
        ]
      },
      "type": "Feature",
      "properties": {
        "hierarchy": [
          "tgn:2094194",
          "tgn:1000001",
          "tgn:1002266",
          "tgn:7012149",
          "tgn:7007710",
          "tgn:7029392"
        ],
        "placetype": [
          "aat:300008347"
        ],
        "id": 2094194,
        "name:xx": "Warwick"
      }
    },
    {
      "geometry": {
        "type": "Point",
        "coordinates": [
          -76.4667,
          39.9833
        ]
      },
      "type": "Feature",
      "properties": {
        "hierarchy": [
          "tgn:2094199",
          "tgn:1000001",
          "tgn:7012149",
          "tgn:7013867",
          "tgn:7007710",
          "tgn:7029392"
        ],
        "placetype": [
          "aat:300008347"
        ],
        "id": 2094199,
        "name:xx": "Washington Boro"
      }
    }
  ]
}
