{
  "geometry": {
    "type": "Point",
    "coordinates": [
      13.35,
      54.55
    ]
  },
  "type": "Feature",
  "properties": {
    "hierarchy": [
      "tgn:7071078",
      "tgn:1000003",
      "tgn:7000094",
      "tgn:7000084",
      "tgn:7029392"
    ],
    "placetype": [
      "aat:300008347"
    ],
    "id": 7071078,
    "name:xx": "Sylvin"
  }
}
