{
  "geometry": {
    "type": "Point",
    "coordinates": [
      -113.2333,
      46.0667
    ]
  },
  "type": "Feature",
  "properties": {
    "hierarchy": [
      "tgn:2697796",
      "tgn:1000001",
      "tgn:7012149",
      "tgn:7020792",
      "tgn:7007524",
      "tgn:7029392"
    ],
    "placetype": [
      "aat:300008706"
    ],
    "id": 2697796,
    "name:xx": "Storm Lake Creek"
  }
}
