{
  "geometry": {
    "type": "Point",
    "coordinates": [
      -83.9667,
      41.5333
    ]
  },
  "type": "Feature",
  "properties": {
    "hierarchy": [
      "tgn:2572289",
      "tgn:1000001",
      "tgn:7012149",
      "tgn:1002398",
      "tgn:7007706",
      "tgn:7029392"
    ],
    "placetype": [
      "aat:300008347"
    ],
    "id": 2572289,
    "name:xx": "Peaceful Valley"
  }
}
