{
  "geometry": {
    "type": "Point",
    "coordinates": [
      -91.5167,
      31.0667
    ]
  },
  "type": "Feature",
  "properties": {
    "hierarchy": [
      "tgn:2180659",
      "tgn:1000001",
      "tgn:7012149",
      "tgn:2001164",
      "tgn:7007522",
      "tgn:7029392"
    ],
    "placetype": [
      "aat:300008706"
    ],
    "id": 2180659,
    "name:xx": "Bloomer Creek"
  }
}
