{
  "geometry": {
    "type": "Point",
    "coordinates": [
      21.0833,
      46.6667
    ]
  },
  "type": "Feature",
  "properties": {
    "hierarchy": [
      "tgn:1042281",
      "tgn:1000341",
      "tgn:1000003",
      "tgn:7006278",
      "tgn:7029392"
    ],
    "placetype": [
      "aat:300008347",
      "aat:300008416",
      "aat:300008375",
      "aat:300387270",
      "aat:300387302"
    ],
    "id": 1042281,
    "name:xx": "Békéscsaba"
  }
}
