{
  "geometry": {
    "type": "Point",
    "coordinates": [
      -84.1167,
      36.1167
    ]
  },
  "type": "Feature",
  "properties": {
    "hierarchy": [
      "tgn:2463382",
      "tgn:2001837",
      "tgn:1000001",
      "tgn:7012149",
      "tgn:7007825",
      "tgn:7029392"
    ],
    "placetype": [
      "aat:300132348"
    ],
    "id": 2463382,
    "name:xx": "Llewellyns Schoals"
  }
}
