{
  "type": "FeatureCollection",
  "features": [
    {
      "geometry": {
        "type": "Point",
        "coordinates": [
          -78.85,
          40.6667
        ]
      },
      "type": "Feature",
      "properties": {
        "hierarchy": [
          "tgn:2688250",
          "tgn:1000001",
          "tgn:7012149",
          "tgn:1002501",
          "tgn:7007710",
          "tgn:7029392"
        ],
        "placetype": [
          "aat:300008347"
        ],
        "id": 2688250,
        "name:xx": "Spruce"
      }
    },
    {
      "geometry": {
        "type": "Point",
        "coordinates": [
          -83.5,
          36.9333
        ]
      },
      "type": "Feature",
      "properties": {
        "hierarchy": [
          "tgn:2688251",
          "tgn:1000001",
          "tgn:2000782",
          "tgn:7012149",
          "tgn:7007255",
          "tgn:7029392"
        ],
        "placetype": [
          "aat:300008699"
        ],
        "id": 2688251,
        "name:xx": "Spruce Branch"
      }
    },
    {
      "geometry": {
        "type": "Point",
        "coordinates": [
          -84.2667,
          37.0667
        ]
      },
      "type": "Feature",
      "properties": {
        "hierarchy": [
          "tgn:2688252",
          "tgn:1000001",
          "tgn:7012149",
          "tgn:2000808",
          "tgn:7007255",
          "tgn:7029392"
        ],
        "placetype": [
          "aat:300008699"
        ],
        "id": 2688252,
        "name:xx": "Spruce Branch"
      }
    },
    {
      "geometry": {
        "type": "Point",
        "coordinates": [
          -83.1833,
          37.65
        ]
      },
      "type": "Feature",
      "properties": {
        "hierarchy": [
          "tgn:2688253",
          "tgn:1000001",
          "tgn:7012149",
          "tgn:2000821",
          "tgn:7007255",
          "tgn:7029392"
        ],
        "placetype": [
          "aat:300008699"
        ],
        "id": 2688253,
        "name:xx": "Spruce Branch"
      }
    },
    {
      "geometry": {
        "type": "Point",
        "coordinates": [
          -83.1333,
          38.2167
        ]
      },
      "type": "Feature",
      "properties": {
        "hierarchy": [
          "tgn:2688254",
          "tgn:1000001",
          "tgn:7012149",
          "tgn:1002354",
          "tgn:7007255",
          "tgn:7029392"
        ],
        "placetype": [
          "aat:300008699"
        ],
        "id": 2688254,
        "name:xx": "Spruce Branch"
      }
    },
    {
      "geometry": {
        "type": "Point",
        "coordinates": [
          -81.9167,
          35.5833
        ]
      },
      "type": "Feature",
      "properties": {
        "hierarchy": [
          "tgn:2688255",
          "tgn:1000001",
          "tgn:7012149",
          "tgn:2001514",
          "tgn:7007709",
          "tgn:7029392"
        ],
        "placetype": [
          "aat:300008699"
        ],
        "id": 2688255,
        "name:xx": "Spruce Branch"
      }
    },
    {
      "geometry": {
        "type": "Point",
        "coordinates": [
          -81.8833,
          36.4833
        ]
      },
      "type": "Feature",
      "properties": {
        "hierarchy": [
          "tgn:2688256",
          "tgn:1000001",
          "tgn:7012149",
          "tgn:2001882",
          "tgn:7007825",
          "tgn:7029392"
        ],
        "placetype": [
          "aat:300008699"
        ],
        "id": 2688256,
        "name:xx": "Spruce Branch"
      }
    },
    {
      "geometry": {
        "type": "Point",
        "coordinates": [
          -73.0833,
          41.4833
        ]
      },
      "type": "Feature",
      "properties": {
        "hierarchy": [
          "tgn:2688259",
          "tgn:1000001",
          "tgn:1002712",
          "tgn:7012149",
          "tgn:7007159",
          "tgn:7029392"
        ],
        "placetype": [
          "aat:300008699"
        ],
        "id": 2688259,
        "name:xx": "Spruce Brook"
      }
    }
  ]
}
