{
  "geometry": {
    "type": "Point",
    "coordinates": [
      -112.4667,
      45.75
    ]
  },
  "type": "Feature",
  "properties": {
    "hierarchy": [
      "tgn:2316780",
      "tgn:1000001",
      "tgn:7012149",
      "tgn:2001306",
      "tgn:7007524",
      "tgn:7029392"
    ],
    "placetype": [
      "aat:300008680"
    ],
    "id": 2316780,
    "name:xx": "Emerald Lake"
  }
}
