{
  "geometry": {
    "type": "Point",
    "coordinates": [
      -87.9167,
      34.6667
    ]
  },
  "type": "Feature",
  "properties": {
    "hierarchy": [
      "tgn:2514869",
      "tgn:7002659",
      "tgn:1000001",
      "tgn:2000016",
      "tgn:7012149",
      "tgn:7029392"
    ],
    "placetype": [
      "aat:300266640"
    ],
    "id": 2514869,
    "name:xx": "Miller Ridge"
  }
}
