{
  "geometry": {
    "type": "Point",
    "coordinates": [
      122.0833,
      40.7833
    ]
  },
  "type": "Feature",
  "properties": {
    "hierarchy": [
      "tgn:1074073",
      "tgn:1000004",
      "tgn:1001390",
      "tgn:1000111",
      "tgn:7029392"
    ],
    "placetype": [
      "aat:300008347"
    ],
    "id": 1074073,
    "name:xx": "Zhongyangqu"
  }
}
