{
  "geometry": {
    "type": "Point",
    "coordinates": [
      -83.3833,
      37.1833
    ]
  },
  "type": "Feature",
  "properties": {
    "hierarchy": [
      "tgn:2451176",
      "tgn:1000001",
      "tgn:7012149",
      "tgn:2000811",
      "tgn:7007255",
      "tgn:7029392"
    ],
    "placetype": [
      "aat:300008699"
    ],
    "id": 2451176,
    "name:xx": "Little Asher Branch"
  }
}
