{
  "geometry": {
    "type": "Point",
    "coordinates": [
      120.48531,
      23.889637
    ]
  },
  "type": "Feature",
  "properties": {
    "hierarchy": [
      "tgn:7470368",
      "tgn:1000004",
      "tgn:7467799",
      "tgn:1000141",
      "tgn:7029392"
    ],
    "placetype": [
      "aat:300008347"
    ],
    "id": 7470368,
    "name:xx": "Buwei"
  }
}
