{
  "geometry": {
    "type": "Point",
    "coordinates": [
      139.45,
      35.7333
    ]
  },
  "type": "Feature",
  "properties": {
    "hierarchy": [
      "tgn:1136232",
      "tgn:1000004",
      "tgn:7000894",
      "tgn:1000120",
      "tgn:7029392"
    ],
    "placetype": [
      "aat:300006165"
    ],
    "id": 1136232,
    "name:xx": "Nobidome-yōsui"
  }
}
