{
  "geometry": {
    "type": "Point",
    "coordinates": [
      24.65,
      41.616
    ]
  },
  "type": "Feature",
  "properties": {
    "hierarchy": [
      "tgn:7593872",
      "tgn:1000003",
      "tgn:7006413",
      "tgn:7029392"
    ],
    "placetype": [
      "aat:300387064",
      "aat:300000774"
    ],
    "id": 7593872,
    "name:xx": "Smolyan"
  }
}
