{
  "geometry": {
    "type": "Point",
    "coordinates": [
      109.5833,
      53.6667
    ]
  },
  "type": "Feature",
  "properties": {
    "hierarchy": [
      "tgn:7014882",
      "tgn:1000004",
      "tgn:7011500",
      "tgn:7002435",
      "tgn:7029392"
    ],
    "placetype": [
      "aat:300008347"
    ],
    "id": 7014882,
    "name:xx": "Barguzin"
  }
}
