{
  "geometry": {
    "type": "Point",
    "coordinates": [
      125.2167,
      11.1167
    ]
  },
  "type": "Feature",
  "properties": {
    "hierarchy": [
      "tgn:1084435",
      "tgn:1000004",
      "tgn:1001516",
      "tgn:1000135",
      "tgn:7029392"
    ],
    "placetype": [
      "aat:300008347"
    ],
    "id": 1084435,
    "name:xx": "Marabut"
  }
}
