{
  "geometry": {
    "type": "Point",
    "coordinates": [
      -5.3833,
      57.4667
    ]
  },
  "type": "Feature",
  "properties": {
    "hierarchy": [
      "tgn:1050421",
      "tgn:7002444",
      "tgn:1000003",
      "tgn:7008082",
      "tgn:7008591",
      "tgn:7029392"
    ],
    "placetype": [
      "aat:300008347"
    ],
    "id": 1050421,
    "name:xx": "Balnacra"
  }
}
