{
  "geometry": {
    "type": "Point",
    "coordinates": [
      -87.6333,
      36.9167
    ]
  },
  "type": "Feature",
  "properties": {
    "hierarchy": [
      "tgn:2661890",
      "tgn:1000001",
      "tgn:2000780",
      "tgn:7012149",
      "tgn:7007255",
      "tgn:7029392"
    ],
    "placetype": [
      "aat:300008706"
    ],
    "id": 2661890,
    "name:xx": "Shurdan Creek"
  }
}
