{
  "geometry": {
    "type": "Point",
    "coordinates": [
      -121.9333,
      37.2667
    ]
  },
  "type": "Feature",
  "properties": {
    "hierarchy": [
      "tgn:2296672",
      "tgn:1000001",
      "tgn:7012149",
      "tgn:7007157",
      "tgn:7014475",
      "tgn:7029392"
    ],
    "placetype": [
      "aat:300008706"
    ],
    "id": 2296672,
    "name:xx": "Dry Creek"
  }
}
