{
  "geometry": {
    "type": "Point",
    "coordinates": [
      -105.9833,
      47.7667
    ]
  },
  "type": "Feature",
  "properties": {
    "hierarchy": [
      "tgn:2238828",
      "tgn:1000001",
      "tgn:7012149",
      "tgn:2001287",
      "tgn:7007524",
      "tgn:7029392"
    ],
    "placetype": [
      "aat:300006191"
    ],
    "id": 2238828,
    "name:xx": "Christianson Reservoir"
  }
}
