{
  "geometry": {
    "type": "Point",
    "coordinates": [
      -97.5167,
      42.0833
    ]
  },
  "type": "Feature",
  "properties": {
    "hierarchy": [
      "tgn:2370855",
      "tgn:1000001",
      "tgn:7012149",
      "tgn:7007525",
      "tgn:7029392"
    ],
    "placetype": [
      "aat:300008706"
    ],
    "id": 2370855,
    "name:xx": "Hadar Creek"
  }
}
