{
  "geometry": {
    "type": "Point",
    "coordinates": [
      32.083333,
      26.166667
    ]
  },
  "type": "Feature",
  "properties": {
    "hierarchy": [
      "tgn:7539309",
      "tgn:7001242",
      "tgn:7016833",
      "tgn:7000123",
      "tgn:7029392"
    ],
    "placetype": [
      "aat:300343519"
    ],
    "name:en": "Saḩḩārah al Gharbī, Ḩawḑ as",
    "id": 7539309
  }
}
