{
  "geometry": {
    "type": "Point",
    "coordinates": [
      17.5333,
      62.5333
    ]
  },
  "type": "Feature",
  "properties": {
    "hierarchy": [
      "tgn:1063550",
      "tgn:1000003",
      "tgn:1000466",
      "tgn:1000097",
      "tgn:7029392"
    ],
    "placetype": [
      "aat:300008347"
    ],
    "id": 1063550,
    "name:xx": "Söråker"
  }
}
