{
  "geometry": {
    "type": "Point",
    "coordinates": [
      -75.6333,
      38.7833
    ]
  },
  "type": "Feature",
  "properties": {
    "hierarchy": [
      "tgn:2690193",
      "tgn:1002933",
      "tgn:1000001",
      "tgn:7012149",
      "tgn:7007239",
      "tgn:7029392"
    ],
    "placetype": [
      "aat:300006075"
    ],
    "id": 2690193,
    "name:xx": "Stafford Ditch"
  }
}
