{
  "geometry": {
    "type": "Point",
    "coordinates": [
      -87.5167,
      40.9667
    ]
  },
  "type": "Feature",
  "properties": {
    "hierarchy": [
      "tgn:2398280",
      "tgn:1000001",
      "tgn:7012149",
      "tgn:7029392"
    ],
    "placetype": [
      "aat:300008699"
    ],
    "id": 2398280,
    "name:xx": "Hooper Branch"
  }
}
