{
  "geometry": {
    "type": "Point",
    "coordinates": [
      -89.3833,
      36.3333
    ]
  },
  "type": "Feature",
  "properties": {
    "hierarchy": [
      "tgn:2657618",
      "tgn:1000001",
      "tgn:7012149",
      "tgn:2001902",
      "tgn:7007825",
      "tgn:7029392"
    ],
    "placetype": [
      "aat:300008905"
    ],
    "id": 2657618,
    "name:xx": "Shelby Lake"
  }
}
