{
  "geometry": {
    "type": "Point",
    "coordinates": [
      -98.1667,
      34.7833
    ]
  },
  "type": "Feature",
  "properties": {
    "hierarchy": [
      "tgn:2527558",
      "tgn:1000001",
      "tgn:2001638",
      "tgn:7012149",
      "tgn:7007707",
      "tgn:7029392"
    ],
    "placetype": [
      "aat:300008347"
    ],
    "id": 2527558,
    "name:xx": "Mount View"
  }
}
