{
  "geometry": {
    "type": "Point",
    "coordinates": [
      -56.616,
      -34.455
    ]
  },
  "type": "Feature",
  "properties": {
    "hierarchy": [
      "tgn:1000747",
      "tgn:1000002",
      "tgn:1000058",
      "tgn:7029392"
    ],
    "placetype": [
      "aat:300387064",
      "aat:300000772"
    ],
    "id": 1000747,
    "name:xx": "San José"
  }
}
