{
  "type": "FeatureCollection",
  "features": [
    {
      "geometry": {
        "type": "Point",
        "coordinates": [
          -103.2,
          22.4
        ]
      },
      "type": "Feature",
      "properties": {
        "hierarchy": [
          "tgn:7366190",
          "tgn:1000001",
          "tgn:7005601",
          "tgn:7005560",
          "tgn:7029392"
        ],
        "placetype": [
          "aat:300008347"
        ],
        "id": 7366190,
        "name:xx": "El Terrero"
      }
    },
    {
      "geometry": {
        "type": "Point",
        "coordinates": [
          -102.85,
          21.866667
        ]
      },
      "type": "Feature",
      "properties": {
        "hierarchy": [
          "tgn:7366191",
          "tgn:7005579",
          "tgn:1000001",
          "tgn:7005560",
          "tgn:7029392"
        ],
        "placetype": [
          "aat:300008347"
        ],
        "id": 7366191,
        "name:xx": "El Terrero"
      }
    },
    {
      "geometry": {
        "type": "Point",
        "coordinates": [
          -98.033333,
          21.683333
        ]
      },
      "type": "Feature",
      "properties": {
        "hierarchy": [
          "tgn:7366192",
          "tgn:1000001",
          "tgn:7005599",
          "tgn:7005560",
          "tgn:7029392"
        ],
        "placetype": [
          "aat:300008347"
        ],
        "id": 7366192,
        "name:xx": "El Terrero"
      }
    },
    {
      "geometry": {
        "type": "Point",
        "coordinates": [
          -98.633333,
          21.516667
        ]
      },
      "type": "Feature",
      "properties": {
        "hierarchy": [
          "tgn:7366193",
          "tgn:1000001",
          "tgn:7005594",
          "tgn:7005560",
          "tgn:7029392"
        ],
        "placetype": [
          "aat:300008347"
        ],
        "id": 7366193,
        "name:xx": "El Terrero"
      }
    },
    {
      "geometry": {
        "type": "Point",
        "coordinates": [
          -101.257778,
          21.328889
        ]
      },
      "type": "Feature",
      "properties": {
        "hierarchy": [
          "tgn:7366194",
          "tgn:7005584",
          "tgn:1000001",
          "tgn:7005560",
          "tgn:7029392"
        ],
        "placetype": [
          "aat:300008347"
        ],
        "id": 7366194,
        "name:xx": "El Terrero"
      }
    },
    {
      "geometry": {
        "type": "Point",
        "coordinates": [
          -101.05,
          21.183333
        ]
      },
      "type": "Feature",
      "properties": {
        "hierarchy": [
          "tgn:7366195",
          "tgn:7005584",
          "tgn:1000001",
          "tgn:7005560",
          "tgn:7029392"
        ],
        "placetype": [
          "aat:300008347"
        ],
        "id": 7366195,
        "name:xx": "El Terrero"
      }
    },
    {
      "geometry": {
        "type": "Point",
        "coordinates": [
          -104.316667,
          21.033333
        ]
      },
      "type": "Feature",
      "properties": {
        "hierarchy": [
          "tgn:7366196",
          "tgn:1000001",
          "tgn:1001906",
          "tgn:7005560",
          "tgn:7029392"
        ],
        "placetype": [
          "aat:300008347"
        ],
        "id": 7366196,
        "name:xx": "El Terrero"
      }
    },
    {
      "geometry": {
        "type": "Point",
        "coordinates": [
          -97.516667,
          20.816667
        ]
      },
      "type": "Feature",
      "properties": {
        "hierarchy": [
          "tgn:7366197",
          "tgn:1000001",
          "tgn:7005599",
          "tgn:7005560",
          "tgn:7029392"
        ],
        "placetype": [
          "aat:300008347"
        ],
        "id": 7366197,
        "name:xx": "El Terrero"
      }
    },
    {
      "geometry": {
        "type": "Point",
        "coordinates": [
          -97.9,
          20.55
        ]
      },
      "type": "Feature",
      "properties": {
        "hierarchy": [
          "tgn:7366198",
          "tgn:1000001",
          "tgn:7005592",
          "tgn:7005560",
          "tgn:7029392"
        ],
        "placetype": [
          "aat:300008347"
        ],
        "id": 7366198,
        "name:xx": "El Terrero"
      }
    },
    {
      "geometry": {
        "type": "Point",
        "coordinates": [
          -100.566667,
          20.133333
        ]
      },
      "type": "Feature",
      "properties": {
        "hierarchy": [
          "tgn:7366199",
          "tgn:7005584",
          "tgn:1000001",
          "tgn:7005560",
          "tgn:7029392"
        ],
        "placetype": [
          "aat:300008347"
        ],
        "id": 7366199,
        "name:xx": "El Terrero"
      }
    }
  ]
}
