{
  "type": "FeatureCollection",
  "features": [
    {
      "geometry": {
        "type": "Point",
        "coordinates": [
          -88.4667,
          44.8333
        ]
      },
      "type": "Feature",
      "properties": {
        "hierarchy": [
          "tgn:2448600",
          "tgn:1000001",
          "tgn:7012149",
          "tgn:2002354",
          "tgn:7007922",
          "tgn:7029392"
        ],
        "placetype": [
          "aat:300008680"
        ],
        "id": 2448600,
        "name:xx": "Lily Lake"
      }
    },
    {
      "geometry": {
        "type": "Point",
        "coordinates": [
          -88.2,
          44.9
        ]
      },
      "type": "Feature",
      "properties": {
        "hierarchy": [
          "tgn:2448601",
          "tgn:1000001",
          "tgn:7012149",
          "tgn:2002341",
          "tgn:7007922",
          "tgn:7029392"
        ],
        "placetype": [
          "aat:300008680"
        ],
        "id": 2448601,
        "name:xx": "Lily Lake"
      }
    },
    {
      "geometry": {
        "type": "Point",
        "coordinates": [
          -88.8333,
          45.4167
        ]
      },
      "type": "Feature",
      "properties": {
        "hierarchy": [
          "tgn:2448603",
          "tgn:1000001",
          "tgn:2002323",
          "tgn:7012149",
          "tgn:7007922",
          "tgn:7029392"
        ],
        "placetype": [
          "aat:300008680"
        ],
        "id": 2448603,
        "name:xx": "Lily Lake"
      }
    },
    {
      "geometry": {
        "type": "Point",
        "coordinates": [
          -89.6333,
          45.5167
        ]
      },
      "type": "Feature",
      "properties": {
        "hierarchy": [
          "tgn:2448604",
          "tgn:1000001",
          "tgn:7012149",
          "tgn:2002334",
          "tgn:7007922",
          "tgn:7029392"
        ],
        "placetype": [
          "aat:300008680"
        ],
        "id": 2448604,
        "name:xx": "Lily Lake"
      }
    },
    {
      "geometry": {
        "type": "Point",
        "coordinates": [
          -89.4833,
          45.5833
        ]
      },
      "type": "Feature",
      "properties": {
        "hierarchy": [
          "tgn:2448605",
          "tgn:1000001",
          "tgn:7012149",
          "tgn:2002342",
          "tgn:7007922",
          "tgn:7029392"
        ],
        "placetype": [
          "aat:300008680"
        ],
        "id": 2448605,
        "name:xx": "Lily Lake"
      }
    },
    {
      "geometry": {
        "type": "Point",
        "coordinates": [
          -92.1,
          45.9833
        ]
      },
      "type": "Feature",
      "properties": {
        "hierarchy": [
          "tgn:2448606",
          "tgn:1000001",
          "tgn:2002311",
          "tgn:7012149",
          "tgn:7007922",
          "tgn:7029392"
        ],
        "placetype": [
          "aat:300008680"
        ],
        "id": 2448606,
        "name:xx": "Lily Lake"
      }
    },
    {
      "geometry": {
        "type": "Point",
        "coordinates": [
          -110.3167,
          43.7667
        ]
      },
      "type": "Feature",
      "properties": {
        "hierarchy": [
          "tgn:2448607",
          "tgn:1000001",
          "tgn:7012149",
          "tgn:2002384",
          "tgn:7007923",
          "tgn:7029392"
        ],
        "placetype": [
          "aat:300008680"
        ],
        "id": 2448607,
        "name:xx": "Lily Lake"
      }
    },
    {
      "geometry": {
        "type": "Point",
        "coordinates": [
          -107.2833,
          44.3
        ]
      },
      "type": "Feature",
      "properties": {
        "hierarchy": [
          "tgn:2448608",
          "tgn:1000001",
          "tgn:2002366",
          "tgn:7012149",
          "tgn:7007923",
          "tgn:7029392"
        ],
        "placetype": [
          "aat:300008680"
        ],
        "id": 2448608,
        "name:xx": "Lily Lake"
      }
    },
    {
      "geometry": {
        "type": "Point",
        "coordinates": [
          -109.25,
          44.3167
        ]
      },
      "type": "Feature",
      "properties": {
        "hierarchy": [
          "tgn:2448609",
          "tgn:1000001",
          "tgn:7012149",
          "tgn:2002379",
          "tgn:7007923",
          "tgn:7029392"
        ],
        "placetype": [
          "aat:300008680"
        ],
        "id": 2448609,
        "name:xx": "Lily Lake"
      }
    }
  ]
}
