{
  "geometry": {
    "type": "Point",
    "coordinates": [
      73.91127,
      28.971059
    ]
  },
  "type": "Feature",
  "properties": {
    "hierarchy": [
      "tgn:7568451",
      "tgn:1000004",
      "tgn:7000198",
      "tgn:7016788",
      "tgn:7029392"
    ],
    "placetype": [
      "aat:300008347"
    ],
    "name:en": "Khāria",
    "id": 7568451
  }
}
