{
  "geometry": {
    "type": "Point",
    "coordinates": [
      -92.1333,
      33.0667
    ]
  },
  "type": "Feature",
  "properties": {
    "hierarchy": [
      "tgn:2369174",
      "tgn:1000001",
      "tgn:7016172",
      "tgn:7012149",
      "tgn:2000174",
      "tgn:7029392"
    ],
    "placetype": [
      "aat:300266640"
    ],
    "id": 2369174,
    "name:xx": "Gum Ridge"
  }
}
