{
  "geometry": {
    "type": "Point",
    "coordinates": [
      -90.3333,
      32.5667
    ]
  },
  "type": "Feature",
  "properties": {
    "hierarchy": [
      "tgn:2290343",
      "tgn:1000001",
      "tgn:7012149",
      "tgn:2001130",
      "tgn:7007522",
      "tgn:7029392"
    ],
    "placetype": [
      "aat:300008699"
    ],
    "id": 2290343,
    "name:xx": "Dodson Branch"
  }
}
