{
  "geometry": {
    "type": "Point",
    "coordinates": [
      -96.0333,
      30.55
    ]
  },
  "type": "Feature",
  "properties": {
    "hierarchy": [
      "tgn:2711404",
      "tgn:1000001",
      "tgn:7012149",
      "tgn:1002429",
      "tgn:7007826",
      "tgn:7029392"
    ],
    "placetype": [
      "aat:300008699"
    ],
    "id": 2711404,
    "name:xx": "Tanyard Branch"
  }
}
