{
  "geometry": {
    "type": "Point",
    "coordinates": [
      -97.55,
      32.6833
    ]
  },
  "type": "Feature",
  "properties": {
    "hierarchy": [
      "tgn:2197307",
      "tgn:1000001",
      "tgn:7012149",
      "tgn:1002771",
      "tgn:7007826",
      "tgn:7029392"
    ],
    "placetype": [
      "aat:300008699"
    ],
    "id": 2197307,
    "name:xx": "Brown Branch"
  }
}
