{
  "geometry": {
    "type": "Point",
    "coordinates": [
      -82.1167,
      41.2333
    ]
  },
  "type": "Feature",
  "properties": {
    "hierarchy": [
      "tgn:2080265",
      "tgn:1000001",
      "tgn:7012149",
      "tgn:1002607",
      "tgn:7007706",
      "tgn:7029392"
    ],
    "placetype": [
      "aat:300008347"
    ],
    "id": 2080265,
    "name:xx": "Lagrange"
  }
}
