{
  "geometry": {
    "type": "Point",
    "coordinates": [
      121.4411,
      25.0656
    ]
  },
  "type": "Feature",
  "properties": {
    "hierarchy": [
      "tgn:7468749",
      "tgn:1000004",
      "tgn:1000454",
      "tgn:1000141",
      "tgn:7029392"
    ],
    "placetype": [
      "aat:300008347"
    ],
    "id": 7468749,
    "name:xx": "Fengshujiao"
  }
}
