{
  "geometry": {
    "type": "Point",
    "coordinates": [
      120.7591,
      24.0772
    ]
  },
  "type": "Feature",
  "properties": {
    "hierarchy": [
      "tgn:7491300",
      "tgn:1000004",
      "tgn:7001009",
      "tgn:1000141",
      "tgn:7029392"
    ],
    "placetype": [
      "aat:300008347"
    ],
    "id": 7491300,
    "name:xx": "Pan'anzi"
  }
}
