{
  "type": "FeatureCollection",
  "features": [
    {
      "geometry": {
        "type": "Point",
        "coordinates": [
          -83.9833,
          34.9167
        ]
      },
      "type": "Feature",
      "properties": {
        "hierarchy": [
          "tgn:2133130",
          "tgn:1000001",
          "tgn:7012149",
          "tgn:2000435",
          "tgn:7007248",
          "tgn:7029392"
        ],
        "placetype": [
          "aat:300008798"
        ],
        "id": 2133130,
        "name:xx": "Anderson Knob"
      }
    },
    {
      "geometry": {
        "type": "Point",
        "coordinates": [
          -85.15,
          35.9
        ]
      },
      "type": "Feature",
      "properties": {
        "hierarchy": [
          "tgn:2133132",
          "tgn:1000001",
          "tgn:7012149",
          "tgn:2001854",
          "tgn:7007825",
          "tgn:7029392"
        ],
        "placetype": [
          "aat:300008798"
        ],
        "id": 2133132,
        "name:xx": "Anderson Knob"
      }
    },
    {
      "geometry": {
        "type": "Point",
        "coordinates": [
          -149.3333,
          61.6167
        ]
      },
      "type": "Feature",
      "properties": {
        "hierarchy": [
          "tgn:2133133",
          "tgn:7006450",
          "tgn:1000001",
          "tgn:2124053",
          "tgn:7012149",
          "tgn:7029392"
        ],
        "placetype": [
          "aat:300008680"
        ],
        "id": 2133133,
        "name:xx": "Anderson Lake"
      }
    },
    {
      "geometry": {
        "type": "Point",
        "coordinates": [
          -109.7,
          34.25
        ]
      },
      "type": "Feature",
      "properties": {
        "hierarchy": [
          "tgn:2133134",
          "tgn:2000090",
          "tgn:1000001",
          "tgn:7006451",
          "tgn:7012149",
          "tgn:7029392"
        ],
        "placetype": [
          "aat:300008680"
        ],
        "id": 2133134,
        "name:xx": "Anderson Lake"
      }
    },
    {
      "geometry": {
        "type": "Point",
        "coordinates": [
          -90.5833,
          35.1667
        ]
      },
      "type": "Feature",
      "properties": {
        "hierarchy": [
          "tgn:2133135",
          "tgn:1000001",
          "tgn:7016172",
          "tgn:2000123",
          "tgn:7012149",
          "tgn:7029392"
        ],
        "placetype": [
          "aat:300008680"
        ],
        "id": 2133135,
        "name:xx": "Anderson Lake"
      }
    },
    {
      "geometry": {
        "type": "Point",
        "coordinates": [
          -90.6833,
          34.7333
        ]
      },
      "type": "Feature",
      "properties": {
        "hierarchy": [
          "tgn:2133136",
          "tgn:1000001",
          "tgn:7016172",
          "tgn:7012149",
          "tgn:2000143",
          "tgn:7029392"
        ],
        "placetype": [
          "aat:300008680"
        ],
        "id": 2133136,
        "name:xx": "Anderson Lake"
      }
    },
    {
      "geometry": {
        "type": "Point",
        "coordinates": [
          -107.2333,
          39.9833
        ]
      },
      "type": "Feature",
      "properties": {
        "hierarchy": [
          "tgn:2133137",
          "tgn:1000001",
          "tgn:7012149",
          "tgn:2000214",
          "tgn:7007158",
          "tgn:7029392"
        ],
        "placetype": [
          "aat:300008680"
        ],
        "id": 2133137,
        "name:xx": "Anderson Lake"
      }
    },
    {
      "geometry": {
        "type": "Point",
        "coordinates": [
          -106.6167,
          39.0167
        ]
      },
      "type": "Feature",
      "properties": {
        "hierarchy": [
          "tgn:2133138",
          "tgn:1000001",
          "tgn:7012149",
          "tgn:7007158",
          "tgn:2000240",
          "tgn:7029392"
        ],
        "placetype": [
          "aat:300008680"
        ],
        "id": 2133138,
        "name:xx": "Anderson Lake"
      }
    },
    {
      "geometry": {
        "type": "Point",
        "coordinates": [
          -83.4167,
          30.4333
        ]
      },
      "type": "Feature",
      "properties": {
        "hierarchy": [
          "tgn:2133139",
          "tgn:1000001",
          "tgn:7012149",
          "tgn:2000279",
          "tgn:7007240",
          "tgn:7029392"
        ],
        "placetype": [
          "aat:300008680"
        ],
        "id": 2133139,
        "name:xx": "Anderson Lake"
      }
    }
  ]
}
