{
  "geometry": {
    "type": "Point",
    "coordinates": [
      34.018264,
      27.95736
    ]
  },
  "type": "Feature",
  "properties": {
    "hierarchy": [
      "tgn:7529039",
      "tgn:7001242",
      "tgn:7016833",
      "tgn:7001336",
      "tgn:7029392"
    ],
    "placetype": [
      "aat:300379998"
    ],
    "name:en": "Umm Qatiya, Wādī",
    "id": 7529039
  }
}
