{
  "geometry": {
    "type": "Point",
    "coordinates": [
      -89.0833,
      32.6833
    ]
  },
  "type": "Feature",
  "properties": {
    "hierarchy": [
      "tgn:2272648",
      "tgn:1000001",
      "tgn:7012149",
      "tgn:2001135",
      "tgn:7007522",
      "tgn:7029392"
    ],
    "placetype": [
      "aat:300006075"
    ],
    "id": 2272648,
    "name:xx": "Cushtusia Canal"
  }
}
