{
  "geometry": {
    "type": "Point",
    "coordinates": [
      -114.3167,
      42.0333
    ]
  },
  "type": "Feature",
  "properties": {
    "hierarchy": [
      "tgn:2773555",
      "tgn:1000001",
      "tgn:7012149",
      "tgn:2000493",
      "tgn:7007250",
      "tgn:7029392"
    ],
    "placetype": [
      "aat:300008697"
    ],
    "id": 2773555,
    "name:xx": "Willis Spring"
  }
}
