{
  "geometry": {
    "type": "Point",
    "coordinates": [
      11.85,
      50.05
    ]
  },
  "type": "Feature",
  "properties": {
    "hierarchy": [
      "tgn:1106367",
      "tgn:7003669",
      "tgn:1000003",
      "tgn:7000084",
      "tgn:7029392"
    ],
    "placetype": [
      "aat:300008795"
    ],
    "id": 1106367,
    "name:xx": "Schneeberg"
  }
}
