{
  "geometry": {
    "type": "Point",
    "coordinates": [
      -87.4333,
      35.1667
    ]
  },
  "type": "Feature",
  "properties": {
    "hierarchy": [
      "tgn:2301877",
      "tgn:1000001",
      "tgn:7012149",
      "tgn:2001886",
      "tgn:7007825",
      "tgn:7029392"
    ],
    "placetype": [
      "aat:300008697"
    ],
    "id": 2301877,
    "name:xx": "Durham Spring"
  }
}
