{
  "geometry": {
    "type": "Point",
    "coordinates": [
      -90.5833,
      34.5667
    ]
  },
  "type": "Feature",
  "properties": {
    "hierarchy": [
      "tgn:2594128",
      "tgn:1000001",
      "tgn:7016172",
      "tgn:7012149",
      "tgn:2000158",
      "tgn:7029392"
    ],
    "placetype": [
      "aat:300008699"
    ],
    "id": 2594128,
    "name:xx": "Porter Bayou"
  }
}
