{
  "geometry": {
    "type": "Point",
    "coordinates": [
      -83.0667,
      31.05
    ]
  },
  "type": "Feature",
  "properties": {
    "hierarchy": [
      "tgn:2000377",
      "tgn:1000001",
      "tgn:7012149",
      "tgn:7007248",
      "tgn:7029392"
    ],
    "placetype": [
      "aat:300387145",
      "aat:300000771"
    ],
    "id": 2000377,
    "name:xx": "Lanier"
  }
}
