{
  "geometry": {
    "type": "Point",
    "coordinates": [
      30.98389,
      30.806776
    ]
  },
  "type": "Feature",
  "properties": {
    "hierarchy": [
      "tgn:7533733",
      "tgn:7001242",
      "tgn:7016833",
      "tgn:7001312",
      "tgn:7029392"
    ],
    "placetype": [
      "aat:300008347"
    ],
    "name:en": "Kafr 'Işām",
    "id": 7533733
  }
}
