{
  "geometry": {
    "type": "Point",
    "coordinates": [
      74.20943,
      33.15135
    ]
  },
  "type": "Feature",
  "properties": {
    "hierarchy": [
      "tgn:7592026",
      "tgn:1000004",
      "tgn:7000198",
      "tgn:7000799",
      "tgn:7029392"
    ],
    "placetype": [
      "aat:300008347"
    ],
    "name:en": "Nuniāl",
    "id": 7592026
  }
}
