{
  "geometry": {
    "type": "Point",
    "coordinates": [
      -85.4667,
      44.75
    ]
  },
  "type": "Feature",
  "properties": {
    "hierarchy": [
      "tgn:2757299",
      "tgn:1000001",
      "tgn:7012149",
      "tgn:2000961",
      "tgn:7007520",
      "tgn:7029392"
    ],
    "placetype": [
      "aat:300008706"
    ],
    "id": 2757299,
    "name:xx": "West Arm Acme Creek"
  }
}
