{
  "geometry": {
    "type": "Point",
    "coordinates": [
      47.7167,
      56.1167
    ]
  },
  "type": "Feature",
  "properties": {
    "hierarchy": [
      "tgn:1056824",
      "tgn:1000004",
      "tgn:7011491",
      "tgn:7002435",
      "tgn:7029392"
    ],
    "placetype": [
      "aat:300008347"
    ],
    "id": 1056824,
    "name:xx": "Marinskij Posad"
  }
}
