{
  "geometry": {
    "type": "Point",
    "coordinates": [
      -84.9167,
      44.1167
    ]
  },
  "type": "Feature",
  "properties": {
    "hierarchy": [
      "tgn:2605741",
      "tgn:1000001",
      "tgn:2000953",
      "tgn:7012149",
      "tgn:7007520",
      "tgn:7029392"
    ],
    "placetype": [
      "aat:300008347"
    ],
    "id": 2605741,
    "name:xx": "Rainbow Bend"
  }
}
