{
  "type": "FeatureCollection",
  "features": [
    {
      "geometry": {
        "type": "Point",
        "coordinates": [
          8.916667,
          49.283333
        ]
      },
      "type": "Feature",
      "properties": {
        "hierarchy": [
          "tgn:7172990",
          "tgn:7003692",
          "tgn:1000003",
          "tgn:7000084",
          "tgn:7029392"
        ],
        "placetype": [
          "aat:300008863"
        ],
        "id": 7172990,
        "name:xx": "Grosser Wald"
      }
    },
    {
      "geometry": {
        "type": "Point",
        "coordinates": [
          8.8,
          49.183333
        ]
      },
      "type": "Feature",
      "properties": {
        "hierarchy": [
          "tgn:7172991",
          "tgn:7003692",
          "tgn:1000003",
          "tgn:7000084",
          "tgn:7029392"
        ],
        "placetype": [
          "aat:300008863"
        ],
        "id": 7172991,
        "name:xx": "Großer Wald"
      }
    },
    {
      "geometry": {
        "type": "Point",
        "coordinates": [
          8.7,
          49
        ]
      },
      "type": "Feature",
      "properties": {
        "hierarchy": [
          "tgn:7172994",
          "tgn:7003692",
          "tgn:1000003",
          "tgn:7000084",
          "tgn:7029392"
        ],
        "placetype": [
          "aat:300008863"
        ],
        "id": 7172994,
        "name:xx": "Großer Wald"
      }
    },
    {
      "geometry": {
        "type": "Point",
        "coordinates": [
          8.533333,
          49.033333
        ]
      },
      "type": "Feature",
      "properties": {
        "hierarchy": [
          "tgn:7172996",
          "tgn:7003692",
          "tgn:1000003",
          "tgn:7000084",
          "tgn:7029392"
        ],
        "placetype": [
          "aat:300008863"
        ],
        "id": 7172996,
        "name:xx": "Großer Wald"
      }
    },
    {
      "geometry": {
        "type": "Point",
        "coordinates": [
          8.216667,
          48.666667
        ]
      },
      "type": "Feature",
      "properties": {
        "hierarchy": [
          "tgn:7172998",
          "tgn:7003692",
          "tgn:1000003",
          "tgn:7000084",
          "tgn:7029392"
        ],
        "placetype": [
          "aat:300008863"
        ],
        "id": 7172998,
        "name:xx": "Großer Wald"
      }
    },
    {
      "geometry": {
        "type": "Point",
        "coordinates": [
          10.75,
          48.433333
        ]
      },
      "type": "Feature",
      "properties": {
        "hierarchy": [
          "tgn:7172999",
          "tgn:7003669",
          "tgn:1000003",
          "tgn:7000084",
          "tgn:7029392"
        ],
        "placetype": [
          "aat:300008863"
        ],
        "id": 7172999,
        "name:xx": "Großer Wald"
      }
    }
  ]
}
