{
  "type": "FeatureCollection",
  "features": [
    {
      "geometry": {
        "type": "Point",
        "coordinates": [
          -95.183333,
          16.45
        ]
      },
      "type": "Feature",
      "properties": {
        "hierarchy": [
          "tgn:7394960",
          "tgn:1000001",
          "tgn:7005591",
          "tgn:7005560",
          "tgn:7029392"
        ],
        "placetype": [
          "aat:300008347"
        ],
        "id": 7394960,
        "name:xx": "San Isidro"
      }
    },
    {
      "geometry": {
        "type": "Point",
        "coordinates": [
          -93.9,
          16.2
        ]
      },
      "type": "Feature",
      "properties": {
        "hierarchy": [
          "tgn:7394961",
          "tgn:7005580",
          "tgn:1000001",
          "tgn:7005560",
          "tgn:7029392"
        ],
        "placetype": [
          "aat:300008347"
        ],
        "id": 7394961,
        "name:xx": "San Isidro"
      }
    },
    {
      "geometry": {
        "type": "Point",
        "coordinates": [
          -93.183333,
          16.183333
        ]
      },
      "type": "Feature",
      "properties": {
        "hierarchy": [
          "tgn:7394962",
          "tgn:7005580",
          "tgn:1000001",
          "tgn:7005560",
          "tgn:7029392"
        ],
        "placetype": [
          "aat:300008347"
        ],
        "id": 7394962,
        "name:xx": "San Isidro"
      }
    },
    {
      "geometry": {
        "type": "Point",
        "coordinates": [
          -96.5,
          15.933333
        ]
      },
      "type": "Feature",
      "properties": {
        "hierarchy": [
          "tgn:7394963",
          "tgn:1000001",
          "tgn:7005591",
          "tgn:7005560",
          "tgn:7029392"
        ],
        "placetype": [
          "aat:300008347"
        ],
        "id": 7394963,
        "name:xx": "San Isidro"
      }
    },
    {
      "geometry": {
        "type": "Point",
        "coordinates": [
          -92.4,
          15.55
        ]
      },
      "type": "Feature",
      "properties": {
        "hierarchy": [
          "tgn:7394964",
          "tgn:7005580",
          "tgn:1000001",
          "tgn:7005560",
          "tgn:7029392"
        ],
        "placetype": [
          "aat:300008347"
        ],
        "id": 7394964,
        "name:xx": "San Isidro"
      }
    },
    {
      "geometry": {
        "type": "Point",
        "coordinates": [
          -92.133333,
          14.883333
        ]
      },
      "type": "Feature",
      "properties": {
        "hierarchy": [
          "tgn:7394965",
          "tgn:7005580",
          "tgn:1000001",
          "tgn:7005560",
          "tgn:7029392"
        ],
        "placetype": [
          "aat:300008347"
        ],
        "id": 7394965,
        "name:xx": "San Isidro"
      }
    },
    {
      "geometry": {
        "type": "Point",
        "coordinates": [
          -116.816667,
          32.516667
        ]
      },
      "type": "Feature",
      "properties": {
        "hierarchy": [
          "tgn:7394966",
          "tgn:1001835",
          "tgn:1000001",
          "tgn:7005560",
          "tgn:7029392"
        ],
        "placetype": [
          "aat:300008777"
        ],
        "id": 7394966,
        "name:xx": "San Isidro"
      }
    },
    {
      "geometry": {
        "type": "Point",
        "coordinates": [
          -101.333333,
          27.533333
        ]
      },
      "type": "Feature",
      "properties": {
        "hierarchy": [
          "tgn:7394967",
          "tgn:1001853",
          "tgn:1000001",
          "tgn:7005560",
          "tgn:7029392"
        ],
        "placetype": [
          "aat:300000241"
        ],
        "id": 7394967,
        "name:xx": "Rancho San Isido"
      }
    },
    {
      "geometry": {
        "type": "Point",
        "coordinates": [
          -111.350833,
          30.770556
        ]
      },
      "type": "Feature",
      "properties": {
        "hierarchy": [
          "tgn:7394968",
          "tgn:1000001",
          "tgn:1001960",
          "tgn:7005560",
          "tgn:7029392"
        ],
        "placetype": [
          "aat:300008347"
        ],
        "id": 7394968,
        "name:xx": "San Inocente"
      }
    }
  ]
}
