{
  "geometry": {
    "type": "Point",
    "coordinates": [
      -75.4167,
      9.1167
    ]
  },
  "type": "Feature",
  "properties": {
    "hierarchy": [
      "tgn:1023763",
      "tgn:1000542",
      "tgn:1000050",
      "tgn:1000002",
      "tgn:7029392"
    ],
    "placetype": [
      "aat:300008347"
    ],
    "id": 1023763,
    "name:xx": "Chinú"
  }
}
