{
  "geometry": {
    "type": "Point",
    "coordinates": [
      -93.1833,
      37.5833
    ]
  },
  "type": "Feature",
  "properties": {
    "hierarchy": [
      "tgn:2182109",
      "tgn:1000001",
      "tgn:7012149",
      "tgn:2001232",
      "tgn:7007523",
      "tgn:7029392"
    ],
    "placetype": [
      "aat:300008798"
    ],
    "id": 2182109,
    "name:xx": "Blue Mound"
  }
}
