{
  "type": "FeatureCollection",
  "features": [
    {
      "geometry": {
        "type": "Point",
        "coordinates": [
          12.116667,
          52.65
        ]
      },
      "type": "Feature",
      "properties": {
        "hierarchy": [
          "tgn:7145420",
          "tgn:1000003",
          "tgn:7003687",
          "tgn:7000084",
          "tgn:7029392"
        ],
        "placetype": [
          "aat:300008863"
        ],
        "id": 7145420,
        "name:xx": "Kossathenheide"
      }
    },
    {
      "geometry": {
        "type": "Point",
        "coordinates": [
          12.7,
          52.433333
        ]
      },
      "type": "Feature",
      "properties": {
        "hierarchy": [
          "tgn:7145421",
          "tgn:7000096",
          "tgn:1000003",
          "tgn:7000084",
          "tgn:7029392"
        ],
        "placetype": [
          "aat:300008903"
        ],
        "id": 7145421,
        "name:xx": "Kossäthenbruch"
      }
    },
    {
      "geometry": {
        "type": "Point",
        "coordinates": [
          12.35,
          52.7
        ]
      },
      "type": "Feature",
      "properties": {
        "hierarchy": [
          "tgn:7145422",
          "tgn:7000096",
          "tgn:1000003",
          "tgn:7000084",
          "tgn:7029392"
        ],
        "placetype": [
          "aat:300008777"
        ],
        "id": 7145422,
        "name:xx": "Kossäthen Berg"
      }
    },
    {
      "geometry": {
        "type": "Point",
        "coordinates": [
          12.8,
          52.516667
        ]
      },
      "type": "Feature",
      "properties": {
        "hierarchy": [
          "tgn:7145423",
          "tgn:7000096",
          "tgn:1000003",
          "tgn:7000084",
          "tgn:7029392"
        ],
        "placetype": [
          "aat:300008777"
        ],
        "id": 7145423,
        "name:xx": "Kossäthenberg"
      }
    },
    {
      "geometry": {
        "type": "Point",
        "coordinates": [
          12,
          49.966667
        ]
      },
      "type": "Feature",
      "properties": {
        "hierarchy": [
          "tgn:7145424",
          "tgn:7003669",
          "tgn:1000003",
          "tgn:7000084",
          "tgn:7029392"
        ],
        "placetype": [
          "aat:300008347"
        ],
        "id": 7145424,
        "name:xx": "Kössain"
      }
    },
    {
      "geometry": {
        "type": "Point",
        "coordinates": [
          12.683333,
          51.616667
        ]
      },
      "type": "Feature",
      "properties": {
        "hierarchy": [
          "tgn:7145425",
          "tgn:1000003",
          "tgn:7003685",
          "tgn:7000084",
          "tgn:7029392"
        ],
        "placetype": [
          "aat:300008347"
        ],
        "id": 7145425,
        "name:xx": "Kossa"
      }
    },
    {
      "geometry": {
        "type": "Point",
        "coordinates": [
          11.75,
          50.716667
        ]
      },
      "type": "Feature",
      "properties": {
        "hierarchy": [
          "tgn:7145426",
          "tgn:1000003",
          "tgn:7003689",
          "tgn:7000084",
          "tgn:7029392"
        ],
        "placetype": [
          "aat:300008347"
        ],
        "id": 7145426,
        "name:xx": "Kospoda"
      }
    },
    {
      "geometry": {
        "type": "Point",
        "coordinates": [
          12.566667,
          51.45
        ]
      },
      "type": "Feature",
      "properties": {
        "hierarchy": [
          "tgn:7145427",
          "tgn:1000003",
          "tgn:7003685",
          "tgn:7000084",
          "tgn:7029392"
        ],
        "placetype": [
          "aat:300008347"
        ],
        "id": 7145427,
        "name:xx": "Kospa"
      }
    },
    {
      "geometry": {
        "type": "Point",
        "coordinates": [
          11.6,
          51.016667
        ]
      },
      "type": "Feature",
      "properties": {
        "hierarchy": [
          "tgn:7145428",
          "tgn:1000003",
          "tgn:7003689",
          "tgn:7000084",
          "tgn:7029392"
        ],
        "placetype": [
          "aat:300008347"
        ],
        "id": 7145428,
        "name:xx": "Kösnitz"
      }
    },
    {
      "geometry": {
        "type": "Point",
        "coordinates": [
          12.4,
          50.966667
        ]
      },
      "type": "Feature",
      "properties": {
        "hierarchy": [
          "tgn:7145429",
          "tgn:1000003",
          "tgn:7003689",
          "tgn:7000084",
          "tgn:7029392"
        ],
        "placetype": [
          "aat:300008347"
        ],
        "id": 7145429,
        "name:xx": "Kosma"
      }
    }
  ]
}
