{
  "geometry": {
    "type": "Point",
    "coordinates": [
      51.35,
      50.1833
    ]
  },
  "type": "Feature",
  "properties": {
    "hierarchy": [
      "tgn:1054413",
      "tgn:1000004",
      "tgn:7011457",
      "tgn:7014786",
      "tgn:7029392"
    ],
    "placetype": [
      "aat:300008347"
    ],
    "id": 1054413,
    "name:xx": "Irubay"
  }
}
