{
  "geometry": {
    "type": "Point",
    "coordinates": [
      72.3667,
      31.95
    ]
  },
  "type": "Feature",
  "properties": {
    "hierarchy": [
      "tgn:1083754",
      "tgn:1000004",
      "tgn:1001490",
      "tgn:1000133",
      "tgn:7029392"
    ],
    "placetype": [
      "aat:300008347"
    ],
    "id": 1083754,
    "name:xx": "Sahiwal"
  }
}
