{
  "geometry": {
    "type": "Point",
    "coordinates": [
      -82.4167,
      37.2833
    ]
  },
  "type": "Feature",
  "properties": {
    "hierarchy": [
      "tgn:2452433",
      "tgn:1000001",
      "tgn:7012149",
      "tgn:2000837",
      "tgn:7007255",
      "tgn:7029392"
    ],
    "placetype": [
      "aat:300008699"
    ],
    "id": 2452433,
    "name:xx": "Little Branch"
  }
}
