{
  "geometry": {
    "type": "Point",
    "coordinates": [
      -81.8667,
      33.5333
    ]
  },
  "type": "Feature",
  "properties": {
    "hierarchy": [
      "tgn:2700711",
      "tgn:2001726",
      "tgn:1000001",
      "tgn:7012149",
      "tgn:7007712",
      "tgn:7029392"
    ],
    "placetype": [
      "aat:300008680"
    ],
    "id": 2700711,
    "name:xx": "Sudlow Lake"
  }
}
