{
  "geometry": {
    "type": "Point",
    "coordinates": [
      76.874045,
      30.210918
    ]
  },
  "type": "Feature",
  "properties": {
    "hierarchy": [
      "tgn:7582739",
      "tgn:1000004",
      "tgn:1001871",
      "tgn:7000198",
      "tgn:7029392"
    ],
    "placetype": [
      "aat:300008347"
    ],
    "name:en": "Dāo Mājra",
    "id": 7582739
  }
}
