{
  "geometry": {
    "type": "Point",
    "coordinates": [
      -83.3167,
      39.5833
    ]
  },
  "type": "Feature",
  "properties": {
    "hierarchy": [
      "tgn:2367957",
      "tgn:1000001",
      "tgn:7012149",
      "tgn:1002372",
      "tgn:7007706",
      "tgn:7029392"
    ],
    "placetype": [
      "aat:300008699"
    ],
    "id": 2367957,
    "name:xx": "Grub Run"
  }
}
