{
  "geometry": {
    "type": "Point",
    "coordinates": [
      22.2125,
      40.672778
    ]
  },
  "type": "Feature",
  "properties": {
    "hierarchy": [
      "tgn:7230348",
      "tgn:7002718",
      "tgn:7002715",
      "tgn:1000003",
      "tgn:1000074",
      "tgn:7029392"
    ],
    "placetype": [
      "aat:300008699"
    ],
    "id": 7230348,
    "name:xx": "Mavronéri Réma"
  }
}
