{
  "geometry": {
    "type": "Point",
    "coordinates": [
      -84.75,
      36.55
    ]
  },
  "type": "Feature",
  "properties": {
    "hierarchy": [
      "tgn:2233045",
      "tgn:1000001",
      "tgn:7012149",
      "tgn:7007825",
      "tgn:7029392"
    ],
    "placetype": [
      "aat:300008706"
    ],
    "id": 2233045,
    "name:xx": "Charit Creek"
  }
}
