{
  "type": "FeatureCollection",
  "features": [
    {
      "geometry": {
        "type": "Point",
        "coordinates": [
          -84.6333,
          35.3667
        ]
      },
      "type": "Feature",
      "properties": {
        "hierarchy": [
          "tgn:2611150",
          "tgn:1000001",
          "tgn:7012149",
          "tgn:7022542",
          "tgn:7007825",
          "tgn:7029392"
        ],
        "placetype": [
          "aat:300008798"
        ],
        "id": 2611150,
        "name:xx": "Red Hills"
      }
    },
    {
      "geometry": {
        "type": "Point",
        "coordinates": [
          -101.0333,
          32.45
        ]
      },
      "type": "Feature",
      "properties": {
        "hierarchy": [
          "tgn:2611151",
          "tgn:1000001",
          "tgn:7012149",
          "tgn:2002043",
          "tgn:7007826",
          "tgn:7029392"
        ],
        "placetype": [
          "aat:300008798"
        ],
        "id": 2611151,
        "name:xx": "Red Hills"
      }
    },
    {
      "geometry": {
        "type": "Point",
        "coordinates": [
          -103.9167,
          30.9333
        ]
      },
      "type": "Feature",
      "properties": {
        "hierarchy": [
          "tgn:2611152",
          "tgn:1000001",
          "tgn:7012149",
          "tgn:2002010",
          "tgn:7007826",
          "tgn:7029392"
        ],
        "placetype": [
          "aat:300386831"
        ],
        "id": 2611152,
        "name:xx": "Red Hills"
      }
    },
    {
      "geometry": {
        "type": "Point",
        "coordinates": [
          -105.2833,
          31.65
        ]
      },
      "type": "Feature",
      "properties": {
        "hierarchy": [
          "tgn:2611153",
          "tgn:1000001",
          "tgn:7012149",
          "tgn:2002005",
          "tgn:7007826",
          "tgn:7029392"
        ],
        "placetype": [
          "aat:300008798"
        ],
        "id": 2611153,
        "name:xx": "Red Hills"
      }
    },
    {
      "geometry": {
        "type": "Point",
        "coordinates": [
          -100.5,
          34.0833
        ]
      },
      "type": "Feature",
      "properties": {
        "hierarchy": [
          "tgn:2611154",
          "tgn:1000001",
          "tgn:7012149",
          "tgn:2001965",
          "tgn:7007826",
          "tgn:7029392"
        ],
        "placetype": [
          "aat:300008798"
        ],
        "id": 2611154,
        "name:xx": "Red Hills"
      }
    },
    {
      "geometry": {
        "type": "Point",
        "coordinates": [
          -112.8333,
          38
        ]
      },
      "type": "Feature",
      "properties": {
        "hierarchy": [
          "tgn:2611155",
          "tgn:1000001",
          "tgn:7012149",
          "tgn:2002111",
          "tgn:7007827",
          "tgn:7029392"
        ],
        "placetype": [
          "aat:300008798"
        ],
        "id": 2611155,
        "name:xx": "Red Hills"
      }
    },
    {
      "geometry": {
        "type": "Point",
        "coordinates": [
          -113.4,
          37.6667
        ]
      },
      "type": "Feature",
      "properties": {
        "hierarchy": [
          "tgn:2611156",
          "tgn:1000001",
          "tgn:7012149",
          "tgn:2002111",
          "tgn:7007827",
          "tgn:7029392"
        ],
        "placetype": [
          "aat:300386831"
        ],
        "id": 2611156,
        "name:xx": "Red Hills"
      }
    },
    {
      "geometry": {
        "type": "Point",
        "coordinates": [
          -113.5667,
          37.1167
        ]
      },
      "type": "Feature",
      "properties": {
        "hierarchy": [
          "tgn:2611157",
          "tgn:1000001",
          "tgn:7012149",
          "tgn:2002127",
          "tgn:7007827",
          "tgn:7029392"
        ],
        "placetype": [
          "aat:300008798"
        ],
        "id": 2611157,
        "name:xx": "Red Hills"
      }
    },
    {
      "geometry": {
        "type": "Point",
        "coordinates": [
          -113.05,
          38.75
        ]
      },
      "type": "Feature",
      "properties": {
        "hierarchy": [
          "tgn:2611158",
          "tgn:1000001",
          "tgn:7012149",
          "tgn:2002114",
          "tgn:7007827",
          "tgn:7029392"
        ],
        "placetype": [
          "aat:300008798"
        ],
        "id": 2611158,
        "name:xx": "Red Hills"
      }
    },
    {
      "geometry": {
        "type": "Point",
        "coordinates": [
          -105.25,
          43.4667
        ]
      },
      "type": "Feature",
      "properties": {
        "hierarchy": [
          "tgn:2611159",
          "tgn:1000001",
          "tgn:2002369",
          "tgn:7012149",
          "tgn:7007923",
          "tgn:7029392"
        ],
        "placetype": [
          "aat:300386831"
        ],
        "id": 2611159,
        "name:xx": "Red Hills"
      }
    }
  ]
}
