{
  "geometry": {
    "type": "Point",
    "coordinates": [
      -69.7167,
      48.15
    ]
  },
  "type": "Feature",
  "properties": {
    "hierarchy": [
      "tgn:1015782",
      "tgn:7005685",
      "tgn:1000001",
      "tgn:7005804",
      "tgn:7029392"
    ],
    "placetype": [
      "aat:300008347"
    ],
    "id": 1015782,
    "name:xx": "Tadoussac"
  }
}
