{
  "geometry": {
    "type": "Point",
    "coordinates": [
      -75.6333,
      40.9333
    ]
  },
  "type": "Feature",
  "properties": {
    "hierarchy": [
      "tgn:2770205",
      "tgn:1000001",
      "tgn:1002233",
      "tgn:7012149",
      "tgn:7007710",
      "tgn:7029392"
    ],
    "placetype": [
      "aat:300008706"
    ],
    "id": 2770205,
    "name:xx": "Wild Creek"
  }
}
