{
  "geometry": {
    "type": "Point",
    "coordinates": [
      -79.0333,
      42.6833
    ]
  },
  "type": "Feature",
  "properties": {
    "hierarchy": [
      "tgn:1012526",
      "tgn:1000001",
      "tgn:7012149",
      "tgn:1002356",
      "tgn:7007568",
      "tgn:7029392"
    ],
    "placetype": [
      "aat:300386846"
    ],
    "id": 1012526,
    "name:xx": "Sturgeon Point"
  }
}
