{
  "geometry": {
    "type": "Point",
    "coordinates": [
      79.4901,
      27.7694
    ]
  },
  "type": "Feature",
  "properties": {
    "hierarchy": [
      "tgn:7559735",
      "tgn:1000004",
      "tgn:7000198",
      "tgn:7016722",
      "tgn:7029392"
    ],
    "placetype": [
      "aat:300008347"
    ],
    "name:en": "Baghauni",
    "id": 7559735
  }
}
