{
  "geometry": {
    "type": "Point",
    "coordinates": [
      -78.95,
      37.7833
    ]
  },
  "type": "Feature",
  "properties": {
    "hierarchy": [
      "tgn:2493416",
      "tgn:1000001",
      "tgn:7012149",
      "tgn:2002175",
      "tgn:7007919",
      "tgn:7029392"
    ],
    "placetype": [
      "aat:300008798"
    ],
    "id": 2493416,
    "name:xx": "Mars Knob"
  }
}
