{
  "geometry": {
    "type": "Point",
    "coordinates": [
      -72.366667,
      -37.55
    ]
  },
  "type": "Feature",
  "properties": {
    "hierarchy": [
      "tgn:7286476",
      "tgn:1001637",
      "tgn:1000049",
      "tgn:1000002",
      "tgn:7029392"
    ],
    "placetype": [
      "aat:300008777"
    ],
    "id": 7286476,
    "name:xx": "Henríquez, Cerro"
  }
}
