{
  "geometry": {
    "type": "Point",
    "coordinates": [
      30.902778,
      31.541667
    ]
  },
  "type": "Feature",
  "properties": {
    "hierarchy": [
      "tgn:7532233",
      "tgn:7001242",
      "tgn:7016833",
      "tgn:1001335",
      "tgn:7029392"
    ],
    "placetype": [
      "aat:300386846"
    ],
    "name:en": "Kûdya, Râs el-",
    "id": 7532233
  }
}
