{
  "geometry": {
    "type": "Point",
    "coordinates": [
      -82.6333,
      30.7167
    ]
  },
  "type": "Feature",
  "properties": {
    "hierarchy": [
      "tgn:2272906",
      "tgn:1000001",
      "tgn:2000323",
      "tgn:7012149",
      "tgn:7007248",
      "tgn:7029392"
    ],
    "placetype": [
      "aat:300008699"
    ],
    "id": 2272906,
    "name:xx": "Cutoff Branch"
  }
}
