{
  "geometry": {
    "type": "Point",
    "coordinates": [
      -89.5167,
      46.2167
    ]
  },
  "type": "Feature",
  "properties": {
    "hierarchy": [
      "tgn:2436959",
      "tgn:1000001",
      "tgn:7012149",
      "tgn:2000960",
      "tgn:7007520",
      "tgn:7029392"
    ],
    "placetype": [
      "aat:300008850"
    ],
    "id": 2436959,
    "name:xx": "Killarney Point"
  }
}
