{
  "geometry": {
    "type": "Point",
    "coordinates": [
      -108.0167,
      33.0667
    ]
  },
  "type": "Feature",
  "properties": {
    "hierarchy": [
      "tgn:2732488",
      "tgn:1000001",
      "tgn:7012149",
      "tgn:2001437",
      "tgn:7007566",
      "tgn:7029392"
    ],
    "placetype": [
      "aat:300006191"
    ],
    "id": 2732488,
    "name:xx": "Turkey Cienega Tank"
  }
}
