{
  "geometry": {
    "type": "Point",
    "coordinates": [
      -80.65,
      36.2167
    ]
  },
  "type": "Feature",
  "properties": {
    "hierarchy": [
      "tgn:2075839",
      "tgn:1000001",
      "tgn:7012149",
      "tgn:2001555",
      "tgn:7007709",
      "tgn:7029392"
    ],
    "placetype": [
      "aat:300008347",
      "aat:300387210"
    ],
    "id": 2075839,
    "name:xx": "Nebo"
  }
}
