{
  "geometry": {
    "type": "Point",
    "coordinates": [
      -80.2833,
      41.5167
    ]
  },
  "type": "Feature",
  "properties": {
    "hierarchy": [
      "tgn:1134506",
      "tgn:1000001",
      "tgn:7012149",
      "tgn:7007710",
      "tgn:7029392"
    ],
    "placetype": [
      "aat:300008706"
    ],
    "id": 1134506,
    "name:xx": "Sandy Creek"
  }
}
