{
  "type": "FeatureCollection",
  "features": [
    {
      "geometry": {
        "type": "Point",
        "coordinates": [
          12.766667,
          41.95
        ]
      },
      "type": "Feature",
      "properties": {
        "hierarchy": [
          "tgn:7054610",
          "tgn:7003138",
          "tgn:1000003",
          "tgn:7003080",
          "tgn:1000080",
          "tgn:7029392"
        ],
        "placetype": [
          "aat:300008347"
        ],
        "id": 7054610,
        "name:xx": "Ponte Lucano"
      }
    },
    {
      "geometry": {
        "type": "Point",
        "coordinates": [
          11.933333,
          45.266667
        ]
      },
      "type": "Feature",
      "properties": {
        "hierarchy": [
          "tgn:7054611",
          "tgn:7002994",
          "tgn:1000003",
          "tgn:7002997",
          "tgn:1000080",
          "tgn:7029392"
        ],
        "placetype": [
          "aat:300006075"
        ],
        "id": 7054611,
        "name:xx": "Canale di Pontelongo"
      }
    },
    {
      "geometry": {
        "type": "Point",
        "coordinates": [
          16.366667,
          39.766667
        ]
      },
      "type": "Feature",
      "properties": {
        "hierarchy": [
          "tgn:7054615",
          "tgn:1003450",
          "tgn:7007850",
          "tgn:1000003",
          "tgn:1000080",
          "tgn:7029392"
        ],
        "placetype": [
          "aat:300008347"
        ],
        "id": 7054615,
        "name:xx": "Ponte Amendola"
      }
    },
    {
      "geometry": {
        "type": "Point",
        "coordinates": [
          9.216667,
          45.833333
        ]
      },
      "type": "Feature",
      "properties": {
        "hierarchy": [
          "tgn:7054616",
          "tgn:7005852",
          "tgn:1000003",
          "tgn:7003237",
          "tgn:1000080",
          "tgn:7029392"
        ],
        "placetype": [
          "aat:300008347"
        ],
        "id": 7054616,
        "name:xx": "Ponte Lambro"
      }
    },
    {
      "geometry": {
        "type": "Point",
        "coordinates": [
          16.2,
          40.95
        ]
      },
      "type": "Feature",
      "properties": {
        "hierarchy": [
          "tgn:7054618",
          "tgn:7003248",
          "tgn:1000003",
          "tgn:7010380",
          "tgn:1000080",
          "tgn:7029392"
        ],
        "placetype": [
          "aat:300008777"
        ],
        "id": 7054618,
        "name:xx": "Ponte Impiso"
      }
    }
  ]
}
