{
  "geometry": {
    "type": "Point",
    "coordinates": [
      -93.9833,
      43.0667
    ]
  },
  "type": "Feature",
  "properties": {
    "hierarchy": [
      "tgn:2310907",
      "tgn:1000001",
      "tgn:7012149",
      "tgn:2000615",
      "tgn:7007253",
      "tgn:7029392"
    ],
    "placetype": [
      "aat:300008706"
    ],
    "id": 2310907,
    "name:xx": "Eddy Creek"
  }
}
