{
  "geometry": {
    "type": "Point",
    "coordinates": [
      -82.6167,
      36.0833
    ]
  },
  "type": "Feature",
  "properties": {
    "hierarchy": [
      "tgn:2733499",
      "tgn:1000001",
      "tgn:7012149",
      "tgn:2001866",
      "tgn:7007825",
      "tgn:7029392"
    ],
    "placetype": [
      "aat:300008761"
    ],
    "id": 2733499,
    "name:xx": "Turkeypen Cove"
  }
}
