{
  "type": "FeatureCollection",
  "features": [
    {
      "geometry": {
        "type": "Point",
        "coordinates": [
          -78.9833,
          40.5167
        ]
      },
      "type": "Feature",
      "properties": {
        "hierarchy": [
          "tgn:2199540",
          "tgn:1000001",
          "tgn:7012149",
          "tgn:1002501",
          "tgn:7007710",
          "tgn:7029392"
        ],
        "placetype": [
          "aat:300008706"
        ],
        "id": 2199540,
        "name:xx": "Brush Creek"
      }
    },
    {
      "geometry": {
        "type": "Point",
        "coordinates": [
          -78.9,
          39.8667
        ]
      },
      "type": "Feature",
      "properties": {
        "hierarchy": [
          "tgn:2199541",
          "tgn:1000001",
          "tgn:7012149",
          "tgn:1002904",
          "tgn:7007710",
          "tgn:7029392"
        ],
        "placetype": [
          "aat:300008706"
        ],
        "id": 2199541,
        "name:xx": "Brush Creek"
      }
    },
    {
      "geometry": {
        "type": "Point",
        "coordinates": [
          -103.4667,
          44.0167
        ]
      },
      "type": "Feature",
      "properties": {
        "hierarchy": [
          "tgn:2199542",
          "tgn:1000001",
          "tgn:7012149",
          "tgn:2001821",
          "tgn:7007713",
          "tgn:7029392"
        ],
        "placetype": [
          "aat:300008706"
        ],
        "id": 2199542,
        "name:xx": "Brush Creek"
      }
    },
    {
      "geometry": {
        "type": "Point",
        "coordinates": [
          -103.15,
          45.7167
        ]
      },
      "type": "Feature",
      "properties": {
        "hierarchy": [
          "tgn:2199543",
          "tgn:1000001",
          "tgn:2001801",
          "tgn:7012149",
          "tgn:7007713",
          "tgn:7029392"
        ],
        "placetype": [
          "aat:300008706"
        ],
        "id": 2199543,
        "name:xx": "Brush Creek"
      }
    },
    {
      "geometry": {
        "type": "Point",
        "coordinates": [
          -102.8,
          43.5667
        ]
      },
      "type": "Feature",
      "properties": {
        "hierarchy": [
          "tgn:2199544",
          "tgn:1000001",
          "tgn:7012149",
          "tgn:2001826",
          "tgn:7007713",
          "tgn:7029392"
        ],
        "placetype": [
          "aat:300008706"
        ],
        "id": 2199544,
        "name:xx": "Brush Creek"
      }
    },
    {
      "geometry": {
        "type": "Point",
        "coordinates": [
          -100.8167,
          44.65
        ]
      },
      "type": "Feature",
      "properties": {
        "hierarchy": [
          "tgn:2199545",
          "tgn:1000001",
          "tgn:7012149",
          "tgn:2001828",
          "tgn:7007713",
          "tgn:7029392"
        ],
        "placetype": [
          "aat:300008706"
        ],
        "id": 2199545,
        "name:xx": "Brush Creek"
      }
    },
    {
      "geometry": {
        "type": "Point",
        "coordinates": [
          -84.7833,
          35.45
        ]
      },
      "type": "Feature",
      "properties": {
        "hierarchy": [
          "tgn:2199546",
          "tgn:1000001",
          "tgn:7012149",
          "tgn:7022542",
          "tgn:7007825",
          "tgn:7029392"
        ],
        "placetype": [
          "aat:300008706"
        ],
        "id": 2199546,
        "name:xx": "Brush Creek"
      }
    },
    {
      "geometry": {
        "type": "Point",
        "coordinates": [
          -87.4833,
          35.5167
        ]
      },
      "type": "Feature",
      "properties": {
        "hierarchy": [
          "tgn:2199547",
          "tgn:1000001",
          "tgn:7012149",
          "tgn:2001887",
          "tgn:7007825",
          "tgn:7029392"
        ],
        "placetype": [
          "aat:300008706"
        ],
        "id": 2199547,
        "name:xx": "Brush Creek"
      }
    },
    {
      "geometry": {
        "type": "Point",
        "coordinates": [
          -87.1167,
          36.2167
        ]
      },
      "type": "Feature",
      "properties": {
        "hierarchy": [
          "tgn:2199548",
          "tgn:1000001",
          "tgn:7012149",
          "tgn:2001847",
          "tgn:7007825",
          "tgn:7029392"
        ],
        "placetype": [
          "aat:300008706"
        ],
        "id": 2199548,
        "name:xx": "Brush Creek"
      }
    },
    {
      "geometry": {
        "type": "Point",
        "coordinates": [
          -84.2,
          36.3333
        ]
      },
      "type": "Feature",
      "properties": {
        "hierarchy": [
          "tgn:2199549",
          "tgn:1000001",
          "tgn:7012149",
          "tgn:2001843",
          "tgn:7007825",
          "tgn:7029392"
        ],
        "placetype": [
          "aat:300008706"
        ],
        "id": 2199549,
        "name:xx": "Brush Creek"
      }
    }
  ]
}
