{
  "geometry": {
    "type": "Point",
    "coordinates": [
      -111.6833,
      41.7833
    ]
  },
  "type": "Feature",
  "properties": {
    "hierarchy": [
      "tgn:2709111",
      "tgn:1000001",
      "tgn:2002103",
      "tgn:7012149",
      "tgn:7007827",
      "tgn:7029392"
    ],
    "placetype": [
      "aat:300008761"
    ],
    "id": 2709111,
    "name:xx": "Tab Hollow"
  }
}
