{
  "geometry": {
    "type": "Point",
    "coordinates": [
      -76.8167,
      43.95
    ]
  },
  "type": "Feature",
  "properties": {
    "hierarchy": [
      "tgn:1009990",
      "tgn:7005685",
      "tgn:1000001",
      "tgn:7013154",
      "tgn:7029392"
    ],
    "placetype": [
      "aat:300386853"
    ],
    "id": 1009990,
    "name:xx": "False Ducks Islands"
  }
}
