{
  "geometry": {
    "type": "Point",
    "coordinates": [
      31.383064,
      30.133636
    ]
  },
  "type": "Feature",
  "properties": {
    "hierarchy": [
      "tgn:7531474",
      "tgn:7001242",
      "tgn:7016833",
      "tgn:1001091",
      "tgn:7029392"
    ],
    "placetype": [
      "aat:300004792"
    ],
    "id": 7531474,
    "name:xx": "Maḩaţţat Muḩawwilāt Aydiyāl"
  }
}
