{
  "geometry": {
    "type": "Point",
    "coordinates": [
      75.505658,
      29.212611
    ]
  },
  "type": "Feature",
  "properties": {
    "hierarchy": [
      "tgn:7578776",
      "tgn:1000004",
      "tgn:1001871",
      "tgn:7000198",
      "tgn:7029392"
    ],
    "placetype": [
      "aat:300008347"
    ],
    "name:en": "Sīswāl",
    "id": 7578776
  }
}
