{
  "geometry": {
    "type": "Point",
    "coordinates": [
      -96.7333,
      38.4667
    ]
  },
  "type": "Feature",
  "properties": {
    "hierarchy": [
      "tgn:2249876",
      "tgn:1000001",
      "tgn:2000668",
      "tgn:7012149",
      "tgn:7007254",
      "tgn:7029392"
    ],
    "placetype": [
      "aat:300008706"
    ],
    "id": 2249876,
    "name:xx": "Collett Creek"
  }
}
