{
  "type": "FeatureCollection",
  "features": [
    {
      "geometry": {
        "type": "Point",
        "coordinates": [
          -81.1,
          39.6667
        ]
      },
      "type": "Feature",
      "properties": {
        "hierarchy": [
          "tgn:2586902",
          "tgn:1000001",
          "tgn:7012149",
          "tgn:2001617",
          "tgn:7007706",
          "tgn:7029392"
        ],
        "placetype": [
          "aat:300008347"
        ],
        "id": 2586902,
        "name:xx": "Plainview"
      }
    },
    {
      "geometry": {
        "type": "Point",
        "coordinates": [
          -95.1167,
          34.1
        ]
      },
      "type": "Feature",
      "properties": {
        "hierarchy": [
          "tgn:2586903",
          "tgn:1000001",
          "tgn:7012149",
          "tgn:2001667",
          "tgn:7007707",
          "tgn:7029392"
        ],
        "placetype": [
          "aat:300008347"
        ],
        "id": 2586903,
        "name:xx": "Plainview"
      }
    },
    {
      "geometry": {
        "type": "Point",
        "coordinates": [
          -99.2333,
          36.8333
        ]
      },
      "type": "Feature",
      "properties": {
        "hierarchy": [
          "tgn:2586904",
          "tgn:1000001",
          "tgn:7012149",
          "tgn:2001698",
          "tgn:7007707",
          "tgn:7029392"
        ],
        "placetype": [
          "aat:300008347"
        ],
        "id": 2586904,
        "name:xx": "Plainview"
      }
    },
    {
      "geometry": {
        "type": "Point",
        "coordinates": [
          -122.85,
          45.5833
        ]
      },
      "type": "Feature",
      "properties": {
        "hierarchy": [
          "tgn:2586905",
          "tgn:1000001",
          "tgn:7012149",
          "tgn:1002699",
          "tgn:7007708",
          "tgn:7029392"
        ],
        "placetype": [
          "aat:300008347"
        ],
        "id": 2586905,
        "name:xx": "Plainview"
      }
    },
    {
      "geometry": {
        "type": "Point",
        "coordinates": [
          -99.95,
          32.85
        ]
      },
      "type": "Feature",
      "properties": {
        "hierarchy": [
          "tgn:2586906",
          "tgn:1000001",
          "tgn:7012149",
          "tgn:2002014",
          "tgn:7007826",
          "tgn:7029392"
        ],
        "placetype": [
          "aat:300008347"
        ],
        "id": 2586906,
        "name:xx": "Plainview"
      }
    },
    {
      "geometry": {
        "type": "Point",
        "coordinates": [
          -99.8167,
          33.0167
        ]
      },
      "type": "Feature",
      "properties": {
        "hierarchy": [
          "tgn:2586907",
          "tgn:1000001",
          "tgn:7012149",
          "tgn:2002000",
          "tgn:7007826",
          "tgn:7029392"
        ],
        "placetype": [
          "aat:300008347"
        ],
        "id": 2586907,
        "name:xx": "Plainview"
      }
    },
    {
      "geometry": {
        "type": "Point",
        "coordinates": [
          -95.25,
          31.2167
        ]
      },
      "type": "Feature",
      "properties": {
        "hierarchy": [
          "tgn:2586908",
          "tgn:1000001",
          "tgn:7012149",
          "tgn:1002486",
          "tgn:7007826",
          "tgn:7029392"
        ],
        "placetype": [
          "aat:300008347"
        ],
        "id": 2586908,
        "name:xx": "Plainview"
      }
    },
    {
      "geometry": {
        "type": "Point",
        "coordinates": [
          -94.5667,
          31.5333
        ]
      },
      "type": "Feature",
      "properties": {
        "hierarchy": [
          "tgn:2586909",
          "tgn:1000001",
          "tgn:7012149",
          "tgn:1002703",
          "tgn:7007826",
          "tgn:7029392"
        ],
        "placetype": [
          "aat:300008347"
        ],
        "id": 2586909,
        "name:xx": "Plainview"
      }
    }
  ]
}
