{
  "geometry": {
    "type": "Point",
    "coordinates": [
      -87.15,
      40.6833
    ]
  },
  "type": "Feature",
  "properties": {
    "hierarchy": [
      "tgn:2325404",
      "tgn:1002177",
      "tgn:1000001",
      "tgn:7012149",
      "tgn:7007252",
      "tgn:7029392"
    ],
    "placetype": [
      "aat:300006075"
    ],
    "id": 2325404,
    "name:xx": "Ferry Ditch"
  }
}
