{
  "geometry": {
    "type": "Point",
    "coordinates": [
      -116.5667,
      38.7333
    ]
  },
  "type": "Feature",
  "properties": {
    "hierarchy": [
      "tgn:2363939",
      "tgn:1000001",
      "tgn:2001418",
      "tgn:7012149",
      "tgn:7007526",
      "tgn:7029392"
    ],
    "placetype": [
      "aat:300008706"
    ],
    "id": 2363939,
    "name:xx": "Green Monster Creek"
  }
}
