{
  "geometry": {
    "type": "Point",
    "coordinates": [
      -89.9333,
      30.6667
    ]
  },
  "type": "Feature",
  "properties": {
    "hierarchy": [
      "tgn:2394948",
      "tgn:1000001",
      "tgn:7012149",
      "tgn:7007256",
      "tgn:7029392"
    ],
    "placetype": [
      "aat:300008706"
    ],
    "id": 2394948,
    "name:xx": "Holdens Creek"
  }
}
