{
  "geometry": {
    "type": "Point",
    "coordinates": [
      96.3333,
      36.6667
    ]
  },
  "type": "Feature",
  "properties": {
    "hierarchy": [
      "tgn:7018877",
      "tgn:1000004",
      "tgn:7002088",
      "tgn:1000111",
      "tgn:7029392"
    ],
    "placetype": [
      "aat:300008680"
    ],
    "id": 7018877,
    "name:xx": "Nan Hulsan Hu"
  }
}
