{
  "geometry": {
    "type": "Point",
    "coordinates": [
      -100.9833,
      29.8833
    ]
  },
  "type": "Feature",
  "properties": {
    "hierarchy": [
      "tgn:2291422",
      "tgn:1000001",
      "tgn:7012149",
      "tgn:2002088",
      "tgn:7007826",
      "tgn:7029392"
    ],
    "placetype": [
      "aat:300008697"
    ],
    "id": 2291422,
    "name:xx": "Dolan Springs"
  }
}
