{
  "geometry": {
    "type": "Point",
    "coordinates": [
      -6.987,
      41.511
    ]
  },
  "type": "Feature",
  "properties": {
    "hierarchy": [
      "tgn:7030486",
      "tgn:7003818",
      "tgn:1000003",
      "tgn:1000090",
      "tgn:7029392"
    ],
    "placetype": [
      "aat:300007783"
    ],
    "name:pt": "Grijó",
    "id": 7030486
  }
}
