{
  "geometry": {
    "type": "Point",
    "coordinates": [
      -121.2167,
      36.0167
    ]
  },
  "type": "Feature",
  "properties": {
    "hierarchy": [
      "tgn:2632685",
      "tgn:1000001",
      "tgn:7012149",
      "tgn:7007157",
      "tgn:1002684",
      "tgn:7029392"
    ],
    "placetype": [
      "aat:300008761"
    ],
    "id": 2632685,
    "name:xx": "Ruby Canyon"
  }
}
