{
  "geometry": {
    "type": "Point",
    "coordinates": [
      31.245278,
      29.403056
    ]
  },
  "type": "Feature",
  "properties": {
    "hierarchy": [
      "tgn:7523711",
      "tgn:7001242",
      "tgn:7016833",
      "tgn:1001083",
      "tgn:7029392"
    ],
    "placetype": [
      "aat:300008347"
    ],
    "name:en": "Kafr Ḩalāwah",
    "id": 7523711
  }
}
