{
  "geometry": {
    "type": "Point",
    "coordinates": [
      -98.7333,
      40.9167
    ]
  },
  "type": "Feature",
  "properties": {
    "hierarchy": [
      "tgn:2330291",
      "tgn:1000001",
      "tgn:7012149",
      "tgn:7007525",
      "tgn:7029392"
    ],
    "placetype": [
      "aat:300008706"
    ],
    "id": 2330291,
    "name:xx": "Flash Creek"
  }
}
