{
  "geometry": {
    "type": "Point",
    "coordinates": [
      -81.8667,
      27.5667
    ]
  },
  "type": "Feature",
  "properties": {
    "hierarchy": [
      "tgn:2374078",
      "tgn:1000001",
      "tgn:1002452",
      "tgn:7012149",
      "tgn:7007240",
      "tgn:7029392"
    ],
    "placetype": [
      "aat:300008905"
    ],
    "id": 2374078,
    "name:xx": "Hammock Pond"
  }
}
