{
  "geometry": {
    "type": "Point",
    "coordinates": [
      -112.35,
      34.4333
    ]
  },
  "type": "Feature",
  "properties": {
    "hierarchy": [
      "tgn:2193336",
      "tgn:1000001",
      "tgn:7006451",
      "tgn:7012149",
      "tgn:2000103",
      "tgn:7029392"
    ],
    "placetype": [
      "aat:300008347"
    ],
    "id": 2193336,
    "name:xx": "Breezy Pines"
  }
}
