{
  "geometry": {
    "type": "Point",
    "coordinates": [
      -93.9833,
      30.8333
    ]
  },
  "type": "Feature",
  "properties": {
    "hierarchy": [
      "tgn:2144804",
      "tgn:1000001",
      "tgn:7012149",
      "tgn:2002009",
      "tgn:7007826",
      "tgn:7029392"
    ],
    "placetype": [
      "aat:300008798"
    ],
    "id": 2144804,
    "name:xx": "Bald Hill"
  }
}
