{
  "geometry": {
    "type": "Point",
    "coordinates": [
      79.538408,
      26.816323
    ]
  },
  "type": "Feature",
  "properties": {
    "hierarchy": [
      "tgn:7565400",
      "tgn:1000004",
      "tgn:7000198",
      "tgn:7016722",
      "tgn:7029392"
    ],
    "placetype": [
      "aat:300008347"
    ],
    "name:en": "Tājpur Bidhūna",
    "id": 7565400
  }
}
