{
  "geometry": {
    "type": "Point",
    "coordinates": [
      -3.95,
      40.35
    ]
  },
  "type": "Feature",
  "properties": {
    "hierarchy": [
      "tgn:7294720",
      "tgn:7010420",
      "tgn:1000003",
      "tgn:7002795",
      "tgn:1000095",
      "tgn:7029392"
    ],
    "placetype": [
      "aat:300008699"
    ],
    "id": 7294720,
    "name:xx": "Vega, Arroyo de la"
  }
}
