{
  "geometry": {
    "type": "Point",
    "coordinates": [
      75.716667,
      15.45
    ]
  },
  "type": "Feature",
  "properties": {
    "hierarchy": [
      "tgn:7575747",
      "tgn:1000004",
      "tgn:7000198",
      "tgn:1001882",
      "tgn:7029392"
    ],
    "placetype": [
      "aat:300007783"
    ],
    "name:en": "Kanginhāl",
    "id": 7575747
  }
}
