{
  "geometry": {
    "type": "Point",
    "coordinates": [
      -121.6667,
      44.05
    ]
  },
  "type": "Feature",
  "properties": {
    "hierarchy": [
      "tgn:2674927",
      "tgn:1000001",
      "tgn:2001705",
      "tgn:7012149",
      "tgn:7007708",
      "tgn:7029392"
    ],
    "placetype": [
      "aat:300008706"
    ],
    "id": 2674927,
    "name:xx": "Soda Creek"
  }
}
