{
  "geometry": {
    "type": "Point",
    "coordinates": [
      -78.5833,
      38.0167
    ]
  },
  "type": "Feature",
  "properties": {
    "hierarchy": [
      "tgn:2154589",
      "tgn:2002137",
      "tgn:1000001",
      "tgn:7012149",
      "tgn:7007919",
      "tgn:7029392"
    ],
    "placetype": [
      "aat:300008798"
    ],
    "id": 2154589,
    "name:xx": "Bear Den Mountain"
  }
}
