{
  "geometry": {
    "type": "Point",
    "coordinates": [
      -85.7167,
      37.0167
    ]
  },
  "type": "Feature",
  "properties": {
    "hierarchy": [
      "tgn:2182712",
      "tgn:1000001",
      "tgn:7012149",
      "tgn:7007255",
      "tgn:7029392"
    ],
    "placetype": [
      "aat:300008706"
    ],
    "id": 2182712,
    "name:xx": "Blue Spring Creek"
  }
}
