{
  "type": "FeatureCollection",
  "features": [
    {
      "geometry": {
        "type": "Point",
        "coordinates": [
          -82.2667,
          37.6167
        ]
      },
      "type": "Feature",
      "properties": {
        "hierarchy": [
          "tgn:2037681",
          "tgn:1000001",
          "tgn:7012149",
          "tgn:2000837",
          "tgn:7007255",
          "tgn:7029392"
        ],
        "placetype": [
          "aat:300008347"
        ],
        "id": 2037681,
        "name:xx": "Belfry"
      }
    },
    {
      "geometry": {
        "type": "Point",
        "coordinates": [
          -83.2833,
          37.7167
        ]
      },
      "type": "Feature",
      "properties": {
        "hierarchy": [
          "tgn:2037685",
          "tgn:1000001",
          "tgn:7012149",
          "tgn:2000853",
          "tgn:7007255",
          "tgn:7029392"
        ],
        "placetype": [
          "aat:300008347",
          "aat:300387210"
        ],
        "id": 2037685,
        "name:xx": "Belknap"
      }
    },
    {
      "geometry": {
        "type": "Point",
        "coordinates": [
          -85.6167,
          38.3667
        ]
      },
      "type": "Feature",
      "properties": {
        "hierarchy": [
          "tgn:2037686",
          "tgn:1000001",
          "tgn:7012149",
          "tgn:1002744",
          "tgn:7007255",
          "tgn:7029392"
        ],
        "placetype": [
          "aat:300008347"
        ],
        "id": 2037686,
        "name:xx": "Belknap Beach"
      }
    },
    {
      "geometry": {
        "type": "Point",
        "coordinates": [
          -83.1167,
          38.0833
        ]
      },
      "type": "Feature",
      "properties": {
        "hierarchy": [
          "tgn:2037687",
          "tgn:1000001",
          "tgn:7012149",
          "tgn:1002354",
          "tgn:7007255",
          "tgn:7029392"
        ],
        "placetype": [
          "aat:300008347",
          "aat:300387210"
        ],
        "id": 2037687,
        "name:xx": "Bell City"
      }
    },
    {
      "geometry": {
        "type": "Point",
        "coordinates": [
          -88.5,
          36.5333
        ]
      },
      "type": "Feature",
      "properties": {
        "hierarchy": [
          "tgn:2037688",
          "tgn:1000001",
          "tgn:7012149",
          "tgn:2000792",
          "tgn:7007255",
          "tgn:7029392"
        ],
        "placetype": [
          "aat:300008347"
        ],
        "id": 2037688,
        "name:xx": "Bell City"
      }
    }
  ]
}
