{
  "type": "FeatureCollection",
  "features": [
    {
      "geometry": {
        "type": "Point",
        "coordinates": [
          -81.3833,
          37.0667
        ]
      },
      "type": "Feature",
      "properties": {
        "hierarchy": [
          "tgn:2372830",
          "tgn:1000001",
          "tgn:7012149",
          "tgn:2002192",
          "tgn:7007919",
          "tgn:7029392"
        ],
        "placetype": [
          "aat:300266640"
        ],
        "id": 2372830,
        "name:xx": "Hall Ridge"
      }
    },
    {
      "geometry": {
        "type": "Point",
        "coordinates": [
          -121.6333,
          46.5667
        ]
      },
      "type": "Feature",
      "properties": {
        "hierarchy": [
          "tgn:2372831",
          "tgn:1000001",
          "tgn:7012149",
          "tgn:1002594",
          "tgn:7007920",
          "tgn:7029392"
        ],
        "placetype": [
          "aat:300266640"
        ],
        "id": 2372831,
        "name:xx": "Hall Ridge"
      }
    },
    {
      "geometry": {
        "type": "Point",
        "coordinates": [
          -85.8167,
          38.55
        ]
      },
      "type": "Feature",
      "properties": {
        "hierarchy": [
          "tgn:2372832",
          "tgn:1000001",
          "tgn:1002273",
          "tgn:7012149",
          "tgn:7007252",
          "tgn:7029392"
        ],
        "placetype": [
          "aat:300008699"
        ],
        "id": 2372832,
        "name:xx": "Hall Run"
      }
    },
    {
      "geometry": {
        "type": "Point",
        "coordinates": [
          -84.2833,
          39.0667
        ]
      },
      "type": "Feature",
      "properties": {
        "hierarchy": [
          "tgn:2372833",
          "tgn:1000001",
          "tgn:1002279",
          "tgn:7012149",
          "tgn:7007706",
          "tgn:7029392"
        ],
        "placetype": [
          "aat:300008699"
        ],
        "id": 2372833,
        "name:xx": "Hall Run"
      }
    },
    {
      "geometry": {
        "type": "Point",
        "coordinates": [
          -78,
          40.9167
        ]
      },
      "type": "Feature",
      "properties": {
        "hierarchy": [
          "tgn:2372834",
          "tgn:1000001",
          "tgn:1002249",
          "tgn:7012149",
          "tgn:7007710",
          "tgn:7029392"
        ],
        "placetype": [
          "aat:300008699"
        ],
        "id": 2372834,
        "name:xx": "Hall Run"
      }
    },
    {
      "geometry": {
        "type": "Point",
        "coordinates": [
          -77.7667,
          41.2667
        ]
      },
      "type": "Feature",
      "properties": {
        "hierarchy": [
          "tgn:2372835",
          "tgn:1000001",
          "tgn:1002286",
          "tgn:7012149",
          "tgn:7007710",
          "tgn:7029392"
        ],
        "placetype": [
          "aat:300008699"
        ],
        "id": 2372835,
        "name:xx": "Hall Run"
      }
    },
    {
      "geometry": {
        "type": "Point",
        "coordinates": [
          -79.45,
          39.7167
        ]
      },
      "type": "Feature",
      "properties": {
        "hierarchy": [
          "tgn:2372836",
          "tgn:1000001",
          "tgn:7012149",
          "tgn:7014185",
          "tgn:7007710",
          "tgn:7029392"
        ],
        "placetype": [
          "aat:300008699"
        ],
        "id": 2372836,
        "name:xx": "Hall Run"
      }
    },
    {
      "geometry": {
        "type": "Point",
        "coordinates": [
          -80.55,
          40.0667
        ]
      },
      "type": "Feature",
      "properties": {
        "hierarchy": [
          "tgn:2372837",
          "tgn:1000001",
          "tgn:7012149",
          "tgn:2002276",
          "tgn:7013961",
          "tgn:7029392"
        ],
        "placetype": [
          "aat:300008699"
        ],
        "id": 2372837,
        "name:xx": "Hall Run"
      }
    },
    {
      "geometry": {
        "type": "Point",
        "coordinates": [
          -85.8167,
          38.7833
        ]
      },
      "type": "Feature",
      "properties": {
        "hierarchy": [
          "tgn:2372838",
          "tgn:1000001",
          "tgn:7012149",
          "tgn:1002508",
          "tgn:7007252",
          "tgn:7029392"
        ],
        "placetype": [
          "aat:300006075"
        ],
        "id": 2372838,
        "name:xx": "Hall Sherman Ditch"
      }
    },
    {
      "geometry": {
        "type": "Point",
        "coordinates": [
          -83.65,
          37.8833
        ]
      },
      "type": "Feature",
      "properties": {
        "hierarchy": [
          "tgn:2372839",
          "tgn:1000001",
          "tgn:7012149",
          "tgn:2000826",
          "tgn:7007255",
          "tgn:7029392"
        ],
        "placetype": [
          "aat:300008699"
        ],
        "id": 2372839,
        "name:xx": "Hall Sink Branch"
      }
    }
  ]
}
