{
  "geometry": {
    "type": "Point",
    "coordinates": [
      -94.4333,
      37.65
    ]
  },
  "type": "Feature",
  "properties": {
    "hierarchy": [
      "tgn:2326487",
      "tgn:1000001",
      "tgn:7012149",
      "tgn:2001253",
      "tgn:7007523",
      "tgn:7029392"
    ],
    "placetype": [
      "aat:300006191"
    ],
    "id": 2326487,
    "name:xx": "Finis Moss Lake"
  }
}
