{
  "geometry": {
    "type": "Point",
    "coordinates": [
      -91.4333,
      37.8167
    ]
  },
  "type": "Feature",
  "properties": {
    "hierarchy": [
      "tgn:2588101",
      "tgn:1000001",
      "tgn:7012149",
      "tgn:2001190",
      "tgn:7007523",
      "tgn:7029392"
    ],
    "placetype": [
      "aat:300006191"
    ],
    "id": 2588101,
    "name:xx": "Ploch Lake"
  }
}
