{
  "geometry": {
    "type": "Point",
    "coordinates": [
      -85.8167,
      38.35
    ]
  },
  "type": "Feature",
  "properties": {
    "hierarchy": [
      "tgn:2144996",
      "tgn:1000001",
      "tgn:7012149",
      "tgn:1002376",
      "tgn:7007252",
      "tgn:7029392"
    ],
    "placetype": [
      "aat:300008706"
    ],
    "id": 2144996,
    "name:xx": "Bald Knob Creek"
  }
}
