{
  "type": "FeatureCollection",
  "features": [
    {
      "geometry": {
        "type": "Point",
        "coordinates": [
          -87.0833,
          39.25
        ]
      },
      "type": "Feature",
      "properties": {
        "hierarchy": [
          "tgn:2275510",
          "tgn:1000001",
          "tgn:2000540",
          "tgn:7012149",
          "tgn:7007252",
          "tgn:7029392"
        ],
        "placetype": [
          "aat:300008347"
        ],
        "id": 2275510,
        "name:xx": "Danville"
      }
    },
    {
      "geometry": {
        "type": "Point",
        "coordinates": [
          -84.7667,
          37.6333
        ]
      },
      "type": "Feature",
      "properties": {
        "hierarchy": [
          "tgn:2275511",
          "tgn:1000001",
          "tgn:7012149",
          "tgn:1002829",
          "tgn:7007255",
          "tgn:7029392"
        ],
        "placetype": [
          "aat:300008347"
        ],
        "id": 2275511,
        "name:xx": "Danville"
      }
    },
    {
      "geometry": {
        "type": "Point",
        "coordinates": [
          -76.9167,
          38.6833
        ]
      },
      "type": "Feature",
      "properties": {
        "hierarchy": [
          "tgn:2275512",
          "tgn:1000001",
          "tgn:2124001",
          "tgn:7012149",
          "tgn:7007516",
          "tgn:7029392"
        ],
        "placetype": [
          "aat:300008347"
        ],
        "id": 2275512,
        "name:xx": "Danville"
      }
    },
    {
      "geometry": {
        "type": "Point",
        "coordinates": [
          -116.5167,
          38.7667
        ]
      },
      "type": "Feature",
      "properties": {
        "hierarchy": [
          "tgn:2275513",
          "tgn:1000001",
          "tgn:2001418",
          "tgn:7012149",
          "tgn:7007526",
          "tgn:7029392"
        ],
        "placetype": [
          "aat:300008347"
        ],
        "id": 2275513,
        "name:xx": "Danville"
      }
    },
    {
      "geometry": {
        "type": "Point",
        "coordinates": [
          -75.4667,
          42
        ]
      },
      "type": "Feature",
      "properties": {
        "hierarchy": [
          "tgn:2275514",
          "tgn:1000001",
          "tgn:1002206",
          "tgn:7012149",
          "tgn:7007568",
          "tgn:7029392"
        ],
        "placetype": [
          "aat:300008347"
        ],
        "id": 2275514,
        "name:xx": "Danville"
      }
    },
    {
      "geometry": {
        "type": "Point",
        "coordinates": [
          -87.9333,
          36.3
        ]
      },
      "type": "Feature",
      "properties": {
        "hierarchy": [
          "tgn:2275516",
          "tgn:1000001",
          "tgn:7012149",
          "tgn:2001878",
          "tgn:7007825",
          "tgn:7029392"
        ],
        "placetype": [
          "aat:300008347"
        ],
        "id": 2275516,
        "name:xx": "Danville"
      }
    },
    {
      "geometry": {
        "type": "Point",
        "coordinates": [
          -122.0167,
          47.35
        ]
      },
      "type": "Feature",
      "properties": {
        "hierarchy": [
          "tgn:2275517",
          "tgn:1000001",
          "tgn:7012149",
          "tgn:7018871",
          "tgn:7007920",
          "tgn:7029392"
        ],
        "placetype": [
          "aat:300008347"
        ],
        "id": 2275517,
        "name:xx": "Danville"
      }
    },
    {
      "geometry": {
        "type": "Point",
        "coordinates": [
          -87.1167,
          34.4167
        ]
      },
      "type": "Feature",
      "properties": {
        "hierarchy": [
          "tgn:2275518",
          "tgn:7002659",
          "tgn:1000001",
          "tgn:7012149",
          "tgn:7029392"
        ],
        "placetype": [
          "aat:300008699"
        ],
        "id": 2275518,
        "name:xx": "Danville Branch"
      }
    },
    {
      "geometry": {
        "type": "Point",
        "coordinates": [
          -116.5667,
          38.7833
        ]
      },
      "type": "Feature",
      "properties": {
        "hierarchy": [
          "tgn:2275519",
          "tgn:1000001",
          "tgn:2001418",
          "tgn:7012149",
          "tgn:7007526",
          "tgn:7029392"
        ],
        "placetype": [
          "aat:300008761"
        ],
        "id": 2275519,
        "name:xx": "Danville Canyon"
      }
    }
  ]
}
