{
  "geometry": {
    "type": "Point",
    "coordinates": [
      -112.7667,
      37.8833
    ]
  },
  "type": "Feature",
  "properties": {
    "hierarchy": [
      "tgn:2109157",
      "tgn:1000001",
      "tgn:7012149",
      "tgn:2002111",
      "tgn:7007827",
      "tgn:7029392"
    ],
    "placetype": [
      "aat:300008347"
    ],
    "id": 2109157,
    "name:xx": "Paragonah"
  }
}
