{
  "geometry": {
    "type": "Point",
    "coordinates": [
      14.6333,
      51.5167
    ]
  },
  "type": "Feature",
  "properties": {
    "hierarchy": [
      "tgn:1037952",
      "tgn:1000003",
      "tgn:7003685",
      "tgn:7000084",
      "tgn:7029392"
    ],
    "placetype": [
      "aat:300008347"
    ],
    "id": 1037952,
    "name:xx": "Weisswasser"
  }
}
