{
  "geometry": {
    "type": "Point",
    "coordinates": [
      76.975,
      28.934444
    ]
  },
  "type": "Feature",
  "properties": {
    "hierarchy": [
      "tgn:7590476",
      "tgn:1000004",
      "tgn:1001871",
      "tgn:7000198",
      "tgn:7029392"
    ],
    "placetype": [
      "aat:300008347"
    ],
    "name:en": "Rohāt",
    "id": 7590476
  }
}
