{
  "geometry": {
    "type": "Point",
    "coordinates": [
      -88.4667,
      43.9167
    ]
  },
  "type": "Feature",
  "properties": {
    "hierarchy": [
      "tgn:2280467",
      "tgn:1000001",
      "tgn:7012149",
      "tgn:2002363",
      "tgn:7007922",
      "tgn:7029392"
    ],
    "placetype": [
      "aat:300008347"
    ],
    "id": 2280467,
    "name:xx": "Decorah Beach"
  }
}
