{
  "type": "FeatureCollection",
  "features": [
    {
      "geometry": {
        "type": "Point",
        "coordinates": [
          5.262777,
          50.740813
        ]
      },
      "type": "Feature",
      "properties": {
        "hierarchy": [
          "tgn:7251960",
          "tgn:7003461",
          "tgn:1000003",
          "tgn:1000063",
          "tgn:7018236",
          "tgn:7029392"
        ],
        "placetype": [
          "aat:300008347"
        ],
        "id": 7251960,
        "name:xx": "Mechelen-Bovelingen"
      }
    },
    {
      "geometry": {
        "type": "Point",
        "coordinates": [
          5.7,
          50.966667
        ]
      },
      "type": "Feature",
      "properties": {
        "hierarchy": [
          "tgn:7251962",
          "tgn:7003461",
          "tgn:1000003",
          "tgn:1000063",
          "tgn:7018236",
          "tgn:7029392"
        ],
        "placetype": [
          "aat:300008347"
        ],
        "id": 7251962,
        "name:xx": "Mechelen-aan-de-Maas"
      }
    },
    {
      "geometry": {
        "type": "Point",
        "coordinates": [
          3.56538,
          50.814488
        ]
      },
      "type": "Feature",
      "properties": {
        "hierarchy": [
          "tgn:7251967",
          "tgn:7003457",
          "tgn:1000003",
          "tgn:1000063",
          "tgn:7018236",
          "tgn:7029392"
        ],
        "placetype": [
          "aat:300008347"
        ],
        "id": 7251967,
        "name:xx": "Melden"
      }
    },
    {
      "geometry": {
        "type": "Point",
        "coordinates": [
          5.716667,
          49.883333
        ]
      },
      "type": "Feature",
      "properties": {
        "hierarchy": [
          "tgn:7251969",
          "tgn:7003465",
          "tgn:1000003",
          "tgn:1000063",
          "tgn:4012014",
          "tgn:7029392"
        ],
        "placetype": [
          "aat:300008863"
        ],
        "id": 7251969,
        "name:xx": "Melch, Bois de"
      }
    }
  ]
}
