{
  "geometry": {
    "type": "Point",
    "coordinates": [
      -93.8833,
      46.8667
    ]
  },
  "type": "Feature",
  "properties": {
    "hierarchy": [
      "tgn:2783027",
      "tgn:1000001",
      "tgn:2001009",
      "tgn:7012149",
      "tgn:7007521",
      "tgn:7029392"
    ],
    "placetype": [
      "aat:300008680"
    ],
    "id": 2783027,
    "name:xx": "Wren Lake"
  }
}
