{
  "geometry": {
    "type": "Point",
    "coordinates": [
      -79.45,
      35.0167
    ]
  },
  "type": "Feature",
  "properties": {
    "hierarchy": [
      "tgn:2458371",
      "tgn:1000001",
      "tgn:7012149",
      "tgn:2001539",
      "tgn:7007709",
      "tgn:7029392"
    ],
    "placetype": [
      "aat:300006191"
    ],
    "id": 2458371,
    "name:xx": "Little Muddy Lake"
  }
}
