{
  "geometry": {
    "type": "Point",
    "coordinates": [
      -102.05,
      39.6333
    ]
  },
  "type": "Feature",
  "properties": {
    "hierarchy": [
      "tgn:2371736",
      "tgn:1000001",
      "tgn:7012149",
      "tgn:7007158",
      "tgn:2000254",
      "tgn:7029392"
    ],
    "placetype": [
      "aat:300006191"
    ],
    "id": 2371736,
    "name:xx": "Hale Ponds"
  }
}
