{
  "geometry": {
    "type": "Point",
    "coordinates": [
      -75.2833,
      40.5667
    ]
  },
  "type": "Feature",
  "properties": {
    "hierarchy": [
      "tgn:2663317",
      "tgn:1000001",
      "tgn:7012149",
      "tgn:1002729",
      "tgn:7007710",
      "tgn:7029392"
    ],
    "placetype": [
      "aat:300008706"
    ],
    "id": 2663317,
    "name:xx": "Silver Creek"
  }
}
