{
  "geometry": {
    "type": "Point",
    "coordinates": [
      -111.7333,
      39.5333
    ]
  },
  "type": "Feature",
  "properties": {
    "hierarchy": [
      "tgn:2280163",
      "tgn:1000001",
      "tgn:7012149",
      "tgn:2002112",
      "tgn:7007827",
      "tgn:7029392"
    ],
    "placetype": [
      "aat:300008761"
    ],
    "id": 2280163,
    "name:xx": "Death Hollow"
  }
}
