{
  "geometry": {
    "type": "Point",
    "coordinates": [
      -118.1833,
      34.1833
    ]
  },
  "type": "Feature",
  "properties": {
    "hierarchy": [
      "tgn:7019086",
      "tgn:1000001",
      "tgn:7012149",
      "tgn:7007157",
      "tgn:1002608",
      "tgn:7029392"
    ],
    "placetype": [
      "aat:300008347"
    ],
    "id": 7019086,
    "name:xx": "La Cañada Flintridge"
  }
}
