{
  "geometry": {
    "type": "Point",
    "coordinates": [
      139.0667,
      35.7833
    ]
  },
  "type": "Feature",
  "properties": {
    "hierarchy": [
      "tgn:1101204",
      "tgn:1000004",
      "tgn:7000894",
      "tgn:1001032",
      "tgn:1000120",
      "tgn:7029392"
    ],
    "placetype": [
      "aat:300006084"
    ],
    "id": 1101204,
    "name:xx": "Ogōchi-dam"
  }
}
