{
  "geometry": {
    "type": "Point",
    "coordinates": [
      85.9189,
      21.249088
    ]
  },
  "type": "Feature",
  "properties": {
    "hierarchy": [
      "tgn:7556556",
      "tgn:1000004",
      "tgn:7000198",
      "tgn:7016694",
      "tgn:7029392"
    ],
    "placetype": [
      "aat:300008347"
    ],
    "name:en": "Sagarpāta",
    "id": 7556556
  }
}
