{
  "geometry": {
    "type": "Point",
    "coordinates": [
      -105.4833,
      44.4167
    ]
  },
  "type": "Feature",
  "properties": {
    "hierarchy": [
      "tgn:2528501",
      "tgn:1000001",
      "tgn:2002367",
      "tgn:7012149",
      "tgn:7007923",
      "tgn:7029392"
    ],
    "placetype": [
      "aat:300000390"
    ],
    "id": 2528501,
    "name:xx": "Moyer Mine"
  }
}
