{
  "geometry": {
    "type": "Point",
    "coordinates": [
      14.4667,
      35.8833
    ]
  },
  "type": "Feature",
  "properties": {
    "hierarchy": [
      "tgn:7005748",
      "tgn:1000003",
      "tgn:7594223",
      "tgn:7005729",
      "tgn:7029392"
    ],
    "placetype": [
      "aat:300008347"
    ],
    "id": 7005748,
    "name:xx": "Qormi"
  }
}
