{
  "type": "FeatureCollection",
  "features": [
    {
      "geometry": {
        "type": "Point",
        "coordinates": [
          13.883333,
          41.266667
        ]
      },
      "type": "Feature",
      "properties": {
        "hierarchy": [
          "tgn:4006175",
          "tgn:7003002",
          "tgn:7003005",
          "tgn:1000003",
          "tgn:1000080",
          "tgn:7029392"
        ],
        "placetype": [
          "aat:300008347"
        ],
        "id": 4006175,
        "name:xx": "Lauro"
      }
    },
    {
      "geometry": {
        "type": "Point",
        "coordinates": [
          8.1,
          48.516667
        ]
      },
      "type": "Feature",
      "properties": {
        "hierarchy": [
          "tgn:4006179",
          "tgn:7003692",
          "tgn:1000003",
          "tgn:7000084",
          "tgn:7029392"
        ],
        "placetype": [
          "aat:300008347",
          "aat:300387200",
          "aat:300008375"
        ],
        "name:en": "Lautenbach",
        "id": 4006179,
        "name:de": "Lautenbach"
      }
    }
  ]
}
