{
  "geometry": {
    "type": "Point",
    "coordinates": [
      31.35,
      31.433333
    ]
  },
  "type": "Feature",
  "properties": {
    "hierarchy": [
      "tgn:7529423",
      "tgn:7001242",
      "tgn:1001059",
      "tgn:7016833",
      "tgn:7029392"
    ],
    "placetype": [
      "aat:300005926"
    ],
    "name:en": "Sīdī 'Aţīyah Abū Māḑī",
    "id": 7529423
  }
}
