{
  "geometry": {
    "type": "Point",
    "coordinates": [
      -99.95,
      32.3333
    ]
  },
  "type": "Feature",
  "properties": {
    "hierarchy": [
      "tgn:2225788",
      "tgn:1000001",
      "tgn:7012149",
      "tgn:2002081",
      "tgn:7007826",
      "tgn:7029392"
    ],
    "placetype": [
      "aat:300008798"
    ],
    "id": 2225788,
    "name:xx": "Cat Heads"
  }
}
