{
  "geometry": {
    "type": "Point",
    "coordinates": [
      -77.9167,
      35.8333
    ]
  },
  "type": "Feature",
  "properties": {
    "hierarchy": [
      "tgn:2077271",
      "tgn:1000001",
      "tgn:7012149",
      "tgn:2001522",
      "tgn:7007709",
      "tgn:7029392"
    ],
    "placetype": [
      "aat:300008347",
      "aat:300387210"
    ],
    "id": 2077271,
    "name:xx": "Winstead Crossroads"
  }
}
