{
  "geometry": {
    "type": "Point",
    "coordinates": [
      -104.3167,
      42.1333
    ]
  },
  "type": "Feature",
  "properties": {
    "hierarchy": [
      "tgn:2608708",
      "tgn:1000001",
      "tgn:7012149",
      "tgn:2002372",
      "tgn:7007923",
      "tgn:7029392"
    ],
    "placetype": [
      "aat:300266640"
    ],
    "id": 2608708,
    "name:xx": "Rattlesnake Point"
  }
}
