{
  "type": "FeatureCollection",
  "features": [
    {
      "geometry": {
        "type": "Point",
        "coordinates": [
          -97.65,
          25.466667
        ]
      },
      "type": "Feature",
      "properties": {
        "hierarchy": [
          "tgn:7381630",
          "tgn:1000001",
          "tgn:7005597",
          "tgn:7005560",
          "tgn:7029392"
        ],
        "placetype": [
          "aat:300008347"
        ],
        "id": 7381630,
        "name:xx": "Los Ángeles"
      }
    },
    {
      "geometry": {
        "type": "Point",
        "coordinates": [
          -106.516667,
          25.233333
        ]
      },
      "type": "Feature",
      "properties": {
        "hierarchy": [
          "tgn:7381631",
          "tgn:7005583",
          "tgn:1000001",
          "tgn:7005560",
          "tgn:7029392"
        ],
        "placetype": [
          "aat:300008347"
        ],
        "id": 7381631,
        "name:xx": "Los Ángeles"
      }
    },
    {
      "geometry": {
        "type": "Point",
        "coordinates": [
          -104.566667,
          25.2
        ]
      },
      "type": "Feature",
      "properties": {
        "hierarchy": [
          "tgn:7381632",
          "tgn:7005583",
          "tgn:1000001",
          "tgn:7005560",
          "tgn:7029392"
        ],
        "placetype": [
          "aat:300008347"
        ],
        "id": 7381632,
        "name:xx": "Los Angeles"
      }
    },
    {
      "geometry": {
        "type": "Point",
        "coordinates": [
          -99.819444,
          24.963611
        ]
      },
      "type": "Feature",
      "properties": {
        "hierarchy": [
          "tgn:7381633",
          "tgn:1000001",
          "tgn:7005589",
          "tgn:7005560",
          "tgn:7029392"
        ],
        "placetype": [
          "aat:300008347"
        ],
        "id": 7381633,
        "name:xx": "Los Angeles"
      }
    },
    {
      "geometry": {
        "type": "Point",
        "coordinates": [
          -103.2,
          24.566667
        ]
      },
      "type": "Feature",
      "properties": {
        "hierarchy": [
          "tgn:7381635",
          "tgn:7005583",
          "tgn:1000001",
          "tgn:7005560",
          "tgn:7029392"
        ],
        "placetype": [
          "aat:300008347"
        ],
        "id": 7381635,
        "name:xx": "Los Angeles"
      }
    },
    {
      "geometry": {
        "type": "Point",
        "coordinates": [
          -99.066667,
          24.416667
        ]
      },
      "type": "Feature",
      "properties": {
        "hierarchy": [
          "tgn:7381636",
          "tgn:1000001",
          "tgn:7005597",
          "tgn:7005560",
          "tgn:7029392"
        ],
        "placetype": [
          "aat:300008347"
        ],
        "id": 7381636,
        "name:xx": "Los Ángeles"
      }
    },
    {
      "geometry": {
        "type": "Point",
        "coordinates": [
          -99.9,
          24.35
        ]
      },
      "type": "Feature",
      "properties": {
        "hierarchy": [
          "tgn:7381637",
          "tgn:1000001",
          "tgn:7005589",
          "tgn:7005560",
          "tgn:7029392"
        ],
        "placetype": [
          "aat:300008347"
        ],
        "id": 7381637,
        "name:xx": "Los Ángeles"
      }
    },
    {
      "geometry": {
        "type": "Point",
        "coordinates": [
          -98.85,
          24.266667
        ]
      },
      "type": "Feature",
      "properties": {
        "hierarchy": [
          "tgn:7381638",
          "tgn:1000001",
          "tgn:7005597",
          "tgn:7005560",
          "tgn:7029392"
        ],
        "placetype": [
          "aat:300008347"
        ],
        "id": 7381638,
        "name:xx": "Los Angeles"
      }
    },
    {
      "geometry": {
        "type": "Point",
        "coordinates": [
          -99.916667,
          24.15
        ]
      },
      "type": "Feature",
      "properties": {
        "hierarchy": [
          "tgn:7381639",
          "tgn:1000001",
          "tgn:7005597",
          "tgn:7005560",
          "tgn:7029392"
        ],
        "placetype": [
          "aat:300008347"
        ],
        "id": 7381639,
        "name:xx": "Los Ángeles"
      }
    }
  ]
}
