{
  "geometry": {
    "type": "Point",
    "coordinates": [
      79.342412,
      27.011007
    ]
  },
  "type": "Feature",
  "properties": {
    "hierarchy": [
      "tgn:7562515",
      "tgn:1000004",
      "tgn:7000198",
      "tgn:7016722",
      "tgn:7029392"
    ],
    "placetype": [
      "aat:300008347"
    ],
    "name:en": "Ratbhānpur",
    "id": 7562515
  }
}
