{
  "geometry": {
    "type": "Point",
    "coordinates": [
      19.25,
      49.85
    ]
  },
  "type": "Feature",
  "properties": {
    "hierarchy": [
      "tgn:7023915",
      "tgn:1000003",
      "tgn:7024125",
      "tgn:7006366",
      "tgn:7029392"
    ],
    "placetype": [
      "aat:300008347"
    ],
    "id": 7023915,
    "name:xx": "Czaniec"
  }
}
