{
  "geometry": {
    "type": "Point",
    "coordinates": [
      -74.65,
      41.7667
    ]
  },
  "type": "Feature",
  "properties": {
    "hierarchy": [
      "tgn:2657705",
      "tgn:1000001",
      "tgn:7012149",
      "tgn:1002926",
      "tgn:7007568",
      "tgn:7029392"
    ],
    "placetype": [
      "aat:300008699"
    ],
    "id": 2657705,
    "name:xx": "Sheldrake Stream"
  }
}
