{
  "geometry": {
    "type": "Point",
    "coordinates": [
      20.783333,
      38.15
    ]
  },
  "type": "Feature",
  "properties": {
    "hierarchy": [
      "tgn:7226191",
      "tgn:7011167",
      "tgn:7001338",
      "tgn:1000003",
      "tgn:1000074",
      "tgn:7029392"
    ],
    "placetype": [
      "aat:300008850"
    ],
    "id": 7226191,
    "name:xx": "Sarakináto, Ákra"
  }
}
