{
  "geometry": {
    "type": "Point",
    "coordinates": [
      -83.7667,
      37.4667
    ]
  },
  "type": "Feature",
  "properties": {
    "hierarchy": [
      "tgn:2299197",
      "tgn:1000001",
      "tgn:7012149",
      "tgn:7007255",
      "tgn:7029392"
    ],
    "placetype": [
      "aat:300008699"
    ],
    "id": 2299197,
    "name:xx": "Duck Fork"
  }
}
