{
  "type": "FeatureCollection",
  "features": [
    {
      "geometry": {
        "type": "Point",
        "coordinates": [
          -88.8833,
          31.1167
        ]
      },
      "type": "Feature",
      "properties": {
        "hierarchy": [
          "tgn:2576530",
          "tgn:1000001",
          "tgn:7012149",
          "tgn:2001141",
          "tgn:7007522",
          "tgn:7029392"
        ],
        "placetype": [
          "aat:300006191"
        ],
        "id": 2576530,
        "name:xx": "Perry, Lake"
      }
    },
    {
      "geometry": {
        "type": "Point",
        "coordinates": [
          -90.05,
          37.65
        ]
      },
      "type": "Feature",
      "properties": {
        "hierarchy": [
          "tgn:2576531",
          "tgn:1000001",
          "tgn:7012149",
          "tgn:2001228",
          "tgn:7007523",
          "tgn:7029392"
        ],
        "placetype": [
          "aat:300006191"
        ],
        "id": 2576531,
        "name:xx": "Perry, Lake"
      }
    },
    {
      "geometry": {
        "type": "Point",
        "coordinates": [
          -116.7167,
          36.2667
        ]
      },
      "type": "Feature",
      "properties": {
        "hierarchy": [
          "tgn:2576533",
          "tgn:1000001",
          "tgn:7012149",
          "tgn:2000183",
          "tgn:7007157",
          "tgn:7029392"
        ],
        "placetype": [
          "aat:300008798"
        ],
        "id": 2576533,
        "name:xx": "Perry, Mount"
      }
    },
    {
      "geometry": {
        "type": "Point",
        "coordinates": [
          -71.0167,
          42.75
        ]
      },
      "type": "Feature",
      "properties": {
        "hierarchy": [
          "tgn:2576534",
          "tgn:1000001",
          "tgn:1002359",
          "tgn:7012149",
          "tgn:7007517",
          "tgn:7029392"
        ],
        "placetype": [
          "aat:300008798"
        ],
        "id": 2576534,
        "name:xx": "Perry, Mount"
      }
    },
    {
      "geometry": {
        "type": "Point",
        "coordinates": [
          -122.9333,
          42.3167
        ]
      },
      "type": "Feature",
      "properties": {
        "hierarchy": [
          "tgn:2576536",
          "tgn:1000001",
          "tgn:7012149",
          "tgn:2001711",
          "tgn:7007708",
          "tgn:7029392"
        ],
        "placetype": [
          "aat:300008347"
        ],
        "id": 2576536,
        "name:xx": "Perrydale"
      }
    },
    {
      "geometry": {
        "type": "Point",
        "coordinates": [
          -80.25,
          36.0333
        ]
      },
      "type": "Feature",
      "properties": {
        "hierarchy": [
          "tgn:2576537",
          "tgn:1000001",
          "tgn:7012149",
          "tgn:2001494",
          "tgn:7007709",
          "tgn:7029392"
        ],
        "placetype": [
          "aat:300008699"
        ],
        "id": 2576537,
        "name:xx": "Perryman Branch"
      }
    },
    {
      "geometry": {
        "type": "Point",
        "coordinates": [
          -98.0167,
          31.2833
        ]
      },
      "type": "Feature",
      "properties": {
        "hierarchy": [
          "tgn:2576538",
          "tgn:1000001",
          "tgn:7012149",
          "tgn:1002303",
          "tgn:7007826",
          "tgn:7029392"
        ],
        "placetype": [
          "aat:300008706"
        ],
        "id": 2576538,
        "name:xx": "Perryman Creek"
      }
    }
  ]
}
