{
  "geometry": {
    "type": "Point",
    "coordinates": [
      -79.7667,
      33.1333
    ]
  },
  "type": "Feature",
  "properties": {
    "hierarchy": [
      "tgn:2337865",
      "tgn:2001732",
      "tgn:1000001",
      "tgn:7012149",
      "tgn:7007712",
      "tgn:7029392"
    ],
    "placetype": [
      "aat:300008699"
    ],
    "id": 2337865,
    "name:xx": "Fox Gully Branch"
  }
}
