{
  "geometry": {
    "type": "Point",
    "coordinates": [
      -98.35,
      44.8833
    ]
  },
  "type": "Feature",
  "properties": {
    "hierarchy": [
      "tgn:2328417",
      "tgn:1000001",
      "tgn:7012149",
      "tgn:2001827",
      "tgn:7007713",
      "tgn:7029392"
    ],
    "placetype": [
      "aat:300055621"
    ],
    "id": 2328417,
    "name:xx": "Fisher Grove"
  }
}
