{
  "geometry": {
    "type": "Point",
    "coordinates": [
      11.85,
      48.95
    ]
  },
  "type": "Feature",
  "properties": {
    "hierarchy": [
      "tgn:7102192",
      "tgn:7003669",
      "tgn:1000003",
      "tgn:7000084",
      "tgn:7029392"
    ],
    "placetype": [
      "aat:300008777"
    ],
    "id": 7102192,
    "name:xx": "Rothenbuckel"
  }
}
