{
  "geometry": {
    "type": "Point",
    "coordinates": [
      76.568,
      20.707
    ]
  },
  "type": "Feature",
  "properties": {
    "hierarchy": [
      "tgn:1075819",
      "tgn:1000004",
      "tgn:7000198",
      "tgn:1001895",
      "tgn:7029392"
    ],
    "placetype": [
      "aat:300008347"
    ],
    "name:en": "Khāmgaon",
    "id": 1075819
  }
}
