{
  "type": "FeatureCollection",
  "features": [
    {
      "geometry": {
        "type": "Point",
        "coordinates": [
          -1.033333,
          60.6
        ]
      },
      "type": "Feature",
      "properties": {
        "hierarchy": [
          "tgn:7458680",
          "tgn:7002444",
          "tgn:1000003",
          "tgn:7029508",
          "tgn:7008591",
          "tgn:7029392"
        ],
        "placetype": [
          "aat:300386846"
        ],
        "name:en": "Lussetter, Ness of",
        "id": 7458680
      }
    },
    {
      "geometry": {
        "type": "Point",
        "coordinates": [
          -5.733333,
          56.4
        ]
      },
      "type": "Feature",
      "properties": {
        "hierarchy": [
          "tgn:7458681",
          "tgn:7019094",
          "tgn:7002444",
          "tgn:1000003",
          "tgn:7008591",
          "tgn:7029392"
        ],
        "placetype": [
          "aat:300008699"
        ],
        "name:en": "Lussa River",
        "id": 7458681
      }
    },
    {
      "geometry": {
        "type": "Point",
        "coordinates": [
          -5.783333,
          56.016667
        ]
      },
      "type": "Feature",
      "properties": {
        "hierarchy": [
          "tgn:7458682",
          "tgn:7019094",
          "tgn:7002444",
          "tgn:1000003",
          "tgn:7008591",
          "tgn:7029392"
        ],
        "placetype": [
          "aat:300132316"
        ],
        "name:en": "Lussa Bay",
        "id": 7458682
      }
    },
    {
      "geometry": {
        "type": "Point",
        "coordinates": [
          -5.533333,
          55.466667
        ]
      },
      "type": "Feature",
      "properties": {
        "hierarchy": [
          "tgn:7458683",
          "tgn:7019094",
          "tgn:7002444",
          "tgn:1000003",
          "tgn:7008591",
          "tgn:7029392"
        ],
        "placetype": [
          "aat:300008761"
        ],
        "name:en": "Lussa, Glen",
        "id": 7458683
      }
    },
    {
      "geometry": {
        "type": "Point",
        "coordinates": [
          -4.633333,
          56.1
        ]
      },
      "type": "Feature",
      "properties": {
        "hierarchy": [
          "tgn:7458684",
          "tgn:7019094",
          "tgn:7002444",
          "tgn:1000003",
          "tgn:7008591",
          "tgn:7029392"
        ],
        "placetype": [
          "aat:300008347"
        ],
        "name:en": "Luss",
        "id": 7458684
      }
    },
    {
      "geometry": {
        "type": "Point",
        "coordinates": [
          -6.9,
          57.883333
        ]
      },
      "type": "Feature",
      "properties": {
        "hierarchy": [
          "tgn:7458685",
          "tgn:7002444",
          "tgn:1000003",
          "tgn:7008094",
          "tgn:7008591",
          "tgn:7029392"
        ],
        "placetype": [
          "aat:300008795"
        ],
        "name:en": "Luskentyre, Ben",
        "id": 7458685
      }
    },
    {
      "geometry": {
        "type": "Point",
        "coordinates": [
          -6.933333,
          57.9
        ]
      },
      "type": "Feature",
      "properties": {
        "hierarchy": [
          "tgn:7458686",
          "tgn:7002444",
          "tgn:1000003",
          "tgn:7008094",
          "tgn:7008591",
          "tgn:7029392"
        ],
        "placetype": [
          "aat:300008347"
        ],
        "name:en": "Luskentyre",
        "id": 7458686
      }
    },
    {
      "geometry": {
        "type": "Point",
        "coordinates": [
          -5.816667,
          57.266667
        ]
      },
      "type": "Feature",
      "properties": {
        "hierarchy": [
          "tgn:7458688",
          "tgn:7002444",
          "tgn:1000003",
          "tgn:7008082",
          "tgn:7008591",
          "tgn:7029392"
        ],
        "placetype": [
          "aat:300008347"
        ],
        "name:en": "Lusa",
        "id": 7458688
      }
    },
    {
      "geometry": {
        "type": "Point",
        "coordinates": [
          -6.083333,
          55.05
        ]
      },
      "type": "Feature",
      "properties": {
        "hierarchy": [
          "tgn:7458689",
          "tgn:7002448",
          "tgn:7019157",
          "tgn:1000003",
          "tgn:7008591",
          "tgn:7029392"
        ],
        "placetype": [
          "aat:300008795"
        ],
        "name:en": "Lurigethan",
        "id": 7458689
      }
    }
  ]
}
