{
  "geometry": {
    "type": "Point",
    "coordinates": [
      27.05,
      53.85
    ]
  },
  "type": "Feature",
  "properties": {
    "hierarchy": [
      "tgn:1107961",
      "tgn:1003391",
      "tgn:1000003",
      "tgn:7006657",
      "tgn:7029392"
    ],
    "placetype": [
      "aat:300008777"
    ],
    "id": 1107961,
    "name:xx": "Dzeržinskaja, gora"
  }
}
