{
  "geometry": {
    "type": "Point",
    "coordinates": [
      -117.9333,
      45.3167
    ]
  },
  "type": "Feature",
  "properties": {
    "hierarchy": [
      "tgn:2358559",
      "tgn:1000001",
      "tgn:7012149",
      "tgn:2001721",
      "tgn:7007708",
      "tgn:7029392"
    ],
    "placetype": [
      "aat:300386845"
    ],
    "id": 2358559,
    "name:xx": "Grande Ronde Valley"
  }
}
