{
  "geometry": {
    "type": "Point",
    "coordinates": [
      26.7167,
      55.8167
    ]
  },
  "type": "Feature",
  "properties": {
    "hierarchy": [
      "tgn:1059472",
      "tgn:7012152",
      "tgn:1000003",
      "tgn:7006541",
      "tgn:7029392"
    ],
    "placetype": [
      "aat:300008347"
    ],
    "id": 1059472,
    "name:xx": "Skrudaliena"
  }
}
