{
  "geometry": {
    "type": "Point",
    "coordinates": [
      0.1833,
      51.4167
    ]
  },
  "type": "Feature",
  "properties": {
    "hierarchy": [
      "tgn:1029544",
      "tgn:7002445",
      "tgn:1000003",
      "tgn:7008153",
      "tgn:7008591",
      "tgn:7029392"
    ],
    "placetype": [
      "aat:300008347"
    ],
    "id": 1029544,
    "name:xx": "Hextable"
  }
}
