{
  "geometry": {
    "type": "Point",
    "coordinates": [
      -114.4167,
      47.7833
    ]
  },
  "type": "Feature",
  "properties": {
    "hierarchy": [
      "tgn:2765810",
      "tgn:1000001",
      "tgn:7012149",
      "tgn:2001283",
      "tgn:7007524",
      "tgn:7029392"
    ],
    "placetype": [
      "aat:300008706"
    ],
    "id": 2765810,
    "name:xx": "White Earth Creek"
  }
}
