{
  "geometry": {
    "type": "Point",
    "coordinates": [
      71.1833,
      41.4667
    ]
  },
  "type": "Feature",
  "properties": {
    "hierarchy": [
      "tgn:1060256",
      "tgn:7011476",
      "tgn:1000004",
      "tgn:7006655",
      "tgn:7029392"
    ],
    "placetype": [
      "aat:300008347"
    ],
    "id": 1060256,
    "name:xx": "Terek-Saj"
  }
}
