{
  "geometry": {
    "type": "Point",
    "coordinates": [
      -123.6333,
      41.4167
    ]
  },
  "type": "Feature",
  "properties": {
    "hierarchy": [
      "tgn:2226667",
      "tgn:1000001",
      "tgn:7012149",
      "tgn:7007157",
      "tgn:2000189",
      "tgn:7029392"
    ],
    "placetype": [
      "aat:300008706"
    ],
    "id": 2226667,
    "name:xx": "Catsup Creek"
  }
}
