{
  "type": "FeatureCollection",
  "features": [
    {
      "geometry": {
        "type": "Point",
        "coordinates": [
          20.383333,
          38.133333
        ]
      },
      "type": "Feature",
      "properties": {
        "hierarchy": [
          "tgn:7233810",
          "tgn:7011167",
          "tgn:7001338",
          "tgn:1000003",
          "tgn:1000074",
          "tgn:7029392"
        ],
        "placetype": [
          "aat:300008808"
        ],
        "id": 7233810,
        "name:xx": "Akrotiríou, Ífaloi"
      }
    },
    {
      "geometry": {
        "type": "Point",
        "coordinates": [
          27.2,
          35.85
        ]
      },
      "type": "Feature",
      "properties": {
        "hierarchy": [
          "tgn:7233811",
          "tgn:7011330",
          "tgn:7002674",
          "tgn:1000003",
          "tgn:1000074",
          "tgn:7029392"
        ],
        "placetype": [
          "aat:300008850"
        ],
        "id": 7233811,
        "name:xx": "Akrotírion, Ákra"
      }
    },
    {
      "geometry": {
        "type": "Point",
        "coordinates": [
          26.566667,
          39.066667
        ]
      },
      "type": "Feature",
      "properties": {
        "hierarchy": [
          "tgn:7233812",
          "tgn:7011163",
          "tgn:7002674",
          "tgn:1000003",
          "tgn:1000074",
          "tgn:7029392"
        ],
        "placetype": [
          "aat:300008347"
        ],
        "id": 7233812,
        "name:xx": "Akrotírion"
      }
    },
    {
      "geometry": {
        "type": "Point",
        "coordinates": [
          20.383333,
          38.15
        ]
      },
      "type": "Feature",
      "properties": {
        "hierarchy": [
          "tgn:7233814",
          "tgn:7011167",
          "tgn:7001338",
          "tgn:1000003",
          "tgn:1000074",
          "tgn:7029392"
        ],
        "placetype": [
          "aat:300132316"
        ],
        "id": 7233814,
        "name:xx": "Akrotíri, Órmos"
      }
    },
    {
      "geometry": {
        "type": "Point",
        "coordinates": [
          24.116667,
          35.55
        ]
      },
      "type": "Feature",
      "properties": {
        "hierarchy": [
          "tgn:7233815",
          "tgn:7002690",
          "tgn:7012056",
          "tgn:1000003",
          "tgn:1000074",
          "tgn:7029392"
        ],
        "placetype": [
          "aat:300008804"
        ],
        "id": 7233815,
        "name:xx": "Akrotíri, Khersónisos"
      }
    },
    {
      "geometry": {
        "type": "Point",
        "coordinates": [
          25.35,
          40.466667
        ]
      },
      "type": "Feature",
      "properties": {
        "hierarchy": [
          "tgn:7233816",
          "tgn:7011170",
          "tgn:7002715",
          "tgn:1000003",
          "tgn:1000074",
          "tgn:7029392"
        ],
        "placetype": [
          "aat:300386846"
        ],
        "id": 7233816,
        "name:xx": "Akrotíri, Ákra"
      }
    },
    {
      "geometry": {
        "type": "Point",
        "coordinates": [
          24.333333,
          36.716667
        ]
      },
      "type": "Feature",
      "properties": {
        "hierarchy": [
          "tgn:7233817",
          "tgn:7011270",
          "tgn:7002674",
          "tgn:1000003",
          "tgn:1000074",
          "tgn:7029392"
        ],
        "placetype": [
          "aat:300386846"
        ],
        "id": 7233817,
        "name:xx": "Akrotíri, Ákra"
      }
    },
    {
      "geometry": {
        "type": "Point",
        "coordinates": [
          24.433333,
          36.666667
        ]
      },
      "type": "Feature",
      "properties": {
        "hierarchy": [
          "tgn:7233818",
          "tgn:7011270",
          "tgn:7002674",
          "tgn:1000003",
          "tgn:1000074",
          "tgn:7029392"
        ],
        "placetype": [
          "aat:300386846"
        ],
        "id": 7233818,
        "name:xx": "Akrotíri, Ákra"
      }
    },
    {
      "geometry": {
        "type": "Point",
        "coordinates": [
          27.116667,
          35.416667
        ]
      },
      "type": "Feature",
      "properties": {
        "hierarchy": [
          "tgn:7233819",
          "tgn:7011330",
          "tgn:7002674",
          "tgn:1000003",
          "tgn:1000074",
          "tgn:7029392"
        ],
        "placetype": [
          "aat:300386846"
        ],
        "id": 7233819,
        "name:xx": "Akrotíri, Ákra"
      }
    }
  ]
}
