{
  "geometry": {
    "type": "Point",
    "coordinates": [
      -82.2667,
      35.15
    ]
  },
  "type": "Feature",
  "properties": {
    "hierarchy": [
      "tgn:2235813",
      "tgn:1000001",
      "tgn:2001747",
      "tgn:7012149",
      "tgn:7007712",
      "tgn:7029392"
    ],
    "placetype": [
      "aat:300266640"
    ],
    "id": 2235813,
    "name:xx": "Chestnut Ridge"
  }
}
