{
  "geometry": {
    "type": "Point",
    "coordinates": [
      -105.6333,
      35.6333
    ]
  },
  "type": "Feature",
  "properties": {
    "hierarchy": [
      "tgn:2478620",
      "tgn:1000001",
      "tgn:7012149",
      "tgn:2001453",
      "tgn:7007566",
      "tgn:7029392"
    ],
    "placetype": [
      "aat:300008761"
    ],
    "id": 2478620,
    "name:xx": "Madera, Cañon de la"
  }
}
