{
  "geometry": {
    "type": "Point",
    "coordinates": [
      -107.65,
      32.3167
    ]
  },
  "type": "Feature",
  "properties": {
    "hierarchy": [
      "tgn:2067226",
      "tgn:1000001",
      "tgn:7012149",
      "tgn:2001444",
      "tgn:7007566",
      "tgn:7029392"
    ],
    "placetype": [
      "aat:300387016"
    ],
    "id": 2067226,
    "name:xx": "Mirage"
  }
}
