{
  "geometry": {
    "type": "Point",
    "coordinates": [
      -85.8667,
      31.7667
    ]
  },
  "type": "Feature",
  "properties": {
    "hierarchy": [
      "tgn:2581125",
      "tgn:7002659",
      "tgn:1000001",
      "tgn:7012149",
      "tgn:2000054",
      "tgn:7029392"
    ],
    "placetype": [
      "aat:300006191"
    ],
    "id": 2581125,
    "name:xx": "Pikes Pond"
  }
}
