{
  "geometry": {
    "type": "Point",
    "coordinates": [
      79.674762,
      27.58215
    ]
  },
  "type": "Feature",
  "properties": {
    "hierarchy": [
      "tgn:7561144",
      "tgn:1000004",
      "tgn:7000198",
      "tgn:7016722",
      "tgn:7029392"
    ],
    "placetype": [
      "aat:300008347"
    ],
    "name:en": "Bānpur",
    "id": 7561144
  }
}
