{
  "geometry": {
    "type": "Point",
    "coordinates": [
      -93.95,
      32.85
    ]
  },
  "type": "Feature",
  "properties": {
    "hierarchy": [
      "tgn:2555908",
      "tgn:1000001",
      "tgn:2000862",
      "tgn:7012149",
      "tgn:7007256",
      "tgn:7029392"
    ],
    "placetype": [
      "aat:300008699"
    ],
    "id": 2555908,
    "name:xx": "Oil Branch"
  }
}
