{
  "geometry": {
    "type": "Point",
    "coordinates": [
      -75.8333,
      39.8833
    ]
  },
  "type": "Feature",
  "properties": {
    "hierarchy": [
      "tgn:2363888",
      "tgn:1000001",
      "tgn:1002266",
      "tgn:7012149",
      "tgn:7007710",
      "tgn:7029392"
    ],
    "placetype": [
      "aat:300008347"
    ],
    "id": 2363888,
    "name:xx": "Green Lawn"
  }
}
