{
  "geometry": {
    "type": "Point",
    "coordinates": [
      -75.2333,
      41.55
    ]
  },
  "type": "Feature",
  "properties": {
    "hierarchy": [
      "tgn:2340014",
      "tgn:1000001",
      "tgn:7012149",
      "tgn:1003008",
      "tgn:7007710",
      "tgn:7029392"
    ],
    "placetype": [
      "aat:300006191"
    ],
    "id": 2340014,
    "name:xx": "Freethy Pond"
  }
}
