{
  "geometry": {
    "type": "Point",
    "coordinates": [
      12.8333,
      26.05
    ]
  },
  "type": "Feature",
  "properties": {
    "hierarchy": [
      "tgn:1111471",
      "tgn:7001242",
      "tgn:7000613",
      "tgn:1000172",
      "tgn:7029392"
    ],
    "placetype": [
      "aat:300008773"
    ],
    "id": 1111471,
    "name:xx": "Barjūj, Wādī"
  }
}
