{
  "geometry": {
    "type": "Point",
    "coordinates": [
      -82.65,
      39.15
    ]
  },
  "type": "Feature",
  "properties": {
    "hierarchy": [
      "tgn:2676265",
      "tgn:1000001",
      "tgn:7012149",
      "tgn:2001614",
      "tgn:7007706",
      "tgn:7029392"
    ],
    "placetype": [
      "aat:300008699"
    ],
    "id": 2676265,
    "name:xx": "Sour Run"
  }
}
