{
  "type": "FeatureCollection",
  "features": [
    {
      "geometry": {
        "type": "Point",
        "coordinates": [
          13.133333,
          41.266667
        ]
      },
      "type": "Feature",
      "properties": {
        "hierarchy": [
          "tgn:7056330",
          "tgn:7003136",
          "tgn:1000003",
          "tgn:7003080",
          "tgn:1000080",
          "tgn:7029392"
        ],
        "placetype": [
          "aat:300006075"
        ],
        "id": 7056330,
        "name:xx": "Canale Olevola"
      }
    },
    {
      "geometry": {
        "type": "Point",
        "coordinates": [
          9,
          40.5
        ]
      },
      "type": "Feature",
      "properties": {
        "hierarchy": [
          "tgn:7056334",
          "tgn:7015163",
          "tgn:1000003",
          "tgn:7003121",
          "tgn:1000080",
          "tgn:7029392"
        ],
        "placetype": [
          "aat:300008699"
        ],
        "id": 7056334,
        "name:xx": "Oletto, Riu"
      }
    },
    {
      "geometry": {
        "type": "Point",
        "coordinates": [
          8.666667,
          45.416667
        ]
      },
      "type": "Feature",
      "properties": {
        "hierarchy": [
          "tgn:7056335",
          "tgn:1003478",
          "tgn:1000003",
          "tgn:7003120",
          "tgn:1000080",
          "tgn:7029392"
        ],
        "placetype": [
          "aat:300008347"
        ],
        "id": 7056335,
        "name:xx": "Olengo"
      }
    },
    {
      "geometry": {
        "type": "Point",
        "coordinates": [
          13.397222,
          46.020278
        ]
      },
      "type": "Feature",
      "properties": {
        "hierarchy": [
          "tgn:7056336",
          "tgn:1003506",
          "tgn:1000003",
          "tgn:7002993",
          "tgn:1000080",
          "tgn:7029392"
        ],
        "placetype": [
          "aat:300008347"
        ],
        "id": 7056336,
        "name:xx": "Oleis"
      }
    },
    {
      "geometry": {
        "type": "Point",
        "coordinates": [
          8.383333,
          45.4
        ]
      },
      "type": "Feature",
      "properties": {
        "hierarchy": [
          "tgn:7056338",
          "tgn:1003510",
          "tgn:1000003",
          "tgn:7003120",
          "tgn:1000080",
          "tgn:7029392"
        ],
        "placetype": [
          "aat:300008347"
        ],
        "id": 7056338,
        "name:xx": "Oldenico"
      }
    },
    {
      "geometry": {
        "type": "Point",
        "coordinates": [
          9.383333,
          45.616667
        ]
      },
      "type": "Feature",
      "properties": {
        "hierarchy": [
          "tgn:7056339",
          "tgn:7003150",
          "tgn:1000003",
          "tgn:7003237",
          "tgn:1000080",
          "tgn:7029392"
        ],
        "placetype": [
          "aat:300008347"
        ],
        "id": 7056339,
        "name:xx": "Oldaniga"
      }
    }
  ]
}
