{
  "geometry": {
    "type": "Point",
    "coordinates": [
      -154.45,
      63.0167
    ]
  },
  "type": "Feature",
  "properties": {
    "hierarchy": [
      "tgn:2337026",
      "tgn:7006450",
      "tgn:1000001",
      "tgn:7012149",
      "tgn:2000089",
      "tgn:7029392"
    ],
    "placetype": [
      "aat:300008680"
    ],
    "id": 2337026,
    "name:xx": "Fourmile Lake"
  }
}
