{
  "geometry": {
    "type": "Point",
    "coordinates": [
      79.368811,
      22.866254
    ]
  },
  "type": "Feature",
  "properties": {
    "hierarchy": [
      "tgn:7574611",
      "tgn:1000004",
      "tgn:7000198",
      "tgn:1001894",
      "tgn:7029392"
    ],
    "placetype": [
      "aat:300008699"
    ],
    "name:en": "Māchārewā River",
    "id": 7574611
  }
}
