{
  "geometry": {
    "type": "Point",
    "coordinates": [
      -121.2333,
      37.9667
    ]
  },
  "type": "Feature",
  "properties": {
    "hierarchy": [
      "tgn:2695965",
      "tgn:1000001",
      "tgn:7012149",
      "tgn:7007157",
      "tgn:1002861",
      "tgn:7029392"
    ],
    "placetype": [
      "aat:300006075"
    ],
    "id": 2695965,
    "name:xx": "Stockton Diverting Canal"
  }
}
