{
  "geometry": {
    "type": "Point",
    "coordinates": [
      -78.4667,
      39.0667
    ]
  },
  "type": "Feature",
  "properties": {
    "hierarchy": [
      "tgn:2711865",
      "tgn:1000001",
      "tgn:7012149",
      "tgn:2002161",
      "tgn:7007919",
      "tgn:7029392"
    ],
    "placetype": [
      "aat:300266640"
    ],
    "id": 2711865,
    "name:xx": "Tarkiln Ridge"
  }
}
