{
  "geometry": {
    "type": "Point",
    "coordinates": [
      -113.05,
      42.8167
    ]
  },
  "type": "Feature",
  "properties": {
    "hierarchy": [
      "tgn:2587740",
      "tgn:1000001",
      "tgn:7012149",
      "tgn:7007250",
      "tgn:7029392"
    ],
    "placetype": [
      "aat:300008761"
    ],
    "id": 2587740,
    "name:xx": "Pleasant Valley"
  }
}
