{
  "geometry": {
    "type": "Point",
    "coordinates": [
      -82.8667,
      24.6167
    ]
  },
  "type": "Feature",
  "properties": {
    "hierarchy": [
      "tgn:2210350",
      "tgn:1000001",
      "tgn:7012149",
      "tgn:1002676",
      "tgn:7007240",
      "tgn:7029392"
    ],
    "placetype": [
      "aat:300132348"
    ],
    "id": 2210350,
    "name:xx": "Bush Key Shoal"
  }
}
