{
  "type": "FeatureCollection",
  "features": [
    {
      "geometry": {
        "type": "Point",
        "coordinates": [
          79.6667,
          46.95
        ]
      },
      "type": "Feature",
      "properties": {
        "hierarchy": [
          "tgn:1137150",
          "tgn:1000004",
          "tgn:7011462",
          "tgn:7014786",
          "tgn:7029392"
        ],
        "placetype": [
          "aat:300008347"
        ],
        "id": 1137150,
        "name:xx": "Aktogay"
      }
    },
    {
      "geometry": {
        "type": "Point",
        "coordinates": [
          74.9667,
          48.2833
        ]
      },
      "type": "Feature",
      "properties": {
        "hierarchy": [
          "tgn:1137151",
          "tgn:1000004",
          "tgn:1003363",
          "tgn:7014786",
          "tgn:7029392"
        ],
        "placetype": [
          "aat:300008347"
        ],
        "id": 1137151,
        "name:xx": "Aktogay"
      }
    },
    {
      "geometry": {
        "type": "Point",
        "coordinates": [
          38.9833,
          56.0833
        ]
      },
      "type": "Feature",
      "properties": {
        "hierarchy": [
          "tgn:1137152",
          "tgn:1000004",
          "tgn:1003421",
          "tgn:7018214",
          "tgn:7002435",
          "tgn:7029392"
        ],
        "placetype": [
          "aat:300008347"
        ],
        "id": 1137152,
        "name:xx": "Akulovo"
      }
    },
    {
      "geometry": {
        "type": "Point",
        "coordinates": [
          37.2667,
          54.2333
        ]
      },
      "type": "Feature",
      "properties": {
        "hierarchy": [
          "tgn:1137153",
          "tgn:1000004",
          "tgn:1003418",
          "tgn:7018214",
          "tgn:7002435",
          "tgn:7029392"
        ],
        "placetype": [
          "aat:300008347"
        ],
        "id": 1137153,
        "name:xx": "Al'ošn'a"
      }
    },
    {
      "geometry": {
        "type": "Point",
        "coordinates": [
          37.75,
          56.15
        ]
      },
      "type": "Feature",
      "properties": {
        "hierarchy": [
          "tgn:1137154",
          "tgn:1000004",
          "tgn:7011573",
          "tgn:7018214",
          "tgn:7002435",
          "tgn:7029392"
        ],
        "placetype": [
          "aat:300008347"
        ],
        "id": 1137154,
        "name:xx": "Alëshino"
      }
    },
    {
      "geometry": {
        "type": "Point",
        "coordinates": [
          35.4667,
          46.55
        ]
      },
      "type": "Feature",
      "properties": {
        "hierarchy": [
          "tgn:1137155",
          "tgn:1000003",
          "tgn:7011670",
          "tgn:7006660",
          "tgn:7029392"
        ],
        "placetype": [
          "aat:300008347"
        ],
        "id": 1137155,
        "name:xx": "Aleksandrovka"
      }
    },
    {
      "geometry": {
        "type": "Point",
        "coordinates": [
          38.9833,
          46.7667
        ]
      },
      "type": "Feature",
      "properties": {
        "hierarchy": [
          "tgn:1137156",
          "tgn:1000004",
          "tgn:1003405",
          "tgn:7018214",
          "tgn:7002435",
          "tgn:7029392"
        ],
        "placetype": [
          "aat:300008347"
        ],
        "id": 1137156,
        "name:xx": "Aleksandrovka"
      }
    },
    {
      "geometry": {
        "type": "Point",
        "coordinates": [
          39.2,
          47.4167
        ]
      },
      "type": "Feature",
      "properties": {
        "hierarchy": [
          "tgn:1137157",
          "tgn:1000004",
          "tgn:1003405",
          "tgn:7018214",
          "tgn:7002435",
          "tgn:7029392"
        ],
        "placetype": [
          "aat:300008347"
        ],
        "id": 1137157,
        "name:xx": "Aleksandrovka"
      }
    },
    {
      "geometry": {
        "type": "Point",
        "coordinates": [
          31.2667,
          47.6667
        ]
      },
      "type": "Feature",
      "properties": {
        "hierarchy": [
          "tgn:1137158",
          "tgn:1000003",
          "tgn:7011665",
          "tgn:7006660",
          "tgn:7029392"
        ],
        "placetype": [
          "aat:300008347"
        ],
        "id": 1137158,
        "name:xx": "Aleksandrovka"
      }
    },
    {
      "geometry": {
        "type": "Point",
        "coordinates": [
          37.5833,
          47.9167
        ]
      },
      "type": "Feature",
      "properties": {
        "hierarchy": [
          "tgn:1137159",
          "tgn:7012076",
          "tgn:1000003",
          "tgn:7006660",
          "tgn:7029392"
        ],
        "placetype": [
          "aat:300008347",
          "aat:300008375"
        ],
        "id": 1137159,
        "name:xx": "Aleksandrovka"
      }
    }
  ]
}
