{
  "geometry": {
    "type": "Point",
    "coordinates": [
      -106.4833,
      43.6667
    ]
  },
  "type": "Feature",
  "properties": {
    "hierarchy": [
      "tgn:2705703",
      "tgn:1000001",
      "tgn:7012149",
      "tgn:2002374",
      "tgn:7007923",
      "tgn:7029392"
    ],
    "placetype": [
      "aat:300006075"
    ],
    "id": 2705703,
    "name:xx": "Sussex Irrigation Canal"
  }
}
