{
  "geometry": {
    "type": "Point",
    "coordinates": [
      -85.8667,
      41.8333
    ]
  },
  "type": "Feature",
  "properties": {
    "hierarchy": [
      "tgn:2528885",
      "tgn:1000001",
      "tgn:1002243",
      "tgn:7012149",
      "tgn:7007520",
      "tgn:7029392"
    ],
    "placetype": [
      "aat:300008706"
    ],
    "id": 2528885,
    "name:xx": "Mud Creek"
  }
}
