{
  "type": "FeatureCollection",
  "features": [
    {
      "geometry": {
        "type": "Point",
        "coordinates": [
          -74.55,
          40.95
        ]
      },
      "type": "Feature",
      "properties": {
        "hierarchy": [
          "tgn:2065873",
          "tgn:1000001",
          "tgn:1002695",
          "tgn:7012149",
          "tgn:7007565",
          "tgn:7029392"
        ],
        "placetype": [
          "aat:300386994"
        ],
        "id": 2065873,
        "name:xx": "Picatinny Arsenal"
      }
    },
    {
      "geometry": {
        "type": "Point",
        "coordinates": [
          -74.5167,
          40.9667
        ]
      },
      "type": "Feature",
      "properties": {
        "hierarchy": [
          "tgn:2065874",
          "tgn:1000001",
          "tgn:1002695",
          "tgn:2065873",
          "tgn:7012149",
          "tgn:7007565",
          "tgn:7029392"
        ],
        "placetype": [
          "aat:300006084"
        ],
        "id": 2065874,
        "name:xx": "Lake Denmark"
      }
    },
    {
      "geometry": {
        "type": "Point",
        "coordinates": [
          -74.9,
          39.0833
        ]
      },
      "type": "Feature",
      "properties": {
        "hierarchy": [
          "tgn:2065875",
          "tgn:1002232",
          "tgn:1000001",
          "tgn:7012149",
          "tgn:7007565",
          "tgn:7029392"
        ],
        "placetype": [
          "aat:300008347"
        ],
        "id": 2065875,
        "name:xx": "Pierces Point"
      }
    },
    {
      "geometry": {
        "type": "Point",
        "coordinates": [
          -74.1667,
          39.9333
        ]
      },
      "type": "Feature",
      "properties": {
        "hierarchy": [
          "tgn:2065877",
          "tgn:1000001",
          "tgn:1002738",
          "tgn:7012149",
          "tgn:7007565",
          "tgn:7029392"
        ],
        "placetype": [
          "aat:300008347"
        ],
        "id": 2065877,
        "name:xx": "Pine Beach"
      }
    },
    {
      "geometry": {
        "type": "Point",
        "coordinates": [
          -74.3333,
          40.85
        ]
      },
      "type": "Feature",
      "properties": {
        "hierarchy": [
          "tgn:2065879",
          "tgn:1000001",
          "tgn:1002695",
          "tgn:7012149",
          "tgn:7007565",
          "tgn:7029392"
        ],
        "placetype": [
          "aat:300008347"
        ],
        "id": 2065879,
        "name:xx": "Pine Brook"
      }
    }
  ]
}
