{
  "geometry": {
    "type": "Point",
    "coordinates": [
      -108.05,
      33.2667
    ]
  },
  "type": "Feature",
  "properties": {
    "hierarchy": [
      "tgn:2620986",
      "tgn:1000001",
      "tgn:2001429",
      "tgn:7012149",
      "tgn:7007566",
      "tgn:7029392"
    ],
    "placetype": [
      "aat:300006191"
    ],
    "id": 2620986,
    "name:xx": "Road Canyon Tank"
  }
}
