{
  "geometry": {
    "type": "Point",
    "coordinates": [
      -77.4667,
      35.0167
    ]
  },
  "type": "Feature",
  "properties": {
    "hierarchy": [
      "tgn:2273353",
      "tgn:1000001",
      "tgn:7012149",
      "tgn:2001510",
      "tgn:7007709",
      "tgn:7029392"
    ],
    "placetype": [
      "aat:300055621"
    ],
    "id": 2273353,
    "name:xx": "Cypress Creek"
  }
}
