{
  "geometry": {
    "type": "Point",
    "coordinates": [
      -117.4667,
      33.4833
    ]
  },
  "type": "Feature",
  "properties": {
    "hierarchy": [
      "tgn:2766772",
      "tgn:1000001",
      "tgn:7012149",
      "tgn:7007157",
      "tgn:1002858",
      "tgn:7029392"
    ],
    "placetype": [
      "aat:300008697"
    ],
    "id": 2766772,
    "name:xx": "White Oak Springs"
  }
}
