{
  "geometry": {
    "type": "Point",
    "coordinates": [
      79.024954,
      26.312291
    ]
  },
  "type": "Feature",
  "properties": {
    "hierarchy": [
      "tgn:7562537",
      "tgn:1000004",
      "tgn:7000198",
      "tgn:1001894",
      "tgn:7029392"
    ],
    "placetype": [
      "aat:300008347"
    ],
    "name:en": "Mahābīrganj",
    "id": 7562537
  }
}
