{
  "geometry": {
    "type": "Point",
    "coordinates": [
      -109.5667,
      45.1667
    ]
  },
  "type": "Feature",
  "properties": {
    "hierarchy": [
      "tgn:2384721",
      "tgn:1000001",
      "tgn:2001264",
      "tgn:7012149",
      "tgn:7007524",
      "tgn:7029392"
    ],
    "placetype": [
      "aat:300008706"
    ],
    "id": 2384721,
    "name:xx": "Hellroaring Creek"
  }
}
