{
  "type": "FeatureCollection",
  "features": [
    {
      "geometry": {
        "type": "Point",
        "coordinates": [
          -85.2,
          35.4667
        ]
      },
      "type": "Feature",
      "properties": {
        "hierarchy": [
          "tgn:2406620",
          "tgn:1000001",
          "tgn:2001840",
          "tgn:7012149",
          "tgn:7007825",
          "tgn:7029392"
        ],
        "placetype": [
          "aat:300008699"
        ],
        "id": 2406620,
        "name:xx": "Hunt Branch"
      }
    },
    {
      "geometry": {
        "type": "Point",
        "coordinates": [
          -87.3167,
          35.5167
        ]
      },
      "type": "Feature",
      "properties": {
        "hierarchy": [
          "tgn:2406621",
          "tgn:1000001",
          "tgn:7012149",
          "tgn:2001887",
          "tgn:7007825",
          "tgn:7029392"
        ],
        "placetype": [
          "aat:300008699"
        ],
        "id": 2406621,
        "name:xx": "Hunt Branch"
      }
    },
    {
      "geometry": {
        "type": "Point",
        "coordinates": [
          -87.55,
          36.1667
        ]
      },
      "type": "Feature",
      "properties": {
        "hierarchy": [
          "tgn:2406622",
          "tgn:1000001",
          "tgn:7012149",
          "tgn:2001858",
          "tgn:7007825",
          "tgn:7029392"
        ],
        "placetype": [
          "aat:300008699"
        ],
        "id": 2406622,
        "name:xx": "Hunt Branch"
      }
    },
    {
      "geometry": {
        "type": "Point",
        "coordinates": [
          -97.1667,
          30.05
        ]
      },
      "type": "Feature",
      "properties": {
        "hierarchy": [
          "tgn:2406623",
          "tgn:1000001",
          "tgn:1002168",
          "tgn:7012149",
          "tgn:7007826",
          "tgn:7029392"
        ],
        "placetype": [
          "aat:300008699"
        ],
        "id": 2406623,
        "name:xx": "Hunt Branch"
      }
    },
    {
      "geometry": {
        "type": "Point",
        "coordinates": [
          -72.9833,
          42.6833
        ]
      },
      "type": "Feature",
      "properties": {
        "hierarchy": [
          "tgn:2406624",
          "tgn:7013388",
          "tgn:1000001",
          "tgn:7012149",
          "tgn:7007517",
          "tgn:7029392"
        ],
        "placetype": [
          "aat:300008699"
        ],
        "id": 2406624,
        "name:xx": "Hunt Brook"
      }
    },
    {
      "geometry": {
        "type": "Point",
        "coordinates": [
          -71.6,
          43.4833
        ]
      },
      "type": "Feature",
      "properties": {
        "hierarchy": [
          "tgn:2406625",
          "tgn:2001422",
          "tgn:1000001",
          "tgn:7012149",
          "tgn:7007564",
          "tgn:7029392"
        ],
        "placetype": [
          "aat:300008699"
        ],
        "id": 2406625,
        "name:xx": "Hunt Brook"
      }
    },
    {
      "geometry": {
        "type": "Point",
        "coordinates": [
          -73.8833,
          43.25
        ]
      },
      "type": "Feature",
      "properties": {
        "hierarchy": [
          "tgn:2406626",
          "tgn:1000001",
          "tgn:7012149",
          "tgn:1002871",
          "tgn:7007568",
          "tgn:7029392"
        ],
        "placetype": [
          "aat:300008699"
        ],
        "id": 2406626,
        "name:xx": "Hunt Brook"
      }
    },
    {
      "geometry": {
        "type": "Point",
        "coordinates": [
          -71.6167,
          41.8833
        ]
      },
      "type": "Feature",
      "properties": {
        "hierarchy": [
          "tgn:2406627",
          "tgn:1002808",
          "tgn:1000001",
          "tgn:7012149",
          "tgn:7007711",
          "tgn:7029392"
        ],
        "placetype": [
          "aat:300008699"
        ],
        "id": 2406627,
        "name:xx": "Hunt Brook"
      }
    },
    {
      "geometry": {
        "type": "Point",
        "coordinates": [
          -72.8,
          44.7
        ]
      },
      "type": "Feature",
      "properties": {
        "hierarchy": [
          "tgn:2406628",
          "tgn:1000001",
          "tgn:7012149",
          "tgn:7007828",
          "tgn:7029392"
        ],
        "placetype": [
          "aat:300008699"
        ],
        "id": 2406628,
        "name:xx": "Hunt Brook"
      }
    },
    {
      "geometry": {
        "type": "Point",
        "coordinates": [
          -120.5333,
          44.6667
        ]
      },
      "type": "Feature",
      "properties": {
        "hierarchy": [
          "tgn:2406629",
          "tgn:1000001",
          "tgn:7012149",
          "tgn:2001712",
          "tgn:7007708",
          "tgn:7029392"
        ],
        "placetype": [
          "aat:300008798"
        ],
        "id": 2406629,
        "name:xx": "Hunt Butte"
      }
    }
  ]
}
