{
  "type": "FeatureCollection",
  "features": [
    {
      "geometry": {
        "type": "Point",
        "coordinates": [
          -77.5167,
          41.6
        ]
      },
      "type": "Feature",
      "properties": {
        "hierarchy": [
          "tgn:2289580",
          "tgn:1000001",
          "tgn:7012149",
          "tgn:1002945",
          "tgn:7007710",
          "tgn:7029392"
        ],
        "placetype": [
          "aat:300008761"
        ],
        "id": 2289580,
        "name:xx": "Dixon Hollow"
      }
    },
    {
      "geometry": {
        "type": "Point",
        "coordinates": [
          -87.6833,
          35.2833
        ]
      },
      "type": "Feature",
      "properties": {
        "hierarchy": [
          "tgn:2289581",
          "tgn:1000001",
          "tgn:7012149",
          "tgn:2001927",
          "tgn:7007825",
          "tgn:7029392"
        ],
        "placetype": [
          "aat:300008761"
        ],
        "id": 2289581,
        "name:xx": "Dixon Hollow"
      }
    },
    {
      "geometry": {
        "type": "Point",
        "coordinates": [
          -82.6667,
          36.4333
        ]
      },
      "type": "Feature",
      "properties": {
        "hierarchy": [
          "tgn:2289582",
          "tgn:1000001",
          "tgn:7012149",
          "tgn:2001918",
          "tgn:7007825",
          "tgn:7029392"
        ],
        "placetype": [
          "aat:300008761"
        ],
        "id": 2289582,
        "name:xx": "Dixon Hollow"
      }
    },
    {
      "geometry": {
        "type": "Point",
        "coordinates": [
          -79.0167,
          41.8333
        ]
      },
      "type": "Feature",
      "properties": {
        "hierarchy": [
          "tgn:2289584",
          "tgn:1000001",
          "tgn:7012149",
          "tgn:1002988",
          "tgn:7007710",
          "tgn:7029392"
        ],
        "placetype": [
          "aat:300008791"
        ],
        "id": 2289584,
        "name:xx": "Dixon Island"
      }
    },
    {
      "geometry": {
        "type": "Point",
        "coordinates": [
          -86.0833,
          36.3333
        ]
      },
      "type": "Feature",
      "properties": {
        "hierarchy": [
          "tgn:2289585",
          "tgn:1000001",
          "tgn:7012149",
          "tgn:2001916",
          "tgn:7007825",
          "tgn:7029392"
        ],
        "placetype": [
          "aat:300008791"
        ],
        "id": 2289585,
        "name:xx": "Dixon Island"
      }
    },
    {
      "geometry": {
        "type": "Point",
        "coordinates": [
          -83.05,
          37.15
        ]
      },
      "type": "Feature",
      "properties": {
        "hierarchy": [
          "tgn:2289586",
          "tgn:1000001",
          "tgn:7012149",
          "tgn:2000836",
          "tgn:7007255",
          "tgn:7029392"
        ],
        "placetype": [
          "aat:300008798"
        ],
        "id": 2289586,
        "name:xx": "Dixon Knob"
      }
    },
    {
      "geometry": {
        "type": "Point",
        "coordinates": [
          -81.15,
          28.8333
        ]
      },
      "type": "Feature",
      "properties": {
        "hierarchy": [
          "tgn:2289587",
          "tgn:1000001",
          "tgn:7012149",
          "tgn:1002977",
          "tgn:7007240",
          "tgn:7029392"
        ],
        "placetype": [
          "aat:300008680"
        ],
        "id": 2289587,
        "name:xx": "Dixon Lake"
      }
    },
    {
      "geometry": {
        "type": "Point",
        "coordinates": [
          -83.05,
          29.7
        ]
      },
      "type": "Feature",
      "properties": {
        "hierarchy": [
          "tgn:2289588",
          "tgn:1000001",
          "tgn:2000263",
          "tgn:7012149",
          "tgn:7007240",
          "tgn:7029392"
        ],
        "placetype": [
          "aat:300008680"
        ],
        "id": 2289588,
        "name:xx": "Dixon Lake"
      }
    },
    {
      "geometry": {
        "type": "Point",
        "coordinates": [
          -86.6,
          30.8
        ]
      },
      "type": "Feature",
      "properties": {
        "hierarchy": [
          "tgn:2289589",
          "tgn:1000001",
          "tgn:7012149",
          "tgn:2000281",
          "tgn:7007240",
          "tgn:7029392"
        ],
        "placetype": [
          "aat:300008680"
        ],
        "id": 2289589,
        "name:xx": "Dixon Lake"
      }
    }
  ]
}
