{
  "geometry": {
    "type": "Point",
    "coordinates": [
      35.35,
      50.1167
    ]
  },
  "type": "Feature",
  "properties": {
    "hierarchy": [
      "tgn:1054248",
      "tgn:1003361",
      "tgn:1000003",
      "tgn:7006660",
      "tgn:7029392"
    ],
    "placetype": [
      "aat:300008347"
    ],
    "id": 1054248,
    "name:xx": "Guty"
  }
}
