{
  "geometry": {
    "type": "Point",
    "coordinates": [
      -122.0833,
      44.8167
    ]
  },
  "type": "Feature",
  "properties": {
    "hierarchy": [
      "tgn:2301254",
      "tgn:1000001",
      "tgn:7012149",
      "tgn:1002636",
      "tgn:7007708",
      "tgn:7029392"
    ],
    "placetype": [
      "aat:300008680"
    ],
    "id": 2301254,
    "name:xx": "Dunlap Lake"
  }
}
