{
  "geometry": {
    "type": "Point",
    "coordinates": [
      31.36758,
      30.104905
    ]
  },
  "type": "Feature",
  "properties": {
    "hierarchy": [
      "tgn:7531744",
      "tgn:7001242",
      "tgn:7016833",
      "tgn:1001091",
      "tgn:7029392"
    ],
    "placetype": [
      "aat:300004792"
    ],
    "id": 7531744,
    "name:xx": "An Nass훮j큰n ash Sharq카y큰n"
  }
}
