{
  "geometry": {
    "type": "Point",
    "coordinates": [
      0.3833,
      43.9667
    ]
  },
  "type": "Feature",
  "properties": {
    "hierarchy": [
      "tgn:1032743",
      "tgn:1000003",
      "tgn:7002889",
      "tgn:1000070",
      "tgn:7029392"
    ],
    "placetype": [
      "aat:300008347"
    ],
    "id": 1032743,
    "name:xx": "Condom"
  }
}
