{
  "geometry": {
    "type": "Point",
    "coordinates": [
      -99.55,
      27.6167
    ]
  },
  "type": "Feature",
  "properties": {
    "hierarchy": [
      "tgn:2312821",
      "tgn:1000001",
      "tgn:7012149",
      "tgn:2002090",
      "tgn:7007826",
      "tgn:7029392"
    ],
    "placetype": [
      "aat:300008798"
    ],
    "id": 2312821,
    "name:xx": "El Pico"
  }
}
