{
  "geometry": {
    "type": "Point",
    "coordinates": [
      -3.566667,
      43.45
    ]
  },
  "type": "Feature",
  "properties": {
    "hierarchy": [
      "tgn:7325499",
      "tgn:7002760",
      "tgn:1000003",
      "tgn:1000095",
      "tgn:7029392"
    ],
    "placetype": [
      "aat:300008347"
    ],
    "id": 7325499,
    "name:xx": "San Mamés de Meruelo"
  }
}
