{
  "geometry": {
    "type": "Point",
    "coordinates": [
      -90.5833,
      38.3167
    ]
  },
  "type": "Feature",
  "properties": {
    "hierarchy": [
      "tgn:2614290",
      "tgn:1000001",
      "tgn:7012149",
      "tgn:1002517",
      "tgn:7007523",
      "tgn:7029392"
    ],
    "placetype": [
      "aat:300008347"
    ],
    "id": 2614290,
    "name:xx": "Regina"
  }
}
