{
  "type": "FeatureCollection",
  "features": [
    {
      "geometry": {
        "type": "Point",
        "coordinates": [
          -112.4,
          38.1833
        ]
      },
      "type": "Feature",
      "properties": {
        "hierarchy": [
          "tgn:1104250",
          "tgn:1000001",
          "tgn:7012149",
          "tgn:7007827",
          "tgn:7029392"
        ],
        "placetype": [
          "aat:300008795"
        ],
        "id": 1104250,
        "name:xx": "Circleville Mountain"
      }
    },
    {
      "geometry": {
        "type": "Point",
        "coordinates": [
          175.4167,
          64.55
        ]
      },
      "type": "Feature",
      "properties": {
        "hierarchy": [
          "tgn:1104252",
          "tgn:6001445",
          "tgn:1000004",
          "tgn:7018214",
          "tgn:7002435",
          "tgn:7029392"
        ],
        "placetype": [
          "aat:300008795"
        ],
        "id": 1104252,
        "name:xx": "Cirk, gora"
      }
    },
    {
      "geometry": {
        "type": "Point",
        "coordinates": [
          -75.2333,
          -12.8
        ]
      },
      "type": "Feature",
      "properties": {
        "hierarchy": [
          "tgn:1104253",
          "tgn:1000638",
          "tgn:1000002",
          "tgn:1000056",
          "tgn:7029392"
        ],
        "placetype": [
          "aat:300008795"
        ],
        "id": 1104253,
        "name:xx": "Citac, Nevado"
      }
    },
    {
      "geometry": {
        "type": "Point",
        "coordinates": [
          12.053333,
          46.380556
        ]
      },
      "type": "Feature",
      "properties": {
        "hierarchy": [
          "tgn:1104256",
          "tgn:7002991",
          "tgn:1000003",
          "tgn:7002997",
          "tgn:1000080",
          "tgn:7029392"
        ],
        "placetype": [
          "aat:300008795"
        ],
        "id": 1104256,
        "name:xx": "Civetta, Monte"
      }
    },
    {
      "geometry": {
        "type": "Point",
        "coordinates": [
          7.4167,
          44.1167
        ]
      },
      "type": "Feature",
      "properties": {
        "hierarchy": [
          "tgn:1104257",
          "tgn:1000003",
          "tgn:7029392"
        ],
        "placetype": [
          "aat:300008795"
        ],
        "id": 1104257,
        "name:xx": "Clapier, Monte"
      }
    },
    {
      "geometry": {
        "type": "Point",
        "coordinates": [
          -115.5833,
          35.5167
        ]
      },
      "type": "Feature",
      "properties": {
        "hierarchy": [
          "tgn:1104259",
          "tgn:1000001",
          "tgn:7012149",
          "tgn:7007157",
          "tgn:1002857",
          "tgn:7029392"
        ],
        "placetype": [
          "aat:300008795"
        ],
        "id": 1104259,
        "name:xx": "Clark Mountain"
      }
    }
  ]
}
