{
  "geometry": {
    "type": "Point",
    "coordinates": [
      -86.2833,
      32.75
    ]
  },
  "type": "Feature",
  "properties": {
    "hierarchy": [
      "tgn:2658208",
      "tgn:7002659",
      "tgn:1000001",
      "tgn:2000018",
      "tgn:7012149",
      "tgn:7029392"
    ],
    "placetype": [
      "aat:300006191"
    ],
    "id": 2658208,
    "name:xx": "Shelton Lake"
  }
}
