{
  "geometry": {
    "type": "Point",
    "coordinates": [
      -86.1667,
      30.7333
    ]
  },
  "type": "Feature",
  "properties": {
    "hierarchy": [
      "tgn:2160941",
      "tgn:1000001",
      "tgn:7012149",
      "tgn:2000290",
      "tgn:7007240",
      "tgn:7029392"
    ],
    "placetype": [
      "aat:300008905"
    ],
    "id": 2160941,
    "name:xx": "Bell Bay"
  }
}
