{
  "geometry": {
    "type": "Point",
    "coordinates": [
      -81.95,
      35.3667
    ]
  },
  "type": "Feature",
  "properties": {
    "hierarchy": [
      "tgn:2243562",
      "tgn:1000001",
      "tgn:7012149",
      "tgn:2001537",
      "tgn:7007709",
      "tgn:7029392"
    ],
    "placetype": [
      "aat:300008706"
    ],
    "id": 2243562,
    "name:xx": "Cleghorn Creek"
  }
}
