{
  "geometry": {
    "type": "Point",
    "coordinates": [
      -0.4833,
      10.9333
    ]
  },
  "type": "Feature",
  "properties": {
    "hierarchy": [
      "tgn:1090212",
      "tgn:7001242",
      "tgn:7018307",
      "tgn:1000166",
      "tgn:7029392"
    ],
    "placetype": [
      "aat:300008347"
    ],
    "id": 1090212,
    "name:xx": "Zebila"
  }
}
