{
  "geometry": {
    "type": "Point",
    "coordinates": [
      -92.0333,
      35.1333
    ]
  },
  "type": "Feature",
  "properties": {
    "hierarchy": [
      "tgn:2205793",
      "tgn:1000001",
      "tgn:7016172",
      "tgn:7012149",
      "tgn:2000177",
      "tgn:7029392"
    ],
    "placetype": [
      "aat:300266640"
    ],
    "id": 2205793,
    "name:xx": "Bull Mountain"
  }
}
