{
  "geometry": {
    "type": "Point",
    "coordinates": [
      17.2333,
      53.2833
    ]
  },
  "type": "Feature",
  "properties": {
    "hierarchy": [
      "tgn:1048885",
      "tgn:1000003",
      "tgn:7024119",
      "tgn:7006366",
      "tgn:7029392"
    ],
    "placetype": [
      "aat:300008347"
    ],
    "id": 1048885,
    "name:xx": "Łobżenica"
  }
}
