{
  "geometry": {
    "type": "Point",
    "coordinates": [
      -120.6333,
      35.2667
    ]
  },
  "type": "Feature",
  "properties": {
    "hierarchy": [
      "tgn:2715364",
      "tgn:1000001",
      "tgn:7012149",
      "tgn:7007157",
      "tgn:1002863",
      "tgn:7029392"
    ],
    "placetype": [
      "aat:300008798"
    ],
    "id": 2715364,
    "name:xx": "Terrace Hill"
  }
}
