{
  "geometry": {
    "type": "Point",
    "coordinates": [
      -110.8167,
      31.7333
    ]
  },
  "type": "Feature",
  "properties": {
    "hierarchy": [
      "tgn:2270528",
      "tgn:1000001",
      "tgn:7006451",
      "tgn:7012149",
      "tgn:2000100",
      "tgn:7029392"
    ],
    "placetype": [
      "aat:300000390",
      "aat:300386993"
    ],
    "id": 2270528,
    "name:xx": "Crystal Mine"
  }
}
