{
  "geometry": {
    "type": "Point",
    "coordinates": [
      74.61466,
      21.855959
    ]
  },
  "type": "Feature",
  "properties": {
    "hierarchy": [
      "tgn:7551416",
      "tgn:1000004",
      "tgn:7000198",
      "tgn:1001894",
      "tgn:7029392"
    ],
    "placetype": [
      "aat:300008347"
    ],
    "name:en": "Bokhrāta",
    "id": 7551416
  }
}
