{
  "geometry": {
    "type": "Point",
    "coordinates": [
      -112.0167,
      32.3333
    ]
  },
  "type": "Feature",
  "properties": {
    "hierarchy": [
      "tgn:2566382",
      "tgn:1000001",
      "tgn:7006451",
      "tgn:7012149",
      "tgn:2000100",
      "tgn:7029392"
    ],
    "placetype": [
      "aat:300008347"
    ],
    "id": 2566382,
    "name:xx": "Palo Verde Stand"
  }
}
