{
  "geometry": {
    "type": "Point",
    "coordinates": [
      -112.2833,
      46.7333
    ]
  },
  "type": "Feature",
  "properties": {
    "hierarchy": [
      "tgn:2635450",
      "tgn:1000001",
      "tgn:7012149",
      "tgn:2001284",
      "tgn:7007524",
      "tgn:7029392"
    ],
    "placetype": [
      "aat:300000390"
    ],
    "id": 2635450,
    "name:xx": "SE SW Section 36 Mine"
  }
}
