{
  "geometry": {
    "type": "Point",
    "coordinates": [
      -118.5333,
      44.4833
    ]
  },
  "type": "Feature",
  "properties": {
    "hierarchy": [
      "tgn:2526561",
      "tgn:1000001",
      "tgn:7012149",
      "tgn:2001708",
      "tgn:7007708",
      "tgn:7029392"
    ],
    "placetype": [
      "aat:300008761"
    ],
    "id": 2526561,
    "name:xx": "Mossy Gulch"
  }
}
