{
  "geometry": {
    "type": "Point",
    "coordinates": [
      39.9333,
      40.95
    ]
  },
  "type": "Feature",
  "properties": {
    "hierarchy": [
      "tgn:1085980",
      "tgn:1000004",
      "tgn:1001576",
      "tgn:7018454",
      "tgn:1000144",
      "tgn:7029392"
    ],
    "placetype": [
      "aat:300008347"
    ],
    "id": 1085980,
    "name:xx": "Araklı"
  }
}
