{
  "geometry": {
    "type": "Point",
    "coordinates": [
      -95.2833,
      47.3167
    ]
  },
  "type": "Feature",
  "properties": {
    "hierarchy": [
      "tgn:2154194",
      "tgn:1000001",
      "tgn:2001013",
      "tgn:7012149",
      "tgn:7007521",
      "tgn:7029392"
    ],
    "placetype": [
      "aat:300008706"
    ],
    "id": 2154194,
    "name:xx": "Bear Creek"
  }
}
