{
  "geometry": {
    "type": "Point",
    "coordinates": [
      -85.5333,
      44.5833
    ]
  },
  "type": "Feature",
  "properties": {
    "hierarchy": [
      "tgn:2052365",
      "tgn:1000001",
      "tgn:7012149",
      "tgn:2000961",
      "tgn:7007520",
      "tgn:7029392"
    ],
    "placetype": [
      "aat:300008347"
    ],
    "id": 2052365,
    "name:xx": "Kingsley"
  }
}
