{
  "type": "FeatureCollection",
  "features": [
    {
      "geometry": {
        "type": "Point",
        "coordinates": [
          9.066667,
          53.066667
        ]
      },
      "type": "Feature",
      "properties": {
        "hierarchy": [
          "tgn:7212790",
          "tgn:1000003",
          "tgn:7003676",
          "tgn:7000084",
          "tgn:7029392"
        ],
        "placetype": [
          "aat:300008347"
        ],
        "id": 7212790,
        "name:xx": "Bockhorster Mühlentor"
      }
    },
    {
      "geometry": {
        "type": "Point",
        "coordinates": [
          9.683333,
          54.233333
        ]
      },
      "type": "Feature",
      "properties": {
        "hierarchy": [
          "tgn:7212791",
          "tgn:1000003",
          "tgn:7003688",
          "tgn:7000084",
          "tgn:7029392"
        ],
        "placetype": [
          "aat:300008777"
        ],
        "id": 7212791,
        "name:xx": "Bockhorst Berg"
      }
    },
    {
      "geometry": {
        "type": "Point",
        "coordinates": [
          9.566667,
          53.35
        ]
      },
      "type": "Feature",
      "properties": {
        "hierarchy": [
          "tgn:7212792",
          "tgn:1000003",
          "tgn:7003676",
          "tgn:7000084",
          "tgn:7029392"
        ],
        "placetype": [
          "aat:300008347"
        ],
        "id": 7212792,
        "name:xx": "Bockhorst"
      }
    },
    {
      "geometry": {
        "type": "Point",
        "coordinates": [
          9.033333,
          53.066667
        ]
      },
      "type": "Feature",
      "properties": {
        "hierarchy": [
          "tgn:7212793",
          "tgn:1000003",
          "tgn:7003676",
          "tgn:7000084",
          "tgn:7029392"
        ],
        "placetype": [
          "aat:300008347"
        ],
        "id": 7212793,
        "name:xx": "Bockhorst"
      }
    },
    {
      "geometry": {
        "type": "Point",
        "coordinates": [
          7.583333,
          53.033333
        ]
      },
      "type": "Feature",
      "properties": {
        "hierarchy": [
          "tgn:7212794",
          "tgn:1000003",
          "tgn:7003676",
          "tgn:7000084",
          "tgn:7029392"
        ],
        "placetype": [
          "aat:300008347"
        ],
        "id": 7212794,
        "name:xx": "Bockhorst"
      }
    },
    {
      "geometry": {
        "type": "Point",
        "coordinates": [
          8.783333,
          52.233333
        ]
      },
      "type": "Feature",
      "properties": {
        "hierarchy": [
          "tgn:7212795",
          "tgn:1000003",
          "tgn:7003677",
          "tgn:7000084",
          "tgn:7029392"
        ],
        "placetype": [
          "aat:300008347"
        ],
        "id": 7212795,
        "name:xx": "Bockhorst"
      }
    },
    {
      "geometry": {
        "type": "Point",
        "coordinates": [
          8.2,
          52.083333
        ]
      },
      "type": "Feature",
      "properties": {
        "hierarchy": [
          "tgn:7212796",
          "tgn:1000003",
          "tgn:7003677",
          "tgn:7000084",
          "tgn:7029392"
        ],
        "placetype": [
          "aat:300008347"
        ],
        "id": 7212796,
        "name:xx": "Bockhorst"
      }
    },
    {
      "geometry": {
        "type": "Point",
        "coordinates": [
          11.066667,
          54.2
        ]
      },
      "type": "Feature",
      "properties": {
        "hierarchy": [
          "tgn:7212797",
          "tgn:1000003",
          "tgn:7003688",
          "tgn:7000084",
          "tgn:7029392"
        ],
        "placetype": [
          "aat:300000206"
        ],
        "id": 7212797,
        "name:xx": "Bockhorst"
      }
    },
    {
      "geometry": {
        "type": "Point",
        "coordinates": [
          9.433333,
          53.616667
        ]
      },
      "type": "Feature",
      "properties": {
        "hierarchy": [
          "tgn:7212798",
          "tgn:1000003",
          "tgn:7003676",
          "tgn:7000084",
          "tgn:7029392"
        ],
        "placetype": [
          "aat:300000206"
        ],
        "id": 7212798,
        "name:xx": "Bockhorst"
      }
    },
    {
      "geometry": {
        "type": "Point",
        "coordinates": [
          8.583333,
          52.85
        ]
      },
      "type": "Feature",
      "properties": {
        "hierarchy": [
          "tgn:7212799",
          "tgn:1000003",
          "tgn:7003676",
          "tgn:7000084",
          "tgn:7029392"
        ],
        "placetype": [
          "aat:300000206"
        ],
        "id": 7212799,
        "name:xx": "Bockhorst"
      }
    }
  ]
}
