{
  "geometry": {
    "type": "Point",
    "coordinates": [
      -96.4333,
      32.2667
    ]
  },
  "type": "Feature",
  "properties": {
    "hierarchy": [
      "tgn:2552338",
      "tgn:1000001",
      "tgn:7012149",
      "tgn:1002709",
      "tgn:7007826",
      "tgn:7029392"
    ],
    "placetype": [
      "aat:300006191"
    ],
    "id": 2552338,
    "name:xx": "Number Three, Reservoir"
  }
}
