{
  "geometry": {
    "type": "Point",
    "coordinates": [
      74.233333,
      19.05
    ]
  },
  "type": "Feature",
  "properties": {
    "hierarchy": [
      "tgn:7544882",
      "tgn:1000004",
      "tgn:7000198",
      "tgn:1001895",
      "tgn:7029392"
    ],
    "placetype": [
      "aat:300008347"
    ],
    "name:en": "Ālkuti",
    "id": 7544882
  }
}
