{
  "geometry": {
    "type": "Point",
    "coordinates": [
      -92.6333,
      35.7667
    ]
  },
  "type": "Feature",
  "properties": {
    "hierarchy": [
      "tgn:2578176",
      "tgn:1000001",
      "tgn:7016172",
      "tgn:7012149",
      "tgn:7029392"
    ],
    "placetype": [
      "aat:300008706"
    ],
    "id": 2578176,
    "name:xx": "Peyton Creek"
  }
}
