{
  "geometry": {
    "type": "Point",
    "coordinates": [
      -121.9167,
      44.4833
    ]
  },
  "type": "Feature",
  "properties": {
    "hierarchy": [
      "tgn:2483944",
      "tgn:1000001",
      "tgn:7012149",
      "tgn:2001717",
      "tgn:7007708",
      "tgn:7029392"
    ],
    "placetype": [
      "aat:300008680"
    ],
    "id": 2483944,
    "name:xx": "Latigo Lake"
  }
}
