{
  "geometry": {
    "type": "Point",
    "coordinates": [
      83.372418,
      26.66846
    ]
  },
  "type": "Feature",
  "properties": {
    "hierarchy": [
      "tgn:7545088",
      "tgn:1000004",
      "tgn:7000198",
      "tgn:7016722",
      "tgn:7029392"
    ],
    "placetype": [
      "aat:300008347"
    ],
    "name:en": "Bhauvāpār",
    "id": 7545088
  }
}
