{
  "geometry": {
    "type": "Point",
    "coordinates": [
      -83.5167,
      37.6833
    ]
  },
  "type": "Feature",
  "properties": {
    "hierarchy": [
      "tgn:2041802",
      "tgn:1000001",
      "tgn:7012149",
      "tgn:2000853",
      "tgn:7007255",
      "tgn:7029392"
    ],
    "placetype": [
      "aat:300008347",
      "aat:300387210"
    ],
    "id": 2041802,
    "name:xx": "Vortex"
  }
}
