{
  "type": "FeatureCollection",
  "features": [
    {
      "geometry": {
        "type": "Point",
        "coordinates": [
          11.85,
          50.3
        ]
      },
      "type": "Feature",
      "properties": {
        "hierarchy": [
          "tgn:7113371",
          "tgn:7003669",
          "tgn:1000003",
          "tgn:7000084",
          "tgn:7029392"
        ],
        "placetype": [
          "aat:300008347"
        ],
        "id": 7113371,
        "name:xx": "Rosenau"
      }
    },
    {
      "geometry": {
        "type": "Point",
        "coordinates": [
          13.416667,
          48.866667
        ]
      },
      "type": "Feature",
      "properties": {
        "hierarchy": [
          "tgn:7113372",
          "tgn:7003669",
          "tgn:1000003",
          "tgn:7000084",
          "tgn:7029392"
        ],
        "placetype": [
          "aat:300008347"
        ],
        "id": 7113372,
        "name:xx": "Rosenau"
      }
    },
    {
      "geometry": {
        "type": "Point",
        "coordinates": [
          13.483333,
          48.566667
        ]
      },
      "type": "Feature",
      "properties": {
        "hierarchy": [
          "tgn:7113373",
          "tgn:7003669",
          "tgn:1000003",
          "tgn:7000084",
          "tgn:7029392"
        ],
        "placetype": [
          "aat:300008347"
        ],
        "id": 7113373,
        "name:xx": "Rosenau"
      }
    },
    {
      "geometry": {
        "type": "Point",
        "coordinates": [
          7.233333,
          50.683333
        ]
      },
      "type": "Feature",
      "properties": {
        "hierarchy": [
          "tgn:7113375",
          "tgn:1000003",
          "tgn:7003677",
          "tgn:7000084",
          "tgn:7029392"
        ],
        "placetype": [
          "aat:300000206"
        ],
        "id": 7113375,
        "name:xx": "Rosenau"
      }
    },
    {
      "geometry": {
        "type": "Point",
        "coordinates": [
          12.95,
          49.2
        ]
      },
      "type": "Feature",
      "properties": {
        "hierarchy": [
          "tgn:7113376",
          "tgn:7003669",
          "tgn:1000003",
          "tgn:7000084",
          "tgn:7029392"
        ],
        "placetype": [
          "aat:300000206"
        ],
        "id": 7113376,
        "name:xx": "Rosenau"
      }
    },
    {
      "geometry": {
        "type": "Point",
        "coordinates": [
          13.75,
          48.6
        ]
      },
      "type": "Feature",
      "properties": {
        "hierarchy": [
          "tgn:7113377",
          "tgn:7003669",
          "tgn:1000003",
          "tgn:7000084",
          "tgn:7029392"
        ],
        "placetype": [
          "aat:300000206"
        ],
        "id": 7113377,
        "name:xx": "Rosenau"
      }
    },
    {
      "geometry": {
        "type": "Point",
        "coordinates": [
          9.033333,
          48.533333
        ]
      },
      "type": "Feature",
      "properties": {
        "hierarchy": [
          "tgn:7113378",
          "tgn:7003692",
          "tgn:1000003",
          "tgn:7000084",
          "tgn:7029392"
        ],
        "placetype": [
          "aat:300000206"
        ],
        "id": 7113378,
        "name:xx": "Rosenau"
      }
    },
    {
      "geometry": {
        "type": "Point",
        "coordinates": [
          11.933333,
          48.433333
        ]
      },
      "type": "Feature",
      "properties": {
        "hierarchy": [
          "tgn:7113379",
          "tgn:7003669",
          "tgn:1000003",
          "tgn:7000084",
          "tgn:7029392"
        ],
        "placetype": [
          "aat:300000206"
        ],
        "id": 7113379,
        "name:xx": "Rosenau"
      }
    }
  ]
}
