{
  "geometry": {
    "type": "Point",
    "coordinates": [
      -82.2167,
      38.2333
    ]
  },
  "type": "Feature",
  "properties": {
    "hierarchy": [
      "tgn:2329900",
      "tgn:1000001",
      "tgn:7012149",
      "tgn:2002272",
      "tgn:7013961",
      "tgn:7029392"
    ],
    "placetype": [
      "aat:300008798"
    ],
    "id": 2329900,
    "name:xx": "Flag Knob"
  }
}
