{
  "geometry": {
    "type": "Point",
    "coordinates": [
      -121.4667,
      35.9167
    ]
  },
  "type": "Feature",
  "properties": {
    "hierarchy": [
      "tgn:2356391",
      "tgn:1000001",
      "tgn:7012149",
      "tgn:7007157",
      "tgn:1002684",
      "tgn:7029392"
    ],
    "placetype": [
      "aat:300008347"
    ],
    "id": 2356391,
    "name:xx": "Gorda"
  }
}
