{
  "geometry": {
    "type": "Point",
    "coordinates": [
      -91.5167,
      31.6333
    ]
  },
  "type": "Feature",
  "properties": {
    "hierarchy": [
      "tgn:2252042",
      "tgn:1000001",
      "tgn:2000868",
      "tgn:7012149",
      "tgn:7007256",
      "tgn:7029392"
    ],
    "placetype": [
      "aat:300008680"
    ],
    "id": 2252042,
    "name:xx": "Concordia, Lake"
  }
}
