{
  "type": "FeatureCollection",
  "features": [
    {
      "geometry": {
        "type": "Point",
        "coordinates": [
          10.3,
          52.983333
        ]
      },
      "type": "Feature",
      "properties": {
        "hierarchy": [
          "tgn:7069640",
          "tgn:1000003",
          "tgn:7003676",
          "tgn:7000084",
          "tgn:7029392"
        ],
        "placetype": [
          "aat:300008777"
        ],
        "id": 7069640,
        "name:xx": "Thonhops-Berg"
      }
    },
    {
      "geometry": {
        "type": "Point",
        "coordinates": [
          9.916667,
          53.216667
        ]
      },
      "type": "Feature",
      "properties": {
        "hierarchy": [
          "tgn:7069641",
          "tgn:1000003",
          "tgn:7003676",
          "tgn:7000084",
          "tgn:7029392"
        ],
        "placetype": [
          "aat:300000206"
        ],
        "id": 7069641,
        "name:xx": "Thonhof"
      }
    },
    {
      "geometry": {
        "type": "Point",
        "coordinates": [
          11.35,
          48.45
        ]
      },
      "type": "Feature",
      "properties": {
        "hierarchy": [
          "tgn:7069642",
          "tgn:7003669",
          "tgn:1000003",
          "tgn:7000084",
          "tgn:7029392"
        ],
        "placetype": [
          "aat:300000206"
        ],
        "id": 7069642,
        "name:xx": "Thonhof"
      }
    },
    {
      "geometry": {
        "type": "Point",
        "coordinates": [
          12.316667,
          50.833333
        ]
      },
      "type": "Feature",
      "properties": {
        "hierarchy": [
          "tgn:7069643",
          "tgn:1000003",
          "tgn:7003689",
          "tgn:7000084",
          "tgn:7029392"
        ],
        "placetype": [
          "aat:300008347"
        ],
        "id": 7069643,
        "name:xx": "Thonhausen"
      }
    },
    {
      "geometry": {
        "type": "Point",
        "coordinates": [
          11.8,
          49.333333
        ]
      },
      "type": "Feature",
      "properties": {
        "hierarchy": [
          "tgn:7069644",
          "tgn:7003669",
          "tgn:1000003",
          "tgn:7000084",
          "tgn:7029392"
        ],
        "placetype": [
          "aat:300008347"
        ],
        "id": 7069644,
        "name:xx": "Thonhausen"
      }
    },
    {
      "geometry": {
        "type": "Point",
        "coordinates": [
          11.833333,
          49.05
        ]
      },
      "type": "Feature",
      "properties": {
        "hierarchy": [
          "tgn:7069645",
          "tgn:7003669",
          "tgn:1000003",
          "tgn:7000084",
          "tgn:7029392"
        ],
        "placetype": [
          "aat:300008347"
        ],
        "id": 7069645,
        "name:xx": "Thonhausen"
      }
    },
    {
      "geometry": {
        "type": "Point",
        "coordinates": [
          11.85,
          48.666667
        ]
      },
      "type": "Feature",
      "properties": {
        "hierarchy": [
          "tgn:7069646",
          "tgn:7003669",
          "tgn:1000003",
          "tgn:7000084",
          "tgn:7029392"
        ],
        "placetype": [
          "aat:300008347"
        ],
        "id": 7069646,
        "name:xx": "Thonhausen"
      }
    },
    {
      "geometry": {
        "type": "Point",
        "coordinates": [
          11.766667,
          48.483333
        ]
      },
      "type": "Feature",
      "properties": {
        "hierarchy": [
          "tgn:7069648",
          "tgn:7003669",
          "tgn:1000003",
          "tgn:7000084",
          "tgn:7029392"
        ],
        "placetype": [
          "aat:300008347"
        ],
        "id": 7069648,
        "name:xx": "Thonhausen"
      }
    },
    {
      "geometry": {
        "type": "Point",
        "coordinates": [
          11.616667,
          48.583333
        ]
      },
      "type": "Feature",
      "properties": {
        "hierarchy": [
          "tgn:7069649",
          "tgn:7003669",
          "tgn:1000003",
          "tgn:7000084",
          "tgn:7029392"
        ],
        "placetype": [
          "aat:300008347"
        ],
        "id": 7069649,
        "name:xx": "Thongräben"
      }
    }
  ]
}
