{
  "type": "FeatureCollection",
  "features": [
    {
      "geometry": {
        "type": "Point",
        "coordinates": [
          -107.25,
          38.2667
        ]
      },
      "type": "Feature",
      "properties": {
        "hierarchy": [
          "tgn:2753000",
          "tgn:1000001",
          "tgn:7012149",
          "tgn:2000217",
          "tgn:7007158",
          "tgn:7029392"
        ],
        "placetype": [
          "aat:300008761"
        ],
        "id": 2753000,
        "name:xx": "Water Gulch"
      }
    },
    {
      "geometry": {
        "type": "Point",
        "coordinates": [
          -114.25,
          43.4833
        ]
      },
      "type": "Feature",
      "properties": {
        "hierarchy": [
          "tgn:2753001",
          "tgn:1000001",
          "tgn:2000458",
          "tgn:7012149",
          "tgn:7007250",
          "tgn:7029392"
        ],
        "placetype": [
          "aat:300008761"
        ],
        "id": 2753001,
        "name:xx": "Water Gulch"
      }
    },
    {
      "geometry": {
        "type": "Point",
        "coordinates": [
          -112.7833,
          45.8167
        ]
      },
      "type": "Feature",
      "properties": {
        "hierarchy": [
          "tgn:2753002",
          "tgn:1000001",
          "tgn:7012149",
          "tgn:2001306",
          "tgn:7007524",
          "tgn:7029392"
        ],
        "placetype": [
          "aat:300008761"
        ],
        "id": 2753002,
        "name:xx": "Water Gulch"
      }
    },
    {
      "geometry": {
        "type": "Point",
        "coordinates": [
          -114.9167,
          47.2167
        ]
      },
      "type": "Feature",
      "properties": {
        "hierarchy": [
          "tgn:2753003",
          "tgn:1000001",
          "tgn:7012149",
          "tgn:2001290",
          "tgn:7007524",
          "tgn:7029392"
        ],
        "placetype": [
          "aat:300008761"
        ],
        "id": 2753003,
        "name:xx": "Water Gulch"
      }
    },
    {
      "geometry": {
        "type": "Point",
        "coordinates": [
          -111.9667,
          45.35
        ]
      },
      "type": "Feature",
      "properties": {
        "hierarchy": [
          "tgn:2753004",
          "tgn:1000001",
          "tgn:7012149",
          "tgn:2001288",
          "tgn:7007524",
          "tgn:7029392"
        ],
        "placetype": [
          "aat:300008761"
        ],
        "id": 2753004,
        "name:xx": "Water Gulch"
      }
    },
    {
      "geometry": {
        "type": "Point",
        "coordinates": [
          -112.2667,
          46.2167
        ]
      },
      "type": "Feature",
      "properties": {
        "hierarchy": [
          "tgn:2753005",
          "tgn:1000001",
          "tgn:7012149",
          "tgn:2001281",
          "tgn:7007524",
          "tgn:7029392"
        ],
        "placetype": [
          "aat:300008761"
        ],
        "id": 2753005,
        "name:xx": "Water Gulch"
      }
    },
    {
      "geometry": {
        "type": "Point",
        "coordinates": [
          -115.4833,
          47.8167
        ]
      },
      "type": "Feature",
      "properties": {
        "hierarchy": [
          "tgn:2753006",
          "tgn:1000001",
          "tgn:7012149",
          "tgn:2001304",
          "tgn:7007524",
          "tgn:7029392"
        ],
        "placetype": [
          "aat:300008761"
        ],
        "id": 2753006,
        "name:xx": "Water Gulch"
      }
    },
    {
      "geometry": {
        "type": "Point",
        "coordinates": [
          -122.8,
          42.1333
        ]
      },
      "type": "Feature",
      "properties": {
        "hierarchy": [
          "tgn:2753007",
          "tgn:1000001",
          "tgn:7012149",
          "tgn:2001711",
          "tgn:7007708",
          "tgn:7029392"
        ],
        "placetype": [
          "aat:300008761"
        ],
        "id": 2753007,
        "name:xx": "Water Gulch"
      }
    },
    {
      "geometry": {
        "type": "Point",
        "coordinates": [
          -118.2,
          43.9167
        ]
      },
      "type": "Feature",
      "properties": {
        "hierarchy": [
          "tgn:2753008",
          "tgn:1000001",
          "tgn:7012149",
          "tgn:2001718",
          "tgn:7007708",
          "tgn:7029392"
        ],
        "placetype": [
          "aat:300008761"
        ],
        "id": 2753008,
        "name:xx": "Water Gulch"
      }
    },
    {
      "geometry": {
        "type": "Point",
        "coordinates": [
          -117.8167,
          44.5667
        ]
      },
      "type": "Feature",
      "properties": {
        "hierarchy": [
          "tgn:2753009",
          "tgn:7013349",
          "tgn:1000001",
          "tgn:7012149",
          "tgn:7007708",
          "tgn:7029392"
        ],
        "placetype": [
          "aat:300008761"
        ],
        "id": 2753009,
        "name:xx": "Water Gulch"
      }
    }
  ]
}
