{
  "geometry": {
    "type": "Point",
    "coordinates": [
      -76.4333,
      42.25
    ]
  },
  "type": "Feature",
  "properties": {
    "hierarchy": [
      "tgn:2269941",
      "tgn:1000001",
      "tgn:7012149",
      "tgn:1002944",
      "tgn:7007568",
      "tgn:7029392"
    ],
    "placetype": [
      "aat:300008347"
    ],
    "id": 2269941,
    "name:xx": "Crum Town"
  }
}
