{
  "geometry": {
    "type": "Point",
    "coordinates": [
      120.5601,
      24.2413
    ]
  },
  "type": "Feature",
  "properties": {
    "hierarchy": [
      "tgn:7498343",
      "tgn:1000004",
      "tgn:7001009",
      "tgn:1000141",
      "tgn:7029392"
    ],
    "placetype": [
      "aat:300007836"
    ],
    "id": 7498343,
    "name:xx": "Shalu Daqiao"
  }
}
