{
  "geometry": {
    "type": "Point",
    "coordinates": [
      46.4833,
      54.4333
    ]
  },
  "type": "Feature",
  "properties": {
    "hierarchy": [
      "tgn:1057132",
      "tgn:1000004",
      "tgn:7011523",
      "tgn:7002435",
      "tgn:7029392"
    ],
    "placetype": [
      "aat:300008347"
    ],
    "id": 1057132,
    "name:xx": "Morga"
  }
}
