{
  "geometry": {
    "type": "Point",
    "coordinates": [
      76.335787,
      26.70003
    ]
  },
  "type": "Feature",
  "properties": {
    "hierarchy": [
      "tgn:7559198",
      "tgn:1000004",
      "tgn:7000198",
      "tgn:7016788",
      "tgn:7029392"
    ],
    "placetype": [
      "aat:300008347"
    ],
    "name:en": "Rāhawās",
    "id": 7559198
  }
}
