{
  "type": "FeatureCollection",
  "features": [
    {
      "geometry": {
        "type": "Point",
        "coordinates": [
          -83.3833,
          33.3167
        ]
      },
      "type": "Feature",
      "properties": {
        "hierarchy": [
          "tgn:2022783",
          "tgn:1000001",
          "tgn:7012149",
          "tgn:2000408",
          "tgn:7007248",
          "tgn:7029392"
        ],
        "placetype": [
          "aat:300008347"
        ],
        "id": 2022783,
        "name:xx": "Eatonton"
      }
    },
    {
      "geometry": {
        "type": "Point",
        "coordinates": [
          -83.7,
          32.6833
        ]
      },
      "type": "Feature",
      "properties": {
        "hierarchy": [
          "tgn:2022785",
          "tgn:1000001",
          "tgn:7012149",
          "tgn:2000402",
          "tgn:7007248",
          "tgn:7029392"
        ],
        "placetype": [
          "aat:300008347",
          "aat:300387210"
        ],
        "id": 2022785,
        "name:xx": "Echeconnee"
      }
    },
    {
      "geometry": {
        "type": "Point",
        "coordinates": [
          -84.9333,
          34.5167
        ]
      },
      "type": "Feature",
      "properties": {
        "hierarchy": [
          "tgn:2022786",
          "tgn:1000001",
          "tgn:7012149",
          "tgn:2000355",
          "tgn:7007248",
          "tgn:7029392"
        ],
        "placetype": [
          "aat:300008347"
        ],
        "id": 2022786,
        "name:xx": "Echota"
      }
    },
    {
      "geometry": {
        "type": "Point",
        "coordinates": [
          -81.3833,
          32.1667
        ]
      },
      "type": "Feature",
      "properties": {
        "hierarchy": [
          "tgn:2022787",
          "tgn:1000001",
          "tgn:7012149",
          "tgn:2000342",
          "tgn:7007248",
          "tgn:7029392"
        ],
        "placetype": [
          "aat:300008347"
        ],
        "id": 2022787,
        "name:xx": "Eden"
      }
    }
  ]
}
