{
  "geometry": {
    "type": "Point",
    "coordinates": [
      -121.7833,
      37.3833
    ]
  },
  "type": "Feature",
  "properties": {
    "hierarchy": [
      "tgn:2131574",
      "tgn:1000001",
      "tgn:7012149",
      "tgn:7007157",
      "tgn:7014475",
      "tgn:7029392"
    ],
    "placetype": [
      "aat:300008798"
    ],
    "id": 2131574,
    "name:xx": "Alum Rock"
  }
}
