{
  "geometry": {
    "type": "Point",
    "coordinates": [
      -109.3333,
      40.3667
    ]
  },
  "type": "Feature",
  "properties": {
    "hierarchy": [
      "tgn:2108973",
      "tgn:1000001",
      "tgn:7012149",
      "tgn:2002124",
      "tgn:7007827",
      "tgn:7029392"
    ],
    "placetype": [
      "aat:300008347"
    ],
    "id": 2108973,
    "name:xx": "Jensen"
  }
}
