{
  "geometry": {
    "type": "Point",
    "coordinates": [
      -75.7833,
      37.9167
    ]
  },
  "type": "Feature",
  "properties": {
    "hierarchy": [
      "tgn:1115025",
      "tgn:1000001",
      "tgn:7012149",
      "tgn:7029392"
    ],
    "placetype": [
      "aat:300266558"
    ],
    "id": 1115025,
    "name:xx": "Pocomoke Sound"
  }
}
