{
  "geometry": {
    "type": "Point",
    "coordinates": [
      -107.9833,
      39.3833
    ]
  },
  "type": "Feature",
  "properties": {
    "hierarchy": [
      "tgn:2576963",
      "tgn:1000001",
      "tgn:7012149",
      "tgn:2000214",
      "tgn:7007158",
      "tgn:7029392"
    ],
    "placetype": [
      "aat:300008706"
    ],
    "id": 2576963,
    "name:xx": "Pete and Bill Creek"
  }
}
