{
  "geometry": {
    "type": "Point",
    "coordinates": [
      68.4333,
      26.25
    ]
  },
  "type": "Feature",
  "properties": {
    "hierarchy": [
      "tgn:1083686",
      "tgn:1000004",
      "tgn:7002462",
      "tgn:1000133",
      "tgn:7029392"
    ],
    "placetype": [
      "aat:300008347",
      "aat:300008375"
    ],
    "id": 1083686,
    "name:xx": "Nawābshāh"
  }
}
