{
  "geometry": {
    "type": "Point",
    "coordinates": [
      -83.4667,
      31.3167
    ]
  },
  "type": "Feature",
  "properties": {
    "hierarchy": [
      "tgn:2200064",
      "tgn:1000001",
      "tgn:2000328",
      "tgn:7012149",
      "tgn:7007248",
      "tgn:7029392"
    ],
    "placetype": [
      "aat:300008706"
    ],
    "id": 2200064,
    "name:xx": "Brushy Creek"
  }
}
