{
  "type": "FeatureCollection",
  "features": [
    {
      "geometry": {
        "type": "Point",
        "coordinates": [
          -105.6833,
          32.7333
        ]
      },
      "type": "Feature",
      "properties": {
        "hierarchy": [
          "tgn:2464870",
          "tgn:1000001",
          "tgn:7012149",
          "tgn:2001447",
          "tgn:7007566",
          "tgn:7029392"
        ],
        "placetype": [
          "aat:300006191"
        ],
        "id": 2464870,
        "name:xx": "Logan Tank"
      }
    },
    {
      "geometry": {
        "type": "Point",
        "coordinates": [
          -118.65,
          44.2
        ]
      },
      "type": "Feature",
      "properties": {
        "hierarchy": [
          "tgn:2464871",
          "tgn:1000001",
          "tgn:7012149",
          "tgn:2001708",
          "tgn:7007708",
          "tgn:7029392"
        ],
        "placetype": [
          "aat:300008761"
        ],
        "id": 2464871,
        "name:xx": "Logan Valley"
      }
    },
    {
      "geometry": {
        "type": "Point",
        "coordinates": [
          -78.35,
          40.55
        ]
      },
      "type": "Feature",
      "properties": {
        "hierarchy": [
          "tgn:2464872",
          "tgn:1000001",
          "tgn:1002185",
          "tgn:7012149",
          "tgn:7007710",
          "tgn:7029392"
        ],
        "placetype": [
          "aat:300008761"
        ],
        "id": 2464872,
        "name:xx": "Logan Valley"
      }
    },
    {
      "geometry": {
        "type": "Point",
        "coordinates": [
          -112.6,
          34.5333
        ]
      },
      "type": "Feature",
      "properties": {
        "hierarchy": [
          "tgn:2464873",
          "tgn:1000001",
          "tgn:7006451",
          "tgn:7012149",
          "tgn:2000103",
          "tgn:7029392"
        ],
        "placetype": [
          "aat:300008699"
        ],
        "id": 2464873,
        "name:xx": "Logan Wash"
      }
    },
    {
      "geometry": {
        "type": "Point",
        "coordinates": [
          -108.15,
          39.4167
        ]
      },
      "type": "Feature",
      "properties": {
        "hierarchy": [
          "tgn:2464874",
          "tgn:1000001",
          "tgn:7012149",
          "tgn:2000214",
          "tgn:7007158",
          "tgn:7029392"
        ],
        "placetype": [
          "aat:300008699"
        ],
        "id": 2464874,
        "name:xx": "Logan Wash"
      }
    },
    {
      "geometry": {
        "type": "Point",
        "coordinates": [
          -114.5167,
          36.5833
        ]
      },
      "type": "Feature",
      "properties": {
        "hierarchy": [
          "tgn:2464875",
          "tgn:1000001",
          "tgn:2001410",
          "tgn:7012149",
          "tgn:7007526",
          "tgn:7029392"
        ],
        "placetype": [
          "aat:300008699"
        ],
        "id": 2464875,
        "name:xx": "Logan Wash"
      }
    },
    {
      "geometry": {
        "type": "Point",
        "coordinates": [
          -83.6833,
          30.5
        ]
      },
      "type": "Feature",
      "properties": {
        "hierarchy": [
          "tgn:2464876",
          "tgn:1000001",
          "tgn:7012149",
          "tgn:2000279",
          "tgn:7007240",
          "tgn:7029392"
        ],
        "placetype": [
          "aat:300008680"
        ],
        "id": 2464876,
        "name:xx": "Logan, Lake"
      }
    },
    {
      "geometry": {
        "type": "Point",
        "coordinates": [
          -82.45,
          39.5333
        ]
      },
      "type": "Feature",
      "properties": {
        "hierarchy": [
          "tgn:2464879",
          "tgn:1000001",
          "tgn:7012149",
          "tgn:2001613",
          "tgn:7007706",
          "tgn:7029392"
        ],
        "placetype": [
          "aat:300006191"
        ],
        "id": 2464879,
        "name:xx": "Logan, Lake"
      }
    }
  ]
}
