{
  "geometry": {
    "type": "Point",
    "coordinates": [
      -119.8333,
      41.8333
    ]
  },
  "type": "Feature",
  "properties": {
    "hierarchy": [
      "tgn:2526148",
      "tgn:1000001",
      "tgn:7012149",
      "tgn:1002999",
      "tgn:7007526",
      "tgn:7029392"
    ],
    "placetype": [
      "aat:300008680"
    ],
    "id": 2526148,
    "name:xx": "Mosquito Lake"
  }
}
