{
  "geometry": {
    "type": "Point",
    "coordinates": [
      -86.45,
      32.1667
    ]
  },
  "type": "Feature",
  "properties": {
    "hierarchy": [
      "tgn:2405343",
      "tgn:7002659",
      "tgn:1000001",
      "tgn:7012149",
      "tgn:2000042",
      "tgn:7029392"
    ],
    "placetype": [
      "aat:300006191"
    ],
    "id": 2405343,
    "name:xx": "Huffmans Pond"
  }
}
