{
  "geometry": {
    "type": "Point",
    "coordinates": [
      -65.8333,
      46.8333
    ]
  },
  "type": "Feature",
  "properties": {
    "hierarchy": [
      "tgn:1129074",
      "tgn:7005685",
      "tgn:1000001",
      "tgn:7005799",
      "tgn:7029392"
    ],
    "placetype": [
      "aat:300008707"
    ],
    "id": 1129074,
    "name:xx": "Renous"
  }
}
