{
  "type": "FeatureCollection",
  "features": [
    {
      "geometry": {
        "type": "Point",
        "coordinates": [
          -78.2167,
          40.8833
        ]
      },
      "type": "Feature",
      "properties": {
        "hierarchy": [
          "tgn:2091905",
          "tgn:1000001",
          "tgn:1002249",
          "tgn:7012149",
          "tgn:7007710",
          "tgn:7029392"
        ],
        "placetype": [
          "aat:300008347"
        ],
        "id": 2091905,
        "name:xx": "Philipsburg"
      }
    },
    {
      "geometry": {
        "type": "Point",
        "coordinates": [
          -77.4833,
          41.9333
        ]
      },
      "type": "Feature",
      "properties": {
        "hierarchy": [
          "tgn:2091908",
          "tgn:1000001",
          "tgn:7012149",
          "tgn:1002945",
          "tgn:7007710",
          "tgn:7029392"
        ],
        "placetype": [
          "aat:300008347",
          "aat:300387210"
        ],
        "id": 2091908,
        "name:xx": "Phillips"
      }
    },
    {
      "geometry": {
        "type": "Point",
        "coordinates": [
          -79.7167,
          39.9333
        ]
      },
      "type": "Feature",
      "properties": {
        "hierarchy": [
          "tgn:2091909",
          "tgn:1000001",
          "tgn:7012149",
          "tgn:7014185",
          "tgn:7007710",
          "tgn:7029392"
        ],
        "placetype": [
          "aat:300008347"
        ],
        "id": 2091909,
        "name:xx": "Phillips"
      }
    }
  ]
}
