{
  "geometry": {
    "type": "Point",
    "coordinates": [
      -119.3833,
      48.3333
    ]
  },
  "type": "Feature",
  "properties": {
    "hierarchy": [
      "tgn:2158640",
      "tgn:1000001",
      "tgn:7012149",
      "tgn:1002742",
      "tgn:7007920",
      "tgn:7029392"
    ],
    "placetype": [
      "aat:300008706"
    ],
    "id": 2158640,
    "name:xx": "Beaverhouse Creek"
  }
}
