{
  "geometry": {
    "type": "Point",
    "coordinates": [
      -107.1333,
      33.2833
    ]
  },
  "type": "Feature",
  "properties": {
    "hierarchy": [
      "tgn:2185748",
      "tgn:1000001",
      "tgn:7012149",
      "tgn:2001455",
      "tgn:7007566",
      "tgn:7029392"
    ],
    "placetype": [
      "aat:300000390"
    ],
    "id": 2185748,
    "name:xx": "Bolander"
  }
}
