{
  "geometry": {
    "type": "Point",
    "coordinates": [
      -109.4667,
      44.45
    ]
  },
  "type": "Feature",
  "properties": {
    "hierarchy": [
      "tgn:2547706",
      "tgn:1000001",
      "tgn:7012149",
      "tgn:2002379",
      "tgn:7007923",
      "tgn:7029392"
    ],
    "placetype": [
      "aat:300006075"
    ],
    "id": 2547706,
    "name:xx": "North Fork Valley Ditch"
  }
}
