{
  "type": "FeatureCollection",
  "features": [
    {
      "geometry": {
        "type": "Point",
        "coordinates": [
          8.05,
          51.466667
        ]
      },
      "type": "Feature",
      "properties": {
        "hierarchy": [
          "tgn:7138800",
          "tgn:1000003",
          "tgn:7003677",
          "tgn:7000084",
          "tgn:7029392"
        ],
        "placetype": [
          "aat:300008777"
        ],
        "id": 7138800,
        "name:xx": "Langer Berg"
      }
    },
    {
      "geometry": {
        "type": "Point",
        "coordinates": [
          13.066667,
          51.433333
        ]
      },
      "type": "Feature",
      "properties": {
        "hierarchy": [
          "tgn:7138801",
          "tgn:1000003",
          "tgn:7003685",
          "tgn:7000084",
          "tgn:7029392"
        ],
        "placetype": [
          "aat:300008777"
        ],
        "id": 7138801,
        "name:xx": "Langer-Berg"
      }
    },
    {
      "geometry": {
        "type": "Point",
        "coordinates": [
          8.483333,
          51.366667
        ]
      },
      "type": "Feature",
      "properties": {
        "hierarchy": [
          "tgn:7138802",
          "tgn:1000003",
          "tgn:7003677",
          "tgn:7000084",
          "tgn:7029392"
        ],
        "placetype": [
          "aat:300008777"
        ],
        "id": 7138802,
        "name:xx": "Langer Berg"
      }
    },
    {
      "geometry": {
        "type": "Point",
        "coordinates": [
          6.866667,
          51.316667
        ]
      },
      "type": "Feature",
      "properties": {
        "hierarchy": [
          "tgn:7138804",
          "tgn:1000003",
          "tgn:7003677",
          "tgn:7000084",
          "tgn:7029392"
        ],
        "placetype": [
          "aat:300008777"
        ],
        "id": 7138804,
        "name:xx": "Langer Berg"
      }
    },
    {
      "geometry": {
        "type": "Point",
        "coordinates": [
          11.733333,
          51.166667
        ]
      },
      "type": "Feature",
      "properties": {
        "hierarchy": [
          "tgn:7138805",
          "tgn:1000003",
          "tgn:7003687",
          "tgn:7000084",
          "tgn:7029392"
        ],
        "placetype": [
          "aat:300008777"
        ],
        "id": 7138805,
        "name:xx": "Langer Berg"
      }
    },
    {
      "geometry": {
        "type": "Point",
        "coordinates": [
          10.983333,
          51.183333
        ]
      },
      "type": "Feature",
      "properties": {
        "hierarchy": [
          "tgn:7138806",
          "tgn:1000003",
          "tgn:7003689",
          "tgn:7000084",
          "tgn:7029392"
        ],
        "placetype": [
          "aat:300008777"
        ],
        "id": 7138806,
        "name:xx": "Langer-Berg"
      }
    },
    {
      "geometry": {
        "type": "Point",
        "coordinates": [
          13.65,
          51.166667
        ]
      },
      "type": "Feature",
      "properties": {
        "hierarchy": [
          "tgn:7138807",
          "tgn:1000003",
          "tgn:7003685",
          "tgn:7000084",
          "tgn:7029392"
        ],
        "placetype": [
          "aat:300008777"
        ],
        "id": 7138807,
        "name:xx": "Langer Berg"
      }
    },
    {
      "geometry": {
        "type": "Point",
        "coordinates": [
          9.816667,
          51.166667
        ]
      },
      "type": "Feature",
      "properties": {
        "hierarchy": [
          "tgn:7138809",
          "tgn:1000003",
          "tgn:7003678",
          "tgn:7000084",
          "tgn:7029392"
        ],
        "placetype": [
          "aat:300008777"
        ],
        "id": 7138809,
        "name:xx": "Langer Berg"
      }
    }
  ]
}
