{
  "type": "FeatureCollection",
  "features": [
    {
      "geometry": {
        "type": "Point",
        "coordinates": [
          100.6,
          20.1167
        ]
      },
      "type": "Feature",
      "properties": {
        "hierarchy": [
          "tgn:1130790",
          "tgn:1000004",
          "tgn:1000125",
          "tgn:7029392"
        ],
        "placetype": [
          "aat:300008707"
        ],
        "id": 1130790,
        "name:xx": "Tha, Nam"
      }
    },
    {
      "geometry": {
        "type": "Point",
        "coordinates": [
          -94.6167,
          60.5167
        ]
      },
      "type": "Feature",
      "properties": {
        "hierarchy": [
          "tgn:1130791",
          "tgn:7005685",
          "tgn:1000001",
          "tgn:7024197",
          "tgn:7029392"
        ],
        "placetype": [
          "aat:300008707"
        ],
        "id": 1130791,
        "name:xx": "Tha-anne"
      }
    },
    {
      "geometry": {
        "type": "Point",
        "coordinates": [
          -72.0667,
          41.5167
        ]
      },
      "type": "Feature",
      "properties": {
        "hierarchy": [
          "tgn:1130792",
          "tgn:1000001",
          "tgn:1002714",
          "tgn:7012149",
          "tgn:7007159",
          "tgn:7029392"
        ],
        "placetype": [
          "aat:300008707"
        ],
        "id": 1130792,
        "name:xx": "Thames"
      }
    },
    {
      "geometry": {
        "type": "Point",
        "coordinates": [
          22.6,
          -20.45
        ]
      },
      "type": "Feature",
      "properties": {
        "hierarchy": [
          "tgn:1130795",
          "tgn:7001242",
          "tgn:1000905",
          "tgn:1000150",
          "tgn:7029392"
        ],
        "placetype": [
          "aat:300008707"
        ],
        "id": 1130795,
        "name:xx": "Thaoge"
      }
    },
    {
      "geometry": {
        "type": "Point",
        "coordinates": [
          97.6667,
          17.8333
        ]
      },
      "type": "Feature",
      "properties": {
        "hierarchy": [
          "tgn:1130797",
          "tgn:1000004",
          "tgn:7029392"
        ],
        "placetype": [
          "aat:300008707"
        ],
        "id": 1130797,
        "name:xx": "Thaungyin"
      }
    }
  ]
}
