{
  "geometry": {
    "type": "Point",
    "coordinates": [
      112.4333,
      34.7833
    ]
  },
  "type": "Feature",
  "properties": {
    "hierarchy": [
      "tgn:7001880",
      "tgn:1000004",
      "tgn:7016672",
      "tgn:1000111",
      "tgn:7029392"
    ],
    "placetype": [
      "aat:300008347",
      "aat:300008389",
      "aat:300387305",
      "aat:300387302",
      "aat:300235099",
      "aat:300387286"
    ],
    "id": 7001880,
    "name:xx": "Luoyang"
  }
}
