{
  "geometry": {
    "type": "Point",
    "coordinates": [
      -92.85,
      41.85
    ]
  },
  "type": "Feature",
  "properties": {
    "hierarchy": [
      "tgn:2476577",
      "tgn:1000001",
      "tgn:7012149",
      "tgn:7007253",
      "tgn:7029392"
    ],
    "placetype": [
      "aat:300008706"
    ],
    "id": 2476577,
    "name:xx": "Lutes Creek"
  }
}
