{
  "geometry": {
    "type": "Point",
    "coordinates": [
      75.044079,
      31.885704
    ]
  },
  "type": "Feature",
  "properties": {
    "hierarchy": [
      "tgn:7574117",
      "tgn:1000004",
      "tgn:7000198",
      "tgn:7016883",
      "tgn:7029392"
    ],
    "placetype": [
      "aat:300008347"
    ],
    "name:en": "Kāla Afghānān",
    "id": 7574117
  }
}
