{
  "geometry": {
    "type": "Point",
    "coordinates": [
      -124.2833,
      42.2833
    ]
  },
  "type": "Feature",
  "properties": {
    "hierarchy": [
      "tgn:2583416",
      "tgn:1000001",
      "tgn:2001704",
      "tgn:7012149",
      "tgn:7007708",
      "tgn:7029392"
    ],
    "placetype": [
      "aat:300008798"
    ],
    "id": 2583416,
    "name:xx": "Pine Point"
  }
}
