{
  "geometry": {
    "type": "Point",
    "coordinates": [
      18.65,
      -17.5667
    ]
  },
  "type": "Feature",
  "properties": {
    "hierarchy": [
      "tgn:1087771",
      "tgn:7001242",
      "tgn:1000149",
      "tgn:1000833",
      "tgn:7029392"
    ],
    "placetype": [
      "aat:300008347"
    ],
    "id": 1087771,
    "name:xx": "Cuangar"
  }
}
