{
  "geometry": {
    "type": "Point",
    "coordinates": [
      -120.5167,
      40.3333
    ]
  },
  "type": "Feature",
  "properties": {
    "hierarchy": [
      "tgn:2150747",
      "tgn:1000001",
      "tgn:7012149",
      "tgn:7007157",
      "tgn:2000184",
      "tgn:7029392"
    ],
    "placetype": [
      "aat:300008798"
    ],
    "id": 2150747,
    "name:xx": "Bass Hill"
  }
}
