{
  "geometry": {
    "type": "Point",
    "coordinates": [
      -83.75,
      37.9833
    ]
  },
  "type": "Feature",
  "properties": {
    "hierarchy": [
      "tgn:2760384",
      "tgn:1000001",
      "tgn:7012149",
      "tgn:2000826",
      "tgn:7007255",
      "tgn:7029392"
    ],
    "placetype": [
      "aat:300008706"
    ],
    "id": 2760384,
    "name:xx": "West Fork Slate Creek"
  }
}
