{
  "geometry": {
    "type": "Point",
    "coordinates": [
      -82.7833,
      32.9333
    ]
  },
  "type": "Feature",
  "properties": {
    "hierarchy": [
      "tgn:1128034",
      "tgn:1000001",
      "tgn:7012149",
      "tgn:7007248",
      "tgn:7029392"
    ],
    "placetype": [
      "aat:300008707"
    ],
    "id": 1128034,
    "name:xx": "Ohoopee"
  }
}
