{
  "geometry": {
    "type": "Point",
    "coordinates": [
      29.8833,
      46.7167
    ]
  },
  "type": "Feature",
  "properties": {
    "hierarchy": [
      "tgn:1125759",
      "tgn:1000003",
      "tgn:1003396",
      "tgn:7006660",
      "tgn:7029392"
    ],
    "placetype": [
      "aat:300008707"
    ],
    "id": 1125759,
    "name:xx": "Kučurgan"
  }
}
