{
  "geometry": {
    "type": "Point",
    "coordinates": [
      -106.1333,
      38.8167
    ]
  },
  "type": "Feature",
  "properties": {
    "hierarchy": [
      "tgn:2424733",
      "tgn:1000001",
      "tgn:2000199",
      "tgn:7012149",
      "tgn:7007158",
      "tgn:7029392"
    ],
    "placetype": [
      "aat:300006075"
    ],
    "id": 2424733,
    "name:xx": "Johnson Ditch"
  }
}
