{
  "geometry": {
    "type": "Point",
    "coordinates": [
      -111.3167,
      34.7833
    ]
  },
  "type": "Feature",
  "properties": {
    "hierarchy": [
      "tgn:2326057",
      "tgn:1000001",
      "tgn:7006451",
      "tgn:2000092",
      "tgn:7012149",
      "tgn:7029392"
    ],
    "placetype": [
      "aat:300006191"
    ],
    "id": 2326057,
    "name:xx": "Fiftyseven Tank"
  }
}
