{
  "geometry": {
    "type": "Point",
    "coordinates": [
      -117.1833,
      41.3833
    ]
  },
  "type": "Feature",
  "properties": {
    "hierarchy": [
      "tgn:2539012",
      "tgn:1000001",
      "tgn:2001414",
      "tgn:7012149",
      "tgn:7007526",
      "tgn:7029392"
    ],
    "placetype": [
      "aat:300008707"
    ],
    "id": 2539012,
    "name:xx": "New Channel Little Humboldt River"
  }
}
