{
  "geometry": {
    "type": "Point",
    "coordinates": [
      32.59834,
      25.336665
    ]
  },
  "type": "Feature",
  "properties": {
    "hierarchy": [
      "tgn:7523522",
      "tgn:7001242",
      "tgn:7001311",
      "tgn:7016833",
      "tgn:7029392"
    ],
    "placetype": [
      "aat:300379998"
    ],
    "name:en": "Falq al Hunūd, Wādī",
    "id": 7523522
  }
}
