{
  "geometry": {
    "type": "Point",
    "coordinates": [
      -113.4167,
      41.9833
    ]
  },
  "type": "Feature",
  "properties": {
    "hierarchy": [
      "tgn:2026147",
      "tgn:1000001",
      "tgn:2000467",
      "tgn:7012149",
      "tgn:7007250",
      "tgn:7029392"
    ],
    "placetype": [
      "aat:300008347",
      "aat:300387210"
    ],
    "id": 2026147,
    "name:xx": "Standrod"
  }
}
