{
  "geometry": {
    "type": "Point",
    "coordinates": [
      -81.7167,
      39.8667
    ]
  },
  "type": "Feature",
  "properties": {
    "hierarchy": [
      "tgn:2685495",
      "tgn:1000001",
      "tgn:7012149",
      "tgn:1002701",
      "tgn:7007706",
      "tgn:7029392"
    ],
    "placetype": [
      "aat:300008347"
    ],
    "id": 2685495,
    "name:xx": "Spratt"
  }
}
