{
  "type": "FeatureCollection",
  "features": [
    {
      "geometry": {
        "type": "Point",
        "coordinates": [
          -82.5167,
          38.1833
        ]
      },
      "type": "Feature",
      "properties": {
        "hierarchy": [
          "tgn:2357872",
          "tgn:1000001",
          "tgn:7012149",
          "tgn:2002299",
          "tgn:7013961",
          "tgn:7029392"
        ],
        "placetype": [
          "aat:300008706"
        ],
        "id": 2357872,
        "name:xx": "Gragston Creek"
      }
    },
    {
      "geometry": {
        "type": "Point",
        "coordinates": [
          -115.2667,
          43.9667
        ]
      },
      "type": "Feature",
      "properties": {
        "hierarchy": [
          "tgn:2357873",
          "tgn:1000001",
          "tgn:2000459",
          "tgn:7012149",
          "tgn:7007250",
          "tgn:7029392"
        ],
        "placetype": [
          "aat:300008347"
        ],
        "id": 2357873,
        "name:xx": "Graham"
      }
    },
    {
      "geometry": {
        "type": "Point",
        "coordinates": [
          -87.1833,
          40.15
        ]
      },
      "type": "Feature",
      "properties": {
        "hierarchy": [
          "tgn:2357874",
          "tgn:1000001",
          "tgn:7012149",
          "tgn:1002380",
          "tgn:7007252",
          "tgn:7029392"
        ],
        "placetype": [
          "aat:300008347"
        ],
        "id": 2357874,
        "name:xx": "Graham"
      }
    },
    {
      "geometry": {
        "type": "Point",
        "coordinates": [
          -87.1833,
          38.7167
        ]
      },
      "type": "Feature",
      "properties": {
        "hierarchy": [
          "tgn:2357875",
          "tgn:1000001",
          "tgn:2000541",
          "tgn:7012149",
          "tgn:7007252",
          "tgn:7029392"
        ],
        "placetype": [
          "aat:300008347"
        ],
        "id": 2357875,
        "name:xx": "Graham"
      }
    },
    {
      "geometry": {
        "type": "Point",
        "coordinates": [
          -92.55,
          31.3
        ]
      },
      "type": "Feature",
      "properties": {
        "hierarchy": [
          "tgn:2357876",
          "tgn:1000001",
          "tgn:7012149",
          "tgn:2000893",
          "tgn:7007256",
          "tgn:7029392"
        ],
        "placetype": [
          "aat:300008347"
        ],
        "id": 2357876,
        "name:xx": "Graham"
      }
    },
    {
      "geometry": {
        "type": "Point",
        "coordinates": [
          -88.8333,
          32.3333
        ]
      },
      "type": "Feature",
      "properties": {
        "hierarchy": [
          "tgn:2357877",
          "tgn:1000001",
          "tgn:7012149",
          "tgn:2001123",
          "tgn:7007522",
          "tgn:7029392"
        ],
        "placetype": [
          "aat:300008347"
        ],
        "id": 2357877,
        "name:xx": "Graham"
      }
    },
    {
      "geometry": {
        "type": "Point",
        "coordinates": [
          -73.8,
          41.1167
        ]
      },
      "type": "Feature",
      "properties": {
        "hierarchy": [
          "tgn:2357878",
          "tgn:1000001",
          "tgn:7012149",
          "tgn:7014612",
          "tgn:7007568",
          "tgn:7029392"
        ],
        "placetype": [
          "aat:300008347"
        ],
        "id": 2357878,
        "name:xx": "Graham"
      }
    },
    {
      "geometry": {
        "type": "Point",
        "coordinates": [
          -81.2,
          39.65
        ]
      },
      "type": "Feature",
      "properties": {
        "hierarchy": [
          "tgn:2357879",
          "tgn:1000001",
          "tgn:7012149",
          "tgn:2001617",
          "tgn:7007706",
          "tgn:7029392"
        ],
        "placetype": [
          "aat:300008347"
        ],
        "id": 2357879,
        "name:xx": "Graham"
      }
    }
  ]
}
