{
  "geometry": {
    "type": "Point",
    "coordinates": [
      -98.15,
      22.016667
    ]
  },
  "type": "Feature",
  "properties": {
    "hierarchy": [
      "tgn:7401386",
      "tgn:1000001",
      "tgn:7005599",
      "tgn:7005560",
      "tgn:7029392"
    ],
    "placetype": [
      "aat:300008347"
    ],
    "id": 7401386,
    "name:xx": "San Cristóbal"
  }
}
