{
  "geometry": {
    "type": "Point",
    "coordinates": [
      -88.125,
      21.3625
    ]
  },
  "type": "Feature",
  "properties": {
    "hierarchy": [
      "tgn:7403268",
      "tgn:1000001",
      "tgn:7005600",
      "tgn:7005560",
      "tgn:7029392"
    ],
    "placetype": [
      "aat:300008347"
    ],
    "id": 7403268,
    "name:xx": "San Antonio Macan"
  }
}
