{
  "type": "FeatureCollection",
  "features": [
    {
      "geometry": {
        "type": "Point",
        "coordinates": [
          78.219274,
          26.270852
        ]
      },
      "type": "Feature",
      "properties": {
        "hierarchy": [
          "tgn:7575460",
          "tgn:1000004",
          "tgn:7000198",
          "tgn:1001894",
          "tgn:7029392"
        ],
        "placetype": [
          "aat:300008347"
        ],
        "name:en": "Mahārājpur",
        "id": 7575460
      }
    },
    {
      "geometry": {
        "type": "Point",
        "coordinates": [
          87.747443,
          25.205791
        ]
      },
      "type": "Feature",
      "properties": {
        "hierarchy": [
          "tgn:7575461",
          "tgn:1000004",
          "tgn:7000198",
          "tgn:1001977",
          "tgn:7029392"
        ],
        "placetype": [
          "aat:300008347"
        ],
        "name:en": "Mahārājpur",
        "id": 7575461
      }
    },
    {
      "geometry": {
        "type": "Point",
        "coordinates": [
          87.8,
          24.816667
        ]
      },
      "type": "Feature",
      "properties": {
        "hierarchy": [
          "tgn:7575462",
          "tgn:1000004",
          "tgn:7000198",
          "tgn:1001977",
          "tgn:7029392"
        ],
        "placetype": [
          "aat:300008347"
        ],
        "name:en": "Mahārājpur",
        "id": 7575462
      }
    },
    {
      "geometry": {
        "type": "Point",
        "coordinates": [
          79.052508,
          23.283612
        ]
      },
      "type": "Feature",
      "properties": {
        "hierarchy": [
          "tgn:7575463",
          "tgn:1000004",
          "tgn:7000198",
          "tgn:1001894",
          "tgn:7029392"
        ],
        "placetype": [
          "aat:300008347"
        ],
        "name:en": "Mahārājpur",
        "id": 7575463
      }
    },
    {
      "geometry": {
        "type": "Point",
        "coordinates": [
          80.363508,
          22.588409
        ]
      },
      "type": "Feature",
      "properties": {
        "hierarchy": [
          "tgn:7575464",
          "tgn:1000004",
          "tgn:7000198",
          "tgn:1001894",
          "tgn:7029392"
        ],
        "placetype": [
          "aat:300008347"
        ],
        "name:en": "Mahārājpur",
        "id": 7575464
      }
    },
    {
      "geometry": {
        "type": "Point",
        "coordinates": [
          81.166667,
          21.966667
        ]
      },
      "type": "Feature",
      "properties": {
        "hierarchy": [
          "tgn:7575465",
          "tgn:1000004",
          "tgn:7031781",
          "tgn:7000198",
          "tgn:7029392"
        ],
        "placetype": [
          "aat:300008347"
        ],
        "name:en": "Mahārājpur",
        "id": 7575465
      }
    },
    {
      "geometry": {
        "type": "Point",
        "coordinates": [
          80.955261,
          27.570234
        ]
      },
      "type": "Feature",
      "properties": {
        "hierarchy": [
          "tgn:7575466",
          "tgn:1000004",
          "tgn:7000198",
          "tgn:7016722",
          "tgn:7029392"
        ],
        "placetype": [
          "aat:300008347"
        ],
        "name:en": "Mahārājnagar",
        "id": 7575466
      }
    },
    {
      "geometry": {
        "type": "Point",
        "coordinates": [
          82.567746,
          21.570937
        ]
      },
      "type": "Feature",
      "properties": {
        "hierarchy": [
          "tgn:7575467",
          "tgn:1000004",
          "tgn:7031781",
          "tgn:7000198",
          "tgn:7029392"
        ],
        "placetype": [
          "aat:300008347"
        ],
        "name:en": "Mahārāji",
        "id": 7575467
      }
    },
    {
      "geometry": {
        "type": "Point",
        "coordinates": [
          81.274593,
          26.381561
        ]
      },
      "type": "Feature",
      "properties": {
        "hierarchy": [
          "tgn:7575469",
          "tgn:1000004",
          "tgn:7000198",
          "tgn:7016722",
          "tgn:7029392"
        ],
        "placetype": [
          "aat:300008347"
        ],
        "name:en": "Mahārājganj",
        "id": 7575469
      }
    }
  ]
}
