{
  "geometry": {
    "type": "Point",
    "coordinates": [
      -111.6167,
      38.0833
    ]
  },
  "type": "Feature",
  "properties": {
    "hierarchy": [
      "tgn:2275963",
      "tgn:1000001",
      "tgn:7012149",
      "tgn:7007827",
      "tgn:7029392"
    ],
    "placetype": [
      "aat:300008761"
    ],
    "id": 2275963,
    "name:xx": "Dark Valley"
  }
}
