{
  "type": "FeatureCollection",
  "features": [
    {
      "geometry": {
        "type": "Point",
        "coordinates": [
          27,
          37.683333
        ]
      },
      "type": "Feature",
      "properties": {
        "hierarchy": [
          "tgn:7223973",
          "tgn:7011164",
          "tgn:7002674",
          "tgn:1000003",
          "tgn:1000074",
          "tgn:7029392"
        ],
        "placetype": [
          "aat:300266559"
        ],
        "id": 7223973,
        "name:xx": "Sámou, Díavlos"
      }
    },
    {
      "geometry": {
        "type": "Point",
        "coordinates": [
          20.650556,
          39.344722
        ]
      },
      "type": "Feature",
      "properties": {
        "hierarchy": [
          "tgn:7223976",
          "tgn:7002709",
          "tgn:7002705",
          "tgn:1000003",
          "tgn:1000074",
          "tgn:7029392"
        ],
        "placetype": [
          "aat:300008347"
        ],
        "id": 7223976,
        "name:xx": "Samonída"
      }
    },
    {
      "geometry": {
        "type": "Point",
        "coordinates": [
          24.1,
          35.416667
        ]
      },
      "type": "Feature",
      "properties": {
        "hierarchy": [
          "tgn:7223977",
          "tgn:7002690",
          "tgn:7012056",
          "tgn:1000003",
          "tgn:1000074",
          "tgn:7029392"
        ],
        "placetype": [
          "aat:300008347"
        ],
        "id": 7223977,
        "name:xx": "Samonás"
      }
    },
    {
      "geometry": {
        "type": "Point",
        "coordinates": [
          20.433333,
          38.25
        ]
      },
      "type": "Feature",
      "properties": {
        "hierarchy": [
          "tgn:7223978",
          "tgn:7011167",
          "tgn:7001338",
          "tgn:1000003",
          "tgn:1000074",
          "tgn:7029392"
        ],
        "placetype": [
          "aat:300386846"
        ],
        "id": 7223978,
        "name:xx": "Samóli, Ákra"
      }
    },
    {
      "geometry": {
        "type": "Point",
        "coordinates": [
          24.666667,
          35.216667
        ]
      },
      "type": "Feature",
      "properties": {
        "hierarchy": [
          "tgn:7223979",
          "tgn:7002690",
          "tgn:7012056",
          "tgn:1000003",
          "tgn:1000074",
          "tgn:7029392"
        ],
        "placetype": [
          "aat:300008798"
        ],
        "id": 7223979,
        "name:xx": "Samítos"
      }
    }
  ]
}
