{
  "geometry": {
    "type": "Point",
    "coordinates": [
      -110.3333,
      37.0333
    ]
  },
  "type": "Feature",
  "properties": {
    "hierarchy": [
      "tgn:2395297",
      "tgn:1000001",
      "tgn:7012149",
      "tgn:2002119",
      "tgn:7007827",
      "tgn:7029392"
    ],
    "placetype": [
      "aat:300008798"
    ],
    "id": 2395297,
    "name:xx": "Holiday Mesa"
  }
}
