{
  "geometry": {
    "type": "Point",
    "coordinates": [
      -104.1667,
      30.6167
    ]
  },
  "type": "Feature",
  "properties": {
    "hierarchy": [
      "tgn:1105414",
      "tgn:1000001",
      "tgn:7012149",
      "tgn:2002010",
      "tgn:7007826",
      "tgn:7029392"
    ],
    "placetype": [
      "aat:300008795"
    ],
    "id": 1105414,
    "name:xx": "Livermore, Mount"
  }
}
