{
  "type": "FeatureCollection",
  "features": [
    {
      "geometry": {
        "type": "Point",
        "coordinates": [
          -4.033333,
          50.516667
        ]
      },
      "type": "Feature",
      "properties": {
        "hierarchy": [
          "tgn:7448473",
          "tgn:7002445",
          "tgn:1000003",
          "tgn:7012077",
          "tgn:7008591",
          "tgn:7029392"
        ],
        "placetype": [
          "aat:300011692"
        ],
        "name:en": "Sharpitor",
        "id": 7448473
      }
    },
    {
      "geometry": {
        "type": "Point",
        "coordinates": [
          -2.05,
          55.316667
        ]
      },
      "type": "Feature",
      "properties": {
        "hierarchy": [
          "tgn:7448474",
          "tgn:7002445",
          "tgn:1000003",
          "tgn:7008165",
          "tgn:7008591",
          "tgn:7029392"
        ],
        "placetype": [
          "aat:300008347"
        ],
        "name:en": "Sharperton",
        "id": 7448474
      }
    },
    {
      "geometry": {
        "type": "Point",
        "coordinates": [
          -2,
          55.783333
        ]
      },
      "type": "Feature",
      "properties": {
        "hierarchy": [
          "tgn:7448475",
          "tgn:7002445",
          "tgn:1000003",
          "tgn:7008165",
          "tgn:7008591",
          "tgn:7029392"
        ],
        "placetype": [
          "aat:300008850"
        ],
        "name:en": "Sharpers Point",
        "id": 7448475
      }
    },
    {
      "geometry": {
        "type": "Point",
        "coordinates": [
          0.566667,
          51.433333
        ]
      },
      "type": "Feature",
      "properties": {
        "hierarchy": [
          "tgn:7448478",
          "tgn:7002445",
          "tgn:1000003",
          "tgn:7026518",
          "tgn:7008591",
          "tgn:7029392"
        ],
        "placetype": [
          "aat:300008347"
        ],
        "name:en": "Sharnal Street",
        "id": 7448478
      }
    }
  ]
}
