{
  "geometry": {
    "type": "Point",
    "coordinates": [
      -91.3167,
      43.25
    ]
  },
  "type": "Feature",
  "properties": {
    "hierarchy": [
      "tgn:2034734",
      "tgn:2000563",
      "tgn:1000001",
      "tgn:7012149",
      "tgn:7007253",
      "tgn:7029392"
    ],
    "placetype": [
      "aat:300008347",
      "aat:300387210"
    ],
    "id": 2034734,
    "name:xx": "Elon"
  }
}
