{
  "geometry": {
    "type": "Point",
    "coordinates": [
      -86.7167,
      40.6333
    ]
  },
  "type": "Feature",
  "properties": {
    "hierarchy": [
      "tgn:2711221",
      "tgn:1000001",
      "tgn:1002236",
      "tgn:7012149",
      "tgn:7007252",
      "tgn:7029392"
    ],
    "placetype": [
      "aat:300008699"
    ],
    "id": 2711221,
    "name:xx": "Tannery Branch"
  }
}
