{
  "geometry": {
    "type": "Point",
    "coordinates": [
      -100.7333,
      29.8833
    ]
  },
  "type": "Feature",
  "properties": {
    "hierarchy": [
      "tgn:2557648",
      "tgn:1000001",
      "tgn:7012149",
      "tgn:2002088",
      "tgn:7007826",
      "tgn:7029392"
    ],
    "placetype": [
      "aat:300008761"
    ],
    "id": 2557648,
    "name:xx": "Old Ranch Draw"
  }
}
