{
  "geometry": {
    "type": "Point",
    "coordinates": [
      -97.6667,
      31.1667
    ]
  },
  "type": "Feature",
  "properties": {
    "hierarchy": [
      "tgn:2728049",
      "tgn:1000001",
      "tgn:1002174",
      "tgn:7012149",
      "tgn:7007826",
      "tgn:7029392"
    ],
    "placetype": [
      "aat:300008798"
    ],
    "id": 2728049,
    "name:xx": "Trapnell Point"
  }
}
