{
  "geometry": {
    "type": "Point",
    "coordinates": [
      -83.5167,
      32.2833
    ]
  },
  "type": "Feature",
  "properties": {
    "hierarchy": [
      "tgn:2133147",
      "tgn:1000001",
      "tgn:7012149",
      "tgn:2000407",
      "tgn:7007248",
      "tgn:7029392"
    ],
    "placetype": [
      "aat:300006191"
    ],
    "id": 2133147,
    "name:xx": "Anderson Lake"
  }
}
