{
  "geometry": {
    "type": "Point",
    "coordinates": [
      -74.5833,
      44.5667
    ]
  },
  "type": "Feature",
  "properties": {
    "hierarchy": [
      "tgn:2480216",
      "tgn:1000001",
      "tgn:7012149",
      "tgn:7007568",
      "tgn:7029392"
    ],
    "placetype": [
      "aat:300008699"
    ],
    "id": 2480216,
    "name:xx": "Lake Ozonia Outlet"
  }
}
