{
  "geometry": {
    "type": "Point",
    "coordinates": [
      45.355,
      39.858
    ]
  },
  "type": "Feature",
  "properties": {
    "hierarchy": [
      "tgn:7031890",
      "tgn:1000004",
      "tgn:7024040",
      "tgn:7006651",
      "tgn:7029392"
    ],
    "placetype": [
      "aat:300008347",
      "aat:300008375"
    ],
    "name:en": "Yeghegis",
    "id": 7031890,
    "name:xx": "Yekhegis"
  }
}
