{
  "geometry": {
    "type": "Point",
    "coordinates": [
      -123.4333,
      39.1833
    ]
  },
  "type": "Feature",
  "properties": {
    "hierarchy": [
      "tgn:2458565",
      "tgn:1000001",
      "tgn:7012149",
      "tgn:7007157",
      "tgn:2000185",
      "tgn:7029392"
    ],
    "placetype": [
      "aat:300008707"
    ],
    "id": 2458565,
    "name:xx": "Little North Fork Navarro River"
  }
}
