{
  "geometry": {
    "type": "Point",
    "coordinates": [
      -71.1333,
      42.9167
    ]
  },
  "type": "Feature",
  "properties": {
    "hierarchy": [
      "tgn:2454350",
      "tgn:1000001",
      "tgn:7014352",
      "tgn:7012149",
      "tgn:7007564",
      "tgn:7029392"
    ],
    "placetype": [
      "aat:300008680"
    ],
    "id": 2454350,
    "name:xx": "Little Cub Pond"
  }
}
