{
  "geometry": {
    "type": "Point",
    "coordinates": [
      -68.5333,
      44.35
    ]
  },
  "type": "Feature",
  "properties": {
    "hierarchy": [
      "tgn:2642058",
      "tgn:1000001",
      "tgn:2000922",
      "tgn:7012149",
      "tgn:7007515",
      "tgn:7029392"
    ],
    "placetype": [
      "aat:300008850"
    ],
    "id": 2642058,
    "name:xx": "Sand Point"
  }
}
