{
  "geometry": {
    "type": "Point",
    "coordinates": [
      -72.05,
      43.3833
    ]
  },
  "type": "Feature",
  "properties": {
    "hierarchy": [
      "tgn:1118280",
      "tgn:1000001",
      "tgn:7012149",
      "tgn:7007564",
      "tgn:7029392"
    ],
    "placetype": [
      "aat:300008680"
    ],
    "id": 1118280,
    "name:xx": "Sunapee Lake"
  }
}
