{
  "geometry": {
    "type": "Point",
    "coordinates": [
      33.768902,
      27.189091
    ]
  },
  "type": "Feature",
  "properties": {
    "hierarchy": [
      "tgn:7523527",
      "tgn:7001242",
      "tgn:7001311",
      "tgn:7016833",
      "tgn:7029392"
    ],
    "placetype": [
      "aat:300379998"
    ],
    "name:en": "Fāliq al Wa'r, Wādī",
    "id": 7523527
  }
}
