{
  "geometry": {
    "type": "Point",
    "coordinates": [
      -83.8667,
      35.2333
    ]
  },
  "type": "Feature",
  "properties": {
    "hierarchy": [
      "tgn:2487908",
      "tgn:1000001",
      "tgn:2001481",
      "tgn:7012149",
      "tgn:7007709",
      "tgn:7029392"
    ],
    "placetype": [
      "aat:300008706"
    ],
    "id": 2487908,
    "name:xx": "Left Fork Webb Creek"
  }
}
