{
  "geometry": {
    "type": "Point",
    "coordinates": [
      31.424965,
      29.643804
    ]
  },
  "type": "Feature",
  "properties": {
    "hierarchy": [
      "tgn:7541043",
      "tgn:7001242",
      "tgn:7016833",
      "tgn:7029392"
    ],
    "placetype": [
      "aat:300379998"
    ],
    "name:en": "Şakhrīyah, Wādī aş",
    "id": 7541043
  }
}
