{
  "geometry": {
    "type": "Point",
    "coordinates": [
      -83.9333,
      31.3333
    ]
  },
  "type": "Feature",
  "properties": {
    "hierarchy": [
      "tgn:2199933",
      "tgn:1000001",
      "tgn:7012149",
      "tgn:7007248",
      "tgn:7029392"
    ],
    "placetype": [
      "aat:300008699"
    ],
    "id": 2199933,
    "name:xx": "Brushy Branch"
  }
}
