{
  "geometry": {
    "type": "Point",
    "coordinates": [
      -77.1167,
      38.9667
    ]
  },
  "type": "Feature",
  "properties": {
    "hierarchy": [
      "tgn:2517164",
      "tgn:1000001",
      "tgn:7016104",
      "tgn:7012149",
      "tgn:7007516",
      "tgn:7029392"
    ],
    "placetype": [
      "aat:300008699"
    ],
    "id": 2517164,
    "name:xx": "Minnehaha Branch"
  }
}
