{
  "geometry": {
    "type": "Point",
    "coordinates": [
      -91.95,
      32.7667
    ]
  },
  "type": "Feature",
  "properties": {
    "hierarchy": [
      "tgn:2589684",
      "tgn:1000001",
      "tgn:7012149",
      "tgn:2000887",
      "tgn:7007256",
      "tgn:7029392"
    ],
    "placetype": [
      "aat:300008347"
    ],
    "id": 2589684,
    "name:xx": "Point Pleasant"
  }
}
