{
  "geometry": {
    "type": "Point",
    "coordinates": [
      -93.8833,
      46.4667
    ]
  },
  "type": "Feature",
  "properties": {
    "hierarchy": [
      "tgn:2054251",
      "tgn:1000001",
      "tgn:2001016",
      "tgn:7012149",
      "tgn:7007521",
      "tgn:7029392"
    ],
    "placetype": [
      "aat:300008347"
    ],
    "id": 2054251,
    "name:xx": "Deerwood"
  }
}
