{
  "geometry": {
    "type": "Point",
    "coordinates": [
      -76.9333,
      37.2333
    ]
  },
  "type": "Feature",
  "properties": {
    "hierarchy": [
      "tgn:2643567",
      "tgn:1000001",
      "tgn:1002257",
      "tgn:7012149",
      "tgn:7007919",
      "tgn:7029392"
    ],
    "placetype": [
      "aat:300008850"
    ],
    "id": 2643567,
    "name:xx": "Sandy Point"
  }
}
