{
  "geometry": {
    "type": "Point",
    "coordinates": [
      -106.65,
      41.5833
    ]
  },
  "type": "Feature",
  "properties": {
    "hierarchy": [
      "tgn:2658152",
      "tgn:1000001",
      "tgn:2002368",
      "tgn:7012149",
      "tgn:7007923",
      "tgn:7029392"
    ],
    "placetype": [
      "aat:300006075"
    ],
    "id": 2658152,
    "name:xx": "Shelton Allen Ditch"
  }
}
