{
  "type": "FeatureCollection",
  "features": [
    {
      "geometry": {
        "type": "Point",
        "coordinates": [
          -2.936742,
          43.270594
        ]
      },
      "type": "Feature",
      "properties": {
        "hierarchy": [
          "tgn:7339250",
          "tgn:7002849",
          "tgn:1000003",
          "tgn:7009604",
          "tgn:1000095",
          "tgn:7029392"
        ],
        "placetype": [
          "aat:300000745"
        ],
        "id": 7339250,
        "name:xx": "Deusto"
      }
    },
    {
      "geometry": {
        "type": "Point",
        "coordinates": [
          -6.083333,
          42.316667
        ]
      },
      "type": "Feature",
      "properties": {
        "hierarchy": [
          "tgn:7339251",
          "tgn:7002826",
          "tgn:7001158",
          "tgn:1000003",
          "tgn:1000095",
          "tgn:7029392"
        ],
        "placetype": [
          "aat:300008347"
        ],
        "id": 7339251,
        "name:xx": "Destriana"
      }
    },
    {
      "geometry": {
        "type": "Point",
        "coordinates": [
          -8,
          42.533333
        ]
      },
      "type": "Feature",
      "properties": {
        "hierarchy": [
          "tgn:7339252",
          "tgn:7002831",
          "tgn:1000003",
          "tgn:7002786",
          "tgn:1000095",
          "tgn:7029392"
        ],
        "placetype": [
          "aat:300008347"
        ],
        "id": 7339252,
        "name:xx": "Destierro"
      }
    },
    {
      "geometry": {
        "type": "Point",
        "coordinates": [
          -8.183333,
          42.15
        ]
      },
      "type": "Feature",
      "properties": {
        "hierarchy": [
          "tgn:7339253",
          "tgn:7002834",
          "tgn:1000003",
          "tgn:7002786",
          "tgn:1000095",
          "tgn:7029392"
        ],
        "placetype": [
          "aat:300008347"
        ],
        "id": 7339253,
        "name:xx": "Desteriz"
      }
    },
    {
      "geometry": {
        "type": "Point",
        "coordinates": [
          -3.466667,
          38.3
        ]
      },
      "type": "Feature",
      "properties": {
        "hierarchy": [
          "tgn:7339254",
          "tgn:7002758",
          "tgn:1001316",
          "tgn:1000003",
          "tgn:1000095",
          "tgn:7029392"
        ],
        "placetype": [
          "aat:300008699"
        ],
        "id": 7339254,
        "name:xx": "Despeñaperros, Río"
      }
    },
    {
      "geometry": {
        "type": "Point",
        "coordinates": [
          -3.5,
          38.4
        ]
      },
      "type": "Feature",
      "properties": {
        "hierarchy": [
          "tgn:7339255",
          "tgn:7002758",
          "tgn:1001316",
          "tgn:1000003",
          "tgn:1000095",
          "tgn:7029392"
        ],
        "placetype": [
          "aat:300259572"
        ],
        "id": 7339255,
        "name:xx": "Despeñaperros, Desfiladero de"
      }
    },
    {
      "geometry": {
        "type": "Point",
        "coordinates": [
          -4.833333,
          38.533333
        ]
      },
      "type": "Feature",
      "properties": {
        "hierarchy": [
          "tgn:7339256",
          "tgn:7002758",
          "tgn:7002817",
          "tgn:1000003",
          "tgn:1000095",
          "tgn:7029392"
        ],
        "placetype": [
          "aat:300008699"
        ],
        "id": 7339256,
        "name:xx": "Despeñadero, Arroyo del"
      }
    },
    {
      "geometry": {
        "type": "Point",
        "coordinates": [
          0.1,
          40.1
        ]
      },
      "type": "Feature",
      "properties": {
        "hierarchy": [
          "tgn:7339258",
          "tgn:7002815",
          "tgn:1000003",
          "tgn:7002793",
          "tgn:1000095",
          "tgn:7029392"
        ],
        "placetype": [
          "aat:300008777"
        ],
        "id": 7339258,
        "name:xx": "Desierto, Cordillera del"
      }
    },
    {
      "geometry": {
        "type": "Point",
        "coordinates": [
          -4.883333,
          43.4
        ]
      },
      "type": "Feature",
      "properties": {
        "hierarchy": [
          "tgn:7339259",
          "tgn:7008911",
          "tgn:1000003",
          "tgn:7002763",
          "tgn:1000095",
          "tgn:7029392"
        ],
        "placetype": [
          "aat:300008791"
        ],
        "id": 7339259,
        "name:xx": "Deshuracado, Islote"
      }
    }
  ]
}
