{
  "geometry": {
    "type": "Point",
    "coordinates": [
      -98.25,
      37.6333
    ]
  },
  "type": "Feature",
  "properties": {
    "hierarchy": [
      "tgn:2438204",
      "tgn:1000001",
      "tgn:7012149",
      "tgn:2000707",
      "tgn:7007254",
      "tgn:7029392"
    ],
    "placetype": [
      "aat:300006191"
    ],
    "id": 2438204,
    "name:xx": "Kingman County State Lake"
  }
}
