{
  "geometry": {
    "type": "Point",
    "coordinates": [
      -88.4333,
      45.9167
    ]
  },
  "type": "Feature",
  "properties": {
    "hierarchy": [
      "tgn:2269907",
      "tgn:1000001",
      "tgn:2002321",
      "tgn:7012149",
      "tgn:7007922",
      "tgn:7029392"
    ],
    "placetype": [
      "aat:300008680"
    ],
    "id": 2269907,
    "name:xx": "Cruiser Lake"
  }
}
