{
  "geometry": {
    "type": "Point",
    "coordinates": [
      -82.1167,
      36.5333
    ]
  },
  "type": "Feature",
  "properties": {
    "hierarchy": [
      "tgn:2460863",
      "tgn:1000001",
      "tgn:7012149",
      "tgn:2001918",
      "tgn:7007825",
      "tgn:7029392"
    ],
    "placetype": [
      "aat:300008706"
    ],
    "id": 2460863,
    "name:xx": "Little Sinking Creek"
  }
}
