{
  "geometry": {
    "type": "Point",
    "coordinates": [
      30.303907,
      29.050464
    ]
  },
  "type": "Feature",
  "properties": {
    "hierarchy": [
      "tgn:7538239",
      "tgn:7001242",
      "tgn:7001105",
      "tgn:7016833",
      "tgn:7029392"
    ],
    "placetype": [
      "aat:300008697"
    ],
    "name:en": "Rayyān al Qiblīyah, 'Ayn ar",
    "id": 7538239
  }
}
