{
  "geometry": {
    "type": "Point",
    "coordinates": [
      -116.05,
      45.4667
    ]
  },
  "type": "Feature",
  "properties": {
    "hierarchy": [
      "tgn:2760228",
      "tgn:1000001",
      "tgn:7012149",
      "tgn:2000476",
      "tgn:7007250",
      "tgn:7029392"
    ],
    "placetype": [
      "aat:300008706"
    ],
    "id": 2760228,
    "name:xx": "West Fork Robbins Creek"
  }
}
