{
  "geometry": {
    "type": "Point",
    "coordinates": [
      -84.1333,
      34.5833
    ]
  },
  "type": "Feature",
  "properties": {
    "hierarchy": [
      "tgn:2319487",
      "tgn:1000001",
      "tgn:7012149",
      "tgn:2000384",
      "tgn:7007248",
      "tgn:7029392"
    ],
    "placetype": [
      "aat:300006191"
    ],
    "id": 2319487,
    "name:xx": "Etowah 32"
  }
}
