{
  "geometry": {
    "type": "Point",
    "coordinates": [
      -72.85,
      -38.016667
    ]
  },
  "type": "Feature",
  "properties": {
    "hierarchy": [
      "tgn:7310457",
      "tgn:1001692",
      "tgn:1000049",
      "tgn:1000002",
      "tgn:7029392"
    ],
    "placetype": [
      "aat:300008777"
    ],
    "id": 7310457,
    "name:xx": "Motrenco, Alto"
  }
}
