{
  "geometry": {
    "type": "Point",
    "coordinates": [
      -70.0167,
      12.1667
    ]
  },
  "type": "Feature",
  "properties": {
    "hierarchy": [
      "tgn:1011180",
      "tgn:1001861",
      "tgn:1000002",
      "tgn:1000059",
      "tgn:7029392"
    ],
    "placetype": [
      "aat:300008850"
    ],
    "id": 1011180,
    "name:xx": "San Román, Cabo"
  }
}
