{
  "geometry": {
    "type": "Point",
    "coordinates": [
      -91.7333,
      38.8833
    ]
  },
  "type": "Feature",
  "properties": {
    "hierarchy": [
      "tgn:2581752",
      "tgn:1000001",
      "tgn:1002223",
      "tgn:7012149",
      "tgn:7007523",
      "tgn:7029392"
    ],
    "placetype": [
      "aat:300008706"
    ],
    "id": 2581752,
    "name:xx": "Pinch Creek"
  }
}
