{
  "geometry": {
    "type": "Point",
    "coordinates": [
      -92.9667,
      32.8333
    ]
  },
  "type": "Feature",
  "properties": {
    "hierarchy": [
      "tgn:2499137",
      "tgn:1000001",
      "tgn:2000867",
      "tgn:7012149",
      "tgn:7007256",
      "tgn:7029392"
    ],
    "placetype": [
      "aat:300008706"
    ],
    "id": 2499137,
    "name:xx": "McCasland Creek"
  }
}
