{
  "type": "FeatureCollection",
  "features": [
    {
      "geometry": {
        "type": "Point",
        "coordinates": [
          12.433333,
          48.033333
        ]
      },
      "type": "Feature",
      "properties": {
        "hierarchy": [
          "tgn:7066630",
          "tgn:7003669",
          "tgn:1000003",
          "tgn:7000084",
          "tgn:7029392"
        ],
        "placetype": [
          "aat:300008347"
        ],
        "id": 7066630,
        "name:xx": "Stockham"
      }
    },
    {
      "geometry": {
        "type": "Point",
        "coordinates": [
          12.3,
          47.733333
        ]
      },
      "type": "Feature",
      "properties": {
        "hierarchy": [
          "tgn:7066631",
          "tgn:7003669",
          "tgn:1000003",
          "tgn:7000084",
          "tgn:7029392"
        ],
        "placetype": [
          "aat:300008347"
        ],
        "id": 7066631,
        "name:xx": "Stockham"
      }
    },
    {
      "geometry": {
        "type": "Point",
        "coordinates": [
          12.4,
          48.2
        ]
      },
      "type": "Feature",
      "properties": {
        "hierarchy": [
          "tgn:7066632",
          "tgn:7003669",
          "tgn:1000003",
          "tgn:7000084",
          "tgn:7029392"
        ],
        "placetype": [
          "aat:300000206"
        ],
        "id": 7066632,
        "name:xx": "Stockham"
      }
    },
    {
      "geometry": {
        "type": "Point",
        "coordinates": [
          12.666667,
          48.066667
        ]
      },
      "type": "Feature",
      "properties": {
        "hierarchy": [
          "tgn:7066633",
          "tgn:7003669",
          "tgn:1000003",
          "tgn:7000084",
          "tgn:7029392"
        ],
        "placetype": [
          "aat:300000206"
        ],
        "id": 7066633,
        "name:xx": "Stockham"
      }
    },
    {
      "geometry": {
        "type": "Point",
        "coordinates": [
          12.766667,
          48
        ]
      },
      "type": "Feature",
      "properties": {
        "hierarchy": [
          "tgn:7066634",
          "tgn:7003669",
          "tgn:1000003",
          "tgn:7000084",
          "tgn:7029392"
        ],
        "placetype": [
          "aat:300000206"
        ],
        "id": 7066634,
        "name:xx": "Stockham"
      }
    },
    {
      "geometry": {
        "type": "Point",
        "coordinates": [
          12.866667,
          47.966667
        ]
      },
      "type": "Feature",
      "properties": {
        "hierarchy": [
          "tgn:7066635",
          "tgn:7003669",
          "tgn:1000003",
          "tgn:7000084",
          "tgn:7029392"
        ],
        "placetype": [
          "aat:300000206"
        ],
        "id": 7066635,
        "name:xx": "Stockham"
      }
    },
    {
      "geometry": {
        "type": "Point",
        "coordinates": [
          12.3,
          47.916667
        ]
      },
      "type": "Feature",
      "properties": {
        "hierarchy": [
          "tgn:7066636",
          "tgn:7003669",
          "tgn:1000003",
          "tgn:7000084",
          "tgn:7029392"
        ],
        "placetype": [
          "aat:300000206"
        ],
        "id": 7066636,
        "name:xx": "Stockham"
      }
    },
    {
      "geometry": {
        "type": "Point",
        "coordinates": [
          12.85,
          47.816667
        ]
      },
      "type": "Feature",
      "properties": {
        "hierarchy": [
          "tgn:7066637",
          "tgn:7003669",
          "tgn:1000003",
          "tgn:7000084",
          "tgn:7029392"
        ],
        "placetype": [
          "aat:300000206"
        ],
        "id": 7066637,
        "name:xx": "Stockham"
      }
    },
    {
      "geometry": {
        "type": "Point",
        "coordinates": [
          9.25,
          49.9
        ]
      },
      "type": "Feature",
      "properties": {
        "hierarchy": [
          "tgn:7066638",
          "tgn:7003669",
          "tgn:1000003",
          "tgn:7000084",
          "tgn:7029392"
        ],
        "placetype": [
          "aat:300008773"
        ],
        "id": 7066638,
        "name:xx": "Stock Grund"
      }
    },
    {
      "geometry": {
        "type": "Point",
        "coordinates": [
          9.866667,
          49.983333
        ]
      },
      "type": "Feature",
      "properties": {
        "hierarchy": [
          "tgn:7066639",
          "tgn:7003669",
          "tgn:1000003",
          "tgn:7000084",
          "tgn:7029392"
        ],
        "placetype": [
          "aat:300008777"
        ],
        "id": 7066639,
        "name:xx": "Stockfeldhöhe"
      }
    }
  ]
}
