{
  "geometry": {
    "type": "Point",
    "coordinates": [
      -76.75,
      39.4333
    ]
  },
  "type": "Feature",
  "properties": {
    "hierarchy": [
      "tgn:2227623",
      "tgn:7016099",
      "tgn:1000001",
      "tgn:7012149",
      "tgn:7007516",
      "tgn:7029392"
    ],
    "placetype": [
      "aat:300386845"
    ],
    "id": 2227623,
    "name:xx": "Caves, The"
  }
}
