{
  "geometry": {
    "type": "Point",
    "coordinates": [
      -115.15,
      47.4667
    ]
  },
  "type": "Feature",
  "properties": {
    "hierarchy": [
      "tgn:2310913",
      "tgn:1000001",
      "tgn:7012149",
      "tgn:2001304",
      "tgn:7007524",
      "tgn:7029392"
    ],
    "placetype": [
      "aat:300008706"
    ],
    "id": 2310913,
    "name:xx": "Eddy Creek"
  }
}
