{
  "geometry": {
    "type": "Point",
    "coordinates": [
      -95.9333,
      36.4833
    ]
  },
  "type": "Feature",
  "properties": {
    "hierarchy": [
      "tgn:2666847",
      "tgn:1000001",
      "tgn:7012149",
      "tgn:7007707",
      "tgn:7029392"
    ],
    "placetype": [
      "aat:300008706"
    ],
    "id": 2666847,
    "name:xx": "Skalall Creek"
  }
}
