{
  "geometry": {
    "type": "Point",
    "coordinates": [
      -81.7833,
      37.2833
    ]
  },
  "type": "Feature",
  "properties": {
    "hierarchy": [
      "tgn:2392465",
      "tgn:1000001",
      "tgn:7012149",
      "tgn:2002274",
      "tgn:7013961",
      "tgn:7029392"
    ],
    "placetype": [
      "aat:300008699"
    ],
    "id": 2392465,
    "name:xx": "Hite Fork"
  }
}
