{
  "geometry": {
    "type": "Point",
    "coordinates": [
      139.1167,
      36.2167
    ]
  },
  "type": "Feature",
  "properties": {
    "hierarchy": [
      "tgn:1080389",
      "tgn:1000004",
      "tgn:7000894",
      "tgn:7016797",
      "tgn:1000120",
      "tgn:7029392"
    ],
    "placetype": [
      "aat:300008347"
    ],
    "id": 1080389,
    "name:xx": "Kamikawa"
  }
}
