{
  "geometry": {
    "type": "Point",
    "coordinates": [
      -99.9333,
      29.1167
    ]
  },
  "type": "Feature",
  "properties": {
    "hierarchy": [
      "tgn:2667137",
      "tgn:1000001",
      "tgn:7012149",
      "tgn:2002087",
      "tgn:7007826",
      "tgn:7029392"
    ],
    "placetype": [
      "aat:300006191"
    ],
    "id": 2667137,
    "name:xx": "Skiffa Tank"
  }
}
