{
  "geometry": {
    "type": "Point",
    "coordinates": [
      11.8667,
      45.85
    ]
  },
  "type": "Feature",
  "properties": {
    "hierarchy": [
      "tgn:1044115",
      "tgn:7002996",
      "tgn:1000003",
      "tgn:7002997",
      "tgn:1000080",
      "tgn:7029392"
    ],
    "placetype": [
      "aat:300008347"
    ],
    "id": 1044115,
    "name:xx": "Cavaso del Tomba"
  }
}
