{
  "type": "FeatureCollection",
  "features": [
    {
      "geometry": {
        "type": "Point",
        "coordinates": [
          10.633333,
          48.766667
        ]
      },
      "type": "Feature",
      "properties": {
        "hierarchy": [
          "tgn:7107140",
          "tgn:7003669",
          "tgn:1000003",
          "tgn:7000084",
          "tgn:7029392"
        ],
        "placetype": [
          "aat:300008777"
        ],
        "id": 7107140,
        "name:xx": "Schellenberg"
      }
    },
    {
      "geometry": {
        "type": "Point",
        "coordinates": [
          10.783333,
          48.716667
        ]
      },
      "type": "Feature",
      "properties": {
        "hierarchy": [
          "tgn:7107141",
          "tgn:7003669",
          "tgn:1000003",
          "tgn:7000084",
          "tgn:7029392"
        ],
        "placetype": [
          "aat:300008777"
        ],
        "id": 7107141,
        "name:xx": "Schellenberg"
      }
    },
    {
      "geometry": {
        "type": "Point",
        "coordinates": [
          9.883333,
          48.316667
        ]
      },
      "type": "Feature",
      "properties": {
        "hierarchy": [
          "tgn:7107142",
          "tgn:7003692",
          "tgn:1000003",
          "tgn:7000084",
          "tgn:7029392"
        ],
        "placetype": [
          "aat:300008777"
        ],
        "id": 7107142,
        "name:xx": "Schellenberg"
      }
    },
    {
      "geometry": {
        "type": "Point",
        "coordinates": [
          11.083333,
          48.266667
        ]
      },
      "type": "Feature",
      "properties": {
        "hierarchy": [
          "tgn:7107143",
          "tgn:7003669",
          "tgn:1000003",
          "tgn:7000084",
          "tgn:7029392"
        ],
        "placetype": [
          "aat:300008777"
        ],
        "id": 7107143,
        "name:xx": "Schellen Berg"
      }
    },
    {
      "geometry": {
        "type": "Point",
        "coordinates": [
          11.316667,
          48.116667
        ]
      },
      "type": "Feature",
      "properties": {
        "hierarchy": [
          "tgn:7107144",
          "tgn:7003669",
          "tgn:1000003",
          "tgn:7000084",
          "tgn:7029392"
        ],
        "placetype": [
          "aat:300008777"
        ],
        "id": 7107144,
        "name:xx": "Schellen Berg"
      }
    },
    {
      "geometry": {
        "type": "Point",
        "coordinates": [
          11.033333,
          48.116667
        ]
      },
      "type": "Feature",
      "properties": {
        "hierarchy": [
          "tgn:7107145",
          "tgn:7003669",
          "tgn:1000003",
          "tgn:7000084",
          "tgn:7029392"
        ],
        "placetype": [
          "aat:300008777"
        ],
        "id": 7107145,
        "name:xx": "Schellenberg"
      }
    },
    {
      "geometry": {
        "type": "Point",
        "coordinates": [
          10.583333,
          48.116667
        ]
      },
      "type": "Feature",
      "properties": {
        "hierarchy": [
          "tgn:7107146",
          "tgn:7003669",
          "tgn:1000003",
          "tgn:7000084",
          "tgn:7029392"
        ],
        "placetype": [
          "aat:300008777"
        ],
        "id": 7107146,
        "name:xx": "Schellenberg"
      }
    },
    {
      "geometry": {
        "type": "Point",
        "coordinates": [
          10.383333,
          48.116667
        ]
      },
      "type": "Feature",
      "properties": {
        "hierarchy": [
          "tgn:7107147",
          "tgn:7003669",
          "tgn:1000003",
          "tgn:7000084",
          "tgn:7029392"
        ],
        "placetype": [
          "aat:300008777"
        ],
        "id": 7107147,
        "name:xx": "Schellenberg"
      }
    },
    {
      "geometry": {
        "type": "Point",
        "coordinates": [
          9.566667,
          48.016667
        ]
      },
      "type": "Feature",
      "properties": {
        "hierarchy": [
          "tgn:7107148",
          "tgn:7003692",
          "tgn:1000003",
          "tgn:7000084",
          "tgn:7029392"
        ],
        "placetype": [
          "aat:300008777"
        ],
        "id": 7107148,
        "name:xx": "Schellenberg"
      }
    },
    {
      "geometry": {
        "type": "Point",
        "coordinates": [
          8.45,
          47.95
        ]
      },
      "type": "Feature",
      "properties": {
        "hierarchy": [
          "tgn:7107149",
          "tgn:7003692",
          "tgn:1000003",
          "tgn:7000084",
          "tgn:7029392"
        ],
        "placetype": [
          "aat:300008777"
        ],
        "id": 7107149,
        "name:xx": "Schellenberg"
      }
    }
  ]
}
