{
  "geometry": {
    "type": "Point",
    "coordinates": [
      -122.35,
      44.0167
    ]
  },
  "type": "Feature",
  "properties": {
    "hierarchy": [
      "tgn:2384071",
      "tgn:1000001",
      "tgn:7012149",
      "tgn:2001716",
      "tgn:7007708",
      "tgn:7029392"
    ],
    "placetype": [
      "aat:300008798"
    ],
    "id": 2384071,
    "name:xx": "Hehe Mountain"
  }
}
