{
  "geometry": {
    "type": "Point",
    "coordinates": [
      -8.581,
      39.257
    ]
  },
  "type": "Feature",
  "properties": {
    "hierarchy": [
      "tgn:1049684",
      "tgn:1000003",
      "tgn:1000926",
      "tgn:1000090",
      "tgn:7029392"
    ],
    "placetype": [
      "aat:300008347"
    ],
    "id": 1049684,
    "name:xx": "Alpiarça"
  }
}
