{
  "geometry": {
    "type": "Point",
    "coordinates": [
      -94.9667,
      33.0333
    ]
  },
  "type": "Feature",
  "properties": {
    "hierarchy": [
      "tgn:2477927",
      "tgn:1000001",
      "tgn:7012149",
      "tgn:1002230",
      "tgn:7007826",
      "tgn:7029392"
    ],
    "placetype": [
      "aat:300008347"
    ],
    "id": 2477927,
    "name:xx": "Macedonia"
  }
}
