{
  "geometry": {
    "type": "Point",
    "coordinates": [
      -91.7167,
      43.4167
    ]
  },
  "type": "Feature",
  "properties": {
    "hierarchy": [
      "tgn:2464027",
      "tgn:1000001",
      "tgn:7012149",
      "tgn:2000656",
      "tgn:7007253",
      "tgn:7029392"
    ],
    "placetype": [
      "aat:300008347"
    ],
    "id": 2464027,
    "name:xx": "Locust"
  }
}
