{
  "geometry": {
    "type": "Point",
    "coordinates": [
      -110.05,
      34.2167
    ]
  },
  "type": "Feature",
  "properties": {
    "hierarchy": [
      "tgn:2392538",
      "tgn:1000001",
      "tgn:7006451",
      "tgn:7012149",
      "tgn:2000099",
      "tgn:7029392"
    ],
    "placetype": [
      "aat:300006191"
    ],
    "id": 2392538,
    "name:xx": "Hiway Tank"
  }
}
