{
  "geometry": {
    "type": "Point",
    "coordinates": [
      -93.2167,
      40.6667
    ]
  },
  "type": "Feature",
  "properties": {
    "hierarchy": [
      "tgn:7020868",
      "tgn:1000001",
      "tgn:7012149",
      "tgn:7029392"
    ],
    "placetype": [
      "aat:300008706"
    ],
    "id": 7020868,
    "name:xx": "Locust Creek"
  }
}
