{
  "type": "FeatureCollection",
  "features": [
    {
      "geometry": {
        "type": "Point",
        "coordinates": [
          31.24906,
          30.3523
        ]
      },
      "type": "Feature",
      "properties": {
        "hierarchy": [
          "tgn:7531020",
          "tgn:7001242",
          "tgn:7016833",
          "tgn:1001092",
          "tgn:7029392"
        ],
        "placetype": [
          "aat:300008347"
        ],
        "id": 7531020,
        "name:xx": "'Izbat ash Sharāqiwah"
      }
    },
    {
      "geometry": {
        "type": "Point",
        "coordinates": [
          31.235684,
          30.372158
        ]
      },
      "type": "Feature",
      "properties": {
        "hierarchy": [
          "tgn:7531021",
          "tgn:7001242",
          "tgn:7016833",
          "tgn:1001092",
          "tgn:7029392"
        ],
        "placetype": [
          "aat:300008347"
        ],
        "id": 7531021,
        "name:xx": "'Izbat Sa'd Mīkhā'īl"
      }
    },
    {
      "geometry": {
        "type": "Point",
        "coordinates": [
          31.130454,
          30.078124
        ]
      },
      "type": "Feature",
      "properties": {
        "hierarchy": [
          "tgn:7531022",
          "tgn:7001242",
          "tgn:7016833",
          "tgn:7029392"
        ],
        "placetype": [
          "aat:300006075"
        ],
        "id": 7531022,
        "name:xx": "Tur'at Birak al Khiyām"
      }
    },
    {
      "geometry": {
        "type": "Point",
        "coordinates": [
          31.096513,
          30.053214
        ]
      },
      "type": "Feature",
      "properties": {
        "hierarchy": [
          "tgn:7531023",
          "tgn:7001242",
          "tgn:7016833",
          "tgn:7029392"
        ],
        "placetype": [
          "aat:300006075"
        ],
        "id": 7531023,
        "name:xx": "Tur'at Nāhiyā"
      }
    },
    {
      "geometry": {
        "type": "Point",
        "coordinates": [
          31.207621,
          30.363264
        ]
      },
      "type": "Feature",
      "properties": {
        "hierarchy": [
          "tgn:7531024",
          "tgn:7001242",
          "tgn:7016833",
          "tgn:1001092",
          "tgn:7029392"
        ],
        "placetype": [
          "aat:300008347"
        ],
        "id": 7531024,
        "name:xx": "'Izbat 'Abd al Qādir Mufriḩ"
      }
    },
    {
      "geometry": {
        "type": "Point",
        "coordinates": [
          31.213206,
          30.368849
        ]
      },
      "type": "Feature",
      "properties": {
        "hierarchy": [
          "tgn:7531025",
          "tgn:7001242",
          "tgn:7016833",
          "tgn:1001092",
          "tgn:7029392"
        ],
        "placetype": [
          "aat:300008347"
        ],
        "id": 7531025,
        "name:xx": "'Izbat Şābir"
      }
    },
    {
      "geometry": {
        "type": "Point",
        "coordinates": [
          31.206173,
          30.377192
        ]
      },
      "type": "Feature",
      "properties": {
        "hierarchy": [
          "tgn:7531026",
          "tgn:7001242",
          "tgn:7016833",
          "tgn:1001092",
          "tgn:7029392"
        ],
        "placetype": [
          "aat:300008347"
        ],
        "id": 7531026,
        "name:xx": "'Izbat 'Abd ar Raḩmān Surūr"
      }
    },
    {
      "geometry": {
        "type": "Point",
        "coordinates": [
          31.228002,
          30.376183
        ]
      },
      "type": "Feature",
      "properties": {
        "hierarchy": [
          "tgn:7531027",
          "tgn:7001242",
          "tgn:7016833",
          "tgn:1001092",
          "tgn:7029392"
        ],
        "placetype": [
          "aat:300008347"
        ],
        "id": 7531027,
        "name:xx": "'Izbat Ḩawḑ Baţāţah"
      }
    },
    {
      "geometry": {
        "type": "Point",
        "coordinates": [
          31.241345,
          30.383726
        ]
      },
      "type": "Feature",
      "properties": {
        "hierarchy": [
          "tgn:7531028",
          "tgn:7001242",
          "tgn:7016833",
          "tgn:1001092",
          "tgn:7029392"
        ],
        "placetype": [
          "aat:300008347"
        ],
        "id": 7531028,
        "name:xx": "'Izbat 'Abd al Ḩamīd al Mahdī"
      }
    },
    {
      "geometry": {
        "type": "Point",
        "coordinates": [
          31.234484,
          30.382968
        ]
      },
      "type": "Feature",
      "properties": {
        "hierarchy": [
          "tgn:7531029",
          "tgn:7001242",
          "tgn:7016833",
          "tgn:1001092",
          "tgn:7029392"
        ],
        "placetype": [
          "aat:300008347"
        ],
        "id": 7531029,
        "name:xx": "'Izbat ad Dayrī"
      }
    }
  ]
}
