{
  "geometry": {
    "type": "Point",
    "coordinates": [
      118.7333,
      39.05
    ]
  },
  "type": "Feature",
  "properties": {
    "hierarchy": [
      "tgn:1009119",
      "tgn:1000004",
      "tgn:7002077",
      "tgn:1000111",
      "tgn:7029392"
    ],
    "placetype": [
      "aat:300008791"
    ],
    "id": 1009119,
    "name:xx": "Shaleitian Dao"
  }
}
