{
  "geometry": {
    "type": "Point",
    "coordinates": [
      150.0333,
      -35.4333
    ]
  },
  "type": "Feature",
  "properties": {
    "hierarchy": [
      "tgn:1101435",
      "tgn:7000490",
      "tgn:1000006",
      "tgn:7001828",
      "tgn:7029392"
    ],
    "placetype": [
      "aat:300008189"
    ],
    "id": 1101435,
    "name:xx": "Budawang National Park"
  }
}
