{
  "geometry": {
    "type": "Point",
    "coordinates": [
      -81.6167,
      36.9667
    ]
  },
  "type": "Feature",
  "properties": {
    "hierarchy": [
      "tgn:2114559",
      "tgn:1000001",
      "tgn:7012149",
      "tgn:2002192",
      "tgn:7007919",
      "tgn:7029392"
    ],
    "placetype": [
      "aat:300008347"
    ],
    "id": 2114559,
    "name:xx": "Tannersville"
  }
}
