{
  "geometry": {
    "type": "Point",
    "coordinates": [
      -119.5333,
      36.4833
    ]
  },
  "type": "Feature",
  "properties": {
    "hierarchy": [
      "tgn:2249268",
      "tgn:1000001",
      "tgn:7012149",
      "tgn:7007157",
      "tgn:7029392"
    ],
    "placetype": [
      "aat:300008699"
    ],
    "id": 2249268,
    "name:xx": "Cole Slough"
  }
}
