{
  "geometry": {
    "type": "Point",
    "coordinates": [
      -59.1667,
      -32.3333
    ]
  },
  "type": "Feature",
  "properties": {
    "hierarchy": [
      "tgn:1019954",
      "tgn:7006477",
      "tgn:1001237",
      "tgn:1000002",
      "tgn:7029392"
    ],
    "placetype": [
      "aat:300008347"
    ],
    "id": 1019954,
    "name:xx": "Rosario del Tala"
  }
}
