{
  "geometry": {
    "type": "Point",
    "coordinates": [
      -91.0167,
      36.8833
    ]
  },
  "type": "Feature",
  "properties": {
    "hierarchy": [
      "tgn:2447633",
      "tgn:1000001",
      "tgn:2001181",
      "tgn:7012149",
      "tgn:7007523",
      "tgn:7029392"
    ],
    "placetype": [
      "aat:300008761"
    ],
    "id": 2447633,
    "name:xx": "Lick Log Hollow"
  }
}
