{
  "type": "FeatureCollection",
  "features": [
    {
      "geometry": {
        "type": "Point",
        "coordinates": [
          9.366667,
          41.3
        ]
      },
      "type": "Feature",
      "properties": {
        "hierarchy": [
          "tgn:7051590",
          "tgn:7015163",
          "tgn:1000003",
          "tgn:7003121",
          "tgn:1000080",
          "tgn:7029392"
        ],
        "placetype": [
          "aat:300132317"
        ],
        "id": 7051590,
        "name:xx": "Muro, Cala"
      }
    },
    {
      "geometry": {
        "type": "Point",
        "coordinates": [
          11.916667,
          43.466667
        ]
      },
      "type": "Feature",
      "properties": {
        "hierarchy": [
          "tgn:7051591",
          "tgn:7003162",
          "tgn:1000003",
          "tgn:7009760",
          "tgn:1000080",
          "tgn:7029392"
        ],
        "placetype": [
          "aat:300008347"
        ],
        "id": 7051591,
        "name:xx": "Muro"
      }
    },
    {
      "geometry": {
        "type": "Point",
        "coordinates": [
          11.4,
          43.116667
        ]
      },
      "type": "Feature",
      "properties": {
        "hierarchy": [
          "tgn:7051592",
          "tgn:7003168",
          "tgn:1000003",
          "tgn:7009760",
          "tgn:1000080",
          "tgn:7029392"
        ],
        "placetype": [
          "aat:300007783"
        ],
        "id": 7051592,
        "name:xx": "Stazione di Murlo"
      }
    },
    {
      "geometry": {
        "type": "Point",
        "coordinates": [
          8.15,
          44.316667
        ]
      },
      "type": "Feature",
      "properties": {
        "hierarchy": [
          "tgn:7051595",
          "tgn:1000003",
          "tgn:7003236",
          "tgn:7003144",
          "tgn:1000080",
          "tgn:7029392"
        ],
        "placetype": [
          "aat:300008347"
        ],
        "id": 7051595,
        "name:xx": "Murialdo"
      }
    },
    {
      "geometry": {
        "type": "Point",
        "coordinates": [
          7.716667,
          45.433333
        ]
      },
      "type": "Feature",
      "properties": {
        "hierarchy": [
          "tgn:7051596",
          "tgn:7003154",
          "tgn:1000003",
          "tgn:7003120",
          "tgn:1000080",
          "tgn:7029392"
        ],
        "placetype": [
          "aat:300008347"
        ],
        "id": 7051596,
        "name:xx": "Muriaglio"
      }
    },
    {
      "geometry": {
        "type": "Point",
        "coordinates": [
          11.4,
          42.733333
        ]
      },
      "type": "Feature",
      "properties": {
        "hierarchy": [
          "tgn:7051598",
          "tgn:1003460",
          "tgn:1000003",
          "tgn:7009760",
          "tgn:1000080",
          "tgn:7029392"
        ],
        "placetype": [
          "aat:300008347"
        ],
        "id": 7051598,
        "name:xx": "Murci"
      }
    },
    {
      "geometry": {
        "type": "Point",
        "coordinates": [
          7.65,
          44.483333
        ]
      },
      "type": "Feature",
      "properties": {
        "hierarchy": [
          "tgn:7051599",
          "tgn:7005126",
          "tgn:1000003",
          "tgn:7003120",
          "tgn:1000080",
          "tgn:7029392"
        ],
        "placetype": [
          "aat:300008347"
        ],
        "id": 7051599,
        "name:xx": "Murazzo"
      }
    }
  ]
}
