{
  "geometry": {
    "type": "Point",
    "coordinates": [
      30.75,
      50.5167
    ]
  },
  "type": "Feature",
  "properties": {
    "hierarchy": [
      "tgn:1053093",
      "tgn:1000003",
      "tgn:7011661",
      "tgn:7006660",
      "tgn:7029392"
    ],
    "placetype": [
      "aat:300008347"
    ],
    "id": 1053093,
    "name:xx": "Brovary"
  }
}
