{
  "geometry": {
    "type": "Point",
    "coordinates": [
      -87.35,
      35.2333
    ]
  },
  "type": "Feature",
  "properties": {
    "hierarchy": [
      "tgn:2398797",
      "tgn:1000001",
      "tgn:7012149",
      "tgn:2001886",
      "tgn:7007825",
      "tgn:7029392"
    ],
    "placetype": [
      "aat:300008697"
    ],
    "id": 2398797,
    "name:xx": "Hope Spring"
  }
}
