{
  "geometry": {
    "type": "Point",
    "coordinates": [
      -116.5833,
      47.4667
    ]
  },
  "type": "Feature",
  "properties": {
    "hierarchy": [
      "tgn:2606194",
      "tgn:1000001",
      "tgn:7012149",
      "tgn:2000479",
      "tgn:7007250",
      "tgn:7029392"
    ],
    "placetype": [
      "aat:300008798"
    ],
    "id": 2606194,
    "name:xx": "Rainy Hill"
  }
}
