{
  "geometry": {
    "type": "Point",
    "coordinates": [
      -113.0167,
      35.1833
    ]
  },
  "type": "Feature",
  "properties": {
    "hierarchy": [
      "tgn:2197243",
      "tgn:1000001",
      "tgn:7006451",
      "tgn:7012149",
      "tgn:2000103",
      "tgn:7029392"
    ],
    "placetype": [
      "aat:300006191"
    ],
    "id": 2197243,
    "name:xx": "Brown Basin Tank"
  }
}
