{
  "geometry": {
    "type": "Point",
    "coordinates": [
      78.060198,
      23.969139
    ]
  },
  "type": "Feature",
  "properties": {
    "hierarchy": [
      "tgn:7577807",
      "tgn:1000004",
      "tgn:7000198",
      "tgn:1001894",
      "tgn:7029392"
    ],
    "placetype": [
      "aat:300008347"
    ],
    "name:en": "Kulhār",
    "id": 7577807
  }
}
