{
  "type": "FeatureCollection",
  "features": [
    {
      "geometry": {
        "type": "Point",
        "coordinates": [
          -75,
          9
        ]
      },
      "type": "Feature",
      "properties": {
        "hierarchy": [
          "tgn:1000771",
          "tgn:1000050",
          "tgn:1000002",
          "tgn:7029392"
        ],
        "placetype": [
          "aat:300387064",
          "aat:300000772"
        ],
        "id": 1000771,
        "name:xx": "Sucre"
      }
    },
    {
      "geometry": {
        "type": "Point",
        "coordinates": [
          -3.3333,
          10.75
        ]
      },
      "type": "Feature",
      "properties": {
        "hierarchy": [
          "tgn:1000772",
          "tgn:7001242",
          "tgn:1000208",
          "tgn:7029392"
        ],
        "placetype": [
          "aat:300387064",
          "aat:300182722"
        ],
        "id": 1000772,
        "name:xx": "Sud-Ouest"
      }
    },
    {
      "geometry": {
        "type": "Point",
        "coordinates": [
          -70.3333,
          -17.6667
        ]
      },
      "type": "Feature",
      "properties": {
        "hierarchy": [
          "tgn:1000773",
          "tgn:1000002",
          "tgn:1000056",
          "tgn:7029392"
        ],
        "placetype": [
          "aat:300387064",
          "aat:300000772",
          "aat:300236112"
        ],
        "id": 1000773,
        "name:xx": "Tacna"
      }
    },
    {
      "geometry": {
        "type": "Point",
        "coordinates": [
          0.8333,
          16
        ]
      },
      "type": "Feature",
      "properties": {
        "hierarchy": [
          "tgn:1000774",
          "tgn:7001242",
          "tgn:1000181",
          "tgn:7029392"
        ],
        "placetype": [
          "aat:300387064",
          "aat:300000772"
        ],
        "id": 1000774,
        "name:xx": "Tahoua"
      }
    },
    {
      "geometry": {
        "type": "Point",
        "coordinates": [
          4.666,
          23.75
        ]
      },
      "type": "Feature",
      "properties": {
        "hierarchy": [
          "tgn:1000775",
          "tgn:7001242",
          "tgn:7016752",
          "tgn:7029392"
        ],
        "placetype": [
          "aat:300387064",
          "aat:300000772"
        ],
        "id": 1000775,
        "name:xx": "Tamanghasset"
      }
    },
    {
      "geometry": {
        "type": "Point",
        "coordinates": [
          -64,
          -21.5
        ]
      },
      "type": "Feature",
      "properties": {
        "hierarchy": [
          "tgn:1000776",
          "tgn:1000046",
          "tgn:1000002",
          "tgn:7029392"
        ],
        "placetype": [
          "aat:300387064",
          "aat:300000772"
        ],
        "id": 1000776,
        "name:xx": "Tarija"
      }
    },
    {
      "geometry": {
        "type": "Point",
        "coordinates": [
          7.833,
          35
        ]
      },
      "type": "Feature",
      "properties": {
        "hierarchy": [
          "tgn:1000779",
          "tgn:7001242",
          "tgn:7016752",
          "tgn:7029392"
        ],
        "placetype": [
          "aat:300387064",
          "aat:300000772"
        ],
        "id": 1000779,
        "name:xx": "Tébessa"
      }
    }
  ]
}
