{
  "geometry": {
    "type": "Point",
    "coordinates": [
      -110.7833,
      47.0667
    ]
  },
  "type": "Feature",
  "properties": {
    "hierarchy": [
      "tgn:2298381",
      "tgn:1000001",
      "tgn:2001266",
      "tgn:7012149",
      "tgn:7007524",
      "tgn:7029392"
    ],
    "placetype": [
      "aat:300266640"
    ],
    "id": 2298381,
    "name:xx": "Dry Ridge"
  }
}
