{
  "type": "FeatureCollection",
  "features": [
    {
      "geometry": {
        "type": "Point",
        "coordinates": [
          -69.4833,
          43.8333
        ]
      },
      "type": "Feature",
      "properties": {
        "hierarchy": [
          "tgn:2600860",
          "tgn:1000001",
          "tgn:2000925",
          "tgn:7012149",
          "tgn:7007515",
          "tgn:7029392"
        ],
        "placetype": [
          "aat:300132348"
        ],
        "id": 2600860,
        "name:xx": "Pumpkin Cove Ledge"
      }
    },
    {
      "geometry": {
        "type": "Point",
        "coordinates": [
          -85.9833,
          31.1
        ]
      },
      "type": "Feature",
      "properties": {
        "hierarchy": [
          "tgn:2600861",
          "tgn:7002659",
          "tgn:1000001",
          "tgn:7012149",
          "tgn:2000030",
          "tgn:7029392"
        ],
        "placetype": [
          "aat:300008706"
        ],
        "id": 2600861,
        "name:xx": "Pumpkin Creek"
      }
    },
    {
      "geometry": {
        "type": "Point",
        "coordinates": [
          -87.4,
          33.7833
        ]
      },
      "type": "Feature",
      "properties": {
        "hierarchy": [
          "tgn:2600862",
          "tgn:7002659",
          "tgn:1000001",
          "tgn:7012149",
          "tgn:2000063",
          "tgn:7029392"
        ],
        "placetype": [
          "aat:300008706"
        ],
        "id": 2600862,
        "name:xx": "Pumpkin Creek"
      }
    },
    {
      "geometry": {
        "type": "Point",
        "coordinates": [
          -91.7333,
          35.9333
        ]
      },
      "type": "Feature",
      "properties": {
        "hierarchy": [
          "tgn:2600863",
          "tgn:1000001",
          "tgn:7016172",
          "tgn:7012149",
          "tgn:7029392"
        ],
        "placetype": [
          "aat:300008706"
        ],
        "id": 2600863,
        "name:xx": "Pumpkin Creek"
      }
    },
    {
      "geometry": {
        "type": "Point",
        "coordinates": [
          -82.6333,
          28.7167
        ]
      },
      "type": "Feature",
      "properties": {
        "hierarchy": [
          "tgn:2600864",
          "tgn:1000001",
          "tgn:1002269",
          "tgn:7012149",
          "tgn:7007240",
          "tgn:7029392"
        ],
        "placetype": [
          "aat:300008706"
        ],
        "id": 2600864,
        "name:xx": "Pumpkin Creek"
      }
    },
    {
      "geometry": {
        "type": "Point",
        "coordinates": [
          -85.1833,
          30.5667
        ]
      },
      "type": "Feature",
      "properties": {
        "hierarchy": [
          "tgn:2600865",
          "tgn:1000001",
          "tgn:7012149",
          "tgn:7007240",
          "tgn:7029392"
        ],
        "placetype": [
          "aat:300008706"
        ],
        "id": 2600865,
        "name:xx": "Pumpkin Creek"
      }
    },
    {
      "geometry": {
        "type": "Point",
        "coordinates": [
          -84.7333,
          31.8833
        ]
      },
      "type": "Feature",
      "properties": {
        "hierarchy": [
          "tgn:2600866",
          "tgn:1000001",
          "tgn:7012149",
          "tgn:2000411",
          "tgn:7007248",
          "tgn:7029392"
        ],
        "placetype": [
          "aat:300008706"
        ],
        "id": 2600866,
        "name:xx": "Pumpkin Creek"
      }
    },
    {
      "geometry": {
        "type": "Point",
        "coordinates": [
          -116.05,
          44.0167
        ]
      },
      "type": "Feature",
      "properties": {
        "hierarchy": [
          "tgn:2600867",
          "tgn:1000001",
          "tgn:2000459",
          "tgn:7012149",
          "tgn:7007250",
          "tgn:7029392"
        ],
        "placetype": [
          "aat:300008706"
        ],
        "id": 2600867,
        "name:xx": "Pumpkin Creek"
      }
    },
    {
      "geometry": {
        "type": "Point",
        "coordinates": [
          -90.7333,
          42.0667
        ]
      },
      "type": "Feature",
      "properties": {
        "hierarchy": [
          "tgn:2600868",
          "tgn:1000001",
          "tgn:7012149",
          "tgn:7007253",
          "tgn:7029392"
        ],
        "placetype": [
          "aat:300008706"
        ],
        "id": 2600868,
        "name:xx": "Pumpkin Creek"
      }
    },
    {
      "geometry": {
        "type": "Point",
        "coordinates": [
          -95.3833,
          37.2833
        ]
      },
      "type": "Feature",
      "properties": {
        "hierarchy": [
          "tgn:2600869",
          "tgn:1000001",
          "tgn:7012149",
          "tgn:7007254",
          "tgn:7029392"
        ],
        "placetype": [
          "aat:300008706"
        ],
        "id": 2600869,
        "name:xx": "Pumpkin Creek"
      }
    }
  ]
}
