{
  "geometry": {
    "type": "Point",
    "coordinates": [
      -117.9667,
      33.7167
    ]
  },
  "type": "Feature",
  "properties": {
    "hierarchy": [
      "tgn:2307863",
      "tgn:1000001",
      "tgn:7012149",
      "tgn:7007157",
      "tgn:1002748",
      "tgn:7029392"
    ],
    "placetype": [
      "aat:300006075"
    ],
    "id": 2307863,
    "name:xx": "East Garden Grove Wintersburg Channel"
  }
}
