{
  "type": "FeatureCollection",
  "features": [
    {
      "geometry": {
        "type": "Point",
        "coordinates": [
          127.3,
          42.5833
        ]
      },
      "type": "Feature",
      "properties": {
        "hierarchy": [
          "tgn:1072070",
          "tgn:1000004",
          "tgn:7002372",
          "tgn:1000111",
          "tgn:7029392"
        ],
        "placetype": [
          "aat:300008347"
        ],
        "id": 1072070,
        "name:xx": "Taipingchuan"
      }
    },
    {
      "geometry": {
        "type": "Point",
        "coordinates": [
          111.7833,
          32.1333
        ]
      },
      "type": "Feature",
      "properties": {
        "hierarchy": [
          "tgn:1072071",
          "tgn:1000004",
          "tgn:7002078",
          "tgn:1000111",
          "tgn:7029392"
        ],
        "placetype": [
          "aat:300008347"
        ],
        "id": 1072071,
        "name:xx": "Taipingdian"
      }
    },
    {
      "geometry": {
        "type": "Point",
        "coordinates": [
          113.5833,
          29.8333
        ]
      },
      "type": "Feature",
      "properties": {
        "hierarchy": [
          "tgn:1072072",
          "tgn:1000004",
          "tgn:7002078",
          "tgn:1000111",
          "tgn:7029392"
        ],
        "placetype": [
          "aat:300008347"
        ],
        "id": 1072072,
        "name:xx": "Taipingkou"
      }
    },
    {
      "geometry": {
        "type": "Point",
        "coordinates": [
          128.2,
          43.4333
        ]
      },
      "type": "Feature",
      "properties": {
        "hierarchy": [
          "tgn:1072073",
          "tgn:1000004",
          "tgn:7002372",
          "tgn:1000111",
          "tgn:7029392"
        ],
        "placetype": [
          "aat:300008347"
        ],
        "id": 1072073,
        "name:xx": "Taipingling"
      }
    },
    {
      "geometry": {
        "type": "Point",
        "coordinates": [
          122.4,
          40.55
        ]
      },
      "type": "Feature",
      "properties": {
        "hierarchy": [
          "tgn:1072074",
          "tgn:1000004",
          "tgn:1001390",
          "tgn:1000111",
          "tgn:7029392"
        ],
        "placetype": [
          "aat:300008347"
        ],
        "id": 1072074,
        "name:xx": "Taipingshan"
      }
    },
    {
      "geometry": {
        "type": "Point",
        "coordinates": [
          125.1667,
          40.8667
        ]
      },
      "type": "Feature",
      "properties": {
        "hierarchy": [
          "tgn:1072075",
          "tgn:1000004",
          "tgn:1001390",
          "tgn:1000111",
          "tgn:7029392"
        ],
        "placetype": [
          "aat:300008347"
        ],
        "id": 1072075,
        "name:xx": "Taipingshao"
      }
    },
    {
      "geometry": {
        "type": "Point",
        "coordinates": [
          103.6,
          29.4333
        ]
      },
      "type": "Feature",
      "properties": {
        "hierarchy": [
          "tgn:1072076",
          "tgn:1000004",
          "tgn:7002087",
          "tgn:1000111",
          "tgn:7029392"
        ],
        "placetype": [
          "aat:300008347"
        ],
        "id": 1072076,
        "name:xx": "Taipingsi"
      }
    },
    {
      "geometry": {
        "type": "Point",
        "coordinates": [
          121.2167,
          42.6
        ]
      },
      "type": "Feature",
      "properties": {
        "hierarchy": [
          "tgn:1072077",
          "tgn:1000004",
          "tgn:7001838",
          "tgn:1000111",
          "tgn:7029392"
        ],
        "placetype": [
          "aat:300008347"
        ],
        "id": 1072077,
        "name:xx": "Taipingxigou"
      }
    },
    {
      "geometry": {
        "type": "Point",
        "coordinates": [
          124.1167,
          42.2333
        ]
      },
      "type": "Feature",
      "properties": {
        "hierarchy": [
          "tgn:1072078",
          "tgn:1000004",
          "tgn:1001390",
          "tgn:1000111",
          "tgn:7029392"
        ],
        "placetype": [
          "aat:300008347"
        ],
        "id": 1072078,
        "name:xx": "Taipingzhai"
      }
    },
    {
      "geometry": {
        "type": "Point",
        "coordinates": [
          105.7833,
          29.4
        ]
      },
      "type": "Feature",
      "properties": {
        "hierarchy": [
          "tgn:1072079",
          "tgn:1000004",
          "tgn:7002087",
          "tgn:1000111",
          "tgn:7029392"
        ],
        "placetype": [
          "aat:300008347"
        ],
        "id": 1072079,
        "name:xx": "Taipingzhen"
      }
    }
  ]
}
