{
  "geometry": {
    "type": "Point",
    "coordinates": [
      -77.6167,
      39.75
    ]
  },
  "type": "Feature",
  "properties": {
    "hierarchy": [
      "tgn:2092153",
      "tgn:1000001",
      "tgn:7012149",
      "tgn:1002387",
      "tgn:7007710",
      "tgn:7029392"
    ],
    "placetype": [
      "aat:300008347"
    ],
    "id": 2092153,
    "name:xx": "Polktown"
  }
}
