{
  "geometry": {
    "type": "Point",
    "coordinates": [
      -123.6833,
      41.2333
    ]
  },
  "type": "Feature",
  "properties": {
    "hierarchy": [
      "tgn:2611654",
      "tgn:1000001",
      "tgn:7012149",
      "tgn:2000181",
      "tgn:7007157",
      "tgn:7029392"
    ],
    "placetype": [
      "aat:300008706"
    ],
    "id": 2611654,
    "name:xx": "Red Mountain Creek"
  }
}
