{
  "type": "FeatureCollection",
  "features": [
    {
      "geometry": {
        "type": "Point",
        "coordinates": [
          6.7,
          49.783333
        ]
      },
      "type": "Feature",
      "properties": {
        "hierarchy": [
          "tgn:1129252",
          "tgn:1000003",
          "tgn:7003682",
          "tgn:7000084",
          "tgn:7029392"
        ],
        "placetype": [
          "aat:300008707",
          "aat:300008699"
        ],
        "id": 1129252,
        "name:xx": "Ruwer"
      }
    },
    {
      "geometry": {
        "type": "Point",
        "coordinates": [
          -122.7167,
          50.4167
        ]
      },
      "type": "Feature",
      "properties": {
        "hierarchy": [
          "tgn:1129256",
          "tgn:7005735",
          "tgn:7005685",
          "tgn:1000001",
          "tgn:7029392"
        ],
        "placetype": [
          "aat:300008707"
        ],
        "id": 1129256,
        "name:xx": "Ryan"
      }
    },
    {
      "geometry": {
        "type": "Point",
        "coordinates": [
          -1.9,
          53.7167
        ]
      },
      "type": "Feature",
      "properties": {
        "hierarchy": [
          "tgn:1129257",
          "tgn:1003573",
          "tgn:7002445",
          "tgn:1000003",
          "tgn:7029507",
          "tgn:7008591",
          "tgn:7029392"
        ],
        "placetype": [
          "aat:300008707"
        ],
        "id": 1129257,
        "name:xx": "Ryburn"
      }
    },
    {
      "geometry": {
        "type": "Point",
        "coordinates": [
          -0.716667,
          54.15
        ]
      },
      "type": "Feature",
      "properties": {
        "hierarchy": [
          "tgn:1129258",
          "tgn:7002445",
          "tgn:1000003",
          "tgn:7008166",
          "tgn:7008591",
          "tgn:7029392"
        ],
        "placetype": [
          "aat:300008707",
          "aat:300008699"
        ],
        "name:en": "Rye",
        "id": 1129258
      }
    },
    {
      "geometry": {
        "type": "Point",
        "coordinates": [
          -1,
          53.4167
        ]
      },
      "type": "Feature",
      "properties": {
        "hierarchy": [
          "tgn:1129259",
          "tgn:7002445",
          "tgn:1000003",
          "tgn:7008167",
          "tgn:7008591",
          "tgn:7029392"
        ],
        "placetype": [
          "aat:300008707"
        ],
        "id": 1129259,
        "name:xx": "Ryton"
      }
    }
  ]
}
