{
  "geometry": {
    "type": "Point",
    "coordinates": [
      -87.9333,
      31.2333
    ]
  },
  "type": "Feature",
  "properties": {
    "hierarchy": [
      "tgn:2761922",
      "tgn:7002659",
      "tgn:1000001",
      "tgn:7012149",
      "tgn:2000064",
      "tgn:7029392"
    ],
    "placetype": [
      "aat:300008707"
    ],
    "id": 2761922,
    "name:xx": "West River"
  }
}
