{
  "geometry": {
    "type": "Point",
    "coordinates": [
      80.9833,
      29.2667
    ]
  },
  "type": "Feature",
  "properties": {
    "hierarchy": [
      "tgn:1083316",
      "tgn:7001433",
      "tgn:7001420",
      "tgn:1000004",
      "tgn:1000132",
      "tgn:7029392"
    ],
    "placetype": [
      "aat:300008347"
    ],
    "id": 1083316,
    "name:xx": "Silgarhi-Dotī"
  }
}
