{
  "geometry": {
    "type": "Point",
    "coordinates": [
      -82.45,
      27.8667
    ]
  },
  "type": "Feature",
  "properties": {
    "hierarchy": [
      "tgn:2468961",
      "tgn:1000001",
      "tgn:1002479",
      "tgn:7012149",
      "tgn:7007240",
      "tgn:7029392"
    ],
    "placetype": [
      "aat:300132348"
    ],
    "id": 2468961,
    "name:xx": "Long Shoal"
  }
}
