{
  "geometry": {
    "type": "Point",
    "coordinates": [
      -82.2667,
      34.0167
    ]
  },
  "type": "Feature",
  "properties": {
    "hierarchy": [
      "tgn:2399234",
      "tgn:1000001",
      "tgn:2001748",
      "tgn:7012149",
      "tgn:7007712",
      "tgn:7029392"
    ],
    "placetype": [
      "aat:300008699"
    ],
    "id": 2399234,
    "name:xx": "Horeb Branch"
  }
}
