{
  "geometry": {
    "type": "Point",
    "coordinates": [
      74.270837,
      33.827961
    ]
  },
  "type": "Feature",
  "properties": {
    "hierarchy": [
      "tgn:7590118",
      "tgn:1000004",
      "tgn:7000198",
      "tgn:7000799",
      "tgn:7029392"
    ],
    "placetype": [
      "aat:300008347"
    ],
    "name:en": "Bedār Balnāl",
    "id": 7590118
  }
}
