{
  "type": "FeatureCollection",
  "features": [
    {
      "geometry": {
        "type": "Point",
        "coordinates": [
          -118.1833,
          44.3167
        ]
      },
      "type": "Feature",
      "properties": {
        "hierarchy": [
          "tgn:2470860",
          "tgn:7013349",
          "tgn:1000001",
          "tgn:7012149",
          "tgn:7007708",
          "tgn:7029392"
        ],
        "placetype": [
          "aat:300008697"
        ],
        "id": 2470860,
        "name:xx": "Lost Cow Spring"
      }
    },
    {
      "geometry": {
        "type": "Point",
        "coordinates": [
          -112.3167,
          35.2333
        ]
      },
      "type": "Feature",
      "properties": {
        "hierarchy": [
          "tgn:2470861",
          "tgn:1000001",
          "tgn:7006451",
          "tgn:2000092",
          "tgn:7012149",
          "tgn:7029392"
        ],
        "placetype": [
          "aat:300006191"
        ],
        "id": 2470861,
        "name:xx": "Lost Cow Tank"
      }
    },
    {
      "geometry": {
        "type": "Point",
        "coordinates": [
          -85.3333,
          33.6167
        ]
      },
      "type": "Feature",
      "properties": {
        "hierarchy": [
          "tgn:2470862",
          "tgn:7002659",
          "tgn:1000001",
          "tgn:2000014",
          "tgn:7012149",
          "tgn:7029392"
        ],
        "placetype": [
          "aat:300008706"
        ],
        "id": 2470862,
        "name:xx": "Lost Creek"
      }
    },
    {
      "geometry": {
        "type": "Point",
        "coordinates": [
          -87.9,
          34.55
        ]
      },
      "type": "Feature",
      "properties": {
        "hierarchy": [
          "tgn:2470863",
          "tgn:7002659",
          "tgn:1000001",
          "tgn:7012149",
          "tgn:2000029",
          "tgn:7029392"
        ],
        "placetype": [
          "aat:300008706"
        ],
        "id": 2470863,
        "name:xx": "Lost Creek"
      }
    },
    {
      "geometry": {
        "type": "Point",
        "coordinates": [
          -87.9667,
          32.4833
        ]
      },
      "type": "Feature",
      "properties": {
        "hierarchy": [
          "tgn:2470864",
          "tgn:7002659",
          "tgn:1000001",
          "tgn:7012149",
          "tgn:2000059",
          "tgn:7029392"
        ],
        "placetype": [
          "aat:300008706"
        ],
        "id": 2470864,
        "name:xx": "Lost Creek"
      }
    },
    {
      "geometry": {
        "type": "Point",
        "coordinates": [
          -86.9833,
          33.5333
        ]
      },
      "type": "Feature",
      "properties": {
        "hierarchy": [
          "tgn:2470865",
          "tgn:7002659",
          "tgn:1000001",
          "tgn:7012149",
          "tgn:2000036",
          "tgn:7029392"
        ],
        "placetype": [
          "aat:300008706"
        ],
        "id": 2470865,
        "name:xx": "Lost Creek"
      }
    },
    {
      "geometry": {
        "type": "Point",
        "coordinates": [
          -87.5833,
          33.9333
        ]
      },
      "type": "Feature",
      "properties": {
        "hierarchy": [
          "tgn:2470866",
          "tgn:7002659",
          "tgn:1000001",
          "tgn:7012149",
          "tgn:2000063",
          "tgn:7029392"
        ],
        "placetype": [
          "aat:300008706"
        ],
        "id": 2470866,
        "name:xx": "Lost Creek"
      }
    },
    {
      "geometry": {
        "type": "Point",
        "coordinates": [
          -87.8833,
          32.25
        ]
      },
      "type": "Feature",
      "properties": {
        "hierarchy": [
          "tgn:2470867",
          "tgn:7002659",
          "tgn:1000001",
          "tgn:7012149",
          "tgn:2000045",
          "tgn:7029392"
        ],
        "placetype": [
          "aat:300008706"
        ],
        "id": 2470867,
        "name:xx": "Lost Creek"
      }
    },
    {
      "geometry": {
        "type": "Point",
        "coordinates": [
          -100,
          39.55
        ]
      },
      "type": "Feature",
      "properties": {
        "hierarchy": [
          "tgn:2470869",
          "tgn:1000001",
          "tgn:7012149",
          "tgn:2000728",
          "tgn:7007254",
          "tgn:7029392"
        ],
        "placetype": [
          "aat:300008706"
        ],
        "id": 2470869,
        "name:xx": "Lost Creek"
      }
    }
  ]
}
