{
  "geometry": {
    "type": "Point",
    "coordinates": [
      78.634191,
      31.70424
    ]
  },
  "type": "Feature",
  "properties": {
    "hierarchy": [
      "tgn:7576185",
      "tgn:1000004",
      "tgn:7000198",
      "tgn:1001996",
      "tgn:7029392"
    ],
    "placetype": [
      "aat:300008347"
    ],
    "name:en": "Lāmache",
    "id": 7576185
  }
}
