{
  "geometry": {
    "type": "Point",
    "coordinates": [
      -99.3167,
      32.9333
    ]
  },
  "type": "Feature",
  "properties": {
    "hierarchy": [
      "tgn:2481362",
      "tgn:1000001",
      "tgn:7012149",
      "tgn:2002084",
      "tgn:7007826",
      "tgn:7029392"
    ],
    "placetype": [
      "aat:300008706"
    ],
    "id": 2481362,
    "name:xx": "Lambshead Creek"
  }
}
