{
  "geometry": {
    "type": "Point",
    "coordinates": [
      -89.5667,
      29.4833
    ]
  },
  "type": "Feature",
  "properties": {
    "hierarchy": [
      "tgn:2704602",
      "tgn:1000001",
      "tgn:7012149",
      "tgn:2000891",
      "tgn:7007256",
      "tgn:7029392"
    ],
    "placetype": [
      "aat:300008850"
    ],
    "id": 2704602,
    "name:xx": "Sunrise Point"
  }
}
