{
  "geometry": {
    "type": "Point",
    "coordinates": [
      -75.4833,
      41.25
    ]
  },
  "type": "Feature",
  "properties": {
    "hierarchy": [
      "tgn:2166070",
      "tgn:1000001",
      "tgn:7012149",
      "tgn:1002564",
      "tgn:7007710",
      "tgn:7029392"
    ],
    "placetype": [
      "aat:300006191"
    ],
    "id": 2166070,
    "name:xx": "Big Bass Lake"
  }
}
