{
  "type": "FeatureCollection",
  "features": [
    {
      "geometry": {
        "type": "Point",
        "coordinates": [
          5.4,
          50
        ]
      },
      "type": "Feature",
      "properties": {
        "hierarchy": [
          "tgn:7254820",
          "tgn:7003465",
          "tgn:1000003",
          "tgn:1000063",
          "tgn:4012014",
          "tgn:7029392"
        ],
        "placetype": [
          "aat:300008347"
        ],
        "id": 7254820,
        "name:xx": "Vesqueville"
      }
    },
    {
      "geometry": {
        "type": "Point",
        "coordinates": [
          5.516216,
          50.334609
        ]
      },
      "type": "Feature",
      "properties": {
        "hierarchy": [
          "tgn:7254822",
          "tgn:7003465",
          "tgn:1000003",
          "tgn:1000063",
          "tgn:4012014",
          "tgn:7029392"
        ],
        "placetype": [
          "aat:300008347"
        ],
        "id": 7254822,
        "name:xx": "Vesin"
      }
    },
    {
      "geometry": {
        "type": "Point",
        "coordinates": [
          5.2,
          49.916667
        ]
      },
      "type": "Feature",
      "properties": {
        "hierarchy": [
          "tgn:7254823",
          "tgn:7003465",
          "tgn:1000003",
          "tgn:1000063",
          "tgn:4012014",
          "tgn:7029392"
        ],
        "placetype": [
          "aat:300008863"
        ],
        "id": 7254823,
        "name:xx": "Vésé, Bois de"
      }
    },
    {
      "geometry": {
        "type": "Point",
        "coordinates": [
          4.95,
          50.216667
        ]
      },
      "type": "Feature",
      "properties": {
        "hierarchy": [
          "tgn:7254825",
          "tgn:7003466",
          "tgn:1000003",
          "tgn:1000063",
          "tgn:4012014",
          "tgn:7029392"
        ],
        "placetype": [
          "aat:300008699"
        ],
        "id": 7254825,
        "name:xx": "Vesce, Ruisseau de"
      }
    },
    {
      "geometry": {
        "type": "Point",
        "coordinates": [
          5.370106,
          50.396649
        ]
      },
      "type": "Feature",
      "properties": {
        "hierarchy": [
          "tgn:7254826",
          "tgn:7003460",
          "tgn:1000003",
          "tgn:1000063",
          "tgn:4012014",
          "tgn:7029392"
        ],
        "placetype": [
          "aat:300008347"
        ],
        "id": 7254826,
        "name:xx": "Vervoz"
      }
    }
  ]
}
