{
  "geometry": {
    "type": "Point",
    "coordinates": [
      -78.9333,
      38.0167
    ]
  },
  "type": "Feature",
  "properties": {
    "hierarchy": [
      "tgn:2112796",
      "tgn:2002142",
      "tgn:1000001",
      "tgn:7012149",
      "tgn:7007919",
      "tgn:7029392"
    ],
    "placetype": [
      "aat:300008347"
    ],
    "id": 2112796,
    "name:xx": "Lyndhurst"
  }
}
