{
  "geometry": {
    "type": "Point",
    "coordinates": [
      120.9667,
      5.9667
    ]
  },
  "type": "Feature",
  "properties": {
    "hierarchy": [
      "tgn:1084267",
      "tgn:1010060",
      "tgn:1007556",
      "tgn:1000004",
      "tgn:1001552",
      "tgn:1000135",
      "tgn:7029392"
    ],
    "placetype": [
      "aat:300008347"
    ],
    "id": 1084267,
    "name:xx": "Indanan"
  }
}
