{
  "geometry": {
    "type": "Point",
    "coordinates": [
      -84.1167,
      34.8167
    ]
  },
  "type": "Feature",
  "properties": {
    "hierarchy": [
      "tgn:2378801",
      "tgn:1000001",
      "tgn:7012149",
      "tgn:2000435",
      "tgn:7007248",
      "tgn:7029392"
    ],
    "placetype": [
      "aat:300132316"
    ],
    "id": 2378801,
    "name:xx": "Hart Cove"
  }
}
