{
  "geometry": {
    "type": "Point",
    "coordinates": [
      -96.9167,
      29.1833
    ]
  },
  "type": "Feature",
  "properties": {
    "hierarchy": [
      "tgn:2153702",
      "tgn:1000001",
      "tgn:7012149",
      "tgn:1002578",
      "tgn:7007826",
      "tgn:7029392"
    ],
    "placetype": [
      "aat:300008699"
    ],
    "id": 2153702,
    "name:xx": "Bear Branch"
  }
}
