{
  "geometry": {
    "type": "Point",
    "coordinates": [
      11.45,
      48.783333
    ]
  },
  "type": "Feature",
  "properties": {
    "hierarchy": [
      "tgn:7167156",
      "tgn:7003669",
      "tgn:1000003",
      "tgn:7000084",
      "tgn:7029392"
    ],
    "placetype": [
      "aat:300008699"
    ],
    "id": 7167156,
    "name:xx": "Haunstädter Bach"
  }
}
