{
  "geometry": {
    "type": "Point",
    "coordinates": [
      -3.7833,
      51.2667
    ]
  },
  "type": "Feature",
  "properties": {
    "hierarchy": [
      "tgn:1011887",
      "tgn:7002445",
      "tgn:1000003",
      "tgn:7012077",
      "tgn:7008591",
      "tgn:7029392"
    ],
    "placetype": [
      "aat:300386846"
    ],
    "id": 1011887,
    "name:xx": "Foreland Point"
  }
}
