{
  "geometry": {
    "type": "Point",
    "coordinates": [
      -93.55,
      30.3667
    ]
  },
  "type": "Feature",
  "properties": {
    "hierarchy": [
      "tgn:2043346",
      "tgn:1000001",
      "tgn:2000863",
      "tgn:7012149",
      "tgn:7007256",
      "tgn:7029392"
    ],
    "placetype": [
      "aat:300387016"
    ],
    "id": 2043346,
    "name:xx": "Lucas"
  }
}
