{
  "geometry": {
    "type": "Point",
    "coordinates": [
      -91.6167,
      30.8167
    ]
  },
  "type": "Feature",
  "properties": {
    "hierarchy": [
      "tgn:2767544",
      "tgn:1000001",
      "tgn:7012149",
      "tgn:2000892",
      "tgn:7007256",
      "tgn:7029392"
    ],
    "placetype": [
      "aat:300008699"
    ],
    "id": 2767544,
    "name:xx": "White Vine, Bayou"
  }
}
