{
  "geometry": {
    "type": "Point",
    "coordinates": [
      -70.9167,
      43.2333
    ]
  },
  "type": "Feature",
  "properties": {
    "hierarchy": [
      "tgn:2178825",
      "tgn:1000001",
      "tgn:2001426",
      "tgn:7012149",
      "tgn:7007564",
      "tgn:7029392"
    ],
    "placetype": [
      "aat:300008798"
    ],
    "id": 2178825,
    "name:xx": "Blackwater Hill"
  }
}
