{
  "geometry": {
    "type": "Point",
    "coordinates": [
      -112.0833,
      39.9167
    ]
  },
  "type": "Feature",
  "properties": {
    "hierarchy": [
      "tgn:2413866",
      "tgn:1000001",
      "tgn:7012149",
      "tgn:2002125",
      "tgn:7007827",
      "tgn:7029392"
    ],
    "placetype": [
      "aat:300000390"
    ],
    "id": 2413866,
    "name:xx": "Iron Blossom Number 3"
  }
}
