{
  "geometry": {
    "type": "Point",
    "coordinates": [
      -70.75,
      42.5833
    ]
  },
  "type": "Feature",
  "properties": {
    "hierarchy": [
      "tgn:2158609",
      "tgn:1000001",
      "tgn:1002359",
      "tgn:7012149",
      "tgn:7007517",
      "tgn:7029392"
    ],
    "placetype": [
      "aat:300008905"
    ],
    "id": 2158609,
    "name:xx": "Beaverdam Swamp"
  }
}
