{
  "geometry": {
    "type": "Point",
    "coordinates": [
      -120.05,
      48.7333
    ]
  },
  "type": "Feature",
  "properties": {
    "hierarchy": [
      "tgn:2397647",
      "tgn:1000001",
      "tgn:7012149",
      "tgn:1002742",
      "tgn:7007920",
      "tgn:7029392"
    ],
    "placetype": [
      "aat:300008706"
    ],
    "id": 2397647,
    "name:xx": "Honeymoon Creek"
  }
}
