{
  "geometry": {
    "type": "Point",
    "coordinates": [
      -76.1833,
      43.65
    ]
  },
  "type": "Feature",
  "properties": {
    "hierarchy": [
      "tgn:2221593",
      "tgn:1000001",
      "tgn:7012149",
      "tgn:1002758",
      "tgn:7007568",
      "tgn:7029392"
    ],
    "placetype": [
      "aat:300008791"
    ],
    "id": 2221593,
    "name:xx": "Carl Island"
  }
}
