{
  "geometry": {
    "type": "Point",
    "coordinates": [
      -117.3167,
      47.9667
    ]
  },
  "type": "Feature",
  "properties": {
    "hierarchy": [
      "tgn:2116294",
      "tgn:1000001",
      "tgn:7012149",
      "tgn:2002249",
      "tgn:7007920",
      "tgn:7029392"
    ],
    "placetype": [
      "aat:300008347"
    ],
    "id": 2116294,
    "name:xx": "Milan"
  }
}
