{
  "geometry": {
    "type": "Point",
    "coordinates": [
      -86.55,
      37.6167
    ]
  },
  "type": "Feature",
  "properties": {
    "hierarchy": [
      "tgn:2283751",
      "tgn:1000001",
      "tgn:2000773",
      "tgn:7012149",
      "tgn:7007255",
      "tgn:7029392"
    ],
    "placetype": [
      "aat:300008347"
    ],
    "id": 2283751,
    "name:xx": "Dempster"
  }
}
