{
  "geometry": {
    "type": "Point",
    "coordinates": [
      14.433333,
      52.35
    ]
  },
  "type": "Feature",
  "properties": {
    "hierarchy": [
      "tgn:7199543",
      "tgn:7000096",
      "tgn:1000003",
      "tgn:7000084",
      "tgn:7029392"
    ],
    "placetype": [
      "aat:300004792"
    ],
    "id": 7199543,
    "name:xx": "Försterei Eduardspring"
  }
}
