{
  "geometry": {
    "type": "Point",
    "coordinates": [
      -76.2167,
      39.3333
    ]
  },
  "type": "Feature",
  "properties": {
    "hierarchy": [
      "tgn:2124556",
      "tgn:1000001",
      "tgn:7016102",
      "tgn:7012149",
      "tgn:7007516",
      "tgn:7029392"
    ],
    "placetype": [
      "aat:300008850"
    ],
    "id": 2124556,
    "name:xx": "Abbey Point"
  }
}
