{
  "type": "FeatureCollection",
  "features": [
    {
      "geometry": {
        "type": "Point",
        "coordinates": [
          -99.533333,
          25.366667
        ]
      },
      "type": "Feature",
      "properties": {
        "hierarchy": [
          "tgn:7389140",
          "tgn:1000001",
          "tgn:7005589",
          "tgn:7005560",
          "tgn:7029392"
        ],
        "placetype": [
          "aat:300008699"
        ],
        "id": 7389140,
        "name:xx": "Pilón, Río"
      }
    },
    {
      "geometry": {
        "type": "Point",
        "coordinates": [
          -98.7,
          23.966667
        ]
      },
      "type": "Feature",
      "properties": {
        "hierarchy": [
          "tgn:7389141",
          "tgn:1000001",
          "tgn:7005597",
          "tgn:7005560",
          "tgn:7029392"
        ],
        "placetype": [
          "aat:300008699"
        ],
        "id": 7389141,
        "name:xx": "Pilón, Río"
      }
    },
    {
      "geometry": {
        "type": "Point",
        "coordinates": [
          -106.1,
          28.25
        ]
      },
      "type": "Feature",
      "properties": {
        "hierarchy": [
          "tgn:7389142",
          "tgn:7005581",
          "tgn:1000001",
          "tgn:7005560",
          "tgn:7029392"
        ],
        "placetype": [
          "aat:300008795"
        ],
        "id": 7389142,
        "name:xx": "Pilon, Cerro el"
      }
    },
    {
      "geometry": {
        "type": "Point",
        "coordinates": [
          -108.233333,
          30.383333
        ]
      },
      "type": "Feature",
      "properties": {
        "hierarchy": [
          "tgn:7389143",
          "tgn:7005581",
          "tgn:1000001",
          "tgn:7005560",
          "tgn:7029392"
        ],
        "placetype": [
          "aat:300008795"
        ],
        "id": 7389143,
        "name:xx": "Pilón, Cerro"
      }
    },
    {
      "geometry": {
        "type": "Point",
        "coordinates": [
          -99.661111,
          24.496667
        ]
      },
      "type": "Feature",
      "properties": {
        "hierarchy": [
          "tgn:7389144",
          "tgn:1000001",
          "tgn:7005597",
          "tgn:7005560",
          "tgn:7029392"
        ],
        "placetype": [
          "aat:300008795"
        ],
        "id": 7389144,
        "name:xx": "Pilón, Cerro"
      }
    },
    {
      "geometry": {
        "type": "Point",
        "coordinates": [
          -99.35,
          20.216667
        ]
      },
      "type": "Feature",
      "properties": {
        "hierarchy": [
          "tgn:7389145",
          "tgn:7005587",
          "tgn:1000001",
          "tgn:7005560",
          "tgn:7029392"
        ],
        "placetype": [
          "aat:300008795"
        ],
        "id": 7389145,
        "name:xx": "Pilón, Cerro"
      }
    },
    {
      "geometry": {
        "type": "Point",
        "coordinates": [
          -99.833333,
          25.216667
        ]
      },
      "type": "Feature",
      "properties": {
        "hierarchy": [
          "tgn:7389146",
          "tgn:1000001",
          "tgn:7005589",
          "tgn:7005560",
          "tgn:7029392"
        ],
        "placetype": [
          "aat:300008347"
        ],
        "id": 7389146,
        "name:xx": "Pilón"
      }
    },
    {
      "geometry": {
        "type": "Point",
        "coordinates": [
          -99.816667,
          21.4
        ]
      },
      "type": "Feature",
      "properties": {
        "hierarchy": [
          "tgn:7389147",
          "tgn:7005584",
          "tgn:1000001",
          "tgn:7005560",
          "tgn:7029392"
        ],
        "placetype": [
          "aat:300008347"
        ],
        "id": 7389147,
        "name:xx": "Pilón"
      }
    },
    {
      "geometry": {
        "type": "Point",
        "coordinates": [
          -99.766667,
          21.1
        ]
      },
      "type": "Feature",
      "properties": {
        "hierarchy": [
          "tgn:7389148",
          "tgn:1000001",
          "tgn:7005593",
          "tgn:7005560",
          "tgn:7029392"
        ],
        "placetype": [
          "aat:300008347"
        ],
        "id": 7389148,
        "name:xx": "Pilón"
      }
    },
    {
      "geometry": {
        "type": "Point",
        "coordinates": [
          -100.166667,
          27.6
        ]
      },
      "type": "Feature",
      "properties": {
        "hierarchy": [
          "tgn:7389149",
          "tgn:1000001",
          "tgn:7005589",
          "tgn:7005560",
          "tgn:7029392"
        ],
        "placetype": [
          "aat:300008680"
        ],
        "id": 7389149,
        "name:xx": "Pillaje, Laguna del"
      }
    }
  ]
}
