{
  "geometry": {
    "type": "Point",
    "coordinates": [
      13.5333,
      49.15
    ]
  },
  "type": "Feature",
  "properties": {
    "hierarchy": [
      "tgn:1027495",
      "tgn:7593919",
      "tgn:1000003",
      "tgn:1001780",
      "tgn:7029392"
    ],
    "placetype": [
      "aat:300008347"
    ],
    "id": 1027495,
    "name:xx": "Rejštejn"
  }
}
