{
  "type": "FeatureCollection",
  "features": [
    {
      "geometry": {
        "type": "Point",
        "coordinates": [
          -69.6,
          43.8
        ]
      },
      "type": "Feature",
      "properties": {
        "hierarchy": [
          "tgn:2221190",
          "tgn:1000001",
          "tgn:2000925",
          "tgn:7012149",
          "tgn:7007515",
          "tgn:7029392"
        ],
        "placetype": [
          "aat:300132348"
        ],
        "id": 2221190,
        "name:xx": "Card Ledge"
      }
    },
    {
      "geometry": {
        "type": "Point",
        "coordinates": [
          -71.6333,
          42
        ]
      },
      "type": "Feature",
      "properties": {
        "hierarchy": [
          "tgn:2221191",
          "tgn:1000001",
          "tgn:7012149",
          "tgn:7029392"
        ],
        "placetype": [
          "aat:300008699"
        ],
        "id": 2221191,
        "name:xx": "Card Machine Brook"
      }
    },
    {
      "geometry": {
        "type": "Point",
        "coordinates": [
          -79.1,
          40.2
        ]
      },
      "type": "Feature",
      "properties": {
        "hierarchy": [
          "tgn:2221192",
          "tgn:1000001",
          "tgn:7012149",
          "tgn:1002904",
          "tgn:7007710",
          "tgn:7029392"
        ],
        "placetype": [
          "aat:300008699"
        ],
        "id": 2221192,
        "name:xx": "Card Machine Run"
      }
    },
    {
      "geometry": {
        "type": "Point",
        "coordinates": [
          -68.2,
          44.5833
        ]
      },
      "type": "Feature",
      "properties": {
        "hierarchy": [
          "tgn:2221193",
          "tgn:1000001",
          "tgn:2000922",
          "tgn:7012149",
          "tgn:7007515",
          "tgn:7029392"
        ],
        "placetype": [
          "aat:300008699"
        ],
        "id": 2221193,
        "name:xx": "Card Mill Stream"
      }
    },
    {
      "geometry": {
        "type": "Point",
        "coordinates": [
          -82.2667,
          37.3667
        ]
      },
      "type": "Feature",
      "properties": {
        "hierarchy": [
          "tgn:2221194",
          "tgn:1000001",
          "tgn:7012149",
          "tgn:2000837",
          "tgn:7007255",
          "tgn:7029392"
        ],
        "placetype": [
          "aat:300008798"
        ],
        "id": 2221194,
        "name:xx": "Card Mountain"
      }
    },
    {
      "geometry": {
        "type": "Point",
        "coordinates": [
          -123.4,
          39.8
        ]
      },
      "type": "Feature",
      "properties": {
        "hierarchy": [
          "tgn:2221195",
          "tgn:1000001",
          "tgn:7012149",
          "tgn:7007157",
          "tgn:2000185",
          "tgn:7029392"
        ],
        "placetype": [
          "aat:300008347"
        ],
        "id": 2221195,
        "name:xx": "Card Place"
      }
    },
    {
      "geometry": {
        "type": "Point",
        "coordinates": [
          -80.3333,
          25.3167
        ]
      },
      "type": "Feature",
      "properties": {
        "hierarchy": [
          "tgn:2221196",
          "tgn:1000001",
          "tgn:7012149",
          "tgn:1002314",
          "tgn:7007240",
          "tgn:7029392"
        ],
        "placetype": [
          "aat:300008850"
        ],
        "id": 2221196,
        "name:xx": "Card Point"
      }
    },
    {
      "geometry": {
        "type": "Point",
        "coordinates": [
          -89.2,
          47.8833
        ]
      },
      "type": "Feature",
      "properties": {
        "hierarchy": [
          "tgn:2221197",
          "tgn:1000001",
          "tgn:7012149",
          "tgn:2000969",
          "tgn:7007520",
          "tgn:7029392"
        ],
        "placetype": [
          "aat:300008850"
        ],
        "id": 2221197,
        "name:xx": "Card Point"
      }
    },
    {
      "geometry": {
        "type": "Point",
        "coordinates": [
          -73.3667,
          42.3167
        ]
      },
      "type": "Feature",
      "properties": {
        "hierarchy": [
          "tgn:2221198",
          "tgn:7013388",
          "tgn:1000001",
          "tgn:7012149",
          "tgn:7007517",
          "tgn:7029392"
        ],
        "placetype": [
          "aat:300008680"
        ],
        "id": 2221198,
        "name:xx": "Card Pond"
      }
    },
    {
      "geometry": {
        "type": "Point",
        "coordinates": [
          -75.2,
          42.6333
        ]
      },
      "type": "Feature",
      "properties": {
        "hierarchy": [
          "tgn:2221199",
          "tgn:1000001",
          "tgn:7012149",
          "tgn:7014318",
          "tgn:7007568",
          "tgn:7029392"
        ],
        "placetype": [
          "aat:300008680"
        ],
        "id": 2221199,
        "name:xx": "Card Pond"
      }
    }
  ]
}
