{
  "geometry": {
    "type": "Point",
    "coordinates": [
      77.989752,
      30.352719
    ]
  },
  "type": "Feature",
  "properties": {
    "hierarchy": [
      "tgn:7591857",
      "tgn:1000004",
      "tgn:7000198",
      "tgn:7031786",
      "tgn:7029392"
    ],
    "placetype": [
      "aat:300008699"
    ],
    "name:en": "Nūn Nādi",
    "id": 7591857
  }
}
