{
  "geometry": {
    "type": "Point",
    "coordinates": [
      -83.4167,
      42.25
    ]
  },
  "type": "Feature",
  "properties": {
    "hierarchy": [
      "tgn:2769896",
      "tgn:1000001",
      "tgn:7012149",
      "tgn:1003005",
      "tgn:7007520",
      "tgn:7029392"
    ],
    "placetype": [
      "aat:300008699"
    ],
    "id": 2769896,
    "name:xx": "Wilbur Drain"
  }
}
