{
  "geometry": {
    "type": "Point",
    "coordinates": [
      31.1167,
      -29.5833
    ]
  },
  "type": "Feature",
  "properties": {
    "hierarchy": [
      "tgn:1093700",
      "tgn:7001242",
      "tgn:7016749",
      "tgn:1000193",
      "tgn:7029392"
    ],
    "placetype": [
      "aat:300008347"
    ],
    "id": 1093700,
    "name:xx": "Tongaat"
  }
}
