{
  "geometry": {
    "type": "Point",
    "coordinates": [
      -78.4667,
      41.5333
    ]
  },
  "type": "Feature",
  "properties": {
    "hierarchy": [
      "tgn:2419542",
      "tgn:1000001",
      "tgn:7012149",
      "tgn:1002352",
      "tgn:7007710",
      "tgn:7029392"
    ],
    "placetype": [
      "aat:300008798"
    ],
    "id": 2419542,
    "name:xx": "Jarrets Summit"
  }
}
