{
  "geometry": {
    "type": "Point",
    "coordinates": [
      -68.9333,
      44.4833
    ]
  },
  "type": "Feature",
  "properties": {
    "hierarchy": [
      "tgn:2585851",
      "tgn:1000001",
      "tgn:7012149",
      "tgn:2000931",
      "tgn:7007515",
      "tgn:7029392"
    ],
    "placetype": [
      "aat:300008699"
    ],
    "id": 2585851,
    "name:xx": "Piper Brook"
  }
}
