{
  "geometry": {
    "type": "Point",
    "coordinates": [
      -110.4333,
      36.9167
    ]
  },
  "type": "Feature",
  "properties": {
    "hierarchy": [
      "tgn:7021539",
      "tgn:1000001",
      "tgn:7012149",
      "tgn:7029392"
    ],
    "placetype": [
      "aat:300008761"
    ],
    "id": 7021539,
    "name:xx": "West Fork Copper Canyon"
  }
}
