{
  "geometry": {
    "type": "Point",
    "coordinates": [
      -13.6333,
      10.45
    ]
  },
  "type": "Feature",
  "properties": {
    "hierarchy": [
      "tgn:1090239",
      "tgn:7000790",
      "tgn:7001242",
      "tgn:1000167",
      "tgn:7029392"
    ],
    "placetype": [
      "aat:300008347"
    ],
    "id": 1090239,
    "name:xx": "Fria"
  }
}
