{
  "geometry": {
    "type": "Point",
    "coordinates": [
      -61.8333,
      -2.8667
    ]
  },
  "type": "Feature",
  "properties": {
    "hierarchy": [
      "tgn:1126762",
      "tgn:1001826",
      "tgn:1000047",
      "tgn:7002456",
      "tgn:1000002",
      "tgn:7029392"
    ],
    "placetype": [
      "aat:300008707"
    ],
    "id": 1126762,
    "name:xx": "Manacá"
  }
}
