{
  "type": "FeatureCollection",
  "features": [
    {
      "geometry": {
        "type": "Point",
        "coordinates": [
          137.8667,
          35.75
        ]
      },
      "type": "Feature",
      "properties": {
        "hierarchy": [
          "tgn:1110041",
          "tgn:7000895",
          "tgn:1000004",
          "tgn:1001010",
          "tgn:1000120",
          "tgn:7029392"
        ],
        "placetype": [
          "aat:300386831"
        ],
        "id": 1110041,
        "name:xx": "Kiso-sammyaku"
      }
    },
    {
      "geometry": {
        "type": "Point",
        "coordinates": [
          142.7167,
          44.3667
        ]
      },
      "type": "Feature",
      "properties": {
        "hierarchy": [
          "tgn:1110042",
          "tgn:1000985",
          "tgn:7016529",
          "tgn:7016531",
          "tgn:1000004",
          "tgn:1000120",
          "tgn:7029392"
        ],
        "placetype": [
          "aat:300386831"
        ],
        "id": 1110042,
        "name:xx": "Kitami-sanchi"
      }
    },
    {
      "geometry": {
        "type": "Point",
        "coordinates": [
          -128.8333,
          53.5
        ]
      },
      "type": "Feature",
      "properties": {
        "hierarchy": [
          "tgn:1110043",
          "tgn:7005735",
          "tgn:7005685",
          "tgn:1000001",
          "tgn:7029392"
        ],
        "placetype": [
          "aat:300386831"
        ],
        "id": 1110043,
        "name:xx": "Kitimat Ranges"
      }
    },
    {
      "geometry": {
        "type": "Point",
        "coordinates": [
          118.1667,
          57.25
        ]
      },
      "type": "Feature",
      "properties": {
        "hierarchy": [
          "tgn:1110044",
          "tgn:1000004",
          "tgn:7002435",
          "tgn:7029392"
        ],
        "placetype": [
          "aat:300386831"
        ],
        "id": 1110044,
        "name:xx": "Kodar, Khrebet"
      }
    },
    {
      "geometry": {
        "type": "Point",
        "coordinates": [
          42,
          43
        ]
      },
      "type": "Feature",
      "properties": {
        "hierarchy": [
          "tgn:1110045",
          "tgn:1000004",
          "tgn:7006653",
          "tgn:7029392"
        ],
        "placetype": [
          "aat:300386831"
        ],
        "id": 1110045,
        "name:xx": "Kodorskiy Khrebet"
      }
    },
    {
      "geometry": {
        "type": "Point",
        "coordinates": [
          -157.9,
          21.45
        ]
      },
      "type": "Feature",
      "properties": {
        "hierarchy": [
          "tgn:1110046",
          "tgn:1002483",
          "tgn:7019080",
          "tgn:1000001",
          "tgn:7012149",
          "tgn:7007249",
          "tgn:7029392"
        ],
        "placetype": [
          "aat:300386831"
        ],
        "id": 1110046,
        "name:xx": "Koolau Range"
      }
    },
    {
      "geometry": {
        "type": "Point",
        "coordinates": [
          -10.0833,
          7.35
        ]
      },
      "type": "Feature",
      "properties": {
        "hierarchy": [
          "tgn:1110048",
          "tgn:7001242",
          "tgn:1000409",
          "tgn:1000171",
          "tgn:7029392"
        ],
        "placetype": [
          "aat:300386831"
        ],
        "id": 1110048,
        "name:xx": "Kpo Range"
      }
    },
    {
      "geometry": {
        "type": "Point",
        "coordinates": [
          93.1,
          53.85
        ]
      },
      "type": "Feature",
      "properties": {
        "hierarchy": [
          "tgn:1110049",
          "tgn:1000004",
          "tgn:1003314",
          "tgn:7018214",
          "tgn:7002435",
          "tgn:7029392"
        ],
        "placetype": [
          "aat:300386831"
        ],
        "id": 1110049,
        "name:xx": "Kryzhina, Khrebet"
      }
    }
  ]
}
