{
  "geometry": {
    "type": "Point",
    "coordinates": [
      -82.1667,
      29.85
    ]
  },
  "type": "Feature",
  "properties": {
    "hierarchy": [
      "tgn:2374374",
      "tgn:2000259",
      "tgn:1000001",
      "tgn:7012149",
      "tgn:7007240",
      "tgn:7029392"
    ],
    "placetype": [
      "aat:300008680"
    ],
    "id": 2374374,
    "name:xx": "Hampton Lake"
  }
}
