{
  "geometry": {
    "type": "Point",
    "coordinates": [
      -83.1667,
      31.0667
    ]
  },
  "type": "Feature",
  "properties": {
    "hierarchy": [
      "tgn:2158415",
      "tgn:1000001",
      "tgn:2000301",
      "tgn:7012149",
      "tgn:7007248",
      "tgn:7029392"
    ],
    "placetype": [
      "aat:300008706"
    ],
    "id": 2158415,
    "name:xx": "Beaverdam Creek"
  }
}
