{
  "type": "FeatureCollection",
  "features": [
    {
      "geometry": {
        "type": "Point",
        "coordinates": [
          12.2,
          50.183333
        ]
      },
      "type": "Feature",
      "properties": {
        "hierarchy": [
          "tgn:7086690",
          "tgn:7003669",
          "tgn:1000003",
          "tgn:7000084",
          "tgn:7029392"
        ],
        "placetype": [
          "aat:300008777"
        ],
        "id": 7086690,
        "name:xx": "Wartberg"
      }
    },
    {
      "geometry": {
        "type": "Point",
        "coordinates": [
          12.116667,
          50.066667
        ]
      },
      "type": "Feature",
      "properties": {
        "hierarchy": [
          "tgn:7086691",
          "tgn:7003669",
          "tgn:1000003",
          "tgn:7000084",
          "tgn:7029392"
        ],
        "placetype": [
          "aat:300008777"
        ],
        "id": 7086691,
        "name:xx": "Wart-Berg"
      }
    },
    {
      "geometry": {
        "type": "Point",
        "coordinates": [
          9.236389,
          49.159444
        ]
      },
      "type": "Feature",
      "properties": {
        "hierarchy": [
          "tgn:7086692",
          "tgn:7003692",
          "tgn:1000003",
          "tgn:7000084",
          "tgn:7029392"
        ],
        "placetype": [
          "aat:300008795"
        ],
        "id": 7086692,
        "name:xx": "Wartberg"
      }
    },
    {
      "geometry": {
        "type": "Point",
        "coordinates": [
          8.733333,
          48.9
        ]
      },
      "type": "Feature",
      "properties": {
        "hierarchy": [
          "tgn:7086693",
          "tgn:7003692",
          "tgn:1000003",
          "tgn:7000084",
          "tgn:7029392"
        ],
        "placetype": [
          "aat:300008777"
        ],
        "id": 7086693,
        "name:xx": "Wartberg"
      }
    },
    {
      "geometry": {
        "type": "Point",
        "coordinates": [
          10.166667,
          48.633333
        ]
      },
      "type": "Feature",
      "properties": {
        "hierarchy": [
          "tgn:7086694",
          "tgn:7003692",
          "tgn:1000003",
          "tgn:7000084",
          "tgn:7029392"
        ],
        "placetype": [
          "aat:300008777"
        ],
        "id": 7086694,
        "name:xx": "Wartberg"
      }
    },
    {
      "geometry": {
        "type": "Point",
        "coordinates": [
          10.533333,
          48.083333
        ]
      },
      "type": "Feature",
      "properties": {
        "hierarchy": [
          "tgn:7086695",
          "tgn:7003669",
          "tgn:1000003",
          "tgn:7000084",
          "tgn:7029392"
        ],
        "placetype": [
          "aat:300008777"
        ],
        "id": 7086695,
        "name:xx": "Wartberg"
      }
    },
    {
      "geometry": {
        "type": "Point",
        "coordinates": [
          11.15,
          47.966667
        ]
      },
      "type": "Feature",
      "properties": {
        "hierarchy": [
          "tgn:7086696",
          "tgn:7003669",
          "tgn:1000003",
          "tgn:7000084",
          "tgn:7029392"
        ],
        "placetype": [
          "aat:300008347"
        ],
        "id": 7086696,
        "name:xx": "Wartaweil"
      }
    },
    {
      "geometry": {
        "type": "Point",
        "coordinates": [
          8.65,
          48.616667
        ]
      },
      "type": "Feature",
      "properties": {
        "hierarchy": [
          "tgn:7086697",
          "tgn:7003692",
          "tgn:1000003",
          "tgn:7000084",
          "tgn:7029392"
        ],
        "placetype": [
          "aat:300008347"
        ],
        "id": 7086697,
        "name:xx": "Wart"
      }
    },
    {
      "geometry": {
        "type": "Point",
        "coordinates": [
          9.466667,
          47.8
        ]
      },
      "type": "Feature",
      "properties": {
        "hierarchy": [
          "tgn:7086698",
          "tgn:7003692",
          "tgn:1000003",
          "tgn:7000084",
          "tgn:7029392"
        ],
        "placetype": [
          "aat:300008347"
        ],
        "id": 7086698,
        "name:xx": "Wart"
      }
    },
    {
      "geometry": {
        "type": "Point",
        "coordinates": [
          11.833333,
          50.4
        ]
      },
      "type": "Feature",
      "properties": {
        "hierarchy": [
          "tgn:7086699",
          "tgn:1000003",
          "tgn:7003689",
          "tgn:7000084",
          "tgn:7029392"
        ],
        "placetype": [
          "aat:300008777"
        ],
        "id": 7086699,
        "name:xx": "Wart"
      }
    }
  ]
}
