{
  "geometry": {
    "type": "Point",
    "coordinates": [
      -165.75,
      61.8167
    ]
  },
  "type": "Feature",
  "properties": {
    "hierarchy": [
      "tgn:2441867",
      "tgn:7006450",
      "tgn:1000001",
      "tgn:7012149",
      "tgn:2000087",
      "tgn:7029392"
    ],
    "placetype": [
      "aat:300132316"
    ],
    "id": 2441867,
    "name:xx": "Kongishluk Bay"
  }
}
