{
  "geometry": {
    "type": "Point",
    "coordinates": [
      13.5833,
      60.0833
    ]
  },
  "type": "Feature",
  "properties": {
    "hierarchy": [
      "tgn:1062919",
      "tgn:1000003",
      "tgn:7010031",
      "tgn:1000097",
      "tgn:7029392"
    ],
    "placetype": [
      "aat:300008347"
    ],
    "id": 1062919,
    "name:xx": "Edebäck"
  }
}
