{
  "geometry": {
    "type": "Point",
    "coordinates": [
      91.265899,
      23.47547
    ]
  },
  "type": "Feature",
  "properties": {
    "hierarchy": [
      "tgn:1077030",
      "tgn:1000004",
      "tgn:7000198",
      "tgn:1001578",
      "tgn:7029392"
    ],
    "placetype": [
      "aat:300008347"
    ],
    "id": 1077030,
    "name:xx": "Sonamura"
  }
}
