{
  "geometry": {
    "type": "Point",
    "coordinates": [
      51.3333,
      50.1667
    ]
  },
  "type": "Feature",
  "properties": {
    "hierarchy": [
      "tgn:1130149",
      "tgn:1000004",
      "tgn:7011457",
      "tgn:7014786",
      "tgn:7029392"
    ],
    "placetype": [
      "aat:300008707"
    ],
    "id": 1130149,
    "name:xx": "Sol'anka"
  }
}
