{
  "type": "FeatureCollection",
  "features": [
    {
      "geometry": {
        "type": "Point",
        "coordinates": [
          -85.8167,
          40.45
        ]
      },
      "type": "Feature",
      "properties": {
        "hierarchy": [
          "tgn:2033107",
          "tgn:1000001",
          "tgn:7012149",
          "tgn:1002416",
          "tgn:7007252",
          "tgn:7029392"
        ],
        "placetype": [
          "aat:300008347",
          "aat:300387210"
        ],
        "id": 2033107,
        "name:xx": "Normal"
      }
    },
    {
      "geometry": {
        "type": "Point",
        "coordinates": [
          -86.2667,
          38.95
        ]
      },
      "type": "Feature",
      "properties": {
        "hierarchy": [
          "tgn:2033108",
          "tgn:1000001",
          "tgn:7012149",
          "tgn:1002508",
          "tgn:7007252",
          "tgn:7029392"
        ],
        "placetype": [
          "aat:300008347"
        ],
        "id": 2033108,
        "name:xx": "Norman"
      }
    },
    {
      "geometry": {
        "type": "Point",
        "coordinates": [
          -86.15,
          40.3
        ]
      },
      "type": "Feature",
      "properties": {
        "hierarchy": [
          "tgn:2033109",
          "tgn:1000001",
          "tgn:7012149",
          "tgn:1002947",
          "tgn:7007252",
          "tgn:7029392"
        ],
        "placetype": [
          "aat:300008347",
          "aat:300387210"
        ],
        "id": 2033109,
        "name:xx": "Normanda"
      }
    }
  ]
}
