{
  "geometry": {
    "type": "Point",
    "coordinates": [
      -86.0667,
      42.3167
    ]
  },
  "type": "Feature",
  "properties": {
    "hierarchy": [
      "tgn:2552518",
      "tgn:1000001",
      "tgn:7012149",
      "tgn:1002353",
      "tgn:7007252",
      "tgn:7029392"
    ],
    "placetype": [
      "aat:300006075"
    ],
    "id": 2552518,
    "name:xx": "Nunemaker Ditch"
  }
}
