{
  "geometry": {
    "type": "Point",
    "coordinates": [
      -121.05,
      41.8167
    ]
  },
  "type": "Feature",
  "properties": {
    "hierarchy": [
      "tgn:2206940",
      "tgn:1000001",
      "tgn:7012149",
      "tgn:7007157",
      "tgn:2000186",
      "tgn:7029392"
    ],
    "placetype": [
      "aat:300008798"
    ],
    "id": 2206940,
    "name:xx": "Bump Heads"
  }
}
