{
  "geometry": {
    "type": "Point",
    "coordinates": [
      -8.098,
      39.808
    ]
  },
  "type": "Feature",
  "properties": {
    "hierarchy": [
      "tgn:1049935",
      "tgn:7003819",
      "tgn:1000003",
      "tgn:1000090",
      "tgn:7029392"
    ],
    "placetype": [
      "aat:300008347",
      "aat:300387218"
    ],
    "id": 1049935,
    "name:xx": "Sertã"
  }
}
