{
  "geometry": {
    "type": "Point",
    "coordinates": [
      -94.05,
      38.4333
    ]
  },
  "type": "Feature",
  "properties": {
    "hierarchy": [
      "tgn:2243096",
      "tgn:1000001",
      "tgn:7012149",
      "tgn:2001202",
      "tgn:7007523",
      "tgn:7029392"
    ],
    "placetype": [
      "aat:300008680"
    ],
    "id": 2243096,
    "name:xx": "Clear Lake"
  }
}
