{
  "geometry": {
    "type": "Point",
    "coordinates": [
      -75.9833,
      43.4667
    ]
  },
  "type": "Feature",
  "properties": {
    "hierarchy": [
      "tgn:2544066",
      "tgn:1000001",
      "tgn:7012149",
      "tgn:1002758",
      "tgn:7007568",
      "tgn:7029392"
    ],
    "placetype": [
      "aat:300008706"
    ],
    "id": 2544066,
    "name:xx": "North Branch Grindstone Creek"
  }
}
