{
  "geometry": {
    "type": "Point",
    "coordinates": [
      -75.4167,
      39.9167
    ]
  },
  "type": "Feature",
  "properties": {
    "hierarchy": [
      "tgn:2239047",
      "tgn:1000001",
      "tgn:1002330",
      "tgn:7012149",
      "tgn:7007710",
      "tgn:7029392"
    ],
    "placetype": [
      "aat:300008699"
    ],
    "id": 2239047,
    "name:xx": "Chrome Run"
  }
}
