{
  "type": "FeatureCollection",
  "features": [
    {
      "geometry": {
        "type": "Point",
        "coordinates": [
          -100.3,
          22.416667
        ]
      },
      "type": "Feature",
      "properties": {
        "hierarchy": [
          "tgn:7355990",
          "tgn:1000001",
          "tgn:7005594",
          "tgn:7005560",
          "tgn:7029392"
        ],
        "placetype": [
          "aat:300007783"
        ],
        "id": 7355990,
        "name:xx": "Cerritos"
      }
    },
    {
      "geometry": {
        "type": "Point",
        "coordinates": [
          -103.733333,
          20.9
        ]
      },
      "type": "Feature",
      "properties": {
        "hierarchy": [
          "tgn:7355991",
          "tgn:7005586",
          "tgn:1000001",
          "tgn:7005560",
          "tgn:7029392"
        ],
        "placetype": [
          "aat:300000241"
        ],
        "id": 7355991,
        "name:xx": "Cerritos"
      }
    },
    {
      "geometry": {
        "type": "Point",
        "coordinates": [
          -101.666667,
          28.1
        ]
      },
      "type": "Feature",
      "properties": {
        "hierarchy": [
          "tgn:7355992",
          "tgn:1001853",
          "tgn:1000001",
          "tgn:7005560",
          "tgn:7029392"
        ],
        "placetype": [
          "aat:300008347"
        ],
        "id": 7355992,
        "name:xx": "Cerritos"
      }
    },
    {
      "geometry": {
        "type": "Point",
        "coordinates": [
          -99.833333,
          27.75
        ]
      },
      "type": "Feature",
      "properties": {
        "hierarchy": [
          "tgn:7355993",
          "tgn:1000001",
          "tgn:7005589",
          "tgn:7005560",
          "tgn:7029392"
        ],
        "placetype": [
          "aat:300008347"
        ],
        "id": 7355993,
        "name:xx": "Cerritos"
      }
    },
    {
      "geometry": {
        "type": "Point",
        "coordinates": [
          -102.033333,
          25.75
        ]
      },
      "type": "Feature",
      "properties": {
        "hierarchy": [
          "tgn:7355994",
          "tgn:1001853",
          "tgn:1000001",
          "tgn:7005560",
          "tgn:7029392"
        ],
        "placetype": [
          "aat:300008347"
        ],
        "id": 7355994,
        "name:xx": "Cerritos"
      }
    },
    {
      "geometry": {
        "type": "Point",
        "coordinates": [
          -99.553889,
          24.445833
        ]
      },
      "type": "Feature",
      "properties": {
        "hierarchy": [
          "tgn:7355995",
          "tgn:1000001",
          "tgn:7005597",
          "tgn:7005560",
          "tgn:7029392"
        ],
        "placetype": [
          "aat:300008347"
        ],
        "id": 7355995,
        "name:xx": "Cerritos"
      }
    },
    {
      "geometry": {
        "type": "Point",
        "coordinates": [
          -100.6,
          23.683333
        ]
      },
      "type": "Feature",
      "properties": {
        "hierarchy": [
          "tgn:7355996",
          "tgn:1000001",
          "tgn:7005594",
          "tgn:7005560",
          "tgn:7029392"
        ],
        "placetype": [
          "aat:300008347"
        ],
        "id": 7355996,
        "name:xx": "Cerritos"
      }
    },
    {
      "geometry": {
        "type": "Point",
        "coordinates": [
          -101.4,
          22.016667
        ]
      },
      "type": "Feature",
      "properties": {
        "hierarchy": [
          "tgn:7355998",
          "tgn:1000001",
          "tgn:7005601",
          "tgn:7005560",
          "tgn:7029392"
        ],
        "placetype": [
          "aat:300008347"
        ],
        "id": 7355998,
        "name:xx": "Cerritos"
      }
    },
    {
      "geometry": {
        "type": "Point",
        "coordinates": [
          -100.9,
          22.016667
        ]
      },
      "type": "Feature",
      "properties": {
        "hierarchy": [
          "tgn:7355999",
          "tgn:1000001",
          "tgn:7005594",
          "tgn:7005560",
          "tgn:7029392"
        ],
        "placetype": [
          "aat:300008347"
        ],
        "id": 7355999,
        "name:xx": "Cerritos"
      }
    }
  ]
}
