{
  "geometry": {
    "type": "Point",
    "coordinates": [
      -82.0667,
      36.4167
    ]
  },
  "type": "Feature",
  "properties": {
    "hierarchy": [
      "tgn:2713159",
      "tgn:1000001",
      "tgn:7012149",
      "tgn:2001846",
      "tgn:7007825",
      "tgn:7029392"
    ],
    "placetype": [
      "aat:300000390"
    ],
    "id": 2713159,
    "name:xx": "Taylor Prospect"
  }
}
