{
  "type": "FeatureCollection",
  "features": [
    {
      "geometry": {
        "type": "Point",
        "coordinates": [
          -90.6,
          34.4833
        ]
      },
      "type": "Feature",
      "properties": {
        "hierarchy": [
          "tgn:2008470",
          "tgn:1000001",
          "tgn:7016172",
          "tgn:7012149",
          "tgn:2000158",
          "tgn:7029392"
        ],
        "placetype": [
          "aat:300008347"
        ],
        "id": 2008470,
        "name:xx": "Helena"
      }
    },
    {
      "geometry": {
        "type": "Point",
        "coordinates": [
          -90.7333,
          34.5833
        ]
      },
      "type": "Feature",
      "properties": {
        "hierarchy": [
          "tgn:2008473",
          "tgn:1000001",
          "tgn:7016172",
          "tgn:7012149",
          "tgn:2000158",
          "tgn:7029392"
        ],
        "placetype": [
          "aat:300008347",
          "aat:300387210"
        ],
        "id": 2008473,
        "name:xx": "Helena Junction"
      }
    },
    {
      "geometry": {
        "type": "Point",
        "coordinates": [
          -93.2,
          34.4333
        ]
      },
      "type": "Feature",
      "properties": {
        "hierarchy": [
          "tgn:2008474",
          "tgn:1000001",
          "tgn:7016172",
          "tgn:7012149",
          "tgn:2000130",
          "tgn:7029392"
        ],
        "placetype": [
          "aat:300008347",
          "aat:300387210"
        ],
        "id": 2008474,
        "name:xx": "Hempwallace"
      }
    },
    {
      "geometry": {
        "type": "Point",
        "coordinates": [
          -92.2167,
          36.3667
        ]
      },
      "type": "Feature",
      "properties": {
        "hierarchy": [
          "tgn:2008475",
          "tgn:2000107",
          "tgn:1000001",
          "tgn:7016172",
          "tgn:7012149",
          "tgn:7029392"
        ],
        "placetype": [
          "aat:300008347"
        ],
        "id": 2008475,
        "name:xx": "Henderson"
      }
    },
    {
      "geometry": {
        "type": "Point",
        "coordinates": [
          -92.2,
          34.5
        ]
      },
      "type": "Feature",
      "properties": {
        "hierarchy": [
          "tgn:2008476",
          "tgn:1000001",
          "tgn:7016172",
          "tgn:7012149",
          "tgn:2000164",
          "tgn:7029392"
        ],
        "placetype": [
          "aat:300008347"
        ],
        "id": 2008476,
        "name:xx": "Hensley"
      }
    },
    {
      "geometry": {
        "type": "Point",
        "coordinates": [
          -92.0333,
          33.8167
        ]
      },
      "type": "Feature",
      "properties": {
        "hierarchy": [
          "tgn:2008478",
          "tgn:1000001",
          "tgn:7016172",
          "tgn:2000117",
          "tgn:7012149",
          "tgn:7029392"
        ],
        "placetype": [
          "aat:300008347",
          "aat:300387210"
        ],
        "id": 2008478,
        "name:xx": "Herbine"
      }
    },
    {
      "geometry": {
        "type": "Point",
        "coordinates": [
          -90.5833,
          35.7667
        ]
      },
      "type": "Feature",
      "properties": {
        "hierarchy": [
          "tgn:2008479",
          "tgn:1000001",
          "tgn:7016172",
          "tgn:2000120",
          "tgn:7012149",
          "tgn:7029392"
        ],
        "placetype": [
          "aat:300008347",
          "aat:300387210"
        ],
        "id": 2008479,
        "name:xx": "Hergett"
      }
    }
  ]
}
