{
  "geometry": {
    "type": "Point",
    "coordinates": [
      -85.6833,
      44.55
    ]
  },
  "type": "Feature",
  "properties": {
    "hierarchy": [
      "tgn:2149919",
      "tgn:1000001",
      "tgn:7012149",
      "tgn:2000961",
      "tgn:7007520",
      "tgn:7029392"
    ],
    "placetype": [
      "aat:300008680"
    ],
    "id": 2149919,
    "name:xx": "Bartlett Lake"
  }
}
