{
  "geometry": {
    "type": "Point",
    "coordinates": [
      30.516667,
      30.45
    ]
  },
  "type": "Feature",
  "properties": {
    "hierarchy": [
      "tgn:7522880",
      "tgn:7001242",
      "tgn:7016833",
      "tgn:1001113",
      "tgn:7029392"
    ],
    "placetype": [
      "aat:300008347"
    ],
    "name:en": "Ash Shaghānibah",
    "id": 7522880
  }
}
