{
  "geometry": {
    "type": "Point",
    "coordinates": [
      -77.4833,
      41.5333
    ]
  },
  "type": "Feature",
  "properties": {
    "hierarchy": [
      "tgn:2710592",
      "tgn:1000001",
      "tgn:7012149",
      "tgn:7007710",
      "tgn:7029392"
    ],
    "placetype": [
      "aat:300008905"
    ],
    "id": 2710592,
    "name:xx": "Tamarack Swamp"
  }
}
