{
  "geometry": {
    "type": "Point",
    "coordinates": [
      31.533333,
      26.733333
    ]
  },
  "type": "Feature",
  "properties": {
    "hierarchy": [
      "tgn:7523687",
      "tgn:7001242",
      "tgn:7016833",
      "tgn:7000124",
      "tgn:7029392"
    ],
    "placetype": [
      "aat:300007783"
    ],
    "name:en": "Maḩaţţat aş Şawāmi'ah",
    "id": 7523687
  }
}
