{
  "geometry": {
    "type": "Point",
    "coordinates": [
      -124.45,
      42.9667
    ]
  },
  "type": "Feature",
  "properties": {
    "hierarchy": [
      "tgn:2267644",
      "tgn:1000001",
      "tgn:2001702",
      "tgn:7012149",
      "tgn:7007708",
      "tgn:7029392"
    ],
    "placetype": [
      "aat:300008680"
    ],
    "id": 2267644,
    "name:xx": "Croft Lake"
  }
}
