{
  "type": "FeatureCollection",
  "features": [
    {
      "geometry": {
        "type": "Point",
        "coordinates": [
          -122.3833,
          43.55
        ]
      },
      "type": "Feature",
      "properties": {
        "hierarchy": [
          "tgn:2522280",
          "tgn:1000001",
          "tgn:7012149",
          "tgn:2001716",
          "tgn:7007708",
          "tgn:7029392"
        ],
        "placetype": [
          "aat:300008680"
        ],
        "id": 2522280,
        "name:xx": "Moon Lake"
      }
    },
    {
      "geometry": {
        "type": "Point",
        "coordinates": [
          -117.3167,
          45.1333
        ]
      },
      "type": "Feature",
      "properties": {
        "hierarchy": [
          "tgn:2522281",
          "tgn:1000001",
          "tgn:7012149",
          "tgn:2001721",
          "tgn:7007708",
          "tgn:7029392"
        ],
        "placetype": [
          "aat:300008680"
        ],
        "id": 2522281,
        "name:xx": "Moon Lake"
      }
    },
    {
      "geometry": {
        "type": "Point",
        "coordinates": [
          -76.0333,
          41.25
        ]
      },
      "type": "Feature",
      "properties": {
        "hierarchy": [
          "tgn:2522282",
          "tgn:1000001",
          "tgn:7012149",
          "tgn:1002612",
          "tgn:7007710",
          "tgn:7029392"
        ],
        "placetype": [
          "aat:300008680"
        ],
        "id": 2522282,
        "name:xx": "Moon Lake"
      }
    },
    {
      "geometry": {
        "type": "Point",
        "coordinates": [
          -89.2667,
          35.5167
        ]
      },
      "type": "Feature",
      "properties": {
        "hierarchy": [
          "tgn:2522283",
          "tgn:1000001",
          "tgn:7012149",
          "tgn:2001874",
          "tgn:7007825",
          "tgn:7029392"
        ],
        "placetype": [
          "aat:300008680"
        ],
        "id": 2522283,
        "name:xx": "Moon Lake"
      }
    },
    {
      "geometry": {
        "type": "Point",
        "coordinates": [
          -97.95,
          26.05
        ]
      },
      "type": "Feature",
      "properties": {
        "hierarchy": [
          "tgn:2522284",
          "tgn:1000001",
          "tgn:7012149",
          "tgn:2001974",
          "tgn:7007826",
          "tgn:7029392"
        ],
        "placetype": [
          "aat:300008680"
        ],
        "id": 2522284,
        "name:xx": "Moon Lake"
      }
    },
    {
      "geometry": {
        "type": "Point",
        "coordinates": [
          -94.1667,
          30.9
        ]
      },
      "type": "Feature",
      "properties": {
        "hierarchy": [
          "tgn:2522285",
          "tgn:1000001",
          "tgn:7012149",
          "tgn:2002009",
          "tgn:7007826",
          "tgn:7029392"
        ],
        "placetype": [
          "aat:300008680"
        ],
        "id": 2522285,
        "name:xx": "Moon Lake"
      }
    },
    {
      "geometry": {
        "type": "Point",
        "coordinates": [
          -110.4833,
          40.55
        ]
      },
      "type": "Feature",
      "properties": {
        "hierarchy": [
          "tgn:2522286",
          "tgn:1000001",
          "tgn:2002107",
          "tgn:7012149",
          "tgn:7007827",
          "tgn:7029392"
        ],
        "placetype": [
          "aat:300006191"
        ],
        "id": 2522286,
        "name:xx": "Moon Lake"
      }
    },
    {
      "geometry": {
        "type": "Point",
        "coordinates": [
          -122.8167,
          47.9833
        ]
      },
      "type": "Feature",
      "properties": {
        "hierarchy": [
          "tgn:2522287",
          "tgn:1000001",
          "tgn:7012149",
          "tgn:1002521",
          "tgn:7007920",
          "tgn:7029392"
        ],
        "placetype": [
          "aat:300008680"
        ],
        "id": 2522287,
        "name:xx": "Moon Lake"
      }
    },
    {
      "geometry": {
        "type": "Point",
        "coordinates": [
          -89.35,
          43.8
        ]
      },
      "type": "Feature",
      "properties": {
        "hierarchy": [
          "tgn:2522288",
          "tgn:1000001",
          "tgn:7012149",
          "tgn:2002338",
          "tgn:7007922",
          "tgn:7029392"
        ],
        "placetype": [
          "aat:300008680"
        ],
        "id": 2522288,
        "name:xx": "Moon Lake"
      }
    },
    {
      "geometry": {
        "type": "Point",
        "coordinates": [
          -91.35,
          45.1667
        ]
      },
      "type": "Feature",
      "properties": {
        "hierarchy": [
          "tgn:2522289",
          "tgn:1000001",
          "tgn:2002313",
          "tgn:7012149",
          "tgn:7007922",
          "tgn:7029392"
        ],
        "placetype": [
          "aat:300008680"
        ],
        "id": 2522289,
        "name:xx": "Moon Lake"
      }
    }
  ]
}
