{
  "geometry": {
    "type": "Point",
    "coordinates": [
      -79.3333,
      40.2833
    ]
  },
  "type": "Feature",
  "properties": {
    "hierarchy": [
      "tgn:2475217",
      "tgn:1000001",
      "tgn:7012149",
      "tgn:1003017",
      "tgn:7007710",
      "tgn:7029392"
    ],
    "placetype": [
      "aat:300008761"
    ],
    "id": 2475217,
    "name:xx": "Loyalhanna Gorge"
  }
}
