{
  "geometry": {
    "type": "Point",
    "coordinates": [
      -77.1333,
      -11.75
    ]
  },
  "type": "Feature",
  "properties": {
    "hierarchy": [
      "tgn:1024357",
      "tgn:1000670",
      "tgn:1000002",
      "tgn:1000056",
      "tgn:7029392"
    ],
    "placetype": [
      "aat:300008347"
    ],
    "id": 1024357,
    "name:xx": "Ancón"
  }
}
