{
  "geometry": {
    "type": "Point",
    "coordinates": [
      -133.4333,
      55.4833
    ]
  },
  "type": "Feature",
  "properties": {
    "hierarchy": [
      "tgn:2589735",
      "tgn:7006450",
      "tgn:1000001",
      "tgn:7012149",
      "tgn:2000082",
      "tgn:7029392"
    ],
    "placetype": [
      "aat:300008850"
    ],
    "id": 2589735,
    "name:xx": "Point Saint Thomas"
  }
}
