{
  "geometry": {
    "type": "Point",
    "coordinates": [
      -113.2667,
      37.7833
    ]
  },
  "type": "Feature",
  "properties": {
    "hierarchy": [
      "tgn:2731242",
      "tgn:1000001",
      "tgn:7012149",
      "tgn:2002111",
      "tgn:7007827",
      "tgn:7029392"
    ],
    "placetype": [
      "aat:300008850"
    ],
    "id": 2731242,
    "name:xx": "Tucker Point"
  }
}
