{
  "geometry": {
    "type": "Point",
    "coordinates": [
      -122.4833,
      44.4667
    ]
  },
  "type": "Feature",
  "properties": {
    "hierarchy": [
      "tgn:2765323",
      "tgn:1000001",
      "tgn:7012149",
      "tgn:2001717",
      "tgn:7007708",
      "tgn:7029392"
    ],
    "placetype": [
      "aat:300008791"
    ],
    "id": 2765323,
    "name:xx": "Whitcomb Island"
  }
}
