{
  "geometry": {
    "type": "Point",
    "coordinates": [
      76.686008,
      30.15176
    ]
  },
  "type": "Feature",
  "properties": {
    "hierarchy": [
      "tgn:7584525",
      "tgn:1000004",
      "tgn:1001871",
      "tgn:7000198",
      "tgn:7029392"
    ],
    "placetype": [
      "aat:300008347"
    ],
    "name:en": "Mājri",
    "id": 7584525
  }
}
