{
  "geometry": {
    "type": "Point",
    "coordinates": [
      -75.0333,
      43.4167
    ]
  },
  "type": "Feature",
  "properties": {
    "hierarchy": [
      "tgn:2138737",
      "tgn:1000001",
      "tgn:7012149",
      "tgn:1002472",
      "tgn:7007568",
      "tgn:7029392"
    ],
    "placetype": [
      "aat:300266640"
    ],
    "id": 2138737,
    "name:xx": "Ash Ridge"
  }
}
