{
  "geometry": {
    "type": "Point",
    "coordinates": [
      -119.6333,
      48.9833
    ]
  },
  "type": "Feature",
  "properties": {
    "hierarchy": [
      "tgn:2131989",
      "tgn:1000001",
      "tgn:7012149",
      "tgn:1002742",
      "tgn:7007920",
      "tgn:7029392"
    ],
    "placetype": [
      "aat:300008798"
    ],
    "id": 2131989,
    "name:xx": "American Butte"
  }
}
