{
  "geometry": {
    "type": "Point",
    "coordinates": [
      -109.4333,
      47.35
    ]
  },
  "type": "Feature",
  "properties": {
    "hierarchy": [
      "tgn:2509363",
      "tgn:1000001",
      "tgn:7012149",
      "tgn:2001273",
      "tgn:7007524",
      "tgn:7029392"
    ],
    "placetype": [
      "aat:300008706"
    ],
    "id": 2509363,
    "name:xx": "Middle Fork Salt Creek"
  }
}
