{
  "type": "FeatureCollection",
  "features": [
    {
      "geometry": {
        "type": "Point",
        "coordinates": [
          -90.2833,
          30.6667
        ]
      },
      "type": "Feature",
      "properties": {
        "hierarchy": [
          "tgn:2205240",
          "tgn:1000001",
          "tgn:7012149",
          "tgn:7007256",
          "tgn:7029392"
        ],
        "placetype": [
          "aat:300008699"
        ],
        "id": 2205240,
        "name:xx": "Bull Branch"
      }
    },
    {
      "geometry": {
        "type": "Point",
        "coordinates": [
          -70.9833,
          44.5333
        ]
      },
      "type": "Feature",
      "properties": {
        "hierarchy": [
          "tgn:2205241",
          "tgn:1000001",
          "tgn:7012149",
          "tgn:2000926",
          "tgn:7007515",
          "tgn:7029392"
        ],
        "placetype": [
          "aat:300008699"
        ],
        "id": 2205241,
        "name:xx": "Bull Branch"
      }
    },
    {
      "geometry": {
        "type": "Point",
        "coordinates": [
          -88.8,
          31.25
        ]
      },
      "type": "Feature",
      "properties": {
        "hierarchy": [
          "tgn:2205242",
          "tgn:1000001",
          "tgn:7012149",
          "tgn:2001106",
          "tgn:7007522",
          "tgn:7029392"
        ],
        "placetype": [
          "aat:300008699"
        ],
        "id": 2205242,
        "name:xx": "Bull Branch"
      }
    },
    {
      "geometry": {
        "type": "Point",
        "coordinates": [
          -88.9167,
          31.65
        ]
      },
      "type": "Feature",
      "properties": {
        "hierarchy": [
          "tgn:2205243",
          "tgn:1000001",
          "tgn:7012149",
          "tgn:2001162",
          "tgn:7007522",
          "tgn:7029392"
        ],
        "placetype": [
          "aat:300008699"
        ],
        "id": 2205243,
        "name:xx": "Bull Branch"
      }
    },
    {
      "geometry": {
        "type": "Point",
        "coordinates": [
          -91.6833,
          38.8
        ]
      },
      "type": "Feature",
      "properties": {
        "hierarchy": [
          "tgn:2205244",
          "tgn:1000001",
          "tgn:1002223",
          "tgn:7012149",
          "tgn:7007523",
          "tgn:7029392"
        ],
        "placetype": [
          "aat:300008699"
        ],
        "id": 2205244,
        "name:xx": "Bull Branch"
      }
    },
    {
      "geometry": {
        "type": "Point",
        "coordinates": [
          -92.9667,
          40.0333
        ]
      },
      "type": "Feature",
      "properties": {
        "hierarchy": [
          "tgn:2205245",
          "tgn:1000001",
          "tgn:7012149",
          "tgn:7007523",
          "tgn:7029392"
        ],
        "placetype": [
          "aat:300008699"
        ],
        "id": 2205245,
        "name:xx": "Bull Branch"
      }
    },
    {
      "geometry": {
        "type": "Point",
        "coordinates": [
          -78.0667,
          34.6833
        ]
      },
      "type": "Feature",
      "properties": {
        "hierarchy": [
          "tgn:2205246",
          "tgn:1000001",
          "tgn:7012149",
          "tgn:2001527",
          "tgn:7007709",
          "tgn:7029392"
        ],
        "placetype": [
          "aat:300008699"
        ],
        "id": 2205246,
        "name:xx": "Bull Branch"
      }
    },
    {
      "geometry": {
        "type": "Point",
        "coordinates": [
          -78.2333,
          34.9
        ]
      },
      "type": "Feature",
      "properties": {
        "hierarchy": [
          "tgn:2205247",
          "tgn:1000001",
          "tgn:7012149",
          "tgn:2001538",
          "tgn:7007709",
          "tgn:7029392"
        ],
        "placetype": [
          "aat:300008699"
        ],
        "id": 2205247,
        "name:xx": "Bull Branch"
      }
    },
    {
      "geometry": {
        "type": "Point",
        "coordinates": [
          -80.4167,
          35
        ]
      },
      "type": "Feature",
      "properties": {
        "hierarchy": [
          "tgn:2205248",
          "tgn:1000001",
          "tgn:7012149",
          "tgn:2001546",
          "tgn:7007709",
          "tgn:7029392"
        ],
        "placetype": [
          "aat:300008699"
        ],
        "id": 2205248,
        "name:xx": "Bull Branch"
      }
    },
    {
      "geometry": {
        "type": "Point",
        "coordinates": [
          -77.55,
          35.0667
        ]
      },
      "type": "Feature",
      "properties": {
        "hierarchy": [
          "tgn:2205249",
          "tgn:1000001",
          "tgn:7012149",
          "tgn:2001510",
          "tgn:7007709",
          "tgn:7029392"
        ],
        "placetype": [
          "aat:300008699"
        ],
        "id": 2205249,
        "name:xx": "Bull Branch"
      }
    }
  ]
}
