{
  "geometry": {
    "type": "Point",
    "coordinates": [
      -77.0667,
      35.3333
    ]
  },
  "type": "Feature",
  "properties": {
    "hierarchy": [
      "tgn:2497002",
      "tgn:1000001",
      "tgn:7012149",
      "tgn:2001486",
      "tgn:7007709",
      "tgn:7029392"
    ],
    "placetype": [
      "aat:300008699"
    ],
    "id": 2497002,
    "name:xx": "Mauls Swamp"
  }
}
