{
  "geometry": {
    "type": "Point",
    "coordinates": [
      -58.65,
      -34.45
    ]
  },
  "type": "Feature",
  "properties": {
    "hierarchy": [
      "tgn:1019421",
      "tgn:1001160",
      "tgn:7006477",
      "tgn:1000002",
      "tgn:7029392"
    ],
    "placetype": [
      "aat:300008347"
    ],
    "id": 1019421,
    "name:xx": "El Talar"
  }
}
