{
  "geometry": {
    "type": "Point",
    "coordinates": [
      -98.65,
      35.9167
    ]
  },
  "type": "Feature",
  "properties": {
    "hierarchy": [
      "tgn:2541746",
      "tgn:1000001",
      "tgn:7012149",
      "tgn:7007707",
      "tgn:7029392"
    ],
    "placetype": [
      "aat:300008706"
    ],
    "id": 2541746,
    "name:xx": "Ninemile Creek"
  }
}
