{
  "geometry": {
    "type": "Point",
    "coordinates": [
      -89.0833,
      35.1833
    ]
  },
  "type": "Feature",
  "properties": {
    "hierarchy": [
      "tgn:2100367",
      "tgn:1000001",
      "tgn:7012149",
      "tgn:2001871",
      "tgn:7007825",
      "tgn:7029392"
    ],
    "placetype": [
      "aat:300008347",
      "aat:300387210"
    ],
    "id": 2100367,
    "name:xx": "Middleburg"
  }
}
