{
  "geometry": {
    "type": "Point",
    "coordinates": [
      -123.1167,
      38.5333
    ]
  },
  "type": "Feature",
  "properties": {
    "hierarchy": [
      "tgn:2169872",
      "tgn:1000001",
      "tgn:7012149",
      "tgn:7007157",
      "tgn:7014516",
      "tgn:7029392"
    ],
    "placetype": [
      "aat:300008798"
    ],
    "id": 2169872,
    "name:xx": "Big Oat Mountain"
  }
}
