{
  "geometry": {
    "type": "Point",
    "coordinates": [
      -111.8333,
      45.0167
    ]
  },
  "type": "Feature",
  "properties": {
    "hierarchy": [
      "tgn:2366685",
      "tgn:1000001",
      "tgn:7012149",
      "tgn:2001288",
      "tgn:7007524",
      "tgn:7029392"
    ],
    "placetype": [
      "aat:300008761"
    ],
    "id": 2366685,
    "name:xx": "Grindstone Gulch"
  }
}
