{
  "geometry": {
    "type": "Point",
    "coordinates": [
      -98.9333,
      41.7833
    ]
  },
  "type": "Feature",
  "properties": {
    "hierarchy": [
      "tgn:2379645",
      "tgn:1000001",
      "tgn:7012149",
      "tgn:2001403",
      "tgn:7007525",
      "tgn:7029392"
    ],
    "placetype": [
      "aat:300008706"
    ],
    "id": 2379645,
    "name:xx": "Haskell Creek"
  }
}
