{
  "geometry": {
    "type": "Point",
    "coordinates": [
      -91.9667,
      31.3667
    ]
  },
  "type": "Feature",
  "properties": {
    "hierarchy": [
      "tgn:2298202",
      "tgn:1000001",
      "tgn:2000866",
      "tgn:7012149",
      "tgn:7007256",
      "tgn:7029392"
    ],
    "placetype": [
      "aat:300008791"
    ],
    "id": 2298202,
    "name:xx": "Dry Larto Island"
  }
}
