{
  "geometry": {
    "type": "Point",
    "coordinates": [
      -65.25,
      -20.6333
    ]
  },
  "type": "Feature",
  "properties": {
    "hierarchy": [
      "tgn:1020263",
      "tgn:1000571",
      "tgn:1000046",
      "tgn:1000002",
      "tgn:7029392"
    ],
    "placetype": [
      "aat:300008347"
    ],
    "id": 1020263,
    "name:xx": "Camargo"
  }
}
