{
  "type": "FeatureCollection",
  "features": [
    {
      "geometry": {
        "type": "Point",
        "coordinates": [
          -75.95,
          42.95
        ]
      },
      "type": "Feature",
      "properties": {
        "hierarchy": [
          "tgn:2379960",
          "tgn:1000001",
          "tgn:7012149",
          "tgn:1002746",
          "tgn:7007568",
          "tgn:7029392"
        ],
        "placetype": [
          "aat:300008761"
        ],
        "id": 2379960,
        "name:xx": "Hatch Gulf"
      }
    },
    {
      "geometry": {
        "type": "Point",
        "coordinates": [
          -70.8833,
          44.15
        ]
      },
      "type": "Feature",
      "properties": {
        "hierarchy": [
          "tgn:2379961",
          "tgn:1000001",
          "tgn:7012149",
          "tgn:2000926",
          "tgn:7007515",
          "tgn:7029392"
        ],
        "placetype": [
          "aat:300008798"
        ],
        "id": 2379961,
        "name:xx": "Hatch Hill"
      }
    },
    {
      "geometry": {
        "type": "Point",
        "coordinates": [
          -69.1167,
          45.0667
        ]
      },
      "type": "Feature",
      "properties": {
        "hierarchy": [
          "tgn:2379962",
          "tgn:1000001",
          "tgn:7012149",
          "tgn:2000927",
          "tgn:7007515",
          "tgn:7029392"
        ],
        "placetype": [
          "aat:300008798"
        ],
        "id": 2379962,
        "name:xx": "Hatch Hill"
      }
    },
    {
      "geometry": {
        "type": "Point",
        "coordinates": [
          -77.3833,
          42.6
        ]
      },
      "type": "Feature",
      "properties": {
        "hierarchy": [
          "tgn:2379963",
          "tgn:1000001",
          "tgn:7012149",
          "tgn:1002747",
          "tgn:7007568",
          "tgn:7029392"
        ],
        "placetype": [
          "aat:300008798"
        ],
        "id": 2379963,
        "name:xx": "Hatch Hill"
      }
    },
    {
      "geometry": {
        "type": "Point",
        "coordinates": [
          -73.3167,
          43.5
        ]
      },
      "type": "Feature",
      "properties": {
        "hierarchy": [
          "tgn:2379964",
          "tgn:1000001",
          "tgn:7012149",
          "tgn:1002993",
          "tgn:7007568",
          "tgn:7029392"
        ],
        "placetype": [
          "aat:300008798"
        ],
        "id": 2379964,
        "name:xx": "Hatch Hill"
      }
    },
    {
      "geometry": {
        "type": "Point",
        "coordinates": [
          -90.7333,
          39.7
        ]
      },
      "type": "Feature",
      "properties": {
        "hierarchy": [
          "tgn:2379965",
          "tgn:1000001",
          "tgn:7012149",
          "tgn:1002786",
          "tgn:7007251",
          "tgn:7029392"
        ],
        "placetype": [
          "aat:300008761"
        ],
        "id": 2379965,
        "name:xx": "Hatch Hollow"
      }
    },
    {
      "geometry": {
        "type": "Point",
        "coordinates": [
          -119.05,
          37.0833
        ]
      },
      "type": "Feature",
      "properties": {
        "hierarchy": [
          "tgn:2379966",
          "tgn:1000001",
          "tgn:7012149",
          "tgn:1002392",
          "tgn:7007157",
          "tgn:7029392"
        ],
        "placetype": [
          "aat:300008680"
        ],
        "id": 2379966,
        "name:xx": "Hatch Lake"
      }
    },
    {
      "geometry": {
        "type": "Point",
        "coordinates": [
          -84.6833,
          44.8833
        ]
      },
      "type": "Feature",
      "properties": {
        "hierarchy": [
          "tgn:2379967",
          "tgn:1000001",
          "tgn:7012149",
          "tgn:2000989",
          "tgn:7007520",
          "tgn:7029392"
        ],
        "placetype": [
          "aat:300008680"
        ],
        "id": 2379967,
        "name:xx": "Hatch Lake"
      }
    },
    {
      "geometry": {
        "type": "Point",
        "coordinates": [
          -93.4667,
          44.5
        ]
      },
      "type": "Feature",
      "properties": {
        "hierarchy": [
          "tgn:2379968",
          "tgn:1000001",
          "tgn:7012149",
          "tgn:2001064",
          "tgn:7007521",
          "tgn:7029392"
        ],
        "placetype": [
          "aat:300008680"
        ],
        "id": 2379968,
        "name:xx": "Hatch Lake"
      }
    },
    {
      "geometry": {
        "type": "Point",
        "coordinates": [
          -93.75,
          47.65
        ]
      },
      "type": "Feature",
      "properties": {
        "hierarchy": [
          "tgn:2379969",
          "tgn:1000001",
          "tgn:7012149",
          "tgn:2001029",
          "tgn:7007521",
          "tgn:7029392"
        ],
        "placetype": [
          "aat:300008680"
        ],
        "id": 2379969,
        "name:xx": "Hatch Lake"
      }
    }
  ]
}
