{
  "geometry": {
    "type": "Point",
    "coordinates": [
      -123.25,
      44.6167
    ]
  },
  "type": "Feature",
  "properties": {
    "hierarchy": [
      "tgn:2266886",
      "tgn:1000001",
      "tgn:2001701",
      "tgn:7012149",
      "tgn:7007708",
      "tgn:7029392"
    ],
    "placetype": [
      "aat:300055621"
    ],
    "id": 2266886,
    "name:xx": "Crescent Valley"
  }
}
