{
  "geometry": {
    "type": "Point",
    "coordinates": [
      -104.4833,
      37.8167
    ]
  },
  "type": "Feature",
  "properties": {
    "hierarchy": [
      "tgn:2713952",
      "tgn:1000001",
      "tgn:7012149",
      "tgn:2000219",
      "tgn:7007158",
      "tgn:7029392"
    ],
    "placetype": [
      "aat:300006191"
    ],
    "id": 2713952,
    "name:xx": "Teeple Reservoir"
  }
}
