{
  "geometry": {
    "type": "Point",
    "coordinates": [
      -160.9833,
      62.0333
    ]
  },
  "type": "Feature",
  "properties": {
    "hierarchy": [
      "tgn:2409783",
      "tgn:7006450",
      "tgn:1000001",
      "tgn:7012149",
      "tgn:7029392"
    ],
    "placetype": [
      "aat:300386831"
    ],
    "id": 2409783,
    "name:xx": "Ilivit Mountains"
  }
}
