{
  "geometry": {
    "type": "Point",
    "coordinates": [
      -56.4333,
      -34.4167
    ]
  },
  "type": "Feature",
  "properties": {
    "hierarchy": [
      "tgn:1024908",
      "tgn:1000747",
      "tgn:1000002",
      "tgn:1000058",
      "tgn:7029392"
    ],
    "placetype": [
      "aat:300008347"
    ],
    "id": 1024908,
    "name:xx": "Ituzaingó"
  }
}
