{
  "geometry": {
    "type": "Point",
    "coordinates": [
      29.416667,
      28.583333
    ]
  },
  "type": "Feature",
  "properties": {
    "hierarchy": [
      "tgn:7537566",
      "tgn:7001242",
      "tgn:7016833",
      "tgn:1001083",
      "tgn:7029392"
    ],
    "placetype": [
      "aat:300386891"
    ],
    "name:en": "Nāshifah, Ḩaţīyat an",
    "id": 7537566
  }
}
