{
  "geometry": {
    "type": "Point",
    "coordinates": [
      -112.4333,
      34.4833
    ]
  },
  "type": "Feature",
  "properties": {
    "hierarchy": [
      "tgn:2739978",
      "tgn:1000001",
      "tgn:7006451",
      "tgn:7012149",
      "tgn:2000103",
      "tgn:7029392"
    ],
    "placetype": [
      "aat:300006191"
    ],
    "id": 2739978,
    "name:xx": "Upper Goldwater Lake"
  }
}
