{
  "geometry": {
    "type": "Point",
    "coordinates": [
      -73.45,
      42.8333
    ]
  },
  "type": "Feature",
  "properties": {
    "hierarchy": [
      "tgn:2068148",
      "tgn:1000001",
      "tgn:7012149",
      "tgn:1002821",
      "tgn:7007568",
      "tgn:7029392"
    ],
    "placetype": [
      "aat:300008347",
      "aat:300387210"
    ],
    "id": 2068148,
    "name:xx": "Boyntonville"
  }
}
