{
  "geometry": {
    "type": "Point",
    "coordinates": [
      30.6167,
      -7.35
    ]
  },
  "type": "Feature",
  "properties": {
    "hierarchy": [
      "tgn:1094760",
      "tgn:7001242",
      "tgn:1001739",
      "tgn:1000203",
      "tgn:7029392"
    ],
    "placetype": [
      "aat:300008347"
    ],
    "id": 1094760,
    "name:xx": "Mtakuja"
  }
}
