{
  "geometry": {
    "type": "Point",
    "coordinates": [
      -88.25,
      44.05
    ]
  },
  "type": "Feature",
  "properties": {
    "hierarchy": [
      "tgn:2697137",
      "tgn:1000001",
      "tgn:2002312",
      "tgn:7012149",
      "tgn:7007922",
      "tgn:7029392"
    ],
    "placetype": [
      "aat:300008699"
    ],
    "id": 2697137,
    "name:xx": "Stony Brook"
  }
}
