{
  "geometry": {
    "type": "Point",
    "coordinates": [
      -82.45,
      35.2333
    ]
  },
  "type": "Feature",
  "properties": {
    "hierarchy": [
      "tgn:2744336",
      "tgn:1000001",
      "tgn:7012149",
      "tgn:2001504",
      "tgn:7007709",
      "tgn:7029392"
    ],
    "placetype": [
      "aat:300008706"
    ],
    "id": 2744336,
    "name:xx": "Vernon Creek"
  }
}
