{
  "geometry": {
    "type": "Point",
    "coordinates": [
      -88.0333,
      46.05
    ]
  },
  "type": "Feature",
  "properties": {
    "hierarchy": [
      "tgn:2710492",
      "tgn:1000001",
      "tgn:2000956",
      "tgn:7012149",
      "tgn:7007520",
      "tgn:7029392"
    ],
    "placetype": [
      "aat:300008680"
    ],
    "id": 2710492,
    "name:xx": "Tamarack Lake"
  }
}
