{
  "geometry": {
    "type": "Point",
    "coordinates": [
      29.853783,
      30.625424
    ]
  },
  "type": "Feature",
  "properties": {
    "hierarchy": [
      "tgn:7534010",
      "tgn:7001242",
      "tgn:7016833",
      "tgn:1001418",
      "tgn:7029392"
    ],
    "placetype": [
      "aat:300008777"
    ],
    "name:en": "Ḩarīr, 'Alam al",
    "id": 7534010
  }
}
