{
  "geometry": {
    "type": "Point",
    "coordinates": [
      -87.7333,
      35.5333
    ]
  },
  "type": "Feature",
  "properties": {
    "hierarchy": [
      "tgn:2754507",
      "tgn:1000001",
      "tgn:7012149",
      "tgn:2001904",
      "tgn:7007825",
      "tgn:7029392"
    ],
    "placetype": [
      "aat:300008761"
    ],
    "id": 2754507,
    "name:xx": "Waxtree Hollow"
  }
}
