{
  "geometry": {
    "type": "Point",
    "coordinates": [
      -83.65,
      44.2167
    ]
  },
  "type": "Feature",
  "properties": {
    "hierarchy": [
      "tgn:2502907",
      "tgn:1000001",
      "tgn:7012149",
      "tgn:2000965",
      "tgn:7007520",
      "tgn:7029392"
    ],
    "placetype": [
      "aat:300008699"
    ],
    "id": 2502907,
    "name:xx": "McMullen Drain"
  }
}
