{
  "geometry": {
    "type": "Point",
    "coordinates": [
      -83.05,
      37.0667
    ]
  },
  "type": "Feature",
  "properties": {
    "hierarchy": [
      "tgn:2757038",
      "tgn:1000001",
      "tgn:7012149",
      "tgn:2000812",
      "tgn:7007255",
      "tgn:7029392"
    ],
    "placetype": [
      "aat:300008347"
    ],
    "id": 2757038,
    "name:xx": "Wentz"
  }
}
