{
  "geometry": {
    "type": "Point",
    "coordinates": [
      -82.6167,
      35.3333
    ]
  },
  "type": "Feature",
  "properties": {
    "hierarchy": [
      "tgn:2183693",
      "tgn:1000001",
      "tgn:7012149",
      "tgn:2001504",
      "tgn:7007709",
      "tgn:7029392"
    ],
    "placetype": [
      "aat:300008706"
    ],
    "id": 2183693,
    "name:xx": "Blythe Mill Creek"
  }
}
