{
  "geometry": {
    "type": "Point",
    "coordinates": [
      -116.65,
      47.45
    ]
  },
  "type": "Feature",
  "properties": {
    "hierarchy": [
      "tgn:2176503",
      "tgn:1000001",
      "tgn:7012149",
      "tgn:2000479",
      "tgn:7007250",
      "tgn:7029392"
    ],
    "placetype": [
      "aat:300006191"
    ],
    "id": 2176503,
    "name:xx": "Black Lake"
  }
}
