{
  "geometry": {
    "type": "Point",
    "coordinates": [
      -99.8833,
      38.8833
    ]
  },
  "type": "Feature",
  "properties": {
    "hierarchy": [
      "tgn:2037246",
      "tgn:1000001",
      "tgn:7012149",
      "tgn:2000757",
      "tgn:7007254",
      "tgn:7029392"
    ],
    "placetype": [
      "aat:300008347",
      "aat:300387210"
    ],
    "id": 2037246,
    "name:xx": "Trego Center"
  }
}
