{
  "geometry": {
    "type": "Point",
    "coordinates": [
      -113.0667,
      39.7667
    ]
  },
  "type": "Feature",
  "properties": {
    "hierarchy": [
      "tgn:2586164",
      "tgn:1000001",
      "tgn:7012149",
      "tgn:2002112",
      "tgn:7007827",
      "tgn:7029392"
    ],
    "placetype": [
      "aat:300008798"
    ],
    "id": 2586164,
    "name:xx": "Pismire Knolls"
  }
}
