{
  "geometry": {
    "type": "Point",
    "coordinates": [
      -87.4833,
      39.5667
    ]
  },
  "type": "Feature",
  "properties": {
    "hierarchy": [
      "tgn:2583578",
      "tgn:1000001",
      "tgn:7012149",
      "tgn:2000559",
      "tgn:7007252",
      "tgn:7029392"
    ],
    "placetype": [
      "aat:300006191"
    ],
    "id": 2583578,
    "name:xx": "Pine Ridge Mine Pond"
  }
}
