{
  "type": "FeatureCollection",
  "features": [
    {
      "geometry": {
        "type": "Point",
        "coordinates": [
          -4.55,
          55.633333
        ]
      },
      "type": "Feature",
      "properties": {
        "hierarchy": [
          "tgn:7456140",
          "tgn:7002444",
          "tgn:7019088",
          "tgn:1000003",
          "tgn:7008591",
          "tgn:7029392"
        ],
        "placetype": [
          "aat:300008347"
        ],
        "name:en": "Crosshouse",
        "id": 7456140
      }
    },
    {
      "geometry": {
        "type": "Point",
        "coordinates": [
          -3.383333,
          56.066667
        ]
      },
      "type": "Feature",
      "properties": {
        "hierarchy": [
          "tgn:7456143",
          "tgn:7002444",
          "tgn:1000003",
          "tgn:7008076",
          "tgn:7008591",
          "tgn:7029392"
        ],
        "placetype": [
          "aat:300008347"
        ],
        "name:en": "Crossgates",
        "id": 7456143
      }
    },
    {
      "geometry": {
        "type": "Point",
        "coordinates": [
          -1.45,
          53.8
        ]
      },
      "type": "Feature",
      "properties": {
        "hierarchy": [
          "tgn:7456144",
          "tgn:7019038",
          "tgn:7002445",
          "tgn:1000003",
          "tgn:7029507",
          "tgn:7008591",
          "tgn:7029392"
        ],
        "placetype": [
          "aat:300008347"
        ],
        "name:en": "Cross Gates",
        "id": 7456144
      }
    },
    {
      "geometry": {
        "type": "Point",
        "coordinates": [
          -3,
          55.9
        ]
      },
      "type": "Feature",
      "properties": {
        "hierarchy": [
          "tgn:7456145",
          "tgn:7002444",
          "tgn:1000003",
          "tgn:7019123",
          "tgn:7008591",
          "tgn:7029392"
        ],
        "placetype": [
          "aat:300008347"
        ],
        "name:en": "Crossgatehall",
        "id": 7456145
      }
    },
    {
      "geometry": {
        "type": "Point",
        "coordinates": [
          -3.833333,
          52.716667
        ]
      },
      "type": "Feature",
      "properties": {
        "hierarchy": [
          "tgn:7456147",
          "tgn:7002443",
          "tgn:1000003",
          "tgn:7029493",
          "tgn:7008591",
          "tgn:7029392"
        ],
        "placetype": [
          "aat:300008347"
        ],
        "name:en": "Cross Foxes",
        "id": 7456147
      }
    },
    {
      "geometry": {
        "type": "Point",
        "coordinates": [
          -3.5,
          56.05
        ]
      },
      "type": "Feature",
      "properties": {
        "hierarchy": [
          "tgn:7456148",
          "tgn:7002444",
          "tgn:1000003",
          "tgn:7008076",
          "tgn:7008591",
          "tgn:7029392"
        ],
        "placetype": [
          "aat:300008347"
        ],
        "name:en": "Crossford",
        "id": 7456148
      }
    },
    {
      "geometry": {
        "type": "Point",
        "coordinates": [
          -3.866667,
          55.7
        ]
      },
      "type": "Feature",
      "properties": {
        "hierarchy": [
          "tgn:7456149",
          "tgn:7002444",
          "tgn:1000003",
          "tgn:7019090",
          "tgn:7008591",
          "tgn:7029392"
        ],
        "placetype": [
          "aat:300008347"
        ],
        "name:en": "Crossford",
        "id": 7456149
      }
    }
  ]
}
