{
  "type": "FeatureCollection",
  "features": [
    {
      "geometry": {
        "type": "Point",
        "coordinates": [
          -81.4333,
          36.45
        ]
      },
      "type": "Feature",
      "properties": {
        "hierarchy": [
          "tgn:2290760",
          "tgn:2001467",
          "tgn:1000001",
          "tgn:7012149",
          "tgn:7007709",
          "tgn:7029392"
        ],
        "placetype": [
          "aat:300008706"
        ],
        "id": 2290760,
        "name:xx": "Dog Creek"
      }
    },
    {
      "geometry": {
        "type": "Point",
        "coordinates": [
          -94.85,
          35.1
        ]
      },
      "type": "Feature",
      "properties": {
        "hierarchy": [
          "tgn:2290761",
          "tgn:1000001",
          "tgn:7012149",
          "tgn:2001662",
          "tgn:7007707",
          "tgn:7029392"
        ],
        "placetype": [
          "aat:300008347"
        ],
        "id": 2290761,
        "name:xx": "Dog Creek"
      }
    },
    {
      "geometry": {
        "type": "Point",
        "coordinates": [
          -95.25,
          34.2833
        ]
      },
      "type": "Feature",
      "properties": {
        "hierarchy": [
          "tgn:2290762",
          "tgn:1000001",
          "tgn:7012149",
          "tgn:2001686",
          "tgn:7007707",
          "tgn:7029392"
        ],
        "placetype": [
          "aat:300008706"
        ],
        "id": 2290762,
        "name:xx": "Dog Creek"
      }
    },
    {
      "geometry": {
        "type": "Point",
        "coordinates": [
          -96.4833,
          36.8667
        ]
      },
      "type": "Feature",
      "properties": {
        "hierarchy": [
          "tgn:2290763",
          "tgn:1000001",
          "tgn:7012149",
          "tgn:2001679",
          "tgn:7007707",
          "tgn:7029392"
        ],
        "placetype": [
          "aat:300008706"
        ],
        "id": 2290763,
        "name:xx": "Dog Creek"
      }
    },
    {
      "geometry": {
        "type": "Point",
        "coordinates": [
          -94.85,
          34.4667
        ]
      },
      "type": "Feature",
      "properties": {
        "hierarchy": [
          "tgn:2290764",
          "tgn:1000001",
          "tgn:7012149",
          "tgn:2001667",
          "tgn:7007707",
          "tgn:7029392"
        ],
        "placetype": [
          "aat:300008706"
        ],
        "id": 2290764,
        "name:xx": "Dog Creek"
      }
    },
    {
      "geometry": {
        "type": "Point",
        "coordinates": [
          -94.8667,
          35.0167
        ]
      },
      "type": "Feature",
      "properties": {
        "hierarchy": [
          "tgn:2290765",
          "tgn:1000001",
          "tgn:7012149",
          "tgn:2001662",
          "tgn:7007707",
          "tgn:7029392"
        ],
        "placetype": [
          "aat:300008706"
        ],
        "id": 2290765,
        "name:xx": "Dog Creek"
      }
    },
    {
      "geometry": {
        "type": "Point",
        "coordinates": [
          -98.85,
          36.6667
        ]
      },
      "type": "Feature",
      "properties": {
        "hierarchy": [
          "tgn:2290766",
          "tgn:1000001",
          "tgn:7012149",
          "tgn:2001698",
          "tgn:7007707",
          "tgn:7029392"
        ],
        "placetype": [
          "aat:300008706"
        ],
        "id": 2290766,
        "name:xx": "Dog Creek"
      }
    },
    {
      "geometry": {
        "type": "Point",
        "coordinates": [
          -96.5,
          35.9167
        ]
      },
      "type": "Feature",
      "properties": {
        "hierarchy": [
          "tgn:2290767",
          "tgn:1000001",
          "tgn:2001641",
          "tgn:7012149",
          "tgn:7007707",
          "tgn:7029392"
        ],
        "placetype": [
          "aat:300008706"
        ],
        "id": 2290767,
        "name:xx": "Dog Creek"
      }
    },
    {
      "geometry": {
        "type": "Point",
        "coordinates": [
          -95.4333,
          36.4
        ]
      },
      "type": "Feature",
      "properties": {
        "hierarchy": [
          "tgn:2290768",
          "tgn:1000001",
          "tgn:7012149",
          "tgn:2001688",
          "tgn:7007707",
          "tgn:7029392"
        ],
        "placetype": [
          "aat:300008706"
        ],
        "id": 2290768,
        "name:xx": "Dog Creek"
      }
    },
    {
      "geometry": {
        "type": "Point",
        "coordinates": [
          -122.5333,
          42.6
        ]
      },
      "type": "Feature",
      "properties": {
        "hierarchy": [
          "tgn:2290769",
          "tgn:1000001",
          "tgn:7012149",
          "tgn:2001711",
          "tgn:7007708",
          "tgn:7029392"
        ],
        "placetype": [
          "aat:300008706"
        ],
        "id": 2290769,
        "name:xx": "Dog Creek"
      }
    }
  ]
}
