{
  "geometry": {
    "type": "Point",
    "coordinates": [
      -79.0667,
      39.0167
    ]
  },
  "type": "Feature",
  "properties": {
    "hierarchy": [
      "tgn:2408587",
      "tgn:1000001",
      "tgn:7012149",
      "tgn:2002266",
      "tgn:7013961",
      "tgn:7029392"
    ],
    "placetype": [
      "aat:300008699"
    ],
    "id": 2408587,
    "name:xx": "Hutton Run"
  }
}
