{
  "geometry": {
    "type": "Point",
    "coordinates": [
      44.4833,
      -16.7167
    ]
  },
  "type": "Feature",
  "properties": {
    "hierarchy": [
      "tgn:1090868",
      "tgn:7001242",
      "tgn:1001405",
      "tgn:1000173",
      "tgn:7029392"
    ],
    "placetype": [
      "aat:300008347"
    ],
    "id": 1090868,
    "name:xx": "Besalampy"
  }
}
