{
  "geometry": {
    "type": "Point",
    "coordinates": [
      22.75,
      37.15
    ]
  },
  "type": "Feature",
  "properties": {
    "hierarchy": [
      "tgn:7227475",
      "tgn:7002735",
      "tgn:7017076",
      "tgn:1000003",
      "tgn:1000074",
      "tgn:7029392"
    ],
    "placetype": [
      "aat:300008795"
    ],
    "id": 7227475,
    "name:xx": "Longáki"
  }
}
