{
  "geometry": {
    "type": "Point",
    "coordinates": [
      -122.6667,
      47.0167
    ]
  },
  "type": "Feature",
  "properties": {
    "hierarchy": [
      "tgn:2223846",
      "tgn:1000001",
      "tgn:7012149",
      "tgn:1002785",
      "tgn:7007920",
      "tgn:7029392"
    ],
    "placetype": [
      "aat:300132451"
    ],
    "id": 2223846,
    "name:xx": "Carter Woods"
  }
}
