{
  "geometry": {
    "type": "Point",
    "coordinates": [
      -99.3667,
      45.9333
    ]
  },
  "type": "Feature",
  "properties": {
    "hierarchy": [
      "tgn:2473133",
      "tgn:1000001",
      "tgn:2001582",
      "tgn:7012149",
      "tgn:7007705",
      "tgn:7029392"
    ],
    "placetype": [
      "aat:300008347"
    ],
    "id": 2473133,
    "name:xx": "Lowell"
  }
}
