{
  "geometry": {
    "type": "Point",
    "coordinates": [
      -77.1167,
      35.7167
    ]
  },
  "type": "Feature",
  "properties": {
    "hierarchy": [
      "tgn:2401384",
      "tgn:1000001",
      "tgn:7012149",
      "tgn:7007709",
      "tgn:7029392"
    ],
    "placetype": [
      "aat:300008699"
    ],
    "id": 2401384,
    "name:xx": "Horsepen Swamp"
  }
}
