{
  "geometry": {
    "type": "Point",
    "coordinates": [
      -109.4667,
      43.6667
    ]
  },
  "type": "Feature",
  "properties": {
    "hierarchy": [
      "tgn:2211781",
      "tgn:1000001",
      "tgn:7012149",
      "tgn:2002371",
      "tgn:7007923",
      "tgn:7029392"
    ],
    "placetype": [
      "aat:300008761"
    ],
    "id": 2211781,
    "name:xx": "Button Draw"
  }
}
