{
  "geometry": {
    "type": "Point",
    "coordinates": [
      -111.5833,
      53.3333
    ]
  },
  "type": "Feature",
  "properties": {
    "hierarchy": [
      "tgn:1115620",
      "tgn:7005694",
      "tgn:7005685",
      "tgn:1000001",
      "tgn:7029392"
    ],
    "placetype": [
      "aat:300008680"
    ],
    "id": 1115620,
    "name:xx": "Birch Lake"
  }
}
