{
  "type": "FeatureCollection",
  "features": [
    {
      "geometry": {
        "type": "Point",
        "coordinates": [
          -98.1,
          20
        ]
      },
      "type": "Feature",
      "properties": {
        "hierarchy": [
          "tgn:7391810",
          "tgn:1000001",
          "tgn:7005592",
          "tgn:7005560",
          "tgn:7029392"
        ],
        "placetype": [
          "aat:300008347"
        ],
        "id": 7391810,
        "name:xx": "Rancho Viejo"
      }
    },
    {
      "geometry": {
        "type": "Point",
        "coordinates": [
          -105.183333,
          19.783333
        ]
      },
      "type": "Feature",
      "properties": {
        "hierarchy": [
          "tgn:7391811",
          "tgn:7005586",
          "tgn:1000001",
          "tgn:7005560",
          "tgn:7029392"
        ],
        "placetype": [
          "aat:300008347"
        ],
        "id": 7391811,
        "name:xx": "Rancho Viejo"
      }
    },
    {
      "geometry": {
        "type": "Point",
        "coordinates": [
          -97.833333,
          19.783333
        ]
      },
      "type": "Feature",
      "properties": {
        "hierarchy": [
          "tgn:7391812",
          "tgn:1000001",
          "tgn:7005592",
          "tgn:7005560",
          "tgn:7029392"
        ],
        "placetype": [
          "aat:300008347"
        ],
        "id": 7391812,
        "name:xx": "Rancho Viejo"
      }
    },
    {
      "geometry": {
        "type": "Point",
        "coordinates": [
          -96.5,
          19.633333
        ]
      },
      "type": "Feature",
      "properties": {
        "hierarchy": [
          "tgn:7391813",
          "tgn:1000001",
          "tgn:7005599",
          "tgn:7005560",
          "tgn:7029392"
        ],
        "placetype": [
          "aat:300008347"
        ],
        "id": 7391813,
        "name:xx": "Rancho Viejo"
      }
    },
    {
      "geometry": {
        "type": "Point",
        "coordinates": [
          -104.25,
          19.383333
        ]
      },
      "type": "Feature",
      "properties": {
        "hierarchy": [
          "tgn:7391814",
          "tgn:7005586",
          "tgn:1000001",
          "tgn:7005560",
          "tgn:7029392"
        ],
        "placetype": [
          "aat:300008347"
        ],
        "id": 7391814,
        "name:xx": "Rancho Viejo"
      }
    },
    {
      "geometry": {
        "type": "Point",
        "coordinates": [
          -97.45,
          18.916667
        ]
      },
      "type": "Feature",
      "properties": {
        "hierarchy": [
          "tgn:7391815",
          "tgn:1000001",
          "tgn:7005592",
          "tgn:7005560",
          "tgn:7029392"
        ],
        "placetype": [
          "aat:300008347"
        ],
        "id": 7391815,
        "name:xx": "Rancho Viejo"
      }
    },
    {
      "geometry": {
        "type": "Point",
        "coordinates": [
          -96.416667,
          18.866667
        ]
      },
      "type": "Feature",
      "properties": {
        "hierarchy": [
          "tgn:7391816",
          "tgn:1000001",
          "tgn:7005599",
          "tgn:7005560",
          "tgn:7029392"
        ],
        "placetype": [
          "aat:300008347"
        ],
        "id": 7391816,
        "name:xx": "Rancho Viejo"
      }
    },
    {
      "geometry": {
        "type": "Point",
        "coordinates": [
          -102.466667,
          18.516667
        ]
      },
      "type": "Feature",
      "properties": {
        "hierarchy": [
          "tgn:7391817",
          "tgn:1000001",
          "tgn:7005590",
          "tgn:7005560",
          "tgn:7029392"
        ],
        "placetype": [
          "aat:300008347"
        ],
        "id": 7391817,
        "name:xx": "Rancho Viejo"
      }
    },
    {
      "geometry": {
        "type": "Point",
        "coordinates": [
          -99.3,
          17.166667
        ]
      },
      "type": "Feature",
      "properties": {
        "hierarchy": [
          "tgn:7391818",
          "tgn:7005585",
          "tgn:1000001",
          "tgn:7005560",
          "tgn:7029392"
        ],
        "placetype": [
          "aat:300008347"
        ],
        "id": 7391818,
        "name:xx": "Rancho Viejo"
      }
    },
    {
      "geometry": {
        "type": "Point",
        "coordinates": [
          -96.916667,
          16.416667
        ]
      },
      "type": "Feature",
      "properties": {
        "hierarchy": [
          "tgn:7391819",
          "tgn:1000001",
          "tgn:7005591",
          "tgn:7005560",
          "tgn:7029392"
        ],
        "placetype": [
          "aat:300008347"
        ],
        "id": 7391819,
        "name:xx": "Rancho Viejo"
      }
    }
  ]
}
