{
  "geometry": {
    "type": "Point",
    "coordinates": [
      -82.15,
      30.9333
    ]
  },
  "type": "Feature",
  "properties": {
    "hierarchy": [
      "tgn:2525738",
      "tgn:1000001",
      "tgn:2000315",
      "tgn:7012149",
      "tgn:7007248",
      "tgn:7029392"
    ],
    "placetype": [
      "aat:300008680"
    ],
    "id": 2525738,
    "name:xx": "Mose Lake"
  }
}
