{
  "geometry": {
    "type": "Point",
    "coordinates": [
      -95.4333,
      31.7167
    ]
  },
  "type": "Feature",
  "properties": {
    "hierarchy": [
      "tgn:2732790",
      "tgn:1002148",
      "tgn:1000001",
      "tgn:7012149",
      "tgn:7007826",
      "tgn:7029392"
    ],
    "placetype": [
      "aat:300008706"
    ],
    "id": 2732790,
    "name:xx": "Turkey Creek"
  }
}
