{
  "geometry": {
    "type": "Point",
    "coordinates": [
      30.95,
      -10.15
    ]
  },
  "type": "Feature",
  "properties": {
    "hierarchy": [
      "tgn:1095904",
      "tgn:7001242",
      "tgn:1001461",
      "tgn:1000209",
      "tgn:7029392"
    ],
    "placetype": [
      "aat:300008347"
    ],
    "id": 1095904,
    "name:xx": "Chilubula Mission"
  }
}
