{
  "geometry": {
    "type": "Point",
    "coordinates": [
      24.5833,
      47.1667
    ]
  },
  "type": "Feature",
  "properties": {
    "hierarchy": [
      "tgn:1000345",
      "tgn:1000003",
      "tgn:1000091",
      "tgn:7029392"
    ],
    "placetype": [
      "aat:300387064",
      "aat:300000771"
    ],
    "id": 1000345,
    "name:xx": "Bistriţa-Năsăud"
  }
}
