{
  "geometry": {
    "type": "Point",
    "coordinates": [
      30.2833,
      41.05
    ]
  },
  "type": "Feature",
  "properties": {
    "hierarchy": [
      "tgn:1140803",
      "tgn:1001361",
      "tgn:1000004",
      "tgn:7018450",
      "tgn:1000144",
      "tgn:7029392"
    ],
    "placetype": [
      "aat:300008347"
    ],
    "id": 1140803,
    "name:xx": "Hocaköy"
  }
}
