{
  "geometry": {
    "type": "Point",
    "coordinates": [
      1.2667,
      48.0167
    ]
  },
  "type": "Feature",
  "properties": {
    "hierarchy": [
      "tgn:1131958",
      "tgn:1000003",
      "tgn:1000070",
      "tgn:7029392"
    ],
    "placetype": [
      "aat:300008707"
    ],
    "id": 1131958,
    "name:xx": "Yèrre"
  }
}
