{
  "geometry": {
    "type": "Point",
    "coordinates": [
      -92.2333,
      35.85
    ]
  },
  "type": "Feature",
  "properties": {
    "hierarchy": [
      "tgn:2662672",
      "tgn:1000001",
      "tgn:7016172",
      "tgn:7012149",
      "tgn:2000173",
      "tgn:7029392"
    ],
    "placetype": [
      "aat:300008761"
    ],
    "id": 2662672,
    "name:xx": "Signboard Hollow"
  }
}
