{
  "geometry": {
    "type": "Point",
    "coordinates": [
      84.766667,
      19.533333
    ]
  },
  "type": "Feature",
  "properties": {
    "hierarchy": [
      "tgn:7547829",
      "tgn:1000004",
      "tgn:7000198",
      "tgn:7016694",
      "tgn:7029392"
    ],
    "placetype": [
      "aat:300008699"
    ],
    "name:en": "Bhāguva Nadī",
    "id": 7547829
  }
}
