{
  "geometry": {
    "type": "Point",
    "coordinates": [
      -70.9167,
      44.8667
    ]
  },
  "type": "Feature",
  "properties": {
    "hierarchy": [
      "tgn:2757315",
      "tgn:1000001",
      "tgn:7012149",
      "tgn:2000926",
      "tgn:7007515",
      "tgn:7029392"
    ],
    "placetype": [
      "aat:300132316"
    ],
    "id": 2757315,
    "name:xx": "West Arm Upper Richardson Lake"
  }
}
