{
  "geometry": {
    "type": "Point",
    "coordinates": [
      117.2667,
      8.5833
    ]
  },
  "type": "Feature",
  "properties": {
    "hierarchy": [
      "tgn:1084115",
      "tgn:1000004",
      "tgn:1001481",
      "tgn:1000135",
      "tgn:7029392"
    ],
    "placetype": [
      "aat:300008347"
    ],
    "id": 1084115,
    "name:xx": "Canipaan"
  }
}
