{
  "type": "FeatureCollection",
  "features": [
    {
      "geometry": {
        "type": "Point",
        "coordinates": [
          12.7,
          50.916667
        ]
      },
      "type": "Feature",
      "properties": {
        "hierarchy": [
          "tgn:7077390",
          "tgn:1000003",
          "tgn:7003685",
          "tgn:7000084",
          "tgn:7029392"
        ],
        "placetype": [
          "aat:300008777"
        ],
        "id": 7077390,
        "name:xx": "Ziegen-Berg"
      }
    },
    {
      "geometry": {
        "type": "Point",
        "coordinates": [
          10.55,
          50.9
        ]
      },
      "type": "Feature",
      "properties": {
        "hierarchy": [
          "tgn:7077391",
          "tgn:1000003",
          "tgn:7003689",
          "tgn:7000084",
          "tgn:7029392"
        ],
        "placetype": [
          "aat:300008777"
        ],
        "id": 7077391,
        "name:xx": "Ziegen-Berg"
      }
    },
    {
      "geometry": {
        "type": "Point",
        "coordinates": [
          7.883333,
          50.866667
        ]
      },
      "type": "Feature",
      "properties": {
        "hierarchy": [
          "tgn:7077392",
          "tgn:1000003",
          "tgn:7003677",
          "tgn:7000084",
          "tgn:7029392"
        ],
        "placetype": [
          "aat:300008777"
        ],
        "id": 7077392,
        "name:xx": "Ziegen-Berg"
      }
    },
    {
      "geometry": {
        "type": "Point",
        "coordinates": [
          9.4,
          50.85
        ]
      },
      "type": "Feature",
      "properties": {
        "hierarchy": [
          "tgn:7077393",
          "tgn:1000003",
          "tgn:7003678",
          "tgn:7000084",
          "tgn:7029392"
        ],
        "placetype": [
          "aat:300008777"
        ],
        "id": 7077393,
        "name:xx": "Ziegen-Berg"
      }
    },
    {
      "geometry": {
        "type": "Point",
        "coordinates": [
          7.2,
          50.85
        ]
      },
      "type": "Feature",
      "properties": {
        "hierarchy": [
          "tgn:7077394",
          "tgn:1000003",
          "tgn:7003677",
          "tgn:7000084",
          "tgn:7029392"
        ],
        "placetype": [
          "aat:300008777"
        ],
        "id": 7077394,
        "name:xx": "Ziegen-Berg"
      }
    },
    {
      "geometry": {
        "type": "Point",
        "coordinates": [
          8.15,
          50.833333
        ]
      },
      "type": "Feature",
      "properties": {
        "hierarchy": [
          "tgn:7077395",
          "tgn:1000003",
          "tgn:7003677",
          "tgn:7000084",
          "tgn:7029392"
        ],
        "placetype": [
          "aat:300008777"
        ],
        "id": 7077395,
        "name:xx": "Ziegen Berg"
      }
    },
    {
      "geometry": {
        "type": "Point",
        "coordinates": [
          8.566667,
          50.816667
        ]
      },
      "type": "Feature",
      "properties": {
        "hierarchy": [
          "tgn:7077396",
          "tgn:1000003",
          "tgn:7003678",
          "tgn:7000084",
          "tgn:7029392"
        ],
        "placetype": [
          "aat:300008777"
        ],
        "id": 7077396,
        "name:xx": "Ziegen-Berg"
      }
    },
    {
      "geometry": {
        "type": "Point",
        "coordinates": [
          13.483333,
          50.733333
        ]
      },
      "type": "Feature",
      "properties": {
        "hierarchy": [
          "tgn:7077397",
          "tgn:1000003",
          "tgn:7003685",
          "tgn:7000084",
          "tgn:7029392"
        ],
        "placetype": [
          "aat:300008777"
        ],
        "id": 7077397,
        "name:xx": "Ziegen-Berg"
      }
    },
    {
      "geometry": {
        "type": "Point",
        "coordinates": [
          10.85,
          50.733333
        ]
      },
      "type": "Feature",
      "properties": {
        "hierarchy": [
          "tgn:7077398",
          "tgn:1000003",
          "tgn:7003689",
          "tgn:7000084",
          "tgn:7029392"
        ],
        "placetype": [
          "aat:300008777"
        ],
        "id": 7077398,
        "name:xx": "Ziegen-Berg"
      }
    },
    {
      "geometry": {
        "type": "Point",
        "coordinates": [
          11.15,
          50.633333
        ]
      },
      "type": "Feature",
      "properties": {
        "hierarchy": [
          "tgn:7077399",
          "tgn:1000003",
          "tgn:7003689",
          "tgn:7000084",
          "tgn:7029392"
        ],
        "placetype": [
          "aat:300008777"
        ],
        "id": 7077399,
        "name:xx": "Ziegen-Berg"
      }
    }
  ]
}
