{
  "geometry": {
    "type": "Point",
    "coordinates": [
      -86.3333,
      34.7167
    ]
  },
  "type": "Feature",
  "properties": {
    "hierarchy": [
      "tgn:2203775",
      "tgn:7002659",
      "tgn:1000001",
      "tgn:7012149",
      "tgn:2000035",
      "tgn:7029392"
    ],
    "placetype": [
      "aat:300386845"
    ],
    "id": 2203775,
    "name:xx": "Bucks Pocket"
  }
}
