{
  "geometry": {
    "type": "Point",
    "coordinates": [
      -91.6167,
      35.8667
    ]
  },
  "type": "Feature",
  "properties": {
    "hierarchy": [
      "tgn:2406705",
      "tgn:1000001",
      "tgn:7016172",
      "tgn:7012149",
      "tgn:2000136",
      "tgn:7029392"
    ],
    "placetype": [
      "aat:300000390"
    ],
    "id": 2406705,
    "name:xx": "Hunt Hollow Mine"
  }
}
