{
  "geometry": {
    "type": "Point",
    "coordinates": [
      -72.9167,
      43.3167
    ]
  },
  "type": "Feature",
  "properties": {
    "hierarchy": [
      "tgn:2719796",
      "tgn:1000001",
      "tgn:1002840",
      "tgn:7012149",
      "tgn:7007828",
      "tgn:7029392"
    ],
    "placetype": [
      "aat:300008699"
    ],
    "id": 2719796,
    "name:xx": "Three Shanties Brook"
  }
}
