{
  "geometry": {
    "type": "Point",
    "coordinates": [
      173.8333,
      0.3333
    ]
  },
  "type": "Feature",
  "properties": {
    "hierarchy": [
      "tgn:1006010",
      "tgn:7002036",
      "tgn:1000217",
      "tgn:1000006",
      "tgn:7029392"
    ],
    "placetype": [
      "aat:300008793"
    ],
    "id": 1006010,
    "name:xx": "Abemama"
  }
}
