{
  "type": "FeatureCollection",
  "features": [
    {
      "geometry": {
        "type": "Point",
        "coordinates": [
          143.5,
          43
        ]
      },
      "type": "Feature",
      "properties": {
        "hierarchy": [
          "tgn:1110980",
          "tgn:1000985",
          "tgn:7016529",
          "tgn:7016531",
          "tgn:1000004",
          "tgn:1000120",
          "tgn:7029392"
        ],
        "placetype": [
          "aat:300008805"
        ],
        "id": 1110980,
        "name:xx": "Tokachi-heiya"
      }
    },
    {
      "geometry": {
        "type": "Point",
        "coordinates": [
          137.25,
          36.6667
        ]
      },
      "type": "Feature",
      "properties": {
        "hierarchy": [
          "tgn:1110981",
          "tgn:7000895",
          "tgn:1000004",
          "tgn:1001037",
          "tgn:1000120",
          "tgn:7029392"
        ],
        "placetype": [
          "aat:300008805"
        ],
        "id": 1110981,
        "name:xx": "Toyama-heiya"
      }
    },
    {
      "geometry": {
        "type": "Point",
        "coordinates": [
          63,
          44.5
        ]
      },
      "type": "Feature",
      "properties": {
        "hierarchy": [
          "tgn:1110984",
          "tgn:1000004",
          "tgn:7029392"
        ],
        "placetype": [
          "aat:300008805"
        ],
        "id": 1110984,
        "name:xx": "Turanskaya Nizmennost"
      }
    },
    {
      "geometry": {
        "type": "Point",
        "coordinates": [
          16.15,
          45.6167
        ]
      },
      "type": "Feature",
      "properties": {
        "hierarchy": [
          "tgn:1110985",
          "tgn:1000003",
          "tgn:7006663",
          "tgn:7029392"
        ],
        "placetype": [
          "aat:300008805"
        ],
        "id": 1110985,
        "name:xx": "Turopolje"
      }
    },
    {
      "geometry": {
        "type": "Point",
        "coordinates": [
          0.6,
          41.416667
        ]
      },
      "type": "Feature",
      "properties": {
        "hierarchy": [
          "tgn:1110986",
          "tgn:7008912",
          "tgn:7030216",
          "tgn:1000003",
          "tgn:1000095",
          "tgn:7029392"
        ],
        "placetype": [
          "aat:300008805"
        ],
        "id": 1110986,
        "name:xx": "Urgel, Llanos de"
      }
    },
    {
      "geometry": {
        "type": "Point",
        "coordinates": [
          88,
          23.5
        ]
      },
      "type": "Feature",
      "properties": {
        "hierarchy": [
          "tgn:1110989",
          "tgn:1000004",
          "tgn:7000198",
          "tgn:1001977",
          "tgn:7029392"
        ],
        "placetype": [
          "aat:300008805"
        ],
        "id": 1110989,
        "name:xx": "West Bhāgīrath Plain"
      }
    }
  ]
}
