{
  "geometry": {
    "type": "Point",
    "coordinates": [
      -106.6333,
      35.0167
    ]
  },
  "type": "Feature",
  "properties": {
    "hierarchy": [
      "tgn:2640482",
      "tgn:1000001",
      "tgn:2001428",
      "tgn:7012149",
      "tgn:7007566",
      "tgn:7029392"
    ],
    "placetype": [
      "aat:300006075"
    ],
    "id": 2640482,
    "name:xx": "San Jose Lateral"
  }
}
