{
  "geometry": {
    "type": "Point",
    "coordinates": [
      -75.75,
      43.15
    ]
  },
  "type": "Feature",
  "properties": {
    "hierarchy": [
      "tgn:2559220",
      "tgn:1000001",
      "tgn:7012149",
      "tgn:1002624",
      "tgn:7007568",
      "tgn:7029392"
    ],
    "placetype": [
      "aat:300008347"
    ],
    "id": 2559220,
    "name:xx": "Oneida Lake Beach East"
  }
}
