{
  "geometry": {
    "type": "Point",
    "coordinates": [
      -81.25,
      28.7667
    ]
  },
  "type": "Feature",
  "properties": {
    "hierarchy": [
      "tgn:2628814",
      "tgn:1000001",
      "tgn:7012149",
      "tgn:1002881",
      "tgn:7007240",
      "tgn:7029392"
    ],
    "placetype": [
      "aat:300008347"
    ],
    "id": 2628814,
    "name:xx": "Rosalind Heights"
  }
}
