{
  "geometry": {
    "type": "Point",
    "coordinates": [
      42.45,
      36.3667
    ]
  },
  "type": "Feature",
  "properties": {
    "hierarchy": [
      "tgn:1079441",
      "tgn:1000004",
      "tgn:1000118",
      "tgn:1001441",
      "tgn:7029392"
    ],
    "placetype": [
      "aat:300008347"
    ],
    "id": 1079441,
    "name:xx": "Tall ʻĀfar"
  }
}
