{
  "geometry": {
    "type": "Point",
    "coordinates": [
      -90.6333,
      34.35
    ]
  },
  "type": "Feature",
  "properties": {
    "hierarchy": [
      "tgn:1121909",
      "tgn:1000001",
      "tgn:7012149",
      "tgn:7007522",
      "tgn:7029392"
    ],
    "placetype": [
      "aat:300008707"
    ],
    "id": 1121909,
    "name:xx": "Big Sunflower"
  }
}
