{
  "type": "FeatureCollection",
  "features": [
    {
      "geometry": {
        "type": "Point",
        "coordinates": [
          -1.5833,
          6.75
        ]
      },
      "type": "Feature",
      "properties": {
        "hierarchy": [
          "tgn:7000570",
          "tgn:1001628",
          "tgn:7001242",
          "tgn:1000166",
          "tgn:7029392"
        ],
        "placetype": [
          "aat:300008347",
          "aat:300387218",
          "aat:300008389",
          "aat:300387512",
          "aat:300387220",
          "aat:300387270",
          "aat:300387285",
          "aat:300387296"
        ],
        "id": 7000570,
        "name:xx": "Kumasi"
      }
    },
    {
      "geometry": {
        "type": "Point",
        "coordinates": [
          29.0833,
          -3.4
        ]
      },
      "type": "Feature",
      "properties": {
        "hierarchy": [
          "tgn:7000571",
          "tgn:7001242",
          "tgn:7016707",
          "tgn:1000159",
          "tgn:7029392"
        ],
        "placetype": [
          "aat:300008347"
        ],
        "id": 7000571,
        "name:xx": "Uvira"
      }
    },
    {
      "geometry": {
        "type": "Point",
        "coordinates": [
          -1.3167,
          5.15
        ]
      },
      "type": "Feature",
      "properties": {
        "hierarchy": [
          "tgn:7000572",
          "tgn:1001653",
          "tgn:7001242",
          "tgn:1000166",
          "tgn:7029392"
        ],
        "placetype": [
          "aat:300008347",
          "aat:300008375",
          "aat:300120599"
        ],
        "id": 7000572,
        "name:xx": "Elmina"
      }
    },
    {
      "geometry": {
        "type": "Point",
        "coordinates": [
          29.1667,
          -5.95
        ]
      },
      "type": "Feature",
      "properties": {
        "hierarchy": [
          "tgn:7000573",
          "tgn:7001242",
          "tgn:7016706",
          "tgn:1000159",
          "tgn:7029392"
        ],
        "placetype": [
          "aat:300008347",
          "aat:300008389",
          "aat:300387226",
          "aat:300120599"
        ],
        "id": 7000573,
        "name:xx": "Kalémié"
      }
    },
    {
      "geometry": {
        "type": "Point",
        "coordinates": [
          25,
          -8.7667
        ]
      },
      "type": "Feature",
      "properties": {
        "hierarchy": [
          "tgn:7000574",
          "tgn:7001242",
          "tgn:7016706",
          "tgn:1000159",
          "tgn:7029392"
        ],
        "placetype": [
          "aat:300008347"
        ],
        "id": 7000574,
        "name:xx": "Kamina"
      }
    },
    {
      "geometry": {
        "type": "Point",
        "coordinates": [
          27.4,
          -7.3
        ]
      },
      "type": "Feature",
      "properties": {
        "hierarchy": [
          "tgn:7000575",
          "tgn:7001242",
          "tgn:7016706",
          "tgn:1000159",
          "tgn:7029392"
        ],
        "placetype": [
          "aat:300008347"
        ],
        "id": 7000575,
        "name:xx": "Manono"
      }
    },
    {
      "geometry": {
        "type": "Point",
        "coordinates": [
          27.4833,
          -11.6833
        ]
      },
      "type": "Feature",
      "properties": {
        "hierarchy": [
          "tgn:7000576",
          "tgn:7001242",
          "tgn:7016706",
          "tgn:1000159",
          "tgn:7029392"
        ],
        "placetype": [
          "aat:300008347",
          "aat:300008389",
          "aat:300387220",
          "aat:300387270"
        ],
        "id": 7000576,
        "name:xx": "Lubumbashi"
      }
    },
    {
      "geometry": {
        "type": "Point",
        "coordinates": [
          0.5,
          10.5
        ]
      },
      "type": "Feature",
      "properties": {
        "hierarchy": [
          "tgn:7000579",
          "tgn:7001242",
          "tgn:7016577",
          "tgn:7029392"
        ],
        "placetype": [
          "aat:300387064",
          "aat:300236112"
        ],
        "id": 7000579,
        "name:xx": "Des Savanes"
      }
    }
  ]
}
