{
  "type": "FeatureCollection",
  "features": [
    {
      "geometry": {
        "type": "Point",
        "coordinates": [
          113.65,
          37.6667
        ]
      },
      "type": "Feature",
      "properties": {
        "hierarchy": [
          "tgn:1139931",
          "tgn:1000004",
          "tgn:7002086",
          "tgn:1000111",
          "tgn:7029392"
        ],
        "placetype": [
          "aat:300008347"
        ],
        "id": 1139931,
        "name:xx": "Xiyang"
      }
    },
    {
      "geometry": {
        "type": "Point",
        "coordinates": [
          113.8,
          34.05
        ]
      },
      "type": "Feature",
      "properties": {
        "hierarchy": [
          "tgn:1139932",
          "tgn:1000004",
          "tgn:7016672",
          "tgn:1000111",
          "tgn:7029392"
        ],
        "placetype": [
          "aat:300008347"
        ],
        "id": 1139932,
        "name:xx": "Xuchang"
      }
    },
    {
      "geometry": {
        "type": "Point",
        "coordinates": [
          113.8167,
          34.5167
        ]
      },
      "type": "Feature",
      "properties": {
        "hierarchy": [
          "tgn:1139933",
          "tgn:1000004",
          "tgn:7016672",
          "tgn:1000111",
          "tgn:7029392"
        ],
        "placetype": [
          "aat:300008347"
        ],
        "id": 1139933,
        "name:xx": "Xuedian"
      }
    },
    {
      "geometry": {
        "type": "Point",
        "coordinates": [
          121.2833,
          31.3833
        ]
      },
      "type": "Feature",
      "properties": {
        "hierarchy": [
          "tgn:1139934",
          "tgn:1000004",
          "tgn:1000958",
          "tgn:1000111",
          "tgn:7029392"
        ],
        "placetype": [
          "aat:300008347"
        ],
        "id": 1139934,
        "name:xx": "Xujiazhai"
      }
    },
    {
      "geometry": {
        "type": "Point",
        "coordinates": [
          120.9,
          31.75
        ]
      },
      "type": "Feature",
      "properties": {
        "hierarchy": [
          "tgn:1139935",
          "tgn:1000004",
          "tgn:7002081",
          "tgn:1000111",
          "tgn:7029392"
        ],
        "placetype": [
          "aat:300008347"
        ],
        "id": 1139935,
        "name:xx": "Xupu"
      }
    },
    {
      "geometry": {
        "type": "Point",
        "coordinates": [
          130.4167,
          45.4
        ]
      },
      "type": "Feature",
      "properties": {
        "hierarchy": [
          "tgn:1139936",
          "tgn:1000004",
          "tgn:1001290",
          "tgn:1000111",
          "tgn:7029392"
        ],
        "placetype": [
          "aat:300008347"
        ],
        "id": 1139936,
        "name:xx": "Yahe"
      }
    },
    {
      "geometry": {
        "type": "Point",
        "coordinates": [
          114,
          33.5833
        ]
      },
      "type": "Feature",
      "properties": {
        "hierarchy": [
          "tgn:1139937",
          "tgn:1000004",
          "tgn:7016672",
          "tgn:1000111",
          "tgn:7029392"
        ],
        "placetype": [
          "aat:300008347"
        ],
        "id": 1139937,
        "name:xx": "Yancheng"
      }
    },
    {
      "geometry": {
        "type": "Point",
        "coordinates": [
          115.8833,
          40.0333
        ]
      },
      "type": "Feature",
      "properties": {
        "hierarchy": [
          "tgn:1139938",
          "tgn:1000956",
          "tgn:1000004",
          "tgn:1000111",
          "tgn:7029392"
        ],
        "placetype": [
          "aat:300008347"
        ],
        "id": 1139938,
        "name:xx": "Yanchi"
      }
    },
    {
      "geometry": {
        "type": "Point",
        "coordinates": [
          112.4833,
          35.5
        ]
      },
      "type": "Feature",
      "properties": {
        "hierarchy": [
          "tgn:1139939",
          "tgn:1000004",
          "tgn:7002086",
          "tgn:1000111",
          "tgn:7029392"
        ],
        "placetype": [
          "aat:300008347"
        ],
        "id": 1139939,
        "name:xx": "Yangcheng"
      }
    }
  ]
}
