{
  "geometry": {
    "type": "Point",
    "coordinates": [
      -81.6667,
      38.4333
    ]
  },
  "type": "Feature",
  "properties": {
    "hierarchy": [
      "tgn:2732288",
      "tgn:1000001",
      "tgn:7012149",
      "tgn:2002270",
      "tgn:7013961",
      "tgn:7029392"
    ],
    "placetype": [
      "aat:300008706"
    ],
    "id": 2732288,
    "name:xx": "Tupper Creek"
  }
}
