{
  "geometry": {
    "type": "Point",
    "coordinates": [
      -110.5167,
      36.7167
    ]
  },
  "type": "Feature",
  "properties": {
    "hierarchy": [
      "tgn:2185575",
      "tgn:1000001",
      "tgn:7006451",
      "tgn:7012149",
      "tgn:2000099",
      "tgn:7029392"
    ],
    "placetype": [
      "aat:300008697"
    ],
    "id": 2185575,
    "name:xx": "Boiling Spring"
  }
}
