{
  "geometry": {
    "type": "Point",
    "coordinates": [
      -90.6167,
      30.35
    ]
  },
  "type": "Feature",
  "properties": {
    "hierarchy": [
      "tgn:2043033",
      "tgn:1000001",
      "tgn:7012149",
      "tgn:2000885",
      "tgn:7007256",
      "tgn:7029392"
    ],
    "placetype": [
      "aat:300008347",
      "aat:300387210"
    ],
    "id": 2043033,
    "name:xx": "Horse Bluff Landing"
  }
}
