{
  "geometry": {
    "type": "Point",
    "coordinates": [
      -109.4333,
      37.4833
    ]
  },
  "type": "Feature",
  "properties": {
    "hierarchy": [
      "tgn:2620981",
      "tgn:1000001",
      "tgn:7012149",
      "tgn:2002119",
      "tgn:7007827",
      "tgn:7029392"
    ],
    "placetype": [
      "aat:300008850"
    ],
    "id": 2620981,
    "name:xx": "Road Canyon Point"
  }
}
