{
  "geometry": {
    "type": "Point",
    "coordinates": [
      -85.9167,
      38.1667
    ]
  },
  "type": "Feature",
  "properties": {
    "hierarchy": [
      "tgn:2508799",
      "tgn:1000001",
      "tgn:7012149",
      "tgn:1002457",
      "tgn:7007252",
      "tgn:7029392"
    ],
    "placetype": [
      "aat:300008706"
    ],
    "id": 2508799,
    "name:xx": "Middle Fork Buck Creek"
  }
}
