{
  "geometry": {
    "type": "Point",
    "coordinates": [
      -104.8333,
      32.0333
    ]
  },
  "type": "Feature",
  "properties": {
    "hierarchy": [
      "tgn:2395377",
      "tgn:1000001",
      "tgn:2001436",
      "tgn:7012149",
      "tgn:7007566",
      "tgn:7029392"
    ],
    "placetype": [
      "aat:300006191"
    ],
    "id": 2395377,
    "name:xx": "Hollan Tank"
  }
}
