{
  "geometry": {
    "type": "Point",
    "coordinates": [
      -161.8667,
      61.8167
    ]
  },
  "type": "Feature",
  "properties": {
    "hierarchy": [
      "tgn:2307583",
      "tgn:7006450",
      "tgn:1000001",
      "tgn:7012149",
      "tgn:2000087",
      "tgn:7029392"
    ],
    "placetype": [
      "aat:300008706"
    ],
    "id": 2307583,
    "name:xx": "East Fork Spruce Creek"
  }
}
