{
  "geometry": {
    "type": "Point",
    "coordinates": [
      -83.35,
      36.1167
    ]
  },
  "type": "Feature",
  "properties": {
    "hierarchy": [
      "tgn:2633980",
      "tgn:1000001",
      "tgn:7012149",
      "tgn:2001881",
      "tgn:7007825",
      "tgn:7029392"
    ],
    "placetype": [
      "aat:300008347"
    ],
    "id": 2633980,
    "name:xx": "Rushy Springs"
  }
}
