{
  "geometry": {
    "type": "Point",
    "coordinates": [
      -106.8667,
      37.1667
    ]
  },
  "type": "Feature",
  "properties": {
    "hierarchy": [
      "tgn:2153515",
      "tgn:2000195",
      "tgn:1000001",
      "tgn:7012149",
      "tgn:7007158",
      "tgn:7029392"
    ],
    "placetype": [
      "aat:300386845"
    ],
    "id": 2153515,
    "name:xx": "Bear Basin"
  }
}
