{
  "geometry": {
    "type": "Point",
    "coordinates": [
      -93.7333,
      38.15
    ]
  },
  "type": "Feature",
  "properties": {
    "hierarchy": [
      "tgn:2343851",
      "tgn:1000001",
      "tgn:7012149",
      "tgn:2001239",
      "tgn:7007523",
      "tgn:7029392"
    ],
    "placetype": [
      "aat:300008706"
    ],
    "id": 2343851,
    "name:xx": "Gallinipper Creek"
  }
}
