{
  "type": "FeatureCollection",
  "features": [
    {
      "geometry": {
        "type": "Point",
        "coordinates": [
          -121.15,
          35.7333
        ]
      },
      "type": "Feature",
      "properties": {
        "hierarchy": [
          "tgn:2208420",
          "tgn:1000001",
          "tgn:7012149",
          "tgn:7007157",
          "tgn:7029392"
        ],
        "placetype": [
          "aat:300008706"
        ],
        "id": 2208420,
        "name:xx": "Burnett Creek"
      }
    },
    {
      "geometry": {
        "type": "Point",
        "coordinates": [
          -108.0667,
          37.6833
        ]
      },
      "type": "Feature",
      "properties": {
        "hierarchy": [
          "tgn:2208421",
          "tgn:1000001",
          "tgn:7012149",
          "tgn:2000208",
          "tgn:7007158",
          "tgn:7029392"
        ],
        "placetype": [
          "aat:300008706"
        ],
        "id": 2208421,
        "name:xx": "Burnett Creek"
      }
    },
    {
      "geometry": {
        "type": "Point",
        "coordinates": [
          -83.9833,
          34.7167
        ]
      },
      "type": "Feature",
      "properties": {
        "hierarchy": [
          "tgn:2208422",
          "tgn:1000001",
          "tgn:7012149",
          "tgn:2000435",
          "tgn:7007248",
          "tgn:7029392"
        ],
        "placetype": [
          "aat:300008706"
        ],
        "id": 2208422,
        "name:xx": "Burnett Creek"
      }
    },
    {
      "geometry": {
        "type": "Point",
        "coordinates": [
          -81.5,
          31.25
        ]
      },
      "type": "Feature",
      "properties": {
        "hierarchy": [
          "tgn:2208423",
          "tgn:1000001",
          "tgn:7012149",
          "tgn:2000354",
          "tgn:7007248",
          "tgn:7029392"
        ],
        "placetype": [
          "aat:300008706"
        ],
        "id": 2208423,
        "name:xx": "Burnett Creek"
      }
    },
    {
      "geometry": {
        "type": "Point",
        "coordinates": [
          -87.0167,
          40.5333
        ]
      },
      "type": "Feature",
      "properties": {
        "hierarchy": [
          "tgn:2208424",
          "tgn:1000001",
          "tgn:7012149",
          "tgn:1002946",
          "tgn:7007252",
          "tgn:7029392"
        ],
        "placetype": [
          "aat:300008706"
        ],
        "id": 2208424,
        "name:xx": "Burnett Creek"
      }
    },
    {
      "geometry": {
        "type": "Point",
        "coordinates": [
          -92.7833,
          42.1
        ]
      },
      "type": "Feature",
      "properties": {
        "hierarchy": [
          "tgn:2208425",
          "tgn:1000001",
          "tgn:7012149",
          "tgn:2000624",
          "tgn:7007253",
          "tgn:7029392"
        ],
        "placetype": [
          "aat:300008706"
        ],
        "id": 2208425,
        "name:xx": "Burnett Creek"
      }
    },
    {
      "geometry": {
        "type": "Point",
        "coordinates": [
          -85.0333,
          42.0833
        ]
      },
      "type": "Feature",
      "properties": {
        "hierarchy": [
          "tgn:2208426",
          "tgn:1000001",
          "tgn:7012149",
          "tgn:7007520",
          "tgn:7029392"
        ],
        "placetype": [
          "aat:300008706"
        ],
        "id": 2208426,
        "name:xx": "Burnett Creek"
      }
    },
    {
      "geometry": {
        "type": "Point",
        "coordinates": [
          -106.95,
          48.7
        ]
      },
      "type": "Feature",
      "properties": {
        "hierarchy": [
          "tgn:2208427",
          "tgn:1000001",
          "tgn:7012149",
          "tgn:2001312",
          "tgn:7007524",
          "tgn:7029392"
        ],
        "placetype": [
          "aat:300008706"
        ],
        "id": 2208427,
        "name:xx": "Burnett Creek"
      }
    },
    {
      "geometry": {
        "type": "Point",
        "coordinates": [
          -72.3333,
          40.8833
        ]
      },
      "type": "Feature",
      "properties": {
        "hierarchy": [
          "tgn:2208428",
          "tgn:1000001",
          "tgn:7012149",
          "tgn:1002924",
          "tgn:7007568",
          "tgn:7029392"
        ],
        "placetype": [
          "aat:300132316"
        ],
        "id": 2208428,
        "name:xx": "Burnett Creek"
      }
    },
    {
      "geometry": {
        "type": "Point",
        "coordinates": [
          -82.8333,
          35.4167
        ]
      },
      "type": "Feature",
      "properties": {
        "hierarchy": [
          "tgn:2208429",
          "tgn:1000001",
          "tgn:7012149",
          "tgn:2001503",
          "tgn:7007709",
          "tgn:7029392"
        ],
        "placetype": [
          "aat:300008706"
        ],
        "id": 2208429,
        "name:xx": "Burnett Creek"
      }
    }
  ]
}
