{
  "geometry": {
    "type": "Point",
    "coordinates": [
      -95.65,
      33.2667
    ]
  },
  "type": "Feature",
  "properties": {
    "hierarchy": [
      "tgn:2106907",
      "tgn:1000001",
      "tgn:7012149",
      "tgn:1002485",
      "tgn:7007826",
      "tgn:7029392"
    ],
    "placetype": [
      "aat:300008347",
      "aat:300387210"
    ],
    "id": 2106907,
    "name:xx": "Posey"
  }
}
