{
  "geometry": {
    "type": "Point",
    "coordinates": [
      -76.7167,
      -4.4167
    ]
  },
  "type": "Feature",
  "properties": {
    "hierarchy": [
      "tgn:1117839",
      "tgn:1000675",
      "tgn:1000002",
      "tgn:1000056",
      "tgn:7029392"
    ],
    "placetype": [
      "aat:300008680"
    ],
    "id": 1117839,
    "name:xx": "Rimachuima, Laguna"
  }
}
