{
  "geometry": {
    "type": "Point",
    "coordinates": [
      -112.8667,
      39.5167
    ]
  },
  "type": "Feature",
  "properties": {
    "hierarchy": [
      "tgn:2167953",
      "tgn:1000001",
      "tgn:7012149",
      "tgn:2002114",
      "tgn:7007827",
      "tgn:7029392"
    ],
    "placetype": [
      "aat:300006191"
    ],
    "id": 2167953,
    "name:xx": "Big Drum Reservoir"
  }
}
