{
  "geometry": {
    "type": "Point",
    "coordinates": [
      -90.0667,
      37.0333
    ]
  },
  "type": "Feature",
  "properties": {
    "hierarchy": [
      "tgn:2359875",
      "tgn:1000001",
      "tgn:2001174",
      "tgn:7012149",
      "tgn:7007523",
      "tgn:7029392"
    ],
    "placetype": [
      "aat:300266640"
    ],
    "id": 2359875,
    "name:xx": "Grapevine Ridge"
  }
}
