{
  "geometry": {
    "type": "Point",
    "coordinates": [
      -98.75,
      21.95
    ]
  },
  "type": "Feature",
  "properties": {
    "hierarchy": [
      "tgn:7426307",
      "tgn:1000001",
      "tgn:7005594",
      "tgn:7005560",
      "tgn:7029392"
    ],
    "placetype": [
      "aat:300387007"
    ],
    "id": 7426307,
    "name:xx": "Tamuín, Zona Arqueológica"
  }
}
