{
  "geometry": {
    "type": "Point",
    "coordinates": [
      -80.25,
      25.6833
    ]
  },
  "type": "Feature",
  "properties": {
    "hierarchy": [
      "tgn:2517481",
      "tgn:1000001",
      "tgn:7012149",
      "tgn:1002314",
      "tgn:7007240",
      "tgn:7029392"
    ],
    "placetype": [
      "aat:300008680"
    ],
    "id": 2517481,
    "name:xx": "Minore, Lago"
  }
}
