{
  "geometry": {
    "type": "Point",
    "coordinates": [
      -119.2833,
      37.95
    ]
  },
  "type": "Feature",
  "properties": {
    "hierarchy": [
      "tgn:2364472",
      "tgn:1000001",
      "tgn:7012149",
      "tgn:7007157",
      "tgn:1002675",
      "tgn:7029392"
    ],
    "placetype": [
      "aat:300008680"
    ],
    "id": 2364472,
    "name:xx": "Green Treble Lake"
  }
}
