{
  "geometry": {
    "type": "Point",
    "coordinates": [
      -101.05,
      48.0833
    ]
  },
  "type": "Feature",
  "properties": {
    "hierarchy": [
      "tgn:2078002",
      "tgn:1000001",
      "tgn:7012149",
      "tgn:2001607",
      "tgn:7007705",
      "tgn:7029392"
    ],
    "placetype": [
      "aat:300008347"
    ],
    "id": 2078002,
    "name:xx": "Sawyer"
  }
}
