{
  "geometry": {
    "type": "Point",
    "coordinates": [
      -97.5667,
      29.9167
    ]
  },
  "type": "Feature",
  "properties": {
    "hierarchy": [
      "tgn:2380695",
      "tgn:1000001",
      "tgn:7012149",
      "tgn:1002220",
      "tgn:7007826",
      "tgn:7029392"
    ],
    "placetype": [
      "aat:300008699"
    ],
    "id": 2380695,
    "name:xx": "Haw Branch"
  }
}
