{
  "geometry": {
    "type": "Point",
    "coordinates": [
      -82.7833,
      36.2667
    ]
  },
  "type": "Feature",
  "properties": {
    "hierarchy": [
      "tgn:2418635",
      "tgn:1000001",
      "tgn:7012149",
      "tgn:2001866",
      "tgn:7007825",
      "tgn:7029392"
    ],
    "placetype": [
      "aat:300008798"
    ],
    "id": 2418635,
    "name:xx": "Jake Knob"
  }
}
