{
  "geometry": {
    "type": "Point",
    "coordinates": [
      12.5667,
      55.9667
    ]
  },
  "type": "Feature",
  "properties": {
    "hierarchy": [
      "tgn:7031599",
      "tgn:7594005",
      "tgn:1000003",
      "tgn:1000066",
      "tgn:7029392"
    ],
    "placetype": [
      "aat:300008347"
    ],
    "id": 7031599,
    "name:xx": "Humlebæk"
  }
}
