{
  "type": "FeatureCollection",
  "features": [
    {
      "geometry": {
        "type": "Point",
        "coordinates": [
          -76.3,
          42.2333
        ]
      },
      "type": "Feature",
      "properties": {
        "hierarchy": [
          "tgn:2218450",
          "tgn:1000001",
          "tgn:7012149",
          "tgn:1002944",
          "tgn:7007568",
          "tgn:7029392"
        ],
        "placetype": [
          "aat:300008798"
        ],
        "id": 2218450,
        "name:xx": "Candor Hill"
      }
    },
    {
      "geometry": {
        "type": "Point",
        "coordinates": [
          -95.8167,
          46.7
        ]
      },
      "type": "Feature",
      "properties": {
        "hierarchy": [
          "tgn:2218451",
          "tgn:1000001",
          "tgn:7012149",
          "tgn:2001054",
          "tgn:7007521",
          "tgn:7029392"
        ],
        "placetype": [
          "aat:300008680"
        ],
        "id": 2218451,
        "name:xx": "Candor Lake"
      }
    },
    {
      "geometry": {
        "type": "Point",
        "coordinates": [
          -109,
          34
        ]
      },
      "type": "Feature",
      "properties": {
        "hierarchy": [
          "tgn:2218452",
          "tgn:1000001",
          "tgn:7012149",
          "tgn:7029392"
        ],
        "placetype": [
          "aat:300008706"
        ],
        "id": 2218452,
        "name:xx": "Candovas Creek"
      }
    },
    {
      "geometry": {
        "type": "Point",
        "coordinates": [
          -85.1667,
          38
        ]
      },
      "type": "Feature",
      "properties": {
        "hierarchy": [
          "tgn:2218453",
          "tgn:1000001",
          "tgn:7012149",
          "tgn:2000843",
          "tgn:7007255",
          "tgn:7029392"
        ],
        "placetype": [
          "aat:300008699"
        ],
        "id": 2218453,
        "name:xx": "Candy Branch"
      }
    },
    {
      "geometry": {
        "type": "Point",
        "coordinates": [
          -82.9167,
          38.2167
        ]
      },
      "type": "Feature",
      "properties": {
        "hierarchy": [
          "tgn:2218454",
          "tgn:1000001",
          "tgn:1002240",
          "tgn:7012149",
          "tgn:7007255",
          "tgn:7029392"
        ],
        "placetype": [
          "aat:300008699"
        ],
        "id": 2218454,
        "name:xx": "Candy Branch"
      }
    },
    {
      "geometry": {
        "type": "Point",
        "coordinates": [
          -82.35,
          34.0667
        ]
      },
      "type": "Feature",
      "properties": {
        "hierarchy": [
          "tgn:2218456",
          "tgn:2001725",
          "tgn:1000001",
          "tgn:7012149",
          "tgn:7007712",
          "tgn:7029392"
        ],
        "placetype": [
          "aat:300008699"
        ],
        "id": 2218456,
        "name:xx": "Candy Branch"
      }
    },
    {
      "geometry": {
        "type": "Point",
        "coordinates": [
          -85.5,
          40.0333
        ]
      },
      "type": "Feature",
      "properties": {
        "hierarchy": [
          "tgn:2218457",
          "tgn:1000001",
          "tgn:7012149",
          "tgn:1002468",
          "tgn:7007252",
          "tgn:7029392"
        ],
        "placetype": [
          "aat:300008699"
        ],
        "id": 2218457,
        "name:xx": "Candy Brook"
      }
    },
    {
      "geometry": {
        "type": "Point",
        "coordinates": [
          -122.6333,
          39.3667
        ]
      },
      "type": "Feature",
      "properties": {
        "hierarchy": [
          "tgn:2218458",
          "tgn:1000001",
          "tgn:7012149",
          "tgn:1002296",
          "tgn:7007157",
          "tgn:7029392"
        ],
        "placetype": [
          "aat:300008697"
        ],
        "id": 2218458,
        "name:xx": "Candy Bucket Spring"
      }
    },
    {
      "geometry": {
        "type": "Point",
        "coordinates": [
          -90.75,
          34.95
        ]
      },
      "type": "Feature",
      "properties": {
        "hierarchy": [
          "tgn:2218459",
          "tgn:1000001",
          "tgn:7016172",
          "tgn:7012149",
          "tgn:2000166",
          "tgn:7029392"
        ],
        "placetype": [
          "aat:300008706"
        ],
        "id": 2218459,
        "name:xx": "Candy Creek"
      }
    }
  ]
}
