{
  "geometry": {
    "type": "Point",
    "coordinates": [
      116.3667,
      25.8833
    ]
  },
  "type": "Feature",
  "properties": {
    "hierarchy": [
      "tgn:1067783",
      "tgn:1000004",
      "tgn:7001796",
      "tgn:1000111",
      "tgn:7029392"
    ],
    "placetype": [
      "aat:300008347"
    ],
    "id": 1067783,
    "name:xx": "Dongjie"
  }
}
