{
  "geometry": {
    "type": "Point",
    "coordinates": [
      -75.25,
      40.0333
    ]
  },
  "type": "Feature",
  "properties": {
    "hierarchy": [
      "tgn:2648476",
      "tgn:1000001",
      "tgn:7012149",
      "tgn:1002690",
      "tgn:7007710",
      "tgn:7029392"
    ],
    "placetype": [
      "aat:300008746"
    ],
    "id": 2648476,
    "name:xx": "Schuylkill Cave"
  }
}
