{
  "geometry": {
    "type": "Point",
    "coordinates": [
      -92.45,
      47.8667
    ]
  },
  "type": "Feature",
  "properties": {
    "hierarchy": [
      "tgn:2717381",
      "tgn:1000001",
      "tgn:7012149",
      "tgn:2001067",
      "tgn:7007521",
      "tgn:7029392"
    ],
    "placetype": [
      "aat:300008791"
    ],
    "id": 2717381,
    "name:xx": "Thirtysix Island"
  }
}
