{
  "geometry": {
    "type": "Point",
    "coordinates": [
      -72.7333,
      45.7333
    ]
  },
  "type": "Feature",
  "properties": {
    "hierarchy": [
      "tgn:1015747",
      "tgn:7005685",
      "tgn:1000001",
      "tgn:7005804",
      "tgn:7029392"
    ],
    "placetype": [
      "aat:300008347"
    ],
    "id": 1015747,
    "name:xx": "Sainte-Hélène-de-Bagot"
  }
}
