{
  "geometry": {
    "type": "Point",
    "coordinates": [
      -83.55,
      41.9667
    ]
  },
  "type": "Feature",
  "properties": {
    "hierarchy": [
      "tgn:2651950",
      "tgn:1000001",
      "tgn:7012149",
      "tgn:1002679",
      "tgn:7007520",
      "tgn:7029392"
    ],
    "placetype": [
      "aat:300008699"
    ],
    "id": 2651950,
    "name:xx": "Seitz Drain"
  }
}
