{
  "geometry": {
    "type": "Point",
    "coordinates": [
      151.1833,
      -33.95
    ]
  },
  "type": "Feature",
  "properties": {
    "hierarchy": [
      "tgn:1123036",
      "tgn:7000490",
      "tgn:1000006",
      "tgn:7001828",
      "tgn:7029392"
    ],
    "placetype": [
      "aat:300008707"
    ],
    "id": 1123036,
    "name:xx": "Cooks River"
  }
}
