{
  "geometry": {
    "type": "Point",
    "coordinates": [
      -103.55,
      45.7167
    ]
  },
  "type": "Feature",
  "properties": {
    "hierarchy": [
      "tgn:2391949",
      "tgn:1000001",
      "tgn:2001801",
      "tgn:7012149",
      "tgn:7007713",
      "tgn:7029392"
    ],
    "placetype": [
      "aat:300000390"
    ],
    "id": 2391949,
    "name:xx": "Hilton Mine"
  }
}
