{
  "geometry": {
    "type": "Point",
    "coordinates": [
      -114.7667,
      37.3833
    ]
  },
  "type": "Feature",
  "properties": {
    "hierarchy": [
      "tgn:2169465",
      "tgn:1000001",
      "tgn:2001416",
      "tgn:7012149",
      "tgn:7007526",
      "tgn:7029392"
    ],
    "placetype": [
      "aat:300008798"
    ],
    "id": 2169465,
    "name:xx": "Big Lime Mountain"
  }
}
