{
  "geometry": {
    "type": "Point",
    "coordinates": [
      -87.2833,
      35.55
    ]
  },
  "type": "Feature",
  "properties": {
    "hierarchy": [
      "tgn:2263387",
      "tgn:1000001",
      "tgn:7012149",
      "tgn:2001896",
      "tgn:7007825",
      "tgn:7029392"
    ],
    "placetype": [
      "aat:300008761"
    ],
    "id": 2263387,
    "name:xx": "Cox Hollow"
  }
}
