{
  "geometry": {
    "type": "Point",
    "coordinates": [
      -96.1667,
      38.55
    ]
  },
  "type": "Feature",
  "properties": {
    "hierarchy": [
      "tgn:2695274",
      "tgn:1000001",
      "tgn:7012149",
      "tgn:2000715",
      "tgn:7007254",
      "tgn:7029392"
    ],
    "placetype": [
      "aat:300008706"
    ],
    "id": 2695274,
    "name:xx": "Stillman Creek"
  }
}
