{
  "geometry": {
    "type": "Point",
    "coordinates": [
      73.0167,
      33.0667
    ]
  },
  "type": "Feature",
  "properties": {
    "hierarchy": [
      "tgn:1083432",
      "tgn:1000004",
      "tgn:1001490",
      "tgn:1000133",
      "tgn:7029392"
    ],
    "placetype": [
      "aat:300008347"
    ],
    "id": 1083432,
    "name:xx": "Dhudial"
  }
}
