{
  "type": "FeatureCollection",
  "features": [
    {
      "geometry": {
        "type": "Point",
        "coordinates": [
          -94.0667,
          37.45
        ]
      },
      "type": "Feature",
      "properties": {
        "hierarchy": [
          "tgn:2276410",
          "tgn:1000001",
          "tgn:7012149",
          "tgn:2001191",
          "tgn:7007523",
          "tgn:7029392"
        ],
        "placetype": [
          "aat:300008347"
        ],
        "id": 2276410,
        "name:xx": "Davenport"
      }
    },
    {
      "geometry": {
        "type": "Point",
        "coordinates": [
          -81.5167,
          36
        ]
      },
      "type": "Feature",
      "properties": {
        "hierarchy": [
          "tgn:2276411",
          "tgn:1000001",
          "tgn:2001476",
          "tgn:7012149",
          "tgn:7007709",
          "tgn:7029392"
        ],
        "placetype": [
          "aat:300008347"
        ],
        "id": 2276411,
        "name:xx": "Davenport"
      }
    },
    {
      "geometry": {
        "type": "Point",
        "coordinates": [
          -88.1167,
          37.0167
        ]
      },
      "type": "Feature",
      "properties": {
        "hierarchy": [
          "tgn:2276412",
          "tgn:1000001",
          "tgn:7012149",
          "tgn:2000816",
          "tgn:7007255",
          "tgn:7029392"
        ],
        "placetype": [
          "aat:300132316"
        ],
        "id": 2276412,
        "name:xx": "Davenport Bay"
      }
    },
    {
      "geometry": {
        "type": "Point",
        "coordinates": [
          -87.2667,
          30.3667
        ]
      },
      "type": "Feature",
      "properties": {
        "hierarchy": [
          "tgn:2276413",
          "tgn:1000001",
          "tgn:2000265",
          "tgn:7012149",
          "tgn:7007240",
          "tgn:7029392"
        ],
        "placetype": [
          "aat:300132316"
        ],
        "id": 2276413,
        "name:xx": "Davenport Bayou"
      }
    },
    {
      "geometry": {
        "type": "Point",
        "coordinates": [
          -84.2,
          36.6333
        ]
      },
      "type": "Feature",
      "properties": {
        "hierarchy": [
          "tgn:2276415",
          "tgn:1000001",
          "tgn:7012149",
          "tgn:2000852",
          "tgn:7007255",
          "tgn:7029392"
        ],
        "placetype": [
          "aat:300008699"
        ],
        "id": 2276415,
        "name:xx": "Davenport Branch"
      }
    },
    {
      "geometry": {
        "type": "Point",
        "coordinates": [
          -74.3667,
          39.95
        ]
      },
      "type": "Feature",
      "properties": {
        "hierarchy": [
          "tgn:2276416",
          "tgn:1000001",
          "tgn:1002738",
          "tgn:7012149",
          "tgn:7007565",
          "tgn:7029392"
        ],
        "placetype": [
          "aat:300008699"
        ],
        "id": 2276416,
        "name:xx": "Davenport Branch"
      }
    },
    {
      "geometry": {
        "type": "Point",
        "coordinates": [
          -81.75,
          34.2333
        ]
      },
      "type": "Feature",
      "properties": {
        "hierarchy": [
          "tgn:2276418",
          "tgn:1000001",
          "tgn:7012149",
          "tgn:2001760",
          "tgn:7007712",
          "tgn:7029392"
        ],
        "placetype": [
          "aat:300008699"
        ],
        "id": 2276418,
        "name:xx": "Davenport Branch"
      }
    },
    {
      "geometry": {
        "type": "Point",
        "coordinates": [
          -97.2833,
          33.8167
        ]
      },
      "type": "Feature",
      "properties": {
        "hierarchy": [
          "tgn:2276419",
          "tgn:1000001",
          "tgn:7012149",
          "tgn:2001964",
          "tgn:7007826",
          "tgn:7029392"
        ],
        "placetype": [
          "aat:300008699"
        ],
        "id": 2276419,
        "name:xx": "Davenport Branch"
      }
    }
  ]
}
