{
  "geometry": {
    "type": "Point",
    "coordinates": [
      33.9667,
      48.8333
    ]
  },
  "type": "Feature",
  "properties": {
    "hierarchy": [
      "tgn:1056968",
      "tgn:7011648",
      "tgn:1000003",
      "tgn:7006660",
      "tgn:7029392"
    ],
    "placetype": [
      "aat:300008347"
    ],
    "id": 1056968,
    "name:xx": "Myshuryn Rih"
  }
}
