{
  "geometry": {
    "type": "Point",
    "coordinates": [
      85.834962,
      20.407137
    ]
  },
  "type": "Feature",
  "properties": {
    "hierarchy": [
      "tgn:7544736",
      "tgn:1000004",
      "tgn:7000198",
      "tgn:7016694",
      "tgn:7029392"
    ],
    "placetype": [
      "aat:300008347"
    ],
    "name:en": "Bārang",
    "id": 7544736
  }
}
