{
  "type": "FeatureCollection",
  "features": [
    {
      "geometry": {
        "type": "Point",
        "coordinates": [
          9.666667,
          54.483333
        ]
      },
      "type": "Feature",
      "properties": {
        "hierarchy": [
          "tgn:4004173",
          "tgn:1000003",
          "tgn:7003688",
          "tgn:7000084",
          "tgn:7029392"
        ],
        "placetype": [
          "aat:300008347"
        ],
        "id": 4004173,
        "name:xx": "Güby"
      }
    },
    {
      "geometry": {
        "type": "Point",
        "coordinates": [
          8.912778,
          49.615556
        ]
      },
      "type": "Feature",
      "properties": {
        "hierarchy": [
          "tgn:4004178",
          "tgn:1000003",
          "tgn:7003678",
          "tgn:7000084",
          "tgn:7029392"
        ],
        "placetype": [
          "aat:300008347"
        ],
        "id": 4004178,
        "name:xx": "Güttersbach"
      }
    }
  ]
}
