{
  "type": "FeatureCollection",
  "features": [
    {
      "geometry": {
        "type": "Point",
        "coordinates": [
          100.8,
          -1.05
        ]
      },
      "type": "Feature",
      "properties": {
        "hierarchy": [
          "tgn:1077350",
          "tgn:1000004",
          "tgn:1001553",
          "tgn:1000116",
          "tgn:7029392"
        ],
        "placetype": [
          "aat:300008347"
        ],
        "id": 1077350,
        "name:xx": "Alahanpanjang"
      }
    },
    {
      "geometry": {
        "type": "Point",
        "coordinates": [
          117,
          -8.5
        ]
      },
      "type": "Feature",
      "properties": {
        "hierarchy": [
          "tgn:1077351",
          "tgn:1009295",
          "tgn:1000004",
          "tgn:1001466",
          "tgn:1000116",
          "tgn:7029392"
        ],
        "placetype": [
          "aat:300008347"
        ],
        "id": 1077351,
        "name:xx": "Alas"
      }
    },
    {
      "geometry": {
        "type": "Point",
        "coordinates": [
          123.3167,
          -1.75
        ]
      },
      "type": "Feature",
      "properties": {
        "hierarchy": [
          "tgn:1077352",
          "tgn:7003783",
          "tgn:1009869",
          "tgn:1000004",
          "tgn:1001548",
          "tgn:1000116",
          "tgn:7029392"
        ],
        "placetype": [
          "aat:300008347"
        ],
        "id": 1077352,
        "name:xx": "Alasan"
      }
    },
    {
      "geometry": {
        "type": "Point",
        "coordinates": [
          97.7833,
          4.7833
        ]
      },
      "type": "Feature",
      "properties": {
        "hierarchy": [
          "tgn:1077353",
          "tgn:7016479",
          "tgn:1000004",
          "tgn:1000116",
          "tgn:7029392"
        ],
        "placetype": [
          "aat:300008347"
        ],
        "id": 1077353,
        "name:xx": "Aluedua"
      }
    },
    {
      "geometry": {
        "type": "Point",
        "coordinates": [
          128.9333,
          -3.3167
        ]
      },
      "type": "Feature",
      "properties": {
        "hierarchy": [
          "tgn:1077354",
          "tgn:1000004",
          "tgn:1001409",
          "tgn:1009102",
          "tgn:1000116",
          "tgn:7029392"
        ],
        "placetype": [
          "aat:300008347"
        ],
        "id": 1077354,
        "name:xx": "Amahai"
      }
    },
    {
      "geometry": {
        "type": "Point",
        "coordinates": [
          110.5,
          -7.2
        ]
      },
      "type": "Feature",
      "properties": {
        "hierarchy": [
          "tgn:1077355",
          "tgn:1000004",
          "tgn:1001322",
          "tgn:1000116",
          "tgn:7029392"
        ],
        "placetype": [
          "aat:300008347"
        ],
        "id": 1077355,
        "name:xx": "Ambarawa"
      }
    },
    {
      "geometry": {
        "type": "Point",
        "coordinates": [
          113.6,
          -8.2667
        ]
      },
      "type": "Feature",
      "properties": {
        "hierarchy": [
          "tgn:1077357",
          "tgn:1000004",
          "tgn:1001323",
          "tgn:1000116",
          "tgn:7029392"
        ],
        "placetype": [
          "aat:300008347"
        ],
        "id": 1077357,
        "name:xx": "Ambulu"
      }
    },
    {
      "geometry": {
        "type": "Point",
        "coordinates": [
          113.75,
          -6.9
        ]
      },
      "type": "Feature",
      "properties": {
        "hierarchy": [
          "tgn:1077358",
          "tgn:1000004",
          "tgn:1001323",
          "tgn:7016723",
          "tgn:1000116",
          "tgn:7029392"
        ],
        "placetype": [
          "aat:300008347"
        ],
        "id": 1077358,
        "name:xx": "Ambuntentimur"
      }
    },
    {
      "geometry": {
        "type": "Point",
        "coordinates": [
          116.3,
          -8.25
        ]
      },
      "type": "Feature",
      "properties": {
        "hierarchy": [
          "tgn:1077359",
          "tgn:1007904",
          "tgn:1000004",
          "tgn:1001466",
          "tgn:1000116",
          "tgn:7029392"
        ],
        "placetype": [
          "aat:300008347"
        ],
        "id": 1077359,
        "name:xx": "Amburambur"
      }
    }
  ]
}
