{
  "geometry": {
    "type": "Point",
    "coordinates": [
      76.008291,
      21.093515
    ]
  },
  "type": "Feature",
  "properties": {
    "hierarchy": [
      "tgn:7558600",
      "tgn:1000004",
      "tgn:7000198",
      "tgn:1001895",
      "tgn:7029392"
    ],
    "placetype": [
      "aat:300008699"
    ],
    "name:en": "Pūrna River",
    "id": 7558600
  }
}
