{
  "type": "FeatureCollection",
  "features": [
    {
      "geometry": {
        "type": "Point",
        "coordinates": [
          -69.566667,
          -21.883333
        ]
      },
      "type": "Feature",
      "properties": {
        "hierarchy": [
          "tgn:7281090",
          "tgn:7016598",
          "tgn:1000049",
          "tgn:1000002",
          "tgn:7029392"
        ],
        "placetype": [
          "aat:300007783"
        ],
        "id": 7281090,
        "name:xx": "Santa Fe"
      }
    },
    {
      "geometry": {
        "type": "Point",
        "coordinates": [
          -72.583333,
          -37.45
        ]
      },
      "type": "Feature",
      "properties": {
        "hierarchy": [
          "tgn:7281091",
          "tgn:1001637",
          "tgn:1000049",
          "tgn:1000002",
          "tgn:7029392"
        ],
        "placetype": [
          "aat:300008347"
        ],
        "id": 7281091,
        "name:xx": "Santa Fe"
      }
    },
    {
      "geometry": {
        "type": "Point",
        "coordinates": [
          -70.183333,
          -26.416667
        ]
      },
      "type": "Feature",
      "properties": {
        "hierarchy": [
          "tgn:7281092",
          "tgn:1001630",
          "tgn:1000049",
          "tgn:1000002",
          "tgn:7029392"
        ],
        "placetype": [
          "aat:300008347"
        ],
        "id": 7281092,
        "name:xx": "Santa Fe"
      }
    },
    {
      "geometry": {
        "type": "Point",
        "coordinates": [
          -71.266667,
          -34.966667
        ]
      },
      "type": "Feature",
      "properties": {
        "hierarchy": [
          "tgn:7281093",
          "tgn:1001705",
          "tgn:1000049",
          "tgn:1000002",
          "tgn:7029392"
        ],
        "placetype": [
          "aat:300000206"
        ],
        "id": 7281093,
        "name:xx": "Santa Fe"
      }
    },
    {
      "geometry": {
        "type": "Point",
        "coordinates": [
          -70.633333,
          -34.233333
        ]
      },
      "type": "Feature",
      "properties": {
        "hierarchy": [
          "tgn:7281094",
          "tgn:1001695",
          "tgn:1000049",
          "tgn:1000002",
          "tgn:7029392"
        ],
        "placetype": [
          "aat:300387200"
        ],
        "id": 7281094,
        "name:xx": "Santa Emilia"
      }
    },
    {
      "geometry": {
        "type": "Point",
        "coordinates": [
          -70.7,
          -34.2
        ]
      },
      "type": "Feature",
      "properties": {
        "hierarchy": [
          "tgn:7281095",
          "tgn:1001695",
          "tgn:1000049",
          "tgn:1000002",
          "tgn:7029392"
        ],
        "placetype": [
          "aat:300000206"
        ],
        "id": 7281095,
        "name:xx": "Santa Emilia"
      }
    },
    {
      "geometry": {
        "type": "Point",
        "coordinates": [
          -72.033333,
          -38.466667
        ]
      },
      "type": "Feature",
      "properties": {
        "hierarchy": [
          "tgn:7281096",
          "tgn:1001692",
          "tgn:1000049",
          "tgn:1000002",
          "tgn:7029392"
        ],
        "placetype": [
          "aat:300000206"
        ],
        "id": 7281096,
        "name:xx": "Santa Ema"
      }
    },
    {
      "geometry": {
        "type": "Point",
        "coordinates": [
          -70.833333,
          -34.4
        ]
      },
      "type": "Feature",
      "properties": {
        "hierarchy": [
          "tgn:7281097",
          "tgn:1001695",
          "tgn:1000049",
          "tgn:1000002",
          "tgn:7029392"
        ],
        "placetype": [
          "aat:300004792"
        ],
        "id": 7281097,
        "name:xx": "Santa Ema"
      }
    },
    {
      "geometry": {
        "type": "Point",
        "coordinates": [
          -71.216667,
          -33.666667
        ]
      },
      "type": "Feature",
      "properties": {
        "hierarchy": [
          "tgn:7281098",
          "tgn:1001708",
          "tgn:1000049",
          "tgn:1000002",
          "tgn:7029392"
        ],
        "placetype": [
          "aat:300008347"
        ],
        "id": 7281098,
        "name:xx": "Santa Elvira"
      }
    },
    {
      "geometry": {
        "type": "Point",
        "coordinates": [
          -71.133333,
          -34.6
        ]
      },
      "type": "Feature",
      "properties": {
        "hierarchy": [
          "tgn:7281099",
          "tgn:1001695",
          "tgn:1000049",
          "tgn:1000002",
          "tgn:7029392"
        ],
        "placetype": [
          "aat:300000206"
        ],
        "id": 7281099,
        "name:xx": "Santa Elvira"
      }
    }
  ]
}
