{
  "geometry": {
    "type": "Point",
    "coordinates": [
      -91.05,
      31.55
    ]
  },
  "type": "Feature",
  "properties": {
    "hierarchy": [
      "tgn:2771674",
      "tgn:1000001",
      "tgn:7012149",
      "tgn:2001104",
      "tgn:7007522",
      "tgn:7029392"
    ],
    "placetype": [
      "aat:300008697"
    ],
    "id": 2771674,
    "name:xx": "Wildwood Spring"
  }
}
