{
  "geometry": {
    "type": "Point",
    "coordinates": [
      -120.5667,
      39.3167
    ]
  },
  "type": "Feature",
  "properties": {
    "hierarchy": [
      "tgn:2010924",
      "tgn:1000001",
      "tgn:7012149",
      "tgn:7007157",
      "tgn:1002710",
      "tgn:7029392"
    ],
    "placetype": [
      "aat:300387016"
    ],
    "id": 2010924,
    "name:xx": "Crystal Lake"
  }
}
