{
  "geometry": {
    "type": "Point",
    "coordinates": [
      -87.5833,
      38.0833
    ]
  },
  "type": "Feature",
  "properties": {
    "hierarchy": [
      "tgn:2464064",
      "tgn:1000001",
      "tgn:7012149",
      "tgn:7007252",
      "tgn:7029392"
    ],
    "placetype": [
      "aat:300008706"
    ],
    "id": 2464064,
    "name:xx": "Locust Creek"
  }
}
