{
  "geometry": {
    "type": "Point",
    "coordinates": [
      -78.3833,
      37.2833
    ]
  },
  "type": "Feature",
  "properties": {
    "hierarchy": [
      "tgn:2367263",
      "tgn:1000001",
      "tgn:7012149",
      "tgn:2002182",
      "tgn:7007919",
      "tgn:7029392"
    ],
    "placetype": [
      "aat:300008706"
    ],
    "id": 2367263,
    "name:xx": "Gross Creek"
  }
}
