{
  "geometry": {
    "type": "Point",
    "coordinates": [
      46.75,
      41.1667
    ]
  },
  "type": "Feature",
  "properties": {
    "hierarchy": [
      "tgn:1121078",
      "tgn:1000004",
      "tgn:7029392"
    ],
    "placetype": [
      "aat:300008707"
    ],
    "id": 1121078,
    "name:xx": "Alazani"
  }
}
