{
  "geometry": {
    "type": "Point",
    "coordinates": [
      -149.8833,
      61.1833
    ]
  },
  "type": "Feature",
  "properties": {
    "hierarchy": [
      "tgn:2327577",
      "tgn:2124017",
      "tgn:7006450",
      "tgn:1000001",
      "tgn:7012149",
      "tgn:7029392"
    ],
    "placetype": [
      "aat:300008706"
    ],
    "id": 2327577,
    "name:xx": "Fish Creek"
  }
}
