{
  "geometry": {
    "type": "Point",
    "coordinates": [
      78.222258,
      21.840519
    ]
  },
  "type": "Feature",
  "properties": {
    "hierarchy": [
      "tgn:7571971",
      "tgn:1000004",
      "tgn:7000198",
      "tgn:1001894",
      "tgn:7029392"
    ],
    "placetype": [
      "aat:300008347"
    ],
    "name:en": "Jāwalkhedā",
    "id": 7571971
  }
}
