{
  "geometry": {
    "type": "Point",
    "coordinates": [
      -98.9167,
      28.4333
    ]
  },
  "type": "Feature",
  "properties": {
    "hierarchy": [
      "tgn:2300431",
      "tgn:1000001",
      "tgn:7012149",
      "tgn:2002027",
      "tgn:7007826",
      "tgn:7029392"
    ],
    "placetype": [
      "aat:300008347"
    ],
    "id": 2300431,
    "name:xx": "Dull"
  }
}
