{
  "geometry": {
    "type": "Point",
    "coordinates": [
      -116.4833,
      45.0333
    ]
  },
  "type": "Feature",
  "properties": {
    "hierarchy": [
      "tgn:2211417",
      "tgn:2000453",
      "tgn:1000001",
      "tgn:7012149",
      "tgn:7007250",
      "tgn:7029392"
    ],
    "placetype": [
      "aat:300008761"
    ],
    "id": 2211417,
    "name:xx": "Butter Gulch"
  }
}
