{
  "geometry": {
    "type": "Point",
    "coordinates": [
      -91.1333,
      30.3167
    ]
  },
  "type": "Feature",
  "properties": {
    "hierarchy": [
      "tgn:2042425",
      "tgn:1000001",
      "tgn:2000870",
      "tgn:7012149",
      "tgn:7007256",
      "tgn:7029392"
    ],
    "placetype": [
      "aat:300387016"
    ],
    "id": 2042425,
    "name:xx": "Burtville"
  }
}
