{
  "geometry": {
    "type": "Point",
    "coordinates": [
      -87.5667,
      34.8833
    ]
  },
  "type": "Feature",
  "properties": {
    "hierarchy": [
      "tgn:2002554",
      "tgn:7002659",
      "tgn:1000001",
      "tgn:7012149",
      "tgn:2000038",
      "tgn:7029392"
    ],
    "placetype": [
      "aat:300008347"
    ],
    "id": 2002554,
    "name:xx": "Bailey Springs"
  }
}
