{
  "geometry": {
    "type": "Point",
    "coordinates": [
      31.233333,
      29.75
    ]
  },
  "type": "Feature",
  "properties": {
    "hierarchy": [
      "tgn:7525333",
      "tgn:7001242",
      "tgn:7016833",
      "tgn:1001083",
      "tgn:7029392"
    ],
    "placetype": [
      "aat:300008347"
    ],
    "name:en": "Dahshūr",
    "id": 7525333
  }
}
