{
  "geometry": {
    "type": "Point",
    "coordinates": [
      -112.2667,
      36.3667
    ]
  },
  "type": "Feature",
  "properties": {
    "hierarchy": [
      "tgn:2602902",
      "tgn:1000001",
      "tgn:7006451",
      "tgn:2000092",
      "tgn:7012149",
      "tgn:7029392"
    ],
    "placetype": [
      "aat:300008697"
    ],
    "id": 2602902,
    "name:xx": "Quaking Aspen Spring"
  }
}
