{
  "geometry": {
    "type": "Point",
    "coordinates": [
      -108.7167,
      39.0833
    ]
  },
  "type": "Feature",
  "properties": {
    "hierarchy": [
      "tgn:2755587",
      "tgn:1000001",
      "tgn:7012149",
      "tgn:2000230",
      "tgn:7007158",
      "tgn:7029392"
    ],
    "placetype": [
      "aat:300008761"
    ],
    "id": 2755587,
    "name:xx": "Wedding Canyon"
  }
}
