{
  "type": "FeatureCollection",
  "features": [
    {
      "geometry": {
        "type": "Point",
        "coordinates": [
          -98.15,
          21.266667
        ]
      },
      "type": "Feature",
      "properties": {
        "hierarchy": [
          "tgn:7440060",
          "tgn:1000001",
          "tgn:7005599",
          "tgn:7005560",
          "tgn:7029392"
        ],
        "placetype": [
          "aat:300008347"
        ],
        "id": 7440060,
        "name:xx": "Santa Clara"
      }
    },
    {
      "geometry": {
        "type": "Point",
        "coordinates": [
          -99.35,
          21.083333
        ]
      },
      "type": "Feature",
      "properties": {
        "hierarchy": [
          "tgn:7440061",
          "tgn:7005587",
          "tgn:1000001",
          "tgn:7005560",
          "tgn:7029392"
        ],
        "placetype": [
          "aat:300008347"
        ],
        "id": 7440061,
        "name:xx": "Santa Clara"
      }
    },
    {
      "geometry": {
        "type": "Point",
        "coordinates": [
          -104.45,
          21
        ]
      },
      "type": "Feature",
      "properties": {
        "hierarchy": [
          "tgn:7440062",
          "tgn:1000001",
          "tgn:1001906",
          "tgn:7005560",
          "tgn:7029392"
        ],
        "placetype": [
          "aat:300008347"
        ],
        "id": 7440062,
        "name:xx": "Santa Clara"
      }
    },
    {
      "geometry": {
        "type": "Point",
        "coordinates": [
          -103.083333,
          20.616667
        ]
      },
      "type": "Feature",
      "properties": {
        "hierarchy": [
          "tgn:7440063",
          "tgn:7005586",
          "tgn:1000001",
          "tgn:7005560",
          "tgn:7029392"
        ],
        "placetype": [
          "aat:300008347"
        ],
        "id": 7440063,
        "name:xx": "Santa Clara"
      }
    },
    {
      "geometry": {
        "type": "Point",
        "coordinates": [
          -101.433333,
          20.166667
        ]
      },
      "type": "Feature",
      "properties": {
        "hierarchy": [
          "tgn:7440064",
          "tgn:1000001",
          "tgn:7005590",
          "tgn:7005560",
          "tgn:7029392"
        ],
        "placetype": [
          "aat:300008347"
        ],
        "id": 7440064,
        "name:xx": "Santa Clara"
      }
    },
    {
      "geometry": {
        "type": "Point",
        "coordinates": [
          -98.766667,
          19.85
        ]
      },
      "type": "Feature",
      "properties": {
        "hierarchy": [
          "tgn:7440065",
          "tgn:1000001",
          "tgn:1001893",
          "tgn:7005560",
          "tgn:7029392"
        ],
        "placetype": [
          "aat:300008347"
        ],
        "id": 7440065,
        "name:xx": "Santa Clara"
      }
    },
    {
      "geometry": {
        "type": "Point",
        "coordinates": [
          -93.25,
          17.7
        ]
      },
      "type": "Feature",
      "properties": {
        "hierarchy": [
          "tgn:7440068",
          "tgn:7005580",
          "tgn:1000001",
          "tgn:7005560",
          "tgn:7029392"
        ],
        "placetype": [
          "aat:300008347"
        ],
        "id": 7440068,
        "name:xx": "Santa Clara"
      }
    },
    {
      "geometry": {
        "type": "Point",
        "coordinates": [
          -93.2,
          17.6
        ]
      },
      "type": "Feature",
      "properties": {
        "hierarchy": [
          "tgn:7440069",
          "tgn:7005580",
          "tgn:1000001",
          "tgn:7005560",
          "tgn:7029392"
        ],
        "placetype": [
          "aat:300008347"
        ],
        "id": 7440069,
        "name:xx": "Santa Clara"
      }
    }
  ]
}
