{
  "geometry": {
    "type": "Point",
    "coordinates": [
      75.808068,
      27.818272
    ]
  },
  "type": "Feature",
  "properties": {
    "hierarchy": [
      "tgn:7552868",
      "tgn:1000004",
      "tgn:7000198",
      "tgn:7016788",
      "tgn:7029392"
    ],
    "placetype": [
      "aat:300008347"
    ],
    "name:en": "Māvanda Tarla",
    "id": 7552868
  }
}
