{
  "geometry": {
    "type": "Point",
    "coordinates": [
      -89.133,
      14.066
    ]
  },
  "type": "Feature",
  "properties": {
    "hierarchy": [
      "tgn:7030481",
      "tgn:1000001",
      "tgn:7005441",
      "tgn:7029392"
    ],
    "placetype": [
      "aat:300008707"
    ],
    "id": 7030481,
    "name:xx": "Acelhuate, Río"
  }
}
