{
  "geometry": {
    "type": "Point",
    "coordinates": [
      124.1667,
      0.9333
    ]
  },
  "type": "Feature",
  "properties": {
    "hierarchy": [
      "tgn:1077525",
      "tgn:1000004",
      "tgn:1001550",
      "tgn:1000116",
      "tgn:7029392"
    ],
    "placetype": [
      "aat:300008347"
    ],
    "id": 1077525,
    "name:xx": "Bolaang Mongondow"
  }
}
