{
  "geometry": {
    "type": "Point",
    "coordinates": [
      -108.1833,
      38.4167
    ]
  },
  "type": "Feature",
  "properties": {
    "hierarchy": [
      "tgn:2276813",
      "tgn:1000001",
      "tgn:7012149",
      "tgn:2000234",
      "tgn:7007158",
      "tgn:7029392"
    ],
    "placetype": [
      "aat:300386845"
    ],
    "id": 2276813,
    "name:xx": "Davis Basin"
  }
}
