{
  "geometry": {
    "type": "Point",
    "coordinates": [
      78.358045,
      24.014923
    ]
  },
  "type": "Feature",
  "properties": {
    "hierarchy": [
      "tgn:7583226",
      "tgn:1000004",
      "tgn:7000198",
      "tgn:1001894",
      "tgn:7029392"
    ],
    "placetype": [
      "aat:300008347"
    ],
    "name:en": "Bāngchi",
    "id": 7583226
  }
}
