{
  "geometry": {
    "type": "Point",
    "coordinates": [
      138.6333,
      37.0167
    ]
  },
  "type": "Feature",
  "properties": {
    "hierarchy": [
      "tgn:1127564",
      "tgn:7016674",
      "tgn:1000004",
      "tgn:1000120",
      "tgn:7029392"
    ],
    "placetype": [
      "aat:300008707"
    ],
    "id": 1127564,
    "name:xx": "Nakatsu-gawa"
  }
}
