{
  "type": "FeatureCollection",
  "features": [
    {
      "geometry": {
        "type": "Point",
        "coordinates": [
          122.457,
          30.709
        ]
      },
      "type": "Feature",
      "properties": {
        "hierarchy": [
          "tgn:1009160",
          "tgn:1000004",
          "tgn:7002076",
          "tgn:1000111",
          "tgn:7029392"
        ],
        "placetype": [
          "aat:300008791"
        ],
        "id": 1009160,
        "name:xx": "Sijiao Shan"
      }
    },
    {
      "geometry": {
        "type": "Point",
        "coordinates": [
          55.2,
          -4.4833
        ]
      },
      "type": "Feature",
      "properties": {
        "hierarchy": [
          "tgn:1009161",
          "tgn:7001703",
          "tgn:7001242",
          "tgn:1000190",
          "tgn:7029392"
        ],
        "placetype": [
          "aat:300008791"
        ],
        "id": 1009161,
        "name:xx": "Silhouette"
      }
    },
    {
      "geometry": {
        "type": "Point",
        "coordinates": [
          -71.5,
          70.9167
        ]
      },
      "type": "Feature",
      "properties": {
        "hierarchy": [
          "tgn:1009162",
          "tgn:7005685",
          "tgn:1000001",
          "tgn:1000296",
          "tgn:7029392"
        ],
        "placetype": [
          "aat:300008791"
        ],
        "id": 1009162,
        "name:xx": "Sillem Island"
      }
    },
    {
      "geometry": {
        "type": "Point",
        "coordinates": [
          122.0333,
          12.8
        ]
      },
      "type": "Feature",
      "properties": {
        "hierarchy": [
          "tgn:1009163",
          "tgn:1000004",
          "tgn:1001504",
          "tgn:1000135",
          "tgn:7029392"
        ],
        "placetype": [
          "aat:300008791"
        ],
        "id": 1009163,
        "name:xx": "Simara Island"
      }
    },
    {
      "geometry": {
        "type": "Point",
        "coordinates": [
          156.55,
          -8.2833
        ]
      },
      "type": "Feature",
      "properties": {
        "hierarchy": [
          "tgn:1009166",
          "tgn:1010171",
          "tgn:1001601",
          "tgn:1000233",
          "tgn:1000006",
          "tgn:7029392"
        ],
        "placetype": [
          "aat:300008791"
        ],
        "id": 1009166,
        "name:xx": "Simbo Island"
      }
    },
    {
      "geometry": {
        "type": "Point",
        "coordinates": [
          -76.5167,
          44.1667
        ]
      },
      "type": "Feature",
      "properties": {
        "hierarchy": [
          "tgn:1009167",
          "tgn:7005685",
          "tgn:1000001",
          "tgn:7013154",
          "tgn:7029392"
        ],
        "placetype": [
          "aat:300008791"
        ],
        "id": 1009167,
        "name:xx": "Simcoe Island"
      }
    },
    {
      "geometry": {
        "type": "Point",
        "coordinates": [
          121.5833,
          5.95
        ]
      },
      "type": "Feature",
      "properties": {
        "hierarchy": [
          "tgn:1009169",
          "tgn:1010060",
          "tgn:1000004",
          "tgn:1001552",
          "tgn:1000135",
          "tgn:7029392"
        ],
        "placetype": [
          "aat:300008791"
        ],
        "id": 1009169,
        "name:xx": "Simisa Island"
      }
    }
  ]
}
