{
  "geometry": {
    "type": "Point",
    "coordinates": [
      9.164167,
      39.1875
    ]
  },
  "type": "Feature",
  "properties": {
    "hierarchy": [
      "tgn:7033991",
      "tgn:1001641",
      "tgn:1000003",
      "tgn:7003121",
      "tgn:1000080",
      "tgn:7029392"
    ],
    "placetype": [
      "aat:300004847"
    ],
    "id": 7033991,
    "name:xx": "Torre Sant'Elia"
  }
}
