{
  "geometry": {
    "type": "Point",
    "coordinates": [
      -0.3667,
      48.2333
    ]
  },
  "type": "Feature",
  "properties": {
    "hierarchy": [
      "tgn:1031994",
      "tgn:1000003",
      "tgn:7002893",
      "tgn:1000070",
      "tgn:7029392"
    ],
    "placetype": [
      "aat:300008347"
    ],
    "id": 1031994,
    "name:xx": "Bais"
  }
}
