{
  "geometry": {
    "type": "Point",
    "coordinates": [
      -88.1667,
      44.9167
    ]
  },
  "type": "Feature",
  "properties": {
    "hierarchy": [
      "tgn:2442974",
      "tgn:1000001",
      "tgn:7012149",
      "tgn:2002341",
      "tgn:7007922",
      "tgn:7029392"
    ],
    "placetype": [
      "aat:300008680"
    ],
    "id": 2442974,
    "name:xx": "Kuplie Lake"
  }
}
