{
  "geometry": {
    "type": "Point",
    "coordinates": [
      -109.4667,
      37.0333
    ]
  },
  "type": "Feature",
  "properties": {
    "hierarchy": [
      "tgn:2189151",
      "tgn:1000001",
      "tgn:7012149",
      "tgn:2002119",
      "tgn:7007827",
      "tgn:7029392"
    ],
    "placetype": [
      "aat:300008798"
    ],
    "id": 2189151,
    "name:xx": "Boundary Butte Mesa"
  }
}
