{
  "geometry": {
    "type": "Point",
    "coordinates": [
      -91.45,
      38.5833
    ]
  },
  "type": "Feature",
  "properties": {
    "hierarchy": [
      "tgn:2334699",
      "tgn:1000001",
      "tgn:7012149",
      "tgn:7007523",
      "tgn:7029392"
    ],
    "placetype": [
      "aat:300008706"
    ],
    "id": 2334699,
    "name:xx": "Fork Creek"
  }
}
