{
  "geometry": {
    "type": "Point",
    "coordinates": [
      34.586944,
      27.950556
    ]
  },
  "type": "Feature",
  "properties": {
    "hierarchy": [
      "tgn:7542168",
      "tgn:7001242",
      "tgn:7016833",
      "tgn:7029392"
    ],
    "placetype": [
      "aat:300379998"
    ],
    "id": 7542168,
    "name:xx": "Thum훮카l, W훮d카 ath"
  }
}
