{
  "geometry": {
    "type": "Point",
    "coordinates": [
      23.2667,
      45.3667
    ]
  },
  "type": "Feature",
  "properties": {
    "hierarchy": [
      "tgn:1050339",
      "tgn:1000003",
      "tgn:7004126",
      "tgn:1000091",
      "tgn:7029392"
    ],
    "placetype": [
      "aat:300008347"
    ],
    "id": 1050339,
    "name:xx": "Vulcan"
  }
}
