{
  "geometry": {
    "type": "Point",
    "coordinates": [
      -78.8833,
      38.0167
    ]
  },
  "type": "Feature",
  "properties": {
    "hierarchy": [
      "tgn:2255617",
      "tgn:2002142",
      "tgn:1000001",
      "tgn:7012149",
      "tgn:7007919",
      "tgn:7029392"
    ],
    "placetype": [
      "aat:300008798"
    ],
    "id": 2255617,
    "name:xx": "Copelands Tetons"
  }
}
