{
  "type": "FeatureCollection",
  "features": [
    {
      "geometry": {
        "type": "Point",
        "coordinates": [
          -111.7333,
          39.4
        ]
      },
      "type": "Feature",
      "properties": {
        "hierarchy": [
          "tgn:2753050",
          "tgn:1000001",
          "tgn:7012149",
          "tgn:7007827",
          "tgn:7029392"
        ],
        "placetype": [
          "aat:300008761"
        ],
        "id": 2753050,
        "name:xx": "Water Hollow"
      }
    },
    {
      "geometry": {
        "type": "Point",
        "coordinates": [
          -111.8167,
          39.5167
        ]
      },
      "type": "Feature",
      "properties": {
        "hierarchy": [
          "tgn:2753051",
          "tgn:1000001",
          "tgn:7012149",
          "tgn:2002112",
          "tgn:7007827",
          "tgn:7029392"
        ],
        "placetype": [
          "aat:300008761"
        ],
        "id": 2753051,
        "name:xx": "Water Hollow"
      }
    },
    {
      "geometry": {
        "type": "Point",
        "coordinates": [
          -111.2667,
          39.9833
        ]
      },
      "type": "Feature",
      "properties": {
        "hierarchy": [
          "tgn:2753052",
          "tgn:1000001",
          "tgn:7012149",
          "tgn:2002125",
          "tgn:7007827",
          "tgn:7029392"
        ],
        "placetype": [
          "aat:300008761"
        ],
        "id": 2753052,
        "name:xx": "Water Hollow"
      }
    },
    {
      "geometry": {
        "type": "Point",
        "coordinates": [
          -111.5833,
          41.3167
        ]
      },
      "type": "Feature",
      "properties": {
        "hierarchy": [
          "tgn:2753053",
          "tgn:1000001",
          "tgn:7012149",
          "tgn:2002129",
          "tgn:7007827",
          "tgn:7029392"
        ],
        "placetype": [
          "aat:300008761"
        ],
        "id": 2753053,
        "name:xx": "Water Hollow"
      }
    },
    {
      "geometry": {
        "type": "Point",
        "coordinates": [
          -112.15,
          41.9833
        ]
      },
      "type": "Feature",
      "properties": {
        "hierarchy": [
          "tgn:2753054",
          "tgn:1000001",
          "tgn:2002102",
          "tgn:7012149",
          "tgn:7007827",
          "tgn:7029392"
        ],
        "placetype": [
          "aat:300008761"
        ],
        "id": 2753054,
        "name:xx": "Water Hollow"
      }
    },
    {
      "geometry": {
        "type": "Point",
        "coordinates": [
          -111.1167,
          40.3
        ]
      },
      "type": "Feature",
      "properties": {
        "hierarchy": [
          "tgn:2753055",
          "tgn:1000001",
          "tgn:7012149",
          "tgn:2002126",
          "tgn:7007827",
          "tgn:7029392"
        ],
        "placetype": [
          "aat:300008761"
        ],
        "id": 2753055,
        "name:xx": "Water Hollow"
      }
    },
    {
      "geometry": {
        "type": "Point",
        "coordinates": [
          -110.2667,
          40.4667
        ]
      },
      "type": "Feature",
      "properties": {
        "hierarchy": [
          "tgn:2753056",
          "tgn:1000001",
          "tgn:2002107",
          "tgn:7012149",
          "tgn:7007827",
          "tgn:7029392"
        ],
        "placetype": [
          "aat:300008761"
        ],
        "id": 2753056,
        "name:xx": "Water Hollow"
      }
    },
    {
      "geometry": {
        "type": "Point",
        "coordinates": [
          -81.95,
          36.4833
        ]
      },
      "type": "Feature",
      "properties": {
        "hierarchy": [
          "tgn:2753057",
          "tgn:1000001",
          "tgn:7012149",
          "tgn:2001846",
          "tgn:7007825",
          "tgn:7029392"
        ],
        "placetype": [
          "aat:300008699"
        ],
        "id": 2753057,
        "name:xx": "Water Hollow Branch"
      }
    },
    {
      "geometry": {
        "type": "Point",
        "coordinates": [
          -111.5667,
          38.9333
        ]
      },
      "type": "Feature",
      "properties": {
        "hierarchy": [
          "tgn:2753058",
          "tgn:1000001",
          "tgn:7012149",
          "tgn:2002121",
          "tgn:7007827",
          "tgn:7029392"
        ],
        "placetype": [
          "aat:300266640"
        ],
        "id": 2753058,
        "name:xx": "Water Hollow Ridge"
      }
    },
    {
      "geometry": {
        "type": "Point",
        "coordinates": [
          -111.0667,
          40.2333
        ]
      },
      "type": "Feature",
      "properties": {
        "hierarchy": [
          "tgn:2753059",
          "tgn:1000001",
          "tgn:7012149",
          "tgn:2002126",
          "tgn:7007827",
          "tgn:7029392"
        ],
        "placetype": [
          "aat:300006075"
        ],
        "id": 2753059,
        "name:xx": "Water Hollow Tunnel"
      }
    }
  ]
}
