{
  "geometry": {
    "type": "Point",
    "coordinates": [
      -70.55,
      -33.85
    ]
  },
  "type": "Feature",
  "properties": {
    "hierarchy": [
      "tgn:7281150",
      "tgn:1001708",
      "tgn:1000049",
      "tgn:1000002",
      "tgn:7029392"
    ],
    "placetype": [
      "aat:300008795"
    ],
    "id": 7281150,
    "name:xx": "San Francisco, Cerro"
  }
}
