{
  "geometry": {
    "type": "Point",
    "coordinates": [
      6.0333,
      46.25
    ]
  },
  "type": "Feature",
  "properties": {
    "hierarchy": [
      "tgn:1035334",
      "tgn:1000003",
      "tgn:1000070",
      "tgn:7002897",
      "tgn:7029392"
    ],
    "placetype": [
      "aat:300008347"
    ],
    "id": 1035334,
    "name:xx": "Saint Génis-Pouilly"
  }
}
