{
  "geometry": {
    "type": "Point",
    "coordinates": [
      -73.8333,
      42.3333
    ]
  },
  "type": "Feature",
  "properties": {
    "hierarchy": [
      "tgn:2068704",
      "tgn:1000001",
      "tgn:7012149",
      "tgn:1002423",
      "tgn:7007568",
      "tgn:7029392"
    ],
    "placetype": [
      "aat:300006448"
    ],
    "id": 2068704,
    "name:xx": "Coxsackie Correctional Facility"
  }
}
