{
  "geometry": {
    "type": "Point",
    "coordinates": [
      -80.9667,
      35.85
    ]
  },
  "type": "Feature",
  "properties": {
    "hierarchy": [
      "tgn:2447006",
      "tgn:1000001",
      "tgn:7012149",
      "tgn:2001507",
      "tgn:7007709",
      "tgn:7029392"
    ],
    "placetype": [
      "aat:300008347"
    ],
    "id": 2447006,
    "name:xx": "Liberty Hill"
  }
}
