{
  "geometry": {
    "type": "Point",
    "coordinates": [
      -71.9667,
      42.5667
    ]
  },
  "type": "Feature",
  "properties": {
    "hierarchy": [
      "tgn:2301426",
      "tgn:1000001",
      "tgn:7012149",
      "tgn:1003038",
      "tgn:7007517",
      "tgn:7029392"
    ],
    "placetype": [
      "aat:300006191"
    ],
    "id": 2301426,
    "name:xx": "Dunn Pond"
  }
}
