{
  "geometry": {
    "type": "Point",
    "coordinates": [
      -89.45,
      30.6667
    ]
  },
  "type": "Feature",
  "properties": {
    "hierarchy": [
      "tgn:2349261",
      "tgn:1000001",
      "tgn:7012149",
      "tgn:2001140",
      "tgn:7007522",
      "tgn:7029392"
    ],
    "placetype": [
      "aat:300006191"
    ],
    "id": 2349261,
    "name:xx": "Gilberts Lake"
  }
}
