{
  "geometry": {
    "type": "Point",
    "coordinates": [
      -90.35,
      43.0333
    ]
  },
  "type": "Feature",
  "properties": {
    "hierarchy": [
      "tgn:2672489",
      "tgn:1000001",
      "tgn:7012149",
      "tgn:2002326",
      "tgn:7007922",
      "tgn:7029392"
    ],
    "placetype": [
      "aat:300008761"
    ],
    "id": 2672489,
    "name:xx": "Smoky Hollow"
  }
}
