{
  "geometry": {
    "type": "Point",
    "coordinates": [
      -118.15,
      36.4833
    ]
  },
  "type": "Feature",
  "properties": {
    "hierarchy": [
      "tgn:2453685",
      "tgn:1000001",
      "tgn:7012149",
      "tgn:2000183",
      "tgn:7007157",
      "tgn:7029392"
    ],
    "placetype": [
      "aat:300008706"
    ],
    "id": 2453685,
    "name:xx": "Little Cottonwood Creek"
  }
}
