{
  "geometry": {
    "type": "Point",
    "coordinates": [
      -87.45,
      33.7167
    ]
  },
  "type": "Feature",
  "properties": {
    "hierarchy": [
      "tgn:2343400",
      "tgn:7002659",
      "tgn:1000001",
      "tgn:7012149",
      "tgn:2000063",
      "tgn:7029392"
    ],
    "placetype": [
      "aat:300008798"
    ],
    "id": 2343400,
    "name:xx": "Gaines Hill"
  }
}
