{
  "geometry": {
    "type": "Point",
    "coordinates": [
      -113.9333,
      46.7167
    ]
  },
  "type": "Feature",
  "properties": {
    "hierarchy": [
      "tgn:2164549",
      "tgn:1000001",
      "tgn:7012149",
      "tgn:2001300",
      "tgn:7007524",
      "tgn:7029392"
    ],
    "placetype": [
      "aat:300000390"
    ],
    "id": 2164549,
    "name:xx": "Berry Rush Mine"
  }
}
