{
  "geometry": {
    "type": "Point",
    "coordinates": [
      -84.1833,
      37.1167
    ]
  },
  "type": "Feature",
  "properties": {
    "hierarchy": [
      "tgn:2462455",
      "tgn:1000001",
      "tgn:7012149",
      "tgn:2000808",
      "tgn:7007255",
      "tgn:7029392"
    ],
    "placetype": [
      "aat:300008706"
    ],
    "id": 2462455,
    "name:xx": "Little White Oak Creek"
  }
}
