{
  "geometry": {
    "type": "Point",
    "coordinates": [
      -113.25,
      47.7667
    ]
  },
  "type": "Feature",
  "properties": {
    "hierarchy": [
      "tgn:2606492",
      "tgn:1000001",
      "tgn:7012149",
      "tgn:2001274",
      "tgn:7007524",
      "tgn:7029392"
    ],
    "placetype": [
      "aat:300008706"
    ],
    "id": 2606492,
    "name:xx": "Rambler Creek"
  }
}
