{
  "type": "FeatureCollection",
  "features": [
    {
      "geometry": {
        "type": "Point",
        "coordinates": [
          -79.2333,
          43.1333
        ]
      },
      "type": "Feature",
      "properties": {
        "hierarchy": [
          "tgn:1015161",
          "tgn:7005685",
          "tgn:1000001",
          "tgn:7013154",
          "tgn:7029392"
        ],
        "placetype": [
          "aat:300008347"
        ],
        "id": 1015161,
        "name:xx": "Thorold"
      }
    },
    {
      "geometry": {
        "type": "Point",
        "coordinates": [
          -79.2,
          43.1
        ]
      },
      "type": "Feature",
      "properties": {
        "hierarchy": [
          "tgn:1015162",
          "tgn:7005685",
          "tgn:1000001",
          "tgn:7013154",
          "tgn:7029392"
        ],
        "placetype": [
          "aat:300008347"
        ],
        "id": 1015162,
        "name:xx": "Thorold South"
      }
    },
    {
      "geometry": {
        "type": "Point",
        "coordinates": [
          -82.4333,
          42.25
        ]
      },
      "type": "Feature",
      "properties": {
        "hierarchy": [
          "tgn:1015164",
          "tgn:7005685",
          "tgn:1000001",
          "tgn:7013154",
          "tgn:7029392"
        ],
        "placetype": [
          "aat:300008347"
        ],
        "id": 1015164,
        "name:xx": "Tilbury"
      }
    },
    {
      "geometry": {
        "type": "Point",
        "coordinates": [
          -80.7333,
          42.8833
        ]
      },
      "type": "Feature",
      "properties": {
        "hierarchy": [
          "tgn:1015165",
          "tgn:7005685",
          "tgn:1000001",
          "tgn:7013154",
          "tgn:7029392"
        ],
        "placetype": [
          "aat:300008347"
        ],
        "id": 1015165,
        "name:xx": "Tillsonburg"
      }
    },
    {
      "geometry": {
        "type": "Point",
        "coordinates": [
          -81.65,
          45.25
        ]
      },
      "type": "Feature",
      "properties": {
        "hierarchy": [
          "tgn:1015167",
          "tgn:7005685",
          "tgn:1000001",
          "tgn:7013154",
          "tgn:7029392"
        ],
        "placetype": [
          "aat:300008347"
        ],
        "id": 1015167,
        "name:xx": "Tobermory"
      }
    },
    {
      "geometry": {
        "type": "Point",
        "coordinates": [
          -79.8,
          44.0333
        ]
      },
      "type": "Feature",
      "properties": {
        "hierarchy": [
          "tgn:1015169",
          "tgn:7005685",
          "tgn:1000001",
          "tgn:7013154",
          "tgn:7029392"
        ],
        "placetype": [
          "aat:300008347"
        ],
        "id": 1015169,
        "name:xx": "Tottenham"
      }
    }
  ]
}
