{
  "geometry": {
    "type": "Point",
    "coordinates": [
      -101.5833,
      32.6167
    ]
  },
  "type": "Feature",
  "properties": {
    "hierarchy": [
      "tgn:2361348",
      "tgn:1000001",
      "tgn:2001943",
      "tgn:7012149",
      "tgn:7007826",
      "tgn:7029392"
    ],
    "placetype": [
      "aat:300006191"
    ],
    "id": 2361348,
    "name:xx": "Gravel Tank"
  }
}
