{
  "geometry": {
    "type": "Point",
    "coordinates": [
      120.2712,
      22.6229
    ]
  },
  "type": "Feature",
  "properties": {
    "hierarchy": [
      "tgn:7496868",
      "tgn:7001004",
      "tgn:1000004",
      "tgn:1000141",
      "tgn:7029392"
    ],
    "placetype": [
      "aat:300386996"
    ],
    "id": 7496868,
    "name:xx": "Gaoxiong Gangwuju"
  }
}
