{
  "geometry": {
    "type": "Point",
    "coordinates": [
      -124.05,
      41.5167
    ]
  },
  "type": "Feature",
  "properties": {
    "hierarchy": [
      "tgn:2332133",
      "tgn:1000001",
      "tgn:7012149",
      "tgn:2000180",
      "tgn:7007157",
      "tgn:7029392"
    ],
    "placetype": [
      "aat:300266640"
    ],
    "id": 2332133,
    "name:xx": "Flint Ridge"
  }
}
