{
  "type": "FeatureCollection",
  "features": [
    {
      "geometry": {
        "type": "Point",
        "coordinates": [
          -70.6,
          -29.966667
        ]
      },
      "type": "Feature",
      "properties": {
        "hierarchy": [
          "tgn:7309380",
          "tgn:1001657",
          "tgn:1000049",
          "tgn:1000002",
          "tgn:7029392"
        ],
        "placetype": [
          "aat:300008697"
        ],
        "id": 7309380,
        "name:xx": "Los Pozos, Aguada"
      }
    },
    {
      "geometry": {
        "type": "Point",
        "coordinates": [
          -70.933333,
          -29.233333
        ]
      },
      "type": "Feature",
      "properties": {
        "hierarchy": [
          "tgn:7309381",
          "tgn:1001657",
          "tgn:1000049",
          "tgn:1000002",
          "tgn:7029392"
        ],
        "placetype": [
          "aat:300008697"
        ],
        "id": 7309381,
        "name:xx": "Los Pozos, Aguada"
      }
    },
    {
      "geometry": {
        "type": "Point",
        "coordinates": [
          -69.266667,
          -25.283333
        ]
      },
      "type": "Feature",
      "properties": {
        "hierarchy": [
          "tgn:7309382",
          "tgn:7016598",
          "tgn:1000049",
          "tgn:1000002",
          "tgn:7029392"
        ],
        "placetype": [
          "aat:300006207"
        ],
        "id": 7309382,
        "name:xx": "Los Pozos"
      }
    },
    {
      "geometry": {
        "type": "Point",
        "coordinates": [
          -70.333333,
          -26.533333
        ]
      },
      "type": "Feature",
      "properties": {
        "hierarchy": [
          "tgn:7309383",
          "tgn:1001630",
          "tgn:1000049",
          "tgn:1000002",
          "tgn:7029392"
        ],
        "placetype": [
          "aat:300387033"
        ],
        "id": 7309383,
        "name:xx": "Los Pozos"
      }
    },
    {
      "geometry": {
        "type": "Point",
        "coordinates": [
          -70.133333,
          -27.55
        ]
      },
      "type": "Feature",
      "properties": {
        "hierarchy": [
          "tgn:7309384",
          "tgn:1001630",
          "tgn:1000049",
          "tgn:1000002",
          "tgn:7029392"
        ],
        "placetype": [
          "aat:300008697"
        ],
        "id": 7309384,
        "name:xx": "Los Pozos"
      }
    },
    {
      "geometry": {
        "type": "Point",
        "coordinates": [
          -71.133333,
          -30.933333
        ]
      },
      "type": "Feature",
      "properties": {
        "hierarchy": [
          "tgn:7309385",
          "tgn:1001657",
          "tgn:1000049",
          "tgn:1000002",
          "tgn:7029392"
        ],
        "placetype": [
          "aat:300387200"
        ],
        "id": 7309385,
        "name:xx": "Los Pozos"
      }
    },
    {
      "geometry": {
        "type": "Point",
        "coordinates": [
          -70.05,
          -28.85
        ]
      },
      "type": "Feature",
      "properties": {
        "hierarchy": [
          "tgn:7309386",
          "tgn:1001630",
          "tgn:1000049",
          "tgn:1000002",
          "tgn:7029392"
        ],
        "placetype": [
          "aat:300005433"
        ],
        "id": 7309386,
        "name:xx": "Los Pozos"
      }
    },
    {
      "geometry": {
        "type": "Point",
        "coordinates": [
          -72.2,
          -35.083333
        ]
      },
      "type": "Feature",
      "properties": {
        "hierarchy": [
          "tgn:7309387",
          "tgn:1001705",
          "tgn:1000049",
          "tgn:1000002",
          "tgn:7029392"
        ],
        "placetype": [
          "aat:300008680"
        ],
        "id": 7309387,
        "name:xx": "Los Pozones, Laguna"
      }
    },
    {
      "geometry": {
        "type": "Point",
        "coordinates": [
          -70.55,
          -32.966667
        ]
      },
      "type": "Feature",
      "properties": {
        "hierarchy": [
          "tgn:7309388",
          "tgn:1001768",
          "tgn:1000049",
          "tgn:1000002",
          "tgn:7029392"
        ],
        "placetype": [
          "aat:300266554",
          "aat:300008699"
        ],
        "id": 7309388,
        "name:xx": "Los Potros, Quebrada"
      }
    },
    {
      "geometry": {
        "type": "Point",
        "coordinates": [
          -70.516667,
          -32.9
        ]
      },
      "type": "Feature",
      "properties": {
        "hierarchy": [
          "tgn:7309389",
          "tgn:1001768",
          "tgn:1000049",
          "tgn:1000002",
          "tgn:7029392"
        ],
        "placetype": [
          "aat:300008798"
        ],
        "id": 7309389,
        "name:xx": "Los Potrillos, Cerro"
      }
    }
  ]
}
