{
  "geometry": {
    "type": "Point",
    "coordinates": [
      32.27253,
      29.298068
    ]
  },
  "type": "Feature",
  "properties": {
    "hierarchy": [
      "tgn:7528065",
      "tgn:7001242",
      "tgn:7016833",
      "tgn:1001110",
      "tgn:7029392"
    ],
    "placetype": [
      "aat:300379998"
    ],
    "name:en": "Umm Buraykīn, Wādī",
    "id": 7528065
  }
}
