{
  "type": "FeatureCollection",
  "features": [
    {
      "geometry": {
        "type": "Point",
        "coordinates": [
          -123.25,
          47.05
        ]
      },
      "type": "Feature",
      "properties": {
        "hierarchy": [
          "tgn:2116194",
          "tgn:1000001",
          "tgn:7012149",
          "tgn:1002418",
          "tgn:7007920",
          "tgn:7029392"
        ],
        "placetype": [
          "aat:300008347"
        ],
        "id": 2116194,
        "name:xx": "McCleary"
      }
    },
    {
      "geometry": {
        "type": "Point",
        "coordinates": [
          -123.2667,
          47.0667
        ]
      },
      "type": "Feature",
      "properties": {
        "hierarchy": [
          "tgn:2116198",
          "tgn:1000001",
          "tgn:7012149",
          "tgn:1002418",
          "tgn:7007920",
          "tgn:7029392"
        ],
        "placetype": [
          "aat:300387016"
        ],
        "id": 2116198,
        "name:xx": "McCleary Junction"
      }
    },
    {
      "geometry": {
        "type": "Point",
        "coordinates": [
          -117.3,
          47.1833
        ]
      },
      "type": "Feature",
      "properties": {
        "hierarchy": [
          "tgn:2116199",
          "tgn:1000001",
          "tgn:7012149",
          "tgn:2002252",
          "tgn:7007920",
          "tgn:7029392"
        ],
        "placetype": [
          "aat:300387016"
        ],
        "id": 2116199,
        "name:xx": "McCoy"
      }
    }
  ]
}
