{
  "geometry": {
    "type": "Point",
    "coordinates": [
      9.45111,
      45.86833
    ]
  },
  "type": "Feature",
  "properties": {
    "hierarchy": [
      "tgn:7047971",
      "tgn:7005023",
      "tgn:1000003",
      "tgn:7003237",
      "tgn:1000080",
      "tgn:7029392"
    ],
    "placetype": [
      "aat:300008805"
    ],
    "id": 7047971,
    "name:xx": "Erna, Piani d'"
  }
}
