{
  "geometry": {
    "type": "Point",
    "coordinates": [
      -80.85,
      32.6833
    ]
  },
  "type": "Feature",
  "properties": {
    "hierarchy": [
      "tgn:2096981",
      "tgn:1000001",
      "tgn:2001749",
      "tgn:7012149",
      "tgn:7007712",
      "tgn:7029392"
    ],
    "placetype": [
      "aat:300008347"
    ],
    "id": 2096981,
    "name:xx": "Yemassee"
  }
}
