{
  "geometry": {
    "type": "Point",
    "coordinates": [
      -112.1167,
      46.3333
    ]
  },
  "type": "Feature",
  "properties": {
    "hierarchy": [
      "tgn:2534365",
      "tgn:1000001",
      "tgn:7012149",
      "tgn:2001281",
      "tgn:7007524",
      "tgn:7029392"
    ],
    "placetype": [
      "aat:300000390"
    ],
    "id": 2534365,
    "name:xx": "NE NE Section 29 Mine"
  }
}
