{
  "type": "FeatureCollection",
  "features": [
    {
      "geometry": {
        "type": "Point",
        "coordinates": [
          -117.7,
          33.5333
        ]
      },
      "type": "Feature",
      "properties": {
        "hierarchy": [
          "tgn:2702631",
          "tgn:1000001",
          "tgn:7012149",
          "tgn:7007157",
          "tgn:1002748",
          "tgn:7029392"
        ],
        "placetype": [
          "aat:300006191"
        ],
        "id": 2702631,
        "name:xx": "Sulphur Creek Reservoir"
      }
    },
    {
      "geometry": {
        "type": "Point",
        "coordinates": [
          -110.8167,
          41.15
        ]
      },
      "type": "Feature",
      "properties": {
        "hierarchy": [
          "tgn:2702632",
          "tgn:1000001",
          "tgn:7012149",
          "tgn:2002385",
          "tgn:7007923",
          "tgn:7029392"
        ],
        "placetype": [
          "aat:300006191"
        ],
        "id": 2702632,
        "name:xx": "Sulphur Creek Reservoir"
      }
    },
    {
      "geometry": {
        "type": "Point",
        "coordinates": [
          -120,
          46.2667
        ]
      },
      "type": "Feature",
      "properties": {
        "hierarchy": [
          "tgn:2702633",
          "tgn:1000001",
          "tgn:7012149",
          "tgn:1003042",
          "tgn:7007920",
          "tgn:7029392"
        ],
        "placetype": [
          "aat:300006075"
        ],
        "id": 2702633,
        "name:xx": "Sulphur Creek Wasteway"
      }
    },
    {
      "geometry": {
        "type": "Point",
        "coordinates": [
          -85.45,
          40
        ]
      },
      "type": "Feature",
      "properties": {
        "hierarchy": [
          "tgn:2702634",
          "tgn:1000001",
          "tgn:7012149",
          "tgn:1002468",
          "tgn:7007252",
          "tgn:7029392"
        ],
        "placetype": [
          "aat:300008699"
        ],
        "id": 2702634,
        "name:xx": "Sulphur Drain"
      }
    },
    {
      "geometry": {
        "type": "Point",
        "coordinates": [
          -109.1833,
          31.8167
        ]
      },
      "type": "Feature",
      "properties": {
        "hierarchy": [
          "tgn:2702635",
          "tgn:1000001",
          "tgn:7006451",
          "tgn:2000091",
          "tgn:7012149",
          "tgn:7029392"
        ],
        "placetype": [
          "aat:300008761"
        ],
        "id": 2702635,
        "name:xx": "Sulphur Draw"
      }
    },
    {
      "geometry": {
        "type": "Point",
        "coordinates": [
          -108.8167,
          40.05
        ]
      },
      "type": "Feature",
      "properties": {
        "hierarchy": [
          "tgn:2702636",
          "tgn:1000001",
          "tgn:7012149",
          "tgn:7007158",
          "tgn:2000243",
          "tgn:7029392"
        ],
        "placetype": [
          "aat:300008761"
        ],
        "id": 2702636,
        "name:xx": "Sulphur Draw"
      }
    },
    {
      "geometry": {
        "type": "Point",
        "coordinates": [
          -100.45,
          31.4333
        ]
      },
      "type": "Feature",
      "properties": {
        "hierarchy": [
          "tgn:2702637",
          "tgn:1000001",
          "tgn:7012149",
          "tgn:2002085",
          "tgn:7007826",
          "tgn:7029392"
        ],
        "placetype": [
          "aat:300008761"
        ],
        "id": 2702637,
        "name:xx": "Sulphur Draw"
      }
    },
    {
      "geometry": {
        "type": "Point",
        "coordinates": [
          -103.0333,
          33.5667
        ]
      },
      "type": "Feature",
      "properties": {
        "hierarchy": [
          "tgn:2702638",
          "tgn:1000001",
          "tgn:7012149",
          "tgn:7007826",
          "tgn:7029392"
        ],
        "placetype": [
          "aat:300008761"
        ],
        "id": 2702638,
        "name:xx": "Sulphur Draw"
      }
    },
    {
      "geometry": {
        "type": "Point",
        "coordinates": [
          -106.2,
          43.5167
        ]
      },
      "type": "Feature",
      "properties": {
        "hierarchy": [
          "tgn:2702639",
          "tgn:1000001",
          "tgn:7012149",
          "tgn:2002374",
          "tgn:7007923",
          "tgn:7029392"
        ],
        "placetype": [
          "aat:300008761"
        ],
        "id": 2702639,
        "name:xx": "Sulphur Draw"
      }
    }
  ]
}
