{
  "geometry": {
    "type": "Point",
    "coordinates": [
      -82.15,
      36.7833
    ]
  },
  "type": "Feature",
  "properties": {
    "hierarchy": [
      "tgn:2169653",
      "tgn:1000001",
      "tgn:7012149",
      "tgn:7007919",
      "tgn:7029392"
    ],
    "placetype": [
      "aat:300008706"
    ],
    "id": 2169653,
    "name:xx": "Big Moccasin Creek"
  }
}
