{
  "geometry": {
    "type": "Point",
    "coordinates": [
      120.7435,
      23.8364
    ]
  },
  "type": "Feature",
  "properties": {
    "hierarchy": [
      "tgn:7467319",
      "tgn:7488858",
      "tgn:1000004",
      "tgn:1000141",
      "tgn:7029392"
    ],
    "placetype": [
      "aat:300008347"
    ],
    "id": 7467319,
    "name:xx": "Ailiaobu"
  }
}
