{
  "geometry": {
    "type": "Point",
    "coordinates": [
      -85.85,
      40.3667
    ]
  },
  "type": "Feature",
  "properties": {
    "hierarchy": [
      "tgn:2371433",
      "tgn:1000001",
      "tgn:7012149",
      "tgn:1002623",
      "tgn:7007252",
      "tgn:7029392"
    ],
    "placetype": [
      "aat:300006075"
    ],
    "id": 2371433,
    "name:xx": "Haines Ditch"
  }
}
