{
  "geometry": {
    "type": "Point",
    "coordinates": [
      -70.15,
      45.9833
    ]
  },
  "type": "Feature",
  "properties": {
    "hierarchy": [
      "tgn:2683511",
      "tgn:1000001",
      "tgn:7012149",
      "tgn:2000930",
      "tgn:7007515",
      "tgn:7029392"
    ],
    "placetype": [
      "aat:300008680"
    ],
    "id": 2683511,
    "name:xx": "Spaulding Pond"
  }
}
