{
  "type": "FeatureCollection",
  "features": [
    {
      "geometry": {
        "type": "Point",
        "coordinates": [
          -3.65,
          58.266667
        ]
      },
      "type": "Feature",
      "properties": {
        "hierarchy": [
          "tgn:7465463",
          "tgn:7002444",
          "tgn:1000003",
          "tgn:7008082",
          "tgn:7008591",
          "tgn:7029392"
        ],
        "placetype": [
          "aat:300008680"
        ],
        "name:en": "Bò Riabhach, Lochan nam",
        "id": 7465463
      }
    },
    {
      "geometry": {
        "type": "Point",
        "coordinates": [
          -3.483333,
          58.216667
        ]
      },
      "type": "Feature",
      "properties": {
        "hierarchy": [
          "tgn:7465464",
          "tgn:7002444",
          "tgn:1000003",
          "tgn:7008082",
          "tgn:7008591",
          "tgn:7029392"
        ],
        "placetype": [
          "aat:300008347"
        ],
        "name:en": "Borgue",
        "id": 7465464
      }
    },
    {
      "geometry": {
        "type": "Point",
        "coordinates": [
          -4.133333,
          54.8
        ]
      },
      "type": "Feature",
      "properties": {
        "hierarchy": [
          "tgn:7465465",
          "tgn:7002444",
          "tgn:7008074",
          "tgn:1000003",
          "tgn:7008591",
          "tgn:7029392"
        ],
        "placetype": [
          "aat:300008347"
        ],
        "name:en": "Borgue",
        "id": 7465465
      }
    },
    {
      "geometry": {
        "type": "Point",
        "coordinates": [
          -4.283333,
          58.5
        ]
      },
      "type": "Feature",
      "properties": {
        "hierarchy": [
          "tgn:7465466",
          "tgn:7002444",
          "tgn:1000003",
          "tgn:7008082",
          "tgn:7008591",
          "tgn:7029392"
        ],
        "placetype": [
          "aat:300004792"
        ],
        "name:en": "Borgie House",
        "id": 7465466
      }
    },
    {
      "geometry": {
        "type": "Point",
        "coordinates": [
          -4.3,
          58.516667
        ]
      },
      "type": "Feature",
      "properties": {
        "hierarchy": [
          "tgn:7465467",
          "tgn:7002444",
          "tgn:1000003",
          "tgn:7008082",
          "tgn:7008591",
          "tgn:7029392"
        ],
        "placetype": [
          "aat:300008699"
        ],
        "name:en": "Borgie, River",
        "id": 7465467
      }
    },
    {
      "geometry": {
        "type": "Point",
        "coordinates": [
          -7.033333,
          57.85
        ]
      },
      "type": "Feature",
      "properties": {
        "hierarchy": [
          "tgn:7465468",
          "tgn:7002444",
          "tgn:1000003",
          "tgn:7008094",
          "tgn:7008591",
          "tgn:7029392"
        ],
        "placetype": [
          "aat:300132316"
        ],
        "name:en": "Borgh, Camus nam",
        "id": 7465468
      }
    }
  ]
}
