{
  "geometry": {
    "type": "Point",
    "coordinates": [
      -4.5667,
      5.6667
    ]
  },
  "type": "Feature",
  "properties": {
    "hierarchy": [
      "tgn:1090403",
      "tgn:1000484",
      "tgn:7001242",
      "tgn:1000168",
      "tgn:7029392"
    ],
    "placetype": [
      "aat:300008347"
    ],
    "id": 1090403,
    "name:xx": "Sikensi"
  }
}
