{
  "geometry": {
    "type": "Point",
    "coordinates": [
      -111.95,
      35.9667
    ]
  },
  "type": "Feature",
  "properties": {
    "hierarchy": [
      "tgn:2205022",
      "tgn:1000001",
      "tgn:7006451",
      "tgn:2000092",
      "tgn:7012149",
      "tgn:7029392"
    ],
    "placetype": [
      "aat:300006191"
    ],
    "id": 2205022,
    "name:xx": "Buggeln Tank"
  }
}
