{
  "geometry": {
    "type": "Point",
    "coordinates": [
      -74.2833,
      44.4167
    ]
  },
  "type": "Feature",
  "properties": {
    "hierarchy": [
      "tgn:2495128",
      "tgn:1000001",
      "tgn:7012149",
      "tgn:7013941",
      "tgn:7007568",
      "tgn:7029392"
    ],
    "placetype": [
      "aat:300008680"
    ],
    "id": 2495128,
    "name:xx": "Marvin Pond"
  }
}
