{
  "geometry": {
    "type": "Point",
    "coordinates": [
      -99.0667,
      31.3167
    ]
  },
  "type": "Feature",
  "properties": {
    "hierarchy": [
      "tgn:2769851",
      "tgn:1000001",
      "tgn:7012149",
      "tgn:2002069",
      "tgn:7007826",
      "tgn:7029392"
    ],
    "placetype": [
      "aat:300008706"
    ],
    "id": 2769851,
    "name:xx": "Wilbarger Creek"
  }
}
