{
  "geometry": {
    "type": "Point",
    "coordinates": [
      -161.25,
      65.2667
    ]
  },
  "type": "Feature",
  "properties": {
    "hierarchy": [
      "tgn:2522156",
      "tgn:7006450",
      "tgn:1000001",
      "tgn:7012149",
      "tgn:2000079",
      "tgn:7029392"
    ],
    "placetype": [
      "aat:300008706"
    ],
    "id": 2522156,
    "name:xx": "Moon Creek"
  }
}
