{
  "geometry": {
    "type": "Point",
    "coordinates": [
      -79.1833,
      41.25
    ]
  },
  "type": "Feature",
  "properties": {
    "hierarchy": [
      "tgn:2607496",
      "tgn:1000001",
      "tgn:7012149",
      "tgn:1002520",
      "tgn:7007710",
      "tgn:7029392"
    ],
    "placetype": [
      "aat:300008699"
    ],
    "id": 2607496,
    "name:xx": "Rankin Run"
  }
}
