{
  "geometry": {
    "type": "Point",
    "coordinates": [
      111.6667,
      56.1333
    ]
  },
  "type": "Feature",
  "properties": {
    "hierarchy": [
      "tgn:1060679",
      "tgn:1000004",
      "tgn:7011500",
      "tgn:7002435",
      "tgn:7029392"
    ],
    "placetype": [
      "aat:300008347"
    ],
    "id": 1060679,
    "name:xx": "Uoyan"
  }
}
