{
  "type": "FeatureCollection",
  "features": [
    {
      "geometry": {
        "type": "Point",
        "coordinates": [
          -84.4333,
          41.3333
        ]
      },
      "type": "Feature",
      "properties": {
        "hierarchy": [
          "tgn:2563800",
          "tgn:1000001",
          "tgn:1002326",
          "tgn:7012149",
          "tgn:7007706",
          "tgn:7029392"
        ],
        "placetype": [
          "aat:300006191"
        ],
        "id": 2563800,
        "name:xx": "Oxbow Lake"
      }
    },
    {
      "geometry": {
        "type": "Point",
        "coordinates": [
          -75.8833,
          41.6
        ]
      },
      "type": "Feature",
      "properties": {
        "hierarchy": [
          "tgn:2563801",
          "tgn:1000001",
          "tgn:7012149",
          "tgn:1003041",
          "tgn:7007710",
          "tgn:7029392"
        ],
        "placetype": [
          "aat:300008680"
        ],
        "id": 2563801,
        "name:xx": "Oxbow Lake"
      }
    },
    {
      "geometry": {
        "type": "Point",
        "coordinates": [
          -105.3833,
          30.8667
        ]
      },
      "type": "Feature",
      "properties": {
        "hierarchy": [
          "tgn:2563802",
          "tgn:1000001",
          "tgn:7012149",
          "tgn:2002005",
          "tgn:7007826",
          "tgn:7029392"
        ],
        "placetype": [
          "aat:300006191"
        ],
        "id": 2563802,
        "name:xx": "Oxbow Lake"
      }
    },
    {
      "geometry": {
        "type": "Point",
        "coordinates": [
          -122.6167,
          46.9833
        ]
      },
      "type": "Feature",
      "properties": {
        "hierarchy": [
          "tgn:2563803",
          "tgn:1000001",
          "tgn:7012149",
          "tgn:1002785",
          "tgn:7007920",
          "tgn:7029392"
        ],
        "placetype": [
          "aat:300006191"
        ],
        "id": 2563803,
        "name:xx": "Oxbow Lake"
      }
    },
    {
      "geometry": {
        "type": "Point",
        "coordinates": [
          -90.0333,
          46.2
        ]
      },
      "type": "Feature",
      "properties": {
        "hierarchy": [
          "tgn:2563804",
          "tgn:1000001",
          "tgn:7012149",
          "tgn:2002327",
          "tgn:7007922",
          "tgn:7029392"
        ],
        "placetype": [
          "aat:300008680"
        ],
        "id": 2563804,
        "name:xx": "Oxbow Lake"
      }
    },
    {
      "geometry": {
        "type": "Point",
        "coordinates": [
          -89.6833,
          46.2333
        ]
      },
      "type": "Feature",
      "properties": {
        "hierarchy": [
          "tgn:2563805",
          "tgn:1000001",
          "tgn:7012149",
          "tgn:2002359",
          "tgn:7007922",
          "tgn:7029392"
        ],
        "placetype": [
          "aat:300008680"
        ],
        "id": 2563805,
        "name:xx": "Oxbow Lake"
      }
    },
    {
      "geometry": {
        "type": "Point",
        "coordinates": [
          -86.3,
          43.8167
        ]
      },
      "type": "Feature",
      "properties": {
        "hierarchy": [
          "tgn:2563806",
          "tgn:1000001",
          "tgn:7012149",
          "tgn:2000976",
          "tgn:7007520",
          "tgn:7029392"
        ],
        "placetype": [
          "aat:300006075"
        ],
        "id": 2563806,
        "name:xx": "Oxbow Lake Drain"
      }
    },
    {
      "geometry": {
        "type": "Point",
        "coordinates": [
          -111.35,
          34.1667
        ]
      },
      "type": "Feature",
      "properties": {
        "hierarchy": [
          "tgn:2563807",
          "tgn:1000001",
          "tgn:7006451",
          "tgn:2000093",
          "tgn:7012149",
          "tgn:7029392"
        ],
        "placetype": [
          "aat:300000390"
        ],
        "id": 2563807,
        "name:xx": "Oxbow Mine"
      }
    },
    {
      "geometry": {
        "type": "Point",
        "coordinates": [
          -110.9833,
          34.2167
        ]
      },
      "type": "Feature",
      "properties": {
        "hierarchy": [
          "tgn:2563808",
          "tgn:1000001",
          "tgn:7006451",
          "tgn:2000093",
          "tgn:7012149",
          "tgn:7029392"
        ],
        "placetype": [
          "aat:300008798"
        ],
        "id": 2563808,
        "name:xx": "Oxbow Mountain"
      }
    },
    {
      "geometry": {
        "type": "Point",
        "coordinates": [
          -93.6667,
          34.7333
        ]
      },
      "type": "Feature",
      "properties": {
        "hierarchy": [
          "tgn:2563809",
          "tgn:1000001",
          "tgn:7016172",
          "tgn:7012149",
          "tgn:7029392"
        ],
        "placetype": [
          "aat:300266640"
        ],
        "id": 2563809,
        "name:xx": "Oxbow Mountain"
      }
    }
  ]
}
