{
  "geometry": {
    "type": "Point",
    "coordinates": [
      -79.4833,
      34.3167
    ]
  },
  "type": "Feature",
  "properties": {
    "hierarchy": [
      "tgn:2164613",
      "tgn:1000001",
      "tgn:2001741",
      "tgn:7012149",
      "tgn:7007712",
      "tgn:7029392"
    ],
    "placetype": [
      "aat:300008347"
    ],
    "id": 2164613,
    "name:xx": "Berrys Crossroads"
  }
}
