{
  "geometry": {
    "type": "Point",
    "coordinates": [
      -96.5833,
      37.2333
    ]
  },
  "type": "Feature",
  "properties": {
    "hierarchy": [
      "tgn:2421981",
      "tgn:1000001",
      "tgn:2000677",
      "tgn:7012149",
      "tgn:7007254",
      "tgn:7029392"
    ],
    "placetype": [
      "aat:300008706"
    ],
    "id": 2421981,
    "name:xx": "Jim Creek"
  }
}
