{
  "geometry": {
    "type": "Point",
    "coordinates": [
      121.62041,
      24.10531
    ]
  },
  "type": "Feature",
  "properties": {
    "hierarchy": [
      "tgn:7491753",
      "tgn:7001010",
      "tgn:1000004",
      "tgn:1000141",
      "tgn:7029392"
    ],
    "placetype": [
      "aat:300008347"
    ],
    "id": 7491753,
    "name:xx": "Beisanzhan"
  }
}
