{
  "geometry": {
    "type": "Point",
    "coordinates": [
      -79.0667,
      40.4833
    ]
  },
  "type": "Feature",
  "properties": {
    "hierarchy": [
      "tgn:2240603",
      "tgn:1000001",
      "tgn:7012149",
      "tgn:1002501",
      "tgn:7007710",
      "tgn:7029392"
    ],
    "placetype": [
      "aat:300008347"
    ],
    "id": 2240603,
    "name:xx": "Claghorn"
  }
}
