{
  "geometry": {
    "type": "Point",
    "coordinates": [
      -89.3333,
      35.1167
    ]
  },
  "type": "Feature",
  "properties": {
    "hierarchy": [
      "tgn:2396299",
      "tgn:1000001",
      "tgn:7012149",
      "tgn:2001860",
      "tgn:7007825",
      "tgn:7029392"
    ],
    "placetype": [
      "aat:300008706"
    ],
    "id": 2396299,
    "name:xx": "Holmes Creek"
  }
}
