{
  "type": "FeatureCollection",
  "features": [
    {
      "geometry": {
        "type": "Point",
        "coordinates": [
          -101.716667,
          21.45
        ]
      },
      "type": "Feature",
      "properties": {
        "hierarchy": [
          "tgn:7397530",
          "tgn:7005586",
          "tgn:1000001",
          "tgn:7005560",
          "tgn:7029392"
        ],
        "placetype": [
          "aat:300008347"
        ],
        "id": 7397530,
        "name:xx": "San Nicolás"
      }
    },
    {
      "geometry": {
        "type": "Point",
        "coordinates": [
          -97.4,
          21.4
        ]
      },
      "type": "Feature",
      "properties": {
        "hierarchy": [
          "tgn:7397531",
          "tgn:1000001",
          "tgn:7005599",
          "tgn:7005560",
          "tgn:7029392"
        ],
        "placetype": [
          "aat:300008347"
        ],
        "id": 7397531,
        "name:xx": "San Nicolás"
      }
    },
    {
      "geometry": {
        "type": "Point",
        "coordinates": [
          -88.8,
          21.333333
        ]
      },
      "type": "Feature",
      "properties": {
        "hierarchy": [
          "tgn:7397532",
          "tgn:1000001",
          "tgn:7005600",
          "tgn:7005560",
          "tgn:7029392"
        ],
        "placetype": [
          "aat:300008347"
        ],
        "id": 7397532,
        "name:xx": "San Nicolás"
      }
    },
    {
      "geometry": {
        "type": "Point",
        "coordinates": [
          -100.2,
          21.05
        ]
      },
      "type": "Feature",
      "properties": {
        "hierarchy": [
          "tgn:7397533",
          "tgn:7005584",
          "tgn:1000001",
          "tgn:7005560",
          "tgn:7029392"
        ],
        "placetype": [
          "aat:300008347"
        ],
        "id": 7397533,
        "name:xx": "San Nicolás"
      }
    },
    {
      "geometry": {
        "type": "Point",
        "coordinates": [
          -103.25,
          20.95
        ]
      },
      "type": "Feature",
      "properties": {
        "hierarchy": [
          "tgn:7397534",
          "tgn:7005586",
          "tgn:1000001",
          "tgn:7005560",
          "tgn:7029392"
        ],
        "placetype": [
          "aat:300008347"
        ],
        "id": 7397534,
        "name:xx": "San Nicolás"
      }
    },
    {
      "geometry": {
        "type": "Point",
        "coordinates": [
          -99.183333,
          20.966667
        ]
      },
      "type": "Feature",
      "properties": {
        "hierarchy": [
          "tgn:7397535",
          "tgn:7005587",
          "tgn:1000001",
          "tgn:7005560",
          "tgn:7029392"
        ],
        "placetype": [
          "aat:300008347"
        ],
        "id": 7397535,
        "name:xx": "San Nicolás"
      }
    },
    {
      "geometry": {
        "type": "Point",
        "coordinates": [
          -98.85,
          20.883333
        ]
      },
      "type": "Feature",
      "properties": {
        "hierarchy": [
          "tgn:7397536",
          "tgn:7005587",
          "tgn:1000001",
          "tgn:7005560",
          "tgn:7029392"
        ],
        "placetype": [
          "aat:300008347"
        ],
        "id": 7397536,
        "name:xx": "San Nicolás"
      }
    },
    {
      "geometry": {
        "type": "Point",
        "coordinates": [
          -89.016667,
          20.75
        ]
      },
      "type": "Feature",
      "properties": {
        "hierarchy": [
          "tgn:7397537",
          "tgn:1000001",
          "tgn:7005600",
          "tgn:7005560",
          "tgn:7029392"
        ],
        "placetype": [
          "aat:300008347"
        ],
        "id": 7397537,
        "name:xx": "San Nicolás"
      }
    },
    {
      "geometry": {
        "type": "Point",
        "coordinates": [
          -104.1,
          20.55
        ]
      },
      "type": "Feature",
      "properties": {
        "hierarchy": [
          "tgn:7397538",
          "tgn:7005586",
          "tgn:1000001",
          "tgn:7005560",
          "tgn:7029392"
        ],
        "placetype": [
          "aat:300008347"
        ],
        "id": 7397538,
        "name:xx": "San Nicolás"
      }
    },
    {
      "geometry": {
        "type": "Point",
        "coordinates": [
          -103.816667,
          20.5
        ]
      },
      "type": "Feature",
      "properties": {
        "hierarchy": [
          "tgn:7397539",
          "tgn:7005586",
          "tgn:1000001",
          "tgn:7005560",
          "tgn:7029392"
        ],
        "placetype": [
          "aat:300008347"
        ],
        "id": 7397539,
        "name:xx": "San Nicolás"
      }
    }
  ]
}
