{
  "geometry": {
    "type": "Point",
    "coordinates": [
      -88.15,
      42.4833
    ]
  },
  "type": "Feature",
  "properties": {
    "hierarchy": [
      "tgn:2573251",
      "tgn:1000001",
      "tgn:7012149",
      "tgn:1002537",
      "tgn:7007922",
      "tgn:7029392"
    ],
    "placetype": [
      "aat:300008680"
    ],
    "id": 2573251,
    "name:xx": "Peat Lake"
  }
}
