{
  "geometry": {
    "type": "Point",
    "coordinates": [
      -78.6167,
      39.1167
    ]
  },
  "type": "Feature",
  "properties": {
    "hierarchy": [
      "tgn:2645053",
      "tgn:1000001",
      "tgn:7012149",
      "tgn:2002266",
      "tgn:7013961",
      "tgn:7029392"
    ],
    "placetype": [
      "aat:300008699"
    ],
    "id": 2645053,
    "name:xx": "Sauerkraut Run"
  }
}
