{
  "geometry": {
    "type": "Point",
    "coordinates": [
      -91.15,
      30.4667
    ]
  },
  "type": "Feature",
  "properties": {
    "hierarchy": [
      "tgn:2390379",
      "tgn:1000001",
      "tgn:2000870",
      "tgn:7012149",
      "tgn:7007256",
      "tgn:7029392"
    ],
    "placetype": [
      "aat:300008347"
    ],
    "id": 2390379,
    "name:xx": "Highland Gardens"
  }
}
