{
  "geometry": {
    "type": "Point",
    "coordinates": [
      17.983333,
      40.05
    ]
  },
  "type": "Feature",
  "properties": {
    "hierarchy": [
      "tgn:7058579",
      "tgn:1003468",
      "tgn:1000003",
      "tgn:7010380",
      "tgn:1000080",
      "tgn:7029392"
    ],
    "placetype": [
      "aat:300000745"
    ],
    "id": 7058579,
    "name:xx": "Borgo"
  }
}
