{
  "type": "FeatureCollection",
  "features": [
    {
      "geometry": {
        "type": "Point",
        "coordinates": [
          -84.3667,
          40.3833
        ]
      },
      "type": "Feature",
      "properties": {
        "hierarchy": [
          "tgn:2080805",
          "tgn:1002159",
          "tgn:1000001",
          "tgn:7012149",
          "tgn:7007706",
          "tgn:7029392"
        ],
        "placetype": [
          "aat:300008347"
        ],
        "id": 2080805,
        "name:xx": "Minster"
      }
    },
    {
      "geometry": {
        "type": "Point",
        "coordinates": [
          -81.35,
          40.9833
        ]
      },
      "type": "Feature",
      "properties": {
        "hierarchy": [
          "tgn:2080807",
          "tgn:1000001",
          "tgn:7012149",
          "tgn:1002797",
          "tgn:7007706",
          "tgn:7029392"
        ],
        "placetype": [
          "aat:300008347",
          "aat:300387210"
        ],
        "id": 2080807,
        "name:xx": "Mishler"
      }
    },
    {
      "geometry": {
        "type": "Point",
        "coordinates": [
          -82.45,
          41.3833
        ]
      },
      "type": "Feature",
      "properties": {
        "hierarchy": [
          "tgn:2080808",
          "tgn:1000001",
          "tgn:7012149",
          "tgn:1002357",
          "tgn:7007706",
          "tgn:7029392"
        ],
        "placetype": [
          "aat:300008347"
        ],
        "id": 2080808,
        "name:xx": "Mitiwanga"
      }
    },
    {
      "geometry": {
        "type": "Point",
        "coordinates": [
          -81.5667,
          40.2667
        ]
      },
      "type": "Feature",
      "properties": {
        "hierarchy": [
          "tgn:2080809",
          "tgn:1000001",
          "tgn:7012149",
          "tgn:1002958",
          "tgn:7007706",
          "tgn:7029392"
        ],
        "placetype": [
          "aat:300008347"
        ],
        "id": 2080809,
        "name:xx": "Mizers"
      }
    }
  ]
}
