{
  "geometry": {
    "type": "Point",
    "coordinates": [
      82.207687,
      22.7232
    ]
  },
  "type": "Feature",
  "properties": {
    "hierarchy": [
      "tgn:7547427",
      "tgn:1000004",
      "tgn:7031781",
      "tgn:7000198",
      "tgn:7029392"
    ],
    "placetype": [
      "aat:300008347"
    ],
    "name:en": "Ahīrpāra",
    "id": 7547427
  }
}
