{
  "geometry": {
    "type": "Point",
    "coordinates": [
      -110.7833,
      34.0333
    ]
  },
  "type": "Feature",
  "properties": {
    "hierarchy": [
      "tgn:2347205",
      "tgn:1000001",
      "tgn:7006451",
      "tgn:2000093",
      "tgn:7012149",
      "tgn:7029392"
    ],
    "placetype": [
      "aat:300008697"
    ],
    "id": 2347205,
    "name:xx": "Gentry Canyon Spring"
  }
}
