{
  "geometry": {
    "type": "Point",
    "coordinates": [
      -88.35,
      34.9333
    ]
  },
  "type": "Feature",
  "properties": {
    "hierarchy": [
      "tgn:2382175",
      "tgn:1000001",
      "tgn:7012149",
      "tgn:2001156",
      "tgn:7007522",
      "tgn:7029392"
    ],
    "placetype": [
      "aat:300008699"
    ],
    "id": 2382175,
    "name:xx": "Haynes Branch"
  }
}
