{
  "geometry": {
    "type": "Point",
    "coordinates": [
      -110.733,
      28.983
    ]
  },
  "type": "Feature",
  "properties": {
    "hierarchy": [
      "tgn:7033090",
      "tgn:1000001",
      "tgn:1001960",
      "tgn:7005560",
      "tgn:7029392"
    ],
    "placetype": [
      "aat:300016638",
      "aat:300000810",
      "aat:300387006"
    ],
    "id": 7033090,
    "name:xx": "El Bajío"
  }
}
