{
  "type": "FeatureCollection",
  "features": [
    {
      "geometry": {
        "type": "Point",
        "coordinates": [
          -95.1167,
          31.2667
        ]
      },
      "type": "Feature",
      "properties": {
        "hierarchy": [
          "tgn:2137380",
          "tgn:1000001",
          "tgn:7012149",
          "tgn:1002486",
          "tgn:7007826",
          "tgn:7029392"
        ],
        "placetype": [
          "aat:300008706"
        ],
        "id": 2137380,
        "name:xx": "Armstrong Creek"
      }
    },
    {
      "geometry": {
        "type": "Point",
        "coordinates": [
          -94.25,
          33.1833
        ]
      },
      "type": "Feature",
      "properties": {
        "hierarchy": [
          "tgn:2137381",
          "tgn:1000001",
          "tgn:7012149",
          "tgn:1002244",
          "tgn:7007826",
          "tgn:7029392"
        ],
        "placetype": [
          "aat:300008706"
        ],
        "id": 2137381,
        "name:xx": "Armstrong Creek"
      }
    },
    {
      "geometry": {
        "type": "Point",
        "coordinates": [
          -98.4333,
          32.25
        ]
      },
      "type": "Feature",
      "properties": {
        "hierarchy": [
          "tgn:2137382",
          "tgn:1000001",
          "tgn:7012149",
          "tgn:7007826",
          "tgn:7029392"
        ],
        "placetype": [
          "aat:300008706"
        ],
        "id": 2137382,
        "name:xx": "Armstrong Creek"
      }
    },
    {
      "geometry": {
        "type": "Point",
        "coordinates": [
          -122.1333,
          48.2333
        ]
      },
      "type": "Feature",
      "properties": {
        "hierarchy": [
          "tgn:2137383",
          "tgn:1000001",
          "tgn:7012149",
          "tgn:1002899",
          "tgn:7007920",
          "tgn:7029392"
        ],
        "placetype": [
          "aat:300008706"
        ],
        "id": 2137383,
        "name:xx": "Armstrong Creek"
      }
    },
    {
      "geometry": {
        "type": "Point",
        "coordinates": [
          -119.0833,
          48.2333
        ]
      },
      "type": "Feature",
      "properties": {
        "hierarchy": [
          "tgn:2137384",
          "tgn:1000001",
          "tgn:7012149",
          "tgn:1002742",
          "tgn:7007920",
          "tgn:7029392"
        ],
        "placetype": [
          "aat:300008706"
        ],
        "id": 2137384,
        "name:xx": "Armstrong Creek"
      }
    },
    {
      "geometry": {
        "type": "Point",
        "coordinates": [
          -81.3167,
          38.0333
        ]
      },
      "type": "Feature",
      "properties": {
        "hierarchy": [
          "tgn:2137385",
          "tgn:1000001",
          "tgn:2002261",
          "tgn:7012149",
          "tgn:7013961",
          "tgn:7029392"
        ],
        "placetype": [
          "aat:300008706"
        ],
        "id": 2137385,
        "name:xx": "Armstrong Creek"
      }
    },
    {
      "geometry": {
        "type": "Point",
        "coordinates": [
          -89.85,
          45.3833
        ]
      },
      "type": "Feature",
      "properties": {
        "hierarchy": [
          "tgn:2137386",
          "tgn:1000001",
          "tgn:7012149",
          "tgn:2002334",
          "tgn:7007922",
          "tgn:7029392"
        ],
        "placetype": [
          "aat:300008706"
        ],
        "id": 2137386,
        "name:xx": "Armstrong Creek"
      }
    },
    {
      "geometry": {
        "type": "Point",
        "coordinates": [
          -88.45,
          45.7
        ]
      },
      "type": "Feature",
      "properties": {
        "hierarchy": [
          "tgn:2137387",
          "tgn:1000001",
          "tgn:2002323",
          "tgn:7012149",
          "tgn:7007922",
          "tgn:7029392"
        ],
        "placetype": [
          "aat:300008706"
        ],
        "id": 2137387,
        "name:xx": "Armstrong Creek"
      }
    },
    {
      "geometry": {
        "type": "Point",
        "coordinates": [
          -85.8667,
          40.3833
        ]
      },
      "type": "Feature",
      "properties": {
        "hierarchy": [
          "tgn:2137388",
          "tgn:1000001",
          "tgn:7012149",
          "tgn:1002947",
          "tgn:7007252",
          "tgn:7029392"
        ],
        "placetype": [
          "aat:300006075"
        ],
        "id": 2137388,
        "name:xx": "Armstrong Ditch"
      }
    },
    {
      "geometry": {
        "type": "Point",
        "coordinates": [
          -86.95,
          41.1333
        ]
      },
      "type": "Feature",
      "properties": {
        "hierarchy": [
          "tgn:2137389",
          "tgn:1000001",
          "tgn:7012149",
          "tgn:1002512",
          "tgn:7007252",
          "tgn:7029392"
        ],
        "placetype": [
          "aat:300006075"
        ],
        "id": 2137389,
        "name:xx": "Armstrong Ditch"
      }
    }
  ]
}
