{
  "geometry": {
    "type": "Point",
    "coordinates": [
      -83.5167,
      37.9833
    ]
  },
  "type": "Feature",
  "properties": {
    "hierarchy": [
      "tgn:2041223",
      "tgn:1000001",
      "tgn:7012149",
      "tgn:2000826",
      "tgn:7007255",
      "tgn:7029392"
    ],
    "placetype": [
      "aat:300008347"
    ],
    "id": 2041223,
    "name:xx": "Scranton"
  }
}
