{
  "geometry": {
    "type": "Point",
    "coordinates": [
      28.656745,
      30.97021
    ]
  },
  "type": "Feature",
  "properties": {
    "hierarchy": [
      "tgn:7520308",
      "tgn:7001242",
      "tgn:7016833",
      "tgn:1001418",
      "tgn:7029392"
    ],
    "placetype": [
      "aat:300008777"
    ],
    "name:en": "Abū Ţāqah, 'Alam",
    "id": 7520308
  }
}
