{
  "geometry": {
    "type": "Point",
    "coordinates": [
      -109.35,
      35.7833
    ]
  },
  "type": "Feature",
  "properties": {
    "hierarchy": [
      "tgn:2730756",
      "tgn:2000090",
      "tgn:1000001",
      "tgn:7006451",
      "tgn:7012149",
      "tgn:7029392"
    ],
    "placetype": [
      "aat:300008697"
    ],
    "id": 2730756,
    "name:xx": "Tseya-Kinsikadi Spring"
  }
}
