{
  "geometry": {
    "type": "Point",
    "coordinates": [
      -90.0333,
      38.5333
    ]
  },
  "type": "Feature",
  "properties": {
    "hierarchy": [
      "tgn:2345855",
      "tgn:1000001",
      "tgn:7012149",
      "tgn:7016022",
      "tgn:7007251",
      "tgn:7029392"
    ],
    "placetype": [
      "aat:300008347"
    ],
    "id": 2345855,
    "name:xx": "Gartside"
  }
}
