{
  "geometry": {
    "type": "Point",
    "coordinates": [
      -81.2833,
      37.3667
    ]
  },
  "type": "Feature",
  "properties": {
    "hierarchy": [
      "tgn:2473809",
      "tgn:1000001",
      "tgn:7012149",
      "tgn:2002278",
      "tgn:7013961",
      "tgn:7029392"
    ],
    "placetype": [
      "aat:300008699"
    ],
    "id": 2473809,
    "name:xx": "Lower Georges Branch"
  }
}
