{
  "type": "FeatureCollection",
  "features": [
    {
      "geometry": {
        "type": "Point",
        "coordinates": [
          -90.7,
          38.0667
        ]
      },
      "type": "Feature",
      "properties": {
        "hierarchy": [
          "tgn:2144760",
          "tgn:1000001",
          "tgn:7012149",
          "tgn:2001254",
          "tgn:7007523",
          "tgn:7029392"
        ],
        "placetype": [
          "aat:300008798"
        ],
        "id": 2144760,
        "name:xx": "Bald Hill"
      }
    },
    {
      "geometry": {
        "type": "Point",
        "coordinates": [
          -114.9667,
          47.25
        ]
      },
      "type": "Feature",
      "properties": {
        "hierarchy": [
          "tgn:2144761",
          "tgn:1000001",
          "tgn:7012149",
          "tgn:2001290",
          "tgn:7007524",
          "tgn:7029392"
        ],
        "placetype": [
          "aat:300008798"
        ],
        "id": 2144761,
        "name:xx": "Bald Hill"
      }
    },
    {
      "geometry": {
        "type": "Point",
        "coordinates": [
          -113.2667,
          48.45
        ]
      },
      "type": "Feature",
      "properties": {
        "hierarchy": [
          "tgn:2144762",
          "tgn:1000001",
          "tgn:7012149",
          "tgn:2001277",
          "tgn:7007524",
          "tgn:7029392"
        ],
        "placetype": [
          "aat:300008798"
        ],
        "id": 2144762,
        "name:xx": "Bald Hill"
      }
    },
    {
      "geometry": {
        "type": "Point",
        "coordinates": [
          -72.3833,
          42.9167
        ]
      },
      "type": "Feature",
      "properties": {
        "hierarchy": [
          "tgn:2144763",
          "tgn:7019618",
          "tgn:1000001",
          "tgn:7012149",
          "tgn:7007564",
          "tgn:7029392"
        ],
        "placetype": [
          "aat:300008798"
        ],
        "id": 2144763,
        "name:xx": "Bald Hill"
      }
    },
    {
      "geometry": {
        "type": "Point",
        "coordinates": [
          -71.4,
          43
        ]
      },
      "type": "Feature",
      "properties": {
        "hierarchy": [
          "tgn:2144764",
          "tgn:1000001",
          "tgn:1002480",
          "tgn:7012149",
          "tgn:7007564",
          "tgn:7029392"
        ],
        "placetype": [
          "aat:300008798"
        ],
        "id": 2144764,
        "name:xx": "Bald Hill"
      }
    },
    {
      "geometry": {
        "type": "Point",
        "coordinates": [
          -71,
          43.05
        ]
      },
      "type": "Feature",
      "properties": {
        "hierarchy": [
          "tgn:2144765",
          "tgn:1000001",
          "tgn:7014352",
          "tgn:7012149",
          "tgn:7007564",
          "tgn:7029392"
        ],
        "placetype": [
          "aat:300008798"
        ],
        "id": 2144765,
        "name:xx": "Bald Hill"
      }
    },
    {
      "geometry": {
        "type": "Point",
        "coordinates": [
          -71.7167,
          43.4833
        ]
      },
      "type": "Feature",
      "properties": {
        "hierarchy": [
          "tgn:2144766",
          "tgn:1000001",
          "tgn:2001425",
          "tgn:7012149",
          "tgn:7007564",
          "tgn:7029392"
        ],
        "placetype": [
          "aat:300008798"
        ],
        "id": 2144766,
        "name:xx": "Bald Hill"
      }
    },
    {
      "geometry": {
        "type": "Point",
        "coordinates": [
          -72.2833,
          43.65
        ]
      },
      "type": "Feature",
      "properties": {
        "hierarchy": [
          "tgn:2144767",
          "tgn:1000001",
          "tgn:2001424",
          "tgn:7012149",
          "tgn:7007564",
          "tgn:7029392"
        ],
        "placetype": [
          "aat:300008798"
        ],
        "id": 2144767,
        "name:xx": "Bald Hill"
      }
    },
    {
      "geometry": {
        "type": "Point",
        "coordinates": [
          -71.1667,
          43.9667
        ]
      },
      "type": "Feature",
      "properties": {
        "hierarchy": [
          "tgn:2144768",
          "tgn:2001423",
          "tgn:1000001",
          "tgn:7012149",
          "tgn:7007564",
          "tgn:7029392"
        ],
        "placetype": [
          "aat:300008798"
        ],
        "id": 2144768,
        "name:xx": "Bald Hill"
      }
    },
    {
      "geometry": {
        "type": "Point",
        "coordinates": [
          -74.4667,
          40.9167
        ]
      },
      "type": "Feature",
      "properties": {
        "hierarchy": [
          "tgn:2144769",
          "tgn:1000001",
          "tgn:1002695",
          "tgn:7012149",
          "tgn:7007565",
          "tgn:7029392"
        ],
        "placetype": [
          "aat:300008798"
        ],
        "id": 2144769,
        "name:xx": "Bald Hill"
      }
    }
  ]
}
