{
  "geometry": {
    "type": "Point",
    "coordinates": [
      -76.4167,
      40.2833
    ]
  },
  "type": "Feature",
  "properties": {
    "hierarchy": [
      "tgn:2787076",
      "tgn:1000001",
      "tgn:7012149",
      "tgn:1002581",
      "tgn:7007710",
      "tgn:7029392"
    ],
    "placetype": [
      "aat:300008347"
    ],
    "id": 2787076,
    "name:xx": "Zinns Mill"
  }
}
