{
  "geometry": {
    "type": "Point",
    "coordinates": [
      -162.0667,
      65.7333
    ]
  },
  "type": "Feature",
  "properties": {
    "hierarchy": [
      "tgn:2732051",
      "tgn:7006450",
      "tgn:1000001",
      "tgn:7012149",
      "tgn:2124014",
      "tgn:7029392"
    ],
    "placetype": [
      "aat:300008706"
    ],
    "id": 2732051,
    "name:xx": "Tunnel Creek"
  }
}
