{
  "geometry": {
    "type": "Point",
    "coordinates": [
      -71.5333,
      41.15
    ]
  },
  "type": "Feature",
  "properties": {
    "hierarchy": [
      "tgn:2682504",
      "tgn:1002996",
      "tgn:1000001",
      "tgn:7012149",
      "tgn:7007711",
      "tgn:7029392"
    ],
    "placetype": [
      "aat:300008850"
    ],
    "id": 2682504,
    "name:xx": "Southeast Point"
  }
}
