{
  "geometry": {
    "type": "Point",
    "coordinates": [
      32.57163,
      25.331607
    ]
  },
  "type": "Feature",
  "properties": {
    "hierarchy": [
      "tgn:7543432",
      "tgn:7001242",
      "tgn:7016833",
      "tgn:7000123",
      "tgn:7029392"
    ],
    "placetype": [
      "aat:300008347"
    ],
    "name:en": "Naj' ad Dayr al Qadīm",
    "id": 7543432
  }
}
