{
  "geometry": {
    "type": "Point",
    "coordinates": [
      -111.7333,
      34.25
    ]
  },
  "type": "Feature",
  "properties": {
    "hierarchy": [
      "tgn:2468251",
      "tgn:1000001",
      "tgn:7006451",
      "tgn:7012149",
      "tgn:2000103",
      "tgn:7029392"
    ],
    "placetype": [
      "aat:300006191"
    ],
    "id": 2468251,
    "name:xx": "Long Mesa Tank"
  }
}
