{
  "type": "FeatureCollection",
  "features": [
    {
      "geometry": {
        "type": "Point",
        "coordinates": [
          76.7333,
          34.9333
        ]
      },
      "type": "Feature",
      "properties": {
        "hierarchy": [
          "tgn:1083800",
          "tgn:7000367",
          "tgn:1000004",
          "tgn:1000133",
          "tgn:7029392"
        ],
        "placetype": [
          "aat:300008347"
        ],
        "id": 1083800,
        "name:xx": "Siari"
      }
    },
    {
      "geometry": {
        "type": "Point",
        "coordinates": [
          67.9,
          29.5167
        ]
      },
      "type": "Feature",
      "properties": {
        "hierarchy": [
          "tgn:1083801",
          "tgn:7000360",
          "tgn:1000004",
          "tgn:1000133",
          "tgn:7029392"
        ],
        "placetype": [
          "aat:300008347"
        ],
        "id": 1083801,
        "name:xx": "Sibi"
      }
    },
    {
      "geometry": {
        "type": "Point",
        "coordinates": [
          72.55,
          31.8333
        ]
      },
      "type": "Feature",
      "properties": {
        "hierarchy": [
          "tgn:1083802",
          "tgn:1000004",
          "tgn:1001490",
          "tgn:1000133",
          "tgn:7029392"
        ],
        "placetype": [
          "aat:300008347"
        ],
        "id": 1083802,
        "name:xx": "Sill훮nw훮li"
      }
    },
    {
      "geometry": {
        "type": "Point",
        "coordinates": [
          73.8833,
          36.1
        ]
      },
      "type": "Feature",
      "properties": {
        "hierarchy": [
          "tgn:1083803",
          "tgn:7000367",
          "tgn:1000004",
          "tgn:1000133",
          "tgn:7029392"
        ],
        "placetype": [
          "aat:300008347"
        ],
        "id": 1083803,
        "name:xx": "Singal"
      }
    },
    {
      "geometry": {
        "type": "Point",
        "coordinates": [
          75.6167,
          35.3
        ]
      },
      "type": "Feature",
      "properties": {
        "hierarchy": [
          "tgn:1083804",
          "tgn:7000367",
          "tgn:1000004",
          "tgn:1000133",
          "tgn:7029392"
        ],
        "placetype": [
          "aat:300008347"
        ],
        "id": 1083804,
        "name:xx": "Sk훮rdu"
      }
    },
    {
      "geometry": {
        "type": "Point",
        "coordinates": [
          74.2,
          32.4333
        ]
      },
      "type": "Feature",
      "properties": {
        "hierarchy": [
          "tgn:1083805",
          "tgn:1000004",
          "tgn:1001490",
          "tgn:1000133",
          "tgn:7029392"
        ],
        "placetype": [
          "aat:300008347"
        ],
        "id": 1083805,
        "name:xx": "Sodhra"
      }
    },
    {
      "geometry": {
        "type": "Point",
        "coordinates": [
          66.6667,
          25.4167
        ]
      },
      "type": "Feature",
      "properties": {
        "hierarchy": [
          "tgn:1083806",
          "tgn:7000360",
          "tgn:1000004",
          "tgn:1000133",
          "tgn:7029392"
        ],
        "placetype": [
          "aat:300008347"
        ],
        "id": 1083806,
        "name:xx": "Sonmiani"
      }
    },
    {
      "geometry": {
        "type": "Point",
        "coordinates": [
          68.1,
          24.6
        ]
      },
      "type": "Feature",
      "properties": {
        "hierarchy": [
          "tgn:1083807",
          "tgn:1000004",
          "tgn:7002462",
          "tgn:1000133",
          "tgn:7029392"
        ],
        "placetype": [
          "aat:300008347"
        ],
        "id": 1083807,
        "name:xx": "Sujawal"
      }
    },
    {
      "geometry": {
        "type": "Point",
        "coordinates": [
          68.9,
          27.7
        ]
      },
      "type": "Feature",
      "properties": {
        "hierarchy": [
          "tgn:1083808",
          "tgn:1000004",
          "tgn:7002462",
          "tgn:1000133",
          "tgn:7029392"
        ],
        "placetype": [
          "aat:300008347",
          "aat:300008375"
        ],
        "id": 1083808,
        "name:xx": "Sukkur"
      }
    },
    {
      "geometry": {
        "type": "Point",
        "coordinates": [
          71.0167,
          33.6833
        ]
      },
      "type": "Feature",
      "properties": {
        "hierarchy": [
          "tgn:1083809",
          "tgn:7002460",
          "tgn:1000004",
          "tgn:1000133",
          "tgn:7029392"
        ],
        "placetype": [
          "aat:300008347"
        ],
        "id": 1083809,
        "name:xx": "Sulaim훮n Khel"
      }
    }
  ]
}
