{
  "geometry": {
    "type": "Point",
    "coordinates": [
      -71.8333,
      41.6167
    ]
  },
  "type": "Feature",
  "properties": {
    "hierarchy": [
      "tgn:2293997",
      "tgn:1000001",
      "tgn:1002714",
      "tgn:7012149",
      "tgn:7007159",
      "tgn:7029392"
    ],
    "placetype": [
      "aat:300008905"
    ],
    "id": 2293997,
    "name:xx": "Douglas Swamp"
  }
}
