{
  "geometry": {
    "type": "Point",
    "coordinates": [
      16.8333,
      44.9667
    ]
  },
  "type": "Feature",
  "properties": {
    "hierarchy": [
      "tgn:1065073",
      "tgn:7018870",
      "tgn:1000003",
      "tgn:7006664",
      "tgn:7029392"
    ],
    "placetype": [
      "aat:300008347"
    ],
    "id": 1065073,
    "name:xx": "Kozarac"
  }
}
