{
  "geometry": {
    "type": "Point",
    "coordinates": [
      -83.655,
      12.792
    ]
  },
  "type": "Feature",
  "properties": {
    "hierarchy": [
      "tgn:1125812",
      "tgn:7593359",
      "tgn:1000001",
      "tgn:7005562",
      "tgn:7029392"
    ],
    "placetype": [
      "aat:300008707"
    ],
    "id": 1125812,
    "name:xx": "Kurinwás, Río"
  }
}
