{
  "geometry": {
    "type": "Point",
    "coordinates": [
      -9.34,
      38.811
    ]
  },
  "type": "Feature",
  "properties": {
    "hierarchy": [
      "tgn:1049916",
      "tgn:1000882",
      "tgn:1000003",
      "tgn:1000090",
      "tgn:7029392"
    ],
    "placetype": [
      "aat:300008347"
    ],
    "id": 1049916,
    "name:xx": "Sacotes"
  }
}
