{
  "geometry": {
    "type": "Point",
    "coordinates": [
      -82.5167,
      40.0667
    ]
  },
  "type": "Feature",
  "properties": {
    "hierarchy": [
      "tgn:2701814",
      "tgn:1000001",
      "tgn:7012149",
      "tgn:1002596",
      "tgn:7007706",
      "tgn:7029392"
    ],
    "placetype": [
      "aat:300008798"
    ],
    "id": 2701814,
    "name:xx": "Sugarloaf Hill"
  }
}
