{
  "geometry": {
    "type": "Point",
    "coordinates": [
      80.663491,
      26.12148
    ]
  },
  "type": "Feature",
  "properties": {
    "hierarchy": [
      "tgn:7553319",
      "tgn:1000004",
      "tgn:7000198",
      "tgn:7016722",
      "tgn:7029392"
    ],
    "placetype": [
      "aat:300008699"
    ],
    "name:en": "Pāndū Nadī",
    "id": 7553319
  }
}
