{
  "geometry": {
    "type": "Point",
    "coordinates": [
      32.598809,
      25.649133
    ]
  },
  "type": "Feature",
  "properties": {
    "hierarchy": [
      "tgn:7520837",
      "tgn:7001242",
      "tgn:7016833",
      "tgn:7528226",
      "tgn:7029392"
    ],
    "placetype": [
      "aat:300008347"
    ],
    "name:en": "Aḑ Ḑab'īyah",
    "id": 7520837
  }
}
