{
  "geometry": {
    "type": "Point",
    "coordinates": [
      -96.3833,
      34.8667
    ]
  },
  "type": "Feature",
  "properties": {
    "hierarchy": [
      "tgn:2136275",
      "tgn:1000001",
      "tgn:7012149",
      "tgn:2001654",
      "tgn:7007707",
      "tgn:7029392"
    ],
    "placetype": [
      "aat:300008706"
    ],
    "id": 2136275,
    "name:xx": "Arbeca Creek"
  }
}
