{
  "geometry": {
    "type": "Point",
    "coordinates": [
      -100.0667,
      44.9167
    ]
  },
  "type": "Feature",
  "properties": {
    "hierarchy": [
      "tgn:2356744",
      "tgn:1000001",
      "tgn:7012149",
      "tgn:2001823",
      "tgn:7007713",
      "tgn:7029392"
    ],
    "placetype": [
      "aat:300008347"
    ],
    "id": 2356744,
    "name:xx": "Gorman"
  }
}
