{
  "geometry": {
    "type": "Point",
    "coordinates": [
      -85.0667,
      36.2833
    ]
  },
  "type": "Feature",
  "properties": {
    "hierarchy": [
      "tgn:2101398",
      "tgn:1000001",
      "tgn:7012149",
      "tgn:2001861",
      "tgn:7007825",
      "tgn:7029392"
    ],
    "placetype": [
      "aat:300008347",
      "aat:300387210"
    ],
    "id": 2101398,
    "name:xx": "Sandy"
  }
}
