{
  "geometry": {
    "type": "Point",
    "coordinates": [
      -93.2833,
      40.8167
    ]
  },
  "type": "Feature",
  "properties": {
    "hierarchy": [
      "tgn:2427268",
      "tgn:1000001",
      "tgn:7012149",
      "tgn:2000653",
      "tgn:7007253",
      "tgn:7029392"
    ],
    "placetype": [
      "aat:300008706"
    ],
    "id": 2427268,
    "name:xx": "Jordan Creek"
  }
}
