{
  "geometry": {
    "type": "Point",
    "coordinates": [
      -75.8667,
      38.1833
    ]
  },
  "type": "Feature",
  "properties": {
    "hierarchy": [
      "tgn:2274776",
      "tgn:1000001",
      "tgn:1002902",
      "tgn:7012149",
      "tgn:7007516",
      "tgn:7029392"
    ],
    "placetype": [
      "aat:300132316"
    ],
    "id": 2274776,
    "name:xx": "Dames Quarter Creek"
  }
}
