{
  "geometry": {
    "type": "Point",
    "coordinates": [
      31.15,
      29.183333
    ]
  },
  "type": "Feature",
  "properties": {
    "hierarchy": [
      "tgn:7529567",
      "tgn:7001242",
      "tgn:7001105",
      "tgn:7016833",
      "tgn:7029392"
    ],
    "placetype": [
      "aat:300379998"
    ],
    "name:en": "Umm Usnara, Wâdî",
    "id": 7529567
  }
}
