{
  "type": "FeatureCollection",
  "features": [
    {
      "geometry": {
        "type": "Point",
        "coordinates": [
          -82.8833,
          29.8167
        ]
      },
      "type": "Feature",
      "properties": {
        "hierarchy": [
          "tgn:2020192",
          "tgn:1000001",
          "tgn:2000269",
          "tgn:7012149",
          "tgn:7007240",
          "tgn:7029392"
        ],
        "placetype": [
          "aat:300008347",
          "aat:300387210"
        ],
        "id": 2020192,
        "name:xx": "Little Lake City"
      }
    },
    {
      "geometry": {
        "type": "Point",
        "coordinates": [
          -85.85,
          30.5667
        ]
      },
      "type": "Feature",
      "properties": {
        "hierarchy": [
          "tgn:2020197",
          "tgn:1000001",
          "tgn:7012149",
          "tgn:2000291",
          "tgn:7007240",
          "tgn:7029392"
        ],
        "placetype": [
          "aat:300008347",
          "aat:300387210"
        ],
        "id": 2020197,
        "name:xx": "Live Oak"
      }
    },
    {
      "geometry": {
        "type": "Point",
        "coordinates": [
          -82.9833,
          30.2833
        ]
      },
      "type": "Feature",
      "properties": {
        "hierarchy": [
          "tgn:2020198",
          "tgn:1000001",
          "tgn:7012149",
          "tgn:2000286",
          "tgn:7007240",
          "tgn:7029392"
        ],
        "placetype": [
          "aat:300008347"
        ],
        "id": 2020198,
        "name:xx": "Live Oak"
      }
    },
    {
      "geometry": {
        "type": "Point",
        "coordinates": [
          -84.2667,
          30.05
        ]
      },
      "type": "Feature",
      "properties": {
        "hierarchy": [
          "tgn:2020199",
          "tgn:1000001",
          "tgn:7012149",
          "tgn:2000289",
          "tgn:7007240",
          "tgn:7029392"
        ],
        "placetype": [
          "aat:300008347"
        ],
        "id": 2020199,
        "name:xx": "Live Oak Island"
      }
    }
  ]
}
