{
  "geometry": {
    "type": "Point",
    "coordinates": [
      -123.4333,
      42.1833
    ]
  },
  "type": "Feature",
  "properties": {
    "hierarchy": [
      "tgn:2455776",
      "tgn:1000001",
      "tgn:7012149",
      "tgn:2001713",
      "tgn:7007708",
      "tgn:7029392"
    ],
    "placetype": [
      "aat:300008706"
    ],
    "id": 2455776,
    "name:xx": "Little Grayback Creek"
  }
}
