{
  "geometry": {
    "type": "Point",
    "coordinates": [
      -101.4167,
      48.2667
    ]
  },
  "type": "Feature",
  "properties": {
    "hierarchy": [
      "tgn:2077465",
      "tgn:1000001",
      "tgn:7012149",
      "tgn:2001607",
      "tgn:7007705",
      "tgn:7029392"
    ],
    "placetype": [
      "aat:300008347"
    ],
    "id": 2077465,
    "name:xx": "Burlington"
  }
}
