{
  "geometry": {
    "type": "Point",
    "coordinates": [
      -91.3833,
      37.9833
    ]
  },
  "type": "Feature",
  "properties": {
    "hierarchy": [
      "tgn:2328889",
      "tgn:1000001",
      "tgn:7012149",
      "tgn:2001190",
      "tgn:7007523",
      "tgn:7029392"
    ],
    "placetype": [
      "aat:300008697"
    ],
    "id": 2328889,
    "name:xx": "Fishing Spring"
  }
}
