{
  "geometry": {
    "type": "Point",
    "coordinates": [
      -112.05,
      39.9667
    ]
  },
  "type": "Feature",
  "properties": {
    "hierarchy": [
      "tgn:2256037",
      "tgn:1000001",
      "tgn:7012149",
      "tgn:2002125",
      "tgn:7007827",
      "tgn:7029392"
    ],
    "placetype": [
      "aat:300000390"
    ],
    "id": 2256037,
    "name:xx": "Copper Leaf"
  }
}
