{
  "geometry": {
    "type": "Point",
    "coordinates": [
      -90.6333,
      44.55
    ]
  },
  "type": "Feature",
  "properties": {
    "hierarchy": [
      "tgn:2122392",
      "tgn:1000001",
      "tgn:2002314",
      "tgn:7012149",
      "tgn:7007922",
      "tgn:7029392"
    ],
    "placetype": [
      "aat:300008347",
      "aat:300387210"
    ],
    "id": 2122392,
    "name:xx": "Sidney"
  }
}
