{
  "geometry": {
    "type": "Point",
    "coordinates": [
      -105.0667,
      39.15
    ]
  },
  "type": "Feature",
  "properties": {
    "hierarchy": [
      "tgn:2409826",
      "tgn:1000001",
      "tgn:7012149",
      "tgn:2000209",
      "tgn:7007158",
      "tgn:7029392"
    ],
    "placetype": [
      "aat:300008761"
    ],
    "id": 2409826,
    "name:xx": "Illinois Gulch"
  }
}
