{
  "geometry": {
    "type": "Point",
    "coordinates": [
      -78.3333,
      35.7833
    ]
  },
  "type": "Feature",
  "properties": {
    "hierarchy": [
      "tgn:7020510",
      "tgn:1000001",
      "tgn:7012149",
      "tgn:2001548",
      "tgn:7007709",
      "tgn:7029392"
    ],
    "placetype": [
      "aat:300006191"
    ],
    "id": 7020510,
    "name:xx": "Johnson, Lake"
  }
}
