{
  "geometry": {
    "type": "Point",
    "coordinates": [
      21.95,
      0.3167
    ]
  },
  "type": "Feature",
  "properties": {
    "hierarchy": [
      "tgn:1089199",
      "tgn:7001242",
      "tgn:7016654",
      "tgn:1000159",
      "tgn:7029392"
    ],
    "placetype": [
      "aat:300008347"
    ],
    "id": 1089199,
    "name:xx": "Lifanga"
  }
}
