{
  "geometry": {
    "type": "Point",
    "coordinates": [
      -116.8333,
      46.0167
    ]
  },
  "type": "Feature",
  "properties": {
    "hierarchy": [
      "tgn:2227152",
      "tgn:1000001",
      "tgn:7012149",
      "tgn:2000486",
      "tgn:7007250",
      "tgn:7029392"
    ],
    "placetype": [
      "aat:300008761"
    ],
    "id": 2227152,
    "name:xx": "Cave Gulch"
  }
}
