{
  "geometry": {
    "type": "Point",
    "coordinates": [
      78.453886,
      24.108487
    ]
  },
  "type": "Feature",
  "properties": {
    "hierarchy": [
      "tgn:7582946",
      "tgn:1000004",
      "tgn:7000198",
      "tgn:1001894",
      "tgn:7029392"
    ],
    "placetype": [
      "aat:300008347"
    ],
    "name:en": "Garhaulīdhīraj Khurd",
    "id": 7582946
  }
}
