{
  "type": "FeatureCollection",
  "features": [
    {
      "geometry": {
        "type": "Point",
        "coordinates": [
          6.9167,
          48.7
        ]
      },
      "type": "Feature",
      "properties": {
        "hierarchy": [
          "tgn:1135940",
          "tgn:1000003",
          "tgn:1000070",
          "tgn:7029392"
        ],
        "placetype": [
          "aat:300006075"
        ],
        "id": 1135940,
        "name:xx": "Houillères de la Sarre, Canal des"
      }
    },
    {
      "geometry": {
        "type": "Point",
        "coordinates": [
          -2.1,
          53.4833
        ]
      },
      "type": "Feature",
      "properties": {
        "hierarchy": [
          "tgn:1135941",
          "tgn:1003611",
          "tgn:7002445",
          "tgn:1000003",
          "tgn:7029507",
          "tgn:7008591",
          "tgn:7029392"
        ],
        "placetype": [
          "aat:300006075"
        ],
        "id": 1135941,
        "name:xx": "Hudderfield Narrow Canal"
      }
    },
    {
      "geometry": {
        "type": "Point",
        "coordinates": [
          2.8833,
          50.85
        ]
      },
      "type": "Feature",
      "properties": {
        "hierarchy": [
          "tgn:1135942",
          "tgn:1000003",
          "tgn:1000063",
          "tgn:7029392"
        ],
        "placetype": [
          "aat:300006075"
        ],
        "id": 1135942,
        "name:xx": "IJzerkanaal"
      }
    },
    {
      "geometry": {
        "type": "Point",
        "coordinates": [
          31.187,
          27.196
        ]
      },
      "type": "Feature",
      "properties": {
        "hierarchy": [
          "tgn:1135943",
          "tgn:7001242",
          "tgn:7016833",
          "tgn:1001114",
          "tgn:7029392"
        ],
        "placetype": [
          "aat:300006075"
        ],
        "name:en": "Tur'at al Ibrāhīmīyah",
        "id": 1135943
      }
    },
    {
      "geometry": {
        "type": "Point",
        "coordinates": [
          -87.9833,
          41.6667
        ]
      },
      "type": "Feature",
      "properties": {
        "hierarchy": [
          "tgn:1135944",
          "tgn:1000001",
          "tgn:7012149",
          "tgn:7007251",
          "tgn:7029392"
        ],
        "placetype": [
          "aat:300006075"
        ],
        "id": 1135944,
        "name:xx": "Illinois and Michigan Canal"
      }
    },
    {
      "geometry": {
        "type": "Point",
        "coordinates": [
          -43.0667,
          -22.8
        ]
      },
      "type": "Feature",
      "properties": {
        "hierarchy": [
          "tgn:1135945",
          "tgn:1001942",
          "tgn:1000047",
          "tgn:7002457",
          "tgn:1000002",
          "tgn:7029392"
        ],
        "placetype": [
          "aat:300006075"
        ],
        "id": 1135945,
        "name:xx": "Imboaçu, Canal"
      }
    },
    {
      "geometry": {
        "type": "Point",
        "coordinates": [
          -81.1,
          27.1667
        ]
      },
      "type": "Feature",
      "properties": {
        "hierarchy": [
          "tgn:1135947",
          "tgn:1000001",
          "tgn:7012149",
          "tgn:7007240",
          "tgn:7029392"
        ],
        "placetype": [
          "aat:300006075"
        ],
        "id": 1135947,
        "name:xx": "Indian Prairie Canal"
      }
    },
    {
      "geometry": {
        "type": "Point",
        "coordinates": [
          -43.6167,
          -22.7667
        ]
      },
      "type": "Feature",
      "properties": {
        "hierarchy": [
          "tgn:1135949",
          "tgn:1001942",
          "tgn:1000047",
          "tgn:7002457",
          "tgn:1000002",
          "tgn:7029392"
        ],
        "placetype": [
          "aat:300006075"
        ],
        "id": 1135949,
        "name:xx": "Ipiranga, Canal"
      }
    }
  ]
}
