{
  "type": "FeatureCollection",
  "features": [
    {
      "geometry": {
        "type": "Point",
        "coordinates": [
          -4.266667,
          51.715
        ]
      },
      "type": "Feature",
      "properties": {
        "hierarchy": [
          "tgn:7458001",
          "tgn:7002443",
          "tgn:5000552",
          "tgn:1000003",
          "tgn:7008591",
          "tgn:7029392"
        ],
        "placetype": [
          "aat:300008777"
        ],
        "name:en": "Pen-bre, Mynydd",
        "id": 7458001
      }
    },
    {
      "geometry": {
        "type": "Point",
        "coordinates": [
          -1.6,
          54.866667
        ]
      },
      "type": "Feature",
      "properties": {
        "hierarchy": [
          "tgn:7458005",
          "tgn:7002445",
          "tgn:1000003",
          "tgn:7008127",
          "tgn:7008591",
          "tgn:7029392"
        ],
        "placetype": [
          "aat:300007783"
        ],
        "name:en": "Pelton Station",
        "id": 7458005
      }
    },
    {
      "geometry": {
        "type": "Point",
        "coordinates": [
          -1.6,
          54.866667
        ]
      },
      "type": "Feature",
      "properties": {
        "hierarchy": [
          "tgn:7458006",
          "tgn:7002445",
          "tgn:1000003",
          "tgn:7008127",
          "tgn:7008591",
          "tgn:7029392"
        ],
        "placetype": [
          "aat:300008347"
        ],
        "name:en": "Pelton Fell",
        "id": 7458006
      }
    },
    {
      "geometry": {
        "type": "Point",
        "coordinates": [
          -1.6,
          54.866667
        ]
      },
      "type": "Feature",
      "properties": {
        "hierarchy": [
          "tgn:7458007",
          "tgn:7002445",
          "tgn:1000003",
          "tgn:7008127",
          "tgn:7008591",
          "tgn:7029392"
        ],
        "placetype": [
          "aat:300008347"
        ],
        "name:en": "Pelton",
        "id": 7458007
      }
    }
  ]
}
