{
  "geometry": {
    "type": "Point",
    "coordinates": [
      -122.9333,
      48.45
    ]
  },
  "type": "Feature",
  "properties": {
    "hierarchy": [
      "tgn:2438458",
      "tgn:1000001",
      "tgn:7012149",
      "tgn:1002862",
      "tgn:7007920",
      "tgn:7029392"
    ],
    "placetype": [
      "aat:300008850"
    ],
    "id": 2438458,
    "name:xx": "Kings Point"
  }
}
