{
  "geometry": {
    "type": "Point",
    "coordinates": [
      -85.5167,
      44.6167
    ]
  },
  "type": "Feature",
  "properties": {
    "hierarchy": [
      "tgn:2497848",
      "tgn:1000001",
      "tgn:7012149",
      "tgn:2000961",
      "tgn:7007520",
      "tgn:7029392"
    ],
    "placetype": [
      "aat:300006191"
    ],
    "id": 2497848,
    "name:xx": "Mayfield Pond"
  }
}
