{
  "geometry": {
    "type": "Point",
    "coordinates": [
      -78.4167,
      34.5833
    ]
  },
  "type": "Feature",
  "properties": {
    "hierarchy": [
      "tgn:2479865",
      "tgn:1000001",
      "tgn:2001471",
      "tgn:7012149",
      "tgn:7007709",
      "tgn:7029392"
    ],
    "placetype": [
      "aat:300008699"
    ],
    "id": 2479865,
    "name:xx": "Lake Drain"
  }
}
