{
  "geometry": {
    "type": "Point",
    "coordinates": [
      -114.65,
      46.7167
    ]
  },
  "type": "Feature",
  "properties": {
    "hierarchy": [
      "tgn:2398846",
      "tgn:1000001",
      "tgn:2000469",
      "tgn:7012149",
      "tgn:7007250",
      "tgn:7029392"
    ],
    "placetype": [
      "aat:300008706"
    ],
    "id": 2398846,
    "name:xx": "Hopeful Creek"
  }
}
