{
  "geometry": {
    "type": "Point",
    "coordinates": [
      74.9167,
      52.8333
    ]
  },
  "type": "Feature",
  "properties": {
    "hierarchy": [
      "tgn:1138034",
      "tgn:1000004",
      "tgn:7011458",
      "tgn:7014786",
      "tgn:7029392"
    ],
    "placetype": [
      "aat:300008347"
    ],
    "id": 1138034,
    "name:xx": "Novoalekseyevka"
  }
}
