{
  "geometry": {
    "type": "Point",
    "coordinates": [
      -93.3167,
      31.4333
    ]
  },
  "type": "Feature",
  "properties": {
    "hierarchy": [
      "tgn:2439549",
      "tgn:1000001",
      "tgn:7012149",
      "tgn:7007256",
      "tgn:7029392"
    ],
    "placetype": [
      "aat:300008699"
    ],
    "id": 2439549,
    "name:xx": "Kisatchie Bayou"
  }
}
