{
  "geometry": {
    "type": "Point",
    "coordinates": [
      -99.2875,
      20.082778
    ]
  },
  "type": "Feature",
  "properties": {
    "hierarchy": [
      "tgn:7412669",
      "tgn:7005587",
      "tgn:1000001",
      "tgn:7005560",
      "tgn:7029392"
    ],
    "placetype": [
      "aat:300007783"
    ],
    "id": 7412669,
    "name:es": "Estación Empresa Norte Distrito Telepango"
  }
}
