{
  "type": "FeatureCollection",
  "features": [
    {
      "geometry": {
        "type": "Point",
        "coordinates": [
          8.083333,
          48.4
        ]
      },
      "type": "Feature",
      "properties": {
        "hierarchy": [
          "tgn:7091340",
          "tgn:7003692",
          "tgn:1000003",
          "tgn:7000084",
          "tgn:7029392"
        ],
        "placetype": [
          "aat:300008347"
        ],
        "id": 7091340,
        "name:xx": "Vor Ernsbach"
      }
    },
    {
      "geometry": {
        "type": "Point",
        "coordinates": [
          8.783333,
          51.033333
        ]
      },
      "type": "Feature",
      "properties": {
        "hierarchy": [
          "tgn:7091341",
          "tgn:1000003",
          "tgn:7003678",
          "tgn:7000084",
          "tgn:7029392"
        ],
        "placetype": [
          "aat:300008777"
        ],
        "id": 7091341,
        "name:xx": "Vogelhaus"
      }
    },
    {
      "geometry": {
        "type": "Point",
        "coordinates": [
          8.4,
          48.75
        ]
      },
      "type": "Feature",
      "properties": {
        "hierarchy": [
          "tgn:7091342",
          "tgn:7003692",
          "tgn:1000003",
          "tgn:7000084",
          "tgn:7029392"
        ],
        "placetype": [
          "aat:300008795"
        ],
        "id": 7091342,
        "name:xx": "Vogelhartskopf"
      }
    },
    {
      "geometry": {
        "type": "Point",
        "coordinates": [
          13.3,
          54.25
        ]
      },
      "type": "Feature",
      "properties": {
        "hierarchy": [
          "tgn:7091343",
          "tgn:1000003",
          "tgn:7000094",
          "tgn:7000084",
          "tgn:7029392"
        ],
        "placetype": [
          "aat:300386846"
        ],
        "id": 7091343,
        "name:xx": "Vogelhaken"
      }
    },
    {
      "geometry": {
        "type": "Point",
        "coordinates": [
          12.9,
          51.616667
        ]
      },
      "type": "Feature",
      "properties": {
        "hierarchy": [
          "tgn:7091344",
          "tgn:1000003",
          "tgn:7003685",
          "tgn:7000084",
          "tgn:7029392"
        ],
        "placetype": [
          "aat:300004792"
        ],
        "id": 7091344,
        "name:xx": "Försterei Vogelgesang"
      }
    },
    {
      "geometry": {
        "type": "Point",
        "coordinates": [
          12.2,
          52.55
        ]
      },
      "type": "Feature",
      "properties": {
        "hierarchy": [
          "tgn:7091345",
          "tgn:7000096",
          "tgn:1000003",
          "tgn:7000084",
          "tgn:7029392"
        ],
        "placetype": [
          "aat:300008347"
        ],
        "id": 7091345,
        "name:xx": "Vogelgesang"
      }
    },
    {
      "geometry": {
        "type": "Point",
        "coordinates": [
          12.65,
          51.733333
        ]
      },
      "type": "Feature",
      "properties": {
        "hierarchy": [
          "tgn:7091346",
          "tgn:1000003",
          "tgn:7003687",
          "tgn:7000084",
          "tgn:7029392"
        ],
        "placetype": [
          "aat:300008347"
        ],
        "id": 7091346,
        "name:xx": "Vogelgesang"
      }
    },
    {
      "geometry": {
        "type": "Point",
        "coordinates": [
          12.916667,
          51.616667
        ]
      },
      "type": "Feature",
      "properties": {
        "hierarchy": [
          "tgn:7091347",
          "tgn:1000003",
          "tgn:7003685",
          "tgn:7000084",
          "tgn:7029392"
        ],
        "placetype": [
          "aat:300008347"
        ],
        "id": 7091347,
        "name:xx": "Vogelgesang"
      }
    },
    {
      "geometry": {
        "type": "Point",
        "coordinates": [
          12.25,
          50.8
        ]
      },
      "type": "Feature",
      "properties": {
        "hierarchy": [
          "tgn:7091348",
          "tgn:1000003",
          "tgn:7003689",
          "tgn:7000084",
          "tgn:7029392"
        ],
        "placetype": [
          "aat:300008347"
        ],
        "id": 7091348,
        "name:xx": "Vogelgesang"
      }
    },
    {
      "geometry": {
        "type": "Point",
        "coordinates": [
          8.433333,
          50.333333
        ]
      },
      "type": "Feature",
      "properties": {
        "hierarchy": [
          "tgn:7091349",
          "tgn:1000003",
          "tgn:7003678",
          "tgn:7000084",
          "tgn:7029392"
        ],
        "placetype": [
          "aat:300008777"
        ],
        "id": 7091349,
        "name:xx": "Vogelgesang"
      }
    }
  ]
}
