{
  "geometry": {
    "type": "Point",
    "coordinates": [
      118.8833,
      27.6833
    ]
  },
  "type": "Feature",
  "properties": {
    "hierarchy": [
      "tgn:1140093",
      "tgn:1000004",
      "tgn:7002076",
      "tgn:1000111",
      "tgn:7029392"
    ],
    "placetype": [
      "aat:300008347"
    ],
    "id": 1140093,
    "name:xx": "Zhukou"
  }
}
