{
  "geometry": {
    "type": "Point",
    "coordinates": [
      76.09577,
      28.440283
    ]
  },
  "type": "Feature",
  "properties": {
    "hierarchy": [
      "tgn:7567187",
      "tgn:1000004",
      "tgn:1001871",
      "tgn:7000198",
      "tgn:7029392"
    ],
    "placetype": [
      "aat:300008347"
    ],
    "name:en": "Naurangāwās",
    "id": 7567187
  }
}
