{
  "geometry": {
    "type": "Point",
    "coordinates": [
      15.95,
      51.4333
    ]
  },
  "type": "Feature",
  "properties": {
    "hierarchy": [
      "tgn:1048969",
      "tgn:7024123",
      "tgn:1000003",
      "tgn:7006366",
      "tgn:7029392"
    ],
    "placetype": [
      "aat:300008347"
    ],
    "id": 1048969,
    "name:xx": "Chocianów"
  }
}
