{
  "geometry": {
    "type": "Point",
    "coordinates": [
      -71.8667,
      42.3167
    ]
  },
  "type": "Feature",
  "properties": {
    "hierarchy": [
      "tgn:2712279",
      "tgn:1000001",
      "tgn:7012149",
      "tgn:1003038",
      "tgn:7007517",
      "tgn:7029392"
    ],
    "placetype": [
      "aat:300008699"
    ],
    "id": 2712279,
    "name:xx": "Tatnuck Brook"
  }
}
