{
  "geometry": {
    "type": "Point",
    "coordinates": [
      80.242177,
      29.44438
    ]
  },
  "type": "Feature",
  "properties": {
    "hierarchy": [
      "tgn:7556929",
      "tgn:1000004",
      "tgn:7000198",
      "tgn:7031786",
      "tgn:7029392"
    ],
    "placetype": [
      "aat:300008699"
    ],
    "name:en": "Rāmgangā River",
    "id": 7556929
  }
}
