{
  "geometry": {
    "type": "Point",
    "coordinates": [
      -82.2833,
      31.4833
    ]
  },
  "type": "Feature",
  "properties": {
    "hierarchy": [
      "tgn:2267954",
      "tgn:1000001",
      "tgn:7012149",
      "tgn:2000404",
      "tgn:7007248",
      "tgn:7029392"
    ],
    "placetype": [
      "aat:300008706"
    ],
    "id": 2267954,
    "name:xx": "Crooked Creek"
  }
}
