{
  "geometry": {
    "type": "Point",
    "coordinates": [
      74.65354,
      30.530088
    ]
  },
  "type": "Feature",
  "properties": {
    "hierarchy": [
      "tgn:7545913",
      "tgn:1000004",
      "tgn:7000198",
      "tgn:7016883",
      "tgn:7029392"
    ],
    "placetype": [
      "aat:300007783"
    ],
    "name:en": "Baruwāli",
    "id": 7545913
  }
}
