{
  "geometry": {
    "type": "Point",
    "coordinates": [
      -113.45,
      46.3667
    ]
  },
  "type": "Feature",
  "properties": {
    "hierarchy": [
      "tgn:2547473",
      "tgn:1000001",
      "tgn:7012149",
      "tgn:2001279",
      "tgn:7007524",
      "tgn:7029392"
    ],
    "placetype": [
      "aat:300008706"
    ],
    "id": 2547473,
    "name:xx": "North Fork Spring Creek"
  }
}
