{
  "geometry": {
    "type": "Point",
    "coordinates": [
      -81.0833,
      26.8333
    ]
  },
  "type": "Feature",
  "properties": {
    "hierarchy": [
      "tgn:2752481",
      "tgn:1000001",
      "tgn:1002408",
      "tgn:7012149",
      "tgn:7007240",
      "tgn:7029392"
    ],
    "placetype": [
      "aat:300008347"
    ],
    "id": 2752481,
    "name:xx": "Washington Park"
  }
}
