{
  "geometry": {
    "type": "Point",
    "coordinates": [
      74.63472,
      28.494821
    ]
  },
  "type": "Feature",
  "properties": {
    "hierarchy": [
      "tgn:7563906",
      "tgn:1000004",
      "tgn:7000198",
      "tgn:7016788",
      "tgn:7029392"
    ],
    "placetype": [
      "aat:300008750"
    ],
    "name:en": "Chāchād Dhora",
    "id": 7563906
  }
}
