{
  "type": "FeatureCollection",
  "features": [
    {
      "geometry": {
        "type": "Point",
        "coordinates": [
          -2.116667,
          53.466667
        ]
      },
      "type": "Feature",
      "properties": {
        "hierarchy": [
          "tgn:7450502",
          "tgn:7002445",
          "tgn:1003650",
          "tgn:1000003",
          "tgn:7026570",
          "tgn:7008591",
          "tgn:7029392"
        ],
        "placetype": [
          "aat:300008347"
        ],
        "name:en": "Guide Bridge",
        "id": 7450502
      }
    },
    {
      "geometry": {
        "type": "Point",
        "coordinates": [
          0.633333,
          50.883333
        ]
      },
      "type": "Feature",
      "properties": {
        "hierarchy": [
          "tgn:7450505",
          "tgn:7002445",
          "tgn:1000003",
          "tgn:7008129",
          "tgn:7008591",
          "tgn:7029392"
        ],
        "placetype": [
          "aat:300008347"
        ],
        "name:en": "Guestling",
        "id": 7450505
      }
    },
    {
      "geometry": {
        "type": "Point",
        "coordinates": [
          -4.816667,
          60.4
        ]
      },
      "type": "Feature",
      "properties": {
        "hierarchy": [
          "tgn:7450506",
          "tgn:7002444",
          "tgn:1000003",
          "tgn:7008082",
          "tgn:7008591",
          "tgn:7029392"
        ],
        "placetype": [
          "aat:300011692"
        ],
        "name:en": "Guens, The",
        "id": 7450506
      }
    },
    {
      "geometry": {
        "type": "Point",
        "coordinates": [
          -4.133333,
          55.45
        ]
      },
      "type": "Feature",
      "properties": {
        "hierarchy": [
          "tgn:7450507",
          "tgn:7002444",
          "tgn:7019088",
          "tgn:1000003",
          "tgn:7008591",
          "tgn:7029392"
        ],
        "placetype": [
          "aat:300008699"
        ],
        "name:en": "Guelt Water",
        "id": 7450507
      }
    },
    {
      "geometry": {
        "type": "Point",
        "coordinates": [
          -3.616667,
          56.616667
        ]
      },
      "type": "Feature",
      "properties": {
        "hierarchy": [
          "tgn:7450508",
          "tgn:7002444",
          "tgn:1000003",
          "tgn:7019152",
          "tgn:7008591",
          "tgn:7029392"
        ],
        "placetype": [
          "aat:300007783"
        ],
        "name:en": "Guay Station",
        "id": 7450508
      }
    },
    {
      "geometry": {
        "type": "Point",
        "coordinates": [
          -2.45,
          56
        ]
      },
      "type": "Feature",
      "properties": {
        "hierarchy": [
          "tgn:7450509",
          "tgn:7002444",
          "tgn:7019115",
          "tgn:1000003",
          "tgn:7008591",
          "tgn:7029392"
        ],
        "placetype": [
          "aat:300387036"
        ],
        "name:en": "Guardy",
        "id": 7450509
      }
    }
  ]
}
