{
  "geometry": {
    "type": "Point",
    "coordinates": [
      90.5333,
      23.55
    ]
  },
  "type": "Feature",
  "properties": {
    "hierarchy": [
      "tgn:1065839",
      "tgn:7000189",
      "tgn:1000004",
      "tgn:1000105",
      "tgn:7029392"
    ],
    "placetype": [
      "aat:300008347"
    ],
    "id": 1065839,
    "name:xx": "Munshiganj"
  }
}
