{
  "type": "FeatureCollection",
  "features": [
    {
      "geometry": {
        "type": "Point",
        "coordinates": [
          -85.6833,
          30.4667
        ]
      },
      "type": "Feature",
      "properties": {
        "hierarchy": [
          "tgn:2752170",
          "tgn:1000001",
          "tgn:7012149",
          "tgn:2000291",
          "tgn:7007240",
          "tgn:7029392"
        ],
        "placetype": [
          "aat:300008680"
        ],
        "id": 2752170,
        "name:xx": "Wash Pond"
      }
    },
    {
      "geometry": {
        "type": "Point",
        "coordinates": [
          -84.9667,
          30.8167
        ]
      },
      "type": "Feature",
      "properties": {
        "hierarchy": [
          "tgn:2752171",
          "tgn:1000001",
          "tgn:2000273",
          "tgn:7012149",
          "tgn:7007240",
          "tgn:7029392"
        ],
        "placetype": [
          "aat:300008680"
        ],
        "id": 2752171,
        "name:xx": "Wash Pond"
      }
    },
    {
      "geometry": {
        "type": "Point",
        "coordinates": [
          -81.8667,
          29.1167
        ]
      },
      "type": "Feature",
      "properties": {
        "hierarchy": [
          "tgn:2752172",
          "tgn:1000001",
          "tgn:7012149",
          "tgn:1002631",
          "tgn:7007240",
          "tgn:7029392"
        ],
        "placetype": [
          "aat:300008680"
        ],
        "id": 2752172,
        "name:xx": "Wash Pond"
      }
    },
    {
      "geometry": {
        "type": "Point",
        "coordinates": [
          -84.8333,
          30.9333
        ]
      },
      "type": "Feature",
      "properties": {
        "hierarchy": [
          "tgn:2752173",
          "tgn:1000001",
          "tgn:7012149",
          "tgn:2000416",
          "tgn:7007248",
          "tgn:7029392"
        ],
        "placetype": [
          "aat:300006191"
        ],
        "id": 2752173,
        "name:xx": "Wash Pond"
      }
    },
    {
      "geometry": {
        "type": "Point",
        "coordinates": [
          -69.9833,
          41.75
        ]
      },
      "type": "Feature",
      "properties": {
        "hierarchy": [
          "tgn:2752174",
          "tgn:1002165",
          "tgn:1000001",
          "tgn:7012149",
          "tgn:7007517",
          "tgn:7029392"
        ],
        "placetype": [
          "aat:300008680"
        ],
        "id": 2752174,
        "name:xx": "Wash Pond"
      }
    },
    {
      "geometry": {
        "type": "Point",
        "coordinates": [
          -71.1667,
          42.8833
        ]
      },
      "type": "Feature",
      "properties": {
        "hierarchy": [
          "tgn:2752175",
          "tgn:1000001",
          "tgn:7014352",
          "tgn:7012149",
          "tgn:7007564",
          "tgn:7029392"
        ],
        "placetype": [
          "aat:300008680"
        ],
        "id": 2752175,
        "name:xx": "Wash Pond"
      }
    },
    {
      "geometry": {
        "type": "Point",
        "coordinates": [
          -71.5667,
          41.2
        ]
      },
      "type": "Feature",
      "properties": {
        "hierarchy": [
          "tgn:2752176",
          "tgn:1002996",
          "tgn:1000001",
          "tgn:7012149",
          "tgn:7007711",
          "tgn:7029392"
        ],
        "placetype": [
          "aat:300008680"
        ],
        "id": 2752176,
        "name:xx": "Wash Pond"
      }
    },
    {
      "geometry": {
        "type": "Point",
        "coordinates": [
          -177.9,
          51.6167
        ]
      },
      "type": "Feature",
      "properties": {
        "hierarchy": [
          "tgn:2752177",
          "tgn:7030516",
          "tgn:7006450",
          "tgn:1000001",
          "tgn:7012149",
          "tgn:7029392"
        ],
        "placetype": [
          "aat:300132348"
        ],
        "id": 2752177,
        "name:xx": "Wash Reef"
      }
    },
    {
      "geometry": {
        "type": "Point",
        "coordinates": [
          -83.1333,
          35.6167
        ]
      },
      "type": "Feature",
      "properties": {
        "hierarchy": [
          "tgn:2752178",
          "tgn:1000001",
          "tgn:7012149",
          "tgn:2001503",
          "tgn:7007709",
          "tgn:7029392"
        ],
        "placetype": [
          "aat:300266640"
        ],
        "id": 2752178,
        "name:xx": "Wash Ridge"
      }
    },
    {
      "geometry": {
        "type": "Point",
        "coordinates": [
          -84.3,
          36.4667
        ]
      },
      "type": "Feature",
      "properties": {
        "hierarchy": [
          "tgn:2752179",
          "tgn:1000001",
          "tgn:7012149",
          "tgn:2001843",
          "tgn:7007825",
          "tgn:7029392"
        ],
        "placetype": [
          "aat:300266640"
        ],
        "id": 2752179,
        "name:xx": "Wash Ridge"
      }
    }
  ]
}
