{
  "geometry": {
    "type": "Point",
    "coordinates": [
      -77.5667,
      37.4333
    ]
  },
  "type": "Feature",
  "properties": {
    "hierarchy": [
      "tgn:2322326",
      "tgn:1000001",
      "tgn:1002267",
      "tgn:7012149",
      "tgn:7007919",
      "tgn:7029392"
    ],
    "placetype": [
      "aat:300008347"
    ],
    "id": 2322326,
    "name:xx": "Falling Creek Farms"
  }
}
