{
  "type": "FeatureCollection",
  "features": [
    {
      "geometry": {
        "type": "Point",
        "coordinates": [
          -118.4333,
          37.1167
        ]
      },
      "type": "Feature",
      "properties": {
        "hierarchy": [
          "tgn:2169950",
          "tgn:1000001",
          "tgn:7012149",
          "tgn:2000183",
          "tgn:7007157",
          "tgn:7029392"
        ],
        "placetype": [
          "aat:300008706"
        ],
        "id": 2169950,
        "name:xx": "Big Pine Creek"
      }
    },
    {
      "geometry": {
        "type": "Point",
        "coordinates": [
          -115.75,
          44.0833
        ]
      },
      "type": "Feature",
      "properties": {
        "hierarchy": [
          "tgn:2169951",
          "tgn:1000001",
          "tgn:2000459",
          "tgn:7012149",
          "tgn:7007250",
          "tgn:7029392"
        ],
        "placetype": [
          "aat:300008706"
        ],
        "id": 2169951,
        "name:xx": "Big Pine Creek"
      }
    },
    {
      "geometry": {
        "type": "Point",
        "coordinates": [
          -107.3167,
          45.0833
        ]
      },
      "type": "Feature",
      "properties": {
        "hierarchy": [
          "tgn:2169953",
          "tgn:1000001",
          "tgn:7012149",
          "tgn:7007524",
          "tgn:7029392"
        ],
        "placetype": [
          "aat:300008706"
        ],
        "id": 2169953,
        "name:xx": "Big Pine Creek"
      }
    },
    {
      "geometry": {
        "type": "Point",
        "coordinates": [
          -110.7667,
          45.2
        ]
      },
      "type": "Feature",
      "properties": {
        "hierarchy": [
          "tgn:2169954",
          "tgn:1000001",
          "tgn:7012149",
          "tgn:2001293",
          "tgn:7007524",
          "tgn:7029392"
        ],
        "placetype": [
          "aat:300008706"
        ],
        "id": 2169954,
        "name:xx": "Big Pine Creek"
      }
    },
    {
      "geometry": {
        "type": "Point",
        "coordinates": [
          -82.8,
          35.7833
        ]
      },
      "type": "Feature",
      "properties": {
        "hierarchy": [
          "tgn:2169955",
          "tgn:1000001",
          "tgn:7012149",
          "tgn:2001516",
          "tgn:7007709",
          "tgn:7029392"
        ],
        "placetype": [
          "aat:300008706"
        ],
        "id": 2169955,
        "name:xx": "Big Pine Creek"
      }
    },
    {
      "geometry": {
        "type": "Point",
        "coordinates": [
          -80.9333,
          36.5167
        ]
      },
      "type": "Feature",
      "properties": {
        "hierarchy": [
          "tgn:2169956",
          "tgn:2001465",
          "tgn:1000001",
          "tgn:7012149",
          "tgn:7007709",
          "tgn:7029392"
        ],
        "placetype": [
          "aat:300008706"
        ],
        "id": 2169956,
        "name:xx": "Big Pine Creek"
      }
    },
    {
      "geometry": {
        "type": "Point",
        "coordinates": [
          -95.2167,
          33.8333
        ]
      },
      "type": "Feature",
      "properties": {
        "hierarchy": [
          "tgn:2169957",
          "tgn:1000001",
          "tgn:7012149",
          "tgn:2002061",
          "tgn:7007826",
          "tgn:7029392"
        ],
        "placetype": [
          "aat:300008706"
        ],
        "id": 2169957,
        "name:xx": "Big Pine Creek"
      }
    },
    {
      "geometry": {
        "type": "Point",
        "coordinates": [
          -89.45,
          45.45
        ]
      },
      "type": "Feature",
      "properties": {
        "hierarchy": [
          "tgn:2169958",
          "tgn:1000001",
          "tgn:7012149",
          "tgn:2002334",
          "tgn:7007922",
          "tgn:7029392"
        ],
        "placetype": [
          "aat:300008706"
        ],
        "id": 2169958,
        "name:xx": "Big Pine Creek"
      }
    },
    {
      "geometry": {
        "type": "Point",
        "coordinates": [
          -77.4667,
          39.95
        ]
      },
      "type": "Feature",
      "properties": {
        "hierarchy": [
          "tgn:2169959",
          "tgn:1000001",
          "tgn:7012149",
          "tgn:7007710",
          "tgn:7029392"
        ],
        "placetype": [
          "aat:300266640"
        ],
        "id": 2169959,
        "name:xx": "Big Pine Flat Ridge"
      }
    }
  ]
}
