{
  "geometry": {
    "type": "Point",
    "coordinates": [
      -88.2833,
      34.9167
    ]
  },
  "type": "Feature",
  "properties": {
    "hierarchy": [
      "tgn:2781651",
      "tgn:1000001",
      "tgn:7012149",
      "tgn:2001156",
      "tgn:7007522",
      "tgn:7029392"
    ],
    "placetype": [
      "aat:300008699"
    ],
    "id": 2781651,
    "name:xx": "Woodruff Branch"
  }
}
