{
  "geometry": {
    "type": "Point",
    "coordinates": [
      -77.3167,
      37.85
    ]
  },
  "type": "Feature",
  "properties": {
    "hierarchy": [
      "tgn:2515399",
      "tgn:1000001",
      "tgn:1002235",
      "tgn:7012149",
      "tgn:7007919",
      "tgn:7029392"
    ],
    "placetype": [
      "aat:300008706"
    ],
    "id": 2515399,
    "name:xx": "Millpond Creek"
  }
}
