{
  "type": "FeatureCollection",
  "features": [
    {
      "geometry": {
        "type": "Point",
        "coordinates": [
          29.4833,
          58.95
        ]
      },
      "type": "Feature",
      "properties": {
        "hierarchy": [
          "tgn:1055890",
          "tgn:1000004",
          "tgn:7011572",
          "tgn:7018214",
          "tgn:7002435",
          "tgn:7029392"
        ],
        "placetype": [
          "aat:300008347"
        ],
        "id": 1055890,
        "name:xx": "Krasnyje Gory"
      }
    },
    {
      "geometry": {
        "type": "Point",
        "coordinates": [
          29.4833,
          47.5
        ]
      },
      "type": "Feature",
      "properties": {
        "hierarchy": [
          "tgn:1055891",
          "tgn:1000003",
          "tgn:1003396",
          "tgn:7006660",
          "tgn:7029392"
        ],
        "placetype": [
          "aat:300008347"
        ],
        "id": 1055891,
        "name:xx": "Krasnyye Okny"
      }
    },
    {
      "geometry": {
        "type": "Point",
        "coordinates": [
          31.7833,
          50.95
        ]
      },
      "type": "Feature",
      "properties": {
        "hierarchy": [
          "tgn:1055892",
          "tgn:7012002",
          "tgn:1000003",
          "tgn:7006660",
          "tgn:7029392"
        ],
        "placetype": [
          "aat:300008347"
        ],
        "id": 1055892,
        "name:xx": "Krasnyje Partizany"
      }
    },
    {
      "geometry": {
        "type": "Point",
        "coordinates": [
          39.7,
          57.5
        ]
      },
      "type": "Feature",
      "properties": {
        "hierarchy": [
          "tgn:1055893",
          "tgn:1000004",
          "tgn:7011608",
          "tgn:7018214",
          "tgn:7002435",
          "tgn:7029392"
        ],
        "placetype": [
          "aat:300008347"
        ],
        "id": 1055893,
        "name:xx": "Krasnyye Tkachi"
      }
    },
    {
      "geometry": {
        "type": "Point",
        "coordinates": [
          33.2,
          57.3833
        ]
      },
      "type": "Feature",
      "properties": {
        "hierarchy": [
          "tgn:1055894",
          "tgn:1000004",
          "tgn:7012941",
          "tgn:7018214",
          "tgn:7002435",
          "tgn:7029392"
        ],
        "placetype": [
          "aat:300008347"
        ],
        "id": 1055894,
        "name:xx": "Krasukha"
      }
    },
    {
      "geometry": {
        "type": "Point",
        "coordinates": [
          38.5167,
          60.95
        ]
      },
      "type": "Feature",
      "properties": {
        "hierarchy": [
          "tgn:1055895",
          "tgn:4000818",
          "tgn:1000004",
          "tgn:7018214",
          "tgn:7002435",
          "tgn:7029392"
        ],
        "placetype": [
          "aat:300008347"
        ],
        "id": 1055895,
        "name:xx": "Krechetovo"
      }
    },
    {
      "geometry": {
        "type": "Point",
        "coordinates": [
          31.4,
          58.6167
        ]
      },
      "type": "Feature",
      "properties": {
        "hierarchy": [
          "tgn:1055896",
          "tgn:1000004",
          "tgn:4008031",
          "tgn:7018214",
          "tgn:7002435",
          "tgn:7029392"
        ],
        "placetype": [
          "aat:300008347"
        ],
        "id": 1055896,
        "name:xx": "Krechevitsy"
      }
    },
    {
      "geometry": {
        "type": "Point",
        "coordinates": [
          80,
          55.85
        ]
      },
      "type": "Feature",
      "properties": {
        "hierarchy": [
          "tgn:1055897",
          "tgn:1000004",
          "tgn:7011589",
          "tgn:7018214",
          "tgn:7002435",
          "tgn:7029392"
        ],
        "placetype": [
          "aat:300008347"
        ],
        "id": 1055897,
        "name:xx": "Kreshchenka"
      }
    },
    {
      "geometry": {
        "type": "Point",
        "coordinates": [
          37.5,
          47.3333
        ]
      },
      "type": "Feature",
      "properties": {
        "hierarchy": [
          "tgn:1055898",
          "tgn:7012076",
          "tgn:1000003",
          "tgn:7006660",
          "tgn:7029392"
        ],
        "placetype": [
          "aat:300008347"
        ],
        "id": 1055898,
        "name:xx": "Kremenevka"
      }
    },
    {
      "geometry": {
        "type": "Point",
        "coordinates": [
          33.4167,
          49.05
        ]
      },
      "type": "Feature",
      "properties": {
        "hierarchy": [
          "tgn:1055899",
          "tgn:1000003",
          "tgn:7011666",
          "tgn:7006660",
          "tgn:7029392"
        ],
        "placetype": [
          "aat:300008347"
        ],
        "id": 1055899,
        "name:xx": "Kremenchug"
      }
    }
  ]
}
