{
  "geometry": {
    "type": "Point",
    "coordinates": [
      42.85,
      37.4167
    ]
  },
  "type": "Feature",
  "properties": {
    "hierarchy": [
      "tgn:1086472",
      "tgn:1001282",
      "tgn:1000004",
      "tgn:7018455",
      "tgn:1000144",
      "tgn:7029392"
    ],
    "placetype": [
      "aat:300008347"
    ],
    "id": 1086472,
    "name:xx": "Uludere"
  }
}
