{
  "geometry": {
    "type": "Point",
    "coordinates": [
      -85.3333,
      33.35
    ]
  },
  "type": "Feature",
  "properties": {
    "hierarchy": [
      "tgn:2218557",
      "tgn:7002659",
      "tgn:1000001",
      "tgn:7012149",
      "tgn:2000055",
      "tgn:7029392"
    ],
    "placetype": [
      "aat:300008706"
    ],
    "id": 2218557,
    "name:xx": "Cane Creek"
  }
}
