{
  "geometry": {
    "type": "Point",
    "coordinates": [
      51.15,
      54.95
    ]
  },
  "type": "Feature",
  "properties": {
    "hierarchy": [
      "tgn:1051269",
      "tgn:1000004",
      "tgn:7002435",
      "tgn:7011524",
      "tgn:7029392"
    ],
    "placetype": [
      "aat:300008347"
    ],
    "id": 1051269,
    "name:xx": "Čer'omuchova"
  }
}
