{
  "geometry": {
    "type": "Point",
    "coordinates": [
      -88.0333,
      37.95
    ]
  },
  "type": "Feature",
  "properties": {
    "hierarchy": [
      "tgn:2453290",
      "tgn:1000001",
      "tgn:7012149",
      "tgn:2000537",
      "tgn:7007251",
      "tgn:7029392"
    ],
    "placetype": [
      "aat:300008798"
    ],
    "id": 2453290,
    "name:xx": "Little Chain Hills"
  }
}
