{
  "geometry": {
    "type": "Point",
    "coordinates": [
      -82.7167,
      38.5167
    ]
  },
  "type": "Feature",
  "properties": {
    "hierarchy": [
      "tgn:2038863",
      "tgn:1000001",
      "tgn:7012149",
      "tgn:1002426",
      "tgn:7007255",
      "tgn:7029392"
    ],
    "placetype": [
      "aat:300008347"
    ],
    "id": 2038863,
    "name:xx": "Flatwoods"
  }
}
