{
  "geometry": {
    "type": "Point",
    "coordinates": [
      -94.9667,
      36.3333
    ]
  },
  "type": "Feature",
  "properties": {
    "hierarchy": [
      "tgn:2176288",
      "tgn:1000001",
      "tgn:7012149",
      "tgn:7007707",
      "tgn:7029392"
    ],
    "placetype": [
      "aat:300008761"
    ],
    "id": 2176288,
    "name:xx": "Black Hollow"
  }
}
