{
  "geometry": {
    "type": "Point",
    "coordinates": [
      -48.75,
      -1.8667
    ]
  },
  "type": "Feature",
  "properties": {
    "hierarchy": [
      "tgn:1022122",
      "tgn:7006247",
      "tgn:1000047",
      "tgn:7002456",
      "tgn:1000002",
      "tgn:7029392"
    ],
    "placetype": [
      "aat:300008347"
    ],
    "id": 1022122,
    "name:xx": "Moju"
  }
}
