{
  "geometry": {
    "type": "Point",
    "coordinates": [
      76.808033,
      30.744172
    ]
  },
  "type": "Feature",
  "properties": {
    "hierarchy": [
      "tgn:7585132",
      "tgn:1000004",
      "tgn:7000200",
      "tgn:7000198",
      "tgn:7029392"
    ],
    "placetype": [
      "aat:300008347"
    ],
    "name:en": "Rāj Bhavan Haryāna",
    "id": 7585132
  }
}
