{
  "type": "FeatureCollection",
  "features": [
    {
      "geometry": {
        "type": "Point",
        "coordinates": [
          9.0167,
          39
        ]
      },
      "type": "Feature",
      "properties": {
        "hierarchy": [
          "tgn:1099851",
          "tgn:1001641",
          "tgn:1000003",
          "tgn:7003121",
          "tgn:1000080",
          "tgn:7029392"
        ],
        "placetype": [
          "aat:300008347",
          "aat:300167671"
        ],
        "id": 1099851,
        "name:xx": "Nora"
      }
    },
    {
      "geometry": {
        "type": "Point",
        "coordinates": [
          15.0333,
          36.9333
        ]
      },
      "type": "Feature",
      "properties": {
        "hierarchy": [
          "tgn:1099853",
          "tgn:1000003",
          "tgn:7003122",
          "tgn:1001753",
          "tgn:1000080",
          "tgn:7029392"
        ],
        "placetype": [
          "aat:300008347",
          "aat:300000810",
          "aat:300167671"
        ],
        "id": 1099853,
        "name:xx": "Noto Antica"
      }
    },
    {
      "geometry": {
        "type": "Point",
        "coordinates": [
          23.7333,
          37.9667
        ]
      },
      "type": "Feature",
      "properties": {
        "hierarchy": [
          "tgn:1099856",
          "tgn:7001393",
          "tgn:7001387",
          "tgn:1000003",
          "tgn:1000074",
          "tgn:7029392"
        ],
        "placetype": [
          "aat:300008057",
          "aat:300387272",
          "aat:300007595"
        ],
        "id": 1099856,
        "name:xx": "Olympieion"
      }
    }
  ]
}
