{
  "geometry": {
    "type": "Point",
    "coordinates": [
      -88.8833,
      34.9833
    ]
  },
  "type": "Feature",
  "properties": {
    "hierarchy": [
      "tgn:2056046",
      "tgn:1000001",
      "tgn:7012149",
      "tgn:2001155",
      "tgn:7007522",
      "tgn:7029392"
    ],
    "placetype": [
      "aat:300008347",
      "aat:300387210"
    ],
    "id": 2056046,
    "name:xx": "Brownfield"
  }
}
