{
  "geometry": {
    "type": "Point",
    "coordinates": [
      -115.85,
      50.25
    ]
  },
  "type": "Feature",
  "properties": {
    "hierarchy": [
      "tgn:1115955",
      "tgn:7005735",
      "tgn:7005685",
      "tgn:1000001",
      "tgn:7029392"
    ],
    "placetype": [
      "aat:300008680"
    ],
    "id": 1115955,
    "name:xx": "Columbia Lake"
  }
}
