{
  "geometry": {
    "type": "Point",
    "coordinates": [
      120.6844,
      23.8971
    ]
  },
  "type": "Feature",
  "properties": {
    "hierarchy": [
      "tgn:7476383",
      "tgn:7488858",
      "tgn:1000004",
      "tgn:1000141",
      "tgn:7029392"
    ],
    "placetype": [
      "aat:300006495"
    ],
    "id": 7476383,
    "name:xx": "Jiahe Guoxiao"
  }
}
