{
  "geometry": {
    "type": "Point",
    "coordinates": [
      -106.3333,
      36.4667
    ]
  },
  "type": "Feature",
  "properties": {
    "hierarchy": [
      "tgn:2218872",
      "tgn:1000001",
      "tgn:7012149",
      "tgn:2001449",
      "tgn:7007566",
      "tgn:7029392"
    ],
    "placetype": [
      "aat:300006191"
    ],
    "id": 2218872,
    "name:xx": "Canevas Tank"
  }
}
