{
  "geometry": {
    "type": "Point",
    "coordinates": [
      -103.3833,
      40.4333
    ]
  },
  "type": "Feature",
  "properties": {
    "hierarchy": [
      "tgn:2598371",
      "tgn:1000001",
      "tgn:7012149",
      "tgn:7007158",
      "tgn:7029392"
    ],
    "placetype": [
      "aat:300006075"
    ],
    "id": 2598371,
    "name:xx": "Prewitt Outlet Canal"
  }
}
