{
  "geometry": {
    "type": "Point",
    "coordinates": [
      -85.8333,
      38.0333
    ]
  },
  "type": "Feature",
  "properties": {
    "hierarchy": [
      "tgn:2574822",
      "tgn:1000001",
      "tgn:2000774",
      "tgn:7012149",
      "tgn:7007255",
      "tgn:7029392"
    ],
    "placetype": [
      "aat:300008798"
    ],
    "id": 2574822,
    "name:xx": "Pendleton Hill"
  }
}
