{
  "type": "FeatureCollection",
  "features": [
    {
      "geometry": {
        "type": "Point",
        "coordinates": [
          -93.6,
          35.0333
        ]
      },
      "type": "Feature",
      "properties": {
        "hierarchy": [
          "tgn:2512440",
          "tgn:1000001",
          "tgn:7016172",
          "tgn:7012149",
          "tgn:2000179",
          "tgn:7029392"
        ],
        "placetype": [
          "aat:300008706"
        ],
        "id": 2512440,
        "name:xx": "Mill Creek"
      }
    },
    {
      "geometry": {
        "type": "Point",
        "coordinates": [
          -93.2,
          35.7667
        ]
      },
      "type": "Feature",
      "properties": {
        "hierarchy": [
          "tgn:2512441",
          "tgn:1000001",
          "tgn:7016172",
          "tgn:7012149",
          "tgn:2000155",
          "tgn:7029392"
        ],
        "placetype": [
          "aat:300008706"
        ],
        "id": 2512441,
        "name:xx": "Mill Creek"
      }
    },
    {
      "geometry": {
        "type": "Point",
        "coordinates": [
          -92.3333,
          35.9
        ]
      },
      "type": "Feature",
      "properties": {
        "hierarchy": [
          "tgn:2512442",
          "tgn:1000001",
          "tgn:7016172",
          "tgn:7012149",
          "tgn:2000173",
          "tgn:7029392"
        ],
        "placetype": [
          "aat:300008706"
        ],
        "id": 2512442,
        "name:xx": "Mill Creek"
      }
    },
    {
      "geometry": {
        "type": "Point",
        "coordinates": [
          -91.45,
          35.9667
        ]
      },
      "type": "Feature",
      "properties": {
        "hierarchy": [
          "tgn:2512443",
          "tgn:1000001",
          "tgn:7016172",
          "tgn:7012149",
          "tgn:2000172",
          "tgn:7029392"
        ],
        "placetype": [
          "aat:300008706"
        ],
        "id": 2512443,
        "name:xx": "Mill Creek"
      }
    },
    {
      "geometry": {
        "type": "Point",
        "coordinates": [
          -92.7,
          36.15
        ]
      },
      "type": "Feature",
      "properties": {
        "hierarchy": [
          "tgn:2512444",
          "tgn:1000001",
          "tgn:7016172",
          "tgn:7012149",
          "tgn:2000149",
          "tgn:7029392"
        ],
        "placetype": [
          "aat:300008706"
        ],
        "id": 2512444,
        "name:xx": "Mill Creek"
      }
    },
    {
      "geometry": {
        "type": "Point",
        "coordinates": [
          -91.7,
          36.4
        ]
      },
      "type": "Feature",
      "properties": {
        "hierarchy": [
          "tgn:2512445",
          "tgn:1000001",
          "tgn:7016172",
          "tgn:7012149",
          "tgn:2000129",
          "tgn:7029392"
        ],
        "placetype": [
          "aat:300008706"
        ],
        "id": 2512445,
        "name:xx": "Mill Creek"
      }
    },
    {
      "geometry": {
        "type": "Point",
        "coordinates": [
          -93.3833,
          33.5167
        ]
      },
      "type": "Feature",
      "properties": {
        "hierarchy": [
          "tgn:2512446",
          "tgn:1000001",
          "tgn:7016172",
          "tgn:7012149",
          "tgn:2000154",
          "tgn:7029392"
        ],
        "placetype": [
          "aat:300008706"
        ],
        "id": 2512446,
        "name:xx": "Mill Creek"
      }
    },
    {
      "geometry": {
        "type": "Point",
        "coordinates": [
          -92.25,
          33.85
        ]
      },
      "type": "Feature",
      "properties": {
        "hierarchy": [
          "tgn:2512447",
          "tgn:1000001",
          "tgn:7016172",
          "tgn:2000117",
          "tgn:7012149",
          "tgn:7029392"
        ],
        "placetype": [
          "aat:300008706"
        ],
        "id": 2512447,
        "name:xx": "Mill Creek"
      }
    },
    {
      "geometry": {
        "type": "Point",
        "coordinates": [
          -93.75,
          34.4
        ]
      },
      "type": "Feature",
      "properties": {
        "hierarchy": [
          "tgn:2512448",
          "tgn:1000001",
          "tgn:7016172",
          "tgn:7012149",
          "tgn:2000153",
          "tgn:7029392"
        ],
        "placetype": [
          "aat:300008706"
        ],
        "id": 2512448,
        "name:xx": "Mill Creek"
      }
    },
    {
      "geometry": {
        "type": "Point",
        "coordinates": [
          -94.25,
          34.4833
        ]
      },
      "type": "Feature",
      "properties": {
        "hierarchy": [
          "tgn:2512449",
          "tgn:1000001",
          "tgn:7016172",
          "tgn:7012149",
          "tgn:2000161",
          "tgn:7029392"
        ],
        "placetype": [
          "aat:300008706"
        ],
        "id": 2512449,
        "name:xx": "Mill Creek"
      }
    }
  ]
}
