{
  "type": "FeatureCollection",
  "features": [
    {
      "geometry": {
        "type": "Point",
        "coordinates": [
          -105,
          26.183333
        ]
      },
      "type": "Feature",
      "properties": {
        "hierarchy": [
          "tgn:7357350",
          "tgn:7005583",
          "tgn:1000001",
          "tgn:7005560",
          "tgn:7029392"
        ],
        "placetype": [
          "aat:300266554",
          "aat:300008699"
        ],
        "id": 7357350,
        "name:xx": "Carrizo, Arroyo del"
      }
    },
    {
      "geometry": {
        "type": "Point",
        "coordinates": [
          -106.816667,
          26.583333
        ]
      },
      "type": "Feature",
      "properties": {
        "hierarchy": [
          "tgn:7357351",
          "tgn:7005581",
          "tgn:1000001",
          "tgn:7005560",
          "tgn:7029392"
        ],
        "placetype": [
          "aat:300008699"
        ],
        "id": 7357351,
        "name:xx": "Carrizo, Arroyo del"
      }
    },
    {
      "geometry": {
        "type": "Point",
        "coordinates": [
          -101.583333,
          24.55
        ]
      },
      "type": "Feature",
      "properties": {
        "hierarchy": [
          "tgn:7357352",
          "tgn:1000001",
          "tgn:7005601",
          "tgn:7005560",
          "tgn:7029392"
        ],
        "placetype": [
          "aat:300008347"
        ],
        "id": 7357352,
        "name:xx": "Cuitáhuac"
      }
    },
    {
      "geometry": {
        "type": "Point",
        "coordinates": [
          -110.45,
          30.916667
        ]
      },
      "type": "Feature",
      "properties": {
        "hierarchy": [
          "tgn:7357353",
          "tgn:1000001",
          "tgn:1001960",
          "tgn:7005560",
          "tgn:7029392"
        ],
        "placetype": [
          "aat:300008699"
        ],
        "id": 7357353,
        "name:xx": "Cuitaca, Arroyo"
      }
    },
    {
      "geometry": {
        "type": "Point",
        "coordinates": [
          -103.8,
          20.633333
        ]
      },
      "type": "Feature",
      "properties": {
        "hierarchy": [
          "tgn:7357357",
          "tgn:7005586",
          "tgn:1000001",
          "tgn:7005560",
          "tgn:7029392"
        ],
        "placetype": [
          "aat:300007783"
        ],
        "id": 7357357,
        "name:xx": "Cuisillos"
      }
    },
    {
      "geometry": {
        "type": "Point",
        "coordinates": [
          -103.766667,
          20.6
        ]
      },
      "type": "Feature",
      "properties": {
        "hierarchy": [
          "tgn:7357358",
          "tgn:7005586",
          "tgn:1000001",
          "tgn:7005560",
          "tgn:7029392"
        ],
        "placetype": [
          "aat:300008347"
        ],
        "id": 7357358,
        "name:xx": "Cuisillos"
      }
    },
    {
      "geometry": {
        "type": "Point",
        "coordinates": [
          -102.616667,
          20.35
        ]
      },
      "type": "Feature",
      "properties": {
        "hierarchy": [
          "tgn:7357359",
          "tgn:7005586",
          "tgn:1000001",
          "tgn:7005560",
          "tgn:7029392"
        ],
        "placetype": [
          "aat:300006191"
        ],
        "id": 7357359,
        "name:xx": "Cuisillo"
      }
    }
  ]
}
