{
  "geometry": {
    "type": "Point",
    "coordinates": [
      23.8833,
      47.9333
    ]
  },
  "type": "Feature",
  "properties": {
    "hierarchy": [
      "tgn:7004054",
      "tgn:1000003",
      "tgn:7002696",
      "tgn:1000091",
      "tgn:7029392"
    ],
    "placetype": [
      "aat:300008347"
    ],
    "id": 7004054,
    "name:xx": "Sighetu Marmaţiei"
  }
}
