{
  "geometry": {
    "type": "Point",
    "coordinates": [
      -103.6833,
      43.3833
    ]
  },
  "type": "Feature",
  "properties": {
    "hierarchy": [
      "tgn:1107454",
      "tgn:1000001",
      "tgn:2001793",
      "tgn:7012149",
      "tgn:7007713",
      "tgn:7029392"
    ],
    "placetype": [
      "aat:300008798"
    ],
    "id": 1107454,
    "name:xx": "Parker Peak"
  }
}
