{
  "type": "FeatureCollection",
  "features": [
    {
      "geometry": {
        "type": "Point",
        "coordinates": [
          9.616667,
          52.833333
        ]
      },
      "type": "Feature",
      "properties": {
        "hierarchy": [
          "tgn:7190151",
          "tgn:1000003",
          "tgn:7003676",
          "tgn:7000084",
          "tgn:7029392"
        ],
        "placetype": [
          "aat:300008347"
        ],
        "id": 7190151,
        "name:xx": "Ellinghausen"
      }
    },
    {
      "geometry": {
        "type": "Point",
        "coordinates": [
          8.583333,
          52.783333
        ]
      },
      "type": "Feature",
      "properties": {
        "hierarchy": [
          "tgn:7190152",
          "tgn:1000003",
          "tgn:7003676",
          "tgn:7000084",
          "tgn:7029392"
        ],
        "placetype": [
          "aat:300008347"
        ],
        "id": 7190152,
        "name:xx": "Ellinghausen"
      }
    },
    {
      "geometry": {
        "type": "Point",
        "coordinates": [
          7.433333,
          51.55
        ]
      },
      "type": "Feature",
      "properties": {
        "hierarchy": [
          "tgn:7190153",
          "tgn:1000003",
          "tgn:7003677",
          "tgn:7000084",
          "tgn:7029392"
        ],
        "placetype": [
          "aat:300008347"
        ],
        "id": 7190153,
        "name:xx": "Ellinghausen"
      }
    },
    {
      "geometry": {
        "type": "Point",
        "coordinates": [
          7.333333,
          51.35
        ]
      },
      "type": "Feature",
      "properties": {
        "hierarchy": [
          "tgn:7190154",
          "tgn:1000003",
          "tgn:7003677",
          "tgn:7000084",
          "tgn:7029392"
        ],
        "placetype": [
          "aat:300008347"
        ],
        "id": 7190154,
        "name:xx": "Ellinghausen"
      }
    },
    {
      "geometry": {
        "type": "Point",
        "coordinates": [
          7.616667,
          51.183333
        ]
      },
      "type": "Feature",
      "properties": {
        "hierarchy": [
          "tgn:7190155",
          "tgn:1000003",
          "tgn:7003677",
          "tgn:7000084",
          "tgn:7029392"
        ],
        "placetype": [
          "aat:300008347"
        ],
        "id": 7190155,
        "name:xx": "Ellinghausen"
      }
    },
    {
      "geometry": {
        "type": "Point",
        "coordinates": [
          7.166667,
          51.116667
        ]
      },
      "type": "Feature",
      "properties": {
        "hierarchy": [
          "tgn:7190156",
          "tgn:1000003",
          "tgn:7003677",
          "tgn:7000084",
          "tgn:7029392"
        ],
        "placetype": [
          "aat:300008347"
        ],
        "id": 7190156,
        "name:xx": "Ellinghausen"
      }
    },
    {
      "geometry": {
        "type": "Point",
        "coordinates": [
          8.65,
          51.633333
        ]
      },
      "type": "Feature",
      "properties": {
        "hierarchy": [
          "tgn:7190157",
          "tgn:1000003",
          "tgn:7003677",
          "tgn:7000084",
          "tgn:7029392"
        ],
        "placetype": [
          "aat:300000206"
        ],
        "id": 7190157,
        "name:xx": "Ellinghausen"
      }
    },
    {
      "geometry": {
        "type": "Point",
        "coordinates": [
          9.816667,
          51.333333
        ]
      },
      "type": "Feature",
      "properties": {
        "hierarchy": [
          "tgn:7190158",
          "tgn:1000003",
          "tgn:7003678",
          "tgn:7000084",
          "tgn:7029392"
        ],
        "placetype": [
          "aat:300008347"
        ],
        "id": 7190158,
        "name:xx": "Ellingerode"
      }
    },
    {
      "geometry": {
        "type": "Point",
        "coordinates": [
          9.7,
          50.983333
        ]
      },
      "type": "Feature",
      "properties": {
        "hierarchy": [
          "tgn:7190159",
          "tgn:1000003",
          "tgn:7003678",
          "tgn:7000084",
          "tgn:7029392"
        ],
        "placetype": [
          "aat:300000206"
        ],
        "id": 7190159,
        "name:xx": "Ellingerode"
      }
    }
  ]
}
