{
  "geometry": {
    "type": "Point",
    "coordinates": [
      -174.5333,
      -4.6667
    ]
  },
  "type": "Feature",
  "properties": {
    "hierarchy": [
      "tgn:1006079",
      "tgn:1010215",
      "tgn:1000217",
      "tgn:1000006",
      "tgn:7029392"
    ],
    "placetype": [
      "aat:300008793"
    ],
    "id": 1006079,
    "name:xx": "Nikumaroro"
  }
}
