{
  "geometry": {
    "type": "Point",
    "coordinates": [
      -122.1833,
      47.45
    ]
  },
  "type": "Feature",
  "properties": {
    "hierarchy": [
      "tgn:2170975",
      "tgn:1000001",
      "tgn:7012149",
      "tgn:7018871",
      "tgn:7007920",
      "tgn:7029392"
    ],
    "placetype": [
      "aat:300008706"
    ],
    "id": 2170975,
    "name:xx": "Big Soos Creek"
  }
}
