{
  "geometry": {
    "type": "Point",
    "coordinates": [
      -69.55,
      -21.95
    ]
  },
  "type": "Feature",
  "properties": {
    "hierarchy": [
      "tgn:7276016",
      "tgn:7016598",
      "tgn:1000049",
      "tgn:1000002",
      "tgn:7029392"
    ],
    "placetype": [
      "aat:300259572"
    ],
    "id": 7276016,
    "name:xx": "Toco, Paso del"
  }
}
