{
  "type": "FeatureCollection",
  "features": [
    {
      "geometry": {
        "type": "Point",
        "coordinates": [
          -81.9333,
          35.0667
        ]
      },
      "type": "Feature",
      "properties": {
        "hierarchy": [
          "tgn:2224580",
          "tgn:1000001",
          "tgn:7012149",
          "tgn:2001766",
          "tgn:7007712",
          "tgn:7029392"
        ],
        "placetype": [
          "aat:300008706"
        ],
        "id": 2224580,
        "name:xx": "Casey Creek"
      }
    },
    {
      "geometry": {
        "type": "Point",
        "coordinates": [
          -117.4167,
          46.6
        ]
      },
      "type": "Feature",
      "properties": {
        "hierarchy": [
          "tgn:2224581",
          "tgn:1000001",
          "tgn:2002245",
          "tgn:7012149",
          "tgn:7007920",
          "tgn:7029392"
        ],
        "placetype": [
          "aat:300008706"
        ],
        "id": 2224581,
        "name:xx": "Casey Creek"
      }
    },
    {
      "geometry": {
        "type": "Point",
        "coordinates": [
          -81.7,
          37.8667
        ]
      },
      "type": "Feature",
      "properties": {
        "hierarchy": [
          "tgn:2224582",
          "tgn:1000001",
          "tgn:2002255",
          "tgn:7012149",
          "tgn:7013961",
          "tgn:7029392"
        ],
        "placetype": [
          "aat:300008706"
        ],
        "id": 2224582,
        "name:xx": "Casey Creek"
      }
    },
    {
      "geometry": {
        "type": "Point",
        "coordinates": [
          -90.9,
          45.85
        ]
      },
      "type": "Feature",
      "properties": {
        "hierarchy": [
          "tgn:2224583",
          "tgn:1000001",
          "tgn:7012149",
          "tgn:2002353",
          "tgn:7007922",
          "tgn:7029392"
        ],
        "placetype": [
          "aat:300008706"
        ],
        "id": 2224583,
        "name:xx": "Casey Creek"
      }
    },
    {
      "geometry": {
        "type": "Point",
        "coordinates": [
          -91.9833,
          45.95
        ]
      },
      "type": "Feature",
      "properties": {
        "hierarchy": [
          "tgn:2224584",
          "tgn:1000001",
          "tgn:7012149",
          "tgn:2002360",
          "tgn:7007922",
          "tgn:7029392"
        ],
        "placetype": [
          "aat:300008706"
        ],
        "id": 2224584,
        "name:xx": "Casey Creek"
      }
    },
    {
      "geometry": {
        "type": "Point",
        "coordinates": [
          -91.6167,
          46.5833
        ]
      },
      "type": "Feature",
      "properties": {
        "hierarchy": [
          "tgn:2224585",
          "tgn:1000001",
          "tgn:2002318",
          "tgn:7012149",
          "tgn:7007922",
          "tgn:7029392"
        ],
        "placetype": [
          "aat:300008706"
        ],
        "id": 2224585,
        "name:xx": "Casey Creek"
      }
    },
    {
      "geometry": {
        "type": "Point",
        "coordinates": [
          -88.9,
          38.2167
        ]
      },
      "type": "Feature",
      "properties": {
        "hierarchy": [
          "tgn:2224586",
          "tgn:1000001",
          "tgn:7012149",
          "tgn:1002514",
          "tgn:7007251",
          "tgn:7029392"
        ],
        "placetype": [
          "aat:300006075"
        ],
        "id": 2224586,
        "name:xx": "Casey Ditch"
      }
    },
    {
      "geometry": {
        "type": "Point",
        "coordinates": [
          -84.1833,
          43.5333
        ]
      },
      "type": "Feature",
      "properties": {
        "hierarchy": [
          "tgn:2224587",
          "tgn:1000001",
          "tgn:7012149",
          "tgn:2000979",
          "tgn:7007520",
          "tgn:7029392"
        ],
        "placetype": [
          "aat:300006075"
        ],
        "id": 2224587,
        "name:xx": "Casey Drain"
      }
    },
    {
      "geometry": {
        "type": "Point",
        "coordinates": [
          -83.0833,
          43.95
        ]
      },
      "type": "Feature",
      "properties": {
        "hierarchy": [
          "tgn:2224588",
          "tgn:1000001",
          "tgn:7012149",
          "tgn:2000964",
          "tgn:7007520",
          "tgn:7029392"
        ],
        "placetype": [
          "aat:300006075"
        ],
        "id": 2224588,
        "name:xx": "Casey Drain"
      }
    },
    {
      "geometry": {
        "type": "Point",
        "coordinates": [
          -100.75,
          44.4833
        ]
      },
      "type": "Feature",
      "properties": {
        "hierarchy": [
          "tgn:2224589",
          "tgn:1000001",
          "tgn:7012149",
          "tgn:2001828",
          "tgn:7007713",
          "tgn:7029392"
        ],
        "placetype": [
          "aat:300008761"
        ],
        "id": 2224589,
        "name:xx": "Casey Draw"
      }
    }
  ]
}
