{
  "geometry": {
    "type": "Point",
    "coordinates": [
      -110.3667,
      53.3667
    ]
  },
  "type": "Feature",
  "properties": {
    "hierarchy": [
      "tgn:1013215",
      "tgn:7005694",
      "tgn:7005685",
      "tgn:1000001",
      "tgn:7029392"
    ],
    "placetype": [
      "aat:300008347"
    ],
    "id": 1013215,
    "name:xx": "Kitscoty"
  }
}
