{
  "geometry": {
    "type": "Point",
    "coordinates": [
      -115.4667,
      39.35
    ]
  },
  "type": "Feature",
  "properties": {
    "hierarchy": [
      "tgn:2210647",
      "tgn:1000001",
      "tgn:7012149",
      "tgn:2001420",
      "tgn:7007526",
      "tgn:7029392"
    ],
    "placetype": [
      "aat:300008798"
    ],
    "id": 2210647,
    "name:xx": "Buster Mountain"
  }
}
