{
  "geometry": {
    "type": "Point",
    "coordinates": [
      -18.1333,
      65.7333
    ]
  },
  "type": "Feature",
  "properties": {
    "hierarchy": [
      "tgn:7006271",
      "tgn:1000003",
      "tgn:1000077",
      "tgn:7029392"
    ],
    "placetype": [
      "aat:300387064",
      "aat:300387173"
    ],
    "id": 7006271,
    "name:xx": "Suður-Múlasýsla"
  }
}
