{
  "type": "FeatureCollection",
  "features": [
    {
      "geometry": {
        "type": "Point",
        "coordinates": [
          4.3,
          52.083333
        ]
      },
      "type": "Feature",
      "properties": {
        "hierarchy": [
          "tgn:7006810",
          "tgn:1000003",
          "tgn:7003632",
          "tgn:7016845",
          "tgn:7029392"
        ],
        "placetype": [
          "aat:300008347",
          "aat:300008389",
          "aat:300387219",
          "aat:300387223"
        ],
        "name:en": "Hague, The",
        "id": 7006810
      }
    },
    {
      "geometry": {
        "type": "Point",
        "coordinates": [
          4.366667,
          52.066667
        ]
      },
      "type": "Feature",
      "properties": {
        "hierarchy": [
          "tgn:7006811",
          "tgn:1000003",
          "tgn:7003632",
          "tgn:7016845",
          "tgn:7029392"
        ],
        "placetype": [
          "aat:300008347"
        ],
        "name:nl": "Voorburg",
        "id": 7006811
      }
    },
    {
      "geometry": {
        "type": "Point",
        "coordinates": [
          4.45,
          52.133333
        ]
      },
      "type": "Feature",
      "properties": {
        "hierarchy": [
          "tgn:7006812",
          "tgn:1000003",
          "tgn:7003632",
          "tgn:7016845",
          "tgn:7029392"
        ],
        "placetype": [
          "aat:300008347"
        ],
        "name:nl": "Voorschoten",
        "id": 7006812
      }
    },
    {
      "geometry": {
        "type": "Point",
        "coordinates": [
          4.416667,
          52.2
        ]
      },
      "type": "Feature",
      "properties": {
        "hierarchy": [
          "tgn:7006814",
          "tgn:1000003",
          "tgn:7003632",
          "tgn:7016845",
          "tgn:7029392"
        ],
        "placetype": [
          "aat:300008347"
        ],
        "name:nl": "Katwijk aan Zee",
        "id": 7006814
      }
    },
    {
      "geometry": {
        "type": "Point",
        "coordinates": [
          14.3,
          40.916667
        ]
      },
      "type": "Feature",
      "properties": {
        "hierarchy": [
          "tgn:7006815",
          "tgn:7003013",
          "tgn:7003005",
          "tgn:1000003",
          "tgn:1000080",
          "tgn:7029392"
        ],
        "placetype": [
          "aat:300008347"
        ],
        "id": 7006815,
        "name:xx": "Afragola"
      }
    },
    {
      "geometry": {
        "type": "Point",
        "coordinates": [
          14.183333,
          40.9
        ]
      },
      "type": "Feature",
      "properties": {
        "hierarchy": [
          "tgn:7006816",
          "tgn:7003013",
          "tgn:7003005",
          "tgn:1000003",
          "tgn:1000080",
          "tgn:7029392"
        ],
        "placetype": [
          "aat:300008347"
        ],
        "id": 7006816,
        "name:xx": "Marano di Napoli"
      }
    },
    {
      "geometry": {
        "type": "Point",
        "coordinates": [
          4.5,
          52.266667
        ]
      },
      "type": "Feature",
      "properties": {
        "hierarchy": [
          "tgn:7006817",
          "tgn:1000003",
          "tgn:7003632",
          "tgn:7016845",
          "tgn:7029392"
        ],
        "placetype": [
          "aat:300008347"
        ],
        "name:nl": "Noordwijkerhout",
        "id": 7006817
      }
    },
    {
      "geometry": {
        "type": "Point",
        "coordinates": [
          4.466667,
          52.183333
        ]
      },
      "type": "Feature",
      "properties": {
        "hierarchy": [
          "tgn:7006818",
          "tgn:1000003",
          "tgn:7003632",
          "tgn:7016845",
          "tgn:7029392"
        ],
        "placetype": [
          "aat:300008347"
        ],
        "name:nl": "Oegstgeest",
        "id": 7006818
      }
    },
    {
      "geometry": {
        "type": "Point",
        "coordinates": [
          14.45,
          40.933333
        ]
      },
      "type": "Feature",
      "properties": {
        "hierarchy": [
          "tgn:7006819",
          "tgn:7003013",
          "tgn:7003005",
          "tgn:1000003",
          "tgn:1000080",
          "tgn:7029392"
        ],
        "placetype": [
          "aat:300008347"
        ],
        "id": 7006819,
        "name:xx": "Marigliano"
      }
    }
  ]
}
