{
  "geometry": {
    "type": "Point",
    "coordinates": [
      -150.8167,
      64.4333
    ]
  },
  "type": "Feature",
  "properties": {
    "hierarchy": [
      "tgn:2762400",
      "tgn:7006450",
      "tgn:1000001",
      "tgn:7012149",
      "tgn:2000089",
      "tgn:7029392"
    ],
    "placetype": [
      "aat:300008680"
    ],
    "id": 2762400,
    "name:xx": "West Twin Lake"
  }
}
