{
  "geometry": {
    "type": "Point",
    "coordinates": [
      -123.7667,
      47.5833
    ]
  },
  "type": "Feature",
  "properties": {
    "hierarchy": [
      "tgn:2326579",
      "tgn:1000001",
      "tgn:7012149",
      "tgn:7007920",
      "tgn:7029392"
    ],
    "placetype": [
      "aat:300008706"
    ],
    "id": 2326579,
    "name:xx": "Finley Creek"
  }
}
