{
  "type": "FeatureCollection",
  "features": [
    {
      "geometry": {
        "type": "Point",
        "coordinates": [
          12.083333,
          48.716667
        ]
      },
      "type": "Feature",
      "properties": {
        "hierarchy": [
          "tgn:7070410",
          "tgn:7003669",
          "tgn:1000003",
          "tgn:7000084",
          "tgn:7029392"
        ],
        "placetype": [
          "aat:300008347"
        ],
        "id": 7070410,
        "name:xx": "Steinbach"
      }
    },
    {
      "geometry": {
        "type": "Point",
        "coordinates": [
          9.416667,
          48.683333
        ]
      },
      "type": "Feature",
      "properties": {
        "hierarchy": [
          "tgn:7070411",
          "tgn:7003692",
          "tgn:1000003",
          "tgn:7000084",
          "tgn:7029392"
        ],
        "placetype": [
          "aat:300008347"
        ],
        "id": 7070411,
        "name:xx": "Steinbach"
      }
    },
    {
      "geometry": {
        "type": "Point",
        "coordinates": [
          11.75,
          48.616667
        ]
      },
      "type": "Feature",
      "properties": {
        "hierarchy": [
          "tgn:7070412",
          "tgn:7003669",
          "tgn:1000003",
          "tgn:7000084",
          "tgn:7029392"
        ],
        "placetype": [
          "aat:300008347"
        ],
        "id": 7070412,
        "name:xx": "Steinbach"
      }
    },
    {
      "geometry": {
        "type": "Point",
        "coordinates": [
          12.183333,
          48.4
        ]
      },
      "type": "Feature",
      "properties": {
        "hierarchy": [
          "tgn:7070413",
          "tgn:7003669",
          "tgn:1000003",
          "tgn:7000084",
          "tgn:7029392"
        ],
        "placetype": [
          "aat:300008347"
        ],
        "id": 7070413,
        "name:xx": "Steinbach"
      }
    },
    {
      "geometry": {
        "type": "Point",
        "coordinates": [
          13.033333,
          48.383333
        ]
      },
      "type": "Feature",
      "properties": {
        "hierarchy": [
          "tgn:7070414",
          "tgn:7003669",
          "tgn:1000003",
          "tgn:7000084",
          "tgn:7029392"
        ],
        "placetype": [
          "aat:300008347"
        ],
        "id": 7070414,
        "name:xx": "Steinbach"
      }
    },
    {
      "geometry": {
        "type": "Point",
        "coordinates": [
          12.766667,
          48.366667
        ]
      },
      "type": "Feature",
      "properties": {
        "hierarchy": [
          "tgn:7070415",
          "tgn:7003669",
          "tgn:1000003",
          "tgn:7000084",
          "tgn:7029392"
        ],
        "placetype": [
          "aat:300008347"
        ],
        "id": 7070415,
        "name:xx": "Steinbach"
      }
    },
    {
      "geometry": {
        "type": "Point",
        "coordinates": [
          7.933333,
          48.316667
        ]
      },
      "type": "Feature",
      "properties": {
        "hierarchy": [
          "tgn:7070416",
          "tgn:7003692",
          "tgn:1000003",
          "tgn:7000084",
          "tgn:7029392"
        ],
        "placetype": [
          "aat:300008347"
        ],
        "id": 7070416,
        "name:xx": "Steinbach"
      }
    },
    {
      "geometry": {
        "type": "Point",
        "coordinates": [
          12.783333,
          48.266667
        ]
      },
      "type": "Feature",
      "properties": {
        "hierarchy": [
          "tgn:7070417",
          "tgn:7003669",
          "tgn:1000003",
          "tgn:7000084",
          "tgn:7029392"
        ],
        "placetype": [
          "aat:300008347"
        ],
        "id": 7070417,
        "name:xx": "Steinbach"
      }
    },
    {
      "geometry": {
        "type": "Point",
        "coordinates": [
          11.05,
          48.183333
        ]
      },
      "type": "Feature",
      "properties": {
        "hierarchy": [
          "tgn:7070418",
          "tgn:7003669",
          "tgn:1000003",
          "tgn:7000084",
          "tgn:7029392"
        ],
        "placetype": [
          "aat:300008347"
        ],
        "id": 7070418,
        "name:xx": "Steinbach"
      }
    },
    {
      "geometry": {
        "type": "Point",
        "coordinates": [
          11.3,
          47.766667
        ]
      },
      "type": "Feature",
      "properties": {
        "hierarchy": [
          "tgn:7070419",
          "tgn:7003669",
          "tgn:1000003",
          "tgn:7000084",
          "tgn:7029392"
        ],
        "placetype": [
          "aat:300008347"
        ],
        "id": 7070419,
        "name:xx": "Steinbach"
      }
    }
  ]
}
