{
  "geometry": {
    "type": "Point",
    "coordinates": [
      89.4333,
      22.7833
    ]
  },
  "type": "Feature",
  "properties": {
    "hierarchy": [
      "tgn:1065688",
      "tgn:1000004",
      "tgn:7000190",
      "tgn:1000105",
      "tgn:7029392"
    ],
    "placetype": [
      "aat:300008347"
    ],
    "id": 1065688,
    "name:xx": "Dumria"
  }
}
