{
  "geometry": {
    "type": "Point",
    "coordinates": [
      -114.5833,
      33.5833
    ]
  },
  "type": "Feature",
  "properties": {
    "hierarchy": [
      "tgn:2273669",
      "tgn:1000001",
      "tgn:7012149",
      "tgn:7007157",
      "tgn:1002828",
      "tgn:7029392"
    ],
    "placetype": [
      "aat:300006075"
    ],
    "id": 2273669,
    "name:xx": "D Canal"
  }
}
