{
  "geometry": {
    "type": "Point",
    "coordinates": [
      -73.81,
      47.891
    ]
  },
  "type": "Feature",
  "properties": {
    "hierarchy": [
      "tgn:7593224",
      "tgn:7005685",
      "tgn:1000001",
      "tgn:7005804",
      "tgn:1015456",
      "tgn:7029392"
    ],
    "placetype": [
      "aat:300008347"
    ],
    "name:fr": "Sanmaur",
    "name:en": "Sanmaur",
    "id": 7593224
  }
}
