{
  "geometry": {
    "type": "Point",
    "coordinates": [
      -70.4167,
      42.0333
    ]
  },
  "type": "Feature",
  "properties": {
    "hierarchy": [
      "tgn:1112763",
      "tgn:1000001",
      "tgn:7012149",
      "tgn:7007517",
      "tgn:7029392"
    ],
    "placetype": [
      "aat:300132316"
    ],
    "id": 1112763,
    "name:xx": "Cape Cod Bay"
  }
}
