{
  "geometry": {
    "type": "Point",
    "coordinates": [
      32.916667,
      24.583333
    ]
  },
  "type": "Feature",
  "properties": {
    "hierarchy": [
      "tgn:7527554",
      "tgn:7001242",
      "tgn:7016833",
      "tgn:7000122",
      "tgn:7029392"
    ],
    "placetype": [
      "aat:300005926"
    ],
    "name:en": "Man훮mat S카d카 Sulaym훮n",
    "id": 7527554
  }
}
