{
  "geometry": {
    "type": "Point",
    "coordinates": [
      -82.5667,
      29.1167
    ]
  },
  "type": "Feature",
  "properties": {
    "hierarchy": [
      "tgn:2720947",
      "tgn:1000001",
      "tgn:7012149",
      "tgn:2000277",
      "tgn:7007240",
      "tgn:7029392"
    ],
    "placetype": [
      "aat:300008347"
    ],
    "id": 2720947,
    "name:xx": "Tidewater"
  }
}
