{
  "geometry": {
    "type": "Point",
    "coordinates": [
      -97.95,
      27.7667
    ]
  },
  "type": "Feature",
  "properties": {
    "hierarchy": [
      "tgn:2163783",
      "tgn:1000001",
      "tgn:7012149",
      "tgn:2002013",
      "tgn:7007826",
      "tgn:7029392"
    ],
    "placetype": [
      "aat:300008347"
    ],
    "id": 2163783,
    "name:xx": "Bentonville"
  }
}
