{
  "geometry": {
    "type": "Point",
    "coordinates": [
      -70.75,
      -30.55
    ]
  },
  "type": "Feature",
  "properties": {
    "hierarchy": [
      "tgn:7278375",
      "tgn:1001657",
      "tgn:1000049",
      "tgn:1000002",
      "tgn:7029392"
    ],
    "placetype": [
      "aat:300008699"
    ],
    "id": 7278375,
    "name:xx": "Vallecito, Quebrada"
  }
}
