{
  "geometry": {
    "type": "Point",
    "coordinates": [
      -109.7333,
      51.8333
    ]
  },
  "type": "Feature",
  "properties": {
    "hierarchy": [
      "tgn:1015929",
      "tgn:7005685",
      "tgn:1000001",
      "tgn:7005805",
      "tgn:7029392"
    ],
    "placetype": [
      "aat:300008347"
    ],
    "id": 1015929,
    "name:xx": "Fusilier"
  }
}
