{
  "geometry": {
    "type": "Point",
    "coordinates": [
      85.440515,
      20.57466
    ]
  },
  "type": "Feature",
  "properties": {
    "hierarchy": [
      "tgn:7580014",
      "tgn:1000004",
      "tgn:7000198",
      "tgn:7016694",
      "tgn:7029392"
    ],
    "placetype": [
      "aat:300008347"
    ],
    "name:en": "Ustapāl",
    "id": 7580014
  }
}
