{
  "geometry": {
    "type": "Point",
    "coordinates": [
      -79.25,
      40.0667
    ]
  },
  "type": "Feature",
  "properties": {
    "hierarchy": [
      "tgn:2441973",
      "tgn:1000001",
      "tgn:7012149",
      "tgn:1002904",
      "tgn:7007710",
      "tgn:7029392"
    ],
    "placetype": [
      "aat:300008697"
    ],
    "id": 2441973,
    "name:xx": "Kooser Spring"
  }
}
