{
  "geometry": {
    "type": "Point",
    "coordinates": [
      -93.958333,
      17.7625
    ]
  },
  "type": "Feature",
  "properties": {
    "hierarchy": [
      "tgn:7385769",
      "tgn:1000001",
      "tgn:7005599",
      "tgn:7005560",
      "tgn:7029392"
    ],
    "placetype": [
      "aat:300008699"
    ],
    "id": 7385769,
    "name:es": "Pedregal, Río"
  }
}
