{
  "geometry": {
    "type": "Point",
    "coordinates": [
      75.6444,
      26.943996
    ]
  },
  "type": "Feature",
  "properties": {
    "hierarchy": [
      "tgn:7559928",
      "tgn:1000004",
      "tgn:7000198",
      "tgn:7016788",
      "tgn:7029392"
    ],
    "placetype": [
      "aat:300008347"
    ],
    "name:en": "Bher큰j카w훮li Dh훮ni",
    "id": 7559928
  }
}
