{
  "geometry": {
    "type": "Point",
    "coordinates": [
      -72.6333,
      44.7167
    ]
  },
  "type": "Feature",
  "properties": {
    "hierarchy": [
      "tgn:2575965",
      "tgn:1000001",
      "tgn:2002133",
      "tgn:7012149",
      "tgn:7007828",
      "tgn:7029392"
    ],
    "placetype": [
      "aat:300008699"
    ],
    "id": 2575965,
    "name:xx": "Perkins Brook"
  }
}
