{
  "type": "FeatureCollection",
  "features": [
    {
      "geometry": {
        "type": "Point",
        "coordinates": [
          -123.15,
          48.6
        ]
      },
      "type": "Feature",
      "properties": {
        "hierarchy": [
          "tgn:2572970",
          "tgn:1000001",
          "tgn:7012149",
          "tgn:1002862",
          "tgn:7007920",
          "tgn:7029392"
        ],
        "placetype": [
          "aat:300008791"
        ],
        "id": 2572970,
        "name:xx": "Pearl Island"
      }
    },
    {
      "geometry": {
        "type": "Point",
        "coordinates": [
          -120.25,
          38.8833
        ]
      },
      "type": "Feature",
      "properties": {
        "hierarchy": [
          "tgn:2572971",
          "tgn:1000001",
          "tgn:7012149",
          "tgn:1002350",
          "tgn:7007157",
          "tgn:7029392"
        ],
        "placetype": [
          "aat:300008680"
        ],
        "id": 2572971,
        "name:xx": "Pearl Lake"
      }
    },
    {
      "geometry": {
        "type": "Point",
        "coordinates": [
          -118.7333,
          37.05
        ]
      },
      "type": "Feature",
      "properties": {
        "hierarchy": [
          "tgn:2572972",
          "tgn:1000001",
          "tgn:7012149",
          "tgn:1002392",
          "tgn:7007157",
          "tgn:7029392"
        ],
        "placetype": [
          "aat:300008680"
        ],
        "id": 2572972,
        "name:xx": "Pearl Lake"
      }
    },
    {
      "geometry": {
        "type": "Point",
        "coordinates": [
          -106.8833,
          40.7667
        ]
      },
      "type": "Feature",
      "properties": {
        "hierarchy": [
          "tgn:2572973",
          "tgn:1000001",
          "tgn:7012149",
          "tgn:7007158",
          "tgn:2000245",
          "tgn:7029392"
        ],
        "placetype": [
          "aat:300006191"
        ],
        "id": 2572973,
        "name:xx": "Pearl Lake"
      }
    },
    {
      "geometry": {
        "type": "Point",
        "coordinates": [
          -82.4833,
          28.1333
        ]
      },
      "type": "Feature",
      "properties": {
        "hierarchy": [
          "tgn:2572974",
          "tgn:1000001",
          "tgn:1002479",
          "tgn:7012149",
          "tgn:7007240",
          "tgn:7029392"
        ],
        "placetype": [
          "aat:300008680"
        ],
        "id": 2572974,
        "name:xx": "Pearl Lake"
      }
    },
    {
      "geometry": {
        "type": "Point",
        "coordinates": [
          -81.1833,
          28.1833
        ]
      },
      "type": "Feature",
      "properties": {
        "hierarchy": [
          "tgn:2572975",
          "tgn:1000001",
          "tgn:7012149",
          "tgn:1002756",
          "tgn:7007240",
          "tgn:7029392"
        ],
        "placetype": [
          "aat:300008680"
        ],
        "id": 2572975,
        "name:xx": "Pearl Lake"
      }
    },
    {
      "geometry": {
        "type": "Point",
        "coordinates": [
          -81.3333,
          28.65
        ]
      },
      "type": "Feature",
      "properties": {
        "hierarchy": [
          "tgn:2572976",
          "tgn:1000001",
          "tgn:7012149",
          "tgn:1002881",
          "tgn:7007240",
          "tgn:7029392"
        ],
        "placetype": [
          "aat:300008680"
        ],
        "id": 2572976,
        "name:xx": "Pearl Lake"
      }
    },
    {
      "geometry": {
        "type": "Point",
        "coordinates": [
          -81.2167,
          28.9833
        ]
      },
      "type": "Feature",
      "properties": {
        "hierarchy": [
          "tgn:2572977",
          "tgn:1000001",
          "tgn:7012149",
          "tgn:1002977",
          "tgn:7007240",
          "tgn:7029392"
        ],
        "placetype": [
          "aat:300008680"
        ],
        "id": 2572977,
        "name:xx": "Pearl Lake"
      }
    },
    {
      "geometry": {
        "type": "Point",
        "coordinates": [
          -84.7833,
          33.3333
        ]
      },
      "type": "Feature",
      "properties": {
        "hierarchy": [
          "tgn:2572978",
          "tgn:1000001",
          "tgn:7012149",
          "tgn:2000329",
          "tgn:7007248",
          "tgn:7029392"
        ],
        "placetype": [
          "aat:300006191"
        ],
        "id": 2572978,
        "name:xx": "Pearl Lake"
      }
    },
    {
      "geometry": {
        "type": "Point",
        "coordinates": [
          -115.9667,
          45.0667
        ]
      },
      "type": "Feature",
      "properties": {
        "hierarchy": [
          "tgn:2572979",
          "tgn:1000001",
          "tgn:7012149",
          "tgn:2000494",
          "tgn:7007250",
          "tgn:7029392"
        ],
        "placetype": [
          "aat:300008680"
        ],
        "id": 2572979,
        "name:xx": "Pearl Lake"
      }
    }
  ]
}
