{
  "geometry": {
    "type": "Point",
    "coordinates": [
      76.999,
      21.347
    ]
  },
  "type": "Feature",
  "properties": {
    "hierarchy": [
      "tgn:1110467",
      "tgn:1000004",
      "tgn:7000198",
      "tgn:1001895",
      "tgn:7029392"
    ],
    "placetype": [
      "aat:300008777"
    ],
    "name:en": "Gawīlgarh Hills",
    "id": 1110467
  }
}
