{
  "geometry": {
    "type": "Point",
    "coordinates": [
      -70.9333,
      43.3333
    ]
  },
  "type": "Feature",
  "properties": {
    "hierarchy": [
      "tgn:2045633",
      "tgn:1000001",
      "tgn:7012149",
      "tgn:2000933",
      "tgn:7007515",
      "tgn:7029392"
    ],
    "placetype": [
      "aat:300008347"
    ],
    "id": 2045633,
    "name:xx": "South Lebanon"
  }
}
