{
  "type": "FeatureCollection",
  "features": [
    {
      "geometry": {
        "type": "Point",
        "coordinates": [
          -118.0333,
          45.4833
        ]
      },
      "type": "Feature",
      "properties": {
        "hierarchy": [
          "tgn:2774070",
          "tgn:1000001",
          "tgn:7012149",
          "tgn:2001721",
          "tgn:7007708",
          "tgn:7029392"
        ],
        "placetype": [
          "aat:300008706"
        ],
        "id": 2774070,
        "name:xx": "Willow Creek"
      }
    },
    {
      "geometry": {
        "type": "Point",
        "coordinates": [
          -123.5,
          43.2833
        ]
      },
      "type": "Feature",
      "properties": {
        "hierarchy": [
          "tgn:2774071",
          "tgn:1000001",
          "tgn:7012149",
          "tgn:2001706",
          "tgn:7007708",
          "tgn:7029392"
        ],
        "placetype": [
          "aat:300008706"
        ],
        "id": 2774071,
        "name:xx": "Willow Creek"
      }
    },
    {
      "geometry": {
        "type": "Point",
        "coordinates": [
          -75.7833,
          40.4167
        ]
      },
      "type": "Feature",
      "properties": {
        "hierarchy": [
          "tgn:2774072",
          "tgn:1000001",
          "tgn:7013387",
          "tgn:7012149",
          "tgn:7007710",
          "tgn:7029392"
        ],
        "placetype": [
          "aat:300008706"
        ],
        "id": 2774072,
        "name:xx": "Willow Creek"
      }
    },
    {
      "geometry": {
        "type": "Point",
        "coordinates": [
          -78.7667,
          41.9667
        ]
      },
      "type": "Feature",
      "properties": {
        "hierarchy": [
          "tgn:2774073",
          "tgn:1000001",
          "tgn:7012149",
          "tgn:7007710",
          "tgn:7029392"
        ],
        "placetype": [
          "aat:300008706"
        ],
        "id": 2774073,
        "name:xx": "Willow Creek"
      }
    },
    {
      "geometry": {
        "type": "Point",
        "coordinates": [
          -79.7,
          34.1333
        ]
      },
      "type": "Feature",
      "properties": {
        "hierarchy": [
          "tgn:2774074",
          "tgn:1000001",
          "tgn:2001745",
          "tgn:7012149",
          "tgn:7007712",
          "tgn:7029392"
        ],
        "placetype": [
          "aat:300008706"
        ],
        "id": 2774074,
        "name:xx": "Willow Creek"
      }
    },
    {
      "geometry": {
        "type": "Point",
        "coordinates": [
          -103.4,
          43.25
        ]
      },
      "type": "Feature",
      "properties": {
        "hierarchy": [
          "tgn:2774075",
          "tgn:1000001",
          "tgn:2001793",
          "tgn:7012149",
          "tgn:7007713",
          "tgn:7029392"
        ],
        "placetype": [
          "aat:300008706"
        ],
        "id": 2774075,
        "name:xx": "Willow Creek"
      }
    },
    {
      "geometry": {
        "type": "Point",
        "coordinates": [
          -102.8667,
          43.35
        ]
      },
      "type": "Feature",
      "properties": {
        "hierarchy": [
          "tgn:2774076",
          "tgn:1000001",
          "tgn:7012149",
          "tgn:2001826",
          "tgn:7007713",
          "tgn:7029392"
        ],
        "placetype": [
          "aat:300008706"
        ],
        "id": 2774076,
        "name:xx": "Willow Creek"
      }
    },
    {
      "geometry": {
        "type": "Point",
        "coordinates": [
          -103.6,
          43.8167
        ]
      },
      "type": "Feature",
      "properties": {
        "hierarchy": [
          "tgn:2774077",
          "tgn:1000001",
          "tgn:2001786",
          "tgn:7012149",
          "tgn:7007713",
          "tgn:7029392"
        ],
        "placetype": [
          "aat:300008706"
        ],
        "id": 2774077,
        "name:xx": "Willow Creek"
      }
    },
    {
      "geometry": {
        "type": "Point",
        "coordinates": [
          -100.1833,
          43.25
        ]
      },
      "type": "Feature",
      "properties": {
        "hierarchy": [
          "tgn:2774078",
          "tgn:1000001",
          "tgn:7012149",
          "tgn:2001831",
          "tgn:7007713",
          "tgn:7029392"
        ],
        "placetype": [
          "aat:300008706"
        ],
        "id": 2774078,
        "name:xx": "Willow Creek"
      }
    },
    {
      "geometry": {
        "type": "Point",
        "coordinates": [
          -98.9667,
          45.8
        ]
      },
      "type": "Feature",
      "properties": {
        "hierarchy": [
          "tgn:2774079",
          "tgn:1000001",
          "tgn:7012149",
          "tgn:7007713",
          "tgn:7029392"
        ],
        "placetype": [
          "aat:300008706"
        ],
        "id": 2774079,
        "name:xx": "Willow Creek"
      }
    }
  ]
}
