{
  "geometry": {
    "type": "Point",
    "coordinates": [
      -82.5667,
      37.15
    ]
  },
  "type": "Feature",
  "properties": {
    "hierarchy": [
      "tgn:2156323",
      "tgn:1000001",
      "tgn:7012149",
      "tgn:7007919",
      "tgn:7029392"
    ],
    "placetype": [
      "aat:300008706"
    ],
    "id": 2156323,
    "name:xx": "Bearpen Creek"
  }
}
