{
  "geometry": {
    "type": "Point",
    "coordinates": [
      -94.3833,
      32.2833
    ]
  },
  "type": "Feature",
  "properties": {
    "hierarchy": [
      "tgn:2287675",
      "tgn:1000001",
      "tgn:7012149",
      "tgn:1002769",
      "tgn:7007826",
      "tgn:7029392"
    ],
    "placetype": [
      "aat:300008706"
    ],
    "id": 2287675,
    "name:xx": "Dillard Creek"
  }
}
