{
  "geometry": {
    "type": "Point",
    "coordinates": [
      79.342514,
      26.328012
    ]
  },
  "type": "Feature",
  "properties": {
    "hierarchy": [
      "tgn:7564772",
      "tgn:1000004",
      "tgn:7000198",
      "tgn:7016722",
      "tgn:7029392"
    ],
    "placetype": [
      "aat:300008347"
    ],
    "name:en": "Abullāhpur Kanār",
    "id": 7564772
  }
}
