{
  "type": "FeatureCollection",
  "features": [
    {
      "geometry": {
        "type": "Point",
        "coordinates": [
          176.633333,
          -39.633333
        ]
      },
      "type": "Feature",
      "properties": {
        "hierarchy": [
          "tgn:7517760",
          "tgn:7016670",
          "tgn:1008380",
          "tgn:1000226",
          "tgn:1000006",
          "tgn:7029392"
        ],
        "placetype": [
          "aat:300008699"
        ],
        "name:en": "Kikowhero Stream",
        "id": 7517760
      }
    },
    {
      "geometry": {
        "type": "Point",
        "coordinates": [
          175.466667,
          -36.733333
        ]
      },
      "type": "Feature",
      "properties": {
        "hierarchy": [
          "tgn:7517761",
          "tgn:7000508",
          "tgn:1008380",
          "tgn:1000226",
          "tgn:1000006",
          "tgn:7029392"
        ],
        "placetype": [
          "aat:300132316"
        ],
        "name:en": "Kikowhakarere Bay",
        "id": 7517761
      }
    },
    {
      "geometry": {
        "type": "Point",
        "coordinates": [
          172.866667,
          -41.65
        ]
      },
      "type": "Feature",
      "properties": {
        "hierarchy": [
          "tgn:7517762",
          "tgn:1009227",
          "tgn:1000226",
          "tgn:7520095",
          "tgn:1000006",
          "tgn:7029392"
        ],
        "placetype": [
          "aat:300008699"
        ],
        "name:en": "Kikiwa",
        "id": 7517762
      }
    },
    {
      "geometry": {
        "type": "Point",
        "coordinates": [
          172.866667,
          -41.65
        ]
      },
      "type": "Feature",
      "properties": {
        "hierarchy": [
          "tgn:7517763",
          "tgn:1009227",
          "tgn:1000226",
          "tgn:7520095",
          "tgn:1000006",
          "tgn:7029392"
        ],
        "placetype": [
          "aat:300008347"
        ],
        "name:en": "Kikiwa",
        "id": 7517763
      }
    },
    {
      "geometry": {
        "type": "Point",
        "coordinates": [
          174.5,
          -36.333333
        ]
      },
      "type": "Feature",
      "properties": {
        "hierarchy": [
          "tgn:7517764",
          "tgn:7000508",
          "tgn:1008380",
          "tgn:1000226",
          "tgn:1000006",
          "tgn:7029392"
        ],
        "placetype": [
          "aat:300008777"
        ],
        "name:en": "Kikitangeo",
        "id": 7517764
      }
    },
    {
      "geometry": {
        "type": "Point",
        "coordinates": [
          173.6,
          -41.533333
        ]
      },
      "type": "Feature",
      "properties": {
        "hierarchy": [
          "tgn:7517766",
          "tgn:1009227",
          "tgn:1000226",
          "tgn:7016729",
          "tgn:1000006",
          "tgn:7029392"
        ],
        "placetype": [
          "aat:300008699"
        ],
        "name:en": "Kiernans Creek",
        "id": 7517766
      }
    },
    {
      "geometry": {
        "type": "Point",
        "coordinates": [
          175.1,
          -39.433333
        ]
      },
      "type": "Feature",
      "properties": {
        "hierarchy": [
          "tgn:7517767",
          "tgn:1008380",
          "tgn:7520093",
          "tgn:1000226",
          "tgn:1000006",
          "tgn:7029392"
        ],
        "placetype": [
          "aat:300008795"
        ],
        "name:en": "Kie Kie",
        "id": 7517767
      }
    },
    {
      "geometry": {
        "type": "Point",
        "coordinates": [
          173.966667,
          -40.766667
        ]
      },
      "type": "Feature",
      "properties": {
        "hierarchy": [
          "tgn:7517768",
          "tgn:1009227",
          "tgn:1000226",
          "tgn:7016729",
          "tgn:1000006",
          "tgn:7029392"
        ],
        "placetype": [
          "aat:300386846"
        ],
        "name:en": "Kidnap Point",
        "id": 7517768
      }
    }
  ]
}
