{
  "geometry": {
    "type": "Point",
    "coordinates": [
      73.7675,
      28.568333
    ]
  },
  "type": "Feature",
  "properties": {
    "hierarchy": [
      "tgn:7568264",
      "tgn:1000004",
      "tgn:7000198",
      "tgn:7016788",
      "tgn:7029392"
    ],
    "placetype": [
      "aat:300167671"
    ],
    "name:en": "Udāna",
    "id": 7568264
  }
}
