{
  "geometry": {
    "type": "Point",
    "coordinates": [
      -73.6833,
      41.65
    ]
  },
  "type": "Feature",
  "properties": {
    "hierarchy": [
      "tgn:2502331",
      "tgn:1000001",
      "tgn:1002347",
      "tgn:7012149",
      "tgn:7007568",
      "tgn:7029392"
    ],
    "placetype": [
      "aat:300006191"
    ],
    "id": 2502331,
    "name:xx": "McKinney Pond"
  }
}
