{
  "geometry": {
    "type": "Point",
    "coordinates": [
      -84.65,
      41.4333
    ]
  },
  "type": "Feature",
  "properties": {
    "hierarchy": [
      "tgn:2457359",
      "tgn:1000001",
      "tgn:7012149",
      "tgn:7007706",
      "tgn:7029392"
    ],
    "placetype": [
      "aat:300008706"
    ],
    "id": 2457359,
    "name:xx": "Little Lick Creek"
  }
}
