{
  "geometry": {
    "type": "Point",
    "coordinates": [
      82.25,
      18.766667
    ]
  },
  "type": "Feature",
  "properties": {
    "hierarchy": [
      "tgn:7557201",
      "tgn:1000004",
      "tgn:7031781",
      "tgn:7000198",
      "tgn:7029392"
    ],
    "placetype": [
      "aat:300008347"
    ],
    "name:en": "Rāmogiri",
    "id": 7557201
  }
}
