{
  "geometry": {
    "type": "Point",
    "coordinates": [
      -97.0833,
      38.3667
    ]
  },
  "type": "Feature",
  "properties": {
    "hierarchy": [
      "tgn:2492761",
      "tgn:1000001",
      "tgn:7012149",
      "tgn:2000717",
      "tgn:7007254",
      "tgn:7029392"
    ],
    "placetype": [
      "aat:300006191"
    ],
    "id": 2492761,
    "name:xx": "Marion Reservoir"
  }
}
