{
  "geometry": {
    "type": "Point",
    "coordinates": [
      -83.8667,
      34.9167
    ]
  },
  "type": "Feature",
  "properties": {
    "hierarchy": [
      "tgn:2726940",
      "tgn:1000001",
      "tgn:7012149",
      "tgn:2000435",
      "tgn:7007248",
      "tgn:7029392"
    ],
    "placetype": [
      "aat:300008347"
    ],
    "id": 2726940,
    "name:xx": "Townsend Mill"
  }
}
