{
  "geometry": {
    "type": "Point",
    "coordinates": [
      5.55,
      51.05
    ]
  },
  "type": "Feature",
  "properties": {
    "hierarchy": [
      "tgn:7238318",
      "tgn:7003461",
      "tgn:1000003",
      "tgn:1000063",
      "tgn:7018236",
      "tgn:7029392"
    ],
    "placetype": [
      "aat:300008688"
    ],
    "id": 7238318,
    "name:xx": "Het Turfven"
  }
}
