{
  "geometry": {
    "type": "Point",
    "coordinates": [
      -111.1333,
      35.6833
    ]
  },
  "type": "Feature",
  "properties": {
    "hierarchy": [
      "tgn:2160363",
      "tgn:1000001",
      "tgn:7006451",
      "tgn:2000092",
      "tgn:7012149",
      "tgn:7029392"
    ],
    "placetype": [
      "aat:300006191"
    ],
    "id": 2160363,
    "name:xx": "Beekid Halani Tank"
  }
}
