{
  "geometry": {
    "type": "Point",
    "coordinates": [
      -68.673,
      18.43
    ]
  },
  "type": "Feature",
  "properties": {
    "hierarchy": [
      "tgn:7593426",
      "tgn:7005402",
      "tgn:1000001",
      "tgn:7005388",
      "tgn:7029392"
    ],
    "placetype": [
      "aat:300008347"
    ],
    "id": 7593426,
    "name:xx": "San Rafael del Yuma"
  }
}
