{
  "type": "FeatureCollection",
  "features": [
    {
      "geometry": {
        "type": "Point",
        "coordinates": [
          -74.6167,
          40.5
        ]
      },
      "type": "Feature",
      "properties": {
        "hierarchy": [
          "tgn:2373550",
          "tgn:1000001",
          "tgn:1002903",
          "tgn:7012149",
          "tgn:7007565",
          "tgn:7029392"
        ],
        "placetype": [
          "aat:300008347"
        ],
        "id": 2373550,
        "name:xx": "Hamilton"
      }
    },
    {
      "geometry": {
        "type": "Point",
        "coordinates": [
          -119.3,
          44.7333
        ]
      },
      "type": "Feature",
      "properties": {
        "hierarchy": [
          "tgn:2373552",
          "tgn:1000001",
          "tgn:7012149",
          "tgn:2001708",
          "tgn:7007708",
          "tgn:7029392"
        ],
        "placetype": [
          "aat:300008347"
        ],
        "id": 2373552,
        "name:xx": "Hamilton"
      }
    },
    {
      "geometry": {
        "type": "Point",
        "coordinates": [
          -82.25,
          36.4833
        ]
      },
      "type": "Feature",
      "properties": {
        "hierarchy": [
          "tgn:2373553",
          "tgn:1000001",
          "tgn:7012149",
          "tgn:2001918",
          "tgn:7007825",
          "tgn:7029392"
        ],
        "placetype": [
          "aat:300008347"
        ],
        "id": 2373553,
        "name:xx": "Hamilton"
      }
    },
    {
      "geometry": {
        "type": "Point",
        "coordinates": [
          -98.9333,
          29.5667
        ]
      },
      "type": "Feature",
      "properties": {
        "hierarchy": [
          "tgn:2373554",
          "tgn:1000001",
          "tgn:2001938",
          "tgn:7012149",
          "tgn:7007826",
          "tgn:7029392"
        ],
        "placetype": [
          "aat:300132316"
        ],
        "id": 2373554,
        "name:xx": "Hamilton"
      }
    },
    {
      "geometry": {
        "type": "Point",
        "coordinates": [
          -77.6,
          37.0167
        ]
      },
      "type": "Feature",
      "properties": {
        "hierarchy": [
          "tgn:2373555",
          "tgn:1000001",
          "tgn:7012149",
          "tgn:1002336",
          "tgn:7007919",
          "tgn:7029392"
        ],
        "placetype": [
          "aat:300008347"
        ],
        "id": 2373555,
        "name:xx": "Hamilton"
      }
    },
    {
      "geometry": {
        "type": "Point",
        "coordinates": [
          -78.1167,
          37.65
        ]
      },
      "type": "Feature",
      "properties": {
        "hierarchy": [
          "tgn:2373556",
          "tgn:1000001",
          "tgn:7012149",
          "tgn:2002156",
          "tgn:7007919",
          "tgn:7029392"
        ],
        "placetype": [
          "aat:300008347"
        ],
        "id": 2373556,
        "name:xx": "Hamilton"
      }
    },
    {
      "geometry": {
        "type": "Point",
        "coordinates": [
          -81.25,
          38.0167
        ]
      },
      "type": "Feature",
      "properties": {
        "hierarchy": [
          "tgn:2373557",
          "tgn:1000001",
          "tgn:2002261",
          "tgn:7012149",
          "tgn:7013961",
          "tgn:7029392"
        ],
        "placetype": [
          "aat:300008347"
        ],
        "id": 2373557,
        "name:xx": "Hamilton"
      }
    },
    {
      "geometry": {
        "type": "Point",
        "coordinates": [
          -87.9667,
          43.2833
        ]
      },
      "type": "Feature",
      "properties": {
        "hierarchy": [
          "tgn:2373558",
          "tgn:1000001",
          "tgn:7012149",
          "tgn:1002766",
          "tgn:7007922",
          "tgn:7029392"
        ],
        "placetype": [
          "aat:300008347"
        ],
        "id": 2373558,
        "name:xx": "Hamilton"
      }
    },
    {
      "geometry": {
        "type": "Point",
        "coordinates": [
          -147.6667,
          64.8333
        ]
      },
      "type": "Feature",
      "properties": {
        "hierarchy": [
          "tgn:2373559",
          "tgn:7006450",
          "tgn:1000001",
          "tgn:7019674",
          "tgn:7012149",
          "tgn:7029392"
        ],
        "placetype": [
          "aat:300008347"
        ],
        "id": 2373559,
        "name:xx": "Hamilton Acres"
      }
    }
  ]
}
