{
  "geometry": {
    "type": "Point",
    "coordinates": [
      -110.8667,
      37.0333
    ]
  },
  "type": "Feature",
  "properties": {
    "hierarchy": [
      "tgn:2399877",
      "tgn:1000001",
      "tgn:7012149",
      "tgn:7029392"
    ],
    "placetype": [
      "aat:300008761"
    ],
    "id": 2399877,
    "name:xx": "Horse Canyon"
  }
}
