{
  "geometry": {
    "type": "Point",
    "coordinates": [
      -90.6333,
      36.6667
    ]
  },
  "type": "Feature",
  "properties": {
    "hierarchy": [
      "tgn:2212304",
      "tgn:1000001",
      "tgn:7012149",
      "tgn:2001237",
      "tgn:7007523",
      "tgn:7029392"
    ],
    "placetype": [
      "aat:300008699"
    ],
    "id": 2212304,
    "name:xx": "Buzzard Run"
  }
}
