{
  "geometry": {
    "type": "Point",
    "coordinates": [
      12.75,
      54.15
    ]
  },
  "type": "Feature",
  "properties": {
    "hierarchy": [
      "tgn:7163212",
      "tgn:1000003",
      "tgn:7000094",
      "tgn:7000084",
      "tgn:7029392"
    ],
    "placetype": [
      "aat:300008347"
    ],
    "id": 7163212,
    "name:xx": "Hugoldsdorf"
  }
}
