{
  "geometry": {
    "type": "Point",
    "coordinates": [
      -113.0667,
      39.4833
    ]
  },
  "type": "Feature",
  "properties": {
    "hierarchy": [
      "tgn:2521696",
      "tgn:1000001",
      "tgn:7012149",
      "tgn:2002114",
      "tgn:7007827",
      "tgn:7029392"
    ],
    "placetype": [
      "aat:300008761"
    ],
    "id": 2521696,
    "name:xx": "Monument Canyon"
  }
}
