{
  "geometry": {
    "type": "Point",
    "coordinates": [
      -112.3333,
      44.0167
    ]
  },
  "type": "Feature",
  "properties": {
    "hierarchy": [
      "tgn:2624367",
      "tgn:1000001",
      "tgn:7012149",
      "tgn:2000477",
      "tgn:7007250",
      "tgn:7029392"
    ],
    "placetype": [
      "aat:300008680"
    ],
    "id": 2624367,
    "name:xx": "Rock Lakes"
  }
}
