{
  "geometry": {
    "type": "Point",
    "coordinates": [
      145.6667,
      -35.9333
    ]
  },
  "type": "Feature",
  "properties": {
    "hierarchy": [
      "tgn:1096577",
      "tgn:7000490",
      "tgn:1000006",
      "tgn:7006238",
      "tgn:7029392"
    ],
    "placetype": [
      "aat:300008347"
    ],
    "id": 1096577,
    "name:xx": "Cobram"
  }
}
