{
  "geometry": {
    "type": "Point",
    "coordinates": [
      -94.3333,
      36.3333
    ]
  },
  "type": "Feature",
  "properties": {
    "hierarchy": [
      "tgn:2000108",
      "tgn:1000001",
      "tgn:7016172",
      "tgn:7012149",
      "tgn:7029392"
    ],
    "placetype": [
      "aat:300387145",
      "aat:300000771"
    ],
    "id": 2000108,
    "name:xx": "Benton"
  }
}
