{
  "geometry": {
    "type": "Point",
    "coordinates": [
      -70.5167,
      41.3667
    ]
  },
  "type": "Feature",
  "properties": {
    "hierarchy": [
      "tgn:2513326",
      "tgn:7014010",
      "tgn:1000001",
      "tgn:1002344",
      "tgn:7012149",
      "tgn:7007517",
      "tgn:7029392"
    ],
    "placetype": [
      "aat:300008798"
    ],
    "id": 2513326,
    "name:xx": "Mill Hill"
  }
}
