{
  "geometry": {
    "type": "Point",
    "coordinates": [
      -9.1667,
      27.4667
    ]
  },
  "type": "Feature",
  "properties": {
    "hierarchy": [
      "tgn:1094048",
      "tgn:7001242",
      "tgn:1000179",
      "tgn:1000200",
      "tgn:7029392"
    ],
    "placetype": [
      "aat:300008347"
    ],
    "id": 1094048,
    "name:xx": "Al Mahbas"
  }
}
