{
  "geometry": {
    "type": "Point",
    "coordinates": [
      -73.7333,
      3.8667
    ]
  },
  "type": "Feature",
  "properties": {
    "hierarchy": [
      "tgn:1023831",
      "tgn:1000050",
      "tgn:1000694",
      "tgn:1000002",
      "tgn:7029392"
    ],
    "placetype": [
      "aat:300008347"
    ],
    "id": 1023831,
    "name:xx": "Guamal"
  }
}
