{
  "geometry": {
    "type": "Point",
    "coordinates": [
      -123.1833,
      45.8167
    ]
  },
  "type": "Feature",
  "properties": {
    "hierarchy": [
      "tgn:2573368",
      "tgn:1000001",
      "tgn:1002293",
      "tgn:7012149",
      "tgn:7007708",
      "tgn:7029392"
    ],
    "placetype": [
      "aat:300008347"
    ],
    "id": 2573368,
    "name:xx": "Pebble"
  }
}
