{
  "geometry": {
    "type": "Point",
    "coordinates": [
      -95.5833,
      31.8833
    ]
  },
  "type": "Feature",
  "properties": {
    "hierarchy": [
      "tgn:2408004",
      "tgn:1002148",
      "tgn:1000001",
      "tgn:7012149",
      "tgn:7007826",
      "tgn:7029392"
    ],
    "placetype": [
      "aat:300008706"
    ],
    "id": 2408004,
    "name:xx": "Hurricane Creek"
  }
}
