{
  "geometry": {
    "type": "Point",
    "coordinates": [
      -79.2167,
      41.15
    ]
  },
  "type": "Feature",
  "properties": {
    "hierarchy": [
      "tgn:2633394",
      "tgn:1000001",
      "tgn:7012149",
      "tgn:7007710",
      "tgn:7029392"
    ],
    "placetype": [
      "aat:300008699"
    ],
    "id": 2633394,
    "name:xx": "Runaway Run"
  }
}
