{
  "geometry": {
    "type": "Point",
    "coordinates": [
      -123.6833,
      41.8667
    ]
  },
  "type": "Feature",
  "properties": {
    "hierarchy": [
      "tgn:2665903",
      "tgn:1000001",
      "tgn:7012149",
      "tgn:2000180",
      "tgn:7007157",
      "tgn:7029392"
    ],
    "placetype": [
      "aat:300008699"
    ],
    "id": 2665903,
    "name:xx": "Siskiyou Fork"
  }
}
