{
  "geometry": {
    "type": "Point",
    "coordinates": [
      -101.55,
      19.65
    ]
  },
  "type": "Feature",
  "properties": {
    "hierarchy": [
      "tgn:7394660",
      "tgn:1000001",
      "tgn:7005590",
      "tgn:7005560",
      "tgn:7029392"
    ],
    "placetype": [
      "aat:300008347"
    ],
    "id": 7394660,
    "name:xx": "San Andrés"
  }
}
