{
  "geometry": {
    "type": "Point",
    "coordinates": [
      -122.4833,
      38.4167
    ]
  },
  "type": "Feature",
  "properties": {
    "hierarchy": [
      "tgn:2145063",
      "tgn:1000001",
      "tgn:7012149",
      "tgn:7007157",
      "tgn:7029392"
    ],
    "placetype": [
      "aat:300008798"
    ],
    "id": 2145063,
    "name:xx": "Bald Mountain"
  }
}
