{
  "geometry": {
    "type": "Point",
    "coordinates": [
      -78.9667,
      39.0167
    ]
  },
  "type": "Feature",
  "properties": {
    "hierarchy": [
      "tgn:2248626",
      "tgn:1000001",
      "tgn:7012149",
      "tgn:2002266",
      "tgn:7013961",
      "tgn:7029392"
    ],
    "placetype": [
      "aat:300008761"
    ],
    "id": 2248626,
    "name:xx": "Cold Spring Hollow"
  }
}
