{
  "geometry": {
    "type": "Point",
    "coordinates": [
      -76.7333,
      37.9667
    ]
  },
  "type": "Feature",
  "properties": {
    "hierarchy": [
      "tgn:2755237",
      "tgn:1000001",
      "tgn:7012149",
      "tgn:7007919",
      "tgn:7029392"
    ],
    "placetype": [
      "aat:300008699"
    ],
    "id": 2755237,
    "name:xx": "Webb Run"
  }
}
