{
  "geometry": {
    "type": "Point",
    "coordinates": [
      -104.1333,
      35.5167
    ]
  },
  "type": "Feature",
  "properties": {
    "hierarchy": [
      "tgn:2731751",
      "tgn:1000001",
      "tgn:7012149",
      "tgn:2001453",
      "tgn:7007566",
      "tgn:7029392"
    ],
    "placetype": [
      "aat:300008706"
    ],
    "id": 2731751,
    "name:xx": "Tulosa Creek"
  }
}
