{
  "geometry": {
    "type": "Point",
    "coordinates": [
      88.498889,
      22.791111
    ]
  },
  "type": "Feature",
  "properties": {
    "hierarchy": [
      "tgn:7586088",
      "tgn:1000004",
      "tgn:7000198",
      "tgn:1001977",
      "tgn:7029392"
    ],
    "placetype": [
      "aat:300008347"
    ],
    "name:en": "Hātdānga",
    "id": 7586088
  }
}
