{
  "geometry": {
    "type": "Point",
    "coordinates": [
      -110.25,
      34.3333
    ]
  },
  "type": "Feature",
  "properties": {
    "hierarchy": [
      "tgn:2608405",
      "tgn:1000001",
      "tgn:7006451",
      "tgn:7012149",
      "tgn:2000099",
      "tgn:7029392"
    ],
    "placetype": [
      "aat:300008761"
    ],
    "id": 2608405,
    "name:xx": "Rattlesnake Draw"
  }
}
