{
  "geometry": {
    "type": "Point",
    "coordinates": [
      -123.7333,
      41.7667
    ]
  },
  "type": "Feature",
  "properties": {
    "hierarchy": [
      "tgn:2314406",
      "tgn:1000001",
      "tgn:7012149",
      "tgn:2000180",
      "tgn:7007157",
      "tgn:7029392"
    ],
    "placetype": [
      "aat:300008680"
    ],
    "id": 2314406,
    "name:xx": "Elk Lake"
  }
}
