{
  "type": "FeatureCollection",
  "features": [
    {
      "geometry": {
        "type": "Point",
        "coordinates": [
          -113.3333,
          48.9
        ]
      },
      "type": "Feature",
      "properties": {
        "hierarchy": [
          "tgn:2355850",
          "tgn:1000001",
          "tgn:7012149",
          "tgn:2001277",
          "tgn:7007524",
          "tgn:7029392"
        ],
        "placetype": [
          "aat:300008680"
        ],
        "id": 2355850,
        "name:xx": "Goose Lake"
      }
    },
    {
      "geometry": {
        "type": "Point",
        "coordinates": [
          -98.55,
          42.1
        ]
      },
      "type": "Feature",
      "properties": {
        "hierarchy": [
          "tgn:2355851",
          "tgn:1000001",
          "tgn:2001360",
          "tgn:7012149",
          "tgn:7007525",
          "tgn:7029392"
        ],
        "placetype": [
          "aat:300008680"
        ],
        "id": 2355851,
        "name:xx": "Goose Lake"
      }
    },
    {
      "geometry": {
        "type": "Point",
        "coordinates": [
          -102.4333,
          41.7667
        ]
      },
      "type": "Feature",
      "properties": {
        "hierarchy": [
          "tgn:2355852",
          "tgn:1000001",
          "tgn:2001350",
          "tgn:7012149",
          "tgn:7007525",
          "tgn:7029392"
        ],
        "placetype": [
          "aat:300008680"
        ],
        "id": 2355852,
        "name:xx": "Goose Lake"
      }
    },
    {
      "geometry": {
        "type": "Point",
        "coordinates": [
          -102.7167,
          41.8333
        ]
      },
      "type": "Feature",
      "properties": {
        "hierarchy": [
          "tgn:2355853",
          "tgn:1000001",
          "tgn:7012149",
          "tgn:2001377",
          "tgn:7007525",
          "tgn:7029392"
        ],
        "placetype": [
          "aat:300008680"
        ],
        "id": 2355853,
        "name:xx": "Goose Lake"
      }
    },
    {
      "geometry": {
        "type": "Point",
        "coordinates": [
          -101.8,
          42.1667
        ]
      },
      "type": "Feature",
      "properties": {
        "hierarchy": [
          "tgn:2355854",
          "tgn:1000001",
          "tgn:2001331",
          "tgn:7012149",
          "tgn:7007525",
          "tgn:7029392"
        ],
        "placetype": [
          "aat:300008680"
        ],
        "id": 2355854,
        "name:xx": "Goose Lake"
      }
    },
    {
      "geometry": {
        "type": "Point",
        "coordinates": [
          -102.1,
          42.4167
        ]
      },
      "type": "Feature",
      "properties": {
        "hierarchy": [
          "tgn:2355855",
          "tgn:1000001",
          "tgn:7012149",
          "tgn:2001396",
          "tgn:7007525",
          "tgn:7029392"
        ],
        "placetype": [
          "aat:300008680"
        ],
        "id": 2355855,
        "name:xx": "Goose Lake"
      }
    },
    {
      "geometry": {
        "type": "Point",
        "coordinates": [
          -99.2833,
          42.45
        ]
      },
      "type": "Feature",
      "properties": {
        "hierarchy": [
          "tgn:2355856",
          "tgn:1000001",
          "tgn:7012149",
          "tgn:2001390",
          "tgn:7007525",
          "tgn:7029392"
        ],
        "placetype": [
          "aat:300008680"
        ],
        "id": 2355856,
        "name:xx": "Goose Lake"
      }
    },
    {
      "geometry": {
        "type": "Point",
        "coordinates": [
          -118.4333,
          39.6167
        ]
      },
      "type": "Feature",
      "properties": {
        "hierarchy": [
          "tgn:2355857",
          "tgn:1000001",
          "tgn:2001409",
          "tgn:7012149",
          "tgn:7007526",
          "tgn:7029392"
        ],
        "placetype": [
          "aat:300006191"
        ],
        "id": 2355857,
        "name:xx": "Goose Lake"
      }
    },
    {
      "geometry": {
        "type": "Point",
        "coordinates": [
          -108.3667,
          33.0167
        ]
      },
      "type": "Feature",
      "properties": {
        "hierarchy": [
          "tgn:2355858",
          "tgn:1000001",
          "tgn:7012149",
          "tgn:2001437",
          "tgn:7007566",
          "tgn:7029392"
        ],
        "placetype": [
          "aat:300008680"
        ],
        "id": 2355858,
        "name:xx": "Goose Lake"
      }
    },
    {
      "geometry": {
        "type": "Point",
        "coordinates": [
          -105.4333,
          36.6333
        ]
      },
      "type": "Feature",
      "properties": {
        "hierarchy": [
          "tgn:2355859",
          "tgn:1000001",
          "tgn:7012149",
          "tgn:2001457",
          "tgn:7007566",
          "tgn:7029392"
        ],
        "placetype": [
          "aat:300008680"
        ],
        "id": 2355859,
        "name:xx": "Goose Lake"
      }
    }
  ]
}
