{
  "geometry": {
    "type": "Point",
    "coordinates": [
      -95.6833,
      30.7333
    ]
  },
  "type": "Feature",
  "properties": {
    "hierarchy": [
      "tgn:2622561",
      "tgn:1000001",
      "tgn:7012149",
      "tgn:1002980",
      "tgn:7007826",
      "tgn:7029392"
    ],
    "placetype": [
      "aat:300008699"
    ],
    "id": 2622561,
    "name:xx": "Robinson Branch"
  }
}
