{
  "geometry": {
    "type": "Point",
    "coordinates": [
      -110.85,
      32.4333
    ]
  },
  "type": "Feature",
  "properties": {
    "hierarchy": [
      "tgn:2221449",
      "tgn:1000001",
      "tgn:7006451",
      "tgn:7012149",
      "tgn:2000100",
      "tgn:7029392"
    ],
    "placetype": [
      "aat:300008697"
    ],
    "id": 2221449,
    "name:xx": "Cargodera Spring"
  }
}
