{
  "type": "FeatureCollection",
  "features": [
    {
      "geometry": {
        "type": "Point",
        "coordinates": [
          31.235049,
          30.036351
        ]
      },
      "type": "Feature",
      "properties": {
        "hierarchy": [
          "tgn:7533250",
          "tgn:7001242",
          "tgn:7016833",
          "tgn:1001091",
          "tgn:7029392"
        ],
        "placetype": [
          "aat:300386996"
        ],
        "id": 7533250,
        "name:xx": "Wizārat at Tarbiyah wa at Ta'līm"
      }
    },
    {
      "geometry": {
        "type": "Point",
        "coordinates": [
          31.235882,
          30.036712
        ]
      },
      "type": "Feature",
      "properties": {
        "hierarchy": [
          "tgn:7533251",
          "tgn:7001242",
          "tgn:7016833",
          "tgn:1001091",
          "tgn:7029392"
        ],
        "placetype": [
          "aat:300386996"
        ],
        "id": 7533251,
        "name:xx": "Wizārat al Baḩth al 'Ilmī"
      }
    },
    {
      "geometry": {
        "type": "Point",
        "coordinates": [
          31.235099,
          30.037029
        ]
      },
      "type": "Feature",
      "properties": {
        "hierarchy": [
          "tgn:7533252",
          "tgn:7001242",
          "tgn:7016833",
          "tgn:1001091",
          "tgn:7029392"
        ],
        "placetype": [
          "aat:300386996"
        ],
        "id": 7533252,
        "name:xx": "Wizārat al Iskān"
      }
    },
    {
      "geometry": {
        "type": "Point",
        "coordinates": [
          31.003218,
          31.090812
        ]
      },
      "type": "Feature",
      "properties": {
        "hierarchy": [
          "tgn:7533253",
          "tgn:7001242",
          "tgn:7016833",
          "tgn:1001335",
          "tgn:7029392"
        ],
        "placetype": [
          "aat:300008347"
        ],
        "name:en": "'Izbat Khamīs",
        "id": 7533253
      }
    },
    {
      "geometry": {
        "type": "Point",
        "coordinates": [
          30.986214,
          31.10319
        ]
      },
      "type": "Feature",
      "properties": {
        "hierarchy": [
          "tgn:7533254",
          "tgn:7001242",
          "tgn:7016833",
          "tgn:1001335",
          "tgn:7029392"
        ],
        "placetype": [
          "aat:300008347"
        ],
        "name:en": "'Izbat 'Uthmān al Mārīyah",
        "id": 7533254
      }
    },
    {
      "geometry": {
        "type": "Point",
        "coordinates": [
          30.986499,
          31.106033
        ]
      },
      "type": "Feature",
      "properties": {
        "hierarchy": [
          "tgn:7533255",
          "tgn:7001242",
          "tgn:7016833",
          "tgn:1001335",
          "tgn:7029392"
        ],
        "placetype": [
          "aat:300008347"
        ],
        "name:en": "'Izbat Muşţafá Darwīsh",
        "id": 7533255
      }
    },
    {
      "geometry": {
        "type": "Point",
        "coordinates": [
          30.965823,
          31.094139
        ]
      },
      "type": "Feature",
      "properties": {
        "hierarchy": [
          "tgn:7533256",
          "tgn:7001242",
          "tgn:7016833",
          "tgn:1001335",
          "tgn:7029392"
        ],
        "placetype": [
          "aat:300008347"
        ],
        "name:en": "'Izbat 'Alī Abū 'Umar",
        "id": 7533256
      }
    },
    {
      "geometry": {
        "type": "Point",
        "coordinates": [
          30.978163,
          31.132797
        ]
      },
      "type": "Feature",
      "properties": {
        "hierarchy": [
          "tgn:7533257",
          "tgn:7001242",
          "tgn:7016833",
          "tgn:1001335",
          "tgn:7029392"
        ],
        "placetype": [
          "aat:300008347"
        ],
        "name:en": "'Izbat al Işlāḩ",
        "id": 7533257
      }
    },
    {
      "geometry": {
        "type": "Point",
        "coordinates": [
          30.982658,
          31.116638
        ]
      },
      "type": "Feature",
      "properties": {
        "hierarchy": [
          "tgn:7533258",
          "tgn:7001242",
          "tgn:7016833",
          "tgn:1001335",
          "tgn:7029392"
        ],
        "placetype": [
          "aat:300008347"
        ],
        "name:en": "'Izbat as Sirū",
        "id": 7533258
      }
    },
    {
      "geometry": {
        "type": "Point",
        "coordinates": [
          30.96654,
          31.108198
        ]
      },
      "type": "Feature",
      "properties": {
        "hierarchy": [
          "tgn:7533259",
          "tgn:7001242",
          "tgn:7016833",
          "tgn:1001335",
          "tgn:7029392"
        ],
        "placetype": [
          "aat:300008347"
        ],
        "name:en": "'Izbat Abū Sa'īd",
        "id": 7533259
      }
    }
  ]
}
