{
  "geometry": {
    "type": "Point",
    "coordinates": [
      -111.7167,
      36.0333
    ]
  },
  "type": "Feature",
  "properties": {
    "hierarchy": [
      "tgn:2473241",
      "tgn:1000001",
      "tgn:7006451",
      "tgn:2000092",
      "tgn:7012149",
      "tgn:7029392"
    ],
    "placetype": [
      "aat:300386845"
    ],
    "id": 2473241,
    "name:xx": "Lower Basin"
  }
}
