{
  "type": "FeatureCollection",
  "features": [
    {
      "geometry": {
        "type": "Point",
        "coordinates": [
          5.15,
          52
        ]
      },
      "type": "Feature",
      "properties": {
        "hierarchy": [
          "tgn:7269490",
          "tgn:1000003",
          "tgn:7003627",
          "tgn:7016845",
          "tgn:7029392"
        ],
        "placetype": [
          "aat:300006163"
        ],
        "name:nl": "Schalkwijk, Polder",
        "id": 7269490
      }
    },
    {
      "geometry": {
        "type": "Point",
        "coordinates": [
          4.666667,
          52.366667
        ]
      },
      "type": "Feature",
      "properties": {
        "hierarchy": [
          "tgn:7269491",
          "tgn:1000003",
          "tgn:7006951",
          "tgn:7016845",
          "tgn:7029392"
        ],
        "placetype": [
          "aat:300008347"
        ],
        "name:nl": "Schalkwijk",
        "id": 7269491
      }
    },
    {
      "geometry": {
        "type": "Point",
        "coordinates": [
          6.2,
          52.266667
        ]
      },
      "type": "Feature",
      "properties": {
        "hierarchy": [
          "tgn:7269493",
          "tgn:1000003",
          "tgn:7003626",
          "tgn:7016845",
          "tgn:7029392"
        ],
        "placetype": [
          "aat:300008347"
        ],
        "name:nl": "Schalkhaar",
        "id": 7269493
      }
    },
    {
      "geometry": {
        "type": "Point",
        "coordinates": [
          5.933333,
          53.166667
        ]
      },
      "type": "Feature",
      "properties": {
        "hierarchy": [
          "tgn:7269494",
          "tgn:7003616",
          "tgn:1000003",
          "tgn:7016845",
          "tgn:7029392"
        ],
        "placetype": [
          "aat:300008678"
        ],
        "name:nl": "Schalkdiep",
        "id": 7269494
      }
    },
    {
      "geometry": {
        "type": "Point",
        "coordinates": [
          4.9,
          51.483333
        ]
      },
      "type": "Feature",
      "properties": {
        "hierarchy": [
          "tgn:7269495",
          "tgn:1000003",
          "tgn:7003624",
          "tgn:7016845",
          "tgn:7029392"
        ],
        "placetype": [
          "aat:300387200"
        ],
        "name:nl": "Schalieven",
        "id": 7269495
      }
    },
    {
      "geometry": {
        "type": "Point",
        "coordinates": [
          5.933333,
          52.7
        ]
      },
      "type": "Feature",
      "properties": {
        "hierarchy": [
          "tgn:7269496",
          "tgn:7003615",
          "tgn:1000003",
          "tgn:7016845",
          "tgn:7029392"
        ],
        "placetype": [
          "aat:300000206"
        ],
        "name:nl": "Schalcohoeve",
        "id": 7269496
      }
    },
    {
      "geometry": {
        "type": "Point",
        "coordinates": [
          6.8,
          52.316667
        ]
      },
      "type": "Feature",
      "properties": {
        "hierarchy": [
          "tgn:7269497",
          "tgn:1000003",
          "tgn:7003626",
          "tgn:7016845",
          "tgn:7029392"
        ],
        "placetype": [
          "aat:300008699"
        ],
        "name:nl": "Schalbeek",
        "id": 7269497
      }
    },
    {
      "geometry": {
        "type": "Point",
        "coordinates": [
          4.183333,
          51.533333
        ]
      },
      "type": "Feature",
      "properties": {
        "hierarchy": [
          "tgn:7269498",
          "tgn:1000003",
          "tgn:7003635",
          "tgn:7016845",
          "tgn:7029392"
        ],
        "placetype": [
          "aat:300006163"
        ],
        "name:nl": "Schakerloopolder",
        "id": 7269498
      }
    },
    {
      "geometry": {
        "type": "Point",
        "coordinates": [
          5.633333,
          51.733333
        ]
      },
      "type": "Feature",
      "properties": {
        "hierarchy": [
          "tgn:7269499",
          "tgn:1000003",
          "tgn:7003624",
          "tgn:7016845",
          "tgn:7029392"
        ],
        "placetype": [
          "aat:300008347"
        ],
        "name:nl": "Schaijkse Hoek",
        "id": 7269499
      }
    }
  ]
}
