{
  "geometry": {
    "type": "Point",
    "coordinates": [
      -2.05,
      48.6333
    ]
  },
  "type": "Feature",
  "properties": {
    "hierarchy": [
      "tgn:1032935",
      "tgn:1000003",
      "tgn:7012216",
      "tgn:1000070",
      "tgn:7029392"
    ],
    "placetype": [
      "aat:300008347"
    ],
    "id": 1032935,
    "name:xx": "Dinard-Saint-Enogat"
  }
}
