{
  "geometry": {
    "type": "Point",
    "coordinates": [
      -65.5833,
      -24.9833
    ]
  },
  "type": "Feature",
  "properties": {
    "hierarchy": [
      "tgn:1019952",
      "tgn:7006477",
      "tgn:1001514",
      "tgn:1000002",
      "tgn:7029392"
    ],
    "placetype": [
      "aat:300008347"
    ],
    "id": 1019952,
    "name:xx": "Rosario de Lerma"
  }
}
