{
  "type": "FeatureCollection",
  "features": [
    {
      "geometry": {
        "type": "Point",
        "coordinates": [
          5.566667,
          49.7
        ]
      },
      "type": "Feature",
      "properties": {
        "hierarchy": [
          "tgn:7259030",
          "tgn:7003465",
          "tgn:1000003",
          "tgn:1000063",
          "tgn:4012014",
          "tgn:7029392"
        ],
        "placetype": [
          "aat:300008347"
        ],
        "id": 7259030,
        "name:xx": "Villers-sur-Semois"
      }
    },
    {
      "geometry": {
        "type": "Point",
        "coordinates": [
          5.116667,
          50.15
        ]
      },
      "type": "Feature",
      "properties": {
        "hierarchy": [
          "tgn:7259032",
          "tgn:7003466",
          "tgn:1000003",
          "tgn:1000063",
          "tgn:4012014",
          "tgn:7029392"
        ],
        "placetype": [
          "aat:300008347"
        ],
        "id": 7259032,
        "name:xx": "Villers-sur-Lesse"
      }
    },
    {
      "geometry": {
        "type": "Point",
        "coordinates": [
          5.547878,
          50.707467
        ]
      },
      "type": "Feature",
      "properties": {
        "hierarchy": [
          "tgn:7259034",
          "tgn:7003460",
          "tgn:1000003",
          "tgn:1000063",
          "tgn:4012014",
          "tgn:7029392"
        ],
        "placetype": [
          "aat:300008347"
        ],
        "id": 7259034,
        "name:xx": "Villers-Saint-Siméon"
      }
    },
    {
      "geometry": {
        "type": "Point",
        "coordinates": [
          4.033333,
          50.433333
        ]
      },
      "type": "Feature",
      "properties": {
        "hierarchy": [
          "tgn:7259036",
          "tgn:7007877",
          "tgn:1000003",
          "tgn:1000063",
          "tgn:4012014",
          "tgn:7029392"
        ],
        "placetype": [
          "aat:300008347"
        ],
        "id": 7259036,
        "name:xx": "Villers-Saint-Ghislain"
      }
    },
    {
      "geometry": {
        "type": "Point",
        "coordinates": [
          5.583333,
          50.366667
        ]
      },
      "type": "Feature",
      "properties": {
        "hierarchy": [
          "tgn:7259038",
          "tgn:7003465",
          "tgn:1000003",
          "tgn:1000063",
          "tgn:4012014",
          "tgn:7029392"
        ],
        "placetype": [
          "aat:300008347"
        ],
        "id": 7259038,
        "name:xx": "Villers-Sainte-Gertrude"
      }
    }
  ]
}
