{
  "geometry": {
    "type": "Point",
    "coordinates": [
      -95.0167,
      29.6333
    ]
  },
  "type": "Feature",
  "properties": {
    "hierarchy": [
      "tgn:2102604",
      "tgn:1000001",
      "tgn:7012149",
      "tgn:1002456",
      "tgn:7007826",
      "tgn:7029392"
    ],
    "placetype": [
      "aat:300008347"
    ],
    "id": 2102604,
    "name:xx": "Bay Oaks"
  }
}
