{
  "geometry": {
    "type": "Point",
    "coordinates": [
      118.85,
      31.05
    ]
  },
  "type": "Feature",
  "properties": {
    "hierarchy": [
      "tgn:1071584",
      "tgn:7002075",
      "tgn:1000004",
      "tgn:1000111",
      "tgn:7029392"
    ],
    "placetype": [
      "aat:300008347"
    ],
    "id": 1071584,
    "name:xx": "Shencun"
  }
}
