{
  "geometry": {
    "type": "Point",
    "coordinates": [
      20.9667,
      41.5167
    ]
  },
  "type": "Feature",
  "properties": {
    "hierarchy": [
      "tgn:1065048",
      "tgn:7015185",
      "tgn:1000003",
      "tgn:7006667",
      "tgn:7029392"
    ],
    "placetype": [
      "aat:300008347"
    ],
    "id": 1065048,
    "name:xx": "Kicevo"
  }
}
