{
  "geometry": {
    "type": "Point",
    "coordinates": [
      -88.0167,
      32.85
    ]
  },
  "type": "Feature",
  "properties": {
    "hierarchy": [
      "tgn:2675610",
      "tgn:7002659",
      "tgn:1000001",
      "tgn:7012149",
      "tgn:2000031",
      "tgn:7029392"
    ],
    "placetype": [
      "aat:300008798"
    ],
    "id": 2675610,
    "name:xx": "Solomon Hill"
  }
}
