{
  "geometry": {
    "type": "Point",
    "coordinates": [
      51.8333,
      56.0167
    ]
  },
  "type": "Feature",
  "properties": {
    "hierarchy": [
      "tgn:1054145",
      "tgn:1000004",
      "tgn:7002435",
      "tgn:7011526",
      "tgn:7029392"
    ],
    "placetype": [
      "aat:300008347"
    ],
    "id": 1054145,
    "name:xx": "Grakhovo"
  }
}
