{
  "geometry": {
    "type": "Point",
    "coordinates": [
      43.2333,
      43.7333
    ]
  },
  "type": "Feature",
  "properties": {
    "hierarchy": [
      "tgn:1059201",
      "tgn:1000004",
      "tgn:7011496",
      "tgn:7002435",
      "tgn:7029392"
    ],
    "placetype": [
      "aat:300008347"
    ],
    "id": 1059201,
    "name:xx": "Sarmakovo"
  }
}
