{
  "type": "FeatureCollection",
  "features": [
    {
      "geometry": {
        "type": "Point",
        "coordinates": [
          8.508,
          40.093
        ]
      },
      "type": "Feature",
      "properties": {
        "hierarchy": [
          "tgn:4002900",
          "tgn:1001730",
          "tgn:1000003",
          "tgn:7003121",
          "tgn:1000080",
          "tgn:7029392"
        ],
        "placetype": [
          "aat:300262964",
          "aat:300008347",
          "aat:300000810",
          "aat:300167671",
          "aat:300020533"
        ],
        "id": 4002900,
        "name:xx": "Cornus"
      }
    },
    {
      "geometry": {
        "type": "Point",
        "coordinates": [
          -1.6,
          51.933333
        ]
      },
      "type": "Feature",
      "properties": {
        "hierarchy": [
          "tgn:4002902",
          "tgn:7002445",
          "tgn:1000003",
          "tgn:7008168",
          "tgn:7008591",
          "tgn:7029392"
        ],
        "placetype": [
          "aat:300008347",
          "aat:300008372"
        ],
        "name:en": "Cornwell",
        "id": 4002902
      }
    },
    {
      "geometry": {
        "type": "Point",
        "coordinates": [
          27.55,
          46.1167
        ]
      },
      "type": "Feature",
      "properties": {
        "hierarchy": [
          "tgn:4002903",
          "tgn:1000003",
          "tgn:1000469",
          "tgn:1000091",
          "tgn:7029392"
        ],
        "placetype": [
          "aat:300008347"
        ],
        "id": 4002903,
        "name:xx": "Coroiu"
      }
    },
    {
      "geometry": {
        "type": "Point",
        "coordinates": [
          -6.933333,
          42.6
        ]
      },
      "type": "Feature",
      "properties": {
        "hierarchy": [
          "tgn:4002905",
          "tgn:7001158",
          "tgn:7002850",
          "tgn:1000003",
          "tgn:1000095",
          "tgn:7029392"
        ],
        "placetype": [
          "aat:300008347"
        ],
        "id": 4002905,
        "name:xx": "Corrales"
      }
    },
    {
      "geometry": {
        "type": "Point",
        "coordinates": [
          4.65,
          50.533333
        ]
      },
      "type": "Feature",
      "properties": {
        "hierarchy": [
          "tgn:4002908",
          "tgn:7003466",
          "tgn:1000003",
          "tgn:1000063",
          "tgn:4012014",
          "tgn:7029392"
        ],
        "placetype": [
          "aat:300008347"
        ],
        "id": 4002908,
        "name:xx": "Corroy-le-Château"
      }
    }
  ]
}
