{
  "geometry": {
    "type": "Point",
    "coordinates": [
      -115.9667,
      49.6667
    ]
  },
  "type": "Feature",
  "properties": {
    "hierarchy": [
      "tgn:1013578",
      "tgn:7005735",
      "tgn:7005685",
      "tgn:1000001",
      "tgn:7029392"
    ],
    "placetype": [
      "aat:300008347"
    ],
    "id": 1013578,
    "name:xx": "Kimberley"
  }
}
