{
  "geometry": {
    "type": "Point",
    "coordinates": [
      -86.6667,
      35.0167
    ]
  },
  "type": "Feature",
  "properties": {
    "hierarchy": [
      "tgn:2146135",
      "tgn:1000001",
      "tgn:7012149",
      "tgn:2001888",
      "tgn:7007825",
      "tgn:7029392"
    ],
    "placetype": [
      "aat:300008761"
    ],
    "id": 2146135,
    "name:xx": "Ballard Hollow"
  }
}
