{
  "type": "FeatureCollection",
  "features": [
    {
      "geometry": {
        "type": "Point",
        "coordinates": [
          -111.883333,
          30.633333
        ]
      },
      "type": "Feature",
      "properties": {
        "hierarchy": [
          "tgn:7391990",
          "tgn:1000001",
          "tgn:1001960",
          "tgn:7005560",
          "tgn:7029392"
        ],
        "placetype": [
          "aat:300008347"
        ],
        "id": 7391990,
        "name:xx": "Rancho El Carrizo"
      }
    },
    {
      "geometry": {
        "type": "Point",
        "coordinates": [
          -108.85,
          30.033333
        ]
      },
      "type": "Feature",
      "properties": {
        "hierarchy": [
          "tgn:7391991",
          "tgn:1000001",
          "tgn:1001960",
          "tgn:7005560",
          "tgn:7029392"
        ],
        "placetype": [
          "aat:300008347"
        ],
        "id": 7391991,
        "name:xx": "Rancho El Carrizo"
      }
    },
    {
      "geometry": {
        "type": "Point",
        "coordinates": [
          -109.466667,
          28.733333
        ]
      },
      "type": "Feature",
      "properties": {
        "hierarchy": [
          "tgn:7391992",
          "tgn:1000001",
          "tgn:1001960",
          "tgn:7005560",
          "tgn:7029392"
        ],
        "placetype": [
          "aat:300008347"
        ],
        "id": 7391992,
        "name:xx": "Rancho El Carrizo"
      }
    },
    {
      "geometry": {
        "type": "Point",
        "coordinates": [
          -105.783333,
          26.533333
        ]
      },
      "type": "Feature",
      "properties": {
        "hierarchy": [
          "tgn:7391993",
          "tgn:7005583",
          "tgn:1000001",
          "tgn:7005560",
          "tgn:7029392"
        ],
        "placetype": [
          "aat:300008347"
        ],
        "id": 7391993,
        "name:xx": "Rancho El Carrizo"
      }
    },
    {
      "geometry": {
        "type": "Point",
        "coordinates": [
          -97.783333,
          24.166667
        ]
      },
      "type": "Feature",
      "properties": {
        "hierarchy": [
          "tgn:7391994",
          "tgn:1000001",
          "tgn:7005597",
          "tgn:7005560",
          "tgn:7029392"
        ],
        "placetype": [
          "aat:300008347"
        ],
        "id": 7391994,
        "name:xx": "Rancho El Carrizo"
      }
    },
    {
      "geometry": {
        "type": "Point",
        "coordinates": [
          -109.3,
          27.383333
        ]
      },
      "type": "Feature",
      "properties": {
        "hierarchy": [
          "tgn:7391995",
          "tgn:1000001",
          "tgn:1001960",
          "tgn:7005560",
          "tgn:7029392"
        ],
        "placetype": [
          "aat:300008347"
        ],
        "id": 7391995,
        "name:xx": "Rancho Viejo"
      }
    },
    {
      "geometry": {
        "type": "Point",
        "coordinates": [
          -107.866667,
          26.95
        ]
      },
      "type": "Feature",
      "properties": {
        "hierarchy": [
          "tgn:7391996",
          "tgn:7005581",
          "tgn:1000001",
          "tgn:7005560",
          "tgn:7029392"
        ],
        "placetype": [
          "aat:300008347"
        ],
        "id": 7391996,
        "name:xx": "Rancho Viejo"
      }
    },
    {
      "geometry": {
        "type": "Point",
        "coordinates": [
          -108.946111,
          26.839444
        ]
      },
      "type": "Feature",
      "properties": {
        "hierarchy": [
          "tgn:7391997",
          "tgn:1000001",
          "tgn:1001960",
          "tgn:7005560",
          "tgn:7029392"
        ],
        "placetype": [
          "aat:300008347"
        ],
        "id": 7391997,
        "name:xx": "Rancho Viejo"
      }
    },
    {
      "geometry": {
        "type": "Point",
        "coordinates": [
          -108.841111,
          26.733056
        ]
      },
      "type": "Feature",
      "properties": {
        "hierarchy": [
          "tgn:7391998",
          "tgn:1000001",
          "tgn:1001960",
          "tgn:7005560",
          "tgn:7029392"
        ],
        "placetype": [
          "aat:300008347"
        ],
        "id": 7391998,
        "name:xx": "Rancho Viejo"
      }
    },
    {
      "geometry": {
        "type": "Point",
        "coordinates": [
          -105.8,
          26.566667
        ]
      },
      "type": "Feature",
      "properties": {
        "hierarchy": [
          "tgn:7391999",
          "tgn:7005583",
          "tgn:1000001",
          "tgn:7005560",
          "tgn:7029392"
        ],
        "placetype": [
          "aat:300008347"
        ],
        "id": 7391999,
        "name:xx": "Rancho Viejo"
      }
    }
  ]
}
