{
  "geometry": {
    "type": "Point",
    "coordinates": [
      -87.65,
      39.0167
    ]
  },
  "type": "Feature",
  "properties": {
    "hierarchy": [
      "tgn:2204221",
      "tgn:1000001",
      "tgn:7012149",
      "tgn:1002678",
      "tgn:7007252",
      "tgn:7029392"
    ],
    "placetype": [
      "aat:300008347"
    ],
    "id": 2204221,
    "name:xx": "Buenavista"
  }
}
