{
  "geometry": {
    "type": "Point",
    "coordinates": [
      -121.9667,
      47.6333
    ]
  },
  "type": "Feature",
  "properties": {
    "hierarchy": [
      "tgn:2132234",
      "tgn:1000001",
      "tgn:7012149",
      "tgn:7018871",
      "tgn:7007920",
      "tgn:7029392"
    ],
    "placetype": [
      "aat:300008680"
    ],
    "id": 2132234,
    "name:xx": "Ames Lake Pothole"
  }
}
