{
  "type": "FeatureCollection",
  "features": [
    {
      "geometry": {
        "type": "Point",
        "coordinates": [
          -122.8333,
          48.6667
        ]
      },
      "type": "Feature",
      "properties": {
        "hierarchy": [
          "tgn:1104300",
          "tgn:1000001",
          "tgn:7012149",
          "tgn:1002862",
          "tgn:7007920",
          "tgn:7029392"
        ],
        "placetype": [
          "aat:300008795"
        ],
        "id": 1104300,
        "name:xx": "Constitution, Mount"
      }
    },
    {
      "geometry": {
        "type": "Point",
        "coordinates": [
          170.166667,
          -43.6
        ]
      },
      "type": "Feature",
      "properties": {
        "hierarchy": [
          "tgn:1104302",
          "tgn:1009227",
          "tgn:7001866",
          "tgn:1000226",
          "tgn:1000006",
          "tgn:7029392"
        ],
        "placetype": [
          "aat:300008795"
        ],
        "name:en": "Cook, Mount",
        "id": 1104302
      }
    },
    {
      "geometry": {
        "type": "Point",
        "coordinates": [
          -103.4667,
          43.7333
        ]
      },
      "type": "Feature",
      "properties": {
        "hierarchy": [
          "tgn:1104304",
          "tgn:1000001",
          "tgn:2001786",
          "tgn:7012149",
          "tgn:7007713",
          "tgn:7029392"
        ],
        "placetype": [
          "aat:300008795"
        ],
        "id": 1104304,
        "name:xx": "Coolidge, Mount"
      }
    },
    {
      "geometry": {
        "type": "Point",
        "coordinates": [
          150.1667,
          -35.0167
        ]
      },
      "type": "Feature",
      "properties": {
        "hierarchy": [
          "tgn:1104305",
          "tgn:7000490",
          "tgn:1000006",
          "tgn:7001828",
          "tgn:7029392"
        ],
        "placetype": [
          "aat:300008795"
        ],
        "id": 1104305,
        "name:xx": "Coolumburra Hill"
      }
    },
    {
      "geometry": {
        "type": "Point",
        "coordinates": [
          -149.8333,
          60.3667
        ]
      },
      "type": "Feature",
      "properties": {
        "hierarchy": [
          "tgn:1104306",
          "tgn:7006450",
          "tgn:1000001",
          "tgn:7012149",
          "tgn:2000082",
          "tgn:7019648",
          "tgn:7029392"
        ],
        "placetype": [
          "aat:300008795"
        ],
        "id": 1104306,
        "name:xx": "Cooper Mountain"
      }
    },
    {
      "geometry": {
        "type": "Point",
        "coordinates": [
          -117.2,
          50.1833
        ]
      },
      "type": "Feature",
      "properties": {
        "hierarchy": [
          "tgn:1104307",
          "tgn:7005735",
          "tgn:7005685",
          "tgn:1000001",
          "tgn:7029392"
        ],
        "placetype": [
          "aat:300008795"
        ],
        "id": 1104307,
        "name:xx": "Cooper, Mount"
      }
    }
  ]
}
