{
  "geometry": {
    "type": "Point",
    "coordinates": [
      33.85,
      48.1167
    ]
  },
  "type": "Feature",
  "properties": {
    "hierarchy": [
      "tgn:1053598",
      "tgn:7011648",
      "tgn:1000003",
      "tgn:7006660",
      "tgn:7029392"
    ],
    "placetype": [
      "aat:300008347"
    ],
    "id": 1053598,
    "name:xx": "Devladovo"
  }
}
