{
  "type": "FeatureCollection",
  "features": [
    {
      "geometry": {
        "type": "Point",
        "coordinates": [
          -102.7833,
          40.9167
        ]
      },
      "type": "Feature",
      "properties": {
        "hierarchy": [
          "tgn:2299070",
          "tgn:1000001",
          "tgn:7012149",
          "tgn:2000229",
          "tgn:7007158",
          "tgn:7029392"
        ],
        "placetype": [
          "aat:300008706"
        ],
        "id": 2299070,
        "name:xx": "Duck Creek"
      }
    },
    {
      "geometry": {
        "type": "Point",
        "coordinates": [
          -75.4833,
          39.3167
        ]
      },
      "type": "Feature",
      "properties": {
        "hierarchy": [
          "tgn:2299071",
          "tgn:1002538",
          "tgn:1000001",
          "tgn:7012149",
          "tgn:7007239",
          "tgn:7029392"
        ],
        "placetype": [
          "aat:300008706"
        ],
        "id": 2299071,
        "name:xx": "Duck Creek"
      }
    },
    {
      "geometry": {
        "type": "Point",
        "coordinates": [
          -81.7667,
          30.1
        ]
      },
      "type": "Feature",
      "properties": {
        "hierarchy": [
          "tgn:2299072",
          "tgn:1000001",
          "tgn:2000261",
          "tgn:7012149",
          "tgn:7007240",
          "tgn:7029392"
        ],
        "placetype": [
          "aat:300008706"
        ],
        "id": 2299072,
        "name:xx": "Duck Creek"
      }
    },
    {
      "geometry": {
        "type": "Point",
        "coordinates": [
          -84.2833,
          32.7
        ]
      },
      "type": "Feature",
      "properties": {
        "hierarchy": [
          "tgn:2299073",
          "tgn:1000001",
          "tgn:7012149",
          "tgn:2000424",
          "tgn:7007248",
          "tgn:7029392"
        ],
        "placetype": [
          "aat:300008706"
        ],
        "id": 2299073,
        "name:xx": "Duck Creek"
      }
    },
    {
      "geometry": {
        "type": "Point",
        "coordinates": [
          -85.3333,
          34.7333
        ]
      },
      "type": "Feature",
      "properties": {
        "hierarchy": [
          "tgn:2299074",
          "tgn:1000001",
          "tgn:7012149",
          "tgn:2000437",
          "tgn:7007248",
          "tgn:7029392"
        ],
        "placetype": [
          "aat:300008706"
        ],
        "id": 2299074,
        "name:xx": "Duck Creek"
      }
    },
    {
      "geometry": {
        "type": "Point",
        "coordinates": [
          -85.3667,
          34.5667
        ]
      },
      "type": "Feature",
      "properties": {
        "hierarchy": [
          "tgn:2299075",
          "tgn:1000001",
          "tgn:2000318",
          "tgn:7012149",
          "tgn:7007248",
          "tgn:7029392"
        ],
        "placetype": [
          "aat:300008347"
        ],
        "id": 2299075,
        "name:xx": "Duck Creek"
      }
    },
    {
      "geometry": {
        "type": "Point",
        "coordinates": [
          -116.9167,
          42.9333
        ]
      },
      "type": "Feature",
      "properties": {
        "hierarchy": [
          "tgn:2299076",
          "tgn:1000001",
          "tgn:7012149",
          "tgn:2000488",
          "tgn:7007250",
          "tgn:7029392"
        ],
        "placetype": [
          "aat:300008706"
        ],
        "id": 2299076,
        "name:xx": "Duck Creek"
      }
    },
    {
      "geometry": {
        "type": "Point",
        "coordinates": [
          -114.6,
          46.3
        ]
      },
      "type": "Feature",
      "properties": {
        "hierarchy": [
          "tgn:2299077",
          "tgn:1000001",
          "tgn:7012149",
          "tgn:2000476",
          "tgn:7007250",
          "tgn:7029392"
        ],
        "placetype": [
          "aat:300008706"
        ],
        "id": 2299077,
        "name:xx": "Duck Creek"
      }
    },
    {
      "geometry": {
        "type": "Point",
        "coordinates": [
          -111.5,
          44.6
        ]
      },
      "type": "Feature",
      "properties": {
        "hierarchy": [
          "tgn:2299078",
          "tgn:1000001",
          "tgn:7012149",
          "tgn:2000473",
          "tgn:7007250",
          "tgn:7029392"
        ],
        "placetype": [
          "aat:300008706"
        ],
        "id": 2299078,
        "name:xx": "Duck Creek"
      }
    },
    {
      "geometry": {
        "type": "Point",
        "coordinates": [
          -113.6833,
          42.4833
        ]
      },
      "type": "Feature",
      "properties": {
        "hierarchy": [
          "tgn:2299079",
          "tgn:1000001",
          "tgn:2000467",
          "tgn:7012149",
          "tgn:7007250",
          "tgn:7029392"
        ],
        "placetype": [
          "aat:300008706"
        ],
        "id": 2299079,
        "name:xx": "Duck Creek"
      }
    }
  ]
}
