{
  "geometry": {
    "type": "Point",
    "coordinates": [
      -102.722222,
      18.325
    ]
  },
  "type": "Feature",
  "properties": {
    "hierarchy": [
      "tgn:7409278",
      "tgn:1000001",
      "tgn:7005590",
      "tgn:7005560",
      "tgn:7029392"
    ],
    "placetype": [
      "aat:300008699"
    ],
    "id": 7409278,
    "name:xx": "Apo, Río"
  }
}
