{
  "geometry": {
    "type": "Point",
    "coordinates": [
      -85.1833,
      40.5333
    ]
  },
  "type": "Feature",
  "properties": {
    "hierarchy": [
      "tgn:2514851",
      "tgn:1000001",
      "tgn:7012149",
      "tgn:1002513",
      "tgn:7007252",
      "tgn:7029392"
    ],
    "placetype": [
      "aat:300006075"
    ],
    "id": 2514851,
    "name:xx": "Miller Pugh Ditch"
  }
}
