{
  "geometry": {
    "type": "Point",
    "coordinates": [
      -86.1167,
      36.0167
    ]
  },
  "type": "Feature",
  "properties": {
    "hierarchy": [
      "tgn:2101658",
      "tgn:1000001",
      "tgn:7012149",
      "tgn:2001931",
      "tgn:7007825",
      "tgn:7029392"
    ],
    "placetype": [
      "aat:300008347"
    ],
    "id": 2101658,
    "name:xx": "Statesville"
  }
}
