{
  "geometry": {
    "type": "Point",
    "coordinates": [
      -99.4333,
      43.0667
    ]
  },
  "type": "Feature",
  "properties": {
    "hierarchy": [
      "tgn:2221720",
      "tgn:1000001",
      "tgn:2001796",
      "tgn:7012149",
      "tgn:7007713",
      "tgn:7029392"
    ],
    "placetype": [
      "aat:300008347"
    ],
    "id": 2221720,
    "name:xx": "Carlock"
  }
}
