{
  "geometry": {
    "type": "Point",
    "coordinates": [
      71.00516,
      27.408057
    ]
  },
  "type": "Feature",
  "properties": {
    "hierarchy": [
      "tgn:7550829",
      "tgn:1000004",
      "tgn:7000198",
      "tgn:7016788",
      "tgn:7029392"
    ],
    "placetype": [
      "aat:300008347"
    ],
    "name:en": "Dīgāh",
    "id": 7550829
  }
}
