{
  "geometry": {
    "type": "Point",
    "coordinates": [
      36.3333,
      41.25
    ]
  },
  "type": "Feature",
  "properties": {
    "hierarchy": [
      "tgn:1001517",
      "tgn:1000004",
      "tgn:7018454",
      "tgn:1000144",
      "tgn:7029392"
    ],
    "placetype": [
      "aat:300387064",
      "aat:300000774"
    ],
    "id": 1001517,
    "name:xx": "Samsun"
  }
}
