{
  "type": "FeatureCollection",
  "features": [
    {
      "geometry": {
        "type": "Point",
        "coordinates": [
          121.283211,
          25.059268
        ]
      },
      "type": "Feature",
      "properties": {
        "hierarchy": [
          "tgn:7491380",
          "tgn:1000004",
          "tgn:7001013",
          "tgn:1000141",
          "tgn:7029392"
        ],
        "placetype": [
          "aat:300008699"
        ],
        "id": 7491380,
        "name:xx": "Dakeng Xi"
      }
    },
    {
      "geometry": {
        "type": "Point",
        "coordinates": [
          120.757129,
          24.199577
        ]
      },
      "type": "Feature",
      "properties": {
        "hierarchy": [
          "tgn:7491381",
          "tgn:1000004",
          "tgn:7001009",
          "tgn:1000141",
          "tgn:7029392"
        ],
        "placetype": [
          "aat:300008699"
        ],
        "id": 7491381,
        "name:xx": "Dakeng Xi"
      }
    },
    {
      "geometry": {
        "type": "Point",
        "coordinates": [
          121.526774,
          25.255081
        ]
      },
      "type": "Feature",
      "properties": {
        "hierarchy": [
          "tgn:7491382",
          "tgn:1000004",
          "tgn:1000454",
          "tgn:1000141",
          "tgn:7029392"
        ],
        "placetype": [
          "aat:300008347"
        ],
        "id": 7491382,
        "name:xx": "Dakeng"
      }
    },
    {
      "geometry": {
        "type": "Point",
        "coordinates": [
          121.433333,
          24.95
        ]
      },
      "type": "Feature",
      "properties": {
        "hierarchy": [
          "tgn:7491384",
          "tgn:1000004",
          "tgn:1000454",
          "tgn:1000141",
          "tgn:7029392"
        ],
        "placetype": [
          "aat:300008347"
        ],
        "id": 7491384,
        "name:xx": "Dakeng"
      }
    },
    {
      "geometry": {
        "type": "Point",
        "coordinates": [
          121.831389,
          24.857222
        ]
      },
      "type": "Feature",
      "properties": {
        "hierarchy": [
          "tgn:7491385",
          "tgn:1000004",
          "tgn:7489179",
          "tgn:1000141",
          "tgn:7029392"
        ],
        "placetype": [
          "aat:300008347"
        ],
        "id": 7491385,
        "name:xx": "Dakeng"
      }
    }
  ]
}
