{
  "geometry": {
    "type": "Point",
    "coordinates": [
      -78.0833,
      34.3667
    ]
  },
  "type": "Feature",
  "properties": {
    "hierarchy": [
      "tgn:2325723",
      "tgn:1000001",
      "tgn:7012149",
      "tgn:2001527",
      "tgn:7007709",
      "tgn:7029392"
    ],
    "placetype": [
      "aat:300132316"
    ],
    "id": 2325723,
    "name:xx": "Field Cove"
  }
}
