{
  "geometry": {
    "type": "Point",
    "coordinates": [
      33.4833,
      52.9167
    ]
  },
  "type": "Feature",
  "properties": {
    "hierarchy": [
      "tgn:1058459",
      "tgn:7011551",
      "tgn:1000004",
      "tgn:7018214",
      "tgn:7002435",
      "tgn:7029392"
    ],
    "placetype": [
      "aat:300008347"
    ],
    "id": 1058459,
    "name:xx": "Pochep"
  }
}
