{
  "geometry": {
    "type": "Point",
    "coordinates": [
      16.75,
      47.55
    ]
  },
  "type": "Feature",
  "properties": {
    "hierarchy": [
      "tgn:1042461",
      "tgn:7006350",
      "tgn:1000003",
      "tgn:7006278",
      "tgn:7029392"
    ],
    "placetype": [
      "aat:300008347"
    ],
    "id": 1042461,
    "name:xx": "Sopronkövesd"
  }
}
