{
  "geometry": {
    "type": "Point",
    "coordinates": [
      71.35,
      32.2833
    ]
  },
  "type": "Feature",
  "properties": {
    "hierarchy": [
      "tgn:1083720",
      "tgn:1000004",
      "tgn:1001490",
      "tgn:1000133",
      "tgn:7029392"
    ],
    "placetype": [
      "aat:300008347"
    ],
    "id": 1083720,
    "name:xx": "Piplān"
  }
}
