{
  "geometry": {
    "type": "Point",
    "coordinates": [
      -105.0167,
      42.45
    ]
  },
  "type": "Feature",
  "properties": {
    "hierarchy": [
      "tgn:2662077",
      "tgn:1000001",
      "tgn:7012149",
      "tgn:2002380",
      "tgn:7007923",
      "tgn:7029392"
    ],
    "placetype": [
      "aat:300008798"
    ],
    "id": 2662077,
    "name:xx": "Sibley Peak"
  }
}
