{
  "geometry": {
    "type": "Point",
    "coordinates": [
      -76.1167,
      41.5667
    ]
  },
  "type": "Feature",
  "properties": {
    "hierarchy": [
      "tgn:2420806",
      "tgn:1000001",
      "tgn:7012149",
      "tgn:1003041",
      "tgn:7007710",
      "tgn:7029392"
    ],
    "placetype": [
      "aat:300006191"
    ],
    "id": 2420806,
    "name:xx": "Jennings Pond"
  }
}
