{
  "geometry": {
    "type": "Point",
    "coordinates": [
      4.65,
      51.8667
    ]
  },
  "type": "Feature",
  "properties": {
    "hierarchy": [
      "tgn:1127857",
      "tgn:1000003",
      "tgn:7016845",
      "tgn:7029392"
    ],
    "placetype": [
      "aat:300008707"
    ],
    "id": 1127857,
    "name:xx": "Noord"
  }
}
