{
  "geometry": {
    "type": "Point",
    "coordinates": [
      -86.7833,
      41.6667
    ]
  },
  "type": "Feature",
  "properties": {
    "hierarchy": [
      "tgn:2188258",
      "tgn:1000001",
      "tgn:7012149",
      "tgn:1002561",
      "tgn:7007252",
      "tgn:7029392"
    ],
    "placetype": [
      "aat:300008706"
    ],
    "id": 2188258,
    "name:xx": "Bosserman Creek"
  }
}
