{
  "type": "FeatureCollection",
  "features": [
    {
      "geometry": {
        "type": "Point",
        "coordinates": [
          12.15,
          51.516667
        ]
      },
      "type": "Feature",
      "properties": {
        "hierarchy": [
          "tgn:7109340",
          "tgn:1000003",
          "tgn:7003687",
          "tgn:7000084",
          "tgn:7029392"
        ],
        "placetype": [
          "aat:300008347"
        ],
        "id": 7109340,
        "name:xx": "Reinsdorf"
      }
    },
    {
      "geometry": {
        "type": "Point",
        "coordinates": [
          11.85,
          51.35
        ]
      },
      "type": "Feature",
      "properties": {
        "hierarchy": [
          "tgn:7109341",
          "tgn:1000003",
          "tgn:7003687",
          "tgn:7000084",
          "tgn:7029392"
        ],
        "placetype": [
          "aat:300008347"
        ],
        "id": 7109341,
        "name:xx": "Reinsdorf"
      }
    },
    {
      "geometry": {
        "type": "Point",
        "coordinates": [
          11.266667,
          51.333333
        ]
      },
      "type": "Feature",
      "properties": {
        "hierarchy": [
          "tgn:7109342",
          "tgn:1000003",
          "tgn:7003689",
          "tgn:7000084",
          "tgn:7029392"
        ],
        "placetype": [
          "aat:300008347"
        ],
        "id": 7109342,
        "name:xx": "Reinsdorf"
      }
    },
    {
      "geometry": {
        "type": "Point",
        "coordinates": [
          11.6,
          51.3
        ]
      },
      "type": "Feature",
      "properties": {
        "hierarchy": [
          "tgn:7109343",
          "tgn:1000003",
          "tgn:7003687",
          "tgn:7000084",
          "tgn:7029392"
        ],
        "placetype": [
          "aat:300008347"
        ],
        "id": 7109343,
        "name:xx": "Reinsdorf"
      }
    },
    {
      "geometry": {
        "type": "Point",
        "coordinates": [
          12.966667,
          51.066667
        ]
      },
      "type": "Feature",
      "properties": {
        "hierarchy": [
          "tgn:7109344",
          "tgn:1000003",
          "tgn:7003685",
          "tgn:7000084",
          "tgn:7029392"
        ],
        "placetype": [
          "aat:300008347"
        ],
        "id": 7109344,
        "name:xx": "Reinsdorf"
      }
    },
    {
      "geometry": {
        "type": "Point",
        "coordinates": [
          11.85,
          50.683333
        ]
      },
      "type": "Feature",
      "properties": {
        "hierarchy": [
          "tgn:7109346",
          "tgn:1000003",
          "tgn:7003689",
          "tgn:7000084",
          "tgn:7029392"
        ],
        "placetype": [
          "aat:300008347"
        ],
        "id": 7109346,
        "name:xx": "Reinsdorf"
      }
    },
    {
      "geometry": {
        "type": "Point",
        "coordinates": [
          13.133333,
          51.166667
        ]
      },
      "type": "Feature",
      "properties": {
        "hierarchy": [
          "tgn:7109347",
          "tgn:1000003",
          "tgn:7003685",
          "tgn:7000084",
          "tgn:7029392"
        ],
        "placetype": [
          "aat:300008347"
        ],
        "id": 7109347,
        "name:xx": "Redemitz"
      }
    },
    {
      "geometry": {
        "type": "Point",
        "coordinates": [
          12.083333,
          52.466667
        ]
      },
      "type": "Feature",
      "properties": {
        "hierarchy": [
          "tgn:7109348",
          "tgn:1000003",
          "tgn:7003687",
          "tgn:7000084",
          "tgn:7029392"
        ],
        "placetype": [
          "aat:300008347"
        ],
        "id": 7109348,
        "name:xx": "Redekin"
      }
    }
  ]
}
