{
  "type": "FeatureCollection",
  "features": [
    {
      "geometry": {
        "type": "Point",
        "coordinates": [
          -80.95,
          36
        ]
      },
      "type": "Feature",
      "properties": {
        "hierarchy": [
          "tgn:2539270",
          "tgn:1000001",
          "tgn:7012149",
          "tgn:2001507",
          "tgn:7007709",
          "tgn:7029392"
        ],
        "placetype": [
          "aat:300008347"
        ],
        "id": 2539270,
        "name:xx": "New Hope"
      }
    },
    {
      "geometry": {
        "type": "Point",
        "coordinates": [
          -80.7,
          36.4167
        ]
      },
      "type": "Feature",
      "properties": {
        "hierarchy": [
          "tgn:2539271",
          "tgn:1000001",
          "tgn:7012149",
          "tgn:2001542",
          "tgn:7007709",
          "tgn:7029392"
        ],
        "placetype": [
          "aat:300008347"
        ],
        "id": 2539271,
        "name:xx": "New Hope"
      }
    },
    {
      "geometry": {
        "type": "Point",
        "coordinates": [
          -83.9,
          38.95
        ]
      },
      "type": "Feature",
      "properties": {
        "hierarchy": [
          "tgn:2539272",
          "tgn:1000001",
          "tgn:1002210",
          "tgn:7012149",
          "tgn:7007706",
          "tgn:7029392"
        ],
        "placetype": [
          "aat:300008347"
        ],
        "id": 2539272,
        "name:xx": "New Hope"
      }
    },
    {
      "geometry": {
        "type": "Point",
        "coordinates": [
          -123.3667,
          42.35
        ]
      },
      "type": "Feature",
      "properties": {
        "hierarchy": [
          "tgn:2539273",
          "tgn:1000001",
          "tgn:7012149",
          "tgn:2001713",
          "tgn:7007708",
          "tgn:7029392"
        ],
        "placetype": [
          "aat:300008347"
        ],
        "id": 2539273,
        "name:xx": "New Hope"
      }
    },
    {
      "geometry": {
        "type": "Point",
        "coordinates": [
          -79.4667,
          33.35
        ]
      },
      "type": "Feature",
      "properties": {
        "hierarchy": [
          "tgn:2539274",
          "tgn:1000001",
          "tgn:2001746",
          "tgn:7012149",
          "tgn:7007712",
          "tgn:7029392"
        ],
        "placetype": [
          "aat:300008347"
        ],
        "id": 2539274,
        "name:xx": "New Hope"
      }
    },
    {
      "geometry": {
        "type": "Point",
        "coordinates": [
          -79.8167,
          33.0833
        ]
      },
      "type": "Feature",
      "properties": {
        "hierarchy": [
          "tgn:2539275",
          "tgn:2001732",
          "tgn:1000001",
          "tgn:7012149",
          "tgn:7007712",
          "tgn:7029392"
        ],
        "placetype": [
          "aat:300008347"
        ],
        "id": 2539275,
        "name:xx": "New Hope"
      }
    },
    {
      "geometry": {
        "type": "Point",
        "coordinates": [
          -88.25,
          36.1833
        ]
      },
      "type": "Feature",
      "properties": {
        "hierarchy": [
          "tgn:2539276",
          "tgn:1000001",
          "tgn:7012149",
          "tgn:2001876",
          "tgn:7007825",
          "tgn:7029392"
        ],
        "placetype": [
          "aat:300008347"
        ],
        "id": 2539276,
        "name:xx": "New Hope"
      }
    },
    {
      "geometry": {
        "type": "Point",
        "coordinates": [
          -86.15,
          35.8167
        ]
      },
      "type": "Feature",
      "properties": {
        "hierarchy": [
          "tgn:2539277",
          "tgn:1000001",
          "tgn:7012149",
          "tgn:2001844",
          "tgn:7007825",
          "tgn:7029392"
        ],
        "placetype": [
          "aat:300008347"
        ],
        "id": 2539277,
        "name:xx": "New Hope"
      }
    },
    {
      "geometry": {
        "type": "Point",
        "coordinates": [
          -85.4333,
          35.25
        ]
      },
      "type": "Feature",
      "properties": {
        "hierarchy": [
          "tgn:2539278",
          "tgn:1000001",
          "tgn:7012149",
          "tgn:2001913",
          "tgn:7007825",
          "tgn:7029392"
        ],
        "placetype": [
          "aat:300008347"
        ],
        "id": 2539278,
        "name:xx": "New Hope"
      }
    },
    {
      "geometry": {
        "type": "Point",
        "coordinates": [
          -88.6833,
          35.95
        ]
      },
      "type": "Feature",
      "properties": {
        "hierarchy": [
          "tgn:2539279",
          "tgn:1000001",
          "tgn:7012149",
          "tgn:2001863",
          "tgn:7007825",
          "tgn:7029392"
        ],
        "placetype": [
          "aat:300008347"
        ],
        "id": 2539279,
        "name:xx": "New Hope"
      }
    }
  ]
}
