{
  "geometry": {
    "type": "Point",
    "coordinates": [
      -73.0167,
      42.75
    ]
  },
  "type": "Feature",
  "properties": {
    "hierarchy": [
      "tgn:2300645",
      "tgn:1000001",
      "tgn:7012149",
      "tgn:7029392"
    ],
    "placetype": [
      "aat:300008699"
    ],
    "id": 2300645,
    "name:xx": "Dunbar Brook"
  }
}
