{
  "type": "FeatureCollection",
  "features": [
    {
      "geometry": {
        "type": "Point",
        "coordinates": [
          -7.616667,
          56.833333
        ]
      },
      "type": "Feature",
      "properties": {
        "hierarchy": [
          "tgn:7458592",
          "tgn:7002444",
          "tgn:1000003",
          "tgn:7008094",
          "tgn:7008591",
          "tgn:7029392"
        ],
        "placetype": [
          "aat:300266558"
        ],
        "name:en": "Mingulay, Sound of",
        "id": 7458592
      }
    },
    {
      "geometry": {
        "type": "Point",
        "coordinates": [
          -6.3,
          57.233333
        ]
      },
      "type": "Feature",
      "properties": {
        "hierarchy": [
          "tgn:7458594",
          "tgn:7002444",
          "tgn:1000003",
          "tgn:7008082",
          "tgn:7008591",
          "tgn:7029392"
        ],
        "placetype": [
          "aat:300387346"
        ],
        "name:en": "Minginish",
        "id": 7458594
      }
    },
    {
      "geometry": {
        "type": "Point",
        "coordinates": [
          -6.2,
          56.633333
        ]
      },
      "type": "Feature",
      "properties": {
        "hierarchy": [
          "tgn:7458595",
          "tgn:7019094",
          "tgn:7002444",
          "tgn:1000003",
          "tgn:7008591",
          "tgn:7029392"
        ],
        "placetype": [
          "aat:300132316"
        ],
        "name:en": "Mingary, Loch",
        "id": 7458595
      }
    },
    {
      "geometry": {
        "type": "Point",
        "coordinates": [
          -4.083333,
          52.916667
        ]
      },
      "type": "Feature",
      "properties": {
        "hierarchy": [
          "tgn:7458596",
          "tgn:7002443",
          "tgn:1000003",
          "tgn:7029493",
          "tgn:7008591",
          "tgn:7029392"
        ],
        "placetype": [
          "aat:300008347"
        ],
        "name:en": "Minffordd",
        "id": 7458596
      }
    },
    {
      "geometry": {
        "type": "Point",
        "coordinates": [
          -1.95,
          51.616667
        ]
      },
      "type": "Feature",
      "properties": {
        "hierarchy": [
          "tgn:7458597",
          "tgn:7002445",
          "tgn:1000003",
          "tgn:7008180",
          "tgn:7008591",
          "tgn:7029392"
        ],
        "placetype": [
          "aat:300008347"
        ],
        "name:en": "Minety",
        "id": 7458597
      }
    },
    {
      "geometry": {
        "type": "Point",
        "coordinates": [
          -3.1,
          53.05
        ]
      },
      "type": "Feature",
      "properties": {
        "hierarchy": [
          "tgn:7458598",
          "tgn:7002443",
          "tgn:1000003",
          "tgn:7019007",
          "tgn:7008591",
          "tgn:7029392"
        ],
        "placetype": [
          "aat:300008347"
        ],
        "name:en": "Minera",
        "id": 7458598
      }
    }
  ]
}
