{
  "geometry": {
    "type": "Point",
    "coordinates": [
      -115.1333,
      40.2333
    ]
  },
  "type": "Feature",
  "properties": {
    "hierarchy": [
      "tgn:2389486",
      "tgn:1000001",
      "tgn:2001411",
      "tgn:7012149",
      "tgn:7007526",
      "tgn:7029392"
    ],
    "placetype": [
      "aat:300008798"
    ],
    "id": 2389486,
    "name:xx": "High Bald Peaks"
  }
}
