{
  "geometry": {
    "type": "Point",
    "coordinates": [
      -114.9667,
      43.9333
    ]
  },
  "type": "Feature",
  "properties": {
    "hierarchy": [
      "tgn:1107556",
      "tgn:1000001",
      "tgn:7012149",
      "tgn:7007250",
      "tgn:7029392"
    ],
    "placetype": [
      "aat:300008798"
    ],
    "id": 1107556,
    "name:xx": "Snowyside Peak"
  }
}
