{
  "geometry": {
    "type": "Point",
    "coordinates": [
      -76.4833,
      36.9167
    ]
  },
  "type": "Feature",
  "properties": {
    "hierarchy": [
      "tgn:2581032",
      "tgn:1000001",
      "tgn:7012149",
      "tgn:7022217",
      "tgn:7007919",
      "tgn:7029392"
    ],
    "placetype": [
      "aat:300008850"
    ],
    "id": 2581032,
    "name:xx": "Pike Point"
  }
}
