{
  "type": "FeatureCollection",
  "features": [
    {
      "geometry": {
        "type": "Point",
        "coordinates": [
          119.2833,
          10.8
        ]
      },
      "type": "Feature",
      "properties": {
        "hierarchy": [
          "tgn:1104310",
          "tgn:1000004",
          "tgn:1001481",
          "tgn:1000135",
          "tgn:7029392"
        ],
        "placetype": [
          "aat:300008795"
        ],
        "id": 1104310,
        "name:xx": "Copoas, Mount"
      }
    },
    {
      "geometry": {
        "type": "Point",
        "coordinates": [
          -132.6,
          55.2333
        ]
      },
      "type": "Feature",
      "properties": {
        "hierarchy": [
          "tgn:1104311",
          "tgn:7006450",
          "tgn:1000001",
          "tgn:7012149",
          "tgn:2000082",
          "tgn:7029392"
        ],
        "placetype": [
          "aat:300008795"
        ],
        "id": 1104311,
        "name:xx": "Copper Mountain"
      }
    },
    {
      "geometry": {
        "type": "Point",
        "coordinates": [
          -107.9167,
          43.4333
        ]
      },
      "type": "Feature",
      "properties": {
        "hierarchy": [
          "tgn:1104312",
          "tgn:1000001",
          "tgn:7012149",
          "tgn:2002371",
          "tgn:7007923",
          "tgn:7029392"
        ],
        "placetype": [
          "aat:300008795"
        ],
        "id": 1104312,
        "name:xx": "Copper Mountain"
      }
    },
    {
      "geometry": {
        "type": "Point",
        "coordinates": [
          -42.9167,
          -21.6667
        ]
      },
      "type": "Feature",
      "properties": {
        "hierarchy": [
          "tgn:1104313",
          "tgn:7006237",
          "tgn:1000047",
          "tgn:7002457",
          "tgn:1000002",
          "tgn:7029392"
        ],
        "placetype": [
          "aat:300008795"
        ],
        "id": 1104313,
        "name:xx": "Coqueiro Grande, Serra do"
      }
    },
    {
      "geometry": {
        "type": "Point",
        "coordinates": [
          -43.2167,
          -22.9667
        ]
      },
      "type": "Feature",
      "properties": {
        "hierarchy": [
          "tgn:1104315",
          "tgn:1001942",
          "tgn:1000047",
          "tgn:7002457",
          "tgn:1000002",
          "tgn:7017095",
          "tgn:7029392"
        ],
        "placetype": [
          "aat:300008795"
        ],
        "id": 1104315,
        "name:xx": "Corcovado"
      }
    },
    {
      "geometry": {
        "type": "Point",
        "coordinates": [
          148.8,
          -35.3
        ]
      },
      "type": "Feature",
      "properties": {
        "hierarchy": [
          "tgn:1104316",
          "tgn:7000490",
          "tgn:1000006",
          "tgn:7001828",
          "tgn:7029392"
        ],
        "placetype": [
          "aat:300008795"
        ],
        "id": 1104316,
        "name:xx": "Coree, Mount"
      }
    },
    {
      "geometry": {
        "type": "Point",
        "coordinates": [
          13.566667,
          42.466667
        ]
      },
      "type": "Feature",
      "properties": {
        "hierarchy": [
          "tgn:1104319",
          "tgn:7009084",
          "tgn:1109070",
          "tgn:1000003",
          "tgn:1000080",
          "tgn:7029392"
        ],
        "placetype": [
          "aat:300008795"
        ],
        "id": 1104319,
        "name:xx": "Corno Grande"
      }
    }
  ]
}
