{
  "geometry": {
    "type": "Point",
    "coordinates": [
      32.2833,
      -14.9167
    ]
  },
  "type": "Feature",
  "properties": {
    "hierarchy": [
      "tgn:1091704",
      "tgn:7001242",
      "tgn:1000940",
      "tgn:1000180",
      "tgn:7029392"
    ],
    "placetype": [
      "aat:300008347"
    ],
    "id": 1091704,
    "name:xx": "Vila Vasco da Gama"
  }
}
