{
  "geometry": {
    "type": "Point",
    "coordinates": [
      -108.35,
      35.1833
    ]
  },
  "type": "Feature",
  "properties": {
    "hierarchy": [
      "tgn:2585951",
      "tgn:1000001",
      "tgn:2001431",
      "tgn:7012149",
      "tgn:7007566",
      "tgn:7029392"
    ],
    "placetype": [
      "aat:300008761"
    ],
    "id": 2585951,
    "name:xx": "Pipkin Canyon"
  }
}
