{
  "type": "FeatureCollection",
  "features": [
    {
      "geometry": {
        "type": "Point",
        "coordinates": [
          -105.583333,
          26.75
        ]
      },
      "type": "Feature",
      "properties": {
        "hierarchy": [
          "tgn:7372800",
          "tgn:7005581",
          "tgn:1000001",
          "tgn:7005560",
          "tgn:7029392"
        ],
        "placetype": [
          "aat:300008347"
        ],
        "id": 7372800,
        "name:xx": "La Casita"
      }
    },
    {
      "geometry": {
        "type": "Point",
        "coordinates": [
          -105.183333,
          26.65
        ]
      },
      "type": "Feature",
      "properties": {
        "hierarchy": [
          "tgn:7372801",
          "tgn:7005581",
          "tgn:1000001",
          "tgn:7005560",
          "tgn:7029392"
        ],
        "placetype": [
          "aat:300008347"
        ],
        "id": 7372801,
        "name:xx": "La Casita"
      }
    },
    {
      "geometry": {
        "type": "Point",
        "coordinates": [
          -100.65,
          25.45
        ]
      },
      "type": "Feature",
      "properties": {
        "hierarchy": [
          "tgn:7372802",
          "tgn:1001853",
          "tgn:1000001",
          "tgn:7005560",
          "tgn:7029392"
        ],
        "placetype": [
          "aat:300008347"
        ],
        "id": 7372802,
        "name:xx": "La Casita"
      }
    },
    {
      "geometry": {
        "type": "Point",
        "coordinates": [
          -101.45,
          25.233333
        ]
      },
      "type": "Feature",
      "properties": {
        "hierarchy": [
          "tgn:7372803",
          "tgn:1001853",
          "tgn:1000001",
          "tgn:7005560",
          "tgn:7029392"
        ],
        "placetype": [
          "aat:300008347"
        ],
        "id": 7372803,
        "name:xx": "La Casita"
      }
    },
    {
      "geometry": {
        "type": "Point",
        "coordinates": [
          -100.716667,
          25
        ]
      },
      "type": "Feature",
      "properties": {
        "hierarchy": [
          "tgn:7372804",
          "tgn:1000001",
          "tgn:7005589",
          "tgn:7005560",
          "tgn:7029392"
        ],
        "placetype": [
          "aat:300008347"
        ],
        "id": 7372804,
        "name:xx": "La Casita"
      }
    },
    {
      "geometry": {
        "type": "Point",
        "coordinates": [
          -106.133333,
          27.283333
        ]
      },
      "type": "Feature",
      "properties": {
        "hierarchy": [
          "tgn:7372806",
          "tgn:7005581",
          "tgn:1000001",
          "tgn:7005560",
          "tgn:7029392"
        ],
        "placetype": [
          "aat:300387007"
        ],
        "id": 7372806,
        "name:xx": "La Casita"
      }
    },
    {
      "geometry": {
        "type": "Point",
        "coordinates": [
          -101.716667,
          27.283333
        ]
      },
      "type": "Feature",
      "properties": {
        "hierarchy": [
          "tgn:7372807",
          "tgn:1001853",
          "tgn:1000001",
          "tgn:7005560",
          "tgn:7029392"
        ],
        "placetype": [
          "aat:300000241"
        ],
        "id": 7372807,
        "name:xx": "Rancho La Cascada"
      }
    },
    {
      "geometry": {
        "type": "Point",
        "coordinates": [
          -107.65,
          25.6
        ]
      },
      "type": "Feature",
      "properties": {
        "hierarchy": [
          "tgn:7372808",
          "tgn:1000001",
          "tgn:7005595",
          "tgn:7005560",
          "tgn:7029392"
        ],
        "placetype": [
          "aat:300008347"
        ],
        "id": 7372808,
        "name:xx": "La Cascada"
      }
    },
    {
      "geometry": {
        "type": "Point",
        "coordinates": [
          -100.7,
          27.966667
        ]
      },
      "type": "Feature",
      "properties": {
        "hierarchy": [
          "tgn:7372809",
          "tgn:1001853",
          "tgn:1000001",
          "tgn:7005560",
          "tgn:7029392"
        ],
        "placetype": [
          "aat:300000241"
        ],
        "id": 7372809,
        "name:xx": "Rancho La Casa de Piedra"
      }
    }
  ]
}
