{
  "geometry": {
    "type": "Point",
    "coordinates": [
      -84.6167,
      39.9833
    ]
  },
  "type": "Feature",
  "properties": {
    "hierarchy": [
      "tgn:2289187",
      "tgn:1000001",
      "tgn:1002317",
      "tgn:7012149",
      "tgn:7007706",
      "tgn:7029392"
    ],
    "placetype": [
      "aat:300008699"
    ],
    "id": 2289187,
    "name:xx": "Dividing Branch"
  }
}
