{
  "type": "FeatureCollection",
  "features": [
    {
      "geometry": {
        "type": "Point",
        "coordinates": [
          -111.9,
          43.7167
        ]
      },
      "type": "Feature",
      "properties": {
        "hierarchy": [
          "tgn:2649480",
          "tgn:1000001",
          "tgn:7012149",
          "tgn:2000477",
          "tgn:7007250",
          "tgn:7029392"
        ],
        "placetype": [
          "aat:300008699"
        ],
        "id": 2649480,
        "name:xx": "Scotts Slough"
      }
    },
    {
      "geometry": {
        "type": "Point",
        "coordinates": [
          -91.8333,
          38.35
        ]
      },
      "type": "Feature",
      "properties": {
        "hierarchy": [
          "tgn:2649481",
          "tgn:1000001",
          "tgn:7012149",
          "tgn:1002755",
          "tgn:7007523",
          "tgn:7029392"
        ],
        "placetype": [
          "aat:300008699"
        ],
        "id": 2649481,
        "name:xx": "Scotts Slough"
      }
    },
    {
      "geometry": {
        "type": "Point",
        "coordinates": [
          -99.3167,
          47.5167
        ]
      },
      "type": "Feature",
      "properties": {
        "hierarchy": [
          "tgn:2649482",
          "tgn:1000001",
          "tgn:7012149",
          "tgn:7007705",
          "tgn:7029392"
        ],
        "placetype": [
          "aat:300008699"
        ],
        "id": 2649482,
        "name:xx": "Scotts Slough"
      }
    },
    {
      "geometry": {
        "type": "Point",
        "coordinates": [
          -96.9833,
          43.6333
        ]
      },
      "type": "Feature",
      "properties": {
        "hierarchy": [
          "tgn:2649483",
          "tgn:1000001",
          "tgn:2001819",
          "tgn:7012149",
          "tgn:7007713",
          "tgn:7029392"
        ],
        "placetype": [
          "aat:300008680"
        ],
        "id": 2649483,
        "name:xx": "Scotts Slough"
      }
    },
    {
      "geometry": {
        "type": "Point",
        "coordinates": [
          -111.9667,
          43.7333
        ]
      },
      "type": "Feature",
      "properties": {
        "hierarchy": [
          "tgn:2649484",
          "tgn:1000001",
          "tgn:7012149",
          "tgn:2000477",
          "tgn:7007250",
          "tgn:7029392"
        ],
        "placetype": [
          "aat:300006075"
        ],
        "id": 2649484,
        "name:xx": "Scotts Slough Canal"
      }
    },
    {
      "geometry": {
        "type": "Point",
        "coordinates": [
          -85.05,
          44.9333
        ]
      },
      "type": "Feature",
      "properties": {
        "hierarchy": [
          "tgn:2649485",
          "tgn:2000945",
          "tgn:1000001",
          "tgn:7012149",
          "tgn:7007520",
          "tgn:7029392"
        ],
        "placetype": [
          "aat:300008697"
        ],
        "id": 2649485,
        "name:xx": "Scotts Spring"
      }
    },
    {
      "geometry": {
        "type": "Point",
        "coordinates": [
          -103.6833,
          41.8167
        ]
      },
      "type": "Feature",
      "properties": {
        "hierarchy": [
          "tgn:2649486",
          "tgn:1000001",
          "tgn:7012149",
          "tgn:2001394",
          "tgn:7007525",
          "tgn:7029392"
        ],
        "placetype": [
          "aat:300008697"
        ],
        "id": 2649486,
        "name:xx": "Scotts Spring"
      }
    },
    {
      "geometry": {
        "type": "Point",
        "coordinates": [
          -119.1,
          38.7
        ]
      },
      "type": "Feature",
      "properties": {
        "hierarchy": [
          "tgn:2649487",
          "tgn:1000001",
          "tgn:1002614",
          "tgn:7012149",
          "tgn:7007526",
          "tgn:7029392"
        ],
        "placetype": [
          "aat:300008697"
        ],
        "id": 2649487,
        "name:xx": "Scotts Spring"
      }
    },
    {
      "geometry": {
        "type": "Point",
        "coordinates": [
          -96.6833,
          30.5333
        ]
      },
      "type": "Feature",
      "properties": {
        "hierarchy": [
          "tgn:2649488",
          "tgn:1000001",
          "tgn:7012149",
          "tgn:1002214",
          "tgn:7007826",
          "tgn:7029392"
        ],
        "placetype": [
          "aat:300008697"
        ],
        "id": 2649488,
        "name:xx": "Scotts Spring"
      }
    }
  ]
}
