{
  "geometry": {
    "type": "Point",
    "coordinates": [
      53.1667,
      57.1667
    ]
  },
  "type": "Feature",
  "properties": {
    "hierarchy": [
      "tgn:1054522",
      "tgn:1000004",
      "tgn:7002435",
      "tgn:7011526",
      "tgn:7029392"
    ],
    "placetype": [
      "aat:300008347"
    ],
    "id": 1054522,
    "name:xx": "Yakshur-Bodya"
  }
}
