{
  "geometry": {
    "type": "Point",
    "coordinates": [
      -105.1833,
      36.8333
    ]
  },
  "type": "Feature",
  "properties": {
    "hierarchy": [
      "tgn:2314221",
      "tgn:1000001",
      "tgn:2001432",
      "tgn:7012149",
      "tgn:7007566",
      "tgn:7029392"
    ],
    "placetype": [
      "aat:300008706"
    ],
    "id": 2314221,
    "name:xx": "Elk Creek"
  }
}
