{
  "type": "FeatureCollection",
  "features": [
    {
      "geometry": {
        "type": "Point",
        "coordinates": [
          11.9,
          49.833333
        ]
      },
      "type": "Feature",
      "properties": {
        "hierarchy": [
          "tgn:1136930",
          "tgn:7003669",
          "tgn:1000003",
          "tgn:7000084",
          "tgn:7029392"
        ],
        "placetype": [
          "aat:300008347"
        ],
        "id": 1136930,
        "name:xx": "Kastl"
      }
    },
    {
      "geometry": {
        "type": "Point",
        "coordinates": [
          7.4,
          49.95
        ]
      },
      "type": "Feature",
      "properties": {
        "hierarchy": [
          "tgn:1136932",
          "tgn:1000003",
          "tgn:7003682",
          "tgn:7000084",
          "tgn:7029392"
        ],
        "placetype": [
          "aat:300008347"
        ],
        "id": 1136932,
        "name:xx": "Kirchberg"
      }
    },
    {
      "geometry": {
        "type": "Point",
        "coordinates": [
          10.366667,
          48.25
        ]
      },
      "type": "Feature",
      "properties": {
        "hierarchy": [
          "tgn:1136933",
          "tgn:7003669",
          "tgn:1000003",
          "tgn:7000084",
          "tgn:7029392"
        ],
        "placetype": [
          "aat:300008347"
        ],
        "id": 1136933,
        "name:xx": "Krumbach"
      }
    },
    {
      "geometry": {
        "type": "Point",
        "coordinates": [
          8.6,
          53.616667
        ]
      },
      "type": "Feature",
      "properties": {
        "hierarchy": [
          "tgn:1136934",
          "tgn:1000003",
          "tgn:7003676",
          "tgn:7000084",
          "tgn:7029392"
        ],
        "placetype": [
          "aat:300008347"
        ],
        "id": 1136934,
        "name:xx": "Langen"
      }
    },
    {
      "geometry": {
        "type": "Point",
        "coordinates": [
          8.316667,
          51.783333
        ]
      },
      "type": "Feature",
      "properties": {
        "hierarchy": [
          "tgn:1136935",
          "tgn:1000003",
          "tgn:7003677",
          "tgn:7000084",
          "tgn:7029392"
        ],
        "placetype": [
          "aat:300008347"
        ],
        "id": 1136935,
        "name:xx": "Langenberg"
      }
    },
    {
      "geometry": {
        "type": "Point",
        "coordinates": [
          9.55,
          52.083333
        ]
      },
      "type": "Feature",
      "properties": {
        "hierarchy": [
          "tgn:1136936",
          "tgn:1000003",
          "tgn:7003676",
          "tgn:7000084",
          "tgn:7029392"
        ],
        "placetype": [
          "aat:300008347"
        ],
        "id": 1136936,
        "name:xx": "Lauenstein"
      }
    },
    {
      "geometry": {
        "type": "Point",
        "coordinates": [
          9.4,
          50.633333
        ]
      },
      "type": "Feature",
      "properties": {
        "hierarchy": [
          "tgn:1136937",
          "tgn:1000003",
          "tgn:7003678",
          "tgn:7000084",
          "tgn:7029392"
        ],
        "placetype": [
          "aat:300008347"
        ],
        "id": 1136937,
        "name:xx": "Lauterbach"
      }
    },
    {
      "geometry": {
        "type": "Point",
        "coordinates": [
          7.516667,
          52.55
        ]
      },
      "type": "Feature",
      "properties": {
        "hierarchy": [
          "tgn:1136938",
          "tgn:1000003",
          "tgn:7003676",
          "tgn:7000084",
          "tgn:7029392"
        ],
        "placetype": [
          "aat:300008347"
        ],
        "id": 1136938,
        "name:xx": "Lengerich"
      }
    }
  ]
}
