{
  "geometry": {
    "type": "Point",
    "coordinates": [
      -73.4667,
      43.2167
    ]
  },
  "type": "Feature",
  "properties": {
    "hierarchy": [
      "tgn:2148163",
      "tgn:1000001",
      "tgn:7012149",
      "tgn:1002993",
      "tgn:7007568",
      "tgn:7029392"
    ],
    "placetype": [
      "aat:300008798"
    ],
    "id": 2148163,
    "name:xx": "Barkley Mountain"
  }
}
