{
  "type": "FeatureCollection",
  "features": [
    {
      "geometry": {
        "type": "Point",
        "coordinates": [
          -106.6,
          24.25
        ]
      },
      "type": "Feature",
      "properties": {
        "hierarchy": [
          "tgn:7429310",
          "tgn:1000001",
          "tgn:7005595",
          "tgn:7005560",
          "tgn:7029392"
        ],
        "placetype": [
          "aat:300008347"
        ],
        "id": 7429310,
        "name:xx": "Playitas"
      }
    },
    {
      "geometry": {
        "type": "Point",
        "coordinates": [
          -106.783333,
          24.483333
        ]
      },
      "type": "Feature",
      "properties": {
        "hierarchy": [
          "tgn:7429313",
          "tgn:1000001",
          "tgn:7005595",
          "tgn:7005560",
          "tgn:7029392"
        ],
        "placetype": [
          "aat:300008347"
        ],
        "id": 7429313,
        "name:xx": "El Palmar de los Fonseca"
      }
    },
    {
      "geometry": {
        "type": "Point",
        "coordinates": [
          -106.65,
          24.5
        ]
      },
      "type": "Feature",
      "properties": {
        "hierarchy": [
          "tgn:7429315",
          "tgn:1000001",
          "tgn:7005595",
          "tgn:7005560",
          "tgn:7029392"
        ],
        "placetype": [
          "aat:300008347"
        ],
        "id": 7429315,
        "name:xx": "La Estrella"
      }
    },
    {
      "geometry": {
        "type": "Point",
        "coordinates": [
          -106.633333,
          24.516667
        ]
      },
      "type": "Feature",
      "properties": {
        "hierarchy": [
          "tgn:7429316",
          "tgn:1000001",
          "tgn:7005595",
          "tgn:7005560",
          "tgn:7029392"
        ],
        "placetype": [
          "aat:300008347"
        ],
        "id": 7429316,
        "name:xx": "Pozo Zarco"
      }
    },
    {
      "geometry": {
        "type": "Point",
        "coordinates": [
          -106.758333,
          24.516667
        ]
      },
      "type": "Feature",
      "properties": {
        "hierarchy": [
          "tgn:7429317",
          "tgn:1000001",
          "tgn:7005595",
          "tgn:7005560",
          "tgn:7029392"
        ],
        "placetype": [
          "aat:300008795"
        ],
        "id": 7429317,
        "name:xx": "Pelón, Cerro"
      }
    },
    {
      "geometry": {
        "type": "Point",
        "coordinates": [
          -106.8,
          24.516667
        ]
      },
      "type": "Feature",
      "properties": {
        "hierarchy": [
          "tgn:7429318",
          "tgn:1000001",
          "tgn:7005595",
          "tgn:7005560",
          "tgn:7029392"
        ],
        "placetype": [
          "aat:300008347"
        ],
        "id": 7429318,
        "name:xx": "El Ranchito"
      }
    },
    {
      "geometry": {
        "type": "Point",
        "coordinates": [
          -106.883333,
          24.3
        ]
      },
      "type": "Feature",
      "properties": {
        "hierarchy": [
          "tgn:7429319",
          "tgn:1000001",
          "tgn:7005595",
          "tgn:7005560",
          "tgn:7029392"
        ],
        "placetype": [
          "aat:300008795"
        ],
        "id": 7429319,
        "name:xx": "El Infierno, Sierra"
      }
    }
  ]
}
