{
  "geometry": {
    "type": "Point",
    "coordinates": [
      -104.3333,
      40.15
    ]
  },
  "type": "Feature",
  "properties": {
    "hierarchy": [
      "tgn:2308373",
      "tgn:1000001",
      "tgn:7012149",
      "tgn:7007158",
      "tgn:2000253",
      "tgn:7029392"
    ],
    "placetype": [
      "aat:300008706"
    ],
    "id": 2308373,
    "name:xx": "East Lost Creek"
  }
}
