{
  "type": "FeatureCollection",
  "features": [
    {
      "geometry": {
        "type": "Point",
        "coordinates": [
          -76.0667,
          44.2667
        ]
      },
      "type": "Feature",
      "properties": {
        "hierarchy": [
          "tgn:2183430",
          "tgn:1000001",
          "tgn:7012149",
          "tgn:1002518",
          "tgn:7007568",
          "tgn:7029392"
        ],
        "placetype": [
          "aat:300008791"
        ],
        "id": 2183430,
        "name:xx": "Bluff Island"
      }
    },
    {
      "geometry": {
        "type": "Point",
        "coordinates": [
          -75.7833,
          44.45
        ]
      },
      "type": "Feature",
      "properties": {
        "hierarchy": [
          "tgn:2183431",
          "tgn:1000001",
          "tgn:7012149",
          "tgn:7016021",
          "tgn:7007568",
          "tgn:7029392"
        ],
        "placetype": [
          "aat:300008791"
        ],
        "id": 2183431,
        "name:xx": "Bluff Island"
      }
    },
    {
      "geometry": {
        "type": "Point",
        "coordinates": [
          -77.95,
          33.85
        ]
      },
      "type": "Feature",
      "properties": {
        "hierarchy": [
          "tgn:2183432",
          "tgn:1000001",
          "tgn:2001472",
          "tgn:7012149",
          "tgn:7007709",
          "tgn:7029392"
        ],
        "placetype": [
          "aat:300008791"
        ],
        "id": 2183432,
        "name:xx": "Bluff Island"
      }
    },
    {
      "geometry": {
        "type": "Point",
        "coordinates": [
          -80.9,
          32.15
        ]
      },
      "type": "Feature",
      "properties": {
        "hierarchy": [
          "tgn:2183433",
          "tgn:2001731",
          "tgn:1000001",
          "tgn:7012149",
          "tgn:7007712",
          "tgn:7029392"
        ],
        "placetype": [
          "aat:300008791"
        ],
        "id": 2183433,
        "name:xx": "Bluff Island"
      }
    },
    {
      "geometry": {
        "type": "Point",
        "coordinates": [
          -80.4833,
          32.5667
        ]
      },
      "type": "Feature",
      "properties": {
        "hierarchy": [
          "tgn:2183434",
          "tgn:1000001",
          "tgn:2001739",
          "tgn:7012149",
          "tgn:7007712",
          "tgn:7029392"
        ],
        "placetype": [
          "aat:300386853"
        ],
        "id": 2183434,
        "name:xx": "Bluff Islands"
      }
    },
    {
      "geometry": {
        "type": "Point",
        "coordinates": [
          -89.9667,
          38.8167
        ]
      },
      "type": "Feature",
      "properties": {
        "hierarchy": [
          "tgn:2183435",
          "tgn:1000001",
          "tgn:7012149",
          "tgn:1002622",
          "tgn:7007251",
          "tgn:7029392"
        ],
        "placetype": [
          "aat:300008347"
        ],
        "id": 2183435,
        "name:xx": "Bluff Junction"
      }
    },
    {
      "geometry": {
        "type": "Point",
        "coordinates": [
          -131.4333,
          55.7667
        ]
      },
      "type": "Feature",
      "properties": {
        "hierarchy": [
          "tgn:2183436",
          "tgn:7006450",
          "tgn:1000001",
          "tgn:2124076",
          "tgn:7012149",
          "tgn:7029392"
        ],
        "placetype": [
          "aat:300008680"
        ],
        "id": 2183436,
        "name:xx": "Bluff Lake"
      }
    },
    {
      "geometry": {
        "type": "Point",
        "coordinates": [
          -93.8167,
          33.5333
        ]
      },
      "type": "Feature",
      "properties": {
        "hierarchy": [
          "tgn:2183437",
          "tgn:1000001",
          "tgn:7016172",
          "tgn:7012149",
          "tgn:2000150",
          "tgn:7029392"
        ],
        "placetype": [
          "aat:300008905"
        ],
        "id": 2183437,
        "name:xx": "Bluff Lake"
      }
    },
    {
      "geometry": {
        "type": "Point",
        "coordinates": [
          -118.5333,
          37.1667
        ]
      },
      "type": "Feature",
      "properties": {
        "hierarchy": [
          "tgn:2183438",
          "tgn:1000001",
          "tgn:7012149",
          "tgn:2000183",
          "tgn:7007157",
          "tgn:7029392"
        ],
        "placetype": [
          "aat:300008680"
        ],
        "id": 2183438,
        "name:xx": "Bluff Lake"
      }
    },
    {
      "geometry": {
        "type": "Point",
        "coordinates": [
          -121.35,
          40.45
        ]
      },
      "type": "Feature",
      "properties": {
        "hierarchy": [
          "tgn:2183439",
          "tgn:1000001",
          "tgn:7012149",
          "tgn:7007157",
          "tgn:2000188",
          "tgn:7029392"
        ],
        "placetype": [
          "aat:300008680"
        ],
        "id": 2183439,
        "name:xx": "Bluff Lake"
      }
    }
  ]
}
