{
  "type": "FeatureCollection",
  "features": [
    {
      "geometry": {
        "type": "Point",
        "coordinates": [
          -7.883333,
          42.766667
        ]
      },
      "type": "Feature",
      "properties": {
        "hierarchy": [
          "tgn:7347330",
          "tgn:7002829",
          "tgn:1000003",
          "tgn:7002786",
          "tgn:1000095",
          "tgn:7029392"
        ],
        "placetype": [
          "aat:300008347"
        ],
        "id": 7347330,
        "name:xx": "Arcos"
      }
    },
    {
      "geometry": {
        "type": "Point",
        "coordinates": [
          -8.533333,
          42.666667
        ]
      },
      "type": "Feature",
      "properties": {
        "hierarchy": [
          "tgn:7347331",
          "tgn:7002834",
          "tgn:1000003",
          "tgn:7002786",
          "tgn:1000095",
          "tgn:7029392"
        ],
        "placetype": [
          "aat:300008347"
        ],
        "id": 7347331,
        "name:xx": "Arcos"
      }
    },
    {
      "geometry": {
        "type": "Point",
        "coordinates": [
          -7.8,
          42.65
        ]
      },
      "type": "Feature",
      "properties": {
        "hierarchy": [
          "tgn:7347332",
          "tgn:7002829",
          "tgn:1000003",
          "tgn:7002786",
          "tgn:1000095",
          "tgn:7029392"
        ],
        "placetype": [
          "aat:300008347"
        ],
        "id": 7347332,
        "name:xx": "Arcos"
      }
    },
    {
      "geometry": {
        "type": "Point",
        "coordinates": [
          -8.933333,
          42.583333
        ]
      },
      "type": "Feature",
      "properties": {
        "hierarchy": [
          "tgn:7347333",
          "tgn:7002824",
          "tgn:1000003",
          "tgn:7002786",
          "tgn:1000095",
          "tgn:7029392"
        ],
        "placetype": [
          "aat:300008347"
        ],
        "id": 7347333,
        "name:xx": "Arcos"
      }
    },
    {
      "geometry": {
        "type": "Point",
        "coordinates": [
          -8.05,
          42.45
        ]
      },
      "type": "Feature",
      "properties": {
        "hierarchy": [
          "tgn:7347334",
          "tgn:7002831",
          "tgn:1000003",
          "tgn:7002786",
          "tgn:1000095",
          "tgn:7029392"
        ],
        "placetype": [
          "aat:300008347"
        ],
        "id": 7347334,
        "name:xx": "Arcos"
      }
    },
    {
      "geometry": {
        "type": "Point",
        "coordinates": [
          -7.033333,
          42.416667
        ]
      },
      "type": "Feature",
      "properties": {
        "hierarchy": [
          "tgn:7347336",
          "tgn:7002831",
          "tgn:1000003",
          "tgn:7002786",
          "tgn:1000095",
          "tgn:7029392"
        ],
        "placetype": [
          "aat:300008347"
        ],
        "id": 7347336,
        "name:xx": "Arcos"
      }
    },
    {
      "geometry": {
        "type": "Point",
        "coordinates": [
          -3.75,
          42.266667
        ]
      },
      "type": "Feature",
      "properties": {
        "hierarchy": [
          "tgn:7347337",
          "tgn:7002810",
          "tgn:7001158",
          "tgn:1000003",
          "tgn:1000095",
          "tgn:7029392"
        ],
        "placetype": [
          "aat:300008347"
        ],
        "id": 7347337,
        "name:xx": "Arcos"
      }
    },
    {
      "geometry": {
        "type": "Point",
        "coordinates": [
          -8.466667,
          42.183333
        ]
      },
      "type": "Feature",
      "properties": {
        "hierarchy": [
          "tgn:7347338",
          "tgn:7002834",
          "tgn:1000003",
          "tgn:7002786",
          "tgn:1000095",
          "tgn:7029392"
        ],
        "placetype": [
          "aat:300008347"
        ],
        "id": 7347338,
        "name:xx": "Arcos"
      }
    },
    {
      "geometry": {
        "type": "Point",
        "coordinates": [
          -3.716667,
          41.116667
        ]
      },
      "type": "Feature",
      "properties": {
        "hierarchy": [
          "tgn:7347339",
          "tgn:7002839",
          "tgn:7001158",
          "tgn:1000003",
          "tgn:1000095",
          "tgn:7029392"
        ],
        "placetype": [
          "aat:300008347"
        ],
        "id": 7347339,
        "name:xx": "Arcones"
      }
    }
  ]
}
