{
  "geometry": {
    "type": "Point",
    "coordinates": [
      -104.8333,
      47.2333
    ]
  },
  "type": "Feature",
  "properties": {
    "hierarchy": [
      "tgn:2720092",
      "tgn:1000001",
      "tgn:7012149",
      "tgn:2001270",
      "tgn:7007524",
      "tgn:7029392"
    ],
    "placetype": [
      "aat:300008706"
    ],
    "id": 2720092,
    "name:xx": "Threemile Creek"
  }
}
