{
  "geometry": {
    "type": "Point",
    "coordinates": [
      -15.5833,
      16.4667
    ]
  },
  "type": "Feature",
  "properties": {
    "hierarchy": [
      "tgn:1092491",
      "tgn:7001242",
      "tgn:1001670",
      "tgn:1000189",
      "tgn:7029392"
    ],
    "placetype": [
      "aat:300008347"
    ],
    "id": 1092491,
    "name:xx": "Dagana"
  }
}
