{
  "geometry": {
    "type": "Point",
    "coordinates": [
      30.39205,
      30.732293
    ]
  },
  "type": "Feature",
  "properties": {
    "hierarchy": [
      "tgn:7531358",
      "tgn:7001242",
      "tgn:1001075",
      "tgn:7016833",
      "tgn:7029392"
    ],
    "placetype": [
      "aat:300008347"
    ],
    "name:en": "Aḩmad Rāmī",
    "id": 7531358
  }
}
