{
  "geometry": {
    "type": "Point",
    "coordinates": [
      -112.3667,
      35.4667
    ]
  },
  "type": "Feature",
  "properties": {
    "hierarchy": [
      "tgn:2766082",
      "tgn:1000001",
      "tgn:7006451",
      "tgn:2000092",
      "tgn:7012149",
      "tgn:7029392"
    ],
    "placetype": [
      "aat:300006191"
    ],
    "id": 2766082,
    "name:xx": "White Horse Tank"
  }
}
