{
  "type": "FeatureCollection",
  "features": [
    {
      "geometry": {
        "type": "Point",
        "coordinates": [
          -71.5833,
          44.2833
        ]
      },
      "type": "Feature",
      "properties": {
        "hierarchy": [
          "tgn:2159940",
          "tgn:1002300",
          "tgn:1000001",
          "tgn:7012149",
          "tgn:7007564",
          "tgn:7029392"
        ],
        "placetype": [
          "aat:300008798"
        ],
        "id": 2159940,
        "name:xx": "Beech Hill"
      }
    },
    {
      "geometry": {
        "type": "Point",
        "coordinates": [
          -73.8167,
          41.1167
        ]
      },
      "type": "Feature",
      "properties": {
        "hierarchy": [
          "tgn:2159941",
          "tgn:1000001",
          "tgn:7012149",
          "tgn:7014612",
          "tgn:7007568",
          "tgn:7029392"
        ],
        "placetype": [
          "aat:300008798"
        ],
        "id": 2159941,
        "name:xx": "Beech Hill"
      }
    },
    {
      "geometry": {
        "type": "Point",
        "coordinates": [
          -74.7833,
          42.0333
        ]
      },
      "type": "Feature",
      "properties": {
        "hierarchy": [
          "tgn:2159942",
          "tgn:1000001",
          "tgn:1002328",
          "tgn:7012149",
          "tgn:7007568",
          "tgn:7029392"
        ],
        "placetype": [
          "aat:300008798"
        ],
        "id": 2159942,
        "name:xx": "Beech Hill"
      }
    },
    {
      "geometry": {
        "type": "Point",
        "coordinates": [
          -76.5333,
          42.3
        ]
      },
      "type": "Feature",
      "properties": {
        "hierarchy": [
          "tgn:2159943",
          "tgn:1000001",
          "tgn:7012149",
          "tgn:1002950",
          "tgn:7007568",
          "tgn:7029392"
        ],
        "placetype": [
          "aat:300008798"
        ],
        "id": 2159943,
        "name:xx": "Beech Hill"
      }
    },
    {
      "geometry": {
        "type": "Point",
        "coordinates": [
          -75.0833,
          43.1
        ]
      },
      "type": "Feature",
      "properties": {
        "hierarchy": [
          "tgn:2159944",
          "tgn:1000001",
          "tgn:7012149",
          "tgn:1002472",
          "tgn:7007568",
          "tgn:7029392"
        ],
        "placetype": [
          "aat:300008798"
        ],
        "id": 2159944,
        "name:xx": "Beech Hill"
      }
    },
    {
      "geometry": {
        "type": "Point",
        "coordinates": [
          -73.8333,
          43.8167
        ]
      },
      "type": "Feature",
      "properties": {
        "hierarchy": [
          "tgn:2159945",
          "tgn:1000001",
          "tgn:7012149",
          "tgn:2001461",
          "tgn:7007568",
          "tgn:7029392"
        ],
        "placetype": [
          "aat:300008798"
        ],
        "id": 2159945,
        "name:xx": "Beech Hill"
      }
    },
    {
      "geometry": {
        "type": "Point",
        "coordinates": [
          -75.35,
          43.8333
        ]
      },
      "type": "Feature",
      "properties": {
        "hierarchy": [
          "tgn:2159946",
          "tgn:1000001",
          "tgn:7012149",
          "tgn:1002593",
          "tgn:7007568",
          "tgn:7029392"
        ],
        "placetype": [
          "aat:300008798"
        ],
        "id": 2159946,
        "name:xx": "Beech Hill"
      }
    },
    {
      "geometry": {
        "type": "Point",
        "coordinates": [
          -77.85,
          42.0333
        ]
      },
      "type": "Feature",
      "properties": {
        "hierarchy": [
          "tgn:2159947",
          "tgn:1002141",
          "tgn:1000001",
          "tgn:7012149",
          "tgn:7007568",
          "tgn:7029392"
        ],
        "placetype": [
          "aat:300008798"
        ],
        "id": 2159947,
        "name:xx": "Beech Hill"
      }
    },
    {
      "geometry": {
        "type": "Point",
        "coordinates": [
          -77.5167,
          41.8167
        ]
      },
      "type": "Feature",
      "properties": {
        "hierarchy": [
          "tgn:2159948",
          "tgn:1000001",
          "tgn:7012149",
          "tgn:1002945",
          "tgn:7007710",
          "tgn:7029392"
        ],
        "placetype": [
          "aat:300008798"
        ],
        "id": 2159948,
        "name:xx": "Beech Hill"
      }
    },
    {
      "geometry": {
        "type": "Point",
        "coordinates": [
          -81.1667,
          32.4667
        ]
      },
      "type": "Feature",
      "properties": {
        "hierarchy": [
          "tgn:2159949",
          "tgn:1000001",
          "tgn:7012149",
          "tgn:2001751",
          "tgn:7007712",
          "tgn:7029392"
        ],
        "placetype": [
          "aat:300008798"
        ],
        "id": 2159949,
        "name:xx": "Beech Hill"
      }
    }
  ]
}
