{
  "geometry": {
    "type": "Point",
    "coordinates": [
      -94.3333,
      35.35
    ]
  },
  "type": "Feature",
  "properties": {
    "hierarchy": [
      "tgn:2771108",
      "tgn:1000001",
      "tgn:7016172",
      "tgn:7012149",
      "tgn:2000170",
      "tgn:7029392"
    ],
    "placetype": [
      "aat:300008798"
    ],
    "id": 2771108,
    "name:xx": "Wildcat Mountain"
  }
}
