{
  "geometry": {
    "type": "Point",
    "coordinates": [
      26.75,
      46.6833
    ]
  },
  "type": "Feature",
  "properties": {
    "hierarchy": [
      "tgn:1050050",
      "tgn:1000342",
      "tgn:1000003",
      "tgn:1000091",
      "tgn:7029392"
    ],
    "placetype": [
      "aat:300008347"
    ],
    "id": 1050050,
    "name:xx": "Buhuși"
  }
}
