{
  "geometry": {
    "type": "Point",
    "coordinates": [
      -85.65,
      35.3667
    ]
  },
  "type": "Feature",
  "properties": {
    "hierarchy": [
      "tgn:2099404",
      "tgn:1000001",
      "tgn:2099400",
      "tgn:7012149",
      "tgn:2001867",
      "tgn:7007825",
      "tgn:7029392"
    ],
    "placetype": [
      "aat:300000745"
    ],
    "id": 2099404,
    "name:xx": "Gruetli"
  }
}
