{
  "geometry": {
    "type": "Point",
    "coordinates": [
      18.1667,
      -0.0667
    ]
  },
  "type": "Feature",
  "properties": {
    "hierarchy": [
      "tgn:1089562",
      "tgn:7001242",
      "tgn:7016654",
      "tgn:1000159",
      "tgn:7029392"
    ],
    "placetype": [
      "aat:300008347"
    ],
    "id": 1089562,
    "name:xx": "Wendji"
  }
}
