{
  "geometry": {
    "type": "Point",
    "coordinates": [
      -92.4333,
      38.9833
    ]
  },
  "type": "Feature",
  "properties": {
    "hierarchy": [
      "tgn:2385429",
      "tgn:1000001",
      "tgn:1002190",
      "tgn:7012149",
      "tgn:7007523",
      "tgn:7029392"
    ],
    "placetype": [
      "aat:300008699"
    ],
    "id": 2385429,
    "name:xx": "Henderson Branch"
  }
}
