{
  "geometry": {
    "type": "Point",
    "coordinates": [
      -73.5333,
      41.5833
    ]
  },
  "type": "Feature",
  "properties": {
    "hierarchy": [
      "tgn:2651641",
      "tgn:1000001",
      "tgn:1002347",
      "tgn:7012149",
      "tgn:7007568",
      "tgn:7029392"
    ],
    "placetype": [
      "aat:300008798"
    ],
    "id": 2651641,
    "name:xx": "Seeley Hill"
  }
}
