{
  "type": "FeatureCollection",
  "features": [
    {
      "geometry": {
        "type": "Point",
        "coordinates": [
          31.639164,
          31.244735
        ]
      },
      "type": "Feature",
      "properties": {
        "hierarchy": [
          "tgn:7543480",
          "tgn:7001242",
          "tgn:1001059",
          "tgn:7016833",
          "tgn:7029392"
        ],
        "placetype": [
          "aat:300000206"
        ],
        "name:en": "'Izbat al Minyāwī",
        "id": 7543480
      }
    },
    {
      "geometry": {
        "type": "Point",
        "coordinates": [
          31.628276,
          31.232982
        ]
      },
      "type": "Feature",
      "properties": {
        "hierarchy": [
          "tgn:7543481",
          "tgn:7001242",
          "tgn:7016833",
          "tgn:1001225",
          "tgn:7029392"
        ],
        "placetype": [
          "aat:300000206"
        ],
        "name:en": "'Izbat Shitā",
        "id": 7543481
      }
    },
    {
      "geometry": {
        "type": "Point",
        "coordinates": [
          31.619374,
          31.240112
        ]
      },
      "type": "Feature",
      "properties": {
        "hierarchy": [
          "tgn:7543482",
          "tgn:7001242",
          "tgn:7016833",
          "tgn:1001225",
          "tgn:7029392"
        ],
        "placetype": [
          "aat:300000206"
        ],
        "name:en": "'Izbat Muţāwi'",
        "id": 7543482
      }
    },
    {
      "geometry": {
        "type": "Point",
        "coordinates": [
          31.602109,
          31.247093
        ]
      },
      "type": "Feature",
      "properties": {
        "hierarchy": [
          "tgn:7543483",
          "tgn:7001242",
          "tgn:1001059",
          "tgn:7016833",
          "tgn:7029392"
        ],
        "placetype": [
          "aat:300000206"
        ],
        "name:en": "'Izbat Muḩammad Ḩasan al 'Abd",
        "id": 7543483
      }
    },
    {
      "geometry": {
        "type": "Point",
        "coordinates": [
          31.612452,
          31.243906
        ]
      },
      "type": "Feature",
      "properties": {
        "hierarchy": [
          "tgn:7543484",
          "tgn:7001242",
          "tgn:1001059",
          "tgn:7016833",
          "tgn:7029392"
        ],
        "placetype": [
          "aat:300008347"
        ],
        "name:en": "'Izbat al 'Askar",
        "id": 7543484
      }
    },
    {
      "geometry": {
        "type": "Point",
        "coordinates": [
          31.513308,
          31.194317
        ]
      },
      "type": "Feature",
      "properties": {
        "hierarchy": [
          "tgn:7543485",
          "tgn:7001242",
          "tgn:1001059",
          "tgn:7016833",
          "tgn:7029392"
        ],
        "placetype": [
          "aat:300006075"
        ],
        "name:en": "Tir'at al Balāmūn",
        "id": 7543485
      }
    },
    {
      "geometry": {
        "type": "Point",
        "coordinates": [
          31.591853,
          31.248506
        ]
      },
      "type": "Feature",
      "properties": {
        "hierarchy": [
          "tgn:7543486",
          "tgn:7001242",
          "tgn:1001059",
          "tgn:7016833",
          "tgn:7029392"
        ],
        "placetype": [
          "aat:300000206"
        ],
        "name:en": "'Izbat Rūsyā",
        "id": 7543486
      }
    },
    {
      "geometry": {
        "type": "Point",
        "coordinates": [
          31.593542,
          31.245119
        ]
      },
      "type": "Feature",
      "properties": {
        "hierarchy": [
          "tgn:7543487",
          "tgn:7001242",
          "tgn:1001059",
          "tgn:7016833",
          "tgn:7029392"
        ],
        "placetype": [
          "aat:300008347"
        ],
        "name:en": "'Izbat Yazbak",
        "id": 7543487
      }
    },
    {
      "geometry": {
        "type": "Point",
        "coordinates": [
          31.585638,
          31.239546
        ]
      },
      "type": "Feature",
      "properties": {
        "hierarchy": [
          "tgn:7543488",
          "tgn:7001242",
          "tgn:1001059",
          "tgn:7016833",
          "tgn:7029392"
        ],
        "placetype": [
          "aat:300008347"
        ],
        "name:en": "'Izbat Ţāhir al Lūzī",
        "id": 7543488
      }
    },
    {
      "geometry": {
        "type": "Point",
        "coordinates": [
          31.572396,
          31.237132
        ]
      },
      "type": "Feature",
      "properties": {
        "hierarchy": [
          "tgn:7543489",
          "tgn:7001242",
          "tgn:1001059",
          "tgn:7016833",
          "tgn:7029392"
        ],
        "placetype": [
          "aat:300000206"
        ],
        "name:en": "'Izbat al Işlāḩ",
        "id": 7543489
      }
    }
  ]
}
