{
  "geometry": {
    "type": "Point",
    "coordinates": [
      122.8167,
      9.3333
    ]
  },
  "type": "Feature",
  "properties": {
    "hierarchy": [
      "tgn:1113933",
      "tgn:1000004",
      "tgn:1001449",
      "tgn:1000135",
      "tgn:7029392"
    ],
    "placetype": [
      "aat:300132316"
    ],
    "id": 1113933,
    "name:xx": "Tolong Bay"
  }
}
