{
  "geometry": {
    "type": "Point",
    "coordinates": [
      -91.3333,
      39.3167
    ]
  },
  "type": "Feature",
  "properties": {
    "hierarchy": [
      "tgn:2643261",
      "tgn:1000001",
      "tgn:7012149",
      "tgn:1002787",
      "tgn:7007523",
      "tgn:7029392"
    ],
    "placetype": [
      "aat:300008706"
    ],
    "id": 2643261,
    "name:xx": "Sandy Creek"
  }
}
