{
  "geometry": {
    "type": "Point",
    "coordinates": [
      32.383333,
      22.65
    ]
  },
  "type": "Feature",
  "properties": {
    "hierarchy": [
      "tgn:7521084",
      "tgn:7001242",
      "tgn:7016833",
      "tgn:7000122",
      "tgn:7029392"
    ],
    "placetype": [
      "aat:300008347"
    ],
    "name:en": "Al Mālikī",
    "id": 7521084
  }
}
