{
  "geometry": {
    "type": "Point",
    "coordinates": [
      -77.3167,
      42.3667
    ]
  },
  "type": "Feature",
  "properties": {
    "hierarchy": [
      "tgn:2248114",
      "tgn:1000001",
      "tgn:7012149",
      "tgn:1002920",
      "tgn:7007568",
      "tgn:7029392"
    ],
    "placetype": [
      "aat:300008699"
    ],
    "id": 2248114,
    "name:xx": "Cold Brook"
  }
}
