{
  "geometry": {
    "type": "Point",
    "coordinates": [
      -105.6333,
      35.35
    ]
  },
  "type": "Feature",
  "properties": {
    "hierarchy": [
      "tgn:2473234",
      "tgn:1000001",
      "tgn:7012149",
      "tgn:2001453",
      "tgn:7007566",
      "tgn:7029392"
    ],
    "placetype": [
      "aat:300006191"
    ],
    "id": 2473234,
    "name:xx": "Lower Barbero Tank"
  }
}
