{
  "type": "FeatureCollection",
  "features": [
    {
      "geometry": {
        "type": "Point",
        "coordinates": [
          -104.6,
          45.2667
        ]
      },
      "type": "Feature",
      "properties": {
        "hierarchy": [
          "tgn:2242911",
          "tgn:1000001",
          "tgn:2001265",
          "tgn:7012149",
          "tgn:7007524",
          "tgn:7029392"
        ],
        "placetype": [
          "aat:300008699"
        ],
        "id": 2242911,
        "name:xx": "Clear Fork"
      }
    },
    {
      "geometry": {
        "type": "Point",
        "coordinates": [
          -80.95,
          40.3167
        ]
      },
      "type": "Feature",
      "properties": {
        "hierarchy": [
          "tgn:2242912",
          "tgn:1000001",
          "tgn:7012149",
          "tgn:1002459",
          "tgn:7007706",
          "tgn:7029392"
        ],
        "placetype": [
          "aat:300008699"
        ],
        "id": 2242912,
        "name:xx": "Clear Fork"
      }
    },
    {
      "geometry": {
        "type": "Point",
        "coordinates": [
          -82.2833,
          38.8167
        ]
      },
      "type": "Feature",
      "properties": {
        "hierarchy": [
          "tgn:2242913",
          "tgn:1000001",
          "tgn:7012149",
          "tgn:2001612",
          "tgn:7007706",
          "tgn:7029392"
        ],
        "placetype": [
          "aat:300008699"
        ],
        "id": 2242913,
        "name:xx": "Clear Fork"
      }
    },
    {
      "geometry": {
        "type": "Point",
        "coordinates": [
          -82.5333,
          38.8167
        ]
      },
      "type": "Feature",
      "properties": {
        "hierarchy": [
          "tgn:2242914",
          "tgn:1000001",
          "tgn:7012149",
          "tgn:7007706",
          "tgn:7029392"
        ],
        "placetype": [
          "aat:300008699"
        ],
        "id": 2242914,
        "name:xx": "Clear Fork"
      }
    },
    {
      "geometry": {
        "type": "Point",
        "coordinates": [
          -82.5333,
          39.5333
        ]
      },
      "type": "Feature",
      "properties": {
        "hierarchy": [
          "tgn:2242915",
          "tgn:1000001",
          "tgn:7012149",
          "tgn:2001613",
          "tgn:7007706",
          "tgn:7029392"
        ],
        "placetype": [
          "aat:300008699"
        ],
        "id": 2242915,
        "name:xx": "Clear Fork"
      }
    },
    {
      "geometry": {
        "type": "Point",
        "coordinates": [
          -121.7833,
          45.4167
        ]
      },
      "type": "Feature",
      "properties": {
        "hierarchy": [
          "tgn:2242916",
          "tgn:1000001",
          "tgn:1002270",
          "tgn:7012149",
          "tgn:7007708",
          "tgn:7029392"
        ],
        "placetype": [
          "aat:300008699"
        ],
        "id": 2242916,
        "name:xx": "Clear Fork"
      }
    },
    {
      "geometry": {
        "type": "Point",
        "coordinates": [
          -82.2667,
          36.1333
        ]
      },
      "type": "Feature",
      "properties": {
        "hierarchy": [
          "tgn:2242917",
          "tgn:1000001",
          "tgn:7012149",
          "tgn:2001922",
          "tgn:7007825",
          "tgn:7029392"
        ],
        "placetype": [
          "aat:300008699"
        ],
        "id": 2242917,
        "name:xx": "Clear Fork"
      }
    },
    {
      "geometry": {
        "type": "Point",
        "coordinates": [
          -82.5,
          36.3667
        ]
      },
      "type": "Feature",
      "properties": {
        "hierarchy": [
          "tgn:2242918",
          "tgn:1000001",
          "tgn:7012149",
          "tgn:2001926",
          "tgn:7007825",
          "tgn:7029392"
        ],
        "placetype": [
          "aat:300008699"
        ],
        "id": 2242918,
        "name:xx": "Clear Fork"
      }
    },
    {
      "geometry": {
        "type": "Point",
        "coordinates": [
          -83.6667,
          35.7167
        ]
      },
      "type": "Feature",
      "properties": {
        "hierarchy": [
          "tgn:2242919",
          "tgn:1000001",
          "tgn:7012149",
          "tgn:2001914",
          "tgn:7007825",
          "tgn:7029392"
        ],
        "placetype": [
          "aat:300008699"
        ],
        "id": 2242919,
        "name:xx": "Clear Fork"
      }
    }
  ]
}
