{
  "geometry": {
    "type": "Point",
    "coordinates": [
      -75.8833,
      42.5667
    ]
  },
  "type": "Feature",
  "properties": {
    "hierarchy": [
      "tgn:2072673",
      "tgn:1000001",
      "tgn:1002302",
      "tgn:7012149",
      "tgn:7007568",
      "tgn:7029392"
    ],
    "placetype": [
      "aat:300008347"
    ],
    "id": 2072673,
    "name:xx": "Taylor"
  }
}
