{
  "geometry": {
    "type": "Point",
    "coordinates": [
      -87.25,
      32.2833
    ]
  },
  "type": "Feature",
  "properties": {
    "hierarchy": [
      "tgn:2501642",
      "tgn:7002659",
      "tgn:1000001",
      "tgn:7012149",
      "tgn:2000023",
      "tgn:7029392"
    ],
    "placetype": [
      "aat:300006191"
    ],
    "id": 2501642,
    "name:xx": "McHugh Lake"
  }
}
