{
  "geometry": {
    "type": "Point",
    "coordinates": [
      -80.05,
      39.4167
    ]
  },
  "type": "Feature",
  "properties": {
    "hierarchy": [
      "tgn:2468947",
      "tgn:1000001",
      "tgn:7012149",
      "tgn:2002275",
      "tgn:7013961",
      "tgn:7029392"
    ],
    "placetype": [
      "aat:300008699"
    ],
    "id": 2468947,
    "name:xx": "Long Run"
  }
}
