{
  "geometry": {
    "type": "Point",
    "coordinates": [
      115.55,
      33.55
    ]
  },
  "type": "Feature",
  "properties": {
    "hierarchy": [
      "tgn:1069808",
      "tgn:7002075",
      "tgn:1000004",
      "tgn:1000111",
      "tgn:7029392"
    ],
    "placetype": [
      "aat:300008347"
    ],
    "id": 1069808,
    "name:xx": "Lidesi"
  }
}
