{
  "geometry": {
    "type": "Point",
    "coordinates": [
      -130.7833,
      55.4667
    ]
  },
  "type": "Feature",
  "properties": {
    "hierarchy": [
      "tgn:2739590",
      "tgn:7006450",
      "tgn:1000001",
      "tgn:7012149",
      "tgn:2000082",
      "tgn:7029392"
    ],
    "placetype": [
      "aat:300008680"
    ],
    "id": 2739590,
    "name:xx": "Upper Checats Lake"
  }
}
