{
  "geometry": {
    "type": "Point",
    "coordinates": [
      -75.6333,
      41.3833
    ]
  },
  "type": "Feature",
  "properties": {
    "hierarchy": [
      "tgn:2527900",
      "tgn:1000001",
      "tgn:7012149",
      "tgn:1002564",
      "tgn:7007710",
      "tgn:7029392"
    ],
    "placetype": [
      "aat:300006191"
    ],
    "id": 2527900,
    "name:xx": "Mountain Lake"
  }
}
