{
  "geometry": {
    "type": "Point",
    "coordinates": [
      -109.7333,
      34.1833
    ]
  },
  "type": "Feature",
  "properties": {
    "hierarchy": [
      "tgn:2779536",
      "tgn:2000090",
      "tgn:1000001",
      "tgn:7006451",
      "tgn:7012149",
      "tgn:7029392"
    ],
    "placetype": [
      "aat:300008798"
    ],
    "id": 2779536,
    "name:xx": "Wolf Mountain"
  }
}
