{
  "geometry": {
    "type": "Point",
    "coordinates": [
      79.690859,
      27.658108
    ]
  },
  "type": "Feature",
  "properties": {
    "hierarchy": [
      "tgn:7560086",
      "tgn:1000004",
      "tgn:7000198",
      "tgn:7016722",
      "tgn:7029392"
    ],
    "placetype": [
      "aat:300008347"
    ],
    "name:en": "Karheran ki Madaiyān",
    "id": 7560086
  }
}
