{
  "type": "FeatureCollection",
  "features": [
    {
      "geometry": {
        "type": "Point",
        "coordinates": [
          -76.9833,
          38.8
        ]
      },
      "type": "Feature",
      "properties": {
        "hierarchy": [
          "tgn:2047091",
          "tgn:1000001",
          "tgn:2124001",
          "tgn:7012149",
          "tgn:7007516",
          "tgn:7029392"
        ],
        "placetype": [
          "aat:300008347"
        ],
        "id": 2047091,
        "name:xx": "Forest Heights"
      }
    },
    {
      "geometry": {
        "type": "Point",
        "coordinates": [
          -76.3833,
          39.5833
        ]
      },
      "type": "Feature",
      "properties": {
        "hierarchy": [
          "tgn:2047092",
          "tgn:1000001",
          "tgn:7016102",
          "tgn:7012149",
          "tgn:7007516",
          "tgn:7029392"
        ],
        "placetype": [
          "aat:300008347"
        ],
        "id": 2047092,
        "name:xx": "Forest Hill"
      }
    },
    {
      "geometry": {
        "type": "Point",
        "coordinates": [
          -76.75,
          39.6
        ]
      },
      "type": "Feature",
      "properties": {
        "hierarchy": [
          "tgn:2047096",
          "tgn:7016099",
          "tgn:1000001",
          "tgn:7012149",
          "tgn:7007516",
          "tgn:7029392"
        ],
        "placetype": [
          "aat:300008347",
          "aat:300387210"
        ],
        "id": 2047096,
        "name:xx": "Foreston"
      }
    },
    {
      "geometry": {
        "type": "Point",
        "coordinates": [
          -76.8667,
          38.8333
        ]
      },
      "type": "Feature",
      "properties": {
        "hierarchy": [
          "tgn:2047097",
          "tgn:1000001",
          "tgn:2124001",
          "tgn:7012149",
          "tgn:7007516",
          "tgn:7029392"
        ],
        "placetype": [
          "aat:300008347"
        ],
        "id": 2047097,
        "name:xx": "Forestville"
      }
    }
  ]
}
