{
  "geometry": {
    "type": "Point",
    "coordinates": [
      -94.1667,
      41.9667
    ]
  },
  "type": "Feature",
  "properties": {
    "hierarchy": [
      "tgn:2421980",
      "tgn:1000001",
      "tgn:7012149",
      "tgn:7007253",
      "tgn:7029392"
    ],
    "placetype": [
      "aat:300008706"
    ],
    "id": 2421980,
    "name:xx": "Jim Creek"
  }
}
