{
  "geometry": {
    "type": "Point",
    "coordinates": [
      -77.45,
      40.8333
    ]
  },
  "type": "Feature",
  "properties": {
    "hierarchy": [
      "tgn:2732135",
      "tgn:1000001",
      "tgn:1002249",
      "tgn:7012149",
      "tgn:7007710",
      "tgn:7029392"
    ],
    "placetype": [
      "aat:300008798"
    ],
    "id": 2732135,
    "name:xx": "Tunnel Mountain"
  }
}
