{
  "geometry": {
    "type": "Point",
    "coordinates": [
      -117.45,
      46.4333
    ]
  },
  "type": "Feature",
  "properties": {
    "hierarchy": [
      "tgn:2570386",
      "tgn:1000001",
      "tgn:7012149",
      "tgn:7007920",
      "tgn:7029392"
    ],
    "placetype": [
      "aat:300008761"
    ],
    "id": 2570386,
    "name:xx": "Pataha Valley"
  }
}
