{
  "geometry": {
    "type": "Point",
    "coordinates": [
      -88.3333,
      35.5167
    ]
  },
  "type": "Feature",
  "properties": {
    "hierarchy": [
      "tgn:2471035",
      "tgn:1000001",
      "tgn:7012149",
      "tgn:2001875",
      "tgn:7007825",
      "tgn:7029392"
    ],
    "placetype": [
      "aat:300008706"
    ],
    "id": 2471035,
    "name:xx": "Lost Creek"
  }
}
