{
  "geometry": {
    "type": "Point",
    "coordinates": [
      -118.1667,
      42.0167
    ]
  },
  "type": "Feature",
  "properties": {
    "hierarchy": [
      "tgn:2630294",
      "tgn:1000001",
      "tgn:7012149",
      "tgn:2001718",
      "tgn:7007708",
      "tgn:7029392"
    ],
    "placetype": [
      "aat:300006191"
    ],
    "id": 2630294,
    "name:xx": "Rough Hole Reservoir"
  }
}
