{
  "geometry": {
    "type": "Point",
    "coordinates": [
      39.4333,
      13.9667
    ]
  },
  "type": "Feature",
  "properties": {
    "hierarchy": [
      "tgn:1089846",
      "tgn:7001242",
      "tgn:1001570",
      "tgn:7000489",
      "tgn:7029392"
    ],
    "placetype": [
      "aat:300008347"
    ],
    "id": 1089846,
    "name:xx": "Hawzēn"
  }
}
