{
  "geometry": {
    "type": "Point",
    "coordinates": [
      34.69743,
      25.385328
    ]
  },
  "type": "Feature",
  "properties": {
    "hierarchy": [
      "tgn:7526719",
      "tgn:7001242",
      "tgn:7001311",
      "tgn:7016833",
      "tgn:7029392"
    ],
    "placetype": [
      "aat:300379998"
    ],
    "name:en": "Wasa'at, Wâdi",
    "id": 7526719
  }
}
