{
  "geometry": {
    "type": "Point",
    "coordinates": [
      89.3333,
      21.6667
    ]
  },
  "type": "Feature",
  "properties": {
    "hierarchy": [
      "tgn:1135784",
      "tgn:1000004",
      "tgn:7000190",
      "tgn:1000105",
      "tgn:7029392"
    ],
    "placetype": [
      "aat:300387055"
    ],
    "id": 1135784,
    "name:xx": "Mālancha"
  }
}
