{
  "geometry": {
    "type": "Point",
    "coordinates": [
      -105.4167,
      35.3333
    ]
  },
  "type": "Feature",
  "properties": {
    "hierarchy": [
      "tgn:2067650",
      "tgn:1000001",
      "tgn:7012149",
      "tgn:2001453",
      "tgn:7007566",
      "tgn:7029392"
    ],
    "placetype": [
      "aat:300008347",
      "aat:300387210"
    ],
    "id": 2067650,
    "name:xx": "Upper Pueblo"
  }
}
