{
  "geometry": {
    "type": "Point",
    "coordinates": [
      -71.35,
      42.7167
    ]
  },
  "type": "Feature",
  "properties": {
    "hierarchy": [
      "tgn:1135249",
      "tgn:1000001",
      "tgn:7012149",
      "tgn:7029392"
    ],
    "placetype": [
      "aat:300008703"
    ],
    "id": 1135249,
    "name:xx": "Gumpas Pond Brook"
  }
}
