{
  "geometry": {
    "type": "Point",
    "coordinates": [
      -121.9833,
      37.1333
    ]
  },
  "type": "Feature",
  "properties": {
    "hierarchy": [
      "tgn:2346404",
      "tgn:1000001",
      "tgn:7012149",
      "tgn:7007157",
      "tgn:7029392"
    ],
    "placetype": [
      "aat:300266640"
    ],
    "id": 2346404,
    "name:xx": "Gatos, Cuesta de los"
  }
}
