{
  "geometry": {
    "type": "Point",
    "coordinates": [
      -82.0833,
      30.2333
    ]
  },
  "type": "Feature",
  "properties": {
    "hierarchy": [
      "tgn:2444027",
      "tgn:2000257",
      "tgn:1000001",
      "tgn:7012149",
      "tgn:7007240",
      "tgn:7029392"
    ],
    "placetype": [
      "aat:300008347"
    ],
    "id": 2444027,
    "name:xx": "LaBuena"
  }
}
