{
  "geometry": {
    "type": "Point",
    "coordinates": [
      -109.3833,
      47.25
    ]
  },
  "type": "Feature",
  "properties": {
    "hierarchy": [
      "tgn:2545546",
      "tgn:1000001",
      "tgn:7012149",
      "tgn:2001273",
      "tgn:7007524",
      "tgn:7029392"
    ],
    "placetype": [
      "aat:300008706"
    ],
    "id": 2545546,
    "name:xx": "North Fork Bull Creek"
  }
}
