{
  "geometry": {
    "type": "Point",
    "coordinates": [
      -75.9667,
      41.3667
    ]
  },
  "type": "Feature",
  "properties": {
    "hierarchy": [
      "tgn:2316472",
      "tgn:1000001",
      "tgn:7012149",
      "tgn:1002612",
      "tgn:7007710",
      "tgn:7029392"
    ],
    "placetype": [
      "aat:300006191"
    ],
    "id": 2316472,
    "name:xx": "Elstons Pond"
  }
}
