{
  "geometry": {
    "type": "Point",
    "coordinates": [
      -93.9333,
      43.8833
    ]
  },
  "type": "Feature",
  "properties": {
    "hierarchy": [
      "tgn:2260941",
      "tgn:1000001",
      "tgn:2001005",
      "tgn:7012149",
      "tgn:7007521",
      "tgn:7029392"
    ],
    "placetype": [
      "aat:300006075"
    ],
    "id": 2260941,
    "name:xx": "County Ditch Number Thirtyfive"
  }
}
