{
  "geometry": {
    "type": "Point",
    "coordinates": [
      -73.1333,
      42.5833
    ]
  },
  "type": "Feature",
  "properties": {
    "hierarchy": [
      "tgn:2137708",
      "tgn:7013388",
      "tgn:1000001",
      "tgn:7012149",
      "tgn:7007517",
      "tgn:7029392"
    ],
    "placetype": [
      "aat:300008347"
    ],
    "id": 2137708,
    "name:xx": "Arnoldsville"
  }
}
