{
  "geometry": {
    "type": "Point",
    "coordinates": [
      -84.4667,
      39.8167
    ]
  },
  "type": "Feature",
  "properties": {
    "hierarchy": [
      "tgn:2445841",
      "tgn:1000001",
      "tgn:7012149",
      "tgn:7007706",
      "tgn:7029392"
    ],
    "placetype": [
      "aat:300008699"
    ],
    "id": 2445841,
    "name:xx": "Lesley Run"
  }
}
