{
  "geometry": {
    "type": "Point",
    "coordinates": [
      121.55,
      25.05
    ]
  },
  "type": "Feature",
  "properties": {
    "hierarchy": [
      "tgn:7492919",
      "tgn:1000004",
      "tgn:1000959",
      "tgn:1000141",
      "tgn:7029392"
    ],
    "placetype": [
      "aat:300387173"
    ],
    "id": 7492919,
    "name:xx": "Songshan Qu"
  }
}
