{
  "geometry": {
    "type": "Point",
    "coordinates": [
      38.2333,
      40.95
    ]
  },
  "type": "Feature",
  "properties": {
    "hierarchy": [
      "tgn:1086123",
      "tgn:1001258",
      "tgn:1000004",
      "tgn:7018454",
      "tgn:1000144",
      "tgn:7029392"
    ],
    "placetype": [
      "aat:300008347"
    ],
    "id": 1086123,
    "name:xx": "Bulancak"
  }
}
