{
  "geometry": {
    "type": "Point",
    "coordinates": [
      -95.9333,
      47.1667
    ]
  },
  "type": "Feature",
  "properties": {
    "hierarchy": [
      "tgn:2055716",
      "tgn:1000001",
      "tgn:7012149",
      "tgn:2001042",
      "tgn:7007521",
      "tgn:7029392"
    ],
    "placetype": [
      "aat:300008347"
    ],
    "id": 2055716,
    "name:xx": "Waubun"
  }
}
