{
  "type": "FeatureCollection",
  "features": [
    {
      "geometry": {
        "type": "Point",
        "coordinates": [
          -105.4,
          26.866667
        ]
      },
      "type": "Feature",
      "properties": {
        "hierarchy": [
          "tgn:7349480",
          "tgn:1001853",
          "tgn:1000001",
          "tgn:7005560",
          "tgn:7029392"
        ],
        "placetype": [
          "aat:300008347"
        ],
        "id": 7349480,
        "name:xx": "Aguaje"
      }
    },
    {
      "geometry": {
        "type": "Point",
        "coordinates": [
          -104.833333,
          26.266667
        ]
      },
      "type": "Feature",
      "properties": {
        "hierarchy": [
          "tgn:7349481",
          "tgn:7005583",
          "tgn:1000001",
          "tgn:7005560",
          "tgn:7029392"
        ],
        "placetype": [
          "aat:300008347"
        ],
        "id": 7349481,
        "name:xx": "Aguaje"
      }
    },
    {
      "geometry": {
        "type": "Point",
        "coordinates": [
          -108.033333,
          25.366667
        ]
      },
      "type": "Feature",
      "properties": {
        "hierarchy": [
          "tgn:7349482",
          "tgn:1000001",
          "tgn:7005595",
          "tgn:7005560",
          "tgn:7029392"
        ],
        "placetype": [
          "aat:300008347"
        ],
        "id": 7349482,
        "name:xx": "Aguaje"
      }
    },
    {
      "geometry": {
        "type": "Point",
        "coordinates": [
          -99.65,
          22.033333
        ]
      },
      "type": "Feature",
      "properties": {
        "hierarchy": [
          "tgn:7349483",
          "tgn:1000001",
          "tgn:7005594",
          "tgn:7005560",
          "tgn:7029392"
        ],
        "placetype": [
          "aat:300008347"
        ],
        "id": 7349483,
        "name:xx": "Aguaje"
      }
    },
    {
      "geometry": {
        "type": "Point",
        "coordinates": [
          -100.616667,
          21.966667
        ]
      },
      "type": "Feature",
      "properties": {
        "hierarchy": [
          "tgn:7349484",
          "tgn:1000001",
          "tgn:7005594",
          "tgn:7005560",
          "tgn:7029392"
        ],
        "placetype": [
          "aat:300008347"
        ],
        "id": 7349484,
        "name:xx": "Aguaje"
      }
    },
    {
      "geometry": {
        "type": "Point",
        "coordinates": [
          -98.266667,
          16.316667
        ]
      },
      "type": "Feature",
      "properties": {
        "hierarchy": [
          "tgn:7349485",
          "tgn:1000001",
          "tgn:7005591",
          "tgn:7005560",
          "tgn:7029392"
        ],
        "placetype": [
          "aat:300008347"
        ],
        "id": 7349485,
        "name:xx": "Aguaje"
      }
    },
    {
      "geometry": {
        "type": "Point",
        "coordinates": [
          -95,
          16.25
        ]
      },
      "type": "Feature",
      "properties": {
        "hierarchy": [
          "tgn:7349486",
          "tgn:1000001",
          "tgn:7005591",
          "tgn:7005560",
          "tgn:7029392"
        ],
        "placetype": [
          "aat:300008347"
        ],
        "id": 7349486,
        "name:xx": "Aguaje"
      }
    },
    {
      "geometry": {
        "type": "Point",
        "coordinates": [
          -105.166667,
          26.866667
        ]
      },
      "type": "Feature",
      "properties": {
        "hierarchy": [
          "tgn:7349487",
          "tgn:7005581",
          "tgn:1000001",
          "tgn:7005560",
          "tgn:7029392"
        ],
        "placetype": [
          "aat:300387007"
        ],
        "id": 7349487,
        "name:xx": "Aguaje"
      }
    },
    {
      "geometry": {
        "type": "Point",
        "coordinates": [
          -94.866667,
          16.25
        ]
      },
      "type": "Feature",
      "properties": {
        "hierarchy": [
          "tgn:7349488",
          "tgn:1000001",
          "tgn:7005591",
          "tgn:7005560",
          "tgn:7029392"
        ],
        "placetype": [
          "aat:300387007"
        ],
        "id": 7349488,
        "name:xx": "Aguaje"
      }
    },
    {
      "geometry": {
        "type": "Point",
        "coordinates": [
          -103.55,
          20.966667
        ]
      },
      "type": "Feature",
      "properties": {
        "hierarchy": [
          "tgn:7349489",
          "tgn:7005586",
          "tgn:1000001",
          "tgn:7005560",
          "tgn:7029392"
        ],
        "placetype": [
          "aat:300266554",
          "aat:300008699"
        ],
        "id": 7349489,
        "name:xx": "Agua Hondo"
      }
    }
  ]
}
