{
  "type": "FeatureCollection",
  "features": [
    {
      "geometry": {
        "type": "Point",
        "coordinates": [
          -42.8,
          -20.8667
        ]
      },
      "type": "Feature",
      "properties": {
        "hierarchy": [
          "tgn:1136520",
          "tgn:7006237",
          "tgn:1000047",
          "tgn:7002457",
          "tgn:1000002",
          "tgn:7029392"
        ],
        "placetype": [
          "aat:300008347"
        ],
        "id": 1136520,
        "name:xx": "Coimbra"
      }
    },
    {
      "geometry": {
        "type": "Point",
        "coordinates": [
          -48.05,
          -14.2
        ]
      },
      "type": "Feature",
      "properties": {
        "hierarchy": [
          "tgn:1136521",
          "tgn:7012827",
          "tgn:7002454",
          "tgn:1000047",
          "tgn:1000002",
          "tgn:7029392"
        ],
        "placetype": [
          "aat:300008347"
        ],
        "id": 1136521,
        "name:xx": "Colinas"
      }
    },
    {
      "geometry": {
        "type": "Point",
        "coordinates": [
          -52.1667,
          -27.2167
        ]
      },
      "type": "Feature",
      "properties": {
        "hierarchy": [
          "tgn:1136522",
          "tgn:7006262",
          "tgn:1000047",
          "tgn:7002458",
          "tgn:1000002",
          "tgn:7029392"
        ],
        "placetype": [
          "aat:300008347"
        ],
        "id": 1136522,
        "name:xx": "Concórdia"
      }
    },
    {
      "geometry": {
        "type": "Point",
        "coordinates": [
          -38.4667,
          -7.5
        ]
      },
      "type": "Feature",
      "properties": {
        "hierarchy": [
          "tgn:1136523",
          "tgn:7005439",
          "tgn:1000047",
          "tgn:7002455",
          "tgn:1000002",
          "tgn:7029392"
        ],
        "placetype": [
          "aat:300008347"
        ],
        "id": 1136523,
        "name:xx": "Conceição"
      }
    },
    {
      "geometry": {
        "type": "Point",
        "coordinates": [
          -35.85,
          -7.0167
        ]
      },
      "type": "Feature",
      "properties": {
        "hierarchy": [
          "tgn:1136524",
          "tgn:7005439",
          "tgn:1000047",
          "tgn:7002455",
          "tgn:1000002",
          "tgn:7029392"
        ],
        "placetype": [
          "aat:300008347"
        ],
        "id": 1136524,
        "name:xx": "Esperança"
      }
    },
    {
      "geometry": {
        "type": "Point",
        "coordinates": [
          -44.3,
          -22.45
        ]
      },
      "type": "Feature",
      "properties": {
        "hierarchy": [
          "tgn:1136525",
          "tgn:1001942",
          "tgn:1000047",
          "tgn:7002457",
          "tgn:1000002",
          "tgn:7029392"
        ],
        "placetype": [
          "aat:300008347"
        ],
        "id": 1136525,
        "name:xx": "Floriano"
      }
    },
    {
      "geometry": {
        "type": "Point",
        "coordinates": [
          -35.6,
          -9.5333
        ]
      },
      "type": "Feature",
      "properties": {
        "hierarchy": [
          "tgn:1136526",
          "tgn:7016581",
          "tgn:1000047",
          "tgn:7002455",
          "tgn:1000002",
          "tgn:7029392"
        ],
        "placetype": [
          "aat:300008347"
        ],
        "id": 1136526,
        "name:xx": "Floriano Peixoto"
      }
    },
    {
      "geometry": {
        "type": "Point",
        "coordinates": [
          -54.25,
          -24.0833
        ]
      },
      "type": "Feature",
      "properties": {
        "hierarchy": [
          "tgn:1136527",
          "tgn:1001925",
          "tgn:1000047",
          "tgn:7002458",
          "tgn:1000002",
          "tgn:7029392"
        ],
        "placetype": [
          "aat:300008347"
        ],
        "id": 1136527,
        "name:xx": "Guaíra"
      }
    },
    {
      "geometry": {
        "type": "Point",
        "coordinates": [
          -51.6667,
          -22.95
        ]
      },
      "type": "Feature",
      "properties": {
        "hierarchy": [
          "tgn:1136528",
          "tgn:1001925",
          "tgn:1000047",
          "tgn:7002458",
          "tgn:1000002",
          "tgn:7029392"
        ],
        "placetype": [
          "aat:300008347"
        ],
        "id": 1136528,
        "name:xx": "Guaraci"
      }
    },
    {
      "geometry": {
        "type": "Point",
        "coordinates": [
          -43.2,
          -22.7167
        ]
      },
      "type": "Feature",
      "properties": {
        "hierarchy": [
          "tgn:1136529",
          "tgn:1001942",
          "tgn:1000047",
          "tgn:7002457",
          "tgn:1000002",
          "tgn:7029392"
        ],
        "placetype": [
          "aat:300008347"
        ],
        "id": 1136529,
        "name:xx": "Ipiranga"
      }
    }
  ]
}
