{
  "geometry": {
    "type": "Point",
    "coordinates": [
      -123.95,
      40.2167
    ]
  },
  "type": "Feature",
  "properties": {
    "hierarchy": [
      "tgn:2496847",
      "tgn:1000001",
      "tgn:7012149",
      "tgn:2000181",
      "tgn:7007157",
      "tgn:7029392"
    ],
    "placetype": [
      "aat:300008761"
    ],
    "id": 2496847,
    "name:xx": "Mattole Canyon"
  }
}
