{
  "geometry": {
    "type": "Point",
    "coordinates": [
      -93.1333,
      31.7333
    ]
  },
  "type": "Feature",
  "properties": {
    "hierarchy": [
      "tgn:2138470",
      "tgn:1000001",
      "tgn:7012149",
      "tgn:2000888",
      "tgn:7007256",
      "tgn:7029392"
    ],
    "placetype": [
      "aat:300008699"
    ],
    "id": 2138470,
    "name:xx": "Ash Bayou"
  }
}
