{
  "geometry": {
    "type": "Point",
    "coordinates": [
      -80.5167,
      35.65
    ]
  },
  "type": "Feature",
  "properties": {
    "hierarchy": [
      "tgn:2341585",
      "tgn:1000001",
      "tgn:7012149",
      "tgn:2001536",
      "tgn:7007709",
      "tgn:7029392"
    ],
    "placetype": [
      "aat:300008347"
    ],
    "id": 2341585,
    "name:xx": "Frohock Mill"
  }
}
