{
  "geometry": {
    "type": "Point",
    "coordinates": [
      -74.7833,
      44.1833
    ]
  },
  "type": "Feature",
  "properties": {
    "hierarchy": [
      "tgn:2192451",
      "tgn:1000001",
      "tgn:7012149",
      "tgn:7016021",
      "tgn:7007568",
      "tgn:7029392"
    ],
    "placetype": [
      "aat:300132316"
    ],
    "id": 2192451,
    "name:xx": "Brandy Brook Flow"
  }
}
