{
  "type": "FeatureCollection",
  "features": [
    {
      "geometry": {
        "type": "Point",
        "coordinates": [
          -6.895556,
          37.161389
        ]
      },
      "type": "Feature",
      "properties": {
        "hierarchy": [
          "tgn:7293290",
          "tgn:7002758",
          "tgn:7002823",
          "tgn:1000003",
          "tgn:1000095",
          "tgn:7029392"
        ],
        "placetype": [
          "aat:300008816"
        ],
        "id": 7293290,
        "name:xx": "Castilla, Playa de"
      }
    },
    {
      "geometry": {
        "type": "Point",
        "coordinates": [
          -6.961944,
          37.182778
        ]
      },
      "type": "Feature",
      "properties": {
        "hierarchy": [
          "tgn:7293291",
          "tgn:7002758",
          "tgn:7002823",
          "tgn:1000003",
          "tgn:1000095",
          "tgn:7029392"
        ],
        "placetype": [
          "aat:300008347"
        ],
        "id": 7293291,
        "name:xx": "Punta Umbría"
      }
    },
    {
      "geometry": {
        "type": "Point",
        "coordinates": [
          -6.3,
          39.983333
        ]
      },
      "type": "Feature",
      "properties": {
        "hierarchy": [
          "tgn:7293292",
          "tgn:7002811",
          "tgn:1000003",
          "tgn:7003837",
          "tgn:1000095",
          "tgn:7029392"
        ],
        "placetype": [
          "aat:300008347"
        ],
        "id": 7293292,
        "name:xx": "Viñuelas de Abajo"
      }
    },
    {
      "geometry": {
        "type": "Point",
        "coordinates": [
          -3.7,
          40.583333
        ]
      },
      "type": "Feature",
      "properties": {
        "hierarchy": [
          "tgn:7293294",
          "tgn:7010420",
          "tgn:1000003",
          "tgn:7002795",
          "tgn:1000095",
          "tgn:7029392"
        ],
        "placetype": [
          "aat:300007783"
        ],
        "id": 7293294,
        "name:xx": "Estación de Viñuelas"
      }
    },
    {
      "geometry": {
        "type": "Point",
        "coordinates": [
          -4.216667,
          37.183333
        ]
      },
      "type": "Feature",
      "properties": {
        "hierarchy": [
          "tgn:7293296",
          "tgn:7002758",
          "tgn:7002821",
          "tgn:1000003",
          "tgn:1000095",
          "tgn:7029392"
        ],
        "placetype": [
          "aat:300008699"
        ],
        "id": 7293296,
        "name:xx": "Viñuelas, Arroyo de las"
      }
    },
    {
      "geometry": {
        "type": "Point",
        "coordinates": [
          -4.666667,
          41.5
        ]
      },
      "type": "Feature",
      "properties": {
        "hierarchy": [
          "tgn:7293298",
          "tgn:7001158",
          "tgn:7002848",
          "tgn:1000003",
          "tgn:1000095",
          "tgn:7029392"
        ],
        "placetype": [
          "aat:300008699"
        ],
        "id": 7293298,
        "name:xx": "Viñuelas, Arroyo"
      }
    }
  ]
}
