{
  "geometry": {
    "type": "Point",
    "coordinates": [
      150.6833,
      -31.3333
    ]
  },
  "type": "Feature",
  "properties": {
    "hierarchy": [
      "tgn:1098506",
      "tgn:7000490",
      "tgn:1000006",
      "tgn:7001828",
      "tgn:7029392"
    ],
    "placetype": [
      "aat:300008347"
    ],
    "id": 1098506,
    "name:xx": "Werris Creek"
  }
}
