{
  "type": "FeatureCollection",
  "features": [
    {
      "geometry": {
        "type": "Point",
        "coordinates": [
          -86.7833,
          41.65
        ]
      },
      "type": "Feature",
      "properties": {
        "hierarchy": [
          "tgn:2779740",
          "tgn:1000001",
          "tgn:7012149",
          "tgn:1002561",
          "tgn:7007252",
          "tgn:7029392"
        ],
        "placetype": [
          "aat:300008699"
        ],
        "id": 2779740,
        "name:xx": "Wolf Run"
      }
    },
    {
      "geometry": {
        "type": "Point",
        "coordinates": [
          -85.7833,
          38.55
        ]
      },
      "type": "Feature",
      "properties": {
        "hierarchy": [
          "tgn:2779741",
          "tgn:1000001",
          "tgn:1002273",
          "tgn:7012149",
          "tgn:7007252",
          "tgn:7029392"
        ],
        "placetype": [
          "aat:300008699"
        ],
        "id": 2779741,
        "name:xx": "Wolf Run"
      }
    },
    {
      "geometry": {
        "type": "Point",
        "coordinates": [
          -85.3167,
          38.7667
        ]
      },
      "type": "Feature",
      "properties": {
        "hierarchy": [
          "tgn:2779742",
          "tgn:1000001",
          "tgn:7012149",
          "tgn:1002515",
          "tgn:7007252",
          "tgn:7029392"
        ],
        "placetype": [
          "aat:300008699"
        ],
        "id": 2779742,
        "name:xx": "Wolf Run"
      }
    },
    {
      "geometry": {
        "type": "Point",
        "coordinates": [
          -94.95,
          40.9
        ]
      },
      "type": "Feature",
      "properties": {
        "hierarchy": [
          "tgn:2779743",
          "tgn:1000001",
          "tgn:7012149",
          "tgn:7007253",
          "tgn:7029392"
        ],
        "placetype": [
          "aat:300008699"
        ],
        "id": 2779743,
        "name:xx": "Wolf Run"
      }
    },
    {
      "geometry": {
        "type": "Point",
        "coordinates": [
          -93.0833,
          41.2167
        ]
      },
      "type": "Feature",
      "properties": {
        "hierarchy": [
          "tgn:2779744",
          "tgn:1000001",
          "tgn:7012149",
          "tgn:2000623",
          "tgn:7007253",
          "tgn:7029392"
        ],
        "placetype": [
          "aat:300008699"
        ],
        "id": 2779744,
        "name:xx": "Wolf Run"
      }
    },
    {
      "geometry": {
        "type": "Point",
        "coordinates": [
          -84.5167,
          38.0167
        ]
      },
      "type": "Feature",
      "properties": {
        "hierarchy": [
          "tgn:2779745",
          "tgn:1000001",
          "tgn:7012149",
          "tgn:1002371",
          "tgn:7007255",
          "tgn:7029392"
        ],
        "placetype": [
          "aat:300008699"
        ],
        "id": 2779745,
        "name:xx": "Wolf Run"
      }
    },
    {
      "geometry": {
        "type": "Point",
        "coordinates": [
          -85.1,
          38.1667
        ]
      },
      "type": "Feature",
      "properties": {
        "hierarchy": [
          "tgn:2779746",
          "tgn:1000001",
          "tgn:7012149",
          "tgn:1002887",
          "tgn:7007255",
          "tgn:7029392"
        ],
        "placetype": [
          "aat:300008699"
        ],
        "id": 2779746,
        "name:xx": "Wolf Run"
      }
    },
    {
      "geometry": {
        "type": "Point",
        "coordinates": [
          -84,
          38.55
        ]
      },
      "type": "Feature",
      "properties": {
        "hierarchy": [
          "tgn:2779747",
          "tgn:1000001",
          "tgn:7012149",
          "tgn:1002829",
          "tgn:7007255",
          "tgn:7029392"
        ],
        "placetype": [
          "aat:300008699"
        ],
        "id": 2779747,
        "name:xx": "Wolf Run"
      }
    },
    {
      "geometry": {
        "type": "Point",
        "coordinates": [
          -90.4833,
          36.95
        ]
      },
      "type": "Feature",
      "properties": {
        "hierarchy": [
          "tgn:2779748",
          "tgn:1000001",
          "tgn:7012149",
          "tgn:2001255",
          "tgn:7007523",
          "tgn:7029392"
        ],
        "placetype": [
          "aat:300008699"
        ],
        "id": 2779748,
        "name:xx": "Wolf Run"
      }
    },
    {
      "geometry": {
        "type": "Point",
        "coordinates": [
          -74.4,
          39.5667
        ]
      },
      "type": "Feature",
      "properties": {
        "hierarchy": [
          "tgn:2779749",
          "tgn:1002215",
          "tgn:1000001",
          "tgn:7012149",
          "tgn:7007565",
          "tgn:7029392"
        ],
        "placetype": [
          "aat:300008699"
        ],
        "id": 2779749,
        "name:xx": "Wolf Run"
      }
    }
  ]
}
