{
  "geometry": {
    "type": "Point",
    "coordinates": [
      -71.15,
      48.7667
    ]
  },
  "type": "Feature",
  "properties": {
    "hierarchy": [
      "tgn:1120038",
      "tgn:7005685",
      "tgn:1000001",
      "tgn:7005804",
      "tgn:7029392"
    ],
    "placetype": [
      "aat:300006191"
    ],
    "id": 1120038,
    "name:xx": "La Mothe, Lac"
  }
}
