{
  "geometry": {
    "type": "Point",
    "coordinates": [
      -88.15,
      34.5167
    ]
  },
  "type": "Feature",
  "properties": {
    "hierarchy": [
      "tgn:2237814",
      "tgn:1000001",
      "tgn:7012149",
      "tgn:7029392"
    ],
    "placetype": [
      "aat:300266640"
    ],
    "id": 2237814,
    "name:xx": "Chinquapin Ridge"
  }
}
