{
  "geometry": {
    "type": "Point",
    "coordinates": [
      -82.4167,
      35.9667
    ]
  },
  "type": "Feature",
  "properties": {
    "hierarchy": [
      "tgn:2456107",
      "tgn:1000001",
      "tgn:7012149",
      "tgn:2001556",
      "tgn:7007709",
      "tgn:7029392"
    ],
    "placetype": [
      "aat:300008699"
    ],
    "id": 2456107,
    "name:xx": "Little Hensley Branch"
  }
}
