{
  "geometry": {
    "type": "Point",
    "coordinates": [
      -87.65,
      31.8667
    ]
  },
  "type": "Feature",
  "properties": {
    "hierarchy": [
      "tgn:2293443",
      "tgn:7002659",
      "tgn:1000001",
      "tgn:7012149",
      "tgn:2000065",
      "tgn:7029392"
    ],
    "placetype": [
      "aat:300386837"
    ],
    "id": 2293443,
    "name:xx": "Double Natural Bridges"
  }
}
