{
  "geometry": {
    "type": "Point",
    "coordinates": [
      -72.4167,
      41.9667
    ]
  },
  "type": "Feature",
  "properties": {
    "hierarchy": [
      "tgn:2654244",
      "tgn:1000001",
      "tgn:1002949",
      "tgn:7012149",
      "tgn:7007159",
      "tgn:7029392"
    ],
    "placetype": [
      "aat:300008699"
    ],
    "id": 2654244,
    "name:xx": "Shady Brook"
  }
}
