{
  "geometry": {
    "type": "Point",
    "coordinates": [
      -71.6667,
      44.9833
    ]
  },
  "type": "Feature",
  "properties": {
    "hierarchy": [
      "tgn:2334434",
      "tgn:1000001",
      "tgn:1002361",
      "tgn:7012149",
      "tgn:7007828",
      "tgn:7029392"
    ],
    "placetype": [
      "aat:300008680"
    ],
    "id": 2334434,
    "name:xx": "Forest Lake"
  }
}
