{
  "geometry": {
    "type": "Point",
    "coordinates": [
      -91.5333,
      42.5833
    ]
  },
  "type": "Feature",
  "properties": {
    "hierarchy": [
      "tgn:2779307",
      "tgn:1000001",
      "tgn:2000588",
      "tgn:7012149",
      "tgn:7007253",
      "tgn:7029392"
    ],
    "placetype": [
      "aat:300008798"
    ],
    "id": 2779307,
    "name:xx": "Wolf Hill"
  }
}
