{
  "geometry": {
    "type": "Point",
    "coordinates": [
      -88.2167,
      43.2333
    ]
  },
  "type": "Feature",
  "properties": {
    "hierarchy": [
      "tgn:2121432",
      "tgn:1000001",
      "tgn:7012149",
      "tgn:1002998",
      "tgn:7007922",
      "tgn:7029392"
    ],
    "placetype": [
      "aat:300008347"
    ],
    "id": 2121432,
    "name:xx": "Hubertus"
  }
}
