{
  "geometry": {
    "type": "Point",
    "coordinates": [
      -95.2667,
      32.0333
    ]
  },
  "type": "Feature",
  "properties": {
    "hierarchy": [
      "tgn:2580272",
      "tgn:1000001",
      "tgn:7012149",
      "tgn:1002263",
      "tgn:7007826",
      "tgn:7029392"
    ],
    "placetype": [
      "aat:300008699"
    ],
    "id": 2580272,
    "name:xx": "Pierson Branch"
  }
}
