{
  "geometry": {
    "type": "Point",
    "coordinates": [
      -119.95,
      37.4833
    ]
  },
  "type": "Feature",
  "properties": {
    "hierarchy": [
      "tgn:2492801",
      "tgn:1000001",
      "tgn:7012149",
      "tgn:7007157",
      "tgn:7014004",
      "tgn:7029392"
    ],
    "placetype": [
      "aat:300000390"
    ],
    "id": 2492801,
    "name:xx": "Mariposa Mine"
  }
}
