{
  "type": "FeatureCollection",
  "features": [
    {
      "geometry": {
        "type": "Point",
        "coordinates": [
          -82.2,
          33.4
        ]
      },
      "type": "Feature",
      "properties": {
        "hierarchy": [
          "tgn:2492130",
          "tgn:1000001",
          "tgn:7012149",
          "tgn:2000412",
          "tgn:7007248",
          "tgn:7029392"
        ],
        "placetype": [
          "aat:300008699"
        ],
        "id": 2492130,
        "name:xx": "Marcum Branch"
      }
    },
    {
      "geometry": {
        "type": "Point",
        "coordinates": [
          -88.8833,
          38.0667
        ]
      },
      "type": "Feature",
      "properties": {
        "hierarchy": [
          "tgn:2492131",
          "tgn:1000001",
          "tgn:2000506",
          "tgn:7012149",
          "tgn:7007251",
          "tgn:7029392"
        ],
        "placetype": [
          "aat:300008699"
        ],
        "id": 2492131,
        "name:xx": "Marcum Branch"
      }
    },
    {
      "geometry": {
        "type": "Point",
        "coordinates": [
          -84.7667,
          36.6
        ]
      },
      "type": "Feature",
      "properties": {
        "hierarchy": [
          "tgn:2492132",
          "tgn:1000001",
          "tgn:7012149",
          "tgn:2000850",
          "tgn:7007255",
          "tgn:7029392"
        ],
        "placetype": [
          "aat:300008699"
        ],
        "id": 2492132,
        "name:xx": "Marcum Branch"
      }
    },
    {
      "geometry": {
        "type": "Point",
        "coordinates": [
          -84.5667,
          36.5333
        ]
      },
      "type": "Feature",
      "properties": {
        "hierarchy": [
          "tgn:2492133",
          "tgn:1000001",
          "tgn:7012149",
          "tgn:2001912",
          "tgn:7007825",
          "tgn:7029392"
        ],
        "placetype": [
          "aat:300008699"
        ],
        "id": 2492133,
        "name:xx": "Marcum Branch"
      }
    },
    {
      "geometry": {
        "type": "Point",
        "coordinates": [
          -82.15,
          37.9
        ]
      },
      "type": "Feature",
      "properties": {
        "hierarchy": [
          "tgn:2492134",
          "tgn:1000001",
          "tgn:7012149",
          "tgn:2002280",
          "tgn:7013961",
          "tgn:7029392"
        ],
        "placetype": [
          "aat:300008699"
        ],
        "id": 2492134,
        "name:xx": "Marcum Branch"
      }
    },
    {
      "geometry": {
        "type": "Point",
        "coordinates": [
          -89.7167,
          34.3
        ]
      },
      "type": "Feature",
      "properties": {
        "hierarchy": [
          "tgn:2492135",
          "tgn:1000001",
          "tgn:7012149",
          "tgn:7007522",
          "tgn:7029392"
        ],
        "placetype": [
          "aat:300008706"
        ],
        "id": 2492135,
        "name:xx": "Marcum Creek"
      }
    },
    {
      "geometry": {
        "type": "Point",
        "coordinates": [
          -96.8333,
          35.1667
        ]
      },
      "type": "Feature",
      "properties": {
        "hierarchy": [
          "tgn:2492136",
          "tgn:1000001",
          "tgn:7012149",
          "tgn:2001685",
          "tgn:7007707",
          "tgn:7029392"
        ],
        "placetype": [
          "aat:300008706"
        ],
        "id": 2492136,
        "name:xx": "Marcum Creek"
      }
    },
    {
      "geometry": {
        "type": "Point",
        "coordinates": [
          -84.3333,
          36.4833
        ]
      },
      "type": "Feature",
      "properties": {
        "hierarchy": [
          "tgn:2492137",
          "tgn:1000001",
          "tgn:7012149",
          "tgn:2001912",
          "tgn:7007825",
          "tgn:7029392"
        ],
        "placetype": [
          "aat:300008706"
        ],
        "id": 2492137,
        "name:xx": "Marcum Creek"
      }
    },
    {
      "geometry": {
        "type": "Point",
        "coordinates": [
          -107.5167,
          44.7333
        ]
      },
      "type": "Feature",
      "properties": {
        "hierarchy": [
          "tgn:2492138",
          "tgn:1000001",
          "tgn:7012149",
          "tgn:2002381",
          "tgn:7007923",
          "tgn:7029392"
        ],
        "placetype": [
          "aat:300008706"
        ],
        "id": 2492138,
        "name:xx": "Marcum Creek"
      }
    },
    {
      "geometry": {
        "type": "Point",
        "coordinates": [
          -82.9,
          36.8667
        ]
      },
      "type": "Feature",
      "properties": {
        "hierarchy": [
          "tgn:2492139",
          "tgn:1000001",
          "tgn:7012149",
          "tgn:7029392"
        ],
        "placetype": [
          "aat:300008761"
        ],
        "id": 2492139,
        "name:xx": "Marcum Hollow"
      }
    }
  ]
}
