{
  "geometry": {
    "type": "Point",
    "coordinates": [
      26.7167,
      45.4667
    ]
  },
  "type": "Feature",
  "properties": {
    "hierarchy": [
      "tgn:1050336",
      "tgn:1000353",
      "tgn:1000003",
      "tgn:1000091",
      "tgn:7029392"
    ],
    "placetype": [
      "aat:300008347"
    ],
    "id": 1050336,
    "name:xx": "Vintilă Vodă"
  }
}
