{
  "geometry": {
    "type": "Point",
    "coordinates": [
      -83.9833,
      36.0667
    ]
  },
  "type": "Feature",
  "properties": {
    "hierarchy": [
      "tgn:2255565",
      "tgn:1000001",
      "tgn:7012149",
      "tgn:2001883",
      "tgn:7007825",
      "tgn:7029392"
    ],
    "placetype": [
      "aat:300008761"
    ],
    "id": 2255565,
    "name:xx": "Copeland Hollow"
  }
}
