{
  "geometry": {
    "type": "Point",
    "coordinates": [
      31.995044,
      30.218763
    ]
  },
  "type": "Feature",
  "properties": {
    "hierarchy": [
      "tgn:7522963",
      "tgn:7001242",
      "tgn:7016833",
      "tgn:1001110",
      "tgn:7029392"
    ],
    "placetype": [
      "aat:300379998"
    ],
    "name:en": "Barāshah, Wādī",
    "id": 7522963
  }
}
