{
  "type": "FeatureCollection",
  "features": [
    {
      "geometry": {
        "type": "Point",
        "coordinates": [
          -87.05,
          34.5167
        ]
      },
      "type": "Feature",
      "properties": {
        "hierarchy": [
          "tgn:2151100",
          "tgn:7002659",
          "tgn:1000001",
          "tgn:7012149",
          "tgn:2000051",
          "tgn:7029392"
        ],
        "placetype": [
          "aat:300008746"
        ],
        "id": 2151100,
        "name:xx": "Bat Cave"
      }
    },
    {
      "geometry": {
        "type": "Point",
        "coordinates": [
          -87.5833,
          34.8833
        ]
      },
      "type": "Feature",
      "properties": {
        "hierarchy": [
          "tgn:2151101",
          "tgn:7002659",
          "tgn:1000001",
          "tgn:7012149",
          "tgn:2000038",
          "tgn:7029392"
        ],
        "placetype": [
          "aat:300008746"
        ],
        "id": 2151101,
        "name:xx": "Bat Cave"
      }
    },
    {
      "geometry": {
        "type": "Point",
        "coordinates": [
          -109.4,
          33.0167
        ]
      },
      "type": "Feature",
      "properties": {
        "hierarchy": [
          "tgn:2151102",
          "tgn:1000001",
          "tgn:7006451",
          "tgn:2000095",
          "tgn:7012149",
          "tgn:7029392"
        ],
        "placetype": [
          "aat:300008746"
        ],
        "id": 2151102,
        "name:xx": "Bat Cave"
      }
    },
    {
      "geometry": {
        "type": "Point",
        "coordinates": [
          -113.8,
          36.0333
        ]
      },
      "type": "Feature",
      "properties": {
        "hierarchy": [
          "tgn:2151103",
          "tgn:1000001",
          "tgn:7006451",
          "tgn:7012149",
          "tgn:2000098",
          "tgn:7029392"
        ],
        "placetype": [
          "aat:300008746"
        ],
        "id": 2151103,
        "name:xx": "Bat Cave"
      }
    },
    {
      "geometry": {
        "type": "Point",
        "coordinates": [
          -91.3667,
          35.85
        ]
      },
      "type": "Feature",
      "properties": {
        "hierarchy": [
          "tgn:2151104",
          "tgn:1000001",
          "tgn:7016172",
          "tgn:7012149",
          "tgn:2000136",
          "tgn:7029392"
        ],
        "placetype": [
          "aat:300008746"
        ],
        "id": 2151104,
        "name:xx": "Bat Cave"
      }
    },
    {
      "geometry": {
        "type": "Point",
        "coordinates": [
          -93.9,
          36.2833
        ]
      },
      "type": "Feature",
      "properties": {
        "hierarchy": [
          "tgn:2151105",
          "tgn:1000001",
          "tgn:2000108",
          "tgn:7016172",
          "tgn:7012149",
          "tgn:7029392"
        ],
        "placetype": [
          "aat:300008746"
        ],
        "id": 2151105,
        "name:xx": "Bat Cave"
      }
    },
    {
      "geometry": {
        "type": "Point",
        "coordinates": [
          -93.25,
          36.1
        ]
      },
      "type": "Feature",
      "properties": {
        "hierarchy": [
          "tgn:2151106",
          "tgn:1000001",
          "tgn:7016172",
          "tgn:7012149",
          "tgn:2000155",
          "tgn:7029392"
        ],
        "placetype": [
          "aat:300008746"
        ],
        "id": 2151106,
        "name:xx": "Bat Cave"
      }
    },
    {
      "geometry": {
        "type": "Point",
        "coordinates": [
          -114.4833,
          34.7
        ]
      },
      "type": "Feature",
      "properties": {
        "hierarchy": [
          "tgn:2151107",
          "tgn:1000001",
          "tgn:7012149",
          "tgn:7007157",
          "tgn:1002857",
          "tgn:7029392"
        ],
        "placetype": [
          "aat:300008746"
        ],
        "id": 2151107,
        "name:xx": "Bat Cave"
      }
    },
    {
      "geometry": {
        "type": "Point",
        "coordinates": [
          -91.2,
          36.6667
        ]
      },
      "type": "Feature",
      "properties": {
        "hierarchy": [
          "tgn:2151108",
          "tgn:1000001",
          "tgn:7012149",
          "tgn:2001225",
          "tgn:7007523",
          "tgn:7029392"
        ],
        "placetype": [
          "aat:300008746"
        ],
        "id": 2151108,
        "name:xx": "Bat Cave"
      }
    },
    {
      "geometry": {
        "type": "Point",
        "coordinates": [
          -92.1333,
          36.7833
        ]
      },
      "type": "Feature",
      "properties": {
        "hierarchy": [
          "tgn:2151109",
          "tgn:1000001",
          "tgn:7012149",
          "tgn:2001226",
          "tgn:7007523",
          "tgn:7029392"
        ],
        "placetype": [
          "aat:300008746"
        ],
        "id": 2151109,
        "name:xx": "Bat Cave"
      }
    }
  ]
}
