{
  "type": "FeatureCollection",
  "features": [
    {
      "geometry": {
        "type": "Point",
        "coordinates": [
          28.1833,
          -26.2
        ]
      },
      "type": "Feature",
      "properties": {
        "hierarchy": [
          "tgn:1101280",
          "tgn:7001242",
          "tgn:7017576",
          "tgn:1000193",
          "tgn:7029392"
        ],
        "placetype": [
          "aat:300000390"
        ],
        "id": 1101280,
        "name:xx": "Witwatersrand Gold Mine"
      }
    },
    {
      "geometry": {
        "type": "Point",
        "coordinates": [
          137.8333,
          35.2
        ]
      },
      "type": "Feature",
      "properties": {
        "hierarchy": [
          "tgn:1101281",
          "tgn:7000895",
          "tgn:1000004",
          "tgn:1000120",
          "tgn:7029392"
        ],
        "placetype": [
          "aat:300007899"
        ],
        "id": 1101281,
        "name:xx": "Ōhara-tunnel"
      }
    },
    {
      "geometry": {
        "type": "Point",
        "coordinates": [
          11.5,
          44.05
        ]
      },
      "type": "Feature",
      "properties": {
        "hierarchy": [
          "tgn:1101282",
          "tgn:7003163",
          "tgn:1000003",
          "tgn:7009760",
          "tgn:1000080",
          "tgn:7029392"
        ],
        "placetype": [
          "aat:300007899"
        ],
        "id": 1101282,
        "name:xx": "Allochio, Galleria degli"
      }
    },
    {
      "geometry": {
        "type": "Point",
        "coordinates": [
          -43.2333,
          -22.9333
        ]
      },
      "type": "Feature",
      "properties": {
        "hierarchy": [
          "tgn:1101283",
          "tgn:1001942",
          "tgn:1000047",
          "tgn:7002457",
          "tgn:1000002",
          "tgn:7017095",
          "tgn:7029392"
        ],
        "placetype": [
          "aat:300007899"
        ],
        "id": 1101283,
        "name:xx": "Andere Reboucas, Túnel"
      }
    },
    {
      "geometry": {
        "type": "Point",
        "coordinates": [
          11.1833,
          44.2167
        ]
      },
      "type": "Feature",
      "properties": {
        "hierarchy": [
          "tgn:1101284",
          "tgn:7008531",
          "tgn:1000003",
          "tgn:1000080",
          "tgn:7029392"
        ],
        "placetype": [
          "aat:300007899"
        ],
        "id": 1101284,
        "name:it": "Appennino, Galleria dell'"
      }
    },
    {
      "geometry": {
        "type": "Point",
        "coordinates": [
          0.0167,
          51.5
        ]
      },
      "type": "Feature",
      "properties": {
        "hierarchy": [
          "tgn:1101287",
          "tgn:7002445",
          "tgn:7011781",
          "tgn:1000003",
          "tgn:7008136",
          "tgn:7008591",
          "tgn:7029392"
        ],
        "placetype": [
          "aat:300007899"
        ],
        "id": 1101287,
        "name:xx": "Blackwall Tunnel"
      }
    },
    {
      "geometry": {
        "type": "Point",
        "coordinates": [
          9.8833,
          44.4167
        ]
      },
      "type": "Feature",
      "properties": {
        "hierarchy": [
          "tgn:1101289",
          "tgn:1003473",
          "tgn:1000003",
          "tgn:7009760",
          "tgn:1000080",
          "tgn:7029392"
        ],
        "placetype": [
          "aat:300007899"
        ],
        "id": 1101289,
        "name:xx": "Borgallo, Galleria del"
      }
    }
  ]
}
