{
  "geometry": {
    "type": "Point",
    "coordinates": [
      -73.85,
      44.0667
    ]
  },
  "type": "Feature",
  "properties": {
    "hierarchy": [
      "tgn:2713547",
      "tgn:1000001",
      "tgn:7012149",
      "tgn:2001461",
      "tgn:7007568",
      "tgn:7029392"
    ],
    "placetype": [
      "aat:300008699"
    ],
    "id": 2713547,
    "name:xx": "Teakettle Brook"
  }
}
