{
  "type": "FeatureCollection",
  "features": [
    {
      "geometry": {
        "type": "Point",
        "coordinates": [
          -94.1833,
          46.3833
        ]
      },
      "type": "Feature",
      "properties": {
        "hierarchy": [
          "tgn:2349190",
          "tgn:1000001",
          "tgn:2001016",
          "tgn:7012149",
          "tgn:7007521",
          "tgn:7029392"
        ],
        "placetype": [
          "aat:300008680"
        ],
        "id": 2349190,
        "name:xx": "Gilbert Lake"
      }
    },
    {
      "geometry": {
        "type": "Point",
        "coordinates": [
          -114.0833,
          48.1833
        ]
      },
      "type": "Feature",
      "properties": {
        "hierarchy": [
          "tgn:2349191",
          "tgn:1000001",
          "tgn:7012149",
          "tgn:2001274",
          "tgn:7007524",
          "tgn:7029392"
        ],
        "placetype": [
          "aat:300008680"
        ],
        "id": 2349191,
        "name:xx": "Gilbert Lake"
      }
    },
    {
      "geometry": {
        "type": "Point",
        "coordinates": [
          -75.1167,
          42.5667
        ]
      },
      "type": "Feature",
      "properties": {
        "hierarchy": [
          "tgn:2349192",
          "tgn:1000001",
          "tgn:7012149",
          "tgn:7014318",
          "tgn:7007568",
          "tgn:7029392"
        ],
        "placetype": [
          "aat:300008680"
        ],
        "id": 2349192,
        "name:xx": "Gilbert Lake"
      }
    },
    {
      "geometry": {
        "type": "Point",
        "coordinates": [
          -79.95,
          34.3833
        ]
      },
      "type": "Feature",
      "properties": {
        "hierarchy": [
          "tgn:2349193",
          "tgn:1000001",
          "tgn:2001740",
          "tgn:7012149",
          "tgn:7007712",
          "tgn:7029392"
        ],
        "placetype": [
          "aat:300006191"
        ],
        "id": 2349193,
        "name:xx": "Gilbert Lake"
      }
    },
    {
      "geometry": {
        "type": "Point",
        "coordinates": [
          -110.3167,
          40.8333
        ]
      },
      "type": "Feature",
      "properties": {
        "hierarchy": [
          "tgn:2349194",
          "tgn:1000001",
          "tgn:7012149",
          "tgn:2002122",
          "tgn:7007827",
          "tgn:7029392"
        ],
        "placetype": [
          "aat:300008680"
        ],
        "id": 2349194,
        "name:xx": "Gilbert Lake"
      }
    },
    {
      "geometry": {
        "type": "Point",
        "coordinates": [
          -118.1333,
          48.9167
        ]
      },
      "type": "Feature",
      "properties": {
        "hierarchy": [
          "tgn:2349195",
          "tgn:1000001",
          "tgn:7012149",
          "tgn:2002250",
          "tgn:7007920",
          "tgn:7029392"
        ],
        "placetype": [
          "aat:300008680"
        ],
        "id": 2349195,
        "name:xx": "Gilbert Lake"
      }
    },
    {
      "geometry": {
        "type": "Point",
        "coordinates": [
          -88.25,
          43.4
        ]
      },
      "type": "Feature",
      "properties": {
        "hierarchy": [
          "tgn:2349196",
          "tgn:1000001",
          "tgn:7012149",
          "tgn:1002998",
          "tgn:7007922",
          "tgn:7029392"
        ],
        "placetype": [
          "aat:300008680"
        ],
        "id": 2349196,
        "name:xx": "Gilbert Lake"
      }
    },
    {
      "geometry": {
        "type": "Point",
        "coordinates": [
          -89.1667,
          44.2
        ]
      },
      "type": "Feature",
      "properties": {
        "hierarchy": [
          "tgn:2349197",
          "tgn:1000001",
          "tgn:7012149",
          "tgn:2002362",
          "tgn:7007922",
          "tgn:7029392"
        ],
        "placetype": [
          "aat:300008680"
        ],
        "id": 2349197,
        "name:xx": "Gilbert Lake"
      }
    },
    {
      "geometry": {
        "type": "Point",
        "coordinates": [
          -92.1833,
          45.35
        ]
      },
      "type": "Feature",
      "properties": {
        "hierarchy": [
          "tgn:2349198",
          "tgn:1000001",
          "tgn:7012149",
          "tgn:2002346",
          "tgn:7007922",
          "tgn:7029392"
        ],
        "placetype": [
          "aat:300008680"
        ],
        "id": 2349198,
        "name:xx": "Gilbert Lake"
      }
    },
    {
      "geometry": {
        "type": "Point",
        "coordinates": [
          -89.45,
          46.2
        ]
      },
      "type": "Feature",
      "properties": {
        "hierarchy": [
          "tgn:2349199",
          "tgn:1000001",
          "tgn:7012149",
          "tgn:2002359",
          "tgn:7007922",
          "tgn:7029392"
        ],
        "placetype": [
          "aat:300008680"
        ],
        "id": 2349199,
        "name:xx": "Gilbert Lake"
      }
    }
  ]
}
