{
  "type": "FeatureCollection",
  "features": [
    {
      "geometry": {
        "type": "Point",
        "coordinates": [
          -2.233333,
          53.45
        ]
      },
      "type": "Feature",
      "properties": {
        "hierarchy": [
          "tgn:7026570",
          "tgn:7002445",
          "tgn:1000003",
          "tgn:7008591",
          "tgn:7029392"
        ],
        "placetype": [
          "aat:300387064",
          "aat:300132618",
          "aat:300000771"
        ],
        "name:en": "Greater Manchester",
        "id": 7026570
      }
    },
    {
      "geometry": {
        "type": "Point",
        "coordinates": [
          -0.1667,
          51.5833
        ]
      },
      "type": "Feature",
      "properties": {
        "hierarchy": [
          "tgn:7026576",
          "tgn:7002445",
          "tgn:7011781",
          "tgn:1000003",
          "tgn:7008136",
          "tgn:7008591",
          "tgn:7029392"
        ],
        "placetype": [
          "aat:300000745",
          "aat:300387064",
          "aat:300000778"
        ],
        "name:en": "Camden",
        "id": 7026576
      }
    },
    {
      "geometry": {
        "type": "Point",
        "coordinates": [
          -2.7333,
          53.5833
        ]
      },
      "type": "Feature",
      "properties": {
        "hierarchy": [
          "tgn:7026578",
          "tgn:7002445",
          "tgn:1000003",
          "tgn:7008154",
          "tgn:7008591",
          "tgn:7029392"
        ],
        "placetype": [
          "aat:300008707",
          "aat:300008699"
        ],
        "name:en": "Douglas, River",
        "id": 7026578
      }
    },
    {
      "geometry": {
        "type": "Point",
        "coordinates": [
          0.7167,
          51.55
        ]
      },
      "type": "Feature",
      "properties": {
        "hierarchy": [
          "tgn:7026579",
          "tgn:7002445",
          "tgn:1000003",
          "tgn:7008591",
          "tgn:7029392"
        ],
        "placetype": [
          "aat:300387064",
          "aat:300387071"
        ],
        "name:en": "Southend-on-Sea",
        "id": 7026579
      }
    }
  ]
}
