{
  "geometry": {
    "type": "Point",
    "coordinates": [
      -82.15,
      34.3667
    ]
  },
  "type": "Feature",
  "properties": {
    "hierarchy": [
      "tgn:2527289",
      "tgn:1000001",
      "tgn:7012149",
      "tgn:2001754",
      "tgn:7007712",
      "tgn:7029392"
    ],
    "placetype": [
      "aat:300008347"
    ],
    "id": 2527289,
    "name:xx": "Mount Olive"
  }
}
