{
  "geometry": {
    "type": "Point",
    "coordinates": [
      -83.5833,
      42.75
    ]
  },
  "type": "Feature",
  "properties": {
    "hierarchy": [
      "tgn:2191992",
      "tgn:1000001",
      "tgn:7012149",
      "tgn:1002737",
      "tgn:7007520",
      "tgn:7029392"
    ],
    "placetype": [
      "aat:300006191"
    ],
    "id": 2191992,
    "name:xx": "Braemar, Lake"
  }
}
