{
  "geometry": {
    "type": "Point",
    "coordinates": [
      -110.1667,
      40.8667
    ]
  },
  "type": "Feature",
  "properties": {
    "hierarchy": [
      "tgn:2718541",
      "tgn:1000001",
      "tgn:7012149",
      "tgn:2002122",
      "tgn:7007827",
      "tgn:7029392"
    ],
    "placetype": [
      "aat:300008798"
    ],
    "id": 2718541,
    "name:xx": "Thompson Peak"
  }
}
