{
  "geometry": {
    "type": "Point",
    "coordinates": [
      -86.1667,
      42.2333
    ]
  },
  "type": "Feature",
  "properties": {
    "hierarchy": [
      "tgn:2644851",
      "tgn:1000001",
      "tgn:7012149",
      "tgn:1002967",
      "tgn:7007520",
      "tgn:7029392"
    ],
    "placetype": [
      "aat:300008680"
    ],
    "id": 2644851,
    "name:xx": "Sassafras Lake"
  }
}
