{
  "geometry": {
    "type": "Point",
    "coordinates": [
      -65.6833,
      -22.7833
    ]
  },
  "type": "Feature",
  "properties": {
    "hierarchy": [
      "tgn:1019116",
      "tgn:7006477",
      "tgn:1001328",
      "tgn:1000002",
      "tgn:7029392"
    ],
    "placetype": [
      "aat:300008347"
    ],
    "id": 1019116,
    "name:xx": "Abra Pampa"
  }
}
