{
  "geometry": {
    "type": "Point",
    "coordinates": [
      14.95,
      46.5333
    ]
  },
  "type": "Feature",
  "properties": {
    "hierarchy": [
      "tgn:1065222",
      "tgn:1000003",
      "tgn:7015085",
      "tgn:7006670",
      "tgn:7029392"
    ],
    "placetype": [
      "aat:300008347"
    ],
    "id": 1065222,
    "name:xx": "Ravne na Koroškem"
  }
}
