{
  "geometry": {
    "type": "Point",
    "coordinates": [
      -82.4667,
      35.5167
    ]
  },
  "type": "Feature",
  "properties": {
    "hierarchy": [
      "tgn:2506263",
      "tgn:1000001",
      "tgn:2001473",
      "tgn:7012149",
      "tgn:7007709",
      "tgn:7029392"
    ],
    "placetype": [
      "aat:300008706"
    ],
    "id": 2506263,
    "name:xx": "Merrill Cove Creek"
  }
}
