{
  "geometry": {
    "type": "Point",
    "coordinates": [
      -81.2833,
      38.7167
    ]
  },
  "type": "Feature",
  "properties": {
    "hierarchy": [
      "tgn:2117830",
      "tgn:1000001",
      "tgn:7012149",
      "tgn:2002293",
      "tgn:7013961",
      "tgn:7029392"
    ],
    "placetype": [
      "aat:300008347",
      "aat:300387210"
    ],
    "id": 2117830,
    "name:xx": "Clover"
  }
}
