{
  "geometry": {
    "type": "Point",
    "coordinates": [
      25.5333,
      45.3833
    ]
  },
  "type": "Feature",
  "properties": {
    "hierarchy": [
      "tgn:1050047",
      "tgn:1000003",
      "tgn:7002699",
      "tgn:1000091",
      "tgn:7029392"
    ],
    "placetype": [
      "aat:300008347"
    ],
    "id": 1050047,
    "name:xx": "Bușteni"
  }
}
