{
  "geometry": {
    "type": "Point",
    "coordinates": [
      78.75,
      10.083333
    ]
  },
  "type": "Feature",
  "properties": {
    "hierarchy": [
      "tgn:7577096",
      "tgn:1000004",
      "tgn:7000198",
      "tgn:7001797",
      "tgn:7029392"
    ],
    "placetype": [
      "aat:300008347"
    ],
    "name:en": "Kovilūr",
    "id": 7577096
  }
}
