{
  "geometry": {
    "type": "Point",
    "coordinates": [
      -109.2167,
      45.3667
    ]
  },
  "type": "Feature",
  "properties": {
    "hierarchy": [
      "tgn:2757742",
      "tgn:1000001",
      "tgn:2001264",
      "tgn:7012149",
      "tgn:7007524",
      "tgn:7029392"
    ],
    "placetype": [
      "aat:300006075"
    ],
    "id": 2757742,
    "name:xx": "West Branch Finn Ditch"
  }
}
