{
  "geometry": {
    "type": "Point",
    "coordinates": [
      -90.9333,
      42.6667
    ]
  },
  "type": "Feature",
  "properties": {
    "hierarchy": [
      "tgn:2207187",
      "tgn:1000001",
      "tgn:7012149",
      "tgn:7029392"
    ],
    "placetype": [
      "aat:300008699"
    ],
    "id": 2207187,
    "name:xx": "Bunker Chute"
  }
}
