{
  "type": "FeatureCollection",
  "features": [
    {
      "geometry": {
        "type": "Point",
        "coordinates": [
          -74.7667,
          39.0667
        ]
      },
      "type": "Feature",
      "properties": {
        "hierarchy": [
          "tgn:2700240",
          "tgn:1002232",
          "tgn:1000001",
          "tgn:7012149",
          "tgn:7007565",
          "tgn:7029392"
        ],
        "placetype": [
          "aat:300008850"
        ],
        "id": 2700240,
        "name:xx": "Sturgeon Point"
      }
    },
    {
      "geometry": {
        "type": "Point",
        "coordinates": [
          -73.95,
          41.9
        ]
      },
      "type": "Feature",
      "properties": {
        "hierarchy": [
          "tgn:2700241",
          "tgn:1000001",
          "tgn:1002347",
          "tgn:7012149",
          "tgn:7007568",
          "tgn:7029392"
        ],
        "placetype": [
          "aat:300008850"
        ],
        "id": 2700241,
        "name:xx": "Sturgeon Point"
      }
    },
    {
      "geometry": {
        "type": "Point",
        "coordinates": [
          -75.7667,
          44.4333
        ]
      },
      "type": "Feature",
      "properties": {
        "hierarchy": [
          "tgn:2700242",
          "tgn:1000001",
          "tgn:7012149",
          "tgn:7016021",
          "tgn:7007568",
          "tgn:7029392"
        ],
        "placetype": [
          "aat:300008850"
        ],
        "id": 2700242,
        "name:xx": "Sturgeon Point"
      }
    },
    {
      "geometry": {
        "type": "Point",
        "coordinates": [
          -77,
          37.3
        ]
      },
      "type": "Feature",
      "properties": {
        "hierarchy": [
          "tgn:2700243",
          "tgn:1000001",
          "tgn:1002257",
          "tgn:7012149",
          "tgn:7007919",
          "tgn:7029392"
        ],
        "placetype": [
          "aat:300008850"
        ],
        "id": 2700243,
        "name:xx": "Sturgeon Point"
      }
    },
    {
      "geometry": {
        "type": "Point",
        "coordinates": [
          -74.7333,
          40.1833
        ]
      },
      "type": "Feature",
      "properties": {
        "hierarchy": [
          "tgn:2700244",
          "tgn:1000001",
          "tgn:1002657",
          "tgn:7012149",
          "tgn:7007565",
          "tgn:7029392"
        ],
        "placetype": [
          "aat:300006191"
        ],
        "id": 2700244,
        "name:xx": "Sturgeon Pond"
      }
    },
    {
      "geometry": {
        "type": "Point",
        "coordinates": [
          -74.0333,
          41.8333
        ]
      },
      "type": "Feature",
      "properties": {
        "hierarchy": [
          "tgn:2700245",
          "tgn:1000001",
          "tgn:7012149",
          "tgn:1002961",
          "tgn:7007568",
          "tgn:7029392"
        ],
        "placetype": [
          "aat:300006191"
        ],
        "id": 2700245,
        "name:xx": "Sturgeon Pool"
      }
    },
    {
      "geometry": {
        "type": "Point",
        "coordinates": [
          -105.6,
          42.0833
        ]
      },
      "type": "Feature",
      "properties": {
        "hierarchy": [
          "tgn:2700247",
          "tgn:2002365",
          "tgn:1000001",
          "tgn:7012149",
          "tgn:7007923",
          "tgn:7029392"
        ],
        "placetype": [
          "aat:300006191"
        ],
        "id": 2700247,
        "name:xx": "Sturgeon Reservoir Number 2"
      }
    },
    {
      "geometry": {
        "type": "Point",
        "coordinates": [
          -163.1,
          65.3833
        ]
      },
      "type": "Feature",
      "properties": {
        "hierarchy": [
          "tgn:2700249",
          "tgn:7006450",
          "tgn:1000001",
          "tgn:7012149",
          "tgn:2000079",
          "tgn:7029392"
        ],
        "placetype": [
          "aat:300008798"
        ],
        "id": 2700249,
        "name:xx": "Sturgeon Ridge"
      }
    }
  ]
}
