{
  "geometry": {
    "type": "Point",
    "coordinates": [
      34.446118,
      25.444261
    ]
  },
  "type": "Feature",
  "properties": {
    "hierarchy": [
      "tgn:7534789",
      "tgn:7001242",
      "tgn:7001311",
      "tgn:7016833",
      "tgn:7029392"
    ],
    "placetype": [
      "aat:300008795"
    ],
    "name:en": "Kadabūrah al Ḩamrā', Jabal",
    "id": 7534789
  }
}
