{
  "geometry": {
    "type": "Point",
    "coordinates": [
      -88.0667,
      37.25
    ]
  },
  "type": "Feature",
  "properties": {
    "hierarchy": [
      "tgn:2266256",
      "tgn:1000001",
      "tgn:7012149",
      "tgn:2000784",
      "tgn:7007255",
      "tgn:7029392"
    ],
    "placetype": [
      "aat:300008798"
    ],
    "id": 2266256,
    "name:xx": "Crayne Knob"
  }
}
