{
  "geometry": {
    "type": "Point",
    "coordinates": [
      -83.2167,
      30.6667
    ]
  },
  "type": "Feature",
  "properties": {
    "hierarchy": [
      "tgn:2635970",
      "tgn:1000001",
      "tgn:7012149",
      "tgn:2000383",
      "tgn:7007248",
      "tgn:7029392"
    ],
    "placetype": [
      "aat:300008680"
    ],
    "id": 2635970,
    "name:xx": "Saddle Bags Pond"
  }
}
