{
  "geometry": {
    "type": "Point",
    "coordinates": [
      -75.6667,
      42.9833
    ]
  },
  "type": "Feature",
  "properties": {
    "hierarchy": [
      "tgn:1134050",
      "tgn:1000001",
      "tgn:7012149",
      "tgn:7007568",
      "tgn:7029392"
    ],
    "placetype": [
      "aat:300008706"
    ],
    "id": 1134050,
    "name:xx": "Oneida Creek"
  }
}
