{
  "geometry": {
    "type": "Point",
    "coordinates": [
      -105.95,
      40.6833
    ]
  },
  "type": "Feature",
  "properties": {
    "hierarchy": [
      "tgn:2609138",
      "tgn:1000001",
      "tgn:7012149",
      "tgn:2000226",
      "tgn:7007158",
      "tgn:7029392"
    ],
    "placetype": [
      "aat:300008680"
    ],
    "id": 2609138,
    "name:xx": "Rawah Lakes"
  }
}
