{
  "type": "FeatureCollection",
  "features": [
    {
      "geometry": {
        "type": "Point",
        "coordinates": [
          -85.25,
          36.5333
        ]
      },
      "type": "Feature",
      "properties": {
        "hierarchy": [
          "tgn:2148700",
          "tgn:1000001",
          "tgn:7012149",
          "tgn:2001905",
          "tgn:7007825",
          "tgn:7029392"
        ],
        "placetype": [
          "aat:300266640"
        ],
        "id": 2148700,
        "name:xx": "Barnes Ridge"
      }
    },
    {
      "geometry": {
        "type": "Point",
        "coordinates": [
          -122.4,
          45.4833
        ]
      },
      "type": "Feature",
      "properties": {
        "hierarchy": [
          "tgn:2148701",
          "tgn:1000001",
          "tgn:7012149",
          "tgn:1002699",
          "tgn:7007708",
          "tgn:7029392"
        ],
        "placetype": [
          "aat:300008347"
        ],
        "id": 2148701,
        "name:xx": "Barnes Road"
      }
    },
    {
      "geometry": {
        "type": "Point",
        "coordinates": [
          -83.95,
          39
        ]
      },
      "type": "Feature",
      "properties": {
        "hierarchy": [
          "tgn:2148702",
          "tgn:1000001",
          "tgn:7012149",
          "tgn:7007706",
          "tgn:7029392"
        ],
        "placetype": [
          "aat:300008699"
        ],
        "id": 2148702,
        "name:xx": "Barnes Run"
      }
    },
    {
      "geometry": {
        "type": "Point",
        "coordinates": [
          -81.3333,
          39.7833
        ]
      },
      "type": "Feature",
      "properties": {
        "hierarchy": [
          "tgn:2148703",
          "tgn:1000001",
          "tgn:7012149",
          "tgn:2001619",
          "tgn:7007706",
          "tgn:7029392"
        ],
        "placetype": [
          "aat:300008699"
        ],
        "id": 2148703,
        "name:xx": "Barnes Run"
      }
    },
    {
      "geometry": {
        "type": "Point",
        "coordinates": [
          -80.9833,
          39.6167
        ]
      },
      "type": "Feature",
      "properties": {
        "hierarchy": [
          "tgn:2148704",
          "tgn:1000001",
          "tgn:7012149",
          "tgn:7029392"
        ],
        "placetype": [
          "aat:300008699"
        ],
        "id": 2148704,
        "name:xx": "Barnes Run"
      }
    },
    {
      "geometry": {
        "type": "Point",
        "coordinates": [
          -76.15,
          40.9667
        ]
      },
      "type": "Feature",
      "properties": {
        "hierarchy": [
          "tgn:2148705",
          "tgn:1000001",
          "tgn:7012149",
          "tgn:1002612",
          "tgn:7007710",
          "tgn:7029392"
        ],
        "placetype": [
          "aat:300008699"
        ],
        "id": 2148705,
        "name:xx": "Barnes Run"
      }
    },
    {
      "geometry": {
        "type": "Point",
        "coordinates": [
          -81.1167,
          38.85
        ]
      },
      "type": "Feature",
      "properties": {
        "hierarchy": [
          "tgn:2148706",
          "tgn:1000001",
          "tgn:2002258",
          "tgn:7012149",
          "tgn:7013961",
          "tgn:7029392"
        ],
        "placetype": [
          "aat:300008699"
        ],
        "id": 2148706,
        "name:xx": "Barnes Run"
      }
    },
    {
      "geometry": {
        "type": "Point",
        "coordinates": [
          -81.6,
          38.9333
        ]
      },
      "type": "Feature",
      "properties": {
        "hierarchy": [
          "tgn:2148707",
          "tgn:1000001",
          "tgn:7012149",
          "tgn:2002268",
          "tgn:7013961",
          "tgn:7029392"
        ],
        "placetype": [
          "aat:300008699"
        ],
        "id": 2148707,
        "name:xx": "Barnes Run"
      }
    },
    {
      "geometry": {
        "type": "Point",
        "coordinates": [
          -79.55,
          39.6833
        ]
      },
      "type": "Feature",
      "properties": {
        "hierarchy": [
          "tgn:2148708",
          "tgn:1000001",
          "tgn:7012149",
          "tgn:2002288",
          "tgn:7013961",
          "tgn:7029392"
        ],
        "placetype": [
          "aat:300008699"
        ],
        "id": 2148708,
        "name:xx": "Barnes Run"
      }
    },
    {
      "geometry": {
        "type": "Point",
        "coordinates": [
          -81.2833,
          38.8667
        ]
      },
      "type": "Feature",
      "properties": {
        "hierarchy": [
          "tgn:2148709",
          "tgn:1000001",
          "tgn:7012149",
          "tgn:2002293",
          "tgn:7013961",
          "tgn:7029392"
        ],
        "placetype": [
          "aat:300008699"
        ],
        "id": 2148709,
        "name:xx": "Barnes Run"
      }
    }
  ]
}
