{
  "geometry": {
    "type": "Point",
    "coordinates": [
      -75.35,
      44.3333
    ]
  },
  "type": "Feature",
  "properties": {
    "hierarchy": [
      "tgn:2239094",
      "tgn:1000001",
      "tgn:7012149",
      "tgn:7016021",
      "tgn:7007568",
      "tgn:7029392"
    ],
    "placetype": [
      "aat:300008680"
    ],
    "id": 2239094,
    "name:xx": "Chub Lake"
  }
}
