{
  "type": "FeatureCollection",
  "features": [
    {
      "geometry": {
        "type": "Point",
        "coordinates": [
          11.5,
          52.166667
        ]
      },
      "type": "Feature",
      "properties": {
        "hierarchy": [
          "tgn:7183260",
          "tgn:1000003",
          "tgn:7003687",
          "tgn:7000084",
          "tgn:7029392"
        ],
        "placetype": [
          "aat:300008777"
        ],
        "id": 7183260,
        "name:xx": "Galgen-Berg"
      }
    },
    {
      "geometry": {
        "type": "Point",
        "coordinates": [
          9.983333,
          52.15
        ]
      },
      "type": "Feature",
      "properties": {
        "hierarchy": [
          "tgn:7183261",
          "tgn:1000003",
          "tgn:7003676",
          "tgn:7000084",
          "tgn:7029392"
        ],
        "placetype": [
          "aat:300008777"
        ],
        "id": 7183261,
        "name:xx": "Galgen-Berg"
      }
    },
    {
      "geometry": {
        "type": "Point",
        "coordinates": [
          13.55,
          52.133333
        ]
      },
      "type": "Feature",
      "properties": {
        "hierarchy": [
          "tgn:7183262",
          "tgn:7000096",
          "tgn:1000003",
          "tgn:7000084",
          "tgn:7029392"
        ],
        "placetype": [
          "aat:300008777"
        ],
        "id": 7183262,
        "name:xx": "Galgen-Berg"
      }
    },
    {
      "geometry": {
        "type": "Point",
        "coordinates": [
          10.733333,
          52.133333
        ]
      },
      "type": "Feature",
      "properties": {
        "hierarchy": [
          "tgn:7183264",
          "tgn:1000003",
          "tgn:7003676",
          "tgn:7000084",
          "tgn:7029392"
        ],
        "placetype": [
          "aat:300008777"
        ],
        "id": 7183264,
        "name:xx": "Galgen-Berg"
      }
    },
    {
      "geometry": {
        "type": "Point",
        "coordinates": [
          11.783333,
          52.1
        ]
      },
      "type": "Feature",
      "properties": {
        "hierarchy": [
          "tgn:7183265",
          "tgn:1000003",
          "tgn:7003687",
          "tgn:7000084",
          "tgn:7029392"
        ],
        "placetype": [
          "aat:300008777"
        ],
        "id": 7183265,
        "name:xx": "Galgen-Berg"
      }
    },
    {
      "geometry": {
        "type": "Point",
        "coordinates": [
          14.483333,
          52.033333
        ]
      },
      "type": "Feature",
      "properties": {
        "hierarchy": [
          "tgn:7183267",
          "tgn:7000096",
          "tgn:1000003",
          "tgn:7000084",
          "tgn:7029392"
        ],
        "placetype": [
          "aat:300008777"
        ],
        "id": 7183267,
        "name:xx": "Galgen-Berg"
      }
    },
    {
      "geometry": {
        "type": "Point",
        "coordinates": [
          11.783333,
          54.15
        ]
      },
      "type": "Feature",
      "properties": {
        "hierarchy": [
          "tgn:7183268",
          "tgn:1000003",
          "tgn:7000094",
          "tgn:7000084",
          "tgn:7029392"
        ],
        "placetype": [
          "aat:300008347"
        ],
        "id": 7183268,
        "name:xx": "Fulgen"
      }
    }
  ]
}
