{
  "geometry": {
    "type": "Point",
    "coordinates": [
      -78.3667,
      33.9667
    ]
  },
  "type": "Feature",
  "properties": {
    "hierarchy": [
      "tgn:2610321",
      "tgn:1000001",
      "tgn:2001472",
      "tgn:7012149",
      "tgn:7007709",
      "tgn:7029392"
    ],
    "placetype": [
      "aat:300008347"
    ],
    "id": 2610321,
    "name:xx": "Red Bug"
  }
}
