{
  "geometry": {
    "type": "Point",
    "coordinates": [
      -86.6833,
      37.9167
    ]
  },
  "type": "Feature",
  "properties": {
    "hierarchy": [
      "tgn:2254874",
      "tgn:1000001",
      "tgn:7012149",
      "tgn:2000550",
      "tgn:7007252",
      "tgn:7029392"
    ],
    "placetype": [
      "aat:300266640"
    ],
    "id": 2254874,
    "name:xx": "Coontail Ridge"
  }
}
