{
  "geometry": {
    "type": "Point",
    "coordinates": [
      -83.6667,
      32.0833
    ]
  },
  "type": "Feature",
  "properties": {
    "hierarchy": [
      "tgn:2575041",
      "tgn:1000001",
      "tgn:7012149",
      "tgn:2000337",
      "tgn:7007248",
      "tgn:7029392"
    ],
    "placetype": [
      "aat:300008706"
    ],
    "id": 2575041,
    "name:xx": "Pennahatchee Creek"
  }
}
