{
  "geometry": {
    "type": "Point",
    "coordinates": [
      -84.5833,
      40.3833
    ]
  },
  "type": "Feature",
  "properties": {
    "hierarchy": [
      "tgn:2743231",
      "tgn:1000001",
      "tgn:7012149",
      "tgn:1002658",
      "tgn:7007706",
      "tgn:7029392"
    ],
    "placetype": [
      "aat:300006075"
    ],
    "id": 2743231,
    "name:xx": "Vandenbush Ditch"
  }
}
