{
  "geometry": {
    "type": "Point",
    "coordinates": [
      26.3167,
      3.0333
    ]
  },
  "type": "Feature",
  "properties": {
    "hierarchy": [
      "tgn:1089497",
      "tgn:7001242",
      "tgn:7016755",
      "tgn:1000159",
      "tgn:7029392"
    ],
    "placetype": [
      "aat:300008347"
    ],
    "id": 1089497,
    "name:xx": "Senza"
  }
}
