{
  "geometry": {
    "type": "Point",
    "coordinates": [
      -80.5167,
      36.9833
    ]
  },
  "type": "Feature",
  "properties": {
    "hierarchy": [
      "tgn:2111321",
      "tgn:1000001",
      "tgn:7012149",
      "tgn:2002158",
      "tgn:7007919",
      "tgn:7029392"
    ],
    "placetype": [
      "aat:300008347",
      "aat:300387210"
    ],
    "id": 2111321,
    "name:xx": "Copper Valley"
  }
}
