{
  "type": "FeatureCollection",
  "features": [
    {
      "geometry": {
        "type": "Point",
        "coordinates": [
          -70.7,
          41.5
        ]
      },
      "type": "Feature",
      "properties": {
        "hierarchy": [
          "tgn:2205740",
          "tgn:1009982",
          "tgn:1000001",
          "tgn:1002344",
          "tgn:7012149",
          "tgn:7007517",
          "tgn:7029392"
        ],
        "placetype": [
          "aat:300008791"
        ],
        "id": 2205740,
        "name:xx": "Bull Island"
      }
    },
    {
      "geometry": {
        "type": "Point",
        "coordinates": [
          -70.75,
          42.65
        ]
      },
      "type": "Feature",
      "properties": {
        "hierarchy": [
          "tgn:2205741",
          "tgn:1000001",
          "tgn:1002359",
          "tgn:7012149",
          "tgn:7007517",
          "tgn:7029392"
        ],
        "placetype": [
          "aat:300008791"
        ],
        "id": 2205741,
        "name:xx": "Bull Island"
      }
    },
    {
      "geometry": {
        "type": "Point",
        "coordinates": [
          -114.1,
          47.7667
        ]
      },
      "type": "Feature",
      "properties": {
        "hierarchy": [
          "tgn:2205743",
          "tgn:1000001",
          "tgn:7012149",
          "tgn:2001283",
          "tgn:7007524",
          "tgn:7029392"
        ],
        "placetype": [
          "aat:300008791"
        ],
        "id": 2205743,
        "name:xx": "Bull Island"
      }
    },
    {
      "geometry": {
        "type": "Point",
        "coordinates": [
          -124.0667,
          43.9833
        ]
      },
      "type": "Feature",
      "properties": {
        "hierarchy": [
          "tgn:2205744",
          "tgn:1000001",
          "tgn:7012149",
          "tgn:2001716",
          "tgn:7007708",
          "tgn:7029392"
        ],
        "placetype": [
          "aat:300008791"
        ],
        "id": 2205744,
        "name:xx": "Bull Island"
      }
    },
    {
      "geometry": {
        "type": "Point",
        "coordinates": [
          -80.8333,
          32.1667
        ]
      },
      "type": "Feature",
      "properties": {
        "hierarchy": [
          "tgn:2205746",
          "tgn:2001731",
          "tgn:1000001",
          "tgn:7012149",
          "tgn:7007712",
          "tgn:7029392"
        ],
        "placetype": [
          "aat:300008791"
        ],
        "id": 2205746,
        "name:xx": "Bull Island"
      }
    },
    {
      "geometry": {
        "type": "Point",
        "coordinates": [
          -79.6,
          32.9
        ]
      },
      "type": "Feature",
      "properties": {
        "hierarchy": [
          "tgn:2205747",
          "tgn:1000001",
          "tgn:2001734",
          "tgn:7012149",
          "tgn:7007712",
          "tgn:7029392"
        ],
        "placetype": [
          "aat:300008791"
        ],
        "id": 2205747,
        "name:xx": "Bull Island"
      }
    },
    {
      "geometry": {
        "type": "Point",
        "coordinates": [
          -90.3833,
          29.15
        ]
      },
      "type": "Feature",
      "properties": {
        "hierarchy": [
          "tgn:2205748",
          "tgn:1000001",
          "tgn:7012149",
          "tgn:2000882",
          "tgn:7007256",
          "tgn:7029392"
        ],
        "placetype": [
          "aat:300386853"
        ],
        "id": 2205748,
        "name:xx": "Bull Islands"
      }
    },
    {
      "geometry": {
        "type": "Point",
        "coordinates": [
          -121.4167,
          43.2
        ]
      },
      "type": "Feature",
      "properties": {
        "hierarchy": [
          "tgn:2205749",
          "tgn:1000001",
          "tgn:7012149",
          "tgn:2001714",
          "tgn:7007708",
          "tgn:7029392"
        ],
        "placetype": [
          "aat:300008697"
        ],
        "id": 2205749,
        "name:xx": "Bull Jack Spring"
      }
    }
  ]
}
