{
  "geometry": {
    "type": "Point",
    "coordinates": [
      21.736944,
      39.2375
    ]
  },
  "type": "Feature",
  "properties": {
    "hierarchy": [
      "tgn:7223440",
      "tgn:7002748",
      "tgn:7001399",
      "tgn:1000003",
      "tgn:1000074",
      "tgn:7029392"
    ],
    "placetype": [
      "aat:300008795"
    ],
    "id": 7223440,
    "name:xx": "Mándra"
  }
}
