{
  "geometry": {
    "type": "Point",
    "coordinates": [
      -100.05,
      35.1333
    ]
  },
  "type": "Feature",
  "properties": {
    "hierarchy": [
      "tgn:2471054",
      "tgn:1000001",
      "tgn:7012149",
      "tgn:2001960",
      "tgn:7007826",
      "tgn:7029392"
    ],
    "placetype": [
      "aat:300008706"
    ],
    "id": 2471054,
    "name:xx": "Lost Creek"
  }
}
