{
  "geometry": {
    "type": "Point",
    "coordinates": [
      -80.1667,
      39.5833
    ]
  },
  "type": "Feature",
  "properties": {
    "hierarchy": [
      "tgn:2567216",
      "tgn:1000001",
      "tgn:7012149",
      "tgn:2002275",
      "tgn:7013961",
      "tgn:7029392"
    ],
    "placetype": [
      "aat:300008699"
    ],
    "id": 2567216,
    "name:xx": "Panther Lick Run"
  }
}
