{
  "geometry": {
    "type": "Point",
    "coordinates": [
      -117.2167,
      34.1833
    ]
  },
  "type": "Feature",
  "properties": {
    "hierarchy": [
      "tgn:2460406",
      "tgn:1000001",
      "tgn:7012149",
      "tgn:7007157",
      "tgn:1002857",
      "tgn:7029392"
    ],
    "placetype": [
      "aat:300008761"
    ],
    "id": 2460406,
    "name:xx": "Little Sand Canyon"
  }
}
