{
  "type": "FeatureCollection",
  "features": [
    {
      "geometry": {
        "type": "Point",
        "coordinates": [
          -121.2,
          36.95
        ]
      },
      "type": "Feature",
      "properties": {
        "hierarchy": [
          "tgn:2226400",
          "tgn:1000001",
          "tgn:7012149",
          "tgn:7007157",
          "tgn:1002656",
          "tgn:7029392"
        ],
        "placetype": [
          "aat:300008798"
        ],
        "id": 2226400,
        "name:xx": "Cathedral Peak"
      }
    },
    {
      "geometry": {
        "type": "Point",
        "coordinates": [
          -119.4,
          37.8333
        ]
      },
      "type": "Feature",
      "properties": {
        "hierarchy": [
          "tgn:2226401",
          "tgn:1000001",
          "tgn:7012149",
          "tgn:7007157",
          "tgn:7029392"
        ],
        "placetype": [
          "aat:300008798"
        ],
        "id": 2226401,
        "name:xx": "Cathedral Peak"
      }
    },
    {
      "geometry": {
        "type": "Point",
        "coordinates": [
          -119.7,
          34.4833
        ]
      },
      "type": "Feature",
      "properties": {
        "hierarchy": [
          "tgn:2226402",
          "tgn:1000001",
          "tgn:7012149",
          "tgn:7007157",
          "tgn:1002867",
          "tgn:7029392"
        ],
        "placetype": [
          "aat:300008798"
        ],
        "id": 2226402,
        "name:xx": "Cathedral Peak"
      }
    },
    {
      "geometry": {
        "type": "Point",
        "coordinates": [
          -106.85,
          39.0333
        ]
      },
      "type": "Feature",
      "properties": {
        "hierarchy": [
          "tgn:2226403",
          "tgn:1000001",
          "tgn:7012149",
          "tgn:7007158",
          "tgn:2000240",
          "tgn:7029392"
        ],
        "placetype": [
          "aat:300008798"
        ],
        "id": 2226403,
        "name:xx": "Cathedral Peak"
      }
    },
    {
      "geometry": {
        "type": "Point",
        "coordinates": [
          -107.5,
          38.5833
        ]
      },
      "type": "Feature",
      "properties": {
        "hierarchy": [
          "tgn:2226404",
          "tgn:1000001",
          "tgn:7012149",
          "tgn:2000234",
          "tgn:7007158",
          "tgn:7029392"
        ],
        "placetype": [
          "aat:300008798"
        ],
        "id": 2226404,
        "name:xx": "Cathedral Peak"
      }
    },
    {
      "geometry": {
        "type": "Point",
        "coordinates": [
          -116.1333,
          47.9333
        ]
      },
      "type": "Feature",
      "properties": {
        "hierarchy": [
          "tgn:2226405",
          "tgn:1000001",
          "tgn:7012149",
          "tgn:2000491",
          "tgn:7007250",
          "tgn:7029392"
        ],
        "placetype": [
          "aat:300008798"
        ],
        "id": 2226405,
        "name:xx": "Cathedral Peak"
      }
    },
    {
      "geometry": {
        "type": "Point",
        "coordinates": [
          -109.9833,
          45.3167
        ]
      },
      "type": "Feature",
      "properties": {
        "hierarchy": [
          "tgn:2226406",
          "tgn:1000001",
          "tgn:7012149",
          "tgn:2001307",
          "tgn:7007524",
          "tgn:7029392"
        ],
        "placetype": [
          "aat:300008798"
        ],
        "id": 2226406,
        "name:xx": "Cathedral Peak"
      }
    },
    {
      "geometry": {
        "type": "Point",
        "coordinates": [
          -113.3,
          47.8167
        ]
      },
      "type": "Feature",
      "properties": {
        "hierarchy": [
          "tgn:2226407",
          "tgn:1000001",
          "tgn:7012149",
          "tgn:2001274",
          "tgn:7007524",
          "tgn:7029392"
        ],
        "placetype": [
          "aat:300008798"
        ],
        "id": 2226407,
        "name:xx": "Cathedral Peak"
      }
    },
    {
      "geometry": {
        "type": "Point",
        "coordinates": [
          -113.85,
          48.8667
        ]
      },
      "type": "Feature",
      "properties": {
        "hierarchy": [
          "tgn:2226408",
          "tgn:1000001",
          "tgn:7012149",
          "tgn:2001277",
          "tgn:7007524",
          "tgn:7029392"
        ],
        "placetype": [
          "aat:300008798"
        ],
        "id": 2226408,
        "name:xx": "Cathedral Peak"
      }
    },
    {
      "geometry": {
        "type": "Point",
        "coordinates": [
          -104.4833,
          30
        ]
      },
      "type": "Feature",
      "properties": {
        "hierarchy": [
          "tgn:2226409",
          "tgn:1000001",
          "tgn:7012149",
          "tgn:2002057",
          "tgn:7007826",
          "tgn:7029392"
        ],
        "placetype": [
          "aat:300008798"
        ],
        "id": 2226409,
        "name:xx": "Cathedral Peak"
      }
    }
  ]
}
