{
  "geometry": {
    "type": "Point",
    "coordinates": [
      -113.6333,
      37.95
    ]
  },
  "type": "Feature",
  "properties": {
    "hierarchy": [
      "tgn:2755569",
      "tgn:1000001",
      "tgn:7012149",
      "tgn:2002111",
      "tgn:7007827",
      "tgn:7029392"
    ],
    "placetype": [
      "aat:300008798"
    ],
    "id": 2755569,
    "name:xx": "Websters Knolls"
  }
}
