{
  "geometry": {
    "type": "Point",
    "coordinates": [
      -111.3167,
      31.4833
    ]
  },
  "type": "Feature",
  "properties": {
    "hierarchy": [
      "tgn:2219687",
      "tgn:1000001",
      "tgn:7006451",
      "tgn:7012149",
      "tgn:2000102",
      "tgn:7029392"
    ],
    "placetype": [
      "aat:300008761"
    ],
    "id": 2219687,
    "name:xx": "Cañoncito"
  }
}
