{
  "type": "FeatureCollection",
  "features": [
    {
      "geometry": {
        "type": "Point",
        "coordinates": [
          -111.1167,
          42.15
        ]
      },
      "type": "Feature",
      "properties": {
        "hierarchy": [
          "tgn:2514440",
          "tgn:2000455",
          "tgn:1000001",
          "tgn:7012149",
          "tgn:7007250",
          "tgn:7029392"
        ],
        "placetype": [
          "aat:300006075"
        ],
        "id": 2514440,
        "name:xx": "Miller Ditch"
      }
    },
    {
      "geometry": {
        "type": "Point",
        "coordinates": [
          -85.0667,
          40.3833
        ]
      },
      "type": "Feature",
      "properties": {
        "hierarchy": [
          "tgn:2514441",
          "tgn:1000001",
          "tgn:7012149",
          "tgn:1002513",
          "tgn:7007252",
          "tgn:7029392"
        ],
        "placetype": [
          "aat:300006075"
        ],
        "id": 2514441,
        "name:xx": "Miller Ditch"
      }
    },
    {
      "geometry": {
        "type": "Point",
        "coordinates": [
          -85.9667,
          40.55
        ]
      },
      "type": "Feature",
      "properties": {
        "hierarchy": [
          "tgn:2514442",
          "tgn:1000001",
          "tgn:7012149",
          "tgn:1002487",
          "tgn:7007252",
          "tgn:7029392"
        ],
        "placetype": [
          "aat:300006075"
        ],
        "id": 2514442,
        "name:xx": "Miller Ditch"
      }
    },
    {
      "geometry": {
        "type": "Point",
        "coordinates": [
          -86.0167,
          40.5833
        ]
      },
      "type": "Feature",
      "properties": {
        "hierarchy": [
          "tgn:2514443",
          "tgn:1000001",
          "tgn:7012149",
          "tgn:1002661",
          "tgn:7007252",
          "tgn:7029392"
        ],
        "placetype": [
          "aat:300006075"
        ],
        "id": 2514443,
        "name:xx": "Miller Ditch"
      }
    },
    {
      "geometry": {
        "type": "Point",
        "coordinates": [
          -85.0667,
          40.65
        ]
      },
      "type": "Feature",
      "properties": {
        "hierarchy": [
          "tgn:2514444",
          "tgn:1000001",
          "tgn:7012149",
          "tgn:1003010",
          "tgn:7007252",
          "tgn:7029392"
        ],
        "placetype": [
          "aat:300006075"
        ],
        "id": 2514444,
        "name:xx": "Miller Ditch"
      }
    },
    {
      "geometry": {
        "type": "Point",
        "coordinates": [
          -86.2167,
          40.9833
        ]
      },
      "type": "Feature",
      "properties": {
        "hierarchy": [
          "tgn:2514445",
          "tgn:1000001",
          "tgn:7012149",
          "tgn:1002396",
          "tgn:7007252",
          "tgn:7029392"
        ],
        "placetype": [
          "aat:300006075"
        ],
        "id": 2514445,
        "name:xx": "Miller Ditch"
      }
    },
    {
      "geometry": {
        "type": "Point",
        "coordinates": [
          -86.5,
          41.0833
        ]
      },
      "type": "Feature",
      "properties": {
        "hierarchy": [
          "tgn:2514446",
          "tgn:1000001",
          "tgn:7012149",
          "tgn:1002809",
          "tgn:7007252",
          "tgn:7029392"
        ],
        "placetype": [
          "aat:300006075"
        ],
        "id": 2514446,
        "name:xx": "Miller Ditch"
      }
    },
    {
      "geometry": {
        "type": "Point",
        "coordinates": [
          -87.2833,
          38.7833
        ]
      },
      "type": "Feature",
      "properties": {
        "hierarchy": [
          "tgn:2514447",
          "tgn:1000001",
          "tgn:7012149",
          "tgn:2000545",
          "tgn:7007252",
          "tgn:7029392"
        ],
        "placetype": [
          "aat:300006075"
        ],
        "id": 2514447,
        "name:xx": "Miller Ditch"
      }
    },
    {
      "geometry": {
        "type": "Point",
        "coordinates": [
          -84.9167,
          40.7833
        ]
      },
      "type": "Feature",
      "properties": {
        "hierarchy": [
          "tgn:2514448",
          "tgn:1002135",
          "tgn:1000001",
          "tgn:7012149",
          "tgn:7007252",
          "tgn:7029392"
        ],
        "placetype": [
          "aat:300006075"
        ],
        "id": 2514448,
        "name:xx": "Miller Ditch"
      }
    },
    {
      "geometry": {
        "type": "Point",
        "coordinates": [
          -86.4333,
          40.8167
        ]
      },
      "type": "Feature",
      "properties": {
        "hierarchy": [
          "tgn:2514449",
          "tgn:1000001",
          "tgn:1002242",
          "tgn:7012149",
          "tgn:7007252",
          "tgn:7029392"
        ],
        "placetype": [
          "aat:300006075"
        ],
        "id": 2514449,
        "name:xx": "Miller Ditch"
      }
    }
  ]
}
