{
  "geometry": {
    "type": "Point",
    "coordinates": [
      -77.3167,
      42.0167
    ]
  },
  "type": "Feature",
  "properties": {
    "hierarchy": [
      "tgn:2126125",
      "tgn:1000001",
      "tgn:7012149",
      "tgn:1002920",
      "tgn:7007568",
      "tgn:7029392"
    ],
    "placetype": [
      "aat:300008798"
    ],
    "id": 2126125,
    "name:xx": "Addison Hill"
  }
}
