{
  "geometry": {
    "type": "Point",
    "coordinates": [
      -6.95,
      38.8833
    ]
  },
  "type": "Feature",
  "properties": {
    "hierarchy": [
      "tgn:1124061",
      "tgn:1000003",
      "tgn:7029392"
    ],
    "placetype": [
      "aat:300008707"
    ],
    "name:pt": "Xevora, Rio",
    "id": 1124061,
    "name:es": "Gévora"
  }
}
