{
  "geometry": {
    "type": "Point",
    "coordinates": [
      12.75,
      43.4833
    ]
  },
  "type": "Feature",
  "properties": {
    "hierarchy": [
      "tgn:7008386",
      "tgn:1003483",
      "tgn:1000003",
      "tgn:7003240",
      "tgn:1000080",
      "tgn:7029392"
    ],
    "placetype": [
      "aat:300000641",
      "aat:300000833"
    ],
    "id": 7008386,
    "name:xx": "Fonte Avellana, Monastero di"
  }
}
