{
  "type": "FeatureCollection",
  "features": [
    {
      "geometry": {
        "type": "Point",
        "coordinates": [
          -68.866667,
          -19.983333
        ]
      },
      "type": "Feature",
      "properties": {
        "hierarchy": [
          "tgn:7316770",
          "tgn:7002464",
          "tgn:1000049",
          "tgn:1000002",
          "tgn:7029392"
        ],
        "placetype": [
          "aat:300008795"
        ],
        "id": 7316770,
        "name:xx": "Conire, Loma"
      }
    },
    {
      "geometry": {
        "type": "Point",
        "coordinates": [
          -68.85,
          -19.966667
        ]
      },
      "type": "Feature",
      "properties": {
        "hierarchy": [
          "tgn:7316771",
          "tgn:7002464",
          "tgn:1000049",
          "tgn:1000002",
          "tgn:7029392"
        ],
        "placetype": [
          "aat:300387200"
        ],
        "id": 7316771,
        "name:xx": "Conire"
      }
    },
    {
      "geometry": {
        "type": "Point",
        "coordinates": [
          -71.633333,
          -38.65
        ]
      },
      "type": "Feature",
      "properties": {
        "hierarchy": [
          "tgn:7316772",
          "tgn:1001692",
          "tgn:1000049",
          "tgn:1000002",
          "tgn:7029392"
        ],
        "placetype": [
          "aat:300008680"
        ],
        "id": 7316772,
        "name:xx": "Conillio, Lago"
      }
    },
    {
      "geometry": {
        "type": "Point",
        "coordinates": [
          -71.616667,
          -38.65
        ]
      },
      "type": "Feature",
      "properties": {
        "hierarchy": [
          "tgn:7316773",
          "tgn:1001692",
          "tgn:1000049",
          "tgn:1000002",
          "tgn:7029392"
        ],
        "placetype": [
          "aat:300008777"
        ],
        "id": 7316773,
        "name:xx": "Conillio"
      }
    },
    {
      "geometry": {
        "type": "Point",
        "coordinates": [
          -73.133333,
          -40.9
        ]
      },
      "type": "Feature",
      "properties": {
        "hierarchy": [
          "tgn:7316774",
          "tgn:1001699",
          "tgn:1000049",
          "tgn:1000002",
          "tgn:7029392"
        ],
        "placetype": [
          "aat:300008699"
        ],
        "id": 7316774,
        "name:xx": "Coñico, Río"
      }
    },
    {
      "geometry": {
        "type": "Point",
        "coordinates": [
          -73,
          -52.933333
        ]
      },
      "type": "Feature",
      "properties": {
        "hierarchy": [
          "tgn:7316775",
          "tgn:1001702",
          "tgn:1000049",
          "tgn:1000002",
          "tgn:7029392"
        ],
        "placetype": [
          "aat:300008795"
        ],
        "id": 7316775,
        "name:xx": "Cónico, Monte"
      }
    },
    {
      "geometry": {
        "type": "Point",
        "coordinates": [
          -74.833333,
          -51.733333
        ]
      },
      "type": "Feature",
      "properties": {
        "hierarchy": [
          "tgn:7316776",
          "tgn:1001702",
          "tgn:1000049",
          "tgn:1000002",
          "tgn:7029392"
        ],
        "placetype": [
          "aat:300008795"
        ],
        "id": 7316776,
        "name:xx": "Cónico, Monte"
      }
    },
    {
      "geometry": {
        "type": "Point",
        "coordinates": [
          -72.4,
          -39.816667
        ]
      },
      "type": "Feature",
      "properties": {
        "hierarchy": [
          "tgn:7316777",
          "tgn:1001699",
          "tgn:1000049",
          "tgn:1000002",
          "tgn:7029392"
        ],
        "placetype": [
          "aat:300008699"
        ],
        "id": 7316777,
        "name:xx": "Coñico, Estero"
      }
    },
    {
      "geometry": {
        "type": "Point",
        "coordinates": [
          -75.083333,
          -48.516667
        ]
      },
      "type": "Feature",
      "properties": {
        "hierarchy": [
          "tgn:7316778",
          "tgn:1001623",
          "tgn:1000049",
          "tgn:1000002",
          "tgn:7029392"
        ],
        "placetype": [
          "aat:300008795"
        ],
        "id": 7316778,
        "name:xx": "Cónico, Cerro"
      }
    },
    {
      "geometry": {
        "type": "Point",
        "coordinates": [
          -71.216667,
          -38.666667
        ]
      },
      "type": "Feature",
      "properties": {
        "hierarchy": [
          "tgn:7316779",
          "tgn:1001692",
          "tgn:1000049",
          "tgn:1000002",
          "tgn:7029392"
        ],
        "placetype": [
          "aat:300008795"
        ],
        "id": 7316779,
        "name:xx": "Cónico, Cerro"
      }
    }
  ]
}
