{
  "type": "FeatureCollection",
  "features": [
    {
      "geometry": {
        "type": "Point",
        "coordinates": [
          -76.35,
          41.1
        ]
      },
      "type": "Feature",
      "properties": {
        "hierarchy": [
          "tgn:2088530",
          "tgn:1000001",
          "tgn:1002294",
          "tgn:7012149",
          "tgn:7007710",
          "tgn:7029392"
        ],
        "placetype": [
          "aat:300008347",
          "aat:300387210"
        ],
        "id": 2088530,
        "name:xx": "Forks"
      }
    },
    {
      "geometry": {
        "type": "Point",
        "coordinates": [
          -76.1167,
          41.5167
        ]
      },
      "type": "Feature",
      "properties": {
        "hierarchy": [
          "tgn:2088531",
          "tgn:1000001",
          "tgn:7012149",
          "tgn:1003041",
          "tgn:7007710",
          "tgn:7029392"
        ],
        "placetype": [
          "aat:300008347"
        ],
        "id": 2088531,
        "name:xx": "Forkston"
      }
    },
    {
      "geometry": {
        "type": "Point",
        "coordinates": [
          -76.6,
          41.4833
        ]
      },
      "type": "Feature",
      "properties": {
        "hierarchy": [
          "tgn:2088532",
          "tgn:1000001",
          "tgn:7012149",
          "tgn:1002927",
          "tgn:7007710",
          "tgn:7029392"
        ],
        "placetype": [
          "aat:300008347"
        ],
        "id": 2088532,
        "name:xx": "Forksville"
      }
    },
    {
      "geometry": {
        "type": "Point",
        "coordinates": [
          -75.2833,
          41.5667
        ]
      },
      "type": "Feature",
      "properties": {
        "hierarchy": [
          "tgn:2088534",
          "tgn:1000001",
          "tgn:7012149",
          "tgn:1003008",
          "tgn:7007710",
          "tgn:7029392"
        ],
        "placetype": [
          "aat:300008347",
          "aat:300387210"
        ],
        "id": 2088534,
        "name:xx": "Fortenia"
      }
    },
    {
      "geometry": {
        "type": "Point",
        "coordinates": [
          -78.4,
          40.4167
        ]
      },
      "type": "Feature",
      "properties": {
        "hierarchy": [
          "tgn:2088535",
          "tgn:1000001",
          "tgn:1002185",
          "tgn:7012149",
          "tgn:7007710",
          "tgn:7029392"
        ],
        "placetype": [
          "aat:300008347"
        ],
        "id": 2088535,
        "name:xx": "Fort Fetter"
      }
    },
    {
      "geometry": {
        "type": "Point",
        "coordinates": [
          -79.2667,
          39.8167
        ]
      },
      "type": "Feature",
      "properties": {
        "hierarchy": [
          "tgn:2088536",
          "tgn:1000001",
          "tgn:7012149",
          "tgn:1002904",
          "tgn:7007710",
          "tgn:7029392"
        ],
        "placetype": [
          "aat:300008347"
        ],
        "id": 2088536,
        "name:xx": "Fort Hill"
      }
    },
    {
      "geometry": {
        "type": "Point",
        "coordinates": [
          -76.9,
          40.3333
        ]
      },
      "type": "Feature",
      "properties": {
        "hierarchy": [
          "tgn:2088538",
          "tgn:1000001",
          "tgn:1002318",
          "tgn:7012149",
          "tgn:7007710",
          "tgn:7029392"
        ],
        "placetype": [
          "aat:300008347"
        ],
        "id": 2088538,
        "name:xx": "Fort Hunter"
      }
    }
  ]
}
