{
  "geometry": {
    "type": "Point",
    "coordinates": [
      -97.2667,
      34.25
    ]
  },
  "type": "Feature",
  "properties": {
    "hierarchy": [
      "tgn:2083671",
      "tgn:1000001",
      "tgn:2001632",
      "tgn:7012149",
      "tgn:7007707",
      "tgn:7029392"
    ],
    "placetype": [
      "aat:300008347",
      "aat:300387210"
    ],
    "id": 2083671,
    "name:xx": "Newport"
  }
}
