{
  "type": "FeatureCollection",
  "features": [
    {
      "geometry": {
        "type": "Point",
        "coordinates": [
          -77.2167,
          35.2167
        ]
      },
      "type": "Feature",
      "properties": {
        "hierarchy": [
          "tgn:2513770",
          "tgn:1000001",
          "tgn:7012149",
          "tgn:2001486",
          "tgn:7007709",
          "tgn:7029392"
        ],
        "placetype": [
          "aat:300008699"
        ],
        "id": 2513770,
        "name:xx": "Mill Run"
      }
    },
    {
      "geometry": {
        "type": "Point",
        "coordinates": [
          -77.9333,
          35.5833
        ]
      },
      "type": "Feature",
      "properties": {
        "hierarchy": [
          "tgn:2513771",
          "tgn:1000001",
          "tgn:7012149",
          "tgn:2001554",
          "tgn:7007709",
          "tgn:7029392"
        ],
        "placetype": [
          "aat:300008699"
        ],
        "id": 2513771,
        "name:xx": "Mill Run"
      }
    },
    {
      "geometry": {
        "type": "Point",
        "coordinates": [
          -77.7667,
          35.3667
        ]
      },
      "type": "Feature",
      "properties": {
        "hierarchy": [
          "tgn:2513772",
          "tgn:1000001",
          "tgn:7012149",
          "tgn:7007709",
          "tgn:7029392"
        ],
        "placetype": [
          "aat:300008699"
        ],
        "id": 2513772,
        "name:xx": "Mill Run"
      }
    },
    {
      "geometry": {
        "type": "Point",
        "coordinates": [
          -77.6667,
          35.5
        ]
      },
      "type": "Feature",
      "properties": {
        "hierarchy": [
          "tgn:2513773",
          "tgn:1000001",
          "tgn:7012149",
          "tgn:2001499",
          "tgn:7007709",
          "tgn:7029392"
        ],
        "placetype": [
          "aat:300008699"
        ],
        "id": 2513773,
        "name:xx": "Mill Run"
      }
    },
    {
      "geometry": {
        "type": "Point",
        "coordinates": [
          -78.1667,
          34.9833
        ]
      },
      "type": "Feature",
      "properties": {
        "hierarchy": [
          "tgn:2513774",
          "tgn:1000001",
          "tgn:7012149",
          "tgn:2001538",
          "tgn:7007709",
          "tgn:7029392"
        ],
        "placetype": [
          "aat:300008699"
        ],
        "id": 2513774,
        "name:xx": "Mill Run"
      }
    },
    {
      "geometry": {
        "type": "Point",
        "coordinates": [
          -81.85,
          38.9167
        ]
      },
      "type": "Feature",
      "properties": {
        "hierarchy": [
          "tgn:2513775",
          "tgn:1000001",
          "tgn:7012149",
          "tgn:2001616",
          "tgn:7007706",
          "tgn:7029392"
        ],
        "placetype": [
          "aat:300008699"
        ],
        "id": 2513775,
        "name:xx": "Mill Run"
      }
    },
    {
      "geometry": {
        "type": "Point",
        "coordinates": [
          -81.95,
          39.95
        ]
      },
      "type": "Feature",
      "properties": {
        "hierarchy": [
          "tgn:2513776",
          "tgn:1000001",
          "tgn:7012149",
          "tgn:1002701",
          "tgn:7007706",
          "tgn:7029392"
        ],
        "placetype": [
          "aat:300008699"
        ],
        "id": 2513776,
        "name:xx": "Mill Run"
      }
    },
    {
      "geometry": {
        "type": "Point",
        "coordinates": [
          -83.0167,
          40.2833
        ]
      },
      "type": "Feature",
      "properties": {
        "hierarchy": [
          "tgn:2513777",
          "tgn:1000001",
          "tgn:1002329",
          "tgn:7012149",
          "tgn:7007706",
          "tgn:7029392"
        ],
        "placetype": [
          "aat:300008699"
        ],
        "id": 2513777,
        "name:xx": "Mill Run"
      }
    },
    {
      "geometry": {
        "type": "Point",
        "coordinates": [
          -81.75,
          39.5833
        ]
      },
      "type": "Feature",
      "properties": {
        "hierarchy": [
          "tgn:2513778",
          "tgn:1000001",
          "tgn:7012149",
          "tgn:2001618",
          "tgn:7007706",
          "tgn:7029392"
        ],
        "placetype": [
          "aat:300008699"
        ],
        "id": 2513778,
        "name:xx": "Mill Run"
      }
    },
    {
      "geometry": {
        "type": "Point",
        "coordinates": [
          -80.9833,
          40.2667
        ]
      },
      "type": "Feature",
      "properties": {
        "hierarchy": [
          "tgn:2513779",
          "tgn:1000001",
          "tgn:7012149",
          "tgn:1002459",
          "tgn:7007706",
          "tgn:7029392"
        ],
        "placetype": [
          "aat:300008699"
        ],
        "id": 2513779,
        "name:xx": "Mill Run"
      }
    }
  ]
}
