{
  "geometry": {
    "type": "Point",
    "coordinates": [
      -82.1167,
      37.3667
    ]
  },
  "type": "Feature",
  "properties": {
    "hierarchy": [
      "tgn:2487612",
      "tgn:1000001",
      "tgn:2002148",
      "tgn:7012149",
      "tgn:7007919",
      "tgn:7029392"
    ],
    "placetype": [
      "aat:300008706"
    ],
    "id": 2487612,
    "name:xx": "Left Fork Home Creek"
  }
}
