{
  "geometry": {
    "type": "Point",
    "coordinates": [
      -116.9333,
      43.6167
    ]
  },
  "type": "Feature",
  "properties": {
    "hierarchy": [
      "tgn:2385048",
      "tgn:1000001",
      "tgn:7012149",
      "tgn:2000488",
      "tgn:7007250",
      "tgn:7029392"
    ],
    "placetype": [
      "aat:300008791"
    ],
    "id": 2385048,
    "name:xx": "Heltons Island"
  }
}
