{
  "geometry": {
    "type": "Point",
    "coordinates": [
      -93.2667,
      46.6833
    ]
  },
  "type": "Feature",
  "properties": {
    "hierarchy": [
      "tgn:2291576",
      "tgn:2000999",
      "tgn:1000001",
      "tgn:7012149",
      "tgn:7007521",
      "tgn:7029392"
    ],
    "placetype": [
      "aat:300008680"
    ],
    "id": 2291576,
    "name:xx": "Dollar Lake"
  }
}
