{
  "geometry": {
    "type": "Point",
    "coordinates": [
      -112.1667,
      47.0667
    ]
  },
  "type": "Feature",
  "properties": {
    "hierarchy": [
      "tgn:2210781",
      "tgn:1000001",
      "tgn:7012149",
      "tgn:2001284",
      "tgn:7007524",
      "tgn:7029392"
    ],
    "placetype": [
      "aat:300008798"
    ],
    "id": 2210781,
    "name:xx": "Butcher Mountain"
  }
}
