{
  "geometry": {
    "type": "Point",
    "coordinates": [
      -125.2333,
      50.1667
    ]
  },
  "type": "Feature",
  "properties": {
    "hierarchy": [
      "tgn:1008692",
      "tgn:7005735",
      "tgn:7005685",
      "tgn:1000001",
      "tgn:7029392"
    ],
    "placetype": [
      "aat:300008791"
    ],
    "id": 1008692,
    "name:xx": "Quadra Island"
  }
}
