{
  "type": "FeatureCollection",
  "features": [
    {
      "geometry": {
        "type": "Point",
        "coordinates": [
          -79.9167,
          9.2
        ]
      },
      "type": "Feature",
      "properties": {
        "hierarchy": [
          "tgn:1119812",
          "tgn:1000001",
          "tgn:7005565",
          "tgn:7029392"
        ],
        "placetype": [
          "aat:300006191"
        ],
        "id": 1119812,
        "name:xx": "Gatún, Lago"
      }
    },
    {
      "geometry": {
        "type": "Point",
        "coordinates": [
          20.75,
          42.9333
        ]
      },
      "type": "Feature",
      "properties": {
        "hierarchy": [
          "tgn:1119813",
          "tgn:7015191",
          "tgn:7029392"
        ],
        "placetype": [
          "aat:300006191"
        ],
        "id": 1119813,
        "name:xx": "Gazivoda Jezero"
      }
    },
    {
      "geometry": {
        "type": "Point",
        "coordinates": [
          -85.9833,
          39.9
        ]
      },
      "type": "Feature",
      "properties": {
        "hierarchy": [
          "tgn:1119814",
          "tgn:1000001",
          "tgn:7012149",
          "tgn:7007252",
          "tgn:7029392"
        ],
        "placetype": [
          "aat:300006191"
        ],
        "id": 1119814,
        "name:xx": "Geist Reservoir"
      }
    },
    {
      "geometry": {
        "type": "Point",
        "coordinates": [
          -97.7167,
          30.6667
        ]
      },
      "type": "Feature",
      "properties": {
        "hierarchy": [
          "tgn:1119816",
          "tgn:1000001",
          "tgn:7012149",
          "tgn:1003026",
          "tgn:7007826",
          "tgn:7029392"
        ],
        "placetype": [
          "aat:300006191"
        ],
        "id": 1119816,
        "name:xx": "Georgetown, Lake"
      }
    },
    {
      "geometry": {
        "type": "Point",
        "coordinates": [
          -121.1167,
          42.2
        ]
      },
      "type": "Feature",
      "properties": {
        "hierarchy": [
          "tgn:1119817",
          "tgn:1000001",
          "tgn:7012149",
          "tgn:2001714",
          "tgn:7007708",
          "tgn:7029392"
        ],
        "placetype": [
          "aat:300006191"
        ],
        "id": 1119817,
        "name:xx": "Gerber Reservoir"
      }
    },
    {
      "geometry": {
        "type": "Point",
        "coordinates": [
          83.203161,
          24.62402
        ]
      },
      "type": "Feature",
      "properties": {
        "hierarchy": [
          "tgn:1119818",
          "tgn:1000004",
          "tgn:7000198",
          "tgn:7016722",
          "tgn:7029392"
        ],
        "placetype": [
          "aat:300006191"
        ],
        "name:en": "Ghaghar Reservoir",
        "id": 1119818
      }
    },
    {
      "geometry": {
        "type": "Point",
        "coordinates": [
          -79.2333,
          43.1
        ]
      },
      "type": "Feature",
      "properties": {
        "hierarchy": [
          "tgn:1119819",
          "tgn:7005685",
          "tgn:1000001",
          "tgn:7013154",
          "tgn:7029392"
        ],
        "placetype": [
          "aat:300006191"
        ],
        "id": 1119819,
        "name:xx": "Gibson, Lake"
      }
    }
  ]
}
