{
  "geometry": {
    "type": "Point",
    "coordinates": [
      21.95,
      -7.0667
    ]
  },
  "type": "Feature",
  "properties": {
    "hierarchy": [
      "tgn:1088895",
      "tgn:1001143",
      "tgn:7001242",
      "tgn:1000159",
      "tgn:7029392"
    ],
    "placetype": [
      "aat:300008347"
    ],
    "id": 1088895,
    "name:xx": "Bumbo"
  }
}
