{
  "type": "FeatureCollection",
  "features": [
    {
      "geometry": {
        "type": "Point",
        "coordinates": [
          -116.55,
          42.5167
        ]
      },
      "type": "Feature",
      "properties": {
        "hierarchy": [
          "tgn:2262651",
          "tgn:1000001",
          "tgn:7012149",
          "tgn:2000488",
          "tgn:7007250",
          "tgn:7029392"
        ],
        "placetype": [
          "aat:300008697"
        ],
        "id": 2262651,
        "name:xx": "Cow Spring"
      }
    },
    {
      "geometry": {
        "type": "Point",
        "coordinates": [
          -112.1167,
          43.0333
        ]
      },
      "type": "Feature",
      "properties": {
        "hierarchy": [
          "tgn:2262652",
          "tgn:1000001",
          "tgn:2000457",
          "tgn:7012149",
          "tgn:7007250",
          "tgn:7029392"
        ],
        "placetype": [
          "aat:300008697"
        ],
        "id": 2262652,
        "name:xx": "Cow Spring"
      }
    },
    {
      "geometry": {
        "type": "Point",
        "coordinates": [
          -115,
          35.5667
        ]
      },
      "type": "Feature",
      "properties": {
        "hierarchy": [
          "tgn:2262653",
          "tgn:1000001",
          "tgn:2001410",
          "tgn:7012149",
          "tgn:7007526",
          "tgn:7029392"
        ],
        "placetype": [
          "aat:300008697"
        ],
        "id": 2262653,
        "name:xx": "Cow Spring"
      }
    },
    {
      "geometry": {
        "type": "Point",
        "coordinates": [
          -119.7667,
          40.7
        ]
      },
      "type": "Feature",
      "properties": {
        "hierarchy": [
          "tgn:2262654",
          "tgn:1000001",
          "tgn:7012149",
          "tgn:1002999",
          "tgn:7007526",
          "tgn:7029392"
        ],
        "placetype": [
          "aat:300008697"
        ],
        "id": 2262654,
        "name:xx": "Cow Spring"
      }
    },
    {
      "geometry": {
        "type": "Point",
        "coordinates": [
          -109.9,
          39.0833
        ]
      },
      "type": "Feature",
      "properties": {
        "hierarchy": [
          "tgn:2262655",
          "tgn:1000001",
          "tgn:7012149",
          "tgn:2002110",
          "tgn:7007827",
          "tgn:7029392"
        ],
        "placetype": [
          "aat:300008697"
        ],
        "id": 2262655,
        "name:xx": "Cow Spring"
      }
    },
    {
      "geometry": {
        "type": "Point",
        "coordinates": [
          -110.75,
          39.9667
        ]
      },
      "type": "Feature",
      "properties": {
        "hierarchy": [
          "tgn:2262656",
          "tgn:1000001",
          "tgn:2002107",
          "tgn:7012149",
          "tgn:7007827",
          "tgn:7029392"
        ],
        "placetype": [
          "aat:300008697"
        ],
        "id": 2262656,
        "name:xx": "Cow Spring"
      }
    },
    {
      "geometry": {
        "type": "Point",
        "coordinates": [
          -109.8333,
          40.5833
        ]
      },
      "type": "Feature",
      "properties": {
        "hierarchy": [
          "tgn:2262657",
          "tgn:1000001",
          "tgn:7012149",
          "tgn:2002124",
          "tgn:7007827",
          "tgn:7029392"
        ],
        "placetype": [
          "aat:300008697"
        ],
        "id": 2262657,
        "name:xx": "Cow Spring"
      }
    },
    {
      "geometry": {
        "type": "Point",
        "coordinates": [
          -109.3333,
          40.95
        ]
      },
      "type": "Feature",
      "properties": {
        "hierarchy": [
          "tgn:2262658",
          "tgn:1000001",
          "tgn:2002105",
          "tgn:7012149",
          "tgn:7007827",
          "tgn:7029392"
        ],
        "placetype": [
          "aat:300008697"
        ],
        "id": 2262658,
        "name:xx": "Cow Spring"
      }
    },
    {
      "geometry": {
        "type": "Point",
        "coordinates": [
          -110.4,
          37.55
        ]
      },
      "type": "Feature",
      "properties": {
        "hierarchy": [
          "tgn:2262659",
          "tgn:1000001",
          "tgn:7012149",
          "tgn:2002119",
          "tgn:7007827",
          "tgn:7029392"
        ],
        "placetype": [
          "aat:300008697"
        ],
        "id": 2262659,
        "name:xx": "Cow Spring"
      }
    }
  ]
}
