{
  "geometry": {
    "type": "Point",
    "coordinates": [
      74.283534,
      33.791307
    ]
  },
  "type": "Feature",
  "properties": {
    "hierarchy": [
      "tgn:7590308",
      "tgn:1000004",
      "tgn:7000198",
      "tgn:7000799",
      "tgn:7029392"
    ],
    "placetype": [
      "aat:300008347"
    ],
    "name:en": "Tārāgarh",
    "id": 7590308
  }
}
