{
  "geometry": {
    "type": "Point",
    "coordinates": [
      -94.7333,
      39.2667
    ]
  },
  "type": "Feature",
  "properties": {
    "hierarchy": [
      "tgn:2361973",
      "tgn:1000001",
      "tgn:7012149",
      "tgn:2001231",
      "tgn:7007523",
      "tgn:7029392"
    ],
    "placetype": [
      "aat:300006191"
    ],
    "id": 2361973,
    "name:xx": "Gray Lake"
  }
}
