{
  "geometry": {
    "type": "Point",
    "coordinates": [
      -79.95,
      40.9333
    ]
  },
  "type": "Feature",
  "properties": {
    "hierarchy": [
      "tgn:2093894",
      "tgn:1000001",
      "tgn:1002217",
      "tgn:7012149",
      "tgn:7007710",
      "tgn:7029392"
    ],
    "placetype": [
      "aat:300008347"
    ],
    "id": 2093894,
    "name:xx": "Unionville"
  }
}
