{
  "geometry": {
    "type": "Point",
    "coordinates": [
      -95.1167,
      43.3667
    ]
  },
  "type": "Feature",
  "properties": {
    "hierarchy": [
      "tgn:2739950",
      "tgn:1000001",
      "tgn:2000590",
      "tgn:7012149",
      "tgn:7007253",
      "tgn:7029392"
    ],
    "placetype": [
      "aat:300008680"
    ],
    "id": 2739950,
    "name:xx": "Upper Gar Lake"
  }
}
