{
  "geometry": {
    "type": "Point",
    "coordinates": [
      -71.2333,
      42.0333
    ]
  },
  "type": "Feature",
  "properties": {
    "hierarchy": [
      "tgn:2385790",
      "tgn:1000001",
      "tgn:7012149",
      "tgn:7007517",
      "tgn:7029392"
    ],
    "placetype": [
      "aat:300008699"
    ],
    "id": 2385790,
    "name:xx": "Henkes Brook"
  }
}
