{
  "geometry": {
    "type": "Point",
    "coordinates": [
      -75.5333,
      39.5167
    ]
  },
  "type": "Feature",
  "properties": {
    "hierarchy": [
      "tgn:2175923",
      "tgn:7014201",
      "tgn:1000001",
      "tgn:7012149",
      "tgn:7007239",
      "tgn:7029392"
    ],
    "placetype": [
      "aat:300132348"
    ],
    "id": 2175923,
    "name:xx": "Black Ditch Bar"
  }
}
