{
  "geometry": {
    "type": "Point",
    "coordinates": [
      -93.8167,
      34.8833
    ]
  },
  "type": "Feature",
  "properties": {
    "hierarchy": [
      "tgn:2549017",
      "tgn:1000001",
      "tgn:7016172",
      "tgn:7012149",
      "tgn:2000168",
      "tgn:7029392"
    ],
    "placetype": [
      "aat:300008706"
    ],
    "id": 2549017,
    "name:xx": "North Prong Brush Creek"
  }
}
