{
  "geometry": {
    "type": "Point",
    "coordinates": [
      -76.6333,
      40.2167
    ]
  },
  "type": "Feature",
  "properties": {
    "hierarchy": [
      "tgn:2414337",
      "tgn:1000001",
      "tgn:1002318",
      "tgn:7012149",
      "tgn:7007710",
      "tgn:7029392"
    ],
    "placetype": [
      "aat:300008699"
    ],
    "id": 2414337,
    "name:xx": "Iron Run"
  }
}
