{
  "geometry": {
    "type": "Point",
    "coordinates": [
      -109.6333,
      41.0167
    ]
  },
  "type": "Feature",
  "properties": {
    "hierarchy": [
      "tgn:2450550",
      "tgn:1000001",
      "tgn:7012149",
      "tgn:2002383",
      "tgn:7007923",
      "tgn:7029392"
    ],
    "placetype": [
      "aat:300008761"
    ],
    "id": 2450550,
    "name:xx": "Linwood Canyon"
  }
}
