{
  "geometry": {
    "type": "Point",
    "coordinates": [
      -75.15,
      39.95
    ]
  },
  "type": "Feature",
  "properties": {
    "hierarchy": [
      "tgn:2592876",
      "tgn:1000001",
      "tgn:7012149",
      "tgn:1002782",
      "tgn:7007710",
      "tgn:7029392"
    ],
    "placetype": [
      "aat:300008347"
    ],
    "id": 2592876,
    "name:xx": "Poplar"
  }
}
