{
  "type": "FeatureCollection",
  "features": [
    {
      "geometry": {
        "type": "Point",
        "coordinates": [
          -106.9333,
          37.6667
        ]
      },
      "type": "Feature",
      "properties": {
        "hierarchy": [
          "tgn:2173790",
          "tgn:1000001",
          "tgn:7012149",
          "tgn:2000231",
          "tgn:7007158",
          "tgn:7029392"
        ],
        "placetype": [
          "aat:300008706"
        ],
        "id": 2173790,
        "name:xx": "Bird Creek"
      }
    },
    {
      "geometry": {
        "type": "Point",
        "coordinates": [
          -82.8167,
          29.1833
        ]
      },
      "type": "Feature",
      "properties": {
        "hierarchy": [
          "tgn:2173791",
          "tgn:1000001",
          "tgn:7012149",
          "tgn:2000277",
          "tgn:7007240",
          "tgn:7029392"
        ],
        "placetype": [
          "aat:300008706"
        ],
        "id": 2173791,
        "name:xx": "Bird Creek"
      }
    },
    {
      "geometry": {
        "type": "Point",
        "coordinates": [
          -113.9667,
          45.3
        ]
      },
      "type": "Feature",
      "properties": {
        "hierarchy": [
          "tgn:2173792",
          "tgn:1000001",
          "tgn:7012149",
          "tgn:2000481",
          "tgn:7007250",
          "tgn:7029392"
        ],
        "placetype": [
          "aat:300008706"
        ],
        "id": 2173792,
        "name:xx": "Bird Creek"
      }
    },
    {
      "geometry": {
        "type": "Point",
        "coordinates": [
          -115.1833,
          43.6333
        ]
      },
      "type": "Feature",
      "properties": {
        "hierarchy": [
          "tgn:2173793",
          "tgn:1000001",
          "tgn:7012149",
          "tgn:2000471",
          "tgn:7007250",
          "tgn:7029392"
        ],
        "placetype": [
          "aat:300008706"
        ],
        "id": 2173793,
        "name:xx": "Bird Creek"
      }
    },
    {
      "geometry": {
        "type": "Point",
        "coordinates": [
          -115.6167,
          47.3
        ]
      },
      "type": "Feature",
      "properties": {
        "hierarchy": [
          "tgn:2173794",
          "tgn:1000001",
          "tgn:7012149",
          "tgn:2000491",
          "tgn:7007250",
          "tgn:7029392"
        ],
        "placetype": [
          "aat:300008706"
        ],
        "id": 2173794,
        "name:xx": "Bird Creek"
      }
    },
    {
      "geometry": {
        "type": "Point",
        "coordinates": [
          -96.6333,
          37.8
        ]
      },
      "type": "Feature",
      "properties": {
        "hierarchy": [
          "tgn:2173795",
          "tgn:1000001",
          "tgn:2000667",
          "tgn:7012149",
          "tgn:7007254",
          "tgn:7029392"
        ],
        "placetype": [
          "aat:300008706"
        ],
        "id": 2173795,
        "name:xx": "Bird Creek"
      }
    },
    {
      "geometry": {
        "type": "Point",
        "coordinates": [
          -92,
          31.9833
        ]
      },
      "type": "Feature",
      "properties": {
        "hierarchy": [
          "tgn:2173796",
          "tgn:1000001",
          "tgn:2000864",
          "tgn:7012149",
          "tgn:7007256",
          "tgn:7029392"
        ],
        "placetype": [
          "aat:300008706"
        ],
        "id": 2173796,
        "name:xx": "Bird Creek"
      }
    },
    {
      "geometry": {
        "type": "Point",
        "coordinates": [
          -87.7,
          45.6667
        ]
      },
      "type": "Feature",
      "properties": {
        "hierarchy": [
          "tgn:2173797",
          "tgn:1000001",
          "tgn:7012149",
          "tgn:2000978",
          "tgn:7007520",
          "tgn:7029392"
        ],
        "placetype": [
          "aat:300008706"
        ],
        "id": 2173797,
        "name:xx": "Bird Creek"
      }
    },
    {
      "geometry": {
        "type": "Point",
        "coordinates": [
          -84.5167,
          41.8167
        ]
      },
      "type": "Feature",
      "properties": {
        "hierarchy": [
          "tgn:2173798",
          "tgn:1000001",
          "tgn:7012149",
          "tgn:1002481",
          "tgn:7007520",
          "tgn:7029392"
        ],
        "placetype": [
          "aat:300008706"
        ],
        "id": 2173798,
        "name:xx": "Bird Creek"
      }
    },
    {
      "geometry": {
        "type": "Point",
        "coordinates": [
          -82.9333,
          43.9
        ]
      },
      "type": "Feature",
      "properties": {
        "hierarchy": [
          "tgn:2173799",
          "tgn:1000001",
          "tgn:7012149",
          "tgn:2000964",
          "tgn:7007520",
          "tgn:7029392"
        ],
        "placetype": [
          "aat:300008706"
        ],
        "id": 2173799,
        "name:xx": "Bird Creek"
      }
    }
  ]
}
