{
  "geometry": {
    "type": "Point",
    "coordinates": [
      -95.3667,
      43.75
    ]
  },
  "type": "Feature",
  "properties": {
    "hierarchy": [
      "tgn:2055005",
      "tgn:1000001",
      "tgn:7012149",
      "tgn:2001030",
      "tgn:7007521",
      "tgn:7029392"
    ],
    "placetype": [
      "aat:300387016"
    ],
    "id": 2055005,
    "name:xx": "Miloma"
  }
}
