{
  "geometry": {
    "type": "Point",
    "coordinates": [
      15.2667,
      51.0167
    ]
  },
  "type": "Feature",
  "properties": {
    "hierarchy": [
      "tgn:1049201",
      "tgn:7024123",
      "tgn:1000003",
      "tgn:7006366",
      "tgn:7029392"
    ],
    "placetype": [
      "aat:300008347"
    ],
    "id": 1049201,
    "name:xx": "Leśna"
  }
}
