{
  "type": "FeatureCollection",
  "features": [
    {
      "geometry": {
        "type": "Point",
        "coordinates": [
          -111.7,
          38.6833
        ]
      },
      "type": "Feature",
      "properties": {
        "hierarchy": [
          "tgn:2471060",
          "tgn:1000001",
          "tgn:7012149",
          "tgn:2002121",
          "tgn:7007827",
          "tgn:7029392"
        ],
        "placetype": [
          "aat:300008706"
        ],
        "id": 2471060,
        "name:xx": "Lost Creek"
      }
    },
    {
      "geometry": {
        "type": "Point",
        "coordinates": [
          -111.4,
          41.35
        ]
      },
      "type": "Feature",
      "properties": {
        "hierarchy": [
          "tgn:2471061",
          "tgn:1000001",
          "tgn:7012149",
          "tgn:2002115",
          "tgn:7007827",
          "tgn:7029392"
        ],
        "placetype": [
          "aat:300008706"
        ],
        "id": 2471061,
        "name:xx": "Lost Creek"
      }
    },
    {
      "geometry": {
        "type": "Point",
        "coordinates": [
          -82.6,
          36.9
        ]
      },
      "type": "Feature",
      "properties": {
        "hierarchy": [
          "tgn:2471062",
          "tgn:1000001",
          "tgn:7012149",
          "tgn:2002195",
          "tgn:7007919",
          "tgn:7029392"
        ],
        "placetype": [
          "aat:300008706"
        ],
        "id": 2471062,
        "name:xx": "Lost Creek"
      }
    },
    {
      "geometry": {
        "type": "Point",
        "coordinates": [
          -117.4333,
          48.8167
        ]
      },
      "type": "Feature",
      "properties": {
        "hierarchy": [
          "tgn:2471063",
          "tgn:1000001",
          "tgn:7012149",
          "tgn:2002248",
          "tgn:7007920",
          "tgn:7029392"
        ],
        "placetype": [
          "aat:300008706"
        ],
        "id": 2471063,
        "name:xx": "Lost Creek"
      }
    },
    {
      "geometry": {
        "type": "Point",
        "coordinates": [
          -121.7167,
          45.7833
        ]
      },
      "type": "Feature",
      "properties": {
        "hierarchy": [
          "tgn:2471064",
          "tgn:1000001",
          "tgn:7012149",
          "tgn:1002897",
          "tgn:7007920",
          "tgn:7029392"
        ],
        "placetype": [
          "aat:300008706"
        ],
        "id": 2471064,
        "name:xx": "Lost Creek"
      }
    },
    {
      "geometry": {
        "type": "Point",
        "coordinates": [
          -122.5333,
          46.0833
        ]
      },
      "type": "Feature",
      "properties": {
        "hierarchy": [
          "tgn:2471065",
          "tgn:1000001",
          "tgn:1002305",
          "tgn:7012149",
          "tgn:7007920",
          "tgn:7029392"
        ],
        "placetype": [
          "aat:300008706"
        ],
        "id": 2471065,
        "name:xx": "Lost Creek"
      }
    },
    {
      "geometry": {
        "type": "Point",
        "coordinates": [
          -123.2,
          46.5667
        ]
      },
      "type": "Feature",
      "properties": {
        "hierarchy": [
          "tgn:2471066",
          "tgn:1000001",
          "tgn:7012149",
          "tgn:1002594",
          "tgn:7007920",
          "tgn:7029392"
        ],
        "placetype": [
          "aat:300008706"
        ],
        "id": 2471066,
        "name:xx": "Lost Creek"
      }
    },
    {
      "geometry": {
        "type": "Point",
        "coordinates": [
          -121.1167,
          46.8833
        ]
      },
      "type": "Feature",
      "properties": {
        "hierarchy": [
          "tgn:2471067",
          "tgn:1000001",
          "tgn:7012149",
          "tgn:1002553",
          "tgn:7007920",
          "tgn:7029392"
        ],
        "placetype": [
          "aat:300008706"
        ],
        "id": 2471067,
        "name:xx": "Lost Creek"
      }
    },
    {
      "geometry": {
        "type": "Point",
        "coordinates": [
          -121.45,
          47.0167
        ]
      },
      "type": "Feature",
      "properties": {
        "hierarchy": [
          "tgn:2471068",
          "tgn:1000001",
          "tgn:7012149",
          "tgn:1002785",
          "tgn:7007920",
          "tgn:7029392"
        ],
        "placetype": [
          "aat:300008706"
        ],
        "id": 2471068,
        "name:xx": "Lost Creek"
      }
    },
    {
      "geometry": {
        "type": "Point",
        "coordinates": [
          -121.75,
          47.4
        ]
      },
      "type": "Feature",
      "properties": {
        "hierarchy": [
          "tgn:2471069",
          "tgn:1000001",
          "tgn:7012149",
          "tgn:7018871",
          "tgn:7007920",
          "tgn:7029392"
        ],
        "placetype": [
          "aat:300008706"
        ],
        "id": 2471069,
        "name:xx": "Lost Creek"
      }
    }
  ]
}
