{
  "geometry": {
    "type": "Point",
    "coordinates": [
      -71.5833,
      42.6833
    ]
  },
  "type": "Feature",
  "properties": {
    "hierarchy": [
      "tgn:2050312",
      "tgn:1000001",
      "tgn:1002665",
      "tgn:7012149",
      "tgn:7007517",
      "tgn:7029392"
    ],
    "placetype": [
      "aat:300008347",
      "aat:300387210"
    ],
    "id": 2050312,
    "name:xx": "North Pepperell"
  }
}
