{
  "geometry": {
    "type": "Point",
    "coordinates": [
      -117.75,
      48.7167
    ]
  },
  "type": "Feature",
  "properties": {
    "hierarchy": [
      "tgn:2627803",
      "tgn:1000001",
      "tgn:7012149",
      "tgn:2002250",
      "tgn:7007920",
      "tgn:7029392"
    ],
    "placetype": [
      "aat:300008798"
    ],
    "id": 2627803,
    "name:xx": "Rogers, Mount"
  }
}
