{
  "geometry": {
    "type": "Point",
    "coordinates": [
      -91.3833,
      32.1167
    ]
  },
  "type": "Feature",
  "properties": {
    "hierarchy": [
      "tgn:2398916",
      "tgn:1000001",
      "tgn:7012149",
      "tgn:2000907",
      "tgn:7007256",
      "tgn:7029392"
    ],
    "placetype": [
      "aat:300008347"
    ],
    "id": 2398916,
    "name:xx": "Hopewell Landing"
  }
}
