{
  "geometry": {
    "type": "Point",
    "coordinates": [
      -81.7167,
      36.3833
    ]
  },
  "type": "Feature",
  "properties": {
    "hierarchy": [
      "tgn:2749000",
      "tgn:1000001",
      "tgn:7012149",
      "tgn:7007709",
      "tgn:7029392"
    ],
    "placetype": [
      "aat:300008699"
    ],
    "id": 2749000,
    "name:xx": "Wallace Branch"
  }
}
