{
  "geometry": {
    "type": "Point",
    "coordinates": [
      -79.6667,
      40.7833
    ]
  },
  "type": "Feature",
  "properties": {
    "hierarchy": [
      "tgn:2665762",
      "tgn:1002153",
      "tgn:1000001",
      "tgn:7012149",
      "tgn:7007710",
      "tgn:7029392"
    ],
    "placetype": [
      "aat:300008699"
    ],
    "id": 2665762,
    "name:xx": "Sipes Run"
  }
}
