{
  "geometry": {
    "type": "Point",
    "coordinates": [
      -70.6667,
      42.6167
    ]
  },
  "type": "Feature",
  "properties": {
    "hierarchy": [
      "tgn:2049828",
      "tgn:1000001",
      "tgn:1002359",
      "tgn:7012149",
      "tgn:7014073",
      "tgn:7007517",
      "tgn:7029392"
    ],
    "placetype": [
      "aat:300000745"
    ],
    "id": 2049828,
    "name:xx": "Riverview"
  }
}
