{
  "geometry": {
    "type": "Point",
    "coordinates": [
      117.25,
      34.5833
    ]
  },
  "type": "Feature",
  "properties": {
    "hierarchy": [
      "tgn:1118679",
      "tgn:1000004",
      "tgn:1000111",
      "tgn:7029392"
    ],
    "placetype": [
      "aat:300008680"
    ],
    "id": 1118679,
    "name:xx": "Weishan Hu"
  }
}
