{
  "type": "FeatureCollection",
  "features": [
    {
      "geometry": {
        "type": "Point",
        "coordinates": [
          11.55,
          49.466667
        ]
      },
      "type": "Feature",
      "properties": {
        "hierarchy": [
          "tgn:7136720",
          "tgn:7003669",
          "tgn:1000003",
          "tgn:7000084",
          "tgn:7029392"
        ],
        "placetype": [
          "aat:300008777"
        ],
        "id": 7136720,
        "name:xx": "Laubberg"
      }
    },
    {
      "geometry": {
        "type": "Point",
        "coordinates": [
          11.8,
          49.35
        ]
      },
      "type": "Feature",
      "properties": {
        "hierarchy": [
          "tgn:7136721",
          "tgn:7003669",
          "tgn:1000003",
          "tgn:7000084",
          "tgn:7029392"
        ],
        "placetype": [
          "aat:300008777"
        ],
        "id": 7136721,
        "name:xx": "Laubberg"
      }
    },
    {
      "geometry": {
        "type": "Point",
        "coordinates": [
          12.466667,
          50.5
        ]
      },
      "type": "Feature",
      "properties": {
        "hierarchy": [
          "tgn:7136722",
          "tgn:1000003",
          "tgn:7003685",
          "tgn:7000084",
          "tgn:7029392"
        ],
        "placetype": [
          "aat:300000206"
        ],
        "id": 7136722,
        "name:xx": "Laubberg"
      }
    },
    {
      "geometry": {
        "type": "Point",
        "coordinates": [
          9.4,
          47.933333
        ]
      },
      "type": "Feature",
      "properties": {
        "hierarchy": [
          "tgn:7136723",
          "tgn:7003692",
          "tgn:1000003",
          "tgn:7000084",
          "tgn:7029392"
        ],
        "placetype": [
          "aat:300008347"
        ],
        "id": 7136723,
        "name:xx": "Laubbach"
      }
    },
    {
      "geometry": {
        "type": "Point",
        "coordinates": [
          12.65,
          47.716667
        ]
      },
      "type": "Feature",
      "properties": {
        "hierarchy": [
          "tgn:7136724",
          "tgn:7003669",
          "tgn:1000003",
          "tgn:7000084",
          "tgn:7029392"
        ],
        "placetype": [
          "aat:300008347"
        ],
        "id": 7136724,
        "name:xx": "Laubau"
      }
    },
    {
      "geometry": {
        "type": "Point",
        "coordinates": [
          8.9,
          50.633333
        ]
      },
      "type": "Feature",
      "properties": {
        "hierarchy": [
          "tgn:7136725",
          "tgn:1000003",
          "tgn:7003678",
          "tgn:7000084",
          "tgn:7029392"
        ],
        "placetype": [
          "aat:300008777"
        ],
        "id": 7136725,
        "name:xx": "Laubachs-Kopf"
      }
    },
    {
      "geometry": {
        "type": "Point",
        "coordinates": [
          6.933333,
          50.466667
        ]
      },
      "type": "Feature",
      "properties": {
        "hierarchy": [
          "tgn:7136726",
          "tgn:1000003",
          "tgn:7003682",
          "tgn:7000084",
          "tgn:7029392"
        ],
        "placetype": [
          "aat:300000206"
        ],
        "id": 7136726,
        "name:xx": "Laubachshof"
      }
    },
    {
      "geometry": {
        "type": "Point",
        "coordinates": [
          7.466667,
          50.5
        ]
      },
      "type": "Feature",
      "properties": {
        "hierarchy": [
          "tgn:7136727",
          "tgn:1000003",
          "tgn:7003682",
          "tgn:7000084",
          "tgn:7029392"
        ],
        "placetype": [
          "aat:300008699"
        ],
        "id": 7136727,
        "name:xx": "Lau-Bach"
      }
    },
    {
      "geometry": {
        "type": "Point",
        "coordinates": [
          8.4,
          50.366667
        ]
      },
      "type": "Feature",
      "properties": {
        "hierarchy": [
          "tgn:7136728",
          "tgn:1000003",
          "tgn:7003678",
          "tgn:7000084",
          "tgn:7029392"
        ],
        "placetype": [
          "aat:300008699"
        ],
        "id": 7136728,
        "name:xx": "Laubach"
      }
    },
    {
      "geometry": {
        "type": "Point",
        "coordinates": [
          9.983333,
          48.15
        ]
      },
      "type": "Feature",
      "properties": {
        "hierarchy": [
          "tgn:7136729",
          "tgn:7003692",
          "tgn:1000003",
          "tgn:7000084",
          "tgn:7029392"
        ],
        "placetype": [
          "aat:300008699"
        ],
        "id": 7136729,
        "name:xx": "Laubach"
      }
    }
  ]
}
