{
  "geometry": {
    "type": "Point",
    "coordinates": [
      -98.9667,
      54.8333
    ]
  },
  "type": "Feature",
  "properties": {
    "hierarchy": [
      "tgn:1127221",
      "tgn:7005685",
      "tgn:1000001",
      "tgn:7005734",
      "tgn:7029392"
    ],
    "placetype": [
      "aat:300008707"
    ],
    "id": 1127221,
    "name:xx": "Mitishto River"
  }
}
