{
  "geometry": {
    "type": "Point",
    "coordinates": [
      -82.25,
      29.3667
    ]
  },
  "type": "Feature",
  "properties": {
    "hierarchy": [
      "tgn:2019262",
      "tgn:1000001",
      "tgn:7012149",
      "tgn:1002631",
      "tgn:7007240",
      "tgn:7029392"
    ],
    "placetype": [
      "aat:300008347"
    ],
    "id": 2019262,
    "name:xx": "Fairfield"
  }
}
