{
  "geometry": {
    "type": "Point",
    "coordinates": [
      -87.7333,
      34.5167
    ]
  },
  "type": "Feature",
  "properties": {
    "hierarchy": [
      "tgn:2726361",
      "tgn:7002659",
      "tgn:1000001",
      "tgn:7012149",
      "tgn:2000029",
      "tgn:7029392"
    ],
    "placetype": [
      "aat:300008699"
    ],
    "id": 2726361,
    "name:xx": "Town Branch"
  }
}
