{
  "geometry": {
    "type": "Point",
    "coordinates": [
      -78.65,
      40.8333
    ]
  },
  "type": "Feature",
  "properties": {
    "hierarchy": [
      "tgn:2731308",
      "tgn:1000001",
      "tgn:1002278",
      "tgn:7012149",
      "tgn:7007710",
      "tgn:7029392"
    ],
    "placetype": [
      "aat:300008699"
    ],
    "id": 2731308,
    "name:xx": "Tuckers Run"
  }
}
