{
  "geometry": {
    "type": "Point",
    "coordinates": [
      -114.4833,
      44.4167
    ]
  },
  "type": "Feature",
  "properties": {
    "hierarchy": [
      "tgn:2774498",
      "tgn:1000001",
      "tgn:2000470",
      "tgn:7012149",
      "tgn:7007250",
      "tgn:7029392"
    ],
    "placetype": [
      "aat:300386845"
    ],
    "id": 2774498,
    "name:xx": "Willow Patch"
  }
}
