{
  "geometry": {
    "type": "Point",
    "coordinates": [
      -114.3167,
      45.5667
    ]
  },
  "type": "Feature",
  "properties": {
    "hierarchy": [
      "tgn:2534538",
      "tgn:1000001",
      "tgn:7012149",
      "tgn:2001300",
      "tgn:7007524",
      "tgn:7029392"
    ],
    "placetype": [
      "aat:300000390"
    ],
    "id": 2534538,
    "name:xx": "NW NW Section 21 Mine"
  }
}
