{
  "geometry": {
    "type": "Point",
    "coordinates": [
      -143.1167,
      64.1333
    ]
  },
  "type": "Feature",
  "properties": {
    "hierarchy": [
      "tgn:2550701",
      "tgn:7006450",
      "tgn:1000001",
      "tgn:7012149",
      "tgn:2000085",
      "tgn:7029392"
    ],
    "placetype": [
      "aat:300008706"
    ],
    "id": 2550701,
    "name:xx": "Norvell Creek"
  }
}
