{
  "geometry": {
    "type": "Point",
    "coordinates": [
      121.10729,
      22.88273
    ]
  },
  "type": "Feature",
  "properties": {
    "hierarchy": [
      "tgn:7498479",
      "tgn:1000004",
      "tgn:7491221",
      "tgn:1000141",
      "tgn:7029392"
    ],
    "placetype": [
      "aat:300007836"
    ],
    "id": 7498479,
    "name:xx": "Jiafeng Qiao"
  }
}
