{
  "geometry": {
    "type": "Point",
    "coordinates": [
      -76.7667,
      34.7833
    ]
  },
  "type": "Feature",
  "properties": {
    "hierarchy": [
      "tgn:2173002",
      "tgn:1000001",
      "tgn:2001477",
      "tgn:7012149",
      "tgn:7007709",
      "tgn:7029392"
    ],
    "placetype": [
      "aat:300008699"
    ],
    "id": 2173002,
    "name:xx": "Billys Branch"
  }
}
