{
  "geometry": {
    "type": "Point",
    "coordinates": [
      22.3167,
      54.3167
    ]
  },
  "type": "Feature",
  "properties": {
    "hierarchy": [
      "tgn:1049054",
      "tgn:1000003",
      "tgn:7024118",
      "tgn:7006366",
      "tgn:7029392"
    ],
    "placetype": [
      "aat:300008347"
    ],
    "id": 1049054,
    "name:xx": "Gołdap"
  }
}
