{
  "type": "FeatureCollection",
  "features": [
    {
      "geometry": {
        "type": "Point",
        "coordinates": [
          -83.7167,
          35.1833
        ]
      },
      "type": "Feature",
      "properties": {
        "hierarchy": [
          "tgn:2581910",
          "tgn:1000001",
          "tgn:7012149",
          "tgn:2001515",
          "tgn:7007709",
          "tgn:7029392"
        ],
        "placetype": [
          "aat:300008699"
        ],
        "id": 2581910,
        "name:xx": "Pine Branch"
      }
    },
    {
      "geometry": {
        "type": "Point",
        "coordinates": [
          -82.6333,
          35.8833
        ]
      },
      "type": "Feature",
      "properties": {
        "hierarchy": [
          "tgn:2581911",
          "tgn:1000001",
          "tgn:7012149",
          "tgn:2001516",
          "tgn:7007709",
          "tgn:7029392"
        ],
        "placetype": [
          "aat:300008699"
        ],
        "id": 2581911,
        "name:xx": "Pine Branch"
      }
    },
    {
      "geometry": {
        "type": "Point",
        "coordinates": [
          -82.0667,
          35.9333
        ]
      },
      "type": "Feature",
      "properties": {
        "hierarchy": [
          "tgn:2581912",
          "tgn:1000001",
          "tgn:7012149",
          "tgn:2001519",
          "tgn:7007709",
          "tgn:7029392"
        ],
        "placetype": [
          "aat:300008699"
        ],
        "id": 2581912,
        "name:xx": "Pine Branch"
      }
    },
    {
      "geometry": {
        "type": "Point",
        "coordinates": [
          -81.9833,
          36
        ]
      },
      "type": "Feature",
      "properties": {
        "hierarchy": [
          "tgn:2581913",
          "tgn:2001468",
          "tgn:1000001",
          "tgn:7012149",
          "tgn:7007709",
          "tgn:7029392"
        ],
        "placetype": [
          "aat:300008699"
        ],
        "id": 2581913,
        "name:xx": "Pine Branch"
      }
    },
    {
      "geometry": {
        "type": "Point",
        "coordinates": [
          -80.8167,
          36.4
        ]
      },
      "type": "Feature",
      "properties": {
        "hierarchy": [
          "tgn:2581914",
          "tgn:1000001",
          "tgn:7012149",
          "tgn:2001542",
          "tgn:7007709",
          "tgn:7029392"
        ],
        "placetype": [
          "aat:300008699"
        ],
        "id": 2581914,
        "name:xx": "Pine Branch"
      }
    },
    {
      "geometry": {
        "type": "Point",
        "coordinates": [
          -79.3167,
          35.85
        ]
      },
      "type": "Feature",
      "properties": {
        "hierarchy": [
          "tgn:2581915",
          "tgn:2001463",
          "tgn:1000001",
          "tgn:7012149",
          "tgn:7007709",
          "tgn:7029392"
        ],
        "placetype": [
          "aat:300008699"
        ],
        "id": 2581915,
        "name:xx": "Pine Branch"
      }
    },
    {
      "geometry": {
        "type": "Point",
        "coordinates": [
          -81.5667,
          36.25
        ]
      },
      "type": "Feature",
      "properties": {
        "hierarchy": [
          "tgn:2581916",
          "tgn:1000001",
          "tgn:7012149",
          "tgn:2001551",
          "tgn:7007709",
          "tgn:7029392"
        ],
        "placetype": [
          "aat:300008699"
        ],
        "id": 2581916,
        "name:xx": "Pine Branch"
      }
    },
    {
      "geometry": {
        "type": "Point",
        "coordinates": [
          -81.3667,
          33.95
        ]
      },
      "type": "Feature",
      "properties": {
        "hierarchy": [
          "tgn:2581917",
          "tgn:1000001",
          "tgn:7012149",
          "tgn:2001756",
          "tgn:7007712",
          "tgn:7029392"
        ],
        "placetype": [
          "aat:300008699"
        ],
        "id": 2581917,
        "name:xx": "Pine Branch"
      }
    },
    {
      "geometry": {
        "type": "Point",
        "coordinates": [
          -85.4667,
          35.45
        ]
      },
      "type": "Feature",
      "properties": {
        "hierarchy": [
          "tgn:2581918",
          "tgn:1000001",
          "tgn:7012149",
          "tgn:2001913",
          "tgn:7007825",
          "tgn:7029392"
        ],
        "placetype": [
          "aat:300008699"
        ],
        "id": 2581918,
        "name:xx": "Pine Branch"
      }
    },
    {
      "geometry": {
        "type": "Point",
        "coordinates": [
          -84.9167,
          35.6333
        ]
      },
      "type": "Feature",
      "properties": {
        "hierarchy": [
          "tgn:2581919",
          "tgn:1000001",
          "tgn:7012149",
          "tgn:2001908",
          "tgn:7007825",
          "tgn:7029392"
        ],
        "placetype": [
          "aat:300008699"
        ],
        "id": 2581919,
        "name:xx": "Pine Branch"
      }
    }
  ]
}
