{
  "geometry": {
    "type": "Point",
    "coordinates": [
      -77.2667,
      37.15
    ]
  },
  "type": "Feature",
  "properties": {
    "hierarchy": [
      "tgn:2534328",
      "tgn:1000001",
      "tgn:7012149",
      "tgn:1002805",
      "tgn:7007919",
      "tgn:7029392"
    ],
    "placetype": [
      "aat:300006191"
    ],
    "id": 2534328,
    "name:xx": "N and W Pond"
  }
}
