{
  "type": "FeatureCollection",
  "features": [
    {
      "geometry": {
        "type": "Point",
        "coordinates": [
          12.466667,
          48.266667
        ]
      },
      "type": "Feature",
      "properties": {
        "hierarchy": [
          "tgn:7108420",
          "tgn:7003669",
          "tgn:1000003",
          "tgn:7000084",
          "tgn:7029392"
        ],
        "placetype": [
          "aat:300000206"
        ],
        "id": 7108420,
        "name:xx": "Reit"
      }
    },
    {
      "geometry": {
        "type": "Point",
        "coordinates": [
          12.033333,
          48.166667
        ]
      },
      "type": "Feature",
      "properties": {
        "hierarchy": [
          "tgn:7108421",
          "tgn:7003669",
          "tgn:1000003",
          "tgn:7000084",
          "tgn:7029392"
        ],
        "placetype": [
          "aat:300000206"
        ],
        "id": 7108421,
        "name:xx": "Reit"
      }
    },
    {
      "geometry": {
        "type": "Point",
        "coordinates": [
          12.616667,
          48.1
        ]
      },
      "type": "Feature",
      "properties": {
        "hierarchy": [
          "tgn:7108422",
          "tgn:7003669",
          "tgn:1000003",
          "tgn:7000084",
          "tgn:7029392"
        ],
        "placetype": [
          "aat:300000206"
        ],
        "id": 7108422,
        "name:xx": "Reit"
      }
    },
    {
      "geometry": {
        "type": "Point",
        "coordinates": [
          12.566667,
          47.983333
        ]
      },
      "type": "Feature",
      "properties": {
        "hierarchy": [
          "tgn:7108424",
          "tgn:7003669",
          "tgn:1000003",
          "tgn:7000084",
          "tgn:7029392"
        ],
        "placetype": [
          "aat:300000206"
        ],
        "id": 7108424,
        "name:xx": "Reit"
      }
    },
    {
      "geometry": {
        "type": "Point",
        "coordinates": [
          12.7,
          48.116667
        ]
      },
      "type": "Feature",
      "properties": {
        "hierarchy": [
          "tgn:7108425",
          "tgn:7003669",
          "tgn:1000003",
          "tgn:7000084",
          "tgn:7029392"
        ],
        "placetype": [
          "aat:300000206"
        ],
        "id": 7108425,
        "name:xx": "Reit"
      }
    },
    {
      "geometry": {
        "type": "Point",
        "coordinates": [
          12.633333,
          48.133333
        ]
      },
      "type": "Feature",
      "properties": {
        "hierarchy": [
          "tgn:7108426",
          "tgn:7003669",
          "tgn:1000003",
          "tgn:7000084",
          "tgn:7029392"
        ],
        "placetype": [
          "aat:300008347"
        ],
        "id": 7108426,
        "name:xx": "Rehdorf"
      }
    },
    {
      "geometry": {
        "type": "Point",
        "coordinates": [
          8.483333,
          52.533333
        ]
      },
      "type": "Feature",
      "properties": {
        "hierarchy": [
          "tgn:7108427",
          "tgn:1000003",
          "tgn:7003676",
          "tgn:7000084",
          "tgn:7029392"
        ],
        "placetype": [
          "aat:300000206"
        ],
        "id": 7108427,
        "name:xx": "Rehdener Bruchhütte"
      }
    },
    {
      "geometry": {
        "type": "Point",
        "coordinates": [
          8.466667,
          52.55
        ]
      },
      "type": "Feature",
      "properties": {
        "hierarchy": [
          "tgn:7108428",
          "tgn:1000003",
          "tgn:7003676",
          "tgn:7000084",
          "tgn:7029392"
        ],
        "placetype": [
          "aat:300386990"
        ],
        "id": 7108428,
        "name:xx": "Rehdener Bruch"
      }
    }
  ]
}
