{
  "geometry": {
    "type": "Point",
    "coordinates": [
      -122.3167,
      37.9167
    ]
  },
  "type": "Feature",
  "properties": {
    "hierarchy": [
      "tgn:2013596",
      "tgn:1000001",
      "tgn:7012149",
      "tgn:7014335",
      "tgn:1002298",
      "tgn:7007157",
      "tgn:7029392"
    ],
    "placetype": [
      "aat:300000745",
      "aat:300387205"
    ],
    "id": 2013596,
    "name:xx": "Stege"
  }
}
