{
  "geometry": {
    "type": "Point",
    "coordinates": [
      -114.0167,
      37.5167
    ]
  },
  "type": "Feature",
  "properties": {
    "hierarchy": [
      "tgn:2306121",
      "tgn:1000001",
      "tgn:7012149",
      "tgn:7029392"
    ],
    "placetype": [
      "aat:300008699"
    ],
    "id": 2306121,
    "name:xx": "East Fork Beaver Dam Wash"
  }
}
