{
  "geometry": {
    "type": "Point",
    "coordinates": [
      21.169,
      47.583
    ]
  },
  "type": "Feature",
  "properties": {
    "hierarchy": [
      "tgn:7031597",
      "tgn:1000385",
      "tgn:1000003",
      "tgn:7006278",
      "tgn:7029392"
    ],
    "placetype": [
      "aat:300008347"
    ],
    "name:en": "Hortobágy",
    "id": 7031597
  }
}
