{
  "geometry": {
    "type": "Point",
    "coordinates": [
      -107.25,
      31.95
    ]
  },
  "type": "Feature",
  "properties": {
    "hierarchy": [
      "tgn:2176230",
      "tgn:1000001",
      "tgn:2001435",
      "tgn:7012149",
      "tgn:7007566",
      "tgn:7029392"
    ],
    "placetype": [
      "aat:300008798"
    ],
    "id": 2176230,
    "name:xx": "Black Hills"
  }
}
