{
  "geometry": {
    "type": "Point",
    "coordinates": [
      -113.2667,
      37.1833
    ]
  },
  "type": "Feature",
  "properties": {
    "hierarchy": [
      "tgn:2289407",
      "tgn:1000001",
      "tgn:7012149",
      "tgn:2002127",
      "tgn:7007827",
      "tgn:7029392"
    ],
    "placetype": [
      "aat:300008697"
    ],
    "id": 2289407,
    "name:xx": "Dixie Hot Springs"
  }
}
