{
  "type": "FeatureCollection",
  "features": [
    {
      "geometry": {
        "type": "Point",
        "coordinates": [
          -110,
          45.2667
        ]
      },
      "type": "Feature",
      "properties": {
        "hierarchy": [
          "tgn:2139550",
          "tgn:1000001",
          "tgn:7012149",
          "tgn:2001307",
          "tgn:7007524",
          "tgn:7029392"
        ],
        "placetype": [
          "aat:300008680"
        ],
        "id": 2139550,
        "name:xx": "Asteroid Lake"
      }
    },
    {
      "geometry": {
        "type": "Point",
        "coordinates": [
          -68.2667,
          44.3
        ]
      },
      "type": "Feature",
      "properties": {
        "hierarchy": [
          "tgn:2139551",
          "tgn:1000001",
          "tgn:2000922",
          "tgn:7012149",
          "tgn:7007515",
          "tgn:7029392"
        ],
        "placetype": [
          "aat:300008347"
        ],
        "id": 2139551,
        "name:xx": "Asticou"
      }
    },
    {
      "geometry": {
        "type": "Point",
        "coordinates": [
          -96.55,
          30.7
        ]
      },
      "type": "Feature",
      "properties": {
        "hierarchy": [
          "tgn:2139552",
          "tgn:1000001",
          "tgn:7012149",
          "tgn:1002830",
          "tgn:7007826",
          "tgn:7029392"
        ],
        "placetype": [
          "aat:300008347"
        ],
        "id": 2139552,
        "name:xx": "Astin"
      }
    },
    {
      "geometry": {
        "type": "Point",
        "coordinates": [
          -84.9667,
          33.7833
        ]
      },
      "type": "Feature",
      "properties": {
        "hierarchy": [
          "tgn:2139553",
          "tgn:1000001",
          "tgn:2000313",
          "tgn:7012149",
          "tgn:7007248",
          "tgn:7029392"
        ],
        "placetype": [
          "aat:300008706"
        ],
        "id": 2139553,
        "name:xx": "Astin Creek"
      }
    },
    {
      "geometry": {
        "type": "Point",
        "coordinates": [
          -109.25,
          31.35
        ]
      },
      "type": "Feature",
      "properties": {
        "hierarchy": [
          "tgn:2139554",
          "tgn:1000001",
          "tgn:7006451",
          "tgn:2000091",
          "tgn:7012149",
          "tgn:7029392"
        ],
        "placetype": [
          "aat:300008697"
        ],
        "id": 2139554,
        "name:xx": "Astin Spring"
      }
    },
    {
      "geometry": {
        "type": "Point",
        "coordinates": [
          -109.25,
          31.35
        ]
      },
      "type": "Feature",
      "properties": {
        "hierarchy": [
          "tgn:2139555",
          "tgn:1000001",
          "tgn:7006451",
          "tgn:2000091",
          "tgn:7012149",
          "tgn:7029392"
        ],
        "placetype": [
          "aat:300006191"
        ],
        "id": 2139555,
        "name:xx": "Astin Tank"
      }
    },
    {
      "geometry": {
        "type": "Point",
        "coordinates": [
          -110.8833,
          42.8
        ]
      },
      "type": "Feature",
      "properties": {
        "hierarchy": [
          "tgn:2139556",
          "tgn:1000001",
          "tgn:7012149",
          "tgn:2002376",
          "tgn:7007923",
          "tgn:7029392"
        ],
        "placetype": [
          "aat:300008706"
        ],
        "id": 2139556,
        "name:xx": "Astle Creek"
      }
    },
    {
      "geometry": {
        "type": "Point",
        "coordinates": [
          -133.6333,
          57.7
        ]
      },
      "type": "Feature",
      "properties": {
        "hierarchy": [
          "tgn:2139557",
          "tgn:7006450",
          "tgn:1000001",
          "tgn:7012149",
          "tgn:7019760",
          "tgn:7029392"
        ],
        "placetype": [
          "aat:300008850"
        ],
        "id": 2139557,
        "name:xx": "Astley, Point"
      }
    },
    {
      "geometry": {
        "type": "Point",
        "coordinates": [
          -88.0667,
          34.05
        ]
      },
      "type": "Feature",
      "properties": {
        "hierarchy": [
          "tgn:2139558",
          "tgn:7002659",
          "tgn:1000001",
          "tgn:7012149",
          "tgn:2000046",
          "tgn:7029392"
        ],
        "placetype": [
          "aat:300008699"
        ],
        "id": 2139558,
        "name:xx": "Aston Branch"
      }
    },
    {
      "geometry": {
        "type": "Point",
        "coordinates": [
          -132.8333,
          54.9333
        ]
      },
      "type": "Feature",
      "properties": {
        "hierarchy": [
          "tgn:2139559",
          "tgn:7006450",
          "tgn:1000001",
          "tgn:7012149",
          "tgn:2000082",
          "tgn:7029392"
        ],
        "placetype": [
          "aat:300008791"
        ],
        "id": 2139559,
        "name:xx": "Aston Island"
      }
    }
  ]
}
