{
  "geometry": {
    "type": "Point",
    "coordinates": [
      -87.9333,
      36.1333
    ]
  },
  "type": "Feature",
  "properties": {
    "hierarchy": [
      "tgn:2718619",
      "tgn:1000001",
      "tgn:2001839",
      "tgn:7012149",
      "tgn:7007825",
      "tgn:7029392"
    ],
    "placetype": [
      "aat:300008699"
    ],
    "id": 2718619,
    "name:xx": "Thompson Slough"
  }
}
