{
  "type": "FeatureCollection",
  "features": [
    {
      "geometry": {
        "type": "Point",
        "coordinates": [
          -93.8,
          31.45
        ]
      },
      "type": "Feature",
      "properties": {
        "hierarchy": [
          "tgn:2129990",
          "tgn:1000001",
          "tgn:7012149",
          "tgn:2002066",
          "tgn:7007826",
          "tgn:7029392"
        ],
        "placetype": [
          "aat:300008706"
        ],
        "id": 2129990,
        "name:xx": "Allen Creek"
      }
    },
    {
      "geometry": {
        "type": "Point",
        "coordinates": [
          -96.1,
          33.4833
        ]
      },
      "type": "Feature",
      "properties": {
        "hierarchy": [
          "tgn:2129991",
          "tgn:1000001",
          "tgn:7012149",
          "tgn:2001983",
          "tgn:7007826",
          "tgn:7029392"
        ],
        "placetype": [
          "aat:300008706"
        ],
        "id": 2129991,
        "name:xx": "Allen Creek"
      }
    },
    {
      "geometry": {
        "type": "Point",
        "coordinates": [
          -93.9833,
          31.6667
        ]
      },
      "type": "Feature",
      "properties": {
        "hierarchy": [
          "tgn:2129992",
          "tgn:1000001",
          "tgn:7012149",
          "tgn:2002073",
          "tgn:7007826",
          "tgn:7029392"
        ],
        "placetype": [
          "aat:300008706"
        ],
        "id": 2129992,
        "name:xx": "Allen Creek"
      }
    },
    {
      "geometry": {
        "type": "Point",
        "coordinates": [
          -100.9667,
          35.1333
        ]
      },
      "type": "Feature",
      "properties": {
        "hierarchy": [
          "tgn:2129993",
          "tgn:1000001",
          "tgn:7012149",
          "tgn:2001976",
          "tgn:7007826",
          "tgn:7029392"
        ],
        "placetype": [
          "aat:300008706"
        ],
        "id": 2129993,
        "name:xx": "Allen Creek"
      }
    },
    {
      "geometry": {
        "type": "Point",
        "coordinates": [
          -98.8167,
          29.85
        ]
      },
      "type": "Feature",
      "properties": {
        "hierarchy": [
          "tgn:2129994",
          "tgn:1000001",
          "tgn:7012149",
          "tgn:2002015",
          "tgn:7007826",
          "tgn:7029392"
        ],
        "placetype": [
          "aat:300008706"
        ],
        "id": 2129994,
        "name:xx": "Allen Creek"
      }
    },
    {
      "geometry": {
        "type": "Point",
        "coordinates": [
          -95.0333,
          31.6833
        ]
      },
      "type": "Feature",
      "properties": {
        "hierarchy": [
          "tgn:2129995",
          "tgn:1000001",
          "tgn:7012149",
          "tgn:1002263",
          "tgn:7007826",
          "tgn:7029392"
        ],
        "placetype": [
          "aat:300008706"
        ],
        "id": 2129995,
        "name:xx": "Allen Creek"
      }
    },
    {
      "geometry": {
        "type": "Point",
        "coordinates": [
          -111.8333,
          37.7333
        ]
      },
      "type": "Feature",
      "properties": {
        "hierarchy": [
          "tgn:2129996",
          "tgn:1000001",
          "tgn:2002109",
          "tgn:7012149",
          "tgn:7007827",
          "tgn:7029392"
        ],
        "placetype": [
          "aat:300008706"
        ],
        "id": 2129996,
        "name:xx": "Allen Creek"
      }
    },
    {
      "geometry": {
        "type": "Point",
        "coordinates": [
          -109.5,
          40.8333
        ]
      },
      "type": "Feature",
      "properties": {
        "hierarchy": [
          "tgn:2129997",
          "tgn:1000001",
          "tgn:2002105",
          "tgn:7012149",
          "tgn:7007827",
          "tgn:7029392"
        ],
        "placetype": [
          "aat:300008706"
        ],
        "id": 2129997,
        "name:xx": "Allen Creek"
      }
    },
    {
      "geometry": {
        "type": "Point",
        "coordinates": [
          -77.8333,
          36.6333
        ]
      },
      "type": "Feature",
      "properties": {
        "hierarchy": [
          "tgn:2129998",
          "tgn:1000001",
          "tgn:2002147",
          "tgn:7012149",
          "tgn:7007919",
          "tgn:7029392"
        ],
        "placetype": [
          "aat:300008706"
        ],
        "id": 2129998,
        "name:xx": "Allen Creek"
      }
    },
    {
      "geometry": {
        "type": "Point",
        "coordinates": [
          -79.3833,
          38.0167
        ]
      },
      "type": "Feature",
      "properties": {
        "hierarchy": [
          "tgn:2129999",
          "tgn:1000001",
          "tgn:7012149",
          "tgn:2002186",
          "tgn:7007919",
          "tgn:7029392"
        ],
        "placetype": [
          "aat:300008706"
        ],
        "id": 2129999,
        "name:xx": "Allen Creek"
      }
    }
  ]
}
