{
  "geometry": {
    "type": "Point",
    "coordinates": [
      173.5833,
      66.2333
    ]
  },
  "type": "Feature",
  "properties": {
    "hierarchy": [
      "tgn:1125270",
      "tgn:6001445",
      "tgn:1000004",
      "tgn:7018214",
      "tgn:7002435",
      "tgn:7029392"
    ],
    "placetype": [
      "aat:300008707"
    ],
    "id": 1125270,
    "name:xx": "Jurumkuvejem"
  }
}
