{
  "geometry": {
    "type": "Point",
    "coordinates": [
      -92.3167,
      35.8167
    ]
  },
  "type": "Feature",
  "properties": {
    "hierarchy": [
      "tgn:2290147",
      "tgn:1000001",
      "tgn:7016172",
      "tgn:7012149",
      "tgn:2000173",
      "tgn:7029392"
    ],
    "placetype": [
      "aat:300266640"
    ],
    "id": 2290147,
    "name:xx": "Dodd Ridge"
  }
}
