{
  "type": "FeatureCollection",
  "features": [
    {
      "geometry": {
        "type": "Point",
        "coordinates": [
          -86.3667,
          36.8167
        ]
      },
      "type": "Feature",
      "properties": {
        "hierarchy": [
          "tgn:2037884",
          "tgn:1000001",
          "tgn:7012149",
          "tgn:2000848",
          "tgn:7007255",
          "tgn:7029392"
        ],
        "placetype": [
          "aat:300008347",
          "aat:300387210"
        ],
        "id": 2037884,
        "name:xx": "Boyce"
      }
    },
    {
      "geometry": {
        "type": "Point",
        "coordinates": [
          -84.3833,
          38.55
        ]
      },
      "type": "Feature",
      "properties": {
        "hierarchy": [
          "tgn:2037885",
          "tgn:1000001",
          "tgn:7012149",
          "tgn:1002458",
          "tgn:7007255",
          "tgn:7029392"
        ],
        "placetype": [
          "aat:300008347"
        ],
        "id": 2037885,
        "name:xx": "Boyd"
      }
    },
    {
      "geometry": {
        "type": "Point",
        "coordinates": [
          -88.5167,
          36.5
        ]
      },
      "type": "Feature",
      "properties": {
        "hierarchy": [
          "tgn:2037888",
          "tgn:1000001",
          "tgn:7012149",
          "tgn:2000792",
          "tgn:7007255",
          "tgn:7029392"
        ],
        "placetype": [
          "aat:300008347",
          "aat:300387210"
        ],
        "id": 2037888,
        "name:xx": "Boydsville"
      }
    },
    {
      "geometry": {
        "type": "Point",
        "coordinates": [
          -84.5,
          38.2833
        ]
      },
      "type": "Feature",
      "properties": {
        "hierarchy": [
          "tgn:2037889",
          "tgn:1000001",
          "tgn:7012149",
          "tgn:1002880",
          "tgn:7007255",
          "tgn:7029392"
        ],
        "placetype": [
          "aat:300008347",
          "aat:300387210"
        ],
        "id": 2037889,
        "name:xx": "Boydtown"
      }
    }
  ]
}
