{
  "geometry": {
    "type": "Point",
    "coordinates": [
      -118.1333,
      33.9667
    ]
  },
  "type": "Feature",
  "properties": {
    "hierarchy": [
      "tgn:2479336",
      "tgn:1000001",
      "tgn:7012149",
      "tgn:7007157",
      "tgn:1002608",
      "tgn:7029392"
    ],
    "placetype": [
      "aat:300008347"
    ],
    "id": 2479336,
    "name:xx": "Laguna"
  }
}
