{
  "geometry": {
    "type": "Point",
    "coordinates": [
      -94.85,
      45.0667
    ]
  },
  "type": "Feature",
  "properties": {
    "hierarchy": [
      "tgn:2505766",
      "tgn:1000001",
      "tgn:7012149",
      "tgn:2001032",
      "tgn:7007521",
      "tgn:7029392"
    ],
    "placetype": [
      "aat:300008680"
    ],
    "id": 2505766,
    "name:xx": "Mennetaga Lake"
  }
}
