{
  "geometry": {
    "type": "Point",
    "coordinates": [
      -131.9833,
      55.05
    ]
  },
  "type": "Feature",
  "properties": {
    "hierarchy": [
      "tgn:2768071",
      "tgn:7006450",
      "tgn:1000001",
      "tgn:7012149",
      "tgn:2000082",
      "tgn:7029392"
    ],
    "placetype": [
      "aat:300008791"
    ],
    "id": 2768071,
    "name:xx": "Whiterock Island"
  }
}
