{
  "geometry": {
    "type": "Point",
    "coordinates": [
      -82.55,
      32.0833
    ]
  },
  "type": "Feature",
  "properties": {
    "hierarchy": [
      "tgn:2629005",
      "tgn:1000001",
      "tgn:7012149",
      "tgn:2000444",
      "tgn:7007248",
      "tgn:7029392"
    ],
    "placetype": [
      "aat:300008680"
    ],
    "id": 2629005,
    "name:xx": "Rose Dew Lake"
  }
}
