{
  "geometry": {
    "type": "Point",
    "coordinates": [
      -76.5667,
      39.0333
    ]
  },
  "type": "Feature",
  "properties": {
    "hierarchy": [
      "tgn:2198290",
      "tgn:7014651",
      "tgn:1000001",
      "tgn:7012149",
      "tgn:7007516",
      "tgn:7029392"
    ],
    "placetype": [
      "aat:300132316"
    ],
    "id": 2198290,
    "name:xx": "Browns Cove"
  }
}
