{
  "geometry": {
    "type": "Point",
    "coordinates": [
      -84.95,
      42.7833
    ]
  },
  "type": "Feature",
  "properties": {
    "hierarchy": [
      "tgn:2051809",
      "tgn:1000001",
      "tgn:7012149",
      "tgn:1002503",
      "tgn:7007520",
      "tgn:7029392"
    ],
    "placetype": [
      "aat:300008347",
      "aat:300387210"
    ],
    "id": 2051809,
    "name:xx": "Sebewa Corners"
  }
}
