{
  "geometry": {
    "type": "Point",
    "coordinates": [
      120.6999,
      24.1859
    ]
  },
  "type": "Feature",
  "properties": {
    "hierarchy": [
      "tgn:7471118",
      "tgn:1000004",
      "tgn:7001009",
      "tgn:1000141",
      "tgn:7029392"
    ],
    "placetype": [
      "aat:300000745"
    ],
    "id": 7471118,
    "name:xx": "Jiushe"
  }
}
