{
  "type": "FeatureCollection",
  "features": [
    {
      "geometry": {
        "type": "Point",
        "coordinates": [
          -91.7167,
          40.4167
        ]
      },
      "type": "Feature",
      "properties": {
        "hierarchy": [
          "tgn:2059270",
          "tgn:1000001",
          "tgn:2001186",
          "tgn:7012149",
          "tgn:7007523",
          "tgn:7029392"
        ],
        "placetype": [
          "aat:300008347"
        ],
        "id": 2059270,
        "name:xx": "Kahoka"
      }
    },
    {
      "geometry": {
        "type": "Point",
        "coordinates": [
          -92.5833,
          38.1333
        ]
      },
      "type": "Feature",
      "properties": {
        "hierarchy": [
          "tgn:2059271",
          "tgn:1000001",
          "tgn:7012149",
          "tgn:1002671",
          "tgn:7007523",
          "tgn:7029392"
        ],
        "placetype": [
          "aat:300008347"
        ],
        "id": 2059271,
        "name:xx": "Kaiser"
      }
    },
    {
      "geometry": {
        "type": "Point",
        "coordinates": [
          -90.5333,
          38.85
        ]
      },
      "type": "Feature",
      "properties": {
        "hierarchy": [
          "tgn:2059272",
          "tgn:1000001",
          "tgn:7012149",
          "tgn:7016166",
          "tgn:7007523",
          "tgn:7029392"
        ],
        "placetype": [
          "aat:300008347"
        ],
        "id": 2059272,
        "name:xx": "Kampville"
      }
    }
  ]
}
