{
  "geometry": {
    "type": "Point",
    "coordinates": [
      26.9333,
      46.9333
    ]
  },
  "type": "Feature",
  "properties": {
    "hierarchy": [
      "tgn:1050256",
      "tgn:1000003",
      "tgn:1000423",
      "tgn:1000091",
      "tgn:7029392"
    ],
    "placetype": [
      "aat:300008347",
      "aat:300008389",
      "aat:300387235",
      "aat:300387302"
    ],
    "id": 1050256,
    "name:xx": "Roman"
  }
}
