{
  "geometry": {
    "type": "Point",
    "coordinates": [
      -76.8333,
      40.75
    ]
  },
  "type": "Feature",
  "properties": {
    "hierarchy": [
      "tgn:2778248",
      "tgn:1000001",
      "tgn:7012149",
      "tgn:1002732",
      "tgn:7007710",
      "tgn:7029392"
    ],
    "placetype": [
      "aat:300008791"
    ],
    "id": 2778248,
    "name:xx": "Wises Island"
  }
}
