{
  "geometry": {
    "type": "Point",
    "coordinates": [
      -113.6833,
      41.6167
    ]
  },
  "type": "Feature",
  "properties": {
    "hierarchy": [
      "tgn:2629354",
      "tgn:1000001",
      "tgn:2002102",
      "tgn:7012149",
      "tgn:7007827",
      "tgn:7029392"
    ],
    "placetype": [
      "aat:300008697"
    ],
    "id": 2629354,
    "name:xx": "Rosebud Spring"
  }
}
