{
  "geometry": {
    "type": "Point",
    "coordinates": [
      -71.5833,
      42.9667
    ]
  },
  "type": "Feature",
  "properties": {
    "hierarchy": [
      "tgn:2394790",
      "tgn:1000001",
      "tgn:1002480",
      "tgn:7012149",
      "tgn:7007564",
      "tgn:7029392"
    ],
    "placetype": [
      "aat:300008798"
    ],
    "id": 2394790,
    "name:xx": "Holbrook Hill"
  }
}
