{
  "geometry": {
    "type": "Point",
    "coordinates": [
      -86.5333,
      46.1333
    ]
  },
  "type": "Feature",
  "properties": {
    "hierarchy": [
      "tgn:2437130",
      "tgn:1000001",
      "tgn:7012149",
      "tgn:7007520",
      "tgn:7029392"
    ],
    "placetype": [
      "aat:300008706"
    ],
    "id": 2437130,
    "name:xx": "Kilpecker Creek"
  }
}
