{
  "type": "FeatureCollection",
  "features": [
    {
      "geometry": {
        "type": "Point",
        "coordinates": [
          -102.75,
          20.5
        ]
      },
      "type": "Feature",
      "properties": {
        "hierarchy": [
          "tgn:7364790",
          "tgn:7005586",
          "tgn:1000001",
          "tgn:7005560",
          "tgn:7029392"
        ],
        "placetype": [
          "aat:300008347"
        ],
        "id": 7364790,
        "name:xx": "El Puerto del Sabino"
      }
    },
    {
      "geometry": {
        "type": "Point",
        "coordinates": [
          -97.883333,
          25
        ]
      },
      "type": "Feature",
      "properties": {
        "hierarchy": [
          "tgn:7364791",
          "tgn:1000001",
          "tgn:7005597",
          "tgn:7005560",
          "tgn:7029392"
        ],
        "placetype": [
          "aat:300008347"
        ],
        "id": 7364791,
        "name:xx": "El Puerto del Rucio"
      }
    },
    {
      "geometry": {
        "type": "Point",
        "coordinates": [
          -104.566667,
          25.5
        ]
      },
      "type": "Feature",
      "properties": {
        "hierarchy": [
          "tgn:7364792",
          "tgn:7005583",
          "tgn:1000001",
          "tgn:7005560",
          "tgn:7029392"
        ],
        "placetype": [
          "aat:300000241"
        ],
        "id": 7364792,
        "name:xx": "Rancho El Puerto del Prieto"
      }
    },
    {
      "geometry": {
        "type": "Point",
        "coordinates": [
          -102.883333,
          24.2
        ]
      },
      "type": "Feature",
      "properties": {
        "hierarchy": [
          "tgn:7364793",
          "tgn:1000001",
          "tgn:7005601",
          "tgn:7005560",
          "tgn:7029392"
        ],
        "placetype": [
          "aat:300259572"
        ],
        "id": 7364793,
        "name:xx": "El Puerto del Muerto"
      }
    },
    {
      "geometry": {
        "type": "Point",
        "coordinates": [
          -102.716667,
          24.483333
        ]
      },
      "type": "Feature",
      "properties": {
        "hierarchy": [
          "tgn:7364794",
          "tgn:7005583",
          "tgn:1000001",
          "tgn:7005560",
          "tgn:7029392"
        ],
        "placetype": [
          "aat:300008347"
        ],
        "id": 7364794,
        "name:xx": "El Puerto de la Palma"
      }
    },
    {
      "geometry": {
        "type": "Point",
        "coordinates": [
          -111.75,
          30.3
        ]
      },
      "type": "Feature",
      "properties": {
        "hierarchy": [
          "tgn:7364795",
          "tgn:1000001",
          "tgn:1001960",
          "tgn:7005560",
          "tgn:7029392"
        ],
        "placetype": [
          "aat:300008347"
        ],
        "id": 7364795,
        "name:xx": "El Puerto de Camú"
      }
    },
    {
      "geometry": {
        "type": "Point",
        "coordinates": [
          -111.783056,
          30.838611
        ]
      },
      "type": "Feature",
      "properties": {
        "hierarchy": [
          "tgn:7364796",
          "tgn:1000001",
          "tgn:1001960",
          "tgn:7005560",
          "tgn:7029392"
        ],
        "placetype": [
          "aat:300008347"
        ],
        "id": 7364796,
        "name:xx": "El Puerto"
      }
    },
    {
      "geometry": {
        "type": "Point",
        "coordinates": [
          -105.516667,
          30.716667
        ]
      },
      "type": "Feature",
      "properties": {
        "hierarchy": [
          "tgn:7364797",
          "tgn:7005581",
          "tgn:1000001",
          "tgn:7005560",
          "tgn:7029392"
        ],
        "placetype": [
          "aat:300000241"
        ],
        "id": 7364797,
        "name:xx": "Rancho El Puerto"
      }
    },
    {
      "geometry": {
        "type": "Point",
        "coordinates": [
          -108.166667,
          30.133333
        ]
      },
      "type": "Feature",
      "properties": {
        "hierarchy": [
          "tgn:7364798",
          "tgn:7005581",
          "tgn:1000001",
          "tgn:7005560",
          "tgn:7029392"
        ],
        "placetype": [
          "aat:300000241"
        ],
        "id": 7364798,
        "name:xx": "Rancho El Puerto"
      }
    },
    {
      "geometry": {
        "type": "Point",
        "coordinates": [
          -111.35,
          29.3
        ]
      },
      "type": "Feature",
      "properties": {
        "hierarchy": [
          "tgn:7364799",
          "tgn:1000001",
          "tgn:1001960",
          "tgn:7005560",
          "tgn:7029392"
        ],
        "placetype": [
          "aat:300000241"
        ],
        "id": 7364799,
        "name:xx": "Rancho El Puerto"
      }
    }
  ]
}
