{
  "geometry": {
    "type": "Point",
    "coordinates": [
      -147.85,
      63.1833
    ]
  },
  "type": "Feature",
  "properties": {
    "hierarchy": [
      "tgn:2211317",
      "tgn:7006450",
      "tgn:1000001",
      "tgn:2124053",
      "tgn:7012149",
      "tgn:7029392"
    ],
    "placetype": [
      "aat:300008680"
    ],
    "id": 2211317,
    "name:xx": "Butte Lake"
  }
}
