{
  "geometry": {
    "type": "Point",
    "coordinates": [
      -87.8167,
      40.4667
    ]
  },
  "type": "Feature",
  "properties": {
    "hierarchy": [
      "tgn:2408360",
      "tgn:1000001",
      "tgn:7012149",
      "tgn:1002974",
      "tgn:7007251",
      "tgn:7029392"
    ],
    "placetype": [
      "aat:300008347"
    ],
    "id": 2408360,
    "name:xx": "Hustle"
  }
}
