{
  "type": "FeatureCollection",
  "features": [
    {
      "geometry": {
        "type": "Point",
        "coordinates": [
          -97.516667,
          25.016667
        ]
      },
      "type": "Feature",
      "properties": {
        "hierarchy": [
          "tgn:7440430",
          "tgn:1000001",
          "tgn:7005597",
          "tgn:7005560",
          "tgn:7029392"
        ],
        "placetype": [
          "aat:300185707"
        ],
        "id": 7440430,
        "name:xx": "Santa María, Boca"
      }
    },
    {
      "geometry": {
        "type": "Point",
        "coordinates": [
          -97.733333,
          24.233333
        ]
      },
      "type": "Feature",
      "properties": {
        "hierarchy": [
          "tgn:7440431",
          "tgn:1000001",
          "tgn:7005597",
          "tgn:7005560",
          "tgn:7029392"
        ],
        "placetype": [
          "aat:300008679"
        ],
        "id": 7440431,
        "name:xx": "Santa María, Bayuco de"
      }
    },
    {
      "geometry": {
        "type": "Point",
        "coordinates": [
          -115.933333,
          30.383333
        ]
      },
      "type": "Feature",
      "properties": {
        "hierarchy": [
          "tgn:7440432",
          "tgn:1001835",
          "tgn:1000001",
          "tgn:7005560",
          "tgn:7029392"
        ],
        "placetype": [
          "aat:300132316"
        ],
        "id": 7440432,
        "name:xx": "Santa Maria, Bahía"
      }
    },
    {
      "geometry": {
        "type": "Point",
        "coordinates": [
          -108.1,
          25.066667
        ]
      },
      "type": "Feature",
      "properties": {
        "hierarchy": [
          "tgn:7440433",
          "tgn:1000001",
          "tgn:7005595",
          "tgn:7005560",
          "tgn:7029392"
        ],
        "placetype": [
          "aat:300132316"
        ],
        "id": 7440433,
        "name:xx": "Santa María, Bahía"
      }
    },
    {
      "geometry": {
        "type": "Point",
        "coordinates": [
          -112.208333,
          24.725
        ]
      },
      "type": "Feature",
      "properties": {
        "hierarchy": [
          "tgn:7440434",
          "tgn:1001836",
          "tgn:1000001",
          "tgn:7005560",
          "tgn:7029392"
        ],
        "placetype": [
          "aat:300132316"
        ],
        "id": 7440434,
        "name:xx": "Santa María, Bahía"
      }
    },
    {
      "geometry": {
        "type": "Point",
        "coordinates": [
          -107.716667,
          25.583333
        ]
      },
      "type": "Feature",
      "properties": {
        "hierarchy": [
          "tgn:7440435",
          "tgn:1000001",
          "tgn:7005595",
          "tgn:7005560",
          "tgn:7029392"
        ],
        "placetype": [
          "aat:300266554",
          "aat:300008699"
        ],
        "id": 7440435,
        "name:xx": "Santa María, Arroyo"
      }
    },
    {
      "geometry": {
        "type": "Point",
        "coordinates": [
          -105.5,
          22.65
        ]
      },
      "type": "Feature",
      "properties": {
        "hierarchy": [
          "tgn:7440436",
          "tgn:1000001",
          "tgn:7005595",
          "tgn:7005560",
          "tgn:7029392"
        ],
        "placetype": [
          "aat:300008699"
        ],
        "id": 7440436,
        "name:xx": "Santa María, Arroyo"
      }
    },
    {
      "geometry": {
        "type": "Point",
        "coordinates": [
          -98.4,
          23.15
        ]
      },
      "type": "Feature",
      "properties": {
        "hierarchy": [
          "tgn:7440437",
          "tgn:1000001",
          "tgn:7005597",
          "tgn:7005560",
          "tgn:7029392"
        ],
        "placetype": [
          "aat:300266554",
          "aat:300008699"
        ],
        "id": 7440437,
        "name:xx": "Santa María"
      }
    },
    {
      "geometry": {
        "type": "Point",
        "coordinates": [
          -100.916667,
          25.6
        ]
      },
      "type": "Feature",
      "properties": {
        "hierarchy": [
          "tgn:7440438",
          "tgn:1001853",
          "tgn:1000001",
          "tgn:7005560",
          "tgn:7029392"
        ],
        "placetype": [
          "aat:300007783"
        ],
        "id": 7440438,
        "name:xx": "Santa María"
      }
    },
    {
      "geometry": {
        "type": "Point",
        "coordinates": [
          -103.983333,
          20.95
        ]
      },
      "type": "Feature",
      "properties": {
        "hierarchy": [
          "tgn:7440439",
          "tgn:7005586",
          "tgn:1000001",
          "tgn:7005560",
          "tgn:7029392"
        ],
        "placetype": [
          "aat:300000241"
        ],
        "id": 7440439,
        "name:xx": "Santa María"
      }
    }
  ]
}
