{
  "geometry": {
    "type": "Point",
    "coordinates": [
      -91.95,
      33.95
    ]
  },
  "type": "Feature",
  "properties": {
    "hierarchy": [
      "tgn:2008351",
      "tgn:1000001",
      "tgn:7016172",
      "tgn:7012149",
      "tgn:2000144",
      "tgn:7029392"
    ],
    "placetype": [
      "aat:300008347"
    ],
    "id": 2008351,
    "name:xx": "Glendale"
  }
}
