{
  "geometry": {
    "type": "Point",
    "coordinates": [
      -82.5833,
      35.0167
    ]
  },
  "type": "Feature",
  "properties": {
    "hierarchy": [
      "tgn:2578832",
      "tgn:1000001",
      "tgn:7012149",
      "tgn:2001763",
      "tgn:7007712",
      "tgn:7029392"
    ],
    "placetype": [
      "aat:300006191"
    ],
    "id": 2578832,
    "name:xx": "Phillips Lake"
  }
}
