{
  "geometry": {
    "type": "Point",
    "coordinates": [
      88.4167,
      26.1667
    ]
  },
  "type": "Feature",
  "properties": {
    "hierarchy": [
      "tgn:1065913",
      "tgn:1000004",
      "tgn:7000191",
      "tgn:1000105",
      "tgn:7029392"
    ],
    "placetype": [
      "aat:300008347"
    ],
    "id": 1065913,
    "name:xx": "Ruhea"
  }
}
