{
  "geometry": {
    "type": "Point",
    "coordinates": [
      121.3833,
      41.6833
    ]
  },
  "type": "Feature",
  "properties": {
    "hierarchy": [
      "tgn:1067378",
      "tgn:1000004",
      "tgn:1001390",
      "tgn:1000111",
      "tgn:7029392"
    ],
    "placetype": [
      "aat:300008347"
    ],
    "id": 1067378,
    "name:xx": "Dahongtaizi"
  }
}
