{
  "geometry": {
    "type": "Point",
    "coordinates": [
      89.0167,
      23.1667
    ]
  },
  "type": "Feature",
  "properties": {
    "hierarchy": [
      "tgn:1065629",
      "tgn:1000004",
      "tgn:7000190",
      "tgn:1000105",
      "tgn:7029392"
    ],
    "placetype": [
      "aat:300008347"
    ],
    "id": 1065629,
    "name:xx": "Bishahari"
  }
}
