{
  "geometry": {
    "type": "Point",
    "coordinates": [
      24.6667,
      54.6667
    ]
  },
  "type": "Feature",
  "properties": {
    "hierarchy": [
      "tgn:1059301",
      "tgn:7594032",
      "tgn:1000003",
      "tgn:7006542",
      "tgn:7029392"
    ],
    "placetype": [
      "aat:300008347"
    ],
    "id": 1059301,
    "name:xx": "Semeliškės"
  }
}
