{
  "type": "FeatureCollection",
  "features": [
    {
      "geometry": {
        "type": "Point",
        "coordinates": [
          -1.116667,
          41.583333
        ]
      },
      "type": "Feature",
      "properties": {
        "hierarchy": [
          "tgn:7332650",
          "tgn:7002759",
          "tgn:7002845",
          "tgn:1000003",
          "tgn:1000095",
          "tgn:7029392"
        ],
        "placetype": [
          "aat:300008347"
        ],
        "id": 7332650,
        "name:xx": "La Muela"
      }
    },
    {
      "geometry": {
        "type": "Point",
        "coordinates": [
          -3.766667,
          42.733333
        ]
      },
      "type": "Feature",
      "properties": {
        "hierarchy": [
          "tgn:7332651",
          "tgn:7002810",
          "tgn:7001158",
          "tgn:1000003",
          "tgn:1000095",
          "tgn:7029392"
        ],
        "placetype": [
          "aat:300008697"
        ],
        "id": 7332651,
        "name:xx": "Lanchares, Fuente de"
      }
    },
    {
      "geometry": {
        "type": "Point",
        "coordinates": [
          -5.416667,
          36.933333
        ]
      },
      "type": "Feature",
      "properties": {
        "hierarchy": [
          "tgn:7332652",
          "tgn:7002813",
          "tgn:7002758",
          "tgn:1000003",
          "tgn:1000095",
          "tgn:7029392"
        ],
        "placetype": [
          "aat:300008347"
        ],
        "id": 7332652,
        "name:xx": "La Muela"
      }
    },
    {
      "geometry": {
        "type": "Point",
        "coordinates": [
          -1.1,
          37.583333
        ]
      },
      "type": "Feature",
      "properties": {
        "hierarchy": [
          "tgn:7332653",
          "tgn:1001439",
          "tgn:1000003",
          "tgn:7002797",
          "tgn:1000095",
          "tgn:7029392"
        ],
        "placetype": [
          "aat:300008798"
        ],
        "id": 7332653,
        "name:xx": "La Muela"
      }
    },
    {
      "geometry": {
        "type": "Point",
        "coordinates": [
          -1.9,
          39.833333
        ]
      },
      "type": "Feature",
      "properties": {
        "hierarchy": [
          "tgn:7332654",
          "tgn:7002818",
          "tgn:1001647",
          "tgn:1000003",
          "tgn:1000095",
          "tgn:7029392"
        ],
        "placetype": [
          "aat:300387200"
        ],
        "id": 7332654,
        "name:xx": "La Muela"
      }
    },
    {
      "geometry": {
        "type": "Point",
        "coordinates": [
          -1.433333,
          39.75
        ]
      },
      "type": "Feature",
      "properties": {
        "hierarchy": [
          "tgn:7332655",
          "tgn:7002818",
          "tgn:1001647",
          "tgn:1000003",
          "tgn:1000095",
          "tgn:7029392"
        ],
        "placetype": [
          "aat:300387200"
        ],
        "id": 7332655,
        "name:xx": "La Muela"
      }
    },
    {
      "geometry": {
        "type": "Point",
        "coordinates": [
          -2.466667,
          39.7
        ]
      },
      "type": "Feature",
      "properties": {
        "hierarchy": [
          "tgn:7332656",
          "tgn:7002818",
          "tgn:1001647",
          "tgn:1000003",
          "tgn:1000095",
          "tgn:7029392"
        ],
        "placetype": [
          "aat:300387200"
        ],
        "id": 7332656,
        "name:xx": "La Muela"
      }
    },
    {
      "geometry": {
        "type": "Point",
        "coordinates": [
          -2.25,
          39.466667
        ]
      },
      "type": "Feature",
      "properties": {
        "hierarchy": [
          "tgn:7332657",
          "tgn:7002818",
          "tgn:1001647",
          "tgn:1000003",
          "tgn:1000095",
          "tgn:7029392"
        ],
        "placetype": [
          "aat:300387200"
        ],
        "id": 7332657,
        "name:xx": "La Muela"
      }
    },
    {
      "geometry": {
        "type": "Point",
        "coordinates": [
          -1.783333,
          39.366667
        ]
      },
      "type": "Feature",
      "properties": {
        "hierarchy": [
          "tgn:7332658",
          "tgn:7002818",
          "tgn:1001647",
          "tgn:1000003",
          "tgn:1000095",
          "tgn:7029392"
        ],
        "placetype": [
          "aat:300387200"
        ],
        "id": 7332658,
        "name:xx": "La Muela"
      }
    },
    {
      "geometry": {
        "type": "Point",
        "coordinates": [
          -1.683333,
          37.55
        ]
      },
      "type": "Feature",
      "properties": {
        "hierarchy": [
          "tgn:7332659",
          "tgn:1001439",
          "tgn:1000003",
          "tgn:7002797",
          "tgn:1000095",
          "tgn:7029392"
        ],
        "placetype": [
          "aat:300008347"
        ],
        "id": 7332659,
        "name:xx": "La Galera"
      }
    }
  ]
}
