{
  "geometry": {
    "type": "Point",
    "coordinates": [
      -4.966667,
      38.85
    ]
  },
  "type": "Feature",
  "properties": {
    "hierarchy": [
      "tgn:7329464",
      "tgn:7002816",
      "tgn:1001647",
      "tgn:1000003",
      "tgn:1000095",
      "tgn:7029392"
    ],
    "placetype": [
      "aat:300266554",
      "aat:300008699"
    ],
    "id": 7329464,
    "name:xx": "Puerto del Madroñal, Arroyo del"
  }
}
