{
  "geometry": {
    "type": "Point",
    "coordinates": [
      -94.6167,
      60.5167
    ]
  },
  "type": "Feature",
  "properties": {
    "hierarchy": [
      "tgn:1130791",
      "tgn:7005685",
      "tgn:1000001",
      "tgn:7024197",
      "tgn:7029392"
    ],
    "placetype": [
      "aat:300008707"
    ],
    "id": 1130791,
    "name:xx": "Tha-anne"
  }
}
