{
  "type": "FeatureCollection",
  "features": [
    {
      "geometry": {
        "type": "Point",
        "coordinates": [
          -1.133333,
          52.8
        ]
      },
      "type": "Feature",
      "properties": {
        "hierarchy": [
          "tgn:4009192",
          "tgn:7002445",
          "tgn:1000003",
          "tgn:7008167",
          "tgn:7008591",
          "tgn:7029392"
        ],
        "placetype": [
          "aat:300008347",
          "aat:300008372"
        ],
        "name:en": "Rempstone",
        "id": 4009192
      }
    },
    {
      "geometry": {
        "type": "Point",
        "coordinates": [
          11.283333,
          44.766667
        ]
      },
      "type": "Feature",
      "properties": {
        "hierarchy": [
          "tgn:4009195",
          "tgn:7003128",
          "tgn:1000003",
          "tgn:7008516",
          "tgn:1000080",
          "tgn:7029392"
        ],
        "placetype": [
          "aat:300008347"
        ],
        "id": 4009195,
        "name:xx": "Renazzo"
      }
    },
    {
      "geometry": {
        "type": "Point",
        "coordinates": [
          -8.404,
          41.636
        ]
      },
      "type": "Feature",
      "properties": {
        "hierarchy": [
          "tgn:4009198",
          "tgn:7010776",
          "tgn:1000003",
          "tgn:1000090",
          "tgn:7029392"
        ],
        "placetype": [
          "aat:300008347"
        ],
        "id": 4009198,
        "name:xx": "Rendufe"
      }
    },
    {
      "geometry": {
        "type": "Point",
        "coordinates": [
          -3.016667,
          40.483333
        ]
      },
      "type": "Feature",
      "properties": {
        "hierarchy": [
          "tgn:4009199",
          "tgn:7002822",
          "tgn:1001647",
          "tgn:1000003",
          "tgn:1000095",
          "tgn:7029392"
        ],
        "placetype": [
          "aat:300008347"
        ],
        "id": 4009199,
        "name:xx": "Renera"
      }
    }
  ]
}
