{
  "geometry": {
    "type": "Point",
    "coordinates": [
      -87.7333,
      37.0333
    ]
  },
  "type": "Feature",
  "properties": {
    "hierarchy": [
      "tgn:2749096",
      "tgn:1000001",
      "tgn:7012149",
      "tgn:7007255",
      "tgn:7029392"
    ],
    "placetype": [
      "aat:300008699"
    ],
    "id": 2749096,
    "name:xx": "Wallace Fork"
  }
}
