{
  "type": "FeatureCollection",
  "features": [
    {
      "geometry": {
        "type": "Point",
        "coordinates": [
          -93.6167,
          46.45
        ]
      },
      "type": "Feature",
      "properties": {
        "hierarchy": [
          "tgn:2316071",
          "tgn:2000999",
          "tgn:1000001",
          "tgn:7012149",
          "tgn:7007521",
          "tgn:7029392"
        ],
        "placetype": [
          "aat:300008680"
        ],
        "id": 2316071,
        "name:xx": "Elm Island Lake"
      }
    },
    {
      "geometry": {
        "type": "Point",
        "coordinates": [
          -69.9167,
          43.75
        ]
      },
      "type": "Feature",
      "properties": {
        "hierarchy": [
          "tgn:2316072",
          "tgn:1000001",
          "tgn:2000920",
          "tgn:7012149",
          "tgn:7007515",
          "tgn:7029392"
        ],
        "placetype": [
          "aat:300386853"
        ],
        "id": 2316072,
        "name:xx": "Elm Islands"
      }
    },
    {
      "geometry": {
        "type": "Point",
        "coordinates": [
          -97.7167,
          31.1667
        ]
      },
      "type": "Feature",
      "properties": {
        "hierarchy": [
          "tgn:2316073",
          "tgn:1000001",
          "tgn:7012149",
          "tgn:1002303",
          "tgn:7007826",
          "tgn:7029392"
        ],
        "placetype": [
          "aat:300008798"
        ],
        "id": 2316073,
        "name:xx": "Elm Knob"
      }
    },
    {
      "geometry": {
        "type": "Point",
        "coordinates": [
          -93.6667,
          42.75
        ]
      },
      "type": "Feature",
      "properties": {
        "hierarchy": [
          "tgn:2316074",
          "tgn:1000001",
          "tgn:7012149",
          "tgn:2000659",
          "tgn:7007253",
          "tgn:7029392"
        ],
        "placetype": [
          "aat:300008680"
        ],
        "id": 2316074,
        "name:xx": "Elm Lake"
      }
    },
    {
      "geometry": {
        "type": "Point",
        "coordinates": [
          -91.8833,
          31.6167
        ]
      },
      "type": "Feature",
      "properties": {
        "hierarchy": [
          "tgn:2316075",
          "tgn:1000001",
          "tgn:2000866",
          "tgn:7012149",
          "tgn:7007256",
          "tgn:7029392"
        ],
        "placetype": [
          "aat:300008680"
        ],
        "id": 2316075,
        "name:xx": "Elm Lake"
      }
    },
    {
      "geometry": {
        "type": "Point",
        "coordinates": [
          -85.4,
          43.7667
        ]
      },
      "type": "Feature",
      "properties": {
        "hierarchy": [
          "tgn:2316076",
          "tgn:1000001",
          "tgn:7012149",
          "tgn:2000977",
          "tgn:7007520",
          "tgn:7029392"
        ],
        "placetype": [
          "aat:300008680"
        ],
        "id": 2316076,
        "name:xx": "Elm Lake"
      }
    },
    {
      "geometry": {
        "type": "Point",
        "coordinates": [
          -93.7833,
          47.6833
        ]
      },
      "type": "Feature",
      "properties": {
        "hierarchy": [
          "tgn:2316077",
          "tgn:1000001",
          "tgn:7012149",
          "tgn:2001029",
          "tgn:7007521",
          "tgn:7029392"
        ],
        "placetype": [
          "aat:300008680"
        ],
        "id": 2316077,
        "name:xx": "Elm Lake"
      }
    },
    {
      "geometry": {
        "type": "Point",
        "coordinates": [
          -90.9667,
          48.0333
        ]
      },
      "type": "Feature",
      "properties": {
        "hierarchy": [
          "tgn:2316078",
          "tgn:1000001",
          "tgn:2001014",
          "tgn:7012149",
          "tgn:7007521",
          "tgn:7029392"
        ],
        "placetype": [
          "aat:300008680"
        ],
        "id": 2316078,
        "name:xx": "Elm Lake"
      }
    },
    {
      "geometry": {
        "type": "Point",
        "coordinates": [
          -94.4667,
          39
        ]
      },
      "type": "Feature",
      "properties": {
        "hierarchy": [
          "tgn:2316079",
          "tgn:1000001",
          "tgn:7012149",
          "tgn:2001208",
          "tgn:7007523",
          "tgn:7029392"
        ],
        "placetype": [
          "aat:300006191"
        ],
        "id": 2316079,
        "name:xx": "Elm Lake"
      }
    }
  ]
}
