{
  "geometry": {
    "type": "Point",
    "coordinates": [
      -121.8833,
      48.7667
    ]
  },
  "type": "Feature",
  "properties": {
    "hierarchy": [
      "tgn:2751266",
      "tgn:1000001",
      "tgn:7012149",
      "tgn:1003020",
      "tgn:7007920",
      "tgn:7029392"
    ],
    "placetype": [
      "aat:300008706"
    ],
    "id": 2751266,
    "name:xx": "Warm Creek"
  }
}
