{
  "geometry": {
    "type": "Point",
    "coordinates": [
      -80.5833,
      33.8667
    ]
  },
  "type": "Feature",
  "properties": {
    "hierarchy": [
      "tgn:2389686",
      "tgn:1000001",
      "tgn:7012149",
      "tgn:2001767",
      "tgn:7007712",
      "tgn:7029392"
    ],
    "placetype": [
      "aat:300008791"
    ],
    "id": 2389686,
    "name:xx": "High Island"
  }
}
