{
  "geometry": {
    "type": "Point",
    "coordinates": [
      -83.6167,
      38.0167
    ]
  },
  "type": "Feature",
  "properties": {
    "hierarchy": [
      "tgn:2222946",
      "tgn:1000001",
      "tgn:7012149",
      "tgn:7007255",
      "tgn:7029392"
    ],
    "placetype": [
      "aat:300008798"
    ],
    "id": 2222946,
    "name:xx": "Carrington Rock"
  }
}
