{
  "type": "FeatureCollection",
  "features": [
    {
      "geometry": {
        "type": "Point",
        "coordinates": [
          -134.1167,
          58.0833
        ]
      },
      "type": "Feature",
      "properties": {
        "hierarchy": [
          "tgn:2358310",
          "tgn:7006450",
          "tgn:1000001",
          "tgn:7012149",
          "tgn:7019760",
          "tgn:7029392"
        ],
        "placetype": [
          "aat:300008791"
        ],
        "id": 2358310,
        "name:xx": "Grand Island"
      }
    },
    {
      "geometry": {
        "type": "Point",
        "coordinates": [
          -161.4167,
          61.6667
        ]
      },
      "type": "Feature",
      "properties": {
        "hierarchy": [
          "tgn:2358311",
          "tgn:7006450",
          "tgn:1000001",
          "tgn:7012149",
          "tgn:2000087",
          "tgn:7029392"
        ],
        "placetype": [
          "aat:300008791"
        ],
        "id": 2358311,
        "name:xx": "Grand Island"
      }
    },
    {
      "geometry": {
        "type": "Point",
        "coordinates": [
          -121.5667,
          38.2333
        ]
      },
      "type": "Feature",
      "properties": {
        "hierarchy": [
          "tgn:2358312",
          "tgn:1000001",
          "tgn:7012149",
          "tgn:7007157",
          "tgn:1002841",
          "tgn:7029392"
        ],
        "placetype": [
          "aat:300008791"
        ],
        "id": 2358312,
        "name:xx": "Grand Island"
      }
    },
    {
      "geometry": {
        "type": "Point",
        "coordinates": [
          -121.8667,
          39.05
        ]
      },
      "type": "Feature",
      "properties": {
        "hierarchy": [
          "tgn:2358313",
          "tgn:1000001",
          "tgn:7012149",
          "tgn:1002296",
          "tgn:7007157",
          "tgn:7029392"
        ],
        "placetype": [
          "aat:300008347"
        ],
        "id": 2358313,
        "name:xx": "Grand Island"
      }
    },
    {
      "geometry": {
        "type": "Point",
        "coordinates": [
          -105.6,
          39.9667
        ]
      },
      "type": "Feature",
      "properties": {
        "hierarchy": [
          "tgn:2358314",
          "tgn:1000001",
          "tgn:2000198",
          "tgn:7012149",
          "tgn:7007158",
          "tgn:7029392"
        ],
        "placetype": [
          "aat:300008347"
        ],
        "id": 2358314,
        "name:xx": "Grand Island"
      }
    },
    {
      "geometry": {
        "type": "Point",
        "coordinates": [
          -90.1333,
          40.2
        ]
      },
      "type": "Feature",
      "properties": {
        "hierarchy": [
          "tgn:2358315",
          "tgn:1000001",
          "tgn:7012149",
          "tgn:1002643",
          "tgn:7007251",
          "tgn:7029392"
        ],
        "placetype": [
          "aat:300008791"
        ],
        "id": 2358315,
        "name:xx": "Grand Island"
      }
    },
    {
      "geometry": {
        "type": "Point",
        "coordinates": [
          -83.5,
          45.3
        ]
      },
      "type": "Feature",
      "properties": {
        "hierarchy": [
          "tgn:2358316",
          "tgn:1000001",
          "tgn:7012149",
          "tgn:2000990",
          "tgn:7007520",
          "tgn:7029392"
        ],
        "placetype": [
          "aat:300008791"
        ],
        "id": 2358316,
        "name:xx": "Grand Island"
      }
    },
    {
      "geometry": {
        "type": "Point",
        "coordinates": [
          -108.8,
          47.6833
        ]
      },
      "type": "Feature",
      "properties": {
        "hierarchy": [
          "tgn:2358317",
          "tgn:1000001",
          "tgn:7012149",
          "tgn:2001295",
          "tgn:7007524",
          "tgn:7029392"
        ],
        "placetype": [
          "aat:300008791"
        ],
        "id": 2358317,
        "name:xx": "Grand Island"
      }
    },
    {
      "geometry": {
        "type": "Point",
        "coordinates": [
          -98.85,
          40.6833
        ]
      },
      "type": "Feature",
      "properties": {
        "hierarchy": [
          "tgn:2358318",
          "tgn:1000001",
          "tgn:2001325",
          "tgn:7012149",
          "tgn:7007525",
          "tgn:7029392"
        ],
        "placetype": [
          "aat:300008791"
        ],
        "id": 2358318,
        "name:xx": "Grand Island"
      }
    },
    {
      "geometry": {
        "type": "Point",
        "coordinates": [
          -123.0333,
          45.1167
        ]
      },
      "type": "Feature",
      "properties": {
        "hierarchy": [
          "tgn:2358319",
          "tgn:1000001",
          "tgn:7012149",
          "tgn:7007708",
          "tgn:7029392"
        ],
        "placetype": [
          "aat:300008791"
        ],
        "id": 2358319,
        "name:xx": "Grand Island"
      }
    }
  ]
}
