{
  "geometry": {
    "type": "Point",
    "coordinates": [
      0.1833,
      49.4167
    ]
  },
  "type": "Feature",
  "properties": {
    "hierarchy": [
      "tgn:1034822",
      "tgn:7002872",
      "tgn:1000003",
      "tgn:1000070",
      "tgn:7029392"
    ],
    "placetype": [
      "aat:300008347"
    ],
    "id": 1034822,
    "name:xx": "Pennedepie"
  }
}
