{
  "geometry": {
    "type": "Point",
    "coordinates": [
      36.5167,
      49.45
    ]
  },
  "type": "Feature",
  "properties": {
    "hierarchy": [
      "tgn:1051589",
      "tgn:1003361",
      "tgn:1000003",
      "tgn:7006660",
      "tgn:7029392"
    ],
    "placetype": [
      "aat:300008347"
    ],
    "id": 1051589,
    "name:xx": "Shebelinka"
  }
}
