{
  "geometry": {
    "type": "Point",
    "coordinates": [
      -55.9333,
      -1.6167
    ]
  },
  "type": "Feature",
  "properties": {
    "hierarchy": [
      "tgn:1118779",
      "tgn:7006247",
      "tgn:1000047",
      "tgn:7002456",
      "tgn:1000002",
      "tgn:7029392"
    ],
    "placetype": [
      "aat:300008680"
    ],
    "id": 1118779,
    "name:xx": "Xiriri, Lago"
  }
}
