{
  "geometry": {
    "type": "Point",
    "coordinates": [
      25.75,
      -33.4833
    ]
  },
  "type": "Feature",
  "properties": {
    "hierarchy": [
      "tgn:1101365",
      "tgn:7001242",
      "tgn:7017583",
      "tgn:1000193",
      "tgn:7029392"
    ],
    "placetype": [
      "aat:300008189"
    ],
    "id": 1101365,
    "name:xx": "Addo Elephant National Park"
  }
}
