{
  "geometry": {
    "type": "Point",
    "coordinates": [
      -105.0167,
      31.4667
    ]
  },
  "type": "Feature",
  "properties": {
    "hierarchy": [
      "tgn:2135571",
      "tgn:1000001",
      "tgn:7012149",
      "tgn:7007826",
      "tgn:7029392"
    ],
    "placetype": [
      "aat:300008761"
    ],
    "id": 2135571,
    "name:xx": "Apache Canyon"
  }
}
