{
  "geometry": {
    "type": "Point",
    "coordinates": [
      -82.4833,
      23.0667
    ]
  },
  "type": "Feature",
  "properties": {
    "hierarchy": [
      "tgn:1129636",
      "tgn:1001206",
      "tgn:1000001",
      "tgn:7004624",
      "tgn:7029392"
    ],
    "placetype": [
      "aat:300008707"
    ],
    "id": 1129636,
    "name:xx": "Santa Cruz"
  }
}
