{
  "geometry": {
    "type": "Point",
    "coordinates": [
      -85.3833,
      36.1333
    ]
  },
  "type": "Feature",
  "properties": {
    "hierarchy": [
      "tgn:2185426",
      "tgn:1000001",
      "tgn:7012149",
      "tgn:2001907",
      "tgn:7007825",
      "tgn:7029392"
    ],
    "placetype": [
      "aat:300008746"
    ],
    "id": 2185426,
    "name:xx": "Bohannon Cave"
  }
}
