{
  "geometry": {
    "type": "Point",
    "coordinates": [
      -82.7667,
      28.0833
    ]
  },
  "type": "Feature",
  "properties": {
    "hierarchy": [
      "tgn:2636687",
      "tgn:1000001",
      "tgn:7012149",
      "tgn:1002790",
      "tgn:7007240",
      "tgn:7029392"
    ],
    "placetype": [
      "aat:300008697"
    ],
    "id": 2636687,
    "name:xx": "Sage Spring"
  }
}
