{
  "geometry": {
    "type": "Point",
    "coordinates": [
      -92.6833,
      48.1667
    ]
  },
  "type": "Feature",
  "properties": {
    "hierarchy": [
      "tgn:2429988",
      "tgn:1000001",
      "tgn:7012149",
      "tgn:7007521",
      "tgn:7029392"
    ],
    "placetype": [
      "aat:300008863"
    ],
    "id": 2429988,
    "name:xx": "Kabetogama State Forest"
  }
}
