{
  "type": "FeatureCollection",
  "features": [
    {
      "geometry": {
        "type": "Point",
        "coordinates": [
          14.25,
          41.183333
        ]
      },
      "type": "Feature",
      "properties": {
        "hierarchy": [
          "tgn:4008801",
          "tgn:7003011",
          "tgn:7003005",
          "tgn:1000003",
          "tgn:1000080",
          "tgn:7029392"
        ],
        "placetype": [
          "aat:300008347"
        ],
        "id": 4008801,
        "name:xx": "Pontelatone"
      }
    },
    {
      "geometry": {
        "type": "Point",
        "coordinates": [
          1.1667,
          48.4833
        ]
      },
      "type": "Feature",
      "properties": {
        "hierarchy": [
          "tgn:4008804",
          "tgn:1000003",
          "tgn:7002877",
          "tgn:1000070",
          "tgn:7029392"
        ],
        "placetype": [
          "aat:300008347"
        ],
        "id": 4008804,
        "name:xx": "Pontgouin"
      }
    }
  ]
}
