{
  "geometry": {
    "type": "Point",
    "coordinates": [
      32.733333,
      23.15
    ]
  },
  "type": "Feature",
  "properties": {
    "hierarchy": [
      "tgn:7540325",
      "tgn:7001242",
      "tgn:7016833",
      "tgn:7000122",
      "tgn:7029392"
    ],
    "placetype": [
      "aat:300185707"
    ],
    "name:en": "Naj' ad Dakkah al Qiblīyah, Khawr",
    "id": 7540325
  }
}
