{
  "geometry": {
    "type": "Point",
    "coordinates": [
      -83.35,
      30.0167
    ]
  },
  "type": "Feature",
  "properties": {
    "hierarchy": [
      "tgn:2402403",
      "tgn:1000001",
      "tgn:2000275",
      "tgn:7012149",
      "tgn:7007240",
      "tgn:7029392"
    ],
    "placetype": [
      "aat:300008905"
    ],
    "id": 2402403,
    "name:xx": "Horton Sog"
  }
}
