{
  "geometry": {
    "type": "Point",
    "coordinates": [
      27.251077,
      30.676902
    ]
  },
  "type": "Feature",
  "properties": {
    "hierarchy": [
      "tgn:7521920",
      "tgn:7001242",
      "tgn:7016833",
      "tgn:1001418",
      "tgn:7029392"
    ],
    "placetype": [
      "aat:300008749"
    ],
    "name:en": "Abū Mukhayyaţ, Minqār",
    "id": 7521920
  }
}
