{
  "geometry": {
    "type": "Point",
    "coordinates": [
      -78.3167,
      37.0333
    ]
  },
  "type": "Feature",
  "properties": {
    "hierarchy": [
      "tgn:2457322",
      "tgn:1000001",
      "tgn:7012149",
      "tgn:2002171",
      "tgn:7007919",
      "tgn:7029392"
    ],
    "placetype": [
      "aat:300008706"
    ],
    "id": 2457322,
    "name:xx": "Little Ledbetter Creek"
  }
}
