{
  "type": "FeatureCollection",
  "features": [
    {
      "geometry": {
        "type": "Point",
        "coordinates": [
          -126.5833,
          49.5833
        ]
      },
      "type": "Feature",
      "properties": {
        "hierarchy": [
          "tgn:1115010",
          "tgn:7005735",
          "tgn:7005685",
          "tgn:1000001",
          "tgn:7029392"
        ],
        "placetype": [
          "aat:300266558"
        ],
        "id": 1115010,
        "name:xx": "Nootka Sound"
      }
    },
    {
      "geometry": {
        "type": "Point",
        "coordinates": [
          -61.75,
          17.1167
        ]
      },
      "type": "Feature",
      "properties": {
        "hierarchy": [
          "tgn:1115011",
          "tgn:1000009",
          "tgn:7032074",
          "tgn:1000001",
          "tgn:7029392"
        ],
        "placetype": [
          "aat:300008713"
        ],
        "id": 1115011,
        "name:xx": "North Sound"
      }
    },
    {
      "geometry": {
        "type": "Point",
        "coordinates": [
          -9.7167,
          53.1833
        ]
      },
      "type": "Feature",
      "properties": {
        "hierarchy": [
          "tgn:1115012",
          "tgn:7003479",
          "tgn:7001198",
          "tgn:1000003",
          "tgn:1000078",
          "tgn:7029392"
        ],
        "placetype": [
          "aat:300266558"
        ],
        "id": 1115012,
        "name:xx": "North Sound"
      }
    },
    {
      "geometry": {
        "type": "Point",
        "coordinates": [
          -2.7667,
          59.3
        ]
      },
      "type": "Feature",
      "properties": {
        "hierarchy": [
          "tgn:1115013",
          "tgn:7002444",
          "tgn:1000003",
          "tgn:7009907",
          "tgn:7008591",
          "tgn:7029392"
        ],
        "placetype": [
          "aat:300266558"
        ],
        "id": 1115013,
        "name:xx": "North Sound"
      }
    },
    {
      "geometry": {
        "type": "Point",
        "coordinates": [
          -74,
          -53.3333
        ]
      },
      "type": "Feature",
      "properties": {
        "hierarchy": [
          "tgn:1115015",
          "tgn:1001702",
          "tgn:1000049",
          "tgn:1000002",
          "tgn:7029392"
        ],
        "placetype": [
          "aat:300266558"
        ],
        "id": 1115015,
        "name:xx": "Otway, Bahía"
      }
    },
    {
      "geometry": {
        "type": "Point",
        "coordinates": [
          -75.9333,
          35.3
        ]
      },
      "type": "Feature",
      "properties": {
        "hierarchy": [
          "tgn:1115016",
          "tgn:1000001",
          "tgn:7012149",
          "tgn:7007709",
          "tgn:7029392"
        ],
        "placetype": [
          "aat:300266558"
        ],
        "id": 1115016,
        "name:xx": "Pamlico Sound"
      }
    },
    {
      "geometry": {
        "type": "Point",
        "coordinates": [
          -1.6833,
          60.3
        ]
      },
      "type": "Feature",
      "properties": {
        "hierarchy": [
          "tgn:1115017",
          "tgn:7002444",
          "tgn:1000003",
          "tgn:7029508",
          "tgn:7008591",
          "tgn:7029392"
        ],
        "placetype": [
          "aat:300266558"
        ],
        "name:en": "Papa, Sound of",
        "id": 1115017
      }
    },
    {
      "geometry": {
        "type": "Point",
        "coordinates": [
          -100,
          -72.9167
        ]
      },
      "type": "Feature",
      "properties": {
        "hierarchy": [
          "tgn:1115019",
          "tgn:1000007",
          "tgn:7029392"
        ],
        "placetype": [
          "aat:300266558"
        ],
        "id": 1115019,
        "name:xx": "Peacock Sound"
      }
    }
  ]
}
