{
  "geometry": {
    "type": "Point",
    "coordinates": [
      37.25,
      30.75
    ]
  },
  "type": "Feature",
  "properties": {
    "hierarchy": [
      "tgn:1110889",
      "tgn:1000004",
      "tgn:1000121",
      "tgn:7029392"
    ],
    "placetype": [
      "aat:300008805"
    ],
    "id": 1110889,
    "name:xx": "Arḍ aṣ-Ṣawwān"
  }
}
