{
  "geometry": {
    "type": "Point",
    "coordinates": [
      -107.1833,
      32.9833
    ]
  },
  "type": "Feature",
  "properties": {
    "hierarchy": [
      "tgn:2443271",
      "tgn:1000001",
      "tgn:7012149",
      "tgn:2001455",
      "tgn:7007566",
      "tgn:7029392"
    ],
    "placetype": [
      "aat:300006191"
    ],
    "id": 2443271,
    "name:xx": "L 7 Red Tank"
  }
}
