{
  "geometry": {
    "type": "Point",
    "coordinates": [
      -88.8833,
      45.9667
    ]
  },
  "type": "Feature",
  "properties": {
    "hierarchy": [
      "tgn:2576512",
      "tgn:1000001",
      "tgn:2002323",
      "tgn:7012149",
      "tgn:7007922",
      "tgn:7029392"
    ],
    "placetype": [
      "aat:300008697"
    ],
    "id": 2576512,
    "name:xx": "Perry Spring"
  }
}
