{
  "geometry": {
    "type": "Point",
    "coordinates": [
      -40.65,
      -5.1667
    ]
  },
  "type": "Feature",
  "properties": {
    "hierarchy": [
      "tgn:1021263",
      "tgn:7006064",
      "tgn:1000047",
      "tgn:7002455",
      "tgn:1000002",
      "tgn:7029392"
    ],
    "placetype": [
      "aat:300008347"
    ],
    "id": 1021263,
    "name:xx": "Crateús"
  }
}
