{
  "type": "FeatureCollection",
  "features": [
    {
      "geometry": {
        "type": "Point",
        "coordinates": [
          -117.4,
          45.4667
        ]
      },
      "type": "Feature",
      "properties": {
        "hierarchy": [
          "tgn:2657170",
          "tgn:1000001",
          "tgn:7012149",
          "tgn:2001722",
          "tgn:7007708",
          "tgn:7029392"
        ],
        "placetype": [
          "aat:300006075"
        ],
        "id": 2657170,
        "name:xx": "Sheep Ridge Ditch"
      }
    },
    {
      "geometry": {
        "type": "Point",
        "coordinates": [
          -145.8167,
          60.75
        ]
      },
      "type": "Feature",
      "properties": {
        "hierarchy": [
          "tgn:2657171",
          "tgn:7006450",
          "tgn:1000001",
          "tgn:7012149",
          "tgn:2000086",
          "tgn:7029392"
        ],
        "placetype": [
          "aat:300008707"
        ],
        "id": 2657171,
        "name:xx": "Sheep River"
      }
    },
    {
      "geometry": {
        "type": "Point",
        "coordinates": [
          -148.7833,
          62.05
        ]
      },
      "type": "Feature",
      "properties": {
        "hierarchy": [
          "tgn:2657172",
          "tgn:7006450",
          "tgn:1000001",
          "tgn:2124053",
          "tgn:7012149",
          "tgn:7029392"
        ],
        "placetype": [
          "aat:300008707"
        ],
        "id": 2657172,
        "name:xx": "Sheep River"
      }
    },
    {
      "geometry": {
        "type": "Point",
        "coordinates": [
          -105.8,
          40.4
        ]
      },
      "type": "Feature",
      "properties": {
        "hierarchy": [
          "tgn:2657173",
          "tgn:1000001",
          "tgn:7012149",
          "tgn:2000216",
          "tgn:7007158",
          "tgn:7029392"
        ],
        "placetype": [
          "aat:300008798"
        ],
        "id": 2657173,
        "name:xx": "Sheep Rock"
      }
    },
    {
      "geometry": {
        "type": "Point",
        "coordinates": [
          -116.6667,
          45.1833
        ]
      },
      "type": "Feature",
      "properties": {
        "hierarchy": [
          "tgn:2657174",
          "tgn:2000453",
          "tgn:1000001",
          "tgn:7012149",
          "tgn:7007250",
          "tgn:7029392"
        ],
        "placetype": [
          "aat:300008798"
        ],
        "id": 2657174,
        "name:xx": "Sheep Rock"
      }
    },
    {
      "geometry": {
        "type": "Point",
        "coordinates": [
          -68.6,
          44.1667
        ]
      },
      "type": "Feature",
      "properties": {
        "hierarchy": [
          "tgn:2657175",
          "tgn:1000001",
          "tgn:2000922",
          "tgn:7012149",
          "tgn:7007515",
          "tgn:7029392"
        ],
        "placetype": [
          "aat:300132348"
        ],
        "id": 2657175,
        "name:xx": "Sheep Rock"
      }
    },
    {
      "geometry": {
        "type": "Point",
        "coordinates": [
          -72.1833,
          42.6167
        ]
      },
      "type": "Feature",
      "properties": {
        "hierarchy": [
          "tgn:2657176",
          "tgn:1000001",
          "tgn:7012149",
          "tgn:1003038",
          "tgn:7007517",
          "tgn:7029392"
        ],
        "placetype": [
          "aat:300008798"
        ],
        "id": 2657176,
        "name:xx": "Sheep Rock"
      }
    },
    {
      "geometry": {
        "type": "Point",
        "coordinates": [
          -82.6667,
          35.4833
        ]
      },
      "type": "Feature",
      "properties": {
        "hierarchy": [
          "tgn:2657177",
          "tgn:1000001",
          "tgn:2001473",
          "tgn:7012149",
          "tgn:7007709",
          "tgn:7029392"
        ],
        "placetype": [
          "aat:300008798"
        ],
        "id": 2657177,
        "name:xx": "Sheep Rock"
      }
    },
    {
      "geometry": {
        "type": "Point",
        "coordinates": [
          -81.15,
          36.4333
        ]
      },
      "type": "Feature",
      "properties": {
        "hierarchy": [
          "tgn:2657178",
          "tgn:2001465",
          "tgn:1000001",
          "tgn:7012149",
          "tgn:7007709",
          "tgn:7029392"
        ],
        "placetype": [
          "aat:300008798"
        ],
        "id": 2657178,
        "name:xx": "Sheep Rock"
      }
    },
    {
      "geometry": {
        "type": "Point",
        "coordinates": [
          -118.7333,
          44.3333
        ]
      },
      "type": "Feature",
      "properties": {
        "hierarchy": [
          "tgn:2657179",
          "tgn:1000001",
          "tgn:7012149",
          "tgn:2001708",
          "tgn:7007708",
          "tgn:7029392"
        ],
        "placetype": [
          "aat:300008798"
        ],
        "id": 2657179,
        "name:xx": "Sheep Rock"
      }
    }
  ]
}
