{
  "geometry": {
    "type": "Point",
    "coordinates": [
      -119.1333,
      44.55
    ]
  },
  "type": "Feature",
  "properties": {
    "hierarchy": [
      "tgn:2307109",
      "tgn:1000001",
      "tgn:7012149",
      "tgn:2001708",
      "tgn:7007708",
      "tgn:7029392"
    ],
    "placetype": [
      "aat:300008706"
    ],
    "id": 2307109,
    "name:xx": "East Fork Mine Creek"
  }
}
