{
  "geometry": {
    "type": "Point",
    "coordinates": [
      69.449167,
      22.356111
    ]
  },
  "type": "Feature",
  "properties": {
    "hierarchy": [
      "tgn:7553307",
      "tgn:1000004",
      "tgn:1001869",
      "tgn:7000198",
      "tgn:7029392"
    ],
    "placetype": [
      "aat:300008791"
    ],
    "name:en": "Pānero Tāpu",
    "id": 7553307
  }
}
