{
  "geometry": {
    "type": "Point",
    "coordinates": [
      -73.05,
      -48.2667
    ]
  },
  "type": "Feature",
  "properties": {
    "hierarchy": [
      "tgn:7005263",
      "tgn:1000002",
      "tgn:7029392"
    ],
    "placetype": [
      "aat:300008795"
    ],
    "id": 7005263,
    "name:xx": "Fitzroy, Cerro"
  }
}
