{
  "geometry": {
    "type": "Point",
    "coordinates": [
      -88.6167,
      35.0667
    ]
  },
  "type": "Feature",
  "properties": {
    "hierarchy": [
      "tgn:2101171",
      "tgn:1000001",
      "tgn:7012149",
      "tgn:7022544",
      "tgn:7007825",
      "tgn:7029392"
    ],
    "placetype": [
      "aat:300008347"
    ],
    "id": 2101171,
    "name:xx": "Ramer"
  }
}
