{
  "geometry": {
    "type": "Point",
    "coordinates": [
      6.95,
      52.65
    ]
  },
  "type": "Feature",
  "properties": {
    "hierarchy": [
      "tgn:7267561",
      "tgn:7003614",
      "tgn:1000003",
      "tgn:7016845",
      "tgn:7029392"
    ],
    "placetype": [
      "aat:300387200"
    ],
    "name:nl": "Oosteindsche Boeën",
    "id": 7267561
  }
}
