{
  "type": "FeatureCollection",
  "features": [
    {
      "geometry": {
        "type": "Point",
        "coordinates": [
          10.716667,
          44.35
        ]
      },
      "type": "Feature",
      "properties": {
        "hierarchy": [
          "tgn:7055050",
          "tgn:7004597",
          "tgn:1000003",
          "tgn:7008516",
          "tgn:1000080",
          "tgn:7029392"
        ],
        "placetype": [
          "aat:300008347"
        ],
        "id": 7055050,
        "name:xx": "Polinago"
      }
    },
    {
      "geometry": {
        "type": "Point",
        "coordinates": [
          9.9,
          44.433333
        ]
      },
      "type": "Feature",
      "properties": {
        "hierarchy": [
          "tgn:7055051",
          "tgn:1003473",
          "tgn:1000003",
          "tgn:7009760",
          "tgn:1000080",
          "tgn:7029392"
        ],
        "placetype": [
          "aat:300008347"
        ],
        "id": 7055051,
        "name:xx": "Polina"
      }
    },
    {
      "geometry": {
        "type": "Point",
        "coordinates": [
          16.516667,
          39.083333
        ]
      },
      "type": "Feature",
      "properties": {
        "hierarchy": [
          "tgn:7055052",
          "tgn:1003447",
          "tgn:7007850",
          "tgn:1000003",
          "tgn:1000080",
          "tgn:7029392"
        ],
        "placetype": [
          "aat:300008347"
        ],
        "id": 7055052,
        "name:xx": "Polimieri"
      }
    },
    {
      "geometry": {
        "type": "Point",
        "coordinates": [
          9.9,
          45.033333
        ]
      },
      "type": "Feature",
      "properties": {
        "hierarchy": [
          "tgn:7055054",
          "tgn:7003132",
          "tgn:1000003",
          "tgn:7008516",
          "tgn:1000080",
          "tgn:7029392"
        ],
        "placetype": [
          "aat:300008347"
        ],
        "id": 7055054,
        "name:xx": "Polignano"
      }
    },
    {
      "geometry": {
        "type": "Point",
        "coordinates": [
          15.516667,
          40.083333
        ]
      },
      "type": "Feature",
      "properties": {
        "hierarchy": [
          "tgn:7055056",
          "tgn:7003005",
          "tgn:7003014",
          "tgn:1000003",
          "tgn:1000080",
          "tgn:7029392"
        ],
        "placetype": [
          "aat:300007783"
        ],
        "id": 7055056,
        "name:xx": "Stazione Policastro Bussentino"
      }
    },
    {
      "geometry": {
        "type": "Point",
        "coordinates": [
          16.033333,
          39.683333
        ]
      },
      "type": "Feature",
      "properties": {
        "hierarchy": [
          "tgn:7055059",
          "tgn:1003450",
          "tgn:7007850",
          "tgn:1000003",
          "tgn:1000080",
          "tgn:7029392"
        ],
        "placetype": [
          "aat:300008347"
        ],
        "id": 7055059,
        "name:xx": "Policastrello"
      }
    }
  ]
}
