{
  "geometry": {
    "type": "Point",
    "coordinates": [
      74.815278,
      34.3125
    ]
  },
  "type": "Feature",
  "properties": {
    "hierarchy": [
      "tgn:7586001",
      "tgn:1000004",
      "tgn:7000198",
      "tgn:7000799",
      "tgn:7029392"
    ],
    "placetype": [
      "aat:300008699"
    ],
    "name:en": "Benāwās Kol",
    "id": 7586001
  }
}
