{
  "geometry": {
    "type": "Point",
    "coordinates": [
      -81.5667,
      38.55
    ]
  },
  "type": "Feature",
  "properties": {
    "hierarchy": [
      "tgn:2786513",
      "tgn:1000001",
      "tgn:7012149",
      "tgn:2002270",
      "tgn:7013961",
      "tgn:7029392"
    ],
    "placetype": [
      "aat:300006191"
    ],
    "id": 2786513,
    "name:xx": "Yukon Lake"
  }
}
