{
  "geometry": {
    "type": "Point",
    "coordinates": [
      21.0575,
      38.550278
    ]
  },
  "type": "Feature",
  "properties": {
    "hierarchy": [
      "tgn:7219020",
      "tgn:7002680",
      "tgn:7001395",
      "tgn:1000003",
      "tgn:1000074",
      "tgn:7029392"
    ],
    "placetype": [
      "aat:300008795"
    ],
    "id": 7219020,
    "name:xx": "Akarnaniká Óri"
  }
}
