{
  "geometry": {
    "type": "Point",
    "coordinates": [
      106.9833,
      16.8167
    ]
  },
  "type": "Feature",
  "properties": {
    "hierarchy": [
      "tgn:1087084",
      "tgn:7001030",
      "tgn:1000004",
      "tgn:1000145",
      "tgn:7029392"
    ],
    "placetype": [
      "aat:300008347"
    ],
    "id": 1087084,
    "name:xx": "Cam Lộ"
  }
}
