{
  "geometry": {
    "type": "Point",
    "coordinates": [
      -3.1167,
      52.2333
    ]
  },
  "type": "Feature",
  "properties": {
    "hierarchy": [
      "tgn:7027185",
      "tgn:7002443",
      "tgn:1000003",
      "tgn:7008050",
      "tgn:7008591",
      "tgn:7029392"
    ],
    "placetype": [
      "aat:300008347",
      "aat:300008372"
    ],
    "id": 7027185,
    "name:xx": "Harpton"
  }
}
