{
  "geometry": {
    "type": "Point",
    "coordinates": [
      -124.3167,
      47.6833
    ]
  },
  "type": "Feature",
  "properties": {
    "hierarchy": [
      "tgn:2641472",
      "tgn:1000001",
      "tgn:7012149",
      "tgn:1002521",
      "tgn:7007920",
      "tgn:7029392"
    ],
    "placetype": [
      "aat:300008706"
    ],
    "id": 2641472,
    "name:xx": "Sand Creek"
  }
}
