{
  "type": "FeatureCollection",
  "features": [
    {
      "geometry": {
        "type": "Point",
        "coordinates": [
          -107.3167,
          37.5167
        ]
      },
      "type": "Feature",
      "properties": {
        "hierarchy": [
          "tgn:2154050",
          "tgn:1000001",
          "tgn:7012149",
          "tgn:2000218",
          "tgn:7007158",
          "tgn:7029392"
        ],
        "placetype": [
          "aat:300008706"
        ],
        "id": 2154050,
        "name:xx": "Bear Creek"
      }
    },
    {
      "geometry": {
        "type": "Point",
        "coordinates": [
          -106.6167,
          37.9
        ]
      },
      "type": "Feature",
      "properties": {
        "hierarchy": [
          "tgn:2154051",
          "tgn:1000001",
          "tgn:7012149",
          "tgn:7007158",
          "tgn:2000246",
          "tgn:7029392"
        ],
        "placetype": [
          "aat:300008706"
        ],
        "id": 2154051,
        "name:xx": "Bear Creek"
      }
    },
    {
      "geometry": {
        "type": "Point",
        "coordinates": [
          -106.6333,
          37.8
        ]
      },
      "type": "Feature",
      "properties": {
        "hierarchy": [
          "tgn:2154052",
          "tgn:1000001",
          "tgn:7012149",
          "tgn:7007158",
          "tgn:2000244",
          "tgn:7029392"
        ],
        "placetype": [
          "aat:300008706"
        ],
        "id": 2154052,
        "name:xx": "Bear Creek"
      }
    },
    {
      "geometry": {
        "type": "Point",
        "coordinates": [
          -106.3,
          37.0333
        ]
      },
      "type": "Feature",
      "properties": {
        "hierarchy": [
          "tgn:2154053",
          "tgn:1000001",
          "tgn:2000202",
          "tgn:7012149",
          "tgn:7007158",
          "tgn:7029392"
        ],
        "placetype": [
          "aat:300008706"
        ],
        "id": 2154053,
        "name:xx": "Bear Creek"
      }
    },
    {
      "geometry": {
        "type": "Point",
        "coordinates": [
          -105.0167,
          38.4667
        ]
      },
      "type": "Feature",
      "properties": {
        "hierarchy": [
          "tgn:2154054",
          "tgn:1000001",
          "tgn:7012149",
          "tgn:2000213",
          "tgn:7007158",
          "tgn:7029392"
        ],
        "placetype": [
          "aat:300008706"
        ],
        "id": 2154054,
        "name:xx": "Bear Creek"
      }
    },
    {
      "geometry": {
        "type": "Point",
        "coordinates": [
          -105.5167,
          37.95
        ]
      },
      "type": "Feature",
      "properties": {
        "hierarchy": [
          "tgn:2154055",
          "tgn:1000001",
          "tgn:7012149",
          "tgn:2000205",
          "tgn:7007158",
          "tgn:7029392"
        ],
        "placetype": [
          "aat:300008706"
        ],
        "id": 2154055,
        "name:xx": "Bear Creek"
      }
    },
    {
      "geometry": {
        "type": "Point",
        "coordinates": [
          -105.15,
          37.9333
        ]
      },
      "type": "Feature",
      "properties": {
        "hierarchy": [
          "tgn:2154056",
          "tgn:1000001",
          "tgn:7012149",
          "tgn:2000219",
          "tgn:7007158",
          "tgn:7029392"
        ],
        "placetype": [
          "aat:300008706"
        ],
        "id": 2154056,
        "name:xx": "Bear Creek"
      }
    },
    {
      "geometry": {
        "type": "Point",
        "coordinates": [
          -105.2167,
          37.4667
        ]
      },
      "type": "Feature",
      "properties": {
        "hierarchy": [
          "tgn:2154057",
          "tgn:1000001",
          "tgn:7012149",
          "tgn:2000203",
          "tgn:7007158",
          "tgn:7029392"
        ],
        "placetype": [
          "aat:300008706"
        ],
        "id": 2154057,
        "name:xx": "Bear Creek"
      }
    },
    {
      "geometry": {
        "type": "Point",
        "coordinates": [
          -105.05,
          37.3
        ]
      },
      "type": "Feature",
      "properties": {
        "hierarchy": [
          "tgn:2154058",
          "tgn:1000001",
          "tgn:7012149",
          "tgn:2000227",
          "tgn:7007158",
          "tgn:7029392"
        ],
        "placetype": [
          "aat:300008706"
        ],
        "id": 2154058,
        "name:xx": "Bear Creek"
      }
    },
    {
      "geometry": {
        "type": "Point",
        "coordinates": [
          -81.2167,
          28.65
        ]
      },
      "type": "Feature",
      "properties": {
        "hierarchy": [
          "tgn:2154059",
          "tgn:1000001",
          "tgn:7012149",
          "tgn:1002881",
          "tgn:7007240",
          "tgn:7029392"
        ],
        "placetype": [
          "aat:300008706"
        ],
        "id": 2154059,
        "name:xx": "Bear Creek"
      }
    }
  ]
}
