{
  "geometry": {
    "type": "Point",
    "coordinates": [
      21.8925,
      39.575
    ]
  },
  "type": "Feature",
  "properties": {
    "hierarchy": [
      "tgn:7230414",
      "tgn:7002752",
      "tgn:7001399",
      "tgn:1000003",
      "tgn:1000074",
      "tgn:7029392"
    ],
    "placetype": [
      "aat:300008347"
    ],
    "id": 7230414,
    "name:xx": "Taxiárchai"
  }
}
