{
  "type": "FeatureCollection",
  "features": [
    {
      "geometry": {
        "type": "Point",
        "coordinates": [
          -89.75,
          42.0667
        ]
      },
      "type": "Feature",
      "properties": {
        "hierarchy": [
          "tgn:2562020",
          "tgn:1000001",
          "tgn:2000498",
          "tgn:7012149",
          "tgn:7007251",
          "tgn:7029392"
        ],
        "placetype": [
          "aat:300008706"
        ],
        "id": 2562020,
        "name:xx": "Otter Creek"
      }
    },
    {
      "geometry": {
        "type": "Point",
        "coordinates": [
          -89.3,
          42.4333
        ]
      },
      "type": "Feature",
      "properties": {
        "hierarchy": [
          "tgn:2562021",
          "tgn:1000001",
          "tgn:7012149",
          "tgn:1003030",
          "tgn:7007251",
          "tgn:7029392"
        ],
        "placetype": [
          "aat:300008706"
        ],
        "id": 2562021,
        "name:xx": "Otter Creek"
      }
    },
    {
      "geometry": {
        "type": "Point",
        "coordinates": [
          -86.5833,
          38.2833
        ]
      },
      "type": "Feature",
      "properties": {
        "hierarchy": [
          "tgn:2562022",
          "tgn:1000001",
          "tgn:1002306",
          "tgn:7012149",
          "tgn:7007252",
          "tgn:7029392"
        ],
        "placetype": [
          "aat:300008706"
        ],
        "id": 2562022,
        "name:xx": "Otter Creek"
      }
    },
    {
      "geometry": {
        "type": "Point",
        "coordinates": [
          -85.7167,
          39.2
        ]
      },
      "type": "Feature",
      "properties": {
        "hierarchy": [
          "tgn:2562023",
          "tgn:1002167",
          "tgn:1000001",
          "tgn:7012149",
          "tgn:7007252",
          "tgn:7029392"
        ],
        "placetype": [
          "aat:300008706"
        ],
        "id": 2562023,
        "name:xx": "Otter Creek"
      }
    },
    {
      "geometry": {
        "type": "Point",
        "coordinates": [
          -85.85,
          41.0167
        ]
      },
      "type": "Feature",
      "properties": {
        "hierarchy": [
          "tgn:2562024",
          "tgn:1000001",
          "tgn:7012149",
          "tgn:1002978",
          "tgn:7007252",
          "tgn:7029392"
        ],
        "placetype": [
          "aat:300008706"
        ],
        "id": 2562024,
        "name:xx": "Otter Creek"
      }
    },
    {
      "geometry": {
        "type": "Point",
        "coordinates": [
          -86.8333,
          41.7167
        ]
      },
      "type": "Feature",
      "properties": {
        "hierarchy": [
          "tgn:2562025",
          "tgn:1000001",
          "tgn:7012149",
          "tgn:1002561",
          "tgn:7007252",
          "tgn:7029392"
        ],
        "placetype": [
          "aat:300008706"
        ],
        "id": 2562025,
        "name:xx": "Otter Creek"
      }
    },
    {
      "geometry": {
        "type": "Point",
        "coordinates": [
          -87.2833,
          38.1333
        ]
      },
      "type": "Feature",
      "properties": {
        "hierarchy": [
          "tgn:2562026",
          "tgn:1000001",
          "tgn:7012149",
          "tgn:2000560",
          "tgn:7007252",
          "tgn:7029392"
        ],
        "placetype": [
          "aat:300008706"
        ],
        "id": 2562026,
        "name:xx": "Otter Creek"
      }
    },
    {
      "geometry": {
        "type": "Point",
        "coordinates": [
          -92.0667,
          43.3
        ]
      },
      "type": "Feature",
      "properties": {
        "hierarchy": [
          "tgn:2562027",
          "tgn:1000001",
          "tgn:7012149",
          "tgn:2000656",
          "tgn:7007253",
          "tgn:7029392"
        ],
        "placetype": [
          "aat:300008706"
        ],
        "id": 2562027,
        "name:xx": "Otter Creek"
      }
    },
    {
      "geometry": {
        "type": "Point",
        "coordinates": [
          -91.1667,
          41.1167
        ]
      },
      "type": "Feature",
      "properties": {
        "hierarchy": [
          "tgn:2562028",
          "tgn:1000001",
          "tgn:7012149",
          "tgn:2000618",
          "tgn:7007253",
          "tgn:7029392"
        ],
        "placetype": [
          "aat:300008706"
        ],
        "id": 2562028,
        "name:xx": "Otter Creek"
      }
    },
    {
      "geometry": {
        "type": "Point",
        "coordinates": [
          -91.8333,
          42.95
        ]
      },
      "type": "Feature",
      "properties": {
        "hierarchy": [
          "tgn:2562029",
          "tgn:1000001",
          "tgn:2000593",
          "tgn:7012149",
          "tgn:7007253",
          "tgn:7029392"
        ],
        "placetype": [
          "aat:300008706"
        ],
        "id": 2562029,
        "name:xx": "Otter Creek"
      }
    }
  ]
}
