{
  "geometry": {
    "type": "Point",
    "coordinates": [
      -90.1333,
      35.6333
    ]
  },
  "type": "Feature",
  "properties": {
    "hierarchy": [
      "tgn:2551681",
      "tgn:1000001",
      "tgn:7016172",
      "tgn:7012149",
      "tgn:2000151",
      "tgn:7029392"
    ],
    "placetype": [
      "aat:300006075"
    ],
    "id": 2551681,
    "name:xx": "Number 40b, Ditch"
  }
}
