{
  "geometry": {
    "type": "Point",
    "coordinates": [
      79.792283,
      27.809609
    ]
  },
  "type": "Feature",
  "properties": {
    "hierarchy": [
      "tgn:7577205",
      "tgn:1000004",
      "tgn:7000198",
      "tgn:7016722",
      "tgn:7029392"
    ],
    "placetype": [
      "aat:300008347"
    ],
    "name:en": "Kānt",
    "id": 7577205
  }
}
