{
  "geometry": {
    "type": "Point",
    "coordinates": [
      -112.1667,
      40.8667
    ]
  },
  "type": "Feature",
  "properties": {
    "hierarchy": [
      "tgn:2501786",
      "tgn:1000001",
      "tgn:2002106",
      "tgn:7012149",
      "tgn:7007827",
      "tgn:7029392"
    ],
    "placetype": [
      "aat:300008697"
    ],
    "id": 2501786,
    "name:xx": "McIntyre Spring"
  }
}
