{
  "type": "FeatureCollection",
  "features": [
    {
      "geometry": {
        "type": "Point",
        "coordinates": [
          -116.166667,
          31.466667
        ]
      },
      "type": "Feature",
      "properties": {
        "hierarchy": [
          "tgn:7348800",
          "tgn:1001835",
          "tgn:1000001",
          "tgn:7005560",
          "tgn:7029392"
        ],
        "placetype": [
          "aat:300008761"
        ],
        "id": 7348800,
        "name:xx": "Agua Blanca, Valle"
      }
    },
    {
      "geometry": {
        "type": "Point",
        "coordinates": [
          -116.216667,
          31.533333
        ]
      },
      "type": "Feature",
      "properties": {
        "hierarchy": [
          "tgn:7348801",
          "tgn:1001835",
          "tgn:1000001",
          "tgn:7005560",
          "tgn:7029392"
        ],
        "placetype": [
          "aat:300008795"
        ],
        "id": 7348801,
        "name:xx": "Agua Blanca, Sierra"
      }
    },
    {
      "geometry": {
        "type": "Point",
        "coordinates": [
          -99.761111,
          24.303333
        ]
      },
      "type": "Feature",
      "properties": {
        "hierarchy": [
          "tgn:7348802",
          "tgn:1000001",
          "tgn:7005589",
          "tgn:7005560",
          "tgn:7029392"
        ],
        "placetype": [
          "aat:300266554",
          "aat:300008699"
        ],
        "id": 7348802,
        "name:xx": "Agua Blanca, Río de"
      }
    },
    {
      "geometry": {
        "type": "Point",
        "coordinates": [
          -103.433333,
          21.033333
        ]
      },
      "type": "Feature",
      "properties": {
        "hierarchy": [
          "tgn:7348803",
          "tgn:1000001",
          "tgn:1001893",
          "tgn:7005560",
          "tgn:7029392"
        ],
        "placetype": [
          "aat:300008699"
        ],
        "id": 7348803,
        "name:xx": "Agua Blanca, Río"
      }
    },
    {
      "geometry": {
        "type": "Point",
        "coordinates": [
          -115.9,
          31.683333
        ]
      },
      "type": "Feature",
      "properties": {
        "hierarchy": [
          "tgn:7348804",
          "tgn:1001835",
          "tgn:1000001",
          "tgn:7005560",
          "tgn:7029392"
        ],
        "placetype": [
          "aat:300000241"
        ],
        "id": 7348804,
        "name:xx": "Rancho Agua Blanca"
      }
    },
    {
      "geometry": {
        "type": "Point",
        "coordinates": [
          -108.683333,
          30.733333
        ]
      },
      "type": "Feature",
      "properties": {
        "hierarchy": [
          "tgn:7348805",
          "tgn:7005581",
          "tgn:1000001",
          "tgn:7005560",
          "tgn:7029392"
        ],
        "placetype": [
          "aat:300000241"
        ],
        "id": 7348805,
        "name:xx": "Rancho Agua Blanca"
      }
    },
    {
      "geometry": {
        "type": "Point",
        "coordinates": [
          -105.4,
          30.416667
        ]
      },
      "type": "Feature",
      "properties": {
        "hierarchy": [
          "tgn:7348806",
          "tgn:7005581",
          "tgn:1000001",
          "tgn:7005560",
          "tgn:7029392"
        ],
        "placetype": [
          "aat:300000241"
        ],
        "id": 7348806,
        "name:xx": "Rancho Agua Blanca"
      }
    },
    {
      "geometry": {
        "type": "Point",
        "coordinates": [
          -111.1,
          30.016667
        ]
      },
      "type": "Feature",
      "properties": {
        "hierarchy": [
          "tgn:7348807",
          "tgn:1000001",
          "tgn:1001960",
          "tgn:7005560",
          "tgn:7029392"
        ],
        "placetype": [
          "aat:300000241"
        ],
        "id": 7348807,
        "name:xx": "Rancho Agua Blanca"
      }
    },
    {
      "geometry": {
        "type": "Point",
        "coordinates": [
          -111.716667,
          29.65
        ]
      },
      "type": "Feature",
      "properties": {
        "hierarchy": [
          "tgn:7348808",
          "tgn:1000001",
          "tgn:1001960",
          "tgn:7005560",
          "tgn:7029392"
        ],
        "placetype": [
          "aat:300000241"
        ],
        "id": 7348808,
        "name:xx": "Rancho Agua Blanca"
      }
    },
    {
      "geometry": {
        "type": "Point",
        "coordinates": [
          -109.85,
          28.733333
        ]
      },
      "type": "Feature",
      "properties": {
        "hierarchy": [
          "tgn:7348809",
          "tgn:1000001",
          "tgn:1001960",
          "tgn:7005560",
          "tgn:7029392"
        ],
        "placetype": [
          "aat:300000241"
        ],
        "id": 7348809,
        "name:xx": "Rancho Agua Blanca"
      }
    }
  ]
}
