{
  "geometry": {
    "type": "Point",
    "coordinates": [
      33.6667,
      51.55
    ]
  },
  "type": "Feature",
  "properties": {
    "hierarchy": [
      "tgn:1054587",
      "tgn:1000003",
      "tgn:1003410",
      "tgn:7006660",
      "tgn:7029392"
    ],
    "placetype": [
      "aat:300008347"
    ],
    "id": 1054587,
    "name:xx": "Yaroslavets'"
  }
}
