{
  "geometry": {
    "type": "Point",
    "coordinates": [
      -110.6167,
      31.9833
    ]
  },
  "type": "Feature",
  "properties": {
    "hierarchy": [
      "tgn:2229879",
      "tgn:1000001",
      "tgn:7006451",
      "tgn:7012149",
      "tgn:2000100",
      "tgn:7029392"
    ],
    "placetype": [
      "aat:300006191"
    ],
    "id": 2229879,
    "name:xx": "Cedar Tank"
  }
}
