{
  "geometry": {
    "type": "Point",
    "coordinates": [
      -91.0333,
      41.1667
    ]
  },
  "type": "Feature",
  "properties": {
    "hierarchy": [
      "tgn:2432932",
      "tgn:1000001",
      "tgn:7012149",
      "tgn:2000520",
      "tgn:7007251",
      "tgn:7029392"
    ],
    "placetype": [
      "aat:300008699"
    ],
    "id": 2432932,
    "name:xx": "Keg Slough"
  }
}
