{
  "geometry": {
    "type": "Point",
    "coordinates": [
      -99.383333,
      24.05
    ]
  },
  "type": "Feature",
  "properties": {
    "hierarchy": [
      "tgn:7370518",
      "tgn:1000001",
      "tgn:7005597",
      "tgn:7005560",
      "tgn:7029392"
    ],
    "placetype": [
      "aat:300008763"
    ],
    "id": 7370518,
    "name:xx": "Guayabas, Cañón de"
  }
}
