{
  "geometry": {
    "type": "Point",
    "coordinates": [
      -85.35,
      35.65
    ]
  },
  "type": "Feature",
  "properties": {
    "hierarchy": [
      "tgn:2322595",
      "tgn:1000001",
      "tgn:7012149",
      "tgn:2001924",
      "tgn:7007825",
      "tgn:7029392"
    ],
    "placetype": [
      "aat:300006191"
    ],
    "id": 2322595,
    "name:xx": "Falls Creek Falls Lake"
  }
}
