{
  "geometry": {
    "type": "Point",
    "coordinates": [
      -87.1667,
      33.3333
    ]
  },
  "type": "Feature",
  "properties": {
    "hierarchy": [
      "tgn:2703736",
      "tgn:7002659",
      "tgn:1000001",
      "tgn:7012149",
      "tgn:2000036",
      "tgn:7029392"
    ],
    "placetype": [
      "aat:300000390"
    ],
    "id": 2703736,
    "name:xx": "Sumter Mine"
  }
}
