{
  "geometry": {
    "type": "Point",
    "coordinates": [
      -96.281111,
      15.8975
    ]
  },
  "type": "Feature",
  "properties": {
    "hierarchy": [
      "tgn:7415234",
      "tgn:1000001",
      "tgn:7005591",
      "tgn:7005560",
      "tgn:7029392"
    ],
    "placetype": [
      "aat:300008347"
    ],
    "id": 7415234,
    "name:es": "Cuajinicuil"
  }
}
