{
  "geometry": {
    "type": "Point",
    "coordinates": [
      -91.45,
      45.3167
    ]
  },
  "type": "Feature",
  "properties": {
    "hierarchy": [
      "tgn:2737219",
      "tgn:1000001",
      "tgn:2719640",
      "tgn:7012149",
      "tgn:2002350",
      "tgn:7007922",
      "tgn:7029392"
    ],
    "placetype": [
      "aat:300008680"
    ],
    "id": 2737219,
    "name:xx": "Two, Lake"
  }
}
