{
  "geometry": {
    "type": "Point",
    "coordinates": [
      -114.9333,
      45.75
    ]
  },
  "type": "Feature",
  "properties": {
    "hierarchy": [
      "tgn:2453489",
      "tgn:1000001",
      "tgn:7012149",
      "tgn:2000476",
      "tgn:7007250",
      "tgn:7029392"
    ],
    "placetype": [
      "aat:300008707"
    ],
    "id": 2453489,
    "name:xx": "Little Clearwater River"
  }
}
