{
  "geometry": {
    "type": "Point",
    "coordinates": [
      -76.1167,
      42.4333
    ]
  },
  "type": "Feature",
  "properties": {
    "hierarchy": [
      "tgn:2305148",
      "tgn:1000001",
      "tgn:7012149",
      "tgn:7007568",
      "tgn:7029392"
    ],
    "placetype": [
      "aat:300008706"
    ],
    "id": 2305148,
    "name:xx": "East Branch Owego Creek"
  }
}
