{
  "geometry": {
    "type": "Point",
    "coordinates": [
      -91.45,
      33.6833
    ]
  },
  "type": "Feature",
  "properties": {
    "hierarchy": [
      "tgn:2273217",
      "tgn:1000001",
      "tgn:7016172",
      "tgn:7012149",
      "tgn:7029392"
    ],
    "placetype": [
      "aat:300008905"
    ],
    "id": 2273217,
    "name:xx": "Cypress Brake"
  }
}
