{
  "geometry": {
    "type": "Point",
    "coordinates": [
      -123.1167,
      46.1833
    ]
  },
  "type": "Feature",
  "properties": {
    "hierarchy": [
      "tgn:2693440",
      "tgn:1000001",
      "tgn:1002305",
      "tgn:7012149",
      "tgn:7007920",
      "tgn:7029392"
    ],
    "placetype": [
      "aat:300008347"
    ],
    "id": 2693440,
    "name:xx": "Stella"
  }
}
