{
  "geometry": {
    "type": "Point",
    "coordinates": [
      -112.1833,
      39.4833
    ]
  },
  "type": "Feature",
  "properties": {
    "hierarchy": [
      "tgn:2770414",
      "tgn:1000001",
      "tgn:7012149",
      "tgn:2002112",
      "tgn:7007827",
      "tgn:7029392"
    ],
    "placetype": [
      "aat:300008798"
    ],
    "id": 2770414,
    "name:xx": "Wild Horse Peak"
  }
}
