{
  "geometry": {
    "type": "Point",
    "coordinates": [
      -72.0167,
      19.15
    ]
  },
  "type": "Feature",
  "properties": {
    "hierarchy": [
      "tgn:1016739",
      "tgn:7005510",
      "tgn:1000001",
      "tgn:7005502",
      "tgn:7029392"
    ],
    "placetype": [
      "aat:300008347",
      "aat:300387225",
      "aat:300008375"
    ],
    "id": 1016739,
    "name:xx": "Hinche"
  }
}
