{
  "geometry": {
    "type": "Point",
    "coordinates": [
      -66.3167,
      -30.35
    ]
  },
  "type": "Feature",
  "properties": {
    "hierarchy": [
      "tgn:1019295",
      "tgn:7006477",
      "tgn:1001376",
      "tgn:1000002",
      "tgn:7029392"
    ],
    "placetype": [
      "aat:300008347"
    ],
    "id": 1019295,
    "name:xx": "Chamical"
  }
}
