{
  "geometry": {
    "type": "Point",
    "coordinates": [
      -74.0667,
      44.9333
    ]
  },
  "type": "Feature",
  "properties": {
    "hierarchy": [
      "tgn:2250053",
      "tgn:1000001",
      "tgn:1002284",
      "tgn:7012149",
      "tgn:7007568",
      "tgn:7029392"
    ],
    "placetype": [
      "aat:300008699"
    ],
    "id": 2250053,
    "name:xx": "Collins Brook"
  }
}
