{
  "geometry": {
    "type": "Point",
    "coordinates": [
      -76.7667,
      41.5167
    ]
  },
  "type": "Feature",
  "properties": {
    "hierarchy": [
      "tgn:2587711",
      "tgn:1000001",
      "tgn:7012149",
      "tgn:7007710",
      "tgn:7029392"
    ],
    "placetype": [
      "aat:300008699"
    ],
    "id": 2587711,
    "name:xx": "Pleasant Stream"
  }
}
