{
  "geometry": {
    "type": "Point",
    "coordinates": [
      -86.05,
      30.7333
    ]
  },
  "type": "Feature",
  "properties": {
    "hierarchy": [
      "tgn:2687488",
      "tgn:1000001",
      "tgn:7012149",
      "tgn:2000290",
      "tgn:7007240",
      "tgn:7029392"
    ],
    "placetype": [
      "aat:300006191"
    ],
    "id": 2687488,
    "name:xx": "Spring Lake Number One"
  }
}
