{
  "type": "FeatureCollection",
  "features": [
    {
      "geometry": {
        "type": "Point",
        "coordinates": [
          -7.3,
          54.533333
        ]
      },
      "type": "Feature",
      "properties": {
        "hierarchy": [
          "tgn:7466530",
          "tgn:7002448",
          "tgn:1000003",
          "tgn:7019206",
          "tgn:7008591",
          "tgn:7029392"
        ],
        "placetype": [
          "aat:300008347"
        ],
        "name:en": "Blackfort",
        "id": 7466530
      }
    },
    {
      "geometry": {
        "type": "Point",
        "coordinates": [
          -3.2,
          55.916667
        ]
      },
      "type": "Feature",
      "properties": {
        "hierarchy": [
          "tgn:7466531",
          "tgn:7002444",
          "tgn:1000003",
          "tgn:7019109",
          "tgn:7008591",
          "tgn:7029392"
        ],
        "placetype": [
          "aat:300008777"
        ],
        "name:en": "Blackford Hill",
        "id": 7466531
      }
    },
    {
      "geometry": {
        "type": "Point",
        "coordinates": [
          -2.483333,
          57.4
        ]
      },
      "type": "Feature",
      "properties": {
        "hierarchy": [
          "tgn:7466532",
          "tgn:5000432",
          "tgn:7002444",
          "tgn:1000003",
          "tgn:7008591",
          "tgn:7029392"
        ],
        "placetype": [
          "aat:300008347"
        ],
        "name:en": "Blackford",
        "id": 7466532
      }
    },
    {
      "geometry": {
        "type": "Point",
        "coordinates": [
          0.1,
          51.45
        ]
      },
      "type": "Feature",
      "properties": {
        "hierarchy": [
          "tgn:7466534",
          "tgn:7018908",
          "tgn:7002445",
          "tgn:1000003",
          "tgn:7008136",
          "tgn:7008591",
          "tgn:7029392"
        ],
        "placetype": [
          "aat:300387200"
        ],
        "name:en": "Blackfen",
        "id": 7466534
      }
    },
    {
      "geometry": {
        "type": "Point",
        "coordinates": [
          -2.533333,
          54.783333
        ]
      },
      "type": "Feature",
      "properties": {
        "hierarchy": [
          "tgn:7466535",
          "tgn:7002445",
          "tgn:1000003",
          "tgn:7008117",
          "tgn:7008591",
          "tgn:7029392"
        ],
        "placetype": [
          "aat:300008795"
        ],
        "name:en": "Black Fell",
        "id": 7466535
      }
    },
    {
      "geometry": {
        "type": "Point",
        "coordinates": [
          -3.333333,
          55.85
        ]
      },
      "type": "Feature",
      "properties": {
        "hierarchy": [
          "tgn:7466537",
          "tgn:7002444",
          "tgn:1000003",
          "tgn:7019109",
          "tgn:7008591",
          "tgn:7029392"
        ],
        "placetype": [
          "aat:300007783"
        ],
        "name:en": "Blackdyke",
        "id": 7466537
      }
    },
    {
      "geometry": {
        "type": "Point",
        "coordinates": [
          -1.483333,
          55.2
        ]
      },
      "type": "Feature",
      "properties": {
        "hierarchy": [
          "tgn:7466538",
          "tgn:7002445",
          "tgn:1000003",
          "tgn:7008165",
          "tgn:7008591",
          "tgn:7029392"
        ],
        "placetype": [
          "aat:300008808"
        ],
        "name:en": "Blackdyke",
        "id": 7466538
      }
    },
    {
      "geometry": {
        "type": "Point",
        "coordinates": [
          -1.516667,
          52.333333
        ]
      },
      "type": "Feature",
      "properties": {
        "hierarchy": [
          "tgn:7466539",
          "tgn:7002445",
          "tgn:1000003",
          "tgn:7008178",
          "tgn:7008591",
          "tgn:7029392"
        ],
        "placetype": [
          "aat:300387502"
        ],
        "name:en": "Blackdown Manor",
        "id": 7466539
      }
    }
  ]
}
