{
  "geometry": {
    "type": "Point",
    "coordinates": [
      -121.4167,
      46.2167
    ]
  },
  "type": "Feature",
  "properties": {
    "hierarchy": [
      "tgn:2266080",
      "tgn:1000001",
      "tgn:7012149",
      "tgn:1003042",
      "tgn:7007920",
      "tgn:7029392"
    ],
    "placetype": [
      "aat:300008706"
    ],
    "id": 2266080,
    "name:xx": "Crawford Creek"
  }
}
