{
  "geometry": {
    "type": "Point",
    "coordinates": [
      69.516667,
      22.95
    ]
  },
  "type": "Feature",
  "properties": {
    "hierarchy": [
      "tgn:7573269",
      "tgn:1000004",
      "tgn:1001869",
      "tgn:7000198",
      "tgn:7029392"
    ],
    "placetype": [
      "aat:300008347"
    ],
    "name:en": "Farādi",
    "id": 7573269
  }
}
