{
  "geometry": {
    "type": "Point",
    "coordinates": [
      -93.5833,
      36.2833
    ]
  },
  "type": "Feature",
  "properties": {
    "hierarchy": [
      "tgn:2219261",
      "tgn:1000001",
      "tgn:7016172",
      "tgn:2000112",
      "tgn:7012149",
      "tgn:7029392"
    ],
    "placetype": [
      "aat:300008761"
    ],
    "id": 2219261,
    "name:xx": "Canfield Hollow"
  }
}
