{
  "geometry": {
    "type": "Point",
    "coordinates": [
      -100.85,
      33.9833
    ]
  },
  "type": "Feature",
  "properties": {
    "hierarchy": [
      "tgn:2370627",
      "tgn:1000001",
      "tgn:7012149",
      "tgn:2002046",
      "tgn:7007826",
      "tgn:7029392"
    ],
    "placetype": [
      "aat:300008761"
    ],
    "id": 2370627,
    "name:xx": "Hackberry Draw"
  }
}
