{
  "geometry": {
    "type": "Point",
    "coordinates": [
      -72.15,
      44.5167
    ]
  },
  "type": "Feature",
  "properties": {
    "hierarchy": [
      "tgn:2402989",
      "tgn:2002131",
      "tgn:1000001",
      "tgn:7012149",
      "tgn:7007828",
      "tgn:7029392"
    ],
    "placetype": [
      "aat:300008699"
    ],
    "id": 2402989,
    "name:xx": "Houghton Brook"
  }
}
