{
  "type": "FeatureCollection",
  "features": [
    {
      "geometry": {
        "type": "Point",
        "coordinates": [
          10.366667,
          47.433333
        ]
      },
      "type": "Feature",
      "properties": {
        "hierarchy": [
          "tgn:7082360",
          "tgn:7003669",
          "tgn:1000003",
          "tgn:7000084",
          "tgn:7029392"
        ],
        "placetype": [
          "aat:300008795"
        ],
        "id": 7082360,
        "name:xx": "Wengenkopf"
      }
    },
    {
      "geometry": {
        "type": "Point",
        "coordinates": [
          10.466667,
          48.916667
        ]
      },
      "type": "Feature",
      "properties": {
        "hierarchy": [
          "tgn:7082361",
          "tgn:7003669",
          "tgn:1000003",
          "tgn:7000084",
          "tgn:7029392"
        ],
        "placetype": [
          "aat:300008347"
        ],
        "id": 7082361,
        "name:xx": "Wengenhausen"
      }
    },
    {
      "geometry": {
        "type": "Point",
        "coordinates": [
          11.366667,
          48.4
        ]
      },
      "type": "Feature",
      "properties": {
        "hierarchy": [
          "tgn:7082362",
          "tgn:7003669",
          "tgn:1000003",
          "tgn:7000084",
          "tgn:7029392"
        ],
        "placetype": [
          "aat:300000206"
        ],
        "id": 7082362,
        "name:xx": "Wengenhausen"
      }
    },
    {
      "geometry": {
        "type": "Point",
        "coordinates": [
          10.133333,
          47.683333
        ]
      },
      "type": "Feature",
      "properties": {
        "hierarchy": [
          "tgn:7082363",
          "tgn:7003669",
          "tgn:1000003",
          "tgn:7000084",
          "tgn:7029392"
        ],
        "placetype": [
          "aat:300008795"
        ],
        "id": 7082363,
        "name:xx": "Wengenberg"
      }
    },
    {
      "geometry": {
        "type": "Point",
        "coordinates": [
          11.166667,
          49.066667
        ]
      },
      "type": "Feature",
      "properties": {
        "hierarchy": [
          "tgn:7082364",
          "tgn:7003669",
          "tgn:1000003",
          "tgn:7000084",
          "tgn:7029392"
        ],
        "placetype": [
          "aat:300008347"
        ],
        "id": 7082364,
        "name:xx": "Wengen"
      }
    },
    {
      "geometry": {
        "type": "Point",
        "coordinates": [
          9.866667,
          48.933333
        ]
      },
      "type": "Feature",
      "properties": {
        "hierarchy": [
          "tgn:7082365",
          "tgn:7003692",
          "tgn:1000003",
          "tgn:7000084",
          "tgn:7029392"
        ],
        "placetype": [
          "aat:300008347"
        ],
        "id": 7082365,
        "name:xx": "Wengen"
      }
    },
    {
      "geometry": {
        "type": "Point",
        "coordinates": [
          11.033333,
          48.666667
        ]
      },
      "type": "Feature",
      "properties": {
        "hierarchy": [
          "tgn:7082366",
          "tgn:7003669",
          "tgn:1000003",
          "tgn:7000084",
          "tgn:7029392"
        ],
        "placetype": [
          "aat:300008347"
        ],
        "id": 7082366,
        "name:xx": "Wengen"
      }
    },
    {
      "geometry": {
        "type": "Point",
        "coordinates": [
          10.6,
          48.516667
        ]
      },
      "type": "Feature",
      "properties": {
        "hierarchy": [
          "tgn:7082367",
          "tgn:7003669",
          "tgn:1000003",
          "tgn:7000084",
          "tgn:7029392"
        ],
        "placetype": [
          "aat:300008347"
        ],
        "id": 7082367,
        "name:xx": "Wengen"
      }
    },
    {
      "geometry": {
        "type": "Point",
        "coordinates": [
          11.083333,
          47.933333
        ]
      },
      "type": "Feature",
      "properties": {
        "hierarchy": [
          "tgn:7082368",
          "tgn:7003669",
          "tgn:1000003",
          "tgn:7000084",
          "tgn:7029392"
        ],
        "placetype": [
          "aat:300008347"
        ],
        "id": 7082368,
        "name:xx": "Wengen"
      }
    },
    {
      "geometry": {
        "type": "Point",
        "coordinates": [
          9.85,
          47.916667
        ]
      },
      "type": "Feature",
      "properties": {
        "hierarchy": [
          "tgn:7082369",
          "tgn:7003692",
          "tgn:1000003",
          "tgn:7000084",
          "tgn:7029392"
        ],
        "placetype": [
          "aat:300008347"
        ],
        "id": 7082369,
        "name:xx": "Wengen"
      }
    }
  ]
}
