{
  "geometry": {
    "type": "Point",
    "coordinates": [
      -86.05,
      43.4167
    ]
  },
  "type": "Feature",
  "properties": {
    "hierarchy": [
      "tgn:2289836",
      "tgn:1000001",
      "tgn:7012149",
      "tgn:1002700",
      "tgn:7007520",
      "tgn:7029392"
    ],
    "placetype": [
      "aat:300006075"
    ],
    "id": 2289836,
    "name:xx": "Dobie Drain"
  }
}
