{
  "geometry": {
    "type": "Point",
    "coordinates": [
      -76.4667,
      41.5667
    ]
  },
  "type": "Feature",
  "properties": {
    "hierarchy": [
      "tgn:2158245",
      "tgn:1000001",
      "tgn:1002194",
      "tgn:7012149",
      "tgn:7007710",
      "tgn:7029392"
    ],
    "placetype": [
      "aat:300008699"
    ],
    "id": 2158245,
    "name:xx": "Beaver Run"
  }
}
