{
  "geometry": {
    "type": "Point",
    "coordinates": [
      37.9833,
      55.8667
    ]
  },
  "type": "Feature",
  "properties": {
    "hierarchy": [
      "tgn:1056908",
      "tgn:1000004",
      "tgn:7011573",
      "tgn:7018214",
      "tgn:7002435",
      "tgn:7029392"
    ],
    "placetype": [
      "aat:300008347"
    ],
    "id": 1056908,
    "name:xx": "Medvežji Oz'ora"
  }
}
