{
  "geometry": {
    "type": "Point",
    "coordinates": [
      -67.95,
      47.1833
    ]
  },
  "type": "Feature",
  "properties": {
    "hierarchy": [
      "tgn:2445824",
      "tgn:2000919",
      "tgn:1000001",
      "tgn:7012149",
      "tgn:7007515",
      "tgn:7029392"
    ],
    "placetype": [
      "aat:300008791"
    ],
    "id": 2445824,
    "name:xx": "Les Trois Island"
  }
}
