{
  "geometry": {
    "type": "Point",
    "coordinates": [
      -80.2333,
      35.8167
    ]
  },
  "type": "Feature",
  "properties": {
    "hierarchy": [
      "tgn:2549125",
      "tgn:1000001",
      "tgn:7012149",
      "tgn:2001489",
      "tgn:7007709",
      "tgn:7029392"
    ],
    "placetype": [
      "aat:300008347"
    ],
    "id": 2549125,
    "name:xx": "North Pugh"
  }
}
