{
  "geometry": {
    "type": "Point",
    "coordinates": [
      -84.6333,
      36.7333
    ]
  },
  "type": "Feature",
  "properties": {
    "hierarchy": [
      "tgn:2667729",
      "tgn:1000001",
      "tgn:7012149",
      "tgn:2000818",
      "tgn:7007255",
      "tgn:7029392"
    ],
    "placetype": [
      "aat:300008798"
    ],
    "id": 2667729,
    "name:xx": "Skullbones Knob"
  }
}
