{
  "geometry": {
    "type": "Point",
    "coordinates": [
      -108.9167,
      40.9667
    ]
  },
  "type": "Feature",
  "properties": {
    "hierarchy": [
      "tgn:2174088",
      "tgn:1000001",
      "tgn:7012149",
      "tgn:7029392"
    ],
    "placetype": [
      "aat:300008761"
    ],
    "id": 2174088,
    "name:xx": "Birdie Gulch"
  }
}
