{
  "type": "FeatureCollection",
  "features": [
    {
      "geometry": {
        "type": "Point",
        "coordinates": [
          -110.4333,
          32.7167
        ]
      },
      "type": "Feature",
      "properties": {
        "hierarchy": [
          "tgn:2550670",
          "tgn:1000001",
          "tgn:7006451",
          "tgn:2000094",
          "tgn:7012149",
          "tgn:7029392"
        ],
        "placetype": [
          "aat:300008697"
        ],
        "id": 2550670,
        "name:xx": "Norton Spring"
      }
    },
    {
      "geometry": {
        "type": "Point",
        "coordinates": [
          -120.4833,
          45.1667
        ]
      },
      "type": "Feature",
      "properties": {
        "hierarchy": [
          "tgn:2550671",
          "tgn:1000001",
          "tgn:7012149",
          "tgn:1002891",
          "tgn:7007708",
          "tgn:7029392"
        ],
        "placetype": [
          "aat:300008697"
        ],
        "id": 2550671,
        "name:xx": "Norton Spring"
      }
    },
    {
      "geometry": {
        "type": "Point",
        "coordinates": [
          -85.5667,
          35.6833
        ]
      },
      "type": "Feature",
      "properties": {
        "hierarchy": [
          "tgn:2550672",
          "tgn:1000001",
          "tgn:7012149",
          "tgn:2001924",
          "tgn:7007825",
          "tgn:7029392"
        ],
        "placetype": [
          "aat:300008697"
        ],
        "id": 2550672,
        "name:xx": "Norton Spring"
      }
    },
    {
      "geometry": {
        "type": "Point",
        "coordinates": [
          -82.75,
          36.0333
        ]
      },
      "type": "Feature",
      "properties": {
        "hierarchy": [
          "tgn:2550673",
          "tgn:1000001",
          "tgn:7012149",
          "tgn:2001866",
          "tgn:7007825",
          "tgn:7029392"
        ],
        "placetype": [
          "aat:300008697"
        ],
        "id": 2550673,
        "name:xx": "Norton Spring"
      }
    },
    {
      "geometry": {
        "type": "Point",
        "coordinates": [
          -98.9,
          29.65
        ]
      },
      "type": "Feature",
      "properties": {
        "hierarchy": [
          "tgn:2550674",
          "tgn:1000001",
          "tgn:2001938",
          "tgn:7012149",
          "tgn:7007826",
          "tgn:7029392"
        ],
        "placetype": [
          "aat:300008697"
        ],
        "id": 2550674,
        "name:xx": "Norton Spring"
      }
    },
    {
      "geometry": {
        "type": "Point",
        "coordinates": [
          -100.05,
          29.5667
        ]
      },
      "type": "Feature",
      "properties": {
        "hierarchy": [
          "tgn:2550675",
          "tgn:1000001",
          "tgn:7012149",
          "tgn:2002087",
          "tgn:7007826",
          "tgn:7029392"
        ],
        "placetype": [
          "aat:300008697"
        ],
        "id": 2550675,
        "name:xx": "Norton Spring"
      }
    },
    {
      "geometry": {
        "type": "Point",
        "coordinates": [
          -78,
          42.1
        ]
      },
      "type": "Feature",
      "properties": {
        "hierarchy": [
          "tgn:2550676",
          "tgn:1002141",
          "tgn:1000001",
          "tgn:7012149",
          "tgn:7007568",
          "tgn:7029392"
        ],
        "placetype": [
          "aat:300008347"
        ],
        "id": 2550676,
        "name:xx": "Norton Summit"
      }
    },
    {
      "geometry": {
        "type": "Point",
        "coordinates": [
          -113.05,
          35.3833
        ]
      },
      "type": "Feature",
      "properties": {
        "hierarchy": [
          "tgn:2550677",
          "tgn:1000001",
          "tgn:7006451",
          "tgn:7012149",
          "tgn:2000103",
          "tgn:7029392"
        ],
        "placetype": [
          "aat:300006191"
        ],
        "id": 2550677,
        "name:xx": "Norton Tank"
      }
    },
    {
      "geometry": {
        "type": "Point",
        "coordinates": [
          -113.8667,
          32.95
        ]
      },
      "type": "Feature",
      "properties": {
        "hierarchy": [
          "tgn:2550678",
          "tgn:1000001",
          "tgn:7006451",
          "tgn:7012149",
          "tgn:2000104",
          "tgn:7029392"
        ],
        "placetype": [
          "aat:300006191"
        ],
        "id": 2550678,
        "name:xx": "Norton Tank"
      }
    },
    {
      "geometry": {
        "type": "Point",
        "coordinates": [
          -103.0167,
          29.6333
        ]
      },
      "type": "Feature",
      "properties": {
        "hierarchy": [
          "tgn:2550679",
          "tgn:1000001",
          "tgn:2001945",
          "tgn:7012149",
          "tgn:7007826",
          "tgn:7029392"
        ],
        "placetype": [
          "aat:300006191"
        ],
        "id": 2550679,
        "name:xx": "Norton Tank"
      }
    }
  ]
}
