{
  "geometry": {
    "type": "Point",
    "coordinates": [
      -90.9167,
      39.0167
    ]
  },
  "type": "Feature",
  "properties": {
    "hierarchy": [
      "tgn:2449700",
      "tgn:1000001",
      "tgn:7012149",
      "tgn:1002598",
      "tgn:7007523",
      "tgn:7029392"
    ],
    "placetype": [
      "aat:300006191"
    ],
    "id": 2449700,
    "name:xx": "Lincoln, Lake"
  }
}
