{
  "geometry": {
    "type": "Point",
    "coordinates": [
      -153.15,
      65.2167
    ]
  },
  "type": "Feature",
  "properties": {
    "hierarchy": [
      "tgn:2183029",
      "tgn:7006450",
      "tgn:1000001",
      "tgn:7012149",
      "tgn:2000089",
      "tgn:7029392"
    ],
    "placetype": [
      "aat:300266640"
    ],
    "id": 2183029,
    "name:xx": "Blueberry Ridge"
  }
}
