{
  "geometry": {
    "type": "Point",
    "coordinates": [
      -104.0833,
      44.4167
    ]
  },
  "type": "Feature",
  "properties": {
    "hierarchy": [
      "tgn:2306591",
      "tgn:1000001",
      "tgn:2002370",
      "tgn:7012149",
      "tgn:7007923",
      "tgn:7029392"
    ],
    "placetype": [
      "aat:300008761"
    ],
    "id": 2306591,
    "name:xx": "East Fork Dugout Gulch"
  }
}
