{
  "geometry": {
    "type": "Point",
    "coordinates": [
      -87.3833,
      34.5167
    ]
  },
  "type": "Feature",
  "properties": {
    "hierarchy": [
      "tgn:2435960",
      "tgn:7002659",
      "tgn:1000001",
      "tgn:7012149",
      "tgn:2000039",
      "tgn:7029392"
    ],
    "placetype": [
      "aat:300008699"
    ],
    "id": 2435960,
    "name:xx": "Key Branch"
  }
}
