{
  "type": "FeatureCollection",
  "features": [
    {
      "geometry": {
        "type": "Point",
        "coordinates": [
          166.9,
          -45.55
        ]
      },
      "type": "Feature",
      "properties": {
        "hierarchy": [
          "tgn:7514690",
          "tgn:1009227",
          "tgn:1000226",
          "tgn:7016822",
          "tgn:1000006",
          "tgn:7029392"
        ],
        "placetype": [
          "aat:300386846"
        ],
        "name:en": "Chatham Point",
        "id": 7514690
      }
    },
    {
      "geometry": {
        "type": "Point",
        "coordinates": [
          -176.5,
          -44
        ]
      },
      "type": "Feature",
      "properties": {
        "hierarchy": [
          "tgn:7514691",
          "tgn:1009931",
          "tgn:1000226",
          "tgn:1000006",
          "tgn:7029392"
        ],
        "placetype": [
          "aat:300387064"
        ],
        "name:en": "Chatham Islands County",
        "id": 7514691
      }
    },
    {
      "geometry": {
        "type": "Point",
        "coordinates": [
          -176.583333,
          -44
        ]
      },
      "type": "Feature",
      "properties": {
        "hierarchy": [
          "tgn:7514692",
          "tgn:1009227",
          "tgn:1000226",
          "tgn:7016822",
          "tgn:1000006",
          "tgn:7029392"
        ],
        "placetype": [
          "aat:300008791"
        ],
        "name:en": "Chatham Islands",
        "id": 7514692
      }
    },
    {
      "geometry": {
        "type": "Point",
        "coordinates": [
          -176.5,
          -43.916667
        ]
      },
      "type": "Feature",
      "properties": {
        "hierarchy": [
          "tgn:7514693",
          "tgn:1009931",
          "tgn:1000226",
          "tgn:1000006",
          "tgn:7029392"
        ],
        "placetype": [
          "aat:300008791"
        ],
        "name:en": "Chatham Island",
        "id": 7514693
      }
    },
    {
      "geometry": {
        "type": "Point",
        "coordinates": [
          175.533333,
          -39.2
        ]
      },
      "type": "Feature",
      "properties": {
        "hierarchy": [
          "tgn:7514694",
          "tgn:1008380",
          "tgn:7520093",
          "tgn:1000226",
          "tgn:1000006",
          "tgn:7029392"
        ],
        "placetype": [
          "aat:300000547"
        ],
        "name:en": "Chateau Tongariro",
        "id": 7514694
      }
    },
    {
      "geometry": {
        "type": "Point",
        "coordinates": [
          171.983333,
          -41.55
        ]
      },
      "type": "Feature",
      "properties": {
        "hierarchy": [
          "tgn:7514695",
          "tgn:1009227",
          "tgn:1000226",
          "tgn:1000006",
          "tgn:7016850",
          "tgn:7029392"
        ],
        "placetype": [
          "aat:300008699"
        ],
        "name:en": "Chasm Stream",
        "id": 7514695
      }
    },
    {
      "geometry": {
        "type": "Point",
        "coordinates": [
          168.85,
          -44.25
        ]
      },
      "type": "Feature",
      "properties": {
        "hierarchy": [
          "tgn:7514696",
          "tgn:1009227",
          "tgn:1000226",
          "tgn:7018437",
          "tgn:1000006",
          "tgn:7029392"
        ],
        "placetype": [
          "aat:300259572"
        ],
        "name:en": "Chasm Pass",
        "id": 7514696
      }
    },
    {
      "geometry": {
        "type": "Point",
        "coordinates": [
          169.3,
          -45.416667
        ]
      },
      "type": "Feature",
      "properties": {
        "hierarchy": [
          "tgn:7514697",
          "tgn:1009227",
          "tgn:1000226",
          "tgn:7018437",
          "tgn:1000006",
          "tgn:7029392"
        ],
        "placetype": [
          "aat:300008699"
        ],
        "name:en": "Chasm Creek",
        "id": 7514697
      }
    },
    {
      "geometry": {
        "type": "Point",
        "coordinates": [
          169.333333,
          -46.583333
        ]
      },
      "type": "Feature",
      "properties": {
        "hierarchy": [
          "tgn:7514699",
          "tgn:1009227",
          "tgn:1000226",
          "tgn:7018437",
          "tgn:1000006",
          "tgn:7029392"
        ],
        "placetype": [
          "aat:300008347"
        ],
        "name:en": "Chaslands",
        "id": 7514699
      }
    }
  ]
}
