{
  "geometry": {
    "type": "Point",
    "coordinates": [
      34.4833,
      48.8667
    ]
  },
  "type": "Feature",
  "properties": {
    "hierarchy": [
      "tgn:7010196",
      "tgn:7011648",
      "tgn:1000003",
      "tgn:7006660",
      "tgn:7029392"
    ],
    "placetype": [
      "aat:300008347"
    ],
    "id": 7010196,
    "name:xx": "Mogil'ov"
  }
}
