{
  "geometry": {
    "type": "Point",
    "coordinates": [
      80.9167,
      50.7167
    ]
  },
  "type": "Feature",
  "properties": {
    "hierarchy": [
      "tgn:1053033",
      "tgn:1000004",
      "tgn:7011462",
      "tgn:7014786",
      "tgn:7029392"
    ],
    "placetype": [
      "aat:300008347"
    ],
    "id": 1053033,
    "name:xx": "Borodūlīkha"
  }
}
