{
  "geometry": {
    "type": "Point",
    "coordinates": [
      -100.3167,
      38.1667
    ]
  },
  "type": "Feature",
  "properties": {
    "hierarchy": [
      "tgn:2326725",
      "tgn:1000001",
      "tgn:2000687",
      "tgn:7012149",
      "tgn:7007254",
      "tgn:7029392"
    ],
    "placetype": [
      "aat:300006191"
    ],
    "id": 2326725,
    "name:xx": "Finney Lake"
  }
}
