{
  "geometry": {
    "type": "Point",
    "coordinates": [
      -5.1333,
      8.2167
    ]
  },
  "type": "Feature",
  "properties": {
    "hierarchy": [
      "tgn:1090407",
      "tgn:7001242",
      "tgn:1000657",
      "tgn:1000168",
      "tgn:7029392"
    ],
    "placetype": [
      "aat:300008347"
    ],
    "id": 1090407,
    "name:xx": "Souroukaha"
  }
}
