{
  "geometry": {
    "type": "Point",
    "coordinates": [
      -79.6333,
      40.2833
    ]
  },
  "type": "Feature",
  "properties": {
    "hierarchy": [
      "tgn:2177927",
      "tgn:1000001",
      "tgn:7012149",
      "tgn:1003017",
      "tgn:7007710",
      "tgn:7029392"
    ],
    "placetype": [
      "aat:300006191"
    ],
    "id": 2177927,
    "name:xx": "Blackberry Pond"
  }
}
