{
  "geometry": {
    "type": "Point",
    "coordinates": [
      -91.0667,
      46.15
    ]
  },
  "type": "Feature",
  "properties": {
    "hierarchy": [
      "tgn:2477004",
      "tgn:1000001",
      "tgn:7012149",
      "tgn:7007922",
      "tgn:7029392"
    ],
    "placetype": [
      "aat:300008706"
    ],
    "id": 2477004,
    "name:xx": "Lynch Creek"
  }
}
