{
  "type": "FeatureCollection",
  "features": [
    {
      "geometry": {
        "type": "Point",
        "coordinates": [
          -81.15,
          39.9167
        ]
      },
      "type": "Feature",
      "properties": {
        "hierarchy": [
          "tgn:2330000",
          "tgn:1002175",
          "tgn:1000001",
          "tgn:7012149",
          "tgn:7007706",
          "tgn:7029392"
        ],
        "placetype": [
          "aat:300008699"
        ],
        "id": 2330000,
        "name:xx": "Flag Run"
      }
    },
    {
      "geometry": {
        "type": "Point",
        "coordinates": [
          -79.1333,
          39.7333
        ]
      },
      "type": "Feature",
      "properties": {
        "hierarchy": [
          "tgn:2330001",
          "tgn:1000001",
          "tgn:7012149",
          "tgn:1002904",
          "tgn:7007710",
          "tgn:7029392"
        ],
        "placetype": [
          "aat:300008699"
        ],
        "id": 2330001,
        "name:xx": "Flag Run"
      }
    },
    {
      "geometry": {
        "type": "Point",
        "coordinates": [
          -77.0667,
          36.7333
        ]
      },
      "type": "Feature",
      "properties": {
        "hierarchy": [
          "tgn:2330002",
          "tgn:1000001",
          "tgn:7012149",
          "tgn:1002911",
          "tgn:7007919",
          "tgn:7029392"
        ],
        "placetype": [
          "aat:300008699"
        ],
        "id": 2330002,
        "name:xx": "Flag Run"
      }
    },
    {
      "geometry": {
        "type": "Point",
        "coordinates": [
          -77.2,
          38.8
        ]
      },
      "type": "Feature",
      "properties": {
        "hierarchy": [
          "tgn:2330003",
          "tgn:1000001",
          "tgn:7012149",
          "tgn:7014160",
          "tgn:7007919",
          "tgn:7029392"
        ],
        "placetype": [
          "aat:300008699"
        ],
        "id": 2330003,
        "name:xx": "Flag Run"
      }
    },
    {
      "geometry": {
        "type": "Point",
        "coordinates": [
          -80.4333,
          39.35
        ]
      },
      "type": "Feature",
      "properties": {
        "hierarchy": [
          "tgn:2330004",
          "tgn:1000001",
          "tgn:7012149",
          "tgn:2002267",
          "tgn:7013961",
          "tgn:7029392"
        ],
        "placetype": [
          "aat:300008699"
        ],
        "id": 2330004,
        "name:xx": "Flag Run"
      }
    },
    {
      "geometry": {
        "type": "Point",
        "coordinates": [
          -80.0667,
          39.2333
        ]
      },
      "type": "Feature",
      "properties": {
        "hierarchy": [
          "tgn:2330005",
          "tgn:1000001",
          "tgn:7012149",
          "tgn:2002295",
          "tgn:7013961",
          "tgn:7029392"
        ],
        "placetype": [
          "aat:300008699"
        ],
        "id": 2330005,
        "name:xx": "Flag Run"
      }
    },
    {
      "geometry": {
        "type": "Point",
        "coordinates": [
          -79.75,
          39.2833
        ]
      },
      "type": "Feature",
      "properties": {
        "hierarchy": [
          "tgn:2330006",
          "tgn:1000001",
          "tgn:7012149",
          "tgn:2002288",
          "tgn:7013961",
          "tgn:7029392"
        ],
        "placetype": [
          "aat:300008699"
        ],
        "id": 2330006,
        "name:xx": "Flag Run"
      }
    },
    {
      "geometry": {
        "type": "Point",
        "coordinates": [
          -77.2,
          36.1167
        ]
      },
      "type": "Feature",
      "properties": {
        "hierarchy": [
          "tgn:2330007",
          "tgn:1000001",
          "tgn:2001470",
          "tgn:7012149",
          "tgn:7007709",
          "tgn:7029392"
        ],
        "placetype": [
          "aat:300008699"
        ],
        "id": 2330007,
        "name:xx": "Flag Run Gut"
      }
    },
    {
      "geometry": {
        "type": "Point",
        "coordinates": [
          -90.9833,
          35.6
        ]
      },
      "type": "Feature",
      "properties": {
        "hierarchy": [
          "tgn:2330008",
          "tgn:1000001",
          "tgn:7016172",
          "tgn:7012149",
          "tgn:2000160",
          "tgn:7029392"
        ],
        "placetype": [
          "aat:300006075"
        ],
        "id": 2330008,
        "name:xx": "Flag Slough Ditch"
      }
    },
    {
      "geometry": {
        "type": "Point",
        "coordinates": [
          -86.0333,
          34.7833
        ]
      },
      "type": "Feature",
      "properties": {
        "hierarchy": [
          "tgn:2330009",
          "tgn:7002659",
          "tgn:1000001",
          "tgn:7012149",
          "tgn:2000035",
          "tgn:7029392"
        ],
        "placetype": [
          "aat:300008697"
        ],
        "id": 2330009,
        "name:xx": "Flag Spring"
      }
    }
  ]
}
