{
  "geometry": {
    "type": "Point",
    "coordinates": [
      -91.9167,
      44.65
    ]
  },
  "type": "Feature",
  "properties": {
    "hierarchy": [
      "tgn:2155141",
      "tgn:1000001",
      "tgn:7012149",
      "tgn:2002344",
      "tgn:7007922",
      "tgn:7029392"
    ],
    "placetype": [
      "aat:300132316"
    ],
    "id": 2155141,
    "name:xx": "Bear Lake"
  }
}
