{
  "type": "FeatureCollection",
  "features": [
    {
      "geometry": {
        "type": "Point",
        "coordinates": [
          -109.35,
          33.2167
        ]
      },
      "type": "Feature",
      "properties": {
        "hierarchy": [
          "tgn:2391220",
          "tgn:1000001",
          "tgn:7006451",
          "tgn:2000095",
          "tgn:7012149",
          "tgn:7029392"
        ],
        "placetype": [
          "aat:300008697"
        ],
        "id": 2391220,
        "name:xx": "Hill Spring"
      }
    },
    {
      "geometry": {
        "type": "Point",
        "coordinates": [
          -111.1667,
          42.6333
        ]
      },
      "type": "Feature",
      "properties": {
        "hierarchy": [
          "tgn:2391221",
          "tgn:1000001",
          "tgn:2000466",
          "tgn:7012149",
          "tgn:7007250",
          "tgn:7029392"
        ],
        "placetype": [
          "aat:300008697"
        ],
        "id": 2391221,
        "name:xx": "Hill Spring"
      }
    },
    {
      "geometry": {
        "type": "Point",
        "coordinates": [
          -114.9833,
          40.35
        ]
      },
      "type": "Feature",
      "properties": {
        "hierarchy": [
          "tgn:2391222",
          "tgn:1000001",
          "tgn:2001411",
          "tgn:7012149",
          "tgn:7007526",
          "tgn:7029392"
        ],
        "placetype": [
          "aat:300008697"
        ],
        "id": 2391222,
        "name:xx": "Hill Spring"
      }
    },
    {
      "geometry": {
        "type": "Point",
        "coordinates": [
          -120.35,
          42.3667
        ]
      },
      "type": "Feature",
      "properties": {
        "hierarchy": [
          "tgn:2391223",
          "tgn:1000001",
          "tgn:7012149",
          "tgn:2001715",
          "tgn:7007708",
          "tgn:7029392"
        ],
        "placetype": [
          "aat:300008697"
        ],
        "id": 2391223,
        "name:xx": "Hill Spring"
      }
    },
    {
      "geometry": {
        "type": "Point",
        "coordinates": [
          -120.6667,
          45.2833
        ]
      },
      "type": "Feature",
      "properties": {
        "hierarchy": [
          "tgn:2391224",
          "tgn:1000001",
          "tgn:7012149",
          "tgn:1002891",
          "tgn:7007708",
          "tgn:7029392"
        ],
        "placetype": [
          "aat:300008697"
        ],
        "id": 2391224,
        "name:xx": "Hill Spring"
      }
    },
    {
      "geometry": {
        "type": "Point",
        "coordinates": [
          -119.75,
          44.9
        ]
      },
      "type": "Feature",
      "properties": {
        "hierarchy": [
          "tgn:2391225",
          "tgn:1000001",
          "tgn:7012149",
          "tgn:2001723",
          "tgn:7007708",
          "tgn:7029392"
        ],
        "placetype": [
          "aat:300008697"
        ],
        "id": 2391225,
        "name:xx": "Hill Spring"
      }
    },
    {
      "geometry": {
        "type": "Point",
        "coordinates": [
          -99.25,
          44.9
        ]
      },
      "type": "Feature",
      "properties": {
        "hierarchy": [
          "tgn:2391226",
          "tgn:1000001",
          "tgn:2001794",
          "tgn:7012149",
          "tgn:7007713",
          "tgn:7029392"
        ],
        "placetype": [
          "aat:300008697"
        ],
        "id": 2391226,
        "name:xx": "Hill Spring"
      }
    },
    {
      "geometry": {
        "type": "Point",
        "coordinates": [
          -101.3833,
          43.6167
        ]
      },
      "type": "Feature",
      "properties": {
        "hierarchy": [
          "tgn:2391227",
          "tgn:1000001",
          "tgn:2001805",
          "tgn:7012149",
          "tgn:7007713",
          "tgn:7029392"
        ],
        "placetype": [
          "aat:300008697"
        ],
        "id": 2391227,
        "name:xx": "Hill Spring"
      }
    },
    {
      "geometry": {
        "type": "Point",
        "coordinates": [
          -84.7667,
          35.3833
        ]
      },
      "type": "Feature",
      "properties": {
        "hierarchy": [
          "tgn:2391228",
          "tgn:1000001",
          "tgn:7012149",
          "tgn:7022542",
          "tgn:7007825",
          "tgn:7029392"
        ],
        "placetype": [
          "aat:300008697"
        ],
        "id": 2391228,
        "name:xx": "Hill Spring"
      }
    },
    {
      "geometry": {
        "type": "Point",
        "coordinates": [
          -112.55,
          40.0667
        ]
      },
      "type": "Feature",
      "properties": {
        "hierarchy": [
          "tgn:2391229",
          "tgn:1000001",
          "tgn:7012149",
          "tgn:2002123",
          "tgn:7007827",
          "tgn:7029392"
        ],
        "placetype": [
          "aat:300008697"
        ],
        "id": 2391229,
        "name:xx": "Hill Spring"
      }
    }
  ]
}
