{
  "geometry": {
    "type": "Point",
    "coordinates": [
      -76.1667,
      40.5333
    ]
  },
  "type": "Feature",
  "properties": {
    "hierarchy": [
      "tgn:2757123",
      "tgn:1000001",
      "tgn:7012149",
      "tgn:1002876",
      "tgn:7007710",
      "tgn:7029392"
    ],
    "placetype": [
      "aat:300008761"
    ],
    "id": 2757123,
    "name:xx": "Werts Hollow"
  }
}
