{
  "geometry": {
    "type": "Point",
    "coordinates": [
      120.365,
      23.8064
    ]
  },
  "type": "Feature",
  "properties": {
    "hierarchy": [
      "tgn:7471021",
      "tgn:1000004",
      "tgn:7001014",
      "tgn:1000141",
      "tgn:7029392"
    ],
    "placetype": [
      "aat:300008347"
    ],
    "id": 7471021,
    "name:xx": "Jiuguzi"
  }
}
