{
  "geometry": {
    "type": "Point",
    "coordinates": [
      -92.6333,
      35.5333
    ]
  },
  "type": "Feature",
  "properties": {
    "hierarchy": [
      "tgn:2425964",
      "tgn:1000001",
      "tgn:7016172",
      "tgn:7012149",
      "tgn:2000175",
      "tgn:7029392"
    ],
    "placetype": [
      "aat:300008706"
    ],
    "id": 2425964,
    "name:xx": "Joneed Creek"
  }
}
