{
  "geometry": {
    "type": "Point",
    "coordinates": [
      -81.7333,
      31.6167
    ]
  },
  "type": "Feature",
  "properties": {
    "hierarchy": [
      "tgn:2202013",
      "tgn:1000001",
      "tgn:7012149",
      "tgn:2000382",
      "tgn:7007248",
      "tgn:7029392"
    ],
    "placetype": [
      "aat:300008791"
    ],
    "id": 2202013,
    "name:xx": "Buck Island"
  }
}
