{
  "geometry": {
    "type": "Point",
    "coordinates": [
      35.4167,
      32.65
    ]
  },
  "type": "Feature",
  "properties": {
    "hierarchy": [
      "tgn:1079452",
      "tgn:7000249",
      "tgn:1000004",
      "tgn:1000119",
      "tgn:7029392"
    ],
    "placetype": [
      "aat:300008347",
      "aat:300008375"
    ],
    "id": 1079452,
    "name:xx": "ʻEn Dor"
  }
}
