{
  "type": "FeatureCollection",
  "features": [
    {
      "geometry": {
        "type": "Point",
        "coordinates": [
          -74.2,
          40.6667
        ]
      },
      "type": "Feature",
      "properties": {
        "hierarchy": [
          "tgn:2265560",
          "tgn:1000001",
          "tgn:1002963",
          "tgn:7012149",
          "tgn:7007565",
          "tgn:7029392"
        ],
        "placetype": [
          "aat:300008347"
        ],
        "id": 2265560,
        "name:xx": "Crane Square"
      }
    },
    {
      "geometry": {
        "type": "Point",
        "coordinates": [
          -81.3,
          28.6
        ]
      },
      "type": "Feature",
      "properties": {
        "hierarchy": [
          "tgn:2265561",
          "tgn:1000001",
          "tgn:7012149",
          "tgn:7007240",
          "tgn:7029392"
        ],
        "placetype": [
          "aat:300008905"
        ],
        "id": 2265561,
        "name:xx": "Crane Strand"
      }
    },
    {
      "geometry": {
        "type": "Point",
        "coordinates": [
          -115.8333,
          40.55
        ]
      },
      "type": "Feature",
      "properties": {
        "hierarchy": [
          "tgn:2265562",
          "tgn:1000001",
          "tgn:2001411",
          "tgn:7012149",
          "tgn:7007526",
          "tgn:7029392"
        ],
        "placetype": [
          "aat:300008699"
        ],
        "id": 2265562,
        "name:xx": "Crane Stream"
      }
    },
    {
      "geometry": {
        "type": "Point",
        "coordinates": [
          -93.5667,
          36.9
        ]
      },
      "type": "Feature",
      "properties": {
        "hierarchy": [
          "tgn:2265563",
          "tgn:1000001",
          "tgn:7012149",
          "tgn:2001249",
          "tgn:7007523",
          "tgn:7029392"
        ],
        "placetype": [
          "aat:300006191"
        ],
        "id": 2265563,
        "name:xx": "Crane Structure Number 1 Reservoir"
      }
    },
    {
      "geometry": {
        "type": "Point",
        "coordinates": [
          -71.5833,
          42.3
        ]
      },
      "type": "Feature",
      "properties": {
        "hierarchy": [
          "tgn:2265564",
          "tgn:1000001",
          "tgn:7012149",
          "tgn:1003038",
          "tgn:7007517",
          "tgn:7029392"
        ],
        "placetype": [
          "aat:300008905"
        ],
        "id": 2265564,
        "name:xx": "Crane Swamp"
      }
    },
    {
      "geometry": {
        "type": "Point",
        "coordinates": [
          -83.4667,
          40.1833
        ]
      },
      "type": "Feature",
      "properties": {
        "hierarchy": [
          "tgn:2265565",
          "tgn:1000001",
          "tgn:7012149",
          "tgn:1002964",
          "tgn:7007706",
          "tgn:7029392"
        ],
        "placetype": [
          "aat:300008905"
        ],
        "id": 2265565,
        "name:xx": "Crane Swamp"
      }
    },
    {
      "geometry": {
        "type": "Point",
        "coordinates": [
          -76.2167,
          41.4833
        ]
      },
      "type": "Feature",
      "properties": {
        "hierarchy": [
          "tgn:2265566",
          "tgn:1000001",
          "tgn:7012149",
          "tgn:1003041",
          "tgn:7007710",
          "tgn:7029392"
        ],
        "placetype": [
          "aat:300008905"
        ],
        "id": 2265566,
        "name:xx": "Crane Swamp"
      }
    },
    {
      "geometry": {
        "type": "Point",
        "coordinates": [
          -76.2833,
          41.6
        ]
      },
      "type": "Feature",
      "properties": {
        "hierarchy": [
          "tgn:2265567",
          "tgn:1000001",
          "tgn:1002194",
          "tgn:7012149",
          "tgn:7007710",
          "tgn:7029392"
        ],
        "placetype": [
          "aat:300008905"
        ],
        "id": 2265567,
        "name:xx": "Crane Swamp"
      }
    },
    {
      "geometry": {
        "type": "Point",
        "coordinates": [
          -86.0833,
          35.0833
        ]
      },
      "type": "Feature",
      "properties": {
        "hierarchy": [
          "tgn:2265568",
          "tgn:1000001",
          "tgn:7012149",
          "tgn:2001862",
          "tgn:7007825",
          "tgn:7029392"
        ],
        "placetype": [
          "aat:300008798"
        ],
        "id": 2265568,
        "name:xx": "Crane Top"
      }
    }
  ]
}
