{
  "geometry": {
    "type": "Point",
    "coordinates": [
      -85.4333,
      37.6167
    ]
  },
  "type": "Feature",
  "properties": {
    "hierarchy": [
      "tgn:2679685",
      "tgn:1000001",
      "tgn:7012149",
      "tgn:7007255",
      "tgn:7029392"
    ],
    "placetype": [
      "aat:300008706"
    ],
    "id": 2679685,
    "name:xx": "South Fork Pottinger Creek"
  }
}
