{
  "geometry": {
    "type": "Point",
    "coordinates": [
      77.05,
      10.05
    ]
  },
  "type": "Feature",
  "properties": {
    "hierarchy": [
      "tgn:7552612",
      "tgn:1000004",
      "tgn:7000198",
      "tgn:1001886",
      "tgn:7029392"
    ],
    "placetype": [
      "aat:300387502"
    ],
    "name:en": "Pallivāsal Tea Estate",
    "id": 7552612
  }
}
