{
  "type": "FeatureCollection",
  "features": [
    {
      "geometry": {
        "type": "Point",
        "coordinates": [
          34.2833,
          5.5
        ]
      },
      "type": "Feature",
      "properties": {
        "hierarchy": [
          "tgn:1125820",
          "tgn:7001242",
          "tgn:7029392"
        ],
        "placetype": [
          "aat:300008707"
        ],
        "id": 1125820,
        "name:xx": "Kurun"
      }
    },
    {
      "geometry": {
        "type": "Point",
        "coordinates": [
          75.75,
          47.8333
        ]
      },
      "type": "Feature",
      "properties": {
        "hierarchy": [
          "tgn:1125821",
          "tgn:1000004",
          "tgn:7014786",
          "tgn:7029392"
        ],
        "placetype": [
          "aat:300008707"
        ],
        "id": 1125821,
        "name:xx": "Kusak"
      }
    },
    {
      "geometry": {
        "type": "Point",
        "coordinates": [
          136.5667,
          34.6
        ]
      },
      "type": "Feature",
      "properties": {
        "hierarchy": [
          "tgn:1125822",
          "tgn:7016674",
          "tgn:1000004",
          "tgn:1000120",
          "tgn:7029392"
        ],
        "placetype": [
          "aat:300008707"
        ],
        "id": 1125822,
        "name:xx": "Kushida"
      }
    },
    {
      "geometry": {
        "type": "Point",
        "coordinates": [
          91.7333,
          24.6
        ]
      },
      "type": "Feature",
      "properties": {
        "hierarchy": [
          "tgn:1125823",
          "tgn:7000188",
          "tgn:1000004",
          "tgn:1000105",
          "tgn:7029392"
        ],
        "placetype": [
          "aat:300008707"
        ],
        "id": 1125823,
        "name:xx": "Kusiyāra"
      }
    },
    {
      "geometry": {
        "type": "Point",
        "coordinates": [
          -154.6333,
          63.0833
        ]
      },
      "type": "Feature",
      "properties": {
        "hierarchy": [
          "tgn:1125824",
          "tgn:7006450",
          "tgn:1000001",
          "tgn:7012149",
          "tgn:7029392"
        ],
        "placetype": [
          "aat:300008707"
        ],
        "id": 1125824,
        "name:xx": "Kuskokwim River"
      }
    }
  ]
}
