{
  "geometry": {
    "type": "Point",
    "coordinates": [
      -83.5667,
      37.3833
    ]
  },
  "type": "Feature",
  "properties": {
    "hierarchy": [
      "tgn:2780051",
      "tgn:1000001",
      "tgn:7012149",
      "tgn:2000835",
      "tgn:7007255",
      "tgn:7029392"
    ],
    "placetype": [
      "aat:300008761"
    ],
    "id": 2780051,
    "name:xx": "Wolfpen Hollow"
  }
}
