{
  "geometry": {
    "type": "Point",
    "coordinates": [
      -85.3833,
      41.1833
    ]
  },
  "type": "Feature",
  "properties": {
    "hierarchy": [
      "tgn:2031429",
      "tgn:1000001",
      "tgn:7012149",
      "tgn:1003022",
      "tgn:7007252",
      "tgn:7029392"
    ],
    "placetype": [
      "aat:300008347"
    ],
    "id": 2031429,
    "name:xx": "Collins"
  }
}
