{
  "geometry": {
    "type": "Point",
    "coordinates": [
      -121.8333,
      46.9333
    ]
  },
  "type": "Feature",
  "properties": {
    "hierarchy": [
      "tgn:2225318",
      "tgn:1000001",
      "tgn:7012149",
      "tgn:1002785",
      "tgn:7007920",
      "tgn:7029392"
    ],
    "placetype": [
      "aat:300008798"
    ],
    "id": 2225318,
    "name:xx": "Castle Peak"
  }
}
