{
  "type": "FeatureCollection",
  "features": [
    {
      "geometry": {
        "type": "Point",
        "coordinates": [
          -103.416667,
          23.166667
        ]
      },
      "type": "Feature",
      "properties": {
        "hierarchy": [
          "tgn:7378180",
          "tgn:1000001",
          "tgn:7005601",
          "tgn:7005560",
          "tgn:7029392"
        ],
        "placetype": [
          "aat:300008347"
        ],
        "id": 7378180,
        "name:xx": "La Presa"
      }
    },
    {
      "geometry": {
        "type": "Point",
        "coordinates": [
          -98.833333,
          23.033333
        ]
      },
      "type": "Feature",
      "properties": {
        "hierarchy": [
          "tgn:7378181",
          "tgn:1000001",
          "tgn:7005597",
          "tgn:7005560",
          "tgn:7029392"
        ],
        "placetype": [
          "aat:300008347"
        ],
        "id": 7378181,
        "name:xx": "La Presa"
      }
    },
    {
      "geometry": {
        "type": "Point",
        "coordinates": [
          -101.1,
          22.683333
        ]
      },
      "type": "Feature",
      "properties": {
        "hierarchy": [
          "tgn:7378182",
          "tgn:1000001",
          "tgn:7005594",
          "tgn:7005560",
          "tgn:7029392"
        ],
        "placetype": [
          "aat:300008347"
        ],
        "id": 7378182,
        "name:xx": "La Presa"
      }
    },
    {
      "geometry": {
        "type": "Point",
        "coordinates": [
          -105.2,
          21.8
        ]
      },
      "type": "Feature",
      "properties": {
        "hierarchy": [
          "tgn:7378183",
          "tgn:1000001",
          "tgn:1001906",
          "tgn:7005560",
          "tgn:7029392"
        ],
        "placetype": [
          "aat:300008347"
        ],
        "id": 7378183,
        "name:xx": "La Presa"
      }
    },
    {
      "geometry": {
        "type": "Point",
        "coordinates": [
          -101.8,
          21.766667
        ]
      },
      "type": "Feature",
      "properties": {
        "hierarchy": [
          "tgn:7378184",
          "tgn:7005586",
          "tgn:1000001",
          "tgn:7005560",
          "tgn:7029392"
        ],
        "placetype": [
          "aat:300008347"
        ],
        "id": 7378184,
        "name:xx": "La Presa"
      }
    },
    {
      "geometry": {
        "type": "Point",
        "coordinates": [
          -105.05,
          21.616667
        ]
      },
      "type": "Feature",
      "properties": {
        "hierarchy": [
          "tgn:7378185",
          "tgn:1000001",
          "tgn:1001906",
          "tgn:7005560",
          "tgn:7029392"
        ],
        "placetype": [
          "aat:300008347"
        ],
        "id": 7378185,
        "name:xx": "La Presa"
      }
    },
    {
      "geometry": {
        "type": "Point",
        "coordinates": [
          -100.663889,
          20.726389
        ]
      },
      "type": "Feature",
      "properties": {
        "hierarchy": [
          "tgn:7378186",
          "tgn:7005584",
          "tgn:1000001",
          "tgn:7005560",
          "tgn:7029392"
        ],
        "placetype": [
          "aat:300008347"
        ],
        "id": 7378186,
        "name:xx": "La Presa"
      }
    },
    {
      "geometry": {
        "type": "Point",
        "coordinates": [
          -103.283333,
          19.7
        ]
      },
      "type": "Feature",
      "properties": {
        "hierarchy": [
          "tgn:7378187",
          "tgn:7005586",
          "tgn:1000001",
          "tgn:7005560",
          "tgn:7029392"
        ],
        "placetype": [
          "aat:300008347"
        ],
        "id": 7378187,
        "name:xx": "La Presa"
      }
    },
    {
      "geometry": {
        "type": "Point",
        "coordinates": [
          -106.266667,
          29.85
        ]
      },
      "type": "Feature",
      "properties": {
        "hierarchy": [
          "tgn:7378188",
          "tgn:7005581",
          "tgn:1000001",
          "tgn:7005560",
          "tgn:7029392"
        ],
        "placetype": [
          "aat:300008697"
        ],
        "id": 7378188,
        "name:xx": "La Prensa, Ojo"
      }
    },
    {
      "geometry": {
        "type": "Point",
        "coordinates": [
          -99.2,
          19.483333
        ]
      },
      "type": "Feature",
      "properties": {
        "hierarchy": [
          "tgn:7378189",
          "tgn:7005575",
          "tgn:1000001",
          "tgn:7005560",
          "tgn:7029392"
        ],
        "placetype": [
          "aat:300008347"
        ],
        "id": 7378189,
        "name:xx": "La Preciosa"
      }
    }
  ]
}
