{
  "geometry": {
    "type": "Point",
    "coordinates": [
      -141.15,
      63.7667
    ]
  },
  "type": "Feature",
  "properties": {
    "hierarchy": [
      "tgn:2548276",
      "tgn:7006450",
      "tgn:1000001",
      "tgn:7012149",
      "tgn:2000085",
      "tgn:7029392"
    ],
    "placetype": [
      "aat:300008707"
    ],
    "id": 2548276,
    "name:xx": "North Ladue River"
  }
}
