{
  "geometry": {
    "type": "Point",
    "coordinates": [
      -119.3667,
      48.0333
    ]
  },
  "type": "Feature",
  "properties": {
    "hierarchy": [
      "tgn:2743690",
      "tgn:1000001",
      "tgn:2002242",
      "tgn:7012149",
      "tgn:7007920",
      "tgn:7029392"
    ],
    "placetype": [
      "aat:300008697"
    ],
    "id": 2743690,
    "name:xx": "Vaughn Spring"
  }
}
