{
  "geometry": {
    "type": "Point",
    "coordinates": [
      -105.3833,
      33.0667
    ]
  },
  "type": "Feature",
  "properties": {
    "hierarchy": [
      "tgn:2473969",
      "tgn:1000001",
      "tgn:7012149",
      "tgn:2001447",
      "tgn:7007566",
      "tgn:7029392"
    ],
    "placetype": [
      "aat:300006191"
    ],
    "id": 2473969,
    "name:xx": "Lower Indian Tank"
  }
}
