{
  "geometry": {
    "type": "Point",
    "coordinates": [
      -81.7167,
      33.7833
    ]
  },
  "type": "Feature",
  "properties": {
    "hierarchy": [
      "tgn:2649250",
      "tgn:1000001",
      "tgn:7013677",
      "tgn:7012149",
      "tgn:7007712",
      "tgn:7029392"
    ],
    "placetype": [
      "aat:300006191"
    ],
    "id": 2649250,
    "name:xx": "Scott Pond"
  }
}
