{
  "geometry": {
    "type": "Point",
    "coordinates": [
      -114.0333,
      37.3667
    ]
  },
  "type": "Feature",
  "properties": {
    "hierarchy": [
      "tgn:2399936",
      "tgn:1000001",
      "tgn:7012149",
      "tgn:2002127",
      "tgn:7007827",
      "tgn:7029392"
    ],
    "placetype": [
      "aat:300008761"
    ],
    "id": 2399936,
    "name:xx": "Horse Canyon"
  }
}
