{
  "type": "FeatureCollection",
  "features": [
    {
      "geometry": {
        "type": "Point",
        "coordinates": [
          -121.65,
          39.25
        ]
      },
      "type": "Feature",
      "properties": {
        "hierarchy": [
          "tgn:2014510",
          "tgn:1000001",
          "tgn:7012149",
          "tgn:7007157",
          "tgn:1002937",
          "tgn:7029392"
        ],
        "placetype": [
          "aat:300387016"
        ],
        "id": 2014510,
        "name:xx": "Sunset"
      }
    },
    {
      "geometry": {
        "type": "Point",
        "coordinates": [
          -118.0667,
          33.7
        ]
      },
      "type": "Feature",
      "properties": {
        "hierarchy": [
          "tgn:2014514",
          "tgn:1000001",
          "tgn:7012149",
          "tgn:7007157",
          "tgn:1002748",
          "tgn:7029392"
        ],
        "placetype": [
          "aat:300008347"
        ],
        "id": 2014514,
        "name:xx": "Sunset Beach"
      }
    },
    {
      "geometry": {
        "type": "Point",
        "coordinates": [
          -121.0833,
          39.2167
        ]
      },
      "type": "Feature",
      "properties": {
        "hierarchy": [
          "tgn:2014515",
          "tgn:1000001",
          "tgn:7012149",
          "tgn:7007157",
          "tgn:1002710",
          "tgn:7029392"
        ],
        "placetype": [
          "aat:300008347"
        ],
        "id": 2014515,
        "name:xx": "Sunset View"
      }
    },
    {
      "geometry": {
        "type": "Point",
        "coordinates": [
          -116.7333,
          33.35
        ]
      },
      "type": "Feature",
      "properties": {
        "hierarchy": [
          "tgn:2014516",
          "tgn:1000001",
          "tgn:7012149",
          "tgn:7007157",
          "tgn:1002858",
          "tgn:7029392"
        ],
        "placetype": [
          "aat:300008347"
        ],
        "id": 2014516,
        "name:xx": "Sunshine Summit"
      }
    },
    {
      "geometry": {
        "type": "Point",
        "coordinates": [
          -120.65,
          40.4
        ]
      },
      "type": "Feature",
      "properties": {
        "hierarchy": [
          "tgn:2014517",
          "tgn:1000001",
          "tgn:7012149",
          "tgn:7007157",
          "tgn:2000184",
          "tgn:7029392"
        ],
        "placetype": [
          "aat:300008347"
        ],
        "id": 2014517,
        "name:xx": "Susanville"
      }
    },
    {
      "geometry": {
        "type": "Point",
        "coordinates": [
          -121.75,
          39.15
        ]
      },
      "type": "Feature",
      "properties": {
        "hierarchy": [
          "tgn:2014518",
          "tgn:1000001",
          "tgn:7012149",
          "tgn:7007157",
          "tgn:1002937",
          "tgn:7029392"
        ],
        "placetype": [
          "aat:300008347"
        ],
        "id": 2014518,
        "name:xx": "Sutter"
      }
    },
    {
      "geometry": {
        "type": "Point",
        "coordinates": [
          -120.8,
          38.3833
        ]
      },
      "type": "Feature",
      "properties": {
        "hierarchy": [
          "tgn:2014519",
          "tgn:1002146",
          "tgn:1000001",
          "tgn:7012149",
          "tgn:7007157",
          "tgn:7029392"
        ],
        "placetype": [
          "aat:300008347"
        ],
        "id": 2014519,
        "name:xx": "Sutter Creek"
      }
    }
  ]
}
