{
  "geometry": {
    "type": "Point",
    "coordinates": [
      -108.9167,
      41.7833
    ]
  },
  "type": "Feature",
  "properties": {
    "hierarchy": [
      "tgn:2787176",
      "tgn:1000001",
      "tgn:7012149",
      "tgn:2002383",
      "tgn:7007923",
      "tgn:7029392"
    ],
    "placetype": [
      "aat:300008798"
    ],
    "id": 2787176,
    "name:xx": "Zirkel Mesa"
  }
}
