{
  "geometry": {
    "type": "Point",
    "coordinates": [
      148.9833,
      -32.55
    ]
  },
  "type": "Feature",
  "properties": {
    "hierarchy": [
      "tgn:1098494",
      "tgn:7000490",
      "tgn:1000006",
      "tgn:7001828",
      "tgn:7029392"
    ],
    "placetype": [
      "aat:300008347"
    ],
    "id": 1098494,
    "name:xx": "Wellington"
  }
}
