{
  "geometry": {
    "type": "Point",
    "coordinates": [
      -86.2333,
      37.25
    ]
  },
  "type": "Feature",
  "properties": {
    "hierarchy": [
      "tgn:2270989",
      "tgn:1000001",
      "tgn:7012149",
      "tgn:2000787",
      "tgn:7007255",
      "tgn:7029392"
    ],
    "placetype": [
      "aat:300008761"
    ],
    "id": 2270989,
    "name:xx": "Cubby Cove"
  }
}
