{
  "geometry": {
    "type": "Point",
    "coordinates": [
      32.4333,
      46.2167
    ]
  },
  "type": "Feature",
  "properties": {
    "hierarchy": [
      "tgn:1053683",
      "tgn:7011651",
      "tgn:1000003",
      "tgn:7006660",
      "tgn:7029392"
    ],
    "placetype": [
      "aat:300008347"
    ],
    "id": 1053683,
    "name:xx": "Dolmativka"
  }
}
