{
  "geometry": {
    "type": "Point",
    "coordinates": [
      -86.2667,
      33.7333
    ]
  },
  "type": "Feature",
  "properties": {
    "hierarchy": [
      "tgn:2368607",
      "tgn:7002659",
      "tgn:1000001",
      "tgn:7012149",
      "tgn:2000057",
      "tgn:7029392"
    ],
    "placetype": [
      "aat:300008761"
    ],
    "id": 2368607,
    "name:xx": "Gulf Hollow"
  }
}
