{
  "geometry": {
    "type": "Point",
    "coordinates": [
      -78.5833,
      34.5833
    ]
  },
  "type": "Feature",
  "properties": {
    "hierarchy": [
      "tgn:2588214",
      "tgn:1000001",
      "tgn:2001471",
      "tgn:7012149",
      "tgn:7007709",
      "tgn:7029392"
    ],
    "placetype": [
      "aat:300008699"
    ],
    "id": 2588214,
    "name:xx": "Plum Branch"
  }
}
