{
  "geometry": {
    "type": "Point",
    "coordinates": [
      -86.7333,
      36.5167
    ]
  },
  "type": "Feature",
  "properties": {
    "hierarchy": [
      "tgn:2157641",
      "tgn:1000001",
      "tgn:7012149",
      "tgn:2001910",
      "tgn:7007825",
      "tgn:7029392"
    ],
    "placetype": [
      "aat:300008706"
    ],
    "id": 2157641,
    "name:xx": "Beaver Dam Creek"
  }
}
