{
  "type": "FeatureCollection",
  "features": [
    {
      "geometry": {
        "type": "Point",
        "coordinates": [
          -104.566667,
          22.716667
        ]
      },
      "type": "Feature",
      "properties": {
        "hierarchy": [
          "tgn:7348771",
          "tgn:7005583",
          "tgn:1000001",
          "tgn:7005560",
          "tgn:7029392"
        ],
        "placetype": [
          "aat:300008347"
        ],
        "id": 7348771,
        "name:xx": "Agua Caliente"
      }
    },
    {
      "geometry": {
        "type": "Point",
        "coordinates": [
          -105.25,
          22.35
        ]
      },
      "type": "Feature",
      "properties": {
        "hierarchy": [
          "tgn:7348772",
          "tgn:1000001",
          "tgn:1001906",
          "tgn:7005560",
          "tgn:7029392"
        ],
        "placetype": [
          "aat:300008347"
        ],
        "id": 7348772,
        "name:xx": "Agua Caliente"
      }
    },
    {
      "geometry": {
        "type": "Point",
        "coordinates": [
          -105.2,
          21.766667
        ]
      },
      "type": "Feature",
      "properties": {
        "hierarchy": [
          "tgn:7348773",
          "tgn:1000001",
          "tgn:1001906",
          "tgn:7005560",
          "tgn:7029392"
        ],
        "placetype": [
          "aat:300008347"
        ],
        "id": 7348773,
        "name:xx": "Agua Caliente"
      }
    },
    {
      "geometry": {
        "type": "Point",
        "coordinates": [
          -104.616667,
          21.65
        ]
      },
      "type": "Feature",
      "properties": {
        "hierarchy": [
          "tgn:7348774",
          "tgn:1000001",
          "tgn:1001906",
          "tgn:7005560",
          "tgn:7029392"
        ],
        "placetype": [
          "aat:300008347"
        ],
        "id": 7348774,
        "name:xx": "Aguacaliente"
      }
    },
    {
      "geometry": {
        "type": "Point",
        "coordinates": [
          -102.55,
          21.283333
        ]
      },
      "type": "Feature",
      "properties": {
        "hierarchy": [
          "tgn:7348775",
          "tgn:1000001",
          "tgn:1001906",
          "tgn:7005560",
          "tgn:7029392"
        ],
        "placetype": [
          "aat:300008347"
        ],
        "id": 7348775,
        "name:xx": "Agua Caliente"
      }
    },
    {
      "geometry": {
        "type": "Point",
        "coordinates": [
          -104.683333,
          21.1
        ]
      },
      "type": "Feature",
      "properties": {
        "hierarchy": [
          "tgn:7348776",
          "tgn:1000001",
          "tgn:1001906",
          "tgn:7005560",
          "tgn:7029392"
        ],
        "placetype": [
          "aat:300008347"
        ],
        "id": 7348776,
        "name:xx": "Agua Caliente"
      }
    },
    {
      "geometry": {
        "type": "Point",
        "coordinates": [
          -103.816667,
          20.516667
        ]
      },
      "type": "Feature",
      "properties": {
        "hierarchy": [
          "tgn:7348777",
          "tgn:7005586",
          "tgn:1000001",
          "tgn:7005560",
          "tgn:7029392"
        ],
        "placetype": [
          "aat:300008347"
        ],
        "id": 7348777,
        "name:xx": "Aguacaliente"
      }
    },
    {
      "geometry": {
        "type": "Point",
        "coordinates": [
          -102.916667,
          20.3
        ]
      },
      "type": "Feature",
      "properties": {
        "hierarchy": [
          "tgn:7348778",
          "tgn:7005586",
          "tgn:1000001",
          "tgn:7005560",
          "tgn:7029392"
        ],
        "placetype": [
          "aat:300008347"
        ],
        "id": 7348778,
        "name:xx": "Agua Caliente"
      }
    },
    {
      "geometry": {
        "type": "Point",
        "coordinates": [
          -105.45,
          20.216667
        ]
      },
      "type": "Feature",
      "properties": {
        "hierarchy": [
          "tgn:7348779",
          "tgn:7005586",
          "tgn:1000001",
          "tgn:7005560",
          "tgn:7029392"
        ],
        "placetype": [
          "aat:300008347"
        ],
        "id": 7348779,
        "name:xx": "Agua Caliente"
      }
    }
  ]
}
