{
  "geometry": {
    "type": "Point",
    "coordinates": [
      31.1323,
      30.193337
    ]
  },
  "type": "Feature",
  "properties": {
    "hierarchy": [
      "tgn:7526313",
      "tgn:7001242",
      "tgn:7016833",
      "tgn:7029392"
    ],
    "placetype": [
      "aat:300006075"
    ],
    "id": 7526313,
    "name:xx": "Ar Rayyāḩ at Tawfīqī"
  }
}
