{
  "geometry": {
    "type": "Point",
    "coordinates": [
      -81.2333,
      37.4167
    ]
  },
  "type": "Feature",
  "properties": {
    "hierarchy": [
      "tgn:2119149",
      "tgn:1000001",
      "tgn:7012149",
      "tgn:2002278",
      "tgn:7013961",
      "tgn:7029392"
    ],
    "placetype": [
      "aat:300008347"
    ],
    "id": 2119149,
    "name:xx": "Matoaka"
  }
}
