{
  "geometry": {
    "type": "Point",
    "coordinates": [
      18.15,
      54.7833
    ]
  },
  "type": "Feature",
  "properties": {
    "hierarchy": [
      "tgn:1049183",
      "tgn:1000003",
      "tgn:7024115",
      "tgn:7006366",
      "tgn:7029392"
    ],
    "placetype": [
      "aat:300008347"
    ],
    "id": 1049183,
    "name:xx": "Krokowa"
  }
}
