{
  "geometry": {
    "type": "Point",
    "coordinates": [
      -42.7833,
      -21.6833
    ]
  },
  "type": "Feature",
  "properties": {
    "hierarchy": [
      "tgn:1136567",
      "tgn:7006237",
      "tgn:1000047",
      "tgn:7002457",
      "tgn:1000002",
      "tgn:7029392"
    ],
    "placetype": [
      "aat:300008347"
    ],
    "id": 1136567,
    "name:xx": "São Domingos"
  }
}
