{
  "geometry": {
    "type": "Point",
    "coordinates": [
      -95.8667,
      40.6333
    ]
  },
  "type": "Feature",
  "properties": {
    "hierarchy": [
      "tgn:2720096",
      "tgn:1000001",
      "tgn:7012149",
      "tgn:2001381",
      "tgn:7007525",
      "tgn:7029392"
    ],
    "placetype": [
      "aat:300008706"
    ],
    "id": 2720096,
    "name:xx": "Threemile Creek"
  }
}
