{
  "geometry": {
    "type": "Point",
    "coordinates": [
      -88.2333,
      35.1167
    ]
  },
  "type": "Feature",
  "properties": {
    "hierarchy": [
      "tgn:2165073",
      "tgn:1000001",
      "tgn:7012149",
      "tgn:2001872",
      "tgn:7007825",
      "tgn:7029392"
    ],
    "placetype": [
      "aat:300008699"
    ],
    "id": 2165073,
    "name:xx": "Bethel Branch"
  }
}
