{
  "geometry": {
    "type": "Point",
    "coordinates": [
      -76.35,
      40.4333
    ]
  },
  "type": "Feature",
  "properties": {
    "hierarchy": [
      "tgn:2268980",
      "tgn:1000001",
      "tgn:7013387",
      "tgn:7012149",
      "tgn:7007710",
      "tgn:7029392"
    ],
    "placetype": [
      "aat:300008347"
    ],
    "id": 2268980,
    "name:xx": "Crosskill Mills"
  }
}
