{
  "type": "FeatureCollection",
  "features": [
    {
      "geometry": {
        "type": "Point",
        "coordinates": [
          6.45,
          52.383333
        ]
      },
      "type": "Feature",
      "properties": {
        "hierarchy": [
          "tgn:1047840",
          "tgn:1000003",
          "tgn:7003626",
          "tgn:7016845",
          "tgn:7029392"
        ],
        "placetype": [
          "aat:300008347"
        ],
        "name:nl": "Hellendoorn",
        "id": 1047840
      }
    },
    {
      "geometry": {
        "type": "Point",
        "coordinates": [
          4.133333,
          51.833333
        ]
      },
      "type": "Feature",
      "properties": {
        "hierarchy": [
          "tgn:1047841",
          "tgn:1000003",
          "tgn:7003632",
          "tgn:7016845",
          "tgn:1009666",
          "tgn:7029392"
        ],
        "placetype": [
          "aat:300008347"
        ],
        "name:nl": "Hellevoetsluis",
        "id": 1047841
      }
    },
    {
      "geometry": {
        "type": "Point",
        "coordinates": [
          5.233333,
          51.633333
        ]
      },
      "type": "Feature",
      "properties": {
        "hierarchy": [
          "tgn:1047843",
          "tgn:1000003",
          "tgn:7003624",
          "tgn:7016845",
          "tgn:7029392"
        ],
        "placetype": [
          "aat:300008347",
          "aat:300008375"
        ],
        "name:nl": "Helvoirt",
        "id": 1047843
      }
    },
    {
      "geometry": {
        "type": "Point",
        "coordinates": [
          4.583333,
          52.3
        ]
      },
      "type": "Feature",
      "properties": {
        "hierarchy": [
          "tgn:1047845",
          "tgn:1000003",
          "tgn:7003632",
          "tgn:7016845",
          "tgn:7029392"
        ],
        "placetype": [
          "aat:300008347"
        ],
        "name:nl": "Hillegom",
        "id": 1047845
      }
    },
    {
      "geometry": {
        "type": "Point",
        "coordinates": [
          5.133333,
          51.483333
        ]
      },
      "type": "Feature",
      "properties": {
        "hierarchy": [
          "tgn:1047846",
          "tgn:1000003",
          "tgn:7003624",
          "tgn:7016845",
          "tgn:7029392"
        ],
        "placetype": [
          "aat:300008347"
        ],
        "name:nl": "Hilvarenbeek",
        "id": 1047846
      }
    },
    {
      "geometry": {
        "type": "Point",
        "coordinates": [
          4.966667,
          52.9
        ]
      },
      "type": "Feature",
      "properties": {
        "hierarchy": [
          "tgn:1047849",
          "tgn:1000003",
          "tgn:7006951",
          "tgn:7016845",
          "tgn:7029392"
        ],
        "placetype": [
          "aat:300008347"
        ],
        "name:nl": "Hippolytushoef",
        "id": 1047849
      }
    }
  ]
}
