{
  "geometry": {
    "type": "Point",
    "coordinates": [
      -80.2167,
      40.1333
    ]
  },
  "type": "Feature",
  "properties": {
    "hierarchy": [
      "tgn:2086601",
      "tgn:1000001",
      "tgn:7012149",
      "tgn:1002995",
      "tgn:7007710",
      "tgn:7029392"
    ],
    "placetype": [
      "aat:300008347"
    ],
    "id": 2086601,
    "name:xx": "Braddock"
  }
}
