{
  "geometry": {
    "type": "Point",
    "coordinates": [
      -108.6333,
      34.0833
    ]
  },
  "type": "Feature",
  "properties": {
    "hierarchy": [
      "tgn:2283612",
      "tgn:1000001",
      "tgn:2001429",
      "tgn:7012149",
      "tgn:7007566",
      "tgn:7029392"
    ],
    "placetype": [
      "aat:300008706"
    ],
    "id": 2283612,
    "name:xx": "Demetrio Creek"
  }
}
