{
  "geometry": {
    "type": "Point",
    "coordinates": [
      -105.3833,
      39.7667
    ]
  },
  "type": "Feature",
  "properties": {
    "hierarchy": [
      "tgn:2151320",
      "tgn:1000001",
      "tgn:7012149",
      "tgn:7007158",
      "tgn:7029392"
    ],
    "placetype": [
      "aat:300008761"
    ],
    "id": 2151320,
    "name:xx": "Bates Gulch"
  }
}
