{
  "geometry": {
    "type": "Point",
    "coordinates": [
      -89.6833,
      45.1667
    ]
  },
  "type": "Feature",
  "properties": {
    "hierarchy": [
      "tgn:2121793",
      "tgn:1000001",
      "tgn:7012149",
      "tgn:2002334",
      "tgn:7007922",
      "tgn:7029392"
    ],
    "placetype": [
      "aat:300008347"
    ],
    "id": 2121793,
    "name:xx": "Merrill"
  }
}
