{
  "geometry": {
    "type": "Point",
    "coordinates": [
      -84.9667,
      34.9167
    ]
  },
  "type": "Feature",
  "properties": {
    "hierarchy": [
      "tgn:2435196",
      "tgn:1000001",
      "tgn:7012149",
      "tgn:2000446",
      "tgn:7007248",
      "tgn:7029392"
    ],
    "placetype": [
      "aat:300008706"
    ],
    "id": 2435196,
    "name:xx": "Kenyon Creek"
  }
}
