{
  "geometry": {
    "type": "Point",
    "coordinates": [
      -71.7833,
      41.3333
    ]
  },
  "type": "Feature",
  "properties": {
    "hierarchy": [
      "tgn:2290046",
      "tgn:1002996",
      "tgn:1000001",
      "tgn:7012149",
      "tgn:7007711",
      "tgn:7029392"
    ],
    "placetype": [
      "aat:300008680"
    ],
    "id": 2290046,
    "name:xx": "Doctor Lewis Pond"
  }
}
