{
  "geometry": {
    "type": "Point",
    "coordinates": [
      -115.3833,
      33.05
    ]
  },
  "type": "Feature",
  "properties": {
    "hierarchy": [
      "tgn:2497880",
      "tgn:1000001",
      "tgn:7012149",
      "tgn:2000182",
      "tgn:7007157",
      "tgn:7029392"
    ],
    "placetype": [
      "aat:300006075"
    ],
    "id": 2497880,
    "name:xx": "Mayflower Lateral"
  }
}
