{
  "type": "FeatureCollection",
  "features": [
    {
      "geometry": {
        "type": "Point",
        "coordinates": [
          -92.85,
          40.6833
        ]
      },
      "type": "Feature",
      "properties": {
        "hierarchy": [
          "tgn:2199410",
          "tgn:7019177",
          "tgn:1000001",
          "tgn:7012149",
          "tgn:7007253",
          "tgn:7029392"
        ],
        "placetype": [
          "aat:300008706"
        ],
        "id": 2199410,
        "name:xx": "Brush Creek"
      }
    },
    {
      "geometry": {
        "type": "Point",
        "coordinates": [
          -91.45,
          40.9333
        ]
      },
      "type": "Feature",
      "properties": {
        "hierarchy": [
          "tgn:2199411",
          "tgn:1000001",
          "tgn:2000604",
          "tgn:7012149",
          "tgn:7007253",
          "tgn:7029392"
        ],
        "placetype": [
          "aat:300008706"
        ],
        "id": 2199411,
        "name:xx": "Brush Creek"
      }
    },
    {
      "geometry": {
        "type": "Point",
        "coordinates": [
          -93.6167,
          40.9
        ]
      },
      "type": "Feature",
      "properties": {
        "hierarchy": [
          "tgn:2199412",
          "tgn:1000001",
          "tgn:7019179",
          "tgn:7012149",
          "tgn:7007253",
          "tgn:7029392"
        ],
        "placetype": [
          "aat:300008706"
        ],
        "id": 2199412,
        "name:xx": "Brush Creek"
      }
    },
    {
      "geometry": {
        "type": "Point",
        "coordinates": [
          -91.9667,
          41.0667
        ]
      },
      "type": "Feature",
      "properties": {
        "hierarchy": [
          "tgn:2199413",
          "tgn:1000001",
          "tgn:7012149",
          "tgn:7007253",
          "tgn:7029392"
        ],
        "placetype": [
          "aat:300008706"
        ],
        "id": 2199413,
        "name:xx": "Brush Creek"
      }
    },
    {
      "geometry": {
        "type": "Point",
        "coordinates": [
          -91.2333,
          40.8167
        ]
      },
      "type": "Feature",
      "properties": {
        "hierarchy": [
          "tgn:2199414",
          "tgn:1000001",
          "tgn:2000589",
          "tgn:7012149",
          "tgn:7007253",
          "tgn:7029392"
        ],
        "placetype": [
          "aat:300008706"
        ],
        "id": 2199414,
        "name:xx": "Brush Creek"
      }
    },
    {
      "geometry": {
        "type": "Point",
        "coordinates": [
          -91.7333,
          42.7333
        ]
      },
      "type": "Feature",
      "properties": {
        "hierarchy": [
          "tgn:2199415",
          "tgn:1000001",
          "tgn:2000593",
          "tgn:7012149",
          "tgn:7007253",
          "tgn:7029392"
        ],
        "placetype": [
          "aat:300008706"
        ],
        "id": 2199415,
        "name:xx": "Brush Creek"
      }
    },
    {
      "geometry": {
        "type": "Point",
        "coordinates": [
          -92.4167,
          40.6
        ]
      },
      "type": "Feature",
      "properties": {
        "hierarchy": [
          "tgn:2199416",
          "tgn:1000001",
          "tgn:7012149",
          "tgn:7029392"
        ],
        "placetype": [
          "aat:300008706"
        ],
        "id": 2199416,
        "name:xx": "Brush Creek"
      }
    },
    {
      "geometry": {
        "type": "Point",
        "coordinates": [
          -94.8167,
          37.2167
        ]
      },
      "type": "Feature",
      "properties": {
        "hierarchy": [
          "tgn:2199417",
          "tgn:1000001",
          "tgn:2000670",
          "tgn:7012149",
          "tgn:7007254",
          "tgn:7029392"
        ],
        "placetype": [
          "aat:300008706"
        ],
        "id": 2199417,
        "name:xx": "Brush Creek"
      }
    },
    {
      "geometry": {
        "type": "Point",
        "coordinates": [
          -94.8,
          37.3833
        ]
      },
      "type": "Feature",
      "properties": {
        "hierarchy": [
          "tgn:2199418",
          "tgn:1000001",
          "tgn:7012149",
          "tgn:7007254",
          "tgn:7029392"
        ],
        "placetype": [
          "aat:300008706"
        ],
        "id": 2199418,
        "name:xx": "Brush Creek"
      }
    },
    {
      "geometry": {
        "type": "Point",
        "coordinates": [
          -98.65,
          37.2
        ]
      },
      "type": "Feature",
      "properties": {
        "hierarchy": [
          "tgn:2199419",
          "tgn:2000663",
          "tgn:1000001",
          "tgn:7012149",
          "tgn:7007254",
          "tgn:7029392"
        ],
        "placetype": [
          "aat:300008706"
        ],
        "id": 2199419,
        "name:xx": "Brush Creek"
      }
    }
  ]
}
