{
  "geometry": {
    "type": "Point",
    "coordinates": [
      93.416,
      48.833
    ]
  },
  "type": "Feature",
  "properties": {
    "hierarchy": [
      "tgn:1122855",
      "tgn:1000004",
      "tgn:7029379",
      "tgn:7029392"
    ],
    "placetype": [
      "aat:300008707"
    ],
    "id": 1122855,
    "name:xx": "Hunguy Gol"
  }
}
