{
  "geometry": {
    "type": "Point",
    "coordinates": [
      -94.65,
      31.7667
    ]
  },
  "type": "Feature",
  "properties": {
    "hierarchy": [
      "tgn:2185140",
      "tgn:1000001",
      "tgn:7012149",
      "tgn:1002703",
      "tgn:7007826",
      "tgn:7029392"
    ],
    "placetype": [
      "aat:300008699"
    ],
    "id": 2185140,
    "name:xx": "Boggy Branch"
  }
}
