{
  "geometry": {
    "type": "Point",
    "coordinates": [
      -77.6833,
      41.1667
    ]
  },
  "type": "Feature",
  "properties": {
    "hierarchy": [
      "tgn:2487380",
      "tgn:1000001",
      "tgn:1002286",
      "tgn:7012149",
      "tgn:7007710",
      "tgn:7029392"
    ],
    "placetype": [
      "aat:300008699"
    ],
    "id": 2487380,
    "name:xx": "Left Branch Puncheon Run"
  }
}
