{
  "geometry": {
    "type": "Point",
    "coordinates": [
      -94.75,
      36.4833
    ]
  },
  "type": "Feature",
  "properties": {
    "hierarchy": [
      "tgn:2282248",
      "tgn:1000001",
      "tgn:7012149",
      "tgn:7029392"
    ],
    "placetype": [
      "aat:300008706"
    ],
    "id": 2282248,
    "name:xx": "Deer Lick Creek"
  }
}
