{
  "geometry": {
    "type": "Point",
    "coordinates": [
      77.88328,
      21.944679
    ]
  },
  "type": "Feature",
  "properties": {
    "hierarchy": [
      "tgn:7552970",
      "tgn:1000004",
      "tgn:7000198",
      "tgn:1001894",
      "tgn:7029392"
    ],
    "placetype": [
      "aat:300007783"
    ],
    "name:en": "Marāmjhiri",
    "id": 7552970
  }
}
