{
  "geometry": {
    "type": "Point",
    "coordinates": [
      9.3167,
      45.4667
    ]
  },
  "type": "Feature",
  "properties": {
    "hierarchy": [
      "tgn:1046470",
      "tgn:7003150",
      "tgn:1000003",
      "tgn:7003237",
      "tgn:1000080",
      "tgn:7029392"
    ],
    "placetype": [
      "aat:300008347"
    ],
    "id": 1046470,
    "name:xx": "San Bovio"
  }
}
