{
  "geometry": {
    "type": "Point",
    "coordinates": [
      3.4167,
      49.1667
    ]
  },
  "type": "Feature",
  "properties": {
    "hierarchy": [
      "tgn:5000986",
      "tgn:1000003",
      "tgn:7002890",
      "tgn:1000070",
      "tgn:7029392"
    ],
    "placetype": [
      "aat:300008347"
    ],
    "id": 5000986,
    "name:xx": "Coincy"
  }
}
