{
  "geometry": {
    "type": "Point",
    "coordinates": [
      -118.1333,
      41.8667
    ]
  },
  "type": "Feature",
  "properties": {
    "hierarchy": [
      "tgn:2400275",
      "tgn:1000001",
      "tgn:2001414",
      "tgn:7012149",
      "tgn:7007526",
      "tgn:7029392"
    ],
    "placetype": [
      "aat:300008697"
    ],
    "id": 2400275,
    "name:xx": "Horse Creek Spring"
  }
}
