{
  "geometry": {
    "type": "Point",
    "coordinates": [
      95.1167,
      21.9667
    ]
  },
  "type": "Feature",
  "properties": {
    "hierarchy": [
      "tgn:1066264",
      "tgn:1000004",
      "tgn:1002109",
      "tgn:1000108",
      "tgn:7029392"
    ],
    "placetype": [
      "aat:300008347"
    ],
    "id": 1066264,
    "name:xx": "Salingyi"
  }
}
