{
  "geometry": {
    "type": "Point",
    "coordinates": [
      74.863889,
      32.684722
    ]
  },
  "type": "Feature",
  "properties": {
    "hierarchy": [
      "tgn:7591898",
      "tgn:1000004",
      "tgn:7000198",
      "tgn:7000799",
      "tgn:7029392"
    ],
    "placetype": [
      "aat:300008347"
    ],
    "name:en": "Dangīāna",
    "id": 7591898
  }
}
