{
  "geometry": {
    "type": "Point",
    "coordinates": [
      72.883333,
      19.05
    ]
  },
  "type": "Feature",
  "properties": {
    "hierarchy": [
      "tgn:7571304",
      "tgn:1000004",
      "tgn:7000198",
      "tgn:1001895",
      "tgn:7029392"
    ],
    "placetype": [
      "aat:300055621"
    ],
    "name:en": "Kāmagār Colony",
    "id": 7571304
  }
}
