{
  "type": "FeatureCollection",
  "features": [
    {
      "geometry": {
        "type": "Point",
        "coordinates": [
          -120.6833,
          40.3
        ]
      },
      "type": "Feature",
      "properties": {
        "hierarchy": [
          "tgn:2286660",
          "tgn:1000001",
          "tgn:7012149",
          "tgn:7007157",
          "tgn:2000184",
          "tgn:7029392"
        ],
        "placetype": [
          "aat:300008798"
        ],
        "id": 2286660,
        "name:xx": "Diamond Mountain"
      }
    },
    {
      "geometry": {
        "type": "Point",
        "coordinates": [
          -108.95,
          40.7167
        ]
      },
      "type": "Feature",
      "properties": {
        "hierarchy": [
          "tgn:2286661",
          "tgn:1000001",
          "tgn:7012149",
          "tgn:2000232",
          "tgn:7007158",
          "tgn:7029392"
        ],
        "placetype": [
          "aat:300008798"
        ],
        "id": 2286661,
        "name:xx": "Diamond Mountain"
      }
    },
    {
      "geometry": {
        "type": "Point",
        "coordinates": [
          -106.5,
          40.3833
        ]
      },
      "type": "Feature",
      "properties": {
        "hierarchy": [
          "tgn:2286662",
          "tgn:1000001",
          "tgn:7012149",
          "tgn:7007158",
          "tgn:7029392"
        ],
        "placetype": [
          "aat:300008798"
        ],
        "id": 2286662,
        "name:xx": "Diamond Mountain"
      }
    },
    {
      "geometry": {
        "type": "Point",
        "coordinates": [
          -113.6667,
          46.9
        ]
      },
      "type": "Feature",
      "properties": {
        "hierarchy": [
          "tgn:2286663",
          "tgn:1000001",
          "tgn:7012149",
          "tgn:2001291",
          "tgn:7007524",
          "tgn:7029392"
        ],
        "placetype": [
          "aat:300008798"
        ],
        "id": 2286663,
        "name:xx": "Diamond Mountain"
      }
    },
    {
      "geometry": {
        "type": "Point",
        "coordinates": [
          -74.1333,
          41.1667
        ]
      },
      "type": "Feature",
      "properties": {
        "hierarchy": [
          "tgn:2286664",
          "tgn:1000001",
          "tgn:7012149",
          "tgn:1002833",
          "tgn:7007568",
          "tgn:7029392"
        ],
        "placetype": [
          "aat:300008798"
        ],
        "id": 2286664,
        "name:xx": "Diamond Mountain"
      }
    },
    {
      "geometry": {
        "type": "Point",
        "coordinates": [
          -74.1,
          43.6
        ]
      },
      "type": "Feature",
      "properties": {
        "hierarchy": [
          "tgn:2286665",
          "tgn:1000001",
          "tgn:7012149",
          "tgn:1002986",
          "tgn:7007568",
          "tgn:7029392"
        ],
        "placetype": [
          "aat:300008798"
        ],
        "id": 2286665,
        "name:xx": "Diamond Mountain"
      }
    },
    {
      "geometry": {
        "type": "Point",
        "coordinates": [
          -109.2333,
          40.6
        ]
      },
      "type": "Feature",
      "properties": {
        "hierarchy": [
          "tgn:2286666",
          "tgn:1000001",
          "tgn:7012149",
          "tgn:2002124",
          "tgn:7007827",
          "tgn:7029392"
        ],
        "placetype": [
          "aat:300008798"
        ],
        "id": 2286666,
        "name:xx": "Diamond Mountain"
      }
    },
    {
      "geometry": {
        "type": "Point",
        "coordinates": [
          -123.2833,
          47.7333
        ]
      },
      "type": "Feature",
      "properties": {
        "hierarchy": [
          "tgn:2286667",
          "tgn:1000001",
          "tgn:7012149",
          "tgn:1002521",
          "tgn:7007920",
          "tgn:7029392"
        ],
        "placetype": [
          "aat:300008798"
        ],
        "id": 2286667,
        "name:xx": "Diamond Mountain"
      }
    },
    {
      "geometry": {
        "type": "Point",
        "coordinates": [
          -109.3,
          40.6333
        ]
      },
      "type": "Feature",
      "properties": {
        "hierarchy": [
          "tgn:2286668",
          "tgn:1000001",
          "tgn:7012149",
          "tgn:2002124",
          "tgn:7007827",
          "tgn:7029392"
        ],
        "placetype": [
          "aat:300008805"
        ],
        "id": 2286668,
        "name:xx": "Diamond Mountain Plateau"
      }
    },
    {
      "geometry": {
        "type": "Point",
        "coordinates": [
          -120.1833,
          40.0333
        ]
      },
      "type": "Feature",
      "properties": {
        "hierarchy": [
          "tgn:2286669",
          "tgn:1000001",
          "tgn:7012149",
          "tgn:7007157",
          "tgn:7029392"
        ],
        "placetype": [
          "aat:300386831"
        ],
        "id": 2286669,
        "name:xx": "Diamond Mountains"
      }
    }
  ]
}
