{
  "type": "FeatureCollection",
  "features": [
    {
      "geometry": {
        "type": "Point",
        "coordinates": [
          8.9,
          52.1
        ]
      },
      "type": "Feature",
      "properties": {
        "hierarchy": [
          "tgn:7198790",
          "tgn:1000003",
          "tgn:7003677",
          "tgn:7000084",
          "tgn:7029392"
        ],
        "placetype": [
          "aat:300000206"
        ],
        "id": 7198790,
        "name:xx": "Eichhof"
      }
    },
    {
      "geometry": {
        "type": "Point",
        "coordinates": [
          8.533333,
          51.933333
        ]
      },
      "type": "Feature",
      "properties": {
        "hierarchy": [
          "tgn:7198791",
          "tgn:1000003",
          "tgn:7003677",
          "tgn:7000084",
          "tgn:7029392"
        ],
        "placetype": [
          "aat:300000206"
        ],
        "id": 7198791,
        "name:xx": "Eichhof"
      }
    },
    {
      "geometry": {
        "type": "Point",
        "coordinates": [
          9.65,
          51.45
        ]
      },
      "type": "Feature",
      "properties": {
        "hierarchy": [
          "tgn:7198792",
          "tgn:1000003",
          "tgn:7003676",
          "tgn:7000084",
          "tgn:7029392"
        ],
        "placetype": [
          "aat:300000206"
        ],
        "id": 7198792,
        "name:xx": "Eichhof"
      }
    },
    {
      "geometry": {
        "type": "Point",
        "coordinates": [
          6.366667,
          51.016667
        ]
      },
      "type": "Feature",
      "properties": {
        "hierarchy": [
          "tgn:7198793",
          "tgn:1000003",
          "tgn:7003677",
          "tgn:7000084",
          "tgn:7029392"
        ],
        "placetype": [
          "aat:300000206"
        ],
        "id": 7198793,
        "name:xx": "Eichhof"
      }
    },
    {
      "geometry": {
        "type": "Point",
        "coordinates": [
          8.9,
          50.95
        ]
      },
      "type": "Feature",
      "properties": {
        "hierarchy": [
          "tgn:7198794",
          "tgn:1000003",
          "tgn:7003678",
          "tgn:7000084",
          "tgn:7029392"
        ],
        "placetype": [
          "aat:300000206"
        ],
        "id": 7198794,
        "name:xx": "Eichhof"
      }
    },
    {
      "geometry": {
        "type": "Point",
        "coordinates": [
          9.216667,
          49.316667
        ]
      },
      "type": "Feature",
      "properties": {
        "hierarchy": [
          "tgn:7198795",
          "tgn:7003692",
          "tgn:1000003",
          "tgn:7000084",
          "tgn:7029392"
        ],
        "placetype": [
          "aat:300000206"
        ],
        "id": 7198795,
        "name:xx": "Eichhof"
      }
    },
    {
      "geometry": {
        "type": "Point",
        "coordinates": [
          12.283333,
          49.083333
        ]
      },
      "type": "Feature",
      "properties": {
        "hierarchy": [
          "tgn:7198796",
          "tgn:7003669",
          "tgn:1000003",
          "tgn:7000084",
          "tgn:7029392"
        ],
        "placetype": [
          "aat:300000206"
        ],
        "id": 7198796,
        "name:xx": "Eichhof"
      }
    },
    {
      "geometry": {
        "type": "Point",
        "coordinates": [
          10.85,
          48.933333
        ]
      },
      "type": "Feature",
      "properties": {
        "hierarchy": [
          "tgn:7198797",
          "tgn:7003669",
          "tgn:1000003",
          "tgn:7000084",
          "tgn:7029392"
        ],
        "placetype": [
          "aat:300000206"
        ],
        "id": 7198797,
        "name:xx": "Eichhof"
      }
    },
    {
      "geometry": {
        "type": "Point",
        "coordinates": [
          8.5,
          48.2
        ]
      },
      "type": "Feature",
      "properties": {
        "hierarchy": [
          "tgn:7198798",
          "tgn:7003692",
          "tgn:1000003",
          "tgn:7000084",
          "tgn:7029392"
        ],
        "placetype": [
          "aat:300000206"
        ],
        "id": 7198798,
        "name:xx": "Eichhof"
      }
    },
    {
      "geometry": {
        "type": "Point",
        "coordinates": [
          8.533333,
          47.783333
        ]
      },
      "type": "Feature",
      "properties": {
        "hierarchy": [
          "tgn:7198799",
          "tgn:7003692",
          "tgn:1000003",
          "tgn:7000084",
          "tgn:7029392"
        ],
        "placetype": [
          "aat:300000206"
        ],
        "id": 7198799,
        "name:xx": "Eichhof"
      }
    }
  ]
}
