{
  "geometry": {
    "type": "Point",
    "coordinates": [
      -85.3167,
      41.3333
    ]
  },
  "type": "Feature",
  "properties": {
    "hierarchy": [
      "tgn:2720362",
      "tgn:1000001",
      "tgn:7012149",
      "tgn:1002723",
      "tgn:7007252",
      "tgn:7029392"
    ],
    "placetype": [
      "aat:300006075"
    ],
    "id": 2720362,
    "name:xx": "Thumma Ditch"
  }
}
