{
  "geometry": {
    "type": "Point",
    "coordinates": [
      -114.7833,
      47.3167
    ]
  },
  "type": "Feature",
  "properties": {
    "hierarchy": [
      "tgn:2604067",
      "tgn:1000001",
      "tgn:7012149",
      "tgn:2001304",
      "tgn:7007524",
      "tgn:7029392"
    ],
    "placetype": [
      "aat:300008697"
    ],
    "id": 2604067,
    "name:xx": "Quinns Hot Springs"
  }
}
