{
  "geometry": {
    "type": "Point",
    "coordinates": [
      11.2833,
      2.3833
    ]
  },
  "type": "Feature",
  "properties": {
    "hierarchy": [
      "tgn:1088147",
      "tgn:1001189",
      "tgn:7001242",
      "tgn:1000153",
      "tgn:7029392"
    ],
    "placetype": [
      "aat:300008347"
    ],
    "id": 1088147,
    "name:xx": "Ambam"
  }
}
