{
  "geometry": {
    "type": "Point",
    "coordinates": [
      48.4667,
      32.3833
    ]
  },
  "type": "Feature",
  "properties": {
    "hierarchy": [
      "tgn:1079062",
      "tgn:1000004",
      "tgn:7002147",
      "tgn:7000231",
      "tgn:7029392"
    ],
    "placetype": [
      "aat:300008347"
    ],
    "id": 1079062,
    "name:xx": "Dezfūl"
  }
}
