{
  "geometry": {
    "type": "Point",
    "coordinates": [
      42.3667,
      42.1667
    ]
  },
  "type": "Feature",
  "properties": {
    "hierarchy": [
      "tgn:1059166",
      "tgn:1000004",
      "tgn:7012215",
      "tgn:7006653",
      "tgn:7029392"
    ],
    "placetype": [
      "aat:300008347"
    ],
    "id": 1059166,
    "name:xx": "Samtredia"
  }
}
