{
  "type": "FeatureCollection",
  "features": [
    {
      "geometry": {
        "type": "Point",
        "coordinates": [
          8.333333,
          50.65
        ]
      },
      "type": "Feature",
      "properties": {
        "hierarchy": [
          "tgn:7097571",
          "tgn:1000003",
          "tgn:7003678",
          "tgn:7000084",
          "tgn:7029392"
        ],
        "placetype": [
          "aat:300008347"
        ],
        "id": 7097571,
        "name:xx": "Sinn"
      }
    },
    {
      "geometry": {
        "type": "Point",
        "coordinates": [
          8.5,
          48.15
        ]
      },
      "type": "Feature",
      "properties": {
        "hierarchy": [
          "tgn:7097572",
          "tgn:7003692",
          "tgn:1000003",
          "tgn:7000084",
          "tgn:7029392"
        ],
        "placetype": [
          "aat:300008347"
        ],
        "id": 7097572,
        "name:xx": "Sinkingen"
      }
    },
    {
      "geometry": {
        "type": "Point",
        "coordinates": [
          13.65,
          50.766667
        ]
      },
      "type": "Feature",
      "properties": {
        "hierarchy": [
          "tgn:7097573",
          "tgn:1000003",
          "tgn:7003685",
          "tgn:7000084",
          "tgn:7029392"
        ],
        "placetype": [
          "aat:300008347"
        ],
        "id": 7097573,
        "name:xx": "Seyde"
      }
    },
    {
      "geometry": {
        "type": "Point",
        "coordinates": [
          11.183333,
          53.1
        ]
      },
      "type": "Feature",
      "properties": {
        "hierarchy": [
          "tgn:7097575",
          "tgn:1000003",
          "tgn:7003676",
          "tgn:7000084",
          "tgn:7029392"
        ],
        "placetype": [
          "aat:300004792"
        ],
        "id": 7097575,
        "name:xx": "Försterei Seybruch"
      }
    },
    {
      "geometry": {
        "type": "Point",
        "coordinates": [
          11.166667,
          53.1
        ]
      },
      "type": "Feature",
      "properties": {
        "hierarchy": [
          "tgn:7097576",
          "tgn:1000003",
          "tgn:7003676",
          "tgn:7000084",
          "tgn:7029392"
        ],
        "placetype": [
          "aat:300008863"
        ],
        "id": 7097576,
        "name:xx": "Seybruch"
      }
    },
    {
      "geometry": {
        "type": "Point",
        "coordinates": [
          12.35,
          48.483333
        ]
      },
      "type": "Feature",
      "properties": {
        "hierarchy": [
          "tgn:7097578",
          "tgn:7003669",
          "tgn:1000003",
          "tgn:7000084",
          "tgn:7029392"
        ],
        "placetype": [
          "aat:300008347"
        ],
        "id": 7097578,
        "name:xx": "Seyboldsdorf"
      }
    },
    {
      "geometry": {
        "type": "Point",
        "coordinates": [
          13.15,
          48.566667
        ]
      },
      "type": "Feature",
      "properties": {
        "hierarchy": [
          "tgn:7097579",
          "tgn:7003669",
          "tgn:1000003",
          "tgn:7000084",
          "tgn:7029392"
        ],
        "placetype": [
          "aat:300000206"
        ],
        "id": 7097579,
        "name:xx": "Sextlgrub"
      }
    }
  ]
}
