{
  "geometry": {
    "type": "Point",
    "coordinates": [
      121.7891,
      25.1294
    ]
  },
  "type": "Feature",
  "properties": {
    "hierarchy": [
      "tgn:7469258",
      "tgn:1000957",
      "tgn:1000004",
      "tgn:1000141",
      "tgn:7029392"
    ],
    "placetype": [
      "aat:300387173"
    ],
    "id": 7469258,
    "name:xx": "Xiaogang Li"
  }
}
