{
  "geometry": {
    "type": "Point",
    "coordinates": [
      -8.3333,
      52.4167
    ]
  },
  "type": "Feature",
  "properties": {
    "hierarchy": [
      "tgn:7001201",
      "tgn:1000003",
      "tgn:1000078",
      "tgn:7029392"
    ],
    "placetype": [
      "aat:300000774"
    ],
    "name:en": "Munster",
    "id": 7001201
  }
}
