{
  "geometry": {
    "type": "Point",
    "coordinates": [
      -92.3833,
      33.6333
    ]
  },
  "type": "Feature",
  "properties": {
    "hierarchy": [
      "tgn:2407886",
      "tgn:1000001",
      "tgn:7016172",
      "tgn:2000111",
      "tgn:7012149",
      "tgn:7029392"
    ],
    "placetype": [
      "aat:300008706"
    ],
    "id": 2407886,
    "name:xx": "Hurricane Creek"
  }
}
