{
  "type": "FeatureCollection",
  "features": [
    {
      "geometry": {
        "type": "Point",
        "coordinates": [
          5.6,
          52.966667
        ]
      },
      "type": "Feature",
      "properties": {
        "hierarchy": [
          "tgn:7266030",
          "tgn:7003616",
          "tgn:1000003",
          "tgn:7016845",
          "tgn:7029392"
        ],
        "placetype": [
          "aat:300006075"
        ],
        "name:nl": "Heegervar",
        "id": 7266030
      }
    },
    {
      "geometry": {
        "type": "Point",
        "coordinates": [
          5.6,
          52.95
        ]
      },
      "type": "Feature",
      "properties": {
        "hierarchy": [
          "tgn:7266031",
          "tgn:7003616",
          "tgn:1000003",
          "tgn:7016845",
          "tgn:7029392"
        ],
        "placetype": [
          "aat:300132316"
        ],
        "name:nl": "Heegermeer",
        "id": 7266031
      }
    },
    {
      "geometry": {
        "type": "Point",
        "coordinates": [
          5.6,
          52.966667
        ]
      },
      "type": "Feature",
      "properties": {
        "hierarchy": [
          "tgn:7266032",
          "tgn:7003616",
          "tgn:1000003",
          "tgn:7016845",
          "tgn:7029392"
        ],
        "placetype": [
          "aat:300008347"
        ],
        "name:nl": "Heeg",
        "id": 7266032
      }
    },
    {
      "geometry": {
        "type": "Point",
        "coordinates": [
          5.816667,
          53.2
        ]
      },
      "type": "Feature",
      "properties": {
        "hierarchy": [
          "tgn:7266033",
          "tgn:7003616",
          "tgn:1000003",
          "tgn:7016845",
          "tgn:7029392"
        ],
        "placetype": [
          "aat:300000745"
        ],
        "name:nl": "Heechterp",
        "id": 7266033
      }
    },
    {
      "geometry": {
        "type": "Point",
        "coordinates": [
          5.25,
          53.383333
        ]
      },
      "type": "Feature",
      "properties": {
        "hierarchy": [
          "tgn:7266034",
          "tgn:7003616",
          "tgn:1000003",
          "tgn:7016845",
          "tgn:7029392"
        ],
        "placetype": [
          "aat:300008347"
        ],
        "name:nl": "Hee",
        "id": 7266034
      }
    },
    {
      "geometry": {
        "type": "Point",
        "coordinates": [
          4.216667,
          51.35
        ]
      },
      "type": "Feature",
      "properties": {
        "hierarchy": [
          "tgn:7266035",
          "tgn:1000003",
          "tgn:7003635",
          "tgn:7016845",
          "tgn:7029392"
        ],
        "placetype": [
          "aat:300006163"
        ],
        "name:nl": "Hedwigepolder",
        "id": 7266035
      }
    },
    {
      "geometry": {
        "type": "Point",
        "coordinates": [
          5.2,
          51.733333
        ]
      },
      "type": "Feature",
      "properties": {
        "hierarchy": [
          "tgn:7266036",
          "tgn:1000003",
          "tgn:7003624",
          "tgn:7016845",
          "tgn:7029392"
        ],
        "placetype": [
          "aat:300008699"
        ],
        "name:nl": "Hedikhuizensche Maas",
        "id": 7266036
      }
    },
    {
      "geometry": {
        "type": "Point",
        "coordinates": [
          5.183333,
          51.733333
        ]
      },
      "type": "Feature",
      "properties": {
        "hierarchy": [
          "tgn:7266037",
          "tgn:1000003",
          "tgn:7003624",
          "tgn:7016845",
          "tgn:7029392"
        ],
        "placetype": [
          "aat:300008347"
        ],
        "name:nl": "Hedikhuizen",
        "id": 7266037
      }
    }
  ]
}
