{
  "geometry": {
    "type": "Point",
    "coordinates": [
      -89.05,
      45.25
    ]
  },
  "type": "Feature",
  "properties": {
    "hierarchy": [
      "tgn:2002333",
      "tgn:1000001",
      "tgn:7012149",
      "tgn:7007922",
      "tgn:7029392"
    ],
    "placetype": [
      "aat:300387145",
      "aat:300000771"
    ],
    "id": 2002333,
    "name:xx": "Langlade"
  }
}
