{
  "type": "FeatureCollection",
  "features": [
    {
      "geometry": {
        "type": "Point",
        "coordinates": [
          -86.5167,
          34.7333
        ]
      },
      "type": "Feature",
      "properties": {
        "hierarchy": [
          "tgn:2248340",
          "tgn:7002659",
          "tgn:1000001",
          "tgn:7012149",
          "tgn:2000044",
          "tgn:7029392"
        ],
        "placetype": [
          "aat:300008697"
        ],
        "id": 2248340,
        "name:xx": "Cold Spring"
      }
    },
    {
      "geometry": {
        "type": "Point",
        "coordinates": [
          -86.8,
          33.9167
        ]
      },
      "type": "Feature",
      "properties": {
        "hierarchy": [
          "tgn:2248341",
          "tgn:7002659",
          "tgn:1000001",
          "tgn:2000004",
          "tgn:7012149",
          "tgn:7029392"
        ],
        "placetype": [
          "aat:300008697"
        ],
        "id": 2248341,
        "name:xx": "Cold Spring"
      }
    },
    {
      "geometry": {
        "type": "Point",
        "coordinates": [
          -110.4,
          32.15
        ]
      },
      "type": "Feature",
      "properties": {
        "hierarchy": [
          "tgn:2248342",
          "tgn:1000001",
          "tgn:7006451",
          "tgn:2000091",
          "tgn:7012149",
          "tgn:7029392"
        ],
        "placetype": [
          "aat:300008697"
        ],
        "id": 2248342,
        "name:xx": "Cold Spring"
      }
    },
    {
      "geometry": {
        "type": "Point",
        "coordinates": [
          -110.7667,
          32.4333
        ]
      },
      "type": "Feature",
      "properties": {
        "hierarchy": [
          "tgn:2248343",
          "tgn:1000001",
          "tgn:7006451",
          "tgn:7012149",
          "tgn:2000100",
          "tgn:7029392"
        ],
        "placetype": [
          "aat:300008697"
        ],
        "id": 2248343,
        "name:xx": "Cold Spring"
      }
    },
    {
      "geometry": {
        "type": "Point",
        "coordinates": [
          -110.45,
          33.5167
        ]
      },
      "type": "Feature",
      "properties": {
        "hierarchy": [
          "tgn:2248345",
          "tgn:1000001",
          "tgn:7006451",
          "tgn:2000093",
          "tgn:7012149",
          "tgn:7029392"
        ],
        "placetype": [
          "aat:300008697"
        ],
        "id": 2248345,
        "name:xx": "Cold Spring"
      }
    },
    {
      "geometry": {
        "type": "Point",
        "coordinates": [
          -109.7167,
          34.1167
        ]
      },
      "type": "Feature",
      "properties": {
        "hierarchy": [
          "tgn:2248346",
          "tgn:2000090",
          "tgn:1000001",
          "tgn:7006451",
          "tgn:7012149",
          "tgn:7029392"
        ],
        "placetype": [
          "aat:300008697"
        ],
        "id": 2248346,
        "name:xx": "Cold Spring"
      }
    },
    {
      "geometry": {
        "type": "Point",
        "coordinates": [
          -113.2333,
          34.6667
        ]
      },
      "type": "Feature",
      "properties": {
        "hierarchy": [
          "tgn:2248347",
          "tgn:1000001",
          "tgn:7006451",
          "tgn:7012149",
          "tgn:2000103",
          "tgn:7029392"
        ],
        "placetype": [
          "aat:300008697"
        ],
        "id": 2248347,
        "name:xx": "Cold Spring"
      }
    },
    {
      "geometry": {
        "type": "Point",
        "coordinates": [
          -113.25,
          36.35
        ]
      },
      "type": "Feature",
      "properties": {
        "hierarchy": [
          "tgn:2248348",
          "tgn:1000001",
          "tgn:7006451",
          "tgn:7012149",
          "tgn:2000098",
          "tgn:7029392"
        ],
        "placetype": [
          "aat:300008697"
        ],
        "id": 2248348,
        "name:xx": "Cold Spring"
      }
    },
    {
      "geometry": {
        "type": "Point",
        "coordinates": [
          -109.0833,
          33
        ]
      },
      "type": "Feature",
      "properties": {
        "hierarchy": [
          "tgn:2248349",
          "tgn:1000001",
          "tgn:7006451",
          "tgn:2000095",
          "tgn:7012149",
          "tgn:7029392"
        ],
        "placetype": [
          "aat:300008697"
        ],
        "id": 2248349,
        "name:xx": "Cold Spring"
      }
    }
  ]
}
