{
  "geometry": {
    "type": "Point",
    "coordinates": [
      -106.9333,
      44.6167
    ]
  },
  "type": "Feature",
  "properties": {
    "hierarchy": [
      "tgn:2374810",
      "tgn:1000001",
      "tgn:7012149",
      "tgn:2002381",
      "tgn:7007923",
      "tgn:7029392"
    ],
    "placetype": [
      "aat:300008699"
    ],
    "id": 2374810,
    "name:xx": "Hanes Fork"
  }
}
