{
  "geometry": {
    "type": "Point",
    "coordinates": [
      -107.4833,
      33.6167
    ]
  },
  "type": "Feature",
  "properties": {
    "hierarchy": [
      "tgn:2473920",
      "tgn:1000001",
      "tgn:7012149",
      "tgn:2001456",
      "tgn:7007566",
      "tgn:7029392"
    ],
    "placetype": [
      "aat:300006191"
    ],
    "id": 2473920,
    "name:xx": "Lower Holdup Tank"
  }
}
