{
  "geometry": {
    "type": "Point",
    "coordinates": [
      -99.6667,
      29.7833
    ]
  },
  "type": "Feature",
  "properties": {
    "hierarchy": [
      "tgn:2387566",
      "tgn:1000001",
      "tgn:7012149",
      "tgn:2002060",
      "tgn:7007826",
      "tgn:7029392"
    ],
    "placetype": [
      "aat:300008761"
    ],
    "id": 2387566,
    "name:xx": "Hi Saw Hollow"
  }
}
