{
  "geometry": {
    "type": "Point",
    "coordinates": [
      -108.2333,
      37.3167
    ]
  },
  "type": "Feature",
  "properties": {
    "hierarchy": [
      "tgn:2505726",
      "tgn:1000001",
      "tgn:7012149",
      "tgn:2000233",
      "tgn:7007158",
      "tgn:7029392"
    ],
    "placetype": [
      "aat:300008798"
    ],
    "id": 2505726,
    "name:xx": "Menefee Mountain"
  }
}
