{
  "geometry": {
    "type": "Point",
    "coordinates": [
      -78.3333,
      35.6333
    ]
  },
  "type": "Feature",
  "properties": {
    "hierarchy": [
      "tgn:2332775",
      "tgn:1000001",
      "tgn:7012149",
      "tgn:2001509",
      "tgn:7007709",
      "tgn:7029392"
    ],
    "placetype": [
      "aat:300006191"
    ],
    "id": 2332775,
    "name:xx": "Flowers Pond Number One"
  }
}
