{
  "geometry": {
    "type": "Point",
    "coordinates": [
      138.7167,
      35.7333
    ]
  },
  "type": "Feature",
  "properties": {
    "hierarchy": [
      "tgn:1079924",
      "tgn:7000895",
      "tgn:1000004",
      "tgn:7016854",
      "tgn:1000120",
      "tgn:7029392"
    ],
    "placetype": [
      "aat:300008347"
    ],
    "id": 1079924,
    "name:xx": "Enzan"
  }
}
