{
  "geometry": {
    "type": "Point",
    "coordinates": [
      79.210734,
      26.990434
    ]
  },
  "type": "Feature",
  "properties": {
    "hierarchy": [
      "tgn:7559865",
      "tgn:1000004",
      "tgn:7000198",
      "tgn:7016722",
      "tgn:7029392"
    ],
    "placetype": [
      "aat:300008347"
    ],
    "name:en": "Chaturīpur",
    "id": 7559865
  }
}
