{
  "geometry": {
    "type": "Point",
    "coordinates": [
      -0.9667,
      51.9833
    ]
  },
  "type": "Feature",
  "properties": {
    "hierarchy": [
      "tgn:7025019",
      "tgn:7002445",
      "tgn:7008104",
      "tgn:1000003",
      "tgn:7008591",
      "tgn:7029392"
    ],
    "placetype": [
      "aat:300008347"
    ],
    "id": 7025019,
    "name:xx": "Bourton"
  }
}
