{
  "geometry": {
    "type": "Point",
    "coordinates": [
      -119.5833,
      38.1667
    ]
  },
  "type": "Feature",
  "properties": {
    "hierarchy": [
      "tgn:2292788",
      "tgn:1000001",
      "tgn:7012149",
      "tgn:7007157",
      "tgn:1002957",
      "tgn:7029392"
    ],
    "placetype": [
      "aat:300008680"
    ],
    "id": 2292788,
    "name:xx": "Dorothy Lake"
  }
}
