{
  "geometry": {
    "type": "Point",
    "coordinates": [
      -109.05,
      33.4667
    ]
  },
  "type": "Feature",
  "properties": {
    "hierarchy": [
      "tgn:2585511",
      "tgn:1000001",
      "tgn:7006451",
      "tgn:2000095",
      "tgn:7012149",
      "tgn:7029392"
    ],
    "placetype": [
      "aat:300008798"
    ],
    "id": 2585511,
    "name:xx": "Pinyon Knob"
  }
}
