{
  "geometry": {
    "type": "Point",
    "coordinates": [
      -82.2333,
      33.1167
    ]
  },
  "type": "Feature",
  "properties": {
    "hierarchy": [
      "tgn:2626125",
      "tgn:1000001",
      "tgn:2000308",
      "tgn:7012149",
      "tgn:7007248",
      "tgn:7029392"
    ],
    "placetype": [
      "aat:300008706"
    ],
    "id": 2626125,
    "name:xx": "Rocky Creek"
  }
}
