{
  "geometry": {
    "type": "Point",
    "coordinates": [
      -103.3167,
      41.9333
    ]
  },
  "type": "Feature",
  "properties": {
    "hierarchy": [
      "tgn:2771441",
      "tgn:1000001",
      "tgn:7012149",
      "tgn:2001377",
      "tgn:7007525",
      "tgn:7029392"
    ],
    "placetype": [
      "aat:300008761"
    ],
    "id": 2771441,
    "name:xx": "Wildhorse Canyon"
  }
}
