{
  "geometry": {
    "type": "Point",
    "coordinates": [
      -115.3667,
      43.5333
    ]
  },
  "type": "Feature",
  "properties": {
    "hierarchy": [
      "tgn:2154832",
      "tgn:1000001",
      "tgn:7012149",
      "tgn:2000471",
      "tgn:7007250",
      "tgn:7029392"
    ],
    "placetype": [
      "aat:300008706"
    ],
    "id": 2154832,
    "name:xx": "Bear Hole Creek"
  }
}
