{
  "geometry": {
    "type": "Point",
    "coordinates": [
      -82.45,
      40.15
    ]
  },
  "type": "Feature",
  "properties": {
    "hierarchy": [
      "tgn:2078809",
      "tgn:1000001",
      "tgn:7012149",
      "tgn:1002596",
      "tgn:7007706",
      "tgn:7029392"
    ],
    "placetype": [
      "aat:300008347"
    ],
    "id": 2078809,
    "name:xx": "Chatham"
  }
}
