{
  "type": "FeatureCollection",
  "features": [
    {
      "geometry": {
        "type": "Point",
        "coordinates": [
          -109.283333,
          27.533333
        ]
      },
      "type": "Feature",
      "properties": {
        "hierarchy": [
          "tgn:7365671",
          "tgn:1000001",
          "tgn:1001960",
          "tgn:7005560",
          "tgn:7029392"
        ],
        "placetype": [
          "aat:300008347"
        ],
        "id": 7365671,
        "name:xx": "Enconada"
      }
    },
    {
      "geometry": {
        "type": "Point",
        "coordinates": [
          -98.666667,
          23.033333
        ]
      },
      "type": "Feature",
      "properties": {
        "hierarchy": [
          "tgn:7365672",
          "tgn:1000001",
          "tgn:7005597",
          "tgn:7005560",
          "tgn:7029392"
        ],
        "placetype": [
          "aat:300008347"
        ],
        "id": 7365672,
        "name:xx": "El Refugio"
      }
    },
    {
      "geometry": {
        "type": "Point",
        "coordinates": [
          -103.133333,
          22.916667
        ]
      },
      "type": "Feature",
      "properties": {
        "hierarchy": [
          "tgn:7365673",
          "tgn:1000001",
          "tgn:7005601",
          "tgn:7005560",
          "tgn:7029392"
        ],
        "placetype": [
          "aat:300008347"
        ],
        "id": 7365673,
        "name:xx": "El Refugio"
      }
    },
    {
      "geometry": {
        "type": "Point",
        "coordinates": [
          -103.05,
          22.6
        ]
      },
      "type": "Feature",
      "properties": {
        "hierarchy": [
          "tgn:7365674",
          "tgn:1000001",
          "tgn:7005601",
          "tgn:7005560",
          "tgn:7029392"
        ],
        "placetype": [
          "aat:300008347"
        ],
        "id": 7365674,
        "name:xx": "El Refugio"
      }
    },
    {
      "geometry": {
        "type": "Point",
        "coordinates": [
          -99.033333,
          22.583333
        ]
      },
      "type": "Feature",
      "properties": {
        "hierarchy": [
          "tgn:7365675",
          "tgn:1000001",
          "tgn:7005597",
          "tgn:7005560",
          "tgn:7029392"
        ],
        "placetype": [
          "aat:300008347"
        ],
        "id": 7365675,
        "name:xx": "El Refugio"
      }
    },
    {
      "geometry": {
        "type": "Point",
        "coordinates": [
          -102.266667,
          22.366667
        ]
      },
      "type": "Feature",
      "properties": {
        "hierarchy": [
          "tgn:7365676",
          "tgn:7005579",
          "tgn:1000001",
          "tgn:7005560",
          "tgn:7029392"
        ],
        "placetype": [
          "aat:300008347"
        ],
        "id": 7365676,
        "name:xx": "El Refugio"
      }
    },
    {
      "geometry": {
        "type": "Point",
        "coordinates": [
          -101.9,
          22.283333
        ]
      },
      "type": "Feature",
      "properties": {
        "hierarchy": [
          "tgn:7365677",
          "tgn:1000001",
          "tgn:7005601",
          "tgn:7005560",
          "tgn:7029392"
        ],
        "placetype": [
          "aat:300008347"
        ],
        "id": 7365677,
        "name:xx": "El Refugio"
      }
    },
    {
      "geometry": {
        "type": "Point",
        "coordinates": [
          -102.216667,
          22.166667
        ]
      },
      "type": "Feature",
      "properties": {
        "hierarchy": [
          "tgn:7365678",
          "tgn:7005579",
          "tgn:1000001",
          "tgn:7005560",
          "tgn:7029392"
        ],
        "placetype": [
          "aat:300008347"
        ],
        "id": 7365678,
        "name:xx": "El Refugio"
      }
    },
    {
      "geometry": {
        "type": "Point",
        "coordinates": [
          -101.516667,
          22
        ]
      },
      "type": "Feature",
      "properties": {
        "hierarchy": [
          "tgn:7365679",
          "tgn:1000001",
          "tgn:7005601",
          "tgn:7005560",
          "tgn:7029392"
        ],
        "placetype": [
          "aat:300008347"
        ],
        "id": 7365679,
        "name:xx": "El Refugio"
      }
    }
  ]
}
