{
  "geometry": {
    "type": "Point",
    "coordinates": [
      -128.316,
      -24.366
    ]
  },
  "type": "Feature",
  "properties": {
    "hierarchy": [
      "tgn:1007379",
      "tgn:7005269",
      "tgn:1000006",
      "tgn:7029392"
    ],
    "placetype": [
      "aat:300008791"
    ],
    "id": 1007379,
    "name:xx": "Henderson Island"
  }
}
