{
  "geometry": {
    "type": "Point",
    "coordinates": [
      40.7667,
      63.85
    ]
  },
  "type": "Feature",
  "properties": {
    "hierarchy": [
      "tgn:1053363",
      "tgn:4000818",
      "tgn:1000004",
      "tgn:7018214",
      "tgn:7002435",
      "tgn:7029392"
    ],
    "placetype": [
      "aat:300008347"
    ],
    "id": 1053363,
    "name:xx": "Kholmogorskaya"
  }
}
