{
  "geometry": {
    "type": "Point",
    "coordinates": [
      30.5833,
      -29.0667
    ]
  },
  "type": "Feature",
  "properties": {
    "hierarchy": [
      "tgn:7000805",
      "tgn:7001242",
      "tgn:7016749",
      "tgn:1000193",
      "tgn:7029392"
    ],
    "placetype": [
      "aat:300008347",
      "aat:300008389"
    ],
    "id": 7000805,
    "name:xx": "Greytown"
  }
}
