{
  "type": "FeatureCollection",
  "features": [
    {
      "geometry": {
        "type": "Point",
        "coordinates": [
          -87.9,
          35.8
        ]
      },
      "type": "Feature",
      "properties": {
        "hierarchy": [
          "tgn:2268150",
          "tgn:1000001",
          "tgn:7012149",
          "tgn:2001904",
          "tgn:7007825",
          "tgn:7029392"
        ],
        "placetype": [
          "aat:300008347"
        ],
        "id": 2268150,
        "name:xx": "Crooked Creek"
      }
    },
    {
      "geometry": {
        "type": "Point",
        "coordinates": [
          -96.6833,
          29.5333
        ]
      },
      "type": "Feature",
      "properties": {
        "hierarchy": [
          "tgn:2268151",
          "tgn:1000001",
          "tgn:7012149",
          "tgn:1002291",
          "tgn:7007826",
          "tgn:7029392"
        ],
        "placetype": [
          "aat:300008706"
        ],
        "id": 2268151,
        "name:xx": "Crooked Creek"
      }
    },
    {
      "geometry": {
        "type": "Point",
        "coordinates": [
          -99.4333,
          31.65
        ]
      },
      "type": "Feature",
      "properties": {
        "hierarchy": [
          "tgn:2268152",
          "tgn:1000001",
          "tgn:7012149",
          "tgn:2001959",
          "tgn:7007826",
          "tgn:7029392"
        ],
        "placetype": [
          "aat:300008706"
        ],
        "id": 2268152,
        "name:xx": "Crooked Creek"
      }
    },
    {
      "geometry": {
        "type": "Point",
        "coordinates": [
          -101.3167,
          32.8333
        ]
      },
      "type": "Feature",
      "properties": {
        "hierarchy": [
          "tgn:2268153",
          "tgn:1000001",
          "tgn:2001943",
          "tgn:7012149",
          "tgn:7007826",
          "tgn:7029392"
        ],
        "placetype": [
          "aat:300008706"
        ],
        "id": 2268153,
        "name:xx": "Crooked Creek"
      }
    },
    {
      "geometry": {
        "type": "Point",
        "coordinates": [
          -95.2667,
          32.9
        ]
      },
      "type": "Feature",
      "properties": {
        "hierarchy": [
          "tgn:2268154",
          "tgn:1000001",
          "tgn:7012149",
          "tgn:1003034",
          "tgn:7007826",
          "tgn:7029392"
        ],
        "placetype": [
          "aat:300008706"
        ],
        "id": 2268154,
        "name:xx": "Crooked Creek"
      }
    },
    {
      "geometry": {
        "type": "Point",
        "coordinates": [
          -96.7333,
          29.5
        ]
      },
      "type": "Feature",
      "properties": {
        "hierarchy": [
          "tgn:2268155",
          "tgn:1000001",
          "tgn:7012149",
          "tgn:1002578",
          "tgn:7007826",
          "tgn:7029392"
        ],
        "placetype": [
          "aat:300008706"
        ],
        "id": 2268155,
        "name:xx": "Crooked Creek"
      }
    },
    {
      "geometry": {
        "type": "Point",
        "coordinates": [
          -99.5167,
          32.1167
        ]
      },
      "type": "Feature",
      "properties": {
        "hierarchy": [
          "tgn:2268156",
          "tgn:1000001",
          "tgn:7012149",
          "tgn:2001951",
          "tgn:7007826",
          "tgn:7029392"
        ],
        "placetype": [
          "aat:300008706"
        ],
        "id": 2268156,
        "name:xx": "Crooked Creek"
      }
    },
    {
      "geometry": {
        "type": "Point",
        "coordinates": [
          -95.9,
          32.6167
        ]
      },
      "type": "Feature",
      "properties": {
        "hierarchy": [
          "tgn:2268157",
          "tgn:1000001",
          "tgn:7012149",
          "tgn:1002969",
          "tgn:7007826",
          "tgn:7029392"
        ],
        "placetype": [
          "aat:300008706"
        ],
        "id": 2268157,
        "name:xx": "Crooked Creek"
      }
    },
    {
      "geometry": {
        "type": "Point",
        "coordinates": [
          -94.9167,
          30.6833
        ]
      },
      "type": "Feature",
      "properties": {
        "hierarchy": [
          "tgn:2268158",
          "tgn:1000001",
          "tgn:7012149",
          "tgn:1002795",
          "tgn:7007826",
          "tgn:7029392"
        ],
        "placetype": [
          "aat:300008706"
        ],
        "id": 2268158,
        "name:xx": "Crooked Creek"
      }
    },
    {
      "geometry": {
        "type": "Point",
        "coordinates": [
          -94.0167,
          31.55
        ]
      },
      "type": "Feature",
      "properties": {
        "hierarchy": [
          "tgn:2268159",
          "tgn:1000001",
          "tgn:7012149",
          "tgn:2002067",
          "tgn:7007826",
          "tgn:7029392"
        ],
        "placetype": [
          "aat:300008706"
        ],
        "id": 2268159,
        "name:xx": "Crooked Creek"
      }
    }
  ]
}
