{
  "geometry": {
    "type": "Point",
    "coordinates": [
      -125.75,
      54.2333
    ]
  },
  "type": "Feature",
  "properties": {
    "hierarchy": [
      "tgn:1013413",
      "tgn:7005735",
      "tgn:7005685",
      "tgn:1000001",
      "tgn:7029392"
    ],
    "placetype": [
      "aat:300008347"
    ],
    "id": 1013413,
    "name:xx": "Burns Lake"
  }
}
