{
  "geometry": {
    "type": "Point",
    "coordinates": [
      -84.4667,
      34.7833
    ]
  },
  "type": "Feature",
  "properties": {
    "hierarchy": [
      "tgn:2235708",
      "tgn:1000001",
      "tgn:7012149",
      "tgn:2000352",
      "tgn:7007248",
      "tgn:7029392"
    ],
    "placetype": [
      "aat:300008798"
    ],
    "id": 2235708,
    "name:xx": "Chestnut Mountain"
  }
}
