{
  "geometry": {
    "type": "Point",
    "coordinates": [
      -71.8667,
      42.5833
    ]
  },
  "type": "Feature",
  "properties": {
    "hierarchy": [
      "tgn:2262946",
      "tgn:1000001",
      "tgn:7012149",
      "tgn:1003038",
      "tgn:7007517",
      "tgn:7029392"
    ],
    "placetype": [
      "aat:300008798"
    ],
    "id": 2262946,
    "name:xx": "Cowees Hill"
  }
}
