{
  "geometry": {
    "type": "Point",
    "coordinates": [
      -95.4833,
      32.55
    ]
  },
  "type": "Feature",
  "properties": {
    "hierarchy": [
      "tgn:2372542",
      "tgn:1000001",
      "tgn:7012149",
      "tgn:1002898",
      "tgn:7007826",
      "tgn:7029392"
    ],
    "placetype": [
      "aat:300008699"
    ],
    "id": 2372542,
    "name:xx": "Hall Branch"
  }
}
