{
  "geometry": {
    "type": "Point",
    "coordinates": [
      -149.4667,
      61.3333
    ]
  },
  "type": "Feature",
  "properties": {
    "hierarchy": [
      "tgn:2222219",
      "tgn:2124017",
      "tgn:7006450",
      "tgn:1000001",
      "tgn:7012149",
      "tgn:7029392"
    ],
    "placetype": [
      "aat:300008706"
    ],
    "id": 2222219,
    "name:xx": "Carol Creek"
  }
}
