{
  "geometry": {
    "type": "Point",
    "coordinates": [
      -6.6667,
      5.9167
    ]
  },
  "type": "Feature",
  "properties": {
    "hierarchy": [
      "tgn:1000768",
      "tgn:7001242",
      "tgn:1000168",
      "tgn:7029392"
    ],
    "placetype": [
      "aat:300387064",
      "aat:300000772"
    ],
    "id": 1000768,
    "name:xx": "Soubré, Département de"
  }
}
