{
  "geometry": {
    "type": "Point",
    "coordinates": [
      -92.0167,
      44.3333
    ]
  },
  "type": "Feature",
  "properties": {
    "hierarchy": [
      "tgn:2364866",
      "tgn:1000001",
      "tgn:7012149",
      "tgn:2001077",
      "tgn:7007521",
      "tgn:7029392"
    ],
    "placetype": [
      "aat:300008798"
    ],
    "id": 2364866,
    "name:xx": "Greenfield Hill"
  }
}
