{
  "geometry": {
    "type": "Point",
    "coordinates": [
      -85.4833,
      35.0167
    ]
  },
  "type": "Feature",
  "properties": {
    "hierarchy": [
      "tgn:2512956",
      "tgn:1000001",
      "tgn:7012149",
      "tgn:2001894",
      "tgn:7007825",
      "tgn:7029392"
    ],
    "placetype": [
      "aat:300008706"
    ],
    "id": 2512956,
    "name:xx": "Mill Creek"
  }
}
