{
  "type": "FeatureCollection",
  "features": [
    {
      "geometry": {
        "type": "Point",
        "coordinates": [
          -70.116667,
          -32.866667
        ]
      },
      "type": "Feature",
      "properties": {
        "hierarchy": [
          "tgn:7287680",
          "tgn:1001768",
          "tgn:1000049",
          "tgn:1000002",
          "tgn:7029392"
        ],
        "placetype": [
          "aat:300008699"
        ],
        "id": 7287680,
        "name:xx": "Juncal, Río"
      }
    },
    {
      "geometry": {
        "type": "Point",
        "coordinates": [
          -69.866667,
          -25.933333
        ]
      },
      "type": "Feature",
      "properties": {
        "hierarchy": [
          "tgn:7287681",
          "tgn:1001630",
          "tgn:1000049",
          "tgn:1000002",
          "tgn:7029392"
        ],
        "placetype": [
          "aat:300266554",
          "aat:300008699"
        ],
        "id": 7287681,
        "name:xx": "Juncal, Quebrada"
      }
    },
    {
      "geometry": {
        "type": "Point",
        "coordinates": [
          -69.533333,
          -25.733333
        ]
      },
      "type": "Feature",
      "properties": {
        "hierarchy": [
          "tgn:7287682",
          "tgn:1001630",
          "tgn:1000049",
          "tgn:1000002",
          "tgn:7029392"
        ],
        "placetype": [
          "aat:300008805"
        ],
        "id": 7287682,
        "name:xx": "Juncal, Pampa"
      }
    },
    {
      "geometry": {
        "type": "Point",
        "coordinates": [
          -72.7,
          -47.366667
        ]
      },
      "type": "Feature",
      "properties": {
        "hierarchy": [
          "tgn:7287683",
          "tgn:1001623",
          "tgn:1000049",
          "tgn:1000002",
          "tgn:7029392"
        ],
        "placetype": [
          "aat:300008680"
        ],
        "id": 7287683,
        "name:xx": "Juncal, Laguna"
      }
    },
    {
      "geometry": {
        "type": "Point",
        "coordinates": [
          -70.166667,
          -32.933333
        ]
      },
      "type": "Feature",
      "properties": {
        "hierarchy": [
          "tgn:7287684",
          "tgn:1001768",
          "tgn:1000049",
          "tgn:1000002",
          "tgn:7029392"
        ],
        "placetype": [
          "aat:300008795"
        ],
        "id": 7287684,
        "name:xx": "Juncal, Cerros de"
      }
    },
    {
      "geometry": {
        "type": "Point",
        "coordinates": [
          -70.083333,
          -33.1
        ]
      },
      "type": "Feature",
      "properties": {
        "hierarchy": [
          "tgn:7287685",
          "tgn:1001768",
          "tgn:1000049",
          "tgn:1000002",
          "tgn:7029392"
        ],
        "placetype": [
          "aat:300008795"
        ],
        "id": 7287685,
        "name:xx": "Juncal, Cerro"
      }
    },
    {
      "geometry": {
        "type": "Point",
        "coordinates": [
          -70.183333,
          -32.9
        ]
      },
      "type": "Feature",
      "properties": {
        "hierarchy": [
          "tgn:7287686",
          "tgn:1001768",
          "tgn:1000049",
          "tgn:1000002",
          "tgn:7029392"
        ],
        "placetype": [
          "aat:300008795"
        ],
        "id": 7287686,
        "name:xx": "Juncal, Cerro"
      }
    },
    {
      "geometry": {
        "type": "Point",
        "coordinates": [
          -69.416667,
          -25.633333
        ]
      },
      "type": "Feature",
      "properties": {
        "hierarchy": [
          "tgn:7287687",
          "tgn:1001630",
          "tgn:1000049",
          "tgn:1000002",
          "tgn:7029392"
        ],
        "placetype": [
          "aat:300008795"
        ],
        "id": 7287687,
        "name:xx": "Juncal, Cerro"
      }
    },
    {
      "geometry": {
        "type": "Point",
        "coordinates": [
          -70.183333,
          -32.9
        ]
      },
      "type": "Feature",
      "properties": {
        "hierarchy": [
          "tgn:7287688",
          "tgn:1001768",
          "tgn:1000049",
          "tgn:1000002",
          "tgn:7029392"
        ],
        "placetype": [
          "aat:300008795"
        ],
        "id": 7287688,
        "name:xx": "Juncal, Alto de"
      }
    },
    {
      "geometry": {
        "type": "Point",
        "coordinates": [
          -72.033333,
          -47.1
        ]
      },
      "type": "Feature",
      "properties": {
        "hierarchy": [
          "tgn:7287689",
          "tgn:1001623",
          "tgn:1000049",
          "tgn:1000002",
          "tgn:7029392"
        ],
        "placetype": [
          "aat:300008795"
        ],
        "id": 7287689,
        "name:xx": "Julio Vicuña, Cerro"
      }
    }
  ]
}
