{
  "geometry": {
    "type": "Point",
    "coordinates": [
      -116.7833,
      39.0333
    ]
  },
  "type": "Feature",
  "properties": {
    "hierarchy": [
      "tgn:2265361",
      "tgn:1000001",
      "tgn:2001418",
      "tgn:7012149",
      "tgn:7007526",
      "tgn:7029392"
    ],
    "placetype": [
      "aat:300008706"
    ],
    "id": 2265361,
    "name:xx": "Crane Creek"
  }
}
