{
  "geometry": {
    "type": "Point",
    "coordinates": [
      -92.35,
      44.4667
    ]
  },
  "type": "Feature",
  "properties": {
    "hierarchy": [
      "tgn:2554108",
      "tgn:1000001",
      "tgn:2001023",
      "tgn:7012149",
      "tgn:7007521",
      "tgn:7029392"
    ],
    "placetype": [
      "aat:300266640"
    ],
    "id": 2554108,
    "name:xx": "Oak Ridge"
  }
}
