{
  "geometry": {
    "type": "Point",
    "coordinates": [
      -99.8667,
      29.2667
    ]
  },
  "type": "Feature",
  "properties": {
    "hierarchy": [
      "tgn:2653402",
      "tgn:1000001",
      "tgn:7012149",
      "tgn:2002087",
      "tgn:7007826",
      "tgn:7029392"
    ],
    "placetype": [
      "aat:300008798"
    ],
    "id": 2653402,
    "name:xx": "Sevenmile Hill"
  }
}
