{
  "type": "FeatureCollection",
  "features": [
    {
      "geometry": {
        "type": "Point",
        "coordinates": [
          -109.3833,
          33.1
        ]
      },
      "type": "Feature",
      "properties": {
        "hierarchy": [
          "tgn:2257470",
          "tgn:1000001",
          "tgn:7006451",
          "tgn:2000095",
          "tgn:7012149",
          "tgn:7029392"
        ],
        "placetype": [
          "aat:300008761"
        ],
        "id": 2257470,
        "name:xx": "Coronado Gulch"
      }
    },
    {
      "geometry": {
        "type": "Point",
        "coordinates": [
          -81.5333,
          40.8333
        ]
      },
      "type": "Feature",
      "properties": {
        "hierarchy": [
          "tgn:2257471",
          "tgn:1000001",
          "tgn:7012149",
          "tgn:1002917",
          "tgn:7007706",
          "tgn:7029392"
        ],
        "placetype": [
          "aat:300006191"
        ],
        "id": 2257471,
        "name:xx": "Coronado Lake"
      }
    },
    {
      "geometry": {
        "type": "Point",
        "coordinates": [
          -111.3333,
          33.55
        ]
      },
      "type": "Feature",
      "properties": {
        "hierarchy": [
          "tgn:2257472",
          "tgn:1000001",
          "tgn:7006451",
          "tgn:7012149",
          "tgn:2000097",
          "tgn:7029392"
        ],
        "placetype": [
          "aat:300008798"
        ],
        "id": 2257472,
        "name:xx": "Coronado Mesa"
      }
    },
    {
      "geometry": {
        "type": "Point",
        "coordinates": [
          -109.4,
          33.1
        ]
      },
      "type": "Feature",
      "properties": {
        "hierarchy": [
          "tgn:2257473",
          "tgn:1000001",
          "tgn:7006451",
          "tgn:2000095",
          "tgn:7012149",
          "tgn:7029392"
        ],
        "placetype": [
          "aat:300000390"
        ],
        "id": 2257473,
        "name:xx": "Coronado Mine"
      }
    },
    {
      "geometry": {
        "type": "Point",
        "coordinates": [
          -122.0667,
          40.7333
        ]
      },
      "type": "Feature",
      "properties": {
        "hierarchy": [
          "tgn:2257474",
          "tgn:1000001",
          "tgn:7012149",
          "tgn:7007157",
          "tgn:2000188",
          "tgn:7029392"
        ],
        "placetype": [
          "aat:300000390"
        ],
        "id": 2257474,
        "name:xx": "Coronado Mine"
      }
    },
    {
      "geometry": {
        "type": "Point",
        "coordinates": [
          -111.7667,
          33.4
        ]
      },
      "type": "Feature",
      "properties": {
        "hierarchy": [
          "tgn:2257475",
          "tgn:1000001",
          "tgn:7006451",
          "tgn:7012149",
          "tgn:2000097",
          "tgn:7029392"
        ],
        "placetype": [
          "aat:300008347"
        ],
        "id": 2257475,
        "name:xx": "Coronado Mobile Home Park"
      }
    },
    {
      "geometry": {
        "type": "Point",
        "coordinates": [
          -109.4,
          33.1167
        ]
      },
      "type": "Feature",
      "properties": {
        "hierarchy": [
          "tgn:2257476",
          "tgn:1000001",
          "tgn:7006451",
          "tgn:2000095",
          "tgn:7012149",
          "tgn:7029392"
        ],
        "placetype": [
          "aat:300008798"
        ],
        "id": 2257476,
        "name:xx": "Coronado Mountain"
      }
    },
    {
      "geometry": {
        "type": "Point",
        "coordinates": [
          -110.6667,
          32.5
        ]
      },
      "type": "Feature",
      "properties": {
        "hierarchy": [
          "tgn:2257478",
          "tgn:1000001",
          "tgn:7012149",
          "tgn:7029392"
        ],
        "placetype": [
          "aat:300008863"
        ],
        "id": 2257478,
        "name:xx": "Coronado National Forest"
      }
    },
    {
      "geometry": {
        "type": "Point",
        "coordinates": [
          -110.2833,
          31.3333
        ]
      },
      "type": "Feature",
      "properties": {
        "hierarchy": [
          "tgn:2257479",
          "tgn:1000001",
          "tgn:7006451",
          "tgn:2000091",
          "tgn:7012149",
          "tgn:7029392"
        ],
        "placetype": [
          "aat:300008798"
        ],
        "id": 2257479,
        "name:xx": "Coronado Peak"
      }
    }
  ]
}
