{
  "geometry": {
    "type": "Point",
    "coordinates": [
      130.65,
      31.75
    ]
  },
  "type": "Feature",
  "properties": {
    "hierarchy": [
      "tgn:1080361",
      "tgn:1000993",
      "tgn:1000004",
      "tgn:7000901",
      "tgn:1000120",
      "tgn:7029392"
    ],
    "placetype": [
      "aat:300008347"
    ],
    "id": 1080361,
    "name:xx": "Kajiki"
  }
}
