{
  "geometry": {
    "type": "Point",
    "coordinates": [
      -77.8333,
      36.8167
    ]
  },
  "type": "Feature",
  "properties": {
    "hierarchy": [
      "tgn:2709878",
      "tgn:1000001",
      "tgn:2002147",
      "tgn:7012149",
      "tgn:7007919",
      "tgn:7029392"
    ],
    "placetype": [
      "aat:300008699"
    ],
    "id": 2709878,
    "name:xx": "Tain Branch"
  }
}
