{
  "geometry": {
    "type": "Point",
    "coordinates": [
      -87.1333,
      40.45
    ]
  },
  "type": "Feature",
  "properties": {
    "hierarchy": [
      "tgn:2394972",
      "tgn:1000001",
      "tgn:7012149",
      "tgn:1002983",
      "tgn:7007252",
      "tgn:7029392"
    ],
    "placetype": [
      "aat:300006075"
    ],
    "id": 2394972,
    "name:xx": "Holder Ditch"
  }
}
