{
  "geometry": {
    "type": "Point",
    "coordinates": [
      -165.1667,
      64.7833
    ]
  },
  "type": "Feature",
  "properties": {
    "hierarchy": [
      "tgn:2626689",
      "tgn:7006450",
      "tgn:1000001",
      "tgn:7012149",
      "tgn:2000079",
      "tgn:7029392"
    ],
    "placetype": [
      "aat:300008706"
    ],
    "id": 2626689,
    "name:xx": "Rocky Mountain Creek"
  }
}
