{
  "geometry": {
    "type": "Point",
    "coordinates": [
      -75.324722,
      -50.3625
    ]
  },
  "type": "Feature",
  "properties": {
    "hierarchy": [
      "tgn:7318538",
      "tgn:1001702",
      "tgn:1000049",
      "tgn:1000002",
      "tgn:7029392"
    ],
    "placetype": [
      "aat:300132316"
    ],
    "id": 7318538,
    "name:xx": "Corbeta Papudo, Bahía"
  }
}
