{
  "type": "FeatureCollection",
  "features": [
    {
      "geometry": {
        "type": "Point",
        "coordinates": [
          -1.95,
          52.333333
        ]
      },
      "type": "Feature",
      "properties": {
        "hierarchy": [
          "tgn:1028301",
          "tgn:7002445",
          "tgn:1000003",
          "tgn:5000227",
          "tgn:7008591",
          "tgn:7029392"
        ],
        "placetype": [
          "aat:300008347"
        ],
        "name:en": "Alvechurch",
        "id": 1028301
      }
    },
    {
      "geometry": {
        "type": "Point",
        "coordinates": [
          -2.531389,
          51.588056
        ]
      },
      "type": "Feature",
      "properties": {
        "hierarchy": [
          "tgn:1028302",
          "tgn:7002445",
          "tgn:1000003",
          "tgn:7019020",
          "tgn:7008591",
          "tgn:7029392"
        ],
        "placetype": [
          "aat:300008347",
          "aat:300008372"
        ],
        "name:en": "Alveston",
        "id": 1028302
      }
    },
    {
      "geometry": {
        "type": "Point",
        "coordinates": [
          -1.583333,
          55.333333
        ]
      },
      "type": "Feature",
      "properties": {
        "hierarchy": [
          "tgn:1028303",
          "tgn:7002445",
          "tgn:1000003",
          "tgn:7008165",
          "tgn:7008591",
          "tgn:7029392"
        ],
        "placetype": [
          "aat:300008347"
        ],
        "name:en": "Amble",
        "id": 1028303
      }
    },
    {
      "geometry": {
        "type": "Point",
        "coordinates": [
          -1.116667,
          54.2
        ]
      },
      "type": "Feature",
      "properties": {
        "hierarchy": [
          "tgn:1028308",
          "tgn:7002445",
          "tgn:1000003",
          "tgn:7008166",
          "tgn:7008591",
          "tgn:7029392"
        ],
        "placetype": [
          "aat:300008347"
        ],
        "name:en": "Ampleforth",
        "id": 1028308
      }
    },
    {
      "geometry": {
        "type": "Point",
        "coordinates": [
          -0.483333,
          52.033333
        ]
      },
      "type": "Feature",
      "properties": {
        "hierarchy": [
          "tgn:1028309",
          "tgn:7002445",
          "tgn:7008103",
          "tgn:1000003",
          "tgn:7008591",
          "tgn:7029392"
        ],
        "placetype": [
          "aat:300008347"
        ],
        "id": 1028309,
        "name:xx": "Ampthill",
        "name:ang": "Ammetelle"
      }
    }
  ]
}
