{
  "geometry": {
    "type": "Point",
    "coordinates": [
      -74.2333,
      39.8667
    ]
  },
  "type": "Feature",
  "properties": {
    "hierarchy": [
      "tgn:2281103",
      "tgn:1000001",
      "tgn:1002738",
      "tgn:7012149",
      "tgn:7007565",
      "tgn:7029392"
    ],
    "placetype": [
      "aat:300008699"
    ],
    "id": 2281103,
    "name:xx": "Deep Hollow Branch"
  }
}
