{
  "geometry": {
    "type": "Point",
    "coordinates": [
      -157.55,
      63.3833
    ]
  },
  "type": "Feature",
  "properties": {
    "hierarchy": [
      "tgn:2373962",
      "tgn:7006450",
      "tgn:1000001",
      "tgn:7012149",
      "tgn:2000089",
      "tgn:7029392"
    ],
    "placetype": [
      "aat:300008706"
    ],
    "id": 2373962,
    "name:xx": "Hammer Creek"
  }
}
