{
  "geometry": {
    "type": "Point",
    "coordinates": [
      41.2333,
      -1.15
    ]
  },
  "type": "Feature",
  "properties": {
    "hierarchy": [
      "tgn:1090477",
      "tgn:7001242",
      "tgn:7593763",
      "tgn:1000169",
      "tgn:7029392"
    ],
    "placetype": [
      "aat:300008347"
    ],
    "id": 1090477,
    "name:xx": "Kolbio"
  }
}
