{
  "geometry": {
    "type": "Point",
    "coordinates": [
      74.528,
      20.553
    ]
  },
  "type": "Feature",
  "properties": {
    "hierarchy": [
      "tgn:1076055",
      "tgn:1000004",
      "tgn:7000198",
      "tgn:1001895",
      "tgn:7029392"
    ],
    "placetype": [
      "aat:300008347"
    ],
    "name:en": "Mālegaon",
    "id": 1076055
  }
}
