{
  "geometry": {
    "type": "Point",
    "coordinates": [
      -108.3333,
      32.4833
    ]
  },
  "type": "Feature",
  "properties": {
    "hierarchy": [
      "tgn:2524897",
      "tgn:1000001",
      "tgn:7012149",
      "tgn:2001437",
      "tgn:7007566",
      "tgn:7029392"
    ],
    "placetype": [
      "aat:300006191"
    ],
    "id": 2524897,
    "name:xx": "Morrell Tank"
  }
}
