{
  "geometry": {
    "type": "Point",
    "coordinates": [
      -80.1833,
      36.75
    ]
  },
  "type": "Feature",
  "properties": {
    "hierarchy": [
      "tgn:2352894",
      "tgn:1000001",
      "tgn:7012149",
      "tgn:2002179",
      "tgn:7007919",
      "tgn:7029392"
    ],
    "placetype": [
      "aat:300008706"
    ],
    "id": 2352894,
    "name:xx": "Goblintown Creek"
  }
}
