{
  "geometry": {
    "type": "Point",
    "coordinates": [
      -80.1833,
      41.2333
    ]
  },
  "type": "Feature",
  "properties": {
    "hierarchy": [
      "tgn:2733690",
      "tgn:1000001",
      "tgn:7012149",
      "tgn:1002659",
      "tgn:7007710",
      "tgn:7029392"
    ],
    "placetype": [
      "aat:300008347"
    ],
    "id": 2733690,
    "name:xx": "Turner"
  }
}
