{
  "geometry": {
    "type": "Point",
    "coordinates": [
      -77.7833,
      41.5833
    ]
  },
  "type": "Feature",
  "properties": {
    "hierarchy": [
      "tgn:2268753",
      "tgn:1000001",
      "tgn:7012149",
      "tgn:1002800",
      "tgn:7007710",
      "tgn:7029392"
    ],
    "placetype": [
      "aat:300008699"
    ],
    "id": 2268753,
    "name:xx": "Cross Fork"
  }
}
