{
  "type": "FeatureCollection",
  "features": [
    {
      "geometry": {
        "type": "Point",
        "coordinates": [
          120.35203,
          22.645735
        ]
      },
      "type": "Feature",
      "properties": {
        "hierarchy": [
          "tgn:7490791",
          "tgn:7001004",
          "tgn:1000004",
          "tgn:1000141",
          "tgn:7029392"
        ],
        "placetype": [
          "aat:300008347"
        ],
        "id": 7490791,
        "name:xx": "Dahua"
      }
    },
    {
      "geometry": {
        "type": "Point",
        "coordinates": [
          120.651361,
          22.959251
        ]
      },
      "type": "Feature",
      "properties": {
        "hierarchy": [
          "tgn:7490797",
          "tgn:7001004",
          "tgn:1000004",
          "tgn:1000141",
          "tgn:7029392"
        ],
        "placetype": [
          "aat:300008347"
        ],
        "id": 7490797,
        "name:xx": "Caodi"
      }
    },
    {
      "geometry": {
        "type": "Point",
        "coordinates": [
          121.255,
          23.185556
        ]
      },
      "type": "Feature",
      "properties": {
        "hierarchy": [
          "tgn:7490799",
          "tgn:7001010",
          "tgn:1000004",
          "tgn:1000141",
          "tgn:7029392"
        ],
        "placetype": [
          "aat:300008347"
        ],
        "id": 7490799,
        "name:xx": "Sangziliao"
      }
    }
  ]
}
