{
  "type": "FeatureCollection",
  "features": [
    {
      "geometry": {
        "type": "Point",
        "coordinates": [
          -138.0667,
          62.4667
        ]
      },
      "type": "Feature",
      "properties": {
        "hierarchy": [
          "tgn:1103740",
          "tgn:7005685",
          "tgn:1000001",
          "tgn:7005806",
          "tgn:7029392"
        ],
        "placetype": [
          "aat:300008795"
        ],
        "id": 1103740,
        "name:xx": "Apex Mountain"
      }
    },
    {
      "geometry": {
        "type": "Point",
        "coordinates": [
          125.2667,
          6.9833
        ]
      },
      "type": "Feature",
      "properties": {
        "hierarchy": [
          "tgn:1103742",
          "tgn:1000004",
          "tgn:1001218",
          "tgn:1000135",
          "tgn:7029392"
        ],
        "placetype": [
          "aat:300008795"
        ],
        "id": 1103742,
        "name:xx": "Apo, Mount"
      }
    },
    {
      "geometry": {
        "type": "Point",
        "coordinates": [
          -79.5,
          37.5167
        ]
      },
      "type": "Feature",
      "properties": {
        "hierarchy": [
          "tgn:1103743",
          "tgn:1000001",
          "tgn:7012149",
          "tgn:7007919",
          "tgn:7029392"
        ],
        "placetype": [
          "aat:300008795"
        ],
        "id": 1103743,
        "name:xx": "Apple Orchard Mountain"
      }
    },
    {
      "geometry": {
        "type": "Point",
        "coordinates": [
          138.6333,
          36.2
        ]
      },
      "type": "Feature",
      "properties": {
        "hierarchy": [
          "tgn:1103744",
          "tgn:1000980",
          "tgn:1000004",
          "tgn:7000894",
          "tgn:1000120",
          "tgn:7029392"
        ],
        "placetype": [
          "aat:300008795"
        ],
        "id": 1103744,
        "name:xx": "Arafune-yama"
      }
    },
    {
      "geometry": {
        "type": "Point",
        "coordinates": [
          138.1667,
          35.5
        ]
      },
      "type": "Feature",
      "properties": {
        "hierarchy": [
          "tgn:1103747",
          "tgn:7000895",
          "tgn:1000004",
          "tgn:1001031",
          "tgn:1000120",
          "tgn:7029392"
        ],
        "placetype": [
          "aat:300008795"
        ],
        "id": 1103747,
        "name:xx": "Arakawa-dake"
      }
    },
    {
      "geometry": {
        "type": "Point",
        "coordinates": [
          46.7,
          42.6333
        ]
      },
      "type": "Feature",
      "properties": {
        "hierarchy": [
          "tgn:1103748",
          "tgn:1000004",
          "tgn:7011494",
          "tgn:7002435",
          "tgn:7029392"
        ],
        "placetype": [
          "aat:300008795"
        ],
        "id": 1103748,
        "name:xx": "Arak-Meer, Khrebet"
      }
    },
    {
      "geometry": {
        "type": "Point",
        "coordinates": [
          -3.666667,
          52.8
        ]
      },
      "type": "Feature",
      "properties": {
        "hierarchy": [
          "tgn:1103749",
          "tgn:7002443",
          "tgn:1000003",
          "tgn:7029493",
          "tgn:7008591",
          "tgn:7029392"
        ],
        "placetype": [
          "aat:300008795"
        ],
        "name:en": "Aran Fawddwy",
        "id": 1103749
      }
    }
  ]
}
