{
  "geometry": {
    "type": "Point",
    "coordinates": [
      74.707876,
      28.397727
    ]
  },
  "type": "Feature",
  "properties": {
    "hierarchy": [
      "tgn:7568612",
      "tgn:1000004",
      "tgn:7000198",
      "tgn:7016788",
      "tgn:7029392"
    ],
    "placetype": [
      "aat:300008347"
    ],
    "name:en": "Kāklāsar",
    "id": 7568612
  }
}
