{
  "geometry": {
    "type": "Point",
    "coordinates": [
      -107.1667,
      44.35
    ]
  },
  "type": "Feature",
  "properties": {
    "hierarchy": [
      "tgn:2186111",
      "tgn:1000001",
      "tgn:7012149",
      "tgn:7007923",
      "tgn:7029392"
    ],
    "placetype": [
      "aat:300008798"
    ],
    "id": 2186111,
    "name:xx": "Bomber Mountain"
  }
}
