{
  "type": "FeatureCollection",
  "features": [
    {
      "geometry": {
        "type": "Point",
        "coordinates": [
          -113.7667,
          44.9667
        ]
      },
      "type": "Feature",
      "properties": {
        "hierarchy": [
          "tgn:2145700",
          "tgn:1000001",
          "tgn:7012149",
          "tgn:2000481",
          "tgn:7007250",
          "tgn:7029392"
        ],
        "placetype": [
          "aat:300008706"
        ],
        "id": 2145700,
        "name:xx": "Baldy Creek"
      }
    },
    {
      "geometry": {
        "type": "Point",
        "coordinates": [
          -116.35,
          47.4333
        ]
      },
      "type": "Feature",
      "properties": {
        "hierarchy": [
          "tgn:2145701",
          "tgn:1000001",
          "tgn:7012149",
          "tgn:2000479",
          "tgn:7007250",
          "tgn:7029392"
        ],
        "placetype": [
          "aat:300008706"
        ],
        "id": 2145701,
        "name:xx": "Baldy Creek"
      }
    },
    {
      "geometry": {
        "type": "Point",
        "coordinates": [
          -86.2,
          38.3667
        ]
      },
      "type": "Feature",
      "properties": {
        "hierarchy": [
          "tgn:2145702",
          "tgn:1000001",
          "tgn:7012149",
          "tgn:1002457",
          "tgn:7007252",
          "tgn:7029392"
        ],
        "placetype": [
          "aat:300008706"
        ],
        "id": 2145702,
        "name:xx": "Baldy Creek"
      }
    },
    {
      "geometry": {
        "type": "Point",
        "coordinates": [
          -115.9,
          48.8167
        ]
      },
      "type": "Feature",
      "properties": {
        "hierarchy": [
          "tgn:2145703",
          "tgn:1000001",
          "tgn:7012149",
          "tgn:2001286",
          "tgn:7007524",
          "tgn:7029392"
        ],
        "placetype": [
          "aat:300008706"
        ],
        "id": 2145703,
        "name:xx": "Baldy Creek"
      }
    },
    {
      "geometry": {
        "type": "Point",
        "coordinates": [
          -122.4833,
          42.0667
        ]
      },
      "type": "Feature",
      "properties": {
        "hierarchy": [
          "tgn:2145704",
          "tgn:1000001",
          "tgn:7012149",
          "tgn:2001711",
          "tgn:7007708",
          "tgn:7029392"
        ],
        "placetype": [
          "aat:300008706"
        ],
        "id": 2145704,
        "name:xx": "Baldy Creek"
      }
    },
    {
      "geometry": {
        "type": "Point",
        "coordinates": [
          -119.7667,
          44.4
        ]
      },
      "type": "Feature",
      "properties": {
        "hierarchy": [
          "tgn:2145705",
          "tgn:1000001",
          "tgn:7012149",
          "tgn:2001723",
          "tgn:7007708",
          "tgn:7029392"
        ],
        "placetype": [
          "aat:300008706"
        ],
        "id": 2145705,
        "name:xx": "Baldy Creek"
      }
    },
    {
      "geometry": {
        "type": "Point",
        "coordinates": [
          -118.3167,
          44.8333
        ]
      },
      "type": "Feature",
      "properties": {
        "hierarchy": [
          "tgn:2145706",
          "tgn:1000001",
          "tgn:7012149",
          "tgn:2001708",
          "tgn:7007708",
          "tgn:7029392"
        ],
        "placetype": [
          "aat:300008706"
        ],
        "id": 2145706,
        "name:xx": "Baldy Creek"
      }
    },
    {
      "geometry": {
        "type": "Point",
        "coordinates": [
          -123.9833,
          44.9333
        ]
      },
      "type": "Feature",
      "properties": {
        "hierarchy": [
          "tgn:2145707",
          "tgn:1000001",
          "tgn:7012149",
          "tgn:1002599",
          "tgn:7007708",
          "tgn:7029392"
        ],
        "placetype": [
          "aat:300008706"
        ],
        "id": 2145707,
        "name:xx": "Baldy Creek"
      }
    },
    {
      "geometry": {
        "type": "Point",
        "coordinates": [
          -123.6833,
          42.5167
        ]
      },
      "type": "Feature",
      "properties": {
        "hierarchy": [
          "tgn:2145708",
          "tgn:1000001",
          "tgn:7012149",
          "tgn:2001713",
          "tgn:7007708",
          "tgn:7029392"
        ],
        "placetype": [
          "aat:300008706"
        ],
        "id": 2145708,
        "name:xx": "Baldy Creek"
      }
    },
    {
      "geometry": {
        "type": "Point",
        "coordinates": [
          -121.6833,
          48.15
        ]
      },
      "type": "Feature",
      "properties": {
        "hierarchy": [
          "tgn:2145709",
          "tgn:1000001",
          "tgn:7012149",
          "tgn:1002899",
          "tgn:7007920",
          "tgn:7029392"
        ],
        "placetype": [
          "aat:300008706"
        ],
        "id": 2145709,
        "name:xx": "Baldy Creek"
      }
    }
  ]
}
