{
  "type": "FeatureCollection",
  "features": [
    {
      "geometry": {
        "type": "Point",
        "coordinates": [
          36.533,
          40.766
        ]
      },
      "type": "Feature",
      "properties": {
        "hierarchy": [
          "tgn:1125500",
          "tgn:1000004",
          "tgn:1001574",
          "tgn:7018454",
          "tgn:1000144",
          "tgn:7029392"
        ],
        "placetype": [
          "aat:300008707"
        ],
        "id": 1125500,
        "name:xx": "Kelkit Çayı"
      }
    },
    {
      "geometry": {
        "type": "Point",
        "coordinates": [
          125.2667,
          49.3333
        ]
      },
      "type": "Feature",
      "properties": {
        "hierarchy": [
          "tgn:1125501",
          "tgn:1000004",
          "tgn:1001290",
          "tgn:1000111",
          "tgn:7029392"
        ],
        "placetype": [
          "aat:300008707"
        ],
        "id": 1125501,
        "name:xx": "Keluo"
      }
    },
    {
      "geometry": {
        "type": "Point",
        "coordinates": [
          90.5167,
          57.2333
        ]
      },
      "type": "Feature",
      "properties": {
        "hierarchy": [
          "tgn:1125503",
          "tgn:1000004",
          "tgn:1003314",
          "tgn:7018214",
          "tgn:7002435",
          "tgn:7029392"
        ],
        "placetype": [
          "aat:300008707"
        ],
        "id": 1125503,
        "name:xx": "Kemchug"
      }
    },
    {
      "geometry": {
        "type": "Point",
        "coordinates": [
          80,
          26
        ]
      },
      "type": "Feature",
      "properties": {
        "hierarchy": [
          "tgn:1125507",
          "tgn:1000004",
          "tgn:7000198",
          "tgn:7029392"
        ],
        "placetype": [
          "aat:300008707"
        ],
        "id": 1125507,
        "name:xx": "Ken"
      }
    },
    {
      "geometry": {
        "type": "Point",
        "coordinates": [
          -4.15,
          55.066667
        ]
      },
      "type": "Feature",
      "properties": {
        "hierarchy": [
          "tgn:1125508",
          "tgn:7002444",
          "tgn:7008074",
          "tgn:1000003",
          "tgn:7008591",
          "tgn:7029392"
        ],
        "placetype": [
          "aat:300008707",
          "aat:300008699"
        ],
        "name:en": "Ken, Water of",
        "id": 1125508
      }
    },
    {
      "geometry": {
        "type": "Point",
        "coordinates": [
          39.1,
          62.0833
        ]
      },
      "type": "Feature",
      "properties": {
        "hierarchy": [
          "tgn:1125509",
          "tgn:4000818",
          "tgn:1000004",
          "tgn:7018214",
          "tgn:7002435",
          "tgn:7029392"
        ],
        "placetype": [
          "aat:300008707"
        ],
        "id": 1125509,
        "name:xx": "Kena"
      }
    }
  ]
}
