{
  "type": "FeatureCollection",
  "features": [
    {
      "geometry": {
        "type": "Point",
        "coordinates": [
          -87.5833,
          35.2167
        ]
      },
      "type": "Feature",
      "properties": {
        "hierarchy": [
          "tgn:2505480",
          "tgn:1000001",
          "tgn:7012149",
          "tgn:2001927",
          "tgn:7007825",
          "tgn:7029392"
        ],
        "placetype": [
          "aat:300008761"
        ],
        "id": 2505480,
        "name:xx": "Melton Hollow"
      }
    },
    {
      "geometry": {
        "type": "Point",
        "coordinates": [
          -85.9833,
          35.8667
        ]
      },
      "type": "Feature",
      "properties": {
        "hierarchy": [
          "tgn:2505481",
          "tgn:1000001",
          "tgn:7012149",
          "tgn:2001844",
          "tgn:7007825",
          "tgn:7029392"
        ],
        "placetype": [
          "aat:300008761"
        ],
        "id": 2505481,
        "name:xx": "Melton Hollow"
      }
    },
    {
      "geometry": {
        "type": "Point",
        "coordinates": [
          -88,
          36.4167
        ]
      },
      "type": "Feature",
      "properties": {
        "hierarchy": [
          "tgn:2505482",
          "tgn:1000001",
          "tgn:7012149",
          "tgn:2001917",
          "tgn:7007825",
          "tgn:7029392"
        ],
        "placetype": [
          "aat:300008761"
        ],
        "id": 2505482,
        "name:xx": "Melton Hollow"
      }
    },
    {
      "geometry": {
        "type": "Point",
        "coordinates": [
          -84.5333,
          32.3667
        ]
      },
      "type": "Feature",
      "properties": {
        "hierarchy": [
          "tgn:2505483",
          "tgn:1000001",
          "tgn:7012149",
          "tgn:2000389",
          "tgn:7007248",
          "tgn:7029392"
        ],
        "placetype": [
          "aat:300006191"
        ],
        "id": 2505483,
        "name:xx": "Melton Lake"
      }
    },
    {
      "geometry": {
        "type": "Point",
        "coordinates": [
          -90.9167,
          30.3667
        ]
      },
      "type": "Feature",
      "properties": {
        "hierarchy": [
          "tgn:2505484",
          "tgn:1000001",
          "tgn:7012149",
          "tgn:2000885",
          "tgn:7007256",
          "tgn:7029392"
        ],
        "placetype": [
          "aat:300008680"
        ],
        "id": 2505484,
        "name:xx": "Melton Lake"
      }
    },
    {
      "geometry": {
        "type": "Point",
        "coordinates": [
          -90.7167,
          33.2833
        ]
      },
      "type": "Feature",
      "properties": {
        "hierarchy": [
          "tgn:2505485",
          "tgn:1000001",
          "tgn:7012149",
          "tgn:2001152",
          "tgn:7007522",
          "tgn:7029392"
        ],
        "placetype": [
          "aat:300008905"
        ],
        "id": 2505485,
        "name:xx": "Melton Lake"
      }
    },
    {
      "geometry": {
        "type": "Point",
        "coordinates": [
          -95.5833,
          36.95
        ]
      },
      "type": "Feature",
      "properties": {
        "hierarchy": [
          "tgn:2505486",
          "tgn:1000001",
          "tgn:7012149",
          "tgn:2001675",
          "tgn:7007707",
          "tgn:7029392"
        ],
        "placetype": [
          "aat:300008680"
        ],
        "id": 2505486,
        "name:xx": "Melton Lake"
      }
    },
    {
      "geometry": {
        "type": "Point",
        "coordinates": [
          -89.35,
          35.65
        ]
      },
      "type": "Feature",
      "properties": {
        "hierarchy": [
          "tgn:2505487",
          "tgn:1000001",
          "tgn:7012149",
          "tgn:2001874",
          "tgn:7007825",
          "tgn:7029392"
        ],
        "placetype": [
          "aat:300006191"
        ],
        "id": 2505487,
        "name:xx": "Melton Lake"
      }
    },
    {
      "geometry": {
        "type": "Point",
        "coordinates": [
          -72.0833,
          41.3333
        ]
      },
      "type": "Feature",
      "properties": {
        "hierarchy": [
          "tgn:2505488",
          "tgn:1000001",
          "tgn:1002714",
          "tgn:7012149",
          "tgn:7007159",
          "tgn:7029392"
        ],
        "placetype": [
          "aat:300132348"
        ],
        "id": 2505488,
        "name:xx": "Melton Ledge"
      }
    },
    {
      "geometry": {
        "type": "Point",
        "coordinates": [
          -82.3,
          29.6
        ]
      },
      "type": "Feature",
      "properties": {
        "hierarchy": [
          "tgn:2505489",
          "tgn:2000256",
          "tgn:1000001",
          "tgn:7012149",
          "tgn:7007240",
          "tgn:7029392"
        ],
        "placetype": [
          "aat:300008347"
        ],
        "id": 2505489,
        "name:xx": "Melton Manor"
      }
    }
  ]
}
