{
  "geometry": {
    "type": "Point",
    "coordinates": [
      79.65573,
      22.57652
    ]
  },
  "type": "Feature",
  "properties": {
    "hierarchy": [
      "tgn:7553143",
      "tgn:1000004",
      "tgn:7000198",
      "tgn:1001894",
      "tgn:7029392"
    ],
    "placetype": [
      "aat:300008347"
    ],
    "name:en": "Marhi",
    "id": 7553143
  }
}
