{
  "geometry": {
    "type": "Point",
    "coordinates": [
      -82.25,
      37.0833
    ]
  },
  "type": "Feature",
  "properties": {
    "hierarchy": [
      "tgn:2745232",
      "tgn:1000001",
      "tgn:7012149",
      "tgn:2002157",
      "tgn:7007919",
      "tgn:7029392"
    ],
    "placetype": [
      "aat:300266640"
    ],
    "id": 2745232,
    "name:xx": "Vince Ridge"
  }
}
