{
  "geometry": {
    "type": "Point",
    "coordinates": [
      -105.9667,
      31.8333
    ]
  },
  "type": "Feature",
  "properties": {
    "hierarchy": [
      "tgn:2596447",
      "tgn:1000001",
      "tgn:7012149",
      "tgn:7007826",
      "tgn:7029392"
    ],
    "placetype": [
      "aat:300008761"
    ],
    "id": 2596447,
    "name:xx": "Pow Wow Canyon"
  }
}
