{
  "geometry": {
    "type": "Point",
    "coordinates": [
      -92.4333,
      47.8667
    ]
  },
  "type": "Feature",
  "properties": {
    "hierarchy": [
      "tgn:2193348",
      "tgn:1000001",
      "tgn:7012149",
      "tgn:2001067",
      "tgn:7007521",
      "tgn:7029392"
    ],
    "placetype": [
      "aat:300008850"
    ],
    "id": 2193348,
    "name:xx": "Breezy Point"
  }
}
