{
  "geometry": {
    "type": "Point",
    "coordinates": [
      -88.15,
      21.25
    ]
  },
  "type": "Feature",
  "properties": {
    "hierarchy": [
      "tgn:7383923",
      "tgn:1000001",
      "tgn:7005600",
      "tgn:7005560",
      "tgn:7029392"
    ],
    "placetype": [
      "aat:300343547"
    ],
    "id": 7383923,
    "name:xx": "Oxcal, Aguada"
  }
}
