{
  "geometry": {
    "type": "Point",
    "coordinates": [
      -74.2667,
      41.9667
    ]
  },
  "type": "Feature",
  "properties": {
    "hierarchy": [
      "tgn:2210352",
      "tgn:1000001",
      "tgn:7012149",
      "tgn:1002961",
      "tgn:7007568",
      "tgn:7029392"
    ],
    "placetype": [
      "aat:300008699"
    ],
    "id": 2210352,
    "name:xx": "Bush Kill"
  }
}
