{
  "geometry": {
    "type": "Point",
    "coordinates": [
      -88.45,
      45.9333
    ]
  },
  "type": "Feature",
  "properties": {
    "hierarchy": [
      "tgn:2619162",
      "tgn:1000001",
      "tgn:7012149",
      "tgn:7029392"
    ],
    "placetype": [
      "aat:300008706"
    ],
    "id": 2619162,
    "name:xx": "Riley Creek"
  }
}
