{
  "geometry": {
    "type": "Point",
    "coordinates": [
      87.2667,
      51.8667
    ]
  },
  "type": "Feature",
  "properties": {
    "hierarchy": [
      "tgn:1052309",
      "tgn:7011495",
      "tgn:1000004",
      "tgn:7002435",
      "tgn:7029392"
    ],
    "placetype": [
      "aat:300008347"
    ],
    "id": 1052309,
    "name:xx": "Artybash"
  }
}
