{
  "geometry": {
    "type": "Point",
    "coordinates": [
      -121.7167,
      45.4167
    ]
  },
  "type": "Feature",
  "properties": {
    "hierarchy": [
      "tgn:2745841",
      "tgn:1000001",
      "tgn:7012149",
      "tgn:2001710",
      "tgn:7007708",
      "tgn:7029392"
    ],
    "placetype": [
      "aat:300266640"
    ],
    "id": 2745841,
    "name:xx": "Vista Ridge"
  }
}
