{
  "geometry": {
    "type": "Point",
    "coordinates": [
      -101.25,
      36.8333
    ]
  },
  "type": "Feature",
  "properties": {
    "hierarchy": [
      "tgn:2083809",
      "tgn:1000001",
      "tgn:7012149",
      "tgn:2001692",
      "tgn:7007707",
      "tgn:7029392"
    ],
    "placetype": [
      "aat:300387016"
    ],
    "id": 2083809,
    "name:xx": "Panoma"
  }
}
