{
  "geometry": {
    "type": "Point",
    "coordinates": [
      -75.65,
      39.4167
    ]
  },
  "type": "Feature",
  "properties": {
    "hierarchy": [
      "tgn:2374981",
      "tgn:7014201",
      "tgn:1000001",
      "tgn:7012149",
      "tgn:7007239",
      "tgn:7029392"
    ],
    "placetype": [
      "aat:300008699"
    ],
    "id": 2374981,
    "name:xx": "Hangmans Run"
  }
}
