{
  "geometry": {
    "type": "Point",
    "coordinates": [
      -95.3833,
      32.4833
    ]
  },
  "type": "Feature",
  "properties": {
    "hierarchy": [
      "tgn:2108013",
      "tgn:1000001",
      "tgn:7012149",
      "tgn:1002898",
      "tgn:7007826",
      "tgn:7029392"
    ],
    "placetype": [
      "aat:300008347"
    ],
    "id": 2108013,
    "name:xx": "Thedford"
  }
}
