{
  "geometry": {
    "type": "Point",
    "coordinates": [
      36.0833,
      32.2333
    ]
  },
  "type": "Feature",
  "properties": {
    "hierarchy": [
      "tgn:1081885",
      "tgn:7018394",
      "tgn:1000004",
      "tgn:1000121",
      "tgn:7029392"
    ],
    "placetype": [
      "aat:300008347"
    ],
    "id": 1081885,
    "name:xx": "Balʻamā"
  }
}
