{
  "geometry": {
    "type": "Point",
    "coordinates": [
      -92.85,
      39.95
    ]
  },
  "type": "Feature",
  "properties": {
    "hierarchy": [
      "tgn:2059853",
      "tgn:1000001",
      "tgn:7012149",
      "tgn:2001214",
      "tgn:7007523",
      "tgn:7029392"
    ],
    "placetype": [
      "aat:300008347"
    ],
    "id": 2059853,
    "name:xx": "New Boston"
  }
}
