{
  "geometry": {
    "type": "Point",
    "coordinates": [
      -73.5667,
      42.5333
    ]
  },
  "type": "Feature",
  "properties": {
    "hierarchy": [
      "tgn:2583809",
      "tgn:1000001",
      "tgn:7012149",
      "tgn:1002821",
      "tgn:7007568",
      "tgn:7029392"
    ],
    "placetype": [
      "aat:300008905"
    ],
    "id": 2583809,
    "name:xx": "Pine Swamp"
  }
}
