{
  "geometry": {
    "type": "Point",
    "coordinates": [
      -146.5667,
      62.3667
    ]
  },
  "type": "Feature",
  "properties": {
    "hierarchy": [
      "tgn:2243971",
      "tgn:7006450",
      "tgn:1000001",
      "tgn:2124053",
      "tgn:7012149",
      "tgn:7029392"
    ],
    "placetype": [
      "aat:300132316"
    ],
    "id": 2243971,
    "name:xx": "Cliff Bay"
  }
}
