{
  "geometry": {
    "type": "Point",
    "coordinates": [
      2.486,
      8.042
    ]
  },
  "type": "Feature",
  "properties": {
    "hierarchy": [
      "tgn:1089637",
      "tgn:7001242",
      "tgn:7032092",
      "tgn:1000160",
      "tgn:7029392"
    ],
    "placetype": [
      "aat:300008347"
    ],
    "id": 1089637,
    "name:xx": "Savé"
  }
}
