{
  "geometry": {
    "type": "Point",
    "coordinates": [
      -110.85,
      32.6667
    ]
  },
  "type": "Feature",
  "properties": {
    "hierarchy": [
      "tgn:2552079",
      "tgn:1000001",
      "tgn:7006451",
      "tgn:7012149",
      "tgn:2000101",
      "tgn:7029392"
    ],
    "placetype": [
      "aat:300006191"
    ],
    "id": 2552079,
    "name:xx": "Number One Dirt Tank"
  }
}
