{
  "geometry": {
    "type": "Point",
    "coordinates": [
      -7.15,
      54.45
    ]
  },
  "type": "Feature",
  "properties": {
    "hierarchy": [
      "tgn:7455115",
      "tgn:7002448",
      "tgn:7019203",
      "tgn:1000003",
      "tgn:7008591",
      "tgn:7029392"
    ],
    "placetype": [
      "aat:300387502"
    ],
    "name:en": "Cecil Manor",
    "id": 7455115
  }
}
