{
  "geometry": {
    "type": "Point",
    "coordinates": [
      -86.1333,
      38.9167
    ]
  },
  "type": "Feature",
  "properties": {
    "hierarchy": [
      "tgn:2146109",
      "tgn:1000001",
      "tgn:7012149",
      "tgn:1002508",
      "tgn:7007252",
      "tgn:7029392"
    ],
    "placetype": [
      "aat:300008706"
    ],
    "id": 2146109,
    "name:xx": "Ballard Creek"
  }
}
