{
  "geometry": {
    "type": "Point",
    "coordinates": [
      -106.8833,
      44.6167
    ]
  },
  "type": "Feature",
  "properties": {
    "hierarchy": [
      "tgn:2568625",
      "tgn:1000001",
      "tgn:7012149",
      "tgn:2002381",
      "tgn:7007923",
      "tgn:7029392"
    ],
    "placetype": [
      "aat:300008699"
    ],
    "id": 2568625,
    "name:xx": "Parken Fork"
  }
}
