{
  "geometry": {
    "type": "Point",
    "coordinates": [
      30.617661,
      30.85382
    ]
  },
  "type": "Feature",
  "properties": {
    "hierarchy": [
      "tgn:7525597",
      "tgn:7001242",
      "tgn:1001075",
      "tgn:7016833",
      "tgn:7029392"
    ],
    "placetype": [
      "aat:300008347"
    ],
    "name:en": "Daqdūqah",
    "id": 7525597
  }
}
