{
  "geometry": {
    "type": "Point",
    "coordinates": [
      74.75376,
      32.746537
    ]
  },
  "type": "Feature",
  "properties": {
    "hierarchy": [
      "tgn:7592322",
      "tgn:1000004",
      "tgn:7000198",
      "tgn:7000799",
      "tgn:7029392"
    ],
    "placetype": [
      "aat:300008347"
    ],
    "name:en": "Shāhzādpur Bhopa",
    "id": 7592322
  }
}
