{
  "geometry": {
    "type": "Point",
    "coordinates": [
      78.774525,
      24.843941
    ]
  },
  "type": "Feature",
  "properties": {
    "hierarchy": [
      "tgn:7584387",
      "tgn:1000004",
      "tgn:7000198",
      "tgn:1001894",
      "tgn:7029392"
    ],
    "placetype": [
      "aat:300008699"
    ],
    "name:en": "Manpasār Nāla",
    "id": 7584387
  }
}
