{
  "geometry": {
    "type": "Point",
    "coordinates": [
      -108.7333,
      35.5167
    ]
  },
  "type": "Feature",
  "properties": {
    "hierarchy": [
      "tgn:7014040",
      "tgn:1000001",
      "tgn:7012149",
      "tgn:7019676",
      "tgn:7007566",
      "tgn:7029392"
    ],
    "placetype": [
      "aat:300008347",
      "aat:300008416",
      "aat:300387305",
      "aat:300008375"
    ],
    "id": 7014040,
    "name:xx": "Gallup"
  }
}
