{
  "geometry": {
    "type": "Point",
    "coordinates": [
      -82.35,
      41.4167
    ]
  },
  "type": "Feature",
  "properties": {
    "hierarchy": [
      "tgn:2559519",
      "tgn:1000001",
      "tgn:7012149",
      "tgn:1002357",
      "tgn:7007706",
      "tgn:7029392"
    ],
    "placetype": [
      "aat:300008680"
    ],
    "id": 2559519,
    "name:xx": "Ontario Lagoon"
  }
}
