{
  "type": "FeatureCollection",
  "features": [
    {
      "geometry": {
        "type": "Point",
        "coordinates": [
          -85.95,
          42.3667
        ]
      },
      "type": "Feature",
      "properties": {
        "hierarchy": [
          "tgn:2051340",
          "tgn:1000001",
          "tgn:7012149",
          "tgn:1002967",
          "tgn:7007520",
          "tgn:7029392"
        ],
        "placetype": [
          "aat:300008347"
        ],
        "id": 2051340,
        "name:xx": "Bloomingdale"
      }
    },
    {
      "geometry": {
        "type": "Point",
        "coordinates": [
          -82.5,
          43.2
        ]
      },
      "type": "Feature",
      "properties": {
        "hierarchy": [
          "tgn:2051344",
          "tgn:1000001",
          "tgn:7012149",
          "tgn:2000995",
          "tgn:7007520",
          "tgn:7029392"
        ],
        "placetype": [
          "aat:300008347"
        ],
        "id": 2051344,
        "name:xx": "Blue Water Beach"
      }
    },
    {
      "geometry": {
        "type": "Point",
        "coordinates": [
          -85.5333,
          41.8
        ]
      },
      "type": "Feature",
      "properties": {
        "hierarchy": [
          "tgn:2051345",
          "tgn:1000001",
          "tgn:7012149",
          "tgn:7016057",
          "tgn:7007520",
          "tgn:7029392"
        ],
        "placetype": [
          "aat:300008347"
        ],
        "id": 2051345,
        "name:xx": "Bluff Beach"
      }
    },
    {
      "geometry": {
        "type": "Point",
        "coordinates": [
          -83.7167,
          43.4167
        ]
      },
      "type": "Feature",
      "properties": {
        "hierarchy": [
          "tgn:2051346",
          "tgn:1000001",
          "tgn:7012149",
          "tgn:2000992",
          "tgn:7007520",
          "tgn:7029392"
        ],
        "placetype": [
          "aat:300008347",
          "aat:300387210"
        ],
        "id": 2051346,
        "name:xx": "Blumfield Corners"
      }
    },
    {
      "geometry": {
        "type": "Point",
        "coordinates": [
          -83.3833,
          41.8667
        ]
      },
      "type": "Feature",
      "properties": {
        "hierarchy": [
          "tgn:2051348",
          "tgn:1000001",
          "tgn:7012149",
          "tgn:1002679",
          "tgn:7007520",
          "tgn:7029392"
        ],
        "placetype": [
          "aat:300008347"
        ],
        "id": 2051348,
        "name:xx": "Bolles Harbor"
      }
    },
    {
      "geometry": {
        "type": "Point",
        "coordinates": [
          -84.25,
          43.7333
        ]
      },
      "type": "Feature",
      "properties": {
        "hierarchy": [
          "tgn:2051349",
          "tgn:1000001",
          "tgn:7012149",
          "tgn:2000979",
          "tgn:7007520",
          "tgn:7029392"
        ],
        "placetype": [
          "aat:300008347",
          "aat:300387210"
        ],
        "id": 2051349,
        "name:xx": "Bombay"
      }
    }
  ]
}
