{
  "geometry": {
    "type": "Point",
    "coordinates": [
      -123.5167,
      41.5167
    ]
  },
  "type": "Feature",
  "properties": {
    "hierarchy": [
      "tgn:2720690",
      "tgn:1000001",
      "tgn:7012149",
      "tgn:7007157",
      "tgn:2000189",
      "tgn:7029392"
    ],
    "placetype": [
      "aat:300132348"
    ],
    "id": 2720690,
    "name:xx": "Ti Bar"
  }
}
