{
  "geometry": {
    "type": "Point",
    "coordinates": [
      3.2833,
      50.2333
    ]
  },
  "type": "Feature",
  "properties": {
    "hierarchy": [
      "tgn:1136081",
      "tgn:1000003",
      "tgn:7001097",
      "tgn:1000070",
      "tgn:7029392"
    ],
    "placetype": [
      "aat:300006075"
    ],
    "id": 1136081,
    "name:xx": "Sensée, Canal de la"
  }
}
