{
  "geometry": {
    "type": "Point",
    "coordinates": [
      85.701783,
      21.713613
    ]
  },
  "type": "Feature",
  "properties": {
    "hierarchy": [
      "tgn:7577553",
      "tgn:1000004",
      "tgn:7000198",
      "tgn:7016694",
      "tgn:7029392"
    ],
    "placetype": [
      "aat:300008347"
    ],
    "name:en": "Khirāitāngri",
    "id": 7577553
  }
}
