{
  "geometry": {
    "type": "Point",
    "coordinates": [
      -98.05,
      24.15
    ]
  },
  "type": "Feature",
  "properties": {
    "hierarchy": [
      "tgn:7424529",
      "tgn:1000001",
      "tgn:7005597",
      "tgn:7005560",
      "tgn:7029392"
    ],
    "placetype": [
      "aat:300008699"
    ],
    "id": 7424529,
    "name:xx": "Trujillo, Río"
  }
}
