{
  "geometry": {
    "type": "Point",
    "coordinates": [
      -113.5667,
      45.1167
    ]
  },
  "type": "Feature",
  "properties": {
    "hierarchy": [
      "tgn:2354442",
      "tgn:1000001",
      "tgn:7012149",
      "tgn:2000481",
      "tgn:7007250",
      "tgn:7029392"
    ],
    "placetype": [
      "aat:300008798"
    ],
    "id": 2354442,
    "name:xx": "Goldstone Mountain"
  }
}
