{
  "geometry": {
    "type": "Point",
    "coordinates": [
      -104.5333,
      43.5667
    ]
  },
  "type": "Feature",
  "properties": {
    "hierarchy": [
      "tgn:2211344",
      "tgn:1000001",
      "tgn:7012149",
      "tgn:2002387",
      "tgn:7007923",
      "tgn:7029392"
    ],
    "placetype": [
      "aat:300006191"
    ],
    "id": 2211344,
    "name:xx": "Butte Reservoir"
  }
}
