{
  "type": "FeatureCollection",
  "features": [
    {
      "geometry": {
        "type": "Point",
        "coordinates": [
          -121.6,
          45.7
        ]
      },
      "type": "Feature",
      "properties": {
        "hierarchy": [
          "tgn:2518750",
          "tgn:1000001",
          "tgn:7012149",
          "tgn:2001710",
          "tgn:7007708",
          "tgn:7029392"
        ],
        "placetype": [
          "aat:300008850"
        ],
        "id": 2518750,
        "name:xx": "Mitchell Point"
      }
    },
    {
      "geometry": {
        "type": "Point",
        "coordinates": [
          -89.6667,
          36.05
        ]
      },
      "type": "Feature",
      "properties": {
        "hierarchy": [
          "tgn:2518751",
          "tgn:1000001",
          "tgn:7012149",
          "tgn:2001859",
          "tgn:7007825",
          "tgn:7029392"
        ],
        "placetype": [
          "aat:300008850"
        ],
        "id": 2518751,
        "name:xx": "Mitchell Point"
      }
    },
    {
      "geometry": {
        "type": "Point",
        "coordinates": [
          -122.6167,
          47.5333
        ]
      },
      "type": "Feature",
      "properties": {
        "hierarchy": [
          "tgn:2518752",
          "tgn:1000001",
          "tgn:7012149",
          "tgn:1002552",
          "tgn:7007920",
          "tgn:7029392"
        ],
        "placetype": [
          "aat:300008850"
        ],
        "id": 2518752,
        "name:xx": "Mitchell Point"
      }
    },
    {
      "geometry": {
        "type": "Point",
        "coordinates": [
          -86.75,
          34.5333
        ]
      },
      "type": "Feature",
      "properties": {
        "hierarchy": [
          "tgn:2518753",
          "tgn:7002659",
          "tgn:1000001",
          "tgn:7012149",
          "tgn:2000051",
          "tgn:7029392"
        ],
        "placetype": [
          "aat:300008680"
        ],
        "id": 2518753,
        "name:xx": "Mitchell Pond"
      }
    },
    {
      "geometry": {
        "type": "Point",
        "coordinates": [
          -72.2833,
          41.45
        ]
      },
      "type": "Feature",
      "properties": {
        "hierarchy": [
          "tgn:2518754",
          "tgn:1000001",
          "tgn:1002714",
          "tgn:7012149",
          "tgn:7007159",
          "tgn:7029392"
        ],
        "placetype": [
          "aat:300008680"
        ],
        "id": 2518754,
        "name:xx": "Mitchell Pond"
      }
    },
    {
      "geometry": {
        "type": "Point",
        "coordinates": [
          -84.15,
          30.7
        ]
      },
      "type": "Feature",
      "properties": {
        "hierarchy": [
          "tgn:2518755",
          "tgn:1000001",
          "tgn:7012149",
          "tgn:2000356",
          "tgn:7007248",
          "tgn:7029392"
        ],
        "placetype": [
          "aat:300008680"
        ],
        "id": 2518755,
        "name:xx": "Mitchell Pond"
      }
    },
    {
      "geometry": {
        "type": "Point",
        "coordinates": [
          -83.9167,
          30.7167
        ]
      },
      "type": "Feature",
      "properties": {
        "hierarchy": [
          "tgn:2518756",
          "tgn:1000001",
          "tgn:7012149",
          "tgn:7014371",
          "tgn:7007248",
          "tgn:7029392"
        ],
        "placetype": [
          "aat:300006191"
        ],
        "id": 2518756,
        "name:xx": "Mitchell Pond"
      }
    },
    {
      "geometry": {
        "type": "Point",
        "coordinates": [
          -100.95,
          37.35
        ]
      },
      "type": "Feature",
      "properties": {
        "hierarchy": [
          "tgn:2518757",
          "tgn:1000001",
          "tgn:7012149",
          "tgn:2000747",
          "tgn:7007254",
          "tgn:7029392"
        ],
        "placetype": [
          "aat:300006191"
        ],
        "id": 2518757,
        "name:xx": "Mitchell Pond"
      }
    },
    {
      "geometry": {
        "type": "Point",
        "coordinates": [
          -89.5167,
          29.2667
        ]
      },
      "type": "Feature",
      "properties": {
        "hierarchy": [
          "tgn:2518758",
          "tgn:1000001",
          "tgn:7012149",
          "tgn:2000891",
          "tgn:7007256",
          "tgn:7029392"
        ],
        "placetype": [
          "aat:300008680"
        ],
        "id": 2518758,
        "name:xx": "Mitchell Pond"
      }
    },
    {
      "geometry": {
        "type": "Point",
        "coordinates": [
          -68.6167,
          44.65
        ]
      },
      "type": "Feature",
      "properties": {
        "hierarchy": [
          "tgn:2518759",
          "tgn:1000001",
          "tgn:2000922",
          "tgn:7012149",
          "tgn:7007515",
          "tgn:7029392"
        ],
        "placetype": [
          "aat:300008680"
        ],
        "id": 2518759,
        "name:xx": "Mitchell Pond"
      }
    }
  ]
}
