{
  "type": "FeatureCollection",
  "features": [
    {
      "geometry": {
        "type": "Point",
        "coordinates": [
          7.5,
          53.016667
        ]
      },
      "type": "Feature",
      "properties": {
        "hierarchy": [
          "tgn:7212290",
          "tgn:1000003",
          "tgn:7003676",
          "tgn:7000084",
          "tgn:7029392"
        ],
        "placetype": [
          "aat:300008347"
        ],
        "id": 7212290,
        "name:xx": "Börgermoor"
      }
    },
    {
      "geometry": {
        "type": "Point",
        "coordinates": [
          9.833333,
          48.433333
        ]
      },
      "type": "Feature",
      "properties": {
        "hierarchy": [
          "tgn:7212291",
          "tgn:7003692",
          "tgn:1000003",
          "tgn:7000084",
          "tgn:7029392"
        ],
        "placetype": [
          "aat:300008863"
        ],
        "id": 7212291,
        "name:xx": "Borgerhau"
      }
    },
    {
      "geometry": {
        "type": "Point",
        "coordinates": [
          11.9,
          54.15
        ]
      },
      "type": "Feature",
      "properties": {
        "hierarchy": [
          "tgn:7212292",
          "tgn:1000003",
          "tgn:7000094",
          "tgn:7000084",
          "tgn:7029392"
        ],
        "placetype": [
          "aat:300000745"
        ],
        "id": 7212292,
        "name:xx": "Börgerende"
      }
    },
    {
      "geometry": {
        "type": "Point",
        "coordinates": [
          8.033333,
          51.6
        ]
      },
      "type": "Feature",
      "properties": {
        "hierarchy": [
          "tgn:7212295",
          "tgn:1000003",
          "tgn:7003677",
          "tgn:7000084",
          "tgn:7029392"
        ],
        "placetype": [
          "aat:300007783"
        ],
        "id": 7212295,
        "name:xx": "Bahnhof Borgeln"
      }
    },
    {
      "geometry": {
        "type": "Point",
        "coordinates": [
          8.033333,
          51.6
        ]
      },
      "type": "Feature",
      "properties": {
        "hierarchy": [
          "tgn:7212296",
          "tgn:1000003",
          "tgn:7003677",
          "tgn:7000084",
          "tgn:7029392"
        ],
        "placetype": [
          "aat:300008347"
        ],
        "id": 7212296,
        "name:xx": "Borgeln"
      }
    },
    {
      "geometry": {
        "type": "Point",
        "coordinates": [
          8.05,
          51.6
        ]
      },
      "type": "Feature",
      "properties": {
        "hierarchy": [
          "tgn:7212297",
          "tgn:1000003",
          "tgn:7003677",
          "tgn:7000084",
          "tgn:7029392"
        ],
        "placetype": [
          "aat:300008347"
        ],
        "id": 7212297,
        "name:xx": "Borgeler Linde"
      }
    },
    {
      "geometry": {
        "type": "Point",
        "coordinates": [
          8.95,
          50.5
        ]
      },
      "type": "Feature",
      "properties": {
        "hierarchy": [
          "tgn:7212298",
          "tgn:1000003",
          "tgn:7003678",
          "tgn:7000084",
          "tgn:7029392"
        ],
        "placetype": [
          "aat:300008777"
        ],
        "id": 7212298,
        "name:xx": "Borgel-Berg"
      }
    },
    {
      "geometry": {
        "type": "Point",
        "coordinates": [
          9.883333,
          54.166667
        ]
      },
      "type": "Feature",
      "properties": {
        "hierarchy": [
          "tgn:7212299",
          "tgn:1000003",
          "tgn:7003688",
          "tgn:7000084",
          "tgn:7029392"
        ],
        "placetype": [
          "aat:300008347"
        ],
        "id": 7212299,
        "name:xx": "Borgdorf-Seedorf"
      }
    }
  ]
}
