{
  "geometry": {
    "type": "Point",
    "coordinates": [
      -84.7833,
      36.8167
    ]
  },
  "type": "Feature",
  "properties": {
    "hierarchy": [
      "tgn:2314602",
      "tgn:1000001",
      "tgn:7012149",
      "tgn:2000850",
      "tgn:7007255",
      "tgn:7029392"
    ],
    "placetype": [
      "aat:300266640"
    ],
    "id": 2314602,
    "name:xx": "Elk Ridge"
  }
}
