{
  "geometry": {
    "type": "Point",
    "coordinates": [
      -135.6833,
      57.3167
    ]
  },
  "type": "Feature",
  "properties": {
    "hierarchy": [
      "tgn:2382630",
      "tgn:7006450",
      "tgn:1000001",
      "tgn:7012149",
      "tgn:2124002",
      "tgn:7029392"
    ],
    "placetype": [
      "aat:300008850"
    ],
    "id": 2382630,
    "name:xx": "Hayward Point"
  }
}
