{
  "geometry": {
    "type": "Point",
    "coordinates": [
      -111.6667,
      34.5167
    ]
  },
  "type": "Feature",
  "properties": {
    "hierarchy": [
      "tgn:2633432",
      "tgn:1000001",
      "tgn:7006451",
      "tgn:7012149",
      "tgn:2000103",
      "tgn:7029392"
    ],
    "placetype": [
      "aat:300006191"
    ],
    "id": 2633432,
    "name:xx": "Runner Tank"
  }
}
