{
  "geometry": {
    "type": "Point",
    "coordinates": [
      51.1667,
      52.9833
    ]
  },
  "type": "Feature",
  "properties": {
    "hierarchy": [
      "tgn:1137891",
      "tgn:1000004",
      "tgn:1003407",
      "tgn:7018214",
      "tgn:7002435",
      "tgn:7029392"
    ],
    "placetype": [
      "aat:300008347"
    ],
    "id": 1137891,
    "name:xx": "Maksimovka"
  }
}
