{
  "geometry": {
    "type": "Point",
    "coordinates": [
      -116.55,
      47.8167
    ]
  },
  "type": "Feature",
  "properties": {
    "hierarchy": [
      "tgn:2142822",
      "tgn:1000001",
      "tgn:7012149",
      "tgn:2000479",
      "tgn:7007250",
      "tgn:7029392"
    ],
    "placetype": [
      "aat:300008798"
    ],
    "id": 2142822,
    "name:xx": "Badger Mountain"
  }
}
