{
  "geometry": {
    "type": "Point",
    "coordinates": [
      -84.7167,
      45.9167
    ]
  },
  "type": "Feature",
  "properties": {
    "hierarchy": [
      "tgn:2604297",
      "tgn:1000001",
      "tgn:7012149",
      "tgn:2000973",
      "tgn:7007520",
      "tgn:7029392"
    ],
    "placetype": [
      "aat:300008798"
    ],
    "id": 2604297,
    "name:xx": "Rabbit Back Peak"
  }
}
