{
  "type": "FeatureCollection",
  "features": [
    {
      "geometry": {
        "type": "Point",
        "coordinates": [
          27.4167,
          46.1833
        ]
      },
      "type": "Feature",
      "properties": {
        "hierarchy": [
          "tgn:1050231",
          "tgn:1000003",
          "tgn:1000476",
          "tgn:1000091",
          "tgn:7029392"
        ],
        "placetype": [
          "aat:300008347"
        ],
        "id": 1050231,
        "name:xx": "Podu Turcului"
      }
    },
    {
      "geometry": {
        "type": "Point",
        "coordinates": [
          27,
          44.9167
        ]
      },
      "type": "Feature",
      "properties": {
        "hierarchy": [
          "tgn:1050232",
          "tgn:1000353",
          "tgn:1000003",
          "tgn:1000091",
          "tgn:7029392"
        ],
        "placetype": [
          "aat:300008347"
        ],
        "id": 1050232,
        "name:xx": "Pogoanele"
      }
    },
    {
      "geometry": {
        "type": "Point",
        "coordinates": [
          23.0333,
          43.9167
        ]
      },
      "type": "Feature",
      "properties": {
        "hierarchy": [
          "tgn:1050233",
          "tgn:1000003",
          "tgn:1000364",
          "tgn:1000091",
          "tgn:7029392"
        ],
        "placetype": [
          "aat:300008347"
        ],
        "id": 1050233,
        "name:xx": "Poiana Mare"
      }
    },
    {
      "geometry": {
        "type": "Point",
        "coordinates": [
          23.3167,
          47.7
        ]
      },
      "type": "Feature",
      "properties": {
        "hierarchy": [
          "tgn:1050234",
          "tgn:1000003",
          "tgn:1000442",
          "tgn:1000091",
          "tgn:7029392"
        ],
        "placetype": [
          "aat:300008347"
        ],
        "id": 1050234,
        "name:xx": "Pomi"
      }
    },
    {
      "geometry": {
        "type": "Point",
        "coordinates": [
          22.4167,
          47.2333
        ]
      },
      "type": "Feature",
      "properties": {
        "hierarchy": [
          "tgn:1050235",
          "tgn:1000344",
          "tgn:1000003",
          "tgn:1000091",
          "tgn:7029392"
        ],
        "placetype": [
          "aat:300008347"
        ],
        "id": 1050235,
        "name:xx": "Popești"
      }
    },
    {
      "geometry": {
        "type": "Point",
        "coordinates": [
          26.1667,
          44.3833
        ]
      },
      "type": "Feature",
      "properties": {
        "hierarchy": [
          "tgn:1050236",
          "tgn:1000003",
          "tgn:7593858",
          "tgn:1000091",
          "tgn:7029392"
        ],
        "placetype": [
          "aat:300008347"
        ],
        "id": 1050236,
        "name:xx": "Popești-Leordeni"
      }
    },
    {
      "geometry": {
        "type": "Point",
        "coordinates": [
          27.5167,
          47.3
        ]
      },
      "type": "Feature",
      "properties": {
        "hierarchy": [
          "tgn:1050237",
          "tgn:1000003",
          "tgn:1000392",
          "tgn:1000091",
          "tgn:7029392"
        ],
        "placetype": [
          "aat:300008347"
        ],
        "id": 1050237,
        "name:xx": "Popricani"
      }
    },
    {
      "geometry": {
        "type": "Point",
        "coordinates": [
          23.6,
          44.35
        ]
      },
      "type": "Feature",
      "properties": {
        "hierarchy": [
          "tgn:1050238",
          "tgn:1000003",
          "tgn:1000364",
          "tgn:1000091",
          "tgn:7029392"
        ],
        "placetype": [
          "aat:300008347"
        ],
        "id": 1050238,
        "name:xx": "Predești"
      }
    },
    {
      "geometry": {
        "type": "Point",
        "coordinates": [
          25.5167,
          45.5
        ]
      },
      "type": "Feature",
      "properties": {
        "hierarchy": [
          "tgn:1050239",
          "tgn:1000351",
          "tgn:1000003",
          "tgn:1000091",
          "tgn:7029392"
        ],
        "placetype": [
          "aat:300008347"
        ],
        "id": 1050239,
        "name:xx": "Predeal"
      }
    }
  ]
}
