{
  "geometry": {
    "type": "Point",
    "coordinates": [
      79.377003,
      27.2188
    ]
  },
  "type": "Feature",
  "properties": {
    "hierarchy": [
      "tgn:7560358",
      "tgn:1000004",
      "tgn:7000198",
      "tgn:7016722",
      "tgn:7029392"
    ],
    "placetype": [
      "aat:300008347"
    ],
    "name:en": "Kāsimpur",
    "id": 7560358
  }
}
