{
  "geometry": {
    "type": "Point",
    "coordinates": [
      32.464554,
      29.89638
    ]
  },
  "type": "Feature",
  "properties": {
    "hierarchy": [
      "tgn:7523832",
      "tgn:7001242",
      "tgn:7016833",
      "tgn:1001110",
      "tgn:7029392"
    ],
    "placetype": [
      "aat:300120599"
    ],
    "name:en": "Mīnā' 'Atāqah",
    "id": 7523832
  }
}
