{
  "type": "FeatureCollection",
  "features": [
    {
      "geometry": {
        "type": "Point",
        "coordinates": [
          -108.85,
          44.4
        ]
      },
      "type": "Feature",
      "properties": {
        "hierarchy": [
          "tgn:2771770",
          "tgn:1000001",
          "tgn:7012149",
          "tgn:2002379",
          "tgn:7007923",
          "tgn:7029392"
        ],
        "placetype": [
          "aat:300000390"
        ],
        "id": 2771770,
        "name:xx": "Wiley Mine"
      }
    },
    {
      "geometry": {
        "type": "Point",
        "coordinates": [
          -83.4,
          34.8
        ]
      },
      "type": "Feature",
      "properties": {
        "hierarchy": [
          "tgn:2771771",
          "tgn:1000001",
          "tgn:7012149",
          "tgn:2000410",
          "tgn:7007248",
          "tgn:7029392"
        ],
        "placetype": [
          "aat:300266640"
        ],
        "id": 2771771,
        "name:xx": "Wiley Mountain"
      }
    },
    {
      "geometry": {
        "type": "Point",
        "coordinates": [
          -70.95,
          44.1833
        ]
      },
      "type": "Feature",
      "properties": {
        "hierarchy": [
          "tgn:2771772",
          "tgn:1000001",
          "tgn:7012149",
          "tgn:2000926",
          "tgn:7007515",
          "tgn:7029392"
        ],
        "placetype": [
          "aat:300008798"
        ],
        "id": 2771772,
        "name:xx": "Wiley Mountain"
      }
    },
    {
      "geometry": {
        "type": "Point",
        "coordinates": [
          -82.5,
          35.7167
        ]
      },
      "type": "Feature",
      "properties": {
        "hierarchy": [
          "tgn:2771773",
          "tgn:1000001",
          "tgn:2001473",
          "tgn:7012149",
          "tgn:7007709",
          "tgn:7029392"
        ],
        "placetype": [
          "aat:300008798"
        ],
        "id": 2771773,
        "name:xx": "Wiley Mountain"
      }
    },
    {
      "geometry": {
        "type": "Point",
        "coordinates": [
          -69.1167,
          44.25
        ]
      },
      "type": "Feature",
      "properties": {
        "hierarchy": [
          "tgn:2771774",
          "tgn:1000001",
          "tgn:7012149",
          "tgn:2000931",
          "tgn:7007515",
          "tgn:7029392"
        ],
        "placetype": [
          "aat:300008850"
        ],
        "id": 2771774,
        "name:xx": "Wiley Neck"
      }
    },
    {
      "geometry": {
        "type": "Point",
        "coordinates": [
          -69.55,
          43.9667
        ]
      },
      "type": "Feature",
      "properties": {
        "hierarchy": [
          "tgn:2771775",
          "tgn:1000001",
          "tgn:2000925",
          "tgn:7012149",
          "tgn:7007515",
          "tgn:7029392"
        ],
        "placetype": [
          "aat:300008850"
        ],
        "id": 2771775,
        "name:xx": "Wiley Point"
      }
    },
    {
      "geometry": {
        "type": "Point",
        "coordinates": [
          -69.6333,
          43.9
        ]
      },
      "type": "Feature",
      "properties": {
        "hierarchy": [
          "tgn:2771776",
          "tgn:1000001",
          "tgn:2000925",
          "tgn:7012149",
          "tgn:7007515",
          "tgn:7029392"
        ],
        "placetype": [
          "aat:300008680"
        ],
        "id": 2771776,
        "name:xx": "Wiley Pond"
      }
    },
    {
      "geometry": {
        "type": "Point",
        "coordinates": [
          -68.5333,
          46
        ]
      },
      "type": "Feature",
      "properties": {
        "hierarchy": [
          "tgn:2771777",
          "tgn:1000001",
          "tgn:7012149",
          "tgn:2000927",
          "tgn:7007515",
          "tgn:7029392"
        ],
        "placetype": [
          "aat:300008680"
        ],
        "id": 2771777,
        "name:xx": "Wiley Pond"
      }
    },
    {
      "geometry": {
        "type": "Point",
        "coordinates": [
          -116.5333,
          42.2333
        ]
      },
      "type": "Feature",
      "properties": {
        "hierarchy": [
          "tgn:2771778",
          "tgn:1000001",
          "tgn:7012149",
          "tgn:2000488",
          "tgn:7007250",
          "tgn:7029392"
        ],
        "placetype": [
          "aat:300006191"
        ],
        "id": 2771778,
        "name:xx": "Wiley Reservoir"
      }
    },
    {
      "geometry": {
        "type": "Point",
        "coordinates": [
          -108.8167,
          44.4
        ]
      },
      "type": "Feature",
      "properties": {
        "hierarchy": [
          "tgn:2771779",
          "tgn:1000001",
          "tgn:7012149",
          "tgn:2002379",
          "tgn:7007923",
          "tgn:7029392"
        ],
        "placetype": [
          "aat:300006191"
        ],
        "id": 2771779,
        "name:xx": "Wiley Reservoir"
      }
    }
  ]
}
