{
  "geometry": {
    "type": "Point",
    "coordinates": [
      -73.8167,
      42.15
    ]
  },
  "type": "Feature",
  "properties": {
    "hierarchy": [
      "tgn:2207673",
      "tgn:1000001",
      "tgn:7013638",
      "tgn:7012149",
      "tgn:7007568",
      "tgn:7029392"
    ],
    "placetype": [
      "aat:300008347"
    ],
    "id": 2207673,
    "name:xx": "Burden"
  }
}
