{
  "geometry": {
    "type": "Point",
    "coordinates": [
      -71.0667,
      41.55
    ]
  },
  "type": "Feature",
  "properties": {
    "hierarchy": [
      "tgn:2480637",
      "tgn:1002201",
      "tgn:1000001",
      "tgn:7012149",
      "tgn:7007517",
      "tgn:7029392"
    ],
    "placetype": [
      "aat:300008791"
    ],
    "id": 2480637,
    "name:xx": "Lakes Island"
  }
}
