{
  "geometry": {
    "type": "Point",
    "coordinates": [
      126.25,
      34.4667
    ]
  },
  "type": "Feature",
  "properties": {
    "hierarchy": [
      "tgn:1082222",
      "tgn:1001193",
      "tgn:1006792",
      "tgn:1000004",
      "tgn:7000299",
      "tgn:7029392"
    ],
    "placetype": [
      "aat:300008347"
    ],
    "id": 1082222,
    "name:xx": "Chindo"
  }
}
