{
  "type": "FeatureCollection",
  "features": [
    {
      "geometry": {
        "type": "Point",
        "coordinates": [
          -84.2333,
          41.9667
        ]
      },
      "type": "Feature",
      "properties": {
        "hierarchy": [
          "tgn:2689290",
          "tgn:1000001",
          "tgn:7012149",
          "tgn:1002588",
          "tgn:7007520",
          "tgn:7029392"
        ],
        "placetype": [
          "aat:300008706"
        ],
        "id": 2689290,
        "name:xx": "Squaw Creek"
      }
    },
    {
      "geometry": {
        "type": "Point",
        "coordinates": [
          -84.2333,
          42.7167
        ]
      },
      "type": "Feature",
      "properties": {
        "hierarchy": [
          "tgn:2689291",
          "tgn:1000001",
          "tgn:7012149",
          "tgn:1002502",
          "tgn:7007520",
          "tgn:7029392"
        ],
        "placetype": [
          "aat:300008706"
        ],
        "id": 2689291,
        "name:xx": "Squaw Creek"
      }
    },
    {
      "geometry": {
        "type": "Point",
        "coordinates": [
          -83.3,
          43.2667
        ]
      },
      "type": "Feature",
      "properties": {
        "hierarchy": [
          "tgn:2689292",
          "tgn:1000001",
          "tgn:7012149",
          "tgn:1002576",
          "tgn:7007520",
          "tgn:7029392"
        ],
        "placetype": [
          "aat:300008706"
        ],
        "id": 2689292,
        "name:xx": "Squaw Creek"
      }
    },
    {
      "geometry": {
        "type": "Point",
        "coordinates": [
          -84.9667,
          43.5833
        ]
      },
      "type": "Feature",
      "properties": {
        "hierarchy": [
          "tgn:2689293",
          "tgn:1000001",
          "tgn:7012149",
          "tgn:2000967",
          "tgn:7007520",
          "tgn:7029392"
        ],
        "placetype": [
          "aat:300008706"
        ],
        "id": 2689293,
        "name:xx": "Squaw Creek"
      }
    },
    {
      "geometry": {
        "type": "Point",
        "coordinates": [
          -94.6333,
          47.8833
        ]
      },
      "type": "Feature",
      "properties": {
        "hierarchy": [
          "tgn:2689294",
          "tgn:2001002",
          "tgn:1000001",
          "tgn:7012149",
          "tgn:7007521",
          "tgn:7029392"
        ],
        "placetype": [
          "aat:300008706"
        ],
        "id": 2689294,
        "name:xx": "Squaw Creek"
      }
    },
    {
      "geometry": {
        "type": "Point",
        "coordinates": [
          -91.7667,
          47.95
        ]
      },
      "type": "Feature",
      "properties": {
        "hierarchy": [
          "tgn:2689295",
          "tgn:1000001",
          "tgn:7012149",
          "tgn:2001036",
          "tgn:7007521",
          "tgn:7029392"
        ],
        "placetype": [
          "aat:300008706"
        ],
        "id": 2689295,
        "name:xx": "Squaw Creek"
      }
    },
    {
      "geometry": {
        "type": "Point",
        "coordinates": [
          -93.0167,
          47.9333
        ]
      },
      "type": "Feature",
      "properties": {
        "hierarchy": [
          "tgn:2689296",
          "tgn:1000001",
          "tgn:7012149",
          "tgn:7007521",
          "tgn:7029392"
        ],
        "placetype": [
          "aat:300008706"
        ],
        "id": 2689296,
        "name:xx": "Squaw Creek"
      }
    },
    {
      "geometry": {
        "type": "Point",
        "coordinates": [
          -92.55,
          46.7167
        ]
      },
      "type": "Feature",
      "properties": {
        "hierarchy": [
          "tgn:2689297",
          "tgn:1000001",
          "tgn:2001007",
          "tgn:7012149",
          "tgn:7007521",
          "tgn:7029392"
        ],
        "placetype": [
          "aat:300008706"
        ],
        "id": 2689297,
        "name:xx": "Squaw Creek"
      }
    },
    {
      "geometry": {
        "type": "Point",
        "coordinates": [
          -95.2333,
          40.4667
        ]
      },
      "type": "Feature",
      "properties": {
        "hierarchy": [
          "tgn:2689298",
          "tgn:2001169",
          "tgn:1000001",
          "tgn:7012149",
          "tgn:7007523",
          "tgn:7029392"
        ],
        "placetype": [
          "aat:300008706"
        ],
        "id": 2689298,
        "name:xx": "Squaw Creek"
      }
    },
    {
      "geometry": {
        "type": "Point",
        "coordinates": [
          -112.55,
          44.9167
        ]
      },
      "type": "Feature",
      "properties": {
        "hierarchy": [
          "tgn:2689299",
          "tgn:1000001",
          "tgn:2001260",
          "tgn:7012149",
          "tgn:7007524",
          "tgn:7029392"
        ],
        "placetype": [
          "aat:300008706"
        ],
        "id": 2689299,
        "name:xx": "Squaw Creek"
      }
    }
  ]
}
