{
  "type": "FeatureCollection",
  "features": [
    {
      "geometry": {
        "type": "Point",
        "coordinates": [
          -109.2,
          28.316667
        ]
      },
      "type": "Feature",
      "properties": {
        "hierarchy": [
          "tgn:7362670",
          "tgn:1000001",
          "tgn:1001960",
          "tgn:7005560",
          "tgn:7029392"
        ],
        "placetype": [
          "aat:300000241"
        ],
        "id": 7362670,
        "name:xx": "Rancho El Durazno"
      }
    },
    {
      "geometry": {
        "type": "Point",
        "coordinates": [
          -106.583333,
          28.116667
        ]
      },
      "type": "Feature",
      "properties": {
        "hierarchy": [
          "tgn:7362671",
          "tgn:7005581",
          "tgn:1000001",
          "tgn:7005560",
          "tgn:7029392"
        ],
        "placetype": [
          "aat:300000241"
        ],
        "id": 7362671,
        "name:xx": "Rancho El Durazno"
      }
    },
    {
      "geometry": {
        "type": "Point",
        "coordinates": [
          -108.316667,
          27.333333
        ]
      },
      "type": "Feature",
      "properties": {
        "hierarchy": [
          "tgn:7362672",
          "tgn:7005581",
          "tgn:1000001",
          "tgn:7005560",
          "tgn:7029392"
        ],
        "placetype": [
          "aat:300000241"
        ],
        "id": 7362672,
        "name:xx": "Rancho El Durazno"
      }
    },
    {
      "geometry": {
        "type": "Point",
        "coordinates": [
          -102.983333,
          20.583333
        ]
      },
      "type": "Feature",
      "properties": {
        "hierarchy": [
          "tgn:7362673",
          "tgn:7005586",
          "tgn:1000001",
          "tgn:7005560",
          "tgn:7029392"
        ],
        "placetype": [
          "aat:300000241"
        ],
        "id": 7362673,
        "name:xx": "El Durazno"
      }
    },
    {
      "geometry": {
        "type": "Point",
        "coordinates": [
          -110.716667,
          30.816667
        ]
      },
      "type": "Feature",
      "properties": {
        "hierarchy": [
          "tgn:7362674",
          "tgn:1000001",
          "tgn:1001960",
          "tgn:7005560",
          "tgn:7029392"
        ],
        "placetype": [
          "aat:300008347"
        ],
        "id": 7362674,
        "name:xx": "El Durazno"
      }
    },
    {
      "geometry": {
        "type": "Point",
        "coordinates": [
          -101.666667,
          28.816667
        ]
      },
      "type": "Feature",
      "properties": {
        "hierarchy": [
          "tgn:7362675",
          "tgn:7005581",
          "tgn:1000001",
          "tgn:7005560",
          "tgn:7029392"
        ],
        "placetype": [
          "aat:300008347"
        ],
        "id": 7362675,
        "name:xx": "El Durazno"
      }
    },
    {
      "geometry": {
        "type": "Point",
        "coordinates": [
          -109.233333,
          30.983333
        ]
      },
      "type": "Feature",
      "properties": {
        "hierarchy": [
          "tgn:7362676",
          "tgn:1000001",
          "tgn:1001960",
          "tgn:7005560",
          "tgn:7029392"
        ],
        "placetype": [
          "aat:300000241"
        ],
        "id": 7362676,
        "name:xx": "Rancho El Alamito"
      }
    },
    {
      "geometry": {
        "type": "Point",
        "coordinates": [
          -111.475556,
          30.980556
        ]
      },
      "type": "Feature",
      "properties": {
        "hierarchy": [
          "tgn:7362677",
          "tgn:1000001",
          "tgn:1001960",
          "tgn:7005560",
          "tgn:7029392"
        ],
        "placetype": [
          "aat:300008347"
        ],
        "id": 7362677,
        "name:xx": "El Alamito"
      }
    },
    {
      "geometry": {
        "type": "Point",
        "coordinates": [
          -111.566667,
          30.716667
        ]
      },
      "type": "Feature",
      "properties": {
        "hierarchy": [
          "tgn:7362678",
          "tgn:1000001",
          "tgn:1001960",
          "tgn:7005560",
          "tgn:7029392"
        ],
        "placetype": [
          "aat:300000241"
        ],
        "id": 7362678,
        "name:xx": "Rancho El Alamito"
      }
    },
    {
      "geometry": {
        "type": "Point",
        "coordinates": [
          -111.016667,
          30.65
        ]
      },
      "type": "Feature",
      "properties": {
        "hierarchy": [
          "tgn:7362679",
          "tgn:1000001",
          "tgn:1001960",
          "tgn:7005560",
          "tgn:7029392"
        ],
        "placetype": [
          "aat:300000241"
        ],
        "id": 7362679,
        "name:xx": "Rancho El Alamito"
      }
    }
  ]
}
