{
  "geometry": {
    "type": "Point",
    "coordinates": [
      -75.25,
      -69.75
    ]
  },
  "type": "Feature",
  "properties": {
    "hierarchy": [
      "tgn:1006773",
      "tgn:1000007",
      "tgn:7029392"
    ],
    "placetype": [
      "aat:300008791"
    ],
    "id": 1006773,
    "name:xx": "Charcot Island"
  }
}
