{
  "geometry": {
    "type": "Point",
    "coordinates": [
      74.7167,
      34.0167
    ]
  },
  "type": "Feature",
  "properties": {
    "hierarchy": [
      "tgn:1074580",
      "tgn:1000004",
      "tgn:7000198",
      "tgn:7000799",
      "tgn:7029392"
    ],
    "placetype": [
      "aat:300008347"
    ],
    "id": 1074580,
    "name:xx": "Bagdom"
  }
}
