{
  "geometry": {
    "type": "Point",
    "coordinates": [
      72.0833,
      38.1333
    ]
  },
  "type": "Feature",
  "properties": {
    "hierarchy": [
      "tgn:1052562",
      "tgn:7011626",
      "tgn:1000004",
      "tgn:7014835",
      "tgn:7029392"
    ],
    "placetype": [
      "aat:300008347"
    ],
    "id": 1052562,
    "name:xx": "Basid"
  }
}
