{
  "type": "FeatureCollection",
  "features": [
    {
      "geometry": {
        "type": "Point",
        "coordinates": [
          -106.316667,
          25.8
        ]
      },
      "type": "Feature",
      "properties": {
        "hierarchy": [
          "tgn:7441050",
          "tgn:7005583",
          "tgn:1000001",
          "tgn:7005560",
          "tgn:7029392"
        ],
        "placetype": [
          "aat:300008347"
        ],
        "id": 7441050,
        "name:xx": "San Lucas"
      }
    },
    {
      "geometry": {
        "type": "Point",
        "coordinates": [
          -111.55,
          25.65
        ]
      },
      "type": "Feature",
      "properties": {
        "hierarchy": [
          "tgn:7441051",
          "tgn:1001836",
          "tgn:1000001",
          "tgn:7005560",
          "tgn:7029392"
        ],
        "placetype": [
          "aat:300008347"
        ],
        "id": 7441051,
        "name:xx": "San Lucas"
      }
    },
    {
      "geometry": {
        "type": "Point",
        "coordinates": [
          -99.566667,
          25.4
        ]
      },
      "type": "Feature",
      "properties": {
        "hierarchy": [
          "tgn:7441052",
          "tgn:1000001",
          "tgn:7005589",
          "tgn:7005560",
          "tgn:7029392"
        ],
        "placetype": [
          "aat:300008347"
        ],
        "id": 7441052,
        "name:xx": "San Lucas"
      }
    },
    {
      "geometry": {
        "type": "Point",
        "coordinates": [
          -100.15,
          24.933333
        ]
      },
      "type": "Feature",
      "properties": {
        "hierarchy": [
          "tgn:7441053",
          "tgn:1000001",
          "tgn:7005589",
          "tgn:7005560",
          "tgn:7029392"
        ],
        "placetype": [
          "aat:300008347"
        ],
        "id": 7441053,
        "name:xx": "San Lucas"
      }
    },
    {
      "geometry": {
        "type": "Point",
        "coordinates": [
          -99.2,
          23.366667
        ]
      },
      "type": "Feature",
      "properties": {
        "hierarchy": [
          "tgn:7441055",
          "tgn:1000001",
          "tgn:7005597",
          "tgn:7005560",
          "tgn:7029392"
        ],
        "placetype": [
          "aat:300008347"
        ],
        "id": 7441055,
        "name:xx": "San Lucas"
      }
    },
    {
      "geometry": {
        "type": "Point",
        "coordinates": [
          -104.4,
          22.55
        ]
      },
      "type": "Feature",
      "properties": {
        "hierarchy": [
          "tgn:7441057",
          "tgn:7005583",
          "tgn:1000001",
          "tgn:7005560",
          "tgn:7029392"
        ],
        "placetype": [
          "aat:300008347"
        ],
        "id": 7441057,
        "name:xx": "San Lucas"
      }
    },
    {
      "geometry": {
        "type": "Point",
        "coordinates": [
          -99.45,
          20.466667
        ]
      },
      "type": "Feature",
      "properties": {
        "hierarchy": [
          "tgn:7441058",
          "tgn:7005587",
          "tgn:1000001",
          "tgn:7005560",
          "tgn:7029392"
        ],
        "placetype": [
          "aat:300008347"
        ],
        "id": 7441058,
        "name:xx": "San Lucas"
      }
    },
    {
      "geometry": {
        "type": "Point",
        "coordinates": [
          -103.366667,
          20.416667
        ]
      },
      "type": "Feature",
      "properties": {
        "hierarchy": [
          "tgn:7441059",
          "tgn:7005586",
          "tgn:1000001",
          "tgn:7005560",
          "tgn:7029392"
        ],
        "placetype": [
          "aat:300008347"
        ],
        "id": 7441059,
        "name:xx": "San Lucas"
      }
    }
  ]
}
