{
  "geometry": {
    "type": "Point",
    "coordinates": [
      31.2167,
      29.85
    ]
  },
  "type": "Feature",
  "properties": {
    "hierarchy": [
      "tgn:1100514",
      "tgn:7001242",
      "tgn:7016833",
      "tgn:1001418",
      "tgn:7029392"
    ],
    "placetype": [
      "aat:300000810",
      "aat:300387004",
      "aat:300000372",
      "aat:300008057"
    ],
    "id": 1100514,
    "name:xx": "Ṣaqqâra"
  }
}
