{
  "geometry": {
    "type": "Point",
    "coordinates": [
      -82.7667,
      42.5833
    ]
  },
  "type": "Feature",
  "properties": {
    "hierarchy": [
      "tgn:2360039",
      "tgn:1000001",
      "tgn:7012149",
      "tgn:1002617",
      "tgn:7007520",
      "tgn:7029392"
    ],
    "placetype": [
      "aat:300008791"
    ],
    "id": 2360039,
    "name:xx": "Grass Island"
  }
}
