{
  "geometry": {
    "type": "Point",
    "coordinates": [
      -80.3833,
      38.7333
    ]
  },
  "type": "Feature",
  "properties": {
    "hierarchy": [
      "tgn:2331046",
      "tgn:1000001",
      "tgn:7012149",
      "tgn:7013961",
      "tgn:7029392"
    ],
    "placetype": [
      "aat:300008699"
    ],
    "id": 2331046,
    "name:xx": "Flat Run"
  }
}
