{
  "type": "FeatureCollection",
  "features": [
    {
      "geometry": {
        "type": "Point",
        "coordinates": [
          12.166667,
          44.0775
        ]
      },
      "type": "Feature",
      "properties": {
        "hierarchy": [
          "tgn:4004000",
          "tgn:7003129",
          "tgn:1000003",
          "tgn:7008516",
          "tgn:1000080",
          "tgn:7029392"
        ],
        "placetype": [
          "aat:300008347"
        ],
        "id": 4004000,
        "name:xx": "Formignano"
      }
    },
    {
      "geometry": {
        "type": "Point",
        "coordinates": [
          17,
          61.75
        ]
      },
      "type": "Feature",
      "properties": {
        "hierarchy": [
          "tgn:4004002",
          "tgn:1000374",
          "tgn:1000003",
          "tgn:1000097",
          "tgn:7029392"
        ],
        "placetype": [
          "aat:300008347"
        ],
        "id": 4004002,
        "name:xx": "Forsa"
      }
    },
    {
      "geometry": {
        "type": "Point",
        "coordinates": [
          -4.033333,
          57.566667
        ]
      },
      "type": "Feature",
      "properties": {
        "hierarchy": [
          "tgn:4004005",
          "tgn:7002444",
          "tgn:1000003",
          "tgn:7008082",
          "tgn:7008591",
          "tgn:7029392"
        ],
        "placetype": [
          "aat:300008347"
        ],
        "name:en": "Fort George",
        "id": 4004005
      }
    }
  ]
}
