{
  "type": "FeatureCollection",
  "features": [
    {
      "geometry": {
        "type": "Point",
        "coordinates": [
          -133.4,
          55.7333
        ]
      },
      "type": "Feature",
      "properties": {
        "hierarchy": [
          "tgn:2725240",
          "tgn:7006450",
          "tgn:1000001",
          "tgn:7012149",
          "tgn:2000082",
          "tgn:7029392"
        ],
        "placetype": [
          "aat:300132316"
        ],
        "id": 2725240,
        "name:xx": "Tonowek Bay"
      }
    },
    {
      "geometry": {
        "type": "Point",
        "coordinates": [
          -133.4,
          55.7667
        ]
      },
      "type": "Feature",
      "properties": {
        "hierarchy": [
          "tgn:2725241",
          "tgn:7006450",
          "tgn:1000001",
          "tgn:7012149",
          "tgn:2000082",
          "tgn:7029392"
        ],
        "placetype": [
          "aat:300008706"
        ],
        "id": 2725241,
        "name:xx": "Tonowek Creek"
      }
    },
    {
      "geometry": {
        "type": "Point",
        "coordinates": [
          -97.1333,
          29.2167
        ]
      },
      "type": "Feature",
      "properties": {
        "hierarchy": [
          "tgn:2725242",
          "tgn:1000001",
          "tgn:7012149",
          "tgn:7021746",
          "tgn:7007826",
          "tgn:7029392"
        ],
        "placetype": [
          "aat:300008706"
        ],
        "id": 2725242,
        "name:xx": "Tonqua Creek"
      }
    },
    {
      "geometry": {
        "type": "Point",
        "coordinates": [
          -116.2,
          37.15
        ]
      },
      "type": "Feature",
      "properties": {
        "hierarchy": [
          "tgn:2725243",
          "tgn:1000001",
          "tgn:2001418",
          "tgn:7012149",
          "tgn:7007526",
          "tgn:7029392"
        ],
        "placetype": [
          "aat:300008699"
        ],
        "id": 2725243,
        "name:xx": "Tonque Wash"
      }
    },
    {
      "geometry": {
        "type": "Point",
        "coordinates": [
          -106.2167,
          35.35
        ]
      },
      "type": "Feature",
      "properties": {
        "hierarchy": [
          "tgn:2725244",
          "tgn:1000001",
          "tgn:7012149",
          "tgn:7007566",
          "tgn:7029392"
        ],
        "placetype": [
          "aat:300008699"
        ],
        "id": 2725244,
        "name:xx": "Tonque, Arroyo"
      }
    },
    {
      "geometry": {
        "type": "Point",
        "coordinates": [
          -122.7833,
          45.35
        ]
      },
      "type": "Feature",
      "properties": {
        "hierarchy": [
          "tgn:2725245",
          "tgn:1000001",
          "tgn:7012149",
          "tgn:1002994",
          "tgn:7007708",
          "tgn:7029392"
        ],
        "placetype": [
          "aat:300008347"
        ],
        "id": 2725245,
        "name:xx": "Tonquin"
      }
    },
    {
      "geometry": {
        "type": "Point",
        "coordinates": [
          -122.8,
          45.35
        ]
      },
      "type": "Feature",
      "properties": {
        "hierarchy": [
          "tgn:2725246",
          "tgn:1000001",
          "tgn:7012149",
          "tgn:1002994",
          "tgn:7007708",
          "tgn:7029392"
        ],
        "placetype": [
          "aat:300055621"
        ],
        "id": 2725246,
        "name:xx": "Tonquin Scablands"
      }
    },
    {
      "geometry": {
        "type": "Point",
        "coordinates": [
          -95.9667,
          46.4333
        ]
      },
      "type": "Feature",
      "properties": {
        "hierarchy": [
          "tgn:2725247",
          "tgn:1000001",
          "tgn:7012149",
          "tgn:2001054",
          "tgn:7007521",
          "tgn:7029392"
        ],
        "placetype": [
          "aat:300008680"
        ],
        "id": 2725247,
        "name:xx": "Tonseth Lake"
      }
    },
    {
      "geometry": {
        "type": "Point",
        "coordinates": [
          -120.1,
          48.7833
        ]
      },
      "type": "Feature",
      "properties": {
        "hierarchy": [
          "tgn:2725248",
          "tgn:1000001",
          "tgn:7012149",
          "tgn:1002742",
          "tgn:7007920",
          "tgn:7029392"
        ],
        "placetype": [
          "aat:300008680"
        ],
        "id": 2725248,
        "name:xx": "Tonseth Lake"
      }
    },
    {
      "geometry": {
        "type": "Point",
        "coordinates": [
          -74.1833,
          42
        ]
      },
      "type": "Feature",
      "properties": {
        "hierarchy": [
          "tgn:2725249",
          "tgn:1000001",
          "tgn:7012149",
          "tgn:1002961",
          "tgn:7007568",
          "tgn:7029392"
        ],
        "placetype": [
          "aat:300008798"
        ],
        "id": 2725249,
        "name:xx": "Tonshi Mountain"
      }
    }
  ]
}
