{
  "geometry": {
    "type": "Point",
    "coordinates": [
      -88.1167,
      32.5333
    ]
  },
  "type": "Feature",
  "properties": {
    "hierarchy": [
      "tgn:2431667",
      "tgn:7002659",
      "tgn:1000001",
      "tgn:7012149",
      "tgn:2000059",
      "tgn:7029392"
    ],
    "placetype": [
      "aat:300006191"
    ],
    "id": 2431667,
    "name:xx": "Katherine Allison Lake"
  }
}
