{
  "geometry": {
    "type": "Point",
    "coordinates": [
      -118.25,
      34.3667
    ]
  },
  "type": "Feature",
  "properties": {
    "hierarchy": [
      "tgn:7022293",
      "tgn:1000001",
      "tgn:7012149",
      "tgn:7007157",
      "tgn:7029392"
    ],
    "placetype": [
      "aat:300008863"
    ],
    "id": 7022293,
    "name:xx": "Angeles National Forest"
  }
}
