{
  "geometry": {
    "type": "Point",
    "coordinates": [
      32.5333,
      47.9667
    ]
  },
  "type": "Feature",
  "properties": {
    "hierarchy": [
      "tgn:1060840",
      "tgn:1000003",
      "tgn:7011662",
      "tgn:7006660",
      "tgn:7029392"
    ],
    "placetype": [
      "aat:300008347"
    ],
    "id": 1060840,
    "name:xx": "Ustinovka"
  }
}
