{
  "geometry": {
    "type": "Point",
    "coordinates": [
      -118.6833,
      44.1333
    ]
  },
  "type": "Feature",
  "properties": {
    "hierarchy": [
      "tgn:2389050",
      "tgn:1000001",
      "tgn:7012149",
      "tgn:2001708",
      "tgn:7007708",
      "tgn:7029392"
    ],
    "placetype": [
      "aat:300008697"
    ],
    "id": 2389050,
    "name:xx": "Hidden Spring"
  }
}
