{
  "geometry": {
    "type": "Point",
    "coordinates": [
      -114.5833,
      37.9333
    ]
  },
  "type": "Feature",
  "properties": {
    "hierarchy": [
      "tgn:2783896",
      "tgn:1000001",
      "tgn:2001416",
      "tgn:7012149",
      "tgn:7007526",
      "tgn:7029392"
    ],
    "placetype": [
      "aat:300000390"
    ],
    "id": 2783896,
    "name:xx": "X-Ray Tunnel"
  }
}
