{
  "geometry": {
    "type": "Point",
    "coordinates": [
      -86.1167,
      30.9167
    ]
  },
  "type": "Feature",
  "properties": {
    "hierarchy": [
      "tgn:2250311",
      "tgn:1000001",
      "tgn:7012149",
      "tgn:2000290",
      "tgn:7007240",
      "tgn:7029392"
    ],
    "placetype": [
      "aat:300008680"
    ],
    "id": 2250311,
    "name:xx": "Collinsworth Pond"
  }
}
