{
  "geometry": {
    "type": "Point",
    "coordinates": [
      109.1667,
      12.6667
    ]
  },
  "type": "Feature",
  "properties": {
    "hierarchy": [
      "tgn:7001055",
      "tgn:1000004",
      "tgn:1000145",
      "tgn:7029392"
    ],
    "placetype": [
      "aat:300387064",
      "aat:300000774"
    ],
    "id": 7001055,
    "name:xx": "Phú Khánh, Tỉnh"
  }
}
