{
  "geometry": {
    "type": "Point",
    "coordinates": [
      11.85,
      53.25
    ]
  },
  "type": "Feature",
  "properties": {
    "hierarchy": [
      "tgn:7156347",
      "tgn:7000096",
      "tgn:1000003",
      "tgn:7000084",
      "tgn:7029392"
    ],
    "placetype": [
      "aat:300008347"
    ],
    "id": 7156347,
    "name:xx": "Kleeste"
  }
}
