{
  "geometry": {
    "type": "Point",
    "coordinates": [
      -112.1333,
      45.4833
    ]
  },
  "type": "Feature",
  "properties": {
    "hierarchy": [
      "tgn:2301845",
      "tgn:1000001",
      "tgn:7012149",
      "tgn:2001288",
      "tgn:7007524",
      "tgn:7029392"
    ],
    "placetype": [
      "aat:300006075"
    ],
    "id": 2301845,
    "name:xx": "Durham Ditch"
  }
}
