{
  "geometry": {
    "type": "Point",
    "coordinates": [
      106.6167,
      10.7167
    ]
  },
  "type": "Feature",
  "properties": {
    "hierarchy": [
      "tgn:1135894",
      "tgn:1000004",
      "tgn:7001069",
      "tgn:7001063",
      "tgn:1000145",
      "tgn:7029392"
    ],
    "placetype": [
      "aat:300006075"
    ],
    "id": 1135894,
    "name:xx": "Doi, Kinh"
  }
}
