{
  "geometry": {
    "type": "Point",
    "coordinates": [
      -115.2167,
      36.4167
    ]
  },
  "type": "Feature",
  "properties": {
    "hierarchy": [
      "tgn:2741299",
      "tgn:1000001",
      "tgn:2001410",
      "tgn:7012149",
      "tgn:7007526",
      "tgn:7029392"
    ],
    "placetype": [
      "aat:300008697"
    ],
    "id": 2741299,
    "name:xx": "Upper White Blotch Spring"
  }
}
