{
  "geometry": {
    "type": "Point",
    "coordinates": [
      31.816667,
      26.55
    ]
  },
  "type": "Feature",
  "properties": {
    "hierarchy": [
      "tgn:7529684",
      "tgn:7001242",
      "tgn:7001311",
      "tgn:7016833",
      "tgn:7029392"
    ],
    "placetype": [
      "aat:300005926"
    ],
    "name:en": "Sīdī Ḩāmid",
    "id": 7529684
  }
}
