{
  "geometry": {
    "type": "Point",
    "coordinates": [
      -94.1667,
      34.3667
    ]
  },
  "type": "Feature",
  "properties": {
    "hierarchy": [
      "tgn:2379016",
      "tgn:1000001",
      "tgn:7016172",
      "tgn:7012149",
      "tgn:2000161",
      "tgn:7029392"
    ],
    "placetype": [
      "aat:300008347"
    ],
    "id": 2379016,
    "name:xx": "Hartley"
  }
}
