{
  "geometry": {
    "type": "Point",
    "coordinates": [
      -111.8167,
      46.9833
    ]
  },
  "type": "Feature",
  "properties": {
    "hierarchy": [
      "tgn:2339389",
      "tgn:1000001",
      "tgn:7012149",
      "tgn:2001284",
      "tgn:7007524",
      "tgn:7029392"
    ],
    "placetype": [
      "aat:300008706"
    ],
    "id": 2339389,
    "name:xx": "Frazier Creek"
  }
}
