{
  "geometry": {
    "type": "Point",
    "coordinates": [
      -73.7667,
      42.9333
    ]
  },
  "type": "Feature",
  "properties": {
    "hierarchy": [
      "tgn:2070373",
      "tgn:1000001",
      "tgn:7012149",
      "tgn:1002871",
      "tgn:7007568",
      "tgn:7029392"
    ],
    "placetype": [
      "aat:300008347"
    ],
    "id": 2070373,
    "name:xx": "Maltaville"
  }
}
