{
  "geometry": {
    "type": "Point",
    "coordinates": [
      -81.6667,
      35.55
    ]
  },
  "type": "Feature",
  "properties": {
    "hierarchy": [
      "tgn:2612311",
      "tgn:1000001",
      "tgn:2001484",
      "tgn:7012149",
      "tgn:7007709",
      "tgn:7029392"
    ],
    "placetype": [
      "aat:300266640"
    ],
    "id": 2612311,
    "name:xx": "Red Spur"
  }
}
