{
  "type": "FeatureCollection",
  "features": [
    {
      "geometry": {
        "type": "Point",
        "coordinates": [
          -3.283333,
          57.466667
        ]
      },
      "type": "Feature",
      "properties": {
        "hierarchy": [
          "tgn:7466400",
          "tgn:7002444",
          "tgn:1000003",
          "tgn:5000451",
          "tgn:7008591",
          "tgn:7029392"
        ],
        "placetype": [
          "aat:300008347"
        ],
        "name:en": "Archiestown",
        "id": 7466400
      }
    },
    {
      "geometry": {
        "type": "Point",
        "coordinates": [
          -2.783333,
          56.033333
        ]
      },
      "type": "Feature",
      "properties": {
        "hierarchy": [
          "tgn:7466401",
          "tgn:7002444",
          "tgn:7019115",
          "tgn:1000003",
          "tgn:7008591",
          "tgn:7029392"
        ],
        "placetype": [
          "aat:300387502"
        ],
        "name:en": "Archerfield",
        "id": 7466401
      }
    },
    {
      "geometry": {
        "type": "Point",
        "coordinates": [
          -2.9,
          55.083333
        ]
      },
      "type": "Feature",
      "properties": {
        "hierarchy": [
          "tgn:7466402",
          "tgn:7002444",
          "tgn:7008074",
          "tgn:1000003",
          "tgn:7008591",
          "tgn:7029392"
        ],
        "placetype": [
          "aat:300008699"
        ],
        "name:en": "Archer Beck",
        "id": 7466402
      }
    },
    {
      "geometry": {
        "type": "Point",
        "coordinates": [
          -4.5,
          53.433333
        ]
      },
      "type": "Feature",
      "properties": {
        "hierarchy": [
          "tgn:7466403",
          "tgn:7008532",
          "tgn:7002443",
          "tgn:1000003",
          "tgn:7008591",
          "tgn:7029392"
        ],
        "placetype": [
          "aat:300008808"
        ],
        "name:en": "Archdeacon Rock",
        "id": 7466403
      }
    },
    {
      "geometry": {
        "type": "Point",
        "coordinates": [
          -1.216667,
          52.216667
        ]
      },
      "type": "Feature",
      "properties": {
        "hierarchy": [
          "tgn:7466405",
          "tgn:7002445",
          "tgn:1000003",
          "tgn:7012031",
          "tgn:7008591",
          "tgn:7029392"
        ],
        "placetype": [
          "aat:300008777"
        ],
        "name:en": "Arbury Hill",
        "id": 7466405
      }
    },
    {
      "geometry": {
        "type": "Point",
        "coordinates": [
          -0.916667,
          51.4
        ]
      },
      "type": "Feature",
      "properties": {
        "hierarchy": [
          "tgn:7466407",
          "tgn:7002445",
          "tgn:1000003",
          "tgn:7026487",
          "tgn:7008591",
          "tgn:7029392"
        ],
        "placetype": [
          "aat:300008347"
        ],
        "name:en": "Arborfield",
        "id": 7466407
      }
    },
    {
      "geometry": {
        "type": "Point",
        "coordinates": [
          -6.5,
          54.616667
        ]
      },
      "type": "Feature",
      "properties": {
        "hierarchy": [
          "tgn:7466408",
          "tgn:7002448",
          "tgn:7019204",
          "tgn:1000003",
          "tgn:7008591",
          "tgn:7029392"
        ],
        "placetype": [
          "aat:300386846"
        ],
        "name:en": "Arboe Point",
        "id": 7466408
      }
    }
  ]
}
