{
  "geometry": {
    "type": "Point",
    "coordinates": [
      120.61,
      23.8128
    ]
  },
  "type": "Feature",
  "properties": {
    "hierarchy": [
      "tgn:7475646",
      "tgn:1000004",
      "tgn:7467799",
      "tgn:1000141",
      "tgn:7029392"
    ],
    "placetype": [
      "aat:300006156"
    ],
    "id": 7475646,
    "name:xx": "Ershui Tifang"
  }
}
