{
  "geometry": {
    "type": "Point",
    "coordinates": [
      101.95,
      16.2833
    ]
  },
  "type": "Feature",
  "properties": {
    "hierarchy": [
      "tgn:1085549",
      "tgn:7000913",
      "tgn:7005193",
      "tgn:1000004",
      "tgn:1000142",
      "tgn:7029392"
    ],
    "placetype": [
      "aat:300008347"
    ],
    "id": 1085549,
    "name:xx": "Kaset Sombun"
  }
}
