{
  "geometry": {
    "type": "Point",
    "coordinates": [
      -85.0333,
      44.4833
    ]
  },
  "type": "Feature",
  "properties": {
    "hierarchy": [
      "tgn:2145660",
      "tgn:1000001",
      "tgn:7012149",
      "tgn:2000980",
      "tgn:7007520",
      "tgn:7029392"
    ],
    "placetype": [
      "aat:300008798"
    ],
    "id": 2145660,
    "name:xx": "Baldy"
  }
}
