{
  "geometry": {
    "type": "Point",
    "coordinates": [
      -115.15,
      47.4333
    ]
  },
  "type": "Feature",
  "properties": {
    "hierarchy": [
      "tgn:2760470",
      "tgn:1000001",
      "tgn:7012149",
      "tgn:2001304",
      "tgn:7007524",
      "tgn:7029392"
    ],
    "placetype": [
      "aat:300008706"
    ],
    "id": 2760470,
    "name:xx": "West Fork Swamp Creek"
  }
}
