{
  "geometry": {
    "type": "Point",
    "coordinates": [
      89.863973,
      26.251677
    ]
  },
  "type": "Feature",
  "properties": {
    "hierarchy": [
      "tgn:7566594",
      "tgn:1000004",
      "tgn:1001832",
      "tgn:7000198",
      "tgn:7029392"
    ],
    "placetype": [
      "aat:300008795"
    ],
    "name:en": "Alakjhāri Pahār",
    "id": 7566594
  }
}
