{
  "geometry": {
    "type": "Point",
    "coordinates": [
      -98.9833,
      44.3333
    ]
  },
  "type": "Feature",
  "properties": {
    "hierarchy": [
      "tgn:2707550",
      "tgn:1000001",
      "tgn:2001799",
      "tgn:7012149",
      "tgn:7007713",
      "tgn:7029392"
    ],
    "placetype": [
      "aat:300008347"
    ],
    "id": 2707550,
    "name:xx": "Sweetland"
  }
}
