{
  "geometry": {
    "type": "Point",
    "coordinates": [
      -76.3833,
      34.95
    ]
  },
  "type": "Feature",
  "properties": {
    "hierarchy": [
      "tgn:2506111",
      "tgn:1000001",
      "tgn:2001477",
      "tgn:7012149",
      "tgn:7007709",
      "tgn:7029392"
    ],
    "placetype": [
      "aat:300008850"
    ],
    "id": 2506111,
    "name:xx": "Merkle Bay Point"
  }
}
