{
  "geometry": {
    "type": "Point",
    "coordinates": [
      29.29,
      -24.95
    ]
  },
  "type": "Feature",
  "properties": {
    "hierarchy": [
      "tgn:1093354",
      "tgn:7001242",
      "tgn:7017574",
      "tgn:1000193",
      "tgn:7029392"
    ],
    "placetype": [
      "aat:300008347"
    ],
    "id": 1093354,
    "name:xx": "Marble Hall"
  }
}
