{
  "geometry": {
    "type": "Point",
    "coordinates": [
      -87.8667,
      41.15
    ]
  },
  "type": "Feature",
  "properties": {
    "hierarchy": [
      "tgn:1002532",
      "tgn:1000001",
      "tgn:7012149",
      "tgn:7007251",
      "tgn:7029392"
    ],
    "placetype": [
      "aat:300387145",
      "aat:300000771"
    ],
    "id": 1002532,
    "name:xx": "Kankakee"
  }
}
