{
  "type": "FeatureCollection",
  "features": [
    {
      "geometry": {
        "type": "Point",
        "coordinates": [
          -111.4833,
          47.75
        ]
      },
      "type": "Feature",
      "properties": {
        "hierarchy": [
          "tgn:7022920",
          "tgn:1000001",
          "tgn:7012149",
          "tgn:7007524",
          "tgn:7029392"
        ],
        "placetype": [
          "aat:300008761"
        ],
        "id": 7022920,
        "name:xx": "Rye Coulee"
      }
    },
    {
      "geometry": {
        "type": "Point",
        "coordinates": [
          -81.7167,
          37.7
        ]
      },
      "type": "Feature",
      "properties": {
        "hierarchy": [
          "tgn:7022921",
          "tgn:1000001",
          "tgn:7012149",
          "tgn:7013961",
          "tgn:7029392"
        ],
        "placetype": [
          "aat:300008699"
        ],
        "id": 7022921,
        "name:xx": "Elk Trace Branch"
      }
    },
    {
      "geometry": {
        "type": "Point",
        "coordinates": [
          -112.0333,
          41.15
        ]
      },
      "type": "Feature",
      "properties": {
        "hierarchy": [
          "tgn:7022922",
          "tgn:1000001",
          "tgn:2002106",
          "tgn:7012149",
          "tgn:7007827",
          "tgn:7029392"
        ],
        "placetype": [
          "aat:300008347"
        ],
        "id": 7022922,
        "name:xx": "Eves Garden"
      }
    },
    {
      "geometry": {
        "type": "Point",
        "coordinates": [
          -118.3,
          39.15
        ]
      },
      "type": "Feature",
      "properties": {
        "hierarchy": [
          "tgn:7022923",
          "tgn:1000001",
          "tgn:7012149",
          "tgn:7007526",
          "tgn:7029392"
        ],
        "placetype": [
          "aat:300000390"
        ],
        "id": 7022923,
        "name:xx": "Eagleville Mine"
      }
    },
    {
      "geometry": {
        "type": "Point",
        "coordinates": [
          -80.5,
          41.6833
        ]
      },
      "type": "Feature",
      "properties": {
        "hierarchy": [
          "tgn:7022924",
          "tgn:1000001",
          "tgn:7012149",
          "tgn:7029392"
        ],
        "placetype": [
          "aat:300008707"
        ],
        "id": 7022924,
        "name:xx": "East Branch Ashtabula River"
      }
    },
    {
      "geometry": {
        "type": "Point",
        "coordinates": [
          -81.2333,
          41.5833
        ]
      },
      "type": "Feature",
      "properties": {
        "hierarchy": [
          "tgn:7022925",
          "tgn:1000001",
          "tgn:7012149",
          "tgn:7007706",
          "tgn:7029392"
        ],
        "placetype": [
          "aat:300008707"
        ],
        "id": 7022925,
        "name:xx": "East Branch Chagrin River"
      }
    },
    {
      "geometry": {
        "type": "Point",
        "coordinates": [
          -80.4167,
          41.75
        ]
      },
      "type": "Feature",
      "properties": {
        "hierarchy": [
          "tgn:7022926",
          "tgn:1000001",
          "tgn:7012149",
          "tgn:7007710",
          "tgn:7029392"
        ],
        "placetype": [
          "aat:300008706"
        ],
        "id": 7022926,
        "name:xx": "East Branch Conneaut Creek"
      }
    },
    {
      "geometry": {
        "type": "Point",
        "coordinates": [
          -76.5167,
          40.6
        ]
      },
      "type": "Feature",
      "properties": {
        "hierarchy": [
          "tgn:7022927",
          "tgn:1000001",
          "tgn:7012149",
          "tgn:7007710",
          "tgn:7029392"
        ],
        "placetype": [
          "aat:300008706"
        ],
        "id": 7022927,
        "name:xx": "East Branch Rausch Creek"
      }
    },
    {
      "geometry": {
        "type": "Point",
        "coordinates": [
          -111.7833,
          33.4
        ]
      },
      "type": "Feature",
      "properties": {
        "hierarchy": [
          "tgn:7022928",
          "tgn:1000001",
          "tgn:7006451",
          "tgn:7012149",
          "tgn:2000097",
          "tgn:7029392"
        ],
        "placetype": [
          "aat:300006075"
        ],
        "id": 7022928,
        "name:xx": "Eastern, Canal"
      }
    },
    {
      "geometry": {
        "type": "Point",
        "coordinates": [
          -104,
          48.4667
        ]
      },
      "type": "Feature",
      "properties": {
        "hierarchy": [
          "tgn:7022929",
          "tgn:1000001",
          "tgn:7012149",
          "tgn:7029392"
        ],
        "placetype": [
          "aat:300008706"
        ],
        "id": 7022929,
        "name:xx": "East Fork Brush Mountain Creek"
      }
    }
  ]
}
