{
  "geometry": {
    "type": "Point",
    "coordinates": [
      -82.1333,
      36.4333
    ]
  },
  "type": "Feature",
  "properties": {
    "hierarchy": [
      "tgn:2248518",
      "tgn:1000001",
      "tgn:7012149",
      "tgn:2001918",
      "tgn:7007825",
      "tgn:7029392"
    ],
    "placetype": [
      "aat:300008699"
    ],
    "id": 2248518,
    "name:xx": "Cold Spring Branch"
  }
}
