{
  "geometry": {
    "type": "Point",
    "coordinates": [
      79.816667,
      10.65
    ]
  },
  "type": "Feature",
  "properties": {
    "hierarchy": [
      "tgn:7581501",
      "tgn:1000004",
      "tgn:7000198",
      "tgn:7001797",
      "tgn:7029392"
    ],
    "placetype": [
      "aat:300008699"
    ],
    "name:en": "Vellār River",
    "id": 7581501
  }
}
