{
  "type": "FeatureCollection",
  "features": [
    {
      "geometry": {
        "type": "Point",
        "coordinates": [
          -116.266667,
          30.966667
        ]
      },
      "type": "Feature",
      "properties": {
        "hierarchy": [
          "tgn:7396820",
          "tgn:1001835",
          "tgn:1000001",
          "tgn:7005560",
          "tgn:7029392"
        ],
        "placetype": [
          "aat:300008699"
        ],
        "id": 7396820,
        "name:xx": "San Rafael, Río"
      }
    },
    {
      "geometry": {
        "type": "Point",
        "coordinates": [
          -112.034722,
          31.186111
        ]
      },
      "type": "Feature",
      "properties": {
        "hierarchy": [
          "tgn:7396821",
          "tgn:1000001",
          "tgn:1001960",
          "tgn:7005560",
          "tgn:7029392"
        ],
        "placetype": [
          "aat:300008347"
        ],
        "id": 7396821,
        "name:xx": "San Rafael"
      }
    },
    {
      "geometry": {
        "type": "Point",
        "coordinates": [
          -116.066667,
          31.083333
        ]
      },
      "type": "Feature",
      "properties": {
        "hierarchy": [
          "tgn:7396822",
          "tgn:1001835",
          "tgn:1000001",
          "tgn:7005560",
          "tgn:7029392"
        ],
        "placetype": [
          "aat:300000241"
        ],
        "id": 7396822,
        "name:xx": "Rancho San Rafael"
      }
    },
    {
      "geometry": {
        "type": "Point",
        "coordinates": [
          -109.516667,
          30.966667
        ]
      },
      "type": "Feature",
      "properties": {
        "hierarchy": [
          "tgn:7396823",
          "tgn:1000001",
          "tgn:1001960",
          "tgn:7005560",
          "tgn:7029392"
        ],
        "placetype": [
          "aat:300000241"
        ],
        "id": 7396823,
        "name:xx": "Rancho San Rafael"
      }
    },
    {
      "geometry": {
        "type": "Point",
        "coordinates": [
          -110.9,
          28.416667
        ]
      },
      "type": "Feature",
      "properties": {
        "hierarchy": [
          "tgn:7396824",
          "tgn:1000001",
          "tgn:1001960",
          "tgn:7005560",
          "tgn:7029392"
        ],
        "placetype": [
          "aat:300000241"
        ],
        "id": 7396824,
        "name:xx": "Rancho San Rafael"
      }
    },
    {
      "geometry": {
        "type": "Point",
        "coordinates": [
          -101.883333,
          28.316667
        ]
      },
      "type": "Feature",
      "properties": {
        "hierarchy": [
          "tgn:7396825",
          "tgn:1001853",
          "tgn:1000001",
          "tgn:7005560",
          "tgn:7029392"
        ],
        "placetype": [
          "aat:300000241"
        ],
        "id": 7396825,
        "name:xx": "Rancho San Rafael"
      }
    },
    {
      "geometry": {
        "type": "Point",
        "coordinates": [
          -105.716667,
          28.15
        ]
      },
      "type": "Feature",
      "properties": {
        "hierarchy": [
          "tgn:7396826",
          "tgn:7005581",
          "tgn:1000001",
          "tgn:7005560",
          "tgn:7029392"
        ],
        "placetype": [
          "aat:300000241"
        ],
        "id": 7396826,
        "name:xx": "Rancho San Rafael"
      }
    },
    {
      "geometry": {
        "type": "Point",
        "coordinates": [
          -103.666667,
          28.083333
        ]
      },
      "type": "Feature",
      "properties": {
        "hierarchy": [
          "tgn:7396827",
          "tgn:1001853",
          "tgn:1000001",
          "tgn:7005560",
          "tgn:7029392"
        ],
        "placetype": [
          "aat:300000241"
        ],
        "id": 7396827,
        "name:xx": "Rancho San Rafael"
      }
    },
    {
      "geometry": {
        "type": "Point",
        "coordinates": [
          -108.616667,
          27.533333
        ]
      },
      "type": "Feature",
      "properties": {
        "hierarchy": [
          "tgn:7396828",
          "tgn:1000001",
          "tgn:1001960",
          "tgn:7005560",
          "tgn:7029392"
        ],
        "placetype": [
          "aat:300000241"
        ],
        "id": 7396828,
        "name:xx": "Rancho San Rafael"
      }
    },
    {
      "geometry": {
        "type": "Point",
        "coordinates": [
          -97.716667,
          19.933333
        ]
      },
      "type": "Feature",
      "properties": {
        "hierarchy": [
          "tgn:7396829",
          "tgn:1000001",
          "tgn:7005592",
          "tgn:7005560",
          "tgn:7029392"
        ],
        "placetype": [
          "aat:300008347"
        ],
        "id": 7396829,
        "name:xx": "San Miguel Acateno"
      }
    }
  ]
}
