{
  "geometry": {
    "type": "Point",
    "coordinates": [
      -77.0167,
      38.25
    ]
  },
  "type": "Feature",
  "properties": {
    "hierarchy": [
      "tgn:2112899",
      "tgn:1000001",
      "tgn:7012149",
      "tgn:1003018",
      "tgn:7007919",
      "tgn:7029392"
    ],
    "placetype": [
      "aat:300008347",
      "aat:300387210"
    ],
    "id": 2112899,
    "name:xx": "Maple Grove"
  }
}
