{
  "geometry": {
    "type": "Point",
    "coordinates": [
      -85.4167,
      43.9667
    ]
  },
  "type": "Feature",
  "properties": {
    "hierarchy": [
      "tgn:2622807",
      "tgn:1000001",
      "tgn:7012149",
      "tgn:2000987",
      "tgn:7007520",
      "tgn:7029392"
    ],
    "placetype": [
      "aat:300008680"
    ],
    "id": 2622807,
    "name:xx": "Robinson Lake"
  }
}
