{
  "geometry": {
    "type": "Point",
    "coordinates": [
      -81.8167,
      38.1833
    ]
  },
  "type": "Feature",
  "properties": {
    "hierarchy": [
      "tgn:2287313",
      "tgn:1000001",
      "tgn:7012149",
      "tgn:7013961",
      "tgn:7029392"
    ],
    "placetype": [
      "aat:300008706"
    ],
    "id": 2287313,
    "name:xx": "Dicks Creek"
  }
}
