{
  "geometry": {
    "type": "Point",
    "coordinates": [
      -68.3333,
      44.4167
    ]
  },
  "type": "Feature",
  "properties": {
    "hierarchy": [
      "tgn:2415619",
      "tgn:1000001",
      "tgn:2000922",
      "tgn:7012149",
      "tgn:7007515",
      "tgn:7029392"
    ],
    "placetype": [
      "aat:300008850"
    ],
    "id": 2415619,
    "name:xx": "Israel Point"
  }
}
