{
  "geometry": {
    "type": "Point",
    "coordinates": [
      -88.05,
      47.4667
    ]
  },
  "type": "Feature",
  "properties": {
    "hierarchy": [
      "tgn:2126641",
      "tgn:1000001",
      "tgn:7012149",
      "tgn:2000969",
      "tgn:7007520",
      "tgn:7029392"
    ],
    "placetype": [
      "aat:300132316"
    ],
    "id": 2126641,
    "name:xx": "Agate Harbor"
  }
}
