{
  "type": "FeatureCollection",
  "features": [
    {
      "geometry": {
        "type": "Point",
        "coordinates": [
          28.0333,
          -26.1667
        ]
      },
      "type": "Feature",
      "properties": {
        "hierarchy": [
          "tgn:1102860",
          "tgn:7001242",
          "tgn:7017576",
          "tgn:1000193",
          "tgn:7029392"
        ],
        "placetype": [
          "aat:300008187"
        ],
        "id": 1102860,
        "name:xx": "Hermann Eckstein Park"
      }
    },
    {
      "geometry": {
        "type": "Point",
        "coordinates": [
          -70.9,
          42.5
        ]
      },
      "type": "Feature",
      "properties": {
        "hierarchy": [
          "tgn:1102863",
          "tgn:1000001",
          "tgn:1002359",
          "tgn:7012149",
          "tgn:7007517",
          "tgn:7029392"
        ],
        "placetype": [
          "aat:300008187"
        ],
        "id": 1102863,
        "name:xx": "Highland Park"
      }
    },
    {
      "geometry": {
        "type": "Point",
        "coordinates": [
          -83.4,
          42.3333
        ]
      },
      "type": "Feature",
      "properties": {
        "hierarchy": [
          "tgn:1102865",
          "tgn:1000001",
          "tgn:7012149",
          "tgn:1003005",
          "tgn:7007520",
          "tgn:7029392"
        ],
        "placetype": [
          "aat:300008187"
        ],
        "id": 1102865,
        "name:xx": "Holliday Park"
      }
    },
    {
      "geometry": {
        "type": "Point",
        "coordinates": [
          121.4667,
          31.2667
        ]
      },
      "type": "Feature",
      "properties": {
        "hierarchy": [
          "tgn:1102866",
          "tgn:1000004",
          "tgn:1000958",
          "tgn:1000111",
          "tgn:7029392"
        ],
        "placetype": [
          "aat:300008187"
        ],
        "id": 1102866,
        "name:xx": "Hongkou Park"
      }
    },
    {
      "geometry": {
        "type": "Point",
        "coordinates": [
          -122.2833,
          37.4333
        ]
      },
      "type": "Feature",
      "properties": {
        "hierarchy": [
          "tgn:1102867",
          "tgn:1000001",
          "tgn:7012149",
          "tgn:7007157",
          "tgn:1002864",
          "tgn:7029392"
        ],
        "placetype": [
          "aat:300008187"
        ],
        "id": 1102867,
        "name:xx": "Huddart Park"
      }
    },
    {
      "geometry": {
        "type": "Point",
        "coordinates": [
          -87.7,
          41.9
        ]
      },
      "type": "Feature",
      "properties": {
        "hierarchy": [
          "tgn:1102869",
          "tgn:1000001",
          "tgn:7013596",
          "tgn:7013649",
          "tgn:7012149",
          "tgn:7007251",
          "tgn:7029392"
        ],
        "placetype": [
          "aat:300008187"
        ],
        "id": 1102869,
        "name:xx": "Humboldt Park"
      }
    }
  ]
}
