{
  "geometry": {
    "type": "Point",
    "coordinates": [
      -90.1167,
      34.65
    ]
  },
  "type": "Feature",
  "properties": {
    "hierarchy": [
      "tgn:2313927",
      "tgn:1000001",
      "tgn:7012149",
      "tgn:2001154",
      "tgn:7007522",
      "tgn:7029392"
    ],
    "placetype": [
      "aat:300008347"
    ],
    "id": 2313927,
    "name:xx": "Eliphaz"
  }
}
