{
  "geometry": {
    "type": "Point",
    "coordinates": [
      31.483333,
      29.75
    ]
  },
  "type": "Feature",
  "properties": {
    "hierarchy": [
      "tgn:7529016",
      "tgn:7001242",
      "tgn:7016833",
      "tgn:1001083",
      "tgn:7029392"
    ],
    "placetype": [
      "aat:300379998"
    ],
    "name:en": "Umm Ratamah, Wādī",
    "id": 7529016
  }
}
