{
  "type": "FeatureCollection",
  "features": [
    {
      "geometry": {
        "type": "Point",
        "coordinates": [
          -75.8167,
          38.35
        ]
      },
      "type": "Feature",
      "properties": {
        "hierarchy": [
          "tgn:2369300",
          "tgn:1000001",
          "tgn:1003023",
          "tgn:7012149",
          "tgn:7007516",
          "tgn:7029392"
        ],
        "placetype": [
          "aat:300008347"
        ],
        "id": 2369300,
        "name:xx": "Gum Swamp"
      }
    },
    {
      "geometry": {
        "type": "Point",
        "coordinates": [
          -76.1667,
          38.4167
        ]
      },
      "type": "Feature",
      "properties": {
        "hierarchy": [
          "tgn:2369301",
          "tgn:1002338",
          "tgn:1000001",
          "tgn:7012149",
          "tgn:7007516",
          "tgn:7029392"
        ],
        "placetype": [
          "aat:300008347"
        ],
        "id": 2369301,
        "name:xx": "Gum Swamp"
      }
    },
    {
      "geometry": {
        "type": "Point",
        "coordinates": [
          -76.15,
          38.4167
        ]
      },
      "type": "Feature",
      "properties": {
        "hierarchy": [
          "tgn:2369302",
          "tgn:1002338",
          "tgn:1000001",
          "tgn:7012149",
          "tgn:7007516",
          "tgn:7029392"
        ],
        "placetype": [
          "aat:300008905"
        ],
        "id": 2369302,
        "name:xx": "Gum Swamp"
      }
    },
    {
      "geometry": {
        "type": "Point",
        "coordinates": [
          -76.0667,
          44.0167
        ]
      },
      "type": "Feature",
      "properties": {
        "hierarchy": [
          "tgn:2369303",
          "tgn:1000001",
          "tgn:7012149",
          "tgn:1002518",
          "tgn:7007568",
          "tgn:7029392"
        ],
        "placetype": [
          "aat:300008905"
        ],
        "id": 2369303,
        "name:xx": "Gum Swamp"
      }
    },
    {
      "geometry": {
        "type": "Point",
        "coordinates": [
          -77.4333,
          35.2
        ]
      },
      "type": "Feature",
      "properties": {
        "hierarchy": [
          "tgn:2369304",
          "tgn:1000001",
          "tgn:7012149",
          "tgn:2001486",
          "tgn:7007709",
          "tgn:7029392"
        ],
        "placetype": [
          "aat:300008699"
        ],
        "id": 2369304,
        "name:xx": "Gum Swamp"
      }
    },
    {
      "geometry": {
        "type": "Point",
        "coordinates": [
          -78.8167,
          35.2833
        ]
      },
      "type": "Feature",
      "properties": {
        "hierarchy": [
          "tgn:2369305",
          "tgn:1000001",
          "tgn:7012149",
          "tgn:2001502",
          "tgn:7007709",
          "tgn:7029392"
        ],
        "placetype": [
          "aat:300008699"
        ],
        "id": 2369305,
        "name:xx": "Gum Swamp"
      }
    },
    {
      "geometry": {
        "type": "Point",
        "coordinates": [
          -78.4833,
          35.45
        ]
      },
      "type": "Feature",
      "properties": {
        "hierarchy": [
          "tgn:2369306",
          "tgn:1000001",
          "tgn:7012149",
          "tgn:2001509",
          "tgn:7007709",
          "tgn:7029392"
        ],
        "placetype": [
          "aat:300008699"
        ],
        "id": 2369306,
        "name:xx": "Gum Swamp"
      }
    },
    {
      "geometry": {
        "type": "Point",
        "coordinates": [
          -77.45,
          35.55
        ]
      },
      "type": "Feature",
      "properties": {
        "hierarchy": [
          "tgn:2369307",
          "tgn:1000001",
          "tgn:7012149",
          "tgn:2001530",
          "tgn:7007709",
          "tgn:7029392"
        ],
        "placetype": [
          "aat:300008699"
        ],
        "id": 2369307,
        "name:xx": "Gum Swamp"
      }
    },
    {
      "geometry": {
        "type": "Point",
        "coordinates": [
          -77.05,
          35.6833
        ]
      },
      "type": "Feature",
      "properties": {
        "hierarchy": [
          "tgn:2369308",
          "tgn:1000001",
          "tgn:7012149",
          "tgn:7007709",
          "tgn:7029392"
        ],
        "placetype": [
          "aat:300008699"
        ],
        "id": 2369308,
        "name:xx": "Gum Swamp"
      }
    },
    {
      "geometry": {
        "type": "Point",
        "coordinates": [
          -78.9167,
          34.2167
        ]
      },
      "type": "Feature",
      "properties": {
        "hierarchy": [
          "tgn:2369309",
          "tgn:1000001",
          "tgn:2001485",
          "tgn:7012149",
          "tgn:7007709",
          "tgn:7029392"
        ],
        "placetype": [
          "aat:300008699"
        ],
        "id": 2369309,
        "name:xx": "Gum Swamp"
      }
    }
  ]
}
