{
  "geometry": {
    "type": "Point",
    "coordinates": [
      -70.8167,
      44.2167
    ]
  },
  "type": "Feature",
  "properties": {
    "hierarchy": [
      "tgn:2730164",
      "tgn:1000001",
      "tgn:7012149",
      "tgn:2000926",
      "tgn:7007515",
      "tgn:7029392"
    ],
    "placetype": [
      "aat:300008680"
    ],
    "id": 2730164,
    "name:xx": "Trout Pond"
  }
}
