{
  "type": "FeatureCollection",
  "features": [
    {
      "geometry": {
        "type": "Point",
        "coordinates": [
          -61,
          14.6667
        ]
      },
      "type": "Feature",
      "properties": {
        "hierarchy": [
          "tgn:7005870",
          "tgn:1000001",
          "tgn:7029392"
        ],
        "placetype": [
          "aat:300387054",
          "aat:300235115",
          "aat:300008791",
          "aat:300387176",
          "aat:300387121"
        ],
        "name:en": "Martinique",
        "id": 7005870
      }
    },
    {
      "geometry": {
        "type": "Point",
        "coordinates": [
          -61.0833,
          14.6
        ]
      },
      "type": "Feature",
      "properties": {
        "hierarchy": [
          "tgn:7005872",
          "tgn:7015038",
          "tgn:1000001",
          "tgn:7005870",
          "tgn:7029392"
        ],
        "placetype": [
          "aat:300008347",
          "aat:300387225",
          "aat:300008389",
          "aat:300387512",
          "aat:300387220",
          "aat:300006909",
          "aat:300120599"
        ],
        "id": 7005872,
        "name:xx": "Fort-de-France"
      }
    },
    {
      "geometry": {
        "type": "Point",
        "coordinates": [
          9.766667,
          45.3
        ]
      },
      "type": "Feature",
      "properties": {
        "hierarchy": [
          "tgn:7005873",
          "tgn:7005869",
          "tgn:1000003",
          "tgn:7003237",
          "tgn:1000080",
          "tgn:7029392"
        ],
        "placetype": [
          "aat:300008347"
        ],
        "id": 7005873,
        "name:xx": "Castelleone"
      }
    },
    {
      "geometry": {
        "type": "Point",
        "coordinates": [
          9.683333,
          45.366667
        ]
      },
      "type": "Feature",
      "properties": {
        "hierarchy": [
          "tgn:7005874",
          "tgn:7005869",
          "tgn:1000003",
          "tgn:7003237",
          "tgn:1000080",
          "tgn:7029392"
        ],
        "placetype": [
          "aat:300008347",
          "aat:300387308",
          "aat:300008375"
        ],
        "id": 7005874,
        "name:xx": "Crema"
      }
    },
    {
      "geometry": {
        "type": "Point",
        "coordinates": [
          9.85,
          45.283333
        ]
      },
      "type": "Feature",
      "properties": {
        "hierarchy": [
          "tgn:7005875",
          "tgn:7005869",
          "tgn:1000003",
          "tgn:7003237",
          "tgn:1000080",
          "tgn:7029392"
        ],
        "placetype": [
          "aat:300008347"
        ],
        "id": 7005875,
        "name:xx": "Soresina"
      }
    },
    {
      "geometry": {
        "type": "Point",
        "coordinates": [
          9.9167,
          45.2333
        ]
      },
      "type": "Feature",
      "properties": {
        "hierarchy": [
          "tgn:7005876",
          "tgn:7005869",
          "tgn:1000003",
          "tgn:7003237",
          "tgn:1000080",
          "tgn:7029392"
        ],
        "placetype": [
          "aat:300008347"
        ],
        "id": 7005876,
        "name:xx": "Paderno"
      }
    },
    {
      "geometry": {
        "type": "Point",
        "coordinates": [
          9.866667,
          45.4
        ]
      },
      "type": "Feature",
      "properties": {
        "hierarchy": [
          "tgn:7005877",
          "tgn:7005869",
          "tgn:1000003",
          "tgn:7003237",
          "tgn:1000080",
          "tgn:7029392"
        ],
        "placetype": [
          "aat:300008347"
        ],
        "id": 7005877,
        "name:xx": "Soncino"
      }
    },
    {
      "geometry": {
        "type": "Point",
        "coordinates": [
          10.433333,
          44.983333
        ]
      },
      "type": "Feature",
      "properties": {
        "hierarchy": [
          "tgn:7005878",
          "tgn:7005869",
          "tgn:1000003",
          "tgn:7003237",
          "tgn:1000080",
          "tgn:7029392"
        ],
        "placetype": [
          "aat:300008347"
        ],
        "id": 7005878,
        "name:xx": "Casalmaggiore"
      }
    },
    {
      "geometry": {
        "type": "Point",
        "coordinates": [
          10.8,
          45.15
        ]
      },
      "type": "Feature",
      "properties": {
        "hierarchy": [
          "tgn:7005879",
          "tgn:7005880",
          "tgn:1000003",
          "tgn:7003237",
          "tgn:1000080",
          "tgn:7029392"
        ],
        "placetype": [
          "aat:300387277",
          "aat:300008347",
          "aat:300008389",
          "aat:300387223",
          "aat:300387270",
          "aat:300387302",
          "aat:300310709",
          "aat:300263063"
        ],
        "name:en": "Mantua",
        "id": 7005879
      }
    }
  ]
}
