{
  "geometry": {
    "type": "Point",
    "coordinates": [
      138.9167,
      -34.7167
    ]
  },
  "type": "Feature",
  "properties": {
    "hierarchy": [
      "tgn:1120496",
      "tgn:7000490",
      "tgn:1000006",
      "tgn:7001831",
      "tgn:7029392"
    ],
    "placetype": [
      "aat:300006191"
    ],
    "id": 1120496,
    "name:xx": "South Warren Reservoir"
  }
}
