{
  "geometry": {
    "type": "Point",
    "coordinates": [
      75.736279,
      28.639517
    ]
  },
  "type": "Feature",
  "properties": {
    "hierarchy": [
      "tgn:7565010",
      "tgn:1000004",
      "tgn:1001871",
      "tgn:7000198",
      "tgn:7029392"
    ],
    "placetype": [
      "aat:300008347"
    ],
    "name:en": "Lādāwās",
    "id": 7565010
  }
}
