{
  "type": "FeatureCollection",
  "features": [
    {
      "geometry": {
        "type": "Point",
        "coordinates": [
          -93.233333,
          18.283333
        ]
      },
      "type": "Feature",
      "properties": {
        "hierarchy": [
          "tgn:7394941",
          "tgn:1000001",
          "tgn:7005596",
          "tgn:7005560",
          "tgn:7029392"
        ],
        "placetype": [
          "aat:300008347"
        ],
        "id": 7394941,
        "name:xx": "San Isidro"
      }
    },
    {
      "geometry": {
        "type": "Point",
        "coordinates": [
          -91.533333,
          18.233333
        ]
      },
      "type": "Feature",
      "properties": {
        "hierarchy": [
          "tgn:7394942",
          "tgn:7005578",
          "tgn:1000001",
          "tgn:7005560",
          "tgn:7029392"
        ],
        "placetype": [
          "aat:300008347"
        ],
        "id": 7394942,
        "name:xx": "San Isidro"
      }
    },
    {
      "geometry": {
        "type": "Point",
        "coordinates": [
          -93.666667,
          18.066667
        ]
      },
      "type": "Feature",
      "properties": {
        "hierarchy": [
          "tgn:7394943",
          "tgn:1000001",
          "tgn:7005596",
          "tgn:7005560",
          "tgn:7029392"
        ],
        "placetype": [
          "aat:300008347"
        ],
        "id": 7394943,
        "name:xx": "San Isidro"
      }
    },
    {
      "geometry": {
        "type": "Point",
        "coordinates": [
          -95.416667,
          18
        ]
      },
      "type": "Feature",
      "properties": {
        "hierarchy": [
          "tgn:7394945",
          "tgn:1000001",
          "tgn:7005599",
          "tgn:7005560",
          "tgn:7029392"
        ],
        "placetype": [
          "aat:300008347"
        ],
        "id": 7394945,
        "name:xx": "San Isidro"
      }
    },
    {
      "geometry": {
        "type": "Point",
        "coordinates": [
          -94.633333,
          17.95
        ]
      },
      "type": "Feature",
      "properties": {
        "hierarchy": [
          "tgn:7394946",
          "tgn:1000001",
          "tgn:7005599",
          "tgn:7005560",
          "tgn:7029392"
        ],
        "placetype": [
          "aat:300008347"
        ],
        "id": 7394946,
        "name:xx": "San Isidro"
      }
    },
    {
      "geometry": {
        "type": "Point",
        "coordinates": [
          -92.05,
          17.916667
        ]
      },
      "type": "Feature",
      "properties": {
        "hierarchy": [
          "tgn:7394947",
          "tgn:1000001",
          "tgn:7005596",
          "tgn:7005560",
          "tgn:7029392"
        ],
        "placetype": [
          "aat:300008347"
        ],
        "id": 7394947,
        "name:xx": "San Isidro"
      }
    },
    {
      "geometry": {
        "type": "Point",
        "coordinates": [
          -93.083333,
          17.783333
        ]
      },
      "type": "Feature",
      "properties": {
        "hierarchy": [
          "tgn:7394948",
          "tgn:7005580",
          "tgn:1000001",
          "tgn:7005560",
          "tgn:7029392"
        ],
        "placetype": [
          "aat:300008347"
        ],
        "id": 7394948,
        "name:xx": "San Isidro"
      }
    }
  ]
}
