{
  "geometry": {
    "type": "Point",
    "coordinates": [
      -78.3167,
      39.2833
    ]
  },
  "type": "Feature",
  "properties": {
    "hierarchy": [
      "tgn:2128129",
      "tgn:1000001",
      "tgn:7012149",
      "tgn:2002161",
      "tgn:7007919",
      "tgn:7029392"
    ],
    "placetype": [
      "aat:300008699"
    ],
    "id": 2128129,
    "name:xx": "Albin Run"
  }
}
