{
  "geometry": {
    "type": "Point",
    "coordinates": [
      -121.0167,
      41.7333
    ]
  },
  "type": "Feature",
  "properties": {
    "hierarchy": [
      "tgn:2274618",
      "tgn:1000001",
      "tgn:7012149",
      "tgn:7007157",
      "tgn:2000186",
      "tgn:7029392"
    ],
    "placetype": [
      "aat:300006191"
    ],
    "id": 2274618,
    "name:xx": "Dalton Reservoir"
  }
}
