{
  "geometry": {
    "type": "Point",
    "coordinates": [
      -87.5167,
      45.45
    ]
  },
  "type": "Feature",
  "properties": {
    "hierarchy": [
      "tgn:2746995",
      "tgn:1000001",
      "tgn:7012149",
      "tgn:2000978",
      "tgn:7007520",
      "tgn:7029392"
    ],
    "placetype": [
      "aat:300008680"
    ],
    "id": 2746995,
    "name:xx": "Wagner Lake"
  }
}
