{
  "geometry": {
    "type": "Point",
    "coordinates": [
      -115.7833,
      39.9167
    ]
  },
  "type": "Feature",
  "properties": {
    "hierarchy": [
      "tgn:2383529",
      "tgn:1000001",
      "tgn:7012149",
      "tgn:2001420",
      "tgn:7007526",
      "tgn:7029392"
    ],
    "placetype": [
      "aat:300008697"
    ],
    "id": 2383529,
    "name:xx": "Heath Spring"
  }
}
