{
  "geometry": {
    "type": "Point",
    "coordinates": [
      -111.4333,
      34.6333
    ]
  },
  "type": "Feature",
  "properties": {
    "hierarchy": [
      "tgn:2146715",
      "tgn:1000001",
      "tgn:7006451",
      "tgn:2000092",
      "tgn:7012149",
      "tgn:7029392"
    ],
    "placetype": [
      "aat:300006191"
    ],
    "id": 2146715,
    "name:xx": "Banfield Tank"
  }
}
