{
  "type": "FeatureCollection",
  "features": [
    {
      "geometry": {
        "type": "Point",
        "coordinates": [
          77.1,
          10.733333
        ]
      },
      "type": "Feature",
      "properties": {
        "hierarchy": [
          "tgn:7555880",
          "tgn:1000004",
          "tgn:7000198",
          "tgn:7001797",
          "tgn:7029392"
        ],
        "placetype": [
          "aat:300008347"
        ],
        "name:en": "Periyanegamam",
        "id": 7555880
      }
    },
    {
      "geometry": {
        "type": "Point",
        "coordinates": [
          76.933333,
          11.15
        ]
      },
      "type": "Feature",
      "properties": {
        "hierarchy": [
          "tgn:7555881",
          "tgn:1000004",
          "tgn:7000198",
          "tgn:7001797",
          "tgn:7029392"
        ],
        "placetype": [
          "aat:300008347"
        ],
        "name:en": "Periyanāyakkanpālaiyam",
        "id": 7555881
      }
    },
    {
      "geometry": {
        "type": "Point",
        "coordinates": [
          75.833333,
          11.833333
        ]
      },
      "type": "Feature",
      "properties": {
        "hierarchy": [
          "tgn:7555883",
          "tgn:1000004",
          "tgn:7000198",
          "tgn:1001886",
          "tgn:7029392"
        ],
        "placetype": [
          "aat:300008347"
        ],
        "name:en": "Periya",
        "id": 7555883
      }
    },
    {
      "geometry": {
        "type": "Point",
        "coordinates": [
          76.233333,
          10.983333
        ]
      },
      "type": "Feature",
      "properties": {
        "hierarchy": [
          "tgn:7555884",
          "tgn:1000004",
          "tgn:7000198",
          "tgn:1001886",
          "tgn:7029392"
        ],
        "placetype": [
          "aat:300008347"
        ],
        "name:en": "Perintalmanna",
        "id": 7555884
      }
    },
    {
      "geometry": {
        "type": "Point",
        "coordinates": [
          75.3,
          12.25
        ]
      },
      "type": "Feature",
      "properties": {
        "hierarchy": [
          "tgn:7555885",
          "tgn:1000004",
          "tgn:7000198",
          "tgn:1001886",
          "tgn:7029392"
        ],
        "placetype": [
          "aat:300008347"
        ],
        "name:en": "Peringom",
        "id": 7555885
      }
    },
    {
      "geometry": {
        "type": "Point",
        "coordinates": [
          76.483333,
          9.116667
        ]
      },
      "type": "Feature",
      "properties": {
        "hierarchy": [
          "tgn:7555886",
          "tgn:1000004",
          "tgn:7000198",
          "tgn:1001886",
          "tgn:7029392"
        ],
        "placetype": [
          "aat:300008347"
        ],
        "name:en": "Perinād",
        "id": 7555886
      }
    },
    {
      "geometry": {
        "type": "Point",
        "coordinates": [
          72.3,
          21.716667
        ]
      },
      "type": "Feature",
      "properties": {
        "hierarchy": [
          "tgn:7555887",
          "tgn:1000004",
          "tgn:1001869",
          "tgn:7000198",
          "tgn:7029392"
        ],
        "placetype": [
          "aat:300011692"
        ],
        "name:en": "Perigee Rock",
        "id": 7555887
      }
    },
    {
      "geometry": {
        "type": "Point",
        "coordinates": [
          76.683333,
          19.3
        ]
      },
      "type": "Feature",
      "properties": {
        "hierarchy": [
          "tgn:7555888",
          "tgn:1000004",
          "tgn:7000198",
          "tgn:1001895",
          "tgn:7029392"
        ],
        "placetype": [
          "aat:300007783"
        ],
        "name:en": "Pergaon",
        "id": 7555888
      }
    }
  ]
}
