{
  "geometry": {
    "type": "Point",
    "coordinates": [
      16.75,
      43.05
    ]
  },
  "type": "Feature",
  "properties": {
    "hierarchy": [
      "tgn:1114175",
      "tgn:1000003",
      "tgn:7006663",
      "tgn:7029392"
    ],
    "placetype": [
      "aat:300008713"
    ],
    "id": 1114175,
    "name:xx": "Korčulanski Kanal"
  }
}
