{
  "geometry": {
    "type": "Point",
    "coordinates": [
      -83.2667,
      37.85
    ]
  },
  "type": "Feature",
  "properties": {
    "hierarchy": [
      "tgn:2278194",
      "tgn:1000001",
      "tgn:7012149",
      "tgn:2000831",
      "tgn:7007255",
      "tgn:7029392"
    ],
    "placetype": [
      "aat:300008699"
    ],
    "id": 2278194,
    "name:xx": "De Board Branch"
  }
}
