{
  "type": "FeatureCollection",
  "features": [
    {
      "geometry": {
        "type": "Point",
        "coordinates": [
          4.65,
          50.8
        ]
      },
      "type": "Feature",
      "properties": {
        "hierarchy": [
          "tgn:1026730",
          "tgn:7018239",
          "tgn:1000003",
          "tgn:1000063",
          "tgn:7018236",
          "tgn:7029392"
        ],
        "placetype": [
          "aat:300008347"
        ],
        "id": 1026730,
        "name:xx": "Sint-Joris-Weert"
      }
    },
    {
      "geometry": {
        "type": "Point",
        "coordinates": [
          4.866667,
          50.916667
        ]
      },
      "type": "Feature",
      "properties": {
        "hierarchy": [
          "tgn:1026731",
          "tgn:7018239",
          "tgn:1000003",
          "tgn:1000063",
          "tgn:7018236",
          "tgn:7029392"
        ],
        "placetype": [
          "aat:300008347"
        ],
        "id": 1026731,
        "name:xx": "Sint-Joris-Winge"
      }
    },
    {
      "geometry": {
        "type": "Point",
        "coordinates": [
          4.5333,
          51.0667
        ]
      },
      "type": "Feature",
      "properties": {
        "hierarchy": [
          "tgn:1026732",
          "tgn:7003456",
          "tgn:1000003",
          "tgn:1000063",
          "tgn:7018236",
          "tgn:7029392"
        ],
        "placetype": [
          "aat:300008347"
        ],
        "id": 1026732,
        "name:xx": "Saint-Katelijne-Waver"
      }
    },
    {
      "geometry": {
        "type": "Point",
        "coordinates": [
          3.211422,
          51.188062
        ]
      },
      "type": "Feature",
      "properties": {
        "hierarchy": [
          "tgn:1026735",
          "tgn:7003458",
          "tgn:1000003",
          "tgn:1000063",
          "tgn:7018236",
          "tgn:7029392"
        ],
        "placetype": [
          "aat:300008347"
        ],
        "id": 1026735,
        "name:xx": "Saint Michiels"
      }
    },
    {
      "geometry": {
        "type": "Point",
        "coordinates": [
          4.243548,
          50.779262
        ]
      },
      "type": "Feature",
      "properties": {
        "hierarchy": [
          "tgn:1026737",
          "tgn:7018239",
          "tgn:1000003",
          "tgn:1000063",
          "tgn:7018236",
          "tgn:7029392"
        ],
        "placetype": [
          "aat:300008347"
        ],
        "id": 1026737,
        "name:xx": "Sint-Pieters-Leeuw"
      }
    },
    {
      "geometry": {
        "type": "Point",
        "coordinates": [
          3.783333,
          50.5
        ]
      },
      "type": "Feature",
      "properties": {
        "hierarchy": [
          "tgn:1026739",
          "tgn:7007877",
          "tgn:1000003",
          "tgn:1000063",
          "tgn:4012014",
          "tgn:7029392"
        ],
        "placetype": [
          "aat:300008347"
        ],
        "id": 1026739,
        "name:xx": "Sirault"
      }
    }
  ]
}
