{
  "geometry": {
    "type": "Point",
    "coordinates": [
      -84.6833,
      44.2167
    ]
  },
  "type": "Feature",
  "properties": {
    "hierarchy": [
      "tgn:2403005",
      "tgn:1000001",
      "tgn:7012149",
      "tgn:7007520",
      "tgn:7029392"
    ],
    "placetype": [
      "aat:300008863"
    ],
    "id": 2403005,
    "name:xx": "Houghton Lake State Forest"
  }
}
