{
  "geometry": {
    "type": "Point",
    "coordinates": [
      -70.2833,
      41.65
    ]
  },
  "type": "Feature",
  "properties": {
    "hierarchy": [
      "tgn:2049957",
      "tgn:1002165",
      "tgn:1000001",
      "tgn:7012149",
      "tgn:7007517",
      "tgn:7029392"
    ],
    "placetype": [
      "aat:300008347"
    ],
    "id": 2049957,
    "name:xx": "Hyannis"
  }
}
