{
  "geometry": {
    "type": "Point",
    "coordinates": [
      -116.7667,
      45.1667
    ]
  },
  "type": "Feature",
  "properties": {
    "hierarchy": [
      "tgn:2501436",
      "tgn:1000001",
      "tgn:7012149",
      "tgn:2001722",
      "tgn:7007708",
      "tgn:7029392"
    ],
    "placetype": [
      "aat:300008697"
    ],
    "id": 2501436,
    "name:xx": "McGraw Spring"
  }
}
