{
  "geometry": {
    "type": "Point",
    "coordinates": [
      -78.9167,
      36.3833
    ]
  },
  "type": "Feature",
  "properties": {
    "hierarchy": [
      "tgn:2498034",
      "tgn:1000001",
      "tgn:7012149",
      "tgn:7029392"
    ],
    "placetype": [
      "aat:300008706"
    ],
    "id": 2498034,
    "name:xx": "Mayo Creek"
  }
}
