{
  "geometry": {
    "type": "Point",
    "coordinates": [
      -7.1667,
      52.1667
    ]
  },
  "type": "Feature",
  "properties": {
    "hierarchy": [
      "tgn:1043038",
      "tgn:7003505",
      "tgn:7001201",
      "tgn:1000003",
      "tgn:1000078",
      "tgn:7029392"
    ],
    "placetype": [
      "aat:300008347"
    ],
    "id": 1043038,
    "name:xx": "Tramore"
  }
}
