{
  "geometry": {
    "type": "Point",
    "coordinates": [
      7.25,
      50.733333
    ]
  },
  "type": "Feature",
  "properties": {
    "hierarchy": [
      "tgn:7076796",
      "tgn:1000003",
      "tgn:7003677",
      "tgn:7000084",
      "tgn:7029392"
    ],
    "placetype": [
      "aat:300055621"
    ],
    "id": 7076796,
    "name:xx": "Pleiser Ländchen"
  }
}
