{
  "geometry": {
    "type": "Point",
    "coordinates": [
      138.4833,
      36.0833
    ]
  },
  "type": "Feature",
  "properties": {
    "hierarchy": [
      "tgn:1080620",
      "tgn:7000895",
      "tgn:1000004",
      "tgn:1001010",
      "tgn:1000120",
      "tgn:7029392"
    ],
    "placetype": [
      "aat:300008347"
    ],
    "id": 1080620,
    "name:xx": "Koumi"
  }
}
