{
  "geometry": {
    "type": "Point",
    "coordinates": [
      12.85,
      48.55
    ]
  },
  "type": "Feature",
  "properties": {
    "hierarchy": [
      "tgn:7145521",
      "tgn:1000003",
      "tgn:7003673",
      "tgn:7000084",
      "tgn:7029392"
    ],
    "placetype": [
      "aat:300000206"
    ],
    "id": 7145521,
    "name:xx": "Knockenthal"
  }
}
