{
  "geometry": {
    "type": "Point",
    "coordinates": [
      -123.1667,
      41.25
    ]
  },
  "type": "Feature",
  "properties": {
    "hierarchy": [
      "tgn:2136883",
      "tgn:1000001",
      "tgn:7012149",
      "tgn:7007157",
      "tgn:2000189",
      "tgn:7029392"
    ],
    "placetype": [
      "aat:300008761"
    ],
    "id": 2136883,
    "name:xx": "Argus Gulch"
  }
}
