{
  "geometry": {
    "type": "Point",
    "coordinates": [
      138.2833,
      -27.6667
    ]
  },
  "type": "Feature",
  "properties": {
    "hierarchy": [
      "tgn:1096660",
      "tgn:7000490",
      "tgn:1000006",
      "tgn:7001831",
      "tgn:7029392"
    ],
    "placetype": [
      "aat:300008347"
    ],
    "id": 1096660,
    "name:xx": "Cowarie"
  }
}
