{
  "geometry": {
    "type": "Point",
    "coordinates": [
      -105.7167,
      44.3667
    ]
  },
  "type": "Feature",
  "properties": {
    "hierarchy": [
      "tgn:2611105",
      "tgn:1000001",
      "tgn:2002367",
      "tgn:7012149",
      "tgn:7007923",
      "tgn:7029392"
    ],
    "placetype": [
      "aat:300008697"
    ],
    "id": 2611105,
    "name:xx": "Red Hill Spring"
  }
}
