{
  "geometry": {
    "type": "Point",
    "coordinates": [
      -72.803,
      2.61
    ]
  },
  "type": "Feature",
  "properties": {
    "hierarchy": [
      "tgn:1124460",
      "tgn:1000050",
      "tgn:1000002",
      "tgn:7029392"
    ],
    "placetype": [
      "aat:300008707"
    ],
    "id": 1124460,
    "name:xx": "Guayabero, Río"
  }
}
