{
  "geometry": {
    "type": "Point",
    "coordinates": [
      -83.1167,
      34.45
    ]
  },
  "type": "Feature",
  "properties": {
    "hierarchy": [
      "tgn:2783281",
      "tgn:1000001",
      "tgn:7012149",
      "tgn:7007248",
      "tgn:7029392"
    ],
    "placetype": [
      "aat:300008699"
    ],
    "id": 2783281,
    "name:xx": "Wrights Branch"
  }
}
