{
  "geometry": {
    "type": "Point",
    "coordinates": [
      -86.9333,
      38.8833
    ]
  },
  "type": "Feature",
  "properties": {
    "hierarchy": [
      "tgn:2425827",
      "tgn:1000001",
      "tgn:2000541",
      "tgn:7012149",
      "tgn:7007252",
      "tgn:7029392"
    ],
    "placetype": [
      "aat:300008798"
    ],
    "id": 2425827,
    "name:xx": "Jolliff Rocks"
  }
}
