{
  "type": "FeatureCollection",
  "features": [
    {
      "geometry": {
        "type": "Point",
        "coordinates": [
          -119.65,
          39.2833
        ]
      },
      "type": "Feature",
      "properties": {
        "hierarchy": [
          "tgn:2729540",
          "tgn:1000001",
          "tgn:7012149",
          "tgn:1002921",
          "tgn:7007526",
          "tgn:7029392"
        ],
        "placetype": [
          "aat:300000390"
        ],
        "id": 2729540,
        "name:xx": "Trojan Mine"
      }
    },
    {
      "geometry": {
        "type": "Point",
        "coordinates": [
          -118.3,
          36.6333
        ]
      },
      "type": "Feature",
      "properties": {
        "hierarchy": [
          "tgn:2729541",
          "tgn:1000001",
          "tgn:7012149",
          "tgn:2000183",
          "tgn:7007157",
          "tgn:7029392"
        ],
        "placetype": [
          "aat:300008798"
        ],
        "id": 2729541,
        "name:xx": "Trojan Peak"
      }
    },
    {
      "geometry": {
        "type": "Point",
        "coordinates": [
          -104.3,
          39.1333
        ]
      },
      "type": "Feature",
      "properties": {
        "hierarchy": [
          "tgn:2729542",
          "tgn:1000001",
          "tgn:7012149",
          "tgn:2000211",
          "tgn:7007158",
          "tgn:7029392"
        ],
        "placetype": [
          "aat:300006191"
        ],
        "id": 2729542,
        "name:xx": "Trojanovich Reservoir"
      }
    },
    {
      "geometry": {
        "type": "Point",
        "coordinates": [
          -134.2,
          56.45
        ]
      },
      "type": "Feature",
      "properties": {
        "hierarchy": [
          "tgn:2729543",
          "tgn:7006450",
          "tgn:1000001",
          "tgn:7012149",
          "tgn:2000088",
          "tgn:7029392"
        ],
        "placetype": [
          "aat:300386853"
        ],
        "id": 2729543,
        "name:xx": "Troller Islands"
      }
    },
    {
      "geometry": {
        "type": "Point",
        "coordinates": [
          -134.2,
          56.4667
        ]
      },
      "type": "Feature",
      "properties": {
        "hierarchy": [
          "tgn:2729544",
          "tgn:7006450",
          "tgn:1000001",
          "tgn:7012149",
          "tgn:2000088",
          "tgn:7029392"
        ],
        "placetype": [
          "aat:300008850"
        ],
        "id": 2729544,
        "name:xx": "Troller Point"
      }
    },
    {
      "geometry": {
        "type": "Point",
        "coordinates": [
          -122.7167,
          46.8
        ]
      },
      "type": "Feature",
      "properties": {
        "hierarchy": [
          "tgn:2729545",
          "tgn:1000001",
          "tgn:7012149",
          "tgn:1002942",
          "tgn:7007920",
          "tgn:7029392"
        ],
        "placetype": [
          "aat:300008699"
        ],
        "id": 2729545,
        "name:xx": "Troller Run"
      }
    },
    {
      "geometry": {
        "type": "Point",
        "coordinates": [
          -132.2,
          55.35
        ]
      },
      "type": "Feature",
      "properties": {
        "hierarchy": [
          "tgn:2729546",
          "tgn:7006450",
          "tgn:1000001",
          "tgn:7012149",
          "tgn:2000082",
          "tgn:7029392"
        ],
        "placetype": [
          "aat:300132316"
        ],
        "id": 2729546,
        "name:xx": "Trollers Cove"
      }
    },
    {
      "geometry": {
        "type": "Point",
        "coordinates": [
          -131.7833,
          55.45
        ]
      },
      "type": "Feature",
      "properties": {
        "hierarchy": [
          "tgn:2729547",
          "tgn:7006450",
          "tgn:1000001",
          "tgn:2124076",
          "tgn:7012149",
          "tgn:7029392"
        ],
        "placetype": [
          "aat:300008706"
        ],
        "id": 2729547,
        "name:xx": "Trollers Creek"
      }
    },
    {
      "geometry": {
        "type": "Point",
        "coordinates": [
          -93.15,
          45.6667
        ]
      },
      "type": "Feature",
      "properties": {
        "hierarchy": [
          "tgn:2729548",
          "tgn:1000001",
          "tgn:7012149",
          "tgn:2001028",
          "tgn:7007521",
          "tgn:7029392"
        ],
        "placetype": [
          "aat:300008680"
        ],
        "id": 2729548,
        "name:xx": "Trollin Lake"
      }
    }
  ]
}
