{
  "geometry": {
    "type": "Point",
    "coordinates": [
      120.1333,
      16.0333
    ]
  },
  "type": "Feature",
  "properties": {
    "hierarchy": [
      "tgn:1120983",
      "tgn:1000004",
      "tgn:7016720",
      "tgn:1000135",
      "tgn:7029392"
    ],
    "placetype": [
      "aat:300008707"
    ],
    "id": 1120983,
    "name:xx": "Agno"
  }
}
