{
  "geometry": {
    "type": "Point",
    "coordinates": [
      -75.7833,
      39.0333
    ]
  },
  "type": "Feature",
  "properties": {
    "hierarchy": [
      "tgn:2047279",
      "tgn:1002234",
      "tgn:1000001",
      "tgn:7012149",
      "tgn:7007516",
      "tgn:7029392"
    ],
    "placetype": [
      "aat:300008347"
    ],
    "id": 2047279,
    "name:xx": "Goldsboro"
  }
}
