{
  "geometry": {
    "type": "Point",
    "coordinates": [
      -86.9333,
      33.9667
    ]
  },
  "type": "Feature",
  "properties": {
    "hierarchy": [
      "tgn:2697425",
      "tgn:7002659",
      "tgn:1000001",
      "tgn:7012149",
      "tgn:2000021",
      "tgn:7029392"
    ],
    "placetype": [
      "aat:300008699"
    ],
    "id": 2697425,
    "name:xx": "Stony Lonesome Branch"
  }
}
