{
  "geometry": {
    "type": "Point",
    "coordinates": [
      -110.6167,
      33.1167
    ]
  },
  "type": "Feature",
  "properties": {
    "hierarchy": [
      "tgn:2500673",
      "tgn:1000001",
      "tgn:7006451",
      "tgn:7012149",
      "tgn:7029392"
    ],
    "placetype": [
      "aat:300008699"
    ],
    "id": 2500673,
    "name:xx": "McDougal Wash"
  }
}
