{
  "geometry": {
    "type": "Point",
    "coordinates": [
      -106.5333,
      44.75
    ]
  },
  "type": "Feature",
  "properties": {
    "hierarchy": [
      "tgn:2204522",
      "tgn:1000001",
      "tgn:7012149",
      "tgn:2002381",
      "tgn:7007923",
      "tgn:7029392"
    ],
    "placetype": [
      "aat:300008706"
    ],
    "id": 2204522,
    "name:xx": "Buffalo Creek"
  }
}
