{
  "geometry": {
    "type": "Point",
    "coordinates": [
      -76.9667,
      41.3667
    ]
  },
  "type": "Feature",
  "properties": {
    "hierarchy": [
      "tgn:2756773",
      "tgn:1000001",
      "tgn:7012149",
      "tgn:1002613",
      "tgn:7007710",
      "tgn:7029392"
    ],
    "placetype": [
      "aat:300008798"
    ],
    "id": 2756773,
    "name:xx": "Wells Mountain, The"
  }
}
