{
  "type": "FeatureCollection",
  "features": [
    {
      "geometry": {
        "type": "Point",
        "coordinates": [
          -78.65,
          41.3667
        ]
      },
      "type": "Feature",
      "properties": {
        "hierarchy": [
          "tgn:2093001",
          "tgn:1000001",
          "tgn:7012149",
          "tgn:1002352",
          "tgn:7007710",
          "tgn:7029392"
        ],
        "placetype": [
          "aat:300008347",
          "aat:300387210"
        ],
        "id": 2093001,
        "name:xx": "Shelvey"
      }
    },
    {
      "geometry": {
        "type": "Point",
        "coordinates": [
          -76.2,
          40.8167
        ]
      },
      "type": "Feature",
      "properties": {
        "hierarchy": [
          "tgn:2093002",
          "tgn:1000001",
          "tgn:7012149",
          "tgn:1002876",
          "tgn:7007710",
          "tgn:7029392"
        ],
        "placetype": [
          "aat:300008347"
        ],
        "id": 2093002,
        "name:xx": "Shenandoah"
      }
    },
    {
      "geometry": {
        "type": "Point",
        "coordinates": [
          -76.2,
          40.8167
        ]
      },
      "type": "Feature",
      "properties": {
        "hierarchy": [
          "tgn:2093005",
          "tgn:1000001",
          "tgn:7012149",
          "tgn:1002876",
          "tgn:7007710",
          "tgn:7029392"
        ],
        "placetype": [
          "aat:300008347"
        ],
        "id": 2093005,
        "name:xx": "Shenandoah Heights"
      }
    },
    {
      "geometry": {
        "type": "Point",
        "coordinates": [
          -80.3833,
          41.3667
        ]
      },
      "type": "Feature",
      "properties": {
        "hierarchy": [
          "tgn:2093006",
          "tgn:1000001",
          "tgn:7012149",
          "tgn:1002659",
          "tgn:7007710",
          "tgn:7029392"
        ],
        "placetype": [
          "aat:300008347"
        ],
        "id": 2093006,
        "name:xx": "Shenango"
      }
    },
    {
      "geometry": {
        "type": "Point",
        "coordinates": [
          -76.3833,
          39.8833
        ]
      },
      "type": "Feature",
      "properties": {
        "hierarchy": [
          "tgn:2093008",
          "tgn:1000001",
          "tgn:7012149",
          "tgn:1003047",
          "tgn:7007710",
          "tgn:7029392"
        ],
        "placetype": [
          "aat:300008347"
        ],
        "id": 2093008,
        "name:xx": "Shenks Ferry"
      }
    }
  ]
}
