{
  "geometry": {
    "type": "Point",
    "coordinates": [
      -100.384722,
      26.6875
    ]
  },
  "type": "Feature",
  "properties": {
    "hierarchy": [
      "tgn:7419617",
      "tgn:1000001",
      "tgn:7005589",
      "tgn:7005560",
      "tgn:7029392"
    ],
    "placetype": [
      "aat:300008699"
    ],
    "id": 7419617,
    "name:es": "La Espantosa, Río"
  }
}
