{
  "geometry": {
    "type": "Point",
    "coordinates": [
      -91.0333,
      41.0833
    ]
  },
  "type": "Feature",
  "properties": {
    "hierarchy": [
      "tgn:2035369",
      "tgn:1000001",
      "tgn:7012149",
      "tgn:2000618",
      "tgn:7007253",
      "tgn:7029392"
    ],
    "placetype": [
      "aat:300008347"
    ],
    "id": 2035369,
    "name:xx": "Oakville"
  }
}
