{
  "geometry": {
    "type": "Point",
    "coordinates": [
      -124.0667,
      46.2833
    ]
  },
  "type": "Feature",
  "properties": {
    "hierarchy": [
      "tgn:2279681",
      "tgn:1000001",
      "tgn:7012149",
      "tgn:1002767",
      "tgn:7007920",
      "tgn:7029392"
    ],
    "placetype": [
      "aat:300132316"
    ],
    "id": 2279681,
    "name:xx": "Deadmans Hollow"
  }
}
