{
  "geometry": {
    "type": "Point",
    "coordinates": [
      -81.5167,
      39.1833
    ]
  },
  "type": "Feature",
  "properties": {
    "hierarchy": [
      "tgn:2119232",
      "tgn:1000001",
      "tgn:7012149",
      "tgn:2002303",
      "tgn:7013961",
      "tgn:7029392"
    ],
    "placetype": [
      "aat:300008347"
    ],
    "id": 2119232,
    "name:xx": "Mineralwells"
  }
}
