{
  "geometry": {
    "type": "Point",
    "coordinates": [
      -78.5667,
      34.3167
    ]
  },
  "type": "Feature",
  "properties": {
    "hierarchy": [
      "tgn:2073489",
      "tgn:1000001",
      "tgn:2001485",
      "tgn:7012149",
      "tgn:7007709",
      "tgn:7029392"
    ],
    "placetype": [
      "aat:300008347",
      "aat:300387210"
    ],
    "id": 2073489,
    "name:xx": "Artesia"
  }
}
