{
  "geometry": {
    "type": "Point",
    "coordinates": [
      -94.55,
      39.45
    ]
  },
  "type": "Feature",
  "properties": {
    "hierarchy": [
      "tgn:2438394",
      "tgn:1000001",
      "tgn:7012149",
      "tgn:2001188",
      "tgn:7007523",
      "tgn:7029392"
    ],
    "placetype": [
      "aat:300006191"
    ],
    "id": 2438394,
    "name:xx": "Kings Lake"
  }
}
