{
  "geometry": {
    "type": "Point",
    "coordinates": [
      -89.5833,
      33.2833
    ]
  },
  "type": "Feature",
  "properties": {
    "hierarchy": [
      "tgn:2142976",
      "tgn:1000001",
      "tgn:7012149",
      "tgn:7007522",
      "tgn:7029392"
    ],
    "placetype": [
      "aat:300008706"
    ],
    "id": 2142976,
    "name:xx": "Bagasha Creek"
  }
}
