{
  "type": "FeatureCollection",
  "features": [
    {
      "geometry": {
        "type": "Point",
        "coordinates": [
          -96.9667,
          34.6
        ]
      },
      "type": "Feature",
      "properties": {
        "hierarchy": [
          "tgn:2083700",
          "tgn:1000001",
          "tgn:7012149",
          "tgn:2001672",
          "tgn:7007707",
          "tgn:7029392"
        ],
        "placetype": [
          "aat:300008347",
          "aat:300387210"
        ],
        "id": 2083700,
        "name:xx": "Oak Grove"
      }
    },
    {
      "geometry": {
        "type": "Point",
        "coordinates": [
          -94.8333,
          34.0333
        ]
      },
      "type": "Feature",
      "properties": {
        "hierarchy": [
          "tgn:2083704",
          "tgn:1000001",
          "tgn:7012149",
          "tgn:2001667",
          "tgn:7007707",
          "tgn:7029392"
        ],
        "placetype": [
          "aat:300008347",
          "aat:300387210"
        ],
        "id": 2083704,
        "name:xx": "Oak Hill"
      }
    },
    {
      "geometry": {
        "type": "Point",
        "coordinates": [
          -96.05,
          36.0667
        ]
      },
      "type": "Feature",
      "properties": {
        "hierarchy": [
          "tgn:2083705",
          "tgn:1000001",
          "tgn:7012149",
          "tgn:2001694",
          "tgn:7007707",
          "tgn:7029392"
        ],
        "placetype": [
          "aat:300008347"
        ],
        "id": 2083705,
        "name:xx": "Oakhurst"
      }
    },
    {
      "geometry": {
        "type": "Point",
        "coordinates": [
          -96.7833,
          34.1
        ]
      },
      "type": "Feature",
      "properties": {
        "hierarchy": [
          "tgn:2083708",
          "tgn:1000001",
          "tgn:7012149",
          "tgn:2001670",
          "tgn:7007707",
          "tgn:7029392"
        ],
        "placetype": [
          "aat:300008347"
        ],
        "id": 2083708,
        "name:xx": "Oakland"
      }
    },
    {
      "geometry": {
        "type": "Point",
        "coordinates": [
          -96.6167,
          34.8167
        ]
      },
      "type": "Feature",
      "properties": {
        "hierarchy": [
          "tgn:2083709",
          "tgn:1000001",
          "tgn:7012149",
          "tgn:2001684",
          "tgn:7007707",
          "tgn:7029392"
        ],
        "placetype": [
          "aat:300008347",
          "aat:300387210"
        ],
        "id": 2083709,
        "name:xx": "Oakman"
      }
    }
  ]
}
