{
  "geometry": {
    "type": "Point",
    "coordinates": [
      -110.8833,
      40.35
    ]
  },
  "type": "Feature",
  "properties": {
    "hierarchy": [
      "tgn:2451690",
      "tgn:1000001",
      "tgn:2002107",
      "tgn:7012149",
      "tgn:7007827",
      "tgn:7029392"
    ],
    "placetype": [
      "aat:300008761"
    ],
    "id": 2451690,
    "name:xx": "Little Bear Hollow"
  }
}
