{
  "type": "FeatureCollection",
  "features": [
    {
      "geometry": {
        "type": "Point",
        "coordinates": [
          -116.9667,
          42.7
        ]
      },
      "type": "Feature",
      "properties": {
        "hierarchy": [
          "tgn:2647990",
          "tgn:1000001",
          "tgn:7012149",
          "tgn:7029392"
        ],
        "placetype": [
          "aat:300008761"
        ],
        "id": 2647990,
        "name:xx": "Schoolhouse Gulch"
      }
    },
    {
      "geometry": {
        "type": "Point",
        "coordinates": [
          -110.0167,
          45.6667
        ]
      },
      "type": "Feature",
      "properties": {
        "hierarchy": [
          "tgn:2647991",
          "tgn:1000001",
          "tgn:7012149",
          "tgn:2001308",
          "tgn:7007524",
          "tgn:7029392"
        ],
        "placetype": [
          "aat:300008761"
        ],
        "id": 2647991,
        "name:xx": "Schoolhouse Gulch"
      }
    },
    {
      "geometry": {
        "type": "Point",
        "coordinates": [
          -114.2333,
          46.7667
        ]
      },
      "type": "Feature",
      "properties": {
        "hierarchy": [
          "tgn:2647992",
          "tgn:1000001",
          "tgn:7012149",
          "tgn:2001291",
          "tgn:7007524",
          "tgn:7029392"
        ],
        "placetype": [
          "aat:300008761"
        ],
        "id": 2647992,
        "name:xx": "Schoolhouse Gulch"
      }
    },
    {
      "geometry": {
        "type": "Point",
        "coordinates": [
          -117.2833,
          43.25
        ]
      },
      "type": "Feature",
      "properties": {
        "hierarchy": [
          "tgn:2647993",
          "tgn:1000001",
          "tgn:7012149",
          "tgn:2001718",
          "tgn:7007708",
          "tgn:7029392"
        ],
        "placetype": [
          "aat:300008761"
        ],
        "id": 2647993,
        "name:xx": "Schoolhouse Gulch"
      }
    },
    {
      "geometry": {
        "type": "Point",
        "coordinates": [
          -119.3667,
          44.0833
        ]
      },
      "type": "Feature",
      "properties": {
        "hierarchy": [
          "tgn:2647994",
          "tgn:1000001",
          "tgn:7012149",
          "tgn:2001708",
          "tgn:7007708",
          "tgn:7029392"
        ],
        "placetype": [
          "aat:300008761"
        ],
        "id": 2647994,
        "name:xx": "Schoolhouse Gulch"
      }
    },
    {
      "geometry": {
        "type": "Point",
        "coordinates": [
          -123.3333,
          42.6333
        ]
      },
      "type": "Feature",
      "properties": {
        "hierarchy": [
          "tgn:2647995",
          "tgn:1000001",
          "tgn:7012149",
          "tgn:2001713",
          "tgn:7007708",
          "tgn:7029392"
        ],
        "placetype": [
          "aat:300008761"
        ],
        "id": 2647995,
        "name:xx": "Schoolhouse Gulch"
      }
    },
    {
      "geometry": {
        "type": "Point",
        "coordinates": [
          -123.15,
          42.35
        ]
      },
      "type": "Feature",
      "properties": {
        "hierarchy": [
          "tgn:2647996",
          "tgn:1000001",
          "tgn:7012149",
          "tgn:2001711",
          "tgn:7007708",
          "tgn:7029392"
        ],
        "placetype": [
          "aat:300008761"
        ],
        "id": 2647996,
        "name:xx": "Schoolhouse Gulch"
      }
    },
    {
      "geometry": {
        "type": "Point",
        "coordinates": [
          -104.0333,
          44.3333
        ]
      },
      "type": "Feature",
      "properties": {
        "hierarchy": [
          "tgn:2647997",
          "tgn:1000001",
          "tgn:2001810",
          "tgn:7012149",
          "tgn:7007713",
          "tgn:7029392"
        ],
        "placetype": [
          "aat:300008761"
        ],
        "id": 2647997,
        "name:xx": "Schoolhouse Gulch"
      }
    },
    {
      "geometry": {
        "type": "Point",
        "coordinates": [
          -107.95,
          44.3167
        ]
      },
      "type": "Feature",
      "properties": {
        "hierarchy": [
          "tgn:2647998",
          "tgn:1000001",
          "tgn:2002366",
          "tgn:7012149",
          "tgn:7007923",
          "tgn:7029392"
        ],
        "placetype": [
          "aat:300008761"
        ],
        "id": 2647998,
        "name:xx": "Schoolhouse Gulch"
      }
    },
    {
      "geometry": {
        "type": "Point",
        "coordinates": [
          -104.1,
          44.3333
        ]
      },
      "type": "Feature",
      "properties": {
        "hierarchy": [
          "tgn:2647999",
          "tgn:1000001",
          "tgn:2002370",
          "tgn:7012149",
          "tgn:7007923",
          "tgn:7029392"
        ],
        "placetype": [
          "aat:300008761"
        ],
        "id": 2647999,
        "name:xx": "Schoolhouse Gulch"
      }
    }
  ]
}
