{
  "geometry": {
    "type": "Point",
    "coordinates": [
      -98.75,
      31.4667
    ]
  },
  "type": "Feature",
  "properties": {
    "hierarchy": [
      "tgn:2231847",
      "tgn:1000001",
      "tgn:7012149",
      "tgn:2002042",
      "tgn:7007826",
      "tgn:7029392"
    ],
    "placetype": [
      "aat:300008706"
    ],
    "id": 2231847,
    "name:xx": "Chambers Creek"
  }
}
