{
  "geometry": {
    "type": "Point",
    "coordinates": [
      8.8167,
      39.6333
    ]
  },
  "type": "Feature",
  "properties": {
    "hierarchy": [
      "tgn:1100314",
      "tgn:1001641",
      "tgn:1000003",
      "tgn:7003121",
      "tgn:1000080",
      "tgn:7029392"
    ],
    "placetype": [
      "aat:300006891"
    ],
    "id": 1100314,
    "name:xx": "Monreale, Castello di"
  }
}
