{
  "type": "FeatureCollection",
  "features": [
    {
      "geometry": {
        "type": "Point",
        "coordinates": [
          3.416667,
          50.583333
        ]
      },
      "type": "Feature",
      "properties": {
        "hierarchy": [
          "tgn:7245240",
          "tgn:7007877",
          "tgn:1000003",
          "tgn:1000063",
          "tgn:4012014",
          "tgn:7029392"
        ],
        "placetype": [
          "aat:300008699"
        ],
        "id": 7245240,
        "name:xx": "Barges"
      }
    },
    {
      "geometry": {
        "type": "Point",
        "coordinates": [
          3.383333,
          50.583333
        ]
      },
      "type": "Feature",
      "properties": {
        "hierarchy": [
          "tgn:7245241",
          "tgn:7007877",
          "tgn:1000003",
          "tgn:1000063",
          "tgn:4012014",
          "tgn:7029392"
        ],
        "placetype": [
          "aat:300008347"
        ],
        "id": 7245241,
        "name:xx": "Barges"
      }
    },
    {
      "geometry": {
        "type": "Point",
        "coordinates": [
          5.083333,
          51
        ]
      },
      "type": "Feature",
      "properties": {
        "hierarchy": [
          "tgn:7245242",
          "tgn:7003461",
          "tgn:1000003",
          "tgn:1000063",
          "tgn:7018236",
          "tgn:7029392"
        ],
        "placetype": [
          "aat:300008347"
        ],
        "id": 7245242,
        "name:xx": "Barenberg"
      }
    },
    {
      "geometry": {
        "type": "Point",
        "coordinates": [
          4.316667,
          50.05
        ]
      },
      "type": "Feature",
      "properties": {
        "hierarchy": [
          "tgn:7245243",
          "tgn:7007877",
          "tgn:1000003",
          "tgn:1000063",
          "tgn:4012014",
          "tgn:7029392"
        ],
        "placetype": [
          "aat:300008699"
        ],
        "id": 7245243,
        "name:xx": "Lierrée, Ruisseau"
      }
    },
    {
      "geometry": {
        "type": "Point",
        "coordinates": [
          5.7,
          50.683333
        ]
      },
      "type": "Feature",
      "properties": {
        "hierarchy": [
          "tgn:7245244",
          "tgn:7003460",
          "tgn:1000003",
          "tgn:1000063",
          "tgn:4012014",
          "tgn:7029392"
        ],
        "placetype": [
          "aat:300006909"
        ],
        "id": 7245244,
        "name:xx": "Fort de Barchon"
      }
    },
    {
      "geometry": {
        "type": "Point",
        "coordinates": [
          5.7,
          50.666667
        ]
      },
      "type": "Feature",
      "properties": {
        "hierarchy": [
          "tgn:7245245",
          "tgn:7003460",
          "tgn:1000003",
          "tgn:1000063",
          "tgn:4012014",
          "tgn:7029392"
        ],
        "placetype": [
          "aat:300008347"
        ],
        "id": 7245245,
        "name:xx": "Barchon"
      }
    },
    {
      "geometry": {
        "type": "Point",
        "coordinates": [
          4.891485,
          50.393396
        ]
      },
      "type": "Feature",
      "properties": {
        "hierarchy": [
          "tgn:7245248",
          "tgn:7003466",
          "tgn:1000003",
          "tgn:1000063",
          "tgn:4012014",
          "tgn:7029392"
        ],
        "placetype": [
          "aat:300008863"
        ],
        "id": 7245248,
        "name:xx": "Acremonts, Bois des"
      }
    },
    {
      "geometry": {
        "type": "Point",
        "coordinates": [
          5.216667,
          49.9
        ]
      },
      "type": "Feature",
      "properties": {
        "hierarchy": [
          "tgn:7245249",
          "tgn:7003465",
          "tgn:1000003",
          "tgn:1000063",
          "tgn:4012014",
          "tgn:7029392"
        ],
        "placetype": [
          "aat:300008347"
        ],
        "id": 7245249,
        "name:xx": "Acremont"
      }
    }
  ]
}
