{
  "geometry": {
    "type": "Point",
    "coordinates": [
      -74.7167,
      43.5667
    ]
  },
  "type": "Feature",
  "properties": {
    "hierarchy": [
      "tgn:2246634",
      "tgn:1000001",
      "tgn:7012149",
      "tgn:1002440",
      "tgn:7007568",
      "tgn:7029392"
    ],
    "placetype": [
      "aat:300008706"
    ],
    "id": 2246634,
    "name:xx": "Cobblestone Creek"
  }
}
