{
  "geometry": {
    "type": "Point",
    "coordinates": [
      -107.0833,
      38.9333
    ]
  },
  "type": "Feature",
  "properties": {
    "hierarchy": [
      "tgn:2648479",
      "tgn:1000001",
      "tgn:7012149",
      "tgn:2000217",
      "tgn:7007158",
      "tgn:7029392"
    ],
    "placetype": [
      "aat:300008798"
    ],
    "id": 2648479,
    "name:xx": "Schuylkill Mountain"
  }
}
