{
  "geometry": {
    "type": "Point",
    "coordinates": [
      -70.0833,
      41.65
    ]
  },
  "type": "Feature",
  "properties": {
    "hierarchy": [
      "tgn:2130055",
      "tgn:1002165",
      "tgn:1000001",
      "tgn:7012149",
      "tgn:7007517",
      "tgn:7029392"
    ],
    "placetype": [
      "aat:300008678"
    ],
    "id": 2130055,
    "name:xx": "Allen Harbor"
  }
}
