{
  "geometry": {
    "type": "Point",
    "coordinates": [
      49.6667,
      48.8333
    ]
  },
  "type": "Feature",
  "properties": {
    "hierarchy": [
      "tgn:1126739",
      "tgn:1000003",
      "tgn:7029392"
    ],
    "placetype": [
      "aat:300008707"
    ],
    "id": 1126739,
    "name:xx": "Malyy Uzen"
  }
}
