{
  "type": "FeatureCollection",
  "features": [
    {
      "geometry": {
        "type": "Point",
        "coordinates": [
          -81.1,
          38.1833
        ]
      },
      "type": "Feature",
      "properties": {
        "hierarchy": [
          "tgn:2156591",
          "tgn:1000001",
          "tgn:2002261",
          "tgn:7012149",
          "tgn:7013961",
          "tgn:7029392"
        ],
        "placetype": [
          "aat:300008798"
        ],
        "id": 2156591,
        "name:xx": "Bearwallow Knob"
      }
    },
    {
      "geometry": {
        "type": "Point",
        "coordinates": [
          -80.4,
          38.2
        ]
      },
      "type": "Feature",
      "properties": {
        "hierarchy": [
          "tgn:2156592",
          "tgn:1000001",
          "tgn:7012149",
          "tgn:2002264",
          "tgn:7013961",
          "tgn:7029392"
        ],
        "placetype": [
          "aat:300008798"
        ],
        "id": 2156592,
        "name:xx": "Bearwallow Knob"
      }
    },
    {
      "geometry": {
        "type": "Point",
        "coordinates": [
          -108.6667,
          33.4333
        ]
      },
      "type": "Feature",
      "properties": {
        "hierarchy": [
          "tgn:2156593",
          "tgn:1000001",
          "tgn:2001429",
          "tgn:7012149",
          "tgn:7007566",
          "tgn:7029392"
        ],
        "placetype": [
          "aat:300008798"
        ],
        "id": 2156593,
        "name:xx": "Bearwallow Mountain"
      }
    },
    {
      "geometry": {
        "type": "Point",
        "coordinates": [
          -82.35,
          35.45
        ]
      },
      "type": "Feature",
      "properties": {
        "hierarchy": [
          "tgn:2156594",
          "tgn:1000001",
          "tgn:7012149",
          "tgn:7007709",
          "tgn:7029392"
        ],
        "placetype": [
          "aat:300008798"
        ],
        "id": 2156594,
        "name:xx": "Bearwallow Mountain"
      }
    },
    {
      "geometry": {
        "type": "Point",
        "coordinates": [
          -78.7667,
          39.85
        ]
      },
      "type": "Feature",
      "properties": {
        "hierarchy": [
          "tgn:2156595",
          "tgn:1000001",
          "tgn:7012149",
          "tgn:1002904",
          "tgn:7007710",
          "tgn:7029392"
        ],
        "placetype": [
          "aat:300008798"
        ],
        "id": 2156595,
        "name:xx": "Bearwallow Mountain"
      }
    },
    {
      "geometry": {
        "type": "Point",
        "coordinates": [
          -78.75,
          39.8833
        ]
      },
      "type": "Feature",
      "properties": {
        "hierarchy": [
          "tgn:2156596",
          "tgn:1002172",
          "tgn:1000001",
          "tgn:7012149",
          "tgn:7007710",
          "tgn:7029392"
        ],
        "placetype": [
          "aat:300008798"
        ],
        "id": 2156596,
        "name:xx": "Bearwallow Mountain"
      }
    },
    {
      "geometry": {
        "type": "Point",
        "coordinates": [
          -83.7167,
          35.7667
        ]
      },
      "type": "Feature",
      "properties": {
        "hierarchy": [
          "tgn:2156597",
          "tgn:1000001",
          "tgn:7012149",
          "tgn:7007825",
          "tgn:7029392"
        ],
        "placetype": [
          "aat:300008798"
        ],
        "id": 2156597,
        "name:xx": "Bearwallow Mountain"
      }
    },
    {
      "geometry": {
        "type": "Point",
        "coordinates": [
          -83.4,
          35.8167
        ]
      },
      "type": "Feature",
      "properties": {
        "hierarchy": [
          "tgn:2156598",
          "tgn:1000001",
          "tgn:7012149",
          "tgn:2001914",
          "tgn:7007825",
          "tgn:7029392"
        ],
        "placetype": [
          "aat:300008798"
        ],
        "id": 2156598,
        "name:xx": "Bearwallow Mountain"
      }
    },
    {
      "geometry": {
        "type": "Point",
        "coordinates": [
          -79.8833,
          37.7333
        ]
      },
      "type": "Feature",
      "properties": {
        "hierarchy": [
          "tgn:2156599",
          "tgn:1000001",
          "tgn:7012149",
          "tgn:7007919",
          "tgn:7029392"
        ],
        "placetype": [
          "aat:300008798"
        ],
        "id": 2156599,
        "name:xx": "Bearwallow Mountain"
      }
    }
  ]
}
