{
  "geometry": {
    "type": "Point",
    "coordinates": [
      -105.7833,
      43.0667
    ]
  },
  "type": "Feature",
  "properties": {
    "hierarchy": [
      "tgn:2636549",
      "tgn:1000001",
      "tgn:2002369",
      "tgn:7012149",
      "tgn:7007923",
      "tgn:7029392"
    ],
    "placetype": [
      "aat:300266640"
    ],
    "id": 2636549,
    "name:xx": "Sage Creek Divide"
  }
}
