{
  "geometry": {
    "type": "Point",
    "coordinates": [
      -118.5833,
      44.45
    ]
  },
  "type": "Feature",
  "properties": {
    "hierarchy": [
      "tgn:2244472",
      "tgn:1000001",
      "tgn:7012149",
      "tgn:2001708",
      "tgn:7007708",
      "tgn:7029392"
    ],
    "placetype": [
      "aat:300008701"
    ],
    "id": 2244472,
    "name:xx": "Cline Draw"
  }
}
