{
  "geometry": {
    "type": "Point",
    "coordinates": [
      -108.1667,
      34.9833
    ]
  },
  "type": "Feature",
  "properties": {
    "hierarchy": [
      "tgn:2735994",
      "tgn:1000001",
      "tgn:2001431",
      "tgn:7012149",
      "tgn:7007566",
      "tgn:7029392"
    ],
    "placetype": [
      "aat:300008680"
    ],
    "id": 2735994,
    "name:xx": "Twin Lakes"
  }
}
