{
  "geometry": {
    "type": "Point",
    "coordinates": [
      -78.15,
      41.55
    ]
  },
  "type": "Feature",
  "properties": {
    "hierarchy": [
      "tgn:2612929",
      "tgn:1000001",
      "tgn:1002229",
      "tgn:7012149",
      "tgn:7007710",
      "tgn:7029392"
    ],
    "placetype": [
      "aat:300008761"
    ],
    "id": 2612929,
    "name:xx": "Rednor Hollow"
  }
}
