{
  "geometry": {
    "type": "Point",
    "coordinates": [
      -93.7333,
      34.7833
    ]
  },
  "type": "Feature",
  "properties": {
    "hierarchy": [
      "tgn:2610306",
      "tgn:1000001",
      "tgn:7016172",
      "tgn:7012149",
      "tgn:2000168",
      "tgn:7029392"
    ],
    "placetype": [
      "aat:300008761"
    ],
    "id": 2610306,
    "name:xx": "Red Buck Hollow"
  }
}
