{
  "geometry": {
    "type": "Point",
    "coordinates": [
      -81.7333,
      32.2167
    ]
  },
  "type": "Feature",
  "properties": {
    "hierarchy": [
      "tgn:2613240",
      "tgn:1000001",
      "tgn:2000307",
      "tgn:7012149",
      "tgn:7007248",
      "tgn:7029392"
    ],
    "placetype": [
      "aat:300008699"
    ],
    "id": 2613240,
    "name:xx": "Reed Branch"
  }
}
