{
  "geometry": {
    "type": "Point",
    "coordinates": [
      -119.35,
      43.8333
    ]
  },
  "type": "Feature",
  "properties": {
    "hierarchy": [
      "tgn:2306201",
      "tgn:1000001",
      "tgn:7012149",
      "tgn:2001709",
      "tgn:7007708",
      "tgn:7029392"
    ],
    "placetype": [
      "aat:300008706"
    ],
    "id": 2306201,
    "name:xx": "East Fork Blue Creek"
  }
}
