{
  "geometry": {
    "type": "Point",
    "coordinates": [
      -85.7667,
      38.2667
    ]
  },
  "type": "Feature",
  "properties": {
    "hierarchy": [
      "tgn:2659912",
      "tgn:1000001",
      "tgn:7012149",
      "tgn:1002516",
      "tgn:7007255",
      "tgn:7029392"
    ],
    "placetype": [
      "aat:300008791"
    ],
    "id": 2659912,
    "name:xx": "Shippingport Island"
  }
}
