{
  "type": "FeatureCollection",
  "features": [
    {
      "geometry": {
        "type": "Point",
        "coordinates": [
          -98.8,
          20.966667
        ]
      },
      "type": "Feature",
      "properties": {
        "hierarchy": [
          "tgn:7358100",
          "tgn:7005587",
          "tgn:1000001",
          "tgn:7005560",
          "tgn:7029392"
        ],
        "placetype": [
          "aat:300008347"
        ],
        "id": 7358100,
        "name:xx": "Cuxhuacán"
      }
    },
    {
      "geometry": {
        "type": "Point",
        "coordinates": [
          -101.366667,
          19.283333
        ]
      },
      "type": "Feature",
      "properties": {
        "hierarchy": [
          "tgn:7358104",
          "tgn:1000001",
          "tgn:7005590",
          "tgn:7005560",
          "tgn:7029392"
        ],
        "placetype": [
          "aat:300008347"
        ],
        "id": 7358104,
        "name:xx": "Cuto de la Esperanza"
      }
    },
    {
      "geometry": {
        "type": "Point",
        "coordinates": [
          -105.216667,
          21.333333
        ]
      },
      "type": "Feature",
      "properties": {
        "hierarchy": [
          "tgn:7358105",
          "tgn:1000001",
          "tgn:1001906",
          "tgn:7005560",
          "tgn:7029392"
        ],
        "placetype": [
          "aat:300008679"
        ],
        "id": 7358105,
        "name:xx": "Custodio, Estero"
      }
    },
    {
      "geometry": {
        "type": "Point",
        "coordinates": [
          -105.25,
          21.35
        ]
      },
      "type": "Feature",
      "properties": {
        "hierarchy": [
          "tgn:7358106",
          "tgn:1000001",
          "tgn:1001906",
          "tgn:7005560",
          "tgn:7029392"
        ],
        "placetype": [
          "aat:300387057"
        ],
        "id": 7358106,
        "name:xx": "Custodio, Boca"
      }
    },
    {
      "geometry": {
        "type": "Point",
        "coordinates": [
          -99.966667,
          22.65
        ]
      },
      "type": "Feature",
      "properties": {
        "hierarchy": [
          "tgn:7358107",
          "tgn:1000001",
          "tgn:7005594",
          "tgn:7005560",
          "tgn:7029392"
        ],
        "placetype": [
          "aat:300008347"
        ],
        "id": 7358107,
        "name:xx": "Custodio"
      }
    },
    {
      "geometry": {
        "type": "Point",
        "coordinates": [
          -92.916667,
          15.95
        ]
      },
      "type": "Feature",
      "properties": {
        "hierarchy": [
          "tgn:7358108",
          "tgn:7005580",
          "tgn:1000001",
          "tgn:7005560",
          "tgn:7029392"
        ],
        "placetype": [
          "aat:300008699"
        ],
        "id": 7358108,
        "name:xx": "Custepec"
      }
    },
    {
      "geometry": {
        "type": "Point",
        "coordinates": [
          -92.966667,
          15.716667
        ]
      },
      "type": "Feature",
      "properties": {
        "hierarchy": [
          "tgn:7358109",
          "tgn:7005580",
          "tgn:1000001",
          "tgn:7005560",
          "tgn:7029392"
        ],
        "placetype": [
          "aat:300008347"
        ],
        "id": 7358109,
        "name:xx": "Custepec"
      }
    }
  ]
}
