{
  "type": "FeatureCollection",
  "features": [
    {
      "geometry": {
        "type": "Point",
        "coordinates": [
          -78.6333,
          35.8
        ]
      },
      "type": "Feature",
      "properties": {
        "hierarchy": [
          "tgn:2347720",
          "tgn:1000001",
          "tgn:7012149",
          "tgn:2001548",
          "tgn:7007709",
          "tgn:7029392"
        ],
        "placetype": [
          "aat:300008347"
        ],
        "id": 2347720,
        "name:xx": "Georgetown"
      }
    },
    {
      "geometry": {
        "type": "Point",
        "coordinates": [
          -77.4333,
          34.7333
        ]
      },
      "type": "Feature",
      "properties": {
        "hierarchy": [
          "tgn:2347721",
          "tgn:1000001",
          "tgn:7012149",
          "tgn:2001524",
          "tgn:7007709",
          "tgn:7029392"
        ],
        "placetype": [
          "aat:300008347"
        ],
        "id": 2347721,
        "name:xx": "Georgetown"
      }
    },
    {
      "geometry": {
        "type": "Point",
        "coordinates": [
          -83.5,
          39.4333
        ]
      },
      "type": "Feature",
      "properties": {
        "hierarchy": [
          "tgn:2347722",
          "tgn:1000001",
          "tgn:7012149",
          "tgn:1002372",
          "tgn:7007706",
          "tgn:7029392"
        ],
        "placetype": [
          "aat:300008347"
        ],
        "id": 2347722,
        "name:xx": "Georgetown"
      }
    },
    {
      "geometry": {
        "type": "Point",
        "coordinates": [
          -84.5333,
          39.9
        ]
      },
      "type": "Feature",
      "properties": {
        "hierarchy": [
          "tgn:2347723",
          "tgn:1000001",
          "tgn:7012149",
          "tgn:1002802",
          "tgn:7007706",
          "tgn:7029392"
        ],
        "placetype": [
          "aat:300008347"
        ],
        "id": 2347723,
        "name:xx": "Georgetown"
      }
    },
    {
      "geometry": {
        "type": "Point",
        "coordinates": [
          -81.5833,
          40
        ]
      },
      "type": "Feature",
      "properties": {
        "hierarchy": [
          "tgn:2347724",
          "tgn:1000001",
          "tgn:7012149",
          "tgn:1002432",
          "tgn:7007706",
          "tgn:7029392"
        ],
        "placetype": [
          "aat:300008347"
        ],
        "id": 2347724,
        "name:xx": "Georgetown"
      }
    },
    {
      "geometry": {
        "type": "Point",
        "coordinates": [
          -80.9167,
          40.2
        ]
      },
      "type": "Feature",
      "properties": {
        "hierarchy": [
          "tgn:2347725",
          "tgn:1000001",
          "tgn:7012149",
          "tgn:1002459",
          "tgn:7007706",
          "tgn:7029392"
        ],
        "placetype": [
          "aat:300008347"
        ],
        "id": 2347725,
        "name:xx": "Georgetown"
      }
    },
    {
      "geometry": {
        "type": "Point",
        "coordinates": [
          -81.8833,
          39.9667
        ]
      },
      "type": "Feature",
      "properties": {
        "hierarchy": [
          "tgn:2347726",
          "tgn:1000001",
          "tgn:7012149",
          "tgn:1002701",
          "tgn:7007706",
          "tgn:7029392"
        ],
        "placetype": [
          "aat:300008347"
        ],
        "id": 2347726,
        "name:xx": "Georgetown"
      }
    },
    {
      "geometry": {
        "type": "Point",
        "coordinates": [
          -76.0833,
          39.9333
        ]
      },
      "type": "Feature",
      "properties": {
        "hierarchy": [
          "tgn:2347729",
          "tgn:1000001",
          "tgn:7012149",
          "tgn:7013867",
          "tgn:7007710",
          "tgn:7029392"
        ],
        "placetype": [
          "aat:300008347"
        ],
        "id": 2347729,
        "name:xx": "Georgetown"
      }
    }
  ]
}
