{
  "geometry": {
    "type": "Point",
    "coordinates": [
      -113.1167,
      46.0833
    ]
  },
  "type": "Feature",
  "properties": {
    "hierarchy": [
      "tgn:2148016",
      "tgn:1000001",
      "tgn:7012149",
      "tgn:7020792",
      "tgn:7007524",
      "tgn:7029392"
    ],
    "placetype": [
      "aat:300008706"
    ],
    "id": 2148016,
    "name:xx": "Barker Creek"
  }
}
