{
  "type": "FeatureCollection",
  "features": [
    {
      "geometry": {
        "type": "Point",
        "coordinates": [
          -147.3667,
          60.7
        ]
      },
      "type": "Feature",
      "properties": {
        "hierarchy": [
          "tgn:2572650",
          "tgn:7006450",
          "tgn:1000001",
          "tgn:7012149",
          "tgn:2000086",
          "tgn:7029392"
        ],
        "placetype": [
          "aat:300008791"
        ],
        "id": 2572650,
        "name:xx": "Peak Island"
      }
    },
    {
      "geometry": {
        "type": "Point",
        "coordinates": [
          -68.8,
          44.2333
        ]
      },
      "type": "Feature",
      "properties": {
        "hierarchy": [
          "tgn:2572651",
          "tgn:1000001",
          "tgn:2000922",
          "tgn:7012149",
          "tgn:7007515",
          "tgn:7029392"
        ],
        "placetype": [
          "aat:300008791"
        ],
        "id": 2572651,
        "name:xx": "Peak Island"
      }
    },
    {
      "geometry": {
        "type": "Point",
        "coordinates": [
          -80.7333,
          37.0167
        ]
      },
      "type": "Feature",
      "properties": {
        "hierarchy": [
          "tgn:2572654",
          "tgn:1000001",
          "tgn:7012149",
          "tgn:2002183",
          "tgn:7007919",
          "tgn:7029392"
        ],
        "placetype": [
          "aat:300008798"
        ],
        "id": 2572654,
        "name:xx": "Peak Knob"
      }
    },
    {
      "geometry": {
        "type": "Point",
        "coordinates": [
          -109.7,
          43.15
        ]
      },
      "type": "Feature",
      "properties": {
        "hierarchy": [
          "tgn:2572655",
          "tgn:1000001",
          "tgn:7012149",
          "tgn:2002382",
          "tgn:7007923",
          "tgn:7029392"
        ],
        "placetype": [
          "aat:300006191"
        ],
        "id": 2572655,
        "name:xx": "Peak Lake"
      }
    },
    {
      "geometry": {
        "type": "Point",
        "coordinates": [
          -123.3167,
          44.5833
        ]
      },
      "type": "Feature",
      "properties": {
        "hierarchy": [
          "tgn:2572656",
          "tgn:1000001",
          "tgn:2001701",
          "tgn:7012149",
          "tgn:7007708",
          "tgn:7029392"
        ],
        "placetype": [
          "aat:300006191"
        ],
        "id": 2572656,
        "name:xx": "Peak Log Pond"
      }
    },
    {
      "geometry": {
        "type": "Point",
        "coordinates": [
          -104.7667,
          37.5667
        ]
      },
      "type": "Feature",
      "properties": {
        "hierarchy": [
          "tgn:2572657",
          "tgn:1000001",
          "tgn:7012149",
          "tgn:2000219",
          "tgn:7007158",
          "tgn:7029392"
        ],
        "placetype": [
          "aat:300000390"
        ],
        "id": 2572657,
        "name:xx": "Peak Mine"
      }
    },
    {
      "geometry": {
        "type": "Point",
        "coordinates": [
          -122.4667,
          37.55
        ]
      },
      "type": "Feature",
      "properties": {
        "hierarchy": [
          "tgn:2572658",
          "tgn:1000001",
          "tgn:7012149",
          "tgn:7007157",
          "tgn:1002864",
          "tgn:7029392"
        ],
        "placetype": [
          "aat:300008798"
        ],
        "id": 2572658,
        "name:xx": "Peak Mountain"
      }
    },
    {
      "geometry": {
        "type": "Point",
        "coordinates": [
          -119.85,
          34.9
        ]
      },
      "type": "Feature",
      "properties": {
        "hierarchy": [
          "tgn:2572659",
          "tgn:1000001",
          "tgn:7012149",
          "tgn:7007157",
          "tgn:1002867",
          "tgn:7029392"
        ],
        "placetype": [
          "aat:300008798"
        ],
        "id": 2572659,
        "name:xx": "Peak Mountain"
      }
    }
  ]
}
