{
  "geometry": {
    "type": "Point",
    "coordinates": [
      -35.2667,
      -5.5167
    ]
  },
  "type": "Feature",
  "properties": {
    "hierarchy": [
      "tgn:1022080",
      "tgn:7006257",
      "tgn:1000047",
      "tgn:7002455",
      "tgn:1000002",
      "tgn:7029392"
    ],
    "placetype": [
      "aat:300008347"
    ],
    "id": 1022080,
    "name:xx": "Maxaranguape"
  }
}
