{
  "geometry": {
    "type": "Point",
    "coordinates": [
      -78.5833,
      38.7167
    ]
  },
  "type": "Feature",
  "properties": {
    "hierarchy": [
      "tgn:2441022",
      "tgn:1000001",
      "tgn:7012149",
      "tgn:2002190",
      "tgn:7007919",
      "tgn:7029392"
    ],
    "placetype": [
      "aat:300008798"
    ],
    "id": 2441022,
    "name:xx": "Knob, The"
  }
}
