{
  "type": "FeatureCollection",
  "features": [
    {
      "geometry": {
        "type": "Point",
        "coordinates": [
          -94.4167,
          31.2667
        ]
      },
      "type": "Feature",
      "properties": {
        "hierarchy": [
          "tgn:2106521",
          "tgn:1002149",
          "tgn:1000001",
          "tgn:7012149",
          "tgn:7007826",
          "tgn:7029392"
        ],
        "placetype": [
          "aat:300008347",
          "aat:300387210"
        ],
        "id": 2106521,
        "name:xx": "Ora"
      }
    },
    {
      "geometry": {
        "type": "Point",
        "coordinates": [
          -98.15,
          32.95
        ]
      },
      "type": "Feature",
      "properties": {
        "hierarchy": [
          "tgn:2106522",
          "tgn:1000001",
          "tgn:7012149",
          "tgn:2002053",
          "tgn:7007826",
          "tgn:7029392"
        ],
        "placetype": [
          "aat:300008347"
        ],
        "id": 2106522,
        "name:xx": "Oran"
      }
    }
  ]
}
