{
  "geometry": {
    "type": "Point",
    "coordinates": [
      31.285851,
      30.10788
    ]
  },
  "type": "Feature",
  "properties": {
    "hierarchy": [
      "tgn:7532103",
      "tgn:7001242",
      "tgn:7016833",
      "tgn:1001091",
      "tgn:7029392"
    ],
    "placetype": [
      "aat:300004792"
    ],
    "id": 7532103,
    "name:xx": "Shirkat an Nīl al 'Āmmah liţ Ţuruq wa al Kabārī"
  }
}
