{
  "geometry": {
    "type": "Point",
    "coordinates": [
      -98.8167,
      47.9333
    ]
  },
  "type": "Feature",
  "properties": {
    "hierarchy": [
      "tgn:2687388",
      "tgn:2001559",
      "tgn:1000001",
      "tgn:7012149",
      "tgn:7007705",
      "tgn:7029392"
    ],
    "placetype": [
      "aat:300008680"
    ],
    "id": 2687388,
    "name:xx": "Spring Lake"
  }
}
