{
  "type": "FeatureCollection",
  "features": [
    {
      "geometry": {
        "type": "Point",
        "coordinates": [
          -111.6,
          35.0333
        ]
      },
      "type": "Feature",
      "properties": {
        "hierarchy": [
          "tgn:2717900",
          "tgn:1000001",
          "tgn:7006451",
          "tgn:2000092",
          "tgn:7012149",
          "tgn:7029392"
        ],
        "placetype": [
          "aat:300008697"
        ],
        "id": 2717900,
        "name:xx": "Thomas Spring"
      }
    },
    {
      "geometry": {
        "type": "Point",
        "coordinates": [
          -83.2167,
          30.1333
        ]
      },
      "type": "Feature",
      "properties": {
        "hierarchy": [
          "tgn:2717901",
          "tgn:1000001",
          "tgn:7012149",
          "tgn:2000286",
          "tgn:7007240",
          "tgn:7029392"
        ],
        "placetype": [
          "aat:300008697"
        ],
        "id": 2717901,
        "name:xx": "Thomas Spring"
      }
    },
    {
      "geometry": {
        "type": "Point",
        "coordinates": [
          -111.6333,
          42.1333
        ]
      },
      "type": "Feature",
      "properties": {
        "hierarchy": [
          "tgn:2717902",
          "tgn:1000001",
          "tgn:7012149",
          "tgn:2000472",
          "tgn:7007250",
          "tgn:7029392"
        ],
        "placetype": [
          "aat:300008697"
        ],
        "id": 2717902,
        "name:xx": "Thomas Spring"
      }
    },
    {
      "geometry": {
        "type": "Point",
        "coordinates": [
          -116.3667,
          45.55
        ]
      },
      "type": "Feature",
      "properties": {
        "hierarchy": [
          "tgn:2717903",
          "tgn:1000001",
          "tgn:7012149",
          "tgn:2000476",
          "tgn:7007250",
          "tgn:7029392"
        ],
        "placetype": [
          "aat:300008697"
        ],
        "id": 2717903,
        "name:xx": "Thomas Spring"
      }
    },
    {
      "geometry": {
        "type": "Point",
        "coordinates": [
          -105.9667,
          45.6167
        ]
      },
      "type": "Feature",
      "properties": {
        "hierarchy": [
          "tgn:2717904",
          "tgn:1000001",
          "tgn:7012149",
          "tgn:2001297",
          "tgn:7007524",
          "tgn:7029392"
        ],
        "placetype": [
          "aat:300008697"
        ],
        "id": 2717904,
        "name:xx": "Thomas Spring"
      }
    },
    {
      "geometry": {
        "type": "Point",
        "coordinates": [
          -119.6167,
          45.0667
        ]
      },
      "type": "Feature",
      "properties": {
        "hierarchy": [
          "tgn:2717905",
          "tgn:1000001",
          "tgn:7012149",
          "tgn:2001719",
          "tgn:7007708",
          "tgn:7029392"
        ],
        "placetype": [
          "aat:300008697"
        ],
        "id": 2717905,
        "name:xx": "Thomas Spring"
      }
    },
    {
      "geometry": {
        "type": "Point",
        "coordinates": [
          -84.6833,
          35.5
        ]
      },
      "type": "Feature",
      "properties": {
        "hierarchy": [
          "tgn:2717906",
          "tgn:1000001",
          "tgn:7012149",
          "tgn:7022542",
          "tgn:7007825",
          "tgn:7029392"
        ],
        "placetype": [
          "aat:300008697"
        ],
        "id": 2717906,
        "name:xx": "Thomas Spring"
      }
    },
    {
      "geometry": {
        "type": "Point",
        "coordinates": [
          -87.0833,
          35.5167
        ]
      },
      "type": "Feature",
      "properties": {
        "hierarchy": [
          "tgn:2717907",
          "tgn:1000001",
          "tgn:7012149",
          "tgn:2001896",
          "tgn:7007825",
          "tgn:7029392"
        ],
        "placetype": [
          "aat:300008697"
        ],
        "id": 2717907,
        "name:xx": "Thomas Spring"
      }
    },
    {
      "geometry": {
        "type": "Point",
        "coordinates": [
          -80.15,
          37.7
        ]
      },
      "type": "Feature",
      "properties": {
        "hierarchy": [
          "tgn:2717909",
          "tgn:2002138",
          "tgn:1000001",
          "tgn:7012149",
          "tgn:7007919",
          "tgn:7029392"
        ],
        "placetype": [
          "aat:300008697"
        ],
        "id": 2717909,
        "name:xx": "Thomas Spring"
      }
    }
  ]
}
