{
  "geometry": {
    "type": "Point",
    "coordinates": [
      -82.35,
      37.1833
    ]
  },
  "type": "Feature",
  "properties": {
    "hierarchy": [
      "tgn:2591798",
      "tgn:1000001",
      "tgn:7012149",
      "tgn:2002157",
      "tgn:7007919",
      "tgn:7029392"
    ],
    "placetype": [
      "aat:300008761"
    ],
    "id": 2591798,
    "name:xx": "Pond Hollow"
  }
}
