{
  "geometry": {
    "type": "Point",
    "coordinates": [
      -76.3333,
      35.8667
    ]
  },
  "type": "Feature",
  "properties": {
    "hierarchy": [
      "tgn:2074271",
      "tgn:1000001",
      "tgn:7012149",
      "tgn:2001545",
      "tgn:7007709",
      "tgn:7029392"
    ],
    "placetype": [
      "aat:300008347",
      "aat:300387210"
    ],
    "id": 2074271,
    "name:xx": "Cross Landing"
  }
}
