{
  "geometry": {
    "type": "Point",
    "coordinates": [
      -83.3833,
      43.7167
    ]
  },
  "type": "Feature",
  "properties": {
    "hierarchy": [
      "tgn:2295205",
      "tgn:1000001",
      "tgn:7012149",
      "tgn:2000964",
      "tgn:7007520",
      "tgn:7029392"
    ],
    "placetype": [
      "aat:300006075"
    ],
    "id": 2295205,
    "name:xx": "Dressier Drain"
  }
}
