{
  "geometry": {
    "type": "Point",
    "coordinates": [
      -78.8333,
      41.85
    ]
  },
  "type": "Feature",
  "properties": {
    "hierarchy": [
      "tgn:2565276",
      "tgn:1000001",
      "tgn:7012149",
      "tgn:7016020",
      "tgn:7007710",
      "tgn:7029392"
    ],
    "placetype": [
      "aat:300266640"
    ],
    "id": 2565276,
    "name:xx": "Paines Summit"
  }
}
