{
  "geometry": {
    "type": "Point",
    "coordinates": [
      -90.9167,
      37.9833
    ]
  },
  "type": "Feature",
  "properties": {
    "hierarchy": [
      "tgn:2646518",
      "tgn:1000001",
      "tgn:7012149",
      "tgn:2001254",
      "tgn:7007523",
      "tgn:7029392"
    ],
    "placetype": [
      "aat:300006191"
    ],
    "id": 2646518,
    "name:xx": "Sayersbrook Lake"
  }
}
