{
  "geometry": {
    "type": "Point",
    "coordinates": [
      -81.8667,
      37.4167
    ]
  },
  "type": "Feature",
  "properties": {
    "hierarchy": [
      "tgn:2567326",
      "tgn:1000001",
      "tgn:7012149",
      "tgn:2002274",
      "tgn:7013961",
      "tgn:7029392"
    ],
    "placetype": [
      "aat:300008863"
    ],
    "id": 2567326,
    "name:xx": "Panther State Forest"
  }
}
