{
  "geometry": {
    "type": "Point",
    "coordinates": [
      -112.6167,
      33.2167
    ]
  },
  "type": "Feature",
  "properties": {
    "hierarchy": [
      "tgn:2631451",
      "tgn:1000001",
      "tgn:7006451",
      "tgn:7012149",
      "tgn:2000097",
      "tgn:7029392"
    ],
    "placetype": [
      "aat:300006191"
    ],
    "id": 2631451,
    "name:xx": "Round Tank"
  }
}
