{
  "geometry": {
    "type": "Point",
    "coordinates": [
      -111.5333,
      33.8333
    ]
  },
  "type": "Feature",
  "properties": {
    "hierarchy": [
      "tgn:2497230",
      "tgn:1000001",
      "tgn:7006451",
      "tgn:7012149",
      "tgn:2000097",
      "tgn:7029392"
    ],
    "placetype": [
      "aat:300008761"
    ],
    "id": 2497230,
    "name:xx": "Maverick Spring Canyon"
  }
}
