{
  "type": "FeatureCollection",
  "features": [
    {
      "geometry": {
        "type": "Point",
        "coordinates": [
          -80.95,
          34.8833
        ]
      },
      "type": "Feature",
      "properties": {
        "hierarchy": [
          "tgn:2666440",
          "tgn:1000001",
          "tgn:7012149",
          "tgn:2001770",
          "tgn:7007712",
          "tgn:7029392"
        ],
        "placetype": [
          "aat:300008706"
        ],
        "id": 2666440,
        "name:xx": "Sixmile Creek"
      }
    },
    {
      "geometry": {
        "type": "Point",
        "coordinates": [
          -96.6333,
          44.55
        ]
      },
      "type": "Feature",
      "properties": {
        "hierarchy": [
          "tgn:2666441",
          "tgn:1000001",
          "tgn:7012149",
          "tgn:7007713",
          "tgn:7029392"
        ],
        "placetype": [
          "aat:300008706"
        ],
        "id": 2666441,
        "name:xx": "Sixmile Creek"
      }
    },
    {
      "geometry": {
        "type": "Point",
        "coordinates": [
          -84.2167,
          35.2667
        ]
      },
      "type": "Feature",
      "properties": {
        "hierarchy": [
          "tgn:2666442",
          "tgn:1000001",
          "tgn:7012149",
          "tgn:2001898",
          "tgn:7007825",
          "tgn:7029392"
        ],
        "placetype": [
          "aat:300008706"
        ],
        "id": 2666442,
        "name:xx": "Sixmile Creek"
      }
    },
    {
      "geometry": {
        "type": "Point",
        "coordinates": [
          -83.9333,
          35.6667
        ]
      },
      "type": "Feature",
      "properties": {
        "hierarchy": [
          "tgn:2666443",
          "tgn:1000001",
          "tgn:2001841",
          "tgn:7012149",
          "tgn:7007825",
          "tgn:7029392"
        ],
        "placetype": [
          "aat:300008706"
        ],
        "id": 2666443,
        "name:xx": "Sixmile Creek"
      }
    },
    {
      "geometry": {
        "type": "Point",
        "coordinates": [
          -97.8333,
          28.0667
        ]
      },
      "type": "Feature",
      "properties": {
        "hierarchy": [
          "tgn:2666444",
          "tgn:1000001",
          "tgn:7012149",
          "tgn:2002068",
          "tgn:7007826",
          "tgn:7029392"
        ],
        "placetype": [
          "aat:300008706"
        ],
        "id": 2666444,
        "name:xx": "Sixmile Creek"
      }
    },
    {
      "geometry": {
        "type": "Point",
        "coordinates": [
          -96.7,
          28.6667
        ]
      },
      "type": "Feature",
      "properties": {
        "hierarchy": [
          "tgn:2666445",
          "tgn:1000001",
          "tgn:7012149",
          "tgn:2001950",
          "tgn:7007826",
          "tgn:7029392"
        ],
        "placetype": [
          "aat:300008706"
        ],
        "id": 2666445,
        "name:xx": "Sixmile Creek"
      }
    },
    {
      "geometry": {
        "type": "Point",
        "coordinates": [
          -96.7333,
          30.7
        ]
      },
      "type": "Feature",
      "properties": {
        "hierarchy": [
          "tgn:2666446",
          "tgn:1000001",
          "tgn:7012149",
          "tgn:1002670",
          "tgn:7007826",
          "tgn:7029392"
        ],
        "placetype": [
          "aat:300008706"
        ],
        "id": 2666446,
        "name:xx": "Sixmile Creek"
      }
    },
    {
      "geometry": {
        "type": "Point",
        "coordinates": [
          -95.3333,
          31.9167
        ]
      },
      "type": "Feature",
      "properties": {
        "hierarchy": [
          "tgn:2666447",
          "tgn:1000001",
          "tgn:7012149",
          "tgn:1002263",
          "tgn:7007826",
          "tgn:7029392"
        ],
        "placetype": [
          "aat:300008706"
        ],
        "id": 2666447,
        "name:xx": "Sixmile Creek"
      }
    },
    {
      "geometry": {
        "type": "Point",
        "coordinates": [
          -95.4833,
          33.6667
        ]
      },
      "type": "Feature",
      "properties": {
        "hierarchy": [
          "tgn:2666448",
          "tgn:1000001",
          "tgn:7012149",
          "tgn:2002024",
          "tgn:7007826",
          "tgn:7029392"
        ],
        "placetype": [
          "aat:300008706"
        ],
        "id": 2666448,
        "name:xx": "Sixmile Creek"
      }
    },
    {
      "geometry": {
        "type": "Point",
        "coordinates": [
          -98.5333,
          29.35
        ]
      },
      "type": "Feature",
      "properties": {
        "hierarchy": [
          "tgn:2666449",
          "tgn:1000001",
          "tgn:2001941",
          "tgn:7012149",
          "tgn:7007826",
          "tgn:7029392"
        ],
        "placetype": [
          "aat:300008706"
        ],
        "id": 2666449,
        "name:xx": "Sixmile Creek"
      }
    }
  ]
}
