{
  "geometry": {
    "type": "Point",
    "coordinates": [
      -82.8167,
      37.35
    ]
  },
  "type": "Feature",
  "properties": {
    "hierarchy": [
      "tgn:2621327",
      "tgn:1000001",
      "tgn:7012149",
      "tgn:2000805",
      "tgn:7007255",
      "tgn:7029392"
    ],
    "placetype": [
      "aat:300008699"
    ],
    "id": 2621327,
    "name:xx": "Roaring Branch"
  }
}
