{
  "type": "FeatureCollection",
  "features": [
    {
      "geometry": {
        "type": "Point",
        "coordinates": [
          -69.733333,
          -18.5
        ]
      },
      "type": "Feature",
      "properties": {
        "hierarchy": [
          "tgn:7314060",
          "tgn:7002464",
          "tgn:1000049",
          "tgn:1000002",
          "tgn:7029392"
        ],
        "placetype": [
          "aat:300008347"
        ],
        "id": 7314060,
        "name:xx": "Livilcar"
      }
    },
    {
      "geometry": {
        "type": "Point",
        "coordinates": [
          -72.716667,
          -38.266667
        ]
      },
      "type": "Feature",
      "properties": {
        "hierarchy": [
          "tgn:7314061",
          "tgn:1001692",
          "tgn:1000049",
          "tgn:1000002",
          "tgn:7029392"
        ],
        "placetype": [
          "aat:300008699"
        ],
        "id": 7314061,
        "name:xx": "Liuque, Estero"
      }
    },
    {
      "geometry": {
        "type": "Point",
        "coordinates": [
          -72.283333,
          -39.4
        ]
      },
      "type": "Feature",
      "properties": {
        "hierarchy": [
          "tgn:7314062",
          "tgn:1001692",
          "tgn:1000049",
          "tgn:1000002",
          "tgn:7029392"
        ],
        "placetype": [
          "aat:300008699"
        ],
        "id": 7314062,
        "name:xx": "Liumalla, Río"
      }
    },
    {
      "geometry": {
        "type": "Point",
        "coordinates": [
          -72.3,
          -39.383333
        ]
      },
      "type": "Feature",
      "properties": {
        "hierarchy": [
          "tgn:7314063",
          "tgn:1001692",
          "tgn:1000049",
          "tgn:1000002",
          "tgn:7029392"
        ],
        "placetype": [
          "aat:300008347"
        ],
        "id": 7314063,
        "name:xx": "Liumalla"
      }
    },
    {
      "geometry": {
        "type": "Point",
        "coordinates": [
          -71.833333,
          -39.25
        ]
      },
      "type": "Feature",
      "properties": {
        "hierarchy": [
          "tgn:7314064",
          "tgn:1001692",
          "tgn:1000049",
          "tgn:1000002",
          "tgn:7029392"
        ],
        "placetype": [
          "aat:300008699"
        ],
        "id": 7314064,
        "name:xx": "Liucura, Río"
      }
    },
    {
      "geometry": {
        "type": "Point",
        "coordinates": [
          -71.1,
          -38.65
        ]
      },
      "type": "Feature",
      "properties": {
        "hierarchy": [
          "tgn:7314065",
          "tgn:1001692",
          "tgn:1000049",
          "tgn:1000002",
          "tgn:7029392"
        ],
        "placetype": [
          "aat:300008699"
        ],
        "id": 7314065,
        "name:xx": "Liucura, Río"
      }
    },
    {
      "geometry": {
        "type": "Point",
        "coordinates": [
          -72.533333,
          -38.283333
        ]
      },
      "type": "Feature",
      "properties": {
        "hierarchy": [
          "tgn:7314066",
          "tgn:1001692",
          "tgn:1000049",
          "tgn:1000002",
          "tgn:7029392"
        ],
        "placetype": [
          "aat:300008699"
        ],
        "id": 7314066,
        "name:xx": "Liucura, Estero"
      }
    },
    {
      "geometry": {
        "type": "Point",
        "coordinates": [
          -71.05,
          -38.633333
        ]
      },
      "type": "Feature",
      "properties": {
        "hierarchy": [
          "tgn:7314067",
          "tgn:1001692",
          "tgn:1000049",
          "tgn:1000002",
          "tgn:7029392"
        ],
        "placetype": [
          "aat:300008795"
        ],
        "id": 7314067,
        "name:xx": "Liucura, Cerro"
      }
    },
    {
      "geometry": {
        "type": "Point",
        "coordinates": [
          -73.783333,
          -46.016667
        ]
      },
      "type": "Feature",
      "properties": {
        "hierarchy": [
          "tgn:7314068",
          "tgn:1001623",
          "tgn:1000049",
          "tgn:1000002",
          "tgn:7029392"
        ],
        "placetype": [
          "aat:300387026"
        ],
        "id": 7314068,
        "name:xx": "Liucura, Canal"
      }
    }
  ]
}
