{
  "type": "FeatureCollection",
  "features": [
    {
      "geometry": {
        "type": "Point",
        "coordinates": [
          22.9,
          37.2
        ]
      },
      "type": "Feature",
      "properties": {
        "hierarchy": [
          "tgn:7227530",
          "tgn:7002735",
          "tgn:7017076",
          "tgn:1000003",
          "tgn:1000074",
          "tgn:7029392"
        ],
        "placetype": [
          "aat:300132316"
        ],
        "id": 7227530,
        "name:xx": "Livadhíon, Órmos"
      }
    },
    {
      "geometry": {
        "type": "Point",
        "coordinates": [
          23.216667,
          40.516667
        ]
      },
      "type": "Feature",
      "properties": {
        "hierarchy": [
          "tgn:7227531",
          "tgn:7002715",
          "tgn:7002731",
          "tgn:1000003",
          "tgn:1000074",
          "tgn:7029392"
        ],
        "placetype": [
          "aat:300008347"
        ],
        "id": 7227531,
        "name:xx": "Livádhion"
      }
    },
    {
      "geometry": {
        "type": "Point",
        "coordinates": [
          22.438056,
          40.500278
        ]
      },
      "type": "Feature",
      "properties": {
        "hierarchy": [
          "tgn:7227532",
          "tgn:7002715",
          "tgn:7002729",
          "tgn:1000003",
          "tgn:1000074",
          "tgn:7029392"
        ],
        "placetype": [
          "aat:300008347"
        ],
        "id": 7227532,
        "name:xx": "Livádion"
      }
    },
    {
      "geometry": {
        "type": "Point",
        "coordinates": [
          22.151667,
          40.125
        ]
      },
      "type": "Feature",
      "properties": {
        "hierarchy": [
          "tgn:7227533",
          "tgn:7002750",
          "tgn:7001399",
          "tgn:1000003",
          "tgn:1000074",
          "tgn:7029392"
        ],
        "placetype": [
          "aat:300008347"
        ],
        "id": 7227533,
        "name:xx": "Livádion"
      }
    },
    {
      "geometry": {
        "type": "Point",
        "coordinates": [
          21.0725,
          39.386667
        ]
      },
      "type": "Feature",
      "properties": {
        "hierarchy": [
          "tgn:7227534",
          "tgn:7002706",
          "tgn:7002705",
          "tgn:1000003",
          "tgn:1000074",
          "tgn:7029392"
        ],
        "placetype": [
          "aat:300008347"
        ],
        "id": 7227534,
        "name:xx": "Livádion"
      }
    },
    {
      "geometry": {
        "type": "Point",
        "coordinates": [
          20.433333,
          38.283333
        ]
      },
      "type": "Feature",
      "properties": {
        "hierarchy": [
          "tgn:7227535",
          "tgn:7011167",
          "tgn:7001338",
          "tgn:1000003",
          "tgn:1000074",
          "tgn:7029392"
        ],
        "placetype": [
          "aat:300008347"
        ],
        "id": 7227535,
        "name:xx": "Livádhion"
      }
    },
    {
      "geometry": {
        "type": "Point",
        "coordinates": [
          24.516667,
          37.15
        ]
      },
      "type": "Feature",
      "properties": {
        "hierarchy": [
          "tgn:7227536",
          "tgn:7011270",
          "tgn:7002674",
          "tgn:1000003",
          "tgn:1000074",
          "tgn:7029392"
        ],
        "placetype": [
          "aat:300008347"
        ],
        "id": 7227536,
        "name:xx": "Livádion"
      }
    },
    {
      "geometry": {
        "type": "Point",
        "coordinates": [
          24.933333,
          36.6
        ]
      },
      "type": "Feature",
      "properties": {
        "hierarchy": [
          "tgn:7227537",
          "tgn:7011270",
          "tgn:7002674",
          "tgn:1000003",
          "tgn:1000074",
          "tgn:7029392"
        ],
        "placetype": [
          "aat:300008347"
        ],
        "id": 7227537,
        "name:xx": "Livádhion"
      }
    },
    {
      "geometry": {
        "type": "Point",
        "coordinates": [
          22.983333,
          36.183333
        ]
      },
      "type": "Feature",
      "properties": {
        "hierarchy": [
          "tgn:7227538",
          "tgn:7002745",
          "tgn:7017076",
          "tgn:1000003",
          "tgn:1000074",
          "tgn:7029392"
        ],
        "placetype": [
          "aat:300008347"
        ],
        "id": 7227538,
        "name:xx": "Livádhion"
      }
    },
    {
      "geometry": {
        "type": "Point",
        "coordinates": [
          21.966667,
          36.8
        ]
      },
      "type": "Feature",
      "properties": {
        "hierarchy": [
          "tgn:7227539",
          "tgn:7002745",
          "tgn:7017076",
          "tgn:1000003",
          "tgn:1000074",
          "tgn:7029392"
        ],
        "placetype": [
          "aat:300386846"
        ],
        "id": 7227539,
        "name:xx": "Livadhiés, Ákra"
      }
    }
  ]
}
