{
  "type": "FeatureCollection",
  "features": [
    {
      "geometry": {
        "type": "Point",
        "coordinates": [
          11.466667,
          44.5
        ]
      },
      "type": "Feature",
      "properties": {
        "hierarchy": [
          "tgn:1044071",
          "tgn:7003127",
          "tgn:1000003",
          "tgn:7008516",
          "tgn:1000080",
          "tgn:7029392"
        ],
        "placetype": [
          "aat:300008347"
        ],
        "id": 1044071,
        "name:xx": "Castenaso"
      }
    },
    {
      "geometry": {
        "type": "Point",
        "coordinates": [
          10.3,
          45.466667
        ]
      },
      "type": "Feature",
      "properties": {
        "hierarchy": [
          "tgn:1044072",
          "tgn:7005765",
          "tgn:1000003",
          "tgn:7003237",
          "tgn:1000080",
          "tgn:7029392"
        ],
        "placetype": [
          "aat:300008347"
        ],
        "id": 1044072,
        "name:xx": "Castenedolo"
      }
    },
    {
      "geometry": {
        "type": "Point",
        "coordinates": [
          11.766667,
          43.533333
        ]
      },
      "type": "Feature",
      "properties": {
        "hierarchy": [
          "tgn:1044073",
          "tgn:7003162",
          "tgn:1000003",
          "tgn:7009760",
          "tgn:1000080",
          "tgn:7029392"
        ],
        "placetype": [
          "aat:300008347"
        ],
        "id": 1044073,
        "name:xx": "Castiglion Fibocchi"
      }
    },
    {
      "geometry": {
        "type": "Point",
        "coordinates": [
          9.516667,
          44.266667
        ]
      },
      "type": "Feature",
      "properties": {
        "hierarchy": [
          "tgn:1044076",
          "tgn:1000003",
          "tgn:7003142",
          "tgn:7003236",
          "tgn:1000080",
          "tgn:7029392"
        ],
        "placetype": [
          "aat:300008347"
        ],
        "id": 1044076,
        "name:xx": "Castiglione Chiavarese"
      }
    },
    {
      "geometry": {
        "type": "Point",
        "coordinates": [
          14.45,
          41.866667
        ]
      },
      "type": "Feature",
      "properties": {
        "hierarchy": [
          "tgn:1044077",
          "tgn:7009084",
          "tgn:7003000",
          "tgn:1000003",
          "tgn:1000080",
          "tgn:7029392"
        ],
        "placetype": [
          "aat:300008347"
        ],
        "id": 1044077,
        "name:xx": "Castiglione Messer Marino"
      }
    },
    {
      "geometry": {
        "type": "Point",
        "coordinates": [
          9.683333,
          45.216667
        ]
      },
      "type": "Feature",
      "properties": {
        "hierarchy": [
          "tgn:1044079",
          "tgn:7024844",
          "tgn:1000003",
          "tgn:7003237",
          "tgn:1000080",
          "tgn:7029392"
        ],
        "placetype": [
          "aat:300008347"
        ],
        "id": 1044079,
        "name:xx": "Castiglione d'Adda"
      }
    }
  ]
}
