{
  "geometry": {
    "type": "Point",
    "coordinates": [
      -88.3667,
      46.2667
    ]
  },
  "type": "Feature",
  "properties": {
    "hierarchy": [
      "tgn:2216724",
      "tgn:1000001",
      "tgn:7012149",
      "tgn:2000966",
      "tgn:7007520",
      "tgn:7029392"
    ],
    "placetype": [
      "aat:300008706"
    ],
    "id": 2216724,
    "name:xx": "Camp Eight Creek"
  }
}
