{
  "geometry": {
    "type": "Point",
    "coordinates": [
      -73.5667,
      42.3333
    ]
  },
  "type": "Feature",
  "properties": {
    "hierarchy": [
      "tgn:2440233",
      "tgn:1000001",
      "tgn:7013638",
      "tgn:7012149",
      "tgn:7007568",
      "tgn:7029392"
    ],
    "placetype": [
      "aat:300008699"
    ],
    "id": 2440233,
    "name:xx": "Kline Kill"
  }
}
