{
  "geometry": {
    "type": "Point",
    "coordinates": [
      -48.3333,
      -1.3667
    ]
  },
  "type": "Feature",
  "properties": {
    "hierarchy": [
      "tgn:1020603",
      "tgn:7006247",
      "tgn:1000047",
      "tgn:7002456",
      "tgn:1000002",
      "tgn:7029392"
    ],
    "placetype": [
      "aat:300008347"
    ],
    "id": 1020603,
    "name:xx": "Ananindeua"
  }
}
