{
  "type": "FeatureCollection",
  "features": [
    {
      "geometry": {
        "type": "Point",
        "coordinates": [
          -95.133333,
          16.633333
        ]
      },
      "type": "Feature",
      "properties": {
        "hierarchy": [
          "tgn:7389670",
          "tgn:1000001",
          "tgn:7005591",
          "tgn:7005560",
          "tgn:7029392"
        ],
        "placetype": [
          "aat:300008347"
        ],
        "id": 7389670,
        "name:xx": "Reparo"
      }
    },
    {
      "geometry": {
        "type": "Point",
        "coordinates": [
          -98.883333,
          16.583333
        ]
      },
      "type": "Feature",
      "properties": {
        "hierarchy": [
          "tgn:7389671",
          "tgn:7005585",
          "tgn:1000001",
          "tgn:7005560",
          "tgn:7029392"
        ],
        "placetype": [
          "aat:300008347"
        ],
        "id": 7389671,
        "name:xx": "Reparo"
      }
    },
    {
      "geometry": {
        "type": "Point",
        "coordinates": [
          -94.366667,
          16.333333
        ]
      },
      "type": "Feature",
      "properties": {
        "hierarchy": [
          "tgn:7389672",
          "tgn:1000001",
          "tgn:7005591",
          "tgn:7005560",
          "tgn:7029392"
        ],
        "placetype": [
          "aat:300008347"
        ],
        "id": 7389672,
        "name:xx": "Reparo"
      }
    },
    {
      "geometry": {
        "type": "Point",
        "coordinates": [
          -95.283333,
          16.166667
        ]
      },
      "type": "Feature",
      "properties": {
        "hierarchy": [
          "tgn:7389673",
          "tgn:1000001",
          "tgn:7005591",
          "tgn:7005560",
          "tgn:7029392"
        ],
        "placetype": [
          "aat:300008347"
        ],
        "id": 7389673,
        "name:xx": "Reparo"
      }
    },
    {
      "geometry": {
        "type": "Point",
        "coordinates": [
          -92.033333,
          15.716667
        ]
      },
      "type": "Feature",
      "properties": {
        "hierarchy": [
          "tgn:7389674",
          "tgn:7005580",
          "tgn:1000001",
          "tgn:7005560",
          "tgn:7029392"
        ],
        "placetype": [
          "aat:300008347"
        ],
        "id": 7389674,
        "name:xx": "Reparo"
      }
    },
    {
      "geometry": {
        "type": "Point",
        "coordinates": [
          -109.8,
          27.3
        ]
      },
      "type": "Feature",
      "properties": {
        "hierarchy": [
          "tgn:7389675",
          "tgn:1000001",
          "tgn:1001960",
          "tgn:7005560",
          "tgn:7029392"
        ],
        "placetype": [
          "aat:300387007"
        ],
        "id": 7389675,
        "name:xx": "Reparo"
      }
    },
    {
      "geometry": {
        "type": "Point",
        "coordinates": [
          -105.216667,
          20.733333
        ]
      },
      "type": "Feature",
      "properties": {
        "hierarchy": [
          "tgn:7389676",
          "tgn:7005586",
          "tgn:1000001",
          "tgn:7005560",
          "tgn:7029392"
        ],
        "placetype": [
          "aat:300008699"
        ],
        "id": 7389676,
        "name:xx": "Reparito, Arroyo"
      }
    },
    {
      "geometry": {
        "type": "Point",
        "coordinates": [
          -102.933333,
          19.516667
        ]
      },
      "type": "Feature",
      "properties": {
        "hierarchy": [
          "tgn:7389677",
          "tgn:7005586",
          "tgn:1000001",
          "tgn:7005560",
          "tgn:7029392"
        ],
        "placetype": [
          "aat:300008347"
        ],
        "id": 7389677,
        "name:xx": "Reparito"
      }
    },
    {
      "geometry": {
        "type": "Point",
        "coordinates": [
          -93.466667,
          17.55
        ]
      },
      "type": "Feature",
      "properties": {
        "hierarchy": [
          "tgn:7389678",
          "tgn:7005580",
          "tgn:1000001",
          "tgn:7005560",
          "tgn:7029392"
        ],
        "placetype": [
          "aat:300008347"
        ],
        "id": 7389678,
        "name:xx": "Renuevo"
      }
    },
    {
      "geometry": {
        "type": "Point",
        "coordinates": [
          -101.933333,
          24.783333
        ]
      },
      "type": "Feature",
      "properties": {
        "hierarchy": [
          "tgn:7389679",
          "tgn:1000001",
          "tgn:7005601",
          "tgn:7005560",
          "tgn:7029392"
        ],
        "placetype": [
          "aat:300000241"
        ],
        "id": 7389679,
        "name:xx": "Rancho Renuevas"
      }
    }
  ]
}
