{
  "geometry": {
    "type": "Point",
    "coordinates": [
      -86.8167,
      34.4833
    ]
  },
  "type": "Feature",
  "properties": {
    "hierarchy": [
      "tgn:2385406",
      "tgn:7002659",
      "tgn:1000001",
      "tgn:7012149",
      "tgn:2000051",
      "tgn:7029392"
    ],
    "placetype": [
      "aat:300008347"
    ],
    "id": 2385406,
    "name:xx": "Henderson"
  }
}
