{
  "geometry": {
    "type": "Point",
    "coordinates": [
      -79.55,
      35.8833
    ]
  },
  "type": "Feature",
  "properties": {
    "hierarchy": [
      "tgn:2690506",
      "tgn:1000001",
      "tgn:7012149",
      "tgn:2001532",
      "tgn:7007709",
      "tgn:7029392"
    ],
    "placetype": [
      "aat:300006191"
    ],
    "id": 2690506,
    "name:xx": "Staley Mill Lake"
  }
}
