{
  "geometry": {
    "type": "Point",
    "coordinates": [
      -121.1333,
      47.2667
    ]
  },
  "type": "Feature",
  "properties": {
    "hierarchy": [
      "tgn:2567646",
      "tgn:1000001",
      "tgn:7012149",
      "tgn:1002553",
      "tgn:7007920",
      "tgn:7029392"
    ],
    "placetype": [
      "aat:300008706"
    ],
    "id": 2567646,
    "name:xx": "Para Creek"
  }
}
