{
  "geometry": {
    "type": "Point",
    "coordinates": [
      13.8333,
      46.75
    ]
  },
  "type": "Feature",
  "properties": {
    "hierarchy": [
      "tgn:7003024",
      "tgn:1000003",
      "tgn:1000062",
      "tgn:7029392"
    ],
    "placetype": [
      "aat:300387064",
      "aat:300235088",
      "aat:300000776"
    ],
    "id": 7003024,
    "name:xx": "Kärnten"
  }
}
