{
  "type": "FeatureCollection",
  "features": [
    {
      "geometry": {
        "type": "Point",
        "coordinates": [
          -1.566667,
          54.033333
        ]
      },
      "type": "Feature",
      "properties": {
        "hierarchy": [
          "tgn:4009304",
          "tgn:7002445",
          "tgn:1000003",
          "tgn:7008166",
          "tgn:7008591",
          "tgn:7029392"
        ],
        "placetype": [
          "aat:300008347"
        ],
        "name:en": "Ripley",
        "id": 4009304
      }
    },
    {
      "geometry": {
        "type": "Point",
        "coordinates": [
          -0.366667,
          52.816667
        ]
      },
      "type": "Feature",
      "properties": {
        "hierarchy": [
          "tgn:4009307",
          "tgn:7002445",
          "tgn:1000003",
          "tgn:7008157",
          "tgn:7008591",
          "tgn:7029392"
        ],
        "placetype": [
          "aat:300008347",
          "aat:300008372"
        ],
        "name:en": "Rippingale",
        "id": 4009307
      }
    },
    {
      "geometry": {
        "type": "Point",
        "coordinates": [
          -2.516667,
          53.416667
        ]
      },
      "type": "Feature",
      "properties": {
        "hierarchy": [
          "tgn:4009309",
          "tgn:7002445",
          "tgn:1000003",
          "tgn:7026534",
          "tgn:7008591",
          "tgn:7029392"
        ],
        "placetype": [
          "aat:300008347"
        ],
        "name:en": "Risley",
        "id": 4009309
      }
    }
  ]
}
