{
  "geometry": {
    "type": "Point",
    "coordinates": [
      -78.4833,
      38.0333
    ]
  },
  "type": "Feature",
  "properties": {
    "hierarchy": [
      "tgn:2647147",
      "tgn:1000001",
      "tgn:7012149",
      "tgn:7007919",
      "tgn:7029392"
    ],
    "placetype": [
      "aat:300008699"
    ],
    "id": 2647147,
    "name:xx": "Schenks Branch"
  }
}
