{
  "geometry": {
    "type": "Point",
    "coordinates": [
      -85.6667,
      12.3333
    ]
  },
  "type": "Feature",
  "properties": {
    "hierarchy": [
      "tgn:1018780",
      "tgn:1000528",
      "tgn:1000001",
      "tgn:7005562",
      "tgn:7029392"
    ],
    "placetype": [
      "aat:300008347"
    ],
    "id": 1018780,
    "name:xx": "San Lorenzo"
  }
}
