{
  "geometry": {
    "type": "Point",
    "coordinates": [
      -121.65,
      39.1333
    ]
  },
  "type": "Feature",
  "properties": {
    "hierarchy": [
      "tgn:2014601",
      "tgn:1000001",
      "tgn:7012149",
      "tgn:7007157",
      "tgn:1002937",
      "tgn:7029392"
    ],
    "placetype": [
      "aat:300008347"
    ],
    "id": 2014601,
    "name:xx": "Tierra Buena"
  }
}
