{
  "geometry": {
    "type": "Point",
    "coordinates": [
      -79.5833,
      34.8667
    ]
  },
  "type": "Feature",
  "properties": {
    "hierarchy": [
      "tgn:2739390",
      "tgn:1000001",
      "tgn:7012149",
      "tgn:2001539",
      "tgn:7007709",
      "tgn:7029392"
    ],
    "placetype": [
      "aat:300008706"
    ],
    "id": 2739390,
    "name:xx": "Upper Beaverdam Creek"
  }
}
