{
  "type": "FeatureCollection",
  "features": [
    {
      "geometry": {
        "type": "Point",
        "coordinates": [
          -101.3167,
          35.9833
        ]
      },
      "type": "Feature",
      "properties": {
        "hierarchy": [
          "tgn:2522820",
          "tgn:1000001",
          "tgn:7012149",
          "tgn:2002006",
          "tgn:7007826",
          "tgn:7029392"
        ],
        "placetype": [
          "aat:300008706"
        ],
        "id": 2522820,
        "name:xx": "Moore Creek"
      }
    },
    {
      "geometry": {
        "type": "Point",
        "coordinates": [
          -76.35,
          37.55
        ]
      },
      "type": "Feature",
      "properties": {
        "hierarchy": [
          "tgn:2522821",
          "tgn:1000001",
          "tgn:7012149",
          "tgn:1002667",
          "tgn:7007919",
          "tgn:7029392"
        ],
        "placetype": [
          "aat:300008706"
        ],
        "id": 2522821,
        "name:xx": "Moore Creek"
      }
    },
    {
      "geometry": {
        "type": "Point",
        "coordinates": [
          -78.0333,
          37.4833
        ]
      },
      "type": "Feature",
      "properties": {
        "hierarchy": [
          "tgn:2522822",
          "tgn:1000001",
          "tgn:7012149",
          "tgn:2002181",
          "tgn:7007919",
          "tgn:7029392"
        ],
        "placetype": [
          "aat:300008706"
        ],
        "id": 2522822,
        "name:xx": "Moore Creek"
      }
    },
    {
      "geometry": {
        "type": "Point",
        "coordinates": [
          -79.6667,
          37.7333
        ]
      },
      "type": "Feature",
      "properties": {
        "hierarchy": [
          "tgn:2522823",
          "tgn:1000001",
          "tgn:7012149",
          "tgn:2002186",
          "tgn:7007919",
          "tgn:7029392"
        ],
        "placetype": [
          "aat:300008706"
        ],
        "id": 2522823,
        "name:xx": "Moore Creek"
      }
    },
    {
      "geometry": {
        "type": "Point",
        "coordinates": [
          -81.0167,
          36.6333
        ]
      },
      "type": "Feature",
      "properties": {
        "hierarchy": [
          "tgn:2522824",
          "tgn:1000001",
          "tgn:7012149",
          "tgn:2002164",
          "tgn:7007919",
          "tgn:7029392"
        ],
        "placetype": [
          "aat:300008706"
        ],
        "id": 2522824,
        "name:xx": "Moore Creek"
      }
    },
    {
      "geometry": {
        "type": "Point",
        "coordinates": [
          -121.8667,
          45.7333
        ]
      },
      "type": "Feature",
      "properties": {
        "hierarchy": [
          "tgn:2522825",
          "tgn:1000001",
          "tgn:7012149",
          "tgn:1002897",
          "tgn:7007920",
          "tgn:7029392"
        ],
        "placetype": [
          "aat:300008706"
        ],
        "id": 2522825,
        "name:xx": "Moore Creek"
      }
    },
    {
      "geometry": {
        "type": "Point",
        "coordinates": [
          -90.55,
          43.8333
        ]
      },
      "type": "Feature",
      "properties": {
        "hierarchy": [
          "tgn:2522826",
          "tgn:1000001",
          "tgn:7012149",
          "tgn:2002340",
          "tgn:7007922",
          "tgn:7029392"
        ],
        "placetype": [
          "aat:300008706"
        ],
        "id": 2522826,
        "name:xx": "Moore Creek"
      }
    },
    {
      "geometry": {
        "type": "Point",
        "coordinates": [
          -110.65,
          42.1
        ]
      },
      "type": "Feature",
      "properties": {
        "hierarchy": [
          "tgn:2522827",
          "tgn:1000001",
          "tgn:7012149",
          "tgn:2002376",
          "tgn:7007923",
          "tgn:7029392"
        ],
        "placetype": [
          "aat:300008706"
        ],
        "id": 2522827,
        "name:xx": "Moore Creek"
      }
    },
    {
      "geometry": {
        "type": "Point",
        "coordinates": [
          -104.6667,
          44.7167
        ]
      },
      "type": "Feature",
      "properties": {
        "hierarchy": [
          "tgn:2522828",
          "tgn:1000001",
          "tgn:2002370",
          "tgn:7012149",
          "tgn:7007923",
          "tgn:7029392"
        ],
        "placetype": [
          "aat:300008706"
        ],
        "id": 2522828,
        "name:xx": "Moore Creek"
      }
    },
    {
      "geometry": {
        "type": "Point",
        "coordinates": [
          -83.5667,
          35.1
        ]
      },
      "type": "Feature",
      "properties": {
        "hierarchy": [
          "tgn:2522829",
          "tgn:1000001",
          "tgn:7012149",
          "tgn:2001515",
          "tgn:7007709",
          "tgn:7029392"
        ],
        "placetype": [
          "aat:300006191"
        ],
        "id": 2522829,
        "name:xx": "Moore Creek Lower Lake"
      }
    }
  ]
}
