{
  "geometry": {
    "type": "Point",
    "coordinates": [
      37.6667,
      -3.3833
    ]
  },
  "type": "Feature",
  "properties": {
    "hierarchy": [
      "tgn:1090553",
      "tgn:7001242",
      "tgn:7593795",
      "tgn:1000169",
      "tgn:7029392"
    ],
    "placetype": [
      "aat:300008347"
    ],
    "id": 1090553,
    "name:xx": "Taveta"
  }
}
