{
  "geometry": {
    "type": "Point",
    "coordinates": [
      -83.9167,
      36.3333
    ]
  },
  "type": "Feature",
  "properties": {
    "hierarchy": [
      "tgn:2765719",
      "tgn:1000001",
      "tgn:7012149",
      "tgn:2001923",
      "tgn:7007825",
      "tgn:7029392"
    ],
    "placetype": [
      "aat:300008706"
    ],
    "id": 2765719,
    "name:xx": "White Creek"
  }
}
