{
  "geometry": {
    "type": "Point",
    "coordinates": [
      -77.1167,
      34.6667
    ]
  },
  "type": "Feature",
  "properties": {
    "hierarchy": [
      "tgn:2380984",
      "tgn:1000001",
      "tgn:7012149",
      "tgn:2001524",
      "tgn:7007709",
      "tgn:7029392"
    ],
    "placetype": [
      "aat:300132316"
    ],
    "id": 2380984,
    "name:xx": "Hawkins Bay"
  }
}
