{
  "geometry": {
    "type": "Point",
    "coordinates": [
      -113.4333,
      42.1833
    ]
  },
  "type": "Feature",
  "properties": {
    "hierarchy": [
      "tgn:2431000",
      "tgn:1000001",
      "tgn:2000467",
      "tgn:7012149",
      "tgn:7007250",
      "tgn:7029392"
    ],
    "placetype": [
      "aat:300008697"
    ],
    "id": 2431000,
    "name:xx": "Kane Spring"
  }
}
