{
  "geometry": {
    "type": "Point",
    "coordinates": [
      -89.05,
      13.3667
    ]
  },
  "type": "Feature",
  "properties": {
    "hierarchy": [
      "tgn:1016547",
      "tgn:7005457",
      "tgn:1000001",
      "tgn:7005441",
      "tgn:7029392"
    ],
    "placetype": [
      "aat:300008347"
    ],
    "id": 1016547,
    "name:xx": "San Marcelino"
  }
}
