{
  "geometry": {
    "type": "Point",
    "coordinates": [
      -117.8833,
      34.6167
    ]
  },
  "type": "Feature",
  "properties": {
    "hierarchy": [
      "tgn:2131085",
      "tgn:1000001",
      "tgn:7012149",
      "tgn:7007157",
      "tgn:1002608",
      "tgn:7029392"
    ],
    "placetype": [
      "aat:300008798"
    ],
    "id": 2131085,
    "name:xx": "Alpine Butte"
  }
}
