{
  "geometry": {
    "type": "Point",
    "coordinates": [
      -64.75,
      -23.8333
    ]
  },
  "type": "Feature",
  "properties": {
    "hierarchy": [
      "tgn:1019689",
      "tgn:7006477",
      "tgn:1001328",
      "tgn:1000002",
      "tgn:7029392"
    ],
    "placetype": [
      "aat:300008347"
    ],
    "id": 1019689,
    "name:xx": "Libertador General San Martin"
  }
}
