{
  "geometry": {
    "type": "Point",
    "coordinates": [
      120.47,
      23.9925
    ]
  },
  "type": "Feature",
  "properties": {
    "hierarchy": [
      "tgn:7490198",
      "tgn:1000004",
      "tgn:7467799",
      "tgn:1000141",
      "tgn:7029392"
    ],
    "placetype": [
      "aat:300008347"
    ],
    "id": 7490198,
    "name:xx": "Bunancun"
  }
}
