{
  "geometry": {
    "type": "Point",
    "coordinates": [
      77.474172,
      29.65542
    ]
  },
  "type": "Feature",
  "properties": {
    "hierarchy": [
      "tgn:7568687",
      "tgn:1000004",
      "tgn:7000198",
      "tgn:7016722",
      "tgn:7029392"
    ],
    "placetype": [
      "aat:300008347"
    ],
    "name:en": "Alīpur",
    "id": 7568687
  }
}
