{
  "geometry": {
    "type": "Point",
    "coordinates": [
      75.7167,
      35.45
    ]
  },
  "type": "Feature",
  "properties": {
    "hierarchy": [
      "tgn:1129962",
      "tgn:7000367",
      "tgn:1000004",
      "tgn:1000133",
      "tgn:7029392"
    ],
    "placetype": [
      "aat:300008707"
    ],
    "id": 1129962,
    "name:xx": "Shigar"
  }
}
