{
  "geometry": {
    "type": "Point",
    "coordinates": [
      106.2667,
      22.6667
    ]
  },
  "type": "Feature",
  "properties": {
    "hierarchy": [
      "tgn:1087089",
      "tgn:7001031",
      "tgn:1000004",
      "tgn:1000145",
      "tgn:7029392"
    ],
    "placetype": [
      "aat:300008347",
      "aat:300387223",
      "aat:300008375"
    ],
    "id": 1087089,
    "name:xx": "Cao Bằng"
  }
}
