{
  "geometry": {
    "type": "Point",
    "coordinates": [
      -119.4167,
      44.2167
    ]
  },
  "type": "Feature",
  "properties": {
    "hierarchy": [
      "tgn:2487992",
      "tgn:1000001",
      "tgn:7012149",
      "tgn:2001708",
      "tgn:7007708",
      "tgn:7029392"
    ],
    "placetype": [
      "aat:300008697"
    ],
    "id": 2487992,
    "name:xx": "Maggot Spring"
  }
}
