{
  "geometry": {
    "type": "Point",
    "coordinates": [
      -111.2333,
      41.7667
    ]
  },
  "type": "Feature",
  "properties": {
    "hierarchy": [
      "tgn:2740854",
      "tgn:1000001",
      "tgn:7012149",
      "tgn:2002117",
      "tgn:7007827",
      "tgn:7029392"
    ],
    "placetype": [
      "aat:300008697"
    ],
    "id": 2740854,
    "name:xx": "Upper Sage Creek Spring"
  }
}
