{
  "geometry": {
    "type": "Point",
    "coordinates": [
      -5.43,
      36.0575
    ]
  },
  "type": "Feature",
  "properties": {
    "hierarchy": [
      "tgn:7295594",
      "tgn:7002813",
      "tgn:7002758",
      "tgn:1000003",
      "tgn:1000095",
      "tgn:7029392"
    ],
    "placetype": [
      "aat:300387036"
    ],
    "id": 7295594,
    "name:xx": "La Perla"
  }
}
