{
  "geometry": {
    "type": "Point",
    "coordinates": [
      -75.5333,
      40.1167
    ]
  },
  "type": "Feature",
  "properties": {
    "hierarchy": [
      "tgn:2094036",
      "tgn:1000001",
      "tgn:1002266",
      "tgn:7012149",
      "tgn:7007710",
      "tgn:7029392"
    ],
    "placetype": [
      "aat:300006610"
    ],
    "id": 2094036,
    "name:xx": "Valley Forge Christian College"
  }
}
