{
  "geometry": {
    "type": "Point",
    "coordinates": [
      75.73325,
      26.244393
    ]
  },
  "type": "Feature",
  "properties": {
    "hierarchy": [
      "tgn:7579203",
      "tgn:1000004",
      "tgn:7000198",
      "tgn:7016788",
      "tgn:7029392"
    ],
    "placetype": [
      "aat:300008699"
    ],
    "name:en": "Sohadra Nadī",
    "id": 7579203
  }
}
