{
  "geometry": {
    "type": "Point",
    "coordinates": [
      -113.4333,
      41.9667
    ]
  },
  "type": "Feature",
  "properties": {
    "hierarchy": [
      "tgn:2687210",
      "tgn:1000001",
      "tgn:2002102",
      "tgn:7012149",
      "tgn:7007827",
      "tgn:7029392"
    ],
    "placetype": [
      "aat:300008761"
    ],
    "id": 2687210,
    "name:xx": "Spring Hollow"
  }
}
