{
  "geometry": {
    "type": "Point",
    "coordinates": [
      -122.2333,
      45.4667
    ]
  },
  "type": "Feature",
  "properties": {
    "hierarchy": [
      "tgn:2561407",
      "tgn:1000001",
      "tgn:7012149",
      "tgn:1002699",
      "tgn:7007708",
      "tgn:7029392"
    ],
    "placetype": [
      "aat:300006191"
    ],
    "id": 2561407,
    "name:xx": "Osburn Reservoir"
  }
}
