{
  "geometry": {
    "type": "Point",
    "coordinates": [
      -176.15,
      52.05
    ]
  },
  "type": "Feature",
  "properties": {
    "hierarchy": [
      "tgn:2127519",
      "tgn:7030516",
      "tgn:7006450",
      "tgn:1000001",
      "tgn:7012149",
      "tgn:7029392"
    ],
    "placetype": [
      "aat:300008706"
    ],
    "id": 2127519,
    "name:xx": "Akuyan Creek"
  }
}
