{
  "geometry": {
    "type": "Point",
    "coordinates": [
      -70.4833,
      43.85
    ]
  },
  "type": "Feature",
  "properties": {
    "hierarchy": [
      "tgn:2567566",
      "tgn:1000001",
      "tgn:2000920",
      "tgn:7012149",
      "tgn:7007515",
      "tgn:7029392"
    ],
    "placetype": [
      "aat:300008791"
    ],
    "id": 2567566,
    "name:xx": "Papoose Island"
  }
}
