{
  "geometry": {
    "type": "Point",
    "coordinates": [
      21.8333,
      37.25
    ]
  },
  "type": "Feature",
  "properties": {
    "hierarchy": [
      "tgn:7011369",
      "tgn:7017076",
      "tgn:1000003",
      "tgn:1000074",
      "tgn:7029392"
    ],
    "placetype": [
      "aat:300387145",
      "aat:300000772",
      "aat:300387131"
    ],
    "id": 7011369,
    "name:xx": "Messinía"
  }
}
