{
  "geometry": {
    "type": "Point",
    "coordinates": [
      19.7333,
      -28.1833
    ]
  },
  "type": "Feature",
  "properties": {
    "hierarchy": [
      "tgn:1094034",
      "tgn:7001242",
      "tgn:7030585",
      "tgn:1000198",
      "tgn:7029392"
    ],
    "placetype": [
      "aat:300008347"
    ],
    "id": 1094034,
    "name:xx": "Ukamas"
  }
}
