{
  "geometry": {
    "type": "Point",
    "coordinates": [
      -76.6333,
      41.5833
    ]
  },
  "type": "Feature",
  "properties": {
    "hierarchy": [
      "tgn:2480085",
      "tgn:1000001",
      "tgn:1002194",
      "tgn:7012149",
      "tgn:7007710",
      "tgn:7029392"
    ],
    "placetype": [
      "aat:300008798"
    ],
    "id": 2480085,
    "name:xx": "Lake Knob"
  }
}
