{
  "geometry": {
    "type": "Point",
    "coordinates": [
      -100.25,
      21.216667
    ]
  },
  "type": "Feature",
  "properties": {
    "hierarchy": [
      "tgn:7384660",
      "tgn:7005584",
      "tgn:1000001",
      "tgn:7005560",
      "tgn:7029392"
    ],
    "placetype": [
      "aat:300008347"
    ],
    "id": 7384660,
    "name:xx": "Misión de Arnedo"
  }
}
