{
  "geometry": {
    "type": "Point",
    "coordinates": [
      -119.6833,
      41.75
    ]
  },
  "type": "Feature",
  "properties": {
    "hierarchy": [
      "tgn:2477628",
      "tgn:1000001",
      "tgn:7012149",
      "tgn:1002999",
      "tgn:7007526",
      "tgn:7029392"
    ],
    "placetype": [
      "aat:300008697"
    ],
    "id": 2477628,
    "name:xx": "MC Springs"
  }
}
