{
  "type": "FeatureCollection",
  "features": [
    {
      "geometry": {
        "type": "Point",
        "coordinates": [
          8.616667,
          48.216667
        ]
      },
      "type": "Feature",
      "properties": {
        "hierarchy": [
          "tgn:7158720",
          "tgn:7003692",
          "tgn:1000003",
          "tgn:7000084",
          "tgn:7029392"
        ],
        "placetype": [
          "aat:300008057"
        ],
        "id": 7158720,
        "name:xx": "Ruine Hohenstein"
      }
    },
    {
      "geometry": {
        "type": "Point",
        "coordinates": [
          9.333333,
          51.65
        ]
      },
      "type": "Feature",
      "properties": {
        "hierarchy": [
          "tgn:7158721",
          "tgn:1000003",
          "tgn:7003677",
          "tgn:7000084",
          "tgn:7029392"
        ],
        "placetype": [
          "aat:300004792"
        ],
        "id": 7158721,
        "name:xx": "Försterei Hohenstein"
      }
    },
    {
      "geometry": {
        "type": "Point",
        "coordinates": [
          8.716667,
          49.716667
        ]
      },
      "type": "Feature",
      "properties": {
        "hierarchy": [
          "tgn:7158722",
          "tgn:1000003",
          "tgn:7003678",
          "tgn:7000084",
          "tgn:7029392"
        ],
        "placetype": [
          "aat:300004792"
        ],
        "id": 7158722,
        "name:xx": "Försterei Hohenstein"
      }
    },
    {
      "geometry": {
        "type": "Point",
        "coordinates": [
          9.333333,
          52.2
        ]
      },
      "type": "Feature",
      "properties": {
        "hierarchy": [
          "tgn:7158723",
          "tgn:1000003",
          "tgn:7003676",
          "tgn:7000084",
          "tgn:7029392"
        ],
        "placetype": [
          "aat:300266640"
        ],
        "id": 7158723,
        "name:xx": "Hohenstein"
      }
    },
    {
      "geometry": {
        "type": "Point",
        "coordinates": [
          10.8,
          54.283333
        ]
      },
      "type": "Feature",
      "properties": {
        "hierarchy": [
          "tgn:7158724",
          "tgn:1000003",
          "tgn:7003688",
          "tgn:7000084",
          "tgn:7029392"
        ],
        "placetype": [
          "aat:300008347"
        ],
        "id": 7158724,
        "name:xx": "Hohenstein"
      }
    },
    {
      "geometry": {
        "type": "Point",
        "coordinates": [
          13.583333,
          53.633333
        ]
      },
      "type": "Feature",
      "properties": {
        "hierarchy": [
          "tgn:7158725",
          "tgn:1000003",
          "tgn:7000094",
          "tgn:7000084",
          "tgn:7029392"
        ],
        "placetype": [
          "aat:300008347"
        ],
        "id": 7158725,
        "name:xx": "Hohenstein"
      }
    },
    {
      "geometry": {
        "type": "Point",
        "coordinates": [
          13.966667,
          52.566667
        ]
      },
      "type": "Feature",
      "properties": {
        "hierarchy": [
          "tgn:7158726",
          "tgn:7000096",
          "tgn:1000003",
          "tgn:7000084",
          "tgn:7029392"
        ],
        "placetype": [
          "aat:300008347"
        ],
        "id": 7158726,
        "name:xx": "Hohenstein"
      }
    },
    {
      "geometry": {
        "type": "Point",
        "coordinates": [
          10.933333,
          50.216667
        ]
      },
      "type": "Feature",
      "properties": {
        "hierarchy": [
          "tgn:7158727",
          "tgn:7003669",
          "tgn:1000003",
          "tgn:7000084",
          "tgn:7029392"
        ],
        "placetype": [
          "aat:300008347"
        ],
        "id": 7158727,
        "name:xx": "Hohenstein"
      }
    },
    {
      "geometry": {
        "type": "Point",
        "coordinates": [
          8.066667,
          50.2
        ]
      },
      "type": "Feature",
      "properties": {
        "hierarchy": [
          "tgn:7158728",
          "tgn:1000003",
          "tgn:7003678",
          "tgn:7000084",
          "tgn:7029392"
        ],
        "placetype": [
          "aat:300387173"
        ],
        "id": 7158728,
        "name:xx": "Hohenstein"
      }
    },
    {
      "geometry": {
        "type": "Point",
        "coordinates": [
          11.433333,
          49.583333
        ]
      },
      "type": "Feature",
      "properties": {
        "hierarchy": [
          "tgn:7158729",
          "tgn:7003669",
          "tgn:1000003",
          "tgn:7000084",
          "tgn:7029392"
        ],
        "placetype": [
          "aat:300008347"
        ],
        "id": 7158729,
        "name:xx": "Hohenstein"
      }
    }
  ]
}
