{
  "geometry": {
    "type": "Point",
    "coordinates": [
      -89.3667,
      45.8333
    ]
  },
  "type": "Feature",
  "properties": {
    "hierarchy": [
      "tgn:2700844",
      "tgn:1000001",
      "tgn:7012149",
      "tgn:2002342",
      "tgn:7007922",
      "tgn:7029392"
    ],
    "placetype": [
      "aat:300008706"
    ],
    "id": 2700844,
    "name:xx": "Sugar Camp Creek"
  }
}
