{
  "geometry": {
    "type": "Point",
    "coordinates": [
      -78.65,
      35.65
    ]
  },
  "type": "Feature",
  "properties": {
    "hierarchy": [
      "tgn:2690356",
      "tgn:1000001",
      "tgn:7012149",
      "tgn:2001548",
      "tgn:7007709",
      "tgn:7029392"
    ],
    "placetype": [
      "aat:300008347"
    ],
    "id": 2690356,
    "name:xx": "Stagecrest"
  }
}
