{
  "geometry": {
    "type": "Point",
    "coordinates": [
      41.55,
      40.3167
    ]
  },
  "type": "Feature",
  "properties": {
    "hierarchy": [
      "tgn:1086943",
      "tgn:7016655",
      "tgn:1000004",
      "tgn:7018455",
      "tgn:1000144",
      "tgn:7029392"
    ],
    "placetype": [
      "aat:300008347"
    ],
    "id": 1086943,
    "name:xx": "Tortum"
  }
}
