{
  "geometry": {
    "type": "Point",
    "coordinates": [
      -95.6333,
      44.9167
    ]
  },
  "type": "Feature",
  "properties": {
    "hierarchy": [
      "tgn:2261007",
      "tgn:1000001",
      "tgn:2001010",
      "tgn:7012149",
      "tgn:7007521",
      "tgn:7029392"
    ],
    "placetype": [
      "aat:300006075"
    ],
    "id": 2261007,
    "name:xx": "County Ditch Number Thirtysix A"
  }
}
