{
  "type": "FeatureCollection",
  "features": [
    {
      "geometry": {
        "type": "Point",
        "coordinates": [
          -95.7167,
          42.35
        ]
      },
      "type": "Feature",
      "properties": {
        "hierarchy": [
          "tgn:2167480",
          "tgn:1000001",
          "tgn:7012149",
          "tgn:2000657",
          "tgn:7007253",
          "tgn:7029392"
        ],
        "placetype": [
          "aat:300008706"
        ],
        "id": 2167480,
        "name:xx": "Big Creek"
      }
    },
    {
      "geometry": {
        "type": "Point",
        "coordinates": [
          -95.3833,
          42.2
        ]
      },
      "type": "Feature",
      "properties": {
        "hierarchy": [
          "tgn:2167481",
          "tgn:1000001",
          "tgn:2000584",
          "tgn:7012149",
          "tgn:7007253",
          "tgn:7029392"
        ],
        "placetype": [
          "aat:300008706"
        ],
        "id": 2167481,
        "name:xx": "Big Creek"
      }
    },
    {
      "geometry": {
        "type": "Point",
        "coordinates": [
          -91.4667,
          42.1333
        ]
      },
      "type": "Feature",
      "properties": {
        "hierarchy": [
          "tgn:2167482",
          "tgn:1000001",
          "tgn:7012149",
          "tgn:2000617",
          "tgn:7007253",
          "tgn:7029392"
        ],
        "placetype": [
          "aat:300008706"
        ],
        "id": 2167482,
        "name:xx": "Big Creek"
      }
    },
    {
      "geometry": {
        "type": "Point",
        "coordinates": [
          -93.8333,
          42.05
        ]
      },
      "type": "Feature",
      "properties": {
        "hierarchy": [
          "tgn:2167483",
          "tgn:1000001",
          "tgn:7012149",
          "tgn:7007253",
          "tgn:7029392"
        ],
        "placetype": [
          "aat:300008706"
        ],
        "id": 2167483,
        "name:xx": "Big Creek"
      }
    },
    {
      "geometry": {
        "type": "Point",
        "coordinates": [
          -99.2333,
          39.8167
        ]
      },
      "type": "Feature",
      "properties": {
        "hierarchy": [
          "tgn:2167484",
          "tgn:1000001",
          "tgn:7012149",
          "tgn:2000733",
          "tgn:7007254",
          "tgn:7029392"
        ],
        "placetype": [
          "aat:300008706"
        ],
        "id": 2167484,
        "name:xx": "Big Creek"
      }
    },
    {
      "geometry": {
        "type": "Point",
        "coordinates": [
          -95.7167,
          38.0833
        ]
      },
      "type": "Feature",
      "properties": {
        "hierarchy": [
          "tgn:2167485",
          "tgn:1000001",
          "tgn:2000675",
          "tgn:7012149",
          "tgn:7007254",
          "tgn:7029392"
        ],
        "placetype": [
          "aat:300008706"
        ],
        "id": 2167485,
        "name:xx": "Big Creek"
      }
    },
    {
      "geometry": {
        "type": "Point",
        "coordinates": [
          -85.45,
          37.0167
        ]
      },
      "type": "Feature",
      "properties": {
        "hierarchy": [
          "tgn:2167486",
          "tgn:2000765",
          "tgn:1000001",
          "tgn:7012149",
          "tgn:7007255",
          "tgn:7029392"
        ],
        "placetype": [
          "aat:300008706"
        ],
        "id": 2167486,
        "name:xx": "Big Creek"
      }
    },
    {
      "geometry": {
        "type": "Point",
        "coordinates": [
          -83.5167,
          37.15
        ]
      },
      "type": "Feature",
      "properties": {
        "hierarchy": [
          "tgn:2167487",
          "tgn:1000001",
          "tgn:7012149",
          "tgn:7007255",
          "tgn:7029392"
        ],
        "placetype": [
          "aat:300008706"
        ],
        "id": 2167487,
        "name:xx": "Big Creek"
      }
    },
    {
      "geometry": {
        "type": "Point",
        "coordinates": [
          -84.4667,
          36.7333
        ]
      },
      "type": "Feature",
      "properties": {
        "hierarchy": [
          "tgn:2167488",
          "tgn:1000001",
          "tgn:7012149",
          "tgn:2000818",
          "tgn:7007255",
          "tgn:7029392"
        ],
        "placetype": [
          "aat:300008706"
        ],
        "id": 2167488,
        "name:xx": "Big Creek"
      }
    },
    {
      "geometry": {
        "type": "Point",
        "coordinates": [
          -83.1667,
          37.1833
        ]
      },
      "type": "Feature",
      "properties": {
        "hierarchy": [
          "tgn:2167489",
          "tgn:1000001",
          "tgn:7012149",
          "tgn:2000836",
          "tgn:7007255",
          "tgn:7029392"
        ],
        "placetype": [
          "aat:300008706"
        ],
        "id": 2167489,
        "name:xx": "Big Creek"
      }
    }
  ]
}
