{
  "geometry": {
    "type": "Point",
    "coordinates": [
      -9.9333,
      52.05
    ]
  },
  "type": "Feature",
  "properties": {
    "hierarchy": [
      "tgn:1042813",
      "tgn:7003498",
      "tgn:7001201",
      "tgn:1000003",
      "tgn:1000078",
      "tgn:7029392"
    ],
    "placetype": [
      "aat:300008347"
    ],
    "id": 1042813,
    "name:xx": "Glenbeigh"
  }
}
