{
  "geometry": {
    "type": "Point",
    "coordinates": [
      -83.8833,
      37.9167
    ]
  },
  "type": "Feature",
  "properties": {
    "hierarchy": [
      "tgn:2494502",
      "tgn:1000001",
      "tgn:7012149",
      "tgn:7007255",
      "tgn:7029392"
    ],
    "placetype": [
      "aat:300008699"
    ],
    "id": 2494502,
    "name:xx": "Martin Fork"
  }
}
