{
  "type": "FeatureCollection",
  "features": [
    {
      "geometry": {
        "type": "Point",
        "coordinates": [
          -94.5833,
          31.1
        ]
      },
      "type": "Feature",
      "properties": {
        "hierarchy": [
          "tgn:2166740",
          "tgn:1002149",
          "tgn:1000001",
          "tgn:7012149",
          "tgn:7007826",
          "tgn:7029392"
        ],
        "placetype": [
          "aat:300008699"
        ],
        "id": 2166740,
        "name:xx": "Big Branch"
      }
    },
    {
      "geometry": {
        "type": "Point",
        "coordinates": [
          -96.1333,
          31.2667
        ]
      },
      "type": "Feature",
      "properties": {
        "hierarchy": [
          "tgn:2166741",
          "tgn:1000001",
          "tgn:7012149",
          "tgn:1002590",
          "tgn:7007826",
          "tgn:7029392"
        ],
        "placetype": [
          "aat:300008699"
        ],
        "id": 2166741,
        "name:xx": "Big Branch"
      }
    },
    {
      "geometry": {
        "type": "Point",
        "coordinates": [
          -93.7167,
          31.3
        ]
      },
      "type": "Feature",
      "properties": {
        "hierarchy": [
          "tgn:2166742",
          "tgn:1000001",
          "tgn:7012149",
          "tgn:2002066",
          "tgn:7007826",
          "tgn:7029392"
        ],
        "placetype": [
          "aat:300008699"
        ],
        "id": 2166742,
        "name:xx": "Big Branch"
      }
    },
    {
      "geometry": {
        "type": "Point",
        "coordinates": [
          -94.1833,
          31.3
        ]
      },
      "type": "Feature",
      "properties": {
        "hierarchy": [
          "tgn:2166743",
          "tgn:1000001",
          "tgn:7012149",
          "tgn:2002067",
          "tgn:7007826",
          "tgn:7029392"
        ],
        "placetype": [
          "aat:300008699"
        ],
        "id": 2166743,
        "name:xx": "Big Branch"
      }
    },
    {
      "geometry": {
        "type": "Point",
        "coordinates": [
          -93.85,
          31.6833
        ]
      },
      "type": "Feature",
      "properties": {
        "hierarchy": [
          "tgn:2166744",
          "tgn:1000001",
          "tgn:7012149",
          "tgn:2002073",
          "tgn:7007826",
          "tgn:7029392"
        ],
        "placetype": [
          "aat:300008699"
        ],
        "id": 2166744,
        "name:xx": "Big Branch"
      }
    },
    {
      "geometry": {
        "type": "Point",
        "coordinates": [
          -93.8833,
          30.45
        ]
      },
      "type": "Feature",
      "properties": {
        "hierarchy": [
          "tgn:2166745",
          "tgn:1000001",
          "tgn:7012149",
          "tgn:2002047",
          "tgn:7007826",
          "tgn:7029392"
        ],
        "placetype": [
          "aat:300008699"
        ],
        "id": 2166745,
        "name:xx": "Big Branch"
      }
    },
    {
      "geometry": {
        "type": "Point",
        "coordinates": [
          -95.1833,
          30.8833
        ]
      },
      "type": "Feature",
      "properties": {
        "hierarchy": [
          "tgn:2166746",
          "tgn:1000001",
          "tgn:7012149",
          "tgn:1002954",
          "tgn:7007826",
          "tgn:7029392"
        ],
        "placetype": [
          "aat:300008699"
        ],
        "id": 2166746,
        "name:xx": "Big Branch"
      }
    },
    {
      "geometry": {
        "type": "Point",
        "coordinates": [
          -95.2833,
          31.2667
        ]
      },
      "type": "Feature",
      "properties": {
        "hierarchy": [
          "tgn:2166747",
          "tgn:1000001",
          "tgn:7012149",
          "tgn:1002486",
          "tgn:7007826",
          "tgn:7029392"
        ],
        "placetype": [
          "aat:300008699"
        ],
        "id": 2166747,
        "name:xx": "Big Branch"
      }
    },
    {
      "geometry": {
        "type": "Point",
        "coordinates": [
          -97.8833,
          30.75
        ]
      },
      "type": "Feature",
      "properties": {
        "hierarchy": [
          "tgn:2166748",
          "tgn:1000001",
          "tgn:7012149",
          "tgn:1003026",
          "tgn:7007826",
          "tgn:7029392"
        ],
        "placetype": [
          "aat:300008699"
        ],
        "id": 2166748,
        "name:xx": "Big Branch"
      }
    },
    {
      "geometry": {
        "type": "Point",
        "coordinates": [
          -94.4667,
          33.3333
        ]
      },
      "type": "Feature",
      "properties": {
        "hierarchy": [
          "tgn:2166749",
          "tgn:1000001",
          "tgn:2001944",
          "tgn:7012149",
          "tgn:7007826",
          "tgn:7029392"
        ],
        "placetype": [
          "aat:300008699"
        ],
        "id": 2166749,
        "name:xx": "Big Branch"
      }
    }
  ]
}
