{
  "geometry": {
    "type": "Point",
    "coordinates": [
      139.6333,
      35.5333
    ]
  },
  "type": "Feature",
  "properties": {
    "hierarchy": [
      "tgn:1005769",
      "tgn:7016696",
      "tgn:1000004",
      "tgn:7000894",
      "tgn:7004836",
      "tgn:1000120",
      "tgn:7029392"
    ],
    "placetype": [
      "aat:300000745"
    ],
    "id": 1005769,
    "name:xx": "Tsunashima"
  }
}
