{
  "geometry": {
    "type": "Point",
    "coordinates": [
      -114.2667,
      43.65
    ]
  },
  "type": "Feature",
  "properties": {
    "hierarchy": [
      "tgn:2729507",
      "tgn:1000001",
      "tgn:2000458",
      "tgn:7012149",
      "tgn:7007250",
      "tgn:7029392"
    ],
    "placetype": [
      "aat:300008761"
    ],
    "id": 2729507,
    "name:xx": "Triumph Gulch"
  }
}
