{
  "geometry": {
    "type": "Point",
    "coordinates": [
      -108.6333,
      46.3667
    ]
  },
  "type": "Feature",
  "properties": {
    "hierarchy": [
      "tgn:2534735",
      "tgn:1000001",
      "tgn:7012149",
      "tgn:2001292",
      "tgn:7007524",
      "tgn:7029392"
    ],
    "placetype": [
      "aat:300006075"
    ],
    "id": 2534735,
    "name:xx": "Naderman Ditch"
  }
}
