{
  "geometry": {
    "type": "Point",
    "coordinates": [
      10.35,
      47.55
    ]
  },
  "type": "Feature",
  "properties": {
    "hierarchy": [
      "tgn:7159127",
      "tgn:7003669",
      "tgn:1000003",
      "tgn:7000084",
      "tgn:7029392"
    ],
    "placetype": [
      "aat:300008699"
    ],
    "id": 7159127,
    "name:xx": "Höll Bach"
  }
}
