{
  "geometry": {
    "type": "Point",
    "coordinates": [
      -109.7833,
      33.2333
    ]
  },
  "type": "Feature",
  "properties": {
    "hierarchy": [
      "tgn:2635324",
      "tgn:1000001",
      "tgn:7006451",
      "tgn:2000094",
      "tgn:7012149",
      "tgn:7029392"
    ],
    "placetype": [
      "aat:300006191"
    ],
    "id": 2635324,
    "name:xx": "SCS Tank"
  }
}
