{
  "type": "FeatureCollection",
  "features": [
    {
      "geometry": {
        "type": "Point",
        "coordinates": [
          -110.433333,
          24.6
        ]
      },
      "type": "Feature",
      "properties": {
        "hierarchy": [
          "tgn:7380540",
          "tgn:1001836",
          "tgn:1000001",
          "tgn:7005560",
          "tgn:7029392"
        ],
        "placetype": [
          "aat:300008791"
        ],
        "id": 7380540,
        "name:xx": "Los Islotes"
      }
    },
    {
      "geometry": {
        "type": "Point",
        "coordinates": [
          -110.4,
          28.016667
        ]
      },
      "type": "Feature",
      "properties": {
        "hierarchy": [
          "tgn:7380541",
          "tgn:1000001",
          "tgn:1001960",
          "tgn:7005560",
          "tgn:7029392"
        ],
        "placetype": [
          "aat:300000241"
        ],
        "id": 7380541,
        "name:xx": "Rancho Los Ingenieros"
      }
    },
    {
      "geometry": {
        "type": "Point",
        "coordinates": [
          -105.333333,
          30.666667
        ]
      },
      "type": "Feature",
      "properties": {
        "hierarchy": [
          "tgn:7380542",
          "tgn:7005581",
          "tgn:1000001",
          "tgn:7005560",
          "tgn:7029392"
        ],
        "placetype": [
          "aat:300000241"
        ],
        "id": 7380542,
        "name:xx": "Rancho Los Infantes"
      }
    },
    {
      "geometry": {
        "type": "Point",
        "coordinates": [
          -100.133333,
          27.9
        ]
      },
      "type": "Feature",
      "properties": {
        "hierarchy": [
          "tgn:7380543",
          "tgn:1001853",
          "tgn:1000001",
          "tgn:7005560",
          "tgn:7029392"
        ],
        "placetype": [
          "aat:300006191"
        ],
        "id": 7380543,
        "name:xx": "Tanque Los Indios"
      }
    },
    {
      "geometry": {
        "type": "Point",
        "coordinates": [
          -101.383333,
          25.033333
        ]
      },
      "type": "Feature",
      "properties": {
        "hierarchy": [
          "tgn:7380544",
          "tgn:1001853",
          "tgn:1000001",
          "tgn:7005560",
          "tgn:7029392"
        ],
        "placetype": [
          "aat:300259572"
        ],
        "id": 7380544,
        "name:xx": "Los Indios, Puerto de"
      }
    },
    {
      "geometry": {
        "type": "Point",
        "coordinates": [
          -100.4,
          27.783333
        ]
      },
      "type": "Feature",
      "properties": {
        "hierarchy": [
          "tgn:7380545",
          "tgn:1001853",
          "tgn:1000001",
          "tgn:7005560",
          "tgn:7029392"
        ],
        "placetype": [
          "aat:300387087"
        ],
        "id": 7380545,
        "name:xx": "Los Indios, Lagunas de"
      }
    },
    {
      "geometry": {
        "type": "Point",
        "coordinates": [
          -101.166667,
          24.7
        ]
      },
      "type": "Feature",
      "properties": {
        "hierarchy": [
          "tgn:7380546",
          "tgn:1000001",
          "tgn:7005601",
          "tgn:7005560",
          "tgn:7029392"
        ],
        "placetype": [
          "aat:300008347"
        ],
        "id": 7380546,
        "name:xx": "Los Indios"
      }
    },
    {
      "geometry": {
        "type": "Point",
        "coordinates": [
          -108.866667,
          27.233333
        ]
      },
      "type": "Feature",
      "properties": {
        "hierarchy": [
          "tgn:7380547",
          "tgn:1000001",
          "tgn:1001960",
          "tgn:7005560",
          "tgn:7029392"
        ],
        "placetype": [
          "aat:300008347"
        ],
        "id": 7380547,
        "name:xx": "Los Igualamos"
      }
    },
    {
      "geometry": {
        "type": "Point",
        "coordinates": [
          -96.566667,
          19.35
        ]
      },
      "type": "Feature",
      "properties": {
        "hierarchy": [
          "tgn:7380549",
          "tgn:1000001",
          "tgn:7005599",
          "tgn:7005560",
          "tgn:7029392"
        ],
        "placetype": [
          "aat:300007783"
        ],
        "id": 7380549,
        "name:xx": "Los Ídolos"
      }
    }
  ]
}
