{
  "type": "FeatureCollection",
  "features": [
    {
      "geometry": {
        "type": "Point",
        "coordinates": [
          14.233333,
          41.083333
        ]
      },
      "type": "Feature",
      "properties": {
        "hierarchy": [
          "tgn:7040750",
          "tgn:7003011",
          "tgn:7003005",
          "tgn:1000003",
          "tgn:1000080",
          "tgn:7029392"
        ],
        "placetype": [
          "aat:300008347"
        ],
        "id": 7040750,
        "name:xx": "San Tammaro"
      }
    },
    {
      "geometry": {
        "type": "Point",
        "coordinates": [
          8.6,
          39.233333
        ]
      },
      "type": "Feature",
      "properties": {
        "hierarchy": [
          "tgn:7040751",
          "tgn:1001641",
          "tgn:1000003",
          "tgn:7003121",
          "tgn:1000080",
          "tgn:7029392"
        ],
        "placetype": [
          "aat:300008795"
        ],
        "id": 7040751,
        "name:xx": "Santa Miai, Monte"
      }
    },
    {
      "geometry": {
        "type": "Point",
        "coordinates": [
          13.316667,
          42.3
        ]
      },
      "type": "Feature",
      "properties": {
        "hierarchy": [
          "tgn:7040752",
          "tgn:7009084",
          "tgn:7004154",
          "tgn:1000003",
          "tgn:1000080",
          "tgn:7029392"
        ],
        "placetype": [
          "aat:300008347"
        ],
        "id": 7040752,
        "name:xx": "Santa Menna"
      }
    },
    {
      "geometry": {
        "type": "Point",
        "coordinates": [
          13.883333,
          41.4
        ]
      },
      "type": "Feature",
      "properties": {
        "hierarchy": [
          "tgn:7040753",
          "tgn:7003011",
          "tgn:7003005",
          "tgn:1000003",
          "tgn:1000080",
          "tgn:7029392"
        ],
        "placetype": [
          "aat:300008347"
        ],
        "id": 7040753,
        "name:xx": "Sant'Ambrogio sul Garigliano"
      }
    },
    {
      "geometry": {
        "type": "Point",
        "coordinates": [
          12.078611,
          45.606111
        ]
      },
      "type": "Feature",
      "properties": {
        "hierarchy": [
          "tgn:7040756",
          "tgn:7003006",
          "tgn:1000003",
          "tgn:7002997",
          "tgn:1000080",
          "tgn:7029392"
        ],
        "placetype": [
          "aat:300008347"
        ],
        "id": 7040756,
        "name:xx": "Sant'Ambrogio"
      }
    },
    {
      "geometry": {
        "type": "Point",
        "coordinates": [
          11.683333,
          43.116667
        ]
      },
      "type": "Feature",
      "properties": {
        "hierarchy": [
          "tgn:7040757",
          "tgn:7003168",
          "tgn:1000003",
          "tgn:7009760",
          "tgn:1000080",
          "tgn:7029392"
        ],
        "placetype": [
          "aat:300008347"
        ],
        "id": 7040757,
        "name:xx": "Sant'Ambrogio"
      }
    },
    {
      "geometry": {
        "type": "Point",
        "coordinates": [
          14.1,
          38.016667
        ]
      },
      "type": "Feature",
      "properties": {
        "hierarchy": [
          "tgn:7040758",
          "tgn:1000003",
          "tgn:7003122",
          "tgn:1001732",
          "tgn:1000080",
          "tgn:7029392"
        ],
        "placetype": [
          "aat:300008347"
        ],
        "id": 7040758,
        "name:xx": "Sant'Ambrogio"
      }
    },
    {
      "geometry": {
        "type": "Point",
        "coordinates": [
          10.983333,
          46.066667
        ]
      },
      "type": "Feature",
      "properties": {
        "hierarchy": [
          "tgn:7040759",
          "tgn:7003158",
          "tgn:1000003",
          "tgn:7003124",
          "tgn:1000080",
          "tgn:7029392"
        ],
        "placetype": [
          "aat:300008347"
        ],
        "id": 7040759,
        "name:xx": "Santa Massenza"
      }
    }
  ]
}
