{
  "geometry": {
    "type": "Point",
    "coordinates": [
      83.088377,
      25.49095
    ]
  },
  "type": "Feature",
  "properties": {
    "hierarchy": [
      "tgn:7555664",
      "tgn:1000004",
      "tgn:7000198",
      "tgn:7016722",
      "tgn:7029392"
    ],
    "placetype": [
      "aat:300008699"
    ],
    "name:en": "Nand Nadī",
    "id": 7555664
  }
}
