{
  "geometry": {
    "type": "Point",
    "coordinates": [
      -96.25,
      29.1667
    ]
  },
  "type": "Feature",
  "properties": {
    "hierarchy": [
      "tgn:2292754",
      "tgn:1000001",
      "tgn:7012149",
      "tgn:1003019",
      "tgn:7007826",
      "tgn:7029392"
    ],
    "placetype": [
      "aat:300008680"
    ],
    "id": 2292754,
    "name:xx": "Dornak Lake"
  }
}
