{
  "geometry": {
    "type": "Point",
    "coordinates": [
      -101.8333,
      44.55
    ]
  },
  "type": "Feature",
  "properties": {
    "hierarchy": [
      "tgn:2418097",
      "tgn:1000001",
      "tgn:7012149",
      "tgn:2001836",
      "tgn:7007713",
      "tgn:7029392"
    ],
    "placetype": [
      "aat:300008697"
    ],
    "id": 2418097,
    "name:xx": "Jackson Spring"
  }
}
