{
  "geometry": {
    "type": "Point",
    "coordinates": [
      -89.6167,
      45.1333
    ]
  },
  "type": "Feature",
  "properties": {
    "hierarchy": [
      "tgn:2583598",
      "tgn:1000001",
      "tgn:7012149",
      "tgn:2002334",
      "tgn:7007922",
      "tgn:7029392"
    ],
    "placetype": [
      "aat:300008347"
    ],
    "id": 2583598,
    "name:xx": "Pine River"
  }
}
