{
  "geometry": {
    "type": "Point",
    "coordinates": [
      -112.5833,
      32.95
    ]
  },
  "type": "Feature",
  "properties": {
    "hierarchy": [
      "tgn:2006586",
      "tgn:1000001",
      "tgn:7006451",
      "tgn:7012149",
      "tgn:2000097",
      "tgn:7029392"
    ],
    "placetype": [
      "aat:300387016"
    ],
    "id": 2006586,
    "name:xx": "Bosque"
  }
}
