{
  "type": "FeatureCollection",
  "features": [
    {
      "geometry": {
        "type": "Point",
        "coordinates": [
          -161.1,
          68.2333
        ]
      },
      "type": "Feature",
      "properties": {
        "hierarchy": [
          "tgn:1105650",
          "tgn:7006450",
          "tgn:1000001",
          "tgn:7012149",
          "tgn:2124005",
          "tgn:7029392"
        ],
        "placetype": [
          "aat:300008795"
        ],
        "id": 1105650,
        "name:xx": "Misheguk Mountain"
      }
    },
    {
      "geometry": {
        "type": "Point",
        "coordinates": [
          36.1167,
          31.9
        ]
      },
      "type": "Feature",
      "properties": {
        "hierarchy": [
          "tgn:1105651",
          "tgn:1002055",
          "tgn:1000004",
          "tgn:1000121",
          "tgn:7029392"
        ],
        "placetype": [
          "aat:300008795"
        ],
        "id": 1105651,
        "name:xx": "Mishqal, Jabal al-"
      }
    },
    {
      "geometry": {
        "type": "Point",
        "coordinates": [
          35.7,
          18.1
        ]
      },
      "type": "Feature",
      "properties": {
        "hierarchy": [
          "tgn:1105653",
          "tgn:1001069",
          "tgn:7001242",
          "tgn:1000201",
          "tgn:7029392"
        ],
        "placetype": [
          "aat:300008795"
        ],
        "id": 1105653,
        "name:xx": "Mismār, Jabal"
      }
    },
    {
      "geometry": {
        "type": "Point",
        "coordinates": [
          -82.25,
          35.75
        ]
      },
      "type": "Feature",
      "properties": {
        "hierarchy": [
          "tgn:1105655",
          "tgn:1000001",
          "tgn:7012149",
          "tgn:2001556",
          "tgn:7007709",
          "tgn:7029392"
        ],
        "placetype": [
          "aat:300008795"
        ],
        "id": 1105655,
        "name:xx": "Mitchell, Mount"
      }
    },
    {
      "geometry": {
        "type": "Point",
        "coordinates": [
          -44.5667,
          -22.1667
        ]
      },
      "type": "Feature",
      "properties": {
        "hierarchy": [
          "tgn:1105656",
          "tgn:7006237",
          "tgn:1000047",
          "tgn:7002457",
          "tgn:1000002",
          "tgn:7029392"
        ],
        "placetype": [
          "aat:300008795"
        ],
        "id": 1105656,
        "name:xx": "Mitra do Bispo"
      }
    },
    {
      "geometry": {
        "type": "Point",
        "coordinates": [
          9.95,
          1.3833
        ]
      },
      "type": "Feature",
      "properties": {
        "hierarchy": [
          "tgn:1105657",
          "tgn:1001736",
          "tgn:7001242",
          "tgn:1000161",
          "tgn:7029392"
        ],
        "placetype": [
          "aat:300008795"
        ],
        "id": 1105657,
        "name:xx": "Mitra, Monte"
      }
    },
    {
      "geometry": {
        "type": "Point",
        "coordinates": [
          175.45,
          -40.8
        ]
      },
      "type": "Feature",
      "properties": {
        "hierarchy": [
          "tgn:1105658",
          "tgn:1008380",
          "tgn:1000226",
          "tgn:7000512",
          "tgn:1000006",
          "tgn:7029392"
        ],
        "placetype": [
          "aat:300008795"
        ],
        "name:en": "Mitre",
        "id": 1105658
      }
    },
    {
      "geometry": {
        "type": "Point",
        "coordinates": [
          137.5833,
          36.3833
        ]
      },
      "type": "Feature",
      "properties": {
        "hierarchy": [
          "tgn:1105659",
          "tgn:7000895",
          "tgn:1000004",
          "tgn:1000120",
          "tgn:7029392"
        ],
        "placetype": [
          "aat:300008795"
        ],
        "id": 1105659,
        "name:xx": "Mitsumarenge-dake"
      }
    }
  ]
}
