{
  "geometry": {
    "type": "Point",
    "coordinates": [
      -83.5667,
      43.05
    ]
  },
  "type": "Feature",
  "properties": {
    "hierarchy": [
      "tgn:2194713",
      "tgn:1000001",
      "tgn:7012149",
      "tgn:1002406",
      "tgn:7007520",
      "tgn:7029392"
    ],
    "placetype": [
      "aat:300006075"
    ],
    "id": 2194713,
    "name:xx": "Brier Drain"
  }
}
