{
  "geometry": {
    "type": "Point",
    "coordinates": [
      -91.5667,
      35.4667
    ]
  },
  "type": "Feature",
  "properties": {
    "hierarchy": [
      "tgn:2342936",
      "tgn:1000001",
      "tgn:7016172",
      "tgn:7012149",
      "tgn:2000138",
      "tgn:7029392"
    ],
    "placetype": [
      "aat:300008699"
    ],
    "id": 2342936,
    "name:xx": "Fussy Branch"
  }
}
