{
  "type": "FeatureCollection",
  "features": [
    {
      "geometry": {
        "type": "Point",
        "coordinates": [
          -78.6333,
          40.8833
        ]
      },
      "type": "Feature",
      "properties": {
        "hierarchy": [
          "tgn:2234690",
          "tgn:1000001",
          "tgn:1002278",
          "tgn:7012149",
          "tgn:7007710",
          "tgn:7029392"
        ],
        "placetype": [
          "aat:300008347"
        ],
        "id": 2234690,
        "name:xx": "Cherry Corner"
      }
    },
    {
      "geometry": {
        "type": "Point",
        "coordinates": [
          -111.6333,
          47.2
        ]
      },
      "type": "Feature",
      "properties": {
        "hierarchy": [
          "tgn:2234692",
          "tgn:1000001",
          "tgn:2001266",
          "tgn:7012149",
          "tgn:7007524",
          "tgn:7029392"
        ],
        "placetype": [
          "aat:300008761"
        ],
        "id": 2234692,
        "name:xx": "Cherry Coulee"
      }
    },
    {
      "geometry": {
        "type": "Point",
        "coordinates": [
          -104.8667,
          47.2333
        ]
      },
      "type": "Feature",
      "properties": {
        "hierarchy": [
          "tgn:2234693",
          "tgn:1000001",
          "tgn:7012149",
          "tgn:2001270",
          "tgn:7007524",
          "tgn:7029392"
        ],
        "placetype": [
          "aat:300008761"
        ],
        "id": 2234693,
        "name:xx": "Cherry Coulee"
      }
    },
    {
      "geometry": {
        "type": "Point",
        "coordinates": [
          -110.85,
          47.6667
        ]
      },
      "type": "Feature",
      "properties": {
        "hierarchy": [
          "tgn:2234694",
          "tgn:1000001",
          "tgn:2001267",
          "tgn:7012149",
          "tgn:7007524",
          "tgn:7029392"
        ],
        "placetype": [
          "aat:300008761"
        ],
        "id": 2234694,
        "name:xx": "Cherry Coulee"
      }
    },
    {
      "geometry": {
        "type": "Point",
        "coordinates": [
          -109.8333,
          48.6333
        ]
      },
      "type": "Feature",
      "properties": {
        "hierarchy": [
          "tgn:2234695",
          "tgn:1000001",
          "tgn:7012149",
          "tgn:2001280",
          "tgn:7007524",
          "tgn:7029392"
        ],
        "placetype": [
          "aat:300008761"
        ],
        "id": 2234695,
        "name:xx": "Cherry Coulee"
      }
    },
    {
      "geometry": {
        "type": "Point",
        "coordinates": [
          -118.5,
          33.45
        ]
      },
      "type": "Feature",
      "properties": {
        "hierarchy": [
          "tgn:2234696",
          "tgn:1000001",
          "tgn:7012149",
          "tgn:7007157",
          "tgn:1002608",
          "tgn:1008999",
          "tgn:7029392"
        ],
        "placetype": [
          "aat:300132316"
        ],
        "id": 2234696,
        "name:xx": "Cherry Cove"
      }
    },
    {
      "geometry": {
        "type": "Point",
        "coordinates": [
          -83.6667,
          34.9833
        ]
      },
      "type": "Feature",
      "properties": {
        "hierarchy": [
          "tgn:2234697",
          "tgn:1000001",
          "tgn:7012149",
          "tgn:2000430",
          "tgn:7007248",
          "tgn:7029392"
        ],
        "placetype": [
          "aat:300386845"
        ],
        "id": 2234697,
        "name:xx": "Cherry Cove"
      }
    },
    {
      "geometry": {
        "type": "Point",
        "coordinates": [
          -68.7667,
          44.05
        ]
      },
      "type": "Feature",
      "properties": {
        "hierarchy": [
          "tgn:2234698",
          "tgn:1000001",
          "tgn:2000924",
          "tgn:7012149",
          "tgn:7007515",
          "tgn:7029392"
        ],
        "placetype": [
          "aat:300132316"
        ],
        "id": 2234698,
        "name:xx": "Cherry Cove"
      }
    },
    {
      "geometry": {
        "type": "Point",
        "coordinates": [
          -83.5167,
          35.0833
        ]
      },
      "type": "Feature",
      "properties": {
        "hierarchy": [
          "tgn:2234699",
          "tgn:1000001",
          "tgn:7012149",
          "tgn:2001515",
          "tgn:7007709",
          "tgn:7029392"
        ],
        "placetype": [
          "aat:300008761"
        ],
        "id": 2234699,
        "name:xx": "Cherry Cove"
      }
    }
  ]
}
