{
  "geometry": {
    "type": "Point",
    "coordinates": [
      -114.6833,
      48.0833
    ]
  },
  "type": "Feature",
  "properties": {
    "hierarchy": [
      "tgn:1126170",
      "tgn:1000001",
      "tgn:7012149",
      "tgn:7007524",
      "tgn:7029392"
    ],
    "placetype": [
      "aat:300008707"
    ],
    "id": 1126170,
    "name:xx": "Little Bitterroot"
  }
}
