{
  "geometry": {
    "type": "Point",
    "coordinates": [
      76.259589,
      32.335718
    ]
  },
  "type": "Feature",
  "properties": {
    "hierarchy": [
      "tgn:7555044",
      "tgn:1000004",
      "tgn:7000198",
      "tgn:1001996",
      "tgn:7029392"
    ],
    "placetype": [
      "aat:300008347"
    ],
    "name:en": "Minkiānī",
    "id": 7555044
  }
}
