{
  "geometry": {
    "type": "Point",
    "coordinates": [
      -87.8833,
      44.55
    ]
  },
  "type": "Feature",
  "properties": {
    "hierarchy": [
      "tgn:2120700",
      "tgn:1000001",
      "tgn:2002309",
      "tgn:7012149",
      "tgn:7007922",
      "tgn:7029392"
    ],
    "placetype": [
      "aat:300008347",
      "aat:300387210"
    ],
    "id": 2120700,
    "name:xx": "Bay Settlement"
  }
}
