{
  "geometry": {
    "type": "Point",
    "coordinates": [
      -89.4167,
      36.35
    ]
  },
  "type": "Feature",
  "properties": {
    "hierarchy": [
      "tgn:2217837",
      "tgn:1000001",
      "tgn:7012149",
      "tgn:2001884",
      "tgn:7007825",
      "tgn:7029392"
    ],
    "placetype": [
      "aat:300008850"
    ],
    "id": 2217837,
    "name:xx": "Campbells Point"
  }
}
