{
  "geometry": {
    "type": "Point",
    "coordinates": [
      -87.7333,
      44.4167
    ]
  },
  "type": "Feature",
  "properties": {
    "hierarchy": [
      "tgn:2234474",
      "tgn:1000001",
      "tgn:7012149",
      "tgn:2002330",
      "tgn:7007922",
      "tgn:7029392"
    ],
    "placetype": [
      "aat:300008347"
    ],
    "id": 2234474,
    "name:xx": "Cherneyville"
  }
}
