{
  "geometry": {
    "type": "Point",
    "coordinates": [
      -77.85,
      35.8167
    ]
  },
  "type": "Feature",
  "properties": {
    "hierarchy": [
      "tgn:2246666",
      "tgn:1000001",
      "tgn:7012149",
      "tgn:2001554",
      "tgn:7007709",
      "tgn:7029392"
    ],
    "placetype": [
      "aat:300008347"
    ],
    "id": 2246666,
    "name:xx": "Cobbs Crossroad"
  }
}
