{
  "geometry": {
    "type": "Point",
    "coordinates": [
      -121.3167,
      35.7333
    ]
  },
  "type": "Feature",
  "properties": {
    "hierarchy": [
      "tgn:2193072",
      "tgn:1000001",
      "tgn:7012149",
      "tgn:7007157",
      "tgn:1002863",
      "tgn:7029392"
    ],
    "placetype": [
      "aat:300008850"
    ],
    "id": 2193072,
    "name:xx": "Breaker Point"
  }
}
