{
  "geometry": {
    "type": "Point",
    "coordinates": [
      -102.7167,
      35.2833
    ]
  },
  "type": "Feature",
  "properties": {
    "hierarchy": [
      "tgn:2471661",
      "tgn:1000001",
      "tgn:7012149",
      "tgn:2002051",
      "tgn:7007826",
      "tgn:7029392"
    ],
    "placetype": [
      "aat:300008761"
    ],
    "id": 2471661,
    "name:xx": "Lost Mule Canyon"
  }
}
