{
  "geometry": {
    "type": "Point",
    "coordinates": [
      -122.4167,
      45.9333
    ]
  },
  "type": "Feature",
  "properties": {
    "hierarchy": [
      "tgn:2301014",
      "tgn:1000001",
      "tgn:1002275",
      "tgn:7012149",
      "tgn:7007920",
      "tgn:7029392"
    ],
    "placetype": [
      "aat:300008798"
    ],
    "id": 2301014,
    "name:xx": "Dunegan Mountain"
  }
}
