{
  "geometry": {
    "type": "Point",
    "coordinates": [
      -157.7333,
      61.7333
    ]
  },
  "type": "Feature",
  "properties": {
    "hierarchy": [
      "tgn:2312343",
      "tgn:7006450",
      "tgn:2000069",
      "tgn:1000001",
      "tgn:7012149",
      "tgn:7029392"
    ],
    "placetype": [
      "aat:300008706"
    ],
    "id": 2312343,
    "name:xx": "Eightmile Creek"
  }
}
