{
  "type": "FeatureCollection",
  "features": [
    {
      "geometry": {
        "type": "Point",
        "coordinates": [
          -96.1333,
          32.9
        ]
      },
      "type": "Feature",
      "properties": {
        "hierarchy": [
          "tgn:2107001",
          "tgn:1000001",
          "tgn:7012149",
          "tgn:1002492",
          "tgn:7007826",
          "tgn:7029392"
        ],
        "placetype": [
          "aat:300008347"
        ],
        "id": 2107001,
        "name:xx": "Quinlan"
      }
    },
    {
      "geometry": {
        "type": "Point",
        "coordinates": [
          -95.3,
          28.9167
        ]
      },
      "type": "Feature",
      "properties": {
        "hierarchy": [
          "tgn:2107002",
          "tgn:1000001",
          "tgn:1002198",
          "tgn:7012149",
          "tgn:7007826",
          "tgn:7029392"
        ],
        "placetype": [
          "aat:300008347"
        ],
        "id": 2107002,
        "name:xx": "Quintana"
      }
    },
    {
      "geometry": {
        "type": "Point",
        "coordinates": [
          -101.05,
          34.35
        ]
      },
      "type": "Feature",
      "properties": {
        "hierarchy": [
          "tgn:2107003",
          "tgn:1000001",
          "tgn:2001946",
          "tgn:7012149",
          "tgn:7007826",
          "tgn:7029392"
        ],
        "placetype": [
          "aat:300008347"
        ],
        "id": 2107003,
        "name:xx": "Quitaque"
      }
    },
    {
      "geometry": {
        "type": "Point",
        "coordinates": [
          -95.45,
          32.7833
        ]
      },
      "type": "Feature",
      "properties": {
        "hierarchy": [
          "tgn:2107005",
          "tgn:1000001",
          "tgn:7012149",
          "tgn:1003034",
          "tgn:7007826",
          "tgn:7029392"
        ],
        "placetype": [
          "aat:300008347"
        ],
        "id": 2107005,
        "name:xx": "Quitman"
      }
    },
    {
      "geometry": {
        "type": "Point",
        "coordinates": [
          -97.75,
          27.8
        ]
      },
      "type": "Feature",
      "properties": {
        "hierarchy": [
          "tgn:2107006",
          "tgn:1000001",
          "tgn:7012149",
          "tgn:2002049",
          "tgn:7007826",
          "tgn:7029392"
        ],
        "placetype": [
          "aat:300008347",
          "aat:300387210"
        ],
        "id": 2107006,
        "name:xx": "Rabb"
      }
    },
    {
      "geometry": {
        "type": "Point",
        "coordinates": [
          -98.15,
          32.2
        ]
      },
      "type": "Feature",
      "properties": {
        "hierarchy": [
          "tgn:2107007",
          "tgn:1000001",
          "tgn:7012149",
          "tgn:2001982",
          "tgn:7007826",
          "tgn:7029392"
        ],
        "placetype": [
          "aat:300008347",
          "aat:300387210"
        ],
        "id": 2107007,
        "name:xx": "Welcome Valley"
      }
    },
    {
      "geometry": {
        "type": "Point",
        "coordinates": [
          -96.8833,
          29.95
        ]
      },
      "type": "Feature",
      "properties": {
        "hierarchy": [
          "tgn:2107009",
          "tgn:1000001",
          "tgn:7012149",
          "tgn:1002374",
          "tgn:7007826",
          "tgn:7029392"
        ],
        "placetype": [
          "aat:300008347",
          "aat:300387210"
        ],
        "id": 2107009,
        "name:xx": "Rabbs Prairie"
      }
    }
  ]
}
