{
  "type": "FeatureCollection",
  "features": [
    {
      "geometry": {
        "type": "Point",
        "coordinates": [
          75.466667,
          19.3
        ]
      },
      "type": "Feature",
      "properties": {
        "hierarchy": [
          "tgn:7546460",
          "tgn:1000004",
          "tgn:7000198",
          "tgn:1001895",
          "tgn:7029392"
        ],
        "placetype": [
          "aat:300008347"
        ],
        "name:en": "Bālam Tākli",
        "id": 7546460
      }
    },
    {
      "geometry": {
        "type": "Point",
        "coordinates": [
          70.433333,
          22.716667
        ]
      },
      "type": "Feature",
      "properties": {
        "hierarchy": [
          "tgn:7546461",
          "tgn:1000004",
          "tgn:1001869",
          "tgn:7000198",
          "tgn:7029392"
        ],
        "placetype": [
          "aat:300008347"
        ],
        "name:en": "Balamba",
        "id": 7546461
      }
    },
    {
      "geometry": {
        "type": "Point",
        "coordinates": [
          80.35,
          27.166667
        ]
      },
      "type": "Feature",
      "properties": {
        "hierarchy": [
          "tgn:7546462",
          "tgn:1000004",
          "tgn:7000198",
          "tgn:7016722",
          "tgn:7029392"
        ],
        "placetype": [
          "aat:300008347"
        ],
        "name:en": "Bālāmau",
        "id": 7546462
      }
    },
    {
      "geometry": {
        "type": "Point",
        "coordinates": [
          84.86873,
          21.536899
        ]
      },
      "type": "Feature",
      "properties": {
        "hierarchy": [
          "tgn:7546463",
          "tgn:1000004",
          "tgn:7000198",
          "tgn:7016694",
          "tgn:7029392"
        ],
        "placetype": [
          "aat:300008347"
        ],
        "name:en": "Bālam",
        "id": 7546463
      }
    },
    {
      "geometry": {
        "type": "Point",
        "coordinates": [
          76.3,
          25.216667
        ]
      },
      "type": "Feature",
      "properties": {
        "hierarchy": [
          "tgn:7546464",
          "tgn:1000004",
          "tgn:7000198",
          "tgn:7016788",
          "tgn:7029392"
        ],
        "placetype": [
          "aat:300008347"
        ],
        "name:en": "Bālākhera",
        "id": 7546464
      }
    },
    {
      "geometry": {
        "type": "Point",
        "coordinates": [
          85.366667,
          22.1
        ]
      },
      "type": "Feature",
      "properties": {
        "hierarchy": [
          "tgn:7546465",
          "tgn:1000004",
          "tgn:7000198",
          "tgn:7016694",
          "tgn:7029392"
        ],
        "placetype": [
          "aat:300008347"
        ],
        "name:en": "Bālāgunda",
        "id": 7546465
      }
    },
    {
      "geometry": {
        "type": "Point",
        "coordinates": [
          80.199095,
          21.811731
        ]
      },
      "type": "Feature",
      "properties": {
        "hierarchy": [
          "tgn:7546467",
          "tgn:1000004",
          "tgn:7000198",
          "tgn:1001894",
          "tgn:7029392"
        ],
        "placetype": [
          "aat:300007783"
        ],
        "name:en": "Bālāghāt Junction",
        "id": 7546467
      }
    }
  ]
}
