{
  "type": "FeatureCollection",
  "features": [
    {
      "geometry": {
        "type": "Point",
        "coordinates": [
          -116.2,
          43.6
        ]
      },
      "type": "Feature",
      "properties": {
        "hierarchy": [
          "tgn:7013443",
          "tgn:2000452",
          "tgn:1000001",
          "tgn:7012149",
          "tgn:7007250",
          "tgn:7029392"
        ],
        "placetype": [
          "aat:300387277",
          "aat:300008347",
          "aat:300387264",
          "aat:300008416",
          "aat:300008389",
          "aat:300387308",
          "aat:300387304",
          "aat:300264742",
          "aat:300387512",
          "aat:300387221",
          "aat:300387306",
          "aat:300387291"
        ],
        "id": 7013443,
        "name:xx": "Boise"
      }
    },
    {
      "geometry": {
        "type": "Point",
        "coordinates": [
          -74.7,
          40.1333
        ]
      },
      "type": "Feature",
      "properties": {
        "hierarchy": [
          "tgn:7013444",
          "tgn:1002215",
          "tgn:1000001",
          "tgn:7012149",
          "tgn:7007565",
          "tgn:7029392"
        ],
        "placetype": [
          "aat:300008347"
        ],
        "id": 7013444,
        "name:xx": "Bordentown"
      }
    },
    {
      "geometry": {
        "type": "Point",
        "coordinates": [
          -71.05,
          42.35
        ]
      },
      "type": "Feature",
      "properties": {
        "hierarchy": [
          "tgn:7013445",
          "tgn:1000001",
          "tgn:1002923",
          "tgn:7012149",
          "tgn:7007517",
          "tgn:7029392"
        ],
        "placetype": [
          "aat:300008347",
          "aat:300008416",
          "aat:300387218",
          "aat:300008389",
          "aat:300387308",
          "aat:300000467",
          "aat:300387511",
          "aat:300005135",
          "aat:300264742",
          "aat:300387221",
          "aat:300387284",
          "aat:300387302",
          "aat:300387291"
        ],
        "id": 7013445,
        "name:xx": "Boston"
      }
    },
    {
      "geometry": {
        "type": "Point",
        "coordinates": [
          -105.2667,
          40
        ]
      },
      "type": "Feature",
      "properties": {
        "hierarchy": [
          "tgn:7013446",
          "tgn:1000001",
          "tgn:2000198",
          "tgn:7012149",
          "tgn:7007158",
          "tgn:7029392"
        ],
        "placetype": [
          "aat:300387277",
          "aat:300008347",
          "aat:300387264",
          "aat:300008416",
          "aat:300008389",
          "aat:300387308",
          "aat:300264742",
          "aat:300387305",
          "aat:300387270",
          "aat:300387302",
          "aat:300387299",
          "aat:300387291"
        ],
        "id": 7013446,
        "name:xx": "Boulder"
      }
    },
    {
      "geometry": {
        "type": "Point",
        "coordinates": [
          -86.4333,
          36.9833
        ]
      },
      "type": "Feature",
      "properties": {
        "hierarchy": [
          "tgn:7013447",
          "tgn:1000001",
          "tgn:7012149",
          "tgn:2000848",
          "tgn:7007255",
          "tgn:7029392"
        ],
        "placetype": [
          "aat:300387277",
          "aat:300008347",
          "aat:300008416",
          "aat:300387218",
          "aat:300008389",
          "aat:300387308",
          "aat:300387296"
        ],
        "id": 7013447,
        "name:xx": "Bowling Green"
      }
    },
    {
      "geometry": {
        "type": "Point",
        "coordinates": [
          -83.65,
          41.3667
        ]
      },
      "type": "Feature",
      "properties": {
        "hierarchy": [
          "tgn:7013448",
          "tgn:1000001",
          "tgn:7012149",
          "tgn:1003033",
          "tgn:7007706",
          "tgn:7029392"
        ],
        "placetype": [
          "aat:300008347"
        ],
        "id": 7013448,
        "name:xx": "Bowling Green"
      }
    },
    {
      "geometry": {
        "type": "Point",
        "coordinates": [
          -111.0333,
          45.6667
        ]
      },
      "type": "Feature",
      "properties": {
        "hierarchy": [
          "tgn:7013449",
          "tgn:1000001",
          "tgn:7012149",
          "tgn:2001275",
          "tgn:7007524",
          "tgn:7029392"
        ],
        "placetype": [
          "aat:300008347"
        ],
        "id": 7013449,
        "name:xx": "Bozeman"
      }
    }
  ]
}
