{
  "type": "FeatureCollection",
  "features": [
    {
      "geometry": {
        "type": "Point",
        "coordinates": [
          6.9667,
          47.1333
        ]
      },
      "type": "Feature",
      "properties": {
        "hierarchy": [
          "tgn:4010601",
          "tgn:7003742",
          "tgn:1000003",
          "tgn:7011731",
          "tgn:7029392"
        ],
        "placetype": [
          "aat:300008347"
        ],
        "id": 4010601,
        "name:xx": "Sonvilier"
      }
    },
    {
      "geometry": {
        "type": "Point",
        "coordinates": [
          20.4167,
          43.0833
        ]
      },
      "type": "Feature",
      "properties": {
        "hierarchy": [
          "tgn:4010602",
          "tgn:1000003",
          "tgn:7006669",
          "tgn:7029392"
        ],
        "placetype": [
          "aat:300000641"
        ],
        "id": 4010602,
        "name:xx": "Sopoćani"
      }
    },
    {
      "geometry": {
        "type": "Point",
        "coordinates": [
          2.0667,
          43.45
        ]
      },
      "type": "Feature",
      "properties": {
        "hierarchy": [
          "tgn:4010604",
          "tgn:1000003",
          "tgn:7002889",
          "tgn:1000070",
          "tgn:7029392"
        ],
        "placetype": [
          "aat:300008347"
        ],
        "id": 4010604,
        "name:xx": "Sorèze"
      }
    },
    {
      "geometry": {
        "type": "Point",
        "coordinates": [
          44.25,
          38.2667
        ]
      },
      "type": "Feature",
      "properties": {
        "hierarchy": [
          "tgn:4010607",
          "tgn:1000004",
          "tgn:1001591",
          "tgn:7018455",
          "tgn:1000144",
          "tgn:7029392"
        ],
        "placetype": [
          "aat:300008347",
          "aat:300008375"
        ],
        "id": 4010607,
        "name:xx": "Soradir"
      }
    }
  ]
}
