{
  "geometry": {
    "type": "Point",
    "coordinates": [
      -111.8167,
      43.25
    ]
  },
  "type": "Feature",
  "properties": {
    "hierarchy": [
      "tgn:2786944",
      "tgn:1000001",
      "tgn:2000457",
      "tgn:7012149",
      "tgn:7007250",
      "tgn:7029392"
    ],
    "placetype": [
      "aat:300008798"
    ],
    "id": 2786944,
    "name:xx": "Ziegler Mountain"
  }
}
