{
  "geometry": {
    "type": "Point",
    "coordinates": [
      21.35,
      43.9333
    ]
  },
  "type": "Feature",
  "properties": {
    "hierarchy": [
      "tgn:1064862",
      "tgn:1000003",
      "tgn:7006669",
      "tgn:7029392"
    ],
    "placetype": [
      "aat:300008347"
    ],
    "id": 1064862,
    "name:xx": "Ćuprija"
  }
}
