{
  "geometry": {
    "type": "Point",
    "coordinates": [
      10.05,
      47.766667
    ]
  },
  "type": "Feature",
  "properties": {
    "hierarchy": [
      "tgn:7092354",
      "tgn:7003692",
      "tgn:1000003",
      "tgn:7000084",
      "tgn:7029392"
    ],
    "placetype": [
      "aat:300000206"
    ],
    "id": 7092354,
    "name:xx": "Urlauer Oberöschhöfe"
  }
}
