{
  "geometry": {
    "type": "Point",
    "coordinates": [
      -85.7333,
      30.6667
    ]
  },
  "type": "Feature",
  "properties": {
    "hierarchy": [
      "tgn:2465120",
      "tgn:1000001",
      "tgn:7012149",
      "tgn:2000291",
      "tgn:7007240",
      "tgn:7029392"
    ],
    "placetype": [
      "aat:300008905"
    ],
    "id": 2465120,
    "name:xx": "Lolly Head Bay"
  }
}
