{
  "geometry": {
    "type": "Point",
    "coordinates": [
      -159.1833,
      61.8833
    ]
  },
  "type": "Feature",
  "properties": {
    "hierarchy": [
      "tgn:2563218",
      "tgn:7006450",
      "tgn:2000069",
      "tgn:1000001",
      "tgn:7012149",
      "tgn:7029392"
    ],
    "placetype": [
      "aat:300008707"
    ],
    "id": 2563218,
    "name:xx": "Owhat River"
  }
}
