{
  "type": "FeatureCollection",
  "features": [
    {
      "geometry": {
        "type": "Point",
        "coordinates": [
          12.15,
          52.666667
        ]
      },
      "type": "Feature",
      "properties": {
        "hierarchy": [
          "tgn:7090600",
          "tgn:1000003",
          "tgn:7003687",
          "tgn:7000084",
          "tgn:7029392"
        ],
        "placetype": [
          "aat:300008777"
        ],
        "id": 7090600,
        "name:xx": "Voßberge"
      }
    },
    {
      "geometry": {
        "type": "Point",
        "coordinates": [
          13.883333,
          53.866667
        ]
      },
      "type": "Feature",
      "properties": {
        "hierarchy": [
          "tgn:7090601",
          "tgn:1000003",
          "tgn:7000094",
          "tgn:7000084",
          "tgn:7029392"
        ],
        "placetype": [
          "aat:300008347"
        ],
        "id": 7090601,
        "name:xx": "Voßberg"
      }
    },
    {
      "geometry": {
        "type": "Point",
        "coordinates": [
          8.55,
          53.25
        ]
      },
      "type": "Feature",
      "properties": {
        "hierarchy": [
          "tgn:7090602",
          "tgn:1000003",
          "tgn:7003676",
          "tgn:7000084",
          "tgn:7029392"
        ],
        "placetype": [
          "aat:300008347"
        ],
        "id": 7090602,
        "name:xx": "Voßberg"
      }
    },
    {
      "geometry": {
        "type": "Point",
        "coordinates": [
          13.833333,
          53.15
        ]
      },
      "type": "Feature",
      "properties": {
        "hierarchy": [
          "tgn:7090603",
          "tgn:7000096",
          "tgn:1000003",
          "tgn:7000084",
          "tgn:7029392"
        ],
        "placetype": [
          "aat:300008347"
        ],
        "id": 7090603,
        "name:xx": "Voßberg"
      }
    },
    {
      "geometry": {
        "type": "Point",
        "coordinates": [
          8.966667,
          52.783333
        ]
      },
      "type": "Feature",
      "properties": {
        "hierarchy": [
          "tgn:7090604",
          "tgn:1000003",
          "tgn:7003676",
          "tgn:7000084",
          "tgn:7029392"
        ],
        "placetype": [
          "aat:300008347"
        ],
        "id": 7090604,
        "name:xx": "Voßberg"
      }
    },
    {
      "geometry": {
        "type": "Point",
        "coordinates": [
          14.383333,
          52.633333
        ]
      },
      "type": "Feature",
      "properties": {
        "hierarchy": [
          "tgn:7090605",
          "tgn:7000096",
          "tgn:1000003",
          "tgn:7000084",
          "tgn:7029392"
        ],
        "placetype": [
          "aat:300008347"
        ],
        "id": 7090605,
        "name:xx": "Voßberg"
      }
    },
    {
      "geometry": {
        "type": "Point",
        "coordinates": [
          11.816667,
          54.116667
        ]
      },
      "type": "Feature",
      "properties": {
        "hierarchy": [
          "tgn:7090606",
          "tgn:1000003",
          "tgn:7000094",
          "tgn:7000084",
          "tgn:7029392"
        ],
        "placetype": [
          "aat:300008777"
        ],
        "id": 7090606,
        "name:xx": "Voß-Berg"
      }
    },
    {
      "geometry": {
        "type": "Point",
        "coordinates": [
          9.45,
          54.1
        ]
      },
      "type": "Feature",
      "properties": {
        "hierarchy": [
          "tgn:7090607",
          "tgn:1000003",
          "tgn:7003688",
          "tgn:7000084",
          "tgn:7029392"
        ],
        "placetype": [
          "aat:300008777"
        ],
        "id": 7090607,
        "name:xx": "Voß-Berg"
      }
    },
    {
      "geometry": {
        "type": "Point",
        "coordinates": [
          12.016667,
          54.016667
        ]
      },
      "type": "Feature",
      "properties": {
        "hierarchy": [
          "tgn:7090608",
          "tgn:1000003",
          "tgn:7000094",
          "tgn:7000084",
          "tgn:7029392"
        ],
        "placetype": [
          "aat:300008777"
        ],
        "id": 7090608,
        "name:xx": "Voß-Berg"
      }
    },
    {
      "geometry": {
        "type": "Point",
        "coordinates": [
          11.9,
          53.85
        ]
      },
      "type": "Feature",
      "properties": {
        "hierarchy": [
          "tgn:7090609",
          "tgn:1000003",
          "tgn:7000094",
          "tgn:7000084",
          "tgn:7029392"
        ],
        "placetype": [
          "aat:300008777"
        ],
        "id": 7090609,
        "name:xx": "Voß-Berg"
      }
    }
  ]
}
