{
  "geometry": {
    "type": "Point",
    "coordinates": [
      -86.0833,
      30.9333
    ]
  },
  "type": "Feature",
  "properties": {
    "hierarchy": [
      "tgn:2235546",
      "tgn:1000001",
      "tgn:7012149",
      "tgn:2000290",
      "tgn:7007240",
      "tgn:7029392"
    ],
    "placetype": [
      "aat:300008706"
    ],
    "id": 2235546,
    "name:xx": "Chestnut Creek"
  }
}
