{
  "geometry": {
    "type": "Point",
    "coordinates": [
      -88.6833,
      30.5667
    ]
  },
  "type": "Feature",
  "properties": {
    "hierarchy": [
      "tgn:2552870",
      "tgn:1000001",
      "tgn:7012149",
      "tgn:2001115",
      "tgn:7007522",
      "tgn:7029392"
    ],
    "placetype": [
      "aat:300006191"
    ],
    "id": 2552870,
    "name:xx": "O Pines Lake"
  }
}
