{
  "geometry": {
    "type": "Point",
    "coordinates": [
      -68.2667,
      44.4833
    ]
  },
  "type": "Feature",
  "properties": {
    "hierarchy": [
      "tgn:2525773",
      "tgn:1000001",
      "tgn:2000922",
      "tgn:7012149",
      "tgn:7007515",
      "tgn:7029392"
    ],
    "placetype": [
      "aat:300008850"
    ],
    "id": 2525773,
    "name:xx": "Mosely Point"
  }
}
