{
  "geometry": {
    "type": "Point",
    "coordinates": [
      80.933333,
      17.633333
    ]
  },
  "type": "Feature",
  "properties": {
    "hierarchy": [
      "tgn:7573303",
      "tgn:1001828",
      "tgn:1000004",
      "tgn:7000198",
      "tgn:7029392"
    ],
    "placetype": [
      "aat:300008347"
    ],
    "name:en": "Gundāla",
    "id": 7573303
  }
}
