{
  "geometry": {
    "type": "Point",
    "coordinates": [
      -93.8333,
      34.2167
    ]
  },
  "type": "Feature",
  "properties": {
    "hierarchy": [
      "tgn:2623446",
      "tgn:1000001",
      "tgn:7016172",
      "tgn:7012149",
      "tgn:2000159",
      "tgn:7029392"
    ],
    "placetype": [
      "aat:300008706"
    ],
    "id": 2623446,
    "name:xx": "Rock Creek"
  }
}
