{
  "geometry": {
    "type": "Point",
    "coordinates": [
      103.6667,
      29.55
    ]
  },
  "type": "Feature",
  "properties": {
    "hierarchy": [
      "tgn:1071858",
      "tgn:1000004",
      "tgn:7002087",
      "tgn:1000111",
      "tgn:7029392"
    ],
    "placetype": [
      "aat:300008347"
    ],
    "id": 1071858,
    "name:xx": "Shuikouchang"
  }
}
