{
  "geometry": {
    "type": "Point",
    "coordinates": [
      -82.1667,
      35.7833
    ]
  },
  "type": "Feature",
  "properties": {
    "hierarchy": [
      "tgn:2510143",
      "tgn:1000001",
      "tgn:7012149",
      "tgn:2001556",
      "tgn:7007709",
      "tgn:7029392"
    ],
    "placetype": [
      "aat:300008706"
    ],
    "id": 2510143,
    "name:xx": "Middle Prong Clear Creek"
  }
}
