{
  "geometry": {
    "type": "Point",
    "coordinates": [
      -79.1833,
      35.9167
    ]
  },
  "type": "Feature",
  "properties": {
    "hierarchy": [
      "tgn:2077176",
      "tgn:1000001",
      "tgn:7012149",
      "tgn:2001525",
      "tgn:7007709",
      "tgn:7029392"
    ],
    "placetype": [
      "aat:300008347",
      "aat:300387210"
    ],
    "id": 2077176,
    "name:xx": "White Cross"
  }
}
