{
  "type": "FeatureCollection",
  "features": [
    {
      "geometry": {
        "type": "Point",
        "coordinates": [
          -84.0667,
          39.4
        ]
      },
      "type": "Feature",
      "properties": {
        "hierarchy": [
          "tgn:2262970",
          "tgn:1000001",
          "tgn:7012149",
          "tgn:1002987",
          "tgn:7007706",
          "tgn:7029392"
        ],
        "placetype": [
          "aat:300008699"
        ],
        "id": 2262970,
        "name:xx": "Cowen Run"
      }
    },
    {
      "geometry": {
        "type": "Point",
        "coordinates": [
          -80.65,
          32.3333
        ]
      },
      "type": "Feature",
      "properties": {
        "hierarchy": [
          "tgn:2262971",
          "tgn:2001731",
          "tgn:1000001",
          "tgn:7012149",
          "tgn:7007712",
          "tgn:7029392"
        ],
        "placetype": [
          "aat:300132348"
        ],
        "id": 2262971,
        "name:xx": "Cowen Spit"
      }
    },
    {
      "geometry": {
        "type": "Point",
        "coordinates": [
          -106.0833,
          33.1667
        ]
      },
      "type": "Feature",
      "properties": {
        "hierarchy": [
          "tgn:2262972",
          "tgn:1000001",
          "tgn:7012149",
          "tgn:2001447",
          "tgn:7007566",
          "tgn:7029392"
        ],
        "placetype": [
          "aat:300008697"
        ],
        "id": 2262972,
        "name:xx": "Cowen Spring"
      }
    },
    {
      "geometry": {
        "type": "Point",
        "coordinates": [
          -106.8,
          39.1833
        ]
      },
      "type": "Feature",
      "properties": {
        "hierarchy": [
          "tgn:2262973",
          "tgn:1000001",
          "tgn:7012149",
          "tgn:7007158",
          "tgn:2000240",
          "tgn:7029392"
        ],
        "placetype": [
          "aat:300000390"
        ],
        "id": 2262973,
        "name:xx": "Cowenhoven Tunnel"
      }
    },
    {
      "geometry": {
        "type": "Point",
        "coordinates": [
          -78.9167,
          40
        ]
      },
      "type": "Feature",
      "properties": {
        "hierarchy": [
          "tgn:2262974",
          "tgn:1000001",
          "tgn:7012149",
          "tgn:7014185",
          "tgn:7007710",
          "tgn:7029392"
        ],
        "placetype": [
          "aat:300006191"
        ],
        "id": 2262974,
        "name:xx": "Cowens Gap Lake"
      }
    },
    {
      "geometry": {
        "type": "Point",
        "coordinates": [
          -88.5,
          30.7333
        ]
      },
      "type": "Feature",
      "properties": {
        "hierarchy": [
          "tgn:2262975",
          "tgn:1000001",
          "tgn:7012149",
          "tgn:7007522",
          "tgn:7029392"
        ],
        "placetype": [
          "aat:300008699"
        ],
        "id": 2262975,
        "name:xx": "Cowerts Branch"
      }
    },
    {
      "geometry": {
        "type": "Point",
        "coordinates": [
          -95.6667,
          36
        ]
      },
      "type": "Feature",
      "properties": {
        "hierarchy": [
          "tgn:2262976",
          "tgn:1000001",
          "tgn:7012149",
          "tgn:2001695",
          "tgn:7007707",
          "tgn:7029392"
        ],
        "placetype": [
          "aat:300008706"
        ],
        "id": 2262976,
        "name:xx": "Coweta Creek"
      }
    },
    {
      "geometry": {
        "type": "Point",
        "coordinates": [
          -84.7667,
          33.45
        ]
      },
      "type": "Feature",
      "properties": {
        "hierarchy": [
          "tgn:2262977",
          "tgn:1000001",
          "tgn:7012149",
          "tgn:2000329",
          "tgn:7007248",
          "tgn:7029392"
        ],
        "placetype": [
          "aat:300006191"
        ],
        "id": 2262977,
        "name:xx": "Coweta, Lake"
      }
    },
    {
      "geometry": {
        "type": "Point",
        "coordinates": [
          -69.6,
          45.1167
        ]
      },
      "type": "Feature",
      "properties": {
        "hierarchy": [
          "tgn:2262978",
          "tgn:1000001",
          "tgn:7012149",
          "tgn:2000928",
          "tgn:7007515",
          "tgn:7029392"
        ],
        "placetype": [
          "aat:300008798"
        ],
        "id": 2262978,
        "name:xx": "Cowett Hill"
      }
    },
    {
      "geometry": {
        "type": "Point",
        "coordinates": [
          -77.6,
          34.9333
        ]
      },
      "type": "Feature",
      "properties": {
        "hierarchy": [
          "tgn:2262979",
          "tgn:1000001",
          "tgn:7012149",
          "tgn:2001524",
          "tgn:7007709",
          "tgn:7029392"
        ],
        "placetype": [
          "aat:300008699"
        ],
        "id": 2262979,
        "name:xx": "Cowford Branch"
      }
    }
  ]
}
