{
  "geometry": {
    "type": "Point",
    "coordinates": [
      -105.8167,
      46.8833
    ]
  },
  "type": "Feature",
  "properties": {
    "hierarchy": [
      "tgn:1132990",
      "tgn:1000001",
      "tgn:7012149",
      "tgn:7007524",
      "tgn:7029392"
    ],
    "placetype": [
      "aat:300008706"
    ],
    "id": 1132990,
    "name:xx": "Custer Creek"
  }
}
