{
  "type": "FeatureCollection",
  "features": [
    {
      "geometry": {
        "type": "Point",
        "coordinates": [
          16.85,
          -29.2833
        ]
      },
      "type": "Feature",
      "properties": {
        "hierarchy": [
          "tgn:1093521",
          "tgn:7001242",
          "tgn:7017582",
          "tgn:1000193",
          "tgn:7029392"
        ],
        "placetype": [
          "aat:300008347"
        ],
        "id": 1093521,
        "name:xx": "Port Nolloth"
      }
    },
    {
      "geometry": {
        "type": "Point",
        "coordinates": [
          30.4667,
          -30.7333
        ]
      },
      "type": "Feature",
      "properties": {
        "hierarchy": [
          "tgn:1093522",
          "tgn:7001242",
          "tgn:7016749",
          "tgn:1000193",
          "tgn:7029392"
        ],
        "placetype": [
          "aat:300008347"
        ],
        "id": 1093522,
        "name:xx": "Port Shepstone"
      }
    },
    {
      "geometry": {
        "type": "Point",
        "coordinates": [
          19,
          -33.0167
        ]
      },
      "type": "Feature",
      "properties": {
        "hierarchy": [
          "tgn:1093523",
          "tgn:7001242",
          "tgn:7017584",
          "tgn:1000193",
          "tgn:7029392"
        ],
        "placetype": [
          "aat:300008347"
        ],
        "id": 1093523,
        "name:xx": "Porterville"
      }
    },
    {
      "geometry": {
        "type": "Point",
        "coordinates": [
          23.0833,
          -28.3333
        ]
      },
      "type": "Feature",
      "properties": {
        "hierarchy": [
          "tgn:1093524",
          "tgn:7001242",
          "tgn:7017582",
          "tgn:1000193",
          "tgn:7029392"
        ],
        "placetype": [
          "aat:300008347"
        ],
        "id": 1093524,
        "name:xx": "Postmasburg"
      }
    },
    {
      "geometry": {
        "type": "Point",
        "coordinates": [
          27.1,
          -26.7
        ]
      },
      "type": "Feature",
      "properties": {
        "hierarchy": [
          "tgn:1093525",
          "tgn:7001242",
          "tgn:7017577",
          "tgn:1000193",
          "tgn:7029392"
        ],
        "placetype": [
          "aat:300008347"
        ],
        "id": 1093525,
        "name:xx": "Potchefstroom"
      }
    },
    {
      "geometry": {
        "type": "Point",
        "coordinates": [
          24.1167,
          -30.2
        ]
      },
      "type": "Feature",
      "properties": {
        "hierarchy": [
          "tgn:1093526",
          "tgn:7001242",
          "tgn:7017582",
          "tgn:1000193",
          "tgn:7029392"
        ],
        "placetype": [
          "aat:300008347"
        ],
        "id": 1093526,
        "name:xx": "Potfontein"
      }
    },
    {
      "geometry": {
        "type": "Point",
        "coordinates": [
          28.9167,
          -24.25
        ]
      },
      "type": "Feature",
      "properties": {
        "hierarchy": [
          "tgn:1093527",
          "tgn:7001242",
          "tgn:7017573",
          "tgn:1000193",
          "tgn:7029392"
        ],
        "placetype": [
          "aat:300008347"
        ],
        "id": 1093527,
        "name:xx": "Potgietersrus"
      }
    },
    {
      "geometry": {
        "type": "Point",
        "coordinates": [
          22.9833,
          -28.5
        ]
      },
      "type": "Feature",
      "properties": {
        "hierarchy": [
          "tgn:1093529",
          "tgn:7001242",
          "tgn:7017582",
          "tgn:1000193",
          "tgn:7029392"
        ],
        "placetype": [
          "aat:300008347"
        ],
        "id": 1093529,
        "name:xx": "Pretoriusvlei"
      }
    }
  ]
}
