{
  "geometry": {
    "type": "Point",
    "coordinates": [
      121.55,
      30.0833
    ]
  },
  "type": "Feature",
  "properties": {
    "hierarchy": [
      "tgn:1070097",
      "tgn:1000004",
      "tgn:7002076",
      "tgn:1000111",
      "tgn:7029392"
    ],
    "placetype": [
      "aat:300008347"
    ],
    "id": 1070097,
    "name:xx": "Longshansuo"
  }
}
