{
  "geometry": {
    "type": "Point",
    "coordinates": [
      -110.4667,
      32.2333
    ]
  },
  "type": "Feature",
  "properties": {
    "hierarchy": [
      "tgn:2741288",
      "tgn:1000001",
      "tgn:7006451",
      "tgn:7012149",
      "tgn:2000100",
      "tgn:7029392"
    ],
    "placetype": [
      "aat:300008697"
    ],
    "id": 2741288,
    "name:xx": "Upper West Fork Spring"
  }
}
