{
  "geometry": {
    "type": "Point",
    "coordinates": [
      -105.4333,
      37.9167
    ]
  },
  "type": "Feature",
  "properties": {
    "hierarchy": [
      "tgn:2463992",
      "tgn:1000001",
      "tgn:7012149",
      "tgn:2000205",
      "tgn:7007158",
      "tgn:7029392"
    ],
    "placetype": [
      "aat:300008798"
    ],
    "id": 2463992,
    "name:xx": "Loco Hill"
  }
}
