{
  "geometry": {
    "type": "Point",
    "coordinates": [
      -79.1167,
      37.7333
    ]
  },
  "type": "Feature",
  "properties": {
    "hierarchy": [
      "tgn:2317732",
      "tgn:2002140",
      "tgn:1000001",
      "tgn:7012149",
      "tgn:7007919",
      "tgn:7029392"
    ],
    "placetype": [
      "aat:300266640"
    ],
    "id": 2317732,
    "name:xx": "England Ridge"
  }
}
