{
  "type": "FeatureCollection",
  "features": [
    {
      "geometry": {
        "type": "Point",
        "coordinates": [
          -95.0167,
          34.4833
        ]
      },
      "type": "Feature",
      "properties": {
        "hierarchy": [
          "tgn:2549961",
          "tgn:1000001",
          "tgn:7012149",
          "tgn:7007707",
          "tgn:7029392"
        ],
        "placetype": [
          "aat:300008706"
        ],
        "id": 2549961,
        "name:xx": "North Watson Creek"
      }
    },
    {
      "geometry": {
        "type": "Point",
        "coordinates": [
          -85.2,
          33.8833
        ]
      },
      "type": "Feature",
      "properties": {
        "hierarchy": [
          "tgn:2549962",
          "tgn:1000001",
          "tgn:7012149",
          "tgn:2000362",
          "tgn:7007248",
          "tgn:7029392"
        ],
        "placetype": [
          "aat:300006191"
        ],
        "id": 2549962,
        "name:xx": "North Watts Lake"
      }
    },
    {
      "geometry": {
        "type": "Point",
        "coordinates": [
          -105.6667,
          38.6
        ]
      },
      "type": "Feature",
      "properties": {
        "hierarchy": [
          "tgn:2549963",
          "tgn:1000001",
          "tgn:7012149",
          "tgn:2000213",
          "tgn:7007158",
          "tgn:7029392"
        ],
        "placetype": [
          "aat:300008706"
        ],
        "id": 2549963,
        "name:xx": "North Waugh Creek"
      }
    },
    {
      "geometry": {
        "type": "Point",
        "coordinates": [
          -94.6667,
          38.7333
        ]
      },
      "type": "Feature",
      "properties": {
        "hierarchy": [
          "tgn:2549965",
          "tgn:1000001",
          "tgn:7012149",
          "tgn:7007254",
          "tgn:7029392"
        ],
        "placetype": [
          "aat:300008706"
        ],
        "id": 2549965,
        "name:xx": "North Wea Creek"
      }
    },
    {
      "geometry": {
        "type": "Point",
        "coordinates": [
          -71.7333,
          43.1
        ]
      },
      "type": "Feature",
      "properties": {
        "hierarchy": [
          "tgn:2549966",
          "tgn:1000001",
          "tgn:1002480",
          "tgn:7012149",
          "tgn:7007564",
          "tgn:7029392"
        ],
        "placetype": [
          "aat:300008347"
        ],
        "id": 2549966,
        "name:xx": "North Weare"
      }
    },
    {
      "geometry": {
        "type": "Point",
        "coordinates": [
          -106.7333,
          33.4833
        ]
      },
      "type": "Feature",
      "properties": {
        "hierarchy": [
          "tgn:2549967",
          "tgn:1000001",
          "tgn:7012149",
          "tgn:2001456",
          "tgn:7007566",
          "tgn:7029392"
        ],
        "placetype": [
          "aat:300006191"
        ],
        "id": 2549967,
        "name:xx": "North Well"
      }
    },
    {
      "geometry": {
        "type": "Point",
        "coordinates": [
          -108.4167,
          32.4
        ]
      },
      "type": "Feature",
      "properties": {
        "hierarchy": [
          "tgn:2549968",
          "tgn:1000001",
          "tgn:7012149",
          "tgn:2001437",
          "tgn:7007566",
          "tgn:7029392"
        ],
        "placetype": [
          "aat:300008761"
        ],
        "id": 2549968,
        "name:xx": "North Well Canyon"
      }
    },
    {
      "geometry": {
        "type": "Point",
        "coordinates": [
          -105.1333,
          32.5833
        ]
      },
      "type": "Feature",
      "properties": {
        "hierarchy": [
          "tgn:2549969",
          "tgn:1000001",
          "tgn:2001430",
          "tgn:7012149",
          "tgn:7007566",
          "tgn:7029392"
        ],
        "placetype": [
          "aat:300006191"
        ],
        "id": 2549969,
        "name:xx": "North Well and Water Storage"
      }
    }
  ]
}
