{
  "geometry": {
    "type": "Point",
    "coordinates": [
      -97.05,
      16.133333
    ]
  },
  "type": "Feature",
  "properties": {
    "hierarchy": [
      "tgn:7386304",
      "tgn:1000001",
      "tgn:7005591",
      "tgn:7005560",
      "tgn:7029392"
    ],
    "placetype": [
      "aat:300008347"
    ],
    "id": 7386304,
    "name:xx": "Peña Larga"
  }
}
