{
  "geometry": {
    "type": "Point",
    "coordinates": [
      74.886111,
      34.2875
    ]
  },
  "type": "Feature",
  "properties": {
    "hierarchy": [
      "tgn:7585721",
      "tgn:1000004",
      "tgn:7000198",
      "tgn:7000799",
      "tgn:7029392"
    ],
    "placetype": [
      "aat:300008347"
    ],
    "name:en": "Gundār",
    "id": 7585721
  }
}
