{
  "geometry": {
    "type": "Point",
    "coordinates": [
      -77.75,
      37.6167
    ]
  },
  "type": "Feature",
  "properties": {
    "hierarchy": [
      "tgn:2635768",
      "tgn:1000001",
      "tgn:7012149",
      "tgn:2002163",
      "tgn:7007919",
      "tgn:7029392"
    ],
    "placetype": [
      "aat:300008798"
    ],
    "id": 2635768,
    "name:xx": "Sabot Hill"
  }
}
