{
  "geometry": {
    "type": "Point",
    "coordinates": [
      28.76706,
      29.499112
    ]
  },
  "type": "Feature",
  "properties": {
    "hierarchy": [
      "tgn:7522039",
      "tgn:7001242",
      "tgn:7016833",
      "tgn:1001418",
      "tgn:7029392"
    ],
    "placetype": [
      "aat:300008750"
    ],
    "name:en": "Abū Rakham, Ghurd",
    "id": 7522039
  }
}
