{
  "geometry": {
    "type": "Point",
    "coordinates": [
      12.566667,
      49.25
    ]
  },
  "type": "Feature",
  "properties": {
    "hierarchy": [
      "tgn:7120480",
      "tgn:7003669",
      "tgn:1000003",
      "tgn:7000084",
      "tgn:7029392"
    ],
    "placetype": [
      "aat:300000206"
    ],
    "id": 7120480,
    "name:xx": "Plattenhöh"
  }
}
