{
  "geometry": {
    "type": "Point",
    "coordinates": [
      -95.7833,
      44.2167
    ]
  },
  "type": "Feature",
  "properties": {
    "hierarchy": [
      "tgn:2391290",
      "tgn:1000001",
      "tgn:7012149",
      "tgn:2001040",
      "tgn:7007521",
      "tgn:7029392"
    ],
    "placetype": [
      "aat:300008680"
    ],
    "id": 2391290,
    "name:xx": "Hill, Lake of the"
  }
}
