{
  "type": "FeatureCollection",
  "features": [
    {
      "geometry": {
        "type": "Point",
        "coordinates": [
          151.2,
          -33.9167
        ]
      },
      "type": "Feature",
      "properties": {
        "hierarchy": [
          "tgn:1005460",
          "tgn:7000490",
          "tgn:1000006",
          "tgn:7001828",
          "tgn:7001923",
          "tgn:7029392"
        ],
        "placetype": [
          "aat:300000745"
        ],
        "id": 1005460,
        "name:xx": "Rosebery"
      }
    },
    {
      "geometry": {
        "type": "Point",
        "coordinates": [
          -79.3667,
          43.6833
        ]
      },
      "type": "Feature",
      "properties": {
        "hierarchy": [
          "tgn:1005462",
          "tgn:7005685",
          "tgn:1000001",
          "tgn:7013284",
          "tgn:7013154",
          "tgn:7013251",
          "tgn:7029392"
        ],
        "placetype": [
          "aat:300000745"
        ],
        "id": 1005462,
        "name:xx": "Rosedale"
      }
    },
    {
      "geometry": {
        "type": "Point",
        "coordinates": [
          7.2,
          51.1667
        ]
      },
      "type": "Feature",
      "properties": {
        "hierarchy": [
          "tgn:1005464",
          "tgn:1000003",
          "tgn:7003677",
          "tgn:7000084",
          "tgn:1040868",
          "tgn:7029392"
        ],
        "placetype": [
          "aat:300000745",
          "aat:300387332"
        ],
        "id": 1005464,
        "name:xx": "Rosenhügel"
      }
    },
    {
      "geometry": {
        "type": "Point",
        "coordinates": [
          13.383333,
          52.6
        ]
      },
      "type": "Feature",
      "properties": {
        "hierarchy": [
          "tgn:1005465",
          "tgn:7003712",
          "tgn:1005309",
          "tgn:7003670",
          "tgn:1000003",
          "tgn:7000084",
          "tgn:7029392"
        ],
        "placetype": [
          "aat:300000745",
          "aat:300387340"
        ],
        "id": 1005465,
        "name:xx": "Rosenthal"
      }
    },
    {
      "geometry": {
        "type": "Point",
        "coordinates": [
          28.05,
          -26.25
        ]
      },
      "type": "Feature",
      "properties": {
        "hierarchy": [
          "tgn:1005466",
          "tgn:7001242",
          "tgn:7017576",
          "tgn:1000193",
          "tgn:7029392"
        ],
        "placetype": [
          "aat:300000745"
        ],
        "id": 1005466,
        "name:xx": "Rosettenville"
      }
    },
    {
      "geometry": {
        "type": "Point",
        "coordinates": [
          -71.1167,
          42.2833
        ]
      },
      "type": "Feature",
      "properties": {
        "hierarchy": [
          "tgn:1005467",
          "tgn:7013445",
          "tgn:1000001",
          "tgn:1002923",
          "tgn:7012149",
          "tgn:7007517",
          "tgn:7029392"
        ],
        "placetype": [
          "aat:300000745"
        ],
        "id": 1005467,
        "name:xx": "Roslindale"
      }
    },
    {
      "geometry": {
        "type": "Point",
        "coordinates": [
          16.3833,
          48.1333
        ]
      },
      "type": "Feature",
      "properties": {
        "hierarchy": [
          "tgn:1005468",
          "tgn:7003321",
          "tgn:7003030",
          "tgn:1000003",
          "tgn:1000062",
          "tgn:7029392"
        ],
        "placetype": [
          "aat:300000874"
        ],
        "id": 1005468,
        "name:xx": "Rothneusiedl"
      }
    },
    {
      "geometry": {
        "type": "Point",
        "coordinates": [
          7.083333,
          51.5
        ]
      },
      "type": "Feature",
      "properties": {
        "hierarchy": [
          "tgn:1005469",
          "tgn:1000003",
          "tgn:7003677",
          "tgn:7000084",
          "tgn:7005080",
          "tgn:7029392"
        ],
        "placetype": [
          "aat:300000745",
          "aat:300387332"
        ],
        "id": 1005469,
        "name:xx": "Rotthausen"
      }
    }
  ]
}
