{
  "geometry": {
    "type": "Point",
    "coordinates": [
      -119.9833,
      36.6667
    ]
  },
  "type": "Feature",
  "properties": {
    "hierarchy": [
      "tgn:2287076",
      "tgn:1000001",
      "tgn:7012149",
      "tgn:1002392",
      "tgn:7007157",
      "tgn:7029392"
    ],
    "placetype": [
      "aat:300006075"
    ],
    "id": 2287076,
    "name:xx": "Dickenson Waste"
  }
}
