{
  "geometry": {
    "type": "Point",
    "coordinates": [
      -93.15,
      31.1667
    ]
  },
  "type": "Feature",
  "properties": {
    "hierarchy": [
      "tgn:2255031",
      "tgn:1000001",
      "tgn:7012149",
      "tgn:2000911",
      "tgn:7007256",
      "tgn:7029392"
    ],
    "placetype": [
      "aat:300008706"
    ],
    "id": 2255031,
    "name:xx": "Cooper Creek"
  }
}
