{
  "geometry": {
    "type": "Point",
    "coordinates": [
      -23.6667,
      65.75
    ]
  },
  "type": "Feature",
  "properties": {
    "hierarchy": [
      "tgn:1114355",
      "tgn:7594021",
      "tgn:1000003",
      "tgn:1000077",
      "tgn:7029392"
    ],
    "placetype": [
      "aat:300008676"
    ],
    "id": 1114355,
    "name:xx": "Arnarfjörður"
  }
}
