{
  "type": "FeatureCollection",
  "features": [
    {
      "geometry": {
        "type": "Point",
        "coordinates": [
          -105.55,
          39.9833
        ]
      },
      "type": "Feature",
      "properties": {
        "hierarchy": [
          "tgn:2283440",
          "tgn:1000001",
          "tgn:2000198",
          "tgn:7012149",
          "tgn:7007158",
          "tgn:7029392"
        ],
        "placetype": [
          "aat:300008706"
        ],
        "id": 2283440,
        "name:xx": "Delonde Creek"
      }
    },
    {
      "geometry": {
        "type": "Point",
        "coordinates": [
          -105.55,
          39.9833
        ]
      },
      "type": "Feature",
      "properties": {
        "hierarchy": [
          "tgn:2283441",
          "tgn:1000001",
          "tgn:2000198",
          "tgn:7012149",
          "tgn:7007158",
          "tgn:7029392"
        ],
        "placetype": [
          "aat:300008761"
        ],
        "id": 2283441,
        "name:xx": "Delonde Gulch"
      }
    },
    {
      "geometry": {
        "type": "Point",
        "coordinates": [
          -118.6333,
          35.5833
        ]
      },
      "type": "Feature",
      "properties": {
        "hierarchy": [
          "tgn:2283442",
          "tgn:1000001",
          "tgn:7012149",
          "tgn:1002545",
          "tgn:7007157",
          "tgn:7029392"
        ],
        "placetype": [
          "aat:300008706"
        ],
        "id": 2283442,
        "name:xx": "Delonegha Creek"
      }
    },
    {
      "geometry": {
        "type": "Point",
        "coordinates": [
          -118.6,
          35.55
        ]
      },
      "type": "Feature",
      "properties": {
        "hierarchy": [
          "tgn:2283443",
          "tgn:1000001",
          "tgn:7012149",
          "tgn:1002545",
          "tgn:7007157",
          "tgn:7029392"
        ],
        "placetype": [
          "aat:300008697"
        ],
        "id": 2283443,
        "name:xx": "Delonegha Hot Springs"
      }
    },
    {
      "geometry": {
        "type": "Point",
        "coordinates": [
          -110.3333,
          42.4333
        ]
      },
      "type": "Feature",
      "properties": {
        "hierarchy": [
          "tgn:2283444",
          "tgn:1000001",
          "tgn:7012149",
          "tgn:2002382",
          "tgn:7007923",
          "tgn:7029392"
        ],
        "placetype": [
          "aat:300008761"
        ],
        "id": 2283444,
        "name:xx": "Deloney Canyon"
      }
    },
    {
      "geometry": {
        "type": "Point",
        "coordinates": [
          -112.6,
          37.8667
        ]
      },
      "type": "Feature",
      "properties": {
        "hierarchy": [
          "tgn:2283446",
          "tgn:1000001",
          "tgn:7012149",
          "tgn:7007827",
          "tgn:7029392"
        ],
        "placetype": [
          "aat:300008706"
        ],
        "id": 2283446,
        "name:xx": "Delong Creek"
      }
    },
    {
      "geometry": {
        "type": "Point",
        "coordinates": [
          -85.1667,
          40.7
        ]
      },
      "type": "Feature",
      "properties": {
        "hierarchy": [
          "tgn:2283447",
          "tgn:1000001",
          "tgn:7012149",
          "tgn:1003010",
          "tgn:7007252",
          "tgn:7029392"
        ],
        "placetype": [
          "aat:300006075"
        ],
        "id": 2283447,
        "name:xx": "Delong Ditch"
      }
    },
    {
      "geometry": {
        "type": "Point",
        "coordinates": [
          -92.4833,
          46.3833
        ]
      },
      "type": "Feature",
      "properties": {
        "hierarchy": [
          "tgn:2283449",
          "tgn:1000001",
          "tgn:7012149",
          "tgn:2001056",
          "tgn:7007521",
          "tgn:7029392"
        ],
        "placetype": [
          "aat:300008680"
        ],
        "id": 2283449,
        "name:xx": "Delong Lake"
      }
    }
  ]
}
