{
  "geometry": {
    "type": "Point",
    "coordinates": [
      -96.0333,
      36.9667
    ]
  },
  "type": "Feature",
  "properties": {
    "hierarchy": [
      "tgn:2559924",
      "tgn:1000001",
      "tgn:7012149",
      "tgn:2001679",
      "tgn:7007707",
      "tgn:7029392"
    ],
    "placetype": [
      "aat:300008706"
    ],
    "id": 2559924,
    "name:xx": "Opossum Creek"
  }
}
