{
  "geometry": {
    "type": "Point",
    "coordinates": [
      -111.1667,
      32.9833
    ]
  },
  "type": "Feature",
  "properties": {
    "hierarchy": [
      "tgn:2209756",
      "tgn:1000001",
      "tgn:7006451",
      "tgn:7012149",
      "tgn:2000101",
      "tgn:7029392"
    ],
    "placetype": [
      "aat:300006191"
    ],
    "id": 2209756,
    "name:xx": "Burro Flaco Tank"
  }
}
