{
  "geometry": {
    "type": "Point",
    "coordinates": [
      -117.6667,
      45.6333
    ]
  },
  "type": "Feature",
  "properties": {
    "hierarchy": [
      "tgn:2472740",
      "tgn:1000001",
      "tgn:7012149",
      "tgn:2001722",
      "tgn:7007708",
      "tgn:7029392"
    ],
    "placetype": [
      "aat:300008347"
    ],
    "id": 2472740,
    "name:xx": "Lovely"
  }
}
