{
  "geometry": {
    "type": "Point",
    "coordinates": [
      -85.6833,
      43.7667
    ]
  },
  "type": "Feature",
  "properties": {
    "hierarchy": [
      "tgn:2764520",
      "tgn:1000001",
      "tgn:7012149",
      "tgn:2000983",
      "tgn:7007520",
      "tgn:7029392"
    ],
    "placetype": [
      "aat:300008706"
    ],
    "id": 2764520,
    "name:xx": "Whipple Creek"
  }
}
