{
  "geometry": {
    "type": "Point",
    "coordinates": [
      -119.85,
      39.9667
    ]
  },
  "type": "Feature",
  "properties": {
    "hierarchy": [
      "tgn:2741313",
      "tgn:1000001",
      "tgn:7012149",
      "tgn:1002999",
      "tgn:7007526",
      "tgn:7029392"
    ],
    "placetype": [
      "aat:300008697"
    ],
    "id": 2741313,
    "name:xx": "Upper Wildcat Spring"
  }
}
