{
  "geometry": {
    "type": "Point",
    "coordinates": [
      -84.9167,
      35.2333
    ]
  },
  "type": "Feature",
  "properties": {
    "hierarchy": [
      "tgn:2135770",
      "tgn:1000001",
      "tgn:2001842",
      "tgn:7012149",
      "tgn:7007825",
      "tgn:7029392"
    ],
    "placetype": [
      "aat:300008699"
    ],
    "id": 2135770,
    "name:xx": "Apison Fork"
  }
}
