{
  "geometry": {
    "type": "Point",
    "coordinates": [
      -74.9833,
      43.5833
    ]
  },
  "type": "Feature",
  "properties": {
    "hierarchy": [
      "tgn:2196969",
      "tgn:1000001",
      "tgn:7012149",
      "tgn:1002472",
      "tgn:7007568",
      "tgn:7029392"
    ],
    "placetype": [
      "aat:300008850"
    ],
    "id": 2196969,
    "name:xx": "Brooktrout Point"
  }
}
