{
  "geometry": {
    "type": "Point",
    "coordinates": [
      -83.95,
      35.1167
    ]
  },
  "type": "Feature",
  "properties": {
    "hierarchy": [
      "tgn:2506969",
      "tgn:1000001",
      "tgn:2001481",
      "tgn:7012149",
      "tgn:7007709",
      "tgn:7029392"
    ],
    "placetype": [
      "aat:300008699"
    ],
    "id": 2506969,
    "name:xx": "Messer Branch"
  }
}
