{
  "geometry": {
    "type": "Point",
    "coordinates": [
      -90.9333,
      36.75
    ]
  },
  "type": "Feature",
  "properties": {
    "hierarchy": [
      "tgn:2731058",
      "tgn:1000001",
      "tgn:7012149",
      "tgn:2001237",
      "tgn:7007523",
      "tgn:7029392"
    ],
    "placetype": [
      "aat:300132316"
    ],
    "id": 2731058,
    "name:xx": "Tucker Bay"
  }
}
