{
  "type": "FeatureCollection",
  "features": [
    {
      "geometry": {
        "type": "Point",
        "coordinates": [
          30.541566,
          31.139108
        ]
      },
      "type": "Feature",
      "properties": {
        "hierarchy": [
          "tgn:7532840",
          "tgn:7001242",
          "tgn:1001075",
          "tgn:7016833",
          "tgn:7029392"
        ],
        "placetype": [
          "aat:300008347"
        ],
        "name:en": "'Izbat as Sa'dīyah",
        "id": 7532840
      }
    },
    {
      "geometry": {
        "type": "Point",
        "coordinates": [
          30.552526,
          31.126117
        ]
      },
      "type": "Feature",
      "properties": {
        "hierarchy": [
          "tgn:7532841",
          "tgn:7001242",
          "tgn:1001075",
          "tgn:7016833",
          "tgn:7029392"
        ],
        "placetype": [
          "aat:300008347"
        ],
        "name:en": "Fīshā al Jadīdah",
        "id": 7532841
      }
    },
    {
      "geometry": {
        "type": "Point",
        "coordinates": [
          30.562556,
          31.131964
        ]
      },
      "type": "Feature",
      "properties": {
        "hierarchy": [
          "tgn:7532842",
          "tgn:7001242",
          "tgn:1001075",
          "tgn:7016833",
          "tgn:7029392"
        ],
        "placetype": [
          "aat:300008347"
        ],
        "name:en": "'Izbat al 'Awām",
        "id": 7532842
      }
    },
    {
      "geometry": {
        "type": "Point",
        "coordinates": [
          30.57459,
          31.138007
        ]
      },
      "type": "Feature",
      "properties": {
        "hierarchy": [
          "tgn:7532843",
          "tgn:7001242",
          "tgn:1001075",
          "tgn:7016833",
          "tgn:7029392"
        ],
        "placetype": [
          "aat:300008347"
        ],
        "name:en": "'Izbat ar Rawḑah",
        "id": 7532843
      }
    },
    {
      "geometry": {
        "type": "Point",
        "coordinates": [
          30.593503,
          31.112962
        ]
      },
      "type": "Feature",
      "properties": {
        "hierarchy": [
          "tgn:7532844",
          "tgn:7001242",
          "tgn:1001075",
          "tgn:7016833",
          "tgn:7029392"
        ],
        "placetype": [
          "aat:300008347"
        ],
        "name:en": "'Izbat 'Alī Khiḑr",
        "id": 7532844
      }
    },
    {
      "geometry": {
        "type": "Point",
        "coordinates": [
          30.583654,
          31.113871
        ]
      },
      "type": "Feature",
      "properties": {
        "hierarchy": [
          "tgn:7532845",
          "tgn:7001242",
          "tgn:1001075",
          "tgn:7016833",
          "tgn:7029392"
        ],
        "placetype": [
          "aat:300008347"
        ],
        "name:en": "'Izbat Abū Nuşayr",
        "id": 7532845
      }
    },
    {
      "geometry": {
        "type": "Point",
        "coordinates": [
          30.602008,
          31.093731
        ]
      },
      "type": "Feature",
      "properties": {
        "hierarchy": [
          "tgn:7532846",
          "tgn:7001242",
          "tgn:1001075",
          "tgn:7016833",
          "tgn:7029392"
        ],
        "placetype": [
          "aat:300006075"
        ],
        "name:en": "Tur'at al Ashrāfīyah",
        "id": 7532846
      }
    },
    {
      "geometry": {
        "type": "Point",
        "coordinates": [
          31.320679,
          30.518472
        ]
      },
      "type": "Feature",
      "properties": {
        "hierarchy": [
          "tgn:7532847",
          "tgn:7001242",
          "tgn:7016833",
          "tgn:1001113",
          "tgn:7029392"
        ],
        "placetype": [
          "aat:300008347"
        ],
        "id": 7532847,
        "name:xx": "'Izbat ad Dīb"
      }
    },
    {
      "geometry": {
        "type": "Point",
        "coordinates": [
          31.319551,
          30.516088
        ]
      },
      "type": "Feature",
      "properties": {
        "hierarchy": [
          "tgn:7532848",
          "tgn:7001242",
          "tgn:7016833",
          "tgn:1001113",
          "tgn:7029392"
        ],
        "placetype": [
          "aat:300008347"
        ],
        "id": 7532848,
        "name:xx": "'Izbat Khayrī"
      }
    },
    {
      "geometry": {
        "type": "Point",
        "coordinates": [
          31.532871,
          30.566191
        ]
      },
      "type": "Feature",
      "properties": {
        "hierarchy": [
          "tgn:7532849",
          "tgn:7001242",
          "tgn:7016833",
          "tgn:1001113",
          "tgn:7029392"
        ],
        "placetype": [
          "aat:300008347"
        ],
        "id": 7532849,
        "name:xx": "'Izbat Ḩasan Aghā"
      }
    }
  ]
}
