{
  "geometry": {
    "type": "Point",
    "coordinates": [
      -83.35,
      37.3667
    ]
  },
  "type": "Feature",
  "properties": {
    "hierarchy": [
      "tgn:2037620",
      "tgn:1000001",
      "tgn:2000772",
      "tgn:7012149",
      "tgn:7007255",
      "tgn:7029392"
    ],
    "placetype": [
      "aat:300008347",
      "aat:300387210"
    ],
    "id": 2037620,
    "name:xx": "Barwick"
  }
}
