{
  "geometry": {
    "type": "Point",
    "coordinates": [
      -99.0333,
      41.5167
    ]
  },
  "type": "Feature",
  "properties": {
    "hierarchy": [
      "tgn:2382325",
      "tgn:1000001",
      "tgn:7012149",
      "tgn:7007525",
      "tgn:7029392"
    ],
    "placetype": [
      "aat:300008706"
    ],
    "id": 2382325,
    "name:xx": "Hays Creek"
  }
}
