{
  "type": "FeatureCollection",
  "features": [
    {
      "geometry": {
        "type": "Point",
        "coordinates": [
          15.85,
          39.716667
        ]
      },
      "type": "Feature",
      "properties": {
        "hierarchy": [
          "tgn:1044890",
          "tgn:1003450",
          "tgn:7007850",
          "tgn:1000003",
          "tgn:1000080",
          "tgn:7029392"
        ],
        "placetype": [
          "aat:300008347"
        ],
        "id": 1044890,
        "name:xx": "Grisolia"
      }
    },
    {
      "geometry": {
        "type": "Point",
        "coordinates": [
          9.933333,
          45.966667
        ]
      },
      "type": "Feature",
      "properties": {
        "hierarchy": [
          "tgn:1044892",
          "tgn:7005023",
          "tgn:1000003",
          "tgn:7003237",
          "tgn:1000080",
          "tgn:7029392"
        ],
        "placetype": [
          "aat:300008347"
        ],
        "id": 1044892,
        "name:xx": "Gromo"
      }
    },
    {
      "geometry": {
        "type": "Point",
        "coordinates": [
          9,
          45.183333
        ]
      },
      "type": "Feature",
      "properties": {
        "hierarchy": [
          "tgn:1044893",
          "tgn:1000003",
          "tgn:7003151",
          "tgn:7003237",
          "tgn:1000080",
          "tgn:7029392"
        ],
        "placetype": [
          "aat:300008347"
        ],
        "id": 1044893,
        "name:xx": "Gropello Cairoli"
      }
    },
    {
      "geometry": {
        "type": "Point",
        "coordinates": [
          7.25,
          45.366667
        ]
      },
      "type": "Feature",
      "properties": {
        "hierarchy": [
          "tgn:1044894",
          "tgn:7003154",
          "tgn:1000003",
          "tgn:7003120",
          "tgn:1000080",
          "tgn:7029392"
        ],
        "placetype": [
          "aat:300008347"
        ],
        "id": 1044894,
        "name:xx": "Groscavallo"
      }
    },
    {
      "geometry": {
        "type": "Point",
        "coordinates": [
          10.25,
          46.283333
        ]
      },
      "type": "Feature",
      "properties": {
        "hierarchy": [
          "tgn:1044896",
          "tgn:1000003",
          "tgn:7003152",
          "tgn:7003237",
          "tgn:1000080",
          "tgn:7029392"
        ],
        "placetype": [
          "aat:300008347"
        ],
        "id": 1044896,
        "name:xx": "Grosotto"
      }
    }
  ]
}
