{
  "geometry": {
    "type": "Point",
    "coordinates": [
      -59.5333,
      13.1667
    ]
  },
  "type": "Feature",
  "properties": {
    "name:en": "Barbados",
    "hierarchy": [
      "tgn:7004770",
      "tgn:1000001",
      "tgn:7029392"
    ],
    "name:ar": "بربادوس",
    "placetype": [
      "aat:300387054",
      "aat:300235115",
      "aat:300387062",
      "aat:300128207",
      "aat:300387174"
    ],
    "name:fr": "Barbade",
    "name:ru": "Барбадос",
    "name:zh": "巴巴多斯",
    "id": 7004770,
    "name:es": "Barbados"
  }
}
