{
  "geometry": {
    "type": "Point",
    "coordinates": [
      74.405556,
      33.758333
    ]
  },
  "type": "Feature",
  "properties": {
    "hierarchy": [
      "tgn:7590403",
      "tgn:1000004",
      "tgn:7000198",
      "tgn:7000799",
      "tgn:7029392"
    ],
    "placetype": [
      "aat:300008795"
    ],
    "name:en": "Bāba Pahār",
    "id": 7590403
  }
}
