{
  "geometry": {
    "type": "Point",
    "coordinates": [
      -104.9167,
      42.75
    ]
  },
  "type": "Feature",
  "properties": {
    "hierarchy": [
      "tgn:2123035",
      "tgn:1000001",
      "tgn:2002369",
      "tgn:7012149",
      "tgn:7007923",
      "tgn:7029392"
    ],
    "placetype": [
      "aat:300008347"
    ],
    "id": 2123035,
    "name:xx": "Lost Springs"
  }
}
