{
  "geometry": {
    "type": "Point",
    "coordinates": [
      16.338,
      46.25
    ]
  },
  "type": "Feature",
  "properties": {
    "hierarchy": [
      "tgn:7017296",
      "tgn:1000003",
      "tgn:7006663",
      "tgn:7029392"
    ],
    "placetype": [
      "aat:300387064",
      "aat:300000771"
    ],
    "id": 7017296,
    "name:xx": "Varaždinska Županija"
  }
}
