{
  "geometry": {
    "type": "Point",
    "coordinates": [
      80.4833,
      54.2667
    ]
  },
  "type": "Feature",
  "properties": {
    "hierarchy": [
      "tgn:1137676",
      "tgn:1000004",
      "tgn:7011589",
      "tgn:7018214",
      "tgn:7002435",
      "tgn:7029392"
    ],
    "placetype": [
      "aat:300008347"
    ],
    "id": 1137676,
    "name:xx": "Kochki"
  }
}
