{
  "geometry": {
    "type": "Point",
    "coordinates": [
      -147.8333,
      60.2167
    ]
  },
  "type": "Feature",
  "properties": {
    "hierarchy": [
      "tgn:2532011",
      "tgn:7006450",
      "tgn:1000001",
      "tgn:7012149",
      "tgn:2000086",
      "tgn:7029392"
    ],
    "placetype": [
      "aat:300132316"
    ],
    "id": 2532011,
    "name:xx": "Mummy Bay"
  }
}
