{
  "type": "FeatureCollection",
  "features": [
    {
      "geometry": {
        "type": "Point",
        "coordinates": [
          -5.45,
          56.1
        ]
      },
      "type": "Feature",
      "properties": {
        "hierarchy": [
          "tgn:7460590",
          "tgn:7019094",
          "tgn:7002444",
          "tgn:1000003",
          "tgn:7008591",
          "tgn:7029392"
        ],
        "placetype": [
          "aat:300008347"
        ],
        "name:en": "Kilbride",
        "id": 7460590
      }
    },
    {
      "geometry": {
        "type": "Point",
        "coordinates": [
          -5.6,
          56.283333
        ]
      },
      "type": "Feature",
      "properties": {
        "hierarchy": [
          "tgn:7460592",
          "tgn:7019094",
          "tgn:7002444",
          "tgn:1000003",
          "tgn:7008591",
          "tgn:7029392"
        ],
        "placetype": [
          "aat:300008347"
        ],
        "name:en": "Kilbrandon",
        "id": 7460592
      }
    },
    {
      "geometry": {
        "type": "Point",
        "coordinates": [
          -5.016667,
          56.266667
        ]
      },
      "type": "Feature",
      "properties": {
        "hierarchy": [
          "tgn:7460593",
          "tgn:7019094",
          "tgn:7002444",
          "tgn:1000003",
          "tgn:7008591",
          "tgn:7029392"
        ],
        "placetype": [
          "aat:300008699"
        ],
        "name:en": "Kilblaan Burn",
        "id": 7460593
      }
    },
    {
      "geometry": {
        "type": "Point",
        "coordinates": [
          -5.666667,
          55.783333
        ]
      },
      "type": "Feature",
      "properties": {
        "hierarchy": [
          "tgn:7460595",
          "tgn:7019094",
          "tgn:7002444",
          "tgn:1000003",
          "tgn:7008591",
          "tgn:7029392"
        ],
        "placetype": [
          "aat:300008850"
        ],
        "name:en": "Kilberry Head",
        "id": 7460595
      }
    },
    {
      "geometry": {
        "type": "Point",
        "coordinates": [
          -7.45,
          57.033333
        ]
      },
      "type": "Feature",
      "properties": {
        "hierarchy": [
          "tgn:7460597",
          "tgn:7002444",
          "tgn:1000003",
          "tgn:7008094",
          "tgn:7008591",
          "tgn:7029392"
        ],
        "placetype": [
          "aat:300008804"
        ],
        "name:en": "Kilbar",
        "id": 7460597
      }
    },
    {
      "geometry": {
        "type": "Point",
        "coordinates": [
          -7.5,
          56.95
        ]
      },
      "type": "Feature",
      "properties": {
        "hierarchy": [
          "tgn:7460598",
          "tgn:7002444",
          "tgn:1000003",
          "tgn:7008094",
          "tgn:7008591",
          "tgn:7029392"
        ],
        "placetype": [
          "aat:300004792"
        ],
        "name:en": "Kiessimul Castle",
        "id": 7460598
      }
    },
    {
      "geometry": {
        "type": "Point",
        "coordinates": [
          -2.6,
          59.216667
        ]
      },
      "type": "Feature",
      "properties": {
        "hierarchy": [
          "tgn:7460599",
          "tgn:7002444",
          "tgn:1000003",
          "tgn:7009907",
          "tgn:7008591",
          "tgn:7029392"
        ],
        "placetype": [
          "aat:300387036"
        ],
        "name:en": "Kierlie Shoal",
        "id": 7460599
      }
    }
  ]
}
