{
  "geometry": {
    "type": "Point",
    "coordinates": [
      45.7667,
      52.6333
    ]
  },
  "type": "Feature",
  "properties": {
    "hierarchy": [
      "tgn:1137865",
      "tgn:1000004",
      "tgn:1003399",
      "tgn:7018214",
      "tgn:7002435",
      "tgn:7029392"
    ],
    "placetype": [
      "aat:300008347"
    ],
    "id": 1137865,
    "name:xx": "Lopatino"
  }
}
