{
  "geometry": {
    "type": "Point",
    "coordinates": [
      -69.2167,
      46.3333
    ]
  },
  "type": "Feature",
  "properties": {
    "hierarchy": [
      "tgn:2130171",
      "tgn:1000001",
      "tgn:7012149",
      "tgn:2000928",
      "tgn:7007515",
      "tgn:7029392"
    ],
    "placetype": [
      "aat:300008798"
    ],
    "id": 2130171,
    "name:xx": "Allen Mountain"
  }
}
