{
  "geometry": {
    "type": "Point",
    "coordinates": [
      -105.35,
      43.8167
    ]
  },
  "type": "Feature",
  "properties": {
    "hierarchy": [
      "tgn:2414902",
      "tgn:1000001",
      "tgn:2002367",
      "tgn:7012149",
      "tgn:7007923",
      "tgn:7029392"
    ],
    "placetype": [
      "aat:300006191"
    ],
    "id": 2414902,
    "name:xx": "Isenberger Reservoir"
  }
}
