{
  "geometry": {
    "type": "Point",
    "coordinates": [
      -164.7667,
      64.4833
    ]
  },
  "type": "Feature",
  "properties": {
    "hierarchy": [
      "tgn:2636402",
      "tgn:7006450",
      "tgn:1000001",
      "tgn:7012149",
      "tgn:2000079",
      "tgn:7029392"
    ],
    "placetype": [
      "aat:300132316"
    ],
    "id": 2636402,
    "name:xx": "Safety Sound"
  }
}
