{
  "geometry": {
    "type": "Point",
    "coordinates": [
      -79.85,
      39.6333
    ]
  },
  "type": "Feature",
  "properties": {
    "hierarchy": [
      "tgn:2491599",
      "tgn:1000001",
      "tgn:7012149",
      "tgn:2002288",
      "tgn:7013961",
      "tgn:7029392"
    ],
    "placetype": [
      "aat:300008699"
    ],
    "id": 2491599,
    "name:xx": "Maple Run"
  }
}
