{
  "type": "FeatureCollection",
  "features": [
    {
      "geometry": {
        "type": "Point",
        "coordinates": [
          120.839527,
          24.191124
        ]
      },
      "type": "Feature",
      "properties": {
        "hierarchy": [
          "tgn:7474570",
          "tgn:1000004",
          "tgn:7001009",
          "tgn:1000141",
          "tgn:7029392"
        ],
        "placetype": [
          "aat:300007836"
        ],
        "id": 7474570,
        "name:xx": "Yong'an Qiao"
      }
    },
    {
      "geometry": {
        "type": "Point",
        "coordinates": [
          119.605177,
          23.622902
        ]
      },
      "type": "Feature",
      "properties": {
        "hierarchy": [
          "tgn:7474571",
          "tgn:1000004",
          "tgn:7004300",
          "tgn:1000141",
          "tgn:7029392"
        ],
        "placetype": [
          "aat:300007836"
        ],
        "id": 7474571,
        "name:xx": "Yong'an Qiao"
      }
    },
    {
      "geometry": {
        "type": "Point",
        "coordinates": [
          120.6,
          24.386667
        ]
      },
      "type": "Feature",
      "properties": {
        "hierarchy": [
          "tgn:7474572",
          "tgn:1000004",
          "tgn:7001009",
          "tgn:1000141",
          "tgn:7029392"
        ],
        "placetype": [
          "aat:300008347"
        ],
        "id": 7474572,
        "name:xx": "Xiada'an"
      }
    },
    {
      "geometry": {
        "type": "Point",
        "coordinates": [
          120.5285,
          24.2238
        ]
      },
      "type": "Feature",
      "properties": {
        "hierarchy": [
          "tgn:7474573",
          "tgn:1000004",
          "tgn:7001009",
          "tgn:1000141",
          "tgn:7029392"
        ],
        "placetype": [
          "aat:300008347"
        ],
        "id": 7474573,
        "name:xx": "Yong'an"
      }
    },
    {
      "geometry": {
        "type": "Point",
        "coordinates": [
          120.633124,
          24.187191
        ]
      },
      "type": "Feature",
      "properties": {
        "hierarchy": [
          "tgn:7474574",
          "tgn:1000004",
          "tgn:7001009",
          "tgn:1000141",
          "tgn:7029392"
        ],
        "placetype": [
          "aat:300387200"
        ],
        "id": 7474574,
        "name:xx": "Yong'an Li"
      }
    },
    {
      "geometry": {
        "type": "Point",
        "coordinates": [
          120.3718,
          23.8492
        ]
      },
      "type": "Feature",
      "properties": {
        "hierarchy": [
          "tgn:7474575",
          "tgn:1000004",
          "tgn:7467799",
          "tgn:1000141",
          "tgn:7029392"
        ],
        "placetype": [
          "aat:300387173"
        ],
        "id": 7474575,
        "name:xx": "Yong'an Cun"
      }
    },
    {
      "geometry": {
        "type": "Point",
        "coordinates": [
          121.143222,
          22.926798
        ]
      },
      "type": "Feature",
      "properties": {
        "hierarchy": [
          "tgn:7474576",
          "tgn:1000004",
          "tgn:7491221",
          "tgn:1000141",
          "tgn:7029392"
        ],
        "placetype": [
          "aat:300008347"
        ],
        "id": 7474576,
        "name:xx": "Yong'ancun"
      }
    },
    {
      "geometry": {
        "type": "Point",
        "coordinates": [
          120.223889,
          22.817222
        ]
      },
      "type": "Feature",
      "properties": {
        "hierarchy": [
          "tgn:7474577",
          "tgn:7001004",
          "tgn:1000004",
          "tgn:1000141",
          "tgn:7029392"
        ],
        "placetype": [
          "aat:300008347"
        ],
        "id": 7474577,
        "name:xx": "Yong'an"
      }
    },
    {
      "geometry": {
        "type": "Point",
        "coordinates": [
          120.975603,
          23.353703
        ]
      },
      "type": "Feature",
      "properties": {
        "hierarchy": [
          "tgn:7474578",
          "tgn:7001004",
          "tgn:1000004",
          "tgn:1000141",
          "tgn:7029392"
        ],
        "placetype": [
          "aat:300008795"
        ],
        "id": 7474578,
        "name:xx": "Yun Feng"
      }
    },
    {
      "geometry": {
        "type": "Point",
        "coordinates": [
          118.440099,
          24.518227
        ]
      },
      "type": "Feature",
      "properties": {
        "hierarchy": [
          "tgn:7474579",
          "tgn:7469009",
          "tgn:1000004",
          "tgn:1000141",
          "tgn:7029392"
        ],
        "placetype": [
          "aat:300387036"
        ],
        "id": 7474579,
        "name:xx": "Yunei"
      }
    }
  ]
}
