{
  "geometry": {
    "type": "Point",
    "coordinates": [
      12.15,
      50.45
    ]
  },
  "type": "Feature",
  "properties": {
    "hierarchy": [
      "tgn:7124326",
      "tgn:1000003",
      "tgn:7003685",
      "tgn:7000084",
      "tgn:7029392"
    ],
    "placetype": [
      "aat:300008688"
    ],
    "id": 7124326,
    "name:xx": "Niederer Mühl-Teich"
  }
}
