{
  "geometry": {
    "type": "Point",
    "coordinates": [
      20.168,
      42.843
    ]
  },
  "type": "Feature",
  "properties": {
    "hierarchy": [
      "tgn:1065226",
      "tgn:7593980",
      "tgn:1000003",
      "tgn:7015657",
      "tgn:7029392"
    ],
    "placetype": [
      "aat:300008347"
    ],
    "id": 1065226,
    "name:xx": "Rožaje"
  }
}
