{
  "geometry": {
    "type": "Point",
    "coordinates": [
      -107.3333,
      39.9667
    ]
  },
  "type": "Feature",
  "properties": {
    "hierarchy": [
      "tgn:2495324",
      "tgn:1000001",
      "tgn:7012149",
      "tgn:7007158",
      "tgn:2000243",
      "tgn:7029392"
    ],
    "placetype": [
      "aat:300008680"
    ],
    "id": 2495324,
    "name:xx": "Mary Loch Lake"
  }
}
