{
  "geometry": {
    "type": "Point",
    "coordinates": [
      -92.5333,
      33.6667
    ]
  },
  "type": "Feature",
  "properties": {
    "hierarchy": [
      "tgn:2510104",
      "tgn:1000001",
      "tgn:7016172",
      "tgn:2000111",
      "tgn:7012149",
      "tgn:7029392"
    ],
    "placetype": [
      "aat:300006191"
    ],
    "id": 2510104,
    "name:xx": "Middle Pond"
  }
}
