{
  "geometry": {
    "type": "Point",
    "coordinates": [
      -77.0333,
      40.5667
    ]
  },
  "type": "Feature",
  "properties": {
    "hierarchy": [
      "tgn:2723249",
      "tgn:1000001",
      "tgn:7012149",
      "tgn:1002779",
      "tgn:7007710",
      "tgn:7029392"
    ],
    "placetype": [
      "aat:300008761"
    ],
    "id": 2723249,
    "name:xx": "Toad Hollow"
  }
}
