{
  "geometry": {
    "type": "Point",
    "coordinates": [
      120.9748,
      24.6639
    ]
  },
  "type": "Feature",
  "properties": {
    "hierarchy": [
      "tgn:7472690",
      "tgn:7487020",
      "tgn:1000004",
      "tgn:1000141",
      "tgn:7029392"
    ],
    "placetype": [
      "aat:300387173"
    ],
    "id": 7472690,
    "name:xx": "Tongjing Cun"
  }
}
