{
  "geometry": {
    "type": "Point",
    "coordinates": [
      -117.3333,
      39.2667
    ]
  },
  "type": "Feature",
  "properties": {
    "hierarchy": [
      "tgn:2625691",
      "tgn:1000001",
      "tgn:2001415",
      "tgn:7012149",
      "tgn:7007526",
      "tgn:7029392"
    ],
    "placetype": [
      "aat:300008798"
    ],
    "id": 2625691,
    "name:xx": "Rocky Bluff"
  }
}
