{
  "geometry": {
    "type": "Point",
    "coordinates": [
      -4.866667,
      43.45
    ]
  },
  "type": "Feature",
  "properties": {
    "hierarchy": [
      "tgn:7325754",
      "tgn:7008911",
      "tgn:1000003",
      "tgn:7002763",
      "tgn:1000095",
      "tgn:7029392"
    ],
    "placetype": [
      "aat:300008816"
    ],
    "id": 7325754,
    "name:xx": "San Antolín, Playa de"
  }
}
