{
  "geometry": {
    "type": "Point",
    "coordinates": [
      -113.0833,
      39.7667
    ]
  },
  "type": "Feature",
  "properties": {
    "hierarchy": [
      "tgn:2586168",
      "tgn:1000001",
      "tgn:7012149",
      "tgn:7007827",
      "tgn:7029392"
    ],
    "placetype": [
      "aat:300008761"
    ],
    "id": 2586168,
    "name:xx": "Pismire Wash"
  }
}
