{
  "type": "FeatureCollection",
  "features": [
    {
      "geometry": {
        "type": "Point",
        "coordinates": [
          -149.8,
          61.2667
        ]
      },
      "type": "Feature",
      "properties": {
        "hierarchy": [
          "tgn:2728850",
          "tgn:2124017",
          "tgn:7006450",
          "tgn:1000001",
          "tgn:7012149",
          "tgn:7029392"
        ],
        "placetype": [
          "aat:300008680"
        ],
        "id": 2728850,
        "name:xx": "Triangle Lake"
      }
    },
    {
      "geometry": {
        "type": "Point",
        "coordinates": [
          -149.2,
          61.55
        ]
      },
      "type": "Feature",
      "properties": {
        "hierarchy": [
          "tgn:2728851",
          "tgn:7006450",
          "tgn:1000001",
          "tgn:2124053",
          "tgn:7012149",
          "tgn:7029392"
        ],
        "placetype": [
          "aat:300008680"
        ],
        "id": 2728851,
        "name:xx": "Triangle Lake"
      }
    },
    {
      "geometry": {
        "type": "Point",
        "coordinates": [
          -120.0833,
          38.85
        ]
      },
      "type": "Feature",
      "properties": {
        "hierarchy": [
          "tgn:2728852",
          "tgn:1000001",
          "tgn:7012149",
          "tgn:1002350",
          "tgn:7007157",
          "tgn:7029392"
        ],
        "placetype": [
          "aat:300008680"
        ],
        "id": 2728852,
        "name:xx": "Triangle Lake"
      }
    },
    {
      "geometry": {
        "type": "Point",
        "coordinates": [
          -121.2,
          40.5167
        ]
      },
      "type": "Feature",
      "properties": {
        "hierarchy": [
          "tgn:2728853",
          "tgn:1000001",
          "tgn:7012149",
          "tgn:7007157",
          "tgn:2000184",
          "tgn:7029392"
        ],
        "placetype": [
          "aat:300006191"
        ],
        "id": 2728853,
        "name:xx": "Triangle Lake"
      }
    },
    {
      "geometry": {
        "type": "Point",
        "coordinates": [
          -105.65,
          40.05
        ]
      },
      "type": "Feature",
      "properties": {
        "hierarchy": [
          "tgn:2728854",
          "tgn:1000001",
          "tgn:7012149",
          "tgn:2000216",
          "tgn:7007158",
          "tgn:7029392"
        ],
        "placetype": [
          "aat:300008680"
        ],
        "id": 2728854,
        "name:xx": "Triangle Lake"
      }
    },
    {
      "geometry": {
        "type": "Point",
        "coordinates": [
          -115.1333,
          43.9167
        ]
      },
      "type": "Feature",
      "properties": {
        "hierarchy": [
          "tgn:2728855",
          "tgn:1000001",
          "tgn:7012149",
          "tgn:2000471",
          "tgn:7007250",
          "tgn:7029392"
        ],
        "placetype": [
          "aat:300008680"
        ],
        "id": 2728855,
        "name:xx": "Triangle Lake"
      }
    },
    {
      "geometry": {
        "type": "Point",
        "coordinates": [
          -116.55,
          45.3167
        ]
      },
      "type": "Feature",
      "properties": {
        "hierarchy": [
          "tgn:2728856",
          "tgn:1000001",
          "tgn:7012149",
          "tgn:2000476",
          "tgn:7007250",
          "tgn:7029392"
        ],
        "placetype": [
          "aat:300008680"
        ],
        "id": 2728856,
        "name:xx": "Triangle Lake"
      }
    },
    {
      "geometry": {
        "type": "Point",
        "coordinates": [
          -83.95,
          42.5167
        ]
      },
      "type": "Feature",
      "properties": {
        "hierarchy": [
          "tgn:2728857",
          "tgn:1000001",
          "tgn:7012149",
          "tgn:1002603",
          "tgn:7007520",
          "tgn:7029392"
        ],
        "placetype": [
          "aat:300008680"
        ],
        "id": 2728857,
        "name:xx": "Triangle Lake"
      }
    },
    {
      "geometry": {
        "type": "Point",
        "coordinates": [
          -86.0833,
          46.5167
        ]
      },
      "type": "Feature",
      "properties": {
        "hierarchy": [
          "tgn:2728858",
          "tgn:2000943",
          "tgn:1000001",
          "tgn:7012149",
          "tgn:7007520",
          "tgn:7029392"
        ],
        "placetype": [
          "aat:300008680"
        ],
        "id": 2728858,
        "name:xx": "Triangle Lake"
      }
    },
    {
      "geometry": {
        "type": "Point",
        "coordinates": [
          -86.5,
          46.1667
        ]
      },
      "type": "Feature",
      "properties": {
        "hierarchy": [
          "tgn:2728859",
          "tgn:1000001",
          "tgn:7012149",
          "tgn:2000996",
          "tgn:7007520",
          "tgn:7029392"
        ],
        "placetype": [
          "aat:300008680"
        ],
        "id": 2728859,
        "name:xx": "Triangle Lake"
      }
    }
  ]
}
