{
  "geometry": {
    "type": "Point",
    "coordinates": [
      88.916932,
      22.570735
    ]
  },
  "type": "Feature",
  "properties": {
    "hierarchy": [
      "tgn:1075427",
      "tgn:1000004",
      "tgn:7000198",
      "tgn:1001977",
      "tgn:7029392"
    ],
    "placetype": [
      "aat:300008347"
    ],
    "name:en": "Hāsnābād",
    "id": 1075427
  }
}
