{
  "geometry": {
    "type": "Point",
    "coordinates": [
      -82.6833,
      28.4167
    ]
  },
  "type": "Feature",
  "properties": {
    "hierarchy": [
      "tgn:2717200",
      "tgn:1000001",
      "tgn:7012149",
      "tgn:1002773",
      "tgn:7007240",
      "tgn:7029392"
    ],
    "placetype": [
      "aat:300008850"
    ],
    "id": 2717200,
    "name:xx": "Third Point"
  }
}
