{
  "geometry": {
    "type": "Point",
    "coordinates": [
      -77.55,
      34.6167
    ]
  },
  "type": "Feature",
  "properties": {
    "hierarchy": [
      "tgn:2658144",
      "tgn:1000001",
      "tgn:7012149",
      "tgn:7007709",
      "tgn:7029392"
    ],
    "placetype": [
      "aat:300008706"
    ],
    "id": 2658144,
    "name:xx": "Shelter Swamp Creek"
  }
}
