{
  "geometry": {
    "type": "Point",
    "coordinates": [
      -113.6667,
      45.9333
    ]
  },
  "type": "Feature",
  "properties": {
    "hierarchy": [
      "tgn:2536857",
      "tgn:1000001",
      "tgn:7012149",
      "tgn:2001300",
      "tgn:7007524",
      "tgn:7029392"
    ],
    "placetype": [
      "aat:300008706"
    ],
    "id": 2536857,
    "name:xx": "Needle Creek"
  }
}
