{
  "geometry": {
    "type": "Point",
    "coordinates": [
      -90.95,
      41.4167
    ]
  },
  "type": "Feature",
  "properties": {
    "hierarchy": [
      "tgn:2387154",
      "tgn:1000001",
      "tgn:7012149",
      "tgn:2000528",
      "tgn:7007251",
      "tgn:7029392"
    ],
    "placetype": [
      "aat:300008791"
    ],
    "id": 2387154,
    "name:xx": "Hershey Island"
  }
}
