{
  "geometry": {
    "type": "Point",
    "coordinates": [
      -105.266667,
      21.75
    ]
  },
  "type": "Feature",
  "properties": {
    "hierarchy": [
      "tgn:7366254",
      "tgn:1000001",
      "tgn:1001906",
      "tgn:7005560",
      "tgn:7029392"
    ],
    "placetype": [
      "aat:300008347"
    ],
    "id": 7366254,
    "name:xx": "El Patroneño"
  }
}
