{
  "geometry": {
    "type": "Point",
    "coordinates": [
      -82.6167,
      36.8833
    ]
  },
  "type": "Feature",
  "properties": {
    "hierarchy": [
      "tgn:2309869",
      "tgn:1000001",
      "tgn:7012149",
      "tgn:2002195",
      "tgn:7007919",
      "tgn:7029392"
    ],
    "placetype": [
      "aat:300008706"
    ],
    "id": 2309869,
    "name:xx": "Eastland Creek"
  }
}
