{
  "type": "FeatureCollection",
  "features": [
    {
      "geometry": {
        "type": "Point",
        "coordinates": [
          11.5667,
          48.25
        ]
      },
      "type": "Feature",
      "properties": {
        "hierarchy": [
          "tgn:7004650",
          "tgn:7003669",
          "tgn:1000003",
          "tgn:7000084",
          "tgn:7029392"
        ],
        "placetype": [
          "aat:300008347"
        ],
        "id": 7004650,
        "name:xx": "Oberschleissheim"
      }
    },
    {
      "geometry": {
        "type": "Point",
        "coordinates": [
          140.1,
          41.4667
        ]
      },
      "type": "Feature",
      "properties": {
        "hierarchy": [
          "tgn:7004651",
          "tgn:1000985",
          "tgn:7016529",
          "tgn:7016531",
          "tgn:1000004",
          "tgn:1000120",
          "tgn:7029392"
        ],
        "placetype": [
          "aat:300008347",
          "aat:300008375"
        ],
        "id": 7004651,
        "name:xx": "Matsumae"
      }
    },
    {
      "geometry": {
        "type": "Point",
        "coordinates": [
          11.933333,
          48.3
        ]
      },
      "type": "Feature",
      "properties": {
        "hierarchy": [
          "tgn:7004652",
          "tgn:7003669",
          "tgn:1000003",
          "tgn:7000084",
          "tgn:7029392"
        ],
        "placetype": [
          "aat:300008347"
        ],
        "id": 7004652,
        "name:xx": "Erding"
      }
    },
    {
      "geometry": {
        "type": "Point",
        "coordinates": [
          137.9667,
          36.3
        ]
      },
      "type": "Feature",
      "properties": {
        "hierarchy": [
          "tgn:7004653",
          "tgn:7000895",
          "tgn:1000004",
          "tgn:1001010",
          "tgn:1000120",
          "tgn:7029392"
        ],
        "placetype": [
          "aat:300008347",
          "aat:300008389",
          "aat:300264742",
          "aat:300387512"
        ],
        "id": 7004653,
        "name:xx": "Matsumoto"
      }
    },
    {
      "geometry": {
        "type": "Point",
        "coordinates": [
          12,
          48.15
        ]
      },
      "type": "Feature",
      "properties": {
        "hierarchy": [
          "tgn:7004654",
          "tgn:7003669",
          "tgn:1000003",
          "tgn:7000084",
          "tgn:7029392"
        ],
        "placetype": [
          "aat:300008347",
          "aat:300000835"
        ],
        "id": 7004654,
        "name:xx": "Hohenlinden"
      }
    },
    {
      "geometry": {
        "type": "Point",
        "coordinates": [
          132.7833,
          33.8333
        ]
      },
      "type": "Feature",
      "properties": {
        "hierarchy": [
          "tgn:7004655",
          "tgn:7004473",
          "tgn:1000004",
          "tgn:7000903",
          "tgn:1000120",
          "tgn:7029392"
        ],
        "placetype": [
          "aat:300008347",
          "aat:300008389",
          "aat:300387220"
        ],
        "id": 7004655,
        "name:xx": "Matsuyama"
      }
    },
    {
      "geometry": {
        "type": "Point",
        "coordinates": [
          11.983333,
          48.4
        ]
      },
      "type": "Feature",
      "properties": {
        "hierarchy": [
          "tgn:7004657",
          "tgn:7003669",
          "tgn:1000003",
          "tgn:7000084",
          "tgn:7029392"
        ],
        "placetype": [
          "aat:300008347"
        ],
        "id": 7004657,
        "name:xx": "Wartenberg"
      }
    },
    {
      "geometry": {
        "type": "Point",
        "coordinates": [
          14.4833,
          40.75
        ]
      },
      "type": "Feature",
      "properties": {
        "hierarchy": [
          "tgn:7004658",
          "tgn:7003013",
          "tgn:7003005",
          "tgn:1000003",
          "tgn:1000080",
          "tgn:7029392"
        ],
        "placetype": [
          "aat:300008347",
          "aat:300387007",
          "aat:300000810",
          "aat:300167671",
          "aat:300008389",
          "aat:300000547",
          "aat:300263063"
        ],
        "id": 7004658,
        "name:xx": "Pompeii"
      }
    },
    {
      "geometry": {
        "type": "Point",
        "coordinates": [
          130.3833,
          32.2167
        ]
      },
      "type": "Feature",
      "properties": {
        "hierarchy": [
          "tgn:7004659",
          "tgn:1000997",
          "tgn:1000004",
          "tgn:7000901",
          "tgn:1000120",
          "tgn:7029392"
        ],
        "placetype": [
          "aat:300008347"
        ],
        "id": 7004659,
        "name:xx": "Minamata"
      }
    }
  ]
}
