{
  "geometry": {
    "type": "Point",
    "coordinates": [
      -71.7667,
      41.9833
    ]
  },
  "type": "Feature",
  "properties": {
    "hierarchy": [
      "tgn:2201897",
      "tgn:1002808",
      "tgn:1000001",
      "tgn:7012149",
      "tgn:7007711",
      "tgn:7029392"
    ],
    "placetype": [
      "aat:300132451"
    ],
    "id": 2201897,
    "name:xx": "Buck Hill"
  }
}
