{
  "geometry": {
    "type": "Point",
    "coordinates": [
      -87.7333,
      15.0167
    ]
  },
  "type": "Feature",
  "properties": {
    "hierarchy": [
      "tgn:1130394",
      "tgn:1000801",
      "tgn:1000001",
      "tgn:7005554",
      "tgn:7029392"
    ],
    "placetype": [
      "aat:300008707"
    ],
    "id": 1130394,
    "name:xx": "Sulaco, Río"
  }
}
