{
  "geometry": {
    "type": "Point",
    "coordinates": [
      31.289145,
      30.299
    ]
  },
  "type": "Feature",
  "properties": {
    "hierarchy": [
      "tgn:7527696",
      "tgn:7001242",
      "tgn:7016833",
      "tgn:1001092",
      "tgn:7029392"
    ],
    "placetype": [
      "aat:300008347"
    ],
    "name:en": "Zāwiyat Sīdī Sanad",
    "id": 7527696
  }
}
