{
  "geometry": {
    "type": "Point",
    "coordinates": [
      80.75,
      16.283333
    ]
  },
  "type": "Feature",
  "properties": {
    "hierarchy": [
      "tgn:7578374",
      "tgn:1001828",
      "tgn:1000004",
      "tgn:7000198",
      "tgn:7029392"
    ],
    "placetype": [
      "aat:300008347"
    ],
    "name:en": "Tūmulūru",
    "id": 7578374
  }
}
