{
  "geometry": {
    "type": "Point",
    "coordinates": [
      -88.8833,
      15.7333
    ]
  },
  "type": "Feature",
  "properties": {
    "hierarchy": [
      "tgn:1116206",
      "tgn:1000650",
      "tgn:1000001",
      "tgn:7005493",
      "tgn:7029392"
    ],
    "placetype": [
      "aat:300008680"
    ],
    "id": 1116206,
    "name:xx": "El Golfete"
  }
}
