{
  "type": "FeatureCollection",
  "features": [
    {
      "geometry": {
        "type": "Point",
        "coordinates": [
          -147.3167,
          61.8833
        ]
      },
      "type": "Feature",
      "properties": {
        "hierarchy": [
          "tgn:1108581",
          "tgn:7006450",
          "tgn:1000001",
          "tgn:2124053",
          "tgn:7012149",
          "tgn:7029392"
        ],
        "placetype": [
          "aat:300259572"
        ],
        "id": 1108581,
        "name:xx": "Tahneta Pass"
      }
    },
    {
      "geometry": {
        "type": "Point",
        "coordinates": [
          73.1833,
          39.7833
        ]
      },
      "type": "Feature",
      "properties": {
        "hierarchy": [
          "tgn:1108582",
          "tgn:1000004",
          "tgn:7012212",
          "tgn:7006655",
          "tgn:7029392"
        ],
        "placetype": [
          "aat:300259572"
        ],
        "id": 1108582,
        "name:xx": "Taldyk, Pereval"
      }
    },
    {
      "geometry": {
        "type": "Point",
        "coordinates": [
          92.45,
          32.7
        ]
      },
      "type": "Feature",
      "properties": {
        "hierarchy": [
          "tgn:1108583",
          "tgn:1000004",
          "tgn:1000111",
          "tgn:7029392"
        ],
        "placetype": [
          "aat:300259572"
        ],
        "id": 1108583,
        "name:xx": "Tanggula Shankou"
      }
    },
    {
      "geometry": {
        "type": "Point",
        "coordinates": [
          -111.2667,
          44.6667
        ]
      },
      "type": "Feature",
      "properties": {
        "hierarchy": [
          "tgn:1108584",
          "tgn:1000001",
          "tgn:7012149",
          "tgn:7029392"
        ],
        "placetype": [
          "aat:300259572"
        ],
        "id": 1108584,
        "name:xx": "Targhee Pass"
      }
    },
    {
      "geometry": {
        "type": "Point",
        "coordinates": [
          -118.2833,
          35.1
        ]
      },
      "type": "Feature",
      "properties": {
        "hierarchy": [
          "tgn:1108586",
          "tgn:1000001",
          "tgn:7012149",
          "tgn:1002545",
          "tgn:7007157",
          "tgn:7029392"
        ],
        "placetype": [
          "aat:300259572"
        ],
        "id": 1108586,
        "name:xx": "Tehachapi Pass"
      }
    },
    {
      "geometry": {
        "type": "Point",
        "coordinates": [
          -118.8667,
          34.8
        ]
      },
      "type": "Feature",
      "properties": {
        "hierarchy": [
          "tgn:1108587",
          "tgn:1000001",
          "tgn:7012149",
          "tgn:7007157",
          "tgn:1002608",
          "tgn:7029392"
        ],
        "placetype": [
          "aat:300259572"
        ],
        "id": 1108587,
        "name:xx": "Tejon Pass"
      }
    }
  ]
}
