{
  "geometry": {
    "type": "Point",
    "coordinates": [
      -83.05,
      30.4333
    ]
  },
  "type": "Feature",
  "properties": {
    "hierarchy": [
      "tgn:2396594",
      "tgn:1000001",
      "tgn:7012149",
      "tgn:7007240",
      "tgn:7029392"
    ],
    "placetype": [
      "aat:300008706"
    ],
    "id": 2396594,
    "name:xx": "Holton Creek"
  }
}
