{
  "geometry": {
    "type": "Point",
    "coordinates": [
      -89.25,
      46.1667
    ]
  },
  "type": "Feature",
  "properties": {
    "hierarchy": [
      "tgn:2397497",
      "tgn:1000001",
      "tgn:7012149",
      "tgn:2000960",
      "tgn:7007520",
      "tgn:7029392"
    ],
    "placetype": [
      "aat:300008680"
    ],
    "id": 2397497,
    "name:xx": "Honey Lake"
  }
}
