{
  "geometry": {
    "type": "Point",
    "coordinates": [
      -100.1167,
      30.8833
    ]
  },
  "type": "Feature",
  "properties": {
    "hierarchy": [
      "tgn:2515277",
      "tgn:1000001",
      "tgn:7012149",
      "tgn:7007826",
      "tgn:7029392"
    ],
    "placetype": [
      "aat:300008761"
    ],
    "id": 2515277,
    "name:xx": "Milligan Draw"
  }
}
