{
  "type": "FeatureCollection",
  "features": [
    {
      "geometry": {
        "type": "Point",
        "coordinates": [
          -102.283333,
          20.633333
        ]
      },
      "type": "Feature",
      "properties": {
        "hierarchy": [
          "tgn:7365690",
          "tgn:7005586",
          "tgn:1000001",
          "tgn:7005560",
          "tgn:7029392"
        ],
        "placetype": [
          "aat:300008347"
        ],
        "id": 7365690,
        "name:xx": "El Refugio"
      }
    },
    {
      "geometry": {
        "type": "Point",
        "coordinates": [
          -102.716667,
          20.533333
        ]
      },
      "type": "Feature",
      "properties": {
        "hierarchy": [
          "tgn:7365691",
          "tgn:7005586",
          "tgn:1000001",
          "tgn:7005560",
          "tgn:7029392"
        ],
        "placetype": [
          "aat:300008347"
        ],
        "id": 7365691,
        "name:xx": "El Refugio"
      }
    },
    {
      "geometry": {
        "type": "Point",
        "coordinates": [
          -90.066667,
          20.416667
        ]
      },
      "type": "Feature",
      "properties": {
        "hierarchy": [
          "tgn:7365692",
          "tgn:7005578",
          "tgn:1000001",
          "tgn:7005560",
          "tgn:7029392"
        ],
        "placetype": [
          "aat:300008347"
        ],
        "id": 7365692,
        "name:xx": "El Refugio"
      }
    },
    {
      "geometry": {
        "type": "Point",
        "coordinates": [
          -99.8,
          20.3
        ]
      },
      "type": "Feature",
      "properties": {
        "hierarchy": [
          "tgn:7365693",
          "tgn:7005587",
          "tgn:1000001",
          "tgn:7005560",
          "tgn:7029392"
        ],
        "placetype": [
          "aat:300008347"
        ],
        "id": 7365693,
        "name:xx": "El Refugio"
      }
    },
    {
      "geometry": {
        "type": "Point",
        "coordinates": [
          -102.216667,
          20.266667
        ]
      },
      "type": "Feature",
      "properties": {
        "hierarchy": [
          "tgn:7365694",
          "tgn:1000001",
          "tgn:7005590",
          "tgn:7005560",
          "tgn:7029392"
        ],
        "placetype": [
          "aat:300008347"
        ],
        "id": 7365694,
        "name:xx": "El Refugio"
      }
    },
    {
      "geometry": {
        "type": "Point",
        "coordinates": [
          -104.766667,
          20.25
        ]
      },
      "type": "Feature",
      "properties": {
        "hierarchy": [
          "tgn:7365695",
          "tgn:7005586",
          "tgn:1000001",
          "tgn:7005560",
          "tgn:7029392"
        ],
        "placetype": [
          "aat:300008347"
        ],
        "id": 7365695,
        "name:xx": "El Refugio"
      }
    },
    {
      "geometry": {
        "type": "Point",
        "coordinates": [
          -103.133333,
          20.116667
        ]
      },
      "type": "Feature",
      "properties": {
        "hierarchy": [
          "tgn:7365696",
          "tgn:7005586",
          "tgn:1000001",
          "tgn:7005560",
          "tgn:7029392"
        ],
        "placetype": [
          "aat:300008347"
        ],
        "id": 7365696,
        "name:xx": "El Refugio"
      }
    },
    {
      "geometry": {
        "type": "Point",
        "coordinates": [
          -96.95,
          20
        ]
      },
      "type": "Feature",
      "properties": {
        "hierarchy": [
          "tgn:7365697",
          "tgn:1000001",
          "tgn:7005599",
          "tgn:7005560",
          "tgn:7029392"
        ],
        "placetype": [
          "aat:300008347"
        ],
        "id": 7365697,
        "name:xx": "El Refugio"
      }
    },
    {
      "geometry": {
        "type": "Point",
        "coordinates": [
          -104.533333,
          19.35
        ]
      },
      "type": "Feature",
      "properties": {
        "hierarchy": [
          "tgn:7365698",
          "tgn:7005586",
          "tgn:1000001",
          "tgn:7005560",
          "tgn:7029392"
        ],
        "placetype": [
          "aat:300008347"
        ],
        "id": 7365698,
        "name:xx": "El Refugio"
      }
    },
    {
      "geometry": {
        "type": "Point",
        "coordinates": [
          -92.883333,
          17.916667
        ]
      },
      "type": "Feature",
      "properties": {
        "hierarchy": [
          "tgn:7365699",
          "tgn:1000001",
          "tgn:7005596",
          "tgn:7005560",
          "tgn:7029392"
        ],
        "placetype": [
          "aat:300008347"
        ],
        "id": 7365699,
        "name:xx": "El Refugio"
      }
    }
  ]
}
