{
  "type": "FeatureCollection",
  "features": [
    {
      "geometry": {
        "type": "Point",
        "coordinates": [
          11.416667,
          48.6
        ]
      },
      "type": "Feature",
      "properties": {
        "hierarchy": [
          "tgn:7093481",
          "tgn:7003669",
          "tgn:1000003",
          "tgn:7000084",
          "tgn:7029392"
        ],
        "placetype": [
          "aat:300000206"
        ],
        "id": 7093481,
        "name:xx": "Schwaig"
      }
    },
    {
      "geometry": {
        "type": "Point",
        "coordinates": [
          12.966667,
          48.55
        ]
      },
      "type": "Feature",
      "properties": {
        "hierarchy": [
          "tgn:7093482",
          "tgn:7003669",
          "tgn:1000003",
          "tgn:7000084",
          "tgn:7029392"
        ],
        "placetype": [
          "aat:300000206"
        ],
        "id": 7093482,
        "name:xx": "Schwaig"
      }
    },
    {
      "geometry": {
        "type": "Point",
        "coordinates": [
          12.9,
          48.216667
        ]
      },
      "type": "Feature",
      "properties": {
        "hierarchy": [
          "tgn:7093483",
          "tgn:7003669",
          "tgn:1000003",
          "tgn:7000084",
          "tgn:7029392"
        ],
        "placetype": [
          "aat:300000206"
        ],
        "id": 7093483,
        "name:xx": "Schwaig"
      }
    },
    {
      "geometry": {
        "type": "Point",
        "coordinates": [
          12.866667,
          47.95
        ]
      },
      "type": "Feature",
      "properties": {
        "hierarchy": [
          "tgn:7093484",
          "tgn:7003669",
          "tgn:1000003",
          "tgn:7000084",
          "tgn:7029392"
        ],
        "placetype": [
          "aat:300000206"
        ],
        "id": 7093484,
        "name:xx": "Schwaig"
      }
    },
    {
      "geometry": {
        "type": "Point",
        "coordinates": [
          12.1,
          47.933333
        ]
      },
      "type": "Feature",
      "properties": {
        "hierarchy": [
          "tgn:7093485",
          "tgn:7003669",
          "tgn:1000003",
          "tgn:7000084",
          "tgn:7029392"
        ],
        "placetype": [
          "aat:300000206"
        ],
        "id": 7093485,
        "name:xx": "Schwaig"
      }
    },
    {
      "geometry": {
        "type": "Point",
        "coordinates": [
          11.933333,
          47.833333
        ]
      },
      "type": "Feature",
      "properties": {
        "hierarchy": [
          "tgn:7093486",
          "tgn:7003669",
          "tgn:1000003",
          "tgn:7000084",
          "tgn:7029392"
        ],
        "placetype": [
          "aat:300000206"
        ],
        "id": 7093486,
        "name:xx": "Schwaig"
      }
    },
    {
      "geometry": {
        "type": "Point",
        "coordinates": [
          13.416667,
          48.616667
        ]
      },
      "type": "Feature",
      "properties": {
        "hierarchy": [
          "tgn:7093487",
          "tgn:7003669",
          "tgn:1000003",
          "tgn:7000084",
          "tgn:7029392"
        ],
        "placetype": [
          "aat:300008347"
        ],
        "id": 7093487,
        "name:xx": "Schwaiberg"
      }
    },
    {
      "geometry": {
        "type": "Point",
        "coordinates": [
          13.066667,
          48.433333
        ]
      },
      "type": "Feature",
      "properties": {
        "hierarchy": [
          "tgn:7093488",
          "tgn:7003669",
          "tgn:1000003",
          "tgn:7000084",
          "tgn:7029392"
        ],
        "placetype": [
          "aat:300008347"
        ],
        "id": 7093488,
        "name:xx": "Schwaibach"
      }
    },
    {
      "geometry": {
        "type": "Point",
        "coordinates": [
          8.033333,
          48.4
        ]
      },
      "type": "Feature",
      "properties": {
        "hierarchy": [
          "tgn:7093489",
          "tgn:7003692",
          "tgn:1000003",
          "tgn:7000084",
          "tgn:7029392"
        ],
        "placetype": [
          "aat:300008347"
        ],
        "id": 7093489,
        "name:xx": "Schwaibach"
      }
    }
  ]
}
