{
  "geometry": {
    "type": "Point",
    "coordinates": [
      33.4667,
      52.85
    ]
  },
  "type": "Feature",
  "properties": {
    "hierarchy": [
      "tgn:1059298",
      "tgn:7011551",
      "tgn:1000004",
      "tgn:7018214",
      "tgn:7002435",
      "tgn:7029392"
    ],
    "placetype": [
      "aat:300008347"
    ],
    "id": 1059298,
    "name:xx": "Semcy"
  }
}
