{
  "type": "FeatureCollection",
  "features": [
    {
      "geometry": {
        "type": "Point",
        "coordinates": [
          -14.5,
          28.05
        ]
      },
      "type": "Feature",
      "properties": {
        "hierarchy": [
          "tgn:1012810",
          "tgn:7002825",
          "tgn:7016622",
          "tgn:1000003",
          "tgn:1000095",
          "tgn:1007139",
          "tgn:7029392"
        ],
        "placetype": [
          "aat:300008804"
        ],
        "id": 1012810,
        "name:xx": "Jandía, Península de"
      }
    },
    {
      "geometry": {
        "type": "Point",
        "coordinates": [
          13.583333,
          54.533333
        ]
      },
      "type": "Feature",
      "properties": {
        "hierarchy": [
          "tgn:1012811",
          "tgn:1000003",
          "tgn:7000094",
          "tgn:7000084",
          "tgn:7029392"
        ],
        "placetype": [
          "aat:300008804"
        ],
        "id": 1012811,
        "name:xx": "Jasmund"
      }
    },
    {
      "geometry": {
        "type": "Point",
        "coordinates": [
          -61,
          -66.1667
        ]
      },
      "type": "Feature",
      "properties": {
        "hierarchy": [
          "tgn:1012812",
          "tgn:1000007",
          "tgn:7029392"
        ],
        "placetype": [
          "aat:300008804"
        ],
        "id": 1012812,
        "name:xx": "Jason Peninsula"
      }
    },
    {
      "geometry": {
        "type": "Point",
        "coordinates": [
          173.7,
          -42.433333
        ]
      },
      "type": "Feature",
      "properties": {
        "hierarchy": [
          "tgn:1012815",
          "tgn:1009227",
          "tgn:7001866",
          "tgn:1000226",
          "tgn:1000006",
          "tgn:7029392"
        ],
        "placetype": [
          "aat:300008804"
        ],
        "name:en": "Kaikoura Peninsula",
        "id": 1012815
      }
    },
    {
      "geometry": {
        "type": "Point",
        "coordinates": [
          160,
          56
        ]
      },
      "type": "Feature",
      "properties": {
        "hierarchy": [
          "tgn:1012817",
          "tgn:1000004",
          "tgn:6002931",
          "tgn:7018214",
          "tgn:7002435",
          "tgn:7029392"
        ],
        "placetype": [
          "aat:300008804"
        ],
        "id": 1012817,
        "name:xx": "Kamchatka"
      }
    },
    {
      "geometry": {
        "type": "Point",
        "coordinates": [
          163,
          56.25
        ]
      },
      "type": "Feature",
      "properties": {
        "hierarchy": [
          "tgn:1012818",
          "tgn:1000004",
          "tgn:6002931",
          "tgn:7018214",
          "tgn:7002435",
          "tgn:7029392"
        ],
        "placetype": [
          "aat:300008804"
        ],
        "id": 1012818,
        "name:xx": "Kamcatskiy Poluostrov"
      }
    }
  ]
}
