{
  "geometry": {
    "type": "Point",
    "coordinates": [
      -76.8833,
      36.9333
    ]
  },
  "type": "Feature",
  "properties": {
    "hierarchy": [
      "tgn:2752039",
      "tgn:1000001",
      "tgn:7012149",
      "tgn:1002911",
      "tgn:7007919",
      "tgn:7029392"
    ],
    "placetype": [
      "aat:300008699"
    ],
    "id": 2752039,
    "name:xx": "Warwick Branch"
  }
}
