{
  "type": "FeatureCollection",
  "features": [
    {
      "geometry": {
        "type": "Point",
        "coordinates": [
          -115.4333,
          46
        ]
      },
      "type": "Feature",
      "properties": {
        "hierarchy": [
          "tgn:2322522",
          "tgn:1000001",
          "tgn:7012149",
          "tgn:2000476",
          "tgn:7007250",
          "tgn:7029392"
        ],
        "placetype": [
          "aat:300008706"
        ],
        "id": 2322522,
        "name:xx": "Falls Creek"
      }
    },
    {
      "geometry": {
        "type": "Point",
        "coordinates": [
          -116.6,
          47.85
        ]
      },
      "type": "Feature",
      "properties": {
        "hierarchy": [
          "tgn:2322524",
          "tgn:1000001",
          "tgn:7012149",
          "tgn:2000479",
          "tgn:7007250",
          "tgn:7029392"
        ],
        "placetype": [
          "aat:300008706"
        ],
        "id": 2322524,
        "name:xx": "Falls Creek"
      }
    },
    {
      "geometry": {
        "type": "Point",
        "coordinates": [
          -116.35,
          48.0333
        ]
      },
      "type": "Feature",
      "properties": {
        "hierarchy": [
          "tgn:2322525",
          "tgn:1000001",
          "tgn:2000460",
          "tgn:7012149",
          "tgn:7007250",
          "tgn:7029392"
        ],
        "placetype": [
          "aat:300008706"
        ],
        "id": 2322525,
        "name:xx": "Falls Creek"
      }
    },
    {
      "geometry": {
        "type": "Point",
        "coordinates": [
          -77.4833,
          39.7167
        ]
      },
      "type": "Feature",
      "properties": {
        "hierarchy": [
          "tgn:2322526",
          "tgn:1000001",
          "tgn:7012149",
          "tgn:7029392"
        ],
        "placetype": [
          "aat:300008706"
        ],
        "id": 2322526,
        "name:xx": "Falls Creek"
      }
    },
    {
      "geometry": {
        "type": "Point",
        "coordinates": [
          -90.2833,
          47.9
        ]
      },
      "type": "Feature",
      "properties": {
        "hierarchy": [
          "tgn:2322527",
          "tgn:1000001",
          "tgn:2001014",
          "tgn:7012149",
          "tgn:7007521",
          "tgn:7029392"
        ],
        "placetype": [
          "aat:300008706"
        ],
        "id": 2322527,
        "name:xx": "Falls Creek"
      }
    },
    {
      "geometry": {
        "type": "Point",
        "coordinates": [
          -93.1,
          44.2833
        ]
      },
      "type": "Feature",
      "properties": {
        "hierarchy": [
          "tgn:2322528",
          "tgn:1000001",
          "tgn:7012149",
          "tgn:2001064",
          "tgn:7007521",
          "tgn:7029392"
        ],
        "placetype": [
          "aat:300008706"
        ],
        "id": 2322528,
        "name:xx": "Falls Creek"
      }
    },
    {
      "geometry": {
        "type": "Point",
        "coordinates": [
          -109.7,
          45.0833
        ]
      },
      "type": "Feature",
      "properties": {
        "hierarchy": [
          "tgn:2322529",
          "tgn:1000001",
          "tgn:2001264",
          "tgn:7012149",
          "tgn:7007524",
          "tgn:7029392"
        ],
        "placetype": [
          "aat:300008706"
        ],
        "id": 2322529,
        "name:xx": "Falls Creek"
      }
    }
  ]
}
