{
  "geometry": {
    "type": "Point",
    "coordinates": [
      -73.9167,
      40.7667
    ]
  },
  "type": "Feature",
  "properties": {
    "hierarchy": [
      "tgn:2396385",
      "tgn:1000001",
      "tgn:7012149",
      "tgn:1002715",
      "tgn:7007568",
      "tgn:7029392"
    ],
    "placetype": [
      "aat:300132348"
    ],
    "id": 2396385,
    "name:xx": "Holmes Rock"
  }
}
