{
  "geometry": {
    "type": "Point",
    "coordinates": [
      -82.85,
      38.1833
    ]
  },
  "type": "Feature",
  "properties": {
    "hierarchy": [
      "tgn:2187666",
      "tgn:1000001",
      "tgn:1002240",
      "tgn:7012149",
      "tgn:7007255",
      "tgn:7029392"
    ],
    "placetype": [
      "aat:300008761"
    ],
    "id": 2187666,
    "name:xx": "Booth Hollow"
  }
}
