{
  "geometry": {
    "type": "Point",
    "coordinates": [
      -105.3667,
      44.3667
    ]
  },
  "type": "Feature",
  "properties": {
    "hierarchy": [
      "tgn:2373278",
      "tgn:1000001",
      "tgn:2002367",
      "tgn:7012149",
      "tgn:7007923",
      "tgn:7029392"
    ],
    "placetype": [
      "aat:300008697"
    ],
    "id": 2373278,
    "name:xx": "Halsted Spring"
  }
}
