{
  "geometry": {
    "type": "Point",
    "coordinates": [
      -92.05,
      34.5833
    ]
  },
  "type": "Feature",
  "properties": {
    "hierarchy": [
      "tgn:2503058",
      "tgn:1000001",
      "tgn:7016172",
      "tgn:7012149",
      "tgn:2000164",
      "tgn:7029392"
    ],
    "placetype": [
      "aat:300008905"
    ],
    "id": 2503058,
    "name:xx": "McNeely Brake"
  }
}
