{
  "geometry": {
    "type": "Point",
    "coordinates": [
      31.198616,
      30.861545
    ]
  },
  "type": "Feature",
  "properties": {
    "hierarchy": [
      "tgn:7537647",
      "tgn:7001242",
      "tgn:7016833",
      "tgn:7001312",
      "tgn:7029392"
    ],
    "placetype": [
      "aat:300008347"
    ],
    "name:en": "Mīt Hāshim",
    "id": 7537647
  }
}
