{
  "geometry": {
    "type": "Point",
    "coordinates": [
      -78.7833,
      38.0167
    ]
  },
  "type": "Feature",
  "properties": {
    "hierarchy": [
      "tgn:2695983",
      "tgn:2002137",
      "tgn:1000001",
      "tgn:7012149",
      "tgn:7007919",
      "tgn:7029392"
    ],
    "placetype": [
      "aat:300008706"
    ],
    "id": 2695983,
    "name:xx": "Stockton Mill Creek"
  }
}
