{
  "geometry": {
    "type": "Point",
    "coordinates": [
      -78.1167,
      39.1833
    ]
  },
  "type": "Feature",
  "properties": {
    "hierarchy": [
      "tgn:2138664",
      "tgn:1000001",
      "tgn:7012149",
      "tgn:2002161",
      "tgn:7007919",
      "tgn:7029392"
    ],
    "placetype": [
      "aat:300008699"
    ],
    "id": 2138664,
    "name:xx": "Ash Hollow Run"
  }
}
