{
  "type": "FeatureCollection",
  "features": [
    {
      "geometry": {
        "type": "Point",
        "coordinates": [
          175.05,
          -39.933333
        ]
      },
      "type": "Feature",
      "properties": {
        "hierarchy": [
          "tgn:7001840",
          "tgn:1008380",
          "tgn:7520093",
          "tgn:1000226",
          "tgn:1000006",
          "tgn:7029392"
        ],
        "placetype": [
          "aat:300008347",
          "aat:300008389",
          "aat:300387316",
          "aat:300000833"
        ],
        "name:en": "Wanganui",
        "id": 7001840
      }
    },
    {
      "geometry": {
        "type": "Point",
        "coordinates": [
          110.75,
          34.7
        ]
      },
      "type": "Feature",
      "properties": {
        "hierarchy": [
          "tgn:7001842",
          "tgn:1000004",
          "tgn:7002086",
          "tgn:1000111",
          "tgn:7029392"
        ],
        "placetype": [
          "aat:300008347",
          "aat:300008375"
        ],
        "id": 7001842,
        "name:xx": "Ruicheng"
      }
    },
    {
      "geometry": {
        "type": "Point",
        "coordinates": [
          116,
          25.8
        ]
      },
      "type": "Feature",
      "properties": {
        "hierarchy": [
          "tgn:7001843",
          "tgn:1000004",
          "tgn:7002082",
          "tgn:1000111",
          "tgn:7029392"
        ],
        "placetype": [
          "aat:300008347",
          "aat:300008375"
        ],
        "id": 7001843,
        "name:xx": "Ruijin"
      }
    },
    {
      "geometry": {
        "type": "Point",
        "coordinates": [
          100.45,
          38.9333
        ]
      },
      "type": "Feature",
      "properties": {
        "hierarchy": [
          "tgn:7001844",
          "tgn:1000004",
          "tgn:1001261",
          "tgn:1000111",
          "tgn:7029392"
        ],
        "placetype": [
          "aat:300008347",
          "aat:300387235",
          "aat:300008375"
        ],
        "id": 7001844,
        "name:xx": "Zhangye"
      }
    },
    {
      "geometry": {
        "type": "Point",
        "coordinates": [
          114.3333,
          34.7833
        ]
      },
      "type": "Feature",
      "properties": {
        "hierarchy": [
          "tgn:7001845",
          "tgn:1000004",
          "tgn:7016672",
          "tgn:1000111",
          "tgn:7029392"
        ],
        "placetype": [
          "aat:300008347",
          "aat:300008389",
          "aat:300387223",
          "aat:300000833",
          "aat:300387302"
        ],
        "id": 7001845,
        "name:xx": "Kaifeng"
      }
    },
    {
      "geometry": {
        "type": "Point",
        "coordinates": [
          101.05,
          41.7833
        ]
      },
      "type": "Feature",
      "properties": {
        "hierarchy": [
          "tgn:7001846",
          "tgn:1000004",
          "tgn:7001838",
          "tgn:1000111",
          "tgn:7029392"
        ],
        "placetype": [
          "aat:300008347",
          "aat:300000810",
          "aat:300167671",
          "aat:300387286"
        ],
        "id": 7001846,
        "name:xx": "Heicheng"
      }
    },
    {
      "geometry": {
        "type": "Point",
        "coordinates": [
          120,
          36.3333
        ]
      },
      "type": "Feature",
      "properties": {
        "hierarchy": [
          "tgn:7001848",
          "tgn:1000004",
          "tgn:7002085",
          "tgn:1000111",
          "tgn:7029392"
        ],
        "placetype": [
          "aat:300008347",
          "aat:300008375",
          "aat:300387270",
          "aat:300387286"
        ],
        "id": 7001848,
        "name:xx": "Jiaoxian"
      }
    },
    {
      "geometry": {
        "type": "Point",
        "coordinates": [
          84.9167,
          45.5
        ]
      },
      "type": "Feature",
      "properties": {
        "hierarchy": [
          "tgn:7001849",
          "tgn:1000004",
          "tgn:7001745",
          "tgn:1000111",
          "tgn:7029392"
        ],
        "placetype": [
          "aat:300008347",
          "aat:300008375"
        ],
        "id": 7001849,
        "name:xx": "Karamay"
      }
    }
  ]
}
