{
  "geometry": {
    "type": "Point",
    "coordinates": [
      -123.45,
      46.65
    ]
  },
  "type": "Feature",
  "properties": {
    "hierarchy": [
      "tgn:2209949",
      "tgn:1000001",
      "tgn:7012149",
      "tgn:1002767",
      "tgn:7007920",
      "tgn:7029392"
    ],
    "placetype": [
      "aat:300008347"
    ],
    "id": 2209949,
    "name:xx": "Burt"
  }
}
