{
  "geometry": {
    "type": "Point",
    "coordinates": [
      -107.65,
      48.8833
    ]
  },
  "type": "Feature",
  "properties": {
    "hierarchy": [
      "tgn:2369920",
      "tgn:1000001",
      "tgn:7012149",
      "tgn:2001295",
      "tgn:7007524",
      "tgn:7029392"
    ],
    "placetype": [
      "aat:300008761"
    ],
    "id": 2369920,
    "name:xx": "Gustin Coulee"
  }
}
