{
  "geometry": {
    "type": "Point",
    "coordinates": [
      -91.55,
      34.15
    ]
  },
  "type": "Feature",
  "properties": {
    "hierarchy": [
      "tgn:2153549",
      "tgn:1000001",
      "tgn:7016172",
      "tgn:7012149",
      "tgn:2000139",
      "tgn:7029392"
    ],
    "placetype": [
      "aat:300008699"
    ],
    "id": 2153549,
    "name:xx": "Bear Bayou"
  }
}
