{
  "geometry": {
    "type": "Point",
    "coordinates": [
      32.3333,
      65.5167
    ]
  },
  "type": "Feature",
  "properties": {
    "hierarchy": [
      "tgn:1055633",
      "tgn:1000004",
      "tgn:7011509",
      "tgn:7002435",
      "tgn:7029392"
    ],
    "placetype": [
      "aat:300008347"
    ],
    "id": 1055633,
    "name:xx": "Korelaksha"
  }
}
