{
  "geometry": {
    "type": "Point",
    "coordinates": [
      -76.55,
      34.65
    ]
  },
  "type": "Feature",
  "properties": {
    "hierarchy": [
      "tgn:2767364",
      "tgn:1000001",
      "tgn:2001477",
      "tgn:7012149",
      "tgn:7007709",
      "tgn:7029392"
    ],
    "placetype": [
      "aat:300008905"
    ],
    "id": 2767364,
    "name:xx": "White Shoal Marsh"
  }
}
