{
  "geometry": {
    "type": "Point",
    "coordinates": [
      -92.25,
      29.8833
    ]
  },
  "type": "Feature",
  "properties": {
    "hierarchy": [
      "tgn:2042589",
      "tgn:1000001",
      "tgn:7012149",
      "tgn:2000910",
      "tgn:7007256",
      "tgn:7029392"
    ],
    "placetype": [
      "aat:300008347"
    ],
    "id": 2042589,
    "name:xx": "Cow Island"
  }
}
