{
  "geometry": {
    "type": "Point",
    "coordinates": [
      -94.2167,
      37.95
    ]
  },
  "type": "Feature",
  "properties": {
    "hierarchy": [
      "tgn:2306127",
      "tgn:1000001",
      "tgn:7012149",
      "tgn:2001253",
      "tgn:7007523",
      "tgn:7029392"
    ],
    "placetype": [
      "aat:300008699"
    ],
    "id": 2306127,
    "name:xx": "East Fork Bee Branch"
  }
}
