{
  "type": "FeatureCollection",
  "features": [
    {
      "geometry": {
        "type": "Point",
        "coordinates": [
          89.5833,
          26.8333
        ]
      },
      "type": "Feature",
      "properties": {
        "hierarchy": [
          "tgn:1131872",
          "tgn:1000004",
          "tgn:7014831",
          "tgn:7029392"
        ],
        "placetype": [
          "aat:300008707"
        ],
        "id": 1131872,
        "name:xx": "Wong Chu"
      }
    },
    {
      "geometry": {
        "type": "Point",
        "coordinates": [
          -158.5833,
          59.2667
        ]
      },
      "type": "Feature",
      "properties": {
        "hierarchy": [
          "tgn:1131873",
          "tgn:7006450",
          "tgn:1000001",
          "tgn:2000071",
          "tgn:7012149",
          "tgn:7029392"
        ],
        "placetype": [
          "aat:300008707"
        ],
        "id": 1131873,
        "name:xx": "Wood River"
      }
    },
    {
      "geometry": {
        "type": "Point",
        "coordinates": [
          -99.8833,
          41.1667
        ]
      },
      "type": "Feature",
      "properties": {
        "hierarchy": [
          "tgn:1131874",
          "tgn:1000001",
          "tgn:7012149",
          "tgn:7007525",
          "tgn:7029392"
        ],
        "placetype": [
          "aat:300008707"
        ],
        "id": 1131874,
        "name:xx": "Wood"
      }
    },
    {
      "geometry": {
        "type": "Point",
        "coordinates": [
          -109.35,
          43.8333
        ]
      },
      "type": "Feature",
      "properties": {
        "hierarchy": [
          "tgn:1131875",
          "tgn:1000001",
          "tgn:7012149",
          "tgn:2002379",
          "tgn:7007923",
          "tgn:7029392"
        ],
        "placetype": [
          "aat:300008707"
        ],
        "id": 1131875,
        "name:xx": "Wood"
      }
    },
    {
      "geometry": {
        "type": "Point",
        "coordinates": [
          -118.45,
          52.1333
        ]
      },
      "type": "Feature",
      "properties": {
        "hierarchy": [
          "tgn:1131876",
          "tgn:7005735",
          "tgn:7005685",
          "tgn:1000001",
          "tgn:7029392"
        ],
        "placetype": [
          "aat:300008707"
        ],
        "id": 1131876,
        "name:xx": "Wood"
      }
    },
    {
      "geometry": {
        "type": "Point",
        "coordinates": [
          -106.1667,
          50.1333
        ]
      },
      "type": "Feature",
      "properties": {
        "hierarchy": [
          "tgn:1131877",
          "tgn:7005685",
          "tgn:1000001",
          "tgn:7005805",
          "tgn:7029392"
        ],
        "placetype": [
          "aat:300008707"
        ],
        "id": 1131877,
        "name:xx": "Wood"
      }
    },
    {
      "geometry": {
        "type": "Point",
        "coordinates": [
          137.9667,
          -21.4667
        ]
      },
      "type": "Feature",
      "properties": {
        "hierarchy": [
          "tgn:1131879",
          "tgn:7000490",
          "tgn:1000006",
          "tgn:7029392"
        ],
        "placetype": [
          "aat:300008707"
        ],
        "id": 1131879,
        "name:xx": "Woodroffe River"
      }
    }
  ]
}
