{
  "geometry": {
    "type": "Point",
    "coordinates": [
      -92.4667,
      42.55
    ]
  },
  "type": "Feature",
  "properties": {
    "hierarchy": [
      "tgn:2279684",
      "tgn:2000567",
      "tgn:1000001",
      "tgn:7012149",
      "tgn:7007253",
      "tgn:7029392"
    ],
    "placetype": [
      "aat:300008791"
    ],
    "id": 2279684,
    "name:xx": "Deadmans Island"
  }
}
