{
  "geometry": {
    "type": "Point",
    "coordinates": [
      -117.4833,
      33.3667
    ]
  },
  "type": "Feature",
  "properties": {
    "hierarchy": [
      "tgn:2333396",
      "tgn:1000001",
      "tgn:7012149",
      "tgn:7007157",
      "tgn:1002858",
      "tgn:7029392"
    ],
    "placetype": [
      "aat:300008761"
    ],
    "id": 2333396,
    "name:xx": "Foley Canyon"
  }
}
