{
  "geometry": {
    "type": "Point",
    "coordinates": [
      -134.2167,
      57.5667
    ]
  },
  "type": "Feature",
  "properties": {
    "hierarchy": [
      "tgn:2784762",
      "tgn:7006450",
      "tgn:1000001",
      "tgn:7012149",
      "tgn:7019760",
      "tgn:7029392"
    ],
    "placetype": [
      "aat:300008798"
    ],
    "id": 2784762,
    "name:xx": "Yellow Bear Mountain"
  }
}
