{
  "geometry": {
    "type": "Point",
    "coordinates": [
      -69.9333,
      43.75
    ]
  },
  "type": "Feature",
  "properties": {
    "hierarchy": [
      "tgn:2736892",
      "tgn:1000001",
      "tgn:2000920",
      "tgn:7012149",
      "tgn:7007515",
      "tgn:7029392"
    ],
    "placetype": [
      "aat:300008791"
    ],
    "id": 2736892,
    "name:xx": "Two Bush Island"
  }
}
