{
  "geometry": {
    "type": "Point",
    "coordinates": [
      -121.55,
      47.6667
    ]
  },
  "type": "Feature",
  "properties": {
    "hierarchy": [
      "tgn:2178209",
      "tgn:1000001",
      "tgn:7012149",
      "tgn:7018871",
      "tgn:7007920",
      "tgn:7029392"
    ],
    "placetype": [
      "aat:300000390"
    ],
    "id": 2178209,
    "name:xx": "Blackhawk Mine"
  }
}
