{
  "geometry": {
    "type": "Point",
    "coordinates": [
      -82.9167,
      29.7833
    ]
  },
  "type": "Feature",
  "properties": {
    "hierarchy": [
      "tgn:2623197",
      "tgn:1000001",
      "tgn:2000269",
      "tgn:7012149",
      "tgn:7007240",
      "tgn:7029392"
    ],
    "placetype": [
      "aat:300008697"
    ],
    "id": 2623197,
    "name:xx": "Rock Bluff Spring"
  }
}
