{
  "geometry": {
    "type": "Point",
    "coordinates": [
      -79.7167,
      39.7833
    ]
  },
  "type": "Feature",
  "properties": {
    "hierarchy": [
      "tgn:2684403",
      "tgn:1000001",
      "tgn:7012149",
      "tgn:7014185",
      "tgn:7007710",
      "tgn:7029392"
    ],
    "placetype": [
      "aat:300008746"
    ],
    "id": 2684403,
    "name:xx": "Spider Cave"
  }
}
