{
  "geometry": {
    "type": "Point",
    "coordinates": [
      -114.8667,
      45.4167
    ]
  },
  "type": "Feature",
  "properties": {
    "hierarchy": [
      "tgn:2482534",
      "tgn:1000001",
      "tgn:7012149",
      "tgn:2000476",
      "tgn:7007250",
      "tgn:7029392"
    ],
    "placetype": [
      "aat:300132348"
    ],
    "id": 2482534,
    "name:xx": "Lantz Bar"
  }
}
