{
  "type": "FeatureCollection",
  "features": [
    {
      "geometry": {
        "type": "Point",
        "coordinates": [
          -76.1833,
          43.5333
        ]
      },
      "type": "Feature",
      "properties": {
        "hierarchy": [
          "tgn:2278111",
          "tgn:1000001",
          "tgn:7012149",
          "tgn:1002758",
          "tgn:7007568",
          "tgn:7029392"
        ],
        "placetype": [
          "aat:300008347"
        ],
        "id": 2278111,
        "name:xx": "Daysville Corner"
      }
    },
    {
      "geometry": {
        "type": "Point",
        "coordinates": [
          -90.3167,
          41.4833
        ]
      },
      "type": "Feature",
      "properties": {
        "hierarchy": [
          "tgn:2278112",
          "tgn:1000001",
          "tgn:7012149",
          "tgn:2000511",
          "tgn:7007251",
          "tgn:7029392"
        ],
        "placetype": [
          "aat:300008347"
        ],
        "id": 2278112,
        "name:xx": "Dayton"
      }
    },
    {
      "geometry": {
        "type": "Point",
        "coordinates": [
          -92.1833,
          41.85
        ]
      },
      "type": "Feature",
      "properties": {
        "hierarchy": [
          "tgn:2278113",
          "tgn:1000001",
          "tgn:7012149",
          "tgn:2000608",
          "tgn:7007253",
          "tgn:7029392"
        ],
        "placetype": [
          "aat:300008347"
        ],
        "id": 2278113,
        "name:xx": "Dayton"
      }
    },
    {
      "geometry": {
        "type": "Point",
        "coordinates": [
          -94.9167,
          40.7167
        ]
      },
      "type": "Feature",
      "properties": {
        "hierarchy": [
          "tgn:2278114",
          "tgn:1000001",
          "tgn:7012149",
          "tgn:2000633",
          "tgn:7007253",
          "tgn:7029392"
        ],
        "placetype": [
          "aat:300008347",
          "aat:300167671"
        ],
        "id": 2278114,
        "name:xx": "Dayton"
      }
    },
    {
      "geometry": {
        "type": "Point",
        "coordinates": [
          -91.15,
          30.4833
        ]
      },
      "type": "Feature",
      "properties": {
        "hierarchy": [
          "tgn:2278115",
          "tgn:1000001",
          "tgn:2000870",
          "tgn:7012149",
          "tgn:7007256",
          "tgn:7029392"
        ],
        "placetype": [
          "aat:300008347"
        ],
        "id": 2278115,
        "name:xx": "Dayton"
      }
    },
    {
      "geometry": {
        "type": "Point",
        "coordinates": [
          -83.2833,
          43.45
        ]
      },
      "type": "Feature",
      "properties": {
        "hierarchy": [
          "tgn:2278116",
          "tgn:1000001",
          "tgn:7012149",
          "tgn:2000997",
          "tgn:7007520",
          "tgn:7029392"
        ],
        "placetype": [
          "aat:300008347"
        ],
        "id": 2278116,
        "name:xx": "Dayton"
      }
    },
    {
      "geometry": {
        "type": "Point",
        "coordinates": [
          -122.5167,
          45.9167
        ]
      },
      "type": "Feature",
      "properties": {
        "hierarchy": [
          "tgn:2278117",
          "tgn:1000001",
          "tgn:1002275",
          "tgn:7012149",
          "tgn:7007920",
          "tgn:7029392"
        ],
        "placetype": [
          "aat:300008347"
        ],
        "id": 2278117,
        "name:xx": "Dayton"
      }
    },
    {
      "geometry": {
        "type": "Point",
        "coordinates": [
          -79.5833,
          39.3
        ]
      },
      "type": "Feature",
      "properties": {
        "hierarchy": [
          "tgn:2278118",
          "tgn:1000001",
          "tgn:7012149",
          "tgn:2002288",
          "tgn:7013961",
          "tgn:7029392"
        ],
        "placetype": [
          "aat:300008347"
        ],
        "id": 2278118,
        "name:xx": "Dayton"
      }
    },
    {
      "geometry": {
        "type": "Point",
        "coordinates": [
          -97.8333,
          45.8333
        ]
      },
      "type": "Feature",
      "properties": {
        "hierarchy": [
          "tgn:2278119",
          "tgn:1000001",
          "tgn:2001815",
          "tgn:7012149",
          "tgn:7007713",
          "tgn:7029392"
        ],
        "placetype": [
          "aat:300006075"
        ],
        "id": 2278119,
        "name:xx": "Dayton - Crow Creek Ditch"
      }
    }
  ]
}
