{
  "geometry": {
    "type": "Point",
    "coordinates": [
      -91.0833,
      39.8833
    ]
  },
  "type": "Feature",
  "properties": {
    "hierarchy": [
      "tgn:1133816",
      "tgn:1000001",
      "tgn:7012149",
      "tgn:7007251",
      "tgn:7029392"
    ],
    "placetype": [
      "aat:300008706"
    ],
    "id": 1133816,
    "name:xx": "McCraney Creek"
  }
}
