{
  "geometry": {
    "type": "Point",
    "coordinates": [
      121.1833,
      27.9833
    ]
  },
  "type": "Feature",
  "properties": {
    "hierarchy": [
      "tgn:1007940",
      "tgn:1000004",
      "tgn:7002076",
      "tgn:1000111",
      "tgn:7029392"
    ],
    "placetype": [
      "aat:300008791"
    ],
    "id": 1007940,
    "name:xx": "Luxi Dao"
  }
}
