{
  "geometry": {
    "type": "Point",
    "coordinates": [
      -109.1833,
      41.6667
    ]
  },
  "type": "Feature",
  "properties": {
    "hierarchy": [
      "tgn:2123134",
      "tgn:1000001",
      "tgn:7012149",
      "tgn:2002383",
      "tgn:7007923",
      "tgn:7029392"
    ],
    "placetype": [
      "aat:300008347"
    ],
    "id": 2123134,
    "name:xx": "Reliance"
  }
}
