{
  "geometry": {
    "type": "Point",
    "coordinates": [
      28.45,
      31.066667
    ]
  },
  "type": "Feature",
  "properties": {
    "hierarchy": [
      "tgn:7538355",
      "tgn:7001242",
      "tgn:7016833",
      "tgn:1001418",
      "tgn:7029392"
    ],
    "placetype": [
      "aat:300386968"
    ],
    "name:en": "Mersà Muḥammad el-Fallâh",
    "id": 7538355
  }
}
