{
  "geometry": {
    "type": "Point",
    "coordinates": [
      -90.6667,
      38.9667
    ]
  },
  "type": "Feature",
  "properties": {
    "hierarchy": [
      "tgn:2159999",
      "tgn:1000001",
      "tgn:1002221",
      "tgn:7012149",
      "tgn:7007251",
      "tgn:7029392"
    ],
    "placetype": [
      "aat:300008347"
    ],
    "id": 2159999,
    "name:xx": "Beech Landing"
  }
}
