{
  "type": "FeatureCollection",
  "features": [
    {
      "geometry": {
        "type": "Point",
        "coordinates": [
          -78.2,
          34.65
        ]
      },
      "type": "Feature",
      "properties": {
        "hierarchy": [
          "tgn:2320890",
          "tgn:1000001",
          "tgn:7012149",
          "tgn:2001538",
          "tgn:7007709",
          "tgn:7029392"
        ],
        "placetype": [
          "aat:300008347"
        ],
        "id": 2320890,
        "name:xx": "Ezzelltown"
      }
    },
    {
      "geometry": {
        "type": "Point",
        "coordinates": [
          -118.7,
          39.55
        ]
      },
      "type": "Feature",
      "properties": {
        "hierarchy": [
          "tgn:2320891",
          "tgn:1000001",
          "tgn:2001409",
          "tgn:7012149",
          "tgn:7007526",
          "tgn:7029392"
        ],
        "placetype": [
          "aat:300006075"
        ],
        "id": 2320891,
        "name:xx": "F 2 Drain"
      }
    },
    {
      "geometry": {
        "type": "Point",
        "coordinates": [
          -100.4167,
          33.55
        ]
      },
      "type": "Feature",
      "properties": {
        "hierarchy": [
          "tgn:2320892",
          "tgn:1000001",
          "tgn:7012149",
          "tgn:2002020",
          "tgn:7007826",
          "tgn:7029392"
        ],
        "placetype": [
          "aat:300008761"
        ],
        "id": 2320892,
        "name:xx": "F A Canyon"
      }
    },
    {
      "geometry": {
        "type": "Point",
        "coordinates": [
          -82.0833,
          35.0167
        ]
      },
      "type": "Feature",
      "properties": {
        "hierarchy": [
          "tgn:2320893",
          "tgn:1000001",
          "tgn:7012149",
          "tgn:2001766",
          "tgn:7007712",
          "tgn:7029392"
        ],
        "placetype": [
          "aat:300006191"
        ],
        "id": 2320893,
        "name:xx": "F Bush Pond"
      }
    },
    {
      "geometry": {
        "type": "Point",
        "coordinates": [
          -105.4,
          43.5667
        ]
      },
      "type": "Feature",
      "properties": {
        "hierarchy": [
          "tgn:2320894",
          "tgn:1000001",
          "tgn:2002367",
          "tgn:7012149",
          "tgn:7007923",
          "tgn:7029392"
        ],
        "placetype": [
          "aat:300006191"
        ],
        "id": 2320894,
        "name:xx": "F C R Detention Reservoir"
      }
    },
    {
      "geometry": {
        "type": "Point",
        "coordinates": [
          -114.5333,
          33.6
        ]
      },
      "type": "Feature",
      "properties": {
        "hierarchy": [
          "tgn:2320895",
          "tgn:1000001",
          "tgn:7012149",
          "tgn:7029392"
        ],
        "placetype": [
          "aat:300006075"
        ],
        "id": 2320895,
        "name:xx": "F Canal"
      }
    },
    {
      "geometry": {
        "type": "Point",
        "coordinates": [
          -114.3,
          42.6667
        ]
      },
      "type": "Feature",
      "properties": {
        "hierarchy": [
          "tgn:2320896",
          "tgn:1000001",
          "tgn:7012149",
          "tgn:2000478",
          "tgn:7007250",
          "tgn:7029392"
        ],
        "placetype": [
          "aat:300006075"
        ],
        "id": 2320896,
        "name:xx": "F Canal"
      }
    },
    {
      "geometry": {
        "type": "Point",
        "coordinates": [
          -121.5833,
          42.1667
        ]
      },
      "type": "Feature",
      "properties": {
        "hierarchy": [
          "tgn:2320897",
          "tgn:1000001",
          "tgn:7012149",
          "tgn:2001714",
          "tgn:7007708",
          "tgn:7029392"
        ],
        "placetype": [
          "aat:300006075"
        ],
        "id": 2320897,
        "name:xx": "F Canal"
      }
    },
    {
      "geometry": {
        "type": "Point",
        "coordinates": [
          -110.2,
          40.4
        ]
      },
      "type": "Feature",
      "properties": {
        "hierarchy": [
          "tgn:2320898",
          "tgn:1000001",
          "tgn:2002107",
          "tgn:7012149",
          "tgn:7007827",
          "tgn:7029392"
        ],
        "placetype": [
          "aat:300006075"
        ],
        "id": 2320898,
        "name:xx": "F Canal"
      }
    },
    {
      "geometry": {
        "type": "Point",
        "coordinates": [
          -80.8,
          34.1167
        ]
      },
      "type": "Feature",
      "properties": {
        "hierarchy": [
          "tgn:2320899",
          "tgn:1000001",
          "tgn:7012149",
          "tgn:2001764",
          "tgn:7007712",
          "tgn:7029392"
        ],
        "placetype": [
          "aat:300006191"
        ],
        "id": 2320899,
        "name:xx": "F Coopers Pond"
      }
    }
  ]
}
