{
  "geometry": {
    "type": "Point",
    "coordinates": [
      -82.0667,
      35.75
    ]
  },
  "type": "Feature",
  "properties": {
    "hierarchy": [
      "tgn:2165229",
      "tgn:1000001",
      "tgn:7012149",
      "tgn:2001514",
      "tgn:7007709",
      "tgn:7029392"
    ],
    "placetype": [
      "aat:300266640"
    ],
    "id": 2165229,
    "name:xx": "Betsy Creek"
  }
}
