{
  "geometry": {
    "type": "Point",
    "coordinates": [
      -78.7333,
      36.8167
    ]
  },
  "type": "Feature",
  "properties": {
    "hierarchy": [
      "tgn:2111235",
      "tgn:1000001",
      "tgn:7012149",
      "tgn:2002166",
      "tgn:7007919",
      "tgn:7029392"
    ],
    "placetype": [
      "aat:300008347"
    ],
    "id": 2111235,
    "name:xx": "Clover"
  }
}
