{
  "type": "FeatureCollection",
  "features": [
    {
      "geometry": {
        "type": "Point",
        "coordinates": [
          -90.0833,
          37.2833
        ]
      },
      "type": "Feature",
      "properties": {
        "hierarchy": [
          "tgn:2575990",
          "tgn:1000001",
          "tgn:2001174",
          "tgn:7012149",
          "tgn:7007523",
          "tgn:7029392"
        ],
        "placetype": [
          "aat:300008706"
        ],
        "id": 2575990,
        "name:xx": "Perkins Creek"
      }
    },
    {
      "geometry": {
        "type": "Point",
        "coordinates": [
          -90.6167,
          38.1
        ]
      },
      "type": "Feature",
      "properties": {
        "hierarchy": [
          "tgn:2575991",
          "tgn:1000001",
          "tgn:7012149",
          "tgn:1002517",
          "tgn:7007523",
          "tgn:7029392"
        ],
        "placetype": [
          "aat:300008706"
        ],
        "id": 2575991,
        "name:xx": "Perkins Creek"
      }
    },
    {
      "geometry": {
        "type": "Point",
        "coordinates": [
          -111.9,
          44.85
        ]
      },
      "type": "Feature",
      "properties": {
        "hierarchy": [
          "tgn:2575992",
          "tgn:1000001",
          "tgn:7012149",
          "tgn:2001288",
          "tgn:7007524",
          "tgn:7029392"
        ],
        "placetype": [
          "aat:300008706"
        ],
        "id": 2575992,
        "name:xx": "Perkins Creek"
      }
    },
    {
      "geometry": {
        "type": "Point",
        "coordinates": [
          -110.7333,
          45.7
        ]
      },
      "type": "Feature",
      "properties": {
        "hierarchy": [
          "tgn:2575993",
          "tgn:1000001",
          "tgn:7012149",
          "tgn:2001293",
          "tgn:7007524",
          "tgn:7029392"
        ],
        "placetype": [
          "aat:300008706"
        ],
        "id": 2575993,
        "name:xx": "Perkins Creek"
      }
    },
    {
      "geometry": {
        "type": "Point",
        "coordinates": [
          -79.55,
          42.0833
        ]
      },
      "type": "Feature",
      "properties": {
        "hierarchy": [
          "tgn:2575994",
          "tgn:1000001",
          "tgn:1002259",
          "tgn:7012149",
          "tgn:7007568",
          "tgn:7029392"
        ],
        "placetype": [
          "aat:300008706"
        ],
        "id": 2575994,
        "name:xx": "Perkins Creek"
      }
    },
    {
      "geometry": {
        "type": "Point",
        "coordinates": [
          -122.9167,
          43.7
        ]
      },
      "type": "Feature",
      "properties": {
        "hierarchy": [
          "tgn:2575995",
          "tgn:1000001",
          "tgn:7012149",
          "tgn:2001716",
          "tgn:7007708",
          "tgn:7029392"
        ],
        "placetype": [
          "aat:300008706"
        ],
        "id": 2575995,
        "name:xx": "Perkins Creek"
      }
    },
    {
      "geometry": {
        "type": "Point",
        "coordinates": [
          -124.0167,
          43.8167
        ]
      },
      "type": "Feature",
      "properties": {
        "hierarchy": [
          "tgn:2575996",
          "tgn:1000001",
          "tgn:7012149",
          "tgn:2001706",
          "tgn:7007708",
          "tgn:7029392"
        ],
        "placetype": [
          "aat:300008706"
        ],
        "id": 2575996,
        "name:xx": "Perkins Creek"
      }
    },
    {
      "geometry": {
        "type": "Point",
        "coordinates": [
          -123.4333,
          45.35
        ]
      },
      "type": "Feature",
      "properties": {
        "hierarchy": [
          "tgn:2575997",
          "tgn:1000001",
          "tgn:7012149",
          "tgn:1003044",
          "tgn:7007708",
          "tgn:7029392"
        ],
        "placetype": [
          "aat:300008706"
        ],
        "id": 2575997,
        "name:xx": "Perkins Creek"
      }
    },
    {
      "geometry": {
        "type": "Point",
        "coordinates": [
          -123.2,
          46.0333
        ]
      },
      "type": "Feature",
      "properties": {
        "hierarchy": [
          "tgn:2575998",
          "tgn:1000001",
          "tgn:1002293",
          "tgn:7012149",
          "tgn:7007708",
          "tgn:7029392"
        ],
        "placetype": [
          "aat:300008706"
        ],
        "id": 2575998,
        "name:xx": "Perkins Creek"
      }
    },
    {
      "geometry": {
        "type": "Point",
        "coordinates": [
          -82.95,
          34.6667
        ]
      },
      "type": "Feature",
      "properties": {
        "hierarchy": [
          "tgn:2575999",
          "tgn:1000001",
          "tgn:7012149",
          "tgn:2001761",
          "tgn:7007712",
          "tgn:7029392"
        ],
        "placetype": [
          "aat:300008706"
        ],
        "id": 2575999,
        "name:xx": "Perkins Creek"
      }
    }
  ]
}
