{
  "geometry": {
    "type": "Point",
    "coordinates": [
      -87.2167,
      31.7667
    ]
  },
  "type": "Feature",
  "properties": {
    "hierarchy": [
      "tgn:2003182",
      "tgn:7002659",
      "tgn:1000001",
      "tgn:7012149",
      "tgn:2000049",
      "tgn:7029392"
    ],
    "placetype": [
      "aat:300387016"
    ],
    "id": 2003182,
    "name:xx": "Corduroy"
  }
}
