{
  "geometry": {
    "type": "Point",
    "coordinates": [
      -81.4833,
      30.7167
    ]
  },
  "type": "Feature",
  "properties": {
    "hierarchy": [
      "tgn:2271533",
      "tgn:1000001",
      "tgn:7012149",
      "tgn:7029392"
    ],
    "placetype": [
      "aat:300132316"
    ],
    "id": 2271533,
    "name:xx": "Cumberland Sound"
  }
}
