{
  "geometry": {
    "type": "Point",
    "coordinates": [
      -73.9167,
      40.8667
    ]
  },
  "type": "Feature",
  "properties": {
    "hierarchy": [
      "tgn:2071146",
      "tgn:1000001",
      "tgn:1002204",
      "tgn:7012149",
      "tgn:7007568",
      "tgn:7029392"
    ],
    "placetype": [
      "aat:300008347"
    ],
    "id": 2071146,
    "name:xx": "Spuyten Duyvil"
  }
}
