{
  "geometry": {
    "type": "Point",
    "coordinates": [
      141.8333,
      -37.2833
    ]
  },
  "type": "Feature",
  "properties": {
    "hierarchy": [
      "tgn:1096172",
      "tgn:7000490",
      "tgn:1000006",
      "tgn:7006238",
      "tgn:7029392"
    ],
    "placetype": [
      "aat:300008347"
    ],
    "id": 1096172,
    "name:xx": "Balmoral"
  }
}
