{
  "geometry": {
    "type": "Point",
    "coordinates": [
      -104.8667,
      36.8833
    ]
  },
  "type": "Feature",
  "properties": {
    "hierarchy": [
      "tgn:2759269",
      "tgn:1000001",
      "tgn:2001432",
      "tgn:7012149",
      "tgn:7007566",
      "tgn:7029392"
    ],
    "placetype": [
      "aat:300008761"
    ],
    "id": 2759269,
    "name:xx": "West Fork Chimney Canyon"
  }
}
