{
  "geometry": {
    "type": "Point",
    "coordinates": [
      -151.0833,
      66.9167
    ]
  },
  "type": "Feature",
  "properties": {
    "hierarchy": [
      "tgn:2592779",
      "tgn:7006450",
      "tgn:1000001",
      "tgn:7012149",
      "tgn:2000089",
      "tgn:7029392"
    ],
    "placetype": [
      "aat:300008798"
    ],
    "id": 2592779,
    "name:xx": "Pope Creek Dome"
  }
}
