{
  "geometry": {
    "type": "Point",
    "coordinates": [
      -109.9167,
      40.4333
    ]
  },
  "type": "Feature",
  "properties": {
    "hierarchy": [
      "tgn:2288634",
      "tgn:1000001",
      "tgn:7012149",
      "tgn:2002124",
      "tgn:7007827",
      "tgn:7029392"
    ],
    "placetype": [
      "aat:300006075"
    ],
    "id": 2288634,
    "name:xx": "Ditch A"
  }
}
