{
  "geometry": {
    "type": "Point",
    "coordinates": [
      -78.7333,
      38.0667
    ]
  },
  "type": "Feature",
  "properties": {
    "hierarchy": [
      "tgn:2462774",
      "tgn:2002137",
      "tgn:1000001",
      "tgn:7012149",
      "tgn:7007919",
      "tgn:7029392"
    ],
    "placetype": [
      "aat:300008798"
    ],
    "id": 2462774,
    "name:xx": "Little Yellow Mountain"
  }
}
