{
  "geometry": {
    "type": "Point",
    "coordinates": [
      -79.6333,
      38.9167
    ]
  },
  "type": "Feature",
  "properties": {
    "hierarchy": [
      "tgn:2562117",
      "tgn:1000001",
      "tgn:7012149",
      "tgn:7013961",
      "tgn:7029392"
    ],
    "placetype": [
      "aat:300008706"
    ],
    "id": 2562117,
    "name:xx": "Otter Creek"
  }
}
