{
  "geometry": {
    "type": "Point",
    "coordinates": [
      -71.5667,
      42.4167
    ]
  },
  "type": "Feature",
  "properties": {
    "hierarchy": [
      "tgn:2761726",
      "tgn:1000001",
      "tgn:7012149",
      "tgn:1003038",
      "tgn:7007517",
      "tgn:7029392"
    ],
    "placetype": [
      "aat:300008680"
    ],
    "id": 2761726,
    "name:xx": "West Pond"
  }
}
