{
  "geometry": {
    "type": "Point",
    "coordinates": [
      -74.3833,
      41.9833
    ]
  },
  "type": "Feature",
  "properties": {
    "hierarchy": [
      "tgn:2282501",
      "tgn:1000001",
      "tgn:7012149",
      "tgn:1002961",
      "tgn:7007568",
      "tgn:7029392"
    ],
    "placetype": [
      "aat:300008699"
    ],
    "id": 2282501,
    "name:xx": "Deer Shanty Brook"
  }
}
