{
  "geometry": {
    "type": "Point",
    "coordinates": [
      -87.5333,
      40.0333
    ]
  },
  "type": "Feature",
  "properties": {
    "hierarchy": [
      "tgn:2765445",
      "tgn:1000001",
      "tgn:7012149",
      "tgn:1002974",
      "tgn:7007251",
      "tgn:7029392"
    ],
    "placetype": [
      "aat:300008699"
    ],
    "id": 2765445,
    "name:xx": "White Branch"
  }
}
