{
  "geometry": {
    "type": "Point",
    "coordinates": [
      -81.0333,
      34.0167
    ]
  },
  "type": "Feature",
  "properties": {
    "hierarchy": [
      "tgn:2210840",
      "tgn:1000001",
      "tgn:7012149",
      "tgn:2001764",
      "tgn:7007712",
      "tgn:7029392"
    ],
    "placetype": [
      "aat:300008347"
    ],
    "id": 2210840,
    "name:xx": "Butchertown"
  }
}
