{
  "type": "FeatureCollection",
  "features": [
    {
      "geometry": {
        "type": "Point",
        "coordinates": [
          -106.866667,
          28.783333
        ]
      },
      "type": "Feature",
      "properties": {
        "hierarchy": [
          "tgn:7377320",
          "tgn:7005581",
          "tgn:1000001",
          "tgn:7005560",
          "tgn:7029392"
        ],
        "placetype": [
          "aat:300008347"
        ],
        "id": 7377320,
        "name:xx": "La Union"
      }
    },
    {
      "geometry": {
        "type": "Point",
        "coordinates": [
          -107.066667,
          28.233333
        ]
      },
      "type": "Feature",
      "properties": {
        "hierarchy": [
          "tgn:7377321",
          "tgn:7005581",
          "tgn:1000001",
          "tgn:7005560",
          "tgn:7029392"
        ],
        "placetype": [
          "aat:300008347"
        ],
        "id": 7377321,
        "name:xx": "La Unión"
      }
    },
    {
      "geometry": {
        "type": "Point",
        "coordinates": [
          -109.6,
          26.816667
        ]
      },
      "type": "Feature",
      "properties": {
        "hierarchy": [
          "tgn:7377322",
          "tgn:1000001",
          "tgn:1001960",
          "tgn:7005560",
          "tgn:7029392"
        ],
        "placetype": [
          "aat:300008347"
        ],
        "id": 7377322,
        "name:xx": "La Unión"
      }
    },
    {
      "geometry": {
        "type": "Point",
        "coordinates": [
          -107.15,
          26.8
        ]
      },
      "type": "Feature",
      "properties": {
        "hierarchy": [
          "tgn:7377323",
          "tgn:7005581",
          "tgn:1000001",
          "tgn:7005560",
          "tgn:7029392"
        ],
        "placetype": [
          "aat:300008347"
        ],
        "id": 7377323,
        "name:xx": "La Unión"
      }
    },
    {
      "geometry": {
        "type": "Point",
        "coordinates": [
          -107.083333,
          25.9
        ]
      },
      "type": "Feature",
      "properties": {
        "hierarchy": [
          "tgn:7377324",
          "tgn:7005581",
          "tgn:1000001",
          "tgn:7005560",
          "tgn:7029392"
        ],
        "placetype": [
          "aat:300008347"
        ],
        "id": 7377324,
        "name:xx": "La Unión"
      }
    },
    {
      "geometry": {
        "type": "Point",
        "coordinates": [
          -97.533333,
          25.866667
        ]
      },
      "type": "Feature",
      "properties": {
        "hierarchy": [
          "tgn:7377325",
          "tgn:1000001",
          "tgn:7005597",
          "tgn:7005560",
          "tgn:7029392"
        ],
        "placetype": [
          "aat:300008347"
        ],
        "id": 7377325,
        "name:xx": "La Union"
      }
    },
    {
      "geometry": {
        "type": "Point",
        "coordinates": [
          -98.764167,
          25.763333
        ]
      },
      "type": "Feature",
      "properties": {
        "hierarchy": [
          "tgn:7377326",
          "tgn:1000001",
          "tgn:7005589",
          "tgn:7005560",
          "tgn:7029392"
        ],
        "placetype": [
          "aat:300008347"
        ],
        "id": 7377326,
        "name:es": "La Unión"
      }
    },
    {
      "geometry": {
        "type": "Point",
        "coordinates": [
          -97.583333,
          25.716667
        ]
      },
      "type": "Feature",
      "properties": {
        "hierarchy": [
          "tgn:7377327",
          "tgn:1000001",
          "tgn:7005597",
          "tgn:7005560",
          "tgn:7029392"
        ],
        "placetype": [
          "aat:300008347"
        ],
        "id": 7377327,
        "name:xx": "La Unión"
      }
    },
    {
      "geometry": {
        "type": "Point",
        "coordinates": [
          -103.4,
          25.6
        ]
      },
      "type": "Feature",
      "properties": {
        "hierarchy": [
          "tgn:7377328",
          "tgn:1001853",
          "tgn:1000001",
          "tgn:7005560",
          "tgn:7029392"
        ],
        "placetype": [
          "aat:300008347"
        ],
        "id": 7377328,
        "name:xx": "La Unión"
      }
    },
    {
      "geometry": {
        "type": "Point",
        "coordinates": [
          -99.95,
          25.383333
        ]
      },
      "type": "Feature",
      "properties": {
        "hierarchy": [
          "tgn:7377329",
          "tgn:1000001",
          "tgn:7005589",
          "tgn:7005560",
          "tgn:7029392"
        ],
        "placetype": [
          "aat:300008347"
        ],
        "id": 7377329,
        "name:xx": "La Unión"
      }
    }
  ]
}
