{
  "geometry": {
    "type": "Point",
    "coordinates": [
      22.5333,
      41.7667
    ]
  },
  "type": "Feature",
  "properties": {
    "hierarchy": [
      "tgn:1109486",
      "tgn:1000003",
      "tgn:7006667",
      "tgn:7029392"
    ],
    "placetype": [
      "aat:300008795"
    ],
    "id": 1109486,
    "name:xx": "Plackovica"
  }
}
