{
  "geometry": {
    "type": "Point",
    "coordinates": [
      -111.2667,
      46.0167
    ]
  },
  "type": "Feature",
  "properties": {
    "hierarchy": [
      "tgn:2401596",
      "tgn:1000001",
      "tgn:7012149",
      "tgn:2001275",
      "tgn:7007524",
      "tgn:7029392"
    ],
    "placetype": [
      "aat:300008697"
    ],
    "id": 2401596,
    "name:xx": "Horseshoe Hills"
  }
}
