{
  "geometry": {
    "type": "Point",
    "coordinates": [
      -97.9833,
      30.5167
    ]
  },
  "type": "Feature",
  "properties": {
    "hierarchy": [
      "tgn:2381192",
      "tgn:1000001",
      "tgn:7012149",
      "tgn:1002952",
      "tgn:7007826",
      "tgn:7029392"
    ],
    "placetype": [
      "aat:300008761"
    ],
    "id": 2381192,
    "name:xx": "Hawks Nest Hollow"
  }
}
