{
  "geometry": {
    "type": "Point",
    "coordinates": [
      -83.2333,
      35.8833
    ]
  },
  "type": "Feature",
  "properties": {
    "hierarchy": [
      "tgn:7022432",
      "tgn:1000001",
      "tgn:7012149",
      "tgn:7007825",
      "tgn:7029392"
    ],
    "placetype": [
      "aat:300008699"
    ],
    "id": 7022432,
    "name:xx": "Breeden Branch"
  }
}
