{
  "type": "FeatureCollection",
  "features": [
    {
      "geometry": {
        "type": "Point",
        "coordinates": [
          139.4833,
          35.3
        ]
      },
      "type": "Feature",
      "properties": {
        "hierarchy": [
          "tgn:1007040",
          "tgn:7016696",
          "tgn:1000004",
          "tgn:7000894",
          "tgn:1000120",
          "tgn:7029392"
        ],
        "placetype": [
          "aat:300008791"
        ],
        "id": 1007040,
        "name:xx": "Eno-shima"
      }
    },
    {
      "geometry": {
        "type": "Point",
        "coordinates": [
          -7.083333,
          57.766667
        ]
      },
      "type": "Feature",
      "properties": {
        "hierarchy": [
          "tgn:1007041",
          "tgn:7002444",
          "tgn:1000003",
          "tgn:7008094",
          "tgn:7008591",
          "tgn:7029392"
        ],
        "placetype": [
          "aat:300008791"
        ],
        "name:en": "Ensay",
        "id": 1007041
      }
    },
    {
      "geometry": {
        "type": "Point",
        "coordinates": [
          -61.7,
          47.3
        ]
      },
      "type": "Feature",
      "properties": {
        "hierarchy": [
          "tgn:1007042",
          "tgn:7005685",
          "tgn:1000001",
          "tgn:7005804",
          "tgn:1010122",
          "tgn:7029392"
        ],
        "placetype": [
          "aat:300008791"
        ],
        "id": 1007042,
        "name:xx": "Entrée, Île d'"
      }
    },
    {
      "geometry": {
        "type": "Point",
        "coordinates": [
          -7.3,
          57.066667
        ]
      },
      "type": "Feature",
      "properties": {
        "hierarchy": [
          "tgn:1007045",
          "tgn:7002444",
          "tgn:1000003",
          "tgn:7008094",
          "tgn:7008591",
          "tgn:7029392"
        ],
        "placetype": [
          "aat:300008791"
        ],
        "name:en": "Eriskay",
        "id": 1007045
      }
    },
    {
      "geometry": {
        "type": "Point",
        "coordinates": [
          169.0833,
          -18.75
        ]
      },
      "type": "Feature",
      "properties": {
        "hierarchy": [
          "tgn:1007046",
          "tgn:1002120",
          "tgn:1000225",
          "tgn:1000006",
          "tgn:7029392"
        ],
        "placetype": [
          "aat:300008791"
        ],
        "id": 1007046,
        "name:xx": "Erromango"
      }
    },
    {
      "geometry": {
        "type": "Point",
        "coordinates": [
          -81.5833,
          9.1
        ]
      },
      "type": "Feature",
      "properties": {
        "hierarchy": [
          "tgn:1007047",
          "tgn:7593354",
          "tgn:1000001",
          "tgn:7005565",
          "tgn:7029392"
        ],
        "placetype": [
          "aat:300008791"
        ],
        "id": 1007047,
        "name:xx": "Escudo de Veraguas, Isla"
      }
    },
    {
      "geometry": {
        "type": "Point",
        "coordinates": [
          -75.416667,
          -48.95
        ]
      },
      "type": "Feature",
      "properties": {
        "hierarchy": [
          "tgn:1007048",
          "tgn:1001702",
          "tgn:1000049",
          "tgn:1000002",
          "tgn:7029392"
        ],
        "placetype": [
          "aat:300008791"
        ],
        "id": 1007048,
        "name:xx": "Esmeralda, Isla"
      }
    }
  ]
}
