{
  "geometry": {
    "type": "Point",
    "coordinates": [
      30.391493,
      31.010424
    ]
  },
  "type": "Feature",
  "properties": {
    "hierarchy": [
      "tgn:7523422",
      "tgn:7001242",
      "tgn:1001075",
      "tgn:7016833",
      "tgn:7029392"
    ],
    "placetype": [
      "aat:300008347"
    ],
    "name:en": "Aş Şafāşīf",
    "id": 7523422
  }
}
