{
  "type": "FeatureCollection",
  "features": [
    {
      "geometry": {
        "type": "Point",
        "coordinates": [
          115,
          31.25
        ]
      },
      "type": "Feature",
      "properties": {
        "hierarchy": [
          "tgn:1108950",
          "tgn:1000004",
          "tgn:1000111",
          "tgn:7029392"
        ],
        "placetype": [
          "aat:300386831"
        ],
        "id": 1108950,
        "name:xx": "Dabie Shan"
      }
    },
    {
      "geometry": {
        "type": "Point",
        "coordinates": [
          1,
          36.4167
        ]
      },
      "type": "Feature",
      "properties": {
        "hierarchy": [
          "tgn:1108951",
          "tgn:7001242",
          "tgn:7016752",
          "tgn:1000596",
          "tgn:7029392"
        ],
        "placetype": [
          "aat:300008795"
        ],
        "id": 1108951,
        "name:xx": "Dahra"
      }
    },
    {
      "geometry": {
        "type": "Point",
        "coordinates": [
          103,
          28
        ]
      },
      "type": "Feature",
      "properties": {
        "hierarchy": [
          "tgn:1108952",
          "tgn:1000004",
          "tgn:7002087",
          "tgn:1000111",
          "tgn:7029392"
        ],
        "placetype": [
          "aat:300008795"
        ],
        "id": 1108952,
        "name:xx": "Daliang Shan"
      }
    },
    {
      "geometry": {
        "type": "Point",
        "coordinates": [
          -108,
          40.2333
        ]
      },
      "type": "Feature",
      "properties": {
        "hierarchy": [
          "tgn:1108953",
          "tgn:1000001",
          "tgn:7012149",
          "tgn:7007158",
          "tgn:7029392"
        ],
        "placetype": [
          "aat:300008795"
        ],
        "id": 1108953,
        "name:xx": "Danforth Hills"
      }
    },
    {
      "geometry": {
        "type": "Point",
        "coordinates": [
          95.8,
          38.9
        ]
      },
      "type": "Feature",
      "properties": {
        "hierarchy": [
          "tgn:1108954",
          "tgn:1000004",
          "tgn:1000111",
          "tgn:7029392"
        ],
        "placetype": [
          "aat:300386831"
        ],
        "id": 1108954,
        "name:xx": "Danghe Nanshan"
      }
    },
    {
      "geometry": {
        "type": "Point",
        "coordinates": [
          -77.3667,
          8.3333
        ]
      },
      "type": "Feature",
      "properties": {
        "hierarchy": [
          "tgn:1108955",
          "tgn:7029392"
        ],
        "placetype": [
          "aat:300386831"
        ],
        "id": 1108955,
        "name:xx": "Darién, Serranía del"
      }
    },
    {
      "geometry": {
        "type": "Point",
        "coordinates": [
          -85.5,
          12.9167
        ]
      },
      "type": "Feature",
      "properties": {
        "hierarchy": [
          "tgn:1108957",
          "tgn:1000001",
          "tgn:7005562",
          "tgn:7029392"
        ],
        "placetype": [
          "aat:300386831"
        ],
        "id": 1108957,
        "name:xx": "Dariense, Cordillera"
      }
    },
    {
      "geometry": {
        "type": "Point",
        "coordinates": [
          -70,
          -54.666667
        ]
      },
      "type": "Feature",
      "properties": {
        "hierarchy": [
          "tgn:1108958",
          "tgn:1001702",
          "tgn:1000049",
          "tgn:1000002",
          "tgn:7005114",
          "tgn:7029392"
        ],
        "placetype": [
          "aat:300386831",
          "aat:300008795"
        ],
        "id": 1108958,
        "name:xx": "Darwin, Cordillera"
      }
    },
    {
      "geometry": {
        "type": "Point",
        "coordinates": [
          99.5,
          38
        ]
      },
      "type": "Feature",
      "properties": {
        "hierarchy": [
          "tgn:1108959",
          "tgn:1000004",
          "tgn:7002088",
          "tgn:1000111",
          "tgn:7029392"
        ],
        "placetype": [
          "aat:300008795"
        ],
        "id": 1108959,
        "name:xx": "Datong Shan"
      }
    }
  ]
}
