{
  "geometry": {
    "type": "Point",
    "coordinates": [
      -111.7667,
      46.3833
    ]
  },
  "type": "Feature",
  "properties": {
    "hierarchy": [
      "tgn:2266287",
      "tgn:1000001",
      "tgn:7012149",
      "tgn:7007524",
      "tgn:7029392"
    ],
    "placetype": [
      "aat:300008706"
    ],
    "id": 2266287,
    "name:xx": "Crazy Creek"
  }
}
