{
  "geometry": {
    "type": "Point",
    "coordinates": [
      -83.4667,
      42.8167
    ]
  },
  "type": "Feature",
  "properties": {
    "hierarchy": [
      "tgn:2535473",
      "tgn:1000001",
      "tgn:7012149",
      "tgn:1002737",
      "tgn:7007520",
      "tgn:7029392"
    ],
    "placetype": [
      "aat:300008680"
    ],
    "id": 2535473,
    "name:xx": "Narrin Lake"
  }
}
