{
  "geometry": {
    "type": "Point",
    "coordinates": [
      -79.7833,
      35.8167
    ]
  },
  "type": "Feature",
  "properties": {
    "hierarchy": [
      "tgn:2278107",
      "tgn:1000001",
      "tgn:7012149",
      "tgn:2001532",
      "tgn:7007709",
      "tgn:7029392"
    ],
    "placetype": [
      "aat:300008347"
    ],
    "id": 2278107,
    "name:xx": "Dayspring"
  }
}
