{
  "geometry": {
    "type": "Point",
    "coordinates": [
      -7.658,
      39.198
    ]
  },
  "type": "Feature",
  "properties": {
    "hierarchy": [
      "tgn:1049685",
      "tgn:7003825",
      "tgn:1000003",
      "tgn:1000090",
      "tgn:7029392"
    ],
    "placetype": [
      "aat:300008347"
    ],
    "id": 1049685,
    "name:xx": "Alter do Chão"
  }
}
