{
  "geometry": {
    "type": "Point",
    "coordinates": [
      -75.7667,
      41.5333
    ]
  },
  "type": "Feature",
  "properties": {
    "hierarchy": [
      "tgn:2729877",
      "tgn:1000001",
      "tgn:7012149",
      "tgn:7007710",
      "tgn:7029392"
    ],
    "placetype": [
      "aat:300008699"
    ],
    "id": 2729877,
    "name:xx": "Trout Brook"
  }
}
