{
  "geometry": {
    "type": "Point",
    "coordinates": [
      17.25,
      47.666
    ]
  },
  "type": "Feature",
  "properties": {
    "hierarchy": [
      "tgn:7006350",
      "tgn:1000003",
      "tgn:7006278",
      "tgn:7029392"
    ],
    "placetype": [
      "aat:300387064",
      "aat:300000771"
    ],
    "id": 7006350,
    "name:xx": "Győr-Moson-Sopron"
  }
}
