{
  "geometry": {
    "type": "Point",
    "coordinates": [
      -86.75,
      32.9833
    ]
  },
  "type": "Feature",
  "properties": {
    "hierarchy": [
      "tgn:2242520",
      "tgn:7002659",
      "tgn:1000001",
      "tgn:2000010",
      "tgn:7012149",
      "tgn:7029392"
    ],
    "placetype": [
      "aat:300008706"
    ],
    "id": 2242520,
    "name:xx": "Clear Creek"
  }
}
