{
  "geometry": {
    "type": "Point",
    "coordinates": [
      -90.65,
      38.1167
    ]
  },
  "type": "Feature",
  "properties": {
    "hierarchy": [
      "tgn:2149253",
      "tgn:1000001",
      "tgn:7012149",
      "tgn:1002517",
      "tgn:7007523",
      "tgn:7029392"
    ],
    "placetype": [
      "aat:300008697"
    ],
    "id": 2149253,
    "name:xx": "Barrel Spring"
  }
}
