{
  "geometry": {
    "type": "Point",
    "coordinates": [
      -80.1667,
      38.25
    ]
  },
  "type": "Feature",
  "properties": {
    "hierarchy": [
      "tgn:2580714",
      "tgn:1000001",
      "tgn:7012149",
      "tgn:2002287",
      "tgn:7013961",
      "tgn:7029392"
    ],
    "placetype": [
      "aat:300008699"
    ],
    "id": 2580714,
    "name:xx": "Pigeon Run"
  }
}
