{
  "type": "FeatureCollection",
  "features": [
    {
      "geometry": {
        "type": "Point",
        "coordinates": [
          -2.65,
          52.45
        ]
      },
      "type": "Feature",
      "properties": {
        "hierarchy": [
          "tgn:7456461",
          "tgn:7002445",
          "tgn:1000003",
          "tgn:7012034",
          "tgn:7008591",
          "tgn:7029392"
        ],
        "placetype": [
          "aat:300008347"
        ],
        "name:en": "Clee Saint Margaret",
        "id": 7456461
      }
    },
    {
      "geometry": {
        "type": "Point",
        "coordinates": [
          -3.7,
          53.2
        ]
      },
      "type": "Feature",
      "properties": {
        "hierarchy": [
          "tgn:7456464",
          "tgn:7002443",
          "tgn:7026970",
          "tgn:1000003",
          "tgn:7008591",
          "tgn:7029392"
        ],
        "placetype": [
          "aat:300008699"
        ],
        "name:en": "Cledwen, Afon",
        "id": 7456464
      }
    },
    {
      "geometry": {
        "type": "Point",
        "coordinates": [
          -3.516667,
          54.5
        ]
      },
      "type": "Feature",
      "properties": {
        "hierarchy": [
          "tgn:7456467",
          "tgn:7002445",
          "tgn:1000003",
          "tgn:7008117",
          "tgn:7008591",
          "tgn:7029392"
        ],
        "placetype": [
          "aat:300008347"
        ],
        "name:en": "Cleator",
        "id": 7456467
      }
    },
    {
      "geometry": {
        "type": "Point",
        "coordinates": [
          -2.933333,
          59.3
        ]
      },
      "type": "Feature",
      "properties": {
        "hierarchy": [
          "tgn:7456468",
          "tgn:7002444",
          "tgn:1000003",
          "tgn:7009907",
          "tgn:7008591",
          "tgn:7029392"
        ],
        "placetype": [
          "aat:300132316"
        ],
        "name:en": "Cleat, Bay of",
        "id": 7456468
      }
    },
    {
      "geometry": {
        "type": "Point",
        "coordinates": [
          -1.6,
          54.516667
        ]
      },
      "type": "Feature",
      "properties": {
        "hierarchy": [
          "tgn:7456469",
          "tgn:7002445",
          "tgn:1000003",
          "tgn:7008166",
          "tgn:7008591",
          "tgn:7029392"
        ],
        "placetype": [
          "aat:300008347"
        ],
        "name:en": "Cleasby",
        "id": 7456469
      }
    }
  ]
}
