{
  "geometry": {
    "type": "Point",
    "coordinates": [
      33.72679,
      28.864837
    ]
  },
  "type": "Feature",
  "properties": {
    "hierarchy": [
      "tgn:7538144",
      "tgn:7001242",
      "tgn:7016833",
      "tgn:7001336",
      "tgn:7029392"
    ],
    "placetype": [
      "aat:300007544"
    ],
    "name:en": "Ash Shaykh Ghannām",
    "id": 7538144
  }
}
