{
  "geometry": {
    "type": "Point",
    "coordinates": [
      -117.5167,
      47.0333
    ]
  },
  "type": "Feature",
  "properties": {
    "hierarchy": [
      "tgn:2462139",
      "tgn:1000001",
      "tgn:7012149",
      "tgn:2002252",
      "tgn:7007920",
      "tgn:7029392"
    ],
    "placetype": [
      "aat:300008706"
    ],
    "id": 2462139,
    "name:xx": "Little Valley Creek"
  }
}
