{
  "type": "FeatureCollection",
  "features": [
    {
      "geometry": {
        "type": "Point",
        "coordinates": [
          -71.5,
          -32.916667
        ]
      },
      "type": "Feature",
      "properties": {
        "hierarchy": [
          "tgn:7291890",
          "tgn:1001768",
          "tgn:1000049",
          "tgn:1000002",
          "tgn:7029392"
        ],
        "placetype": [
          "aat:300000517"
        ],
        "id": 7291890,
        "name:xx": "Enap"
      }
    },
    {
      "geometry": {
        "type": "Point",
        "coordinates": [
          -68.983333,
          -20.7
        ]
      },
      "type": "Feature",
      "properties": {
        "hierarchy": [
          "tgn:7291891",
          "tgn:7002464",
          "tgn:1000049",
          "tgn:1000002",
          "tgn:7029392"
        ],
        "placetype": [
          "aat:300008795"
        ],
        "id": 7291891,
        "name:xx": "Empexa, Cerro"
      }
    },
    {
      "geometry": {
        "type": "Point",
        "coordinates": [
          -72.266667,
          -45.25
        ]
      },
      "type": "Feature",
      "properties": {
        "hierarchy": [
          "tgn:7291892",
          "tgn:1001623",
          "tgn:1000049",
          "tgn:1000002",
          "tgn:7029392"
        ],
        "placetype": [
          "aat:300008699"
        ],
        "id": 7291892,
        "name:xx": "Emperador Guillermo, Río"
      }
    },
    {
      "geometry": {
        "type": "Point",
        "coordinates": [
          -72.466667,
          -35.633333
        ]
      },
      "type": "Feature",
      "properties": {
        "hierarchy": [
          "tgn:7291894",
          "tgn:1001705",
          "tgn:1000049",
          "tgn:1000002",
          "tgn:7029392"
        ],
        "placetype": [
          "aat:300008699"
        ],
        "id": 7291894,
        "name:xx": "Empedrado, Estero"
      }
    },
    {
      "geometry": {
        "type": "Point",
        "coordinates": [
          -73.95,
          -45.466667
        ]
      },
      "type": "Feature",
      "properties": {
        "hierarchy": [
          "tgn:7291895",
          "tgn:1001623",
          "tgn:1000049",
          "tgn:1000002",
          "tgn:7029392"
        ],
        "placetype": [
          "aat:300008676"
        ],
        "id": 7291895,
        "name:xx": "Empedrado, Estero"
      }
    },
    {
      "geometry": {
        "type": "Point",
        "coordinates": [
          -72.283333,
          -35.6
        ]
      },
      "type": "Feature",
      "properties": {
        "hierarchy": [
          "tgn:7291896",
          "tgn:1001705",
          "tgn:1000049",
          "tgn:1000002",
          "tgn:7029392"
        ],
        "placetype": [
          "aat:300008347"
        ],
        "id": 7291896,
        "name:xx": "Empedrado"
      }
    },
    {
      "geometry": {
        "type": "Point",
        "coordinates": [
          -70.133333,
          -26.416667
        ]
      },
      "type": "Feature",
      "properties": {
        "hierarchy": [
          "tgn:7291897",
          "tgn:1001630",
          "tgn:1000049",
          "tgn:1000002",
          "tgn:7029392"
        ],
        "placetype": [
          "aat:300007783"
        ],
        "id": 7291897,
        "name:xx": "Empalme"
      }
    },
    {
      "geometry": {
        "type": "Point",
        "coordinates": [
          -69.616667,
          -20.7
        ]
      },
      "type": "Feature",
      "properties": {
        "hierarchy": [
          "tgn:7291898",
          "tgn:7002464",
          "tgn:1000049",
          "tgn:1000002",
          "tgn:7029392"
        ],
        "placetype": [
          "aat:300007783"
        ],
        "id": 7291898,
        "name:xx": "Empalme"
      }
    },
    {
      "geometry": {
        "type": "Point",
        "coordinates": [
          -69.6,
          -20.7
        ]
      },
      "type": "Feature",
      "properties": {
        "hierarchy": [
          "tgn:7291899",
          "tgn:7002464",
          "tgn:1000049",
          "tgn:1000002",
          "tgn:7029392"
        ],
        "placetype": [
          "aat:300000517"
        ],
        "id": 7291899,
        "name:xx": "Empalme"
      }
    }
  ]
}
