{
  "type": "FeatureCollection",
  "features": [
    {
      "geometry": {
        "type": "Point",
        "coordinates": [
          12.083333,
          42.216667
        ]
      },
      "type": "Feature",
      "properties": {
        "hierarchy": [
          "tgn:5002470",
          "tgn:7003139",
          "tgn:1000003",
          "tgn:7003080",
          "tgn:1000080",
          "tgn:7029392"
        ],
        "placetype": [
          "aat:300008347"
        ],
        "id": 5002470,
        "name:xx": "Vejano"
      }
    },
    {
      "geometry": {
        "type": "Point",
        "coordinates": [
          8.866667,
          44.416667
        ]
      },
      "type": "Feature",
      "properties": {
        "hierarchy": [
          "tgn:5002474",
          "tgn:1000003",
          "tgn:7003142",
          "tgn:7003236",
          "tgn:1000080",
          "tgn:7029392"
        ],
        "placetype": [
          "aat:300008347",
          "aat:300000745"
        ],
        "id": 5002474,
        "name:xx": "San Pier d'Arena"
      }
    },
    {
      "geometry": {
        "type": "Point",
        "coordinates": [
          9.183333,
          44.333333
        ]
      },
      "type": "Feature",
      "properties": {
        "hierarchy": [
          "tgn:5002478",
          "tgn:1000003",
          "tgn:7003142",
          "tgn:7003236",
          "tgn:1000080",
          "tgn:7029392"
        ],
        "placetype": [
          "aat:300008347"
        ],
        "id": 5002478,
        "name:xx": "San Lorenzo della Costa"
      }
    }
  ]
}
