{
  "geometry": {
    "type": "Point",
    "coordinates": [
      -105.35,
      39.9167
    ]
  },
  "type": "Feature",
  "properties": {
    "hierarchy": [
      "tgn:2245806",
      "tgn:1000001",
      "tgn:7012149",
      "tgn:7007158",
      "tgn:7029392"
    ],
    "placetype": [
      "aat:300008761"
    ],
    "id": 2245806,
    "name:xx": "Coal Creek Canyon"
  }
}
