{
  "geometry": {
    "type": "Point",
    "coordinates": [
      -77.3333,
      5.75
    ]
  },
  "type": "Feature",
  "properties": {
    "hierarchy": [
      "tgn:1112492",
      "tgn:7016640",
      "tgn:1000050",
      "tgn:1000002",
      "tgn:7029392"
    ],
    "placetype": [
      "aat:300132315"
    ],
    "id": 1112492,
    "name:xx": "Tribugá, Golfo de"
  }
}
