{
  "geometry": {
    "type": "Point",
    "coordinates": [
      -112.55,
      40.2167
    ]
  },
  "type": "Feature",
  "properties": {
    "hierarchy": [
      "tgn:2305976",
      "tgn:1000001",
      "tgn:7012149",
      "tgn:2002123",
      "tgn:7007827",
      "tgn:7029392"
    ],
    "placetype": [
      "aat:300008706"
    ],
    "id": 2305976,
    "name:xx": "East Faust Creek"
  }
}
