{
  "geometry": {
    "type": "Point",
    "coordinates": [
      -99.9167,
      34.1167
    ]
  },
  "type": "Feature",
  "properties": {
    "hierarchy": [
      "tgn:2228558",
      "tgn:1000001",
      "tgn:7012149",
      "tgn:2001986",
      "tgn:7007826",
      "tgn:7029392"
    ],
    "placetype": [
      "aat:300008706"
    ],
    "id": 2228558,
    "name:xx": "Cedar Creek"
  }
}
