{
  "geometry": {
    "type": "Point",
    "coordinates": [
      -98.35,
      31.5333
    ]
  },
  "type": "Feature",
  "properties": {
    "hierarchy": [
      "tgn:2279548",
      "tgn:1000001",
      "tgn:7012149",
      "tgn:2001996",
      "tgn:7007826",
      "tgn:7029392"
    ],
    "placetype": [
      "aat:300008798"
    ],
    "id": 2279548,
    "name:xx": "Deadman Mountain"
  }
}
