{
  "geometry": {
    "type": "Point",
    "coordinates": [
      -96.2833,
      29.8167
    ]
  },
  "type": "Feature",
  "properties": {
    "hierarchy": [
      "tgn:2267854",
      "tgn:1000001",
      "tgn:1002161",
      "tgn:7012149",
      "tgn:7007826",
      "tgn:7029392"
    ],
    "placetype": [
      "aat:300008699"
    ],
    "id": 2267854,
    "name:xx": "Crooked Branch"
  }
}
