{
  "geometry": {
    "type": "Point",
    "coordinates": [
      42.2833,
      2.3667
    ]
  },
  "type": "Feature",
  "properties": {
    "hierarchy": [
      "tgn:1092761",
      "tgn:7001242",
      "tgn:1001676",
      "tgn:1000192",
      "tgn:7029392"
    ],
    "placetype": [
      "aat:300008347"
    ],
    "id": 1092761,
    "name:xx": "Saránley"
  }
}
