{
  "geometry": {
    "type": "Point",
    "coordinates": [
      -108.4167,
      33.3667
    ]
  },
  "type": "Feature",
  "properties": {
    "hierarchy": [
      "tgn:2126527",
      "tgn:1000001",
      "tgn:2001429",
      "tgn:7012149",
      "tgn:7007566",
      "tgn:7029392"
    ],
    "placetype": [
      "aat:300008798"
    ],
    "id": 2126527,
    "name:xx": "Aeroplane Mesa"
  }
}
