{
  "geometry": {
    "type": "Point",
    "coordinates": [
      -97.4167,
      35.95
    ]
  },
  "type": "Feature",
  "properties": {
    "hierarchy": [
      "tgn:2485355",
      "tgn:1000001",
      "tgn:7012149",
      "tgn:2001664",
      "tgn:7007707",
      "tgn:7029392"
    ],
    "placetype": [
      "aat:300008347"
    ],
    "id": 2485355,
    "name:xx": "Lawrie"
  }
}
