{
  "geometry": {
    "type": "Point",
    "coordinates": [
      -110.5833,
      36.9833
    ]
  },
  "type": "Feature",
  "properties": {
    "hierarchy": [
      "tgn:2538495",
      "tgn:1000001",
      "tgn:7012149",
      "tgn:7029392"
    ],
    "placetype": [
      "aat:300008699"
    ],
    "id": 2538495,
    "name:xx": "Neskahi Wash"
  }
}
