{
  "geometry": {
    "type": "Point",
    "coordinates": [
      -92.7667,
      38.0667
    ]
  },
  "type": "Feature",
  "properties": {
    "hierarchy": [
      "tgn:2446831",
      "tgn:1000001",
      "tgn:2001178",
      "tgn:7012149",
      "tgn:7007523",
      "tgn:7029392"
    ],
    "placetype": [
      "aat:300132316"
    ],
    "id": 2446831,
    "name:xx": "Libby Cove"
  }
}
