{
  "geometry": {
    "type": "Point",
    "coordinates": [
      -87.3333,
      33.2333
    ]
  },
  "type": "Feature",
  "properties": {
    "hierarchy": [
      "tgn:2587603",
      "tgn:7002659",
      "tgn:1000001",
      "tgn:7012149",
      "tgn:2000062",
      "tgn:7029392"
    ],
    "placetype": [
      "aat:300266640"
    ],
    "id": 2587603,
    "name:xx": "Pleasant Ridge"
  }
}
