{
  "geometry": {
    "type": "Point",
    "coordinates": [
      45.5833,
      53.1167
    ]
  },
  "type": "Feature",
  "properties": {
    "hierarchy": [
      "tgn:1137613",
      "tgn:1000004",
      "tgn:1003399",
      "tgn:7018214",
      "tgn:7002435",
      "tgn:7029392"
    ],
    "placetype": [
      "aat:300008347"
    ],
    "id": 1137613,
    "name:xx": "Kanayevka"
  }
}
