{
  "geometry": {
    "type": "Point",
    "coordinates": [
      -90.0833,
      35.3833
    ]
  },
  "type": "Feature",
  "properties": {
    "hierarchy": [
      "tgn:2257439",
      "tgn:1000001",
      "tgn:7012149",
      "tgn:2001920",
      "tgn:7007825",
      "tgn:7029392"
    ],
    "placetype": [
      "aat:300132348"
    ],
    "id": 2257439,
    "name:xx": "Corona Bar"
  }
}
