{
  "geometry": {
    "type": "Point",
    "coordinates": [
      -102.116667,
      18.6625
    ]
  },
  "type": "Feature",
  "properties": {
    "hierarchy": [
      "tgn:7410174",
      "tgn:1000001",
      "tgn:7005590",
      "tgn:7005560",
      "tgn:7029392"
    ],
    "placetype": [
      "aat:300008347"
    ],
    "id": 7410174,
    "name:xx": "La Fundición"
  }
}
