{
  "geometry": {
    "type": "Point",
    "coordinates": [
      -116.3667,
      38.5167
    ]
  },
  "type": "Feature",
  "properties": {
    "hierarchy": [
      "tgn:2740130",
      "tgn:1000001",
      "tgn:2001418",
      "tgn:7012149",
      "tgn:7007526",
      "tgn:7029392"
    ],
    "placetype": [
      "aat:300008697"
    ],
    "id": 2740130,
    "name:xx": "Upper Hot Creek Ranch Spring"
  }
}
