{
  "geometry": {
    "type": "Point",
    "coordinates": [
      -95.75,
      31.5667
    ]
  },
  "type": "Feature",
  "properties": {
    "hierarchy": [
      "tgn:2267256",
      "tgn:1000001",
      "tgn:7012149",
      "tgn:1002590",
      "tgn:7007826",
      "tgn:7029392"
    ],
    "placetype": [
      "aat:300008680"
    ],
    "id": 2267256,
    "name:xx": "Criminal Lake"
  }
}
