{
  "geometry": {
    "type": "Point",
    "coordinates": [
      -118.65,
      48.7167
    ]
  },
  "type": "Feature",
  "properties": {
    "hierarchy": [
      "tgn:2116516",
      "tgn:1000001",
      "tgn:2002243",
      "tgn:7012149",
      "tgn:7007920",
      "tgn:7029392"
    ],
    "placetype": [
      "aat:300387016"
    ],
    "id": 2116516,
    "name:xx": "Pollard"
  }
}
