{
  "type": "FeatureCollection",
  "features": [
    {
      "geometry": {
        "type": "Point",
        "coordinates": [
          5.9,
          51.75
        ]
      },
      "type": "Feature",
      "properties": {
        "hierarchy": [
          "tgn:7267590",
          "tgn:1000003",
          "tgn:7003622",
          "tgn:7016845",
          "tgn:7029392"
        ],
        "placetype": [
          "aat:300008777"
        ],
        "name:nl": "Oostberg",
        "id": 7267590
      }
    },
    {
      "geometry": {
        "type": "Point",
        "coordinates": [
          4.983333,
          52.566667
        ]
      },
      "type": "Feature",
      "properties": {
        "hierarchy": [
          "tgn:7267591",
          "tgn:1000003",
          "tgn:7006951",
          "tgn:7016845",
          "tgn:7029392"
        ],
        "placetype": [
          "aat:300008347"
        ],
        "name:nl": "Oostbeemster",
        "id": 7267591
      }
    },
    {
      "geometry": {
        "type": "Point",
        "coordinates": [
          5.716667,
          51.433333
        ]
      },
      "type": "Feature",
      "properties": {
        "hierarchy": [
          "tgn:7267592",
          "tgn:1000003",
          "tgn:7003624",
          "tgn:7016845",
          "tgn:7029392"
        ],
        "placetype": [
          "aat:300008347"
        ],
        "name:nl": "Oostappen",
        "id": 7267592
      }
    },
    {
      "geometry": {
        "type": "Point",
        "coordinates": [
          7,
          53.216667
        ]
      },
      "type": "Feature",
      "properties": {
        "hierarchy": [
          "tgn:7267593",
          "tgn:1000003",
          "tgn:7003613",
          "tgn:7016845",
          "tgn:7029392"
        ],
        "placetype": [
          "aat:300387200"
        ],
        "name:nl": "Nieuwland",
        "id": 7267593
      }
    },
    {
      "geometry": {
        "type": "Point",
        "coordinates": [
          5.2,
          51.7
        ]
      },
      "type": "Feature",
      "properties": {
        "hierarchy": [
          "tgn:7267594",
          "tgn:1000003",
          "tgn:7003624",
          "tgn:7016845",
          "tgn:7029392"
        ],
        "placetype": [
          "aat:300008347"
        ],
        "name:nl": "Nieuwkuijk",
        "id": 7267594
      }
    },
    {
      "geometry": {
        "type": "Point",
        "coordinates": [
          5.6,
          53.216667
        ]
      },
      "type": "Feature",
      "properties": {
        "hierarchy": [
          "tgn:7267595",
          "tgn:7003616",
          "tgn:1000003",
          "tgn:7016845",
          "tgn:7029392"
        ],
        "placetype": [
          "aat:300008347"
        ],
        "name:nl": "Ried",
        "id": 7267595
      }
    },
    {
      "geometry": {
        "type": "Point",
        "coordinates": [
          5.616667,
          53.233333
        ]
      },
      "type": "Feature",
      "properties": {
        "hierarchy": [
          "tgn:7267596",
          "tgn:7003616",
          "tgn:1000003",
          "tgn:7016845",
          "tgn:7029392"
        ],
        "placetype": [
          "aat:300006075"
        ],
        "name:nl": "Ried",
        "id": 7267596
      }
    },
    {
      "geometry": {
        "type": "Point",
        "coordinates": [
          5.216667,
          52.166667
        ]
      },
      "type": "Feature",
      "properties": {
        "hierarchy": [
          "tgn:7267597",
          "tgn:1000003",
          "tgn:7003627",
          "tgn:7016845",
          "tgn:7029392"
        ],
        "placetype": [
          "aat:300008863"
        ],
        "name:nl": "Ridderoordse Bossen",
        "id": 7267597
      }
    }
  ]
}
