{
  "geometry": {
    "type": "Point",
    "coordinates": [
      -9.1667,
      5.6667
    ]
  },
  "type": "Feature",
  "properties": {
    "hierarchy": [
      "tgn:1122639",
      "tgn:7001242",
      "tgn:1000171",
      "tgn:7029392"
    ],
    "placetype": [
      "aat:300008707"
    ],
    "id": 1122639,
    "name:xx": "Cestos"
  }
}
