{
  "geometry": {
    "type": "Point",
    "coordinates": [
      -106.9167,
      43.15
    ]
  },
  "type": "Feature",
  "properties": {
    "hierarchy": [
      "tgn:2227160",
      "tgn:1000001",
      "tgn:7012149",
      "tgn:2002377",
      "tgn:7007923",
      "tgn:7029392"
    ],
    "placetype": [
      "aat:300006191"
    ],
    "id": 2227160,
    "name:xx": "Cave Gulch Reservoir"
  }
}
