{
  "geometry": {
    "type": "Point",
    "coordinates": [
      -83.65,
      32.5833
    ]
  },
  "type": "Feature",
  "properties": {
    "hierarchy": [
      "tgn:2403514",
      "tgn:1000001",
      "tgn:7012149",
      "tgn:2000367",
      "tgn:7007248",
      "tgn:7029392"
    ],
    "placetype": [
      "aat:300008699"
    ],
    "id": 2403514,
    "name:xx": "Howard Branch"
  }
}
