{
  "geometry": {
    "type": "Point",
    "coordinates": [
      -91.5333,
      44.35
    ]
  },
  "type": "Feature",
  "properties": {
    "hierarchy": [
      "tgn:2769324",
      "tgn:1000001",
      "tgn:7012149",
      "tgn:7007922",
      "tgn:7029392"
    ],
    "placetype": [
      "aat:300008761"
    ],
    "id": 2769324,
    "name:xx": "Wickham Valley"
  }
}
