{
  "geometry": {
    "type": "Point",
    "coordinates": [
      -81.65,
      36.3167
    ]
  },
  "type": "Feature",
  "properties": {
    "hierarchy": [
      "tgn:2467642",
      "tgn:1000001",
      "tgn:7012149",
      "tgn:7007709",
      "tgn:7029392"
    ],
    "placetype": [
      "aat:300008706"
    ],
    "id": 2467642,
    "name:xx": "Long Hope Creek"
  }
}
