{
  "geometry": {
    "type": "Point",
    "coordinates": [
      -106.0667,
      44.05
    ]
  },
  "type": "Feature",
  "properties": {
    "hierarchy": [
      "tgn:2271332",
      "tgn:1000001",
      "tgn:7012149",
      "tgn:2002374",
      "tgn:7007923",
      "tgn:7029392"
    ],
    "placetype": [
      "aat:300008761"
    ],
    "id": 2271332,
    "name:xx": "Culp Draw"
  }
}
