{
  "geometry": {
    "type": "Point",
    "coordinates": [
      -104.2667,
      44.9167
    ]
  },
  "type": "Feature",
  "properties": {
    "hierarchy": [
      "tgn:2540044",
      "tgn:1000001",
      "tgn:2002370",
      "tgn:7012149",
      "tgn:7007923",
      "tgn:7029392"
    ],
    "placetype": [
      "aat:300006191"
    ],
    "id": 2540044,
    "name:xx": "Newby Creek Reservoir"
  }
}
