{
  "geometry": {
    "type": "Point",
    "coordinates": [
      -159.9167,
      56.1833
    ]
  },
  "type": "Feature",
  "properties": {
    "hierarchy": [
      "tgn:2304701",
      "tgn:7030515",
      "tgn:7006450",
      "tgn:1000001",
      "tgn:7012149",
      "tgn:7029392"
    ],
    "placetype": [
      "aat:300132316"
    ],
    "id": 2304701,
    "name:xx": "East Bight"
  }
}
