{
  "geometry": {
    "type": "Point",
    "coordinates": [
      122.3667,
      40.7667
    ]
  },
  "type": "Feature",
  "properties": {
    "hierarchy": [
      "tgn:1067354",
      "tgn:1000004",
      "tgn:1001390",
      "tgn:1000111",
      "tgn:7029392"
    ],
    "placetype": [
      "aat:300008347"
    ],
    "id": 1067354,
    "name:xx": "Dagaokan"
  }
}
