{
  "geometry": {
    "type": "Point",
    "coordinates": [
      -100.4833,
      32.25
    ]
  },
  "type": "Feature",
  "properties": {
    "hierarchy": [
      "tgn:1134756",
      "tgn:1000001",
      "tgn:7012149",
      "tgn:7007826",
      "tgn:7029392"
    ],
    "placetype": [
      "aat:300008706"
    ],
    "id": 1134756,
    "name:xx": "Sweetwater Creek"
  }
}
