{
  "geometry": {
    "type": "Point",
    "coordinates": [
      16.25,
      50.9167
    ]
  },
  "type": "Feature",
  "properties": {
    "hierarchy": [
      "tgn:6002572",
      "tgn:7024123",
      "tgn:1000003",
      "tgn:7006366",
      "tgn:7029392"
    ],
    "placetype": [
      "aat:300008347",
      "aat:300000835",
      "aat:300008375"
    ],
    "id": 6002572,
    "name:xx": "DaÌœbromierz"
  }
}
