{
  "type": "FeatureCollection",
  "features": [
    {
      "geometry": {
        "type": "Point",
        "coordinates": [
          -1.35,
          60
        ]
      },
      "type": "Feature",
      "properties": {
        "hierarchy": [
          "tgn:7461971",
          "tgn:7002444",
          "tgn:1000003",
          "tgn:7029508",
          "tgn:7008591",
          "tgn:7029392"
        ],
        "placetype": [
          "aat:300008850"
        ],
        "name:en": "Ireland, Ness of",
        "id": 7461971
      }
    },
    {
      "geometry": {
        "type": "Point",
        "coordinates": [
          -3.25,
          58.966667
        ]
      },
      "type": "Feature",
      "properties": {
        "hierarchy": [
          "tgn:7461972",
          "tgn:7002444",
          "tgn:1000003",
          "tgn:7009907",
          "tgn:7008591",
          "tgn:7029392"
        ],
        "placetype": [
          "aat:300132316"
        ],
        "name:en": "Ireland, Bay of",
        "id": 7461972
      }
    },
    {
      "geometry": {
        "type": "Point",
        "coordinates": [
          -8,
          53.333333
        ]
      },
      "type": "Feature",
      "properties": {
        "hierarchy": [
          "tgn:7461973",
          "tgn:7002448",
          "tgn:7008700",
          "tgn:1000003",
          "tgn:7008591",
          "tgn:7029392"
        ],
        "placetype": [
          "aat:300008791"
        ],
        "name:en": "Ireland",
        "id": 7461973
      }
    },
    {
      "geometry": {
        "type": "Point",
        "coordinates": [
          -3.183333,
          54.733333
        ]
      },
      "type": "Feature",
      "properties": {
        "hierarchy": [
          "tgn:7461974",
          "tgn:7002445",
          "tgn:1000003",
          "tgn:7008117",
          "tgn:7008591",
          "tgn:7029392"
        ],
        "placetype": [
          "aat:300008347"
        ],
        "name:en": "Ireby",
        "id": 7461974
      }
    },
    {
      "geometry": {
        "type": "Point",
        "coordinates": [
          -2.616667,
          59.3
        ]
      },
      "type": "Feature",
      "properties": {
        "hierarchy": [
          "tgn:7461975",
          "tgn:7002444",
          "tgn:1000003",
          "tgn:7009907",
          "tgn:7008591",
          "tgn:7029392"
        ],
        "placetype": [
          "aat:300008791"
        ],
        "name:en": "Ire, Holms of",
        "id": 7461975
      }
    },
    {
      "geometry": {
        "type": "Point",
        "coordinates": [
          -1.966667,
          53.033333
        ]
      },
      "type": "Feature",
      "properties": {
        "hierarchy": [
          "tgn:7461979",
          "tgn:7002445",
          "tgn:1000003",
          "tgn:7008174",
          "tgn:7008591",
          "tgn:7029392"
        ],
        "placetype": [
          "aat:300008347"
        ],
        "name:en": "Ipstones",
        "id": 7461979
      }
    }
  ]
}
