{
  "geometry": {
    "type": "Point",
    "coordinates": [
      -112.45,
      43.0667
    ]
  },
  "type": "Feature",
  "properties": {
    "hierarchy": [
      "tgn:2354176",
      "tgn:1000001",
      "tgn:2000457",
      "tgn:7012149",
      "tgn:7007250",
      "tgn:7029392"
    ],
    "placetype": [
      "aat:300006075"
    ],
    "id": 2354176,
    "name:xx": "Golden Lateral"
  }
}
