{
  "geometry": {
    "type": "Point",
    "coordinates": [
      -83.85,
      33.9333
    ]
  },
  "type": "Feature",
  "properties": {
    "hierarchy": [
      "tgn:2228287",
      "tgn:1000001",
      "tgn:7012149",
      "tgn:7007248",
      "tgn:7029392"
    ],
    "placetype": [
      "aat:300008706"
    ],
    "id": 2228287,
    "name:xx": "Cedar Creek"
  }
}
