{
  "geometry": {
    "type": "Point",
    "coordinates": [
      -68.6167,
      43.9833
    ]
  },
  "type": "Feature",
  "properties": {
    "hierarchy": [
      "tgn:2621398",
      "tgn:1000001",
      "tgn:2000924",
      "tgn:7012149",
      "tgn:7007515",
      "tgn:7029392"
    ],
    "placetype": [
      "aat:300132348"
    ],
    "id": 2621398,
    "name:xx": "Roaring Bull Ledge"
  }
}
