{
  "geometry": {
    "type": "Point",
    "coordinates": [
      -96.15,
      36.5167
    ]
  },
  "type": "Feature",
  "properties": {
    "hierarchy": [
      "tgn:2349543",
      "tgn:1000001",
      "tgn:7012149",
      "tgn:2001679",
      "tgn:7007707",
      "tgn:7029392"
    ],
    "placetype": [
      "aat:300008347"
    ],
    "id": 2349543,
    "name:xx": "Gilland"
  }
}
