{
  "type": "FeatureCollection",
  "features": [
    {
      "geometry": {
        "type": "Point",
        "coordinates": [
          31.150336,
          27.222328
        ]
      },
      "type": "Feature",
      "properties": {
        "hierarchy": [
          "tgn:7521411",
          "tgn:7001242",
          "tgn:7016833",
          "tgn:1001114",
          "tgn:7029392"
        ],
        "placetype": [
          "aat:300008347"
        ],
        "name:en": "Al Akrād wa Banī Zayd",
        "id": 7521411
      }
    },
    {
      "geometry": {
        "type": "Point",
        "coordinates": [
          31.764425,
          30.682789
        ]
      },
      "type": "Feature",
      "properties": {
        "hierarchy": [
          "tgn:7521412",
          "tgn:7001242",
          "tgn:7016833",
          "tgn:1001113",
          "tgn:7029392"
        ],
        "placetype": [
          "aat:300008347"
        ],
        "id": 7521412,
        "name:xx": "Al Akhmīyīn"
      }
    },
    {
      "geometry": {
        "type": "Point",
        "coordinates": [
          31.170393,
          30.169654
        ]
      },
      "type": "Feature",
      "properties": {
        "hierarchy": [
          "tgn:7521413",
          "tgn:7001242",
          "tgn:7016833",
          "tgn:1001092",
          "tgn:7029392"
        ],
        "placetype": [
          "aat:300008347"
        ],
        "id": 7521413,
        "name:xx": "Al Akhmīyīn"
      }
    },
    {
      "geometry": {
        "type": "Point",
        "coordinates": [
          30.758618,
          31.160169
        ]
      },
      "type": "Feature",
      "properties": {
        "hierarchy": [
          "tgn:7521414",
          "tgn:7001242",
          "tgn:7016833",
          "tgn:1001335",
          "tgn:7029392"
        ],
        "placetype": [
          "aat:300008347"
        ],
        "name:en": "Al 'Ajūzayn",
        "id": 7521414
      }
    },
    {
      "geometry": {
        "type": "Point",
        "coordinates": [
          31.210905,
          30.050609
        ]
      },
      "type": "Feature",
      "properties": {
        "hierarchy": [
          "tgn:7521415",
          "tgn:7001242",
          "tgn:7016833",
          "tgn:1001083",
          "tgn:7029392"
        ],
        "placetype": [
          "aat:300008347"
        ],
        "id": 7521415,
        "name:xx": "Al 'Ajūzah"
      }
    },
    {
      "geometry": {
        "type": "Point",
        "coordinates": [
          31.9,
          31.466667
        ]
      },
      "type": "Feature",
      "properties": {
        "hierarchy": [
          "tgn:7521416",
          "tgn:7001242",
          "tgn:7016833",
          "tgn:1001225",
          "tgn:7029392"
        ],
        "placetype": [
          "aat:300008791"
        ],
        "name:en": "Al 'Ajūz",
        "id": 7521416
      }
    },
    {
      "geometry": {
        "type": "Point",
        "coordinates": [
          34.422778,
          30.185833
        ]
      },
      "type": "Feature",
      "properties": {
        "hierarchy": [
          "tgn:7521417",
          "tgn:7001242",
          "tgn:7016833",
          "tgn:7001335",
          "tgn:7029392"
        ],
        "placetype": [
          "aat:300006207"
        ],
        "id": 7521417,
        "name:xx": "Al 'Ajrūd"
      }
    },
    {
      "geometry": {
        "type": "Point",
        "coordinates": [
          32.383333,
          30.066667
        ]
      },
      "type": "Feature",
      "properties": {
        "hierarchy": [
          "tgn:7521418",
          "tgn:7001242",
          "tgn:7016833",
          "tgn:1001110",
          "tgn:7029392"
        ],
        "placetype": [
          "aat:300008057"
        ],
        "name:en": "Al 'Ajrūd",
        "id": 7521418
      }
    },
    {
      "geometry": {
        "type": "Point",
        "coordinates": [
          28.397327,
          30.818912
        ]
      },
      "type": "Feature",
      "properties": {
        "hierarchy": [
          "tgn:7521419",
          "tgn:7001242",
          "tgn:7016833",
          "tgn:1001418",
          "tgn:7029392"
        ],
        "placetype": [
          "aat:300008777"
        ],
        "name:en": "Al 'Ajramīyah",
        "id": 7521419
      }
    }
  ]
}
