{
  "geometry": {
    "type": "Point",
    "coordinates": [
      55.7333,
      29.4667
    ]
  },
  "type": "Feature",
  "properties": {
    "hierarchy": [
      "tgn:6005494",
      "tgn:1000004",
      "tgn:1001352",
      "tgn:7000231",
      "tgn:7029392"
    ],
    "placetype": [
      "aat:300008347",
      "aat:300008375"
    ],
    "id": 6005494,
    "name:xx": "Sirjan"
  }
}
