{
  "geometry": {
    "type": "Point",
    "coordinates": [
      85.811341,
      21.76385
    ]
  },
  "type": "Feature",
  "properties": {
    "hierarchy": [
      "tgn:7556195",
      "tgn:1000004",
      "tgn:7000198",
      "tgn:7016694",
      "tgn:7029392"
    ],
    "placetype": [
      "aat:300008347"
    ],
    "name:en": "Rājnagar",
    "id": 7556195
  }
}
