{
  "geometry": {
    "type": "Point",
    "coordinates": [
      119.1667,
      39.3333
    ]
  },
  "type": "Feature",
  "properties": {
    "hierarchy": [
      "tgn:1126417",
      "tgn:1000004",
      "tgn:7002077",
      "tgn:1000111",
      "tgn:7029392"
    ],
    "placetype": [
      "aat:300008707"
    ],
    "id": 1126417,
    "name:xx": "Luan"
  }
}
