{
  "geometry": {
    "type": "Point",
    "coordinates": [
      -75.0667,
      40.8333
    ]
  },
  "type": "Feature",
  "properties": {
    "hierarchy": [
      "tgn:2478292",
      "tgn:1000001",
      "tgn:1002985",
      "tgn:7012149",
      "tgn:7007565",
      "tgn:7029392"
    ],
    "placetype": [
      "aat:300008791"
    ],
    "id": 2478292,
    "name:xx": "Macks Island"
  }
}
