{
  "geometry": {
    "type": "Point",
    "coordinates": [
      -100.1167,
      29.1667
    ]
  },
  "type": "Feature",
  "properties": {
    "hierarchy": [
      "tgn:2530967",
      "tgn:1000001",
      "tgn:7012149",
      "tgn:2002021",
      "tgn:7007826",
      "tgn:7029392"
    ],
    "placetype": [
      "aat:300008798"
    ],
    "id": 2530967,
    "name:xx": "Muela Mountain"
  }
}
