{
  "geometry": {
    "type": "Point",
    "coordinates": [
      -122.7167,
      38.9667
    ]
  },
  "type": "Feature",
  "properties": {
    "hierarchy": [
      "tgn:2441883",
      "tgn:1000001",
      "tgn:7012149",
      "tgn:7007157",
      "tgn:1002566",
      "tgn:7029392"
    ],
    "placetype": [
      "aat:300132316"
    ],
    "id": 2441883,
    "name:xx": "Konocti Bay"
  }
}
