{
  "geometry": {
    "type": "Point",
    "coordinates": [
      -82.7333,
      32.5833
    ]
  },
  "type": "Feature",
  "properties": {
    "hierarchy": [
      "tgn:2432771",
      "tgn:1000001",
      "tgn:7012149",
      "tgn:2000378",
      "tgn:7007248",
      "tgn:7029392"
    ],
    "placetype": [
      "aat:300008347"
    ],
    "id": 2432771,
    "name:xx": "Keenes Crossing"
  }
}
