{
  "type": "FeatureCollection",
  "features": [
    {
      "geometry": {
        "type": "Point",
        "coordinates": [
          -106.2167,
          45.4167
        ]
      },
      "type": "Feature",
      "properties": {
        "hierarchy": [
          "tgn:2239050",
          "tgn:1000001",
          "tgn:7012149",
          "tgn:2001297",
          "tgn:7007524",
          "tgn:7029392"
        ],
        "placetype": [
          "aat:300008706"
        ],
        "id": 2239050,
        "name:xx": "Chromo Creek"
      }
    },
    {
      "geometry": {
        "type": "Point",
        "coordinates": [
          -106.1833,
          45.4333
        ]
      },
      "type": "Feature",
      "properties": {
        "hierarchy": [
          "tgn:2239054",
          "tgn:1000001",
          "tgn:7012149",
          "tgn:2001297",
          "tgn:7007524",
          "tgn:7029392"
        ],
        "placetype": [
          "aat:300006191"
        ],
        "id": 2239054,
        "name:xx": "Chromo Reservoir"
      }
    },
    {
      "geometry": {
        "type": "Point",
        "coordinates": [
          -106.2,
          45.4167
        ]
      },
      "type": "Feature",
      "properties": {
        "hierarchy": [
          "tgn:2239055",
          "tgn:1000001",
          "tgn:7012149",
          "tgn:2001297",
          "tgn:7007524",
          "tgn:7029392"
        ],
        "placetype": [
          "aat:300008697"
        ],
        "id": 2239055,
        "name:xx": "Chromo Spring"
      }
    },
    {
      "geometry": {
        "type": "Point",
        "coordinates": [
          -93.9333,
          46.3
        ]
      },
      "type": "Feature",
      "properties": {
        "hierarchy": [
          "tgn:2239056",
          "tgn:1000001",
          "tgn:2001016",
          "tgn:7012149",
          "tgn:7007521",
          "tgn:7029392"
        ],
        "placetype": [
          "aat:300008680"
        ],
        "id": 2239056,
        "name:xx": "Chrysler Lake"
      }
    },
    {
      "geometry": {
        "type": "Point",
        "coordinates": [
          -73.6,
          42.1
        ]
      },
      "type": "Feature",
      "properties": {
        "hierarchy": [
          "tgn:2239057",
          "tgn:1000001",
          "tgn:7013638",
          "tgn:7012149",
          "tgn:7007568",
          "tgn:7029392"
        ],
        "placetype": [
          "aat:300008680"
        ],
        "id": 2239057,
        "name:xx": "Chrysler Pond"
      }
    },
    {
      "geometry": {
        "type": "Point",
        "coordinates": [
          -73.6,
          42.1
        ]
      },
      "type": "Feature",
      "properties": {
        "hierarchy": [
          "tgn:2239058",
          "tgn:1000001",
          "tgn:7013638",
          "tgn:7012149",
          "tgn:7007568",
          "tgn:7029392"
        ],
        "placetype": [
          "aat:300008699"
        ],
        "id": 2239058,
        "name:xx": "Chrysler Pond Outlet"
      }
    },
    {
      "geometry": {
        "type": "Point",
        "coordinates": [
          -106.3333,
          38.65
        ]
      },
      "type": "Feature",
      "properties": {
        "hierarchy": [
          "tgn:2239059",
          "tgn:1000001",
          "tgn:2000199",
          "tgn:7012149",
          "tgn:7007158",
          "tgn:7029392"
        ],
        "placetype": [
          "aat:300008798"
        ],
        "id": 2239059,
        "name:xx": "Chrysolite Mountain"
      }
    }
  ]
}
