{
  "geometry": {
    "type": "Point",
    "coordinates": [
      -90.15,
      31.8333
    ]
  },
  "type": "Feature",
  "properties": {
    "hierarchy": [
      "tgn:2438769",
      "tgn:1000001",
      "tgn:2001100",
      "tgn:7012149",
      "tgn:7007522",
      "tgn:7029392"
    ],
    "placetype": [
      "aat:300008347"
    ],
    "id": 2438769,
    "name:xx": "Kinnaird"
  }
}
