{
  "type": "FeatureCollection",
  "features": [
    {
      "geometry": {
        "type": "Point",
        "coordinates": [
          38.8833,
          37.7333
        ]
      },
      "type": "Feature",
      "properties": {
        "hierarchy": [
          "tgn:4011193",
          "tgn:1001060",
          "tgn:1000004",
          "tgn:7018456",
          "tgn:1000144",
          "tgn:7029392"
        ],
        "placetype": [
          "aat:300008347",
          "aat:300008375"
        ],
        "id": 4011193,
        "name:xx": "Tille"
      }
    },
    {
      "geometry": {
        "type": "Point",
        "coordinates": [
          -2.816667,
          53.05
        ]
      },
      "type": "Feature",
      "properties": {
        "hierarchy": [
          "tgn:4011194",
          "tgn:7002445",
          "tgn:7008114",
          "tgn:1000003",
          "tgn:7008591",
          "tgn:7029392"
        ],
        "placetype": [
          "aat:300008347"
        ],
        "id": 4011194,
        "name:ang": "Tillestone"
      }
    },
    {
      "geometry": {
        "type": "Point",
        "coordinates": [
          21.4667,
          48.1667
        ]
      },
      "type": "Feature",
      "properties": {
        "hierarchy": [
          "tgn:4011195",
          "tgn:1000348",
          "tgn:1000003",
          "tgn:7006278",
          "tgn:7029392"
        ],
        "placetype": [
          "aat:300008347"
        ],
        "id": 4011195,
        "name:xx": "Timár"
      }
    }
  ]
}
