{
  "geometry": {
    "type": "Point",
    "coordinates": [
      -88.75,
      44.4333
    ]
  },
  "type": "Feature",
  "properties": {
    "hierarchy": [
      "tgn:2228608",
      "tgn:1000001",
      "tgn:7012149",
      "tgn:2002361",
      "tgn:7007922",
      "tgn:7029392"
    ],
    "placetype": [
      "aat:300008706"
    ],
    "id": 2228608,
    "name:xx": "Cedar Creek"
  }
}
