{
  "geometry": {
    "type": "Point",
    "coordinates": [
      -82.9167,
      37.1833
    ]
  },
  "type": "Feature",
  "properties": {
    "hierarchy": [
      "tgn:2125663",
      "tgn:1000001",
      "tgn:7012149",
      "tgn:2000812",
      "tgn:7007255",
      "tgn:7029392"
    ],
    "placetype": [
      "aat:300008699"
    ],
    "id": 2125663,
    "name:xx": "Adams Branch"
  }
}
