{
  "geometry": {
    "type": "Point",
    "coordinates": [
      -119.3333,
      34.3667
    ]
  },
  "type": "Feature",
  "properties": {
    "hierarchy": [
      "tgn:2224778",
      "tgn:1000001",
      "tgn:7012149",
      "tgn:7007157",
      "tgn:1002972",
      "tgn:7029392"
    ],
    "placetype": [
      "aat:300006191"
    ],
    "id": 2224778,
    "name:xx": "Casitas, Lake"
  }
}
