{
  "geometry": {
    "type": "Point",
    "coordinates": [
      -78.3833,
      40.3667
    ]
  },
  "type": "Feature",
  "properties": {
    "hierarchy": [
      "tgn:2661143",
      "tgn:1000001",
      "tgn:7012149",
      "tgn:7007710",
      "tgn:7029392"
    ],
    "placetype": [
      "aat:300266640"
    ],
    "id": 2661143,
    "name:xx": "Short Mountain"
  }
}
