{
  "geometry": {
    "type": "Point",
    "coordinates": [
      71.4167,
      34.1667
    ]
  },
  "type": "Feature",
  "properties": {
    "hierarchy": [
      "tgn:1083857",
      "tgn:7002460",
      "tgn:1000004",
      "tgn:1000133",
      "tgn:7029392"
    ],
    "placetype": [
      "aat:300008347"
    ],
    "id": 1083857,
    "name:xx": "Warsak"
  }
}
