{
  "geometry": {
    "type": "Point",
    "coordinates": [
      -112.15,
      41.9833
    ]
  },
  "type": "Feature",
  "properties": {
    "hierarchy": [
      "tgn:2753054",
      "tgn:1000001",
      "tgn:2002102",
      "tgn:7012149",
      "tgn:7007827",
      "tgn:7029392"
    ],
    "placetype": [
      "aat:300008761"
    ],
    "id": 2753054,
    "name:xx": "Water Hollow"
  }
}
