{
  "geometry": {
    "type": "Point",
    "coordinates": [
      -82.95,
      40.0333
    ]
  },
  "type": "Feature",
  "properties": {
    "hierarchy": [
      "tgn:2081087",
      "tgn:1000001",
      "tgn:7012149",
      "tgn:1002386",
      "tgn:7007706",
      "tgn:7029392"
    ],
    "placetype": [
      "aat:300247594"
    ],
    "id": 2081087,
    "name:xx": "Northern Lights Shopping Center"
  }
}
