{
  "geometry": {
    "type": "Point",
    "coordinates": [
      -81.8833,
      37.5167
    ]
  },
  "type": "Feature",
  "properties": {
    "hierarchy": [
      "tgn:2118716",
      "tgn:1000001",
      "tgn:7012149",
      "tgn:2002274",
      "tgn:7013961",
      "tgn:7029392"
    ],
    "placetype": [
      "aat:300008347"
    ],
    "id": 2118716,
    "name:xx": "Isaban"
  }
}
