{
  "geometry": {
    "type": "Point",
    "coordinates": [
      -83.55,
      44.8167
    ]
  },
  "type": "Feature",
  "properties": {
    "hierarchy": [
      "tgn:2239614",
      "tgn:2000942",
      "tgn:1000001",
      "tgn:7012149",
      "tgn:7007520",
      "tgn:7029392"
    ],
    "placetype": [
      "aat:300008850"
    ],
    "id": 2239614,
    "name:xx": "Churchill Point"
  }
}
