{
  "geometry": {
    "type": "Point",
    "coordinates": [
      -89.5333,
      43.9667
    ]
  },
  "type": "Feature",
  "properties": {
    "hierarchy": [
      "tgn:2709723",
      "tgn:1000001",
      "tgn:7012149",
      "tgn:2002338",
      "tgn:7007922",
      "tgn:7029392"
    ],
    "placetype": [
      "aat:300008706"
    ],
    "id": 2709723,
    "name:xx": "Tagatz Creek"
  }
}
