{
  "geometry": {
    "type": "Point",
    "coordinates": [
      -88.7833,
      46.9167
    ]
  },
  "type": "Feature",
  "properties": {
    "hierarchy": [
      "tgn:2543899",
      "tgn:1000001",
      "tgn:7012149",
      "tgn:2000963",
      "tgn:7007520",
      "tgn:7029392"
    ],
    "placetype": [
      "aat:300008706"
    ],
    "id": 2543899,
    "name:xx": "North Branch Bear Creek"
  }
}
