{
  "geometry": {
    "type": "Point",
    "coordinates": [
      31.186813,
      30.624056
    ]
  },
  "type": "Feature",
  "properties": {
    "hierarchy": [
      "tgn:7536904",
      "tgn:7001242",
      "tgn:7016833",
      "tgn:1001087",
      "tgn:7029392"
    ],
    "placetype": [
      "aat:300008347"
    ],
    "name:en": "Kafr Banī Ghiryān",
    "id": 7536904
  }
}
