{
  "type": "FeatureCollection",
  "features": [
    {
      "geometry": {
        "type": "Point",
        "coordinates": [
          138.7,
          -35.1167
        ]
      },
      "type": "Feature",
      "properties": {
        "hierarchy": [
          "tgn:1120180",
          "tgn:7000490",
          "tgn:1000006",
          "tgn:7001831",
          "tgn:7029392"
        ],
        "placetype": [
          "aat:300006191"
        ],
        "id": 1120180,
        "name:xx": "Mount Bold Reservoir"
      }
    },
    {
      "geometry": {
        "type": "Point",
        "coordinates": [
          -96.9333,
          32.7167
        ]
      },
      "type": "Feature",
      "properties": {
        "hierarchy": [
          "tgn:1120181",
          "tgn:1000001",
          "tgn:7012149",
          "tgn:1002315",
          "tgn:7007826",
          "tgn:7029392"
        ],
        "placetype": [
          "aat:300006191"
        ],
        "id": 1120181,
        "name:xx": "Mountain Creek Lake"
      }
    },
    {
      "geometry": {
        "type": "Point",
        "coordinates": [
          139.4167,
          35.7667
        ]
      },
      "type": "Feature",
      "properties": {
        "hierarchy": [
          "tgn:1120183",
          "tgn:1000004",
          "tgn:7000894",
          "tgn:1000120",
          "tgn:7029392"
        ],
        "placetype": [
          "aat:300006191"
        ],
        "id": 1120183,
        "name:xx": "Murayama-chosuichi"
      }
    },
    {
      "geometry": {
        "type": "Point",
        "coordinates": [
          -94.4167,
          32.0333
        ]
      },
      "type": "Feature",
      "properties": {
        "hierarchy": [
          "tgn:1120185",
          "tgn:1000001",
          "tgn:7012149",
          "tgn:1002769",
          "tgn:7007826",
          "tgn:7029392"
        ],
        "placetype": [
          "aat:300006191"
        ],
        "id": 1120185,
        "name:xx": "Murvaul, Lake"
      }
    },
    {
      "geometry": {
        "type": "Point",
        "coordinates": [
          138.4333,
          -35.4
        ]
      },
      "type": "Feature",
      "properties": {
        "hierarchy": [
          "tgn:1120186",
          "tgn:7000490",
          "tgn:1000006",
          "tgn:7001831",
          "tgn:7029392"
        ],
        "placetype": [
          "aat:300006191"
        ],
        "id": 1120186,
        "name:xx": "Myponga Reservoir"
      }
    },
    {
      "geometry": {
        "type": "Point",
        "coordinates": [
          32,
          22.6667
        ]
      },
      "type": "Feature",
      "properties": {
        "hierarchy": [
          "tgn:1120187",
          "tgn:7001242",
          "tgn:7029392"
        ],
        "placetype": [
          "aat:300006191"
        ],
        "name:en": "Buḩayrat Nāşir",
        "id": 1120187
      }
    },
    {
      "geometry": {
        "type": "Point",
        "coordinates": [
          79.211,
          16.544
        ]
      },
      "type": "Feature",
      "properties": {
        "hierarchy": [
          "tgn:1120188",
          "tgn:1001828",
          "tgn:1000004",
          "tgn:7000198",
          "tgn:7029392"
        ],
        "placetype": [
          "aat:300006191"
        ],
        "name:en": "Nāgārjuna Sāgar",
        "id": 1120188
      }
    }
  ]
}
