{
  "geometry": {
    "type": "Point",
    "coordinates": [
      -91.7833,
      40.2167
    ]
  },
  "type": "Feature",
  "properties": {
    "hierarchy": [
      "tgn:2783453",
      "tgn:1000001",
      "tgn:7012149",
      "tgn:1002592",
      "tgn:7007523",
      "tgn:7029392"
    ],
    "placetype": [
      "aat:300006191"
    ],
    "id": 2783453,
    "name:xx": "Wurtzburger Lake"
  }
}
