{
  "geometry": {
    "type": "Point",
    "coordinates": [
      20.25,
      46.25
    ]
  },
  "type": "Feature",
  "properties": {
    "hierarchy": [
      "tgn:7015929",
      "tgn:1000003",
      "tgn:7029392"
    ],
    "placetype": [
      "aat:300008707"
    ],
    "name:hu": "Maros",
    "name:ro": "Mureș",
    "id": 7015929
  }
}
