{
  "geometry": {
    "type": "Point",
    "coordinates": [
      -96.561111,
      19.15
    ]
  },
  "type": "Feature",
  "properties": {
    "hierarchy": [
      "tgn:7401959",
      "tgn:1000001",
      "tgn:7005599",
      "tgn:7005560",
      "tgn:7029392"
    ],
    "placetype": [
      "aat:300008347"
    ],
    "id": 7401959,
    "name:xx": "Paso Limón"
  }
}
