{
  "geometry": {
    "type": "Point",
    "coordinates": [
      27.130556,
      36.8525
    ]
  },
  "type": "Feature",
  "properties": {
    "hierarchy": [
      "tgn:7219882",
      "tgn:7011330",
      "tgn:7002674",
      "tgn:1000003",
      "tgn:1000074",
      "tgn:7029392"
    ],
    "placetype": [
      "aat:300387200"
    ],
    "id": 7219882,
    "name:xx": "Stavroú Pérama"
  }
}
