{
  "geometry": {
    "type": "Point",
    "coordinates": [
      -82.2667,
      30.9167
    ]
  },
  "type": "Feature",
  "properties": {
    "hierarchy": [
      "tgn:2171898",
      "tgn:1000001",
      "tgn:2000315",
      "tgn:7012149",
      "tgn:7007248",
      "tgn:7029392"
    ],
    "placetype": [
      "aat:300008680"
    ],
    "id": 2171898,
    "name:xx": "Big Water Lake"
  }
}
