{
  "geometry": {
    "type": "Point",
    "coordinates": [
      74.565278,
      32.8375
    ]
  },
  "type": "Feature",
  "properties": {
    "hierarchy": [
      "tgn:7592185",
      "tgn:1000004",
      "tgn:7000198",
      "tgn:7000799",
      "tgn:7029392"
    ],
    "placetype": [
      "aat:300266554",
      "aat:300008699"
    ],
    "name:en": "Thindewāli",
    "id": 7592185
  }
}
