{
  "geometry": {
    "type": "Point",
    "coordinates": [
      -82.1333,
      38.0167
    ]
  },
  "type": "Feature",
  "properties": {
    "hierarchy": [
      "tgn:2198230",
      "tgn:1000001",
      "tgn:7012149",
      "tgn:2002272",
      "tgn:7013961",
      "tgn:7029392"
    ],
    "placetype": [
      "aat:300008699"
    ],
    "id": 2198230,
    "name:xx": "Browns Branch"
  }
}
