{
  "geometry": {
    "type": "Point",
    "coordinates": [
      -146.2167,
      60.7833
    ]
  },
  "type": "Feature",
  "properties": {
    "hierarchy": [
      "tgn:7022602",
      "tgn:7006450",
      "tgn:1000001",
      "tgn:7012149",
      "tgn:7029392"
    ],
    "placetype": [
      "aat:300008706"
    ],
    "id": 7022602,
    "name:xx": "Control Creek"
  }
}
