{
  "geometry": {
    "type": "Point",
    "coordinates": [
      -85.9333,
      36.3333
    ]
  },
  "type": "Feature",
  "properties": {
    "hierarchy": [
      "tgn:2341057",
      "tgn:1000001",
      "tgn:7012149",
      "tgn:2001916",
      "tgn:7007825",
      "tgn:7029392"
    ],
    "placetype": [
      "aat:300008761"
    ],
    "id": 2341057,
    "name:xx": "Friendship Hollow"
  }
}
