{
  "type": "FeatureCollection",
  "features": [
    {
      "geometry": {
        "type": "Point",
        "coordinates": [
          7.283333,
          51.25
        ]
      },
      "type": "Feature",
      "properties": {
        "hierarchy": [
          "tgn:7084790",
          "tgn:1000003",
          "tgn:7003677",
          "tgn:7000084",
          "tgn:7029392"
        ],
        "placetype": [
          "aat:300008347"
        ],
        "id": 7084790,
        "name:xx": "Weuste"
      }
    },
    {
      "geometry": {
        "type": "Point",
        "coordinates": [
          7.233333,
          51.3
        ]
      },
      "type": "Feature",
      "properties": {
        "hierarchy": [
          "tgn:7084791",
          "tgn:1000003",
          "tgn:7003677",
          "tgn:7000084",
          "tgn:7029392"
        ],
        "placetype": [
          "aat:300000206"
        ],
        "id": 7084791,
        "name:xx": "Weuste"
      }
    },
    {
      "geometry": {
        "type": "Point",
        "coordinates": [
          8.033333,
          51.216667
        ]
      },
      "type": "Feature",
      "properties": {
        "hierarchy": [
          "tgn:7084792",
          "tgn:1000003",
          "tgn:7003677",
          "tgn:7000084",
          "tgn:7029392"
        ],
        "placetype": [
          "aat:300008347"
        ],
        "id": 7084792,
        "name:xx": "Weuspert"
      }
    },
    {
      "geometry": {
        "type": "Point",
        "coordinates": [
          13.05,
          48.616667
        ]
      },
      "type": "Feature",
      "properties": {
        "hierarchy": [
          "tgn:7084793",
          "tgn:7003669",
          "tgn:1000003",
          "tgn:7000084",
          "tgn:7029392"
        ],
        "placetype": [
          "aat:300008347"
        ],
        "id": 7084793,
        "name:xx": "Wetzstein"
      }
    },
    {
      "geometry": {
        "type": "Point",
        "coordinates": [
          11.783333,
          50.083333
        ]
      },
      "type": "Feature",
      "properties": {
        "hierarchy": [
          "tgn:7084794",
          "tgn:7003669",
          "tgn:1000003",
          "tgn:7000084",
          "tgn:7029392"
        ],
        "placetype": [
          "aat:300008795"
        ],
        "id": 7084794,
        "name:xx": "Wetzstein"
      }
    },
    {
      "geometry": {
        "type": "Point",
        "coordinates": [
          9.016667,
          50.883333
        ]
      },
      "type": "Feature",
      "properties": {
        "hierarchy": [
          "tgn:7084795",
          "tgn:1000003",
          "tgn:7003678",
          "tgn:7000084",
          "tgn:7029392"
        ],
        "placetype": [
          "aat:300008777"
        ],
        "id": 7084795,
        "name:xx": "Wetzstein"
      }
    },
    {
      "geometry": {
        "type": "Point",
        "coordinates": [
          9.166667,
          50.25
        ]
      },
      "type": "Feature",
      "properties": {
        "hierarchy": [
          "tgn:7084797",
          "tgn:1000003",
          "tgn:7003678",
          "tgn:7000084",
          "tgn:7029392"
        ],
        "placetype": [
          "aat:300008777"
        ],
        "id": 7084797,
        "name:xx": "Wetzstein"
      }
    },
    {
      "geometry": {
        "type": "Point",
        "coordinates": [
          11.016667,
          47.666667
        ]
      },
      "type": "Feature",
      "properties": {
        "hierarchy": [
          "tgn:7084798",
          "tgn:7003669",
          "tgn:1000003",
          "tgn:7000084",
          "tgn:7029392"
        ],
        "placetype": [
          "aat:300008777"
        ],
        "id": 7084798,
        "name:xx": "Wetzstein"
      }
    },
    {
      "geometry": {
        "type": "Point",
        "coordinates": [
          9.633333,
          50.75
        ]
      },
      "type": "Feature",
      "properties": {
        "hierarchy": [
          "tgn:7084799",
          "tgn:1000003",
          "tgn:7003678",
          "tgn:7000084",
          "tgn:7029392"
        ],
        "placetype": [
          "aat:300008347"
        ],
        "id": 7084799,
        "name:xx": "Wetzlos"
      }
    }
  ]
}
