{
  "geometry": {
    "type": "Point",
    "coordinates": [
      -119.0333,
      45.6667
    ]
  },
  "type": "Feature",
  "properties": {
    "hierarchy": [
      "tgn:2235189",
      "tgn:1000001",
      "tgn:7012149",
      "tgn:2001720",
      "tgn:7007708",
      "tgn:7029392"
    ],
    "placetype": [
      "aat:300008697"
    ],
    "id": 2235189,
    "name:xx": "Cherry Spring"
  }
}
