{
  "geometry": {
    "type": "Point",
    "coordinates": [
      -123.15,
      40.1167
    ]
  },
  "type": "Feature",
  "properties": {
    "hierarchy": [
      "tgn:2753642",
      "tgn:1000001",
      "tgn:7012149",
      "tgn:7007157",
      "tgn:2000191",
      "tgn:7029392"
    ],
    "placetype": [
      "aat:300008697"
    ],
    "id": 2753642,
    "name:xx": "Waterspout"
  }
}
