{
  "geometry": {
    "type": "Point",
    "coordinates": [
      -152.75,
      58.3667
    ]
  },
  "type": "Feature",
  "properties": {
    "hierarchy": [
      "tgn:2291866",
      "tgn:7006450",
      "tgn:1000001",
      "tgn:2124012",
      "tgn:7012149",
      "tgn:7029392"
    ],
    "placetype": [
      "aat:300008798"
    ],
    "id": 2291866,
    "name:xx": "Dome Peak"
  }
}
