{
  "geometry": {
    "type": "Point",
    "coordinates": [
      111.2333,
      55.8667
    ]
  },
  "type": "Feature",
  "properties": {
    "hierarchy": [
      "tgn:6006309",
      "tgn:1000004",
      "tgn:7011500",
      "tgn:7002435",
      "tgn:7029392"
    ],
    "placetype": [
      "aat:300008347"
    ],
    "id": 6006309,
    "name:xx": "Verkhne-Angarsk"
  }
}
