{
  "geometry": {
    "type": "Point",
    "coordinates": [
      141.9833,
      39.6333
    ]
  },
  "type": "Feature",
  "properties": {
    "hierarchy": [
      "tgn:7004661",
      "tgn:7016687",
      "tgn:1000004",
      "tgn:7000893",
      "tgn:1000120",
      "tgn:7029392"
    ],
    "placetype": [
      "aat:300008347",
      "aat:300008389"
    ],
    "id": 7004661,
    "name:xx": "Miyako"
  }
}
