{
  "geometry": {
    "type": "Point",
    "coordinates": [
      -83.5333,
      32.8667
    ]
  },
  "type": "Feature",
  "properties": {
    "hierarchy": [
      "tgn:2185097",
      "tgn:1000001",
      "tgn:2000302",
      "tgn:7012149",
      "tgn:7007248",
      "tgn:7029392"
    ],
    "placetype": [
      "aat:300008699"
    ],
    "id": 2185097,
    "name:xx": "Boggy Branch"
  }
}
