{
  "geometry": {
    "type": "Point",
    "coordinates": [
      -0.3333,
      43.0333
    ]
  },
  "type": "Feature",
  "properties": {
    "hierarchy": [
      "tgn:1107421",
      "tgn:7002878",
      "tgn:1000003",
      "tgn:1000070",
      "tgn:7029392"
    ],
    "placetype": [
      "aat:300008798"
    ],
    "id": 1107421,
    "name:xx": "Moulle, Pic de"
  }
}
