{
  "geometry": {
    "type": "Point",
    "coordinates": [
      25.85,
      36.35
    ]
  },
  "type": "Feature",
  "properties": {
    "hierarchy": [
      "tgn:7232102",
      "tgn:7011270",
      "tgn:7002674",
      "tgn:1000003",
      "tgn:1000074",
      "tgn:7029392"
    ],
    "placetype": [
      "aat:300008795"
    ],
    "id": 7232102,
    "name:xx": "Kálamos"
  }
}
