{
  "geometry": {
    "type": "Point",
    "coordinates": [
      -97.9667,
      27.4833
    ]
  },
  "type": "Feature",
  "properties": {
    "hierarchy": [
      "tgn:2318842",
      "tgn:1000001",
      "tgn:7012149",
      "tgn:2002022",
      "tgn:7007826",
      "tgn:7029392"
    ],
    "placetype": [
      "aat:300006191"
    ],
    "id": 2318842,
    "name:xx": "Escondido Lake"
  }
}
