{
  "type": "FeatureCollection",
  "features": [
    {
      "geometry": {
        "type": "Point",
        "coordinates": [
          -99.8333,
          28.9333
        ]
      },
      "type": "Feature",
      "properties": {
        "hierarchy": [
          "tgn:2105536",
          "tgn:1000001",
          "tgn:7012149",
          "tgn:2002100",
          "tgn:7007826",
          "tgn:7029392"
        ],
        "placetype": [
          "aat:300008347"
        ],
        "id": 2105536,
        "name:xx": "La Pryor"
      }
    },
    {
      "geometry": {
        "type": "Point",
        "coordinates": [
          -98.7333,
          26.3333
        ]
      },
      "type": "Feature",
      "properties": {
        "hierarchy": [
          "tgn:2105537",
          "tgn:1000001",
          "tgn:7012149",
          "tgn:2002075",
          "tgn:7007826",
          "tgn:7029392"
        ],
        "placetype": [
          "aat:300008347"
        ],
        "id": 2105537,
        "name:xx": "La Puerta"
      }
    },
    {
      "geometry": {
        "type": "Point",
        "coordinates": [
          -99.5,
          27.5
        ]
      },
      "type": "Feature",
      "properties": {
        "hierarchy": [
          "tgn:2105538",
          "tgn:1000001",
          "tgn:7012149",
          "tgn:2002090",
          "tgn:7007826",
          "tgn:7029392"
        ],
        "placetype": [
          "aat:300387277",
          "aat:300008347",
          "aat:300008416",
          "aat:300008389",
          "aat:300387257",
          "aat:300387308",
          "aat:300005135",
          "aat:300264742",
          "aat:300008486",
          "aat:300387302",
          "aat:300387287",
          "aat:300387291"
        ],
        "id": 2105538,
        "name:xx": "Laredo"
      }
    }
  ]
}
