{
  "geometry": {
    "type": "Point",
    "coordinates": [
      -93.6333,
      44.9167
    ]
  },
  "type": "Feature",
  "properties": {
    "hierarchy": [
      "tgn:2578391",
      "tgn:1000001",
      "tgn:2001025",
      "tgn:7012149",
      "tgn:7007521",
      "tgn:7029392"
    ],
    "placetype": [
      "aat:300132316"
    ],
    "id": 2578391,
    "name:xx": "Phelps Bay"
  }
}
