{
  "geometry": {
    "type": "Point",
    "coordinates": [
      -153.0667,
      65.3667
    ]
  },
  "type": "Feature",
  "properties": {
    "hierarchy": [
      "tgn:2366569",
      "tgn:7006450",
      "tgn:1000001",
      "tgn:7012149",
      "tgn:2000089",
      "tgn:7029392"
    ],
    "placetype": [
      "aat:300008706"
    ],
    "id": 2366569,
    "name:xx": "Grimm Creek"
  }
}
