{
  "geometry": {
    "type": "Point",
    "coordinates": [
      -96.0333,
      32.8833
    ]
  },
  "type": "Feature",
  "properties": {
    "hierarchy": [
      "tgn:2749529",
      "tgn:1000001",
      "tgn:7012149",
      "tgn:1002492",
      "tgn:7007826",
      "tgn:7029392"
    ],
    "placetype": [
      "aat:300132316"
    ],
    "id": 2749529,
    "name:xx": "Walnut Cove"
  }
}
