{
  "geometry": {
    "type": "Point",
    "coordinates": [
      -117.6333,
      46.65
    ]
  },
  "type": "Feature",
  "properties": {
    "hierarchy": [
      "tgn:2584698",
      "tgn:1000001",
      "tgn:2002245",
      "tgn:7012149",
      "tgn:7007920",
      "tgn:7029392"
    ],
    "placetype": [
      "aat:300008761"
    ],
    "id": 2584698,
    "name:xx": "Ping Gulch"
  }
}
