{
  "geometry": {
    "type": "Point",
    "coordinates": [
      73.8333,
      33.9167
    ]
  },
  "type": "Feature",
  "properties": {
    "hierarchy": [
      "tgn:1002105",
      "tgn:1000004",
      "tgn:7029392"
    ],
    "placetype": [
      "aat:300387346"
    ],
    "id": 1002105,
    "name:xx": "Punch"
  }
}
