{
  "geometry": {
    "type": "Point",
    "coordinates": [
      34.098625,
      27.893024
    ]
  },
  "type": "Feature",
  "properties": {
    "hierarchy": [
      "tgn:7528846",
      "tgn:7001242",
      "tgn:7016833",
      "tgn:7001336",
      "tgn:7029392"
    ],
    "placetype": [
      "aat:300379998"
    ],
    "name:en": "Umm Malaq, Wādī",
    "id": 7528846
  }
}
