{
  "geometry": {
    "type": "Point",
    "coordinates": [
      -79.8333,
      37.8667
    ]
  },
  "type": "Feature",
  "properties": {
    "hierarchy": [
      "tgn:2583787",
      "tgn:2002138",
      "tgn:1000001",
      "tgn:7012149",
      "tgn:7007919",
      "tgn:7029392"
    ],
    "placetype": [
      "aat:300266640"
    ],
    "id": 2583787,
    "name:xx": "Pine Spur Ridge"
  }
}
