{
  "geometry": {
    "type": "Point",
    "coordinates": [
      30.833333,
      28.45
    ]
  },
  "type": "Feature",
  "properties": {
    "hierarchy": [
      "tgn:7521993",
      "tgn:7001242",
      "tgn:7016833",
      "tgn:1001088",
      "tgn:7029392"
    ],
    "placetype": [
      "aat:300008347"
    ],
    "name:en": "Al Fārūqīyah",
    "id": 7521993
  }
}
