{
  "geometry": {
    "type": "Point",
    "coordinates": [
      76.73601,
      31.589161
    ]
  },
  "type": "Feature",
  "properties": {
    "hierarchy": [
      "tgn:7578738",
      "tgn:1000004",
      "tgn:7000198",
      "tgn:1001996",
      "tgn:7029392"
    ],
    "placetype": [
      "aat:300008347"
    ],
    "name:en": "Tānda",
    "id": 7578738
  }
}
