{
  "geometry": {
    "type": "Point",
    "coordinates": [
      106.75,
      -6.1167
    ]
  },
  "type": "Feature",
  "properties": {
    "hierarchy": [
      "tgn:1135834",
      "tgn:7002854",
      "tgn:1001318",
      "tgn:1000004",
      "tgn:1000116",
      "tgn:7029392"
    ],
    "placetype": [
      "aat:300006075"
    ],
    "id": 1135834,
    "name:xx": "Banjir Kanal"
  }
}
