{
  "geometry": {
    "type": "Point",
    "coordinates": [
      -84.2333,
      36.7167
    ]
  },
  "type": "Feature",
  "properties": {
    "hierarchy": [
      "tgn:2426811",
      "tgn:1000001",
      "tgn:7012149",
      "tgn:2000852",
      "tgn:7007255",
      "tgn:7029392"
    ],
    "placetype": [
      "aat:300008798"
    ],
    "id": 2426811,
    "name:xx": "Jones Peak"
  }
}
