{
  "geometry": {
    "type": "Point",
    "coordinates": [
      10.35,
      56.4333
    ]
  },
  "type": "Feature",
  "properties": {
    "hierarchy": [
      "tgn:1100273",
      "tgn:7594006",
      "tgn:1000003",
      "tgn:1000066",
      "tgn:7029392"
    ],
    "placetype": [
      "aat:300006891"
    ],
    "id": 1100273,
    "name:xx": "Gammel Estrup"
  }
}
