{
  "geometry": {
    "type": "Point",
    "coordinates": [
      -87.8333,
      41.8333
    ]
  },
  "type": "Feature",
  "properties": {
    "hierarchy": [
      "tgn:2196607",
      "tgn:1000001",
      "tgn:7013649",
      "tgn:7012149",
      "tgn:7007251",
      "tgn:7029392"
    ],
    "placetype": [
      "aat:300132451"
    ],
    "id": 2196607,
    "name:xx": "Brookfield Woods"
  }
}
