{
  "geometry": {
    "type": "Point",
    "coordinates": [
      -85.2167,
      31.2833
    ]
  },
  "type": "Feature",
  "properties": {
    "hierarchy": [
      "tgn:2344062",
      "tgn:7002659",
      "tgn:1000001",
      "tgn:7012149",
      "tgn:7029392"
    ],
    "placetype": [
      "aat:300008699"
    ],
    "id": 2344062,
    "name:xx": "Gamble Branch"
  }
}
