{
  "geometry": {
    "type": "Point",
    "coordinates": [
      151.1167,
      -29.25
    ]
  },
  "type": "Feature",
  "properties": {
    "hierarchy": [
      "tgn:1096126",
      "tgn:7000490",
      "tgn:1000006",
      "tgn:7001828",
      "tgn:7029392"
    ],
    "placetype": [
      "aat:300008347"
    ],
    "id": 1096126,
    "name:xx": "Ashford"
  }
}
