{
  "geometry": {
    "type": "Point",
    "coordinates": [
      -90.25,
      36.7833
    ]
  },
  "type": "Feature",
  "properties": {
    "hierarchy": [
      "tgn:2674492",
      "tgn:1000001",
      "tgn:2001176",
      "tgn:7012149",
      "tgn:7007523",
      "tgn:7029392"
    ],
    "placetype": [
      "aat:300006075"
    ],
    "id": 2674492,
    "name:xx": "Snyder Ditch"
  }
}
