{
  "type": "FeatureCollection",
  "features": [
    {
      "geometry": {
        "type": "Point",
        "coordinates": [
          44.555,
          33.354
        ]
      },
      "type": "Feature",
      "properties": {
        "hierarchy": [
          "tgn:7032790",
          "tgn:1000004",
          "tgn:1001221",
          "tgn:1000118",
          "tgn:7029392"
        ],
        "placetype": [
          "aat:300008347",
          "aat:300000810",
          "aat:300167671"
        ],
        "id": 7032790,
        "name:xx": "Khafajah"
      }
    },
    {
      "geometry": {
        "type": "Point",
        "coordinates": [
          -89.369167,
          13.8275
        ]
      },
      "type": "Feature",
      "properties": {
        "hierarchy": [
          "tgn:7032792",
          "tgn:7005455",
          "tgn:1000001",
          "tgn:7005441",
          "tgn:7029392"
        ],
        "placetype": [
          "aat:300017826",
          "aat:300008347",
          "aat:300000810",
          "aat:300167671",
          "aat:300008057",
          "aat:300263063"
        ],
        "id": 7032792,
        "name:xx": "Joya de Cerén"
      }
    },
    {
      "geometry": {
        "type": "Point",
        "coordinates": [
          46.004,
          31.382
        ]
      },
      "type": "Feature",
      "properties": {
        "hierarchy": [
          "tgn:7032798",
          "tgn:1000004",
          "tgn:1001220",
          "tgn:1000118",
          "tgn:7029392"
        ],
        "placetype": [
          "aat:300234611",
          "aat:300008347",
          "aat:300000810",
          "aat:300167671",
          "aat:300019726"
        ],
        "id": 7032798,
        "name:xx": "Tell Madineh"
      }
    }
  ]
}
