{
  "geometry": {
    "type": "Point",
    "coordinates": [
      27.883333,
      28.566667
    ]
  },
  "type": "Feature",
  "properties": {
    "hierarchy": [
      "tgn:7525429",
      "tgn:7001242",
      "tgn:7016833",
      "tgn:1001083",
      "tgn:7029392"
    ],
    "placetype": [
      "aat:300055621"
    ],
    "name:en": "Baḥr Bela Mâ'",
    "id": 7525429
  }
}
