{
  "geometry": {
    "type": "Point",
    "coordinates": [
      -105.3167,
      32.85
    ]
  },
  "type": "Feature",
  "properties": {
    "hierarchy": [
      "tgn:2681308",
      "tgn:1000001",
      "tgn:2001430",
      "tgn:7012149",
      "tgn:7007566",
      "tgn:7029392"
    ],
    "placetype": [
      "aat:300006191"
    ],
    "id": 2681308,
    "name:xx": "South Pasture Tank Number 1"
  }
}
