{
  "geometry": {
    "type": "Point",
    "coordinates": [
      -75.25,
      38.05
    ]
  },
  "type": "Feature",
  "properties": {
    "hierarchy": [
      "tgn:2633270",
      "tgn:1000001",
      "tgn:1003037",
      "tgn:7012149",
      "tgn:7007516",
      "tgn:7029392"
    ],
    "placetype": [
      "aat:300132316"
    ],
    "id": 2633270,
    "name:xx": "Rum Harbor"
  }
}
