{
  "geometry": {
    "type": "Point",
    "coordinates": [
      -82.0667,
      33.3167
    ]
  },
  "type": "Feature",
  "properties": {
    "hierarchy": [
      "tgn:2461099",
      "tgn:1000001",
      "tgn:7012149",
      "tgn:2000412",
      "tgn:7007248",
      "tgn:7029392"
    ],
    "placetype": [
      "aat:300008706"
    ],
    "id": 2461099,
    "name:xx": "Little Spirit Creek"
  }
}
