{
  "geometry": {
    "type": "Point",
    "coordinates": [
      -113.5167,
      36.3167
    ]
  },
  "type": "Feature",
  "properties": {
    "hierarchy": [
      "tgn:2126999",
      "tgn:1000001",
      "tgn:7006451",
      "tgn:7012149",
      "tgn:2000098",
      "tgn:7029392"
    ],
    "placetype": [
      "aat:300008761"
    ],
    "id": 2126999,
    "name:xx": "Agway Valley"
  }
}
