{
  "geometry": {
    "type": "Point",
    "coordinates": [
      -119.4167,
      48.9833
    ]
  },
  "type": "Feature",
  "properties": {
    "hierarchy": [
      "tgn:2367991",
      "tgn:1000001",
      "tgn:7012149",
      "tgn:1002742",
      "tgn:7007920",
      "tgn:7029392"
    ],
    "placetype": [
      "aat:300132316"
    ],
    "id": 2367991,
    "name:xx": "Grubbs Cove"
  }
}
