{
  "geometry": {
    "type": "Point",
    "coordinates": [
      105.95,
      28.9333
    ]
  },
  "type": "Feature",
  "properties": {
    "hierarchy": [
      "tgn:1066648",
      "tgn:1000004",
      "tgn:7002087",
      "tgn:1000111",
      "tgn:7029392"
    ],
    "placetype": [
      "aat:300008347"
    ],
    "id": 1066648,
    "name:xx": "Bailuchang"
  }
}
