{
  "type": "FeatureCollection",
  "features": [
    {
      "geometry": {
        "type": "Point",
        "coordinates": [
          -98.166667,
          24.333333
        ]
      },
      "type": "Feature",
      "properties": {
        "hierarchy": [
          "tgn:7436520",
          "tgn:1000001",
          "tgn:7005597",
          "tgn:7005560",
          "tgn:7029392"
        ],
        "placetype": [
          "aat:300008699"
        ],
        "id": 7436520,
        "name:xx": "Soldados, Arroyo"
      }
    },
    {
      "geometry": {
        "type": "Point",
        "coordinates": [
          -105.316667,
          28.883333
        ]
      },
      "type": "Feature",
      "properties": {
        "hierarchy": [
          "tgn:7436522",
          "tgn:7005581",
          "tgn:1000001",
          "tgn:7005560",
          "tgn:7029392"
        ],
        "placetype": [
          "aat:300000241"
        ],
        "id": 7436522,
        "name:xx": "Rancho Soldado"
      }
    },
    {
      "geometry": {
        "type": "Point",
        "coordinates": [
          -101.783333,
          25.066667
        ]
      },
      "type": "Feature",
      "properties": {
        "hierarchy": [
          "tgn:7436523",
          "tgn:1001853",
          "tgn:1000001",
          "tgn:7005560",
          "tgn:7029392"
        ],
        "placetype": [
          "aat:300259572"
        ],
        "id": 7436523,
        "name:xx": "Soldado, Puerto del"
      }
    },
    {
      "geometry": {
        "type": "Point",
        "coordinates": [
          -110.966667,
          27.95
        ]
      },
      "type": "Feature",
      "properties": {
        "hierarchy": [
          "tgn:7436524",
          "tgn:1000001",
          "tgn:1001960",
          "tgn:7005560",
          "tgn:7029392"
        ],
        "placetype": [
          "aat:300008679"
        ],
        "id": 7436524,
        "name:xx": "Soldado, Estero del"
      }
    },
    {
      "geometry": {
        "type": "Point",
        "coordinates": [
          -101.7,
          29.666667
        ]
      },
      "type": "Feature",
      "properties": {
        "hierarchy": [
          "tgn:7436525",
          "tgn:1001853",
          "tgn:1000001",
          "tgn:7005560",
          "tgn:7029392"
        ],
        "placetype": [
          "aat:300266554",
          "aat:300008699"
        ],
        "id": 7436525,
        "name:xx": "Soldado, Arroyo del"
      }
    },
    {
      "geometry": {
        "type": "Point",
        "coordinates": [
          -99.85,
          23.533333
        ]
      },
      "type": "Feature",
      "properties": {
        "hierarchy": [
          "tgn:7436526",
          "tgn:1000001",
          "tgn:7005597",
          "tgn:7005560",
          "tgn:7029392"
        ],
        "placetype": [
          "aat:300266554",
          "aat:300008699"
        ],
        "id": 7436526,
        "name:xx": "Soldado"
      }
    },
    {
      "geometry": {
        "type": "Point",
        "coordinates": [
          -110.7,
          30.45
        ]
      },
      "type": "Feature",
      "properties": {
        "hierarchy": [
          "tgn:7436527",
          "tgn:1000001",
          "tgn:1001960",
          "tgn:7005560",
          "tgn:7029392"
        ],
        "placetype": [
          "aat:300008347"
        ],
        "id": 7436527,
        "name:xx": "Soldado"
      }
    },
    {
      "geometry": {
        "type": "Point",
        "coordinates": [
          -105.266667,
          28.866667
        ]
      },
      "type": "Feature",
      "properties": {
        "hierarchy": [
          "tgn:7436528",
          "tgn:7005581",
          "tgn:1000001",
          "tgn:7005560",
          "tgn:7029392"
        ],
        "placetype": [
          "aat:300008347"
        ],
        "id": 7436528,
        "name:xx": "Soldado"
      }
    },
    {
      "geometry": {
        "type": "Point",
        "coordinates": [
          -104.933333,
          23.916667
        ]
      },
      "type": "Feature",
      "properties": {
        "hierarchy": [
          "tgn:7436529",
          "tgn:7005583",
          "tgn:1000001",
          "tgn:7005560",
          "tgn:7029392"
        ],
        "placetype": [
          "aat:300008347"
        ],
        "id": 7436529,
        "name:xx": "Soldado"
      }
    }
  ]
}
