{
  "geometry": {
    "type": "Point",
    "coordinates": [
      -80.8667,
      34.3333
    ]
  },
  "type": "Feature",
  "properties": {
    "hierarchy": [
      "tgn:2623127",
      "tgn:1000001",
      "tgn:2001744",
      "tgn:7012149",
      "tgn:7007712",
      "tgn:7029392"
    ],
    "placetype": [
      "aat:300008706"
    ],
    "id": 2623127,
    "name:xx": "Rochelle Creek"
  }
}
