{
  "geometry": {
    "type": "Point",
    "coordinates": [
      -92.8333,
      45.35
    ]
  },
  "type": "Feature",
  "properties": {
    "hierarchy": [
      "tgn:2442471",
      "tgn:1000001",
      "tgn:2001011",
      "tgn:7012149",
      "tgn:7007521",
      "tgn:7029392"
    ],
    "placetype": [
      "aat:300008680"
    ],
    "id": 2442471,
    "name:xx": "Kroon Lake"
  }
}
