{
  "type": "FeatureCollection",
  "features": [
    {
      "geometry": {
        "type": "Point",
        "coordinates": [
          -3.2,
          51.5
        ]
      },
      "type": "Feature",
      "properties": {
        "hierarchy": [
          "tgn:7458910",
          "tgn:7002443",
          "tgn:7018962",
          "tgn:1000003",
          "tgn:7008591",
          "tgn:7029392"
        ],
        "placetype": [
          "aat:300000745"
        ],
        "name:en": "Maendy",
        "id": 7458910
      }
    },
    {
      "geometry": {
        "type": "Point",
        "coordinates": [
          -2.283333,
          52.116667
        ]
      },
      "type": "Feature",
      "properties": {
        "hierarchy": [
          "tgn:7458913",
          "tgn:7002445",
          "tgn:1000003",
          "tgn:5000227",
          "tgn:7008591",
          "tgn:7029392"
        ],
        "placetype": [
          "aat:300008347"
        ],
        "name:en": "Madresfield",
        "id": 7458913
      }
    },
    {
      "geometry": {
        "type": "Point",
        "coordinates": [
          0.05,
          52.216667
        ]
      },
      "type": "Feature",
      "properties": {
        "hierarchy": [
          "tgn:7458915",
          "tgn:7002445",
          "tgn:7011980",
          "tgn:1000003",
          "tgn:7008591",
          "tgn:7029392"
        ],
        "placetype": [
          "aat:300008347"
        ],
        "name:en": "Madingley",
        "id": 7458915
      }
    },
    {
      "geometry": {
        "type": "Point",
        "coordinates": [
          -2.316667,
          53
        ]
      },
      "type": "Feature",
      "properties": {
        "hierarchy": [
          "tgn:7458916",
          "tgn:7002445",
          "tgn:1000003",
          "tgn:7008174",
          "tgn:7008591",
          "tgn:7029392"
        ],
        "placetype": [
          "aat:300008347"
        ],
        "name:en": "Madeley Heath",
        "id": 7458916
      }
    },
    {
      "geometry": {
        "type": "Point",
        "coordinates": [
          -2.45,
          52.633333
        ]
      },
      "type": "Feature",
      "properties": {
        "hierarchy": [
          "tgn:7458917",
          "tgn:7002445",
          "tgn:1000003",
          "tgn:7026533",
          "tgn:7008591",
          "tgn:7029392"
        ],
        "placetype": [
          "aat:300387502"
        ],
        "name:en": "Madeley Court",
        "id": 7458917
      }
    }
  ]
}
