{
  "geometry": {
    "type": "Point",
    "coordinates": [
      -105.5667,
      44.3833
    ]
  },
  "type": "Feature",
  "properties": {
    "hierarchy": [
      "tgn:2634168",
      "tgn:1000001",
      "tgn:2002367",
      "tgn:7012149",
      "tgn:7007923",
      "tgn:7029392"
    ],
    "placetype": [
      "aat:300008761"
    ],
    "id": 2634168,
    "name:xx": "Russell Draw"
  }
}
