{
  "geometry": {
    "type": "Point",
    "coordinates": [
      -78.95,
      34.5833
    ]
  },
  "type": "Feature",
  "properties": {
    "hierarchy": [
      "tgn:2487028",
      "tgn:1000001",
      "tgn:7012149",
      "tgn:2001534",
      "tgn:7007709",
      "tgn:7029392"
    ],
    "placetype": [
      "aat:300006191"
    ],
    "id": 2487028,
    "name:xx": "Lee Pond"
  }
}
