{
  "geometry": {
    "type": "Point",
    "coordinates": [
      79.394553,
      26.389022
    ]
  },
  "type": "Feature",
  "properties": {
    "hierarchy": [
      "tgn:7565961",
      "tgn:1000004",
      "tgn:7000198",
      "tgn:7016722",
      "tgn:7029392"
    ],
    "placetype": [
      "aat:300008347"
    ],
    "name:en": "Jamālīpur",
    "id": 7565961
  }
}
