{
  "geometry": {
    "type": "Point",
    "coordinates": [
      130.9167,
      34.4167
    ]
  },
  "type": "Feature",
  "properties": {
    "hierarchy": [
      "tgn:1114056",
      "tgn:7000897",
      "tgn:1001040",
      "tgn:1000004",
      "tgn:1000120",
      "tgn:7029392"
    ],
    "placetype": [
      "aat:300132316"
    ],
    "id": 1114056,
    "name:xx": "Yuya-wan"
  }
}
