{
  "geometry": {
    "type": "Point",
    "coordinates": [
      -99.95,
      21.45
    ]
  },
  "type": "Feature",
  "properties": {
    "hierarchy": [
      "tgn:7426764",
      "tgn:1000001",
      "tgn:7005594",
      "tgn:7005560",
      "tgn:7029392"
    ],
    "placetype": [
      "aat:300008699"
    ],
    "id": 7426764,
    "name:xx": "La Cañada, Arroyo"
  }
}
