{
  "geometry": {
    "type": "Point",
    "coordinates": [
      -72.1833,
      43.1167
    ]
  },
  "type": "Feature",
  "properties": {
    "hierarchy": [
      "tgn:2745152",
      "tgn:7019618",
      "tgn:1000001",
      "tgn:7012149",
      "tgn:7007564",
      "tgn:7029392"
    ],
    "placetype": [
      "aat:300006191"
    ],
    "id": 2745152,
    "name:xx": "Village Pond"
  }
}
