{
  "geometry": {
    "type": "Point",
    "coordinates": [
      -79.05,
      35.2667
    ]
  },
  "type": "Feature",
  "properties": {
    "hierarchy": [
      "tgn:2076747",
      "tgn:1000001",
      "tgn:7012149",
      "tgn:2001502",
      "tgn:7007709",
      "tgn:7029392"
    ],
    "placetype": [
      "aat:300008347",
      "aat:300387210"
    ],
    "id": 2076747,
    "name:xx": "Spout Springs"
  }
}
