{
  "geometry": {
    "type": "Point",
    "coordinates": [
      12.1667,
      49.6667
    ]
  },
  "type": "Feature",
  "properties": {
    "hierarchy": [
      "tgn:1041700",
      "tgn:7003669",
      "tgn:1000003",
      "tgn:7000084",
      "tgn:7029392"
    ],
    "placetype": [
      "aat:300008347"
    ],
    "id": 1041700,
    "name:xx": "Weiden in der Oberpfalz"
  }
}
