{
  "geometry": {
    "type": "Point",
    "coordinates": [
      -90.85,
      45.95
    ]
  },
  "type": "Feature",
  "properties": {
    "hierarchy": [
      "tgn:2700192",
      "tgn:1000001",
      "tgn:7012149",
      "tgn:2002353",
      "tgn:7007922",
      "tgn:7029392"
    ],
    "placetype": [
      "aat:300132316"
    ],
    "id": 2700192,
    "name:xx": "Sturgeon Bay"
  }
}
