{
  "geometry": {
    "type": "Point",
    "coordinates": [
      -117.1833,
      41.5833
    ]
  },
  "type": "Feature",
  "properties": {
    "hierarchy": [
      "tgn:2767007",
      "tgn:1000001",
      "tgn:2001414",
      "tgn:7012149",
      "tgn:7007526",
      "tgn:7029392"
    ],
    "placetype": [
      "aat:300266640"
    ],
    "id": 2767007,
    "name:xx": "White Ridge"
  }
}
