{
  "geometry": {
    "type": "Point",
    "coordinates": [
      -37.95,
      -4.7333
    ]
  },
  "type": "Feature",
  "properties": {
    "hierarchy": [
      "tgn:1022302",
      "tgn:7006064",
      "tgn:1000047",
      "tgn:7002455",
      "tgn:1000002",
      "tgn:7029392"
    ],
    "placetype": [
      "aat:300008347"
    ],
    "id": 1022302,
    "name:xx": "Palhano"
  }
}
