{
  "geometry": {
    "type": "Point",
    "coordinates": [
      -105.8667,
      44.45
    ]
  },
  "type": "Feature",
  "properties": {
    "hierarchy": [
      "tgn:2122907",
      "tgn:1000001",
      "tgn:2002367",
      "tgn:7012149",
      "tgn:7007923",
      "tgn:7029392"
    ],
    "placetype": [
      "aat:300387016"
    ],
    "id": 2122907,
    "name:xx": "Echeta"
  }
}
