{
  "geometry": {
    "type": "Point",
    "coordinates": [
      -96.8667,
      28.2667
    ]
  },
  "type": "Feature",
  "properties": {
    "hierarchy": [
      "tgn:2683238",
      "tgn:7013313",
      "tgn:1000001",
      "tgn:7012149",
      "tgn:7007826",
      "tgn:7029392"
    ],
    "placetype": [
      "aat:300008347"
    ],
    "id": 2683238,
    "name:xx": "Spanish Village"
  }
}
