{
  "geometry": {
    "type": "Point",
    "coordinates": [
      -88.15,
      34.6167
    ]
  },
  "type": "Feature",
  "properties": {
    "hierarchy": [
      "tgn:7023434",
      "tgn:1000001",
      "tgn:7012149",
      "tgn:7029392"
    ],
    "placetype": [
      "aat:300008699"
    ],
    "id": 7023434,
    "name:xx": "Mingo Branch"
  }
}
