{
  "geometry": {
    "type": "Point",
    "coordinates": [
      -92.3833,
      30.0833
    ]
  },
  "type": "Feature",
  "properties": {
    "hierarchy": [
      "tgn:2664654",
      "tgn:2000854",
      "tgn:1000001",
      "tgn:7012149",
      "tgn:7007256",
      "tgn:7029392"
    ],
    "placetype": [
      "aat:300008699"
    ],
    "id": 2664654,
    "name:xx": "Simmons Gully"
  }
}
