{
  "geometry": {
    "type": "Point",
    "coordinates": [
      31.556301,
      26.873181
    ]
  },
  "type": "Feature",
  "properties": {
    "hierarchy": [
      "tgn:7520113",
      "tgn:7001242",
      "tgn:7001311",
      "tgn:7016833",
      "tgn:7029392"
    ],
    "placetype": [
      "aat:300379998"
    ],
    "name:en": "Abū Shīḩ, Wādī",
    "id": 7520113
  }
}
