{
  "geometry": {
    "type": "Point",
    "coordinates": [
      31.30664,
      30.091544
    ]
  },
  "type": "Feature",
  "properties": {
    "hierarchy": [
      "tgn:7526437",
      "tgn:7001242",
      "tgn:7016833",
      "tgn:1001091",
      "tgn:7029392"
    ],
    "placetype": [
      "aat:300006676"
    ],
    "id": 7526437,
    "name:xx": "Mustashfá Manshīyat al Bakrī al 'Āmm"
  }
}
