{
  "type": "FeatureCollection",
  "features": [
    {
      "geometry": {
        "type": "Point",
        "coordinates": [
          -4.616667,
          52.083333
        ]
      },
      "type": "Feature",
      "properties": {
        "hierarchy": [
          "tgn:7443272",
          "tgn:7002443",
          "tgn:7017242",
          "tgn:1000003",
          "tgn:7008591",
          "tgn:7029392"
        ],
        "placetype": [
          "aat:300387173"
        ],
        "name:en": "Teifiside",
        "id": 7443272
      }
    },
    {
      "geometry": {
        "type": "Point",
        "coordinates": [
          -2.018611,
          51.090278
        ]
      },
      "type": "Feature",
      "properties": {
        "hierarchy": [
          "tgn:7443274",
          "tgn:7002445",
          "tgn:1000003",
          "tgn:7008180",
          "tgn:7008591",
          "tgn:7029392"
        ],
        "placetype": [
          "aat:300008347"
        ],
        "name:en": "Teffont Magna",
        "id": 7443274
      }
    },
    {
      "geometry": {
        "type": "Point",
        "coordinates": [
          -1.233333,
          54.566667
        ]
      },
      "type": "Feature",
      "properties": {
        "hierarchy": [
          "tgn:7443275",
          "tgn:7002445",
          "tgn:1000003",
          "tgn:7019066",
          "tgn:7008591",
          "tgn:7029392"
        ],
        "placetype": [
          "aat:300000745"
        ],
        "name:en": "Teesside County Borough",
        "id": 7443275
      }
    },
    {
      "geometry": {
        "type": "Point",
        "coordinates": [
          -1.166667,
          54.65
        ]
      },
      "type": "Feature",
      "properties": {
        "hierarchy": [
          "tgn:7443277",
          "tgn:7002445",
          "tgn:1000003",
          "tgn:7019068",
          "tgn:7008591",
          "tgn:7029392"
        ],
        "placetype": [
          "aat:300008699"
        ],
        "name:en": "Tees Mouth",
        "id": 7443277
      }
    },
    {
      "geometry": {
        "type": "Point",
        "coordinates": [
          -6.316667,
          54.9
        ]
      },
      "type": "Feature",
      "properties": {
        "hierarchy": [
          "tgn:7443279",
          "tgn:7019164",
          "tgn:7002448",
          "tgn:1000003",
          "tgn:7008591",
          "tgn:7029392"
        ],
        "placetype": [
          "aat:300008347"
        ],
        "name:en": "Teeshan",
        "id": 7443279
      }
    }
  ]
}
