{
  "geometry": {
    "type": "Point",
    "coordinates": [
      -117.0333,
      32.9833
    ]
  },
  "type": "Feature",
  "properties": {
    "hierarchy": [
      "tgn:2736306",
      "tgn:1000001",
      "tgn:7012149",
      "tgn:7007157",
      "tgn:1002858",
      "tgn:7029392"
    ],
    "placetype": [
      "aat:300008798"
    ],
    "id": 2736306,
    "name:xx": "Twin Peaks"
  }
}
