{
  "geometry": {
    "type": "Point",
    "coordinates": [
      -86.3833,
      31.9667
    ]
  },
  "type": "Feature",
  "properties": {
    "hierarchy": [
      "tgn:2164066",
      "tgn:7002659",
      "tgn:1000001",
      "tgn:2000020",
      "tgn:7012149",
      "tgn:7029392"
    ],
    "placetype": [
      "aat:300008706"
    ],
    "id": 2164066,
    "name:xx": "Berkley Mill Creek"
  }
}
