{
  "geometry": {
    "type": "Point",
    "coordinates": [
      -73.523889,
      -42.6625
    ]
  },
  "type": "Feature",
  "properties": {
    "hierarchy": [
      "tgn:7319092",
      "tgn:1001699",
      "tgn:1000049",
      "tgn:1000002",
      "tgn:7029392"
    ],
    "placetype": [
      "aat:300386846"
    ],
    "id": 7319092,
    "name:xx": "Lelbún, Punta"
  }
}
