{
  "geometry": {
    "type": "Point",
    "coordinates": [
      -86.1667,
      37.0333
    ]
  },
  "type": "Feature",
  "properties": {
    "hierarchy": [
      "tgn:2581442",
      "tgn:1000001",
      "tgn:7012149",
      "tgn:2000848",
      "tgn:7007255",
      "tgn:7029392"
    ],
    "placetype": [
      "aat:300008798"
    ],
    "id": 2581442,
    "name:xx": "Pilot Knob"
  }
}
