{
  "geometry": {
    "type": "Point",
    "coordinates": [
      34.507381,
      29.246043
    ]
  },
  "type": "Feature",
  "properties": {
    "hierarchy": [
      "tgn:7541459",
      "tgn:7001242",
      "tgn:7016833",
      "tgn:7001336",
      "tgn:7029392"
    ],
    "placetype": [
      "aat:300379998"
    ],
    "name:en": "Ab큰 'Al훮qah, W훮d카",
    "id": 7541459
  }
}
