{
  "geometry": {
    "type": "Point",
    "coordinates": [
      -92.1167,
      36.8167
    ]
  },
  "type": "Feature",
  "properties": {
    "hierarchy": [
      "tgn:2171072",
      "tgn:1000001",
      "tgn:7012149",
      "tgn:2001196",
      "tgn:7007523",
      "tgn:7029392"
    ],
    "placetype": [
      "aat:300008697"
    ],
    "id": 2171072,
    "name:xx": "Big Spring"
  }
}
