{
  "geometry": {
    "type": "Point",
    "coordinates": [
      -113.2333,
      47.7667
    ]
  },
  "type": "Feature",
  "properties": {
    "hierarchy": [
      "tgn:2767025",
      "tgn:1000001",
      "tgn:7012149",
      "tgn:7007524",
      "tgn:7029392"
    ],
    "placetype": [
      "aat:300008707"
    ],
    "id": 2767025,
    "name:xx": "White River"
  }
}
