{
  "geometry": {
    "type": "Point",
    "coordinates": [
      -111.7833,
      41.8167
    ]
  },
  "type": "Feature",
  "properties": {
    "hierarchy": [
      "tgn:2467450",
      "tgn:1000001",
      "tgn:2002103",
      "tgn:7012149",
      "tgn:7007827",
      "tgn:7029392"
    ],
    "placetype": [
      "aat:300008798"
    ],
    "id": 2467450,
    "name:xx": "Long Hill"
  }
}
