{
  "geometry": {
    "type": "Point",
    "coordinates": [
      -3.05,
      36.866667
    ]
  },
  "type": "Feature",
  "properties": {
    "hierarchy": [
      "tgn:7299935",
      "tgn:7002805",
      "tgn:7002758",
      "tgn:1000003",
      "tgn:1000095",
      "tgn:7029392"
    ],
    "placetype": [
      "aat:300008347"
    ],
    "id": 7299935,
    "name:xx": "Turón"
  }
}
