{
  "type": "FeatureCollection",
  "features": [
    {
      "geometry": {
        "type": "Point",
        "coordinates": [
          25.700158,
          30.667739
        ]
      },
      "type": "Feature",
      "properties": {
        "hierarchy": [
          "tgn:7537340",
          "tgn:7001242",
          "tgn:7016833",
          "tgn:1001418",
          "tgn:7029392"
        ],
        "placetype": [
          "aat:300006960"
        ],
        "name:en": "Quweiret el Irîs",
        "id": 7537340
      }
    },
    {
      "geometry": {
        "type": "Point",
        "coordinates": [
          31.133333,
          30.55
        ]
      },
      "type": "Feature",
      "properties": {
        "hierarchy": [
          "tgn:7537342",
          "tgn:7001242",
          "tgn:7016833",
          "tgn:1001087",
          "tgn:7029392"
        ],
        "placetype": [
          "aat:300007783"
        ],
        "name:en": "Maḩaţţat Quwaysinā",
        "id": 7537342
      }
    },
    {
      "geometry": {
        "type": "Point",
        "coordinates": [
          34.148925,
          26.351264
        ]
      },
      "type": "Feature",
      "properties": {
        "hierarchy": [
          "tgn:7537344",
          "tgn:7001242",
          "tgn:7001311",
          "tgn:7016833",
          "tgn:7029392"
        ],
        "placetype": [
          "aat:300379998"
        ],
        "name:en": "Quway', Wādī",
        "id": 7537344
      }
    },
    {
      "geometry": {
        "type": "Point",
        "coordinates": [
          34.133568,
          26.353027
        ]
      },
      "type": "Feature",
      "properties": {
        "hierarchy": [
          "tgn:7537345",
          "tgn:7001242",
          "tgn:7001311",
          "tgn:7016833",
          "tgn:7029392"
        ],
        "placetype": [
          "aat:300006207"
        ],
        "name:en": "Bi'r Quway'",
        "id": 7537345
      }
    },
    {
      "geometry": {
        "type": "Point",
        "coordinates": [
          31.933333,
          31.216667
        ]
      },
      "type": "Feature",
      "properties": {
        "hierarchy": [
          "tgn:7537347",
          "tgn:7001242",
          "tgn:1001059",
          "tgn:7016833",
          "tgn:7029392"
        ],
        "placetype": [
          "aat:300008791"
        ],
        "name:en": "Quţūr, Jazīrat",
        "id": 7537347
      }
    },
    {
      "geometry": {
        "type": "Point",
        "coordinates": [
          30.95,
          30.966667
        ]
      },
      "type": "Feature",
      "properties": {
        "hierarchy": [
          "tgn:7537348",
          "tgn:7001242",
          "tgn:7016833",
          "tgn:7001312",
          "tgn:7029392"
        ],
        "placetype": [
          "aat:300007783"
        ],
        "name:en": "Quţūr",
        "id": 7537348
      }
    }
  ]
}
