{
  "type": "FeatureCollection",
  "features": [
    {
      "geometry": {
        "type": "Point",
        "coordinates": [
          140.9167,
          53.4
        ]
      },
      "type": "Feature",
      "properties": {
        "hierarchy": [
          "tgn:1052960",
          "tgn:1000004",
          "tgn:7014474",
          "tgn:7018214",
          "tgn:7002435",
          "tgn:7029392"
        ],
        "placetype": [
          "aat:300008347"
        ],
        "id": 1052960,
        "name:xx": "Bol'šoj Vlasjevo"
      }
    },
    {
      "geometry": {
        "type": "Point",
        "coordinates": [
          48.6,
          55.05
        ]
      },
      "type": "Feature",
      "properties": {
        "hierarchy": [
          "tgn:1052961",
          "tgn:1000004",
          "tgn:7002435",
          "tgn:7011524",
          "tgn:7029392"
        ],
        "placetype": [
          "aat:300008347"
        ],
        "id": 1052961,
        "name:xx": "Bol'shoye Shemyakino"
      }
    },
    {
      "geometry": {
        "type": "Point",
        "coordinates": [
          38.95,
          54.5833
        ]
      },
      "type": "Feature",
      "properties": {
        "hierarchy": [
          "tgn:1052962",
          "tgn:1000004",
          "tgn:1003404",
          "tgn:7018214",
          "tgn:7002435",
          "tgn:7029392"
        ],
        "placetype": [
          "aat:300008347"
        ],
        "id": 1052962,
        "name:xx": "Bol'šoje Žokovo"
      }
    },
    {
      "geometry": {
        "type": "Point",
        "coordinates": [
          79.5833,
          43.3333
        ]
      },
      "type": "Feature",
      "properties": {
        "hierarchy": [
          "tgn:1052963",
          "tgn:1003353",
          "tgn:1000004",
          "tgn:7014786",
          "tgn:7029392"
        ],
        "placetype": [
          "aat:300008347"
        ],
        "id": 1052963,
        "name:xx": "Bol'šoje Aksu"
      }
    },
    {
      "geometry": {
        "type": "Point",
        "coordinates": [
          38.2,
          55.25
        ]
      },
      "type": "Feature",
      "properties": {
        "hierarchy": [
          "tgn:1052964",
          "tgn:1000004",
          "tgn:7011573",
          "tgn:7018214",
          "tgn:7002435",
          "tgn:7029392"
        ],
        "placetype": [
          "aat:300008347"
        ],
        "id": 1052964,
        "name:xx": "Alekseyevskoye"
      }
    },
    {
      "geometry": {
        "type": "Point",
        "coordinates": [
          45.2833,
          55
        ]
      },
      "type": "Feature",
      "properties": {
        "hierarchy": [
          "tgn:1052965",
          "tgn:1000004",
          "tgn:7011585",
          "tgn:7018214",
          "tgn:7002435",
          "tgn:7029392"
        ],
        "placetype": [
          "aat:300008347"
        ],
        "id": 1052965,
        "name:xx": "Bol'shoye Boldino"
      }
    },
    {
      "geometry": {
        "type": "Point",
        "coordinates": [
          38.6167,
          55.85
        ]
      },
      "type": "Feature",
      "properties": {
        "hierarchy": [
          "tgn:1052966",
          "tgn:1000004",
          "tgn:7011573",
          "tgn:7018214",
          "tgn:7002435",
          "tgn:7029392"
        ],
        "placetype": [
          "aat:300008347"
        ],
        "id": 1052966,
        "name:xx": "Bol'shoye Bun'kovo"
      }
    },
    {
      "geometry": {
        "type": "Point",
        "coordinates": [
          105.4167,
          52.0833
        ]
      },
      "type": "Feature",
      "properties": {
        "hierarchy": [
          "tgn:1052967",
          "tgn:1003373",
          "tgn:1000004",
          "tgn:7018214",
          "tgn:7002435",
          "tgn:7029392"
        ],
        "placetype": [
          "aat:300008347"
        ],
        "id": 1052967,
        "name:xx": "Bol'shoye Goloustnoye"
      }
    },
    {
      "geometry": {
        "type": "Point",
        "coordinates": [
          37.1,
          50.6333
        ]
      },
      "type": "Feature",
      "properties": {
        "hierarchy": [
          "tgn:1052968",
          "tgn:6000729",
          "tgn:1000004",
          "tgn:7018214",
          "tgn:7002435",
          "tgn:7029392"
        ],
        "placetype": [
          "aat:300008347"
        ],
        "id": 1052968,
        "name:xx": "Bol'shoye Gorodishche"
      }
    },
    {
      "geometry": {
        "type": "Point",
        "coordinates": [
          45.5167,
          55.0167
        ]
      },
      "type": "Feature",
      "properties": {
        "hierarchy": [
          "tgn:1052969",
          "tgn:1000004",
          "tgn:7011523",
          "tgn:7002435",
          "tgn:7029392"
        ],
        "placetype": [
          "aat:300008347"
        ],
        "id": 1052969,
        "name:xx": "Bol'shoye Ignatovo"
      }
    }
  ]
}
