{
  "geometry": {
    "type": "Point",
    "coordinates": [
      -94.8667,
      32.0833
    ]
  },
  "type": "Feature",
  "properties": {
    "hierarchy": [
      "tgn:2104781",
      "tgn:1000001",
      "tgn:7012149",
      "tgn:1002839",
      "tgn:7007826",
      "tgn:7029392"
    ],
    "placetype": [
      "aat:300008347",
      "aat:300387210"
    ],
    "id": 2104781,
    "name:xx": "Hickey"
  }
}
