{
  "geometry": {
    "type": "Point",
    "coordinates": [
      38.6167,
      55.9333
    ]
  },
  "type": "Feature",
  "properties": {
    "hierarchy": [
      "tgn:1060311",
      "tgn:1000004",
      "tgn:7011573",
      "tgn:7018214",
      "tgn:7002435",
      "tgn:7029392"
    ],
    "placetype": [
      "aat:300008347"
    ],
    "id": 1060311,
    "name:xx": "Timkovo"
  }
}
