{
  "geometry": {
    "type": "Point",
    "coordinates": [
      35.3667,
      32.9333
    ]
  },
  "type": "Feature",
  "properties": {
    "hierarchy": [
      "tgn:1079607",
      "tgn:7000249",
      "tgn:1000004",
      "tgn:1000119",
      "tgn:7029392"
    ],
    "placetype": [
      "aat:300008347"
    ],
    "id": 1079607,
    "name:xx": "Rama"
  }
}
