{
  "geometry": {
    "type": "Point",
    "coordinates": [
      5.95,
      48.45
    ]
  },
  "type": "Feature",
  "properties": {
    "hierarchy": [
      "tgn:1033081",
      "tgn:1000003",
      "tgn:7002883",
      "tgn:1000070",
      "tgn:7029392"
    ],
    "placetype": [
      "aat:300008347"
    ],
    "id": 1033081,
    "name:xx": "Favières"
  }
}
