{
  "geometry": {
    "type": "Point",
    "coordinates": [
      -100.3667,
      33.3167
    ]
  },
  "type": "Feature",
  "properties": {
    "hierarchy": [
      "tgn:2544562",
      "tgn:1000001",
      "tgn:7012149",
      "tgn:2002078",
      "tgn:7007826",
      "tgn:7029392"
    ],
    "placetype": [
      "aat:300008761"
    ],
    "id": 2544562,
    "name:xx": "North Camp Hollow"
  }
}
