{
  "geometry": {
    "type": "Point",
    "coordinates": [
      -86.2833,
      39.6333
    ]
  },
  "type": "Feature",
  "properties": {
    "hierarchy": [
      "tgn:2602524",
      "tgn:1000001",
      "tgn:7012149",
      "tgn:7007252",
      "tgn:7029392"
    ],
    "placetype": [
      "aat:300008699"
    ],
    "id": 2602524,
    "name:xx": "Quack Branch"
  }
}
