{
  "geometry": {
    "type": "Point",
    "coordinates": [
      -109.4667,
      45.3333
    ]
  },
  "type": "Feature",
  "properties": {
    "hierarchy": [
      "tgn:2572232",
      "tgn:1000001",
      "tgn:2001264",
      "tgn:7012149",
      "tgn:7007524",
      "tgn:7029392"
    ],
    "placetype": [
      "aat:300006075"
    ],
    "id": 2572232,
    "name:xx": "Peabody Ditch"
  }
}
