{
  "geometry": {
    "type": "Point",
    "coordinates": [
      -85.4833,
      42.6167
    ]
  },
  "type": "Feature",
  "properties": {
    "hierarchy": [
      "tgn:2772892",
      "tgn:1002166",
      "tgn:1000001",
      "tgn:7012149",
      "tgn:7007520",
      "tgn:7029392"
    ],
    "placetype": [
      "aat:300008680"
    ],
    "id": 2772892,
    "name:xx": "Williams Lake"
  }
}
