{
  "geometry": {
    "type": "Point",
    "coordinates": [
      -121.2167,
      41.8167
    ]
  },
  "type": "Feature",
  "properties": {
    "hierarchy": [
      "tgn:2243195",
      "tgn:1000001",
      "tgn:7012149",
      "tgn:7007157",
      "tgn:2000186",
      "tgn:7029392"
    ],
    "placetype": [
      "aat:300386831"
    ],
    "id": 2243195,
    "name:xx": "Clear Lake Hills"
  }
}
