{
  "geometry": {
    "type": "Point",
    "coordinates": [
      -75.1667,
      38.2167
    ]
  },
  "type": "Feature",
  "properties": {
    "hierarchy": [
      "tgn:2364148",
      "tgn:1000001",
      "tgn:1003037",
      "tgn:7012149",
      "tgn:7007516",
      "tgn:7029392"
    ],
    "placetype": [
      "aat:300008850"
    ],
    "id": 2364148,
    "name:xx": "Green Point"
  }
}
