{
  "geometry": {
    "type": "Point",
    "coordinates": [
      31.666667,
      31.25
    ]
  },
  "type": "Feature",
  "properties": {
    "hierarchy": [
      "tgn:7529321",
      "tgn:7001242",
      "tgn:7016833",
      "tgn:1001225",
      "tgn:7029392"
    ],
    "placetype": [
      "aat:300266755"
    ],
    "name:en": "Tall al Kāshif",
    "id": 7529321
  }
}
