{
  "geometry": {
    "type": "Point",
    "coordinates": [
      -84.1833,
      34.6167
    ]
  },
  "type": "Feature",
  "properties": {
    "hierarchy": [
      "tgn:2146024",
      "tgn:1000001",
      "tgn:7012149",
      "tgn:7007248",
      "tgn:7029392"
    ],
    "placetype": [
      "aat:300008798"
    ],
    "id": 2146024,
    "name:xx": "Ball Mountain"
  }
}
