{
  "geometry": {
    "type": "Point",
    "coordinates": [
      31.428609,
      30.792993
    ]
  },
  "type": "Feature",
  "properties": {
    "hierarchy": [
      "tgn:7534879",
      "tgn:7001242",
      "tgn:1001059",
      "tgn:7016833",
      "tgn:7029392"
    ],
    "placetype": [
      "aat:300008347"
    ],
    "name:en": "Kafr Abū Birrī",
    "id": 7534879
  }
}
