{
  "geometry": {
    "type": "Point",
    "coordinates": [
      -105.6167,
      37.7667
    ]
  },
  "type": "Feature",
  "properties": {
    "hierarchy": [
      "tgn:2412190",
      "tgn:1000001",
      "tgn:7012149",
      "tgn:7007158",
      "tgn:2000246",
      "tgn:7029392"
    ],
    "placetype": [
      "aat:300008680"
    ],
    "id": 2412190,
    "name:xx": "Indian Spring"
  }
}
