{
  "geometry": {
    "type": "Point",
    "coordinates": [
      -91.25,
      46.45
    ]
  },
  "type": "Feature",
  "properties": {
    "hierarchy": [
      "tgn:2395592",
      "tgn:2002308",
      "tgn:1000001",
      "tgn:7012149",
      "tgn:7007922",
      "tgn:7029392"
    ],
    "placetype": [
      "aat:300008680"
    ],
    "id": 2395592,
    "name:xx": "Hollibar Lake"
  }
}
