{
  "geometry": {
    "type": "Point",
    "coordinates": [
      -105.8667,
      39.55
    ]
  },
  "type": "Feature",
  "properties": {
    "hierarchy": [
      "tgn:2161337",
      "tgn:1000001",
      "tgn:7012149",
      "tgn:7007158",
      "tgn:2000250",
      "tgn:7029392"
    ],
    "placetype": [
      "aat:300000390"
    ],
    "id": 2161337,
    "name:xx": "Bell Mine"
  }
}
