{
  "type": "FeatureCollection",
  "features": [
    {
      "geometry": {
        "type": "Point",
        "coordinates": [
          9.2,
          48.733333
        ]
      },
      "type": "Feature",
      "properties": {
        "hierarchy": [
          "tgn:7095861",
          "tgn:7003692",
          "tgn:1000003",
          "tgn:7000084",
          "tgn:7029392"
        ],
        "placetype": [
          "aat:300008347"
        ],
        "id": 7095861,
        "name:xx": "Schönberg"
      }
    },
    {
      "geometry": {
        "type": "Point",
        "coordinates": [
          13.766667,
          48.683333
        ]
      },
      "type": "Feature",
      "properties": {
        "hierarchy": [
          "tgn:7095862",
          "tgn:7003669",
          "tgn:1000003",
          "tgn:7000084",
          "tgn:7029392"
        ],
        "placetype": [
          "aat:300008347"
        ],
        "id": 7095862,
        "name:xx": "Schönberg"
      }
    },
    {
      "geometry": {
        "type": "Point",
        "coordinates": [
          11.4,
          48.516667
        ]
      },
      "type": "Feature",
      "properties": {
        "hierarchy": [
          "tgn:7095863",
          "tgn:7003669",
          "tgn:1000003",
          "tgn:7000084",
          "tgn:7029392"
        ],
        "placetype": [
          "aat:300008347"
        ],
        "id": 7095863,
        "name:xx": "Schönberg"
      }
    },
    {
      "geometry": {
        "type": "Point",
        "coordinates": [
          7.983333,
          48.316667
        ]
      },
      "type": "Feature",
      "properties": {
        "hierarchy": [
          "tgn:7095864",
          "tgn:7003692",
          "tgn:1000003",
          "tgn:7000084",
          "tgn:7029392"
        ],
        "placetype": [
          "aat:300008347"
        ],
        "id": 7095864,
        "name:xx": "Schönberg"
      }
    },
    {
      "geometry": {
        "type": "Point",
        "coordinates": [
          12.433333,
          48.333333
        ]
      },
      "type": "Feature",
      "properties": {
        "hierarchy": [
          "tgn:7095865",
          "tgn:7003669",
          "tgn:1000003",
          "tgn:7000084",
          "tgn:7029392"
        ],
        "placetype": [
          "aat:300008347"
        ],
        "id": 7095865,
        "name:xx": "Schönberg"
      }
    },
    {
      "geometry": {
        "type": "Point",
        "coordinates": [
          12.283333,
          48.066667
        ]
      },
      "type": "Feature",
      "properties": {
        "hierarchy": [
          "tgn:7095866",
          "tgn:7003669",
          "tgn:1000003",
          "tgn:7000084",
          "tgn:7029392"
        ],
        "placetype": [
          "aat:300008347"
        ],
        "id": 7095866,
        "name:xx": "Schönberg"
      }
    },
    {
      "geometry": {
        "type": "Point",
        "coordinates": [
          12.5,
          48.05
        ]
      },
      "type": "Feature",
      "properties": {
        "hierarchy": [
          "tgn:7095867",
          "tgn:7003669",
          "tgn:1000003",
          "tgn:7000084",
          "tgn:7029392"
        ],
        "placetype": [
          "aat:300008347"
        ],
        "id": 7095867,
        "name:xx": "Schönberg"
      }
    },
    {
      "geometry": {
        "type": "Point",
        "coordinates": [
          11.8,
          47.766667
        ]
      },
      "type": "Feature",
      "properties": {
        "hierarchy": [
          "tgn:7095868",
          "tgn:7003669",
          "tgn:1000003",
          "tgn:7000084",
          "tgn:7029392"
        ],
        "placetype": [
          "aat:300008347"
        ],
        "id": 7095868,
        "name:xx": "Schönberg"
      }
    },
    {
      "geometry": {
        "type": "Point",
        "coordinates": [
          10.983333,
          47.716667
        ]
      },
      "type": "Feature",
      "properties": {
        "hierarchy": [
          "tgn:7095869",
          "tgn:7003669",
          "tgn:1000003",
          "tgn:7000084",
          "tgn:7029392"
        ],
        "placetype": [
          "aat:300008347"
        ],
        "id": 7095869,
        "name:xx": "Schönberg"
      }
    }
  ]
}
