{
  "geometry": {
    "type": "Point",
    "coordinates": [
      -99.5833,
      37.2833
    ]
  },
  "type": "Feature",
  "properties": {
    "hierarchy": [
      "tgn:2446724",
      "tgn:1000001",
      "tgn:2000672",
      "tgn:7012149",
      "tgn:7007254",
      "tgn:7029392"
    ],
    "placetype": [
      "aat:300008347"
    ],
    "id": 2446724,
    "name:xx": "Lexington"
  }
}
