{
  "geometry": {
    "type": "Point",
    "coordinates": [
      -109.5167,
      40.45
    ]
  },
  "type": "Feature",
  "properties": {
    "hierarchy": [
      "tgn:2109353",
      "tgn:1000001",
      "tgn:7012149",
      "tgn:2002124",
      "tgn:7007827",
      "tgn:7029392"
    ],
    "placetype": [
      "aat:300008347"
    ],
    "id": 2109353,
    "name:xx": "Vernal"
  }
}
