{
  "geometry": {
    "type": "Point",
    "coordinates": [
      -100.3667,
      45.65
    ]
  },
  "type": "Feature",
  "properties": {
    "hierarchy": [
      "tgn:2627825",
      "tgn:1000001",
      "tgn:2001780",
      "tgn:7012149",
      "tgn:7007713",
      "tgn:7029392"
    ],
    "placetype": [
      "aat:300132316"
    ],
    "id": 2627825,
    "name:xx": "Rogo Bay"
  }
}
