{
  "geometry": {
    "type": "Point",
    "coordinates": [
      -1.1667,
      5.3333
    ]
  },
  "type": "Feature",
  "properties": {
    "hierarchy": [
      "tgn:1090115",
      "tgn:1001653",
      "tgn:7001242",
      "tgn:1000166",
      "tgn:7029392"
    ],
    "placetype": [
      "aat:300008347",
      "aat:300008375"
    ],
    "id": 1090115,
    "name:xx": "Dunkwa"
  }
}
