{
  "geometry": {
    "type": "Point",
    "coordinates": [
      -102.5667,
      35.0833
    ]
  },
  "type": "Feature",
  "properties": {
    "hierarchy": [
      "tgn:2562881",
      "tgn:1000001",
      "tgn:7012149",
      "tgn:2001972",
      "tgn:7007826",
      "tgn:7029392"
    ],
    "placetype": [
      "aat:300008680"
    ],
    "id": 2562881,
    "name:xx": "Overstreet Lake"
  }
}
