{
  "geometry": {
    "type": "Point",
    "coordinates": [
      43.2833,
      51.6667
    ]
  },
  "type": "Feature",
  "properties": {
    "hierarchy": [
      "tgn:1052948",
      "tgn:1000004",
      "tgn:1003408",
      "tgn:7018214",
      "tgn:7002435",
      "tgn:7029392"
    ],
    "placetype": [
      "aat:300008347"
    ],
    "id": 1052948,
    "name:xx": "Bol'shoy Melik"
  }
}
