{
  "geometry": {
    "type": "Point",
    "coordinates": [
      -60.3333,
      -32.0833
    ]
  },
  "type": "Feature",
  "properties": {
    "hierarchy": [
      "tgn:1019369",
      "tgn:7006477",
      "tgn:1001237",
      "tgn:1000002",
      "tgn:7029392"
    ],
    "placetype": [
      "aat:300008347"
    ],
    "id": 1019369,
    "name:xx": "Crespo"
  }
}
