{
  "geometry": {
    "type": "Point",
    "coordinates": [
      -120.7833,
      40.8667
    ]
  },
  "type": "Feature",
  "properties": {
    "hierarchy": [
      "tgn:2254268",
      "tgn:1000001",
      "tgn:7012149",
      "tgn:7007157",
      "tgn:2000184",
      "tgn:7029392"
    ],
    "placetype": [
      "aat:300008697"
    ],
    "id": 2254268,
    "name:xx": "Coon Camp Spring"
  }
}
