{
  "geometry": {
    "type": "Point",
    "coordinates": [
      -8.8333,
      31.1667
    ]
  },
  "type": "Feature",
  "properties": {
    "hierarchy": [
      "tgn:1091391",
      "tgn:7001242",
      "tgn:7593677",
      "tgn:1000179",
      "tgn:7029392"
    ],
    "placetype": [
      "aat:300008347"
    ],
    "id": 1091391,
    "name:xx": "Imi-n-Tanoute"
  }
}
