{
  "geometry": {
    "type": "Point",
    "coordinates": [
      -76.8167,
      37.2833
    ]
  },
  "type": "Feature",
  "properties": {
    "hierarchy": [
      "tgn:2750661",
      "tgn:1000001",
      "tgn:7012149",
      "tgn:1002511",
      "tgn:7007919",
      "tgn:7029392"
    ],
    "placetype": [
      "aat:300006191"
    ],
    "id": 2750661,
    "name:xx": "Warburton Pond"
  }
}
