{
  "type": "FeatureCollection",
  "features": [
    {
      "geometry": {
        "type": "Point",
        "coordinates": [
          3.949557,
          50.891894
        ]
      },
      "type": "Feature",
      "properties": {
        "hierarchy": [
          "tgn:7247330",
          "tgn:7003457",
          "tgn:1000003",
          "tgn:1000063",
          "tgn:7018236",
          "tgn:7029392"
        ],
        "placetype": [
          "aat:300008347"
        ],
        "id": 7247330,
        "name:xx": "Dries"
      }
    },
    {
      "geometry": {
        "type": "Point",
        "coordinates": [
          3.545048,
          50.828553
        ]
      },
      "type": "Feature",
      "properties": {
        "hierarchy": [
          "tgn:7247332",
          "tgn:7003457",
          "tgn:1000003",
          "tgn:1000063",
          "tgn:7018236",
          "tgn:7029392"
        ],
        "placetype": [
          "aat:300008347"
        ],
        "id": 7247332,
        "name:xx": "Dries"
      }
    },
    {
      "geometry": {
        "type": "Point",
        "coordinates": [
          3.833333,
          50.783333
        ]
      },
      "type": "Feature",
      "properties": {
        "hierarchy": [
          "tgn:7247334",
          "tgn:7003457",
          "tgn:1000003",
          "tgn:1000063",
          "tgn:7018236",
          "tgn:7029392"
        ],
        "placetype": [
          "aat:300008347"
        ],
        "id": 7247334,
        "name:xx": "Dries"
      }
    },
    {
      "geometry": {
        "type": "Point",
        "coordinates": [
          3.363894,
          50.756933
        ]
      },
      "type": "Feature",
      "properties": {
        "hierarchy": [
          "tgn:7247335",
          "tgn:7003458",
          "tgn:1000003",
          "tgn:1000063",
          "tgn:7018236",
          "tgn:7029392"
        ],
        "placetype": [
          "aat:300008347"
        ],
        "id": 7247335,
        "name:xx": "Dries"
      }
    },
    {
      "geometry": {
        "type": "Point",
        "coordinates": [
          3.983333,
          50.616667
        ]
      },
      "type": "Feature",
      "properties": {
        "hierarchy": [
          "tgn:7247337",
          "tgn:7007877",
          "tgn:1000003",
          "tgn:1000063",
          "tgn:4012014",
          "tgn:7029392"
        ],
        "placetype": [
          "aat:300000206"
        ],
        "id": 7247337,
        "name:xx": "Ferme de la Drière"
      }
    },
    {
      "geometry": {
        "type": "Point",
        "coordinates": [
          3.357104,
          51.165595
        ]
      },
      "type": "Feature",
      "properties": {
        "hierarchy": [
          "tgn:7247338",
          "tgn:7003458",
          "tgn:1000003",
          "tgn:1000063",
          "tgn:7018236",
          "tgn:7029392"
        ],
        "placetype": [
          "aat:300008347"
        ],
        "id": 7247338,
        "name:xx": "Drie Pikkels"
      }
    },
    {
      "geometry": {
        "type": "Point",
        "coordinates": [
          3.188972,
          50.854532
        ]
      },
      "type": "Feature",
      "properties": {
        "hierarchy": [
          "tgn:7247339",
          "tgn:7003458",
          "tgn:1000003",
          "tgn:1000063",
          "tgn:7018236",
          "tgn:7029392"
        ],
        "placetype": [
          "aat:300008347"
        ],
        "id": 7247339,
        "name:xx": "Drie Masten"
      }
    }
  ]
}
