{
  "geometry": {
    "type": "Point",
    "coordinates": [
      -95.5167,
      43.4833
    ]
  },
  "type": "Feature",
  "properties": {
    "hierarchy": [
      "tgn:2561696",
      "tgn:1000001",
      "tgn:7012149",
      "tgn:2000632",
      "tgn:7007253",
      "tgn:7029392"
    ],
    "placetype": [
      "aat:300008706"
    ],
    "id": 2561696,
    "name:xx": "Osterman Creek"
  }
}
