{
  "geometry": {
    "type": "Point",
    "coordinates": [
      117.4167,
      23.6667
    ]
  },
  "type": "Feature",
  "properties": {
    "hierarchy": [
      "tgn:1006973",
      "tgn:1000004",
      "tgn:7001796",
      "tgn:1000111",
      "tgn:7029392"
    ],
    "placetype": [
      "aat:300008791"
    ],
    "id": 1006973,
    "name:xx": "Dongshan Dao"
  }
}
