{
  "geometry": {
    "type": "Point",
    "coordinates": [
      -109.1833,
      47.1833
    ]
  },
  "type": "Feature",
  "properties": {
    "hierarchy": [
      "tgn:2270566",
      "tgn:1000001",
      "tgn:7012149",
      "tgn:2001273",
      "tgn:7007524",
      "tgn:7029392"
    ],
    "placetype": [
      "aat:300008798"
    ],
    "id": 2270566,
    "name:xx": "Crystal Peak"
  }
}
