{
  "geometry": {
    "type": "Point",
    "coordinates": [
      -96.95,
      32.5833
    ]
  },
  "type": "Feature",
  "properties": {
    "hierarchy": [
      "tgn:1134335",
      "tgn:1000001",
      "tgn:7012149",
      "tgn:7007826",
      "tgn:7029392"
    ],
    "placetype": [
      "aat:300008706"
    ],
    "id": 1134335,
    "name:xx": "Red Oak Creek"
  }
}
