{
  "geometry": {
    "type": "Point",
    "coordinates": [
      28.675,
      54.89
    ]
  },
  "type": "Feature",
  "properties": {
    "hierarchy": [
      "tgn:1123822",
      "tgn:7011701",
      "tgn:1000003",
      "tgn:7006657",
      "tgn:7029392"
    ],
    "placetype": [
      "aat:300008707"
    ],
    "id": 1123822,
    "name:xx": "Esa"
  }
}
