{
  "geometry": {
    "type": "Point",
    "coordinates": [
      -82.0167,
      35.9167
    ]
  },
  "type": "Feature",
  "properties": {
    "hierarchy": [
      "tgn:2457255",
      "tgn:1000001",
      "tgn:7012149",
      "tgn:2001519",
      "tgn:7007709",
      "tgn:7029392"
    ],
    "placetype": [
      "aat:300008699"
    ],
    "id": 2457255,
    "name:xx": "Little Laurel Branch"
  }
}
