{
  "geometry": {
    "type": "Point",
    "coordinates": [
      -102.6833,
      45.0167
    ]
  },
  "type": "Feature",
  "properties": {
    "hierarchy": [
      "tgn:2228129",
      "tgn:1000001",
      "tgn:2001816",
      "tgn:7012149",
      "tgn:7007713",
      "tgn:7029392"
    ],
    "placetype": [
      "aat:300008347"
    ],
    "id": 2228129,
    "name:xx": "Cedar Canyon"
  }
}
