{
  "geometry": {
    "type": "Point",
    "coordinates": [
      -76.6833,
      38.15
    ]
  },
  "type": "Feature",
  "properties": {
    "hierarchy": [
      "tgn:2387043",
      "tgn:1000001",
      "tgn:7012149",
      "tgn:1003018",
      "tgn:7007919",
      "tgn:7029392"
    ],
    "placetype": [
      "aat:300008680"
    ],
    "id": 2387043,
    "name:xx": "Herring Pond"
  }
}
