{
  "geometry": {
    "type": "Point",
    "coordinates": [
      -75.5667,
      39.6833
    ]
  },
  "type": "Feature",
  "properties": {
    "hierarchy": [
      "tgn:2250496",
      "tgn:7014201",
      "tgn:1000001",
      "tgn:7012149",
      "tgn:7007239",
      "tgn:7029392"
    ],
    "placetype": [
      "aat:300008347"
    ],
    "id": 2250496,
    "name:xx": "Colonial Village Apartments"
  }
}
