{
  "geometry": {
    "type": "Point",
    "coordinates": [
      -121.4333,
      46.1833
    ]
  },
  "type": "Feature",
  "properties": {
    "hierarchy": [
      "tgn:2169798",
      "tgn:1000001",
      "tgn:7012149",
      "tgn:1003042",
      "tgn:7007920",
      "tgn:7029392"
    ],
    "placetype": [
      "aat:300008706"
    ],
    "id": 2169798,
    "name:xx": "Big Muddy Creek"
  }
}
