{
  "geometry": {
    "type": "Point",
    "coordinates": [
      -111.9667,
      41.25
    ]
  },
  "type": "Feature",
  "properties": {
    "hierarchy": [
      "tgn:2560296",
      "tgn:1000001",
      "tgn:7012149",
      "tgn:2002129",
      "tgn:7007827",
      "tgn:7029392"
    ],
    "placetype": [
      "aat:300008347"
    ],
    "id": 2560296,
    "name:xx": "Orchard Grove Addition"
  }
}
