{
  "geometry": {
    "type": "Point",
    "coordinates": [
      -82.4667,
      35.3167
    ]
  },
  "type": "Feature",
  "properties": {
    "hierarchy": [
      "tgn:2475977",
      "tgn:1000001",
      "tgn:7012149",
      "tgn:2001504",
      "tgn:7007709",
      "tgn:7029392"
    ],
    "placetype": [
      "aat:300006191"
    ],
    "id": 2475977,
    "name:xx": "Lugana Lake"
  }
}
