{
  "geometry": {
    "type": "Point",
    "coordinates": [
      125.65,
      10.4667
    ]
  },
  "type": "Feature",
  "properties": {
    "hierarchy": [
      "tgn:1011807",
      "tgn:1006959",
      "tgn:1000004",
      "tgn:1001556",
      "tgn:1000135",
      "tgn:7029392"
    ],
    "placetype": [
      "aat:300386846"
    ],
    "id": 1011807,
    "name:xx": "Desolation Point"
  }
}
