{
  "type": "FeatureCollection",
  "features": [
    {
      "geometry": {
        "type": "Point",
        "coordinates": [
          168,
          -46.583333
        ]
      },
      "type": "Feature",
      "properties": {
        "hierarchy": [
          "tgn:1115130",
          "tgn:1009227",
          "tgn:1000226",
          "tgn:7016822",
          "tgn:1000006",
          "tgn:7029392"
        ],
        "placetype": [
          "aat:300266559"
        ],
        "name:en": "Foveaux Strait",
        "id": 1115130
      }
    },
    {
      "geometry": {
        "type": "Point",
        "coordinates": [
          -96,
          72
        ]
      },
      "type": "Feature",
      "properties": {
        "hierarchy": [
          "tgn:1115131",
          "tgn:7005685",
          "tgn:1000001",
          "tgn:1000296",
          "tgn:7029392"
        ],
        "placetype": [
          "aat:300266559"
        ],
        "id": 1115131,
        "name:xx": "Franklin Strait"
      }
    },
    {
      "geometry": {
        "type": "Point",
        "coordinates": [
          149.1667,
          45.5
        ]
      },
      "type": "Feature",
      "properties": {
        "hierarchy": [
          "tgn:1115132",
          "tgn:7016712",
          "tgn:1000004",
          "tgn:1003406",
          "tgn:7018214",
          "tgn:7002435",
          "tgn:7029392"
        ],
        "placetype": [
          "aat:300266559"
        ],
        "id": 1115132,
        "name:xx": "Friza, Proliv"
      }
    },
    {
      "geometry": {
        "type": "Point",
        "coordinates": [
          -84,
          69.9167
        ]
      },
      "type": "Feature",
      "properties": {
        "hierarchy": [
          "tgn:1115133",
          "tgn:7005685",
          "tgn:1000001",
          "tgn:7024197",
          "tgn:7029392"
        ],
        "placetype": [
          "aat:300266559"
        ],
        "id": 1115133,
        "name:xx": "Fury and Hecla Strait"
      }
    },
    {
      "geometry": {
        "type": "Point",
        "coordinates": [
          -65.6667,
          61.8333
        ]
      },
      "type": "Feature",
      "properties": {
        "hierarchy": [
          "tgn:1115134",
          "tgn:7005685",
          "tgn:1000001",
          "tgn:1000296",
          "tgn:7029392"
        ],
        "placetype": [
          "aat:300266559"
        ],
        "id": 1115134,
        "name:xx": "Gabriel Strait"
      }
    },
    {
      "geometry": {
        "type": "Point",
        "coordinates": [
          -124,
          49.0833
        ]
      },
      "type": "Feature",
      "properties": {
        "hierarchy": [
          "tgn:1115136",
          "tgn:1000001",
          "tgn:7029392"
        ],
        "placetype": [
          "aat:300266559"
        ],
        "id": 1115136,
        "name:xx": "Georgia, Strait of"
      }
    },
    {
      "geometry": {
        "type": "Point",
        "coordinates": [
          -5.6,
          35.95
        ]
      },
      "type": "Feature",
      "properties": {
        "hierarchy": [
          "tgn:1115137",
          "tgn:7029392"
        ],
        "placetype": [
          "aat:300266559"
        ],
        "id": 1115137,
        "name:xx": "Gibraltar, Strait of"
      }
    },
    {
      "geometry": {
        "type": "Point",
        "coordinates": [
          122.7333,
          10.5
        ]
      },
      "type": "Feature",
      "properties": {
        "hierarchy": [
          "tgn:1115139",
          "tgn:1000004",
          "tgn:1000135",
          "tgn:7029392"
        ],
        "placetype": [
          "aat:300266559"
        ],
        "id": 1115139,
        "name:xx": "Guimaras Strait"
      }
    }
  ]
}
