{
  "geometry": {
    "type": "Point",
    "coordinates": [
      -105.0333,
      39.7667
    ]
  },
  "type": "Feature",
  "properties": {
    "hierarchy": [
      "tgn:2164036",
      "tgn:1000001",
      "tgn:7012149",
      "tgn:2000207",
      "tgn:7007158",
      "tgn:7029392"
    ],
    "placetype": [
      "aat:300008680"
    ],
    "id": 2164036,
    "name:xx": "Berkeley Lake"
  }
}
