{
  "type": "FeatureCollection",
  "features": [
    {
      "geometry": {
        "type": "Point",
        "coordinates": [
          -101.283333,
          22.65
        ]
      },
      "type": "Feature",
      "properties": {
        "hierarchy": [
          "tgn:7395500",
          "tgn:1000001",
          "tgn:7005594",
          "tgn:7005560",
          "tgn:7029392"
        ],
        "placetype": [
          "aat:300008347"
        ],
        "id": 7395500,
        "name:xx": "San Antonio"
      }
    },
    {
      "geometry": {
        "type": "Point",
        "coordinates": [
          -101.15,
          22.616667
        ]
      },
      "type": "Feature",
      "properties": {
        "hierarchy": [
          "tgn:7395501",
          "tgn:1000001",
          "tgn:7005594",
          "tgn:7005560",
          "tgn:7029392"
        ],
        "placetype": [
          "aat:300008347"
        ],
        "id": 7395501,
        "name:xx": "San Antonio"
      }
    },
    {
      "geometry": {
        "type": "Point",
        "coordinates": [
          -99.266667,
          22.616667
        ]
      },
      "type": "Feature",
      "properties": {
        "hierarchy": [
          "tgn:7395502",
          "tgn:1000001",
          "tgn:7005597",
          "tgn:7005560",
          "tgn:7029392"
        ],
        "placetype": [
          "aat:300008347"
        ],
        "id": 7395502,
        "name:xx": "San Antonio"
      }
    },
    {
      "geometry": {
        "type": "Point",
        "coordinates": [
          -103.833333,
          22.55
        ]
      },
      "type": "Feature",
      "properties": {
        "hierarchy": [
          "tgn:7395503",
          "tgn:1000001",
          "tgn:7005601",
          "tgn:7005560",
          "tgn:7029392"
        ],
        "placetype": [
          "aat:300008347"
        ],
        "id": 7395503,
        "name:xx": "San Antonio"
      }
    },
    {
      "geometry": {
        "type": "Point",
        "coordinates": [
          -105.333333,
          22.383333
        ]
      },
      "type": "Feature",
      "properties": {
        "hierarchy": [
          "tgn:7395504",
          "tgn:1000001",
          "tgn:1001906",
          "tgn:7005560",
          "tgn:7029392"
        ],
        "placetype": [
          "aat:300008347"
        ],
        "id": 7395504,
        "name:xx": "San Antonio"
      }
    },
    {
      "geometry": {
        "type": "Point",
        "coordinates": [
          -101.5,
          22.3
        ]
      },
      "type": "Feature",
      "properties": {
        "hierarchy": [
          "tgn:7395505",
          "tgn:1000001",
          "tgn:7005601",
          "tgn:7005560",
          "tgn:7029392"
        ],
        "placetype": [
          "aat:300008347"
        ],
        "id": 7395505,
        "name:xx": "San Antonio"
      }
    },
    {
      "geometry": {
        "type": "Point",
        "coordinates": [
          -102.25,
          22.216667
        ]
      },
      "type": "Feature",
      "properties": {
        "hierarchy": [
          "tgn:7395506",
          "tgn:7005579",
          "tgn:1000001",
          "tgn:7005560",
          "tgn:7029392"
        ],
        "placetype": [
          "aat:300008347"
        ],
        "id": 7395506,
        "name:xx": "San Antonio"
      }
    },
    {
      "geometry": {
        "type": "Point",
        "coordinates": [
          -102.166667,
          22.1
        ]
      },
      "type": "Feature",
      "properties": {
        "hierarchy": [
          "tgn:7395508",
          "tgn:7005579",
          "tgn:1000001",
          "tgn:7005560",
          "tgn:7029392"
        ],
        "placetype": [
          "aat:300008347"
        ],
        "id": 7395508,
        "name:xx": "San Antonio"
      }
    },
    {
      "geometry": {
        "type": "Point",
        "coordinates": [
          -101.366667,
          22.033333
        ]
      },
      "type": "Feature",
      "properties": {
        "hierarchy": [
          "tgn:7395509",
          "tgn:1000001",
          "tgn:7005594",
          "tgn:7005560",
          "tgn:7029392"
        ],
        "placetype": [
          "aat:300008347"
        ],
        "id": 7395509,
        "name:xx": "San Antonio"
      }
    }
  ]
}
