{
  "type": "FeatureCollection",
  "features": [
    {
      "geometry": {
        "type": "Point",
        "coordinates": [
          -84.35,
          37.0667
        ]
      },
      "type": "Feature",
      "properties": {
        "hierarchy": [
          "tgn:2585740",
          "tgn:1000001",
          "tgn:7012149",
          "tgn:2000839",
          "tgn:7007255",
          "tgn:7029392"
        ],
        "placetype": [
          "aat:300008761"
        ],
        "id": 2585740,
        "name:xx": "Pipe Line Hollow"
      }
    },
    {
      "geometry": {
        "type": "Point",
        "coordinates": [
          -77.65,
          41.5667
        ]
      },
      "type": "Feature",
      "properties": {
        "hierarchy": [
          "tgn:2585741",
          "tgn:1000001",
          "tgn:7012149",
          "tgn:1002800",
          "tgn:7007710",
          "tgn:7029392"
        ],
        "placetype": [
          "aat:300008761"
        ],
        "id": 2585741,
        "name:xx": "Pipe Line Hollow"
      }
    },
    {
      "geometry": {
        "type": "Point",
        "coordinates": [
          -81.1667,
          32.1
        ]
      },
      "type": "Feature",
      "properties": {
        "hierarchy": [
          "tgn:2585742",
          "tgn:1000001",
          "tgn:2000316",
          "tgn:7012149",
          "tgn:7007248",
          "tgn:7029392"
        ],
        "placetype": [
          "aat:300006075"
        ],
        "id": 2585742,
        "name:xx": "Pipe Makers Canal"
      }
    },
    {
      "geometry": {
        "type": "Point",
        "coordinates": [
          -82.4,
          37.8
        ]
      },
      "type": "Feature",
      "properties": {
        "hierarchy": [
          "tgn:2585743",
          "tgn:1000001",
          "tgn:7012149",
          "tgn:2000824",
          "tgn:7007255",
          "tgn:7029392"
        ],
        "placetype": [
          "aat:300008699"
        ],
        "id": 2585743,
        "name:xx": "Pipe Mud Branch"
      }
    },
    {
      "geometry": {
        "type": "Point",
        "coordinates": [
          -109.3833,
          42.9333
        ]
      },
      "type": "Feature",
      "properties": {
        "hierarchy": [
          "tgn:2585745",
          "tgn:1000001",
          "tgn:7012149",
          "tgn:2002371",
          "tgn:7007923",
          "tgn:7029392"
        ],
        "placetype": [
          "aat:300008798"
        ],
        "id": 2585745,
        "name:xx": "Pipe Organ"
      }
    },
    {
      "geometry": {
        "type": "Point",
        "coordinates": [
          -116.8833,
          38.7
        ]
      },
      "type": "Feature",
      "properties": {
        "hierarchy": [
          "tgn:2585746",
          "tgn:1000001",
          "tgn:2001418",
          "tgn:7012149",
          "tgn:7007526",
          "tgn:7029392"
        ],
        "placetype": [
          "aat:300008697"
        ],
        "id": 2585746,
        "name:xx": "Pipe Organ Spring"
      }
    },
    {
      "geometry": {
        "type": "Point",
        "coordinates": [
          -105.6,
          44.1667
        ]
      },
      "type": "Feature",
      "properties": {
        "hierarchy": [
          "tgn:2585747",
          "tgn:1000001",
          "tgn:2002367",
          "tgn:7012149",
          "tgn:7007923",
          "tgn:7029392"
        ],
        "placetype": [
          "aat:300006191"
        ],
        "id": 2585747,
        "name:xx": "Pipe Reservoir"
      }
    },
    {
      "geometry": {
        "type": "Point",
        "coordinates": [
          -87.3,
          35.8167
        ]
      },
      "type": "Feature",
      "properties": {
        "hierarchy": [
          "tgn:2585748",
          "tgn:1000001",
          "tgn:7012149",
          "tgn:7015666",
          "tgn:7007825",
          "tgn:7029392"
        ],
        "placetype": [
          "aat:300266640"
        ],
        "id": 2585748,
        "name:xx": "Pipe Ridge"
      }
    },
    {
      "geometry": {
        "type": "Point",
        "coordinates": [
          -86.6167,
          37.6333
        ]
      },
      "type": "Feature",
      "properties": {
        "hierarchy": [
          "tgn:2585749",
          "tgn:1000001",
          "tgn:2000773",
          "tgn:7012149",
          "tgn:7007255",
          "tgn:7029392"
        ],
        "placetype": [
          "aat:300008699"
        ],
        "id": 2585749,
        "name:xx": "Pipe Run"
      }
    }
  ]
}
