{
  "geometry": {
    "type": "Point",
    "coordinates": [
      -110.5667,
      45.0333
    ]
  },
  "type": "Feature",
  "properties": {
    "hierarchy": [
      "tgn:2560644",
      "tgn:1000001",
      "tgn:7012149",
      "tgn:2001293",
      "tgn:7007524",
      "tgn:7029392"
    ],
    "placetype": [
      "aat:300008798"
    ],
    "id": 2560644,
    "name:xx": "Oregon Mountain"
  }
}
