{
  "geometry": {
    "type": "Point",
    "coordinates": [
      -110.6167,
      37.85
    ]
  },
  "type": "Feature",
  "properties": {
    "hierarchy": [
      "tgn:2781701",
      "tgn:1000001",
      "tgn:2002109",
      "tgn:7012149",
      "tgn:7007827",
      "tgn:7029392"
    ],
    "placetype": [
      "aat:300008697"
    ],
    "id": 2781701,
    "name:xx": "Woodruff Spring"
  }
}
