{
  "type": "FeatureCollection",
  "features": [
    {
      "geometry": {
        "type": "Point",
        "coordinates": [
          -90.033333,
          20.133333
        ]
      },
      "type": "Feature",
      "properties": {
        "hierarchy": [
          "tgn:7360370",
          "tgn:7005578",
          "tgn:1000001",
          "tgn:7005560",
          "tgn:7029392"
        ],
        "placetype": [
          "aat:300008347"
        ],
        "id": 7360370,
        "name:xx": "Dzitnup"
      }
    },
    {
      "geometry": {
        "type": "Point",
        "coordinates": [
          -89.4,
          20.783333
        ]
      },
      "type": "Feature",
      "properties": {
        "hierarchy": [
          "tgn:7360371",
          "tgn:1000001",
          "tgn:7005600",
          "tgn:7005560",
          "tgn:7029392"
        ],
        "placetype": [
          "aat:300008347"
        ],
        "id": 7360371,
        "name:xx": "Dzitiná"
      }
    },
    {
      "geometry": {
        "type": "Point",
        "coordinates": [
          -88.533333,
          20.833333
        ]
      },
      "type": "Feature",
      "properties": {
        "hierarchy": [
          "tgn:7360373",
          "tgn:1000001",
          "tgn:7005600",
          "tgn:7005560",
          "tgn:7029392"
        ],
        "placetype": [
          "aat:300007783"
        ],
        "id": 7360373,
        "name:xx": "Estación Dzitás"
      }
    },
    {
      "geometry": {
        "type": "Point",
        "coordinates": [
          -89.283333,
          21.05
        ]
      },
      "type": "Feature",
      "properties": {
        "hierarchy": [
          "tgn:7360375",
          "tgn:1000001",
          "tgn:7005600",
          "tgn:7005560",
          "tgn:7029392"
        ],
        "placetype": [
          "aat:300008347"
        ],
        "id": 7360375,
        "name:xx": "Dzina"
      }
    },
    {
      "geometry": {
        "type": "Point",
        "coordinates": [
          -88.8,
          21.433333
        ]
      },
      "type": "Feature",
      "properties": {
        "hierarchy": [
          "tgn:7360378",
          "tgn:1000001",
          "tgn:7005600",
          "tgn:7005560",
          "tgn:7029392"
        ],
        "placetype": [
          "aat:300185707"
        ],
        "id": 7360378,
        "name:xx": "Dzilam, Boca de"
      }
    },
    {
      "geometry": {
        "type": "Point",
        "coordinates": [
          -88.333333,
          21.3
        ]
      },
      "type": "Feature",
      "properties": {
        "hierarchy": [
          "tgn:7360379",
          "tgn:1000001",
          "tgn:7005600",
          "tgn:7005560",
          "tgn:7029392"
        ],
        "placetype": [
          "aat:300008347"
        ],
        "id": 7360379,
        "name:xx": "Dzidzya"
      }
    }
  ]
}
