{
  "geometry": {
    "type": "Point",
    "coordinates": [
      134.9167,
      33.9167
    ]
  },
  "type": "Feature",
  "properties": {
    "hierarchy": [
      "tgn:1114173",
      "tgn:1000004",
      "tgn:1000120",
      "tgn:7029392"
    ],
    "placetype": [
      "aat:300008713"
    ],
    "id": 1114173,
    "name:xx": "Kii-suidō"
  }
}
