{
  "geometry": {
    "type": "Point",
    "coordinates": [
      76.133333,
      16.333333
    ]
  },
  "type": "Feature",
  "properties": {
    "hierarchy": [
      "tgn:7552781",
      "tgn:1000004",
      "tgn:7000198",
      "tgn:1001882",
      "tgn:7029392"
    ],
    "placetype": [
      "aat:300008347"
    ],
    "name:en": "Muddebihāl",
    "id": 7552781
  }
}
