{
  "geometry": {
    "type": "Point",
    "coordinates": [
      9.75,
      45.75
    ]
  },
  "type": "Feature",
  "properties": {
    "hierarchy": [
      "tgn:1045650",
      "tgn:7005023",
      "tgn:1000003",
      "tgn:7003237",
      "tgn:1000080",
      "tgn:7029392"
    ],
    "placetype": [
      "aat:300008347"
    ],
    "id": 1045650,
    "name:xx": "Nembro"
  }
}
