{
  "geometry": {
    "type": "Point",
    "coordinates": [
      -100.4167,
      31.4667
    ]
  },
  "type": "Feature",
  "properties": {
    "hierarchy": [
      "tgn:2131645",
      "tgn:1000001",
      "tgn:7012149",
      "tgn:2002085",
      "tgn:7007826",
      "tgn:7029392"
    ],
    "placetype": [
      "aat:300008347"
    ],
    "id": 2131645,
    "name:xx": "Alvery Junction"
  }
}
