{
  "geometry": {
    "type": "Point",
    "coordinates": [
      -104.4333,
      42.2667
    ]
  },
  "type": "Feature",
  "properties": {
    "hierarchy": [
      "tgn:2667351",
      "tgn:1000001",
      "tgn:7012149",
      "tgn:2002372",
      "tgn:7007923",
      "tgn:7029392"
    ],
    "placetype": [
      "aat:300006191"
    ],
    "id": 2667351,
    "name:xx": "Skinner Reservoir"
  }
}
