{
  "geometry": {
    "type": "Point",
    "coordinates": [
      78.72144,
      29.952189
    ]
  },
  "type": "Feature",
  "properties": {
    "hierarchy": [
      "tgn:7569716",
      "tgn:1000004",
      "tgn:7000198",
      "tgn:7031786",
      "tgn:7029392"
    ],
    "placetype": [
      "aat:300008347"
    ],
    "name:en": "Hairākholi",
    "id": 7569716
  }
}
