{
  "geometry": {
    "type": "Point",
    "coordinates": [
      123.6833,
      13.25
    ]
  },
  "type": "Feature",
  "properties": {
    "hierarchy": [
      "tgn:1107717",
      "tgn:1001094",
      "tgn:1000004",
      "tgn:1000135",
      "tgn:7029392"
    ],
    "placetype": [
      "aat:300132325"
    ],
    "id": 1107717,
    "name:xx": "Mayon Volcano"
  }
}
