{
  "geometry": {
    "type": "Point",
    "coordinates": [
      116.5333,
      29.8833
    ]
  },
  "type": "Feature",
  "properties": {
    "hierarchy": [
      "tgn:1070837",
      "tgn:1000004",
      "tgn:7002082",
      "tgn:1000111",
      "tgn:7029392"
    ],
    "placetype": [
      "aat:300008347"
    ],
    "id": 1070837,
    "name:xx": "Pengze"
  }
}
