{
  "geometry": {
    "type": "Point",
    "coordinates": [
      32.533333,
      25.583333
    ]
  },
  "type": "Feature",
  "properties": {
    "hierarchy": [
      "tgn:7525966",
      "tgn:7001242",
      "tgn:7016833",
      "tgn:7000123",
      "tgn:7029392"
    ],
    "placetype": [
      "aat:300005926"
    ],
    "name:en": "Sīdī Ḩassān",
    "id": 7525966
  }
}
