{
  "geometry": {
    "type": "Point",
    "coordinates": [
      -94.5167,
      32.8333
    ]
  },
  "type": "Feature",
  "properties": {
    "hierarchy": [
      "tgn:2561081",
      "tgn:1000001",
      "tgn:7012149",
      "tgn:1002637",
      "tgn:7007826",
      "tgn:7029392"
    ],
    "placetype": [
      "aat:300008347"
    ],
    "id": 2561081,
    "name:xx": "Orrs"
  }
}
