{
  "geometry": {
    "type": "Point",
    "coordinates": [
      -87.5167,
      44.6333
    ]
  },
  "type": "Feature",
  "properties": {
    "hierarchy": [
      "tgn:2198993",
      "tgn:1000001",
      "tgn:7012149",
      "tgn:2002330",
      "tgn:7007922",
      "tgn:7029392"
    ],
    "placetype": [
      "aat:300008706"
    ],
    "id": 2198993,
    "name:xx": "Bruemmer Creek"
  }
}
