{
  "geometry": {
    "type": "Point",
    "coordinates": [
      -82.0667,
      38.0667
    ]
  },
  "type": "Feature",
  "properties": {
    "hierarchy": [
      "tgn:2118903",
      "tgn:1000001",
      "tgn:7012149",
      "tgn:2002272",
      "tgn:7013961",
      "tgn:7029392"
    ],
    "placetype": [
      "aat:300008347"
    ],
    "id": 2118903,
    "name:xx": "Leet"
  }
}
