{
  "geometry": {
    "type": "Point",
    "coordinates": [
      -109.7333,
      43.6667
    ]
  },
  "type": "Feature",
  "properties": {
    "hierarchy": [
      "tgn:2162600",
      "tgn:1000001",
      "tgn:7012149",
      "tgn:2002371",
      "tgn:7007923",
      "tgn:7029392"
    ],
    "placetype": [
      "aat:300008706"
    ],
    "id": 2162600,
    "name:xx": "Bench Creek"
  }
}
