{
  "geometry": {
    "type": "Point",
    "coordinates": [
      -96.1333,
      36.7333
    ]
  },
  "type": "Feature",
  "properties": {
    "hierarchy": [
      "tgn:2216570",
      "tgn:1000001",
      "tgn:7012149",
      "tgn:2001679",
      "tgn:7007707",
      "tgn:7029392"
    ],
    "placetype": [
      "aat:300008706"
    ],
    "id": 2216570,
    "name:xx": "Camp Creek"
  }
}
