{
  "geometry": {
    "type": "Point",
    "coordinates": [
      -81.7667,
      38.8167
    ]
  },
  "type": "Feature",
  "properties": {
    "hierarchy": [
      "tgn:2408518",
      "tgn:1000001",
      "tgn:7012149",
      "tgn:2002268",
      "tgn:7013961",
      "tgn:7029392"
    ],
    "placetype": [
      "aat:300006191"
    ],
    "id": 2408518,
    "name:xx": "Hutchison Lake"
  }
}
