{
  "geometry": {
    "type": "Point",
    "coordinates": [
      -89.8667,
      32.0833
    ]
  },
  "type": "Feature",
  "properties": {
    "hierarchy": [
      "tgn:2056124",
      "tgn:1000001",
      "tgn:7012149",
      "tgn:2001146",
      "tgn:7007522",
      "tgn:7029392"
    ],
    "placetype": [
      "aat:300008347",
      "aat:300387210"
    ],
    "id": 2056124,
    "name:xx": "Cato"
  }
}
