{
  "geometry": {
    "type": "Point",
    "coordinates": [
      -44.5667,
      -4.7167
    ]
  },
  "type": "Feature",
  "properties": {
    "hierarchy": [
      "tgn:1020494",
      "tgn:7006246",
      "tgn:1000047",
      "tgn:7002455",
      "tgn:1000002",
      "tgn:7029392"
    ],
    "placetype": [
      "aat:300008347"
    ],
    "id": 1020494,
    "name:xx": "Olho d'Água das Cunhãs"
  }
}
