{
  "geometry": {
    "type": "Point",
    "coordinates": [
      -108.0833,
      37.4333
    ]
  },
  "type": "Feature",
  "properties": {
    "hierarchy": [
      "tgn:2562961",
      "tgn:1000001",
      "tgn:7012149",
      "tgn:2000233",
      "tgn:7007158",
      "tgn:7029392"
    ],
    "placetype": [
      "aat:300386845"
    ],
    "id": 2562961,
    "name:xx": "Owen Basin"
  }
}
