{
  "geometry": {
    "type": "Point",
    "coordinates": [
      78.768018,
      25.036173
    ]
  },
  "type": "Feature",
  "properties": {
    "hierarchy": [
      "tgn:7584149",
      "tgn:1000004",
      "tgn:7000198",
      "tgn:1001894",
      "tgn:7029392"
    ],
    "placetype": [
      "aat:300008347"
    ],
    "name:en": "Bindāri",
    "id": 7584149
  }
}
