{
  "geometry": {
    "type": "Point",
    "coordinates": [
      151.5833,
      7.3333
    ]
  },
  "type": "Feature",
  "properties": {
    "hierarchy": [
      "tgn:1009482",
      "tgn:7018508",
      "tgn:1010363",
      "tgn:1000220",
      "tgn:1000006",
      "tgn:7029392"
    ],
    "placetype": [
      "aat:300008791"
    ],
    "id": 1009482,
    "name:xx": "Tol"
  }
}
