{
  "geometry": {
    "type": "Point",
    "coordinates": [
      -118.1167,
      44.2667
    ]
  },
  "type": "Feature",
  "properties": {
    "hierarchy": [
      "tgn:2180302",
      "tgn:1000001",
      "tgn:7012149",
      "tgn:2001718",
      "tgn:7007708",
      "tgn:7029392"
    ],
    "placetype": [
      "aat:300008697"
    ],
    "id": 2180302,
    "name:xx": "Block and Tackle Spring"
  }
}
