{
  "geometry": {
    "type": "Point",
    "coordinates": [
      -100.6167,
      33.3833
    ]
  },
  "type": "Feature",
  "properties": {
    "hierarchy": [
      "tgn:2681438",
      "tgn:1000001",
      "tgn:7012149",
      "tgn:7007826",
      "tgn:7029392"
    ],
    "placetype": [
      "aat:300008761"
    ],
    "id": 2681438,
    "name:xx": "South Pole Canyon"
  }
}
