{
  "type": "FeatureCollection",
  "features": [
    {
      "geometry": {
        "type": "Point",
        "coordinates": [
          -86.55,
          31.1
        ]
      },
      "type": "Feature",
      "properties": {
        "hierarchy": [
          "tgn:2181840",
          "tgn:7002659",
          "tgn:1000001",
          "tgn:2000019",
          "tgn:7012149",
          "tgn:7029392"
        ],
        "placetype": [
          "aat:300008680"
        ],
        "id": 2181840,
        "name:xx": "Blue Lake"
      }
    },
    {
      "geometry": {
        "type": "Point",
        "coordinates": [
          -88.0833,
          32.7833
        ]
      },
      "type": "Feature",
      "properties": {
        "hierarchy": [
          "tgn:2181841",
          "tgn:7002659",
          "tgn:1000001",
          "tgn:7012149",
          "tgn:2000059",
          "tgn:7029392"
        ],
        "placetype": [
          "aat:300008680"
        ],
        "id": 2181841,
        "name:xx": "Blue Lake"
      }
    },
    {
      "geometry": {
        "type": "Point",
        "coordinates": [
          -130.9,
          56.3333
        ]
      },
      "type": "Feature",
      "properties": {
        "hierarchy": [
          "tgn:2181842",
          "tgn:7006450",
          "tgn:1000001",
          "tgn:7012149",
          "tgn:2000082",
          "tgn:7029392"
        ],
        "placetype": [
          "aat:300008680"
        ],
        "id": 2181842,
        "name:xx": "Blue Lake"
      }
    },
    {
      "geometry": {
        "type": "Point",
        "coordinates": [
          -152.8833,
          59.9667
        ]
      },
      "type": "Feature",
      "properties": {
        "hierarchy": [
          "tgn:2181843",
          "tgn:7006450",
          "tgn:1000001",
          "tgn:7019698",
          "tgn:7012149",
          "tgn:7029392"
        ],
        "placetype": [
          "aat:300008680"
        ],
        "id": 2181843,
        "name:xx": "Blue Lake"
      }
    },
    {
      "geometry": {
        "type": "Point",
        "coordinates": [
          -146.8167,
          62.2
        ]
      },
      "type": "Feature",
      "properties": {
        "hierarchy": [
          "tgn:2181844",
          "tgn:7006450",
          "tgn:1000001",
          "tgn:7012149",
          "tgn:2000086",
          "tgn:7029392"
        ],
        "placetype": [
          "aat:300008680"
        ],
        "id": 2181844,
        "name:xx": "Blue Lake"
      }
    },
    {
      "geometry": {
        "type": "Point",
        "coordinates": [
          -135.1833,
          57.05
        ]
      },
      "type": "Feature",
      "properties": {
        "hierarchy": [
          "tgn:2181845",
          "tgn:7006450",
          "tgn:1000001",
          "tgn:7012149",
          "tgn:2124002",
          "tgn:7029392"
        ],
        "placetype": [
          "aat:300006191"
        ],
        "id": 2181845,
        "name:xx": "Blue Lake"
      }
    },
    {
      "geometry": {
        "type": "Point",
        "coordinates": [
          -109.8,
          34.0667
        ]
      },
      "type": "Feature",
      "properties": {
        "hierarchy": [
          "tgn:2181846",
          "tgn:2000090",
          "tgn:1000001",
          "tgn:7006451",
          "tgn:7012149",
          "tgn:7029392"
        ],
        "placetype": [
          "aat:300008680"
        ],
        "id": 2181846,
        "name:xx": "Blue Lake"
      }
    },
    {
      "geometry": {
        "type": "Point",
        "coordinates": [
          -110.75,
          36.5
        ]
      },
      "type": "Feature",
      "properties": {
        "hierarchy": [
          "tgn:2181847",
          "tgn:1000001",
          "tgn:7006451",
          "tgn:2000092",
          "tgn:7012149",
          "tgn:7029392"
        ],
        "placetype": [
          "aat:300006191"
        ],
        "id": 2181847,
        "name:xx": "Blue Lake"
      }
    },
    {
      "geometry": {
        "type": "Point",
        "coordinates": [
          -92.7667,
          33.5833
        ]
      },
      "type": "Feature",
      "properties": {
        "hierarchy": [
          "tgn:2181848",
          "tgn:1000001",
          "tgn:7016172",
          "tgn:7012149",
          "tgn:2000156",
          "tgn:7029392"
        ],
        "placetype": [
          "aat:300008680"
        ],
        "id": 2181848,
        "name:xx": "Blue Lake"
      }
    },
    {
      "geometry": {
        "type": "Point",
        "coordinates": [
          -91.45,
          34.8
        ]
      },
      "type": "Feature",
      "properties": {
        "hierarchy": [
          "tgn:2181849",
          "tgn:1000001",
          "tgn:7016172",
          "tgn:7012149",
          "tgn:2000163",
          "tgn:7029392"
        ],
        "placetype": [
          "aat:300008680"
        ],
        "id": 2181849,
        "name:xx": "Blue Lake"
      }
    }
  ]
}
