{
  "geometry": {
    "type": "Point",
    "coordinates": [
      -82.4667,
      29.1833
    ]
  },
  "type": "Feature",
  "properties": {
    "hierarchy": [
      "tgn:2288110",
      "tgn:1000001",
      "tgn:7012149",
      "tgn:1002631",
      "tgn:7007240",
      "tgn:7029392"
    ],
    "placetype": [
      "aat:300008905"
    ],
    "id": 2288110,
    "name:xx": "Dinner Sink Pond"
  }
}
