{
  "geometry": {
    "type": "Point",
    "coordinates": [
      172.8167,
      52.9167
    ]
  },
  "type": "Feature",
  "properties": {
    "hierarchy": [
      "tgn:2693475",
      "tgn:7030516",
      "tgn:7006450",
      "tgn:1000001",
      "tgn:7012149",
      "tgn:7029392"
    ],
    "placetype": [
      "aat:300008707"
    ],
    "id": 2693475,
    "name:xx": "Steller River"
  }
}
