{
  "type": "FeatureCollection",
  "features": [
    {
      "geometry": {
        "type": "Point",
        "coordinates": [
          -122.1833,
          41.35
        ]
      },
      "type": "Feature",
      "properties": {
        "hierarchy": [
          "tgn:2566940",
          "tgn:1000001",
          "tgn:7012149",
          "tgn:7007157",
          "tgn:2000189",
          "tgn:7029392"
        ],
        "placetype": [
          "aat:300008706"
        ],
        "id": 2566940,
        "name:xx": "Panther Creek"
      }
    },
    {
      "geometry": {
        "type": "Point",
        "coordinates": [
          -123.0667,
          39.4333
        ]
      },
      "type": "Feature",
      "properties": {
        "hierarchy": [
          "tgn:2566941",
          "tgn:1000001",
          "tgn:7012149",
          "tgn:7007157",
          "tgn:1002566",
          "tgn:7029392"
        ],
        "placetype": [
          "aat:300008706"
        ],
        "id": 2566941,
        "name:xx": "Panther Creek"
      }
    },
    {
      "geometry": {
        "type": "Point",
        "coordinates": [
          -121.5333,
          37.0667
        ]
      },
      "type": "Feature",
      "properties": {
        "hierarchy": [
          "tgn:2566942",
          "tgn:1000001",
          "tgn:7012149",
          "tgn:7007157",
          "tgn:7014475",
          "tgn:7029392"
        ],
        "placetype": [
          "aat:300008706"
        ],
        "id": 2566942,
        "name:xx": "Panther Creek"
      }
    },
    {
      "geometry": {
        "type": "Point",
        "coordinates": [
          -105.05,
          38.0833
        ]
      },
      "type": "Feature",
      "properties": {
        "hierarchy": [
          "tgn:2566943",
          "tgn:1000001",
          "tgn:7012149",
          "tgn:7007158",
          "tgn:7029392"
        ],
        "placetype": [
          "aat:300008706"
        ],
        "id": 2566943,
        "name:xx": "Panther Creek"
      }
    },
    {
      "geometry": {
        "type": "Point",
        "coordinates": [
          -86.8167,
          30.4667
        ]
      },
      "type": "Feature",
      "properties": {
        "hierarchy": [
          "tgn:2566944",
          "tgn:1000001",
          "tgn:7012149",
          "tgn:2000285",
          "tgn:7007240",
          "tgn:7029392"
        ],
        "placetype": [
          "aat:300008706"
        ],
        "id": 2566944,
        "name:xx": "Panther Creek"
      }
    },
    {
      "geometry": {
        "type": "Point",
        "coordinates": [
          -86.0333,
          30.7
        ]
      },
      "type": "Feature",
      "properties": {
        "hierarchy": [
          "tgn:2566945",
          "tgn:1000001",
          "tgn:7012149",
          "tgn:2000290",
          "tgn:7007240",
          "tgn:7029392"
        ],
        "placetype": [
          "aat:300008706"
        ],
        "id": 2566945,
        "name:xx": "Panther Creek"
      }
    },
    {
      "geometry": {
        "type": "Point",
        "coordinates": [
          -84.8667,
          30.3833
        ]
      },
      "type": "Feature",
      "properties": {
        "hierarchy": [
          "tgn:2566946",
          "tgn:1000001",
          "tgn:7012149",
          "tgn:2000278",
          "tgn:7007240",
          "tgn:7029392"
        ],
        "placetype": [
          "aat:300008706"
        ],
        "id": 2566946,
        "name:xx": "Panther Creek"
      }
    },
    {
      "geometry": {
        "type": "Point",
        "coordinates": [
          -84.05,
          30.5833
        ]
      },
      "type": "Feature",
      "properties": {
        "hierarchy": [
          "tgn:2566947",
          "tgn:1000001",
          "tgn:7012149",
          "tgn:2000276",
          "tgn:7007240",
          "tgn:7029392"
        ],
        "placetype": [
          "aat:300008706"
        ],
        "id": 2566947,
        "name:xx": "Panther Creek"
      }
    },
    {
      "geometry": {
        "type": "Point",
        "coordinates": [
          -86.65,
          30.9833
        ]
      },
      "type": "Feature",
      "properties": {
        "hierarchy": [
          "tgn:2566948",
          "tgn:1000001",
          "tgn:7012149",
          "tgn:2000281",
          "tgn:7007240",
          "tgn:7029392"
        ],
        "placetype": [
          "aat:300008706"
        ],
        "id": 2566948,
        "name:xx": "Panther Creek"
      }
    },
    {
      "geometry": {
        "type": "Point",
        "coordinates": [
          -84.7,
          33.1833
        ]
      },
      "type": "Feature",
      "properties": {
        "hierarchy": [
          "tgn:2566949",
          "tgn:1000001",
          "tgn:7012149",
          "tgn:2000390",
          "tgn:7007248",
          "tgn:7029392"
        ],
        "placetype": [
          "aat:300008706"
        ],
        "id": 2566949,
        "name:xx": "Panther Creek"
      }
    }
  ]
}
