{
  "geometry": {
    "type": "Point",
    "coordinates": [
      -87.75,
      36.05
    ]
  },
  "type": "Feature",
  "properties": {
    "hierarchy": [
      "tgn:2231914",
      "tgn:1000001",
      "tgn:7012149",
      "tgn:2001879",
      "tgn:7007825",
      "tgn:7029392"
    ],
    "placetype": [
      "aat:300008697"
    ],
    "id": 2231914,
    "name:xx": "Chambers Spring"
  }
}
