{
  "geometry": {
    "type": "Point",
    "coordinates": [
      -120.1667,
      38.8167
    ]
  },
  "type": "Feature",
  "properties": {
    "hierarchy": [
      "tgn:2739921",
      "tgn:1000001",
      "tgn:7012149",
      "tgn:1002350",
      "tgn:7007157",
      "tgn:7029392"
    ],
    "placetype": [
      "aat:300008347"
    ],
    "id": 2739921,
    "name:xx": "Upper Forni"
  }
}
