{
  "geometry": {
    "type": "Point",
    "coordinates": [
      -78.9667,
      40.4167
    ]
  },
  "type": "Feature",
  "properties": {
    "hierarchy": [
      "tgn:2326369",
      "tgn:1000001",
      "tgn:7012149",
      "tgn:1002501",
      "tgn:7007710",
      "tgn:7029392"
    ],
    "placetype": [
      "aat:300006191"
    ],
    "id": 2326369,
    "name:xx": "Findley Run Reservoir"
  }
}
