{
  "geometry": {
    "type": "Point",
    "coordinates": [
      -85.8333,
      32.8167
    ]
  },
  "type": "Feature",
  "properties": {
    "hierarchy": [
      "tgn:2000061",
      "tgn:7002659",
      "tgn:1000001",
      "tgn:7012149",
      "tgn:7029392"
    ],
    "placetype": [
      "aat:300387145",
      "aat:300000771"
    ],
    "id": 2000061,
    "name:xx": "Tallapoosa"
  }
}
