{
  "geometry": {
    "type": "Point",
    "coordinates": [
      20.95,
      37.75
    ]
  },
  "type": "Feature",
  "properties": {
    "hierarchy": [
      "tgn:7218285",
      "tgn:7011167",
      "tgn:7001338",
      "tgn:1000003",
      "tgn:1000074",
      "tgn:7029392"
    ],
    "placetype": [
      "aat:300008347"
    ],
    "id": 7218285,
    "name:xx": "Xirokástellon"
  }
}
