{
  "geometry": {
    "type": "Point",
    "coordinates": [
      -92.1333,
      37.7833
    ]
  },
  "type": "Feature",
  "properties": {
    "hierarchy": [
      "tgn:2771626",
      "tgn:1000001",
      "tgn:7012149",
      "tgn:2001233",
      "tgn:7007523",
      "tgn:7029392"
    ],
    "placetype": [
      "aat:300008746"
    ],
    "id": 2771626,
    "name:xx": "Wildwood Cave"
  }
}
