{
  "geometry": {
    "type": "Point",
    "coordinates": [
      32.583333,
      25.983333
    ]
  },
  "type": "Feature",
  "properties": {
    "hierarchy": [
      "tgn:7537130",
      "tgn:7001242",
      "tgn:7016833",
      "tgn:7000123",
      "tgn:7029392"
    ],
    "placetype": [
      "aat:300379998"
    ],
    "name:en": "Ḩalab, Wādī",
    "id": 7537130
  }
}
