{
  "geometry": {
    "type": "Point",
    "coordinates": [
      74.150509,
      33.112355
    ]
  },
  "type": "Feature",
  "properties": {
    "hierarchy": [
      "tgn:7589034",
      "tgn:1000004",
      "tgn:7000198",
      "tgn:7000799",
      "tgn:7029392"
    ],
    "placetype": [
      "aat:300008347"
    ],
    "name:en": "Nihāla",
    "id": 7589034
  }
}
