{
  "geometry": {
    "type": "Point",
    "coordinates": [
      117.2667,
      -31.15
    ]
  },
  "type": "Feature",
  "properties": {
    "hierarchy": [
      "tgn:1098365",
      "tgn:7000490",
      "tgn:1000006",
      "tgn:7001834",
      "tgn:7029392"
    ],
    "placetype": [
      "aat:300008347"
    ],
    "id": 1098365,
    "name:xx": "Trayning"
  }
}
