{
  "type": "FeatureCollection",
  "features": [
    {
      "geometry": {
        "type": "Point",
        "coordinates": [
          -85.3833,
          36.6833
        ]
      },
      "type": "Feature",
      "properties": {
        "hierarchy": [
          "tgn:2596080",
          "tgn:1000001",
          "tgn:7012149",
          "tgn:2000785",
          "tgn:7007255",
          "tgn:7029392"
        ],
        "placetype": [
          "aat:300008706"
        ],
        "id": 2596080,
        "name:xx": "Potters Creek"
      }
    },
    {
      "geometry": {
        "type": "Point",
        "coordinates": [
          -80.8667,
          36.4667
        ]
      },
      "type": "Feature",
      "properties": {
        "hierarchy": [
          "tgn:2596081",
          "tgn:1000001",
          "tgn:7012149",
          "tgn:2001542",
          "tgn:7007709",
          "tgn:7029392"
        ],
        "placetype": [
          "aat:300008706"
        ],
        "id": 2596081,
        "name:xx": "Potters Creek"
      }
    },
    {
      "geometry": {
        "type": "Point",
        "coordinates": [
          -117.7,
          45.25
        ]
      },
      "type": "Feature",
      "properties": {
        "hierarchy": [
          "tgn:2596082",
          "tgn:1000001",
          "tgn:7012149",
          "tgn:2001721",
          "tgn:7007708",
          "tgn:7029392"
        ],
        "placetype": [
          "aat:300008706"
        ],
        "id": 2596082,
        "name:xx": "Potters Creek"
      }
    },
    {
      "geometry": {
        "type": "Point",
        "coordinates": [
          -89.1,
          35.25
        ]
      },
      "type": "Feature",
      "properties": {
        "hierarchy": [
          "tgn:2596083",
          "tgn:1000001",
          "tgn:7012149",
          "tgn:2001871",
          "tgn:7007825",
          "tgn:7029392"
        ],
        "placetype": [
          "aat:300008706"
        ],
        "id": 2596083,
        "name:xx": "Potters Creek"
      }
    },
    {
      "geometry": {
        "type": "Point",
        "coordinates": [
          -94.4667,
          32.55
        ]
      },
      "type": "Feature",
      "properties": {
        "hierarchy": [
          "tgn:2596084",
          "tgn:1000001",
          "tgn:7012149",
          "tgn:7007826",
          "tgn:7029392"
        ],
        "placetype": [
          "aat:300008706"
        ],
        "id": 2596084,
        "name:xx": "Potters Creek"
      }
    },
    {
      "geometry": {
        "type": "Point",
        "coordinates": [
          -113.7,
          41.7167
        ]
      },
      "type": "Feature",
      "properties": {
        "hierarchy": [
          "tgn:2596085",
          "tgn:1000001",
          "tgn:2002102",
          "tgn:7012149",
          "tgn:7007827",
          "tgn:7029392"
        ],
        "placetype": [
          "aat:300008706"
        ],
        "id": 2596085,
        "name:xx": "Potters Creek"
      }
    },
    {
      "geometry": {
        "type": "Point",
        "coordinates": [
          -88.6833,
          44.3167
        ]
      },
      "type": "Feature",
      "properties": {
        "hierarchy": [
          "tgn:2596086",
          "tgn:1000001",
          "tgn:7012149",
          "tgn:7007922",
          "tgn:7029392"
        ],
        "placetype": [
          "aat:300008706"
        ],
        "id": 2596086,
        "name:xx": "Potters Creek"
      }
    },
    {
      "geometry": {
        "type": "Point",
        "coordinates": [
          -78.8,
          34.3
        ]
      },
      "type": "Feature",
      "properties": {
        "hierarchy": [
          "tgn:2596087",
          "tgn:1000001",
          "tgn:2001485",
          "tgn:7012149",
          "tgn:7007709",
          "tgn:7029392"
        ],
        "placetype": [
          "aat:300008347"
        ],
        "id": 2596087,
        "name:xx": "Potters Curve"
      }
    },
    {
      "geometry": {
        "type": "Point",
        "coordinates": [
          -110.9667,
          45.85
        ]
      },
      "type": "Feature",
      "properties": {
        "hierarchy": [
          "tgn:2596088",
          "tgn:1000001",
          "tgn:7012149",
          "tgn:2001275",
          "tgn:7007524",
          "tgn:7029392"
        ],
        "placetype": [
          "aat:300008761"
        ],
        "id": 2596088,
        "name:xx": "Potters Gulch"
      }
    },
    {
      "geometry": {
        "type": "Point",
        "coordinates": [
          -112.9167,
          35.95
        ]
      },
      "type": "Feature",
      "properties": {
        "hierarchy": [
          "tgn:2596089",
          "tgn:1000001",
          "tgn:7006451",
          "tgn:2000092",
          "tgn:7012149",
          "tgn:7029392"
        ],
        "placetype": [
          "aat:300006191"
        ],
        "id": 2596089,
        "name:xx": "Potters Hole"
      }
    }
  ]
}
