{
  "geometry": {
    "type": "Point",
    "coordinates": [
      -71.1333,
      41.6167
    ]
  },
  "type": "Feature",
  "properties": {
    "hierarchy": [
      "tgn:2645551",
      "tgn:1002201",
      "tgn:1000001",
      "tgn:7012149",
      "tgn:7007517",
      "tgn:7029392"
    ],
    "placetype": [
      "aat:300008680"
    ],
    "id": 2645551,
    "name:xx": "Sawdy Pond"
  }
}
