{
  "type": "FeatureCollection",
  "features": [
    {
      "geometry": {
        "type": "Point",
        "coordinates": [
          -104.866667,
          27.583333
        ]
      },
      "type": "Feature",
      "properties": {
        "hierarchy": [
          "tgn:7393570",
          "tgn:7005581",
          "tgn:1000001",
          "tgn:7005560",
          "tgn:7029392"
        ],
        "placetype": [
          "aat:300000241"
        ],
        "id": 7393570,
        "name:xx": "Rancho San Francisco"
      }
    },
    {
      "geometry": {
        "type": "Point",
        "coordinates": [
          -105.2,
          27.4
        ]
      },
      "type": "Feature",
      "properties": {
        "hierarchy": [
          "tgn:7393571",
          "tgn:7005581",
          "tgn:1000001",
          "tgn:7005560",
          "tgn:7029392"
        ],
        "placetype": [
          "aat:300000241"
        ],
        "id": 7393571,
        "name:xx": "Rancho San Francisco"
      }
    },
    {
      "geometry": {
        "type": "Point",
        "coordinates": [
          -105.266667,
          27.116667
        ]
      },
      "type": "Feature",
      "properties": {
        "hierarchy": [
          "tgn:7393572",
          "tgn:7005581",
          "tgn:1000001",
          "tgn:7005560",
          "tgn:7029392"
        ],
        "placetype": [
          "aat:300000241"
        ],
        "id": 7393572,
        "name:xx": "Rancho San Francisco"
      }
    },
    {
      "geometry": {
        "type": "Point",
        "coordinates": [
          -105.5,
          26.783333
        ]
      },
      "type": "Feature",
      "properties": {
        "hierarchy": [
          "tgn:7393573",
          "tgn:7005581",
          "tgn:1000001",
          "tgn:7005560",
          "tgn:7029392"
        ],
        "placetype": [
          "aat:300000241"
        ],
        "id": 7393573,
        "name:xx": "Rancho San Francisco"
      }
    },
    {
      "geometry": {
        "type": "Point",
        "coordinates": [
          -98.516667,
          26.116667
        ]
      },
      "type": "Feature",
      "properties": {
        "hierarchy": [
          "tgn:7393574",
          "tgn:1000001",
          "tgn:7005597",
          "tgn:7005560",
          "tgn:7029392"
        ],
        "placetype": [
          "aat:300000241"
        ],
        "id": 7393574,
        "name:xx": "Rancho San Francisco"
      }
    },
    {
      "geometry": {
        "type": "Point",
        "coordinates": [
          -101.966667,
          25.733333
        ]
      },
      "type": "Feature",
      "properties": {
        "hierarchy": [
          "tgn:7393575",
          "tgn:1001853",
          "tgn:1000001",
          "tgn:7005560",
          "tgn:7029392"
        ],
        "placetype": [
          "aat:300000241"
        ],
        "id": 7393575,
        "name:xx": "Rancho San Francisco"
      }
    },
    {
      "geometry": {
        "type": "Point",
        "coordinates": [
          -103.733333,
          25.5
        ]
      },
      "type": "Feature",
      "properties": {
        "hierarchy": [
          "tgn:7393576",
          "tgn:7005583",
          "tgn:1000001",
          "tgn:7005560",
          "tgn:7029392"
        ],
        "placetype": [
          "aat:300000241"
        ],
        "id": 7393576,
        "name:xx": "Rancho San Francisco"
      }
    },
    {
      "geometry": {
        "type": "Point",
        "coordinates": [
          -107.416667,
          25.483333
        ]
      },
      "type": "Feature",
      "properties": {
        "hierarchy": [
          "tgn:7393577",
          "tgn:1000001",
          "tgn:7005595",
          "tgn:7005560",
          "tgn:7029392"
        ],
        "placetype": [
          "aat:300000241"
        ],
        "id": 7393577,
        "name:xx": "Rancho San Francisco"
      }
    },
    {
      "geometry": {
        "type": "Point",
        "coordinates": [
          -105.016667,
          25.216667
        ]
      },
      "type": "Feature",
      "properties": {
        "hierarchy": [
          "tgn:7393578",
          "tgn:7005583",
          "tgn:1000001",
          "tgn:7005560",
          "tgn:7029392"
        ],
        "placetype": [
          "aat:300000241"
        ],
        "id": 7393578,
        "name:xx": "Rancho San Francisco"
      }
    },
    {
      "geometry": {
        "type": "Point",
        "coordinates": [
          -102.483333,
          24.966667
        ]
      },
      "type": "Feature",
      "properties": {
        "hierarchy": [
          "tgn:7393579",
          "tgn:1000001",
          "tgn:7005601",
          "tgn:7005560",
          "tgn:7029392"
        ],
        "placetype": [
          "aat:300000241"
        ],
        "id": 7393579,
        "name:xx": "Rancho San Francisco"
      }
    }
  ]
}
