{
  "type": "FeatureCollection",
  "features": [
    {
      "geometry": {
        "type": "Point",
        "coordinates": [
          12.5,
          41.8833
        ]
      },
      "type": "Feature",
      "properties": {
        "hierarchy": [
          "tgn:1100020",
          "tgn:7003138",
          "tgn:1000003",
          "tgn:7003080",
          "tgn:1000080",
          "tgn:7000874",
          "tgn:7029392"
        ],
        "placetype": [
          "aat:300007466",
          "aat:300007501"
        ],
        "id": 1100020,
        "name:xx": "San Giovanni in Laterano"
      }
    },
    {
      "geometry": {
        "type": "Point",
        "coordinates": [
          -0.6667,
          42.5
        ]
      },
      "type": "Feature",
      "properties": {
        "hierarchy": [
          "tgn:1100021",
          "tgn:7002759",
          "tgn:7008909",
          "tgn:1000003",
          "tgn:1000095",
          "tgn:7029392"
        ],
        "placetype": [
          "aat:300000641"
        ],
        "id": 1100021,
        "name:xx": "San Juan de Peña, Monasterio"
      }
    },
    {
      "geometry": {
        "type": "Point",
        "coordinates": [
          12.95,
          47.516667
        ]
      },
      "type": "Feature",
      "properties": {
        "hierarchy": [
          "tgn:1100024",
          "tgn:7003669",
          "tgn:1000003",
          "tgn:7000084",
          "tgn:7029392"
        ],
        "placetype": [
          "aat:300007466"
        ],
        "id": 1100024,
        "name:xx": "Sankt Bartholomä"
      }
    },
    {
      "geometry": {
        "type": "Point",
        "coordinates": [
          8.7,
          40.6833
        ]
      },
      "type": "Feature",
      "properties": {
        "hierarchy": [
          "tgn:1100026",
          "tgn:7015163",
          "tgn:1000003",
          "tgn:7003121",
          "tgn:1000080",
          "tgn:7029392"
        ],
        "placetype": [
          "aat:300007466"
        ],
        "id": 1100026,
        "name:xx": "Santissima Trinita di Saccargia"
      }
    },
    {
      "geometry": {
        "type": "Point",
        "coordinates": [
          9.6833,
          48.0167
        ]
      },
      "type": "Feature",
      "properties": {
        "hierarchy": [
          "tgn:1100028",
          "tgn:7003692",
          "tgn:1000003",
          "tgn:7000084",
          "tgn:7029392"
        ],
        "placetype": [
          "aat:300007466"
        ],
        "id": 1100028,
        "name:xx": "Steinhausen"
      }
    }
  ]
}
