{
  "geometry": {
    "type": "Point",
    "coordinates": [
      75.35,
      21.683333
    ]
  },
  "type": "Feature",
  "properties": {
    "hierarchy": [
      "tgn:7549767",
      "tgn:1000004",
      "tgn:7000198",
      "tgn:1001894",
      "tgn:7029392"
    ],
    "placetype": [
      "aat:300006909"
    ],
    "name:en": "Bījāgarh Fort",
    "id": 7549767
  }
}
