{
  "geometry": {
    "type": "Point",
    "coordinates": [
      -82.5833,
      35.5833
    ]
  },
  "type": "Feature",
  "properties": {
    "hierarchy": [
      "tgn:2382764",
      "tgn:1000001",
      "tgn:2001473",
      "tgn:7012149",
      "tgn:7007709",
      "tgn:7029392"
    ],
    "placetype": [
      "aat:300008347"
    ],
    "id": 2382764,
    "name:xx": "Hazel Green"
  }
}
