{
  "geometry": {
    "type": "Point",
    "coordinates": [
      31.9667,
      48.5333
    ]
  },
  "type": "Feature",
  "properties": {
    "hierarchy": [
      "tgn:1051633",
      "tgn:1000003",
      "tgn:7011662",
      "tgn:7006660",
      "tgn:7029392"
    ],
    "placetype": [
      "aat:300008347"
    ],
    "id": 1051633,
    "name:xx": "Shestakivka"
  }
}
