{
  "geometry": {
    "type": "Point",
    "coordinates": [
      -94.15,
      32.8167
    ]
  },
  "type": "Feature",
  "properties": {
    "hierarchy": [
      "tgn:2672117",
      "tgn:1000001",
      "tgn:7012149",
      "tgn:1002637",
      "tgn:7007826",
      "tgn:7029392"
    ],
    "placetype": [
      "aat:300008699"
    ],
    "id": 2672117,
    "name:xx": "Smithland Branch"
  }
}
