{
  "type": "FeatureCollection",
  "features": [
    {
      "geometry": {
        "type": "Point",
        "coordinates": [
          -71.5833,
          45.4
        ]
      },
      "type": "Feature",
      "properties": {
        "hierarchy": [
          "tgn:1123630",
          "tgn:7005685",
          "tgn:1000001",
          "tgn:7005804",
          "tgn:7029392"
        ],
        "placetype": [
          "aat:300008707"
        ],
        "id": 1123630,
        "name:xx": "Eaton Nord"
      }
    },
    {
      "geometry": {
        "type": "Point",
        "coordinates": [
          -0.733333,
          53.5
        ]
      },
      "type": "Feature",
      "properties": {
        "hierarchy": [
          "tgn:1123631",
          "tgn:7002445",
          "tgn:1000003",
          "tgn:7008157",
          "tgn:7008591",
          "tgn:7029392"
        ],
        "placetype": [
          "aat:300008707",
          "aat:300008699"
        ],
        "name:en": "Eau",
        "id": 1123631
      }
    },
    {
      "geometry": {
        "type": "Point",
        "coordinates": [
          -90.9667,
          44.7167
        ]
      },
      "type": "Feature",
      "properties": {
        "hierarchy": [
          "tgn:1123632",
          "tgn:1000001",
          "tgn:2002320",
          "tgn:7012149",
          "tgn:7007922",
          "tgn:7029392"
        ],
        "placetype": [
          "aat:300008707"
        ],
        "id": 1123632,
        "name:xx": "Eau Claire"
      }
    },
    {
      "geometry": {
        "type": "Point",
        "coordinates": [
          -92.2333,
          45.0167
        ]
      },
      "type": "Feature",
      "properties": {
        "hierarchy": [
          "tgn:1123633",
          "tgn:1000001",
          "tgn:7012149",
          "tgn:7007922",
          "tgn:7029392"
        ],
        "placetype": [
          "aat:300008707"
        ],
        "id": 1123633,
        "name:xx": "Eau Galle"
      }
    },
    {
      "geometry": {
        "type": "Point",
        "coordinates": [
          4.4,
          50.3
        ]
      },
      "type": "Feature",
      "properties": {
        "hierarchy": [
          "tgn:1123634",
          "tgn:1000003",
          "tgn:1000063",
          "tgn:7029392"
        ],
        "placetype": [
          "aat:300008707"
        ],
        "id": 1123634,
        "name:xx": "Eau d' Heure"
      }
    },
    {
      "geometry": {
        "type": "Point",
        "coordinates": [
          1.1167,
          49.9167
        ]
      },
      "type": "Feature",
      "properties": {
        "hierarchy": [
          "tgn:1123635",
          "tgn:1000003",
          "tgn:7002882",
          "tgn:1000070",
          "tgn:7029392"
        ],
        "placetype": [
          "aat:300008707"
        ],
        "id": 1123635,
        "name:xx": "Eaulne"
      }
    },
    {
      "geometry": {
        "type": "Point",
        "coordinates": [
          -2.991111,
          51.550833
        ]
      },
      "type": "Feature",
      "properties": {
        "hierarchy": [
          "tgn:1123636",
          "tgn:7002443",
          "tgn:1000003",
          "tgn:7008591",
          "tgn:7029392"
        ],
        "placetype": [
          "aat:300008707",
          "aat:300008699"
        ],
        "name:en": "Ebbw",
        "id": 1123636
      }
    }
  ]
}
