{
  "geometry": {
    "type": "Point",
    "coordinates": [
      -107.5167,
      42.4167
    ]
  },
  "type": "Feature",
  "properties": {
    "hierarchy": [
      "tgn:7019748",
      "tgn:1000001",
      "tgn:2002368",
      "tgn:7012149",
      "tgn:7007923",
      "tgn:7029392"
    ],
    "placetype": [
      "aat:300006191"
    ],
    "id": 7019748,
    "name:xx": "Speyers Reservoir"
  }
}
