{
  "geometry": {
    "type": "Point",
    "coordinates": [
      -91.1333,
      41.9833
    ]
  },
  "type": "Feature",
  "properties": {
    "hierarchy": [
      "tgn:2035381",
      "tgn:1000001",
      "tgn:7012149",
      "tgn:2000613",
      "tgn:7007253",
      "tgn:7029392"
    ],
    "placetype": [
      "aat:300008347"
    ],
    "id": 2035381,
    "name:xx": "Olin"
  }
}
