{
  "type": "FeatureCollection",
  "features": [
    {
      "geometry": {
        "type": "Point",
        "coordinates": [
          -107.25,
          28.883333
        ]
      },
      "type": "Feature",
      "properties": {
        "hierarchy": [
          "tgn:7393450",
          "tgn:7005581",
          "tgn:1000001",
          "tgn:7005560",
          "tgn:7029392"
        ],
        "placetype": [
          "aat:300008347"
        ],
        "id": 7393450,
        "name:xx": "San Juan de los Ojos"
      }
    },
    {
      "geometry": {
        "type": "Point",
        "coordinates": [
          -101.316667,
          21.283333
        ]
      },
      "type": "Feature",
      "properties": {
        "hierarchy": [
          "tgn:7393451",
          "tgn:7005584",
          "tgn:1000001",
          "tgn:7005560",
          "tgn:7029392"
        ],
        "placetype": [
          "aat:300008347"
        ],
        "id": 7393451,
        "name:xx": "San Juan de los Llanos"
      }
    },
    {
      "geometry": {
        "type": "Point",
        "coordinates": [
          -103.75,
          22.483333
        ]
      },
      "type": "Feature",
      "properties": {
        "hierarchy": [
          "tgn:7393452",
          "tgn:7005586",
          "tgn:1000001",
          "tgn:7005560",
          "tgn:7029392"
        ],
        "placetype": [
          "aat:300008347"
        ],
        "id": 7393452,
        "name:xx": "San Juan de los Lirios"
      }
    },
    {
      "geometry": {
        "type": "Point",
        "coordinates": [
          -89.283333,
          21.066667
        ]
      },
      "type": "Feature",
      "properties": {
        "hierarchy": [
          "tgn:7393453",
          "tgn:1000001",
          "tgn:7005600",
          "tgn:7005560",
          "tgn:7029392"
        ],
        "placetype": [
          "aat:300008347"
        ],
        "id": 7393453,
        "name:xx": "San José"
      }
    },
    {
      "geometry": {
        "type": "Point",
        "coordinates": [
          -101.95,
          21.016667
        ]
      },
      "type": "Feature",
      "properties": {
        "hierarchy": [
          "tgn:7393454",
          "tgn:7005586",
          "tgn:1000001",
          "tgn:7005560",
          "tgn:7029392"
        ],
        "placetype": [
          "aat:300008347"
        ],
        "id": 7393454,
        "name:xx": "San José"
      }
    },
    {
      "geometry": {
        "type": "Point",
        "coordinates": [
          -89.516667,
          21.016667
        ]
      },
      "type": "Feature",
      "properties": {
        "hierarchy": [
          "tgn:7393455",
          "tgn:1000001",
          "tgn:7005600",
          "tgn:7005560",
          "tgn:7029392"
        ],
        "placetype": [
          "aat:300008347"
        ],
        "id": 7393455,
        "name:xx": "San José"
      }
    },
    {
      "geometry": {
        "type": "Point",
        "coordinates": [
          -101.7,
          21
        ]
      },
      "type": "Feature",
      "properties": {
        "hierarchy": [
          "tgn:7393456",
          "tgn:7005584",
          "tgn:1000001",
          "tgn:7005560",
          "tgn:7029392"
        ],
        "placetype": [
          "aat:300008347"
        ],
        "id": 7393456,
        "name:xx": "San José"
      }
    },
    {
      "geometry": {
        "type": "Point",
        "coordinates": [
          -89.116667,
          20.85
        ]
      },
      "type": "Feature",
      "properties": {
        "hierarchy": [
          "tgn:7393457",
          "tgn:1000001",
          "tgn:7005600",
          "tgn:7005560",
          "tgn:7029392"
        ],
        "placetype": [
          "aat:300008347"
        ],
        "id": 7393457,
        "name:xx": "San José"
      }
    },
    {
      "geometry": {
        "type": "Point",
        "coordinates": [
          -103.333333,
          20.833333
        ]
      },
      "type": "Feature",
      "properties": {
        "hierarchy": [
          "tgn:7393459",
          "tgn:7005586",
          "tgn:1000001",
          "tgn:7005560",
          "tgn:7029392"
        ],
        "placetype": [
          "aat:300008347"
        ],
        "id": 7393459,
        "name:xx": "San José"
      }
    }
  ]
}
