{
  "geometry": {
    "type": "Point",
    "coordinates": [
      -82.0167,
      30.9333
    ]
  },
  "type": "Feature",
  "properties": {
    "hierarchy": [
      "tgn:2540100",
      "tgn:1000001",
      "tgn:2000315",
      "tgn:7012149",
      "tgn:7007248",
      "tgn:7029392"
    ],
    "placetype": [
      "aat:300008347"
    ],
    "id": 2540100,
    "name:xx": "Newell"
  }
}
