{
  "geometry": {
    "type": "Point",
    "coordinates": [
      -96.9833,
      37.2333
    ]
  },
  "type": "Feature",
  "properties": {
    "hierarchy": [
      "tgn:2037393",
      "tgn:1000001",
      "tgn:2000677",
      "tgn:7012149",
      "tgn:7007254",
      "tgn:7029392"
    ],
    "placetype": [
      "aat:300008347"
    ],
    "id": 2037393,
    "name:xx": "Winfield"
  }
}
