{
  "geometry": {
    "type": "Point",
    "coordinates": [
      -119.0667,
      44.65
    ]
  },
  "type": "Feature",
  "properties": {
    "hierarchy": [
      "tgn:2467184",
      "tgn:1000001",
      "tgn:7012149",
      "tgn:2001708",
      "tgn:7007708",
      "tgn:7029392"
    ],
    "placetype": [
      "aat:300008798"
    ],
    "id": 2467184,
    "name:xx": "Long Creek Mountain"
  }
}
