{
  "geometry": {
    "type": "Point",
    "coordinates": [
      -135.2833,
      57.0333
    ]
  },
  "type": "Feature",
  "properties": {
    "hierarchy": [
      "tgn:2516823",
      "tgn:7006450",
      "tgn:1000001",
      "tgn:7012149",
      "tgn:2124002",
      "tgn:7029392"
    ],
    "placetype": [
      "aat:300008791"
    ],
    "id": 2516823,
    "name:xx": "Minett Island"
  }
}
