{
  "geometry": {
    "type": "Point",
    "coordinates": [
      -80.0167,
      40.55
    ]
  },
  "type": "Feature",
  "properties": {
    "hierarchy": [
      "tgn:2338214",
      "tgn:7013272",
      "tgn:1000001",
      "tgn:7012149",
      "tgn:7007710",
      "tgn:7029392"
    ],
    "placetype": [
      "aat:300008347"
    ],
    "id": 2338214,
    "name:xx": "Fox Ridge"
  }
}
