{
  "geometry": {
    "type": "Point",
    "coordinates": [
      33.43331,
      28.364993
    ]
  },
  "type": "Feature",
  "properties": {
    "hierarchy": [
      "tgn:7526546",
      "tgn:7001242",
      "tgn:7016833",
      "tgn:7001336",
      "tgn:7029392"
    ],
    "placetype": [
      "aat:300386846"
    ],
    "id": 7526546,
    "name:xx": "Wā'ir, Ra's al"
  }
}
