{
  "geometry": {
    "type": "Point",
    "coordinates": [
      -88.3833,
      34.3167
    ]
  },
  "type": "Feature",
  "properties": {
    "hierarchy": [
      "tgn:2415717",
      "tgn:1000001",
      "tgn:7012149",
      "tgn:2001114",
      "tgn:7007522",
      "tgn:7029392"
    ],
    "placetype": [
      "aat:300006191"
    ],
    "id": 2415717,
    "name:xx": "Itawamba, Lake"
  }
}
