{
  "geometry": {
    "type": "Point",
    "coordinates": [
      7.1667,
      43.8167
    ]
  },
  "type": "Feature",
  "properties": {
    "hierarchy": [
      "tgn:1033837",
      "tgn:1000003",
      "tgn:1000070",
      "tgn:7002895",
      "tgn:7029392"
    ],
    "placetype": [
      "aat:300008347"
    ],
    "id": 1033837,
    "name:xx": "Le Broc"
  }
}
