{
  "geometry": {
    "type": "Point",
    "coordinates": [
      -110.15,
      32.3667
    ]
  },
  "type": "Feature",
  "properties": {
    "hierarchy": [
      "tgn:2145374",
      "tgn:1000001",
      "tgn:7006451",
      "tgn:2000091",
      "tgn:7012149",
      "tgn:7029392"
    ],
    "placetype": [
      "aat:300006191"
    ],
    "id": 2145374,
    "name:xx": "Bald Ridge Number Two Tank"
  }
}
