{
  "geometry": {
    "type": "Point",
    "coordinates": [
      -113.5333,
      33.8167
    ]
  },
  "type": "Feature",
  "properties": {
    "hierarchy": [
      "tgn:2007522",
      "tgn:1000001",
      "tgn:7006451",
      "tgn:7012149",
      "tgn:2000104",
      "tgn:7029392"
    ],
    "placetype": [
      "aat:300008347"
    ],
    "id": 2007522,
    "name:xx": "Wenden"
  }
}
