{
  "geometry": {
    "type": "Point",
    "coordinates": [
      103.0333,
      21.3833
    ]
  },
  "type": "Feature",
  "properties": {
    "hierarchy": [
      "tgn:7004238",
      "tgn:1000004",
      "tgn:7001048",
      "tgn:1000145",
      "tgn:7029392"
    ],
    "placetype": [
      "aat:300008347",
      "aat:300000835",
      "aat:300387275",
      "aat:300008372"
    ],
    "id": 7004238,
    "name:xx": "Diện Biên Phủ"
  }
}
