{
  "geometry": {
    "type": "Point",
    "coordinates": [
      -13.8333,
      65.5333
    ]
  },
  "type": "Feature",
  "properties": {
    "hierarchy": [
      "tgn:1042516",
      "tgn:7594015",
      "tgn:1000003",
      "tgn:1000077",
      "tgn:7029392"
    ],
    "placetype": [
      "aat:300008347"
    ],
    "id": 1042516,
    "name:xx": "Bakkagerdhi"
  }
}
