{
  "geometry": {
    "type": "Point",
    "coordinates": [
      -105.1667,
      42.5333
    ]
  },
  "type": "Feature",
  "properties": {
    "hierarchy": [
      "tgn:2523824",
      "tgn:1000001",
      "tgn:7012149",
      "tgn:2002380",
      "tgn:7007923",
      "tgn:7029392"
    ],
    "placetype": [
      "aat:300006191"
    ],
    "id": 2523824,
    "name:xx": "Moran Reservoir"
  }
}
