{
  "geometry": {
    "type": "Point",
    "coordinates": [
      -101.75,
      37.15
    ]
  },
  "type": "Feature",
  "properties": {
    "hierarchy": [
      "tgn:2769960",
      "tgn:1000001",
      "tgn:7012149",
      "tgn:2000724",
      "tgn:7007254",
      "tgn:7029392"
    ],
    "placetype": [
      "aat:300008680"
    ],
    "id": 2769960,
    "name:xx": "Wilburton Pond"
  }
}
