{
  "geometry": {
    "type": "Point",
    "coordinates": [
      -90.45,
      38.0167
    ]
  },
  "type": "Feature",
  "properties": {
    "hierarchy": [
      "tgn:2190829",
      "tgn:1000001",
      "tgn:7012149",
      "tgn:7007523",
      "tgn:7029392"
    ],
    "placetype": [
      "aat:300008699"
    ],
    "id": 2190829,
    "name:xx": "Boyd Branch"
  }
}
