{
  "geometry": {
    "type": "Point",
    "coordinates": [
      21.75,
      -34.0167
    ]
  },
  "type": "Feature",
  "properties": {
    "hierarchy": [
      "tgn:1093152",
      "tgn:7001242",
      "tgn:7017584",
      "tgn:1000193",
      "tgn:7029392"
    ],
    "placetype": [
      "aat:300008347"
    ],
    "id": 1093152,
    "name:xx": "Herbertsdale"
  }
}
