{
  "type": "FeatureCollection",
  "features": [
    {
      "geometry": {
        "type": "Point",
        "coordinates": [
          -115.5667,
          47.1667
        ]
      },
      "type": "Feature",
      "properties": {
        "hierarchy": [
          "tgn:2342960",
          "tgn:1000001",
          "tgn:7012149",
          "tgn:2000491",
          "tgn:7007250",
          "tgn:7029392"
        ],
        "placetype": [
          "aat:300008706"
        ],
        "id": 2342960,
        "name:xx": "Fuzzy Creek"
      }
    },
    {
      "geometry": {
        "type": "Point",
        "coordinates": [
          -115.4667,
          46.6
        ]
      },
      "type": "Feature",
      "properties": {
        "hierarchy": [
          "tgn:2342961",
          "tgn:1000001",
          "tgn:2000469",
          "tgn:7012149",
          "tgn:7007250",
          "tgn:7029392"
        ],
        "placetype": [
          "aat:300008706"
        ],
        "id": 2342961,
        "name:xx": "Fuzzy Creek"
      }
    },
    {
      "geometry": {
        "type": "Point",
        "coordinates": [
          -99.9667,
          31.6
        ]
      },
      "type": "Feature",
      "properties": {
        "hierarchy": [
          "tgn:2342962",
          "tgn:1000001",
          "tgn:7012149",
          "tgn:7007826",
          "tgn:7029392"
        ],
        "placetype": [
          "aat:300008706"
        ],
        "id": 2342962,
        "name:xx": "Fuzzy Creek"
      }
    },
    {
      "geometry": {
        "type": "Point",
        "coordinates": [
          -124.1333,
          42.8167
        ]
      },
      "type": "Feature",
      "properties": {
        "hierarchy": [
          "tgn:2342963",
          "tgn:1000001",
          "tgn:2001702",
          "tgn:7012149",
          "tgn:7007708",
          "tgn:7029392"
        ],
        "placetype": [
          "aat:300008761"
        ],
        "id": 2342963,
        "name:xx": "Fuzzy Gulch"
      }
    },
    {
      "geometry": {
        "type": "Point",
        "coordinates": [
          -106.1833,
          35.2
        ]
      },
      "type": "Feature",
      "properties": {
        "hierarchy": [
          "tgn:2342964",
          "tgn:1000001",
          "tgn:7012149",
          "tgn:2001454",
          "tgn:7007566",
          "tgn:7029392"
        ],
        "placetype": [
          "aat:300000390"
        ],
        "id": 2342964,
        "name:xx": "Fuzzy Jim Claim"
      }
    },
    {
      "geometry": {
        "type": "Point",
        "coordinates": [
          -115.5667,
          47.1667
        ]
      },
      "type": "Feature",
      "properties": {
        "hierarchy": [
          "tgn:2342965",
          "tgn:1000001",
          "tgn:7012149",
          "tgn:2000491",
          "tgn:7007250",
          "tgn:7029392"
        ],
        "placetype": [
          "aat:300008850"
        ],
        "id": 2342965,
        "name:xx": "Fuzzy Peak"
      }
    },
    {
      "geometry": {
        "type": "Point",
        "coordinates": [
          -116.2667,
          40.6167
        ]
      },
      "type": "Feature",
      "properties": {
        "hierarchy": [
          "tgn:2342966",
          "tgn:1000001",
          "tgn:2001413",
          "tgn:7012149",
          "tgn:7007526",
          "tgn:7029392"
        ],
        "placetype": [
          "aat:300008697"
        ],
        "id": 2342966,
        "name:xx": "Fuzzy Spring"
      }
    },
    {
      "geometry": {
        "type": "Point",
        "coordinates": [
          -123.15,
          46.9333
        ]
      },
      "type": "Feature",
      "properties": {
        "hierarchy": [
          "tgn:2342967",
          "tgn:1000001",
          "tgn:7012149",
          "tgn:1002418",
          "tgn:7007920",
          "tgn:7029392"
        ],
        "placetype": [
          "aat:300008798"
        ],
        "id": 2342967,
        "name:xx": "Fuzzy Top"
      }
    },
    {
      "geometry": {
        "type": "Point",
        "coordinates": [
          -79.5,
          36.9667
        ]
      },
      "type": "Feature",
      "properties": {
        "hierarchy": [
          "tgn:2342968",
          "tgn:1000001",
          "tgn:7012149",
          "tgn:2002180",
          "tgn:7007919",
          "tgn:7029392"
        ],
        "placetype": [
          "aat:300006191"
        ],
        "id": 2342968,
        "name:xx": "Fuzzys Lake"
      }
    }
  ]
}
