{
  "geometry": {
    "type": "Point",
    "coordinates": [
      -78.85,
      42.15
    ]
  },
  "type": "Feature",
  "properties": {
    "hierarchy": [
      "tgn:2704069",
      "tgn:1000001",
      "tgn:1002245",
      "tgn:7012149",
      "tgn:7007568",
      "tgn:7029392"
    ],
    "placetype": [
      "aat:300008699"
    ],
    "id": 2704069,
    "name:xx": "Sunfish Run"
  }
}
