{
  "type": "FeatureCollection",
  "features": [
    {
      "geometry": {
        "type": "Point",
        "coordinates": [
          5.466667,
          52.966667
        ]
      },
      "type": "Feature",
      "properties": {
        "hierarchy": [
          "tgn:7272940",
          "tgn:7003616",
          "tgn:1000003",
          "tgn:7016845",
          "tgn:7029392"
        ],
        "placetype": [
          "aat:300006163"
        ],
        "name:nl": "Ursulapolder",
        "id": 7272940
      }
    },
    {
      "geometry": {
        "type": "Point",
        "coordinates": [
          4.95,
          52.616667
        ]
      },
      "type": "Feature",
      "properties": {
        "hierarchy": [
          "tgn:7272941",
          "tgn:1000003",
          "tgn:7006951",
          "tgn:7016845",
          "tgn:7029392"
        ],
        "placetype": [
          "aat:300006075"
        ],
        "name:nl": "Ursemmervaart",
        "id": 7272941
      }
    },
    {
      "geometry": {
        "type": "Point",
        "coordinates": [
          4.916667,
          52.633333
        ]
      },
      "type": "Feature",
      "properties": {
        "hierarchy": [
          "tgn:7272942",
          "tgn:1000003",
          "tgn:7006951",
          "tgn:7016845",
          "tgn:7029392"
        ],
        "placetype": [
          "aat:300006163"
        ],
        "name:nl": "Ursem, Polder",
        "id": 7272942
      }
    },
    {
      "geometry": {
        "type": "Point",
        "coordinates": [
          4.9,
          52.633333
        ]
      },
      "type": "Feature",
      "properties": {
        "hierarchy": [
          "tgn:7272944",
          "tgn:1000003",
          "tgn:7006951",
          "tgn:7016845",
          "tgn:7029392"
        ],
        "placetype": [
          "aat:300008347"
        ],
        "name:nl": "Ursem",
        "id": 7272944
      }
    },
    {
      "geometry": {
        "type": "Point",
        "coordinates": [
          5.766667,
          51
        ]
      },
      "type": "Feature",
      "properties": {
        "hierarchy": [
          "tgn:7272946",
          "tgn:1000003",
          "tgn:7003622",
          "tgn:7016845",
          "tgn:7029392"
        ],
        "placetype": [
          "aat:300008347"
        ],
        "name:nl": "Urmond",
        "id": 7272946
      }
    },
    {
      "geometry": {
        "type": "Point",
        "coordinates": [
          5.533333,
          51.433333
        ]
      },
      "type": "Feature",
      "properties": {
        "hierarchy": [
          "tgn:7272947",
          "tgn:1000003",
          "tgn:7003624",
          "tgn:7016845",
          "tgn:7029392"
        ],
        "placetype": [
          "aat:300008347"
        ],
        "name:nl": "Urkhoven",
        "id": 7272947
      }
    },
    {
      "geometry": {
        "type": "Point",
        "coordinates": [
          5.75,
          52.7
        ]
      },
      "type": "Feature",
      "properties": {
        "hierarchy": [
          "tgn:7272948",
          "tgn:7003615",
          "tgn:1000003",
          "tgn:7016845",
          "tgn:7029392"
        ],
        "placetype": [
          "aat:300006075"
        ],
        "name:nl": "Urkervaart",
        "id": 7272948
      }
    },
    {
      "geometry": {
        "type": "Point",
        "coordinates": [
          5.55,
          52.6
        ]
      },
      "type": "Feature",
      "properties": {
        "hierarchy": [
          "tgn:7272949",
          "tgn:7003615",
          "tgn:1000003",
          "tgn:7016845",
          "tgn:7029392"
        ],
        "placetype": [
          "aat:300008850"
        ],
        "name:nl": "Urkerhoek",
        "id": 7272949
      }
    }
  ]
}
