{
  "geometry": {
    "type": "Point",
    "coordinates": [
      -114.1833,
      48.0667
    ]
  },
  "type": "Feature",
  "properties": {
    "hierarchy": [
      "tgn:2430639",
      "tgn:1000001",
      "tgn:7012149",
      "tgn:2001274",
      "tgn:7007524",
      "tgn:7029392"
    ],
    "placetype": [
      "aat:300132316"
    ],
    "id": 2430639,
    "name:xx": "Kalispell Bay"
  }
}
