{
  "geometry": {
    "type": "Point",
    "coordinates": [
      -86.4333,
      39.7667
    ]
  },
  "type": "Feature",
  "properties": {
    "hierarchy": [
      "tgn:2486700",
      "tgn:1000001",
      "tgn:7012149",
      "tgn:1002465",
      "tgn:7007252",
      "tgn:7029392"
    ],
    "placetype": [
      "aat:300006191"
    ],
    "id": 2486700,
    "name:xx": "Ledgewood Lake"
  }
}
