{
  "geometry": {
    "type": "Point",
    "coordinates": [
      -0.7333,
      34.9833
    ]
  },
  "type": "Feature",
  "properties": {
    "hierarchy": [
      "tgn:1127045",
      "tgn:7001242",
      "tgn:7016752",
      "tgn:1000763",
      "tgn:7029392"
    ],
    "placetype": [
      "aat:300008707"
    ],
    "id": 1127045,
    "name:xx": "Mekerra"
  }
}
