{
  "geometry": {
    "type": "Point",
    "coordinates": [
      33.818333,
      29.985
    ]
  },
  "type": "Feature",
  "properties": {
    "hierarchy": [
      "tgn:7543689",
      "tgn:7001242",
      "tgn:7016833",
      "tgn:7001335",
      "tgn:7029392"
    ],
    "placetype": [
      "aat:300379998"
    ],
    "id": 7543689,
    "name:xx": "Abu 'Aweirât, Wâdi"
  }
}
