{
  "type": "FeatureCollection",
  "features": [
    {
      "geometry": {
        "type": "Point",
        "coordinates": [
          136.1333,
          33.9
        ]
      },
      "type": "Feature",
      "properties": {
        "hierarchy": [
          "tgn:1080641",
          "tgn:1000004",
          "tgn:1001007",
          "tgn:7000896",
          "tgn:1000120",
          "tgn:7029392"
        ],
        "placetype": [
          "aat:300008347"
        ],
        "id": 1080641,
        "name:xx": "Kumano"
      }
    },
    {
      "geometry": {
        "type": "Point",
        "coordinates": [
          135.3667,
          34.4
        ]
      },
      "type": "Feature",
      "properties": {
        "hierarchy": [
          "tgn:1080642",
          "tgn:1000004",
          "tgn:1000962",
          "tgn:7000896",
          "tgn:1000120",
          "tgn:7029392"
        ],
        "placetype": [
          "aat:300008347"
        ],
        "id": 1080642,
        "name:xx": "Kumatori"
      }
    },
    {
      "geometry": {
        "type": "Point",
        "coordinates": [
          133.9,
          35.05
        ]
      },
      "type": "Feature",
      "properties": {
        "hierarchy": [
          "tgn:1080643",
          "tgn:1001015",
          "tgn:7000897",
          "tgn:1000004",
          "tgn:1000120",
          "tgn:7029392"
        ],
        "placetype": [
          "aat:300008347"
        ],
        "id": 1080643,
        "name:xx": "Kume"
      }
    },
    {
      "geometry": {
        "type": "Point",
        "coordinates": [
          133.9667,
          34.9333
        ]
      },
      "type": "Feature",
      "properties": {
        "hierarchy": [
          "tgn:1080644",
          "tgn:1001015",
          "tgn:7000897",
          "tgn:1000004",
          "tgn:1000120",
          "tgn:7029392"
        ],
        "placetype": [
          "aat:300008347"
        ],
        "id": 1080644,
        "name:xx": "Kumenan"
      }
    },
    {
      "geometry": {
        "type": "Point",
        "coordinates": [
          134.9167,
          35.6
        ]
      },
      "type": "Feature",
      "properties": {
        "hierarchy": [
          "tgn:1080645",
          "tgn:1000004",
          "tgn:1000998",
          "tgn:7000896",
          "tgn:1000120",
          "tgn:7029392"
        ],
        "placetype": [
          "aat:300008347"
        ],
        "id": 1080645,
        "name:xx": "Kumihama"
      }
    },
    {
      "geometry": {
        "type": "Point",
        "coordinates": [
          135.75,
          34.8833
        ]
      },
      "type": "Feature",
      "properties": {
        "hierarchy": [
          "tgn:1080646",
          "tgn:1000004",
          "tgn:1000998",
          "tgn:7000896",
          "tgn:1000120",
          "tgn:7029392"
        ],
        "placetype": [
          "aat:300008347"
        ],
        "id": 1080646,
        "name:xx": "Kumiyama"
      }
    },
    {
      "geometry": {
        "type": "Point",
        "coordinates": [
          138.6333,
          36.5833
        ]
      },
      "type": "Feature",
      "properties": {
        "hierarchy": [
          "tgn:1080647",
          "tgn:1000980",
          "tgn:1000004",
          "tgn:7000894",
          "tgn:1000120",
          "tgn:7029392"
        ],
        "placetype": [
          "aat:300008347"
        ],
        "id": 1080647,
        "name:xx": "Kuni"
      }
    },
    {
      "geometry": {
        "type": "Point",
        "coordinates": [
          128.1667,
          26.75
        ]
      },
      "type": "Feature",
      "properties": {
        "hierarchy": [
          "tgn:1080648",
          "tgn:1010195",
          "tgn:7004299",
          "tgn:1000004",
          "tgn:7000902",
          "tgn:1001016",
          "tgn:1000120",
          "tgn:7029392"
        ],
        "placetype": [
          "aat:300008347"
        ],
        "id": 1080648,
        "name:xx": "Kunigami"
      }
    },
    {
      "geometry": {
        "type": "Point",
        "coordinates": [
          131.6,
          33.6833
        ]
      },
      "type": "Feature",
      "properties": {
        "hierarchy": [
          "tgn:1080649",
          "tgn:1000961",
          "tgn:1000004",
          "tgn:7000901",
          "tgn:1000120",
          "tgn:7029392"
        ],
        "placetype": [
          "aat:300008347"
        ],
        "id": 1080649,
        "name:xx": "Kunimi"
      }
    }
  ]
}
