{
  "geometry": {
    "type": "Point",
    "coordinates": [
      -121.1167,
      46.65
    ]
  },
  "type": "Feature",
  "properties": {
    "hierarchy": [
      "tgn:2116625",
      "tgn:1000001",
      "tgn:7012149",
      "tgn:1003042",
      "tgn:7007920",
      "tgn:7029392"
    ],
    "placetype": [
      "aat:300008347"
    ],
    "id": 2116625,
    "name:xx": "Rimrock"
  }
}
