{
  "geometry": {
    "type": "Point",
    "coordinates": [
      -85.05,
      36.4833
    ]
  },
  "type": "Feature",
  "properties": {
    "hierarchy": [
      "tgn:2267199",
      "tgn:1000001",
      "tgn:7012149",
      "tgn:7007825",
      "tgn:7029392"
    ],
    "placetype": [
      "aat:300008706"
    ],
    "id": 2267199,
    "name:xx": "Cricket Creek"
  }
}
