{
  "geometry": {
    "type": "Point",
    "coordinates": [
      120.9667,
      14.6833
    ]
  },
  "type": "Feature",
  "properties": {
    "hierarchy": [
      "tgn:1131095",
      "tgn:1000004",
      "tgn:7016720",
      "tgn:1000135",
      "tgn:7029392"
    ],
    "placetype": [
      "aat:300008707"
    ],
    "id": 1131095,
    "name:xx": "Tuliahan River"
  }
}
