{
  "type": "FeatureCollection",
  "features": [
    {
      "geometry": {
        "type": "Point",
        "coordinates": [
          12.016667,
          46.576389
        ]
      },
      "type": "Feature",
      "properties": {
        "hierarchy": [
          "tgn:5004181",
          "tgn:1000003",
          "tgn:7003122",
          "tgn:1001737",
          "tgn:1000080",
          "tgn:7029392"
        ],
        "placetype": [
          "aat:300008795"
        ],
        "id": 5004181,
        "name:xx": "Monte Casale"
      }
    },
    {
      "geometry": {
        "type": "Point",
        "coordinates": [
          12.1,
          43.183333
        ]
      },
      "type": "Feature",
      "properties": {
        "hierarchy": [
          "tgn:5004183",
          "tgn:7003170",
          "tgn:1000003",
          "tgn:7003125",
          "tgn:1000080",
          "tgn:7005067",
          "tgn:7029392"
        ],
        "placetype": [
          "aat:300008791"
        ],
        "id": 5004183,
        "name:xx": "Isola Maggiore"
      }
    }
  ]
}
