{
  "geometry": {
    "type": "Point",
    "coordinates": [
      -82.8833,
      41.05
    ]
  },
  "type": "Feature",
  "properties": {
    "hierarchy": [
      "tgn:2078287",
      "tgn:1000001",
      "tgn:7012149",
      "tgn:1002883",
      "tgn:7007706",
      "tgn:7029392"
    ],
    "placetype": [
      "aat:300008347"
    ],
    "id": 2078287,
    "name:xx": "Attica"
  }
}
