{
  "geometry": {
    "type": "Point",
    "coordinates": [
      -86.3167,
      35.0167
    ]
  },
  "type": "Feature",
  "properties": {
    "hierarchy": [
      "tgn:2622668",
      "tgn:1000001",
      "tgn:7012149",
      "tgn:7007825",
      "tgn:7029392"
    ],
    "placetype": [
      "aat:300008706"
    ],
    "id": 2622668,
    "name:xx": "Robinson Creek"
  }
}
