{
  "geometry": {
    "type": "Point",
    "coordinates": [
      -104.1833,
      30.9167
    ]
  },
  "type": "Feature",
  "properties": {
    "hierarchy": [
      "tgn:2510351",
      "tgn:1000001",
      "tgn:7012149",
      "tgn:2002010",
      "tgn:7007826",
      "tgn:7029392"
    ],
    "placetype": [
      "aat:300006191"
    ],
    "id": 2510351,
    "name:xx": "Middle Rock House Tank"
  }
}
