{
  "geometry": {
    "type": "Point",
    "coordinates": [
      -71.2333,
      43.2167
    ]
  },
  "type": "Feature",
  "properties": {
    "hierarchy": [
      "tgn:2550519",
      "tgn:1000001",
      "tgn:7014352",
      "tgn:7012149",
      "tgn:7007564",
      "tgn:7029392"
    ],
    "placetype": [
      "aat:300008347"
    ],
    "id": 2550519,
    "name:xx": "Northwood Narrows"
  }
}
