{
  "geometry": {
    "type": "Point",
    "coordinates": [
      -110.0667,
      45.2333
    ]
  },
  "type": "Feature",
  "properties": {
    "hierarchy": [
      "tgn:2427415",
      "tgn:1000001",
      "tgn:7012149",
      "tgn:2001308",
      "tgn:7007524",
      "tgn:7029392"
    ],
    "placetype": [
      "aat:300008798"
    ],
    "id": 2427415,
    "name:xx": "Jordan Mountain"
  }
}
