{
  "geometry": {
    "type": "Point",
    "coordinates": [
      79.188509,
      26.790322
    ]
  },
  "type": "Feature",
  "properties": {
    "hierarchy": [
      "tgn:7562196",
      "tgn:1000004",
      "tgn:7000198",
      "tgn:7016722",
      "tgn:7029392"
    ],
    "placetype": [
      "aat:300008347"
    ],
    "name:en": "Nagla Mahājīr",
    "id": 7562196
  }
}
