{
  "type": "FeatureCollection",
  "features": [
    {
      "geometry": {
        "type": "Point",
        "coordinates": [
          11.866667,
          44.766667
        ]
      },
      "type": "Feature",
      "properties": {
        "hierarchy": [
          "tgn:7042380",
          "tgn:7003128",
          "tgn:1000003",
          "tgn:7008516",
          "tgn:1000080",
          "tgn:7029392"
        ],
        "placetype": [
          "aat:300008347"
        ],
        "id": 7042380,
        "name:xx": "Rovereto"
      }
    },
    {
      "geometry": {
        "type": "Point",
        "coordinates": [
          11.95,
          43.933333
        ]
      },
      "type": "Feature",
      "properties": {
        "hierarchy": [
          "tgn:7042381",
          "tgn:7003129",
          "tgn:1000003",
          "tgn:7008516",
          "tgn:1000080",
          "tgn:7029392"
        ],
        "placetype": [
          "aat:300008347"
        ],
        "id": 7042381,
        "name:xx": "Rovereti"
      }
    },
    {
      "geometry": {
        "type": "Point",
        "coordinates": [
          12.617778,
          46.003889
        ]
      },
      "type": "Feature",
      "properties": {
        "hierarchy": [
          "tgn:7042382",
          "tgn:1003488",
          "tgn:1000003",
          "tgn:7002993",
          "tgn:1000080",
          "tgn:7029392"
        ],
        "placetype": [
          "aat:300008347"
        ],
        "id": 7042382,
        "name:xx": "Roveredo in Piano"
      }
    },
    {
      "geometry": {
        "type": "Point",
        "coordinates": [
          13.25,
          46.4
        ]
      },
      "type": "Feature",
      "properties": {
        "hierarchy": [
          "tgn:7042383",
          "tgn:1003506",
          "tgn:1000003",
          "tgn:7002993",
          "tgn:1000080",
          "tgn:7029392"
        ],
        "placetype": [
          "aat:300008347"
        ],
        "id": 7042383,
        "name:xx": "Roveredo"
      }
    },
    {
      "geometry": {
        "type": "Point",
        "coordinates": [
          11.983333,
          44.2
        ]
      },
      "type": "Feature",
      "properties": {
        "hierarchy": [
          "tgn:7042385",
          "tgn:7003129",
          "tgn:1000003",
          "tgn:7008516",
          "tgn:1000080",
          "tgn:7029392"
        ],
        "placetype": [
          "aat:300008347"
        ],
        "id": 7042385,
        "name:xx": "Rovere"
      }
    },
    {
      "geometry": {
        "type": "Point",
        "coordinates": [
          8.1,
          43.916667
        ]
      },
      "type": "Feature",
      "properties": {
        "hierarchy": [
          "tgn:7042386",
          "tgn:1000003",
          "tgn:7003141",
          "tgn:7003236",
          "tgn:1000080",
          "tgn:7029392"
        ],
        "placetype": [
          "aat:300008347"
        ],
        "id": 7042386,
        "name:xx": "Rovere"
      }
    },
    {
      "geometry": {
        "type": "Point",
        "coordinates": [
          11.75,
          45.066667
        ]
      },
      "type": "Feature",
      "properties": {
        "hierarchy": [
          "tgn:7042388",
          "tgn:7002995",
          "tgn:1000003",
          "tgn:7002997",
          "tgn:1000080",
          "tgn:7029392"
        ],
        "placetype": [
          "aat:300008347"
        ],
        "id": 7042388,
        "name:xx": "Roverdicrè"
      }
    }
  ]
}
