{
  "geometry": {
    "type": "Point",
    "coordinates": [
      -76.2833,
      39.4167
    ]
  },
  "type": "Feature",
  "properties": {
    "hierarchy": [
      "tgn:2484060",
      "tgn:1000001",
      "tgn:7016102",
      "tgn:7012149",
      "tgn:7007516",
      "tgn:7029392"
    ],
    "placetype": [
      "aat:300008706"
    ],
    "id": 2484060,
    "name:xx": "Lauderick Creek"
  }
}
