{
  "geometry": {
    "type": "Point",
    "coordinates": [
      -74.0833,
      42.0833
    ]
  },
  "type": "Feature",
  "properties": {
    "hierarchy": [
      "tgn:2645476",
      "tgn:1000001",
      "tgn:7012149",
      "tgn:1002961",
      "tgn:7007568",
      "tgn:7029392"
    ],
    "placetype": [
      "aat:300008699"
    ],
    "id": 2645476,
    "name:xx": "Saw Kill"
  }
}
