{
  "geometry": {
    "type": "Point",
    "coordinates": [
      -112.1833,
      34.4167
    ]
  },
  "type": "Feature",
  "properties": {
    "hierarchy": [
      "tgn:2696045",
      "tgn:1000001",
      "tgn:7006451",
      "tgn:7012149",
      "tgn:2000103",
      "tgn:7029392"
    ],
    "placetype": [
      "aat:300000390"
    ],
    "id": 2696045,
    "name:xx": "Stoddard Mine"
  }
}
