{
  "geometry": {
    "type": "Point",
    "coordinates": [
      39.2667,
      49.5833
    ]
  },
  "type": "Feature",
  "properties": {
    "hierarchy": [
      "tgn:1053695",
      "tgn:1000003",
      "tgn:7012067",
      "tgn:7006660",
      "tgn:7029392"
    ],
    "placetype": [
      "aat:300008347"
    ],
    "id": 1053695,
    "name:xx": "Dontsivka"
  }
}
