{
  "geometry": {
    "type": "Point",
    "coordinates": [
      -53.7333,
      -32.75
    ]
  },
  "type": "Feature",
  "properties": {
    "hierarchy": [
      "tgn:1024952",
      "tgn:7002646",
      "tgn:1000002",
      "tgn:1000058",
      "tgn:7029392"
    ],
    "placetype": [
      "aat:300008347"
    ],
    "id": 1024952,
    "name:xx": "Plácido Rosas"
  }
}
