{
  "geometry": {
    "type": "Point",
    "coordinates": [
      -89.3667,
      32.25
    ]
  },
  "type": "Feature",
  "properties": {
    "hierarchy": [
      "tgn:2748126",
      "tgn:1000001",
      "tgn:7012149",
      "tgn:2001147",
      "tgn:7007522",
      "tgn:7029392"
    ],
    "placetype": [
      "aat:300008798"
    ],
    "id": 2748126,
    "name:xx": "Walk Hill"
  }
}
