{
  "geometry": {
    "type": "Point",
    "coordinates": [
      27.85,
      30.733333
    ]
  },
  "type": "Feature",
  "properties": {
    "hierarchy": [
      "tgn:7533400",
      "tgn:7001242",
      "tgn:7016833",
      "tgn:1001418",
      "tgn:7029392"
    ],
    "placetype": [
      "aat:300005926"
    ],
    "name:en": "Qabr Ḥamîd",
    "id": 7533400
  }
}
