{
  "geometry": {
    "type": "Point",
    "coordinates": [
      -124.2667,
      48.15
    ]
  },
  "type": "Feature",
  "properties": {
    "hierarchy": [
      "tgn:2602500",
      "tgn:1000001",
      "tgn:1002271",
      "tgn:7012149",
      "tgn:7007920",
      "tgn:7029392"
    ],
    "placetype": [
      "aat:300008707"
    ],
    "id": 2602500,
    "name:xx": "Pysht River"
  }
}
