{
  "geometry": {
    "type": "Point",
    "coordinates": [
      -63.0667,
      -12.6667
    ]
  },
  "type": "Feature",
  "properties": {
    "hierarchy": [
      "tgn:1129296",
      "tgn:1001944",
      "tgn:1000047",
      "tgn:7002456",
      "tgn:1000002",
      "tgn:7029392"
    ],
    "placetype": [
      "aat:300008707"
    ],
    "id": 1129296,
    "name:xx": "São Simão"
  }
}
