{
  "geometry": {
    "type": "Point",
    "coordinates": [
      -112.3667,
      37.5333
    ]
  },
  "type": "Feature",
  "properties": {
    "hierarchy": [
      "tgn:2685897",
      "tgn:1000001",
      "tgn:7012149",
      "tgn:7007827",
      "tgn:7029392"
    ],
    "placetype": [
      "aat:300008699"
    ],
    "id": 2685897,
    "name:xx": "Spring Branch"
  }
}
