{
  "geometry": {
    "type": "Point",
    "coordinates": [
      -88.05,
      43.5167
    ]
  },
  "type": "Feature",
  "properties": {
    "hierarchy": [
      "tgn:2734849",
      "tgn:1000001",
      "tgn:7012149",
      "tgn:1002998",
      "tgn:7007922",
      "tgn:7029392"
    ],
    "placetype": [
      "aat:300008680"
    ],
    "id": 2734849,
    "name:xx": "Twelve, Lake"
  }
}
