{
  "type": "FeatureCollection",
  "features": [
    {
      "geometry": {
        "type": "Point",
        "coordinates": [
          -81.35,
          38.3833
        ]
      },
      "type": "Feature",
      "properties": {
        "hierarchy": [
          "tgn:2320030",
          "tgn:1000001",
          "tgn:7012149",
          "tgn:2002270",
          "tgn:7013961",
          "tgn:7029392"
        ],
        "placetype": [
          "aat:300008699"
        ],
        "id": 2320030,
        "name:xx": "Evans Fork"
      }
    },
    {
      "geometry": {
        "type": "Point",
        "coordinates": [
          -118.8167,
          36.7667
        ]
      },
      "type": "Feature",
      "properties": {
        "hierarchy": [
          "tgn:2320031",
          "tgn:1000001",
          "tgn:7012149",
          "tgn:1002392",
          "tgn:7007157",
          "tgn:7029392"
        ],
        "placetype": [
          "aat:300132451"
        ],
        "id": 2320031,
        "name:xx": "Evans Grove"
      }
    },
    {
      "geometry": {
        "type": "Point",
        "coordinates": [
          -106.2,
          39.25
        ]
      },
      "type": "Feature",
      "properties": {
        "hierarchy": [
          "tgn:2320032",
          "tgn:1000001",
          "tgn:7012149",
          "tgn:2000224",
          "tgn:7007158",
          "tgn:7029392"
        ],
        "placetype": [
          "aat:300008761"
        ],
        "id": 2320032,
        "name:xx": "Evans Gulch"
      }
    },
    {
      "geometry": {
        "type": "Point",
        "coordinates": [
          -105.4833,
          37.7
        ]
      },
      "type": "Feature",
      "properties": {
        "hierarchy": [
          "tgn:2320033",
          "tgn:2000193",
          "tgn:1000001",
          "tgn:7012149",
          "tgn:7007158",
          "tgn:7029392"
        ],
        "placetype": [
          "aat:300008761"
        ],
        "id": 2320033,
        "name:xx": "Evans Gulch"
      }
    },
    {
      "geometry": {
        "type": "Point",
        "coordinates": [
          -115.6833,
          47.5167
        ]
      },
      "type": "Feature",
      "properties": {
        "hierarchy": [
          "tgn:2320034",
          "tgn:1000001",
          "tgn:7012149",
          "tgn:2001304",
          "tgn:7007524",
          "tgn:7029392"
        ],
        "placetype": [
          "aat:300008761"
        ],
        "id": 2320034,
        "name:xx": "Evans Gulch"
      }
    },
    {
      "geometry": {
        "type": "Point",
        "coordinates": [
          -117.7667,
          44.4667
        ]
      },
      "type": "Feature",
      "properties": {
        "hierarchy": [
          "tgn:2320035",
          "tgn:7013349",
          "tgn:1000001",
          "tgn:7012149",
          "tgn:7007708",
          "tgn:7029392"
        ],
        "placetype": [
          "aat:300008761"
        ],
        "id": 2320035,
        "name:xx": "Evans Gulch"
      }
    },
    {
      "geometry": {
        "type": "Point",
        "coordinates": [
          -123.1333,
          42.6
        ]
      },
      "type": "Feature",
      "properties": {
        "hierarchy": [
          "tgn:2320036",
          "tgn:1000001",
          "tgn:7012149",
          "tgn:2001711",
          "tgn:7007708",
          "tgn:7029392"
        ],
        "placetype": [
          "aat:300008761"
        ],
        "id": 2320036,
        "name:xx": "Evans Gulch"
      }
    },
    {
      "geometry": {
        "type": "Point",
        "coordinates": [
          -106.2,
          39.25
        ]
      },
      "type": "Feature",
      "properties": {
        "hierarchy": [
          "tgn:2320037",
          "tgn:1000001",
          "tgn:7012149",
          "tgn:2000224",
          "tgn:7007158",
          "tgn:7029392"
        ],
        "placetype": [
          "aat:300006191"
        ],
        "id": 2320037,
        "name:xx": "Evans Gulch Number 2 Reservoir"
      }
    },
    {
      "geometry": {
        "type": "Point",
        "coordinates": [
          -70.8,
          44.15
        ]
      },
      "type": "Feature",
      "properties": {
        "hierarchy": [
          "tgn:2320038",
          "tgn:1000001",
          "tgn:7012149",
          "tgn:2000926",
          "tgn:7007515",
          "tgn:7029392"
        ],
        "placetype": [
          "aat:300008798"
        ],
        "id": 2320038,
        "name:xx": "Evans Hill"
      }
    }
  ]
}
