{
  "geometry": {
    "type": "Point",
    "coordinates": [
      -108.55,
      33.7667
    ]
  },
  "type": "Feature",
  "properties": {
    "hierarchy": [
      "tgn:2473519",
      "tgn:1000001",
      "tgn:2001429",
      "tgn:7012149",
      "tgn:7007566",
      "tgn:7029392"
    ],
    "placetype": [
      "aat:300008697"
    ],
    "id": 2473519,
    "name:xx": "Lower Cold Spring"
  }
}
