{
  "geometry": {
    "type": "Point",
    "coordinates": [
      79.29191,
      26.141669
    ]
  },
  "type": "Feature",
  "properties": {
    "hierarchy": [
      "tgn:7565036",
      "tgn:1000004",
      "tgn:7000198",
      "tgn:7016722",
      "tgn:7029392"
    ],
    "placetype": [
      "aat:300008347"
    ],
    "name:en": "Surhār",
    "id": 7565036
  }
}
