{
  "geometry": {
    "type": "Point",
    "coordinates": [
      31.3333,
      53.2833
    ]
  },
  "type": "Feature",
  "properties": {
    "hierarchy": [
      "tgn:1058460",
      "tgn:7011700",
      "tgn:1000003",
      "tgn:7006657",
      "tgn:7029392"
    ],
    "placetype": [
      "aat:300008347"
    ],
    "id": 1058460,
    "name:xx": "Počepy"
  }
}
