{
  "geometry": {
    "type": "Point",
    "coordinates": [
      8.35,
      50.25
    ]
  },
  "type": "Feature",
  "properties": {
    "hierarchy": [
      "tgn:7196024",
      "tgn:1000003",
      "tgn:7003678",
      "tgn:7000084",
      "tgn:7029392"
    ],
    "placetype": [
      "aat:300008777"
    ],
    "id": 7196024,
    "name:xx": "Dinkelstein"
  }
}
