{
  "type": "FeatureCollection",
  "features": [
    {
      "geometry": {
        "type": "Point",
        "coordinates": [
          -76.8833,
          40.95
        ]
      },
      "type": "Feature",
      "properties": {
        "hierarchy": [
          "tgn:7013880",
          "tgn:1000001",
          "tgn:7012149",
          "tgn:1002965",
          "tgn:7007710",
          "tgn:7029392"
        ],
        "placetype": [
          "aat:300008347"
        ],
        "id": 7013880,
        "name:xx": "Lewisburg"
      }
    },
    {
      "geometry": {
        "type": "Point",
        "coordinates": [
          7.716667,
          51.466667
        ]
      },
      "type": "Feature",
      "properties": {
        "hierarchy": [
          "tgn:7013884",
          "tgn:1000003",
          "tgn:7003677",
          "tgn:7000084",
          "tgn:7029392"
        ],
        "placetype": [
          "aat:300008347"
        ],
        "id": 7013884,
        "name:xx": "Ardey"
      }
    },
    {
      "geometry": {
        "type": "Point",
        "coordinates": [
          -70.2,
          44.1
        ]
      },
      "type": "Feature",
      "properties": {
        "hierarchy": [
          "tgn:7013885",
          "tgn:2000918",
          "tgn:1000001",
          "tgn:7012149",
          "tgn:7007515",
          "tgn:7029392"
        ],
        "placetype": [
          "aat:300387277",
          "aat:300008347",
          "aat:300008389",
          "aat:300387308",
          "aat:300264742",
          "aat:300387512",
          "aat:300387291"
        ],
        "id": 7013885,
        "name:xx": "Lewiston"
      }
    },
    {
      "geometry": {
        "type": "Point",
        "coordinates": [
          -79.0333,
          43.1667
        ]
      },
      "type": "Feature",
      "properties": {
        "hierarchy": [
          "tgn:7013886",
          "tgn:1000001",
          "tgn:7012149",
          "tgn:1002718",
          "tgn:7007568",
          "tgn:7029392"
        ],
        "placetype": [
          "aat:300008347"
        ],
        "id": 7013886,
        "name:xx": "Lewiston"
      }
    },
    {
      "geometry": {
        "type": "Point",
        "coordinates": [
          -84.5,
          38.0333
        ]
      },
      "type": "Feature",
      "properties": {
        "hierarchy": [
          "tgn:7013887",
          "tgn:1000001",
          "tgn:7012149",
          "tgn:1002371",
          "tgn:7007255",
          "tgn:7029392"
        ],
        "placetype": [
          "aat:300008347",
          "aat:300008416",
          "aat:300008389",
          "aat:300387276",
          "aat:300387308",
          "aat:300005135",
          "aat:300387265",
          "aat:300387285",
          "aat:300387293"
        ],
        "id": 7013887,
        "name:xx": "Lexington"
      }
    },
    {
      "geometry": {
        "type": "Point",
        "coordinates": [
          -71.2167,
          42.4333
        ]
      },
      "type": "Feature",
      "properties": {
        "hierarchy": [
          "tgn:7013888",
          "tgn:1000001",
          "tgn:1002665",
          "tgn:7012149",
          "tgn:7007517",
          "tgn:7029392"
        ],
        "placetype": [
          "aat:300008347",
          "aat:300000835"
        ],
        "id": 7013888,
        "name:xx": "Lexington"
      }
    },
    {
      "geometry": {
        "type": "Point",
        "coordinates": [
          -79.4333,
          37.7833
        ]
      },
      "type": "Feature",
      "properties": {
        "hierarchy": [
          "tgn:7013889",
          "tgn:1000001",
          "tgn:7012149",
          "tgn:2002216",
          "tgn:7007919",
          "tgn:7029392"
        ],
        "placetype": [
          "aat:300008347"
        ],
        "id": 7013889,
        "name:xx": "Lexington"
      }
    }
  ]
}
