{
  "geometry": {
    "type": "Point",
    "coordinates": [
      9.8833,
      55.4667
    ]
  },
  "type": "Feature",
  "properties": {
    "hierarchy": [
      "tgn:1028026",
      "tgn:1000003",
      "tgn:7594009",
      "tgn:1000066",
      "tgn:7029392"
    ],
    "placetype": [
      "aat:300008347"
    ],
    "id": 1028026,
    "name:xx": "Nørre Åby"
  }
}
