{
  "geometry": {
    "type": "Point",
    "coordinates": [
      -91.8667,
      46.3833
    ]
  },
  "type": "Feature",
  "properties": {
    "hierarchy": [
      "tgn:2307126",
      "tgn:1000001",
      "tgn:2002318",
      "tgn:7012149",
      "tgn:7007922",
      "tgn:7029392"
    ],
    "placetype": [
      "aat:300008707"
    ],
    "id": 2307126,
    "name:xx": "East Fork Moose River"
  }
}
