{
  "geometry": {
    "type": "Point",
    "coordinates": [
      -111.6667,
      42.1667
    ]
  },
  "type": "Feature",
  "properties": {
    "hierarchy": [
      "tgn:2682404",
      "tgn:1000001",
      "tgn:7012149",
      "tgn:2000472",
      "tgn:7007250",
      "tgn:7029392"
    ],
    "placetype": [
      "aat:300386845"
    ],
    "id": 2682404,
    "name:xx": "South Worm Creek Basin"
  }
}
