{
  "geometry": {
    "type": "Point",
    "coordinates": [
      79.9366,
      27.1696
    ]
  },
  "type": "Feature",
  "properties": {
    "hierarchy": [
      "tgn:7562038",
      "tgn:1000004",
      "tgn:7000198",
      "tgn:7016722",
      "tgn:7029392"
    ],
    "placetype": [
      "aat:300008347"
    ],
    "name:en": "Rāmpur Majhiāra",
    "id": 7562038
  }
}
