{
  "type": "FeatureCollection",
  "features": [
    {
      "geometry": {
        "type": "Point",
        "coordinates": [
          -86.9,
          40.25
        ]
      },
      "type": "Feature",
      "properties": {
        "hierarchy": [
          "tgn:2433270",
          "tgn:1000001",
          "tgn:7012149",
          "tgn:1002946",
          "tgn:7007252",
          "tgn:7029392"
        ],
        "placetype": [
          "aat:300006075"
        ],
        "id": 2433270,
        "name:xx": "Kellerman Leaming Ditch"
      }
    },
    {
      "geometry": {
        "type": "Point",
        "coordinates": [
          -87.3167,
          33.35
        ]
      },
      "type": "Feature",
      "properties": {
        "hierarchy": [
          "tgn:2433271",
          "tgn:7002659",
          "tgn:1000001",
          "tgn:7012149",
          "tgn:2000062",
          "tgn:7029392"
        ],
        "placetype": [
          "aat:300000390"
        ],
        "id": 2433271,
        "name:xx": "Kellerman Mine"
      }
    },
    {
      "geometry": {
        "type": "Point",
        "coordinates": [
          -87.3333,
          33.3333
        ]
      },
      "type": "Feature",
      "properties": {
        "hierarchy": [
          "tgn:2433272",
          "tgn:7002659",
          "tgn:1000001",
          "tgn:7012149",
          "tgn:2000062",
          "tgn:7029392"
        ],
        "placetype": [
          "aat:300000390"
        ],
        "id": 2433272,
        "name:xx": "Kellerman Number 1 Mine"
      }
    },
    {
      "geometry": {
        "type": "Point",
        "coordinates": [
          -87.3,
          33.2833
        ]
      },
      "type": "Feature",
      "properties": {
        "hierarchy": [
          "tgn:2433273",
          "tgn:7002659",
          "tgn:1000001",
          "tgn:7012149",
          "tgn:2000062",
          "tgn:7029392"
        ],
        "placetype": [
          "aat:300000390"
        ],
        "id": 2433273,
        "name:xx": "Kellerman Number 2 Mine"
      }
    },
    {
      "geometry": {
        "type": "Point",
        "coordinates": [
          -74.4,
          43.9833
        ]
      },
      "type": "Feature",
      "properties": {
        "hierarchy": [
          "tgn:2433275",
          "tgn:1000001",
          "tgn:7012149",
          "tgn:1002440",
          "tgn:7007568",
          "tgn:7029392"
        ],
        "placetype": [
          "aat:300132316"
        ],
        "id": 2433275,
        "name:xx": "Kellers Bay"
      }
    },
    {
      "geometry": {
        "type": "Point",
        "coordinates": [
          -91.0833,
          30.9333
        ]
      },
      "type": "Feature",
      "properties": {
        "hierarchy": [
          "tgn:2433276",
          "tgn:1000001",
          "tgn:2000872",
          "tgn:7012149",
          "tgn:7007256",
          "tgn:7029392"
        ],
        "placetype": [
          "aat:300008699"
        ],
        "id": 2433276,
        "name:xx": "Kellers Bayou"
      }
    },
    {
      "geometry": {
        "type": "Point",
        "coordinates": [
          -112.0167,
          43.7667
        ]
      },
      "type": "Feature",
      "properties": {
        "hierarchy": [
          "tgn:2433277",
          "tgn:1000001",
          "tgn:7012149",
          "tgn:2000477",
          "tgn:7007250",
          "tgn:7029392"
        ],
        "placetype": [
          "aat:300008791"
        ],
        "id": 2433277,
        "name:xx": "Kellers Island"
      }
    },
    {
      "geometry": {
        "type": "Point",
        "coordinates": [
          -91.6833,
          31
        ]
      },
      "type": "Feature",
      "properties": {
        "hierarchy": [
          "tgn:2433278",
          "tgn:1000001",
          "tgn:7012149",
          "tgn:2000892",
          "tgn:7007256",
          "tgn:7029392"
        ],
        "placetype": [
          "aat:300008680"
        ],
        "id": 2433278,
        "name:xx": "Kellers Lake"
      }
    },
    {
      "geometry": {
        "type": "Point",
        "coordinates": [
          -84.1,
          39.2667
        ]
      },
      "type": "Feature",
      "properties": {
        "hierarchy": [
          "tgn:2433279",
          "tgn:1000001",
          "tgn:7012149",
          "tgn:1002987",
          "tgn:7007706",
          "tgn:7029392"
        ],
        "placetype": [
          "aat:300008699"
        ],
        "id": 2433279,
        "name:xx": "Kellers Run"
      }
    }
  ]
}
