{
  "geometry": {
    "type": "Point",
    "coordinates": [
      -113.6333,
      41.8667
    ]
  },
  "type": "Feature",
  "properties": {
    "hierarchy": [
      "tgn:2626037",
      "tgn:1000001",
      "tgn:2002102",
      "tgn:7012149",
      "tgn:7007827",
      "tgn:7029392"
    ],
    "placetype": [
      "aat:300008761"
    ],
    "id": 2626037,
    "name:xx": "Rocky Canyon"
  }
}
