{
  "geometry": {
    "type": "Point",
    "coordinates": [
      -97.9167,
      30.8167
    ]
  },
  "type": "Feature",
  "properties": {
    "hierarchy": [
      "tgn:2105886",
      "tgn:1000001",
      "tgn:7012149",
      "tgn:2001949",
      "tgn:7007826",
      "tgn:7029392"
    ],
    "placetype": [
      "aat:300008347",
      "aat:300387210"
    ],
    "id": 2105886,
    "name:xx": "Mahomet"
  }
}
