{
  "geometry": {
    "type": "Point",
    "coordinates": [
      -149.6667,
      63.45
    ]
  },
  "type": "Feature",
  "properties": {
    "hierarchy": [
      "tgn:2307675",
      "tgn:7006450",
      "tgn:1000001",
      "tgn:7030547",
      "tgn:7012149",
      "tgn:7029392"
    ],
    "placetype": [
      "aat:300008707"
    ],
    "id": 2307675,
    "name:xx": "East Fork Toklat River"
  }
}
