{
  "type": "FeatureCollection",
  "features": [
    {
      "geometry": {
        "type": "Point",
        "coordinates": [
          -0.0833,
          22.5833
        ]
      },
      "type": "Feature",
      "properties": {
        "hierarchy": [
          "tgn:1127740",
          "tgn:7002445",
          "tgn:7011980",
          "tgn:1000003",
          "tgn:7008591",
          "tgn:7029392"
        ],
        "placetype": [
          "aat:300008707"
        ],
        "id": 1127740,
        "name:xx": "New Bedford"
      }
    },
    {
      "geometry": {
        "type": "Point",
        "coordinates": [
          -109.8,
          43.1833
        ]
      },
      "type": "Feature",
      "properties": {
        "hierarchy": [
          "tgn:1127741",
          "tgn:1000001",
          "tgn:7012149",
          "tgn:2002382",
          "tgn:7007923",
          "tgn:7029392"
        ],
        "placetype": [
          "aat:300008707"
        ],
        "id": 1127741,
        "name:xx": "New Fork"
      }
    },
    {
      "geometry": {
        "type": "Point",
        "coordinates": [
          -99.266667,
          16.9
        ]
      },
      "type": "Feature",
      "properties": {
        "hierarchy": [
          "tgn:1127746",
          "tgn:1000001",
          "tgn:7005590",
          "tgn:7005560",
          "tgn:7029392"
        ],
        "placetype": [
          "aat:300008707",
          "aat:300008699"
        ],
        "id": 1127746,
        "name:xx": "Nexpa, Río"
      }
    },
    {
      "geometry": {
        "type": "Point",
        "coordinates": [
          39.931,
          0.466
        ]
      },
      "type": "Feature",
      "properties": {
        "hierarchy": [
          "tgn:1127748",
          "tgn:7001242",
          "tgn:1000169",
          "tgn:7029392"
        ],
        "placetype": [
          "aat:300008707"
        ],
        "id": 1127748,
        "name:xx": "Ng'iro, Ewaso"
      }
    },
    {
      "geometry": {
        "type": "Point",
        "coordinates": [
          13.8167,
          12.6833
        ]
      },
      "type": "Feature",
      "properties": {
        "hierarchy": [
          "tgn:1127749",
          "tgn:7001242",
          "tgn:7000542",
          "tgn:1000182",
          "tgn:7029392"
        ],
        "placetype": [
          "aat:300008707"
        ],
        "id": 1127749,
        "name:xx": "Nqadda"
      }
    }
  ]
}
