{
  "geometry": {
    "type": "Point",
    "coordinates": [
      -66.3333,
      -32.9167
    ]
  },
  "type": "Feature",
  "properties": {
    "hierarchy": [
      "tgn:1019556",
      "tgn:7006477",
      "tgn:1001520",
      "tgn:1000002",
      "tgn:7029392"
    ],
    "placetype": [
      "aat:300008347"
    ],
    "id": 1019556,
    "name:xx": "Hipólito Yrigoyen"
  }
}
