{
  "type": "FeatureCollection",
  "features": [
    {
      "geometry": {
        "type": "Point",
        "coordinates": [
          -104.55,
          63.6167
        ]
      },
      "type": "Feature",
      "properties": {
        "hierarchy": [
          "tgn:1124550",
          "tgn:7005685",
          "tgn:1000001",
          "tgn:1000296",
          "tgn:7029392"
        ],
        "placetype": [
          "aat:300008707"
        ],
        "id": 1124550,
        "name:xx": "Hanbury"
      }
    },
    {
      "geometry": {
        "type": "Point",
        "coordinates": [
          36,
          9.5833
        ]
      },
      "type": "Feature",
      "properties": {
        "hierarchy": [
          "tgn:1124551",
          "tgn:7001242",
          "tgn:1001597",
          "tgn:7000489",
          "tgn:7029392"
        ],
        "placetype": [
          "aat:300008707"
        ],
        "id": 1124551,
        "name:xx": "Hanger Wenz"
      }
    },
    {
      "geometry": {
        "type": "Point",
        "coordinates": [
          4.1833,
          50.3167
        ]
      },
      "type": "Feature",
      "properties": {
        "hierarchy": [
          "tgn:1124554",
          "tgn:1000003",
          "tgn:7029392"
        ],
        "placetype": [
          "aat:300008707"
        ],
        "name:fr": "Hantes",
        "id": 1124554
      }
    },
    {
      "geometry": {
        "type": "Point",
        "coordinates": [
          -72.4333,
          67.5333
        ]
      },
      "type": "Feature",
      "properties": {
        "hierarchy": [
          "tgn:1124555",
          "tgn:7013003",
          "tgn:7005685",
          "tgn:1000001",
          "tgn:7024197",
          "tgn:7029392"
        ],
        "placetype": [
          "aat:300008707"
        ],
        "id": 1124555,
        "name:xx": "Hantzsch"
      }
    },
    {
      "geometry": {
        "type": "Point",
        "coordinates": [
          38.871,
          41.009
        ]
      },
      "type": "Feature",
      "properties": {
        "hierarchy": [
          "tgn:1124558",
          "tgn:1001258",
          "tgn:1000004",
          "tgn:7018454",
          "tgn:1000144",
          "tgn:7029392"
        ],
        "placetype": [
          "aat:300008707"
        ],
        "id": 1124558,
        "name:xx": "Doğankent Çayı"
      }
    }
  ]
}
