{
  "geometry": {
    "type": "Point",
    "coordinates": [
      -76.45,
      39.6833
    ]
  },
  "type": "Feature",
  "properties": {
    "hierarchy": [
      "tgn:2376962",
      "tgn:1000001",
      "tgn:7016102",
      "tgn:7012149",
      "tgn:7007516",
      "tgn:7029392"
    ],
    "placetype": [
      "aat:300008347"
    ],
    "id": 2376962,
    "name:xx": "Harkins"
  }
}
