{
  "geometry": {
    "type": "Point",
    "coordinates": [
      -98.8167,
      28.9167
    ]
  },
  "type": "Feature",
  "properties": {
    "hierarchy": [
      "tgn:2106050",
      "tgn:1000001",
      "tgn:7012149",
      "tgn:2001987",
      "tgn:7007826",
      "tgn:7029392"
    ],
    "placetype": [
      "aat:300008347",
      "aat:300387210"
    ],
    "id": 2106050,
    "name:xx": "Miguel"
  }
}
