{
  "geometry": {
    "type": "Point",
    "coordinates": [
      31.297456,
      30.04268
    ]
  },
  "type": "Feature",
  "properties": {
    "hierarchy": [
      "tgn:7526160",
      "tgn:7001242",
      "tgn:7016833",
      "tgn:1001091",
      "tgn:7029392"
    ],
    "placetype": [
      "aat:300004792"
    ],
    "id": 7526160,
    "name:xx": "Makhbaz Ālī"
  }
}
