{
  "geometry": {
    "type": "Point",
    "coordinates": [
      -89.3833,
      38.0833
    ]
  },
  "type": "Feature",
  "properties": {
    "hierarchy": [
      "tgn:2581818",
      "tgn:1000001",
      "tgn:7012149",
      "tgn:2000522",
      "tgn:7007251",
      "tgn:7029392"
    ],
    "placetype": [
      "aat:300006191"
    ],
    "id": 2581818,
    "name:xx": "Pinckneyville Reservoir"
  }
}
