{
  "geometry": {
    "type": "Point",
    "coordinates": [
      -88.15,
      35.2333
    ]
  },
  "type": "Feature",
  "properties": {
    "hierarchy": [
      "tgn:2173755",
      "tgn:1000001",
      "tgn:7012149",
      "tgn:2001872",
      "tgn:7007825",
      "tgn:7029392"
    ],
    "placetype": [
      "aat:300008699"
    ],
    "id": 2173755,
    "name:xx": "Bird Branch"
  }
}
