{
  "type": "FeatureCollection",
  "features": [
    {
      "geometry": {
        "type": "Point",
        "coordinates": [
          -98.6667,
          44.7833
        ]
      },
      "type": "Feature",
      "properties": {
        "hierarchy": [
          "tgn:2259230",
          "tgn:1000001",
          "tgn:7012149",
          "tgn:2001827",
          "tgn:7007713",
          "tgn:7029392"
        ],
        "placetype": [
          "aat:300008680"
        ],
        "id": 2259230,
        "name:xx": "Cottonwood Lake"
      }
    },
    {
      "geometry": {
        "type": "Point",
        "coordinates": [
          -99.9,
          44.8333
        ]
      },
      "type": "Feature",
      "properties": {
        "hierarchy": [
          "tgn:2259231",
          "tgn:1000001",
          "tgn:7012149",
          "tgn:2001829",
          "tgn:7007713",
          "tgn:7029392"
        ],
        "placetype": [
          "aat:300008680"
        ],
        "id": 2259231,
        "name:xx": "Cottonwood Lake"
      }
    },
    {
      "geometry": {
        "type": "Point",
        "coordinates": [
          -97.4167,
          45.7167
        ]
      },
      "type": "Feature",
      "properties": {
        "hierarchy": [
          "tgn:2259233",
          "tgn:1000001",
          "tgn:2001815",
          "tgn:7012149",
          "tgn:7007713",
          "tgn:7029392"
        ],
        "placetype": [
          "aat:300008680"
        ],
        "id": 2259233,
        "name:xx": "Cottonwood Lake"
      }
    },
    {
      "geometry": {
        "type": "Point",
        "coordinates": [
          -97.6833,
          45.1167
        ]
      },
      "type": "Feature",
      "properties": {
        "hierarchy": [
          "tgn:2259234",
          "tgn:1000001",
          "tgn:2001782",
          "tgn:7012149",
          "tgn:7007713",
          "tgn:7029392"
        ],
        "placetype": [
          "aat:300008680"
        ],
        "id": 2259234,
        "name:xx": "Cottonwood Lake"
      }
    },
    {
      "geometry": {
        "type": "Point",
        "coordinates": [
          -105.9667,
          31.55
        ]
      },
      "type": "Feature",
      "properties": {
        "hierarchy": [
          "tgn:2259235",
          "tgn:1000001",
          "tgn:7012149",
          "tgn:2002005",
          "tgn:7007826",
          "tgn:7029392"
        ],
        "placetype": [
          "aat:300008680"
        ],
        "id": 2259235,
        "name:xx": "Cottonwood Lake"
      }
    },
    {
      "geometry": {
        "type": "Point",
        "coordinates": [
          -101.1167,
          34.35
        ]
      },
      "type": "Feature",
      "properties": {
        "hierarchy": [
          "tgn:2259236",
          "tgn:1000001",
          "tgn:2001946",
          "tgn:7012149",
          "tgn:7007826",
          "tgn:7029392"
        ],
        "placetype": [
          "aat:300006191"
        ],
        "id": 2259236,
        "name:xx": "Cottonwood Lake"
      }
    },
    {
      "geometry": {
        "type": "Point",
        "coordinates": [
          -97.5667,
          33.4
        ]
      },
      "type": "Feature",
      "properties": {
        "hierarchy": [
          "tgn:2259237",
          "tgn:1000001",
          "tgn:7012149",
          "tgn:1003031",
          "tgn:7007826",
          "tgn:7029392"
        ],
        "placetype": [
          "aat:300006191"
        ],
        "id": 2259237,
        "name:xx": "Cottonwood Lake"
      }
    },
    {
      "geometry": {
        "type": "Point",
        "coordinates": [
          -109.4333,
          37.05
        ]
      },
      "type": "Feature",
      "properties": {
        "hierarchy": [
          "tgn:2259238",
          "tgn:1000001",
          "tgn:7012149",
          "tgn:2002119",
          "tgn:7007827",
          "tgn:7029392"
        ],
        "placetype": [
          "aat:300008680"
        ],
        "id": 2259238,
        "name:xx": "Cottonwood Lake"
      }
    },
    {
      "geometry": {
        "type": "Point",
        "coordinates": [
          -121.4167,
          47.3333
        ]
      },
      "type": "Feature",
      "properties": {
        "hierarchy": [
          "tgn:2259239",
          "tgn:1000001",
          "tgn:7012149",
          "tgn:1002553",
          "tgn:7007920",
          "tgn:7029392"
        ],
        "placetype": [
          "aat:300008680"
        ],
        "id": 2259239,
        "name:xx": "Cottonwood Lake"
      }
    }
  ]
}
