{
  "type": "FeatureCollection",
  "features": [
    {
      "geometry": {
        "type": "Point",
        "coordinates": [
          -122.0167,
          40.4167
        ]
      },
      "type": "Feature",
      "properties": {
        "hierarchy": [
          "tgn:2249350",
          "tgn:1000001",
          "tgn:7012149",
          "tgn:7007157",
          "tgn:7029392"
        ],
        "placetype": [
          "aat:300006075"
        ],
        "id": 2249350,
        "name:xx": "Coleman Canal"
      }
    },
    {
      "geometry": {
        "type": "Point",
        "coordinates": [
          -122.1667,
          38.4833
        ]
      },
      "type": "Feature",
      "properties": {
        "hierarchy": [
          "tgn:2249351",
          "tgn:1000001",
          "tgn:7012149",
          "tgn:7007157",
          "tgn:1002706",
          "tgn:7029392"
        ],
        "placetype": [
          "aat:300008761"
        ],
        "id": 2249351,
        "name:xx": "Coleman Canyon"
      }
    },
    {
      "geometry": {
        "type": "Point",
        "coordinates": [
          -121.3,
          36.1333
        ]
      },
      "type": "Feature",
      "properties": {
        "hierarchy": [
          "tgn:2249352",
          "tgn:1000001",
          "tgn:7012149",
          "tgn:7007157",
          "tgn:1002684",
          "tgn:7029392"
        ],
        "placetype": [
          "aat:300008761"
        ],
        "id": 2249352,
        "name:xx": "Coleman Canyon"
      }
    },
    {
      "geometry": {
        "type": "Point",
        "coordinates": [
          -105.0833,
          37.4167
        ]
      },
      "type": "Feature",
      "properties": {
        "hierarchy": [
          "tgn:2249353",
          "tgn:1000001",
          "tgn:7012149",
          "tgn:2000219",
          "tgn:7007158",
          "tgn:7029392"
        ],
        "placetype": [
          "aat:300008761"
        ],
        "id": 2249353,
        "name:xx": "Coleman Canyon"
      }
    },
    {
      "geometry": {
        "type": "Point",
        "coordinates": [
          -111.3833,
          44.15
        ]
      },
      "type": "Feature",
      "properties": {
        "hierarchy": [
          "tgn:2249354",
          "tgn:1000001",
          "tgn:7012149",
          "tgn:2000473",
          "tgn:7007250",
          "tgn:7029392"
        ],
        "placetype": [
          "aat:300008761"
        ],
        "id": 2249354,
        "name:xx": "Coleman Canyon"
      }
    },
    {
      "geometry": {
        "type": "Point",
        "coordinates": [
          -115.7333,
          41.7333
        ]
      },
      "type": "Feature",
      "properties": {
        "hierarchy": [
          "tgn:2249355",
          "tgn:1000001",
          "tgn:2001411",
          "tgn:7012149",
          "tgn:7007526",
          "tgn:7029392"
        ],
        "placetype": [
          "aat:300008761"
        ],
        "id": 2249355,
        "name:xx": "Coleman Canyon"
      }
    },
    {
      "geometry": {
        "type": "Point",
        "coordinates": [
          -119.7167,
          41.9333
        ]
      },
      "type": "Feature",
      "properties": {
        "hierarchy": [
          "tgn:2249356",
          "tgn:1000001",
          "tgn:7012149",
          "tgn:1002999",
          "tgn:7007526",
          "tgn:7029392"
        ],
        "placetype": [
          "aat:300008761"
        ],
        "id": 2249356,
        "name:xx": "Coleman Canyon"
      }
    },
    {
      "geometry": {
        "type": "Point",
        "coordinates": [
          -120.9667,
          44.6333
        ]
      },
      "type": "Feature",
      "properties": {
        "hierarchy": [
          "tgn:2249358",
          "tgn:1000001",
          "tgn:7012149",
          "tgn:2001712",
          "tgn:7007708",
          "tgn:7029392"
        ],
        "placetype": [
          "aat:300008761"
        ],
        "id": 2249358,
        "name:xx": "Coleman Canyon"
      }
    },
    {
      "geometry": {
        "type": "Point",
        "coordinates": [
          -120.7333,
          46.9833
        ]
      },
      "type": "Feature",
      "properties": {
        "hierarchy": [
          "tgn:2249359",
          "tgn:1000001",
          "tgn:7012149",
          "tgn:1002553",
          "tgn:7007920",
          "tgn:7029392"
        ],
        "placetype": [
          "aat:300008761"
        ],
        "id": 2249359,
        "name:xx": "Coleman Canyon"
      }
    }
  ]
}
