{
  "geometry": {
    "type": "Point",
    "coordinates": [
      76.751163,
      30.017443
    ]
  },
  "type": "Feature",
  "properties": {
    "hierarchy": [
      "tgn:7583327",
      "tgn:1000004",
      "tgn:1001871",
      "tgn:7000198",
      "tgn:7029392"
    ],
    "placetype": [
      "aat:300008347"
    ],
    "name:en": "Rāmnagar",
    "id": 7583327
  }
}
