{
  "geometry": {
    "type": "Point",
    "coordinates": [
      128.45,
      36.65
    ]
  },
  "type": "Feature",
  "properties": {
    "hierarchy": [
      "tgn:1082415",
      "tgn:1000004",
      "tgn:1001372",
      "tgn:7000299",
      "tgn:7029392"
    ],
    "placetype": [
      "aat:300008347"
    ],
    "id": 1082415,
    "name:xx": "Yech'ŏn"
  }
}
