{
  "type": "FeatureCollection",
  "features": [
    {
      "geometry": {
        "type": "Point",
        "coordinates": [
          3.75,
          50.833333
        ]
      },
      "type": "Feature",
      "properties": {
        "hierarchy": [
          "tgn:7238936",
          "tgn:7003457",
          "tgn:1000003",
          "tgn:1000063",
          "tgn:7018236",
          "tgn:7029392"
        ],
        "placetype": [
          "aat:300008347"
        ],
        "id": 7238936,
        "name:xx": "Hoeksken"
      }
    },
    {
      "geometry": {
        "type": "Point",
        "coordinates": [
          2.86244,
          50.948036
        ]
      },
      "type": "Feature",
      "properties": {
        "hierarchy": [
          "tgn:7238938",
          "tgn:7003458",
          "tgn:1000003",
          "tgn:1000063",
          "tgn:7018236",
          "tgn:7029392"
        ],
        "placetype": [
          "aat:300008347"
        ],
        "id": 7238938,
        "name:xx": "Hoekje"
      }
    },
    {
      "geometry": {
        "type": "Point",
        "coordinates": [
          4.866667,
          51.366667
        ]
      },
      "type": "Feature",
      "properties": {
        "hierarchy": [
          "tgn:7238939",
          "tgn:7003456",
          "tgn:1000003",
          "tgn:1000063",
          "tgn:7018236",
          "tgn:7029392"
        ],
        "placetype": [
          "aat:300008347"
        ],
        "id": 7238939,
        "name:xx": "Hoekeinde"
      }
    }
  ]
}
