{
  "geometry": {
    "type": "Point",
    "coordinates": [
      -91.3333,
      39.7833
    ]
  },
  "type": "Feature",
  "properties": {
    "hierarchy": [
      "tgn:2646984",
      "tgn:1002134",
      "tgn:1000001",
      "tgn:7012149",
      "tgn:7007251",
      "tgn:7029392"
    ],
    "placetype": [
      "aat:300008680"
    ],
    "id": 2646984,
    "name:xx": "Schaeffer Pond"
  }
}
