{
  "geometry": {
    "type": "Point",
    "coordinates": [
      -147.3833,
      70.35
    ]
  },
  "type": "Feature",
  "properties": {
    "hierarchy": [
      "tgn:2499480",
      "tgn:7006450",
      "tgn:1000001",
      "tgn:7012149",
      "tgn:2124005",
      "tgn:7029392"
    ],
    "placetype": [
      "aat:300386853"
    ],
    "id": 2499480,
    "name:xx": "McClure Islands"
  }
}
