{
  "geometry": {
    "type": "Point",
    "coordinates": [
      -105.9333,
      45.7833
    ]
  },
  "type": "Feature",
  "properties": {
    "hierarchy": [
      "tgn:2636713",
      "tgn:1000001",
      "tgn:7012149",
      "tgn:7007524",
      "tgn:7029392"
    ],
    "placetype": [
      "aat:300008706"
    ],
    "id": 2636713,
    "name:xx": "Sagebrush Creek"
  }
}
