{
  "geometry": {
    "type": "Point",
    "coordinates": [
      -99.7667,
      32.5333
    ]
  },
  "type": "Feature",
  "properties": {
    "hierarchy": [
      "tgn:2106353",
      "tgn:1000001",
      "tgn:7012149",
      "tgn:2002014",
      "tgn:7007826",
      "tgn:7029392"
    ],
    "placetype": [
      "aat:300008347"
    ],
    "id": 2106353,
    "name:xx": "North Abilene"
  }
}
