{
  "geometry": {
    "type": "Point",
    "coordinates": [
      97.45,
      58.1667
    ]
  },
  "type": "Feature",
  "properties": {
    "hierarchy": [
      "tgn:1055033",
      "tgn:1000004",
      "tgn:1003314",
      "tgn:7018214",
      "tgn:7002435",
      "tgn:7029392"
    ],
    "placetype": [
      "aat:300008347"
    ],
    "id": 1055033,
    "name:xx": "Karabula"
  }
}
