{
  "geometry": {
    "type": "Point",
    "coordinates": [
      77.016111,
      31.155
    ]
  },
  "type": "Feature",
  "properties": {
    "hierarchy": [
      "tgn:7568757",
      "tgn:1000004",
      "tgn:7000198",
      "tgn:1001996",
      "tgn:7029392"
    ],
    "placetype": [
      "aat:300008347"
    ],
    "name:en": "Miyān",
    "id": 7568757
  }
}
