{
  "geometry": {
    "type": "Point",
    "coordinates": [
      -95.4833,
      31.0667
    ]
  },
  "type": "Feature",
  "properties": {
    "hierarchy": [
      "tgn:2215524",
      "tgn:1000001",
      "tgn:7012149",
      "tgn:1002486",
      "tgn:7007826",
      "tgn:7029392"
    ],
    "placetype": [
      "aat:300008680"
    ],
    "id": 2215524,
    "name:xx": "Calvert Lake"
  }
}
