{
  "geometry": {
    "type": "Point",
    "coordinates": [
      -84.2667,
      39.4333
    ]
  },
  "type": "Feature",
  "properties": {
    "hierarchy": [
      "tgn:2692195",
      "tgn:1000001",
      "tgn:7012149",
      "tgn:1002987",
      "tgn:7007706",
      "tgn:7029392"
    ],
    "placetype": [
      "aat:300008706"
    ],
    "id": 2692195,
    "name:xx": "Station Creek"
  }
}
