{
  "geometry": {
    "type": "Point",
    "coordinates": [
      17.3333,
      42.9667
    ]
  },
  "type": "Feature",
  "properties": {
    "hierarchy": [
      "tgn:1012900",
      "tgn:7017310",
      "tgn:1000003",
      "tgn:7006663",
      "tgn:7029392"
    ],
    "placetype": [
      "aat:300008804"
    ],
    "id": 1012900,
    "name:xx": "Pelješac"
  }
}
