{
  "geometry": {
    "type": "Point",
    "coordinates": [
      -84.3167,
      41.9167
    ]
  },
  "type": "Feature",
  "properties": {
    "hierarchy": [
      "tgn:2570610",
      "tgn:1000001",
      "tgn:7012149",
      "tgn:1002588",
      "tgn:7007520",
      "tgn:7029392"
    ],
    "placetype": [
      "aat:300008699"
    ],
    "id": 2570610,
    "name:xx": "Patrick Drain"
  }
}
