{
  "geometry": {
    "type": "Point",
    "coordinates": [
      -83.3667,
      34.1833
    ]
  },
  "type": "Feature",
  "properties": {
    "hierarchy": [
      "tgn:2320075",
      "tgn:1000001",
      "tgn:7012149",
      "tgn:2000368",
      "tgn:7007248",
      "tgn:7029392"
    ],
    "placetype": [
      "aat:300006191"
    ],
    "id": 2320075,
    "name:xx": "Evans Lake"
  }
}
