{
  "geometry": {
    "type": "Point",
    "coordinates": [
      36.8667,
      9.0333
    ]
  },
  "type": "Feature",
  "properties": {
    "hierarchy": [
      "tgn:1089954",
      "tgn:7001242",
      "tgn:1001597",
      "tgn:7000489",
      "tgn:7029392"
    ],
    "placetype": [
      "aat:300008347"
    ],
    "id": 1089954,
    "name:xx": "Sīrē"
  }
}
