{
  "geometry": {
    "type": "Point",
    "coordinates": [
      2.1833,
      49.0167
    ]
  },
  "type": "Feature",
  "properties": {
    "hierarchy": [
      "tgn:1032049",
      "tgn:1000003",
      "tgn:7002883",
      "tgn:1000070",
      "tgn:7029392"
    ],
    "placetype": [
      "aat:300008347"
    ],
    "id": 1032049,
    "name:xx": "Beauchamp"
  }
}
