{
  "type": "FeatureCollection",
  "features": [
    {
      "geometry": {
        "type": "Point",
        "coordinates": [
          13.683333,
          42.3
        ]
      },
      "type": "Feature",
      "properties": {
        "hierarchy": [
          "tgn:5002060",
          "tgn:7009084",
          "tgn:7004154",
          "tgn:1000003",
          "tgn:1000080",
          "tgn:7029392"
        ],
        "placetype": [
          "aat:300008347"
        ],
        "id": 5002060,
        "name:xx": "Castelvecchio Calvisio"
      }
    },
    {
      "geometry": {
        "type": "Point",
        "coordinates": [
          13.35,
          42.016667
        ]
      },
      "type": "Feature",
      "properties": {
        "hierarchy": [
          "tgn:5002063",
          "tgn:7009084",
          "tgn:7004154",
          "tgn:1000003",
          "tgn:1000080",
          "tgn:7029392"
        ],
        "placetype": [
          "aat:300008347"
        ],
        "id": 5002063,
        "name:xx": "Corcumello"
      }
    },
    {
      "geometry": {
        "type": "Point",
        "coordinates": [
          12.073333,
          44.329167
        ]
      },
      "type": "Feature",
      "properties": {
        "hierarchy": [
          "tgn:5002065",
          "tgn:7009084",
          "tgn:7003000",
          "tgn:1000003",
          "tgn:1000080",
          "tgn:7029392"
        ],
        "placetype": [
          "aat:300008347"
        ],
        "id": 5002065,
        "name:xx": "Filetto"
      }
    },
    {
      "geometry": {
        "type": "Point",
        "coordinates": [
          11.883333,
          44.216667
        ]
      },
      "type": "Feature",
      "properties": {
        "hierarchy": [
          "tgn:5002066",
          "tgn:7009084",
          "tgn:7004154",
          "tgn:1000003",
          "tgn:1000080",
          "tgn:7029392"
        ],
        "placetype": [
          "aat:300008347"
        ],
        "id": 5002066,
        "name:xx": "Fossa"
      }
    },
    {
      "geometry": {
        "type": "Point",
        "coordinates": [
          13.45,
          42.316667
        ]
      },
      "type": "Feature",
      "properties": {
        "hierarchy": [
          "tgn:5002069",
          "tgn:7009084",
          "tgn:7004154",
          "tgn:1000003",
          "tgn:1000080",
          "tgn:7029392"
        ],
        "placetype": [
          "aat:300008347"
        ],
        "id": 5002069,
        "name:xx": "Monticchio"
      }
    }
  ]
}
