{
  "geometry": {
    "type": "Point",
    "coordinates": [
      -90.7333,
      38.9167
    ]
  },
  "type": "Feature",
  "properties": {
    "hierarchy": [
      "tgn:2557488",
      "tgn:1000001",
      "tgn:7012149",
      "tgn:1002598",
      "tgn:7007523",
      "tgn:7029392"
    ],
    "placetype": [
      "aat:300008798"
    ],
    "id": 2557488,
    "name:xx": "Old Monroe Mounds"
  }
}
