{
  "geometry": {
    "type": "Point",
    "coordinates": [
      40.6667,
      -11.15
    ]
  },
  "type": "Feature",
  "properties": {
    "hierarchy": [
      "tgn:1008137",
      "tgn:1000821",
      "tgn:7001242",
      "tgn:1000180",
      "tgn:7029392"
    ],
    "placetype": [
      "aat:300008791"
    ],
    "id": 1008137,
    "name:xx": "Metundo, Ilha"
  }
}
