{
  "geometry": {
    "type": "Point",
    "coordinates": [
      -0.15,
      45.4667
    ]
  },
  "type": "Feature",
  "properties": {
    "hierarchy": [
      "tgn:1032010",
      "tgn:1000003",
      "tgn:7002892",
      "tgn:1000070",
      "tgn:7029392"
    ],
    "placetype": [
      "aat:300008347"
    ],
    "id": 1032010,
    "name:xx": "Barbezieux-Saint Hilaire"
  }
}
