{
  "type": "FeatureCollection",
  "features": [
    {
      "geometry": {
        "type": "Point",
        "coordinates": [
          -74.7167,
          39.2833
        ]
      },
      "type": "Feature",
      "properties": {
        "hierarchy": [
          "tgn:2562070",
          "tgn:1002232",
          "tgn:1000001",
          "tgn:7012149",
          "tgn:7007565",
          "tgn:7029392"
        ],
        "placetype": [
          "aat:300008706"
        ],
        "id": 2562070,
        "name:xx": "Otter Creek"
      }
    },
    {
      "geometry": {
        "type": "Point",
        "coordinates": [
          -75.9,
          35.55
        ]
      },
      "type": "Feature",
      "properties": {
        "hierarchy": [
          "tgn:2562071",
          "tgn:1000001",
          "tgn:7012149",
          "tgn:2001506",
          "tgn:7007709",
          "tgn:7029392"
        ],
        "placetype": [
          "aat:300132316"
        ],
        "id": 2562071,
        "name:xx": "Otter Creek"
      }
    },
    {
      "geometry": {
        "type": "Point",
        "coordinates": [
          -76.9333,
          34.95
        ]
      },
      "type": "Feature",
      "properties": {
        "hierarchy": [
          "tgn:2562072",
          "tgn:1000001",
          "tgn:7012149",
          "tgn:2001486",
          "tgn:7007709",
          "tgn:7029392"
        ],
        "placetype": [
          "aat:300008706"
        ],
        "id": 2562072,
        "name:xx": "Otter Creek"
      }
    },
    {
      "geometry": {
        "type": "Point",
        "coordinates": [
          -76.6,
          35.3
        ]
      },
      "type": "Feature",
      "properties": {
        "hierarchy": [
          "tgn:2562073",
          "tgn:1000001",
          "tgn:7012149",
          "tgn:2001526",
          "tgn:7007709",
          "tgn:7029392"
        ],
        "placetype": [
          "aat:300008706"
        ],
        "id": 2562073,
        "name:xx": "Otter Creek"
      }
    },
    {
      "geometry": {
        "type": "Point",
        "coordinates": [
          -83.5667,
          35.25
        ]
      },
      "type": "Feature",
      "properties": {
        "hierarchy": [
          "tgn:2562074",
          "tgn:1000001",
          "tgn:7012149",
          "tgn:2001515",
          "tgn:7007709",
          "tgn:7029392"
        ],
        "placetype": [
          "aat:300008706"
        ],
        "id": 2562074,
        "name:xx": "Otter Creek"
      }
    },
    {
      "geometry": {
        "type": "Point",
        "coordinates": [
          -82.1333,
          35.5167
        ]
      },
      "type": "Feature",
      "properties": {
        "hierarchy": [
          "tgn:2562075",
          "tgn:1000001",
          "tgn:7012149",
          "tgn:2001537",
          "tgn:7007709",
          "tgn:7029392"
        ],
        "placetype": [
          "aat:300008706"
        ],
        "id": 2562075,
        "name:xx": "Otter Creek"
      }
    },
    {
      "geometry": {
        "type": "Point",
        "coordinates": [
          -77.7167,
          35.7
        ]
      },
      "type": "Feature",
      "properties": {
        "hierarchy": [
          "tgn:2562076",
          "tgn:1000001",
          "tgn:7012149",
          "tgn:7007709",
          "tgn:7029392"
        ],
        "placetype": [
          "aat:300008706"
        ],
        "id": 2562076,
        "name:xx": "Otter Creek"
      }
    },
    {
      "geometry": {
        "type": "Point",
        "coordinates": [
          -82.0833,
          35.5167
        ]
      },
      "type": "Feature",
      "properties": {
        "hierarchy": [
          "tgn:2562077",
          "tgn:1000001",
          "tgn:7012149",
          "tgn:2001537",
          "tgn:7007709",
          "tgn:7029392"
        ],
        "placetype": [
          "aat:300008347"
        ],
        "id": 2562077,
        "name:xx": "Otter Creek"
      }
    },
    {
      "geometry": {
        "type": "Point",
        "coordinates": [
          -101.55,
          47.0333
        ]
      },
      "type": "Feature",
      "properties": {
        "hierarchy": [
          "tgn:2562078",
          "tgn:1000001",
          "tgn:2001589",
          "tgn:7012149",
          "tgn:7007705",
          "tgn:7029392"
        ],
        "placetype": [
          "aat:300008347"
        ],
        "id": 2562078,
        "name:xx": "Otter Creek"
      }
    },
    {
      "geometry": {
        "type": "Point",
        "coordinates": [
          -101.4,
          46.4833
        ]
      },
      "type": "Feature",
      "properties": {
        "hierarchy": [
          "tgn:2562079",
          "tgn:1000001",
          "tgn:2001575",
          "tgn:7012149",
          "tgn:7007705",
          "tgn:7029392"
        ],
        "placetype": [
          "aat:300008706"
        ],
        "id": 2562079,
        "name:xx": "Otter Creek"
      }
    }
  ]
}
