{
  "geometry": {
    "type": "Point",
    "coordinates": [
      -81.8333,
      36.8667
    ]
  },
  "type": "Feature",
  "properties": {
    "hierarchy": [
      "tgn:2731867",
      "tgn:1000001",
      "tgn:7012149",
      "tgn:2002194",
      "tgn:7007919",
      "tgn:7029392"
    ],
    "placetype": [
      "aat:300008347"
    ],
    "id": 2731867,
    "name:xx": "Tumbling Creek"
  }
}
