{
  "geometry": {
    "type": "Point",
    "coordinates": [
      -118.3833,
      34.5167
    ]
  },
  "type": "Feature",
  "properties": {
    "hierarchy": [
      "tgn:2709360",
      "tgn:1000001",
      "tgn:7012149",
      "tgn:7007157",
      "tgn:1002608",
      "tgn:7029392"
    ],
    "placetype": [
      "aat:300008798"
    ],
    "id": 2709360,
    "name:xx": "Table Rock"
  }
}
