{
  "geometry": {
    "type": "Point",
    "coordinates": [
      -149.0333,
      60.6167
    ]
  },
  "type": "Feature",
  "properties": {
    "hierarchy": [
      "tgn:2586789",
      "tgn:7006450",
      "tgn:1000001",
      "tgn:7012149",
      "tgn:7029392"
    ],
    "placetype": [
      "aat:300008707"
    ],
    "id": 2586789,
    "name:xx": "Placer River"
  }
}
