{
  "geometry": {
    "type": "Point",
    "coordinates": [
      -35.55,
      -9.3333
    ]
  },
  "type": "Feature",
  "properties": {
    "hierarchy": [
      "tgn:1022861",
      "tgn:7016581",
      "tgn:1000047",
      "tgn:7002455",
      "tgn:1000002",
      "tgn:7029392"
    ],
    "placetype": [
      "aat:300008347"
    ],
    "id": 1022861,
    "name:xx": "São Luís do Quitunde"
  }
}
