{
  "geometry": {
    "type": "Point",
    "coordinates": [
      30.625278,
      31.143333
    ]
  },
  "type": "Feature",
  "properties": {
    "hierarchy": [
      "tgn:7526540",
      "tgn:7001242",
      "tgn:1001075",
      "tgn:7016833",
      "tgn:7029392"
    ],
    "placetype": [
      "aat:300008791"
    ],
    "name:en": "Wakā'ilah, Jazīrat al",
    "id": 7526540
  }
}
