{
  "geometry": {
    "type": "Point",
    "coordinates": [
      3.7167,
      49.8167
    ]
  },
  "type": "Feature",
  "properties": {
    "hierarchy": [
      "tgn:1035217",
      "tgn:1000003",
      "tgn:7002890",
      "tgn:1000070",
      "tgn:7029392"
    ],
    "placetype": [
      "aat:300008347"
    ],
    "id": 1035217,
    "name:xx": "Sains-Richaumont"
  }
}
