{
  "geometry": {
    "type": "Point",
    "coordinates": [
      -116.8975,
      32.155556
    ]
  },
  "type": "Feature",
  "properties": {
    "hierarchy": [
      "tgn:7429701",
      "tgn:1001835",
      "tgn:1000001",
      "tgn:7005560",
      "tgn:7029392"
    ],
    "placetype": [
      "aat:300008347"
    ],
    "id": 7429701,
    "name:xx": "Campo López"
  }
}
