{
  "geometry": {
    "type": "Point",
    "coordinates": [
      15.083,
      -8.916
    ]
  },
  "type": "Feature",
  "properties": {
    "hierarchy": [
      "tgn:1000834",
      "tgn:7001242",
      "tgn:1000149",
      "tgn:7029392"
    ],
    "placetype": [
      "aat:300387064",
      "aat:300000774"
    ],
    "id": 1000834,
    "name:xx": "Kwanza Norte"
  }
}
