{
  "geometry": {
    "type": "Point",
    "coordinates": [
      -95.0667,
      33.15
    ]
  },
  "type": "Feature",
  "properties": {
    "hierarchy": [
      "tgn:2766773",
      "tgn:1000001",
      "tgn:7012149",
      "tgn:1002948",
      "tgn:7007826",
      "tgn:7029392"
    ],
    "placetype": [
      "aat:300008347"
    ],
    "id": 2766773,
    "name:xx": "White Oak Springs"
  }
}
