{
  "geometry": {
    "type": "Point",
    "coordinates": [
      -121.4833,
      40.2833
    ]
  },
  "type": "Feature",
  "properties": {
    "hierarchy": [
      "tgn:2706188",
      "tgn:1000001",
      "tgn:7012149",
      "tgn:7007157",
      "tgn:2000190",
      "tgn:7029392"
    ],
    "placetype": [
      "aat:300008706"
    ],
    "id": 2706188,
    "name:xx": "Swamp Creek"
  }
}
