{
  "type": "FeatureCollection",
  "features": [
    {
      "geometry": {
        "type": "Point",
        "coordinates": [
          -81.2167,
          39.45
        ]
      },
      "type": "Feature",
      "properties": {
        "hierarchy": [
          "tgn:2583510",
          "tgn:1000001",
          "tgn:7012149",
          "tgn:2001622",
          "tgn:7007706",
          "tgn:7029392"
        ],
        "placetype": [
          "aat:300266640"
        ],
        "id": 2583510,
        "name:xx": "Pine Ridge"
      }
    },
    {
      "geometry": {
        "type": "Point",
        "coordinates": [
          -98.4333,
          35
        ]
      },
      "type": "Feature",
      "properties": {
        "hierarchy": [
          "tgn:2583511",
          "tgn:1000001",
          "tgn:2001630",
          "tgn:7012149",
          "tgn:7007707",
          "tgn:7029392"
        ],
        "placetype": [
          "aat:300008347"
        ],
        "id": 2583511,
        "name:xx": "Pine Ridge"
      }
    },
    {
      "geometry": {
        "type": "Point",
        "coordinates": [
          -121.85,
          42.5833
        ]
      },
      "type": "Feature",
      "properties": {
        "hierarchy": [
          "tgn:2583512",
          "tgn:1000001",
          "tgn:7012149",
          "tgn:2001714",
          "tgn:7007708",
          "tgn:7029392"
        ],
        "placetype": [
          "aat:300008347"
        ],
        "id": 2583512,
        "name:xx": "Pine Ridge"
      }
    },
    {
      "geometry": {
        "type": "Point",
        "coordinates": [
          -121.05,
          44.4167
        ]
      },
      "type": "Feature",
      "properties": {
        "hierarchy": [
          "tgn:2583513",
          "tgn:1000001",
          "tgn:7012149",
          "tgn:2001712",
          "tgn:7007708",
          "tgn:7029392"
        ],
        "placetype": [
          "aat:300266640"
        ],
        "id": 2583513,
        "name:xx": "Pine Ridge"
      }
    },
    {
      "geometry": {
        "type": "Point",
        "coordinates": [
          -121.9333,
          44.5667
        ]
      },
      "type": "Feature",
      "properties": {
        "hierarchy": [
          "tgn:2583514",
          "tgn:1000001",
          "tgn:7012149",
          "tgn:2001717",
          "tgn:7007708",
          "tgn:7029392"
        ],
        "placetype": [
          "aat:300266640"
        ],
        "id": 2583514,
        "name:xx": "Pine Ridge"
      }
    },
    {
      "geometry": {
        "type": "Point",
        "coordinates": [
          -118.15,
          45.9333
        ]
      },
      "type": "Feature",
      "properties": {
        "hierarchy": [
          "tgn:2583515",
          "tgn:1000001",
          "tgn:7012149",
          "tgn:2001720",
          "tgn:7007708",
          "tgn:7029392"
        ],
        "placetype": [
          "aat:300266640"
        ],
        "id": 2583515,
        "name:xx": "Pine Ridge"
      }
    },
    {
      "geometry": {
        "type": "Point",
        "coordinates": [
          -119.9833,
          45.1167
        ]
      },
      "type": "Feature",
      "properties": {
        "hierarchy": [
          "tgn:2583516",
          "tgn:1000001",
          "tgn:7012149",
          "tgn:2001707",
          "tgn:7007708",
          "tgn:7029392"
        ],
        "placetype": [
          "aat:300266640"
        ],
        "id": 2583516,
        "name:xx": "Pine Ridge"
      }
    },
    {
      "geometry": {
        "type": "Point",
        "coordinates": [
          -120.75,
          43.7667
        ]
      },
      "type": "Feature",
      "properties": {
        "hierarchy": [
          "tgn:2583517",
          "tgn:1000001",
          "tgn:2001705",
          "tgn:7012149",
          "tgn:7007708",
          "tgn:7029392"
        ],
        "placetype": [
          "aat:300266640"
        ],
        "id": 2583517,
        "name:xx": "Pine Ridge"
      }
    },
    {
      "geometry": {
        "type": "Point",
        "coordinates": [
          -120.25,
          43.35
        ]
      },
      "type": "Feature",
      "properties": {
        "hierarchy": [
          "tgn:2583518",
          "tgn:1000001",
          "tgn:7012149",
          "tgn:2001715",
          "tgn:7007708",
          "tgn:7029392"
        ],
        "placetype": [
          "aat:300266640"
        ],
        "id": 2583518,
        "name:xx": "Pine Ridge"
      }
    },
    {
      "geometry": {
        "type": "Point",
        "coordinates": [
          -78.1833,
          40.0333
        ]
      },
      "type": "Feature",
      "properties": {
        "hierarchy": [
          "tgn:2583519",
          "tgn:1000001",
          "tgn:7012149",
          "tgn:1002399",
          "tgn:7007710",
          "tgn:7029392"
        ],
        "placetype": [
          "aat:300266640"
        ],
        "id": 2583519,
        "name:xx": "Pine Ridge"
      }
    }
  ]
}
