{
  "geometry": {
    "type": "Point",
    "coordinates": [
      -93.1667,
      37.6333
    ]
  },
  "type": "Feature",
  "properties": {
    "hierarchy": [
      "tgn:2199463",
      "tgn:1000001",
      "tgn:7012149",
      "tgn:2001232",
      "tgn:7007523",
      "tgn:7029392"
    ],
    "placetype": [
      "aat:300008706"
    ],
    "id": 2199463,
    "name:xx": "Brush Creek"
  }
}
