{
  "type": "FeatureCollection",
  "features": [
    {
      "geometry": {
        "type": "Point",
        "coordinates": [
          22.3,
          38.916667
        ]
      },
      "type": "Feature",
      "properties": {
        "hierarchy": [
          "tgn:5002020",
          "tgn:7002684",
          "tgn:7001395",
          "tgn:1000003",
          "tgn:1000074",
          "tgn:7029392"
        ],
        "placetype": [
          "aat:300008347"
        ],
        "id": 5002020,
        "name:xx": "Lianokládhion"
      }
    },
    {
      "geometry": {
        "type": "Point",
        "coordinates": [
          22.45,
          39.05
        ]
      },
      "type": "Feature",
      "properties": {
        "hierarchy": [
          "tgn:5002021",
          "tgn:7002716",
          "tgn:7002715",
          "tgn:1000003",
          "tgn:1000074",
          "tgn:7029392"
        ],
        "placetype": [
          "aat:300008347"
        ],
        "id": 5002021,
        "name:xx": "Meliteia"
      }
    },
    {
      "geometry": {
        "type": "Point",
        "coordinates": [
          22.565556,
          41.067778
        ]
      },
      "type": "Feature",
      "properties": {
        "hierarchy": [
          "tgn:5002022",
          "tgn:7002725",
          "tgn:7002715",
          "tgn:1000003",
          "tgn:1000074",
          "tgn:7029392"
        ],
        "placetype": [
          "aat:300008347"
        ],
        "id": 5002022,
        "name:xx": "Mikrón Dhásos"
      }
    },
    {
      "geometry": {
        "type": "Point",
        "coordinates": [
          22.816667,
          39.283333
        ]
      },
      "type": "Feature",
      "properties": {
        "hierarchy": [
          "tgn:5002024",
          "tgn:7002751",
          "tgn:7001399",
          "tgn:1000003",
          "tgn:1000074",
          "tgn:7029392"
        ],
        "placetype": [
          "aat:300008347"
        ],
        "id": 5002024,
        "name:xx": "Nea Ankhíalos"
      }
    }
  ]
}
