{
  "geometry": {
    "type": "Point",
    "coordinates": [
      -85.05,
      40.2833
    ]
  },
  "type": "Feature",
  "properties": {
    "hierarchy": [
      "tgn:2595676",
      "tgn:1000001",
      "tgn:7012149",
      "tgn:1002818",
      "tgn:7007252",
      "tgn:7029392"
    ],
    "placetype": [
      "aat:300008699"
    ],
    "id": 2595676,
    "name:xx": "Potent Run"
  }
}
