{
  "geometry": {
    "type": "Point",
    "coordinates": [
      -105.7167,
      40.3333
    ]
  },
  "type": "Feature",
  "properties": {
    "hierarchy": [
      "tgn:2403070",
      "tgn:1000001",
      "tgn:7012149",
      "tgn:2000226",
      "tgn:7007158",
      "tgn:7029392"
    ],
    "placetype": [
      "aat:300008680"
    ],
    "id": 2403070,
    "name:xx": "Hourglass Lake"
  }
}
