{
  "geometry": {
    "type": "Point",
    "coordinates": [
      -88.4833,
      37.0667
    ]
  },
  "type": "Feature",
  "properties": {
    "hierarchy": [
      "tgn:2158541",
      "tgn:1000001",
      "tgn:7012149",
      "tgn:2000519",
      "tgn:7007251",
      "tgn:7029392"
    ],
    "placetype": [
      "aat:300008680"
    ],
    "id": 2158541,
    "name:xx": "Beaverdam Lake"
  }
}
