{
  "type": "FeatureCollection",
  "features": [
    {
      "geometry": {
        "type": "Point",
        "coordinates": [
          -93.2167,
          33.4333
        ]
      },
      "type": "Feature",
      "properties": {
        "hierarchy": [
          "tgn:1132950",
          "tgn:1000001",
          "tgn:7016172",
          "tgn:7012149",
          "tgn:7029392"
        ],
        "placetype": [
          "aat:300008706"
        ],
        "id": 1132950,
        "name:xx": "Crooked Creek"
      }
    },
    {
      "geometry": {
        "type": "Point",
        "coordinates": [
          -88.8667,
          38.7167
        ]
      },
      "type": "Feature",
      "properties": {
        "hierarchy": [
          "tgn:1132951",
          "tgn:1000001",
          "tgn:7012149",
          "tgn:7007251",
          "tgn:7029392"
        ],
        "placetype": [
          "aat:300008706"
        ],
        "id": 1132951,
        "name:xx": "Crooked Creek"
      }
    },
    {
      "geometry": {
        "type": "Point",
        "coordinates": [
          -86.6167,
          38.8333
        ]
      },
      "type": "Feature",
      "properties": {
        "hierarchy": [
          "tgn:1132952",
          "tgn:1000001",
          "tgn:7012149",
          "tgn:7007252",
          "tgn:7029392"
        ],
        "placetype": [
          "aat:300008706"
        ],
        "id": 1132952,
        "name:xx": "Crooked Creek"
      }
    },
    {
      "geometry": {
        "type": "Point",
        "coordinates": [
          -79.0667,
          40.6833
        ]
      },
      "type": "Feature",
      "properties": {
        "hierarchy": [
          "tgn:1132954",
          "tgn:1000001",
          "tgn:7012149",
          "tgn:7007710",
          "tgn:7029392"
        ],
        "placetype": [
          "aat:300008706"
        ],
        "id": 1132954,
        "name:xx": "Crooked Creek"
      }
    },
    {
      "geometry": {
        "type": "Point",
        "coordinates": [
          -100.0833,
          36.95
        ]
      },
      "type": "Feature",
      "properties": {
        "hierarchy": [
          "tgn:1132955",
          "tgn:1000001",
          "tgn:7012149",
          "tgn:7029392"
        ],
        "placetype": [
          "aat:300008706"
        ],
        "id": 1132955,
        "name:xx": "Crooked Creek"
      }
    },
    {
      "geometry": {
        "type": "Point",
        "coordinates": [
          -118.4833,
          36.7333
        ]
      },
      "type": "Feature",
      "properties": {
        "hierarchy": [
          "tgn:1132956",
          "tgn:1000001",
          "tgn:7012149",
          "tgn:7007157",
          "tgn:7029392"
        ],
        "placetype": [
          "aat:300008706"
        ],
        "id": 1132956,
        "name:xx": "Cross Creek"
      }
    },
    {
      "geometry": {
        "type": "Point",
        "coordinates": [
          -80.9333,
          40.3333
        ]
      },
      "type": "Feature",
      "properties": {
        "hierarchy": [
          "tgn:1132957",
          "tgn:1000001",
          "tgn:7012149",
          "tgn:7007706",
          "tgn:7029392"
        ],
        "placetype": [
          "aat:300008706"
        ],
        "id": 1132957,
        "name:xx": "Cross Creek"
      }
    },
    {
      "geometry": {
        "type": "Point",
        "coordinates": [
          -74.5333,
          40.05
        ]
      },
      "type": "Feature",
      "properties": {
        "hierarchy": [
          "tgn:1132958",
          "tgn:1000001",
          "tgn:7012149",
          "tgn:7007565",
          "tgn:7029392"
        ],
        "placetype": [
          "aat:300008706"
        ],
        "id": 1132958,
        "name:xx": "Crosswicks Creek"
      }
    },
    {
      "geometry": {
        "type": "Point",
        "coordinates": [
          -100.8333,
          33.65
        ]
      },
      "type": "Feature",
      "properties": {
        "hierarchy": [
          "tgn:1132959",
          "tgn:1000001",
          "tgn:7012149",
          "tgn:7007826",
          "tgn:7029392"
        ],
        "placetype": [
          "aat:300008706"
        ],
        "id": 1132959,
        "name:xx": "Croton Creek"
      }
    }
  ]
}
