{
  "geometry": {
    "type": "Point",
    "coordinates": [
      -98.1833,
      47.05
    ]
  },
  "type": "Feature",
  "properties": {
    "hierarchy": [
      "tgn:2555332",
      "tgn:2001558",
      "tgn:1000001",
      "tgn:7012149",
      "tgn:7007705",
      "tgn:7029392"
    ],
    "placetype": [
      "aat:300008347"
    ],
    "id": 2555332,
    "name:xx": "Odell"
  }
}
