{
  "geometry": {
    "type": "Point",
    "coordinates": [
      -158.1167,
      21.4833
    ]
  },
  "type": "Feature",
  "properties": {
    "hierarchy": [
      "tgn:2647496",
      "tgn:1002483",
      "tgn:7019080",
      "tgn:1000001",
      "tgn:7012149",
      "tgn:7007249",
      "tgn:7029392"
    ],
    "placetype": [
      "aat:300008863"
    ],
    "id": 2647496,
    "name:xx": "Schofield Barracks Forest Reserve"
  }
}
