{
  "type": "FeatureCollection",
  "features": [
    {
      "geometry": {
        "type": "Point",
        "coordinates": [
          -7.966667,
          42.033333
        ]
      },
      "type": "Feature",
      "properties": {
        "hierarchy": [
          "tgn:7007421",
          "tgn:7002831",
          "tgn:1000003",
          "tgn:7002786",
          "tgn:1000095",
          "tgn:7029392"
        ],
        "placetype": [
          "aat:300008347"
        ],
        "id": 7007421,
        "name:xx": "Bande"
      }
    },
    {
      "geometry": {
        "type": "Point",
        "coordinates": [
          7.65,
          47.5167
        ]
      },
      "type": "Feature",
      "properties": {
        "hierarchy": [
          "tgn:7007424",
          "tgn:7003740",
          "tgn:1000003",
          "tgn:7011731",
          "tgn:7029392"
        ],
        "placetype": [
          "aat:300008347"
        ],
        "id": 7007424,
        "name:xx": "Muttenz"
      }
    },
    {
      "geometry": {
        "type": "Point",
        "coordinates": [
          7.1167,
          46.9333
        ]
      },
      "type": "Feature",
      "properties": {
        "hierarchy": [
          "tgn:7007425",
          "tgn:7003745",
          "tgn:1000003",
          "tgn:7011731",
          "tgn:7029392"
        ],
        "placetype": [
          "aat:300008347",
          "aat:300008375"
        ],
        "id": 7007425,
        "name:xx": "Murten"
      }
    },
    {
      "geometry": {
        "type": "Point",
        "coordinates": [
          2.1741,
          41.398371
        ]
      },
      "type": "Feature",
      "properties": {
        "hierarchy": [
          "tgn:7007426",
          "tgn:7002808",
          "tgn:7030216",
          "tgn:1000003",
          "tgn:1000095",
          "tgn:7029392"
        ],
        "placetype": [
          "aat:300262964",
          "aat:300008347",
          "aat:300008389",
          "aat:300387512",
          "aat:300387223",
          "aat:300387320",
          "aat:300387220",
          "aat:300387284",
          "aat:300387270",
          "aat:300387302",
          "aat:300120599",
          "aat:300387291",
          "aat:300387296"
        ],
        "id": 7007426,
        "name:xx": "Barcelona"
      }
    },
    {
      "geometry": {
        "type": "Point",
        "coordinates": [
          9.0667,
          47.1
        ]
      },
      "type": "Feature",
      "properties": {
        "hierarchy": [
          "tgn:7007427",
          "tgn:7003747",
          "tgn:1000003",
          "tgn:7011731",
          "tgn:7029392"
        ],
        "placetype": [
          "aat:300008347"
        ],
        "id": 7007427,
        "name:xx": "Näfels"
      }
    },
    {
      "geometry": {
        "type": "Point",
        "coordinates": [
          8,
          46.3333
        ]
      },
      "type": "Feature",
      "properties": {
        "hierarchy": [
          "tgn:7007428",
          "tgn:1000003",
          "tgn:7003762",
          "tgn:7011731",
          "tgn:7029392"
        ],
        "placetype": [
          "aat:300008347"
        ],
        "id": 7007428,
        "name:xx": "Naters"
      }
    },
    {
      "geometry": {
        "type": "Point",
        "coordinates": [
          9.2,
          47.2333
        ]
      },
      "type": "Feature",
      "properties": {
        "hierarchy": [
          "tgn:7007429",
          "tgn:1000003",
          "tgn:7003755",
          "tgn:7011731",
          "tgn:7029392"
        ],
        "placetype": [
          "aat:300008347"
        ],
        "id": 7007429,
        "name:xx": "Neu Sankt Johann"
      }
    }
  ]
}
