{
  "type": "FeatureCollection",
  "features": [
    {
      "geometry": {
        "type": "Point",
        "coordinates": [
          -70.9167,
          43.0833
        ]
      },
      "type": "Feature",
      "properties": {
        "hierarchy": [
          "tgn:2315690",
          "tgn:1000001",
          "tgn:2001426",
          "tgn:7012149",
          "tgn:7007564",
          "tgn:7029392"
        ],
        "placetype": [
          "aat:300008699"
        ],
        "id": 2315690,
        "name:xx": "Ellison Brook"
      }
    },
    {
      "geometry": {
        "type": "Point",
        "coordinates": [
          -110.8333,
          34.0667
        ]
      },
      "type": "Feature",
      "properties": {
        "hierarchy": [
          "tgn:2315691",
          "tgn:1000001",
          "tgn:7006451",
          "tgn:7012149",
          "tgn:7029392"
        ],
        "placetype": [
          "aat:300008706"
        ],
        "id": 2315691,
        "name:xx": "Ellison Creek"
      }
    },
    {
      "geometry": {
        "type": "Point",
        "coordinates": [
          -111.15,
          34.4
        ]
      },
      "type": "Feature",
      "properties": {
        "hierarchy": [
          "tgn:2315692",
          "tgn:1000001",
          "tgn:7006451",
          "tgn:2000093",
          "tgn:7012149",
          "tgn:7029392"
        ],
        "placetype": [
          "aat:300008706"
        ],
        "id": 2315692,
        "name:xx": "Ellison Creek"
      }
    },
    {
      "geometry": {
        "type": "Point",
        "coordinates": [
          -123.8667,
          40.6333
        ]
      },
      "type": "Feature",
      "properties": {
        "hierarchy": [
          "tgn:2315693",
          "tgn:1000001",
          "tgn:7012149",
          "tgn:2000181",
          "tgn:7007157",
          "tgn:7029392"
        ],
        "placetype": [
          "aat:300008706"
        ],
        "id": 2315693,
        "name:xx": "Ellison Creek"
      }
    },
    {
      "geometry": {
        "type": "Point",
        "coordinates": [
          -83.3333,
          33.7333
        ]
      },
      "type": "Feature",
      "properties": {
        "hierarchy": [
          "tgn:2315694",
          "tgn:1000001",
          "tgn:7012149",
          "tgn:7007248",
          "tgn:7029392"
        ],
        "placetype": [
          "aat:300008706"
        ],
        "id": 2315694,
        "name:xx": "Ellison Creek"
      }
    },
    {
      "geometry": {
        "type": "Point",
        "coordinates": [
          -115.4167,
          45.0333
        ]
      },
      "type": "Feature",
      "properties": {
        "hierarchy": [
          "tgn:2315695",
          "tgn:1000001",
          "tgn:7012149",
          "tgn:2000494",
          "tgn:7007250",
          "tgn:7029392"
        ],
        "placetype": [
          "aat:300008706"
        ],
        "id": 2315695,
        "name:xx": "Ellison Creek"
      }
    },
    {
      "geometry": {
        "type": "Point",
        "coordinates": [
          -90.6833,
          40.7
        ]
      },
      "type": "Feature",
      "properties": {
        "hierarchy": [
          "tgn:2315696",
          "tgn:1000001",
          "tgn:7012149",
          "tgn:7007251",
          "tgn:7029392"
        ],
        "placetype": [
          "aat:300008706"
        ],
        "id": 2315696,
        "name:xx": "Ellison Creek"
      }
    },
    {
      "geometry": {
        "type": "Point",
        "coordinates": [
          -88.35,
          36.7667
        ]
      },
      "type": "Feature",
      "properties": {
        "hierarchy": [
          "tgn:2315697",
          "tgn:1000001",
          "tgn:7012149",
          "tgn:2000823",
          "tgn:7007255",
          "tgn:7029392"
        ],
        "placetype": [
          "aat:300008706"
        ],
        "id": 2315697,
        "name:xx": "Ellison Creek"
      }
    },
    {
      "geometry": {
        "type": "Point",
        "coordinates": [
          -90.1167,
          32.85
        ]
      },
      "type": "Feature",
      "properties": {
        "hierarchy": [
          "tgn:2315698",
          "tgn:1000001",
          "tgn:7012149",
          "tgn:2001167",
          "tgn:7007522",
          "tgn:7029392"
        ],
        "placetype": [
          "aat:300008706"
        ],
        "id": 2315698,
        "name:xx": "Ellison Creek"
      }
    },
    {
      "geometry": {
        "type": "Point",
        "coordinates": [
          -115.4,
          39
        ]
      },
      "type": "Feature",
      "properties": {
        "hierarchy": [
          "tgn:2315699",
          "tgn:1000001",
          "tgn:7012149",
          "tgn:2001420",
          "tgn:7007526",
          "tgn:7029392"
        ],
        "placetype": [
          "aat:300008706"
        ],
        "id": 2315699,
        "name:xx": "Ellison Creek"
      }
    }
  ]
}
