{
  "geometry": {
    "type": "Point",
    "coordinates": [
      -92.6667,
      33.75
    ]
  },
  "type": "Feature",
  "properties": {
    "hierarchy": [
      "tgn:2345432",
      "tgn:1000001",
      "tgn:7016172",
      "tgn:7012149",
      "tgn:2000156",
      "tgn:7029392"
    ],
    "placetype": [
      "aat:300006191"
    ],
    "id": 2345432,
    "name:xx": "Garner Lake Number One"
  }
}
