{
  "geometry": {
    "type": "Point",
    "coordinates": [
      -119.3167,
      37.7667
    ]
  },
  "type": "Feature",
  "properties": {
    "hierarchy": [
      "tgn:2343862",
      "tgn:1000001",
      "tgn:7012149",
      "tgn:7007157",
      "tgn:7014004",
      "tgn:7029392"
    ],
    "placetype": [
      "aat:300008680"
    ],
    "id": 2343862,
    "name:xx": "Gallison Lake"
  }
}
