{
  "geometry": {
    "type": "Point",
    "coordinates": [
      58.8333,
      25.6667
    ]
  },
  "type": "Feature",
  "properties": {
    "hierarchy": [
      "tgn:1079288",
      "tgn:1000004",
      "tgn:7000228",
      "tgn:7000231",
      "tgn:7029392"
    ],
    "placetype": [
      "aat:300008347"
    ],
    "id": 1079288,
    "name:xx": "Sūrak"
  }
}
