{
  "geometry": {
    "type": "Point",
    "coordinates": [
      -106.34,
      24.2175
    ]
  },
  "type": "Feature",
  "properties": {
    "hierarchy": [
      "tgn:7363750",
      "tgn:1000001",
      "tgn:7005595",
      "tgn:7005560",
      "tgn:7029392"
    ],
    "placetype": [
      "aat:300008347"
    ],
    "id": 7363750,
    "name:xx": "El Chilar"
  }
}
