{
  "geometry": {
    "type": "Point",
    "coordinates": [
      -93.4833,
      40.2167
    ]
  },
  "type": "Feature",
  "properties": {
    "hierarchy": [
      "tgn:2569494",
      "tgn:1000001",
      "tgn:7012149",
      "tgn:2001200",
      "tgn:7007523",
      "tgn:7029392"
    ],
    "placetype": [
      "aat:300006191"
    ],
    "id": 2569494,
    "name:xx": "Parr Lake"
  }
}
