{
  "geometry": {
    "type": "Point",
    "coordinates": [
      31.311813,
      30.009238
    ]
  },
  "type": "Feature",
  "properties": {
    "hierarchy": [
      "tgn:7526064",
      "tgn:7001242",
      "tgn:7016833",
      "tgn:1001091",
      "tgn:7029392"
    ],
    "placetype": [
      "aat:300004792"
    ],
    "id": 7526064,
    "name:xx": "Al Markaz al Qawmī lil Imtiḩānāt wa at Taqwīm at Tarbawī"
  }
}
