{
  "geometry": {
    "type": "Point",
    "coordinates": [
      -124.6667,
      48.05
    ]
  },
  "type": "Feature",
  "properties": {
    "hierarchy": [
      "tgn:2130370",
      "tgn:1000001",
      "tgn:1002271",
      "tgn:7012149",
      "tgn:7007920",
      "tgn:7029392"
    ],
    "placetype": [
      "aat:300008699"
    ],
    "id": 2130370,
    "name:xx": "Allens Slough"
  }
}
