{
  "geometry": {
    "type": "Point",
    "coordinates": [
      -84.9333,
      34.3667
    ]
  },
  "type": "Feature",
  "properties": {
    "hierarchy": [
      "tgn:2021871",
      "tgn:1000001",
      "tgn:2000299",
      "tgn:7012149",
      "tgn:7007248",
      "tgn:7029392"
    ],
    "placetype": [
      "aat:300008347"
    ],
    "id": 2021871,
    "name:xx": "Adairsville"
  }
}
