{
  "geometry": {
    "type": "Point",
    "coordinates": [
      9.15,
      51.316667
    ]
  },
  "type": "Feature",
  "properties": {
    "hierarchy": [
      "tgn:7066721",
      "tgn:1000003",
      "tgn:7003678",
      "tgn:7000084",
      "tgn:7029392"
    ],
    "placetype": [
      "aat:300008777"
    ],
    "id": 7066721,
    "name:xx": "Stöcke-Berg"
  }
}
