{
  "geometry": {
    "type": "Point",
    "coordinates": [
      -154.1833,
      59.7833
    ]
  },
  "type": "Feature",
  "properties": {
    "hierarchy": [
      "tgn:2441461",
      "tgn:7006450",
      "tgn:1000001",
      "tgn:7030517",
      "tgn:7012149",
      "tgn:7029392"
    ],
    "placetype": [
      "aat:300132316"
    ],
    "id": 2441461,
    "name:xx": "Knutson Bay"
  }
}
