{
  "geometry": {
    "type": "Point",
    "coordinates": [
      -106.1833,
      40.8333
    ]
  },
  "type": "Feature",
  "properties": {
    "hierarchy": [
      "tgn:2204886",
      "tgn:1000001",
      "tgn:7012149",
      "tgn:2000220",
      "tgn:7007158",
      "tgn:7029392"
    ],
    "placetype": [
      "aat:300008761"
    ],
    "id": 2204886,
    "name:xx": "Buffmeyer Draw"
  }
}
