{
  "geometry": {
    "type": "Point",
    "coordinates": [
      139.45,
      36.1667
    ]
  },
  "type": "Feature",
  "properties": {
    "hierarchy": [
      "tgn:7031919",
      "tgn:1000004",
      "tgn:7000894",
      "tgn:7016797",
      "tgn:1000120",
      "tgn:7029392"
    ],
    "placetype": [
      "aat:300008347",
      "aat:300008375"
    ],
    "id": 7031919,
    "name:xx": "Gyōda"
  }
}
