{
  "geometry": {
    "type": "Point",
    "coordinates": [
      -92.85,
      33.2667
    ]
  },
  "type": "Feature",
  "properties": {
    "hierarchy": [
      "tgn:2450857",
      "tgn:1000001",
      "tgn:7016172",
      "tgn:7012149",
      "tgn:2000174",
      "tgn:7029392"
    ],
    "placetype": [
      "aat:300006191"
    ],
    "id": 2450857,
    "name:xx": "Lisbon, Lake"
  }
}
