{
  "geometry": {
    "type": "Point",
    "coordinates": [
      -97.8333,
      31.3333
    ]
  },
  "type": "Feature",
  "properties": {
    "hierarchy": [
      "tgn:2386342",
      "tgn:1000001",
      "tgn:7012149",
      "tgn:1002303",
      "tgn:7007826",
      "tgn:7029392"
    ],
    "placetype": [
      "aat:300008706"
    ],
    "id": 2386342,
    "name:xx": "Henson Creek"
  }
}
