{
  "geometry": {
    "type": "Point",
    "coordinates": [
      -86.6667,
      37.0167
    ]
  },
  "type": "Feature",
  "properties": {
    "hierarchy": [
      "tgn:2160725",
      "tgn:1000001",
      "tgn:7012149",
      "tgn:7007255",
      "tgn:7029392"
    ],
    "placetype": [
      "aat:300008706"
    ],
    "id": 2160725,
    "name:xx": "Belcher Creek"
  }
}
