{
  "geometry": {
    "type": "Point",
    "coordinates": [
      -111.9333,
      38.6167
    ]
  },
  "type": "Feature",
  "properties": {
    "hierarchy": [
      "tgn:2611837",
      "tgn:1000001",
      "tgn:7012149",
      "tgn:2002121",
      "tgn:7007827",
      "tgn:7029392"
    ],
    "placetype": [
      "aat:300266640"
    ],
    "id": 2611837,
    "name:xx": "Red Pine Ridge"
  }
}
