{
  "geometry": {
    "type": "Point",
    "coordinates": [
      -113.4833,
      33.3833
    ]
  },
  "type": "Feature",
  "properties": {
    "hierarchy": [
      "tgn:2125916",
      "tgn:1000001",
      "tgn:7006451",
      "tgn:7012149",
      "tgn:2000096",
      "tgn:7029392"
    ],
    "placetype": [
      "aat:300000390"
    ],
    "id": 2125916,
    "name:xx": "Adams Mine"
  }
}
