{
  "type": "FeatureCollection",
  "features": [
    {
      "geometry": {
        "type": "Point",
        "coordinates": [
          -3.666667,
          57.416667
        ]
      },
      "type": "Feature",
      "properties": {
        "hierarchy": [
          "tgn:7466870",
          "tgn:7002444",
          "tgn:1000003",
          "tgn:7008082",
          "tgn:7008591",
          "tgn:7029392"
        ],
        "placetype": [
          "aat:300008699"
        ],
        "name:en": "Anaboard Burn",
        "id": 7466870
      }
    },
    {
      "geometry": {
        "type": "Point",
        "coordinates": [
          -4.416667,
          56.233333
        ]
      },
      "type": "Feature",
      "properties": {
        "hierarchy": [
          "tgn:7466871",
          "tgn:7002444",
          "tgn:1000003",
          "tgn:5000460",
          "tgn:7008591",
          "tgn:7029392"
        ],
        "placetype": [
          "aat:300008795"
        ],
        "name:en": "An, Ben",
        "id": 7466871
      }
    },
    {
      "geometry": {
        "type": "Point",
        "coordinates": [
          -4.660556,
          51.731944
        ]
      },
      "type": "Feature",
      "properties": {
        "hierarchy": [
          "tgn:7466873",
          "tgn:7002443",
          "tgn:1000003",
          "tgn:7018993",
          "tgn:7008591",
          "tgn:7029392"
        ],
        "placetype": [
          "aat:300008347"
        ],
        "name:en": "Amroth",
        "id": 7466873
      }
    },
    {
      "geometry": {
        "type": "Point",
        "coordinates": [
          -1.116667,
          54.183333
        ]
      },
      "type": "Feature",
      "properties": {
        "hierarchy": [
          "tgn:7466878",
          "tgn:7002445",
          "tgn:1000003",
          "tgn:7008166",
          "tgn:7008591",
          "tgn:7029392"
        ],
        "placetype": [
          "aat:300007783"
        ],
        "name:en": "Ampleforth Station",
        "id": 7466878
      }
    }
  ]
}
