{
  "geometry": {
    "type": "Point",
    "coordinates": [
      33.178254,
      24.557726
    ]
  },
  "type": "Feature",
  "properties": {
    "hierarchy": [
      "tgn:7538199",
      "tgn:7001242",
      "tgn:7001311",
      "tgn:7016833",
      "tgn:7029392"
    ],
    "placetype": [
      "aat:300379998"
    ],
    "name:en": "Mudrik, Wādī",
    "id": 7538199
  }
}
