{
  "geometry": {
    "type": "Point",
    "coordinates": [
      -106.5333,
      40.65
    ]
  },
  "type": "Feature",
  "properties": {
    "hierarchy": [
      "tgn:2559690",
      "tgn:1000001",
      "tgn:7012149",
      "tgn:2000220",
      "tgn:7007158",
      "tgn:7029392"
    ],
    "placetype": [
      "aat:300006075"
    ],
    "id": 2559690,
    "name:xx": "Open A Diamond Ditch"
  }
}
