{
  "type": "FeatureCollection",
  "features": [
    {
      "geometry": {
        "type": "Point",
        "coordinates": [
          -98.3667,
          32.25
        ]
      },
      "type": "Feature",
      "properties": {
        "hierarchy": [
          "tgn:2355400",
          "tgn:1000001",
          "tgn:7012149",
          "tgn:2001982",
          "tgn:7007826",
          "tgn:7029392"
        ],
        "placetype": [
          "aat:300008699"
        ],
        "id": 2355400,
        "name:xx": "Goose Branch"
      }
    },
    {
      "geometry": {
        "type": "Point",
        "coordinates": [
          -96.8,
          31.2333
        ]
      },
      "type": "Feature",
      "properties": {
        "hierarchy": [
          "tgn:2355401",
          "tgn:1000001",
          "tgn:7012149",
          "tgn:1002367",
          "tgn:7007826",
          "tgn:7029392"
        ],
        "placetype": [
          "aat:300008699"
        ],
        "id": 2355401,
        "name:xx": "Goose Branch"
      }
    },
    {
      "geometry": {
        "type": "Point",
        "coordinates": [
          -94.1333,
          31.25
        ]
      },
      "type": "Feature",
      "properties": {
        "hierarchy": [
          "tgn:2355402",
          "tgn:1000001",
          "tgn:7012149",
          "tgn:2002067",
          "tgn:7007826",
          "tgn:7029392"
        ],
        "placetype": [
          "aat:300008699"
        ],
        "id": 2355402,
        "name:xx": "Goose Branch"
      }
    },
    {
      "geometry": {
        "type": "Point",
        "coordinates": [
          -107.7833,
          45.2
        ]
      },
      "type": "Feature",
      "properties": {
        "hierarchy": [
          "tgn:2355403",
          "tgn:1000001",
          "tgn:2001261",
          "tgn:7012149",
          "tgn:7007524",
          "tgn:7029392"
        ],
        "placetype": [
          "aat:300008761"
        ],
        "id": 2355403,
        "name:xx": "Goose Coulee"
      }
    },
    {
      "geometry": {
        "type": "Point",
        "coordinates": [
          -133.2667,
          56.9333
        ]
      },
      "type": "Feature",
      "properties": {
        "hierarchy": [
          "tgn:2355404",
          "tgn:7006450",
          "tgn:1000001",
          "tgn:7012149",
          "tgn:2000088",
          "tgn:7029392"
        ],
        "placetype": [
          "aat:300132316"
        ],
        "id": 2355404,
        "name:xx": "Goose Cove"
      }
    },
    {
      "geometry": {
        "type": "Point",
        "coordinates": [
          -135.5333,
          57.5
        ]
      },
      "type": "Feature",
      "properties": {
        "hierarchy": [
          "tgn:2355405",
          "tgn:7006450",
          "tgn:1000001",
          "tgn:7012149",
          "tgn:2124002",
          "tgn:7029392"
        ],
        "placetype": [
          "aat:300132316"
        ],
        "id": 2355405,
        "name:xx": "Goose Cove"
      }
    },
    {
      "geometry": {
        "type": "Point",
        "coordinates": [
          -136.1,
          58.95
        ]
      },
      "type": "Feature",
      "properties": {
        "hierarchy": [
          "tgn:2355406",
          "tgn:7006450",
          "tgn:1000001",
          "tgn:7012149",
          "tgn:7019760",
          "tgn:7029392"
        ],
        "placetype": [
          "aat:300132316"
        ],
        "id": 2355406,
        "name:xx": "Goose Cove"
      }
    },
    {
      "geometry": {
        "type": "Point",
        "coordinates": [
          -70.0333,
          43.8333
        ]
      },
      "type": "Feature",
      "properties": {
        "hierarchy": [
          "tgn:2355407",
          "tgn:1000001",
          "tgn:2000920",
          "tgn:7012149",
          "tgn:7007515",
          "tgn:7029392"
        ],
        "placetype": [
          "aat:300132316"
        ],
        "id": 2355407,
        "name:xx": "Goose Cove"
      }
    },
    {
      "geometry": {
        "type": "Point",
        "coordinates": [
          -69.8167,
          43.9667
        ]
      },
      "type": "Feature",
      "properties": {
        "hierarchy": [
          "tgn:2355408",
          "tgn:1000001",
          "tgn:7012149",
          "tgn:2000929",
          "tgn:7007515",
          "tgn:7029392"
        ],
        "placetype": [
          "aat:300132316"
        ],
        "id": 2355408,
        "name:xx": "Goose Cove"
      }
    },
    {
      "geometry": {
        "type": "Point",
        "coordinates": [
          -68.7,
          44.1667
        ]
      },
      "type": "Feature",
      "properties": {
        "hierarchy": [
          "tgn:2355409",
          "tgn:1000001",
          "tgn:2000922",
          "tgn:7012149",
          "tgn:7007515",
          "tgn:7029392"
        ],
        "placetype": [
          "aat:300132316"
        ],
        "id": 2355409,
        "name:xx": "Goose Cove"
      }
    }
  ]
}
