{
  "type": "FeatureCollection",
  "features": [
    {
      "geometry": {
        "type": "Point",
        "coordinates": [
          -91.35,
          40.4167
        ]
      },
      "type": "Feature",
      "properties": {
        "hierarchy": [
          "tgn:2362150",
          "tgn:1000001",
          "tgn:7012149",
          "tgn:1002446",
          "tgn:7007251",
          "tgn:7029392"
        ],
        "placetype": [
          "aat:300132316"
        ],
        "id": 2362150,
        "name:xx": "Grays Bay"
      }
    },
    {
      "geometry": {
        "type": "Point",
        "coordinates": [
          -93.4833,
          44.95
        ]
      },
      "type": "Feature",
      "properties": {
        "hierarchy": [
          "tgn:2362151",
          "tgn:1000001",
          "tgn:2001025",
          "tgn:7012149",
          "tgn:7007521",
          "tgn:7029392"
        ],
        "placetype": [
          "aat:300132316"
        ],
        "id": 2362151,
        "name:xx": "Grays Bay"
      }
    },
    {
      "geometry": {
        "type": "Point",
        "coordinates": [
          -78.6333,
          34.5833
        ]
      },
      "type": "Feature",
      "properties": {
        "hierarchy": [
          "tgn:2362152",
          "tgn:1000001",
          "tgn:2001471",
          "tgn:7012149",
          "tgn:7007709",
          "tgn:7029392"
        ],
        "placetype": [
          "aat:300008905"
        ],
        "id": 2362152,
        "name:xx": "Grays Bay"
      }
    },
    {
      "geometry": {
        "type": "Point",
        "coordinates": [
          -123.7,
          46.2833
        ]
      },
      "type": "Feature",
      "properties": {
        "hierarchy": [
          "tgn:2362153",
          "tgn:1000001",
          "tgn:7012149",
          "tgn:7007920",
          "tgn:7029392"
        ],
        "placetype": [
          "aat:300132316"
        ],
        "id": 2362153,
        "name:xx": "Grays Bay"
      }
    },
    {
      "geometry": {
        "type": "Point",
        "coordinates": [
          -91.2667,
          29.5667
        ]
      },
      "type": "Feature",
      "properties": {
        "hierarchy": [
          "tgn:2362154",
          "tgn:1000001",
          "tgn:7012149",
          "tgn:2000904",
          "tgn:7007256",
          "tgn:7029392"
        ],
        "placetype": [
          "aat:300008699"
        ],
        "id": 2362154,
        "name:xx": "Grays Bayou"
      }
    },
    {
      "geometry": {
        "type": "Point",
        "coordinates": [
          -93.9333,
          30.0333
        ]
      },
      "type": "Feature",
      "properties": {
        "hierarchy": [
          "tgn:2362155",
          "tgn:1000001",
          "tgn:7012149",
          "tgn:2002052",
          "tgn:7007826",
          "tgn:7029392"
        ],
        "placetype": [
          "aat:300008699"
        ],
        "id": 2362155,
        "name:xx": "Grays Bayou"
      }
    },
    {
      "geometry": {
        "type": "Point",
        "coordinates": [
          -83.2667,
          36.7833
        ]
      },
      "type": "Feature",
      "properties": {
        "hierarchy": [
          "tgn:2362156",
          "tgn:1000001",
          "tgn:7012149",
          "tgn:2000797",
          "tgn:7007255",
          "tgn:7029392"
        ],
        "placetype": [
          "aat:300008699"
        ],
        "id": 2362156,
        "name:xx": "Grays Branch"
      }
    },
    {
      "geometry": {
        "type": "Point",
        "coordinates": [
          -82.6667,
          37.1833
        ]
      },
      "type": "Feature",
      "properties": {
        "hierarchy": [
          "tgn:2362157",
          "tgn:1000001",
          "tgn:7012149",
          "tgn:2000812",
          "tgn:7007255",
          "tgn:7029392"
        ],
        "placetype": [
          "aat:300008699"
        ],
        "id": 2362157,
        "name:xx": "Grays Branch"
      }
    },
    {
      "geometry": {
        "type": "Point",
        "coordinates": [
          -83.6667,
          37.8
        ]
      },
      "type": "Feature",
      "properties": {
        "hierarchy": [
          "tgn:2362158",
          "tgn:1000001",
          "tgn:7012149",
          "tgn:2000838",
          "tgn:7007255",
          "tgn:7029392"
        ],
        "placetype": [
          "aat:300008699"
        ],
        "id": 2362158,
        "name:xx": "Grays Branch"
      }
    },
    {
      "geometry": {
        "type": "Point",
        "coordinates": [
          -87.4333,
          37.1
        ]
      },
      "type": "Feature",
      "properties": {
        "hierarchy": [
          "tgn:2362159",
          "tgn:1000001",
          "tgn:7012149",
          "tgn:7007255",
          "tgn:7029392"
        ],
        "placetype": [
          "aat:300008699"
        ],
        "id": 2362159,
        "name:xx": "Grays Branch"
      }
    }
  ]
}
