{
  "geometry": {
    "type": "Point",
    "coordinates": [
      -94.25,
      40.3333
    ]
  },
  "type": "Feature",
  "properties": {
    "hierarchy": [
      "tgn:2465829",
      "tgn:1000001",
      "tgn:7012149",
      "tgn:2001198",
      "tgn:7007523",
      "tgn:7029392"
    ],
    "placetype": [
      "aat:300008347"
    ],
    "id": 2465829,
    "name:xx": "Lone Star"
  }
}
