{
  "geometry": {
    "type": "Point",
    "coordinates": [
      -98.75,
      28.3833
    ]
  },
  "type": "Feature",
  "properties": {
    "hierarchy": [
      "tgn:2644998",
      "tgn:1000001",
      "tgn:7012149",
      "tgn:2002035",
      "tgn:7007826",
      "tgn:7029392"
    ],
    "placetype": [
      "aat:300006191"
    ],
    "id": 2644998,
    "name:xx": "Sauce Verde Tank"
  }
}
