{
  "geometry": {
    "type": "Point",
    "coordinates": [
      -83.6667,
      35.0167
    ]
  },
  "type": "Feature",
  "properties": {
    "hierarchy": [
      "tgn:2076628",
      "tgn:1000001",
      "tgn:2001483",
      "tgn:7012149",
      "tgn:7007709",
      "tgn:7029392"
    ],
    "placetype": [
      "aat:300008347"
    ],
    "id": 2076628,
    "name:xx": "Shooting Creek"
  }
}
