{
  "type": "FeatureCollection",
  "features": [
    {
      "geometry": {
        "type": "Point",
        "coordinates": [
          9.366667,
          53.866667
        ]
      },
      "type": "Feature",
      "properties": {
        "hierarchy": [
          "tgn:7124840",
          "tgn:1000003",
          "tgn:7003688",
          "tgn:7000084",
          "tgn:7029392"
        ],
        "placetype": [
          "aat:300000206"
        ],
        "id": 7124840,
        "name:xx": "Neumühlen"
      }
    },
    {
      "geometry": {
        "type": "Point",
        "coordinates": [
          8.733333,
          53.616667
        ]
      },
      "type": "Feature",
      "properties": {
        "hierarchy": [
          "tgn:7124841",
          "tgn:1000003",
          "tgn:7003676",
          "tgn:7000084",
          "tgn:7029392"
        ],
        "placetype": [
          "aat:300000206"
        ],
        "id": 7124841,
        "name:xx": "Neumühlen"
      }
    },
    {
      "geometry": {
        "type": "Point",
        "coordinates": [
          11.35,
          53.616667
        ]
      },
      "type": "Feature",
      "properties": {
        "hierarchy": [
          "tgn:7124843",
          "tgn:1000003",
          "tgn:7000094",
          "tgn:7000084",
          "tgn:7029392"
        ],
        "placetype": [
          "aat:300000745"
        ],
        "id": 7124843,
        "name:xx": "Neumühle"
      }
    },
    {
      "geometry": {
        "type": "Point",
        "coordinates": [
          10.733333,
          53.016667
        ]
      },
      "type": "Feature",
      "properties": {
        "hierarchy": [
          "tgn:7124844",
          "tgn:1000003",
          "tgn:7003676",
          "tgn:7000084",
          "tgn:7029392"
        ],
        "placetype": [
          "aat:300008347"
        ],
        "id": 7124844,
        "name:xx": "Neumühle"
      }
    },
    {
      "geometry": {
        "type": "Point",
        "coordinates": [
          12.833333,
          52.966667
        ]
      },
      "type": "Feature",
      "properties": {
        "hierarchy": [
          "tgn:7124845",
          "tgn:7000096",
          "tgn:1000003",
          "tgn:7000084",
          "tgn:7029392"
        ],
        "placetype": [
          "aat:300008347"
        ],
        "id": 7124845,
        "name:xx": "Neumühle"
      }
    },
    {
      "geometry": {
        "type": "Point",
        "coordinates": [
          14.383333,
          51.65
        ]
      },
      "type": "Feature",
      "properties": {
        "hierarchy": [
          "tgn:7124846",
          "tgn:7000096",
          "tgn:1000003",
          "tgn:7000084",
          "tgn:7029392"
        ],
        "placetype": [
          "aat:300008347"
        ],
        "id": 7124846,
        "name:xx": "Neumühle"
      }
    },
    {
      "geometry": {
        "type": "Point",
        "coordinates": [
          12.166667,
          50.7
        ]
      },
      "type": "Feature",
      "properties": {
        "hierarchy": [
          "tgn:7124847",
          "tgn:1000003",
          "tgn:7003689",
          "tgn:7000084",
          "tgn:7029392"
        ],
        "placetype": [
          "aat:300008347"
        ],
        "id": 7124847,
        "name:xx": "Neumühle"
      }
    },
    {
      "geometry": {
        "type": "Point",
        "coordinates": [
          12.633333,
          50.666667
        ]
      },
      "type": "Feature",
      "properties": {
        "hierarchy": [
          "tgn:7124848",
          "tgn:1000003",
          "tgn:7003685",
          "tgn:7000084",
          "tgn:7029392"
        ],
        "placetype": [
          "aat:300008347"
        ],
        "id": 7124848,
        "name:xx": "Neumühle"
      }
    },
    {
      "geometry": {
        "type": "Point",
        "coordinates": [
          11.783333,
          50.283333
        ]
      },
      "type": "Feature",
      "properties": {
        "hierarchy": [
          "tgn:7124849",
          "tgn:7003669",
          "tgn:1000003",
          "tgn:7000084",
          "tgn:7029392"
        ],
        "placetype": [
          "aat:300008347"
        ],
        "id": 7124849,
        "name:xx": "Neumühle"
      }
    }
  ]
}
