{
  "geometry": {
    "type": "Point",
    "coordinates": [
      -76.1167,
      36.8667
    ]
  },
  "type": "Feature",
  "properties": {
    "hierarchy": [
      "tgn:2778358",
      "tgn:1000001",
      "tgn:7012149",
      "tgn:7022218",
      "tgn:7007919",
      "tgn:7029392"
    ],
    "placetype": [
      "aat:300008850"
    ],
    "id": 2778358,
    "name:xx": "Witch Duck Point"
  }
}
