{
  "geometry": {
    "type": "Point",
    "coordinates": [
      -72.1275,
      -43.483889
    ]
  },
  "type": "Feature",
  "properties": {
    "hierarchy": [
      "tgn:7289968",
      "tgn:1001699",
      "tgn:1000049",
      "tgn:1000002",
      "tgn:7029392"
    ],
    "placetype": [
      "aat:300008699"
    ],
    "id": 7289968,
    "name:xx": "El Azul, Río"
  }
}
