{
  "type": "FeatureCollection",
  "features": [
    {
      "geometry": {
        "type": "Point",
        "coordinates": [
          11.2,
          53.566667
        ]
      },
      "type": "Feature",
      "properties": {
        "hierarchy": [
          "tgn:7197610",
          "tgn:1000003",
          "tgn:7000094",
          "tgn:7000084",
          "tgn:7029392"
        ],
        "placetype": [
          "aat:300008863"
        ],
        "id": 7197610,
        "name:xx": "Dümmerhütter Forst"
      }
    },
    {
      "geometry": {
        "type": "Point",
        "coordinates": [
          11.233333,
          53.566667
        ]
      },
      "type": "Feature",
      "properties": {
        "hierarchy": [
          "tgn:7197611",
          "tgn:1000003",
          "tgn:7000094",
          "tgn:7000084",
          "tgn:7029392"
        ],
        "placetype": [
          "aat:300008347"
        ],
        "id": 7197611,
        "name:xx": "Dümmerhütte"
      }
    },
    {
      "geometry": {
        "type": "Point",
        "coordinates": [
          11.5,
          51.4
        ]
      },
      "type": "Feature",
      "properties": {
        "hierarchy": [
          "tgn:7197612",
          "tgn:1000003",
          "tgn:7003687",
          "tgn:7000084",
          "tgn:7029392"
        ],
        "placetype": [
          "aat:300008777"
        ],
        "id": 7197612,
        "name:xx": "Dummer-Berg"
      }
    },
    {
      "geometry": {
        "type": "Point",
        "coordinates": [
          7.483333,
          51.85
        ]
      },
      "type": "Feature",
      "properties": {
        "hierarchy": [
          "tgn:7197613",
          "tgn:1000003",
          "tgn:7003677",
          "tgn:7000084",
          "tgn:7029392"
        ],
        "placetype": [
          "aat:300008699"
        ],
        "id": 7197613,
        "name:xx": "Dümmer"
      }
    },
    {
      "geometry": {
        "type": "Point",
        "coordinates": [
          11.2,
          53.583333
        ]
      },
      "type": "Feature",
      "properties": {
        "hierarchy": [
          "tgn:7197614",
          "tgn:1000003",
          "tgn:7000094",
          "tgn:7000084",
          "tgn:7029392"
        ],
        "placetype": [
          "aat:300008347"
        ],
        "id": 7197614,
        "name:xx": "Dümmer"
      }
    },
    {
      "geometry": {
        "type": "Point",
        "coordinates": [
          12.95,
          48.533333
        ]
      },
      "type": "Feature",
      "properties": {
        "hierarchy": [
          "tgn:7197616",
          "tgn:7003669",
          "tgn:1000003",
          "tgn:7000084",
          "tgn:7029392"
        ],
        "placetype": [
          "aat:300008347"
        ],
        "id": 7197616,
        "name:xx": "Dummeldorf"
      }
    },
    {
      "geometry": {
        "type": "Point",
        "coordinates": [
          7.266667,
          51.683333
        ]
      },
      "type": "Feature",
      "properties": {
        "hierarchy": [
          "tgn:7197619",
          "tgn:1000003",
          "tgn:7003677",
          "tgn:7000084",
          "tgn:7029392"
        ],
        "placetype": [
          "aat:300008777"
        ],
        "id": 7197619,
        "name:xx": "Dumm-Berg"
      }
    }
  ]
}
