{
  "geometry": {
    "type": "Point",
    "coordinates": [
      -77.8167,
      35.8833
    ]
  },
  "type": "Feature",
  "properties": {
    "hierarchy": [
      "tgn:2453542",
      "tgn:1000001",
      "tgn:7012149",
      "tgn:7007709",
      "tgn:7029392"
    ],
    "placetype": [
      "aat:300008699"
    ],
    "id": 2453542,
    "name:xx": "Little Cokey Swamp"
  }
}
