{
  "geometry": {
    "type": "Point",
    "coordinates": [
      -90.8167,
      38.1333
    ]
  },
  "type": "Feature",
  "properties": {
    "hierarchy": [
      "tgn:2391773",
      "tgn:1000001",
      "tgn:7012149",
      "tgn:2001254",
      "tgn:7007523",
      "tgn:7029392"
    ],
    "placetype": [
      "aat:300006191"
    ],
    "id": 2391773,
    "name:xx": "Hillside View Lake"
  }
}
