{
  "geometry": {
    "type": "Point",
    "coordinates": [
      -107.1333,
      37.4333
    ]
  },
  "type": "Feature",
  "properties": {
    "hierarchy": [
      "tgn:2579953",
      "tgn:1000001",
      "tgn:7012149",
      "tgn:7007158",
      "tgn:7029392"
    ],
    "placetype": [
      "aat:300006075"
    ],
    "id": 2579953,
    "name:xx": "Piedra Falls Ditch"
  }
}
