{
  "geometry": {
    "type": "Point",
    "coordinates": [
      30.55,
      29.383333
    ]
  },
  "type": "Feature",
  "properties": {
    "hierarchy": [
      "tgn:7540126",
      "tgn:7001242",
      "tgn:7001105",
      "tgn:7016833",
      "tgn:7029392"
    ],
    "placetype": [
      "aat:300000833"
    ],
    "id": 7540126,
    "name:xx": "Qaşr al Banāt"
  }
}
