{
  "geometry": {
    "type": "Point",
    "coordinates": [
      124.9167,
      38.1667
    ]
  },
  "type": "Feature",
  "properties": {
    "hierarchy": [
      "tgn:1082051",
      "tgn:1001301",
      "tgn:1000004",
      "tgn:1000122",
      "tgn:7029392"
    ],
    "placetype": [
      "aat:300008347"
    ],
    "id": 1082051,
    "name:xx": "Monggŭmpo"
  }
}
