{
  "geometry": {
    "type": "Point",
    "coordinates": [
      -149.8167,
      62.3833
    ]
  },
  "type": "Feature",
  "properties": {
    "hierarchy": [
      "tgn:2431717",
      "tgn:7006450",
      "tgn:1000001",
      "tgn:2124053",
      "tgn:7012149",
      "tgn:7029392"
    ],
    "placetype": [
      "aat:300008680"
    ],
    "id": 2431717,
    "name:xx": "Katie Lake"
  }
}
