{
  "type": "FeatureCollection",
  "features": [
    {
      "geometry": {
        "type": "Point",
        "coordinates": [
          165.4167,
          -20.95
        ]
      },
      "type": "Feature",
      "properties": {
        "hierarchy": [
          "tgn:1010490",
          "tgn:7000665",
          "tgn:1000223",
          "tgn:1000006",
          "tgn:7029392"
        ],
        "placetype": [
          "aat:300008850"
        ],
        "id": 1010490,
        "name:xx": "Bayes, Cap"
      }
    },
    {
      "geometry": {
        "type": "Point",
        "coordinates": [
          -125.3333,
          48.7333
        ]
      },
      "type": "Feature",
      "properties": {
        "hierarchy": [
          "tgn:1010491",
          "tgn:7005735",
          "tgn:7005685",
          "tgn:1000001",
          "tgn:7013409",
          "tgn:7029392"
        ],
        "placetype": [
          "aat:300008850"
        ],
        "id": 1010491,
        "name:xx": "Beale, Cape"
      }
    },
    {
      "geometry": {
        "type": "Point",
        "coordinates": [
          -71.422,
          17.605
        ]
      },
      "type": "Feature",
      "properties": {
        "hierarchy": [
          "tgn:1010492",
          "tgn:7005412",
          "tgn:1000001",
          "tgn:7005388",
          "tgn:7029392"
        ],
        "placetype": [
          "aat:300008850"
        ],
        "id": 1010492,
        "name:xx": "Beata, Cabo"
      }
    },
    {
      "geometry": {
        "type": "Point",
        "coordinates": [
          -9.3167,
          32.6333
        ]
      },
      "type": "Feature",
      "properties": {
        "hierarchy": [
          "tgn:1010495",
          "tgn:7593672",
          "tgn:7001242",
          "tgn:1000179",
          "tgn:7029392"
        ],
        "placetype": [
          "aat:300008850"
        ],
        "id": 1010495,
        "name:xx": "Beddouza, Cap"
      }
    }
  ]
}
