{
  "geometry": {
    "type": "Point",
    "coordinates": [
      -105.15,
      41.4167
    ]
  },
  "type": "Feature",
  "properties": {
    "hierarchy": [
      "tgn:2675985",
      "tgn:1000001",
      "tgn:7012149",
      "tgn:2002375",
      "tgn:7007923",
      "tgn:7029392"
    ],
    "placetype": [
      "aat:300006075"
    ],
    "id": 2675985,
    "name:xx": "Sophia Ditch"
  }
}
