{
  "geometry": {
    "type": "Point",
    "coordinates": [
      10.05,
      51.05
    ]
  },
  "type": "Feature",
  "properties": {
    "hierarchy": [
      "tgn:7111176",
      "tgn:1000003",
      "tgn:7003678",
      "tgn:7000084",
      "tgn:7029392"
    ],
    "placetype": [
      "aat:300000206"
    ],
    "id": 7111176,
    "name:xx": "Vorwerk Rittersberg"
  }
}
