{
  "geometry": {
    "type": "Point",
    "coordinates": [
      -81.5167,
      37.4333
    ]
  },
  "type": "Feature",
  "properties": {
    "hierarchy": [
      "tgn:2513084",
      "tgn:1000001",
      "tgn:7012149",
      "tgn:2002274",
      "tgn:7013961",
      "tgn:7029392"
    ],
    "placetype": [
      "aat:300008706"
    ],
    "id": 2513084,
    "name:xx": "Mill Creek"
  }
}
