{
  "geometry": {
    "type": "Point",
    "coordinates": [
      34.838367,
      23.478661
    ]
  },
  "type": "Feature",
  "properties": {
    "hierarchy": [
      "tgn:7527987",
      "tgn:7001242",
      "tgn:7001311",
      "tgn:7016833",
      "tgn:7029392"
    ],
    "placetype": [
      "aat:300379998"
    ],
    "name:en": "Silsila, Wâdi",
    "id": 7527987
  }
}
