{
  "geometry": {
    "type": "Point",
    "coordinates": [
      -68.2833,
      -34.6167
    ]
  },
  "type": "Feature",
  "properties": {
    "hierarchy": [
      "tgn:1019372",
      "tgn:7006477",
      "tgn:1001427",
      "tgn:1000002",
      "tgn:7029392"
    ],
    "placetype": [
      "aat:300008347"
    ],
    "id": 1019372,
    "name:xx": "Cuadro Nacional"
  }
}
