{
  "geometry": {
    "type": "Point",
    "coordinates": [
      -99.9167,
      29.85
    ]
  },
  "type": "Feature",
  "properties": {
    "hierarchy": [
      "tgn:2573541",
      "tgn:1000001",
      "tgn:7012149",
      "tgn:2002060",
      "tgn:7007826",
      "tgn:7029392"
    ],
    "placetype": [
      "aat:300008697"
    ],
    "id": 2573541,
    "name:xx": "Pecan Springs"
  }
}
