{
  "type": "FeatureCollection",
  "features": [
    {
      "geometry": {
        "type": "Point",
        "coordinates": [
          -155.8167,
          20.0167
        ]
      },
      "type": "Feature",
      "properties": {
        "hierarchy": [
          "tgn:2747780",
          "tgn:7023902",
          "tgn:1000001",
          "tgn:7012149",
          "tgn:7007249",
          "tgn:7029392"
        ],
        "placetype": [
          "aat:300008850"
        ],
        "id": 2747780,
        "name:xx": "Waiulaula Point"
      }
    },
    {
      "geometry": {
        "type": "Point",
        "coordinates": [
          -155.6,
          20.0333
        ]
      },
      "type": "Feature",
      "properties": {
        "hierarchy": [
          "tgn:2747782",
          "tgn:7023902",
          "tgn:1000001",
          "tgn:7012149",
          "tgn:7007249",
          "tgn:7029392"
        ],
        "placetype": [
          "aat:300008699"
        ],
        "id": 2747782,
        "name:xx": "Waiulili Stream"
      }
    },
    {
      "geometry": {
        "type": "Point",
        "coordinates": [
          -155.8833,
          19.9167
        ]
      },
      "type": "Feature",
      "properties": {
        "hierarchy": [
          "tgn:2747783",
          "tgn:7023902",
          "tgn:1000001",
          "tgn:7012149",
          "tgn:7007249",
          "tgn:7029392"
        ],
        "placetype": [
          "aat:300132316"
        ],
        "id": 2747783,
        "name:xx": "Waiulua Bay"
      }
    },
    {
      "geometry": {
        "type": "Point",
        "coordinates": [
          -155.3833,
          19.2
        ]
      },
      "type": "Feature",
      "properties": {
        "hierarchy": [
          "tgn:2747784",
          "tgn:7023902",
          "tgn:1000001",
          "tgn:7012149",
          "tgn:7007249",
          "tgn:7029392"
        ],
        "placetype": [
          "aat:300008850"
        ],
        "id": 2747784,
        "name:xx": "Waiwelawela Point"
      }
    },
    {
      "geometry": {
        "type": "Point",
        "coordinates": [
          -155.7333,
          20.2
        ]
      },
      "type": "Feature",
      "properties": {
        "hierarchy": [
          "tgn:2747785",
          "tgn:7023902",
          "tgn:1000001",
          "tgn:7012149",
          "tgn:7007249",
          "tgn:7029392"
        ],
        "placetype": [
          "aat:300055621"
        ],
        "id": 2747785,
        "name:xx": "Wakaina"
      }
    },
    {
      "geometry": {
        "type": "Point",
        "coordinates": [
          -83.0167,
          29.2
        ]
      },
      "type": "Feature",
      "properties": {
        "hierarchy": [
          "tgn:2747786",
          "tgn:1000001",
          "tgn:7012149",
          "tgn:2000277",
          "tgn:7007240",
          "tgn:7029392"
        ],
        "placetype": [
          "aat:300008347",
          "aat:300167671"
        ],
        "id": 2747786,
        "name:xx": "Wakasassa"
      }
    },
    {
      "geometry": {
        "type": "Point",
        "coordinates": [
          -82,
          40.1167
        ]
      },
      "type": "Feature",
      "properties": {
        "hierarchy": [
          "tgn:2747787",
          "tgn:1000001",
          "tgn:2079316",
          "tgn:7012149",
          "tgn:1002701",
          "tgn:7007706",
          "tgn:7029392"
        ],
        "placetype": [
          "aat:300008347",
          "aat:300000745"
        ],
        "id": 2747787,
        "name:xx": "Wakatomika"
      }
    },
    {
      "geometry": {
        "type": "Point",
        "coordinates": [
          -92.2,
          36.3
        ]
      },
      "type": "Feature",
      "properties": {
        "hierarchy": [
          "tgn:2747788",
          "tgn:2000107",
          "tgn:1000001",
          "tgn:7016172",
          "tgn:7012149",
          "tgn:7029392"
        ],
        "placetype": [
          "aat:300008347"
        ],
        "id": 2747788,
        "name:xx": "Wake"
      }
    },
    {
      "geometry": {
        "type": "Point",
        "coordinates": [
          -121.6,
          43.8333
        ]
      },
      "type": "Feature",
      "properties": {
        "hierarchy": [
          "tgn:2747789",
          "tgn:1000001",
          "tgn:2001705",
          "tgn:7012149",
          "tgn:7007708",
          "tgn:7029392"
        ],
        "placetype": [
          "aat:300266640"
        ],
        "id": 2747789,
        "name:xx": "Wake Butte"
      }
    }
  ]
}
