{
  "geometry": {
    "type": "Point",
    "coordinates": [
      -84.1667,
      37.6167
    ]
  },
  "type": "Feature",
  "properties": {
    "hierarchy": [
      "tgn:2295741",
      "tgn:1000001",
      "tgn:7012149",
      "tgn:7007255",
      "tgn:7029392"
    ],
    "placetype": [
      "aat:300008706"
    ],
    "id": 2295741,
    "name:xx": "Drowning Creek"
  }
}
