{
  "geometry": {
    "type": "Point",
    "coordinates": [
      -98.6333,
      34.6333
    ]
  },
  "type": "Feature",
  "properties": {
    "hierarchy": [
      "tgn:2083149",
      "tgn:1000001",
      "tgn:2001638",
      "tgn:7012149",
      "tgn:7007707",
      "tgn:7029392"
    ],
    "placetype": [
      "aat:300387016"
    ],
    "id": 2083149,
    "name:xx": "Eagle"
  }
}
