{
  "geometry": {
    "type": "Point",
    "coordinates": [
      -75.0667,
      39.8833
    ]
  },
  "type": "Feature",
  "properties": {
    "hierarchy": [
      "tgn:2577039",
      "tgn:1002227",
      "tgn:1000001",
      "tgn:7012149",
      "tgn:7007565",
      "tgn:7029392"
    ],
    "placetype": [
      "aat:300008706"
    ],
    "id": 2577039,
    "name:xx": "Peter Creek"
  }
}
