{
  "geometry": {
    "type": "Point",
    "coordinates": [
      -2.05,
      40.55
    ]
  },
  "type": "Feature",
  "properties": {
    "hierarchy": [
      "tgn:7331194",
      "tgn:7002818",
      "tgn:1001647",
      "tgn:1000003",
      "tgn:1000095",
      "tgn:7029392"
    ],
    "placetype": [
      "aat:300008680"
    ],
    "id": 7331194,
    "name:xx": "Grande, Laguna"
  }
}
