{
  "geometry": {
    "type": "Point",
    "coordinates": [
      -88.0667,
      45.2833
    ]
  },
  "type": "Feature",
  "properties": {
    "hierarchy": [
      "tgn:2474219",
      "tgn:1000001",
      "tgn:7012149",
      "tgn:2002337",
      "tgn:7007922",
      "tgn:7029392"
    ],
    "placetype": [
      "aat:300008699"
    ],
    "id": 2474219,
    "name:xx": "Lower Middle Inlet"
  }
}
