{
  "type": "FeatureCollection",
  "features": [
    {
      "geometry": {
        "type": "Point",
        "coordinates": [
          30.896946,
          29.462546
        ]
      },
      "type": "Feature",
      "properties": {
        "hierarchy": [
          "tgn:7541150",
          "tgn:7001242",
          "tgn:7001105",
          "tgn:7016833",
          "tgn:7029392"
        ],
        "placetype": [
          "aat:300008347"
        ],
        "name:en": "'Izbat aş Şabāḩīyah",
        "id": 7541150
      }
    },
    {
      "geometry": {
        "type": "Point",
        "coordinates": [
          30.884532,
          29.462091
        ]
      },
      "type": "Feature",
      "properties": {
        "hierarchy": [
          "tgn:7541151",
          "tgn:7001242",
          "tgn:7001105",
          "tgn:7016833",
          "tgn:7029392"
        ],
        "placetype": [
          "aat:300008347"
        ],
        "name:en": "'Izbat Ḩusayn Abū Shannāf",
        "id": 7541151
      }
    },
    {
      "geometry": {
        "type": "Point",
        "coordinates": [
          30.930782,
          29.487578
        ]
      },
      "type": "Feature",
      "properties": {
        "hierarchy": [
          "tgn:7541152",
          "tgn:7001242",
          "tgn:7001105",
          "tgn:7016833",
          "tgn:7029392"
        ],
        "placetype": [
          "aat:300008347"
        ],
        "name:en": "'Izbat Jazīrat Kāmil",
        "id": 7541152
      }
    },
    {
      "geometry": {
        "type": "Point",
        "coordinates": [
          30.883105,
          29.431356
        ]
      },
      "type": "Feature",
      "properties": {
        "hierarchy": [
          "tgn:7541153",
          "tgn:7001242",
          "tgn:7001105",
          "tgn:7016833",
          "tgn:7029392"
        ],
        "placetype": [
          "aat:300008347"
        ],
        "name:en": "'Izbat Ḩusnī",
        "id": 7541153
      }
    },
    {
      "geometry": {
        "type": "Point",
        "coordinates": [
          30.880289,
          29.461459
        ]
      },
      "type": "Feature",
      "properties": {
        "hierarchy": [
          "tgn:7541154",
          "tgn:7001242",
          "tgn:7001105",
          "tgn:7016833",
          "tgn:7029392"
        ],
        "placetype": [
          "aat:300008347"
        ],
        "name:en": "Minsha'at Banī 'Uthmān",
        "id": 7541154
      }
    },
    {
      "geometry": {
        "type": "Point",
        "coordinates": [
          30.881639,
          29.46591
        ]
      },
      "type": "Feature",
      "properties": {
        "hierarchy": [
          "tgn:7541155",
          "tgn:7001242",
          "tgn:7001105",
          "tgn:7016833",
          "tgn:7029392"
        ],
        "placetype": [
          "aat:300008347"
        ],
        "name:en": "'Izbat al 'Arīf",
        "id": 7541155
      }
    },
    {
      "geometry": {
        "type": "Point",
        "coordinates": [
          30.879144,
          29.483576
        ]
      },
      "type": "Feature",
      "properties": {
        "hierarchy": [
          "tgn:7541156",
          "tgn:7001242",
          "tgn:7001105",
          "tgn:7016833",
          "tgn:7029392"
        ],
        "placetype": [
          "aat:300008347"
        ],
        "name:en": "'Izbat al Barm",
        "id": 7541156
      }
    },
    {
      "geometry": {
        "type": "Point",
        "coordinates": [
          30.86764,
          29.497279
        ]
      },
      "type": "Feature",
      "properties": {
        "hierarchy": [
          "tgn:7541157",
          "tgn:7001242",
          "tgn:7001105",
          "tgn:7016833",
          "tgn:7029392"
        ],
        "placetype": [
          "aat:300008347"
        ],
        "name:en": "'Izbat 'Abd al 'Az̧īm",
        "id": 7541157
      }
    },
    {
      "geometry": {
        "type": "Point",
        "coordinates": [
          30.846598,
          29.469618
        ]
      },
      "type": "Feature",
      "properties": {
        "hierarchy": [
          "tgn:7541158",
          "tgn:7001242",
          "tgn:7001105",
          "tgn:7016833",
          "tgn:7029392"
        ],
        "placetype": [
          "aat:300008347"
        ],
        "name:en": "'Izbat Muḩammad Jūdah",
        "id": 7541158
      }
    },
    {
      "geometry": {
        "type": "Point",
        "coordinates": [
          30.865579,
          29.465803
        ]
      },
      "type": "Feature",
      "properties": {
        "hierarchy": [
          "tgn:7541159",
          "tgn:7001242",
          "tgn:7001105",
          "tgn:7016833",
          "tgn:7029392"
        ],
        "placetype": [
          "aat:300008347"
        ],
        "name:en": "'Izbat Abū Su'ād",
        "id": 7541159
      }
    }
  ]
}
