{
  "geometry": {
    "type": "Point",
    "coordinates": [
      -117.4833,
      46.7167
    ]
  },
  "type": "Feature",
  "properties": {
    "hierarchy": [
      "tgn:2695437",
      "tgn:1000001",
      "tgn:7012149",
      "tgn:2002252",
      "tgn:7007920",
      "tgn:7029392"
    ],
    "placetype": [
      "aat:300008761"
    ],
    "id": 2695437,
    "name:xx": "Stine Gulch"
  }
}
