{
  "geometry": {
    "type": "Point",
    "coordinates": [
      -0.05,
      38.816667
    ]
  },
  "type": "Feature",
  "properties": {
    "hierarchy": [
      "tgn:7327604",
      "tgn:7002804",
      "tgn:1000003",
      "tgn:7002793",
      "tgn:1000095",
      "tgn:7029392"
    ],
    "placetype": [
      "aat:300008347"
    ],
    "id": 7327604,
    "name:xx": "Ráfol de Almunia"
  }
}
