{
  "type": "FeatureCollection",
  "features": [
    {
      "geometry": {
        "type": "Point",
        "coordinates": [
          -111.9,
          46.3167
        ]
      },
      "type": "Feature",
      "properties": {
        "hierarchy": [
          "tgn:2604420",
          "tgn:1000001",
          "tgn:7012149",
          "tgn:2001281",
          "tgn:7007524",
          "tgn:7029392"
        ],
        "placetype": [
          "aat:300008761"
        ],
        "id": 2604420,
        "name:xx": "Rabbit Gulch"
      }
    },
    {
      "geometry": {
        "type": "Point",
        "coordinates": [
          -103.5667,
          43.8833
        ]
      },
      "type": "Feature",
      "properties": {
        "hierarchy": [
          "tgn:2604421",
          "tgn:1000001",
          "tgn:7012149",
          "tgn:2001821",
          "tgn:7007713",
          "tgn:7029392"
        ],
        "placetype": [
          "aat:300008761"
        ],
        "id": 2604421,
        "name:xx": "Rabbit Gulch"
      }
    },
    {
      "geometry": {
        "type": "Point",
        "coordinates": [
          -110.7,
          40.3
        ]
      },
      "type": "Feature",
      "properties": {
        "hierarchy": [
          "tgn:2604422",
          "tgn:1000001",
          "tgn:2002107",
          "tgn:7012149",
          "tgn:7007827",
          "tgn:7029392"
        ],
        "placetype": [
          "aat:300008761"
        ],
        "id": 2604422,
        "name:xx": "Rabbit Gulch"
      }
    },
    {
      "geometry": {
        "type": "Point",
        "coordinates": [
          -85.95,
          38.0167
        ]
      },
      "type": "Feature",
      "properties": {
        "hierarchy": [
          "tgn:2604423",
          "tgn:1000001",
          "tgn:7012149",
          "tgn:1002457",
          "tgn:7007252",
          "tgn:7029392"
        ],
        "placetype": [
          "aat:300266640"
        ],
        "id": 2604423,
        "name:xx": "Rabbit Hash Ridge"
      }
    },
    {
      "geometry": {
        "type": "Point",
        "coordinates": [
          -119.9167,
          37.1333
        ]
      },
      "type": "Feature",
      "properties": {
        "hierarchy": [
          "tgn:2604424",
          "tgn:1000001",
          "tgn:7012149",
          "tgn:7007157",
          "tgn:1002621",
          "tgn:7029392"
        ],
        "placetype": [
          "aat:300008798"
        ],
        "id": 2604424,
        "name:xx": "Rabbit Hill"
      }
    },
    {
      "geometry": {
        "type": "Point",
        "coordinates": [
          -122.3833,
          41.6667
        ]
      },
      "type": "Feature",
      "properties": {
        "hierarchy": [
          "tgn:2604425",
          "tgn:1000001",
          "tgn:7012149",
          "tgn:7007157",
          "tgn:2000189",
          "tgn:7029392"
        ],
        "placetype": [
          "aat:300008798"
        ],
        "id": 2604425,
        "name:xx": "Rabbit Hill"
      }
    },
    {
      "geometry": {
        "type": "Point",
        "coordinates": [
          -73.3167,
          41.7167
        ]
      },
      "type": "Feature",
      "properties": {
        "hierarchy": [
          "tgn:2604426",
          "tgn:1000001",
          "tgn:1002601",
          "tgn:7012149",
          "tgn:7007159",
          "tgn:7029392"
        ],
        "placetype": [
          "aat:300008798"
        ],
        "id": 2604426,
        "name:xx": "Rabbit Hill"
      }
    },
    {
      "geometry": {
        "type": "Point",
        "coordinates": [
          -116.4,
          39.1833
        ]
      },
      "type": "Feature",
      "properties": {
        "hierarchy": [
          "tgn:2604427",
          "tgn:1000001",
          "tgn:2001413",
          "tgn:7012149",
          "tgn:7007526",
          "tgn:7029392"
        ],
        "placetype": [
          "aat:300008798"
        ],
        "id": 2604427,
        "name:xx": "Rabbit Hill"
      }
    },
    {
      "geometry": {
        "type": "Point",
        "coordinates": [
          -106.3667,
          35.7833
        ]
      },
      "type": "Feature",
      "properties": {
        "hierarchy": [
          "tgn:2604428",
          "tgn:1000001",
          "tgn:7012149",
          "tgn:2001451",
          "tgn:7007566",
          "tgn:7029392"
        ],
        "placetype": [
          "aat:300008798"
        ],
        "id": 2604428,
        "name:xx": "Rabbit Hill"
      }
    },
    {
      "geometry": {
        "type": "Point",
        "coordinates": [
          -98.45,
          34.7167
        ]
      },
      "type": "Feature",
      "properties": {
        "hierarchy": [
          "tgn:2604429",
          "tgn:1000001",
          "tgn:2001638",
          "tgn:7012149",
          "tgn:7007707",
          "tgn:7029392"
        ],
        "placetype": [
          "aat:300008798"
        ],
        "id": 2604429,
        "name:xx": "Rabbit Hill"
      }
    }
  ]
}
