{
  "geometry": {
    "type": "Point",
    "coordinates": [
      -163.0167,
      64.5167
    ]
  },
  "type": "Feature",
  "properties": {
    "hierarchy": [
      "tgn:2681970",
      "tgn:7006450",
      "tgn:1000001",
      "tgn:7012149",
      "tgn:2000079",
      "tgn:7029392"
    ],
    "placetype": [
      "aat:300132348"
    ],
    "id": 2681970,
    "name:xx": "South Spit"
  }
}
