{
  "geometry": {
    "type": "Point",
    "coordinates": [
      -92.15,
      31.65
    ]
  },
  "type": "Feature",
  "properties": {
    "hierarchy": [
      "tgn:2320868",
      "tgn:1000001",
      "tgn:7012149",
      "tgn:2000883",
      "tgn:7007256",
      "tgn:7029392"
    ],
    "placetype": [
      "aat:300008699"
    ],
    "id": 2320868,
    "name:xx": "Ezell Branch"
  }
}
