{
  "geometry": {
    "type": "Point",
    "coordinates": [
      -91.0333,
      36.9167
    ]
  },
  "type": "Feature",
  "properties": {
    "hierarchy": [
      "tgn:2438776",
      "tgn:1000001",
      "tgn:2001181",
      "tgn:7012149",
      "tgn:7007523",
      "tgn:7029392"
    ],
    "placetype": [
      "aat:300008761"
    ],
    "id": 2438776,
    "name:xx": "Kinnard Hollow"
  }
}
