{
  "geometry": {
    "type": "Point",
    "coordinates": [
      -92.95,
      34.9667
    ]
  },
  "type": "Feature",
  "properties": {
    "hierarchy": [
      "tgn:2168140",
      "tgn:1000001",
      "tgn:7016172",
      "tgn:7012149",
      "tgn:2000157",
      "tgn:7029392"
    ],
    "placetype": [
      "aat:300006191"
    ],
    "id": 2168140,
    "name:xx": "Big Fish Pond"
  }
}
