{
  "geometry": {
    "type": "Point",
    "coordinates": [
      -105.3833,
      31.55
    ]
  },
  "type": "Feature",
  "properties": {
    "hierarchy": [
      "tgn:2179513",
      "tgn:1000001",
      "tgn:7012149",
      "tgn:2002005",
      "tgn:7007826",
      "tgn:7029392"
    ],
    "placetype": [
      "aat:300008761"
    ],
    "id": 2179513,
    "name:xx": "Blanco Draw"
  }
}
