{
  "geometry": {
    "type": "Point",
    "coordinates": [
      -104.45,
      33.2833
    ]
  },
  "type": "Feature",
  "properties": {
    "hierarchy": [
      "tgn:2067218",
      "tgn:1000001",
      "tgn:2001430",
      "tgn:7012149",
      "tgn:7007566",
      "tgn:7029392"
    ],
    "placetype": [
      "aat:300008347"
    ],
    "id": 2067218,
    "name:xx": "Midway"
  }
}
