{
  "geometry": {
    "type": "Point",
    "coordinates": [
      -116.95,
      43.5167
    ]
  },
  "type": "Feature",
  "properties": {
    "hierarchy": [
      "tgn:2677388",
      "tgn:1000001",
      "tgn:7012149",
      "tgn:7029392"
    ],
    "placetype": [
      "aat:300006075"
    ],
    "id": 2677388,
    "name:xx": "South Canal"
  }
}
