{
  "geometry": {
    "type": "Point",
    "coordinates": [
      21.4333,
      32.4667
    ]
  },
  "type": "Feature",
  "properties": {
    "hierarchy": [
      "tgn:7001663",
      "tgn:7000606",
      "tgn:7001242",
      "tgn:1000172",
      "tgn:7029392"
    ],
    "placetype": [
      "aat:300008347",
      "aat:300000810"
    ],
    "id": 7001663,
    "name:xx": "Qaşr Lībīyā"
  }
}
