{
  "geometry": {
    "type": "Point",
    "coordinates": [
      -109.65,
      43.9667
    ]
  },
  "type": "Feature",
  "properties": {
    "hierarchy": [
      "tgn:2376498",
      "tgn:1000001",
      "tgn:7012149",
      "tgn:2002379",
      "tgn:7007923",
      "tgn:7029392"
    ],
    "placetype": [
      "aat:300008798"
    ],
    "id": 2376498,
    "name:xx": "Hardluck Mountain"
  }
}
