{
  "geometry": {
    "type": "Point",
    "coordinates": [
      -114.0833,
      37.4333
    ]
  },
  "type": "Feature",
  "properties": {
    "hierarchy": [
      "tgn:2290003",
      "tgn:1000001",
      "tgn:7012149",
      "tgn:7029392"
    ],
    "placetype": [
      "aat:300008761"
    ],
    "id": 2290003,
    "name:xx": "Docs Pass Canyon"
  }
}
