{
  "geometry": {
    "type": "Point",
    "coordinates": [
      -81.2333,
      38.4167
    ]
  },
  "type": "Feature",
  "properties": {
    "hierarchy": [
      "tgn:2555393",
      "tgn:1000001",
      "tgn:2002259",
      "tgn:7012149",
      "tgn:7013961",
      "tgn:7029392"
    ],
    "placetype": [
      "aat:300008347"
    ],
    "id": 2555393,
    "name:xx": "Odessa"
  }
}
