{
  "geometry": {
    "type": "Point",
    "coordinates": [
      -73.5833,
      41.3167
    ]
  },
  "type": "Feature",
  "properties": {
    "hierarchy": [
      "tgn:2072114",
      "tgn:1000001",
      "tgn:7012149",
      "tgn:7014612",
      "tgn:7007568",
      "tgn:7029392"
    ],
    "placetype": [
      "aat:300008347"
    ],
    "id": 2072114,
    "name:xx": "Salem Center"
  }
}
