{
  "geometry": {
    "type": "Point",
    "coordinates": [
      74.975,
      32.666667
    ]
  },
  "type": "Feature",
  "properties": {
    "hierarchy": [
      "tgn:7592064",
      "tgn:1000004",
      "tgn:7000198",
      "tgn:7000799",
      "tgn:7029392"
    ],
    "placetype": [
      "aat:300008347"
    ],
    "name:en": "Tukār",
    "id": 7592064
  }
}
