{
  "geometry": {
    "type": "Point",
    "coordinates": [
      -112.85,
      37.6833
    ]
  },
  "type": "Feature",
  "properties": {
    "hierarchy": [
      "tgn:2298191",
      "tgn:1000001",
      "tgn:7012149",
      "tgn:2002111",
      "tgn:7007827",
      "tgn:7029392"
    ],
    "placetype": [
      "aat:300008706"
    ],
    "id": 2298191,
    "name:xx": "Dry Lakes Creek"
  }
}
