{
  "type": "FeatureCollection",
  "features": [
    {
      "geometry": {
        "type": "Point",
        "coordinates": [
          -120.5333,
          41.3167
        ]
      },
      "type": "Feature",
      "properties": {
        "hierarchy": [
          "tgn:2012530",
          "tgn:1000001",
          "tgn:7012149",
          "tgn:7007157",
          "tgn:2000186",
          "tgn:7029392"
        ],
        "placetype": [
          "aat:300387016"
        ],
        "id": 2012530,
        "name:xx": "McArthur"
      }
    },
    {
      "geometry": {
        "type": "Point",
        "coordinates": [
          -121.95,
          38.0333
        ]
      },
      "type": "Feature",
      "properties": {
        "hierarchy": [
          "tgn:2012531",
          "tgn:1000001",
          "tgn:7012149",
          "tgn:1002298",
          "tgn:7007157",
          "tgn:7029392"
        ],
        "placetype": [
          "aat:300387016"
        ],
        "id": 2012531,
        "name:xx": "McAvoy"
      }
    },
    {
      "geometry": {
        "type": "Point",
        "coordinates": [
          -123.8333,
          40.3167
        ]
      },
      "type": "Feature",
      "properties": {
        "hierarchy": [
          "tgn:2012532",
          "tgn:1000001",
          "tgn:7012149",
          "tgn:2000181",
          "tgn:7007157",
          "tgn:7029392"
        ],
        "placetype": [
          "aat:300008347",
          "aat:300387210"
        ],
        "id": 2012532,
        "name:xx": "McCann"
      }
    },
    {
      "geometry": {
        "type": "Point",
        "coordinates": [
          -122,
          41.8167
        ]
      },
      "type": "Feature",
      "properties": {
        "hierarchy": [
          "tgn:2012537",
          "tgn:1000001",
          "tgn:7012149",
          "tgn:7007157",
          "tgn:2000189",
          "tgn:7029392"
        ],
        "placetype": [
          "aat:300008347"
        ],
        "id": 2012537,
        "name:xx": "Macdoel"
      }
    },
    {
      "geometry": {
        "type": "Point",
        "coordinates": [
          -119.2167,
          35.6667
        ]
      },
      "type": "Feature",
      "properties": {
        "hierarchy": [
          "tgn:2012538",
          "tgn:1000001",
          "tgn:7012149",
          "tgn:1002545",
          "tgn:7007157",
          "tgn:7029392"
        ],
        "placetype": [
          "aat:300008347"
        ],
        "id": 2012538,
        "name:xx": "McFarland"
      }
    },
    {
      "geometry": {
        "type": "Point",
        "coordinates": [
          -121,
          37.7
        ]
      },
      "type": "Feature",
      "properties": {
        "hierarchy": [
          "tgn:2012539",
          "tgn:1000001",
          "tgn:7012149",
          "tgn:7007157",
          "tgn:1002915",
          "tgn:7029392"
        ],
        "placetype": [
          "aat:300387016"
        ],
        "id": 2012539,
        "name:xx": "McHenry"
      }
    }
  ]
}
