{
  "type": "FeatureCollection",
  "features": [
    {
      "geometry": {
        "type": "Point",
        "coordinates": [
          -164.0333,
          59.9333
        ]
      },
      "type": "Feature",
      "properties": {
        "hierarchy": [
          "tgn:2006181",
          "tgn:7006450",
          "tgn:2000069",
          "tgn:1000001",
          "tgn:7012149",
          "tgn:7029392"
        ],
        "placetype": [
          "aat:300008347"
        ],
        "id": 2006181,
        "name:xx": "Kipnuk"
      }
    },
    {
      "geometry": {
        "type": "Point",
        "coordinates": [
          -152.3333,
          58.1833
        ]
      },
      "type": "Feature",
      "properties": {
        "hierarchy": [
          "tgn:2006182",
          "tgn:7019709",
          "tgn:7006450",
          "tgn:1000001",
          "tgn:2124012",
          "tgn:7012149",
          "tgn:7029392"
        ],
        "placetype": [
          "aat:300387016"
        ],
        "id": 2006182,
        "name:xx": "Kitoi"
      }
    },
    {
      "geometry": {
        "type": "Point",
        "coordinates": [
          -164.5333,
          67.7167
        ]
      },
      "type": "Feature",
      "properties": {
        "hierarchy": [
          "tgn:2006183",
          "tgn:7006450",
          "tgn:1000001",
          "tgn:7012149",
          "tgn:2124014",
          "tgn:7029392"
        ],
        "placetype": [
          "aat:300008347"
        ],
        "id": 2006183,
        "name:xx": "Kivalina"
      }
    },
    {
      "geometry": {
        "type": "Point",
        "coordinates": [
          -136.0833,
          57.6333
        ]
      },
      "type": "Feature",
      "properties": {
        "hierarchy": [
          "tgn:2006184",
          "tgn:7006450",
          "tgn:1000001",
          "tgn:7012149",
          "tgn:2124002",
          "tgn:7029392"
        ],
        "placetype": [
          "aat:300387016"
        ],
        "id": 2006184,
        "name:xx": "Klag Bay"
      }
    },
    {
      "geometry": {
        "type": "Point",
        "coordinates": [
          -156.8667,
          66.9
        ]
      },
      "type": "Feature",
      "properties": {
        "hierarchy": [
          "tgn:2006188",
          "tgn:7006450",
          "tgn:1000001",
          "tgn:7012149",
          "tgn:2124014",
          "tgn:7029392"
        ],
        "placetype": [
          "aat:300008347"
        ],
        "id": 2006188,
        "name:xx": "Kobuk"
      }
    }
  ]
}
