{
  "geometry": {
    "type": "Point",
    "coordinates": [
      2.15,
      14.5333
    ]
  },
  "type": "Feature",
  "properties": {
    "hierarchy": [
      "tgn:1091793",
      "tgn:7001242",
      "tgn:7032820",
      "tgn:1000181",
      "tgn:7029392"
    ],
    "placetype": [
      "aat:300008347"
    ],
    "id": 1091793,
    "name:xx": "Ouallam"
  }
}
