{
  "geometry": {
    "type": "Point",
    "coordinates": [
      -119.95,
      47.7833
    ]
  },
  "type": "Feature",
  "properties": {
    "hierarchy": [
      "tgn:2418101",
      "tgn:1000001",
      "tgn:2002242",
      "tgn:7012149",
      "tgn:7007920",
      "tgn:7029392"
    ],
    "placetype": [
      "aat:300008697"
    ],
    "id": 2418101,
    "name:xx": "Jackson Spring"
  }
}
