{
  "geometry": {
    "type": "Point",
    "coordinates": [
      -44.7833,
      -20.65
    ]
  },
  "type": "Feature",
  "properties": {
    "hierarchy": [
      "tgn:1022263",
      "tgn:7006237",
      "tgn:1000047",
      "tgn:7002457",
      "tgn:1000002",
      "tgn:7029392"
    ],
    "placetype": [
      "aat:300008347"
    ],
    "id": 1022263,
    "name:xx": "Oliveira"
  }
}
