{
  "geometry": {
    "type": "Point",
    "coordinates": [
      -76.3333,
      39.4667
    ]
  },
  "type": "Feature",
  "properties": {
    "hierarchy": [
      "tgn:2139817",
      "tgn:1000001",
      "tgn:7016102",
      "tgn:7012149",
      "tgn:7007516",
      "tgn:7029392"
    ],
    "placetype": [
      "aat:300006191"
    ],
    "id": 2139817,
    "name:xx": "Atkisson Reservoir"
  }
}
