{
  "geometry": {
    "type": "Point",
    "coordinates": [
      -80.0667,
      43.8667
    ]
  },
  "type": "Feature",
  "properties": {
    "hierarchy": [
      "tgn:1014549",
      "tgn:7005685",
      "tgn:1000001",
      "tgn:7013154",
      "tgn:7029392"
    ],
    "placetype": [
      "aat:300008347"
    ],
    "id": 1014549,
    "name:xx": "Alton"
  }
}
