{
  "geometry": {
    "type": "Point",
    "coordinates": [
      -80.7667,
      37.8167
    ]
  },
  "type": "Feature",
  "properties": {
    "hierarchy": [
      "tgn:2418921",
      "tgn:1000001",
      "tgn:7012149",
      "tgn:2002294",
      "tgn:7013961",
      "tgn:7029392"
    ],
    "placetype": [
      "aat:300008697"
    ],
    "id": 2418921,
    "name:xx": "James Harless Spring"
  }
}
