{
  "geometry": {
    "type": "Point",
    "coordinates": [
      -84.5667,
      42.6333
    ]
  },
  "type": "Feature",
  "properties": {
    "hierarchy": [
      "tgn:2505751",
      "tgn:1000001",
      "tgn:7012149",
      "tgn:1002502",
      "tgn:7007520",
      "tgn:7029392"
    ],
    "placetype": [
      "aat:300006075"
    ],
    "id": 2505751,
    "name:xx": "Menger Drain"
  }
}
