{
  "geometry": {
    "type": "Point",
    "coordinates": [
      -99.0333,
      46.9167
    ]
  },
  "type": "Feature",
  "properties": {
    "hierarchy": [
      "tgn:2517152",
      "tgn:1000001",
      "tgn:2001603",
      "tgn:7012149",
      "tgn:7007705",
      "tgn:7029392"
    ],
    "placetype": [
      "aat:300008706"
    ],
    "id": 2517152,
    "name:xx": "Minneapolis Flats Creek"
  }
}
