{
  "geometry": {
    "type": "Point",
    "coordinates": [
      -110.85,
      34.4833
    ]
  },
  "type": "Feature",
  "properties": {
    "hierarchy": [
      "tgn:2467275",
      "tgn:1000001",
      "tgn:7006451",
      "tgn:2000092",
      "tgn:7012149",
      "tgn:7029392"
    ],
    "placetype": [
      "aat:300386845"
    ],
    "id": 2467275,
    "name:xx": "Long Draw Water Catchment"
  }
}
