{
  "geometry": {
    "type": "Point",
    "coordinates": [
      -119.4333,
      34.4667
    ]
  },
  "type": "Feature",
  "properties": {
    "hierarchy": [
      "tgn:2619499",
      "tgn:1000001",
      "tgn:7012149",
      "tgn:7007157",
      "tgn:7029392"
    ],
    "placetype": [
      "aat:300008706"
    ],
    "id": 2619499,
    "name:xx": "Rincon Creek"
  }
}
