{
  "geometry": {
    "type": "Point",
    "coordinates": [
      -100.283333,
      20.65
    ]
  },
  "type": "Feature",
  "properties": {
    "hierarchy": [
      "tgn:7352847",
      "tgn:1000001",
      "tgn:7005593",
      "tgn:7005560",
      "tgn:7029392"
    ],
    "placetype": [
      "aat:300008347"
    ],
    "id": 7352847,
    "name:xx": "Buena Vista"
  }
}
