{
  "geometry": {
    "type": "Point",
    "coordinates": [
      -81.0833,
      36.45
    ]
  },
  "type": "Feature",
  "properties": {
    "hierarchy": [
      "tgn:2350754",
      "tgn:2001465",
      "tgn:1000001",
      "tgn:7012149",
      "tgn:7007709",
      "tgn:7029392"
    ],
    "placetype": [
      "aat:300008706"
    ],
    "id": 2350754,
    "name:xx": "Glade Creek"
  }
}
