{
  "type": "FeatureCollection",
  "features": [
    {
      "geometry": {
        "type": "Point",
        "coordinates": [
          -111.45,
          42
        ]
      },
      "type": "Feature",
      "properties": {
        "hierarchy": [
          "tgn:2607390",
          "tgn:2000455",
          "tgn:1000001",
          "tgn:7012149",
          "tgn:7007250",
          "tgn:7029392"
        ],
        "placetype": [
          "aat:300008680"
        ],
        "id": 2607390,
        "name:xx": "Ranger Dip"
      }
    },
    {
      "geometry": {
        "type": "Point",
        "coordinates": [
          -84.7667,
          43.1833
        ]
      },
      "type": "Feature",
      "properties": {
        "hierarchy": [
          "tgn:2607391",
          "tgn:1000001",
          "tgn:7012149",
          "tgn:2000962",
          "tgn:7007520",
          "tgn:7029392"
        ],
        "placetype": [
          "aat:300006075"
        ],
        "id": 2607391,
        "name:xx": "Ranger Drain"
      }
    },
    {
      "geometry": {
        "type": "Point",
        "coordinates": [
          -110.6167,
          34.3667
        ]
      },
      "type": "Feature",
      "properties": {
        "hierarchy": [
          "tgn:2607392",
          "tgn:1000001",
          "tgn:7006451",
          "tgn:7012149",
          "tgn:2000099",
          "tgn:7029392"
        ],
        "placetype": [
          "aat:300008761"
        ],
        "id": 2607392,
        "name:xx": "Ranger Draw"
      }
    },
    {
      "geometry": {
        "type": "Point",
        "coordinates": [
          -103.9667,
          44.3
        ]
      },
      "type": "Feature",
      "properties": {
        "hierarchy": [
          "tgn:2607393",
          "tgn:1000001",
          "tgn:2001810",
          "tgn:7012149",
          "tgn:7007713",
          "tgn:7029392"
        ],
        "placetype": [
          "aat:300008761"
        ],
        "id": 2607393,
        "name:xx": "Ranger Draw"
      }
    },
    {
      "geometry": {
        "type": "Point",
        "coordinates": [
          -106.1,
          39.8667
        ]
      },
      "type": "Feature",
      "properties": {
        "hierarchy": [
          "tgn:2607394",
          "tgn:1000001",
          "tgn:7012149",
          "tgn:2000216",
          "tgn:7007158",
          "tgn:7029392"
        ],
        "placetype": [
          "aat:300008761"
        ],
        "id": 2607394,
        "name:xx": "Ranger Gulch"
      }
    },
    {
      "geometry": {
        "type": "Point",
        "coordinates": [
          -95.2,
          35.8833
        ]
      },
      "type": "Feature",
      "properties": {
        "hierarchy": [
          "tgn:2607395",
          "tgn:1000001",
          "tgn:2001633",
          "tgn:7012149",
          "tgn:7007707",
          "tgn:7029392"
        ],
        "placetype": [
          "aat:300386831"
        ],
        "id": 2607395,
        "name:xx": "Ranger Hills"
      }
    },
    {
      "geometry": {
        "type": "Point",
        "coordinates": [
          -99.8167,
          29.9833
        ]
      },
      "type": "Feature",
      "properties": {
        "hierarchy": [
          "tgn:2607396",
          "tgn:1000001",
          "tgn:7012149",
          "tgn:2002060",
          "tgn:7007826",
          "tgn:7029392"
        ],
        "placetype": [
          "aat:300008761"
        ],
        "id": 2607396,
        "name:xx": "Ranger Hollow"
      }
    },
    {
      "geometry": {
        "type": "Point",
        "coordinates": [
          -111.5,
          41.4167
        ]
      },
      "type": "Feature",
      "properties": {
        "hierarchy": [
          "tgn:2607397",
          "tgn:1000001",
          "tgn:7012149",
          "tgn:2002117",
          "tgn:7007827",
          "tgn:7029392"
        ],
        "placetype": [
          "aat:300008761"
        ],
        "id": 2607397,
        "name:xx": "Ranger Hollow"
      }
    },
    {
      "geometry": {
        "type": "Point",
        "coordinates": [
          -73.6,
          43.5667
        ]
      },
      "type": "Feature",
      "properties": {
        "hierarchy": [
          "tgn:2607398",
          "tgn:1000001",
          "tgn:7012149",
          "tgn:1002986",
          "tgn:7007568",
          "tgn:7029392"
        ],
        "placetype": [
          "aat:300008791"
        ],
        "id": 2607398,
        "name:xx": "Ranger Island"
      }
    },
    {
      "geometry": {
        "type": "Point",
        "coordinates": [
          -118.6833,
          36.65
        ]
      },
      "type": "Feature",
      "properties": {
        "hierarchy": [
          "tgn:2607399",
          "tgn:1000001",
          "tgn:7012149",
          "tgn:7007157",
          "tgn:1002956",
          "tgn:7029392"
        ],
        "placetype": [
          "aat:300008680"
        ],
        "id": 2607399,
        "name:xx": "Ranger Lake"
      }
    }
  ]
}
