{
  "geometry": {
    "type": "Point",
    "coordinates": [
      55.65,
      -20.9166
    ]
  },
  "type": "Feature",
  "properties": {
    "hierarchy": [
      "tgn:7032276",
      "tgn:7001680",
      "tgn:7001242",
      "tgn:1000184",
      "tgn:7029392"
    ],
    "placetype": [
      "aat:300008347"
    ],
    "name:fr": "Cambuston",
    "id": 7032276
  }
}
