{
  "geometry": {
    "type": "Point",
    "coordinates": [
      74.841667,
      32.675
    ]
  },
  "type": "Feature",
  "properties": {
    "hierarchy": [
      "tgn:7591788",
      "tgn:1000004",
      "tgn:7000198",
      "tgn:7000799",
      "tgn:7029392"
    ],
    "placetype": [
      "aat:300008347"
    ],
    "name:en": "Sikligar Kaliān",
    "id": 7591788
  }
}
