{
  "geometry": {
    "type": "Point",
    "coordinates": [
      101.8667,
      58.9667
    ]
  },
  "type": "Feature",
  "properties": {
    "hierarchy": [
      "tgn:1058194",
      "tgn:1000004",
      "tgn:1003314",
      "tgn:7018214",
      "tgn:7002435",
      "tgn:7029392"
    ],
    "placetype": [
      "aat:300008347"
    ],
    "id": 1058194,
    "name:xx": "Panovo"
  }
}
