{
  "geometry": {
    "type": "Point",
    "coordinates": [
      7.6333,
      51.3667
    ]
  },
  "type": "Feature",
  "properties": {
    "hierarchy": [
      "tgn:1040616",
      "tgn:1000003",
      "tgn:7003677",
      "tgn:7000084",
      "tgn:7029392"
    ],
    "placetype": [
      "aat:300008347"
    ],
    "id": 1040616,
    "name:xx": "Oestrich"
  }
}
