{
  "geometry": {
    "type": "Point",
    "coordinates": [
      -115.8167,
      46.3333
    ]
  },
  "type": "Feature",
  "properties": {
    "hierarchy": [
      "tgn:2199266",
      "tgn:1000001",
      "tgn:2000469",
      "tgn:7012149",
      "tgn:7007250",
      "tgn:7029392"
    ],
    "placetype": [
      "aat:300008706"
    ],
    "id": 2199266,
    "name:xx": "Brunt Creek"
  }
}
