{
  "geometry": {
    "type": "Point",
    "coordinates": [
      -92.1833,
      38.55
    ]
  },
  "type": "Feature",
  "properties": {
    "hierarchy": [
      "tgn:2704822",
      "tgn:1000001",
      "tgn:7012149",
      "tgn:1002288",
      "tgn:7007523",
      "tgn:7029392"
    ],
    "placetype": [
      "aat:300006191"
    ],
    "id": 2704822,
    "name:xx": "Sunset Lake"
  }
}
