{
  "geometry": {
    "type": "Point",
    "coordinates": [
      -77.8333,
      55.3333
    ]
  },
  "type": "Feature",
  "properties": {
    "hierarchy": [
      "tgn:1015570",
      "tgn:7005685",
      "tgn:1000001",
      "tgn:7005804",
      "tgn:7029392"
    ],
    "placetype": [
      "aat:300008347"
    ],
    "id": 1015570,
    "name:xx": "Poste-de-la-Baleine"
  }
}
