{
  "geometry": {
    "type": "Point",
    "coordinates": [
      -116.7333,
      45.0833
    ]
  },
  "type": "Feature",
  "properties": {
    "hierarchy": [
      "tgn:2449164",
      "tgn:2000453",
      "tgn:1000001",
      "tgn:7012149",
      "tgn:7007250",
      "tgn:7029392"
    ],
    "placetype": [
      "aat:300008706"
    ],
    "id": 2449164,
    "name:xx": "Limepoint Creek"
  }
}
