{
  "geometry": {
    "type": "Point",
    "coordinates": [
      -108.8167,
      46.9667
    ]
  },
  "type": "Feature",
  "properties": {
    "hierarchy": [
      "tgn:2546113",
      "tgn:1000001",
      "tgn:7012149",
      "tgn:2001273",
      "tgn:7007524",
      "tgn:7029392"
    ],
    "placetype": [
      "aat:300008706"
    ],
    "id": 2546113,
    "name:xx": "North Fork Elk Creek"
  }
}
