{
  "geometry": {
    "type": "Point",
    "coordinates": [
      26.55,
      64.5333
    ]
  },
  "type": "Feature",
  "properties": {
    "hierarchy": [
      "tgn:7010073",
      "tgn:1001475",
      "tgn:1000003",
      "tgn:1000069",
      "tgn:7029392"
    ],
    "placetype": [
      "aat:300008189"
    ],
    "id": 7010073,
    "name:xx": "Rokuan kansallispuisto"
  }
}
