{
  "geometry": {
    "type": "Point",
    "coordinates": [
      -94.8333,
      37.8667
    ]
  },
  "type": "Feature",
  "properties": {
    "hierarchy": [
      "tgn:2228325",
      "tgn:2000665",
      "tgn:1000001",
      "tgn:7012149",
      "tgn:7007254",
      "tgn:7029392"
    ],
    "placetype": [
      "aat:300008706"
    ],
    "id": 2228325,
    "name:xx": "Cedar Creek"
  }
}
