{
  "geometry": {
    "type": "Point",
    "coordinates": [
      67.8167,
      38.0167
    ]
  },
  "type": "Feature",
  "properties": {
    "hierarchy": [
      "tgn:1051747",
      "tgn:1000004",
      "tgn:7012261",
      "tgn:7006661",
      "tgn:7029392"
    ],
    "placetype": [
      "aat:300008347"
    ],
    "id": 1051747,
    "name:xx": "Shurchi"
  }
}
