{
  "geometry": {
    "type": "Point",
    "coordinates": [
      -93.7667,
      35.5333
    ]
  },
  "type": "Feature",
  "properties": {
    "hierarchy": [
      "tgn:2705737",
      "tgn:1000001",
      "tgn:7016172",
      "tgn:7012149",
      "tgn:2000128",
      "tgn:7029392"
    ],
    "placetype": [
      "aat:300008347"
    ],
    "id": 2705737,
    "name:xx": "Sutherland Crossroads"
  }
}
