{
  "geometry": {
    "type": "Point",
    "coordinates": [
      -75.2667,
      42.1167
    ]
  },
  "type": "Feature",
  "properties": {
    "hierarchy": [
      "tgn:2240576",
      "tgn:1000001",
      "tgn:1002328",
      "tgn:7012149",
      "tgn:7007568",
      "tgn:7029392"
    ],
    "placetype": [
      "aat:300008798"
    ],
    "id": 2240576,
    "name:xx": "Clabber Peak"
  }
}
