{
  "geometry": {
    "type": "Point",
    "coordinates": [
      73.75,
      24.783333
    ]
  },
  "type": "Feature",
  "properties": {
    "hierarchy": [
      "tgn:7551973",
      "tgn:1000004",
      "tgn:7000198",
      "tgn:7016788",
      "tgn:7029392"
    ],
    "placetype": [
      "aat:300008347"
    ],
    "name:en": "Delwāra",
    "id": 7551973
  }
}
