{
  "geometry": {
    "type": "Point",
    "coordinates": [
      -78.05,
      38.8833
    ]
  },
  "type": "Feature",
  "properties": {
    "hierarchy": [
      "tgn:2628175",
      "tgn:1000001",
      "tgn:7012149",
      "tgn:1002368",
      "tgn:7007919",
      "tgn:7029392"
    ],
    "placetype": [
      "aat:300008761"
    ],
    "id": 2628175,
    "name:xx": "Rolls Hollow"
  }
}
