{
  "geometry": {
    "type": "Point",
    "coordinates": [
      -80.9833,
      34.0167
    ]
  },
  "type": "Feature",
  "properties": {
    "hierarchy": [
      "tgn:2574632",
      "tgn:1000001",
      "tgn:7012149",
      "tgn:2001764",
      "tgn:7007712",
      "tgn:7029392"
    ],
    "placetype": [
      "aat:300008699"
    ],
    "id": 2574632,
    "name:xx": "Pen Branch"
  }
}
