{
  "geometry": {
    "type": "Point",
    "coordinates": [
      31.5667,
      39.45
    ]
  },
  "type": "Feature",
  "properties": {
    "hierarchy": [
      "tgn:1086829",
      "tgn:1001242",
      "tgn:1000004",
      "tgn:7018453",
      "tgn:1000144",
      "tgn:7029392"
    ],
    "placetype": [
      "aat:300008347"
    ],
    "id": 1086829,
    "name:xx": "Sivrihisar"
  }
}
