{
  "geometry": {
    "type": "Point",
    "coordinates": [
      -80.3667,
      41.9667
    ]
  },
  "type": "Feature",
  "properties": {
    "hierarchy": [
      "tgn:2268620",
      "tgn:1000001",
      "tgn:7012149",
      "tgn:1002358",
      "tgn:7007710",
      "tgn:7029392"
    ],
    "placetype": [
      "aat:300008347"
    ],
    "id": 2268620,
    "name:xx": "Cross"
  }
}
