{
  "type": "FeatureCollection",
  "features": [
    {
      "geometry": {
        "type": "Point",
        "coordinates": [
          -84.95,
          30.8
        ]
      },
      "type": "Feature",
      "properties": {
        "hierarchy": [
          "tgn:2641860",
          "tgn:1000001",
          "tgn:2000273",
          "tgn:7012149",
          "tgn:7007240",
          "tgn:7029392"
        ],
        "placetype": [
          "aat:300008680"
        ],
        "id": 2641860,
        "name:xx": "Sand Lake"
      }
    },
    {
      "geometry": {
        "type": "Point",
        "coordinates": [
          -85.6333,
          30.4667
        ]
      },
      "type": "Feature",
      "properties": {
        "hierarchy": [
          "tgn:2641861",
          "tgn:1000001",
          "tgn:7012149",
          "tgn:2000291",
          "tgn:7007240",
          "tgn:7029392"
        ],
        "placetype": [
          "aat:300008680"
        ],
        "id": 2641861,
        "name:xx": "Sand Lake"
      }
    },
    {
      "geometry": {
        "type": "Point",
        "coordinates": [
          -82.1667,
          30.9
        ]
      },
      "type": "Feature",
      "properties": {
        "hierarchy": [
          "tgn:2641862",
          "tgn:1000001",
          "tgn:2000315",
          "tgn:7012149",
          "tgn:7007248",
          "tgn:7029392"
        ],
        "placetype": [
          "aat:300008680"
        ],
        "id": 2641862,
        "name:xx": "Sand Lake"
      }
    },
    {
      "geometry": {
        "type": "Point",
        "coordinates": [
          -114.0833,
          42.8667
        ]
      },
      "type": "Feature",
      "properties": {
        "hierarchy": [
          "tgn:2641863",
          "tgn:1000001",
          "tgn:7012149",
          "tgn:2000483",
          "tgn:7007250",
          "tgn:7029392"
        ],
        "placetype": [
          "aat:300008680"
        ],
        "id": 2641863,
        "name:xx": "Sand Lake"
      }
    },
    {
      "geometry": {
        "type": "Point",
        "coordinates": [
          -116.3833,
          48.5
        ]
      },
      "type": "Feature",
      "properties": {
        "hierarchy": [
          "tgn:2641864",
          "tgn:1000001",
          "tgn:7012149",
          "tgn:7007250",
          "tgn:7029392"
        ],
        "placetype": [
          "aat:300008680"
        ],
        "id": 2641864,
        "name:xx": "Sand Lake"
      }
    },
    {
      "geometry": {
        "type": "Point",
        "coordinates": [
          -91.4,
          39.8333
        ]
      },
      "type": "Feature",
      "properties": {
        "hierarchy": [
          "tgn:2641865",
          "tgn:1002134",
          "tgn:1000001",
          "tgn:7012149",
          "tgn:7007251",
          "tgn:7029392"
        ],
        "placetype": [
          "aat:300008680"
        ],
        "id": 2641865,
        "name:xx": "Sand Lake"
      }
    },
    {
      "geometry": {
        "type": "Point",
        "coordinates": [
          -88.0333,
          42.4
        ]
      },
      "type": "Feature",
      "properties": {
        "hierarchy": [
          "tgn:2641866",
          "tgn:1000001",
          "tgn:7012149",
          "tgn:7013855",
          "tgn:7007251",
          "tgn:7029392"
        ],
        "placetype": [
          "aat:300008680"
        ],
        "id": 2641866,
        "name:xx": "Sand Lake"
      }
    },
    {
      "geometry": {
        "type": "Point",
        "coordinates": [
          -85.3833,
          41.3167
        ]
      },
      "type": "Feature",
      "properties": {
        "hierarchy": [
          "tgn:2641867",
          "tgn:1000001",
          "tgn:7012149",
          "tgn:1002723",
          "tgn:7007252",
          "tgn:7029392"
        ],
        "placetype": [
          "aat:300008680"
        ],
        "id": 2641867,
        "name:xx": "Sand Lake"
      }
    },
    {
      "geometry": {
        "type": "Point",
        "coordinates": [
          -96.55,
          39.1667
        ]
      },
      "type": "Feature",
      "properties": {
        "hierarchy": [
          "tgn:2641868",
          "tgn:1000001",
          "tgn:7012149",
          "tgn:2000740",
          "tgn:7007254",
          "tgn:7029392"
        ],
        "placetype": [
          "aat:300008680"
        ],
        "id": 2641868,
        "name:xx": "Sand Lake"
      }
    },
    {
      "geometry": {
        "type": "Point",
        "coordinates": [
          -93.5833,
          30.7667
        ]
      },
      "type": "Feature",
      "properties": {
        "hierarchy": [
          "tgn:2641869",
          "tgn:1000001",
          "tgn:2000859",
          "tgn:7012149",
          "tgn:7007256",
          "tgn:7029392"
        ],
        "placetype": [
          "aat:300008680"
        ],
        "id": 2641869,
        "name:xx": "Sand Lake"
      }
    }
  ]
}
