{
  "type": "FeatureCollection",
  "features": [
    {
      "geometry": {
        "type": "Point",
        "coordinates": [
          -85.0833,
          32.4
        ]
      },
      "type": "Feature",
      "properties": {
        "hierarchy": [
          "tgn:2189790",
          "tgn:7002659",
          "tgn:1000001",
          "tgn:7012149",
          "tgn:2000056",
          "tgn:7029392"
        ],
        "placetype": [
          "aat:300006191"
        ],
        "id": 2189790,
        "name:xx": "Bowers Lake"
      }
    },
    {
      "geometry": {
        "type": "Point",
        "coordinates": [
          -81.95,
          29.0333
        ]
      },
      "type": "Feature",
      "properties": {
        "hierarchy": [
          "tgn:2189791",
          "tgn:1000001",
          "tgn:7012149",
          "tgn:1002631",
          "tgn:7007240",
          "tgn:7029392"
        ],
        "placetype": [
          "aat:300008680"
        ],
        "id": 2189791,
        "name:xx": "Bowers Lake"
      }
    },
    {
      "geometry": {
        "type": "Point",
        "coordinates": [
          -82.5667,
          38.45
        ]
      },
      "type": "Feature",
      "properties": {
        "hierarchy": [
          "tgn:2189792",
          "tgn:1000001",
          "tgn:7012149",
          "tgn:2001615",
          "tgn:7007706",
          "tgn:7029392"
        ],
        "placetype": [
          "aat:300006191"
        ],
        "id": 2189792,
        "name:xx": "Bowers Lake"
      }
    },
    {
      "geometry": {
        "type": "Point",
        "coordinates": [
          -96.75,
          30.5667
        ]
      },
      "type": "Feature",
      "properties": {
        "hierarchy": [
          "tgn:2189793",
          "tgn:1000001",
          "tgn:7012149",
          "tgn:1002214",
          "tgn:7007826",
          "tgn:7029392"
        ],
        "placetype": [
          "aat:300006191"
        ],
        "id": 2189793,
        "name:xx": "Bowers Lake"
      }
    },
    {
      "geometry": {
        "type": "Point",
        "coordinates": [
          -119.7,
          48.9167
        ]
      },
      "type": "Feature",
      "properties": {
        "hierarchy": [
          "tgn:2189794",
          "tgn:1000001",
          "tgn:7012149",
          "tgn:1002742",
          "tgn:7007920",
          "tgn:7029392"
        ],
        "placetype": [
          "aat:300008680"
        ],
        "id": 2189794,
        "name:xx": "Bowers Lake"
      }
    },
    {
      "geometry": {
        "type": "Point",
        "coordinates": [
          -121.8667,
          48.1
        ]
      },
      "type": "Feature",
      "properties": {
        "hierarchy": [
          "tgn:2189795",
          "tgn:1000001",
          "tgn:7012149",
          "tgn:1002899",
          "tgn:7007920",
          "tgn:7029392"
        ],
        "placetype": [
          "aat:300008680"
        ],
        "id": 2189795,
        "name:xx": "Bowers Lake"
      }
    },
    {
      "geometry": {
        "type": "Point",
        "coordinates": [
          -88.9167,
          42.7833
        ]
      },
      "type": "Feature",
      "properties": {
        "hierarchy": [
          "tgn:2189796",
          "tgn:1000001",
          "tgn:7012149",
          "tgn:7014350",
          "tgn:7007922",
          "tgn:7029392"
        ],
        "placetype": [
          "aat:300008905"
        ],
        "id": 2189796,
        "name:xx": "Bowers Lake"
      }
    },
    {
      "geometry": {
        "type": "Point",
        "coordinates": [
          -107.05,
          38.1167
        ]
      },
      "type": "Feature",
      "properties": {
        "hierarchy": [
          "tgn:2189797",
          "tgn:1000001",
          "tgn:7012149",
          "tgn:2000218",
          "tgn:7007158",
          "tgn:7029392"
        ],
        "placetype": [
          "aat:300006191"
        ],
        "id": 2189797,
        "name:xx": "Bowers Lakes"
      }
    },
    {
      "geometry": {
        "type": "Point",
        "coordinates": [
          -119.8333,
          39.2833
        ]
      },
      "type": "Feature",
      "properties": {
        "hierarchy": [
          "tgn:2189798",
          "tgn:1000001",
          "tgn:7012149",
          "tgn:1002999",
          "tgn:7007526",
          "tgn:7029392"
        ],
        "placetype": [
          "aat:300008697"
        ],
        "id": 2189798,
        "name:xx": "Bowers Mansion Hot Spring"
      }
    },
    {
      "geometry": {
        "type": "Point",
        "coordinates": [
          -82.1167,
          36.35
        ]
      },
      "type": "Feature",
      "properties": {
        "hierarchy": [
          "tgn:2189799",
          "tgn:1000001",
          "tgn:7012149",
          "tgn:2001846",
          "tgn:7007825",
          "tgn:7029392"
        ],
        "placetype": [
          "aat:300000390"
        ],
        "id": 2189799,
        "name:xx": "Bowers Mine"
      }
    }
  ]
}
