{
  "geometry": {
    "type": "Point",
    "coordinates": [
      -92.45,
      35.8333
    ]
  },
  "type": "Feature",
  "properties": {
    "hierarchy": [
      "tgn:2009153",
      "tgn:1000001",
      "tgn:7016172",
      "tgn:7012149",
      "tgn:2000169",
      "tgn:7029392"
    ],
    "placetype": [
      "aat:300008347",
      "aat:300387210"
    ],
    "id": 2009153,
    "name:xx": "Oxley"
  }
}
