{
  "geometry": {
    "type": "Point",
    "coordinates": [
      -80.8833,
      38.05
    ]
  },
  "type": "Feature",
  "properties": {
    "hierarchy": [
      "tgn:2165333",
      "tgn:1000001",
      "tgn:2002261",
      "tgn:7012149",
      "tgn:7013961",
      "tgn:7029392"
    ],
    "placetype": [
      "aat:300008798"
    ],
    "id": 2165333,
    "name:xx": "Betty Bell Knob"
  }
}
