{
  "geometry": {
    "type": "Point",
    "coordinates": [
      -110.9667,
      33.3333
    ]
  },
  "type": "Feature",
  "properties": {
    "hierarchy": [
      "tgn:2413885",
      "tgn:1000001",
      "tgn:7006451",
      "tgn:7012149",
      "tgn:2000101",
      "tgn:7029392"
    ],
    "placetype": [
      "aat:300008761"
    ],
    "id": 2413885,
    "name:xx": "Iron Canyon"
  }
}
