{
  "geometry": {
    "type": "Point",
    "coordinates": [
      -96.2333,
      38.2833
    ]
  },
  "type": "Feature",
  "properties": {
    "hierarchy": [
      "tgn:2245721",
      "tgn:1000001",
      "tgn:7012149",
      "tgn:2000715",
      "tgn:7007254",
      "tgn:7029392"
    ],
    "placetype": [
      "aat:300008706"
    ],
    "id": 2245721,
    "name:xx": "Coal Creek"
  }
}
