{
  "geometry": {
    "type": "Point",
    "coordinates": [
      -121.0667,
      42.0833
    ]
  },
  "type": "Feature",
  "properties": {
    "hierarchy": [
      "tgn:2685547",
      "tgn:1000001",
      "tgn:7012149",
      "tgn:2001714",
      "tgn:7007708",
      "tgn:7029392"
    ],
    "placetype": [
      "aat:300006191"
    ],
    "id": 2685547,
    "name:xx": "Spreader Reservoir"
  }
}
