{
  "geometry": {
    "type": "Point",
    "coordinates": [
      15.0167,
      -1.9167
    ]
  },
  "type": "Feature",
  "properties": {
    "hierarchy": [
      "tgn:1088696",
      "tgn:7001242",
      "tgn:1001022",
      "tgn:1000158",
      "tgn:7029392"
    ],
    "placetype": [
      "aat:300008347"
    ],
    "id": 1088696,
    "name:xx": "Mingo"
  }
}
