{
  "geometry": {
    "type": "Point",
    "coordinates": [
      -123.5167,
      39.3833
    ]
  },
  "type": "Feature",
  "properties": {
    "hierarchy": [
      "tgn:2231733",
      "tgn:1000001",
      "tgn:7012149",
      "tgn:7007157",
      "tgn:2000185",
      "tgn:7029392"
    ],
    "placetype": [
      "aat:300008706"
    ],
    "id": 2231733,
    "name:xx": "Chamberlain Creek"
  }
}
