{
  "geometry": {
    "type": "Point",
    "coordinates": [
      -110.95,
      31.95
    ]
  },
  "type": "Feature",
  "properties": {
    "hierarchy": [
      "tgn:2007272",
      "tgn:1000001",
      "tgn:7006451",
      "tgn:7012149",
      "tgn:2000100",
      "tgn:7029392"
    ],
    "placetype": [
      "aat:300008347"
    ],
    "id": 2007272,
    "name:xx": "Sahuarita"
  }
}
