{
  "geometry": {
    "type": "Point",
    "coordinates": [
      -77.3333,
      42.9667
    ]
  },
  "type": "Feature",
  "properties": {
    "hierarchy": [
      "tgn:2175732",
      "tgn:1000001",
      "tgn:7012149",
      "tgn:1002747",
      "tgn:7007568",
      "tgn:7029392"
    ],
    "placetype": [
      "aat:300008706"
    ],
    "id": 2175732,
    "name:xx": "Black Creek"
  }
}
