{
  "geometry": {
    "type": "Point",
    "coordinates": [
      -153.35,
      59.8667
    ]
  },
  "type": "Feature",
  "properties": {
    "hierarchy": [
      "tgn:2237679",
      "tgn:7006450",
      "tgn:1000001",
      "tgn:7019698",
      "tgn:7012149",
      "tgn:7029392"
    ],
    "placetype": [
      "aat:300008707"
    ],
    "id": 2237679,
    "name:xx": "Chinitna River"
  }
}
