{
  "geometry": {
    "type": "Point",
    "coordinates": [
      -68.3167,
      44.45
    ]
  },
  "type": "Feature",
  "properties": {
    "hierarchy": [
      "tgn:2044745",
      "tgn:1000001",
      "tgn:2000922",
      "tgn:7012149",
      "tgn:7007515",
      "tgn:7029392"
    ],
    "placetype": [
      "aat:300008347"
    ],
    "id": 2044745,
    "name:xx": "East Lamoine"
  }
}
