{
  "geometry": {
    "type": "Point",
    "coordinates": [
      -87.1833,
      31.7333
    ]
  },
  "type": "Feature",
  "properties": {
    "hierarchy": [
      "tgn:2692953",
      "tgn:7002659",
      "tgn:1000001",
      "tgn:7012149",
      "tgn:2000049",
      "tgn:7029392"
    ],
    "placetype": [
      "aat:300006191"
    ],
    "id": 2692953,
    "name:xx": "Steels Lake"
  }
}
