{
  "geometry": {
    "type": "Point",
    "coordinates": [
      -86.55,
      38.0167
    ]
  },
  "type": "Feature",
  "properties": {
    "hierarchy": [
      "tgn:2376462",
      "tgn:1000001",
      "tgn:7012149",
      "tgn:2000550",
      "tgn:7007252",
      "tgn:7029392"
    ],
    "placetype": [
      "aat:300006191"
    ],
    "id": 2376462,
    "name:xx": "Harding Pond"
  }
}
