{
  "geometry": {
    "type": "Point",
    "coordinates": [
      -111.0667,
      39.0167
    ]
  },
  "type": "Feature",
  "properties": {
    "hierarchy": [
      "tgn:2656339",
      "tgn:1000001",
      "tgn:2002108",
      "tgn:7012149",
      "tgn:7007827",
      "tgn:7029392"
    ],
    "placetype": [
      "aat:300008761"
    ],
    "id": 2656339,
    "name:xx": "Shearing Corral Draw"
  }
}
