{
  "geometry": {
    "type": "Point",
    "coordinates": [
      -54.5667,
      48.9667
    ]
  },
  "type": "Feature",
  "properties": {
    "hierarchy": [
      "tgn:1014209",
      "tgn:7005685",
      "tgn:7005807",
      "tgn:1000001",
      "tgn:7005801",
      "tgn:7029392"
    ],
    "placetype": [
      "aat:300008347"
    ],
    "id": 1014209,
    "name:xx": "Gander"
  }
}
