{
  "type": "FeatureCollection",
  "features": [
    {
      "geometry": {
        "type": "Point",
        "coordinates": [
          -106.05,
          26.716667
        ]
      },
      "type": "Feature",
      "properties": {
        "hierarchy": [
          "tgn:7375760",
          "tgn:7005583",
          "tgn:1000001",
          "tgn:7005560",
          "tgn:7029392"
        ],
        "placetype": [
          "aat:300007783"
        ],
        "id": 7375760,
        "name:xx": "Llano Blanco"
      }
    },
    {
      "geometry": {
        "type": "Point",
        "coordinates": [
          -111.833333,
          30.616667
        ]
      },
      "type": "Feature",
      "properties": {
        "hierarchy": [
          "tgn:7375761",
          "tgn:1000001",
          "tgn:1001960",
          "tgn:7005560",
          "tgn:7029392"
        ],
        "placetype": [
          "aat:300008347"
        ],
        "id": 7375761,
        "name:xx": "Llano Blanco"
      }
    },
    {
      "geometry": {
        "type": "Point",
        "coordinates": [
          -99.683333,
          26.716667
        ]
      },
      "type": "Feature",
      "properties": {
        "hierarchy": [
          "tgn:7375762",
          "tgn:1000001",
          "tgn:7005589",
          "tgn:7005560",
          "tgn:7029392"
        ],
        "placetype": [
          "aat:300008347"
        ],
        "id": 7375762,
        "name:xx": "Llano Blanco"
      }
    },
    {
      "geometry": {
        "type": "Point",
        "coordinates": [
          -106.883333,
          26.05
        ]
      },
      "type": "Feature",
      "properties": {
        "hierarchy": [
          "tgn:7375763",
          "tgn:7005581",
          "tgn:1000001",
          "tgn:7005560",
          "tgn:7029392"
        ],
        "placetype": [
          "aat:300008347"
        ],
        "id": 7375763,
        "name:xx": "Llano Blanco"
      }
    },
    {
      "geometry": {
        "type": "Point",
        "coordinates": [
          -98.866667,
          25.983333
        ]
      },
      "type": "Feature",
      "properties": {
        "hierarchy": [
          "tgn:7375764",
          "tgn:1000001",
          "tgn:7005597",
          "tgn:7005560",
          "tgn:7029392"
        ],
        "placetype": [
          "aat:300008347"
        ],
        "id": 7375764,
        "name:xx": "Llano Blanco"
      }
    },
    {
      "geometry": {
        "type": "Point",
        "coordinates": [
          -105.633333,
          25.683333
        ]
      },
      "type": "Feature",
      "properties": {
        "hierarchy": [
          "tgn:7375765",
          "tgn:7005583",
          "tgn:1000001",
          "tgn:7005560",
          "tgn:7029392"
        ],
        "placetype": [
          "aat:300008347"
        ],
        "id": 7375765,
        "name:xx": "Llano Blanco"
      }
    },
    {
      "geometry": {
        "type": "Point",
        "coordinates": [
          -95.05,
          16.816667
        ]
      },
      "type": "Feature",
      "properties": {
        "hierarchy": [
          "tgn:7375766",
          "tgn:1000001",
          "tgn:7005591",
          "tgn:7005560",
          "tgn:7029392"
        ],
        "placetype": [
          "aat:300008347"
        ],
        "id": 7375766,
        "name:xx": "Llano Barro"
      }
    },
    {
      "geometry": {
        "type": "Point",
        "coordinates": [
          -101.783333,
          25.333333
        ]
      },
      "type": "Feature",
      "properties": {
        "hierarchy": [
          "tgn:7375767",
          "tgn:1001853",
          "tgn:1000001",
          "tgn:7005560",
          "tgn:7029392"
        ],
        "placetype": [
          "aat:300008811"
        ],
        "id": 7375767,
        "name:xx": "Llano, Mesa del"
      }
    },
    {
      "geometry": {
        "type": "Point",
        "coordinates": [
          -111.1,
          30.366667
        ]
      },
      "type": "Feature",
      "properties": {
        "hierarchy": [
          "tgn:7375768",
          "tgn:1000001",
          "tgn:1001960",
          "tgn:7005560",
          "tgn:7029392"
        ],
        "placetype": [
          "aat:300007783"
        ],
        "id": 7375768,
        "name:xx": "Llano"
      }
    },
    {
      "geometry": {
        "type": "Point",
        "coordinates": [
          -106.766667,
          28.466667
        ]
      },
      "type": "Feature",
      "properties": {
        "hierarchy": [
          "tgn:7375769",
          "tgn:7005581",
          "tgn:1000001",
          "tgn:7005560",
          "tgn:7029392"
        ],
        "placetype": [
          "aat:300007783"
        ],
        "id": 7375769,
        "name:xx": "Llano"
      }
    }
  ]
}
