{
  "geometry": {
    "type": "Point",
    "coordinates": [
      -82.6167,
      35.95
    ]
  },
  "type": "Feature",
  "properties": {
    "hierarchy": [
      "tgn:2370533",
      "tgn:1000001",
      "tgn:7012149",
      "tgn:2001516",
      "tgn:7007709",
      "tgn:7029392"
    ],
    "placetype": [
      "aat:300008798"
    ],
    "id": 2370533,
    "name:xx": "Hack Knob"
  }
}
