{
  "type": "FeatureCollection",
  "features": [
    {
      "geometry": {
        "type": "Point",
        "coordinates": [
          -92.8,
          29.6833
        ]
      },
      "type": "Feature",
      "properties": {
        "hierarchy": [
          "tgn:2598510",
          "tgn:1000001",
          "tgn:7020676",
          "tgn:7012149",
          "tgn:7007256",
          "tgn:7029392"
        ],
        "placetype": [
          "aat:300008680"
        ],
        "id": 2598510,
        "name:xx": "Price Lake"
      }
    },
    {
      "geometry": {
        "type": "Point",
        "coordinates": [
          -84.2833,
          42.2
        ]
      },
      "type": "Feature",
      "properties": {
        "hierarchy": [
          "tgn:2598511",
          "tgn:1000001",
          "tgn:7012149",
          "tgn:1002509",
          "tgn:7007520",
          "tgn:7029392"
        ],
        "placetype": [
          "aat:300008680"
        ],
        "id": 2598511,
        "name:xx": "Price Lake"
      }
    },
    {
      "geometry": {
        "type": "Point",
        "coordinates": [
          -85.1667,
          44.6167
        ]
      },
      "type": "Feature",
      "properties": {
        "hierarchy": [
          "tgn:2598512",
          "tgn:1000001",
          "tgn:7012149",
          "tgn:2000968",
          "tgn:7007520",
          "tgn:7029392"
        ],
        "placetype": [
          "aat:300008680"
        ],
        "id": 2598512,
        "name:xx": "Price Lake"
      }
    },
    {
      "geometry": {
        "type": "Point",
        "coordinates": [
          -81.7167,
          36.1333
        ]
      },
      "type": "Feature",
      "properties": {
        "hierarchy": [
          "tgn:2598513",
          "tgn:1000001",
          "tgn:7012149",
          "tgn:2001551",
          "tgn:7007709",
          "tgn:7029392"
        ],
        "placetype": [
          "aat:300006191"
        ],
        "id": 2598513,
        "name:xx": "Price Lake"
      }
    },
    {
      "geometry": {
        "type": "Point",
        "coordinates": [
          -87.0833,
          36.05
        ]
      },
      "type": "Feature",
      "properties": {
        "hierarchy": [
          "tgn:2598514",
          "tgn:1000001",
          "tgn:7012149",
          "tgn:2001847",
          "tgn:7007825",
          "tgn:7029392"
        ],
        "placetype": [
          "aat:300006191"
        ],
        "id": 2598514,
        "name:xx": "Price Lake"
      }
    },
    {
      "geometry": {
        "type": "Point",
        "coordinates": [
          -121.6,
          48.85
        ]
      },
      "type": "Feature",
      "properties": {
        "hierarchy": [
          "tgn:2598515",
          "tgn:1000001",
          "tgn:7012149",
          "tgn:1003020",
          "tgn:7007920",
          "tgn:7029392"
        ],
        "placetype": [
          "aat:300008680"
        ],
        "id": 2598515,
        "name:xx": "Price Lake"
      }
    },
    {
      "geometry": {
        "type": "Point",
        "coordinates": [
          -123.1667,
          47.4667
        ]
      },
      "type": "Feature",
      "properties": {
        "hierarchy": [
          "tgn:2598516",
          "tgn:1000001",
          "tgn:7012149",
          "tgn:1002645",
          "tgn:7007920",
          "tgn:7029392"
        ],
        "placetype": [
          "aat:300008680"
        ],
        "id": 2598516,
        "name:xx": "Price Lake"
      }
    },
    {
      "geometry": {
        "type": "Point",
        "coordinates": [
          -121.4167,
          47.5
        ]
      },
      "type": "Feature",
      "properties": {
        "hierarchy": [
          "tgn:2598517",
          "tgn:1000001",
          "tgn:7012149",
          "tgn:7018871",
          "tgn:7007920",
          "tgn:7029392"
        ],
        "placetype": [
          "aat:300008680"
        ],
        "id": 2598517,
        "name:xx": "Price Lake"
      }
    },
    {
      "geometry": {
        "type": "Point",
        "coordinates": [
          -90.65,
          45.75
        ]
      },
      "type": "Feature",
      "properties": {
        "hierarchy": [
          "tgn:2598518",
          "tgn:1000001",
          "tgn:7012149",
          "tgn:2002348",
          "tgn:7007922",
          "tgn:7029392"
        ],
        "placetype": [
          "aat:300008680"
        ],
        "id": 2598518,
        "name:xx": "Price Lake"
      }
    },
    {
      "geometry": {
        "type": "Point",
        "coordinates": [
          -88.3833,
          45.85
        ]
      },
      "type": "Feature",
      "properties": {
        "hierarchy": [
          "tgn:2598519",
          "tgn:1000001",
          "tgn:2002321",
          "tgn:7012149",
          "tgn:7007922",
          "tgn:7029392"
        ],
        "placetype": [
          "aat:300008680"
        ],
        "id": 2598519,
        "name:xx": "Price Lake"
      }
    }
  ]
}
