{
  "geometry": {
    "type": "Point",
    "coordinates": [
      -110.4667,
      35.3667
    ]
  },
  "type": "Feature",
  "properties": {
    "hierarchy": [
      "tgn:2232302",
      "tgn:1000001",
      "tgn:7006451",
      "tgn:7012149",
      "tgn:2000099",
      "tgn:7029392"
    ],
    "placetype": [
      "aat:300008697"
    ],
    "id": 2232302,
    "name:xx": "Chandler Springs"
  }
}
