{
  "geometry": {
    "type": "Point",
    "coordinates": [
      -79.4167,
      34.95
    ]
  },
  "type": "Feature",
  "properties": {
    "hierarchy": [
      "tgn:2289446",
      "tgn:1000001",
      "tgn:7012149",
      "tgn:2001539",
      "tgn:7007709",
      "tgn:7029392"
    ],
    "placetype": [
      "aat:300006191"
    ],
    "id": 2289446,
    "name:xx": "Dixie Pond"
  }
}
