{
  "geometry": {
    "type": "Point",
    "coordinates": [
      79.229972,
      26.433387
    ]
  },
  "type": "Feature",
  "properties": {
    "hierarchy": [
      "tgn:7562797",
      "tgn:1000004",
      "tgn:7000198",
      "tgn:7016722",
      "tgn:7029392"
    ],
    "placetype": [
      "aat:300008347"
    ],
    "name:en": "Gūnj Kalān",
    "id": 7562797
  }
}
