{
  "geometry": {
    "type": "Point",
    "coordinates": [
      -105.5833,
      41.0333
    ]
  },
  "type": "Feature",
  "properties": {
    "hierarchy": [
      "tgn:2188874",
      "tgn:2002365",
      "tgn:1000001",
      "tgn:7012149",
      "tgn:7007923",
      "tgn:7029392"
    ],
    "placetype": [
      "aat:300008706"
    ],
    "id": 2188874,
    "name:xx": "Boulder Creek"
  }
}
