{
  "type": "FeatureCollection",
  "features": [
    {
      "geometry": {
        "type": "Point",
        "coordinates": [
          -118.9667,
          34.4333
        ]
      },
      "type": "Feature",
      "properties": {
        "hierarchy": [
          "tgn:2673690",
          "tgn:1000001",
          "tgn:7012149",
          "tgn:7007157",
          "tgn:1002972",
          "tgn:7029392"
        ],
        "placetype": [
          "aat:300008761"
        ],
        "id": 2673690,
        "name:xx": "Snow Canyon"
      }
    },
    {
      "geometry": {
        "type": "Point",
        "coordinates": [
          -117.4833,
          36.2
        ]
      },
      "type": "Feature",
      "properties": {
        "hierarchy": [
          "tgn:2673691",
          "tgn:1000001",
          "tgn:7012149",
          "tgn:2000183",
          "tgn:7007157",
          "tgn:7029392"
        ],
        "placetype": [
          "aat:300008761"
        ],
        "id": 2673691,
        "name:xx": "Snow Canyon"
      }
    },
    {
      "geometry": {
        "type": "Point",
        "coordinates": [
          -116.6833,
          33.8
        ]
      },
      "type": "Feature",
      "properties": {
        "hierarchy": [
          "tgn:2673692",
          "tgn:1000001",
          "tgn:7012149",
          "tgn:7007157",
          "tgn:1002828",
          "tgn:7029392"
        ],
        "placetype": [
          "aat:300008761"
        ],
        "id": 2673692,
        "name:xx": "Snow Canyon"
      }
    },
    {
      "geometry": {
        "type": "Point",
        "coordinates": [
          -115.25,
          36.8167
        ]
      },
      "type": "Feature",
      "properties": {
        "hierarchy": [
          "tgn:2673693",
          "tgn:1000001",
          "tgn:2001410",
          "tgn:7012149",
          "tgn:7007526",
          "tgn:7029392"
        ],
        "placetype": [
          "aat:300008761"
        ],
        "id": 2673693,
        "name:xx": "Snow Canyon"
      }
    },
    {
      "geometry": {
        "type": "Point",
        "coordinates": [
          -116,
          41.4667
        ]
      },
      "type": "Feature",
      "properties": {
        "hierarchy": [
          "tgn:2673694",
          "tgn:1000001",
          "tgn:2001411",
          "tgn:7012149",
          "tgn:7007526",
          "tgn:7029392"
        ],
        "placetype": [
          "aat:300008761"
        ],
        "id": 2673694,
        "name:xx": "Snow Canyon"
      }
    },
    {
      "geometry": {
        "type": "Point",
        "coordinates": [
          -105.6167,
          33.25
        ]
      },
      "type": "Feature",
      "properties": {
        "hierarchy": [
          "tgn:2673695",
          "tgn:1000001",
          "tgn:7012149",
          "tgn:2001447",
          "tgn:7007566",
          "tgn:7029392"
        ],
        "placetype": [
          "aat:300008761"
        ],
        "id": 2673695,
        "name:xx": "Snow Canyon"
      }
    },
    {
      "geometry": {
        "type": "Point",
        "coordinates": [
          -108.6167,
          33.45
        ]
      },
      "type": "Feature",
      "properties": {
        "hierarchy": [
          "tgn:2673696",
          "tgn:1000001",
          "tgn:2001429",
          "tgn:7012149",
          "tgn:7007566",
          "tgn:7029392"
        ],
        "placetype": [
          "aat:300008761"
        ],
        "id": 2673696,
        "name:xx": "Snow Canyon"
      }
    },
    {
      "geometry": {
        "type": "Point",
        "coordinates": [
          -112.2167,
          38.9333
        ]
      },
      "type": "Feature",
      "properties": {
        "hierarchy": [
          "tgn:2673697",
          "tgn:1000001",
          "tgn:7012149",
          "tgn:2002114",
          "tgn:7007827",
          "tgn:7029392"
        ],
        "placetype": [
          "aat:300008761"
        ],
        "id": 2673697,
        "name:xx": "Snow Canyon"
      }
    },
    {
      "geometry": {
        "type": "Point",
        "coordinates": [
          -111.9833,
          41.5667
        ]
      },
      "type": "Feature",
      "properties": {
        "hierarchy": [
          "tgn:2673698",
          "tgn:1000001",
          "tgn:2002103",
          "tgn:7012149",
          "tgn:7007827",
          "tgn:7029392"
        ],
        "placetype": [
          "aat:300008761"
        ],
        "id": 2673698,
        "name:xx": "Snow Canyon"
      }
    },
    {
      "geometry": {
        "type": "Point",
        "coordinates": [
          -113.65,
          37.25
        ]
      },
      "type": "Feature",
      "properties": {
        "hierarchy": [
          "tgn:2673699",
          "tgn:1000001",
          "tgn:7012149",
          "tgn:2002127",
          "tgn:7007827",
          "tgn:7029392"
        ],
        "placetype": [
          "aat:300008761"
        ],
        "id": 2673699,
        "name:xx": "Snow Canyon"
      }
    }
  ]
}
