{
  "geometry": {
    "type": "Point",
    "coordinates": [
      -74.0833,
      43.0667
    ]
  },
  "type": "Feature",
  "properties": {
    "hierarchy": [
      "tgn:2434866",
      "tgn:1000001",
      "tgn:7012149",
      "tgn:7007568",
      "tgn:7029392"
    ],
    "placetype": [
      "aat:300008706"
    ],
    "id": 2434866,
    "name:xx": "Kennyetto Creek"
  }
}
