{
  "geometry": {
    "type": "Point",
    "coordinates": [
      39.5333,
      9.2833
    ]
  },
  "type": "Feature",
  "properties": {
    "hierarchy": [
      "tgn:1105595",
      "tgn:7001242",
      "tgn:1001535",
      "tgn:7000489",
      "tgn:7029392"
    ],
    "placetype": [
      "aat:300008795"
    ],
    "id": 1105595,
    "name:xx": "Megezez"
  }
}
