{
  "geometry": {
    "type": "Point",
    "coordinates": [
      -95.7833,
      37.75
    ]
  },
  "type": "Feature",
  "properties": {
    "hierarchy": [
      "tgn:2663110",
      "tgn:1000001",
      "tgn:7012149",
      "tgn:2000763",
      "tgn:7007254",
      "tgn:7029392"
    ],
    "placetype": [
      "aat:300008798"
    ],
    "id": 2663110,
    "name:xx": "Silver City Dome"
  }
}
