{
  "geometry": {
    "type": "Point",
    "coordinates": [
      -67.7833,
      45.2333
    ]
  },
  "type": "Feature",
  "properties": {
    "hierarchy": [
      "tgn:2154630",
      "tgn:1000001",
      "tgn:7012149",
      "tgn:7014589",
      "tgn:7007515",
      "tgn:7029392"
    ],
    "placetype": [
      "aat:300008347"
    ],
    "id": 2154630,
    "name:xx": "Bear Frap Landing"
  }
}
