{
  "geometry": {
    "type": "Point",
    "coordinates": [
      -76.55,
      35.65
    ]
  },
  "type": "Feature",
  "properties": {
    "hierarchy": [
      "tgn:2601180",
      "tgn:1000001",
      "tgn:7012149",
      "tgn:2001506",
      "tgn:7007709",
      "tgn:7029392"
    ],
    "placetype": [
      "aat:300006075"
    ],
    "id": 2601180,
    "name:xx": "Pungo Lake Canal"
  }
}
