{
  "geometry": {
    "type": "Point",
    "coordinates": [
      33.2675,
      31.213056
    ]
  },
  "type": "Feature",
  "properties": {
    "hierarchy": [
      "tgn:7544128",
      "tgn:7001242",
      "tgn:7016833",
      "tgn:7001335",
      "tgn:7029392"
    ],
    "placetype": [
      "aat:300008678"
    ],
    "id": 7544128,
    "name:xx": "Raqm ath Th훮n카, B큰gh훮z"
  }
}
