{
  "geometry": {
    "type": "Point",
    "coordinates": [
      -74.7667,
      44.3667
    ]
  },
  "type": "Feature",
  "properties": {
    "hierarchy": [
      "tgn:2239529",
      "tgn:1000001",
      "tgn:7012149",
      "tgn:7016021",
      "tgn:7007568",
      "tgn:7029392"
    ],
    "placetype": [
      "aat:300008680"
    ],
    "id": 2239529,
    "name:xx": "Church Pond"
  }
}
