{
  "geometry": {
    "type": "Point",
    "coordinates": [
      -135.4167,
      57.1667
    ]
  },
  "type": "Feature",
  "properties": {
    "hierarchy": [
      "tgn:2290966",
      "tgn:7006450",
      "tgn:1000001",
      "tgn:7012149",
      "tgn:2124002",
      "tgn:7029392"
    ],
    "placetype": [
      "aat:300008850"
    ],
    "id": 2290966,
    "name:xx": "Dog Point"
  }
}
