{
  "type": "FeatureCollection",
  "features": [
    {
      "geometry": {
        "type": "Point",
        "coordinates": [
          -123.3,
          40.3
        ]
      },
      "type": "Feature",
      "properties": {
        "hierarchy": [
          "tgn:2132590",
          "tgn:1000001",
          "tgn:7012149",
          "tgn:7007157",
          "tgn:2000191",
          "tgn:7029392"
        ],
        "placetype": [
          "aat:300008706"
        ],
        "id": 2132590,
        "name:xx": "Anada Creek"
      }
    },
    {
      "geometry": {
        "type": "Point",
        "coordinates": [
          -97.0667,
          34.0333
        ]
      },
      "type": "Feature",
      "properties": {
        "hierarchy": [
          "tgn:2132591",
          "tgn:1000001",
          "tgn:7012149",
          "tgn:2001665",
          "tgn:7007707",
          "tgn:7029392"
        ],
        "placetype": [
          "aat:300008706"
        ],
        "id": 2132591,
        "name:xx": "Anadarche Creek"
      }
    },
    {
      "geometry": {
        "type": "Point",
        "coordinates": [
          -94.7833,
          31.9
        ]
      },
      "type": "Feature",
      "properties": {
        "hierarchy": [
          "tgn:2132592",
          "tgn:1000001",
          "tgn:7012149",
          "tgn:1002839",
          "tgn:7007826",
          "tgn:7029392"
        ],
        "placetype": [
          "aat:300008706"
        ],
        "id": 2132592,
        "name:xx": "Anadarko Creek"
      }
    },
    {
      "geometry": {
        "type": "Point",
        "coordinates": [
          -155.8833,
          19.9167
        ]
      },
      "type": "Feature",
      "properties": {
        "hierarchy": [
          "tgn:2132593",
          "tgn:7023902",
          "tgn:1000001",
          "tgn:7012149",
          "tgn:7007249",
          "tgn:7029392"
        ],
        "placetype": [
          "aat:300008347"
        ],
        "id": 2132593,
        "name:xx": "Anaehoomalu"
      }
    },
    {
      "geometry": {
        "type": "Point",
        "coordinates": [
          -155.8833,
          19.9167
        ]
      },
      "type": "Feature",
      "properties": {
        "hierarchy": [
          "tgn:2132594",
          "tgn:7023902",
          "tgn:1000001",
          "tgn:7012149",
          "tgn:7007249",
          "tgn:7029392"
        ],
        "placetype": [
          "aat:300132316"
        ],
        "id": 2132594,
        "name:xx": "Anaehoomalu Bay"
      }
    },
    {
      "geometry": {
        "type": "Point",
        "coordinates": [
          -155.8833,
          19.9167
        ]
      },
      "type": "Feature",
      "properties": {
        "hierarchy": [
          "tgn:2132598",
          "tgn:7023902",
          "tgn:1000001",
          "tgn:7012149",
          "tgn:7007249",
          "tgn:7029392"
        ],
        "placetype": [
          "aat:300008850"
        ],
        "id": 2132598,
        "name:xx": "Anaehoomalu Point"
      }
    },
    {
      "geometry": {
        "type": "Point",
        "coordinates": [
          -175.8833,
          51.85
        ]
      },
      "type": "Feature",
      "properties": {
        "hierarchy": [
          "tgn:2132599",
          "tgn:7030516",
          "tgn:7006450",
          "tgn:1000001",
          "tgn:7012149",
          "tgn:7029392"
        ],
        "placetype": [
          "aat:300008791"
        ],
        "id": 2132599,
        "name:xx": "Anagaksik Island"
      }
    }
  ]
}
