{
  "geometry": {
    "type": "Point",
    "coordinates": [
      -117.15,
      33.1333
    ]
  },
  "type": "Feature",
  "properties": {
    "hierarchy": [
      "tgn:2640645",
      "tgn:1000001",
      "tgn:7012149",
      "tgn:7007157",
      "tgn:1002858",
      "tgn:7029392"
    ],
    "placetype": [
      "aat:300008706"
    ],
    "id": 2640645,
    "name:xx": "San Marcos Creek"
  }
}
