{
  "geometry": {
    "type": "Point",
    "coordinates": [
      32.0167,
      40.3333
    ]
  },
  "type": "Feature",
  "properties": {
    "hierarchy": [
      "tgn:1086530",
      "tgn:1001101",
      "tgn:1000004",
      "tgn:7018453",
      "tgn:1000144",
      "tgn:7029392"
    ],
    "placetype": [
      "aat:300008347"
    ],
    "id": 1086530,
    "name:xx": "Karaşar"
  }
}
