{
  "type": "FeatureCollection",
  "features": [
    {
      "geometry": {
        "type": "Point",
        "coordinates": [
          -107.753889,
          24.919167
        ]
      },
      "type": "Feature",
      "properties": {
        "hierarchy": [
          "tgn:7354400",
          "tgn:1000001",
          "tgn:7005595",
          "tgn:7005560",
          "tgn:7029392"
        ],
        "placetype": [
          "aat:300008347"
        ],
        "id": 7354400,
        "name:xx": "Casas Viejas"
      }
    },
    {
      "geometry": {
        "type": "Point",
        "coordinates": [
          -106.812778,
          24.039167
        ]
      },
      "type": "Feature",
      "properties": {
        "hierarchy": [
          "tgn:7354401",
          "tgn:1000001",
          "tgn:7005595",
          "tgn:7005560",
          "tgn:7029392"
        ],
        "placetype": [
          "aat:300008347"
        ],
        "id": 7354401,
        "name:xx": "Casas Viejas"
      }
    },
    {
      "geometry": {
        "type": "Point",
        "coordinates": [
          -99.1,
          22.183333
        ]
      },
      "type": "Feature",
      "properties": {
        "hierarchy": [
          "tgn:7354402",
          "tgn:1000001",
          "tgn:7005594",
          "tgn:7005560",
          "tgn:7029392"
        ],
        "placetype": [
          "aat:300008347"
        ],
        "id": 7354402,
        "name:xx": "Casas Viejas"
      }
    },
    {
      "geometry": {
        "type": "Point",
        "coordinates": [
          -102.216667,
          21.333333
        ]
      },
      "type": "Feature",
      "properties": {
        "hierarchy": [
          "tgn:7354403",
          "tgn:7005586",
          "tgn:1000001",
          "tgn:7005560",
          "tgn:7029392"
        ],
        "placetype": [
          "aat:300008347"
        ],
        "id": 7354403,
        "name:xx": "Casas Viejas"
      }
    },
    {
      "geometry": {
        "type": "Point",
        "coordinates": [
          -99.9,
          20.933333
        ]
      },
      "type": "Feature",
      "properties": {
        "hierarchy": [
          "tgn:7354404",
          "tgn:1000001",
          "tgn:7005593",
          "tgn:7005560",
          "tgn:7029392"
        ],
        "placetype": [
          "aat:300008347"
        ],
        "id": 7354404,
        "name:xx": "Casas Viejas"
      }
    },
    {
      "geometry": {
        "type": "Point",
        "coordinates": [
          -95.55,
          18.366667
        ]
      },
      "type": "Feature",
      "properties": {
        "hierarchy": [
          "tgn:7354405",
          "tgn:1000001",
          "tgn:7005599",
          "tgn:7005560",
          "tgn:7029392"
        ],
        "placetype": [
          "aat:300008347"
        ],
        "id": 7354405,
        "name:xx": "Casas Viejas"
      }
    },
    {
      "geometry": {
        "type": "Point",
        "coordinates": [
          -94.666667,
          18.1
        ]
      },
      "type": "Feature",
      "properties": {
        "hierarchy": [
          "tgn:7354406",
          "tgn:1000001",
          "tgn:7005599",
          "tgn:7005560",
          "tgn:7029392"
        ],
        "placetype": [
          "aat:300008347"
        ],
        "id": 7354406,
        "name:xx": "Casas Viejas"
      }
    },
    {
      "geometry": {
        "type": "Point",
        "coordinates": [
          -95,
          18.083333
        ]
      },
      "type": "Feature",
      "properties": {
        "hierarchy": [
          "tgn:7354407",
          "tgn:1000001",
          "tgn:7005599",
          "tgn:7005560",
          "tgn:7029392"
        ],
        "placetype": [
          "aat:300008347"
        ],
        "id": 7354407,
        "name:xx": "Casas Viejas"
      }
    },
    {
      "geometry": {
        "type": "Point",
        "coordinates": [
          -101.533333,
          18
        ]
      },
      "type": "Feature",
      "properties": {
        "hierarchy": [
          "tgn:7354408",
          "tgn:7005585",
          "tgn:1000001",
          "tgn:7005560",
          "tgn:7029392"
        ],
        "placetype": [
          "aat:300008347"
        ],
        "id": 7354408,
        "name:xx": "Casas Viejas"
      }
    },
    {
      "geometry": {
        "type": "Point",
        "coordinates": [
          -95.266667,
          17.983333
        ]
      },
      "type": "Feature",
      "properties": {
        "hierarchy": [
          "tgn:7354409",
          "tgn:1000001",
          "tgn:7005599",
          "tgn:7005560",
          "tgn:7029392"
        ],
        "placetype": [
          "aat:300008347"
        ],
        "id": 7354409,
        "name:xx": "Casas Viejas"
      }
    }
  ]
}
