{
  "geometry": {
    "type": "Point",
    "coordinates": [
      -84.9167,
      43.8167
    ]
  },
  "type": "Feature",
  "properties": {
    "hierarchy": [
      "tgn:2279621",
      "tgn:1000001",
      "tgn:2000953",
      "tgn:7012149",
      "tgn:7007520",
      "tgn:7029392"
    ],
    "placetype": [
      "aat:300008905"
    ],
    "id": 2279621,
    "name:xx": "Deadman Swamp"
  }
}
