{
  "geometry": {
    "type": "Point",
    "coordinates": [
      -104.6167,
      43.2833
    ]
  },
  "type": "Feature",
  "properties": {
    "hierarchy": [
      "tgn:2425681",
      "tgn:1000001",
      "tgn:7012149",
      "tgn:2002378",
      "tgn:7007923",
      "tgn:7029392"
    ],
    "placetype": [
      "aat:300006191"
    ],
    "id": 2425681,
    "name:xx": "Johnston Number 1 Reservoir"
  }
}
