{
  "geometry": {
    "type": "Point",
    "coordinates": [
      -95.2833,
      30.1333
    ]
  },
  "type": "Feature",
  "properties": {
    "hierarchy": [
      "tgn:2769376",
      "tgn:1000001",
      "tgn:7012149",
      "tgn:1002691",
      "tgn:7007826",
      "tgn:7029392"
    ],
    "placetype": [
      "aat:300008905"
    ],
    "id": 2769376,
    "name:xx": "Wickizer Pond"
  }
}
