{
  "geometry": {
    "type": "Point",
    "coordinates": [
      -97.7833,
      25.6333
    ]
  },
  "type": "Feature",
  "properties": {
    "hierarchy": [
      "tgn:1017353",
      "tgn:1000001",
      "tgn:7005597",
      "tgn:7005560",
      "tgn:7029392"
    ],
    "placetype": [
      "aat:300008347"
    ],
    "id": 1017353,
    "name:xx": "Doce de Octubre"
  }
}
