{
  "geometry": {
    "type": "Point",
    "coordinates": [
      -93.3833,
      33.8333
    ]
  },
  "type": "Feature",
  "properties": {
    "hierarchy": [
      "tgn:2522760",
      "tgn:1000001",
      "tgn:7016172",
      "tgn:7012149",
      "tgn:7029392"
    ],
    "placetype": [
      "aat:300008706"
    ],
    "id": 2522760,
    "name:xx": "Moore Creek"
  }
}
