{
  "type": "FeatureCollection",
  "features": [
    {
      "geometry": {
        "type": "Point",
        "coordinates": [
          -112.3167,
          44.4667
        ]
      },
      "type": "Feature",
      "properties": {
        "hierarchy": [
          "tgn:2435800",
          "tgn:1000001",
          "tgn:2000468",
          "tgn:7012149",
          "tgn:7007250",
          "tgn:7029392"
        ],
        "placetype": [
          "aat:300008706"
        ],
        "id": 2435800,
        "name:xx": "Kettle Creek"
      }
    },
    {
      "geometry": {
        "type": "Point",
        "coordinates": [
          -87.3833,
          39.1833
        ]
      },
      "type": "Feature",
      "properties": {
        "hierarchy": [
          "tgn:2435801",
          "tgn:1000001",
          "tgn:7012149",
          "tgn:2000556",
          "tgn:7007252",
          "tgn:7029392"
        ],
        "placetype": [
          "aat:300008706"
        ],
        "id": 2435801,
        "name:xx": "Kettle Creek"
      }
    },
    {
      "geometry": {
        "type": "Point",
        "coordinates": [
          -92.4667,
          40.9833
        ]
      },
      "type": "Feature",
      "properties": {
        "hierarchy": [
          "tgn:2435802",
          "tgn:1000001",
          "tgn:7012149",
          "tgn:2000650",
          "tgn:7007253",
          "tgn:7029392"
        ],
        "placetype": [
          "aat:300008706"
        ],
        "id": 2435802,
        "name:xx": "Kettle Creek"
      }
    },
    {
      "geometry": {
        "type": "Point",
        "coordinates": [
          -85.0167,
          37.2833
        ]
      },
      "type": "Feature",
      "properties": {
        "hierarchy": [
          "tgn:2435803",
          "tgn:1000001",
          "tgn:2000779",
          "tgn:7012149",
          "tgn:7007255",
          "tgn:7029392"
        ],
        "placetype": [
          "aat:300008706"
        ],
        "id": 2435803,
        "name:xx": "Kettle Creek"
      }
    },
    {
      "geometry": {
        "type": "Point",
        "coordinates": [
          -85.4,
          36.6667
        ]
      },
      "type": "Feature",
      "properties": {
        "hierarchy": [
          "tgn:2435804",
          "tgn:1000001",
          "tgn:7012149",
          "tgn:7029392"
        ],
        "placetype": [
          "aat:300008706"
        ],
        "id": 2435804,
        "name:xx": "Kettle Creek"
      }
    },
    {
      "geometry": {
        "type": "Point",
        "coordinates": [
          -89.3333,
          34.35
        ]
      },
      "type": "Feature",
      "properties": {
        "hierarchy": [
          "tgn:2435805",
          "tgn:1000001",
          "tgn:7012149",
          "tgn:2001121",
          "tgn:7007522",
          "tgn:7029392"
        ],
        "placetype": [
          "aat:300008706"
        ],
        "id": 2435805,
        "name:xx": "Kettle Creek"
      }
    },
    {
      "geometry": {
        "type": "Point",
        "coordinates": [
          -93.85,
          39.75
        ]
      },
      "type": "Feature",
      "properties": {
        "hierarchy": [
          "tgn:2435806",
          "tgn:1000001",
          "tgn:7012149",
          "tgn:7007523",
          "tgn:7029392"
        ],
        "placetype": [
          "aat:300008706"
        ],
        "id": 2435806,
        "name:xx": "Kettle Creek"
      }
    },
    {
      "geometry": {
        "type": "Point",
        "coordinates": [
          -74.2,
          40.0333
        ]
      },
      "type": "Feature",
      "properties": {
        "hierarchy": [
          "tgn:2435807",
          "tgn:1000001",
          "tgn:1002738",
          "tgn:7012149",
          "tgn:7007565",
          "tgn:7029392"
        ],
        "placetype": [
          "aat:300008706"
        ],
        "id": 2435807,
        "name:xx": "Kettle Creek"
      }
    },
    {
      "geometry": {
        "type": "Point",
        "coordinates": [
          -122.8833,
          42.0167
        ]
      },
      "type": "Feature",
      "properties": {
        "hierarchy": [
          "tgn:2435808",
          "tgn:1000001",
          "tgn:7012149",
          "tgn:2001711",
          "tgn:7007708",
          "tgn:7029392"
        ],
        "placetype": [
          "aat:300008706"
        ],
        "id": 2435808,
        "name:xx": "Kettle Creek"
      }
    },
    {
      "geometry": {
        "type": "Point",
        "coordinates": [
          -117.2667,
          45.05
        ]
      },
      "type": "Feature",
      "properties": {
        "hierarchy": [
          "tgn:2435809",
          "tgn:7013349",
          "tgn:1000001",
          "tgn:7012149",
          "tgn:7007708",
          "tgn:7029392"
        ],
        "placetype": [
          "aat:300008706"
        ],
        "id": 2435809,
        "name:xx": "Kettle Creek"
      }
    }
  ]
}
