{
  "geometry": {
    "type": "Point",
    "coordinates": [
      -119.5167,
      41.2833
    ]
  },
  "type": "Feature",
  "properties": {
    "hierarchy": [
      "tgn:2457575",
      "tgn:1000001",
      "tgn:7012149",
      "tgn:1002999",
      "tgn:7007526",
      "tgn:7029392"
    ],
    "placetype": [
      "aat:300006191"
    ],
    "id": 2457575,
    "name:xx": "Little Mahogany Reservoir"
  }
}
