{
  "geometry": {
    "type": "Point",
    "coordinates": [
      -139.5333,
      63.1667
    ]
  },
  "type": "Feature",
  "properties": {
    "hierarchy": [
      "tgn:1131752",
      "tgn:1000001",
      "tgn:7029392"
    ],
    "placetype": [
      "aat:300008707"
    ],
    "id": 1131752,
    "name:xx": "White"
  }
}
