{
  "geometry": {
    "type": "Point",
    "coordinates": [
      -106.0167,
      48.05
    ]
  },
  "type": "Feature",
  "properties": {
    "hierarchy": [
      "tgn:2339340",
      "tgn:1000001",
      "tgn:7012149",
      "tgn:2001312",
      "tgn:7007524",
      "tgn:7029392"
    ],
    "placetype": [
      "aat:300006191"
    ],
    "id": 2339340,
    "name:xx": "Frazer Lake"
  }
}
