{
  "geometry": {
    "type": "Point",
    "coordinates": [
      -78.1833,
      34.3667
    ]
  },
  "type": "Feature",
  "properties": {
    "hierarchy": [
      "tgn:2155750",
      "tgn:1000001",
      "tgn:7012149",
      "tgn:2001527",
      "tgn:7007709",
      "tgn:7029392"
    ],
    "placetype": [
      "aat:300008905"
    ],
    "id": 2155750,
    "name:xx": "Bear Swamp"
  }
}
