{
  "geometry": {
    "type": "Point",
    "coordinates": [
      -122.9167,
      47.25
    ]
  },
  "type": "Feature",
  "properties": {
    "hierarchy": [
      "tgn:2359388",
      "tgn:1000001",
      "tgn:7012149",
      "tgn:1002645",
      "tgn:7007920",
      "tgn:7029392"
    ],
    "placetype": [
      "aat:300008347"
    ],
    "id": 2359388,
    "name:xx": "Grant"
  }
}
