{
  "geometry": {
    "type": "Point",
    "coordinates": [
      -74.4833,
      43.4833
    ]
  },
  "type": "Feature",
  "properties": {
    "hierarchy": [
      "tgn:2745926",
      "tgn:1000001",
      "tgn:7012149",
      "tgn:1002440",
      "tgn:7007568",
      "tgn:7029392"
    ],
    "placetype": [
      "aat:300008680"
    ],
    "id": 2745926,
    "name:xx": "Vly Lake"
  }
}
