{
  "type": "FeatureCollection",
  "features": [
    {
      "geometry": {
        "type": "Point",
        "coordinates": [
          -117.0167,
          40.6167
        ]
      },
      "type": "Feature",
      "properties": {
        "hierarchy": [
          "tgn:2256001",
          "tgn:1000001",
          "tgn:2001415",
          "tgn:7012149",
          "tgn:7007526",
          "tgn:7029392"
        ],
        "placetype": [
          "aat:300000390"
        ],
        "id": 2256001,
        "name:xx": "Copper King Mine"
      }
    },
    {
      "geometry": {
        "type": "Point",
        "coordinates": [
          -116.2333,
          40.8
        ]
      },
      "type": "Feature",
      "properties": {
        "hierarchy": [
          "tgn:2256002",
          "tgn:1000001",
          "tgn:2001413",
          "tgn:7012149",
          "tgn:7007526",
          "tgn:7029392"
        ],
        "placetype": [
          "aat:300000390"
        ],
        "id": 2256002,
        "name:xx": "Copper King Mine"
      }
    },
    {
      "geometry": {
        "type": "Point",
        "coordinates": [
          -119.5667,
          39.05
        ]
      },
      "type": "Feature",
      "properties": {
        "hierarchy": [
          "tgn:2256003",
          "tgn:1000001",
          "tgn:1002340",
          "tgn:7012149",
          "tgn:7007526",
          "tgn:7029392"
        ],
        "placetype": [
          "aat:300000390"
        ],
        "id": 2256003,
        "name:xx": "Copper King Mine"
      }
    },
    {
      "geometry": {
        "type": "Point",
        "coordinates": [
          -117.6,
          38.9
        ]
      },
      "type": "Feature",
      "properties": {
        "hierarchy": [
          "tgn:2256004",
          "tgn:1000001",
          "tgn:2001418",
          "tgn:7012149",
          "tgn:7007526",
          "tgn:7029392"
        ],
        "placetype": [
          "aat:300000390"
        ],
        "id": 2256004,
        "name:xx": "Copper King Mine"
      }
    },
    {
      "geometry": {
        "type": "Point",
        "coordinates": [
          -118.8333,
          40
        ]
      },
      "type": "Feature",
      "properties": {
        "hierarchy": [
          "tgn:2256005",
          "tgn:1000001",
          "tgn:2001419",
          "tgn:7012149",
          "tgn:7007526",
          "tgn:7029392"
        ],
        "placetype": [
          "aat:300000390"
        ],
        "id": 2256005,
        "name:xx": "Copper King Mine"
      }
    },
    {
      "geometry": {
        "type": "Point",
        "coordinates": [
          -114.8167,
          41.7667
        ]
      },
      "type": "Feature",
      "properties": {
        "hierarchy": [
          "tgn:2256006",
          "tgn:1000001",
          "tgn:2001411",
          "tgn:7012149",
          "tgn:7007526",
          "tgn:7029392"
        ],
        "placetype": [
          "aat:300000390"
        ],
        "id": 2256006,
        "name:xx": "Copper King Mine"
      }
    },
    {
      "geometry": {
        "type": "Point",
        "coordinates": [
          -107.5333,
          32.9667
        ]
      },
      "type": "Feature",
      "properties": {
        "hierarchy": [
          "tgn:2256007",
          "tgn:1000001",
          "tgn:7012149",
          "tgn:2001455",
          "tgn:7007566",
          "tgn:7029392"
        ],
        "placetype": [
          "aat:300000390"
        ],
        "id": 2256007,
        "name:xx": "Copper King Mine"
      }
    },
    {
      "geometry": {
        "type": "Point",
        "coordinates": [
          -105.4,
          36.7
        ]
      },
      "type": "Feature",
      "properties": {
        "hierarchy": [
          "tgn:2256008",
          "tgn:1000001",
          "tgn:7012149",
          "tgn:2001457",
          "tgn:7007566",
          "tgn:7029392"
        ],
        "placetype": [
          "aat:300000390"
        ],
        "id": 2256008,
        "name:xx": "Copper King Mine"
      }
    },
    {
      "geometry": {
        "type": "Point",
        "coordinates": [
          -113.1,
          38.4
        ]
      },
      "type": "Feature",
      "properties": {
        "hierarchy": [
          "tgn:2256009",
          "tgn:2002101",
          "tgn:1000001",
          "tgn:7012149",
          "tgn:7007827",
          "tgn:7029392"
        ],
        "placetype": [
          "aat:300000390"
        ],
        "id": 2256009,
        "name:xx": "Copper King Mine"
      }
    }
  ]
}
