{
  "type": "FeatureCollection",
  "features": [
    {
      "geometry": {
        "type": "Point",
        "coordinates": [
          -82.5,
          34.1
        ]
      },
      "type": "Feature",
      "properties": {
        "hierarchy": [
          "tgn:2235400",
          "tgn:2001725",
          "tgn:1000001",
          "tgn:7012149",
          "tgn:7007712",
          "tgn:7029392"
        ],
        "placetype": [
          "aat:300008347"
        ],
        "id": 2235400,
        "name:xx": "Chesnut Hill"
      }
    },
    {
      "geometry": {
        "type": "Point",
        "coordinates": [
          -89.8,
          34.0167
        ]
      },
      "type": "Feature",
      "properties": {
        "hierarchy": [
          "tgn:2235401",
          "tgn:1000001",
          "tgn:7012149",
          "tgn:2001166",
          "tgn:7007522",
          "tgn:7029392"
        ],
        "placetype": [
          "aat:300006191"
        ],
        "id": 2235401,
        "name:xx": "Chesnut Lake"
      }
    },
    {
      "geometry": {
        "type": "Point",
        "coordinates": [
          -79.75,
          36.9
        ]
      },
      "type": "Feature",
      "properties": {
        "hierarchy": [
          "tgn:2235403",
          "tgn:1000001",
          "tgn:7012149",
          "tgn:2002160",
          "tgn:7007919",
          "tgn:7029392"
        ],
        "placetype": [
          "aat:300008798"
        ],
        "id": 2235403,
        "name:xx": "Chesnut Mountain"
      }
    },
    {
      "geometry": {
        "type": "Point",
        "coordinates": [
          -80.9833,
          37.2667
        ]
      },
      "type": "Feature",
      "properties": {
        "hierarchy": [
          "tgn:2235404",
          "tgn:1000001",
          "tgn:7012149",
          "tgn:2002162",
          "tgn:7007919",
          "tgn:7029392"
        ],
        "placetype": [
          "aat:300266640"
        ],
        "id": 2235404,
        "name:xx": "Chesnut Ridge"
      }
    },
    {
      "geometry": {
        "type": "Point",
        "coordinates": [
          -79.6167,
          38.1833
        ]
      },
      "type": "Feature",
      "properties": {
        "hierarchy": [
          "tgn:2235405",
          "tgn:1000001",
          "tgn:7012149",
          "tgn:7007919",
          "tgn:7029392"
        ],
        "placetype": [
          "aat:300266640"
        ],
        "id": 2235405,
        "name:xx": "Chesnut Ridge"
      }
    },
    {
      "geometry": {
        "type": "Point",
        "coordinates": [
          -79.6,
          38.2
        ]
      },
      "type": "Feature",
      "properties": {
        "hierarchy": [
          "tgn:2235407",
          "tgn:1000001",
          "tgn:7012149",
          "tgn:2002168",
          "tgn:7007919",
          "tgn:7029392"
        ],
        "placetype": [
          "aat:300008746"
        ],
        "id": 2235407,
        "name:xx": "Chesnut Ridge Blowing Cave"
      }
    },
    {
      "geometry": {
        "type": "Point",
        "coordinates": [
          -76.05,
          36.8333
        ]
      },
      "type": "Feature",
      "properties": {
        "hierarchy": [
          "tgn:2235408",
          "tgn:1000001",
          "tgn:7012149",
          "tgn:7022218",
          "tgn:7007919",
          "tgn:7029392"
        ],
        "placetype": [
          "aat:300008347"
        ],
        "id": 2235408,
        "name:xx": "Chesopeian Colony"
      }
    },
    {
      "geometry": {
        "type": "Point",
        "coordinates": [
          -83.6667,
          35.45
        ]
      },
      "type": "Feature",
      "properties": {
        "hierarchy": [
          "tgn:2235409",
          "tgn:1000001",
          "tgn:7012149",
          "tgn:2001543",
          "tgn:7007709",
          "tgn:7029392"
        ],
        "placetype": [
          "aat:300008699"
        ],
        "id": 2235409,
        "name:xx": "Chesquaw Branch"
      }
    }
  ]
}
