{
  "geometry": {
    "type": "Point",
    "coordinates": [
      13.6833,
      56.1667
    ]
  },
  "type": "Feature",
  "properties": {
    "hierarchy": [
      "tgn:1062960",
      "tgn:1000003",
      "tgn:7024622",
      "tgn:1000097",
      "tgn:7029392"
    ],
    "placetype": [
      "aat:300008347"
    ],
    "id": 1062960,
    "name:xx": "Finja"
  }
}
