{
  "geometry": {
    "type": "Point",
    "coordinates": [
      -85.9333,
      36.75
    ]
  },
  "type": "Feature",
  "properties": {
    "hierarchy": [
      "tgn:2410418",
      "tgn:2000768",
      "tgn:1000001",
      "tgn:7012149",
      "tgn:7007255",
      "tgn:7029392"
    ],
    "placetype": [
      "aat:300008699"
    ],
    "id": 2410418,
    "name:xx": "Indian Camp Branch"
  }
}
