{
  "geometry": {
    "type": "Point",
    "coordinates": [
      -3.75,
      42.116667
    ]
  },
  "type": "Feature",
  "properties": {
    "hierarchy": [
      "tgn:7343731",
      "tgn:7002810",
      "tgn:7001158",
      "tgn:1000003",
      "tgn:1000095",
      "tgn:7029392"
    ],
    "placetype": [
      "aat:300008699"
    ],
    "id": 7343731,
    "name:xx": "Carabidas, Río"
  }
}
