{
  "geometry": {
    "type": "Point",
    "coordinates": [
      -111.4667,
      45.55
    ]
  },
  "type": "Feature",
  "properties": {
    "hierarchy": [
      "tgn:2314508",
      "tgn:1000001",
      "tgn:7012149",
      "tgn:2001288",
      "tgn:7007524",
      "tgn:7029392"
    ],
    "placetype": [
      "aat:300008798"
    ],
    "id": 2314508,
    "name:xx": "Elk Mountain"
  }
}
