{
  "type": "FeatureCollection",
  "features": [
    {
      "geometry": {
        "type": "Point",
        "coordinates": [
          9.657222,
          39.925556
        ]
      },
      "type": "Feature",
      "properties": {
        "hierarchy": [
          "tgn:1047160",
          "tgn:1001724",
          "tgn:1000003",
          "tgn:7003121",
          "tgn:1000080",
          "tgn:7029392"
        ],
        "placetype": [
          "aat:300008347"
        ],
        "id": 1047160,
        "name:xx": "Tortolì"
      }
    },
    {
      "geometry": {
        "type": "Point",
        "coordinates": [
          15.8,
          39.933333
        ]
      },
      "type": "Feature",
      "properties": {
        "hierarchy": [
          "tgn:1047162",
          "tgn:1003450",
          "tgn:7007850",
          "tgn:1000003",
          "tgn:1000080",
          "tgn:7029392"
        ],
        "placetype": [
          "aat:300008347"
        ],
        "id": 1047162,
        "name:xx": "Tortora"
      }
    },
    {
      "geometry": {
        "type": "Point",
        "coordinates": [
          13.916667,
          42.8
        ]
      },
      "type": "Feature",
      "properties": {
        "hierarchy": [
          "tgn:1047163",
          "tgn:7009084",
          "tgn:7003001",
          "tgn:1000003",
          "tgn:1000080",
          "tgn:7029392"
        ],
        "placetype": [
          "aat:300008347"
        ],
        "id": 1047163,
        "name:xx": "Tortoreto"
      }
    },
    {
      "geometry": {
        "type": "Point",
        "coordinates": [
          14.816667,
          38.033333
        ]
      },
      "type": "Feature",
      "properties": {
        "hierarchy": [
          "tgn:1047164",
          "tgn:1000003",
          "tgn:7003122",
          "tgn:7003157",
          "tgn:1000080",
          "tgn:7029392"
        ],
        "placetype": [
          "aat:300008347"
        ],
        "id": 1047164,
        "name:xx": "Tortorici"
      }
    },
    {
      "geometry": {
        "type": "Point",
        "coordinates": [
          11.5167,
          43.75
        ]
      },
      "type": "Feature",
      "properties": {
        "hierarchy": [
          "tgn:1047166",
          "tgn:7003163",
          "tgn:1000003",
          "tgn:7009760",
          "tgn:1000080",
          "tgn:7029392"
        ],
        "placetype": [
          "aat:300008347"
        ],
        "id": 1047166,
        "name:xx": "Tosi"
      }
    },
    {
      "geometry": {
        "type": "Point",
        "coordinates": [
          13.65,
          37.983333
        ]
      },
      "type": "Feature",
      "properties": {
        "hierarchy": [
          "tgn:1047168",
          "tgn:1000003",
          "tgn:7003122",
          "tgn:1001732",
          "tgn:1000080",
          "tgn:7029392"
        ],
        "placetype": [
          "aat:300008347"
        ],
        "id": 1047168,
        "name:xx": "Trabia"
      }
    },
    {
      "geometry": {
        "type": "Point",
        "coordinates": [
          8.9,
          45.716667
        ]
      },
      "type": "Feature",
      "properties": {
        "hierarchy": [
          "tgn:1047169",
          "tgn:1000003",
          "tgn:1003508",
          "tgn:7003237",
          "tgn:1000080",
          "tgn:7029392"
        ],
        "placetype": [
          "aat:300008347"
        ],
        "id": 1047169,
        "name:xx": "Tradate"
      }
    }
  ]
}
