{
  "geometry": {
    "type": "Point",
    "coordinates": [
      -92.7333,
      39.1833
    ]
  },
  "type": "Feature",
  "properties": {
    "hierarchy": [
      "tgn:2125809",
      "tgn:1000001",
      "tgn:7012149",
      "tgn:2001205",
      "tgn:7007523",
      "tgn:7029392"
    ],
    "placetype": [
      "aat:300008699"
    ],
    "id": 2125809,
    "name:xx": "Adams Fork"
  }
}
