{
  "geometry": {
    "type": "Point",
    "coordinates": [
      -94.2333,
      45.6333
    ]
  },
  "type": "Feature",
  "properties": {
    "hierarchy": [
      "tgn:2144465",
      "tgn:1000001",
      "tgn:7012149",
      "tgn:2001071",
      "tgn:7007521",
      "tgn:7029392"
    ],
    "placetype": [
      "aat:300008680"
    ],
    "id": 2144465,
    "name:xx": "Bakers Lake"
  }
}
