{
  "geometry": {
    "type": "Point",
    "coordinates": [
      -116.7167,
      38.4167
    ]
  },
  "type": "Feature",
  "properties": {
    "hierarchy": [
      "tgn:2206996",
      "tgn:1000001",
      "tgn:2001418",
      "tgn:7012149",
      "tgn:7007526",
      "tgn:7029392"
    ],
    "placetype": [
      "aat:300008761"
    ],
    "id": 2206996,
    "name:xx": "Bunch Brush Canyon"
  }
}
