{
  "geometry": {
    "type": "Point",
    "coordinates": [
      -84.8167,
      42.4333
    ]
  },
  "type": "Feature",
  "properties": {
    "hierarchy": [
      "tgn:2308647",
      "tgn:1000001",
      "tgn:2000957",
      "tgn:7012149",
      "tgn:7007520",
      "tgn:7029392"
    ],
    "placetype": [
      "aat:300006075"
    ],
    "id": 2308647,
    "name:xx": "East Page Ditch"
  }
}
