{
  "geometry": {
    "type": "Point",
    "coordinates": [
      -84.3333,
      39.05
    ]
  },
  "type": "Feature",
  "properties": {
    "hierarchy": [
      "tgn:2138417",
      "tgn:1000001",
      "tgn:7012149",
      "tgn:1002441",
      "tgn:7007706",
      "tgn:7029392"
    ],
    "placetype": [
      "aat:300008347"
    ],
    "id": 2138417,
    "name:xx": "Asbury"
  }
}
