{
  "type": "FeatureCollection",
  "features": [
    {
      "geometry": {
        "type": "Point",
        "coordinates": [
          10.233333,
          52.3
        ]
      },
      "type": "Feature",
      "properties": {
        "hierarchy": [
          "tgn:7121390",
          "tgn:1000003",
          "tgn:7003676",
          "tgn:7000084",
          "tgn:7029392"
        ],
        "placetype": [
          "aat:300008699"
        ],
        "id": 7121390,
        "name:xx": "Pisser"
      }
    },
    {
      "geometry": {
        "type": "Point",
        "coordinates": [
          12.15,
          51.333333
        ]
      },
      "type": "Feature",
      "properties": {
        "hierarchy": [
          "tgn:7121391",
          "tgn:1000003",
          "tgn:7003687",
          "tgn:7000084",
          "tgn:7029392"
        ],
        "placetype": [
          "aat:300008347"
        ],
        "id": 7121391,
        "name:xx": "Pissen"
      }
    },
    {
      "geometry": {
        "type": "Point",
        "coordinates": [
          11.066667,
          53.116667
        ]
      },
      "type": "Feature",
      "properties": {
        "hierarchy": [
          "tgn:7121392",
          "tgn:1000003",
          "tgn:7003676",
          "tgn:7000084",
          "tgn:7029392"
        ],
        "placetype": [
          "aat:300008347"
        ],
        "id": 7121392,
        "name:xx": "Pisselberg"
      }
    },
    {
      "geometry": {
        "type": "Point",
        "coordinates": [
          12,
          51.783333
        ]
      },
      "type": "Feature",
      "properties": {
        "hierarchy": [
          "tgn:7121393",
          "tgn:1000003",
          "tgn:7003687",
          "tgn:7000084",
          "tgn:7029392"
        ],
        "placetype": [
          "aat:300008347"
        ],
        "id": 7121393,
        "name:xx": "Pißdorf"
      }
    },
    {
      "geometry": {
        "type": "Point",
        "coordinates": [
          12.333333,
          49.333333
        ]
      },
      "type": "Feature",
      "properties": {
        "hierarchy": [
          "tgn:7121394",
          "tgn:7003669",
          "tgn:1000003",
          "tgn:7000084",
          "tgn:7029392"
        ],
        "placetype": [
          "aat:300008347"
        ],
        "id": 7121394,
        "name:xx": "Pissau"
      }
    },
    {
      "geometry": {
        "type": "Point",
        "coordinates": [
          14.4,
          52.533333
        ]
      },
      "type": "Feature",
      "properties": {
        "hierarchy": [
          "tgn:7121395",
          "tgn:7000096",
          "tgn:1000003",
          "tgn:7000084",
          "tgn:7029392"
        ],
        "placetype": [
          "aat:300000206"
        ],
        "id": 7121395,
        "name:xx": "Pismühle"
      }
    },
    {
      "geometry": {
        "type": "Point",
        "coordinates": [
          13.6,
          48.616667
        ]
      },
      "type": "Feature",
      "properties": {
        "hierarchy": [
          "tgn:7121396",
          "tgn:7003669",
          "tgn:1000003",
          "tgn:7000084",
          "tgn:7029392"
        ],
        "placetype": [
          "aat:300008347"
        ],
        "id": 7121396,
        "name:xx": "Pisling"
      }
    },
    {
      "geometry": {
        "type": "Point",
        "coordinates": [
          14.2,
          51.283333
        ]
      },
      "type": "Feature",
      "properties": {
        "hierarchy": [
          "tgn:7121397",
          "tgn:1000003",
          "tgn:7003685",
          "tgn:7000084",
          "tgn:7029392"
        ],
        "placetype": [
          "aat:300008347"
        ],
        "id": 7121397,
        "name:xx": "Piskowitz"
      }
    },
    {
      "geometry": {
        "type": "Point",
        "coordinates": [
          13.383333,
          51.2
        ]
      },
      "type": "Feature",
      "properties": {
        "hierarchy": [
          "tgn:7121398",
          "tgn:1000003",
          "tgn:7003685",
          "tgn:7000084",
          "tgn:7029392"
        ],
        "placetype": [
          "aat:300008347"
        ],
        "id": 7121398,
        "name:xx": "Piskowitz"
      }
    },
    {
      "geometry": {
        "type": "Point",
        "coordinates": [
          13.433333,
          51.1
        ]
      },
      "type": "Feature",
      "properties": {
        "hierarchy": [
          "tgn:7121399",
          "tgn:1000003",
          "tgn:7003685",
          "tgn:7000084",
          "tgn:7029392"
        ],
        "placetype": [
          "aat:300008347"
        ],
        "id": 7121399,
        "name:xx": "Piskowitz"
      }
    }
  ]
}
