{
  "geometry": {
    "type": "Point",
    "coordinates": [
      37.1833,
      -16.0333
    ]
  },
  "type": "Feature",
  "properties": {
    "hierarchy": [
      "tgn:1091522",
      "tgn:7001242",
      "tgn:1000955",
      "tgn:1000180",
      "tgn:7029392"
    ],
    "placetype": [
      "aat:300008347"
    ],
    "id": 1091522,
    "name:xx": "Errego"
  }
}
