{
  "type": "FeatureCollection",
  "features": [
    {
      "geometry": {
        "type": "Point",
        "coordinates": [
          -83.8333,
          34.9667
        ]
      },
      "type": "Feature",
      "properties": {
        "hierarchy": [
          "tgn:2267960",
          "tgn:1000001",
          "tgn:7012149",
          "tgn:2000430",
          "tgn:7007248",
          "tgn:7029392"
        ],
        "placetype": [
          "aat:300008706"
        ],
        "id": 2267960,
        "name:xx": "Crooked Creek"
      }
    },
    {
      "geometry": {
        "type": "Point",
        "coordinates": [
          -83.35,
          33.3667
        ]
      },
      "type": "Feature",
      "properties": {
        "hierarchy": [
          "tgn:2267961",
          "tgn:1000001",
          "tgn:7012149",
          "tgn:2000408",
          "tgn:7007248",
          "tgn:7029392"
        ],
        "placetype": [
          "aat:300008706"
        ],
        "id": 2267961,
        "name:xx": "Crooked Creek"
      }
    },
    {
      "geometry": {
        "type": "Point",
        "coordinates": [
          -81.4,
          31.2
        ]
      },
      "type": "Feature",
      "properties": {
        "hierarchy": [
          "tgn:2267962",
          "tgn:1000001",
          "tgn:7012149",
          "tgn:2000354",
          "tgn:7007248",
          "tgn:7029392"
        ],
        "placetype": [
          "aat:300008706"
        ],
        "id": 2267962,
        "name:xx": "Crooked Creek"
      }
    },
    {
      "geometry": {
        "type": "Point",
        "coordinates": [
          -83.4833,
          34.05
        ]
      },
      "type": "Feature",
      "properties": {
        "hierarchy": [
          "tgn:2267963",
          "tgn:1000001",
          "tgn:7012149",
          "tgn:2000369",
          "tgn:7007248",
          "tgn:7029392"
        ],
        "placetype": [
          "aat:300008706"
        ],
        "id": 2267963,
        "name:xx": "Crooked Creek"
      }
    },
    {
      "geometry": {
        "type": "Point",
        "coordinates": [
          -111.65,
          42.0167
        ]
      },
      "type": "Feature",
      "properties": {
        "hierarchy": [
          "tgn:2267964",
          "tgn:1000001",
          "tgn:7012149",
          "tgn:2000472",
          "tgn:7007250",
          "tgn:7029392"
        ],
        "placetype": [
          "aat:300008706"
        ],
        "id": 2267964,
        "name:xx": "Crooked Creek"
      }
    },
    {
      "geometry": {
        "type": "Point",
        "coordinates": [
          -111.1667,
          42.9167
        ]
      },
      "type": "Feature",
      "properties": {
        "hierarchy": [
          "tgn:2267965",
          "tgn:1000001",
          "tgn:2000466",
          "tgn:7012149",
          "tgn:7007250",
          "tgn:7029392"
        ],
        "placetype": [
          "aat:300008706"
        ],
        "id": 2267965,
        "name:xx": "Crooked Creek"
      }
    },
    {
      "geometry": {
        "type": "Point",
        "coordinates": [
          -115.6333,
          43.3
        ]
      },
      "type": "Feature",
      "properties": {
        "hierarchy": [
          "tgn:2267966",
          "tgn:1000001",
          "tgn:7012149",
          "tgn:2000471",
          "tgn:7007250",
          "tgn:7029392"
        ],
        "placetype": [
          "aat:300008706"
        ],
        "id": 2267966,
        "name:xx": "Crooked Creek"
      }
    },
    {
      "geometry": {
        "type": "Point",
        "coordinates": [
          -111.3167,
          44.5833
        ]
      },
      "type": "Feature",
      "properties": {
        "hierarchy": [
          "tgn:2267967",
          "tgn:1000001",
          "tgn:7012149",
          "tgn:2000473",
          "tgn:7007250",
          "tgn:7029392"
        ],
        "placetype": [
          "aat:300008706"
        ],
        "id": 2267967,
        "name:xx": "Crooked Creek"
      }
    },
    {
      "geometry": {
        "type": "Point",
        "coordinates": [
          -115.0667,
          44.2
        ]
      },
      "type": "Feature",
      "properties": {
        "hierarchy": [
          "tgn:2267968",
          "tgn:1000001",
          "tgn:2000470",
          "tgn:7012149",
          "tgn:7007250",
          "tgn:7029392"
        ],
        "placetype": [
          "aat:300008706"
        ],
        "id": 2267968,
        "name:xx": "Crooked Creek"
      }
    },
    {
      "geometry": {
        "type": "Point",
        "coordinates": [
          -111.35,
          43.7833
        ]
      },
      "type": "Feature",
      "properties": {
        "hierarchy": [
          "tgn:2267969",
          "tgn:1000001",
          "tgn:7012149",
          "tgn:7007250",
          "tgn:7029392"
        ],
        "placetype": [
          "aat:300008706"
        ],
        "id": 2267969,
        "name:xx": "Crooked Creek"
      }
    }
  ]
}
