{
  "geometry": {
    "type": "Point",
    "coordinates": [
      -94.6667,
      43.4833
    ]
  },
  "type": "Feature",
  "properties": {
    "hierarchy": [
      "tgn:2174204",
      "tgn:1000001",
      "tgn:2000592",
      "tgn:7012149",
      "tgn:7007253",
      "tgn:7029392"
    ],
    "placetype": [
      "aat:300008680"
    ],
    "id": 2174204,
    "name:xx": "Birge Lake"
  }
}
