{
  "geometry": {
    "type": "Point",
    "coordinates": [
      -93.4667,
      41.3667
    ]
  },
  "type": "Feature",
  "properties": {
    "hierarchy": [
      "tgn:2034237",
      "tgn:1000001",
      "tgn:7012149",
      "tgn:2000651",
      "tgn:7007253",
      "tgn:7029392"
    ],
    "placetype": [
      "aat:300008347"
    ],
    "id": 2034237,
    "name:xx": "Ackworth"
  }
}
