{
  "type": "FeatureCollection",
  "features": [
    {
      "geometry": {
        "type": "Point",
        "coordinates": [
          123.1333,
          12.95
        ]
      },
      "type": "Feature",
      "properties": {
        "hierarchy": [
          "tgn:1006642",
          "tgn:1000004",
          "tgn:1001419",
          "tgn:1000135",
          "tgn:7029392"
        ],
        "placetype": [
          "aat:300008791"
        ],
        "id": 1006642,
        "name:xx": "Burias Island"
      }
    },
    {
      "geometry": {
        "type": "Point",
        "coordinates": [
          -105,
          -73
        ]
      },
      "type": "Feature",
      "properties": {
        "hierarchy": [
          "tgn:1006643",
          "tgn:1000007",
          "tgn:7029392"
        ],
        "placetype": [
          "aat:300008791"
        ],
        "id": 1006643,
        "name:xx": "Burke Island"
      }
    },
    {
      "geometry": {
        "type": "Point",
        "coordinates": [
          -74.8333,
          40.0833
        ]
      },
      "type": "Feature",
      "properties": {
        "hierarchy": [
          "tgn:1006644",
          "tgn:1002215",
          "tgn:1000001",
          "tgn:7012149",
          "tgn:7007565",
          "tgn:7029392"
        ],
        "placetype": [
          "aat:300008791"
        ],
        "id": 1006644,
        "name:xx": "Burlington Island"
      }
    },
    {
      "geometry": {
        "type": "Point",
        "coordinates": [
          -131.3,
          52.4167
        ]
      },
      "type": "Feature",
      "properties": {
        "hierarchy": [
          "tgn:1006645",
          "tgn:7005735",
          "tgn:7005685",
          "tgn:1000001",
          "tgn:1010228",
          "tgn:7029392"
        ],
        "placetype": [
          "aat:300008791"
        ],
        "id": 1006645,
        "name:xx": "Burnaby Island"
      }
    },
    {
      "geometry": {
        "type": "Point",
        "coordinates": [
          0.6833,
          51.4167
        ]
      },
      "type": "Feature",
      "properties": {
        "hierarchy": [
          "tgn:1006646",
          "tgn:7002445",
          "tgn:1000003",
          "tgn:7008153",
          "tgn:7008591",
          "tgn:7029392"
        ],
        "placetype": [
          "aat:300008791"
        ],
        "id": 1006646,
        "name:xx": "Burntwick Island"
      }
    },
    {
      "geometry": {
        "type": "Point",
        "coordinates": [
          -2.9,
          58.85
        ]
      },
      "type": "Feature",
      "properties": {
        "hierarchy": [
          "tgn:1006647",
          "tgn:7002444",
          "tgn:1000003",
          "tgn:7009907",
          "tgn:7008591",
          "tgn:7029392"
        ],
        "placetype": [
          "aat:300008791"
        ],
        "name:en": "Burray",
        "id": 1006647
      }
    },
    {
      "geometry": {
        "type": "Point",
        "coordinates": [
          -122.7,
          48.4667
        ]
      },
      "type": "Feature",
      "properties": {
        "hierarchy": [
          "tgn:1006648",
          "tgn:1000001",
          "tgn:7012149",
          "tgn:7014510",
          "tgn:7007920",
          "tgn:7029392"
        ],
        "placetype": [
          "aat:300008791"
        ],
        "id": 1006648,
        "name:xx": "Burrows Island"
      }
    },
    {
      "geometry": {
        "type": "Point",
        "coordinates": [
          -4.312778,
          51.609167
        ]
      },
      "type": "Feature",
      "properties": {
        "hierarchy": [
          "tgn:1006649",
          "tgn:7002443",
          "tgn:1000003",
          "tgn:7018973",
          "tgn:7008591",
          "tgn:7029392"
        ],
        "placetype": [
          "aat:300008791"
        ],
        "name:en": "Burry Holms",
        "id": 1006649
      }
    }
  ]
}
