{
  "geometry": {
    "type": "Point",
    "coordinates": [
      -107.4167,
      48.5333
    ]
  },
  "type": "Feature",
  "properties": {
    "hierarchy": [
      "tgn:2768521",
      "tgn:1000001",
      "tgn:7012149",
      "tgn:2001295",
      "tgn:7007524",
      "tgn:7029392"
    ],
    "placetype": [
      "aat:300008706"
    ],
    "id": 2768521,
    "name:xx": "Whitewater Creek"
  }
}
