{
  "geometry": {
    "type": "Point",
    "coordinates": [
      -98.0333,
      28.8167
    ]
  },
  "type": "Feature",
  "properties": {
    "hierarchy": [
      "tgn:2103505",
      "tgn:1000001",
      "tgn:7012149",
      "tgn:1002533",
      "tgn:7007826",
      "tgn:7029392"
    ],
    "placetype": [
      "aat:300008347"
    ],
    "id": 2103505,
    "name:xx": "Coy City"
  }
}
