{
  "geometry": {
    "type": "Point",
    "coordinates": [
      17.0167,
      50.6167
    ]
  },
  "type": "Feature",
  "properties": {
    "hierarchy": [
      "tgn:1049649",
      "tgn:7024123",
      "tgn:1000003",
      "tgn:7006366",
      "tgn:7029392"
    ],
    "placetype": [
      "aat:300008347"
    ],
    "id": 1049649,
    "name:xx": "ZieÌœbice"
  }
}
