{
  "geometry": {
    "type": "Point",
    "coordinates": [
      -77.2167,
      37.3333
    ]
  },
  "type": "Feature",
  "properties": {
    "hierarchy": [
      "tgn:2437157",
      "tgn:1000001",
      "tgn:1002257",
      "tgn:7012149",
      "tgn:7007919",
      "tgn:7029392"
    ],
    "placetype": [
      "aat:300008798"
    ],
    "id": 2437157,
    "name:xx": "Kimages Hill"
  }
}
