{
  "geometry": {
    "type": "Point",
    "coordinates": [
      -103.4167,
      43.8167
    ]
  },
  "type": "Feature",
  "properties": {
    "hierarchy": [
      "tgn:2781578",
      "tgn:1000001",
      "tgn:2001786",
      "tgn:7012149",
      "tgn:7007713",
      "tgn:7029392"
    ],
    "placetype": [
      "aat:300266640"
    ],
    "id": 2781578,
    "name:xx": "Woodpecker Ridge"
  }
}
