{
  "geometry": {
    "type": "Point",
    "coordinates": [
      -96.8333,
      29.9333
    ]
  },
  "type": "Feature",
  "properties": {
    "hierarchy": [
      "tgn:2181139",
      "tgn:1000001",
      "tgn:7012149",
      "tgn:1002374",
      "tgn:7007826",
      "tgn:7029392"
    ],
    "placetype": [
      "aat:300008699"
    ],
    "id": 2181139,
    "name:xx": "Blue Branch"
  }
}
