{
  "geometry": {
    "type": "Point",
    "coordinates": [
      4.6667,
      47.9167
    ]
  },
  "type": "Feature",
  "properties": {
    "hierarchy": [
      "tgn:1032332",
      "tgn:1000003",
      "tgn:7002875",
      "tgn:1000070",
      "tgn:7029392"
    ],
    "placetype": [
      "aat:300008347"
    ],
    "id": 1032332,
    "name:xx": "Brion-sur-Ource"
  }
}
