{
  "geometry": {
    "type": "Point",
    "coordinates": [
      -98.9667,
      28.3333
    ]
  },
  "type": "Feature",
  "properties": {
    "hierarchy": [
      "tgn:2645232",
      "tgn:1000001",
      "tgn:7012149",
      "tgn:2002027",
      "tgn:7007826",
      "tgn:7029392"
    ],
    "placetype": [
      "aat:300008706"
    ],
    "id": 2645232,
    "name:xx": "Sauz Creek"
  }
}
