{
  "geometry": {
    "type": "Point",
    "coordinates": [
      102.08,
      49.05
    ]
  },
  "type": "Feature",
  "properties": {
    "hierarchy": [
      "tgn:1083043",
      "tgn:1001163",
      "tgn:1000004",
      "tgn:7029379",
      "tgn:7029392"
    ],
    "placetype": [
      "aat:300008347"
    ],
    "id": 1083043,
    "name:xx": "Sharga"
  }
}
