{
  "type": "FeatureCollection",
  "features": [
    {
      "geometry": {
        "type": "Point",
        "coordinates": [
          4.7,
          52.616667
        ]
      },
      "type": "Feature",
      "properties": {
        "hierarchy": [
          "tgn:7266850",
          "tgn:1000003",
          "tgn:7006951",
          "tgn:7016845",
          "tgn:7029392"
        ],
        "placetype": [
          "aat:300008699"
        ],
        "name:nl": "Hoevervaart",
        "id": 7266850
      }
    },
    {
      "geometry": {
        "type": "Point",
        "coordinates": [
          4.816667,
          51.616667
        ]
      },
      "type": "Feature",
      "properties": {
        "hierarchy": [
          "tgn:7266851",
          "tgn:1000003",
          "tgn:7003624",
          "tgn:7016845",
          "tgn:7029392"
        ],
        "placetype": [
          "aat:300008347"
        ],
        "name:nl": "Hoeveneind",
        "id": 7266851
      }
    },
    {
      "geometry": {
        "type": "Point",
        "coordinates": [
          5.633333,
          51.666667
        ]
      },
      "type": "Feature",
      "properties": {
        "hierarchy": [
          "tgn:7266853",
          "tgn:1000003",
          "tgn:7003624",
          "tgn:7016845",
          "tgn:7029392"
        ],
        "placetype": [
          "aat:300008347"
        ],
        "name:nl": "Hoeven",
        "id": 7266853
      }
    },
    {
      "geometry": {
        "type": "Point",
        "coordinates": [
          5.816667,
          51.65
        ]
      },
      "type": "Feature",
      "properties": {
        "hierarchy": [
          "tgn:7266854",
          "tgn:1000003",
          "tgn:7003624",
          "tgn:7016845",
          "tgn:7029392"
        ],
        "placetype": [
          "aat:300008347"
        ],
        "name:nl": "Hoeven",
        "id": 7266854
      }
    },
    {
      "geometry": {
        "type": "Point",
        "coordinates": [
          4.583333,
          51.583333
        ]
      },
      "type": "Feature",
      "properties": {
        "hierarchy": [
          "tgn:7266855",
          "tgn:1000003",
          "tgn:7003624",
          "tgn:7016845",
          "tgn:7029392"
        ],
        "placetype": [
          "aat:300008347"
        ],
        "name:nl": "Hoeven",
        "id": 7266855
      }
    },
    {
      "geometry": {
        "type": "Point",
        "coordinates": [
          5.8,
          51.5
        ]
      },
      "type": "Feature",
      "properties": {
        "hierarchy": [
          "tgn:7266856",
          "tgn:1000003",
          "tgn:7003624",
          "tgn:7016845",
          "tgn:7029392"
        ],
        "placetype": [
          "aat:300008347"
        ],
        "name:nl": "Hoeven",
        "id": 7266856
      }
    },
    {
      "geometry": {
        "type": "Point",
        "coordinates": [
          5.45,
          51.5
        ]
      },
      "type": "Feature",
      "properties": {
        "hierarchy": [
          "tgn:7266857",
          "tgn:1000003",
          "tgn:7003624",
          "tgn:7016845",
          "tgn:7029392"
        ],
        "placetype": [
          "aat:300008347"
        ],
        "name:nl": "Hoeven",
        "id": 7266857
      }
    },
    {
      "geometry": {
        "type": "Point",
        "coordinates": [
          5.516667,
          52.166667
        ]
      },
      "type": "Feature",
      "properties": {
        "hierarchy": [
          "tgn:7266858",
          "tgn:7003619",
          "tgn:1000003",
          "tgn:7016845",
          "tgn:7029392"
        ],
        "placetype": [
          "aat:300008699"
        ],
        "name:nl": "Hoevelakensche Beek",
        "id": 7266858
      }
    }
  ]
}
