{
  "geometry": {
    "type": "Point",
    "coordinates": [
      -110.7833,
      43.7833
    ]
  },
  "type": "Feature",
  "properties": {
    "hierarchy": [
      "tgn:2396017",
      "tgn:1000001",
      "tgn:7012149",
      "tgn:2002384",
      "tgn:7007923",
      "tgn:7029392"
    ],
    "placetype": [
      "aat:300008680"
    ],
    "id": 2396017,
    "name:xx": "Holly Lake"
  }
}
