{
  "geometry": {
    "type": "Point",
    "coordinates": [
      -105.4667,
      40.1833
    ]
  },
  "type": "Feature",
  "properties": {
    "hierarchy": [
      "tgn:2583961",
      "tgn:1000001",
      "tgn:2000198",
      "tgn:7012149",
      "tgn:7007158",
      "tgn:7029392"
    ],
    "placetype": [
      "aat:300008347"
    ],
    "id": 2583961,
    "name:xx": "Pine Valley"
  }
}
