{
  "type": "FeatureCollection",
  "features": [
    {
      "geometry": {
        "type": "Point",
        "coordinates": [
          -106.1667,
          39.8167
        ]
      },
      "type": "Feature",
      "properties": {
        "hierarchy": [
          "tgn:2318740",
          "tgn:1000001",
          "tgn:7012149",
          "tgn:7007158",
          "tgn:2000250",
          "tgn:7029392"
        ],
        "placetype": [
          "aat:300008761"
        ],
        "id": 2318740,
        "name:xx": "Erwin Gulch"
      }
    },
    {
      "geometry": {
        "type": "Point",
        "coordinates": [
          -86.1833,
          34.9167
        ]
      },
      "type": "Feature",
      "properties": {
        "hierarchy": [
          "tgn:2318741",
          "tgn:7002659",
          "tgn:1000001",
          "tgn:7012149",
          "tgn:2000035",
          "tgn:7029392"
        ],
        "placetype": [
          "aat:300008761"
        ],
        "id": 2318741,
        "name:xx": "Erwin Hollow"
      }
    },
    {
      "geometry": {
        "type": "Point",
        "coordinates": [
          -83.15,
          38.3667
        ]
      },
      "type": "Feature",
      "properties": {
        "hierarchy": [
          "tgn:2318742",
          "tgn:1000001",
          "tgn:1002240",
          "tgn:7012149",
          "tgn:7007255",
          "tgn:7029392"
        ],
        "placetype": [
          "aat:300008761"
        ],
        "id": 2318742,
        "name:xx": "Erwin Hollow"
      }
    },
    {
      "geometry": {
        "type": "Point",
        "coordinates": [
          -77.0833,
          42.2167
        ]
      },
      "type": "Feature",
      "properties": {
        "hierarchy": [
          "tgn:2318743",
          "tgn:1000001",
          "tgn:7012149",
          "tgn:1002920",
          "tgn:7007568",
          "tgn:7029392"
        ],
        "placetype": [
          "aat:300008761"
        ],
        "id": 2318743,
        "name:xx": "Erwin Hollow"
      }
    },
    {
      "geometry": {
        "type": "Point",
        "coordinates": [
          -80.6333,
          40.3167
        ]
      },
      "type": "Feature",
      "properties": {
        "hierarchy": [
          "tgn:2318744",
          "tgn:1000001",
          "tgn:7012149",
          "tgn:1002519",
          "tgn:7007706",
          "tgn:7029392"
        ],
        "placetype": [
          "aat:300008761"
        ],
        "id": 2318744,
        "name:xx": "Erwin Hollow"
      }
    },
    {
      "geometry": {
        "type": "Point",
        "coordinates": [
          -82.7167,
          39.0833
        ]
      },
      "type": "Feature",
      "properties": {
        "hierarchy": [
          "tgn:2318745",
          "tgn:1000001",
          "tgn:7012149",
          "tgn:2001614",
          "tgn:7007706",
          "tgn:7029392"
        ],
        "placetype": [
          "aat:300008761"
        ],
        "id": 2318745,
        "name:xx": "Erwin Hollow"
      }
    },
    {
      "geometry": {
        "type": "Point",
        "coordinates": [
          -93.7333,
          33.9
        ]
      },
      "type": "Feature",
      "properties": {
        "hierarchy": [
          "tgn:2318746",
          "tgn:1000001",
          "tgn:7016172",
          "tgn:7012149",
          "tgn:2000133",
          "tgn:7029392"
        ],
        "placetype": [
          "aat:300006191"
        ],
        "id": 2318746,
        "name:xx": "Erwin Lake"
      }
    },
    {
      "geometry": {
        "type": "Point",
        "coordinates": [
          -83.2333,
          42.8
        ]
      },
      "type": "Feature",
      "properties": {
        "hierarchy": [
          "tgn:2318747",
          "tgn:1000001",
          "tgn:7012149",
          "tgn:1002737",
          "tgn:7007520",
          "tgn:7029392"
        ],
        "placetype": [
          "aat:300008680"
        ],
        "id": 2318747,
        "name:xx": "Erwin Lake"
      }
    },
    {
      "geometry": {
        "type": "Point",
        "coordinates": [
          -95.7,
          45.9667
        ]
      },
      "type": "Feature",
      "properties": {
        "hierarchy": [
          "tgn:2318748",
          "tgn:1000001",
          "tgn:2001019",
          "tgn:7012149",
          "tgn:7007521",
          "tgn:7029392"
        ],
        "placetype": [
          "aat:300008680"
        ],
        "id": 2318748,
        "name:xx": "Erwin Lake"
      }
    },
    {
      "geometry": {
        "type": "Point",
        "coordinates": [
          -80.0333,
          34.3333
        ]
      },
      "type": "Feature",
      "properties": {
        "hierarchy": [
          "tgn:2318749",
          "tgn:1000001",
          "tgn:2001740",
          "tgn:7012149",
          "tgn:7007712",
          "tgn:7029392"
        ],
        "placetype": [
          "aat:300008347"
        ],
        "id": 2318749,
        "name:xx": "Erwin Park"
      }
    }
  ]
}
