{
  "geometry": {
    "type": "Point",
    "coordinates": [
      -100.05,
      35.9667
    ]
  },
  "type": "Feature",
  "properties": {
    "hierarchy": [
      "tgn:2554815",
      "tgn:1000001",
      "tgn:7012149",
      "tgn:7029392"
    ],
    "placetype": [
      "aat:300008706"
    ],
    "id": 2554815,
    "name:xx": "Oasis Creek"
  }
}
