{
  "geometry": {
    "type": "Point",
    "coordinates": [
      35.083333,
      24.45
    ]
  },
  "type": "Feature",
  "properties": {
    "hierarchy": [
      "tgn:7525182",
      "tgn:7001242",
      "tgn:7001311",
      "tgn:7016833",
      "tgn:7029392"
    ],
    "placetype": [
      "aat:300008805"
    ],
    "name:en": "Andîdabât, Plain of",
    "id": 7525182
  }
}
