{
  "geometry": {
    "type": "Point",
    "coordinates": [
      -76.3167,
      38.6833
    ]
  },
  "type": "Feature",
  "properties": {
    "hierarchy": [
      "tgn:2291293",
      "tgn:1000001",
      "tgn:2000939",
      "tgn:7012149",
      "tgn:7007516",
      "tgn:7029392"
    ],
    "placetype": [
      "aat:300132316"
    ],
    "id": 2291293,
    "name:xx": "Dogwood Harbor"
  }
}
