{
  "type": "FeatureCollection",
  "features": [
    {
      "geometry": {
        "type": "Point",
        "coordinates": [
          -3.616667,
          41.183333
        ]
      },
      "type": "Feature",
      "properties": {
        "hierarchy": [
          "tgn:7298100",
          "tgn:7002839",
          "tgn:7001158",
          "tgn:1000003",
          "tgn:1000095",
          "tgn:7029392"
        ],
        "placetype": [
          "aat:300008347"
        ],
        "id": 7298100,
        "name:xx": "Siguero"
      }
    },
    {
      "geometry": {
        "type": "Point",
        "coordinates": [
          -1.6,
          40.666667
        ]
      },
      "type": "Feature",
      "properties": {
        "hierarchy": [
          "tgn:7298101",
          "tgn:7002822",
          "tgn:1001647",
          "tgn:1000003",
          "tgn:1000095",
          "tgn:7029392"
        ],
        "placetype": [
          "aat:300259572"
        ],
        "id": 7298101,
        "name:xx": "Siguenza, Collado de"
      }
    },
    {
      "geometry": {
        "type": "Point",
        "coordinates": [
          -8.433333,
          42.966667
        ]
      },
      "type": "Feature",
      "properties": {
        "hierarchy": [
          "tgn:7298103",
          "tgn:7002824",
          "tgn:1000003",
          "tgn:7002786",
          "tgn:1000095",
          "tgn:7029392"
        ],
        "placetype": [
          "aat:300008347"
        ],
        "id": 7298103,
        "name:xx": "Sigüeiro"
      }
    },
    {
      "geometry": {
        "type": "Point",
        "coordinates": [
          -8.366667,
          43.283333
        ]
      },
      "type": "Feature",
      "properties": {
        "hierarchy": [
          "tgn:7298104",
          "tgn:7002824",
          "tgn:1000003",
          "tgn:7002786",
          "tgn:1000095",
          "tgn:7029392"
        ],
        "placetype": [
          "aat:300008347"
        ],
        "id": 7298104,
        "name:xx": "Sigrás de Arriba"
      }
    },
    {
      "geometry": {
        "type": "Point",
        "coordinates": [
          -8.366667,
          43.283333
        ]
      },
      "type": "Feature",
      "properties": {
        "hierarchy": [
          "tgn:7298105",
          "tgn:7002824",
          "tgn:1000003",
          "tgn:7002786",
          "tgn:1000095",
          "tgn:7029392"
        ],
        "placetype": [
          "aat:300008347"
        ],
        "id": 7298105,
        "name:xx": "Sigrás de Abajo"
      }
    },
    {
      "geometry": {
        "type": "Point",
        "coordinates": [
          -7.016667,
          43.016667
        ]
      },
      "type": "Feature",
      "properties": {
        "hierarchy": [
          "tgn:7298107",
          "tgn:7002829",
          "tgn:1000003",
          "tgn:7002786",
          "tgn:1000095",
          "tgn:7029392"
        ],
        "placetype": [
          "aat:300008347"
        ],
        "id": 7298107,
        "name:xx": "Signada"
      }
    },
    {
      "geometry": {
        "type": "Point",
        "coordinates": [
          -4.933333,
          40.8
        ]
      },
      "type": "Feature",
      "properties": {
        "hierarchy": [
          "tgn:7298108",
          "tgn:7002806",
          "tgn:7001158",
          "tgn:1000003",
          "tgn:1000095",
          "tgn:7029392"
        ],
        "placetype": [
          "aat:300008347"
        ],
        "id": 7298108,
        "name:xx": "Sigeres"
      }
    }
  ]
}
