{
  "geometry": {
    "type": "Point",
    "coordinates": [
      29.75,
      45.6833
    ]
  },
  "type": "Feature",
  "properties": {
    "hierarchy": [
      "tgn:1056445",
      "tgn:1000003",
      "tgn:1003396",
      "tgn:7006660",
      "tgn:7029392"
    ],
    "placetype": [
      "aat:300008347"
    ],
    "id": 1056445,
    "name:xx": "Lyman"
  }
}
