{
  "geometry": {
    "type": "Point",
    "coordinates": [
      20.8333,
      9.4333
    ]
  },
  "type": "Feature",
  "properties": {
    "hierarchy": [
      "tgn:1125372",
      "tgn:7001242",
      "tgn:1000155",
      "tgn:7029392"
    ],
    "placetype": [
      "aat:300008707"
    ],
    "id": 1125372,
    "name:xx": "Kameur"
  }
}
