{
  "geometry": {
    "type": "Point",
    "coordinates": [
      -84.6667,
      32.8667
    ]
  },
  "type": "Feature",
  "properties": {
    "hierarchy": [
      "tgn:2744961",
      "tgn:1000001",
      "tgn:7012149",
      "tgn:2000390",
      "tgn:7007248",
      "tgn:7029392"
    ],
    "placetype": [
      "aat:300055621"
    ],
    "id": 2744961,
    "name:xx": "View, The"
  }
}
