{
  "geometry": {
    "type": "Point",
    "coordinates": [
      120.5622,
      22.8832
    ]
  },
  "type": "Feature",
  "properties": {
    "hierarchy": [
      "tgn:7492593",
      "tgn:7001004",
      "tgn:1000004",
      "tgn:1000141",
      "tgn:7029392"
    ],
    "placetype": [
      "aat:300008347"
    ],
    "id": 7492593,
    "name:xx": "Shantang"
  }
}
