{
  "geometry": {
    "type": "Point",
    "coordinates": [
      -77.4333,
      42.35
    ]
  },
  "type": "Feature",
  "properties": {
    "hierarchy": [
      "tgn:2673397",
      "tgn:1000001",
      "tgn:7012149",
      "tgn:1002920",
      "tgn:7007568",
      "tgn:7029392"
    ],
    "placetype": [
      "aat:300008798"
    ],
    "id": 2673397,
    "name:xx": "Snell Hill"
  }
}
