{
  "geometry": {
    "type": "Point",
    "coordinates": [
      -80.2333,
      37.35
    ]
  },
  "type": "Feature",
  "properties": {
    "hierarchy": [
      "tgn:2783091",
      "tgn:1000001",
      "tgn:7012149",
      "tgn:7014344",
      "tgn:7007919",
      "tgn:7029392"
    ],
    "placetype": [
      "aat:300008699"
    ],
    "id": 2783091,
    "name:xx": "Wright Branch"
  }
}
