{
  "type": "FeatureCollection",
  "features": [
    {
      "geometry": {
        "type": "Point",
        "coordinates": [
          -159.35,
          22.0833
        ]
      },
      "type": "Feature",
      "properties": {
        "hierarchy": [
          "tgn:2025030",
          "tgn:1007657",
          "tgn:1002534",
          "tgn:1000001",
          "tgn:7012149",
          "tgn:7007249",
          "tgn:7029392"
        ],
        "placetype": [
          "aat:300008347"
        ],
        "id": 2025030,
        "name:xx": "Kapaa"
      }
    },
    {
      "geometry": {
        "type": "Point",
        "coordinates": [
          -155.8,
          20.2167
        ]
      },
      "type": "Feature",
      "properties": {
        "hierarchy": [
          "tgn:2025034",
          "tgn:7023902",
          "tgn:1000001",
          "tgn:7012149",
          "tgn:7007249",
          "tgn:7029392"
        ],
        "placetype": [
          "aat:300008347"
        ],
        "id": 2025034,
        "name:xx": "Kapaau"
      }
    },
    {
      "geometry": {
        "type": "Point",
        "coordinates": [
          -155.2,
          19.9667
        ]
      },
      "type": "Feature",
      "properties": {
        "hierarchy": [
          "tgn:2025038",
          "tgn:7023902",
          "tgn:1000001",
          "tgn:7012149",
          "tgn:7007249",
          "tgn:7029392"
        ],
        "placetype": [
          "aat:300008347"
        ],
        "id": 2025038,
        "name:xx": "Kapehu"
      }
    },
    {
      "geometry": {
        "type": "Point",
        "coordinates": [
          -154.8333,
          19.4833
        ]
      },
      "type": "Feature",
      "properties": {
        "hierarchy": [
          "tgn:2025039",
          "tgn:7023902",
          "tgn:1000001",
          "tgn:7012149",
          "tgn:7007249",
          "tgn:7029392"
        ],
        "placetype": [
          "aat:300008347"
        ],
        "id": 2025039,
        "name:xx": "Kapoho"
      }
    }
  ]
}
