{
  "geometry": {
    "type": "Point",
    "coordinates": [
      -81.35,
      27.2833
    ]
  },
  "type": "Feature",
  "properties": {
    "hierarchy": [
      "tgn:2573042",
      "tgn:1000001",
      "tgn:1002477",
      "tgn:7012149",
      "tgn:7007240",
      "tgn:7029392"
    ],
    "placetype": [
      "aat:300008680"
    ],
    "id": 2573042,
    "name:xx": "Pearl, Lake"
  }
}
