{
  "geometry": {
    "type": "Point",
    "coordinates": [
      25.0833,
      -28.9833
    ]
  },
  "type": "Feature",
  "properties": {
    "hierarchy": [
      "tgn:1093493",
      "tgn:7001242",
      "tgn:7016562",
      "tgn:1000193",
      "tgn:7029392"
    ],
    "placetype": [
      "aat:300008347"
    ],
    "id": 1093493,
    "name:xx": "Perdeberg"
  }
}
