{
  "geometry": {
    "type": "Point",
    "coordinates": [
      -90.75,
      39.2833
    ]
  },
  "type": "Feature",
  "properties": {
    "hierarchy": [
      "tgn:2278949",
      "tgn:1000001",
      "tgn:1002221",
      "tgn:7012149",
      "tgn:7007251",
      "tgn:7029392"
    ],
    "placetype": [
      "aat:300008791"
    ],
    "id": 2278949,
    "name:xx": "Dead Mans Island"
  }
}
