{
  "geometry": {
    "type": "Point",
    "coordinates": [
      -81.0167,
      36.4333
    ]
  },
  "type": "Feature",
  "properties": {
    "hierarchy": [
      "tgn:2074101",
      "tgn:2001465",
      "tgn:1000001",
      "tgn:7012149",
      "tgn:7007709",
      "tgn:7029392"
    ],
    "placetype": [
      "aat:300008347"
    ],
    "id": 2074101,
    "name:xx": "Cherry Lane"
  }
}
