{
  "geometry": {
    "type": "Point",
    "coordinates": [
      -111.8667,
      44.7167
    ]
  },
  "type": "Feature",
  "properties": {
    "hierarchy": [
      "tgn:2227769",
      "tgn:1000001",
      "tgn:2001260",
      "tgn:7012149",
      "tgn:7007524",
      "tgn:7029392"
    ],
    "placetype": [
      "aat:300008697"
    ],
    "id": 2227769,
    "name:xx": "Cayuse Spring"
  }
}
