{
  "geometry": {
    "type": "Point",
    "coordinates": [
      -105.4333,
      32.85
    ]
  },
  "type": "Feature",
  "properties": {
    "hierarchy": [
      "tgn:2782160",
      "tgn:1000001",
      "tgn:7012149",
      "tgn:2001447",
      "tgn:7007566",
      "tgn:7029392"
    ],
    "placetype": [
      "aat:300008761"
    ],
    "id": 2782160,
    "name:xx": "Woodson Canyon"
  }
}
