{
  "geometry": {
    "type": "Point",
    "coordinates": [
      -112.05,
      37.1833
    ]
  },
  "type": "Feature",
  "properties": {
    "hierarchy": [
      "tgn:2437263",
      "tgn:1000001",
      "tgn:7012149",
      "tgn:2002113",
      "tgn:7007827",
      "tgn:7029392"
    ],
    "placetype": [
      "aat:300008761"
    ],
    "id": 2437263,
    "name:xx": "Kimball Valley"
  }
}
