{
  "type": "FeatureCollection",
  "features": [
    {
      "geometry": {
        "type": "Point",
        "coordinates": [
          -98.9833,
          19.4
        ]
      },
      "type": "Feature",
      "properties": {
        "hierarchy": [
          "tgn:1135880",
          "tgn:1000001",
          "tgn:1001893",
          "tgn:7005560",
          "tgn:7029392"
        ],
        "placetype": [
          "aat:300006075"
        ],
        "id": 1135880,
        "name:xx": "Colorado"
      }
    },
    {
      "geometry": {
        "type": "Point",
        "coordinates": [
          -122,
          39.05
        ]
      },
      "type": "Feature",
      "properties": {
        "hierarchy": [
          "tgn:1135881",
          "tgn:1000001",
          "tgn:7012149",
          "tgn:1002296",
          "tgn:7007157",
          "tgn:7029392"
        ],
        "placetype": [
          "aat:300006075"
        ],
        "id": 1135881,
        "name:xx": "Colusa Trough"
      }
    },
    {
      "geometry": {
        "type": "Point",
        "coordinates": [
          -121.9,
          38
        ]
      },
      "type": "Feature",
      "properties": {
        "hierarchy": [
          "tgn:1135882",
          "tgn:1000001",
          "tgn:7012149",
          "tgn:1002298",
          "tgn:7007157",
          "tgn:7029392"
        ],
        "placetype": [
          "aat:300006075"
        ],
        "id": 1135882,
        "name:xx": "Contra Costa Canal"
      }
    },
    {
      "geometry": {
        "type": "Point",
        "coordinates": [
          4.65,
          43.6667
        ]
      },
      "type": "Feature",
      "properties": {
        "hierarchy": [
          "tgn:1135883",
          "tgn:1000003",
          "tgn:1000070",
          "tgn:7002895",
          "tgn:7029392"
        ],
        "placetype": [
          "aat:300006075"
        ],
        "id": 1135883,
        "name:xx": "Craponne, Canal de"
      }
    },
    {
      "geometry": {
        "type": "Point",
        "coordinates": [
          87.8167,
          23.25
        ]
      },
      "type": "Feature",
      "properties": {
        "hierarchy": [
          "tgn:1135884",
          "tgn:1000004",
          "tgn:7000198",
          "tgn:1001977",
          "tgn:7029392"
        ],
        "placetype": [
          "aat:300006075"
        ],
        "id": 1135884,
        "name:xx": "Dāmodar Main Canal"
      }
    },
    {
      "geometry": {
        "type": "Point",
        "coordinates": [
          119.5167,
          32.2
        ]
      },
      "type": "Feature",
      "properties": {
        "hierarchy": [
          "tgn:1135885",
          "tgn:1000004",
          "tgn:7002081",
          "tgn:1000111",
          "tgn:7029392"
        ],
        "placetype": [
          "aat:300006075"
        ],
        "id": 1135885,
        "name:xx": "Da Yunhe"
      }
    },
    {
      "geometry": {
        "type": "Point",
        "coordinates": [
          7.35,
          51.65
        ]
      },
      "type": "Feature",
      "properties": {
        "hierarchy": [
          "tgn:1135886",
          "tgn:1000003",
          "tgn:7003677",
          "tgn:7000084",
          "tgn:7029392"
        ],
        "placetype": [
          "aat:300006075"
        ],
        "id": 1135886,
        "name:xx": "Datteln-Hamm-Kanal"
      }
    },
    {
      "geometry": {
        "type": "Point",
        "coordinates": [
          -74.6167,
          40.4
        ]
      },
      "type": "Feature",
      "properties": {
        "hierarchy": [
          "tgn:1135887",
          "tgn:1000001",
          "tgn:7012149",
          "tgn:7007565",
          "tgn:7029392"
        ],
        "placetype": [
          "aat:300006075"
        ],
        "id": 1135887,
        "name:xx": "Delaware and Raritan Canal"
      }
    },
    {
      "geometry": {
        "type": "Point",
        "coordinates": [
          4.4167,
          51.9333
        ]
      },
      "type": "Feature",
      "properties": {
        "hierarchy": [
          "tgn:1135888",
          "tgn:1000003",
          "tgn:7016845",
          "tgn:7029392"
        ],
        "placetype": [
          "aat:300006075"
        ],
        "id": 1135888,
        "name:xx": "Delftsche Schie"
      }
    }
  ]
}
