{
  "geometry": {
    "type": "Point",
    "coordinates": [
      -82.4167,
      32.2333
    ]
  },
  "type": "Feature",
  "properties": {
    "hierarchy": [
      "tgn:2718560",
      "tgn:1000001",
      "tgn:7012149",
      "tgn:2000429",
      "tgn:7007248",
      "tgn:7029392"
    ],
    "placetype": [
      "aat:300008680"
    ],
    "id": 2718560,
    "name:xx": "Thompson Pond"
  }
}
