{
  "type": "FeatureCollection",
  "features": [
    {
      "geometry": {
        "type": "Point",
        "coordinates": [
          11.233333,
          44.366667
        ]
      },
      "type": "Feature",
      "properties": {
        "hierarchy": [
          "tgn:1129891",
          "tgn:7003127",
          "tgn:1000003",
          "tgn:7008516",
          "tgn:1000080",
          "tgn:7029392"
        ],
        "placetype": [
          "aat:300008707",
          "aat:300008699"
        ],
        "id": 1129891,
        "name:xx": "Setta"
      }
    },
    {
      "geometry": {
        "type": "Point",
        "coordinates": [
          -0.85,
          54.183333
        ]
      },
      "type": "Feature",
      "properties": {
        "hierarchy": [
          "tgn:1129896",
          "tgn:7002445",
          "tgn:1000003",
          "tgn:7008166",
          "tgn:7008591",
          "tgn:7029392"
        ],
        "placetype": [
          "aat:300008707",
          "aat:300008699"
        ],
        "name:en": "Seven",
        "id": 1129896
      }
    },
    {
      "geometry": {
        "type": "Point",
        "coordinates": [
          -2.636111,
          51.611667
        ]
      },
      "type": "Feature",
      "properties": {
        "hierarchy": [
          "tgn:1129899",
          "tgn:7008653",
          "tgn:1000003",
          "tgn:7008591",
          "tgn:7029392"
        ],
        "placetype": [
          "aat:300008707",
          "aat:300008699"
        ],
        "name:en": "Severn",
        "id": 1129899
      }
    }
  ]
}
