{
  "geometry": {
    "type": "Point",
    "coordinates": [
      -141.8667,
      62.0667
    ]
  },
  "type": "Feature",
  "properties": {
    "hierarchy": [
      "tgn:2318479",
      "tgn:7006450",
      "tgn:1000001",
      "tgn:7012149",
      "tgn:2000086",
      "tgn:7029392"
    ],
    "placetype": [
      "aat:300008761"
    ],
    "id": 2318479,
    "name:xx": "Erickson Gulch"
  }
}
