{
  "geometry": {
    "type": "Point",
    "coordinates": [
      -153.15,
      57.1833
    ]
  },
  "type": "Feature",
  "properties": {
    "hierarchy": [
      "tgn:2322865",
      "tgn:7006450",
      "tgn:1000001",
      "tgn:2124012",
      "tgn:7012149",
      "tgn:7029392"
    ],
    "placetype": [
      "aat:300008850"
    ],
    "id": 2322865,
    "name:xx": "Fang Point"
  }
}
