{
  "geometry": {
    "type": "Point",
    "coordinates": [
      -83.3667,
      42.5833
    ]
  },
  "type": "Feature",
  "properties": {
    "hierarchy": [
      "tgn:2229018",
      "tgn:1000001",
      "tgn:7012149",
      "tgn:1002737",
      "tgn:7007520",
      "tgn:7029392"
    ],
    "placetype": [
      "aat:300008791"
    ],
    "id": 2229018,
    "name:xx": "Cedar Island"
  }
}
