{
  "type": "FeatureCollection",
  "features": [
    {
      "geometry": {
        "type": "Point",
        "coordinates": [
          -86.6333,
          34.7833
        ]
      },
      "type": "Feature",
      "properties": {
        "hierarchy": [
          "tgn:2286430",
          "tgn:7002659",
          "tgn:1000001",
          "tgn:7012149",
          "tgn:2000044",
          "tgn:7029392"
        ],
        "placetype": [
          "aat:300008746"
        ],
        "id": 2286430,
        "name:xx": "Diamond Cave"
      }
    },
    {
      "geometry": {
        "type": "Point",
        "coordinates": [
          -93.2333,
          35.9833
        ]
      },
      "type": "Feature",
      "properties": {
        "hierarchy": [
          "tgn:2286431",
          "tgn:1000001",
          "tgn:7016172",
          "tgn:7012149",
          "tgn:2000155",
          "tgn:7029392"
        ],
        "placetype": [
          "aat:300008746"
        ],
        "id": 2286431,
        "name:xx": "Diamond Cave"
      }
    },
    {
      "geometry": {
        "type": "Point",
        "coordinates": [
          -104.6833,
          34.0167
        ]
      },
      "type": "Feature",
      "properties": {
        "hierarchy": [
          "tgn:2286432",
          "tgn:1000001",
          "tgn:7019560",
          "tgn:7012149",
          "tgn:7007566",
          "tgn:7029392"
        ],
        "placetype": [
          "aat:300008746"
        ],
        "id": 2286432,
        "name:xx": "Diamond Cave"
      }
    },
    {
      "geometry": {
        "type": "Point",
        "coordinates": [
          -77.5,
          40.7333
        ]
      },
      "type": "Feature",
      "properties": {
        "hierarchy": [
          "tgn:2286433",
          "tgn:1000001",
          "tgn:7012149",
          "tgn:1002669",
          "tgn:7007710",
          "tgn:7029392"
        ],
        "placetype": [
          "aat:300008746"
        ],
        "id": 2286433,
        "name:xx": "Diamond Cave"
      }
    },
    {
      "geometry": {
        "type": "Point",
        "coordinates": [
          -86.5833,
          36.2667
        ]
      },
      "type": "Feature",
      "properties": {
        "hierarchy": [
          "tgn:2286434",
          "tgn:1000001",
          "tgn:7012149",
          "tgn:2001919",
          "tgn:7007825",
          "tgn:7029392"
        ],
        "placetype": [
          "aat:300008746"
        ],
        "id": 2286434,
        "name:xx": "Diamond Cave"
      }
    },
    {
      "geometry": {
        "type": "Point",
        "coordinates": [
          -98.1,
          31.3667
        ]
      },
      "type": "Feature",
      "properties": {
        "hierarchy": [
          "tgn:2286435",
          "tgn:1000001",
          "tgn:7012149",
          "tgn:1002303",
          "tgn:7007826",
          "tgn:7029392"
        ],
        "placetype": [
          "aat:300008746"
        ],
        "id": 2286435,
        "name:xx": "Diamond Cave"
      }
    },
    {
      "geometry": {
        "type": "Point",
        "coordinates": [
          -86.05,
          37.1
        ]
      },
      "type": "Feature",
      "properties": {
        "hierarchy": [
          "tgn:2286436",
          "tgn:2000768",
          "tgn:1000001",
          "tgn:7012149",
          "tgn:7007255",
          "tgn:7029392"
        ],
        "placetype": [
          "aat:300008746"
        ],
        "id": 2286436,
        "name:xx": "Diamond Caverns"
      }
    },
    {
      "geometry": {
        "type": "Point",
        "coordinates": [
          -111.4167,
          46.5833
        ]
      },
      "type": "Feature",
      "properties": {
        "hierarchy": [
          "tgn:2286437",
          "tgn:1000001",
          "tgn:2001263",
          "tgn:7012149",
          "tgn:7007524",
          "tgn:7029392"
        ],
        "placetype": [
          "aat:300008347"
        ],
        "id": 2286437,
        "name:xx": "Diamond City"
      }
    },
    {
      "geometry": {
        "type": "Point",
        "coordinates": [
          -115.85,
          39.7333
        ]
      },
      "type": "Feature",
      "properties": {
        "hierarchy": [
          "tgn:2286438",
          "tgn:1000001",
          "tgn:2001413",
          "tgn:7012149",
          "tgn:7007526",
          "tgn:7029392"
        ],
        "placetype": [
          "aat:300008347"
        ],
        "id": 2286438,
        "name:xx": "Diamond City"
      }
    },
    {
      "geometry": {
        "type": "Point",
        "coordinates": [
          -103.6833,
          44.15
        ]
      },
      "type": "Feature",
      "properties": {
        "hierarchy": [
          "tgn:2286439",
          "tgn:1000001",
          "tgn:2001810",
          "tgn:7012149",
          "tgn:7007713",
          "tgn:7029392"
        ],
        "placetype": [
          "aat:300008347"
        ],
        "id": 2286439,
        "name:xx": "Diamond City"
      }
    }
  ]
}
