{
  "geometry": {
    "type": "Point",
    "coordinates": [
      48.4833,
      52.1833
    ]
  },
  "type": "Feature",
  "properties": {
    "hierarchy": [
      "tgn:1057803",
      "tgn:1000004",
      "tgn:1003408",
      "tgn:7018214",
      "tgn:7002435",
      "tgn:7029392"
    ],
    "placetype": [
      "aat:300008347"
    ],
    "id": 1057803,
    "name:xx": "Novozacharkino"
  }
}
