{
  "type": "FeatureCollection",
  "features": [
    {
      "geometry": {
        "type": "Point",
        "coordinates": [
          -117.65,
          34.2333
        ]
      },
      "type": "Feature",
      "properties": {
        "hierarchy": [
          "tgn:2012854",
          "tgn:1000001",
          "tgn:7012149",
          "tgn:7007157",
          "tgn:1002857",
          "tgn:7029392"
        ],
        "placetype": [
          "aat:300008347"
        ],
        "id": 2012854,
        "name:xx": "Mount Baldy"
      }
    },
    {
      "geometry": {
        "type": "Point",
        "coordinates": [
          -120.0333,
          37.5
        ]
      },
      "type": "Feature",
      "properties": {
        "hierarchy": [
          "tgn:2012855",
          "tgn:1000001",
          "tgn:7012149",
          "tgn:7007157",
          "tgn:7014004",
          "tgn:7029392"
        ],
        "placetype": [
          "aat:300008347"
        ],
        "id": 2012855,
        "name:xx": "Mount Bullion"
      }
    },
    {
      "geometry": {
        "type": "Point",
        "coordinates": [
          -122,
          41.7833
        ]
      },
      "type": "Feature",
      "properties": {
        "hierarchy": [
          "tgn:2012857",
          "tgn:1000001",
          "tgn:7012149",
          "tgn:7007157",
          "tgn:2000189",
          "tgn:7029392"
        ],
        "placetype": [
          "aat:300008347"
        ],
        "id": 2012857,
        "name:xx": "Mount Hebron"
      }
    },
    {
      "geometry": {
        "type": "Point",
        "coordinates": [
          -122.05,
          37.05
        ]
      },
      "type": "Feature",
      "properties": {
        "hierarchy": [
          "tgn:2012859",
          "tgn:1000001",
          "tgn:7012149",
          "tgn:7007157",
          "tgn:1002869",
          "tgn:7029392"
        ],
        "placetype": [
          "aat:300008347"
        ],
        "id": 2012859,
        "name:xx": "Mount Hermon"
      }
    }
  ]
}
