{
  "geometry": {
    "type": "Point",
    "coordinates": [
      -86.4333,
      34.0667
    ]
  },
  "type": "Feature",
  "properties": {
    "hierarchy": [
      "tgn:2216156",
      "tgn:7002659",
      "tgn:1000001",
      "tgn:2000004",
      "tgn:7012149",
      "tgn:7029392"
    ],
    "placetype": [
      "aat:300008699"
    ],
    "id": 2216156,
    "name:xx": "Camp Branch"
  }
}
