{
  "geometry": {
    "type": "Point",
    "coordinates": [
      -105.2333,
      35.2167
    ]
  },
  "type": "Feature",
  "properties": {
    "hierarchy": [
      "tgn:2274791",
      "tgn:1000001",
      "tgn:7012149",
      "tgn:2001453",
      "tgn:7007566",
      "tgn:7029392"
    ],
    "placetype": [
      "aat:300008761"
    ],
    "id": 2274791,
    "name:xx": "Damiana, Cañon de la"
  }
}
