{
  "geometry": {
    "type": "Point",
    "coordinates": [
      -101.7667,
      44.4167
    ]
  },
  "type": "Feature",
  "properties": {
    "hierarchy": [
      "tgn:2760413",
      "tgn:1000001",
      "tgn:2001797",
      "tgn:7012149",
      "tgn:7007713",
      "tgn:7029392"
    ],
    "placetype": [
      "aat:300008706"
    ],
    "id": 2760413,
    "name:xx": "West Fork Spotted Bear Creek"
  }
}
