{
  "geometry": {
    "type": "Point",
    "coordinates": [
      -74.85,
      40.75
    ]
  },
  "type": "Feature",
  "properties": {
    "hierarchy": [
      "tgn:2688624",
      "tgn:1000001",
      "tgn:1002493",
      "tgn:7012149",
      "tgn:7007565",
      "tgn:7029392"
    ],
    "placetype": [
      "aat:300008699"
    ],
    "id": 2688624,
    "name:xx": "Spruce Run"
  }
}
