{
  "geometry": {
    "type": "Point",
    "coordinates": [
      106.5833,
      20.25
    ]
  },
  "type": "Feature",
  "properties": {
    "hierarchy": [
      "tgn:1129038",
      "tgn:1000004",
      "tgn:7029392"
    ],
    "placetype": [
      "aat:300008707"
    ],
    "id": 1129038,
    "name:xx": "Song Koi"
  }
}
