{
  "geometry": {
    "type": "Point",
    "coordinates": [
      -112.1667,
      40.85
    ]
  },
  "type": "Feature",
  "properties": {
    "hierarchy": [
      "tgn:2134835",
      "tgn:1000001",
      "tgn:7012149",
      "tgn:7007827",
      "tgn:7029392"
    ],
    "placetype": [
      "aat:300132348"
    ],
    "id": 2134835,
    "name:xx": "Antelope Island Bar"
  }
}
