{
  "geometry": {
    "type": "Point",
    "coordinates": [
      -74.1167,
      41.7833
    ]
  },
  "type": "Feature",
  "properties": {
    "hierarchy": [
      "tgn:2370099",
      "tgn:1000001",
      "tgn:7012149",
      "tgn:1002961",
      "tgn:7007568",
      "tgn:7029392"
    ],
    "placetype": [
      "aat:300008798"
    ],
    "id": 2370099,
    "name:xx": "Guyot Hill"
  }
}
