{
  "geometry": {
    "type": "Point",
    "coordinates": [
      -90.6833,
      39.0333
    ]
  },
  "type": "Feature",
  "properties": {
    "hierarchy": [
      "tgn:2460177",
      "tgn:1000001",
      "tgn:1002221",
      "tgn:7012149",
      "tgn:7007251",
      "tgn:7029392"
    ],
    "placetype": [
      "aat:300008680"
    ],
    "id": 2460177,
    "name:xx": "Little Round Pond"
  }
}
