{
  "geometry": {
    "type": "Point",
    "coordinates": [
      -85.75,
      39.8833
    ]
  },
  "type": "Feature",
  "properties": {
    "hierarchy": [
      "tgn:2149487",
      "tgn:1000001",
      "tgn:7012149",
      "tgn:1002447",
      "tgn:7007252",
      "tgn:7029392"
    ],
    "placetype": [
      "aat:300006075"
    ],
    "id": 2149487,
    "name:xx": "Barrett Ditch"
  }
}
