{
  "geometry": {
    "type": "Point",
    "coordinates": [
      -86.4333,
      46.5333
    ]
  },
  "type": "Feature",
  "properties": {
    "hierarchy": [
      "tgn:2232620",
      "tgn:2000943",
      "tgn:1000001",
      "tgn:7012149",
      "tgn:7007520",
      "tgn:7029392"
    ],
    "placetype": [
      "aat:300008680"
    ],
    "id": 2232620,
    "name:xx": "Chapel Lake"
  }
}
