{
  "type": "FeatureCollection",
  "features": [
    {
      "geometry": {
        "type": "Point",
        "coordinates": [
          -134.15,
          56.1
        ]
      },
      "type": "Feature",
      "properties": {
        "hierarchy": [
          "tgn:2403800",
          "tgn:7006450",
          "tgn:1000001",
          "tgn:7012149",
          "tgn:2000088",
          "tgn:7029392"
        ],
        "placetype": [
          "aat:300008798"
        ],
        "id": 2403800,
        "name:xx": "Howard, Mount"
      }
    },
    {
      "geometry": {
        "type": "Point",
        "coordinates": [
          -117.1667,
          45.25
        ]
      },
      "type": "Feature",
      "properties": {
        "hierarchy": [
          "tgn:2403801",
          "tgn:1000001",
          "tgn:7012149",
          "tgn:2001722",
          "tgn:7007708",
          "tgn:7029392"
        ],
        "placetype": [
          "aat:300008798"
        ],
        "id": 2403801,
        "name:xx": "Howard, Mount"
      }
    },
    {
      "geometry": {
        "type": "Point",
        "coordinates": [
          -120.95,
          47.8
        ]
      },
      "type": "Feature",
      "properties": {
        "hierarchy": [
          "tgn:2403802",
          "tgn:1000001",
          "tgn:1002260",
          "tgn:7012149",
          "tgn:7007920",
          "tgn:7029392"
        ],
        "placetype": [
          "aat:300008798"
        ],
        "id": 2403802,
        "name:xx": "Howard, Mount"
      }
    },
    {
      "geometry": {
        "type": "Point",
        "coordinates": [
          -135.05,
          58.2833
        ]
      },
      "type": "Feature",
      "properties": {
        "hierarchy": [
          "tgn:2403803",
          "tgn:7006450",
          "tgn:1000001",
          "tgn:2124077",
          "tgn:7012149",
          "tgn:7029392"
        ],
        "placetype": [
          "aat:300008850"
        ],
        "id": 2403803,
        "name:xx": "Howard, Point"
      }
    },
    {
      "geometry": {
        "type": "Point",
        "coordinates": [
          -93.7833,
          30.7333
        ]
      },
      "type": "Feature",
      "properties": {
        "hierarchy": [
          "tgn:2403805",
          "tgn:1000001",
          "tgn:7012149",
          "tgn:2002047",
          "tgn:7007826",
          "tgn:7029392"
        ],
        "placetype": [
          "aat:300008347"
        ],
        "id": 2403805,
        "name:xx": "Howards"
      }
    },
    {
      "geometry": {
        "type": "Point",
        "coordinates": [
          -88.1,
          32.8
        ]
      },
      "type": "Feature",
      "properties": {
        "hierarchy": [
          "tgn:2403806",
          "tgn:7002659",
          "tgn:1000001",
          "tgn:7012149",
          "tgn:2000031",
          "tgn:7029392"
        ],
        "placetype": [
          "aat:300132348"
        ],
        "id": 2403806,
        "name:xx": "Howards Bar"
      }
    },
    {
      "geometry": {
        "type": "Point",
        "coordinates": [
          -95.15,
          43.4
        ]
      },
      "type": "Feature",
      "properties": {
        "hierarchy": [
          "tgn:2403807",
          "tgn:1000001",
          "tgn:2000590",
          "tgn:7012149",
          "tgn:7007253",
          "tgn:7029392"
        ],
        "placetype": [
          "aat:300132316"
        ],
        "id": 2403807,
        "name:xx": "Howards Bay"
      }
    },
    {
      "geometry": {
        "type": "Point",
        "coordinates": [
          -92.0833,
          46.7333
        ]
      },
      "type": "Feature",
      "properties": {
        "hierarchy": [
          "tgn:2403808",
          "tgn:1000001",
          "tgn:2002318",
          "tgn:7012149",
          "tgn:7007922",
          "tgn:7029392"
        ],
        "placetype": [
          "aat:300008678"
        ],
        "id": 2403808,
        "name:xx": "Howards Bay"
      }
    }
  ]
}
