{
  "geometry": {
    "type": "Point",
    "coordinates": [
      137.9833,
      -34.0833
    ]
  },
  "type": "Feature",
  "properties": {
    "hierarchy": [
      "tgn:7006236",
      "tgn:7000490",
      "tgn:1000006",
      "tgn:7001831",
      "tgn:7029392"
    ],
    "placetype": [
      "aat:300008347"
    ],
    "id": 7006236,
    "name:xx": "Melton"
  }
}
