{
  "geometry": {
    "type": "Point",
    "coordinates": [
      -88.8333,
      46.0333
    ]
  },
  "type": "Feature",
  "properties": {
    "hierarchy": [
      "tgn:2199065",
      "tgn:1000001",
      "tgn:7012149",
      "tgn:7029392"
    ],
    "placetype": [
      "aat:300008707"
    ],
    "id": 2199065,
    "name:xx": "Brule River"
  }
}
