{
  "geometry": {
    "type": "Point",
    "coordinates": [
      -86.8167,
      41.7333
    ]
  },
  "type": "Feature",
  "properties": {
    "hierarchy": [
      "tgn:2765770",
      "tgn:1000001",
      "tgn:7012149",
      "tgn:1002561",
      "tgn:7007252",
      "tgn:7029392"
    ],
    "placetype": [
      "aat:300006075"
    ],
    "id": 2765770,
    "name:xx": "White Ditch"
  }
}
