{
  "geometry": {
    "type": "Point",
    "coordinates": [
      31.201416,
      30.766052
    ]
  },
  "type": "Feature",
  "properties": {
    "hierarchy": [
      "tgn:7534250",
      "tgn:7001242",
      "tgn:7016833",
      "tgn:7001312",
      "tgn:7029392"
    ],
    "placetype": [
      "aat:300008347"
    ],
    "name:en": "Kafr Shubrā Qallūj",
    "id": 7534250
  }
}
