{
  "geometry": {
    "type": "Point",
    "coordinates": [
      74.833813,
      34.05204
    ]
  },
  "type": "Feature",
  "properties": {
    "hierarchy": [
      "tgn:7587988",
      "tgn:1000004",
      "tgn:7000198",
      "tgn:7000799",
      "tgn:7029392"
    ],
    "placetype": [
      "aat:300008347"
    ],
    "name:en": "Pādshāhibāgh",
    "id": 7587988
  }
}
