{
  "geometry": {
    "type": "Point",
    "coordinates": [
      -109.8833,
      31.4167
    ]
  },
  "type": "Feature",
  "properties": {
    "hierarchy": [
      "tgn:2485060",
      "tgn:1000001",
      "tgn:7006451",
      "tgn:2000091",
      "tgn:7012149",
      "tgn:7029392"
    ],
    "placetype": [
      "aat:300000390"
    ],
    "id": 2485060,
    "name:xx": "Lavender Open Pit Mine"
  }
}
