{
  "geometry": {
    "type": "Point",
    "coordinates": [
      31.45,
      29.833333
    ]
  },
  "type": "Feature",
  "properties": {
    "hierarchy": [
      "tgn:7525047",
      "tgn:7001242",
      "tgn:7016833",
      "tgn:1001083",
      "tgn:7029392"
    ],
    "placetype": [
      "aat:300379998"
    ],
    "name:en": "Dabāb, Wādī ad",
    "id": 7525047
  }
}
