{
  "geometry": {
    "type": "Point",
    "coordinates": [
      -70.9333,
      42.7167
    ]
  },
  "type": "Feature",
  "properties": {
    "hierarchy": [
      "tgn:2362975",
      "tgn:1000001",
      "tgn:1002359",
      "tgn:7012149",
      "tgn:7007517",
      "tgn:7029392"
    ],
    "placetype": [
      "aat:300008699"
    ],
    "id": 2362975,
    "name:xx": "Great Swamp Brook"
  }
}
