{
  "geometry": {
    "type": "Point",
    "coordinates": [
      10.05,
      54.45
    ]
  },
  "type": "Feature",
  "properties": {
    "hierarchy": [
      "tgn:7147718",
      "tgn:1000003",
      "tgn:7003688",
      "tgn:7000084",
      "tgn:7029392"
    ],
    "placetype": [
      "aat:300000206"
    ],
    "id": 7147718,
    "name:xx": "Kückenkorb"
  }
}
