{
  "type": "FeatureCollection",
  "features": [
    {
      "geometry": {
        "type": "Point",
        "coordinates": [
          -81.9667,
          33
        ]
      },
      "type": "Feature",
      "properties": {
        "hierarchy": [
          "tgn:2409530",
          "tgn:1000001",
          "tgn:2000308",
          "tgn:7012149",
          "tgn:7007248",
          "tgn:7029392"
        ],
        "placetype": [
          "aat:300008347"
        ],
        "id": 2409530,
        "name:xx": "Idlewood"
      }
    },
    {
      "geometry": {
        "type": "Point",
        "coordinates": [
          -89.95,
          30.0167
        ]
      },
      "type": "Feature",
      "properties": {
        "hierarchy": [
          "tgn:2409531",
          "tgn:1000001",
          "tgn:7012149",
          "tgn:2000889",
          "tgn:7007256",
          "tgn:7029392"
        ],
        "placetype": [
          "aat:300008347"
        ],
        "id": 2409531,
        "name:xx": "Idlewood"
      }
    },
    {
      "geometry": {
        "type": "Point",
        "coordinates": [
          -79.5167,
          34.7333
        ]
      },
      "type": "Feature",
      "properties": {
        "hierarchy": [
          "tgn:2409532",
          "tgn:1000001",
          "tgn:7012149",
          "tgn:2001539",
          "tgn:7007709",
          "tgn:7029392"
        ],
        "placetype": [
          "aat:300008347"
        ],
        "id": 2409532,
        "name:xx": "Idlewood"
      }
    },
    {
      "geometry": {
        "type": "Point",
        "coordinates": [
          -84.4667,
          39.1333
        ]
      },
      "type": "Feature",
      "properties": {
        "hierarchy": [
          "tgn:2409533",
          "tgn:1000001",
          "tgn:7012149",
          "tgn:1002441",
          "tgn:7007706",
          "tgn:7029392"
        ],
        "placetype": [
          "aat:300008347"
        ],
        "id": 2409533,
        "name:xx": "Idlewood"
      }
    },
    {
      "geometry": {
        "type": "Point",
        "coordinates": [
          -74.9333,
          40.15
        ]
      },
      "type": "Feature",
      "properties": {
        "hierarchy": [
          "tgn:2409534",
          "tgn:1000001",
          "tgn:1002213",
          "tgn:7012149",
          "tgn:7007710",
          "tgn:7029392"
        ],
        "placetype": [
          "aat:300008347"
        ],
        "id": 2409534,
        "name:xx": "Idlewood"
      }
    },
    {
      "geometry": {
        "type": "Point",
        "coordinates": [
          -82.1833,
          34.2333
        ]
      },
      "type": "Feature",
      "properties": {
        "hierarchy": [
          "tgn:2409535",
          "tgn:1000001",
          "tgn:2001748",
          "tgn:7012149",
          "tgn:7007712",
          "tgn:7029392"
        ],
        "placetype": [
          "aat:300008347"
        ],
        "id": 2409535,
        "name:xx": "Idlewood"
      }
    },
    {
      "geometry": {
        "type": "Point",
        "coordinates": [
          -80.3833,
          33.9167
        ]
      },
      "type": "Feature",
      "properties": {
        "hierarchy": [
          "tgn:2409536",
          "tgn:1000001",
          "tgn:7012149",
          "tgn:2001767",
          "tgn:7007712",
          "tgn:7029392"
        ],
        "placetype": [
          "aat:300008347"
        ],
        "id": 2409536,
        "name:xx": "Idlewood"
      }
    },
    {
      "geometry": {
        "type": "Point",
        "coordinates": [
          -80.6667,
          35.1333
        ]
      },
      "type": "Feature",
      "properties": {
        "hierarchy": [
          "tgn:2409537",
          "tgn:1000001",
          "tgn:7012149",
          "tgn:7014021",
          "tgn:7007709",
          "tgn:7029392"
        ],
        "placetype": [
          "aat:300008347"
        ],
        "id": 2409537,
        "name:xx": "Idlewood Acres"
      }
    },
    {
      "geometry": {
        "type": "Point",
        "coordinates": [
          -84,
          36.0167
        ]
      },
      "type": "Feature",
      "properties": {
        "hierarchy": [
          "tgn:2409538",
          "tgn:1000001",
          "tgn:7012149",
          "tgn:2001883",
          "tgn:7007825",
          "tgn:7029392"
        ],
        "placetype": [
          "aat:300008347"
        ],
        "id": 2409538,
        "name:xx": "Idlewood Acres"
      }
    },
    {
      "geometry": {
        "type": "Point",
        "coordinates": [
          -118.2667,
          34.1833
        ]
      },
      "type": "Feature",
      "properties": {
        "hierarchy": [
          "tgn:2409539",
          "tgn:1000001",
          "tgn:7012149",
          "tgn:7007157",
          "tgn:1002608",
          "tgn:7029392"
        ],
        "placetype": [
          "aat:300008761"
        ],
        "id": 2409539,
        "name:xx": "Idlewood Canyon"
      }
    }
  ]
}
