{
  "geometry": {
    "type": "Point",
    "coordinates": [
      74.36263,
      33.227646
    ]
  },
  "type": "Feature",
  "properties": {
    "hierarchy": [
      "tgn:7581061",
      "tgn:1000004",
      "tgn:7000198",
      "tgn:7000799",
      "tgn:7029392"
    ],
    "placetype": [
      "aat:300008347"
    ],
    "name:en": "Siāl Sūi",
    "id": 7581061
  }
}
