{
  "geometry": {
    "type": "Point",
    "coordinates": [
      -86.05,
      32.4833
    ]
  },
  "type": "Feature",
  "properties": {
    "hierarchy": [
      "tgn:2655444",
      "tgn:7002659",
      "tgn:1000001",
      "tgn:7012149",
      "tgn:2000025",
      "tgn:7029392"
    ],
    "placetype": [
      "aat:300008699"
    ],
    "id": 2655444,
    "name:xx": "Sharp Branch"
  }
}
