{
  "geometry": {
    "type": "Point",
    "coordinates": [
      -76.0333,
      38.1667
    ]
  },
  "type": "Feature",
  "properties": {
    "hierarchy": [
      "tgn:2362645",
      "tgn:1002338",
      "tgn:1000001",
      "tgn:7012149",
      "tgn:7007516",
      "tgn:7029392"
    ],
    "placetype": [
      "aat:300132316"
    ],
    "id": 2362645,
    "name:xx": "Great Cove Creek"
  }
}
