{
  "geometry": {
    "type": "Point",
    "coordinates": [
      -80.1167,
      36.8167
    ]
  },
  "type": "Feature",
  "properties": {
    "hierarchy": [
      "tgn:2363259",
      "tgn:1000001",
      "tgn:7012149",
      "tgn:2002179",
      "tgn:7007919",
      "tgn:7029392"
    ],
    "placetype": [
      "aat:300008699"
    ],
    "id": 2363259,
    "name:xx": "Green Branch"
  }
}
