{
  "type": "FeatureCollection",
  "features": [
    {
      "geometry": {
        "type": "Point",
        "coordinates": [
          -88.1167,
          37.5167
        ]
      },
      "type": "Feature",
      "properties": {
        "hierarchy": [
          "tgn:2028693",
          "tgn:1000001",
          "tgn:7012149",
          "tgn:2000509",
          "tgn:7007251",
          "tgn:7029392"
        ],
        "placetype": [
          "aat:300008347",
          "aat:300387210"
        ],
        "id": 2028693,
        "name:xx": "Lamb"
      }
    },
    {
      "geometry": {
        "type": "Point",
        "coordinates": [
          -89.2667,
          41.5167
        ]
      },
      "type": "Feature",
      "properties": {
        "hierarchy": [
          "tgn:2028695",
          "tgn:1000001",
          "tgn:2000497",
          "tgn:7012149",
          "tgn:7007251",
          "tgn:7029392"
        ],
        "placetype": [
          "aat:300008347"
        ],
        "id": 2028695,
        "name:xx": "La Moille"
      }
    },
    {
      "geometry": {
        "type": "Point",
        "coordinates": [
          -89.8333,
          42.1
        ]
      },
      "type": "Feature",
      "properties": {
        "hierarchy": [
          "tgn:2028697",
          "tgn:1000001",
          "tgn:2000498",
          "tgn:7012149",
          "tgn:7007251",
          "tgn:7029392"
        ],
        "placetype": [
          "aat:300008347"
        ],
        "id": 2028697,
        "name:xx": "Lanark"
      }
    },
    {
      "geometry": {
        "type": "Point",
        "coordinates": [
          -87.85,
          38.5333
        ]
      },
      "type": "Feature",
      "properties": {
        "hierarchy": [
          "tgn:2028698",
          "tgn:1000001",
          "tgn:7012149",
          "tgn:2000535",
          "tgn:7007251",
          "tgn:7029392"
        ],
        "placetype": [
          "aat:300008347"
        ],
        "id": 2028698,
        "name:xx": "Lancaster"
      }
    },
    {
      "geometry": {
        "type": "Point",
        "coordinates": [
          -87.8833,
          38.85
        ]
      },
      "type": "Feature",
      "properties": {
        "hierarchy": [
          "tgn:2028699",
          "tgn:1000001",
          "tgn:2000501",
          "tgn:7012149",
          "tgn:7007251",
          "tgn:7029392"
        ],
        "placetype": [
          "aat:300008347"
        ],
        "id": 2028699,
        "name:xx": "Landes"
      }
    }
  ]
}
