{
  "geometry": {
    "type": "Point",
    "coordinates": [
      -77.2833,
      41.0667
    ]
  },
  "type": "Feature",
  "properties": {
    "hierarchy": [
      "tgn:2629371",
      "tgn:1000001",
      "tgn:1002286",
      "tgn:7012149",
      "tgn:7007710",
      "tgn:7029392"
    ],
    "placetype": [
      "aat:300055621"
    ],
    "id": 2629371,
    "name:xx": "Rosecrans Bog Natural Area"
  }
}
