{
  "type": "FeatureCollection",
  "features": [
    {
      "geometry": {
        "type": "Point",
        "coordinates": [
          -87.65,
          36.8667
        ]
      },
      "type": "Feature",
      "properties": {
        "hierarchy": [
          "tgn:2039120",
          "tgn:1000001",
          "tgn:2000780",
          "tgn:7012149",
          "tgn:7007255",
          "tgn:7029392"
        ],
        "placetype": [
          "aat:300008347"
        ],
        "id": 2039120,
        "name:xx": "Gracey"
      }
    },
    {
      "geometry": {
        "type": "Point",
        "coordinates": [
          -85.4167,
          37.05
        ]
      },
      "type": "Feature",
      "properties": {
        "hierarchy": [
          "tgn:2039121",
          "tgn:2000765",
          "tgn:1000001",
          "tgn:7012149",
          "tgn:7007255",
          "tgn:7029392"
        ],
        "placetype": [
          "aat:300008347"
        ],
        "id": 2039121,
        "name:xx": "Gradyville"
      }
    },
    {
      "geometry": {
        "type": "Point",
        "coordinates": [
          -85,
          38.15
        ]
      },
      "type": "Feature",
      "properties": {
        "hierarchy": [
          "tgn:2039122",
          "tgn:1000001",
          "tgn:7012149",
          "tgn:1002887",
          "tgn:7007255",
          "tgn:7029392"
        ],
        "placetype": [
          "aat:300008347"
        ],
        "id": 2039122,
        "name:xx": "Graefenburg"
      }
    },
    {
      "geometry": {
        "type": "Point",
        "coordinates": [
          -87.5167,
          37.8167
        ]
      },
      "type": "Feature",
      "properties": {
        "hierarchy": [
          "tgn:2039125",
          "tgn:1000001",
          "tgn:7012149",
          "tgn:2000799",
          "tgn:7007255",
          "tgn:7029392"
        ],
        "placetype": [
          "aat:300008347"
        ],
        "id": 2039125,
        "name:xx": "Graham Hill"
      }
    },
    {
      "geometry": {
        "type": "Point",
        "coordinates": [
          -88.7667,
          37.1
        ]
      },
      "type": "Feature",
      "properties": {
        "hierarchy": [
          "tgn:2039126",
          "tgn:1000001",
          "tgn:7012149",
          "tgn:2000817",
          "tgn:7007255",
          "tgn:7029392"
        ],
        "placetype": [
          "aat:300008347"
        ],
        "id": 2039126,
        "name:xx": "Grahamville"
      }
    },
    {
      "geometry": {
        "type": "Point",
        "coordinates": [
          -83.0667,
          38.2833
        ]
      },
      "type": "Feature",
      "properties": {
        "hierarchy": [
          "tgn:2039127",
          "tgn:1000001",
          "tgn:1002240",
          "tgn:7012149",
          "tgn:7007255",
          "tgn:7029392"
        ],
        "placetype": [
          "aat:300008347"
        ],
        "id": 2039127,
        "name:xx": "Grahn"
      }
    },
    {
      "geometry": {
        "type": "Point",
        "coordinates": [
          -86.5333,
          37.3
        ]
      },
      "type": "Feature",
      "properties": {
        "hierarchy": [
          "tgn:2039128",
          "tgn:1000001",
          "tgn:2000775",
          "tgn:7012149",
          "tgn:7007255",
          "tgn:7029392"
        ],
        "placetype": [
          "aat:300008347",
          "aat:300387210"
        ],
        "id": 2039128,
        "name:xx": "Grancer"
      }
    },
    {
      "geometry": {
        "type": "Point",
        "coordinates": [
          -88.2333,
          37
        ]
      },
      "type": "Feature",
      "properties": {
        "hierarchy": [
          "tgn:2039129",
          "tgn:1000001",
          "tgn:7012149",
          "tgn:2000814",
          "tgn:7007255",
          "tgn:7029392"
        ],
        "placetype": [
          "aat:300008347"
        ],
        "id": 2039129,
        "name:xx": "Grand Rivers"
      }
    }
  ]
}
