{
  "geometry": {
    "type": "Point",
    "coordinates": [
      45.4167,
      57.3167
    ]
  },
  "type": "Feature",
  "properties": {
    "hierarchy": [
      "tgn:1051611",
      "tgn:1000004",
      "tgn:7011585",
      "tgn:7018214",
      "tgn:7002435",
      "tgn:7029392"
    ],
    "placetype": [
      "aat:300008347"
    ],
    "id": 1051611,
    "name:xx": "Shemanikha"
  }
}
