{
  "geometry": {
    "type": "Point",
    "coordinates": [
      -106.0167,
      45.6333
    ]
  },
  "type": "Feature",
  "properties": {
    "hierarchy": [
      "tgn:2497424",
      "tgn:1000001",
      "tgn:7012149",
      "tgn:2001297",
      "tgn:7007524",
      "tgn:7029392"
    ],
    "placetype": [
      "aat:300008706"
    ],
    "id": 2497424,
    "name:xx": "Maxwell Creek"
  }
}
