{
  "geometry": {
    "type": "Point",
    "coordinates": [
      -93.2833,
      33.8833
    ]
  },
  "type": "Feature",
  "properties": {
    "hierarchy": [
      "tgn:2158276",
      "tgn:1000001",
      "tgn:7016172",
      "tgn:7012149",
      "tgn:7029392"
    ],
    "placetype": [
      "aat:300008699"
    ],
    "id": 2158276,
    "name:xx": "Beaver Slough"
  }
}
