{
  "geometry": {
    "type": "Point",
    "coordinates": [
      15.5667,
      60.65
    ]
  },
  "type": "Feature",
  "properties": {
    "hierarchy": [
      "tgn:1062789",
      "tgn:1000403",
      "tgn:1000003",
      "tgn:1000097",
      "tgn:7029392"
    ],
    "placetype": [
      "aat:300008347"
    ],
    "id": 1062789,
    "name:xx": "Bäckehagen"
  }
}
