{
  "geometry": {
    "type": "Point",
    "coordinates": [
      -91.1333,
      45.2667
    ]
  },
  "type": "Feature",
  "properties": {
    "hierarchy": [
      "tgn:2757200",
      "tgn:1000001",
      "tgn:2002313",
      "tgn:7012149",
      "tgn:7007922",
      "tgn:7029392"
    ],
    "placetype": [
      "aat:300008680"
    ],
    "id": 2757200,
    "name:xx": "Wesley Lake"
  }
}
