{
  "geometry": {
    "type": "Point",
    "coordinates": [
      -78.531,
      -1.387
    ]
  },
  "type": "Feature",
  "properties": {
    "hierarchy": [
      "tgn:7593318",
      "tgn:1001582",
      "tgn:7002561",
      "tgn:1000051",
      "tgn:1000002",
      "tgn:7029392"
    ],
    "placetype": [
      "aat:300008347"
    ],
    "id": 7593318,
    "name:xx": "Huambaló"
  }
}
