{
  "geometry": {
    "type": "Point",
    "coordinates": [
      -106.2167,
      38.3167
    ]
  },
  "type": "Feature",
  "properties": {
    "hierarchy": [
      "tgn:2308462",
      "tgn:1000001",
      "tgn:7012149",
      "tgn:7007158",
      "tgn:2000246",
      "tgn:7029392"
    ],
    "placetype": [
      "aat:300008706"
    ],
    "id": 2308462,
    "name:xx": "East Middle Creek"
  }
}
