{
  "type": "FeatureCollection",
  "features": [
    {
      "geometry": {
        "type": "Point",
        "coordinates": [
          -98.55,
          25.733333
        ]
      },
      "type": "Feature",
      "properties": {
        "hierarchy": [
          "tgn:7363160",
          "tgn:1000001",
          "tgn:7005597",
          "tgn:7005560",
          "tgn:7029392"
        ],
        "placetype": [
          "aat:300008347"
        ],
        "id": 7363160,
        "name:xx": "El Mezquite"
      }
    },
    {
      "geometry": {
        "type": "Point",
        "coordinates": [
          -107.25,
          25.716667
        ]
      },
      "type": "Feature",
      "properties": {
        "hierarchy": [
          "tgn:7363161",
          "tgn:1000001",
          "tgn:7005595",
          "tgn:7005560",
          "tgn:7029392"
        ],
        "placetype": [
          "aat:300008347"
        ],
        "id": 7363161,
        "name:xx": "El Mezquite"
      }
    },
    {
      "geometry": {
        "type": "Point",
        "coordinates": [
          -108.1,
          25.7
        ]
      },
      "type": "Feature",
      "properties": {
        "hierarchy": [
          "tgn:7363162",
          "tgn:1000001",
          "tgn:7005595",
          "tgn:7005560",
          "tgn:7029392"
        ],
        "placetype": [
          "aat:300008347"
        ],
        "id": 7363162,
        "name:xx": "El Mezquite"
      }
    },
    {
      "geometry": {
        "type": "Point",
        "coordinates": [
          -107.866667,
          25.6
        ]
      },
      "type": "Feature",
      "properties": {
        "hierarchy": [
          "tgn:7363163",
          "tgn:1000001",
          "tgn:7005595",
          "tgn:7005560",
          "tgn:7029392"
        ],
        "placetype": [
          "aat:300008347"
        ],
        "id": 7363163,
        "name:xx": "El Mezquite"
      }
    },
    {
      "geometry": {
        "type": "Point",
        "coordinates": [
          -98.583333,
          25.266667
        ]
      },
      "type": "Feature",
      "properties": {
        "hierarchy": [
          "tgn:7363164",
          "tgn:1000001",
          "tgn:7005597",
          "tgn:7005560",
          "tgn:7029392"
        ],
        "placetype": [
          "aat:300008347"
        ],
        "id": 7363164,
        "name:xx": "El Mezquite"
      }
    },
    {
      "geometry": {
        "type": "Point",
        "coordinates": [
          -101.95,
          25.25
        ]
      },
      "type": "Feature",
      "properties": {
        "hierarchy": [
          "tgn:7363165",
          "tgn:1001853",
          "tgn:1000001",
          "tgn:7005560",
          "tgn:7029392"
        ],
        "placetype": [
          "aat:300008347"
        ],
        "id": 7363165,
        "name:xx": "El Mezquite"
      }
    },
    {
      "geometry": {
        "type": "Point",
        "coordinates": [
          -97.716667,
          25.05
        ]
      },
      "type": "Feature",
      "properties": {
        "hierarchy": [
          "tgn:7363166",
          "tgn:1000001",
          "tgn:7005597",
          "tgn:7005560",
          "tgn:7029392"
        ],
        "placetype": [
          "aat:300008347"
        ],
        "id": 7363166,
        "name:xx": "El Mezquite"
      }
    },
    {
      "geometry": {
        "type": "Point",
        "coordinates": [
          -97.566667,
          24.916667
        ]
      },
      "type": "Feature",
      "properties": {
        "hierarchy": [
          "tgn:7363167",
          "tgn:1000001",
          "tgn:7005597",
          "tgn:7005560",
          "tgn:7029392"
        ],
        "placetype": [
          "aat:300008347"
        ],
        "id": 7363167,
        "name:xx": "El Mezquite"
      }
    },
    {
      "geometry": {
        "type": "Point",
        "coordinates": [
          -101.25,
          24.9
        ]
      },
      "type": "Feature",
      "properties": {
        "hierarchy": [
          "tgn:7363168",
          "tgn:1001853",
          "tgn:1000001",
          "tgn:7005560",
          "tgn:7029392"
        ],
        "placetype": [
          "aat:300008347"
        ],
        "id": 7363168,
        "name:xx": "El Mezquite"
      }
    },
    {
      "geometry": {
        "type": "Point",
        "coordinates": [
          -102.75,
          23.533333
        ]
      },
      "type": "Feature",
      "properties": {
        "hierarchy": [
          "tgn:7363169",
          "tgn:1000001",
          "tgn:7005601",
          "tgn:7005560",
          "tgn:7029392"
        ],
        "placetype": [
          "aat:300008347"
        ],
        "id": 7363169,
        "name:xx": "El Mezquite"
      }
    }
  ]
}
