{
  "geometry": {
    "type": "Point",
    "coordinates": [
      -80.2333,
      34.8833
    ]
  },
  "type": "Feature",
  "properties": {
    "hierarchy": [
      "tgn:2633935",
      "tgn:2001466",
      "tgn:1000001",
      "tgn:7012149",
      "tgn:7007709",
      "tgn:7029392"
    ],
    "placetype": [
      "aat:300008699"
    ],
    "id": 2633935,
    "name:xx": "Rushing Branch"
  }
}
