{
  "geometry": {
    "type": "Point",
    "coordinates": [
      -51.3333,
      -1.75
    ]
  },
  "type": "Feature",
  "properties": {
    "hierarchy": [
      "tgn:1112780",
      "tgn:7006247",
      "tgn:1000047",
      "tgn:7002456",
      "tgn:1000002",
      "tgn:7029392"
    ],
    "placetype": [
      "aat:300132316"
    ],
    "id": 1112780,
    "name:xx": "Caxiuana, Baía de"
  }
}
