{
  "geometry": {
    "type": "Point",
    "coordinates": [
      -108.6167,
      34.0667
    ]
  },
  "type": "Feature",
  "properties": {
    "hierarchy": [
      "tgn:2377991",
      "tgn:1000001",
      "tgn:2001429",
      "tgn:7012149",
      "tgn:7007566",
      "tgn:7029392"
    ],
    "placetype": [
      "aat:300008761"
    ],
    "id": 2377991,
    "name:xx": "Harris Canyon"
  }
}
