{
  "geometry": {
    "type": "Point",
    "coordinates": [
      -135.8833,
      58.45
    ]
  },
  "type": "Feature",
  "properties": {
    "hierarchy": [
      "tgn:2149875",
      "tgn:7006450",
      "tgn:1000001",
      "tgn:7012149",
      "tgn:7019760",
      "tgn:7029392"
    ],
    "placetype": [
      "aat:300132316"
    ],
    "id": 2149875,
    "name:xx": "Bartlett Cove"
  }
}
