{
  "geometry": {
    "type": "Point",
    "coordinates": [
      -91.4667,
      30.7167
    ]
  },
  "type": "Feature",
  "properties": {
    "hierarchy": [
      "tgn:2637628",
      "tgn:1000001",
      "tgn:7012149",
      "tgn:2000892",
      "tgn:7007256",
      "tgn:7029392"
    ],
    "placetype": [
      "aat:300008791"
    ],
    "id": 2637628,
    "name:xx": "Saint Maurice Towhead"
  }
}
