{
  "geometry": {
    "type": "Point",
    "coordinates": [
      83.75,
      21.75
    ]
  },
  "type": "Feature",
  "properties": {
    "hierarchy": [
      "tgn:7001689",
      "tgn:1000004",
      "tgn:7000198",
      "tgn:7016694",
      "tgn:7029392"
    ],
    "placetype": [
      "aat:300006191"
    ],
    "name:en": "Hīrākūd Reservoir",
    "id": 7001689
  }
}
