{
  "geometry": {
    "type": "Point",
    "coordinates": [
      19.2667,
      5.0167
    ]
  },
  "type": "Feature",
  "properties": {
    "hierarchy": [
      "tgn:1089453",
      "tgn:7001242",
      "tgn:7016654",
      "tgn:1000159",
      "tgn:7029392"
    ],
    "placetype": [
      "aat:300008347"
    ],
    "id": 1089453,
    "name:xx": "Pandu"
  }
}
