{
  "geometry": {
    "type": "Point",
    "coordinates": [
      63.2333,
      33.7833
    ]
  },
  "type": "Feature",
  "properties": {
    "hierarchy": [
      "tgn:1065426",
      "tgn:7016612",
      "tgn:1000004",
      "tgn:1001249",
      "tgn:7029392"
    ],
    "placetype": [
      "aat:300008347"
    ],
    "id": 1065426,
    "name:xx": "Farsi"
  }
}
