{
  "geometry": {
    "type": "Point",
    "coordinates": [
      -83.55,
      37.3333
    ]
  },
  "type": "Feature",
  "properties": {
    "hierarchy": [
      "tgn:2690019",
      "tgn:1000001",
      "tgn:7012149",
      "tgn:2000835",
      "tgn:7007255",
      "tgn:7029392"
    ],
    "placetype": [
      "aat:300008699"
    ],
    "id": 2690019,
    "name:xx": "Stable Branch"
  }
}
