{
  "geometry": {
    "type": "Point",
    "coordinates": [
      -119.6333,
      47.9833
    ]
  },
  "type": "Feature",
  "properties": {
    "hierarchy": [
      "tgn:2633130",
      "tgn:1000001",
      "tgn:7012149",
      "tgn:7007920",
      "tgn:7029392"
    ],
    "placetype": [
      "aat:300006191"
    ],
    "id": 2633130,
    "name:xx": "Rufus Woods Lake"
  }
}
