{
  "geometry": {
    "type": "Point",
    "coordinates": [
      10.7333,
      53.9167
    ]
  },
  "type": "Feature",
  "properties": {
    "hierarchy": [
      "tgn:1005617",
      "tgn:1000003",
      "tgn:7003688",
      "tgn:7000084",
      "tgn:7029392"
    ],
    "placetype": [
      "aat:300000745"
    ],
    "id": 1005617,
    "name:xx": "Siems-Dänischburg"
  }
}
