{
  "geometry": {
    "type": "Point",
    "coordinates": [
      -95.7833,
      44.1667
    ]
  },
  "type": "Feature",
  "properties": {
    "hierarchy": [
      "tgn:2492436",
      "tgn:1000001",
      "tgn:7012149",
      "tgn:2001049",
      "tgn:7007521",
      "tgn:7029392"
    ],
    "placetype": [
      "aat:300008680"
    ],
    "id": 2492436,
    "name:xx": "Maria, Lake"
  }
}
