{
  "geometry": {
    "type": "Point",
    "coordinates": [
      -89.1333,
      43.2833
    ]
  },
  "type": "Feature",
  "properties": {
    "hierarchy": [
      "tgn:1126964",
      "tgn:1000001",
      "tgn:7012149",
      "tgn:7007922",
      "tgn:7029392"
    ],
    "placetype": [
      "aat:300008707"
    ],
    "id": 1126964,
    "name:xx": "Maunesha"
  }
}
