{
  "geometry": {
    "type": "Point",
    "coordinates": [
      -50.25,
      63.0167
    ]
  },
  "type": "Feature",
  "properties": {
    "hierarchy": [
      "tgn:7024507",
      "tgn:7593554",
      "tgn:1000001",
      "tgn:7024573",
      "tgn:7029392"
    ],
    "placetype": [
      "aat:300008791"
    ],
    "id": 7024507,
    "name:xx": "Qeqertaq"
  }
}
