{
  "geometry": {
    "type": "Point",
    "coordinates": [
      -92.65,
      45.8167
    ]
  },
  "type": "Feature",
  "properties": {
    "hierarchy": [
      "tgn:2740058",
      "tgn:1000001",
      "tgn:2002311",
      "tgn:7012149",
      "tgn:7007922",
      "tgn:7029392"
    ],
    "placetype": [
      "aat:300008905"
    ],
    "id": 2740058,
    "name:xx": "Upper Hay Creek Flowage"
  }
}
