{
  "geometry": {
    "type": "Point",
    "coordinates": [
      -115.5167,
      47.55
    ]
  },
  "type": "Feature",
  "properties": {
    "hierarchy": [
      "tgn:2349165",
      "tgn:1000001",
      "tgn:7012149",
      "tgn:2001304",
      "tgn:7007524",
      "tgn:7029392"
    ],
    "placetype": [
      "aat:300008761"
    ],
    "id": 2349165,
    "name:xx": "Gilbert Gulch"
  }
}
