{
  "geometry": {
    "type": "Point",
    "coordinates": [
      -109.4667,
      43.1667
    ]
  },
  "type": "Feature",
  "properties": {
    "hierarchy": [
      "tgn:2265830",
      "tgn:1000001",
      "tgn:7012149",
      "tgn:2002371",
      "tgn:7007923",
      "tgn:7029392"
    ],
    "placetype": [
      "aat:300008680"
    ],
    "id": 2265830,
    "name:xx": "Crater Lake"
  }
}
