{
  "geometry": {
    "type": "Point",
    "coordinates": [
      -85.4333,
      36.5667
    ]
  },
  "type": "Feature",
  "properties": {
    "hierarchy": [
      "tgn:2616735",
      "tgn:1000001",
      "tgn:7012149",
      "tgn:2001850",
      "tgn:7007825",
      "tgn:7029392"
    ],
    "placetype": [
      "aat:300008746"
    ],
    "id": 2616735,
    "name:xx": "Rich Cave"
  }
}
