{
  "geometry": {
    "type": "Point",
    "coordinates": [
      -97.95,
      29.4167
    ]
  },
  "type": "Feature",
  "properties": {
    "hierarchy": [
      "tgn:1133122",
      "tgn:1000001",
      "tgn:7012149",
      "tgn:7007826",
      "tgn:7029392"
    ],
    "placetype": [
      "aat:300008706"
    ],
    "id": 1133122,
    "name:xx": "Ecleto Creek"
  }
}
