{
  "type": "FeatureCollection",
  "features": [
    {
      "geometry": {
        "type": "Point",
        "coordinates": [
          -82.6,
          37.4333
        ]
      },
      "type": "Feature",
      "properties": {
        "hierarchy": [
          "tgn:2621980",
          "tgn:1000001",
          "tgn:7012149",
          "tgn:2000789",
          "tgn:7007255",
          "tgn:7029392"
        ],
        "placetype": [
          "aat:300008699"
        ],
        "id": 2621980,
        "name:xx": "Roberts Branch"
      }
    },
    {
      "geometry": {
        "type": "Point",
        "coordinates": [
          -82.7833,
          38.0667
        ]
      },
      "type": "Feature",
      "properties": {
        "hierarchy": [
          "tgn:2621981",
          "tgn:1000001",
          "tgn:7012149",
          "tgn:2000809",
          "tgn:7007255",
          "tgn:7029392"
        ],
        "placetype": [
          "aat:300008699"
        ],
        "id": 2621981,
        "name:xx": "Roberts Branch"
      }
    },
    {
      "geometry": {
        "type": "Point",
        "coordinates": [
          -83.4333,
          38.2
        ]
      },
      "type": "Feature",
      "properties": {
        "hierarchy": [
          "tgn:2621982",
          "tgn:1000001",
          "tgn:7012149",
          "tgn:1002837",
          "tgn:7007255",
          "tgn:7029392"
        ],
        "placetype": [
          "aat:300008699"
        ],
        "id": 2621982,
        "name:xx": "Roberts Branch"
      }
    },
    {
      "geometry": {
        "type": "Point",
        "coordinates": [
          -82.5,
          37.8833
        ]
      },
      "type": "Feature",
      "properties": {
        "hierarchy": [
          "tgn:2621983",
          "tgn:1000001",
          "tgn:7012149",
          "tgn:2000824",
          "tgn:7007255",
          "tgn:7029392"
        ],
        "placetype": [
          "aat:300008699"
        ],
        "id": 2621983,
        "name:xx": "Roberts Branch"
      }
    },
    {
      "geometry": {
        "type": "Point",
        "coordinates": [
          -93.9167,
          31.95
        ]
      },
      "type": "Feature",
      "properties": {
        "hierarchy": [
          "tgn:2621984",
          "tgn:1000001",
          "tgn:7020680",
          "tgn:7012149",
          "tgn:7007256",
          "tgn:7029392"
        ],
        "placetype": [
          "aat:300008699"
        ],
        "id": 2621984,
        "name:xx": "Roberts Branch"
      }
    },
    {
      "geometry": {
        "type": "Point",
        "coordinates": [
          -88.5833,
          34.15
        ]
      },
      "type": "Feature",
      "properties": {
        "hierarchy": [
          "tgn:2621985",
          "tgn:1000001",
          "tgn:7012149",
          "tgn:7007522",
          "tgn:7029392"
        ],
        "placetype": [
          "aat:300008699"
        ],
        "id": 2621985,
        "name:xx": "Roberts Branch"
      }
    },
    {
      "geometry": {
        "type": "Point",
        "coordinates": [
          -92.15,
          36.55
        ]
      },
      "type": "Feature",
      "properties": {
        "hierarchy": [
          "tgn:2621986",
          "tgn:1000001",
          "tgn:7012149",
          "tgn:2001226",
          "tgn:7007523",
          "tgn:7029392"
        ],
        "placetype": [
          "aat:300008699"
        ],
        "id": 2621986,
        "name:xx": "Roberts Branch"
      }
    },
    {
      "geometry": {
        "type": "Point",
        "coordinates": [
          -94.45,
          39.6167
        ]
      },
      "type": "Feature",
      "properties": {
        "hierarchy": [
          "tgn:2621987",
          "tgn:1000001",
          "tgn:7012149",
          "tgn:2001188",
          "tgn:7007523",
          "tgn:7029392"
        ],
        "placetype": [
          "aat:300008699"
        ],
        "id": 2621987,
        "name:xx": "Roberts Branch"
      }
    },
    {
      "geometry": {
        "type": "Point",
        "coordinates": [
          -93.05,
          38.3
        ]
      },
      "type": "Feature",
      "properties": {
        "hierarchy": [
          "tgn:2621988",
          "tgn:1000001",
          "tgn:7012149",
          "tgn:2001221",
          "tgn:7007523",
          "tgn:7029392"
        ],
        "placetype": [
          "aat:300008699"
        ],
        "id": 2621988,
        "name:xx": "Roberts Branch"
      }
    },
    {
      "geometry": {
        "type": "Point",
        "coordinates": [
          -74.6,
          39.8167
        ]
      },
      "type": "Feature",
      "properties": {
        "hierarchy": [
          "tgn:2621989",
          "tgn:1002215",
          "tgn:1000001",
          "tgn:7012149",
          "tgn:7007565",
          "tgn:7029392"
        ],
        "placetype": [
          "aat:300008699"
        ],
        "id": 2621989,
        "name:xx": "Roberts Branch"
      }
    }
  ]
}
