{
  "geometry": {
    "type": "Point",
    "coordinates": [
      -87.4833,
      32.4333
    ]
  },
  "type": "Feature",
  "properties": {
    "hierarchy": [
      "tgn:2712462",
      "tgn:7002659",
      "tgn:1000001",
      "tgn:7012149",
      "tgn:7029392"
    ],
    "placetype": [
      "aat:300008706"
    ],
    "id": 2712462,
    "name:xx": "Tayloe Creek"
  }
}
