{
  "type": "FeatureCollection",
  "features": [
    {
      "geometry": {
        "type": "Point",
        "coordinates": [
          103,
          33.5833
        ]
      },
      "type": "Feature",
      "properties": {
        "hierarchy": [
          "tgn:1109350",
          "tgn:1000004",
          "tgn:7002087",
          "tgn:1000111",
          "tgn:7029392"
        ],
        "placetype": [
          "aat:300008795"
        ],
        "id": 1109350,
        "name:xx": "Min Shan"
      }
    },
    {
      "geometry": {
        "type": "Point",
        "coordinates": [
          -89.6667,
          15.1667
        ]
      },
      "type": "Feature",
      "properties": {
        "hierarchy": [
          "tgn:1109351",
          "tgn:1000001",
          "tgn:7005493",
          "tgn:7029392"
        ],
        "placetype": [
          "aat:300008795"
        ],
        "id": 1109351,
        "name:xx": "Minas, Sierra de las"
      }
    },
    {
      "geometry": {
        "type": "Point",
        "coordinates": [
          121.4,
          15.4833
        ]
      },
      "type": "Feature",
      "properties": {
        "hierarchy": [
          "tgn:1109352",
          "tgn:1000004",
          "tgn:1001496",
          "tgn:1000135",
          "tgn:7029392"
        ],
        "placetype": [
          "aat:300008795"
        ],
        "id": 1109352,
        "name:xx": "Mingan Mountains"
      }
    },
    {
      "geometry": {
        "type": "Point",
        "coordinates": [
          138.3333,
          35.2333
        ]
      },
      "type": "Feature",
      "properties": {
        "hierarchy": [
          "tgn:1109353",
          "tgn:7000895",
          "tgn:1000004",
          "tgn:1000120",
          "tgn:7029392"
        ],
        "placetype": [
          "aat:300008795"
        ],
        "id": 1109353,
        "name:xx": "Minobu-sanchi"
      }
    },
    {
      "geometry": {
        "type": "Point",
        "coordinates": [
          -46.3333,
          -23.7833
        ]
      },
      "type": "Feature",
      "properties": {
        "hierarchy": [
          "tgn:1109356",
          "tgn:1001945",
          "tgn:1000047",
          "tgn:7002457",
          "tgn:1000002",
          "tgn:7029392"
        ],
        "placetype": [
          "aat:300008795"
        ],
        "id": 1109356,
        "name:xx": "Mogi, Serra do"
      }
    },
    {
      "geometry": {
        "type": "Point",
        "coordinates": [
          -108.5167,
          33.2167
        ]
      },
      "type": "Feature",
      "properties": {
        "hierarchy": [
          "tgn:1109357",
          "tgn:1000001",
          "tgn:7012149",
          "tgn:7007566",
          "tgn:7029392"
        ],
        "placetype": [
          "aat:300008795"
        ],
        "id": 1109357,
        "name:xx": "Mogollon Mountains"
      }
    },
    {
      "geometry": {
        "type": "Point",
        "coordinates": [
          -4,
          57.166667
        ]
      },
      "type": "Feature",
      "properties": {
        "hierarchy": [
          "tgn:1109359",
          "tgn:7002444",
          "tgn:1000003",
          "tgn:7008082",
          "tgn:7008591",
          "tgn:7029392"
        ],
        "placetype": [
          "aat:300008795"
        ],
        "name:en": "Monadhliath Mountains",
        "id": 1109359
      }
    }
  ]
}
