{
  "geometry": {
    "type": "Point",
    "coordinates": [
      13.6667,
      -9.15
    ]
  },
  "type": "Feature",
  "properties": {
    "hierarchy": [
      "tgn:1087720",
      "tgn:1000811",
      "tgn:7001242",
      "tgn:1000149",
      "tgn:7029392"
    ],
    "placetype": [
      "aat:300008347"
    ],
    "id": 1087720,
    "name:xx": "Catete"
  }
}
