{
  "geometry": {
    "type": "Point",
    "coordinates": [
      106.1667,
      10.6667
    ]
  },
  "type": "Feature",
  "properties": {
    "hierarchy": [
      "tgn:7001051",
      "tgn:1000004",
      "tgn:1000145",
      "tgn:7029392"
    ],
    "placetype": [
      "aat:300387064",
      "aat:300000774"
    ],
    "id": 7001051,
    "name:xx": "Long An, Tỉnh"
  }
}
