{
  "type": "FeatureCollection",
  "features": [
    {
      "geometry": {
        "type": "Point",
        "coordinates": [
          22.25,
          55.2167
        ]
      },
      "type": "Feature",
      "properties": {
        "hierarchy": [
          "tgn:1120860",
          "tgn:1000003",
          "tgn:7006611",
          "tgn:7006542",
          "tgn:7029392"
        ],
        "placetype": [
          "aat:300008707"
        ],
        "id": 1120860,
        "name:xx": "Šešuvis"
      }
    },
    {
      "geometry": {
        "type": "Point",
        "coordinates": [
          72.5167,
          49.9
        ]
      },
      "type": "Feature",
      "properties": {
        "hierarchy": [
          "tgn:1120865",
          "tgn:1000004",
          "tgn:7014786",
          "tgn:7029392"
        ],
        "placetype": [
          "aat:300008707"
        ],
        "id": 1120865,
        "name:xx": "Sherubay-Nura"
      }
    },
    {
      "geometry": {
        "type": "Point",
        "coordinates": [
          96.966,
          51.35
        ]
      },
      "type": "Feature",
      "properties": {
        "hierarchy": [
          "tgn:1120868",
          "tgn:1000004",
          "tgn:7029379",
          "tgn:7029392"
        ],
        "placetype": [
          "aat:300008707"
        ],
        "id": 1120868,
        "name:xx": "Šišchid"
      }
    },
    {
      "geometry": {
        "type": "Point",
        "coordinates": [
          52.3333,
          50.1667
        ]
      },
      "type": "Feature",
      "properties": {
        "hierarchy": [
          "tgn:1120869",
          "tgn:1000004",
          "tgn:7011457",
          "tgn:7014786",
          "tgn:7029392"
        ],
        "placetype": [
          "aat:300008707"
        ],
        "id": 1120869,
        "name:xx": "Shiderty"
      }
    }
  ]
}
