{
  "geometry": {
    "type": "Point",
    "coordinates": [
      -82.0833,
      36.25
    ]
  },
  "type": "Feature",
  "properties": {
    "hierarchy": [
      "tgn:2630375",
      "tgn:1000001",
      "tgn:7012149",
      "tgn:2001846",
      "tgn:7007825",
      "tgn:7029392"
    ],
    "placetype": [
      "aat:300266640"
    ],
    "id": 2630375,
    "name:xx": "Rough Ridge"
  }
}
