{
  "geometry": {
    "type": "Point",
    "coordinates": [
      93.65,
      44.8333
    ]
  },
  "type": "Feature",
  "properties": {
    "hierarchy": [
      "tgn:1071992",
      "tgn:1000004",
      "tgn:7001745",
      "tgn:1000111",
      "tgn:7029392"
    ],
    "placetype": [
      "aat:300008347"
    ],
    "id": 1071992,
    "name:xx": "Suhaitu"
  }
}
