{
  "geometry": {
    "type": "Point",
    "coordinates": [
      -86.3333,
      39.8667
    ]
  },
  "type": "Feature",
  "properties": {
    "hierarchy": [
      "tgn:2303439",
      "tgn:1000001",
      "tgn:7012149",
      "tgn:7007252",
      "tgn:7029392"
    ],
    "placetype": [
      "aat:300008706"
    ],
    "id": 2303439,
    "name:xx": "Eagle Crest Creek"
  }
}
