{
  "geometry": {
    "type": "Point",
    "coordinates": [
      22.1667,
      32.95
    ]
  },
  "type": "Feature",
  "properties": {
    "hierarchy": [
      "tgn:7000654",
      "tgn:7001242",
      "tgn:7000605",
      "tgn:1000172",
      "tgn:7029392"
    ],
    "placetype": [
      "aat:300008850"
    ],
    "id": 7000654,
    "name:xx": "Hilāl, Ra's al"
  }
}
