{
  "geometry": {
    "type": "Point",
    "coordinates": [
      -117.8333,
      33.6167
    ]
  },
  "type": "Feature",
  "properties": {
    "hierarchy": [
      "tgn:2187130",
      "tgn:1000001",
      "tgn:7012149",
      "tgn:7007157",
      "tgn:1002748",
      "tgn:7029392"
    ],
    "placetype": [
      "aat:300006191"
    ],
    "id": 2187130,
    "name:xx": "Bonta Reservoir"
  }
}
