{
  "geometry": {
    "type": "Point",
    "coordinates": [
      -85.8833,
      34.45
    ]
  },
  "type": "Feature",
  "properties": {
    "hierarchy": [
      "tgn:2197268",
      "tgn:7002659",
      "tgn:1000001",
      "tgn:7012149",
      "tgn:7021514",
      "tgn:7029392"
    ],
    "placetype": [
      "aat:300008699"
    ],
    "id": 2197268,
    "name:xx": "Brown Branch"
  }
}
