{
  "geometry": {
    "type": "Point",
    "coordinates": [
      4.85,
      44.9667
    ]
  },
  "type": "Feature",
  "properties": {
    "hierarchy": [
      "tgn:1032771",
      "tgn:1000003",
      "tgn:1000070",
      "tgn:7002897",
      "tgn:7029392"
    ],
    "placetype": [
      "aat:300008347"
    ],
    "id": 1032771,
    "name:xx": "Cornas"
  }
}
