{
  "geometry": {
    "type": "Point",
    "coordinates": [
      -111.35,
      45.3833
    ]
  },
  "type": "Feature",
  "properties": {
    "hierarchy": [
      "tgn:2153091",
      "tgn:1000001",
      "tgn:7012149",
      "tgn:2001288",
      "tgn:7007524",
      "tgn:7029392"
    ],
    "placetype": [
      "aat:300008347"
    ],
    "id": 2153091,
    "name:xx": "Beacon Point"
  }
}
