{
  "geometry": {
    "type": "Point",
    "coordinates": [
      -120.1667,
      33.9167
    ]
  },
  "type": "Feature",
  "properties": {
    "hierarchy": [
      "tgn:2245379",
      "tgn:1000001",
      "tgn:7012149",
      "tgn:1009018",
      "tgn:7007157",
      "tgn:1002867",
      "tgn:7029392"
    ],
    "placetype": [
      "aat:300008850"
    ],
    "id": 2245379,
    "name:xx": "Cluster Point"
  }
}
