{
  "type": "FeatureCollection",
  "features": [
    {
      "geometry": {
        "type": "Point",
        "coordinates": [
          -115.2667,
          44.9
        ]
      },
      "type": "Feature",
      "properties": {
        "hierarchy": [
          "tgn:2325040",
          "tgn:1000001",
          "tgn:7012149",
          "tgn:2000494",
          "tgn:7007250",
          "tgn:7029392"
        ],
        "placetype": [
          "aat:300008706"
        ],
        "id": 2325040,
        "name:xx": "Fern Creek"
      }
    },
    {
      "geometry": {
        "type": "Point",
        "coordinates": [
          -115.4833,
          46.0667
        ]
      },
      "type": "Feature",
      "properties": {
        "hierarchy": [
          "tgn:2325041",
          "tgn:1000001",
          "tgn:7012149",
          "tgn:2000476",
          "tgn:7007250",
          "tgn:7029392"
        ],
        "placetype": [
          "aat:300008706"
        ],
        "id": 2325041,
        "name:xx": "Fern Creek"
      }
    },
    {
      "geometry": {
        "type": "Point",
        "coordinates": [
          -116.4333,
          47.6167
        ]
      },
      "type": "Feature",
      "properties": {
        "hierarchy": [
          "tgn:2325042",
          "tgn:1000001",
          "tgn:7012149",
          "tgn:2000479",
          "tgn:7007250",
          "tgn:7029392"
        ],
        "placetype": [
          "aat:300008706"
        ],
        "id": 2325042,
        "name:xx": "Fern Creek"
      }
    },
    {
      "geometry": {
        "type": "Point",
        "coordinates": [
          -116.2333,
          48.8333
        ]
      },
      "type": "Feature",
      "properties": {
        "hierarchy": [
          "tgn:2325043",
          "tgn:1000001",
          "tgn:2000462",
          "tgn:7012149",
          "tgn:7007250",
          "tgn:7029392"
        ],
        "placetype": [
          "aat:300008706"
        ],
        "id": 2325043,
        "name:xx": "Fern Creek"
      }
    },
    {
      "geometry": {
        "type": "Point",
        "coordinates": [
          -115.55,
          46.8667
        ]
      },
      "type": "Feature",
      "properties": {
        "hierarchy": [
          "tgn:2325044",
          "tgn:1000001",
          "tgn:2000469",
          "tgn:7012149",
          "tgn:7007250",
          "tgn:7029392"
        ],
        "placetype": [
          "aat:300008706"
        ],
        "id": 2325044,
        "name:xx": "Fern Creek"
      }
    },
    {
      "geometry": {
        "type": "Point",
        "coordinates": [
          -116.4667,
          47
        ]
      },
      "type": "Feature",
      "properties": {
        "hierarchy": [
          "tgn:2325045",
          "tgn:1000001",
          "tgn:7012149",
          "tgn:2000480",
          "tgn:7007250",
          "tgn:7029392"
        ],
        "placetype": [
          "aat:300008706"
        ],
        "id": 2325045,
        "name:xx": "Fern Creek"
      }
    },
    {
      "geometry": {
        "type": "Point",
        "coordinates": [
          -95.9167,
          42.2833
        ]
      },
      "type": "Feature",
      "properties": {
        "hierarchy": [
          "tgn:2325046",
          "tgn:1000001",
          "tgn:7012149",
          "tgn:2000657",
          "tgn:7007253",
          "tgn:7029392"
        ],
        "placetype": [
          "aat:300008706"
        ],
        "id": 2325046,
        "name:xx": "Fern Creek"
      }
    },
    {
      "geometry": {
        "type": "Point",
        "coordinates": [
          -85.5667,
          38.1667
        ]
      },
      "type": "Feature",
      "properties": {
        "hierarchy": [
          "tgn:2325047",
          "tgn:1000001",
          "tgn:7012149",
          "tgn:1002516",
          "tgn:7007255",
          "tgn:7029392"
        ],
        "placetype": [
          "aat:300008706"
        ],
        "id": 2325047,
        "name:xx": "Fern Creek"
      }
    },
    {
      "geometry": {
        "type": "Point",
        "coordinates": [
          -87.8833,
          45.85
        ]
      },
      "type": "Feature",
      "properties": {
        "hierarchy": [
          "tgn:2325048",
          "tgn:1000001",
          "tgn:2000956",
          "tgn:7012149",
          "tgn:7007520",
          "tgn:7029392"
        ],
        "placetype": [
          "aat:300008706"
        ],
        "id": 2325048,
        "name:xx": "Fern Creek"
      }
    },
    {
      "geometry": {
        "type": "Point",
        "coordinates": [
          -114.1833,
          45.9833
        ]
      },
      "type": "Feature",
      "properties": {
        "hierarchy": [
          "tgn:2325049",
          "tgn:1000001",
          "tgn:7012149",
          "tgn:2001300",
          "tgn:7007524",
          "tgn:7029392"
        ],
        "placetype": [
          "aat:300008706"
        ],
        "id": 2325049,
        "name:xx": "Fern Creek"
      }
    }
  ]
}
