{
  "geometry": {
    "type": "Point",
    "coordinates": [
      -70.9833,
      41.5167
    ]
  },
  "type": "Feature",
  "properties": {
    "hierarchy": [
      "tgn:2670016",
      "tgn:1002201",
      "tgn:1000001",
      "tgn:7012149",
      "tgn:7007517",
      "tgn:7029392"
    ],
    "placetype": [
      "aat:300008850"
    ],
    "id": 2670016,
    "name:xx": "Slocums Neck"
  }
}
