{
  "geometry": {
    "type": "Point",
    "coordinates": [
      23.4167,
      45.45
    ]
  },
  "type": "Feature",
  "properties": {
    "hierarchy": [
      "tgn:1050223",
      "tgn:1000003",
      "tgn:7004126",
      "tgn:1000091",
      "tgn:7029392"
    ],
    "placetype": [
      "aat:300008347"
    ],
    "id": 1050223,
    "name:xx": "Petrila"
  }
}
