{
  "geometry": {
    "type": "Point",
    "coordinates": [
      -72.726,
      1.186
    ]
  },
  "type": "Feature",
  "properties": {
    "hierarchy": [
      "tgn:1131116",
      "tgn:1002083",
      "tgn:1000050",
      "tgn:1000002",
      "tgn:7029392"
    ],
    "placetype": [
      "aat:300008707"
    ],
    "id": 1131116,
    "name:xx": "Tunía, Río"
  }
}
