{
  "geometry": {
    "type": "Point",
    "coordinates": [
      -58.5667,
      -26.9167
    ]
  },
  "type": "Feature",
  "properties": {
    "hierarchy": [
      "tgn:1019886",
      "tgn:1001195",
      "tgn:7006477",
      "tgn:1000002",
      "tgn:7029392"
    ],
    "placetype": [
      "aat:300008347"
    ],
    "id": 1019886,
    "name:xx": "Puerto Bermejo"
  }
}
