{
  "geometry": {
    "type": "Point",
    "coordinates": [
      -88.8333,
      38.5167
    ]
  },
  "type": "Feature",
  "properties": {
    "hierarchy": [
      "tgn:2565577",
      "tgn:1000001",
      "tgn:7012149",
      "tgn:1002632",
      "tgn:7007251",
      "tgn:7029392"
    ],
    "placetype": [
      "aat:300008706"
    ],
    "id": 2565577,
    "name:xx": "Paintrock Creek"
  }
}
