{
  "type": "FeatureCollection",
  "features": [
    {
      "geometry": {
        "type": "Point",
        "coordinates": [
          -78.1333,
          43.0333
        ]
      },
      "type": "Feature",
      "properties": {
        "hierarchy": [
          "tgn:2329260",
          "tgn:1000001",
          "tgn:7012149",
          "tgn:1002407",
          "tgn:7007568",
          "tgn:7029392"
        ],
        "placetype": [
          "aat:300008347"
        ],
        "id": 2329260,
        "name:xx": "Five Corners"
      }
    },
    {
      "geometry": {
        "type": "Point",
        "coordinates": [
          -75.6833,
          43.0667
        ]
      },
      "type": "Feature",
      "properties": {
        "hierarchy": [
          "tgn:2329261",
          "tgn:1000001",
          "tgn:7012149",
          "tgn:1002624",
          "tgn:7007568",
          "tgn:7029392"
        ],
        "placetype": [
          "aat:300008347"
        ],
        "id": 2329261,
        "name:xx": "Five Corners"
      }
    },
    {
      "geometry": {
        "type": "Point",
        "coordinates": [
          -78.1833,
          43.25
        ]
      },
      "type": "Feature",
      "properties": {
        "hierarchy": [
          "tgn:2329262",
          "tgn:1000001",
          "tgn:7012149",
          "tgn:1002752",
          "tgn:7007568",
          "tgn:7029392"
        ],
        "placetype": [
          "aat:300008347"
        ],
        "id": 2329262,
        "name:xx": "Five Corners"
      }
    },
    {
      "geometry": {
        "type": "Point",
        "coordinates": [
          -82.5833,
          40.3167
        ]
      },
      "type": "Feature",
      "properties": {
        "hierarchy": [
          "tgn:2329263",
          "tgn:1000001",
          "tgn:7012149",
          "tgn:1002556",
          "tgn:7007706",
          "tgn:7029392"
        ],
        "placetype": [
          "aat:300008347"
        ],
        "id": 2329263,
        "name:xx": "Five Corners"
      }
    },
    {
      "geometry": {
        "type": "Point",
        "coordinates": [
          -81.3333,
          41.0333
        ]
      },
      "type": "Feature",
      "properties": {
        "hierarchy": [
          "tgn:2329264",
          "tgn:1000001",
          "tgn:7012149",
          "tgn:1002797",
          "tgn:7007706",
          "tgn:7029392"
        ],
        "placetype": [
          "aat:300008347"
        ],
        "id": 2329264,
        "name:xx": "Five Corners"
      }
    },
    {
      "geometry": {
        "type": "Point",
        "coordinates": [
          -82.65,
          40.7667
        ]
      },
      "type": "Feature",
      "properties": {
        "hierarchy": [
          "tgn:2329265",
          "tgn:1000001",
          "tgn:7012149",
          "tgn:1002823",
          "tgn:7007706",
          "tgn:7029392"
        ],
        "placetype": [
          "aat:300008347"
        ],
        "id": 2329265,
        "name:xx": "Five Corners"
      }
    },
    {
      "geometry": {
        "type": "Point",
        "coordinates": [
          -118.85,
          46.5
        ]
      },
      "type": "Feature",
      "properties": {
        "hierarchy": [
          "tgn:2329266",
          "tgn:1000001",
          "tgn:2002244",
          "tgn:7012149",
          "tgn:7007920",
          "tgn:7029392"
        ],
        "placetype": [
          "aat:300008347"
        ],
        "id": 2329266,
        "name:xx": "Five Corners"
      }
    },
    {
      "geometry": {
        "type": "Point",
        "coordinates": [
          -122.3167,
          47.45
        ]
      },
      "type": "Feature",
      "properties": {
        "hierarchy": [
          "tgn:2329267",
          "tgn:1000001",
          "tgn:7012149",
          "tgn:7018871",
          "tgn:7007920",
          "tgn:7029392"
        ],
        "placetype": [
          "aat:300008347"
        ],
        "id": 2329267,
        "name:xx": "Five Corners"
      }
    },
    {
      "geometry": {
        "type": "Point",
        "coordinates": [
          -122.5833,
          46.9167
        ]
      },
      "type": "Feature",
      "properties": {
        "hierarchy": [
          "tgn:2329268",
          "tgn:1000001",
          "tgn:7012149",
          "tgn:1002942",
          "tgn:7007920",
          "tgn:7029392"
        ],
        "placetype": [
          "aat:300008347"
        ],
        "id": 2329268,
        "name:xx": "Five Corners"
      }
    },
    {
      "geometry": {
        "type": "Point",
        "coordinates": [
          -89.0333,
          44.8
        ]
      },
      "type": "Feature",
      "properties": {
        "hierarchy": [
          "tgn:2329269",
          "tgn:1000001",
          "tgn:7012149",
          "tgn:2002354",
          "tgn:7007922",
          "tgn:7029392"
        ],
        "placetype": [
          "aat:300008347"
        ],
        "id": 2329269,
        "name:xx": "Five Corners"
      }
    }
  ]
}
