{
  "type": "FeatureCollection",
  "features": [
    {
      "geometry": {
        "type": "Point",
        "coordinates": [
          -70.9,
          44.35
        ]
      },
      "type": "Feature",
      "properties": {
        "hierarchy": [
          "tgn:2737640",
          "tgn:1000001",
          "tgn:7012149",
          "tgn:2000926",
          "tgn:7007515",
          "tgn:7029392"
        ],
        "placetype": [
          "aat:300008798"
        ],
        "id": 2737640,
        "name:xx": "Tyler Mountain"
      }
    },
    {
      "geometry": {
        "type": "Point",
        "coordinates": [
          -76.25,
          41.5333
        ]
      },
      "type": "Feature",
      "properties": {
        "hierarchy": [
          "tgn:2737641",
          "tgn:1000001",
          "tgn:7012149",
          "tgn:7007710",
          "tgn:7029392"
        ],
        "placetype": [
          "aat:300008798"
        ],
        "id": 2737641,
        "name:xx": "Tyler Mountain"
      }
    },
    {
      "geometry": {
        "type": "Point",
        "coordinates": [
          -84.15,
          35.4167
        ]
      },
      "type": "Feature",
      "properties": {
        "hierarchy": [
          "tgn:2737642",
          "tgn:1000001",
          "tgn:7012149",
          "tgn:2001898",
          "tgn:7007825",
          "tgn:7029392"
        ],
        "placetype": [
          "aat:300008798"
        ],
        "id": 2737642,
        "name:xx": "Tyler Mountain"
      }
    },
    {
      "geometry": {
        "type": "Point",
        "coordinates": [
          -85.2333,
          36.1833
        ]
      },
      "type": "Feature",
      "properties": {
        "hierarchy": [
          "tgn:2737643",
          "tgn:1000001",
          "tgn:7012149",
          "tgn:2001903",
          "tgn:7007825",
          "tgn:7029392"
        ],
        "placetype": [
          "aat:300008798"
        ],
        "id": 2737643,
        "name:xx": "Tyler Mountain"
      }
    },
    {
      "geometry": {
        "type": "Point",
        "coordinates": [
          -72.4333,
          43.7833
        ]
      },
      "type": "Feature",
      "properties": {
        "hierarchy": [
          "tgn:2737644",
          "tgn:1000001",
          "tgn:2002136",
          "tgn:7012149",
          "tgn:7007828",
          "tgn:7029392"
        ],
        "placetype": [
          "aat:300008798"
        ],
        "id": 2737644,
        "name:xx": "Tyler Mountain"
      }
    },
    {
      "geometry": {
        "type": "Point",
        "coordinates": [
          -81.7333,
          38.4
        ]
      },
      "type": "Feature",
      "properties": {
        "hierarchy": [
          "tgn:2737645",
          "tgn:1000001",
          "tgn:7012149",
          "tgn:2002270",
          "tgn:7013961",
          "tgn:7029392"
        ],
        "placetype": [
          "aat:300008798"
        ],
        "id": 2737645,
        "name:xx": "Tyler Mountain"
      }
    },
    {
      "geometry": {
        "type": "Point",
        "coordinates": [
          -118.7,
          35.8833
        ]
      },
      "type": "Feature",
      "properties": {
        "hierarchy": [
          "tgn:2737646",
          "tgn:1000001",
          "tgn:7012149",
          "tgn:7007157",
          "tgn:1002956",
          "tgn:7029392"
        ],
        "placetype": [
          "aat:300008798"
        ],
        "id": 2737646,
        "name:xx": "Tyler Peak"
      }
    },
    {
      "geometry": {
        "type": "Point",
        "coordinates": [
          -112.95,
          43.9833
        ]
      },
      "type": "Feature",
      "properties": {
        "hierarchy": [
          "tgn:2737647",
          "tgn:1000001",
          "tgn:2000468",
          "tgn:7012149",
          "tgn:7007250",
          "tgn:7029392"
        ],
        "placetype": [
          "aat:300008798"
        ],
        "id": 2737647,
        "name:xx": "Tyler Peak"
      }
    },
    {
      "geometry": {
        "type": "Point",
        "coordinates": [
          -123.1333,
          47.9
        ]
      },
      "type": "Feature",
      "properties": {
        "hierarchy": [
          "tgn:2737648",
          "tgn:1000001",
          "tgn:1002271",
          "tgn:7012149",
          "tgn:7007920",
          "tgn:7029392"
        ],
        "placetype": [
          "aat:300008798"
        ],
        "id": 2737648,
        "name:xx": "Tyler Peak"
      }
    },
    {
      "geometry": {
        "type": "Point",
        "coordinates": [
          -113.45,
          46.6333
        ]
      },
      "type": "Feature",
      "properties": {
        "hierarchy": [
          "tgn:2737649",
          "tgn:1000001",
          "tgn:7012149",
          "tgn:2001279",
          "tgn:7007524",
          "tgn:7029392"
        ],
        "placetype": [
          "aat:300008798"
        ],
        "id": 2737649,
        "name:xx": "Tyler Point"
      }
    }
  ]
}
