{
  "type": "FeatureCollection",
  "features": [
    {
      "geometry": {
        "type": "Point",
        "coordinates": [
          6.7333,
          43.7667
        ]
      },
      "type": "Feature",
      "properties": {
        "hierarchy": [
          "tgn:1032391",
          "tgn:1000003",
          "tgn:1000070",
          "tgn:7002895",
          "tgn:7029392"
        ],
        "placetype": [
          "aat:300008347"
        ],
        "id": 1032391,
        "name:xx": "Caille"
      }
    },
    {
      "geometry": {
        "type": "Point",
        "coordinates": [
          9,
          42.3333
        ]
      },
      "type": "Feature",
      "properties": {
        "hierarchy": [
          "tgn:1032393",
          "tgn:1000003",
          "tgn:7594273",
          "tgn:1000070",
          "tgn:7029392"
        ],
        "placetype": [
          "aat:300008347"
        ],
        "id": 1032393,
        "name:xx": "Calacuccia"
      }
    },
    {
      "geometry": {
        "type": "Point",
        "coordinates": [
          -3.4333,
          48.4
        ]
      },
      "type": "Feature",
      "properties": {
        "hierarchy": [
          "tgn:1032395",
          "tgn:1000003",
          "tgn:7012216",
          "tgn:1000070",
          "tgn:7029392"
        ],
        "placetype": [
          "aat:300008347"
        ],
        "id": 1032395,
        "name:xx": "Callac"
      }
    },
    {
      "geometry": {
        "type": "Point",
        "coordinates": [
          6.55,
          43.5833
        ]
      },
      "type": "Feature",
      "properties": {
        "hierarchy": [
          "tgn:1032396",
          "tgn:1000003",
          "tgn:1000070",
          "tgn:7002895",
          "tgn:7029392"
        ],
        "placetype": [
          "aat:300008347"
        ],
        "id": 1032396,
        "name:xx": "Callas"
      }
    },
    {
      "geometry": {
        "type": "Point",
        "coordinates": [
          2.4833,
          50.4833
        ]
      },
      "type": "Feature",
      "properties": {
        "hierarchy": [
          "tgn:1032397",
          "tgn:1000003",
          "tgn:7001097",
          "tgn:1000070",
          "tgn:7029392"
        ],
        "placetype": [
          "aat:300008347"
        ],
        "id": 1032397,
        "name:xx": "Calonne-Ricouart"
      }
    },
    {
      "geometry": {
        "type": "Point",
        "coordinates": [
          4.85,
          45.8
        ]
      },
      "type": "Feature",
      "properties": {
        "hierarchy": [
          "tgn:1032398",
          "tgn:1000003",
          "tgn:1000070",
          "tgn:7002897",
          "tgn:7029392"
        ],
        "placetype": [
          "aat:300008347"
        ],
        "id": 1032398,
        "name:xx": "Caluire-et-Cuire"
      }
    },
    {
      "geometry": {
        "type": "Point",
        "coordinates": [
          8.7333,
          42.5667
        ]
      },
      "type": "Feature",
      "properties": {
        "hierarchy": [
          "tgn:1032399",
          "tgn:1000003",
          "tgn:7594273",
          "tgn:1000070",
          "tgn:7029392"
        ],
        "placetype": [
          "aat:300008347"
        ],
        "id": 1032399,
        "name:xx": "Calvi"
      }
    }
  ]
}
