{
  "type": "FeatureCollection",
  "features": [
    {
      "geometry": {
        "type": "Point",
        "coordinates": [
          30.65,
          28.533333
        ]
      },
      "type": "Feature",
      "properties": {
        "hierarchy": [
          "tgn:7529180",
          "tgn:7001242",
          "tgn:7016833",
          "tgn:1001088",
          "tgn:7029392"
        ],
        "placetype": [
          "aat:300005926"
        ],
        "name:en": "Sīdī 'Alī al Ḩamām",
        "id": 7529180
      }
    },
    {
      "geometry": {
        "type": "Point",
        "coordinates": [
          31.567761,
          30.857518
        ]
      },
      "type": "Feature",
      "properties": {
        "hierarchy": [
          "tgn:7529181",
          "tgn:7001242",
          "tgn:1001059",
          "tgn:7016833",
          "tgn:7029392"
        ],
        "placetype": [
          "aat:300006075"
        ],
        "id": 7529181,
        "name:xx": "Tur'at Maḩbūbah"
      }
    },
    {
      "geometry": {
        "type": "Point",
        "coordinates": [
          31.450767,
          30.877649
        ]
      },
      "type": "Feature",
      "properties": {
        "hierarchy": [
          "tgn:7529182",
          "tgn:7001242",
          "tgn:1001059",
          "tgn:7016833",
          "tgn:7029392"
        ],
        "placetype": [
          "aat:300006075"
        ],
        "id": 7529182,
        "name:xx": "Tur'at 'Uthmān"
      }
    },
    {
      "geometry": {
        "type": "Point",
        "coordinates": [
          31.545604,
          30.856603
        ]
      },
      "type": "Feature",
      "properties": {
        "hierarchy": [
          "tgn:7529183",
          "tgn:7001242",
          "tgn:1001059",
          "tgn:7016833",
          "tgn:7029392"
        ],
        "placetype": [
          "aat:300006075"
        ],
        "id": 7529183,
        "name:xx": "Tur'at 'Alī Riḑā"
      }
    },
    {
      "geometry": {
        "type": "Point",
        "coordinates": [
          31.512989,
          30.807845
        ]
      },
      "type": "Feature",
      "properties": {
        "hierarchy": [
          "tgn:7529184",
          "tgn:7001242",
          "tgn:7016833",
          "tgn:7029392"
        ],
        "placetype": [
          "aat:300006075"
        ],
        "id": 7529184,
        "name:xx": "Tur'at al Fidn"
      }
    },
    {
      "geometry": {
        "type": "Point",
        "coordinates": [
          31.523578,
          30.809806
        ]
      },
      "type": "Feature",
      "properties": {
        "hierarchy": [
          "tgn:7529185",
          "tgn:7001242",
          "tgn:7016833",
          "tgn:7029392"
        ],
        "placetype": [
          "aat:300006075"
        ],
        "id": 7529185,
        "name:xx": "Tur'at al Qanān"
      }
    },
    {
      "geometry": {
        "type": "Point",
        "coordinates": [
          31.566127,
          30.813204
        ]
      },
      "type": "Feature",
      "properties": {
        "hierarchy": [
          "tgn:7529186",
          "tgn:7001242",
          "tgn:7016833",
          "tgn:7029392"
        ],
        "placetype": [
          "aat:300006075"
        ],
        "id": 7529186,
        "name:xx": "Tur'at Ḩānūt"
      }
    },
    {
      "geometry": {
        "type": "Point",
        "coordinates": [
          31.498349,
          30.74608
        ]
      },
      "type": "Feature",
      "properties": {
        "hierarchy": [
          "tgn:7529187",
          "tgn:7001242",
          "tgn:7016833",
          "tgn:1001113",
          "tgn:7029392"
        ],
        "placetype": [
          "aat:300006075"
        ],
        "id": 7529187,
        "name:xx": "Tur'at Ikrāsh"
      }
    },
    {
      "geometry": {
        "type": "Point",
        "coordinates": [
          31.469281,
          31.350956
        ]
      },
      "type": "Feature",
      "properties": {
        "hierarchy": [
          "tgn:7529188",
          "tgn:7001242",
          "tgn:7016833",
          "tgn:1001335",
          "tgn:7029392"
        ],
        "placetype": [
          "aat:300008347"
        ],
        "id": 7529188,
        "name:xx": "'Izbat al Amlāk"
      }
    },
    {
      "geometry": {
        "type": "Point",
        "coordinates": [
          31.506954,
          30.593626
        ]
      },
      "type": "Feature",
      "properties": {
        "hierarchy": [
          "tgn:7529189",
          "tgn:7001242",
          "tgn:7016833",
          "tgn:1001113",
          "tgn:7029392"
        ],
        "placetype": [
          "aat:300006075"
        ],
        "id": 7529189,
        "name:xx": "Baḩr al Mashtūl"
      }
    }
  ]
}
