{
  "geometry": {
    "type": "Point",
    "coordinates": [
      -109.6833,
      44.1833
    ]
  },
  "type": "Feature",
  "properties": {
    "hierarchy": [
      "tgn:2401393",
      "tgn:1000001",
      "tgn:7012149",
      "tgn:2002379",
      "tgn:7007923",
      "tgn:7029392"
    ],
    "placetype": [
      "aat:300008798"
    ],
    "id": 2401393,
    "name:xx": "Horses Head"
  }
}
