{
  "geometry": {
    "type": "Point",
    "coordinates": [
      6.55,
      45.95
    ]
  },
  "type": "Feature",
  "properties": {
    "hierarchy": [
      "tgn:1107462",
      "tgn:1000003",
      "tgn:1000070",
      "tgn:7002897",
      "tgn:7029392"
    ],
    "placetype": [
      "aat:300008798"
    ],
    "id": 1107462,
    "name:xx": "Percée"
  }
}
