{
  "type": "FeatureCollection",
  "features": [
    {
      "geometry": {
        "type": "Point",
        "coordinates": [
          -4.4,
          56.033333
        ]
      },
      "type": "Feature",
      "properties": {
        "hierarchy": [
          "tgn:7455850",
          "tgn:7002444",
          "tgn:1000003",
          "tgn:5000460",
          "tgn:7008591",
          "tgn:7029392"
        ],
        "placetype": [
          "aat:300008699"
        ],
        "name:en": "Dualt Burn",
        "id": 7455850
      }
    },
    {
      "geometry": {
        "type": "Point",
        "coordinates": [
          -6.333333,
          57.366667
        ]
      },
      "type": "Feature",
      "properties": {
        "hierarchy": [
          "tgn:7455851",
          "tgn:7002444",
          "tgn:1000003",
          "tgn:7008082",
          "tgn:7008591",
          "tgn:7029392"
        ],
        "placetype": [
          "aat:300008680"
        ],
        "name:en": "Duagrich, Loch",
        "id": 7455851
      }
    },
    {
      "geometry": {
        "type": "Point",
        "coordinates": [
          -4.033333,
          53.316667
        ]
      },
      "type": "Feature",
      "properties": {
        "hierarchy": [
          "tgn:7455852",
          "tgn:7008532",
          "tgn:7002443",
          "tgn:1000003",
          "tgn:7008591",
          "tgn:7029392"
        ],
        "placetype": [
          "aat:300386846"
        ],
        "name:en": "Du, Trwyn",
        "id": 7455852
      }
    },
    {
      "geometry": {
        "type": "Point",
        "coordinates": [
          -5.166667,
          50.05
        ]
      },
      "type": "Feature",
      "properties": {
        "hierarchy": [
          "tgn:7455853",
          "tgn:7002445",
          "tgn:7008116",
          "tgn:1000003",
          "tgn:7008591",
          "tgn:7029392"
        ],
        "placetype": [
          "aat:300387200"
        ],
        "name:en": "Dry Tree",
        "id": 7455853
      }
    },
    {
      "geometry": {
        "type": "Point",
        "coordinates": [
          -4.100833,
          51.863611
        ]
      },
      "type": "Feature",
      "properties": {
        "hierarchy": [
          "tgn:7455854",
          "tgn:7002443",
          "tgn:5000552",
          "tgn:1000003",
          "tgn:7008591",
          "tgn:7029392"
        ],
        "placetype": [
          "aat:300008347"
        ],
        "name:en": "Dryslwyn",
        "id": 7455854
      }
    },
    {
      "geometry": {
        "type": "Point",
        "coordinates": [
          -6.25,
          57.3
        ]
      },
      "type": "Feature",
      "properties": {
        "hierarchy": [
          "tgn:7455855",
          "tgn:7002444",
          "tgn:1000003",
          "tgn:7008082",
          "tgn:7008591",
          "tgn:7029392"
        ],
        "placetype": [
          "aat:300008761"
        ],
        "name:en": "Drynoch, Glen",
        "id": 7455855
      }
    },
    {
      "geometry": {
        "type": "Point",
        "coordinates": [
          -6.3,
          57.283333
        ]
      },
      "type": "Feature",
      "properties": {
        "hierarchy": [
          "tgn:7455856",
          "tgn:7002444",
          "tgn:1000003",
          "tgn:7008082",
          "tgn:7008591",
          "tgn:7029392"
        ],
        "placetype": [
          "aat:300008347"
        ],
        "name:en": "Drynoch",
        "id": 7455856
      }
    },
    {
      "geometry": {
        "type": "Point",
        "coordinates": [
          -3.9,
          57.433333
        ]
      },
      "type": "Feature",
      "properties": {
        "hierarchy": [
          "tgn:7455857",
          "tgn:7002444",
          "tgn:1000003",
          "tgn:7008082",
          "tgn:7008591",
          "tgn:7029392"
        ],
        "placetype": [
          "aat:300387502"
        ],
        "name:en": "Drynachan Lodge",
        "id": 7455857
      }
    },
    {
      "geometry": {
        "type": "Point",
        "coordinates": [
          -3.15,
          55.5
        ]
      },
      "type": "Feature",
      "properties": {
        "hierarchy": [
          "tgn:7455859",
          "tgn:7002444",
          "tgn:1000003",
          "tgn:7008072",
          "tgn:7008591",
          "tgn:7029392"
        ],
        "placetype": [
          "aat:300008699"
        ],
        "name:en": "Dryhope Burn",
        "id": 7455859
      }
    }
  ]
}
