{
  "geometry": {
    "type": "Point",
    "coordinates": [
      -89.3333,
      38.95
    ]
  },
  "type": "Feature",
  "properties": {
    "hierarchy": [
      "tgn:2030768",
      "tgn:1000001",
      "tgn:1002186",
      "tgn:7012149",
      "tgn:7007251",
      "tgn:7029392"
    ],
    "placetype": [
      "aat:300008347"
    ],
    "id": 2030768,
    "name:xx": "Woburn"
  }
}
