{
  "geometry": {
    "type": "Point",
    "coordinates": [
      9.9333,
      2.9333
    ]
  },
  "type": "Feature",
  "properties": {
    "hierarchy": [
      "tgn:1088210",
      "tgn:1001189",
      "tgn:7001242",
      "tgn:1000153",
      "tgn:7029392"
    ],
    "placetype": [
      "aat:300008347"
    ],
    "id": 1088210,
    "name:xx": "Kribi"
  }
}
