{
  "geometry": {
    "type": "Point",
    "coordinates": [
      -112.0333,
      34.7667
    ]
  },
  "type": "Feature",
  "properties": {
    "hierarchy": [
      "tgn:2573726",
      "tgn:1000001",
      "tgn:7006451",
      "tgn:7012149",
      "tgn:2000103",
      "tgn:7029392"
    ],
    "placetype": [
      "aat:300006191"
    ],
    "id": 2573726,
    "name:xx": "Pecks Lake"
  }
}
