{
  "geometry": {
    "type": "Point",
    "coordinates": [
      -73.5333,
      42.5167
    ]
  },
  "type": "Feature",
  "properties": {
    "hierarchy": [
      "tgn:2272468",
      "tgn:1000001",
      "tgn:7012149",
      "tgn:1002821",
      "tgn:7007568",
      "tgn:7029392"
    ],
    "placetype": [
      "aat:300008798"
    ],
    "id": 2272468,
    "name:xx": "Curtis Mountain"
  }
}
