{
  "geometry": {
    "type": "Point",
    "coordinates": [
      -111.8667,
      37.8333
    ]
  },
  "type": "Feature",
  "properties": {
    "hierarchy": [
      "tgn:2488857",
      "tgn:1000001",
      "tgn:2002109",
      "tgn:7012149",
      "tgn:7007827",
      "tgn:7029392"
    ],
    "placetype": [
      "aat:300008761"
    ],
    "id": 2488857,
    "name:xx": "Main Canyon"
  }
}
