{
  "geometry": {
    "type": "Point",
    "coordinates": [
      -110.7333,
      31.75
    ]
  },
  "type": "Feature",
  "properties": {
    "hierarchy": [
      "tgn:2006847",
      "tgn:1000001",
      "tgn:7006451",
      "tgn:7012149",
      "tgn:2000100",
      "tgn:7029392"
    ],
    "placetype": [
      "aat:300008347",
      "aat:300387210"
    ],
    "id": 2006847,
    "name:xx": "Greaterville"
  }
}
