{
  "geometry": {
    "type": "Point",
    "coordinates": [
      88.421336,
      23.724479
    ]
  },
  "type": "Feature",
  "properties": {
    "hierarchy": [
      "tgn:7545441",
      "tgn:1000004",
      "tgn:7000198",
      "tgn:1001977",
      "tgn:7029392"
    ],
    "placetype": [
      "aat:300008347"
    ],
    "name:en": "Bārnia",
    "id": 7545441
  }
}
