{
  "geometry": {
    "type": "Point",
    "coordinates": [
      -85.9667,
      43.2167
    ]
  },
  "type": "Feature",
  "properties": {
    "hierarchy": [
      "tgn:2594230",
      "tgn:1000001",
      "tgn:7012149",
      "tgn:1002700",
      "tgn:7007520",
      "tgn:7029392"
    ],
    "placetype": [
      "aat:300006075"
    ],
    "id": 2594230,
    "name:xx": "Porter Drain"
  }
}
