{
  "geometry": {
    "type": "Point",
    "coordinates": [
      21.85,
      38.333333
    ]
  },
  "type": "Feature",
  "properties": {
    "hierarchy": [
      "tgn:7227642",
      "tgn:7002680",
      "tgn:7001395",
      "tgn:1000003",
      "tgn:1000074",
      "tgn:7029392"
    ],
    "placetype": [
      "aat:300008347"
    ],
    "id": 7227642,
    "name:xx": "Káto Arakhovítika"
  }
}
