{
  "geometry": {
    "type": "Point",
    "coordinates": [
      -122.0333,
      40.7833
    ]
  },
  "type": "Feature",
  "properties": {
    "hierarchy": [
      "tgn:2498902",
      "tgn:1000001",
      "tgn:7012149",
      "tgn:7007157",
      "tgn:2000188",
      "tgn:7029392"
    ],
    "placetype": [
      "aat:300008761"
    ],
    "id": 2498902,
    "name:xx": "McCandless Gulch"
  }
}
