{
  "geometry": {
    "type": "Point",
    "coordinates": [
      -70.25,
      -34.416667
    ]
  },
  "type": "Feature",
  "properties": {
    "hierarchy": [
      "tgn:7291835",
      "tgn:1001695",
      "tgn:1000049",
      "tgn:1000002",
      "tgn:7029392"
    ],
    "placetype": [
      "aat:300008699"
    ],
    "id": 7291835,
    "name:xx": "Flores, Cajón de"
  }
}
