{
  "geometry": {
    "type": "Point",
    "coordinates": [
      76.619259,
      27.321724
    ]
  },
  "type": "Feature",
  "properties": {
    "hierarchy": [
      "tgn:7550826",
      "tgn:1000004",
      "tgn:7000198",
      "tgn:7016788",
      "tgn:7029392"
    ],
    "placetype": [
      "aat:300007783"
    ],
    "name:en": "Digāwora Railroad Station",
    "id": 7550826
  }
}
