{
  "geometry": {
    "type": "Point",
    "coordinates": [
      -72.0333,
      42.3833
    ]
  },
  "type": "Feature",
  "properties": {
    "hierarchy": [
      "tgn:2248871",
      "tgn:1000001",
      "tgn:7012149",
      "tgn:1003038",
      "tgn:7007517",
      "tgn:7029392"
    ],
    "placetype": [
      "aat:300008347"
    ],
    "id": 2248871,
    "name:xx": "Coldbrook Springs"
  }
}
