{
  "geometry": {
    "type": "Point",
    "coordinates": [
      -104.8833,
      31.9833
    ]
  },
  "type": "Feature",
  "properties": {
    "hierarchy": [
      "tgn:2264018",
      "tgn:1000001",
      "tgn:7012149",
      "tgn:2001969",
      "tgn:7007826",
      "tgn:7029392"
    ],
    "placetype": [
      "aat:300008798"
    ],
    "id": 2264018,
    "name:xx": "Coyote Peak"
  }
}
