{
  "geometry": {
    "type": "Point",
    "coordinates": [
      -94.2333,
      33.6833
    ]
  },
  "type": "Feature",
  "properties": {
    "hierarchy": [
      "tgn:2251374",
      "tgn:1000001",
      "tgn:7016172",
      "tgn:7012149",
      "tgn:2000145",
      "tgn:7029392"
    ],
    "placetype": [
      "aat:300008347"
    ],
    "id": 2251374,
    "name:xx": "Comet"
  }
}
