{
  "geometry": {
    "type": "Point",
    "coordinates": [
      -106.55,
      40.7667
    ]
  },
  "type": "Feature",
  "properties": {
    "hierarchy": [
      "tgn:2479830",
      "tgn:1000001",
      "tgn:7012149",
      "tgn:2000220",
      "tgn:7007158",
      "tgn:7029392"
    ],
    "placetype": [
      "aat:300006075"
    ],
    "id": 2479830,
    "name:xx": "Lake Creek Ditch"
  }
}
