{
  "geometry": {
    "type": "Point",
    "coordinates": [
      -116.15,
      39.4333
    ]
  },
  "type": "Feature",
  "properties": {
    "hierarchy": [
      "tgn:2488476",
      "tgn:1000001",
      "tgn:2001413",
      "tgn:7012149",
      "tgn:7007526",
      "tgn:7029392"
    ],
    "placetype": [
      "aat:300386831"
    ],
    "id": 2488476,
    "name:xx": "Mahogany Hills"
  }
}
