{
  "geometry": {
    "type": "Point",
    "coordinates": [
      61.3333,
      25.7167
    ]
  },
  "type": "Feature",
  "properties": {
    "hierarchy": [
      "tgn:1078983",
      "tgn:1000004",
      "tgn:7002176",
      "tgn:7000231",
      "tgn:7029392"
    ],
    "placetype": [
      "aat:300008347"
    ],
    "id": 1078983,
    "name:xx": "Bāhū Kalāt"
  }
}
