{
  "type": "FeatureCollection",
  "features": [
    {
      "geometry": {
        "type": "Point",
        "coordinates": [
          -104.95,
          27.083333
        ]
      },
      "type": "Feature",
      "properties": {
        "hierarchy": [
          "tgn:7359390",
          "tgn:7005581",
          "tgn:1000001",
          "tgn:7005560",
          "tgn:7029392"
        ],
        "placetype": [
          "aat:300008347"
        ],
        "id": 7359390,
        "name:xx": "Dolores"
      }
    },
    {
      "geometry": {
        "type": "Point",
        "coordinates": [
          -107.166667,
          26
        ]
      },
      "type": "Feature",
      "properties": {
        "hierarchy": [
          "tgn:7359392",
          "tgn:7005581",
          "tgn:1000001",
          "tgn:7005560",
          "tgn:7029392"
        ],
        "placetype": [
          "aat:300008347"
        ],
        "id": 7359392,
        "name:xx": "Dolores"
      }
    },
    {
      "geometry": {
        "type": "Point",
        "coordinates": [
          -103.566667,
          25.716667
        ]
      },
      "type": "Feature",
      "properties": {
        "hierarchy": [
          "tgn:7359393",
          "tgn:7005583",
          "tgn:1000001",
          "tgn:7005560",
          "tgn:7029392"
        ],
        "placetype": [
          "aat:300008347"
        ],
        "id": 7359393,
        "name:xx": "Dolores"
      }
    },
    {
      "geometry": {
        "type": "Point",
        "coordinates": [
          -101.883333,
          25.533333
        ]
      },
      "type": "Feature",
      "properties": {
        "hierarchy": [
          "tgn:7359394",
          "tgn:1001853",
          "tgn:1000001",
          "tgn:7005560",
          "tgn:7029392"
        ],
        "placetype": [
          "aat:300008347"
        ],
        "id": 7359394,
        "name:xx": "Dolores"
      }
    },
    {
      "geometry": {
        "type": "Point",
        "coordinates": [
          -104.3,
          25.483333
        ]
      },
      "type": "Feature",
      "properties": {
        "hierarchy": [
          "tgn:7359395",
          "tgn:7005583",
          "tgn:1000001",
          "tgn:7005560",
          "tgn:7029392"
        ],
        "placetype": [
          "aat:300008347"
        ],
        "id": 7359395,
        "name:xx": "Dolores"
      }
    },
    {
      "geometry": {
        "type": "Point",
        "coordinates": [
          -99.65,
          25.25
        ]
      },
      "type": "Feature",
      "properties": {
        "hierarchy": [
          "tgn:7359396",
          "tgn:1000001",
          "tgn:7005589",
          "tgn:7005560",
          "tgn:7029392"
        ],
        "placetype": [
          "aat:300008347"
        ],
        "id": 7359396,
        "name:xx": "Dolores"
      }
    },
    {
      "geometry": {
        "type": "Point",
        "coordinates": [
          -99.85,
          25.133333
        ]
      },
      "type": "Feature",
      "properties": {
        "hierarchy": [
          "tgn:7359397",
          "tgn:1000001",
          "tgn:7005589",
          "tgn:7005560",
          "tgn:7029392"
        ],
        "placetype": [
          "aat:300008347"
        ],
        "id": 7359397,
        "name:xx": "Dolores"
      }
    },
    {
      "geometry": {
        "type": "Point",
        "coordinates": [
          -100.166667,
          24.616667
        ]
      },
      "type": "Feature",
      "properties": {
        "hierarchy": [
          "tgn:7359398",
          "tgn:1000001",
          "tgn:7005589",
          "tgn:7005560",
          "tgn:7029392"
        ],
        "placetype": [
          "aat:300008347"
        ],
        "id": 7359398,
        "name:xx": "Dolores"
      }
    },
    {
      "geometry": {
        "type": "Point",
        "coordinates": [
          -99.843611,
          24.171667
        ]
      },
      "type": "Feature",
      "properties": {
        "hierarchy": [
          "tgn:7359399",
          "tgn:1000001",
          "tgn:7005589",
          "tgn:7005560",
          "tgn:7029392"
        ],
        "placetype": [
          "aat:300008347"
        ],
        "id": 7359399,
        "name:xx": "Dolores"
      }
    }
  ]
}
