{
  "geometry": {
    "type": "Point",
    "coordinates": [
      -95.9833,
      29.1667
    ]
  },
  "type": "Feature",
  "properties": {
    "hierarchy": [
      "tgn:2218729",
      "tgn:1000001",
      "tgn:7012149",
      "tgn:1003019",
      "tgn:7007826",
      "tgn:7029392"
    ],
    "placetype": [
      "aat:300008347"
    ],
    "id": 2218729,
    "name:xx": "Cane Junction"
  }
}
