{
  "geometry": {
    "type": "Point",
    "coordinates": [
      -62.518,
      9.358
    ]
  },
  "type": "Feature",
  "properties": {
    "hierarchy": [
      "tgn:1130849",
      "tgn:1000002",
      "tgn:1000059",
      "tgn:7029392"
    ],
    "placetype": [
      "aat:300008707"
    ],
    "id": 1130849,
    "name:xx": "Tigre, Río"
  }
}
