{
  "geometry": {
    "type": "Point",
    "coordinates": [
      -106.4667,
      38.75
    ]
  },
  "type": "Feature",
  "properties": {
    "hierarchy": [
      "tgn:2016411",
      "tgn:1000001",
      "tgn:7012149",
      "tgn:2000217",
      "tgn:7007158",
      "tgn:7029392"
    ],
    "placetype": [
      "aat:300008347",
      "aat:300387247"
    ],
    "id": 2016411,
    "name:xx": "Tincup"
  }
}
