{
  "type": "FeatureCollection",
  "features": [
    {
      "geometry": {
        "type": "Point",
        "coordinates": [
          -70.7667,
          43.45
        ]
      },
      "type": "Feature",
      "properties": {
        "hierarchy": [
          "tgn:2700040",
          "tgn:1000001",
          "tgn:7012149",
          "tgn:2000933",
          "tgn:7007515",
          "tgn:7029392"
        ],
        "placetype": [
          "aat:300006191"
        ],
        "id": 2700040,
        "name:xx": "Stump Pond"
      }
    },
    {
      "geometry": {
        "type": "Point",
        "coordinates": [
          -70.9667,
          43.6167
        ]
      },
      "type": "Feature",
      "properties": {
        "hierarchy": [
          "tgn:2700041",
          "tgn:1000001",
          "tgn:7012149",
          "tgn:7029392"
        ],
        "placetype": [
          "aat:300008680"
        ],
        "id": 2700041,
        "name:xx": "Stump Pond"
      }
    },
    {
      "geometry": {
        "type": "Point",
        "coordinates": [
          -71.9667,
          42.5667
        ]
      },
      "type": "Feature",
      "properties": {
        "hierarchy": [
          "tgn:2700042",
          "tgn:1000001",
          "tgn:7012149",
          "tgn:1003038",
          "tgn:7007517",
          "tgn:7029392"
        ],
        "placetype": [
          "aat:300008680"
        ],
        "id": 2700042,
        "name:xx": "Stump Pond"
      }
    },
    {
      "geometry": {
        "type": "Point",
        "coordinates": [
          -71.8833,
          42.35
        ]
      },
      "type": "Feature",
      "properties": {
        "hierarchy": [
          "tgn:2700043",
          "tgn:1000001",
          "tgn:7012149",
          "tgn:1003038",
          "tgn:7007517",
          "tgn:7029392"
        ],
        "placetype": [
          "aat:300006191"
        ],
        "id": 2700043,
        "name:xx": "Stump Pond"
      }
    },
    {
      "geometry": {
        "type": "Point",
        "coordinates": [
          -71.55,
          42.8
        ]
      },
      "type": "Feature",
      "properties": {
        "hierarchy": [
          "tgn:2700046",
          "tgn:1000001",
          "tgn:1002480",
          "tgn:7012149",
          "tgn:7007564",
          "tgn:7029392"
        ],
        "placetype": [
          "aat:300006191"
        ],
        "id": 2700046,
        "name:xx": "Stump Pond"
      }
    },
    {
      "geometry": {
        "type": "Point",
        "coordinates": [
          -70.9833,
          43.6167
        ]
      },
      "type": "Feature",
      "properties": {
        "hierarchy": [
          "tgn:2700047",
          "tgn:2001423",
          "tgn:1000001",
          "tgn:7012149",
          "tgn:7007564",
          "tgn:7029392"
        ],
        "placetype": [
          "aat:300008680"
        ],
        "id": 2700047,
        "name:xx": "Stump Pond"
      }
    },
    {
      "geometry": {
        "type": "Point",
        "coordinates": [
          -71.9333,
          42.7333
        ]
      },
      "type": "Feature",
      "properties": {
        "hierarchy": [
          "tgn:2700048",
          "tgn:7019618",
          "tgn:1000001",
          "tgn:7012149",
          "tgn:7007564",
          "tgn:7029392"
        ],
        "placetype": [
          "aat:300008680"
        ],
        "id": 2700048,
        "name:xx": "Stump Pond"
      }
    },
    {
      "geometry": {
        "type": "Point",
        "coordinates": [
          -74.1167,
          40.5833
        ]
      },
      "type": "Feature",
      "properties": {
        "hierarchy": [
          "tgn:2700049",
          "tgn:1000001",
          "tgn:7012149",
          "tgn:7015817",
          "tgn:7007568",
          "tgn:7029392"
        ],
        "placetype": [
          "aat:300008680"
        ],
        "id": 2700049,
        "name:xx": "Stump Pond"
      }
    }
  ]
}
