{
  "geometry": {
    "type": "Point",
    "coordinates": [
      0.75,
      8.75
    ]
  },
  "type": "Feature",
  "properties": {
    "hierarchy": [
      "tgn:1094880",
      "tgn:7000581",
      "tgn:7001242",
      "tgn:7016577",
      "tgn:7029392"
    ],
    "placetype": [
      "aat:300008347"
    ],
    "id": 1094880,
    "name:xx": "Fazao"
  }
}
