{
  "geometry": {
    "type": "Point",
    "coordinates": [
      -94.3333,
      43.5667
    ]
  },
  "type": "Feature",
  "properties": {
    "hierarchy": [
      "tgn:2451214",
      "tgn:1000001",
      "tgn:7012149",
      "tgn:7007521",
      "tgn:7029392"
    ],
    "placetype": [
      "aat:300008706"
    ],
    "id": 2451214,
    "name:xx": "Little Badger Creek"
  }
}
