{
  "geometry": {
    "type": "Point",
    "coordinates": [
      -100.3333,
      29.3833
    ]
  },
  "type": "Feature",
  "properties": {
    "hierarchy": [
      "tgn:2450011",
      "tgn:1000001",
      "tgn:7012149",
      "tgn:2002021",
      "tgn:7007826",
      "tgn:7029392"
    ],
    "placetype": [
      "aat:300008706"
    ],
    "id": 2450011,
    "name:xx": "Lindsey Creek"
  }
}
