{
  "geometry": {
    "type": "Point",
    "coordinates": [
      -83.4167,
      34.45
    ]
  },
  "type": "Feature",
  "properties": {
    "hierarchy": [
      "tgn:2712235",
      "tgn:2000297",
      "tgn:1000001",
      "tgn:7012149",
      "tgn:7007248",
      "tgn:7029392"
    ],
    "placetype": [
      "aat:300008706"
    ],
    "id": 2712235,
    "name:xx": "Tates Creek"
  }
}
