{
  "geometry": {
    "type": "Point",
    "coordinates": [
      -2.8833,
      34.4167
    ]
  },
  "type": "Feature",
  "properties": {
    "hierarchy": [
      "tgn:1091453",
      "tgn:7001242",
      "tgn:1000179",
      "tgn:7593698",
      "tgn:7029392"
    ],
    "placetype": [
      "aat:300008347"
    ],
    "id": 1091453,
    "name:xx": "Taourirt"
  }
}
