{
  "geometry": {
    "type": "Point",
    "coordinates": [
      -75.8167,
      37.1833
    ]
  },
  "type": "Feature",
  "properties": {
    "hierarchy": [
      "tgn:2534126",
      "tgn:1000001",
      "tgn:7012149",
      "tgn:1002730",
      "tgn:7007919",
      "tgn:7029392"
    ],
    "placetype": [
      "aat:300008791"
    ],
    "id": 2534126,
    "name:xx": "Myrtle Island"
  }
}
