{
  "geometry": {
    "type": "Point",
    "coordinates": [
      -102.3167,
      33.9167
    ]
  },
  "type": "Feature",
  "properties": {
    "hierarchy": [
      "tgn:2105666",
      "tgn:1000001",
      "tgn:7012149",
      "tgn:2002025",
      "tgn:7007826",
      "tgn:7029392"
    ],
    "placetype": [
      "aat:300008347"
    ],
    "id": 2105666,
    "name:xx": "Littlefield"
  }
}
