{
  "geometry": {
    "type": "Point",
    "coordinates": [
      -85.65,
      34.7333
    ]
  },
  "type": "Feature",
  "properties": {
    "hierarchy": [
      "tgn:2495198",
      "tgn:7002659",
      "tgn:1000001",
      "tgn:7012149",
      "tgn:7021514",
      "tgn:7029392"
    ],
    "placetype": [
      "aat:300008699"
    ],
    "id": 2495198,
    "name:xx": "Mary Branch"
  }
}
