{
  "geometry": {
    "type": "Point",
    "coordinates": [
      -78.4333,
      40.1167
    ]
  },
  "type": "Feature",
  "properties": {
    "hierarchy": [
      "tgn:2409906",
      "tgn:1002172",
      "tgn:1000001",
      "tgn:7012149",
      "tgn:7007710",
      "tgn:7029392"
    ],
    "placetype": [
      "aat:300008699"
    ],
    "id": 2409906,
    "name:xx": "Imlertown Run"
  }
}
