{
  "geometry": {
    "type": "Point",
    "coordinates": [
      -90.5167,
      43.25
    ]
  },
  "type": "Feature",
  "properties": {
    "hierarchy": [
      "tgn:2514606",
      "tgn:1000001",
      "tgn:7012149",
      "tgn:2002349",
      "tgn:7007922",
      "tgn:7029392"
    ],
    "placetype": [
      "aat:300008761"
    ],
    "id": 2514606,
    "name:xx": "Miller Hollow"
  }
}
