{
  "geometry": {
    "type": "Point",
    "coordinates": [
      -87.4833,
      32.85
    ]
  },
  "type": "Feature",
  "properties": {
    "hierarchy": [
      "tgn:2003866",
      "tgn:7002659",
      "tgn:1000001",
      "tgn:7012149",
      "tgn:2000032",
      "tgn:7029392"
    ],
    "placetype": [
      "aat:300008347",
      "aat:300387210"
    ],
    "id": 2003866,
    "name:xx": "Hogglesville"
  }
}
