{
  "geometry": {
    "type": "Point",
    "coordinates": [
      79.179156,
      24.584716
    ]
  },
  "type": "Feature",
  "properties": {
    "hierarchy": [
      "tgn:7566253",
      "tgn:1000004",
      "tgn:7000198",
      "tgn:1001894",
      "tgn:7029392"
    ],
    "placetype": [
      "aat:300008347"
    ],
    "name:en": "Kushāi",
    "id": 7566253
  }
}
