{
  "geometry": {
    "type": "Point",
    "coordinates": [
      -87.9833,
      31.0167
    ]
  },
  "type": "Feature",
  "properties": {
    "hierarchy": [
      "tgn:2495265",
      "tgn:7002659",
      "tgn:1000001",
      "tgn:7012149",
      "tgn:2000048",
      "tgn:7029392"
    ],
    "placetype": [
      "aat:300008850"
    ],
    "id": 2495265,
    "name:xx": "Mary Ida Point"
  }
}
