{
  "type": "FeatureCollection",
  "features": [
    {
      "geometry": {
        "type": "Point",
        "coordinates": [
          -103.366667,
          25.55
        ]
      },
      "type": "Feature",
      "properties": {
        "hierarchy": [
          "tgn:7440370",
          "tgn:1001853",
          "tgn:1000001",
          "tgn:7005560",
          "tgn:7029392"
        ],
        "placetype": [
          "aat:300008347"
        ],
        "id": 7440370,
        "name:xx": "San Luis"
      }
    },
    {
      "geometry": {
        "type": "Point",
        "coordinates": [
          -103.5,
          25.266667
        ]
      },
      "type": "Feature",
      "properties": {
        "hierarchy": [
          "tgn:7440371",
          "tgn:7005583",
          "tgn:1000001",
          "tgn:7005560",
          "tgn:7029392"
        ],
        "placetype": [
          "aat:300008347"
        ],
        "id": 7440371,
        "name:xx": "San Luis"
      }
    },
    {
      "geometry": {
        "type": "Point",
        "coordinates": [
          -105.05,
          24.833333
        ]
      },
      "type": "Feature",
      "properties": {
        "hierarchy": [
          "tgn:7440373",
          "tgn:7005583",
          "tgn:1000001",
          "tgn:7005560",
          "tgn:7029392"
        ],
        "placetype": [
          "aat:300008347"
        ],
        "id": 7440373,
        "name:xx": "San Luis"
      }
    },
    {
      "geometry": {
        "type": "Point",
        "coordinates": [
          -103.95,
          23.633333
        ]
      },
      "type": "Feature",
      "properties": {
        "hierarchy": [
          "tgn:7440374",
          "tgn:7005583",
          "tgn:1000001",
          "tgn:7005560",
          "tgn:7029392"
        ],
        "placetype": [
          "aat:300008347"
        ],
        "id": 7440374,
        "name:xx": "San Luis"
      }
    },
    {
      "geometry": {
        "type": "Point",
        "coordinates": [
          -103.366667,
          22.833333
        ]
      },
      "type": "Feature",
      "properties": {
        "hierarchy": [
          "tgn:7440375",
          "tgn:1000001",
          "tgn:7005601",
          "tgn:7005560",
          "tgn:7029392"
        ],
        "placetype": [
          "aat:300008347"
        ],
        "id": 7440375,
        "name:xx": "San Luis"
      }
    },
    {
      "geometry": {
        "type": "Point",
        "coordinates": [
          -102.783333,
          22.266667
        ]
      },
      "type": "Feature",
      "properties": {
        "hierarchy": [
          "tgn:7440376",
          "tgn:1000001",
          "tgn:7005601",
          "tgn:7005560",
          "tgn:7029392"
        ],
        "placetype": [
          "aat:300008347"
        ],
        "id": 7440376,
        "name:xx": "San Luis"
      }
    },
    {
      "geometry": {
        "type": "Point",
        "coordinates": [
          -88.916667,
          21.333333
        ]
      },
      "type": "Feature",
      "properties": {
        "hierarchy": [
          "tgn:7440377",
          "tgn:1000001",
          "tgn:7005600",
          "tgn:7005560",
          "tgn:7029392"
        ],
        "placetype": [
          "aat:300008347"
        ],
        "id": 7440377,
        "name:xx": "San Luis"
      }
    },
    {
      "geometry": {
        "type": "Point",
        "coordinates": [
          -88.95,
          21.133333
        ]
      },
      "type": "Feature",
      "properties": {
        "hierarchy": [
          "tgn:7440378",
          "tgn:1000001",
          "tgn:7005600",
          "tgn:7005560",
          "tgn:7029392"
        ],
        "placetype": [
          "aat:300008347"
        ],
        "id": 7440378,
        "name:xx": "San Luis"
      }
    },
    {
      "geometry": {
        "type": "Point",
        "coordinates": [
          -103.433333,
          21.1
        ]
      },
      "type": "Feature",
      "properties": {
        "hierarchy": [
          "tgn:7440379",
          "tgn:7005586",
          "tgn:1000001",
          "tgn:7005560",
          "tgn:7029392"
        ],
        "placetype": [
          "aat:300008347"
        ],
        "id": 7440379,
        "name:xx": "San Luis"
      }
    }
  ]
}
