{
  "geometry": {
    "type": "Point",
    "coordinates": [
      -88.4333,
      42.9667
    ]
  },
  "type": "Feature",
  "properties": {
    "hierarchy": [
      "tgn:2561900",
      "tgn:1000001",
      "tgn:7012149",
      "tgn:1003002",
      "tgn:7007922",
      "tgn:7029392"
    ],
    "placetype": [
      "aat:300008347"
    ],
    "id": 2561900,
    "name:xx": "Ottawa"
  }
}
