{
  "geometry": {
    "type": "Point",
    "coordinates": [
      -87.9167,
      34.4333
    ]
  },
  "type": "Feature",
  "properties": {
    "hierarchy": [
      "tgn:2604001",
      "tgn:7002659",
      "tgn:1000001",
      "tgn:7012149",
      "tgn:2000029",
      "tgn:7029392"
    ],
    "placetype": [
      "aat:300008699"
    ],
    "id": 2604001,
    "name:xx": "Quinn Branch"
  }
}
