{
  "geometry": {
    "type": "Point",
    "coordinates": [
      -73.1167,
      42.05
    ]
  },
  "type": "Feature",
  "properties": {
    "hierarchy": [
      "tgn:2574557",
      "tgn:7013388",
      "tgn:1000001",
      "tgn:7012149",
      "tgn:7007517",
      "tgn:7029392"
    ],
    "placetype": [
      "aat:300006191"
    ],
    "id": 2574557,
    "name:xx": "Pelton Reservoir"
  }
}
