{
  "geometry": {
    "type": "Point",
    "coordinates": [
      -113.0333,
      34.9833
    ]
  },
  "type": "Feature",
  "properties": {
    "hierarchy": [
      "tgn:2476568",
      "tgn:1000001",
      "tgn:7006451",
      "tgn:7012149",
      "tgn:2000103",
      "tgn:7029392"
    ],
    "placetype": [
      "aat:300006191"
    ],
    "id": 2476568,
    "name:xx": "Luteky Tank"
  }
}
