{
  "geometry": {
    "type": "Point",
    "coordinates": [
      -156.2167,
      20.75
    ]
  },
  "type": "Feature",
  "properties": {
    "hierarchy": [
      "tgn:2397780",
      "tgn:1002648",
      "tgn:1000001",
      "tgn:7019158",
      "tgn:7012149",
      "tgn:7007249",
      "tgn:7029392"
    ],
    "placetype": [
      "aat:300008699"
    ],
    "id": 2397780,
    "name:xx": "Honomanu Stream"
  }
}
