{
  "geometry": {
    "type": "Point",
    "coordinates": [
      -81.7333,
      27.7667
    ]
  },
  "type": "Feature",
  "properties": {
    "hierarchy": [
      "tgn:2625747",
      "tgn:1000001",
      "tgn:7012149",
      "tgn:1002793",
      "tgn:7007240",
      "tgn:7029392"
    ],
    "placetype": [
      "aat:300008699"
    ],
    "id": 2625747,
    "name:xx": "Rocky Branch"
  }
}
