{
  "geometry": {
    "type": "Point",
    "coordinates": [
      -79.65,
      41.8167
    ]
  },
  "type": "Feature",
  "properties": {
    "hierarchy": [
      "tgn:2309909",
      "tgn:1000001",
      "tgn:1002308",
      "tgn:7012149",
      "tgn:7007710",
      "tgn:7029392"
    ],
    "placetype": [
      "aat:300008798"
    ],
    "id": 2309909,
    "name:xx": "Eastman Hill"
  }
}
