{
  "geometry": {
    "type": "Point",
    "coordinates": [
      17.593,
      -27.666
    ]
  },
  "type": "Feature",
  "properties": {
    "hierarchy": [
      "tgn:7031948",
      "tgn:7001242",
      "tgn:7030585",
      "tgn:1000198",
      "tgn:7029392"
    ],
    "placetype": [
      "aat:300008763"
    ],
    "name:en": "Visrivier Canyon",
    "id": 7031948
  }
}
