{
  "geometry": {
    "type": "Point",
    "coordinates": [
      -150.7333,
      67.4833
    ]
  },
  "type": "Feature",
  "properties": {
    "hierarchy": [
      "tgn:2617435",
      "tgn:7006450",
      "tgn:1000001",
      "tgn:7012149",
      "tgn:2000089",
      "tgn:7029392"
    ],
    "placetype": [
      "aat:300008706"
    ],
    "id": 2617435,
    "name:xx": "Richmond Creek"
  }
}
