{
  "geometry": {
    "type": "Point",
    "coordinates": [
      4.7833,
      44.9333
    ]
  },
  "type": "Feature",
  "properties": {
    "hierarchy": [
      "tgn:1108390",
      "tgn:1000003",
      "tgn:1000070",
      "tgn:7002897",
      "tgn:7029392"
    ],
    "placetype": [
      "aat:300259572"
    ],
    "id": 1108390,
    "name:xx": "Fans, Col des"
  }
}
