{
  "geometry": {
    "type": "Point",
    "coordinates": [
      140.0333,
      36.9667
    ]
  },
  "type": "Feature",
  "properties": {
    "hierarchy": [
      "tgn:1080670",
      "tgn:1000004",
      "tgn:7000894",
      "tgn:1001034",
      "tgn:1000120",
      "tgn:7029392"
    ],
    "placetype": [
      "aat:300008347"
    ],
    "id": 1080670,
    "name:xx": "Kuroiso"
  }
}
