{
  "geometry": {
    "type": "Point",
    "coordinates": [
      32.616667,
      25.633333
    ]
  },
  "type": "Feature",
  "properties": {
    "hierarchy": [
      "tgn:7525944",
      "tgn:7001242",
      "tgn:7016833",
      "tgn:7000123",
      "tgn:7029392"
    ],
    "placetype": [
      "aat:300005926"
    ],
    "name:en": "S카d카 Ibr훮h카m",
    "id": 7525944
  }
}
