{
  "geometry": {
    "type": "Point",
    "coordinates": [
      -99.3833,
      27.5167
    ]
  },
  "type": "Feature",
  "properties": {
    "hierarchy": [
      "tgn:2493423",
      "tgn:1000001",
      "tgn:7012149",
      "tgn:2002090",
      "tgn:7007826",
      "tgn:7029392"
    ],
    "placetype": [
      "aat:300006191"
    ],
    "id": 2493423,
    "name:xx": "Mars Tank"
  }
}
