{
  "geometry": {
    "type": "Point",
    "coordinates": [
      -71.9333,
      42.2167
    ]
  },
  "type": "Feature",
  "properties": {
    "hierarchy": [
      "tgn:2188649",
      "tgn:1000001",
      "tgn:7012149",
      "tgn:1003038",
      "tgn:7007517",
      "tgn:7029392"
    ],
    "placetype": [
      "aat:300008680"
    ],
    "id": 2188649,
    "name:xx": "Bouchard Pond"
  }
}
