{
  "geometry": {
    "type": "Point",
    "coordinates": [
      -123.1167,
      46.0833
    ]
  },
  "type": "Feature",
  "properties": {
    "hierarchy": [
      "tgn:2566038",
      "tgn:1000001",
      "tgn:1002293",
      "tgn:7012149",
      "tgn:7007708",
      "tgn:7029392"
    ],
    "placetype": [
      "aat:300008706"
    ],
    "id": 2566038,
    "name:xx": "Palmer Creek"
  }
}
