{
  "geometry": {
    "type": "Point",
    "coordinates": [
      -64.8167,
      -3.1833
    ]
  },
  "type": "Feature",
  "properties": {
    "hierarchy": [
      "tgn:1122388",
      "tgn:1001826",
      "tgn:1000047",
      "tgn:7002456",
      "tgn:1000002",
      "tgn:7029392"
    ],
    "placetype": [
      "aat:300008707"
    ],
    "id": 1122388,
    "name:xx": "Caiçara"
  }
}
