{
  "geometry": {
    "type": "Point",
    "coordinates": [
      -86.7333,
      46.3833
    ]
  },
  "type": "Feature",
  "properties": {
    "hierarchy": [
      "tgn:2134271",
      "tgn:2000943",
      "tgn:1000001",
      "tgn:7012149",
      "tgn:7007520",
      "tgn:7029392"
    ],
    "placetype": [
      "aat:300008707"
    ],
    "id": 2134271,
    "name:xx": "Anna River"
  }
}
