{
  "geometry": {
    "type": "Point",
    "coordinates": [
      -177.1833,
      51.9333
    ]
  },
  "type": "Feature",
  "properties": {
    "hierarchy": [
      "tgn:2220517",
      "tgn:7030516",
      "tgn:7006450",
      "tgn:1000001",
      "tgn:7012149",
      "tgn:7029392"
    ],
    "placetype": [
      "aat:300008850"
    ],
    "id": 2220517,
    "name:xx": "Cape Miga"
  }
}
