{
  "type": "FeatureCollection",
  "features": [
    {
      "geometry": {
        "type": "Point",
        "coordinates": [
          -90.75,
          39.95
        ]
      },
      "type": "Feature",
      "properties": {
        "hierarchy": [
          "tgn:2140910",
          "tgn:1000001",
          "tgn:1002208",
          "tgn:7012149",
          "tgn:7007251",
          "tgn:7029392"
        ],
        "placetype": [
          "aat:300008699"
        ],
        "id": 2140910,
        "name:xx": "Avery Branch"
      }
    },
    {
      "geometry": {
        "type": "Point",
        "coordinates": [
          -81.85,
          36.3167
        ]
      },
      "type": "Feature",
      "properties": {
        "hierarchy": [
          "tgn:2140911",
          "tgn:1000001",
          "tgn:7012149",
          "tgn:2001882",
          "tgn:7007825",
          "tgn:7029392"
        ],
        "placetype": [
          "aat:300008699"
        ],
        "id": 2140911,
        "name:xx": "Avery Branch"
      }
    },
    {
      "geometry": {
        "type": "Point",
        "coordinates": [
          -84.6,
          35.9167
        ]
      },
      "type": "Feature",
      "properties": {
        "hierarchy": [
          "tgn:2140912",
          "tgn:1000001",
          "tgn:7012149",
          "tgn:2001909",
          "tgn:7007825",
          "tgn:7029392"
        ],
        "placetype": [
          "aat:300008699"
        ],
        "id": 2140912,
        "name:xx": "Avery Branch"
      }
    },
    {
      "geometry": {
        "type": "Point",
        "coordinates": [
          -97.4833,
          30.5
        ]
      },
      "type": "Feature",
      "properties": {
        "hierarchy": [
          "tgn:2140913",
          "tgn:1000001",
          "tgn:7012149",
          "tgn:1003026",
          "tgn:7007826",
          "tgn:7029392"
        ],
        "placetype": [
          "aat:300008699"
        ],
        "id": 2140913,
        "name:xx": "Avery Branch"
      }
    },
    {
      "geometry": {
        "type": "Point",
        "coordinates": [
          -72.4167,
          42
        ]
      },
      "type": "Feature",
      "properties": {
        "hierarchy": [
          "tgn:2140914",
          "tgn:1000001",
          "tgn:1002949",
          "tgn:7012149",
          "tgn:7007159",
          "tgn:7029392"
        ],
        "placetype": [
          "aat:300008699"
        ],
        "id": 2140914,
        "name:xx": "Avery Brook"
      }
    },
    {
      "geometry": {
        "type": "Point",
        "coordinates": [
          -68.4167,
          45.0667
        ]
      },
      "type": "Feature",
      "properties": {
        "hierarchy": [
          "tgn:2140915",
          "tgn:1000001",
          "tgn:7012149",
          "tgn:2000927",
          "tgn:7007515",
          "tgn:7029392"
        ],
        "placetype": [
          "aat:300008699"
        ],
        "id": 2140915,
        "name:xx": "Avery Brook"
      }
    },
    {
      "geometry": {
        "type": "Point",
        "coordinates": [
          -69.6833,
          46.3
        ]
      },
      "type": "Feature",
      "properties": {
        "hierarchy": [
          "tgn:2140916",
          "tgn:1000001",
          "tgn:7012149",
          "tgn:2000928",
          "tgn:7007515",
          "tgn:7029392"
        ],
        "placetype": [
          "aat:300008699"
        ],
        "id": 2140916,
        "name:xx": "Avery Brook"
      }
    },
    {
      "geometry": {
        "type": "Point",
        "coordinates": [
          -72.8167,
          42.6667
        ]
      },
      "type": "Feature",
      "properties": {
        "hierarchy": [
          "tgn:2140917",
          "tgn:1000001",
          "tgn:7013942",
          "tgn:7012149",
          "tgn:7007517",
          "tgn:7029392"
        ],
        "placetype": [
          "aat:300008699"
        ],
        "id": 2140917,
        "name:xx": "Avery Brook"
      }
    },
    {
      "geometry": {
        "type": "Point",
        "coordinates": [
          -71.7333,
          43.85
        ]
      },
      "type": "Feature",
      "properties": {
        "hierarchy": [
          "tgn:2140918",
          "tgn:1000001",
          "tgn:2001424",
          "tgn:7012149",
          "tgn:7007564",
          "tgn:7029392"
        ],
        "placetype": [
          "aat:300008699"
        ],
        "id": 2140918,
        "name:xx": "Avery Brook"
      }
    },
    {
      "geometry": {
        "type": "Point",
        "coordinates": [
          -72.3,
          43.7833
        ]
      },
      "type": "Feature",
      "properties": {
        "hierarchy": [
          "tgn:2140919",
          "tgn:1000001",
          "tgn:7012149",
          "tgn:7007828",
          "tgn:7029392"
        ],
        "placetype": [
          "aat:300008699"
        ],
        "id": 2140919,
        "name:xx": "Avery Brook"
      }
    }
  ]
}
