{
  "type": "FeatureCollection",
  "features": [
    {
      "geometry": {
        "type": "Point",
        "coordinates": [
          4.291101,
          51.212543
        ]
      },
      "type": "Feature",
      "properties": {
        "hierarchy": [
          "tgn:7252352",
          "tgn:7003457",
          "tgn:1000003",
          "tgn:1000063",
          "tgn:7018236",
          "tgn:7029392"
        ],
        "placetype": [
          "aat:300008699"
        ],
        "id": 7252352,
        "name:xx": "Molenbeek"
      }
    },
    {
      "geometry": {
        "type": "Point",
        "coordinates": [
          4.036427,
          51.191456
        ]
      },
      "type": "Feature",
      "properties": {
        "hierarchy": [
          "tgn:7252353",
          "tgn:7003457",
          "tgn:1000003",
          "tgn:1000063",
          "tgn:7018236",
          "tgn:7029392"
        ],
        "placetype": [
          "aat:300008699"
        ],
        "id": 7252353,
        "name:xx": "Molenbeek"
      }
    },
    {
      "geometry": {
        "type": "Point",
        "coordinates": [
          4.633333,
          51.166667
        ]
      },
      "type": "Feature",
      "properties": {
        "hierarchy": [
          "tgn:7252354",
          "tgn:7003456",
          "tgn:1000003",
          "tgn:1000063",
          "tgn:7018236",
          "tgn:7029392"
        ],
        "placetype": [
          "aat:300008699"
        ],
        "id": 7252354,
        "name:xx": "Molenbeek"
      }
    },
    {
      "geometry": {
        "type": "Point",
        "coordinates": [
          4.366667,
          51.1
        ]
      },
      "type": "Feature",
      "properties": {
        "hierarchy": [
          "tgn:7252355",
          "tgn:7003456",
          "tgn:1000003",
          "tgn:1000063",
          "tgn:7018236",
          "tgn:7029392"
        ],
        "placetype": [
          "aat:300008699"
        ],
        "id": 7252355,
        "name:xx": "Molenbeek"
      }
    },
    {
      "geometry": {
        "type": "Point",
        "coordinates": [
          4.25,
          51.05
        ]
      },
      "type": "Feature",
      "properties": {
        "hierarchy": [
          "tgn:7252356",
          "tgn:7003456",
          "tgn:1000003",
          "tgn:1000063",
          "tgn:7018236",
          "tgn:7029392"
        ],
        "placetype": [
          "aat:300008699"
        ],
        "id": 7252356,
        "name:xx": "Molenbeek"
      }
    },
    {
      "geometry": {
        "type": "Point",
        "coordinates": [
          4.783333,
          51.066667
        ]
      },
      "type": "Feature",
      "properties": {
        "hierarchy": [
          "tgn:7252357",
          "tgn:7003456",
          "tgn:1000003",
          "tgn:1000063",
          "tgn:7018236",
          "tgn:7029392"
        ],
        "placetype": [
          "aat:300008699"
        ],
        "id": 7252357,
        "name:xx": "Molenbeek"
      }
    },
    {
      "geometry": {
        "type": "Point",
        "coordinates": [
          3.883333,
          50.766667
        ]
      },
      "type": "Feature",
      "properties": {
        "hierarchy": [
          "tgn:7252359",
          "tgn:7003457",
          "tgn:1000003",
          "tgn:1000063",
          "tgn:7018236",
          "tgn:7029392"
        ],
        "placetype": [
          "aat:300008699"
        ],
        "id": 7252359,
        "name:xx": "Molenbeek"
      }
    }
  ]
}
