{
  "type": "FeatureCollection",
  "features": [
    {
      "geometry": {
        "type": "Point",
        "coordinates": [
          -105.05,
          37.9833
        ]
      },
      "type": "Feature",
      "properties": {
        "hierarchy": [
          "tgn:2016260",
          "tgn:1000001",
          "tgn:7012149",
          "tgn:2000205",
          "tgn:7007158",
          "tgn:7029392"
        ],
        "placetype": [
          "aat:300008347",
          "aat:300387247"
        ],
        "id": 2016260,
        "name:xx": "San Isabel"
      }
    },
    {
      "geometry": {
        "type": "Point",
        "coordinates": [
          -105.4167,
          37.2
        ]
      },
      "type": "Feature",
      "properties": {
        "hierarchy": [
          "tgn:2016262",
          "tgn:1000001",
          "tgn:7012149",
          "tgn:2000203",
          "tgn:7007158",
          "tgn:7029392"
        ],
        "placetype": [
          "aat:300008347"
        ],
        "id": 2016262,
        "name:xx": "San Luis"
      }
    },
    {
      "geometry": {
        "type": "Point",
        "coordinates": [
          -105.3833,
          37.1333
        ]
      },
      "type": "Feature",
      "properties": {
        "hierarchy": [
          "tgn:2016263",
          "tgn:1000001",
          "tgn:7012149",
          "tgn:2000203",
          "tgn:7007158",
          "tgn:7029392"
        ],
        "placetype": [
          "aat:300008347"
        ],
        "id": 2016263,
        "name:xx": "San Pablo"
      }
    },
    {
      "geometry": {
        "type": "Point",
        "coordinates": [
          -105.4,
          37.15
        ]
      },
      "type": "Feature",
      "properties": {
        "hierarchy": [
          "tgn:2016264",
          "tgn:1000001",
          "tgn:7012149",
          "tgn:2000203",
          "tgn:7007158",
          "tgn:7029392"
        ],
        "placetype": [
          "aat:300008347"
        ],
        "id": 2016264,
        "name:xx": "San Pedro"
      }
    },
    {
      "geometry": {
        "type": "Point",
        "coordinates": [
          -107.3,
          38.45
        ]
      },
      "type": "Feature",
      "properties": {
        "hierarchy": [
          "tgn:2016265",
          "tgn:1000001",
          "tgn:7012149",
          "tgn:2000217",
          "tgn:7007158",
          "tgn:7029392"
        ],
        "placetype": [
          "aat:300008347"
        ],
        "id": 2016265,
        "name:xx": "Sapinero"
      }
    },
    {
      "geometry": {
        "type": "Point",
        "coordinates": [
          -104.75,
          37.1167
        ]
      },
      "type": "Feature",
      "properties": {
        "hierarchy": [
          "tgn:2016266",
          "tgn:1000001",
          "tgn:7012149",
          "tgn:2000227",
          "tgn:7007158",
          "tgn:7029392"
        ],
        "placetype": [
          "aat:300008347"
        ],
        "id": 2016266,
        "name:xx": "Sarcillo"
      }
    },
    {
      "geometry": {
        "type": "Point",
        "coordinates": [
          -106.4,
          38.4
        ]
      },
      "type": "Feature",
      "properties": {
        "hierarchy": [
          "tgn:2016268",
          "tgn:1000001",
          "tgn:7012149",
          "tgn:7007158",
          "tgn:2000246",
          "tgn:7029392"
        ],
        "placetype": [
          "aat:300008347"
        ],
        "id": 2016268,
        "name:xx": "Sargents"
      }
    }
  ]
}
