{
  "geometry": {
    "type": "Point",
    "coordinates": [
      143.6333,
      -38.0333
    ]
  },
  "type": "Feature",
  "properties": {
    "hierarchy": [
      "tgn:1096671",
      "tgn:7000490",
      "tgn:1000006",
      "tgn:7006238",
      "tgn:7029392"
    ],
    "placetype": [
      "aat:300008347"
    ],
    "id": 1096671,
    "name:xx": "Cressy"
  }
}
