{
  "type": "FeatureCollection",
  "features": [
    {
      "geometry": {
        "type": "Point",
        "coordinates": [
          6.6667,
          44.5
        ]
      },
      "type": "Feature",
      "properties": {
        "hierarchy": [
          "tgn:1109460",
          "tgn:1000003",
          "tgn:1000070",
          "tgn:7002895",
          "tgn:7029392"
        ],
        "placetype": [
          "aat:300008795"
        ],
        "id": 1109460,
        "name:xx": "Parpaillon, Montagne de"
      }
    },
    {
      "geometry": {
        "type": "Point",
        "coordinates": [
          -0.633333,
          42.516667
        ]
      },
      "type": "Feature",
      "properties": {
        "hierarchy": [
          "tgn:1109461",
          "tgn:7002759",
          "tgn:1000003",
          "tgn:1000095",
          "tgn:7029392"
        ],
        "placetype": [
          "aat:300386831",
          "aat:300008795"
        ],
        "id": 1109461,
        "name:xx": "Peña, Sierra de la"
      }
    },
    {
      "geometry": {
        "type": "Point",
        "coordinates": [
          -109,
          32.2
        ]
      },
      "type": "Feature",
      "properties": {
        "hierarchy": [
          "tgn:1109464",
          "tgn:1000001",
          "tgn:7012149",
          "tgn:7029392"
        ],
        "placetype": [
          "aat:300008795"
        ],
        "id": 1109464,
        "name:xx": "Peloncillo Mountains"
      }
    },
    {
      "geometry": {
        "type": "Point",
        "coordinates": [
          15.333333,
          38.05
        ]
      },
      "type": "Feature",
      "properties": {
        "hierarchy": [
          "tgn:1109465",
          "tgn:1000003",
          "tgn:7003122",
          "tgn:7003157",
          "tgn:1000080",
          "tgn:7029392"
        ],
        "placetype": [
          "aat:300008795"
        ],
        "id": 1109465,
        "name:xx": "Peloritani, Monti"
      }
    },
    {
      "geometry": {
        "type": "Point",
        "coordinates": [
          -2.0833,
          54.15
        ]
      },
      "type": "Feature",
      "properties": {
        "hierarchy": [
          "tgn:1109468",
          "tgn:7002445",
          "tgn:1000003",
          "tgn:7008591",
          "tgn:7029392"
        ],
        "placetype": [
          "aat:300008795"
        ],
        "id": 1109468,
        "name:xx": "Pennine Chain"
      }
    }
  ]
}
