{
  "type": "FeatureCollection",
  "features": [
    {
      "geometry": {
        "type": "Point",
        "coordinates": [
          -78.05,
          38.5
        ]
      },
      "type": "Feature",
      "properties": {
        "hierarchy": [
          "tgn:2113410",
          "tgn:1000001",
          "tgn:7012149",
          "tgn:2002155",
          "tgn:7007919",
          "tgn:7029392"
        ],
        "placetype": [
          "aat:300008347"
        ],
        "id": 2113410,
        "name:xx": "Norman"
      }
    },
    {
      "geometry": {
        "type": "Point",
        "coordinates": [
          -76.4,
          37.4333
        ]
      },
      "type": "Feature",
      "properties": {
        "hierarchy": [
          "tgn:2113411",
          "tgn:1000001",
          "tgn:7012149",
          "tgn:1002647",
          "tgn:7007919",
          "tgn:7029392"
        ],
        "placetype": [
          "aat:300008347"
        ],
        "id": 2113411,
        "name:xx": "North"
      }
    },
    {
      "geometry": {
        "type": "Point",
        "coordinates": [
          -78.45,
          38.0667
        ]
      },
      "type": "Feature",
      "properties": {
        "hierarchy": [
          "tgn:2113413",
          "tgn:2002137",
          "tgn:1000001",
          "tgn:7012149",
          "tgn:7007919",
          "tgn:7029392"
        ],
        "placetype": [
          "aat:300008347"
        ],
        "id": 2113413,
        "name:xx": "Northfields"
      }
    },
    {
      "geometry": {
        "type": "Point",
        "coordinates": [
          -77.6833,
          39.05
        ]
      },
      "type": "Feature",
      "properties": {
        "hierarchy": [
          "tgn:2113414",
          "tgn:1000001",
          "tgn:7012149",
          "tgn:7015770",
          "tgn:7007919",
          "tgn:7029392"
        ],
        "placetype": [
          "aat:300008347",
          "aat:300387210"
        ],
        "id": 2113414,
        "name:xx": "North Fork"
      }
    },
    {
      "geometry": {
        "type": "Point",
        "coordinates": [
          -81.1,
          37.25
        ]
      },
      "type": "Feature",
      "properties": {
        "hierarchy": [
          "tgn:2113415",
          "tgn:1000001",
          "tgn:2002145",
          "tgn:7012149",
          "tgn:7007919",
          "tgn:7029392"
        ],
        "placetype": [
          "aat:300008347",
          "aat:300387210"
        ],
        "id": 2113415,
        "name:xx": "North Gap"
      }
    },
    {
      "geometry": {
        "type": "Point",
        "coordinates": [
          -78.6333,
          37.9333
        ]
      },
      "type": "Feature",
      "properties": {
        "hierarchy": [
          "tgn:2113416",
          "tgn:2002137",
          "tgn:1000001",
          "tgn:7012149",
          "tgn:7007919",
          "tgn:7029392"
        ],
        "placetype": [
          "aat:300008347"
        ],
        "id": 2113416,
        "name:xx": "North Garden"
      }
    },
    {
      "geometry": {
        "type": "Point",
        "coordinates": [
          -78.95,
          37.0167
        ]
      },
      "type": "Feature",
      "properties": {
        "hierarchy": [
          "tgn:2113418",
          "tgn:1000001",
          "tgn:7012149",
          "tgn:2002166",
          "tgn:7007919",
          "tgn:7029392"
        ],
        "placetype": [
          "aat:300008347",
          "aat:300387210"
        ],
        "id": 2113418,
        "name:xx": "North Halifax"
      }
    },
    {
      "geometry": {
        "type": "Point",
        "coordinates": [
          -81.7,
          36.9
        ]
      },
      "type": "Feature",
      "properties": {
        "hierarchy": [
          "tgn:2113419",
          "tgn:1000001",
          "tgn:7012149",
          "tgn:2002191",
          "tgn:7007919",
          "tgn:7029392"
        ],
        "placetype": [
          "aat:300008347"
        ],
        "id": 2113419,
        "name:xx": "North Holston"
      }
    }
  ]
}
