{
  "geometry": {
    "type": "Point",
    "coordinates": [
      -55.8833,
      50.9167
    ]
  },
  "type": "Feature",
  "properties": {
    "hierarchy": [
      "tgn:1014181",
      "tgn:7005685",
      "tgn:7005807",
      "tgn:1000001",
      "tgn:7005801",
      "tgn:7029392"
    ],
    "placetype": [
      "aat:300008347"
    ],
    "id": 1014181,
    "name:xx": "Conche"
  }
}
