{
  "geometry": {
    "type": "Point",
    "coordinates": [
      118.3833,
      41.8333
    ]
  },
  "type": "Feature",
  "properties": {
    "hierarchy": [
      "tgn:1072495",
      "tgn:1000004",
      "tgn:7001838",
      "tgn:1000111",
      "tgn:7029392"
    ],
    "placetype": [
      "aat:300008347"
    ],
    "id": 1072495,
    "name:xx": "Wangyefu"
  }
}
