{
  "geometry": {
    "type": "Point",
    "coordinates": [
      -94.4333,
      35.35
    ]
  },
  "type": "Feature",
  "properties": {
    "hierarchy": [
      "tgn:2082799",
      "tgn:1000001",
      "tgn:7012149",
      "tgn:2001662",
      "tgn:7007707",
      "tgn:7029392"
    ],
    "placetype": [
      "aat:300008347"
    ],
    "id": 2082799,
    "name:xx": "Arkoma"
  }
}
