{
  "geometry": {
    "type": "Point",
    "coordinates": [
      -84.2833,
      35.9167
    ]
  },
  "type": "Feature",
  "properties": {
    "hierarchy": [
      "tgn:2505462",
      "tgn:1000001",
      "tgn:7012149",
      "tgn:2001909",
      "tgn:7007825",
      "tgn:7029392"
    ],
    "placetype": [
      "aat:300008699"
    ],
    "id": 2505462,
    "name:xx": "Melton Branch"
  }
}
