{
  "geometry": {
    "type": "Point",
    "coordinates": [
      84.24833,
      25.183758
    ]
  },
  "type": "Feature",
  "properties": {
    "hierarchy": [
      "tgn:7571293",
      "tgn:1000004",
      "tgn:1001842",
      "tgn:7000198",
      "tgn:7029392"
    ],
    "placetype": [
      "aat:300008347"
    ],
    "name:en": "Ghusiya Kalān",
    "id": 7571293
  }
}
