{
  "geometry": {
    "type": "Point",
    "coordinates": [
      -88.8333,
      34.5667
    ]
  },
  "type": "Feature",
  "properties": {
    "hierarchy": [
      "tgn:2210577",
      "tgn:1000001",
      "tgn:7012149",
      "tgn:2001158",
      "tgn:7007522",
      "tgn:7029392"
    ],
    "placetype": [
      "aat:300008706"
    ],
    "id": 2210577,
    "name:xx": "Bussel Creek"
  }
}
