{
  "type": "FeatureCollection",
  "features": [
    {
      "geometry": {
        "type": "Point",
        "coordinates": [
          -80.9167,
          25.4167
        ]
      },
      "type": "Feature",
      "properties": {
        "hierarchy": [
          "tgn:2141030",
          "tgn:1000001",
          "tgn:7012149",
          "tgn:1002676",
          "tgn:7007240",
          "tgn:7029392"
        ],
        "placetype": [
          "aat:300008706"
        ],
        "id": 2141030,
        "name:xx": "Avocado Creek"
      }
    },
    {
      "geometry": {
        "type": "Point",
        "coordinates": [
          -119.4,
          36.7833
        ]
      },
      "type": "Feature",
      "properties": {
        "hierarchy": [
          "tgn:2141031",
          "tgn:1000001",
          "tgn:7012149",
          "tgn:1002392",
          "tgn:7007157",
          "tgn:7029392"
        ],
        "placetype": [
          "aat:300008680"
        ],
        "id": 2141031,
        "name:xx": "Avocado Lake"
      }
    },
    {
      "geometry": {
        "type": "Point",
        "coordinates": [
          -113.35,
          39.8333
        ]
      },
      "type": "Feature",
      "properties": {
        "hierarchy": [
          "tgn:2141032",
          "tgn:1000001",
          "tgn:7012149",
          "tgn:2002112",
          "tgn:7007827",
          "tgn:7029392"
        ],
        "placetype": [
          "aat:300006191"
        ],
        "id": 2141032,
        "name:xx": "Avocet Pool"
      }
    },
    {
      "geometry": {
        "type": "Point",
        "coordinates": [
          -164.8667,
          62.6
        ]
      },
      "type": "Feature",
      "properties": {
        "hierarchy": [
          "tgn:2141033",
          "tgn:7006450",
          "tgn:1000001",
          "tgn:7012149",
          "tgn:2000087",
          "tgn:7029392"
        ],
        "placetype": [
          "aat:300008791"
        ],
        "id": 2141033,
        "name:xx": "Avogon Island"
      }
    },
    {
      "geometry": {
        "type": "Point",
        "coordinates": [
          -70.2667,
          44.8
        ]
      },
      "type": "Feature",
      "properties": {
        "hierarchy": [
          "tgn:2141035",
          "tgn:1000001",
          "tgn:2000921",
          "tgn:7012149",
          "tgn:7007515",
          "tgn:7029392"
        ],
        "placetype": [
          "aat:300008347"
        ],
        "id": 2141035,
        "name:xx": "Avon"
      }
    },
    {
      "geometry": {
        "type": "Point",
        "coordinates": [
          -111.8,
          41.5167
        ]
      },
      "type": "Feature",
      "properties": {
        "hierarchy": [
          "tgn:2141036",
          "tgn:1000001",
          "tgn:2002103",
          "tgn:7012149",
          "tgn:7007827",
          "tgn:7029392"
        ],
        "placetype": [
          "aat:300008347"
        ],
        "id": 2141036,
        "name:xx": "Avon"
      }
    },
    {
      "geometry": {
        "type": "Point",
        "coordinates": [
          -82.05,
          41.5
        ]
      },
      "type": "Feature",
      "properties": {
        "hierarchy": [
          "tgn:2141037",
          "tgn:1000001",
          "tgn:7012149",
          "tgn:1002607",
          "tgn:7007706",
          "tgn:7029392"
        ],
        "placetype": [
          "aat:300386845"
        ],
        "id": 2141037,
        "name:xx": "Avon Basin"
      }
    },
    {
      "geometry": {
        "type": "Point",
        "coordinates": [
          -82.0167,
          41.45
        ]
      },
      "type": "Feature",
      "properties": {
        "hierarchy": [
          "tgn:2141038",
          "tgn:1000001",
          "tgn:7012149",
          "tgn:1002607",
          "tgn:7007706",
          "tgn:7029392"
        ],
        "placetype": [
          "aat:300008347"
        ],
        "id": 2141038,
        "name:xx": "Avon Center"
      }
    },
    {
      "geometry": {
        "type": "Point",
        "coordinates": [
          -70.25,
          44.8
        ]
      },
      "type": "Feature",
      "properties": {
        "hierarchy": [
          "tgn:2141039",
          "tgn:1000001",
          "tgn:2000921",
          "tgn:7012149",
          "tgn:7007515",
          "tgn:7029392"
        ],
        "placetype": [
          "aat:300008347"
        ],
        "id": 2141039,
        "name:xx": "Avon Corner"
      }
    }
  ]
}
