{
  "geometry": {
    "type": "Point",
    "coordinates": [
      -121.1833,
      40.7667
    ]
  },
  "type": "Feature",
  "properties": {
    "hierarchy": [
      "tgn:2178561",
      "tgn:1000001",
      "tgn:7012149",
      "tgn:7007157",
      "tgn:2000184",
      "tgn:7029392"
    ],
    "placetype": [
      "aat:300008798"
    ],
    "id": 2178561,
    "name:xx": "Blacks Mountain"
  }
}
