{
  "type": "FeatureCollection",
  "features": [
    {
      "geometry": {
        "type": "Point",
        "coordinates": [
          -97.65,
          31.7333
        ]
      },
      "type": "Feature",
      "properties": {
        "hierarchy": [
          "tgn:2269020",
          "tgn:1000001",
          "tgn:1002191",
          "tgn:7012149",
          "tgn:7007826",
          "tgn:7029392"
        ],
        "placetype": [
          "aat:300008347"
        ],
        "id": 2269020,
        "name:xx": "Crossroad Store"
      }
    },
    {
      "geometry": {
        "type": "Point",
        "coordinates": [
          -111.0333,
          34.65
        ]
      },
      "type": "Feature",
      "properties": {
        "hierarchy": [
          "tgn:2269021",
          "tgn:1000001",
          "tgn:7006451",
          "tgn:2000092",
          "tgn:7012149",
          "tgn:7029392"
        ],
        "placetype": [
          "aat:300006191"
        ],
        "id": 2269021,
        "name:xx": "Crossroad Tank"
      }
    },
    {
      "geometry": {
        "type": "Point",
        "coordinates": [
          -106.25,
          33.2167
        ]
      },
      "type": "Feature",
      "properties": {
        "hierarchy": [
          "tgn:2269022",
          "tgn:1000001",
          "tgn:7012149",
          "tgn:2001447",
          "tgn:7007566",
          "tgn:7029392"
        ],
        "placetype": [
          "aat:300006191"
        ],
        "id": 2269022,
        "name:xx": "Crossroad Tank"
      }
    },
    {
      "geometry": {
        "type": "Point",
        "coordinates": [
          -86.0667,
          39.75
        ]
      },
      "type": "Feature",
      "properties": {
        "hierarchy": [
          "tgn:2269023",
          "tgn:1000001",
          "tgn:7012149",
          "tgn:1002633",
          "tgn:7007252",
          "tgn:7029392"
        ],
        "placetype": [
          "aat:300008347"
        ],
        "id": 2269023,
        "name:xx": "Crossroad Temple"
      }
    },
    {
      "geometry": {
        "type": "Point",
        "coordinates": [
          -93.7167,
          33.7167
        ]
      },
      "type": "Feature",
      "properties": {
        "hierarchy": [
          "tgn:2269024",
          "tgn:1000001",
          "tgn:7016172",
          "tgn:7012149",
          "tgn:2000133",
          "tgn:7029392"
        ],
        "placetype": [
          "aat:300008347"
        ],
        "id": 2269024,
        "name:xx": "Crossroads"
      }
    },
    {
      "geometry": {
        "type": "Point",
        "coordinates": [
          -93.4833,
          35.1833
        ]
      },
      "type": "Feature",
      "properties": {
        "hierarchy": [
          "tgn:2269025",
          "tgn:1000001",
          "tgn:7016172",
          "tgn:7012149",
          "tgn:2000179",
          "tgn:7029392"
        ],
        "placetype": [
          "aat:300008347"
        ],
        "id": 2269025,
        "name:xx": "Crossroads"
      }
    },
    {
      "geometry": {
        "type": "Point",
        "coordinates": [
          -92.0833,
          36.1833
        ]
      },
      "type": "Feature",
      "properties": {
        "hierarchy": [
          "tgn:2269026",
          "tgn:1000001",
          "tgn:7016172",
          "tgn:7012149",
          "tgn:2000137",
          "tgn:7029392"
        ],
        "placetype": [
          "aat:300008347"
        ],
        "id": 2269026,
        "name:xx": "Crossroads"
      }
    },
    {
      "geometry": {
        "type": "Point",
        "coordinates": [
          -92.6333,
          34.8833
        ]
      },
      "type": "Feature",
      "properties": {
        "hierarchy": [
          "tgn:2269027",
          "tgn:1000001",
          "tgn:7016172",
          "tgn:7012149",
          "tgn:2000164",
          "tgn:7029392"
        ],
        "placetype": [
          "aat:300008347"
        ],
        "id": 2269027,
        "name:xx": "Crossroads"
      }
    },
    {
      "geometry": {
        "type": "Point",
        "coordinates": [
          -83.1333,
          30.4833
        ]
      },
      "type": "Feature",
      "properties": {
        "hierarchy": [
          "tgn:2269028",
          "tgn:1000001",
          "tgn:2000271",
          "tgn:7012149",
          "tgn:7007240",
          "tgn:7029392"
        ],
        "placetype": [
          "aat:300008347"
        ],
        "id": 2269028,
        "name:xx": "Crossroads"
      }
    },
    {
      "geometry": {
        "type": "Point",
        "coordinates": [
          -84.7333,
          31.3333
        ]
      },
      "type": "Feature",
      "properties": {
        "hierarchy": [
          "tgn:2269029",
          "tgn:1000001",
          "tgn:7012149",
          "tgn:2000340",
          "tgn:7007248",
          "tgn:7029392"
        ],
        "placetype": [
          "aat:300008347"
        ],
        "id": 2269029,
        "name:xx": "Crossroads"
      }
    }
  ]
}
