{
  "geometry": {
    "type": "Point",
    "coordinates": [
      -91.4667,
      38.4167
    ]
  },
  "type": "Feature",
  "properties": {
    "hierarchy": [
      "tgn:2328861",
      "tgn:1000001",
      "tgn:7012149",
      "tgn:1002402",
      "tgn:7007523",
      "tgn:7029392"
    ],
    "placetype": [
      "aat:300006191"
    ],
    "id": 2328861,
    "name:xx": "Fishing Lake"
  }
}
