{
  "geometry": {
    "type": "Point",
    "coordinates": [
      -110.15,
      40.0833
    ]
  },
  "type": "Feature",
  "properties": {
    "hierarchy": [
      "tgn:2587836",
      "tgn:1000001",
      "tgn:7012149",
      "tgn:7007827",
      "tgn:7029392"
    ],
    "placetype": [
      "aat:300008761"
    ],
    "id": 2587836,
    "name:xx": "Pleasant Valley"
  }
}
