{
  "geometry": {
    "type": "Point",
    "coordinates": [
      -111.2333,
      37.3333
    ]
  },
  "type": "Feature",
  "properties": {
    "hierarchy": [
      "tgn:2703907",
      "tgn:1000001",
      "tgn:7012149",
      "tgn:2002113",
      "tgn:7007827",
      "tgn:7029392"
    ],
    "placetype": [
      "aat:300008761"
    ],
    "id": 2703907,
    "name:xx": "Sunday Canyon"
  }
}
