{
  "geometry": {
    "type": "Point",
    "coordinates": [
      85.833333,
      19.866667
    ]
  },
  "type": "Feature",
  "properties": {
    "hierarchy": [
      "tgn:7554386",
      "tgn:1000004",
      "tgn:7000198",
      "tgn:7016694",
      "tgn:7029392"
    ],
    "placetype": [
      "aat:300007783"
    ],
    "name:en": "Mālatīpātpur",
    "id": 7554386
  }
}
