{
  "geometry": {
    "type": "Point",
    "coordinates": [
      -90.3333,
      37.6167
    ]
  },
  "type": "Feature",
  "properties": {
    "hierarchy": [
      "tgn:2766774",
      "tgn:1000001",
      "tgn:7012149",
      "tgn:2001217",
      "tgn:7007523",
      "tgn:7029392"
    ],
    "placetype": [
      "aat:300008699"
    ],
    "id": 2766774,
    "name:xx": "White Oak Springs Branch"
  }
}
