{
  "geometry": {
    "type": "Point",
    "coordinates": [
      -120.1167,
      46.05
    ]
  },
  "type": "Feature",
  "properties": {
    "hierarchy": [
      "tgn:2421211",
      "tgn:1000001",
      "tgn:7012149",
      "tgn:7007920",
      "tgn:7029392"
    ],
    "placetype": [
      "aat:300008761"
    ],
    "id": 2421211,
    "name:xx": "Jerry Canyon"
  }
}
