{
  "geometry": {
    "type": "Point",
    "coordinates": [
      -106.1833,
      39.3667
    ]
  },
  "type": "Feature",
  "properties": {
    "hierarchy": [
      "tgn:2204863",
      "tgn:1000001",
      "tgn:7012149",
      "tgn:7007158",
      "tgn:7029392"
    ],
    "placetype": [
      "aat:300008680"
    ],
    "id": 2204863,
    "name:xx": "Buffehr Lake"
  }
}
