{
  "geometry": {
    "type": "Point",
    "coordinates": [
      37.8333,
      54.3333
    ]
  },
  "type": "Feature",
  "properties": {
    "hierarchy": [
      "tgn:1003418",
      "tgn:1000004",
      "tgn:7018214",
      "tgn:7002435",
      "tgn:7029392"
    ],
    "placetype": [
      "aat:300387145",
      "aat:300235107"
    ],
    "id": 1003418,
    "name:xx": "Tulskaya Oblast'"
  }
}
