{
  "geometry": {
    "type": "Point",
    "coordinates": [
      73.533333,
      19.066667
    ]
  },
  "type": "Feature",
  "properties": {
    "hierarchy": [
      "tgn:7545532",
      "tgn:1000004",
      "tgn:7000198",
      "tgn:1001895",
      "tgn:7029392"
    ],
    "placetype": [
      "aat:300008347"
    ],
    "name:en": "Bhīmāshankar",
    "id": 7545532
  }
}
