{
  "geometry": {
    "type": "Point",
    "coordinates": [
      -113.9167,
      39.8833
    ]
  },
  "type": "Feature",
  "properties": {
    "hierarchy": [
      "tgn:2283351",
      "tgn:1000001",
      "tgn:7012149",
      "tgn:2002112",
      "tgn:7007827",
      "tgn:7029392"
    ],
    "placetype": [
      "aat:300386845"
    ],
    "id": 2283351,
    "name:xx": "Delle, The"
  }
}
