{
  "geometry": {
    "type": "Point",
    "coordinates": [
      -111.4833,
      41.4333
    ]
  },
  "type": "Feature",
  "properties": {
    "hierarchy": [
      "tgn:2288174",
      "tgn:1000001",
      "tgn:7012149",
      "tgn:2002117",
      "tgn:7007827",
      "tgn:7029392"
    ],
    "placetype": [
      "aat:300008761"
    ],
    "id": 2288174,
    "name:xx": "Dip Hollow"
  }
}
