{
  "geometry": {
    "type": "Point",
    "coordinates": [
      14.6667,
      57.65
    ]
  },
  "type": "Feature",
  "properties": {
    "hierarchy": [
      "tgn:1063412",
      "tgn:1000003",
      "tgn:1000396",
      "tgn:1000097",
      "tgn:7029392"
    ],
    "placetype": [
      "aat:300008347"
    ],
    "id": 1063412,
    "name:xx": "Nässjö"
  }
}
