{
  "geometry": {
    "type": "Point",
    "coordinates": [
      -111.4167,
      31.4333
    ]
  },
  "type": "Feature",
  "properties": {
    "hierarchy": [
      "tgn:2187937",
      "tgn:1000001",
      "tgn:7006451",
      "tgn:7012149",
      "tgn:2000100",
      "tgn:7029392"
    ],
    "placetype": [
      "aat:300000390"
    ],
    "id": 2187937,
    "name:xx": "Border Mine"
  }
}
