{
  "geometry": {
    "type": "Point",
    "coordinates": [
      -80.8833,
      32.3833
    ]
  },
  "type": "Feature",
  "properties": {
    "hierarchy": [
      "tgn:2484679",
      "tgn:1000001",
      "tgn:7012149",
      "tgn:2001751",
      "tgn:7007712",
      "tgn:7029392"
    ],
    "placetype": [
      "aat:300008850"
    ],
    "id": 2484679,
    "name:xx": "Laurel Point"
  }
}
