{
  "type": "FeatureCollection",
  "features": [
    {
      "geometry": {
        "type": "Point",
        "coordinates": [
          -83.3167,
          38.55
        ]
      },
      "type": "Feature",
      "properties": {
        "hierarchy": [
          "tgn:2624620",
          "tgn:1000001",
          "tgn:7012149",
          "tgn:1002591",
          "tgn:7007255",
          "tgn:7029392"
        ],
        "placetype": [
          "aat:300008699"
        ],
        "id": 2624620,
        "name:xx": "Rock Run"
      }
    },
    {
      "geometry": {
        "type": "Point",
        "coordinates": [
          -76.1833,
          39.5667
        ]
      },
      "type": "Feature",
      "properties": {
        "hierarchy": [
          "tgn:2624621",
          "tgn:1000001",
          "tgn:7016102",
          "tgn:7012149",
          "tgn:7007516",
          "tgn:7029392"
        ],
        "placetype": [
          "aat:300008699"
        ],
        "id": 2624621,
        "name:xx": "Rock Run"
      }
    },
    {
      "geometry": {
        "type": "Point",
        "coordinates": [
          -76.0833,
          39.6167
        ]
      },
      "type": "Feature",
      "properties": {
        "hierarchy": [
          "tgn:2624622",
          "tgn:1002247",
          "tgn:1000001",
          "tgn:7012149",
          "tgn:7007516",
          "tgn:7029392"
        ],
        "placetype": [
          "aat:300008699"
        ],
        "id": 2624622,
        "name:xx": "Rock Run"
      }
    },
    {
      "geometry": {
        "type": "Point",
        "coordinates": [
          -76.1167,
          39.6
        ]
      },
      "type": "Feature",
      "properties": {
        "hierarchy": [
          "tgn:2624623",
          "tgn:1002247",
          "tgn:1000001",
          "tgn:7012149",
          "tgn:7007516",
          "tgn:7029392"
        ],
        "placetype": [
          "aat:300008347"
        ],
        "id": 2624623,
        "name:xx": "Rock Run"
      }
    },
    {
      "geometry": {
        "type": "Point",
        "coordinates": [
          -77.5167,
          42.2167
        ]
      },
      "type": "Feature",
      "properties": {
        "hierarchy": [
          "tgn:2624624",
          "tgn:1000001",
          "tgn:7012149",
          "tgn:1002920",
          "tgn:7007568",
          "tgn:7029392"
        ],
        "placetype": [
          "aat:300008699"
        ],
        "id": 2624624,
        "name:xx": "Rock Run"
      }
    },
    {
      "geometry": {
        "type": "Point",
        "coordinates": [
          -83.9,
          39.9833
        ]
      },
      "type": "Feature",
      "properties": {
        "hierarchy": [
          "tgn:2624625",
          "tgn:1000001",
          "tgn:1002274",
          "tgn:7012149",
          "tgn:7007706",
          "tgn:7029392"
        ],
        "placetype": [
          "aat:300008699"
        ],
        "id": 2624625,
        "name:xx": "Rock Run"
      }
    },
    {
      "geometry": {
        "type": "Point",
        "coordinates": [
          -83.15,
          38.9333
        ]
      },
      "type": "Feature",
      "properties": {
        "hierarchy": [
          "tgn:2624626",
          "tgn:1000001",
          "tgn:7012149",
          "tgn:7007706",
          "tgn:7029392"
        ],
        "placetype": [
          "aat:300008699"
        ],
        "id": 2624626,
        "name:xx": "Rock Run"
      }
    },
    {
      "geometry": {
        "type": "Point",
        "coordinates": [
          -81.8,
          39.0333
        ]
      },
      "type": "Feature",
      "properties": {
        "hierarchy": [
          "tgn:2624627",
          "tgn:1000001",
          "tgn:7012149",
          "tgn:2001616",
          "tgn:7007706",
          "tgn:7029392"
        ],
        "placetype": [
          "aat:300008699"
        ],
        "id": 2624627,
        "name:xx": "Rock Run"
      }
    },
    {
      "geometry": {
        "type": "Point",
        "coordinates": [
          -83.3,
          38.6333
        ]
      },
      "type": "Feature",
      "properties": {
        "hierarchy": [
          "tgn:2624628",
          "tgn:1002136",
          "tgn:1000001",
          "tgn:7012149",
          "tgn:7007706",
          "tgn:7029392"
        ],
        "placetype": [
          "aat:300008699"
        ],
        "id": 2624628,
        "name:xx": "Rock Run"
      }
    },
    {
      "geometry": {
        "type": "Point",
        "coordinates": [
          -81.8167,
          40.2333
        ]
      },
      "type": "Feature",
      "properties": {
        "hierarchy": [
          "tgn:2624629",
          "tgn:1000001",
          "tgn:1002304",
          "tgn:7012149",
          "tgn:7007706",
          "tgn:7029392"
        ],
        "placetype": [
          "aat:300008699"
        ],
        "id": 2624629,
        "name:xx": "Rock Run"
      }
    }
  ]
}
