{
  "geometry": {
    "type": "Point",
    "coordinates": [
      120.3375,
      22.936111
    ]
  },
  "type": "Feature",
  "properties": {
    "hierarchy": [
      "tgn:7501061",
      "tgn:1000004",
      "tgn:7490934",
      "tgn:1000141",
      "tgn:7029392"
    ],
    "placetype": [
      "aat:300387033"
    ],
    "id": 7501061,
    "name:xx": "Shenkengzi"
  }
}
