{
  "geometry": {
    "type": "Point",
    "coordinates": [
      6.8667,
      45.5333
    ]
  },
  "type": "Feature",
  "properties": {
    "hierarchy": [
      "tgn:1106101",
      "tgn:1000003",
      "tgn:1000070",
      "tgn:7002897",
      "tgn:7029392"
    ],
    "placetype": [
      "aat:300008795"
    ],
    "id": 1106101,
    "name:xx": "Pourri, Mont"
  }
}
