{
  "geometry": {
    "type": "Point",
    "coordinates": [
      -95.0833,
      42.0167
    ]
  },
  "type": "Feature",
  "properties": {
    "hierarchy": [
      "tgn:2304758",
      "tgn:1000001",
      "tgn:7012149",
      "tgn:7007253",
      "tgn:7029392"
    ],
    "placetype": [
      "aat:300008707"
    ],
    "id": 2304758,
    "name:xx": "East Boyer River"
  }
}
