{
  "geometry": {
    "type": "Point",
    "coordinates": [
      116.0833,
      -26.0833
    ]
  },
  "type": "Feature",
  "properties": {
    "hierarchy": [
      "tgn:1096450",
      "tgn:7000490",
      "tgn:1000006",
      "tgn:7001834",
      "tgn:7029392"
    ],
    "placetype": [
      "aat:300008347"
    ],
    "id": 1096450,
    "name:xx": "Byro"
  }
}
