{
  "geometry": {
    "type": "Point",
    "coordinates": [
      26.002778,
      38.5975
    ]
  },
  "type": "Feature",
  "properties": {
    "hierarchy": [
      "tgn:7217287",
      "tgn:7011161",
      "tgn:7002674",
      "tgn:1000003",
      "tgn:1000074",
      "tgn:7029392"
    ],
    "placetype": [
      "aat:300008798"
    ],
    "id": 7217287,
    "name:xx": "Kapsáli"
  }
}
