{
  "geometry": {
    "type": "Point",
    "coordinates": [
      -119.4333,
      37.6167
    ]
  },
  "type": "Feature",
  "properties": {
    "hierarchy": [
      "tgn:2409797",
      "tgn:1000001",
      "tgn:7012149",
      "tgn:7007157",
      "tgn:7029392"
    ],
    "placetype": [
      "aat:300008706"
    ],
    "id": 2409797,
    "name:xx": "Illilouette Creek"
  }
}
