{
  "geometry": {
    "type": "Point",
    "coordinates": [
      -76.5667,
      36.5167
    ]
  },
  "type": "Feature",
  "properties": {
    "hierarchy": [
      "tgn:2741487",
      "tgn:1000001",
      "tgn:7012149",
      "tgn:1002403",
      "tgn:7007709",
      "tgn:7029392"
    ],
    "placetype": [
      "aat:300008791"
    ],
    "id": 2741487,
    "name:xx": "Ure Island"
  }
}
