{
  "geometry": {
    "type": "Point",
    "coordinates": [
      87.961472,
      22.469224
    ]
  },
  "type": "Feature",
  "properties": {
    "hierarchy": [
      "tgn:1074503",
      "tgn:1000004",
      "tgn:7000198",
      "tgn:1001977",
      "tgn:7029392"
    ],
    "placetype": [
      "aat:300008347"
    ],
    "name:en": "Bāgnān",
    "id": 1074503
  }
}
