{
  "geometry": {
    "type": "Point",
    "coordinates": [
      -91.3833,
      31.3167
    ]
  },
  "type": "Feature",
  "properties": {
    "hierarchy": [
      "tgn:2633434",
      "tgn:1000001",
      "tgn:7012149",
      "tgn:2001164",
      "tgn:7007522",
      "tgn:7029392"
    ],
    "placetype": [
      "aat:300008699"
    ],
    "id": 2633434,
    "name:xx": "Running Bayou"
  }
}
