{
  "geometry": {
    "type": "Point",
    "coordinates": [
      -94.75,
      41.6333
    ]
  },
  "type": "Feature",
  "properties": {
    "hierarchy": [
      "tgn:2336877",
      "tgn:2000565",
      "tgn:1000001",
      "tgn:7012149",
      "tgn:7007253",
      "tgn:7029392"
    ],
    "placetype": [
      "aat:300008706"
    ],
    "id": 2336877,
    "name:xx": "Fourmile Creek"
  }
}
