{
  "geometry": {
    "type": "Point",
    "coordinates": [
      -87.1333,
      33.2667
    ]
  },
  "type": "Feature",
  "properties": {
    "hierarchy": [
      "tgn:2515350",
      "tgn:7002659",
      "tgn:1000001",
      "tgn:7012149",
      "tgn:2000062",
      "tgn:7029392"
    ],
    "placetype": [
      "aat:300006191"
    ],
    "id": 2515350,
    "name:xx": "Million Dollar Lake"
  }
}
