{
  "geometry": {
    "type": "Point",
    "coordinates": [
      -108.6667,
      38.9333
    ]
  },
  "type": "Feature",
  "properties": {
    "hierarchy": [
      "tgn:2444453",
      "tgn:1000001",
      "tgn:7012149",
      "tgn:2000230",
      "tgn:7007158",
      "tgn:7029392"
    ],
    "placetype": [
      "aat:300008761"
    ],
    "id": 2444453,
    "name:xx": "Ladder Canyon"
  }
}
