{
  "type": "FeatureCollection",
  "features": [
    {
      "geometry": {
        "type": "Point",
        "coordinates": [
          -91.5167,
          37.2833
        ]
      },
      "type": "Feature",
      "properties": {
        "hierarchy": [
          "tgn:2360660",
          "tgn:1000001",
          "tgn:7012149",
          "tgn:2001247",
          "tgn:7007523",
          "tgn:7029392"
        ],
        "placetype": [
          "aat:300008761"
        ],
        "id": 2360660,
        "name:xx": "Grassy Hollow"
      }
    },
    {
      "geometry": {
        "type": "Point",
        "coordinates": [
          -90.75,
          38.1667
        ]
      },
      "type": "Feature",
      "properties": {
        "hierarchy": [
          "tgn:2360661",
          "tgn:1000001",
          "tgn:7012149",
          "tgn:7007523",
          "tgn:7029392"
        ],
        "placetype": [
          "aat:300008761"
        ],
        "id": 2360661,
        "name:xx": "Grassy Hollow"
      }
    },
    {
      "geometry": {
        "type": "Point",
        "coordinates": [
          -72.2167,
          41.0167
        ]
      },
      "type": "Feature",
      "properties": {
        "hierarchy": [
          "tgn:2360663",
          "tgn:1000001",
          "tgn:7012149",
          "tgn:1002924",
          "tgn:7007568",
          "tgn:7029392"
        ],
        "placetype": [
          "aat:300386845"
        ],
        "id": 2360663,
        "name:xx": "Grassy Hollow"
      }
    },
    {
      "geometry": {
        "type": "Point",
        "coordinates": [
          -95.8333,
          34.3833
        ]
      },
      "type": "Feature",
      "properties": {
        "hierarchy": [
          "tgn:2360664",
          "tgn:2001625",
          "tgn:1000001",
          "tgn:7012149",
          "tgn:7007707",
          "tgn:7029392"
        ],
        "placetype": [
          "aat:300008761"
        ],
        "id": 2360664,
        "name:xx": "Grassy Hollow"
      }
    },
    {
      "geometry": {
        "type": "Point",
        "coordinates": [
          -76.3833,
          41.35
        ]
      },
      "type": "Feature",
      "properties": {
        "hierarchy": [
          "tgn:2360665",
          "tgn:1000001",
          "tgn:7012149",
          "tgn:7007710",
          "tgn:7029392"
        ],
        "placetype": [
          "aat:300008761"
        ],
        "id": 2360665,
        "name:xx": "Grassy Hollow"
      }
    },
    {
      "geometry": {
        "type": "Point",
        "coordinates": [
          -87.9667,
          35.85
        ]
      },
      "type": "Feature",
      "properties": {
        "hierarchy": [
          "tgn:2360666",
          "tgn:1000001",
          "tgn:2001839",
          "tgn:7012149",
          "tgn:7007825",
          "tgn:7029392"
        ],
        "placetype": [
          "aat:300008761"
        ],
        "id": 2360666,
        "name:xx": "Grassy Hollow"
      }
    },
    {
      "geometry": {
        "type": "Point",
        "coordinates": [
          -87.3667,
          35.9
        ]
      },
      "type": "Feature",
      "properties": {
        "hierarchy": [
          "tgn:2360667",
          "tgn:1000001",
          "tgn:7012149",
          "tgn:7015666",
          "tgn:7007825",
          "tgn:7029392"
        ],
        "placetype": [
          "aat:300008761"
        ],
        "id": 2360667,
        "name:xx": "Grassy Hollow"
      }
    },
    {
      "geometry": {
        "type": "Point",
        "coordinates": [
          -83.5333,
          36.5
        ]
      },
      "type": "Feature",
      "properties": {
        "hierarchy": [
          "tgn:2360668",
          "tgn:1000001",
          "tgn:7012149",
          "tgn:2001849",
          "tgn:7007825",
          "tgn:7029392"
        ],
        "placetype": [
          "aat:300008761"
        ],
        "id": 2360668,
        "name:xx": "Grassy Hollow"
      }
    },
    {
      "geometry": {
        "type": "Point",
        "coordinates": [
          -96.45,
          31.4
        ]
      },
      "type": "Feature",
      "properties": {
        "hierarchy": [
          "tgn:2360669",
          "tgn:1000001",
          "tgn:7012149",
          "tgn:1002597",
          "tgn:7007826",
          "tgn:7029392"
        ],
        "placetype": [
          "aat:300008761"
        ],
        "id": 2360669,
        "name:xx": "Grassy Hollow"
      }
    }
  ]
}
