{
  "geometry": {
    "type": "Point",
    "coordinates": [
      103.7667,
      1.4333
    ]
  },
  "type": "Feature",
  "properties": {
    "hierarchy": [
      "tgn:7001490",
      "tgn:1000004",
      "tgn:1000138",
      "tgn:7000381",
      "tgn:7029392"
    ],
    "placetype": [
      "aat:300008347"
    ],
    "id": 7001490,
    "name:xx": "Kampong Mandai Kechil"
  }
}
