{
  "geometry": {
    "type": "Point",
    "coordinates": [
      -90.6333,
      41.9833
    ]
  },
  "type": "Feature",
  "properties": {
    "hierarchy": [
      "tgn:2738721",
      "tgn:1000001",
      "tgn:7012149",
      "tgn:7007253",
      "tgn:7029392"
    ],
    "placetype": [
      "aat:300008706"
    ],
    "id": 2738721,
    "name:xx": "Union Creek"
  }
}
