{
  "geometry": {
    "type": "Point",
    "coordinates": [
      125.1667,
      42.8833
    ]
  },
  "type": "Feature",
  "properties": {
    "hierarchy": [
      "tgn:1069797",
      "tgn:1000004",
      "tgn:7002372",
      "tgn:1000111",
      "tgn:7029392"
    ],
    "placetype": [
      "aat:300008347"
    ],
    "id": 1069797,
    "name:xx": "Liaoyuan"
  }
}
