{
  "type": "FeatureCollection",
  "features": [
    {
      "geometry": {
        "type": "Point",
        "coordinates": [
          -75.5,
          37.8333
        ]
      },
      "type": "Feature",
      "properties": {
        "hierarchy": [
          "tgn:2563950",
          "tgn:1002132",
          "tgn:1000001",
          "tgn:7012149",
          "tgn:7007919",
          "tgn:7029392"
        ],
        "placetype": [
          "aat:300132316"
        ],
        "id": 2563950,
        "name:xx": "Oyster Bay"
      }
    },
    {
      "geometry": {
        "type": "Point",
        "coordinates": [
          -123.0667,
          47.1
        ]
      },
      "type": "Feature",
      "properties": {
        "hierarchy": [
          "tgn:2563951",
          "tgn:1000001",
          "tgn:7012149",
          "tgn:7007920",
          "tgn:7029392"
        ],
        "placetype": [
          "aat:300132316"
        ],
        "id": 2563951,
        "name:xx": "Oyster Bay"
      }
    },
    {
      "geometry": {
        "type": "Point",
        "coordinates": [
          -122.6667,
          47.5667
        ]
      },
      "type": "Feature",
      "properties": {
        "hierarchy": [
          "tgn:2563952",
          "tgn:1000001",
          "tgn:7012149",
          "tgn:1002552",
          "tgn:7007920",
          "tgn:7029392"
        ],
        "placetype": [
          "aat:300132316"
        ],
        "id": 2563952,
        "name:xx": "Oyster Bay"
      }
    },
    {
      "geometry": {
        "type": "Point",
        "coordinates": [
          -90.5,
          29.3
        ]
      },
      "type": "Feature",
      "properties": {
        "hierarchy": [
          "tgn:2563953",
          "tgn:1000001",
          "tgn:7012149",
          "tgn:2000908",
          "tgn:7007256",
          "tgn:7029392"
        ],
        "placetype": [
          "aat:300008699"
        ],
        "id": 2563953,
        "name:xx": "Oyster Bayou"
      }
    },
    {
      "geometry": {
        "type": "Point",
        "coordinates": [
          -91.5167,
          29.5833
        ]
      },
      "type": "Feature",
      "properties": {
        "hierarchy": [
          "tgn:2563954",
          "tgn:1000001",
          "tgn:7012149",
          "tgn:2000904",
          "tgn:7007256",
          "tgn:7029392"
        ],
        "placetype": [
          "aat:300008699"
        ],
        "id": 2563954,
        "name:xx": "Oyster Bayou"
      }
    },
    {
      "geometry": {
        "type": "Point",
        "coordinates": [
          -93.3667,
          29.8167
        ]
      },
      "type": "Feature",
      "properties": {
        "hierarchy": [
          "tgn:2563955",
          "tgn:1000001",
          "tgn:7020676",
          "tgn:7012149",
          "tgn:7007256",
          "tgn:7029392"
        ],
        "placetype": [
          "aat:300008699"
        ],
        "id": 2563955,
        "name:xx": "Oyster Bayou"
      }
    },
    {
      "geometry": {
        "type": "Point",
        "coordinates": [
          -94.5,
          29.8167
        ]
      },
      "type": "Feature",
      "properties": {
        "hierarchy": [
          "tgn:2563956",
          "tgn:1000001",
          "tgn:7012149",
          "tgn:1002251",
          "tgn:7007826",
          "tgn:7029392"
        ],
        "placetype": [
          "aat:300008699"
        ],
        "id": 2563956,
        "name:xx": "Oyster Bayou"
      }
    },
    {
      "geometry": {
        "type": "Point",
        "coordinates": [
          -91.5167,
          40.0333
        ]
      },
      "type": "Feature",
      "properties": {
        "hierarchy": [
          "tgn:2563957",
          "tgn:1000001",
          "tgn:7012149",
          "tgn:1002592",
          "tgn:7007523",
          "tgn:7029392"
        ],
        "placetype": [
          "aat:300008699"
        ],
        "id": 2563957,
        "name:xx": "Oyster Branch"
      }
    },
    {
      "geometry": {
        "type": "Point",
        "coordinates": [
          -84.3667,
          30
        ]
      },
      "type": "Feature",
      "properties": {
        "hierarchy": [
          "tgn:2563958",
          "tgn:1000001",
          "tgn:7012149",
          "tgn:2000289",
          "tgn:7007240",
          "tgn:7029392"
        ],
        "placetype": [
          "aat:300132316"
        ],
        "id": 2563958,
        "name:xx": "Oyster Cove"
      }
    },
    {
      "geometry": {
        "type": "Point",
        "coordinates": [
          -76.3167,
          38.4833
        ]
      },
      "type": "Feature",
      "properties": {
        "hierarchy": [
          "tgn:2563959",
          "tgn:1002338",
          "tgn:1000001",
          "tgn:7012149",
          "tgn:7007516",
          "tgn:7029392"
        ],
        "placetype": [
          "aat:300132316"
        ],
        "id": 2563959,
        "name:xx": "Oyster Cove"
      }
    }
  ]
}
