{
  "geometry": {
    "type": "Point",
    "coordinates": [
      -89.6167,
      40.0667
    ]
  },
  "type": "Feature",
  "properties": {
    "hierarchy": [
      "tgn:2425505",
      "tgn:1000001",
      "tgn:7012149",
      "tgn:1002655",
      "tgn:7007251",
      "tgn:7029392"
    ],
    "placetype": [
      "aat:300000390"
    ],
    "id": 2425505,
    "name:xx": "Johnson Valley Mine"
  }
}
