{
  "geometry": {
    "type": "Point",
    "coordinates": [
      -169.5167,
      62.9667
    ]
  },
  "type": "Feature",
  "properties": {
    "hierarchy": [
      "tgn:2436324",
      "tgn:7006450",
      "tgn:1000001",
      "tgn:7012149",
      "tgn:2000079",
      "tgn:7029392"
    ],
    "placetype": [
      "aat:300008850"
    ],
    "id": 2436324,
    "name:xx": "Kialegak Point"
  }
}
