{
  "type": "FeatureCollection",
  "features": [
    {
      "geometry": {
        "type": "Point",
        "coordinates": [
          31.116667,
          29.166667
        ]
      },
      "type": "Feature",
      "properties": {
        "hierarchy": [
          "tgn:7524860",
          "tgn:7001242",
          "tgn:7001105",
          "tgn:7016833",
          "tgn:7029392"
        ],
        "placetype": [
          "aat:300008347"
        ],
        "name:en": "'Ezbet Anṭônyûs",
        "id": 7524860
      }
    },
    {
      "geometry": {
        "type": "Point",
        "coordinates": [
          30.608056,
          31.281111
        ]
      },
      "type": "Feature",
      "properties": {
        "hierarchy": [
          "tgn:7524861",
          "tgn:7001242",
          "tgn:7016833",
          "tgn:1001335",
          "tgn:7029392"
        ],
        "placetype": [
          "aat:300008347"
        ],
        "name:en": "'Ezbet 'Amr & el-Quni",
        "id": 7524861
      }
    },
    {
      "geometry": {
        "type": "Point",
        "coordinates": [
          30.559196,
          31.303632
        ]
      },
      "type": "Feature",
      "properties": {
        "hierarchy": [
          "tgn:7524862",
          "tgn:7001242",
          "tgn:7016833",
          "tgn:1001335",
          "tgn:7029392"
        ],
        "placetype": [
          "aat:300008347"
        ],
        "name:en": "'Izbat 'Umar",
        "id": 7524862
      }
    },
    {
      "geometry": {
        "type": "Point",
        "coordinates": [
          30.139167,
          30.933056
        ]
      },
      "type": "Feature",
      "properties": {
        "hierarchy": [
          "tgn:7524863",
          "tgn:7001242",
          "tgn:1001075",
          "tgn:7016833",
          "tgn:7029392"
        ],
        "placetype": [
          "aat:300008347"
        ],
        "name:en": "'Ezbet Amîn Mûsa",
        "id": 7524863
      }
    },
    {
      "geometry": {
        "type": "Point",
        "coordinates": [
          30.9,
          28.733333
        ]
      },
      "type": "Feature",
      "properties": {
        "hierarchy": [
          "tgn:7524864",
          "tgn:7001242",
          "tgn:7016833",
          "tgn:1001142",
          "tgn:7029392"
        ],
        "placetype": [
          "aat:300008347"
        ],
        "name:en": "'Ezbet Amin",
        "id": 7524864
      }
    },
    {
      "geometry": {
        "type": "Point",
        "coordinates": [
          31.595,
          30.971389
        ]
      },
      "type": "Feature",
      "properties": {
        "hierarchy": [
          "tgn:7524865",
          "tgn:7001242",
          "tgn:1001059",
          "tgn:7016833",
          "tgn:7029392"
        ],
        "placetype": [
          "aat:300008347"
        ],
        "name:en": "'Ezbet 'Allâq Bakr",
        "id": 7524865
      }
    },
    {
      "geometry": {
        "type": "Point",
        "coordinates": [
          31.445324,
          31.353427
        ]
      },
      "type": "Feature",
      "properties": {
        "hierarchy": [
          "tgn:7524866",
          "tgn:7001242",
          "tgn:1001059",
          "tgn:7016833",
          "tgn:7029392"
        ],
        "placetype": [
          "aat:300008347"
        ],
        "id": 7524866,
        "name:xx": "'Izbat 'Allām"
      }
    },
    {
      "geometry": {
        "type": "Point",
        "coordinates": [
          31.683333,
          31.216667
        ]
      },
      "type": "Feature",
      "properties": {
        "hierarchy": [
          "tgn:7524867",
          "tgn:7001242",
          "tgn:1001059",
          "tgn:7016833",
          "tgn:7029392"
        ],
        "placetype": [
          "aat:300008347"
        ],
        "name:en": "'Ezbet 'Aliy el-Dîn",
        "id": 7524867
      }
    },
    {
      "geometry": {
        "type": "Point",
        "coordinates": [
          30.816667,
          28.033333
        ]
      },
      "type": "Feature",
      "properties": {
        "hierarchy": [
          "tgn:7524868",
          "tgn:7001242",
          "tgn:7016833",
          "tgn:1001088",
          "tgn:7029392"
        ],
        "placetype": [
          "aat:300008347"
        ],
        "name:en": "'Ezbet 'Alî Sha'râwî",
        "id": 7524868
      }
    },
    {
      "geometry": {
        "type": "Point",
        "coordinates": [
          31.167453,
          31.330879
        ]
      },
      "type": "Feature",
      "properties": {
        "hierarchy": [
          "tgn:7524869",
          "tgn:7001242",
          "tgn:7016833",
          "tgn:1001335",
          "tgn:7029392"
        ],
        "placetype": [
          "aat:300008347"
        ],
        "id": 7524869,
        "name:xx": "Abū Shāhīn"
      }
    }
  ]
}
