{
  "geometry": {
    "type": "Point",
    "coordinates": [
      -95.1333,
      31.65
    ]
  },
  "type": "Feature",
  "properties": {
    "hierarchy": [
      "tgn:2514159",
      "tgn:1000001",
      "tgn:7012149",
      "tgn:1002263",
      "tgn:7007826",
      "tgn:7029392"
    ],
    "placetype": [
      "aat:300008699"
    ],
    "id": 2514159,
    "name:xx": "Miller Branch"
  }
}
