{
  "geometry": {
    "type": "Point",
    "coordinates": [
      -112.2667,
      35.2167
    ]
  },
  "type": "Feature",
  "properties": {
    "hierarchy": [
      "tgn:7021904",
      "tgn:1000001",
      "tgn:7006451",
      "tgn:2000092",
      "tgn:7012149",
      "tgn:7029392"
    ],
    "placetype": [
      "aat:300006191"
    ],
    "id": 7021904,
    "name:xx": "Reed Tank"
  }
}
