{
  "geometry": {
    "type": "Point",
    "coordinates": [
      -142.5167,
      63.0167
    ]
  },
  "type": "Feature",
  "properties": {
    "hierarchy": [
      "tgn:2239221",
      "tgn:7006450",
      "tgn:1000001",
      "tgn:7012149",
      "tgn:2000085",
      "tgn:7029392"
    ],
    "placetype": [
      "aat:300008680"
    ],
    "id": 2239221,
    "name:xx": "Chuimund Lake"
  }
}
