{
  "geometry": {
    "type": "Point",
    "coordinates": [
      -92.0167,
      31.9833
    ]
  },
  "type": "Feature",
  "properties": {
    "hierarchy": [
      "tgn:2174987",
      "tgn:1000001",
      "tgn:2000864",
      "tgn:7012149",
      "tgn:7007256",
      "tgn:7029392"
    ],
    "placetype": [
      "aat:300008699"
    ],
    "id": 2174987,
    "name:xx": "Black Bayou"
  }
}
