{
  "geometry": {
    "type": "Point",
    "coordinates": [
      -95.4833,
      31.8667
    ]
  },
  "type": "Feature",
  "properties": {
    "hierarchy": [
      "tgn:2766600",
      "tgn:1002148",
      "tgn:1000001",
      "tgn:7012149",
      "tgn:7007826",
      "tgn:7029392"
    ],
    "placetype": [
      "aat:300008706"
    ],
    "id": 2766600,
    "name:xx": "White Oak Creek"
  }
}
