{
  "geometry": {
    "type": "Point",
    "coordinates": [
      -76.8833,
      42.75
    ]
  },
  "type": "Feature",
  "properties": {
    "hierarchy": [
      "tgn:2769988",
      "tgn:1000001",
      "tgn:7012149",
      "tgn:1002882",
      "tgn:7007568",
      "tgn:7029392"
    ],
    "placetype": [
      "aat:300008706"
    ],
    "id": 2769988,
    "name:xx": "Wilcox Creek"
  }
}
