{
  "geometry": {
    "type": "Point",
    "coordinates": [
      139.0167,
      37.7667
    ]
  },
  "type": "Feature",
  "properties": {
    "hierarchy": [
      "tgn:1081363",
      "tgn:7000895",
      "tgn:1000004",
      "tgn:1001014",
      "tgn:1000120",
      "tgn:7029392"
    ],
    "placetype": [
      "aat:300008347"
    ],
    "id": 1081363,
    "name:xx": "Shirone"
  }
}
