{
  "geometry": {
    "type": "Point",
    "coordinates": [
      -78.5833,
      39.4667
    ]
  },
  "type": "Feature",
  "properties": {
    "hierarchy": [
      "tgn:2174020",
      "tgn:1000001",
      "tgn:7012149",
      "tgn:2002265",
      "tgn:7013961",
      "tgn:7029392"
    ],
    "placetype": [
      "aat:300266640"
    ],
    "id": 2174020,
    "name:xx": "Bird Ridge"
  }
}
