{
  "geometry": {
    "type": "Point",
    "coordinates": [
      -111.45,
      38.9833
    ]
  },
  "type": "Feature",
  "properties": {
    "hierarchy": [
      "tgn:2133378",
      "tgn:1000001",
      "tgn:7012149",
      "tgn:2002121",
      "tgn:7007827",
      "tgn:7029392"
    ],
    "placetype": [
      "aat:300008697"
    ],
    "id": 2133378,
    "name:xx": "Anderson Spring"
  }
}
