{
  "geometry": {
    "type": "Point",
    "coordinates": [
      83.11623,
      22.128319
    ]
  },
  "type": "Feature",
  "properties": {
    "hierarchy": [
      "tgn:7551475",
      "tgn:1000004",
      "tgn:7031781",
      "tgn:7000198",
      "tgn:7029392"
    ],
    "placetype": [
      "aat:300008347"
    ],
    "name:en": "Chhāl",
    "id": 7551475
  }
}
