{
  "geometry": {
    "type": "Point",
    "coordinates": [
      -94.2667,
      40.1667
    ]
  },
  "type": "Feature",
  "properties": {
    "hierarchy": [
      "tgn:2060917",
      "tgn:1000001",
      "tgn:7012149",
      "tgn:2001198",
      "tgn:7007523",
      "tgn:7029392"
    ],
    "placetype": [
      "aat:300387016"
    ],
    "id": 2060917,
    "name:xx": "Whitten"
  }
}
