{
  "geometry": {
    "type": "Point",
    "coordinates": [
      -99.4833,
      27.5667
    ]
  },
  "type": "Feature",
  "properties": {
    "hierarchy": [
      "tgn:2282994",
      "tgn:1000001",
      "tgn:7012149",
      "tgn:2002090",
      "tgn:7007826",
      "tgn:7029392"
    ],
    "placetype": [
      "aat:300008347"
    ],
    "id": 2282994,
    "name:xx": "Del Mar"
  }
}
