{
  "geometry": {
    "type": "Point",
    "coordinates": [
      -79.7167,
      38.9333
    ]
  },
  "type": "Feature",
  "properties": {
    "hierarchy": [
      "tgn:1103937",
      "tgn:1000001",
      "tgn:7012149",
      "tgn:2002291",
      "tgn:7013961",
      "tgn:7029392"
    ],
    "placetype": [
      "aat:300008795"
    ],
    "id": 1103937,
    "name:xx": "Bickle Knob"
  }
}
