{
  "type": "FeatureCollection",
  "features": [
    {
      "geometry": {
        "type": "Point",
        "coordinates": [
          -101.766667,
          22.683333
        ]
      },
      "type": "Feature",
      "properties": {
        "hierarchy": [
          "tgn:7390100",
          "tgn:1000001",
          "tgn:7005594",
          "tgn:7005560",
          "tgn:7029392"
        ],
        "placetype": [
          "aat:300008347"
        ],
        "id": 7390100,
        "name:xx": "Salitrillo"
      }
    },
    {
      "geometry": {
        "type": "Point",
        "coordinates": [
          -100.716667,
          22.65
        ]
      },
      "type": "Feature",
      "properties": {
        "hierarchy": [
          "tgn:7390101",
          "tgn:1000001",
          "tgn:7005594",
          "tgn:7005560",
          "tgn:7029392"
        ],
        "placetype": [
          "aat:300008347"
        ],
        "id": 7390101,
        "name:xx": "Salitrillo"
      }
    },
    {
      "geometry": {
        "type": "Point",
        "coordinates": [
          -100.966667,
          21.883333
        ]
      },
      "type": "Feature",
      "properties": {
        "hierarchy": [
          "tgn:7390102",
          "tgn:1000001",
          "tgn:7005594",
          "tgn:7005560",
          "tgn:7029392"
        ],
        "placetype": [
          "aat:300008347"
        ],
        "id": 7390102,
        "name:xx": "Salitrillo"
      }
    },
    {
      "geometry": {
        "type": "Point",
        "coordinates": [
          -98.616667,
          21.583333
        ]
      },
      "type": "Feature",
      "properties": {
        "hierarchy": [
          "tgn:7390103",
          "tgn:1000001",
          "tgn:7005594",
          "tgn:7005560",
          "tgn:7029392"
        ],
        "placetype": [
          "aat:300008347"
        ],
        "id": 7390103,
        "name:xx": "Rincón"
      }
    },
    {
      "geometry": {
        "type": "Point",
        "coordinates": [
          -99.116667,
          20
        ]
      },
      "type": "Feature",
      "properties": {
        "hierarchy": [
          "tgn:7390104",
          "tgn:1000001",
          "tgn:1001893",
          "tgn:7005560",
          "tgn:7029392"
        ],
        "placetype": [
          "aat:300008347"
        ],
        "id": 7390104,
        "name:xx": "Rincón"
      }
    },
    {
      "geometry": {
        "type": "Point",
        "coordinates": [
          -100.066667,
          17.95
        ]
      },
      "type": "Feature",
      "properties": {
        "hierarchy": [
          "tgn:7390105",
          "tgn:7005585",
          "tgn:1000001",
          "tgn:7005560",
          "tgn:7029392"
        ],
        "placetype": [
          "aat:300008347"
        ],
        "id": 7390105,
        "name:xx": "Rincón"
      }
    },
    {
      "geometry": {
        "type": "Point",
        "coordinates": [
          -91.533333,
          17.866667
        ]
      },
      "type": "Feature",
      "properties": {
        "hierarchy": [
          "tgn:7390106",
          "tgn:1000001",
          "tgn:7005596",
          "tgn:7005560",
          "tgn:7029392"
        ],
        "placetype": [
          "aat:300008347"
        ],
        "id": 7390106,
        "name:xx": "Rincón"
      }
    },
    {
      "geometry": {
        "type": "Point",
        "coordinates": [
          -93.65,
          17.8
        ]
      },
      "type": "Feature",
      "properties": {
        "hierarchy": [
          "tgn:7390107",
          "tgn:1000001",
          "tgn:7005596",
          "tgn:7005560",
          "tgn:7029392"
        ],
        "placetype": [
          "aat:300008347"
        ],
        "id": 7390107,
        "name:xx": "Rincón"
      }
    },
    {
      "geometry": {
        "type": "Point",
        "coordinates": [
          -97.973611,
          16.639167
        ]
      },
      "type": "Feature",
      "properties": {
        "hierarchy": [
          "tgn:7390108",
          "tgn:1000001",
          "tgn:7005591",
          "tgn:7005560",
          "tgn:7029392"
        ],
        "placetype": [
          "aat:300008347"
        ],
        "id": 7390108,
        "name:es": "Santa María del Rincón"
      }
    }
  ]
}
