{
  "geometry": {
    "type": "Point",
    "coordinates": [
      46.8333,
      -19.8333
    ]
  },
  "type": "Feature",
  "properties": {
    "hierarchy": [
      "tgn:1090869",
      "tgn:1001103",
      "tgn:7001242",
      "tgn:1000173",
      "tgn:7029392"
    ],
    "placetype": [
      "aat:300008347"
    ],
    "id": 1090869,
    "name:xx": "Betafo"
  }
}
