{
  "geometry": {
    "type": "Point",
    "coordinates": [
      131.85,
      33.2667
    ]
  },
  "type": "Feature",
  "properties": {
    "hierarchy": [
      "tgn:1081170",
      "tgn:1000961",
      "tgn:1000004",
      "tgn:7000901",
      "tgn:1000120",
      "tgn:7029392"
    ],
    "placetype": [
      "aat:300008347"
    ],
    "id": 1081170,
    "name:xx": "Saganoseki"
  }
}
