{
  "type": "FeatureCollection",
  "features": [
    {
      "geometry": {
        "type": "Point",
        "coordinates": [
          6.15,
          52.15
        ]
      },
      "type": "Feature",
      "properties": {
        "hierarchy": [
          "tgn:7260090",
          "tgn:7003619",
          "tgn:1000003",
          "tgn:7016845",
          "tgn:7029392"
        ],
        "placetype": [
          "aat:300008347"
        ],
        "name:nl": "Empe",
        "id": 7260090
      }
    },
    {
      "geometry": {
        "type": "Point",
        "coordinates": [
          5.533333,
          52.05
        ]
      },
      "type": "Feature",
      "properties": {
        "hierarchy": [
          "tgn:7260091",
          "tgn:1000003",
          "tgn:7003627",
          "tgn:7016845",
          "tgn:7029392"
        ],
        "placetype": [
          "aat:300008777"
        ],
        "name:nl": "Emminkhuizerberg",
        "id": 7260091
      }
    },
    {
      "geometry": {
        "type": "Point",
        "coordinates": [
          5.533333,
          52.05
        ]
      },
      "type": "Feature",
      "properties": {
        "hierarchy": [
          "tgn:7260092",
          "tgn:1000003",
          "tgn:7003627",
          "tgn:7016845",
          "tgn:7029392"
        ],
        "placetype": [
          "aat:300008347"
        ],
        "name:nl": "Emminkhuizen",
        "id": 7260092
      }
    },
    {
      "geometry": {
        "type": "Point",
        "coordinates": [
          4.983333,
          51.783333
        ]
      },
      "type": "Feature",
      "properties": {
        "hierarchy": [
          "tgn:7260093",
          "tgn:1000003",
          "tgn:7003624",
          "tgn:7016845",
          "tgn:7029392"
        ],
        "placetype": [
          "aat:300008347"
        ],
        "name:nl": "Emmikhoven",
        "id": 7260093
      }
    },
    {
      "geometry": {
        "type": "Point",
        "coordinates": [
          4.933333,
          51.766667
        ]
      },
      "type": "Feature",
      "properties": {
        "hierarchy": [
          "tgn:7260094",
          "tgn:1000003",
          "tgn:7003624",
          "tgn:7016845",
          "tgn:7029392"
        ],
        "placetype": [
          "aat:300007836"
        ],
        "name:nl": "Emmickhovense Brug",
        "id": 7260094
      }
    },
    {
      "geometry": {
        "type": "Point",
        "coordinates": [
          6.866667,
          52.8
        ]
      },
      "type": "Feature",
      "properties": {
        "hierarchy": [
          "tgn:7260095",
          "tgn:7003614",
          "tgn:1000003",
          "tgn:7016845",
          "tgn:7029392"
        ],
        "placetype": [
          "aat:300387200"
        ],
        "name:nl": "Emmerveld",
        "id": 7260095
      }
    },
    {
      "geometry": {
        "type": "Point",
        "coordinates": [
          6.15,
          52.5
        ]
      },
      "type": "Feature",
      "properties": {
        "hierarchy": [
          "tgn:7260096",
          "tgn:1000003",
          "tgn:7003626",
          "tgn:7016845",
          "tgn:7029392"
        ],
        "placetype": [
          "aat:300006075"
        ],
        "name:nl": "Emmertochtsloot",
        "id": 7260096
      }
    },
    {
      "geometry": {
        "type": "Point",
        "coordinates": [
          6.95,
          52.8
        ]
      },
      "type": "Feature",
      "properties": {
        "hierarchy": [
          "tgn:7260097",
          "tgn:7003614",
          "tgn:1000003",
          "tgn:7016845",
          "tgn:7029392"
        ],
        "placetype": [
          "aat:300008178"
        ],
        "name:nl": "Emmerschans",
        "id": 7260097
      }
    },
    {
      "geometry": {
        "type": "Point",
        "coordinates": [
          6.933333,
          52.8
        ]
      },
      "type": "Feature",
      "properties": {
        "hierarchy": [
          "tgn:7260098",
          "tgn:7003614",
          "tgn:1000003",
          "tgn:7016845",
          "tgn:7029392"
        ],
        "placetype": [
          "aat:300008347"
        ],
        "name:nl": "Emmerschans",
        "id": 7260098
      }
    },
    {
      "geometry": {
        "type": "Point",
        "coordinates": [
          6.9,
          52.8
        ]
      },
      "type": "Feature",
      "properties": {
        "hierarchy": [
          "tgn:7260099",
          "tgn:7003614",
          "tgn:1000003",
          "tgn:7016845",
          "tgn:7029392"
        ],
        "placetype": [
          "aat:300000745"
        ],
        "name:nl": "Emmermeer",
        "id": 7260099
      }
    }
  ]
}
