{
  "type": "FeatureCollection",
  "features": [
    {
      "geometry": {
        "type": "Point",
        "coordinates": [
          9.55,
          47.1333
        ]
      },
      "type": "Feature",
      "properties": {
        "hierarchy": [
          "tgn:7003361",
          "tgn:7032087",
          "tgn:1000003",
          "tgn:7003515",
          "tgn:7029392"
        ],
        "placetype": [
          "aat:300008347"
        ],
        "id": 7003361,
        "name:xx": "Triesenberg"
      }
    },
    {
      "geometry": {
        "type": "Point",
        "coordinates": [
          9.5167,
          47.1667
        ]
      },
      "type": "Feature",
      "properties": {
        "hierarchy": [
          "tgn:7003362",
          "tgn:1000003",
          "tgn:7003515",
          "tgn:7029392"
        ],
        "placetype": [
          "aat:300387179",
          "aat:300387064",
          "aat:300387186",
          "aat:300387081"
        ],
        "id": 7003362,
        "name:xx": "Oberland"
      }
    },
    {
      "geometry": {
        "type": "Point",
        "coordinates": [
          9.5,
          47.25
        ]
      },
      "type": "Feature",
      "properties": {
        "hierarchy": [
          "tgn:7003365",
          "tgn:1000003",
          "tgn:7003515",
          "tgn:7029392"
        ],
        "placetype": [
          "aat:300387179",
          "aat:300387064",
          "aat:300387186",
          "aat:300387081"
        ],
        "id": 7003365,
        "name:xx": "Unterland"
      }
    },
    {
      "geometry": {
        "type": "Point",
        "coordinates": [
          9.55,
          47.1833
        ]
      },
      "type": "Feature",
      "properties": {
        "hierarchy": [
          "tgn:7003366",
          "tgn:7032082",
          "tgn:1000003",
          "tgn:7003515",
          "tgn:7029392"
        ],
        "placetype": [
          "aat:300008347"
        ],
        "id": 7003366,
        "name:xx": "Planken"
      }
    },
    {
      "geometry": {
        "type": "Point",
        "coordinates": [
          9.5333,
          47.1333
        ]
      },
      "type": "Feature",
      "properties": {
        "hierarchy": [
          "tgn:7003367",
          "tgn:7032088",
          "tgn:1000003",
          "tgn:7003515",
          "tgn:7029392"
        ],
        "placetype": [
          "aat:300008347",
          "aat:300387219",
          "aat:300008375"
        ],
        "id": 7003367,
        "name:xx": "Vaduz"
      }
    }
  ]
}
