{
  "geometry": {
    "type": "Point",
    "coordinates": [
      -108.15,
      43.2333
    ]
  },
  "type": "Feature",
  "properties": {
    "hierarchy": [
      "tgn:2571604",
      "tgn:1000001",
      "tgn:7012149",
      "tgn:2002371",
      "tgn:7007923",
      "tgn:7029392"
    ],
    "placetype": [
      "aat:300006075"
    ],
    "id": 2571604,
    "name:xx": "Pavillion Main Lateral"
  }
}
