{
  "geometry": {
    "type": "Point",
    "coordinates": [
      -85.9333,
      34.9167
    ]
  },
  "type": "Feature",
  "properties": {
    "hierarchy": [
      "tgn:2673818",
      "tgn:7002659",
      "tgn:1000001",
      "tgn:7012149",
      "tgn:2000035",
      "tgn:7029392"
    ],
    "placetype": [
      "aat:300008746"
    ],
    "id": 2673818,
    "name:xx": "Snow Flower Pit"
  }
}
