{
  "geometry": {
    "type": "Point",
    "coordinates": [
      -81.5667,
      38.7833
    ]
  },
  "type": "Feature",
  "properties": {
    "hierarchy": [
      "tgn:2377235",
      "tgn:1000001",
      "tgn:7012149",
      "tgn:2002268",
      "tgn:7013961",
      "tgn:7029392"
    ],
    "placetype": [
      "aat:300266640"
    ],
    "id": 2377235,
    "name:xx": "Harmon Ridge"
  }
}
