{
  "geometry": {
    "type": "Point",
    "coordinates": [
      -94.5667,
      40.9167
    ]
  },
  "type": "Feature",
  "properties": {
    "hierarchy": [
      "tgn:2646533",
      "tgn:1000001",
      "tgn:7012149",
      "tgn:7007253",
      "tgn:7029392"
    ],
    "placetype": [
      "aat:300008706"
    ],
    "id": 2646533,
    "name:xx": "Saylings Creek"
  }
}
