{
  "type": "FeatureCollection",
  "features": [
    {
      "geometry": {
        "type": "Point",
        "coordinates": [
          -107.8,
          36.8167
        ]
      },
      "type": "Feature",
      "properties": {
        "hierarchy": [
          "tgn:2640940",
          "tgn:1000001",
          "tgn:7012149",
          "tgn:2001452",
          "tgn:7007566",
          "tgn:7029392"
        ],
        "placetype": [
          "aat:300008697"
        ],
        "id": 2640940,
        "name:xx": "Sanchez Spring"
      }
    },
    {
      "geometry": {
        "type": "Point",
        "coordinates": [
          -99.95,
          29.9167
        ]
      },
      "type": "Feature",
      "properties": {
        "hierarchy": [
          "tgn:2640941",
          "tgn:1000001",
          "tgn:7012149",
          "tgn:2002060",
          "tgn:7007826",
          "tgn:7029392"
        ],
        "placetype": [
          "aat:300008697"
        ],
        "id": 2640941,
        "name:xx": "Sanchez Spring"
      }
    },
    {
      "geometry": {
        "type": "Point",
        "coordinates": [
          -103.0333,
          35.4167
        ]
      },
      "type": "Feature",
      "properties": {
        "hierarchy": [
          "tgn:2640942",
          "tgn:1000001",
          "tgn:7012149",
          "tgn:2002051",
          "tgn:7007826",
          "tgn:7029392"
        ],
        "placetype": [
          "aat:300008697"
        ],
        "id": 2640942,
        "name:xx": "Sanchez Spring"
      }
    },
    {
      "geometry": {
        "type": "Point",
        "coordinates": [
          -107.2333,
          43.3167
        ]
      },
      "type": "Feature",
      "properties": {
        "hierarchy": [
          "tgn:2640943",
          "tgn:1000001",
          "tgn:7012149",
          "tgn:2002377",
          "tgn:7007923",
          "tgn:7029392"
        ],
        "placetype": [
          "aat:300008697"
        ],
        "id": 2640943,
        "name:xx": "Sanchez Spring"
      }
    },
    {
      "geometry": {
        "type": "Point",
        "coordinates": [
          -105.5167,
          37.1667
        ]
      },
      "type": "Feature",
      "properties": {
        "hierarchy": [
          "tgn:2640945",
          "tgn:1000001",
          "tgn:7012149",
          "tgn:2000203",
          "tgn:7007158",
          "tgn:7029392"
        ],
        "placetype": [
          "aat:300006191"
        ],
        "id": 2640945,
        "name:xx": "Sanchez Stabilizing Reservoir"
      }
    },
    {
      "geometry": {
        "type": "Point",
        "coordinates": [
          -107.5833,
          34.65
        ]
      },
      "type": "Feature",
      "properties": {
        "hierarchy": [
          "tgn:2640946",
          "tgn:1000001",
          "tgn:2001431",
          "tgn:7012149",
          "tgn:7007566",
          "tgn:7029392"
        ],
        "placetype": [
          "aat:300006191"
        ],
        "id": 2640946,
        "name:xx": "Sanchez Tank"
      }
    },
    {
      "geometry": {
        "type": "Point",
        "coordinates": [
          -108.3833,
          35.3167
        ]
      },
      "type": "Feature",
      "properties": {
        "hierarchy": [
          "tgn:2640947",
          "tgn:1000001",
          "tgn:7012149",
          "tgn:7019676",
          "tgn:7007566",
          "tgn:7029392"
        ],
        "placetype": [
          "aat:300006191"
        ],
        "id": 2640947,
        "name:xx": "Sanchez Tank"
      }
    },
    {
      "geometry": {
        "type": "Point",
        "coordinates": [
          -103.0167,
          35.4
        ]
      },
      "type": "Feature",
      "properties": {
        "hierarchy": [
          "tgn:2640948",
          "tgn:1000001",
          "tgn:7012149",
          "tgn:2002051",
          "tgn:7007826",
          "tgn:7029392"
        ],
        "placetype": [
          "aat:300006191"
        ],
        "id": 2640948,
        "name:xx": "Sanchez Tank"
      }
    },
    {
      "geometry": {
        "type": "Point",
        "coordinates": [
          -107.4833,
          33.85
        ]
      },
      "type": "Feature",
      "properties": {
        "hierarchy": [
          "tgn:2640949",
          "tgn:1000001",
          "tgn:7012149",
          "tgn:2001456",
          "tgn:7007566",
          "tgn:7029392"
        ],
        "placetype": [
          "aat:300008697"
        ],
        "id": 2640949,
        "name:xx": "Sanchez Trough Spring"
      }
    }
  ]
}
