{
  "geometry": {
    "type": "Point",
    "coordinates": [
      -123.7833,
      47.0667
    ]
  },
  "type": "Feature",
  "properties": {
    "hierarchy": [
      "tgn:2164593",
      "tgn:1000001",
      "tgn:7012149",
      "tgn:1002418",
      "tgn:7007920",
      "tgn:7029392"
    ],
    "placetype": [
      "aat:300008706"
    ],
    "id": 2164593,
    "name:xx": "Berryman Creek"
  }
}
