{
  "type": "FeatureCollection",
  "features": [
    {
      "geometry": {
        "type": "Point",
        "coordinates": [
          -107.9833,
          37.1
        ]
      },
      "type": "Feature",
      "properties": {
        "hierarchy": [
          "tgn:2631480",
          "tgn:1000001",
          "tgn:7012149",
          "tgn:2000225",
          "tgn:7007158",
          "tgn:7029392"
        ],
        "placetype": [
          "aat:300008798"
        ],
        "id": 2631480,
        "name:xx": "Round Top"
      }
    },
    {
      "geometry": {
        "type": "Point",
        "coordinates": [
          -107.7667,
          38.15
        ]
      },
      "type": "Feature",
      "properties": {
        "hierarchy": [
          "tgn:2631481",
          "tgn:1000001",
          "tgn:7012149",
          "tgn:2000237",
          "tgn:7007158",
          "tgn:7029392"
        ],
        "placetype": [
          "aat:300008798"
        ],
        "id": 2631481,
        "name:xx": "Round Top"
      }
    },
    {
      "geometry": {
        "type": "Point",
        "coordinates": [
          -81.5167,
          30.4167
        ]
      },
      "type": "Feature",
      "properties": {
        "hierarchy": [
          "tgn:2631482",
          "tgn:1000001",
          "tgn:2000264",
          "tgn:7012149",
          "tgn:7007240",
          "tgn:7029392"
        ],
        "placetype": [
          "aat:300008798"
        ],
        "id": 2631482,
        "name:xx": "Round Top"
      }
    },
    {
      "geometry": {
        "type": "Point",
        "coordinates": [
          -84.1,
          34.7
        ]
      },
      "type": "Feature",
      "properties": {
        "hierarchy": [
          "tgn:2631483",
          "tgn:1000001",
          "tgn:7012149",
          "tgn:2000435",
          "tgn:7007248",
          "tgn:7029392"
        ],
        "placetype": [
          "aat:300008798"
        ],
        "id": 2631483,
        "name:xx": "Round Top"
      }
    },
    {
      "geometry": {
        "type": "Point",
        "coordinates": [
          -83.65,
          34.8333
        ]
      },
      "type": "Feature",
      "properties": {
        "hierarchy": [
          "tgn:2631484",
          "tgn:1000001",
          "tgn:7012149",
          "tgn:7007248",
          "tgn:7029392"
        ],
        "placetype": [
          "aat:300008798"
        ],
        "id": 2631484,
        "name:xx": "Round Top"
      }
    },
    {
      "geometry": {
        "type": "Point",
        "coordinates": [
          -83.4667,
          34.8833
        ]
      },
      "type": "Feature",
      "properties": {
        "hierarchy": [
          "tgn:2631485",
          "tgn:1000001",
          "tgn:7012149",
          "tgn:2000410",
          "tgn:7007248",
          "tgn:7029392"
        ],
        "placetype": [
          "aat:300008798"
        ],
        "id": 2631485,
        "name:xx": "Round Top"
      }
    },
    {
      "geometry": {
        "type": "Point",
        "coordinates": [
          -85.4,
          34.8333
        ]
      },
      "type": "Feature",
      "properties": {
        "hierarchy": [
          "tgn:2631486",
          "tgn:1000001",
          "tgn:7012149",
          "tgn:2000437",
          "tgn:7007248",
          "tgn:7029392"
        ],
        "placetype": [
          "aat:300008798"
        ],
        "id": 2631486,
        "name:xx": "Round Top"
      }
    },
    {
      "geometry": {
        "type": "Point",
        "coordinates": [
          -83.7333,
          34.8667
        ]
      },
      "type": "Feature",
      "properties": {
        "hierarchy": [
          "tgn:2631487",
          "tgn:1000001",
          "tgn:7012149",
          "tgn:2000430",
          "tgn:7007248",
          "tgn:7029392"
        ],
        "placetype": [
          "aat:300008798"
        ],
        "id": 2631487,
        "name:xx": "Round Top"
      }
    },
    {
      "geometry": {
        "type": "Point",
        "coordinates": [
          -157.8167,
          21.3167
        ]
      },
      "type": "Feature",
      "properties": {
        "hierarchy": [
          "tgn:2631488",
          "tgn:1002483",
          "tgn:7019080",
          "tgn:1000001",
          "tgn:7012149",
          "tgn:7007249",
          "tgn:7029392"
        ],
        "placetype": [
          "aat:300008798"
        ],
        "id": 2631488,
        "name:xx": "Round Top"
      }
    },
    {
      "geometry": {
        "type": "Point",
        "coordinates": [
          -116.5,
          47.3833
        ]
      },
      "type": "Feature",
      "properties": {
        "hierarchy": [
          "tgn:2631489",
          "tgn:2000456",
          "tgn:1000001",
          "tgn:7012149",
          "tgn:7007250",
          "tgn:7029392"
        ],
        "placetype": [
          "aat:300008798"
        ],
        "id": 2631489,
        "name:xx": "Round Top"
      }
    }
  ]
}
