{
  "type": "FeatureCollection",
  "features": [
    {
      "geometry": {
        "type": "Point",
        "coordinates": [
          -69.8667,
          46.1667
        ]
      },
      "type": "Feature",
      "properties": {
        "hierarchy": [
          "tgn:2242400",
          "tgn:1000001",
          "tgn:7012149",
          "tgn:2000930",
          "tgn:7007515",
          "tgn:7029392"
        ],
        "placetype": [
          "aat:300008680"
        ],
        "id": 2242400,
        "name:xx": "Clayton Pond"
      }
    },
    {
      "geometry": {
        "type": "Point",
        "coordinates": [
          -103.9167,
          44.2
        ]
      },
      "type": "Feature",
      "properties": {
        "hierarchy": [
          "tgn:2242401",
          "tgn:1000001",
          "tgn:2001810",
          "tgn:7012149",
          "tgn:7007713",
          "tgn:7029392"
        ],
        "placetype": [
          "aat:300008680"
        ],
        "id": 2242401,
        "name:xx": "Clayton Pond"
      }
    },
    {
      "geometry": {
        "type": "Point",
        "coordinates": [
          -106.3,
          40.5
        ]
      },
      "type": "Feature",
      "properties": {
        "hierarchy": [
          "tgn:2242402",
          "tgn:1000001",
          "tgn:7012149",
          "tgn:2000220",
          "tgn:7007158",
          "tgn:7029392"
        ],
        "placetype": [
          "aat:300006191"
        ],
        "id": 2242402,
        "name:xx": "Clayton Reservoir"
      }
    },
    {
      "geometry": {
        "type": "Point",
        "coordinates": [
          -119.85,
          44.25
        ]
      },
      "type": "Feature",
      "properties": {
        "hierarchy": [
          "tgn:2242403",
          "tgn:1000001",
          "tgn:2001703",
          "tgn:7012149",
          "tgn:7007708",
          "tgn:7029392"
        ],
        "placetype": [
          "aat:300006191"
        ],
        "id": 2242403,
        "name:xx": "Clayton Reservoir"
      }
    },
    {
      "geometry": {
        "type": "Point",
        "coordinates": [
          -92.8,
          36.6833
        ]
      },
      "type": "Feature",
      "properties": {
        "hierarchy": [
          "tgn:2242404",
          "tgn:1000001",
          "tgn:7012149",
          "tgn:2001251",
          "tgn:7007523",
          "tgn:7029392"
        ],
        "placetype": [
          "aat:300266640"
        ],
        "id": 2242404,
        "name:xx": "Clayton Ridge"
      }
    },
    {
      "geometry": {
        "type": "Point",
        "coordinates": [
          -117.4667,
          37.6833
        ]
      },
      "type": "Feature",
      "properties": {
        "hierarchy": [
          "tgn:2242405",
          "tgn:1000001",
          "tgn:2001412",
          "tgn:7012149",
          "tgn:7007526",
          "tgn:7029392"
        ],
        "placetype": [
          "aat:300266640"
        ],
        "id": 2242405,
        "name:xx": "Clayton Ridge"
      }
    },
    {
      "geometry": {
        "type": "Point",
        "coordinates": [
          -107.9333,
          40.7667
        ]
      },
      "type": "Feature",
      "properties": {
        "hierarchy": [
          "tgn:2242407",
          "tgn:1000001",
          "tgn:7012149",
          "tgn:2000232",
          "tgn:7007158",
          "tgn:7029392"
        ],
        "placetype": [
          "aat:300008697"
        ],
        "id": 2242407,
        "name:xx": "Clayton Spring"
      }
    },
    {
      "geometry": {
        "type": "Point",
        "coordinates": [
          -108.4833,
          33.3667
        ]
      },
      "type": "Feature",
      "properties": {
        "hierarchy": [
          "tgn:2242408",
          "tgn:1000001",
          "tgn:2001429",
          "tgn:7012149",
          "tgn:7007566",
          "tgn:7029392"
        ],
        "placetype": [
          "aat:300008697"
        ],
        "id": 2242408,
        "name:xx": "Clayton Spring"
      }
    },
    {
      "geometry": {
        "type": "Point",
        "coordinates": [
          -118.1167,
          44.6
        ]
      },
      "type": "Feature",
      "properties": {
        "hierarchy": [
          "tgn:2242409",
          "tgn:7013349",
          "tgn:1000001",
          "tgn:7012149",
          "tgn:7007708",
          "tgn:7029392"
        ],
        "placetype": [
          "aat:300008697"
        ],
        "id": 2242409,
        "name:xx": "Clayton Spring"
      }
    }
  ]
}
