{
  "geometry": {
    "type": "Point",
    "coordinates": [
      -103.6333,
      44.3167
    ]
  },
  "type": "Feature",
  "properties": {
    "hierarchy": [
      "tgn:2382018",
      "tgn:1000001",
      "tgn:2001810",
      "tgn:7012149",
      "tgn:7007713",
      "tgn:7029392"
    ],
    "placetype": [
      "aat:300000390"
    ],
    "id": 2382018,
    "name:xx": "Hayes Mine"
  }
}
