{
  "geometry": {
    "type": "Point",
    "coordinates": [
      -88.2833,
      42.45
    ]
  },
  "type": "Feature",
  "properties": {
    "hierarchy": [
      "tgn:2391095",
      "tgn:1000001",
      "tgn:7012149",
      "tgn:7019014",
      "tgn:7007251",
      "tgn:7029392"
    ],
    "placetype": [
      "aat:300008798"
    ],
    "id": 2391095,
    "name:xx": "Hill Fifteen"
  }
}
