{
  "geometry": {
    "type": "Point",
    "coordinates": [
      -120.6667,
      36.0333
    ]
  },
  "type": "Feature",
  "properties": {
    "hierarchy": [
      "tgn:2196052",
      "tgn:1000001",
      "tgn:7012149",
      "tgn:7007157",
      "tgn:1002684",
      "tgn:7029392"
    ],
    "placetype": [
      "aat:300008697"
    ],
    "id": 2196052,
    "name:xx": "Brock Springs"
  }
}
