{
  "geometry": {
    "type": "Point",
    "coordinates": [
      31.00702,
      30.501618
    ]
  },
  "type": "Feature",
  "properties": {
    "hierarchy": [
      "tgn:7537448",
      "tgn:7001242",
      "tgn:7016833",
      "tgn:1001087",
      "tgn:7029392"
    ],
    "placetype": [
      "aat:300008347"
    ],
    "name:en": "Shanawān",
    "id": 7537448
  }
}
