{
  "geometry": {
    "type": "Point",
    "coordinates": [
      34.59909,
      29.072651
    ]
  },
  "type": "Feature",
  "properties": {
    "hierarchy": [
      "tgn:7521751",
      "tgn:7001242",
      "tgn:7016833",
      "tgn:7001336",
      "tgn:7029392"
    ],
    "placetype": [
      "aat:300008795"
    ],
    "name:en": "Abū Khashib, Jabal",
    "id": 7521751
  }
}
