{
  "geometry": {
    "type": "Point",
    "coordinates": [
      -108.0667,
      38.6167
    ]
  },
  "type": "Feature",
  "properties": {
    "hierarchy": [
      "tgn:2211582",
      "tgn:1000001",
      "tgn:7012149",
      "tgn:7007158",
      "tgn:7029392"
    ],
    "placetype": [
      "aat:300008706"
    ],
    "id": 2211582,
    "name:xx": "Buttermilk Creek"
  }
}
