{
  "geometry": {
    "type": "Point",
    "coordinates": [
      -70.7167,
      43.0167
    ]
  },
  "type": "Feature",
  "properties": {
    "hierarchy": [
      "tgn:2650248",
      "tgn:1000001",
      "tgn:7014352",
      "tgn:7012149",
      "tgn:7007564",
      "tgn:7029392"
    ],
    "placetype": [
      "aat:300132348"
    ],
    "id": 2650248,
    "name:xx": "Seal Rocks"
  }
}
