{
  "geometry": {
    "type": "Point",
    "coordinates": [
      -109.85,
      34.8333
    ]
  },
  "type": "Feature",
  "properties": {
    "hierarchy": [
      "tgn:2222765",
      "tgn:1000001",
      "tgn:7006451",
      "tgn:7012149",
      "tgn:2000099",
      "tgn:7029392"
    ],
    "placetype": [
      "aat:300008761"
    ],
    "id": 2222765,
    "name:xx": "Carr Lake Draw"
  }
}
