{
  "geometry": {
    "type": "Point",
    "coordinates": [
      -88.35,
      13.3667
    ]
  },
  "type": "Feature",
  "properties": {
    "hierarchy": [
      "tgn:1016522",
      "tgn:7005462",
      "tgn:1000001",
      "tgn:7005441",
      "tgn:7029392"
    ],
    "placetype": [
      "aat:300008347"
    ],
    "id": 1016522,
    "name:xx": "El Tránsito"
  }
}
