{
  "geometry": {
    "type": "Point",
    "coordinates": [
      15.428,
      -12.17
    ]
  },
  "type": "Feature",
  "properties": {
    "hierarchy": [
      "tgn:1109134",
      "tgn:7001242",
      "tgn:1000149",
      "tgn:1000868",
      "tgn:7029392"
    ],
    "placetype": [
      "aat:300008795"
    ],
    "id": 1109134,
    "name:xx": "Humbi, Serra"
  }
}
