{
  "geometry": {
    "type": "Point",
    "coordinates": [
      -72.25,
      44.65
    ]
  },
  "type": "Feature",
  "properties": {
    "hierarchy": [
      "tgn:2667897",
      "tgn:1000001",
      "tgn:1002753",
      "tgn:7012149",
      "tgn:7007828",
      "tgn:7029392"
    ],
    "placetype": [
      "aat:300008761"
    ],
    "id": 2667897,
    "name:xx": "Skunk Hollow"
  }
}
