{
  "geometry": {
    "type": "Point",
    "coordinates": [
      -116.7667,
      42.9167
    ]
  },
  "type": "Feature",
  "properties": {
    "hierarchy": [
      "tgn:2332009",
      "tgn:1000001",
      "tgn:7012149",
      "tgn:2000488",
      "tgn:7007250",
      "tgn:7029392"
    ],
    "placetype": [
      "aat:300008347"
    ],
    "id": 2332009,
    "name:xx": "Flint"
  }
}
