{
  "geometry": {
    "type": "Point",
    "coordinates": [
      -85.9167,
      41.45
    ]
  },
  "type": "Feature",
  "properties": {
    "hierarchy": [
      "tgn:2746967",
      "tgn:1000001",
      "tgn:7012149",
      "tgn:1002353",
      "tgn:7007252",
      "tgn:7029392"
    ],
    "placetype": [
      "aat:300006075"
    ],
    "id": 2746967,
    "name:xx": "Wagner Ditch"
  }
}
