{
  "geometry": {
    "type": "Point",
    "coordinates": [
      -70.85,
      -34.45
    ]
  },
  "type": "Feature",
  "properties": {
    "hierarchy": [
      "tgn:7292121",
      "tgn:1001695",
      "tgn:1000049",
      "tgn:1000002",
      "tgn:7029392"
    ],
    "placetype": [
      "aat:300387200"
    ],
    "id": 7292121,
    "name:xx": "El Vergel"
  }
}
