{
  "geometry": {
    "type": "Point",
    "coordinates": [
      24.08805,
      37.77362
    ]
  },
  "type": "Feature",
  "properties": {
    "hierarchy": [
      "tgn:7218643",
      "tgn:7002681",
      "tgn:7001395",
      "tgn:1000003",
      "tgn:1000074",
      "tgn:7029392"
    ],
    "placetype": [
      "aat:300132316"
    ],
    "id": 7218643,
    "name:xx": "Vromopoúsi, Ormískos"
  }
}
