{
  "type": "FeatureCollection",
  "features": [
    {
      "geometry": {
        "type": "Point",
        "coordinates": [
          12.966667,
          51.666667
        ]
      },
      "type": "Feature",
      "properties": {
        "hierarchy": [
          "tgn:7150850",
          "tgn:1000003",
          "tgn:7003687",
          "tgn:7000084",
          "tgn:7029392"
        ],
        "placetype": [
          "aat:300008347"
        ],
        "id": 7150850,
        "name:xx": "Labrun"
      }
    },
    {
      "geometry": {
        "type": "Point",
        "coordinates": [
          14.066667,
          53.916667
        ]
      },
      "type": "Feature",
      "properties": {
        "hierarchy": [
          "tgn:7150851",
          "tgn:1000003",
          "tgn:7000094",
          "tgn:7000084",
          "tgn:7029392"
        ],
        "placetype": [
          "aat:300008347"
        ],
        "id": 7150851,
        "name:xx": "Labömitz"
      }
    },
    {
      "geometry": {
        "type": "Point",
        "coordinates": [
          12.7,
          51.866667
        ]
      },
      "type": "Feature",
      "properties": {
        "hierarchy": [
          "tgn:7150853",
          "tgn:1000003",
          "tgn:7003687",
          "tgn:7000084",
          "tgn:7029392"
        ],
        "placetype": [
          "aat:300008347"
        ],
        "id": 7150853,
        "name:xx": "Labetz"
      }
    },
    {
      "geometry": {
        "type": "Point",
        "coordinates": [
          10.383333,
          49.1
        ]
      },
      "type": "Feature",
      "properties": {
        "hierarchy": [
          "tgn:7150855",
          "tgn:7003669",
          "tgn:1000003",
          "tgn:7000084",
          "tgn:7029392"
        ],
        "placetype": [
          "aat:300008347"
        ],
        "id": 7150855,
        "name:xx": "Labertswend"
      }
    },
    {
      "geometry": {
        "type": "Point",
        "coordinates": [
          11.866667,
          49.2
        ]
      },
      "type": "Feature",
      "properties": {
        "hierarchy": [
          "tgn:7150856",
          "tgn:7003669",
          "tgn:1000003",
          "tgn:7000084",
          "tgn:7029392"
        ],
        "placetype": [
          "aat:300000206"
        ],
        "id": 7150856,
        "name:xx": "Laberthal"
      }
    },
    {
      "geometry": {
        "type": "Point",
        "coordinates": [
          11.483333,
          49.3
        ]
      },
      "type": "Feature",
      "properties": {
        "hierarchy": [
          "tgn:7150857",
          "tgn:7003669",
          "tgn:1000003",
          "tgn:7000084",
          "tgn:7029392"
        ],
        "placetype": [
          "aat:300008347"
        ],
        "id": 7150857,
        "name:xx": "Labersricht"
      }
    },
    {
      "geometry": {
        "type": "Point",
        "coordinates": [
          11.3,
          48.483333
        ]
      },
      "type": "Feature",
      "properties": {
        "hierarchy": [
          "tgn:7150858",
          "tgn:7003669",
          "tgn:1000003",
          "tgn:7000084",
          "tgn:7029392"
        ],
        "placetype": [
          "aat:300008347"
        ],
        "id": 7150858,
        "name:xx": "Labersdorf"
      }
    },
    {
      "geometry": {
        "type": "Point",
        "coordinates": [
          11.35,
          48.5
        ]
      },
      "type": "Feature",
      "properties": {
        "hierarchy": [
          "tgn:7150859",
          "tgn:7003669",
          "tgn:1000003",
          "tgn:7000084",
          "tgn:7029392"
        ],
        "placetype": [
          "aat:300008347"
        ],
        "id": 7150859,
        "name:xx": "Labersberg"
      }
    }
  ]
}
