{
  "geometry": {
    "type": "Point",
    "coordinates": [
      -8.085,
      37.698
    ]
  },
  "type": "Feature",
  "properties": {
    "hierarchy": [
      "tgn:1049743",
      "tgn:1000810",
      "tgn:1000003",
      "tgn:1000090",
      "tgn:7029392"
    ],
    "placetype": [
      "aat:300008347",
      "aat:300387218"
    ],
    "id": 1049743,
    "name:xx": "Castro Verde"
  }
}
