{
  "type": "FeatureCollection",
  "features": [
    {
      "geometry": {
        "type": "Point",
        "coordinates": [
          0.266667,
          50.95
        ]
      },
      "type": "Feature",
      "properties": {
        "hierarchy": [
          "tgn:1029500",
          "tgn:7002445",
          "tgn:1000003",
          "tgn:7008129",
          "tgn:7008591",
          "tgn:7029392"
        ],
        "placetype": [
          "aat:300008347"
        ],
        "name:en": "Heathfield",
        "id": 1029500
      }
    },
    {
      "geometry": {
        "type": "Point",
        "coordinates": [
          -2.45,
          53.4
        ]
      },
      "type": "Feature",
      "properties": {
        "hierarchy": [
          "tgn:1029501",
          "tgn:7002445",
          "tgn:7008114",
          "tgn:1000003",
          "tgn:7008591",
          "tgn:7029392"
        ],
        "placetype": [
          "aat:300008347"
        ],
        "id": 1029501,
        "name:xx": "Heatley"
      }
    },
    {
      "geometry": {
        "type": "Point",
        "coordinates": [
          -2.1833,
          53.4167
        ]
      },
      "type": "Feature",
      "properties": {
        "hierarchy": [
          "tgn:1029502",
          "tgn:7002445",
          "tgn:1003647",
          "tgn:1000003",
          "tgn:7026570",
          "tgn:7008591",
          "tgn:7029392"
        ],
        "placetype": [
          "aat:300008347"
        ],
        "id": 1029502,
        "name:xx": "Heaton Moor"
      }
    },
    {
      "geometry": {
        "type": "Point",
        "coordinates": [
          0.25,
          51.3
        ]
      },
      "type": "Feature",
      "properties": {
        "hierarchy": [
          "tgn:1029503",
          "tgn:7002445",
          "tgn:1000003",
          "tgn:7008153",
          "tgn:7008591",
          "tgn:7029392"
        ],
        "placetype": [
          "aat:300008347"
        ],
        "id": 1029503,
        "name:xx": "Heaverham"
      }
    },
    {
      "geometry": {
        "type": "Point",
        "coordinates": [
          -2.15,
          53.4
        ]
      },
      "type": "Feature",
      "properties": {
        "hierarchy": [
          "tgn:1029504",
          "tgn:7002445",
          "tgn:1003647",
          "tgn:1000003",
          "tgn:7026570",
          "tgn:7008591",
          "tgn:7029392"
        ],
        "placetype": [
          "aat:300008347"
        ],
        "id": 1029504,
        "name:xx": "Heaviley"
      }
    },
    {
      "geometry": {
        "type": "Point",
        "coordinates": [
          -1.516667,
          54.966667
        ]
      },
      "type": "Feature",
      "properties": {
        "hierarchy": [
          "tgn:1029505",
          "tgn:7019071",
          "tgn:7002445",
          "tgn:1000003",
          "tgn:7012033",
          "tgn:7008591",
          "tgn:7029392"
        ],
        "placetype": [
          "aat:300008347"
        ],
        "name:en": "Hebburn",
        "id": 1029505
      }
    },
    {
      "geometry": {
        "type": "Point",
        "coordinates": [
          -2.016667,
          53.75
        ]
      },
      "type": "Feature",
      "properties": {
        "hierarchy": [
          "tgn:1029506",
          "tgn:1003573",
          "tgn:7002445",
          "tgn:1000003",
          "tgn:7029507",
          "tgn:7008591",
          "tgn:7029392"
        ],
        "placetype": [
          "aat:300008347"
        ],
        "name:en": "Hebden Bridge",
        "id": 1029506
      }
    },
    {
      "geometry": {
        "type": "Point",
        "coordinates": [
          -1.3,
          50.9
        ]
      },
      "type": "Feature",
      "properties": {
        "hierarchy": [
          "tgn:1029508",
          "tgn:7002445",
          "tgn:1000003",
          "tgn:7008139",
          "tgn:7008591",
          "tgn:7029392"
        ],
        "placetype": [
          "aat:300008347"
        ],
        "id": 1029508,
        "name:xx": "Hedge End"
      }
    },
    {
      "geometry": {
        "type": "Point",
        "coordinates": [
          -0.6,
          51.566667
        ]
      },
      "type": "Feature",
      "properties": {
        "hierarchy": [
          "tgn:1029509",
          "tgn:7002445",
          "tgn:7008104",
          "tgn:1000003",
          "tgn:7008591",
          "tgn:7029392"
        ],
        "placetype": [
          "aat:300008347"
        ],
        "name:en": "Hedgerley",
        "id": 1029509
      }
    }
  ]
}
