{
  "type": "FeatureCollection",
  "features": [
    {
      "geometry": {
        "type": "Point",
        "coordinates": [
          -111.5167,
          39.4
        ]
      },
      "type": "Feature",
      "properties": {
        "hierarchy": [
          "tgn:2765940",
          "tgn:1000001",
          "tgn:7012149",
          "tgn:2002120",
          "tgn:7007827",
          "tgn:7029392"
        ],
        "placetype": [
          "aat:300008798"
        ],
        "id": 2765940,
        "name:xx": "White Hill"
      }
    },
    {
      "geometry": {
        "type": "Point",
        "coordinates": [
          -109.1,
          40.8833
        ]
      },
      "type": "Feature",
      "properties": {
        "hierarchy": [
          "tgn:2765941",
          "tgn:1000001",
          "tgn:2002105",
          "tgn:7012149",
          "tgn:7007827",
          "tgn:7029392"
        ],
        "placetype": [
          "aat:300008798"
        ],
        "id": 2765941,
        "name:xx": "White Hill"
      }
    },
    {
      "geometry": {
        "type": "Point",
        "coordinates": [
          -112.85,
          37.75
        ]
      },
      "type": "Feature",
      "properties": {
        "hierarchy": [
          "tgn:2765942",
          "tgn:1000001",
          "tgn:7012149",
          "tgn:2002111",
          "tgn:7007827",
          "tgn:7029392"
        ],
        "placetype": [
          "aat:300008798"
        ],
        "id": 2765942,
        "name:xx": "White Hill"
      }
    },
    {
      "geometry": {
        "type": "Point",
        "coordinates": [
          -72.15,
          44.1833
        ]
      },
      "type": "Feature",
      "properties": {
        "hierarchy": [
          "tgn:2765943",
          "tgn:1000001",
          "tgn:2002134",
          "tgn:7012149",
          "tgn:7007828",
          "tgn:7029392"
        ],
        "placetype": [
          "aat:300008798"
        ],
        "id": 2765943,
        "name:xx": "White Hill"
      }
    },
    {
      "geometry": {
        "type": "Point",
        "coordinates": [
          -76.0167,
          36.9
        ]
      },
      "type": "Feature",
      "properties": {
        "hierarchy": [
          "tgn:2765944",
          "tgn:1000001",
          "tgn:7012149",
          "tgn:7022218",
          "tgn:7007919",
          "tgn:7029392"
        ],
        "placetype": [
          "aat:300008798"
        ],
        "id": 2765944,
        "name:xx": "White Hill"
      }
    },
    {
      "geometry": {
        "type": "Point",
        "coordinates": [
          -79.35,
          37.95
        ]
      },
      "type": "Feature",
      "properties": {
        "hierarchy": [
          "tgn:2765945",
          "tgn:1000001",
          "tgn:7012149",
          "tgn:2002186",
          "tgn:7007919",
          "tgn:7029392"
        ],
        "placetype": [
          "aat:300008798"
        ],
        "id": 2765945,
        "name:xx": "White Hill"
      }
    },
    {
      "geometry": {
        "type": "Point",
        "coordinates": [
          -81.3167,
          38.5333
        ]
      },
      "type": "Feature",
      "properties": {
        "hierarchy": [
          "tgn:2765946",
          "tgn:1000001",
          "tgn:7012149",
          "tgn:2002293",
          "tgn:7013961",
          "tgn:7029392"
        ],
        "placetype": [
          "aat:300008798"
        ],
        "id": 2765946,
        "name:xx": "White Hill"
      }
    },
    {
      "geometry": {
        "type": "Point",
        "coordinates": [
          -90.2167,
          42.5333
        ]
      },
      "type": "Feature",
      "properties": {
        "hierarchy": [
          "tgn:2765947",
          "tgn:1000001",
          "tgn:7012149",
          "tgn:2002332",
          "tgn:7007922",
          "tgn:7029392"
        ],
        "placetype": [
          "aat:300008798"
        ],
        "id": 2765947,
        "name:xx": "White Hill"
      }
    },
    {
      "geometry": {
        "type": "Point",
        "coordinates": [
          -104.6,
          43.05
        ]
      },
      "type": "Feature",
      "properties": {
        "hierarchy": [
          "tgn:2765948",
          "tgn:1000001",
          "tgn:7012149",
          "tgn:2002378",
          "tgn:7007923",
          "tgn:7029392"
        ],
        "placetype": [
          "aat:300008798"
        ],
        "id": 2765948,
        "name:xx": "White Hill"
      }
    },
    {
      "geometry": {
        "type": "Point",
        "coordinates": [
          -120.7167,
          42.7
        ]
      },
      "type": "Feature",
      "properties": {
        "hierarchy": [
          "tgn:2765949",
          "tgn:1000001",
          "tgn:7012149",
          "tgn:2001715",
          "tgn:7007708",
          "tgn:7029392"
        ],
        "placetype": [
          "aat:300008706"
        ],
        "id": 2765949,
        "name:xx": "White Hill Creek"
      }
    }
  ]
}
