{
  "geometry": {
    "type": "Point",
    "coordinates": [
      -89.65,
      39.3167
    ]
  },
  "type": "Feature",
  "properties": {
    "hierarchy": [
      "tgn:2786691",
      "tgn:1000001",
      "tgn:7012149",
      "tgn:1002685",
      "tgn:7007251",
      "tgn:7029392"
    ],
    "placetype": [
      "aat:300008347"
    ],
    "id": 2786691,
    "name:xx": "Zanesville"
  }
}
