{
  "geometry": {
    "type": "Point",
    "coordinates": [
      14.5833,
      -2.3167
    ]
  },
  "type": "Feature",
  "properties": {
    "hierarchy": [
      "tgn:1088665",
      "tgn:7001242",
      "tgn:1001022",
      "tgn:1000158",
      "tgn:7029392"
    ],
    "placetype": [
      "aat:300008347"
    ],
    "id": 1088665,
    "name:xx": "Lékana"
  }
}
