{
  "geometry": {
    "type": "Point",
    "coordinates": [
      102.5833,
      2.0167
    ]
  },
  "type": "Feature",
  "properties": {
    "hierarchy": [
      "tgn:1082880",
      "tgn:7016691",
      "tgn:7000317",
      "tgn:1000004",
      "tgn:1000128",
      "tgn:7029392"
    ],
    "placetype": [
      "aat:300008347",
      "aat:300008375",
      "aat:300120599"
    ],
    "id": 1082880,
    "name:xx": "Muar"
  }
}
