{
  "type": "FeatureCollection",
  "features": [
    {
      "geometry": {
        "type": "Point",
        "coordinates": [
          -90.5,
          46.05
        ]
      },
      "type": "Feature",
      "properties": {
        "hierarchy": [
          "tgn:2538050",
          "tgn:2002306",
          "tgn:1000001",
          "tgn:7012149",
          "tgn:7007922",
          "tgn:7029392"
        ],
        "placetype": [
          "aat:300008706"
        ],
        "id": 2538050,
        "name:xx": "Nelson Creek"
      }
    },
    {
      "geometry": {
        "type": "Point",
        "coordinates": [
          -91.65,
          46.6333
        ]
      },
      "type": "Feature",
      "properties": {
        "hierarchy": [
          "tgn:2538051",
          "tgn:1000001",
          "tgn:2002318",
          "tgn:7012149",
          "tgn:7007922",
          "tgn:7029392"
        ],
        "placetype": [
          "aat:300008706"
        ],
        "id": 2538051,
        "name:xx": "Nelson Creek"
      }
    },
    {
      "geometry": {
        "type": "Point",
        "coordinates": [
          -90.4333,
          44.8
        ]
      },
      "type": "Feature",
      "properties": {
        "hierarchy": [
          "tgn:2538052",
          "tgn:1000001",
          "tgn:2002314",
          "tgn:7012149",
          "tgn:7007922",
          "tgn:7029392"
        ],
        "placetype": [
          "aat:300008706"
        ],
        "id": 2538052,
        "name:xx": "Nelson Creek"
      }
    },
    {
      "geometry": {
        "type": "Point",
        "coordinates": [
          -90.5833,
          45.7667
        ]
      },
      "type": "Feature",
      "properties": {
        "hierarchy": [
          "tgn:2538053",
          "tgn:1000001",
          "tgn:7012149",
          "tgn:2002348",
          "tgn:7007922",
          "tgn:7029392"
        ],
        "placetype": [
          "aat:300008706"
        ],
        "id": 2538053,
        "name:xx": "Nelson Creek"
      }
    },
    {
      "geometry": {
        "type": "Point",
        "coordinates": [
          -106.2,
          47.55
        ]
      },
      "type": "Feature",
      "properties": {
        "hierarchy": [
          "tgn:2538054",
          "tgn:1000001",
          "tgn:7012149",
          "tgn:2001287",
          "tgn:7007524",
          "tgn:7029392"
        ],
        "placetype": [
          "aat:300132316"
        ],
        "id": 2538054,
        "name:xx": "Nelson Creek Bay"
      }
    },
    {
      "geometry": {
        "type": "Point",
        "coordinates": [
          -108.25,
          38.15
        ]
      },
      "type": "Feature",
      "properties": {
        "hierarchy": [
          "tgn:2538055",
          "tgn:1000001",
          "tgn:7012149",
          "tgn:7007158",
          "tgn:7029392"
        ],
        "placetype": [
          "aat:300006075"
        ],
        "id": 2538055,
        "name:xx": "Nelson Ditch"
      }
    },
    {
      "geometry": {
        "type": "Point",
        "coordinates": [
          -86.5167,
          41.3333
        ]
      },
      "type": "Feature",
      "properties": {
        "hierarchy": [
          "tgn:2538056",
          "tgn:1000001",
          "tgn:7012149",
          "tgn:1002918",
          "tgn:7007252",
          "tgn:7029392"
        ],
        "placetype": [
          "aat:300006075"
        ],
        "id": 2538056,
        "name:xx": "Nelson Ditch"
      }
    },
    {
      "geometry": {
        "type": "Point",
        "coordinates": [
          -85.5,
          39.9
        ]
      },
      "type": "Feature",
      "properties": {
        "hierarchy": [
          "tgn:2538057",
          "tgn:1000001",
          "tgn:7012149",
          "tgn:1002468",
          "tgn:7007252",
          "tgn:7029392"
        ],
        "placetype": [
          "aat:300006075"
        ],
        "id": 2538057,
        "name:xx": "Nelson Ditch"
      }
    },
    {
      "geometry": {
        "type": "Point",
        "coordinates": [
          -95.9833,
          41.6667
        ]
      },
      "type": "Feature",
      "properties": {
        "hierarchy": [
          "tgn:2538058",
          "tgn:1000001",
          "tgn:2000603",
          "tgn:7012149",
          "tgn:7007253",
          "tgn:7029392"
        ],
        "placetype": [
          "aat:300006075"
        ],
        "id": 2538058,
        "name:xx": "Nelson Ditch"
      }
    },
    {
      "geometry": {
        "type": "Point",
        "coordinates": [
          -119.1333,
          38.8833
        ]
      },
      "type": "Feature",
      "properties": {
        "hierarchy": [
          "tgn:2538059",
          "tgn:1000001",
          "tgn:1002614",
          "tgn:7012149",
          "tgn:7007526",
          "tgn:7029392"
        ],
        "placetype": [
          "aat:300006075"
        ],
        "id": 2538059,
        "name:xx": "Nelson Ditch"
      }
    }
  ]
}
