{
  "type": "FeatureCollection",
  "features": [
    {
      "geometry": {
        "type": "Point",
        "coordinates": [
          121.9167,
          14
        ]
      },
      "type": "Feature",
      "properties": {
        "hierarchy": [
          "tgn:1083960",
          "tgn:1000004",
          "tgn:1001496",
          "tgn:1000135",
          "tgn:7029392"
        ],
        "placetype": [
          "aat:300008347"
        ],
        "id": 1083960,
        "name:xx": "Atimonan"
      }
    },
    {
      "geometry": {
        "type": "Point",
        "coordinates": [
          123.1333,
          9.85
        ]
      },
      "type": "Feature",
      "properties": {
        "hierarchy": [
          "tgn:1083961",
          "tgn:1000004",
          "tgn:1001449",
          "tgn:1000135",
          "tgn:7029392"
        ],
        "placetype": [
          "aat:300008347"
        ],
        "id": 1083961,
        "name:xx": "Ayuñgon"
      }
    },
    {
      "geometry": {
        "type": "Point",
        "coordinates": [
          123.4,
          12.1667
        ]
      },
      "type": "Feature",
      "properties": {
        "hierarchy": [
          "tgn:1083962",
          "tgn:1000004",
          "tgn:1001419",
          "tgn:1000135",
          "tgn:7029392"
        ],
        "placetype": [
          "aat:300008347"
        ],
        "id": 1083962,
        "name:xx": "Bañgad"
      }
    },
    {
      "geometry": {
        "type": "Point",
        "coordinates": [
          123.3667,
          13.45
        ]
      },
      "type": "Feature",
      "properties": {
        "hierarchy": [
          "tgn:1083963",
          "tgn:1000004",
          "tgn:1001175",
          "tgn:1000135",
          "tgn:7029392"
        ],
        "placetype": [
          "aat:300008347"
        ],
        "id": 1083963,
        "name:xx": "Baao"
      }
    },
    {
      "geometry": {
        "type": "Point",
        "coordinates": [
          125.7,
          7.1167
        ]
      },
      "type": "Feature",
      "properties": {
        "hierarchy": [
          "tgn:1083964",
          "tgn:1000004",
          "tgn:1008938",
          "tgn:1001218",
          "tgn:1000135",
          "tgn:7029392"
        ],
        "placetype": [
          "aat:300008347"
        ],
        "id": 1083964,
        "name:xx": "Babak"
      }
    },
    {
      "geometry": {
        "type": "Point",
        "coordinates": [
          118.9,
          9.9833
        ]
      },
      "type": "Feature",
      "properties": {
        "hierarchy": [
          "tgn:1083965",
          "tgn:1000004",
          "tgn:1001481",
          "tgn:1000135",
          "tgn:7029392"
        ],
        "placetype": [
          "aat:300008347"
        ],
        "id": 1083965,
        "name:xx": "Babuyan"
      }
    },
    {
      "geometry": {
        "type": "Point",
        "coordinates": [
          123.7833,
          13.3
        ]
      },
      "type": "Feature",
      "properties": {
        "hierarchy": [
          "tgn:1083966",
          "tgn:1001094",
          "tgn:1000004",
          "tgn:1000135",
          "tgn:7029392"
        ],
        "placetype": [
          "aat:300008347"
        ],
        "id": 1083966,
        "name:xx": "Bacacay"
      }
    },
    {
      "geometry": {
        "type": "Point",
        "coordinates": [
          119.8,
          10.45
        ]
      },
      "type": "Feature",
      "properties": {
        "hierarchy": [
          "tgn:1083967",
          "tgn:1000004",
          "tgn:1006991",
          "tgn:1001481",
          "tgn:1000135",
          "tgn:7029392"
        ],
        "placetype": [
          "aat:300008347"
        ],
        "id": 1083967,
        "name:xx": "Bacao"
      }
    },
    {
      "geometry": {
        "type": "Point",
        "coordinates": [
          122.1,
          12.4667
        ]
      },
      "type": "Feature",
      "properties": {
        "hierarchy": [
          "tgn:1083969",
          "tgn:1009333",
          "tgn:1000004",
          "tgn:1001504",
          "tgn:1000135",
          "tgn:7029392"
        ],
        "placetype": [
          "aat:300008347"
        ],
        "id": 1083969,
        "name:xx": "Bachauan"
      }
    }
  ]
}
