{
  "type": "FeatureCollection",
  "features": [
    {
      "geometry": {
        "type": "Point",
        "coordinates": [
          -79.2,
          36.85
        ]
      },
      "type": "Feature",
      "properties": {
        "hierarchy": [
          "tgn:2173820",
          "tgn:1000001",
          "tgn:7012149",
          "tgn:2002180",
          "tgn:7007919",
          "tgn:7029392"
        ],
        "placetype": [
          "aat:300008706"
        ],
        "id": 2173820,
        "name:xx": "Bird Creek"
      }
    },
    {
      "geometry": {
        "type": "Point",
        "coordinates": [
          -121.4333,
          46.1333
        ]
      },
      "type": "Feature",
      "properties": {
        "hierarchy": [
          "tgn:2173821",
          "tgn:1000001",
          "tgn:7012149",
          "tgn:7007920",
          "tgn:7029392"
        ],
        "placetype": [
          "aat:300008706"
        ],
        "id": 2173821,
        "name:xx": "Bird Creek"
      }
    },
    {
      "geometry": {
        "type": "Point",
        "coordinates": [
          -120.75,
          48.2667
        ]
      },
      "type": "Feature",
      "properties": {
        "hierarchy": [
          "tgn:2173822",
          "tgn:1000001",
          "tgn:1002260",
          "tgn:7012149",
          "tgn:7007920",
          "tgn:7029392"
        ],
        "placetype": [
          "aat:300008706"
        ],
        "id": 2173822,
        "name:xx": "Bird Creek"
      }
    },
    {
      "geometry": {
        "type": "Point",
        "coordinates": [
          -89.3333,
          44.0833
        ]
      },
      "type": "Feature",
      "properties": {
        "hierarchy": [
          "tgn:2173823",
          "tgn:1000001",
          "tgn:7012149",
          "tgn:2002362",
          "tgn:7007922",
          "tgn:7029392"
        ],
        "placetype": [
          "aat:300008706"
        ],
        "id": 2173823,
        "name:xx": "Bird Creek"
      }
    },
    {
      "geometry": {
        "type": "Point",
        "coordinates": [
          -106.2,
          41.1833
        ]
      },
      "type": "Feature",
      "properties": {
        "hierarchy": [
          "tgn:2173824",
          "tgn:2002365",
          "tgn:1000001",
          "tgn:7012149",
          "tgn:7007923",
          "tgn:7029392"
        ],
        "placetype": [
          "aat:300008706"
        ],
        "id": 2173824,
        "name:xx": "Bird Creek"
      }
    },
    {
      "geometry": {
        "type": "Point",
        "coordinates": [
          -110.75,
          42.2833
        ]
      },
      "type": "Feature",
      "properties": {
        "hierarchy": [
          "tgn:2173825",
          "tgn:1000001",
          "tgn:7012149",
          "tgn:2002376",
          "tgn:7007923",
          "tgn:7029392"
        ],
        "placetype": [
          "aat:300008706"
        ],
        "id": 2173825,
        "name:xx": "Bird Creek"
      }
    },
    {
      "geometry": {
        "type": "Point",
        "coordinates": [
          -83.5833,
          42.15
        ]
      },
      "type": "Feature",
      "properties": {
        "hierarchy": [
          "tgn:2173826",
          "tgn:1000001",
          "tgn:7012149",
          "tgn:1003000",
          "tgn:7007520",
          "tgn:7029392"
        ],
        "placetype": [
          "aat:300006075"
        ],
        "id": 2173826,
        "name:xx": "Bird Drain"
      }
    },
    {
      "geometry": {
        "type": "Point",
        "coordinates": [
          -83.5,
          43.0667
        ]
      },
      "type": "Feature",
      "properties": {
        "hierarchy": [
          "tgn:2173827",
          "tgn:1000001",
          "tgn:7012149",
          "tgn:1002406",
          "tgn:7007520",
          "tgn:7029392"
        ],
        "placetype": [
          "aat:300006075"
        ],
        "id": 2173827,
        "name:xx": "Bird Drain"
      }
    },
    {
      "geometry": {
        "type": "Point",
        "coordinates": [
          -84.2333,
          41.85
        ]
      },
      "type": "Feature",
      "properties": {
        "hierarchy": [
          "tgn:2173828",
          "tgn:1000001",
          "tgn:7012149",
          "tgn:1002588",
          "tgn:7007520",
          "tgn:7029392"
        ],
        "placetype": [
          "aat:300008699"
        ],
        "id": 2173828,
        "name:xx": "Bird Drain"
      }
    },
    {
      "geometry": {
        "type": "Point",
        "coordinates": [
          -110.25,
          42.35
        ]
      },
      "type": "Feature",
      "properties": {
        "hierarchy": [
          "tgn:2173829",
          "tgn:1000001",
          "tgn:7012149",
          "tgn:2002382",
          "tgn:7007923",
          "tgn:7029392"
        ],
        "placetype": [
          "aat:300008761"
        ],
        "id": 2173829,
        "name:xx": "Bird Draw"
      }
    }
  ]
}
