{
  "geometry": {
    "type": "Point",
    "coordinates": [
      -93.7833,
      40.75
    ]
  },
  "type": "Feature",
  "properties": {
    "hierarchy": [
      "tgn:7019179",
      "tgn:1000001",
      "tgn:7012149",
      "tgn:7007253",
      "tgn:7029392"
    ],
    "placetype": [
      "aat:300387145",
      "aat:300000771"
    ],
    "id": 7019179,
    "name:xx": "Decatur"
  }
}
