{
  "geometry": {
    "type": "Point",
    "coordinates": [
      123.0833,
      0.55
    ]
  },
  "type": "Feature",
  "properties": {
    "hierarchy": [
      "tgn:1077687",
      "tgn:1000004",
      "tgn:1001550",
      "tgn:1000116",
      "tgn:7029392"
    ],
    "placetype": [
      "aat:300008347"
    ],
    "id": 1077687,
    "name:xx": "Gorontalo"
  }
}
