{
  "geometry": {
    "type": "Point",
    "coordinates": [
      8.083333,
      51.15
    ]
  },
  "type": "Feature",
  "properties": {
    "hierarchy": [
      "tgn:7093998",
      "tgn:1000003",
      "tgn:7003677",
      "tgn:7000084",
      "tgn:7029392"
    ],
    "placetype": [
      "aat:300000206"
    ],
    "id": 7093998,
    "name:xx": "Schönscheid"
  }
}
