{
  "geometry": {
    "type": "Point",
    "coordinates": [
      -94.1167,
      31.0167
    ]
  },
  "type": "Feature",
  "properties": {
    "hierarchy": [
      "tgn:2620434",
      "tgn:1002149",
      "tgn:1000001",
      "tgn:7012149",
      "tgn:7007826",
      "tgn:7029392"
    ],
    "placetype": [
      "aat:300266640"
    ],
    "id": 2620434,
    "name:xx": "River Ridge"
  }
}
