{
  "type": "FeatureCollection",
  "features": [
    {
      "geometry": {
        "type": "Point",
        "coordinates": [
          -69.5333,
          44.75
        ]
      },
      "type": "Feature",
      "properties": {
        "hierarchy": [
          "tgn:2239430",
          "tgn:1000001",
          "tgn:7012149",
          "tgn:2000930",
          "tgn:7007515",
          "tgn:7029392"
        ],
        "placetype": [
          "aat:300008798"
        ],
        "id": 2239430,
        "name:xx": "Church Hill"
      }
    },
    {
      "geometry": {
        "type": "Point",
        "coordinates": [
          -73.05,
          42.2167
        ]
      },
      "type": "Feature",
      "properties": {
        "hierarchy": [
          "tgn:2239431",
          "tgn:7013388",
          "tgn:1000001",
          "tgn:7012149",
          "tgn:7007517",
          "tgn:7029392"
        ],
        "placetype": [
          "aat:300008798"
        ],
        "id": 2239431,
        "name:xx": "Church Hill"
      }
    },
    {
      "geometry": {
        "type": "Point",
        "coordinates": [
          -72.1,
          42.5833
        ]
      },
      "type": "Feature",
      "properties": {
        "hierarchy": [
          "tgn:2239432",
          "tgn:1000001",
          "tgn:7012149",
          "tgn:1003038",
          "tgn:7007517",
          "tgn:7029392"
        ],
        "placetype": [
          "aat:300008798"
        ],
        "id": 2239432,
        "name:xx": "Church Hill"
      }
    },
    {
      "geometry": {
        "type": "Point",
        "coordinates": [
          -89.2833,
          33.55
        ]
      },
      "type": "Feature",
      "properties": {
        "hierarchy": [
          "tgn:2239433",
          "tgn:1000001",
          "tgn:7012149",
          "tgn:2001163",
          "tgn:7007522",
          "tgn:7029392"
        ],
        "placetype": [
          "aat:300008798"
        ],
        "id": 2239433,
        "name:xx": "Church Hill"
      }
    },
    {
      "geometry": {
        "type": "Point",
        "coordinates": [
          -109.1833,
          45.3667
        ]
      },
      "type": "Feature",
      "properties": {
        "hierarchy": [
          "tgn:2239434",
          "tgn:1000001",
          "tgn:2001264",
          "tgn:7012149",
          "tgn:7007524",
          "tgn:7029392"
        ],
        "placetype": [
          "aat:300008798"
        ],
        "id": 2239434,
        "name:xx": "Church Hill"
      }
    },
    {
      "geometry": {
        "type": "Point",
        "coordinates": [
          -73.55,
          41.65
        ]
      },
      "type": "Feature",
      "properties": {
        "hierarchy": [
          "tgn:2239435",
          "tgn:1000001",
          "tgn:1002347",
          "tgn:7012149",
          "tgn:7007568",
          "tgn:7029392"
        ],
        "placetype": [
          "aat:300008798"
        ],
        "id": 2239435,
        "name:xx": "Church Hill"
      }
    },
    {
      "geometry": {
        "type": "Point",
        "coordinates": [
          -75.5,
          42.7167
        ]
      },
      "type": "Feature",
      "properties": {
        "hierarchy": [
          "tgn:2239436",
          "tgn:1000001",
          "tgn:1002262",
          "tgn:7012149",
          "tgn:7007568",
          "tgn:7029392"
        ],
        "placetype": [
          "aat:300008798"
        ],
        "id": 2239436,
        "name:xx": "Church Hill"
      }
    },
    {
      "geometry": {
        "type": "Point",
        "coordinates": [
          -73.8167,
          42.2167
        ]
      },
      "type": "Feature",
      "properties": {
        "hierarchy": [
          "tgn:2239437",
          "tgn:1000001",
          "tgn:7013638",
          "tgn:7012149",
          "tgn:7007568",
          "tgn:7029392"
        ],
        "placetype": [
          "aat:300008798"
        ],
        "id": 2239437,
        "name:xx": "Church Hill"
      }
    },
    {
      "geometry": {
        "type": "Point",
        "coordinates": [
          -78.0333,
          36.4667
        ]
      },
      "type": "Feature",
      "properties": {
        "hierarchy": [
          "tgn:2239438",
          "tgn:1000001",
          "tgn:7012149",
          "tgn:2001549",
          "tgn:7007709",
          "tgn:7029392"
        ],
        "placetype": [
          "aat:300008347"
        ],
        "id": 2239438,
        "name:xx": "Church Hill"
      }
    },
    {
      "geometry": {
        "type": "Point",
        "coordinates": [
          -101.8833,
          48.5
        ]
      },
      "type": "Feature",
      "properties": {
        "hierarchy": [
          "tgn:2239439",
          "tgn:1000001",
          "tgn:7012149",
          "tgn:2001607",
          "tgn:7007705",
          "tgn:7029392"
        ],
        "placetype": [
          "aat:300008798"
        ],
        "id": 2239439,
        "name:xx": "Church Hill"
      }
    }
  ]
}
