{
  "type": "FeatureCollection",
  "features": [
    {
      "geometry": {
        "type": "Point",
        "coordinates": [
          -8.383333,
          43
        ]
      },
      "type": "Feature",
      "properties": {
        "hierarchy": [
          "tgn:7296130",
          "tgn:7002824",
          "tgn:1000003",
          "tgn:7002786",
          "tgn:1000095",
          "tgn:7029392"
        ],
        "placetype": [
          "aat:300008347"
        ],
        "id": 7296130,
        "name:xx": "Villarromarís"
      }
    },
    {
      "geometry": {
        "type": "Point",
        "coordinates": [
          -5.833333,
          42.7
        ]
      },
      "type": "Feature",
      "properties": {
        "hierarchy": [
          "tgn:7296131",
          "tgn:7002826",
          "tgn:7001158",
          "tgn:1000003",
          "tgn:1000095",
          "tgn:7029392"
        ],
        "placetype": [
          "aat:300008347"
        ],
        "id": 7296131,
        "name:xx": "Villarrodrigo de Ordás"
      }
    },
    {
      "geometry": {
        "type": "Point",
        "coordinates": [
          -5.533333,
          42.633333
        ]
      },
      "type": "Feature",
      "properties": {
        "hierarchy": [
          "tgn:7296132",
          "tgn:7002826",
          "tgn:7001158",
          "tgn:1000003",
          "tgn:1000095",
          "tgn:7029392"
        ],
        "placetype": [
          "aat:300008347"
        ],
        "id": 7296132,
        "name:xx": "Villarrodrigo de las Regueras"
      }
    },
    {
      "geometry": {
        "type": "Point",
        "coordinates": [
          -2.65,
          38.5
        ]
      },
      "type": "Feature",
      "properties": {
        "hierarchy": [
          "tgn:7296133",
          "tgn:7002758",
          "tgn:1001316",
          "tgn:1000003",
          "tgn:1000095",
          "tgn:7029392"
        ],
        "placetype": [
          "aat:300008699"
        ],
        "id": 7296133,
        "name:xx": "Villarrodrigo, Río de"
      }
    },
    {
      "geometry": {
        "type": "Point",
        "coordinates": [
          -2.6,
          38.483333
        ]
      },
      "type": "Feature",
      "properties": {
        "hierarchy": [
          "tgn:7296134",
          "tgn:7002758",
          "tgn:1001316",
          "tgn:1000003",
          "tgn:1000095",
          "tgn:7029392"
        ],
        "placetype": [
          "aat:300008347"
        ],
        "id": 7296134,
        "name:xx": "Villarrodrigo"
      }
    },
    {
      "geometry": {
        "type": "Point",
        "coordinates": [
          -4.8,
          42.483333
        ]
      },
      "type": "Feature",
      "properties": {
        "hierarchy": [
          "tgn:7296136",
          "tgn:7002832",
          "tgn:7001158",
          "tgn:1000003",
          "tgn:1000095",
          "tgn:7029392"
        ],
        "placetype": [
          "aat:300008347"
        ],
        "id": 7296136,
        "name:xx": "Villarrobejo"
      }
    },
    {
      "geometry": {
        "type": "Point",
        "coordinates": [
          -5.516667,
          42.483333
        ]
      },
      "type": "Feature",
      "properties": {
        "hierarchy": [
          "tgn:7296137",
          "tgn:7002826",
          "tgn:7001158",
          "tgn:1000003",
          "tgn:1000095",
          "tgn:7029392"
        ],
        "placetype": [
          "aat:300008347"
        ],
        "id": 7296137,
        "name:xx": "Villarroañe"
      }
    },
    {
      "geometry": {
        "type": "Point",
        "coordinates": [
          -5.733333,
          42.383333
        ]
      },
      "type": "Feature",
      "properties": {
        "hierarchy": [
          "tgn:7296138",
          "tgn:7002826",
          "tgn:7001158",
          "tgn:1000003",
          "tgn:1000095",
          "tgn:7029392"
        ],
        "placetype": [
          "aat:300008347"
        ],
        "id": 7296138,
        "name:xx": "Villarrín del Páramo"
      }
    },
    {
      "geometry": {
        "type": "Point",
        "coordinates": [
          -5.633333,
          41.8
        ]
      },
      "type": "Feature",
      "properties": {
        "hierarchy": [
          "tgn:7296139",
          "tgn:7001158",
          "tgn:7002850",
          "tgn:1000003",
          "tgn:1000095",
          "tgn:7029392"
        ],
        "placetype": [
          "aat:300008347"
        ],
        "id": 7296139,
        "name:xx": "Villarrín de Campos"
      }
    }
  ]
}
