{
  "geometry": {
    "type": "Point",
    "coordinates": [
      -114.7667,
      46.3667
    ]
  },
  "type": "Feature",
  "properties": {
    "hierarchy": [
      "tgn:2644978",
      "tgn:1000001",
      "tgn:7012149",
      "tgn:2000476",
      "tgn:7007250",
      "tgn:7029392"
    ],
    "placetype": [
      "aat:300266640"
    ],
    "id": 2644978,
    "name:xx": "Saturday Ridge"
  }
}
