{
  "geometry": {
    "type": "Point",
    "coordinates": [
      -71.9833,
      42.2833
    ]
  },
  "type": "Feature",
  "properties": {
    "hierarchy": [
      "tgn:2203098",
      "tgn:1000001",
      "tgn:7012149",
      "tgn:1003038",
      "tgn:7007517",
      "tgn:7029392"
    ],
    "placetype": [
      "aat:300006191"
    ],
    "id": 2203098,
    "name:xx": "Buckhill Pond"
  }
}
