{
  "geometry": {
    "type": "Point",
    "coordinates": [
      -89.0167,
      32.55
    ]
  },
  "type": "Feature",
  "properties": {
    "hierarchy": [
      "tgn:2292729",
      "tgn:1000001",
      "tgn:7012149",
      "tgn:2001136",
      "tgn:7007522",
      "tgn:7029392"
    ],
    "placetype": [
      "aat:300008699"
    ],
    "id": 2292729,
    "name:xx": "Dorman Branch"
  }
}
