{
  "geometry": {
    "type": "Point",
    "coordinates": [
      -93.0833,
      40.0167
    ]
  },
  "type": "Feature",
  "properties": {
    "hierarchy": [
      "tgn:2318173",
      "tgn:1000001",
      "tgn:7012149",
      "tgn:2001214",
      "tgn:7007523",
      "tgn:7029392"
    ],
    "placetype": [
      "aat:300008347"
    ],
    "id": 2318173,
    "name:xx": "Enterprise"
  }
}
