{
  "geometry": {
    "type": "Point",
    "coordinates": [
      -111.75,
      40.85
    ]
  },
  "type": "Feature",
  "properties": {
    "hierarchy": [
      "tgn:2259158",
      "tgn:1000001",
      "tgn:7012149",
      "tgn:2002118",
      "tgn:7007827",
      "tgn:7029392"
    ],
    "placetype": [
      "aat:300008761"
    ],
    "id": 2259158,
    "name:xx": "Cottonwood Gulch"
  }
}
