{
  "geometry": {
    "type": "Point",
    "coordinates": [
      143.5667,
      -38.6333
    ]
  },
  "type": "Feature",
  "properties": {
    "hierarchy": [
      "tgn:1096223",
      "tgn:7000490",
      "tgn:1000006",
      "tgn:7006238",
      "tgn:7029392"
    ],
    "placetype": [
      "aat:300008347"
    ],
    "id": 1096223,
    "name:xx": "Beech Forest"
  }
}
