{
  "geometry": {
    "type": "Point",
    "coordinates": [
      74.585,
      16.428
    ]
  },
  "type": "Feature",
  "properties": {
    "hierarchy": [
      "tgn:1074997",
      "tgn:1000004",
      "tgn:7000198",
      "tgn:1001882",
      "tgn:7029392"
    ],
    "placetype": [
      "aat:300008347"
    ],
    "name:en": "Chikodi",
    "id": 1074997
  }
}
