{
  "geometry": {
    "type": "Point",
    "coordinates": [
      25.525,
      58.425
    ]
  },
  "type": "Feature",
  "properties": {
    "hierarchy": [
      "tgn:1058137",
      "tgn:7006644",
      "tgn:1000003",
      "tgn:7006540",
      "tgn:7029392"
    ],
    "placetype": [
      "aat:300008347"
    ],
    "name:en": "Pärsti",
    "id": 1058137
  }
}
