{
  "geometry": {
    "type": "Point",
    "coordinates": [
      -109.8833,
      45.0333
    ]
  },
  "type": "Feature",
  "properties": {
    "hierarchy": [
      "tgn:2241640",
      "tgn:1000001",
      "tgn:7012149",
      "tgn:7029392"
    ],
    "placetype": [
      "aat:300008707"
    ],
    "id": 2241640,
    "name:xx": "Clarks Fork Yellowstone River"
  }
}
