{
  "geometry": {
    "type": "Point",
    "coordinates": [
      78.922895,
      24.915138
    ]
  },
  "type": "Feature",
  "properties": {
    "hierarchy": [
      "tgn:7584838",
      "tgn:1000004",
      "tgn:7000198",
      "tgn:1001894",
      "tgn:7029392"
    ],
    "placetype": [
      "aat:300008699"
    ],
    "name:en": "Sūpa Nāla",
    "id": 7584838
  }
}
