{
  "geometry": {
    "type": "Point",
    "coordinates": [
      -90.8667,
      38.0833
    ]
  },
  "type": "Feature",
  "properties": {
    "hierarchy": [
      "tgn:2242681",
      "tgn:1000001",
      "tgn:7012149",
      "tgn:2001254",
      "tgn:7007523",
      "tgn:7029392"
    ],
    "placetype": [
      "aat:300008706"
    ],
    "id": 2242681,
    "name:xx": "Clear Creek"
  }
}
