{
  "geometry": {
    "type": "Point",
    "coordinates": [
      93.05,
      13.65
    ]
  },
  "type": "Feature",
  "properties": {
    "hierarchy": [
      "tgn:7549238",
      "tgn:1009838",
      "tgn:7000204",
      "tgn:1000004",
      "tgn:7000198",
      "tgn:7029392"
    ],
    "placetype": [
      "aat:300008791"
    ],
    "name:en": "East Island",
    "id": 7549238
  }
}
