{
  "geometry": {
    "type": "Point",
    "coordinates": [
      -87.7375,
      20.925
    ]
  },
  "type": "Feature",
  "properties": {
    "hierarchy": [
      "tgn:7403064",
      "tgn:1000001",
      "tgn:7005600",
      "tgn:7005560",
      "tgn:7029392"
    ],
    "placetype": [
      "aat:300008347"
    ],
    "id": 7403064,
    "name:xx": "San Juan Chen"
  }
}
