{
  "geometry": {
    "type": "Point",
    "coordinates": [
      -77.4833,
      41.7167
    ]
  },
  "type": "Feature",
  "properties": {
    "hierarchy": [
      "tgn:2279479",
      "tgn:1000001",
      "tgn:7012149",
      "tgn:1002945",
      "tgn:7007710",
      "tgn:7029392"
    ],
    "placetype": [
      "aat:300008761"
    ],
    "id": 2279479,
    "name:xx": "Deadman Hollow"
  }
}
