{
  "type": "FeatureCollection",
  "features": [
    {
      "geometry": {
        "type": "Point",
        "coordinates": [
          1.35,
          51.25
        ]
      },
      "type": "Feature",
      "properties": {
        "hierarchy": [
          "tgn:7444540",
          "tgn:7002445",
          "tgn:1000003",
          "tgn:7008153",
          "tgn:7008591",
          "tgn:7029392"
        ],
        "placetype": [
          "aat:300008347"
        ],
        "name:en": "Worth",
        "id": 7444540
      }
    },
    {
      "geometry": {
        "type": "Point",
        "coordinates": [
          -0.133333,
          51.1
        ]
      },
      "type": "Feature",
      "properties": {
        "hierarchy": [
          "tgn:7444541",
          "tgn:7002445",
          "tgn:1000003",
          "tgn:7008134",
          "tgn:7008591",
          "tgn:7029392"
        ],
        "placetype": [
          "aat:300008347"
        ],
        "name:en": "Worth",
        "id": 7444541
      }
    },
    {
      "geometry": {
        "type": "Point",
        "coordinates": [
          -1.466667,
          53.533333
        ]
      },
      "type": "Feature",
      "properties": {
        "hierarchy": [
          "tgn:7444545",
          "tgn:7019048",
          "tgn:7002445",
          "tgn:1000003",
          "tgn:7029505",
          "tgn:7008591",
          "tgn:7029392"
        ],
        "placetype": [
          "aat:300008347"
        ],
        "name:en": "Worsbrough Bridge",
        "id": 7444545
      }
    }
  ]
}
