{
  "geometry": {
    "type": "Point",
    "coordinates": [
      -104.9333,
      42.4667
    ]
  },
  "type": "Feature",
  "properties": {
    "hierarchy": [
      "tgn:1119822",
      "tgn:1000001",
      "tgn:7012149",
      "tgn:7007923",
      "tgn:7029392"
    ],
    "placetype": [
      "aat:300006191"
    ],
    "id": 1119822,
    "name:xx": "Glendo Reservoir"
  }
}
