{
  "geometry": {
    "type": "Point",
    "coordinates": [
      30.441116,
      30.369486
    ]
  },
  "type": "Feature",
  "properties": {
    "hierarchy": [
      "tgn:7539463",
      "tgn:7001242",
      "tgn:1001075",
      "tgn:7016833",
      "tgn:7029392"
    ],
    "placetype": [
      "aat:300386891"
    ],
    "name:en": "Sakrān, Ḩaţīyat as",
    "id": 7539463
  }
}
