{
  "type": "FeatureCollection",
  "features": [
    {
      "geometry": {
        "type": "Point",
        "coordinates": [
          -94.2167,
          30.9833
        ]
      },
      "type": "Feature",
      "properties": {
        "hierarchy": [
          "tgn:2281311",
          "tgn:1000001",
          "tgn:7012149",
          "tgn:2002009",
          "tgn:7007826",
          "tgn:7029392"
        ],
        "placetype": [
          "aat:300008699"
        ],
        "id": 2281311,
        "name:xx": "Deep Slough"
      }
    },
    {
      "geometry": {
        "type": "Point",
        "coordinates": [
          -92,
          32.8167
        ]
      },
      "type": "Feature",
      "properties": {
        "hierarchy": [
          "tgn:2281313",
          "tgn:1000001",
          "tgn:7012149",
          "tgn:2000887",
          "tgn:7007256",
          "tgn:7029392"
        ],
        "placetype": [
          "aat:300006191"
        ],
        "id": 2281313,
        "name:xx": "Deep Slough Pond"
      }
    },
    {
      "geometry": {
        "type": "Point",
        "coordinates": [
          -107.9833,
          39.0167
        ]
      },
      "type": "Feature",
      "properties": {
        "hierarchy": [
          "tgn:2281314",
          "tgn:1000001",
          "tgn:7012149",
          "tgn:2000206",
          "tgn:7007158",
          "tgn:7029392"
        ],
        "placetype": [
          "aat:300006191"
        ],
        "id": 2281314,
        "name:xx": "Deep Slough Reservoir"
      }
    },
    {
      "geometry": {
        "type": "Point",
        "coordinates": [
          -117.95,
          37.7667
        ]
      },
      "type": "Feature",
      "properties": {
        "hierarchy": [
          "tgn:2281317",
          "tgn:1000001",
          "tgn:2001412",
          "tgn:7012149",
          "tgn:7007526",
          "tgn:7029392"
        ],
        "placetype": [
          "aat:300008697"
        ],
        "id": 2281317,
        "name:xx": "Deep Spring"
      }
    },
    {
      "geometry": {
        "type": "Point",
        "coordinates": [
          -118.8833,
          44.6
        ]
      },
      "type": "Feature",
      "properties": {
        "hierarchy": [
          "tgn:2281318",
          "tgn:1000001",
          "tgn:7012149",
          "tgn:2001708",
          "tgn:7007708",
          "tgn:7029392"
        ],
        "placetype": [
          "aat:300008697"
        ],
        "id": 2281318,
        "name:xx": "Deep Spring"
      }
    },
    {
      "geometry": {
        "type": "Point",
        "coordinates": [
          -83.95,
          36.0667
        ]
      },
      "type": "Feature",
      "properties": {
        "hierarchy": [
          "tgn:2281319",
          "tgn:1000001",
          "tgn:7012149",
          "tgn:2001883",
          "tgn:7007825",
          "tgn:7029392"
        ],
        "placetype": [
          "aat:300008697"
        ],
        "id": 2281319,
        "name:xx": "Deep Spring"
      }
    }
  ]
}
