{
  "geometry": {
    "type": "Point",
    "coordinates": [
      -106.3667,
      40.25
    ]
  },
  "type": "Feature",
  "properties": {
    "hierarchy": [
      "tgn:2175651",
      "tgn:1000001",
      "tgn:7012149",
      "tgn:2000216",
      "tgn:7007158",
      "tgn:7029392"
    ],
    "placetype": [
      "aat:300008706"
    ],
    "id": 2175651,
    "name:xx": "Black Creek"
  }
}
