{
  "geometry": {
    "type": "Point",
    "coordinates": [
      -95.3167,
      39.2833
    ]
  },
  "type": "Feature",
  "properties": {
    "hierarchy": [
      "tgn:2328913",
      "tgn:1000001",
      "tgn:2000703",
      "tgn:7012149",
      "tgn:7007254",
      "tgn:7029392"
    ],
    "placetype": [
      "aat:300008706"
    ],
    "id": 2328913,
    "name:xx": "Fishpond Creek"
  }
}
