{
  "geometry": {
    "type": "Point",
    "coordinates": [
      77.816667,
      8.85
    ]
  },
  "type": "Feature",
  "properties": {
    "hierarchy": [
      "tgn:7549129",
      "tgn:1000004",
      "tgn:7000198",
      "tgn:7001797",
      "tgn:7029392"
    ],
    "placetype": [
      "aat:300008699"
    ],
    "name:en": "Chittār River",
    "id": 7549129
  }
}
