{
  "geometry": {
    "type": "Point",
    "coordinates": [
      -105.8333,
      35.6667
    ]
  },
  "type": "Feature",
  "properties": {
    "hierarchy": [
      "tgn:2644536",
      "tgn:1000001",
      "tgn:7012149",
      "tgn:2001454",
      "tgn:7007566",
      "tgn:7029392"
    ],
    "placetype": [
      "aat:300008699"
    ],
    "id": 2644536,
    "name:xx": "Sarca Creek, Agua"
  }
}
