{
  "geometry": {
    "type": "Point",
    "coordinates": [
      -122.9667,
      42.1667
    ]
  },
  "type": "Feature",
  "properties": {
    "hierarchy": [
      "tgn:2197881",
      "tgn:1000001",
      "tgn:7012149",
      "tgn:2001711",
      "tgn:7007708",
      "tgn:7029392"
    ],
    "placetype": [
      "aat:300006191"
    ],
    "id": 2197881,
    "name:xx": "Brown Reservoir"
  }
}
