{
  "type": "FeatureCollection",
  "features": [
    {
      "geometry": {
        "type": "Point",
        "coordinates": [
          16.6833,
          39.15
        ]
      },
      "type": "Feature",
      "properties": {
        "hierarchy": [
          "tgn:1104670",
          "tgn:1003447",
          "tgn:7007850",
          "tgn:1000003",
          "tgn:1000080",
          "tgn:7029392"
        ],
        "placetype": [
          "aat:300008795"
        ],
        "id": 1104670,
        "name:xx": "Gariglione, Monte"
      }
    },
    {
      "geometry": {
        "type": "Point",
        "coordinates": [
          76.55,
          35.6
        ]
      },
      "type": "Feature",
      "properties": {
        "hierarchy": [
          "tgn:1104673",
          "tgn:1000004",
          "tgn:7029392"
        ],
        "placetype": [
          "aat:300008795"
        ],
        "id": 1104673,
        "name:xx": "Gasherbrum"
      }
    },
    {
      "geometry": {
        "type": "Point",
        "coordinates": [
          86.3333,
          27.9167
        ]
      },
      "type": "Feature",
      "properties": {
        "hierarchy": [
          "tgn:1104674",
          "tgn:1000004",
          "tgn:7029392"
        ],
        "placetype": [
          "aat:300008795"
        ],
        "id": 1104674,
        "name:xx": "Gauri Sankar"
      }
    },
    {
      "geometry": {
        "type": "Point",
        "coordinates": [
          -120.8667,
          42.4833
        ]
      },
      "type": "Feature",
      "properties": {
        "hierarchy": [
          "tgn:1104676",
          "tgn:1000001",
          "tgn:7012149",
          "tgn:7007708",
          "tgn:7029392"
        ],
        "placetype": [
          "aat:300008795"
        ],
        "id": 1104676,
        "name:xx": "Gearhart Mountain"
      }
    },
    {
      "geometry": {
        "type": "Point",
        "coordinates": [
          10.266667,
          50.6
        ]
      },
      "type": "Feature",
      "properties": {
        "hierarchy": [
          "tgn:1104677",
          "tgn:1000003",
          "tgn:7003689",
          "tgn:7000084",
          "tgn:7029392"
        ],
        "placetype": [
          "aat:300008777",
          "aat:300008795"
        ],
        "id": 1104677,
        "name:xx": "Gebaberg"
      }
    },
    {
      "geometry": {
        "type": "Point",
        "coordinates": [
          13.583333,
          48.85
        ]
      },
      "type": "Feature",
      "properties": {
        "hierarchy": [
          "tgn:1104679",
          "tgn:7003669",
          "tgn:1000003",
          "tgn:7000084",
          "tgn:7029392"
        ],
        "placetype": [
          "aat:300008777",
          "aat:300008795"
        ],
        "id": 1104679,
        "name:xx": "Geisberg"
      }
    }
  ]
}
