{
  "geometry": {
    "type": "Point",
    "coordinates": [
      -148.5333,
      60.6333
    ]
  },
  "type": "Feature",
  "properties": {
    "hierarchy": [
      "tgn:2606192",
      "tgn:7006450",
      "tgn:1000001",
      "tgn:7012149",
      "tgn:2000086",
      "tgn:7029392"
    ],
    "placetype": [
      "aat:300008835"
    ],
    "id": 2606192,
    "name:xx": "Rainy Glacier"
  }
}
