{
  "geometry": {
    "type": "Point",
    "coordinates": [
      -110.95,
      40.65
    ]
  },
  "type": "Feature",
  "properties": {
    "hierarchy": [
      "tgn:2654865",
      "tgn:1000001",
      "tgn:7012149",
      "tgn:2002122",
      "tgn:7007827",
      "tgn:7029392"
    ],
    "placetype": [
      "aat:300008680"
    ],
    "id": 2654865,
    "name:xx": "Shallow Lake"
  }
}
