{
  "geometry": {
    "type": "Point",
    "coordinates": [
      -124.0667,
      40.0167
    ]
  },
  "type": "Feature",
  "properties": {
    "hierarchy": [
      "tgn:2014236",
      "tgn:1000001",
      "tgn:7012149",
      "tgn:2000181",
      "tgn:7007157",
      "tgn:7029392"
    ],
    "placetype": [
      "aat:300008347"
    ],
    "id": 2014236,
    "name:xx": "Shelter Cove"
  }
}
