{
  "geometry": {
    "type": "Point",
    "coordinates": [
      -106.6167,
      36.0167
    ]
  },
  "type": "Feature",
  "properties": {
    "hierarchy": [
      "tgn:2246831",
      "tgn:1000001",
      "tgn:7012149",
      "tgn:2001449",
      "tgn:7007566",
      "tgn:7029392"
    ],
    "placetype": [
      "aat:300008697"
    ],
    "id": 2246831,
    "name:xx": "Cochina Spring"
  }
}
