{
  "geometry": {
    "type": "Point",
    "coordinates": [
      -81.2667,
      37.9833
    ]
  },
  "type": "Feature",
  "properties": {
    "hierarchy": [
      "tgn:2455357",
      "tgn:1000001",
      "tgn:2002261",
      "tgn:7012149",
      "tgn:7013961",
      "tgn:7029392"
    ],
    "placetype": [
      "aat:300008699"
    ],
    "id": 2455357,
    "name:xx": "Little Fork"
  }
}
