{
  "geometry": {
    "type": "Point",
    "coordinates": [
      -112.55,
      42.5667
    ]
  },
  "type": "Feature",
  "properties": {
    "hierarchy": [
      "tgn:2571451",
      "tgn:1000001",
      "tgn:7012149",
      "tgn:2000490",
      "tgn:7007250",
      "tgn:7029392"
    ],
    "placetype": [
      "aat:300008347"
    ],
    "id": 2571451,
    "name:xx": "Pauline"
  }
}
