{
  "geometry": {
    "type": "Point",
    "coordinates": [
      -85.8833,
      43.4833
    ]
  },
  "type": "Feature",
  "properties": {
    "hierarchy": [
      "tgn:2573628",
      "tgn:1000001",
      "tgn:7012149",
      "tgn:2000983",
      "tgn:7007520",
      "tgn:7029392"
    ],
    "placetype": [
      "aat:300008680"
    ],
    "id": 2573628,
    "name:xx": "Peck Lake"
  }
}
