{
  "geometry": {
    "type": "Point",
    "coordinates": [
      -85.1333,
      37.45
    ]
  },
  "type": "Feature",
  "properties": {
    "hierarchy": [
      "tgn:2557295",
      "tgn:1000001",
      "tgn:7012149",
      "tgn:2000822",
      "tgn:7007255",
      "tgn:7029392"
    ],
    "placetype": [
      "aat:300008706"
    ],
    "id": 2557295,
    "name:xx": "Old Lick Creek"
  }
}
