{
  "geometry": {
    "type": "Point",
    "coordinates": [
      -78.7667,
      38.0667
    ]
  },
  "type": "Feature",
  "properties": {
    "hierarchy": [
      "tgn:2214790",
      "tgn:1000001",
      "tgn:7012149",
      "tgn:7007919",
      "tgn:7029392"
    ],
    "placetype": [
      "aat:300008798"
    ],
    "id": 2214790,
    "name:xx": "Calf Mountain"
  }
}
