{
  "geometry": {
    "type": "Point",
    "coordinates": [
      -78.6167,
      38.9667
    ]
  },
  "type": "Feature",
  "properties": {
    "hierarchy": [
      "tgn:2513508",
      "tgn:1000001",
      "tgn:7012149",
      "tgn:7029392"
    ],
    "placetype": [
      "aat:300008798"
    ],
    "id": 2513508,
    "name:xx": "Mill Mountain"
  }
}
