{
  "type": "FeatureCollection",
  "features": [
    {
      "geometry": {
        "type": "Point",
        "coordinates": [
          -80.5833,
          35.65
        ]
      },
      "type": "Feature",
      "properties": {
        "hierarchy": [
          "tgn:2294640",
          "tgn:1000001",
          "tgn:7012149",
          "tgn:2001536",
          "tgn:7007709",
          "tgn:7029392"
        ],
        "placetype": [
          "aat:300008699"
        ],
        "id": 2294640,
        "name:xx": "Draft Branch"
      }
    },
    {
      "geometry": {
        "type": "Point",
        "coordinates": [
          -80.7167,
          33.8167
        ]
      },
      "type": "Feature",
      "properties": {
        "hierarchy": [
          "tgn:2294641",
          "tgn:1000001",
          "tgn:7012149",
          "tgn:2001764",
          "tgn:7007712",
          "tgn:7029392"
        ],
        "placetype": [
          "aat:300006191"
        ],
        "id": 2294641,
        "name:xx": "Drafts Pond"
      }
    },
    {
      "geometry": {
        "type": "Point",
        "coordinates": [
          -107.85,
          34.2
        ]
      },
      "type": "Feature",
      "properties": {
        "hierarchy": [
          "tgn:2294642",
          "tgn:1000001",
          "tgn:2001429",
          "tgn:7012149",
          "tgn:7007566",
          "tgn:7029392"
        ],
        "placetype": [
          "aat:300008697"
        ],
        "id": 2294642,
        "name:xx": "Drag A Spring"
      }
    },
    {
      "geometry": {
        "type": "Point",
        "coordinates": [
          -68.05,
          45.05
        ]
      },
      "type": "Feature",
      "properties": {
        "hierarchy": [
          "tgn:2294643",
          "tgn:1000001",
          "tgn:2000922",
          "tgn:7012149",
          "tgn:7007515",
          "tgn:7029392"
        ],
        "placetype": [
          "aat:300008699"
        ],
        "id": 2294643,
        "name:xx": "Drag Brook"
      }
    },
    {
      "geometry": {
        "type": "Point",
        "coordinates": [
          -108.2167,
          47.4
        ]
      },
      "type": "Feature",
      "properties": {
        "hierarchy": [
          "tgn:2294644",
          "tgn:1000001",
          "tgn:7012149",
          "tgn:7007524",
          "tgn:7029392"
        ],
        "placetype": [
          "aat:300008706"
        ],
        "id": 2294644,
        "name:xx": "Drag Creek"
      }
    },
    {
      "geometry": {
        "type": "Point",
        "coordinates": [
          -79.8,
          36.5667
        ]
      },
      "type": "Feature",
      "properties": {
        "hierarchy": [
          "tgn:2294645",
          "tgn:1000001",
          "tgn:7012149",
          "tgn:2002167",
          "tgn:7007919",
          "tgn:7029392"
        ],
        "placetype": [
          "aat:300008706"
        ],
        "id": 2294645,
        "name:xx": "Drag Creek"
      }
    },
    {
      "geometry": {
        "type": "Point",
        "coordinates": [
          -82.4,
          37.95
        ]
      },
      "type": "Feature",
      "properties": {
        "hierarchy": [
          "tgn:2294646",
          "tgn:1000001",
          "tgn:7012149",
          "tgn:2002299",
          "tgn:7013961",
          "tgn:7029392"
        ],
        "placetype": [
          "aat:300008706"
        ],
        "id": 2294646,
        "name:xx": "Drag Creek"
      }
    },
    {
      "geometry": {
        "type": "Point",
        "coordinates": [
          -74.2,
          41.0833
        ]
      },
      "type": "Feature",
      "properties": {
        "hierarchy": [
          "tgn:2294647",
          "tgn:1002178",
          "tgn:1000001",
          "tgn:7012149",
          "tgn:7007565",
          "tgn:7029392"
        ],
        "placetype": [
          "aat:300008798"
        ],
        "id": 2294647,
        "name:xx": "Drag Hill"
      }
    },
    {
      "geometry": {
        "type": "Point",
        "coordinates": [
          -112.55,
          38.25
        ]
      },
      "type": "Feature",
      "properties": {
        "hierarchy": [
          "tgn:2294648",
          "tgn:2002101",
          "tgn:1000001",
          "tgn:7012149",
          "tgn:7007827",
          "tgn:7029392"
        ],
        "placetype": [
          "aat:300008761"
        ],
        "id": 2294648,
        "name:xx": "Drag Hollow"
      }
    },
    {
      "geometry": {
        "type": "Point",
        "coordinates": [
          -112.55,
          38.4
        ]
      },
      "type": "Feature",
      "properties": {
        "hierarchy": [
          "tgn:2294649",
          "tgn:2002101",
          "tgn:1000001",
          "tgn:7012149",
          "tgn:7007827",
          "tgn:7029392"
        ],
        "placetype": [
          "aat:300008697"
        ],
        "id": 2294649,
        "name:xx": "Drag Hollow Spring"
      }
    }
  ]
}
