{
  "geometry": {
    "type": "Point",
    "coordinates": [
      -81.95,
      37.8333
    ]
  },
  "type": "Feature",
  "properties": {
    "hierarchy": [
      "tgn:2120076",
      "tgn:1000001",
      "tgn:7012149",
      "tgn:2002273",
      "tgn:7013961",
      "tgn:7029392"
    ],
    "placetype": [
      "aat:300008347"
    ],
    "id": 2120076,
    "name:xx": "Stollings"
  }
}
