{
  "geometry": {
    "type": "Point",
    "coordinates": [
      -111.4667,
      41.9167
    ]
  },
  "type": "Feature",
  "properties": {
    "hierarchy": [
      "tgn:2557296",
      "tgn:1000001",
      "tgn:7012149",
      "tgn:2002117",
      "tgn:7007827",
      "tgn:7029392"
    ],
    "placetype": [
      "aat:300008347"
    ],
    "id": 2557296,
    "name:xx": "Old Limber Pine"
  }
}
