{
  "type": "FeatureCollection",
  "features": [
    {
      "geometry": {
        "type": "Point",
        "coordinates": [
          4.083333,
          50.65
        ]
      },
      "type": "Feature",
      "properties": {
        "hierarchy": [
          "tgn:7250230",
          "tgn:7007877",
          "tgn:1000003",
          "tgn:1000063",
          "tgn:4012014",
          "tgn:7029392"
        ],
        "placetype": [
          "aat:300000206"
        ],
        "id": 7250230,
        "name:xx": "Prés"
      }
    },
    {
      "geometry": {
        "type": "Point",
        "coordinates": [
          3.70768,
          50.731489
        ]
      },
      "type": "Feature",
      "properties": {
        "hierarchy": [
          "tgn:7250231",
          "tgn:7007877",
          "tgn:1000003",
          "tgn:1000063",
          "tgn:4012014",
          "tgn:7029392"
        ],
        "placetype": [
          "aat:300008347"
        ],
        "id": 7250231,
        "name:xx": "Paradis"
      }
    },
    {
      "geometry": {
        "type": "Point",
        "coordinates": [
          4.366667,
          50.683333
        ]
      },
      "type": "Feature",
      "properties": {
        "hierarchy": [
          "tgn:7250232",
          "tgn:7007877",
          "tgn:1000003",
          "tgn:1000063",
          "tgn:4012014",
          "tgn:7029392"
        ],
        "placetype": [
          "aat:300008347"
        ],
        "id": 7250232,
        "name:xx": "Paradis"
      }
    },
    {
      "geometry": {
        "type": "Point",
        "coordinates": [
          3.356167,
          50.645263
        ]
      },
      "type": "Feature",
      "properties": {
        "hierarchy": [
          "tgn:7250233",
          "tgn:7007877",
          "tgn:1000003",
          "tgn:1000063",
          "tgn:4012014",
          "tgn:7029392"
        ],
        "placetype": [
          "aat:300008347"
        ],
        "id": 7250233,
        "name:xx": "Paradis"
      }
    },
    {
      "geometry": {
        "type": "Point",
        "coordinates": [
          5.683333,
          50.416667
        ]
      },
      "type": "Feature",
      "properties": {
        "hierarchy": [
          "tgn:7250234",
          "tgn:7003460",
          "tgn:1000003",
          "tgn:1000063",
          "tgn:4012014",
          "tgn:7029392"
        ],
        "placetype": [
          "aat:300008347"
        ],
        "id": 7250234,
        "name:xx": "Paradis"
      }
    },
    {
      "geometry": {
        "type": "Point",
        "coordinates": [
          5.12353,
          50.32096
        ]
      },
      "type": "Feature",
      "properties": {
        "hierarchy": [
          "tgn:7250235",
          "tgn:7003466",
          "tgn:1000003",
          "tgn:1000063",
          "tgn:4012014",
          "tgn:7029392"
        ],
        "placetype": [
          "aat:300008347"
        ],
        "id": 7250235,
        "name:xx": "Paradis"
      }
    },
    {
      "geometry": {
        "type": "Point",
        "coordinates": [
          5.483333,
          50.133333
        ]
      },
      "type": "Feature",
      "properties": {
        "hierarchy": [
          "tgn:7250236",
          "tgn:7003465",
          "tgn:1000003",
          "tgn:1000063",
          "tgn:4012014",
          "tgn:7029392"
        ],
        "placetype": [
          "aat:300008347"
        ],
        "id": 7250236,
        "name:xx": "Paradis"
      }
    },
    {
      "geometry": {
        "type": "Point",
        "coordinates": [
          4.1,
          51.15
        ]
      },
      "type": "Feature",
      "properties": {
        "hierarchy": [
          "tgn:7250237",
          "tgn:7003457",
          "tgn:1000003",
          "tgn:1000063",
          "tgn:7018236",
          "tgn:7029392"
        ],
        "placetype": [
          "aat:300008347"
        ],
        "id": 7250237,
        "name:xx": "Paradijs"
      }
    },
    {
      "geometry": {
        "type": "Point",
        "coordinates": [
          5.616667,
          50.583333
        ]
      },
      "type": "Feature",
      "properties": {
        "hierarchy": [
          "tgn:7250238",
          "tgn:7003460",
          "tgn:1000003",
          "tgn:1000063",
          "tgn:4012014",
          "tgn:7029392"
        ],
        "placetype": [
          "aat:300008863"
        ],
        "id": 7250238,
        "name:xx": "Oblusteine, Bois d'"
      }
    },
    {
      "geometry": {
        "type": "Point",
        "coordinates": [
          3.364121,
          50.661841
        ]
      },
      "type": "Feature",
      "properties": {
        "hierarchy": [
          "tgn:7250239",
          "tgn:7007877",
          "tgn:1000003",
          "tgn:1000063",
          "tgn:4012014",
          "tgn:7029392"
        ],
        "placetype": [
          "aat:300008347"
        ],
        "id": 7250239,
        "name:xx": "Obigies"
      }
    }
  ]
}
