{
  "geometry": {
    "type": "Point",
    "coordinates": [
      -100.1667,
      42.9667
    ]
  },
  "type": "Feature",
  "properties": {
    "hierarchy": [
      "tgn:2654075",
      "tgn:1000001",
      "tgn:7012149",
      "tgn:7029392"
    ],
    "placetype": [
      "aat:300008706"
    ],
    "id": 2654075,
    "name:xx": "Shadley Creek"
  }
}
