{
  "type": "FeatureCollection",
  "features": [
    {
      "geometry": {
        "type": "Point",
        "coordinates": [
          0.066667,
          38.85
        ]
      },
      "type": "Feature",
      "properties": {
        "hierarchy": [
          "tgn:7305090",
          "tgn:7002804",
          "tgn:1000003",
          "tgn:7002793",
          "tgn:1000095",
          "tgn:7029392"
        ],
        "placetype": [
          "aat:300008347"
        ],
        "id": 7305090,
        "name:xx": "Las Bovetes"
      }
    },
    {
      "geometry": {
        "type": "Point",
        "coordinates": [
          -0.8,
          38.083333
        ]
      },
      "type": "Feature",
      "properties": {
        "hierarchy": [
          "tgn:7305091",
          "tgn:7002804",
          "tgn:1000003",
          "tgn:7002793",
          "tgn:1000095",
          "tgn:7029392"
        ],
        "placetype": [
          "aat:300008347"
        ],
        "id": 7305091,
        "name:xx": "Las Bóvedas"
      }
    },
    {
      "geometry": {
        "type": "Point",
        "coordinates": [
          -9,
          42.9
        ]
      },
      "type": "Feature",
      "properties": {
        "hierarchy": [
          "tgn:7305092",
          "tgn:7002824",
          "tgn:1000003",
          "tgn:7002786",
          "tgn:1000095",
          "tgn:7029392"
        ],
        "placetype": [
          "aat:300008347"
        ],
        "id": 7305092,
        "name:xx": "Las Bouzas"
      }
    },
    {
      "geometry": {
        "type": "Point",
        "coordinates": [
          -13.9,
          28.266667
        ]
      },
      "type": "Feature",
      "properties": {
        "hierarchy": [
          "tgn:7305093",
          "tgn:7002825",
          "tgn:7016622",
          "tgn:1000003",
          "tgn:1000095",
          "tgn:7029392"
        ],
        "placetype": [
          "aat:300386846"
        ],
        "id": 7305093,
        "name:xx": "Las Borriquillas, Punta"
      }
    },
    {
      "geometry": {
        "type": "Point",
        "coordinates": [
          0.717707,
          42.737908
        ]
      },
      "type": "Feature",
      "properties": {
        "hierarchy": [
          "tgn:7305094",
          "tgn:7008912",
          "tgn:7030216",
          "tgn:1000003",
          "tgn:1000095",
          "tgn:7029392"
        ],
        "placetype": [
          "aat:300008347"
        ],
        "id": 7305094,
        "name:xx": "Las Bordas"
      }
    },
    {
      "geometry": {
        "type": "Point",
        "coordinates": [
          0.85,
          42.2
        ]
      },
      "type": "Feature",
      "properties": {
        "hierarchy": [
          "tgn:7305095",
          "tgn:7008912",
          "tgn:7030216",
          "tgn:1000003",
          "tgn:1000095",
          "tgn:7029392"
        ],
        "placetype": [
          "aat:300008347"
        ],
        "id": 7305095,
        "name:xx": "Las Bordas"
      }
    },
    {
      "geometry": {
        "type": "Point",
        "coordinates": [
          -1.8,
          37.25
        ]
      },
      "type": "Feature",
      "properties": {
        "hierarchy": [
          "tgn:7305096",
          "tgn:7002805",
          "tgn:7002758",
          "tgn:1000003",
          "tgn:1000095",
          "tgn:7029392"
        ],
        "placetype": [
          "aat:300008347"
        ],
        "id": 7305096,
        "name:xx": "Las Bombardas"
      }
    },
    {
      "geometry": {
        "type": "Point",
        "coordinates": [
          -5.3,
          42.85
        ]
      },
      "type": "Feature",
      "properties": {
        "hierarchy": [
          "tgn:7305097",
          "tgn:7002826",
          "tgn:7001158",
          "tgn:1000003",
          "tgn:1000095",
          "tgn:7029392"
        ],
        "placetype": [
          "aat:300008347"
        ],
        "id": 7305097,
        "name:xx": "Las Bodas"
      }
    },
    {
      "geometry": {
        "type": "Point",
        "coordinates": [
          -4.166667,
          39.216667
        ]
      },
      "type": "Feature",
      "properties": {
        "hierarchy": [
          "tgn:7305098",
          "tgn:7002816",
          "tgn:1001647",
          "tgn:1000003",
          "tgn:1000095",
          "tgn:7029392"
        ],
        "placetype": [
          "aat:300008347"
        ],
        "id": 7305098,
        "name:xx": "Las Betetas"
      }
    },
    {
      "geometry": {
        "type": "Point",
        "coordinates": [
          -6.133333,
          40.066667
        ]
      },
      "type": "Feature",
      "properties": {
        "hierarchy": [
          "tgn:7305099",
          "tgn:7002811",
          "tgn:1000003",
          "tgn:7003837",
          "tgn:1000095",
          "tgn:7029392"
        ],
        "placetype": [
          "aat:300008347"
        ],
        "id": 7305099,
        "name:xx": "Las Berrozanas"
      }
    }
  ]
}
