{
  "geometry": {
    "type": "Point",
    "coordinates": [
      -77.15,
      37.6667
    ]
  },
  "type": "Feature",
  "properties": {
    "hierarchy": [
      "tgn:2272047",
      "tgn:1000001",
      "tgn:7012149",
      "tgn:1002548",
      "tgn:7007919",
      "tgn:7029392"
    ],
    "placetype": [
      "aat:300006191"
    ],
    "id": 2272047,
    "name:xx": "Curling Pond"
  }
}
