{
  "geometry": {
    "type": "Point",
    "coordinates": [
      -84.75,
      45.25
    ]
  },
  "type": "Feature",
  "properties": {
    "hierarchy": [
      "tgn:2232246",
      "tgn:1000001",
      "tgn:2000950",
      "tgn:7012149",
      "tgn:7007520",
      "tgn:7029392"
    ],
    "placetype": [
      "aat:300008798"
    ],
    "id": 2232246,
    "name:xx": "Chandler Hill"
  }
}
