{
  "type": "FeatureCollection",
  "features": [
    {
      "geometry": {
        "type": "Point",
        "coordinates": [
          -109.7667,
          38.15
        ]
      },
      "type": "Feature",
      "properties": {
        "hierarchy": [
          "tgn:2689200",
          "tgn:1000001",
          "tgn:7012149",
          "tgn:2002119",
          "tgn:7007827",
          "tgn:7029392"
        ],
        "placetype": [
          "aat:300008798"
        ],
        "id": 2689200,
        "name:xx": "Squaw Butte"
      }
    },
    {
      "geometry": {
        "type": "Point",
        "coordinates": [
          -122.2667,
          45.7667
        ]
      },
      "type": "Feature",
      "properties": {
        "hierarchy": [
          "tgn:2689201",
          "tgn:1000001",
          "tgn:1002275",
          "tgn:7012149",
          "tgn:7007920",
          "tgn:7029392"
        ],
        "placetype": [
          "aat:300008798"
        ],
        "id": 2689201,
        "name:xx": "Squaw Butte"
      }
    },
    {
      "geometry": {
        "type": "Point",
        "coordinates": [
          -121.8,
          46.1167
        ]
      },
      "type": "Feature",
      "properties": {
        "hierarchy": [
          "tgn:2689202",
          "tgn:1000001",
          "tgn:7012149",
          "tgn:1002897",
          "tgn:7007920",
          "tgn:7029392"
        ],
        "placetype": [
          "aat:300008798"
        ],
        "id": 2689202,
        "name:xx": "Squaw Butte"
      }
    },
    {
      "geometry": {
        "type": "Point",
        "coordinates": [
          -107.8167,
          43.05
        ]
      },
      "type": "Feature",
      "properties": {
        "hierarchy": [
          "tgn:2689203",
          "tgn:1000001",
          "tgn:7012149",
          "tgn:2002371",
          "tgn:7007923",
          "tgn:7029392"
        ],
        "placetype": [
          "aat:300008798"
        ],
        "id": 2689203,
        "name:xx": "Squaw Butte"
      }
    },
    {
      "geometry": {
        "type": "Point",
        "coordinates": [
          -105.2333,
          44.7833
        ]
      },
      "type": "Feature",
      "properties": {
        "hierarchy": [
          "tgn:2689204",
          "tgn:1000001",
          "tgn:2002367",
          "tgn:7012149",
          "tgn:7007923",
          "tgn:7029392"
        ],
        "placetype": [
          "aat:300008798"
        ],
        "id": 2689204,
        "name:xx": "Squaw Butte"
      }
    },
    {
      "geometry": {
        "type": "Point",
        "coordinates": [
          -106.2167,
          44.8833
        ]
      },
      "type": "Feature",
      "properties": {
        "hierarchy": [
          "tgn:2689205",
          "tgn:1000001",
          "tgn:7012149",
          "tgn:2002381",
          "tgn:7007923",
          "tgn:7029392"
        ],
        "placetype": [
          "aat:300008798"
        ],
        "id": 2689205,
        "name:xx": "Squaw Butte"
      }
    },
    {
      "geometry": {
        "type": "Point",
        "coordinates": [
          -120.25,
          42.2667
        ]
      },
      "type": "Feature",
      "properties": {
        "hierarchy": [
          "tgn:2689206",
          "tgn:1000001",
          "tgn:7012149",
          "tgn:2001715",
          "tgn:7007708",
          "tgn:7029392"
        ],
        "placetype": [
          "aat:300008706"
        ],
        "id": 2689206,
        "name:xx": "Squaw Butte Creek"
      }
    },
    {
      "geometry": {
        "type": "Point",
        "coordinates": [
          -112.4833,
          48.5333
        ]
      },
      "type": "Feature",
      "properties": {
        "hierarchy": [
          "tgn:2689207",
          "tgn:1000001",
          "tgn:7012149",
          "tgn:2001277",
          "tgn:7007524",
          "tgn:7029392"
        ],
        "placetype": [
          "aat:300008697"
        ],
        "id": 2689207,
        "name:xx": "Squaw Buttes"
      }
    },
    {
      "geometry": {
        "type": "Point",
        "coordinates": [
          -102.7167,
          44.9
        ]
      },
      "type": "Feature",
      "properties": {
        "hierarchy": [
          "tgn:2689208",
          "tgn:1000001",
          "tgn:2001816",
          "tgn:7012149",
          "tgn:7007713",
          "tgn:7029392"
        ],
        "placetype": [
          "aat:300008798"
        ],
        "id": 2689208,
        "name:xx": "Squaw Buttes"
      }
    },
    {
      "geometry": {
        "type": "Point",
        "coordinates": [
          -104.5333,
          44.8
        ]
      },
      "type": "Feature",
      "properties": {
        "hierarchy": [
          "tgn:2689209",
          "tgn:1000001",
          "tgn:2002370",
          "tgn:7012149",
          "tgn:7007923",
          "tgn:7029392"
        ],
        "placetype": [
          "aat:300008798"
        ],
        "id": 2689209,
        "name:xx": "Squaw Buttes"
      }
    }
  ]
}
