{
  "geometry": {
    "type": "Point",
    "coordinates": [
      -98.2333,
      39.05
    ]
  },
  "type": "Feature",
  "properties": {
    "hierarchy": [
      "tgn:2036428",
      "tgn:1000001",
      "tgn:7012149",
      "tgn:2000712",
      "tgn:7007254",
      "tgn:7029392"
    ],
    "placetype": [
      "aat:300387016"
    ],
    "id": 2036428,
    "name:xx": "Goldenrod"
  }
}
