{
  "geometry": {
    "type": "Point",
    "coordinates": [
      -70.35,
      41.6333
    ]
  },
  "type": "Feature",
  "properties": {
    "hierarchy": [
      "tgn:2249483",
      "tgn:1002165",
      "tgn:1000001",
      "tgn:7012149",
      "tgn:7007517",
      "tgn:7029392"
    ],
    "placetype": [
      "aat:300008680"
    ],
    "id": 2249483,
    "name:xx": "Coleman Pond"
  }
}
