{
  "geometry": {
    "type": "Point",
    "coordinates": [
      -75.4167,
      41.9333
    ]
  },
  "type": "Feature",
  "properties": {
    "hierarchy": [
      "tgn:2658756",
      "tgn:1000001",
      "tgn:7012149",
      "tgn:7029392"
    ],
    "placetype": [
      "aat:300008706"
    ],
    "id": 2658756,
    "name:xx": "Sherman Creek"
  }
}
