{
  "geometry": {
    "type": "Point",
    "coordinates": [
      -161.6833,
      66.7333
    ]
  },
  "type": "Feature",
  "properties": {
    "hierarchy": [
      "tgn:2446588",
      "tgn:7006450",
      "tgn:1000001",
      "tgn:7012149",
      "tgn:2124014",
      "tgn:7029392"
    ],
    "placetype": [
      "aat:300008699"
    ],
    "id": 2446588,
    "name:xx": "Lewis Rich Channel"
  }
}
