{
  "type": "FeatureCollection",
  "features": [
    {
      "geometry": {
        "type": "Point",
        "coordinates": [
          12.066667,
          48.583333
        ]
      },
      "type": "Feature",
      "properties": {
        "hierarchy": [
          "tgn:7160160",
          "tgn:7003669",
          "tgn:1000003",
          "tgn:7000084",
          "tgn:7029392"
        ],
        "placetype": [
          "aat:300000206"
        ],
        "id": 7160160,
        "name:xx": "Höfen"
      }
    },
    {
      "geometry": {
        "type": "Point",
        "coordinates": [
          12.733333,
          48.55
        ]
      },
      "type": "Feature",
      "properties": {
        "hierarchy": [
          "tgn:7160161",
          "tgn:7003669",
          "tgn:1000003",
          "tgn:7000084",
          "tgn:7029392"
        ],
        "placetype": [
          "aat:300000206"
        ],
        "id": 7160161,
        "name:xx": "Höfen"
      }
    },
    {
      "geometry": {
        "type": "Point",
        "coordinates": [
          12.883333,
          47.95
        ]
      },
      "type": "Feature",
      "properties": {
        "hierarchy": [
          "tgn:7160162",
          "tgn:7003669",
          "tgn:1000003",
          "tgn:7000084",
          "tgn:7029392"
        ],
        "placetype": [
          "aat:300000206"
        ],
        "id": 7160162,
        "name:xx": "Höfen"
      }
    },
    {
      "geometry": {
        "type": "Point",
        "coordinates": [
          12.65,
          47.85
        ]
      },
      "type": "Feature",
      "properties": {
        "hierarchy": [
          "tgn:7160163",
          "tgn:7003669",
          "tgn:1000003",
          "tgn:7000084",
          "tgn:7029392"
        ],
        "placetype": [
          "aat:300000206"
        ],
        "id": 7160163,
        "name:xx": "Höfen"
      }
    },
    {
      "geometry": {
        "type": "Point",
        "coordinates": [
          10.35,
          47.816667
        ]
      },
      "type": "Feature",
      "properties": {
        "hierarchy": [
          "tgn:7160164",
          "tgn:7003669",
          "tgn:1000003",
          "tgn:7000084",
          "tgn:7029392"
        ],
        "placetype": [
          "aat:300000206"
        ],
        "id": 7160164,
        "name:xx": "Höfen"
      }
    },
    {
      "geometry": {
        "type": "Point",
        "coordinates": [
          9.833333,
          47.733333
        ]
      },
      "type": "Feature",
      "properties": {
        "hierarchy": [
          "tgn:7160165",
          "tgn:7003692",
          "tgn:1000003",
          "tgn:7000084",
          "tgn:7029392"
        ],
        "placetype": [
          "aat:300000206"
        ],
        "id": 7160165,
        "name:xx": "Höfen"
      }
    },
    {
      "geometry": {
        "type": "Point",
        "coordinates": [
          9.416667,
          47.683333
        ]
      },
      "type": "Feature",
      "properties": {
        "hierarchy": [
          "tgn:7160166",
          "tgn:7003692",
          "tgn:1000003",
          "tgn:7000084",
          "tgn:7029392"
        ],
        "placetype": [
          "aat:300000206"
        ],
        "id": 7160166,
        "name:xx": "Hofen"
      }
    },
    {
      "geometry": {
        "type": "Point",
        "coordinates": [
          9.816667,
          48.15
        ]
      },
      "type": "Feature",
      "properties": {
        "hierarchy": [
          "tgn:7160167",
          "tgn:7003692",
          "tgn:1000003",
          "tgn:7000084",
          "tgn:7029392"
        ],
        "placetype": [
          "aat:300387173"
        ],
        "id": 7160167,
        "name:xx": "Höfen"
      }
    },
    {
      "geometry": {
        "type": "Point",
        "coordinates": [
          11.133333,
          48.733333
        ]
      },
      "type": "Feature",
      "properties": {
        "hierarchy": [
          "tgn:7160168",
          "tgn:7003669",
          "tgn:1000003",
          "tgn:7000084",
          "tgn:7029392"
        ],
        "placetype": [
          "aat:300000206"
        ],
        "id": 7160168,
        "name:xx": "Höfelhof"
      }
    },
    {
      "geometry": {
        "type": "Point",
        "coordinates": [
          9.483333,
          52.25
        ]
      },
      "type": "Feature",
      "properties": {
        "hierarchy": [
          "tgn:7160169",
          "tgn:1000003",
          "tgn:7003676",
          "tgn:7000084",
          "tgn:7029392"
        ],
        "placetype": [
          "aat:300008777"
        ],
        "id": 7160169,
        "name:xx": "Höfeler"
      }
    }
  ]
}
