{
  "geometry": {
    "type": "Point",
    "coordinates": [
      -111.75,
      40.8833
    ]
  },
  "type": "Feature",
  "properties": {
    "hierarchy": [
      "tgn:2394777",
      "tgn:1000001",
      "tgn:2002106",
      "tgn:7012149",
      "tgn:7007827",
      "tgn:7029392"
    ],
    "placetype": [
      "aat:300008761"
    ],
    "id": 2394777,
    "name:xx": "Holbrook Canyon"
  }
}
