{
  "geometry": {
    "type": "Point",
    "coordinates": [
      -88.8833,
      36.9833
    ]
  },
  "type": "Feature",
  "properties": {
    "hierarchy": [
      "tgn:2406231",
      "tgn:2000767",
      "tgn:1000001",
      "tgn:7012149",
      "tgn:7007255",
      "tgn:7029392"
    ],
    "placetype": [
      "aat:300008706"
    ],
    "id": 2406231,
    "name:xx": "Humphrey Creek"
  }
}
