{
  "geometry": {
    "type": "Point",
    "coordinates": [
      -77.2833,
      37.85
    ]
  },
  "type": "Feature",
  "properties": {
    "hierarchy": [
      "tgn:2311103",
      "tgn:1000001",
      "tgn:1002235",
      "tgn:7012149",
      "tgn:7007919",
      "tgn:7029392"
    ],
    "placetype": [
      "aat:300008347"
    ],
    "id": 2311103,
    "name:xx": "Edgar"
  }
}
