{
  "type": "FeatureCollection",
  "features": [
    {
      "geometry": {
        "type": "Point",
        "coordinates": [
          -92.7667,
          36.2167
        ]
      },
      "type": "Feature",
      "properties": {
        "hierarchy": [
          "tgn:2568860",
          "tgn:1000001",
          "tgn:7016172",
          "tgn:7012149",
          "tgn:2000149",
          "tgn:7029392"
        ],
        "placetype": [
          "aat:300008761"
        ],
        "id": 2568860,
        "name:xx": "Parker Hollow"
      }
    },
    {
      "geometry": {
        "type": "Point",
        "coordinates": [
          -91.6,
          37.4833
        ]
      },
      "type": "Feature",
      "properties": {
        "hierarchy": [
          "tgn:2568861",
          "tgn:1000001",
          "tgn:7012149",
          "tgn:2001195",
          "tgn:7007523",
          "tgn:7029392"
        ],
        "placetype": [
          "aat:300008761"
        ],
        "id": 2568861,
        "name:xx": "Parker Hollow"
      }
    },
    {
      "geometry": {
        "type": "Point",
        "coordinates": [
          -91.9333,
          38.0833
        ]
      },
      "type": "Feature",
      "properties": {
        "hierarchy": [
          "tgn:2568862",
          "tgn:1000001",
          "tgn:7012149",
          "tgn:1002629",
          "tgn:7007523",
          "tgn:7029392"
        ],
        "placetype": [
          "aat:300008761"
        ],
        "id": 2568862,
        "name:xx": "Parker Hollow"
      }
    },
    {
      "geometry": {
        "type": "Point",
        "coordinates": [
          -94.7667,
          39.2
        ]
      },
      "type": "Feature",
      "properties": {
        "hierarchy": [
          "tgn:2568863",
          "tgn:1000001",
          "tgn:7012149",
          "tgn:2001231",
          "tgn:7007523",
          "tgn:7029392"
        ],
        "placetype": [
          "aat:300008761"
        ],
        "id": 2568863,
        "name:xx": "Parker Hollow"
      }
    },
    {
      "geometry": {
        "type": "Point",
        "coordinates": [
          -91.45,
          37.4
        ]
      },
      "type": "Feature",
      "properties": {
        "hierarchy": [
          "tgn:2568864",
          "tgn:1000001",
          "tgn:7012149",
          "tgn:2001247",
          "tgn:7007523",
          "tgn:7029392"
        ],
        "placetype": [
          "aat:300008761"
        ],
        "id": 2568864,
        "name:xx": "Parker Hollow"
      }
    },
    {
      "geometry": {
        "type": "Point",
        "coordinates": [
          -91.2333,
          37.5833
        ]
      },
      "type": "Feature",
      "properties": {
        "hierarchy": [
          "tgn:2568865",
          "tgn:1000001",
          "tgn:7012149",
          "tgn:2001236",
          "tgn:7007523",
          "tgn:7029392"
        ],
        "placetype": [
          "aat:300008761"
        ],
        "id": 2568865,
        "name:xx": "Parker Hollow"
      }
    },
    {
      "geometry": {
        "type": "Point",
        "coordinates": [
          -75.3333,
          42.2667
        ]
      },
      "type": "Feature",
      "properties": {
        "hierarchy": [
          "tgn:2568866",
          "tgn:1000001",
          "tgn:1002328",
          "tgn:7012149",
          "tgn:7007568",
          "tgn:7029392"
        ],
        "placetype": [
          "aat:300008761"
        ],
        "id": 2568866,
        "name:xx": "Parker Hollow"
      }
    },
    {
      "geometry": {
        "type": "Point",
        "coordinates": [
          -77.3333,
          41.3333
        ]
      },
      "type": "Feature",
      "properties": {
        "hierarchy": [
          "tgn:2568867",
          "tgn:1000001",
          "tgn:7012149",
          "tgn:1002613",
          "tgn:7007710",
          "tgn:7029392"
        ],
        "placetype": [
          "aat:300008761"
        ],
        "id": 2568867,
        "name:xx": "Parker Hollow"
      }
    },
    {
      "geometry": {
        "type": "Point",
        "coordinates": [
          -78.2167,
          41.4
        ]
      },
      "type": "Feature",
      "properties": {
        "hierarchy": [
          "tgn:2568868",
          "tgn:1000001",
          "tgn:1002229",
          "tgn:7012149",
          "tgn:7007710",
          "tgn:7029392"
        ],
        "placetype": [
          "aat:300008761"
        ],
        "id": 2568868,
        "name:xx": "Parker Hollow"
      }
    },
    {
      "geometry": {
        "type": "Point",
        "coordinates": [
          -77.7667,
          41.55
        ]
      },
      "type": "Feature",
      "properties": {
        "hierarchy": [
          "tgn:2568869",
          "tgn:1000001",
          "tgn:7012149",
          "tgn:1002800",
          "tgn:7007710",
          "tgn:7029392"
        ],
        "placetype": [
          "aat:300008761"
        ],
        "id": 2568869,
        "name:xx": "Parker Hollow"
      }
    }
  ]
}
