{
  "geometry": {
    "type": "Point",
    "coordinates": [
      -75.1833,
      43.7333
    ]
  },
  "type": "Feature",
  "properties": {
    "hierarchy": [
      "tgn:2459061",
      "tgn:1000001",
      "tgn:7012149",
      "tgn:1002593",
      "tgn:7007568",
      "tgn:7029392"
    ],
    "placetype": [
      "aat:300008706"
    ],
    "id": 2459061,
    "name:xx": "Little Pine Creek"
  }
}
