{
  "type": "FeatureCollection",
  "features": [
    {
      "geometry": {
        "type": "Point",
        "coordinates": [
          -5.766667,
          43.4
        ]
      },
      "type": "Feature",
      "properties": {
        "hierarchy": [
          "tgn:7293960",
          "tgn:7008911",
          "tgn:1000003",
          "tgn:7002763",
          "tgn:1000095",
          "tgn:7029392"
        ],
        "placetype": [
          "aat:300008347"
        ],
        "id": 7293960,
        "name:xx": "Viella"
      }
    },
    {
      "geometry": {
        "type": "Point",
        "coordinates": [
          -3.683333,
          42.25
        ]
      },
      "type": "Feature",
      "properties": {
        "hierarchy": [
          "tgn:7293962",
          "tgn:7002810",
          "tgn:7001158",
          "tgn:1000003",
          "tgn:1000095",
          "tgn:7029392"
        ],
        "placetype": [
          "aat:300008699"
        ],
        "id": 7293962,
        "name:xx": "Viejo, Río"
      }
    },
    {
      "geometry": {
        "type": "Point",
        "coordinates": [
          -4.05,
          41.083333
        ]
      },
      "type": "Feature",
      "properties": {
        "hierarchy": [
          "tgn:7293963",
          "tgn:7002839",
          "tgn:7001158",
          "tgn:1000003",
          "tgn:1000095",
          "tgn:7029392"
        ],
        "placetype": [
          "aat:300008699"
        ],
        "id": 7293963,
        "name:xx": "Viejo, Río"
      }
    },
    {
      "geometry": {
        "type": "Point",
        "coordinates": [
          -6.85,
          40.266667
        ]
      },
      "type": "Feature",
      "properties": {
        "hierarchy": [
          "tgn:7293964",
          "tgn:7002835",
          "tgn:7001158",
          "tgn:1000003",
          "tgn:1000095",
          "tgn:7029392"
        ],
        "placetype": [
          "aat:300259572"
        ],
        "id": 7293964,
        "name:xx": "Viejo, Puerto"
      }
    },
    {
      "geometry": {
        "type": "Point",
        "coordinates": [
          -13.533333,
          29.283333
        ]
      },
      "type": "Feature",
      "properties": {
        "hierarchy": [
          "tgn:7293965",
          "tgn:7002825",
          "tgn:7016622",
          "tgn:1000003",
          "tgn:1000095",
          "tgn:7029392"
        ],
        "placetype": [
          "aat:300132317"
        ],
        "id": 7293965,
        "name:xx": "Viejo, Puerto"
      }
    },
    {
      "geometry": {
        "type": "Point",
        "coordinates": [
          -16.675,
          28.258333
        ]
      },
      "type": "Feature",
      "properties": {
        "hierarchy": [
          "tgn:7293966",
          "tgn:7002836",
          "tgn:7016622",
          "tgn:1000003",
          "tgn:1000095",
          "tgn:7029392"
        ],
        "placetype": [
          "aat:300008798"
        ],
        "id": 7293966,
        "name:xx": "Viejo, Pico"
      }
    },
    {
      "geometry": {
        "type": "Point",
        "coordinates": [
          -1.416667,
          41.666667
        ]
      },
      "type": "Feature",
      "properties": {
        "hierarchy": [
          "tgn:7293967",
          "tgn:7002759",
          "tgn:7002845",
          "tgn:1000003",
          "tgn:1000095",
          "tgn:7029392"
        ],
        "placetype": [
          "aat:300008688"
        ],
        "id": 7293967,
        "name:xx": "Viejo, Pantano"
      }
    },
    {
      "geometry": {
        "type": "Point",
        "coordinates": [
          -4.85,
          40.85
        ]
      },
      "type": "Feature",
      "properties": {
        "hierarchy": [
          "tgn:7293968",
          "tgn:7002806",
          "tgn:7001158",
          "tgn:1000003",
          "tgn:1000095",
          "tgn:7029392"
        ],
        "placetype": [
          "aat:300266554",
          "aat:300008699"
        ],
        "id": 7293968,
        "name:xx": "Viejo, Arroyo"
      }
    },
    {
      "geometry": {
        "type": "Point",
        "coordinates": [
          -4.666667,
          41.533333
        ]
      },
      "type": "Feature",
      "properties": {
        "hierarchy": [
          "tgn:7293969",
          "tgn:7001158",
          "tgn:7002848",
          "tgn:1000003",
          "tgn:1000095",
          "tgn:7029392"
        ],
        "placetype": [
          "aat:300008699"
        ],
        "id": 7293969,
        "name:xx": "Viejo, Arroyo"
      }
    }
  ]
}
