{
  "geometry": {
    "type": "Point",
    "coordinates": [
      -103.8667,
      35.4167
    ]
  },
  "type": "Feature",
  "properties": {
    "hierarchy": [
      "tgn:2343201",
      "tgn:1000001",
      "tgn:7012149",
      "tgn:2001453",
      "tgn:7007566",
      "tgn:7029392"
    ],
    "placetype": [
      "aat:300006191"
    ],
    "id": 2343201,
    "name:xx": "Gacho Tank"
  }
}
