{
  "geometry": {
    "type": "Point",
    "coordinates": [
      -82.25,
      35.5667
    ]
  },
  "type": "Feature",
  "properties": {
    "hierarchy": [
      "tgn:2444561",
      "tgn:1000001",
      "tgn:7012149",
      "tgn:2001514",
      "tgn:7007709",
      "tgn:7029392"
    ],
    "placetype": [
      "aat:300008707"
    ],
    "id": 2444561,
    "name:xx": "Left Prong Catawba River"
  }
}
