{
  "geometry": {
    "type": "Point",
    "coordinates": [
      115.9167,
      38.8333
    ]
  },
  "type": "Feature",
  "properties": {
    "hierarchy": [
      "tgn:1132180",
      "tgn:1000004",
      "tgn:1000111",
      "tgn:7029392"
    ],
    "placetype": [
      "aat:300008707"
    ],
    "id": 1132180,
    "name:xx": "Zhulong He"
  }
}
