{
  "geometry": {
    "type": "Point",
    "coordinates": [
      -77.3833,
      42.2833
    ]
  },
  "type": "Feature",
  "properties": {
    "hierarchy": [
      "tgn:2514552",
      "tgn:1000001",
      "tgn:7012149",
      "tgn:1002920",
      "tgn:7007568",
      "tgn:7029392"
    ],
    "placetype": [
      "aat:300008798"
    ],
    "id": 2514552,
    "name:xx": "Miller Hill"
  }
}
