{
  "geometry": {
    "type": "Point",
    "coordinates": [
      -73.3333,
      41.5167
    ]
  },
  "type": "Feature",
  "properties": {
    "hierarchy": [
      "tgn:2216297",
      "tgn:1000001",
      "tgn:7012149",
      "tgn:7007159",
      "tgn:7029392"
    ],
    "placetype": [
      "aat:300008699"
    ],
    "id": 2216297,
    "name:xx": "Camp Brook"
  }
}
