{
  "type": "FeatureCollection",
  "features": [
    {
      "geometry": {
        "type": "Point",
        "coordinates": [
          -90.366667,
          19.85
        ]
      },
      "type": "Feature",
      "properties": {
        "hierarchy": [
          "tgn:7389320",
          "tgn:7005578",
          "tgn:1000001",
          "tgn:7005560",
          "tgn:7029392"
        ],
        "placetype": [
          "aat:300008347"
        ],
        "id": 7389320,
        "name:xx": "Sahcacal"
      }
    },
    {
      "geometry": {
        "type": "Point",
        "coordinates": [
          -88.733333,
          20.283333
        ]
      },
      "type": "Feature",
      "properties": {
        "hierarchy": [
          "tgn:7389321",
          "tgn:1000001",
          "tgn:7005600",
          "tgn:7005560",
          "tgn:7029392"
        ],
        "placetype": [
          "aat:300008347"
        ],
        "id": 7389321,
        "name:xx": "Sahcabchén"
      }
    },
    {
      "geometry": {
        "type": "Point",
        "coordinates": [
          -89.983333,
          19.883333
        ]
      },
      "type": "Feature",
      "properties": {
        "hierarchy": [
          "tgn:7389322",
          "tgn:7005578",
          "tgn:1000001",
          "tgn:7005560",
          "tgn:7029392"
        ],
        "placetype": [
          "aat:300008347"
        ],
        "id": 7389322,
        "name:xx": "Sahcabchén"
      }
    },
    {
      "geometry": {
        "type": "Point",
        "coordinates": [
          -97.666667,
          21.566667
        ]
      },
      "type": "Feature",
      "properties": {
        "hierarchy": [
          "tgn:7389323",
          "tgn:1000001",
          "tgn:7005599",
          "tgn:7005560",
          "tgn:7029392"
        ],
        "placetype": [
          "aat:300008347"
        ],
        "id": 7389323,
        "name:xx": "Rancho Nuevo"
      }
    },
    {
      "geometry": {
        "type": "Point",
        "coordinates": [
          -97.9,
          21.366667
        ]
      },
      "type": "Feature",
      "properties": {
        "hierarchy": [
          "tgn:7389324",
          "tgn:1000001",
          "tgn:7005599",
          "tgn:7005560",
          "tgn:7029392"
        ],
        "placetype": [
          "aat:300008347"
        ],
        "id": 7389324,
        "name:xx": "Rancho Nuevo"
      }
    },
    {
      "geometry": {
        "type": "Point",
        "coordinates": [
          -97.616667,
          21.166667
        ]
      },
      "type": "Feature",
      "properties": {
        "hierarchy": [
          "tgn:7389325",
          "tgn:1000001",
          "tgn:7005599",
          "tgn:7005560",
          "tgn:7029392"
        ],
        "placetype": [
          "aat:300008347"
        ],
        "id": 7389325,
        "name:xx": "Rancho Nuevo"
      }
    },
    {
      "geometry": {
        "type": "Point",
        "coordinates": [
          -104.2,
          21.15
        ]
      },
      "type": "Feature",
      "properties": {
        "hierarchy": [
          "tgn:7389326",
          "tgn:7005586",
          "tgn:1000001",
          "tgn:7005560",
          "tgn:7029392"
        ],
        "placetype": [
          "aat:300008347"
        ],
        "id": 7389326,
        "name:xx": "Rancho Nuevo"
      }
    },
    {
      "geometry": {
        "type": "Point",
        "coordinates": [
          -97.85,
          21
        ]
      },
      "type": "Feature",
      "properties": {
        "hierarchy": [
          "tgn:7389327",
          "tgn:1000001",
          "tgn:7005599",
          "tgn:7005560",
          "tgn:7029392"
        ],
        "placetype": [
          "aat:300008347"
        ],
        "id": 7389327,
        "name:xx": "Rancho Nuevo"
      }
    },
    {
      "geometry": {
        "type": "Point",
        "coordinates": [
          -101.633333,
          20.966667
        ]
      },
      "type": "Feature",
      "properties": {
        "hierarchy": [
          "tgn:7389328",
          "tgn:7005584",
          "tgn:1000001",
          "tgn:7005560",
          "tgn:7029392"
        ],
        "placetype": [
          "aat:300008347"
        ],
        "id": 7389328,
        "name:xx": "Rancho Nuevo"
      }
    },
    {
      "geometry": {
        "type": "Point",
        "coordinates": [
          -102.883333,
          20.716667
        ]
      },
      "type": "Feature",
      "properties": {
        "hierarchy": [
          "tgn:7389329",
          "tgn:7005586",
          "tgn:1000001",
          "tgn:7005560",
          "tgn:7029392"
        ],
        "placetype": [
          "aat:300008347"
        ],
        "id": 7389329,
        "name:xx": "Rancho Nuevo"
      }
    }
  ]
}
