{
  "geometry": {
    "type": "Point",
    "coordinates": [
      -83.2167,
      36.25
    ]
  },
  "type": "Feature",
  "properties": {
    "hierarchy": [
      "tgn:2290386",
      "tgn:1000001",
      "tgn:7012149",
      "tgn:2001868",
      "tgn:7007825",
      "tgn:7029392"
    ],
    "placetype": [
      "aat:300008697"
    ],
    "id": 2290386,
    "name:xx": "Dodson Spring"
  }
}
