{
  "geometry": {
    "type": "Point",
    "coordinates": [
      -85.65,
      37.0333
    ]
  },
  "type": "Feature",
  "properties": {
    "hierarchy": [
      "tgn:2241588",
      "tgn:1000001",
      "tgn:7012149",
      "tgn:2000828",
      "tgn:7007255",
      "tgn:7029392"
    ],
    "placetype": [
      "aat:300008347"
    ],
    "id": 2241588,
    "name:xx": "Clarks Corner"
  }
}
