{
  "geometry": {
    "type": "Point",
    "coordinates": [
      -117.5167,
      37.55
    ]
  },
  "type": "Feature",
  "properties": {
    "hierarchy": [
      "tgn:2409973",
      "tgn:1000001",
      "tgn:2001412",
      "tgn:7012149",
      "tgn:7007526",
      "tgn:7029392"
    ],
    "placetype": [
      "aat:300000390"
    ],
    "id": 2409973,
    "name:xx": "Imperial Mine"
  }
}
