{
  "geometry": {
    "type": "Point",
    "coordinates": [
      -105.1667,
      40.5667
    ]
  },
  "type": "Feature",
  "properties": {
    "hierarchy": [
      "tgn:2560264",
      "tgn:1000001",
      "tgn:7012149",
      "tgn:2000226",
      "tgn:7007158",
      "tgn:7029392"
    ],
    "placetype": [
      "aat:300132316"
    ],
    "id": 2560264,
    "name:xx": "Orchard Cove"
  }
}
