{
  "geometry": {
    "type": "Point",
    "coordinates": [
      -71.8333,
      -17.1667
    ]
  },
  "type": "Feature",
  "properties": {
    "hierarchy": [
      "tgn:1024710",
      "tgn:1000508",
      "tgn:1000002",
      "tgn:1000056",
      "tgn:7029392"
    ],
    "placetype": [
      "aat:300008347"
    ],
    "id": 1024710,
    "name:xx": "Punta de Bombón"
  }
}
