{
  "geometry": {
    "type": "Point",
    "coordinates": [
      -82.4167,
      35.8333
    ]
  },
  "type": "Feature",
  "properties": {
    "hierarchy": [
      "tgn:2248274",
      "tgn:1000001",
      "tgn:7012149",
      "tgn:7007709",
      "tgn:7029392"
    ],
    "placetype": [
      "aat:300008798"
    ],
    "id": 2248274,
    "name:xx": "Cold Knob"
  }
}
