{
  "geometry": {
    "type": "Point",
    "coordinates": [
      -83.75,
      39.4333
    ]
  },
  "type": "Feature",
  "properties": {
    "hierarchy": [
      "tgn:2412117",
      "tgn:1000001",
      "tgn:1002285",
      "tgn:7012149",
      "tgn:7007706",
      "tgn:7029392"
    ],
    "placetype": [
      "aat:300008699"
    ],
    "id": 2412117,
    "name:xx": "Indian Run"
  }
}
