{
  "type": "FeatureCollection",
  "features": [
    {
      "geometry": {
        "type": "Point",
        "coordinates": [
          14,
          -2
        ]
      },
      "type": "Feature",
      "properties": {
        "hierarchy": [
          "tgn:1001680",
          "tgn:7001242",
          "tgn:1000164",
          "tgn:7029392"
        ],
        "placetype": [
          "aat:300387064",
          "aat:300000774"
        ],
        "id": 1001680,
        "name:xx": "Haut-Ogooué"
      }
    },
    {
      "geometry": {
        "type": "Point",
        "coordinates": [
          45.5,
          4
        ]
      },
      "type": "Feature",
      "properties": {
        "hierarchy": [
          "tgn:1001681",
          "tgn:7001242",
          "tgn:1000192",
          "tgn:7029392"
        ],
        "placetype": [
          "aat:300387064",
          "aat:300236112"
        ],
        "id": 1001681,
        "name:xx": "Hiiraan"
      }
    },
    {
      "geometry": {
        "type": "Point",
        "coordinates": [
          -7.25,
          19
        ]
      },
      "type": "Feature",
      "properties": {
        "hierarchy": [
          "tgn:1001682",
          "tgn:7001242",
          "tgn:1000176",
          "tgn:7029392"
        ],
        "placetype": [
          "aat:300387064",
          "aat:300236112"
        ],
        "id": 1001682,
        "name:xx": "Hodh ech Chargui, Région du"
      }
    },
    {
      "geometry": {
        "type": "Point",
        "coordinates": [
          -10,
          16.5
        ]
      },
      "type": "Feature",
      "properties": {
        "hierarchy": [
          "tgn:1001683",
          "tgn:7001242",
          "tgn:1000176",
          "tgn:7029392"
        ],
        "placetype": [
          "aat:300387064",
          "aat:300236112"
        ],
        "id": 1001683,
        "name:xx": "Hodh el Gharbi, Région du"
      }
    },
    {
      "geometry": {
        "type": "Point",
        "coordinates": [
          -15,
          19.8333
        ]
      },
      "type": "Feature",
      "properties": {
        "hierarchy": [
          "tgn:1001684",
          "tgn:7001242",
          "tgn:1000176",
          "tgn:7029392"
        ],
        "placetype": [
          "aat:300387064",
          "aat:300236112"
        ],
        "id": 1001684,
        "name:xx": "Inchiri"
      }
    },
    {
      "geometry": {
        "type": "Point",
        "coordinates": [
          35,
          -9
        ]
      },
      "type": "Feature",
      "properties": {
        "hierarchy": [
          "tgn:1001685",
          "tgn:7001242",
          "tgn:1000203",
          "tgn:7029392"
        ],
        "placetype": [
          "aat:300387064",
          "aat:300236112"
        ],
        "id": 1001685,
        "name:xx": "Iringa"
      }
    },
    {
      "geometry": {
        "type": "Point",
        "coordinates": [
          43,
          1
        ]
      },
      "type": "Feature",
      "properties": {
        "hierarchy": [
          "tgn:1001686",
          "tgn:7001242",
          "tgn:1000192",
          "tgn:7029392"
        ],
        "placetype": [
          "aat:300387064",
          "aat:300236112"
        ],
        "id": 1001686,
        "name:xx": "Jubbada Dhexe"
      }
    },
    {
      "geometry": {
        "type": "Point",
        "coordinates": [
          41.25,
          0.0167
        ]
      },
      "type": "Feature",
      "properties": {
        "hierarchy": [
          "tgn:1001687",
          "tgn:7001242",
          "tgn:1000192",
          "tgn:7029392"
        ],
        "placetype": [
          "aat:300387064",
          "aat:300236112"
        ],
        "id": 1001687,
        "name:xx": "Jubbada Hoose"
      }
    },
    {
      "geometry": {
        "type": "Point",
        "coordinates": [
          -11,
          14
        ]
      },
      "type": "Feature",
      "properties": {
        "hierarchy": [
          "tgn:1001688",
          "tgn:7001242",
          "tgn:1000175",
          "tgn:7029392"
        ],
        "placetype": [
          "aat:300387064",
          "aat:300236112"
        ],
        "id": 1001688,
        "name:xx": "Kayes, Région de"
      }
    },
    {
      "geometry": {
        "type": "Point",
        "coordinates": [
          30.5,
          -4.5
        ]
      },
      "type": "Feature",
      "properties": {
        "hierarchy": [
          "tgn:1001689",
          "tgn:7001242",
          "tgn:1000203",
          "tgn:7029392"
        ],
        "placetype": [
          "aat:300387064",
          "aat:300236112"
        ],
        "id": 1001689,
        "name:xx": "Kigoma"
      }
    }
  ]
}
