{
  "geometry": {
    "type": "Point",
    "coordinates": [
      -84.9833,
      44.4167
    ]
  },
  "type": "Feature",
  "properties": {
    "hierarchy": [
      "tgn:2126112",
      "tgn:1000001",
      "tgn:7012149",
      "tgn:2000980",
      "tgn:7007520",
      "tgn:7029392"
    ],
    "placetype": [
      "aat:300008706"
    ],
    "id": 2126112,
    "name:xx": "Addis Creek"
  }
}
