{
  "geometry": {
    "type": "Point",
    "coordinates": [
      31.836776,
      30.214316
    ]
  },
  "type": "Feature",
  "properties": {
    "hierarchy": [
      "tgn:7522481",
      "tgn:7001242",
      "tgn:7016833",
      "tgn:1001091",
      "tgn:7029392"
    ],
    "placetype": [
      "aat:300379998"
    ],
    "name:en": "Dayr al Bayḑā', Wādī",
    "id": 7522481
  }
}
