{
  "geometry": {
    "type": "Point",
    "coordinates": [
      -89.8167,
      33.8333
    ]
  },
  "type": "Feature",
  "properties": {
    "hierarchy": [
      "tgn:2620549",
      "tgn:1000001",
      "tgn:7012149",
      "tgn:2001107",
      "tgn:7007522",
      "tgn:7029392"
    ],
    "placetype": [
      "aat:300008347"
    ],
    "id": 2620549,
    "name:xx": "Riverdale"
  }
}
