{
  "geometry": {
    "type": "Point",
    "coordinates": [
      8.25,
      40.75
    ]
  },
  "type": "Feature",
  "properties": {
    "hierarchy": [
      "tgn:1112046",
      "tgn:7015163",
      "tgn:1000003",
      "tgn:7003121",
      "tgn:1000080",
      "tgn:7029392"
    ],
    "placetype": [
      "aat:300055621",
      "aat:300387346"
    ],
    "id": 1112046,
    "name:xx": "La Nurra"
  }
}
