{
  "geometry": {
    "type": "Point",
    "coordinates": [
      -80.5333,
      38.6167
    ]
  },
  "type": "Feature",
  "properties": {
    "hierarchy": [
      "tgn:2751142",
      "tgn:1000001",
      "tgn:2002256",
      "tgn:7012149",
      "tgn:7013961",
      "tgn:7029392"
    ],
    "placetype": [
      "aat:300008798"
    ],
    "id": 2751142,
    "name:xx": "Ware Mountain"
  }
}
