{
  "geometry": {
    "type": "Point",
    "coordinates": [
      -120.5667,
      46.9167
    ]
  },
  "type": "Feature",
  "properties": {
    "hierarchy": [
      "tgn:2661911",
      "tgn:1000001",
      "tgn:7012149",
      "tgn:1002553",
      "tgn:7007920",
      "tgn:7029392"
    ],
    "placetype": [
      "aat:300008761"
    ],
    "id": 2661911,
    "name:xx": "Shushuskin Canyon"
  }
}
