{
  "geometry": {
    "type": "Point",
    "coordinates": [
      -107.8833,
      35.3833
    ]
  },
  "type": "Feature",
  "properties": {
    "hierarchy": [
      "tgn:2274339",
      "tgn:1000001",
      "tgn:7012149",
      "tgn:7019676",
      "tgn:7007566",
      "tgn:7029392"
    ],
    "placetype": [
      "aat:300000390"
    ],
    "id": 2274339,
    "name:xx": "Dakota Mine"
  }
}
