{
  "geometry": {
    "type": "Point",
    "coordinates": [
      9.7333,
      46.8333
    ]
  },
  "type": "Feature",
  "properties": {
    "hierarchy": [
      "tgn:1064168",
      "tgn:7003748",
      "tgn:1000003",
      "tgn:7011731",
      "tgn:7029392"
    ],
    "placetype": [
      "aat:300008347"
    ],
    "id": 1064168,
    "name:xx": "Langwies"
  }
}
