{
  "geometry": {
    "type": "Point",
    "coordinates": [
      11.65,
      48.183333
    ]
  },
  "type": "Feature",
  "properties": {
    "hierarchy": [
      "tgn:1041486",
      "tgn:7003669",
      "tgn:1000003",
      "tgn:7000084",
      "tgn:7029392"
    ],
    "placetype": [
      "aat:300008347"
    ],
    "id": 1041486,
    "name:xx": "Unterföhring"
  }
}
