{
  "geometry": {
    "type": "Point",
    "coordinates": [
      2.795846,
      51.08828
    ]
  },
  "type": "Feature",
  "properties": {
    "hierarchy": [
      "tgn:7248365",
      "tgn:7003458",
      "tgn:1000003",
      "tgn:1000063",
      "tgn:7018236",
      "tgn:7029392"
    ],
    "placetype": [
      "aat:300000206"
    ],
    "id": 7248365,
    "name:xx": "Berkelhof"
  }
}
