{
  "geometry": {
    "type": "Point",
    "coordinates": [
      -112.7667,
      36.65
    ]
  },
  "type": "Feature",
  "properties": {
    "hierarchy": [
      "tgn:2724344",
      "tgn:1000001",
      "tgn:7006451",
      "tgn:7012149",
      "tgn:2000098",
      "tgn:7029392"
    ],
    "placetype": [
      "aat:300006191"
    ],
    "id": 2724344,
    "name:xx": "Tom Lamb Reservoir"
  }
}
