{
  "geometry": {
    "type": "Point",
    "coordinates": [
      -91.6667,
      35.4167
    ]
  },
  "type": "Feature",
  "properties": {
    "hierarchy": [
      "tgn:2712168",
      "tgn:1000001",
      "tgn:7016172",
      "tgn:7012149",
      "tgn:2000177",
      "tgn:7029392"
    ],
    "placetype": [
      "aat:300008798"
    ],
    "id": 2712168,
    "name:xx": "Tater Hill"
  }
}
