{
  "type": "FeatureCollection",
  "features": [
    {
      "geometry": {
        "type": "Point",
        "coordinates": [
          -0.4,
          52.116667
        ]
      },
      "type": "Feature",
      "properties": {
        "hierarchy": [
          "tgn:4002233",
          "tgn:7002445",
          "tgn:7008103",
          "tgn:1000003",
          "tgn:7008591",
          "tgn:7029392"
        ],
        "placetype": [
          "aat:300008347"
        ],
        "id": 4002233,
        "name:xx": "Cardington",
        "name:ang": "Chernetone"
      }
    },
    {
      "geometry": {
        "type": "Point",
        "coordinates": [
          13.264722,
          46.008056
        ]
      },
      "type": "Feature",
      "properties": {
        "hierarchy": [
          "tgn:4002237",
          "tgn:1003506",
          "tgn:1000003",
          "tgn:7002993",
          "tgn:1000080",
          "tgn:7029392"
        ],
        "placetype": [
          "aat:300008347"
        ],
        "id": 4002237,
        "name:xx": "Cargnacco"
      }
    }
  ]
}
