{
  "geometry": {
    "type": "Point",
    "coordinates": [
      103.7833,
      1.35
    ]
  },
  "type": "Feature",
  "properties": {
    "hierarchy": [
      "tgn:1108253",
      "tgn:1000004",
      "tgn:1000138",
      "tgn:7000381",
      "tgn:7029392"
    ],
    "placetype": [
      "aat:300008777"
    ],
    "id": 1108253,
    "name:xx": "Timah Bukit"
  }
}
