{
  "geometry": {
    "type": "Point",
    "coordinates": [
      -94.15,
      46.6667
    ]
  },
  "type": "Feature",
  "properties": {
    "hierarchy": [
      "tgn:2398228",
      "tgn:1000001",
      "tgn:2001016",
      "tgn:7012149",
      "tgn:7007521",
      "tgn:7029392"
    ],
    "placetype": [
      "aat:300008680"
    ],
    "id": 2398228,
    "name:xx": "Hooligans Hole"
  }
}
