{
  "geometry": {
    "type": "Point",
    "coordinates": [
      -80.1833,
      40.4833
    ]
  },
  "type": "Feature",
  "properties": {
    "hierarchy": [
      "tgn:2505030",
      "tgn:7013272",
      "tgn:1000001",
      "tgn:7012149",
      "tgn:7007710",
      "tgn:7029392"
    ],
    "placetype": [
      "aat:300008699"
    ],
    "id": 2505030,
    "name:xx": "Meeks Run"
  }
}
