{
  "geometry": {
    "type": "Point",
    "coordinates": [
      32.5667,
      29.95
    ]
  },
  "type": "Feature",
  "properties": {
    "hierarchy": [
      "tgn:1004023",
      "tgn:7001242",
      "tgn:7016833",
      "tgn:1001110",
      "tgn:7029392"
    ],
    "placetype": [
      "aat:300000745"
    ],
    "id": 1004023,
    "name:xx": "Būr Ibrāhīm"
  }
}
