{
  "geometry": {
    "type": "Point",
    "coordinates": [
      -112.9667,
      47.3333
    ]
  },
  "type": "Feature",
  "properties": {
    "hierarchy": [
      "tgn:2729013",
      "tgn:1000001",
      "tgn:7012149",
      "tgn:2001284",
      "tgn:7007524",
      "tgn:7029392"
    ],
    "placetype": [
      "aat:300008798"
    ],
    "id": 2729013,
    "name:xx": "Trident Peaks"
  }
}
