{
  "geometry": {
    "type": "Point",
    "coordinates": [
      -62.65,
      45.5667
    ]
  },
  "type": "Feature",
  "properties": {
    "hierarchy": [
      "tgn:1014514",
      "tgn:7005685",
      "tgn:1000001",
      "tgn:7005802",
      "tgn:7029392"
    ],
    "placetype": [
      "aat:300008347"
    ],
    "id": 1014514,
    "name:xx": "Stellarton"
  }
}
