{
  "type": "FeatureCollection",
  "features": [
    {
      "geometry": {
        "type": "Point",
        "coordinates": [
          68.9667,
          42.1
        ]
      },
      "type": "Feature",
      "properties": {
        "hierarchy": [
          "tgn:1057120",
          "tgn:1000004",
          "tgn:7012947",
          "tgn:7014786",
          "tgn:7029392"
        ],
        "placetype": [
          "aat:300008347"
        ],
        "id": 1057120,
        "name:xx": "Montajtas"
      }
    },
    {
      "geometry": {
        "type": "Point",
        "coordinates": [
          84.6667,
          56.7667
        ]
      },
      "type": "Feature",
      "properties": {
        "hierarchy": [
          "tgn:1057121",
          "tgn:1000004",
          "tgn:7011604",
          "tgn:7018214",
          "tgn:7002435",
          "tgn:7029392"
        ],
        "placetype": [
          "aat:300008347"
        ],
        "id": 1057121,
        "name:xx": "Moryakovskiy Zaton"
      }
    },
    {
      "geometry": {
        "type": "Point",
        "coordinates": [
          37.3333,
          55.9333
        ]
      },
      "type": "Feature",
      "properties": {
        "hierarchy": [
          "tgn:1057122",
          "tgn:1000004",
          "tgn:7011573",
          "tgn:7018214",
          "tgn:7002435",
          "tgn:7029392"
        ],
        "placetype": [
          "aat:300008347"
        ],
        "id": 1057122,
        "name:xx": "Morščichino"
      }
    },
    {
      "geometry": {
        "type": "Point",
        "coordinates": [
          41.8,
          53.4333
        ]
      },
      "type": "Feature",
      "properties": {
        "hierarchy": [
          "tgn:1057123",
          "tgn:1000004",
          "tgn:1003417",
          "tgn:7018214",
          "tgn:7002435",
          "tgn:7029392"
        ],
        "placetype": [
          "aat:300008347"
        ],
        "id": 1057123,
        "name:xx": "Morshansk"
      }
    },
    {
      "geometry": {
        "type": "Point",
        "coordinates": [
          40.2,
          59.6167
        ]
      },
      "type": "Feature",
      "properties": {
        "hierarchy": [
          "tgn:1057124",
          "tgn:1000004",
          "tgn:7017317",
          "tgn:7018214",
          "tgn:7002435",
          "tgn:7029392"
        ],
        "placetype": [
          "aat:300008347"
        ],
        "id": 1057124,
        "name:xx": "Morzhenga"
      }
    },
    {
      "geometry": {
        "type": "Point",
        "coordinates": [
          47.8333,
          51.2833
        ]
      },
      "type": "Feature",
      "properties": {
        "hierarchy": [
          "tgn:1057125",
          "tgn:1000004",
          "tgn:1003408",
          "tgn:7018214",
          "tgn:7002435",
          "tgn:7029392"
        ],
        "placetype": [
          "aat:300008347"
        ],
        "id": 1057125,
        "name:xx": "Morcy"
      }
    },
    {
      "geometry": {
        "type": "Point",
        "coordinates": [
          51.9167,
          61.3333
        ]
      },
      "type": "Feature",
      "properties": {
        "hierarchy": [
          "tgn:1057126",
          "tgn:1000004",
          "tgn:6003149",
          "tgn:7002435",
          "tgn:7029392"
        ],
        "placetype": [
          "aat:300008347"
        ],
        "id": 1057126,
        "name:xx": "Mordino"
      }
    },
    {
      "geometry": {
        "type": "Point",
        "coordinates": [
          45.8,
          51.1167
        ]
      },
      "type": "Feature",
      "properties": {
        "hierarchy": [
          "tgn:1057127",
          "tgn:1000004",
          "tgn:1003408",
          "tgn:7018214",
          "tgn:7002435",
          "tgn:7029392"
        ],
        "placetype": [
          "aat:300008347"
        ],
        "id": 1057127,
        "name:xx": "Mordovo"
      }
    },
    {
      "geometry": {
        "type": "Point",
        "coordinates": [
          51.6,
          53.7833
        ]
      },
      "type": "Feature",
      "properties": {
        "hierarchy": [
          "tgn:1057128",
          "tgn:1000004",
          "tgn:1003407",
          "tgn:7018214",
          "tgn:7002435",
          "tgn:7029392"
        ],
        "placetype": [
          "aat:300008347"
        ],
        "id": 1057128,
        "name:xx": "Mordovo-Adel'akovo"
      }
    },
    {
      "geometry": {
        "type": "Point",
        "coordinates": [
          52.5167,
          53.8
        ]
      },
      "type": "Feature",
      "properties": {
        "hierarchy": [
          "tgn:1057129",
          "tgn:1000004",
          "tgn:1003398",
          "tgn:7018214",
          "tgn:7002435",
          "tgn:7029392"
        ],
        "placetype": [
          "aat:300008347"
        ],
        "id": 1057129,
        "name:xx": "Mordovskiy Buguruslan"
      }
    }
  ]
}
