{
  "type": "FeatureCollection",
  "features": [
    {
      "geometry": {
        "type": "Point",
        "coordinates": [
          -85.2,
          36.1833
        ]
      },
      "type": "Feature",
      "properties": {
        "hierarchy": [
          "tgn:2638370",
          "tgn:1000001",
          "tgn:7012149",
          "tgn:2001903",
          "tgn:7007825",
          "tgn:7029392"
        ],
        "placetype": [
          "aat:300008761"
        ],
        "id": 2638370,
        "name:xx": "Sally Hollow"
      }
    },
    {
      "geometry": {
        "type": "Point",
        "coordinates": [
          -82.5167,
          36.1333
        ]
      },
      "type": "Feature",
      "properties": {
        "hierarchy": [
          "tgn:2638371",
          "tgn:1000001",
          "tgn:7012149",
          "tgn:2001922",
          "tgn:7007825",
          "tgn:7029392"
        ],
        "placetype": [
          "aat:300008761"
        ],
        "id": 2638371,
        "name:xx": "Sally Hollow"
      }
    },
    {
      "geometry": {
        "type": "Point",
        "coordinates": [
          -79.9833,
          38.2167
        ]
      },
      "type": "Feature",
      "properties": {
        "hierarchy": [
          "tgn:2638372",
          "tgn:1000001",
          "tgn:7012149",
          "tgn:2002287",
          "tgn:7013961",
          "tgn:7029392"
        ],
        "placetype": [
          "aat:300008761"
        ],
        "id": 2638372,
        "name:xx": "Sally Hollow"
      }
    },
    {
      "geometry": {
        "type": "Point",
        "coordinates": [
          -82.95,
          36.9
        ]
      },
      "type": "Feature",
      "properties": {
        "hierarchy": [
          "tgn:2638373",
          "tgn:1000001",
          "tgn:7012149",
          "tgn:2000797",
          "tgn:7007255",
          "tgn:7029392"
        ],
        "placetype": [
          "aat:300008699"
        ],
        "id": 2638373,
        "name:xx": "Sally Huff Branch"
      }
    },
    {
      "geometry": {
        "type": "Point",
        "coordinates": [
          -153.3333,
          57.7333
        ]
      },
      "type": "Feature",
      "properties": {
        "hierarchy": [
          "tgn:2638374",
          "tgn:7006450",
          "tgn:1000001",
          "tgn:2124012",
          "tgn:7012149",
          "tgn:7029392"
        ],
        "placetype": [
          "aat:300008791"
        ],
        "id": 2638374,
        "name:xx": "Sally Island"
      }
    },
    {
      "geometry": {
        "type": "Point",
        "coordinates": [
          -67.9333,
          44.4
        ]
      },
      "type": "Feature",
      "properties": {
        "hierarchy": [
          "tgn:2638375",
          "tgn:1000001",
          "tgn:2000922",
          "tgn:7012149",
          "tgn:7007515",
          "tgn:7029392"
        ],
        "placetype": [
          "aat:300008791"
        ],
        "id": 2638375,
        "name:xx": "Sally Island"
      }
    },
    {
      "geometry": {
        "type": "Point",
        "coordinates": [
          -67.9,
          44.45
        ]
      },
      "type": "Feature",
      "properties": {
        "hierarchy": [
          "tgn:2638376",
          "tgn:1000001",
          "tgn:7012149",
          "tgn:7014589",
          "tgn:7007515",
          "tgn:7029392"
        ],
        "placetype": [
          "aat:300008791"
        ],
        "id": 2638376,
        "name:xx": "Sally Island"
      }
    },
    {
      "geometry": {
        "type": "Point",
        "coordinates": [
          -67.9333,
          44.3833
        ]
      },
      "type": "Feature",
      "properties": {
        "hierarchy": [
          "tgn:2638377",
          "tgn:1000001",
          "tgn:2000922",
          "tgn:7012149",
          "tgn:7007515",
          "tgn:7029392"
        ],
        "placetype": [
          "aat:300386853"
        ],
        "id": 2638377,
        "name:xx": "Sally Islands"
      }
    },
    {
      "geometry": {
        "type": "Point",
        "coordinates": [
          -84.4,
          34.9667
        ]
      },
      "type": "Feature",
      "properties": {
        "hierarchy": [
          "tgn:2638378",
          "tgn:1000001",
          "tgn:7012149",
          "tgn:2000346",
          "tgn:7007248",
          "tgn:7029392"
        ],
        "placetype": [
          "aat:300000390"
        ],
        "id": 2638378,
        "name:xx": "Sally Jane Prospect"
      }
    },
    {
      "geometry": {
        "type": "Point",
        "coordinates": [
          -95,
          35.45
        ]
      },
      "type": "Feature",
      "properties": {
        "hierarchy": [
          "tgn:2638379",
          "tgn:1000001",
          "tgn:7012149",
          "tgn:2001690",
          "tgn:7007707",
          "tgn:7029392"
        ],
        "placetype": [
          "aat:300006191"
        ],
        "id": 2638379,
        "name:xx": "Sally Jones Lake"
      }
    }
  ]
}
