{
  "geometry": {
    "type": "Point",
    "coordinates": [
      -122.7833,
      42.35
    ]
  },
  "type": "Feature",
  "properties": {
    "hierarchy": [
      "tgn:2632254",
      "tgn:1000001",
      "tgn:7012149",
      "tgn:2001711",
      "tgn:7007708",
      "tgn:7029392"
    ],
    "placetype": [
      "aat:300008798"
    ],
    "id": 2632254,
    "name:xx": "Roxy Ann Peak"
  }
}
