{
  "geometry": {
    "type": "Point",
    "coordinates": [
      -70.8333,
      42.5333
    ]
  },
  "type": "Feature",
  "properties": {
    "hierarchy": [
      "tgn:2362711",
      "tgn:1000001",
      "tgn:1002359",
      "tgn:7012149",
      "tgn:7007517",
      "tgn:7029392"
    ],
    "placetype": [
      "aat:300008791"
    ],
    "id": 2362711,
    "name:xx": "Great Haste Island"
  }
}
