{
  "geometry": {
    "type": "Point",
    "coordinates": [
      68.05,
      27.5833
    ]
  },
  "type": "Feature",
  "properties": {
    "hierarchy": [
      "tgn:1083547",
      "tgn:1000004",
      "tgn:7002462",
      "tgn:1000133",
      "tgn:7029392"
    ],
    "placetype": [
      "aat:300008347"
    ],
    "id": 1083547,
    "name:xx": "Qambar"
  }
}
