{
  "geometry": {
    "type": "Point",
    "coordinates": [
      -82.5167,
      36.9667
    ]
  },
  "type": "Feature",
  "properties": {
    "hierarchy": [
      "tgn:2778210",
      "tgn:1000001",
      "tgn:7012149",
      "tgn:2002195",
      "tgn:7007919",
      "tgn:7029392"
    ],
    "placetype": [
      "aat:300008680"
    ],
    "id": 2778210,
    "name:xx": "Wise, Lake"
  }
}
