{
  "geometry": {
    "type": "Point",
    "coordinates": [
      -82.4167,
      37.4167
    ]
  },
  "type": "Feature",
  "properties": {
    "hierarchy": [
      "tgn:2328977",
      "tgn:1000001",
      "tgn:7012149",
      "tgn:2000837",
      "tgn:7007255",
      "tgn:7029392"
    ],
    "placetype": [
      "aat:300006191"
    ],
    "id": 2328977,
    "name:xx": "Fishtrap Lake"
  }
}
