{
  "geometry": {
    "type": "Point",
    "coordinates": [
      -77.9167,
      39.45
    ]
  },
  "type": "Feature",
  "properties": {
    "hierarchy": [
      "tgn:2117485",
      "tgn:1000001",
      "tgn:2002254",
      "tgn:7012149",
      "tgn:7013961",
      "tgn:7029392"
    ],
    "placetype": [
      "aat:300008347"
    ],
    "id": 2117485,
    "name:xx": "Blairton"
  }
}
