{
  "type": "FeatureCollection",
  "features": [
    {
      "geometry": {
        "type": "Point",
        "coordinates": [
          -90.0333,
          36.2
        ]
      },
      "type": "Feature",
      "properties": {
        "hierarchy": [
          "tgn:2288750",
          "tgn:1000001",
          "tgn:7012149",
          "tgn:2001197",
          "tgn:7007523",
          "tgn:7029392"
        ],
        "placetype": [
          "aat:300006075"
        ],
        "id": 2288750,
        "name:xx": "Ditch Number 19"
      }
    },
    {
      "geometry": {
        "type": "Point",
        "coordinates": [
          -93.8167,
          42.6333
        ]
      },
      "type": "Feature",
      "properties": {
        "hierarchy": [
          "tgn:2288751",
          "tgn:1000001",
          "tgn:7012149",
          "tgn:2000659",
          "tgn:7007253",
          "tgn:7029392"
        ],
        "placetype": [
          "aat:300006075"
        ],
        "id": 2288751,
        "name:xx": "Ditch Number 192"
      }
    },
    {
      "geometry": {
        "type": "Point",
        "coordinates": [
          -93.75,
          42.7
        ]
      },
      "type": "Feature",
      "properties": {
        "hierarchy": [
          "tgn:2288752",
          "tgn:1000001",
          "tgn:7012149",
          "tgn:2000659",
          "tgn:7007253",
          "tgn:7029392"
        ],
        "placetype": [
          "aat:300006075"
        ],
        "id": 2288752,
        "name:xx": "Ditch Number 2"
      }
    },
    {
      "geometry": {
        "type": "Point",
        "coordinates": [
          -93.4833,
          41.7
        ]
      },
      "type": "Feature",
      "properties": {
        "hierarchy": [
          "tgn:2288753",
          "tgn:1000001",
          "tgn:7012149",
          "tgn:2000637",
          "tgn:7007253",
          "tgn:7029392"
        ],
        "placetype": [
          "aat:300006075"
        ],
        "id": 2288753,
        "name:xx": "Ditch Number 2"
      }
    },
    {
      "geometry": {
        "type": "Point",
        "coordinates": [
          -94.7667,
          43.25
        ]
      },
      "type": "Feature",
      "properties": {
        "hierarchy": [
          "tgn:2288754",
          "tgn:1000001",
          "tgn:7012149",
          "tgn:7019181",
          "tgn:7007253",
          "tgn:7029392"
        ],
        "placetype": [
          "aat:300006075"
        ],
        "id": 2288754,
        "name:xx": "Ditch Number 2"
      }
    },
    {
      "geometry": {
        "type": "Point",
        "coordinates": [
          -91.3833,
          41.5
        ]
      },
      "type": "Feature",
      "properties": {
        "hierarchy": [
          "tgn:2288755",
          "tgn:1000001",
          "tgn:7012149",
          "tgn:2000612",
          "tgn:7007253",
          "tgn:7029392"
        ],
        "placetype": [
          "aat:300006075"
        ],
        "id": 2288755,
        "name:xx": "Ditch Number 2"
      }
    },
    {
      "geometry": {
        "type": "Point",
        "coordinates": [
          -93.2833,
          43.4333
        ]
      },
      "type": "Feature",
      "properties": {
        "hierarchy": [
          "tgn:2288756",
          "tgn:1000001",
          "tgn:7012149",
          "tgn:2000658",
          "tgn:7007253",
          "tgn:7029392"
        ],
        "placetype": [
          "aat:300006075"
        ],
        "id": 2288756,
        "name:xx": "Ditch Number 2"
      }
    },
    {
      "geometry": {
        "type": "Point",
        "coordinates": [
          -89.9,
          36.1167
        ]
      },
      "type": "Feature",
      "properties": {
        "hierarchy": [
          "tgn:2288757",
          "tgn:1000001",
          "tgn:7012149",
          "tgn:2001227",
          "tgn:7007523",
          "tgn:7029392"
        ],
        "placetype": [
          "aat:300006075"
        ],
        "id": 2288757,
        "name:xx": "Ditch Number 2"
      }
    },
    {
      "geometry": {
        "type": "Point",
        "coordinates": [
          -90,
          36.0167
        ]
      },
      "type": "Feature",
      "properties": {
        "hierarchy": [
          "tgn:2288758",
          "tgn:1000001",
          "tgn:7012149",
          "tgn:2001197",
          "tgn:7007523",
          "tgn:7029392"
        ],
        "placetype": [
          "aat:300006075"
        ],
        "id": 2288758,
        "name:xx": "Ditch Number 2"
      }
    },
    {
      "geometry": {
        "type": "Point",
        "coordinates": [
          -89.9333,
          36.5
        ]
      },
      "type": "Feature",
      "properties": {
        "hierarchy": [
          "tgn:2288759",
          "tgn:1000001",
          "tgn:7012149",
          "tgn:7007523",
          "tgn:7029392"
        ],
        "placetype": [
          "aat:300006075"
        ],
        "id": 2288759,
        "name:xx": "Ditch Number 2"
      }
    }
  ]
}
