{
  "geometry": {
    "type": "Point",
    "coordinates": [
      17.4333,
      6.0167
    ]
  },
  "type": "Feature",
  "properties": {
    "hierarchy": [
      "tgn:1088440",
      "tgn:7001242",
      "tgn:1001020",
      "tgn:1000155",
      "tgn:7029392"
    ],
    "placetype": [
      "aat:300008347"
    ],
    "id": 1088440,
    "name:xx": "Togho"
  }
}
