{
  "type": "FeatureCollection",
  "features": [
    {
      "geometry": {
        "type": "Point",
        "coordinates": [
          -108,
          37.6667
        ]
      },
      "type": "Feature",
      "properties": {
        "hierarchy": [
          "tgn:2688390",
          "tgn:1000001",
          "tgn:7012149",
          "tgn:2000208",
          "tgn:7007158",
          "tgn:7029392"
        ],
        "placetype": [
          "aat:300008761"
        ],
        "id": 2688390,
        "name:xx": "Spruce Gulch"
      }
    },
    {
      "geometry": {
        "type": "Point",
        "coordinates": [
          -105.25,
          40.55
        ]
      },
      "type": "Feature",
      "properties": {
        "hierarchy": [
          "tgn:2688391",
          "tgn:1000001",
          "tgn:7012149",
          "tgn:2000226",
          "tgn:7007158",
          "tgn:7029392"
        ],
        "placetype": [
          "aat:300008761"
        ],
        "id": 2688391,
        "name:xx": "Spruce Gulch"
      }
    },
    {
      "geometry": {
        "type": "Point",
        "coordinates": [
          -105.35,
          40.1167
        ]
      },
      "type": "Feature",
      "properties": {
        "hierarchy": [
          "tgn:2688392",
          "tgn:1000001",
          "tgn:2000198",
          "tgn:7012149",
          "tgn:7007158",
          "tgn:7029392"
        ],
        "placetype": [
          "aat:300008761"
        ],
        "id": 2688392,
        "name:xx": "Spruce Gulch"
      }
    },
    {
      "geometry": {
        "type": "Point",
        "coordinates": [
          -105.2333,
          39
        ]
      },
      "type": "Feature",
      "properties": {
        "hierarchy": [
          "tgn:2688393",
          "tgn:1000001",
          "tgn:7012149",
          "tgn:7007158",
          "tgn:2000251",
          "tgn:7029392"
        ],
        "placetype": [
          "aat:300008761"
        ],
        "id": 2688393,
        "name:xx": "Spruce Gulch"
      }
    },
    {
      "geometry": {
        "type": "Point",
        "coordinates": [
          -106.2667,
          38.75
        ]
      },
      "type": "Feature",
      "properties": {
        "hierarchy": [
          "tgn:2688394",
          "tgn:1000001",
          "tgn:2000199",
          "tgn:7012149",
          "tgn:7007158",
          "tgn:7029392"
        ],
        "placetype": [
          "aat:300008761"
        ],
        "id": 2688394,
        "name:xx": "Spruce Gulch"
      }
    },
    {
      "geometry": {
        "type": "Point",
        "coordinates": [
          -106.7,
          38.3167
        ]
      },
      "type": "Feature",
      "properties": {
        "hierarchy": [
          "tgn:2688395",
          "tgn:1000001",
          "tgn:7012149",
          "tgn:7007158",
          "tgn:2000246",
          "tgn:7029392"
        ],
        "placetype": [
          "aat:300008761"
        ],
        "id": 2688395,
        "name:xx": "Spruce Gulch"
      }
    },
    {
      "geometry": {
        "type": "Point",
        "coordinates": [
          -114.4167,
          44.4167
        ]
      },
      "type": "Feature",
      "properties": {
        "hierarchy": [
          "tgn:2688396",
          "tgn:1000001",
          "tgn:2000470",
          "tgn:7012149",
          "tgn:7007250",
          "tgn:7029392"
        ],
        "placetype": [
          "aat:300008761"
        ],
        "id": 2688396,
        "name:xx": "Spruce Gulch"
      }
    },
    {
      "geometry": {
        "type": "Point",
        "coordinates": [
          -114.0833,
          45.4667
        ]
      },
      "type": "Feature",
      "properties": {
        "hierarchy": [
          "tgn:2688397",
          "tgn:1000001",
          "tgn:7012149",
          "tgn:2000481",
          "tgn:7007250",
          "tgn:7029392"
        ],
        "placetype": [
          "aat:300008761"
        ],
        "id": 2688397,
        "name:xx": "Spruce Gulch"
      }
    },
    {
      "geometry": {
        "type": "Point",
        "coordinates": [
          -110.8167,
          46.7333
        ]
      },
      "type": "Feature",
      "properties": {
        "hierarchy": [
          "tgn:2688398",
          "tgn:1000001",
          "tgn:7012149",
          "tgn:2001289",
          "tgn:7007524",
          "tgn:7029392"
        ],
        "placetype": [
          "aat:300008761"
        ],
        "id": 2688398,
        "name:xx": "Spruce Gulch"
      }
    },
    {
      "geometry": {
        "type": "Point",
        "coordinates": [
          -112.3833,
          46.1833
        ]
      },
      "type": "Feature",
      "properties": {
        "hierarchy": [
          "tgn:2688399",
          "tgn:1000001",
          "tgn:7012149",
          "tgn:2001281",
          "tgn:7007524",
          "tgn:7029392"
        ],
        "placetype": [
          "aat:300008761"
        ],
        "id": 2688399,
        "name:xx": "Spruce Gulch"
      }
    }
  ]
}
