{
  "geometry": {
    "type": "Point",
    "coordinates": [
      -87.3833,
      35.75
    ]
  },
  "type": "Feature",
  "properties": {
    "hierarchy": [
      "tgn:2325794",
      "tgn:1000001",
      "tgn:7012149",
      "tgn:7015666",
      "tgn:7007825",
      "tgn:7029392"
    ],
    "placetype": [
      "aat:300008699"
    ],
    "id": 2325794,
    "name:xx": "Fielders Branch"
  }
}
