{
  "geometry": {
    "type": "Point",
    "coordinates": [
      -85.2167,
      44.2667
    ]
  },
  "type": "Feature",
  "properties": {
    "hierarchy": [
      "tgn:2712728",
      "tgn:1000001",
      "tgn:7012149",
      "tgn:2000980",
      "tgn:7007520",
      "tgn:7029392"
    ],
    "placetype": [
      "aat:300008706"
    ],
    "id": 2712728,
    "name:xx": "Taylor Creek"
  }
}
