{
  "type": "FeatureCollection",
  "features": [
    {
      "geometry": {
        "type": "Point",
        "coordinates": [
          -2.216667,
          52.85
        ]
      },
      "type": "Feature",
      "properties": {
        "hierarchy": [
          "tgn:7454430",
          "tgn:7002445",
          "tgn:1000003",
          "tgn:7008174",
          "tgn:7008591",
          "tgn:7029392"
        ],
        "placetype": [
          "aat:300008347"
        ],
        "name:en": "Chebsey",
        "id": 7454430
      }
    },
    {
      "geometry": {
        "type": "Point",
        "coordinates": [
          -4.516667,
          56.45
        ]
      },
      "type": "Feature",
      "properties": {
        "hierarchy": [
          "tgn:7454431",
          "tgn:7002444",
          "tgn:1000003",
          "tgn:5000460",
          "tgn:7008591",
          "tgn:7029392"
        ],
        "placetype": [
          "aat:300008795"
        ],
        "name:en": "Cheathaich, Beinn",
        "id": 7454431
      }
    }
  ]
}
