{
  "type": "FeatureCollection",
  "features": [
    {
      "geometry": {
        "type": "Point",
        "coordinates": [
          -74.6167,
          42.45
        ]
      },
      "type": "Feature",
      "properties": {
        "hierarchy": [
          "tgn:2230400",
          "tgn:1000001",
          "tgn:7012149",
          "tgn:7007568",
          "tgn:7029392"
        ],
        "placetype": [
          "aat:300008699"
        ],
        "id": 2230400,
        "name:xx": "Center Brook"
      }
    },
    {
      "geometry": {
        "type": "Point",
        "coordinates": [
          -72.2833,
          44.0333
        ]
      },
      "type": "Feature",
      "properties": {
        "hierarchy": [
          "tgn:2230401",
          "tgn:1000001",
          "tgn:2002134",
          "tgn:7012149",
          "tgn:7007828",
          "tgn:7029392"
        ],
        "placetype": [
          "aat:300008699"
        ],
        "id": 2230401,
        "name:xx": "Center Brook"
      }
    },
    {
      "geometry": {
        "type": "Point",
        "coordinates": [
          -73.45,
          42.9833
        ]
      },
      "type": "Feature",
      "properties": {
        "hierarchy": [
          "tgn:2230402",
          "tgn:1000001",
          "tgn:7012149",
          "tgn:1002993",
          "tgn:7007568",
          "tgn:7029392"
        ],
        "placetype": [
          "aat:300008347"
        ],
        "id": 2230402,
        "name:xx": "Center Cambridge"
      }
    },
    {
      "geometry": {
        "type": "Point",
        "coordinates": [
          -111.0833,
          43.8167
        ]
      },
      "type": "Feature",
      "properties": {
        "hierarchy": [
          "tgn:2230403",
          "tgn:1000001",
          "tgn:7012149",
          "tgn:2000492",
          "tgn:7007250",
          "tgn:7029392"
        ],
        "placetype": [
          "aat:300006075"
        ],
        "id": 2230403,
        "name:xx": "Center Canal"
      }
    },
    {
      "geometry": {
        "type": "Point",
        "coordinates": [
          -116.0333,
          44.6
        ]
      },
      "type": "Feature",
      "properties": {
        "hierarchy": [
          "tgn:2230404",
          "tgn:1000001",
          "tgn:7012149",
          "tgn:2000494",
          "tgn:7007250",
          "tgn:7029392"
        ],
        "placetype": [
          "aat:300006075"
        ],
        "id": 2230404,
        "name:xx": "Center Canal"
      }
    },
    {
      "geometry": {
        "type": "Point",
        "coordinates": [
          -111.9333,
          43.4667
        ]
      },
      "type": "Feature",
      "properties": {
        "hierarchy": [
          "tgn:2230405",
          "tgn:1000001",
          "tgn:2000461",
          "tgn:7012149",
          "tgn:7007250",
          "tgn:7029392"
        ],
        "placetype": [
          "aat:300006075"
        ],
        "id": 2230405,
        "name:xx": "Center Canal"
      }
    },
    {
      "geometry": {
        "type": "Point",
        "coordinates": [
          -121.8,
          42.05
        ]
      },
      "type": "Feature",
      "properties": {
        "hierarchy": [
          "tgn:2230406",
          "tgn:1000001",
          "tgn:7012149",
          "tgn:2001714",
          "tgn:7007708",
          "tgn:7029392"
        ],
        "placetype": [
          "aat:300006075"
        ],
        "id": 2230406,
        "name:xx": "Center Canal"
      }
    },
    {
      "geometry": {
        "type": "Point",
        "coordinates": [
          -118.8333,
          43.0333
        ]
      },
      "type": "Feature",
      "properties": {
        "hierarchy": [
          "tgn:2230407",
          "tgn:1000001",
          "tgn:7012149",
          "tgn:2001709",
          "tgn:7007708",
          "tgn:7029392"
        ],
        "placetype": [
          "aat:300006075"
        ],
        "id": 2230407,
        "name:xx": "Center Canal"
      }
    },
    {
      "geometry": {
        "type": "Point",
        "coordinates": [
          -112.2667,
          37.1
        ]
      },
      "type": "Feature",
      "properties": {
        "hierarchy": [
          "tgn:2230408",
          "tgn:1000001",
          "tgn:7012149",
          "tgn:2002113",
          "tgn:7007827",
          "tgn:7029392"
        ],
        "placetype": [
          "aat:300008761"
        ],
        "id": 2230408,
        "name:xx": "Center Canyon"
      }
    },
    {
      "geometry": {
        "type": "Point",
        "coordinates": [
          -111.1167,
          40.05
        ]
      },
      "type": "Feature",
      "properties": {
        "hierarchy": [
          "tgn:2230409",
          "tgn:1000001",
          "tgn:7012149",
          "tgn:2002126",
          "tgn:7007827",
          "tgn:7029392"
        ],
        "placetype": [
          "aat:300008761"
        ],
        "id": 2230409,
        "name:xx": "Center Canyon"
      }
    }
  ]
}
