{
  "type": "FeatureCollection",
  "features": [
    {
      "geometry": {
        "type": "Point",
        "coordinates": [
          12.9833,
          52.4333
        ]
      },
      "type": "Feature",
      "properties": {
        "hierarchy": [
          "tgn:1004140",
          "tgn:7000096",
          "tgn:1000003",
          "tgn:7000084",
          "tgn:7029392"
        ],
        "placetype": [
          "aat:300000745"
        ],
        "id": 1004140,
        "name:xx": "Bornim"
      }
    },
    {
      "geometry": {
        "type": "Point",
        "coordinates": [
          13.033333,
          52.416667
        ]
      },
      "type": "Feature",
      "properties": {
        "hierarchy": [
          "tgn:1004141",
          "tgn:7000096",
          "tgn:1000003",
          "tgn:7000084",
          "tgn:7029392"
        ],
        "placetype": [
          "aat:300000745"
        ],
        "id": 1004141,
        "name:xx": "Bornstedt"
      }
    },
    {
      "geometry": {
        "type": "Point",
        "coordinates": [
          29.0833,
          40.95
        ]
      },
      "type": "Feature",
      "properties": {
        "hierarchy": [
          "tgn:1004143",
          "tgn:1001052",
          "tgn:1000004",
          "tgn:7002473",
          "tgn:7018450",
          "tgn:1000144",
          "tgn:7029392"
        ],
        "placetype": [
          "aat:300000745"
        ],
        "id": 1004143,
        "name:xx": "Bostancı"
      }
    },
    {
      "geometry": {
        "type": "Point",
        "coordinates": [
          -43.2,
          -22.9667
        ]
      },
      "type": "Feature",
      "properties": {
        "hierarchy": [
          "tgn:1004144",
          "tgn:1001942",
          "tgn:1000047",
          "tgn:7002457",
          "tgn:1000002",
          "tgn:7017095",
          "tgn:7029392"
        ],
        "placetype": [
          "aat:300000745"
        ],
        "id": 1004144,
        "name:xx": "Botafogo"
      }
    },
    {
      "geometry": {
        "type": "Point",
        "coordinates": [
          -0.1167,
          51.6833
        ]
      },
      "type": "Feature",
      "properties": {
        "hierarchy": [
          "tgn:1004145",
          "tgn:7002445",
          "tgn:7018914",
          "tgn:1000003",
          "tgn:7008136",
          "tgn:7008591",
          "tgn:7029392"
        ],
        "placetype": [
          "aat:300000745"
        ],
        "id": 1004145,
        "name:xx": "Botany Bay"
      }
    },
    {
      "geometry": {
        "type": "Point",
        "coordinates": [
          -58.5667,
          -34.5
        ]
      },
      "type": "Feature",
      "properties": {
        "hierarchy": [
          "tgn:1004146",
          "tgn:1001160",
          "tgn:7006477",
          "tgn:1000002",
          "tgn:1136460",
          "tgn:7029392"
        ],
        "placetype": [
          "aat:300000745"
        ],
        "id": 1004146,
        "name:xx": "Boulogne"
      }
    },
    {
      "geometry": {
        "type": "Point",
        "coordinates": [
          29.0333,
          41.1
        ]
      },
      "type": "Feature",
      "properties": {
        "hierarchy": [
          "tgn:1004147",
          "tgn:1001052",
          "tgn:1000004",
          "tgn:7002473",
          "tgn:7018450",
          "tgn:1000144",
          "tgn:7029392"
        ],
        "placetype": [
          "aat:300000745"
        ],
        "id": 1004147,
        "name:xx": "Boyacıköy"
      }
    },
    {
      "geometry": {
        "type": "Point",
        "coordinates": [
          -46.6,
          -23.5333
        ]
      },
      "type": "Feature",
      "properties": {
        "hierarchy": [
          "tgn:1004149",
          "tgn:1001945",
          "tgn:1000047",
          "tgn:7002457",
          "tgn:1000002",
          "tgn:7017121",
          "tgn:7029392"
        ],
        "placetype": [
          "aat:300000745"
        ],
        "id": 1004149,
        "name:xx": "Brás"
      }
    }
  ]
}
