{
  "geometry": {
    "type": "Point",
    "coordinates": [
      -37.7667,
      -11.4833
    ]
  },
  "type": "Feature",
  "properties": {
    "hierarchy": [
      "tgn:1021271",
      "tgn:1001955",
      "tgn:1000047",
      "tgn:7002455",
      "tgn:1000002",
      "tgn:7029392"
    ],
    "placetype": [
      "aat:300008347"
    ],
    "id": 1021271,
    "name:xx": "Cristinápolis"
  }
}
