{
  "geometry": {
    "type": "Point",
    "coordinates": [
      29.983333,
      31.233333
    ]
  },
  "type": "Feature",
  "properties": {
    "hierarchy": [
      "tgn:7536162",
      "tgn:7001242",
      "tgn:7016833",
      "tgn:1001079",
      "tgn:7029392"
    ],
    "placetype": [
      "aat:300007783"
    ],
    "name:en": "Maḩaţţat Ghabriyāl",
    "id": 7536162
  }
}
