{
  "geometry": {
    "type": "Point",
    "coordinates": [
      53.1667,
      55.8667
    ]
  },
  "type": "Feature",
  "properties": {
    "hierarchy": [
      "tgn:1137765",
      "tgn:1000004",
      "tgn:7002435",
      "tgn:7011524",
      "tgn:7029392"
    ],
    "placetype": [
      "aat:300008347"
    ],
    "id": 1137765,
    "name:xx": "Krasnyy Bor"
  }
}
