{
  "geometry": {
    "type": "Point",
    "coordinates": [
      -142.45,
      61.6167
    ]
  },
  "type": "Feature",
  "properties": {
    "hierarchy": [
      "tgn:2542258",
      "tgn:7006450",
      "tgn:1000001",
      "tgn:7012149",
      "tgn:2000086",
      "tgn:7029392"
    ],
    "placetype": [
      "aat:300008835"
    ],
    "id": 2542258,
    "name:xx": "Nizina Glacier"
  }
}
