{
  "geometry": {
    "type": "Point",
    "coordinates": [
      -77.3667,
      41.0167
    ]
  },
  "type": "Feature",
  "properties": {
    "hierarchy": [
      "tgn:2575559",
      "tgn:1000001",
      "tgn:1002286",
      "tgn:7012149",
      "tgn:7007710",
      "tgn:7029392"
    ],
    "placetype": [
      "aat:300008699"
    ],
    "id": 2575559,
    "name:xx": "Pepper Run"
  }
}
