{
  "type": "FeatureCollection",
  "features": [
    {
      "geometry": {
        "type": "Point",
        "coordinates": [
          -90.2167,
          39.7
        ]
      },
      "type": "Feature",
      "properties": {
        "hierarchy": [
          "tgn:2030204",
          "tgn:1000001",
          "tgn:7012149",
          "tgn:1002693",
          "tgn:7007251",
          "tgn:7029392"
        ],
        "placetype": [
          "aat:300008347"
        ],
        "id": 2030204,
        "name:xx": "South Jacksonville"
      }
    },
    {
      "geometry": {
        "type": "Point",
        "coordinates": [
          -89.65,
          40.4833
        ]
      },
      "type": "Feature",
      "properties": {
        "hierarchy": [
          "tgn:2030207",
          "tgn:1000001",
          "tgn:7012149",
          "tgn:2000533",
          "tgn:7007251",
          "tgn:7029392"
        ],
        "placetype": [
          "aat:300008347"
        ],
        "id": 2030207,
        "name:xx": "South Pekin"
      }
    },
    {
      "geometry": {
        "type": "Point",
        "coordinates": [
          -89.8833,
          40.7833
        ]
      },
      "type": "Feature",
      "properties": {
        "hierarchy": [
          "tgn:2030208",
          "tgn:1000001",
          "tgn:7012149",
          "tgn:2000521",
          "tgn:7007251",
          "tgn:7029392"
        ],
        "placetype": [
          "aat:300008347",
          "aat:300387210"
        ],
        "id": 2030208,
        "name:xx": "Southport"
      }
    },
    {
      "geometry": {
        "type": "Point",
        "coordinates": [
          -89.5333,
          40.8333
        ]
      },
      "type": "Feature",
      "properties": {
        "hierarchy": [
          "tgn:2030209",
          "tgn:1000001",
          "tgn:7012149",
          "tgn:2000521",
          "tgn:7007251",
          "tgn:7029392"
        ],
        "placetype": [
          "aat:300008347"
        ],
        "id": 2030209,
        "name:xx": "South Rome"
      }
    }
  ]
}
