{
  "geometry": {
    "type": "Point",
    "coordinates": [
      -54.6167,
      -16.4833
    ]
  },
  "type": "Feature",
  "properties": {
    "hierarchy": [
      "tgn:1022733",
      "tgn:7006260",
      "tgn:7002454",
      "tgn:1000047",
      "tgn:1000002",
      "tgn:7029392"
    ],
    "placetype": [
      "aat:300008347",
      "aat:300008389"
    ],
    "id": 1022733,
    "name:xx": "Rondonópolis"
  }
}
