{
  "geometry": {
    "type": "Point",
    "coordinates": [
      124.8333,
      46.05
    ]
  },
  "type": "Feature",
  "properties": {
    "hierarchy": [
      "tgn:1138887",
      "tgn:1000004",
      "tgn:1001290",
      "tgn:1000111",
      "tgn:7029392"
    ],
    "placetype": [
      "aat:300008347"
    ],
    "id": 1138887,
    "name:xx": "Datong"
  }
}
