{
  "geometry": {
    "type": "Point",
    "coordinates": [
      84.483333,
      19.45
    ]
  },
  "type": "Feature",
  "properties": {
    "hierarchy": [
      "tgn:7558061",
      "tgn:1000004",
      "tgn:7000198",
      "tgn:7016694",
      "tgn:7029392"
    ],
    "placetype": [
      "aat:300008347"
    ],
    "name:en": "Pudāmāri",
    "id": 7558061
  }
}
