{
  "geometry": {
    "type": "Point",
    "coordinates": [
      -100.0167,
      29.1667
    ]
  },
  "type": "Feature",
  "properties": {
    "hierarchy": [
      "tgn:2354527",
      "tgn:1000001",
      "tgn:7012149",
      "tgn:2002087",
      "tgn:7007826",
      "tgn:7029392"
    ],
    "placetype": [
      "aat:300006191"
    ],
    "id": 2354527,
    "name:xx": "Golondrina Waterhole"
  }
}
