{
  "type": "FeatureCollection",
  "features": [
    {
      "geometry": {
        "type": "Point",
        "coordinates": [
          35.7167,
          47.6333
        ]
      },
      "type": "Feature",
      "properties": {
        "hierarchy": [
          "tgn:1137650",
          "tgn:1000003",
          "tgn:7011670",
          "tgn:7006660",
          "tgn:7029392"
        ],
        "placetype": [
          "aat:300008347"
        ],
        "id": 1137650,
        "name:xx": "Kirovo"
      }
    },
    {
      "geometry": {
        "type": "Point",
        "coordinates": [
          37.9167,
          48.3833
        ]
      },
      "type": "Feature",
      "properties": {
        "hierarchy": [
          "tgn:1137651",
          "tgn:7012076",
          "tgn:1000003",
          "tgn:7006660",
          "tgn:7029392"
        ],
        "placetype": [
          "aat:300008347",
          "aat:300008375"
        ],
        "id": 1137651,
        "name:xx": "Kirovo"
      }
    },
    {
      "geometry": {
        "type": "Point",
        "coordinates": [
          38.05,
          48.8333
        ]
      },
      "type": "Feature",
      "properties": {
        "hierarchy": [
          "tgn:1137652",
          "tgn:7012076",
          "tgn:1000003",
          "tgn:7006660",
          "tgn:7029392"
        ],
        "placetype": [
          "aat:300008347",
          "aat:300008375"
        ],
        "id": 1137652,
        "name:xx": "Kirovo"
      }
    },
    {
      "geometry": {
        "type": "Point",
        "coordinates": [
          29.4167,
          51.5
        ]
      },
      "type": "Feature",
      "properties": {
        "hierarchy": [
          "tgn:1137653",
          "tgn:7012187",
          "tgn:1000003",
          "tgn:7006657",
          "tgn:7029392"
        ],
        "placetype": [
          "aat:300008347"
        ],
        "id": 1137653,
        "name:xx": "Kirovo"
      }
    },
    {
      "geometry": {
        "type": "Point",
        "coordinates": [
          63.7667,
          55.55
        ]
      },
      "type": "Feature",
      "properties": {
        "hierarchy": [
          "tgn:1137654",
          "tgn:1000004",
          "tgn:6003227",
          "tgn:7018214",
          "tgn:7002435",
          "tgn:7029392"
        ],
        "placetype": [
          "aat:300008347"
        ],
        "id": 1137654,
        "name:xx": "Kirovo"
      }
    },
    {
      "geometry": {
        "type": "Point",
        "coordinates": [
          48.7167,
          38.7833
        ]
      },
      "type": "Feature",
      "properties": {
        "hierarchy": [
          "tgn:1137655",
          "tgn:7011438",
          "tgn:1000004",
          "tgn:7006646",
          "tgn:7029392"
        ],
        "placetype": [
          "aat:300008347"
        ],
        "id": 1137655,
        "name:xx": "Kirovsk"
      }
    },
    {
      "geometry": {
        "type": "Point",
        "coordinates": [
          38.65,
          48.6333
        ]
      },
      "type": "Feature",
      "properties": {
        "hierarchy": [
          "tgn:1137656",
          "tgn:1000003",
          "tgn:7012067",
          "tgn:7006660",
          "tgn:7029392"
        ],
        "placetype": [
          "aat:300008347"
        ],
        "id": 1137656,
        "name:xx": "Kirovs'k"
      }
    },
    {
      "geometry": {
        "type": "Point",
        "coordinates": [
          37.9333,
          49.0167
        ]
      },
      "type": "Feature",
      "properties": {
        "hierarchy": [
          "tgn:1137657",
          "tgn:7012076",
          "tgn:1000003",
          "tgn:7006660",
          "tgn:7029392"
        ],
        "placetype": [
          "aat:300008347"
        ],
        "id": 1137657,
        "name:xx": "Kirovs'k"
      }
    },
    {
      "geometry": {
        "type": "Point",
        "coordinates": [
          29.4833,
          53.2667
        ]
      },
      "type": "Feature",
      "properties": {
        "hierarchy": [
          "tgn:1137658",
          "tgn:7011700",
          "tgn:1000003",
          "tgn:7006657",
          "tgn:7029392"
        ],
        "placetype": [
          "aat:300008347"
        ],
        "id": 1137658,
        "name:xx": "Kirovsk"
      }
    },
    {
      "geometry": {
        "type": "Point",
        "coordinates": [
          31,
          59.8167
        ]
      },
      "type": "Feature",
      "properties": {
        "hierarchy": [
          "tgn:1137659",
          "tgn:1000004",
          "tgn:7011572",
          "tgn:7018214",
          "tgn:7002435",
          "tgn:7029392"
        ],
        "placetype": [
          "aat:300008347"
        ],
        "id": 1137659,
        "name:xx": "Kirovsk"
      }
    }
  ]
}
