{
  "geometry": {
    "type": "Point",
    "coordinates": [
      -68.6833,
      11.35
    ]
  },
  "type": "Feature",
  "properties": {
    "hierarchy": [
      "tgn:1012601",
      "tgn:1001861",
      "tgn:1000002",
      "tgn:1000059",
      "tgn:7029392"
    ],
    "placetype": [
      "aat:300386846"
    ],
    "id": 1012601,
    "name:xx": "Uvero, Punta"
  }
}
