{
  "geometry": {
    "type": "Point",
    "coordinates": [
      -78.2333,
      38.0167
    ]
  },
  "type": "Feature",
  "properties": {
    "hierarchy": [
      "tgn:2308847",
      "tgn:1000001",
      "tgn:7012149",
      "tgn:2002170",
      "tgn:7007919",
      "tgn:7029392"
    ],
    "placetype": [
      "aat:300008706"
    ],
    "id": 2308847,
    "name:xx": "East Prong Beaverdam Creek"
  }
}
