{
  "geometry": {
    "type": "Point",
    "coordinates": [
      34.179823,
      28.73221
    ]
  },
  "type": "Feature",
  "properties": {
    "hierarchy": [
      "tgn:7544494",
      "tgn:7001242",
      "tgn:7016833",
      "tgn:7001336",
      "tgn:7029392"
    ],
    "placetype": [
      "aat:300379998"
    ],
    "name:en": "Mirad, Wādī",
    "id": 7544494
  }
}
