{
  "type": "FeatureCollection",
  "features": [
    {
      "geometry": {
        "type": "Point",
        "coordinates": [
          -104.216667,
          19.733333
        ]
      },
      "type": "Feature",
      "properties": {
        "hierarchy": [
          "tgn:7374060",
          "tgn:7005586",
          "tgn:1000001",
          "tgn:7005560",
          "tgn:7029392"
        ],
        "placetype": [
          "aat:300008347"
        ],
        "id": 7374060,
        "name:xx": "La Aldaba"
      }
    },
    {
      "geometry": {
        "type": "Point",
        "coordinates": [
          -104.2,
          19.966667
        ]
      },
      "type": "Feature",
      "properties": {
        "hierarchy": [
          "tgn:7374061",
          "tgn:7005586",
          "tgn:1000001",
          "tgn:7005560",
          "tgn:7029392"
        ],
        "placetype": [
          "aat:300008347"
        ],
        "id": 7374061,
        "name:xx": "La Alcaparrosa"
      }
    },
    {
      "geometry": {
        "type": "Point",
        "coordinates": [
          -102.25,
          20.283333
        ]
      },
      "type": "Feature",
      "properties": {
        "hierarchy": [
          "tgn:7374062",
          "tgn:1000001",
          "tgn:7005590",
          "tgn:7005560",
          "tgn:7029392"
        ],
        "placetype": [
          "aat:300006191"
        ],
        "id": 7374062,
        "name:xx": "La Alberca"
      }
    },
    {
      "geometry": {
        "type": "Point",
        "coordinates": [
          -103.316667,
          19.766667
        ]
      },
      "type": "Feature",
      "properties": {
        "hierarchy": [
          "tgn:7374063",
          "tgn:7005586",
          "tgn:1000001",
          "tgn:7005560",
          "tgn:7029392"
        ],
        "placetype": [
          "aat:300000241"
        ],
        "id": 7374063,
        "name:xx": "La Alberca"
      }
    },
    {
      "geometry": {
        "type": "Point",
        "coordinates": [
          -98.966667,
          23.483333
        ]
      },
      "type": "Feature",
      "properties": {
        "hierarchy": [
          "tgn:7374064",
          "tgn:1000001",
          "tgn:7005597",
          "tgn:7005560",
          "tgn:7029392"
        ],
        "placetype": [
          "aat:300008347"
        ],
        "id": 7374064,
        "name:xx": "La Alberca"
      }
    },
    {
      "geometry": {
        "type": "Point",
        "coordinates": [
          -100.566667,
          21.216667
        ]
      },
      "type": "Feature",
      "properties": {
        "hierarchy": [
          "tgn:7374065",
          "tgn:7005584",
          "tgn:1000001",
          "tgn:7005560",
          "tgn:7029392"
        ],
        "placetype": [
          "aat:300008347"
        ],
        "id": 7374065,
        "name:xx": "La Alberca"
      }
    },
    {
      "geometry": {
        "type": "Point",
        "coordinates": [
          -103.15,
          19.8
        ]
      },
      "type": "Feature",
      "properties": {
        "hierarchy": [
          "tgn:7374066",
          "tgn:7005586",
          "tgn:1000001",
          "tgn:7005560",
          "tgn:7029392"
        ],
        "placetype": [
          "aat:300008347"
        ],
        "id": 7374066,
        "name:xx": "La Alberca"
      }
    },
    {
      "geometry": {
        "type": "Point",
        "coordinates": [
          -102.25,
          19.233333
        ]
      },
      "type": "Feature",
      "properties": {
        "hierarchy": [
          "tgn:7374067",
          "tgn:1000001",
          "tgn:7005590",
          "tgn:7005560",
          "tgn:7029392"
        ],
        "placetype": [
          "aat:300008347"
        ],
        "id": 7374067,
        "name:xx": "La Alberca"
      }
    },
    {
      "geometry": {
        "type": "Point",
        "coordinates": [
          -93.416667,
          16.516667
        ]
      },
      "type": "Feature",
      "properties": {
        "hierarchy": [
          "tgn:7374068",
          "tgn:7005580",
          "tgn:1000001",
          "tgn:7005560",
          "tgn:7029392"
        ],
        "placetype": [
          "aat:300008347"
        ],
        "id": 7374068,
        "name:xx": "La Majada"
      }
    },
    {
      "geometry": {
        "type": "Point",
        "coordinates": [
          -94.566667,
          16.3
        ]
      },
      "type": "Feature",
      "properties": {
        "hierarchy": [
          "tgn:7374069",
          "tgn:1000001",
          "tgn:7005591",
          "tgn:7005560",
          "tgn:7029392"
        ],
        "placetype": [
          "aat:300008347"
        ],
        "id": 7374069,
        "name:xx": "La Majada"
      }
    }
  ]
}
