{
  "geometry": {
    "type": "Point",
    "coordinates": [
      -84.7667,
      43.25
    ]
  },
  "type": "Feature",
  "properties": {
    "hierarchy": [
      "tgn:2620468",
      "tgn:1000001",
      "tgn:7012149",
      "tgn:7007520",
      "tgn:7029392"
    ],
    "placetype": [
      "aat:300008699"
    ],
    "id": 2620468,
    "name:xx": "River Styx"
  }
}
