{
  "geometry": {
    "type": "Point",
    "coordinates": [
      -99.9667,
      29.4833
    ]
  },
  "type": "Feature",
  "properties": {
    "hierarchy": [
      "tgn:2429668",
      "tgn:1000001",
      "tgn:7012149",
      "tgn:2002087",
      "tgn:7007826",
      "tgn:7029392"
    ],
    "placetype": [
      "aat:300008761"
    ],
    "id": 2429668,
    "name:xx": "Junor Hollow"
  }
}
