{
  "type": "FeatureCollection",
  "features": [
    {
      "geometry": {
        "type": "Point",
        "coordinates": [
          -99.35,
          21.333333
        ]
      },
      "type": "Feature",
      "properties": {
        "hierarchy": [
          "tgn:7384940",
          "tgn:1000001",
          "tgn:7005593",
          "tgn:7005560",
          "tgn:7029392"
        ],
        "placetype": [
          "aat:300008347"
        ],
        "id": 7384940,
        "name:xx": "Ojo de Agua"
      }
    },
    {
      "geometry": {
        "type": "Point",
        "coordinates": [
          -101.116667,
          21.133333
        ]
      },
      "type": "Feature",
      "properties": {
        "hierarchy": [
          "tgn:7384941",
          "tgn:7005584",
          "tgn:1000001",
          "tgn:7005560",
          "tgn:7029392"
        ],
        "placetype": [
          "aat:300008347"
        ],
        "id": 7384941,
        "name:xx": "Ojo de Agua"
      }
    },
    {
      "geometry": {
        "type": "Point",
        "coordinates": [
          -98.916667,
          21.116667
        ]
      },
      "type": "Feature",
      "properties": {
        "hierarchy": [
          "tgn:7384942",
          "tgn:7005587",
          "tgn:1000001",
          "tgn:7005560",
          "tgn:7029392"
        ],
        "placetype": [
          "aat:300008347"
        ],
        "id": 7384942,
        "name:xx": "Ojo de Agua"
      }
    },
    {
      "geometry": {
        "type": "Point",
        "coordinates": [
          -104.416667,
          21.016667
        ]
      },
      "type": "Feature",
      "properties": {
        "hierarchy": [
          "tgn:7384943",
          "tgn:1000001",
          "tgn:1001906",
          "tgn:7005560",
          "tgn:7029392"
        ],
        "placetype": [
          "aat:300008347"
        ],
        "id": 7384943,
        "name:xx": "Ojo de Agua"
      }
    },
    {
      "geometry": {
        "type": "Point",
        "coordinates": [
          -104.2,
          20.983333
        ]
      },
      "type": "Feature",
      "properties": {
        "hierarchy": [
          "tgn:7384944",
          "tgn:1000001",
          "tgn:1001906",
          "tgn:7005560",
          "tgn:7029392"
        ],
        "placetype": [
          "aat:300008347"
        ],
        "id": 7384944,
        "name:xx": "Ojo de Agua"
      }
    },
    {
      "geometry": {
        "type": "Point",
        "coordinates": [
          -100.016667,
          20.966667
        ]
      },
      "type": "Feature",
      "properties": {
        "hierarchy": [
          "tgn:7384945",
          "tgn:1000001",
          "tgn:7005593",
          "tgn:7005560",
          "tgn:7029392"
        ],
        "placetype": [
          "aat:300008347"
        ],
        "id": 7384945,
        "name:xx": "Ojo de Agua"
      }
    },
    {
      "geometry": {
        "type": "Point",
        "coordinates": [
          -100.416667,
          20.883333
        ]
      },
      "type": "Feature",
      "properties": {
        "hierarchy": [
          "tgn:7384946",
          "tgn:7005584",
          "tgn:1000001",
          "tgn:7005560",
          "tgn:7029392"
        ],
        "placetype": [
          "aat:300008347"
        ],
        "id": 7384946,
        "name:xx": "Ojo de Agua"
      }
    },
    {
      "geometry": {
        "type": "Point",
        "coordinates": [
          -103.033333,
          20.833333
        ]
      },
      "type": "Feature",
      "properties": {
        "hierarchy": [
          "tgn:7384947",
          "tgn:7005586",
          "tgn:1000001",
          "tgn:7005560",
          "tgn:7029392"
        ],
        "placetype": [
          "aat:300008347"
        ],
        "id": 7384947,
        "name:xx": "Ojo de Agua"
      }
    },
    {
      "geometry": {
        "type": "Point",
        "coordinates": [
          -102.216667,
          20.7
        ]
      },
      "type": "Feature",
      "properties": {
        "hierarchy": [
          "tgn:7384948",
          "tgn:7005586",
          "tgn:1000001",
          "tgn:7005560",
          "tgn:7029392"
        ],
        "placetype": [
          "aat:300008347"
        ],
        "id": 7384948,
        "name:xx": "Ojo de Agua"
      }
    },
    {
      "geometry": {
        "type": "Point",
        "coordinates": [
          -102.85,
          20.666667
        ]
      },
      "type": "Feature",
      "properties": {
        "hierarchy": [
          "tgn:7384949",
          "tgn:7005586",
          "tgn:1000001",
          "tgn:7005560",
          "tgn:7029392"
        ],
        "placetype": [
          "aat:300008347"
        ],
        "id": 7384949,
        "name:xx": "Ojo de Agua"
      }
    }
  ]
}
