{
  "geometry": {
    "type": "Point",
    "coordinates": [
      -99.1833,
      33.8833
    ]
  },
  "type": "Feature",
  "properties": {
    "hierarchy": [
      "tgn:2681291",
      "tgn:1000001",
      "tgn:7012149",
      "tgn:2002093",
      "tgn:7007826",
      "tgn:7029392"
    ],
    "placetype": [
      "aat:300006191"
    ],
    "id": 2681291,
    "name:xx": "South Parker Tank"
  }
}
