{
  "geometry": {
    "type": "Point",
    "coordinates": [
      -99.8833,
      40.8167
    ]
  },
  "type": "Feature",
  "properties": {
    "hierarchy": [
      "tgn:2062082",
      "tgn:1000001",
      "tgn:2001339",
      "tgn:7012149",
      "tgn:7007525",
      "tgn:7029392"
    ],
    "placetype": [
      "aat:300008347"
    ],
    "id": 2062082,
    "name:xx": "Darr"
  }
}
