{
  "geometry": {
    "type": "Point",
    "coordinates": [
      33.728397,
      29.736025
    ]
  },
  "type": "Feature",
  "properties": {
    "hierarchy": [
      "tgn:7520654",
      "tgn:7001242",
      "tgn:7016833",
      "tgn:7001336",
      "tgn:7029392"
    ],
    "placetype": [
      "aat:300379998"
    ],
    "id": 7520654,
    "name:xx": "Ab큰 Ad카b, W훮d카"
  }
}
