{
  "type": "FeatureCollection",
  "features": [
    {
      "geometry": {
        "type": "Point",
        "coordinates": [
          -42.8167,
          -22.9167
        ]
      },
      "type": "Feature",
      "properties": {
        "hierarchy": [
          "tgn:7017090",
          "tgn:1001942",
          "tgn:1000047",
          "tgn:7002457",
          "tgn:1000002",
          "tgn:7029392"
        ],
        "placetype": [
          "aat:300008347",
          "aat:300265612",
          "aat:300008375"
        ],
        "id": 7017090,
        "name:xx": "Maricá"
      }
    },
    {
      "geometry": {
        "type": "Point",
        "coordinates": [
          -43.4167,
          -22.8167
        ]
      },
      "type": "Feature",
      "properties": {
        "hierarchy": [
          "tgn:7017091",
          "tgn:1001942",
          "tgn:1000047",
          "tgn:7002457",
          "tgn:1000002",
          "tgn:7029392"
        ],
        "placetype": [
          "aat:300387277",
          "aat:300008347",
          "aat:300008389",
          "aat:300000874",
          "aat:300387302"
        ],
        "id": 7017091,
        "name:xx": "Nilópolis"
      }
    },
    {
      "geometry": {
        "type": "Point",
        "coordinates": [
          -43.1,
          -22.9
        ]
      },
      "type": "Feature",
      "properties": {
        "hierarchy": [
          "tgn:7017092",
          "tgn:1001942",
          "tgn:1000047",
          "tgn:7002457",
          "tgn:1000002",
          "tgn:7029392"
        ],
        "placetype": [
          "aat:300008347",
          "aat:300008389",
          "aat:300000403",
          "aat:300387221",
          "aat:300000874",
          "aat:300387302"
        ],
        "id": 7017092,
        "name:xx": "Niterói"
      }
    },
    {
      "geometry": {
        "type": "Point",
        "coordinates": [
          -43.4667,
          -22.75
        ]
      },
      "type": "Feature",
      "properties": {
        "hierarchy": [
          "tgn:7017093",
          "tgn:1001942",
          "tgn:1000047",
          "tgn:7002457",
          "tgn:1000002",
          "tgn:7029392"
        ],
        "placetype": [
          "aat:300008347",
          "aat:300008389",
          "aat:300265612",
          "aat:300387302"
        ],
        "id": 7017093,
        "name:xx": "Nova Iguaçu"
      }
    },
    {
      "geometry": {
        "type": "Point",
        "coordinates": [
          -43.2833,
          -22.8833
        ]
      },
      "type": "Feature",
      "properties": {
        "hierarchy": [
          "tgn:7017095",
          "tgn:1001942",
          "tgn:1000047",
          "tgn:7002457",
          "tgn:1000002",
          "tgn:7029392"
        ],
        "placetype": [
          "aat:300008347",
          "aat:300008389",
          "aat:300387219",
          "aat:300005135",
          "aat:300387512",
          "aat:300387221",
          "aat:300387302",
          "aat:300120599",
          "aat:300387291"
        ],
        "name:fr": "France Antarctique",
        "name:pt": "França Antartica",
        "id": 7017095
      }
    },
    {
      "geometry": {
        "type": "Point",
        "coordinates": [
          -43.0833,
          -22.8
        ]
      },
      "type": "Feature",
      "properties": {
        "hierarchy": [
          "tgn:7017097",
          "tgn:1001942",
          "tgn:1000047",
          "tgn:7002457",
          "tgn:1000002",
          "tgn:7029392"
        ],
        "placetype": [
          "aat:300008347",
          "aat:300008389",
          "aat:300000874",
          "aat:300387302"
        ],
        "id": 7017097,
        "name:xx": "São Gonçalo"
      }
    },
    {
      "geometry": {
        "type": "Point",
        "coordinates": [
          -43.3667,
          -22.8
        ]
      },
      "type": "Feature",
      "properties": {
        "hierarchy": [
          "tgn:7017098",
          "tgn:1001942",
          "tgn:1000047",
          "tgn:7002457",
          "tgn:1000002",
          "tgn:7029392"
        ],
        "placetype": [
          "aat:300387277",
          "aat:300008347",
          "aat:300008389",
          "aat:300000874",
          "aat:300387302"
        ],
        "id": 7017098,
        "name:xx": "São João de Merití"
      }
    },
    {
      "geometry": {
        "type": "Point",
        "coordinates": [
          -46.3333,
          -23.4
        ]
      },
      "type": "Feature",
      "properties": {
        "hierarchy": [
          "tgn:7017099",
          "tgn:1001945",
          "tgn:1000047",
          "tgn:7002457",
          "tgn:1000002",
          "tgn:7029392"
        ],
        "placetype": [
          "aat:300008347",
          "aat:300000874",
          "aat:300008375"
        ],
        "id": 7017099,
        "name:xx": "Arujá"
      }
    }
  ]
}
