{
  "type": "FeatureCollection",
  "features": [
    {
      "geometry": {
        "type": "Point",
        "coordinates": [
          -74.95,
          40.4
        ]
      },
      "type": "Feature",
      "properties": {
        "hierarchy": [
          "tgn:2064220",
          "tgn:1000001",
          "tgn:1002493",
          "tgn:7012149",
          "tgn:7007565",
          "tgn:7029392"
        ],
        "placetype": [
          "aat:300008347"
        ],
        "id": 2064220,
        "name:xx": "Brookville"
      }
    },
    {
      "geometry": {
        "type": "Point",
        "coordinates": [
          -75.0667,
          39.5167
        ]
      },
      "type": "Feature",
      "properties": {
        "hierarchy": [
          "tgn:2064222",
          "tgn:1000001",
          "tgn:7014449",
          "tgn:7012149",
          "tgn:7007565",
          "tgn:7029392"
        ],
        "placetype": [
          "aat:300008347"
        ],
        "id": 2064222,
        "name:xx": "Brotmanville"
      }
    },
    {
      "geometry": {
        "type": "Point",
        "coordinates": [
          -74.5833,
          39.9667
        ]
      },
      "type": "Feature",
      "properties": {
        "hierarchy": [
          "tgn:2064223",
          "tgn:1002215",
          "tgn:1000001",
          "tgn:7012149",
          "tgn:7007565",
          "tgn:7029392"
        ],
        "placetype": [
          "aat:300008347"
        ],
        "id": 2064223,
        "name:xx": "Browns Mills"
      }
    },
    {
      "geometry": {
        "type": "Point",
        "coordinates": [
          -74.3,
          40.4
        ]
      },
      "type": "Feature",
      "properties": {
        "hierarchy": [
          "tgn:2064224",
          "tgn:1000001",
          "tgn:1002666",
          "tgn:7012149",
          "tgn:7007565",
          "tgn:7029392"
        ],
        "placetype": [
          "aat:300008347"
        ],
        "id": 2064224,
        "name:xx": "Browntown"
      }
    },
    {
      "geometry": {
        "type": "Point",
        "coordinates": [
          -75,
          39.3167
        ]
      },
      "type": "Feature",
      "properties": {
        "hierarchy": [
          "tgn:2064229",
          "tgn:1002309",
          "tgn:1000001",
          "tgn:7012149",
          "tgn:7007565",
          "tgn:7029392"
        ],
        "placetype": [
          "aat:300008347"
        ],
        "id": 2064229,
        "name:xx": "Buckshutem"
      }
    }
  ]
}
