{
  "geometry": {
    "type": "Point",
    "coordinates": [
      10.75,
      54.133333
    ]
  },
  "type": "Feature",
  "properties": {
    "hierarchy": [
      "tgn:7169208",
      "tgn:1000003",
      "tgn:7003688",
      "tgn:7000084",
      "tgn:7029392"
    ],
    "placetype": [
      "aat:300004792"
    ],
    "id": 7169208,
    "name:xx": "Försterei Helle"
  }
}
