{
  "geometry": {
    "type": "Point",
    "coordinates": [
      -4.05,
      37.75
    ]
  },
  "type": "Feature",
  "properties": {
    "hierarchy": [
      "tgn:7334193",
      "tgn:7002758",
      "tgn:1001316",
      "tgn:1000003",
      "tgn:1000095",
      "tgn:7029392"
    ],
    "placetype": [
      "aat:300008347"
    ],
    "id": 7334193,
    "name:xx": "El Madroño"
  }
}
