{
  "geometry": {
    "type": "Point",
    "coordinates": [
      75.6339,
      26.9568
    ]
  },
  "type": "Feature",
  "properties": {
    "hierarchy": [
      "tgn:7559943",
      "tgn:1000004",
      "tgn:7000198",
      "tgn:7016788",
      "tgn:7029392"
    ],
    "placetype": [
      "aat:300008347"
    ],
    "name:en": "Sabrāmpura",
    "id": 7559943
  }
}
