{
  "geometry": {
    "type": "Point",
    "coordinates": [
      -0.4167,
      42.9833
    ]
  },
  "type": "Feature",
  "properties": {
    "hierarchy": [
      "tgn:1033800",
      "tgn:7002878",
      "tgn:1000003",
      "tgn:1000070",
      "tgn:7029392"
    ],
    "placetype": [
      "aat:300008347"
    ],
    "id": 1033800,
    "name:xx": "Laruns"
  }
}
