{
  "type": "FeatureCollection",
  "features": [
    {
      "geometry": {
        "type": "Point",
        "coordinates": [
          12.4,
          50.916667
        ]
      },
      "type": "Feature",
      "properties": {
        "hierarchy": [
          "tgn:7147230",
          "tgn:1000003",
          "tgn:7003689",
          "tgn:7000084",
          "tgn:7029392"
        ],
        "placetype": [
          "aat:300008347"
        ],
        "id": 7147230,
        "name:xx": "Kleinmückern"
      }
    },
    {
      "geometry": {
        "type": "Point",
        "coordinates": [
          11.733333,
          52.6
        ]
      },
      "type": "Feature",
      "properties": {
        "hierarchy": [
          "tgn:7147231",
          "tgn:1000003",
          "tgn:7003687",
          "tgn:7000084",
          "tgn:7029392"
        ],
        "placetype": [
          "aat:300008347"
        ],
        "id": 7147231,
        "name:xx": "Klein Möringen"
      }
    },
    {
      "geometry": {
        "type": "Point",
        "coordinates": [
          7.333333,
          53.516667
        ]
      },
      "type": "Feature",
      "properties": {
        "hierarchy": [
          "tgn:7147232",
          "tgn:1000003",
          "tgn:7003676",
          "tgn:7000084",
          "tgn:7029392"
        ],
        "placetype": [
          "aat:300000206"
        ],
        "id": 7147232,
        "name:xx": "Klein Moorburg"
      }
    },
    {
      "geometry": {
        "type": "Point",
        "coordinates": [
          9.9,
          54.533333
        ]
      },
      "type": "Feature",
      "properties": {
        "hierarchy": [
          "tgn:7147233",
          "tgn:1000003",
          "tgn:7003688",
          "tgn:7000084",
          "tgn:7029392"
        ],
        "placetype": [
          "aat:300000206"
        ],
        "id": 7147233,
        "name:xx": "Klein Moorbrücke"
      }
    },
    {
      "geometry": {
        "type": "Point",
        "coordinates": [
          9.1,
          54.3
        ]
      },
      "type": "Feature",
      "properties": {
        "hierarchy": [
          "tgn:7147234",
          "tgn:1000003",
          "tgn:7003688",
          "tgn:7000084",
          "tgn:7029392"
        ],
        "placetype": [
          "aat:300008347"
        ],
        "id": 7147234,
        "name:xx": "Kleinmoor"
      }
    },
    {
      "geometry": {
        "type": "Point",
        "coordinates": [
          10.033333,
          53.433333
        ]
      },
      "type": "Feature",
      "properties": {
        "hierarchy": [
          "tgn:7147235",
          "tgn:1000003",
          "tgn:7003676",
          "tgn:7000084",
          "tgn:7029392"
        ],
        "placetype": [
          "aat:300008347"
        ],
        "id": 7147235,
        "name:xx": "Klein Moor"
      }
    },
    {
      "geometry": {
        "type": "Point",
        "coordinates": [
          8.916667,
          53.166667
        ]
      },
      "type": "Feature",
      "properties": {
        "hierarchy": [
          "tgn:7147236",
          "tgn:1000003",
          "tgn:7003676",
          "tgn:7000084",
          "tgn:7029392"
        ],
        "placetype": [
          "aat:300008347"
        ],
        "id": 7147236,
        "name:xx": "Kleinmoor"
      }
    },
    {
      "geometry": {
        "type": "Point",
        "coordinates": [
          9.65,
          50.7
        ]
      },
      "type": "Feature",
      "properties": {
        "hierarchy": [
          "tgn:7147237",
          "tgn:1000003",
          "tgn:7003678",
          "tgn:7000084",
          "tgn:7029392"
        ],
        "placetype": [
          "aat:300008347"
        ],
        "id": 7147237,
        "name:xx": "Kleinmoor"
      }
    },
    {
      "geometry": {
        "type": "Point",
        "coordinates": [
          6.666667,
          51
        ]
      },
      "type": "Feature",
      "properties": {
        "hierarchy": [
          "tgn:7147238",
          "tgn:1000003",
          "tgn:7003677",
          "tgn:7000084",
          "tgn:7029392"
        ],
        "placetype": [
          "aat:300008347"
        ],
        "id": 7147238,
        "name:xx": "Klein Mönchhof"
      }
    },
    {
      "geometry": {
        "type": "Point",
        "coordinates": [
          10.883333,
          53.75
        ]
      },
      "type": "Feature",
      "properties": {
        "hierarchy": [
          "tgn:7147239",
          "tgn:1000003",
          "tgn:7000094",
          "tgn:7000084",
          "tgn:7029392"
        ],
        "placetype": [
          "aat:300008347"
        ],
        "id": 7147239,
        "name:xx": "Klein Molzahn"
      }
    }
  ]
}
