{
  "geometry": {
    "type": "Point",
    "coordinates": [
      -104.4167,
      45.3333
    ]
  },
  "type": "Feature",
  "properties": {
    "hierarchy": [
      "tgn:2597401",
      "tgn:1000001",
      "tgn:2001265",
      "tgn:7012149",
      "tgn:7007524",
      "tgn:7029392"
    ],
    "placetype": [
      "aat:300008706"
    ],
    "id": 2597401,
    "name:xx": "Prairie Dog Creek"
  }
}
