{
  "geometry": {
    "type": "Point",
    "coordinates": [
      118.4667,
      31.8667
    ]
  },
  "type": "Feature",
  "properties": {
    "hierarchy": [
      "tgn:1139767",
      "tgn:7002075",
      "tgn:1000004",
      "tgn:1000111",
      "tgn:7029392"
    ],
    "placetype": [
      "aat:300008347"
    ],
    "id": 1139767,
    "name:xx": "Wujiang"
  }
}
