{
  "geometry": {
    "type": "Point",
    "coordinates": [
      -88.7167,
      37.6833
    ]
  },
  "type": "Feature",
  "properties": {
    "hierarchy": [
      "tgn:2194681",
      "tgn:1000001",
      "tgn:7012149",
      "tgn:7007251",
      "tgn:7029392"
    ],
    "placetype": [
      "aat:300008706"
    ],
    "id": 2194681,
    "name:xx": "Brier Creek"
  }
}
