{
  "geometry": {
    "type": "Point",
    "coordinates": [
      142.75,
      42.6667
    ]
  },
  "type": "Feature",
  "properties": {
    "hierarchy": [
      "tgn:1110002",
      "tgn:1000985",
      "tgn:7016529",
      "tgn:7016531",
      "tgn:1000004",
      "tgn:1000120",
      "tgn:7029392"
    ],
    "placetype": [
      "aat:300386831"
    ],
    "id": 1110002,
    "name:xx": "Hidaka-sammyaku"
  }
}
