{
  "geometry": {
    "type": "Point",
    "coordinates": [
      74.412563,
      32.9577
    ]
  },
  "type": "Feature",
  "properties": {
    "hierarchy": [
      "tgn:7591006",
      "tgn:1000004",
      "tgn:7000198",
      "tgn:7000799",
      "tgn:7029392"
    ],
    "placetype": [
      "aat:300008347"
    ],
    "name:en": "Kamāid",
    "id": 7591006
  }
}
