{
  "geometry": {
    "type": "Point",
    "coordinates": [
      -94.2167,
      36.55
    ]
  },
  "type": "Feature",
  "properties": {
    "hierarchy": [
      "tgn:2137490",
      "tgn:1000001",
      "tgn:7012149",
      "tgn:2001216",
      "tgn:7007523",
      "tgn:7029392"
    ],
    "placetype": [
      "aat:300008347"
    ],
    "id": 2137490,
    "name:xx": "Arnett"
  }
}
