{
  "geometry": {
    "type": "Point",
    "coordinates": [
      -97.0833,
      29.7667
    ]
  },
  "type": "Feature",
  "properties": {
    "hierarchy": [
      "tgn:2104229",
      "tgn:1000001",
      "tgn:7012149",
      "tgn:1002374",
      "tgn:7007826",
      "tgn:7029392"
    ],
    "placetype": [
      "aat:300008347",
      "aat:300387210"
    ],
    "id": 2104229,
    "name:xx": "Floy"
  }
}
