{
  "geometry": {
    "type": "Point",
    "coordinates": [
      106.016,
      38.963
    ]
  },
  "type": "Feature",
  "properties": {
    "hierarchy": [
      "tgn:1109113",
      "tgn:1000004",
      "tgn:1000111",
      "tgn:7029392"
    ],
    "placetype": [
      "aat:300386831"
    ],
    "id": 1109113,
    "name:xx": "Helan Shan"
  }
}
