{
  "geometry": {
    "type": "Point",
    "coordinates": [
      32.8167,
      -4.7333
    ]
  },
  "type": "Feature",
  "properties": {
    "hierarchy": [
      "tgn:1094814",
      "tgn:7001242",
      "tgn:7016572",
      "tgn:1000203",
      "tgn:7029392"
    ],
    "placetype": [
      "aat:300008347"
    ],
    "id": 1094814,
    "name:xx": "Nzubuka"
  }
}
