{
  "geometry": {
    "type": "Point",
    "coordinates": [
      -81.4667,
      28.95
    ]
  },
  "type": "Feature",
  "properties": {
    "hierarchy": [
      "tgn:2727287",
      "tgn:1000001",
      "tgn:7012149",
      "tgn:1002567",
      "tgn:7007240",
      "tgn:7029392"
    ],
    "placetype": [
      "aat:300008905"
    ],
    "id": 2727287,
    "name:xx": "Tracy, Lake"
  }
}
