{
  "geometry": {
    "type": "Point",
    "coordinates": [
      -68.9833,
      44.1667
    ]
  },
  "type": "Feature",
  "properties": {
    "hierarchy": [
      "tgn:2492841",
      "tgn:1000001",
      "tgn:2000924",
      "tgn:7012149",
      "tgn:7007515",
      "tgn:7029392"
    ],
    "placetype": [
      "aat:300008791"
    ],
    "id": 2492841,
    "name:xx": "Mark Island"
  }
}
