{
  "geometry": {
    "type": "Point",
    "coordinates": [
      -84.1667,
      42.9833
    ]
  },
  "type": "Feature",
  "properties": {
    "hierarchy": [
      "tgn:2052915",
      "tgn:1000001",
      "tgn:7012149",
      "tgn:1002892",
      "tgn:7007520",
      "tgn:7029392"
    ],
    "placetype": [
      "aat:300008347"
    ],
    "id": 2052915,
    "name:xx": "Owosso"
  }
}
