{
  "geometry": {
    "type": "Point",
    "coordinates": [
      34.300069,
      28.69271
    ]
  },
  "type": "Feature",
  "properties": {
    "hierarchy": [
      "tgn:7542992",
      "tgn:7001242",
      "tgn:7016833",
      "tgn:7001336",
      "tgn:7029392"
    ],
    "placetype": [
      "aat:300008795"
    ],
    "name:en": "Hayyālah, Jabal",
    "id": 7542992
  }
}
