{
  "geometry": {
    "type": "Point",
    "coordinates": [
      -87.1333,
      39.1833
    ]
  },
  "type": "Feature",
  "properties": {
    "hierarchy": [
      "tgn:2483811",
      "tgn:1000001",
      "tgn:2000540",
      "tgn:7012149",
      "tgn:7007252",
      "tgn:7029392"
    ],
    "placetype": [
      "aat:300006075"
    ],
    "id": 2483811,
    "name:xx": "Lateral Number Four"
  }
}
