{
  "geometry": {
    "type": "Point",
    "coordinates": [
      -78.3333,
      40.75
    ]
  },
  "type": "Feature",
  "properties": {
    "hierarchy": [
      "tgn:2631867",
      "tgn:1000001",
      "tgn:1002249",
      "tgn:7012149",
      "tgn:7007710",
      "tgn:7029392"
    ],
    "placetype": [
      "aat:300008699"
    ],
    "id": 2631867,
    "name:xx": "Roup Run"
  }
}
