{
  "geometry": {
    "type": "Point",
    "coordinates": [
      38.8333,
      37.9667
    ]
  },
  "type": "Feature",
  "properties": {
    "hierarchy": [
      "tgn:1086349",
      "tgn:1001060",
      "tgn:1000004",
      "tgn:7018456",
      "tgn:1000144",
      "tgn:7029392"
    ],
    "placetype": [
      "aat:300008347"
    ],
    "id": 1086349,
    "name:xx": "Gerger"
  }
}
