{
  "geometry": {
    "type": "Point",
    "coordinates": [
      16.8333,
      47.1167
    ]
  },
  "type": "Feature",
  "properties": {
    "hierarchy": [
      "tgn:1130190",
      "tgn:1000003",
      "tgn:1000468",
      "tgn:7006278",
      "tgn:7029392"
    ],
    "placetype": [
      "aat:300008707"
    ],
    "id": 1130190,
    "name:xx": "Sorok-patak"
  }
}
