{
  "geometry": {
    "type": "Point",
    "coordinates": [
      -114.2167,
      46.6833
    ]
  },
  "type": "Feature",
  "properties": {
    "hierarchy": [
      "tgn:2221884",
      "tgn:1000001",
      "tgn:7012149",
      "tgn:2001291",
      "tgn:7007524",
      "tgn:7029392"
    ],
    "placetype": [
      "aat:300008680"
    ],
    "id": 2221884,
    "name:xx": "Carlton Lake"
  }
}
