{
  "geometry": {
    "type": "Point",
    "coordinates": [
      -97.95,
      32.9333
    ]
  },
  "type": "Feature",
  "properties": {
    "hierarchy": [
      "tgn:2620003",
      "tgn:1000001",
      "tgn:7012149",
      "tgn:1002771",
      "tgn:7007826",
      "tgn:7029392"
    ],
    "placetype": [
      "aat:300008699"
    ],
    "id": 2620003,
    "name:xx": "Rippy Branch"
  }
}
