{
  "geometry": {
    "type": "Point",
    "coordinates": [
      -77.3667,
      34.75
    ]
  },
  "type": "Feature",
  "properties": {
    "hierarchy": [
      "tgn:2201076",
      "tgn:1000001",
      "tgn:7012149",
      "tgn:2001524",
      "tgn:7007709",
      "tgn:7029392"
    ],
    "placetype": [
      "aat:300008347"
    ],
    "id": 2201076,
    "name:xx": "Brynn Marr"
  }
}
