{
  "geometry": {
    "type": "Point",
    "coordinates": [
      -73.3667,
      42.5667
    ]
  },
  "type": "Feature",
  "properties": {
    "hierarchy": [
      "tgn:2366898",
      "tgn:1000001",
      "tgn:7012149",
      "tgn:1002821",
      "tgn:7007568",
      "tgn:7029392"
    ],
    "placetype": [
      "aat:300008680"
    ],
    "id": 2366898,
    "name:xx": "Griswold Pond"
  }
}
