{
  "geometry": {
    "type": "Point",
    "coordinates": [
      -80.6667,
      26.6833
    ]
  },
  "type": "Feature",
  "properties": {
    "hierarchy": [
      "tgn:2018592",
      "tgn:1000001",
      "tgn:7012149",
      "tgn:1002768",
      "tgn:7007240",
      "tgn:7029392"
    ],
    "placetype": [
      "aat:300008347"
    ],
    "id": 2018592,
    "name:xx": "Belle Glade"
  }
}
