{
  "geometry": {
    "type": "Point",
    "coordinates": [
      -85.7333,
      30.5667
    ]
  },
  "type": "Feature",
  "properties": {
    "hierarchy": [
      "tgn:2322914",
      "tgn:1000001",
      "tgn:7012149",
      "tgn:2000291",
      "tgn:7007240",
      "tgn:7029392"
    ],
    "placetype": [
      "aat:300008699"
    ],
    "id": 2322914,
    "name:xx": "Fanning Branch"
  }
}
