{
  "type": "FeatureCollection",
  "features": [
    {
      "geometry": {
        "type": "Point",
        "coordinates": [
          -108.333333,
          31.333333
        ]
      },
      "type": "Feature",
      "properties": {
        "hierarchy": [
          "tgn:7387200",
          "tgn:1000001",
          "tgn:1001893",
          "tgn:7005560",
          "tgn:7029392"
        ],
        "placetype": [
          "aat:300008777"
        ],
        "id": 7387200,
        "name:xx": "Perro, Sierra del"
      }
    },
    {
      "geometry": {
        "type": "Point",
        "coordinates": [
          -97.833333,
          24.483333
        ]
      },
      "type": "Feature",
      "properties": {
        "hierarchy": [
          "tgn:7387201",
          "tgn:1000001",
          "tgn:7005597",
          "tgn:7005560",
          "tgn:7029392"
        ],
        "placetype": [
          "aat:300008679"
        ],
        "id": 7387201,
        "name:xx": "Perro, Canal del"
      }
    },
    {
      "geometry": {
        "type": "Point",
        "coordinates": [
          -104.35,
          19.366667
        ]
      },
      "type": "Feature",
      "properties": {
        "hierarchy": [
          "tgn:7387202",
          "tgn:7005586",
          "tgn:1000001",
          "tgn:7005560",
          "tgn:7029392"
        ],
        "placetype": [
          "aat:300008795"
        ],
        "id": 7387202,
        "name:xx": "Perote, Sierra"
      }
    },
    {
      "geometry": {
        "type": "Point",
        "coordinates": [
          -104.008333,
          19.366667
        ]
      },
      "type": "Feature",
      "properties": {
        "hierarchy": [
          "tgn:7387203",
          "tgn:7016644",
          "tgn:1000001",
          "tgn:7005560",
          "tgn:7029392"
        ],
        "placetype": [
          "aat:300008795"
        ],
        "id": 7387203,
        "name:xx": "Perote, Sierra"
      }
    },
    {
      "geometry": {
        "type": "Point",
        "coordinates": [
          -104.266667,
          19.666667
        ]
      },
      "type": "Feature",
      "properties": {
        "hierarchy": [
          "tgn:7387204",
          "tgn:7005586",
          "tgn:1000001",
          "tgn:7005560",
          "tgn:7029392"
        ],
        "placetype": [
          "aat:300008795"
        ],
        "id": 7387204,
        "name:xx": "Perote, Cerro el"
      }
    },
    {
      "geometry": {
        "type": "Point",
        "coordinates": [
          -97.25,
          19.566667
        ]
      },
      "type": "Feature",
      "properties": {
        "hierarchy": [
          "tgn:7387205",
          "tgn:1000001",
          "tgn:7005599",
          "tgn:7005560",
          "tgn:7029392"
        ],
        "placetype": [
          "aat:300007783"
        ],
        "id": 7387205,
        "name:xx": "Perote"
      }
    },
    {
      "geometry": {
        "type": "Point",
        "coordinates": [
          -105,
          27.033333
        ]
      },
      "type": "Feature",
      "properties": {
        "hierarchy": [
          "tgn:7387206",
          "tgn:7005581",
          "tgn:1000001",
          "tgn:7005560",
          "tgn:7029392"
        ],
        "placetype": [
          "aat:300008347"
        ],
        "id": 7387206,
        "name:xx": "Perote"
      }
    },
    {
      "geometry": {
        "type": "Point",
        "coordinates": [
          -102.2,
          25.433333
        ]
      },
      "type": "Feature",
      "properties": {
        "hierarchy": [
          "tgn:7387207",
          "tgn:1001853",
          "tgn:1000001",
          "tgn:7005560",
          "tgn:7029392"
        ],
        "placetype": [
          "aat:300008347"
        ],
        "id": 7387207,
        "name:xx": "Perote"
      }
    },
    {
      "geometry": {
        "type": "Point",
        "coordinates": [
          -100,
          21.766667
        ]
      },
      "type": "Feature",
      "properties": {
        "hierarchy": [
          "tgn:7387208",
          "tgn:1000001",
          "tgn:7005594",
          "tgn:7005560",
          "tgn:7029392"
        ],
        "placetype": [
          "aat:300008347"
        ],
        "id": 7387208,
        "name:xx": "Perote"
      }
    }
  ]
}
