{
  "geometry": {
    "type": "Point",
    "coordinates": [
      79.65521,
      26.963836
    ]
  },
  "type": "Feature",
  "properties": {
    "hierarchy": [
      "tgn:7564141",
      "tgn:1000004",
      "tgn:7000198",
      "tgn:7016722",
      "tgn:7029392"
    ],
    "placetype": [
      "aat:300008347"
    ],
    "name:en": "Sahlāpur",
    "id": 7564141
  }
}
