{
  "type": "FeatureCollection",
  "features": [
    {
      "geometry": {
        "type": "Point",
        "coordinates": [
          10.035278,
          53.56
        ]
      },
      "type": "Feature",
      "properties": {
        "hierarchy": [
          "tgn:7148522",
          "tgn:1000003",
          "tgn:7003673",
          "tgn:7000084",
          "tgn:7029392"
        ],
        "placetype": [
          "aat:300007783"
        ],
        "id": 7148522,
        "name:xx": "Bahnhof Landwehr"
      }
    },
    {
      "geometry": {
        "type": "Point",
        "coordinates": [
          11.866667,
          53.05
        ]
      },
      "type": "Feature",
      "properties": {
        "hierarchy": [
          "tgn:7148523",
          "tgn:7000096",
          "tgn:1000003",
          "tgn:7000084",
          "tgn:7029392"
        ],
        "placetype": [
          "aat:300008699"
        ],
        "id": 7148523,
        "name:xx": "Landwehr"
      }
    },
    {
      "geometry": {
        "type": "Point",
        "coordinates": [
          9.016667,
          52.95
        ]
      },
      "type": "Feature",
      "properties": {
        "hierarchy": [
          "tgn:7148524",
          "tgn:1000003",
          "tgn:7003676",
          "tgn:7000084",
          "tgn:7029392"
        ],
        "placetype": [
          "aat:300008699"
        ],
        "id": 7148524,
        "name:xx": "Landwehr"
      }
    },
    {
      "geometry": {
        "type": "Point",
        "coordinates": [
          8.15,
          52.633333
        ]
      },
      "type": "Feature",
      "properties": {
        "hierarchy": [
          "tgn:7148525",
          "tgn:1000003",
          "tgn:7003676",
          "tgn:7000084",
          "tgn:7029392"
        ],
        "placetype": [
          "aat:300008699"
        ],
        "id": 7148525,
        "name:xx": "Landwehr"
      }
    },
    {
      "geometry": {
        "type": "Point",
        "coordinates": [
          9.783333,
          52.3
        ]
      },
      "type": "Feature",
      "properties": {
        "hierarchy": [
          "tgn:7148526",
          "tgn:1000003",
          "tgn:7003676",
          "tgn:7000084",
          "tgn:7029392"
        ],
        "placetype": [
          "aat:300008699"
        ],
        "id": 7148526,
        "name:xx": "Landwehr"
      }
    },
    {
      "geometry": {
        "type": "Point",
        "coordinates": [
          12.6,
          51.85
        ]
      },
      "type": "Feature",
      "properties": {
        "hierarchy": [
          "tgn:7148528",
          "tgn:1000003",
          "tgn:7003687",
          "tgn:7000084",
          "tgn:7029392"
        ],
        "placetype": [
          "aat:300008699"
        ],
        "id": 7148528,
        "name:xx": "Landwehr"
      }
    },
    {
      "geometry": {
        "type": "Point",
        "coordinates": [
          10.466667,
          51.15
        ]
      },
      "type": "Feature",
      "properties": {
        "hierarchy": [
          "tgn:7148529",
          "tgn:1000003",
          "tgn:7003689",
          "tgn:7000084",
          "tgn:7029392"
        ],
        "placetype": [
          "aat:300008699"
        ],
        "id": 7148529,
        "name:xx": "Landwehr"
      }
    }
  ]
}
