{
  "geometry": {
    "type": "Point",
    "coordinates": [
      39.8667,
      21.4167
    ]
  },
  "type": "Feature",
  "properties": {
    "hierarchy": [
      "tgn:1084896",
      "tgn:7000679",
      "tgn:7003866",
      "tgn:1000004",
      "tgn:1000137",
      "tgn:7029392"
    ],
    "placetype": [
      "aat:300008347"
    ],
    "id": 1084896,
    "name:xx": "Munā"
  }
}
