{
  "geometry": {
    "type": "Point",
    "coordinates": [
      -88.25,
      32.9833
    ]
  },
  "type": "Feature",
  "properties": {
    "hierarchy": [
      "tgn:2627587",
      "tgn:7002659",
      "tgn:1000001",
      "tgn:7012149",
      "tgn:2000059",
      "tgn:7029392"
    ],
    "placetype": [
      "aat:300008706"
    ],
    "id": 2627587,
    "name:xx": "Rogers Creek"
  }
}
