{
  "geometry": {
    "type": "Point",
    "coordinates": [
      -85.9833,
      41.0167
    ]
  },
  "type": "Feature",
  "properties": {
    "hierarchy": [
      "tgn:2741068",
      "tgn:1000001",
      "tgn:7012149",
      "tgn:1002396",
      "tgn:7007252",
      "tgn:7029392"
    ],
    "placetype": [
      "aat:300008680"
    ],
    "id": 2741068,
    "name:xx": "Upper Summit Lake"
  }
}
