{
  "geometry": {
    "type": "Point",
    "coordinates": [
      74.089731,
      34.316339
    ]
  },
  "type": "Feature",
  "properties": {
    "hierarchy": [
      "tgn:7586686",
      "tgn:1000004",
      "tgn:7000198",
      "tgn:7000799",
      "tgn:7029392"
    ],
    "placetype": [
      "aat:300008699"
    ],
    "name:en": "Batānwāla Nār",
    "id": 7586686
  }
}
