{
  "type": "FeatureCollection",
  "features": [
    {
      "geometry": {
        "type": "Point",
        "coordinates": [
          -78.5833,
          35.8667
        ]
      },
      "type": "Feature",
      "properties": {
        "hierarchy": [
          "tgn:2342420",
          "tgn:1000001",
          "tgn:7012149",
          "tgn:2001548",
          "tgn:7007709",
          "tgn:7029392"
        ],
        "placetype": [
          "aat:300006191"
        ],
        "id": 2342420,
        "name:xx": "Fuller Pond"
      }
    },
    {
      "geometry": {
        "type": "Point",
        "coordinates": [
          -81.35,
          33.2
        ]
      },
      "type": "Feature",
      "properties": {
        "hierarchy": [
          "tgn:2342421",
          "tgn:2001730",
          "tgn:1000001",
          "tgn:7012149",
          "tgn:7007712",
          "tgn:7029392"
        ],
        "placetype": [
          "aat:300006191"
        ],
        "id": 2342421,
        "name:xx": "Fuller Pond"
      }
    },
    {
      "geometry": {
        "type": "Point",
        "coordinates": [
          -111.7833,
          33.4
        ]
      },
      "type": "Feature",
      "properties": {
        "hierarchy": [
          "tgn:2342422",
          "tgn:1000001",
          "tgn:7006451",
          "tgn:7012149",
          "tgn:2000097",
          "tgn:7029392"
        ],
        "placetype": [
          "aat:300008347"
        ],
        "id": 2342422,
        "name:xx": "Fuller Ranch"
      }
    },
    {
      "geometry": {
        "type": "Point",
        "coordinates": [
          -106.45,
          40.5
        ]
      },
      "type": "Feature",
      "properties": {
        "hierarchy": [
          "tgn:2342423",
          "tgn:1000001",
          "tgn:7012149",
          "tgn:2000220",
          "tgn:7007158",
          "tgn:7029392"
        ],
        "placetype": [
          "aat:300006191"
        ],
        "id": 2342423,
        "name:xx": "Fuller Reservoir"
      }
    },
    {
      "geometry": {
        "type": "Point",
        "coordinates": [
          -114.2167,
          42.35
        ]
      },
      "type": "Feature",
      "properties": {
        "hierarchy": [
          "tgn:2342424",
          "tgn:1000001",
          "tgn:2000467",
          "tgn:7012149",
          "tgn:7007250",
          "tgn:7029392"
        ],
        "placetype": [
          "aat:300006191"
        ],
        "id": 2342424,
        "name:xx": "Fuller Reservoir"
      }
    },
    {
      "geometry": {
        "type": "Point",
        "coordinates": [
          -108.0167,
          43.05
        ]
      },
      "type": "Feature",
      "properties": {
        "hierarchy": [
          "tgn:2342425",
          "tgn:1000001",
          "tgn:7012149",
          "tgn:2002371",
          "tgn:7007923",
          "tgn:7029392"
        ],
        "placetype": [
          "aat:300006191"
        ],
        "id": 2342425,
        "name:xx": "Fuller Reservoir"
      }
    },
    {
      "geometry": {
        "type": "Point",
        "coordinates": [
          -116.7,
          33.8167
        ]
      },
      "type": "Feature",
      "properties": {
        "hierarchy": [
          "tgn:2342426",
          "tgn:1000001",
          "tgn:7012149",
          "tgn:7007157",
          "tgn:1002828",
          "tgn:7029392"
        ],
        "placetype": [
          "aat:300266640"
        ],
        "id": 2342426,
        "name:xx": "Fuller Ridge"
      }
    },
    {
      "geometry": {
        "type": "Point",
        "coordinates": [
          -85.1167,
          35
        ]
      },
      "type": "Feature",
      "properties": {
        "hierarchy": [
          "tgn:2342427",
          "tgn:1000001",
          "tgn:7012149",
          "tgn:2001869",
          "tgn:7007825",
          "tgn:7029392"
        ],
        "placetype": [
          "aat:300266640"
        ],
        "id": 2342427,
        "name:xx": "Fuller Ridge"
      }
    },
    {
      "geometry": {
        "type": "Point",
        "coordinates": [
          -69.8333,
          43.6833
        ]
      },
      "type": "Feature",
      "properties": {
        "hierarchy": [
          "tgn:2342428",
          "tgn:1000001",
          "tgn:7012149",
          "tgn:2000929",
          "tgn:7007515",
          "tgn:7029392"
        ],
        "placetype": [
          "aat:300008791"
        ],
        "id": 2342428,
        "name:xx": "Fuller Rock"
      }
    },
    {
      "geometry": {
        "type": "Point",
        "coordinates": [
          -79,
          41.0667
        ]
      },
      "type": "Feature",
      "properties": {
        "hierarchy": [
          "tgn:2342429",
          "tgn:1000001",
          "tgn:7012149",
          "tgn:1002520",
          "tgn:7007710",
          "tgn:7029392"
        ],
        "placetype": [
          "aat:300008699"
        ],
        "id": 2342429,
        "name:xx": "Fuller Run"
      }
    }
  ]
}
