{
  "type": "FeatureCollection",
  "features": [
    {
      "geometry": {
        "type": "Point",
        "coordinates": [
          -72.816667,
          -45.416667
        ]
      },
      "type": "Feature",
      "properties": {
        "hierarchy": [
          "tgn:7292770",
          "tgn:1001623",
          "tgn:1000049",
          "tgn:1000002",
          "tgn:7029392"
        ],
        "placetype": [
          "aat:300387036"
        ],
        "id": 7292770,
        "name:xx": "Estribor, Banco de"
      }
    },
    {
      "geometry": {
        "type": "Point",
        "coordinates": [
          -71.3,
          -32.516667
        ]
      },
      "type": "Feature",
      "properties": {
        "hierarchy": [
          "tgn:7292771",
          "tgn:1001768",
          "tgn:1000049",
          "tgn:1000002",
          "tgn:7029392"
        ],
        "placetype": [
          "aat:300387200"
        ],
        "id": 7292771,
        "name:xx": "El Tamborcillo"
      }
    },
    {
      "geometry": {
        "type": "Point",
        "coordinates": [
          -72.166667,
          -38.583333
        ]
      },
      "type": "Feature",
      "properties": {
        "hierarchy": [
          "tgn:7292772",
          "tgn:1001692",
          "tgn:1000049",
          "tgn:1000002",
          "tgn:7029392"
        ],
        "placetype": [
          "aat:300008699"
        ],
        "id": 7292772,
        "name:xx": "El Tambor, Estero"
      }
    },
    {
      "geometry": {
        "type": "Point",
        "coordinates": [
          -71.366667,
          -34.6
        ]
      },
      "type": "Feature",
      "properties": {
        "hierarchy": [
          "tgn:7292773",
          "tgn:1001695",
          "tgn:1000049",
          "tgn:1000002",
          "tgn:7029392"
        ],
        "placetype": [
          "aat:300008347"
        ],
        "id": 7292773,
        "name:xx": "El Tambo"
      }
    },
    {
      "geometry": {
        "type": "Point",
        "coordinates": [
          -70.983333,
          -34.483333
        ]
      },
      "type": "Feature",
      "properties": {
        "hierarchy": [
          "tgn:7292774",
          "tgn:1001695",
          "tgn:1000049",
          "tgn:1000002",
          "tgn:7029392"
        ],
        "placetype": [
          "aat:300008347"
        ],
        "id": 7292774,
        "name:xx": "El Tambo"
      }
    },
    {
      "geometry": {
        "type": "Point",
        "coordinates": [
          -70.7,
          -32.766667
        ]
      },
      "type": "Feature",
      "properties": {
        "hierarchy": [
          "tgn:7292775",
          "tgn:1001768",
          "tgn:1000049",
          "tgn:1000002",
          "tgn:7029392"
        ],
        "placetype": [
          "aat:300008347"
        ],
        "id": 7292775,
        "name:xx": "El Tambo"
      }
    },
    {
      "geometry": {
        "type": "Point",
        "coordinates": [
          -70.825556,
          -29.997222
        ]
      },
      "type": "Feature",
      "properties": {
        "hierarchy": [
          "tgn:7292776",
          "tgn:1001657",
          "tgn:1000049",
          "tgn:1000002",
          "tgn:7029392"
        ],
        "placetype": [
          "aat:300008347"
        ],
        "id": 7292776,
        "name:xx": "El Tambo"
      }
    },
    {
      "geometry": {
        "type": "Point",
        "coordinates": [
          -70,
          -18.4
        ]
      },
      "type": "Feature",
      "properties": {
        "hierarchy": [
          "tgn:7292777",
          "tgn:7002464",
          "tgn:1000049",
          "tgn:1000002",
          "tgn:7029392"
        ],
        "placetype": [
          "aat:300008347"
        ],
        "id": 7292777,
        "name:xx": "El Tambo"
      }
    },
    {
      "geometry": {
        "type": "Point",
        "coordinates": [
          -72.95,
          -48.983333
        ]
      },
      "type": "Feature",
      "properties": {
        "hierarchy": [
          "tgn:7292778",
          "tgn:1001623",
          "tgn:1000049",
          "tgn:1000002",
          "tgn:7029392"
        ],
        "placetype": [
          "aat:300387200"
        ],
        "id": 7292778,
        "name:xx": "El Tambo"
      }
    },
    {
      "geometry": {
        "type": "Point",
        "coordinates": [
          -71.016667,
          -31.8
        ]
      },
      "type": "Feature",
      "properties": {
        "hierarchy": [
          "tgn:7292779",
          "tgn:1001657",
          "tgn:1000049",
          "tgn:1000002",
          "tgn:7029392"
        ],
        "placetype": [
          "aat:300000206"
        ],
        "id": 7292779,
        "name:xx": "El Tambo"
      }
    }
  ]
}
