{
  "geometry": {
    "type": "Point",
    "coordinates": [
      8.55,
      51.35
    ]
  },
  "type": "Feature",
  "properties": {
    "hierarchy": [
      "tgn:7212513",
      "tgn:1000003",
      "tgn:7003677",
      "tgn:7000084",
      "tgn:7029392"
    ],
    "placetype": [
      "aat:300008777"
    ],
    "id": 7212513,
    "name:xx": "Bor-Berg"
  }
}
