{
  "type": "FeatureCollection",
  "features": [
    {
      "geometry": {
        "type": "Point",
        "coordinates": [
          -93.4833,
          43.8
        ]
      },
      "type": "Feature",
      "properties": {
        "hierarchy": [
          "tgn:2054610",
          "tgn:1000001",
          "tgn:2001022",
          "tgn:7012149",
          "tgn:7007521",
          "tgn:7029392"
        ],
        "placetype": [
          "aat:300008347"
        ],
        "id": 2054610,
        "name:xx": "Hartland"
      }
    },
    {
      "geometry": {
        "type": "Point",
        "coordinates": [
          -93.6,
          46.6
        ]
      },
      "type": "Feature",
      "properties": {
        "hierarchy": [
          "tgn:2054612",
          "tgn:2000999",
          "tgn:1000001",
          "tgn:7012149",
          "tgn:7007521",
          "tgn:7029392"
        ],
        "placetype": [
          "aat:300008347",
          "aat:300387210"
        ],
        "id": 2054612,
        "name:xx": "Hassman"
      }
    },
    {
      "geometry": {
        "type": "Point",
        "coordinates": [
          -92.85,
          44.7333
        ]
      },
      "type": "Feature",
      "properties": {
        "hierarchy": [
          "tgn:2054613",
          "tgn:1000001",
          "tgn:2001017",
          "tgn:7012149",
          "tgn:7007521",
          "tgn:7029392"
        ],
        "placetype": [
          "aat:300008347"
        ],
        "id": 2054613,
        "name:xx": "Hastings"
      }
    },
    {
      "geometry": {
        "type": "Point",
        "coordinates": [
          -93.9667,
          45.3667
        ]
      },
      "type": "Feature",
      "properties": {
        "hierarchy": [
          "tgn:2054617",
          "tgn:1000001",
          "tgn:7012149",
          "tgn:2001084",
          "tgn:7007521",
          "tgn:7029392"
        ],
        "placetype": [
          "aat:300008347"
        ],
        "id": 2054617,
        "name:xx": "Hasty"
      }
    },
    {
      "geometry": {
        "type": "Point",
        "coordinates": [
          -96.1833,
          43.95
        ]
      },
      "type": "Feature",
      "properties": {
        "hierarchy": [
          "tgn:2054618",
          "tgn:1000001",
          "tgn:7012149",
          "tgn:2001057",
          "tgn:7007521",
          "tgn:7029392"
        ],
        "placetype": [
          "aat:300008347"
        ],
        "id": 2054618,
        "name:xx": "Hatfield"
      }
    },
    {
      "geometry": {
        "type": "Point",
        "coordinates": [
          -93.1333,
          44.05
        ]
      },
      "type": "Feature",
      "properties": {
        "hierarchy": [
          "tgn:2054619",
          "tgn:1000001",
          "tgn:7012149",
          "tgn:2001072",
          "tgn:7007521",
          "tgn:7029392"
        ],
        "placetype": [
          "aat:300008347"
        ],
        "id": 2054619,
        "name:xx": "Havana"
      }
    }
  ]
}
