{
  "geometry": {
    "type": "Point",
    "coordinates": [
      -82.65,
      29.5167
    ]
  },
  "type": "Feature",
  "properties": {
    "hierarchy": [
      "tgn:2692233",
      "tgn:1000001",
      "tgn:7012149",
      "tgn:2000277",
      "tgn:7007240",
      "tgn:7029392"
    ],
    "placetype": [
      "aat:300008680"
    ],
    "id": 2692233,
    "name:xx": "Station Pond"
  }
}
