{
  "geometry": {
    "type": "Point",
    "coordinates": [
      -110.4833,
      33.7333
    ]
  },
  "type": "Feature",
  "properties": {
    "hierarchy": [
      "tgn:2408948",
      "tgn:1000001",
      "tgn:7006451",
      "tgn:2000093",
      "tgn:7012149",
      "tgn:7029392"
    ],
    "placetype": [
      "aat:300008761"
    ],
    "id": 2408948,
    "name:xx": "I S Hole"
  }
}
