{
  "geometry": {
    "type": "Point",
    "coordinates": [
      -76.8333,
      41.9333
    ]
  },
  "type": "Feature",
  "properties": {
    "hierarchy": [
      "tgn:2144115",
      "tgn:1000001",
      "tgn:1002194",
      "tgn:7012149",
      "tgn:7007710",
      "tgn:7029392"
    ],
    "placetype": [
      "aat:300008798"
    ],
    "id": 2144115,
    "name:xx": "Baker Hill"
  }
}
