{
  "type": "FeatureCollection",
  "features": [
    {
      "geometry": {
        "type": "Point",
        "coordinates": [
          9.833333,
          49.283333
        ]
      },
      "type": "Feature",
      "properties": {
        "hierarchy": [
          "tgn:7159430",
          "tgn:7003692",
          "tgn:1000003",
          "tgn:7000084",
          "tgn:7029392"
        ],
        "placetype": [
          "aat:300008805"
        ],
        "id": 7159430,
        "name:xx": "Hohenloher Ebene"
      }
    },
    {
      "geometry": {
        "type": "Point",
        "coordinates": [
          12.233333,
          51.216667
        ]
      },
      "type": "Feature",
      "properties": {
        "hierarchy": [
          "tgn:7159431",
          "tgn:1000003",
          "tgn:7003685",
          "tgn:7000084",
          "tgn:7029392"
        ],
        "placetype": [
          "aat:300008347"
        ],
        "id": 7159431,
        "name:xx": "Hohenlohe"
      }
    },
    {
      "geometry": {
        "type": "Point",
        "coordinates": [
          8.233333,
          48.133333
        ]
      },
      "type": "Feature",
      "properties": {
        "hierarchy": [
          "tgn:7159432",
          "tgn:7003692",
          "tgn:1000003",
          "tgn:7000084",
          "tgn:7029392"
        ],
        "placetype": [
          "aat:300000206"
        ],
        "id": 7159432,
        "name:xx": "Hoflehen"
      }
    },
    {
      "geometry": {
        "type": "Point",
        "coordinates": [
          8.783333,
          48.033333
        ]
      },
      "type": "Feature",
      "properties": {
        "hierarchy": [
          "tgn:7159433",
          "tgn:7003692",
          "tgn:1000003",
          "tgn:7000084",
          "tgn:7029392"
        ],
        "placetype": [
          "aat:300008347"
        ],
        "id": 7159433,
        "name:xx": "Höfle"
      }
    },
    {
      "geometry": {
        "type": "Point",
        "coordinates": [
          10.9,
          47.766667
        ]
      },
      "type": "Feature",
      "properties": {
        "hierarchy": [
          "tgn:7159434",
          "tgn:7003669",
          "tgn:1000003",
          "tgn:7000084",
          "tgn:7029392"
        ],
        "placetype": [
          "aat:300008347"
        ],
        "id": 7159434,
        "name:xx": "Höfle"
      }
    },
    {
      "geometry": {
        "type": "Point",
        "coordinates": [
          8.016667,
          47.75
        ]
      },
      "type": "Feature",
      "properties": {
        "hierarchy": [
          "tgn:7159435",
          "tgn:7003692",
          "tgn:1000003",
          "tgn:7000084",
          "tgn:7029392"
        ],
        "placetype": [
          "aat:300008347"
        ],
        "id": 7159435,
        "name:xx": "Höfle"
      }
    },
    {
      "geometry": {
        "type": "Point",
        "coordinates": [
          9.5,
          48.683333
        ]
      },
      "type": "Feature",
      "properties": {
        "hierarchy": [
          "tgn:7159436",
          "tgn:7003692",
          "tgn:1000003",
          "tgn:7000084",
          "tgn:7029392"
        ],
        "placetype": [
          "aat:300000206"
        ],
        "id": 7159436,
        "name:xx": "Höfle"
      }
    },
    {
      "geometry": {
        "type": "Point",
        "coordinates": [
          8.133333,
          48.483333
        ]
      },
      "type": "Feature",
      "properties": {
        "hierarchy": [
          "tgn:7159437",
          "tgn:7003692",
          "tgn:1000003",
          "tgn:7000084",
          "tgn:7029392"
        ],
        "placetype": [
          "aat:300000206"
        ],
        "id": 7159437,
        "name:xx": "Höfle"
      }
    },
    {
      "geometry": {
        "type": "Point",
        "coordinates": [
          11.166667,
          47.483333
        ]
      },
      "type": "Feature",
      "properties": {
        "hierarchy": [
          "tgn:7159438",
          "tgn:7003669",
          "tgn:1000003",
          "tgn:7000084",
          "tgn:7029392"
        ],
        "placetype": [
          "aat:300000206"
        ],
        "id": 7159438,
        "name:xx": "Höfle"
      }
    },
    {
      "geometry": {
        "type": "Point",
        "coordinates": [
          10.1,
          47.466667
        ]
      },
      "type": "Feature",
      "properties": {
        "hierarchy": [
          "tgn:7159439",
          "tgn:7003669",
          "tgn:1000003",
          "tgn:7000084",
          "tgn:7029392"
        ],
        "placetype": [
          "aat:300000206"
        ],
        "id": 7159439,
        "name:xx": "Höfle"
      }
    }
  ]
}
