{
  "geometry": {
    "type": "Point",
    "coordinates": [
      74.75396,
      31.677147
    ]
  },
  "type": "Feature",
  "properties": {
    "hierarchy": [
      "tgn:7587609",
      "tgn:1000004",
      "tgn:7000198",
      "tgn:7016883",
      "tgn:7029392"
    ],
    "placetype": [
      "aat:300007558"
    ],
    "name:en": "Rām Tīrth",
    "id": 7587609
  }
}
