{
  "geometry": {
    "type": "Point",
    "coordinates": [
      25.55,
      35.25
    ]
  },
  "type": "Feature",
  "properties": {
    "hierarchy": [
      "tgn:7223605",
      "tgn:7002692",
      "tgn:7012056",
      "tgn:1000003",
      "tgn:1000074",
      "tgn:7029392"
    ],
    "placetype": [
      "aat:300008795"
    ],
    "id": 7223605,
    "name:xx": "Selená Óri"
  }
}
