{
  "geometry": {
    "type": "Point",
    "coordinates": [
      -83.0833,
      37.0833
    ]
  },
  "type": "Feature",
  "properties": {
    "hierarchy": [
      "tgn:2281380",
      "tgn:1000001",
      "tgn:7012149",
      "tgn:2000836",
      "tgn:7007255",
      "tgn:7029392"
    ],
    "placetype": [
      "aat:300008699"
    ],
    "id": 2281380,
    "name:xx": "Deephole Branch"
  }
}
