{
  "type": "FeatureCollection",
  "features": [
    {
      "geometry": {
        "type": "Point",
        "coordinates": [
          -118.45,
          45.2333
        ]
      },
      "type": "Feature",
      "properties": {
        "hierarchy": [
          "tgn:2182230",
          "tgn:1000001",
          "tgn:7012149",
          "tgn:2001721",
          "tgn:7007708",
          "tgn:7029392"
        ],
        "placetype": [
          "aat:300008697"
        ],
        "id": 2182230,
        "name:xx": "Blue Mountain Spring"
      }
    },
    {
      "geometry": {
        "type": "Point",
        "coordinates": [
          -108.9167,
          40.3
        ]
      },
      "type": "Feature",
      "properties": {
        "hierarchy": [
          "tgn:2182231",
          "tgn:1000001",
          "tgn:7012149",
          "tgn:2000232",
          "tgn:7007158",
          "tgn:7029392"
        ],
        "placetype": [
          "aat:300008697"
        ],
        "id": 2182231,
        "name:xx": "Blue Mountain Spring Number 1"
      }
    },
    {
      "geometry": {
        "type": "Point",
        "coordinates": [
          -108.95,
          40.3
        ]
      },
      "type": "Feature",
      "properties": {
        "hierarchy": [
          "tgn:2182232",
          "tgn:1000001",
          "tgn:7012149",
          "tgn:2000232",
          "tgn:7007158",
          "tgn:7029392"
        ],
        "placetype": [
          "aat:300008697"
        ],
        "id": 2182232,
        "name:xx": "Blue Mountain Spring Number 2"
      }
    },
    {
      "geometry": {
        "type": "Point",
        "coordinates": [
          -108.9,
          40.3
        ]
      },
      "type": "Feature",
      "properties": {
        "hierarchy": [
          "tgn:2182233",
          "tgn:1000001",
          "tgn:7012149",
          "tgn:2000232",
          "tgn:7007158",
          "tgn:7029392"
        ],
        "placetype": [
          "aat:300008697"
        ],
        "id": 2182233,
        "name:xx": "Blue Mountain Spring Number 3"
      }
    },
    {
      "geometry": {
        "type": "Point",
        "coordinates": [
          -108.9833,
          40.35
        ]
      },
      "type": "Feature",
      "properties": {
        "hierarchy": [
          "tgn:2182234",
          "tgn:1000001",
          "tgn:7012149",
          "tgn:2000232",
          "tgn:7007158",
          "tgn:7029392"
        ],
        "placetype": [
          "aat:300008697"
        ],
        "id": 2182234,
        "name:xx": "Blue Mountain Spring Number 4"
      }
    },
    {
      "geometry": {
        "type": "Point",
        "coordinates": [
          -74.8,
          44.3333
        ]
      },
      "type": "Feature",
      "properties": {
        "hierarchy": [
          "tgn:2182235",
          "tgn:1000001",
          "tgn:7012149",
          "tgn:7016021",
          "tgn:7007568",
          "tgn:7029392"
        ],
        "placetype": [
          "aat:300008699"
        ],
        "id": 2182235,
        "name:xx": "Blue Mountain Stream"
      }
    },
    {
      "geometry": {
        "type": "Point",
        "coordinates": [
          -118.3333,
          44.55
        ]
      },
      "type": "Feature",
      "properties": {
        "hierarchy": [
          "tgn:2182236",
          "tgn:7013349",
          "tgn:1000001",
          "tgn:7012149",
          "tgn:7007708",
          "tgn:7029392"
        ],
        "placetype": [
          "aat:300008798"
        ],
        "id": 2182236,
        "name:xx": "Blue Mountain Summit"
      }
    },
    {
      "geometry": {
        "type": "Point",
        "coordinates": [
          -113.2,
          35.6167
        ]
      },
      "type": "Feature",
      "properties": {
        "hierarchy": [
          "tgn:2182237",
          "tgn:1000001",
          "tgn:7006451",
          "tgn:2000092",
          "tgn:7012149",
          "tgn:7029392"
        ],
        "placetype": [
          "aat:300006191"
        ],
        "id": 2182237,
        "name:xx": "Blue Mountain Tank"
      }
    },
    {
      "geometry": {
        "type": "Point",
        "coordinates": [
          -85.9,
          46.2833
        ]
      },
      "type": "Feature",
      "properties": {
        "hierarchy": [
          "tgn:2182239",
          "tgn:1000001",
          "tgn:7012149",
          "tgn:2000996",
          "tgn:7007520",
          "tgn:7029392"
        ],
        "placetype": [
          "aat:300008798"
        ],
        "id": 2182239,
        "name:xx": "Blue Mountains"
      }
    }
  ]
}
