{
  "type": "FeatureCollection",
  "features": [
    {
      "geometry": {
        "type": "Point",
        "coordinates": [
          -147.5333,
          64.9333
        ]
      },
      "type": "Feature",
      "properties": {
        "hierarchy": [
          "tgn:2317680",
          "tgn:7006450",
          "tgn:1000001",
          "tgn:7019674",
          "tgn:7012149",
          "tgn:7029392"
        ],
        "placetype": [
          "aat:300008706"
        ],
        "id": 2317680,
        "name:xx": "Engineer Creek"
      }
    },
    {
      "geometry": {
        "type": "Point",
        "coordinates": [
          -161.6833,
          61.8167
        ]
      },
      "type": "Feature",
      "properties": {
        "hierarchy": [
          "tgn:2317681",
          "tgn:7006450",
          "tgn:1000001",
          "tgn:7012149",
          "tgn:2000087",
          "tgn:7029392"
        ],
        "placetype": [
          "aat:300008706"
        ],
        "id": 2317681,
        "name:xx": "Engineer Creek"
      }
    },
    {
      "geometry": {
        "type": "Point",
        "coordinates": [
          -122.05,
          43.5833
        ]
      },
      "type": "Feature",
      "properties": {
        "hierarchy": [
          "tgn:2317682",
          "tgn:1000001",
          "tgn:7012149",
          "tgn:2001714",
          "tgn:7007708",
          "tgn:7029392"
        ],
        "placetype": [
          "aat:300008706"
        ],
        "id": 2317682,
        "name:xx": "Engineer Creek"
      }
    },
    {
      "geometry": {
        "type": "Point",
        "coordinates": [
          -161.85,
          61.75
        ]
      },
      "type": "Feature",
      "properties": {
        "hierarchy": [
          "tgn:2317683",
          "tgn:7006450",
          "tgn:1000001",
          "tgn:7012149",
          "tgn:2000087",
          "tgn:7029392"
        ],
        "placetype": [
          "aat:300008798"
        ],
        "id": 2317683,
        "name:xx": "Engineer Hill"
      }
    },
    {
      "geometry": {
        "type": "Point",
        "coordinates": [
          -106.3833,
          31.7667
        ]
      },
      "type": "Feature",
      "properties": {
        "hierarchy": [
          "tgn:2317684",
          "tgn:1000001",
          "tgn:7012149",
          "tgn:2001981",
          "tgn:7007826",
          "tgn:7029392"
        ],
        "placetype": [
          "aat:300008798"
        ],
        "id": 2317684,
        "name:xx": "Engineer Hill"
      }
    },
    {
      "geometry": {
        "type": "Point",
        "coordinates": [
          -150.3167,
          60.4667
        ]
      },
      "type": "Feature",
      "properties": {
        "hierarchy": [
          "tgn:2317685",
          "tgn:7006450",
          "tgn:1000001",
          "tgn:7019698",
          "tgn:7012149",
          "tgn:7029392"
        ],
        "placetype": [
          "aat:300008680"
        ],
        "id": 2317685,
        "name:xx": "Engineer Lake"
      }
    },
    {
      "geometry": {
        "type": "Point",
        "coordinates": [
          -161.7833,
          61.7333
        ]
      },
      "type": "Feature",
      "properties": {
        "hierarchy": [
          "tgn:2317686",
          "tgn:7006450",
          "tgn:1000001",
          "tgn:7012149",
          "tgn:2000087",
          "tgn:7029392"
        ],
        "placetype": [
          "aat:300008680"
        ],
        "id": 2317686,
        "name:xx": "Engineer Lake"
      }
    },
    {
      "geometry": {
        "type": "Point",
        "coordinates": [
          -94.1167,
          35.2667
        ]
      },
      "type": "Feature",
      "properties": {
        "hierarchy": [
          "tgn:2317687",
          "tgn:1000001",
          "tgn:7016172",
          "tgn:7012149",
          "tgn:2000170",
          "tgn:7029392"
        ],
        "placetype": [
          "aat:300006191"
        ],
        "id": 2317687,
        "name:xx": "Engineer Lake"
      }
    },
    {
      "geometry": {
        "type": "Point",
        "coordinates": [
          -93.0667,
          31.1167
        ]
      },
      "type": "Feature",
      "properties": {
        "hierarchy": [
          "tgn:2317688",
          "tgn:1000001",
          "tgn:7012149",
          "tgn:2000911",
          "tgn:7007256",
          "tgn:7029392"
        ],
        "placetype": [
          "aat:300006191"
        ],
        "id": 2317688,
        "name:xx": "Engineer Lake"
      }
    },
    {
      "geometry": {
        "type": "Point",
        "coordinates": [
          -107.5833,
          37.9667
        ]
      },
      "type": "Feature",
      "properties": {
        "hierarchy": [
          "tgn:2317689",
          "tgn:1000001",
          "tgn:7012149",
          "tgn:7007158",
          "tgn:7029392"
        ],
        "placetype": [
          "aat:300008798"
        ],
        "id": 2317689,
        "name:xx": "Engineer Mountain"
      }
    }
  ]
}
