{
  "geometry": {
    "type": "Point",
    "coordinates": [
      -66.029,
      -10.815
    ]
  },
  "type": "Feature",
  "properties": {
    "hierarchy": [
      "tgn:1128165",
      "tgn:1000722",
      "tgn:1000046",
      "tgn:1000002",
      "tgn:7029392"
    ],
    "placetype": [
      "aat:300008707"
    ],
    "id": 1128165,
    "name:xx": "Orthón, Río"
  }
}
