{
  "geometry": {
    "type": "Point",
    "coordinates": [
      -70.3167,
      43.7333
    ]
  },
  "type": "Feature",
  "properties": {
    "hierarchy": [
      "tgn:2517390",
      "tgn:1000001",
      "tgn:2000920",
      "tgn:7012149",
      "tgn:7007515",
      "tgn:7029392"
    ],
    "placetype": [
      "aat:300008699"
    ],
    "id": 2517390,
    "name:xx": "Minnow Brook"
  }
}
