{
  "geometry": {
    "type": "Point",
    "coordinates": [
      48.6667,
      53.4167
    ]
  },
  "type": "Feature",
  "properties": {
    "hierarchy": [
      "tgn:1051654",
      "tgn:1000004",
      "tgn:1003407",
      "tgn:7018214",
      "tgn:7002435",
      "tgn:7029392"
    ],
    "placetype": [
      "aat:300008347"
    ],
    "id": 1051654,
    "name:xx": "Shigony"
  }
}
