{
  "type": "FeatureCollection",
  "features": [
    {
      "geometry": {
        "type": "Point",
        "coordinates": [
          -98.383333,
          24.883333
        ]
      },
      "type": "Feature",
      "properties": {
        "hierarchy": [
          "tgn:7361170",
          "tgn:1000001",
          "tgn:7005597",
          "tgn:7005560",
          "tgn:7029392"
        ],
        "placetype": [
          "aat:300000241"
        ],
        "id": 7361170,
        "name:xx": "Rancho El Ocotillo"
      }
    },
    {
      "geometry": {
        "type": "Point",
        "coordinates": [
          -102.666667,
          20.75
        ]
      },
      "type": "Feature",
      "properties": {
        "hierarchy": [
          "tgn:7361171",
          "tgn:7005586",
          "tgn:1000001",
          "tgn:7005560",
          "tgn:7029392"
        ],
        "placetype": [
          "aat:300000241"
        ],
        "id": 7361171,
        "name:xx": "El Ocotillo"
      }
    },
    {
      "geometry": {
        "type": "Point",
        "coordinates": [
          -104.633333,
          21.216667
        ]
      },
      "type": "Feature",
      "properties": {
        "hierarchy": [
          "tgn:7361172",
          "tgn:1000001",
          "tgn:1001906",
          "tgn:7005560",
          "tgn:7029392"
        ],
        "placetype": [
          "aat:300008347"
        ],
        "id": 7361172,
        "name:xx": "El Ocotillo"
      }
    },
    {
      "geometry": {
        "type": "Point",
        "coordinates": [
          -93.2,
          16.25
        ]
      },
      "type": "Feature",
      "properties": {
        "hierarchy": [
          "tgn:7361173",
          "tgn:7005580",
          "tgn:1000001",
          "tgn:7005560",
          "tgn:7029392"
        ],
        "placetype": [
          "aat:300008347"
        ],
        "id": 7361173,
        "name:xx": "El Ocotillo"
      }
    },
    {
      "geometry": {
        "type": "Point",
        "coordinates": [
          -98.466667,
          24.4
        ]
      },
      "type": "Feature",
      "properties": {
        "hierarchy": [
          "tgn:7361174",
          "tgn:1000001",
          "tgn:7005597",
          "tgn:7005560",
          "tgn:7029392"
        ],
        "placetype": [
          "aat:300008347"
        ],
        "id": 7361174,
        "name:xx": "El Ocotillal"
      }
    },
    {
      "geometry": {
        "type": "Point",
        "coordinates": [
          -102.65,
          19.466667
        ]
      },
      "type": "Feature",
      "properties": {
        "hierarchy": [
          "tgn:7361175",
          "tgn:1000001",
          "tgn:7005590",
          "tgn:7005560",
          "tgn:7029392"
        ],
        "placetype": [
          "aat:300008777"
        ],
        "id": 7361175,
        "name:xx": "El Ocote, Cerro"
      }
    },
    {
      "geometry": {
        "type": "Point",
        "coordinates": [
          -102.083333,
          20.966667
        ]
      },
      "type": "Feature",
      "properties": {
        "hierarchy": [
          "tgn:7361176",
          "tgn:7005586",
          "tgn:1000001",
          "tgn:7005560",
          "tgn:7029392"
        ],
        "placetype": [
          "aat:300000241"
        ],
        "id": 7361176,
        "name:xx": "El Ocote"
      }
    },
    {
      "geometry": {
        "type": "Point",
        "coordinates": [
          -104.033333,
          22.016667
        ]
      },
      "type": "Feature",
      "properties": {
        "hierarchy": [
          "tgn:7361177",
          "tgn:7005586",
          "tgn:1000001",
          "tgn:7005560",
          "tgn:7029392"
        ],
        "placetype": [
          "aat:300008347"
        ],
        "id": 7361177,
        "name:xx": "El Ocote"
      }
    },
    {
      "geometry": {
        "type": "Point",
        "coordinates": [
          -102.833333,
          21.9
        ]
      },
      "type": "Feature",
      "properties": {
        "hierarchy": [
          "tgn:7361178",
          "tgn:7005579",
          "tgn:1000001",
          "tgn:7005560",
          "tgn:7029392"
        ],
        "placetype": [
          "aat:300008347"
        ],
        "id": 7361178,
        "name:xx": "El Ocote"
      }
    },
    {
      "geometry": {
        "type": "Point",
        "coordinates": [
          -103.033333,
          20.583333
        ]
      },
      "type": "Feature",
      "properties": {
        "hierarchy": [
          "tgn:7361179",
          "tgn:7005586",
          "tgn:1000001",
          "tgn:7005560",
          "tgn:7029392"
        ],
        "placetype": [
          "aat:300008347"
        ],
        "id": 7361179,
        "name:xx": "El Ocote"
      }
    }
  ]
}
