{
  "type": "FeatureCollection",
  "features": [
    {
      "geometry": {
        "type": "Point",
        "coordinates": [
          -95.8333,
          34.0667
        ]
      },
      "type": "Feature",
      "properties": {
        "hierarchy": [
          "tgn:2162620",
          "tgn:1000001",
          "tgn:2001634",
          "tgn:7012149",
          "tgn:7007707",
          "tgn:7029392"
        ],
        "placetype": [
          "aat:300008680"
        ],
        "id": 2162620,
        "name:xx": "Bench Lake"
      }
    },
    {
      "geometry": {
        "type": "Point",
        "coordinates": [
          -113.3333,
          37.1333
        ]
      },
      "type": "Feature",
      "properties": {
        "hierarchy": [
          "tgn:2162621",
          "tgn:1000001",
          "tgn:7012149",
          "tgn:2002127",
          "tgn:7007827",
          "tgn:7029392"
        ],
        "placetype": [
          "aat:300008680"
        ],
        "id": 2162621,
        "name:xx": "Bench Lake"
      }
    },
    {
      "geometry": {
        "type": "Point",
        "coordinates": [
          -110.9333,
          40.7
        ]
      },
      "type": "Feature",
      "properties": {
        "hierarchy": [
          "tgn:2162622",
          "tgn:1000001",
          "tgn:7012149",
          "tgn:2002122",
          "tgn:7007827",
          "tgn:7029392"
        ],
        "placetype": [
          "aat:300008680"
        ],
        "id": 2162622,
        "name:xx": "Bench Lake"
      }
    },
    {
      "geometry": {
        "type": "Point",
        "coordinates": [
          -110.7,
          40.7333
        ]
      },
      "type": "Feature",
      "properties": {
        "hierarchy": [
          "tgn:2162623",
          "tgn:1000001",
          "tgn:2002107",
          "tgn:7012149",
          "tgn:7007827",
          "tgn:7029392"
        ],
        "placetype": [
          "aat:300008680"
        ],
        "id": 2162623,
        "name:xx": "Bench Lake"
      }
    },
    {
      "geometry": {
        "type": "Point",
        "coordinates": [
          -121.3833,
          46.15
        ]
      },
      "type": "Feature",
      "properties": {
        "hierarchy": [
          "tgn:2162624",
          "tgn:1000001",
          "tgn:7012149",
          "tgn:1003042",
          "tgn:7007920",
          "tgn:7029392"
        ],
        "placetype": [
          "aat:300008680"
        ],
        "id": 2162624,
        "name:xx": "Bench Lake"
      }
    },
    {
      "geometry": {
        "type": "Point",
        "coordinates": [
          -121.6833,
          46.75
        ]
      },
      "type": "Feature",
      "properties": {
        "hierarchy": [
          "tgn:2162625",
          "tgn:1000001",
          "tgn:7012149",
          "tgn:1002594",
          "tgn:7007920",
          "tgn:7029392"
        ],
        "placetype": [
          "aat:300008680"
        ],
        "id": 2162625,
        "name:xx": "Bench Lake"
      }
    },
    {
      "geometry": {
        "type": "Point",
        "coordinates": [
          -121.1333,
          48.35
        ]
      },
      "type": "Feature",
      "properties": {
        "hierarchy": [
          "tgn:2162626",
          "tgn:1000001",
          "tgn:7012149",
          "tgn:7014510",
          "tgn:7007920",
          "tgn:7029392"
        ],
        "placetype": [
          "aat:300008680"
        ],
        "id": 2162626,
        "name:xx": "Bench Lake"
      }
    },
    {
      "geometry": {
        "type": "Point",
        "coordinates": [
          -121.5,
          47.65
        ]
      },
      "type": "Feature",
      "properties": {
        "hierarchy": [
          "tgn:2162627",
          "tgn:1000001",
          "tgn:7012149",
          "tgn:7018871",
          "tgn:7007920",
          "tgn:7029392"
        ],
        "placetype": [
          "aat:300008680"
        ],
        "id": 2162627,
        "name:xx": "Bench Lake"
      }
    },
    {
      "geometry": {
        "type": "Point",
        "coordinates": [
          -109.7833,
          43.2333
        ]
      },
      "type": "Feature",
      "properties": {
        "hierarchy": [
          "tgn:2162628",
          "tgn:1000001",
          "tgn:7012149",
          "tgn:2002382",
          "tgn:7007923",
          "tgn:7029392"
        ],
        "placetype": [
          "aat:300008680"
        ],
        "id": 2162628,
        "name:xx": "Bench Lake"
      }
    },
    {
      "geometry": {
        "type": "Point",
        "coordinates": [
          -119,
          37.5
        ]
      },
      "type": "Feature",
      "properties": {
        "hierarchy": [
          "tgn:2162629",
          "tgn:1000001",
          "tgn:7012149",
          "tgn:1002392",
          "tgn:7007157",
          "tgn:7029392"
        ],
        "placetype": [
          "aat:300008680"
        ],
        "id": 2162629,
        "name:xx": "Bench Lakes"
      }
    }
  ]
}
