{
  "geometry": {
    "type": "Point",
    "coordinates": [
      31.201389,
      31.515
    ]
  },
  "type": "Feature",
  "properties": {
    "hierarchy": [
      "tgn:7521206",
      "tgn:7001242",
      "tgn:7016833",
      "tgn:1001335",
      "tgn:7029392"
    ],
    "placetype": [
      "aat:300008057"
    ],
    "name:en": "Tall Abū Dukhkhān",
    "id": 7521206
  }
}
