{
  "geometry": {
    "type": "Point",
    "coordinates": [
      -2.066667,
      39.95
    ]
  },
  "type": "Feature",
  "properties": {
    "hierarchy": [
      "tgn:7296849",
      "tgn:7002818",
      "tgn:1001647",
      "tgn:1000003",
      "tgn:1000095",
      "tgn:7029392"
    ],
    "placetype": [
      "aat:300008347"
    ],
    "id": 7296849,
    "name:xx": "Villar del Saz de Arcas"
  }
}
