{
  "geometry": {
    "type": "Point",
    "coordinates": [
      -88.5833,
      43.7667
    ]
  },
  "type": "Feature",
  "properties": {
    "hierarchy": [
      "tgn:2653372",
      "tgn:1000001",
      "tgn:7020939",
      "tgn:7012149",
      "tgn:7007922",
      "tgn:7029392"
    ],
    "placetype": [
      "aat:300008706"
    ],
    "id": 2653372,
    "name:xx": "Sevenmile Creek"
  }
}
