{
  "geometry": {
    "type": "Point",
    "coordinates": [
      -80.85,
      36.3667
    ]
  },
  "type": "Feature",
  "properties": {
    "hierarchy": [
      "tgn:2075779",
      "tgn:1000001",
      "tgn:7012149",
      "tgn:2001542",
      "tgn:7007709",
      "tgn:7029392"
    ],
    "placetype": [
      "aat:300008347",
      "aat:300387210"
    ],
    "id": 2075779,
    "name:xx": "Mountain Park"
  }
}
