{
  "geometry": {
    "type": "Point",
    "coordinates": [
      -101.05,
      33.1833
    ]
  },
  "type": "Feature",
  "properties": {
    "hierarchy": [
      "tgn:2235494",
      "tgn:1000001",
      "tgn:7012149",
      "tgn:2001989",
      "tgn:7007826",
      "tgn:7029392"
    ],
    "placetype": [
      "aat:300006191"
    ],
    "id": 2235494,
    "name:xx": "Chestney Tank"
  }
}
