{
  "geometry": {
    "type": "Point",
    "coordinates": [
      -88.1167,
      46.2167
    ]
  },
  "type": "Feature",
  "properties": {
    "hierarchy": [
      "tgn:2266856",
      "tgn:1000001",
      "tgn:7012149",
      "tgn:7007520",
      "tgn:7029392"
    ],
    "placetype": [
      "aat:300008680"
    ],
    "id": 2266856,
    "name:xx": "Crescent Pond"
  }
}
