{
  "geometry": {
    "type": "Point",
    "coordinates": [
      -79.45,
      36.1833
    ]
  },
  "type": "Feature",
  "properties": {
    "hierarchy": [
      "tgn:2074150",
      "tgn:2001463",
      "tgn:1000001",
      "tgn:7012149",
      "tgn:7007709",
      "tgn:7029392"
    ],
    "placetype": [
      "aat:300008347"
    ],
    "id": 2074150,
    "name:xx": "Clover Garden"
  }
}
