{
  "geometry": {
    "type": "Point",
    "coordinates": [
      -76.7833,
      40.9667
    ]
  },
  "type": "Feature",
  "properties": {
    "hierarchy": [
      "tgn:2441049",
      "tgn:1000001",
      "tgn:7012149",
      "tgn:1002732",
      "tgn:7007710",
      "tgn:7029392"
    ],
    "placetype": [
      "aat:300008798"
    ],
    "id": 2441049,
    "name:xx": "Knobs, The"
  }
}
