{
  "geometry": {
    "type": "Point",
    "coordinates": [
      -91.7167,
      34.65
    ]
  },
  "type": "Feature",
  "properties": {
    "hierarchy": [
      "tgn:2569095",
      "tgn:1000001",
      "tgn:7016172",
      "tgn:7012149",
      "tgn:2000147",
      "tgn:7029392"
    ],
    "placetype": [
      "aat:300008347"
    ],
    "id": 2569095,
    "name:xx": "Parkers Corner"
  }
}
