{
  "type": "FeatureCollection",
  "features": [
    {
      "geometry": {
        "type": "Point",
        "coordinates": [
          -109.6833,
          48.15
        ]
      },
      "type": "Feature",
      "properties": {
        "hierarchy": [
          "tgn:2176840",
          "tgn:1000001",
          "tgn:7012149",
          "tgn:7007524",
          "tgn:7029392"
        ],
        "placetype": [
          "aat:300008798"
        ],
        "id": 2176840,
        "name:xx": "Black Mountain"
      }
    },
    {
      "geometry": {
        "type": "Point",
        "coordinates": [
          -115.0333,
          35.9167
        ]
      },
      "type": "Feature",
      "properties": {
        "hierarchy": [
          "tgn:2176841",
          "tgn:1000001",
          "tgn:2001410",
          "tgn:7012149",
          "tgn:7007526",
          "tgn:7029392"
        ],
        "placetype": [
          "aat:300008798"
        ],
        "id": 2176841,
        "name:xx": "Black Mountain"
      }
    },
    {
      "geometry": {
        "type": "Point",
        "coordinates": [
          -117.45,
          37.3167
        ]
      },
      "type": "Feature",
      "properties": {
        "hierarchy": [
          "tgn:2176842",
          "tgn:1000001",
          "tgn:2001412",
          "tgn:7012149",
          "tgn:7007526",
          "tgn:7029392"
        ],
        "placetype": [
          "aat:300008798"
        ],
        "id": 2176842,
        "name:xx": "Black Mountain"
      }
    },
    {
      "geometry": {
        "type": "Point",
        "coordinates": [
          -114.1,
          37.4333
        ]
      },
      "type": "Feature",
      "properties": {
        "hierarchy": [
          "tgn:2176843",
          "tgn:1000001",
          "tgn:2001416",
          "tgn:7012149",
          "tgn:7007526",
          "tgn:7029392"
        ],
        "placetype": [
          "aat:300008798"
        ],
        "id": 2176843,
        "name:xx": "Black Mountain"
      }
    },
    {
      "geometry": {
        "type": "Point",
        "coordinates": [
          -117.2,
          38.15
        ]
      },
      "type": "Feature",
      "properties": {
        "hierarchy": [
          "tgn:2176844",
          "tgn:1000001",
          "tgn:2001418",
          "tgn:7012149",
          "tgn:7007526",
          "tgn:7029392"
        ],
        "placetype": [
          "aat:300008798"
        ],
        "id": 2176844,
        "name:xx": "Black Mountain"
      }
    },
    {
      "geometry": {
        "type": "Point",
        "coordinates": [
          -119.2833,
          38.5833
        ]
      },
      "type": "Feature",
      "properties": {
        "hierarchy": [
          "tgn:2176845",
          "tgn:1000001",
          "tgn:1002614",
          "tgn:7012149",
          "tgn:7007526",
          "tgn:7029392"
        ],
        "placetype": [
          "aat:300008798"
        ],
        "id": 2176845,
        "name:xx": "Black Mountain"
      }
    },
    {
      "geometry": {
        "type": "Point",
        "coordinates": [
          -118.9,
          38.9333
        ]
      },
      "type": "Feature",
      "properties": {
        "hierarchy": [
          "tgn:2176846",
          "tgn:1000001",
          "tgn:2001417",
          "tgn:7012149",
          "tgn:7007526",
          "tgn:7029392"
        ],
        "placetype": [
          "aat:300008798"
        ],
        "id": 2176846,
        "name:xx": "Black Mountain"
      }
    },
    {
      "geometry": {
        "type": "Point",
        "coordinates": [
          -115.9833,
          40.2167
        ]
      },
      "type": "Feature",
      "properties": {
        "hierarchy": [
          "tgn:2176847",
          "tgn:1000001",
          "tgn:2001411",
          "tgn:7012149",
          "tgn:7007526",
          "tgn:7029392"
        ],
        "placetype": [
          "aat:300008798"
        ],
        "id": 2176847,
        "name:xx": "Black Mountain"
      }
    },
    {
      "geometry": {
        "type": "Point",
        "coordinates": [
          -119.1333,
          41.3167
        ]
      },
      "type": "Feature",
      "properties": {
        "hierarchy": [
          "tgn:2176848",
          "tgn:1000001",
          "tgn:2001414",
          "tgn:7012149",
          "tgn:7007526",
          "tgn:7029392"
        ],
        "placetype": [
          "aat:300008798"
        ],
        "id": 2176848,
        "name:xx": "Black Mountain"
      }
    },
    {
      "geometry": {
        "type": "Point",
        "coordinates": [
          -119.3,
          39.7667
        ]
      },
      "type": "Feature",
      "properties": {
        "hierarchy": [
          "tgn:2176849",
          "tgn:1000001",
          "tgn:7012149",
          "tgn:1002999",
          "tgn:7007526",
          "tgn:7029392"
        ],
        "placetype": [
          "aat:300008798"
        ],
        "id": 2176849,
        "name:xx": "Black Mountain"
      }
    }
  ]
}
