{
  "geometry": {
    "type": "Point",
    "coordinates": [
      -82.5333,
      33.8333
    ]
  },
  "type": "Feature",
  "properties": {
    "hierarchy": [
      "tgn:2512565",
      "tgn:1000001",
      "tgn:7012149",
      "tgn:2000381",
      "tgn:7007248",
      "tgn:7029392"
    ],
    "placetype": [
      "aat:300008706"
    ],
    "id": 2512565,
    "name:xx": "Mill Creek"
  }
}
