{
  "geometry": {
    "type": "Point",
    "coordinates": [
      -111.9167,
      41.1167
    ]
  },
  "type": "Feature",
  "properties": {
    "hierarchy": [
      "tgn:2234877",
      "tgn:1000001",
      "tgn:2002106",
      "tgn:7012149",
      "tgn:7007827",
      "tgn:7029392"
    ],
    "placetype": [
      "aat:300008347"
    ],
    "id": 2234877,
    "name:xx": "Cherry Farm Estates"
  }
}
