{
  "geometry": {
    "type": "Point",
    "coordinates": [
      -75.8167,
      39.65
    ]
  },
  "type": "Feature",
  "properties": {
    "hierarchy": [
      "tgn:7022900",
      "tgn:1002247",
      "tgn:1000001",
      "tgn:7012149",
      "tgn:7007516",
      "tgn:7029392"
    ],
    "placetype": [
      "aat:300008347"
    ],
    "id": 7022900,
    "name:xx": "Elk Mills"
  }
}
