{
  "geometry": {
    "type": "Point",
    "coordinates": [
      11.3333,
      59.55
    ]
  },
  "type": "Feature",
  "properties": {
    "hierarchy": [
      "tgn:1048667",
      "tgn:7003651",
      "tgn:1000003",
      "tgn:1000088",
      "tgn:7029392"
    ],
    "placetype": [
      "aat:300008347"
    ],
    "id": 1048667,
    "name:xx": "Mysen"
  }
}
