{
  "geometry": {
    "type": "Point",
    "coordinates": [
      -121.4167,
      46.4833
    ]
  },
  "type": "Feature",
  "properties": {
    "hierarchy": [
      "tgn:2352660",
      "tgn:1000001",
      "tgn:7012149",
      "tgn:1003042",
      "tgn:7007920",
      "tgn:7029392"
    ],
    "placetype": [
      "aat:300008798"
    ],
    "id": 2352660,
    "name:xx": "Goat Rocks"
  }
}
