{
  "geometry": {
    "type": "Point",
    "coordinates": [
      3.8333,
      45.9167
    ]
  },
  "type": "Feature",
  "properties": {
    "hierarchy": [
      "tgn:1035400",
      "tgn:1000003",
      "tgn:1000070",
      "tgn:7002897",
      "tgn:7029392"
    ],
    "placetype": [
      "aat:300008347"
    ],
    "id": 1035400,
    "name:xx": "Saint-Just-en-Chevalet"
  }
}
