{
  "geometry": {
    "type": "Point",
    "coordinates": [
      -82.4167,
      36.15
    ]
  },
  "type": "Feature",
  "properties": {
    "hierarchy": [
      "tgn:2218163",
      "tgn:1000001",
      "tgn:7012149",
      "tgn:7007825",
      "tgn:7029392"
    ],
    "placetype": [
      "aat:300008761"
    ],
    "id": 2218163,
    "name:xx": "Canah Hollow"
  }
}
