{
  "geometry": {
    "type": "Point",
    "coordinates": [
      19.65,
      43.3833
    ]
  },
  "type": "Feature",
  "properties": {
    "hierarchy": [
      "tgn:1065203",
      "tgn:1000003",
      "tgn:7006669",
      "tgn:7029392"
    ],
    "placetype": [
      "aat:300008347"
    ],
    "id": 1065203,
    "name:xx": "Prijepolje"
  }
}
