{
  "geometry": {
    "type": "Point",
    "coordinates": [
      30.93473,
      30.874163
    ]
  },
  "type": "Feature",
  "properties": {
    "hierarchy": [
      "tgn:7540413",
      "tgn:7001242",
      "tgn:7016833",
      "tgn:7001312",
      "tgn:7029392"
    ],
    "placetype": [
      "aat:300008347"
    ],
    "name:en": "Minshāt al Junaydī",
    "id": 7540413
  }
}
