{
  "geometry": {
    "type": "Point",
    "coordinates": [
      31.776906,
      30.680883
    ]
  },
  "type": "Feature",
  "properties": {
    "hierarchy": [
      "tgn:7523691",
      "tgn:7001242",
      "tgn:7016833",
      "tgn:1001113",
      "tgn:7029392"
    ],
    "placetype": [
      "aat:300008347"
    ],
    "name:en": "Aş Şawāliḩ",
    "id": 7523691
  }
}
