{
  "type": "FeatureCollection",
  "features": [
    {
      "geometry": {
        "type": "Point",
        "coordinates": [
          -82.55,
          32.1833
        ]
      },
      "type": "Feature",
      "properties": {
        "hierarchy": [
          "tgn:2449240",
          "tgn:1000001",
          "tgn:7012149",
          "tgn:2000394",
          "tgn:7007248",
          "tgn:7029392"
        ],
        "placetype": [
          "aat:300008706"
        ],
        "id": 2449240,
        "name:xx": "Limestone Creek"
      }
    },
    {
      "geometry": {
        "type": "Point",
        "coordinates": [
          -83.8,
          32.05
        ]
      },
      "type": "Feature",
      "properties": {
        "hierarchy": [
          "tgn:2449241",
          "tgn:1000001",
          "tgn:7012149",
          "tgn:2000337",
          "tgn:7007248",
          "tgn:7029392"
        ],
        "placetype": [
          "aat:300008706"
        ],
        "id": 2449241,
        "name:xx": "Limestone Creek"
      }
    },
    {
      "geometry": {
        "type": "Point",
        "coordinates": [
          -83.3333,
          32.3667
        ]
      },
      "type": "Feature",
      "properties": {
        "hierarchy": [
          "tgn:2449242",
          "tgn:1000001",
          "tgn:7012149",
          "tgn:7007248",
          "tgn:7029392"
        ],
        "placetype": [
          "aat:300008706"
        ],
        "id": 2449242,
        "name:xx": "Limestone Creek"
      }
    },
    {
      "geometry": {
        "type": "Point",
        "coordinates": [
          -83.7167,
          32.3833
        ]
      },
      "type": "Feature",
      "properties": {
        "hierarchy": [
          "tgn:2449243",
          "tgn:1000001",
          "tgn:7012149",
          "tgn:2000367",
          "tgn:7007248",
          "tgn:7029392"
        ],
        "placetype": [
          "aat:300008706"
        ],
        "id": 2449243,
        "name:xx": "Limestone Creek"
      }
    },
    {
      "geometry": {
        "type": "Point",
        "coordinates": [
          -82.8,
          32.95
        ]
      },
      "type": "Feature",
      "properties": {
        "hierarchy": [
          "tgn:2449244",
          "tgn:1000001",
          "tgn:7012149",
          "tgn:2000441",
          "tgn:7007248",
          "tgn:7029392"
        ],
        "placetype": [
          "aat:300008706"
        ],
        "id": 2449244,
        "name:xx": "Limestone Creek"
      }
    },
    {
      "geometry": {
        "type": "Point",
        "coordinates": [
          -85.2167,
          33.7
        ]
      },
      "type": "Feature",
      "properties": {
        "hierarchy": [
          "tgn:2449245",
          "tgn:1000001",
          "tgn:7012149",
          "tgn:2000362",
          "tgn:7007248",
          "tgn:7029392"
        ],
        "placetype": [
          "aat:300008706"
        ],
        "id": 2449245,
        "name:xx": "Limestone Creek"
      }
    },
    {
      "geometry": {
        "type": "Point",
        "coordinates": [
          -88.9167,
          38.4167
        ]
      },
      "type": "Feature",
      "properties": {
        "hierarchy": [
          "tgn:2449246",
          "tgn:1000001",
          "tgn:7012149",
          "tgn:1002514",
          "tgn:7007251",
          "tgn:7029392"
        ],
        "placetype": [
          "aat:300008706"
        ],
        "id": 2449246,
        "name:xx": "Limestone Creek"
      }
    },
    {
      "geometry": {
        "type": "Point",
        "coordinates": [
          -88.7333,
          38.9333
        ]
      },
      "type": "Feature",
      "properties": {
        "hierarchy": [
          "tgn:2449247",
          "tgn:1000001",
          "tgn:1002349",
          "tgn:7012149",
          "tgn:7007251",
          "tgn:7029392"
        ],
        "placetype": [
          "aat:300008706"
        ],
        "id": 2449247,
        "name:xx": "Limestone Creek"
      }
    },
    {
      "geometry": {
        "type": "Point",
        "coordinates": [
          -88.3667,
          38.9667
        ]
      },
      "type": "Feature",
      "properties": {
        "hierarchy": [
          "tgn:2449248",
          "tgn:1000001",
          "tgn:7012149",
          "tgn:7007251",
          "tgn:7029392"
        ],
        "placetype": [
          "aat:300008706"
        ],
        "id": 2449248,
        "name:xx": "Limestone Creek"
      }
    },
    {
      "geometry": {
        "type": "Point",
        "coordinates": [
          -86.7,
          39.4167
        ]
      },
      "type": "Feature",
      "properties": {
        "hierarchy": [
          "tgn:2449249",
          "tgn:1000001",
          "tgn:7012149",
          "tgn:2000548",
          "tgn:7007252",
          "tgn:7029392"
        ],
        "placetype": [
          "aat:300008706"
        ],
        "id": 2449249,
        "name:xx": "Limestone Creek"
      }
    }
  ]
}
