{
  "geometry": {
    "type": "Point",
    "coordinates": [
      -93.05,
      46.4333
    ]
  },
  "type": "Feature",
  "properties": {
    "hierarchy": [
      "tgn:2628362",
      "tgn:2000999",
      "tgn:1000001",
      "tgn:7012149",
      "tgn:7007521",
      "tgn:7029392"
    ],
    "placetype": [
      "aat:300008347"
    ],
    "id": 2628362,
    "name:xx": "Ronald"
  }
}
