{
  "type": "FeatureCollection",
  "features": [
    {
      "geometry": {
        "type": "Point",
        "coordinates": [
          -68.066667,
          -23.083333
        ]
      },
      "type": "Feature",
      "properties": {
        "hierarchy": [
          "tgn:7280500",
          "tgn:7016598",
          "tgn:1000049",
          "tgn:1000002",
          "tgn:7029392"
        ],
        "placetype": [
          "aat:300008347"
        ],
        "id": 7280500,
        "name:xx": "Tambillo"
      }
    },
    {
      "geometry": {
        "type": "Point",
        "coordinates": [
          -69.166667,
          -20.45
        ]
      },
      "type": "Feature",
      "properties": {
        "hierarchy": [
          "tgn:7280501",
          "tgn:7002464",
          "tgn:1000049",
          "tgn:1000002",
          "tgn:7029392"
        ],
        "placetype": [
          "aat:300008347"
        ],
        "id": 7280501,
        "name:xx": "Tambillo"
      }
    },
    {
      "geometry": {
        "type": "Point",
        "coordinates": [
          -69.4,
          -20.25
        ]
      },
      "type": "Feature",
      "properties": {
        "hierarchy": [
          "tgn:7280502",
          "tgn:7002464",
          "tgn:1000049",
          "tgn:1000002",
          "tgn:7029392"
        ],
        "placetype": [
          "aat:300008347"
        ],
        "id": 7280502,
        "name:xx": "Tambillo"
      }
    },
    {
      "geometry": {
        "type": "Point",
        "coordinates": [
          -68.1,
          -23.116667
        ]
      },
      "type": "Feature",
      "properties": {
        "hierarchy": [
          "tgn:7280503",
          "tgn:7016598",
          "tgn:1000049",
          "tgn:1000002",
          "tgn:7029392"
        ],
        "placetype": [
          "aat:300000517"
        ],
        "id": 7280503,
        "name:xx": "Tambillo"
      }
    },
    {
      "geometry": {
        "type": "Point",
        "coordinates": [
          -69.4,
          -26.733333
        ]
      },
      "type": "Feature",
      "properties": {
        "hierarchy": [
          "tgn:7280504",
          "tgn:1001630",
          "tgn:1000049",
          "tgn:1000002",
          "tgn:7029392"
        ],
        "placetype": [
          "aat:300008795"
        ],
        "id": 7280504,
        "name:xx": "Tambería, Cerro"
      }
    },
    {
      "geometry": {
        "type": "Point",
        "coordinates": [
          -69.7,
          -26.616667
        ]
      },
      "type": "Feature",
      "properties": {
        "hierarchy": [
          "tgn:7280505",
          "tgn:1001630",
          "tgn:1000049",
          "tgn:1000002",
          "tgn:7029392"
        ],
        "placetype": [
          "aat:300008795"
        ],
        "id": 7280505,
        "name:xx": "Tambería, Cerro"
      }
    },
    {
      "geometry": {
        "type": "Point",
        "coordinates": [
          -69.783333,
          -28.466667
        ]
      },
      "type": "Feature",
      "properties": {
        "hierarchy": [
          "tgn:7280506",
          "tgn:1001630",
          "tgn:1000049",
          "tgn:1000002",
          "tgn:7029392"
        ],
        "placetype": [
          "aat:300008347"
        ],
        "id": 7280506,
        "name:xx": "Tambería"
      }
    },
    {
      "geometry": {
        "type": "Point",
        "coordinates": [
          -69.466667,
          -27.866667
        ]
      },
      "type": "Feature",
      "properties": {
        "hierarchy": [
          "tgn:7280507",
          "tgn:1001630",
          "tgn:1000049",
          "tgn:1000002",
          "tgn:7029392"
        ],
        "placetype": [
          "aat:300008347"
        ],
        "id": 7280507,
        "name:xx": "Tambería"
      }
    },
    {
      "geometry": {
        "type": "Point",
        "coordinates": [
          -69.15,
          -26.833333
        ]
      },
      "type": "Feature",
      "properties": {
        "hierarchy": [
          "tgn:7280508",
          "tgn:1001630",
          "tgn:1000049",
          "tgn:1000002",
          "tgn:7029392"
        ],
        "placetype": [
          "aat:300008347"
        ],
        "id": 7280508,
        "name:xx": "Tambería"
      }
    },
    {
      "geometry": {
        "type": "Point",
        "coordinates": [
          -69.583333,
          -28.216667
        ]
      },
      "type": "Feature",
      "properties": {
        "hierarchy": [
          "tgn:7280509",
          "tgn:1001630",
          "tgn:1000049",
          "tgn:1000002",
          "tgn:7029392"
        ],
        "placetype": [
          "aat:300387200"
        ],
        "id": 7280509,
        "name:xx": "Tambería"
      }
    }
  ]
}
