{
  "geometry": {
    "type": "Point",
    "coordinates": [
      17.0333,
      59.3833
    ]
  },
  "type": "Feature",
  "properties": {
    "hierarchy": [
      "tgn:7009862",
      "tgn:1000003",
      "tgn:7003781",
      "tgn:1000097",
      "tgn:7029392"
    ],
    "placetype": [
      "aat:300008347"
    ],
    "id": 7009862,
    "name:xx": "Strängnäs"
  }
}
