{
  "geometry": {
    "type": "Point",
    "coordinates": [
      23.8333,
      46.5833
    ]
  },
  "type": "Feature",
  "properties": {
    "hierarchy": [
      "tgn:7005773",
      "tgn:7004278",
      "tgn:1000003",
      "tgn:1000091",
      "tgn:7029392"
    ],
    "placetype": [
      "aat:300008347",
      "aat:300008375",
      "aat:300387302",
      "aat:300387291"
    ],
    "id": 7005773,
    "name:xx": "Turda"
  }
}
