{
  "type": "FeatureCollection",
  "features": [
    {
      "geometry": {
        "type": "Point",
        "coordinates": [
          -5.083333,
          43.016667
        ]
      },
      "type": "Feature",
      "properties": {
        "hierarchy": [
          "tgn:7339110",
          "tgn:7002826",
          "tgn:7001158",
          "tgn:1000003",
          "tgn:1000095",
          "tgn:7029392"
        ],
        "placetype": [
          "aat:300008798"
        ],
        "id": 7339110,
        "name:xx": "Cruz, Peña"
      }
    },
    {
      "geometry": {
        "type": "Point",
        "coordinates": [
          -1.15,
          42.6
        ]
      },
      "type": "Feature",
      "properties": {
        "hierarchy": [
          "tgn:7339111",
          "tgn:7002759",
          "tgn:7002845",
          "tgn:1000003",
          "tgn:1000095",
          "tgn:7029392"
        ],
        "placetype": [
          "aat:300008795"
        ],
        "id": 7339111,
        "name:xx": "Cruz, Monte"
      }
    },
    {
      "geometry": {
        "type": "Point",
        "coordinates": [
          -4.8,
          38.616667
        ]
      },
      "type": "Feature",
      "properties": {
        "hierarchy": [
          "tgn:7339112",
          "tgn:7002816",
          "tgn:1001647",
          "tgn:1000003",
          "tgn:1000095",
          "tgn:7029392"
        ],
        "placetype": [
          "aat:300259572"
        ],
        "id": 7339112,
        "name:xx": "Cruz, Collado de la"
      }
    },
    {
      "geometry": {
        "type": "Point",
        "coordinates": [
          -2.616667,
          37.616667
        ]
      },
      "type": "Feature",
      "properties": {
        "hierarchy": [
          "tgn:7339113",
          "tgn:7002758",
          "tgn:7002821",
          "tgn:1000003",
          "tgn:1000095",
          "tgn:7029392"
        ],
        "placetype": [
          "aat:300008777"
        ],
        "id": 7339113,
        "name:xx": "Cruz, Cerrillo de la"
      }
    },
    {
      "geometry": {
        "type": "Point",
        "coordinates": [
          -6.166667,
          39.633333
        ]
      },
      "type": "Feature",
      "properties": {
        "hierarchy": [
          "tgn:7339114",
          "tgn:7002811",
          "tgn:1000003",
          "tgn:7003837",
          "tgn:1000095",
          "tgn:7029392"
        ],
        "placetype": [
          "aat:300266554",
          "aat:300008699"
        ],
        "id": 7339114,
        "name:xx": "Cruz, Cañada de la"
      }
    },
    {
      "geometry": {
        "type": "Point",
        "coordinates": [
          -16.35,
          28.3
        ]
      },
      "type": "Feature",
      "properties": {
        "hierarchy": [
          "tgn:7339115",
          "tgn:7002836",
          "tgn:7016622",
          "tgn:1000003",
          "tgn:1000095",
          "tgn:7029392"
        ],
        "placetype": [
          "aat:300132317"
        ],
        "id": 7339115,
        "name:xx": "Cruz, Caleta de la"
      }
    },
    {
      "geometry": {
        "type": "Point",
        "coordinates": [
          -5.2,
          36.933333
        ]
      },
      "type": "Feature",
      "properties": {
        "hierarchy": [
          "tgn:7339116",
          "tgn:7002813",
          "tgn:7002758",
          "tgn:1000003",
          "tgn:1000095",
          "tgn:7029392"
        ],
        "placetype": [
          "aat:300266640"
        ],
        "id": 7339116,
        "name:xx": "Cordillera, Loma de la"
      }
    },
    {
      "geometry": {
        "type": "Point",
        "coordinates": [
          2.766667,
          39.85
        ]
      },
      "type": "Feature",
      "properties": {
        "hierarchy": [
          "tgn:7339118",
          "tgn:7001122",
          "tgn:1000003",
          "tgn:7002765",
          "tgn:1000095",
          "tgn:7029392"
        ],
        "placetype": [
          "aat:300386846"
        ],
        "id": 7339118,
        "name:xx": "Corda, Morro de sa"
      }
    },
    {
      "geometry": {
        "type": "Point",
        "coordinates": [
          -9.15,
          42.9
        ]
      },
      "type": "Feature",
      "properties": {
        "hierarchy": [
          "tgn:7339119",
          "tgn:7002824",
          "tgn:1000003",
          "tgn:7002786",
          "tgn:1000095",
          "tgn:7029392"
        ],
        "placetype": [
          "aat:300266571"
        ],
        "id": 7339119,
        "name:xx": "Corcubión, Ría de"
      }
    }
  ]
}
