{
  "geometry": {
    "type": "Point",
    "coordinates": [
      2.2333,
      41.4833
    ]
  },
  "type": "Feature",
  "properties": {
    "hierarchy": [
      "tgn:1061819",
      "tgn:7002808",
      "tgn:7030216",
      "tgn:1000003",
      "tgn:1000095",
      "tgn:7029392"
    ],
    "placetype": [
      "aat:300008347"
    ],
    "id": 1061819,
    "name:xx": "Barriada Pomar Alto"
  }
}
