{
  "geometry": {
    "type": "Point",
    "coordinates": [
      -101.4333,
      31.9333
    ]
  },
  "type": "Feature",
  "properties": {
    "hierarchy": [
      "tgn:2590860",
      "tgn:1000001",
      "tgn:7012149",
      "tgn:2001991",
      "tgn:7007826",
      "tgn:7029392"
    ],
    "placetype": [
      "aat:300008706"
    ],
    "id": 2590860,
    "name:xx": "Polecat Creek"
  }
}
