{
  "type": "FeatureCollection",
  "features": [
    {
      "geometry": {
        "type": "Point",
        "coordinates": [
          -1.316667,
          53.433333
        ]
      },
      "type": "Feature",
      "properties": {
        "hierarchy": [
          "tgn:7464120",
          "tgn:7019049",
          "tgn:7002445",
          "tgn:1000003",
          "tgn:7029505",
          "tgn:7008591",
          "tgn:7029392"
        ],
        "placetype": [
          "aat:300008347"
        ],
        "name:en": "Aldwarke",
        "id": 7464120
      }
    },
    {
      "geometry": {
        "type": "Point",
        "coordinates": [
          1.583333,
          52.183333
        ]
      },
      "type": "Feature",
      "properties": {
        "hierarchy": [
          "tgn:7464123",
          "tgn:7002445",
          "tgn:1000003",
          "tgn:7008185",
          "tgn:7008591",
          "tgn:7029392"
        ],
        "placetype": [
          "aat:300008347"
        ],
        "name:en": "Aldringham",
        "id": 7464123
      }
    },
    {
      "geometry": {
        "type": "Point",
        "coordinates": [
          -4.316667,
          57.4
        ]
      },
      "type": "Feature",
      "properties": {
        "hierarchy": [
          "tgn:7464125",
          "tgn:7002444",
          "tgn:1000003",
          "tgn:7008082",
          "tgn:7008591",
          "tgn:7029392"
        ],
        "placetype": [
          "aat:300004792"
        ],
        "name:en": "Aldourie Castle",
        "id": 7464125
      }
    },
    {
      "geometry": {
        "type": "Point",
        "coordinates": [
          -4.566667,
          55.2
        ]
      },
      "type": "Feature",
      "properties": {
        "hierarchy": [
          "tgn:7464126",
          "tgn:7002444",
          "tgn:1000003",
          "tgn:7019085",
          "tgn:7008591",
          "tgn:7029392"
        ],
        "placetype": [
          "aat:300008680"
        ],
        "name:en": "Aldinna Loch",
        "id": 7464126
      }
    },
    {
      "geometry": {
        "type": "Point",
        "coordinates": [
          -4.083333,
          57.783333
        ]
      },
      "type": "Feature",
      "properties": {
        "hierarchy": [
          "tgn:7464129",
          "tgn:7002444",
          "tgn:1000003",
          "tgn:7008082",
          "tgn:7008591",
          "tgn:7029392"
        ],
        "placetype": [
          "aat:300008761"
        ],
        "name:en": "Aldie, Glen",
        "id": 7464129
      }
    }
  ]
}
