{
  "geometry": {
    "type": "Point",
    "coordinates": [
      -85.8333,
      39.9167
    ]
  },
  "type": "Feature",
  "properties": {
    "hierarchy": [
      "tgn:2417712",
      "tgn:1000001",
      "tgn:7012149",
      "tgn:1002447",
      "tgn:7007252",
      "tgn:7029392"
    ],
    "placetype": [
      "aat:300006075"
    ],
    "id": 2417712,
    "name:xx": "Jackson Ditch"
  }
}
