{
  "geometry": {
    "type": "Point",
    "coordinates": [
      -102.3833,
      39.6167
    ]
  },
  "type": "Feature",
  "properties": {
    "hierarchy": [
      "tgn:2235471",
      "tgn:1000001",
      "tgn:7012149",
      "tgn:7007158",
      "tgn:2000254",
      "tgn:7029392"
    ],
    "placetype": [
      "aat:300006191"
    ],
    "id": 2235471,
    "name:xx": "Chester Wieser Erosion Control Number 1 Reservoir"
  }
}
