{
  "geometry": {
    "type": "Point",
    "coordinates": [
      -71.5833,
      42.75
    ]
  },
  "type": "Feature",
  "properties": {
    "hierarchy": [
      "tgn:2663778",
      "tgn:1000001",
      "tgn:1002480",
      "tgn:7012149",
      "tgn:7007564",
      "tgn:7029392"
    ],
    "placetype": [
      "aat:300008680"
    ],
    "id": 2663778,
    "name:xx": "Silver Lake"
  }
}
