{
  "geometry": {
    "type": "Point",
    "coordinates": [
      -80.0833,
      41.3667
    ]
  },
  "type": "Feature",
  "properties": {
    "hierarchy": [
      "tgn:2771821",
      "tgn:1000001",
      "tgn:7012149",
      "tgn:1002659",
      "tgn:7007710",
      "tgn:7029392"
    ],
    "placetype": [
      "aat:300006191"
    ],
    "id": 2771821,
    "name:xx": "Wilheim, Lake"
  }
}
