{
  "geometry": {
    "type": "Point",
    "coordinates": [
      -76.75,
      37.9667
    ]
  },
  "type": "Feature",
  "properties": {
    "hierarchy": [
      "tgn:2241720",
      "tgn:1000001",
      "tgn:7012149",
      "tgn:7014334",
      "tgn:7007919",
      "tgn:7029392"
    ],
    "placetype": [
      "aat:300008699"
    ],
    "id": 2241720,
    "name:xx": "Clarks Run"
  }
}
