{
  "geometry": {
    "type": "Point",
    "coordinates": [
      -89.5167,
      39.0333
    ]
  },
  "type": "Feature",
  "properties": {
    "hierarchy": [
      "tgn:2566552",
      "tgn:1000001",
      "tgn:7012149",
      "tgn:1002685",
      "tgn:7007251",
      "tgn:7029392"
    ],
    "placetype": [
      "aat:300006191"
    ],
    "id": 2566552,
    "name:xx": "Panama Lake"
  }
}
