{
  "type": "FeatureCollection",
  "features": [
    {
      "geometry": {
        "type": "Point",
        "coordinates": [
          31.986474,
          31.137041
        ]
      },
      "type": "Feature",
      "properties": {
        "hierarchy": [
          "tgn:7542950",
          "tgn:7001242",
          "tgn:1001059",
          "tgn:7016833",
          "tgn:7029392"
        ],
        "placetype": [
          "aat:300008347"
        ],
        "name:en": "'Izbat al Jayyār",
        "id": 7542950
      }
    },
    {
      "geometry": {
        "type": "Point",
        "coordinates": [
          31.97898,
          31.146033
        ]
      },
      "type": "Feature",
      "properties": {
        "hierarchy": [
          "tgn:7542951",
          "tgn:7001242",
          "tgn:1001059",
          "tgn:7016833",
          "tgn:7029392"
        ],
        "placetype": [
          "aat:300000206"
        ],
        "name:en": "'Izbat al Ballāsī",
        "id": 7542951
      }
    },
    {
      "geometry": {
        "type": "Point",
        "coordinates": [
          31.919806,
          31.143888
        ]
      },
      "type": "Feature",
      "properties": {
        "hierarchy": [
          "tgn:7542952",
          "tgn:7001242",
          "tgn:1001059",
          "tgn:7016833",
          "tgn:7029392"
        ],
        "placetype": [
          "aat:300006075"
        ],
        "name:en": "Tir'at al Ḩisāb",
        "id": 7542952
      }
    },
    {
      "geometry": {
        "type": "Point",
        "coordinates": [
          31.895509,
          31.13977
        ]
      },
      "type": "Feature",
      "properties": {
        "hierarchy": [
          "tgn:7542953",
          "tgn:7001242",
          "tgn:1001059",
          "tgn:7016833",
          "tgn:7029392"
        ],
        "placetype": [
          "aat:300008347"
        ],
        "name:en": "'Izbat aţ Ţāhirī",
        "id": 7542953
      }
    },
    {
      "geometry": {
        "type": "Point",
        "coordinates": [
          31.893848,
          31.140182
        ]
      },
      "type": "Feature",
      "properties": {
        "hierarchy": [
          "tgn:7542954",
          "tgn:7001242",
          "tgn:1001059",
          "tgn:7016833",
          "tgn:7029392"
        ],
        "placetype": [
          "aat:300000206"
        ],
        "name:en": "'Izbat 'Abd al Qādir",
        "id": 7542954
      }
    },
    {
      "geometry": {
        "type": "Point",
        "coordinates": [
          31.872624,
          31.133623
        ]
      },
      "type": "Feature",
      "properties": {
        "hierarchy": [
          "tgn:7542955",
          "tgn:7001242",
          "tgn:1001059",
          "tgn:7016833",
          "tgn:7029392"
        ],
        "placetype": [
          "aat:300008347"
        ],
        "name:en": "'Izbat ar Rawḑah",
        "id": 7542955
      }
    },
    {
      "geometry": {
        "type": "Point",
        "coordinates": [
          31.87858,
          31.145037
        ]
      },
      "type": "Feature",
      "properties": {
        "hierarchy": [
          "tgn:7542956",
          "tgn:7001242",
          "tgn:1001059",
          "tgn:7016833",
          "tgn:7029392"
        ],
        "placetype": [
          "aat:300000206"
        ],
        "name:en": "'Izbat al Ibrāhimīyah",
        "id": 7542956
      }
    },
    {
      "geometry": {
        "type": "Point",
        "coordinates": [
          31.851538,
          31.151234
        ]
      },
      "type": "Feature",
      "properties": {
        "hierarchy": [
          "tgn:7542957",
          "tgn:7001242",
          "tgn:1001059",
          "tgn:7016833",
          "tgn:7029392"
        ],
        "placetype": [
          "aat:300000206"
        ],
        "name:en": "'Izbat al 'Ilwāyah",
        "id": 7542957
      }
    },
    {
      "geometry": {
        "type": "Point",
        "coordinates": [
          31.853057,
          31.141592
        ]
      },
      "type": "Feature",
      "properties": {
        "hierarchy": [
          "tgn:7542958",
          "tgn:7001242",
          "tgn:1001059",
          "tgn:7016833",
          "tgn:7029392"
        ],
        "placetype": [
          "aat:300000206"
        ],
        "name:en": "'Izbat Umm Qalwīḩ",
        "id": 7542958
      }
    },
    {
      "geometry": {
        "type": "Point",
        "coordinates": [
          32.092276,
          30.954329
        ]
      },
      "type": "Feature",
      "properties": {
        "hierarchy": [
          "tgn:7542959",
          "tgn:7001242",
          "tgn:7016833",
          "tgn:1001113",
          "tgn:7029392"
        ],
        "placetype": [
          "aat:300008347"
        ],
        "name:en": "Qaryat Ţāriq Bin Ziyād an Namūdhajīyah",
        "id": 7542959
      }
    }
  ]
}
