{
  "geometry": {
    "type": "Point",
    "coordinates": [
      -91.1667,
      32.05
    ]
  },
  "type": "Feature",
  "properties": {
    "hierarchy": [
      "tgn:2766673",
      "tgn:1000001",
      "tgn:7012149",
      "tgn:2000907",
      "tgn:7007256",
      "tgn:7029392"
    ],
    "placetype": [
      "aat:300008680"
    ],
    "id": 2766673,
    "name:xx": "White Oak Lake"
  }
}
