{
  "type": "FeatureCollection",
  "features": [
    {
      "geometry": {
        "type": "Point",
        "coordinates": [
          3.05,
          46.6
        ]
      },
      "type": "Feature",
      "properties": {
        "hierarchy": [
          "tgn:4001740",
          "tgn:7002871",
          "tgn:1000003",
          "tgn:1000070",
          "tgn:7029392"
        ],
        "placetype": [
          "aat:300008347"
        ],
        "id": 4001740,
        "name:xx": "Bourbon l'Archambault"
      }
    },
    {
      "geometry": {
        "type": "Point",
        "coordinates": [
          7.55,
          47.5833
        ]
      },
      "type": "Feature",
      "properties": {
        "hierarchy": [
          "tgn:4001748",
          "tgn:7002870",
          "tgn:1000003",
          "tgn:1000070",
          "tgn:7029392"
        ],
        "placetype": [
          "aat:300008347"
        ],
        "id": 4001748,
        "name:xx": "Bourgfelden"
      }
    }
  ]
}
