{
  "geometry": {
    "type": "Point",
    "coordinates": [
      -95.5833,
      34.4167
    ]
  },
  "type": "Feature",
  "properties": {
    "hierarchy": [
      "tgn:2319532",
      "tgn:1000001",
      "tgn:7012149",
      "tgn:2001686",
      "tgn:7007707",
      "tgn:7029392"
    ],
    "placetype": [
      "aat:300008347"
    ],
    "id": 2319532,
    "name:xx": "Eubanks"
  }
}
