{
  "geometry": {
    "type": "Point",
    "coordinates": [
      -90.2833,
      40.2333
    ]
  },
  "type": "Feature",
  "properties": {
    "hierarchy": [
      "tgn:2435600",
      "tgn:1000001",
      "tgn:1002395",
      "tgn:7012149",
      "tgn:7007251",
      "tgn:7029392"
    ],
    "placetype": [
      "aat:300008706"
    ],
    "id": 2435600,
    "name:xx": "Kerton Creek"
  }
}
