{
  "geometry": {
    "type": "Point",
    "coordinates": [
      -118.15,
      48.8167
    ]
  },
  "type": "Feature",
  "properties": {
    "hierarchy": [
      "tgn:2648816",
      "tgn:1000001",
      "tgn:7012149",
      "tgn:2002250",
      "tgn:7007920",
      "tgn:7029392"
    ],
    "placetype": [
      "aat:300000390"
    ],
    "id": 2648816,
    "name:xx": "Scotia Mine"
  }
}
