{
  "geometry": {
    "type": "Point",
    "coordinates": [
      -123.5167,
      38.75
    ]
  },
  "type": "Feature",
  "properties": {
    "hierarchy": [
      "tgn:2368163",
      "tgn:1000001",
      "tgn:7012149",
      "tgn:7007157",
      "tgn:7014516",
      "tgn:7029392"
    ],
    "placetype": [
      "aat:300008850"
    ],
    "id": 2368163,
    "name:xx": "Gualala Point"
  }
}
