{
  "geometry": {
    "type": "Point",
    "coordinates": [
      28.4667,
      49.3167
    ]
  },
  "type": "Feature",
  "properties": {
    "hierarchy": [
      "tgn:1059864",
      "tgn:1000003",
      "tgn:7011999",
      "tgn:7006660",
      "tgn:7029392"
    ],
    "placetype": [
      "aat:300008347"
    ],
    "id": 1059864,
    "name:xx": "Stryzhavka"
  }
}
