{
  "geometry": {
    "type": "Point",
    "coordinates": [
      40.9167,
      50.6667
    ]
  },
  "type": "Feature",
  "properties": {
    "hierarchy": [
      "tgn:1061357",
      "tgn:1000004",
      "tgn:1003424",
      "tgn:7018214",
      "tgn:7002435",
      "tgn:7029392"
    ],
    "placetype": [
      "aat:300008347"
    ],
    "id": 1061357,
    "name:xx": "Vorobyevka"
  }
}
