{
  "type": "FeatureCollection",
  "features": [
    {
      "geometry": {
        "type": "Point",
        "coordinates": [
          6,
          52.016667
        ]
      },
      "type": "Feature",
      "properties": {
        "hierarchy": [
          "tgn:7258150",
          "tgn:7003619",
          "tgn:1000003",
          "tgn:7016845",
          "tgn:7029392"
        ],
        "placetype": [
          "aat:300008863"
        ],
        "name:nl": "Beekhuizense Bos",
        "id": 7258150
      }
    },
    {
      "geometry": {
        "type": "Point",
        "coordinates": [
          5.983333,
          52.016667
        ]
      },
      "type": "Feature",
      "properties": {
        "hierarchy": [
          "tgn:7258151",
          "tgn:7003619",
          "tgn:1000003",
          "tgn:7016845",
          "tgn:7029392"
        ],
        "placetype": [
          "aat:300387502"
        ],
        "name:nl": "Beekhuizen",
        "id": 7258151
      }
    },
    {
      "geometry": {
        "type": "Point",
        "coordinates": [
          5.4,
          51.3
        ]
      },
      "type": "Feature",
      "properties": {
        "hierarchy": [
          "tgn:7258152",
          "tgn:1000003",
          "tgn:7003624",
          "tgn:7016845",
          "tgn:7029392"
        ],
        "placetype": [
          "aat:300008187"
        ],
        "name:nl": "Beekerheide",
        "id": 7258152
      }
    },
    {
      "geometry": {
        "type": "Point",
        "coordinates": [
          5.783333,
          50.933333
        ]
      },
      "type": "Feature",
      "properties": {
        "hierarchy": [
          "tgn:7258154",
          "tgn:1000003",
          "tgn:7003622",
          "tgn:7016845",
          "tgn:7029392"
        ],
        "placetype": [
          "aat:300007783"
        ],
        "name:nl": "Beek-Elsloo",
        "id": 7258154
      }
    },
    {
      "geometry": {
        "type": "Point",
        "coordinates": [
          6.833333,
          52.35
        ]
      },
      "type": "Feature",
      "properties": {
        "hierarchy": [
          "tgn:7258155",
          "tgn:1000003",
          "tgn:7003626",
          "tgn:7016845",
          "tgn:7029392"
        ],
        "placetype": [
          "aat:300008347"
        ],
        "name:nl": "Beekdorp",
        "id": 7258155
      }
    },
    {
      "geometry": {
        "type": "Point",
        "coordinates": [
          6.016667,
          52.15
        ]
      },
      "type": "Feature",
      "properties": {
        "hierarchy": [
          "tgn:7258156",
          "tgn:7003619",
          "tgn:1000003",
          "tgn:7016845",
          "tgn:7029392"
        ],
        "placetype": [
          "aat:300008699"
        ],
        "name:nl": "Beekbergsche Beek",
        "id": 7258156
      }
    }
  ]
}
