{
  "geometry": {
    "type": "Point",
    "coordinates": [
      -106.3833,
      33.05
    ]
  },
  "type": "Feature",
  "properties": {
    "hierarchy": [
      "tgn:2460363",
      "tgn:1000001",
      "tgn:7012149",
      "tgn:2001455",
      "tgn:7007566",
      "tgn:7029392"
    ],
    "placetype": [
      "aat:300008680"
    ],
    "id": 2460363,
    "name:xx": "Little Salt Lake"
  }
}
