{
  "geometry": {
    "type": "Point",
    "coordinates": [
      3.1667,
      42.4333
    ]
  },
  "type": "Feature",
  "properties": {
    "hierarchy": [
      "tgn:1010565",
      "tgn:1000003",
      "tgn:7002885",
      "tgn:1000070",
      "tgn:7029392"
    ],
    "placetype": [
      "aat:300008850"
    ],
    "id": 1010565,
    "name:xx": "Cerbère, Cap"
  }
}
