{
  "geometry": {
    "type": "Point",
    "coordinates": [
      -76.1333,
      38.5167
    ]
  },
  "type": "Feature",
  "properties": {
    "hierarchy": [
      "tgn:2328808",
      "tgn:1002338",
      "tgn:1000001",
      "tgn:7012149",
      "tgn:7007516",
      "tgn:7029392"
    ],
    "placetype": [
      "aat:300008706"
    ],
    "id": 2328808,
    "name:xx": "Fishing Creek"
  }
}
