{
  "geometry": {
    "type": "Point",
    "coordinates": [
      -84.0667,
      44.7667
    ]
  },
  "type": "Feature",
  "properties": {
    "hierarchy": [
      "tgn:2500083",
      "tgn:1000001",
      "tgn:7012149",
      "tgn:2000988",
      "tgn:7007520",
      "tgn:7029392"
    ],
    "placetype": [
      "aat:300008680"
    ],
    "id": 2500083,
    "name:xx": "McCreedie Lake"
  }
}
