{
  "geometry": {
    "type": "Point",
    "coordinates": [
      -115.0667,
      34.8667
    ]
  },
  "type": "Feature",
  "properties": {
    "hierarchy": [
      "tgn:2353141",
      "tgn:1000001",
      "tgn:7012149",
      "tgn:7007157",
      "tgn:1002857",
      "tgn:7029392"
    ],
    "placetype": [
      "aat:300008798"
    ],
    "id": 2353141,
    "name:xx": "Goffs Butte"
  }
}
