{
  "geometry": {
    "type": "Point",
    "coordinates": [
      -78.05,
      37.6667
    ]
  },
  "type": "Feature",
  "properties": {
    "hierarchy": [
      "tgn:2603630",
      "tgn:1000001",
      "tgn:7012149",
      "tgn:2002163",
      "tgn:7007919",
      "tgn:7029392"
    ],
    "placetype": [
      "aat:300006191"
    ],
    "id": 2603630,
    "name:xx": "Queensmeer Lake"
  }
}
