{
  "geometry": {
    "type": "Point",
    "coordinates": [
      -70.8667,
      41.7333
    ]
  },
  "type": "Feature",
  "properties": {
    "hierarchy": [
      "tgn:2379047",
      "tgn:1000001",
      "tgn:7014423",
      "tgn:7012149",
      "tgn:7007517",
      "tgn:7029392"
    ],
    "placetype": [
      "aat:300006191"
    ],
    "id": 2379047,
    "name:xx": "Hartley Mill Pond"
  }
}
