{
  "geometry": {
    "type": "Point",
    "coordinates": [
      -122.85,
      44.9833
    ]
  },
  "type": "Feature",
  "properties": {
    "hierarchy": [
      "tgn:2212414",
      "tgn:1000001",
      "tgn:7012149",
      "tgn:1002636",
      "tgn:7007708",
      "tgn:7029392"
    ],
    "placetype": [
      "aat:300006191"
    ],
    "id": 2212414,
    "name:xx": "Bye Reservoir"
  }
}
