{
  "geometry": {
    "type": "Point",
    "coordinates": [
      122.4833,
      11.05
    ]
  },
  "type": "Feature",
  "properties": {
    "hierarchy": [
      "tgn:1084331",
      "tgn:1000004",
      "tgn:1001307",
      "tgn:1000135",
      "tgn:7029392"
    ],
    "placetype": [
      "aat:300008347"
    ],
    "id": 1084331,
    "name:xx": "Lambunao"
  }
}
