{
  "geometry": {
    "type": "Point",
    "coordinates": [
      74.48349,
      23.021216
    ]
  },
  "type": "Feature",
  "properties": {
    "hierarchy": [
      "tgn:7573825",
      "tgn:1000004",
      "tgn:7000198",
      "tgn:1001894",
      "tgn:7029392"
    ],
    "placetype": [
      "aat:300008347"
    ],
    "name:en": "Itāwa",
    "id": 7573825
  }
}
