{
  "geometry": {
    "type": "Point",
    "coordinates": [
      -77.55,
      39.55
    ]
  },
  "type": "Feature",
  "properties": {
    "hierarchy": [
      "tgn:1132727",
      "tgn:1000001",
      "tgn:7016101",
      "tgn:7012149",
      "tgn:7007516",
      "tgn:7029392"
    ],
    "placetype": [
      "aat:300008706"
    ],
    "id": 1132727,
    "name:xx": "Catoctin Creek"
  }
}
