{
  "geometry": {
    "type": "Point",
    "coordinates": [
      -85.2333,
      35.8667
    ]
  },
  "type": "Feature",
  "properties": {
    "hierarchy": [
      "tgn:2463933",
      "tgn:1000001",
      "tgn:7012149",
      "tgn:2001929",
      "tgn:7007825",
      "tgn:7029392"
    ],
    "placetype": [
      "aat:300008746"
    ],
    "id": 2463933,
    "name:xx": "Lockwood Cave"
  }
}
