{
  "geometry": {
    "type": "Point",
    "coordinates": [
      -88.65,
      39.1667
    ]
  },
  "type": "Feature",
  "properties": {
    "hierarchy": [
      "tgn:2524998",
      "tgn:1000001",
      "tgn:1002349",
      "tgn:7012149",
      "tgn:7007251",
      "tgn:7029392"
    ],
    "placetype": [
      "aat:300008706"
    ],
    "id": 2524998,
    "name:xx": "Morris Creek"
  }
}
