{
  "geometry": {
    "type": "Point",
    "coordinates": [
      32.945771,
      24.727204
    ]
  },
  "type": "Feature",
  "properties": {
    "hierarchy": [
      "tgn:7527688",
      "tgn:7001242",
      "tgn:7001311",
      "tgn:7016833",
      "tgn:7029392"
    ],
    "placetype": [
      "aat:300379998"
    ],
    "name:en": "Zayd, Wādī",
    "id": 7527688
  }
}
