{
  "geometry": {
    "type": "Point",
    "coordinates": [
      -95.9333,
      35.7833
    ]
  },
  "type": "Feature",
  "properties": {
    "hierarchy": [
      "tgn:2683196",
      "tgn:1000001",
      "tgn:7012149",
      "tgn:2001678",
      "tgn:7007707",
      "tgn:7029392"
    ],
    "placetype": [
      "aat:300008798"
    ],
    "id": 2683196,
    "name:xx": "Spanish Peak"
  }
}
