{
  "geometry": {
    "type": "Point",
    "coordinates": [
      30.833333,
      28.566667
    ]
  },
  "type": "Feature",
  "properties": {
    "hierarchy": [
      "tgn:7533642",
      "tgn:7001242",
      "tgn:7016833",
      "tgn:1001088",
      "tgn:7029392"
    ],
    "placetype": [
      "aat:300008791"
    ],
    "name:en": "Jarābi', Jazīrat al",
    "id": 7533642
  }
}
