{
  "geometry": {
    "type": "Point",
    "coordinates": [
      -1.1333,
      43.6667
    ]
  },
  "type": "Feature",
  "properties": {
    "hierarchy": [
      "tgn:1126543",
      "tgn:7002878",
      "tgn:1000003",
      "tgn:1000070",
      "tgn:7029392"
    ],
    "placetype": [
      "aat:300008707"
    ],
    "id": 1126543,
    "name:xx": "Luy"
  }
}
