{
  "geometry": {
    "type": "Point",
    "coordinates": [
      30.594562,
      30.851003
    ]
  },
  "type": "Feature",
  "properties": {
    "hierarchy": [
      "tgn:7533929",
      "tgn:7001242",
      "tgn:1001075",
      "tgn:7016833",
      "tgn:7029392"
    ],
    "placetype": [
      "aat:300008347"
    ],
    "name:en": "Jazā'ir 'Īsá",
    "id": 7533929
  }
}
