{
  "geometry": {
    "type": "Point",
    "coordinates": [
      -83.2167,
      35.7167
    ]
  },
  "type": "Feature",
  "properties": {
    "hierarchy": [
      "tgn:7022474",
      "tgn:1000001",
      "tgn:7012149",
      "tgn:7029392"
    ],
    "placetype": [
      "aat:300008798"
    ],
    "id": 7022474,
    "name:xx": "Camel Hump Knob"
  }
}
