{
  "geometry": {
    "type": "Point",
    "coordinates": [
      -107.4167,
      40.6333
    ]
  },
  "type": "Feature",
  "properties": {
    "hierarchy": [
      "tgn:2194584",
      "tgn:1000001",
      "tgn:7012149",
      "tgn:2000232",
      "tgn:7007158",
      "tgn:7029392"
    ],
    "placetype": [
      "aat:300000390"
    ],
    "id": 2194584,
    "name:xx": "Bridges Mine"
  }
}
