{
  "geometry": {
    "type": "Point",
    "coordinates": [
      -90.7667,
      31.85
    ]
  },
  "type": "Feature",
  "properties": {
    "hierarchy": [
      "tgn:2563062",
      "tgn:1000001",
      "tgn:2001096",
      "tgn:7012149",
      "tgn:7007522",
      "tgn:7029392"
    ],
    "placetype": [
      "aat:300008699"
    ],
    "id": 2563062,
    "name:xx": "Owens Branch"
  }
}
