{
  "geometry": {
    "type": "Point",
    "coordinates": [
      -121.8667,
      38.0333
    ]
  },
  "type": "Feature",
  "properties": {
    "hierarchy": [
      "tgn:2589446",
      "tgn:1000001",
      "tgn:7012149",
      "tgn:1002298",
      "tgn:7007157",
      "tgn:7029392"
    ],
    "placetype": [
      "aat:300008850"
    ],
    "id": 2589446,
    "name:xx": "Point Emmet"
  }
}
