{
  "geometry": {
    "type": "Point",
    "coordinates": [
      -96.9833,
      28.05
    ]
  },
  "type": "Feature",
  "properties": {
    "hierarchy": [
      "tgn:2136203",
      "tgn:1000001",
      "tgn:7012149",
      "tgn:7007826",
      "tgn:7029392"
    ],
    "placetype": [
      "aat:300132316"
    ],
    "id": 2136203,
    "name:xx": "Aransas Bay"
  }
}
