{
  "geometry": {
    "type": "Point",
    "coordinates": [
      -88.55,
      38.2167
    ]
  },
  "type": "Feature",
  "properties": {
    "hierarchy": [
      "tgn:2026527",
      "tgn:1000001",
      "tgn:7012149",
      "tgn:2000508",
      "tgn:7007251",
      "tgn:7029392"
    ],
    "placetype": [
      "aat:300008347"
    ],
    "id": 2026527,
    "name:xx": "Belle Prairie City"
  }
}
