{
  "geometry": {
    "type": "Point",
    "coordinates": [
      31.186489,
      30.000388
    ]
  },
  "type": "Feature",
  "properties": {
    "hierarchy": [
      "tgn:7530676",
      "tgn:7001242",
      "tgn:7016833",
      "tgn:1001083",
      "tgn:7029392"
    ],
    "placetype": [
      "aat:300000745"
    ],
    "id": 7530676,
    "name:xx": "Masākin Abū al Futūḩ"
  }
}
