{
  "geometry": {
    "type": "Point",
    "coordinates": [
      -83.1833,
      37.9167
    ]
  },
  "type": "Feature",
  "properties": {
    "hierarchy": [
      "tgn:2039940",
      "tgn:1000001",
      "tgn:7012149",
      "tgn:2000831",
      "tgn:7007255",
      "tgn:7029392"
    ],
    "placetype": [
      "aat:300387210",
      "aat:300008707"
    ],
    "id": 2039940,
    "name:xx": "Lick Branch"
  }
}
