{
  "geometry": {
    "type": "Point",
    "coordinates": [
      32.683333,
      30.316667
    ]
  },
  "type": "Feature",
  "properties": {
    "hierarchy": [
      "tgn:7528587",
      "tgn:7001242",
      "tgn:7016833",
      "tgn:7001335",
      "tgn:7029392"
    ],
    "placetype": [
      "aat:300008750"
    ],
    "name:en": "Umm 'Iz̧ām, Kathīb",
    "id": 7528587
  }
}
