{
  "geometry": {
    "type": "Point",
    "coordinates": [
      -114.5833,
      35.3667
    ]
  },
  "type": "Feature",
  "properties": {
    "hierarchy": [
      "tgn:7019996",
      "tgn:1000001",
      "tgn:7012149",
      "tgn:7029392"
    ],
    "placetype": [
      "aat:300386845",
      "aat:300008761"
    ],
    "id": 7019996,
    "name:xx": "Cottonwood Valley"
  }
}
