{
  "type": "FeatureCollection",
  "features": [
    {
      "geometry": {
        "type": "Point",
        "coordinates": [
          5.95,
          48.45
        ]
      },
      "type": "Feature",
      "properties": {
        "hierarchy": [
          "tgn:1033081",
          "tgn:1000003",
          "tgn:7002883",
          "tgn:1000070",
          "tgn:7029392"
        ],
        "placetype": [
          "aat:300008347"
        ],
        "id": 1033081,
        "name:xx": "Favières"
      }
    },
    {
      "geometry": {
        "type": "Point",
        "coordinates": [
          1.65,
          48.95
        ]
      },
      "type": "Feature",
      "properties": {
        "hierarchy": [
          "tgn:1033082",
          "tgn:1000003",
          "tgn:7002883",
          "tgn:1000070",
          "tgn:7029392"
        ],
        "placetype": [
          "aat:300008347"
        ],
        "id": 1033082,
        "name:xx": "Favrieux"
      }
    },
    {
      "geometry": {
        "type": "Point",
        "coordinates": [
          4.25,
          44.9833
        ]
      },
      "type": "Feature",
      "properties": {
        "hierarchy": [
          "tgn:1033083",
          "tgn:7002871",
          "tgn:1000003",
          "tgn:1000070",
          "tgn:7029392"
        ],
        "placetype": [
          "aat:300008347"
        ],
        "id": 1033083,
        "name:xx": "Fay-sur-Lignon"
      }
    },
    {
      "geometry": {
        "type": "Point",
        "coordinates": [
          6.7167,
          43.6333
        ]
      },
      "type": "Feature",
      "properties": {
        "hierarchy": [
          "tgn:1033084",
          "tgn:1000003",
          "tgn:1000070",
          "tgn:7002895",
          "tgn:7029392"
        ],
        "placetype": [
          "aat:300008347"
        ],
        "id": 1033084,
        "name:xx": "Fayence"
      }
    },
    {
      "geometry": {
        "type": "Point",
        "coordinates": [
          5.6,
          47.7833
        ]
      },
      "type": "Feature",
      "properties": {
        "hierarchy": [
          "tgn:1033085",
          "tgn:1000003",
          "tgn:7002880",
          "tgn:1000070",
          "tgn:7029392"
        ],
        "placetype": [
          "aat:300008347"
        ],
        "id": 1033085,
        "name:xx": "Fayl-Billot"
      }
    },
    {
      "geometry": {
        "type": "Point",
        "coordinates": [
          3.9167,
          50.3
        ]
      },
      "type": "Feature",
      "properties": {
        "hierarchy": [
          "tgn:1033086",
          "tgn:1000003",
          "tgn:7001097",
          "tgn:1000070",
          "tgn:7029392"
        ],
        "placetype": [
          "aat:300008347"
        ],
        "id": 1033086,
        "name:xx": "Feignies"
      }
    },
    {
      "geometry": {
        "type": "Point",
        "coordinates": [
          4,
          50.25
        ]
      },
      "type": "Feature",
      "properties": {
        "hierarchy": [
          "tgn:1033089",
          "tgn:1000003",
          "tgn:7001097",
          "tgn:1000070",
          "tgn:7029392"
        ],
        "placetype": [
          "aat:300008347"
        ],
        "id": 1033089,
        "name:xx": "Ferrière-la-Grand"
      }
    }
  ]
}
