{
  "geometry": {
    "type": "Point",
    "coordinates": [
      14.8333,
      46.0333
    ]
  },
  "type": "Feature",
  "properties": {
    "hierarchy": [
      "tgn:7015109",
      "tgn:1000003",
      "tgn:7006670",
      "tgn:7029392"
    ],
    "placetype": [
      "aat:300387064",
      "aat:300387081"
    ],
    "id": 7015109,
    "name:xx": "Litija, Občina"
  }
}
