{
  "geometry": {
    "type": "Point",
    "coordinates": [
      1.860957,
      41.4404
    ]
  },
  "type": "Feature",
  "properties": {
    "hierarchy": [
      "tgn:7336443",
      "tgn:7002808",
      "tgn:7030216",
      "tgn:1000003",
      "tgn:1000095",
      "tgn:7029392"
    ],
    "placetype": [
      "aat:300008347"
    ],
    "id": 7336443,
    "name:xx": "Gélida"
  }
}
