{
  "geometry": {
    "type": "Point",
    "coordinates": [
      46.1333,
      25.1333
    ]
  },
  "type": "Feature",
  "properties": {
    "hierarchy": [
      "tgn:1084778",
      "tgn:7000680",
      "tgn:1000004",
      "tgn:7003879",
      "tgn:1000137",
      "tgn:7029392"
    ],
    "placetype": [
      "aat:300008347"
    ],
    "id": 1084778,
    "name:xx": "Ḥuraymilā"
  }
}
