{
  "geometry": {
    "type": "Point",
    "coordinates": [
      15.1167,
      59.0833
    ]
  },
  "type": "Feature",
  "properties": {
    "hierarchy": [
      "tgn:1063091",
      "tgn:1000003",
      "tgn:1000331",
      "tgn:1000097",
      "tgn:7029392"
    ],
    "placetype": [
      "aat:300008347"
    ],
    "id": 1063091,
    "name:xx": "Hallsberg"
  }
}
