{
  "geometry": {
    "type": "Point",
    "coordinates": [
      138.1167,
      56.4833
    ]
  },
  "type": "Feature",
  "properties": {
    "hierarchy": [
      "tgn:1137132",
      "tgn:1000004",
      "tgn:7014474",
      "tgn:7018214",
      "tgn:7002435",
      "tgn:7029392"
    ],
    "placetype": [
      "aat:300008347"
    ],
    "id": 1137132,
    "name:xx": "Ayan"
  }
}
