{
  "geometry": {
    "type": "Point",
    "coordinates": [
      13.65,
      54.55
    ]
  },
  "type": "Feature",
  "properties": {
    "hierarchy": [
      "tgn:7145725",
      "tgn:1000003",
      "tgn:7000094",
      "tgn:7000084",
      "tgn:7029392"
    ],
    "placetype": [
      "aat:300266640"
    ],
    "id": 7145725,
    "name:xx": "Kollicker Berge"
  }
}
