{
  "geometry": {
    "type": "Point",
    "coordinates": [
      -110.5333,
      44.8667
    ]
  },
  "type": "Feature",
  "properties": {
    "hierarchy": [
      "tgn:2333546",
      "tgn:1000001",
      "tgn:7012149",
      "tgn:2002379",
      "tgn:7007923",
      "tgn:7029392"
    ],
    "placetype": [
      "aat:300008798"
    ],
    "id": 2333546,
    "name:xx": "Folsom Peak"
  }
}
