{
  "geometry": {
    "type": "Point",
    "coordinates": [
      -82.9167,
      42.4167
    ]
  },
  "type": "Feature",
  "properties": {
    "hierarchy": [
      "tgn:2052134",
      "tgn:1000001",
      "tgn:7012149",
      "tgn:1003005",
      "tgn:7007520",
      "tgn:7029392"
    ],
    "placetype": [
      "aat:300008347"
    ],
    "id": 2052134,
    "name:xx": "Harper Woods"
  }
}
