{
  "type": "FeatureCollection",
  "features": [
    {
      "geometry": {
        "type": "Point",
        "coordinates": [
          -73.683333,
          -43.9
        ]
      },
      "type": "Feature",
      "properties": {
        "hierarchy": [
          "tgn:7309310",
          "tgn:1001699",
          "tgn:1000049",
          "tgn:1000002",
          "tgn:7029392"
        ],
        "placetype": [
          "aat:300008791"
        ],
        "id": 7309310,
        "name:xx": "Luisa, Isla"
      }
    },
    {
      "geometry": {
        "type": "Point",
        "coordinates": [
          -68.783333,
          -55.466667
        ]
      },
      "type": "Feature",
      "properties": {
        "hierarchy": [
          "tgn:7309311",
          "tgn:1001702",
          "tgn:1000049",
          "tgn:1000002",
          "tgn:7029392"
        ],
        "placetype": [
          "aat:300008676"
        ],
        "id": 7309311,
        "name:xx": "Luisa, Bahía"
      }
    },
    {
      "geometry": {
        "type": "Point",
        "coordinates": [
          -75.55,
          -48.85
        ]
      },
      "type": "Feature",
      "properties": {
        "hierarchy": [
          "tgn:7309312",
          "tgn:1001702",
          "tgn:1000049",
          "tgn:1000002",
          "tgn:7029392"
        ],
        "placetype": [
          "aat:300008676"
        ],
        "id": 7309312,
        "name:xx": "Luis, Seno"
      }
    },
    {
      "geometry": {
        "type": "Point",
        "coordinates": [
          -72.166667,
          -53.25
        ]
      },
      "type": "Feature",
      "properties": {
        "hierarchy": [
          "tgn:7309313",
          "tgn:1001702",
          "tgn:1000049",
          "tgn:1000002",
          "tgn:7029392"
        ],
        "placetype": [
          "aat:300386846"
        ],
        "id": 7309313,
        "name:xx": "Luis, Punta"
      }
    },
    {
      "geometry": {
        "type": "Point",
        "coordinates": [
          -75.25,
          -48.2
        ]
      },
      "type": "Feature",
      "properties": {
        "hierarchy": [
          "tgn:7309314",
          "tgn:1001623",
          "tgn:1000049",
          "tgn:1000002",
          "tgn:7029392"
        ],
        "placetype": [
          "aat:300386846"
        ],
        "id": 7309314,
        "name:xx": "Luis, Punta"
      }
    },
    {
      "geometry": {
        "type": "Point",
        "coordinates": [
          -71.833333,
          -54.1
        ]
      },
      "type": "Feature",
      "properties": {
        "hierarchy": [
          "tgn:7309315",
          "tgn:1001702",
          "tgn:1000049",
          "tgn:1000002",
          "tgn:7029392"
        ],
        "placetype": [
          "aat:300132317"
        ],
        "id": 7309315,
        "name:xx": "Luis, Puerto"
      }
    },
    {
      "geometry": {
        "type": "Point",
        "coordinates": [
          -74.716667,
          -45.766667
        ]
      },
      "type": "Feature",
      "properties": {
        "hierarchy": [
          "tgn:7309316",
          "tgn:1001623",
          "tgn:1000049",
          "tgn:1000002",
          "tgn:7029392"
        ],
        "placetype": [
          "aat:300008791"
        ],
        "id": 7309316,
        "name:xx": "Luis, Islote"
      }
    },
    {
      "geometry": {
        "type": "Point",
        "coordinates": [
          -74.333333,
          -51.65
        ]
      },
      "type": "Feature",
      "properties": {
        "hierarchy": [
          "tgn:7309317",
          "tgn:1001702",
          "tgn:1000049",
          "tgn:1000002",
          "tgn:7029392"
        ],
        "placetype": [
          "aat:300008791"
        ],
        "id": 7309317,
        "name:xx": "Luis, Isla"
      }
    },
    {
      "geometry": {
        "type": "Point",
        "coordinates": [
          -73.516667,
          -53.116667
        ]
      },
      "type": "Feature",
      "properties": {
        "hierarchy": [
          "tgn:7309318",
          "tgn:1001702",
          "tgn:1000049",
          "tgn:1000002",
          "tgn:7029392"
        ],
        "placetype": [
          "aat:300132317"
        ],
        "id": 7309318,
        "name:xx": "Luis, Caleta"
      }
    },
    {
      "geometry": {
        "type": "Point",
        "coordinates": [
          -66.783333,
          -55.3
        ]
      },
      "type": "Feature",
      "properties": {
        "hierarchy": [
          "tgn:7309319",
          "tgn:1001702",
          "tgn:1000049",
          "tgn:1000002",
          "tgn:7029392"
        ],
        "placetype": [
          "aat:300008791"
        ],
        "id": 7309319,
        "name:xx": "Luff, Isla"
      }
    }
  ]
}
