{
  "geometry": {
    "type": "Point",
    "coordinates": [
      -123.1833,
      41.8667
    ]
  },
  "type": "Feature",
  "properties": {
    "hierarchy": [
      "tgn:2275969",
      "tgn:1000001",
      "tgn:7012149",
      "tgn:7007157",
      "tgn:2000189",
      "tgn:7029392"
    ],
    "placetype": [
      "aat:300008706"
    ],
    "id": 2275969,
    "name:xx": "Darkey Creek"
  }
}
