{
  "geometry": {
    "type": "Point",
    "coordinates": [
      -87.15,
      33.6333
    ]
  },
  "type": "Feature",
  "properties": {
    "hierarchy": [
      "tgn:2598013",
      "tgn:7002659",
      "tgn:1000001",
      "tgn:7012149",
      "tgn:7029392"
    ],
    "placetype": [
      "aat:300008706"
    ],
    "id": 2598013,
    "name:xx": "Prescott Creek"
  }
}
