{
  "geometry": {
    "type": "Point",
    "coordinates": [
      -117.0667,
      47.8167
    ]
  },
  "type": "Feature",
  "properties": {
    "hierarchy": [
      "tgn:2364054",
      "tgn:1000001",
      "tgn:7012149",
      "tgn:2002249",
      "tgn:7007920",
      "tgn:7029392"
    ],
    "placetype": [
      "aat:300008798"
    ],
    "id": 2364054,
    "name:xx": "Green Mountain"
  }
}
