{
  "geometry": {
    "type": "Point",
    "coordinates": [
      15.3667,
      49.0167
    ]
  },
  "type": "Feature",
  "properties": {
    "hierarchy": [
      "tgn:1027094",
      "tgn:7011506",
      "tgn:1000003",
      "tgn:1001780",
      "tgn:7029392"
    ],
    "placetype": [
      "aat:300008347"
    ],
    "id": 1027094,
    "name:xx": "Bolikov"
  }
}
