{
  "geometry": {
    "type": "Point",
    "coordinates": [
      -111.9333,
      43.4333
    ]
  },
  "type": "Feature",
  "properties": {
    "hierarchy": [
      "tgn:2390595",
      "tgn:1000001",
      "tgn:2000461",
      "tgn:7012149",
      "tgn:7007250",
      "tgn:7029392"
    ],
    "placetype": [
      "aat:300006075"
    ],
    "id": 2390595,
    "name:xx": "Highline Canal"
  }
}
