{
  "geometry": {
    "type": "Point",
    "coordinates": [
      -104.9375,
      21.375
    ]
  },
  "type": "Feature",
  "properties": {
    "hierarchy": [
      "tgn:7403625",
      "tgn:1000001",
      "tgn:1001906",
      "tgn:7005560",
      "tgn:7029392"
    ],
    "placetype": [
      "aat:300008347"
    ],
    "id": 7403625,
    "name:xx": "El Carrizal"
  }
}
