{
  "geometry": {
    "type": "Point",
    "coordinates": [
      103.1333,
      5.3167
    ]
  },
  "type": "Feature",
  "properties": {
    "hierarchy": [
      "tgn:1082716",
      "tgn:7000317",
      "tgn:1000004",
      "tgn:7016831",
      "tgn:1000128",
      "tgn:7029392"
    ],
    "placetype": [
      "aat:300008347"
    ],
    "id": 1082716,
    "name:xx": "Chabang Tiga"
  }
}
