{
  "geometry": {
    "type": "Point",
    "coordinates": [
      27.479162,
      31.195724
    ]
  },
  "type": "Feature",
  "properties": {
    "hierarchy": [
      "tgn:7527524",
      "tgn:7001242",
      "tgn:7016833",
      "tgn:1001418",
      "tgn:7029392"
    ],
    "placetype": [
      "aat:300387007"
    ],
    "name:en": "Zāwiyat al Ḩawālah",
    "id": 7527524
  }
}
