{
  "geometry": {
    "type": "Point",
    "coordinates": [
      52.0667,
      35.35
    ]
  },
  "type": "Feature",
  "properties": {
    "hierarchy": [
      "tgn:1079073",
      "tgn:1000004",
      "tgn:1001528",
      "tgn:7000231",
      "tgn:7029392"
    ],
    "placetype": [
      "aat:300008347"
    ],
    "id": 1079073,
    "name:xx": "Eyvānakī"
  }
}
