{
  "geometry": {
    "type": "Point",
    "coordinates": [
      -74.2333,
      44.25
    ]
  },
  "type": "Feature",
  "properties": {
    "hierarchy": [
      "tgn:2206057",
      "tgn:1000001",
      "tgn:7012149",
      "tgn:7013941",
      "tgn:7007568",
      "tgn:7029392"
    ],
    "placetype": [
      "aat:300132316"
    ],
    "id": 2206057,
    "name:xx": "Bull Rush Bay"
  }
}
