{
  "geometry": {
    "type": "Point",
    "coordinates": [
      -83.55,
      35.9333
    ]
  },
  "type": "Feature",
  "properties": {
    "hierarchy": [
      "tgn:2636406",
      "tgn:1000001",
      "tgn:7012149",
      "tgn:2001914",
      "tgn:7007825",
      "tgn:7029392"
    ],
    "placetype": [
      "aat:300008791"
    ],
    "id": 2636406,
    "name:xx": "Saffell Island"
  }
}
