{
  "geometry": {
    "type": "Point",
    "coordinates": [
      -114.5167,
      48.1333
    ]
  },
  "type": "Feature",
  "properties": {
    "hierarchy": [
      "tgn:2393298",
      "tgn:1000001",
      "tgn:7012149",
      "tgn:2001274",
      "tgn:7007524",
      "tgn:7029392"
    ],
    "placetype": [
      "aat:300008761"
    ],
    "id": 2393298,
    "name:xx": "Hoffman Draw"
  }
}
