{
  "geometry": {
    "type": "Point",
    "coordinates": [
      -76.45,
      39.0333
    ]
  },
  "type": "Feature",
  "properties": {
    "hierarchy": [
      "tgn:2767720",
      "tgn:7014651",
      "tgn:1000001",
      "tgn:7012149",
      "tgn:7007516",
      "tgn:7029392"
    ],
    "placetype": [
      "aat:300008706"
    ],
    "id": 2767720,
    "name:xx": "Whitehall Creek"
  }
}
