{
  "geometry": {
    "type": "Point",
    "coordinates": [
      -90.45,
      42.1833
    ]
  },
  "type": "Feature",
  "properties": {
    "hierarchy": [
      "tgn:2299086",
      "tgn:1000001",
      "tgn:7012149",
      "tgn:2000609",
      "tgn:7007253",
      "tgn:7029392"
    ],
    "placetype": [
      "aat:300008706"
    ],
    "id": 2299086,
    "name:xx": "Duck Creek"
  }
}
