{
  "geometry": {
    "type": "Point",
    "coordinates": [
      -91.75,
      18.6625
    ]
  },
  "type": "Feature",
  "properties": {
    "hierarchy": [
      "tgn:7404477",
      "tgn:7005578",
      "tgn:1000001",
      "tgn:7005560",
      "tgn:7029392"
    ],
    "placetype": [
      "aat:300008347"
    ],
    "id": 7404477,
    "name:xx": "El Carmen"
  }
}
