{
  "geometry": {
    "type": "Point",
    "coordinates": [
      -89.7333,
      46.7333
    ]
  },
  "type": "Feature",
  "properties": {
    "hierarchy": [
      "tgn:2456574",
      "tgn:1000001",
      "tgn:7012149",
      "tgn:2000986",
      "tgn:7007520",
      "tgn:7029392"
    ],
    "placetype": [
      "aat:300008707"
    ],
    "id": 2456574,
    "name:xx": "Little Iron River"
  }
}
