{
  "geometry": {
    "type": "Point",
    "coordinates": [
      -108.0333,
      42.7833
    ]
  },
  "type": "Feature",
  "properties": {
    "hierarchy": [
      "tgn:2251859",
      "tgn:1000001",
      "tgn:7012149",
      "tgn:2002371",
      "tgn:7007923",
      "tgn:7029392"
    ],
    "placetype": [
      "aat:300008706"
    ],
    "id": 2251859,
    "name:xx": "Conant Creek"
  }
}
