{
  "geometry": {
    "type": "Point",
    "coordinates": [
      -94.25,
      39.75
    ]
  },
  "type": "Feature",
  "properties": {
    "hierarchy": [
      "tgn:2216010",
      "tgn:2216028",
      "tgn:1000001",
      "tgn:7012149",
      "tgn:7021844",
      "tgn:7007523",
      "tgn:7029392"
    ],
    "placetype": [
      "aat:300006191"
    ],
    "id": 2216010,
    "name:xx": "Cameron Number 1 Reservoir"
  }
}
