{
  "geometry": {
    "type": "Point",
    "coordinates": [
      120.35,
      30.4333
    ]
  },
  "type": "Feature",
  "properties": {
    "hierarchy": [
      "tgn:1073231",
      "tgn:1000004",
      "tgn:7002076",
      "tgn:1000111",
      "tgn:7029392"
    ],
    "placetype": [
      "aat:300008347"
    ],
    "id": 1073231,
    "name:xx": "Xucun"
  }
}
