{
  "type": "FeatureCollection",
  "features": [
    {
      "geometry": {
        "type": "Point",
        "coordinates": [
          -95.25,
          32.9167
        ]
      },
      "type": "Feature",
      "properties": {
        "hierarchy": [
          "tgn:2194000",
          "tgn:1000001",
          "tgn:7012149",
          "tgn:7007826",
          "tgn:7029392"
        ],
        "placetype": [
          "aat:300008706"
        ],
        "id": 2194000,
        "name:xx": "Briary Creek"
      }
    },
    {
      "geometry": {
        "type": "Point",
        "coordinates": [
          -78.6333,
          34.8
        ]
      },
      "type": "Feature",
      "properties": {
        "hierarchy": [
          "tgn:2194001",
          "tgn:1000001",
          "tgn:2001471",
          "tgn:7012149",
          "tgn:7007709",
          "tgn:7029392"
        ],
        "placetype": [
          "aat:300008699"
        ],
        "id": 2194001,
        "name:xx": "Briary Stream"
      }
    },
    {
      "geometry": {
        "type": "Point",
        "coordinates": [
          -85.9667,
          34.0833
        ]
      },
      "type": "Feature",
      "properties": {
        "hierarchy": [
          "tgn:2194002",
          "tgn:7002659",
          "tgn:1000001",
          "tgn:7012149",
          "tgn:2000027",
          "tgn:7029392"
        ],
        "placetype": [
          "aat:300008347"
        ],
        "id": 2194002,
        "name:xx": "Brice"
      }
    },
    {
      "geometry": {
        "type": "Point",
        "coordinates": [
          -90.2667,
          35.0833
        ]
      },
      "type": "Feature",
      "properties": {
        "hierarchy": [
          "tgn:2194003",
          "tgn:1000001",
          "tgn:7016172",
          "tgn:2000122",
          "tgn:7012149",
          "tgn:7029392"
        ],
        "placetype": [
          "aat:300008347"
        ],
        "id": 2194003,
        "name:xx": "Brice"
      }
    },
    {
      "geometry": {
        "type": "Point",
        "coordinates": [
          -85.15,
          34.1
        ]
      },
      "type": "Feature",
      "properties": {
        "hierarchy": [
          "tgn:2194004",
          "tgn:1000001",
          "tgn:7012149",
          "tgn:2000348",
          "tgn:7007248",
          "tgn:7029392"
        ],
        "placetype": [
          "aat:300008347"
        ],
        "id": 2194004,
        "name:xx": "Brice"
      }
    },
    {
      "geometry": {
        "type": "Point",
        "coordinates": [
          -76.9333,
          38.55
        ]
      },
      "type": "Feature",
      "properties": {
        "hierarchy": [
          "tgn:2194005",
          "tgn:7016100",
          "tgn:1000001",
          "tgn:7012149",
          "tgn:7007516",
          "tgn:7029392"
        ],
        "placetype": [
          "aat:300008347"
        ],
        "id": 2194005,
        "name:xx": "Brice"
      }
    },
    {
      "geometry": {
        "type": "Point",
        "coordinates": [
          -84.75,
          43.15
        ]
      },
      "type": "Feature",
      "properties": {
        "hierarchy": [
          "tgn:2194006",
          "tgn:1000001",
          "tgn:7012149",
          "tgn:2000962",
          "tgn:7007520",
          "tgn:7029392"
        ],
        "placetype": [
          "aat:300008347"
        ],
        "id": 2194006,
        "name:xx": "Brice"
      }
    },
    {
      "geometry": {
        "type": "Point",
        "coordinates": [
          -88.4333,
          34.9667
        ]
      },
      "type": "Feature",
      "properties": {
        "hierarchy": [
          "tgn:2194008",
          "tgn:2001087",
          "tgn:1000001",
          "tgn:7012149",
          "tgn:7007522",
          "tgn:7029392"
        ],
        "placetype": [
          "aat:300008699"
        ],
        "id": 2194008,
        "name:xx": "Brice Branch"
      }
    },
    {
      "geometry": {
        "type": "Point",
        "coordinates": [
          -83.75,
          36.1
        ]
      },
      "type": "Feature",
      "properties": {
        "hierarchy": [
          "tgn:2194009",
          "tgn:1000001",
          "tgn:7012149",
          "tgn:2001883",
          "tgn:7007825",
          "tgn:7029392"
        ],
        "placetype": [
          "aat:300008699"
        ],
        "id": 2194009,
        "name:xx": "Brice Branch"
      }
    }
  ]
}
