{
  "geometry": {
    "type": "Point",
    "coordinates": [
      24.25,
      35.366667
    ]
  },
  "type": "Feature",
  "properties": {
    "hierarchy": [
      "tgn:7217980",
      "tgn:7002690",
      "tgn:7012056",
      "tgn:1000003",
      "tgn:1000074",
      "tgn:7029392"
    ],
    "placetype": [
      "aat:300386968"
    ],
    "id": 7217980,
    "name:xx": "Angirovólion Yeoryioupoléos"
  }
}
