{
  "geometry": {
    "type": "Point",
    "coordinates": [
      -107.5167,
      37.0167
    ]
  },
  "type": "Feature",
  "properties": {
    "hierarchy": [
      "tgn:2681369",
      "tgn:1000001",
      "tgn:7012149",
      "tgn:7029392"
    ],
    "placetype": [
      "aat:300006075"
    ],
    "id": 2681369,
    "name:xx": "South Pine River Lateral"
  }
}
