{
  "geometry": {
    "type": "Point",
    "coordinates": [
      120.84887,
      24.27933
    ]
  },
  "type": "Feature",
  "properties": {
    "hierarchy": [
      "tgn:7496038",
      "tgn:1000004",
      "tgn:7001009",
      "tgn:1000141",
      "tgn:7029392"
    ],
    "placetype": [
      "aat:300008798"
    ],
    "id": 7496038,
    "name:xx": "Dongshi"
  }
}
