{
  "geometry": {
    "type": "Point",
    "coordinates": [
      -105.35,
      40.1667
    ]
  },
  "type": "Feature",
  "properties": {
    "hierarchy": [
      "tgn:2164539",
      "tgn:1000001",
      "tgn:2000198",
      "tgn:7012149",
      "tgn:7007158",
      "tgn:7029392"
    ],
    "placetype": [
      "aat:300266640"
    ],
    "id": 2164539,
    "name:xx": "Berry Ridge"
  }
}
