{
  "type": "FeatureCollection",
  "features": [
    {
      "geometry": {
        "type": "Point",
        "coordinates": [
          -91.833333,
          16.833333
        ]
      },
      "type": "Feature",
      "properties": {
        "hierarchy": [
          "tgn:7362340",
          "tgn:7005580",
          "tgn:1000001",
          "tgn:7005560",
          "tgn:7029392"
        ],
        "placetype": [
          "aat:300008347"
        ],
        "id": 7362340,
        "name:xx": "El Paraíso"
      }
    },
    {
      "geometry": {
        "type": "Point",
        "coordinates": [
          -92.783333,
          16.8
        ]
      },
      "type": "Feature",
      "properties": {
        "hierarchy": [
          "tgn:7362341",
          "tgn:7005580",
          "tgn:1000001",
          "tgn:7005560",
          "tgn:7029392"
        ],
        "placetype": [
          "aat:300008347"
        ],
        "id": 7362341,
        "name:xx": "El Paraíso"
      }
    },
    {
      "geometry": {
        "type": "Point",
        "coordinates": [
          -93.9,
          16.616667
        ]
      },
      "type": "Feature",
      "properties": {
        "hierarchy": [
          "tgn:7362342",
          "tgn:7005580",
          "tgn:1000001",
          "tgn:7005560",
          "tgn:7029392"
        ],
        "placetype": [
          "aat:300008347"
        ],
        "id": 7362342,
        "name:xx": "El Paraíso"
      }
    },
    {
      "geometry": {
        "type": "Point",
        "coordinates": [
          -93.416667,
          16.616667
        ]
      },
      "type": "Feature",
      "properties": {
        "hierarchy": [
          "tgn:7362343",
          "tgn:7005580",
          "tgn:1000001",
          "tgn:7005560",
          "tgn:7029392"
        ],
        "placetype": [
          "aat:300008347"
        ],
        "id": 7362343,
        "name:xx": "El Paraíso"
      }
    },
    {
      "geometry": {
        "type": "Point",
        "coordinates": [
          -93.8,
          16.3
        ]
      },
      "type": "Feature",
      "properties": {
        "hierarchy": [
          "tgn:7362344",
          "tgn:7005580",
          "tgn:1000001",
          "tgn:7005560",
          "tgn:7029392"
        ],
        "placetype": [
          "aat:300008347"
        ],
        "id": 7362344,
        "name:xx": "El Paraíso"
      }
    },
    {
      "geometry": {
        "type": "Point",
        "coordinates": [
          -92.4,
          14.983333
        ]
      },
      "type": "Feature",
      "properties": {
        "hierarchy": [
          "tgn:7362345",
          "tgn:7005580",
          "tgn:1000001",
          "tgn:7005560",
          "tgn:7029392"
        ],
        "placetype": [
          "aat:300008347"
        ],
        "id": 7362345,
        "name:xx": "El Paraíso"
      }
    },
    {
      "geometry": {
        "type": "Point",
        "coordinates": [
          -98.9,
          25.883333
        ]
      },
      "type": "Feature",
      "properties": {
        "hierarchy": [
          "tgn:7362347",
          "tgn:1000001",
          "tgn:7005589",
          "tgn:7005560",
          "tgn:7029392"
        ],
        "placetype": [
          "aat:300266554",
          "aat:300008699"
        ],
        "id": 7362347,
        "name:xx": "El Paraguay, Arroyo"
      }
    },
    {
      "geometry": {
        "type": "Point",
        "coordinates": [
          -91.116667,
          18.166667
        ]
      },
      "type": "Feature",
      "properties": {
        "hierarchy": [
          "tgn:7362348",
          "tgn:7005578",
          "tgn:1000001",
          "tgn:7005560",
          "tgn:7029392"
        ],
        "placetype": [
          "aat:300008347"
        ],
        "id": 7362348,
        "name:xx": "El Paraguas"
      }
    },
    {
      "geometry": {
        "type": "Point",
        "coordinates": [
          -96.216667,
          18.916667
        ]
      },
      "type": "Feature",
      "properties": {
        "hierarchy": [
          "tgn:7362349",
          "tgn:1000001",
          "tgn:7005599",
          "tgn:7005560",
          "tgn:7029392"
        ],
        "placetype": [
          "aat:300008347"
        ],
        "id": 7362349,
        "name:xx": "El Parado"
      }
    }
  ]
}
