{
  "geometry": {
    "type": "Point",
    "coordinates": [
      -103.3333,
      29.3333
    ]
  },
  "type": "Feature",
  "properties": {
    "hierarchy": [
      "tgn:2269118",
      "tgn:1000001",
      "tgn:2001945",
      "tgn:7012149",
      "tgn:7007826",
      "tgn:7029392"
    ],
    "placetype": [
      "aat:300008697"
    ],
    "id": 2269118,
    "name:xx": "Croton Spring"
  }
}
