{
  "geometry": {
    "type": "Point",
    "coordinates": [
      36.35,
      -6.4167
    ]
  },
  "type": "Feature",
  "properties": {
    "hierarchy": [
      "tgn:1094758",
      "tgn:1001662",
      "tgn:7001242",
      "tgn:1000203",
      "tgn:7029392"
    ],
    "placetype": [
      "aat:300008347"
    ],
    "id": 1094758,
    "name:xx": "Msagali"
  }
}
