{
  "type": "FeatureCollection",
  "features": [
    {
      "geometry": {
        "type": "Point",
        "coordinates": [
          -73.4667,
          43.9333
        ]
      },
      "type": "Feature",
      "properties": {
        "hierarchy": [
          "tgn:2068743",
          "tgn:1000001",
          "tgn:7012149",
          "tgn:2001461",
          "tgn:7007568",
          "tgn:7029392"
        ],
        "placetype": [
          "aat:300008347",
          "aat:300387210"
        ],
        "id": 2068743,
        "name:xx": "Crown Point Center"
      }
    },
    {
      "geometry": {
        "type": "Point",
        "coordinates": [
          -73.9167,
          41.2333
        ]
      },
      "type": "Feature",
      "properties": {
        "hierarchy": [
          "tgn:2068745",
          "tgn:1000001",
          "tgn:7012149",
          "tgn:7014612",
          "tgn:7007568",
          "tgn:7029392"
        ],
        "placetype": [
          "aat:300008347"
        ],
        "id": 2068745,
        "name:xx": "Crugers"
      }
    },
    {
      "geometry": {
        "type": "Point",
        "coordinates": [
          -74.7,
          43.0333
        ]
      },
      "type": "Feature",
      "properties": {
        "hierarchy": [
          "tgn:2068746",
          "tgn:1000001",
          "tgn:7012149",
          "tgn:1002397",
          "tgn:7007568",
          "tgn:7029392"
        ],
        "placetype": [
          "aat:300008347",
          "aat:300387210"
        ],
        "id": 2068746,
        "name:xx": "Crum Creek"
      }
    },
    {
      "geometry": {
        "type": "Point",
        "coordinates": [
          -75.3333,
          43.8167
        ]
      },
      "type": "Feature",
      "properties": {
        "hierarchy": [
          "tgn:2068747",
          "tgn:1000001",
          "tgn:7012149",
          "tgn:1002593",
          "tgn:7007568",
          "tgn:7029392"
        ],
        "placetype": [
          "aat:300008347",
          "aat:300387210"
        ],
        "id": 2068747,
        "name:xx": "Crystal Dale"
      }
    },
    {
      "geometry": {
        "type": "Point",
        "coordinates": [
          -78.3333,
          42.45
        ]
      },
      "type": "Feature",
      "properties": {
        "hierarchy": [
          "tgn:2068749",
          "tgn:1000001",
          "tgn:1002245",
          "tgn:7012149",
          "tgn:7007568",
          "tgn:7029392"
        ],
        "placetype": [
          "aat:300008680"
        ],
        "id": 2068749,
        "name:xx": "Crystal Lake"
      }
    }
  ]
}
