{
  "geometry": {
    "type": "Point",
    "coordinates": [
      -121.2333,
      40.6667
    ]
  },
  "type": "Feature",
  "properties": {
    "hierarchy": [
      "tgn:2371934",
      "tgn:1000001",
      "tgn:7012149",
      "tgn:7007157",
      "tgn:2000184",
      "tgn:7029392"
    ],
    "placetype": [
      "aat:300006191"
    ],
    "id": 2371934,
    "name:xx": "Half Cabin Reservoir"
  }
}
