{
  "geometry": {
    "type": "Point",
    "coordinates": [
      -82.8667,
      43.8333
    ]
  },
  "type": "Feature",
  "properties": {
    "hierarchy": [
      "tgn:2498234",
      "tgn:1000001",
      "tgn:7012149",
      "tgn:2000964",
      "tgn:7007520",
      "tgn:7029392"
    ],
    "placetype": [
      "aat:300006075"
    ],
    "id": 2498234,
    "name:xx": "Mazure Drain"
  }
}
