{
  "geometry": {
    "type": "Point",
    "coordinates": [
      -82.6333,
      41.2833
    ]
  },
  "type": "Feature",
  "properties": {
    "hierarchy": [
      "tgn:1124766",
      "tgn:1000001",
      "tgn:7012149",
      "tgn:1002357",
      "tgn:7007706",
      "tgn:7029392"
    ],
    "placetype": [
      "aat:300008707"
    ],
    "id": 1124766,
    "name:xx": "Huron"
  }
}
