{
  "type": "FeatureCollection",
  "features": [
    {
      "geometry": {
        "type": "Point",
        "coordinates": [
          -85.6333,
          34.8667
        ]
      },
      "type": "Feature",
      "properties": {
        "hierarchy": [
          "tgn:2467750",
          "tgn:7002659",
          "tgn:1000001",
          "tgn:7012149",
          "tgn:2000035",
          "tgn:7029392"
        ],
        "placetype": [
          "aat:300008706"
        ],
        "id": 2467750,
        "name:xx": "Long Island Creek"
      }
    },
    {
      "geometry": {
        "type": "Point",
        "coordinates": [
          -84.35,
          33.9
        ]
      },
      "type": "Feature",
      "properties": {
        "hierarchy": [
          "tgn:2467751",
          "tgn:1000001",
          "tgn:7012149",
          "tgn:2000351",
          "tgn:7007248",
          "tgn:7029392"
        ],
        "placetype": [
          "aat:300008706"
        ],
        "id": 2467751,
        "name:xx": "Long Island Creek"
      }
    },
    {
      "geometry": {
        "type": "Point",
        "coordinates": [
          -94.7167,
          30.25
        ]
      },
      "type": "Feature",
      "properties": {
        "hierarchy": [
          "tgn:2467752",
          "tgn:1000001",
          "tgn:7012149",
          "tgn:1002595",
          "tgn:7007826",
          "tgn:7029392"
        ],
        "placetype": [
          "aat:300008706"
        ],
        "id": 2467752,
        "name:xx": "Long Island Creek"
      }
    },
    {
      "geometry": {
        "type": "Point",
        "coordinates": [
          -78.2167,
          37.8667
        ]
      },
      "type": "Feature",
      "properties": {
        "hierarchy": [
          "tgn:2467753",
          "tgn:1000001",
          "tgn:7012149",
          "tgn:2002159",
          "tgn:7007919",
          "tgn:7029392"
        ],
        "placetype": [
          "aat:300008706"
        ],
        "id": 2467753,
        "name:xx": "Long Island Creek"
      }
    },
    {
      "geometry": {
        "type": "Point",
        "coordinates": [
          -102.6833,
          40.8667
        ]
      },
      "type": "Feature",
      "properties": {
        "hierarchy": [
          "tgn:2467754",
          "tgn:1000001",
          "tgn:7012149",
          "tgn:7007158",
          "tgn:7029392"
        ],
        "placetype": [
          "aat:300006075"
        ],
        "id": 2467754,
        "name:xx": "Long Island Ditch"
      }
    },
    {
      "geometry": {
        "type": "Point",
        "coordinates": [
          -92.6,
          29.6833
        ]
      },
      "type": "Feature",
      "properties": {
        "hierarchy": [
          "tgn:2467755",
          "tgn:1000001",
          "tgn:7012149",
          "tgn:2000910",
          "tgn:7007256",
          "tgn:7029392"
        ],
        "placetype": [
          "aat:300006075"
        ],
        "id": 2467755,
        "name:xx": "Long Island Ditch"
      }
    },
    {
      "geometry": {
        "type": "Point",
        "coordinates": [
          -68.4833,
          44.3
        ]
      },
      "type": "Feature",
      "properties": {
        "hierarchy": [
          "tgn:2467756",
          "tgn:1000001",
          "tgn:2000922",
          "tgn:7012149",
          "tgn:7007515",
          "tgn:7029392"
        ],
        "placetype": [
          "aat:300008850"
        ],
        "id": 2467756,
        "name:xx": "Long Island Hub"
      }
    },
    {
      "geometry": {
        "type": "Point",
        "coordinates": [
          -90.75,
          48
        ]
      },
      "type": "Feature",
      "properties": {
        "hierarchy": [
          "tgn:2467757",
          "tgn:1000001",
          "tgn:2001014",
          "tgn:7012149",
          "tgn:7007521",
          "tgn:7029392"
        ],
        "placetype": [
          "aat:300008680"
        ],
        "id": 2467757,
        "name:xx": "Long Island Lake"
      }
    },
    {
      "geometry": {
        "type": "Point",
        "coordinates": [
          -69.4,
          43.9833
        ]
      },
      "type": "Feature",
      "properties": {
        "hierarchy": [
          "tgn:2467758",
          "tgn:1000001",
          "tgn:2000925",
          "tgn:7012149",
          "tgn:7007515",
          "tgn:7029392"
        ],
        "placetype": [
          "aat:300132348"
        ],
        "id": 2467758,
        "name:xx": "Long Island Ledges"
      }
    },
    {
      "geometry": {
        "type": "Point",
        "coordinates": [
          -81.6167,
          27
        ]
      },
      "type": "Feature",
      "properties": {
        "hierarchy": [
          "tgn:2467759",
          "tgn:1000001",
          "tgn:7012149",
          "tgn:7007240",
          "tgn:7029392"
        ],
        "placetype": [
          "aat:300008905"
        ],
        "id": 2467759,
        "name:xx": "Long Island Marsh"
      }
    }
  ]
}
