{
  "geometry": {
    "type": "Point",
    "coordinates": [
      -90.4167,
      45.8667
    ]
  },
  "type": "Feature",
  "properties": {
    "hierarchy": [
      "tgn:2121195",
      "tgn:1000001",
      "tgn:7012149",
      "tgn:2002348",
      "tgn:7007922",
      "tgn:7029392"
    ],
    "placetype": [
      "aat:300008347"
    ],
    "id": 2121195,
    "name:xx": "Fifield"
  }
}
