{
  "geometry": {
    "type": "Point",
    "coordinates": [
      -104.5667,
      44.2333
    ]
  },
  "type": "Feature",
  "properties": {
    "hierarchy": [
      "tgn:2210200",
      "tgn:1000001",
      "tgn:2002370",
      "tgn:7012149",
      "tgn:7007923",
      "tgn:7029392"
    ],
    "placetype": [
      "aat:300008761"
    ],
    "id": 2210200,
    "name:xx": "Busby Draw"
  }
}
