{
  "geometry": {
    "type": "Point",
    "coordinates": [
      -77.05,
      36.0667
    ]
  },
  "type": "Feature",
  "properties": {
    "hierarchy": [
      "tgn:2076324",
      "tgn:1000001",
      "tgn:2001470",
      "tgn:7012149",
      "tgn:7007709",
      "tgn:7029392"
    ],
    "placetype": [
      "aat:300008347"
    ],
    "id": 2076324,
    "name:xx": "Republican"
  }
}
