{
  "geometry": {
    "type": "Point",
    "coordinates": [
      -87.5667,
      32.65
    ]
  },
  "type": "Feature",
  "properties": {
    "hierarchy": [
      "tgn:2446511",
      "tgn:7002659",
      "tgn:1000001",
      "tgn:7012149",
      "tgn:2000032",
      "tgn:7029392"
    ],
    "placetype": [
      "aat:300006191"
    ],
    "id": 2446511,
    "name:xx": "Lewis Lawson Lake Number Five"
  }
}
