{
  "geometry": {
    "type": "Point",
    "coordinates": [
      82.866667,
      19.966667
    ]
  },
  "type": "Feature",
  "properties": {
    "hierarchy": [
      "tgn:7551569",
      "tgn:1000004",
      "tgn:7031781",
      "tgn:7000198",
      "tgn:7029392"
    ],
    "placetype": [
      "aat:300008347"
    ],
    "name:en": "Dāspur",
    "id": 7551569
  }
}
