{
  "geometry": {
    "type": "Point",
    "coordinates": [
      -43.55,
      -22.5333
    ]
  },
  "type": "Feature",
  "properties": {
    "hierarchy": [
      "tgn:1021217",
      "tgn:1001942",
      "tgn:1000047",
      "tgn:7002457",
      "tgn:1000002",
      "tgn:7029392"
    ],
    "placetype": [
      "aat:300008347"
    ],
    "id": 1021217,
    "name:xx": "Conrado"
  }
}
