{
  "geometry": {
    "type": "Point",
    "coordinates": [
      -109.2833,
      38.2833
    ]
  },
  "type": "Feature",
  "properties": {
    "hierarchy": [
      "tgn:2740740",
      "tgn:1000001",
      "tgn:7012149",
      "tgn:2002119",
      "tgn:7007827",
      "tgn:7029392"
    ],
    "placetype": [
      "aat:300006191"
    ],
    "id": 2740740,
    "name:xx": "Upper Rattlesnake Ranch Number One Reservoir"
  }
}
