{
  "type": "FeatureCollection",
  "features": [
    {
      "geometry": {
        "type": "Point",
        "coordinates": [
          -104.65,
          25.216667
        ]
      },
      "type": "Feature",
      "properties": {
        "hierarchy": [
          "tgn:7440130",
          "tgn:7005583",
          "tgn:1000001",
          "tgn:7005560",
          "tgn:7029392"
        ],
        "placetype": [
          "aat:300008795"
        ],
        "id": 7440130,
        "name:xx": "San Pedro, Cerro de"
      }
    },
    {
      "geometry": {
        "type": "Point",
        "coordinates": [
          -109.25,
          27.166667
        ]
      },
      "type": "Feature",
      "properties": {
        "hierarchy": [
          "tgn:7440131",
          "tgn:1000001",
          "tgn:1001960",
          "tgn:7005560",
          "tgn:7029392"
        ],
        "placetype": [
          "aat:300008795"
        ],
        "id": 7440131,
        "name:xx": "San Pedro, Cerro"
      }
    },
    {
      "geometry": {
        "type": "Point",
        "coordinates": [
          -108.5175,
          26.520278
        ]
      },
      "type": "Feature",
      "properties": {
        "hierarchy": [
          "tgn:7440132",
          "tgn:1000001",
          "tgn:7005595",
          "tgn:7005560",
          "tgn:7029392"
        ],
        "placetype": [
          "aat:300008795"
        ],
        "id": 7440132,
        "name:xx": "San Pedro, Cerro"
      }
    },
    {
      "geometry": {
        "type": "Point",
        "coordinates": [
          -106.05,
          25.983333
        ]
      },
      "type": "Feature",
      "properties": {
        "hierarchy": [
          "tgn:7440133",
          "tgn:7005583",
          "tgn:1000001",
          "tgn:7005560",
          "tgn:7029392"
        ],
        "placetype": [
          "aat:300008795"
        ],
        "id": 7440133,
        "name:xx": "San Pedro, Cerro"
      }
    },
    {
      "geometry": {
        "type": "Point",
        "coordinates": [
          -104.916667,
          20.316667
        ]
      },
      "type": "Feature",
      "properties": {
        "hierarchy": [
          "tgn:7440134",
          "tgn:7005586",
          "tgn:1000001",
          "tgn:7005560",
          "tgn:7029392"
        ],
        "placetype": [
          "aat:300008795"
        ],
        "id": 7440134,
        "name:xx": "San Pedro, Cerro"
      }
    },
    {
      "geometry": {
        "type": "Point",
        "coordinates": [
          -103.933333,
          22.766667
        ]
      },
      "type": "Feature",
      "properties": {
        "hierarchy": [
          "tgn:7440135",
          "tgn:1000001",
          "tgn:7005601",
          "tgn:7005560",
          "tgn:7029392"
        ],
        "placetype": [
          "aat:300008777"
        ],
        "id": 7440135,
        "name:xx": "San Pedro, Cerro"
      }
    },
    {
      "geometry": {
        "type": "Point",
        "coordinates": [
          -100.966667,
          24.6
        ]
      },
      "type": "Feature",
      "properties": {
        "hierarchy": [
          "tgn:7440136",
          "tgn:1001853",
          "tgn:1000001",
          "tgn:7005560",
          "tgn:7029392"
        ],
        "placetype": [
          "aat:300008763"
        ],
        "id": 7440136,
        "name:xx": "San Pedro, Cañón de"
      }
    },
    {
      "geometry": {
        "type": "Point",
        "coordinates": [
          -92.466667,
          18.65
        ]
      },
      "type": "Feature",
      "properties": {
        "hierarchy": [
          "tgn:7440137",
          "tgn:1000001",
          "tgn:1001893",
          "tgn:7005560",
          "tgn:7029392"
        ],
        "placetype": [
          "aat:300386885"
        ],
        "id": 7440137,
        "name:xx": "San Pedro, Barra de"
      }
    },
    {
      "geometry": {
        "type": "Point",
        "coordinates": [
          -111.283333,
          28.083333
        ]
      },
      "type": "Feature",
      "properties": {
        "hierarchy": [
          "tgn:7440138",
          "tgn:1000001",
          "tgn:1001960",
          "tgn:7005560",
          "tgn:7029392"
        ],
        "placetype": [
          "aat:300132317"
        ],
        "id": 7440138,
        "name:xx": "San Pedro, Bahía"
      }
    },
    {
      "geometry": {
        "type": "Point",
        "coordinates": [
          -100.15,
          27.933333
        ]
      },
      "type": "Feature",
      "properties": {
        "hierarchy": [
          "tgn:7440139",
          "tgn:1001853",
          "tgn:1000001",
          "tgn:7005560",
          "tgn:7029392"
        ],
        "placetype": [
          "aat:300008699"
        ],
        "id": 7440139,
        "name:xx": "San Pedro, Arroyo de"
      }
    }
  ]
}
