{
  "geometry": {
    "type": "Point",
    "coordinates": [
      34.071655,
      23.118318
    ]
  },
  "type": "Feature",
  "properties": {
    "hierarchy": [
      "tgn:7522046",
      "tgn:7001242",
      "tgn:7001311",
      "tgn:7016833",
      "tgn:7029392"
    ],
    "placetype": [
      "aat:300008795"
    ],
    "name:en": "Abū Raḩāyah, Jabal",
    "id": 7522046
  }
}
