{
  "geometry": {
    "type": "Point",
    "coordinates": [
      -103.9167,
      43.0667
    ]
  },
  "type": "Feature",
  "properties": {
    "hierarchy": [
      "tgn:2216599",
      "tgn:1000001",
      "tgn:2001793",
      "tgn:7012149",
      "tgn:7007713",
      "tgn:7029392"
    ],
    "placetype": [
      "aat:300008706"
    ],
    "id": 2216599,
    "name:xx": "Camp Creek"
  }
}
