{
  "geometry": {
    "type": "Point",
    "coordinates": [
      14.5833,
      46.2333
    ]
  },
  "type": "Feature",
  "properties": {
    "hierarchy": [
      "tgn:7015644",
      "tgn:7015101",
      "tgn:1000003",
      "tgn:7006670",
      "tgn:7029392"
    ],
    "placetype": [
      "aat:300008347",
      "aat:300387222",
      "aat:300008375"
    ],
    "id": 7015644,
    "name:xx": "Kamnik"
  }
}
