{
  "geometry": {
    "type": "Point",
    "coordinates": [
      -76.6167,
      42.35
    ]
  },
  "type": "Feature",
  "properties": {
    "hierarchy": [
      "tgn:2327883",
      "tgn:1000001",
      "tgn:7012149",
      "tgn:1002950",
      "tgn:7007568",
      "tgn:7029392"
    ],
    "placetype": [
      "aat:300008699"
    ],
    "id": 2327883,
    "name:xx": "Fish Kill"
  }
}
