{
  "geometry": {
    "type": "Point",
    "coordinates": [
      -113.1667,
      35.3167
    ]
  },
  "type": "Feature",
  "properties": {
    "hierarchy": [
      "tgn:2653572",
      "tgn:1000001",
      "tgn:7006451",
      "tgn:7012149",
      "tgn:2000103",
      "tgn:7029392"
    ],
    "placetype": [
      "aat:300008805"
    ],
    "id": 2653572,
    "name:xx": "Seventyfour Plains"
  }
}
