{
  "geometry": {
    "type": "Point",
    "coordinates": [
      -82.55,
      38.7833
    ]
  },
  "type": "Feature",
  "properties": {
    "hierarchy": [
      "tgn:2298383",
      "tgn:1000001",
      "tgn:7012149",
      "tgn:7007706",
      "tgn:7029392"
    ],
    "placetype": [
      "aat:300266640"
    ],
    "id": 2298383,
    "name:xx": "Dry Ridge"
  }
}
