{
  "geometry": {
    "type": "Point",
    "coordinates": [
      121.4776,
      25.1298
    ]
  },
  "type": "Feature",
  "properties": {
    "hierarchy": [
      "tgn:7489372",
      "tgn:1000004",
      "tgn:1000959",
      "tgn:1000141",
      "tgn:7029392"
    ],
    "placetype": [
      "aat:300387173"
    ],
    "id": 7489372,
    "name:xx": "Yide Li"
  }
}
