{
  "geometry": {
    "type": "Point",
    "coordinates": [
      -89.0833,
      32.3833
    ]
  },
  "type": "Feature",
  "properties": {
    "hierarchy": [
      "tgn:2748189",
      "tgn:1000001",
      "tgn:7012149",
      "tgn:2001136",
      "tgn:7007522",
      "tgn:7029392"
    ],
    "placetype": [
      "aat:300008699"
    ],
    "id": 2748189,
    "name:xx": "Walker Branch"
  }
}
