{
  "geometry": {
    "type": "Point",
    "coordinates": [
      -120.6833,
      35.4167
    ]
  },
  "type": "Feature",
  "properties": {
    "hierarchy": [
      "tgn:2303812",
      "tgn:1000001",
      "tgn:7012149",
      "tgn:7007157",
      "tgn:1002863",
      "tgn:7029392"
    ],
    "placetype": [
      "aat:300008798"
    ],
    "id": 2303812,
    "name:xx": "Eagle Peak"
  }
}
