{
  "geometry": {
    "type": "Point",
    "coordinates": [
      -89.6167,
      35.45
    ]
  },
  "type": "Feature",
  "properties": {
    "hierarchy": [
      "tgn:2508020",
      "tgn:1000001",
      "tgn:7012149",
      "tgn:7007825",
      "tgn:7029392"
    ],
    "placetype": [
      "aat:300006075"
    ],
    "id": 2508020,
    "name:xx": "Middle Beaver Creek Canal"
  }
}
