{
  "geometry": {
    "type": "Point",
    "coordinates": [
      -72.5167,
      40.9833
    ]
  },
  "type": "Feature",
  "properties": {
    "hierarchy": [
      "tgn:2418890",
      "tgn:1000001",
      "tgn:7012149",
      "tgn:1002924",
      "tgn:7007568",
      "tgn:7029392"
    ],
    "placetype": [
      "aat:300008706"
    ],
    "id": 2418890,
    "name:xx": "James Creek"
  }
}
