{
  "geometry": {
    "type": "Point",
    "coordinates": [
      -77.0333,
      38.5333
    ]
  },
  "type": "Feature",
  "properties": {
    "hierarchy": [
      "tgn:2047876",
      "tgn:7016100",
      "tgn:1000001",
      "tgn:7012149",
      "tgn:7007516",
      "tgn:7029392"
    ],
    "placetype": [
      "aat:300008347",
      "aat:300387210"
    ],
    "id": 2047876,
    "name:xx": "Marshalls Corner"
  }
}
