{
  "geometry": {
    "type": "Point",
    "coordinates": [
      117.7833,
      4.1333
    ]
  },
  "type": "Feature",
  "properties": {
    "hierarchy": [
      "tgn:1009071",
      "tgn:1000004",
      "tgn:7029392"
    ],
    "placetype": [
      "aat:300008791"
    ],
    "id": 1009071,
    "name:xx": "Sebatik, Pulau"
  }
}
