{
  "geometry": {
    "type": "Point",
    "coordinates": [
      -84.8833,
      42.3667
    ]
  },
  "type": "Feature",
  "properties": {
    "hierarchy": [
      "tgn:2691923",
      "tgn:1000001",
      "tgn:1002222",
      "tgn:7012149",
      "tgn:7007520",
      "tgn:7029392"
    ],
    "placetype": [
      "aat:300006075"
    ],
    "id": 2691923,
    "name:xx": "State And Indian Creek Drain"
  }
}
