{
  "geometry": {
    "type": "Point",
    "coordinates": [
      80.25,
      20.85
    ]
  },
  "type": "Feature",
  "properties": {
    "hierarchy": [
      "tgn:7552383",
      "tgn:1000004",
      "tgn:7000198",
      "tgn:1001895",
      "tgn:7029392"
    ],
    "placetype": [
      "aat:300008347"
    ],
    "name:en": "Palāndur",
    "id": 7552383
  }
}
