{
  "geometry": {
    "type": "Point",
    "coordinates": [
      -110.5833,
      42.3667
    ]
  },
  "type": "Feature",
  "properties": {
    "hierarchy": [
      "tgn:2456263",
      "tgn:1000001",
      "tgn:7012149",
      "tgn:7007923",
      "tgn:7029392"
    ],
    "placetype": [
      "aat:300008706"
    ],
    "id": 2456263,
    "name:xx": "Little Hornet Creek"
  }
}
