{
  "geometry": {
    "type": "Point",
    "coordinates": [
      -83.0333,
      37.9833
    ]
  },
  "type": "Feature",
  "properties": {
    "hierarchy": [
      "tgn:2313456",
      "tgn:1000001",
      "tgn:7012149",
      "tgn:1002354",
      "tgn:7007255",
      "tgn:7029392"
    ],
    "placetype": [
      "aat:300008699"
    ],
    "id": 2313456,
    "name:xx": "Eldridge Branch"
  }
}
