{
  "geometry": {
    "type": "Point",
    "coordinates": [
      -83.15,
      33.9167
    ]
  },
  "type": "Feature",
  "properties": {
    "hierarchy": [
      "tgn:2285824",
      "tgn:1000001",
      "tgn:7012149",
      "tgn:2000400",
      "tgn:7007248",
      "tgn:7029392"
    ],
    "placetype": [
      "aat:300006191"
    ],
    "id": 2285824,
    "name:xx": "Devils Pond"
  }
}
