{
  "geometry": {
    "type": "Point",
    "coordinates": [
      -7.9167,
      52.3667
    ]
  },
  "type": "Feature",
  "properties": {
    "hierarchy": [
      "tgn:1042669",
      "tgn:7593749",
      "tgn:7001201",
      "tgn:1000003",
      "tgn:1000078",
      "tgn:7029392"
    ],
    "placetype": [
      "aat:300008347"
    ],
    "id": 1042669,
    "name:xx": "Cahir"
  }
}
