{
  "geometry": {
    "type": "Point",
    "coordinates": [
      -92.0833,
      46.75
    ]
  },
  "type": "Feature",
  "properties": {
    "hierarchy": [
      "tgn:2300451",
      "tgn:1000001",
      "tgn:7012149",
      "tgn:2001067",
      "tgn:7007521",
      "tgn:7029392"
    ],
    "placetype": [
      "aat:300132316"
    ],
    "id": 2300451,
    "name:xx": "Duluth Harbor Basin Southern Section"
  }
}
