{
  "geometry": {
    "type": "Point",
    "coordinates": [
      102.0167,
      14.7167
    ]
  },
  "type": "Feature",
  "properties": {
    "hierarchy": [
      "tgn:1085618",
      "tgn:7005193",
      "tgn:1000004",
      "tgn:7000932",
      "tgn:1000142",
      "tgn:7029392"
    ],
    "placetype": [
      "aat:300008347"
    ],
    "id": 1085618,
    "name:xx": "Pak Thong Chai"
  }
}
