{
  "geometry": {
    "type": "Point",
    "coordinates": [
      132.6333,
      33.9667
    ]
  },
  "type": "Feature",
  "properties": {
    "hierarchy": [
      "tgn:1080939",
      "tgn:7004473",
      "tgn:1000004",
      "tgn:7000903",
      "tgn:1008276",
      "tgn:1000120",
      "tgn:7029392"
    ],
    "placetype": [
      "aat:300008347"
    ],
    "id": 1080939,
    "name:xx": "Nakajima"
  }
}
