{
  "geometry": {
    "type": "Point",
    "coordinates": [
      -106.5833,
      31.8167
    ]
  },
  "type": "Feature",
  "properties": {
    "hierarchy": [
      "tgn:2521574",
      "tgn:1000001",
      "tgn:7012149",
      "tgn:2001981",
      "tgn:7007826",
      "tgn:7029392"
    ],
    "placetype": [
      "aat:300006075"
    ],
    "id": 2521574,
    "name:xx": "Montoya Drain"
  }
}
