{
  "geometry": {
    "type": "Point",
    "coordinates": [
      -119.5667,
      45.0167
    ]
  },
  "type": "Feature",
  "properties": {
    "hierarchy": [
      "tgn:2719936",
      "tgn:1000001",
      "tgn:7012149",
      "tgn:7007708",
      "tgn:7029392"
    ],
    "placetype": [
      "aat:300008706"
    ],
    "id": 2719936,
    "name:xx": "Three Trough Creek"
  }
}
