{
  "geometry": {
    "type": "Point",
    "coordinates": [
      120.5698,
      24.0556
    ]
  },
  "type": "Feature",
  "properties": {
    "hierarchy": [
      "tgn:7472088",
      "tgn:1000004",
      "tgn:7467799",
      "tgn:1000141",
      "tgn:7029392"
    ],
    "placetype": [
      "aat:300008347"
    ],
    "id": 7472088,
    "name:xx": "Caozibu"
  }
}
