{
  "geometry": {
    "type": "Point",
    "coordinates": [
      123.1667,
      41.9667
    ]
  },
  "type": "Feature",
  "properties": {
    "hierarchy": [
      "tgn:1139232",
      "tgn:1000004",
      "tgn:1001390",
      "tgn:1000111",
      "tgn:7029392"
    ],
    "placetype": [
      "aat:300008347"
    ],
    "id": 1139232,
    "name:xx": "Laobian"
  }
}
