{
  "type": "FeatureCollection",
  "features": [
    {
      "geometry": {
        "type": "Point",
        "coordinates": [
          -88.4667,
          37.0333
        ]
      },
      "type": "Feature",
      "properties": {
        "hierarchy": [
          "tgn:2039810",
          "tgn:1000001",
          "tgn:7012149",
          "tgn:2000814",
          "tgn:7007255",
          "tgn:7029392"
        ],
        "placetype": [
          "aat:300008347"
        ],
        "id": 2039810,
        "name:xx": "Ledbetter"
      }
    },
    {
      "geometry": {
        "type": "Point",
        "coordinates": [
          -82.7,
          38.0167
        ]
      },
      "type": "Feature",
      "properties": {
        "hierarchy": [
          "tgn:2039811",
          "tgn:1000001",
          "tgn:7012149",
          "tgn:2000809",
          "tgn:7007255",
          "tgn:7029392"
        ],
        "placetype": [
          "aat:300008347",
          "aat:300387210"
        ],
        "id": 2039811,
        "name:xx": "Ledocio"
      }
    },
    {
      "geometry": {
        "type": "Point",
        "coordinates": [
          -83.3167,
          37.7333
        ]
      },
      "type": "Feature",
      "properties": {
        "hierarchy": [
          "tgn:2039813",
          "tgn:1000001",
          "tgn:7012149",
          "tgn:2000853",
          "tgn:7007255",
          "tgn:7029392"
        ],
        "placetype": [
          "aat:300008347"
        ],
        "id": 2039813,
        "name:xx": "Lee City"
      }
    },
    {
      "geometry": {
        "type": "Point",
        "coordinates": [
          -83.6833,
          37.7
        ]
      },
      "type": "Feature",
      "properties": {
        "hierarchy": [
          "tgn:2039814",
          "tgn:1000001",
          "tgn:7012149",
          "tgn:2000810",
          "tgn:7007255",
          "tgn:7029392"
        ],
        "placetype": [
          "aat:300008347"
        ],
        "id": 2039814,
        "name:xx": "Leeco"
      }
    },
    {
      "geometry": {
        "type": "Point",
        "coordinates": [
          -84.4167,
          38.2833
        ]
      },
      "type": "Feature",
      "properties": {
        "hierarchy": [
          "tgn:2039815",
          "tgn:1000001",
          "tgn:7012149",
          "tgn:1002458",
          "tgn:7007255",
          "tgn:7029392"
        ],
        "placetype": [
          "aat:300008347"
        ],
        "id": 2039815,
        "name:xx": "Leesburg"
      }
    },
    {
      "geometry": {
        "type": "Point",
        "coordinates": [
          -84.4167,
          38.3333
        ]
      },
      "type": "Feature",
      "properties": {
        "hierarchy": [
          "tgn:2039816",
          "tgn:1000001",
          "tgn:7012149",
          "tgn:1002458",
          "tgn:7007255",
          "tgn:7029392"
        ],
        "placetype": [
          "aat:300008347",
          "aat:300387210"
        ],
        "id": 2039816,
        "name:xx": "Lees Lick"
      }
    },
    {
      "geometry": {
        "type": "Point",
        "coordinates": [
          -83.8833,
          37.6
        ]
      },
      "type": "Feature",
      "properties": {
        "hierarchy": [
          "tgn:2039819",
          "tgn:1000001",
          "tgn:7012149",
          "tgn:2000788",
          "tgn:7007255",
          "tgn:7029392"
        ],
        "placetype": [
          "aat:300008347",
          "aat:300387210"
        ],
        "id": 2039819,
        "name:xx": "Leighton"
      }
    }
  ]
}
