{
  "geometry": {
    "type": "Point",
    "coordinates": [
      79.0167,
      44.65
    ]
  },
  "type": "Feature",
  "properties": {
    "hierarchy": [
      "tgn:1059028",
      "tgn:1000004",
      "tgn:1003416",
      "tgn:7014786",
      "tgn:7029392"
    ],
    "placetype": [
      "aat:300008347"
    ],
    "id": 1059028,
    "name:xx": "Rudnichnyy"
  }
}
