{
  "geometry": {
    "type": "Point",
    "coordinates": [
      -78.5667,
      43.1833
    ]
  },
  "type": "Feature",
  "properties": {
    "hierarchy": [
      "tgn:2517805",
      "tgn:1000001",
      "tgn:7012149",
      "tgn:1002718",
      "tgn:7007568",
      "tgn:7029392"
    ],
    "placetype": [
      "aat:300008680"
    ],
    "id": 2517805,
    "name:xx": "Mirror Lake"
  }
}
