{
  "geometry": {
    "type": "Point",
    "coordinates": [
      -150.4167,
      68.0667
    ]
  },
  "type": "Feature",
  "properties": {
    "hierarchy": [
      "tgn:2559580",
      "tgn:7006450",
      "tgn:1000001",
      "tgn:7012149",
      "tgn:2124005",
      "tgn:7029392"
    ],
    "placetype": [
      "aat:300008761"
    ],
    "id": 2559580,
    "name:xx": "Oolah Valley"
  }
}
