{
  "type": "FeatureCollection",
  "features": [
    {
      "geometry": {
        "type": "Point",
        "coordinates": [
          -83.25,
          31.25
        ]
      },
      "type": "Feature",
      "properties": {
        "hierarchy": [
          "tgn:2613791",
          "tgn:1000001",
          "tgn:2000301",
          "tgn:7012149",
          "tgn:7007248",
          "tgn:7029392"
        ],
        "placetype": [
          "aat:300008706"
        ],
        "id": 2613791,
        "name:xx": "Reedy Creek"
      }
    },
    {
      "geometry": {
        "type": "Point",
        "coordinates": [
          -83.25,
          31.5
        ]
      },
      "type": "Feature",
      "properties": {
        "hierarchy": [
          "tgn:2613792",
          "tgn:1000001",
          "tgn:7012149",
          "tgn:2000368",
          "tgn:7007248",
          "tgn:7029392"
        ],
        "placetype": [
          "aat:300008706"
        ],
        "id": 2613792,
        "name:xx": "Reedy Creek"
      }
    },
    {
      "geometry": {
        "type": "Point",
        "coordinates": [
          -84.45,
          31.8667
        ]
      },
      "type": "Feature",
      "properties": {
        "hierarchy": [
          "tgn:2613793",
          "tgn:1000001",
          "tgn:7012149",
          "tgn:2000426",
          "tgn:7007248",
          "tgn:7029392"
        ],
        "placetype": [
          "aat:300008706"
        ],
        "id": 2613793,
        "name:xx": "Reedy Creek"
      }
    },
    {
      "geometry": {
        "type": "Point",
        "coordinates": [
          -82.3333,
          32.3667
        ]
      },
      "type": "Feature",
      "properties": {
        "hierarchy": [
          "tgn:2613794",
          "tgn:1000001",
          "tgn:7012149",
          "tgn:7007248",
          "tgn:7029392"
        ],
        "placetype": [
          "aat:300008706"
        ],
        "id": 2613794,
        "name:xx": "Reedy Creek"
      }
    },
    {
      "geometry": {
        "type": "Point",
        "coordinates": [
          -82.4667,
          32.45
        ]
      },
      "type": "Feature",
      "properties": {
        "hierarchy": [
          "tgn:2613795",
          "tgn:1000001",
          "tgn:7012149",
          "tgn:2000431",
          "tgn:7007248",
          "tgn:7029392"
        ],
        "placetype": [
          "aat:300008706"
        ],
        "id": 2613795,
        "name:xx": "Reedy Creek"
      }
    },
    {
      "geometry": {
        "type": "Point",
        "coordinates": [
          -83.9,
          32.9833
        ]
      },
      "type": "Feature",
      "properties": {
        "hierarchy": [
          "tgn:2613796",
          "tgn:1000001",
          "tgn:7012149",
          "tgn:2000393",
          "tgn:7007248",
          "tgn:7029392"
        ],
        "placetype": [
          "aat:300008706"
        ],
        "id": 2613796,
        "name:xx": "Reedy Creek"
      }
    },
    {
      "geometry": {
        "type": "Point",
        "coordinates": [
          -83.2333,
          33.0167
        ]
      },
      "type": "Feature",
      "properties": {
        "hierarchy": [
          "tgn:2613797",
          "tgn:2000296",
          "tgn:1000001",
          "tgn:7012149",
          "tgn:7007248",
          "tgn:7029392"
        ],
        "placetype": [
          "aat:300008706"
        ],
        "id": 2613797,
        "name:xx": "Reedy Creek"
      }
    },
    {
      "geometry": {
        "type": "Point",
        "coordinates": [
          -83.6833,
          33.7
        ]
      },
      "type": "Feature",
      "properties": {
        "hierarchy": [
          "tgn:2613798",
          "tgn:1000001",
          "tgn:7012149",
          "tgn:2000438",
          "tgn:7007248",
          "tgn:7029392"
        ],
        "placetype": [
          "aat:300008706"
        ],
        "id": 2613798,
        "name:xx": "Reedy Creek"
      }
    },
    {
      "geometry": {
        "type": "Point",
        "coordinates": [
          -82.9833,
          30.9333
        ]
      },
      "type": "Feature",
      "properties": {
        "hierarchy": [
          "tgn:2613799",
          "tgn:1000001",
          "tgn:7012149",
          "tgn:2000377",
          "tgn:7007248",
          "tgn:7029392"
        ],
        "placetype": [
          "aat:300008706"
        ],
        "id": 2613799,
        "name:xx": "Reedy Creek"
      }
    }
  ]
}
