{
  "geometry": {
    "type": "Point",
    "coordinates": [
      -114.2833,
      44.4167
    ]
  },
  "type": "Feature",
  "properties": {
    "hierarchy": [
      "tgn:2780493",
      "tgn:1000001",
      "tgn:2000470",
      "tgn:7012149",
      "tgn:7007250",
      "tgn:7029392"
    ],
    "placetype": [
      "aat:300008706"
    ],
    "id": 2780493,
    "name:xx": "Wood Creek"
  }
}
