{
  "geometry": {
    "type": "Point",
    "coordinates": [
      -58.8167,
      -3.9667
    ]
  },
  "type": "Feature",
  "properties": {
    "hierarchy": [
      "tgn:1126888",
      "tgn:7006247",
      "tgn:1000047",
      "tgn:7002456",
      "tgn:1000002",
      "tgn:7029392"
    ],
    "placetype": [
      "aat:300008707"
    ],
    "id": 1126888,
    "name:xx": "Marimari"
  }
}
