{
  "geometry": {
    "type": "Point",
    "coordinates": [
      41.9333,
      55.3333
    ]
  },
  "type": "Feature",
  "properties": {
    "hierarchy": [
      "tgn:1056237",
      "tgn:1000004",
      "tgn:1003421",
      "tgn:7018214",
      "tgn:7002435",
      "tgn:7029392"
    ],
    "placetype": [
      "aat:300008347"
    ],
    "id": 1056237,
    "name:xx": "Lyakhi"
  }
}
