{
  "type": "FeatureCollection",
  "features": [
    {
      "geometry": {
        "type": "Point",
        "coordinates": [
          -121.95,
          45.3833
        ]
      },
      "type": "Feature",
      "properties": {
        "hierarchy": [
          "tgn:2548600",
          "tgn:1000001",
          "tgn:1002270",
          "tgn:7012149",
          "tgn:7007708",
          "tgn:7029392"
        ],
        "placetype": [
          "aat:300008798"
        ],
        "id": 2548600,
        "name:xx": "North Mountain"
      }
    },
    {
      "geometry": {
        "type": "Point",
        "coordinates": [
          -76.2,
          41.3167
        ]
      },
      "type": "Feature",
      "properties": {
        "hierarchy": [
          "tgn:2548601",
          "tgn:1000001",
          "tgn:7012149",
          "tgn:7007710",
          "tgn:7029392"
        ],
        "placetype": [
          "aat:300008798"
        ],
        "id": 2548601,
        "name:xx": "North Mountain"
      }
    },
    {
      "geometry": {
        "type": "Point",
        "coordinates": [
          -83.8667,
          36.5333
        ]
      },
      "type": "Feature",
      "properties": {
        "hierarchy": [
          "tgn:2548602",
          "tgn:1000001",
          "tgn:7012149",
          "tgn:2001849",
          "tgn:7007825",
          "tgn:7029392"
        ],
        "placetype": [
          "aat:300008798"
        ],
        "id": 2548602,
        "name:xx": "North Mountain"
      }
    },
    {
      "geometry": {
        "type": "Point",
        "coordinates": [
          -103.1667,
          30.5667
        ]
      },
      "type": "Feature",
      "properties": {
        "hierarchy": [
          "tgn:2548603",
          "tgn:1000001",
          "tgn:7012149",
          "tgn:2002055",
          "tgn:7007826",
          "tgn:7029392"
        ],
        "placetype": [
          "aat:300008798"
        ],
        "id": 2548603,
        "name:xx": "North Mountain"
      }
    },
    {
      "geometry": {
        "type": "Point",
        "coordinates": [
          -104.6667,
          31.6667
        ]
      },
      "type": "Feature",
      "properties": {
        "hierarchy": [
          "tgn:2548604",
          "tgn:1000001",
          "tgn:7012149",
          "tgn:2001969",
          "tgn:7007826",
          "tgn:7029392"
        ],
        "placetype": [
          "aat:300008798"
        ],
        "id": 2548604,
        "name:xx": "North Mountain"
      }
    },
    {
      "geometry": {
        "type": "Point",
        "coordinates": [
          -79.2667,
          38.15
        ]
      },
      "type": "Feature",
      "properties": {
        "hierarchy": [
          "tgn:2548605",
          "tgn:2002142",
          "tgn:1000001",
          "tgn:7012149",
          "tgn:7007919",
          "tgn:7029392"
        ],
        "placetype": [
          "aat:300008347"
        ],
        "id": 2548605,
        "name:xx": "North Mountain"
      }
    },
    {
      "geometry": {
        "type": "Point",
        "coordinates": [
          -78.15,
          39.3167
        ]
      },
      "type": "Feature",
      "properties": {
        "hierarchy": [
          "tgn:2548606",
          "tgn:1000001",
          "tgn:7012149",
          "tgn:7029392"
        ],
        "placetype": [
          "aat:300008798"
        ],
        "id": 2548606,
        "name:xx": "North Mountain"
      }
    },
    {
      "geometry": {
        "type": "Point",
        "coordinates": [
          -121.6,
          48.3167
        ]
      },
      "type": "Feature",
      "properties": {
        "hierarchy": [
          "tgn:2548607",
          "tgn:1000001",
          "tgn:7012149",
          "tgn:7014510",
          "tgn:7007920",
          "tgn:7029392"
        ],
        "placetype": [
          "aat:300008798"
        ],
        "id": 2548607,
        "name:xx": "North Mountain"
      }
    },
    {
      "geometry": {
        "type": "Point",
        "coordinates": [
          -110.5,
          42.5167
        ]
      },
      "type": "Feature",
      "properties": {
        "hierarchy": [
          "tgn:2548608",
          "tgn:1000001",
          "tgn:7012149",
          "tgn:2002382",
          "tgn:7007923",
          "tgn:7029392"
        ],
        "placetype": [
          "aat:300008798"
        ],
        "id": 2548608,
        "name:xx": "North Mountain"
      }
    },
    {
      "geometry": {
        "type": "Point",
        "coordinates": [
          -116.9167,
          33.8333
        ]
      },
      "type": "Feature",
      "properties": {
        "hierarchy": [
          "tgn:2548609",
          "tgn:1000001",
          "tgn:7012149",
          "tgn:7007157",
          "tgn:1002828",
          "tgn:7029392"
        ],
        "placetype": [
          "aat:300055621"
        ],
        "id": 2548609,
        "name:xx": "North Mountain Experimental Area"
      }
    }
  ]
}
