{
  "geometry": {
    "type": "Point",
    "coordinates": [
      -91.05,
      38.1667
    ]
  },
  "type": "Feature",
  "properties": {
    "hierarchy": [
      "tgn:2179719",
      "tgn:1000001",
      "tgn:7012149",
      "tgn:2001254",
      "tgn:7007523",
      "tgn:7029392"
    ],
    "placetype": [
      "aat:300000390"
    ],
    "id": 2179719,
    "name:xx": "Blanton Limonite Bank"
  }
}
