{
  "geometry": {
    "type": "Point",
    "coordinates": [
      -113.2667,
      33.7333
    ]
  },
  "type": "Feature",
  "properties": {
    "hierarchy": [
      "tgn:2450738",
      "tgn:1000001",
      "tgn:7006451",
      "tgn:7012149",
      "tgn:2000097",
      "tgn:7029392"
    ],
    "placetype": [
      "aat:300000390"
    ],
    "id": 2450738,
    "name:xx": "Lions Den Mine"
  }
}
