{
  "geometry": {
    "type": "Point",
    "coordinates": [
      -133.0167,
      55.0667
    ]
  },
  "type": "Feature",
  "properties": {
    "hierarchy": [
      "tgn:2744940",
      "tgn:7006450",
      "tgn:1000001",
      "tgn:7012149",
      "tgn:2000082",
      "tgn:7029392"
    ],
    "placetype": [
      "aat:300132316"
    ],
    "id": 2744940,
    "name:xx": "View Cove"
  }
}
