{
  "geometry": {
    "type": "Point",
    "coordinates": [
      -136.55,
      58.9333
    ]
  },
  "type": "Feature",
  "properties": {
    "hierarchy": [
      "tgn:2603483",
      "tgn:7006450",
      "tgn:1000001",
      "tgn:7012149",
      "tgn:7019760",
      "tgn:7029392"
    ],
    "placetype": [
      "aat:300132316"
    ],
    "id": 2603483,
    "name:xx": "Queen Inlet"
  }
}
