{
  "geometry": {
    "type": "Point",
    "coordinates": [
      -76.5333,
      34.9167
    ]
  },
  "type": "Feature",
  "properties": {
    "hierarchy": [
      "tgn:2290453",
      "tgn:1000001",
      "tgn:2001477",
      "tgn:7012149",
      "tgn:7007709",
      "tgn:7029392"
    ],
    "placetype": [
      "aat:300008706"
    ],
    "id": 2290453,
    "name:xx": "Doe Creek"
  }
}
