{
  "geometry": {
    "type": "Point",
    "coordinates": [
      -73.6333,
      8.9667
    ]
  },
  "type": "Feature",
  "properties": {
    "hierarchy": [
      "tgn:1023903",
      "tgn:7002476",
      "tgn:1000050",
      "tgn:1000002",
      "tgn:7029392"
    ],
    "placetype": [
      "aat:300008347"
    ],
    "id": 1023903,
    "name:xx": "Pailitas"
  }
}
