{
  "geometry": {
    "type": "Point",
    "coordinates": [
      -91.8667,
      44.15
    ]
  },
  "type": "Feature",
  "properties": {
    "hierarchy": [
      "tgn:2126023",
      "tgn:1000001",
      "tgn:7012149",
      "tgn:2001083",
      "tgn:7007521",
      "tgn:7029392"
    ],
    "placetype": [
      "aat:300008761"
    ],
    "id": 2126023,
    "name:xx": "Adams Valley"
  }
}
