{
  "geometry": {
    "type": "Point",
    "coordinates": [
      -75.2167,
      40.4167
    ]
  },
  "type": "Feature",
  "properties": {
    "hierarchy": [
      "tgn:2305163",
      "tgn:1000001",
      "tgn:7012149",
      "tgn:7007710",
      "tgn:7029392"
    ],
    "placetype": [
      "aat:300008706"
    ],
    "id": 2305163,
    "name:xx": "East Branch Perkiomen Creek"
  }
}
