{
  "geometry": {
    "type": "Point",
    "coordinates": [
      -82.1333,
      27.2333
    ]
  },
  "type": "Feature",
  "properties": {
    "hierarchy": [
      "tgn:2529926",
      "tgn:1000001",
      "tgn:7012149",
      "tgn:7007240",
      "tgn:7029392"
    ],
    "placetype": [
      "aat:300008699"
    ],
    "id": 2529926,
    "name:xx": "Mud Slough"
  }
}
