{
  "geometry": {
    "type": "Point",
    "coordinates": [
      -81.4667,
      38.45
    ]
  },
  "type": "Feature",
  "properties": {
    "hierarchy": [
      "tgn:2350502",
      "tgn:1000001",
      "tgn:7012149",
      "tgn:2002270",
      "tgn:7013961",
      "tgn:7029392"
    ],
    "placetype": [
      "aat:300008699"
    ],
    "id": 2350502,
    "name:xx": "Given Fork"
  }
}
