{
  "geometry": {
    "type": "Point",
    "coordinates": [
      74.775,
      34.272222
    ]
  },
  "type": "Feature",
  "properties": {
    "hierarchy": [
      "tgn:7589283",
      "tgn:1000004",
      "tgn:7000198",
      "tgn:7000799",
      "tgn:7029392"
    ],
    "placetype": [
      "aat:300008347"
    ],
    "name:en": "Bāgh-i-Zamān",
    "id": 7589283
  }
}
