{
  "geometry": {
    "type": "Point",
    "coordinates": [
      115.2667,
      31.9833
    ]
  },
  "type": "Feature",
  "properties": {
    "hierarchy": [
      "tgn:1069145",
      "tgn:1000004",
      "tgn:7016672",
      "tgn:1000111",
      "tgn:7029392"
    ],
    "placetype": [
      "aat:300008347"
    ],
    "id": 1069145,
    "name:xx": "Jiangjiaji"
  }
}
