{
  "geometry": {
    "type": "Point",
    "coordinates": [
      -105.85,
      46.3833
    ]
  },
  "type": "Feature",
  "properties": {
    "hierarchy": [
      "tgn:2685296",
      "tgn:1000001",
      "tgn:2001268",
      "tgn:7012149",
      "tgn:7007524",
      "tgn:7029392"
    ],
    "placetype": [
      "aat:300006191"
    ],
    "id": 2685296,
    "name:xx": "Spotted Eagle Lake"
  }
}
