{
  "geometry": {
    "type": "Point",
    "coordinates": [
      -86.05,
      31.6333
    ]
  },
  "type": "Feature",
  "properties": {
    "hierarchy": [
      "tgn:2694773",
      "tgn:7002659",
      "tgn:1000001",
      "tgn:7012149",
      "tgn:2000054",
      "tgn:7029392"
    ],
    "placetype": [
      "aat:300008680"
    ],
    "id": 2694773,
    "name:xx": "Stewarts Pond"
  }
}
