{
  "geometry": {
    "type": "Point",
    "coordinates": [
      -85.2833,
      41.55
    ]
  },
  "type": "Feature",
  "properties": {
    "hierarchy": [
      "tgn:2178405",
      "tgn:1000001",
      "tgn:7012149",
      "tgn:1002565",
      "tgn:7007252",
      "tgn:7029392"
    ],
    "placetype": [
      "aat:300008680"
    ],
    "id": 2178405,
    "name:xx": "Blackman Lake"
  }
}
