{
  "geometry": {
    "type": "Point",
    "coordinates": [
      -118.2167,
      45.0333
    ]
  },
  "type": "Feature",
  "properties": {
    "hierarchy": [
      "tgn:2135146",
      "tgn:1000001",
      "tgn:7012149",
      "tgn:2001721",
      "tgn:7007708",
      "tgn:7029392"
    ],
    "placetype": [
      "aat:300008798"
    ],
    "id": 2135146,
    "name:xx": "Anthony Butte"
  }
}
