{
  "geometry": {
    "type": "Point",
    "coordinates": [
      -122.4167,
      39.0167
    ]
  },
  "type": "Feature",
  "properties": {
    "hierarchy": [
      "tgn:2179625",
      "tgn:1000001",
      "tgn:7012149",
      "tgn:1002296",
      "tgn:7007157",
      "tgn:7029392"
    ],
    "placetype": [
      "aat:300008697"
    ],
    "id": 2179625,
    "name:xx": "Blank Spring"
  }
}
