{
  "geometry": {
    "type": "Point",
    "coordinates": [
      -94.1167,
      38.2167
    ]
  },
  "type": "Feature",
  "properties": {
    "hierarchy": [
      "tgn:2539971",
      "tgn:2001172",
      "tgn:1000001",
      "tgn:7012149",
      "tgn:7007523",
      "tgn:7029392"
    ],
    "placetype": [
      "aat:300008699"
    ],
    "id": 2539971,
    "name:xx": "Newberry Branch"
  }
}
