{
  "geometry": {
    "type": "Point",
    "coordinates": [
      -105.3333,
      36.0667
    ]
  },
  "type": "Feature",
  "properties": {
    "hierarchy": [
      "tgn:2312828",
      "tgn:1000001",
      "tgn:7012149",
      "tgn:2001446",
      "tgn:7007566",
      "tgn:7029392"
    ],
    "placetype": [
      "aat:300055621"
    ],
    "id": 2312828,
    "name:xx": "El Poso"
  }
}
