{
  "type": "FeatureCollection",
  "features": [
    {
      "geometry": {
        "type": "Point",
        "coordinates": [
          -83.45,
          31.7333
        ]
      },
      "type": "Feature",
      "properties": {
        "hierarchy": [
          "tgn:2766670",
          "tgn:1000001",
          "tgn:7012149",
          "tgn:2000433",
          "tgn:7007248",
          "tgn:7029392"
        ],
        "placetype": [
          "aat:300008680"
        ],
        "id": 2766670,
        "name:xx": "White Oak Lake"
      }
    },
    {
      "geometry": {
        "type": "Point",
        "coordinates": [
          -89.2167,
          40.6167
        ]
      },
      "type": "Feature",
      "properties": {
        "hierarchy": [
          "tgn:2766671",
          "tgn:1000001",
          "tgn:7012149",
          "tgn:1003035",
          "tgn:7007251",
          "tgn:7029392"
        ],
        "placetype": [
          "aat:300006191"
        ],
        "id": 2766671,
        "name:xx": "White Oak Lake"
      }
    },
    {
      "geometry": {
        "type": "Point",
        "coordinates": [
          -87.15,
          38.3833
        ]
      },
      "type": "Feature",
      "properties": {
        "hierarchy": [
          "tgn:2766672",
          "tgn:1000001",
          "tgn:7012149",
          "tgn:2000551",
          "tgn:7007252",
          "tgn:7029392"
        ],
        "placetype": [
          "aat:300006191"
        ],
        "id": 2766672,
        "name:xx": "White Oak Lake"
      }
    },
    {
      "geometry": {
        "type": "Point",
        "coordinates": [
          -91.1667,
          32.05
        ]
      },
      "type": "Feature",
      "properties": {
        "hierarchy": [
          "tgn:2766673",
          "tgn:1000001",
          "tgn:7012149",
          "tgn:2000907",
          "tgn:7007256",
          "tgn:7029392"
        ],
        "placetype": [
          "aat:300008680"
        ],
        "id": 2766673,
        "name:xx": "White Oak Lake"
      }
    },
    {
      "geometry": {
        "type": "Point",
        "coordinates": [
          -93.8667,
          46.9
        ]
      },
      "type": "Feature",
      "properties": {
        "hierarchy": [
          "tgn:2766674",
          "tgn:1000001",
          "tgn:2001009",
          "tgn:7012149",
          "tgn:7007521",
          "tgn:7029392"
        ],
        "placetype": [
          "aat:300008680"
        ],
        "id": 2766674,
        "name:xx": "White Oak Lake"
      }
    },
    {
      "geometry": {
        "type": "Point",
        "coordinates": [
          -93.7667,
          47.3
        ]
      },
      "type": "Feature",
      "properties": {
        "hierarchy": [
          "tgn:2766675",
          "tgn:1000001",
          "tgn:7012149",
          "tgn:2001029",
          "tgn:7007521",
          "tgn:7029392"
        ],
        "placetype": [
          "aat:300008680"
        ],
        "id": 2766675,
        "name:xx": "White Oak Lake"
      }
    },
    {
      "geometry": {
        "type": "Point",
        "coordinates": [
          -78.8667,
          34.6667
        ]
      },
      "type": "Feature",
      "properties": {
        "hierarchy": [
          "tgn:2766677",
          "tgn:1000001",
          "tgn:7012149",
          "tgn:2001534",
          "tgn:7007709",
          "tgn:7029392"
        ],
        "placetype": [
          "aat:300006191"
        ],
        "id": 2766677,
        "name:xx": "White Oak Lake"
      }
    },
    {
      "geometry": {
        "type": "Point",
        "coordinates": [
          -79.2167,
          34.1
        ]
      },
      "type": "Feature",
      "properties": {
        "hierarchy": [
          "tgn:2766679",
          "tgn:1000001",
          "tgn:7012149",
          "tgn:2001750",
          "tgn:7007712",
          "tgn:7029392"
        ],
        "placetype": [
          "aat:300008680"
        ],
        "id": 2766679,
        "name:xx": "White Oak Lake"
      }
    }
  ]
}
