{
  "geometry": {
    "type": "Point",
    "coordinates": [
      -106.3167,
      42.7333
    ]
  },
  "type": "Feature",
  "properties": {
    "hierarchy": [
      "tgn:2138403",
      "tgn:1000001",
      "tgn:7012149",
      "tgn:2002377",
      "tgn:7007923",
      "tgn:7029392"
    ],
    "placetype": [
      "aat:300008697"
    ],
    "id": 2138403,
    "name:xx": "Asbestos Spring"
  }
}
