{
  "geometry": {
    "type": "Point",
    "coordinates": [
      -107.3167,
      44.55
    ]
  },
  "type": "Feature",
  "properties": {
    "hierarchy": [
      "tgn:2636147",
      "tgn:1000001",
      "tgn:7012149",
      "tgn:2002374",
      "tgn:7007923",
      "tgn:7029392"
    ],
    "placetype": [
      "aat:300008798"
    ],
    "id": 2636147,
    "name:xx": "Saddle Mountain"
  }
}
