{
  "geometry": {
    "type": "Point",
    "coordinates": [
      -76.3667,
      39.5667
    ]
  },
  "type": "Feature",
  "properties": {
    "hierarchy": [
      "tgn:2212509",
      "tgn:1000001",
      "tgn:7016102",
      "tgn:7012149",
      "tgn:7007516",
      "tgn:7029392"
    ],
    "placetype": [
      "aat:300008699"
    ],
    "id": 2212509,
    "name:xx": "Bynum Run"
  }
}
