{
  "geometry": {
    "type": "Point",
    "coordinates": [
      -87.0167,
      40.5833
    ]
  },
  "type": "Feature",
  "properties": {
    "hierarchy": [
      "tgn:2630521",
      "tgn:1000001",
      "tgn:7012149",
      "tgn:1003021",
      "tgn:7007252",
      "tgn:7029392"
    ],
    "placetype": [
      "aat:300008347"
    ],
    "id": 2630521,
    "name:xx": "Round Grove"
  }
}
