{
  "geometry": {
    "type": "Point",
    "coordinates": [
      -75.0333,
      43.2833
    ]
  },
  "type": "Feature",
  "properties": {
    "hierarchy": [
      "tgn:2776174",
      "tgn:1000001",
      "tgn:7012149",
      "tgn:1002472",
      "tgn:7007568",
      "tgn:7029392"
    ],
    "placetype": [
      "aat:300008699"
    ],
    "id": 2776174,
    "name:xx": "Wilt Brook"
  }
}
