{
  "geometry": {
    "type": "Point",
    "coordinates": [
      -79.95,
      32.7333
    ]
  },
  "type": "Feature",
  "properties": {
    "hierarchy": [
      "tgn:2780120",
      "tgn:1000001",
      "tgn:2001734",
      "tgn:7012149",
      "tgn:7007712",
      "tgn:7029392"
    ],
    "placetype": [
      "aat:300008699"
    ],
    "id": 2780120,
    "name:xx": "Wolfpit Run"
  }
}
