{
  "geometry": {
    "type": "Point",
    "coordinates": [
      117.4833,
      40.6667
    ]
  },
  "type": "Feature",
  "properties": {
    "hierarchy": [
      "tgn:1068255",
      "tgn:1000956",
      "tgn:1000004",
      "tgn:1000111",
      "tgn:7029392"
    ],
    "placetype": [
      "aat:300008347"
    ],
    "id": 1068255,
    "name:xx": "Gaoshanbao"
  }
}
