{
  "type": "FeatureCollection",
  "features": [
    {
      "geometry": {
        "type": "Point",
        "coordinates": [
          -86,
          41.4333
        ]
      },
      "type": "Feature",
      "properties": {
        "hierarchy": [
          "tgn:2033010",
          "tgn:1000001",
          "tgn:7012149",
          "tgn:1002353",
          "tgn:7007252",
          "tgn:7029392"
        ],
        "placetype": [
          "aat:300008347"
        ],
        "id": 2033010,
        "name:xx": "Nappanee"
      }
    },
    {
      "geometry": {
        "type": "Point",
        "coordinates": [
          -85.9333,
          38.3667
        ]
      },
      "type": "Feature",
      "properties": {
        "hierarchy": [
          "tgn:2033015",
          "tgn:1000001",
          "tgn:7012149",
          "tgn:1002376",
          "tgn:7007252",
          "tgn:7029392"
        ],
        "placetype": [
          "aat:300008347",
          "aat:300387210"
        ],
        "id": 2033015,
        "name:xx": "Navilleton"
      }
    },
    {
      "geometry": {
        "type": "Point",
        "coordinates": [
          -86.1167,
          40.7
        ]
      },
      "type": "Feature",
      "properties": {
        "hierarchy": [
          "tgn:2033016",
          "tgn:1000001",
          "tgn:7012149",
          "tgn:1002661",
          "tgn:7007252",
          "tgn:7029392"
        ],
        "placetype": [
          "aat:300008347",
          "aat:300387210"
        ],
        "id": 2033016,
        "name:xx": "Nead"
      }
    },
    {
      "geometry": {
        "type": "Point",
        "coordinates": [
          -85.45,
          39.05
        ]
      },
      "type": "Feature",
      "properties": {
        "hierarchy": [
          "tgn:2033017",
          "tgn:1000001",
          "tgn:7012149",
          "tgn:1002523",
          "tgn:7007252",
          "tgn:7029392"
        ],
        "placetype": [
          "aat:300008347"
        ],
        "id": 2033017,
        "name:xx": "Nebraska"
      }
    },
    {
      "geometry": {
        "type": "Point",
        "coordinates": [
          -85.9667,
          39.5167
        ]
      },
      "type": "Feature",
      "properties": {
        "hierarchy": [
          "tgn:2033018",
          "tgn:1000001",
          "tgn:7012149",
          "tgn:1002525",
          "tgn:7007252",
          "tgn:7029392"
        ],
        "placetype": [
          "aat:300008347"
        ],
        "id": 2033018,
        "name:xx": "Needham"
      }
    },
    {
      "geometry": {
        "type": "Point",
        "coordinates": [
          -86.5167,
          38.9167
        ]
      },
      "type": "Feature",
      "properties": {
        "hierarchy": [
          "tgn:2033019",
          "tgn:1000001",
          "tgn:7012149",
          "tgn:1002579",
          "tgn:7007252",
          "tgn:7029392"
        ],
        "placetype": [
          "aat:300008347"
        ],
        "id": 2033019,
        "name:xx": "Needmore"
      }
    }
  ]
}
