{
  "geometry": {
    "type": "Point",
    "coordinates": [
      171.05,
      -43.35
    ]
  },
  "type": "Feature",
  "properties": {
    "hierarchy": [
      "tgn:7509977",
      "tgn:1009227",
      "tgn:7001866",
      "tgn:1000226",
      "tgn:1000006",
      "tgn:7029392"
    ],
    "placetype": [
      "aat:300008798"
    ],
    "name:en": "Tent Peak",
    "id": 7509977
  }
}
