{
  "geometry": {
    "type": "Point",
    "coordinates": [
      -102.6333,
      43.7833
    ]
  },
  "type": "Feature",
  "properties": {
    "hierarchy": [
      "tgn:2378937",
      "tgn:1000001",
      "tgn:7012149",
      "tgn:2001821",
      "tgn:7007713",
      "tgn:7029392"
    ],
    "placetype": [
      "aat:300008798"
    ],
    "id": 2378937,
    "name:xx": "Hart Table"
  }
}
