{
  "geometry": {
    "type": "Point",
    "coordinates": [
      -105.9333,
      38.8167
    ]
  },
  "type": "Feature",
  "properties": {
    "hierarchy": [
      "tgn:2150952",
      "tgn:1000001",
      "tgn:7012149",
      "tgn:7007158",
      "tgn:7029392"
    ],
    "placetype": [
      "aat:300266640"
    ],
    "id": 2150952,
    "name:xx": "Bassam Ridge"
  }
}
