{
  "type": "FeatureCollection",
  "features": [
    {
      "geometry": {
        "type": "Point",
        "coordinates": [
          -84.5833,
          42.25
        ]
      },
      "type": "Feature",
      "properties": {
        "hierarchy": [
          "tgn:2052940",
          "tgn:1000001",
          "tgn:7012149",
          "tgn:1002509",
          "tgn:7007520",
          "tgn:7029392"
        ],
        "placetype": [
          "aat:300008347"
        ],
        "id": 2052940,
        "name:xx": "Parma"
      }
    },
    {
      "geometry": {
        "type": "Point",
        "coordinates": [
          -85.4,
          43.0333
        ]
      },
      "type": "Feature",
      "properties": {
        "hierarchy": [
          "tgn:2052941",
          "tgn:1000001",
          "tgn:7012149",
          "tgn:1002540",
          "tgn:7007520",
          "tgn:7029392"
        ],
        "placetype": [
          "aat:300008347",
          "aat:300387210"
        ],
        "id": 2052941,
        "name:xx": "Parnell"
      }
    },
    {
      "geometry": {
        "type": "Point",
        "coordinates": [
          -83.7667,
          42.6833
        ]
      },
      "type": "Feature",
      "properties": {
        "hierarchy": [
          "tgn:2052942",
          "tgn:1000001",
          "tgn:7012149",
          "tgn:1002603",
          "tgn:7007520",
          "tgn:7029392"
        ],
        "placetype": [
          "aat:300008347"
        ],
        "id": 2052942,
        "name:xx": "Parshallville"
      }
    },
    {
      "geometry": {
        "type": "Point",
        "coordinates": [
          -84.8333,
          42.4
        ]
      },
      "type": "Feature",
      "properties": {
        "hierarchy": [
          "tgn:2052943",
          "tgn:1000001",
          "tgn:1002222",
          "tgn:7012149",
          "tgn:7007520",
          "tgn:7029392"
        ],
        "placetype": [
          "aat:300008347"
        ],
        "id": 2052943,
        "name:xx": "Partello"
      }
    },
    {
      "geometry": {
        "type": "Point",
        "coordinates": [
          -87.4167,
          46.5833
        ]
      },
      "type": "Feature",
      "properties": {
        "hierarchy": [
          "tgn:2052944",
          "tgn:1000001",
          "tgn:7012149",
          "tgn:2000975",
          "tgn:7007520",
          "tgn:7029392"
        ],
        "placetype": [
          "aat:300387016"
        ],
        "id": 2052944,
        "name:xx": "Partridge"
      }
    },
    {
      "geometry": {
        "type": "Point",
        "coordinates": [
          -83.4167,
          41.9167
        ]
      },
      "type": "Feature",
      "properties": {
        "hierarchy": [
          "tgn:2052946",
          "tgn:1000001",
          "tgn:7012149",
          "tgn:1002679",
          "tgn:7007520",
          "tgn:7029392"
        ],
        "placetype": [
          "aat:300008347"
        ],
        "id": 2052946,
        "name:xx": "Patterson Gardens"
      }
    },
    {
      "geometry": {
        "type": "Point",
        "coordinates": [
          -89.1667,
          46.4
        ]
      },
      "type": "Feature",
      "properties": {
        "hierarchy": [
          "tgn:2052948",
          "tgn:1000001",
          "tgn:7012149",
          "tgn:2000986",
          "tgn:7007520",
          "tgn:7029392"
        ],
        "placetype": [
          "aat:300008347"
        ],
        "id": 2052948,
        "name:xx": "Paulding"
      }
    }
  ]
}
