{
  "geometry": {
    "type": "Point",
    "coordinates": [
      -72.85,
      41.85
    ]
  },
  "type": "Feature",
  "properties": {
    "hierarchy": [
      "tgn:2726728",
      "tgn:1000001",
      "tgn:1002461",
      "tgn:7012149",
      "tgn:7007159",
      "tgn:7029392"
    ],
    "placetype": [
      "aat:300008680"
    ],
    "id": 2726728,
    "name:xx": "Town Pool"
  }
}
