{
  "geometry": {
    "type": "Point",
    "coordinates": [
      -99.4333,
      33.0167
    ]
  },
  "type": "Feature",
  "properties": {
    "hierarchy": [
      "tgn:2204833",
      "tgn:1000001",
      "tgn:7012149",
      "tgn:2002084",
      "tgn:7007826",
      "tgn:7029392"
    ],
    "placetype": [
      "aat:300006191"
    ],
    "id": 2204833,
    "name:xx": "Buffalo Tank"
  }
}
