{
  "geometry": {
    "type": "Point",
    "coordinates": [
      -86.6833,
      33.4833
    ]
  },
  "type": "Feature",
  "properties": {
    "hierarchy": [
      "tgn:2562909",
      "tgn:7002659",
      "tgn:1000001",
      "tgn:7012149",
      "tgn:2000036",
      "tgn:7029392"
    ],
    "placetype": [
      "aat:300000390"
    ],
    "id": 2562909,
    "name:xx": "Overton Number 1 Slope Mine"
  }
}
