{
  "geometry": {
    "type": "Point",
    "coordinates": [
      -110.4167,
      32.7833
    ]
  },
  "type": "Feature",
  "properties": {
    "hierarchy": [
      "tgn:2732528",
      "tgn:1000001",
      "tgn:7006451",
      "tgn:2000094",
      "tgn:7012149",
      "tgn:7029392"
    ],
    "placetype": [
      "aat:300008706"
    ],
    "id": 2732528,
    "name:xx": "Turkey Creek"
  }
}
