{
  "geometry": {
    "type": "Point",
    "coordinates": [
      9.25,
      41.3667
    ]
  },
  "type": "Feature",
  "properties": {
    "hierarchy": [
      "tgn:1006744",
      "tgn:1000003",
      "tgn:7594273",
      "tgn:1000070",
      "tgn:7029392"
    ],
    "placetype": [
      "aat:300008791"
    ],
    "id": 1006744,
    "name:xx": "Cavallo, I"
  }
}
