{
  "type": "FeatureCollection",
  "features": [
    {
      "geometry": {
        "type": "Point",
        "coordinates": [
          3,
          42.8333
        ]
      },
      "type": "Feature",
      "properties": {
        "hierarchy": [
          "tgn:1114770",
          "tgn:1000003",
          "tgn:7002885",
          "tgn:1000070",
          "tgn:7029392"
        ],
        "placetype": [
          "aat:300008679"
        ],
        "id": 1114770,
        "name:xx": "Leucate, Étang de"
      }
    },
    {
      "geometry": {
        "type": "Point",
        "coordinates": [
          -87.6,
          15.75
        ]
      },
      "type": "Feature",
      "properties": {
        "hierarchy": [
          "tgn:1114772",
          "tgn:1000512",
          "tgn:1000001",
          "tgn:7005554",
          "tgn:7029392"
        ],
        "placetype": [
          "aat:300008679"
        ],
        "id": 1114772,
        "name:xx": "Los Micos, Laguna de"
      }
    },
    {
      "geometry": {
        "type": "Point",
        "coordinates": [
          -93.666667,
          18.333333
        ]
      },
      "type": "Feature",
      "properties": {
        "hierarchy": [
          "tgn:1114774",
          "tgn:1000001",
          "tgn:7005596",
          "tgn:7005560",
          "tgn:7029392"
        ],
        "placetype": [
          "aat:300008679"
        ],
        "id": 1114774,
        "name:xx": "Machona, Laguna"
      }
    },
    {
      "geometry": {
        "type": "Point",
        "coordinates": [
          -97.666667,
          25
        ]
      },
      "type": "Feature",
      "properties": {
        "hierarchy": [
          "tgn:1114776",
          "tgn:1000001",
          "tgn:7005597",
          "tgn:7005560",
          "tgn:7029392"
        ],
        "placetype": [
          "aat:300008679"
        ],
        "id": 1114776,
        "name:xx": "Madre, Laguna"
      }
    },
    {
      "geometry": {
        "type": "Point",
        "coordinates": [
          -52.8,
          -33.1
        ]
      },
      "type": "Feature",
      "properties": {
        "hierarchy": [
          "tgn:1114777",
          "tgn:1001941",
          "tgn:1000047",
          "tgn:7002458",
          "tgn:1000002",
          "tgn:7029392"
        ],
        "placetype": [
          "aat:300008679"
        ],
        "id": 1114777,
        "name:xx": "Mangueira, Lagoa"
      }
    },
    {
      "geometry": {
        "type": "Point",
        "coordinates": [
          -157.3667,
          1.95
        ]
      },
      "type": "Feature",
      "properties": {
        "hierarchy": [
          "tgn:1114778",
          "tgn:7002038",
          "tgn:1006044",
          "tgn:1000217",
          "tgn:1000006",
          "tgn:7029392"
        ],
        "placetype": [
          "aat:300008679"
        ],
        "id": 1114778,
        "name:xx": "Manulu Lagoon"
      }
    },
    {
      "geometry": {
        "type": "Point",
        "coordinates": [
          -57.4,
          -37.6167
        ]
      },
      "type": "Feature",
      "properties": {
        "hierarchy": [
          "tgn:1114779",
          "tgn:1001160",
          "tgn:7006477",
          "tgn:1000002",
          "tgn:7029392"
        ],
        "placetype": [
          "aat:300008679"
        ],
        "id": 1114779,
        "name:xx": "Mar Chiquita, Laguna"
      }
    }
  ]
}
