{
  "geometry": {
    "type": "Point",
    "coordinates": [
      -83.95,
      35.2333
    ]
  },
  "type": "Feature",
  "properties": {
    "hierarchy": [
      "tgn:2369407",
      "tgn:1000001",
      "tgn:7012149",
      "tgn:2001497",
      "tgn:7007709",
      "tgn:7029392"
    ],
    "placetype": [
      "aat:300008699"
    ],
    "id": 2369407,
    "name:xx": "Gumstock Branch"
  }
}
