{
  "geometry": {
    "type": "Point",
    "coordinates": [
      16.2833,
      48.1667
    ]
  },
  "type": "Feature",
  "properties": {
    "hierarchy": [
      "tgn:7003182",
      "tgn:7003025",
      "tgn:1000003",
      "tgn:1000062",
      "tgn:7029392"
    ],
    "placetype": [
      "aat:300006165",
      "aat:300386965"
    ],
    "id": 7003182,
    "name:xx": "Erste Wiener Hochquellenleitung"
  }
}
