{
  "geometry": {
    "type": "Point",
    "coordinates": [
      -80.7833,
      32.85
    ]
  },
  "type": "Feature",
  "properties": {
    "hierarchy": [
      "tgn:2643676",
      "tgn:1000001",
      "tgn:2001739",
      "tgn:7012149",
      "tgn:7007712",
      "tgn:7029392"
    ],
    "placetype": [
      "aat:300008699"
    ],
    "id": 2643676,
    "name:xx": "Sandy Run"
  }
}
