{
  "geometry": {
    "type": "Point",
    "coordinates": [
      -96.2167,
      33.2333
    ]
  },
  "type": "Feature",
  "properties": {
    "hierarchy": [
      "tgn:2305497",
      "tgn:1000001",
      "tgn:7012149",
      "tgn:1002492",
      "tgn:7007826",
      "tgn:7029392"
    ],
    "placetype": [
      "aat:300008706"
    ],
    "id": 2305497,
    "name:xx": "East Caddo Creek"
  }
}
