{
  "geometry": {
    "type": "Point",
    "coordinates": [
      -86.5833,
      33.5833
    ]
  },
  "type": "Feature",
  "properties": {
    "hierarchy": [
      "tgn:2750397",
      "tgn:7002659",
      "tgn:1000001",
      "tgn:7012149",
      "tgn:2000036",
      "tgn:7029392"
    ],
    "placetype": [
      "aat:300006191"
    ],
    "id": 2750397,
    "name:xx": "Wanderland Lake"
  }
}
