{
  "geometry": {
    "type": "Point",
    "coordinates": [
      -88.1333,
      34.8667
    ]
  },
  "type": "Feature",
  "properties": {
    "hierarchy": [
      "tgn:2339514",
      "tgn:1000001",
      "tgn:7012149",
      "tgn:2001156",
      "tgn:7007522",
      "tgn:7029392"
    ],
    "placetype": [
      "aat:300008761"
    ],
    "id": 2339514,
    "name:xx": "Fred Hollow"
  }
}
