{
  "type": "FeatureCollection",
  "features": [
    {
      "geometry": {
        "type": "Point",
        "coordinates": [
          6,
          53.366667
        ]
      },
      "type": "Feature",
      "properties": {
        "hierarchy": [
          "tgn:7269170",
          "tgn:7003616",
          "tgn:1000003",
          "tgn:7016845",
          "tgn:7029392"
        ],
        "placetype": [
          "aat:300006075",
          "aat:300008699"
        ],
        "name:nl": "Oude Hulp",
        "id": 7269170
      }
    },
    {
      "geometry": {
        "type": "Point",
        "coordinates": [
          4.983333,
          53.283333
        ]
      },
      "type": "Feature",
      "properties": {
        "hierarchy": [
          "tgn:7269171",
          "tgn:7003616",
          "tgn:1000003",
          "tgn:7016845",
          "tgn:7029392"
        ],
        "placetype": [
          "aat:300386887"
        ],
        "name:nl": "Oude Huizenlid",
        "id": 7269171
      }
    },
    {
      "geometry": {
        "type": "Point",
        "coordinates": [
          6.05,
          50.866667
        ]
      },
      "type": "Feature",
      "properties": {
        "hierarchy": [
          "tgn:7269172",
          "tgn:1000003",
          "tgn:7003622",
          "tgn:7016845",
          "tgn:7029392"
        ],
        "placetype": [
          "aat:300008187"
        ],
        "name:nl": "Oud Ehrenstein",
        "id": 7269172
      }
    },
    {
      "geometry": {
        "type": "Point",
        "coordinates": [
          4.883333,
          52.4
        ]
      },
      "type": "Feature",
      "properties": {
        "hierarchy": [
          "tgn:7269173",
          "tgn:1000003",
          "tgn:7006951",
          "tgn:7016845",
          "tgn:7029392"
        ],
        "placetype": [
          "aat:300120801"
        ],
        "name:nl": "Oude Houthaven",
        "id": 7269173
      }
    },
    {
      "geometry": {
        "type": "Point",
        "coordinates": [
          6.1,
          52.983333
        ]
      },
      "type": "Feature",
      "properties": {
        "hierarchy": [
          "tgn:7269174",
          "tgn:7003616",
          "tgn:1000003",
          "tgn:7016845",
          "tgn:7029392"
        ],
        "placetype": [
          "aat:300008347"
        ],
        "name:nl": "Oudehornstercompagnie",
        "id": 7269174
      }
    },
    {
      "geometry": {
        "type": "Point",
        "coordinates": [
          6.066667,
          52.966667
        ]
      },
      "type": "Feature",
      "properties": {
        "hierarchy": [
          "tgn:7269175",
          "tgn:7003616",
          "tgn:1000003",
          "tgn:7016845",
          "tgn:7029392"
        ],
        "placetype": [
          "aat:300008347"
        ],
        "name:nl": "Oudehorne",
        "id": 7269175
      }
    },
    {
      "geometry": {
        "type": "Point",
        "coordinates": [
          5.2,
          51.566667
        ]
      },
      "type": "Feature",
      "properties": {
        "hierarchy": [
          "tgn:7269176",
          "tgn:1000003",
          "tgn:7003624",
          "tgn:7016845",
          "tgn:7029392"
        ],
        "placetype": [
          "aat:300387502"
        ],
        "name:nl": "Oude Hondsberg",
        "id": 7269176
      }
    },
    {
      "geometry": {
        "type": "Point",
        "coordinates": [
          4.5,
          52.166667
        ]
      },
      "type": "Feature",
      "properties": {
        "hierarchy": [
          "tgn:7269177",
          "tgn:1000003",
          "tgn:7003632",
          "tgn:7016845",
          "tgn:7029392"
        ],
        "placetype": [
          "aat:300006075"
        ],
        "name:nl": "Oude Herengracht",
        "id": 7269177
      }
    },
    {
      "geometry": {
        "type": "Point",
        "coordinates": [
          6.5,
          53.216667
        ]
      },
      "type": "Feature",
      "properties": {
        "hierarchy": [
          "tgn:7269178",
          "tgn:1000003",
          "tgn:7003613",
          "tgn:7016845",
          "tgn:7029392"
        ],
        "placetype": [
          "aat:300006163"
        ],
        "name:nl": "Oude Held, Polder de",
        "id": 7269178
      }
    },
    {
      "geometry": {
        "type": "Point",
        "coordinates": [
          4.266667,
          51.583333
        ]
      },
      "type": "Feature",
      "properties": {
        "hierarchy": [
          "tgn:7269179",
          "tgn:1000003",
          "tgn:7003624",
          "tgn:7016845",
          "tgn:7029392"
        ],
        "placetype": [
          "aat:300006163"
        ],
        "name:nl": "Oude Heipolder",
        "id": 7269179
      }
    }
  ]
}
