{
  "geometry": {
    "type": "Point",
    "coordinates": [
      -75.9667,
      39.55
    ]
  },
  "type": "Feature",
  "properties": {
    "hierarchy": [
      "tgn:2374521",
      "tgn:1002247",
      "tgn:1000001",
      "tgn:7012149",
      "tgn:7007516",
      "tgn:7029392"
    ],
    "placetype": [
      "aat:300008850"
    ],
    "id": 2374521,
    "name:xx": "Hance Point"
  }
}
