{
  "geometry": {
    "type": "Point",
    "coordinates": [
      -80.3667,
      37.55
    ]
  },
  "type": "Feature",
  "properties": {
    "hierarchy": [
      "tgn:2439739",
      "tgn:1000001",
      "tgn:7012149",
      "tgn:2002282",
      "tgn:7013961",
      "tgn:7029392"
    ],
    "placetype": [
      "aat:300008697"
    ],
    "id": 2439739,
    "name:xx": "Kitchen Creek Spring"
  }
}
