{
  "geometry": {
    "type": "Point",
    "coordinates": [
      -87.9833,
      38.7667
    ]
  },
  "type": "Feature",
  "properties": {
    "hierarchy": [
      "tgn:2306704",
      "tgn:1000001",
      "tgn:7012149",
      "tgn:2000527",
      "tgn:7007251",
      "tgn:7029392"
    ],
    "placetype": [
      "aat:300008707"
    ],
    "id": 2306704,
    "name:xx": "East Fork Fox River"
  }
}
