{
  "geometry": {
    "type": "Point",
    "coordinates": [
      116.0333,
      39.4667
    ]
  },
  "type": "Feature",
  "properties": {
    "hierarchy": [
      "tgn:1073256",
      "tgn:1000004",
      "tgn:7002077",
      "tgn:1000111",
      "tgn:7029392"
    ],
    "placetype": [
      "aat:300008347"
    ],
    "id": 1073256,
    "name:xx": "Xuliying"
  }
}
