{
  "geometry": {
    "type": "Point",
    "coordinates": [
      27.895833,
      31.086389
    ]
  },
  "type": "Feature",
  "properties": {
    "hierarchy": [
      "tgn:7527697",
      "tgn:7001242",
      "tgn:7016833",
      "tgn:1001418",
      "tgn:7029392"
    ],
    "placetype": [
      "aat:300008347"
    ],
    "name:en": "Zāwiyat Sīdī Mūsá",
    "id": 7527697
  }
}
