{
  "type": "FeatureCollection",
  "features": [
    {
      "geometry": {
        "type": "Point",
        "coordinates": [
          18.5833,
          3.6833
        ]
      },
      "type": "Feature",
      "properties": {
        "hierarchy": [
          "tgn:1126301",
          "tgn:7001242",
          "tgn:1000155",
          "tgn:7029392"
        ],
        "placetype": [
          "aat:300008707"
        ],
        "id": 1126301,
        "name:xx": "Lobaye"
      }
    },
    {
      "geometry": {
        "type": "Point",
        "coordinates": [
          -6.7667,
          6.0167
        ]
      },
      "type": "Feature",
      "properties": {
        "hierarchy": [
          "tgn:1126302",
          "tgn:7001242",
          "tgn:1000168",
          "tgn:7029392"
        ],
        "placetype": [
          "aat:300008707"
        ],
        "id": 1126302,
        "name:xx": "Lobo"
      }
    },
    {
      "geometry": {
        "type": "Point",
        "coordinates": [
          -3.466667,
          54.966667
        ]
      },
      "type": "Feature",
      "properties": {
        "hierarchy": [
          "tgn:1126303",
          "tgn:7002444",
          "tgn:7008074",
          "tgn:1000003",
          "tgn:7008591",
          "tgn:7029392"
        ],
        "placetype": [
          "aat:300008707",
          "aat:300008699"
        ],
        "name:en": "Lochar Water",
        "id": 1126303
      }
    },
    {
      "geometry": {
        "type": "Point",
        "coordinates": [
          -114.6667,
          46.5
        ]
      },
      "type": "Feature",
      "properties": {
        "hierarchy": [
          "tgn:1126304",
          "tgn:1000001",
          "tgn:7012149",
          "tgn:2000476",
          "tgn:7007250",
          "tgn:7029392"
        ],
        "placetype": [
          "aat:300008707"
        ],
        "id": 1126304,
        "name:xx": "Lochsa"
      }
    },
    {
      "geometry": {
        "type": "Point",
        "coordinates": [
          -0.866667,
          51.5
        ]
      },
      "type": "Feature",
      "properties": {
        "hierarchy": [
          "tgn:1126307",
          "tgn:7002445",
          "tgn:1000003",
          "tgn:7008591",
          "tgn:7029392"
        ],
        "placetype": [
          "aat:300008707",
          "aat:300008699"
        ],
        "name:en": "Loddon",
        "id": 1126307
      }
    }
  ]
}
