{
  "geometry": {
    "type": "Point",
    "coordinates": [
      -110.8667,
      33.4833
    ]
  },
  "type": "Feature",
  "properties": {
    "hierarchy": [
      "tgn:2401006",
      "tgn:1000001",
      "tgn:7006451",
      "tgn:2000093",
      "tgn:7012149",
      "tgn:7029392"
    ],
    "placetype": [
      "aat:300006191"
    ],
    "id": 2401006,
    "name:xx": "Horse Tank Number Two"
  }
}
