{
  "geometry": {
    "type": "Point",
    "coordinates": [
      -120.6833,
      37.7167
    ]
  },
  "type": "Feature",
  "properties": {
    "hierarchy": [
      "tgn:2013280",
      "tgn:1000001",
      "tgn:7012149",
      "tgn:7007157",
      "tgn:1002915",
      "tgn:7029392"
    ],
    "placetype": [
      "aat:300387016"
    ],
    "id": 2013280,
    "name:xx": "Paulsell"
  }
}
