{
  "type": "FeatureCollection",
  "features": [
    {
      "geometry": {
        "type": "Point",
        "coordinates": [
          -101.033333,
          26.966667
        ]
      },
      "type": "Feature",
      "properties": {
        "hierarchy": [
          "tgn:7361430",
          "tgn:1001853",
          "tgn:1000001",
          "tgn:7005560",
          "tgn:7029392"
        ],
        "placetype": [
          "aat:300008347"
        ],
        "id": 7361430,
        "name:xx": "El Cajón"
      }
    },
    {
      "geometry": {
        "type": "Point",
        "coordinates": [
          -108.708611,
          26.8525
        ]
      },
      "type": "Feature",
      "properties": {
        "hierarchy": [
          "tgn:7361431",
          "tgn:1000001",
          "tgn:1001960",
          "tgn:7005560",
          "tgn:7029392"
        ],
        "placetype": [
          "aat:300008347"
        ],
        "id": 7361431,
        "name:xx": "El Cajón"
      }
    },
    {
      "geometry": {
        "type": "Point",
        "coordinates": [
          -108.226111,
          26.775556
        ]
      },
      "type": "Feature",
      "properties": {
        "hierarchy": [
          "tgn:7361432",
          "tgn:1000001",
          "tgn:7005595",
          "tgn:7005560",
          "tgn:7029392"
        ],
        "placetype": [
          "aat:300008347"
        ],
        "id": 7361432,
        "name:xx": "El Cajón"
      }
    },
    {
      "geometry": {
        "type": "Point",
        "coordinates": [
          -108.421667,
          26.523611
        ]
      },
      "type": "Feature",
      "properties": {
        "hierarchy": [
          "tgn:7361433",
          "tgn:1000001",
          "tgn:7005595",
          "tgn:7005560",
          "tgn:7029392"
        ],
        "placetype": [
          "aat:300008347"
        ],
        "id": 7361433,
        "name:xx": "El Cajón"
      }
    },
    {
      "geometry": {
        "type": "Point",
        "coordinates": [
          -106.433333,
          25.866667
        ]
      },
      "type": "Feature",
      "properties": {
        "hierarchy": [
          "tgn:7361434",
          "tgn:7005583",
          "tgn:1000001",
          "tgn:7005560",
          "tgn:7029392"
        ],
        "placetype": [
          "aat:300008347"
        ],
        "id": 7361434,
        "name:xx": "El Cajón"
      }
    },
    {
      "geometry": {
        "type": "Point",
        "coordinates": [
          -106.583333,
          24.983333
        ]
      },
      "type": "Feature",
      "properties": {
        "hierarchy": [
          "tgn:7361435",
          "tgn:7005583",
          "tgn:1000001",
          "tgn:7005560",
          "tgn:7029392"
        ],
        "placetype": [
          "aat:300008347"
        ],
        "id": 7361435,
        "name:xx": "El Cajón"
      }
    },
    {
      "geometry": {
        "type": "Point",
        "coordinates": [
          -106.636389,
          24.478889
        ]
      },
      "type": "Feature",
      "properties": {
        "hierarchy": [
          "tgn:7361436",
          "tgn:1000001",
          "tgn:7005595",
          "tgn:7005560",
          "tgn:7029392"
        ],
        "placetype": [
          "aat:300008347"
        ],
        "id": 7361436,
        "name:xx": "El Cajón"
      }
    },
    {
      "geometry": {
        "type": "Point",
        "coordinates": [
          -105.383333,
          23.5
        ]
      },
      "type": "Feature",
      "properties": {
        "hierarchy": [
          "tgn:7361437",
          "tgn:7005583",
          "tgn:1000001",
          "tgn:7005560",
          "tgn:7029392"
        ],
        "placetype": [
          "aat:300008347"
        ],
        "id": 7361437,
        "name:xx": "El Cajón"
      }
    },
    {
      "geometry": {
        "type": "Point",
        "coordinates": [
          -106.033333,
          23.35
        ]
      },
      "type": "Feature",
      "properties": {
        "hierarchy": [
          "tgn:7361438",
          "tgn:1000001",
          "tgn:7005595",
          "tgn:7005560",
          "tgn:7029392"
        ],
        "placetype": [
          "aat:300008347"
        ],
        "id": 7361438,
        "name:xx": "El Cajón"
      }
    },
    {
      "geometry": {
        "type": "Point",
        "coordinates": [
          -99.633333,
          20.4
        ]
      },
      "type": "Feature",
      "properties": {
        "hierarchy": [
          "tgn:7361439",
          "tgn:7005587",
          "tgn:1000001",
          "tgn:7005560",
          "tgn:7029392"
        ],
        "placetype": [
          "aat:300008347"
        ],
        "id": 7361439,
        "name:xx": "El Cajón"
      }
    }
  ]
}
