{
  "geometry": {
    "type": "Point",
    "coordinates": [
      10.616667,
      49.05
    ]
  },
  "type": "Feature",
  "properties": {
    "hierarchy": [
      "tgn:7134348",
      "tgn:7003669",
      "tgn:1000003",
      "tgn:7000084",
      "tgn:7029392"
    ],
    "placetype": [
      "aat:300008699"
    ],
    "id": 7134348,
    "name:xx": "Mühlbach"
  }
}
