{
  "geometry": {
    "type": "Point",
    "coordinates": [
      -83.7167,
      35.3667
    ]
  },
  "type": "Feature",
  "properties": {
    "hierarchy": [
      "tgn:2707692",
      "tgn:1000001",
      "tgn:7012149",
      "tgn:2001497",
      "tgn:7007709",
      "tgn:7029392"
    ],
    "placetype": [
      "aat:300008706"
    ],
    "id": 2707692,
    "name:xx": "Sweetwater Creek"
  }
}
