{
  "geometry": {
    "type": "Point",
    "coordinates": [
      -81.0833,
      39.0333
    ]
  },
  "type": "Feature",
  "properties": {
    "hierarchy": [
      "tgn:2600036",
      "tgn:1000001",
      "tgn:7012149",
      "tgn:2002292",
      "tgn:7013961",
      "tgn:7029392"
    ],
    "placetype": [
      "aat:300008699"
    ],
    "id": 2600036,
    "name:xx": "Prunty Run"
  }
}
