{
  "geometry": {
    "type": "Point",
    "coordinates": [
      22.25,
      36.85
    ]
  },
  "type": "Feature",
  "properties": {
    "hierarchy": [
      "tgn:7225000",
      "tgn:7002735",
      "tgn:7017076",
      "tgn:1000003",
      "tgn:1000074",
      "tgn:7029392"
    ],
    "placetype": [
      "aat:300132316"
    ],
    "id": 7225000,
    "name:xx": "Stoúpas, Órmos"
  }
}
