{
  "type": "FeatureCollection",
  "features": [
    {
      "geometry": {
        "type": "Point",
        "coordinates": [
          28.199135,
          25.96346
        ]
      },
      "type": "Feature",
      "properties": {
        "hierarchy": [
          "tgn:7534760",
          "tgn:7001242",
          "tgn:7016833",
          "tgn:7001334",
          "tgn:7029392"
        ],
        "placetype": [
          "aat:300008777"
        ],
        "name:en": "Malik, Qūr al",
        "id": 7534760
      }
    },
    {
      "geometry": {
        "type": "Point",
        "coordinates": [
          32.883333,
          24.1
        ]
      },
      "type": "Feature",
      "properties": {
        "hierarchy": [
          "tgn:7534761",
          "tgn:7001242",
          "tgn:7016833",
          "tgn:7000122",
          "tgn:7029392"
        ],
        "placetype": [
          "aat:300008791"
        ],
        "name:en": "Malik, Jazīrat al",
        "id": 7534761
      }
    },
    {
      "geometry": {
        "type": "Point",
        "coordinates": [
          32.883333,
          23.95
        ]
      },
      "type": "Feature",
      "properties": {
        "hierarchy": [
          "tgn:7534762",
          "tgn:7001242",
          "tgn:7016833",
          "tgn:7000122",
          "tgn:7029392"
        ],
        "placetype": [
          "aat:300008777"
        ],
        "name:en": "Mālik, Jabal",
        "id": 7534762
      }
    },
    {
      "geometry": {
        "type": "Point",
        "coordinates": [
          31.233333,
          29.783333
        ]
      },
      "type": "Feature",
      "properties": {
        "hierarchy": [
          "tgn:7534763",
          "tgn:7001242",
          "tgn:7016833",
          "tgn:1001083",
          "tgn:7029392"
        ],
        "placetype": [
          "aat:300008680"
        ],
        "name:en": "Malik, Birkat al",
        "id": 7534763
      }
    },
    {
      "geometry": {
        "type": "Point",
        "coordinates": [
          30.541139,
          25.198953
        ]
      },
      "type": "Feature",
      "properties": {
        "hierarchy": [
          "tgn:7534764",
          "tgn:7001242",
          "tgn:7016833",
          "tgn:7001334",
          "tgn:7029392"
        ],
        "placetype": [
          "aat:300008697"
        ],
        "name:en": "Malik, 'Ayn al",
        "id": 7534764
      }
    },
    {
      "geometry": {
        "type": "Point",
        "coordinates": [
          33.325556,
          30.638611
        ]
      },
      "type": "Feature",
      "properties": {
        "hierarchy": [
          "tgn:7534765",
          "tgn:7001242",
          "tgn:7016833",
          "tgn:7001335",
          "tgn:7029392"
        ],
        "placetype": [
          "aat:300006207"
        ],
        "name:en": "Bi'r al Malḩī",
        "id": 7534765
      }
    },
    {
      "geometry": {
        "type": "Point",
        "coordinates": [
          34.625086,
          29.785857
        ]
      },
      "type": "Feature",
      "properties": {
        "hierarchy": [
          "tgn:7534766",
          "tgn:7001242",
          "tgn:7016833",
          "tgn:7001335",
          "tgn:7029392"
        ],
        "placetype": [
          "aat:300379998"
        ],
        "name:en": "Māliḩah, Wādī al",
        "id": 7534766
      }
    },
    {
      "geometry": {
        "type": "Point",
        "coordinates": [
          31.299044,
          30.576238
        ]
      },
      "type": "Feature",
      "properties": {
        "hierarchy": [
          "tgn:7534767",
          "tgn:7001242",
          "tgn:7016833",
          "tgn:1001092",
          "tgn:7029392"
        ],
        "placetype": [
          "aat:300008347"
        ],
        "id": 7534767,
        "name:xx": "Kafr 'Abd as Sayyid Nawwār"
      }
    },
    {
      "geometry": {
        "type": "Point",
        "coordinates": [
          31.693399,
          30.805868
        ]
      },
      "type": "Feature",
      "properties": {
        "hierarchy": [
          "tgn:7534768",
          "tgn:7001242",
          "tgn:7016833",
          "tgn:1001113",
          "tgn:7029392"
        ],
        "placetype": [
          "aat:300008347"
        ],
        "id": 7534768,
        "name:xx": "Kafr 'Abd ash Shahīd"
      }
    },
    {
      "geometry": {
        "type": "Point",
        "coordinates": [
          31.238675,
          30.672275
        ]
      },
      "type": "Feature",
      "properties": {
        "hierarchy": [
          "tgn:7534769",
          "tgn:7001242",
          "tgn:7016833",
          "tgn:7001312",
          "tgn:7029392"
        ],
        "placetype": [
          "aat:300008347"
        ],
        "name:en": "Kafr 'Abd ar Raḩmān",
        "id": 7534769
      }
    }
  ]
}
