{
  "type": "FeatureCollection",
  "features": [
    {
      "geometry": {
        "type": "Point",
        "coordinates": [
          -84.3167,
          33.5833
        ]
      },
      "type": "Feature",
      "properties": {
        "hierarchy": [
          "tgn:2472330",
          "tgn:1000001",
          "tgn:2000322",
          "tgn:7012149",
          "tgn:7007248",
          "tgn:7029392"
        ],
        "placetype": [
          "aat:300006191"
        ],
        "id": 2472330,
        "name:xx": "Louise, Lake"
      }
    },
    {
      "geometry": {
        "type": "Point",
        "coordinates": [
          -89.2333,
          42.1333
        ]
      },
      "type": "Feature",
      "properties": {
        "hierarchy": [
          "tgn:2472332",
          "tgn:1000001",
          "tgn:7012149",
          "tgn:1002739",
          "tgn:7007251",
          "tgn:7029392"
        ],
        "placetype": [
          "aat:300008680"
        ],
        "id": 2472332,
        "name:xx": "Louise, Lake"
      }
    },
    {
      "geometry": {
        "type": "Point",
        "coordinates": [
          -87.1333,
          41.45
        ]
      },
      "type": "Feature",
      "properties": {
        "hierarchy": [
          "tgn:2472333",
          "tgn:1000001",
          "tgn:7012149",
          "tgn:1002798",
          "tgn:7007252",
          "tgn:7029392"
        ],
        "placetype": [
          "aat:300006191"
        ],
        "id": 2472333,
        "name:xx": "Louise, Lake"
      }
    },
    {
      "geometry": {
        "type": "Point",
        "coordinates": [
          -97,
          37.0667
        ]
      },
      "type": "Feature",
      "properties": {
        "hierarchy": [
          "tgn:2472334",
          "tgn:1000001",
          "tgn:2000677",
          "tgn:7012149",
          "tgn:7007254",
          "tgn:7029392"
        ],
        "placetype": [
          "aat:300006191"
        ],
        "id": 2472334,
        "name:xx": "Louise, Lake"
      }
    },
    {
      "geometry": {
        "type": "Point",
        "coordinates": [
          -79.2167,
          39.6833
        ]
      },
      "type": "Feature",
      "properties": {
        "hierarchy": [
          "tgn:2472335",
          "tgn:1000001",
          "tgn:2000935",
          "tgn:7012149",
          "tgn:7007516",
          "tgn:7029392"
        ],
        "placetype": [
          "aat:300006191"
        ],
        "id": 2472335,
        "name:xx": "Louise, Lake"
      }
    },
    {
      "geometry": {
        "type": "Point",
        "coordinates": [
          -86.6,
          41.85
        ]
      },
      "type": "Feature",
      "properties": {
        "hierarchy": [
          "tgn:2472336",
          "tgn:1000001",
          "tgn:1002182",
          "tgn:7012149",
          "tgn:7007520",
          "tgn:7029392"
        ],
        "placetype": [
          "aat:300008680"
        ],
        "id": 2472336,
        "name:xx": "Louise, Lake"
      }
    },
    {
      "geometry": {
        "type": "Point",
        "coordinates": [
          -83.4167,
          42.8167
        ]
      },
      "type": "Feature",
      "properties": {
        "hierarchy": [
          "tgn:2472337",
          "tgn:1000001",
          "tgn:7012149",
          "tgn:1002737",
          "tgn:7007520",
          "tgn:7029392"
        ],
        "placetype": [
          "aat:300008680"
        ],
        "id": 2472337,
        "name:xx": "Louise, Lake"
      }
    },
    {
      "geometry": {
        "type": "Point",
        "coordinates": [
          -85.9,
          44.65
        ]
      },
      "type": "Feature",
      "properties": {
        "hierarchy": [
          "tgn:2472338",
          "tgn:1000001",
          "tgn:2000949",
          "tgn:7012149",
          "tgn:7007520",
          "tgn:7029392"
        ],
        "placetype": [
          "aat:300008680"
        ],
        "id": 2472338,
        "name:xx": "Louise, Lake"
      }
    },
    {
      "geometry": {
        "type": "Point",
        "coordinates": [
          -83.9667,
          45.2833
        ]
      },
      "type": "Feature",
      "properties": {
        "hierarchy": [
          "tgn:2472339",
          "tgn:1000001",
          "tgn:7012149",
          "tgn:2000990",
          "tgn:7007520",
          "tgn:7029392"
        ],
        "placetype": [
          "aat:300008680"
        ],
        "id": 2472339,
        "name:xx": "Louise, Lake"
      }
    }
  ]
}
