{
  "geometry": {
    "type": "Point",
    "coordinates": [
      -76.05,
      38.0833
    ]
  },
  "type": "Feature",
  "properties": {
    "hierarchy": [
      "tgn:2651525",
      "tgn:1000001",
      "tgn:1002902",
      "tgn:7012149",
      "tgn:7007516",
      "tgn:7029392"
    ],
    "placetype": [
      "aat:300008850"
    ],
    "id": 2651525,
    "name:xx": "Sedgy Point"
  }
}
