{
  "geometry": {
    "type": "Point",
    "coordinates": [
      -108.5333,
      42.3667
    ]
  },
  "type": "Feature",
  "properties": {
    "hierarchy": [
      "tgn:2134830",
      "tgn:1000001",
      "tgn:7012149",
      "tgn:2002371",
      "tgn:7007923",
      "tgn:7029392"
    ],
    "placetype": [
      "aat:300266640"
    ],
    "id": 2134830,
    "name:xx": "Antelope Hills"
  }
}
