{
  "geometry": {
    "type": "Point",
    "coordinates": [
      73.95636,
      26.096823
    ]
  },
  "type": "Feature",
  "properties": {
    "hierarchy": [
      "tgn:7574952",
      "tgn:1000004",
      "tgn:7000198",
      "tgn:7016788",
      "tgn:7029392"
    ],
    "placetype": [
      "aat:300008347"
    ],
    "name:en": "Kushālpura",
    "id": 7574952
  }
}
