{
  "geometry": {
    "type": "Point",
    "coordinates": [
      -77.0333,
      34.8333
    ]
  },
  "type": "Feature",
  "properties": {
    "hierarchy": [
      "tgn:2407120",
      "tgn:1000001",
      "tgn:7012149",
      "tgn:7007709",
      "tgn:7029392"
    ],
    "placetype": [
      "aat:300008706"
    ],
    "id": 2407120,
    "name:xx": "Hunters Creek"
  }
}
