{
  "geometry": {
    "type": "Point",
    "coordinates": [
      -100.2833,
      46.6833
    ]
  },
  "type": "Feature",
  "properties": {
    "hierarchy": [
      "tgn:1117073",
      "tgn:1000001",
      "tgn:7012149",
      "tgn:7007705",
      "tgn:7029392"
    ],
    "placetype": [
      "aat:300008680"
    ],
    "id": 1117073,
    "name:xx": "Long Lake"
  }
}
