{
  "geometry": {
    "type": "Point",
    "coordinates": [
      14.8333,
      63.3333
    ]
  },
  "type": "Feature",
  "properties": {
    "hierarchy": [
      "tgn:1063319",
      "tgn:1000003",
      "tgn:7003773",
      "tgn:1000097",
      "tgn:7029392"
    ],
    "placetype": [
      "aat:300008347"
    ],
    "id": 1063319,
    "name:xx": "Lit"
  }
}
