{
  "geometry": {
    "type": "Point",
    "coordinates": [
      -132.35,
      55.5667
    ]
  },
  "type": "Feature",
  "properties": {
    "hierarchy": [
      "tgn:2418373",
      "tgn:7006450",
      "tgn:1000001",
      "tgn:7012149",
      "tgn:2000082",
      "tgn:7029392"
    ],
    "placetype": [
      "aat:300008798"
    ],
    "id": 2418373,
    "name:xx": "Jacobs Mountain"
  }
}
