{
  "geometry": {
    "type": "Point",
    "coordinates": [
      -97.6333,
      33.3667
    ]
  },
  "type": "Feature",
  "properties": {
    "hierarchy": [
      "tgn:2146003",
      "tgn:1000001",
      "tgn:7012149",
      "tgn:1003031",
      "tgn:7007826",
      "tgn:7029392"
    ],
    "placetype": [
      "aat:300008798"
    ],
    "id": 2146003,
    "name:xx": "Ball Knob Hill"
  }
}
