{
  "geometry": {
    "type": "Point",
    "coordinates": [
      -73.1833,
      43.8333
    ]
  },
  "type": "Feature",
  "properties": {
    "hierarchy": [
      "tgn:2156517",
      "tgn:2002130",
      "tgn:1000001",
      "tgn:7012149",
      "tgn:7007828",
      "tgn:7029392"
    ],
    "placetype": [
      "aat:300008791"
    ],
    "id": 2156517,
    "name:xx": "Beartrap Island"
  }
}
