{
  "geometry": {
    "type": "Point",
    "coordinates": [
      -119.0167,
      36.9167
    ]
  },
  "type": "Feature",
  "properties": {
    "hierarchy": [
      "tgn:2177491",
      "tgn:1000001",
      "tgn:7012149",
      "tgn:1002392",
      "tgn:7007157",
      "tgn:7029392"
    ],
    "placetype": [
      "aat:300006191"
    ],
    "id": 2177491,
    "name:xx": "Black Rock Reservoir"
  }
}
