{
  "geometry": {
    "type": "Point",
    "coordinates": [
      -92.4333,
      36.4167
    ]
  },
  "type": "Feature",
  "properties": {
    "hierarchy": [
      "tgn:7022328",
      "tgn:1000001",
      "tgn:7012149",
      "tgn:7029392"
    ],
    "placetype": [
      "aat:300008798"
    ],
    "id": 7022328,
    "name:xx": "Bald Dave"
  }
}
