{
  "geometry": {
    "type": "Point",
    "coordinates": [
      -109.4833,
      37.8667
    ]
  },
  "type": "Feature",
  "properties": {
    "hierarchy": [
      "tgn:2490975",
      "tgn:1000001",
      "tgn:7012149",
      "tgn:7029392"
    ],
    "placetype": [
      "aat:300008863"
    ],
    "id": 2490975,
    "name:xx": "Manti-La Sal National Forest-La Sal Division"
  }
}
