{
  "geometry": {
    "type": "Point",
    "coordinates": [
      -86.5167,
      40.35
    ]
  },
  "type": "Feature",
  "properties": {
    "hierarchy": [
      "tgn:2191175",
      "tgn:1000001",
      "tgn:1002282",
      "tgn:7012149",
      "tgn:7007252",
      "tgn:7029392"
    ],
    "placetype": [
      "aat:300006075"
    ],
    "id": 2191175,
    "name:xx": "Boyles Ditch"
  }
}
