{
  "geometry": {
    "type": "Point",
    "coordinates": [
      -111.5667,
      41.15
    ]
  },
  "type": "Feature",
  "properties": {
    "hierarchy": [
      "tgn:2603019",
      "tgn:1000001",
      "tgn:7012149",
      "tgn:2002115",
      "tgn:7007827",
      "tgn:7029392"
    ],
    "placetype": [
      "aat:300008706"
    ],
    "id": 2603019,
    "name:xx": "Quarry Cottonwood Creek"
  }
}
