{
  "geometry": {
    "type": "Point",
    "coordinates": [
      -87.0833,
      33.9833
    ]
  },
  "type": "Feature",
  "properties": {
    "hierarchy": [
      "tgn:2002492",
      "tgn:7002659",
      "tgn:1000001",
      "tgn:7012149",
      "tgn:2000021",
      "tgn:7029392"
    ],
    "placetype": [
      "aat:300008347",
      "aat:300387210"
    ],
    "id": 2002492,
    "name:xx": "Ardell"
  }
}
