{
  "geometry": {
    "type": "Point",
    "coordinates": [
      -123.15,
      40.35
    ]
  },
  "type": "Feature",
  "properties": {
    "hierarchy": [
      "tgn:2672439",
      "tgn:1000001",
      "tgn:7012149",
      "tgn:7007157",
      "tgn:2000191",
      "tgn:7029392"
    ],
    "placetype": [
      "aat:300008706"
    ],
    "id": 2672439,
    "name:xx": "Smoky Creek"
  }
}
