{
  "geometry": {
    "type": "Point",
    "coordinates": [
      -93.25,
      30.9833
    ]
  },
  "type": "Feature",
  "properties": {
    "hierarchy": [
      "tgn:2453465",
      "tgn:1000001",
      "tgn:7012149",
      "tgn:2000911",
      "tgn:7007256",
      "tgn:7029392"
    ],
    "placetype": [
      "aat:300008706"
    ],
    "id": 2453465,
    "name:xx": "Little Clear Creek"
  }
}
