{
  "geometry": {
    "type": "Point",
    "coordinates": [
      30.638321,
      30.826984
    ]
  },
  "type": "Feature",
  "properties": {
    "hierarchy": [
      "tgn:7531320",
      "tgn:7001242",
      "tgn:1001075",
      "tgn:7016833",
      "tgn:7029392"
    ],
    "placetype": [
      "aat:300006075"
    ],
    "name:en": "Tur'at Abū Diyāb al 'Ulyā",
    "id": 7531320
  }
}
