{
  "geometry": {
    "type": "Point",
    "coordinates": [
      -81.6167,
      39.0333
    ]
  },
  "type": "Feature",
  "properties": {
    "hierarchy": [
      "tgn:2575083",
      "tgn:1000001",
      "tgn:7012149",
      "tgn:7013961",
      "tgn:7029392"
    ],
    "placetype": [
      "aat:300008699"
    ],
    "id": 2575083,
    "name:xx": "Pennike Run"
  }
}
