{
  "geometry": {
    "type": "Point",
    "coordinates": [
      -84.4667,
      33.2833
    ]
  },
  "type": "Feature",
  "properties": {
    "hierarchy": [
      "tgn:7022589",
      "tgn:1000001",
      "tgn:7012149",
      "tgn:7007248",
      "tgn:7029392"
    ],
    "placetype": [
      "aat:300006191"
    ],
    "id": 7022589,
    "name:xx": "Kelley Lake"
  }
}
