{
  "type": "FeatureCollection",
  "features": [
    {
      "geometry": {
        "type": "Point",
        "coordinates": [
          -71.75,
          43.7833
        ]
      },
      "type": "Feature",
      "properties": {
        "hierarchy": [
          "tgn:2469980",
          "tgn:1000001",
          "tgn:2001424",
          "tgn:7012149",
          "tgn:7007564",
          "tgn:7029392"
        ],
        "placetype": [
          "aat:300008680"
        ],
        "id": 2469980,
        "name:xx": "Loon Lake"
      }
    },
    {
      "geometry": {
        "type": "Point",
        "coordinates": [
          -77.5667,
          42.4833
        ]
      },
      "type": "Feature",
      "properties": {
        "hierarchy": [
          "tgn:2469981",
          "tgn:1000001",
          "tgn:7012149",
          "tgn:1002920",
          "tgn:7007568",
          "tgn:7029392"
        ],
        "placetype": [
          "aat:300008680"
        ],
        "id": 2469981,
        "name:xx": "Loon Lake"
      }
    },
    {
      "geometry": {
        "type": "Point",
        "coordinates": [
          -73.85,
          43.6667
        ]
      },
      "type": "Feature",
      "properties": {
        "hierarchy": [
          "tgn:2469982",
          "tgn:1000001",
          "tgn:7012149",
          "tgn:1002986",
          "tgn:7007568",
          "tgn:7029392"
        ],
        "placetype": [
          "aat:300008680"
        ],
        "id": 2469982,
        "name:xx": "Loon Lake"
      }
    },
    {
      "geometry": {
        "type": "Point",
        "coordinates": [
          -74.9333,
          43.9
        ]
      },
      "type": "Feature",
      "properties": {
        "hierarchy": [
          "tgn:2469983",
          "tgn:1000001",
          "tgn:7012149",
          "tgn:1002472",
          "tgn:7007568",
          "tgn:7029392"
        ],
        "placetype": [
          "aat:300008680"
        ],
        "id": 2469983,
        "name:xx": "Loon Lake"
      }
    },
    {
      "geometry": {
        "type": "Point",
        "coordinates": [
          -74.0667,
          44.55
        ]
      },
      "type": "Feature",
      "properties": {
        "hierarchy": [
          "tgn:2469984",
          "tgn:1000001",
          "tgn:7012149",
          "tgn:7013941",
          "tgn:7007568",
          "tgn:7029392"
        ],
        "placetype": [
          "aat:300008680"
        ],
        "id": 2469984,
        "name:xx": "Loon Lake"
      }
    },
    {
      "geometry": {
        "type": "Point",
        "coordinates": [
          -100.3,
          48.9333
        ]
      },
      "type": "Feature",
      "properties": {
        "hierarchy": [
          "tgn:2469985",
          "tgn:7020393",
          "tgn:1000001",
          "tgn:7012149",
          "tgn:7007705",
          "tgn:7029392"
        ],
        "placetype": [
          "aat:300008680"
        ],
        "id": 2469985,
        "name:xx": "Loon Lake"
      }
    },
    {
      "geometry": {
        "type": "Point",
        "coordinates": [
          -123.8333,
          43.5833
        ]
      },
      "type": "Feature",
      "properties": {
        "hierarchy": [
          "tgn:2469986",
          "tgn:1000001",
          "tgn:7012149",
          "tgn:2001706",
          "tgn:7007708",
          "tgn:7029392"
        ],
        "placetype": [
          "aat:300008680"
        ],
        "id": 2469986,
        "name:xx": "Loon Lake"
      }
    },
    {
      "geometry": {
        "type": "Point",
        "coordinates": [
          -124.1333,
          43.8667
        ]
      },
      "type": "Feature",
      "properties": {
        "hierarchy": [
          "tgn:2469987",
          "tgn:1000001",
          "tgn:7012149",
          "tgn:2001716",
          "tgn:7007708",
          "tgn:7029392"
        ],
        "placetype": [
          "aat:300008680"
        ],
        "id": 2469987,
        "name:xx": "Loon Lake"
      }
    },
    {
      "geometry": {
        "type": "Point",
        "coordinates": [
          -117.6167,
          48.0333
        ]
      },
      "type": "Feature",
      "properties": {
        "hierarchy": [
          "tgn:2469988",
          "tgn:1000001",
          "tgn:7012149",
          "tgn:2002250",
          "tgn:7007920",
          "tgn:7029392"
        ],
        "placetype": [
          "aat:300008680"
        ],
        "id": 2469988,
        "name:xx": "Loon Lake"
      }
    },
    {
      "geometry": {
        "type": "Point",
        "coordinates": [
          -88.5,
          44.8333
        ]
      },
      "type": "Feature",
      "properties": {
        "hierarchy": [
          "tgn:2469989",
          "tgn:1000001",
          "tgn:7012149",
          "tgn:2002354",
          "tgn:7007922",
          "tgn:7029392"
        ],
        "placetype": [
          "aat:300008680"
        ],
        "id": 2469989,
        "name:xx": "Loon Lake"
      }
    }
  ]
}
