{
  "geometry": {
    "type": "Point",
    "coordinates": [
      -96.0667,
      33.35
    ]
  },
  "type": "Feature",
  "properties": {
    "hierarchy": [
      "tgn:2563980",
      "tgn:1000001",
      "tgn:7012149",
      "tgn:1002492",
      "tgn:7007826",
      "tgn:7029392"
    ],
    "placetype": [
      "aat:300008706"
    ],
    "id": 2563980,
    "name:xx": "Oyster Creek"
  }
}
