{
  "geometry": {
    "type": "Point",
    "coordinates": [
      -112.1333,
      39.9667
    ]
  },
  "type": "Feature",
  "properties": {
    "hierarchy": [
      "tgn:2622587",
      "tgn:1000001",
      "tgn:7012149",
      "tgn:2002112",
      "tgn:7007827",
      "tgn:7029392"
    ],
    "placetype": [
      "aat:300008761"
    ],
    "id": 2622587,
    "name:xx": "Robinson Canyon"
  }
}
