{
  "geometry": {
    "type": "Point",
    "coordinates": [
      126.8167,
      37.7167
    ]
  },
  "type": "Feature",
  "properties": {
    "hierarchy": [
      "tgn:1082305",
      "tgn:1000004",
      "tgn:1001370",
      "tgn:7000299",
      "tgn:7029392"
    ],
    "placetype": [
      "aat:300008347"
    ],
    "id": 1082305,
    "name:xx": "Munbong-ni"
  }
}
