{
  "geometry": {
    "type": "Point",
    "coordinates": [
      -107.75,
      37.8833
    ]
  },
  "type": "Feature",
  "properties": {
    "hierarchy": [
      "tgn:2593742",
      "tgn:1000001",
      "tgn:7012149",
      "tgn:7007158",
      "tgn:2000247",
      "tgn:7029392"
    ],
    "placetype": [
      "aat:300008680"
    ],
    "id": 2593742,
    "name:xx": "Porphyry Lake"
  }
}
