{
  "geometry": {
    "type": "Point",
    "coordinates": [
      -111.8167,
      45.5667
    ]
  },
  "type": "Feature",
  "properties": {
    "hierarchy": [
      "tgn:2749174",
      "tgn:1000001",
      "tgn:7012149",
      "tgn:2001288",
      "tgn:7007524",
      "tgn:7029392"
    ],
    "placetype": [
      "aat:300008798"
    ],
    "id": 2749174,
    "name:xx": "Wallace Peak"
  }
}
