{
  "geometry": {
    "type": "Point",
    "coordinates": [
      120.8167,
      27.65
    ]
  },
  "type": "Feature",
  "properties": {
    "hierarchy": [
      "tgn:1006798",
      "tgn:1000004",
      "tgn:7002076",
      "tgn:1000111",
      "tgn:7029392"
    ],
    "placetype": [
      "aat:300008791"
    ],
    "id": 1006798,
    "name:xx": "Chitou Shan"
  }
}
