{
  "geometry": {
    "type": "Point",
    "coordinates": [
      -5.716,
      -15.916
    ]
  },
  "type": "Feature",
  "properties": {
    "hierarchy": [
      "tgn:7593118",
      "tgn:7005278",
      "tgn:7001242",
      "tgn:7005277",
      "tgn:7029392"
    ],
    "placetype": [
      "aat:300387007"
    ],
    "id": 7593118,
    "name:xx": "Ruperts Battery"
  }
}
