{
  "geometry": {
    "type": "Point",
    "coordinates": [
      -92.85,
      41.0667
    ]
  },
  "type": "Feature",
  "properties": {
    "hierarchy": [
      "tgn:2371189",
      "tgn:1000001",
      "tgn:7012149",
      "tgn:2000628",
      "tgn:7007253",
      "tgn:7029392"
    ],
    "placetype": [
      "aat:300008347"
    ],
    "id": 2371189,
    "name:xx": "Hagerty"
  }
}
