{
  "geometry": {
    "type": "Point",
    "coordinates": [
      -123.4833,
      60.2333
    ]
  },
  "type": "Feature",
  "properties": {
    "hierarchy": [
      "tgn:1128576",
      "tgn:7005685",
      "tgn:1000001",
      "tgn:7029392"
    ],
    "placetype": [
      "aat:300008707"
    ],
    "id": 1128576,
    "name:xx": "Petitot"
  }
}
