{
  "geometry": {
    "type": "Point",
    "coordinates": [
      -109.9667,
      34.0167
    ]
  },
  "type": "Feature",
  "properties": {
    "hierarchy": [
      "tgn:2337220",
      "tgn:1000001",
      "tgn:7006451",
      "tgn:7012149",
      "tgn:2000099",
      "tgn:7029392"
    ],
    "placetype": [
      "aat:300008761"
    ],
    "id": 2337220,
    "name:xx": "Fourth Hollow"
  }
}
