{
  "type": "FeatureCollection",
  "features": [
    {
      "geometry": {
        "type": "Point",
        "coordinates": [
          121.6776,
          25.128703
        ]
      },
      "type": "Feature",
      "properties": {
        "hierarchy": [
          "tgn:7489290",
          "tgn:1000957",
          "tgn:1000004",
          "tgn:1000141",
          "tgn:7029392"
        ],
        "placetype": [
          "aat:300008347"
        ],
        "id": 7489290,
        "name:xx": "Neiliao"
      }
    },
    {
      "geometry": {
        "type": "Point",
        "coordinates": [
          121.577706,
          25.142823
        ]
      },
      "type": "Feature",
      "properties": {
        "hierarchy": [
          "tgn:7489291",
          "tgn:1000004",
          "tgn:1000959",
          "tgn:1000141",
          "tgn:7029392"
        ],
        "placetype": [
          "aat:300008347"
        ],
        "id": 7489291,
        "name:xx": "Neiliao"
      }
    },
    {
      "geometry": {
        "type": "Point",
        "coordinates": [
          120.653611,
          23.633333
        ]
      },
      "type": "Feature",
      "properties": {
        "hierarchy": [
          "tgn:7489294",
          "tgn:7488858",
          "tgn:1000004",
          "tgn:1000141",
          "tgn:7029392"
        ],
        "placetype": [
          "aat:300008347"
        ],
        "id": 7489294,
        "name:xx": "Neiliao"
      }
    },
    {
      "geometry": {
        "type": "Point",
        "coordinates": [
          120.348945,
          23.617505
        ]
      },
      "type": "Feature",
      "properties": {
        "hierarchy": [
          "tgn:7489295",
          "tgn:1000004",
          "tgn:7001014",
          "tgn:1000141",
          "tgn:7029392"
        ],
        "placetype": [
          "aat:300008347"
        ],
        "id": 7489295,
        "name:xx": "Neiliao"
      }
    },
    {
      "geometry": {
        "type": "Point",
        "coordinates": [
          120.532392,
          22.838212
        ]
      },
      "type": "Feature",
      "properties": {
        "hierarchy": [
          "tgn:7489296",
          "tgn:1000004",
          "tgn:7492971",
          "tgn:1000141",
          "tgn:7029392"
        ],
        "placetype": [
          "aat:300008347"
        ],
        "id": 7489296,
        "name:xx": "Neiliao"
      }
    },
    {
      "geometry": {
        "type": "Point",
        "coordinates": [
          120.619008,
          22.857049
        ]
      },
      "type": "Feature",
      "properties": {
        "hierarchy": [
          "tgn:7489297",
          "tgn:1000004",
          "tgn:7492971",
          "tgn:1000141",
          "tgn:7029392"
        ],
        "placetype": [
          "aat:300008347"
        ],
        "id": 7489297,
        "name:xx": "Ailiao"
      }
    },
    {
      "geometry": {
        "type": "Point",
        "coordinates": [
          120.618333,
          22.392222
        ]
      },
      "type": "Feature",
      "properties": {
        "hierarchy": [
          "tgn:7489298",
          "tgn:1000004",
          "tgn:7492971",
          "tgn:1000141",
          "tgn:7029392"
        ],
        "placetype": [
          "aat:300008347"
        ],
        "id": 7489298,
        "name:xx": "Neiliao"
      }
    },
    {
      "geometry": {
        "type": "Point",
        "coordinates": [
          121.261389,
          24.9725
        ]
      },
      "type": "Feature",
      "properties": {
        "hierarchy": [
          "tgn:7489299",
          "tgn:1000004",
          "tgn:7001013",
          "tgn:1000141",
          "tgn:7029392"
        ],
        "placetype": [
          "aat:300008347"
        ],
        "id": 7489299,
        "name:xx": "Neili"
      }
    }
  ]
}
