{
  "type": "FeatureCollection",
  "features": [
    {
      "geometry": {
        "type": "Point",
        "coordinates": [
          -99.744444,
          24.0275
        ]
      },
      "type": "Feature",
      "properties": {
        "hierarchy": [
          "tgn:7374720",
          "tgn:1000001",
          "tgn:7005589",
          "tgn:7005560",
          "tgn:7029392"
        ],
        "placetype": [
          "aat:300008795"
        ],
        "id": 7374720,
        "name:xx": "La Lagunita, Sierra"
      }
    },
    {
      "geometry": {
        "type": "Point",
        "coordinates": [
          -99.633333,
          22.816667
        ]
      },
      "type": "Feature",
      "properties": {
        "hierarchy": [
          "tgn:7374721",
          "tgn:1000001",
          "tgn:7005597",
          "tgn:7005560",
          "tgn:7029392"
        ],
        "placetype": [
          "aat:300008795"
        ],
        "id": 7374721,
        "name:xx": "Lagunita, Sierra"
      }
    },
    {
      "geometry": {
        "type": "Point",
        "coordinates": [
          -112.016667,
          31.533333
        ]
      },
      "type": "Feature",
      "properties": {
        "hierarchy": [
          "tgn:7374722",
          "tgn:1000001",
          "tgn:1001960",
          "tgn:7005560",
          "tgn:7029392"
        ],
        "placetype": [
          "aat:300006191"
        ],
        "id": 7374722,
        "name:xx": "Presa Lagunita"
      }
    },
    {
      "geometry": {
        "type": "Point",
        "coordinates": [
          -107.733333,
          30.4
        ]
      },
      "type": "Feature",
      "properties": {
        "hierarchy": [
          "tgn:7374723",
          "tgn:7005581",
          "tgn:1000001",
          "tgn:7005560",
          "tgn:7029392"
        ],
        "placetype": [
          "aat:300008795"
        ],
        "id": 7374723,
        "name:xx": "Lagunita, Cerro"
      }
    },
    {
      "geometry": {
        "type": "Point",
        "coordinates": [
          -106.816667,
          28.333333
        ]
      },
      "type": "Feature",
      "properties": {
        "hierarchy": [
          "tgn:7374724",
          "tgn:7005581",
          "tgn:1000001",
          "tgn:7005560",
          "tgn:7029392"
        ],
        "placetype": [
          "aat:300008347"
        ],
        "id": 7374724,
        "name:xx": "Lagunita"
      }
    },
    {
      "geometry": {
        "type": "Point",
        "coordinates": [
          -99.976944,
          23.495833
        ]
      },
      "type": "Feature",
      "properties": {
        "hierarchy": [
          "tgn:7374725",
          "tgn:1000001",
          "tgn:7005589",
          "tgn:7005560",
          "tgn:7029392"
        ],
        "placetype": [
          "aat:300008347"
        ],
        "id": 7374725,
        "name:xx": "Lagunita"
      }
    },
    {
      "geometry": {
        "type": "Point",
        "coordinates": [
          -99.944444,
          25.334722
        ]
      },
      "type": "Feature",
      "properties": {
        "hierarchy": [
          "tgn:7374726",
          "tgn:1000001",
          "tgn:7005589",
          "tgn:7005560",
          "tgn:7029392"
        ],
        "placetype": [
          "aat:300008347"
        ],
        "id": 7374726,
        "name:es": "La Cruz"
      }
    },
    {
      "geometry": {
        "type": "Point",
        "coordinates": [
          -99.55,
          25.283333
        ]
      },
      "type": "Feature",
      "properties": {
        "hierarchy": [
          "tgn:7374727",
          "tgn:1000001",
          "tgn:7005589",
          "tgn:7005560",
          "tgn:7029392"
        ],
        "placetype": [
          "aat:300008347"
        ],
        "id": 7374727,
        "name:xx": "La Cruz"
      }
    },
    {
      "geometry": {
        "type": "Point",
        "coordinates": [
          -99.85,
          25.133333
        ]
      },
      "type": "Feature",
      "properties": {
        "hierarchy": [
          "tgn:7374728",
          "tgn:1000001",
          "tgn:7005589",
          "tgn:7005560",
          "tgn:7029392"
        ],
        "placetype": [
          "aat:300008347"
        ],
        "id": 7374728,
        "name:xx": "La Cruz"
      }
    },
    {
      "geometry": {
        "type": "Point",
        "coordinates": [
          -107.55,
          25.066667
        ]
      },
      "type": "Feature",
      "properties": {
        "hierarchy": [
          "tgn:7374729",
          "tgn:1000001",
          "tgn:7005595",
          "tgn:7005560",
          "tgn:7029392"
        ],
        "placetype": [
          "aat:300008347"
        ],
        "id": 7374729,
        "name:xx": "La Cruz"
      }
    }
  ]
}
