{
  "geometry": {
    "type": "Point",
    "coordinates": [
      -101.6667,
      34.9667
    ]
  },
  "type": "Feature",
  "properties": {
    "hierarchy": [
      "tgn:2199988",
      "tgn:1000001",
      "tgn:7012149",
      "tgn:2002058",
      "tgn:7007826",
      "tgn:7029392"
    ],
    "placetype": [
      "aat:300008798"
    ],
    "id": 2199988,
    "name:xx": "Brushy Butte"
  }
}
