{
  "geometry": {
    "type": "Point",
    "coordinates": [
      74.95,
      32.525
    ]
  },
  "type": "Feature",
  "properties": {
    "hierarchy": [
      "tgn:7590644",
      "tgn:1000004",
      "tgn:7000198",
      "tgn:7000799",
      "tgn:7029392"
    ],
    "placetype": [
      "aat:300008347"
    ],
    "name:en": "Rarwān Khurd",
    "id": 7590644
  }
}
