{
  "geometry": {
    "type": "Point",
    "coordinates": [
      -109.4167,
      43.2833
    ]
  },
  "type": "Feature",
  "properties": {
    "hierarchy": [
      "tgn:2298395",
      "tgn:1000001",
      "tgn:7012149",
      "tgn:7029392"
    ],
    "placetype": [
      "aat:300266640"
    ],
    "id": 2298395,
    "name:xx": "Dry Ridge"
  }
}
