{
  "geometry": {
    "type": "Point",
    "coordinates": [
      -120.8333,
      42.1667
    ]
  },
  "type": "Feature",
  "properties": {
    "hierarchy": [
      "tgn:2396362",
      "tgn:1000001",
      "tgn:7012149",
      "tgn:2001715",
      "tgn:7007708",
      "tgn:7029392"
    ],
    "placetype": [
      "aat:300008905"
    ],
    "id": 2396362,
    "name:xx": "Holmes Meadow"
  }
}
