{
  "geometry": {
    "type": "Point",
    "coordinates": [
      -89.5167,
      32.6667
    ]
  },
  "type": "Feature",
  "properties": {
    "hierarchy": [
      "tgn:2056486",
      "tgn:1000001",
      "tgn:7012149",
      "tgn:2001125",
      "tgn:7007522",
      "tgn:7029392"
    ],
    "placetype": [
      "aat:300008347",
      "aat:300387210"
    ],
    "id": 2056486,
    "name:xx": "Gill"
  }
}
