{
  "type": "FeatureCollection",
  "features": [
    {
      "geometry": {
        "type": "Point",
        "coordinates": [
          -0.333333,
          39.2
        ]
      },
      "type": "Feature",
      "properties": {
        "hierarchy": [
          "tgn:7323230",
          "tgn:7001165",
          "tgn:1000003",
          "tgn:7002793",
          "tgn:1000095",
          "tgn:7029392"
        ],
        "placetype": [
          "aat:300008347"
        ],
        "id": 7323230,
        "name:xx": "Riola"
      }
    },
    {
      "geometry": {
        "type": "Point",
        "coordinates": [
          -7.283333,
          43.166667
        ]
      },
      "type": "Feature",
      "properties": {
        "hierarchy": [
          "tgn:7323231",
          "tgn:7002829",
          "tgn:1000003",
          "tgn:7002786",
          "tgn:1000095",
          "tgn:7029392"
        ],
        "placetype": [
          "aat:300008347"
        ],
        "id": 7323231,
        "name:xx": "Riojuán"
      }
    },
    {
      "geometry": {
        "type": "Point",
        "coordinates": [
          -2.666667,
          42.5
        ]
      },
      "type": "Feature",
      "properties": {
        "hierarchy": [
          "tgn:7323232",
          "tgn:7007088",
          "tgn:1000003",
          "tgn:7009604",
          "tgn:1000095",
          "tgn:7029392"
        ],
        "placetype": [
          "aat:300387346"
        ],
        "id": 7323232,
        "name:xx": "Rioja Alavesa"
      }
    },
    {
      "geometry": {
        "type": "Point",
        "coordinates": [
          -4.3,
          36.916667
        ]
      },
      "type": "Feature",
      "properties": {
        "hierarchy": [
          "tgn:7323234",
          "tgn:7002758",
          "tgn:7002830",
          "tgn:1000003",
          "tgn:1000095",
          "tgn:7029392"
        ],
        "placetype": [
          "aat:300008347"
        ],
        "id": 7323234,
        "name:xx": "Ríogordo"
      }
    },
    {
      "geometry": {
        "type": "Point",
        "coordinates": [
          -3.45,
          41.25
        ]
      },
      "type": "Feature",
      "properties": {
        "hierarchy": [
          "tgn:7323235",
          "tgn:7002839",
          "tgn:7001158",
          "tgn:1000003",
          "tgn:1000095",
          "tgn:7029392"
        ],
        "placetype": [
          "aat:300008347"
        ],
        "id": 7323235,
        "name:xx": "Ríofrío de Riaza"
      }
    },
    {
      "geometry": {
        "type": "Point",
        "coordinates": [
          -6.166667,
          41.816667
        ]
      },
      "type": "Feature",
      "properties": {
        "hierarchy": [
          "tgn:7323237",
          "tgn:7001158",
          "tgn:7002850",
          "tgn:1000003",
          "tgn:1000095",
          "tgn:7029392"
        ],
        "placetype": [
          "aat:300008347"
        ],
        "id": 7323237,
        "name:xx": "Ríofrío de Aliste"
      }
    },
    {
      "geometry": {
        "type": "Point",
        "coordinates": [
          -4.466667,
          39.1
        ]
      },
      "type": "Feature",
      "properties": {
        "hierarchy": [
          "tgn:7323238",
          "tgn:7002816",
          "tgn:1001647",
          "tgn:1000003",
          "tgn:1000095",
          "tgn:7029392"
        ],
        "placetype": [
          "aat:300266640"
        ],
        "id": 7323238,
        "name:xx": "Río Frío, Sierra de"
      }
    },
    {
      "geometry": {
        "type": "Point",
        "coordinates": [
          -6.166667,
          41.733333
        ]
      },
      "type": "Feature",
      "properties": {
        "hierarchy": [
          "tgn:7323239",
          "tgn:7001158",
          "tgn:7002850",
          "tgn:1000003",
          "tgn:1000095",
          "tgn:7029392"
        ],
        "placetype": [
          "aat:300008699"
        ],
        "id": 7323239,
        "name:xx": "Ríofrío, Rivera de"
      }
    }
  ]
}
