{
  "geometry": {
    "type": "Point",
    "coordinates": [
      -81.7167,
      37.75
    ]
  },
  "type": "Feature",
  "properties": {
    "hierarchy": [
      "tgn:2427342",
      "tgn:1000001",
      "tgn:7012149",
      "tgn:2002273",
      "tgn:7013961",
      "tgn:7029392"
    ],
    "placetype": [
      "aat:300008699"
    ],
    "id": 2427342,
    "name:xx": "Jordan Fork"
  }
}
