{
  "geometry": {
    "type": "Point",
    "coordinates": [
      -111.05,
      42.0667
    ]
  },
  "type": "Feature",
  "properties": {
    "hierarchy": [
      "tgn:2297840",
      "tgn:1000001",
      "tgn:7012149",
      "tgn:7029392"
    ],
    "placetype": [
      "aat:300008761"
    ],
    "id": 2297840,
    "name:xx": "Dry Hollow"
  }
}
