{
  "geometry": {
    "type": "Point",
    "coordinates": [
      -152.4333,
      57.7833
    ]
  },
  "type": "Feature",
  "properties": {
    "hierarchy": [
      "tgn:2581291",
      "tgn:7006450",
      "tgn:1000001",
      "tgn:2124012",
      "tgn:7012149",
      "tgn:7029392"
    ],
    "placetype": [
      "aat:300008798"
    ],
    "id": 2581291,
    "name:xx": "Pillar Mountain"
  }
}
