{
  "geometry": {
    "type": "Point",
    "coordinates": [
      -114.15,
      47.6833
    ]
  },
  "type": "Feature",
  "properties": {
    "hierarchy": [
      "tgn:2061628",
      "tgn:1000001",
      "tgn:7012149",
      "tgn:2001283",
      "tgn:7007524",
      "tgn:7029392"
    ],
    "placetype": [
      "aat:300008347"
    ],
    "id": 2061628,
    "name:xx": "Polson"
  }
}
