{
  "geometry": {
    "type": "Point",
    "coordinates": [
      -76.6833,
      44.7667
    ]
  },
  "type": "Feature",
  "properties": {
    "hierarchy": [
      "tgn:1118119",
      "tgn:7005685",
      "tgn:1000001",
      "tgn:7013154",
      "tgn:7029392"
    ],
    "placetype": [
      "aat:300008680"
    ],
    "id": 1118119,
    "name:xx": "Sharbot Lake"
  }
}
