{
  "geometry": {
    "type": "Point",
    "coordinates": [
      -103.2333,
      48.1833
    ]
  },
  "type": "Feature",
  "properties": {
    "hierarchy": [
      "tgn:2525539",
      "tgn:1000001",
      "tgn:7012149",
      "tgn:2001609",
      "tgn:7007705",
      "tgn:7029392"
    ],
    "placetype": [
      "aat:300008697"
    ],
    "id": 2525539,
    "name:xx": "Mort Adams Spring"
  }
}
