{
  "geometry": {
    "type": "Point",
    "coordinates": [
      -142.6667,
      61.45
    ]
  },
  "type": "Feature",
  "properties": {
    "hierarchy": [
      "tgn:2541469",
      "tgn:7006450",
      "tgn:1000001",
      "tgn:7012149",
      "tgn:2000086",
      "tgn:7029392"
    ],
    "placetype": [
      "aat:300000390"
    ],
    "id": 2541469,
    "name:xx": "Nikolai Mine"
  }
}
