{
  "geometry": {
    "type": "Point",
    "coordinates": [
      -90.6667,
      43.85
    ]
  },
  "type": "Feature",
  "properties": {
    "hierarchy": [
      "tgn:2323374",
      "tgn:1000001",
      "tgn:7012149",
      "tgn:2002340",
      "tgn:7007922",
      "tgn:7029392"
    ],
    "placetype": [
      "aat:300008761"
    ],
    "id": 2323374,
    "name:xx": "Farmers Valley"
  }
}
