{
  "geometry": {
    "type": "Point",
    "coordinates": [
      -4.266667,
      40.95
    ]
  },
  "type": "Feature",
  "properties": {
    "hierarchy": [
      "tgn:7307113",
      "tgn:7002839",
      "tgn:7001158",
      "tgn:1000003",
      "tgn:1000095",
      "tgn:7029392"
    ],
    "placetype": [
      "aat:300008347"
    ],
    "id": 7307113,
    "name:xx": "Martín Miguel"
  }
}
