{
  "geometry": {
    "type": "Point",
    "coordinates": [
      9.7167,
      55.7333
    ]
  },
  "type": "Feature",
  "properties": {
    "hierarchy": [
      "tgn:1027771",
      "tgn:7594006",
      "tgn:1000003",
      "tgn:1000066",
      "tgn:7029392"
    ],
    "placetype": [
      "aat:300008347"
    ],
    "id": 1027771,
    "name:xx": "Daugård"
  }
}
