{
  "geometry": {
    "type": "Point",
    "coordinates": [
      -88.0167,
      45.4167
    ]
  },
  "type": "Feature",
  "properties": {
    "hierarchy": [
      "tgn:2524330",
      "tgn:1000001",
      "tgn:7012149",
      "tgn:2002337",
      "tgn:7007922",
      "tgn:7029392"
    ],
    "placetype": [
      "aat:300008680"
    ],
    "id": 2524330,
    "name:xx": "Morgan Lake"
  }
}
