{
  "geometry": {
    "type": "Point",
    "coordinates": [
      -81.1667,
      38.5833
    ]
  },
  "type": "Feature",
  "properties": {
    "hierarchy": [
      "tgn:2170716",
      "tgn:1000001",
      "tgn:7012149",
      "tgn:7013961",
      "tgn:7029392"
    ],
    "placetype": [
      "aat:300008706"
    ],
    "id": 2170716,
    "name:xx": "Big Sandy Creek"
  }
}
