{
  "geometry": {
    "type": "Point",
    "coordinates": [
      -81.5833,
      38.3833
    ]
  },
  "type": "Feature",
  "properties": {
    "hierarchy": [
      "tgn:2517123",
      "tgn:1000001",
      "tgn:7012149",
      "tgn:2002270",
      "tgn:7013961",
      "tgn:7029392"
    ],
    "placetype": [
      "aat:300132348"
    ],
    "id": 2517123,
    "name:xx": "Mink Shoals"
  }
}
