{
  "geometry": {
    "type": "Point",
    "coordinates": [
      -90.05,
      38.65
    ]
  },
  "type": "Feature",
  "properties": {
    "hierarchy": [
      "tgn:2520662",
      "tgn:1000001",
      "tgn:7012149",
      "tgn:1002622",
      "tgn:7007251",
      "tgn:7029392"
    ],
    "placetype": [
      "aat:300008798"
    ],
    "id": 2520662,
    "name:xx": "Monks Mound"
  }
}
