{
  "geometry": {
    "type": "Point",
    "coordinates": [
      -7.448,
      38.14
    ]
  },
  "type": "Feature",
  "properties": {
    "hierarchy": [
      "tgn:7010972",
      "tgn:1000810",
      "tgn:1000003",
      "tgn:1000090",
      "tgn:7029392"
    ],
    "placetype": [
      "aat:300008347",
      "aat:300387218"
    ],
    "id": 7010972,
    "name:xx": "Moura"
  }
}
