{
  "geometry": {
    "type": "Point",
    "coordinates": [
      -87.8167,
      33.4167
    ]
  },
  "type": "Feature",
  "properties": {
    "hierarchy": [
      "tgn:2618896",
      "tgn:7002659",
      "tgn:1000001",
      "tgn:7012149",
      "tgn:2000062",
      "tgn:7029392"
    ],
    "placetype": [
      "aat:300008706"
    ],
    "id": 2618896,
    "name:xx": "Right Hand Fork Dunn Creek"
  }
}
