{
  "geometry": {
    "type": "Point",
    "coordinates": [
      -75.3833,
      40.5667
    ]
  },
  "type": "Feature",
  "properties": {
    "hierarchy": [
      "tgn:2094731",
      "tgn:1000001",
      "tgn:7012149",
      "tgn:1002729",
      "tgn:7007710",
      "tgn:7029392"
    ],
    "placetype": [
      "aat:300008347"
    ],
    "id": 2094731,
    "name:xx": "Wydnor"
  }
}
