{
  "type": "FeatureCollection",
  "features": [
    {
      "geometry": {
        "type": "Point",
        "coordinates": [
          -97.3167,
          39.9833
        ]
      },
      "type": "Feature",
      "properties": {
        "hierarchy": [
          "tgn:2190070",
          "tgn:1000001",
          "tgn:7012149",
          "tgn:2000760",
          "tgn:7007254",
          "tgn:7029392"
        ],
        "placetype": [
          "aat:300008706"
        ],
        "id": 2190070,
        "name:xx": "Bowman Creek"
      }
    },
    {
      "geometry": {
        "type": "Point",
        "coordinates": [
          -84.5333,
          38.9
        ]
      },
      "type": "Feature",
      "properties": {
        "hierarchy": [
          "tgn:2190071",
          "tgn:1000001",
          "tgn:7012149",
          "tgn:1002544",
          "tgn:7007255",
          "tgn:7029392"
        ],
        "placetype": [
          "aat:300008706"
        ],
        "id": 2190071,
        "name:xx": "Bowman Creek"
      }
    },
    {
      "geometry": {
        "type": "Point",
        "coordinates": [
          -76.9,
          38.45
        ]
      },
      "type": "Feature",
      "properties": {
        "hierarchy": [
          "tgn:2190072",
          "tgn:7016100",
          "tgn:1000001",
          "tgn:7012149",
          "tgn:7007516",
          "tgn:7029392"
        ],
        "placetype": [
          "aat:300008706"
        ],
        "id": 2190072,
        "name:xx": "Bowman Creek"
      }
    },
    {
      "geometry": {
        "type": "Point",
        "coordinates": [
          -93.85,
          47.8
        ]
      },
      "type": "Feature",
      "properties": {
        "hierarchy": [
          "tgn:2190073",
          "tgn:1000001",
          "tgn:7012149",
          "tgn:2001029",
          "tgn:7007521",
          "tgn:7029392"
        ],
        "placetype": [
          "aat:300008706"
        ],
        "id": 2190073,
        "name:xx": "Bowman Creek"
      }
    },
    {
      "geometry": {
        "type": "Point",
        "coordinates": [
          -92.65,
          37.2833
        ]
      },
      "type": "Feature",
      "properties": {
        "hierarchy": [
          "tgn:2190074",
          "tgn:1000001",
          "tgn:7012149",
          "tgn:2001258",
          "tgn:7007523",
          "tgn:7029392"
        ],
        "placetype": [
          "aat:300008706"
        ],
        "id": 2190074,
        "name:xx": "Bowman Creek"
      }
    },
    {
      "geometry": {
        "type": "Point",
        "coordinates": [
          -106.25,
          45.4833
        ]
      },
      "type": "Feature",
      "properties": {
        "hierarchy": [
          "tgn:2190075",
          "tgn:1000001",
          "tgn:7012149",
          "tgn:2001303",
          "tgn:7007524",
          "tgn:7029392"
        ],
        "placetype": [
          "aat:300008706"
        ],
        "id": 2190075,
        "name:xx": "Bowman Creek"
      }
    },
    {
      "geometry": {
        "type": "Point",
        "coordinates": [
          -114.05,
          48.9667
        ]
      },
      "type": "Feature",
      "properties": {
        "hierarchy": [
          "tgn:2190076",
          "tgn:1000001",
          "tgn:7012149",
          "tgn:2001274",
          "tgn:7007524",
          "tgn:7029392"
        ],
        "placetype": [
          "aat:300008706"
        ],
        "id": 2190076,
        "name:xx": "Bowman Creek"
      }
    },
    {
      "geometry": {
        "type": "Point",
        "coordinates": [
          -117.1,
          39.1667
        ]
      },
      "type": "Feature",
      "properties": {
        "hierarchy": [
          "tgn:2190077",
          "tgn:1000001",
          "tgn:7012149",
          "tgn:7007526",
          "tgn:7029392"
        ],
        "placetype": [
          "aat:300008706"
        ],
        "id": 2190077,
        "name:xx": "Bowman Creek"
      }
    },
    {
      "geometry": {
        "type": "Point",
        "coordinates": [
          -75.35,
          44.2167
        ]
      },
      "type": "Feature",
      "properties": {
        "hierarchy": [
          "tgn:2190078",
          "tgn:1000001",
          "tgn:7012149",
          "tgn:7016021",
          "tgn:7007568",
          "tgn:7029392"
        ],
        "placetype": [
          "aat:300008706"
        ],
        "id": 2190078,
        "name:xx": "Bowman Creek"
      }
    },
    {
      "geometry": {
        "type": "Point",
        "coordinates": [
          -75.6667,
          42.5167
        ]
      },
      "type": "Feature",
      "properties": {
        "hierarchy": [
          "tgn:2190079",
          "tgn:1000001",
          "tgn:1002262",
          "tgn:7012149",
          "tgn:7007568",
          "tgn:7029392"
        ],
        "placetype": [
          "aat:300008706"
        ],
        "id": 2190079,
        "name:xx": "Bowman Creek"
      }
    }
  ]
}
