{
  "geometry": {
    "type": "Point",
    "coordinates": [
      -93.6333,
      42.2667
    ]
  },
  "type": "Feature",
  "properties": {
    "hierarchy": [
      "tgn:2462219",
      "tgn:1000001",
      "tgn:2000600",
      "tgn:7012149",
      "tgn:7007253",
      "tgn:7029392"
    ],
    "placetype": [
      "aat:300008680"
    ],
    "id": 2462219,
    "name:xx": "Little Wall Lake"
  }
}
