{
  "geometry": {
    "type": "Point",
    "coordinates": [
      31.929167,
      31.284722
    ]
  },
  "type": "Feature",
  "properties": {
    "hierarchy": [
      "tgn:7544356",
      "tgn:7001242",
      "tgn:1001059",
      "tgn:7016833",
      "tgn:7029392"
    ],
    "placetype": [
      "aat:300008713"
    ],
    "name:en": "Zawā'ir, Maqţa'",
    "id": 7544356
  }
}
