{
  "geometry": {
    "type": "Point",
    "coordinates": [
      -95.8667,
      34.0167
    ]
  },
  "type": "Feature",
  "properties": {
    "hierarchy": [
      "tgn:2082886",
      "tgn:1000001",
      "tgn:2001634",
      "tgn:7012149",
      "tgn:7007707",
      "tgn:7029392"
    ],
    "placetype": [
      "aat:300008347"
    ],
    "id": 2082886,
    "name:xx": "Boswell"
  }
}
