{
  "geometry": {
    "type": "Point",
    "coordinates": [
      -111.3667,
      31.4667
    ]
  },
  "type": "Feature",
  "properties": {
    "hierarchy": [
      "tgn:2246815",
      "tgn:1000001",
      "tgn:7006451",
      "tgn:7012149",
      "tgn:7029392"
    ],
    "placetype": [
      "aat:300008761"
    ],
    "id": 2246815,
    "name:xx": "Coches Canyon"
  }
}
