{
  "geometry": {
    "type": "Point",
    "coordinates": [
      -117.3667,
      48.9167
    ]
  },
  "type": "Feature",
  "properties": {
    "hierarchy": [
      "tgn:2150201",
      "tgn:1000001",
      "tgn:7012149",
      "tgn:2002248",
      "tgn:7007920",
      "tgn:7029392"
    ],
    "placetype": [
      "aat:300008798"
    ],
    "id": 2150201,
    "name:xx": "Basalt Hill"
  }
}
