{
  "geometry": {
    "type": "Point",
    "coordinates": [
      -98.0167,
      29.55
    ]
  },
  "type": "Feature",
  "properties": {
    "hierarchy": [
      "tgn:2525278",
      "tgn:1000001",
      "tgn:7012149",
      "tgn:1002431",
      "tgn:7007826",
      "tgn:7029392"
    ],
    "placetype": [
      "aat:300008347"
    ],
    "id": 2525278,
    "name:xx": "Morrison Falls"
  }
}
