{
  "geometry": {
    "type": "Point",
    "coordinates": [
      -99.3333,
      29.9167
    ]
  },
  "type": "Feature",
  "properties": {
    "hierarchy": [
      "tgn:2460074",
      "tgn:1000001",
      "tgn:7012149",
      "tgn:7007826",
      "tgn:7029392"
    ],
    "placetype": [
      "aat:300008706"
    ],
    "id": 2460074,
    "name:xx": "Little Rocky Creek"
  }
}
