{
  "type": "FeatureCollection",
  "features": [
    {
      "geometry": {
        "type": "Point",
        "coordinates": [
          -79.7333,
          34.8833
        ]
      },
      "type": "Feature",
      "properties": {
        "hierarchy": [
          "tgn:2158360",
          "tgn:1000001",
          "tgn:7012149",
          "tgn:2001533",
          "tgn:7007709",
          "tgn:7029392"
        ],
        "placetype": [
          "aat:300008699"
        ],
        "id": 2158360,
        "name:xx": "Beaverdam Branch"
      }
    },
    {
      "geometry": {
        "type": "Point",
        "coordinates": [
          -77.2833,
          34.9667
        ]
      },
      "type": "Feature",
      "properties": {
        "hierarchy": [
          "tgn:2158361",
          "tgn:1000001",
          "tgn:7012149",
          "tgn:2001510",
          "tgn:7007709",
          "tgn:7029392"
        ],
        "placetype": [
          "aat:300008699"
        ],
        "id": 2158361,
        "name:xx": "Beaverdam Branch"
      }
    },
    {
      "geometry": {
        "type": "Point",
        "coordinates": [
          -77.9833,
          35
        ]
      },
      "type": "Feature",
      "properties": {
        "hierarchy": [
          "tgn:2158362",
          "tgn:1000001",
          "tgn:7012149",
          "tgn:2001491",
          "tgn:7007709",
          "tgn:7029392"
        ],
        "placetype": [
          "aat:300008699"
        ],
        "id": 2158362,
        "name:xx": "Beaverdam Branch"
      }
    },
    {
      "geometry": {
        "type": "Point",
        "coordinates": [
          -77.8,
          35.1667
        ]
      },
      "type": "Feature",
      "properties": {
        "hierarchy": [
          "tgn:2158363",
          "tgn:1000001",
          "tgn:7012149",
          "tgn:7007709",
          "tgn:7029392"
        ],
        "placetype": [
          "aat:300008699"
        ],
        "id": 2158363,
        "name:xx": "Beaverdam Branch"
      }
    },
    {
      "geometry": {
        "type": "Point",
        "coordinates": [
          -77.2167,
          35.1667
        ]
      },
      "type": "Feature",
      "properties": {
        "hierarchy": [
          "tgn:2158364",
          "tgn:1000001",
          "tgn:7012149",
          "tgn:2001486",
          "tgn:7007709",
          "tgn:7029392"
        ],
        "placetype": [
          "aat:300008699"
        ],
        "id": 2158364,
        "name:xx": "Beaverdam Branch"
      }
    },
    {
      "geometry": {
        "type": "Point",
        "coordinates": [
          -78.5667,
          35.5167
        ]
      },
      "type": "Feature",
      "properties": {
        "hierarchy": [
          "tgn:2158365",
          "tgn:1000001",
          "tgn:7012149",
          "tgn:2001509",
          "tgn:7007709",
          "tgn:7029392"
        ],
        "placetype": [
          "aat:300008699"
        ],
        "id": 2158365,
        "name:xx": "Beaverdam Branch"
      }
    },
    {
      "geometry": {
        "type": "Point",
        "coordinates": [
          -78.1,
          36.0167
        ]
      },
      "type": "Feature",
      "properties": {
        "hierarchy": [
          "tgn:2158366",
          "tgn:1000001",
          "tgn:7012149",
          "tgn:2001522",
          "tgn:7007709",
          "tgn:7029392"
        ],
        "placetype": [
          "aat:300008699"
        ],
        "id": 2158366,
        "name:xx": "Beaverdam Branch"
      }
    },
    {
      "geometry": {
        "type": "Point",
        "coordinates": [
          -79.0167,
          34.85
        ]
      },
      "type": "Feature",
      "properties": {
        "hierarchy": [
          "tgn:2158367",
          "tgn:1000001",
          "tgn:7012149",
          "tgn:2001534",
          "tgn:7007709",
          "tgn:7029392"
        ],
        "placetype": [
          "aat:300008699"
        ],
        "id": 2158367,
        "name:xx": "Beaverdam Branch"
      }
    },
    {
      "geometry": {
        "type": "Point",
        "coordinates": [
          -82,
          35.55
        ]
      },
      "type": "Feature",
      "properties": {
        "hierarchy": [
          "tgn:2158368",
          "tgn:1000001",
          "tgn:7012149",
          "tgn:2001514",
          "tgn:7007709",
          "tgn:7029392"
        ],
        "placetype": [
          "aat:300008699"
        ],
        "id": 2158368,
        "name:xx": "Beaverdam Branch"
      }
    },
    {
      "geometry": {
        "type": "Point",
        "coordinates": [
          -80.7,
          35.8
        ]
      },
      "type": "Feature",
      "properties": {
        "hierarchy": [
          "tgn:2158369",
          "tgn:1000001",
          "tgn:7012149",
          "tgn:2001536",
          "tgn:7007709",
          "tgn:7029392"
        ],
        "placetype": [
          "aat:300008699"
        ],
        "id": 2158369,
        "name:xx": "Beaverdam Branch"
      }
    }
  ]
}
