{
  "geometry": {
    "type": "Point",
    "coordinates": [
      112.4333,
      -7.0833
    ]
  },
  "type": "Feature",
  "properties": {
    "hierarchy": [
      "tgn:1077960",
      "tgn:1000004",
      "tgn:1001323",
      "tgn:1000116",
      "tgn:7029392"
    ],
    "placetype": [
      "aat:300008347"
    ],
    "id": 1077960,
    "name:xx": "Lamongan"
  }
}
