{
  "geometry": {
    "type": "Point",
    "coordinates": [
      -71.3833,
      42.25
    ]
  },
  "type": "Feature",
  "properties": {
    "hierarchy": [
      "tgn:2199655",
      "tgn:1000001",
      "tgn:1002665",
      "tgn:7012149",
      "tgn:7007517",
      "tgn:7029392"
    ],
    "placetype": [
      "aat:300008798"
    ],
    "id": 2199655,
    "name:xx": "Brush Hill"
  }
}
