{
  "geometry": {
    "type": "Point",
    "coordinates": [
      103.05,
      0.8667
    ]
  },
  "type": "Feature",
  "properties": {
    "hierarchy": [
      "tgn:1078763",
      "tgn:1000004",
      "tgn:1001502",
      "tgn:1008727",
      "tgn:1000116",
      "tgn:7029392"
    ],
    "placetype": [
      "aat:300008347"
    ],
    "id": 1078763,
    "name:xx": "Teluksamak"
  }
}
