{
  "type": "FeatureCollection",
  "features": [
    {
      "geometry": {
        "type": "Point",
        "coordinates": [
          -97.7833,
          46
        ]
      },
      "type": "Feature",
      "properties": {
        "hierarchy": [
          "tgn:1131800",
          "tgn:1000001",
          "tgn:7012149",
          "tgn:7007705",
          "tgn:7029392"
        ],
        "placetype": [
          "aat:300008707"
        ],
        "id": 1131800,
        "name:xx": "Wild Rice"
      }
    },
    {
      "geometry": {
        "type": "Point",
        "coordinates": [
          -117.3167,
          54.05
        ]
      },
      "type": "Feature",
      "properties": {
        "hierarchy": [
          "tgn:1131803",
          "tgn:7005694",
          "tgn:7005685",
          "tgn:1000001",
          "tgn:7029392"
        ],
        "placetype": [
          "aat:300008707"
        ],
        "id": 1131803,
        "name:xx": "Wildhay"
      }
    },
    {
      "geometry": {
        "type": "Point",
        "coordinates": [
          25.451,
          -32.596
        ]
      },
      "type": "Feature",
      "properties": {
        "hierarchy": [
          "tgn:1131804",
          "tgn:7001242",
          "tgn:7017583",
          "tgn:1000193",
          "tgn:7029392"
        ],
        "placetype": [
          "aat:300008707"
        ],
        "id": 1131804,
        "name:xx": "Wilge"
      }
    },
    {
      "geometry": {
        "type": "Point",
        "coordinates": [
          -123.0167,
          44.0167
        ]
      },
      "type": "Feature",
      "properties": {
        "hierarchy": [
          "tgn:1131806",
          "tgn:1000001",
          "tgn:7012149",
          "tgn:7007708",
          "tgn:7029392"
        ],
        "placetype": [
          "aat:300008707"
        ],
        "id": 1131806,
        "name:xx": "Willamette"
      }
    },
    {
      "geometry": {
        "type": "Point",
        "coordinates": [
          -123.4,
          46.4833
        ]
      },
      "type": "Feature",
      "properties": {
        "hierarchy": [
          "tgn:1131809",
          "tgn:1000001",
          "tgn:7012149",
          "tgn:1002767",
          "tgn:7007920",
          "tgn:7029392"
        ],
        "placetype": [
          "aat:300008707"
        ],
        "id": 1131809,
        "name:xx": "Willapa"
      }
    }
  ]
}
