{
  "geometry": {
    "type": "Point",
    "coordinates": [
      -85.6833,
      30.2167
    ]
  },
  "type": "Feature",
  "properties": {
    "hierarchy": [
      "tgn:2355384",
      "tgn:2000258",
      "tgn:1000001",
      "tgn:7012149",
      "tgn:7007240",
      "tgn:7029392"
    ],
    "placetype": [
      "aat:300132316"
    ],
    "id": 2355384,
    "name:xx": "Goose Bayou"
  }
}
