{
  "geometry": {
    "type": "Point",
    "coordinates": [
      39.2667,
      49.9333
    ]
  },
  "type": "Feature",
  "properties": {
    "hierarchy": [
      "tgn:1055933",
      "tgn:1000004",
      "tgn:1003424",
      "tgn:7018214",
      "tgn:7002435",
      "tgn:7029392"
    ],
    "placetype": [
      "aat:300008347"
    ],
    "id": 1055933,
    "name:xx": "Krivonosovo"
  }
}
