{
  "geometry": {
    "type": "Point",
    "coordinates": [
      -78.6167,
      38.9667
    ]
  },
  "type": "Feature",
  "properties": {
    "hierarchy": [
      "tgn:2461327",
      "tgn:1000001",
      "tgn:7012149",
      "tgn:2002190",
      "tgn:7007919",
      "tgn:7029392"
    ],
    "placetype": [
      "aat:300008706"
    ],
    "id": 2461327,
    "name:xx": "Little Stony Creek"
  }
}
