{
  "geometry": {
    "type": "Point",
    "coordinates": [
      78.443,
      30.73
    ]
  },
  "type": "Feature",
  "properties": {
    "hierarchy": [
      "tgn:1077255",
      "tgn:1000004",
      "tgn:7000198",
      "tgn:7031786",
      "tgn:7029392"
    ],
    "placetype": [
      "aat:300008347"
    ],
    "name:en": "Uttarkāshi",
    "id": 1077255
  }
}
