{
  "geometry": {
    "type": "Point",
    "coordinates": [
      -146.7833,
      60.9667
    ]
  },
  "type": "Feature",
  "properties": {
    "hierarchy": [
      "tgn:2742054",
      "tgn:7006450",
      "tgn:1000001",
      "tgn:7012149",
      "tgn:2000086",
      "tgn:7029392"
    ],
    "placetype": [
      "aat:300132316"
    ],
    "id": 2742054,
    "name:xx": "Valdez Arm"
  }
}
