{
  "type": "FeatureCollection",
  "features": [
    {
      "geometry": {
        "type": "Point",
        "coordinates": [
          -103.25,
          27.5
        ]
      },
      "type": "Feature",
      "properties": {
        "hierarchy": [
          "tgn:7436280",
          "tgn:1001853",
          "tgn:1000001",
          "tgn:7005560",
          "tgn:7029392"
        ],
        "placetype": [
          "aat:300006191"
        ],
        "id": 7436280,
        "name:xx": "Tanque Soledad"
      }
    },
    {
      "geometry": {
        "type": "Point",
        "coordinates": [
          -112.933333,
          30.816667
        ]
      },
      "type": "Feature",
      "properties": {
        "hierarchy": [
          "tgn:7436281",
          "tgn:1000001",
          "tgn:1001960",
          "tgn:7005560",
          "tgn:7029392"
        ],
        "placetype": [
          "aat:300008795"
        ],
        "id": 7436281,
        "name:xx": "Soledad, Sierrita de la"
      }
    },
    {
      "geometry": {
        "type": "Point",
        "coordinates": [
          -104.6,
          26.566667
        ]
      },
      "type": "Feature",
      "properties": {
        "hierarchy": [
          "tgn:7436282",
          "tgn:7005581",
          "tgn:1000001",
          "tgn:7005560",
          "tgn:7029392"
        ],
        "placetype": [
          "aat:300008795"
        ],
        "id": 7436282,
        "name:xx": "Soledad, Sierra de la"
      }
    },
    {
      "geometry": {
        "type": "Point",
        "coordinates": [
          -116.766667,
          31.55
        ]
      },
      "type": "Feature",
      "properties": {
        "hierarchy": [
          "tgn:7436283",
          "tgn:1001835",
          "tgn:1000001",
          "tgn:7005560",
          "tgn:7029392"
        ],
        "placetype": [
          "aat:300011692"
        ],
        "id": 7436283,
        "name:xx": "Soledad, Rocas"
      }
    },
    {
      "geometry": {
        "type": "Point",
        "coordinates": [
          -100.65,
          25.933333
        ]
      },
      "type": "Feature",
      "properties": {
        "hierarchy": [
          "tgn:7436284",
          "tgn:1000001",
          "tgn:7005589",
          "tgn:7005560",
          "tgn:7029392"
        ],
        "placetype": [
          "aat:300266554",
          "aat:300008699"
        ],
        "id": 7436284,
        "name:xx": "Soledad, Río de"
      }
    },
    {
      "geometry": {
        "type": "Point",
        "coordinates": [
          -100.3,
          26.216667
        ]
      },
      "type": "Feature",
      "properties": {
        "hierarchy": [
          "tgn:7436285",
          "tgn:1000001",
          "tgn:7005589",
          "tgn:7005560",
          "tgn:7029392"
        ],
        "placetype": [
          "aat:300000241"
        ],
        "id": 7436285,
        "name:xx": "Rancho Soledad"
      }
    },
    {
      "geometry": {
        "type": "Point",
        "coordinates": [
          -106.55,
          26.016667
        ]
      },
      "type": "Feature",
      "properties": {
        "hierarchy": [
          "tgn:7436286",
          "tgn:7005583",
          "tgn:1000001",
          "tgn:7005560",
          "tgn:7029392"
        ],
        "placetype": [
          "aat:300000241"
        ],
        "id": 7436286,
        "name:xx": "Rancho Soledad"
      }
    },
    {
      "geometry": {
        "type": "Point",
        "coordinates": [
          -109.583333,
          23.583333
        ]
      },
      "type": "Feature",
      "properties": {
        "hierarchy": [
          "tgn:7436287",
          "tgn:1001836",
          "tgn:1000001",
          "tgn:7005560",
          "tgn:7029392"
        ],
        "placetype": [
          "aat:300386846"
        ],
        "id": 7436287,
        "name:xx": "Soledad, Punta"
      }
    },
    {
      "geometry": {
        "type": "Point",
        "coordinates": [
          -105.2,
          19.616667
        ]
      },
      "type": "Feature",
      "properties": {
        "hierarchy": [
          "tgn:7436288",
          "tgn:7005586",
          "tgn:1000001",
          "tgn:7005560",
          "tgn:7029392"
        ],
        "placetype": [
          "aat:300386846"
        ],
        "id": 7436288,
        "name:xx": "Soledad, Punta"
      }
    },
    {
      "geometry": {
        "type": "Point",
        "coordinates": [
          -107.15,
          26.5
        ]
      },
      "type": "Feature",
      "properties": {
        "hierarchy": [
          "tgn:7436289",
          "tgn:7005581",
          "tgn:1000001",
          "tgn:7005560",
          "tgn:7029392"
        ],
        "placetype": [
          "aat:300008795"
        ],
        "id": 7436289,
        "name:xx": "Soledad, Picacho"
      }
    }
  ]
}
