{
  "geometry": {
    "type": "Point",
    "coordinates": [
      -82.6333,
      33.0167
    ]
  },
  "type": "Feature",
  "properties": {
    "hierarchy": [
      "tgn:2373097",
      "tgn:1000001",
      "tgn:7012149",
      "tgn:2000441",
      "tgn:7007248",
      "tgn:7029392"
    ],
    "placetype": [
      "aat:300008347"
    ],
    "id": 2373097,
    "name:xx": "Halls Crossing"
  }
}
