{
  "geometry": {
    "type": "Point",
    "coordinates": [
      121.7545,
      24.727
    ]
  },
  "type": "Feature",
  "properties": {
    "hierarchy": [
      "tgn:7478849",
      "tgn:1000004",
      "tgn:7489179",
      "tgn:1000141",
      "tgn:7029392"
    ],
    "placetype": [
      "aat:300008347"
    ],
    "id": 7478849,
    "name:xx": "Sijiu'er"
  }
}
