{
  "geometry": {
    "type": "Point",
    "coordinates": [
      -93.2167,
      30.75
    ]
  },
  "type": "Feature",
  "properties": {
    "hierarchy": [
      "tgn:2780845",
      "tgn:1000001",
      "tgn:2000859",
      "tgn:7012149",
      "tgn:7007256",
      "tgn:7029392"
    ],
    "placetype": [
      "aat:300008699"
    ],
    "id": 2780845,
    "name:xx": "Woodard Branch"
  }
}
