{
  "geometry": {
    "type": "Point",
    "coordinates": [
      -76.5667,
      39.75
    ]
  },
  "type": "Feature",
  "properties": {
    "hierarchy": [
      "tgn:2444869",
      "tgn:1000001",
      "tgn:7012149",
      "tgn:1003047",
      "tgn:7007710",
      "tgn:7029392"
    ],
    "placetype": [
      "aat:300008706"
    ],
    "id": 2444869,
    "name:xx": "Leibs Creek"
  }
}
