{
  "geometry": {
    "type": "Point",
    "coordinates": [
      -5.3833,
      35.35
    ]
  },
  "type": "Feature",
  "properties": {
    "hierarchy": [
      "tgn:1091439",
      "tgn:7001242",
      "tgn:1000179",
      "tgn:7593695",
      "tgn:7029392"
    ],
    "placetype": [
      "aat:300008347"
    ],
    "id": 1091439,
    "name:xx": "Souk el Arba des Beni Hassan"
  }
}
