{
  "geometry": {
    "type": "Point",
    "coordinates": [
      -73.65,
      41.95
    ]
  },
  "type": "Feature",
  "properties": {
    "hierarchy": [
      "tgn:2371599",
      "tgn:1000001",
      "tgn:1002347",
      "tgn:7012149",
      "tgn:7007568",
      "tgn:7029392"
    ],
    "placetype": [
      "aat:300008680"
    ],
    "id": 2371599,
    "name:xx": "Halcyon Lake"
  }
}
