{
  "geometry": {
    "type": "Point",
    "coordinates": [
      -95.8833,
      37.55
    ]
  },
  "type": "Feature",
  "properties": {
    "hierarchy": [
      "tgn:2588227",
      "tgn:1000001",
      "tgn:7012149",
      "tgn:2000762",
      "tgn:7007254",
      "tgn:7029392"
    ],
    "placetype": [
      "aat:300008707"
    ],
    "id": 2588227,
    "name:xx": "Plum Branch Fall River"
  }
}
