{
  "type": "FeatureCollection",
  "features": [
    {
      "geometry": {
        "type": "Point",
        "coordinates": [
          20.683333,
          39.416667
        ]
      },
      "type": "Feature",
      "properties": {
        "hierarchy": [
          "tgn:7222190",
          "tgn:7002707",
          "tgn:7002705",
          "tgn:1000003",
          "tgn:1000074",
          "tgn:7029392"
        ],
        "placetype": [
          "aat:300008795"
        ],
        "id": 7222190,
        "name:xx": "Sisoúni"
      }
    },
    {
      "geometry": {
        "type": "Point",
        "coordinates": [
          25.516667,
          35.316667
        ]
      },
      "type": "Feature",
      "properties": {
        "hierarchy": [
          "tgn:7222191",
          "tgn:7002692",
          "tgn:7012056",
          "tgn:1000003",
          "tgn:1000074",
          "tgn:7029392"
        ],
        "placetype": [
          "aat:300132316"
        ],
        "id": 7222191,
        "name:xx": "Sisíou, Limín"
      }
    },
    {
      "geometry": {
        "type": "Point",
        "coordinates": [
          25.516667,
          35.3
        ]
      },
      "type": "Feature",
      "properties": {
        "hierarchy": [
          "tgn:7222192",
          "tgn:7002692",
          "tgn:7012056",
          "tgn:1000003",
          "tgn:1000074",
          "tgn:7029392"
        ],
        "placetype": [
          "aat:300008347"
        ],
        "id": 7222192,
        "name:xx": "Sísion"
      }
    },
    {
      "geometry": {
        "type": "Point",
        "coordinates": [
          24.9,
          35.3
        ]
      },
      "type": "Feature",
      "properties": {
        "hierarchy": [
          "tgn:7222193",
          "tgn:7002690",
          "tgn:7012056",
          "tgn:1000003",
          "tgn:1000074",
          "tgn:7029392"
        ],
        "placetype": [
          "aat:300008347"
        ],
        "id": 7222193,
        "name:xx": "Sísarkha"
      }
    },
    {
      "geometry": {
        "type": "Point",
        "coordinates": [
          21.5,
          40.433333
        ]
      },
      "type": "Feature",
      "properties": {
        "hierarchy": [
          "tgn:7222194",
          "tgn:7002724",
          "tgn:7002715",
          "tgn:1000003",
          "tgn:1000074",
          "tgn:7029392"
        ],
        "placetype": [
          "aat:300008347"
        ],
        "id": 7222194,
        "name:xx": "Sisánion"
      }
    },
    {
      "geometry": {
        "type": "Point",
        "coordinates": [
          23.416667,
          40.95
        ]
      },
      "type": "Feature",
      "properties": {
        "hierarchy": [
          "tgn:7222195",
          "tgn:7002725",
          "tgn:7002715",
          "tgn:1000003",
          "tgn:1000074",
          "tgn:7029392"
        ],
        "placetype": [
          "aat:300008347"
        ],
        "id": 7222195,
        "name:xx": "Sisamía"
      }
    },
    {
      "geometry": {
        "type": "Point",
        "coordinates": [
          24.883333,
          35.4
        ]
      },
      "type": "Feature",
      "properties": {
        "hierarchy": [
          "tgn:7222196",
          "tgn:7002691",
          "tgn:7012056",
          "tgn:1000003",
          "tgn:1000074",
          "tgn:7029392"
        ],
        "placetype": [
          "aat:300008347"
        ],
        "id": 7222196,
        "name:xx": "Sísai"
      }
    },
    {
      "geometry": {
        "type": "Point",
        "coordinates": [
          21.9,
          37.366667
        ]
      },
      "type": "Feature",
      "properties": {
        "hierarchy": [
          "tgn:7222197",
          "tgn:7011369",
          "tgn:7017076",
          "tgn:1000003",
          "tgn:1000074",
          "tgn:7029392"
        ],
        "placetype": [
          "aat:300008347"
        ],
        "id": 7222197,
        "name:xx": "Sírrizon"
      }
    },
    {
      "geometry": {
        "type": "Point",
        "coordinates": [
          24.95,
          37.433333
        ]
      },
      "type": "Feature",
      "properties": {
        "hierarchy": [
          "tgn:7222198",
          "tgn:7011270",
          "tgn:7002674",
          "tgn:1000003",
          "tgn:1000074",
          "tgn:7029392"
        ],
        "placetype": [
          "aat:300008678"
        ],
        "id": 7222198,
        "name:xx": "Sýrou, Liménas"
      }
    }
  ]
}
