{
  "type": "FeatureCollection",
  "features": [
    {
      "geometry": {
        "type": "Point",
        "coordinates": [
          -76.6,
          37.55
        ]
      },
      "type": "Feature",
      "properties": {
        "hierarchy": [
          "tgn:2111940",
          "tgn:1000001",
          "tgn:7012149",
          "tgn:1002411",
          "tgn:7007919",
          "tgn:7029392"
        ],
        "placetype": [
          "aat:300008347",
          "aat:300387210"
        ],
        "id": 2111940,
        "name:xx": "Glenns"
      }
    },
    {
      "geometry": {
        "type": "Point",
        "coordinates": [
          -76.4833,
          37.4
        ]
      },
      "type": "Feature",
      "properties": {
        "hierarchy": [
          "tgn:2111943",
          "tgn:1000001",
          "tgn:7012149",
          "tgn:1002411",
          "tgn:7007919",
          "tgn:7029392"
        ],
        "placetype": [
          "aat:300008347"
        ],
        "id": 2111943,
        "name:xx": "Glen Roy Estates"
      }
    },
    {
      "geometry": {
        "type": "Point",
        "coordinates": [
          -80.1333,
          37.2667
        ]
      },
      "type": "Feature",
      "properties": {
        "hierarchy": [
          "tgn:2111944",
          "tgn:1000001",
          "tgn:7012149",
          "tgn:7014344",
          "tgn:7007919",
          "tgn:7029392"
        ],
        "placetype": [
          "aat:300008347"
        ],
        "id": 2111944,
        "name:xx": "Glenvar"
      }
    },
    {
      "geometry": {
        "type": "Point",
        "coordinates": [
          -79.8167,
          37.75
        ]
      },
      "type": "Feature",
      "properties": {
        "hierarchy": [
          "tgn:2111945",
          "tgn:1000001",
          "tgn:2002146",
          "tgn:7012149",
          "tgn:7007919",
          "tgn:7029392"
        ],
        "placetype": [
          "aat:300008347"
        ],
        "id": 2111945,
        "name:xx": "Glen Wilton"
      }
    },
    {
      "geometry": {
        "type": "Point",
        "coordinates": [
          -77.3833,
          37.5667
        ]
      },
      "type": "Feature",
      "properties": {
        "hierarchy": [
          "tgn:2111947",
          "tgn:1000001",
          "tgn:7012149",
          "tgn:1002467",
          "tgn:7007919",
          "tgn:7029392"
        ],
        "placetype": [
          "aat:300008347"
        ],
        "id": 2111947,
        "name:xx": "Glenwood Farms"
      }
    }
  ]
}
