{
  "geometry": {
    "type": "Point",
    "coordinates": [
      -119.2667,
      39.2667
    ]
  },
  "type": "Feature",
  "properties": {
    "hierarchy": [
      "tgn:2239580",
      "tgn:1000001",
      "tgn:1002614",
      "tgn:7012149",
      "tgn:7007526",
      "tgn:7029392"
    ],
    "placetype": [
      "aat:300008347"
    ],
    "id": 2239580,
    "name:xx": "Churchill"
  }
}
