{
  "geometry": {
    "type": "Point",
    "coordinates": [
      -80.1667,
      39.1333
    ]
  },
  "type": "Feature",
  "properties": {
    "hierarchy": [
      "tgn:2265598",
      "tgn:2002253",
      "tgn:1000001",
      "tgn:7012149",
      "tgn:7013961",
      "tgn:7029392"
    ],
    "placetype": [
      "aat:300008699"
    ],
    "id": 2265598,
    "name:xx": "Cranes Fork"
  }
}
