{
  "geometry": {
    "type": "Point",
    "coordinates": [
      -0.1833,
      51.2667
    ]
  },
  "type": "Feature",
  "properties": {
    "hierarchy": [
      "tgn:5000922",
      "tgn:7002445",
      "tgn:1000003",
      "tgn:7008175",
      "tgn:7008591",
      "tgn:7029392"
    ],
    "placetype": [
      "aat:300008347"
    ],
    "id": 5000922,
    "name:xx": "Mugswell"
  }
}
