{
  "geometry": {
    "type": "Point",
    "coordinates": [
      138.8833,
      -34.6167
    ]
  },
  "type": "Feature",
  "properties": {
    "hierarchy": [
      "tgn:1097426",
      "tgn:7000490",
      "tgn:1000006",
      "tgn:7001831",
      "tgn:7029392"
    ],
    "placetype": [
      "aat:300008347"
    ],
    "id": 1097426,
    "name:xx": "Lyndoch"
  }
}
