{
  "geometry": {
    "type": "Point",
    "coordinates": [
      123.2333,
      10.7833
    ]
  },
  "type": "Feature",
  "properties": {
    "hierarchy": [
      "tgn:1106457",
      "tgn:1000004",
      "tgn:1001448",
      "tgn:1000135",
      "tgn:7029392"
    ],
    "placetype": [
      "aat:300008795"
    ],
    "id": 1106457,
    "name:xx": "Silay, Mount"
  }
}
