{
  "type": "FeatureCollection",
  "features": [
    {
      "geometry": {
        "type": "Point",
        "coordinates": [
          -97.3333,
          27.4333
        ]
      },
      "type": "Feature",
      "properties": {
        "hierarchy": [
          "tgn:2624210",
          "tgn:1000001",
          "tgn:7012149",
          "tgn:2002022",
          "tgn:7007826",
          "tgn:7029392"
        ],
        "placetype": [
          "aat:300008791"
        ],
        "id": 2624210,
        "name:xx": "Rock Island"
      }
    },
    {
      "geometry": {
        "type": "Point",
        "coordinates": [
          -112.3,
          41.45
        ]
      },
      "type": "Feature",
      "properties": {
        "hierarchy": [
          "tgn:2624211",
          "tgn:1000001",
          "tgn:2002102",
          "tgn:7012149",
          "tgn:7007827",
          "tgn:7029392"
        ],
        "placetype": [
          "aat:300008791"
        ],
        "id": 2624211,
        "name:xx": "Rock Island"
      }
    },
    {
      "geometry": {
        "type": "Point",
        "coordinates": [
          -73.3667,
          44.1333
        ]
      },
      "type": "Feature",
      "properties": {
        "hierarchy": [
          "tgn:2624212",
          "tgn:2002130",
          "tgn:1000001",
          "tgn:7012149",
          "tgn:7007828",
          "tgn:7029392"
        ],
        "placetype": [
          "aat:300008791"
        ],
        "id": 2624212,
        "name:xx": "Rock Island"
      }
    },
    {
      "geometry": {
        "type": "Point",
        "coordinates": [
          -73.15,
          44.7667
        ]
      },
      "type": "Feature",
      "properties": {
        "hierarchy": [
          "tgn:2624213",
          "tgn:1000001",
          "tgn:1002389",
          "tgn:7012149",
          "tgn:7007828",
          "tgn:7029392"
        ],
        "placetype": [
          "aat:300008791"
        ],
        "id": 2624213,
        "name:xx": "Rock Island"
      }
    },
    {
      "geometry": {
        "type": "Point",
        "coordinates": [
          -78.5333,
          37.75
        ]
      },
      "type": "Feature",
      "properties": {
        "hierarchy": [
          "tgn:2624214",
          "tgn:2002137",
          "tgn:1000001",
          "tgn:7012149",
          "tgn:7007919",
          "tgn:7029392"
        ],
        "placetype": [
          "aat:300008791"
        ],
        "id": 2624214,
        "name:xx": "Rock Island"
      }
    },
    {
      "geometry": {
        "type": "Point",
        "coordinates": [
          -120.0833,
          47.3333
        ]
      },
      "type": "Feature",
      "properties": {
        "hierarchy": [
          "tgn:2624215",
          "tgn:1000001",
          "tgn:2002242",
          "tgn:7012149",
          "tgn:7007920",
          "tgn:7029392"
        ],
        "placetype": [
          "aat:300008791"
        ],
        "id": 2624215,
        "name:xx": "Rock Island"
      }
    },
    {
      "geometry": {
        "type": "Point",
        "coordinates": [
          -119.6167,
          45.9
        ]
      },
      "type": "Feature",
      "properties": {
        "hierarchy": [
          "tgn:2624216",
          "tgn:2002240",
          "tgn:1000001",
          "tgn:7012149",
          "tgn:7007920",
          "tgn:7029392"
        ],
        "placetype": [
          "aat:300008791"
        ],
        "id": 2624216,
        "name:xx": "Rock Island"
      }
    },
    {
      "geometry": {
        "type": "Point",
        "coordinates": [
          -122.6333,
          47.85
        ]
      },
      "type": "Feature",
      "properties": {
        "hierarchy": [
          "tgn:2624217",
          "tgn:1000001",
          "tgn:7012149",
          "tgn:1002521",
          "tgn:7007920",
          "tgn:7029392"
        ],
        "placetype": [
          "aat:300132348"
        ],
        "id": 2624217,
        "name:xx": "Rock Island"
      }
    },
    {
      "geometry": {
        "type": "Point",
        "coordinates": [
          -89.75,
          45.2
        ]
      },
      "type": "Feature",
      "properties": {
        "hierarchy": [
          "tgn:2624218",
          "tgn:1000001",
          "tgn:7012149",
          "tgn:2002334",
          "tgn:7007922",
          "tgn:7029392"
        ],
        "placetype": [
          "aat:300008791"
        ],
        "id": 2624218,
        "name:xx": "Rock Island"
      }
    },
    {
      "geometry": {
        "type": "Point",
        "coordinates": [
          -92.6667,
          45.3667
        ]
      },
      "type": "Feature",
      "properties": {
        "hierarchy": [
          "tgn:2624219",
          "tgn:1000001",
          "tgn:7012149",
          "tgn:2002346",
          "tgn:7007922",
          "tgn:7029392"
        ],
        "placetype": [
          "aat:300008791"
        ],
        "id": 2624219,
        "name:xx": "Rock Island"
      }
    }
  ]
}
