{
  "geometry": {
    "type": "Point",
    "coordinates": [
      67.25,
      34.75
    ]
  },
  "type": "Feature",
  "properties": {
    "hierarchy": [
      "tgn:1001122",
      "tgn:7016612",
      "tgn:1000004",
      "tgn:7029392"
    ],
    "placetype": [
      "aat:300387064",
      "aat:300000774"
    ],
    "id": 1001122,
    "name:xx": "Bāmīān"
  }
}
