{
  "geometry": {
    "type": "Point",
    "coordinates": [
      -83.3167,
      42.75
    ]
  },
  "type": "Feature",
  "properties": {
    "hierarchy": [
      "tgn:2471424",
      "tgn:1000001",
      "tgn:7012149",
      "tgn:1002737",
      "tgn:7007520",
      "tgn:7029392"
    ],
    "placetype": [
      "aat:300008905"
    ],
    "id": 2471424,
    "name:xx": "Lost Lake"
  }
}
