{
  "type": "FeatureCollection",
  "features": [
    {
      "geometry": {
        "type": "Point",
        "coordinates": [
          -83.4667,
          31.2333
        ]
      },
      "type": "Feature",
      "properties": {
        "hierarchy": [
          "tgn:2290400",
          "tgn:1000001",
          "tgn:2000328",
          "tgn:7012149",
          "tgn:7007248",
          "tgn:7029392"
        ],
        "placetype": [
          "aat:300008699"
        ],
        "id": 2290400,
        "name:xx": "Doe Branch"
      }
    },
    {
      "geometry": {
        "type": "Point",
        "coordinates": [
          -83.6333,
          37.7667
        ]
      },
      "type": "Feature",
      "properties": {
        "hierarchy": [
          "tgn:2290401",
          "tgn:1000001",
          "tgn:7012149",
          "tgn:2000853",
          "tgn:7007255",
          "tgn:7029392"
        ],
        "placetype": [
          "aat:300008699"
        ],
        "id": 2290401,
        "name:xx": "Doe Branch"
      }
    },
    {
      "geometry": {
        "type": "Point",
        "coordinates": [
          -83.2667,
          37.8
        ]
      },
      "type": "Feature",
      "properties": {
        "hierarchy": [
          "tgn:2290402",
          "tgn:1000001",
          "tgn:7012149",
          "tgn:2000831",
          "tgn:7007255",
          "tgn:7029392"
        ],
        "placetype": [
          "aat:300008699"
        ],
        "id": 2290402,
        "name:xx": "Doe Branch"
      }
    },
    {
      "geometry": {
        "type": "Point",
        "coordinates": [
          -83.4,
          38.3167
        ]
      },
      "type": "Feature",
      "properties": {
        "hierarchy": [
          "tgn:2290403",
          "tgn:1000001",
          "tgn:7012149",
          "tgn:1002837",
          "tgn:7007255",
          "tgn:7029392"
        ],
        "placetype": [
          "aat:300008699"
        ],
        "id": 2290403,
        "name:xx": "Doe Branch"
      }
    },
    {
      "geometry": {
        "type": "Point",
        "coordinates": [
          -92.9667,
          32.9333
        ]
      },
      "type": "Feature",
      "properties": {
        "hierarchy": [
          "tgn:2290404",
          "tgn:1000001",
          "tgn:2000867",
          "tgn:7012149",
          "tgn:7007256",
          "tgn:7029392"
        ],
        "placetype": [
          "aat:300008699"
        ],
        "id": 2290404,
        "name:xx": "Doe Branch"
      }
    },
    {
      "geometry": {
        "type": "Point",
        "coordinates": [
          -90.5667,
          30.5
        ]
      },
      "type": "Feature",
      "properties": {
        "hierarchy": [
          "tgn:2290405",
          "tgn:1000001",
          "tgn:7012149",
          "tgn:7007256",
          "tgn:7029392"
        ],
        "placetype": [
          "aat:300008699"
        ],
        "id": 2290405,
        "name:xx": "Doe Branch"
      }
    },
    {
      "geometry": {
        "type": "Point",
        "coordinates": [
          -83,
          35.1833
        ]
      },
      "type": "Feature",
      "properties": {
        "hierarchy": [
          "tgn:2290406",
          "tgn:1000001",
          "tgn:7012149",
          "tgn:2001508",
          "tgn:7007709",
          "tgn:7029392"
        ],
        "placetype": [
          "aat:300008699"
        ],
        "id": 2290406,
        "name:xx": "Doe Branch"
      }
    },
    {
      "geometry": {
        "type": "Point",
        "coordinates": [
          -82.8,
          35.8333
        ]
      },
      "type": "Feature",
      "properties": {
        "hierarchy": [
          "tgn:2290407",
          "tgn:1000001",
          "tgn:7012149",
          "tgn:2001516",
          "tgn:7007709",
          "tgn:7029392"
        ],
        "placetype": [
          "aat:300008699"
        ],
        "id": 2290407,
        "name:xx": "Doe Branch"
      }
    },
    {
      "geometry": {
        "type": "Point",
        "coordinates": [
          -81.7,
          36.35
        ]
      },
      "type": "Feature",
      "properties": {
        "hierarchy": [
          "tgn:2290408",
          "tgn:1000001",
          "tgn:7012149",
          "tgn:2001551",
          "tgn:7007709",
          "tgn:7029392"
        ],
        "placetype": [
          "aat:300008699"
        ],
        "id": 2290408,
        "name:xx": "Doe Branch"
      }
    },
    {
      "geometry": {
        "type": "Point",
        "coordinates": [
          -82.9333,
          35.8667
        ]
      },
      "type": "Feature",
      "properties": {
        "hierarchy": [
          "tgn:2290409",
          "tgn:1000001",
          "tgn:7012149",
          "tgn:2001851",
          "tgn:7007825",
          "tgn:7029392"
        ],
        "placetype": [
          "aat:300008699"
        ],
        "id": 2290409,
        "name:xx": "Doe Branch"
      }
    }
  ]
}
