{
  "type": "FeatureCollection",
  "features": [
    {
      "geometry": {
        "type": "Point",
        "coordinates": [
          -107.116667,
          28.733333
        ]
      },
      "type": "Feature",
      "properties": {
        "hierarchy": [
          "tgn:7430850",
          "tgn:7005581",
          "tgn:1000001",
          "tgn:7005560",
          "tgn:7029392"
        ],
        "placetype": [
          "aat:300008347"
        ],
        "id": 7430850,
        "name:xx": "Campo 113"
      }
    },
    {
      "geometry": {
        "type": "Point",
        "coordinates": [
          -107.166667,
          28.8
        ]
      },
      "type": "Feature",
      "properties": {
        "hierarchy": [
          "tgn:7430851",
          "tgn:7005581",
          "tgn:1000001",
          "tgn:7005560",
          "tgn:7029392"
        ],
        "placetype": [
          "aat:300008347"
        ],
        "id": 7430851,
        "name:xx": "Campo 112"
      }
    },
    {
      "geometry": {
        "type": "Point",
        "coordinates": [
          -107.083333,
          28.716667
        ]
      },
      "type": "Feature",
      "properties": {
        "hierarchy": [
          "tgn:7430852",
          "tgn:7005581",
          "tgn:1000001",
          "tgn:7005560",
          "tgn:7029392"
        ],
        "placetype": [
          "aat:300008347"
        ],
        "id": 7430852,
        "name:xx": "Campo 111"
      }
    },
    {
      "geometry": {
        "type": "Point",
        "coordinates": [
          -107.083333,
          28.8
        ]
      },
      "type": "Feature",
      "properties": {
        "hierarchy": [
          "tgn:7430853",
          "tgn:7005581",
          "tgn:1000001",
          "tgn:7005560",
          "tgn:7029392"
        ],
        "placetype": [
          "aat:300008347"
        ],
        "id": 7430853,
        "name:xx": "Campo 109"
      }
    },
    {
      "geometry": {
        "type": "Point",
        "coordinates": [
          -107.05,
          28.783333
        ]
      },
      "type": "Feature",
      "properties": {
        "hierarchy": [
          "tgn:7430854",
          "tgn:7005581",
          "tgn:1000001",
          "tgn:7005560",
          "tgn:7029392"
        ],
        "placetype": [
          "aat:300008347"
        ],
        "id": 7430854,
        "name:xx": "Campo 106"
      }
    },
    {
      "geometry": {
        "type": "Point",
        "coordinates": [
          -106.75,
          28.416667
        ]
      },
      "type": "Feature",
      "properties": {
        "hierarchy": [
          "tgn:7430856",
          "tgn:7005581",
          "tgn:1000001",
          "tgn:7005560",
          "tgn:7029392"
        ],
        "placetype": [
          "aat:300008347"
        ],
        "id": 7430856,
        "name:xx": "Campo 4"
      }
    },
    {
      "geometry": {
        "type": "Point",
        "coordinates": [
          -108.433333,
          25.916667
        ]
      },
      "type": "Feature",
      "properties": {
        "hierarchy": [
          "tgn:7430857",
          "tgn:1000001",
          "tgn:7005595",
          "tgn:7005560",
          "tgn:7029392"
        ],
        "placetype": [
          "aat:300008347"
        ],
        "id": 7430857,
        "name:xx": "Tepan"
      }
    },
    {
      "geometry": {
        "type": "Point",
        "coordinates": [
          -108.533333,
          25.966667
        ]
      },
      "type": "Feature",
      "properties": {
        "hierarchy": [
          "tgn:7430858",
          "tgn:1000001",
          "tgn:7005595",
          "tgn:7005560",
          "tgn:7029392"
        ],
        "placetype": [
          "aat:300008347"
        ],
        "id": 7430858,
        "name:xx": "El Coche"
      }
    },
    {
      "geometry": {
        "type": "Point",
        "coordinates": [
          -108.466667,
          25.933333
        ]
      },
      "type": "Feature",
      "properties": {
        "hierarchy": [
          "tgn:7430859",
          "tgn:1000001",
          "tgn:7005595",
          "tgn:7005560",
          "tgn:7029392"
        ],
        "placetype": [
          "aat:300008347"
        ],
        "id": 7430859,
        "name:xx": "Tepehuaje"
      }
    }
  ]
}
