{
  "geometry": {
    "type": "Point",
    "coordinates": [
      -61.7333,
      12.1333
    ]
  },
  "type": "Feature",
  "properties": {
    "hierarchy": [
      "tgn:1016584",
      "tgn:7017254",
      "tgn:1000001",
      "tgn:7004771",
      "tgn:7029392"
    ],
    "placetype": [
      "aat:300008347"
    ],
    "id": 1016584,
    "name:xx": "Grand Bay"
  }
}
