{
  "geometry": {
    "type": "Point",
    "coordinates": [
      -114.5667,
      35.2333
    ]
  },
  "type": "Feature",
  "properties": {
    "hierarchy": [
      "tgn:2157161",
      "tgn:1000001",
      "tgn:7006451",
      "tgn:7012149",
      "tgn:2000098",
      "tgn:7029392"
    ],
    "placetype": [
      "aat:300132316"
    ],
    "id": 2157161,
    "name:xx": "Beaver Cove"
  }
}
