{
  "geometry": {
    "type": "Point",
    "coordinates": [
      -107.6833,
      35.3667
    ]
  },
  "type": "Feature",
  "properties": {
    "hierarchy": [
      "tgn:2605137",
      "tgn:1000001",
      "tgn:7012149",
      "tgn:7007566",
      "tgn:7029392"
    ],
    "placetype": [
      "aat:300008761"
    ],
    "id": 2605137,
    "name:xx": "Rafael Canyon"
  }
}
