{
  "geometry": {
    "type": "Point",
    "coordinates": [
      30.563057,
      28.504375
    ]
  },
  "type": "Feature",
  "properties": {
    "hierarchy": [
      "tgn:7543900",
      "tgn:7001242",
      "tgn:7016833",
      "tgn:1001088",
      "tgn:7029392"
    ],
    "placetype": [
      "aat:300008777"
    ],
    "name:en": "Sawdā', Tilāl",
    "id": 7543900
  }
}
