{
  "geometry": {
    "type": "Point",
    "coordinates": [
      27.570783,
      31.185796
    ]
  },
  "type": "Feature",
  "properties": {
    "hierarchy": [
      "tgn:7527495",
      "tgn:7001242",
      "tgn:7016833",
      "tgn:1001418",
      "tgn:7029392"
    ],
    "placetype": [
      "aat:300005926"
    ],
    "name:en": "S카d카 Ab큰 an N큰r",
    "id": 7527495
  }
}
