{
  "type": "FeatureCollection",
  "features": [
    {
      "geometry": {
        "type": "Point",
        "coordinates": [
          -1.55,
          54.966667
        ]
      },
      "type": "Feature",
      "properties": {
        "hierarchy": [
          "tgn:7447823",
          "tgn:7019073",
          "tgn:7002445",
          "tgn:1000003",
          "tgn:7012033",
          "tgn:7008591",
          "tgn:7029392"
        ],
        "placetype": [
          "aat:300386846"
        ],
        "name:en": "Saint Anthony's Point",
        "id": 7447823
      }
    },
    {
      "geometry": {
        "type": "Point",
        "coordinates": [
          -5,
          50.133333
        ]
      },
      "type": "Feature",
      "properties": {
        "hierarchy": [
          "tgn:7447824",
          "tgn:7002445",
          "tgn:7008116",
          "tgn:1000003",
          "tgn:7008591",
          "tgn:7029392"
        ],
        "placetype": [
          "aat:300008850"
        ],
        "name:en": "Saint Anthony Head",
        "id": 7447824
      }
    },
    {
      "geometry": {
        "type": "Point",
        "coordinates": [
          -5.1,
          50.083333
        ]
      },
      "type": "Feature",
      "properties": {
        "hierarchy": [
          "tgn:7447825",
          "tgn:7002445",
          "tgn:7008116",
          "tgn:1000003",
          "tgn:7008591",
          "tgn:7029392"
        ],
        "placetype": [
          "aat:300008347"
        ],
        "name:en": "Saint Anthony",
        "id": 7447825
      }
    },
    {
      "geometry": {
        "type": "Point",
        "coordinates": [
          -3.237778,
          51.434167
        ]
      },
      "type": "Feature",
      "properties": {
        "hierarchy": [
          "tgn:7447828",
          "tgn:7002443",
          "tgn:1000003",
          "tgn:7018966",
          "tgn:7008591",
          "tgn:7029392"
        ],
        "placetype": [
          "aat:300008347"
        ],
        "name:en": "Saint Andrews Major",
        "id": 7447828
      }
    }
  ]
}
