{
  "type": "FeatureCollection",
  "features": [
    {
      "geometry": {
        "type": "Point",
        "coordinates": [
          -82.9833,
          36.75
        ]
      },
      "type": "Feature",
      "properties": {
        "hierarchy": [
          "tgn:2168590",
          "tgn:1000001",
          "tgn:7012149",
          "tgn:2002169",
          "tgn:7007919",
          "tgn:7029392"
        ],
        "placetype": [
          "aat:300008798"
        ],
        "id": 2168590,
        "name:xx": "Big Hill"
      }
    },
    {
      "geometry": {
        "type": "Point",
        "coordinates": [
          -79.8167,
          37.7167
        ]
      },
      "type": "Feature",
      "properties": {
        "hierarchy": [
          "tgn:2168591",
          "tgn:1000001",
          "tgn:2002146",
          "tgn:7012149",
          "tgn:7007919",
          "tgn:7029392"
        ],
        "placetype": [
          "aat:300008798"
        ],
        "id": 2168591,
        "name:xx": "Big Hill"
      }
    },
    {
      "geometry": {
        "type": "Point",
        "coordinates": [
          -79.4,
          37.8667
        ]
      },
      "type": "Feature",
      "properties": {
        "hierarchy": [
          "tgn:2168592",
          "tgn:1000001",
          "tgn:7012149",
          "tgn:2002186",
          "tgn:7007919",
          "tgn:7029392"
        ],
        "placetype": [
          "aat:300008798"
        ],
        "id": 2168592,
        "name:xx": "Big Hill"
      }
    },
    {
      "geometry": {
        "type": "Point",
        "coordinates": [
          -79.4833,
          38.3167
        ]
      },
      "type": "Feature",
      "properties": {
        "hierarchy": [
          "tgn:2168593",
          "tgn:1000001",
          "tgn:7012149",
          "tgn:2002168",
          "tgn:7007919",
          "tgn:7029392"
        ],
        "placetype": [
          "aat:300008798"
        ],
        "id": 2168593,
        "name:xx": "Big Hill"
      }
    },
    {
      "geometry": {
        "type": "Point",
        "coordinates": [
          -120.4833,
          48
        ]
      },
      "type": "Feature",
      "properties": {
        "hierarchy": [
          "tgn:2168594",
          "tgn:1000001",
          "tgn:1002260",
          "tgn:7012149",
          "tgn:7007920",
          "tgn:7029392"
        ],
        "placetype": [
          "aat:300008798"
        ],
        "id": 2168594,
        "name:xx": "Big Hill"
      }
    },
    {
      "geometry": {
        "type": "Point",
        "coordinates": [
          -80.0667,
          38.1333
        ]
      },
      "type": "Feature",
      "properties": {
        "hierarchy": [
          "tgn:2168595",
          "tgn:1000001",
          "tgn:7012149",
          "tgn:2002287",
          "tgn:7013961",
          "tgn:7029392"
        ],
        "placetype": [
          "aat:300008798"
        ],
        "id": 2168595,
        "name:xx": "Big Hill"
      }
    },
    {
      "geometry": {
        "type": "Point",
        "coordinates": [
          -105.4167,
          41.45
        ]
      },
      "type": "Feature",
      "properties": {
        "hierarchy": [
          "tgn:2168596",
          "tgn:2002365",
          "tgn:1000001",
          "tgn:7012149",
          "tgn:7007923",
          "tgn:7029392"
        ],
        "placetype": [
          "aat:300008798"
        ],
        "id": 2168596,
        "name:xx": "Big Hill"
      }
    },
    {
      "geometry": {
        "type": "Point",
        "coordinates": [
          -110.9333,
          42.0833
        ]
      },
      "type": "Feature",
      "properties": {
        "hierarchy": [
          "tgn:2168597",
          "tgn:1000001",
          "tgn:7012149",
          "tgn:2002376",
          "tgn:7007923",
          "tgn:7029392"
        ],
        "placetype": [
          "aat:300008798"
        ],
        "id": 2168597,
        "name:xx": "Big Hill"
      }
    },
    {
      "geometry": {
        "type": "Point",
        "coordinates": [
          -108,
          41.6333
        ]
      },
      "type": "Feature",
      "properties": {
        "hierarchy": [
          "tgn:2168598",
          "tgn:1000001",
          "tgn:7012149",
          "tgn:2002383",
          "tgn:7007923",
          "tgn:7029392"
        ],
        "placetype": [
          "aat:300008798"
        ],
        "id": 2168598,
        "name:xx": "Big Hill"
      }
    },
    {
      "geometry": {
        "type": "Point",
        "coordinates": [
          -88.2,
          38.1
        ]
      },
      "type": "Feature",
      "properties": {
        "hierarchy": [
          "tgn:2168599",
          "tgn:1000001",
          "tgn:7012149",
          "tgn:2000537",
          "tgn:7007251",
          "tgn:7029392"
        ],
        "placetype": [
          "aat:300008699"
        ],
        "id": 2168599,
        "name:xx": "Big Hill Branch"
      }
    }
  ]
}
