{
  "geometry": {
    "type": "Point",
    "coordinates": [
      -107.8833,
      39.95
    ]
  },
  "type": "Feature",
  "properties": {
    "hierarchy": [
      "tgn:7019352",
      "tgn:1000001",
      "tgn:7012149",
      "tgn:7007158",
      "tgn:2000243",
      "tgn:7029392"
    ],
    "placetype": [
      "aat:300008798"
    ],
    "id": 7019352,
    "name:xx": "LO 7 Hill"
  }
}
