{
  "geometry": {
    "type": "Point",
    "coordinates": [
      -87.9667,
      30.9667
    ]
  },
  "type": "Feature",
  "properties": {
    "hierarchy": [
      "tgn:2659813",
      "tgn:7002659",
      "tgn:1000001",
      "tgn:7012149",
      "tgn:2000048",
      "tgn:7029392"
    ],
    "placetype": [
      "aat:300006075"
    ],
    "id": 2659813,
    "name:xx": "Shipes Canal"
  }
}
