{
  "geometry": {
    "type": "Point",
    "coordinates": [
      -77.7833,
      40.8667
    ]
  },
  "type": "Feature",
  "properties": {
    "hierarchy": [
      "tgn:2328650",
      "tgn:1000001",
      "tgn:1002249",
      "tgn:7012149",
      "tgn:7007710",
      "tgn:7029392"
    ],
    "placetype": [
      "aat:300008347"
    ],
    "id": 2328650,
    "name:xx": "Fishermans Paradise"
  }
}
