{
  "geometry": {
    "type": "Point",
    "coordinates": [
      -94.8667,
      29.8833
    ]
  },
  "type": "Feature",
  "properties": {
    "hierarchy": [
      "tgn:2235086",
      "tgn:1000001",
      "tgn:7012149",
      "tgn:7007826",
      "tgn:7029392"
    ],
    "placetype": [
      "aat:300008761"
    ],
    "id": 2235086,
    "name:xx": "Cherry Point Gully"
  }
}
