{
  "geometry": {
    "type": "Point",
    "coordinates": [
      -94.2667,
      34.9833
    ]
  },
  "type": "Feature",
  "properties": {
    "hierarchy": [
      "tgn:2234504",
      "tgn:1000001",
      "tgn:7016172",
      "tgn:7012149",
      "tgn:2000170",
      "tgn:7029392"
    ],
    "placetype": [
      "aat:300008706"
    ],
    "id": 2234504,
    "name:xx": "Cherokee Creek"
  }
}
