{
  "geometry": {
    "type": "Point",
    "coordinates": [
      -121.2333,
      46.9667
    ]
  },
  "type": "Feature",
  "properties": {
    "hierarchy": [
      "tgn:2325920",
      "tgn:1000001",
      "tgn:7012149",
      "tgn:1003042",
      "tgn:7007920",
      "tgn:7029392"
    ],
    "placetype": [
      "aat:300266640"
    ],
    "id": 2325920,
    "name:xx": "Fifes Ridge"
  }
}
