{
  "geometry": {
    "type": "Point",
    "coordinates": [
      -112.6833,
      42.5833
    ]
  },
  "type": "Feature",
  "properties": {
    "hierarchy": [
      "tgn:2689266",
      "tgn:1000001",
      "tgn:7012149",
      "tgn:2000490",
      "tgn:7007250",
      "tgn:7029392"
    ],
    "placetype": [
      "aat:300008706"
    ],
    "id": 2689266,
    "name:xx": "Squaw Creek"
  }
}
