{
  "type": "FeatureCollection",
  "features": [
    {
      "geometry": {
        "type": "Point",
        "coordinates": [
          -7.2,
          42.566667
        ]
      },
      "type": "Feature",
      "properties": {
        "hierarchy": [
          "tgn:7325190",
          "tgn:7002829",
          "tgn:1000003",
          "tgn:7002786",
          "tgn:1000095",
          "tgn:7029392"
        ],
        "placetype": [
          "aat:300008347"
        ],
        "id": 7325190,
        "name:xx": "Santa Eufemia"
      }
    },
    {
      "geometry": {
        "type": "Point",
        "coordinates": [
          -6.033333,
          37.3
        ]
      },
      "type": "Feature",
      "properties": {
        "hierarchy": [
          "tgn:7325192",
          "tgn:7002758",
          "tgn:7002841",
          "tgn:1000003",
          "tgn:1000095",
          "tgn:7029392"
        ],
        "placetype": [
          "aat:300008347"
        ],
        "id": 7325192,
        "name:xx": "Santa Eufemia"
      }
    },
    {
      "geometry": {
        "type": "Point",
        "coordinates": [
          -2.766667,
          42.85
        ]
      },
      "type": "Feature",
      "properties": {
        "hierarchy": [
          "tgn:7325193",
          "tgn:7007088",
          "tgn:1000003",
          "tgn:7009604",
          "tgn:1000095",
          "tgn:7029392"
        ],
        "placetype": [
          "aat:300008699"
        ],
        "id": 7325193,
        "name:xx": "Santa Engracia, Río"
      }
    },
    {
      "geometry": {
        "type": "Point",
        "coordinates": [
          -0.783333,
          42.6
        ]
      },
      "type": "Feature",
      "properties": {
        "hierarchy": [
          "tgn:7325194",
          "tgn:7002759",
          "tgn:7008909",
          "tgn:1000003",
          "tgn:1000095",
          "tgn:7029392"
        ],
        "placetype": [
          "aat:300008347"
        ],
        "id": 7325194,
        "name:xx": "Santa Engracia"
      }
    },
    {
      "geometry": {
        "type": "Point",
        "coordinates": [
          -2.3,
          42.316667
        ]
      },
      "type": "Feature",
      "properties": {
        "hierarchy": [
          "tgn:7325195",
          "tgn:7002827",
          "tgn:1000003",
          "tgn:7002789",
          "tgn:1000095",
          "tgn:7029392"
        ],
        "placetype": [
          "aat:300008347"
        ],
        "id": 7325195,
        "name:xx": "Santa Engracia"
      }
    },
    {
      "geometry": {
        "type": "Point",
        "coordinates": [
          -0.644653,
          42.314605
        ]
      },
      "type": "Feature",
      "properties": {
        "hierarchy": [
          "tgn:7325196",
          "tgn:7002759",
          "tgn:7008909",
          "tgn:1000003",
          "tgn:1000095",
          "tgn:7029392"
        ],
        "placetype": [
          "aat:300008347"
        ],
        "id": 7325196,
        "name:xx": "Santa Engracia"
      }
    },
    {
      "geometry": {
        "type": "Point",
        "coordinates": [
          -6.966667,
          38.916667
        ]
      },
      "type": "Feature",
      "properties": {
        "hierarchy": [
          "tgn:7325197",
          "tgn:7002807",
          "tgn:1000003",
          "tgn:7003837",
          "tgn:1000095",
          "tgn:7029392"
        ],
        "placetype": [
          "aat:300008347"
        ],
        "id": 7325197,
        "name:xx": "Santa Engracia"
      }
    },
    {
      "geometry": {
        "type": "Point",
        "coordinates": [
          -4.85,
          37.566667
        ]
      },
      "type": "Feature",
      "properties": {
        "hierarchy": [
          "tgn:7325198",
          "tgn:7002758",
          "tgn:7002817",
          "tgn:1000003",
          "tgn:1000095",
          "tgn:7029392"
        ],
        "placetype": [
          "aat:300008347"
        ],
        "id": 7325198,
        "name:xx": "Santaella"
      }
    },
    {
      "geometry": {
        "type": "Point",
        "coordinates": [
          -5.883333,
          42.266667
        ]
      },
      "type": "Feature",
      "properties": {
        "hierarchy": [
          "tgn:7325199",
          "tgn:7002826",
          "tgn:7001158",
          "tgn:1000003",
          "tgn:1000095",
          "tgn:7029392"
        ],
        "placetype": [
          "aat:300008347"
        ],
        "id": 7325199,
        "name:xx": "Santa Elena de Jamuz"
      }
    }
  ]
}
