{
  "geometry": {
    "type": "Point",
    "coordinates": [
      -80.9167,
      40.1833
    ]
  },
  "type": "Feature",
  "properties": {
    "hierarchy": [
      "tgn:2571218",
      "tgn:1000001",
      "tgn:7012149",
      "tgn:7007706",
      "tgn:7029392"
    ],
    "placetype": [
      "aat:300008699"
    ],
    "id": 2571218,
    "name:xx": "Patton Run"
  }
}
