{
  "geometry": {
    "type": "Point",
    "coordinates": [
      44.5667,
      62.6333
    ]
  },
  "type": "Feature",
  "properties": {
    "hierarchy": [
      "tgn:1059243",
      "tgn:4000818",
      "tgn:1000004",
      "tgn:7018214",
      "tgn:7002435",
      "tgn:7029392"
    ],
    "placetype": [
      "aat:300008347"
    ],
    "id": 1059243,
    "name:xx": "Savino-Borisovskaya"
  }
}
