{
  "type": "FeatureCollection",
  "features": [
    {
      "geometry": {
        "type": "Point",
        "coordinates": [
          -93.4667,
          31.8
        ]
      },
      "type": "Feature",
      "properties": {
        "hierarchy": [
          "tgn:2640710",
          "tgn:1000001",
          "tgn:7012149",
          "tgn:7029392"
        ],
        "placetype": [
          "aat:300008699"
        ],
        "id": 2640710,
        "name:xx": "San Miguel, Bayou"
      }
    },
    {
      "geometry": {
        "type": "Point",
        "coordinates": [
          -106.85,
          35.9
        ]
      },
      "type": "Feature",
      "properties": {
        "hierarchy": [
          "tgn:2640711",
          "tgn:1000001",
          "tgn:7012149",
          "tgn:2001451",
          "tgn:7007566",
          "tgn:7029392"
        ],
        "placetype": [
          "aat:300008761"
        ],
        "id": 2640711,
        "name:xx": "San Miguelito Canyon"
      }
    },
    {
      "geometry": {
        "type": "Point",
        "coordinates": [
          -120.5,
          34.5667
        ]
      },
      "type": "Feature",
      "properties": {
        "hierarchy": [
          "tgn:2640712",
          "tgn:1000001",
          "tgn:7012149",
          "tgn:7007157",
          "tgn:1002867",
          "tgn:7029392"
        ],
        "placetype": [
          "aat:300008706"
        ],
        "id": 2640712,
        "name:xx": "San Miguelito Creek"
      }
    },
    {
      "geometry": {
        "type": "Point",
        "coordinates": [
          -118.9,
          34.0667
        ]
      },
      "type": "Feature",
      "properties": {
        "hierarchy": [
          "tgn:2640714",
          "tgn:1000001",
          "tgn:7012149",
          "tgn:7007157",
          "tgn:1002608",
          "tgn:7029392"
        ],
        "placetype": [
          "aat:300008761"
        ],
        "id": 2640714,
        "name:xx": "San Nicholas Canyon"
      }
    },
    {
      "geometry": {
        "type": "Point",
        "coordinates": [
          -106.5,
          32.5667
        ]
      },
      "type": "Feature",
      "properties": {
        "hierarchy": [
          "tgn:2640715",
          "tgn:1000001",
          "tgn:2001435",
          "tgn:7012149",
          "tgn:7007566",
          "tgn:7029392"
        ],
        "placetype": [
          "aat:300008697"
        ],
        "id": 2640715,
        "name:xx": "San Nicholas Spring"
      }
    },
    {
      "geometry": {
        "type": "Point",
        "coordinates": [
          -81.6167,
          30.2667
        ]
      },
      "type": "Feature",
      "properties": {
        "hierarchy": [
          "tgn:2640716",
          "tgn:1000001",
          "tgn:2000264",
          "tgn:7012149",
          "tgn:7007240",
          "tgn:7029392"
        ],
        "placetype": [
          "aat:300008347",
          "aat:300167671"
        ],
        "id": 2640716,
        "name:xx": "San Nicolas Palica"
      }
    },
    {
      "geometry": {
        "type": "Point",
        "coordinates": [
          -106.4333,
          32.5833
        ]
      },
      "type": "Feature",
      "properties": {
        "hierarchy": [
          "tgn:2640717",
          "tgn:1000001",
          "tgn:2001435",
          "tgn:7012149",
          "tgn:7007566",
          "tgn:7029392"
        ],
        "placetype": [
          "aat:300008697"
        ],
        "id": 2640717,
        "name:xx": "San Nicolas Spring"
      }
    },
    {
      "geometry": {
        "type": "Point",
        "coordinates": [
          -81.55,
          29.85
        ]
      },
      "type": "Feature",
      "properties": {
        "hierarchy": [
          "tgn:2640718",
          "tgn:1000001",
          "tgn:7012149",
          "tgn:2000283",
          "tgn:7007240",
          "tgn:7029392"
        ],
        "placetype": [
          "aat:300008347",
          "aat:300167671",
          "aat:300008486"
        ],
        "id": 2640718,
        "name:xx": "San Nicolas Tolentino"
      }
    },
    {
      "geometry": {
        "type": "Point",
        "coordinates": [
          -118.0333,
          34.1833
        ]
      },
      "type": "Feature",
      "properties": {
        "hierarchy": [
          "tgn:2640719",
          "tgn:1000001",
          "tgn:7012149",
          "tgn:7007157",
          "tgn:1002608",
          "tgn:7029392"
        ],
        "placetype": [
          "aat:300008761"
        ],
        "id": 2640719,
        "name:xx": "San Olene Canyon"
      }
    }
  ]
}
