{
  "geometry": {
    "type": "Point",
    "coordinates": [
      -76.3833,
      37.4167
    ]
  },
  "type": "Feature",
  "properties": {
    "hierarchy": [
      "tgn:2365083",
      "tgn:1000001",
      "tgn:7012149",
      "tgn:1002647",
      "tgn:7007919",
      "tgn:7029392"
    ],
    "placetype": [
      "aat:300132316"
    ],
    "id": 2365083,
    "name:xx": "Greenmansion Cove"
  }
}
