{
  "geometry": {
    "type": "Point",
    "coordinates": [
      113.7167,
      23.7167
    ]
  },
  "type": "Feature",
  "properties": {
    "hierarchy": [
      "tgn:1069757",
      "tgn:1000004",
      "tgn:7005232",
      "tgn:1000111",
      "tgn:7029392"
    ],
    "placetype": [
      "aat:300008347"
    ],
    "id": 1069757,
    "name:xx": "Liangkou"
  }
}
