{
  "geometry": {
    "type": "Point",
    "coordinates": [
      -104.0667,
      44.2667
    ]
  },
  "type": "Feature",
  "properties": {
    "hierarchy": [
      "tgn:2671245",
      "tgn:1000001",
      "tgn:2002370",
      "tgn:7012149",
      "tgn:7007923",
      "tgn:7029392"
    ],
    "placetype": [
      "aat:300008761"
    ],
    "id": 2671245,
    "name:xx": "Smith Draw"
  }
}
