{
  "type": "FeatureCollection",
  "features": [
    {
      "geometry": {
        "type": "Point",
        "coordinates": [
          -76.9667,
          39.55
        ]
      },
      "type": "Feature",
      "properties": {
        "hierarchy": [
          "tgn:2158230",
          "tgn:1002238",
          "tgn:1000001",
          "tgn:7012149",
          "tgn:7007516",
          "tgn:7029392"
        ],
        "placetype": [
          "aat:300008699"
        ],
        "id": 2158230,
        "name:xx": "Beaver Run"
      }
    },
    {
      "geometry": {
        "type": "Point",
        "coordinates": [
          -90.7,
          31.55
        ]
      },
      "type": "Feature",
      "properties": {
        "hierarchy": [
          "tgn:2158231",
          "tgn:1000001",
          "tgn:7012149",
          "tgn:2001104",
          "tgn:7007522",
          "tgn:7029392"
        ],
        "placetype": [
          "aat:300008699"
        ],
        "id": 2158231,
        "name:xx": "Beaver Run"
      }
    },
    {
      "geometry": {
        "type": "Point",
        "coordinates": [
          -90.0833,
          32.7167
        ]
      },
      "type": "Feature",
      "properties": {
        "hierarchy": [
          "tgn:2158232",
          "tgn:1000001",
          "tgn:7012149",
          "tgn:2001167",
          "tgn:7007522",
          "tgn:7029392"
        ],
        "placetype": [
          "aat:300008699"
        ],
        "id": 2158232,
        "name:xx": "Beaver Run"
      }
    },
    {
      "geometry": {
        "type": "Point",
        "coordinates": [
          -88.6167,
          31.5167
        ]
      },
      "type": "Feature",
      "properties": {
        "hierarchy": [
          "tgn:2158233",
          "tgn:1000001",
          "tgn:7012149",
          "tgn:2001162",
          "tgn:7007522",
          "tgn:7029392"
        ],
        "placetype": [
          "aat:300008699"
        ],
        "id": 2158233,
        "name:xx": "Beaver Run"
      }
    },
    {
      "geometry": {
        "type": "Point",
        "coordinates": [
          -74.6167,
          41.15
        ]
      },
      "type": "Feature",
      "properties": {
        "hierarchy": [
          "tgn:2158234",
          "tgn:1000001",
          "tgn:1002934",
          "tgn:7012149",
          "tgn:7007565",
          "tgn:7029392"
        ],
        "placetype": [
          "aat:300008347"
        ],
        "id": 2158234,
        "name:xx": "Beaver Run"
      }
    },
    {
      "geometry": {
        "type": "Point",
        "coordinates": [
          -74.5,
          39.6667
        ]
      },
      "type": "Feature",
      "properties": {
        "hierarchy": [
          "tgn:2158235",
          "tgn:1002215",
          "tgn:1000001",
          "tgn:7012149",
          "tgn:7007565",
          "tgn:7029392"
        ],
        "placetype": [
          "aat:300008699"
        ],
        "id": 2158235,
        "name:xx": "Beaver Run"
      }
    },
    {
      "geometry": {
        "type": "Point",
        "coordinates": [
          -82.9167,
          40.5667
        ]
      },
      "type": "Feature",
      "properties": {
        "hierarchy": [
          "tgn:2158236",
          "tgn:1000001",
          "tgn:7012149",
          "tgn:7007706",
          "tgn:7029392"
        ],
        "placetype": [
          "aat:300008699"
        ],
        "id": 2158236,
        "name:xx": "Beaver Run"
      }
    },
    {
      "geometry": {
        "type": "Point",
        "coordinates": [
          -81.0333,
          40.8167
        ]
      },
      "type": "Feature",
      "properties": {
        "hierarchy": [
          "tgn:2158237",
          "tgn:1000001",
          "tgn:1002295",
          "tgn:7012149",
          "tgn:7007706",
          "tgn:7029392"
        ],
        "placetype": [
          "aat:300008699"
        ],
        "id": 2158237,
        "name:xx": "Beaver Run"
      }
    },
    {
      "geometry": {
        "type": "Point",
        "coordinates": [
          -82.55,
          39.9833
        ]
      },
      "type": "Feature",
      "properties": {
        "hierarchy": [
          "tgn:2158238",
          "tgn:1000001",
          "tgn:7012149",
          "tgn:1002596",
          "tgn:7007706",
          "tgn:7029392"
        ],
        "placetype": [
          "aat:300008699"
        ],
        "id": 2158238,
        "name:xx": "Beaver Run"
      }
    },
    {
      "geometry": {
        "type": "Point",
        "coordinates": [
          -82.0833,
          40.4
        ]
      },
      "type": "Feature",
      "properties": {
        "hierarchy": [
          "tgn:2158239",
          "tgn:1000001",
          "tgn:1002304",
          "tgn:7012149",
          "tgn:7007706",
          "tgn:7029392"
        ],
        "placetype": [
          "aat:300008699"
        ],
        "id": 2158239,
        "name:xx": "Beaver Run"
      }
    }
  ]
}
