{
  "geometry": {
    "type": "Point",
    "coordinates": [
      -89.3167,
      39.8167
    ]
  },
  "type": "Feature",
  "properties": {
    "hierarchy": [
      "tgn:2366370",
      "tgn:1000001",
      "tgn:7012149",
      "tgn:1002866",
      "tgn:7007251",
      "tgn:7029392"
    ],
    "placetype": [
      "aat:300008706"
    ],
    "id": 2366370,
    "name:xx": "Griffith Creek"
  }
}
