{
  "geometry": {
    "type": "Point",
    "coordinates": [
      -101.2667,
      43.3333
    ]
  },
  "type": "Feature",
  "properties": {
    "hierarchy": [
      "tgn:2178461",
      "tgn:2001773",
      "tgn:1000001",
      "tgn:7012149",
      "tgn:7007713",
      "tgn:7029392"
    ],
    "placetype": [
      "aat:300008347"
    ],
    "id": 2178461,
    "name:xx": "Blackpipe"
  }
}
