{
  "type": "FeatureCollection",
  "features": [
    {
      "geometry": {
        "type": "Point",
        "coordinates": [
          -134.966,
          -23.099
        ]
      },
      "type": "Feature",
      "properties": {
        "hierarchy": [
          "tgn:7593230",
          "tgn:1010009",
          "tgn:1000216",
          "tgn:1000006",
          "tgn:7029392"
        ],
        "placetype": [
          "aat:300008791",
          "aat:300386852",
          "aat:300386992"
        ],
        "name:en": "Île Mangareva",
        "id": 7593230,
        "name:xx": "Mangareva"
      }
    },
    {
      "geometry": {
        "type": "Point",
        "coordinates": [
          -70.174,
          -38.786
        ]
      },
      "type": "Feature",
      "properties": {
        "hierarchy": [
          "tgn:7593232",
          "tgn:7006477",
          "tgn:1001450",
          "tgn:1000002",
          "tgn:7029392"
        ],
        "placetype": [
          "aat:300008347"
        ],
        "id": 7593232,
        "name:xx": "Portada Covunco"
      }
    },
    {
      "geometry": {
        "type": "Point",
        "coordinates": [
          11.023,
          50.915
        ]
      },
      "type": "Feature",
      "properties": {
        "hierarchy": [
          "tgn:7593233",
          "tgn:1000003",
          "tgn:7003689",
          "tgn:7000084",
          "tgn:7029392"
        ],
        "placetype": [
          "aat:300008347"
        ],
        "id": 7593233,
        "name:xx": "Waltersleben"
      }
    },
    {
      "geometry": {
        "type": "Point",
        "coordinates": [
          -3.547,
          42.371
        ]
      },
      "type": "Feature",
      "properties": {
        "hierarchy": [
          "tgn:7593237",
          "tgn:1000003",
          "tgn:1000095",
          "tgn:7029392"
        ],
        "placetype": [
          "aat:300008795"
        ],
        "id": 7593237,
        "name:xx": "Sierra de Atapuerca"
      }
    }
  ]
}
