{
  "geometry": {
    "type": "Point",
    "coordinates": [
      -81.35,
      36.35
    ]
  },
  "type": "Feature",
  "properties": {
    "hierarchy": [
      "tgn:2630058",
      "tgn:1000001",
      "tgn:7012149",
      "tgn:7007709",
      "tgn:7029392"
    ],
    "placetype": [
      "aat:300008706"
    ],
    "id": 2630058,
    "name:xx": "Roten Creek"
  }
}
