{
  "geometry": {
    "type": "Point",
    "coordinates": [
      -87.3167,
      40.3167
    ]
  },
  "type": "Feature",
  "properties": {
    "hierarchy": [
      "tgn:2329441",
      "tgn:1000001",
      "tgn:7012149",
      "tgn:1002983",
      "tgn:7007252",
      "tgn:7029392"
    ],
    "placetype": [
      "aat:300008347"
    ],
    "id": 2329441,
    "name:xx": "Five Points"
  }
}
