{
  "geometry": {
    "type": "Point",
    "coordinates": [
      26.85,
      37.116667
    ]
  },
  "type": "Feature",
  "properties": {
    "hierarchy": [
      "tgn:7230031",
      "tgn:7011330",
      "tgn:7002674",
      "tgn:1000003",
      "tgn:1000074",
      "tgn:7029392"
    ],
    "placetype": [
      "aat:300132316"
    ],
    "id": 7230031,
    "name:xx": "Lakkí, Limín"
  }
}
