{
  "geometry": {
    "type": "Point",
    "coordinates": [
      -79.2167,
      43.2167
    ]
  },
  "type": "Feature",
  "properties": {
    "hierarchy": [
      "tgn:7018804",
      "tgn:7005685",
      "tgn:1000001",
      "tgn:7013154",
      "tgn:7029392"
    ],
    "placetype": [
      "aat:300006075"
    ],
    "id": 7018804,
    "name:xx": "Welland Ship Canal"
  }
}
