{
  "geometry": {
    "type": "Point",
    "coordinates": [
      -116.5167,
      45.6333
    ]
  },
  "type": "Feature",
  "properties": {
    "hierarchy": [
      "tgn:2277097",
      "tgn:1000001",
      "tgn:7012149",
      "tgn:2001722",
      "tgn:7007708",
      "tgn:7029392"
    ],
    "placetype": [
      "aat:300008706"
    ],
    "id": 2277097,
    "name:xx": "Davis Creek"
  }
}
