{
  "geometry": {
    "type": "Point",
    "coordinates": [
      -84.9833,
      35.95
    ]
  },
  "type": "Feature",
  "properties": {
    "hierarchy": [
      "tgn:2390390",
      "tgn:1000001",
      "tgn:7012149",
      "tgn:2001854",
      "tgn:7007825",
      "tgn:7029392"
    ],
    "placetype": [
      "aat:300008347"
    ],
    "id": 2390390,
    "name:xx": "Highland Homesite Addition"
  }
}
