{
  "geometry": {
    "type": "Point",
    "coordinates": [
      -76.0333,
      36.25
    ]
  },
  "type": "Feature",
  "properties": {
    "hierarchy": [
      "tgn:2578510",
      "tgn:1000001",
      "tgn:1002228",
      "tgn:7012149",
      "tgn:7007709",
      "tgn:7029392"
    ],
    "placetype": [
      "aat:300008347"
    ],
    "id": 2578510,
    "name:xx": "Philadelphia"
  }
}
