{
  "geometry": {
    "type": "Point",
    "coordinates": [
      -76.9333,
      34.8333
    ]
  },
  "type": "Feature",
  "properties": {
    "hierarchy": [
      "tgn:2550441",
      "tgn:1000001",
      "tgn:2001477",
      "tgn:7012149",
      "tgn:7007709",
      "tgn:7029392"
    ],
    "placetype": [
      "aat:300008707"
    ],
    "id": 2550441,
    "name:xx": "Northwest Prong Newport River"
  }
}
