{
  "geometry": {
    "type": "Point",
    "coordinates": [
      -87.75,
      42.7833
    ]
  },
  "type": "Feature",
  "properties": {
    "hierarchy": [
      "tgn:2122719",
      "tgn:1000001",
      "tgn:7012149",
      "tgn:1002815",
      "tgn:7007922",
      "tgn:7029392"
    ],
    "placetype": [
      "aat:300008347"
    ],
    "id": 2122719,
    "name:xx": "Wind Point"
  }
}
