{
  "geometry": {
    "type": "Point",
    "coordinates": [
      28.0167,
      -32.9333
    ]
  },
  "type": "Feature",
  "properties": {
    "hierarchy": [
      "tgn:1093104",
      "tgn:7001242",
      "tgn:7017583",
      "tgn:1000193",
      "tgn:7029392"
    ],
    "placetype": [
      "aat:300008347"
    ],
    "id": 1093104,
    "name:xx": "Gonubie Mouth"
  }
}
