{
  "geometry": {
    "type": "Point",
    "coordinates": [
      -99.95,
      32.9167
    ]
  },
  "type": "Feature",
  "properties": {
    "hierarchy": [
      "tgn:2108136",
      "tgn:1000001",
      "tgn:7012149",
      "tgn:2002014",
      "tgn:7007826",
      "tgn:7029392"
    ],
    "placetype": [
      "aat:300008347",
      "aat:300387210"
    ],
    "id": 2108136,
    "name:xx": "Tuxedo"
  }
}
