{
  "geometry": {
    "type": "Point",
    "coordinates": [
      -77.0167,
      35.6667
    ]
  },
  "type": "Feature",
  "properties": {
    "hierarchy": [
      "tgn:2513909",
      "tgn:1000001",
      "tgn:7012149",
      "tgn:7007709",
      "tgn:7029392"
    ],
    "placetype": [
      "aat:300008699"
    ],
    "id": 2513909,
    "name:xx": "Mill Swamp"
  }
}
