{
  "geometry": {
    "type": "Point",
    "coordinates": [
      -118.95,
      34.6667
    ]
  },
  "type": "Feature",
  "properties": {
    "hierarchy": [
      "tgn:2127754",
      "tgn:1000001",
      "tgn:7012149",
      "tgn:7007157",
      "tgn:1002972",
      "tgn:7029392"
    ],
    "placetype": [
      "aat:300008798"
    ],
    "id": 2127754,
    "name:xx": "Alamo Mountain"
  }
}
