{
  "geometry": {
    "type": "Point",
    "coordinates": [
      -107.45,
      33.0833
    ]
  },
  "type": "Feature",
  "properties": {
    "hierarchy": [
      "tgn:2711026",
      "tgn:1000001",
      "tgn:7012149",
      "tgn:2001455",
      "tgn:7007566",
      "tgn:7029392"
    ],
    "placetype": [
      "aat:300006191"
    ],
    "id": 2711026,
    "name:xx": "Tank Sixteen"
  }
}
