{
  "type": "FeatureCollection",
  "features": [
    {
      "geometry": {
        "type": "Point",
        "coordinates": [
          -113.7667,
          43.6
        ]
      },
      "type": "Feature",
      "properties": {
        "hierarchy": [
          "tgn:2134680",
          "tgn:1000001",
          "tgn:7012149",
          "tgn:7007250",
          "tgn:7029392"
        ],
        "placetype": [
          "aat:300008706"
        ],
        "id": 2134680,
        "name:xx": "Antelope Creek"
      }
    },
    {
      "geometry": {
        "type": "Point",
        "coordinates": [
          -116.15,
          44.4
        ]
      },
      "type": "Feature",
      "properties": {
        "hierarchy": [
          "tgn:2134681",
          "tgn:1000001",
          "tgn:7012149",
          "tgn:2000474",
          "tgn:7007250",
          "tgn:7029392"
        ],
        "placetype": [
          "aat:300008706"
        ],
        "id": 2134681,
        "name:xx": "Antelope Creek"
      }
    },
    {
      "geometry": {
        "type": "Point",
        "coordinates": [
          -97.3167,
          37.3
        ]
      },
      "type": "Feature",
      "properties": {
        "hierarchy": [
          "tgn:2134682",
          "tgn:1000001",
          "tgn:7012149",
          "tgn:2000755",
          "tgn:7007254",
          "tgn:7029392"
        ],
        "placetype": [
          "aat:300008706"
        ],
        "id": 2134682,
        "name:xx": "Antelope Creek"
      }
    },
    {
      "geometry": {
        "type": "Point",
        "coordinates": [
          -97.1667,
          37.35
        ]
      },
      "type": "Feature",
      "properties": {
        "hierarchy": [
          "tgn:2134683",
          "tgn:1000001",
          "tgn:7012149",
          "tgn:7007254",
          "tgn:7029392"
        ],
        "placetype": [
          "aat:300008706"
        ],
        "id": 2134683,
        "name:xx": "Antelope Creek"
      }
    },
    {
      "geometry": {
        "type": "Point",
        "coordinates": [
          -98.5,
          37.3
        ]
      },
      "type": "Feature",
      "properties": {
        "hierarchy": [
          "tgn:2134684",
          "tgn:2000663",
          "tgn:1000001",
          "tgn:7012149",
          "tgn:7007254",
          "tgn:7029392"
        ],
        "placetype": [
          "aat:300008706"
        ],
        "id": 2134684,
        "name:xx": "Antelope Creek"
      }
    },
    {
      "geometry": {
        "type": "Point",
        "coordinates": [
          -99.9667,
          37.2333
        ]
      },
      "type": "Feature",
      "properties": {
        "hierarchy": [
          "tgn:2134685",
          "tgn:1000001",
          "tgn:2000672",
          "tgn:7012149",
          "tgn:7007254",
          "tgn:7029392"
        ],
        "placetype": [
          "aat:300008706"
        ],
        "id": 2134685,
        "name:xx": "Antelope Creek"
      }
    },
    {
      "geometry": {
        "type": "Point",
        "coordinates": [
          -98.3,
          39.9667
        ]
      },
      "type": "Feature",
      "properties": {
        "hierarchy": [
          "tgn:2134686",
          "tgn:1000001",
          "tgn:2000704",
          "tgn:7012149",
          "tgn:7007254",
          "tgn:7029392"
        ],
        "placetype": [
          "aat:300008706"
        ],
        "id": 2134686,
        "name:xx": "Antelope Creek"
      }
    },
    {
      "geometry": {
        "type": "Point",
        "coordinates": [
          -98.2833,
          39.3667
        ]
      },
      "type": "Feature",
      "properties": {
        "hierarchy": [
          "tgn:2134687",
          "tgn:1000001",
          "tgn:7012149",
          "tgn:2000721",
          "tgn:7007254",
          "tgn:7029392"
        ],
        "placetype": [
          "aat:300008706"
        ],
        "id": 2134687,
        "name:xx": "Antelope Creek"
      }
    },
    {
      "geometry": {
        "type": "Point",
        "coordinates": [
          -97.6833,
          39
        ]
      },
      "type": "Feature",
      "properties": {
        "hierarchy": [
          "tgn:2134688",
          "tgn:1000001",
          "tgn:7012149",
          "tgn:2000731",
          "tgn:7007254",
          "tgn:7029392"
        ],
        "placetype": [
          "aat:300008706"
        ],
        "id": 2134688,
        "name:xx": "Antelope Creek"
      }
    },
    {
      "geometry": {
        "type": "Point",
        "coordinates": [
          -97.25,
          38.2167
        ]
      },
      "type": "Feature",
      "properties": {
        "hierarchy": [
          "tgn:2134689",
          "tgn:1000001",
          "tgn:7012149",
          "tgn:2000717",
          "tgn:7007254",
          "tgn:7029392"
        ],
        "placetype": [
          "aat:300008706"
        ],
        "id": 2134689,
        "name:xx": "Antelope Creek"
      }
    }
  ]
}
