{
  "geometry": {
    "type": "Point",
    "coordinates": [
      21.6167,
      55.5167
    ]
  },
  "type": "Feature",
  "properties": {
    "hierarchy": [
      "tgn:1051755",
      "tgn:1000003",
      "tgn:7006607",
      "tgn:7006542",
      "tgn:7029392"
    ],
    "placetype": [
      "aat:300008347"
    ],
    "id": 1051755,
    "name:xx": "Švėkšna"
  }
}
