{
  "geometry": {
    "type": "Point",
    "coordinates": [
      -92.05,
      33.4833
    ]
  },
  "type": "Feature",
  "properties": {
    "hierarchy": [
      "tgn:2672878",
      "tgn:1000001",
      "tgn:7016172",
      "tgn:2000110",
      "tgn:7012149",
      "tgn:7029392"
    ],
    "placetype": [
      "aat:300008706"
    ],
    "id": 2672878,
    "name:xx": "Snake Creek"
  }
}
