{
  "geometry": {
    "type": "Point",
    "coordinates": [
      -95.8667,
      41.2167
    ]
  },
  "type": "Feature",
  "properties": {
    "hierarchy": [
      "tgn:2411105",
      "tgn:1000001",
      "tgn:7012149",
      "tgn:2000638",
      "tgn:7007253",
      "tgn:7029392"
    ],
    "placetype": [
      "aat:300006075"
    ],
    "id": 2411105,
    "name:xx": "Indian Creek Ditch"
  }
}
