{
  "geometry": {
    "type": "Point",
    "coordinates": [
      -76.9333,
      34.7333
    ]
  },
  "type": "Feature",
  "properties": {
    "hierarchy": [
      "tgn:2778750",
      "tgn:1000001",
      "tgn:2001477",
      "tgn:7012149",
      "tgn:7007709",
      "tgn:7029392"
    ],
    "placetype": [
      "aat:300008699"
    ],
    "id": 2778750,
    "name:xx": "Wolf Branch"
  }
}
