{
  "geometry": {
    "type": "Point",
    "coordinates": [
      -107.7167,
      48.3667
    ]
  },
  "type": "Feature",
  "properties": {
    "hierarchy": [
      "tgn:2570674",
      "tgn:1000001",
      "tgn:7012149",
      "tgn:2001295",
      "tgn:7007524",
      "tgn:7029392"
    ],
    "placetype": [
      "aat:300006191"
    ],
    "id": 2570674,
    "name:xx": "Patrol Road Pond"
  }
}
