{
  "geometry": {
    "type": "Point",
    "coordinates": [
      78.701571,
      24.54129
    ]
  },
  "type": "Feature",
  "properties": {
    "hierarchy": [
      "tgn:7583959",
      "tgn:1000004",
      "tgn:7000198",
      "tgn:7016722",
      "tgn:7029392"
    ],
    "placetype": [
      "aat:300266554",
      "aat:300008699"
    ],
    "name:en": "Malandu Nāla",
    "id": 7583959
  }
}
