{
  "geometry": {
    "type": "Point",
    "coordinates": [
      -104.3167,
      35.6833
    ]
  },
  "type": "Feature",
  "properties": {
    "hierarchy": [
      "tgn:2312926",
      "tgn:1000001",
      "tgn:7012149",
      "tgn:2001453",
      "tgn:7007566",
      "tgn:7029392"
    ],
    "placetype": [
      "aat:300000390"
    ],
    "id": 2312926,
    "name:xx": "El Villa Claim"
  }
}
