{
  "geometry": {
    "type": "Point",
    "coordinates": [
      -109.1333,
      33.85
    ]
  },
  "type": "Feature",
  "properties": {
    "hierarchy": [
      "tgn:2347704",
      "tgn:2000090",
      "tgn:1000001",
      "tgn:7006451",
      "tgn:7012149",
      "tgn:7029392"
    ],
    "placetype": [
      "aat:300006191"
    ],
    "id": 2347704,
    "name:xx": "Georges Tank"
  }
}
