{
  "geometry": {
    "type": "Point",
    "coordinates": [
      -85.9667,
      35.2167
    ]
  },
  "type": "Feature",
  "properties": {
    "hierarchy": [
      "tgn:2439345",
      "tgn:1000001",
      "tgn:7012149",
      "tgn:2001862",
      "tgn:7007825",
      "tgn:7029392"
    ],
    "placetype": [
      "aat:300008761"
    ],
    "id": 2439345,
    "name:xx": "Kirk Hollow"
  }
}
