{
  "geometry": {
    "type": "Point",
    "coordinates": [
      -93.4833,
      39.35
    ]
  },
  "type": "Feature",
  "properties": {
    "hierarchy": [
      "tgn:2058269",
      "tgn:1000001",
      "tgn:2001180",
      "tgn:7012149",
      "tgn:7007523",
      "tgn:7029392"
    ],
    "placetype": [
      "aat:300008347"
    ],
    "id": 2058269,
    "name:xx": "Carrollton"
  }
}
