{
  "geometry": {
    "type": "Point",
    "coordinates": [
      -77.5333,
      40.3667
    ]
  },
  "type": "Feature",
  "properties": {
    "hierarchy": [
      "tgn:2431157",
      "tgn:1000001",
      "tgn:7012149",
      "tgn:1002779",
      "tgn:7007710",
      "tgn:7029392"
    ],
    "placetype": [
      "aat:300008761"
    ],
    "id": 2431157,
    "name:xx": "Kansas Valley"
  }
}
