{
  "geometry": {
    "type": "Point",
    "coordinates": [
      -108.1667,
      38.3333
    ]
  },
  "type": "Feature",
  "properties": {
    "hierarchy": [
      "tgn:2362187",
      "tgn:1000001",
      "tgn:7012149",
      "tgn:2000234",
      "tgn:7007158",
      "tgn:7029392"
    ],
    "placetype": [
      "aat:300008706"
    ],
    "id": 2362187,
    "name:xx": "Grays Creek"
  }
}
