{
  "geometry": {
    "type": "Point",
    "coordinates": [
      -73.4333,
      44.0167
    ]
  },
  "type": "Feature",
  "properties": {
    "hierarchy": [
      "tgn:2560378",
      "tgn:1000001",
      "tgn:7012149",
      "tgn:2001461",
      "tgn:7007568",
      "tgn:7029392"
    ],
    "placetype": [
      "aat:300008850"
    ],
    "id": 2560378,
    "name:xx": "Orchard Point"
  }
}
