{
  "geometry": {
    "type": "Point",
    "coordinates": [
      78.62148,
      29.12067
    ]
  },
  "type": "Feature",
  "properties": {
    "hierarchy": [
      "tgn:7556522",
      "tgn:1000004",
      "tgn:7000198",
      "tgn:7016722",
      "tgn:7029392"
    ],
    "placetype": [
      "aat:300008347"
    ],
    "name:en": "Sahaspur",
    "id": 7556522
  }
}
