{
  "geometry": {
    "type": "Point",
    "coordinates": [
      -121.15,
      39.4833
    ]
  },
  "type": "Feature",
  "properties": {
    "hierarchy": [
      "tgn:2317431",
      "tgn:1000001",
      "tgn:7012149",
      "tgn:7007157",
      "tgn:1003050",
      "tgn:7029392"
    ],
    "placetype": [
      "aat:300266640"
    ],
    "id": 2317431,
    "name:xx": "Empire Ridge"
  }
}
