{
  "geometry": {
    "type": "Point",
    "coordinates": [
      -88.1333,
      32.3167
    ]
  },
  "type": "Feature",
  "properties": {
    "hierarchy": [
      "tgn:2208333",
      "tgn:7002659",
      "tgn:1000001",
      "tgn:7012149",
      "tgn:7029392"
    ],
    "placetype": [
      "aat:300008699"
    ],
    "id": 2208333,
    "name:xx": "Burnam Branch"
  }
}
