{
  "geometry": {
    "type": "Point",
    "coordinates": [
      -84.85,
      38.2333
    ]
  },
  "type": "Feature",
  "properties": {
    "hierarchy": [
      "tgn:2366664",
      "tgn:1000001",
      "tgn:7012149",
      "tgn:1002382",
      "tgn:7007255",
      "tgn:7029392"
    ],
    "placetype": [
      "aat:300008706"
    ],
    "id": 2366664,
    "name:xx": "Grindstone Creek"
  }
}
