{
  "geometry": {
    "type": "Point",
    "coordinates": [
      -110.1833,
      33.45
    ]
  },
  "type": "Feature",
  "properties": {
    "hierarchy": [
      "tgn:1129526",
      "tgn:1000001",
      "tgn:7006451",
      "tgn:7012149",
      "tgn:7029392"
    ],
    "placetype": [
      "aat:300008707"
    ],
    "id": 1129526,
    "name:xx": "San Carlos"
  }
}
