{
  "geometry": {
    "type": "Point",
    "coordinates": [
      21.8667,
      61.4333
    ]
  },
  "type": "Feature",
  "properties": {
    "hierarchy": [
      "tgn:1031280",
      "tgn:7024077",
      "tgn:1000003",
      "tgn:1000069",
      "tgn:7029392"
    ],
    "placetype": [
      "aat:300008347"
    ],
    "id": 1031280,
    "name:xx": "Friitala"
  }
}
