{
  "geometry": {
    "type": "Point",
    "coordinates": [
      -82.3833,
      33.0667
    ]
  },
  "type": "Feature",
  "properties": {
    "hierarchy": [
      "tgn:2695668",
      "tgn:1000001",
      "tgn:7012149",
      "tgn:2000372",
      "tgn:7007248",
      "tgn:7029392"
    ],
    "placetype": [
      "aat:300008699"
    ],
    "id": 2695668,
    "name:xx": "Stinson Branch"
  }
}
