{
  "geometry": {
    "type": "Point",
    "coordinates": [
      31.271417,
      30.040515
    ]
  },
  "type": "Feature",
  "properties": {
    "hierarchy": [
      "tgn:7527221",
      "tgn:7001242",
      "tgn:7016833",
      "tgn:1001091",
      "tgn:7029392"
    ],
    "placetype": [
      "aat:300266755"
    ],
    "id": 7527221,
    "name:xx": "Madāfin al Mujāwirīn"
  }
}
