{
  "type": "FeatureCollection",
  "features": [
    {
      "geometry": {
        "type": "Point",
        "coordinates": [
          -103.166667,
          23.016667
        ]
      },
      "type": "Feature",
      "properties": {
        "hierarchy": [
          "tgn:7352380",
          "tgn:1000001",
          "tgn:7005601",
          "tgn:7005560",
          "tgn:7029392"
        ],
        "placetype": [
          "aat:300008347"
        ],
        "id": 7352380,
        "name:xx": "Amapola"
      }
    },
    {
      "geometry": {
        "type": "Point",
        "coordinates": [
          -95.2,
          18.233333
        ]
      },
      "type": "Feature",
      "properties": {
        "hierarchy": [
          "tgn:7352381",
          "tgn:1000001",
          "tgn:7005599",
          "tgn:7005560",
          "tgn:7029392"
        ],
        "placetype": [
          "aat:300008347"
        ],
        "id": 7352381,
        "name:xx": "Amapan"
      }
    },
    {
      "geometry": {
        "type": "Point",
        "coordinates": [
          -108.25,
          25.983333
        ]
      },
      "type": "Feature",
      "properties": {
        "hierarchy": [
          "tgn:7352382",
          "tgn:1000001",
          "tgn:7005595",
          "tgn:7005560",
          "tgn:7029392"
        ],
        "placetype": [
          "aat:300008347"
        ],
        "id": 7352382,
        "name:xx": "Amapal"
      }
    },
    {
      "geometry": {
        "type": "Point",
        "coordinates": [
          -96.283333,
          18.266667
        ]
      },
      "type": "Feature",
      "properties": {
        "hierarchy": [
          "tgn:7352384",
          "tgn:1000001",
          "tgn:1001893",
          "tgn:7005560",
          "tgn:7029392"
        ],
        "placetype": [
          "aat:300008699"
        ],
        "id": 7352384,
        "name:xx": "Amapa, Río"
      }
    },
    {
      "geometry": {
        "type": "Point",
        "coordinates": [
          -96.316667,
          18.383333
        ]
      },
      "type": "Feature",
      "properties": {
        "hierarchy": [
          "tgn:7352385",
          "tgn:1000001",
          "tgn:7005599",
          "tgn:7005560",
          "tgn:7029392"
        ],
        "placetype": [
          "aat:300007783"
        ],
        "id": 7352385,
        "name:xx": "Amapa"
      }
    },
    {
      "geometry": {
        "type": "Point",
        "coordinates": [
          -107.7,
          25.4
        ]
      },
      "type": "Feature",
      "properties": {
        "hierarchy": [
          "tgn:7352386",
          "tgn:1000001",
          "tgn:7005595",
          "tgn:7005560",
          "tgn:7029392"
        ],
        "placetype": [
          "aat:300008347"
        ],
        "id": 7352386,
        "name:xx": "Amapa"
      }
    },
    {
      "geometry": {
        "type": "Point",
        "coordinates": [
          -105.266667,
          21.783333
        ]
      },
      "type": "Feature",
      "properties": {
        "hierarchy": [
          "tgn:7352387",
          "tgn:1000001",
          "tgn:1001906",
          "tgn:7005560",
          "tgn:7029392"
        ],
        "placetype": [
          "aat:300008347"
        ],
        "id": 7352387,
        "name:xx": "Amapa"
      }
    },
    {
      "geometry": {
        "type": "Point",
        "coordinates": [
          -96.3,
          18.316667
        ]
      },
      "type": "Feature",
      "properties": {
        "hierarchy": [
          "tgn:7352388",
          "tgn:1000001",
          "tgn:7005591",
          "tgn:7005560",
          "tgn:7029392"
        ],
        "placetype": [
          "aat:300008347"
        ],
        "id": 7352388,
        "name:xx": "Amapa"
      }
    },
    {
      "geometry": {
        "type": "Point",
        "coordinates": [
          -94.883333,
          17.85
        ]
      },
      "type": "Feature",
      "properties": {
        "hierarchy": [
          "tgn:7352389",
          "tgn:1000001",
          "tgn:7005599",
          "tgn:7005560",
          "tgn:7029392"
        ],
        "placetype": [
          "aat:300008347"
        ],
        "id": 7352389,
        "name:xx": "Amapa"
      }
    }
  ]
}
