{
  "type": "FeatureCollection",
  "features": [
    {
      "geometry": {
        "type": "Point",
        "coordinates": [
          -109.316667,
          27.666667
        ]
      },
      "type": "Feature",
      "properties": {
        "hierarchy": [
          "tgn:7388670",
          "tgn:1000001",
          "tgn:1001960",
          "tgn:7005560",
          "tgn:7029392"
        ],
        "placetype": [
          "aat:300008795"
        ],
        "id": 7388670,
        "name:xx": "Punta de Agua, Cerro"
      }
    },
    {
      "geometry": {
        "type": "Point",
        "coordinates": [
          -104.333333,
          19.1
        ]
      },
      "type": "Feature",
      "properties": {
        "hierarchy": [
          "tgn:7388671",
          "tgn:7016644",
          "tgn:1000001",
          "tgn:7005560",
          "tgn:7029392"
        ],
        "placetype": [
          "aat:300266554",
          "aat:300008699"
        ],
        "id": 7388671,
        "name:xx": "Punta de Agua"
      }
    },
    {
      "geometry": {
        "type": "Point",
        "coordinates": [
          -111,
          30.933333
        ]
      },
      "type": "Feature",
      "properties": {
        "hierarchy": [
          "tgn:7388672",
          "tgn:1000001",
          "tgn:1001960",
          "tgn:7005560",
          "tgn:7029392"
        ],
        "placetype": [
          "aat:300008347"
        ],
        "id": 7388672,
        "name:xx": "Punta de Agua"
      }
    },
    {
      "geometry": {
        "type": "Point",
        "coordinates": [
          -110.833333,
          29.6
        ]
      },
      "type": "Feature",
      "properties": {
        "hierarchy": [
          "tgn:7388673",
          "tgn:1000001",
          "tgn:1001960",
          "tgn:7005560",
          "tgn:7029392"
        ],
        "placetype": [
          "aat:300008347"
        ],
        "id": 7388673,
        "name:xx": "Punta de Agua"
      }
    },
    {
      "geometry": {
        "type": "Point",
        "coordinates": [
          -106.333333,
          28.9
        ]
      },
      "type": "Feature",
      "properties": {
        "hierarchy": [
          "tgn:7388674",
          "tgn:7005581",
          "tgn:1000001",
          "tgn:7005560",
          "tgn:7029392"
        ],
        "placetype": [
          "aat:300008347"
        ],
        "id": 7388674,
        "name:xx": "Punta de Agua"
      }
    },
    {
      "geometry": {
        "type": "Point",
        "coordinates": [
          -104.283333,
          28.75
        ]
      },
      "type": "Feature",
      "properties": {
        "hierarchy": [
          "tgn:7388675",
          "tgn:7005581",
          "tgn:1000001",
          "tgn:7005560",
          "tgn:7029392"
        ],
        "placetype": [
          "aat:300008347"
        ],
        "id": 7388675,
        "name:xx": "Punta de Agua"
      }
    },
    {
      "geometry": {
        "type": "Point",
        "coordinates": [
          -110.416667,
          28.433333
        ]
      },
      "type": "Feature",
      "properties": {
        "hierarchy": [
          "tgn:7388676",
          "tgn:1000001",
          "tgn:1001960",
          "tgn:7005560",
          "tgn:7029392"
        ],
        "placetype": [
          "aat:300008347"
        ],
        "id": 7388676,
        "name:xx": "Punta de Agua"
      }
    },
    {
      "geometry": {
        "type": "Point",
        "coordinates": [
          -105.066667,
          26.55
        ]
      },
      "type": "Feature",
      "properties": {
        "hierarchy": [
          "tgn:7388677",
          "tgn:7005581",
          "tgn:1000001",
          "tgn:7005560",
          "tgn:7029392"
        ],
        "placetype": [
          "aat:300008347"
        ],
        "id": 7388677,
        "name:xx": "Punta de Agua"
      }
    },
    {
      "geometry": {
        "type": "Point",
        "coordinates": [
          -97.65,
          25.916667
        ]
      },
      "type": "Feature",
      "properties": {
        "hierarchy": [
          "tgn:7388678",
          "tgn:1000001",
          "tgn:7005597",
          "tgn:7005560",
          "tgn:7029392"
        ],
        "placetype": [
          "aat:300008347"
        ],
        "id": 7388678,
        "name:xx": "Punta de Agua"
      }
    },
    {
      "geometry": {
        "type": "Point",
        "coordinates": [
          -103.7,
          19.85
        ]
      },
      "type": "Feature",
      "properties": {
        "hierarchy": [
          "tgn:7388679",
          "tgn:7005586",
          "tgn:1000001",
          "tgn:7005560",
          "tgn:7029392"
        ],
        "placetype": [
          "aat:300008347"
        ],
        "id": 7388679,
        "name:xx": "Punta de Agua"
      }
    }
  ]
}
