{
  "geometry": {
    "type": "Point",
    "coordinates": [
      123.8833,
      12.6667
    ]
  },
  "type": "Feature",
  "properties": {
    "hierarchy": [
      "tgn:1140717",
      "tgn:1000004",
      "tgn:1001540",
      "tgn:1000135",
      "tgn:7029392"
    ],
    "placetype": [
      "aat:300008347"
    ],
    "id": 1140717,
    "name:xx": "Bulan"
  }
}
