{
  "geometry": {
    "type": "Point",
    "coordinates": [
      -90.8167,
      47.7167
    ]
  },
  "type": "Feature",
  "properties": {
    "hierarchy": [
      "tgn:2397665",
      "tgn:1000001",
      "tgn:2001014",
      "tgn:7012149",
      "tgn:7007521",
      "tgn:7029392"
    ],
    "placetype": [
      "aat:300008798"
    ],
    "id": 2397665,
    "name:xx": "Honeymoon Mountain"
  }
}
