{
  "geometry": {
    "type": "Point",
    "coordinates": [
      -94.25,
      31.2333
    ]
  },
  "type": "Feature",
  "properties": {
    "hierarchy": [
      "tgn:2609424",
      "tgn:1000001",
      "tgn:7012149",
      "tgn:2002067",
      "tgn:7007826",
      "tgn:7029392"
    ],
    "placetype": [
      "aat:300008699"
    ],
    "id": 2609424,
    "name:xx": "Rayburn Branch"
  }
}
