{
  "geometry": {
    "type": "Point",
    "coordinates": [
      79.919444,
      13.1575
    ]
  },
  "type": "Feature",
  "properties": {
    "hierarchy": [
      "tgn:7567827",
      "tgn:1000004",
      "tgn:7000198",
      "tgn:7001797",
      "tgn:7029392"
    ],
    "placetype": [
      "aat:300008347"
    ],
    "name:en": "Ikkādu",
    "id": 7567827
  }
}
