{
  "type": "FeatureCollection",
  "features": [
    {
      "geometry": {
        "type": "Point",
        "coordinates": [
          -160.35,
          55.35
        ]
      },
      "type": "Feature",
      "properties": {
        "hierarchy": [
          "tgn:2585990",
          "tgn:7030515",
          "tgn:7006450",
          "tgn:1000001",
          "tgn:7012149",
          "tgn:7029392"
        ],
        "placetype": [
          "aat:300132316"
        ],
        "id": 2585990,
        "name:xx": "Pirate Cove"
      }
    },
    {
      "geometry": {
        "type": "Point",
        "coordinates": [
          -135.3667,
          56.9833
        ]
      },
      "type": "Feature",
      "properties": {
        "hierarchy": [
          "tgn:2585991",
          "tgn:7006450",
          "tgn:1000001",
          "tgn:7012149",
          "tgn:2124002",
          "tgn:7029392"
        ],
        "placetype": [
          "aat:300132316"
        ],
        "id": 2585991,
        "name:xx": "Pirate Cove"
      }
    },
    {
      "geometry": {
        "type": "Point",
        "coordinates": [
          -148.2833,
          60.8667
        ]
      },
      "type": "Feature",
      "properties": {
        "hierarchy": [
          "tgn:2585992",
          "tgn:7006450",
          "tgn:1000001",
          "tgn:7012149",
          "tgn:2000086",
          "tgn:7029392"
        ],
        "placetype": [
          "aat:300132316"
        ],
        "id": 2585992,
        "name:xx": "Pirate Cove"
      }
    },
    {
      "geometry": {
        "type": "Point",
        "coordinates": [
          -86.65,
          30.3833
        ]
      },
      "type": "Feature",
      "properties": {
        "hierarchy": [
          "tgn:2585993",
          "tgn:1000001",
          "tgn:7012149",
          "tgn:2000281",
          "tgn:7007240",
          "tgn:7029392"
        ],
        "placetype": [
          "aat:300132316"
        ],
        "id": 2585993,
        "name:xx": "Pirate Cove"
      }
    },
    {
      "geometry": {
        "type": "Point",
        "coordinates": [
          -124.05,
          44.8167
        ]
      },
      "type": "Feature",
      "properties": {
        "hierarchy": [
          "tgn:2585994",
          "tgn:1000001",
          "tgn:7012149",
          "tgn:1002599",
          "tgn:7007708",
          "tgn:7029392"
        ],
        "placetype": [
          "aat:300132316"
        ],
        "id": 2585994,
        "name:xx": "Pirate Cove"
      }
    },
    {
      "geometry": {
        "type": "Point",
        "coordinates": [
          -79,
          33.5833
        ]
      },
      "type": "Feature",
      "properties": {
        "hierarchy": [
          "tgn:2585995",
          "tgn:1000001",
          "tgn:7012149",
          "tgn:2001750",
          "tgn:7007712",
          "tgn:7029392"
        ],
        "placetype": [
          "aat:300008347"
        ],
        "id": 2585995,
        "name:xx": "Pirate Cove"
      }
    },
    {
      "geometry": {
        "type": "Point",
        "coordinates": [
          -165.2167,
          65.65
        ]
      },
      "type": "Feature",
      "properties": {
        "hierarchy": [
          "tgn:2585996",
          "tgn:7006450",
          "tgn:1000001",
          "tgn:7012149",
          "tgn:2000079",
          "tgn:7029392"
        ],
        "placetype": [
          "aat:300008706"
        ],
        "id": 2585996,
        "name:xx": "Pirate Creek"
      }
    },
    {
      "geometry": {
        "type": "Point",
        "coordinates": [
          -150.4667,
          63.3
        ]
      },
      "type": "Feature",
      "properties": {
        "hierarchy": [
          "tgn:2585997",
          "tgn:7006450",
          "tgn:1000001",
          "tgn:7012149",
          "tgn:2000089",
          "tgn:7029392"
        ],
        "placetype": [
          "aat:300008706"
        ],
        "id": 2585997,
        "name:xx": "Pirate Creek"
      }
    },
    {
      "geometry": {
        "type": "Point",
        "coordinates": [
          -67.5333,
          45.55
        ]
      },
      "type": "Feature",
      "properties": {
        "hierarchy": [
          "tgn:2585998",
          "tgn:1000001",
          "tgn:7012149",
          "tgn:7014589",
          "tgn:7007515",
          "tgn:7029392"
        ],
        "placetype": [
          "aat:300008798"
        ],
        "id": 2585998,
        "name:xx": "Pirate Hill"
      }
    },
    {
      "geometry": {
        "type": "Point",
        "coordinates": [
          -87.25,
          45.1667
        ]
      },
      "type": "Feature",
      "properties": {
        "hierarchy": [
          "tgn:2585999",
          "tgn:1000001",
          "tgn:2002317",
          "tgn:7012149",
          "tgn:7007922",
          "tgn:7029392"
        ],
        "placetype": [
          "aat:300008791"
        ],
        "id": 2585999,
        "name:xx": "Pirate Island"
      }
    }
  ]
}
