{
  "geometry": {
    "type": "Point",
    "coordinates": [
      -90.2667,
      40.1333
    ]
  },
  "type": "Feature",
  "properties": {
    "hierarchy": [
      "tgn:1118237",
      "tgn:1000001",
      "tgn:7012149",
      "tgn:1002643",
      "tgn:7007251",
      "tgn:7029392"
    ],
    "placetype": [
      "aat:300008680"
    ],
    "id": 1118237,
    "name:xx": "Stewart Lake"
  }
}
