{
  "geometry": {
    "type": "Point",
    "coordinates": [
      76.852105,
      30.611793
    ]
  },
  "type": "Feature",
  "properties": {
    "hierarchy": [
      "tgn:7582277",
      "tgn:1000004",
      "tgn:7000198",
      "tgn:7016883",
      "tgn:7029392"
    ],
    "placetype": [
      "aat:300008347"
    ],
    "name:en": "Mīrpur",
    "id": 7582277
  }
}
