{
  "geometry": {
    "type": "Point",
    "coordinates": [
      -110.3333,
      45.3833
    ]
  },
  "type": "Feature",
  "properties": {
    "hierarchy": [
      "tgn:2683808",
      "tgn:1000001",
      "tgn:7012149",
      "tgn:7007524",
      "tgn:7029392"
    ],
    "placetype": [
      "aat:300008706"
    ],
    "id": 2683808,
    "name:xx": "Speculator Creek"
  }
}
