{
  "geometry": {
    "type": "Point",
    "coordinates": [
      -93.9167,
      30.85
    ]
  },
  "type": "Feature",
  "properties": {
    "hierarchy": [
      "tgn:2433097",
      "tgn:1000001",
      "tgn:7012149",
      "tgn:2002009",
      "tgn:7007826",
      "tgn:7029392"
    ],
    "placetype": [
      "aat:300008347"
    ],
    "id": 2433097,
    "name:xx": "Keithton"
  }
}
