{
  "type": "FeatureCollection",
  "features": [
    {
      "geometry": {
        "type": "Point",
        "coordinates": [
          -2.933333,
          53.466667
        ]
      },
      "type": "Feature",
      "properties": {
        "hierarchy": [
          "tgn:1028270",
          "tgn:1003641",
          "tgn:7002445",
          "tgn:1000003",
          "tgn:7029504",
          "tgn:7008591",
          "tgn:7029392"
        ],
        "placetype": [
          "aat:300008347"
        ],
        "name:en": "Aintree",
        "id": 1028270
      }
    },
    {
      "geometry": {
        "type": "Point",
        "coordinates": [
          -2.266667,
          52.633333
        ]
      },
      "type": "Feature",
      "properties": {
        "hierarchy": [
          "tgn:1028271",
          "tgn:7002445",
          "tgn:1000003",
          "tgn:7012034",
          "tgn:7008591",
          "tgn:7029392"
        ],
        "placetype": [
          "aat:300008347",
          "aat:300008372"
        ],
        "name:en": "Albrighton",
        "id": 1028271
      }
    },
    {
      "geometry": {
        "type": "Point",
        "coordinates": [
          -0.483333,
          51.2
        ]
      },
      "type": "Feature",
      "properties": {
        "hierarchy": [
          "tgn:1028272",
          "tgn:7002445",
          "tgn:1000003",
          "tgn:7008175",
          "tgn:7008591",
          "tgn:7029392"
        ],
        "placetype": [
          "aat:300008347"
        ],
        "name:en": "Albury",
        "id": 1028272
      }
    },
    {
      "geometry": {
        "type": "Point",
        "coordinates": [
          -1.616667,
          51.466667
        ]
      },
      "type": "Feature",
      "properties": {
        "hierarchy": [
          "tgn:1028274",
          "tgn:7002445",
          "tgn:1000003",
          "tgn:7008180",
          "tgn:7008591",
          "tgn:7029392"
        ],
        "placetype": [
          "aat:300008347"
        ],
        "name:en": "Aldbourne",
        "id": 1028274
      }
    },
    {
      "geometry": {
        "type": "Point",
        "coordinates": [
          -0.116667,
          53.816667
        ]
      },
      "type": "Feature",
      "properties": {
        "hierarchy": [
          "tgn:1028275",
          "tgn:7002445",
          "tgn:1000003",
          "tgn:7019057",
          "tgn:7008591",
          "tgn:7029392"
        ],
        "placetype": [
          "aat:300008347",
          "aat:300008372"
        ],
        "id": 1028275,
        "name:xx": "Aldbrough"
      }
    },
    {
      "geometry": {
        "type": "Point",
        "coordinates": [
          -0.6,
          51.8
        ]
      },
      "type": "Feature",
      "properties": {
        "hierarchy": [
          "tgn:1028276",
          "tgn:7002445",
          "tgn:1000003",
          "tgn:7008145",
          "tgn:7008591",
          "tgn:7029392"
        ],
        "placetype": [
          "aat:300008347",
          "aat:300008372"
        ],
        "name:en": "Aldbury",
        "id": 1028276
      }
    },
    {
      "geometry": {
        "type": "Point",
        "coordinates": [
          -2.233333,
          53.3
        ]
      },
      "type": "Feature",
      "properties": {
        "hierarchy": [
          "tgn:1028279",
          "tgn:7002445",
          "tgn:7008114",
          "tgn:1000003",
          "tgn:7008591",
          "tgn:7029392"
        ],
        "placetype": [
          "aat:300008347"
        ],
        "name:en": "Alderley Edge",
        "id": 1028279
      }
    }
  ]
}
