{
  "geometry": {
    "type": "Point",
    "coordinates": [
      -72.2333,
      43.2833
    ]
  },
  "type": "Feature",
  "properties": {
    "hierarchy": [
      "tgn:2595451",
      "tgn:1000001",
      "tgn:2001427",
      "tgn:7012149",
      "tgn:7007564",
      "tgn:7029392"
    ],
    "placetype": [
      "aat:300008798"
    ],
    "id": 2595451,
    "name:xx": "Potato Hill"
  }
}
