{
  "geometry": {
    "type": "Point",
    "coordinates": [
      -74.85,
      43.3833
    ]
  },
  "type": "Feature",
  "properties": {
    "hierarchy": [
      "tgn:2542642",
      "tgn:1000001",
      "tgn:7012149",
      "tgn:1002472",
      "tgn:7007568",
      "tgn:7029392"
    ],
    "placetype": [
      "aat:300008347"
    ],
    "id": 2542642,
    "name:xx": "Nobleboro"
  }
}
