{
  "geometry": {
    "type": "Point",
    "coordinates": [
      -85.3833,
      35.5333
    ]
  },
  "type": "Feature",
  "properties": {
    "hierarchy": [
      "tgn:2743173",
      "tgn:1000001",
      "tgn:2001840",
      "tgn:7012149",
      "tgn:7007825",
      "tgn:7029392"
    ],
    "placetype": [
      "aat:300008798"
    ],
    "id": 2743173,
    "name:xx": "Vance Mountain"
  }
}
