{
  "geometry": {
    "type": "Point",
    "coordinates": [
      -116.9333,
      45.8167
    ]
  },
  "type": "Feature",
  "properties": {
    "hierarchy": [
      "tgn:2190594",
      "tgn:1000001",
      "tgn:7012149",
      "tgn:2001722",
      "tgn:7007708",
      "tgn:7029392"
    ],
    "placetype": [
      "aat:300008697"
    ],
    "id": 2190594,
    "name:xx": "Box Spring"
  }
}
