{
  "geometry": {
    "type": "Point",
    "coordinates": [
      -114.65,
      43.6333
    ]
  },
  "type": "Feature",
  "properties": {
    "hierarchy": [
      "tgn:2487759",
      "tgn:1000001",
      "tgn:7012149",
      "tgn:7007250",
      "tgn:7029392"
    ],
    "placetype": [
      "aat:300008706"
    ],
    "id": 2487759,
    "name:xx": "Left Fork Placer Creek"
  }
}
