{
  "geometry": {
    "type": "Point",
    "coordinates": [
      84.8333,
      28.0667
    ]
  },
  "type": "Feature",
  "properties": {
    "hierarchy": [
      "tgn:1083269",
      "tgn:7001425",
      "tgn:7001417",
      "tgn:1000004",
      "tgn:1000132",
      "tgn:7029392"
    ],
    "placetype": [
      "aat:300008347"
    ],
    "id": 1083269,
    "name:xx": "Burāthum"
  }
}
