{
  "geometry": {
    "type": "Point",
    "coordinates": [
      125.1333,
      38.35
    ]
  },
  "type": "Feature",
  "properties": {
    "hierarchy": [
      "tgn:1082130",
      "tgn:1001301",
      "tgn:1000004",
      "tgn:1000122",
      "tgn:7029392"
    ],
    "placetype": [
      "aat:300008347"
    ],
    "id": 1082130,
    "name:xx": "Songhwa-ŭp"
  }
}
