{
  "geometry": {
    "type": "Point",
    "coordinates": [
      -122.5167,
      37.8167
    ]
  },
  "type": "Feature",
  "properties": {
    "hierarchy": [
      "tgn:2627219",
      "tgn:1000001",
      "tgn:7012149",
      "tgn:7007157",
      "tgn:7014005",
      "tgn:7029392"
    ],
    "placetype": [
      "aat:300008680"
    ],
    "id": 2627219,
    "name:xx": "Rodeo Lagoon"
  }
}
