{
  "geometry": {
    "type": "Point",
    "coordinates": [
      -80.5167,
      33.4833
    ]
  },
  "type": "Feature",
  "properties": {
    "hierarchy": [
      "tgn:2765527",
      "tgn:1000001",
      "tgn:7012149",
      "tgn:2001762",
      "tgn:7007712",
      "tgn:7029392"
    ],
    "placetype": [
      "aat:300008699"
    ],
    "id": 2765527,
    "name:xx": "White Cane Branch"
  }
}
