{
  "geometry": {
    "type": "Point",
    "coordinates": [
      -83.1333,
      38.5167
    ]
  },
  "type": "Feature",
  "properties": {
    "hierarchy": [
      "tgn:2719752",
      "tgn:1000001",
      "tgn:7012149",
      "tgn:1002426",
      "tgn:7007255",
      "tgn:7029392"
    ],
    "placetype": [
      "aat:300008699"
    ],
    "id": 2719752,
    "name:xx": "Three Prong Branch"
  }
}
