{
  "geometry": {
    "type": "Point",
    "coordinates": [
      -93.7333,
      30.5333
    ]
  },
  "type": "Feature",
  "properties": {
    "hierarchy": [
      "tgn:2573516",
      "tgn:1000001",
      "tgn:7012149",
      "tgn:2002047",
      "tgn:7007826",
      "tgn:7029392"
    ],
    "placetype": [
      "aat:300008680"
    ],
    "id": 2573516,
    "name:xx": "Pecan Lake"
  }
}
