{
  "geometry": {
    "type": "Point",
    "coordinates": [
      3.7333,
      46.25
    ]
  },
  "type": "Feature",
  "properties": {
    "hierarchy": [
      "tgn:1033792",
      "tgn:7002871",
      "tgn:1000003",
      "tgn:1000070",
      "tgn:7029392"
    ],
    "placetype": [
      "aat:300008347"
    ],
    "id": 1033792,
    "name:xx": "Lapalisse"
  }
}
