{
  "geometry": {
    "type": "Point",
    "coordinates": [
      -114.2833,
      35.0333
    ]
  },
  "type": "Feature",
  "properties": {
    "hierarchy": [
      "tgn:2353900",
      "tgn:1000001",
      "tgn:7006451",
      "tgn:7012149",
      "tgn:2000098",
      "tgn:7029392"
    ],
    "placetype": [
      "aat:300000390"
    ],
    "id": 2353900,
    "name:xx": "Gold Trail Mine"
  }
}
