{
  "geometry": {
    "type": "Point",
    "coordinates": [
      -89.25,
      31.6833
    ]
  },
  "type": "Feature",
  "properties": {
    "hierarchy": [
      "tgn:2679399",
      "tgn:1000001",
      "tgn:7012149",
      "tgn:2001119",
      "tgn:7007522",
      "tgn:7029392"
    ],
    "placetype": [
      "aat:300008706"
    ],
    "id": 2679399,
    "name:xx": "South Fork Mill Creek"
  }
}
