{
  "geometry": {
    "type": "Point",
    "coordinates": [
      -107.75,
      37.95
    ]
  },
  "type": "Feature",
  "properties": {
    "hierarchy": [
      "tgn:2507973",
      "tgn:1000001",
      "tgn:7012149",
      "tgn:7007158",
      "tgn:2000248",
      "tgn:7029392"
    ],
    "placetype": [
      "aat:300386845"
    ],
    "id": 2507973,
    "name:xx": "Middle Basin"
  }
}
