{
  "geometry": {
    "type": "Point",
    "coordinates": [
      -92.1167,
      46.5833
    ]
  },
  "type": "Feature",
  "properties": {
    "hierarchy": [
      "tgn:2120791",
      "tgn:1000001",
      "tgn:2002318",
      "tgn:7012149",
      "tgn:7007922",
      "tgn:7029392"
    ],
    "placetype": [
      "aat:300387016"
    ],
    "id": 2120791,
    "name:xx": "Boylston"
  }
}
