{
  "geometry": {
    "type": "Point",
    "coordinates": [
      -89.0333,
      35.5667
    ]
  },
  "type": "Feature",
  "properties": {
    "hierarchy": [
      "tgn:2616350",
      "tgn:1000001",
      "tgn:7012149",
      "tgn:7007825",
      "tgn:7029392"
    ],
    "placetype": [
      "aat:300008699"
    ],
    "id": 2616350,
    "name:xx": "Rice Branch"
  }
}
