{
  "geometry": {
    "type": "Point",
    "coordinates": [
      -83.7667,
      42.3167
    ]
  },
  "type": "Feature",
  "properties": {
    "hierarchy": [
      "tgn:2051226",
      "tgn:1000001",
      "tgn:7012149",
      "tgn:1003000",
      "tgn:7007520",
      "tgn:7029392"
    ],
    "placetype": [
      "aat:300008347"
    ],
    "id": 2051226,
    "name:xx": "Barton Hills"
  }
}
