{
  "geometry": {
    "type": "Point",
    "coordinates": [
      -72.1333,
      41.7333
    ]
  },
  "type": "Feature",
  "properties": {
    "hierarchy": [
      "tgn:2146349",
      "tgn:1000001",
      "tgn:1003028",
      "tgn:7012149",
      "tgn:7007159",
      "tgn:7029392"
    ],
    "placetype": [
      "aat:300008699"
    ],
    "id": 2146349,
    "name:xx": "Ballymahack Brook"
  }
}
