{
  "geometry": {
    "type": "Point",
    "coordinates": [
      -101.55,
      18.0667
    ]
  },
  "type": "Feature",
  "properties": {
    "hierarchy": [
      "tgn:1017929",
      "tgn:7005585",
      "tgn:1000001",
      "tgn:7005560",
      "tgn:7029392"
    ],
    "placetype": [
      "aat:300008347"
    ],
    "id": 1017929,
    "name:xx": "Nueva Cuadrilla"
  }
}
