{
  "geometry": {
    "type": "Point",
    "coordinates": [
      -110.9167,
      33.3667
    ]
  },
  "type": "Feature",
  "properties": {
    "hierarchy": [
      "tgn:2563886",
      "tgn:1000001",
      "tgn:7006451",
      "tgn:2000093",
      "tgn:7012149",
      "tgn:7029392"
    ],
    "placetype": [
      "aat:300008697"
    ],
    "id": 2563886,
    "name:xx": "Oxhide Mine Spring"
  }
}
