{
  "geometry": {
    "type": "Point",
    "coordinates": [
      -169.6667,
      -14.1833
    ]
  },
  "type": "Feature",
  "properties": {
    "hierarchy": [
      "tgn:1115075",
      "tgn:7005667",
      "tgn:1010126",
      "tgn:1000006",
      "tgn:7029392"
    ],
    "placetype": [
      "aat:300266559"
    ],
    "id": 1115075,
    "name:xx": "Asaga Strait"
  }
}
