{
  "geometry": {
    "type": "Point",
    "coordinates": [
      -95.7833,
      40.7833
    ]
  },
  "type": "Feature",
  "properties": {
    "hierarchy": [
      "tgn:2533692",
      "tgn:1000001",
      "tgn:2000596",
      "tgn:7012149",
      "tgn:7007253",
      "tgn:7029392"
    ],
    "placetype": [
      "aat:300006075"
    ],
    "id": 2533692,
    "name:xx": "Mustard Lateral"
  }
}
