{
  "geometry": {
    "type": "Point",
    "coordinates": [
      11.0333,
      59.2667
    ]
  },
  "type": "Feature",
  "properties": {
    "hierarchy": [
      "tgn:1048553",
      "tgn:7003651",
      "tgn:1000003",
      "tgn:1000088",
      "tgn:7029392"
    ],
    "placetype": [
      "aat:300008347"
    ],
    "id": 1048553,
    "name:xx": "Greåker"
  }
}
