{
  "geometry": {
    "type": "Point",
    "coordinates": [
      -79.2833,
      38.8667
    ]
  },
  "type": "Feature",
  "properties": {
    "hierarchy": [
      "tgn:1102047",
      "tgn:1000001",
      "tgn:7012149",
      "tgn:7013961",
      "tgn:7029392"
    ],
    "placetype": [
      "aat:300000510"
    ],
    "id": 1102047,
    "name:xx": "Spruce Knob-Seneca Rocks National Recreation Area"
  }
}
