{
  "type": "FeatureCollection",
  "features": [
    {
      "geometry": {
        "type": "Point",
        "coordinates": [
          -3,
          54.366667
        ]
      },
      "type": "Feature",
      "properties": {
        "hierarchy": [
          "tgn:7031571",
          "tgn:7002445",
          "tgn:1000003",
          "tgn:7008117",
          "tgn:7008591",
          "tgn:7029392"
        ],
        "placetype": [
          "aat:300008347"
        ],
        "name:en": "Hawkshead",
        "id": 7031571
      }
    },
    {
      "geometry": {
        "type": "Point",
        "coordinates": [
          35.118,
          32.644
        ]
      },
      "type": "Feature",
      "properties": {
        "hierarchy": [
          "tgn:7031574",
          "tgn:7000249",
          "tgn:1000004",
          "tgn:1000119",
          "tgn:7029392"
        ],
        "placetype": [
          "aat:300008347"
        ],
        "id": 7031574,
        "name:xx": "HaẔorea'"
      }
    },
    {
      "geometry": {
        "type": "Point",
        "coordinates": [
          16.965,
          46.156
        ]
      },
      "type": "Feature",
      "properties": {
        "hierarchy": [
          "tgn:7031577",
          "tgn:7017297",
          "tgn:1000003",
          "tgn:7006663",
          "tgn:7029392"
        ],
        "placetype": [
          "aat:300008347"
        ],
        "id": 7031577,
        "name:xx": "Hlebine"
      }
    }
  ]
}
