{
  "geometry": {
    "type": "Point",
    "coordinates": [
      -122.7833,
      48.5833
    ]
  },
  "type": "Feature",
  "properties": {
    "hierarchy": [
      "tgn:2684614",
      "tgn:1000001",
      "tgn:7012149",
      "tgn:1002862",
      "tgn:7007920",
      "tgn:7029392"
    ],
    "placetype": [
      "aat:300132348"
    ],
    "id": 2684614,
    "name:xx": "Spindle Rock"
  }
}
