{
  "geometry": {
    "type": "Point",
    "coordinates": [
      -95.4667,
      32.7167
    ]
  },
  "type": "Feature",
  "properties": {
    "hierarchy": [
      "tgn:2345429",
      "tgn:1000001",
      "tgn:7012149",
      "tgn:1003034",
      "tgn:7007826",
      "tgn:7029392"
    ],
    "placetype": [
      "aat:300006191"
    ],
    "id": 2345429,
    "name:xx": "Garner Lake"
  }
}
