{
  "geometry": {
    "type": "Point",
    "coordinates": [
      -120.65,
      35.4167
    ]
  },
  "type": "Feature",
  "properties": {
    "hierarchy": [
      "tgn:1134104",
      "tgn:1000001",
      "tgn:7012149",
      "tgn:7007157",
      "tgn:1002863",
      "tgn:7029392"
    ],
    "placetype": [
      "aat:300008706"
    ],
    "id": 1134104,
    "name:xx": "Paloma Creek"
  }
}
