{
  "geometry": {
    "type": "Point",
    "coordinates": [
      -84.15,
      37.9833
    ]
  },
  "type": "Feature",
  "properties": {
    "hierarchy": [
      "tgn:2306700",
      "tgn:1000001",
      "tgn:2000781",
      "tgn:7012149",
      "tgn:7007255",
      "tgn:7029392"
    ],
    "placetype": [
      "aat:300008706"
    ],
    "id": 2306700,
    "name:xx": "East Fork Fourmile Creek"
  }
}
