{
  "geometry": {
    "type": "Point",
    "coordinates": [
      -91.9167,
      34.05
    ]
  },
  "type": "Feature",
  "properties": {
    "hierarchy": [
      "tgn:2191816",
      "tgn:1000001",
      "tgn:7016172",
      "tgn:7012149",
      "tgn:2000144",
      "tgn:7029392"
    ],
    "placetype": [
      "aat:300008905"
    ],
    "id": 2191816,
    "name:xx": "Bradshaw Brake"
  }
}
