{
  "geometry": {
    "type": "Point",
    "coordinates": [
      -84.7667,
      35.65
    ]
  },
  "type": "Feature",
  "properties": {
    "hierarchy": [
      "tgn:2148049",
      "tgn:1000001",
      "tgn:7012149",
      "tgn:2001908",
      "tgn:7007825",
      "tgn:7029392"
    ],
    "placetype": [
      "aat:300008791"
    ],
    "id": 2148049,
    "name:xx": "Barker Island"
  }
}
