{
  "geometry": {
    "type": "Point",
    "coordinates": [
      -81.6833,
      28.5333
    ]
  },
  "type": "Feature",
  "properties": {
    "hierarchy": [
      "tgn:2225209",
      "tgn:1000001",
      "tgn:7012149",
      "tgn:1002567",
      "tgn:7007240",
      "tgn:7029392"
    ],
    "placetype": [
      "aat:300008347"
    ],
    "id": 2225209,
    "name:xx": "Castle Hill"
  }
}
