{
  "geometry": {
    "type": "Point",
    "coordinates": [
      -43.9833,
      -18.6667
    ]
  },
  "type": "Feature",
  "properties": {
    "hierarchy": [
      "tgn:1122876",
      "tgn:7006237",
      "tgn:1000047",
      "tgn:7002457",
      "tgn:1000002",
      "tgn:7029392"
    ],
    "placetype": [
      "aat:300008707"
    ],
    "id": 1122876,
    "name:xx": "Cipó"
  }
}
