{
  "geometry": {
    "type": "Point",
    "coordinates": [
      121.65,
      25.05
    ]
  },
  "type": "Feature",
  "properties": {
    "hierarchy": [
      "tgn:7490432",
      "tgn:1000957",
      "tgn:1000004",
      "tgn:1000141",
      "tgn:7029392"
    ],
    "placetype": [
      "aat:300008347"
    ],
    "id": 7490432,
    "name:xx": "Shimenkeng"
  }
}
