{
  "geometry": {
    "type": "Point",
    "coordinates": [
      -119.35,
      37.55
    ]
  },
  "type": "Feature",
  "properties": {
    "hierarchy": [
      "tgn:2660013",
      "tgn:1000001",
      "tgn:7012149",
      "tgn:7007157",
      "tgn:1002621",
      "tgn:7029392"
    ],
    "placetype": [
      "aat:300008706"
    ],
    "id": 2660013,
    "name:xx": "Shirley Creek"
  }
}
