{
  "geometry": {
    "type": "Point",
    "coordinates": [
      -85.7333,
      36.0167
    ]
  },
  "type": "Feature",
  "properties": {
    "hierarchy": [
      "tgn:2573850",
      "tgn:1000001",
      "tgn:7012149",
      "tgn:7022246",
      "tgn:7007825",
      "tgn:7029392"
    ],
    "placetype": [
      "aat:300266640"
    ],
    "id": 2573850,
    "name:xx": "Pedigo Ridge"
  }
}
