{
  "geometry": {
    "type": "Point",
    "coordinates": [
      44.542,
      40.807
    ]
  },
  "type": "Feature",
  "properties": {
    "hierarchy": [
      "tgn:7024067",
      "tgn:1000004",
      "tgn:7024036",
      "tgn:7006651",
      "tgn:7029392"
    ],
    "placetype": [
      "aat:300008347",
      "aat:300387220",
      "aat:300008375"
    ],
    "name:en": "Gugark'",
    "id": 7024067
  }
}
