{
  "geometry": {
    "type": "Point",
    "coordinates": [
      -120.75,
      43.7667
    ]
  },
  "type": "Feature",
  "properties": {
    "hierarchy": [
      "tgn:2583517",
      "tgn:1000001",
      "tgn:2001705",
      "tgn:7012149",
      "tgn:7007708",
      "tgn:7029392"
    ],
    "placetype": [
      "aat:300266640"
    ],
    "id": 2583517,
    "name:xx": "Pine Ridge"
  }
}
