{
  "geometry": {
    "type": "Point",
    "coordinates": [
      -120.4833,
      44.9667
    ]
  },
  "type": "Feature",
  "properties": {
    "hierarchy": [
      "tgn:2169324",
      "tgn:1000001",
      "tgn:7012149",
      "tgn:1002990",
      "tgn:7007708",
      "tgn:7029392"
    ],
    "placetype": [
      "aat:300008680"
    ],
    "id": 2169324,
    "name:xx": "Big Lake"
  }
}
