{
  "geometry": {
    "type": "Point",
    "coordinates": [
      57.95,
      50.2333
    ]
  },
  "type": "Feature",
  "properties": {
    "hierarchy": [
      "tgn:1057749",
      "tgn:7011450",
      "tgn:1000004",
      "tgn:7014786",
      "tgn:7029392"
    ],
    "placetype": [
      "aat:300008347"
    ],
    "id": 1057749,
    "name:xx": "Novorossiyskiy"
  }
}
