{
  "geometry": {
    "type": "Point",
    "coordinates": [
      -73.7167,
      43.4833
    ]
  },
  "type": "Feature",
  "properties": {
    "hierarchy": [
      "tgn:2158118",
      "tgn:1000001",
      "tgn:7012149",
      "tgn:1002986",
      "tgn:7007568",
      "tgn:7029392"
    ],
    "placetype": [
      "aat:300008680"
    ],
    "id": 2158118,
    "name:xx": "Beaver Pond"
  }
}
