{
  "geometry": {
    "type": "Point",
    "coordinates": [
      -110.8833,
      47.3333
    ]
  },
  "type": "Feature",
  "properties": {
    "hierarchy": [
      "tgn:2137246",
      "tgn:1000001",
      "tgn:2001266",
      "tgn:7012149",
      "tgn:7007524",
      "tgn:7029392"
    ],
    "placetype": [
      "aat:300008347"
    ],
    "id": 2137246,
    "name:xx": "Armington Junction"
  }
}
