{
  "geometry": {
    "type": "Point",
    "coordinates": [
      -99.963,
      27.116
    ]
  },
  "type": "Feature",
  "properties": {
    "hierarchy": [
      "tgn:1132680",
      "tgn:1000001",
      "tgn:7005589",
      "tgn:7005560",
      "tgn:7029392"
    ],
    "placetype": [
      "aat:300266554",
      "aat:300008706",
      "aat:300008699"
    ],
    "id": 1132680,
    "name:xx": "Camarón"
  }
}
