{
  "geometry": {
    "type": "Point",
    "coordinates": [
      -82.15,
      33.55
    ]
  },
  "type": "Feature",
  "properties": {
    "hierarchy": [
      "tgn:2663682",
      "tgn:1000001",
      "tgn:2000327",
      "tgn:7012149",
      "tgn:7007248",
      "tgn:7029392"
    ],
    "placetype": [
      "aat:300006191"
    ],
    "id": 2663682,
    "name:xx": "Silver Lake"
  }
}
