{
  "geometry": {
    "type": "Point",
    "coordinates": [
      31.3115,
      30.123504
    ]
  },
  "type": "Feature",
  "properties": {
    "hierarchy": [
      "tgn:1003936",
      "tgn:7001242",
      "tgn:7016833",
      "tgn:1001091",
      "tgn:7029392"
    ],
    "placetype": [
      "aat:300000745"
    ],
    "id": 1003936,
    "name:xx": "Al Maṭarīyah"
  }
}
