{
  "geometry": {
    "type": "Point",
    "coordinates": [
      12.5167,
      50.6667
    ]
  },
  "type": "Feature",
  "properties": {
    "hierarchy": [
      "tgn:1037996",
      "tgn:1000003",
      "tgn:7003685",
      "tgn:7000084",
      "tgn:7029392"
    ],
    "placetype": [
      "aat:300008347"
    ],
    "id": 1037996,
    "name:xx": "Wilkau-Hasslau"
  }
}
