{
  "geometry": {
    "type": "Point",
    "coordinates": [
      -123.3167,
      45.3167
    ]
  },
  "type": "Feature",
  "properties": {
    "hierarchy": [
      "tgn:2527847",
      "tgn:1000001",
      "tgn:7012149",
      "tgn:1003044",
      "tgn:7007708",
      "tgn:7029392"
    ],
    "placetype": [
      "aat:300008347"
    ],
    "id": 2527847,
    "name:xx": "Mountain House"
  }
}
