{
  "geometry": {
    "type": "Point",
    "coordinates": [
      -83.8833,
      35.65
    ]
  },
  "type": "Feature",
  "properties": {
    "hierarchy": [
      "tgn:2315506",
      "tgn:1000001",
      "tgn:2001841",
      "tgn:7012149",
      "tgn:7007825",
      "tgn:7029392"
    ],
    "placetype": [
      "aat:300008798"
    ],
    "id": 2315506,
    "name:xx": "Ellis Butt"
  }
}
