{
  "geometry": {
    "type": "Point",
    "coordinates": [
      90.5833,
      23.4167
    ]
  },
  "type": "Feature",
  "properties": {
    "hierarchy": [
      "tgn:7001674",
      "tgn:1000004",
      "tgn:7029392"
    ],
    "placetype": [
      "aat:300008707",
      "aat:300386998"
    ],
    "name:en": "Ganges, River",
    "id": 7001674
  }
}
