{
  "geometry": {
    "type": "Point",
    "coordinates": [
      31.533687,
      30.061154
    ]
  },
  "type": "Feature",
  "properties": {
    "hierarchy": [
      "tgn:7531624",
      "tgn:7001242",
      "tgn:7016833",
      "tgn:7029392"
    ],
    "placetype": [
      "aat:300379998"
    ],
    "id": 7531624,
    "name:xx": "Nāşūrī, Wādī an"
  }
}
