{
  "geometry": {
    "type": "Point",
    "coordinates": [
      -96.183333,
      17.95
    ]
  },
  "type": "Feature",
  "properties": {
    "hierarchy": [
      "tgn:7394575",
      "tgn:1000001",
      "tgn:7005591",
      "tgn:7005560",
      "tgn:7029392"
    ],
    "placetype": [
      "aat:300008347"
    ],
    "id": 7394575,
    "name:xx": "San José Chiltepec"
  }
}
