{
  "geometry": {
    "type": "Point",
    "coordinates": [
      -155.05,
      19.65
    ]
  },
  "type": "Feature",
  "properties": {
    "hierarchy": [
      "tgn:2566535",
      "tgn:7023902",
      "tgn:1000001",
      "tgn:7012149",
      "tgn:7007249",
      "tgn:7029392"
    ],
    "placetype": [
      "aat:300008863"
    ],
    "id": 2566535,
    "name:xx": "Panaewa Forest Reserve"
  }
}
