{
  "geometry": {
    "type": "Point",
    "coordinates": [
      -108.0667,
      47.1833
    ]
  },
  "type": "Feature",
  "properties": {
    "hierarchy": [
      "tgn:2371864",
      "tgn:1000001",
      "tgn:7012149",
      "tgn:2001294",
      "tgn:7007524",
      "tgn:7029392"
    ],
    "placetype": [
      "aat:300008761"
    ],
    "id": 2371864,
    "name:xx": "Haley Coulee"
  }
}
