{
  "geometry": {
    "type": "Point",
    "coordinates": [
      -79.1667,
      41.0833
    ]
  },
  "type": "Feature",
  "properties": {
    "hierarchy": [
      "tgn:2089192",
      "tgn:1000001",
      "tgn:7012149",
      "tgn:1002520",
      "tgn:7007710",
      "tgn:7029392"
    ],
    "placetype": [
      "aat:300008347"
    ],
    "id": 2089192,
    "name:xx": "Heathville"
  }
}
