{
  "geometry": {
    "type": "Point",
    "coordinates": [
      -97.85,
      30.7667
    ]
  },
  "type": "Feature",
  "properties": {
    "hierarchy": [
      "tgn:2102365",
      "tgn:1000001",
      "tgn:7012149",
      "tgn:1003026",
      "tgn:7007826",
      "tgn:7029392"
    ],
    "placetype": [
      "aat:300008347"
    ],
    "id": 2102365,
    "name:xx": "Andice"
  }
}
