{
  "geometry": {
    "type": "Point",
    "coordinates": [
      31.24462,
      30.072881
    ]
  },
  "type": "Feature",
  "properties": {
    "hierarchy": [
      "tgn:7531927",
      "tgn:7001242",
      "tgn:7016833",
      "tgn:1001091",
      "tgn:7029392"
    ],
    "placetype": [
      "aat:300006036"
    ],
    "id": 7531927,
    "name:xx": "Barīd Shubrā"
  }
}
