{
  "geometry": {
    "type": "Point",
    "coordinates": [
      -115.9333,
      42.2333
    ]
  },
  "type": "Feature",
  "properties": {
    "hierarchy": [
      "tgn:2721841",
      "tgn:1000001",
      "tgn:7012149",
      "tgn:2000488",
      "tgn:7007250",
      "tgn:7029392"
    ],
    "placetype": [
      "aat:300006191"
    ],
    "id": 2721841,
    "name:xx": "Timber Draw Reservoir"
  }
}
