{
  "geometry": {
    "type": "Point",
    "coordinates": [
      -90.6167,
      30.2167
    ]
  },
  "type": "Feature",
  "properties": {
    "hierarchy": [
      "tgn:2130599",
      "tgn:1000001",
      "tgn:7012149",
      "tgn:7007256",
      "tgn:7029392"
    ],
    "placetype": [
      "aat:300008791"
    ],
    "id": 2130599,
    "name:xx": "Alligator Island"
  }
}
