{
  "geometry": {
    "type": "Point",
    "coordinates": [
      -92.4167,
      40.0833
    ]
  },
  "type": "Feature",
  "properties": {
    "hierarchy": [
      "tgn:2058879",
      "tgn:1002133",
      "tgn:1000001",
      "tgn:7012149",
      "tgn:7007523",
      "tgn:7029392"
    ],
    "placetype": [
      "aat:300008347"
    ],
    "id": 2058879,
    "name:xx": "Gibbs"
  }
}
