{
  "geometry": {
    "type": "Point",
    "coordinates": [
      -84.0333,
      32.7833
    ]
  },
  "type": "Feature",
  "properties": {
    "hierarchy": [
      "tgn:2296094",
      "tgn:1000001",
      "tgn:7012149",
      "tgn:2000330",
      "tgn:7007248",
      "tgn:7029392"
    ],
    "placetype": [
      "aat:300008699"
    ],
    "id": 2296094,
    "name:xx": "Dry Branch"
  }
}
