{
  "geometry": {
    "type": "Point",
    "coordinates": [
      -80.9667,
      38.0167
    ]
  },
  "type": "Feature",
  "properties": {
    "hierarchy": [
      "tgn:2621040",
      "tgn:1000001",
      "tgn:2002261",
      "tgn:7012149",
      "tgn:7013961",
      "tgn:7029392"
    ],
    "placetype": [
      "aat:300008699"
    ],
    "id": 2621040,
    "name:xx": "Road Fork"
  }
}
