{
  "geometry": {
    "type": "Point",
    "coordinates": [
      -81.1833,
      36.75
    ]
  },
  "type": "Feature",
  "properties": {
    "hierarchy": [
      "tgn:2732887",
      "tgn:1000001",
      "tgn:7012149",
      "tgn:2002164",
      "tgn:7007919",
      "tgn:7029392"
    ],
    "placetype": [
      "aat:300008699"
    ],
    "id": 2732887,
    "name:xx": "Turkey Fork"
  }
}
