{
  "geometry": {
    "type": "Point",
    "coordinates": [
      -79.35,
      37.5333
    ]
  },
  "type": "Feature",
  "properties": {
    "hierarchy": [
      "tgn:2110658",
      "tgn:1000001",
      "tgn:2002144",
      "tgn:7012149",
      "tgn:7007919",
      "tgn:7029392"
    ],
    "placetype": [
      "aat:300008347"
    ],
    "id": 2110658,
    "name:xx": "Big Island"
  }
}
