{
  "geometry": {
    "type": "Point",
    "coordinates": [
      -85.2667,
      36.2667
    ]
  },
  "type": "Feature",
  "properties": {
    "hierarchy": [
      "tgn:2379200",
      "tgn:1000001",
      "tgn:7012149",
      "tgn:2001903",
      "tgn:7007825",
      "tgn:7029392"
    ],
    "placetype": [
      "aat:300008761"
    ],
    "id": 2379200,
    "name:xx": "Hartsaw Cove"
  }
}
