{
  "geometry": {
    "type": "Point",
    "coordinates": [
      -78.7667,
      37.75
    ]
  },
  "type": "Feature",
  "properties": {
    "hierarchy": [
      "tgn:2157494",
      "tgn:1000001",
      "tgn:7012149",
      "tgn:2002175",
      "tgn:7007919",
      "tgn:7029392"
    ],
    "placetype": [
      "aat:300008706"
    ],
    "id": 2157494,
    "name:xx": "Beaver Creek"
  }
}
