{
  "geometry": {
    "type": "Point",
    "coordinates": [
      83.782265,
      25.39714
    ]
  },
  "type": "Feature",
  "properties": {
    "hierarchy": [
      "tgn:7549959",
      "tgn:1000004",
      "tgn:1001842",
      "tgn:7000198",
      "tgn:7029392"
    ],
    "placetype": [
      "aat:300008699"
    ],
    "name:en": "Dharmautī Nadī",
    "id": 7549959
  }
}
