{
  "geometry": {
    "type": "Point",
    "coordinates": [
      -46.3667,
      -21.2833
    ]
  },
  "type": "Feature",
  "properties": {
    "hierarchy": [
      "tgn:1021907",
      "tgn:7006237",
      "tgn:1000047",
      "tgn:7002457",
      "tgn:1000002",
      "tgn:7029392"
    ],
    "placetype": [
      "aat:300008347"
    ],
    "id": 1021907,
    "name:xx": "Juréia"
  }
}
