{
  "geometry": {
    "type": "Point",
    "coordinates": [
      -82.4833,
      36.8167
    ]
  },
  "type": "Feature",
  "properties": {
    "hierarchy": [
      "tgn:2270834",
      "tgn:1000001",
      "tgn:7012149",
      "tgn:2002189",
      "tgn:7007919",
      "tgn:7029392"
    ],
    "placetype": [
      "aat:300008706"
    ],
    "id": 2270834,
    "name:xx": "Cub Creek"
  }
}
