{
  "geometry": {
    "type": "Point",
    "coordinates": [
      -91.15,
      35.7333
    ]
  },
  "type": "Feature",
  "properties": {
    "hierarchy": [
      "tgn:2706717",
      "tgn:1000001",
      "tgn:7016172",
      "tgn:7012149",
      "tgn:2000138",
      "tgn:7029392"
    ],
    "placetype": [
      "aat:300006075"
    ],
    "id": 2706717,
    "name:xx": "Swan Pond Ditch"
  }
}
