{
  "geometry": {
    "type": "Point",
    "coordinates": [
      -108.8333,
      39.9167
    ]
  },
  "type": "Feature",
  "properties": {
    "hierarchy": [
      "tgn:2168844",
      "tgn:1000001",
      "tgn:7012149",
      "tgn:7007158",
      "tgn:2000243",
      "tgn:7029392"
    ],
    "placetype": [
      "aat:300006191"
    ],
    "id": 2168844,
    "name:xx": "Big Horse Draw Reservoir"
  }
}
