{
  "geometry": {
    "type": "Point",
    "coordinates": [
      -105.65,
      39.9333
    ]
  },
  "type": "Feature",
  "properties": {
    "hierarchy": [
      "tgn:2420845",
      "tgn:1000001",
      "tgn:7012149",
      "tgn:7007158",
      "tgn:7029392"
    ],
    "placetype": [
      "aat:300008706"
    ],
    "id": 2420845,
    "name:xx": "Jenny Creek"
  }
}
