{
  "geometry": {
    "type": "Point",
    "coordinates": [
      -83.6833,
      37.1667
    ]
  },
  "type": "Feature",
  "properties": {
    "hierarchy": [
      "tgn:2451934",
      "tgn:1000001",
      "tgn:2000782",
      "tgn:7012149",
      "tgn:7007255",
      "tgn:7029392"
    ],
    "placetype": [
      "aat:300008706"
    ],
    "id": 2451934,
    "name:xx": "Little Beech Creek"
  }
}
