{
  "geometry": {
    "type": "Point",
    "coordinates": [
      72.8833,
      40.8667
    ]
  },
  "type": "Feature",
  "properties": {
    "hierarchy": [
      "tgn:1125775",
      "tgn:1000004",
      "tgn:7029392"
    ],
    "placetype": [
      "aat:300008707"
    ],
    "id": 1125775,
    "name:xx": "Kugart"
  }
}
