{
  "geometry": {
    "type": "Point",
    "coordinates": [
      -81.75,
      36.85
    ]
  },
  "type": "Feature",
  "properties": {
    "hierarchy": [
      "tgn:2501621",
      "tgn:1000001",
      "tgn:7012149",
      "tgn:7007919",
      "tgn:7029392"
    ],
    "placetype": [
      "aat:300008706"
    ],
    "id": 2501621,
    "name:xx": "McHenry Creek"
  }
}
