{
  "geometry": {
    "type": "Point",
    "coordinates": [
      -81.5333,
      40.8333
    ]
  },
  "type": "Feature",
  "properties": {
    "hierarchy": [
      "tgn:2257471",
      "tgn:1000001",
      "tgn:7012149",
      "tgn:1002917",
      "tgn:7007706",
      "tgn:7029392"
    ],
    "placetype": [
      "aat:300006191"
    ],
    "id": 2257471,
    "name:xx": "Coronado Lake"
  }
}
