{
  "geometry": {
    "type": "Point",
    "coordinates": [
      88.172222,
      22.796944
    ]
  },
  "type": "Feature",
  "properties": {
    "hierarchy": [
      "tgn:1075148",
      "tgn:1000004",
      "tgn:7000198",
      "tgn:1001977",
      "tgn:7029392"
    ],
    "placetype": [
      "aat:300008347"
    ],
    "name:en": "Dhānyahānā",
    "id": 1075148
  }
}
