{
  "geometry": {
    "type": "Point",
    "coordinates": [
      -117.55,
      47.55
    ]
  },
  "type": "Feature",
  "properties": {
    "hierarchy": [
      "tgn:2536830",
      "tgn:1000001",
      "tgn:7012149",
      "tgn:2002249",
      "tgn:7007920",
      "tgn:7029392"
    ],
    "placetype": [
      "aat:300008798"
    ],
    "id": 2536830,
    "name:xx": "Needham Hill"
  }
}
