{
  "geometry": {
    "type": "Point",
    "coordinates": [
      -44.3667,
      -23.05
    ]
  },
  "type": "Feature",
  "properties": {
    "hierarchy": [
      "tgn:1007549",
      "tgn:1001942",
      "tgn:1000047",
      "tgn:7002457",
      "tgn:1000002",
      "tgn:7029392"
    ],
    "placetype": [
      "aat:300008791"
    ],
    "id": 1007549,
    "name:xx": "Jibóia, Ilha da"
  }
}
