{
  "geometry": {
    "type": "Point",
    "coordinates": [
      -106.1167,
      35.3333
    ]
  },
  "type": "Feature",
  "properties": {
    "hierarchy": [
      "tgn:2291738",
      "tgn:1000001",
      "tgn:7012149",
      "tgn:2001454",
      "tgn:7007566",
      "tgn:7029392"
    ],
    "placetype": [
      "aat:300008347",
      "aat:300167671"
    ],
    "id": 2291738,
    "name:xx": "Dolores"
  }
}
