{
  "geometry": {
    "type": "Point",
    "coordinates": [
      -87.1833,
      33.0333
    ]
  },
  "type": "Feature",
  "properties": {
    "hierarchy": [
      "tgn:2672158",
      "tgn:7002659",
      "tgn:1000001",
      "tgn:2000003",
      "tgn:7012149",
      "tgn:7029392"
    ],
    "placetype": [
      "aat:300008347"
    ],
    "id": 2672158,
    "name:xx": "Smiths Ford"
  }
}
