{
  "geometry": {
    "type": "Point",
    "coordinates": [
      -76.0167,
      38.9667
    ]
  },
  "type": "Feature",
  "properties": {
    "hierarchy": [
      "tgn:2550822",
      "tgn:1000001",
      "tgn:7012149",
      "tgn:7007516",
      "tgn:7029392"
    ],
    "placetype": [
      "aat:300008706"
    ],
    "id": 2550822,
    "name:xx": "Norwich Creek"
  }
}
