{
  "geometry": {
    "type": "Point",
    "coordinates": [
      -156.9667,
      67.0333
    ]
  },
  "type": "Feature",
  "properties": {
    "hierarchy": [
      "tgn:2147025",
      "tgn:7006450",
      "tgn:1000001",
      "tgn:7012149",
      "tgn:2124014",
      "tgn:7029392"
    ],
    "placetype": [
      "aat:300008798"
    ],
    "id": 2147025,
    "name:xx": "Bannock Mountain"
  }
}
