{
  "geometry": {
    "type": "Point",
    "coordinates": [
      -100.35,
      31.9333
    ]
  },
  "type": "Feature",
  "properties": {
    "hierarchy": [
      "tgn:2732780",
      "tgn:1000001",
      "tgn:7012149",
      "tgn:2001958",
      "tgn:7007826",
      "tgn:7029392"
    ],
    "placetype": [
      "aat:300008706"
    ],
    "id": 2732780,
    "name:xx": "Turkey Creek"
  }
}
