{
  "geometry": {
    "type": "Point",
    "coordinates": [
      72.6833,
      41.8333
    ]
  },
  "type": "Feature",
  "properties": {
    "hierarchy": [
      "tgn:1056207",
      "tgn:1000004",
      "tgn:7011478",
      "tgn:7006655",
      "tgn:7029392"
    ],
    "placetype": [
      "aat:300008347"
    ],
    "id": 1056207,
    "name:xx": "Kyrkkazyk"
  }
}
