{
  "geometry": {
    "type": "Point",
    "coordinates": [
      -79.0833,
      41.8833
    ]
  },
  "type": "Feature",
  "properties": {
    "hierarchy": [
      "tgn:2355654",
      "tgn:1000001",
      "tgn:7012149",
      "tgn:1002988",
      "tgn:7007710",
      "tgn:7029392"
    ],
    "placetype": [
      "aat:300008798"
    ],
    "id": 2355654,
    "name:xx": "Goose Heaven Hill"
  }
}
