{
  "geometry": {
    "type": "Point",
    "coordinates": [
      -38.9167,
      -13.6333
    ]
  },
  "type": "Feature",
  "properties": {
    "hierarchy": [
      "tgn:1006556",
      "tgn:1001834",
      "tgn:1000047",
      "tgn:7002455",
      "tgn:1000002",
      "tgn:7029392"
    ],
    "placetype": [
      "aat:300008791"
    ],
    "id": 1006556,
    "name:xx": "Boipeba, Ilha"
  }
}
