{
  "geometry": {
    "type": "Point",
    "coordinates": [
      58.7667,
      34.35
    ]
  },
  "type": "Feature",
  "properties": {
    "hierarchy": [
      "tgn:1078988",
      "tgn:1000004",
      "tgn:7016768",
      "tgn:7000231",
      "tgn:7029392"
    ],
    "placetype": [
      "aat:300008347"
    ],
    "id": 1078988,
    "name:xx": "Bīdokht"
  }
}
