{
  "geometry": {
    "type": "Point",
    "coordinates": [
      -76.0833,
      44.2667
    ]
  },
  "type": "Feature",
  "properties": {
    "hierarchy": [
      "tgn:2633958",
      "tgn:1000001",
      "tgn:7012149",
      "tgn:1002518",
      "tgn:7007568",
      "tgn:7029392"
    ],
    "placetype": [
      "aat:300132316"
    ],
    "id": 2633958,
    "name:xx": "Rusho Bay"
  }
}
