{
  "type": "FeatureCollection",
  "features": [
    {
      "geometry": {
        "type": "Point",
        "coordinates": [
          -85.15,
          30.6167
        ]
      },
      "type": "Feature",
      "properties": {
        "hierarchy": [
          "tgn:2021290",
          "tgn:1000001",
          "tgn:2000273",
          "tgn:7012149",
          "tgn:7007240",
          "tgn:7029392"
        ],
        "placetype": [
          "aat:300008347"
        ],
        "id": 2021290,
        "name:xx": "Sink Creek"
      }
    },
    {
      "geometry": {
        "type": "Point",
        "coordinates": [
          -83.65,
          30.35
        ]
      },
      "type": "Feature",
      "properties": {
        "hierarchy": [
          "tgn:2021291",
          "tgn:1000001",
          "tgn:7012149",
          "tgn:2000279",
          "tgn:7007240",
          "tgn:7029392"
        ],
        "placetype": [
          "aat:300008347"
        ],
        "id": 2021291,
        "name:xx": "Sirmans"
      }
    },
    {
      "geometry": {
        "type": "Point",
        "coordinates": [
          -81.3833,
          28.45
        ]
      },
      "type": "Feature",
      "properties": {
        "hierarchy": [
          "tgn:2021293",
          "tgn:1000001",
          "tgn:7012149",
          "tgn:1002749",
          "tgn:7007240",
          "tgn:7029392"
        ],
        "placetype": [
          "aat:300008347"
        ],
        "id": 2021293,
        "name:xx": "Sky Lake"
      }
    },
    {
      "geometry": {
        "type": "Point",
        "coordinates": [
          -81.2167,
          28.6333
        ]
      },
      "type": "Feature",
      "properties": {
        "hierarchy": [
          "tgn:2021298",
          "tgn:1000001",
          "tgn:7012149",
          "tgn:1002881",
          "tgn:7007240",
          "tgn:7029392"
        ],
        "placetype": [
          "aat:300008347",
          "aat:300387210"
        ],
        "id": 2021298,
        "name:xx": "Slavia"
      }
    }
  ]
}
