{
  "geometry": {
    "type": "Point",
    "coordinates": [
      -116.3833,
      48.9667
    ]
  },
  "type": "Feature",
  "properties": {
    "hierarchy": [
      "tgn:2372608",
      "tgn:1000001",
      "tgn:2000462",
      "tgn:7012149",
      "tgn:7007250",
      "tgn:7029392"
    ],
    "placetype": [
      "aat:300008706"
    ],
    "id": 2372608,
    "name:xx": "Hall Creek"
  }
}
