{
  "geometry": {
    "type": "Point",
    "coordinates": [
      26.4833,
      50.3333
    ]
  },
  "type": "Feature",
  "properties": {
    "hierarchy": [
      "tgn:1058071",
      "tgn:1000003",
      "tgn:7011667",
      "tgn:7006660",
      "tgn:7029392"
    ],
    "placetype": [
      "aat:300008347"
    ],
    "id": 1058071,
    "name:xx": "Ostroh"
  }
}
