{
  "geometry": {
    "type": "Point",
    "coordinates": [
      82.233333,
      19.55
    ]
  },
  "type": "Feature",
  "properties": {
    "hierarchy": [
      "tgn:7575354",
      "tgn:1000004",
      "tgn:7031781",
      "tgn:7000198",
      "tgn:7029392"
    ],
    "placetype": [
      "aat:300008347"
    ],
    "name:en": "Kerāgān",
    "id": 7575354
  }
}
