{
  "type": "FeatureCollection",
  "features": [
    {
      "geometry": {
        "type": "Point",
        "coordinates": [
          -138.7167,
          59.9
        ]
      },
      "type": "Feature",
      "properties": {
        "hierarchy": [
          "tgn:2137290",
          "tgn:7006450",
          "tgn:1000001",
          "tgn:7012149",
          "tgn:7030574",
          "tgn:7029392"
        ],
        "placetype": [
          "aat:300008798"
        ],
        "id": 2137290,
        "name:xx": "Armour, Mount"
      }
    },
    {
      "geometry": {
        "type": "Point",
        "coordinates": [
          -99.4,
          48.8667
        ]
      },
      "type": "Feature",
      "properties": {
        "hierarchy": [
          "tgn:2137291",
          "tgn:1000001",
          "tgn:7012149",
          "tgn:2001604",
          "tgn:7007705",
          "tgn:7029392"
        ],
        "placetype": [
          "aat:300006191"
        ],
        "id": 2137291,
        "name:xx": "Armourdale Lake"
      }
    },
    {
      "geometry": {
        "type": "Point",
        "coordinates": [
          -72.6333,
          42.6
        ]
      },
      "type": "Feature",
      "properties": {
        "hierarchy": [
          "tgn:2137293",
          "tgn:1000001",
          "tgn:7013942",
          "tgn:7012149",
          "tgn:7007517",
          "tgn:7029392"
        ],
        "placetype": [
          "aat:300008699"
        ],
        "id": 2137293,
        "name:xx": "Arms Brook"
      }
    },
    {
      "geometry": {
        "type": "Point",
        "coordinates": [
          -113.5167,
          39.0167
        ]
      },
      "type": "Feature",
      "properties": {
        "hierarchy": [
          "tgn:2137294",
          "tgn:1000001",
          "tgn:7012149",
          "tgn:2002114",
          "tgn:7007827",
          "tgn:7029392"
        ],
        "placetype": [
          "aat:300008761"
        ],
        "id": 2137294,
        "name:xx": "Arms Canyon"
      }
    },
    {
      "geometry": {
        "type": "Point",
        "coordinates": [
          -83.8,
          42.3667
        ]
      },
      "type": "Feature",
      "properties": {
        "hierarchy": [
          "tgn:2137295",
          "tgn:1000001",
          "tgn:7012149",
          "tgn:7007520",
          "tgn:7029392"
        ],
        "placetype": [
          "aat:300008706"
        ],
        "id": 2137295,
        "name:xx": "Arms Creek"
      }
    },
    {
      "geometry": {
        "type": "Point",
        "coordinates": [
          -88.2,
          35.7
        ]
      },
      "type": "Feature",
      "properties": {
        "hierarchy": [
          "tgn:2137296",
          "tgn:1000001",
          "tgn:7012149",
          "tgn:7007825",
          "tgn:7029392"
        ],
        "placetype": [
          "aat:300008706"
        ],
        "id": 2137296,
        "name:xx": "Arms Creek"
      }
    },
    {
      "geometry": {
        "type": "Point",
        "coordinates": [
          -94.7,
          32.7333
        ]
      },
      "type": "Feature",
      "properties": {
        "hierarchy": [
          "tgn:2137297",
          "tgn:1000001",
          "tgn:7012149",
          "tgn:7007826",
          "tgn:7029392"
        ],
        "placetype": [
          "aat:300008706"
        ],
        "id": 2137297,
        "name:xx": "Arms Creek"
      }
    },
    {
      "geometry": {
        "type": "Point",
        "coordinates": [
          -70.65,
          41.95
        ]
      },
      "type": "Feature",
      "properties": {
        "hierarchy": [
          "tgn:2137298",
          "tgn:1000001",
          "tgn:7014423",
          "tgn:7012149",
          "tgn:7007517",
          "tgn:7029392"
        ],
        "placetype": [
          "aat:300006191"
        ],
        "id": 2137298,
        "name:xx": "Arms House Pond"
      }
    },
    {
      "geometry": {
        "type": "Point",
        "coordinates": [
          -84.1333,
          33.0667
        ]
      },
      "type": "Feature",
      "properties": {
        "hierarchy": [
          "tgn:2137299",
          "tgn:1000001",
          "tgn:7012149",
          "tgn:2000376",
          "tgn:7007248",
          "tgn:7029392"
        ],
        "placetype": [
          "aat:300006191"
        ],
        "id": 2137299,
        "name:xx": "Arms Lake"
      }
    }
  ]
}
