{
  "type": "FeatureCollection",
  "features": [
    {
      "geometry": {
        "type": "Point",
        "coordinates": [
          -0.316667,
          51.6
        ]
      },
      "type": "Feature",
      "properties": {
        "hierarchy": [
          "tgn:7452731",
          "tgn:7002445",
          "tgn:7018918",
          "tgn:1000003",
          "tgn:7008136",
          "tgn:7008591",
          "tgn:7029392"
        ],
        "placetype": [
          "aat:300008347",
          "aat:300000745"
        ],
        "name:en": "Harrow Weald",
        "id": 7452731
      }
    },
    {
      "geometry": {
        "type": "Point",
        "coordinates": [
          -1.55,
          54.55
        ]
      },
      "type": "Feature",
      "properties": {
        "hierarchy": [
          "tgn:7452733",
          "tgn:7002445",
          "tgn:1000003",
          "tgn:7026514",
          "tgn:7008591",
          "tgn:7029392"
        ],
        "placetype": [
          "aat:300000745"
        ],
        "name:en": "Harrowgate Hill",
        "id": 7452733
      }
    },
    {
      "geometry": {
        "type": "Point",
        "coordinates": [
          -0.716667,
          52.316667
        ]
      },
      "type": "Feature",
      "properties": {
        "hierarchy": [
          "tgn:7452734",
          "tgn:7002445",
          "tgn:1000003",
          "tgn:7012031",
          "tgn:7008591",
          "tgn:7029392"
        ],
        "placetype": [
          "aat:300008347"
        ],
        "name:en": "Harrowden",
        "id": 7452734
      }
    },
    {
      "geometry": {
        "type": "Point",
        "coordinates": [
          -4.316667,
          55.15
        ]
      },
      "type": "Feature",
      "properties": {
        "hierarchy": [
          "tgn:7452735",
          "tgn:7002444",
          "tgn:7008074",
          "tgn:1000003",
          "tgn:7008591",
          "tgn:7029392"
        ],
        "placetype": [
          "aat:300008680"
        ],
        "name:en": "Harrow, Loch",
        "id": 7452735
      }
    },
    {
      "geometry": {
        "type": "Point",
        "coordinates": [
          -2.383333,
          53.933333
        ]
      },
      "type": "Feature",
      "properties": {
        "hierarchy": [
          "tgn:7452737",
          "tgn:7002445",
          "tgn:1000003",
          "tgn:7008154",
          "tgn:7008591",
          "tgn:7029392"
        ],
        "placetype": [
          "aat:300008347"
        ],
        "name:en": "Harrop Fold",
        "id": 7452737
      }
    }
  ]
}
