{
  "type": "FeatureCollection",
  "features": [
    {
      "geometry": {
        "type": "Point",
        "coordinates": [
          10.966667,
          44.216667
        ]
      },
      "type": "Feature",
      "properties": {
        "hierarchy": [
          "tgn:7058790",
          "tgn:7003127",
          "tgn:1000003",
          "tgn:7008516",
          "tgn:1000080",
          "tgn:7029392"
        ],
        "placetype": [
          "aat:300008347"
        ],
        "id": 7058790,
        "name:xx": "Bombiana"
      }
    },
    {
      "geometry": {
        "type": "Point",
        "coordinates": [
          11.616667,
          45.6
        ]
      },
      "type": "Feature",
      "properties": {
        "hierarchy": [
          "tgn:7058793",
          "tgn:7003008",
          "tgn:1000003",
          "tgn:7002997",
          "tgn:1000080",
          "tgn:7029392"
        ],
        "placetype": [
          "aat:300008347"
        ],
        "id": 7058793,
        "name:xx": "Bolzano Vicentino"
      }
    },
    {
      "geometry": {
        "type": "Point",
        "coordinates": [
          8.45,
          45.766667
        ]
      },
      "type": "Feature",
      "properties": {
        "hierarchy": [
          "tgn:7058794",
          "tgn:1003478",
          "tgn:1000003",
          "tgn:7003120",
          "tgn:1000080",
          "tgn:7029392"
        ],
        "placetype": [
          "aat:300008347"
        ],
        "id": 7058794,
        "name:xx": "Bolzano Novarese"
      }
    },
    {
      "geometry": {
        "type": "Point",
        "coordinates": [
          13.683333,
          42.383333
        ]
      },
      "type": "Feature",
      "properties": {
        "hierarchy": [
          "tgn:7058798",
          "tgn:7009084",
          "tgn:7004154",
          "tgn:1000003",
          "tgn:1000080",
          "tgn:7029392"
        ],
        "placetype": [
          "aat:300008795"
        ],
        "id": 7058798,
        "name:xx": "Bolza, Monte"
      }
    }
  ]
}
