{
  "geometry": {
    "type": "Point",
    "coordinates": [
      -72.2167,
      42.15
    ]
  },
  "type": "Feature",
  "properties": {
    "hierarchy": [
      "tgn:2712590",
      "tgn:1000001",
      "tgn:7012149",
      "tgn:7007517",
      "tgn:7029392"
    ],
    "placetype": [
      "aat:300008699"
    ],
    "id": 2712590,
    "name:xx": "Taylor Brook"
  }
}
