{
  "type": "FeatureCollection",
  "features": [
    {
      "geometry": {
        "type": "Point",
        "coordinates": [
          -84.6167,
          45.85
        ]
      },
      "type": "Feature",
      "properties": {
        "hierarchy": [
          "tgn:1007960",
          "tgn:1000001",
          "tgn:7012149",
          "tgn:2000973",
          "tgn:7007520",
          "tgn:7029392"
        ],
        "placetype": [
          "aat:300008791"
        ],
        "id": 1007960,
        "name:xx": "Mackinac Island"
      }
    },
    {
      "geometry": {
        "type": "Point",
        "coordinates": [
          123.9667,
          10.2667
        ]
      },
      "type": "Feature",
      "properties": {
        "hierarchy": [
          "tgn:1007962",
          "tgn:1000004",
          "tgn:1001185",
          "tgn:1000135",
          "tgn:7029392"
        ],
        "placetype": [
          "aat:300008791"
        ],
        "id": 1007962,
        "name:xx": "Mactan Island"
      }
    },
    {
      "geometry": {
        "type": "Point",
        "coordinates": [
          122.8167,
          14.4
        ]
      },
      "type": "Feature",
      "properties": {
        "hierarchy": [
          "tgn:1007963",
          "tgn:1009907",
          "tgn:1000004",
          "tgn:1001174",
          "tgn:1000135",
          "tgn:7029392"
        ],
        "placetype": [
          "aat:300008791"
        ],
        "id": 1007963,
        "name:xx": "Maculabo Island"
      }
    },
    {
      "geometry": {
        "type": "Point",
        "coordinates": [
          -60.9667,
          45.5
        ]
      },
      "type": "Feature",
      "properties": {
        "hierarchy": [
          "tgn:1007964",
          "tgn:7005685",
          "tgn:1000001",
          "tgn:7005802",
          "tgn:7029392"
        ],
        "placetype": [
          "aat:300008791"
        ],
        "id": 1007964,
        "name:xx": "Madame, Isle"
      }
    },
    {
      "geometry": {
        "type": "Point",
        "coordinates": [
          9.416667,
          41.233333
        ]
      },
      "type": "Feature",
      "properties": {
        "hierarchy": [
          "tgn:1007966",
          "tgn:7015163",
          "tgn:1000003",
          "tgn:7003121",
          "tgn:1000080",
          "tgn:7029392"
        ],
        "placetype": [
          "aat:300008791"
        ],
        "id": 1007966,
        "name:xx": "Maddalena, Isola"
      }
    },
    {
      "geometry": {
        "type": "Point",
        "coordinates": [
          -90.6833,
          46.8
        ]
      },
      "type": "Feature",
      "properties": {
        "hierarchy": [
          "tgn:1007968",
          "tgn:7024130",
          "tgn:1000001",
          "tgn:7012149",
          "tgn:7007922",
          "tgn:7029392"
        ],
        "placetype": [
          "aat:300008791"
        ],
        "id": 1007968,
        "name:xx": "Madeline Island"
      }
    },
    {
      "geometry": {
        "type": "Point",
        "coordinates": [
          -75.0833,
          -50.25
        ]
      },
      "type": "Feature",
      "properties": {
        "hierarchy": [
          "tgn:1007969",
          "tgn:1001702",
          "tgn:1000049",
          "tgn:1000002",
          "tgn:7029392"
        ],
        "placetype": [
          "aat:300008791"
        ],
        "id": 1007969,
        "name:xx": "Madre de Dios, Isla"
      }
    }
  ]
}
