{
  "geometry": {
    "type": "Point",
    "coordinates": [
      -37.3833,
      -9.7333
    ]
  },
  "type": "Feature",
  "properties": {
    "hierarchy": [
      "tgn:1022287",
      "tgn:7016581",
      "tgn:1000047",
      "tgn:7002455",
      "tgn:1000002",
      "tgn:7029392"
    ],
    "placetype": [
      "aat:300008347"
    ],
    "id": 1022287,
    "name:xx": "Pão de Açúcar"
  }
}
