{
  "geometry": {
    "type": "Point",
    "coordinates": [
      -155.7667,
      20.2333
    ]
  },
  "type": "Feature",
  "properties": {
    "hierarchy": [
      "tgn:2431886",
      "tgn:7023902",
      "tgn:1000001",
      "tgn:7012149",
      "tgn:7007249",
      "tgn:7029392"
    ],
    "placetype": [
      "aat:300008850"
    ],
    "id": 2431886,
    "name:xx": "Kauhola Point"
  }
}
