{
  "geometry": {
    "type": "Point",
    "coordinates": [
      -76.85,
      41.4167
    ]
  },
  "type": "Feature",
  "properties": {
    "hierarchy": [
      "tgn:2094135",
      "tgn:1000001",
      "tgn:7012149",
      "tgn:1002613",
      "tgn:7007710",
      "tgn:7029392"
    ],
    "placetype": [
      "aat:300008347",
      "aat:300387210"
    ],
    "id": 2094135,
    "name:xx": "Wallis Run"
  }
}
