{
  "geometry": {
    "type": "Point",
    "coordinates": [
      -79.8833,
      36.1833
    ]
  },
  "type": "Feature",
  "properties": {
    "hierarchy": [
      "tgn:2494607",
      "tgn:1000001",
      "tgn:7012149",
      "tgn:2001500",
      "tgn:7007709",
      "tgn:7029392"
    ],
    "placetype": [
      "aat:300006191"
    ],
    "id": 2494607,
    "name:xx": "Martin Lake"
  }
}
