{
  "geometry": {
    "type": "Point",
    "coordinates": [
      -96.0167,
      41.75
    ]
  },
  "type": "Feature",
  "properties": {
    "hierarchy": [
      "tgn:2675393",
      "tgn:1000001",
      "tgn:2000603",
      "tgn:7012149",
      "tgn:7007253",
      "tgn:7029392"
    ],
    "placetype": [
      "aat:300006075"
    ],
    "id": 2675393,
    "name:xx": "Soldier River Cutoff"
  }
}
