{
  "geometry": {
    "type": "Point",
    "coordinates": [
      102.8667,
      36.4167
    ]
  },
  "type": "Feature",
  "properties": {
    "hierarchy": [
      "tgn:1073460",
      "tgn:1000004",
      "tgn:1001261",
      "tgn:1000111",
      "tgn:7029392"
    ],
    "placetype": [
      "aat:300008347"
    ],
    "id": 1073460,
    "name:xx": "Yaojie"
  }
}
