{
  "geometry": {
    "type": "Point",
    "coordinates": [
      -86.7167,
      34.3667
    ]
  },
  "type": "Feature",
  "properties": {
    "hierarchy": [
      "tgn:2535534",
      "tgn:7002659",
      "tgn:1000001",
      "tgn:7012149",
      "tgn:2000051",
      "tgn:7029392"
    ],
    "placetype": [
      "aat:300266640"
    ],
    "id": 2535534,
    "name:xx": "Narrow Ridge"
  }
}
