{
  "geometry": {
    "type": "Point",
    "coordinates": [
      -75.8333,
      41.65
    ]
  },
  "type": "Feature",
  "properties": {
    "hierarchy": [
      "tgn:2256607",
      "tgn:1000001",
      "tgn:7012149",
      "tgn:1002932",
      "tgn:7007710",
      "tgn:7029392"
    ],
    "placetype": [
      "aat:300008680"
    ],
    "id": 2256607,
    "name:xx": "Cord Pond"
  }
}
