{
  "geometry": {
    "type": "Point",
    "coordinates": [
      -77.806,
      -8.631
    ]
  },
  "type": "Feature",
  "properties": {
    "hierarchy": [
      "tgn:7593357",
      "tgn:7593353",
      "tgn:1000001",
      "tgn:7005565",
      "tgn:7029392"
    ],
    "placetype": [
      "aat:300008347"
    ],
    "id": 7593357,
    "name:xx": "Membrillo"
  }
}
