{
  "geometry": {
    "type": "Point",
    "coordinates": [
      31.654865,
      29.225739
    ]
  },
  "type": "Feature",
  "properties": {
    "hierarchy": [
      "tgn:7528231",
      "tgn:7001242",
      "tgn:7016833",
      "tgn:7029392"
    ],
    "placetype": [
      "aat:300379998"
    ],
    "id": 7528231,
    "name:xx": "Abū Qarn, Wādī"
  }
}
