{
  "geometry": {
    "type": "Point",
    "coordinates": [
      -113.8333,
      39.9167
    ]
  },
  "type": "Feature",
  "properties": {
    "hierarchy": [
      "tgn:2560943",
      "tgn:1000001",
      "tgn:7012149",
      "tgn:2002123",
      "tgn:7007827",
      "tgn:7029392"
    ],
    "placetype": [
      "aat:300000390"
    ],
    "id": 2560943,
    "name:xx": "Oro del Rey Mine"
  }
}
