{
  "geometry": {
    "type": "Point",
    "coordinates": [
      3.4167,
      8.9167
    ]
  },
  "type": "Feature",
  "properties": {
    "hierarchy": [
      "tgn:1092055",
      "tgn:7001242",
      "tgn:1001888",
      "tgn:1000182",
      "tgn:7029392"
    ],
    "placetype": [
      "aat:300008347"
    ],
    "id": 1092055,
    "name:xx": "Ilesha Ibarida"
  }
}
