{
  "geometry": {
    "type": "Point",
    "coordinates": [
      45.3333,
      56.5333
    ]
  },
  "type": "Feature",
  "properties": {
    "hierarchy": [
      "tgn:1057403",
      "tgn:1000004",
      "tgn:7011585",
      "tgn:7018214",
      "tgn:7002435",
      "tgn:7029392"
    ],
    "placetype": [
      "aat:300008347"
    ],
    "id": 1057403,
    "name:xx": "Nestiary"
  }
}
