{
  "geometry": {
    "type": "Point",
    "coordinates": [
      -70.0833,
      44.7667
    ]
  },
  "type": "Feature",
  "properties": {
    "hierarchy": [
      "tgn:2327544",
      "tgn:1000001",
      "tgn:2000921",
      "tgn:7012149",
      "tgn:7007515",
      "tgn:7029392"
    ],
    "placetype": [
      "aat:300008699"
    ],
    "id": 2327544,
    "name:xx": "Fish Brook"
  }
}
