{
  "type": "FeatureCollection",
  "features": [
    {
      "geometry": {
        "type": "Point",
        "coordinates": [
          -70.6,
          -32.966667
        ]
      },
      "type": "Feature",
      "properties": {
        "hierarchy": [
          "tgn:7317500",
          "tgn:1001768",
          "tgn:1000049",
          "tgn:1000002",
          "tgn:7029392"
        ],
        "placetype": [
          "aat:300008795"
        ],
        "id": 7317500,
        "name:xx": "Cobre de Chacabuco, Cerro"
      }
    },
    {
      "geometry": {
        "type": "Point",
        "coordinates": [
          -71.116667,
          -32.466667
        ]
      },
      "type": "Feature",
      "properties": {
        "hierarchy": [
          "tgn:7317501",
          "tgn:1001768",
          "tgn:1000049",
          "tgn:1000002",
          "tgn:7029392"
        ],
        "placetype": [
          "aat:300266554",
          "aat:300008699"
        ],
        "id": 7317501,
        "name:xx": "Cobre, Quebrada del"
      }
    },
    {
      "geometry": {
        "type": "Point",
        "coordinates": [
          -70.65,
          -31.3
        ]
      },
      "type": "Feature",
      "properties": {
        "hierarchy": [
          "tgn:7317502",
          "tgn:1001657",
          "tgn:1000049",
          "tgn:1000002",
          "tgn:7029392"
        ],
        "placetype": [
          "aat:300259572"
        ],
        "id": 7317502,
        "name:xx": "Cobre, Portezuelo del"
      }
    },
    {
      "geometry": {
        "type": "Point",
        "coordinates": [
          -70.216667,
          -33.883333
        ]
      },
      "type": "Feature",
      "properties": {
        "hierarchy": [
          "tgn:7317503",
          "tgn:1001708",
          "tgn:1000049",
          "tgn:1000002",
          "tgn:7029392"
        ],
        "placetype": [
          "aat:300008699"
        ],
        "id": 7317503,
        "name:xx": "Cobre, Estero del"
      }
    },
    {
      "geometry": {
        "type": "Point",
        "coordinates": [
          -70.666667,
          -31.383333
        ]
      },
      "type": "Feature",
      "properties": {
        "hierarchy": [
          "tgn:7317504",
          "tgn:1001657",
          "tgn:1000049",
          "tgn:1000002",
          "tgn:7029392"
        ],
        "placetype": [
          "aat:300008699"
        ],
        "id": 7317504,
        "name:xx": "Cobre, Estero del"
      }
    },
    {
      "geometry": {
        "type": "Point",
        "coordinates": [
          -71.35,
          -36.566667
        ]
      },
      "type": "Feature",
      "properties": {
        "hierarchy": [
          "tgn:7317505",
          "tgn:1001637",
          "tgn:1000049",
          "tgn:1000002",
          "tgn:7029392"
        ],
        "placetype": [
          "aat:300008795"
        ],
        "id": 7317505,
        "name:xx": "Cobre, Cerro del"
      }
    },
    {
      "geometry": {
        "type": "Point",
        "coordinates": [
          -70.25,
          -33.916667
        ]
      },
      "type": "Feature",
      "properties": {
        "hierarchy": [
          "tgn:7317506",
          "tgn:1001708",
          "tgn:1000049",
          "tgn:1000002",
          "tgn:7029392"
        ],
        "placetype": [
          "aat:300008795"
        ],
        "id": 7317506,
        "name:xx": "Cobre, Cerro del"
      }
    },
    {
      "geometry": {
        "type": "Point",
        "coordinates": [
          -70.366667,
          -33.833333
        ]
      },
      "type": "Feature",
      "properties": {
        "hierarchy": [
          "tgn:7317507",
          "tgn:1001708",
          "tgn:1000049",
          "tgn:1000002",
          "tgn:7029392"
        ],
        "placetype": [
          "aat:300008795"
        ],
        "id": 7317507,
        "name:xx": "Cobre, Cerro del"
      }
    },
    {
      "geometry": {
        "type": "Point",
        "coordinates": [
          -71.316667,
          -29.75
        ]
      },
      "type": "Feature",
      "properties": {
        "hierarchy": [
          "tgn:7317508",
          "tgn:1001657",
          "tgn:1000049",
          "tgn:1000002",
          "tgn:7029392"
        ],
        "placetype": [
          "aat:300008795"
        ],
        "id": 7317508,
        "name:xx": "Cobre, Cerro del"
      }
    },
    {
      "geometry": {
        "type": "Point",
        "coordinates": [
          -71.316667,
          -32.85
        ]
      },
      "type": "Feature",
      "properties": {
        "hierarchy": [
          "tgn:7317509",
          "tgn:1001768",
          "tgn:1000049",
          "tgn:1000002",
          "tgn:7029392"
        ],
        "placetype": [
          "aat:300008777"
        ],
        "id": 7317509,
        "name:xx": "Cobre, Cerro del"
      }
    }
  ]
}
