{
  "geometry": {
    "type": "Point",
    "coordinates": [
      -78.7667,
      38.85
    ]
  },
  "type": "Feature",
  "properties": {
    "hierarchy": [
      "tgn:2323692",
      "tgn:1000001",
      "tgn:7012149",
      "tgn:2002190",
      "tgn:7007919",
      "tgn:7029392"
    ],
    "placetype": [
      "aat:300008798"
    ],
    "id": 2323692,
    "name:xx": "Fat Mountain"
  }
}
