{
  "geometry": {
    "type": "Point",
    "coordinates": [
      -82.1333,
      35.55
    ]
  },
  "type": "Feature",
  "properties": {
    "hierarchy": [
      "tgn:2216555",
      "tgn:1000001",
      "tgn:7012149",
      "tgn:2001514",
      "tgn:7007709",
      "tgn:7029392"
    ],
    "placetype": [
      "aat:300008706"
    ],
    "id": 2216555,
    "name:xx": "Camp Creek"
  }
}
