{
  "type": "FeatureCollection",
  "features": [
    {
      "geometry": {
        "type": "Point",
        "coordinates": [
          12.733333,
          53.566667
        ]
      },
      "type": "Feature",
      "properties": {
        "hierarchy": [
          "tgn:7180431",
          "tgn:1000003",
          "tgn:7000094",
          "tgn:7000084",
          "tgn:7029392"
        ],
        "placetype": [
          "aat:300008777"
        ],
        "id": 7180431,
        "name:xx": "Fuchs Berg"
      }
    },
    {
      "geometry": {
        "type": "Point",
        "coordinates": [
          13.933333,
          53.466667
        ]
      },
      "type": "Feature",
      "properties": {
        "hierarchy": [
          "tgn:7180432",
          "tgn:1000003",
          "tgn:7000094",
          "tgn:7000084",
          "tgn:7029392"
        ],
        "placetype": [
          "aat:300008777"
        ],
        "id": 7180432,
        "name:xx": "Fuchs-Berg"
      }
    },
    {
      "geometry": {
        "type": "Point",
        "coordinates": [
          9.35,
          53.466667
        ]
      },
      "type": "Feature",
      "properties": {
        "hierarchy": [
          "tgn:7180433",
          "tgn:1000003",
          "tgn:7003676",
          "tgn:7000084",
          "tgn:7029392"
        ],
        "placetype": [
          "aat:300008777"
        ],
        "id": 7180433,
        "name:xx": "Fuchs-Berg"
      }
    },
    {
      "geometry": {
        "type": "Point",
        "coordinates": [
          11.1,
          53.45
        ]
      },
      "type": "Feature",
      "properties": {
        "hierarchy": [
          "tgn:7180434",
          "tgn:1000003",
          "tgn:7000094",
          "tgn:7000084",
          "tgn:7029392"
        ],
        "placetype": [
          "aat:300008777"
        ],
        "id": 7180434,
        "name:xx": "Fuchs-Berg"
      }
    },
    {
      "geometry": {
        "type": "Point",
        "coordinates": [
          10,
          53.433333
        ]
      },
      "type": "Feature",
      "properties": {
        "hierarchy": [
          "tgn:7180435",
          "tgn:1000003",
          "tgn:7003673",
          "tgn:7000084",
          "tgn:7029392"
        ],
        "placetype": [
          "aat:300008777"
        ],
        "id": 7180435,
        "name:xx": "Fuchs-Berg"
      }
    },
    {
      "geometry": {
        "type": "Point",
        "coordinates": [
          13.983333,
          53.366667
        ]
      },
      "type": "Feature",
      "properties": {
        "hierarchy": [
          "tgn:7180436",
          "tgn:7000096",
          "tgn:1000003",
          "tgn:7000084",
          "tgn:7029392"
        ],
        "placetype": [
          "aat:300008777"
        ],
        "id": 7180436,
        "name:xx": "Fuchs-Berg"
      }
    },
    {
      "geometry": {
        "type": "Point",
        "coordinates": [
          13.55,
          53.35
        ]
      },
      "type": "Feature",
      "properties": {
        "hierarchy": [
          "tgn:7180437",
          "tgn:7000096",
          "tgn:1000003",
          "tgn:7000084",
          "tgn:7029392"
        ],
        "placetype": [
          "aat:300008777"
        ],
        "id": 7180437,
        "name:xx": "Fuchs-Berg"
      }
    },
    {
      "geometry": {
        "type": "Point",
        "coordinates": [
          11.716667,
          53.35
        ]
      },
      "type": "Feature",
      "properties": {
        "hierarchy": [
          "tgn:7180438",
          "tgn:1000003",
          "tgn:7000094",
          "tgn:7000084",
          "tgn:7029392"
        ],
        "placetype": [
          "aat:300008777"
        ],
        "id": 7180438,
        "name:xx": "Fuchs-Berg"
      }
    },
    {
      "geometry": {
        "type": "Point",
        "coordinates": [
          8.616667,
          53.35
        ]
      },
      "type": "Feature",
      "properties": {
        "hierarchy": [
          "tgn:7180439",
          "tgn:1000003",
          "tgn:7003676",
          "tgn:7000084",
          "tgn:7029392"
        ],
        "placetype": [
          "aat:300008777"
        ],
        "id": 7180439,
        "name:xx": "Fuchs-Berg"
      }
    }
  ]
}
