{
  "geometry": {
    "type": "Point",
    "coordinates": [
      -115.5667,
      36.1833
    ]
  },
  "type": "Feature",
  "properties": {
    "hierarchy": [
      "tgn:2766946",
      "tgn:1000001",
      "tgn:2001410",
      "tgn:7012149",
      "tgn:7007526",
      "tgn:7029392"
    ],
    "placetype": [
      "aat:300008697"
    ],
    "id": 2766946,
    "name:xx": "White Point Spring"
  }
}
