{
  "geometry": {
    "type": "Point",
    "coordinates": [
      74.5875,
      32.969444
    ]
  },
  "type": "Feature",
  "properties": {
    "hierarchy": [
      "tgn:7591494",
      "tgn:1000004",
      "tgn:7000198",
      "tgn:7000799",
      "tgn:7029392"
    ],
    "placetype": [
      "aat:300008347"
    ],
    "name:en": "Ainbūshāhi da Danna",
    "id": 7591494
  }
}
