{
  "type": "FeatureCollection",
  "features": [
    {
      "geometry": {
        "type": "Point",
        "coordinates": [
          -84.9,
          41.55
        ]
      },
      "type": "Feature",
      "properties": {
        "hierarchy": [
          "tgn:2031380",
          "tgn:1000001",
          "tgn:7012149",
          "tgn:1002919",
          "tgn:7007252",
          "tgn:7029392"
        ],
        "placetype": [
          "aat:300008347"
        ],
        "id": 2031380,
        "name:xx": "Clarks Landing"
      }
    },
    {
      "geometry": {
        "type": "Point",
        "coordinates": [
          -85.9,
          40.0167
        ]
      },
      "type": "Feature",
      "properties": {
        "hierarchy": [
          "tgn:2031381",
          "tgn:1000001",
          "tgn:7012149",
          "tgn:1002439",
          "tgn:7007252",
          "tgn:7029392"
        ],
        "placetype": [
          "aat:300008347"
        ],
        "id": 2031381,
        "name:xx": "Clarksville"
      }
    },
    {
      "geometry": {
        "type": "Point",
        "coordinates": [
          -85.75,
          38.2833
        ]
      },
      "type": "Feature",
      "properties": {
        "hierarchy": [
          "tgn:2031382",
          "tgn:1000001",
          "tgn:1002273",
          "tgn:7012149",
          "tgn:7007252",
          "tgn:7029392"
        ],
        "placetype": [
          "aat:300008347"
        ],
        "id": 2031382,
        "name:xx": "Clarksville"
      }
    },
    {
      "geometry": {
        "type": "Point",
        "coordinates": [
          -87.1,
          39.2667
        ]
      },
      "type": "Feature",
      "properties": {
        "hierarchy": [
          "tgn:2031388",
          "tgn:1000001",
          "tgn:2000540",
          "tgn:7012149",
          "tgn:7007252",
          "tgn:7029392"
        ],
        "placetype": [
          "aat:300008347"
        ],
        "id": 2031388,
        "name:xx": "Clay City"
      }
    },
    {
      "geometry": {
        "type": "Point",
        "coordinates": [
          -86.95,
          38.0667
        ]
      },
      "type": "Feature",
      "properties": {
        "hierarchy": [
          "tgn:2031389",
          "tgn:1000001",
          "tgn:7012149",
          "tgn:2000555",
          "tgn:7007252",
          "tgn:7029392"
        ],
        "placetype": [
          "aat:300008347",
          "aat:300387210"
        ],
        "id": 2031389,
        "name:xx": "Clay City"
      }
    }
  ]
}
