{
  "geometry": {
    "type": "Point",
    "coordinates": [
      -77.3667,
      8.3333
    ]
  },
  "type": "Feature",
  "properties": {
    "hierarchy": [
      "tgn:1108955",
      "tgn:7029392"
    ],
    "placetype": [
      "aat:300386831"
    ],
    "id": 1108955,
    "name:xx": "Darién, Serranía del"
  }
}
