{
  "geometry": {
    "type": "Point",
    "coordinates": [
      78.35922,
      24.85866
    ]
  },
  "type": "Feature",
  "properties": {
    "hierarchy": [
      "tgn:7582063",
      "tgn:1000004",
      "tgn:7000198",
      "tgn:7016722",
      "tgn:7029392"
    ],
    "placetype": [
      "aat:300008699"
    ],
    "name:en": "Bhati",
    "id": 7582063
  }
}
