{
  "geometry": {
    "type": "Point",
    "coordinates": [
      -95.5167,
      43.8333
    ]
  },
  "type": "Feature",
  "properties": {
    "hierarchy": [
      "tgn:2428404",
      "tgn:1000001",
      "tgn:7012149",
      "tgn:7007521",
      "tgn:7029392"
    ],
    "placetype": [
      "aat:300006075"
    ],
    "id": 2428404,
    "name:xx": "Judicial Ditch Number Twentysix"
  }
}
