{
  "geometry": {
    "type": "Point",
    "coordinates": [
      7.15,
      52.05
    ]
  },
  "type": "Feature",
  "properties": {
    "hierarchy": [
      "tgn:7095347",
      "tgn:1000003",
      "tgn:7003677",
      "tgn:7000084",
      "tgn:7029392"
    ],
    "placetype": [
      "aat:300000206"
    ],
    "id": 7095347,
    "name:xx": "Schulte Eißing"
  }
}
