{
  "type": "FeatureCollection",
  "features": [
    {
      "geometry": {
        "type": "Point",
        "coordinates": [
          -98.9,
          19.216667
        ]
      },
      "type": "Feature",
      "properties": {
        "hierarchy": [
          "tgn:7441002",
          "tgn:1000001",
          "tgn:1001893",
          "tgn:7005560",
          "tgn:7029392"
        ],
        "placetype": [
          "aat:300008347"
        ],
        "id": 7441002,
        "name:xx": "San Pablo Atlazalpan"
      }
    },
    {
      "geometry": {
        "type": "Point",
        "coordinates": [
          -98.183333,
          19.333333
        ]
      },
      "type": "Feature",
      "properties": {
        "hierarchy": [
          "tgn:7441003",
          "tgn:1000001",
          "tgn:7005598",
          "tgn:7005560",
          "tgn:7029392"
        ],
        "placetype": [
          "aat:300008347"
        ],
        "id": 7441003,
        "name:xx": "San Pablo Apetatitlán"
      }
    },
    {
      "geometry": {
        "type": "Point",
        "coordinates": [
          -98.083333,
          18.116667
        ]
      },
      "type": "Feature",
      "properties": {
        "hierarchy": [
          "tgn:7441004",
          "tgn:1000001",
          "tgn:7005592",
          "tgn:7005560",
          "tgn:7029392"
        ],
        "placetype": [
          "aat:300008347"
        ],
        "id": 7441004,
        "name:xx": "San Pablo Amicano"
      }
    },
    {
      "geometry": {
        "type": "Point",
        "coordinates": [
          -115.883333,
          31.5
        ]
      },
      "type": "Feature",
      "properties": {
        "hierarchy": [
          "tgn:7441005",
          "tgn:1001835",
          "tgn:1000001",
          "tgn:7005560",
          "tgn:7029392"
        ],
        "placetype": [
          "aat:300008761"
        ],
        "id": 7441005,
        "name:xx": "San Pablo, Valle de"
      }
    },
    {
      "geometry": {
        "type": "Point",
        "coordinates": [
          -109,
          25.85
        ]
      },
      "type": "Feature",
      "properties": {
        "hierarchy": [
          "tgn:7441006",
          "tgn:1000001",
          "tgn:7005595",
          "tgn:7005560",
          "tgn:7029392"
        ],
        "placetype": [
          "aat:300008795"
        ],
        "id": 7441006,
        "name:xx": "San Pablo, Sierra"
      }
    },
    {
      "geometry": {
        "type": "Point",
        "coordinates": [
          -95.733333,
          16.333333
        ]
      },
      "type": "Feature",
      "properties": {
        "hierarchy": [
          "tgn:7441007",
          "tgn:1000001",
          "tgn:7005591",
          "tgn:7005560",
          "tgn:7029392"
        ],
        "placetype": [
          "aat:300008699"
        ],
        "id": 7441007,
        "name:xx": "San Pablo, Río"
      }
    },
    {
      "geometry": {
        "type": "Point",
        "coordinates": [
          -116.433333,
          32.366667
        ]
      },
      "type": "Feature",
      "properties": {
        "hierarchy": [
          "tgn:7441008",
          "tgn:1001835",
          "tgn:1000001",
          "tgn:7005560",
          "tgn:7029392"
        ],
        "placetype": [
          "aat:300000241"
        ],
        "id": 7441008,
        "name:xx": "Rancho San Pablo"
      }
    },
    {
      "geometry": {
        "type": "Point",
        "coordinates": [
          -115.95,
          31.5
        ]
      },
      "type": "Feature",
      "properties": {
        "hierarchy": [
          "tgn:7441009",
          "tgn:1001835",
          "tgn:1000001",
          "tgn:7005560",
          "tgn:7029392"
        ],
        "placetype": [
          "aat:300000241"
        ],
        "id": 7441009,
        "name:xx": "Rancho San Pablo"
      }
    }
  ]
}
