{
  "geometry": {
    "type": "Point",
    "coordinates": [
      -108.45,
      42.6667
    ]
  },
  "type": "Feature",
  "properties": {
    "hierarchy": [
      "tgn:2642942",
      "tgn:1000001",
      "tgn:7012149",
      "tgn:2002371",
      "tgn:7007923",
      "tgn:7029392"
    ],
    "placetype": [
      "aat:300006191"
    ],
    "id": 2642942,
    "name:xx": "Sandstone Reservoir"
  }
}
