{
  "geometry": {
    "type": "Point",
    "coordinates": [
      31.25,
      30.25
    ]
  },
  "type": "Feature",
  "properties": {
    "hierarchy": [
      "tgn:7529448",
      "tgn:7001242",
      "tgn:7016833",
      "tgn:1001092",
      "tgn:7029392"
    ],
    "placetype": [
      "aat:300005926"
    ],
    "id": 7529448,
    "name:xx": "Sīdī an Najdī"
  }
}
