{
  "geometry": {
    "type": "Point",
    "coordinates": [
      32.566667,
      26.783333
    ]
  },
  "type": "Feature",
  "properties": {
    "hierarchy": [
      "tgn:7536581",
      "tgn:7001242",
      "tgn:7001311",
      "tgn:7016833",
      "tgn:7029392"
    ],
    "placetype": [
      "aat:300379998"
    ],
    "name:en": "Gurdi el- Soghair, Wâdi",
    "id": 7536581
  }
}
