{
  "geometry": {
    "type": "Point",
    "coordinates": [
      -83.4333,
      36.1833
    ]
  },
  "type": "Feature",
  "properties": {
    "hierarchy": [
      "tgn:2567349",
      "tgn:1000001",
      "tgn:7012149",
      "tgn:7007825",
      "tgn:7029392"
    ],
    "placetype": [
      "aat:300132348"
    ],
    "id": 2567349,
    "name:xx": "Panthers Shoals"
  }
}
