{
  "geometry": {
    "type": "Point",
    "coordinates": [
      -121.4167,
      36.1333
    ]
  },
  "type": "Feature",
  "properties": {
    "hierarchy": [
      "tgn:1107336",
      "tgn:1000001",
      "tgn:7012149",
      "tgn:7007157",
      "tgn:1002684",
      "tgn:7029392"
    ],
    "placetype": [
      "aat:300008798"
    ],
    "id": 1107336,
    "name:xx": "Junipero Serra Peak"
  }
}
