{
  "type": "FeatureCollection",
  "features": [
    {
      "geometry": {
        "type": "Point",
        "coordinates": [
          -3.55,
          55.6
        ]
      },
      "type": "Feature",
      "properties": {
        "hierarchy": [
          "tgn:7453911",
          "tgn:7002444",
          "tgn:1000003",
          "tgn:7019090",
          "tgn:7008591",
          "tgn:7029392"
        ],
        "placetype": [
          "aat:300007783"
        ],
        "name:en": "Coulter Station",
        "id": 7453911
      }
    },
    {
      "geometry": {
        "type": "Point",
        "coordinates": [
          -2.073611,
          51.285556
        ]
      },
      "type": "Feature",
      "properties": {
        "hierarchy": [
          "tgn:7453912",
          "tgn:7002445",
          "tgn:1000003",
          "tgn:7008180",
          "tgn:7008591",
          "tgn:7029392"
        ],
        "placetype": [
          "aat:300008347"
        ],
        "name:en": "Coulston",
        "id": 7453912
      }
    },
    {
      "geometry": {
        "type": "Point",
        "coordinates": [
          -4.416667,
          58.35
        ]
      },
      "type": "Feature",
      "properties": {
        "hierarchy": [
          "tgn:7453913",
          "tgn:7002444",
          "tgn:1000003",
          "tgn:7008082",
          "tgn:7008591",
          "tgn:7029392"
        ],
        "placetype": [
          "aat:300008680"
        ],
        "name:en": "Coulside, Loch",
        "id": 7453913
      }
    },
    {
      "geometry": {
        "type": "Point",
        "coordinates": [
          -4.883333,
          56.05
        ]
      },
      "type": "Feature",
      "properties": {
        "hierarchy": [
          "tgn:7453915",
          "tgn:7019094",
          "tgn:7002444",
          "tgn:1000003",
          "tgn:7008591",
          "tgn:7029392"
        ],
        "placetype": [
          "aat:300008347"
        ],
        "name:en": "Coulport",
        "id": 7453915
      }
    },
    {
      "geometry": {
        "type": "Point",
        "coordinates": [
          -6.5,
          55.8
        ]
      },
      "type": "Feature",
      "properties": {
        "hierarchy": [
          "tgn:7453916",
          "tgn:7019094",
          "tgn:7002444",
          "tgn:1000003",
          "tgn:7008591",
          "tgn:7029392"
        ],
        "placetype": [
          "aat:300386846"
        ],
        "name:en": "Coul Point",
        "id": 7453916
      }
    },
    {
      "geometry": {
        "type": "Point",
        "coordinates": [
          -3.716667,
          57.5
        ]
      },
      "type": "Feature",
      "properties": {
        "hierarchy": [
          "tgn:7453917",
          "tgn:7002444",
          "tgn:1000003",
          "tgn:5000451",
          "tgn:7008591",
          "tgn:7029392"
        ],
        "placetype": [
          "aat:300004792"
        ],
        "name:en": "Coulmony House",
        "id": 7453917
      }
    },
    {
      "geometry": {
        "type": "Point",
        "coordinates": [
          -2.8,
          57.1
        ]
      },
      "type": "Feature",
      "properties": {
        "hierarchy": [
          "tgn:7453918",
          "tgn:5000432",
          "tgn:7002444",
          "tgn:1000003",
          "tgn:7008591",
          "tgn:7029392"
        ],
        "placetype": [
          "aat:300008347"
        ],
        "name:en": "Coull",
        "id": 7453918
      }
    },
    {
      "geometry": {
        "type": "Point",
        "coordinates": [
          -5.35,
          57.55
        ]
      },
      "type": "Feature",
      "properties": {
        "hierarchy": [
          "tgn:7453919",
          "tgn:7002444",
          "tgn:1000003",
          "tgn:7008082",
          "tgn:7008591",
          "tgn:7029392"
        ],
        "placetype": [
          "aat:300004792"
        ],
        "name:en": "Coulin Lodge",
        "id": 7453919
      }
    }
  ]
}
