{
  "geometry": {
    "type": "Point",
    "coordinates": [
      -88.1667,
      43.9667
    ]
  },
  "type": "Feature",
  "properties": {
    "hierarchy": [
      "tgn:2120914",
      "tgn:1000001",
      "tgn:2002312",
      "tgn:7012149",
      "tgn:7007922",
      "tgn:7029392"
    ],
    "placetype": [
      "aat:300008347"
    ],
    "id": 2120914,
    "name:xx": "Charlesburg"
  }
}
