{
  "geometry": {
    "type": "Point",
    "coordinates": [
      -75.6333,
      43.2667
    ]
  },
  "type": "Feature",
  "properties": {
    "hierarchy": [
      "tgn:2068113",
      "tgn:1000001",
      "tgn:7012149",
      "tgn:7014287",
      "tgn:7007568",
      "tgn:7029392"
    ],
    "placetype": [
      "aat:300008347"
    ],
    "id": 2068113,
    "name:xx": "Blossvale"
  }
}
