{
  "geometry": {
    "type": "Point",
    "coordinates": [
      -76.1333,
      38.3333
    ]
  },
  "type": "Feature",
  "properties": {
    "hierarchy": [
      "tgn:2480742",
      "tgn:1002338",
      "tgn:1000001",
      "tgn:7012149",
      "tgn:7007516",
      "tgn:7029392"
    ],
    "placetype": [
      "aat:300008347"
    ],
    "id": 2480742,
    "name:xx": "Lakesville"
  }
}
