{
  "geometry": {
    "type": "Point",
    "coordinates": [
      -80.4167,
      38.0667
    ]
  },
  "type": "Feature",
  "properties": {
    "hierarchy": [
      "tgn:2215759",
      "tgn:1000001",
      "tgn:7012149",
      "tgn:2002264",
      "tgn:7013961",
      "tgn:7029392"
    ],
    "placetype": [
      "aat:300008699"
    ],
    "id": 2215759,
    "name:xx": "Camel Branch"
  }
}
