{
  "geometry": {
    "type": "Point",
    "coordinates": [
      -92.5833,
      34.75
    ]
  },
  "type": "Feature",
  "properties": {
    "hierarchy": [
      "tgn:2375951",
      "tgn:1000001",
      "tgn:7016172",
      "tgn:7012149",
      "tgn:2000167",
      "tgn:7029392"
    ],
    "placetype": [
      "aat:300006191"
    ],
    "id": 2375951,
    "name:xx": "Happy Valley Lake"
  }
}
