{
  "geometry": {
    "type": "Point",
    "coordinates": [
      -83.9833,
      39.5667
    ]
  },
  "type": "Feature",
  "properties": {
    "hierarchy": [
      "tgn:2257353",
      "tgn:1000001",
      "tgn:7012149",
      "tgn:1002424",
      "tgn:7007706",
      "tgn:7029392"
    ],
    "placetype": [
      "aat:300008347"
    ],
    "id": 2257353,
    "name:xx": "Cornstalk"
  }
}
