{
  "type": "FeatureCollection",
  "features": [
    {
      "geometry": {
        "type": "Point",
        "coordinates": [
          -83.2833,
          29.95
        ]
      },
      "type": "Feature",
      "properties": {
        "hierarchy": [
          "tgn:2779660",
          "tgn:1000001",
          "tgn:2000275",
          "tgn:7012149",
          "tgn:7007240",
          "tgn:7029392"
        ],
        "placetype": [
          "aat:300008905"
        ],
        "id": 2779660,
        "name:xx": "Wolf Pond"
      }
    },
    {
      "geometry": {
        "type": "Point",
        "coordinates": [
          -84.4667,
          31.35
        ]
      },
      "type": "Feature",
      "properties": {
        "hierarchy": [
          "tgn:2779661",
          "tgn:2000295",
          "tgn:1000001",
          "tgn:7012149",
          "tgn:7007248",
          "tgn:7029392"
        ],
        "placetype": [
          "aat:300008680"
        ],
        "id": 2779661,
        "name:xx": "Wolf Pond"
      }
    },
    {
      "geometry": {
        "type": "Point",
        "coordinates": [
          -83.7667,
          32.1833
        ]
      },
      "type": "Feature",
      "properties": {
        "hierarchy": [
          "tgn:2779662",
          "tgn:1000001",
          "tgn:7012149",
          "tgn:2000337",
          "tgn:7007248",
          "tgn:7029392"
        ],
        "placetype": [
          "aat:300008680"
        ],
        "id": 2779662,
        "name:xx": "Wolf Pond"
      }
    },
    {
      "geometry": {
        "type": "Point",
        "coordinates": [
          -69.7333,
          43.9667
        ]
      },
      "type": "Feature",
      "properties": {
        "hierarchy": [
          "tgn:2779663",
          "tgn:1000001",
          "tgn:7012149",
          "tgn:2000929",
          "tgn:7007515",
          "tgn:7029392"
        ],
        "placetype": [
          "aat:300008680"
        ],
        "id": 2779663,
        "name:xx": "Wolf Pond"
      }
    },
    {
      "geometry": {
        "type": "Point",
        "coordinates": [
          -70.7333,
          41.95
        ]
      },
      "type": "Feature",
      "properties": {
        "hierarchy": [
          "tgn:2779664",
          "tgn:1000001",
          "tgn:7014423",
          "tgn:7012149",
          "tgn:7007517",
          "tgn:7029392"
        ],
        "placetype": [
          "aat:300008680"
        ],
        "id": 2779664,
        "name:xx": "Wolf Pond"
      }
    },
    {
      "geometry": {
        "type": "Point",
        "coordinates": [
          -74.35,
          44.5167
        ]
      },
      "type": "Feature",
      "properties": {
        "hierarchy": [
          "tgn:2779665",
          "tgn:1000001",
          "tgn:7012149",
          "tgn:7013941",
          "tgn:7007568",
          "tgn:7029392"
        ],
        "placetype": [
          "aat:300008680"
        ],
        "id": 2779665,
        "name:xx": "Wolf Pond"
      }
    },
    {
      "geometry": {
        "type": "Point",
        "coordinates": [
          -74.95,
          41.5
        ]
      },
      "type": "Feature",
      "properties": {
        "hierarchy": [
          "tgn:2779666",
          "tgn:1000001",
          "tgn:7012149",
          "tgn:1002926",
          "tgn:7007568",
          "tgn:7029392"
        ],
        "placetype": [
          "aat:300008680"
        ],
        "id": 2779666,
        "name:xx": "Wolf Pond"
      }
    },
    {
      "geometry": {
        "type": "Point",
        "coordinates": [
          -73.9833,
          43.4833
        ]
      },
      "type": "Feature",
      "properties": {
        "hierarchy": [
          "tgn:2779667",
          "tgn:1000001",
          "tgn:7012149",
          "tgn:1002986",
          "tgn:7007568",
          "tgn:7029392"
        ],
        "placetype": [
          "aat:300008680"
        ],
        "id": 2779667,
        "name:xx": "Wolf Pond"
      }
    },
    {
      "geometry": {
        "type": "Point",
        "coordinates": [
          -73.6167,
          43.8
        ]
      },
      "type": "Feature",
      "properties": {
        "hierarchy": [
          "tgn:2779668",
          "tgn:1000001",
          "tgn:7012149",
          "tgn:2001461",
          "tgn:7007568",
          "tgn:7029392"
        ],
        "placetype": [
          "aat:300008680"
        ],
        "id": 2779668,
        "name:xx": "Wolf Pond"
      }
    },
    {
      "geometry": {
        "type": "Point",
        "coordinates": [
          -74.3333,
          43.8833
        ]
      },
      "type": "Feature",
      "properties": {
        "hierarchy": [
          "tgn:2779669",
          "tgn:1000001",
          "tgn:7012149",
          "tgn:1002440",
          "tgn:7007568",
          "tgn:7029392"
        ],
        "placetype": [
          "aat:300008680"
        ],
        "id": 2779669,
        "name:xx": "Wolf Pond"
      }
    }
  ]
}
