{
  "type": "FeatureCollection",
  "features": [
    {
      "geometry": {
        "type": "Point",
        "coordinates": [
          -110.5167,
          32.2
        ]
      },
      "type": "Feature",
      "properties": {
        "hierarchy": [
          "tgn:2613920",
          "tgn:1000001",
          "tgn:7006451",
          "tgn:7012149",
          "tgn:2000100",
          "tgn:7029392"
        ],
        "placetype": [
          "aat:300008798"
        ],
        "id": 2613920,
        "name:xx": "Reef Rock"
      }
    },
    {
      "geometry": {
        "type": "Point",
        "coordinates": [
          -120.05,
          35.9
        ]
      },
      "type": "Feature",
      "properties": {
        "hierarchy": [
          "tgn:2613921",
          "tgn:1000001",
          "tgn:7012149",
          "tgn:1002550",
          "tgn:7007157",
          "tgn:7029392"
        ],
        "placetype": [
          "aat:300008347"
        ],
        "id": 2613921,
        "name:xx": "Reef Station"
      }
    },
    {
      "geometry": {
        "type": "Point",
        "coordinates": [
          -110.3,
          32.9
        ]
      },
      "type": "Feature",
      "properties": {
        "hierarchy": [
          "tgn:2613922",
          "tgn:1000001",
          "tgn:7006451",
          "tgn:2000094",
          "tgn:7012149",
          "tgn:7029392"
        ],
        "placetype": [
          "aat:300006191"
        ],
        "id": 2613922,
        "name:xx": "Reef Tank"
      }
    },
    {
      "geometry": {
        "type": "Point",
        "coordinates": [
          -110.7667,
          32.45
        ]
      },
      "type": "Feature",
      "properties": {
        "hierarchy": [
          "tgn:2613923",
          "tgn:1000001",
          "tgn:7006451",
          "tgn:7012149",
          "tgn:2000100",
          "tgn:7029392"
        ],
        "placetype": [
          "aat:300266640"
        ],
        "id": 2613923,
        "name:xx": "Reef of Rock"
      }
    },
    {
      "geometry": {
        "type": "Point",
        "coordinates": [
          -109.7,
          37.8167
        ]
      },
      "type": "Feature",
      "properties": {
        "hierarchy": [
          "tgn:2613924",
          "tgn:1000001",
          "tgn:7012149",
          "tgn:2002119",
          "tgn:7007827",
          "tgn:7029392"
        ],
        "placetype": [
          "aat:300266640"
        ],
        "id": 2613924,
        "name:xx": "Reef of Rocks"
      }
    },
    {
      "geometry": {
        "type": "Point",
        "coordinates": [
          -106.0167,
          38.6333
        ]
      },
      "type": "Feature",
      "properties": {
        "hierarchy": [
          "tgn:2613925",
          "tgn:1000001",
          "tgn:2000199",
          "tgn:7012149",
          "tgn:7007158",
          "tgn:7029392"
        ],
        "placetype": [
          "aat:300008798"
        ],
        "id": 2613925,
        "name:xx": "Reef, The"
      }
    },
    {
      "geometry": {
        "type": "Point",
        "coordinates": [
          -112.1,
          47.1
        ]
      },
      "type": "Feature",
      "properties": {
        "hierarchy": [
          "tgn:2613926",
          "tgn:1000001",
          "tgn:7012149",
          "tgn:2001284",
          "tgn:7007524",
          "tgn:7029392"
        ],
        "placetype": [
          "aat:300008697"
        ],
        "id": 2613926,
        "name:xx": "Reef, The"
      }
    },
    {
      "geometry": {
        "type": "Point",
        "coordinates": [
          -109.3,
          40.5
        ]
      },
      "type": "Feature",
      "properties": {
        "hierarchy": [
          "tgn:2613927",
          "tgn:1000001",
          "tgn:7012149",
          "tgn:2002124",
          "tgn:7007827",
          "tgn:7029392"
        ],
        "placetype": [
          "aat:300266640"
        ],
        "id": 2613927,
        "name:xx": "Reef, The"
      }
    },
    {
      "geometry": {
        "type": "Point",
        "coordinates": [
          -91.5,
          46.75
        ]
      },
      "type": "Feature",
      "properties": {
        "hierarchy": [
          "tgn:2613928",
          "tgn:2002308",
          "tgn:1000001",
          "tgn:7012149",
          "tgn:7007922",
          "tgn:7029392"
        ],
        "placetype": [
          "aat:300008706"
        ],
        "id": 2613928,
        "name:xx": "Reefer Creek"
      }
    },
    {
      "geometry": {
        "type": "Point",
        "coordinates": [
          -82.7333,
          27.65
        ]
      },
      "type": "Feature",
      "properties": {
        "hierarchy": [
          "tgn:2613929",
          "tgn:1000001",
          "tgn:7012149",
          "tgn:1002790",
          "tgn:7007240",
          "tgn:7029392"
        ],
        "placetype": [
          "aat:300008791"
        ],
        "id": 2613929,
        "name:xx": "Reefs, The"
      }
    }
  ]
}
