{
  "geometry": {
    "type": "Point",
    "coordinates": [
      79.9371,
      27.1903
    ]
  },
  "type": "Feature",
  "properties": {
    "hierarchy": [
      "tgn:7561841",
      "tgn:1000004",
      "tgn:7000198",
      "tgn:7016722",
      "tgn:7029392"
    ],
    "placetype": [
      "aat:300008347"
    ],
    "name:en": "Nekpur Nawāda",
    "id": 7561841
  }
}
