{
  "geometry": {
    "type": "Point",
    "coordinates": [
      -72.7667,
      41.25
    ]
  },
  "type": "Feature",
  "properties": {
    "hierarchy": [
      "tgn:2767528",
      "tgn:1000001",
      "tgn:1002712",
      "tgn:7012149",
      "tgn:7007159",
      "tgn:7029392"
    ],
    "placetype": [
      "aat:300008791"
    ],
    "id": 2767528,
    "name:xx": "White Top Rock"
  }
}
