{
  "type": "FeatureCollection",
  "features": [
    {
      "geometry": {
        "type": "Point",
        "coordinates": [
          -17.966667,
          27.7
        ]
      },
      "type": "Feature",
      "properties": {
        "hierarchy": [
          "tgn:7297370",
          "tgn:7002836",
          "tgn:7016622",
          "tgn:1000003",
          "tgn:1000095",
          "tgn:7029392"
        ],
        "placetype": [
          "aat:300008347"
        ],
        "id": 7297370,
        "name:xx": "Taibique"
      }
    },
    {
      "geometry": {
        "type": "Point",
        "coordinates": [
          -2.166667,
          38.166667
        ]
      },
      "type": "Feature",
      "properties": {
        "hierarchy": [
          "tgn:7297371",
          "tgn:7002803",
          "tgn:1001647",
          "tgn:1000003",
          "tgn:1000095",
          "tgn:7029392"
        ],
        "placetype": [
          "aat:300008795"
        ],
        "id": 7297371,
        "name:xx": "Taibilla, Sierra de"
      }
    },
    {
      "geometry": {
        "type": "Point",
        "coordinates": [
          -2.15,
          38.4
        ]
      },
      "type": "Feature",
      "properties": {
        "hierarchy": [
          "tgn:7297372",
          "tgn:7002803",
          "tgn:1001647",
          "tgn:1000003",
          "tgn:1000095",
          "tgn:7029392"
        ],
        "placetype": [
          "aat:300008699"
        ],
        "id": 7297372,
        "name:xx": "Taibilla, Río"
      }
    },
    {
      "geometry": {
        "type": "Point",
        "coordinates": [
          1.192884,
          42.290358
        ]
      },
      "type": "Feature",
      "properties": {
        "hierarchy": [
          "tgn:7297373",
          "tgn:7008912",
          "tgn:7030216",
          "tgn:1000003",
          "tgn:1000095",
          "tgn:7029392"
        ],
        "placetype": [
          "aat:300008347"
        ],
        "id": 7297373,
        "name:xx": "Tahús"
      }
    },
    {
      "geometry": {
        "type": "Point",
        "coordinates": [
          -16.25,
          28.483333
        ]
      },
      "type": "Feature",
      "properties": {
        "hierarchy": [
          "tgn:7297375",
          "tgn:7002836",
          "tgn:7016622",
          "tgn:1000003",
          "tgn:1000095",
          "tgn:7029392"
        ],
        "placetype": [
          "aat:300266554",
          "aat:300008699"
        ],
        "id": 7297375,
        "name:xx": "Tahodio, Barranco de"
      }
    },
    {
      "geometry": {
        "type": "Point",
        "coordinates": [
          -16.25,
          28.483333
        ]
      },
      "type": "Feature",
      "properties": {
        "hierarchy": [
          "tgn:7297376",
          "tgn:7002836",
          "tgn:7016622",
          "tgn:1000003",
          "tgn:1000095",
          "tgn:7029392"
        ],
        "placetype": [
          "aat:300008347"
        ],
        "id": 7297376,
        "name:xx": "Tahodio"
      }
    },
    {
      "geometry": {
        "type": "Point",
        "coordinates": [
          -13.533333,
          29
        ]
      },
      "type": "Feature",
      "properties": {
        "hierarchy": [
          "tgn:7297377",
          "tgn:7002825",
          "tgn:7016622",
          "tgn:1000003",
          "tgn:1000095",
          "tgn:7029392"
        ],
        "placetype": [
          "aat:300008347"
        ],
        "id": 7297377,
        "name:xx": "Tahiche"
      }
    },
    {
      "geometry": {
        "type": "Point",
        "coordinates": [
          -2.283333,
          37.233333
        ]
      },
      "type": "Feature",
      "properties": {
        "hierarchy": [
          "tgn:7297378",
          "tgn:7002805",
          "tgn:7002758",
          "tgn:1000003",
          "tgn:1000095",
          "tgn:7029392"
        ],
        "placetype": [
          "aat:300008347"
        ],
        "id": 7297378,
        "name:xx": "Tahal"
      }
    },
    {
      "geometry": {
        "type": "Point",
        "coordinates": [
          -9.4,
          38.666667
        ]
      },
      "type": "Feature",
      "properties": {
        "hierarchy": [
          "tgn:7297379",
          "tgn:7002807",
          "tgn:1000003",
          "tgn:7003837",
          "tgn:1000095",
          "tgn:7029392"
        ],
        "placetype": [
          "aat:300008699"
        ],
        "id": 7297379,
        "name:xx": "Tejo, Rio"
      }
    }
  ]
}
