{
  "geometry": {
    "type": "Point",
    "coordinates": [
      85.37895,
      22.053102
    ]
  },
  "type": "Feature",
  "properties": {
    "hierarchy": [
      "tgn:7572382",
      "tgn:1000004",
      "tgn:7000198",
      "tgn:7016694",
      "tgn:7029392"
    ],
    "placetype": [
      "aat:300008347"
    ],
    "name:en": "Jhārgaon",
    "id": 7572382
  }
}
