{
  "geometry": {
    "type": "Point",
    "coordinates": [
      15.7833,
      47.75
    ]
  },
  "type": "Feature",
  "properties": {
    "hierarchy": [
      "tgn:1111679",
      "tgn:7003025",
      "tgn:1000003",
      "tgn:1000062",
      "tgn:7029392"
    ],
    "placetype": [
      "aat:300008761"
    ],
    "id": 1111679,
    "name:xx": "Höllental"
  }
}
