{
  "geometry": {
    "type": "Point",
    "coordinates": [
      -77.6833,
      41.8167
    ]
  },
  "type": "Feature",
  "properties": {
    "hierarchy": [
      "tgn:2333195",
      "tgn:1000001",
      "tgn:7012149",
      "tgn:1002800",
      "tgn:7007710",
      "tgn:7029392"
    ],
    "placetype": [
      "aat:300008761"
    ],
    "id": 2333195,
    "name:xx": "Flynn Hollow"
  }
}
