{
  "geometry": {
    "type": "Point",
    "coordinates": [
      30.666667,
      28.583333
    ]
  },
  "type": "Feature",
  "properties": {
    "hierarchy": [
      "tgn:7539475",
      "tgn:7001242",
      "tgn:7016833",
      "tgn:1001088",
      "tgn:7029392"
    ],
    "placetype": [
      "aat:300008347"
    ],
    "name:en": "Sakanāt 'Arab 'Alī 'Abd al Karīm Ruḩayyim",
    "id": 7539475
  }
}
