{
  "geometry": {
    "type": "Point",
    "coordinates": [
      10.6167,
      57.7333
    ]
  },
  "type": "Feature",
  "properties": {
    "hierarchy": [
      "tgn:7003593",
      "tgn:7594007",
      "tgn:1000003",
      "tgn:1000066",
      "tgn:7029392"
    ],
    "placetype": [
      "aat:300008347"
    ],
    "id": 7003593,
    "name:xx": "Skagen"
  }
}
