{
  "geometry": {
    "type": "Point",
    "coordinates": [
      -119.2667,
      37.6667
    ]
  },
  "type": "Feature",
  "properties": {
    "hierarchy": [
      "tgn:2162581",
      "tgn:1000001",
      "tgn:7012149",
      "tgn:7007157",
      "tgn:1002621",
      "tgn:7029392"
    ],
    "placetype": [
      "aat:300008761"
    ],
    "id": 2162581,
    "name:xx": "Bench Canyon"
  }
}
