{
  "geometry": {
    "type": "Point",
    "coordinates": [
      -111.1667,
      40.3667
    ]
  },
  "type": "Feature",
  "properties": {
    "hierarchy": [
      "tgn:2272110",
      "tgn:1000001",
      "tgn:7012149",
      "tgn:2002126",
      "tgn:7007827",
      "tgn:7029392"
    ],
    "placetype": [
      "aat:300008798"
    ],
    "id": 2272110,
    "name:xx": "Currant Creek Peak"
  }
}
