{
  "geometry": {
    "type": "Point",
    "coordinates": [
      -45.9167,
      -9.2833
    ]
  },
  "type": "Feature",
  "properties": {
    "hierarchy": [
      "tgn:1128415",
      "tgn:7006246",
      "tgn:1000047",
      "tgn:7002455",
      "tgn:1000002",
      "tgn:7029392"
    ],
    "placetype": [
      "aat:300008707"
    ],
    "id": 1128415,
    "name:xx": "Parnaìbinha"
  }
}
