{
  "geometry": {
    "type": "Point",
    "coordinates": [
      -114.3667,
      36.1167
    ]
  },
  "type": "Feature",
  "properties": {
    "hierarchy": [
      "tgn:2308764",
      "tgn:1000001",
      "tgn:7006451",
      "tgn:7012149",
      "tgn:2000098",
      "tgn:7029392"
    ],
    "placetype": [
      "aat:300008850"
    ],
    "id": 2308764,
    "name:xx": "East Point"
  }
}
