{
  "geometry": {
    "type": "Point",
    "coordinates": [
      9.416667,
      51.65
    ]
  },
  "type": "Feature",
  "properties": {
    "hierarchy": [
      "tgn:7078692",
      "tgn:1000003",
      "tgn:7003676",
      "tgn:7000084",
      "tgn:7029392"
    ],
    "placetype": [
      "aat:300004792"
    ],
    "id": 7078692,
    "name:xx": "Försterei Würrigsen"
  }
}
