{
  "geometry": {
    "type": "Point",
    "coordinates": [
      6.1333,
      48.2833
    ]
  },
  "type": "Feature",
  "properties": {
    "hierarchy": [
      "tgn:4007012",
      "tgn:1000003",
      "tgn:7002888",
      "tgn:1000070",
      "tgn:7029392"
    ],
    "placetype": [
      "aat:300008347"
    ],
    "id": 4007012,
    "name:xx": "Mattaincourt"
  }
}
