{
  "geometry": {
    "type": "Point",
    "coordinates": [
      33.47163,
      26.91725
    ]
  },
  "type": "Feature",
  "properties": {
    "hierarchy": [
      "tgn:7521174",
      "tgn:7001242",
      "tgn:7001311",
      "tgn:7016833",
      "tgn:7029392"
    ],
    "placetype": [
      "aat:300008795"
    ],
    "name:en": "Abū Ḑalf, Jabal",
    "id": 7521174
  }
}
