{
  "geometry": {
    "type": "Point",
    "coordinates": [
      136.5167,
      -33.8833
    ]
  },
  "type": "Feature",
  "properties": {
    "hierarchy": [
      "tgn:1096119",
      "tgn:7000490",
      "tgn:1000006",
      "tgn:7001831",
      "tgn:7029392"
    ],
    "placetype": [
      "aat:300008347"
    ],
    "id": 1096119,
    "name:xx": "Arno Bay"
  }
}
