{
  "geometry": {
    "type": "Point",
    "coordinates": [
      -111.6167,
      39.7667
    ]
  },
  "type": "Feature",
  "properties": {
    "hierarchy": [
      "tgn:2618709",
      "tgn:1000001",
      "tgn:7012149",
      "tgn:2002112",
      "tgn:7007827",
      "tgn:7029392"
    ],
    "placetype": [
      "aat:300008706"
    ],
    "id": 2618709,
    "name:xx": "Right Fork Pole Creek"
  }
}
