{
  "geometry": {
    "type": "Point",
    "coordinates": [
      -78.75,
      39.65
    ]
  },
  "type": "Feature",
  "properties": {
    "hierarchy": [
      "tgn:2046811",
      "tgn:2000934",
      "tgn:1000001",
      "tgn:7012149",
      "tgn:7007516",
      "tgn:7029392"
    ],
    "placetype": [
      "aat:300008347",
      "aat:300008416",
      "aat:300008389",
      "aat:300387308",
      "aat:300387305",
      "aat:300387320",
      "aat:300387270"
    ],
    "id": 2046811,
    "name:xx": "Cumberland"
  }
}
