{
  "geometry": {
    "type": "Point",
    "coordinates": [
      -112.85,
      37.6833
    ]
  },
  "type": "Feature",
  "properties": {
    "hierarchy": [
      "tgn:2536246",
      "tgn:1000001",
      "tgn:7012149",
      "tgn:2002111",
      "tgn:7007827",
      "tgn:7029392"
    ],
    "placetype": [
      "aat:300008798"
    ],
    "id": 2536246,
    "name:xx": "Navajo Point"
  }
}
