{
  "geometry": {
    "type": "Point",
    "coordinates": [
      -86.0333,
      37.0833
    ]
  },
  "type": "Feature",
  "properties": {
    "hierarchy": [
      "tgn:2040688",
      "tgn:2000768",
      "tgn:1000001",
      "tgn:7012149",
      "tgn:7007255",
      "tgn:7029392"
    ],
    "placetype": [
      "aat:300008347"
    ],
    "id": 2040688,
    "name:xx": "Park City"
  }
}
