{
  "geometry": {
    "type": "Point",
    "coordinates": [
      -75.8833,
      38.6667
    ]
  },
  "type": "Feature",
  "properties": {
    "hierarchy": [
      "tgn:2046252",
      "tgn:1002338",
      "tgn:1000001",
      "tgn:7012149",
      "tgn:7007516",
      "tgn:7029392"
    ],
    "placetype": [
      "aat:300008347"
    ],
    "id": 2046252,
    "name:xx": "Beulah"
  }
}
