{
  "geometry": {
    "type": "Point",
    "coordinates": [
      -88.6833,
      41.2333
    ]
  },
  "type": "Feature",
  "properties": {
    "hierarchy": [
      "tgn:2261860",
      "tgn:1000001",
      "tgn:7012149",
      "tgn:1002562",
      "tgn:7007251",
      "tgn:7029392"
    ],
    "placetype": [
      "aat:300008706"
    ],
    "id": 2261860,
    "name:xx": "Covel Creek"
  }
}
