{
  "geometry": {
    "type": "Point",
    "coordinates": [
      74.9875,
      32.7625
    ]
  },
  "type": "Feature",
  "properties": {
    "hierarchy": [
      "tgn:7589477",
      "tgn:1000004",
      "tgn:7000198",
      "tgn:7000799",
      "tgn:7029392"
    ],
    "placetype": [
      "aat:300008347"
    ],
    "name:en": "Bhaira Laihr",
    "id": 7589477
  }
}
