{
  "geometry": {
    "type": "Point",
    "coordinates": [
      -46.4667,
      -23.4167
    ]
  },
  "type": "Feature",
  "properties": {
    "hierarchy": [
      "tgn:1134779",
      "tgn:1001945",
      "tgn:1000047",
      "tgn:7002457",
      "tgn:1000002",
      "tgn:7029392"
    ],
    "placetype": [
      "aat:300008706"
    ],
    "id": 1134779,
    "name:xx": "Tanque Grande, Ribeirão"
  }
}
