{
  "geometry": {
    "type": "Point",
    "coordinates": [
      -82.25,
      35.7667
    ]
  },
  "type": "Feature",
  "properties": {
    "hierarchy": [
      "tgn:2171719",
      "tgn:1000001",
      "tgn:7012149",
      "tgn:2001556",
      "tgn:7007709",
      "tgn:7029392"
    ],
    "placetype": [
      "aat:300008798"
    ],
    "id": 2171719,
    "name:xx": "Big Tom"
  }
}
