{
  "type": "FeatureCollection",
  "features": [
    {
      "geometry": {
        "type": "Point",
        "coordinates": [
          -91.05,
          35.9167
        ]
      },
      "type": "Feature",
      "properties": {
        "hierarchy": [
          "tgn:2215540",
          "tgn:1000001",
          "tgn:7016172",
          "tgn:7012149",
          "tgn:2000142",
          "tgn:7029392"
        ],
        "placetype": [
          "aat:300008347"
        ],
        "id": 2215540,
        "name:xx": "Calvin"
      }
    },
    {
      "geometry": {
        "type": "Point",
        "coordinates": [
          -83.7,
          33.3667
        ]
      },
      "type": "Feature",
      "properties": {
        "hierarchy": [
          "tgn:2215541",
          "tgn:1000001",
          "tgn:7012149",
          "tgn:2000370",
          "tgn:7007248",
          "tgn:7029392"
        ],
        "placetype": [
          "aat:300008347"
        ],
        "id": 2215541,
        "name:xx": "Calvin"
      }
    },
    {
      "geometry": {
        "type": "Point",
        "coordinates": [
          -83.1333,
          32
        ]
      },
      "type": "Feature",
      "properties": {
        "hierarchy": [
          "tgn:2215542",
          "tgn:1000001",
          "tgn:7012149",
          "tgn:2000336",
          "tgn:7007248",
          "tgn:7029392"
        ],
        "placetype": [
          "aat:300008347"
        ],
        "id": 2215542,
        "name:xx": "Calvin"
      }
    },
    {
      "geometry": {
        "type": "Point",
        "coordinates": [
          -81.35,
          34.8
        ]
      },
      "type": "Feature",
      "properties": {
        "hierarchy": [
          "tgn:2215544",
          "tgn:1000001",
          "tgn:2001736",
          "tgn:7012149",
          "tgn:7007712",
          "tgn:7029392"
        ],
        "placetype": [
          "aat:300008347"
        ],
        "id": 2215544,
        "name:xx": "Calvin"
      }
    },
    {
      "geometry": {
        "type": "Point",
        "coordinates": [
          -94.4167,
          34.5833
        ]
      },
      "type": "Feature",
      "properties": {
        "hierarchy": [
          "tgn:2215545",
          "tgn:1000001",
          "tgn:7016172",
          "tgn:7012149",
          "tgn:2000161",
          "tgn:7029392"
        ],
        "placetype": [
          "aat:300008699"
        ],
        "id": 2215545,
        "name:xx": "Calvin Branch"
      }
    },
    {
      "geometry": {
        "type": "Point",
        "coordinates": [
          -84.2667,
          36.1833
        ]
      },
      "type": "Feature",
      "properties": {
        "hierarchy": [
          "tgn:2215546",
          "tgn:2001837",
          "tgn:1000001",
          "tgn:7012149",
          "tgn:7007825",
          "tgn:7029392"
        ],
        "placetype": [
          "aat:300008699"
        ],
        "id": 2215546,
        "name:xx": "Calvin Branch"
      }
    },
    {
      "geometry": {
        "type": "Point",
        "coordinates": [
          -84.4833,
          36.2667
        ]
      },
      "type": "Feature",
      "properties": {
        "hierarchy": [
          "tgn:2215547",
          "tgn:1000001",
          "tgn:7012149",
          "tgn:2001912",
          "tgn:7007825",
          "tgn:7029392"
        ],
        "placetype": [
          "aat:300008699"
        ],
        "id": 2215547,
        "name:xx": "Calvin Branch"
      }
    },
    {
      "geometry": {
        "type": "Point",
        "coordinates": [
          -81.8333,
          37.7833
        ]
      },
      "type": "Feature",
      "properties": {
        "hierarchy": [
          "tgn:2215548",
          "tgn:1000001",
          "tgn:7012149",
          "tgn:2002273",
          "tgn:7013961",
          "tgn:7029392"
        ],
        "placetype": [
          "aat:300008699"
        ],
        "id": 2215548,
        "name:xx": "Calvin Branch"
      }
    },
    {
      "geometry": {
        "type": "Point",
        "coordinates": [
          -87.7333,
          30.5
        ]
      },
      "type": "Feature",
      "properties": {
        "hierarchy": [
          "tgn:2215549",
          "tgn:2000001",
          "tgn:7002659",
          "tgn:1000001",
          "tgn:7012149",
          "tgn:7029392"
        ],
        "placetype": [
          "aat:300006191"
        ],
        "id": 2215549,
        "name:xx": "Calvin Childress Number One Lake"
      }
    }
  ]
}
