{
  "geometry": {
    "type": "Point",
    "coordinates": [
      -75.8167,
      43.5167
    ]
  },
  "type": "Feature",
  "properties": {
    "hierarchy": [
      "tgn:2071863",
      "tgn:1000001",
      "tgn:7012149",
      "tgn:1002758",
      "tgn:7007568",
      "tgn:7029392"
    ],
    "placetype": [
      "aat:300008347"
    ],
    "id": 2071863,
    "name:xx": "Redfield"
  }
}
