{
  "type": "FeatureCollection",
  "features": [
    {
      "geometry": {
        "type": "Point",
        "coordinates": [
          4.2,
          50.233333
        ]
      },
      "type": "Feature",
      "properties": {
        "hierarchy": [
          "tgn:7247660",
          "tgn:7007877",
          "tgn:1000003",
          "tgn:1000063",
          "tgn:4012014",
          "tgn:7029392"
        ],
        "placetype": [
          "aat:300008347"
        ],
        "id": 7247660,
        "name:xx": "Chaudeville"
      }
    },
    {
      "geometry": {
        "type": "Point",
        "coordinates": [
          4.483333,
          50.7
        ]
      },
      "type": "Feature",
      "properties": {
        "hierarchy": [
          "tgn:7247661",
          "tgn:7018238",
          "tgn:1000003",
          "tgn:1000063",
          "tgn:4012014",
          "tgn:7029392"
        ],
        "placetype": [
          "aat:300008347"
        ],
        "id": 7247661,
        "name:xx": "Chaubrire"
      }
    },
    {
      "geometry": {
        "type": "Point",
        "coordinates": [
          5.683333,
          49.633333
        ]
      },
      "type": "Feature",
      "properties": {
        "hierarchy": [
          "tgn:7247662",
          "tgn:7003465",
          "tgn:1000003",
          "tgn:1000063",
          "tgn:4012014",
          "tgn:7029392"
        ],
        "placetype": [
          "aat:300008863"
        ],
        "id": 7247662,
        "name:xx": "Châtillon, Bois de"
      }
    },
    {
      "geometry": {
        "type": "Point",
        "coordinates": [
          5.7,
          49.633333
        ]
      },
      "type": "Feature",
      "properties": {
        "hierarchy": [
          "tgn:7247663",
          "tgn:7003465",
          "tgn:1000003",
          "tgn:1000063",
          "tgn:4012014",
          "tgn:7029392"
        ],
        "placetype": [
          "aat:300008347"
        ],
        "id": 7247663,
        "name:xx": "Châtillon"
      }
    },
    {
      "geometry": {
        "type": "Point",
        "coordinates": [
          4.55,
          50.383333
        ]
      },
      "type": "Feature",
      "properties": {
        "hierarchy": [
          "tgn:7247667",
          "tgn:7007877",
          "tgn:1000003",
          "tgn:1000063",
          "tgn:4012014",
          "tgn:7029392"
        ],
        "placetype": [
          "aat:300008863"
        ],
        "id": 7247667,
        "name:xx": "Châtelet, Bois de"
      }
    }
  ]
}
