{
  "type": "FeatureCollection",
  "features": [
    {
      "geometry": {
        "type": "Point",
        "coordinates": [
          5.466667,
          49.8
        ]
      },
      "type": "Feature",
      "properties": {
        "hierarchy": [
          "tgn:7244740",
          "tgn:7003465",
          "tgn:1000003",
          "tgn:1000063",
          "tgn:4012014",
          "tgn:7029392"
        ],
        "placetype": [
          "aat:300008347"
        ],
        "id": 7244740,
        "name:xx": "Assenois"
      }
    },
    {
      "geometry": {
        "type": "Point",
        "coordinates": [
          3.678281,
          51.039127
        ]
      },
      "type": "Feature",
      "properties": {
        "hierarchy": [
          "tgn:7244744",
          "tgn:7003457",
          "tgn:1000003",
          "tgn:1000063",
          "tgn:7018236",
          "tgn:7029392"
        ],
        "placetype": [
          "aat:300008347"
        ],
        "id": 7244744,
        "name:xx": "Assels"
      }
    },
    {
      "geometry": {
        "type": "Point",
        "coordinates": [
          3.754366,
          50.947989
        ]
      },
      "type": "Feature",
      "properties": {
        "hierarchy": [
          "tgn:7244745",
          "tgn:7003457",
          "tgn:1000003",
          "tgn:1000063",
          "tgn:7018236",
          "tgn:7029392"
        ],
        "placetype": [
          "aat:300008347"
        ],
        "id": 7244745,
        "name:xx": "Asselkouter"
      }
    },
    {
      "geometry": {
        "type": "Point",
        "coordinates": [
          5.75,
          50.716667
        ]
      },
      "type": "Feature",
      "properties": {
        "hierarchy": [
          "tgn:7244748",
          "tgn:7003460",
          "tgn:1000003",
          "tgn:1000063",
          "tgn:4012014",
          "tgn:7029392"
        ],
        "placetype": [
          "aat:300008699"
        ],
        "id": 7244748,
        "name:xx": "Asse, Ruisseau d'"
      }
    }
  ]
}
