{
  "geometry": {
    "type": "Point",
    "coordinates": [
      50.55,
      55.3667
    ]
  },
  "type": "Feature",
  "properties": {
    "hierarchy": [
      "tgn:1051395",
      "tgn:1000004",
      "tgn:7002435",
      "tgn:7011524",
      "tgn:7029392"
    ],
    "placetype": [
      "aat:300008347"
    ],
    "id": 1051395,
    "name:xx": "Chistopol"
  }
}
