{
  "geometry": {
    "type": "Point",
    "coordinates": [
      -91.8667,
      44.6333
    ]
  },
  "type": "Feature",
  "properties": {
    "hierarchy": [
      "tgn:2448779",
      "tgn:1000001",
      "tgn:7012149",
      "tgn:2002344",
      "tgn:7007922",
      "tgn:7029392"
    ],
    "placetype": [
      "aat:300008347"
    ],
    "id": 2448779,
    "name:xx": "Lima"
  }
}
