{
  "type": "FeatureCollection",
  "features": [
    {
      "geometry": {
        "type": "Point",
        "coordinates": [
          -95.0667,
          35
        ]
      },
      "type": "Feature",
      "properties": {
        "hierarchy": [
          "tgn:2462750",
          "tgn:1000001",
          "tgn:7012149",
          "tgn:2001661",
          "tgn:7007707",
          "tgn:7029392"
        ],
        "placetype": [
          "aat:300008798"
        ],
        "id": 2462750,
        "name:xx": "Little Yancy Mountain"
      }
    },
    {
      "geometry": {
        "type": "Point",
        "coordinates": [
          -80.6167,
          41.25
        ]
      },
      "type": "Feature",
      "properties": {
        "hierarchy": [
          "tgn:2462751",
          "tgn:1000001",
          "tgn:7012149",
          "tgn:7029392"
        ],
        "placetype": [
          "aat:300008699"
        ],
        "id": 2462751,
        "name:xx": "Little Yankee Run"
      }
    },
    {
      "geometry": {
        "type": "Point",
        "coordinates": [
          -123.6,
          44.7
        ]
      },
      "type": "Feature",
      "properties": {
        "hierarchy": [
          "tgn:2462752",
          "tgn:1000001",
          "tgn:7012149",
          "tgn:7007708",
          "tgn:7029392"
        ],
        "placetype": [
          "aat:300008707"
        ],
        "id": 2462752,
        "name:xx": "Little Yaquina River"
      }
    },
    {
      "geometry": {
        "type": "Point",
        "coordinates": [
          -105.5833,
          31.4833
        ]
      },
      "type": "Feature",
      "properties": {
        "hierarchy": [
          "tgn:2462753",
          "tgn:1000001",
          "tgn:7012149",
          "tgn:2002005",
          "tgn:7007826",
          "tgn:7029392"
        ],
        "placetype": [
          "aat:300006191"
        ],
        "id": 2462753,
        "name:xx": "Little Yeader Tank"
      }
    },
    {
      "geometry": {
        "type": "Point",
        "coordinates": [
          -83.2833,
          36.6667
        ]
      },
      "type": "Feature",
      "properties": {
        "hierarchy": [
          "tgn:2462754",
          "tgn:1000001",
          "tgn:7012149",
          "tgn:2002169",
          "tgn:7007919",
          "tgn:7029392"
        ],
        "placetype": [
          "aat:300008699"
        ],
        "id": 2462754,
        "name:xx": "Little Yellow Branch"
      }
    },
    {
      "geometry": {
        "type": "Point",
        "coordinates": [
          -87.4833,
          33.3667
        ]
      },
      "type": "Feature",
      "properties": {
        "hierarchy": [
          "tgn:2462755",
          "tgn:7002659",
          "tgn:1000001",
          "tgn:7012149",
          "tgn:2000062",
          "tgn:7029392"
        ],
        "placetype": [
          "aat:300008706"
        ],
        "id": 2462755,
        "name:xx": "Little Yellow Creek"
      }
    },
    {
      "geometry": {
        "type": "Point",
        "coordinates": [
          -87.5,
          33.6333
        ]
      },
      "type": "Feature",
      "properties": {
        "hierarchy": [
          "tgn:2462756",
          "tgn:7002659",
          "tgn:1000001",
          "tgn:7012149",
          "tgn:7029392"
        ],
        "placetype": [
          "aat:300008706"
        ],
        "id": 2462756,
        "name:xx": "Little Yellow Creek"
      }
    },
    {
      "geometry": {
        "type": "Point",
        "coordinates": [
          -87.9833,
          33.9
        ]
      },
      "type": "Feature",
      "properties": {
        "hierarchy": [
          "tgn:2462757",
          "tgn:7002659",
          "tgn:1000001",
          "tgn:7012149",
          "tgn:2000037",
          "tgn:7029392"
        ],
        "placetype": [
          "aat:300008706"
        ],
        "id": 2462757,
        "name:xx": "Little Yellow Creek"
      }
    },
    {
      "geometry": {
        "type": "Point",
        "coordinates": [
          -83.9,
          34.4333
        ]
      },
      "type": "Feature",
      "properties": {
        "hierarchy": [
          "tgn:2462758",
          "tgn:1000001",
          "tgn:7012149",
          "tgn:2000360",
          "tgn:7007248",
          "tgn:7029392"
        ],
        "placetype": [
          "aat:300008706"
        ],
        "id": 2462758,
        "name:xx": "Little Yellow Creek"
      }
    },
    {
      "geometry": {
        "type": "Point",
        "coordinates": [
          -85.9,
          41.5333
        ]
      },
      "type": "Feature",
      "properties": {
        "hierarchy": [
          "tgn:2462759",
          "tgn:1000001",
          "tgn:7012149",
          "tgn:1002353",
          "tgn:7007252",
          "tgn:7029392"
        ],
        "placetype": [
          "aat:300008706"
        ],
        "id": 2462759,
        "name:xx": "Little Yellow Creek"
      }
    }
  ]
}
