{
  "geometry": {
    "type": "Point",
    "coordinates": [
      -113.6833,
      45.25
    ]
  },
  "type": "Feature",
  "properties": {
    "hierarchy": [
      "tgn:2521829",
      "tgn:1000001",
      "tgn:7012149",
      "tgn:7029392"
    ],
    "placetype": [
      "aat:300008798"
    ],
    "id": 2521829,
    "name:xx": "Monument Peak"
  }
}
