{
  "geometry": {
    "type": "Point",
    "coordinates": [
      -112.2167,
      37.9833
    ]
  },
  "type": "Feature",
  "properties": {
    "hierarchy": [
      "tgn:2678626",
      "tgn:1000001",
      "tgn:2002109",
      "tgn:7012149",
      "tgn:7007827",
      "tgn:7029392"
    ],
    "placetype": [
      "aat:300008706"
    ],
    "id": 2678626,
    "name:xx": "South Fork Deer Creek"
  }
}
