{
  "geometry": {
    "type": "Point",
    "coordinates": [
      -115.3667,
      44.2667
    ]
  },
  "type": "Feature",
  "properties": {
    "hierarchy": [
      "tgn:2542397",
      "tgn:1000001",
      "tgn:2000459",
      "tgn:7012149",
      "tgn:7007250",
      "tgn:7029392"
    ],
    "placetype": [
      "aat:300008706"
    ],
    "id": 2542397,
    "name:xx": "No Name Creek"
  }
}
