{
  "geometry": {
    "type": "Point",
    "coordinates": [
      -86.7833,
      36.9333
    ]
  },
  "type": "Feature",
  "properties": {
    "hierarchy": [
      "tgn:2038148",
      "tgn:1000001",
      "tgn:7012149",
      "tgn:2000815",
      "tgn:7007255",
      "tgn:7029392"
    ],
    "placetype": [
      "aat:300008347",
      "aat:300387210"
    ],
    "id": 2038148,
    "name:xx": "Chandlers Chapel"
  }
}
