{
  "type": "FeatureCollection",
  "features": [
    {
      "geometry": {
        "type": "Point",
        "coordinates": [
          15.816667,
          39.716667
        ]
      },
      "type": "Feature",
      "properties": {
        "hierarchy": [
          "tgn:7047670",
          "tgn:1003450",
          "tgn:7007850",
          "tgn:1000003",
          "tgn:1000080",
          "tgn:7029392"
        ],
        "placetype": [
          "aat:300008347"
        ],
        "id": 7047670,
        "name:xx": "Cirella"
      }
    },
    {
      "geometry": {
        "type": "Point",
        "coordinates": [
          16.1,
          38.233333
        ]
      },
      "type": "Feature",
      "properties": {
        "hierarchy": [
          "tgn:7047671",
          "tgn:7007850",
          "tgn:1003491",
          "tgn:1000003",
          "tgn:1000080",
          "tgn:7029392"
        ],
        "placetype": [
          "aat:300008347"
        ],
        "id": 7047671,
        "name:xx": "Cirella"
      }
    },
    {
      "geometry": {
        "type": "Point",
        "coordinates": [
          13.05,
          41.216667
        ]
      },
      "type": "Feature",
      "properties": {
        "hierarchy": [
          "tgn:7047675",
          "tgn:7003136",
          "tgn:1000003",
          "tgn:7003080",
          "tgn:1000080",
          "tgn:7029392"
        ],
        "placetype": [
          "aat:300008850"
        ],
        "id": 7047675,
        "name:xx": "Circeo, Capo"
      }
    },
    {
      "geometry": {
        "type": "Point",
        "coordinates": [
          13.05,
          41.216667
        ]
      },
      "type": "Feature",
      "properties": {
        "hierarchy": [
          "tgn:7047676",
          "tgn:7003136",
          "tgn:1000003",
          "tgn:7003080",
          "tgn:1000080",
          "tgn:7029392"
        ],
        "placetype": [
          "aat:300008795"
        ],
        "id": 7047676,
        "name:xx": "Circello, Monte"
      }
    },
    {
      "geometry": {
        "type": "Point",
        "coordinates": [
          14.8,
          41.35
        ]
      },
      "type": "Feature",
      "properties": {
        "hierarchy": [
          "tgn:7047677",
          "tgn:7004595",
          "tgn:7003005",
          "tgn:1000003",
          "tgn:1000080",
          "tgn:7029392"
        ],
        "placetype": [
          "aat:300008347"
        ],
        "id": 7047677,
        "name:xx": "Circello"
      }
    },
    {
      "geometry": {
        "type": "Point",
        "coordinates": [
          14,
          42.5
        ]
      },
      "type": "Feature",
      "properties": {
        "hierarchy": [
          "tgn:7047678",
          "tgn:7009084",
          "tgn:1003484",
          "tgn:1000003",
          "tgn:1000080",
          "tgn:7029392"
        ],
        "placetype": [
          "aat:300008347"
        ],
        "id": 7047678,
        "name:xx": "Cipresso"
      }
    },
    {
      "geometry": {
        "type": "Point",
        "coordinates": [
          7.933333,
          43.85
        ]
      },
      "type": "Feature",
      "properties": {
        "hierarchy": [
          "tgn:7047679",
          "tgn:1000003",
          "tgn:7003141",
          "tgn:7003236",
          "tgn:1000080",
          "tgn:7029392"
        ],
        "placetype": [
          "aat:300008347"
        ],
        "id": 7047679,
        "name:xx": "Cipressa"
      }
    }
  ]
}
