{
  "geometry": {
    "type": "Point",
    "coordinates": [
      -75.2667,
      40.65
    ]
  },
  "type": "Feature",
  "properties": {
    "hierarchy": [
      "tgn:2599644",
      "tgn:1000001",
      "tgn:7012149",
      "tgn:1002729",
      "tgn:7007710",
      "tgn:7029392"
    ],
    "placetype": [
      "aat:300008347"
    ],
    "id": 2599644,
    "name:xx": "Prospect Park"
  }
}
