{
  "geometry": {
    "type": "Point",
    "coordinates": [
      -111.2333,
      43.2167
    ]
  },
  "type": "Feature",
  "properties": {
    "hierarchy": [
      "tgn:2236446",
      "tgn:1000001",
      "tgn:2000461",
      "tgn:7012149",
      "tgn:7007250",
      "tgn:7029392"
    ],
    "placetype": [
      "aat:300266640"
    ],
    "id": 2236446,
    "name:xx": "Chicken Ridge"
  }
}
