{
  "type": "FeatureCollection",
  "features": [
    {
      "geometry": {
        "type": "Point",
        "coordinates": [
          17.1667,
          46.6667
        ]
      },
      "type": "Feature",
      "properties": {
        "hierarchy": [
          "tgn:4012463",
          "tgn:1000003",
          "tgn:1000474",
          "tgn:7006278",
          "tgn:7029392"
        ],
        "placetype": [
          "aat:300008347"
        ],
        "id": 4012463,
        "name:xx": "Zalavár"
      }
    },
    {
      "geometry": {
        "type": "Point",
        "coordinates": [
          -4.133333,
          40.966667
        ]
      },
      "type": "Feature",
      "properties": {
        "hierarchy": [
          "tgn:4012465",
          "tgn:7002839",
          "tgn:7001158",
          "tgn:1000003",
          "tgn:1000095",
          "tgn:7029392"
        ],
        "placetype": [
          "aat:300008347"
        ],
        "id": 4012465,
        "name:xx": "Zamarramala"
      }
    },
    {
      "geometry": {
        "type": "Point",
        "coordinates": [
          9.85,
          45.683333
        ]
      },
      "type": "Feature",
      "properties": {
        "hierarchy": [
          "tgn:4012469",
          "tgn:7005023",
          "tgn:1000003",
          "tgn:7003237",
          "tgn:1000080",
          "tgn:7029392"
        ],
        "placetype": [
          "aat:300008347"
        ],
        "id": 4012469,
        "name:xx": "Zandobbio"
      }
    }
  ]
}
