{
  "geometry": {
    "type": "Point",
    "coordinates": [
      -119.0667,
      38.3333
    ]
  },
  "type": "Feature",
  "properties": {
    "hierarchy": [
      "tgn:2305541",
      "tgn:1000001",
      "tgn:7012149",
      "tgn:7029392"
    ],
    "placetype": [
      "aat:300008761"
    ],
    "id": 2305541,
    "name:xx": "East Canyon"
  }
}
