{
  "geometry": {
    "type": "Point",
    "coordinates": [
      -78.2667,
      38.75
    ]
  },
  "type": "Feature",
  "properties": {
    "hierarchy": [
      "tgn:2362537",
      "tgn:1000001",
      "tgn:7012149",
      "tgn:2002193",
      "tgn:7007919",
      "tgn:7029392"
    ],
    "placetype": [
      "aat:300008699"
    ],
    "id": 2362537,
    "name:xx": "Greasy Run"
  }
}
