{
  "geometry": {
    "type": "Point",
    "coordinates": [
      -73.45,
      42.6667
    ]
  },
  "type": "Feature",
  "properties": {
    "hierarchy": [
      "tgn:2265247",
      "tgn:1000001",
      "tgn:7012149",
      "tgn:1002821",
      "tgn:7007568",
      "tgn:7029392"
    ],
    "placetype": [
      "aat:300008706"
    ],
    "id": 2265247,
    "name:xx": "Cranberry Vly Creek"
  }
}
