{
  "geometry": {
    "type": "Point",
    "coordinates": [
      31.293889,
      30.945
    ]
  },
  "type": "Feature",
  "properties": {
    "hierarchy": [
      "tgn:7521847",
      "tgn:7001242",
      "tgn:1001059",
      "tgn:7016833",
      "tgn:7029392"
    ],
    "placetype": [
      "aat:300008347"
    ],
    "name:en": "Al Baylūq",
    "id": 7521847
  }
}
