{
  "geometry": {
    "type": "Point",
    "coordinates": [
      -116.15,
      48.2333
    ]
  },
  "type": "Feature",
  "properties": {
    "hierarchy": [
      "tgn:2695027",
      "tgn:1000001",
      "tgn:2000460",
      "tgn:7012149",
      "tgn:7007250",
      "tgn:7029392"
    ],
    "placetype": [
      "aat:300008680"
    ],
    "id": 2695027,
    "name:xx": "Still Lake"
  }
}
