{
  "geometry": {
    "type": "Point",
    "coordinates": [
      26.6667,
      53.2667
    ]
  },
  "type": "Feature",
  "properties": {
    "hierarchy": [
      "tgn:7010226",
      "tgn:1003391",
      "tgn:1000003",
      "tgn:7006657",
      "tgn:7029392"
    ],
    "placetype": [
      "aat:300008347"
    ],
    "id": 7010226,
    "name:xx": "Nesvizh"
  }
}
