{
  "geometry": {
    "type": "Point",
    "coordinates": [
      -69.152,
      19.301
    ]
  },
  "type": "Feature",
  "properties": {
    "hierarchy": [
      "tgn:1011163",
      "tgn:7005416",
      "tgn:1000001",
      "tgn:7005388",
      "tgn:7029392"
    ],
    "placetype": [
      "aat:300008850"
    ],
    "id": 1011163,
    "name:xx": "Samaná, Cabo"
  }
}
