{
  "geometry": {
    "type": "Point",
    "coordinates": [
      -79.8833,
      40.1167
    ]
  },
  "type": "Feature",
  "properties": {
    "hierarchy": [
      "tgn:2735237",
      "tgn:1000001",
      "tgn:7012149",
      "tgn:1002995",
      "tgn:7007710",
      "tgn:7029392"
    ],
    "placetype": [
      "aat:300008761"
    ],
    "id": 2735237,
    "name:xx": "Twilight Hollow"
  }
}
