{
  "geometry": {
    "type": "Point",
    "coordinates": [
      -70.016667,
      -52.95
    ]
  },
  "type": "Feature",
  "properties": {
    "hierarchy": [
      "tgn:7310701",
      "tgn:1001702",
      "tgn:1000049",
      "tgn:1000002",
      "tgn:7029392"
    ],
    "placetype": [
      "aat:300008795"
    ],
    "id": 7310701,
    "name:xx": "Morrión, Cerro"
  }
}
