{
  "geometry": {
    "type": "Point",
    "coordinates": [
      -80.6667,
      38.8833
    ]
  },
  "type": "Feature",
  "properties": {
    "hierarchy": [
      "tgn:2469340",
      "tgn:1000001",
      "tgn:7012149",
      "tgn:7013961",
      "tgn:7029392"
    ],
    "placetype": [
      "aat:300008699"
    ],
    "id": 2469340,
    "name:xx": "Longshoal Run"
  }
}
