{
  "geometry": {
    "type": "Point",
    "coordinates": [
      -85.0833,
      35.4167
    ]
  },
  "type": "Feature",
  "properties": {
    "hierarchy": [
      "tgn:2178457",
      "tgn:1000001",
      "tgn:7012149",
      "tgn:2001869",
      "tgn:7007825",
      "tgn:7029392"
    ],
    "placetype": [
      "aat:300266640"
    ],
    "id": 2178457,
    "name:xx": "Blackoak Ridge"
  }
}
