{
  "type": "FeatureCollection",
  "features": [
    {
      "geometry": {
        "type": "Point",
        "coordinates": [
          -73.5833,
          43.0833
        ]
      },
      "type": "Feature",
      "properties": {
        "hierarchy": [
          "tgn:2072900",
          "tgn:1000001",
          "tgn:7012149",
          "tgn:1002871",
          "tgn:7007568",
          "tgn:7029392"
        ],
        "placetype": [
          "aat:300008347"
        ],
        "id": 2072900,
        "name:xx": "Victory Mills"
      }
    },
    {
      "geometry": {
        "type": "Point",
        "coordinates": [
          -75.7,
          43.2333
        ]
      },
      "type": "Feature",
      "properties": {
        "hierarchy": [
          "tgn:2072901",
          "tgn:1000001",
          "tgn:7012149",
          "tgn:7014287",
          "tgn:7007568",
          "tgn:7029392"
        ],
        "placetype": [
          "aat:300008347"
        ],
        "id": 2072901,
        "name:xx": "Vienna"
      }
    },
    {
      "geometry": {
        "type": "Point",
        "coordinates": [
          -73.8667,
          42.0833
        ]
      },
      "type": "Feature",
      "properties": {
        "hierarchy": [
          "tgn:2072902",
          "tgn:1000001",
          "tgn:7013638",
          "tgn:7012149",
          "tgn:7007568",
          "tgn:7029392"
        ],
        "placetype": [
          "aat:300008347",
          "aat:300387210"
        ],
        "id": 2072902,
        "name:xx": "Viewmonte"
      }
    },
    {
      "geometry": {
        "type": "Point",
        "coordinates": [
          -73.1833,
          40.85
        ]
      },
      "type": "Feature",
      "properties": {
        "hierarchy": [
          "tgn:2072906",
          "tgn:1000001",
          "tgn:7012149",
          "tgn:1002924",
          "tgn:7007568",
          "tgn:7029392"
        ],
        "placetype": [
          "aat:300008347"
        ],
        "id": 2072906,
        "name:xx": "Village of the Branch"
      }
    },
    {
      "geometry": {
        "type": "Point",
        "coordinates": [
          -77.4,
          42.8333
        ]
      },
      "type": "Feature",
      "properties": {
        "hierarchy": [
          "tgn:2072909",
          "tgn:1000001",
          "tgn:7012149",
          "tgn:1002747",
          "tgn:7007568",
          "tgn:7029392"
        ],
        "placetype": [
          "aat:300008347",
          "aat:300387210"
        ],
        "id": 2072909,
        "name:xx": "Vincent"
      }
    }
  ]
}
