{
  "geometry": {
    "type": "Point",
    "coordinates": [
      -66.9167,
      10.416
    ]
  },
  "type": "Feature",
  "properties": {
    "hierarchy": [
      "tgn:1134912",
      "tgn:1000002",
      "tgn:1000059",
      "tgn:7029392"
    ],
    "placetype": [
      "aat:300008706",
      "aat:300008699"
    ],
    "id": 1134912,
    "name:xx": "Turmerito, Río"
  }
}
