{
  "geometry": {
    "type": "Point",
    "coordinates": [
      -81.6833,
      34.8167
    ]
  },
  "type": "Feature",
  "properties": {
    "hierarchy": [
      "tgn:2174366",
      "tgn:1000001",
      "tgn:7012149",
      "tgn:2001768",
      "tgn:7007712",
      "tgn:7029392"
    ],
    "placetype": [
      "aat:300008699"
    ],
    "id": 2174366,
    "name:xx": "Bishop Branch"
  }
}
