{
  "geometry": {
    "type": "Point",
    "coordinates": [
      -85.9667,
      32.0667
    ]
  },
  "type": "Feature",
  "properties": {
    "hierarchy": [
      "tgn:2490728",
      "tgn:7002659",
      "tgn:1000001",
      "tgn:7012149",
      "tgn:7029392"
    ],
    "placetype": [
      "aat:300008706"
    ],
    "id": 2490728,
    "name:xx": "Mannings Creek"
  }
}
