{
  "geometry": {
    "type": "Point",
    "coordinates": [
      105.1167,
      19.55
    ]
  },
  "type": "Feature",
  "properties": {
    "hierarchy": [
      "tgn:1087219",
      "tgn:1000004",
      "tgn:7001053",
      "tgn:1000145",
      "tgn:7029392"
    ],
    "placetype": [
      "aat:300008347"
    ],
    "id": 1087219,
    "name:xx": "Quí Châu"
  }
}
