{
  "geometry": {
    "type": "Point",
    "coordinates": [
      -96.05,
      48.9833
    ]
  },
  "type": "Feature",
  "properties": {
    "hierarchy": [
      "tgn:2582318",
      "tgn:1000001",
      "tgn:7012149",
      "tgn:2001066",
      "tgn:7007521",
      "tgn:7029392"
    ],
    "placetype": [
      "aat:300006075"
    ],
    "id": 2582318,
    "name:xx": "Pine Creek Ditch"
  }
}
