{
  "geometry": {
    "type": "Point",
    "coordinates": [
      17.9333,
      -3.1167
    ]
  },
  "type": "Feature",
  "properties": {
    "hierarchy": [
      "tgn:1089434",
      "tgn:1001143",
      "tgn:7001242",
      "tgn:1000159",
      "tgn:7029392"
    ],
    "placetype": [
      "aat:300008347"
    ],
    "id": 1089434,
    "name:xx": "Nsontin"
  }
}
