{
  "type": "FeatureCollection",
  "features": [
    {
      "geometry": {
        "type": "Point",
        "coordinates": [
          30.1872,
          31.269051
        ]
      },
      "type": "Feature",
      "properties": {
        "hierarchy": [
          "tgn:7530460",
          "tgn:7001242",
          "tgn:1001075",
          "tgn:7016833",
          "tgn:7029392"
        ],
        "placetype": [
          "aat:300000206"
        ],
        "name:en": "'Izbat Qāsim",
        "id": 7530460
      }
    },
    {
      "geometry": {
        "type": "Point",
        "coordinates": [
          30.151824,
          31.259096
        ]
      },
      "type": "Feature",
      "properties": {
        "hierarchy": [
          "tgn:7530461",
          "tgn:7001242",
          "tgn:1001075",
          "tgn:7016833",
          "tgn:7029392"
        ],
        "placetype": [
          "aat:300008347"
        ],
        "name:en": "Zirzārah",
        "id": 7530461
      }
    },
    {
      "geometry": {
        "type": "Point",
        "coordinates": [
          30.147889,
          31.268418
        ]
      },
      "type": "Feature",
      "properties": {
        "hierarchy": [
          "tgn:7530462",
          "tgn:7001242",
          "tgn:1001075",
          "tgn:7016833",
          "tgn:7029392"
        ],
        "placetype": [
          "aat:300000206"
        ],
        "name:en": "'Izbat as Sittīn",
        "id": 7530462
      }
    },
    {
      "geometry": {
        "type": "Point",
        "coordinates": [
          30.13925,
          31.257983
        ]
      },
      "type": "Feature",
      "properties": {
        "hierarchy": [
          "tgn:7530463",
          "tgn:7001242",
          "tgn:7016833",
          "tgn:1001079",
          "tgn:7029392"
        ],
        "placetype": [
          "aat:300008347"
        ],
        "name:en": "'Izbat Fāyid",
        "id": 7530463
      }
    },
    {
      "geometry": {
        "type": "Point",
        "coordinates": [
          30.082735,
          31.277219
        ]
      },
      "type": "Feature",
      "properties": {
        "hierarchy": [
          "tgn:7530464",
          "tgn:7001242",
          "tgn:7016833",
          "tgn:7029392"
        ],
        "placetype": [
          "aat:300006075"
        ],
        "name:en": "At Tur'ah ar Ra'īsīyah ash Sharqīyah",
        "id": 7530464
      }
    },
    {
      "geometry": {
        "type": "Point",
        "coordinates": [
          30.127028,
          31.266641
        ]
      },
      "type": "Feature",
      "properties": {
        "hierarchy": [
          "tgn:7530465",
          "tgn:7001242",
          "tgn:7016833",
          "tgn:1001079",
          "tgn:7029392"
        ],
        "placetype": [
          "aat:300008347"
        ],
        "name:en": "'Izbat aţ Ţarḩ",
        "id": 7530465
      }
    },
    {
      "geometry": {
        "type": "Point",
        "coordinates": [
          30.094856,
          31.252498
        ]
      },
      "type": "Feature",
      "properties": {
        "hierarchy": [
          "tgn:7530466",
          "tgn:7001242",
          "tgn:1001075",
          "tgn:7016833",
          "tgn:7029392"
        ],
        "placetype": [
          "aat:300008347"
        ],
        "name:en": "'Izbat ash Shandīdī",
        "id": 7530466
      }
    },
    {
      "geometry": {
        "type": "Point",
        "coordinates": [
          30.087419,
          31.251377
        ]
      },
      "type": "Feature",
      "properties": {
        "hierarchy": [
          "tgn:7530467",
          "tgn:7001242",
          "tgn:1001075",
          "tgn:7016833",
          "tgn:7029392"
        ],
        "placetype": [
          "aat:300000206"
        ],
        "name:en": "'Izbat al Bank",
        "id": 7530467
      }
    },
    {
      "geometry": {
        "type": "Point",
        "coordinates": [
          30.055877,
          31.259571
        ]
      },
      "type": "Feature",
      "properties": {
        "hierarchy": [
          "tgn:7530468",
          "tgn:7001242",
          "tgn:7016833",
          "tgn:1001079",
          "tgn:7029392"
        ],
        "placetype": [
          "aat:300008347"
        ],
        "name:en": "'Izbat Ḩawḑ 12",
        "id": 7530468
      }
    },
    {
      "geometry": {
        "type": "Point",
        "coordinates": [
          30.052708,
          31.252137
        ]
      },
      "type": "Feature",
      "properties": {
        "hierarchy": [
          "tgn:7530469",
          "tgn:7001242",
          "tgn:7016833",
          "tgn:1001079",
          "tgn:7029392"
        ],
        "placetype": [
          "aat:300008347"
        ],
        "name:en": "'Izbat Dibbānah",
        "id": 7530469
      }
    }
  ]
}
