{
  "geometry": {
    "type": "Point",
    "coordinates": [
      117.9667,
      26.75
    ]
  },
  "type": "Feature",
  "properties": {
    "hierarchy": [
      "tgn:1139814",
      "tgn:1000004",
      "tgn:7001796",
      "tgn:1000111",
      "tgn:7029392"
    ],
    "placetype": [
      "aat:300008347"
    ],
    "id": 1139814,
    "name:xx": "Xiayang"
  }
}
