{
  "geometry": {
    "type": "Point",
    "coordinates": [
      17.1667,
      46.7167
    ]
  },
  "type": "Feature",
  "properties": {
    "hierarchy": [
      "tgn:1042447",
      "tgn:1000003",
      "tgn:1000474",
      "tgn:7006278",
      "tgn:7029392"
    ],
    "placetype": [
      "aat:300008347"
    ],
    "id": 1042447,
    "name:xx": "Sármellék"
  }
}
