{
  "geometry": {
    "type": "Point",
    "coordinates": [
      74.313889,
      34.463889
    ]
  },
  "type": "Feature",
  "properties": {
    "hierarchy": [
      "tgn:7586579",
      "tgn:1000004",
      "tgn:7000198",
      "tgn:7000799",
      "tgn:7029392"
    ],
    "placetype": [
      "aat:300008699"
    ],
    "name:en": "Chal Nār",
    "id": 7586579
  }
}
