{
  "geometry": {
    "type": "Point",
    "coordinates": [
      -75.25,
      38.8167
    ]
  },
  "type": "Feature",
  "properties": {
    "hierarchy": [
      "tgn:2554066",
      "tgn:1002933",
      "tgn:1000001",
      "tgn:7012149",
      "tgn:7007239",
      "tgn:7029392"
    ],
    "placetype": [
      "aat:300008680"
    ],
    "id": 2554066,
    "name:xx": "Oak Pond"
  }
}
