{
  "geometry": {
    "type": "Point",
    "coordinates": [
      1.4833,
      47.65
    ]
  },
  "type": "Feature",
  "properties": {
    "hierarchy": [
      "tgn:1035310",
      "tgn:1000003",
      "tgn:7002877",
      "tgn:1000070",
      "tgn:7029392"
    ],
    "placetype": [
      "aat:300008347"
    ],
    "id": 1035310,
    "name:xx": "Saint-Dyé-sur-Loire"
  }
}
