{
  "geometry": {
    "type": "Point",
    "coordinates": [
      -147.4667,
      64.7667
    ]
  },
  "type": "Feature",
  "properties": {
    "hierarchy": [
      "tgn:2242542",
      "tgn:7006450",
      "tgn:1000001",
      "tgn:7019674",
      "tgn:7012149",
      "tgn:7029392"
    ],
    "placetype": [
      "aat:300008706"
    ],
    "id": 2242542,
    "name:xx": "Clear Creek"
  }
}
