{
  "type": "FeatureCollection",
  "features": [
    {
      "geometry": {
        "type": "Point",
        "coordinates": [
          -141.1167,
          64.0833
        ]
      },
      "type": "Feature",
      "properties": {
        "hierarchy": [
          "tgn:2781790",
          "tgn:7006450",
          "tgn:1000001",
          "tgn:7012149",
          "tgn:2000085",
          "tgn:7029392"
        ],
        "placetype": [
          "aat:300008706"
        ],
        "id": 2781790,
        "name:xx": "Woods Creek"
      }
    },
    {
      "geometry": {
        "type": "Point",
        "coordinates": [
          -146.5,
          62.0667
        ]
      },
      "type": "Feature",
      "properties": {
        "hierarchy": [
          "tgn:2781791",
          "tgn:7006450",
          "tgn:1000001",
          "tgn:7012149",
          "tgn:2000086",
          "tgn:7029392"
        ],
        "placetype": [
          "aat:300008706"
        ],
        "id": 2781791,
        "name:xx": "Woods Creek"
      }
    },
    {
      "geometry": {
        "type": "Point",
        "coordinates": [
          -159.65,
          63.4
        ]
      },
      "type": "Feature",
      "properties": {
        "hierarchy": [
          "tgn:2781792",
          "tgn:7006450",
          "tgn:1000001",
          "tgn:7012149",
          "tgn:2000089",
          "tgn:7029392"
        ],
        "placetype": [
          "aat:300008706"
        ],
        "id": 2781792,
        "name:xx": "Woods Creek"
      }
    },
    {
      "geometry": {
        "type": "Point",
        "coordinates": [
          -109.1333,
          33.9667
        ]
      },
      "type": "Feature",
      "properties": {
        "hierarchy": [
          "tgn:2781793",
          "tgn:2000090",
          "tgn:1000001",
          "tgn:7006451",
          "tgn:7012149",
          "tgn:7029392"
        ],
        "placetype": [
          "aat:300008706"
        ],
        "id": 2781793,
        "name:xx": "Woods Creek"
      }
    },
    {
      "geometry": {
        "type": "Point",
        "coordinates": [
          -124.15,
          40.2
        ]
      },
      "type": "Feature",
      "properties": {
        "hierarchy": [
          "tgn:2781794",
          "tgn:1000001",
          "tgn:7012149",
          "tgn:2000181",
          "tgn:7007157",
          "tgn:7029392"
        ],
        "placetype": [
          "aat:300008706"
        ],
        "id": 2781794,
        "name:xx": "Woods Creek"
      }
    },
    {
      "geometry": {
        "type": "Point",
        "coordinates": [
          -118.4,
          36.9333
        ]
      },
      "type": "Feature",
      "properties": {
        "hierarchy": [
          "tgn:2781795",
          "tgn:1000001",
          "tgn:7012149",
          "tgn:1002392",
          "tgn:7007157",
          "tgn:7029392"
        ],
        "placetype": [
          "aat:300008706"
        ],
        "id": 2781795,
        "name:xx": "Woods Creek"
      }
    },
    {
      "geometry": {
        "type": "Point",
        "coordinates": [
          -123.0167,
          38.6
        ]
      },
      "type": "Feature",
      "properties": {
        "hierarchy": [
          "tgn:2781796",
          "tgn:1000001",
          "tgn:7012149",
          "tgn:7007157",
          "tgn:7014516",
          "tgn:7029392"
        ],
        "placetype": [
          "aat:300008706"
        ],
        "id": 2781796,
        "name:xx": "Woods Creek"
      }
    },
    {
      "geometry": {
        "type": "Point",
        "coordinates": [
          -121.2333,
          39.3167
        ]
      },
      "type": "Feature",
      "properties": {
        "hierarchy": [
          "tgn:2781797",
          "tgn:1000001",
          "tgn:7012149",
          "tgn:7007157",
          "tgn:1003050",
          "tgn:7029392"
        ],
        "placetype": [
          "aat:300008706"
        ],
        "id": 2781797,
        "name:xx": "Woods Creek"
      }
    },
    {
      "geometry": {
        "type": "Point",
        "coordinates": [
          -120.3333,
          38.0333
        ]
      },
      "type": "Feature",
      "properties": {
        "hierarchy": [
          "tgn:2781798",
          "tgn:1000001",
          "tgn:7012149",
          "tgn:7007157",
          "tgn:1002957",
          "tgn:7029392"
        ],
        "placetype": [
          "aat:300008706"
        ],
        "id": 2781798,
        "name:xx": "Woods Creek"
      }
    },
    {
      "geometry": {
        "type": "Point",
        "coordinates": [
          -105.8833,
          39.7167
        ]
      },
      "type": "Feature",
      "properties": {
        "hierarchy": [
          "tgn:2781799",
          "tgn:1000001",
          "tgn:2000201",
          "tgn:7012149",
          "tgn:7007158",
          "tgn:7029392"
        ],
        "placetype": [
          "aat:300008706"
        ],
        "id": 2781799,
        "name:xx": "Woods Creek"
      }
    }
  ]
}
