{
  "geometry": {
    "type": "Point",
    "coordinates": [
      76.838859,
      30.060495
    ]
  },
  "type": "Feature",
  "properties": {
    "hierarchy": [
      "tgn:7583164",
      "tgn:1000004",
      "tgn:1001871",
      "tgn:7000198",
      "tgn:7029392"
    ],
    "placetype": [
      "aat:300008347"
    ],
    "name:en": "Sarāi Sukhi",
    "id": 7583164
  }
}
