{
  "type": "FeatureCollection",
  "features": [
    {
      "geometry": {
        "type": "Point",
        "coordinates": [
          -71.3667,
          41.6667
        ]
      },
      "type": "Feature",
      "properties": {
        "hierarchy": [
          "tgn:2642080",
          "tgn:1002541",
          "tgn:1000001",
          "tgn:7012149",
          "tgn:7007711",
          "tgn:7029392"
        ],
        "placetype": [
          "aat:300008850"
        ],
        "id": 2642080,
        "name:xx": "Sand Point"
      }
    },
    {
      "geometry": {
        "type": "Point",
        "coordinates": [
          -94.7167,
          29.85
        ]
      },
      "type": "Feature",
      "properties": {
        "hierarchy": [
          "tgn:2642081",
          "tgn:1000001",
          "tgn:7012149",
          "tgn:1002251",
          "tgn:7007826",
          "tgn:7029392"
        ],
        "placetype": [
          "aat:300008850"
        ],
        "id": 2642081,
        "name:xx": "Sand Point"
      }
    },
    {
      "geometry": {
        "type": "Point",
        "coordinates": [
          -96.4833,
          28.5667
        ]
      },
      "type": "Feature",
      "properties": {
        "hierarchy": [
          "tgn:2642082",
          "tgn:1000001",
          "tgn:7012149",
          "tgn:2001950",
          "tgn:7007826",
          "tgn:7029392"
        ],
        "placetype": [
          "aat:300008850"
        ],
        "id": 2642082,
        "name:xx": "Sand Point"
      }
    },
    {
      "geometry": {
        "type": "Point",
        "coordinates": [
          -122.25,
          47.6667
        ]
      },
      "type": "Feature",
      "properties": {
        "hierarchy": [
          "tgn:2642083",
          "tgn:1000001",
          "tgn:7012149",
          "tgn:7018871",
          "tgn:7007920",
          "tgn:7029392"
        ],
        "placetype": [
          "aat:300008850"
        ],
        "id": 2642083,
        "name:xx": "Sand Point"
      }
    },
    {
      "geometry": {
        "type": "Point",
        "coordinates": [
          -117.75,
          48.9333
        ]
      },
      "type": "Feature",
      "properties": {
        "hierarchy": [
          "tgn:2642084",
          "tgn:1000001",
          "tgn:7012149",
          "tgn:2002250",
          "tgn:7007920",
          "tgn:7029392"
        ],
        "placetype": [
          "aat:300008850"
        ],
        "id": 2642084,
        "name:xx": "Sand Point"
      }
    },
    {
      "geometry": {
        "type": "Point",
        "coordinates": [
          -124.7,
          48.1167
        ]
      },
      "type": "Feature",
      "properties": {
        "hierarchy": [
          "tgn:2642085",
          "tgn:1000001",
          "tgn:1002271",
          "tgn:7012149",
          "tgn:7007920",
          "tgn:7029392"
        ],
        "placetype": [
          "aat:300008850"
        ],
        "id": 2642085,
        "name:xx": "Sand Point"
      }
    },
    {
      "geometry": {
        "type": "Point",
        "coordinates": [
          -90.95,
          46.9333
        ]
      },
      "type": "Feature",
      "properties": {
        "hierarchy": [
          "tgn:2642086",
          "tgn:2002308",
          "tgn:1000001",
          "tgn:7012149",
          "tgn:7007922",
          "tgn:7029392"
        ],
        "placetype": [
          "aat:300008850"
        ],
        "id": 2642086,
        "name:xx": "Sand Point"
      }
    },
    {
      "geometry": {
        "type": "Point",
        "coordinates": [
          -90.45,
          46.9833
        ]
      },
      "type": "Feature",
      "properties": {
        "hierarchy": [
          "tgn:2642087",
          "tgn:2002306",
          "tgn:1000001",
          "tgn:7012149",
          "tgn:7007922",
          "tgn:7029392"
        ],
        "placetype": [
          "aat:300008850"
        ],
        "id": 2642087,
        "name:xx": "Sand Point"
      }
    },
    {
      "geometry": {
        "type": "Point",
        "coordinates": [
          -87.3667,
          45.1833
        ]
      },
      "type": "Feature",
      "properties": {
        "hierarchy": [
          "tgn:2642088",
          "tgn:1000001",
          "tgn:2002317",
          "tgn:7012149",
          "tgn:7007922",
          "tgn:7029392"
        ],
        "placetype": [
          "aat:300008850"
        ],
        "id": 2642088,
        "name:xx": "Sand Point"
      }
    },
    {
      "geometry": {
        "type": "Point",
        "coordinates": [
          -109.15,
          43.1667
        ]
      },
      "type": "Feature",
      "properties": {
        "hierarchy": [
          "tgn:2642089",
          "tgn:1000001",
          "tgn:7012149",
          "tgn:2002371",
          "tgn:7007923",
          "tgn:7029392"
        ],
        "placetype": [
          "aat:300008850"
        ],
        "id": 2642089,
        "name:xx": "Sand Point"
      }
    }
  ]
}
