{
  "geometry": {
    "type": "Point",
    "coordinates": [
      16.4667,
      46.5667
    ]
  },
  "type": "Feature",
  "properties": {
    "hierarchy": [
      "tgn:7015108",
      "tgn:1000003",
      "tgn:7006670",
      "tgn:7029392"
    ],
    "placetype": [
      "aat:300387064",
      "aat:300387081"
    ],
    "id": 7015108,
    "name:xx": "Lendava, Občina"
  }
}
