{
  "geometry": {
    "type": "Point",
    "coordinates": [
      -76.4333,
      38.1833
    ]
  },
  "type": "Feature",
  "properties": {
    "hierarchy": [
      "tgn:2564941",
      "tgn:1000001",
      "tgn:7016098",
      "tgn:7012149",
      "tgn:7007516",
      "tgn:7029392"
    ],
    "placetype": [
      "aat:300008850"
    ],
    "id": 2564941,
    "name:xx": "Pagan Point"
  }
}
