{
  "geometry": {
    "type": "Point",
    "coordinates": [
      76.25,
      20.35
    ]
  },
  "type": "Feature",
  "properties": {
    "hierarchy": [
      "tgn:1074994",
      "tgn:1000004",
      "tgn:7000198",
      "tgn:1001895",
      "tgn:7029392"
    ],
    "placetype": [
      "aat:300008347"
    ],
    "name:en": "Chikhli",
    "id": 1074994
  }
}
