{
  "geometry": {
    "type": "Point",
    "coordinates": [
      112.25,
      35.75
    ]
  },
  "type": "Feature",
  "properties": {
    "hierarchy": [
      "tgn:1071119",
      "tgn:1000004",
      "tgn:7002086",
      "tgn:1000111",
      "tgn:7029392"
    ],
    "placetype": [
      "aat:300008347"
    ],
    "id": 1071119,
    "name:xx": "Qinshui"
  }
}
