{
  "type": "FeatureCollection",
  "features": [
    {
      "geometry": {
        "type": "Point",
        "coordinates": [
          -107.416667,
          25.833333
        ]
      },
      "type": "Feature",
      "properties": {
        "hierarchy": [
          "tgn:7355420",
          "tgn:1000001",
          "tgn:7005595",
          "tgn:7005560",
          "tgn:7029392"
        ],
        "placetype": [
          "aat:300008347"
        ],
        "id": 7355420,
        "name:xx": "Cieneguilla"
      }
    },
    {
      "geometry": {
        "type": "Point",
        "coordinates": [
          -104.65,
          25.65
        ]
      },
      "type": "Feature",
      "properties": {
        "hierarchy": [
          "tgn:7355421",
          "tgn:7005583",
          "tgn:1000001",
          "tgn:7005560",
          "tgn:7029392"
        ],
        "placetype": [
          "aat:300008347"
        ],
        "id": 7355421,
        "name:xx": "Cieneguilla"
      }
    },
    {
      "geometry": {
        "type": "Point",
        "coordinates": [
          -107.583333,
          25.633333
        ]
      },
      "type": "Feature",
      "properties": {
        "hierarchy": [
          "tgn:7355422",
          "tgn:1000001",
          "tgn:7005595",
          "tgn:7005560",
          "tgn:7029392"
        ],
        "placetype": [
          "aat:300008347"
        ],
        "id": 7355422,
        "name:xx": "Cíeneguilla"
      }
    },
    {
      "geometry": {
        "type": "Point",
        "coordinates": [
          -107.483333,
          25.483333
        ]
      },
      "type": "Feature",
      "properties": {
        "hierarchy": [
          "tgn:7355423",
          "tgn:1000001",
          "tgn:7005595",
          "tgn:7005560",
          "tgn:7029392"
        ],
        "placetype": [
          "aat:300008347"
        ],
        "id": 7355423,
        "name:xx": "Cieneguilla"
      }
    },
    {
      "geometry": {
        "type": "Point",
        "coordinates": [
          -100.133333,
          25.4
        ]
      },
      "type": "Feature",
      "properties": {
        "hierarchy": [
          "tgn:7355424",
          "tgn:1000001",
          "tgn:7005589",
          "tgn:7005560",
          "tgn:7029392"
        ],
        "placetype": [
          "aat:300008347"
        ],
        "id": 7355424,
        "name:xx": "Cieneguilla"
      }
    },
    {
      "geometry": {
        "type": "Point",
        "coordinates": [
          -103.083333,
          24.083333
        ]
      },
      "type": "Feature",
      "properties": {
        "hierarchy": [
          "tgn:7355425",
          "tgn:1000001",
          "tgn:7005601",
          "tgn:7005560",
          "tgn:7029392"
        ],
        "placetype": [
          "aat:300008347"
        ],
        "id": 7355425,
        "name:xx": "Cieneguilla"
      }
    },
    {
      "geometry": {
        "type": "Point",
        "coordinates": [
          -104.0525,
          24.052222
        ]
      },
      "type": "Feature",
      "properties": {
        "hierarchy": [
          "tgn:7355426",
          "tgn:7005583",
          "tgn:1000001",
          "tgn:7005560",
          "tgn:7029392"
        ],
        "placetype": [
          "aat:300008347"
        ],
        "id": 7355426,
        "name:xx": "Cieneguilla"
      }
    },
    {
      "geometry": {
        "type": "Point",
        "coordinates": [
          -99.733333,
          23.75
        ]
      },
      "type": "Feature",
      "properties": {
        "hierarchy": [
          "tgn:7355427",
          "tgn:1000001",
          "tgn:7005597",
          "tgn:7005560",
          "tgn:7029392"
        ],
        "placetype": [
          "aat:300008347"
        ],
        "id": 7355427,
        "name:xx": "Cieneguilla"
      }
    },
    {
      "geometry": {
        "type": "Point",
        "coordinates": [
          -102.783333,
          23.016667
        ]
      },
      "type": "Feature",
      "properties": {
        "hierarchy": [
          "tgn:7355428",
          "tgn:1000001",
          "tgn:7005601",
          "tgn:7005560",
          "tgn:7029392"
        ],
        "placetype": [
          "aat:300008347"
        ],
        "id": 7355428,
        "name:xx": "Cieneguilla"
      }
    },
    {
      "geometry": {
        "type": "Point",
        "coordinates": [
          -99.716667,
          22.866667
        ]
      },
      "type": "Feature",
      "properties": {
        "hierarchy": [
          "tgn:7355429",
          "tgn:1000001",
          "tgn:7005597",
          "tgn:7005560",
          "tgn:7029392"
        ],
        "placetype": [
          "aat:300008347"
        ],
        "id": 7355429,
        "name:xx": "Cieneguilla"
      }
    }
  ]
}
