{
  "type": "FeatureCollection",
  "features": [
    {
      "geometry": {
        "type": "Point",
        "coordinates": [
          -82.9167,
          33.2833
        ]
      },
      "type": "Feature",
      "properties": {
        "hierarchy": [
          "tgn:2249450",
          "tgn:1000001",
          "tgn:7012149",
          "tgn:2000361",
          "tgn:7007248",
          "tgn:7029392"
        ],
        "placetype": [
          "aat:300006191"
        ],
        "id": 2249450,
        "name:xx": "Coleman Lake"
      }
    },
    {
      "geometry": {
        "type": "Point",
        "coordinates": [
          -89.3167,
          41.2833
        ]
      },
      "type": "Feature",
      "properties": {
        "hierarchy": [
          "tgn:2249451",
          "tgn:1000001",
          "tgn:7012149",
          "tgn:2000525",
          "tgn:7007251",
          "tgn:7029392"
        ],
        "placetype": [
          "aat:300008680"
        ],
        "id": 2249451,
        "name:xx": "Coleman Lake"
      }
    },
    {
      "geometry": {
        "type": "Point",
        "coordinates": [
          -85.2667,
          42.4167
        ]
      },
      "type": "Feature",
      "properties": {
        "hierarchy": [
          "tgn:2249452",
          "tgn:1002166",
          "tgn:1000001",
          "tgn:7012149",
          "tgn:7007520",
          "tgn:7029392"
        ],
        "placetype": [
          "aat:300008680"
        ],
        "id": 2249452,
        "name:xx": "Coleman Lake"
      }
    },
    {
      "geometry": {
        "type": "Point",
        "coordinates": [
          -95.2833,
          47.0167
        ]
      },
      "type": "Feature",
      "properties": {
        "hierarchy": [
          "tgn:2249453",
          "tgn:2001001",
          "tgn:1000001",
          "tgn:7012149",
          "tgn:7007521",
          "tgn:7029392"
        ],
        "placetype": [
          "aat:300008680"
        ],
        "id": 2249453,
        "name:xx": "Coleman Lake"
      }
    },
    {
      "geometry": {
        "type": "Point",
        "coordinates": [
          -94.4,
          47.6333
        ]
      },
      "type": "Feature",
      "properties": {
        "hierarchy": [
          "tgn:2249454",
          "tgn:1000001",
          "tgn:7012149",
          "tgn:7007521",
          "tgn:7029392"
        ],
        "placetype": [
          "aat:300008680"
        ],
        "id": 2249454,
        "name:xx": "Coleman Lake"
      }
    },
    {
      "geometry": {
        "type": "Point",
        "coordinates": [
          -93.7167,
          37.9333
        ]
      },
      "type": "Feature",
      "properties": {
        "hierarchy": [
          "tgn:2249455",
          "tgn:1000001",
          "tgn:7012149",
          "tgn:2001239",
          "tgn:7007523",
          "tgn:7029392"
        ],
        "placetype": [
          "aat:300006191"
        ],
        "id": 2249455,
        "name:xx": "Coleman Lake"
      }
    },
    {
      "geometry": {
        "type": "Point",
        "coordinates": [
          -101.15,
          42.3667
        ]
      },
      "type": "Feature",
      "properties": {
        "hierarchy": [
          "tgn:2249456",
          "tgn:1000001",
          "tgn:2001331",
          "tgn:7012149",
          "tgn:7007525",
          "tgn:7029392"
        ],
        "placetype": [
          "aat:300008680"
        ],
        "id": 2249456,
        "name:xx": "Coleman Lake"
      }
    },
    {
      "geometry": {
        "type": "Point",
        "coordinates": [
          -119.8167,
          42.05
        ]
      },
      "type": "Feature",
      "properties": {
        "hierarchy": [
          "tgn:2249457",
          "tgn:1000001",
          "tgn:7012149",
          "tgn:2001715",
          "tgn:7007708",
          "tgn:7029392"
        ],
        "placetype": [
          "aat:300008680"
        ],
        "id": 2249457,
        "name:xx": "Coleman Lake"
      }
    },
    {
      "geometry": {
        "type": "Point",
        "coordinates": [
          -81.1333,
          32.35
        ]
      },
      "type": "Feature",
      "properties": {
        "hierarchy": [
          "tgn:2249458",
          "tgn:1000001",
          "tgn:7012149",
          "tgn:2001751",
          "tgn:7007712",
          "tgn:7029392"
        ],
        "placetype": [
          "aat:300132316"
        ],
        "id": 2249458,
        "name:xx": "Coleman Lake"
      }
    },
    {
      "geometry": {
        "type": "Point",
        "coordinates": [
          -81.8333,
          33.2667
        ]
      },
      "type": "Feature",
      "properties": {
        "hierarchy": [
          "tgn:2249459",
          "tgn:2001726",
          "tgn:1000001",
          "tgn:7012149",
          "tgn:7007712",
          "tgn:7029392"
        ],
        "placetype": [
          "aat:300008680"
        ],
        "id": 2249459,
        "name:xx": "Coleman Lake"
      }
    }
  ]
}
