{
  "geometry": {
    "type": "Point",
    "coordinates": [
      78.9832,
      24.92678
    ]
  },
  "type": "Feature",
  "properties": {
    "hierarchy": [
      "tgn:7584124",
      "tgn:1000004",
      "tgn:7000198",
      "tgn:1001894",
      "tgn:7029392"
    ],
    "placetype": [
      "aat:300008347"
    ],
    "name:en": "Berīkhirka",
    "id": 7584124
  }
}
