{
  "geometry": {
    "type": "Point",
    "coordinates": [
      -86.1167,
      45.0167
    ]
  },
  "type": "Feature",
  "properties": {
    "hierarchy": [
      "tgn:2325909",
      "tgn:1000001",
      "tgn:7012149",
      "tgn:7007520",
      "tgn:7029392"
    ],
    "placetype": [
      "aat:300008863"
    ],
    "id": 2325909,
    "name:xx": "Fife Lake State Forest"
  }
}
