{
  "geometry": {
    "type": "Point",
    "coordinates": [
      -86.3667,
      42.0333
    ]
  },
  "type": "Feature",
  "properties": {
    "hierarchy": [
      "tgn:2053346",
      "tgn:1000001",
      "tgn:1002182",
      "tgn:7012149",
      "tgn:7007520",
      "tgn:7029392"
    ],
    "placetype": [
      "aat:300008347"
    ],
    "id": 2053346,
    "name:xx": "Sodus"
  }
}
