{
  "geometry": {
    "type": "Point",
    "coordinates": [
      8.783333,
      52.05
    ]
  },
  "type": "Feature",
  "properties": {
    "hierarchy": [
      "tgn:7184659",
      "tgn:1000003",
      "tgn:7003677",
      "tgn:7000084",
      "tgn:7029392"
    ],
    "placetype": [
      "aat:300387173"
    ],
    "id": 7184659,
    "name:xx": "Grastrup-Hölsen"
  }
}
