{
  "geometry": {
    "type": "Point",
    "coordinates": [
      -81.25,
      36.5167
    ]
  },
  "type": "Feature",
  "properties": {
    "hierarchy": [
      "tgn:2144487",
      "tgn:2001465",
      "tgn:1000001",
      "tgn:7012149",
      "tgn:7007709",
      "tgn:7029392"
    ],
    "placetype": [
      "aat:300266640"
    ],
    "id": 2144487,
    "name:xx": "Bakers Ridge"
  }
}
