{
  "type": "FeatureCollection",
  "features": [
    {
      "geometry": {
        "type": "Point",
        "coordinates": [
          14.616667,
          51.566667
        ]
      },
      "type": "Feature",
      "properties": {
        "hierarchy": [
          "tgn:7155390",
          "tgn:7000096",
          "tgn:1000003",
          "tgn:7000084",
          "tgn:7029392"
        ],
        "placetype": [
          "aat:300008347"
        ],
        "id": 7155390,
        "name:xx": "Klein Düben"
      }
    },
    {
      "geometry": {
        "type": "Point",
        "coordinates": [
          12.833333,
          51.75
        ]
      },
      "type": "Feature",
      "properties": {
        "hierarchy": [
          "tgn:7155391",
          "tgn:1000003",
          "tgn:7003687",
          "tgn:7000084",
          "tgn:7029392"
        ],
        "placetype": [
          "aat:300008347"
        ],
        "id": 7155391,
        "name:xx": "Kleindröben"
      }
    },
    {
      "geometry": {
        "type": "Point",
        "coordinates": [
          7.233333,
          50.933333
        ]
      },
      "type": "Feature",
      "properties": {
        "hierarchy": [
          "tgn:7155392",
          "tgn:1000003",
          "tgn:7003677",
          "tgn:7000084",
          "tgn:7029392"
        ],
        "placetype": [
          "aat:300008347"
        ],
        "id": 7155392,
        "name:xx": "Klein Dresbach"
      }
    },
    {
      "geometry": {
        "type": "Point",
        "coordinates": [
          8.016667,
          52.533333
        ]
      },
      "type": "Feature",
      "properties": {
        "hierarchy": [
          "tgn:7155393",
          "tgn:1000003",
          "tgn:7003676",
          "tgn:7000084",
          "tgn:7029392"
        ],
        "placetype": [
          "aat:300008347"
        ],
        "id": 7155393,
        "name:xx": "Klein Drehle"
      }
    },
    {
      "geometry": {
        "type": "Point",
        "coordinates": [
          14.15,
          51.1
        ]
      },
      "type": "Feature",
      "properties": {
        "hierarchy": [
          "tgn:7155394",
          "tgn:1000003",
          "tgn:7003685",
          "tgn:7000084",
          "tgn:7029392"
        ],
        "placetype": [
          "aat:300008347"
        ],
        "id": 7155394,
        "name:xx": "Kleindrebnitz"
      }
    },
    {
      "geometry": {
        "type": "Point",
        "coordinates": [
          12.1,
          50.75
        ]
      },
      "type": "Feature",
      "properties": {
        "hierarchy": [
          "tgn:7155395",
          "tgn:1000003",
          "tgn:7003689",
          "tgn:7000084",
          "tgn:7029392"
        ],
        "placetype": [
          "aat:300008347"
        ],
        "id": 7155395,
        "name:xx": "Kleindraxdorf"
      }
    },
    {
      "geometry": {
        "type": "Point",
        "coordinates": [
          8.2,
          52.2
        ]
      },
      "type": "Feature",
      "properties": {
        "hierarchy": [
          "tgn:7155396",
          "tgn:1000003",
          "tgn:7003676",
          "tgn:7000084",
          "tgn:7029392"
        ],
        "placetype": [
          "aat:300000206"
        ],
        "id": 7155396,
        "name:xx": "Klein Dratum"
      }
    },
    {
      "geometry": {
        "type": "Point",
        "coordinates": [
          12.866667,
          53.5
        ]
      },
      "type": "Feature",
      "properties": {
        "hierarchy": [
          "tgn:7155397",
          "tgn:1000003",
          "tgn:7000094",
          "tgn:7000084",
          "tgn:7029392"
        ],
        "placetype": [
          "aat:300008347"
        ],
        "id": 7155397,
        "name:xx": "Klein Dratow"
      }
    },
    {
      "geometry": {
        "type": "Point",
        "coordinates": [
          9.9,
          53.516667
        ]
      },
      "type": "Feature",
      "properties": {
        "hierarchy": [
          "tgn:7155398",
          "tgn:1000003",
          "tgn:7003673",
          "tgn:7000084",
          "tgn:7029392"
        ],
        "placetype": [
          "aat:300008347"
        ],
        "id": 7155398,
        "name:xx": "Klein Dradenau"
      }
    },
    {
      "geometry": {
        "type": "Point",
        "coordinates": [
          7.4,
          52.7
        ]
      },
      "type": "Feature",
      "properties": {
        "hierarchy": [
          "tgn:7155399",
          "tgn:1000003",
          "tgn:7003676",
          "tgn:7000084",
          "tgn:7029392"
        ],
        "placetype": [
          "aat:300008347"
        ],
        "id": 7155399,
        "name:xx": "Klein Dörgen"
      }
    }
  ]
}
