{
  "geometry": {
    "type": "Point",
    "coordinates": [
      111.2667,
      26.9833
    ]
  },
  "type": "Feature",
  "properties": {
    "hierarchy": [
      "tgn:1071554",
      "tgn:1000004",
      "tgn:7002079",
      "tgn:1000111",
      "tgn:7029392"
    ],
    "placetype": [
      "aat:300008347"
    ],
    "id": 1071554,
    "name:xx": "Shaoyang"
  }
}
