{
  "geometry": {
    "type": "Point",
    "coordinates": [
      -101.9667,
      46.5667
    ]
  },
  "type": "Feature",
  "properties": {
    "hierarchy": [
      "tgn:2448250",
      "tgn:1000001",
      "tgn:2001575",
      "tgn:7012149",
      "tgn:7007705",
      "tgn:7029392"
    ],
    "placetype": [
      "aat:300000390"
    ],
    "id": 2448250,
    "name:xx": "Lignite Mine"
  }
}
