{
  "geometry": {
    "type": "Point",
    "coordinates": [
      75.697098,
      26.997418
    ]
  },
  "type": "Feature",
  "properties": {
    "hierarchy": [
      "tgn:7559851",
      "tgn:1000004",
      "tgn:7000198",
      "tgn:7016788",
      "tgn:7029392"
    ],
    "placetype": [
      "aat:300008347"
    ],
    "name:en": "M훮t훮w훮li Dh훮ni",
    "id": 7559851
  }
}
