{
  "geometry": {
    "type": "Point",
    "coordinates": [
      -78.3667,
      38.2167
    ]
  },
  "type": "Feature",
  "properties": {
    "hierarchy": [
      "tgn:2114068",
      "tgn:1000001",
      "tgn:7012149",
      "tgn:2002165",
      "tgn:7007919",
      "tgn:7029392"
    ],
    "placetype": [
      "aat:300008347"
    ],
    "id": 2114068,
    "name:xx": "Ruckersville"
  }
}
