{
  "type": "FeatureCollection",
  "features": [
    {
      "geometry": {
        "type": "Point",
        "coordinates": [
          -101.8,
          21.233333
        ]
      },
      "type": "Feature",
      "properties": {
        "hierarchy": [
          "tgn:7377590",
          "tgn:7005586",
          "tgn:1000001",
          "tgn:7005560",
          "tgn:7029392"
        ],
        "placetype": [
          "aat:300008347"
        ],
        "id": 7377590,
        "name:xx": "La Venta"
      }
    },
    {
      "geometry": {
        "type": "Point",
        "coordinates": [
          -101.516667,
          21.2
        ]
      },
      "type": "Feature",
      "properties": {
        "hierarchy": [
          "tgn:7377591",
          "tgn:7005584",
          "tgn:1000001",
          "tgn:7005560",
          "tgn:7029392"
        ],
        "placetype": [
          "aat:300008347"
        ],
        "id": 7377591,
        "name:xx": "La Venta"
      }
    },
    {
      "geometry": {
        "type": "Point",
        "coordinates": [
          -100.783333,
          21.116667
        ]
      },
      "type": "Feature",
      "properties": {
        "hierarchy": [
          "tgn:7377592",
          "tgn:7005584",
          "tgn:1000001",
          "tgn:7005560",
          "tgn:7029392"
        ],
        "placetype": [
          "aat:300008347"
        ],
        "id": 7377592,
        "name:xx": "La Venta"
      }
    },
    {
      "geometry": {
        "type": "Point",
        "coordinates": [
          -104.927222,
          24.759444
        ]
      },
      "type": "Feature",
      "properties": {
        "hierarchy": [
          "tgn:7377593",
          "tgn:7005583",
          "tgn:1000001",
          "tgn:7005560",
          "tgn:7029392"
        ],
        "placetype": [
          "aat:300008347"
        ],
        "id": 7377593,
        "name:xx": "La Soledad"
      }
    },
    {
      "geometry": {
        "type": "Point",
        "coordinates": [
          -103.833333,
          23.65
        ]
      },
      "type": "Feature",
      "properties": {
        "hierarchy": [
          "tgn:7377594",
          "tgn:7005583",
          "tgn:1000001",
          "tgn:7005560",
          "tgn:7029392"
        ],
        "placetype": [
          "aat:300008347"
        ],
        "id": 7377594,
        "name:xx": "La Soledad"
      }
    },
    {
      "geometry": {
        "type": "Point",
        "coordinates": [
          -104.033333,
          23.633333
        ]
      },
      "type": "Feature",
      "properties": {
        "hierarchy": [
          "tgn:7377595",
          "tgn:7005583",
          "tgn:1000001",
          "tgn:7005560",
          "tgn:7029392"
        ],
        "placetype": [
          "aat:300008347"
        ],
        "id": 7377595,
        "name:xx": "La Soledad"
      }
    },
    {
      "geometry": {
        "type": "Point",
        "coordinates": [
          -99.183333,
          23.25
        ]
      },
      "type": "Feature",
      "properties": {
        "hierarchy": [
          "tgn:7377596",
          "tgn:1000001",
          "tgn:7005597",
          "tgn:7005560",
          "tgn:7029392"
        ],
        "placetype": [
          "aat:300008347"
        ],
        "id": 7377596,
        "name:xx": "La Soledad"
      }
    },
    {
      "geometry": {
        "type": "Point",
        "coordinates": [
          -109.966667,
          23.133333
        ]
      },
      "type": "Feature",
      "properties": {
        "hierarchy": [
          "tgn:7377597",
          "tgn:1001836",
          "tgn:1000001",
          "tgn:7005560",
          "tgn:7029392"
        ],
        "placetype": [
          "aat:300008347"
        ],
        "id": 7377597,
        "name:xx": "La Soledad"
      }
    },
    {
      "geometry": {
        "type": "Point",
        "coordinates": [
          -104.3,
          22.733333
        ]
      },
      "type": "Feature",
      "properties": {
        "hierarchy": [
          "tgn:7377598",
          "tgn:7005583",
          "tgn:1000001",
          "tgn:7005560",
          "tgn:7029392"
        ],
        "placetype": [
          "aat:300008347"
        ],
        "id": 7377598,
        "name:xx": "La Soledad"
      }
    },
    {
      "geometry": {
        "type": "Point",
        "coordinates": [
          -103.883333,
          22.416667
        ]
      },
      "type": "Feature",
      "properties": {
        "hierarchy": [
          "tgn:7377599",
          "tgn:7005586",
          "tgn:1000001",
          "tgn:7005560",
          "tgn:7029392"
        ],
        "placetype": [
          "aat:300008347"
        ],
        "id": 7377599,
        "name:xx": "La Soledad"
      }
    }
  ]
}
