{
  "geometry": {
    "type": "Point",
    "coordinates": [
      91.8667,
      21.8333
    ]
  },
  "type": "Feature",
  "properties": {
    "hierarchy": [
      "tgn:1007761",
      "tgn:7000188",
      "tgn:1000004",
      "tgn:1000105",
      "tgn:7029392"
    ],
    "placetype": [
      "aat:300008791"
    ],
    "id": 1007761,
    "name:xx": "Kutubdia Island"
  }
}
