{
  "geometry": {
    "type": "Point",
    "coordinates": [
      -89.2833,
      39.0833
    ]
  },
  "type": "Feature",
  "properties": {
    "hierarchy": [
      "tgn:2528820",
      "tgn:1000001",
      "tgn:7012149",
      "tgn:1002685",
      "tgn:7007251",
      "tgn:7029392"
    ],
    "placetype": [
      "aat:300008706"
    ],
    "id": 2528820,
    "name:xx": "Mud Creek"
  }
}
