{
  "geometry": {
    "type": "Point",
    "coordinates": [
      -111.1167,
      34.4333
    ]
  },
  "type": "Feature",
  "properties": {
    "hierarchy": [
      "tgn:2402560",
      "tgn:1000001",
      "tgn:7006451",
      "tgn:2000092",
      "tgn:7012149",
      "tgn:7029392"
    ],
    "placetype": [
      "aat:300266640"
    ],
    "id": 2402560,
    "name:xx": "Hospital Ridge"
  }
}
