{
  "geometry": {
    "type": "Point",
    "coordinates": [
      15.6333,
      46.4833
    ]
  },
  "type": "Feature",
  "properties": {
    "hierarchy": [
      "tgn:1065357",
      "tgn:1000003",
      "tgn:7015085",
      "tgn:7006670",
      "tgn:7029392"
    ],
    "placetype": [
      "aat:300008347"
    ],
    "id": 1065357,
    "name:xx": "Zgornje Hoče"
  }
}
