{
  "geometry": {
    "type": "Point",
    "coordinates": [
      -74.5833,
      41.65
    ]
  },
  "type": "Feature",
  "properties": {
    "hierarchy": [
      "tgn:2069416",
      "tgn:1000001",
      "tgn:7012149",
      "tgn:1002926",
      "tgn:7007568",
      "tgn:7029392"
    ],
    "placetype": [
      "aat:300008347"
    ],
    "id": 2069416,
    "name:xx": "Glen Wild"
  }
}
