{
  "geometry": {
    "type": "Point",
    "coordinates": [
      -85.4667,
      36.6667
    ]
  },
  "type": "Feature",
  "properties": {
    "hierarchy": [
      "tgn:2368320",
      "tgn:1000001",
      "tgn:7012149",
      "tgn:2000785",
      "tgn:7007255",
      "tgn:7029392"
    ],
    "placetype": [
      "aat:300008761"
    ],
    "id": 2368320,
    "name:xx": "Guffey Hollow"
  }
}
