{
  "type": "FeatureCollection",
  "features": [
    {
      "geometry": {
        "type": "Point",
        "coordinates": [
          -109.7333,
          48.1833
        ]
      },
      "type": "Feature",
      "properties": {
        "hierarchy": [
          "tgn:2530540",
          "tgn:1000001",
          "tgn:2001267",
          "tgn:7012149",
          "tgn:7007524",
          "tgn:7029392"
        ],
        "placetype": [
          "aat:300008706"
        ],
        "id": 2530540,
        "name:xx": "Muddy Creek"
      }
    },
    {
      "geometry": {
        "type": "Point",
        "coordinates": [
          -96.0167,
          40.3667
        ]
      },
      "type": "Feature",
      "properties": {
        "hierarchy": [
          "tgn:2530541",
          "tgn:1000001",
          "tgn:7012149",
          "tgn:7007525",
          "tgn:7029392"
        ],
        "placetype": [
          "aat:300008706"
        ],
        "id": 2530541,
        "name:xx": "Muddy Creek"
      }
    },
    {
      "geometry": {
        "type": "Point",
        "coordinates": [
          -96.35,
          40.6167
        ]
      },
      "type": "Feature",
      "properties": {
        "hierarchy": [
          "tgn:2530542",
          "tgn:1000001",
          "tgn:7012149",
          "tgn:2001381",
          "tgn:7007525",
          "tgn:7029392"
        ],
        "placetype": [
          "aat:300008706"
        ],
        "id": 2530542,
        "name:xx": "Muddy Creek"
      }
    },
    {
      "geometry": {
        "type": "Point",
        "coordinates": [
          -75.4167,
          39.3833
        ]
      },
      "type": "Feature",
      "properties": {
        "hierarchy": [
          "tgn:2530543",
          "tgn:1000001",
          "tgn:7014449",
          "tgn:7012149",
          "tgn:7007565",
          "tgn:7029392"
        ],
        "placetype": [
          "aat:300008706"
        ],
        "id": 2530543,
        "name:xx": "Muddy Creek"
      }
    },
    {
      "geometry": {
        "type": "Point",
        "coordinates": [
          -79.0167,
          42.5667
        ]
      },
      "type": "Feature",
      "properties": {
        "hierarchy": [
          "tgn:2530545",
          "tgn:1000001",
          "tgn:7012149",
          "tgn:1002356",
          "tgn:7007568",
          "tgn:7029392"
        ],
        "placetype": [
          "aat:300008706"
        ],
        "id": 2530545,
        "name:xx": "Muddy Creek"
      }
    },
    {
      "geometry": {
        "type": "Point",
        "coordinates": [
          -76.6667,
          35.3
        ]
      },
      "type": "Feature",
      "properties": {
        "hierarchy": [
          "tgn:2530546",
          "tgn:1000001",
          "tgn:7013368",
          "tgn:7012149",
          "tgn:7007709",
          "tgn:7029392"
        ],
        "placetype": [
          "aat:300008706"
        ],
        "id": 2530546,
        "name:xx": "Muddy Creek"
      }
    },
    {
      "geometry": {
        "type": "Point",
        "coordinates": [
          -81.2167,
          35.45
        ]
      },
      "type": "Feature",
      "properties": {
        "hierarchy": [
          "tgn:2530547",
          "tgn:1000001",
          "tgn:7012149",
          "tgn:7007709",
          "tgn:7029392"
        ],
        "placetype": [
          "aat:300008706"
        ],
        "id": 2530547,
        "name:xx": "Muddy Creek"
      }
    },
    {
      "geometry": {
        "type": "Point",
        "coordinates": [
          -75.85,
          35.6
        ]
      },
      "type": "Feature",
      "properties": {
        "hierarchy": [
          "tgn:2530548",
          "tgn:1000001",
          "tgn:7012149",
          "tgn:2001488",
          "tgn:7007709",
          "tgn:7029392"
        ],
        "placetype": [
          "aat:300008706"
        ],
        "id": 2530548,
        "name:xx": "Muddy Creek"
      }
    },
    {
      "geometry": {
        "type": "Point",
        "coordinates": [
          -81.3,
          35.7
        ]
      },
      "type": "Feature",
      "properties": {
        "hierarchy": [
          "tgn:2530549",
          "tgn:1000001",
          "tgn:2001479",
          "tgn:7012149",
          "tgn:7007709",
          "tgn:7029392"
        ],
        "placetype": [
          "aat:300008706"
        ],
        "id": 2530549,
        "name:xx": "Muddy Creek"
      }
    }
  ]
}
