{
  "geometry": {
    "type": "Point",
    "coordinates": [
      -100.3333,
      48.1333
    ]
  },
  "type": "Feature",
  "properties": {
    "hierarchy": [
      "tgn:2144605",
      "tgn:1000001",
      "tgn:2001581",
      "tgn:7012149",
      "tgn:7007705",
      "tgn:7029392"
    ],
    "placetype": [
      "aat:300008798"
    ],
    "id": 2144605,
    "name:xx": "Bald Butte"
  }
}
