{
  "geometry": {
    "type": "Point",
    "coordinates": [
      -96.6333,
      33.9667
    ]
  },
  "type": "Feature",
  "properties": {
    "hierarchy": [
      "tgn:2128089",
      "tgn:1000001",
      "tgn:7012149",
      "tgn:7007707",
      "tgn:7029392"
    ],
    "placetype": [
      "aat:300008706"
    ],
    "id": 2128089,
    "name:xx": "Alberta Creek"
  }
}
