{
  "geometry": {
    "type": "Point",
    "coordinates": [
      -86.45,
      35.1833
    ]
  },
  "type": "Feature",
  "properties": {
    "hierarchy": [
      "tgn:2531183",
      "tgn:1000001",
      "tgn:7012149",
      "tgn:2001888",
      "tgn:7007825",
      "tgn:7029392"
    ],
    "placetype": [
      "aat:300008706"
    ],
    "id": 2531183,
    "name:xx": "Mulberry Creek"
  }
}
