{
  "geometry": {
    "type": "Point",
    "coordinates": [
      24.0167,
      48.9667
    ]
  },
  "type": "Feature",
  "properties": {
    "hierarchy": [
      "tgn:1053678",
      "tgn:7011650",
      "tgn:1000003",
      "tgn:7006660",
      "tgn:7029392"
    ],
    "placetype": [
      "aat:300008347"
    ],
    "id": 1053678,
    "name:xx": "Dolyna"
  }
}
