{
  "geometry": {
    "type": "Point",
    "coordinates": [
      -161.8667,
      61.5667
    ]
  },
  "type": "Feature",
  "properties": {
    "hierarchy": [
      "tgn:2752285",
      "tgn:7006450",
      "tgn:1000001",
      "tgn:7012149",
      "tgn:2000087",
      "tgn:7029392"
    ],
    "placetype": [
      "aat:300008699"
    ],
    "id": 2752285,
    "name:xx": "Washburn Slough"
  }
}
