{
  "geometry": {
    "type": "Point",
    "coordinates": [
      -116.7833,
      43.1667
    ]
  },
  "type": "Feature",
  "properties": {
    "hierarchy": [
      "tgn:2373687",
      "tgn:1000001",
      "tgn:7012149",
      "tgn:2000488",
      "tgn:7007250",
      "tgn:7029392"
    ],
    "placetype": [
      "aat:300008761"
    ],
    "id": 2373687,
    "name:xx": "Hamilton Gulch"
  }
}
