{
  "geometry": {
    "type": "Point",
    "coordinates": [
      -98.9167,
      36.8167
    ]
  },
  "type": "Feature",
  "properties": {
    "hierarchy": [
      "tgn:1133090",
      "tgn:1000001",
      "tgn:7012149",
      "tgn:7007707",
      "tgn:7029392"
    ],
    "placetype": [
      "aat:300008706"
    ],
    "id": 1133090,
    "name:xx": "Eagle Chief Creek"
  }
}
