{
  "geometry": {
    "type": "Point",
    "coordinates": [
      -117.85,
      39.5667
    ]
  },
  "type": "Feature",
  "properties": {
    "hierarchy": [
      "tgn:2750586",
      "tgn:1000001",
      "tgn:2001409",
      "tgn:7012149",
      "tgn:7007526",
      "tgn:7029392"
    ],
    "placetype": [
      "aat:300008761"
    ],
    "id": 2750586,
    "name:xx": "War Canyon"
  }
}
