{
  "geometry": {
    "type": "Point",
    "coordinates": [
      76.816667,
      9.383333
    ]
  },
  "type": "Feature",
  "properties": {
    "hierarchy": [
      "tgn:7557720",
      "tgn:1000004",
      "tgn:7000198",
      "tgn:1001886",
      "tgn:7029392"
    ],
    "placetype": [
      "aat:300008347"
    ],
    "name:en": "Rānī",
    "id": 7557720
  }
}
