{
  "type": "FeatureCollection",
  "features": [
    {
      "geometry": {
        "type": "Point",
        "coordinates": [
          -120.1833,
          44.3
        ]
      },
      "type": "Feature",
      "properties": {
        "hierarchy": [
          "tgn:2398790",
          "tgn:1000001",
          "tgn:2001703",
          "tgn:7012149",
          "tgn:7007708",
          "tgn:7029392"
        ],
        "placetype": [
          "aat:300006191"
        ],
        "id": 2398790,
        "name:xx": "Hope Reservoir"
      }
    },
    {
      "geometry": {
        "type": "Point",
        "coordinates": [
          -107.0167,
          38.7333
        ]
      },
      "type": "Feature",
      "properties": {
        "hierarchy": [
          "tgn:2398791",
          "tgn:1000001",
          "tgn:7012149",
          "tgn:2000217",
          "tgn:7007158",
          "tgn:7029392"
        ],
        "placetype": [
          "aat:300006075"
        ],
        "id": 2398791,
        "name:xx": "Hope Resich Ditch"
      }
    },
    {
      "geometry": {
        "type": "Point",
        "coordinates": [
          -111.8,
          46.2333
        ]
      },
      "type": "Feature",
      "properties": {
        "hierarchy": [
          "tgn:2398793",
          "tgn:1000001",
          "tgn:7012149",
          "tgn:2001281",
          "tgn:7007524",
          "tgn:7029392"
        ],
        "placetype": [
          "aat:300008697"
        ],
        "id": 2398793,
        "name:xx": "Hope Spring"
      }
    },
    {
      "geometry": {
        "type": "Point",
        "coordinates": [
          -117.3,
          41.6667
        ]
      },
      "type": "Feature",
      "properties": {
        "hierarchy": [
          "tgn:2398794",
          "tgn:1000001",
          "tgn:2001414",
          "tgn:7012149",
          "tgn:7007526",
          "tgn:7029392"
        ],
        "placetype": [
          "aat:300008697"
        ],
        "id": 2398794,
        "name:xx": "Hope Spring"
      }
    },
    {
      "geometry": {
        "type": "Point",
        "coordinates": [
          -123.6667,
          42.05
        ]
      },
      "type": "Feature",
      "properties": {
        "hierarchy": [
          "tgn:2398795",
          "tgn:1000001",
          "tgn:7012149",
          "tgn:2001713",
          "tgn:7007708",
          "tgn:7029392"
        ],
        "placetype": [
          "aat:300008697"
        ],
        "id": 2398795,
        "name:xx": "Hope Spring"
      }
    },
    {
      "geometry": {
        "type": "Point",
        "coordinates": [
          -122.7667,
          42.1667
        ]
      },
      "type": "Feature",
      "properties": {
        "hierarchy": [
          "tgn:2398796",
          "tgn:1000001",
          "tgn:7012149",
          "tgn:2001711",
          "tgn:7007708",
          "tgn:7029392"
        ],
        "placetype": [
          "aat:300008697"
        ],
        "id": 2398796,
        "name:xx": "Hope Spring"
      }
    },
    {
      "geometry": {
        "type": "Point",
        "coordinates": [
          -87.35,
          35.2333
        ]
      },
      "type": "Feature",
      "properties": {
        "hierarchy": [
          "tgn:2398797",
          "tgn:1000001",
          "tgn:7012149",
          "tgn:2001886",
          "tgn:7007825",
          "tgn:7029392"
        ],
        "placetype": [
          "aat:300008697"
        ],
        "id": 2398797,
        "name:xx": "Hope Spring"
      }
    },
    {
      "geometry": {
        "type": "Point",
        "coordinates": [
          -90.2,
          32.3667
        ]
      },
      "type": "Feature",
      "properties": {
        "hierarchy": [
          "tgn:2398798",
          "tgn:1000001",
          "tgn:7012149",
          "tgn:2001110",
          "tgn:7007522",
          "tgn:7029392"
        ],
        "placetype": [
          "aat:300008347"
        ],
        "id": 2398798,
        "name:xx": "Hope Springs"
      }
    },
    {
      "geometry": {
        "type": "Point",
        "coordinates": [
          -94.5,
          32.6833
        ]
      },
      "type": "Feature",
      "properties": {
        "hierarchy": [
          "tgn:2398799",
          "tgn:1000001",
          "tgn:7012149",
          "tgn:7007826",
          "tgn:7029392"
        ],
        "placetype": [
          "aat:300006191"
        ],
        "id": 2398799,
        "name:xx": "Hope Springs Lake"
      }
    }
  ]
}
