{
  "geometry": {
    "type": "Point",
    "coordinates": [
      28.666667,
      30.75
    ]
  },
  "type": "Feature",
  "properties": {
    "hierarchy": [
      "tgn:7523657",
      "tgn:7001242",
      "tgn:7016833",
      "tgn:1001418",
      "tgn:7029392"
    ],
    "placetype": [
      "aat:300386860"
    ],
    "name:en": "Bayḑā', Dayr al",
    "id": 7523657
  }
}
