{
  "type": "FeatureCollection",
  "features": [
    {
      "geometry": {
        "type": "Point",
        "coordinates": [
          169.833333,
          -43.4
        ]
      },
      "type": "Feature",
      "properties": {
        "hierarchy": [
          "tgn:1011921",
          "tgn:1009227",
          "tgn:1000226",
          "tgn:1000006",
          "tgn:7016850",
          "tgn:7029392"
        ],
        "placetype": [
          "aat:300386846"
        ],
        "id": 1011921,
        "name:xx": "Gillespie Point"
      }
    },
    {
      "geometry": {
        "type": "Point",
        "coordinates": [
          -61.25,
          15.3333
        ]
      },
      "type": "Feature",
      "properties": {
        "hierarchy": [
          "tgn:1011922",
          "tgn:7014983",
          "tgn:1000001",
          "tgn:7004641",
          "tgn:7029392"
        ],
        "placetype": [
          "aat:300386846"
        ],
        "id": 1011922,
        "name:xx": "Giraud, Pointe"
      }
    },
    {
      "geometry": {
        "type": "Point",
        "coordinates": [
          -82.1667,
          22.4
        ]
      },
      "type": "Feature",
      "properties": {
        "hierarchy": [
          "tgn:1011924",
          "tgn:1001424",
          "tgn:1000001",
          "tgn:7004624",
          "tgn:7029392"
        ],
        "placetype": [
          "aat:300386846"
        ],
        "id": 1011924,
        "name:xx": "Gorda, Punta"
      }
    },
    {
      "geometry": {
        "type": "Point",
        "coordinates": [
          -110.883333,
          27.933333
        ]
      },
      "type": "Feature",
      "properties": {
        "hierarchy": [
          "tgn:1011925",
          "tgn:1000001",
          "tgn:7005599",
          "tgn:7005560",
          "tgn:7029392"
        ],
        "placetype": [
          "aat:300386846"
        ],
        "id": 1011925,
        "name:xx": "Gorda, Punta"
      }
    },
    {
      "geometry": {
        "type": "Point",
        "coordinates": [
          -83.799,
          11.441
        ]
      },
      "type": "Feature",
      "properties": {
        "hierarchy": [
          "tgn:1011926",
          "tgn:7593359",
          "tgn:1000001",
          "tgn:7005562",
          "tgn:7029392"
        ],
        "placetype": [
          "aat:300386846"
        ],
        "id": 1011926,
        "name:xx": "Punta Grindston Bay"
      }
    },
    {
      "geometry": {
        "type": "Point",
        "coordinates": [
          -70.3,
          -19.3
        ]
      },
      "type": "Feature",
      "properties": {
        "hierarchy": [
          "tgn:1011927",
          "tgn:7002464",
          "tgn:1000049",
          "tgn:1000002",
          "tgn:7029392"
        ],
        "placetype": [
          "aat:300386846"
        ],
        "id": 1011927,
        "name:xx": "Gorda, Punta"
      }
    },
    {
      "geometry": {
        "type": "Point",
        "coordinates": [
          -150.95,
          59.1833
        ]
      },
      "type": "Feature",
      "properties": {
        "hierarchy": [
          "tgn:1011928",
          "tgn:7006450",
          "tgn:1000001",
          "tgn:7019698",
          "tgn:7012149",
          "tgn:7029392"
        ],
        "placetype": [
          "aat:300386846"
        ],
        "id": 1011928,
        "name:xx": "Gore Point"
      }
    }
  ]
}
