{
  "geometry": {
    "type": "Point",
    "coordinates": [
      27.6667,
      53.75
    ]
  },
  "type": "Feature",
  "properties": {
    "hierarchy": [
      "tgn:1056984",
      "tgn:1003391",
      "tgn:1000003",
      "tgn:7006657",
      "tgn:7029392"
    ],
    "placetype": [
      "aat:300008347"
    ],
    "id": 1056984,
    "name:xx": "Michanoviči"
  }
}
