{
  "geometry": {
    "type": "Point",
    "coordinates": [
      -89.4167,
      36.65
    ]
  },
  "type": "Feature",
  "properties": {
    "hierarchy": [
      "tgn:2246032",
      "tgn:1000001",
      "tgn:7012149",
      "tgn:2001222",
      "tgn:7007523",
      "tgn:7029392"
    ],
    "placetype": [
      "aat:300006075"
    ],
    "id": 2246032,
    "name:xx": "Coal Oil Ditch"
  }
}
