{
  "type": "FeatureCollection",
  "features": [
    {
      "geometry": {
        "type": "Point",
        "coordinates": [
          13.433333,
          38.133333
        ]
      },
      "type": "Feature",
      "properties": {
        "hierarchy": [
          "tgn:1112440",
          "tgn:1000003",
          "tgn:7003122",
          "tgn:1001732",
          "tgn:1000080",
          "tgn:7029392"
        ],
        "placetype": [
          "aat:300132315"
        ],
        "id": 1112440,
        "name:xx": "Palermo, Golfo di"
      }
    },
    {
      "geometry": {
        "type": "Point",
        "coordinates": [
          8.508333,
          39.025833
        ]
      },
      "type": "Feature",
      "properties": {
        "hierarchy": [
          "tgn:1112441",
          "tgn:1001641",
          "tgn:1000003",
          "tgn:7003121",
          "tgn:1000080",
          "tgn:7029392"
        ],
        "placetype": [
          "aat:300132315"
        ],
        "id": 1112441,
        "name:xx": "Palmas, Golfo di"
      }
    },
    {
      "geometry": {
        "type": "Point",
        "coordinates": [
          -79.5,
          8
        ]
      },
      "type": "Feature",
      "properties": {
        "hierarchy": [
          "tgn:1112442",
          "tgn:1000001",
          "tgn:7005565",
          "tgn:7029392"
        ],
        "placetype": [
          "aat:300132315"
        ],
        "id": 1112442,
        "name:xx": "Panamá, Golfo de"
      }
    },
    {
      "geometry": {
        "type": "Point",
        "coordinates": [
          122.25,
          10.25
        ]
      },
      "type": "Feature",
      "properties": {
        "hierarchy": [
          "tgn:1112443",
          "tgn:1000004",
          "tgn:1000135",
          "tgn:7029392"
        ],
        "placetype": [
          "aat:300132315"
        ],
        "id": 1112443,
        "name:xx": "Panay Gulf"
      }
    },
    {
      "geometry": {
        "type": "Point",
        "coordinates": [
          -62,
          10.3333
        ]
      },
      "type": "Feature",
      "properties": {
        "hierarchy": [
          "tgn:1112446",
          "tgn:7029392"
        ],
        "placetype": [
          "aat:300132315"
        ],
        "id": 1112446,
        "name:xx": "Paria, Gulf of"
      }
    },
    {
      "geometry": {
        "type": "Point",
        "coordinates": [
          15.083333,
          38.2
        ]
      },
      "type": "Feature",
      "properties": {
        "hierarchy": [
          "tgn:1112447",
          "tgn:1000003",
          "tgn:7003122",
          "tgn:7003157",
          "tgn:1000080",
          "tgn:7029392"
        ],
        "placetype": [
          "aat:300132315"
        ],
        "id": 1112447,
        "name:xx": "Patti, Golfo di"
      }
    },
    {
      "geometry": {
        "type": "Point",
        "coordinates": [
          -74.833333,
          -47.366667
        ]
      },
      "type": "Feature",
      "properties": {
        "hierarchy": [
          "tgn:1112448",
          "tgn:1001623",
          "tgn:1000049",
          "tgn:1000002",
          "tgn:7029392"
        ],
        "placetype": [
          "aat:300132315"
        ],
        "id": 1112448,
        "name:xx": "Penas, Golfo de"
      }
    }
  ]
}
