{
  "geometry": {
    "type": "Point",
    "coordinates": [
      -123.1333,
      38.55
    ]
  },
  "type": "Feature",
  "properties": {
    "hierarchy": [
      "tgn:2181792",
      "tgn:1000001",
      "tgn:7012149",
      "tgn:7007157",
      "tgn:7014516",
      "tgn:7029392"
    ],
    "placetype": [
      "aat:300266640"
    ],
    "id": 2181792,
    "name:xx": "Blue Jay Ridge"
  }
}
