{
  "geometry": {
    "type": "Point",
    "coordinates": [
      -111.4667,
      38.8333
    ]
  },
  "type": "Feature",
  "properties": {
    "hierarchy": [
      "tgn:2549957",
      "tgn:1000001",
      "tgn:7012149",
      "tgn:2002121",
      "tgn:7007827",
      "tgn:7029392"
    ],
    "placetype": [
      "aat:300008761"
    ],
    "id": 2549957,
    "name:xx": "North Water Hollow"
  }
}
