{
  "geometry": {
    "type": "Point",
    "coordinates": [
      -77.4333,
      40.0167
    ]
  },
  "type": "Feature",
  "properties": {
    "hierarchy": [
      "tgn:2468304",
      "tgn:1000001",
      "tgn:1002310",
      "tgn:7012149",
      "tgn:7007710",
      "tgn:7029392"
    ],
    "placetype": [
      "aat:300008798"
    ],
    "id": 2468304,
    "name:xx": "Long Mountain"
  }
}
