{
  "geometry": {
    "type": "Point",
    "coordinates": [
      -112.9333,
      44.8667
    ]
  },
  "type": "Feature",
  "properties": {
    "hierarchy": [
      "tgn:2545941",
      "tgn:1000001",
      "tgn:2001260",
      "tgn:7012149",
      "tgn:7007524",
      "tgn:7029392"
    ],
    "placetype": [
      "aat:300008706"
    ],
    "id": 2545941,
    "name:xx": "North Fork Deer Canyon Creek"
  }
}
