{
  "geometry": {
    "type": "Point",
    "coordinates": [
      -91.7667,
      45.65
    ]
  },
  "type": "Feature",
  "properties": {
    "hierarchy": [
      "tgn:2520356",
      "tgn:1000001",
      "tgn:7012149",
      "tgn:2002360",
      "tgn:7007922",
      "tgn:7029392"
    ],
    "placetype": [
      "aat:300008680"
    ],
    "id": 2520356,
    "name:xx": "Monday Lake"
  }
}
