{
  "geometry": {
    "type": "Point",
    "coordinates": [
      -86.1833,
      43.65
    ]
  },
  "type": "Feature",
  "properties": {
    "hierarchy": [
      "tgn:2246729",
      "tgn:1000001",
      "tgn:7012149",
      "tgn:2000984",
      "tgn:7007520",
      "tgn:7029392"
    ],
    "placetype": [
      "aat:300008680"
    ],
    "id": 2246729,
    "name:xx": "Cobmoosa Lake"
  }
}
