{
  "geometry": {
    "type": "Point",
    "coordinates": [
      -77.4667,
      40.95
    ]
  },
  "type": "Feature",
  "properties": {
    "hierarchy": [
      "tgn:2777234",
      "tgn:1000001",
      "tgn:1002249",
      "tgn:7012149",
      "tgn:7007710",
      "tgn:7029392"
    ],
    "placetype": [
      "aat:300008798"
    ],
    "id": 2777234,
    "name:xx": "Winehead, The"
  }
}
