{
  "geometry": {
    "type": "Point",
    "coordinates": [
      -114.8333,
      36.0667
    ]
  },
  "type": "Feature",
  "properties": {
    "hierarchy": [
      "tgn:2705342",
      "tgn:1000001",
      "tgn:2001410",
      "tgn:7012149",
      "tgn:7007526",
      "tgn:7029392"
    ],
    "placetype": [
      "aat:300006191"
    ],
    "id": 2705342,
    "name:xx": "Surge Tank Number Two"
  }
}
