{
  "geometry": {
    "type": "Point",
    "coordinates": [
      -65.9167,
      -47.0833
    ]
  },
  "type": "Feature",
  "properties": {
    "hierarchy": [
      "tgn:1011333",
      "tgn:7006477",
      "tgn:1001522",
      "tgn:1000002",
      "tgn:7029392"
    ],
    "placetype": [
      "aat:300008850"
    ],
    "id": 1011333,
    "name:xx": "Tres Puntas, Cabo"
  }
}
