{
  "geometry": {
    "type": "Point",
    "coordinates": [
      -165.9167,
      61.8167
    ]
  },
  "type": "Feature",
  "properties": {
    "hierarchy": [
      "tgn:2589771",
      "tgn:7006450",
      "tgn:1000001",
      "tgn:7012149",
      "tgn:2000087",
      "tgn:7029392"
    ],
    "placetype": [
      "aat:300008850"
    ],
    "id": 2589771,
    "name:xx": "Point Smith"
  }
}
