{
  "type": "FeatureCollection",
  "features": [
    {
      "geometry": {
        "type": "Point",
        "coordinates": [
          8.583333,
          53.833333
        ]
      },
      "type": "Feature",
      "properties": {
        "hierarchy": [
          "tgn:7194600",
          "tgn:1000003",
          "tgn:7003676",
          "tgn:7000084",
          "tgn:7029392"
        ],
        "placetype": [
          "aat:300000206"
        ],
        "id": 7194600,
        "name:xx": "Demor"
      }
    },
    {
      "geometry": {
        "type": "Point",
        "coordinates": [
          14.2,
          52.4
        ]
      },
      "type": "Feature",
      "properties": {
        "hierarchy": [
          "tgn:7194601",
          "tgn:7000096",
          "tgn:1000003",
          "tgn:7000084",
          "tgn:7029392"
        ],
        "placetype": [
          "aat:300000206"
        ],
        "id": 7194601,
        "name:xx": "Vorwerk Demnitz"
      }
    },
    {
      "geometry": {
        "type": "Point",
        "coordinates": [
          13.8,
          53.7
        ]
      },
      "type": "Feature",
      "properties": {
        "hierarchy": [
          "tgn:7194602",
          "tgn:1000003",
          "tgn:7000094",
          "tgn:7000084",
          "tgn:7029392"
        ],
        "placetype": [
          "aat:300008347"
        ],
        "id": 7194602,
        "name:xx": "Demnitz"
      }
    },
    {
      "geometry": {
        "type": "Point",
        "coordinates": [
          14.2,
          52.383333
        ]
      },
      "type": "Feature",
      "properties": {
        "hierarchy": [
          "tgn:7194603",
          "tgn:7000096",
          "tgn:1000003",
          "tgn:7000084",
          "tgn:7029392"
        ],
        "placetype": [
          "aat:300008347"
        ],
        "id": 7194603,
        "name:xx": "Demnitz"
      }
    },
    {
      "geometry": {
        "type": "Point",
        "coordinates": [
          13.183333,
          48.583333
        ]
      },
      "type": "Feature",
      "properties": {
        "hierarchy": [
          "tgn:7194604",
          "tgn:7003669",
          "tgn:1000003",
          "tgn:7000084",
          "tgn:7029392"
        ],
        "placetype": [
          "aat:300000206"
        ],
        "id": 7194604,
        "name:xx": "Demmlstadl"
      }
    },
    {
      "geometry": {
        "type": "Point",
        "coordinates": [
          12.516667,
          53.3
        ]
      },
      "type": "Feature",
      "properties": {
        "hierarchy": [
          "tgn:7194605",
          "tgn:1000003",
          "tgn:7000094",
          "tgn:7000084",
          "tgn:7029392"
        ],
        "placetype": [
          "aat:300008680"
        ],
        "id": 7194605,
        "name:xx": "Demmin-See"
      }
    },
    {
      "geometry": {
        "type": "Point",
        "coordinates": [
          12.533333,
          53.3
        ]
      },
      "type": "Feature",
      "properties": {
        "hierarchy": [
          "tgn:7194606",
          "tgn:1000003",
          "tgn:7000094",
          "tgn:7000084",
          "tgn:7029392"
        ],
        "placetype": [
          "aat:300008863"
        ],
        "id": 7194606,
        "name:xx": "Demminholz"
      }
    },
    {
      "geometry": {
        "type": "Point",
        "coordinates": [
          10.45,
          48.683333
        ]
      },
      "type": "Feature",
      "properties": {
        "hierarchy": [
          "tgn:7194607",
          "tgn:7003692",
          "tgn:1000003",
          "tgn:7000084",
          "tgn:7029392"
        ],
        "placetype": [
          "aat:300008347"
        ],
        "id": 7194607,
        "name:xx": "Demmingen"
      }
    },
    {
      "geometry": {
        "type": "Point",
        "coordinates": [
          6.5,
          51.833333
        ]
      },
      "type": "Feature",
      "properties": {
        "hierarchy": [
          "tgn:7194608",
          "tgn:1000003",
          "tgn:7003677",
          "tgn:7000084",
          "tgn:7029392"
        ],
        "placetype": [
          "aat:300000206"
        ],
        "id": 7194608,
        "name:xx": "Demming"
      }
    },
    {
      "geometry": {
        "type": "Point",
        "coordinates": [
          13.033333,
          53.966667
        ]
      },
      "type": "Feature",
      "properties": {
        "hierarchy": [
          "tgn:7194609",
          "tgn:1000003",
          "tgn:7000094",
          "tgn:7000084",
          "tgn:7029392"
        ],
        "placetype": [
          "aat:300008863"
        ],
        "id": 7194609,
        "name:xx": "Demminer Stadtwald"
      }
    }
  ]
}
