{
  "geometry": {
    "type": "Point",
    "coordinates": [
      -86.9167,
      37.6667
    ]
  },
  "type": "Feature",
  "properties": {
    "hierarchy": [
      "tgn:2218776",
      "tgn:1000001",
      "tgn:7012149",
      "tgn:2000786",
      "tgn:7007255",
      "tgn:7029392"
    ],
    "placetype": [
      "aat:300008699"
    ],
    "id": 2218776,
    "name:xx": "Cane Run"
  }
}
