{
  "type": "FeatureCollection",
  "features": [
    {
      "geometry": {
        "type": "Point",
        "coordinates": [
          -77.2167,
          38.7667
        ]
      },
      "type": "Feature",
      "properties": {
        "hierarchy": [
          "tgn:2115003",
          "tgn:1000001",
          "tgn:7012149",
          "tgn:7014160",
          "tgn:7007919",
          "tgn:7029392"
        ],
        "placetype": [
          "aat:300008347"
        ],
        "id": 2115003,
        "name:xx": "West Springfield"
      }
    },
    {
      "geometry": {
        "type": "Point",
        "coordinates": [
          -78.8333,
          36.8833
        ]
      },
      "type": "Feature",
      "properties": {
        "hierarchy": [
          "tgn:2115009",
          "tgn:1000001",
          "tgn:7012149",
          "tgn:2002166",
          "tgn:7007919",
          "tgn:7029392"
        ],
        "placetype": [
          "aat:300008347",
          "aat:300387210"
        ],
        "id": 2115009,
        "name:xx": "Wests Store"
      }
    }
  ]
}
