{
  "geometry": {
    "type": "Point",
    "coordinates": [
      79.565369,
      27.607194
    ]
  },
  "type": "Feature",
  "properties": {
    "hierarchy": [
      "tgn:7560531",
      "tgn:1000004",
      "tgn:7000198",
      "tgn:7016722",
      "tgn:7029392"
    ],
    "placetype": [
      "aat:300008347"
    ],
    "name:en": "Sulemānpurpatti",
    "id": 7560531
  }
}
