{
  "geometry": {
    "type": "Point",
    "coordinates": [
      -153.2833,
      59.7333
    ]
  },
  "type": "Feature",
  "properties": {
    "hierarchy": [
      "tgn:2329124",
      "tgn:7006450",
      "tgn:1000001",
      "tgn:7019698",
      "tgn:7012149",
      "tgn:7029392"
    ],
    "placetype": [
      "aat:300008706"
    ],
    "id": 2329124,
    "name:xx": "Fitz Creek"
  }
}
