{
  "geometry": {
    "type": "Point",
    "coordinates": [
      -99.3667,
      33.5333
    ]
  },
  "type": "Feature",
  "properties": {
    "hierarchy": [
      "tgn:2213300",
      "tgn:1000001",
      "tgn:2001939",
      "tgn:7012149",
      "tgn:7007826",
      "tgn:7029392"
    ],
    "placetype": [
      "aat:300008706"
    ],
    "id": 2213300,
    "name:xx": "Cabin Creek"
  }
}
