{
  "type": "FeatureCollection",
  "features": [
    {
      "geometry": {
        "type": "Point",
        "coordinates": [
          -100.616667,
          21.2
        ]
      },
      "type": "Feature",
      "properties": {
        "hierarchy": [
          "tgn:7368770",
          "tgn:7005584",
          "tgn:1000001",
          "tgn:7005560",
          "tgn:7029392"
        ],
        "placetype": [
          "aat:300008347"
        ],
        "id": 7368770,
        "name:xx": "Guadalupe"
      }
    },
    {
      "geometry": {
        "type": "Point",
        "coordinates": [
          -103.25,
          20.85
        ]
      },
      "type": "Feature",
      "properties": {
        "hierarchy": [
          "tgn:7368771",
          "tgn:7005586",
          "tgn:1000001",
          "tgn:7005560",
          "tgn:7029392"
        ],
        "placetype": [
          "aat:300008347"
        ],
        "id": 7368771,
        "name:xx": "Guadalupe"
      }
    },
    {
      "geometry": {
        "type": "Point",
        "coordinates": [
          -101.956944,
          20.906111
        ]
      },
      "type": "Feature",
      "properties": {
        "hierarchy": [
          "tgn:7368773",
          "tgn:7005584",
          "tgn:1000001",
          "tgn:7005560",
          "tgn:7029392"
        ],
        "placetype": [
          "aat:300008347"
        ],
        "id": 7368773,
        "name:xx": "Guadalupe"
      }
    },
    {
      "geometry": {
        "type": "Point",
        "coordinates": [
          -99.716667,
          20.85
        ]
      },
      "type": "Feature",
      "properties": {
        "hierarchy": [
          "tgn:7368774",
          "tgn:1000001",
          "tgn:7005593",
          "tgn:7005560",
          "tgn:7029392"
        ],
        "placetype": [
          "aat:300008347"
        ],
        "id": 7368774,
        "name:xx": "Guadalupe"
      }
    },
    {
      "geometry": {
        "type": "Point",
        "coordinates": [
          -100.116667,
          20.833333
        ]
      },
      "type": "Feature",
      "properties": {
        "hierarchy": [
          "tgn:7368775",
          "tgn:1000001",
          "tgn:7005593",
          "tgn:7005560",
          "tgn:7029392"
        ],
        "placetype": [
          "aat:300008347"
        ],
        "id": 7368775,
        "name:xx": "Guadalupe"
      }
    },
    {
      "geometry": {
        "type": "Point",
        "coordinates": [
          -104.133333,
          20.783333
        ]
      },
      "type": "Feature",
      "properties": {
        "hierarchy": [
          "tgn:7368776",
          "tgn:7005586",
          "tgn:1000001",
          "tgn:7005560",
          "tgn:7029392"
        ],
        "placetype": [
          "aat:300008347"
        ],
        "id": 7368776,
        "name:xx": "Guadalupe"
      }
    },
    {
      "geometry": {
        "type": "Point",
        "coordinates": [
          -103.7,
          20.666667
        ]
      },
      "type": "Feature",
      "properties": {
        "hierarchy": [
          "tgn:7368777",
          "tgn:7005586",
          "tgn:1000001",
          "tgn:7005560",
          "tgn:7029392"
        ],
        "placetype": [
          "aat:300008347"
        ],
        "id": 7368777,
        "name:xx": "Guadalupe"
      }
    },
    {
      "geometry": {
        "type": "Point",
        "coordinates": [
          -101.15,
          20.616667
        ]
      },
      "type": "Feature",
      "properties": {
        "hierarchy": [
          "tgn:7368778",
          "tgn:7005584",
          "tgn:1000001",
          "tgn:7005560",
          "tgn:7029392"
        ],
        "placetype": [
          "aat:300008347"
        ],
        "id": 7368778,
        "name:xx": "Guadalupe"
      }
    },
    {
      "geometry": {
        "type": "Point",
        "coordinates": [
          -101.466667,
          20.6
        ]
      },
      "type": "Feature",
      "properties": {
        "hierarchy": [
          "tgn:7368779",
          "tgn:7005584",
          "tgn:1000001",
          "tgn:7005560",
          "tgn:7029392"
        ],
        "placetype": [
          "aat:300008347"
        ],
        "id": 7368779,
        "name:xx": "Guadalupe"
      }
    }
  ]
}
