{
  "geometry": {
    "type": "Point",
    "coordinates": [
      -69.7167,
      45.3333
    ]
  },
  "type": "Feature",
  "properties": {
    "hierarchy": [
      "tgn:7023514",
      "tgn:1000001",
      "tgn:7012149",
      "tgn:7007515",
      "tgn:7029392"
    ],
    "placetype": [
      "aat:300008699"
    ],
    "id": 7023514,
    "name:xx": "Mud Pond Brook"
  }
}
