{
  "geometry": {
    "type": "Point",
    "coordinates": [
      11.05,
      47.75
    ]
  },
  "type": "Feature",
  "properties": {
    "hierarchy": [
      "tgn:7144160",
      "tgn:7003669",
      "tgn:1000003",
      "tgn:7000084",
      "tgn:7029392"
    ],
    "placetype": [
      "aat:300008699"
    ],
    "id": 7144160,
    "name:xx": "Kohl-Bach"
  }
}
