{
  "geometry": {
    "type": "Point",
    "coordinates": [
      -75.85,
      38.8167
    ]
  },
  "type": "Feature",
  "properties": {
    "hierarchy": [
      "tgn:2596096",
      "tgn:1002234",
      "tgn:1000001",
      "tgn:7012149",
      "tgn:7007516",
      "tgn:7029392"
    ],
    "placetype": [
      "aat:300008347"
    ],
    "id": 2596096,
    "name:xx": "Potters Landing"
  }
}
