{
  "geometry": {
    "type": "Point",
    "coordinates": [
      -95.3167,
      46.9167
    ]
  },
  "type": "Feature",
  "properties": {
    "hierarchy": [
      "tgn:2370200",
      "tgn:2001001",
      "tgn:1000001",
      "tgn:7012149",
      "tgn:7007521",
      "tgn:7029392"
    ],
    "placetype": [
      "aat:300008680"
    ],
    "id": 2370200,
    "name:xx": "Gyles Lake"
  }
}
