{
  "geometry": {
    "type": "Point",
    "coordinates": [
      79.928377,
      22.368361
    ]
  },
  "type": "Feature",
  "properties": {
    "hierarchy": [
      "tgn:7556557",
      "tgn:1000004",
      "tgn:7000198",
      "tgn:1001894",
      "tgn:7029392"
    ],
    "placetype": [
      "aat:300008699"
    ],
    "name:en": "Sāgar Nadī",
    "id": 7556557
  }
}
