{
  "type": "FeatureCollection",
  "features": [
    {
      "geometry": {
        "type": "Point",
        "coordinates": [
          15.266667,
          41.5
        ]
      },
      "type": "Feature",
      "properties": {
        "hierarchy": [
          "tgn:7036612",
          "tgn:1003455",
          "tgn:1000003",
          "tgn:7010380",
          "tgn:1000080",
          "tgn:7029392"
        ],
        "placetype": [
          "aat:300008699"
        ],
        "id": 7036612,
        "name:xx": "Volturino, Fiumara di"
      }
    },
    {
      "geometry": {
        "type": "Point",
        "coordinates": [
          12.040833,
          44.034444
        ]
      },
      "type": "Feature",
      "properties": {
        "hierarchy": [
          "tgn:7036617",
          "tgn:7003129",
          "tgn:1000003",
          "tgn:7008516",
          "tgn:1000080",
          "tgn:7029392"
        ],
        "placetype": [
          "aat:300008347"
        ],
        "id": 7036617,
        "name:xx": "Voltre"
      }
    },
    {
      "geometry": {
        "type": "Point",
        "coordinates": [
          13.05,
          45.683333
        ]
      },
      "type": "Feature",
      "properties": {
        "hierarchy": [
          "tgn:7036618",
          "tgn:1003506",
          "tgn:1000003",
          "tgn:7002993",
          "tgn:1000080",
          "tgn:7029392"
        ],
        "placetype": [
          "aat:300008347"
        ],
        "id": 7036618,
        "name:xx": "Volton"
      }
    },
    {
      "geometry": {
        "type": "Point",
        "coordinates": [
          12.75,
          43.2
        ]
      },
      "type": "Feature",
      "properties": {
        "hierarchy": [
          "tgn:7036619",
          "tgn:7003170",
          "tgn:1000003",
          "tgn:7003125",
          "tgn:1000080",
          "tgn:7029392"
        ],
        "placetype": [
          "aat:300008347"
        ],
        "id": 7036619,
        "name:xx": "Voltole"
      }
    }
  ]
}
