{
  "geometry": {
    "type": "Point",
    "coordinates": [
      23.4333,
      -27.5833
    ]
  },
  "type": "Feature",
  "properties": {
    "hierarchy": [
      "tgn:1110508",
      "tgn:7001242",
      "tgn:7029392"
    ],
    "placetype": [
      "aat:300008777"
    ],
    "id": 1110508,
    "name:xx": "Kuruman-Heuwels"
  }
}
