{
  "geometry": {
    "type": "Point",
    "coordinates": [
      -0.65,
      37.65
    ]
  },
  "type": "Feature",
  "properties": {
    "hierarchy": [
      "tgn:7334375",
      "tgn:1001439",
      "tgn:1000003",
      "tgn:7002797",
      "tgn:1000095",
      "tgn:7029392"
    ],
    "placetype": [
      "aat:300008791"
    ],
    "id": 7334375,
    "name:xx": "Hormigón, Islote"
  }
}
