{
  "geometry": {
    "type": "Point",
    "coordinates": [
      -67.25,
      0.0333
    ]
  },
  "type": "Feature",
  "properties": {
    "hierarchy": [
      "tgn:7014806",
      "tgn:1000002",
      "tgn:7029392"
    ],
    "placetype": [
      "aat:300008707"
    ],
    "id": 7014806,
    "name:xx": "Uaupés"
  }
}
