{
  "geometry": {
    "type": "Point",
    "coordinates": [
      -77.4167,
      41.6667
    ]
  },
  "type": "Feature",
  "properties": {
    "hierarchy": [
      "tgn:2089734",
      "tgn:1000001",
      "tgn:7012149",
      "tgn:1002945",
      "tgn:7007710",
      "tgn:7029392"
    ],
    "placetype": [
      "aat:300008347",
      "aat:300387210"
    ],
    "id": 2089734,
    "name:xx": "Kennedy"
  }
}
