{
  "geometry": {
    "type": "Point",
    "coordinates": [
      -78.65,
      39.6333
    ]
  },
  "type": "Feature",
  "properties": {
    "hierarchy": [
      "tgn:2735221",
      "tgn:2000934",
      "tgn:1000001",
      "tgn:7012149",
      "tgn:7007516",
      "tgn:7029392"
    ],
    "placetype": [
      "aat:300008347"
    ],
    "id": 2735221,
    "name:xx": "Twiggtown"
  }
}
