{
  "geometry": {
    "type": "Point",
    "coordinates": [
      12.5167,
      50.35
    ]
  },
  "type": "Feature",
  "properties": {
    "hierarchy": [
      "tgn:1027299",
      "tgn:7593913",
      "tgn:1000003",
      "tgn:1001780",
      "tgn:7029392"
    ],
    "placetype": [
      "aat:300008347"
    ],
    "id": 1027299,
    "name:xx": "Kraslice"
  }
}
