{
  "type": "FeatureCollection",
  "features": [
    {
      "geometry": {
        "type": "Point",
        "coordinates": [
          -85.35,
          37.2833
        ]
      },
      "type": "Feature",
      "properties": {
        "hierarchy": [
          "tgn:2581750",
          "tgn:1000001",
          "tgn:7012149",
          "tgn:2000844",
          "tgn:7007255",
          "tgn:7029392"
        ],
        "placetype": [
          "aat:300008706"
        ],
        "id": 2581750,
        "name:xx": "Pinch Creek"
      }
    },
    {
      "geometry": {
        "type": "Point",
        "coordinates": [
          -91.5167,
          38.8667
        ]
      },
      "type": "Feature",
      "properties": {
        "hierarchy": [
          "tgn:2581751",
          "tgn:1000001",
          "tgn:7012149",
          "tgn:1002687",
          "tgn:7007523",
          "tgn:7029392"
        ],
        "placetype": [
          "aat:300008706"
        ],
        "id": 2581751,
        "name:xx": "Pinch Creek"
      }
    },
    {
      "geometry": {
        "type": "Point",
        "coordinates": [
          -91.7333,
          38.8833
        ]
      },
      "type": "Feature",
      "properties": {
        "hierarchy": [
          "tgn:2581752",
          "tgn:1000001",
          "tgn:1002223",
          "tgn:7012149",
          "tgn:7007523",
          "tgn:7029392"
        ],
        "placetype": [
          "aat:300008706"
        ],
        "id": 2581752,
        "name:xx": "Pinch Creek"
      }
    },
    {
      "geometry": {
        "type": "Point",
        "coordinates": [
          -81.45,
          38.4167
        ]
      },
      "type": "Feature",
      "properties": {
        "hierarchy": [
          "tgn:2581753",
          "tgn:1000001",
          "tgn:7012149",
          "tgn:2002270",
          "tgn:7013961",
          "tgn:7029392"
        ],
        "placetype": [
          "aat:300008706"
        ],
        "id": 2581753,
        "name:xx": "Pinch Creek"
      }
    },
    {
      "geometry": {
        "type": "Point",
        "coordinates": [
          -80.9833,
          37.6833
        ]
      },
      "type": "Feature",
      "properties": {
        "hierarchy": [
          "tgn:2581754",
          "tgn:1000001",
          "tgn:7012149",
          "tgn:2002290",
          "tgn:7013961",
          "tgn:7029392"
        ],
        "placetype": [
          "aat:300008706"
        ],
        "id": 2581754,
        "name:xx": "Pinch Creek"
      }
    },
    {
      "geometry": {
        "type": "Point",
        "coordinates": [
          -91.75,
          44.65
        ]
      },
      "type": "Feature",
      "properties": {
        "hierarchy": [
          "tgn:2581755",
          "tgn:1000001",
          "tgn:2002319",
          "tgn:7012149",
          "tgn:7007922",
          "tgn:7029392"
        ],
        "placetype": [
          "aat:300008706"
        ],
        "id": 2581755,
        "name:xx": "Pinch Creek"
      }
    },
    {
      "geometry": {
        "type": "Point",
        "coordinates": [
          -115.7667,
          44
        ]
      },
      "type": "Feature",
      "properties": {
        "hierarchy": [
          "tgn:2581756",
          "tgn:1000001",
          "tgn:2000459",
          "tgn:7012149",
          "tgn:7007250",
          "tgn:7029392"
        ],
        "placetype": [
          "aat:300008761"
        ],
        "id": 2581756,
        "name:xx": "Pinch Gulch"
      }
    },
    {
      "geometry": {
        "type": "Point",
        "coordinates": [
          -78.2,
          34.0833
        ]
      },
      "type": "Feature",
      "properties": {
        "hierarchy": [
          "tgn:2581757",
          "tgn:1000001",
          "tgn:2001472",
          "tgn:7012149",
          "tgn:7007709",
          "tgn:7029392"
        ],
        "placetype": [
          "aat:300008706"
        ],
        "id": 2581757,
        "name:xx": "Pinch Gut Creek"
      }
    },
    {
      "geometry": {
        "type": "Point",
        "coordinates": [
          -80.15,
          34.9333
        ]
      },
      "type": "Feature",
      "properties": {
        "hierarchy": [
          "tgn:2581758",
          "tgn:2001466",
          "tgn:1000001",
          "tgn:7012149",
          "tgn:7007709",
          "tgn:7029392"
        ],
        "placetype": [
          "aat:300008706"
        ],
        "id": 2581758,
        "name:xx": "Pinch Gut Creek"
      }
    },
    {
      "geometry": {
        "type": "Point",
        "coordinates": [
          -80.4333,
          36.4667
        ]
      },
      "type": "Feature",
      "properties": {
        "hierarchy": [
          "tgn:2581759",
          "tgn:1000001",
          "tgn:7012149",
          "tgn:7007709",
          "tgn:7029392"
        ],
        "placetype": [
          "aat:300008706"
        ],
        "id": 2581759,
        "name:xx": "Pinch Gut Creek"
      }
    }
  ]
}
