{
  "geometry": {
    "type": "Point",
    "coordinates": [
      -109.2833,
      42.75
    ]
  },
  "type": "Feature",
  "properties": {
    "hierarchy": [
      "tgn:2273897",
      "tgn:1000001",
      "tgn:7012149",
      "tgn:2002382",
      "tgn:7007923",
      "tgn:7029392"
    ],
    "placetype": [
      "aat:300008680"
    ],
    "id": 2273897,
    "name:xx": "Dads Lake"
  }
}
