{
  "geometry": {
    "type": "Point",
    "coordinates": [
      -120.8333,
      46.4833
    ]
  },
  "type": "Feature",
  "properties": {
    "hierarchy": [
      "tgn:2548525",
      "tgn:1000001",
      "tgn:7012149",
      "tgn:1003042",
      "tgn:7007920",
      "tgn:7029392"
    ],
    "placetype": [
      "aat:300008706"
    ],
    "id": 2548525,
    "name:xx": "North Medicine Creek"
  }
}
