{
  "geometry": {
    "type": "Point",
    "coordinates": [
      -108.05,
      31.9667
    ]
  },
  "type": "Feature",
  "properties": {
    "hierarchy": [
      "tgn:2344457",
      "tgn:1000001",
      "tgn:7012149",
      "tgn:2001444",
      "tgn:7007566",
      "tgn:7029392"
    ],
    "placetype": [
      "aat:300008798"
    ],
    "id": 2344457,
    "name:xx": "Gap Hill"
  }
}
