{
  "geometry": {
    "type": "Point",
    "coordinates": [
      -105.7667,
      39.45
    ]
  },
  "type": "Feature",
  "properties": {
    "hierarchy": [
      "tgn:2186504",
      "tgn:1000001",
      "tgn:7012149",
      "tgn:2000238",
      "tgn:7007158",
      "tgn:7029392"
    ],
    "placetype": [
      "aat:300008761"
    ],
    "id": 2186504,
    "name:xx": "Bone Gulch"
  }
}
