{
  "geometry": {
    "type": "Point",
    "coordinates": [
      -111.45,
      38.75
    ]
  },
  "type": "Feature",
  "properties": {
    "hierarchy": [
      "tgn:2415905",
      "tgn:1000001",
      "tgn:7012149",
      "tgn:7007827",
      "tgn:7029392"
    ],
    "placetype": [
      "aat:300008706"
    ],
    "id": 2415905,
    "name:xx": "Ivie Creek"
  }
}
