{
  "geometry": {
    "type": "Point",
    "coordinates": [
      -85.1833,
      33.75
    ]
  },
  "type": "Feature",
  "properties": {
    "hierarchy": [
      "tgn:2163062",
      "tgn:1000001",
      "tgn:7012149",
      "tgn:2000362",
      "tgn:7007248",
      "tgn:7029392"
    ],
    "placetype": [
      "aat:300008706"
    ],
    "id": 2163062,
    "name:xx": "Bennett Creek"
  }
}
