{
  "geometry": {
    "type": "Point",
    "coordinates": [
      -95.7833,
      45.8833
    ]
  },
  "type": "Feature",
  "properties": {
    "hierarchy": [
      "tgn:2392572",
      "tgn:1000001",
      "tgn:2001024",
      "tgn:7012149",
      "tgn:7007521",
      "tgn:7029392"
    ],
    "placetype": [
      "aat:300008680"
    ],
    "id": 2392572,
    "name:xx": "Hjermenrud Lake"
  }
}
