{
  "geometry": {
    "type": "Point",
    "coordinates": [
      31.302957,
      30.44259
    ]
  },
  "type": "Feature",
  "properties": {
    "hierarchy": [
      "tgn:7536187",
      "tgn:7001242",
      "tgn:7016833",
      "tgn:1001113",
      "tgn:7029392"
    ],
    "placetype": [
      "aat:300008347"
    ],
    "name:en": "Kafr ash Sha'āwirah",
    "id": 7536187
  }
}
