{
  "geometry": {
    "type": "Point",
    "coordinates": [
      -114.0167,
      41.2333
    ]
  },
  "type": "Feature",
  "properties": {
    "hierarchy": [
      "tgn:2190332",
      "tgn:1000001",
      "tgn:7012149",
      "tgn:7029392"
    ],
    "placetype": [
      "aat:300008761"
    ],
    "id": 2190332,
    "name:xx": "Box Canyon"
  }
}
