{
  "geometry": {
    "type": "Point",
    "coordinates": [
      3.0333,
      48.6333
    ]
  },
  "type": "Feature",
  "properties": {
    "hierarchy": [
      "tgn:4004251",
      "tgn:1000003",
      "tgn:7002883",
      "tgn:1000070",
      "tgn:7029392"
    ],
    "placetype": [
      "aat:300008347"
    ],
    "id": 4004251,
    "name:xx": "Gastins"
  }
}
