{
  "geometry": {
    "type": "Point",
    "coordinates": [
      -114.2167,
      36.1333
    ]
  },
  "type": "Feature",
  "properties": {
    "hierarchy": [
      "tgn:2345538",
      "tgn:1000001",
      "tgn:2001410",
      "tgn:7012149",
      "tgn:7007526",
      "tgn:7029392"
    ],
    "placetype": [
      "aat:300008761"
    ],
    "id": 2345538,
    "name:xx": "Garnet Valley"
  }
}
