{
  "geometry": {
    "type": "Point",
    "coordinates": [
      -82.4167,
      36.1667
    ]
  },
  "type": "Feature",
  "properties": {
    "hierarchy": [
      "tgn:2278492",
      "tgn:1000001",
      "tgn:7012149",
      "tgn:2001926",
      "tgn:7007825",
      "tgn:7029392"
    ],
    "placetype": [
      "aat:300008706"
    ],
    "id": 2278492,
    "name:xx": "Deacon Creek"
  }
}
