{
  "geometry": {
    "type": "Point",
    "coordinates": [
      -83.6167,
      40.6667
    ]
  },
  "type": "Feature",
  "properties": {
    "hierarchy": [
      "tgn:2409520",
      "tgn:1000001",
      "tgn:7012149",
      "tgn:1002453",
      "tgn:7007706",
      "tgn:7029392"
    ],
    "placetype": [
      "aat:300006191"
    ],
    "id": 2409520,
    "name:xx": "Idlewild, Lake"
  }
}
