{
  "type": "FeatureCollection",
  "features": [
    {
      "geometry": {
        "type": "Point",
        "coordinates": [
          8.8,
          44.433
        ]
      },
      "type": "Feature",
      "properties": {
        "hierarchy": [
          "tgn:7005330",
          "tgn:1000003",
          "tgn:7003142",
          "tgn:7003236",
          "tgn:1000080",
          "tgn:7029392"
        ],
        "placetype": [
          "aat:300008347"
        ],
        "id": 7005330,
        "name:xx": "Pegli"
      }
    },
    {
      "geometry": {
        "type": "Point",
        "coordinates": [
          8.7,
          44.533333
        ]
      },
      "type": "Feature",
      "properties": {
        "hierarchy": [
          "tgn:7005331",
          "tgn:1000003",
          "tgn:7003142",
          "tgn:7003236",
          "tgn:1000080",
          "tgn:7029392"
        ],
        "placetype": [
          "aat:300008347"
        ],
        "id": 7005331,
        "name:xx": "Campo Ligure"
      }
    },
    {
      "geometry": {
        "type": "Point",
        "coordinates": [
          -76,
          24
        ]
      },
      "type": "Feature",
      "properties": {
        "name:eo": "Bahamoj",
        "name:en": "Bahamas",
        "hierarchy": [
          "tgn:7005332",
          "tgn:1000001",
          "tgn:7029392"
        ],
        "name:ar": "جزر ا بٍهاما",
        "name:fr": "Bahamas",
        "name:de": "Bahamas",
        "placetype": [
          "aat:300387054",
          "aat:300235115",
          "aat:300128207",
          "aat:300387174"
        ],
        "name:slv": "Bahamov",
        "name:ru": "Багамские Острова",
        "name:zh": "巴哈马",
        "id": 7005332,
        "name:es": "Bahamas"
      }
    },
    {
      "geometry": {
        "type": "Point",
        "coordinates": [
          9.166667,
          44.416667
        ]
      },
      "type": "Feature",
      "properties": {
        "hierarchy": [
          "tgn:7005334",
          "tgn:1000003",
          "tgn:7003142",
          "tgn:7003236",
          "tgn:1000080",
          "tgn:7029392"
        ],
        "placetype": [
          "aat:300008347"
        ],
        "id": 7005334,
        "name:xx": "Uscio"
      }
    },
    {
      "geometry": {
        "type": "Point",
        "coordinates": [
          9.4,
          44.266667
        ]
      },
      "type": "Feature",
      "properties": {
        "hierarchy": [
          "tgn:7005335",
          "tgn:1000003",
          "tgn:7003142",
          "tgn:7003236",
          "tgn:1000080",
          "tgn:7029392"
        ],
        "placetype": [
          "aat:300008347",
          "aat:300008375",
          "aat:300387292"
        ],
        "id": 7005335,
        "name:xx": "Sestri Levante"
      }
    },
    {
      "geometry": {
        "type": "Point",
        "coordinates": [
          9.2,
          44.333333
        ]
      },
      "type": "Feature",
      "properties": {
        "hierarchy": [
          "tgn:7005336",
          "tgn:1000003",
          "tgn:7003142",
          "tgn:7003236",
          "tgn:1000080",
          "tgn:7029392"
        ],
        "placetype": [
          "aat:300008347"
        ],
        "id": 7005336,
        "name:xx": "Santa Margherita Ligure"
      }
    },
    {
      "geometry": {
        "type": "Point",
        "coordinates": [
          9.5,
          44.233333
        ]
      },
      "type": "Feature",
      "properties": {
        "hierarchy": [
          "tgn:7005337",
          "tgn:1000003",
          "tgn:7003142",
          "tgn:7003236",
          "tgn:1000080",
          "tgn:7029392"
        ],
        "placetype": [
          "aat:300008347"
        ],
        "id": 7005337,
        "name:xx": "Moneglia"
      }
    },
    {
      "geometry": {
        "type": "Point",
        "coordinates": [
          9.35,
          44.3
        ]
      },
      "type": "Feature",
      "properties": {
        "hierarchy": [
          "tgn:7005338",
          "tgn:1000003",
          "tgn:7003142",
          "tgn:7003236",
          "tgn:1000080",
          "tgn:7029392"
        ],
        "placetype": [
          "aat:300008347"
        ],
        "id": 7005338,
        "name:xx": "Lavagna"
      }
    },
    {
      "geometry": {
        "type": "Point",
        "coordinates": [
          9.233333,
          44.35
        ]
      },
      "type": "Feature",
      "properties": {
        "hierarchy": [
          "tgn:7005339",
          "tgn:1000003",
          "tgn:7003142",
          "tgn:7003236",
          "tgn:1000080",
          "tgn:7029392"
        ],
        "placetype": [
          "aat:300008347",
          "aat:300008375",
          "aat:300120599",
          "aat:300387291"
        ],
        "id": 7005339,
        "name:xx": "Rapallo"
      }
    }
  ]
}
