{
  "geometry": {
    "type": "Point",
    "coordinates": [
      -117.7833,
      46.3167
    ]
  },
  "type": "Feature",
  "properties": {
    "hierarchy": [
      "tgn:2691915",
      "tgn:1000001",
      "tgn:2002241",
      "tgn:7012149",
      "tgn:7007920",
      "tgn:7029392"
    ],
    "placetype": [
      "aat:300266640"
    ],
    "id": 2691915,
    "name:xx": "Starvout Ridge"
  }
}
