{
  "geometry": {
    "type": "Point",
    "coordinates": [
      25.466667,
      29.233333
    ]
  },
  "type": "Feature",
  "properties": {
    "hierarchy": [
      "tgn:7529052",
      "tgn:7001242",
      "tgn:7016833",
      "tgn:1001418",
      "tgn:7029392"
    ],
    "placetype": [
      "aat:300008697"
    ],
    "name:en": "Ţaghāghīn al Fawqānīyah, 'Ayn",
    "id": 7529052
  }
}
