{
  "type": "FeatureCollection",
  "features": [
    {
      "geometry": {
        "type": "Point",
        "coordinates": [
          6.6,
          52.566667
        ]
      },
      "type": "Feature",
      "properties": {
        "hierarchy": [
          "tgn:7266020",
          "tgn:1000003",
          "tgn:7003626",
          "tgn:7016845",
          "tgn:7029392"
        ],
        "placetype": [
          "aat:300000745"
        ],
        "name:nl": "Heemse",
        "id": 7266020
      }
    },
    {
      "geometry": {
        "type": "Point",
        "coordinates": [
          7.1,
          53.116667
        ]
      },
      "type": "Feature",
      "properties": {
        "hierarchy": [
          "tgn:7266021",
          "tgn:1000003",
          "tgn:7003613",
          "tgn:7016845",
          "tgn:7029392"
        ],
        "placetype": [
          "aat:300000206"
        ],
        "name:nl": "Heemhoeve",
        "id": 7266021
      }
    },
    {
      "geometry": {
        "type": "Point",
        "coordinates": [
          6.466667,
          51.966667
        ]
      },
      "type": "Feature",
      "properties": {
        "hierarchy": [
          "tgn:7266022",
          "tgn:7003619",
          "tgn:1000003",
          "tgn:7016845",
          "tgn:7029392"
        ],
        "placetype": [
          "aat:300008347"
        ],
        "name:nl": "Heelweg",
        "id": 7266022
      }
    },
    {
      "geometry": {
        "type": "Point",
        "coordinates": [
          5.75,
          51.983333
        ]
      },
      "type": "Feature",
      "properties": {
        "hierarchy": [
          "tgn:7266023",
          "tgn:7003619",
          "tgn:1000003",
          "tgn:7016845",
          "tgn:7029392"
        ],
        "placetype": [
          "aat:300008347"
        ],
        "name:nl": "Heelsum",
        "id": 7266023
      }
    },
    {
      "geometry": {
        "type": "Point",
        "coordinates": [
          5.883333,
          51.2
        ]
      },
      "type": "Feature",
      "properties": {
        "hierarchy": [
          "tgn:7266025",
          "tgn:1000003",
          "tgn:7003622",
          "tgn:7016845",
          "tgn:7029392"
        ],
        "placetype": [
          "aat:300008680"
        ],
        "name:nl": "Heelderpeel, Natuurbad",
        "id": 7266025
      }
    },
    {
      "geometry": {
        "type": "Point",
        "coordinates": [
          6.2,
          52.016667
        ]
      },
      "type": "Feature",
      "properties": {
        "hierarchy": [
          "tgn:7266027",
          "tgn:7003619",
          "tgn:1000003",
          "tgn:7016845",
          "tgn:7029392"
        ],
        "placetype": [
          "aat:300008178"
        ],
        "name:nl": "Heekenbroek",
        "id": 7266027
      }
    },
    {
      "geometry": {
        "type": "Point",
        "coordinates": [
          5.866667,
          50.883333
        ]
      },
      "type": "Feature",
      "properties": {
        "hierarchy": [
          "tgn:7266028",
          "tgn:1000003",
          "tgn:7003622",
          "tgn:7016845",
          "tgn:7029392"
        ],
        "placetype": [
          "aat:300008347"
        ],
        "name:nl": "Heek",
        "id": 7266028
      }
    },
    {
      "geometry": {
        "type": "Point",
        "coordinates": [
          6.15,
          51.933333
        ]
      },
      "type": "Feature",
      "properties": {
        "hierarchy": [
          "tgn:7266029",
          "tgn:7003619",
          "tgn:1000003",
          "tgn:7016845",
          "tgn:7029392"
        ],
        "placetype": [
          "aat:300008347"
        ],
        "name:nl": "Heegh",
        "id": 7266029
      }
    }
  ]
}
