{
  "type": "FeatureCollection",
  "features": [
    {
      "geometry": {
        "type": "Point",
        "coordinates": [
          -104.183333,
          25.1
        ]
      },
      "type": "Feature",
      "properties": {
        "hierarchy": [
          "tgn:7354220",
          "tgn:7005583",
          "tgn:1000001",
          "tgn:7005560",
          "tgn:7029392"
        ],
        "placetype": [
          "aat:300008347"
        ],
        "id": 7354220,
        "name:xx": "Casas Coloradas"
      }
    },
    {
      "geometry": {
        "type": "Point",
        "coordinates": [
          -102.5,
          22.616667
        ]
      },
      "type": "Feature",
      "properties": {
        "hierarchy": [
          "tgn:7354221",
          "tgn:1000001",
          "tgn:7005601",
          "tgn:7005560",
          "tgn:7029392"
        ],
        "placetype": [
          "aat:300008347"
        ],
        "id": 7354221,
        "name:xx": "Casas Coloradas"
      }
    },
    {
      "geometry": {
        "type": "Point",
        "coordinates": [
          -105.366667,
          22.483333
        ]
      },
      "type": "Feature",
      "properties": {
        "hierarchy": [
          "tgn:7354222",
          "tgn:1000001",
          "tgn:1001906",
          "tgn:7005560",
          "tgn:7029392"
        ],
        "placetype": [
          "aat:300008347"
        ],
        "id": 7354222,
        "name:xx": "Casas Coloradas"
      }
    },
    {
      "geometry": {
        "type": "Point",
        "coordinates": [
          -106.6,
          25.983333
        ]
      },
      "type": "Feature",
      "properties": {
        "hierarchy": [
          "tgn:7354223",
          "tgn:7005581",
          "tgn:1000001",
          "tgn:7005560",
          "tgn:7029392"
        ],
        "placetype": [
          "aat:300000241"
        ],
        "id": 7354223,
        "name:xx": "Rancho Casas Blancas"
      }
    },
    {
      "geometry": {
        "type": "Point",
        "coordinates": [
          -102.05,
          20.883333
        ]
      },
      "type": "Feature",
      "properties": {
        "hierarchy": [
          "tgn:7354224",
          "tgn:7005586",
          "tgn:1000001",
          "tgn:7005560",
          "tgn:7029392"
        ],
        "placetype": [
          "aat:300000241"
        ],
        "id": 7354224,
        "name:xx": "San Felipe de Jesús"
      }
    },
    {
      "geometry": {
        "type": "Point",
        "coordinates": [
          -112.966667,
          27.033333
        ]
      },
      "type": "Feature",
      "properties": {
        "hierarchy": [
          "tgn:7354225",
          "tgn:1001836",
          "tgn:1000001",
          "tgn:7005560",
          "tgn:7029392"
        ],
        "placetype": [
          "aat:300008347"
        ],
        "id": 7354225,
        "name:xx": "Casas Blancas"
      }
    },
    {
      "geometry": {
        "type": "Point",
        "coordinates": [
          -105,
          25.4
        ]
      },
      "type": "Feature",
      "properties": {
        "hierarchy": [
          "tgn:7354226",
          "tgn:7005583",
          "tgn:1000001",
          "tgn:7005560",
          "tgn:7029392"
        ],
        "placetype": [
          "aat:300008347"
        ],
        "id": 7354226,
        "name:xx": "Casas Blancas"
      }
    },
    {
      "geometry": {
        "type": "Point",
        "coordinates": [
          -101.216667,
          21.383333
        ]
      },
      "type": "Feature",
      "properties": {
        "hierarchy": [
          "tgn:7354227",
          "tgn:7005584",
          "tgn:1000001",
          "tgn:7005560",
          "tgn:7029392"
        ],
        "placetype": [
          "aat:300008347"
        ],
        "id": 7354227,
        "name:xx": "Casas Blancas"
      }
    },
    {
      "geometry": {
        "type": "Point",
        "coordinates": [
          -101.966667,
          20.9
        ]
      },
      "type": "Feature",
      "properties": {
        "hierarchy": [
          "tgn:7354228",
          "tgn:7005584",
          "tgn:1000001",
          "tgn:7005560",
          "tgn:7029392"
        ],
        "placetype": [
          "aat:300008347"
        ],
        "id": 7354228,
        "name:xx": "Casas Blancas"
      }
    },
    {
      "geometry": {
        "type": "Point",
        "coordinates": [
          -101.433333,
          20.316667
        ]
      },
      "type": "Feature",
      "properties": {
        "hierarchy": [
          "tgn:7354229",
          "tgn:7005584",
          "tgn:1000001",
          "tgn:7005560",
          "tgn:7029392"
        ],
        "placetype": [
          "aat:300008347"
        ],
        "id": 7354229,
        "name:xx": "Casas Blancas"
      }
    }
  ]
}
