{
  "type": "FeatureCollection",
  "features": [
    {
      "geometry": {
        "type": "Point",
        "coordinates": [
          -87.541,
          33.209
        ]
      },
      "type": "Feature",
      "properties": {
        "hierarchy": [
          "tgn:4011501",
          "tgn:7002659",
          "tgn:1000001",
          "tgn:7012149",
          "tgn:2005546",
          "tgn:2000062",
          "tgn:7029392"
        ],
        "placetype": [
          "aat:300006617"
        ],
        "id": 4011501,
        "name:xx": "University of Alabama"
      }
    },
    {
      "geometry": {
        "type": "Point",
        "coordinates": [
          -1.433333,
          53.283333
        ]
      },
      "type": "Feature",
      "properties": {
        "hierarchy": [
          "tgn:4011505",
          "tgn:7002445",
          "tgn:1000003",
          "tgn:7008118",
          "tgn:7008591",
          "tgn:7029392"
        ],
        "placetype": [
          "aat:300008347"
        ],
        "name:en": "Unstone",
        "id": 4011505
      }
    },
    {
      "geometry": {
        "type": "Point",
        "coordinates": [
          11.766667,
          47.883333
        ]
      },
      "type": "Feature",
      "properties": {
        "hierarchy": [
          "tgn:4011506",
          "tgn:7003669",
          "tgn:1000003",
          "tgn:7000084",
          "tgn:7029392"
        ],
        "placetype": [
          "aat:300008347"
        ],
        "id": 4011506,
        "name:xx": "Unterdarching"
      }
    },
    {
      "geometry": {
        "type": "Point",
        "coordinates": [
          10.15,
          49.883333
        ]
      },
      "type": "Feature",
      "properties": {
        "hierarchy": [
          "tgn:4011507",
          "tgn:7003669",
          "tgn:1000003",
          "tgn:7000084",
          "tgn:7029392"
        ],
        "placetype": [
          "aat:300008347"
        ],
        "id": 4011507,
        "name:xx": "Untereisenheim"
      }
    }
  ]
}
