{
  "geometry": {
    "type": "Point",
    "coordinates": [
      30.916667,
      30.65
    ]
  },
  "type": "Feature",
  "properties": {
    "hierarchy": [
      "tgn:7529163",
      "tgn:7001242",
      "tgn:7016833",
      "tgn:1001087",
      "tgn:7029392"
    ],
    "placetype": [
      "aat:300005926"
    ],
    "name:en": "Sīdī 'Alī Qamar",
    "id": 7529163
  }
}
