{
  "geometry": {
    "type": "Point",
    "coordinates": [
      -91.016667,
      17.2875
    ]
  },
  "type": "Feature",
  "properties": {
    "hierarchy": [
      "tgn:7412955",
      "tgn:1000001",
      "tgn:7005596",
      "tgn:7005560",
      "tgn:7029392"
    ],
    "placetype": [
      "aat:300008347"
    ],
    "id": 7412955,
    "name:es": "La Piedra"
  }
}
