{
  "geometry": {
    "type": "Point",
    "coordinates": [
      -80.1167,
      37.2167
    ]
  },
  "type": "Feature",
  "properties": {
    "hierarchy": [
      "tgn:2355307",
      "tgn:1000001",
      "tgn:7012149",
      "tgn:7014344",
      "tgn:7007919",
      "tgn:7029392"
    ],
    "placetype": [
      "aat:300008746"
    ],
    "id": 2355307,
    "name:xx": "Goodwins Cave"
  }
}
