{
  "geometry": {
    "type": "Point",
    "coordinates": [
      -123.5333,
      46.9333
    ]
  },
  "type": "Feature",
  "properties": {
    "hierarchy": [
      "tgn:2760567",
      "tgn:1000001",
      "tgn:7012149",
      "tgn:1002418",
      "tgn:7007920",
      "tgn:7029392"
    ],
    "placetype": [
      "aat:300008706"
    ],
    "id": 2760567,
    "name:xx": "West Fork Vesta Creek"
  }
}
