{
  "geometry": {
    "type": "Point",
    "coordinates": [
      -97.3833,
      29.3667
    ]
  },
  "type": "Feature",
  "properties": {
    "hierarchy": [
      "tgn:1133041",
      "tgn:1000001",
      "tgn:7012149",
      "tgn:7007826",
      "tgn:7029392"
    ],
    "placetype": [
      "aat:300008706"
    ],
    "id": 1133041,
    "name:xx": "Denton Creek"
  }
}
