{
  "geometry": {
    "type": "Point",
    "coordinates": [
      -168.8167,
      63.0667
    ]
  },
  "type": "Feature",
  "properties": {
    "hierarchy": [
      "tgn:2601251",
      "tgn:7006450",
      "tgn:1000001",
      "tgn:7012149",
      "tgn:2000079",
      "tgn:7029392"
    ],
    "placetype": [
      "aat:300386853"
    ],
    "id": 2601251,
    "name:xx": "Punuk Islands"
  }
}
