{
  "geometry": {
    "type": "Point",
    "coordinates": [
      85.461576,
      22.35282
    ]
  },
  "type": "Feature",
  "properties": {
    "hierarchy": [
      "tgn:7547853",
      "tgn:1000004",
      "tgn:7000198",
      "tgn:7031783",
      "tgn:7029392"
    ],
    "placetype": [
      "aat:300008347"
    ],
    "name:en": "Bānki",
    "id": 7547853
  }
}
