{
  "geometry": {
    "type": "Point",
    "coordinates": [
      42.7667,
      47.4333
    ]
  },
  "type": "Feature",
  "properties": {
    "hierarchy": [
      "tgn:1053753",
      "tgn:1000004",
      "tgn:1003405",
      "tgn:7018214",
      "tgn:7002435",
      "tgn:7029392"
    ],
    "placetype": [
      "aat:300008347"
    ],
    "id": 1053753,
    "name:xx": "Dubovskoye"
  }
}
