{
  "geometry": {
    "type": "Point",
    "coordinates": [
      -116.2833,
      40.55
    ]
  },
  "type": "Feature",
  "properties": {
    "hierarchy": [
      "tgn:2626024",
      "tgn:1000001",
      "tgn:2001413",
      "tgn:7012149",
      "tgn:7007526",
      "tgn:7029392"
    ],
    "placetype": [
      "aat:300008761"
    ],
    "id": 2626024,
    "name:xx": "Rocky Canyon"
  }
}
