{
  "geometry": {
    "type": "Point",
    "coordinates": [
      -78.3167,
      41.6167
    ]
  },
  "type": "Feature",
  "properties": {
    "hierarchy": [
      "tgn:2580563",
      "tgn:1000001",
      "tgn:7012149",
      "tgn:7016020",
      "tgn:7007710",
      "tgn:7029392"
    ],
    "placetype": [
      "aat:300008761"
    ],
    "id": 2580563,
    "name:xx": "Pigeon Hollow"
  }
}
