{
  "geometry": {
    "type": "Point",
    "coordinates": [
      -112.5167,
      32.9833
    ]
  },
  "type": "Feature",
  "properties": {
    "hierarchy": [
      "tgn:2492494",
      "tgn:1000001",
      "tgn:7006451",
      "tgn:7012149",
      "tgn:2000097",
      "tgn:7029392"
    ],
    "placetype": [
      "aat:300008798"
    ],
    "id": 2492494,
    "name:xx": "Maricopa Mountains"
  }
}
