{
  "type": "FeatureCollection",
  "features": [
    {
      "geometry": {
        "type": "Point",
        "coordinates": [
          -105.6667,
          35
        ]
      },
      "type": "Feature",
      "properties": {
        "hierarchy": [
          "tgn:2066831",
          "tgn:1000001",
          "tgn:7012149",
          "tgn:2001458",
          "tgn:7007566",
          "tgn:7029392"
        ],
        "placetype": [
          "aat:300008347"
        ],
        "id": 2066831,
        "name:xx": "Clines Corners"
      }
    },
    {
      "geometry": {
        "type": "Point",
        "coordinates": [
          -105.7333,
          32.95
        ]
      },
      "type": "Feature",
      "properties": {
        "hierarchy": [
          "tgn:2066833",
          "tgn:1000001",
          "tgn:7012149",
          "tgn:2001447",
          "tgn:7007566",
          "tgn:7029392"
        ],
        "placetype": [
          "aat:300008347"
        ],
        "id": 2066833,
        "name:xx": "Cloudcroft"
      }
    },
    {
      "geometry": {
        "type": "Point",
        "coordinates": [
          -108.9167,
          31.4167
        ]
      },
      "type": "Feature",
      "properties": {
        "hierarchy": [
          "tgn:2066834",
          "tgn:1000001",
          "tgn:7012149",
          "tgn:2001440",
          "tgn:7007566",
          "tgn:7029392"
        ],
        "placetype": [
          "aat:300008347",
          "aat:300387210"
        ],
        "id": 2066834,
        "name:xx": "Cloverdale"
      }
    },
    {
      "geometry": {
        "type": "Point",
        "coordinates": [
          -103.2,
          34.4
        ]
      },
      "type": "Feature",
      "properties": {
        "hierarchy": [
          "tgn:2066835",
          "tgn:1000001",
          "tgn:2001433",
          "tgn:7012149",
          "tgn:7007566",
          "tgn:7029392"
        ],
        "placetype": [
          "aat:300008347",
          "aat:300008416"
        ],
        "id": 2066835,
        "name:xx": "Clovis"
      }
    },
    {
      "geometry": {
        "type": "Point",
        "coordinates": [
          -108.1,
          32.7667
        ]
      },
      "type": "Feature",
      "properties": {
        "hierarchy": [
          "tgn:2066836",
          "tgn:1000001",
          "tgn:7012149",
          "tgn:2001437",
          "tgn:7007566",
          "tgn:7029392"
        ],
        "placetype": [
          "aat:300387016"
        ],
        "id": 2066836,
        "name:xx": "Cobre"
      }
    },
    {
      "geometry": {
        "type": "Point",
        "coordinates": [
          -106.3333,
          35.6
        ]
      },
      "type": "Feature",
      "properties": {
        "hierarchy": [
          "tgn:2066837",
          "tgn:1000001",
          "tgn:7012149",
          "tgn:2001451",
          "tgn:7007566",
          "tgn:7029392"
        ],
        "placetype": [
          "aat:300008347"
        ],
        "id": 2066837,
        "name:xx": "Cochiti Pueblo"
      }
    },
    {
      "geometry": {
        "type": "Point",
        "coordinates": [
          -106.3667,
          35.6167
        ]
      },
      "type": "Feature",
      "properties": {
        "hierarchy": [
          "tgn:2066838",
          "tgn:1000001",
          "tgn:7012149",
          "tgn:2001451",
          "tgn:7007566",
          "tgn:7029392"
        ],
        "placetype": [
          "aat:300008347",
          "aat:300387324"
        ],
        "id": 2066838,
        "name:xx": "Cochiti Indian Reservation"
      }
    },
    {
      "geometry": {
        "type": "Point",
        "coordinates": [
          -106.3333,
          35.6333
        ]
      },
      "type": "Feature",
      "properties": {
        "hierarchy": [
          "tgn:2066839",
          "tgn:1000001",
          "tgn:7012149",
          "tgn:2001451",
          "tgn:7007566",
          "tgn:7029392"
        ],
        "placetype": [
          "aat:300008347"
        ],
        "id": 2066839,
        "name:xx": "Cochiti Lake"
      }
    }
  ]
}
