{
  "geometry": {
    "type": "Point",
    "coordinates": [
      -112.7667,
      42.3333
    ]
  },
  "type": "Feature",
  "properties": {
    "hierarchy": [
      "tgn:2250719",
      "tgn:1000001",
      "tgn:7012149",
      "tgn:2000490",
      "tgn:7007250",
      "tgn:7029392"
    ],
    "placetype": [
      "aat:300008761"
    ],
    "id": 2250719,
    "name:xx": "Colson Canyon"
  }
}
