{
  "type": "FeatureCollection",
  "features": [
    {
      "geometry": {
        "type": "Point",
        "coordinates": [
          1.6,
          46.3833
        ]
      },
      "type": "Feature",
      "properties": {
        "hierarchy": [
          "tgn:4003054",
          "tgn:1000003",
          "tgn:7001095",
          "tgn:1000070",
          "tgn:7029392"
        ],
        "placetype": [
          "aat:300008347"
        ],
        "id": 4003054,
        "name:xx": "Crozant"
      }
    },
    {
      "geometry": {
        "type": "Point",
        "coordinates": [
          3.7667,
          49.25
        ]
      },
      "type": "Feature",
      "properties": {
        "hierarchy": [
          "tgn:4003056",
          "tgn:1000003",
          "tgn:7002880",
          "tgn:1000070",
          "tgn:7029392"
        ],
        "placetype": [
          "aat:300008347"
        ],
        "id": 4003056,
        "name:xx": "Crugny"
      }
    }
  ]
}
