{
  "geometry": {
    "type": "Point",
    "coordinates": [
      -90.9333,
      46.1333
    ]
  },
  "type": "Feature",
  "properties": {
    "hierarchy": [
      "tgn:2473501",
      "tgn:1000001",
      "tgn:7012149",
      "tgn:2002353",
      "tgn:7007922",
      "tgn:7029392"
    ],
    "placetype": [
      "aat:300008680"
    ],
    "id": 2473501,
    "name:xx": "Lower Clam Lake"
  }
}
