{
  "geometry": {
    "type": "Point",
    "coordinates": [
      -160.9833,
      61.9167
    ]
  },
  "type": "Feature",
  "properties": {
    "hierarchy": [
      "tgn:2145444",
      "tgn:7006450",
      "tgn:1000001",
      "tgn:7012149",
      "tgn:2000087",
      "tgn:7029392"
    ],
    "placetype": [
      "aat:300008798"
    ],
    "id": 2145444,
    "name:xx": "Baldhead Mountain"
  }
}
