{
  "geometry": {
    "type": "Point",
    "coordinates": [
      -109.4833,
      33.8333
    ]
  },
  "type": "Feature",
  "properties": {
    "hierarchy": [
      "tgn:2299416",
      "tgn:2000090",
      "tgn:1000001",
      "tgn:7006451",
      "tgn:7012149",
      "tgn:7029392"
    ],
    "placetype": [
      "aat:300006191"
    ],
    "id": 2299416,
    "name:xx": "Duck Lake Tank"
  }
}
