{
  "geometry": {
    "type": "Point",
    "coordinates": [
      31.7927,
      31.404337
    ]
  },
  "type": "Feature",
  "properties": {
    "hierarchy": [
      "tgn:7523140",
      "tgn:7001242",
      "tgn:1001059",
      "tgn:7016833",
      "tgn:7029392"
    ],
    "placetype": [
      "aat:300008347"
    ],
    "name:en": "Ash Shu'arā'",
    "id": 7523140
  }
}
