{
  "geometry": {
    "type": "Point",
    "coordinates": [
      -64.1833,
      48.5167
    ]
  },
  "type": "Feature",
  "properties": {
    "hierarchy": [
      "tgn:1122114",
      "tgn:7005685",
      "tgn:1000001",
      "tgn:7005804",
      "tgn:7029392"
    ],
    "placetype": [
      "aat:300008707"
    ],
    "id": 1122114,
    "name:xx": "Bonaventure"
  }
}
