{
  "type": "FeatureCollection",
  "features": [
    {
      "geometry": {
        "type": "Point",
        "coordinates": [
          -108.8667,
          43
        ]
      },
      "type": "Feature",
      "properties": {
        "hierarchy": [
          "tgn:1126271",
          "tgn:1000001",
          "tgn:7012149",
          "tgn:2002371",
          "tgn:7007923",
          "tgn:7029392"
        ],
        "placetype": [
          "aat:300008707"
        ],
        "id": 1126271,
        "name:xx": "Little Wind"
      }
    },
    {
      "geometry": {
        "type": "Point",
        "coordinates": [
          -89.35,
          44.7333
        ]
      },
      "type": "Feature",
      "properties": {
        "hierarchy": [
          "tgn:1126274",
          "tgn:1000001",
          "tgn:7012149",
          "tgn:7007922",
          "tgn:7029392"
        ],
        "placetype": [
          "aat:300008707"
        ],
        "id": 1126274,
        "name:xx": "Little Wolf"
      }
    },
    {
      "geometry": {
        "type": "Point",
        "coordinates": [
          -114,
          43.75
        ]
      },
      "type": "Feature",
      "properties": {
        "hierarchy": [
          "tgn:1126275",
          "tgn:1000001",
          "tgn:7012149",
          "tgn:7007250",
          "tgn:7029392"
        ],
        "placetype": [
          "aat:300008707"
        ],
        "id": 1126275,
        "name:xx": "Little Wood"
      }
    },
    {
      "geometry": {
        "type": "Point",
        "coordinates": [
          43.4167,
          32.2
        ]
      },
      "type": "Feature",
      "properties": {
        "hierarchy": [
          "tgn:1126276",
          "tgn:1000004",
          "tgn:7029392"
        ],
        "placetype": [
          "aat:300008707"
        ],
        "id": 1126276,
        "name:xx": "Zāb-E Kūchek"
      }
    },
    {
      "geometry": {
        "type": "Point",
        "coordinates": [
          109.75,
          23.8667
        ]
      },
      "type": "Feature",
      "properties": {
        "hierarchy": [
          "tgn:1126278",
          "tgn:1000004",
          "tgn:1001678",
          "tgn:1000111",
          "tgn:7029392"
        ],
        "placetype": [
          "aat:300008707"
        ],
        "id": 1126278,
        "name:xx": "Liu"
      }
    },
    {
      "geometry": {
        "type": "Point",
        "coordinates": [
          120.5,
          40.2667
        ]
      },
      "type": "Feature",
      "properties": {
        "hierarchy": [
          "tgn:1126279",
          "tgn:1000004",
          "tgn:1001390",
          "tgn:1000111",
          "tgn:7029392"
        ],
        "placetype": [
          "aat:300008707"
        ],
        "id": 1126279,
        "name:xx": "Liugu He"
      }
    }
  ]
}
