{
  "geometry": {
    "type": "Point",
    "coordinates": [
      -85.65,
      32.3667
    ]
  },
  "type": "Feature",
  "properties": {
    "hierarchy": [
      "tgn:2326273",
      "tgn:7002659",
      "tgn:1000001",
      "tgn:7012149",
      "tgn:2000043",
      "tgn:7029392"
    ],
    "placetype": [
      "aat:300006191"
    ],
    "id": 2326273,
    "name:xx": "Fin and Feather Lake"
  }
}
