{
  "geometry": {
    "type": "Point",
    "coordinates": [
      -110.9167,
      43.8333
    ]
  },
  "type": "Feature",
  "properties": {
    "hierarchy": [
      "tgn:2722372",
      "tgn:1000001",
      "tgn:7012149",
      "tgn:2002384",
      "tgn:7007923",
      "tgn:7029392"
    ],
    "placetype": [
      "aat:300008706"
    ],
    "id": 2722372,
    "name:xx": "Tin Cup Creek"
  }
}
