{
  "geometry": {
    "type": "Point",
    "coordinates": [
      -72.1167,
      42.8667
    ]
  },
  "type": "Feature",
  "properties": {
    "hierarchy": [
      "tgn:2351203",
      "tgn:7019618",
      "tgn:1000001",
      "tgn:7012149",
      "tgn:7007564",
      "tgn:7029392"
    ],
    "placetype": [
      "aat:300008699"
    ],
    "id": 2351203,
    "name:xx": "Gleason Brook"
  }
}
