{
  "geometry": {
    "type": "Point",
    "coordinates": [
      22.9833,
      0.6333
    ]
  },
  "type": "Feature",
  "properties": {
    "hierarchy": [
      "tgn:1089503",
      "tgn:7001242",
      "tgn:7016755",
      "tgn:1000159",
      "tgn:7029392"
    ],
    "placetype": [
      "aat:300008347"
    ],
    "id": 1089503,
    "name:xx": "Simba"
  }
}
