{
  "geometry": {
    "type": "Point",
    "coordinates": [
      -91.1667,
      47.6667
    ]
  },
  "type": "Feature",
  "properties": {
    "hierarchy": [
      "tgn:2333477",
      "tgn:1000001",
      "tgn:7012149",
      "tgn:2001036",
      "tgn:7007521",
      "tgn:7029392"
    ],
    "placetype": [
      "aat:300008706"
    ],
    "id": 2333477,
    "name:xx": "Folly Creek"
  }
}
