{
  "geometry": {
    "type": "Point",
    "coordinates": [
      -96.8833,
      29.5333
    ]
  },
  "type": "Feature",
  "properties": {
    "hierarchy": [
      "tgn:2105368",
      "tgn:1000001",
      "tgn:7012149",
      "tgn:1002578",
      "tgn:7007826",
      "tgn:7029392"
    ],
    "placetype": [
      "aat:300008347",
      "aat:300387210"
    ],
    "id": 2105368,
    "name:xx": "Kinkler"
  }
}
