{
  "geometry": {
    "type": "Point",
    "coordinates": [
      -88.6833,
      39.0667
    ]
  },
  "type": "Feature",
  "properties": {
    "hierarchy": [
      "tgn:2027485",
      "tgn:1000001",
      "tgn:1002349",
      "tgn:7012149",
      "tgn:7007251",
      "tgn:7029392"
    ],
    "placetype": [
      "aat:300008347",
      "aat:300387210"
    ],
    "id": 2027485,
    "name:xx": "Dexter"
  }
}
