{
  "geometry": {
    "type": "Point",
    "coordinates": [
      -111.1833,
      43.6333
    ]
  },
  "type": "Feature",
  "properties": {
    "hierarchy": [
      "tgn:2567749",
      "tgn:1000001",
      "tgn:7012149",
      "tgn:2000492",
      "tgn:7007250",
      "tgn:7029392"
    ],
    "placetype": [
      "aat:300008706"
    ],
    "id": 2567749,
    "name:xx": "Paradise Creek"
  }
}
