{
  "geometry": {
    "type": "Point",
    "coordinates": [
      -91.75,
      31.55
    ]
  },
  "type": "Feature",
  "properties": {
    "hierarchy": [
      "tgn:2278184",
      "tgn:1000001",
      "tgn:2000868",
      "tgn:7012149",
      "tgn:7007256",
      "tgn:7029392"
    ],
    "placetype": [
      "aat:300008680"
    ],
    "id": 2278184,
    "name:xx": "De Armond Lake"
  }
}
