{
  "geometry": {
    "type": "Point",
    "coordinates": [
      -96.25,
      32.6167
    ]
  },
  "type": "Feature",
  "properties": {
    "hierarchy": [
      "tgn:2431843",
      "tgn:1000001",
      "tgn:7012149",
      "tgn:1002535",
      "tgn:7007826",
      "tgn:7029392"
    ],
    "placetype": [
      "aat:300008699"
    ],
    "id": 2431843,
    "name:xx": "Kaufman Branch"
  }
}
