{
  "geometry": {
    "type": "Point",
    "coordinates": [
      -85.9167,
      35.1667
    ]
  },
  "type": "Feature",
  "properties": {
    "hierarchy": [
      "tgn:2470852",
      "tgn:1000001",
      "tgn:7012149",
      "tgn:2001862",
      "tgn:7007825",
      "tgn:7029392"
    ],
    "placetype": [
      "aat:300008761"
    ],
    "id": 2470852,
    "name:xx": "Lost Cove"
  }
}
