{
  "type": "FeatureCollection",
  "features": [
    {
      "geometry": {
        "type": "Point",
        "coordinates": [
          26.533,
          47.533
        ]
      },
      "type": "Feature",
      "properties": {
        "hierarchy": [
          "tgn:1130360",
          "tgn:1000003",
          "tgn:1000091",
          "tgn:7029392"
        ],
        "placetype": [
          "aat:300008707"
        ],
        "id": 1130360,
        "name:xx": "Suchava"
      }
    },
    {
      "geometry": {
        "type": "Point",
        "coordinates": [
          -93.016667,
          16.6
        ]
      },
      "type": "Feature",
      "properties": {
        "hierarchy": [
          "tgn:1130362",
          "tgn:7005580",
          "tgn:1000001",
          "tgn:7005560",
          "tgn:7029392"
        ],
        "placetype": [
          "aat:300008707",
          "aat:300008699"
        ],
        "id": 1130362,
        "name:xx": "Suchiapa"
      }
    },
    {
      "geometry": {
        "type": "Point",
        "coordinates": [
          38.4167,
          47.2667
        ]
      },
      "type": "Feature",
      "properties": {
        "hierarchy": [
          "tgn:1130364",
          "tgn:1000003",
          "tgn:7029392"
        ],
        "placetype": [
          "aat:300008707"
        ],
        "id": 1130364,
        "name:xx": "Suchoj Jelančik"
      }
    },
    {
      "geometry": {
        "type": "Point",
        "coordinates": [
          -89.2833,
          14.0333
        ]
      },
      "type": "Feature",
      "properties": {
        "hierarchy": [
          "tgn:1130368",
          "tgn:1000001",
          "tgn:7005441",
          "tgn:7029392"
        ],
        "placetype": [
          "aat:300008707"
        ],
        "id": 1130368,
        "name:xx": "Sucio, Río"
      }
    },
    {
      "geometry": {
        "type": "Point",
        "coordinates": [
          -77.116,
          7.445
        ]
      },
      "type": "Feature",
      "properties": {
        "hierarchy": [
          "tgn:1130369",
          "tgn:1000050",
          "tgn:1000002",
          "tgn:7029392"
        ],
        "placetype": [
          "aat:300008707"
        ],
        "id": 1130369,
        "name:xx": "Sucio, Río"
      }
    }
  ]
}
