{
  "geometry": {
    "type": "Point",
    "coordinates": [
      -81.0833,
      27.3667
    ]
  },
  "type": "Feature",
  "properties": {
    "hierarchy": [
      "tgn:2018995",
      "tgn:1000001",
      "tgn:1002477",
      "tgn:7012149",
      "tgn:7007240",
      "tgn:7029392"
    ],
    "placetype": [
      "aat:300008347",
      "aat:300387210"
    ],
    "id": 2018995,
    "name:xx": "Cornwell"
  }
}
