{
  "geometry": {
    "type": "Point",
    "coordinates": [
      -95.65,
      32.1667
    ]
  },
  "type": "Feature",
  "properties": {
    "hierarchy": [
      "tgn:2185131",
      "tgn:1000001",
      "tgn:7012149",
      "tgn:1002464",
      "tgn:7007826",
      "tgn:7029392"
    ],
    "placetype": [
      "aat:300008699"
    ],
    "id": 2185131,
    "name:xx": "Boggy Branch"
  }
}
