{
  "type": "FeatureCollection",
  "features": [
    {
      "geometry": {
        "type": "Point",
        "coordinates": [
          102.0333,
          35.9333
        ]
      },
      "type": "Feature",
      "properties": {
        "hierarchy": [
          "tgn:1069090",
          "tgn:1000004",
          "tgn:7002088",
          "tgn:1000111",
          "tgn:7029392"
        ],
        "placetype": [
          "aat:300008347"
        ],
        "id": 1069090,
        "name:xx": "Magitang"
      }
    },
    {
      "geometry": {
        "type": "Point",
        "coordinates": [
          122.9,
          46.7333
        ]
      },
      "type": "Feature",
      "properties": {
        "hierarchy": [
          "tgn:1069091",
          "tgn:1000004",
          "tgn:7001838",
          "tgn:1000111",
          "tgn:7029392"
        ],
        "placetype": [
          "aat:300008347"
        ],
        "id": 1069091,
        "name:xx": "Jalaid Qi"
      }
    },
    {
      "geometry": {
        "type": "Point",
        "coordinates": [
          122.9,
          43.1
        ]
      },
      "type": "Feature",
      "properties": {
        "hierarchy": [
          "tgn:1069092",
          "tgn:1000004",
          "tgn:7001838",
          "tgn:1000111",
          "tgn:7029392"
        ],
        "placetype": [
          "aat:300008347"
        ],
        "id": 1069092,
        "name:xx": "Jargalang"
      }
    },
    {
      "geometry": {
        "type": "Point",
        "coordinates": [
          121,
          44.6
        ]
      },
      "type": "Feature",
      "properties": {
        "hierarchy": [
          "tgn:1069093",
          "tgn:1000004",
          "tgn:7001838",
          "tgn:1000111",
          "tgn:7029392"
        ],
        "placetype": [
          "aat:300008347"
        ],
        "id": 1069093,
        "name:xx": "Jarud Qi"
      }
    },
    {
      "geometry": {
        "type": "Point",
        "coordinates": [
          85.6667,
          47.5
        ]
      },
      "type": "Feature",
      "properties": {
        "hierarchy": [
          "tgn:1069094",
          "tgn:1000004",
          "tgn:7001745",
          "tgn:1000111",
          "tgn:7029392"
        ],
        "placetype": [
          "aat:300008347"
        ],
        "id": 1069094,
        "name:xx": "Jeminary"
      }
    },
    {
      "geometry": {
        "type": "Point",
        "coordinates": [
          115,
          27.1333
        ]
      },
      "type": "Feature",
      "properties": {
        "hierarchy": [
          "tgn:1069095",
          "tgn:1000004",
          "tgn:7002082",
          "tgn:1000111",
          "tgn:7029392"
        ],
        "placetype": [
          "aat:300008347"
        ],
        "id": 1069095,
        "name:xx": "Ji'an"
      }
    },
    {
      "geometry": {
        "type": "Point",
        "coordinates": [
          106.0333,
          30.5167
        ]
      },
      "type": "Feature",
      "properties": {
        "hierarchy": [
          "tgn:1069096",
          "tgn:1000004",
          "tgn:7002087",
          "tgn:1000111",
          "tgn:7029392"
        ],
        "placetype": [
          "aat:300008347"
        ],
        "id": 1069096,
        "name:xx": "Ji'anchang"
      }
    },
    {
      "geometry": {
        "type": "Point",
        "coordinates": [
          107.05,
          25.1667
        ]
      },
      "type": "Feature",
      "properties": {
        "hierarchy": [
          "tgn:1069097",
          "tgn:1000004",
          "tgn:1001678",
          "tgn:1000111",
          "tgn:7029392"
        ],
        "placetype": [
          "aat:300008347"
        ],
        "id": 1069097,
        "name:xx": "Jiaban"
      }
    },
    {
      "geometry": {
        "type": "Point",
        "coordinates": [
          92.7333,
          29.1833
        ]
      },
      "type": "Feature",
      "properties": {
        "hierarchy": [
          "tgn:1069098",
          "tgn:1000004",
          "tgn:7001319",
          "tgn:1000111",
          "tgn:7029392"
        ],
        "placetype": [
          "aat:300008347"
        ],
        "id": 1069098,
        "name:xx": "Jiacha"
      }
    },
    {
      "geometry": {
        "type": "Point",
        "coordinates": [
          121.25,
          31.4
        ]
      },
      "type": "Feature",
      "properties": {
        "hierarchy": [
          "tgn:1069099",
          "tgn:1000004",
          "tgn:1000958",
          "tgn:1000111",
          "tgn:7029392"
        ],
        "placetype": [
          "aat:300008347"
        ],
        "id": 1069099,
        "name:xx": "Jiading"
      }
    }
  ]
}
