{
  "geometry": {
    "type": "Point",
    "coordinates": [
      -108.6667,
      46.9333
    ]
  },
  "type": "Feature",
  "properties": {
    "hierarchy": [
      "tgn:2511907",
      "tgn:1000001",
      "tgn:7012149",
      "tgn:2001273",
      "tgn:7007524",
      "tgn:7029392"
    ],
    "placetype": [
      "aat:300008697"
    ],
    "id": 2511907,
    "name:xx": "Milk Springs"
  }
}
