{
  "geometry": {
    "type": "Point",
    "coordinates": [
      48.7333,
      53.3167
    ]
  },
  "type": "Feature",
  "properties": {
    "hierarchy": [
      "tgn:1054206",
      "tgn:1000004",
      "tgn:1003407",
      "tgn:7018214",
      "tgn:7002435",
      "tgn:7029392"
    ],
    "placetype": [
      "aat:300008347"
    ],
    "id": 1054206,
    "name:xx": "Gubino"
  }
}
