{
  "geometry": {
    "type": "Point",
    "coordinates": [
      -80.5667,
      39.7833
    ]
  },
  "type": "Feature",
  "properties": {
    "hierarchy": [
      "tgn:2229678",
      "tgn:1000001",
      "tgn:7012149",
      "tgn:2002276",
      "tgn:7013961",
      "tgn:7029392"
    ],
    "placetype": [
      "aat:300008699"
    ],
    "id": 2229678,
    "name:xx": "Cedar Run"
  }
}
