{
  "geometry": {
    "type": "Point",
    "coordinates": [
      -114.8667,
      44.6167
    ]
  },
  "type": "Feature",
  "properties": {
    "hierarchy": [
      "tgn:2506080",
      "tgn:1000001",
      "tgn:2000470",
      "tgn:7012149",
      "tgn:7007250",
      "tgn:7029392"
    ],
    "placetype": [
      "aat:300008706"
    ],
    "id": 2506080,
    "name:xx": "Merino Creek"
  }
}
