{
  "type": "FeatureCollection",
  "features": [
    {
      "geometry": {
        "type": "Point",
        "coordinates": [
          -69.9833,
          44.5667
        ]
      },
      "type": "Feature",
      "properties": {
        "hierarchy": [
          "tgn:2404270",
          "tgn:1000001",
          "tgn:2000923",
          "tgn:7012149",
          "tgn:7007515",
          "tgn:7029392"
        ],
        "placetype": [
          "aat:300008798"
        ],
        "id": 2404270,
        "name:xx": "Hoyt Hill"
      }
    },
    {
      "geometry": {
        "type": "Point",
        "coordinates": [
          -71.2,
          42.9167
        ]
      },
      "type": "Feature",
      "properties": {
        "hierarchy": [
          "tgn:2404271",
          "tgn:1000001",
          "tgn:7014352",
          "tgn:7012149",
          "tgn:7007564",
          "tgn:7029392"
        ],
        "placetype": [
          "aat:300008798"
        ],
        "id": 2404271,
        "name:xx": "Hoyt Hill"
      }
    },
    {
      "geometry": {
        "type": "Point",
        "coordinates": [
          -72.0333,
          43.4833
        ]
      },
      "type": "Feature",
      "properties": {
        "hierarchy": [
          "tgn:2404272",
          "tgn:1000001",
          "tgn:2001427",
          "tgn:7012149",
          "tgn:7007564",
          "tgn:7029392"
        ],
        "placetype": [
          "aat:300008798"
        ],
        "id": 2404272,
        "name:xx": "Hoyt Hill"
      }
    },
    {
      "geometry": {
        "type": "Point",
        "coordinates": [
          -71.9333,
          43.6333
        ]
      },
      "type": "Feature",
      "properties": {
        "hierarchy": [
          "tgn:2404273",
          "tgn:1000001",
          "tgn:2001424",
          "tgn:7012149",
          "tgn:7007564",
          "tgn:7029392"
        ],
        "placetype": [
          "aat:300008798"
        ],
        "id": 2404273,
        "name:xx": "Hoyt Hill"
      }
    },
    {
      "geometry": {
        "type": "Point",
        "coordinates": [
          -74.25,
          42.0833
        ]
      },
      "type": "Feature",
      "properties": {
        "hierarchy": [
          "tgn:2404274",
          "tgn:1000001",
          "tgn:7012149",
          "tgn:1002961",
          "tgn:7007568",
          "tgn:7029392"
        ],
        "placetype": [
          "aat:300008761"
        ],
        "id": 2404274,
        "name:xx": "Hoyt Hollow"
      }
    },
    {
      "geometry": {
        "type": "Point",
        "coordinates": [
          -77.3833,
          41.5167
        ]
      },
      "type": "Feature",
      "properties": {
        "hierarchy": [
          "tgn:2404275",
          "tgn:1000001",
          "tgn:7012149",
          "tgn:1002613",
          "tgn:7007710",
          "tgn:7029392"
        ],
        "placetype": [
          "aat:300008761"
        ],
        "id": 2404275,
        "name:xx": "Hoyt Hollow"
      }
    },
    {
      "geometry": {
        "type": "Point",
        "coordinates": [
          -73.4167,
          41.0667
        ]
      },
      "type": "Feature",
      "properties": {
        "hierarchy": [
          "tgn:2404276",
          "tgn:1002366",
          "tgn:1000001",
          "tgn:7012149",
          "tgn:7007159",
          "tgn:7029392"
        ],
        "placetype": [
          "aat:300008791"
        ],
        "id": 2404276,
        "name:xx": "Hoyt Island"
      }
    },
    {
      "geometry": {
        "type": "Point",
        "coordinates": [
          -69.8667,
          44.55
        ]
      },
      "type": "Feature",
      "properties": {
        "hierarchy": [
          "tgn:2404277",
          "tgn:1000001",
          "tgn:2000923",
          "tgn:7012149",
          "tgn:7007515",
          "tgn:7029392"
        ],
        "placetype": [
          "aat:300008791"
        ],
        "id": 2404277,
        "name:xx": "Hoyt Island"
      }
    },
    {
      "geometry": {
        "type": "Point",
        "coordinates": [
          -92.4333,
          47.9
        ]
      },
      "type": "Feature",
      "properties": {
        "hierarchy": [
          "tgn:2404278",
          "tgn:1000001",
          "tgn:7012149",
          "tgn:2001067",
          "tgn:7007521",
          "tgn:7029392"
        ],
        "placetype": [
          "aat:300008791"
        ],
        "id": 2404278,
        "name:xx": "Hoyt Island"
      }
    },
    {
      "geometry": {
        "type": "Point",
        "coordinates": [
          -85.8167,
          43.55
        ]
      },
      "type": "Feature",
      "properties": {
        "hierarchy": [
          "tgn:2404279",
          "tgn:1000001",
          "tgn:7012149",
          "tgn:2000984",
          "tgn:7007520",
          "tgn:7029392"
        ],
        "placetype": [
          "aat:300008680"
        ],
        "id": 2404279,
        "name:xx": "Hoyt Lake"
      }
    }
  ]
}
