{
  "geometry": {
    "type": "Point",
    "coordinates": [
      -120.2667,
      38.0833
    ]
  },
  "type": "Feature",
  "properties": {
    "hierarchy": [
      "tgn:2434169",
      "tgn:1000001",
      "tgn:7012149",
      "tgn:7007157",
      "tgn:1002957",
      "tgn:7029392"
    ],
    "placetype": [
      "aat:300000390"
    ],
    "id": 2434169,
    "name:xx": "Keltz Mine"
  }
}
