{
  "geometry": {
    "type": "Point",
    "coordinates": [
      -89.8833,
      38.8833
    ]
  },
  "type": "Feature",
  "properties": {
    "hierarchy": [
      "tgn:2026879",
      "tgn:1000001",
      "tgn:7012149",
      "tgn:1002622",
      "tgn:7007251",
      "tgn:7029392"
    ],
    "placetype": [
      "aat:300008347"
    ],
    "id": 2026879,
    "name:xx": "Carpenter"
  }
}
