{
  "geometry": {
    "type": "Point",
    "coordinates": [
      -97.4167,
      33.3833
    ]
  },
  "type": "Feature",
  "properties": {
    "hierarchy": [
      "tgn:2548782",
      "tgn:1000001",
      "tgn:7012149",
      "tgn:1003031",
      "tgn:7007826",
      "tgn:7029392"
    ],
    "placetype": [
      "aat:300008706"
    ],
    "id": 2548782,
    "name:xx": "North Pecan Creek"
  }
}
