{
  "geometry": {
    "type": "Point",
    "coordinates": [
      -100.15,
      45.1667
    ]
  },
  "type": "Feature",
  "properties": {
    "hierarchy": [
      "tgn:2692466",
      "tgn:1000001",
      "tgn:7012149",
      "tgn:2001823",
      "tgn:7007713",
      "tgn:7029392"
    ],
    "placetype": [
      "aat:300008706"
    ],
    "id": 2692466,
    "name:xx": "Steamboat Creek"
  }
}
