{
  "geometry": {
    "type": "Point",
    "coordinates": [
      -93.4833,
      41.0167
    ]
  },
  "type": "Feature",
  "properties": {
    "hierarchy": [
      "tgn:2693640",
      "tgn:1000001",
      "tgn:7012149",
      "tgn:2000619",
      "tgn:7007253",
      "tgn:7029392"
    ],
    "placetype": [
      "aat:300006191"
    ],
    "id": 2693640,
    "name:xx": "Stephens Forest Pond"
  }
}
