{
  "geometry": {
    "type": "Point",
    "coordinates": [
      14.5167,
      35.9167
    ]
  },
  "type": "Feature",
  "properties": {
    "hierarchy": [
      "tgn:7005746",
      "tgn:1000003",
      "tgn:7594236",
      "tgn:7005729",
      "tgn:7029392"
    ],
    "placetype": [
      "aat:300008347"
    ],
    "id": 7005746,
    "name:xx": "Sliema"
  }
}
