{
  "geometry": {
    "type": "Point",
    "coordinates": [
      -111.5833,
      32.2667
    ]
  },
  "type": "Feature",
  "properties": {
    "hierarchy": [
      "tgn:2126982",
      "tgn:1000001",
      "tgn:7006451",
      "tgn:7012149",
      "tgn:7029392"
    ],
    "placetype": [
      "aat:300008761"
    ],
    "id": 2126982,
    "name:xx": "Aguirre Valley"
  }
}
