{
  "geometry": {
    "type": "Point",
    "coordinates": [
      -99.7833,
      48.9167
    ]
  },
  "type": "Feature",
  "properties": {
    "hierarchy": [
      "tgn:2763901",
      "tgn:1000001",
      "tgn:2001596",
      "tgn:7012149",
      "tgn:7007705",
      "tgn:7029392"
    ],
    "placetype": [
      "aat:300008680"
    ],
    "id": 2763901,
    "name:xx": "Wheaton Lake"
  }
}
