{
  "geometry": {
    "type": "Point",
    "coordinates": [
      -120.9167,
      48.3333
    ]
  },
  "type": "Feature",
  "properties": {
    "hierarchy": [
      "tgn:2126758",
      "tgn:1000001",
      "tgn:1002260",
      "tgn:7012149",
      "tgn:7007920",
      "tgn:7029392"
    ],
    "placetype": [
      "aat:300008706"
    ],
    "id": 2126758,
    "name:xx": "Agnes Creek"
  }
}
