{
  "geometry": {
    "type": "Point",
    "coordinates": [
      30.5908,
      31.312692
    ]
  },
  "type": "Feature",
  "properties": {
    "hierarchy": [
      "tgn:7530532",
      "tgn:7001242",
      "tgn:7016833",
      "tgn:1001335",
      "tgn:7029392"
    ],
    "placetype": [
      "aat:300006075"
    ],
    "name:en": "Baḩr al Qaşşābī",
    "id": 7530532
  }
}
