{
  "geometry": {
    "type": "Point",
    "coordinates": [
      -109.1833,
      44.2167
    ]
  },
  "type": "Feature",
  "properties": {
    "hierarchy": [
      "tgn:2578424",
      "tgn:1000001",
      "tgn:7012149",
      "tgn:2002379",
      "tgn:7007923",
      "tgn:7029392"
    ],
    "placetype": [
      "aat:300006191"
    ],
    "id": 2578424,
    "name:xx": "Phelps Enlargement Thomas Reservoir"
  }
}
