{
  "geometry": {
    "type": "Point",
    "coordinates": [
      -82.9833,
      37.9833
    ]
  },
  "type": "Feature",
  "properties": {
    "hierarchy": [
      "tgn:2041603",
      "tgn:1000001",
      "tgn:7012149",
      "tgn:2000809",
      "tgn:7007255",
      "tgn:7029392"
    ],
    "placetype": [
      "aat:300008347",
      "aat:300387210"
    ],
    "id": 2041603,
    "name:xx": "Terryville"
  }
}
