{
  "geometry": {
    "type": "Point",
    "coordinates": [
      -105.3833,
      40.1167
    ]
  },
  "type": "Feature",
  "properties": {
    "hierarchy": [
      "tgn:2593733",
      "tgn:1000001",
      "tgn:2000198",
      "tgn:7012149",
      "tgn:7007158",
      "tgn:7029392"
    ],
    "placetype": [
      "aat:300008761"
    ],
    "id": 2593733,
    "name:xx": "Porphyry Gulch"
  }
}
