{
  "geometry": {
    "type": "Point",
    "coordinates": [
      -96.0667,
      29.4667
    ]
  },
  "type": "Feature",
  "properties": {
    "hierarchy": [
      "tgn:2192793",
      "tgn:1000001",
      "tgn:7012149",
      "tgn:1003019",
      "tgn:7007826",
      "tgn:7029392"
    ],
    "placetype": [
      "aat:300008699"
    ],
    "id": 2192793,
    "name:xx": "Bratcher Slough"
  }
}
