{
  "type": "FeatureCollection",
  "features": [
    {
      "geometry": {
        "type": "Point",
        "coordinates": [
          -68.7167,
          44.3167
        ]
      },
      "type": "Feature",
      "properties": {
        "hierarchy": [
          "tgn:2362280",
          "tgn:1000001",
          "tgn:2000922",
          "tgn:7012149",
          "tgn:7007515",
          "tgn:7029392"
        ],
        "placetype": [
          "aat:300008850"
        ],
        "id": 2362280,
        "name:xx": "Grays Point"
      }
    },
    {
      "geometry": {
        "type": "Point",
        "coordinates": [
          -75.1333,
          38.2667
        ]
      },
      "type": "Feature",
      "properties": {
        "hierarchy": [
          "tgn:2362281",
          "tgn:1000001",
          "tgn:1003037",
          "tgn:7012149",
          "tgn:7007516",
          "tgn:7029392"
        ],
        "placetype": [
          "aat:300008850"
        ],
        "id": 2362281,
        "name:xx": "Grays Point"
      }
    },
    {
      "geometry": {
        "type": "Point",
        "coordinates": [
          -76.4667,
          39.0667
        ]
      },
      "type": "Feature",
      "properties": {
        "hierarchy": [
          "tgn:2362282",
          "tgn:7014651",
          "tgn:1000001",
          "tgn:7012149",
          "tgn:7007516",
          "tgn:7029392"
        ],
        "placetype": [
          "aat:300008850"
        ],
        "id": 2362282,
        "name:xx": "Grays Point"
      }
    },
    {
      "geometry": {
        "type": "Point",
        "coordinates": [
          -89.4667,
          37.2333
        ]
      },
      "type": "Feature",
      "properties": {
        "hierarchy": [
          "tgn:2362283",
          "tgn:1000001",
          "tgn:7012149",
          "tgn:2001246",
          "tgn:7007523",
          "tgn:7029392"
        ],
        "placetype": [
          "aat:300008850"
        ],
        "id": 2362283,
        "name:xx": "Grays Point"
      }
    },
    {
      "geometry": {
        "type": "Point",
        "coordinates": [
          -73.9667,
          44.3333
        ]
      },
      "type": "Feature",
      "properties": {
        "hierarchy": [
          "tgn:2362284",
          "tgn:1000001",
          "tgn:7012149",
          "tgn:2001461",
          "tgn:7007568",
          "tgn:7029392"
        ],
        "placetype": [
          "aat:300008850"
        ],
        "id": 2362284,
        "name:xx": "Grays Point"
      }
    },
    {
      "geometry": {
        "type": "Point",
        "coordinates": [
          -78.3333,
          34.4167
        ]
      },
      "type": "Feature",
      "properties": {
        "hierarchy": [
          "tgn:2362285",
          "tgn:1000001",
          "tgn:2001471",
          "tgn:7012149",
          "tgn:7007709",
          "tgn:7029392"
        ],
        "placetype": [
          "aat:300008850"
        ],
        "id": 2362285,
        "name:xx": "Grays Point"
      }
    },
    {
      "geometry": {
        "type": "Point",
        "coordinates": [
          -85.1667,
          35.15
        ]
      },
      "type": "Feature",
      "properties": {
        "hierarchy": [
          "tgn:2362286",
          "tgn:1000001",
          "tgn:7012149",
          "tgn:2001869",
          "tgn:7007825",
          "tgn:7029392"
        ],
        "placetype": [
          "aat:300008850"
        ],
        "id": 2362286,
        "name:xx": "Grays Point"
      }
    },
    {
      "geometry": {
        "type": "Point",
        "coordinates": [
          -123.7667,
          46.2667
        ]
      },
      "type": "Feature",
      "properties": {
        "hierarchy": [
          "tgn:2362287",
          "tgn:1000001",
          "tgn:7012149",
          "tgn:1002767",
          "tgn:7007920",
          "tgn:7029392"
        ],
        "placetype": [
          "aat:300008850"
        ],
        "id": 2362287,
        "name:xx": "Grays Point"
      }
    },
    {
      "geometry": {
        "type": "Point",
        "coordinates": [
          -73.6167,
          41.1333
        ]
      },
      "type": "Feature",
      "properties": {
        "hierarchy": [
          "tgn:2362288",
          "tgn:1002366",
          "tgn:1000001",
          "tgn:7012149",
          "tgn:7007159",
          "tgn:7029392"
        ],
        "placetype": [
          "aat:300006191"
        ],
        "id": 2362288,
        "name:xx": "Grays Pond"
      }
    },
    {
      "geometry": {
        "type": "Point",
        "coordinates": [
          -87.5167,
          38.8667
        ]
      },
      "type": "Feature",
      "properties": {
        "hierarchy": [
          "tgn:2362289",
          "tgn:1000001",
          "tgn:7012149",
          "tgn:2000545",
          "tgn:7007252",
          "tgn:7029392"
        ],
        "placetype": [
          "aat:300008680"
        ],
        "id": 2362289,
        "name:xx": "Grays Pond"
      }
    }
  ]
}
