{
  "geometry": {
    "type": "Point",
    "coordinates": [
      68.25,
      38.3333
    ]
  },
  "type": "Feature",
  "properties": {
    "hierarchy": [
      "tgn:1109872",
      "tgn:1000004",
      "tgn:7029392"
    ],
    "placetype": [
      "aat:300386831"
    ],
    "id": 1109872,
    "name:xx": "Babatag, Khrebet"
  }
}
