{
  "geometry": {
    "type": "Point",
    "coordinates": [
      -94.1833,
      40.5167
    ]
  },
  "type": "Feature",
  "properties": {
    "hierarchy": [
      "tgn:2759086",
      "tgn:1000001",
      "tgn:7012149",
      "tgn:2001201",
      "tgn:7007523",
      "tgn:7029392"
    ],
    "placetype": [
      "aat:300008706"
    ],
    "id": 2759086,
    "name:xx": "West Fork Big Muddy Creek"
  }
}
