{
  "geometry": {
    "type": "Point",
    "coordinates": [
      -122.6833,
      48.2167
    ]
  },
  "type": "Feature",
  "properties": {
    "hierarchy": [
      "tgn:1113603",
      "tgn:1000001",
      "tgn:7012149",
      "tgn:1002505",
      "tgn:7007920",
      "tgn:7029392"
    ],
    "placetype": [
      "aat:300132316"
    ],
    "id": 1113603,
    "name:xx": "Penn Cove"
  }
}
