{
  "geometry": {
    "type": "Point",
    "coordinates": [
      -58.7667,
      -33.7167
    ]
  },
  "type": "Feature",
  "properties": {
    "hierarchy": [
      "tgn:1133761",
      "tgn:7006477",
      "tgn:1001237",
      "tgn:1000002",
      "tgn:7029392"
    ],
    "placetype": [
      "aat:300008706"
    ],
    "id": 1133761,
    "name:xx": "Malambo, Arroyo"
  }
}
