{
  "geometry": {
    "type": "Point",
    "coordinates": [
      -71.2667,
      41.5167
    ]
  },
  "type": "Feature",
  "properties": {
    "hierarchy": [
      "tgn:2488716",
      "tgn:1002996",
      "tgn:1000001",
      "tgn:7012149",
      "tgn:7007711",
      "tgn:7029392"
    ],
    "placetype": [
      "aat:300008707"
    ],
    "id": 2488716,
    "name:xx": "Maidford River"
  }
}
