{
  "geometry": {
    "type": "Point",
    "coordinates": [
      -114.45,
      39.3333
    ]
  },
  "type": "Feature",
  "properties": {
    "hierarchy": [
      "tgn:2709688",
      "tgn:1000001",
      "tgn:7012149",
      "tgn:2001420",
      "tgn:7007526",
      "tgn:7029392"
    ],
    "placetype": [
      "aat:300008680"
    ],
    "id": 2709688,
    "name:xx": "Taft Lake"
  }
}
