{
  "geometry": {
    "type": "Point",
    "coordinates": [
      -120.8167,
      39.45
    ]
  },
  "type": "Feature",
  "properties": {
    "hierarchy": [
      "tgn:2416990",
      "tgn:1000001",
      "tgn:7012149",
      "tgn:7007157",
      "tgn:7029392"
    ],
    "placetype": [
      "aat:300008761"
    ],
    "id": 2416990,
    "name:xx": "Jackass Ravine"
  }
}
