{
  "geometry": {
    "type": "Point",
    "coordinates": [
      120.472222,
      23.3575
    ]
  },
  "type": "Feature",
  "properties": {
    "hierarchy": [
      "tgn:7487131",
      "tgn:1000004",
      "tgn:7490934",
      "tgn:1000141",
      "tgn:7029392"
    ],
    "placetype": [
      "aat:300008699"
    ],
    "id": 7487131,
    "name:xx": "Baishui Xi"
  }
}
