{
  "geometry": {
    "type": "Point",
    "coordinates": [
      -85.8167,
      37.9667
    ]
  },
  "type": "Feature",
  "properties": {
    "hierarchy": [
      "tgn:2229515",
      "tgn:1000001",
      "tgn:2000774",
      "tgn:7012149",
      "tgn:7007255",
      "tgn:7029392"
    ],
    "placetype": [
      "aat:300008699"
    ],
    "id": 2229515,
    "name:xx": "Cedar Point Branch"
  }
}
