{
  "geometry": {
    "type": "Point",
    "coordinates": [
      -85.05,
      40.6333
    ]
  },
  "type": "Feature",
  "properties": {
    "hierarchy": [
      "tgn:2616456",
      "tgn:1002135",
      "tgn:1000001",
      "tgn:7012149",
      "tgn:7007252",
      "tgn:7029392"
    ],
    "placetype": [
      "aat:300006075"
    ],
    "id": 2616456,
    "name:xx": "Rice Ditch"
  }
}
