{
  "geometry": {
    "type": "Point",
    "coordinates": [
      31.275352,
      30.072222
    ]
  },
  "type": "Feature",
  "properties": {
    "hierarchy": [
      "tgn:7526773",
      "tgn:7001242",
      "tgn:7016833",
      "tgn:1001091",
      "tgn:7029392"
    ],
    "placetype": [
      "aat:300007466"
    ],
    "id": 7526773,
    "name:xx": "Al Kanīsah al Marqaşīyah"
  }
}
