{
  "geometry": {
    "type": "Point",
    "coordinates": [
      -76.0833,
      -9.7667
    ]
  },
  "type": "Feature",
  "properties": {
    "hierarchy": [
      "tgn:1024349",
      "tgn:1000637",
      "tgn:1000002",
      "tgn:1000056",
      "tgn:7029392"
    ],
    "placetype": [
      "aat:300008347"
    ],
    "id": 1024349,
    "name:xx": "Acomayo"
  }
}
