{
  "geometry": {
    "type": "Point",
    "coordinates": [
      -74.4167,
      39.3667
    ]
  },
  "type": "Feature",
  "properties": {
    "hierarchy": [
      "tgn:2283496",
      "tgn:1002157",
      "tgn:1000001",
      "tgn:7012149",
      "tgn:7007565",
      "tgn:7029392"
    ],
    "placetype": [
      "aat:300008678"
    ],
    "id": 2283496,
    "name:xx": "Delta Basin"
  }
}
