{
  "geometry": {
    "type": "Point",
    "coordinates": [
      120.2444,
      23.3613
    ]
  },
  "type": "Feature",
  "properties": {
    "hierarchy": [
      "tgn:7471237",
      "tgn:7468018",
      "tgn:1000004",
      "tgn:1000141",
      "tgn:7029392"
    ],
    "placetype": [
      "aat:300008347"
    ],
    "id": 7471237,
    "name:xx": "Xinzhuang"
  }
}
