{
  "geometry": {
    "type": "Point",
    "coordinates": [
      -79.2167,
      35.45
    ]
  },
  "type": "Feature",
  "properties": {
    "hierarchy": [
      "tgn:2570903",
      "tgn:1000001",
      "tgn:7012149",
      "tgn:7007709",
      "tgn:7029392"
    ],
    "placetype": [
      "aat:300008706"
    ],
    "id": 2570903,
    "name:xx": "Patterson Creek"
  }
}
