{
  "type": "FeatureCollection",
  "features": [
    {
      "geometry": {
        "type": "Point",
        "coordinates": [
          -82.45,
          34.6333
        ]
      },
      "type": "Feature",
      "properties": {
        "hierarchy": [
          "tgn:2096450",
          "tgn:2001728",
          "tgn:1000001",
          "tgn:7012149",
          "tgn:7007712",
          "tgn:7029392"
        ],
        "placetype": [
          "aat:300008347"
        ],
        "id": 2096450,
        "name:xx": "Pelzer"
      }
    },
    {
      "geometry": {
        "type": "Point",
        "coordinates": [
          -79.85,
          34.0833
        ]
      },
      "type": "Feature",
      "properties": {
        "hierarchy": [
          "tgn:2096455",
          "tgn:1000001",
          "tgn:2001745",
          "tgn:7012149",
          "tgn:7007712",
          "tgn:7029392"
        ],
        "placetype": [
          "aat:300008347",
          "aat:300387210"
        ],
        "id": 2096455,
        "name:xx": "Peniel Crossroads"
      }
    },
    {
      "geometry": {
        "type": "Point",
        "coordinates": [
          -83.1167,
          34.65
        ]
      },
      "type": "Feature",
      "properties": {
        "hierarchy": [
          "tgn:2096459",
          "tgn:1000001",
          "tgn:7012149",
          "tgn:2001761",
          "tgn:7007712",
          "tgn:7029392"
        ],
        "placetype": [
          "aat:300008347",
          "aat:300387210"
        ],
        "id": 2096459,
        "name:xx": "Percival Crossroads"
      }
    }
  ]
}
