{
  "geometry": {
    "type": "Point",
    "coordinates": [
      -76.85,
      41.8833
    ]
  },
  "type": "Feature",
  "properties": {
    "hierarchy": [
      "tgn:2779925",
      "tgn:1000001",
      "tgn:1002194",
      "tgn:7012149",
      "tgn:7007710",
      "tgn:7029392"
    ],
    "placetype": [
      "aat:300008761"
    ],
    "id": 2779925,
    "name:xx": "Wolfe Hollow"
  }
}
