{
  "geometry": {
    "type": "Point",
    "coordinates": [
      -2.15,
      37.55
    ]
  },
  "type": "Feature",
  "properties": {
    "hierarchy": [
      "tgn:7322776",
      "tgn:7002805",
      "tgn:7002758",
      "tgn:1000003",
      "tgn:1000095",
      "tgn:7029392"
    ],
    "placetype": [
      "aat:300266640"
    ],
    "id": 7322776,
    "name:xx": "Saliente, Sierra del"
  }
}
