{
  "geometry": {
    "type": "Point",
    "coordinates": [
      -80.6667,
      24.8667
    ]
  },
  "type": "Feature",
  "properties": {
    "hierarchy": [
      "tgn:2411580",
      "tgn:1000001",
      "tgn:7012149",
      "tgn:1002676",
      "tgn:7007240",
      "tgn:7029392"
    ],
    "placetype": [
      "aat:300008791"
    ],
    "id": 2411580,
    "name:xx": "Indian Key"
  }
}
