{
  "geometry": {
    "type": "Point",
    "coordinates": [
      14.2333,
      53.8833
    ]
  },
  "type": "Feature",
  "properties": {
    "hierarchy": [
      "tgn:1048858",
      "tgn:1000003",
      "tgn:7024114",
      "tgn:7006366",
      "tgn:7029392"
    ],
    "placetype": [
      "aat:300008347",
      "aat:300000547",
      "aat:300008375",
      "aat:300120599"
    ],
    "id": 1048858,
    "name:xx": "Świnoujście"
  }
}
