{
  "type": "FeatureCollection",
  "features": [
    {
      "geometry": {
        "type": "Point",
        "coordinates": [
          -6.6,
          43.233333
        ]
      },
      "type": "Feature",
      "properties": {
        "hierarchy": [
          "tgn:7295460",
          "tgn:7008911",
          "tgn:1000003",
          "tgn:7002763",
          "tgn:1000095",
          "tgn:7029392"
        ],
        "placetype": [
          "aat:300008347"
        ],
        "id": 7295460,
        "name:xx": "Villaverde"
      }
    },
    {
      "geometry": {
        "type": "Point",
        "coordinates": [
          -3.55,
          43.183333
        ]
      },
      "type": "Feature",
      "properties": {
        "hierarchy": [
          "tgn:7295461",
          "tgn:7002760",
          "tgn:1000003",
          "tgn:1000095",
          "tgn:7029392"
        ],
        "placetype": [
          "aat:300008347"
        ],
        "id": 7295461,
        "name:xx": "Villaverde"
      }
    },
    {
      "geometry": {
        "type": "Point",
        "coordinates": [
          -4.683333,
          43.083333
        ]
      },
      "type": "Feature",
      "properties": {
        "hierarchy": [
          "tgn:7295462",
          "tgn:7002760",
          "tgn:1000003",
          "tgn:1000095",
          "tgn:7029392"
        ],
        "placetype": [
          "aat:300008347"
        ],
        "id": 7295462,
        "name:xx": "Villaverde"
      }
    },
    {
      "geometry": {
        "type": "Point",
        "coordinates": [
          -7,
          42.933333
        ]
      },
      "type": "Feature",
      "properties": {
        "hierarchy": [
          "tgn:7295463",
          "tgn:7002829",
          "tgn:1000003",
          "tgn:7002786",
          "tgn:1000095",
          "tgn:7029392"
        ],
        "placetype": [
          "aat:300008347"
        ],
        "id": 7295463,
        "name:xx": "Villaverde"
      }
    },
    {
      "geometry": {
        "type": "Point",
        "coordinates": [
          -6.083333,
          42.783333
        ]
      },
      "type": "Feature",
      "properties": {
        "hierarchy": [
          "tgn:7295464",
          "tgn:7002826",
          "tgn:7001158",
          "tgn:1000003",
          "tgn:1000095",
          "tgn:7029392"
        ],
        "placetype": [
          "aat:300008347"
        ],
        "id": 7295464,
        "name:xx": "Villaverde"
      }
    },
    {
      "geometry": {
        "type": "Point",
        "coordinates": [
          -2.567021,
          42.624372
        ]
      },
      "type": "Feature",
      "properties": {
        "hierarchy": [
          "tgn:7295465",
          "tgn:7007088",
          "tgn:1000003",
          "tgn:7009604",
          "tgn:1000095",
          "tgn:7029392"
        ],
        "placetype": [
          "aat:300008347"
        ],
        "id": 7295465,
        "name:xx": "Villaverde"
      }
    },
    {
      "geometry": {
        "type": "Point",
        "coordinates": [
          -3.7,
          40.35
        ]
      },
      "type": "Feature",
      "properties": {
        "hierarchy": [
          "tgn:7295466",
          "tgn:7010420",
          "tgn:1000003",
          "tgn:7002795",
          "tgn:1000095",
          "tgn:7029392"
        ],
        "placetype": [
          "aat:300008347"
        ],
        "id": 7295466,
        "name:xx": "Villaverde"
      }
    },
    {
      "geometry": {
        "type": "Point",
        "coordinates": [
          -2.366667,
          38.8
        ]
      },
      "type": "Feature",
      "properties": {
        "hierarchy": [
          "tgn:7295467",
          "tgn:7002803",
          "tgn:1001647",
          "tgn:1000003",
          "tgn:1000095",
          "tgn:7029392"
        ],
        "placetype": [
          "aat:300008347"
        ],
        "id": 7295467,
        "name:xx": "Villaverde"
      }
    },
    {
      "geometry": {
        "type": "Point",
        "coordinates": [
          -13.9,
          28.616667
        ]
      },
      "type": "Feature",
      "properties": {
        "hierarchy": [
          "tgn:7295468",
          "tgn:7002825",
          "tgn:7016622",
          "tgn:1000003",
          "tgn:1000095",
          "tgn:7029392"
        ],
        "placetype": [
          "aat:300008347"
        ],
        "id": 7295468,
        "name:xx": "Villaverde"
      }
    },
    {
      "geometry": {
        "type": "Point",
        "coordinates": [
          -6.966667,
          42.883333
        ]
      },
      "type": "Feature",
      "properties": {
        "hierarchy": [
          "tgn:7295469",
          "tgn:7002829",
          "tgn:1000003",
          "tgn:7002786",
          "tgn:1000095",
          "tgn:7029392"
        ],
        "placetype": [
          "aat:300008347"
        ],
        "id": 7295469,
        "name:xx": "Villaver"
      }
    }
  ]
}
