{
  "geometry": {
    "type": "Point",
    "coordinates": [
      35.983,
      41.75
    ]
  },
  "type": "Feature",
  "properties": {
    "hierarchy": [
      "tgn:6002441",
      "tgn:1000004",
      "tgn:1000144",
      "tgn:7029392"
    ],
    "placetype": [
      "aat:300000835",
      "aat:300008707"
    ],
    "id": 6002441,
    "name:xx": "Kızılırmak"
  }
}
