{
  "geometry": {
    "type": "Point",
    "coordinates": [
      -76.1167,
      35.35
    ]
  },
  "type": "Feature",
  "properties": {
    "hierarchy": [
      "tgn:2429442",
      "tgn:1000001",
      "tgn:7012149",
      "tgn:2001506",
      "tgn:7007709",
      "tgn:7029392"
    ],
    "placetype": [
      "aat:300008850"
    ],
    "id": 2429442,
    "name:xx": "Juniper Creek Point"
  }
}
