{
  "geometry": {
    "type": "Point",
    "coordinates": [
      -108.7167,
      36.9667
    ]
  },
  "type": "Feature",
  "properties": {
    "hierarchy": [
      "tgn:2331249",
      "tgn:1000001",
      "tgn:7012149",
      "tgn:2001452",
      "tgn:7007566",
      "tgn:7029392"
    ],
    "placetype": [
      "aat:300008798"
    ],
    "id": 2331249,
    "name:xx": "Flat Top Rock"
  }
}
