{
  "geometry": {
    "type": "Point",
    "coordinates": [
      -8.244,
      40.93
    ]
  },
  "type": "Feature",
  "properties": {
    "hierarchy": [
      "tgn:7031779",
      "tgn:7010608",
      "tgn:1000003",
      "tgn:1000090",
      "tgn:7029392"
    ],
    "placetype": [
      "aat:300008347",
      "aat:300387218"
    ],
    "id": 7031779,
    "name:xx": "Arouca"
  }
}
