{
  "geometry": {
    "type": "Point",
    "coordinates": [
      -82.7167,
      35.0833
    ]
  },
  "type": "Feature",
  "properties": {
    "hierarchy": [
      "tgn:2461552",
      "tgn:1000001",
      "tgn:2001747",
      "tgn:7012149",
      "tgn:7007712",
      "tgn:7029392"
    ],
    "placetype": [
      "aat:300008706"
    ],
    "id": 2461552,
    "name:xx": "Little Table Rock Creek"
  }
}
