{
  "type": "FeatureCollection",
  "features": [
    {
      "geometry": {
        "type": "Point",
        "coordinates": [
          -104.433333,
          19.483333
        ]
      },
      "type": "Feature",
      "properties": {
        "hierarchy": [
          "tgn:7354630",
          "tgn:7005586",
          "tgn:1000001",
          "tgn:7005560",
          "tgn:7029392"
        ],
        "placetype": [
          "aat:300008347"
        ],
        "id": 7354630,
        "name:xx": "Charco Azul"
      }
    },
    {
      "geometry": {
        "type": "Point",
        "coordinates": [
          -104.25,
          19.9
        ]
      },
      "type": "Feature",
      "properties": {
        "hierarchy": [
          "tgn:7354631",
          "tgn:7005586",
          "tgn:1000001",
          "tgn:7005560",
          "tgn:7029392"
        ],
        "placetype": [
          "aat:300008680"
        ],
        "id": 7354631,
        "name:xx": "Charco Azul"
      }
    },
    {
      "geometry": {
        "type": "Point",
        "coordinates": [
          -98.5,
          25.65
        ]
      },
      "type": "Feature",
      "properties": {
        "hierarchy": [
          "tgn:7354632",
          "tgn:1000001",
          "tgn:7005597",
          "tgn:7005560",
          "tgn:7029392"
        ],
        "placetype": [
          "aat:300008347"
        ],
        "id": 7354632,
        "name:xx": "Charco Añejo"
      }
    },
    {
      "geometry": {
        "type": "Point",
        "coordinates": [
          -97.883333,
          25.9
        ]
      },
      "type": "Feature",
      "properties": {
        "hierarchy": [
          "tgn:7354633",
          "tgn:1000001",
          "tgn:7005597",
          "tgn:7005560",
          "tgn:7029392"
        ],
        "placetype": [
          "aat:300008347"
        ],
        "id": 7354633,
        "name:xx": "Charco Anacuita"
      }
    },
    {
      "geometry": {
        "type": "Point",
        "coordinates": [
          -96.7,
          19.716667
        ]
      },
      "type": "Feature",
      "properties": {
        "hierarchy": [
          "tgn:7354634",
          "tgn:1000001",
          "tgn:7005599",
          "tgn:7005560",
          "tgn:7029392"
        ],
        "placetype": [
          "aat:300008795"
        ],
        "id": 7354634,
        "name:xx": "Charco, Cerro"
      }
    },
    {
      "geometry": {
        "type": "Point",
        "coordinates": [
          -106.183333,
          28.333333
        ]
      },
      "type": "Feature",
      "properties": {
        "hierarchy": [
          "tgn:7354635",
          "tgn:7005581",
          "tgn:1000001",
          "tgn:7005560",
          "tgn:7029392"
        ],
        "placetype": [
          "aat:300266554",
          "aat:300008699"
        ],
        "id": 7354635,
        "name:xx": "Charco, Arroyo del"
      }
    },
    {
      "geometry": {
        "type": "Point",
        "coordinates": [
          -106.2,
          28.2
        ]
      },
      "type": "Feature",
      "properties": {
        "hierarchy": [
          "tgn:7354636",
          "tgn:7005581",
          "tgn:1000001",
          "tgn:7005560",
          "tgn:7029392"
        ],
        "placetype": [
          "aat:300008699"
        ],
        "id": 7354636,
        "name:xx": "Charco, Arroyo del"
      }
    },
    {
      "geometry": {
        "type": "Point",
        "coordinates": [
          -101.35,
          27.65
        ]
      },
      "type": "Feature",
      "properties": {
        "hierarchy": [
          "tgn:7354637",
          "tgn:1001853",
          "tgn:1000001",
          "tgn:7005560",
          "tgn:7029392"
        ],
        "placetype": [
          "aat:300008347"
        ],
        "id": 7354637,
        "name:xx": "Charco"
      }
    },
    {
      "geometry": {
        "type": "Point",
        "coordinates": [
          -99.789167,
          24.946667
        ]
      },
      "type": "Feature",
      "properties": {
        "hierarchy": [
          "tgn:7354638",
          "tgn:1000001",
          "tgn:7005589",
          "tgn:7005560",
          "tgn:7029392"
        ],
        "placetype": [
          "aat:300008347"
        ],
        "id": 7354638,
        "name:xx": "Charco"
      }
    },
    {
      "geometry": {
        "type": "Point",
        "coordinates": [
          -101.216667,
          23.1
        ]
      },
      "type": "Feature",
      "properties": {
        "hierarchy": [
          "tgn:7354639",
          "tgn:1000001",
          "tgn:7005594",
          "tgn:7005560",
          "tgn:7029392"
        ],
        "placetype": [
          "aat:300008347"
        ],
        "id": 7354639,
        "name:xx": "Charcas Viejas"
      }
    }
  ]
}
