{
  "geometry": {
    "type": "Point",
    "coordinates": [
      120.6003,
      22.6666
    ]
  },
  "type": "Feature",
  "properties": {
    "hierarchy": [
      "tgn:7481148",
      "tgn:1000004",
      "tgn:7492971",
      "tgn:1000141",
      "tgn:7029392"
    ],
    "placetype": [
      "aat:300006495"
    ],
    "id": 7481148,
    "name:xx": "Chongwen Guoxiao"
  }
}
