{
  "geometry": {
    "type": "Point",
    "coordinates": [
      145.7667,
      -24.0833
    ]
  },
  "type": "Feature",
  "properties": {
    "hierarchy": [
      "tgn:1098620",
      "tgn:7000490",
      "tgn:1000006",
      "tgn:7001830",
      "tgn:7029392"
    ],
    "placetype": [
      "aat:300008347"
    ],
    "id": 1098620,
    "name:xx": "Yalleroi"
  }
}
