{
  "geometry": {
    "type": "Point",
    "coordinates": [
      -80.5333,
      28.4667
    ]
  },
  "type": "Feature",
  "properties": {
    "hierarchy": [
      "tgn:2218348",
      "tgn:1000001",
      "tgn:1002200",
      "tgn:7012149",
      "tgn:7007240",
      "tgn:7029392"
    ],
    "placetype": [
      "aat:300008347"
    ],
    "id": 2218348,
    "name:xx": "Canaveral"
  }
}
