{
  "geometry": {
    "type": "Point",
    "coordinates": [
      -105.15,
      37.15
    ]
  },
  "type": "Feature",
  "properties": {
    "hierarchy": [
      "tgn:2471350",
      "tgn:1000001",
      "tgn:7012149",
      "tgn:7007158",
      "tgn:7029392"
    ],
    "placetype": [
      "aat:300008680"
    ],
    "id": 2471350,
    "name:xx": "Lost Lake"
  }
}
