{
  "type": "FeatureCollection",
  "features": [
    {
      "geometry": {
        "type": "Point",
        "coordinates": [
          74.383333,
          25.366667
        ]
      },
      "type": "Feature",
      "properties": {
        "hierarchy": [
          "tgn:7032900",
          "tgn:1000004",
          "tgn:7000198",
          "tgn:7016788",
          "tgn:7029392"
        ],
        "placetype": [
          "aat:300008347",
          "aat:300000810",
          "aat:300387006",
          "aat:300391520"
        ],
        "name:en": "Bāgor",
        "id": 7032900
      }
    },
    {
      "geometry": {
        "type": "Point",
        "coordinates": [
          25.811111,
          35.125833
        ]
      },
      "type": "Feature",
      "properties": {
        "hierarchy": [
          "tgn:7032903",
          "tgn:7002692",
          "tgn:7012056",
          "tgn:1000003",
          "tgn:1000074",
          "tgn:7029392"
        ],
        "placetype": [
          "aat:300020226",
          "aat:300000810",
          "aat:300019275",
          "aat:300008791",
          "aat:300387004",
          "aat:300008804"
        ],
        "id": 7032903,
        "name:xx": "Mochlos Island"
      }
    }
  ]
}
