{
  "geometry": {
    "type": "Point",
    "coordinates": [
      -85.85,
      39.4333
    ]
  },
  "type": "Feature",
  "properties": {
    "hierarchy": [
      "tgn:2520403",
      "tgn:1000001",
      "tgn:7012149",
      "tgn:1002886",
      "tgn:7007252",
      "tgn:7029392"
    ],
    "placetype": [
      "aat:300008798"
    ],
    "id": 2520403,
    "name:xx": "Money Hill"
  }
}
