{
  "geometry": {
    "type": "Point",
    "coordinates": [
      108.5667,
      -6.9667
    ]
  },
  "type": "Feature",
  "properties": {
    "hierarchy": [
      "tgn:1077578",
      "tgn:1001321",
      "tgn:1000004",
      "tgn:1000116",
      "tgn:7029392"
    ],
    "placetype": [
      "aat:300008347"
    ],
    "id": 1077578,
    "name:xx": "Ciawigebang"
  }
}
