{
  "geometry": {
    "type": "Point",
    "coordinates": [
      -89.0833,
      45.3833
    ]
  },
  "type": "Feature",
  "properties": {
    "hierarchy": [
      "tgn:2441074",
      "tgn:1000001",
      "tgn:7012149",
      "tgn:2002333",
      "tgn:7007922",
      "tgn:7029392"
    ],
    "placetype": [
      "aat:300008697"
    ],
    "id": 2441074,
    "name:xx": "Knoke Spring"
  }
}
