{
  "geometry": {
    "type": "Point",
    "coordinates": [
      -73.1833,
      40.9333
    ]
  },
  "type": "Feature",
  "properties": {
    "hierarchy": [
      "tgn:1113837",
      "tgn:1000001",
      "tgn:7012149",
      "tgn:1002924",
      "tgn:7007568",
      "tgn:7029392"
    ],
    "placetype": [
      "aat:300132316"
    ],
    "id": 1113837,
    "name:xx": "Smithtown Bay"
  }
}
