{
  "geometry": {
    "type": "Point",
    "coordinates": [
      78.92005,
      24.678468
    ]
  },
  "type": "Feature",
  "properties": {
    "hierarchy": [
      "tgn:7584994",
      "tgn:1000004",
      "tgn:7000198",
      "tgn:1001894",
      "tgn:7029392"
    ],
    "placetype": [
      "aat:300008347"
    ],
    "name:en": "Belātāl",
    "id": 7584994
  }
}
