{
  "geometry": {
    "type": "Point",
    "coordinates": [
      108.6667,
      18.5167
    ]
  },
  "type": "Feature",
  "properties": {
    "hierarchy": [
      "tgn:1073551",
      "tgn:1000004",
      "tgn:7001800",
      "tgn:1000111",
      "tgn:7029392"
    ],
    "placetype": [
      "aat:300008347"
    ],
    "id": 1073551,
    "name:xx": "Yinggehai"
  }
}
