{
  "geometry": {
    "type": "Point",
    "coordinates": [
      -96.75,
      43.6667
    ]
  },
  "type": "Feature",
  "properties": {
    "hierarchy": [
      "tgn:2001819",
      "tgn:1000001",
      "tgn:7012149",
      "tgn:7007713",
      "tgn:7029392"
    ],
    "placetype": [
      "aat:300387145",
      "aat:300000771"
    ],
    "id": 2001819,
    "name:xx": "Minnehaha"
  }
}
