{
  "geometry": {
    "type": "Point",
    "coordinates": [
      -121.2833,
      38.4167
    ]
  },
  "type": "Feature",
  "properties": {
    "hierarchy": [
      "tgn:2014233",
      "tgn:1000001",
      "tgn:7012149",
      "tgn:7007157",
      "tgn:1002841",
      "tgn:7029392"
    ],
    "placetype": [
      "aat:300008347",
      "aat:300387210"
    ],
    "id": 2014233,
    "name:xx": "Sheldon"
  }
}
