{
  "geometry": {
    "type": "Point",
    "coordinates": [
      -122.5333,
      38.6167
    ]
  },
  "type": "Feature",
  "properties": {
    "hierarchy": [
      "tgn:2491624",
      "tgn:1000001",
      "tgn:7012149",
      "tgn:7007157",
      "tgn:1002706",
      "tgn:7029392"
    ],
    "placetype": [
      "aat:300008697"
    ],
    "id": 2491624,
    "name:xx": "Maple Spring"
  }
}
