{
  "geometry": {
    "type": "Point",
    "coordinates": [
      -104.3167,
      34.0833
    ]
  },
  "type": "Feature",
  "properties": {
    "hierarchy": [
      "tgn:2639290",
      "tgn:1000001",
      "tgn:7019560",
      "tgn:7012149",
      "tgn:7007566",
      "tgn:7029392"
    ],
    "placetype": [
      "aat:300008697"
    ],
    "id": 2639290,
    "name:xx": "Salt Spring"
  }
}
