{
  "type": "FeatureCollection",
  "features": [
    {
      "geometry": {
        "type": "Point",
        "coordinates": [
          -93.5667,
          36.6167
        ]
      },
      "type": "Feature",
      "properties": {
        "hierarchy": [
          "tgn:2166100",
          "tgn:1000001",
          "tgn:7012149",
          "tgn:2001249",
          "tgn:7007523",
          "tgn:7029392"
        ],
        "placetype": [
          "aat:300132316"
        ],
        "id": 2166100,
        "name:xx": "Big Bay"
      }
    },
    {
      "geometry": {
        "type": "Point",
        "coordinates": [
          -74.55,
          43.3667
        ]
      },
      "type": "Feature",
      "properties": {
        "hierarchy": [
          "tgn:2166101",
          "tgn:1000001",
          "tgn:7012149",
          "tgn:1002440",
          "tgn:7007568",
          "tgn:7029392"
        ],
        "placetype": [
          "aat:300132316"
        ],
        "id": 2166101,
        "name:xx": "Big Bay"
      }
    },
    {
      "geometry": {
        "type": "Point",
        "coordinates": [
          -75.6167,
          44.4333
        ]
      },
      "type": "Feature",
      "properties": {
        "hierarchy": [
          "tgn:2166102",
          "tgn:1000001",
          "tgn:7012149",
          "tgn:7016021",
          "tgn:7007568",
          "tgn:7029392"
        ],
        "placetype": [
          "aat:300132316"
        ],
        "id": 2166102,
        "name:xx": "Big Bay"
      }
    },
    {
      "geometry": {
        "type": "Point",
        "coordinates": [
          -76.1,
          43.2333
        ]
      },
      "type": "Feature",
      "properties": {
        "hierarchy": [
          "tgn:2166103",
          "tgn:1000001",
          "tgn:7012149",
          "tgn:1002758",
          "tgn:7007568",
          "tgn:7029392"
        ],
        "placetype": [
          "aat:300132316"
        ],
        "id": 2166103,
        "name:xx": "Big Bay"
      }
    },
    {
      "geometry": {
        "type": "Point",
        "coordinates": [
          -76.1167,
          43.2333
        ]
      },
      "type": "Feature",
      "properties": {
        "hierarchy": [
          "tgn:2166104",
          "tgn:1000001",
          "tgn:7012149",
          "tgn:1002758",
          "tgn:7007568",
          "tgn:7029392"
        ],
        "placetype": [
          "aat:300008347"
        ],
        "id": 2166104,
        "name:xx": "Big Bay"
      }
    },
    {
      "geometry": {
        "type": "Point",
        "coordinates": [
          -76.8,
          35.4833
        ]
      },
      "type": "Feature",
      "properties": {
        "hierarchy": [
          "tgn:2166105",
          "tgn:1000001",
          "tgn:7013368",
          "tgn:7012149",
          "tgn:7007709",
          "tgn:7029392"
        ],
        "placetype": [
          "aat:300132316"
        ],
        "id": 2166105,
        "name:xx": "Big Bay"
      }
    },
    {
      "geometry": {
        "type": "Point",
        "coordinates": [
          -77.9667,
          34.05
        ]
      },
      "type": "Feature",
      "properties": {
        "hierarchy": [
          "tgn:2166106",
          "tgn:1000001",
          "tgn:2001472",
          "tgn:7012149",
          "tgn:7007709",
          "tgn:7029392"
        ],
        "placetype": [
          "aat:300008905"
        ],
        "id": 2166106,
        "name:xx": "Big Bay"
      }
    },
    {
      "geometry": {
        "type": "Point",
        "coordinates": [
          -78.6833,
          34.2
        ]
      },
      "type": "Feature",
      "properties": {
        "hierarchy": [
          "tgn:2166107",
          "tgn:1000001",
          "tgn:2001485",
          "tgn:7012149",
          "tgn:7007709",
          "tgn:7029392"
        ],
        "placetype": [
          "aat:300008905"
        ],
        "id": 2166107,
        "name:xx": "Big Bay"
      }
    },
    {
      "geometry": {
        "type": "Point",
        "coordinates": [
          -78.5,
          34.4
        ]
      },
      "type": "Feature",
      "properties": {
        "hierarchy": [
          "tgn:2166108",
          "tgn:1000001",
          "tgn:2001471",
          "tgn:7012149",
          "tgn:7007709",
          "tgn:7029392"
        ],
        "placetype": [
          "aat:300008905"
        ],
        "id": 2166108,
        "name:xx": "Big Bay"
      }
    },
    {
      "geometry": {
        "type": "Point",
        "coordinates": [
          -79.0667,
          34.4333
        ]
      },
      "type": "Feature",
      "properties": {
        "hierarchy": [
          "tgn:2166109",
          "tgn:1000001",
          "tgn:7012149",
          "tgn:2001534",
          "tgn:7007709",
          "tgn:7029392"
        ],
        "placetype": [
          "aat:300008905"
        ],
        "id": 2166109,
        "name:xx": "Big Bay"
      }
    }
  ]
}
