{
  "geometry": {
    "type": "Point",
    "coordinates": [
      -99.7333,
      39.2667
    ]
  },
  "type": "Feature",
  "properties": {
    "hierarchy": [
      "tgn:2770345",
      "tgn:1000001",
      "tgn:2000692",
      "tgn:7012149",
      "tgn:7007254",
      "tgn:7029392"
    ],
    "placetype": [
      "aat:300008706"
    ],
    "id": 2770345,
    "name:xx": "Wild Horse Creek"
  }
}
