{
  "geometry": {
    "type": "Point",
    "coordinates": [
      -85.1833,
      40.4167
    ]
  },
  "type": "Feature",
  "properties": {
    "hierarchy": [
      "tgn:2378036",
      "tgn:1000001",
      "tgn:7012149",
      "tgn:1002513",
      "tgn:7007252",
      "tgn:7029392"
    ],
    "placetype": [
      "aat:300008706"
    ],
    "id": 2378036,
    "name:xx": "Harris Creek"
  }
}
