{
  "type": "FeatureCollection",
  "features": [
    {
      "geometry": {
        "type": "Point",
        "coordinates": [
          23.7,
          38.616667
        ]
      },
      "type": "Feature",
      "properties": {
        "hierarchy": [
          "tgn:7223361",
          "tgn:7002681",
          "tgn:7001395",
          "tgn:1000003",
          "tgn:1000074",
          "tgn:7029392"
        ],
        "placetype": [
          "aat:300008347"
        ],
        "id": 7223361,
        "name:xx": "Platánia"
      }
    },
    {
      "geometry": {
        "type": "Point",
        "coordinates": [
          21.833333,
          37.383333
        ]
      },
      "type": "Feature",
      "properties": {
        "hierarchy": [
          "tgn:7223362",
          "tgn:7011369",
          "tgn:7017076",
          "tgn:1000003",
          "tgn:1000074",
          "tgn:7029392"
        ],
        "placetype": [
          "aat:300008347"
        ],
        "id": 7223362,
        "name:xx": "Platánia"
      }
    },
    {
      "geometry": {
        "type": "Point",
        "coordinates": [
          24.7,
          35.233333
        ]
      },
      "type": "Feature",
      "properties": {
        "hierarchy": [
          "tgn:7223363",
          "tgn:7002690",
          "tgn:7012056",
          "tgn:1000003",
          "tgn:1000074",
          "tgn:7029392"
        ],
        "placetype": [
          "aat:300008347"
        ],
        "id": 7223363,
        "name:xx": "Platánia"
      }
    },
    {
      "geometry": {
        "type": "Point",
        "coordinates": [
          22.046389,
          40.760833
        ]
      },
      "type": "Feature",
      "properties": {
        "hierarchy": [
          "tgn:7223364",
          "tgn:7002728",
          "tgn:7002715",
          "tgn:1000003",
          "tgn:1000074",
          "tgn:7029392"
        ],
        "placetype": [
          "aat:300008347"
        ],
        "id": 7223364,
        "name:xx": "Platáni"
      }
    },
    {
      "geometry": {
        "type": "Point",
        "coordinates": [
          22.633333,
          36.833333
        ]
      },
      "type": "Feature",
      "properties": {
        "hierarchy": [
          "tgn:7223365",
          "tgn:7002735",
          "tgn:7017076",
          "tgn:1000003",
          "tgn:1000074",
          "tgn:7029392"
        ],
        "placetype": [
          "aat:300008699"
        ],
        "id": 7223365,
        "name:xx": "Platánes Réma"
      }
    },
    {
      "geometry": {
        "type": "Point",
        "coordinates": [
          23.783333,
          35.416667
        ]
      },
      "type": "Feature",
      "properties": {
        "hierarchy": [
          "tgn:7223366",
          "tgn:7002690",
          "tgn:7012056",
          "tgn:1000003",
          "tgn:1000074",
          "tgn:7029392"
        ],
        "placetype": [
          "aat:300008347"
        ],
        "id": 7223366,
        "name:xx": "Platanés"
      }
    },
    {
      "geometry": {
        "type": "Point",
        "coordinates": [
          24.533333,
          35.366667
        ]
      },
      "type": "Feature",
      "properties": {
        "hierarchy": [
          "tgn:7223367",
          "tgn:7002690",
          "tgn:7012056",
          "tgn:1000003",
          "tgn:1000074",
          "tgn:7029392"
        ],
        "placetype": [
          "aat:300008347"
        ],
        "id": 7223367,
        "name:xx": "Platanés"
      }
    },
    {
      "geometry": {
        "type": "Point",
        "coordinates": [
          23.75,
          35.266667
        ]
      },
      "type": "Feature",
      "properties": {
        "hierarchy": [
          "tgn:7223368",
          "tgn:7002690",
          "tgn:7012056",
          "tgn:1000003",
          "tgn:1000074",
          "tgn:7029392"
        ],
        "placetype": [
          "aat:300008347"
        ],
        "id": 7223368,
        "name:xx": "Platanés"
      }
    },
    {
      "geometry": {
        "type": "Point",
        "coordinates": [
          24.583333,
          35.166667
        ]
      },
      "type": "Feature",
      "properties": {
        "hierarchy": [
          "tgn:7223369",
          "tgn:7002690",
          "tgn:7012056",
          "tgn:1000003",
          "tgn:1000074",
          "tgn:7029392"
        ],
        "placetype": [
          "aat:300008347"
        ],
        "id": 7223369,
        "name:xx": "Platanés"
      }
    }
  ]
}
