{
  "geometry": {
    "type": "Point",
    "coordinates": [
      118.6667,
      24.6333
    ]
  },
  "type": "Feature",
  "properties": {
    "hierarchy": [
      "tgn:1071604",
      "tgn:1000004",
      "tgn:7001796",
      "tgn:1000111",
      "tgn:7029392"
    ],
    "placetype": [
      "aat:300008347"
    ],
    "id": 1071604,
    "name:xx": "Shenhu"
  }
}
