{
  "geometry": {
    "type": "Point",
    "coordinates": [
      -74.2167,
      44.1833
    ]
  },
  "type": "Feature",
  "properties": {
    "hierarchy": [
      "tgn:2183027",
      "tgn:1000001",
      "tgn:7012149",
      "tgn:7013941",
      "tgn:7007568",
      "tgn:7029392"
    ],
    "placetype": [
      "aat:300008680"
    ],
    "id": 2183027,
    "name:xx": "Blueberry Pond"
  }
}
