{
  "geometry": {
    "type": "Point",
    "coordinates": [
      -92.3833,
      46.0167
    ]
  },
  "type": "Feature",
  "properties": {
    "hierarchy": [
      "tgn:2643855",
      "tgn:1000001",
      "tgn:7012149",
      "tgn:2001056",
      "tgn:7007521",
      "tgn:7029392"
    ],
    "placetype": [
      "aat:300008706"
    ],
    "id": 2643855,
    "name:xx": "Sangeta Creek"
  }
}
