{
  "type": "FeatureCollection",
  "features": [
    {
      "geometry": {
        "type": "Point",
        "coordinates": [
          -89.85,
          39.2167
        ]
      },
      "type": "Feature",
      "properties": {
        "hierarchy": [
          "tgn:2200460",
          "tgn:1000001",
          "tgn:7012149",
          "tgn:1002620",
          "tgn:7007251",
          "tgn:7029392"
        ],
        "placetype": [
          "aat:300008798"
        ],
        "id": 2200460,
        "name:xx": "Brushy Mound"
      }
    },
    {
      "geometry": {
        "type": "Point",
        "coordinates": [
          -93.15,
          37.5667
        ]
      },
      "type": "Feature",
      "properties": {
        "hierarchy": [
          "tgn:2200461",
          "tgn:1000001",
          "tgn:7012149",
          "tgn:2001192",
          "tgn:7007523",
          "tgn:7029392"
        ],
        "placetype": [
          "aat:300008798"
        ],
        "id": 2200461,
        "name:xx": "Brushy Mound"
      }
    },
    {
      "geometry": {
        "type": "Point",
        "coordinates": [
          -94.3833,
          38.1333
        ]
      },
      "type": "Feature",
      "properties": {
        "hierarchy": [
          "tgn:2200462",
          "tgn:2001172",
          "tgn:1000001",
          "tgn:7012149",
          "tgn:7007523",
          "tgn:7029392"
        ],
        "placetype": [
          "aat:300008798"
        ],
        "id": 2200462,
        "name:xx": "Brushy Mound"
      }
    },
    {
      "geometry": {
        "type": "Point",
        "coordinates": [
          -95.65,
          36.4
        ]
      },
      "type": "Feature",
      "properties": {
        "hierarchy": [
          "tgn:2200463",
          "tgn:1000001",
          "tgn:7012149",
          "tgn:2001688",
          "tgn:7007707",
          "tgn:7029392"
        ],
        "placetype": [
          "aat:300008798"
        ],
        "id": 2200463,
        "name:xx": "Brushy Mound"
      }
    },
    {
      "geometry": {
        "type": "Point",
        "coordinates": [
          -97.3333,
          32.55
        ]
      },
      "type": "Feature",
      "properties": {
        "hierarchy": [
          "tgn:2200464",
          "tgn:1000001",
          "tgn:7012149",
          "tgn:1002526",
          "tgn:7007826",
          "tgn:7029392"
        ],
        "placetype": [
          "aat:300008798"
        ],
        "id": 2200464,
        "name:xx": "Brushy Mound"
      }
    },
    {
      "geometry": {
        "type": "Point",
        "coordinates": [
          -97.7833,
          33.15
        ]
      },
      "type": "Feature",
      "properties": {
        "hierarchy": [
          "tgn:2200465",
          "tgn:1000001",
          "tgn:7012149",
          "tgn:1003031",
          "tgn:7007826",
          "tgn:7029392"
        ],
        "placetype": [
          "aat:300008798"
        ],
        "id": 2200465,
        "name:xx": "Brushy Mound"
      }
    },
    {
      "geometry": {
        "type": "Point",
        "coordinates": [
          -97.9,
          33.5833
        ]
      },
      "type": "Feature",
      "properties": {
        "hierarchy": [
          "tgn:2200466",
          "tgn:1000001",
          "tgn:7012149",
          "tgn:2002044",
          "tgn:7007826",
          "tgn:7029392"
        ],
        "placetype": [
          "aat:300008798"
        ],
        "id": 2200466,
        "name:xx": "Brushy Mound"
      }
    },
    {
      "geometry": {
        "type": "Point",
        "coordinates": [
          -96.9333,
          33.8833
        ]
      },
      "type": "Feature",
      "properties": {
        "hierarchy": [
          "tgn:2200467",
          "tgn:1000001",
          "tgn:7012149",
          "tgn:7007826",
          "tgn:7029392"
        ],
        "placetype": [
          "aat:300008798"
        ],
        "id": 2200467,
        "name:xx": "Brushy Mound"
      }
    },
    {
      "geometry": {
        "type": "Point",
        "coordinates": [
          -94.3833,
          38.1333
        ]
      },
      "type": "Feature",
      "properties": {
        "hierarchy": [
          "tgn:2200468",
          "tgn:2001172",
          "tgn:1000001",
          "tgn:7012149",
          "tgn:7007523",
          "tgn:7029392"
        ],
        "placetype": [
          "aat:300006191"
        ],
        "id": 2200468,
        "name:xx": "Brushy Mound Lake"
      }
    },
    {
      "geometry": {
        "type": "Point",
        "coordinates": [
          -92.5,
          45.0833
        ]
      },
      "type": "Feature",
      "properties": {
        "hierarchy": [
          "tgn:2200469",
          "tgn:1000001",
          "tgn:7012149",
          "tgn:2002351",
          "tgn:7007922",
          "tgn:7029392"
        ],
        "placetype": [
          "aat:300008680"
        ],
        "id": 2200469,
        "name:xx": "Brushy Mound Lake"
      }
    }
  ]
}
