{
  "geometry": {
    "type": "Point",
    "coordinates": [
      -120.75,
      35.65
    ]
  },
  "type": "Feature",
  "properties": {
    "hierarchy": [
      "tgn:2533684",
      "tgn:1000001",
      "tgn:7012149",
      "tgn:7007157",
      "tgn:1002863",
      "tgn:7029392"
    ],
    "placetype": [
      "aat:300008706"
    ],
    "id": 2533684,
    "name:xx": "Mustard Creek"
  }
}
