{
  "type": "FeatureCollection",
  "features": [
    {
      "geometry": {
        "type": "Point",
        "coordinates": [
          -111.35,
          33.4667
        ]
      },
      "type": "Feature",
      "properties": {
        "hierarchy": [
          "tgn:2176770",
          "tgn:1000001",
          "tgn:7006451",
          "tgn:7012149",
          "tgn:2000097",
          "tgn:7029392"
        ],
        "placetype": [
          "aat:300008798"
        ],
        "id": 2176770,
        "name:xx": "Black Mountain"
      }
    },
    {
      "geometry": {
        "type": "Point",
        "coordinates": [
          -110.6667,
          33.65
        ]
      },
      "type": "Feature",
      "properties": {
        "hierarchy": [
          "tgn:2176771",
          "tgn:1000001",
          "tgn:7006451",
          "tgn:2000093",
          "tgn:7012149",
          "tgn:7029392"
        ],
        "placetype": [
          "aat:300008798"
        ],
        "id": 2176771,
        "name:xx": "Black Mountain"
      }
    },
    {
      "geometry": {
        "type": "Point",
        "coordinates": [
          -113.1,
          34.1833
        ]
      },
      "type": "Feature",
      "properties": {
        "hierarchy": [
          "tgn:2176772",
          "tgn:1000001",
          "tgn:7006451",
          "tgn:7012149",
          "tgn:2000103",
          "tgn:7029392"
        ],
        "placetype": [
          "aat:300008798"
        ],
        "id": 2176772,
        "name:xx": "Black Mountain"
      }
    },
    {
      "geometry": {
        "type": "Point",
        "coordinates": [
          -111.4667,
          35.4
        ]
      },
      "type": "Feature",
      "properties": {
        "hierarchy": [
          "tgn:2176773",
          "tgn:1000001",
          "tgn:7006451",
          "tgn:2000092",
          "tgn:7012149",
          "tgn:7029392"
        ],
        "placetype": [
          "aat:300008798"
        ],
        "id": 2176773,
        "name:xx": "Black Mountain"
      }
    },
    {
      "geometry": {
        "type": "Point",
        "coordinates": [
          -114.0333,
          34.4833
        ]
      },
      "type": "Feature",
      "properties": {
        "hierarchy": [
          "tgn:2176774",
          "tgn:1000001",
          "tgn:7006451",
          "tgn:7012149",
          "tgn:2000098",
          "tgn:7029392"
        ],
        "placetype": [
          "aat:300008798"
        ],
        "id": 2176774,
        "name:xx": "Black Mountain"
      }
    },
    {
      "geometry": {
        "type": "Point",
        "coordinates": [
          -112.1667,
          32.7333
        ]
      },
      "type": "Feature",
      "properties": {
        "hierarchy": [
          "tgn:2176775",
          "tgn:1000001",
          "tgn:7006451",
          "tgn:7012149",
          "tgn:2000101",
          "tgn:7029392"
        ],
        "placetype": [
          "aat:300008798"
        ],
        "id": 2176775,
        "name:xx": "Black Mountain"
      }
    },
    {
      "geometry": {
        "type": "Point",
        "coordinates": [
          -92.6667,
          35.5333
        ]
      },
      "type": "Feature",
      "properties": {
        "hierarchy": [
          "tgn:2176776",
          "tgn:1000001",
          "tgn:7016172",
          "tgn:7012149",
          "tgn:2000175",
          "tgn:7029392"
        ],
        "placetype": [
          "aat:300008798"
        ],
        "id": 2176776,
        "name:xx": "Black Mountain"
      }
    },
    {
      "geometry": {
        "type": "Point",
        "coordinates": [
          -93.8667,
          35.6667
        ]
      },
      "type": "Feature",
      "properties": {
        "hierarchy": [
          "tgn:2176777",
          "tgn:1000001",
          "tgn:7016172",
          "tgn:7012149",
          "tgn:2000128",
          "tgn:7029392"
        ],
        "placetype": [
          "aat:300008798"
        ],
        "id": 2176777,
        "name:xx": "Black Mountain"
      }
    },
    {
      "geometry": {
        "type": "Point",
        "coordinates": [
          -93.45,
          36.2167
        ]
      },
      "type": "Feature",
      "properties": {
        "hierarchy": [
          "tgn:2176778",
          "tgn:1000001",
          "tgn:7016172",
          "tgn:2000112",
          "tgn:7012149",
          "tgn:7029392"
        ],
        "placetype": [
          "aat:300008798"
        ],
        "id": 2176778,
        "name:xx": "Black Mountain"
      }
    },
    {
      "geometry": {
        "type": "Point",
        "coordinates": [
          -118.3667,
          36.8
        ]
      },
      "type": "Feature",
      "properties": {
        "hierarchy": [
          "tgn:2176779",
          "tgn:1000001",
          "tgn:7012149",
          "tgn:7007157",
          "tgn:7029392"
        ],
        "placetype": [
          "aat:300008798"
        ],
        "id": 2176779,
        "name:xx": "Black Mountain"
      }
    }
  ]
}
