{
  "geometry": {
    "type": "Point",
    "coordinates": [
      -90.4333,
      34.0667
    ]
  },
  "type": "Feature",
  "properties": {
    "hierarchy": [
      "tgn:2298036",
      "tgn:1000001",
      "tgn:7012149",
      "tgn:7007522",
      "tgn:7029392"
    ],
    "placetype": [
      "aat:300008680"
    ],
    "id": 2298036,
    "name:xx": "Dry Lake"
  }
}
