{
  "geometry": {
    "type": "Point",
    "coordinates": [
      -121.1833,
      36.4333
    ]
  },
  "type": "Feature",
  "properties": {
    "hierarchy": [
      "tgn:7023580",
      "tgn:1000001",
      "tgn:7012149",
      "tgn:7007157",
      "tgn:7029392"
    ],
    "placetype": [
      "aat:300008798"
    ],
    "id": 7023580,
    "name:xx": "North Chalone Peak"
  }
}
