{
  "type": "FeatureCollection",
  "features": [
    {
      "geometry": {
        "type": "Point",
        "coordinates": [
          -106.2,
          31.5
        ]
      },
      "type": "Feature",
      "properties": {
        "hierarchy": [
          "tgn:7371760",
          "tgn:7005581",
          "tgn:1000001",
          "tgn:7005560",
          "tgn:7029392"
        ],
        "placetype": [
          "aat:300008347"
        ],
        "id": 7371760,
        "name:xx": "La Isla"
      }
    },
    {
      "geometry": {
        "type": "Point",
        "coordinates": [
          -99.133333,
          26.4
        ]
      },
      "type": "Feature",
      "properties": {
        "hierarchy": [
          "tgn:7371761",
          "tgn:1000001",
          "tgn:7005597",
          "tgn:7005560",
          "tgn:7029392"
        ],
        "placetype": [
          "aat:300008347"
        ],
        "id": 7371761,
        "name:xx": "La Isla"
      }
    },
    {
      "geometry": {
        "type": "Point",
        "coordinates": [
          -88.933333,
          21.383333
        ]
      },
      "type": "Feature",
      "properties": {
        "hierarchy": [
          "tgn:7371762",
          "tgn:1000001",
          "tgn:7005600",
          "tgn:7005560",
          "tgn:7029392"
        ],
        "placetype": [
          "aat:300008347"
        ],
        "id": 7371762,
        "name:xx": "La Isla"
      }
    },
    {
      "geometry": {
        "type": "Point",
        "coordinates": [
          -102.333333,
          20.5
        ]
      },
      "type": "Feature",
      "properties": {
        "hierarchy": [
          "tgn:7371763",
          "tgn:7005586",
          "tgn:1000001",
          "tgn:7005560",
          "tgn:7029392"
        ],
        "placetype": [
          "aat:300008347"
        ],
        "id": 7371763,
        "name:xx": "La Isla"
      }
    },
    {
      "geometry": {
        "type": "Point",
        "coordinates": [
          -97.066667,
          20.133333
        ]
      },
      "type": "Feature",
      "properties": {
        "hierarchy": [
          "tgn:7371764",
          "tgn:1000001",
          "tgn:7005599",
          "tgn:7005560",
          "tgn:7029392"
        ],
        "placetype": [
          "aat:300008347"
        ],
        "id": 7371764,
        "name:xx": "La Isla"
      }
    },
    {
      "geometry": {
        "type": "Point",
        "coordinates": [
          -100.083333,
          19.266667
        ]
      },
      "type": "Feature",
      "properties": {
        "hierarchy": [
          "tgn:7371765",
          "tgn:1000001",
          "tgn:1001893",
          "tgn:7005560",
          "tgn:7029392"
        ],
        "placetype": [
          "aat:300008347"
        ],
        "id": 7371765,
        "name:xx": "La Isla"
      }
    },
    {
      "geometry": {
        "type": "Point",
        "coordinates": [
          -96.15,
          18.6
        ]
      },
      "type": "Feature",
      "properties": {
        "hierarchy": [
          "tgn:7371766",
          "tgn:1000001",
          "tgn:7005599",
          "tgn:7005560",
          "tgn:7029392"
        ],
        "placetype": [
          "aat:300008347"
        ],
        "id": 7371766,
        "name:xx": "La Isla"
      }
    },
    {
      "geometry": {
        "type": "Point",
        "coordinates": [
          -91.483333,
          17.466667
        ]
      },
      "type": "Feature",
      "properties": {
        "hierarchy": [
          "tgn:7371767",
          "tgn:1000001",
          "tgn:7005596",
          "tgn:7005560",
          "tgn:7029392"
        ],
        "placetype": [
          "aat:300008347"
        ],
        "id": 7371767,
        "name:xx": "La Isla"
      }
    },
    {
      "geometry": {
        "type": "Point",
        "coordinates": [
          -94.25,
          16.116667
        ]
      },
      "type": "Feature",
      "properties": {
        "hierarchy": [
          "tgn:7371768",
          "tgn:1000001",
          "tgn:7005591",
          "tgn:7005560",
          "tgn:7029392"
        ],
        "placetype": [
          "aat:300008347"
        ],
        "id": 7371768,
        "name:xx": "La Isla"
      }
    },
    {
      "geometry": {
        "type": "Point",
        "coordinates": [
          -101.283333,
          25.066667
        ]
      },
      "type": "Feature",
      "properties": {
        "hierarchy": [
          "tgn:7371769",
          "tgn:1001853",
          "tgn:1000001",
          "tgn:7005560",
          "tgn:7029392"
        ],
        "placetype": [
          "aat:300266640"
        ],
        "id": 7371769,
        "name:xx": "La India, Sierra de"
      }
    }
  ]
}
