{
  "type": "FeatureCollection",
  "features": [
    {
      "geometry": {
        "type": "Point",
        "coordinates": [
          -90.233333,
          19.866667
        ]
      },
      "type": "Feature",
      "properties": {
        "hierarchy": [
          "tgn:7396360",
          "tgn:7005578",
          "tgn:1000001",
          "tgn:7005560",
          "tgn:7029392"
        ],
        "placetype": [
          "aat:300008347"
        ],
        "id": 7396360,
        "name:xx": "Santa Rita"
      }
    },
    {
      "geometry": {
        "type": "Point",
        "coordinates": [
          -90.4,
          19.483333
        ]
      },
      "type": "Feature",
      "properties": {
        "hierarchy": [
          "tgn:7396361",
          "tgn:7005578",
          "tgn:1000001",
          "tgn:7005560",
          "tgn:7029392"
        ],
        "placetype": [
          "aat:300008347"
        ],
        "id": 7396361,
        "name:xx": "Santa Rita"
      }
    },
    {
      "geometry": {
        "type": "Point",
        "coordinates": [
          -97.416667,
          19.066667
        ]
      },
      "type": "Feature",
      "properties": {
        "hierarchy": [
          "tgn:7396362",
          "tgn:1000001",
          "tgn:7005592",
          "tgn:7005560",
          "tgn:7029392"
        ],
        "placetype": [
          "aat:300008347"
        ],
        "id": 7396362,
        "name:xx": "Santa Rita"
      }
    },
    {
      "geometry": {
        "type": "Point",
        "coordinates": [
          -104.083333,
          19
        ]
      },
      "type": "Feature",
      "properties": {
        "hierarchy": [
          "tgn:7396363",
          "tgn:7016644",
          "tgn:1000001",
          "tgn:7005560",
          "tgn:7029392"
        ],
        "placetype": [
          "aat:300008347"
        ],
        "id": 7396363,
        "name:xx": "Santa Rita"
      }
    },
    {
      "geometry": {
        "type": "Point",
        "coordinates": [
          -96.316667,
          18.933333
        ]
      },
      "type": "Feature",
      "properties": {
        "hierarchy": [
          "tgn:7396364",
          "tgn:1000001",
          "tgn:7005599",
          "tgn:7005560",
          "tgn:7029392"
        ],
        "placetype": [
          "aat:300008347"
        ],
        "id": 7396364,
        "name:xx": "Santa Rita"
      }
    },
    {
      "geometry": {
        "type": "Point",
        "coordinates": [
          -92.566667,
          18.55
        ]
      },
      "type": "Feature",
      "properties": {
        "hierarchy": [
          "tgn:7396365",
          "tgn:1000001",
          "tgn:7005596",
          "tgn:7005560",
          "tgn:7029392"
        ],
        "placetype": [
          "aat:300008347"
        ],
        "id": 7396365,
        "name:xx": "Santa Rita"
      }
    },
    {
      "geometry": {
        "type": "Point",
        "coordinates": [
          -92.35,
          18.433333
        ]
      },
      "type": "Feature",
      "properties": {
        "hierarchy": [
          "tgn:7396366",
          "tgn:1000001",
          "tgn:7005596",
          "tgn:7005560",
          "tgn:7029392"
        ],
        "placetype": [
          "aat:300008347"
        ],
        "id": 7396366,
        "name:xx": "Santa Rita"
      }
    },
    {
      "geometry": {
        "type": "Point",
        "coordinates": [
          -101.583333,
          18.366667
        ]
      },
      "type": "Feature",
      "properties": {
        "hierarchy": [
          "tgn:7396367",
          "tgn:7005585",
          "tgn:1000001",
          "tgn:7005560",
          "tgn:7029392"
        ],
        "placetype": [
          "aat:300008347"
        ],
        "id": 7396367,
        "name:xx": "Santa Rita"
      }
    },
    {
      "geometry": {
        "type": "Point",
        "coordinates": [
          -92.016667,
          18.25
        ]
      },
      "type": "Feature",
      "properties": {
        "hierarchy": [
          "tgn:7396368",
          "tgn:7005578",
          "tgn:1000001",
          "tgn:7005560",
          "tgn:7029392"
        ],
        "placetype": [
          "aat:300008347"
        ],
        "id": 7396368,
        "name:xx": "Santa Rita"
      }
    },
    {
      "geometry": {
        "type": "Point",
        "coordinates": [
          -91.216667,
          18.166667
        ]
      },
      "type": "Feature",
      "properties": {
        "hierarchy": [
          "tgn:7396369",
          "tgn:7005578",
          "tgn:1000001",
          "tgn:7005560",
          "tgn:7029392"
        ],
        "placetype": [
          "aat:300008347"
        ],
        "id": 7396369,
        "name:xx": "Santa Rita"
      }
    }
  ]
}
