{
  "geometry": {
    "type": "Point",
    "coordinates": [
      -91.8667,
      33.7667
    ]
  },
  "type": "Feature",
  "properties": {
    "hierarchy": [
      "tgn:2587047",
      "tgn:1000001",
      "tgn:7016172",
      "tgn:7012149",
      "tgn:2000126",
      "tgn:7029392"
    ],
    "placetype": [
      "aat:300008347"
    ],
    "id": 2587047,
    "name:xx": "Plantersville"
  }
}
