{
  "geometry": {
    "type": "Point",
    "coordinates": [
      -87.9167,
      38.5833
    ]
  },
  "type": "Feature",
  "properties": {
    "hierarchy": [
      "tgn:2026571",
      "tgn:1000001",
      "tgn:7012149",
      "tgn:2000527",
      "tgn:7007251",
      "tgn:7029392"
    ],
    "placetype": [
      "aat:300008347"
    ],
    "id": 2026571,
    "name:xx": "Berryville"
  }
}
