{
  "geometry": {
    "type": "Point",
    "coordinates": [
      -109.4333,
      33.8667
    ]
  },
  "type": "Feature",
  "properties": {
    "hierarchy": [
      "tgn:2651400",
      "tgn:2000090",
      "tgn:1000001",
      "tgn:7006451",
      "tgn:7012149",
      "tgn:7029392"
    ],
    "placetype": [
      "aat:300006191"
    ],
    "id": 2651400,
    "name:xx": "Section Twenty-Five Tank"
  }
}
