{
  "geometry": {
    "type": "Point",
    "coordinates": [
      -71.8167,
      43.1667
    ]
  },
  "type": "Feature",
  "properties": {
    "hierarchy": [
      "tgn:2599268",
      "tgn:1000001",
      "tgn:2001425",
      "tgn:7012149",
      "tgn:7007564",
      "tgn:7029392"
    ],
    "placetype": [
      "aat:300008798"
    ],
    "id": 2599268,
    "name:xx": "Proctor Hill"
  }
}
