{
  "geometry": {
    "type": "Point",
    "coordinates": [
      -72.05,
      46.6667
    ]
  },
  "type": "Feature",
  "properties": {
    "hierarchy": [
      "tgn:1015691",
      "tgn:7005685",
      "tgn:1000001",
      "tgn:7005804",
      "tgn:7029392"
    ],
    "placetype": [
      "aat:300008347"
    ],
    "id": 1015691,
    "name:xx": "Saint-Marc-des-Carrières"
  }
}
