{
  "type": "FeatureCollection",
  "features": [
    {
      "geometry": {
        "type": "Point",
        "coordinates": [
          -3.766667,
          43.4
        ]
      },
      "type": "Feature",
      "properties": {
        "hierarchy": [
          "tgn:7330740",
          "tgn:7002760",
          "tgn:1000003",
          "tgn:1000095",
          "tgn:7029392"
        ],
        "placetype": [
          "aat:300008347"
        ],
        "id": 7330740,
        "name:xx": "Heras"
      }
    },
    {
      "geometry": {
        "type": "Point",
        "coordinates": [
          -3.1,
          40.8
        ]
      },
      "type": "Feature",
      "properties": {
        "hierarchy": [
          "tgn:7330741",
          "tgn:7002822",
          "tgn:1001647",
          "tgn:1000003",
          "tgn:1000095",
          "tgn:7029392"
        ],
        "placetype": [
          "aat:300008347"
        ],
        "id": 7330741,
        "name:xx": "Heras"
      }
    },
    {
      "geometry": {
        "type": "Point",
        "coordinates": [
          -3.45,
          43.2
        ]
      },
      "type": "Feature",
      "properties": {
        "hierarchy": [
          "tgn:7330742",
          "tgn:7002760",
          "tgn:1000003",
          "tgn:1000095",
          "tgn:7029392"
        ],
        "placetype": [
          "aat:300008347"
        ],
        "id": 7330742,
        "name:xx": "Herada"
      }
    },
    {
      "geometry": {
        "type": "Point",
        "coordinates": [
          -2.716667,
          40.716667
        ]
      },
      "type": "Feature",
      "properties": {
        "hierarchy": [
          "tgn:7330744",
          "tgn:7002822",
          "tgn:1001647",
          "tgn:1000003",
          "tgn:1000095",
          "tgn:7029392"
        ],
        "placetype": [
          "aat:300008347"
        ],
        "id": 7330744,
        "name:xx": "Henche"
      }
    },
    {
      "geometry": {
        "type": "Point",
        "coordinates": [
          -1.566667,
          39.633333
        ]
      },
      "type": "Feature",
      "properties": {
        "hierarchy": [
          "tgn:7330745",
          "tgn:7002818",
          "tgn:1001647",
          "tgn:1000003",
          "tgn:1000095",
          "tgn:7029392"
        ],
        "placetype": [
          "aat:300008699"
        ],
        "id": 7330745,
        "name:xx": "Henares, Río de"
      }
    },
    {
      "geometry": {
        "type": "Point",
        "coordinates": [
          -3.5,
          40.4
        ]
      },
      "type": "Feature",
      "properties": {
        "hierarchy": [
          "tgn:7330746",
          "tgn:7010420",
          "tgn:1000003",
          "tgn:7002795",
          "tgn:1000095",
          "tgn:7029392"
        ],
        "placetype": [
          "aat:300008699"
        ],
        "id": 7330746,
        "name:xx": "Henares, Río"
      }
    },
    {
      "geometry": {
        "type": "Point",
        "coordinates": [
          -1.916667,
          37.6
        ]
      },
      "type": "Feature",
      "properties": {
        "hierarchy": [
          "tgn:7330747",
          "tgn:1001439",
          "tgn:1000003",
          "tgn:7002797",
          "tgn:1000095",
          "tgn:7029392"
        ],
        "placetype": [
          "aat:300008347"
        ],
        "id": 7330747,
        "name:xx": "Henares"
      }
    },
    {
      "geometry": {
        "type": "Point",
        "coordinates": [
          -1.483333,
          39.866667
        ]
      },
      "type": "Feature",
      "properties": {
        "hierarchy": [
          "tgn:7330748",
          "tgn:7002818",
          "tgn:1001647",
          "tgn:1000003",
          "tgn:1000095",
          "tgn:7029392"
        ],
        "placetype": [
          "aat:300008347"
        ],
        "id": 7330748,
        "name:xx": "Henarejos"
      }
    },
    {
      "geometry": {
        "type": "Point",
        "coordinates": [
          -3.9,
          41.833333
        ]
      },
      "type": "Feature",
      "properties": {
        "hierarchy": [
          "tgn:7330749",
          "tgn:7002810",
          "tgn:7001158",
          "tgn:1000003",
          "tgn:1000095",
          "tgn:7029392"
        ],
        "placetype": [
          "aat:300008699"
        ],
        "id": 7330749,
        "name:xx": "Henar, Río"
      }
    }
  ]
}
