{
  "geometry": {
    "type": "Point",
    "coordinates": [
      -75.6833,
      41.0333
    ]
  },
  "type": "Feature",
  "properties": {
    "hierarchy": [
      "tgn:2388405",
      "tgn:1000001",
      "tgn:1002233",
      "tgn:7012149",
      "tgn:7007710",
      "tgn:7029392"
    ],
    "placetype": [
      "aat:300006191"
    ],
    "id": 2388405,
    "name:xx": "Hickory Run Lake"
  }
}
