{
  "type": "FeatureCollection",
  "features": [
    {
      "geometry": {
        "type": "Point",
        "coordinates": [
          -93.2833,
          38.8167
        ]
      },
      "type": "Feature",
      "properties": {
        "hierarchy": [
          "tgn:2200110",
          "tgn:1000001",
          "tgn:7012149",
          "tgn:2001229",
          "tgn:7007523",
          "tgn:7029392"
        ],
        "placetype": [
          "aat:300008706"
        ],
        "id": 2200110,
        "name:xx": "Brushy Creek"
      }
    },
    {
      "geometry": {
        "type": "Point",
        "coordinates": [
          -94.4833,
          39.35
        ]
      },
      "type": "Feature",
      "properties": {
        "hierarchy": [
          "tgn:2200111",
          "tgn:1000001",
          "tgn:2001187",
          "tgn:7012149",
          "tgn:7007523",
          "tgn:7029392"
        ],
        "placetype": [
          "aat:300008706"
        ],
        "id": 2200111,
        "name:xx": "Brushy Creek"
      }
    },
    {
      "geometry": {
        "type": "Point",
        "coordinates": [
          -94,
          40.0833
        ]
      },
      "type": "Feature",
      "properties": {
        "hierarchy": [
          "tgn:2200112",
          "tgn:1000001",
          "tgn:7012149",
          "tgn:2001193",
          "tgn:7007523",
          "tgn:7029392"
        ],
        "placetype": [
          "aat:300008706"
        ],
        "id": 2200112,
        "name:xx": "Brushy Creek"
      }
    },
    {
      "geometry": {
        "type": "Point",
        "coordinates": [
          -92.8,
          36.7333
        ]
      },
      "type": "Feature",
      "properties": {
        "hierarchy": [
          "tgn:2200113",
          "tgn:1000001",
          "tgn:7012149",
          "tgn:2001251",
          "tgn:7007523",
          "tgn:7029392"
        ],
        "placetype": [
          "aat:300008706"
        ],
        "id": 2200113,
        "name:xx": "Brushy Creek"
      }
    },
    {
      "geometry": {
        "type": "Point",
        "coordinates": [
          -90.6333,
          37.35
        ]
      },
      "type": "Feature",
      "properties": {
        "hierarchy": [
          "tgn:2200114",
          "tgn:1000001",
          "tgn:7012149",
          "tgn:2001207",
          "tgn:7007523",
          "tgn:7029392"
        ],
        "placetype": [
          "aat:300008706"
        ],
        "id": 2200114,
        "name:xx": "Brushy Creek"
      }
    },
    {
      "geometry": {
        "type": "Point",
        "coordinates": [
          -91.8667,
          37.2833
        ]
      },
      "type": "Feature",
      "properties": {
        "hierarchy": [
          "tgn:2200115",
          "tgn:1000001",
          "tgn:7012149",
          "tgn:2001252",
          "tgn:7007523",
          "tgn:7029392"
        ],
        "placetype": [
          "aat:300008706"
        ],
        "id": 2200115,
        "name:xx": "Brushy Creek"
      }
    },
    {
      "geometry": {
        "type": "Point",
        "coordinates": [
          -93.2333,
          37.5833
        ]
      },
      "type": "Feature",
      "properties": {
        "hierarchy": [
          "tgn:2200116",
          "tgn:1000001",
          "tgn:7012149",
          "tgn:2001232",
          "tgn:7007523",
          "tgn:7029392"
        ],
        "placetype": [
          "aat:300008706"
        ],
        "id": 2200116,
        "name:xx": "Brushy Creek"
      }
    },
    {
      "geometry": {
        "type": "Point",
        "coordinates": [
          -90.1,
          37.7167
        ]
      },
      "type": "Feature",
      "properties": {
        "hierarchy": [
          "tgn:2200117",
          "tgn:1000001",
          "tgn:7012149",
          "tgn:2001240",
          "tgn:7007523",
          "tgn:7029392"
        ],
        "placetype": [
          "aat:300008706"
        ],
        "id": 2200117,
        "name:xx": "Brushy Creek"
      }
    },
    {
      "geometry": {
        "type": "Point",
        "coordinates": [
          -92.2333,
          38.1333
        ]
      },
      "type": "Feature",
      "properties": {
        "hierarchy": [
          "tgn:2200118",
          "tgn:1000001",
          "tgn:7012149",
          "tgn:1002671",
          "tgn:7007523",
          "tgn:7029392"
        ],
        "placetype": [
          "aat:300008706"
        ],
        "id": 2200118,
        "name:xx": "Brushy Creek"
      }
    },
    {
      "geometry": {
        "type": "Point",
        "coordinates": [
          -92.9167,
          38.2833
        ]
      },
      "type": "Feature",
      "properties": {
        "hierarchy": [
          "tgn:2200119",
          "tgn:1000001",
          "tgn:7012149",
          "tgn:2001221",
          "tgn:7007523",
          "tgn:7029392"
        ],
        "placetype": [
          "aat:300008706"
        ],
        "id": 2200119,
        "name:xx": "Brushy Creek"
      }
    }
  ]
}
