{
  "geometry": {
    "type": "Point",
    "coordinates": [
      -90.9667,
      43.1167
    ]
  },
  "type": "Feature",
  "properties": {
    "hierarchy": [
      "tgn:2754411",
      "tgn:1000001",
      "tgn:2002316",
      "tgn:7012149",
      "tgn:7007922",
      "tgn:7029392"
    ],
    "placetype": [
      "aat:300266640"
    ],
    "id": 2754411,
    "name:xx": "Wauzeka Ridge"
  }
}
