{
  "geometry": {
    "type": "Point",
    "coordinates": [
      -91.9333,
      37.9833
    ]
  },
  "type": "Feature",
  "properties": {
    "hierarchy": [
      "tgn:2126548",
      "tgn:1000001",
      "tgn:7012149",
      "tgn:2001230",
      "tgn:7007523",
      "tgn:7029392"
    ],
    "placetype": [
      "aat:300006191"
    ],
    "id": 2126548,
    "name:xx": "Affolter Lake"
  }
}
