{
  "geometry": {
    "type": "Point",
    "coordinates": [
      -112.9167,
      34.0167
    ]
  },
  "type": "Feature",
  "properties": {
    "hierarchy": [
      "tgn:2169931",
      "tgn:1000001",
      "tgn:7006451",
      "tgn:7012149",
      "tgn:2000103",
      "tgn:7029392"
    ],
    "placetype": [
      "aat:300006191"
    ],
    "id": 2169931,
    "name:xx": "Big Pemberton Tank"
  }
}
