{
  "type": "FeatureCollection",
  "features": [
    {
      "geometry": {
        "type": "Point",
        "coordinates": [
          6.5,
          52.766667
        ]
      },
      "type": "Feature",
      "properties": {
        "hierarchy": [
          "tgn:7259890",
          "tgn:7003614",
          "tgn:1000003",
          "tgn:7016845",
          "tgn:7029392"
        ],
        "placetype": [
          "aat:300008863"
        ],
        "name:nl": "Amhoftsbos",
        "id": 7259890
      }
    },
    {
      "geometry": {
        "type": "Point",
        "coordinates": [
          6.6,
          52.933333
        ]
      },
      "type": "Feature",
      "properties": {
        "hierarchy": [
          "tgn:7259891",
          "tgn:7003614",
          "tgn:1000003",
          "tgn:7016845",
          "tgn:7029392"
        ],
        "placetype": [
          "aat:300387200"
        ],
        "name:nl": "Amerveld",
        "id": 7259891
      }
    },
    {
      "geometry": {
        "type": "Point",
        "coordinates": [
          5.5,
          52
        ]
      },
      "type": "Feature",
      "properties": {
        "hierarchy": [
          "tgn:7259894",
          "tgn:1000003",
          "tgn:7003627",
          "tgn:7016845",
          "tgn:7029392"
        ],
        "placetype": [
          "aat:300008863"
        ],
        "name:nl": "Amerongse Bos",
        "id": 7259894
      }
    },
    {
      "geometry": {
        "type": "Point",
        "coordinates": [
          5.483333,
          52.016667
        ]
      },
      "type": "Feature",
      "properties": {
        "hierarchy": [
          "tgn:7259895",
          "tgn:1000003",
          "tgn:7003627",
          "tgn:7016845",
          "tgn:7029392"
        ],
        "placetype": [
          "aat:300008187"
        ],
        "name:nl": "Boswachterij Amerongse Berg",
        "id": 7259895
      }
    },
    {
      "geometry": {
        "type": "Point",
        "coordinates": [
          5.483333,
          52
        ]
      },
      "type": "Feature",
      "properties": {
        "hierarchy": [
          "tgn:7259896",
          "tgn:1000003",
          "tgn:7003627",
          "tgn:7016845",
          "tgn:7029392"
        ],
        "placetype": [
          "aat:300008777"
        ],
        "name:nl": "Amerongsche Berg",
        "id": 7259896
      }
    },
    {
      "geometry": {
        "type": "Point",
        "coordinates": [
          5.35,
          51.983333
        ]
      },
      "type": "Feature",
      "properties": {
        "hierarchy": [
          "tgn:7259897",
          "tgn:1000003",
          "tgn:7003627",
          "tgn:7016845",
          "tgn:7029392"
        ],
        "placetype": [
          "aat:300006075"
        ],
        "name:nl": "Amerongerwetering",
        "id": 7259897
      }
    },
    {
      "geometry": {
        "type": "Point",
        "coordinates": [
          5.45,
          52
        ]
      },
      "type": "Feature",
      "properties": {
        "hierarchy": [
          "tgn:7259898",
          "tgn:1000003",
          "tgn:7003627",
          "tgn:7016845",
          "tgn:7029392"
        ],
        "placetype": [
          "aat:300006891"
        ],
        "name:nl": "Kasteel Amerongen",
        "id": 7259898
      }
    }
  ]
}
