{
  "type": "FeatureCollection",
  "features": [
    {
      "geometry": {
        "type": "Point",
        "coordinates": [
          -70.5833,
          41.5333
        ]
      },
      "type": "Feature",
      "properties": {
        "hierarchy": [
          "tgn:2459320",
          "tgn:1002165",
          "tgn:1000001",
          "tgn:7012149",
          "tgn:7007517",
          "tgn:7029392"
        ],
        "placetype": [
          "aat:300008680"
        ],
        "id": 2459320,
        "name:xx": "Little Pond"
      }
    },
    {
      "geometry": {
        "type": "Point",
        "coordinates": [
          -71.5667,
          43.2167
        ]
      },
      "type": "Feature",
      "properties": {
        "hierarchy": [
          "tgn:2459321",
          "tgn:1000001",
          "tgn:2001425",
          "tgn:7012149",
          "tgn:7007564",
          "tgn:7029392"
        ],
        "placetype": [
          "aat:300008680"
        ],
        "id": 2459321,
        "name:xx": "Little Pond"
      }
    },
    {
      "geometry": {
        "type": "Point",
        "coordinates": [
          -71.8333,
          43.7333
        ]
      },
      "type": "Feature",
      "properties": {
        "hierarchy": [
          "tgn:2459322",
          "tgn:1000001",
          "tgn:2001424",
          "tgn:7012149",
          "tgn:7007564",
          "tgn:7029392"
        ],
        "placetype": [
          "aat:300008680"
        ],
        "id": 2459322,
        "name:xx": "Little Pond"
      }
    },
    {
      "geometry": {
        "type": "Point",
        "coordinates": [
          -71.4667,
          43.6667
        ]
      },
      "type": "Feature",
      "properties": {
        "hierarchy": [
          "tgn:2459323",
          "tgn:2001422",
          "tgn:1000001",
          "tgn:7012149",
          "tgn:7007564",
          "tgn:7029392"
        ],
        "placetype": [
          "aat:300008680"
        ],
        "id": 2459323,
        "name:xx": "Little Pond"
      }
    },
    {
      "geometry": {
        "type": "Point",
        "coordinates": [
          -71.4,
          43.7833
        ]
      },
      "type": "Feature",
      "properties": {
        "hierarchy": [
          "tgn:2459324",
          "tgn:2001423",
          "tgn:1000001",
          "tgn:7012149",
          "tgn:7007564",
          "tgn:7029392"
        ],
        "placetype": [
          "aat:300008680"
        ],
        "id": 2459324,
        "name:xx": "Little Pond"
      }
    },
    {
      "geometry": {
        "type": "Point",
        "coordinates": [
          -72.0833,
          41.0667
        ]
      },
      "type": "Feature",
      "properties": {
        "hierarchy": [
          "tgn:2459325",
          "tgn:1000001",
          "tgn:7012149",
          "tgn:1002924",
          "tgn:7007568",
          "tgn:7029392"
        ],
        "placetype": [
          "aat:300008680"
        ],
        "id": 2459325,
        "name:xx": "Little Pond"
      }
    },
    {
      "geometry": {
        "type": "Point",
        "coordinates": [
          -74.6833,
          41.4667
        ]
      },
      "type": "Feature",
      "properties": {
        "hierarchy": [
          "tgn:2459326",
          "tgn:1000001",
          "tgn:7012149",
          "tgn:1002751",
          "tgn:7007568",
          "tgn:7029392"
        ],
        "placetype": [
          "aat:300008680"
        ],
        "id": 2459326,
        "name:xx": "Little Pond"
      }
    },
    {
      "geometry": {
        "type": "Point",
        "coordinates": [
          -73.55,
          41.4667
        ]
      },
      "type": "Feature",
      "properties": {
        "hierarchy": [
          "tgn:2459327",
          "tgn:1000001",
          "tgn:7012149",
          "tgn:1002810",
          "tgn:7007568",
          "tgn:7029392"
        ],
        "placetype": [
          "aat:300008680"
        ],
        "id": 2459327,
        "name:xx": "Little Pond"
      }
    },
    {
      "geometry": {
        "type": "Point",
        "coordinates": [
          -74.7333,
          42.0333
        ]
      },
      "type": "Feature",
      "properties": {
        "hierarchy": [
          "tgn:2459328",
          "tgn:1000001",
          "tgn:1002328",
          "tgn:7012149",
          "tgn:7007568",
          "tgn:7029392"
        ],
        "placetype": [
          "aat:300008680"
        ],
        "id": 2459328,
        "name:xx": "Little Pond"
      }
    },
    {
      "geometry": {
        "type": "Point",
        "coordinates": [
          -77.6167,
          43.2667
        ]
      },
      "type": "Feature",
      "properties": {
        "hierarchy": [
          "tgn:2459329",
          "tgn:1000001",
          "tgn:7012149",
          "tgn:1002681",
          "tgn:7007568",
          "tgn:7029392"
        ],
        "placetype": [
          "aat:300008680"
        ],
        "id": 2459329,
        "name:xx": "Little Pond"
      }
    }
  ]
}
