{
  "geometry": {
    "type": "Point",
    "coordinates": [
      -70.7333,
      41.4833
    ]
  },
  "type": "Feature",
  "properties": {
    "hierarchy": [
      "tgn:2778400",
      "tgn:1000001",
      "tgn:1002344",
      "tgn:7012149",
      "tgn:7007517",
      "tgn:7029392"
    ],
    "placetype": [
      "aat:300008761"
    ],
    "id": 2778400,
    "name:xx": "Witches Glen"
  }
}
