{
  "geometry": {
    "type": "Point",
    "coordinates": [
      -77.3833,
      42.5667
    ]
  },
  "type": "Feature",
  "properties": {
    "hierarchy": [
      "tgn:2440520",
      "tgn:1000001",
      "tgn:7012149",
      "tgn:7007568",
      "tgn:7029392"
    ],
    "placetype": [
      "aat:300008798"
    ],
    "id": 2440520,
    "name:xx": "Knapp Hill"
  }
}
