{
  "geometry": {
    "type": "Point",
    "coordinates": [
      -98.2167,
      39.3667
    ]
  },
  "type": "Feature",
  "properties": {
    "hierarchy": [
      "tgn:2486457",
      "tgn:1000001",
      "tgn:7012149",
      "tgn:2000721",
      "tgn:7007254",
      "tgn:7029392"
    ],
    "placetype": [
      "aat:300008706"
    ],
    "id": 2486457,
    "name:xx": "Leban Creek"
  }
}
