{
  "geometry": {
    "type": "Point",
    "coordinates": [
      -91.7167,
      33.9333
    ]
  },
  "type": "Feature",
  "properties": {
    "hierarchy": [
      "tgn:2348653",
      "tgn:1000001",
      "tgn:7016172",
      "tgn:7012149",
      "tgn:2000144",
      "tgn:7029392"
    ],
    "placetype": [
      "aat:300008905"
    ],
    "id": 2348653,
    "name:xx": "Gibson Brake"
  }
}
