{
  "geometry": {
    "type": "Point",
    "coordinates": [
      -105.0167,
      41.7167
    ]
  },
  "type": "Feature",
  "properties": {
    "hierarchy": [
      "tgn:2617225",
      "tgn:1000001",
      "tgn:7012149",
      "tgn:2002380",
      "tgn:7007923",
      "tgn:7029392"
    ],
    "placetype": [
      "aat:300008697"
    ],
    "id": 2617225,
    "name:xx": "Richeau Spring"
  }
}
