{
  "geometry": {
    "type": "Point",
    "coordinates": [
      -100.316667,
      22.75
    ]
  },
  "type": "Feature",
  "properties": {
    "hierarchy": [
      "tgn:7426151",
      "tgn:1000001",
      "tgn:7005594",
      "tgn:7005560",
      "tgn:7029392"
    ],
    "placetype": [
      "aat:300008699"
    ],
    "id": 7426151,
    "name:xx": "Cien Tinajas, Río"
  }
}
