{
  "type": "FeatureCollection",
  "features": [
    {
      "geometry": {
        "type": "Point",
        "coordinates": [
          -90.0833,
          47.9667
        ]
      },
      "type": "Feature",
      "properties": {
        "hierarchy": [
          "tgn:2158440",
          "tgn:1000001",
          "tgn:2001014",
          "tgn:7012149",
          "tgn:7007521",
          "tgn:7029392"
        ],
        "placetype": [
          "aat:300008706"
        ],
        "id": 2158440,
        "name:xx": "Beaverdam Creek"
      }
    },
    {
      "geometry": {
        "type": "Point",
        "coordinates": [
          -88.55,
          30.9833
        ]
      },
      "type": "Feature",
      "properties": {
        "hierarchy": [
          "tgn:2158441",
          "tgn:1000001",
          "tgn:7012149",
          "tgn:7007522",
          "tgn:7029392"
        ],
        "placetype": [
          "aat:300008706"
        ],
        "id": 2158441,
        "name:xx": "Beaverdam Creek"
      }
    },
    {
      "geometry": {
        "type": "Point",
        "coordinates": [
          -89.4833,
          31.9833
        ]
      },
      "type": "Feature",
      "properties": {
        "hierarchy": [
          "tgn:2158442",
          "tgn:1000001",
          "tgn:7012149",
          "tgn:2001150",
          "tgn:7007522",
          "tgn:7029392"
        ],
        "placetype": [
          "aat:300008706"
        ],
        "id": 2158442,
        "name:xx": "Beaverdam Creek"
      }
    },
    {
      "geometry": {
        "type": "Point",
        "coordinates": [
          -90.35,
          32.0667
        ]
      },
      "type": "Feature",
      "properties": {
        "hierarchy": [
          "tgn:2158443",
          "tgn:1000001",
          "tgn:7012149",
          "tgn:2001110",
          "tgn:7007522",
          "tgn:7029392"
        ],
        "placetype": [
          "aat:300008706"
        ],
        "id": 2158443,
        "name:xx": "Beaverdam Creek"
      }
    },
    {
      "geometry": {
        "type": "Point",
        "coordinates": [
          -89.5333,
          30.8667
        ]
      },
      "type": "Feature",
      "properties": {
        "hierarchy": [
          "tgn:2158444",
          "tgn:1000001",
          "tgn:7012149",
          "tgn:2001140",
          "tgn:7007522",
          "tgn:7029392"
        ],
        "placetype": [
          "aat:300008706"
        ],
        "id": 2158444,
        "name:xx": "Beaverdam Creek"
      }
    },
    {
      "geometry": {
        "type": "Point",
        "coordinates": [
          -88.8833,
          31.8667
        ]
      },
      "type": "Feature",
      "properties": {
        "hierarchy": [
          "tgn:2158445",
          "tgn:1000001",
          "tgn:2001097",
          "tgn:7012149",
          "tgn:7007522",
          "tgn:7029392"
        ],
        "placetype": [
          "aat:300008706"
        ],
        "id": 2158445,
        "name:xx": "Beaverdam Creek"
      }
    },
    {
      "geometry": {
        "type": "Point",
        "coordinates": [
          -88.7333,
          34.9667
        ]
      },
      "type": "Feature",
      "properties": {
        "hierarchy": [
          "tgn:2158446",
          "tgn:2001087",
          "tgn:1000001",
          "tgn:7012149",
          "tgn:7007522",
          "tgn:7029392"
        ],
        "placetype": [
          "aat:300008706"
        ],
        "id": 2158446,
        "name:xx": "Beaverdam Creek"
      }
    },
    {
      "geometry": {
        "type": "Point",
        "coordinates": [
          -89.4833,
          31.2
        ]
      },
      "type": "Feature",
      "properties": {
        "hierarchy": [
          "tgn:2158447",
          "tgn:1000001",
          "tgn:7012149",
          "tgn:2001122",
          "tgn:7007522",
          "tgn:7029392"
        ],
        "placetype": [
          "aat:300008706"
        ],
        "id": 2158447,
        "name:xx": "Beaverdam Creek"
      }
    },
    {
      "geometry": {
        "type": "Point",
        "coordinates": [
          -93.4,
          38.7833
        ]
      },
      "type": "Feature",
      "properties": {
        "hierarchy": [
          "tgn:2158448",
          "tgn:1000001",
          "tgn:7012149",
          "tgn:2001229",
          "tgn:7007523",
          "tgn:7029392"
        ],
        "placetype": [
          "aat:300008706"
        ],
        "id": 2158448,
        "name:xx": "Beaverdam Creek"
      }
    },
    {
      "geometry": {
        "type": "Point",
        "coordinates": [
          -92.0333,
          39.0833
        ]
      },
      "type": "Feature",
      "properties": {
        "hierarchy": [
          "tgn:2158449",
          "tgn:1002158",
          "tgn:1000001",
          "tgn:7012149",
          "tgn:7007523",
          "tgn:7029392"
        ],
        "placetype": [
          "aat:300008706"
        ],
        "id": 2158449,
        "name:xx": "Beaverdam Creek"
      }
    }
  ]
}
