{
  "geometry": {
    "type": "Point",
    "coordinates": [
      -80.4833,
      38.8833
    ]
  },
  "type": "Feature",
  "properties": {
    "hierarchy": [
      "tgn:2418210",
      "tgn:1000001",
      "tgn:7012149",
      "tgn:2002271",
      "tgn:7013961",
      "tgn:7029392"
    ],
    "placetype": [
      "aat:300008347"
    ],
    "id": 2418210,
    "name:xx": "Jacksonville"
  }
}
