{
  "type": "FeatureCollection",
  "features": [
    {
      "geometry": {
        "type": "Point",
        "coordinates": [
          -106.2,
          28.083333
        ]
      },
      "type": "Feature",
      "properties": {
        "hierarchy": [
          "tgn:7367730",
          "tgn:7005581",
          "tgn:1000001",
          "tgn:7005560",
          "tgn:7029392"
        ],
        "placetype": [
          "aat:300008347"
        ],
        "id": 7367730,
        "name:xx": "El Salitre"
      }
    },
    {
      "geometry": {
        "type": "Point",
        "coordinates": [
          -105.766667,
          27.566667
        ]
      },
      "type": "Feature",
      "properties": {
        "hierarchy": [
          "tgn:7367731",
          "tgn:7005581",
          "tgn:1000001",
          "tgn:7005560",
          "tgn:7029392"
        ],
        "placetype": [
          "aat:300008347"
        ],
        "id": 7367731,
        "name:xx": "El Salitre"
      }
    },
    {
      "geometry": {
        "type": "Point",
        "coordinates": [
          -100.316667,
          27.3
        ]
      },
      "type": "Feature",
      "properties": {
        "hierarchy": [
          "tgn:7367732",
          "tgn:1000001",
          "tgn:7005589",
          "tgn:7005560",
          "tgn:7029392"
        ],
        "placetype": [
          "aat:300008347"
        ],
        "id": 7367732,
        "name:xx": "El Salitre"
      }
    },
    {
      "geometry": {
        "type": "Point",
        "coordinates": [
          -106.266667,
          27.1
        ]
      },
      "type": "Feature",
      "properties": {
        "hierarchy": [
          "tgn:7367733",
          "tgn:7005581",
          "tgn:1000001",
          "tgn:7005560",
          "tgn:7029392"
        ],
        "placetype": [
          "aat:300008347"
        ],
        "id": 7367733,
        "name:xx": "El Salitre"
      }
    },
    {
      "geometry": {
        "type": "Point",
        "coordinates": [
          -101.433333,
          26.383333
        ]
      },
      "type": "Feature",
      "properties": {
        "hierarchy": [
          "tgn:7367734",
          "tgn:1001853",
          "tgn:1000001",
          "tgn:7005560",
          "tgn:7029392"
        ],
        "placetype": [
          "aat:300008347"
        ],
        "id": 7367734,
        "name:xx": "El Salitre"
      }
    },
    {
      "geometry": {
        "type": "Point",
        "coordinates": [
          -106.116667,
          25.85
        ]
      },
      "type": "Feature",
      "properties": {
        "hierarchy": [
          "tgn:7367735",
          "tgn:7005583",
          "tgn:1000001",
          "tgn:7005560",
          "tgn:7029392"
        ],
        "placetype": [
          "aat:300008347"
        ],
        "id": 7367735,
        "name:xx": "El Salitre"
      }
    },
    {
      "geometry": {
        "type": "Point",
        "coordinates": [
          -108.166667,
          25.416667
        ]
      },
      "type": "Feature",
      "properties": {
        "hierarchy": [
          "tgn:7367736",
          "tgn:1000001",
          "tgn:7005595",
          "tgn:7005560",
          "tgn:7029392"
        ],
        "placetype": [
          "aat:300008347"
        ],
        "id": 7367736,
        "name:xx": "El Salitre"
      }
    },
    {
      "geometry": {
        "type": "Point",
        "coordinates": [
          -99.783333,
          25.4
        ]
      },
      "type": "Feature",
      "properties": {
        "hierarchy": [
          "tgn:7367737",
          "tgn:1000001",
          "tgn:7005589",
          "tgn:7005560",
          "tgn:7029392"
        ],
        "placetype": [
          "aat:300008347"
        ],
        "id": 7367737,
        "name:xx": "El Salitre"
      }
    },
    {
      "geometry": {
        "type": "Point",
        "coordinates": [
          -105.283333,
          25.25
        ]
      },
      "type": "Feature",
      "properties": {
        "hierarchy": [
          "tgn:7367738",
          "tgn:7005583",
          "tgn:1000001",
          "tgn:7005560",
          "tgn:7029392"
        ],
        "placetype": [
          "aat:300008347"
        ],
        "id": 7367738,
        "name:xx": "El Salitre"
      }
    },
    {
      "geometry": {
        "type": "Point",
        "coordinates": [
          -99.7675,
          24.970278
        ]
      },
      "type": "Feature",
      "properties": {
        "hierarchy": [
          "tgn:7367739",
          "tgn:1000001",
          "tgn:7005589",
          "tgn:7005560",
          "tgn:7029392"
        ],
        "placetype": [
          "aat:300008347"
        ],
        "id": 7367739,
        "name:xx": "El Salitre"
      }
    }
  ]
}
