{
  "type": "FeatureCollection",
  "features": [
    {
      "geometry": {
        "type": "Point",
        "coordinates": [
          -76.2667,
          43.8333
        ]
      },
      "type": "Feature",
      "properties": {
        "hierarchy": [
          "tgn:2609280",
          "tgn:1000001",
          "tgn:7012149",
          "tgn:1002518",
          "tgn:7007568",
          "tgn:7029392"
        ],
        "placetype": [
          "aat:300132316"
        ],
        "id": 2609280,
        "name:xx": "Ray Bay"
      }
    },
    {
      "geometry": {
        "type": "Point",
        "coordinates": [
          -85.6833,
          36.3667
        ]
      },
      "type": "Feature",
      "properties": {
        "hierarchy": [
          "tgn:2609281",
          "tgn:1000001",
          "tgn:7012149",
          "tgn:2001880",
          "tgn:7007825",
          "tgn:7029392"
        ],
        "placetype": [
          "aat:300008798"
        ],
        "id": 2609281,
        "name:xx": "Ray Bluff Knob"
      }
    },
    {
      "geometry": {
        "type": "Point",
        "coordinates": [
          -91.3,
          35.7333
        ]
      },
      "type": "Feature",
      "properties": {
        "hierarchy": [
          "tgn:2609282",
          "tgn:1000001",
          "tgn:7016172",
          "tgn:7012149",
          "tgn:2000138",
          "tgn:7029392"
        ],
        "placetype": [
          "aat:300008905"
        ],
        "id": 2609282,
        "name:xx": "Ray Brake"
      }
    },
    {
      "geometry": {
        "type": "Point",
        "coordinates": [
          -85.8333,
          33.4
        ]
      },
      "type": "Feature",
      "properties": {
        "hierarchy": [
          "tgn:2609283",
          "tgn:7002659",
          "tgn:1000001",
          "tgn:2000013",
          "tgn:7012149",
          "tgn:7029392"
        ],
        "placetype": [
          "aat:300008699"
        ],
        "id": 2609283,
        "name:xx": "Ray Branch"
      }
    },
    {
      "geometry": {
        "type": "Point",
        "coordinates": [
          -87.8833,
          34.3833
        ]
      },
      "type": "Feature",
      "properties": {
        "hierarchy": [
          "tgn:2609284",
          "tgn:7002659",
          "tgn:1000001",
          "tgn:7012149",
          "tgn:2000029",
          "tgn:7029392"
        ],
        "placetype": [
          "aat:300008699"
        ],
        "id": 2609284,
        "name:xx": "Ray Branch"
      }
    },
    {
      "geometry": {
        "type": "Point",
        "coordinates": [
          -94.1833,
          34.8
        ]
      },
      "type": "Feature",
      "properties": {
        "hierarchy": [
          "tgn:2609285",
          "tgn:1000001",
          "tgn:7016172",
          "tgn:7012149",
          "tgn:2000168",
          "tgn:7029392"
        ],
        "placetype": [
          "aat:300008699"
        ],
        "id": 2609285,
        "name:xx": "Ray Branch"
      }
    },
    {
      "geometry": {
        "type": "Point",
        "coordinates": [
          -83.0333,
          30.8833
        ]
      },
      "type": "Feature",
      "properties": {
        "hierarchy": [
          "tgn:2609286",
          "tgn:1000001",
          "tgn:7012149",
          "tgn:2000383",
          "tgn:7007248",
          "tgn:7029392"
        ],
        "placetype": [
          "aat:300008699"
        ],
        "id": 2609286,
        "name:xx": "Ray Branch"
      }
    },
    {
      "geometry": {
        "type": "Point",
        "coordinates": [
          -82.5833,
          37.4333
        ]
      },
      "type": "Feature",
      "properties": {
        "hierarchy": [
          "tgn:2609287",
          "tgn:1000001",
          "tgn:7012149",
          "tgn:2000837",
          "tgn:7007255",
          "tgn:7029392"
        ],
        "placetype": [
          "aat:300008699"
        ],
        "id": 2609287,
        "name:xx": "Ray Branch"
      }
    },
    {
      "geometry": {
        "type": "Point",
        "coordinates": [
          -88.4833,
          36.75
        ]
      },
      "type": "Feature",
      "properties": {
        "hierarchy": [
          "tgn:2609288",
          "tgn:1000001",
          "tgn:7012149",
          "tgn:2000792",
          "tgn:7007255",
          "tgn:7029392"
        ],
        "placetype": [
          "aat:300008699"
        ],
        "id": 2609288,
        "name:xx": "Ray Branch"
      }
    },
    {
      "geometry": {
        "type": "Point",
        "coordinates": [
          -88.15,
          34.4167
        ]
      },
      "type": "Feature",
      "properties": {
        "hierarchy": [
          "tgn:2609289",
          "tgn:1000001",
          "tgn:7012149",
          "tgn:2001114",
          "tgn:7007522",
          "tgn:7029392"
        ],
        "placetype": [
          "aat:300008699"
        ],
        "id": 2609289,
        "name:xx": "Ray Branch"
      }
    }
  ]
}
