{
  "type": "FeatureCollection",
  "features": [
    {
      "geometry": {
        "type": "Point",
        "coordinates": [
          -78.3833,
          40.4667
        ]
      },
      "type": "Feature",
      "properties": {
        "hierarchy": [
          "tgn:2089910",
          "tgn:1000001",
          "tgn:1002185",
          "tgn:7012149",
          "tgn:7007710",
          "tgn:7029392"
        ],
        "placetype": [
          "aat:300008347"
        ],
        "id": 2089910,
        "name:xx": "Lakemont"
      }
    },
    {
      "geometry": {
        "type": "Point",
        "coordinates": [
          -75.65,
          41.85
        ]
      },
      "type": "Feature",
      "properties": {
        "hierarchy": [
          "tgn:2089914",
          "tgn:1000001",
          "tgn:7012149",
          "tgn:1002932",
          "tgn:7007710",
          "tgn:7029392"
        ],
        "placetype": [
          "aat:300008347"
        ],
        "id": 2089914,
        "name:xx": "Lakeside"
      }
    },
    {
      "geometry": {
        "type": "Point",
        "coordinates": [
          -75.6167,
          41.85
        ]
      },
      "type": "Feature",
      "properties": {
        "hierarchy": [
          "tgn:2089916",
          "tgn:1000001",
          "tgn:7012149",
          "tgn:1002932",
          "tgn:7007710",
          "tgn:7029392"
        ],
        "placetype": [
          "aat:300008347"
        ],
        "id": 2089916,
        "name:xx": "Lakeview"
      }
    },
    {
      "geometry": {
        "type": "Point",
        "coordinates": [
          -76.8,
          40.2667
        ]
      },
      "type": "Feature",
      "properties": {
        "hierarchy": [
          "tgn:2089917",
          "tgn:1000001",
          "tgn:1002318",
          "tgn:7012149",
          "tgn:7007710",
          "tgn:7029392"
        ],
        "placetype": [
          "aat:300008347"
        ],
        "id": 2089917,
        "name:xx": "Lakeview Heights"
      }
    },
    {
      "geometry": {
        "type": "Point",
        "coordinates": [
          -75.2667,
          41.4333
        ]
      },
      "type": "Feature",
      "properties": {
        "hierarchy": [
          "tgn:2089918",
          "tgn:1000001",
          "tgn:7012149",
          "tgn:1003008",
          "tgn:7007710",
          "tgn:7029392"
        ],
        "placetype": [
          "aat:300008347"
        ],
        "id": 2089918,
        "name:xx": "Lakeville"
      }
    }
  ]
}
