{
  "geometry": {
    "type": "Point",
    "coordinates": [
      -85.8167,
      11.4667
    ]
  },
  "type": "Feature",
  "properties": {
    "hierarchy": [
      "tgn:1018775",
      "tgn:1000742",
      "tgn:1000001",
      "tgn:7005562",
      "tgn:7029392"
    ],
    "placetype": [
      "aat:300008347"
    ],
    "id": 1018775,
    "name:xx": "San Jorge"
  }
}
