{
  "geometry": {
    "type": "Point",
    "coordinates": [
      -87.2167,
      34.0667
    ]
  },
  "type": "Feature",
  "properties": {
    "hierarchy": [
      "tgn:2288524",
      "tgn:7002659",
      "tgn:1000001",
      "tgn:7012149",
      "tgn:2000066",
      "tgn:7029392"
    ],
    "placetype": [
      "aat:300008706"
    ],
    "id": 2288524,
    "name:xx": "Dismal Creek"
  }
}
