{
  "geometry": {
    "type": "Point",
    "coordinates": [
      78.816109,
      24.73943
    ]
  },
  "type": "Feature",
  "properties": {
    "hierarchy": [
      "tgn:7584832",
      "tgn:1000004",
      "tgn:7000198",
      "tgn:1001894",
      "tgn:7029392"
    ],
    "placetype": [
      "aat:300008347"
    ],
    "name:en": "Mahārājpura",
    "id": 7584832
  }
}
