{
  "geometry": {
    "type": "Point",
    "coordinates": [
      -123.3333,
      47.1833
    ]
  },
  "type": "Feature",
  "properties": {
    "hierarchy": [
      "tgn:2265148",
      "tgn:1000001",
      "tgn:7012149",
      "tgn:1002645",
      "tgn:7007920",
      "tgn:7029392"
    ],
    "placetype": [
      "aat:300008905"
    ],
    "id": 2265148,
    "name:xx": "Cranberry Marsh"
  }
}
