{
  "geometry": {
    "type": "Point",
    "coordinates": [
      -105.3833,
      33.4833
    ]
  },
  "type": "Feature",
  "properties": {
    "hierarchy": [
      "tgn:2324189",
      "tgn:1000001",
      "tgn:7012149",
      "tgn:2001442",
      "tgn:7007566",
      "tgn:7029392"
    ],
    "placetype": [
      "aat:300008746"
    ],
    "id": 2324189,
    "name:xx": "Feather Cave"
  }
}
