{
  "geometry": {
    "type": "Point",
    "coordinates": [
      50.8167,
      51.1833
    ]
  },
  "type": "Feature",
  "properties": {
    "hierarchy": [
      "tgn:1058308",
      "tgn:1000004",
      "tgn:7011457",
      "tgn:7014786",
      "tgn:7029392"
    ],
    "placetype": [
      "aat:300008347"
    ],
    "id": 1058308,
    "name:xx": "Perem'otnoje"
  }
}
