{
  "geometry": {
    "type": "Point",
    "coordinates": [
      136.4667,
      35.3667
    ]
  },
  "type": "Feature",
  "properties": {
    "hierarchy": [
      "tgn:1081243",
      "tgn:7000895",
      "tgn:1000004",
      "tgn:1000977",
      "tgn:1000120",
      "tgn:7029392"
    ],
    "placetype": [
      "aat:300008347"
    ],
    "id": 1081243,
    "name:xx": "Sekigahara"
  }
}
