{
  "geometry": {
    "type": "Point",
    "coordinates": [
      -75.8667,
      38.35
    ]
  },
  "type": "Feature",
  "properties": {
    "hierarchy": [
      "tgn:2596249",
      "tgn:1000001",
      "tgn:7012149",
      "tgn:7007516",
      "tgn:7029392"
    ],
    "placetype": [
      "aat:300008905"
    ],
    "id": 2596249,
    "name:xx": "Pound Marsh"
  }
}
