{
  "geometry": {
    "type": "Point",
    "coordinates": [
      121.6239,
      25.2402
    ]
  },
  "type": "Feature",
  "properties": {
    "hierarchy": [
      "tgn:7497004",
      "tgn:1000004",
      "tgn:1000454",
      "tgn:1000141",
      "tgn:7029392"
    ],
    "placetype": [
      "aat:300008187"
    ],
    "id": 7497004,
    "name:xx": "Yuntai Leyuan"
  }
}
