{
  "type": "FeatureCollection",
  "features": [
    {
      "geometry": {
        "type": "Point",
        "coordinates": [
          -114.3333,
          45.45
        ]
      },
      "type": "Feature",
      "properties": {
        "hierarchy": [
          "tgn:2188810",
          "tgn:1000001",
          "tgn:7012149",
          "tgn:2000481",
          "tgn:7007250",
          "tgn:7029392"
        ],
        "placetype": [
          "aat:300008706"
        ],
        "id": 2188810,
        "name:xx": "Boulder Creek"
      }
    },
    {
      "geometry": {
        "type": "Point",
        "coordinates": [
          -115.8,
          47.4167
        ]
      },
      "type": "Feature",
      "properties": {
        "hierarchy": [
          "tgn:2188811",
          "tgn:1000001",
          "tgn:7012149",
          "tgn:2000491",
          "tgn:7007250",
          "tgn:7029392"
        ],
        "placetype": [
          "aat:300008706"
        ],
        "id": 2188811,
        "name:xx": "Boulder Creek"
      }
    },
    {
      "geometry": {
        "type": "Point",
        "coordinates": [
          -116.4667,
          47.8333
        ]
      },
      "type": "Feature",
      "properties": {
        "hierarchy": [
          "tgn:2188812",
          "tgn:1000001",
          "tgn:7012149",
          "tgn:2000479",
          "tgn:7007250",
          "tgn:7029392"
        ],
        "placetype": [
          "aat:300008706"
        ],
        "id": 2188812,
        "name:xx": "Boulder Creek"
      }
    },
    {
      "geometry": {
        "type": "Point",
        "coordinates": [
          -113.0667,
          44.0667
        ]
      },
      "type": "Feature",
      "properties": {
        "hierarchy": [
          "tgn:2188813",
          "tgn:1000001",
          "tgn:2000463",
          "tgn:7012149",
          "tgn:7007250",
          "tgn:7029392"
        ],
        "placetype": [
          "aat:300008706"
        ],
        "id": 2188813,
        "name:xx": "Boulder Creek"
      }
    },
    {
      "geometry": {
        "type": "Point",
        "coordinates": [
          -114.7667,
          46.6667
        ]
      },
      "type": "Feature",
      "properties": {
        "hierarchy": [
          "tgn:2188814",
          "tgn:1000001",
          "tgn:7012149",
          "tgn:7007250",
          "tgn:7029392"
        ],
        "placetype": [
          "aat:300008706"
        ],
        "id": 2188814,
        "name:xx": "Boulder Creek"
      }
    },
    {
      "geometry": {
        "type": "Point",
        "coordinates": [
          -114.5,
          43.8333
        ]
      },
      "type": "Feature",
      "properties": {
        "hierarchy": [
          "tgn:2188815",
          "tgn:1000001",
          "tgn:2000458",
          "tgn:7012149",
          "tgn:7007250",
          "tgn:7029392"
        ],
        "placetype": [
          "aat:300008706"
        ],
        "id": 2188815,
        "name:xx": "Boulder Creek"
      }
    },
    {
      "geometry": {
        "type": "Point",
        "coordinates": [
          -115.7,
          43.85
        ]
      },
      "type": "Feature",
      "properties": {
        "hierarchy": [
          "tgn:2188816",
          "tgn:1000001",
          "tgn:2000459",
          "tgn:7012149",
          "tgn:7007250",
          "tgn:7029392"
        ],
        "placetype": [
          "aat:300008706"
        ],
        "id": 2188816,
        "name:xx": "Boulder Creek"
      }
    },
    {
      "geometry": {
        "type": "Point",
        "coordinates": [
          -116.7167,
          45.0333
        ]
      },
      "type": "Feature",
      "properties": {
        "hierarchy": [
          "tgn:2188817",
          "tgn:2000453",
          "tgn:1000001",
          "tgn:7012149",
          "tgn:7007250",
          "tgn:7029392"
        ],
        "placetype": [
          "aat:300008706"
        ],
        "id": 2188817,
        "name:xx": "Boulder Creek"
      }
    },
    {
      "geometry": {
        "type": "Point",
        "coordinates": [
          -116.3833,
          46.7167
        ]
      },
      "type": "Feature",
      "properties": {
        "hierarchy": [
          "tgn:2188818",
          "tgn:1000001",
          "tgn:7012149",
          "tgn:2000480",
          "tgn:7007250",
          "tgn:7029392"
        ],
        "placetype": [
          "aat:300008706"
        ],
        "id": 2188818,
        "name:xx": "Boulder Creek"
      }
    },
    {
      "geometry": {
        "type": "Point",
        "coordinates": [
          -116.1667,
          48.5167
        ]
      },
      "type": "Feature",
      "properties": {
        "hierarchy": [
          "tgn:2188819",
          "tgn:1000001",
          "tgn:2000462",
          "tgn:7012149",
          "tgn:7007250",
          "tgn:7029392"
        ],
        "placetype": [
          "aat:300008706"
        ],
        "id": 2188819,
        "name:xx": "Boulder Creek"
      }
    }
  ]
}
