{
  "geometry": {
    "type": "Point",
    "coordinates": [
      116.8167,
      1.0333
    ]
  },
  "type": "Feature",
  "properties": {
    "hierarchy": [
      "tgn:1078189",
      "tgn:1000004",
      "tgn:1001339",
      "tgn:1000116",
      "tgn:7029392"
    ],
    "placetype": [
      "aat:300008347"
    ],
    "id": 1078189,
    "name:xx": "Muarawahau"
  }
}
