{
  "geometry": {
    "type": "Point",
    "coordinates": [
      78.980029,
      24.19617
    ]
  },
  "type": "Feature",
  "properties": {
    "hierarchy": [
      "tgn:7582314",
      "tgn:1000004",
      "tgn:7000198",
      "tgn:1001894",
      "tgn:7029392"
    ],
    "placetype": [
      "aat:300008347"
    ],
    "name:en": "Mālkhowān",
    "id": 7582314
  }
}
