{
  "geometry": {
    "type": "Point",
    "coordinates": [
      -122.5833,
      45.3667
    ]
  },
  "type": "Feature",
  "properties": {
    "hierarchy": [
      "tgn:2240592",
      "tgn:1000001",
      "tgn:1002270",
      "tgn:7012149",
      "tgn:7007708",
      "tgn:7029392"
    ],
    "placetype": [
      "aat:300008680"
    ],
    "id": 2240592,
    "name:xx": "Clackamette Lake"
  }
}
