{
  "type": "FeatureCollection",
  "features": [
    {
      "geometry": {
        "type": "Point",
        "coordinates": [
          -69.85,
          -25.3
        ]
      },
      "type": "Feature",
      "properties": {
        "hierarchy": [
          "tgn:7279980",
          "tgn:7016598",
          "tgn:1000049",
          "tgn:1000002",
          "tgn:7029392"
        ],
        "placetype": [
          "aat:300007783"
        ],
        "id": 7279980,
        "name:xx": "Refresco"
      }
    },
    {
      "geometry": {
        "type": "Point",
        "coordinates": [
          -69.766667,
          -23.416667
        ]
      },
      "type": "Feature",
      "properties": {
        "hierarchy": [
          "tgn:7279981",
          "tgn:7016598",
          "tgn:1000049",
          "tgn:1000002",
          "tgn:7029392"
        ],
        "placetype": [
          "aat:300008347"
        ],
        "id": 7279981,
        "name:xx": "Refresco"
      }
    },
    {
      "geometry": {
        "type": "Point",
        "coordinates": [
          -75.7,
          -46.716667
        ]
      },
      "type": "Feature",
      "properties": {
        "hierarchy": [
          "tgn:7279982",
          "tgn:1001623",
          "tgn:1000049",
          "tgn:1000002",
          "tgn:7029392"
        ],
        "placetype": [
          "aat:300386846"
        ],
        "id": 7279982,
        "name:xx": "Rees, Punta"
      }
    },
    {
      "geometry": {
        "type": "Point",
        "coordinates": [
          -70.983333,
          -54.15
        ]
      },
      "type": "Feature",
      "properties": {
        "hierarchy": [
          "tgn:7279983",
          "tgn:1001702",
          "tgn:1000049",
          "tgn:1000002",
          "tgn:7029392"
        ],
        "placetype": [
          "aat:300008791"
        ],
        "id": 7279983,
        "name:xx": "Rees, Isla"
      }
    },
    {
      "geometry": {
        "type": "Point",
        "coordinates": [
          -75.65,
          -46.583333
        ]
      },
      "type": "Feature",
      "properties": {
        "hierarchy": [
          "tgn:7279984",
          "tgn:1001623",
          "tgn:1000049",
          "tgn:1000002",
          "tgn:7029392"
        ],
        "placetype": [
          "aat:300008791"
        ],
        "id": 7279984,
        "name:xx": "Rees, Isla"
      }
    },
    {
      "geometry": {
        "type": "Point",
        "coordinates": [
          -67.05,
          -55.066667
        ]
      },
      "type": "Feature",
      "properties": {
        "hierarchy": [
          "tgn:7279985",
          "tgn:1001702",
          "tgn:1000049",
          "tgn:1000002",
          "tgn:7029392"
        ],
        "placetype": [
          "aat:300386846"
        ],
        "id": 7279985,
        "name:xx": "Rees, Cabo"
      }
    },
    {
      "geometry": {
        "type": "Point",
        "coordinates": [
          -73.716667,
          -53.333333
        ]
      },
      "type": "Feature",
      "properties": {
        "hierarchy": [
          "tgn:7279986",
          "tgn:1001702",
          "tgn:1000049",
          "tgn:1000002",
          "tgn:7029392"
        ],
        "placetype": [
          "aat:300008791"
        ],
        "id": 7279986,
        "name:xx": "Redwood, Isla"
      }
    },
    {
      "geometry": {
        "type": "Point",
        "coordinates": [
          -72.783333,
          -53.3
        ]
      },
      "type": "Feature",
      "properties": {
        "hierarchy": [
          "tgn:7279987",
          "tgn:1001702",
          "tgn:1000049",
          "tgn:1000002",
          "tgn:7029392"
        ],
        "placetype": [
          "aat:300008795"
        ],
        "id": 7279987,
        "name:xx": "Redondo, Monte"
      }
    },
    {
      "geometry": {
        "type": "Point",
        "coordinates": [
          -70.966667,
          -35.033333
        ]
      },
      "type": "Feature",
      "properties": {
        "hierarchy": [
          "tgn:7279988",
          "tgn:1001705",
          "tgn:1000049",
          "tgn:1000002",
          "tgn:7029392"
        ],
        "placetype": [
          "aat:300008795"
        ],
        "id": 7279988,
        "name:xx": "Redondo, Monte"
      }
    },
    {
      "geometry": {
        "type": "Point",
        "coordinates": [
          -73.716667,
          -52.85
        ]
      },
      "type": "Feature",
      "properties": {
        "hierarchy": [
          "tgn:7279989",
          "tgn:1001702",
          "tgn:1000049",
          "tgn:1000002",
          "tgn:7029392"
        ],
        "placetype": [
          "aat:300008791"
        ],
        "id": 7279989,
        "name:xx": "Redondo, Islote"
      }
    }
  ]
}
