{
  "geometry": {
    "type": "Point",
    "coordinates": [
      140.1833,
      37.1167
    ]
  },
  "type": "Feature",
  "properties": {
    "hierarchy": [
      "tgn:7004814",
      "tgn:1000976",
      "tgn:1000004",
      "tgn:7000893",
      "tgn:1000120",
      "tgn:7029392"
    ],
    "placetype": [
      "aat:300008347"
    ],
    "id": 7004814,
    "name:xx": "Shirakawa"
  }
}
