{
  "geometry": {
    "type": "Point",
    "coordinates": [
      -110.15,
      33.8333
    ]
  },
  "type": "Feature",
  "properties": {
    "hierarchy": [
      "tgn:2557769",
      "tgn:1000001",
      "tgn:7006451",
      "tgn:2000093",
      "tgn:7012149",
      "tgn:7029392"
    ],
    "placetype": [
      "aat:300006191"
    ],
    "id": 2557769,
    "name:xx": "Old Road Tank"
  }
}
