{
  "geometry": {
    "type": "Point",
    "coordinates": [
      -105.0833,
      44.9667
    ]
  },
  "type": "Feature",
  "properties": {
    "hierarchy": [
      "tgn:2667850",
      "tgn:1000001",
      "tgn:7012149",
      "tgn:7007923",
      "tgn:7029392"
    ],
    "placetype": [
      "aat:300008706"
    ],
    "id": 2667850,
    "name:xx": "Skunk Creek"
  }
}
