{
  "geometry": {
    "type": "Point",
    "coordinates": [
      -100.261111,
      24.4175
    ]
  },
  "type": "Feature",
  "properties": {
    "hierarchy": [
      "tgn:7418485",
      "tgn:1000001",
      "tgn:7005589",
      "tgn:7005560",
      "tgn:7029392"
    ],
    "placetype": [
      "aat:300008347"
    ],
    "id": 7418485,
    "name:es": "San José de la Hoya"
  }
}
