{
  "geometry": {
    "type": "Point",
    "coordinates": [
      -108.6667,
      38.8167
    ]
  },
  "type": "Feature",
  "properties": {
    "hierarchy": [
      "tgn:2674465",
      "tgn:1000001",
      "tgn:7012149",
      "tgn:2000230",
      "tgn:7007158",
      "tgn:7029392"
    ],
    "placetype": [
      "aat:300008706"
    ],
    "id": 2674465,
    "name:xx": "Snyder Creek"
  }
}
