{
  "geometry": {
    "type": "Point",
    "coordinates": [
      -75.2167,
      42.4167
    ]
  },
  "type": "Feature",
  "properties": {
    "hierarchy": [
      "tgn:2763890",
      "tgn:1000001",
      "tgn:7012149",
      "tgn:7014318",
      "tgn:7007568",
      "tgn:7029392"
    ],
    "placetype": [
      "aat:300008706"
    ],
    "id": 2763890,
    "name:xx": "Wheaton Creek"
  }
}
