{
  "geometry": {
    "type": "Point",
    "coordinates": [
      21.4167,
      52.8833
    ]
  },
  "type": "Feature",
  "properties": {
    "hierarchy": [
      "tgn:1049397",
      "tgn:1000003",
      "tgn:7024122",
      "tgn:7006366",
      "tgn:7029392"
    ],
    "placetype": [
      "aat:300008347"
    ],
    "id": 1049397,
    "name:xx": "Różan"
  }
}
