{
  "type": "FeatureCollection",
  "features": [
    {
      "geometry": {
        "type": "Point",
        "coordinates": [
          -68.683333,
          -20.583333
        ]
      },
      "type": "Feature",
      "properties": {
        "hierarchy": [
          "tgn:7307900",
          "tgn:7002464",
          "tgn:1000049",
          "tgn:1000002",
          "tgn:7029392"
        ],
        "placetype": [
          "aat:300008805"
        ],
        "id": 7307900,
        "name:xx": "Negra, Pampa"
      }
    },
    {
      "geometry": {
        "type": "Point",
        "coordinates": [
          -71.616667,
          -44.466667
        ]
      },
      "type": "Feature",
      "properties": {
        "hierarchy": [
          "tgn:7307901",
          "tgn:1001623",
          "tgn:1000049",
          "tgn:1000002",
          "tgn:7029392"
        ],
        "placetype": [
          "aat:300266640"
        ],
        "id": 7307901,
        "name:xx": "Negra, Loma"
      }
    },
    {
      "geometry": {
        "type": "Point",
        "coordinates": [
          -70.416667,
          -26.433333
        ]
      },
      "type": "Feature",
      "properties": {
        "hierarchy": [
          "tgn:7307902",
          "tgn:1001630",
          "tgn:1000049",
          "tgn:1000002",
          "tgn:7029392"
        ],
        "placetype": [
          "aat:300008795"
        ],
        "id": 7307902,
        "name:xx": "Negra, Loma"
      }
    },
    {
      "geometry": {
        "type": "Point",
        "coordinates": [
          -70.983333,
          -30.983333
        ]
      },
      "type": "Feature",
      "properties": {
        "hierarchy": [
          "tgn:7307903",
          "tgn:1001657",
          "tgn:1000049",
          "tgn:1000002",
          "tgn:7029392"
        ],
        "placetype": [
          "aat:300008777"
        ],
        "id": 7307903,
        "name:xx": "Negra, Loma"
      }
    },
    {
      "geometry": {
        "type": "Point",
        "coordinates": [
          -71.216667,
          -29.75
        ]
      },
      "type": "Feature",
      "properties": {
        "hierarchy": [
          "tgn:7307904",
          "tgn:1001657",
          "tgn:1000049",
          "tgn:1000002",
          "tgn:7029392"
        ],
        "placetype": [
          "aat:300008777"
        ],
        "id": 7307904,
        "name:xx": "Negra, Loma"
      }
    },
    {
      "geometry": {
        "type": "Point",
        "coordinates": [
          -72.716667,
          -48.5
        ]
      },
      "type": "Feature",
      "properties": {
        "hierarchy": [
          "tgn:7307905",
          "tgn:1001623",
          "tgn:1000049",
          "tgn:1000002",
          "tgn:7029392"
        ],
        "placetype": [
          "aat:300008680"
        ],
        "id": 7307905,
        "name:xx": "Negra, Laguna"
      }
    },
    {
      "geometry": {
        "type": "Point",
        "coordinates": [
          -72.083333,
          -44.433333
        ]
      },
      "type": "Feature",
      "properties": {
        "hierarchy": [
          "tgn:7307906",
          "tgn:1001623",
          "tgn:1000049",
          "tgn:1000002",
          "tgn:7029392"
        ],
        "placetype": [
          "aat:300008680"
        ],
        "id": 7307906,
        "name:xx": "Negra, Laguna"
      }
    },
    {
      "geometry": {
        "type": "Point",
        "coordinates": [
          -71.816667,
          -38.583333
        ]
      },
      "type": "Feature",
      "properties": {
        "hierarchy": [
          "tgn:7307907",
          "tgn:1001692",
          "tgn:1000049",
          "tgn:1000002",
          "tgn:7029392"
        ],
        "placetype": [
          "aat:300008680"
        ],
        "id": 7307907,
        "name:xx": "Negra, Laguna"
      }
    },
    {
      "geometry": {
        "type": "Point",
        "coordinates": [
          -70.133333,
          -33.65
        ]
      },
      "type": "Feature",
      "properties": {
        "hierarchy": [
          "tgn:7307908",
          "tgn:1001708",
          "tgn:1000049",
          "tgn:1000002",
          "tgn:7029392"
        ],
        "placetype": [
          "aat:300008680"
        ],
        "id": 7307908,
        "name:xx": "Negra, Laguna"
      }
    },
    {
      "geometry": {
        "type": "Point",
        "coordinates": [
          -72.25,
          -53.083333
        ]
      },
      "type": "Feature",
      "properties": {
        "hierarchy": [
          "tgn:7307909",
          "tgn:1001702",
          "tgn:1000049",
          "tgn:1000002",
          "tgn:7029392"
        ],
        "placetype": [
          "aat:300008791"
        ],
        "id": 7307909,
        "name:xx": "Negra, Isla"
      }
    }
  ]
}
