{
  "geometry": {
    "type": "Point",
    "coordinates": [
      -108.9667,
      36.4833
    ]
  },
  "type": "Feature",
  "properties": {
    "hierarchy": [
      "tgn:2730738",
      "tgn:1000001",
      "tgn:7012149",
      "tgn:2001452",
      "tgn:7007566",
      "tgn:7029392"
    ],
    "placetype": [
      "aat:300008699"
    ],
    "id": 2730738,
    "name:xx": "Tse-clani-to Wash"
  }
}
