{
  "geometry": {
    "type": "Point",
    "coordinates": [
      -85.65,
      37.3667
    ]
  },
  "type": "Feature",
  "properties": {
    "hierarchy": [
      "tgn:2281235",
      "tgn:1000001",
      "tgn:7012149",
      "tgn:2000794",
      "tgn:7007255",
      "tgn:7029392"
    ],
    "placetype": [
      "aat:300008680"
    ],
    "id": 2281235,
    "name:xx": "Deep Pond"
  }
}
