{
  "geometry": {
    "type": "Point",
    "coordinates": [
      -92.7667,
      33.4667
    ]
  },
  "type": "Feature",
  "properties": {
    "hierarchy": [
      "tgn:2008293",
      "tgn:1000001",
      "tgn:7016172",
      "tgn:7012149",
      "tgn:2000156",
      "tgn:7029392"
    ],
    "placetype": [
      "aat:300008347"
    ],
    "id": 2008293,
    "name:xx": "Frenchport"
  }
}
