{
  "geometry": {
    "type": "Point",
    "coordinates": [
      -92.9167,
      32.5833
    ]
  },
  "type": "Feature",
  "properties": {
    "hierarchy": [
      "tgn:2176613",
      "tgn:1000001",
      "tgn:7012149",
      "tgn:7007256",
      "tgn:7029392"
    ],
    "placetype": [
      "aat:300008706"
    ],
    "id": 2176613,
    "name:xx": "Black Lake Creek"
  }
}
