{
  "geometry": {
    "type": "Point",
    "coordinates": [
      24.25,
      41.25
    ]
  },
  "type": "Feature",
  "properties": {
    "hierarchy": [
      "tgn:7218316",
      "tgn:7011170",
      "tgn:7002715",
      "tgn:1000003",
      "tgn:1000074",
      "tgn:7029392"
    ],
    "placetype": [
      "aat:300008057"
    ],
    "id": 7218316,
    "name:xx": "Xilokópos"
  }
}
