{
  "geometry": {
    "type": "Point",
    "coordinates": [
      -88.7167,
      46.0333
    ]
  },
  "type": "Feature",
  "properties": {
    "hierarchy": [
      "tgn:2216936",
      "tgn:1000001",
      "tgn:7012149",
      "tgn:2000966",
      "tgn:7007520",
      "tgn:7029392"
    ],
    "placetype": [
      "aat:300008680"
    ],
    "id": 2216936,
    "name:xx": "Camp Lake"
  }
}
