{
  "type": "FeatureCollection",
  "features": [
    {
      "geometry": {
        "type": "Point",
        "coordinates": [
          21.533333,
          38.683333
        ]
      },
      "type": "Feature",
      "properties": {
        "hierarchy": [
          "tgn:7233690",
          "tgn:4003773",
          "tgn:7001395",
          "tgn:1000003",
          "tgn:1000074",
          "tgn:7029392"
        ],
        "placetype": [
          "aat:300008347"
        ],
        "id": 7233690,
        "name:xx": "Ayía Paraskeví"
      }
    },
    {
      "geometry": {
        "type": "Point",
        "coordinates": [
          22.75,
          38.583333
        ]
      },
      "type": "Feature",
      "properties": {
        "hierarchy": [
          "tgn:7233691",
          "tgn:7002741",
          "tgn:7017076",
          "tgn:1000003",
          "tgn:1000074",
          "tgn:7029392"
        ],
        "placetype": [
          "aat:300008347"
        ],
        "id": 7233691,
        "name:xx": "Ayía Paraskeví"
      }
    },
    {
      "geometry": {
        "type": "Point",
        "coordinates": [
          21.866667,
          38.466667
        ]
      },
      "type": "Feature",
      "properties": {
        "hierarchy": [
          "tgn:7233692",
          "tgn:4003773",
          "tgn:7001395",
          "tgn:1000003",
          "tgn:1000074",
          "tgn:7029392"
        ],
        "placetype": [
          "aat:300008347"
        ],
        "id": 7233692,
        "name:xx": "Ayía Paraskeví"
      }
    },
    {
      "geometry": {
        "type": "Point",
        "coordinates": [
          22.983333,
          38.4
        ]
      },
      "type": "Feature",
      "properties": {
        "hierarchy": [
          "tgn:7233693",
          "tgn:7002741",
          "tgn:7017076",
          "tgn:1000003",
          "tgn:1000074",
          "tgn:7029392"
        ],
        "placetype": [
          "aat:300008347"
        ],
        "id": 7233693,
        "name:xx": "Ayía Paraskeví"
      }
    },
    {
      "geometry": {
        "type": "Point",
        "coordinates": [
          21.833333,
          38.133333
        ]
      },
      "type": "Feature",
      "properties": {
        "hierarchy": [
          "tgn:7233694",
          "tgn:7002743",
          "tgn:7017076",
          "tgn:1000003",
          "tgn:1000074",
          "tgn:7029392"
        ],
        "placetype": [
          "aat:300008347"
        ],
        "id": 7233694,
        "name:xx": "Ayía Paraskeví"
      }
    },
    {
      "geometry": {
        "type": "Point",
        "coordinates": [
          23.9,
          37.783333
        ]
      },
      "type": "Feature",
      "properties": {
        "hierarchy": [
          "tgn:7233696",
          "tgn:7002681",
          "tgn:7001395",
          "tgn:1000003",
          "tgn:1000074",
          "tgn:7029392"
        ],
        "placetype": [
          "aat:300008347"
        ],
        "id": 7233696,
        "name:xx": "Ayía Paraskeví"
      }
    },
    {
      "geometry": {
        "type": "Point",
        "coordinates": [
          23.016667,
          36.666667
        ]
      },
      "type": "Feature",
      "properties": {
        "hierarchy": [
          "tgn:7233697",
          "tgn:7002745",
          "tgn:7017076",
          "tgn:1000003",
          "tgn:1000074",
          "tgn:7029392"
        ],
        "placetype": [
          "aat:300008347"
        ],
        "id": 7233697,
        "name:xx": "Ayía Paraskeví"
      }
    },
    {
      "geometry": {
        "type": "Point",
        "coordinates": [
          23.55,
          35.4
        ]
      },
      "type": "Feature",
      "properties": {
        "hierarchy": [
          "tgn:7233698",
          "tgn:7002690",
          "tgn:7012056",
          "tgn:1000003",
          "tgn:1000074",
          "tgn:7029392"
        ],
        "placetype": [
          "aat:300008347"
        ],
        "id": 7233698,
        "name:xx": "Ayía Paraskeví"
      }
    },
    {
      "geometry": {
        "type": "Point",
        "coordinates": [
          24.566667,
          35.35
        ]
      },
      "type": "Feature",
      "properties": {
        "hierarchy": [
          "tgn:7233699",
          "tgn:7002690",
          "tgn:7012056",
          "tgn:1000003",
          "tgn:1000074",
          "tgn:7029392"
        ],
        "placetype": [
          "aat:300008347"
        ],
        "id": 7233699,
        "name:xx": "Ayía Paraskeví"
      }
    }
  ]
}
