{
  "type": "FeatureCollection",
  "features": [
    {
      "geometry": {
        "type": "Point",
        "coordinates": [
          30.816667,
          28.816667
        ]
      },
      "type": "Feature",
      "properties": {
        "hierarchy": [
          "tgn:7526660",
          "tgn:7001242",
          "tgn:7016833",
          "tgn:1001142",
          "tgn:7029392"
        ],
        "placetype": [
          "aat:300005926"
        ],
        "name:en": "Sīdī Muḩammad Abū an Nūr",
        "id": 7526660
      }
    },
    {
      "geometry": {
        "type": "Point",
        "coordinates": [
          25.420324,
          31.274978
        ]
      },
      "type": "Feature",
      "properties": {
        "hierarchy": [
          "tgn:7526661",
          "tgn:7001242",
          "tgn:7016833",
          "tgn:1001418",
          "tgn:7029392"
        ],
        "placetype": [
          "aat:300005926"
        ],
        "name:en": "Sīdī Muḩammad 'Abd ar Rāziq",
        "id": 7526661
      }
    },
    {
      "geometry": {
        "type": "Point",
        "coordinates": [
          31.383333,
          31.133333
        ]
      },
      "type": "Feature",
      "properties": {
        "hierarchy": [
          "tgn:7526662",
          "tgn:7001242",
          "tgn:1001059",
          "tgn:7016833",
          "tgn:7029392"
        ],
        "placetype": [
          "aat:300005926"
        ],
        "name:en": "Sīdī Muḩammad 'Abd Allāh",
        "id": 7526662
      }
    },
    {
      "geometry": {
        "type": "Point",
        "coordinates": [
          30.866667,
          27.9
        ]
      },
      "type": "Feature",
      "properties": {
        "hierarchy": [
          "tgn:7526663",
          "tgn:7001242",
          "tgn:7016833",
          "tgn:1001088",
          "tgn:7029392"
        ],
        "placetype": [
          "aat:300005926"
        ],
        "name:en": "Sīdī Muḩammad 'Abd al Bāqī",
        "id": 7526663
      }
    },
    {
      "geometry": {
        "type": "Point",
        "coordinates": [
          32.716667,
          25.166667
        ]
      },
      "type": "Feature",
      "properties": {
        "hierarchy": [
          "tgn:7526664",
          "tgn:7001242",
          "tgn:7016833",
          "tgn:7000122",
          "tgn:7029392"
        ],
        "placetype": [
          "aat:300005926"
        ],
        "name:en": "Manāmat Sīdī Muḩammad",
        "id": 7526664
      }
    },
    {
      "geometry": {
        "type": "Point",
        "coordinates": [
          30.933333,
          28.866667
        ]
      },
      "type": "Feature",
      "properties": {
        "hierarchy": [
          "tgn:7526665",
          "tgn:7001242",
          "tgn:7016833",
          "tgn:1001142",
          "tgn:7029392"
        ],
        "placetype": [
          "aat:300005926"
        ],
        "name:en": "Sīdī Muḩammad",
        "id": 7526665
      }
    },
    {
      "geometry": {
        "type": "Point",
        "coordinates": [
          31.083333,
          27.2
        ]
      },
      "type": "Feature",
      "properties": {
        "hierarchy": [
          "tgn:7526666",
          "tgn:7001242",
          "tgn:7016833",
          "tgn:1001114",
          "tgn:7029392"
        ],
        "placetype": [
          "aat:300005926"
        ],
        "name:en": "Sīdī Muḩammad",
        "id": 7526666
      }
    },
    {
      "geometry": {
        "type": "Point",
        "coordinates": [
          31.233333,
          27.183333
        ]
      },
      "type": "Feature",
      "properties": {
        "hierarchy": [
          "tgn:7526667",
          "tgn:7001242",
          "tgn:7016833",
          "tgn:1001114",
          "tgn:7029392"
        ],
        "placetype": [
          "aat:300005926"
        ],
        "name:en": "Sīdī Muḩammad",
        "id": 7526667
      }
    },
    {
      "geometry": {
        "type": "Point",
        "coordinates": [
          31.233333,
          27.05
        ]
      },
      "type": "Feature",
      "properties": {
        "hierarchy": [
          "tgn:7526668",
          "tgn:7001242",
          "tgn:7016833",
          "tgn:1001114",
          "tgn:7029392"
        ],
        "placetype": [
          "aat:300005926"
        ],
        "name:en": "Sīdī Muḩammad",
        "id": 7526668
      }
    },
    {
      "geometry": {
        "type": "Point",
        "coordinates": [
          31.4,
          26.883333
        ]
      },
      "type": "Feature",
      "properties": {
        "hierarchy": [
          "tgn:7526669",
          "tgn:7001242",
          "tgn:7016833",
          "tgn:7000124",
          "tgn:7029392"
        ],
        "placetype": [
          "aat:300005926"
        ],
        "name:en": "Sīdī Muḩammad",
        "id": 7526669
      }
    }
  ]
}
