{
  "geometry": {
    "type": "Point",
    "coordinates": [
      -97.0833,
      33.9167
    ]
  },
  "type": "Feature",
  "properties": {
    "hierarchy": [
      "tgn:2572648",
      "tgn:1000001",
      "tgn:7012149",
      "tgn:2001665",
      "tgn:7007707",
      "tgn:7029392"
    ],
    "placetype": [
      "aat:300008798"
    ],
    "id": 2572648,
    "name:xx": "Peak Hill"
  }
}
