{
  "geometry": {
    "type": "Point",
    "coordinates": [
      -112.4667,
      33.95
    ]
  },
  "type": "Feature",
  "properties": {
    "hierarchy": [
      "tgn:2358709",
      "tgn:1000001",
      "tgn:7006451",
      "tgn:7012149",
      "tgn:2000103",
      "tgn:7029392"
    ],
    "placetype": [
      "aat:300006191"
    ],
    "id": 2358709,
    "name:xx": "Grandview Tank"
  }
}
