{
  "type": "FeatureCollection",
  "features": [
    {
      "geometry": {
        "type": "Point",
        "coordinates": [
          11.266667,
          44.8
        ]
      },
      "type": "Feature",
      "properties": {
        "hierarchy": [
          "tgn:4004200",
          "tgn:7004597",
          "tgn:1000003",
          "tgn:7008516",
          "tgn:1000080",
          "tgn:7029392"
        ],
        "placetype": [
          "aat:300008347"
        ],
        "id": 4004200,
        "name:xx": "Galeazza Pepoli"
      }
    },
    {
      "geometry": {
        "type": "Point",
        "coordinates": [
          20.791111,
          39.3325
        ]
      },
      "type": "Feature",
      "properties": {
        "hierarchy": [
          "tgn:4004205",
          "tgn:7002691",
          "tgn:7012056",
          "tgn:1000003",
          "tgn:1000074",
          "tgn:7029392"
        ],
        "placetype": [
          "aat:300008347",
          "aat:300008372"
        ],
        "id": 4004205,
        "name:xx": "Ayía Galíni"
      }
    },
    {
      "geometry": {
        "type": "Point",
        "coordinates": [
          -10.3667,
          52.1667
        ]
      },
      "type": "Feature",
      "properties": {
        "hierarchy": [
          "tgn:4004207",
          "tgn:7003498",
          "tgn:7001201",
          "tgn:1000003",
          "tgn:1000078",
          "tgn:7029392"
        ],
        "placetype": [
          "aat:300008347"
        ],
        "id": 4004207,
        "name:xx": "Gallarus"
      }
    }
  ]
}
