{
  "geometry": {
    "type": "Point",
    "coordinates": [
      -79.7833,
      34.1333
    ]
  },
  "type": "Feature",
  "properties": {
    "hierarchy": [
      "tgn:2282664",
      "tgn:1000001",
      "tgn:2001745",
      "tgn:7012149",
      "tgn:7007712",
      "tgn:7029392"
    ],
    "placetype": [
      "aat:300008347"
    ],
    "id": 2282664,
    "name:xx": "Deerfield"
  }
}
