{
  "geometry": {
    "type": "Point",
    "coordinates": [
      26.55,
      29.883333
    ]
  },
  "type": "Feature",
  "properties": {
    "hierarchy": [
      "tgn:7524258",
      "tgn:7001242",
      "tgn:7016833",
      "tgn:1001418",
      "tgn:7029392"
    ],
    "placetype": [
      "aat:300055621"
    ],
    "name:en": "El Shiṭeirât",
    "id": 7524258
  }
}
