{
  "geometry": {
    "type": "Point",
    "coordinates": [
      25.0833,
      54.15
    ]
  },
  "type": "Feature",
  "properties": {
    "hierarchy": [
      "tgn:1053816",
      "tgn:1000003",
      "tgn:7006604",
      "tgn:7006542",
      "tgn:7029392"
    ],
    "placetype": [
      "aat:300008347"
    ],
    "id": 1053816,
    "name:xx": "Eišiškės"
  }
}
