{
  "geometry": {
    "type": "Point",
    "coordinates": [
      136.0333,
      34.8667
    ]
  },
  "type": "Feature",
  "properties": {
    "hierarchy": [
      "tgn:1081284",
      "tgn:1000004",
      "tgn:7000896",
      "tgn:7000277",
      "tgn:1000120",
      "tgn:7029392"
    ],
    "placetype": [
      "aat:300008347"
    ],
    "id": 1081284,
    "name:xx": "Shigaraki"
  }
}
