{
  "geometry": {
    "type": "Point",
    "coordinates": [
      -103.65,
      22.55
    ]
  },
  "type": "Feature",
  "properties": {
    "hierarchy": [
      "tgn:7352882",
      "tgn:7005586",
      "tgn:1000001",
      "tgn:7005560",
      "tgn:7029392"
    ],
    "placetype": [
      "aat:300008699"
    ],
    "id": 7352882,
    "name:xx": "Atotoac, Río"
  }
}
