{
  "type": "FeatureCollection",
  "features": [
    {
      "geometry": {
        "type": "Point",
        "coordinates": [
          -113.6833,
          47.1333
        ]
      },
      "type": "Feature",
      "properties": {
        "hierarchy": [
          "tgn:2367520",
          "tgn:1000001",
          "tgn:7012149",
          "tgn:2001291",
          "tgn:7007524",
          "tgn:7029392"
        ],
        "placetype": [
          "aat:300008706"
        ],
        "id": 2367520,
        "name:xx": "Grouse Creek"
      }
    },
    {
      "geometry": {
        "type": "Point",
        "coordinates": [
          -115.3833,
          47.8167
        ]
      },
      "type": "Feature",
      "properties": {
        "hierarchy": [
          "tgn:2367521",
          "tgn:1000001",
          "tgn:7012149",
          "tgn:2001304",
          "tgn:7007524",
          "tgn:7029392"
        ],
        "placetype": [
          "aat:300008706"
        ],
        "id": 2367521,
        "name:xx": "Grouse Creek"
      }
    },
    {
      "geometry": {
        "type": "Point",
        "coordinates": [
          -113.4833,
          48.05
        ]
      },
      "type": "Feature",
      "properties": {
        "hierarchy": [
          "tgn:2367522",
          "tgn:1000001",
          "tgn:7012149",
          "tgn:2001274",
          "tgn:7007524",
          "tgn:7029392"
        ],
        "placetype": [
          "aat:300008706"
        ],
        "id": 2367522,
        "name:xx": "Grouse Creek"
      }
    },
    {
      "geometry": {
        "type": "Point",
        "coordinates": [
          -110.7667,
          45.8
        ]
      },
      "type": "Feature",
      "properties": {
        "hierarchy": [
          "tgn:2367523",
          "tgn:1000001",
          "tgn:7012149",
          "tgn:7007524",
          "tgn:7029392"
        ],
        "placetype": [
          "aat:300008706"
        ],
        "id": 2367523,
        "name:xx": "Grouse Creek"
      }
    },
    {
      "geometry": {
        "type": "Point",
        "coordinates": [
          -112.8,
          47.7167
        ]
      },
      "type": "Feature",
      "properties": {
        "hierarchy": [
          "tgn:2367524",
          "tgn:1000001",
          "tgn:7012149",
          "tgn:2001309",
          "tgn:7007524",
          "tgn:7029392"
        ],
        "placetype": [
          "aat:300008706"
        ],
        "id": 2367524,
        "name:xx": "Grouse Creek"
      }
    },
    {
      "geometry": {
        "type": "Point",
        "coordinates": [
          -110.2833,
          45.4833
        ]
      },
      "type": "Feature",
      "properties": {
        "hierarchy": [
          "tgn:2367525",
          "tgn:1000001",
          "tgn:7012149",
          "tgn:2001293",
          "tgn:7007524",
          "tgn:7029392"
        ],
        "placetype": [
          "aat:300008706"
        ],
        "id": 2367525,
        "name:xx": "Grouse Creek"
      }
    },
    {
      "geometry": {
        "type": "Point",
        "coordinates": [
          -112.2667,
          46.0167
        ]
      },
      "type": "Feature",
      "properties": {
        "hierarchy": [
          "tgn:2367526",
          "tgn:1000001",
          "tgn:7012149",
          "tgn:2001281",
          "tgn:7007524",
          "tgn:7029392"
        ],
        "placetype": [
          "aat:300008706"
        ],
        "id": 2367526,
        "name:xx": "Grouse Creek"
      }
    },
    {
      "geometry": {
        "type": "Point",
        "coordinates": [
          -116.4667,
          40.0167
        ]
      },
      "type": "Feature",
      "properties": {
        "hierarchy": [
          "tgn:2367527",
          "tgn:1000001",
          "tgn:2001413",
          "tgn:7012149",
          "tgn:7007526",
          "tgn:7029392"
        ],
        "placetype": [
          "aat:300008706"
        ],
        "id": 2367527,
        "name:xx": "Grouse Creek"
      }
    },
    {
      "geometry": {
        "type": "Point",
        "coordinates": [
          -116.85,
          40.3833
        ]
      },
      "type": "Feature",
      "properties": {
        "hierarchy": [
          "tgn:2367528",
          "tgn:1000001",
          "tgn:2001415",
          "tgn:7012149",
          "tgn:7007526",
          "tgn:7029392"
        ],
        "placetype": [
          "aat:300008706"
        ],
        "id": 2367528,
        "name:xx": "Grouse Creek"
      }
    },
    {
      "geometry": {
        "type": "Point",
        "coordinates": [
          -114.05,
          41.5667
        ]
      },
      "type": "Feature",
      "properties": {
        "hierarchy": [
          "tgn:2367529",
          "tgn:1000001",
          "tgn:2001411",
          "tgn:7012149",
          "tgn:7007526",
          "tgn:7029392"
        ],
        "placetype": [
          "aat:300008706"
        ],
        "id": 2367529,
        "name:xx": "Grouse Creek"
      }
    }
  ]
}
