{
  "geometry": {
    "type": "Point",
    "coordinates": [
      -76.7333,
      -7.1667
    ]
  },
  "type": "Feature",
  "properties": {
    "hierarchy": [
      "tgn:1024563",
      "tgn:1000749",
      "tgn:1000002",
      "tgn:1000056",
      "tgn:7029392"
    ],
    "placetype": [
      "aat:300008347"
    ],
    "id": 1024563,
    "name:xx": "Juanjuí"
  }
}
