{
  "geometry": {
    "type": "Point",
    "coordinates": [
      -92.7333,
      33.8833
    ]
  },
  "type": "Feature",
  "properties": {
    "hierarchy": [
      "tgn:2731667",
      "tgn:1000001",
      "tgn:7016172",
      "tgn:7012149",
      "tgn:7029392"
    ],
    "placetype": [
      "aat:300008706"
    ],
    "id": 2731667,
    "name:xx": "Tulip Creek"
  }
}
