{
  "geometry": {
    "type": "Point",
    "coordinates": [
      -115.7667,
      33.3667
    ]
  },
  "type": "Feature",
  "properties": {
    "hierarchy": [
      "tgn:2010231",
      "tgn:1000001",
      "tgn:7012149",
      "tgn:2000182",
      "tgn:7007157",
      "tgn:7029392"
    ],
    "placetype": [
      "aat:300387016"
    ],
    "id": 2010231,
    "name:xx": "Bertram"
  }
}
