{
  "geometry": {
    "type": "Point",
    "coordinates": [
      -84.1667,
      43.9167
    ]
  },
  "type": "Feature",
  "properties": {
    "hierarchy": [
      "tgn:2636472",
      "tgn:1000001",
      "tgn:7012149",
      "tgn:7007520",
      "tgn:7029392"
    ],
    "placetype": [
      "aat:300008706"
    ],
    "id": 2636472,
    "name:xx": "Saganing Creek"
  }
}
