{
  "geometry": {
    "type": "Point",
    "coordinates": [
      17.6667,
      59.25
    ]
  },
  "type": "Feature",
  "properties": {
    "hierarchy": [
      "tgn:1063559",
      "tgn:1000003",
      "tgn:7003777",
      "tgn:1000097",
      "tgn:7029392"
    ],
    "placetype": [
      "aat:300008347"
    ],
    "id": 1063559,
    "name:xx": "Salem"
  }
}
