{
  "geometry": {
    "type": "Point",
    "coordinates": [
      117.9833,
      34.4167
    ]
  },
  "type": "Feature",
  "properties": {
    "hierarchy": [
      "tgn:1068392",
      "tgn:1000004",
      "tgn:7002081",
      "tgn:1000111",
      "tgn:7029392"
    ],
    "placetype": [
      "aat:300008347"
    ],
    "id": 1068392,
    "name:xx": "Guanhu"
  }
}
