{
  "geometry": {
    "type": "Point",
    "coordinates": [
      -7.8667,
      53.9167
    ]
  },
  "type": "Feature",
  "properties": {
    "hierarchy": [
      "tgn:1042931",
      "tgn:7003480",
      "tgn:7001198",
      "tgn:1000003",
      "tgn:1000078",
      "tgn:7029392"
    ],
    "placetype": [
      "aat:300008347"
    ],
    "id": 1042931,
    "name:xx": "Mohill"
  }
}
