{
  "geometry": {
    "type": "Point",
    "coordinates": [
      -68.7833,
      44.4167
    ]
  },
  "type": "Feature",
  "properties": {
    "hierarchy": [
      "tgn:2184768",
      "tgn:1000001",
      "tgn:2000922",
      "tgn:7012149",
      "tgn:7007515",
      "tgn:7029392"
    ],
    "placetype": [
      "aat:300008699"
    ],
    "id": 2184768,
    "name:xx": "Bog Brook"
  }
}
