{
  "geometry": {
    "type": "Point",
    "coordinates": [
      -75.8333,
      38.3333
    ]
  },
  "type": "Feature",
  "properties": {
    "hierarchy": [
      "tgn:2399547",
      "tgn:1000001",
      "tgn:1003023",
      "tgn:7012149",
      "tgn:7007516",
      "tgn:7029392"
    ],
    "placetype": [
      "aat:300008699"
    ],
    "id": 2399547,
    "name:xx": "Horner Gut"
  }
}
