{
  "type": "FeatureCollection",
  "features": [
    {
      "geometry": {
        "type": "Point",
        "coordinates": [
          -116.45,
          48.75
        ]
      },
      "type": "Feature",
      "properties": {
        "hierarchy": [
          "tgn:2241070",
          "tgn:1000001",
          "tgn:2000462",
          "tgn:7012149",
          "tgn:7007250",
          "tgn:7029392"
        ],
        "placetype": [
          "aat:300008706"
        ],
        "id": 2241070,
        "name:xx": "Clark Creek"
      }
    },
    {
      "geometry": {
        "type": "Point",
        "coordinates": [
          -111.4,
          43.1667
        ]
      },
      "type": "Feature",
      "properties": {
        "hierarchy": [
          "tgn:2241071",
          "tgn:1000001",
          "tgn:2000461",
          "tgn:7012149",
          "tgn:7007250",
          "tgn:7029392"
        ],
        "placetype": [
          "aat:300008706"
        ],
        "id": 2241071,
        "name:xx": "Clark Creek"
      }
    },
    {
      "geometry": {
        "type": "Point",
        "coordinates": [
          -115.3167,
          45.2
        ]
      },
      "type": "Feature",
      "properties": {
        "hierarchy": [
          "tgn:2241072",
          "tgn:1000001",
          "tgn:7012149",
          "tgn:2000476",
          "tgn:7007250",
          "tgn:7029392"
        ],
        "placetype": [
          "aat:300008706"
        ],
        "id": 2241072,
        "name:xx": "Clark Creek"
      }
    },
    {
      "geometry": {
        "type": "Point",
        "coordinates": [
          -116.5,
          47.45
        ]
      },
      "type": "Feature",
      "properties": {
        "hierarchy": [
          "tgn:2241073",
          "tgn:1000001",
          "tgn:7012149",
          "tgn:2000479",
          "tgn:7007250",
          "tgn:7029392"
        ],
        "placetype": [
          "aat:300008706"
        ],
        "id": 2241073,
        "name:xx": "Clark Creek"
      }
    },
    {
      "geometry": {
        "type": "Point",
        "coordinates": [
          -116.15,
          47.9667
        ]
      },
      "type": "Feature",
      "properties": {
        "hierarchy": [
          "tgn:2241074",
          "tgn:1000001",
          "tgn:7012149",
          "tgn:2000491",
          "tgn:7007250",
          "tgn:7029392"
        ],
        "placetype": [
          "aat:300008706"
        ],
        "id": 2241074,
        "name:xx": "Clark Creek"
      }
    },
    {
      "geometry": {
        "type": "Point",
        "coordinates": [
          -86.9333,
          39.15
        ]
      },
      "type": "Feature",
      "properties": {
        "hierarchy": [
          "tgn:2241075",
          "tgn:1000001",
          "tgn:7012149",
          "tgn:2000544",
          "tgn:7007252",
          "tgn:7029392"
        ],
        "placetype": [
          "aat:300008706"
        ],
        "id": 2241075,
        "name:xx": "Clark Creek"
      }
    },
    {
      "geometry": {
        "type": "Point",
        "coordinates": [
          -91.3167,
          43.3667
        ]
      },
      "type": "Feature",
      "properties": {
        "hierarchy": [
          "tgn:2241076",
          "tgn:2000563",
          "tgn:1000001",
          "tgn:7012149",
          "tgn:7007253",
          "tgn:7029392"
        ],
        "placetype": [
          "aat:300008706"
        ],
        "id": 2241076,
        "name:xx": "Clark Creek"
      }
    },
    {
      "geometry": {
        "type": "Point",
        "coordinates": [
          -92.3833,
          32.45
        ]
      },
      "type": "Feature",
      "properties": {
        "hierarchy": [
          "tgn:2241077",
          "tgn:1000001",
          "tgn:7012149",
          "tgn:2000890",
          "tgn:7007256",
          "tgn:7029392"
        ],
        "placetype": [
          "aat:300008706"
        ],
        "id": 2241077,
        "name:xx": "Clark Creek"
      }
    },
    {
      "geometry": {
        "type": "Point",
        "coordinates": [
          -87.7667,
          46.6667
        ]
      },
      "type": "Feature",
      "properties": {
        "hierarchy": [
          "tgn:2241078",
          "tgn:1000001",
          "tgn:7012149",
          "tgn:2000975",
          "tgn:7007520",
          "tgn:7029392"
        ],
        "placetype": [
          "aat:300008706"
        ],
        "id": 2241078,
        "name:xx": "Clark Creek"
      }
    },
    {
      "geometry": {
        "type": "Point",
        "coordinates": [
          -91.5167,
          31.0667
        ]
      },
      "type": "Feature",
      "properties": {
        "hierarchy": [
          "tgn:2241079",
          "tgn:1000001",
          "tgn:7012149",
          "tgn:2001164",
          "tgn:7007522",
          "tgn:7029392"
        ],
        "placetype": [
          "aat:300008706"
        ],
        "id": 2241079,
        "name:xx": "Clark Creek"
      }
    }
  ]
}
