{
  "geometry": {
    "type": "Point",
    "coordinates": [
      73.35,
      34.55
    ]
  },
  "type": "Feature",
  "properties": {
    "hierarchy": [
      "tgn:1083353",
      "tgn:7002460",
      "tgn:1000004",
      "tgn:1000133",
      "tgn:7029392"
    ],
    "placetype": [
      "aat:300008347"
    ],
    "id": 1083353,
    "name:xx": "Bālākot"
  }
}
