{
  "geometry": {
    "type": "Point",
    "coordinates": [
      -86.2667,
      38.7667
    ]
  },
  "type": "Feature",
  "properties": {
    "hierarchy": [
      "tgn:2031838",
      "tgn:1000001",
      "tgn:7012149",
      "tgn:1002579",
      "tgn:7007252",
      "tgn:7029392"
    ],
    "placetype": [
      "aat:300008347"
    ],
    "id": 2031838,
    "name:xx": "Fort Ritner"
  }
}
