{
  "geometry": {
    "type": "Point",
    "coordinates": [
      16.3333,
      3.9167
    ]
  },
  "type": "Feature",
  "properties": {
    "hierarchy": [
      "tgn:1001027",
      "tgn:7001242",
      "tgn:1000155",
      "tgn:7029392"
    ],
    "placetype": [
      "aat:300387064",
      "aat:300235099"
    ],
    "id": 1001027,
    "name:xx": "Sangha-Mbaere"
  }
}
