{
  "geometry": {
    "type": "Point",
    "coordinates": [
      -118.6333,
      35.45
    ]
  },
  "type": "Feature",
  "properties": {
    "hierarchy": [
      "tgn:2691582",
      "tgn:1000001",
      "tgn:7012149",
      "tgn:1002545",
      "tgn:7007157",
      "tgn:7029392"
    ],
    "placetype": [
      "aat:300008706"
    ],
    "id": 2691582,
    "name:xx": "Stark Creek"
  }
}
