{
  "geometry": {
    "type": "Point",
    "coordinates": [
      -83.3333,
      36.75
    ]
  },
  "type": "Feature",
  "properties": {
    "hierarchy": [
      "tgn:2037600",
      "tgn:1000001",
      "tgn:7012149",
      "tgn:2000797",
      "tgn:7007255",
      "tgn:7029392"
    ],
    "placetype": [
      "aat:300008347"
    ],
    "id": 2037600,
    "name:xx": "Bardo"
  }
}
