{
  "type": "FeatureCollection",
  "features": [
    {
      "geometry": {
        "type": "Point",
        "coordinates": [
          -1.8333,
          9.2
        ]
      },
      "type": "Feature",
      "properties": {
        "hierarchy": [
          "tgn:1090110",
          "tgn:7001242",
          "tgn:1001722",
          "tgn:1000166",
          "tgn:7029392"
        ],
        "placetype": [
          "aat:300008347"
        ],
        "id": 1090110,
        "name:xx": "Damongo"
      }
    },
    {
      "geometry": {
        "type": "Point",
        "coordinates": [
          -1.4333,
          10.6167
        ]
      },
      "type": "Feature",
      "properties": {
        "hierarchy": [
          "tgn:1090111",
          "tgn:7001242",
          "tgn:7018307",
          "tgn:1000166",
          "tgn:7029392"
        ],
        "placetype": [
          "aat:300008347"
        ],
        "id": 1090111,
        "name:xx": "Doninga"
      }
    },
    {
      "geometry": {
        "type": "Point",
        "coordinates": [
          -2.8833,
          7.2833
        ]
      },
      "type": "Feature",
      "properties": {
        "hierarchy": [
          "tgn:1090112",
          "tgn:1001640",
          "tgn:7001242",
          "tgn:1000166",
          "tgn:7029392"
        ],
        "placetype": [
          "aat:300008347"
        ],
        "id": 1090112,
        "name:xx": "Dormaa Ahenkro"
      }
    },
    {
      "geometry": {
        "type": "Point",
        "coordinates": [
          -0.9833,
          10.5
        ]
      },
      "type": "Feature",
      "properties": {
        "hierarchy": [
          "tgn:1090113",
          "tgn:7001242",
          "tgn:1001722",
          "tgn:1000166",
          "tgn:7029392"
        ],
        "placetype": [
          "aat:300008347"
        ],
        "id": 1090113,
        "name:xx": "Du"
      }
    },
    {
      "geometry": {
        "type": "Point",
        "coordinates": [
          -2.1,
          7.1667
        ]
      },
      "type": "Feature",
      "properties": {
        "hierarchy": [
          "tgn:1090114",
          "tgn:1001640",
          "tgn:7001242",
          "tgn:1000166",
          "tgn:7029392"
        ],
        "placetype": [
          "aat:300008347"
        ],
        "id": 1090114,
        "name:xx": "Duayaw Nkwanta"
      }
    },
    {
      "geometry": {
        "type": "Point",
        "coordinates": [
          -1.1667,
          5.3333
        ]
      },
      "type": "Feature",
      "properties": {
        "hierarchy": [
          "tgn:1090115",
          "tgn:1001653",
          "tgn:7001242",
          "tgn:1000166",
          "tgn:7029392"
        ],
        "placetype": [
          "aat:300008347",
          "aat:300008375"
        ],
        "id": 1090115,
        "name:xx": "Dunkwa"
      }
    },
    {
      "geometry": {
        "type": "Point",
        "coordinates": [
          1,
          6.2333
        ]
      },
      "type": "Feature",
      "properties": {
        "hierarchy": [
          "tgn:1090116",
          "tgn:7001242",
          "tgn:1001770",
          "tgn:1000166",
          "tgn:7029392"
        ],
        "placetype": [
          "aat:300008347"
        ],
        "id": 1090116,
        "name:xx": "Dzodze"
      }
    },
    {
      "geometry": {
        "type": "Point",
        "coordinates": [
          -1.4,
          6.85
        ]
      },
      "type": "Feature",
      "properties": {
        "hierarchy": [
          "tgn:1090117",
          "tgn:1001628",
          "tgn:7001242",
          "tgn:1000166",
          "tgn:7029392"
        ],
        "placetype": [
          "aat:300008347"
        ],
        "id": 1090117,
        "name:xx": "Efiduasi"
      }
    },
    {
      "geometry": {
        "type": "Point",
        "coordinates": [
          -1.25,
          7.3833
        ]
      },
      "type": "Feature",
      "properties": {
        "hierarchy": [
          "tgn:1090118",
          "tgn:1001628",
          "tgn:7001242",
          "tgn:1000166",
          "tgn:7029392"
        ],
        "placetype": [
          "aat:300008347"
        ],
        "id": 1090118,
        "name:xx": "Ejura"
      }
    }
  ]
}
