{
  "geometry": {
    "type": "Point",
    "coordinates": [
      -75.9333,
      39.2333
    ]
  },
  "type": "Feature",
  "properties": {
    "hierarchy": [
      "tgn:2233670",
      "tgn:1000001",
      "tgn:1002539",
      "tgn:7012149",
      "tgn:7007516",
      "tgn:7029392"
    ],
    "placetype": [
      "aat:300008791"
    ],
    "id": 2233670,
    "name:xx": "Chase Island"
  }
}
