{
  "geometry": {
    "type": "Point",
    "coordinates": [
      35.7667,
      48.95
    ]
  },
  "type": "Feature",
  "properties": {
    "hierarchy": [
      "tgn:1051546",
      "tgn:7011648",
      "tgn:1000003",
      "tgn:7006660",
      "tgn:7029392"
    ],
    "placetype": [
      "aat:300008347"
    ],
    "id": 1051546,
    "name:xx": "Shandrivka"
  }
}
