{
  "geometry": {
    "type": "Point",
    "coordinates": [
      25.05,
      45.2667
    ]
  },
  "type": "Feature",
  "properties": {
    "hierarchy": [
      "tgn:7004130",
      "tgn:7002693",
      "tgn:1000003",
      "tgn:1000091",
      "tgn:7029392"
    ],
    "placetype": [
      "aat:300008347"
    ],
    "id": 7004130,
    "name:xx": "Cîmpulung"
  }
}
