{
  "geometry": {
    "type": "Point",
    "coordinates": [
      9.0833,
      47.6167
    ]
  },
  "type": "Feature",
  "properties": {
    "hierarchy": [
      "tgn:1064035",
      "tgn:1000003",
      "tgn:7003759",
      "tgn:7011731",
      "tgn:7029392"
    ],
    "placetype": [
      "aat:300008347"
    ],
    "id": 1064035,
    "name:xx": "Engwilen"
  }
}
