{
  "geometry": {
    "type": "Point",
    "coordinates": [
      121.6589,
      24.1612
    ]
  },
  "type": "Feature",
  "properties": {
    "hierarchy": [
      "tgn:7472111",
      "tgn:7001010",
      "tgn:1000004",
      "tgn:1000141",
      "tgn:7029392"
    ],
    "placetype": [
      "aat:300008347"
    ],
    "id": 7472111,
    "name:xx": "Shangkan"
  }
}
