{
  "geometry": {
    "type": "Point",
    "coordinates": [
      -75.6667,
      39.9667
    ]
  },
  "type": "Feature",
  "properties": {
    "hierarchy": [
      "tgn:2089096",
      "tgn:1000001",
      "tgn:1002266",
      "tgn:7012149",
      "tgn:7007710",
      "tgn:7029392"
    ],
    "placetype": [
      "aat:300008347"
    ],
    "id": 2089096,
    "name:xx": "Harmony Hill"
  }
}
