{
  "geometry": {
    "type": "Point",
    "coordinates": [
      -92.0667,
      36.0167
    ]
  },
  "type": "Feature",
  "properties": {
    "hierarchy": [
      "tgn:2186533",
      "tgn:1000001",
      "tgn:7016172",
      "tgn:7012149",
      "tgn:2000137",
      "tgn:7029392"
    ],
    "placetype": [
      "aat:300055621"
    ],
    "id": 2186533,
    "name:xx": "Bone Island"
  }
}
