{
  "geometry": {
    "type": "Point",
    "coordinates": [
      -89.0167,
      34.1667
    ]
  },
  "type": "Feature",
  "properties": {
    "hierarchy": [
      "tgn:2055838",
      "tgn:1000001",
      "tgn:7012149",
      "tgn:2001143",
      "tgn:7007522",
      "tgn:7029392"
    ],
    "placetype": [
      "aat:300008347"
    ],
    "id": 2055838,
    "name:xx": "Algoma"
  }
}
