{
  "geometry": {
    "type": "Point",
    "coordinates": [
      -76.4833,
      38.3667
    ]
  },
  "type": "Feature",
  "properties": {
    "hierarchy": [
      "tgn:2733752",
      "tgn:1002224",
      "tgn:1000001",
      "tgn:7012149",
      "tgn:7007516",
      "tgn:7029392"
    ],
    "placetype": [
      "aat:300132316"
    ],
    "id": 2733752,
    "name:xx": "Turner Cove"
  }
}
