{
  "geometry": {
    "type": "Point",
    "coordinates": [
      -110.5333,
      44.8667
    ]
  },
  "type": "Feature",
  "properties": {
    "hierarchy": [
      "tgn:2178730",
      "tgn:1000001",
      "tgn:7012149",
      "tgn:7029392"
    ],
    "placetype": [
      "aat:300008706"
    ],
    "id": 2178730,
    "name:xx": "Blacktail Deer Creek"
  }
}
