{
  "type": "FeatureCollection",
  "features": [
    {
      "geometry": {
        "type": "Point",
        "coordinates": [
          -85.9167,
          30.8833
        ]
      },
      "type": "Feature",
      "properties": {
        "hierarchy": [
          "tgn:2506240",
          "tgn:1000001",
          "tgn:2000272",
          "tgn:7012149",
          "tgn:7007240",
          "tgn:7029392"
        ],
        "placetype": [
          "aat:300008699"
        ],
        "id": 2506240,
        "name:xx": "Merrill Branch"
      }
    },
    {
      "geometry": {
        "type": "Point",
        "coordinates": [
          -90,
          33.4167
        ]
      },
      "type": "Feature",
      "properties": {
        "hierarchy": [
          "tgn:2506241",
          "tgn:1000001",
          "tgn:2001093",
          "tgn:7012149",
          "tgn:7007522",
          "tgn:7029392"
        ],
        "placetype": [
          "aat:300008699"
        ],
        "id": 2506241,
        "name:xx": "Merrill Branch"
      }
    },
    {
      "geometry": {
        "type": "Point",
        "coordinates": [
          -86.45,
          35.0167
        ]
      },
      "type": "Feature",
      "properties": {
        "hierarchy": [
          "tgn:2506242",
          "tgn:1000001",
          "tgn:7012149",
          "tgn:2001888",
          "tgn:7007825",
          "tgn:7029392"
        ],
        "placetype": [
          "aat:300008699"
        ],
        "id": 2506242,
        "name:xx": "Merrill Branch"
      }
    },
    {
      "geometry": {
        "type": "Point",
        "coordinates": [
          -88.2167,
          36.4
        ]
      },
      "type": "Feature",
      "properties": {
        "hierarchy": [
          "tgn:2506243",
          "tgn:1000001",
          "tgn:7012149",
          "tgn:2001876",
          "tgn:7007825",
          "tgn:7029392"
        ],
        "placetype": [
          "aat:300008699"
        ],
        "id": 2506243,
        "name:xx": "Merrill Branch"
      }
    },
    {
      "geometry": {
        "type": "Point",
        "coordinates": [
          -70.4333,
          43.5667
        ]
      },
      "type": "Feature",
      "properties": {
        "hierarchy": [
          "tgn:2506244",
          "tgn:1000001",
          "tgn:7012149",
          "tgn:7007515",
          "tgn:7029392"
        ],
        "placetype": [
          "aat:300008699"
        ],
        "id": 2506244,
        "name:xx": "Merrill Brook"
      }
    },
    {
      "geometry": {
        "type": "Point",
        "coordinates": [
          -70.9,
          44.45
        ]
      },
      "type": "Feature",
      "properties": {
        "hierarchy": [
          "tgn:2506245",
          "tgn:1000001",
          "tgn:7012149",
          "tgn:2000926",
          "tgn:7007515",
          "tgn:7029392"
        ],
        "placetype": [
          "aat:300008699"
        ],
        "id": 2506245,
        "name:xx": "Merrill Brook"
      }
    },
    {
      "geometry": {
        "type": "Point",
        "coordinates": [
          -69.3,
          45.1833
        ]
      },
      "type": "Feature",
      "properties": {
        "hierarchy": [
          "tgn:2506246",
          "tgn:1000001",
          "tgn:7012149",
          "tgn:2000928",
          "tgn:7007515",
          "tgn:7029392"
        ],
        "placetype": [
          "aat:300008699"
        ],
        "id": 2506246,
        "name:xx": "Merrill Brook"
      }
    },
    {
      "geometry": {
        "type": "Point",
        "coordinates": [
          -68.6333,
          45.2667
        ]
      },
      "type": "Feature",
      "properties": {
        "hierarchy": [
          "tgn:2506247",
          "tgn:1000001",
          "tgn:7012149",
          "tgn:2000927",
          "tgn:7007515",
          "tgn:7029392"
        ],
        "placetype": [
          "aat:300008699"
        ],
        "id": 2506247,
        "name:xx": "Merrill Brook"
      }
    },
    {
      "geometry": {
        "type": "Point",
        "coordinates": [
          -67.9167,
          45.7833
        ]
      },
      "type": "Feature",
      "properties": {
        "hierarchy": [
          "tgn:2506248",
          "tgn:2000919",
          "tgn:1000001",
          "tgn:7012149",
          "tgn:7007515",
          "tgn:7029392"
        ],
        "placetype": [
          "aat:300008699"
        ],
        "id": 2506248,
        "name:xx": "Merrill Brook"
      }
    },
    {
      "geometry": {
        "type": "Point",
        "coordinates": [
          -70.1167,
          43.8667
        ]
      },
      "type": "Feature",
      "properties": {
        "hierarchy": [
          "tgn:2506249",
          "tgn:1000001",
          "tgn:2000920",
          "tgn:7012149",
          "tgn:7007515",
          "tgn:7029392"
        ],
        "placetype": [
          "aat:300008699"
        ],
        "id": 2506249,
        "name:xx": "Merrill Brook"
      }
    }
  ]
}
