{
  "geometry": {
    "type": "Point",
    "coordinates": [
      -91.75,
      48.0667
    ]
  },
  "type": "Feature",
  "properties": {
    "hierarchy": [
      "tgn:2400539",
      "tgn:1000001",
      "tgn:7012149",
      "tgn:2001036",
      "tgn:7007521",
      "tgn:7029392"
    ],
    "placetype": [
      "aat:300008680"
    ],
    "id": 2400539,
    "name:xx": "Horse Lake"
  }
}
