{
  "geometry": {
    "type": "Point",
    "coordinates": [
      -75.5333,
      39.1833
    ]
  },
  "type": "Feature",
  "properties": {
    "hierarchy": [
      "tgn:2017839",
      "tgn:1002538",
      "tgn:1000001",
      "tgn:7012149",
      "tgn:7007239",
      "tgn:7029392"
    ],
    "placetype": [
      "aat:300008347"
    ],
    "id": 2017839,
    "name:xx": "Dupont Manor"
  }
}
