{
  "geometry": {
    "type": "Point",
    "coordinates": [
      -81.6167,
      30.1167
    ]
  },
  "type": "Feature",
  "properties": {
    "hierarchy": [
      "tgn:2757203",
      "tgn:1000001",
      "tgn:7012149",
      "tgn:2000283",
      "tgn:7007240",
      "tgn:7029392"
    ],
    "placetype": [
      "aat:300008347"
    ],
    "id": 2757203,
    "name:xx": "Wesley Manor Retirement Village"
  }
}
