{
  "geometry": {
    "type": "Point",
    "coordinates": [
      -123.7667,
      44.9833
    ]
  },
  "type": "Feature",
  "properties": {
    "hierarchy": [
      "tgn:2635968",
      "tgn:1000001",
      "tgn:7012149",
      "tgn:7007708",
      "tgn:7029392"
    ],
    "placetype": [
      "aat:300008798"
    ],
    "id": 2635968,
    "name:xx": "Saddle Bag Mountain"
  }
}
