{
  "geometry": {
    "type": "Point",
    "coordinates": [
      -109.05,
      33.7667
    ]
  },
  "type": "Feature",
  "properties": {
    "hierarchy": [
      "tgn:2138077",
      "tgn:2000090",
      "tgn:1000001",
      "tgn:7006451",
      "tgn:7012149",
      "tgn:7029392"
    ],
    "placetype": [
      "aat:300006191"
    ],
    "id": 2138077,
    "name:xx": "Arroy Tank"
  }
}
