{
  "geometry": {
    "type": "Point",
    "coordinates": [
      -117.75,
      47.0833
    ]
  },
  "type": "Feature",
  "properties": {
    "hierarchy": [
      "tgn:2299385",
      "tgn:1000001",
      "tgn:7012149",
      "tgn:2002252",
      "tgn:7007920",
      "tgn:7029392"
    ],
    "placetype": [
      "aat:300008680"
    ],
    "id": 2299385,
    "name:xx": "Duck Lake"
  }
}
