{
  "geometry": {
    "type": "Point",
    "coordinates": [
      -73.45,
      42.8667
    ]
  },
  "type": "Feature",
  "properties": {
    "hierarchy": [
      "tgn:2777308",
      "tgn:1000001",
      "tgn:7012149",
      "tgn:1002821",
      "tgn:7007568",
      "tgn:7029392"
    ],
    "placetype": [
      "aat:300008680"
    ],
    "id": 2777308,
    "name:xx": "Wing Pond"
  }
}
