{
  "geometry": {
    "type": "Point",
    "coordinates": [
      -90.2333,
      37.35
    ]
  },
  "type": "Feature",
  "properties": {
    "hierarchy": [
      "tgn:2350115",
      "tgn:1000001",
      "tgn:7012149",
      "tgn:2001217",
      "tgn:7007523",
      "tgn:7029392"
    ],
    "placetype": [
      "aat:300008706"
    ],
    "id": 2350115,
    "name:xx": "Gimlet Creek"
  }
}
