{
  "geometry": {
    "type": "Point",
    "coordinates": [
      -95.8833,
      34.5833
    ]
  },
  "type": "Feature",
  "properties": {
    "hierarchy": [
      "tgn:2757171",
      "tgn:2001625",
      "tgn:1000001",
      "tgn:7012149",
      "tgn:7007707",
      "tgn:7029392"
    ],
    "placetype": [
      "aat:300008347"
    ],
    "id": 2757171,
    "name:xx": "Wesley"
  }
}
