{
  "geometry": {
    "type": "Point",
    "coordinates": [
      -79.7167,
      35.75
    ]
  },
  "type": "Feature",
  "properties": {
    "hierarchy": [
      "tgn:2073993",
      "tgn:1000001",
      "tgn:7012149",
      "tgn:2001532",
      "tgn:7007709",
      "tgn:7029392"
    ],
    "placetype": [
      "aat:300008347"
    ],
    "id": 2073993,
    "name:xx": "Cedar Falls"
  }
}
