{
  "geometry": {
    "type": "Point",
    "coordinates": [
      -80.1167,
      39.7667
    ]
  },
  "type": "Feature",
  "properties": {
    "hierarchy": [
      "tgn:2338262",
      "tgn:1000001",
      "tgn:7012149",
      "tgn:2001724",
      "tgn:7007710",
      "tgn:7029392"
    ],
    "placetype": [
      "aat:300008699"
    ],
    "id": 2338262,
    "name:xx": "Fox Run"
  }
}
