{
  "geometry": {
    "type": "Point",
    "coordinates": [
      14.6333,
      56.8667
    ]
  },
  "type": "Feature",
  "properties": {
    "hierarchy": [
      "tgn:1063010",
      "tgn:1000003",
      "tgn:1000405",
      "tgn:1000097",
      "tgn:7029392"
    ],
    "placetype": [
      "aat:300008347"
    ],
    "id": 1063010,
    "name:xx": "Gemla"
  }
}
