{
  "geometry": {
    "type": "Point",
    "coordinates": [
      31.8167,
      -1.3167
    ]
  },
  "type": "Feature",
  "properties": {
    "hierarchy": [
      "tgn:1094564",
      "tgn:7001242",
      "tgn:1001778",
      "tgn:1000203",
      "tgn:7029392"
    ],
    "placetype": [
      "aat:300008347",
      "aat:300387220"
    ],
    "id": 1094564,
    "name:xx": "Bukoba"
  }
}
