{
  "geometry": {
    "type": "Point",
    "coordinates": [
      -103.8167,
      47.3667
    ]
  },
  "type": "Feature",
  "properties": {
    "hierarchy": [
      "tgn:2547088",
      "tgn:1000001",
      "tgn:7012149",
      "tgn:7007705",
      "tgn:7029392"
    ],
    "placetype": [
      "aat:300008706"
    ],
    "id": 2547088,
    "name:xx": "North Fork Prairie Dog Creek"
  }
}
