{
  "geometry": {
    "type": "Point",
    "coordinates": [
      -96.2833,
      33.0167
    ]
  },
  "type": "Feature",
  "properties": {
    "hierarchy": [
      "tgn:2571920",
      "tgn:1000001",
      "tgn:7012149",
      "tgn:7007826",
      "tgn:7029392"
    ],
    "placetype": [
      "aat:300008706"
    ],
    "id": 2571920,
    "name:xx": "Payne Creek"
  }
}
