{
  "geometry": {
    "type": "Point",
    "coordinates": [
      -114.0333,
      44.4833
    ]
  },
  "type": "Feature",
  "properties": {
    "hierarchy": [
      "tgn:2688731",
      "tgn:1000001",
      "tgn:2000470",
      "tgn:7012149",
      "tgn:7007250",
      "tgn:7029392"
    ],
    "placetype": [
      "aat:300386845"
    ],
    "id": 2688731,
    "name:xx": "Spud Basin"
  }
}
