{
  "geometry": {
    "type": "Point",
    "coordinates": [
      -86.45,
      38.4667
    ]
  },
  "type": "Feature",
  "properties": {
    "hierarchy": [
      "tgn:2033309",
      "tgn:1000001",
      "tgn:7012149",
      "tgn:1002750",
      "tgn:7007252",
      "tgn:7029392"
    ],
    "placetype": [
      "aat:300008347",
      "aat:300387210"
    ],
    "id": 2033309,
    "name:xx": "Pine Valley"
  }
}
