{
  "geometry": {
    "type": "Point",
    "coordinates": [
      110.75,
      -2.9833
    ]
  },
  "type": "Feature",
  "properties": {
    "hierarchy": [
      "tgn:1078105",
      "tgn:1000004",
      "tgn:1001338",
      "tgn:1000116",
      "tgn:7029392"
    ],
    "placetype": [
      "aat:300008347"
    ],
    "id": 1078105,
    "name:xx": "Matua"
  }
}
