{
  "geometry": {
    "type": "Point",
    "coordinates": [
      32.05,
      64.75
    ]
  },
  "type": "Feature",
  "properties": {
    "hierarchy": [
      "tgn:1054756",
      "tgn:1000004",
      "tgn:7011509",
      "tgn:7002435",
      "tgn:7029392"
    ],
    "placetype": [
      "aat:300008347"
    ],
    "id": 1054756,
    "name:xx": "Yushkozero"
  }
}
