{
  "geometry": {
    "type": "Point",
    "coordinates": [
      2.36524,
      42.313455
    ]
  },
  "type": "Feature",
  "properties": {
    "hierarchy": [
      "tgn:7343355",
      "tgn:7002820",
      "tgn:7030216",
      "tgn:1000003",
      "tgn:1000095",
      "tgn:7029392"
    ],
    "placetype": [
      "aat:300008347"
    ],
    "id": 7343355,
    "name:xx": "Camprodón"
  }
}
