{
  "geometry": {
    "type": "Point",
    "coordinates": [
      -119.75,
      34.5833
    ]
  },
  "type": "Feature",
  "properties": {
    "hierarchy": [
      "tgn:2612988",
      "tgn:1000001",
      "tgn:7012149",
      "tgn:7007157",
      "tgn:1002867",
      "tgn:7029392"
    ],
    "placetype": [
      "aat:300008761"
    ],
    "id": 2612988,
    "name:xx": "Redrock Canyon"
  }
}
