{
  "geometry": {
    "type": "Point",
    "coordinates": [
      -97.55,
      31.2167
    ]
  },
  "type": "Feature",
  "properties": {
    "hierarchy": [
      "tgn:2563395",
      "tgn:1000001",
      "tgn:1002174",
      "tgn:7012149",
      "tgn:7007826",
      "tgn:7029392"
    ],
    "placetype": [
      "aat:300008798"
    ],
    "id": 2563395,
    "name:xx": "Owl Creek Mountains"
  }
}
