{
  "geometry": {
    "type": "Point",
    "coordinates": [
      -104.05,
      34.9167
    ]
  },
  "type": "Feature",
  "properties": {
    "hierarchy": [
      "tgn:2712638",
      "tgn:1000001",
      "tgn:7012149",
      "tgn:2001448",
      "tgn:7007566",
      "tgn:7029392"
    ],
    "placetype": [
      "aat:300008761"
    ],
    "id": 2712638,
    "name:xx": "Taylor Canyon"
  }
}
