{
  "type": "FeatureCollection",
  "features": [
    {
      "geometry": {
        "type": "Point",
        "coordinates": [
          8.8,
          50.816667
        ]
      },
      "type": "Feature",
      "properties": {
        "hierarchy": [
          "tgn:7116883",
          "tgn:1000003",
          "tgn:7003678",
          "tgn:7000084",
          "tgn:7029392"
        ],
        "placetype": [
          "aat:300008777"
        ],
        "id": 7116883,
        "name:xx": "Orten-Berg"
      }
    },
    {
      "geometry": {
        "type": "Point",
        "coordinates": [
          8.8,
          48.166667
        ]
      },
      "type": "Feature",
      "properties": {
        "hierarchy": [
          "tgn:7116884",
          "tgn:7003692",
          "tgn:1000003",
          "tgn:7000084",
          "tgn:7029392"
        ],
        "placetype": [
          "aat:300008777"
        ],
        "id": 7116884,
        "name:xx": "Ortenberg"
      }
    },
    {
      "geometry": {
        "type": "Point",
        "coordinates": [
          8,
          48.45
        ]
      },
      "type": "Feature",
      "properties": {
        "hierarchy": [
          "tgn:7116885",
          "tgn:7003692",
          "tgn:1000003",
          "tgn:7000084",
          "tgn:7029392"
        ],
        "placetype": [
          "aat:300055621"
        ],
        "id": 7116885,
        "name:xx": "Ortenau"
      }
    },
    {
      "geometry": {
        "type": "Point",
        "coordinates": [
          11.5,
          50.483333
        ]
      },
      "type": "Feature",
      "properties": {
        "hierarchy": [
          "tgn:7116886",
          "tgn:1000003",
          "tgn:7003689",
          "tgn:7000084",
          "tgn:7029392"
        ],
        "placetype": [
          "aat:300008347"
        ],
        "id": 7116886,
        "name:xx": "Örtelsbruch"
      }
    },
    {
      "geometry": {
        "type": "Point",
        "coordinates": [
          10.95,
          50.316667
        ]
      },
      "type": "Feature",
      "properties": {
        "hierarchy": [
          "tgn:7116887",
          "tgn:7003669",
          "tgn:1000003",
          "tgn:7000084",
          "tgn:7029392"
        ],
        "placetype": [
          "aat:300008777"
        ],
        "id": 7116887,
        "name:xx": "Ortels-Berg"
      }
    },
    {
      "geometry": {
        "type": "Point",
        "coordinates": [
          9.05,
          52.466667
        ]
      },
      "type": "Feature",
      "properties": {
        "hierarchy": [
          "tgn:7116888",
          "tgn:1000003",
          "tgn:7003677",
          "tgn:7000084",
          "tgn:7029392"
        ],
        "placetype": [
          "aat:300008347"
        ],
        "id": 7116888,
        "name:xx": "Kolonie Ortbruch"
      }
    },
    {
      "geometry": {
        "type": "Point",
        "coordinates": [
          8.583333,
          52.866667
        ]
      },
      "type": "Feature",
      "properties": {
        "hierarchy": [
          "tgn:7116889",
          "tgn:1000003",
          "tgn:7003676",
          "tgn:7000084",
          "tgn:7029392"
        ],
        "placetype": [
          "aat:300000206"
        ],
        "id": 7116889,
        "name:xx": "Ortbrook"
      }
    }
  ]
}
