{
  "geometry": {
    "type": "Point",
    "coordinates": [
      -116.0167,
      48.2167
    ]
  },
  "type": "Feature",
  "properties": {
    "hierarchy": [
      "tgn:2645259",
      "tgn:1000001",
      "tgn:7012149",
      "tgn:7029392"
    ],
    "placetype": [
      "aat:300008706"
    ],
    "id": 2645259,
    "name:xx": "Savage Creek"
  }
}
