{
  "geometry": {
    "type": "Point",
    "coordinates": [
      -85.9167,
      39.45
    ]
  },
  "type": "Feature",
  "properties": {
    "hierarchy": [
      "tgn:2500116",
      "tgn:1000001",
      "tgn:7012149",
      "tgn:7007252",
      "tgn:7029392"
    ],
    "placetype": [
      "aat:300006075"
    ],
    "id": 2500116,
    "name:xx": "McCue Medsker Ditch"
  }
}
