{
  "geometry": {
    "type": "Point",
    "coordinates": [
      -121.3833,
      39.4333
    ]
  },
  "type": "Feature",
  "properties": {
    "hierarchy": [
      "tgn:2626556",
      "tgn:1000001",
      "tgn:1002218",
      "tgn:7012149",
      "tgn:7007157",
      "tgn:7029392"
    ],
    "placetype": [
      "aat:300008706"
    ],
    "id": 2626556,
    "name:xx": "Rocky Honcut Creek"
  }
}
