{
  "geometry": {
    "type": "Point",
    "coordinates": [
      -123.95,
      42.1333
    ]
  },
  "type": "Feature",
  "properties": {
    "hierarchy": [
      "tgn:2547409",
      "tgn:1000001",
      "tgn:7012149",
      "tgn:7029392"
    ],
    "placetype": [
      "aat:300008707"
    ],
    "id": 2547409,
    "name:xx": "North Fork Smith River"
  }
}
