{
  "geometry": {
    "type": "Point",
    "coordinates": [
      -112.25,
      34.3333
    ]
  },
  "type": "Feature",
  "properties": {
    "hierarchy": [
      "tgn:2376990",
      "tgn:1000001",
      "tgn:7006451",
      "tgn:7012149",
      "tgn:2000103",
      "tgn:7029392"
    ],
    "placetype": [
      "aat:300000390"
    ],
    "id": 2376990,
    "name:xx": "Harl Tank"
  }
}
