{
  "type": "FeatureCollection",
  "features": [
    {
      "geometry": {
        "type": "Point",
        "coordinates": [
          -81.3667,
          37.5667
        ]
      },
      "type": "Feature",
      "properties": {
        "hierarchy": [
          "tgn:2119331",
          "tgn:1000001",
          "tgn:7012149",
          "tgn:2002304",
          "tgn:7013961",
          "tgn:7029392"
        ],
        "placetype": [
          "aat:300008347"
        ],
        "id": 2119331,
        "name:xx": "Mullens"
      }
    },
    {
      "geometry": {
        "type": "Point",
        "coordinates": [
          -81.55,
          37.5667
        ]
      },
      "type": "Feature",
      "properties": {
        "hierarchy": [
          "tgn:2119335",
          "tgn:1000001",
          "tgn:7012149",
          "tgn:2002304",
          "tgn:7013961",
          "tgn:7029392"
        ],
        "placetype": [
          "aat:300008347"
        ],
        "id": 2119335,
        "name:xx": "Mullensville"
      }
    },
    {
      "geometry": {
        "type": "Point",
        "coordinates": [
          -81.2,
          39
        ]
      },
      "type": "Feature",
      "properties": {
        "hierarchy": [
          "tgn:2119336",
          "tgn:1000001",
          "tgn:7012149",
          "tgn:2002302",
          "tgn:7013961",
          "tgn:7029392"
        ],
        "placetype": [
          "aat:300008347"
        ],
        "id": 2119336,
        "name:xx": "Munday"
      }
    },
    {
      "geometry": {
        "type": "Point",
        "coordinates": [
          -80.1333,
          39.05
        ]
      },
      "type": "Feature",
      "properties": {
        "hierarchy": [
          "tgn:2119338",
          "tgn:2002253",
          "tgn:1000001",
          "tgn:7012149",
          "tgn:7013961",
          "tgn:7029392"
        ],
        "placetype": [
          "aat:300008347",
          "aat:300387210"
        ],
        "id": 2119338,
        "name:xx": "Murphy"
      }
    },
    {
      "geometry": {
        "type": "Point",
        "coordinates": [
          -81.4333,
          39.2333
        ]
      },
      "type": "Feature",
      "properties": {
        "hierarchy": [
          "tgn:2119339",
          "tgn:1000001",
          "tgn:7012149",
          "tgn:2002303",
          "tgn:7013961",
          "tgn:7029392"
        ],
        "placetype": [
          "aat:300008347"
        ],
        "id": 2119339,
        "name:xx": "Murphytown"
      }
    }
  ]
}
