{
  "geometry": {
    "type": "Point",
    "coordinates": [
      -84.9833,
      39.7667
    ]
  },
  "type": "Feature",
  "properties": {
    "hierarchy": [
      "tgn:2351520",
      "tgn:1000001",
      "tgn:7012149",
      "tgn:1003004",
      "tgn:7007252",
      "tgn:7029392"
    ],
    "placetype": [
      "aat:300006191"
    ],
    "id": 2351520,
    "name:xx": "Glen White Lake"
  }
}
