{
  "geometry": {
    "type": "Point",
    "coordinates": [
      -117.8667,
      40.7333
    ]
  },
  "type": "Feature",
  "properties": {
    "hierarchy": [
      "tgn:2388728",
      "tgn:1000001",
      "tgn:2001419",
      "tgn:7012149",
      "tgn:7007526",
      "tgn:7029392"
    ],
    "placetype": [
      "aat:300008761"
    ],
    "id": 2388728,
    "name:xx": "Hidden Canyon"
  }
}
