{
  "geometry": {
    "type": "Point",
    "coordinates": [
      -95.7167,
      31.8667
    ]
  },
  "type": "Feature",
  "properties": {
    "hierarchy": [
      "tgn:2106108",
      "tgn:1002148",
      "tgn:1000001",
      "tgn:7012149",
      "tgn:7007826",
      "tgn:7029392"
    ],
    "placetype": [
      "aat:300008347"
    ],
    "id": 2106108,
    "name:xx": "Montalba"
  }
}
