{
  "type": "FeatureCollection",
  "features": [
    {
      "geometry": {
        "type": "Point",
        "coordinates": [
          16.2833,
          48.1167
        ]
      },
      "type": "Feature",
      "properties": {
        "hierarchy": [
          "tgn:1025470",
          "tgn:7003025",
          "tgn:1000003",
          "tgn:1000062",
          "tgn:7029392"
        ],
        "placetype": [
          "aat:300008347"
        ],
        "id": 1025470,
        "name:xx": "Brunn am Gebirge"
      }
    },
    {
      "geometry": {
        "type": "Point",
        "coordinates": [
          13.1,
          48.2
        ]
      },
      "type": "Feature",
      "properties": {
        "hierarchy": [
          "tgn:1025471",
          "tgn:7003026",
          "tgn:1000003",
          "tgn:1000062",
          "tgn:7029392"
        ],
        "placetype": [
          "aat:300008347"
        ],
        "id": 1025471,
        "name:xx": "Burgkirchen"
      }
    },
    {
      "geometry": {
        "type": "Point",
        "coordinates": [
          13.6667,
          46.8
        ]
      },
      "type": "Feature",
      "properties": {
        "hierarchy": [
          "tgn:1025472",
          "tgn:7003024",
          "tgn:1000003",
          "tgn:1000062",
          "tgn:7029392"
        ],
        "placetype": [
          "aat:300008347"
        ],
        "id": 1025472,
        "name:xx": "Döbriach"
      }
    },
    {
      "geometry": {
        "type": "Point",
        "coordinates": [
          12.9,
          46.9833
        ]
      },
      "type": "Feature",
      "properties": {
        "hierarchy": [
          "tgn:1025473",
          "tgn:7003024",
          "tgn:1000003",
          "tgn:1000062",
          "tgn:7029392"
        ],
        "placetype": [
          "aat:300008347"
        ],
        "id": 1025473,
        "name:xx": "Döllach"
      }
    },
    {
      "geometry": {
        "type": "Point",
        "coordinates": [
          16.8667,
          48.4833
        ]
      },
      "type": "Feature",
      "properties": {
        "hierarchy": [
          "tgn:1025475",
          "tgn:7003025",
          "tgn:1000003",
          "tgn:1000062",
          "tgn:7029392"
        ],
        "placetype": [
          "aat:300008347"
        ],
        "id": 1025475,
        "name:xx": "Dürnkrut"
      }
    },
    {
      "geometry": {
        "type": "Point",
        "coordinates": [
          10,
          47.1167
        ]
      },
      "type": "Feature",
      "properties": {
        "hierarchy": [
          "tgn:1025476",
          "tgn:7018001",
          "tgn:1000003",
          "tgn:1000062",
          "tgn:7029392"
        ],
        "placetype": [
          "aat:300008347"
        ],
        "id": 1025476,
        "name:xx": "Dalaas"
      }
    },
    {
      "geometry": {
        "type": "Point",
        "coordinates": [
          9.8833,
          47.2833
        ]
      },
      "type": "Feature",
      "properties": {
        "hierarchy": [
          "tgn:1025477",
          "tgn:7018001",
          "tgn:1000003",
          "tgn:1000062",
          "tgn:7029392"
        ],
        "placetype": [
          "aat:300008347"
        ],
        "id": 1025477,
        "name:xx": "Damüls"
      }
    },
    {
      "geometry": {
        "type": "Point",
        "coordinates": [
          13.0833,
          46.6667
        ]
      },
      "type": "Feature",
      "properties": {
        "hierarchy": [
          "tgn:1025478",
          "tgn:7003024",
          "tgn:1000003",
          "tgn:1000062",
          "tgn:7029392"
        ],
        "placetype": [
          "aat:300008347"
        ],
        "id": 1025478,
        "name:xx": "Dellach"
      }
    }
  ]
}
