{
  "geometry": {
    "type": "Point",
    "coordinates": [
      104.8667,
      30.5833
    ]
  },
  "type": "Feature",
  "properties": {
    "hierarchy": [
      "tgn:1069360",
      "tgn:1000004",
      "tgn:7002087",
      "tgn:1000111",
      "tgn:7029392"
    ],
    "placetype": [
      "aat:300008347"
    ],
    "id": 1069360,
    "name:xx": "Jinshanxiang"
  }
}
