{
  "geometry": {
    "type": "Point",
    "coordinates": [
      -75.8167,
      37.5833
    ]
  },
  "type": "Feature",
  "properties": {
    "hierarchy": [
      "tgn:2299881",
      "tgn:1002132",
      "tgn:1000001",
      "tgn:7012149",
      "tgn:7007919",
      "tgn:7029392"
    ],
    "placetype": [
      "aat:300006191"
    ],
    "id": 2299881,
    "name:xx": "Duer Pond"
  }
}
