{
  "geometry": {
    "type": "Point",
    "coordinates": [
      20.4667,
      52.0333
    ]
  },
  "type": "Feature",
  "properties": {
    "hierarchy": [
      "tgn:7007592",
      "tgn:1000003",
      "tgn:7024121",
      "tgn:7006366",
      "tgn:7029392"
    ],
    "placetype": [
      "aat:300008347"
    ],
    "id": 7007592,
    "name:xx": "Zyrardów"
  }
}
