{
  "geometry": {
    "type": "Point",
    "coordinates": [
      -85.75,
      35.4833
    ]
  },
  "type": "Feature",
  "properties": {
    "hierarchy": [
      "tgn:2550086",
      "tgn:1000001",
      "tgn:7012149",
      "tgn:2001867",
      "tgn:7007825",
      "tgn:7029392"
    ],
    "placetype": [
      "aat:300008746"
    ],
    "id": 2550086,
    "name:xx": "Northcutt Cave"
  }
}
