{
  "geometry": {
    "type": "Point",
    "coordinates": [
      -112.0333,
      39.75
    ]
  },
  "type": "Feature",
  "properties": {
    "hierarchy": [
      "tgn:2454691",
      "tgn:1000001",
      "tgn:7012149",
      "tgn:7007827",
      "tgn:7029392"
    ],
    "placetype": [
      "aat:300008761"
    ],
    "id": 2454691,
    "name:xx": "Little Dog Valley"
  }
}
