{
  "geometry": {
    "type": "Point",
    "coordinates": [
      7.1833,
      51.4167
    ]
  },
  "type": "Feature",
  "properties": {
    "hierarchy": [
      "tgn:1134091",
      "tgn:1000003",
      "tgn:7003677",
      "tgn:7000084",
      "tgn:7029392"
    ],
    "placetype": [
      "aat:300008706"
    ],
    "id": 1134091,
    "name:xx": "Paasbach"
  }
}
