{
  "geometry": {
    "type": "Point",
    "coordinates": [
      -78.3667,
      37.8833
    ]
  },
  "type": "Feature",
  "properties": {
    "hierarchy": [
      "tgn:2333003",
      "tgn:1000001",
      "tgn:7012149",
      "tgn:2002159",
      "tgn:7007919",
      "tgn:7029392"
    ],
    "placetype": [
      "aat:300006191"
    ],
    "id": 2333003,
    "name:xx": "Fluvanna Ruritan Lake"
  }
}
