{
  "geometry": {
    "type": "Point",
    "coordinates": [
      80.5667,
      16.0667
    ]
  },
  "type": "Feature",
  "properties": {
    "hierarchy": [
      "tgn:1076623",
      "tgn:1001828",
      "tgn:1000004",
      "tgn:7000198",
      "tgn:7029392"
    ],
    "placetype": [
      "aat:300008347"
    ],
    "name:en": "Ponnūru",
    "id": 1076623
  }
}
