{
  "geometry": {
    "type": "Point",
    "coordinates": [
      31.553227,
      26.663872
    ]
  },
  "type": "Feature",
  "properties": {
    "hierarchy": [
      "tgn:7524571",
      "tgn:7001242",
      "tgn:7016833",
      "tgn:7000124",
      "tgn:7029392"
    ],
    "placetype": [
      "aat:300008347"
    ],
    "name:en": "Awlād Ismā'īl",
    "id": 7524571
  }
}
