{
  "geometry": {
    "type": "Point",
    "coordinates": [
      31.70658,
      30.75018
    ]
  },
  "type": "Feature",
  "properties": {
    "hierarchy": [
      "tgn:7529073",
      "tgn:7001242",
      "tgn:7016833",
      "tgn:1001113",
      "tgn:7029392"
    ],
    "placetype": [
      "aat:300006075"
    ],
    "id": 7529073,
    "name:xx": "Tur'at al Mashā'lah"
  }
}
