{
  "geometry": {
    "type": "Point",
    "coordinates": [
      -81.0333,
      34.95
    ]
  },
  "type": "Feature",
  "properties": {
    "hierarchy": [
      "tgn:2383609",
      "tgn:1000001",
      "tgn:7012149",
      "tgn:2001770",
      "tgn:7007712",
      "tgn:7029392"
    ],
    "placetype": [
      "aat:300008347"
    ],
    "id": 2383609,
    "name:xx": "Heatherwood"
  }
}
