{
  "geometry": {
    "type": "Point",
    "coordinates": [
      -121.0667,
      46.6333
    ]
  },
  "type": "Feature",
  "properties": {
    "hierarchy": [
      "tgn:2237195",
      "tgn:1000001",
      "tgn:7012149",
      "tgn:1003042",
      "tgn:7007920",
      "tgn:7029392"
    ],
    "placetype": [
      "aat:300008798"
    ],
    "id": 2237195,
    "name:xx": "Chimney Peaks"
  }
}
