{
  "geometry": {
    "type": "Point",
    "coordinates": [
      -91.6167,
      36.5667
    ]
  },
  "type": "Feature",
  "properties": {
    "hierarchy": [
      "tgn:2317856",
      "tgn:1000001",
      "tgn:7012149",
      "tgn:7029392"
    ],
    "placetype": [
      "aat:300008706"
    ],
    "id": 2317856,
    "name:xx": "English Creek"
  }
}
