{
  "geometry": {
    "type": "Point",
    "coordinates": [
      -111.05,
      34.4833
    ]
  },
  "type": "Feature",
  "properties": {
    "hierarchy": [
      "tgn:2771957",
      "tgn:1000001",
      "tgn:7006451",
      "tgn:2000092",
      "tgn:7012149",
      "tgn:7029392"
    ],
    "placetype": [
      "aat:300008761"
    ],
    "id": 2771957,
    "name:xx": "Wilkins Canyon"
  }
}
