{
  "geometry": {
    "type": "Point",
    "coordinates": [
      116.5333,
      40.0167
    ]
  },
  "type": "Feature",
  "properties": {
    "hierarchy": [
      "tgn:1067062",
      "tgn:1000956",
      "tgn:1000004",
      "tgn:1000111",
      "tgn:7029392"
    ],
    "placetype": [
      "aat:300008347"
    ],
    "id": 1067062,
    "name:xx": "Changdian"
  }
}
