{
  "geometry": {
    "type": "Point",
    "coordinates": [
      -103.6833,
      38.9667
    ]
  },
  "type": "Feature",
  "properties": {
    "hierarchy": [
      "tgn:2339523",
      "tgn:1000001",
      "tgn:7012149",
      "tgn:2000228",
      "tgn:7007158",
      "tgn:7029392"
    ],
    "placetype": [
      "aat:300006191"
    ],
    "id": 2339523,
    "name:xx": "Fred Pauls Detention Reservoir Number 1"
  }
}
