{
  "geometry": {
    "type": "Point",
    "coordinates": [
      -109.45,
      45.4833
    ]
  },
  "type": "Feature",
  "properties": {
    "hierarchy": [
      "tgn:2629968",
      "tgn:1000001",
      "tgn:7012149",
      "tgn:2001307",
      "tgn:7007524",
      "tgn:7029392"
    ],
    "placetype": [
      "aat:300006075"
    ],
    "id": 2629968,
    "name:xx": "Ross-Flannigan Ditch"
  }
}
