{
  "geometry": {
    "type": "Point",
    "coordinates": [
      3.2667,
      49.1667
    ]
  },
  "type": "Feature",
  "properties": {
    "hierarchy": [
      "tgn:7010558",
      "tgn:1000003",
      "tgn:7002890",
      "tgn:1000070",
      "tgn:7029392"
    ],
    "placetype": [
      "aat:300008347"
    ],
    "id": 7010558,
    "name:xx": "Neuilly-Saint Front"
  }
}
