{
  "geometry": {
    "type": "Point",
    "coordinates": [
      -86.4167,
      32.65
    ]
  },
  "type": "Feature",
  "properties": {
    "hierarchy": [
      "tgn:2582379",
      "tgn:7002659",
      "tgn:1000001",
      "tgn:2000010",
      "tgn:7012149",
      "tgn:7029392"
    ],
    "placetype": [
      "aat:300008347"
    ],
    "id": 2582379,
    "name:xx": "Pine Flat"
  }
}
