{
  "geometry": {
    "type": "Point",
    "coordinates": [
      -95.9667,
      39.3333
    ]
  },
  "type": "Feature",
  "properties": {
    "hierarchy": [
      "tgn:2409818",
      "tgn:1000001",
      "tgn:2000702",
      "tgn:7012149",
      "tgn:7007254",
      "tgn:7029392"
    ],
    "placetype": [
      "aat:300008706"
    ],
    "id": 2409818,
    "name:xx": "Illinois Creek"
  }
}
