{
  "geometry": {
    "type": "Point",
    "coordinates": [
      37.05,
      33.35
    ]
  },
  "type": "Feature",
  "properties": {
    "hierarchy": [
      "tgn:1107821",
      "tgn:1000004",
      "tgn:7593756",
      "tgn:1000140",
      "tgn:7029392"
    ],
    "placetype": [
      "aat:300008777"
    ],
    "id": 1107821,
    "name:xx": "Ḥajar, Tall al-"
  }
}
