{
  "geometry": {
    "type": "Point",
    "coordinates": [
      6.45,
      50.55
    ]
  },
  "type": "Feature",
  "properties": {
    "hierarchy": [
      "tgn:1039561",
      "tgn:1000003",
      "tgn:7003677",
      "tgn:7000084",
      "tgn:7029392"
    ],
    "placetype": [
      "aat:300008347"
    ],
    "id": 1039561,
    "name:xx": "Herhahn"
  }
}
