{
  "geometry": {
    "type": "Point",
    "coordinates": [
      -105.3333,
      36.75
    ]
  },
  "type": "Feature",
  "properties": {
    "hierarchy": [
      "tgn:2168152",
      "tgn:1000001",
      "tgn:7012149",
      "tgn:2001457",
      "tgn:7007566",
      "tgn:7029392"
    ],
    "placetype": [
      "aat:300000390"
    ],
    "id": 2168152,
    "name:xx": "Big Five Prospect"
  }
}
