{
  "type": "FeatureCollection",
  "features": [
    {
      "geometry": {
        "type": "Point",
        "coordinates": [
          4.5,
          51.5
        ]
      },
      "type": "Feature",
      "properties": {
        "hierarchy": [
          "tgn:7268750",
          "tgn:1000003",
          "tgn:7003624",
          "tgn:7016845",
          "tgn:7029392"
        ],
        "placetype": [
          "aat:300008688"
        ],
        "name:nl": "Rozenven",
        "id": 7268750
      }
    },
    {
      "geometry": {
        "type": "Point",
        "coordinates": [
          4.833333,
          52.016667
        ]
      },
      "type": "Feature",
      "properties": {
        "hierarchy": [
          "tgn:7268751",
          "tgn:1000003",
          "tgn:7003632",
          "tgn:7016845",
          "tgn:7029392"
        ],
        "placetype": [
          "aat:300006163"
        ],
        "name:nl": "Rozendaal, Polder",
        "id": 7268751
      }
    },
    {
      "geometry": {
        "type": "Point",
        "coordinates": [
          5.933333,
          51.133333
        ]
      },
      "type": "Feature",
      "properties": {
        "hierarchy": [
          "tgn:7268753",
          "tgn:1000003",
          "tgn:7003622",
          "tgn:7016845",
          "tgn:7029392"
        ],
        "placetype": [
          "aat:300008187"
        ],
        "name:nl": "Rozendaal",
        "id": 7268753
      }
    },
    {
      "geometry": {
        "type": "Point",
        "coordinates": [
          4.85,
          52.016667
        ]
      },
      "type": "Feature",
      "properties": {
        "hierarchy": [
          "tgn:7268755",
          "tgn:1000003",
          "tgn:7003632",
          "tgn:7016845",
          "tgn:7029392"
        ],
        "placetype": [
          "aat:300008347"
        ],
        "name:nl": "Rozendaal",
        "id": 7268755
      }
    },
    {
      "geometry": {
        "type": "Point",
        "coordinates": [
          6.05,
          51.383333
        ]
      },
      "type": "Feature",
      "properties": {
        "hierarchy": [
          "tgn:7268756",
          "tgn:1000003",
          "tgn:7003622",
          "tgn:7016845",
          "tgn:7029392"
        ],
        "placetype": [
          "aat:300008347"
        ],
        "name:nl": "Rozendaal",
        "id": 7268756
      }
    },
    {
      "geometry": {
        "type": "Point",
        "coordinates": [
          4.733333,
          52.283333
        ]
      },
      "type": "Feature",
      "properties": {
        "hierarchy": [
          "tgn:7268758",
          "tgn:1000003",
          "tgn:7006951",
          "tgn:7016845",
          "tgn:7029392"
        ],
        "placetype": [
          "aat:300008347"
        ],
        "name:nl": "Rozenburg",
        "id": 7268758
      }
    },
    {
      "geometry": {
        "type": "Point",
        "coordinates": [
          4.25,
          51.9
        ]
      },
      "type": "Feature",
      "properties": {
        "hierarchy": [
          "tgn:7268759",
          "tgn:1000003",
          "tgn:7003632",
          "tgn:7016845",
          "tgn:7029392"
        ],
        "placetype": [
          "aat:300008347",
          "aat:300387200"
        ],
        "name:nl": "Rozenburg",
        "id": 7268759
      }
    }
  ]
}
