{
  "geometry": {
    "type": "Point",
    "coordinates": [
      121.7946,
      24.6642
    ]
  },
  "type": "Feature",
  "properties": {
    "hierarchy": [
      "tgn:7474299",
      "tgn:1000004",
      "tgn:7489179",
      "tgn:1000141",
      "tgn:7029392"
    ],
    "placetype": [
      "aat:300008347"
    ],
    "id": 7474299,
    "name:xx": "Yuemei"
  }
}
