{
  "geometry": {
    "type": "Point",
    "coordinates": [
      -149.0333,
      61.7167
    ]
  },
  "type": "Feature",
  "properties": {
    "hierarchy": [
      "tgn:2538929",
      "tgn:7006450",
      "tgn:1000001",
      "tgn:2124053",
      "tgn:7012149",
      "tgn:7029392"
    ],
    "placetype": [
      "aat:300000390"
    ],
    "id": 2538929,
    "name:xx": "New Black Diamond Mine"
  }
}
