{
  "geometry": {
    "type": "Point",
    "coordinates": [
      3.3667,
      36.25
    ]
  },
  "type": "Feature",
  "properties": {
    "hierarchy": [
      "tgn:1087431",
      "tgn:7001242",
      "tgn:1000597",
      "tgn:7016752",
      "tgn:7029392"
    ],
    "placetype": [
      "aat:300008347"
    ],
    "id": 1087431,
    "name:xx": "El Arba"
  }
}
