{
  "geometry": {
    "type": "Point",
    "coordinates": [
      -112.15,
      33.1333
    ]
  },
  "type": "Feature",
  "properties": {
    "hierarchy": [
      "tgn:2521340",
      "tgn:1000001",
      "tgn:7006451",
      "tgn:7012149",
      "tgn:2000101",
      "tgn:7029392"
    ],
    "placetype": [
      "aat:300008798"
    ],
    "id": 2521340,
    "name:xx": "Montezumas Head"
  }
}
