{
  "geometry": {
    "type": "Point",
    "coordinates": [
      -76.0667,
      41.6667
    ]
  },
  "type": "Feature",
  "properties": {
    "hierarchy": [
      "tgn:2223627",
      "tgn:1000001",
      "tgn:7012149",
      "tgn:1002932",
      "tgn:7007710",
      "tgn:7029392"
    ],
    "placetype": [
      "aat:300008706"
    ],
    "id": 2223627,
    "name:xx": "Carter Creek"
  }
}
