{
  "geometry": {
    "type": "Point",
    "coordinates": [
      -101.3667,
      31.6333
    ]
  },
  "type": "Feature",
  "properties": {
    "hierarchy": [
      "tgn:2257669",
      "tgn:1000001",
      "tgn:7012149",
      "tgn:2002059",
      "tgn:7007826",
      "tgn:7029392"
    ],
    "placetype": [
      "aat:300008706"
    ],
    "id": 2257669,
    "name:xx": "Corral Creek"
  }
}
