{
  "geometry": {
    "type": "Point",
    "coordinates": [
      -116.95,
      45.8833
    ]
  },
  "type": "Feature",
  "properties": {
    "hierarchy": [
      "tgn:2341499",
      "tgn:1000001",
      "tgn:7012149",
      "tgn:2001722",
      "tgn:7007708",
      "tgn:7029392"
    ],
    "placetype": [
      "aat:300008680"
    ],
    "id": 2341499,
    "name:xx": "Frog Pond"
  }
}
