{
  "geometry": {
    "type": "Point",
    "coordinates": [
      -120.8833,
      39.35
    ]
  },
  "type": "Feature",
  "properties": {
    "hierarchy": [
      "tgn:1002710",
      "tgn:1000001",
      "tgn:7012149",
      "tgn:7007157",
      "tgn:7029392"
    ],
    "placetype": [
      "aat:300387145",
      "aat:300000771"
    ],
    "id": 1002710,
    "name:xx": "Nevada"
  }
}
