{
  "geometry": {
    "type": "Point",
    "coordinates": [
      7.85,
      51.15
    ]
  },
  "type": "Feature",
  "properties": {
    "hierarchy": [
      "tgn:7170711",
      "tgn:1000003",
      "tgn:7003677",
      "tgn:7000084",
      "tgn:7029392"
    ],
    "placetype": [
      "aat:300008777"
    ],
    "id": 7170711,
    "name:xx": "Heß-Berg"
  }
}
