{
  "geometry": {
    "type": "Point",
    "coordinates": [
      47.8667,
      -18.3667
    ]
  },
  "type": "Feature",
  "properties": {
    "hierarchy": [
      "tgn:1090807",
      "tgn:1001103",
      "tgn:7001242",
      "tgn:1000173",
      "tgn:7029392"
    ],
    "placetype": [
      "aat:300008347"
    ],
    "id": 1090807,
    "name:xx": "Anjozorobe"
  }
}
