{
  "geometry": {
    "type": "Point",
    "coordinates": [
      -75.6333,
      41.7667
    ]
  },
  "type": "Feature",
  "properties": {
    "hierarchy": [
      "tgn:2721130",
      "tgn:1000001",
      "tgn:7012149",
      "tgn:1002932",
      "tgn:7007710",
      "tgn:7029392"
    ],
    "placetype": [
      "aat:300008798"
    ],
    "id": 2721130,
    "name:xx": "Tiffany Hill"
  }
}
