{
  "geometry": {
    "type": "Point",
    "coordinates": [
      -5.85,
      42.75
    ]
  },
  "type": "Feature",
  "properties": {
    "hierarchy": [
      "tgn:7323386",
      "tgn:7002826",
      "tgn:7001158",
      "tgn:1000003",
      "tgn:1000095",
      "tgn:7029392"
    ],
    "placetype": [
      "aat:300008347"
    ],
    "id": 7323386,
    "name:xx": "Ríocastrillo de Ordás"
  }
}
