{
  "geometry": {
    "type": "Point",
    "coordinates": [
      -99.1425,
      19.981667
    ]
  },
  "type": "Feature",
  "properties": {
    "hierarchy": [
      "tgn:7398507",
      "tgn:1000001",
      "tgn:1001893",
      "tgn:7005560",
      "tgn:7029392"
    ],
    "placetype": [
      "aat:300008347"
    ],
    "id": 7398507,
    "name:xx": "Pérez de Galeana"
  }
}
