{
  "type": "FeatureCollection",
  "features": [
    {
      "geometry": {
        "type": "Point",
        "coordinates": [
          -24.25,
          16.5833
        ]
      },
      "type": "Feature",
      "properties": {
        "hierarchy": [
          "tgn:1008852",
          "tgn:7001634",
          "tgn:7001242",
          "tgn:7001632",
          "tgn:7029392"
        ],
        "placetype": [
          "aat:300387145",
          "aat:300008791",
          "aat:300000771"
        ],
        "id": 1008852,
        "name:xx": "São Nicolau"
      }
    },
    {
      "geometry": {
        "type": "Point",
        "coordinates": [
          -45.2833,
          -23.8833
        ]
      },
      "type": "Feature",
      "properties": {
        "hierarchy": [
          "tgn:1008853",
          "tgn:1001945",
          "tgn:1000047",
          "tgn:7002457",
          "tgn:1000002",
          "tgn:7029392"
        ],
        "placetype": [
          "aat:300008791"
        ],
        "id": 1008853,
        "name:xx": "São Sebastião, Ilha de"
      }
    },
    {
      "geometry": {
        "type": "Point",
        "coordinates": [
          -25,
          16.8333
        ]
      },
      "type": "Feature",
      "properties": {
        "hierarchy": [
          "tgn:1008855",
          "tgn:7001634",
          "tgn:7001242",
          "tgn:7001632",
          "tgn:7029392"
        ],
        "placetype": [
          "aat:300387145",
          "aat:300008791",
          "aat:300000771"
        ],
        "id": 1008855,
        "name:xx": "São Vicente"
      }
    },
    {
      "geometry": {
        "type": "Point",
        "coordinates": [
          8.55,
          54.466667
        ]
      },
      "type": "Feature",
      "properties": {
        "hierarchy": [
          "tgn:1008856",
          "tgn:1000003",
          "tgn:7003688",
          "tgn:7000084",
          "tgn:7029392"
        ],
        "placetype": [
          "aat:300008791"
        ],
        "id": 1008856,
        "name:xx": "Süderoog"
      }
    },
    {
      "geometry": {
        "type": "Point",
        "coordinates": [
          8.733333,
          54.466667
        ]
      },
      "type": "Feature",
      "properties": {
        "hierarchy": [
          "tgn:1008857",
          "tgn:1000003",
          "tgn:7003688",
          "tgn:7000084",
          "tgn:7029392"
        ],
        "placetype": [
          "aat:300008791"
        ],
        "id": 1008857,
        "name:xx": "Südfall"
      }
    },
    {
      "geometry": {
        "type": "Point",
        "coordinates": [
          125,
          38.6333
        ]
      },
      "type": "Feature",
      "properties": {
        "hierarchy": [
          "tgn:1008859",
          "tgn:1001301",
          "tgn:1000004",
          "tgn:1000122",
          "tgn:7029392"
        ],
        "placetype": [
          "aat:300008791"
        ],
        "id": 1008859,
        "name:xx": "Sŏk-to"
      }
    }
  ]
}
