{
  "type": "FeatureCollection",
  "features": [
    {
      "geometry": {
        "type": "Point",
        "coordinates": [
          -116.5,
          36.8667
        ]
      },
      "type": "Feature",
      "properties": {
        "hierarchy": [
          "tgn:2214950",
          "tgn:1000001",
          "tgn:2001418",
          "tgn:7012149",
          "tgn:7007526",
          "tgn:7029392"
        ],
        "placetype": [
          "aat:300008798"
        ],
        "id": 2214950,
        "name:xx": "Calico Hills"
      }
    },
    {
      "geometry": {
        "type": "Point",
        "coordinates": [
          -119.2333,
          41.2
        ]
      },
      "type": "Feature",
      "properties": {
        "hierarchy": [
          "tgn:2214951",
          "tgn:1000001",
          "tgn:7012149",
          "tgn:7007526",
          "tgn:7029392"
        ],
        "placetype": [
          "aat:300386831"
        ],
        "id": 2214951,
        "name:xx": "Calico Hills"
      }
    },
    {
      "geometry": {
        "type": "Point",
        "coordinates": [
          -90.3333,
          38.2
        ]
      },
      "type": "Feature",
      "properties": {
        "hierarchy": [
          "tgn:2214952",
          "tgn:1000001",
          "tgn:7012149",
          "tgn:1002677",
          "tgn:7007251",
          "tgn:7029392"
        ],
        "placetype": [
          "aat:300008791"
        ],
        "id": 2214952,
        "name:xx": "Calico Island"
      }
    },
    {
      "geometry": {
        "type": "Point",
        "coordinates": [
          -91.1,
          48.0667
        ]
      },
      "type": "Feature",
      "properties": {
        "hierarchy": [
          "tgn:2214953",
          "tgn:1000001",
          "tgn:7012149",
          "tgn:2001036",
          "tgn:7007521",
          "tgn:7029392"
        ],
        "placetype": [
          "aat:300008680"
        ],
        "id": 2214953,
        "name:xx": "Calico Lake"
      }
    },
    {
      "geometry": {
        "type": "Point",
        "coordinates": [
          -112.4667,
          43.0667
        ]
      },
      "type": "Feature",
      "properties": {
        "hierarchy": [
          "tgn:2214954",
          "tgn:1000001",
          "tgn:2000457",
          "tgn:7012149",
          "tgn:7007250",
          "tgn:7029392"
        ],
        "placetype": [
          "aat:300006075"
        ],
        "id": 2214954,
        "name:xx": "Calico Lateral"
      }
    },
    {
      "geometry": {
        "type": "Point",
        "coordinates": [
          -93.7333,
          35.2333
        ]
      },
      "type": "Feature",
      "properties": {
        "hierarchy": [
          "tgn:2214955",
          "tgn:1000001",
          "tgn:7016172",
          "tgn:7012149",
          "tgn:2000146",
          "tgn:7029392"
        ],
        "placetype": [
          "aat:300008798"
        ],
        "id": 2214955,
        "name:xx": "Calico Mountain"
      }
    },
    {
      "geometry": {
        "type": "Point",
        "coordinates": [
          -106.3,
          38.6167
        ]
      },
      "type": "Feature",
      "properties": {
        "hierarchy": [
          "tgn:2214956",
          "tgn:1000001",
          "tgn:2000199",
          "tgn:7012149",
          "tgn:7007158",
          "tgn:7029392"
        ],
        "placetype": [
          "aat:300008798"
        ],
        "id": 2214956,
        "name:xx": "Calico Mountain"
      }
    },
    {
      "geometry": {
        "type": "Point",
        "coordinates": [
          -84.2,
          36.55
        ]
      },
      "type": "Feature",
      "properties": {
        "hierarchy": [
          "tgn:2214957",
          "tgn:1000001",
          "tgn:7012149",
          "tgn:2001843",
          "tgn:7007825",
          "tgn:7029392"
        ],
        "placetype": [
          "aat:300008798"
        ],
        "id": 2214957,
        "name:xx": "Calico Mountain"
      }
    },
    {
      "geometry": {
        "type": "Point",
        "coordinates": [
          -116.8333,
          34.9667
        ]
      },
      "type": "Feature",
      "properties": {
        "hierarchy": [
          "tgn:2214958",
          "tgn:1000001",
          "tgn:7012149",
          "tgn:7007157",
          "tgn:1002857",
          "tgn:7029392"
        ],
        "placetype": [
          "aat:300386831"
        ],
        "id": 2214958,
        "name:xx": "Calico Mountains"
      }
    },
    {
      "geometry": {
        "type": "Point",
        "coordinates": [
          -117.3167,
          41.8
        ]
      },
      "type": "Feature",
      "properties": {
        "hierarchy": [
          "tgn:2214959",
          "tgn:1000001",
          "tgn:2001414",
          "tgn:7012149",
          "tgn:7007526",
          "tgn:7029392"
        ],
        "placetype": [
          "aat:300386831"
        ],
        "id": 2214959,
        "name:xx": "Calico Mountains"
      }
    }
  ]
}
