{
  "geometry": {
    "type": "Point",
    "coordinates": [
      -122.8667,
      39.1833
    ]
  },
  "type": "Feature",
  "properties": {
    "hierarchy": [
      "tgn:2639663",
      "tgn:1000001",
      "tgn:7012149",
      "tgn:7007157",
      "tgn:1002566",
      "tgn:7029392"
    ],
    "placetype": [
      "aat:300266640"
    ],
    "id": 2639663,
    "name:xx": "Sam Alley Ridge"
  }
}
