{
  "type": "FeatureCollection",
  "features": [
    {
      "geometry": {
        "type": "Point",
        "coordinates": [
          -158.7167,
          59.3833
        ]
      },
      "type": "Feature",
      "properties": {
        "hierarchy": [
          "tgn:2375680",
          "tgn:7006450",
          "tgn:1000001",
          "tgn:2000071",
          "tgn:7012149",
          "tgn:7029392"
        ],
        "placetype": [
          "aat:300008706"
        ],
        "id": 2375680,
        "name:xx": "Happy Creek"
      }
    },
    {
      "geometry": {
        "type": "Point",
        "coordinates": [
          -151.6667,
          59.9667
        ]
      },
      "type": "Feature",
      "properties": {
        "hierarchy": [
          "tgn:2375681",
          "tgn:7006450",
          "tgn:1000001",
          "tgn:7019698",
          "tgn:7012149",
          "tgn:7029392"
        ],
        "placetype": [
          "aat:300008706"
        ],
        "id": 2375681,
        "name:xx": "Happy Creek"
      }
    },
    {
      "geometry": {
        "type": "Point",
        "coordinates": [
          -161.8667,
          61.8833
        ]
      },
      "type": "Feature",
      "properties": {
        "hierarchy": [
          "tgn:2375682",
          "tgn:7006450",
          "tgn:1000001",
          "tgn:7012149",
          "tgn:2000087",
          "tgn:7029392"
        ],
        "placetype": [
          "aat:300008706"
        ],
        "id": 2375682,
        "name:xx": "Happy Creek"
      }
    },
    {
      "geometry": {
        "type": "Point",
        "coordinates": [
          -147.9833,
          64.8667
        ]
      },
      "type": "Feature",
      "properties": {
        "hierarchy": [
          "tgn:2375683",
          "tgn:7006450",
          "tgn:1000001",
          "tgn:7019674",
          "tgn:7012149",
          "tgn:7029392"
        ],
        "placetype": [
          "aat:300008706"
        ],
        "id": 2375683,
        "name:xx": "Happy Creek"
      }
    },
    {
      "geometry": {
        "type": "Point",
        "coordinates": [
          -157.9833,
          62.3833
        ]
      },
      "type": "Feature",
      "properties": {
        "hierarchy": [
          "tgn:2375684",
          "tgn:7006450",
          "tgn:1000001",
          "tgn:7012149",
          "tgn:2000089",
          "tgn:7029392"
        ],
        "placetype": [
          "aat:300008706"
        ],
        "id": 2375684,
        "name:xx": "Happy Creek"
      }
    },
    {
      "geometry": {
        "type": "Point",
        "coordinates": [
          -80.65,
          28.6167
        ]
      },
      "type": "Feature",
      "properties": {
        "hierarchy": [
          "tgn:2375685",
          "tgn:1000001",
          "tgn:1002200",
          "tgn:7012149",
          "tgn:7007240",
          "tgn:7029392"
        ],
        "placetype": [
          "aat:300008706"
        ],
        "id": 2375685,
        "name:xx": "Happy Creek"
      }
    },
    {
      "geometry": {
        "type": "Point",
        "coordinates": [
          -116.6833,
          47.2333
        ]
      },
      "type": "Feature",
      "properties": {
        "hierarchy": [
          "tgn:2375686",
          "tgn:2000456",
          "tgn:1000001",
          "tgn:7012149",
          "tgn:7007250",
          "tgn:7029392"
        ],
        "placetype": [
          "aat:300008706"
        ],
        "id": 2375686,
        "name:xx": "Happy Creek"
      }
    },
    {
      "geometry": {
        "type": "Point",
        "coordinates": [
          -99.95,
          39.2167
        ]
      },
      "type": "Feature",
      "properties": {
        "hierarchy": [
          "tgn:2375687",
          "tgn:1000001",
          "tgn:7012149",
          "tgn:7007254",
          "tgn:7029392"
        ],
        "placetype": [
          "aat:300008706"
        ],
        "id": 2375687,
        "name:xx": "Happy Creek"
      }
    },
    {
      "geometry": {
        "type": "Point",
        "coordinates": [
          -113.05,
          45.55
        ]
      },
      "type": "Feature",
      "properties": {
        "hierarchy": [
          "tgn:2375688",
          "tgn:1000001",
          "tgn:2001260",
          "tgn:7012149",
          "tgn:7007524",
          "tgn:7029392"
        ],
        "placetype": [
          "aat:300008706"
        ],
        "id": 2375688,
        "name:xx": "Happy Creek"
      }
    },
    {
      "geometry": {
        "type": "Point",
        "coordinates": [
          -112.8167,
          48.0667
        ]
      },
      "type": "Feature",
      "properties": {
        "hierarchy": [
          "tgn:2375689",
          "tgn:1000001",
          "tgn:7012149",
          "tgn:2001309",
          "tgn:7007524",
          "tgn:7029392"
        ],
        "placetype": [
          "aat:300008706"
        ],
        "id": 2375689,
        "name:xx": "Happy Creek"
      }
    }
  ]
}
