{
  "geometry": {
    "type": "Point",
    "coordinates": [
      -78.2167,
      40.1667
    ]
  },
  "type": "Feature",
  "properties": {
    "hierarchy": [
      "tgn:2627683",
      "tgn:1002172",
      "tgn:1000001",
      "tgn:7012149",
      "tgn:7007710",
      "tgn:7029392"
    ],
    "placetype": [
      "aat:300008798"
    ],
    "id": 2627683,
    "name:xx": "Rogers Knob"
  }
}
