{
  "geometry": {
    "type": "Point",
    "coordinates": [
      -110.8833,
      32.95
    ]
  },
  "type": "Feature",
  "properties": {
    "hierarchy": [
      "tgn:2410491",
      "tgn:1000001",
      "tgn:7006451",
      "tgn:7012149",
      "tgn:2000101",
      "tgn:7029392"
    ],
    "placetype": [
      "aat:300008699"
    ],
    "id": 2410491,
    "name:xx": "Indian Camp Wash"
  }
}
