{
  "type": "FeatureCollection",
  "features": [
    {
      "geometry": {
        "type": "Point",
        "coordinates": [
          10.716667,
          51.8
        ]
      },
      "type": "Feature",
      "properties": {
        "hierarchy": [
          "tgn:7173020",
          "tgn:1000003",
          "tgn:7003687",
          "tgn:7000084",
          "tgn:7029392"
        ],
        "placetype": [
          "aat:300008777"
        ],
        "id": 7173020,
        "name:xx": "Großer Thumkuhlenkopf"
      }
    },
    {
      "geometry": {
        "type": "Point",
        "coordinates": [
          12.416667,
          54.05
        ]
      },
      "type": "Feature",
      "properties": {
        "hierarchy": [
          "tgn:7173021",
          "tgn:1000003",
          "tgn:7000094",
          "tgn:7000084",
          "tgn:7029392"
        ],
        "placetype": [
          "aat:300008680"
        ],
        "id": 7173021,
        "name:xx": "Großer Teufelssee"
      }
    },
    {
      "geometry": {
        "type": "Point",
        "coordinates": [
          11.8,
          53.9
        ]
      },
      "type": "Feature",
      "properties": {
        "hierarchy": [
          "tgn:7173022",
          "tgn:1000003",
          "tgn:7000094",
          "tgn:7000084",
          "tgn:7029392"
        ],
        "placetype": [
          "aat:300008680"
        ],
        "id": 7173022,
        "name:xx": "Großer Tessiner See"
      }
    },
    {
      "geometry": {
        "type": "Point",
        "coordinates": [
          10.316667,
          53.1
        ]
      },
      "type": "Feature",
      "properties": {
        "hierarchy": [
          "tgn:7173023",
          "tgn:1000003",
          "tgn:7003676",
          "tgn:7000084",
          "tgn:7029392"
        ],
        "placetype": [
          "aat:300008863"
        ],
        "id": 7173023,
        "name:xx": "Großer Tellmer Busch"
      }
    },
    {
      "geometry": {
        "type": "Point",
        "coordinates": [
          10.366667,
          51.683333
        ]
      },
      "type": "Feature",
      "properties": {
        "hierarchy": [
          "tgn:7173024",
          "tgn:1000003",
          "tgn:7003676",
          "tgn:7000084",
          "tgn:7029392"
        ],
        "placetype": [
          "aat:300008777"
        ],
        "id": 7173024,
        "name:xx": "Großer Teichtalskopf"
      }
    },
    {
      "geometry": {
        "type": "Point",
        "coordinates": [
          12.166667,
          49.966667
        ]
      },
      "type": "Feature",
      "properties": {
        "hierarchy": [
          "tgn:7173025",
          "tgn:7003669",
          "tgn:1000003",
          "tgn:7000084",
          "tgn:7029392"
        ],
        "placetype": [
          "aat:300008777"
        ],
        "id": 7173025,
        "name:xx": "Großer Teichel Berg"
      }
    },
    {
      "geometry": {
        "type": "Point",
        "coordinates": [
          13.8,
          51.783333
        ]
      },
      "type": "Feature",
      "properties": {
        "hierarchy": [
          "tgn:7173026",
          "tgn:7000096",
          "tgn:1000003",
          "tgn:7000084",
          "tgn:7029392"
        ],
        "placetype": [
          "aat:300008688"
        ],
        "id": 7173026,
        "name:xx": "Großer Teich"
      }
    },
    {
      "geometry": {
        "type": "Point",
        "coordinates": [
          14.633333,
          51.683333
        ]
      },
      "type": "Feature",
      "properties": {
        "hierarchy": [
          "tgn:7173029",
          "tgn:7000096",
          "tgn:1000003",
          "tgn:7000084",
          "tgn:7029392"
        ],
        "placetype": [
          "aat:300008688"
        ],
        "id": 7173029,
        "name:xx": "Großer Teich"
      }
    }
  ]
}
