{
  "geometry": {
    "type": "Point",
    "coordinates": [
      -83.773,
      11.508
    ]
  },
  "type": "Feature",
  "properties": {
    "hierarchy": [
      "tgn:1128873",
      "tgn:1000001",
      "tgn:7005562",
      "tgn:7029392"
    ],
    "placetype": [
      "aat:300008707"
    ],
    "id": 1128873,
    "name:xx": "Punta Gorda, Río"
  }
}
