{
  "geometry": {
    "type": "Point",
    "coordinates": [
      -81.8667,
      38.2833
    ]
  },
  "type": "Feature",
  "properties": {
    "hierarchy": [
      "tgn:2627044",
      "tgn:1000001",
      "tgn:7012149",
      "tgn:2002272",
      "tgn:7013961",
      "tgn:7029392"
    ],
    "placetype": [
      "aat:300008699"
    ],
    "id": 2627044,
    "name:xx": "Rocky Run"
  }
}
