{
  "type": "FeatureCollection",
  "features": [
    {
      "geometry": {
        "type": "Point",
        "coordinates": [
          -75.5667,
          39.9
        ]
      },
      "type": "Feature",
      "properties": {
        "hierarchy": [
          "tgn:1134312",
          "tgn:1000001",
          "tgn:1002266",
          "tgn:7012149",
          "tgn:7007710",
          "tgn:7029392"
        ],
        "placetype": [
          "aat:300008706"
        ],
        "id": 1134312,
        "name:xx": "Radley Run"
      }
    },
    {
      "geometry": {
        "type": "Point",
        "coordinates": [
          -124.15,
          47.3
        ]
      },
      "type": "Feature",
      "properties": {
        "hierarchy": [
          "tgn:1134313",
          "tgn:1000001",
          "tgn:7012149",
          "tgn:1002418",
          "tgn:7007920",
          "tgn:7029392"
        ],
        "placetype": [
          "aat:300008706"
        ],
        "id": 1134313,
        "name:xx": "Railroad Creek"
      }
    },
    {
      "geometry": {
        "type": "Point",
        "coordinates": [
          -89.1667,
          39.35
        ]
      },
      "type": "Feature",
      "properties": {
        "hierarchy": [
          "tgn:1134314",
          "tgn:1000001",
          "tgn:7012149",
          "tgn:7007251",
          "tgn:7029392"
        ],
        "placetype": [
          "aat:300008706"
        ],
        "id": 1134314,
        "name:xx": "Ramsey Creek"
      }
    },
    {
      "geometry": {
        "type": "Point",
        "coordinates": [
          -74.85,
          39.9833
        ]
      },
      "type": "Feature",
      "properties": {
        "hierarchy": [
          "tgn:1134315",
          "tgn:1002215",
          "tgn:1000001",
          "tgn:7012149",
          "tgn:7007565",
          "tgn:7029392"
        ],
        "placetype": [
          "aat:300008706"
        ],
        "id": 1134315,
        "name:xx": "Rancocas Creek"
      }
    },
    {
      "geometry": {
        "type": "Point",
        "coordinates": [
          -110.05,
          39.3
        ]
      },
      "type": "Feature",
      "properties": {
        "hierarchy": [
          "tgn:1134319",
          "tgn:1000001",
          "tgn:7012149",
          "tgn:7007827",
          "tgn:7029392"
        ],
        "placetype": [
          "aat:300008706"
        ],
        "id": 1134319,
        "name:xx": "Range Creek"
      }
    }
  ]
}
