{
  "geometry": {
    "type": "Point",
    "coordinates": [
      -78.2667,
      41.3667
    ]
  },
  "type": "Feature",
  "properties": {
    "hierarchy": [
      "tgn:2388643",
      "tgn:1000001",
      "tgn:7012149",
      "tgn:1002352",
      "tgn:7007710",
      "tgn:7029392"
    ],
    "placetype": [
      "aat:300055621"
    ],
    "id": 2388643,
    "name:xx": "Hicks Run Camping Area"
  }
}
