{
  "geometry": {
    "type": "Point",
    "coordinates": [
      -79.6833,
      38.85
    ]
  },
  "type": "Feature",
  "properties": {
    "hierarchy": [
      "tgn:2684328",
      "tgn:1000001",
      "tgn:7012149",
      "tgn:2002291",
      "tgn:7013961",
      "tgn:7029392"
    ],
    "placetype": [
      "aat:300008699"
    ],
    "id": 2684328,
    "name:xx": "Spicelick Run"
  }
}
