{
  "geometry": {
    "type": "Point",
    "coordinates": [
      4.25,
      49.4167
    ]
  },
  "type": "Feature",
  "properties": {
    "hierarchy": [
      "tgn:1032114",
      "tgn:1000003",
      "tgn:7002880",
      "tgn:1000070",
      "tgn:7029392"
    ],
    "placetype": [
      "aat:300008347"
    ],
    "id": 1032114,
    "name:xx": "Bergnicourt"
  }
}
