{
  "geometry": {
    "type": "Point",
    "coordinates": [
      -79.6333,
      36.0333
    ]
  },
  "type": "Feature",
  "properties": {
    "hierarchy": [
      "tgn:2365619",
      "tgn:1000001",
      "tgn:7012149",
      "tgn:2001500",
      "tgn:7007709",
      "tgn:7029392"
    ],
    "placetype": [
      "aat:300008347"
    ],
    "id": 2365619,
    "name:xx": "Greesons Crossroads"
  }
}
