{
  "geometry": {
    "type": "Point",
    "coordinates": [
      -120.85,
      42.1833
    ]
  },
  "type": "Feature",
  "properties": {
    "hierarchy": [
      "tgn:2137064",
      "tgn:1000001",
      "tgn:7012149",
      "tgn:2001715",
      "tgn:7007708",
      "tgn:7029392"
    ],
    "placetype": [
      "aat:300006191"
    ],
    "id": 2137064,
    "name:xx": "Arkansas Reservoir"
  }
}
