{
  "geometry": {
    "type": "Point",
    "coordinates": [
      31.387827,
      30.075045
    ]
  },
  "type": "Feature",
  "properties": {
    "hierarchy": [
      "tgn:7537125",
      "tgn:7001242",
      "tgn:7016833",
      "tgn:1001091",
      "tgn:7029392"
    ],
    "placetype": [
      "aat:300379998"
    ],
    "name:en": "Ḩalazūnī, Wādī al",
    "id": 7537125
  }
}
