{
  "type": "FeatureCollection",
  "features": [
    {
      "geometry": {
        "type": "Point",
        "coordinates": [
          -114.0333,
          41.7333
        ]
      },
      "type": "Feature",
      "properties": {
        "hierarchy": [
          "tgn:2767140",
          "tgn:1000001",
          "tgn:7012149",
          "tgn:7029392"
        ],
        "placetype": [
          "aat:300008706"
        ],
        "id": 2767140,
        "name:xx": "White Rock Creek"
      }
    },
    {
      "geometry": {
        "type": "Point",
        "coordinates": [
          -123.4,
          42.1667
        ]
      },
      "type": "Feature",
      "properties": {
        "hierarchy": [
          "tgn:2767141",
          "tgn:1000001",
          "tgn:7012149",
          "tgn:2001713",
          "tgn:7007708",
          "tgn:7029392"
        ],
        "placetype": [
          "aat:300008706"
        ],
        "id": 2767141,
        "name:xx": "White Rock Creek"
      }
    },
    {
      "geometry": {
        "type": "Point",
        "coordinates": [
          -123.0333,
          43.1333
        ]
      },
      "type": "Feature",
      "properties": {
        "hierarchy": [
          "tgn:2767142",
          "tgn:1000001",
          "tgn:7012149",
          "tgn:2001706",
          "tgn:7007708",
          "tgn:7029392"
        ],
        "placetype": [
          "aat:300008706"
        ],
        "id": 2767142,
        "name:xx": "White Rock Creek"
      }
    },
    {
      "geometry": {
        "type": "Point",
        "coordinates": [
          -124.25,
          42.95
        ]
      },
      "type": "Feature",
      "properties": {
        "hierarchy": [
          "tgn:2767143",
          "tgn:1000001",
          "tgn:2001704",
          "tgn:7012149",
          "tgn:7007708",
          "tgn:7029392"
        ],
        "placetype": [
          "aat:300008706"
        ],
        "id": 2767143,
        "name:xx": "White Rock Creek"
      }
    },
    {
      "geometry": {
        "type": "Point",
        "coordinates": [
          -117.6,
          42.95
        ]
      },
      "type": "Feature",
      "properties": {
        "hierarchy": [
          "tgn:2767144",
          "tgn:1000001",
          "tgn:7012149",
          "tgn:2001718",
          "tgn:7007708",
          "tgn:7029392"
        ],
        "placetype": [
          "aat:300008706"
        ],
        "id": 2767144,
        "name:xx": "White Rock Creek"
      }
    },
    {
      "geometry": {
        "type": "Point",
        "coordinates": [
          -122.4667,
          44.5833
        ]
      },
      "type": "Feature",
      "properties": {
        "hierarchy": [
          "tgn:2767145",
          "tgn:1000001",
          "tgn:7012149",
          "tgn:2001717",
          "tgn:7007708",
          "tgn:7029392"
        ],
        "placetype": [
          "aat:300008706"
        ],
        "id": 2767145,
        "name:xx": "White Rock Creek"
      }
    },
    {
      "geometry": {
        "type": "Point",
        "coordinates": [
          -83.0667,
          34.9667
        ]
      },
      "type": "Feature",
      "properties": {
        "hierarchy": [
          "tgn:2767146",
          "tgn:1000001",
          "tgn:7012149",
          "tgn:2001761",
          "tgn:7007712",
          "tgn:7029392"
        ],
        "placetype": [
          "aat:300008706"
        ],
        "id": 2767146,
        "name:xx": "White Rock Creek"
      }
    },
    {
      "geometry": {
        "type": "Point",
        "coordinates": [
          -96.6167,
          33.1
        ]
      },
      "type": "Feature",
      "properties": {
        "hierarchy": [
          "tgn:2767147",
          "tgn:1000001",
          "tgn:7012149",
          "tgn:1002290",
          "tgn:7007826",
          "tgn:7029392"
        ],
        "placetype": [
          "aat:300008706"
        ],
        "id": 2767147,
        "name:xx": "White Rock Creek"
      }
    },
    {
      "geometry": {
        "type": "Point",
        "coordinates": [
          -94.9333,
          33.6333
        ]
      },
      "type": "Feature",
      "properties": {
        "hierarchy": [
          "tgn:2767148",
          "tgn:1000001",
          "tgn:7012149",
          "tgn:2002061",
          "tgn:7007826",
          "tgn:7029392"
        ],
        "placetype": [
          "aat:300008706"
        ],
        "id": 2767148,
        "name:xx": "White Rock Creek"
      }
    },
    {
      "geometry": {
        "type": "Point",
        "coordinates": [
          -96.3,
          31.7333
        ]
      },
      "type": "Feature",
      "properties": {
        "hierarchy": [
          "tgn:2767149",
          "tgn:1000001",
          "tgn:7012149",
          "tgn:1002391",
          "tgn:7007826",
          "tgn:7029392"
        ],
        "placetype": [
          "aat:300008706"
        ],
        "id": 2767149,
        "name:xx": "White Rock Creek"
      }
    }
  ]
}
