{
  "geometry": {
    "type": "Point",
    "coordinates": [
      -71.2167,
      43.5333
    ]
  },
  "type": "Feature",
  "properties": {
    "hierarchy": [
      "tgn:2242135",
      "tgn:2001422",
      "tgn:1000001",
      "tgn:7012149",
      "tgn:7007564",
      "tgn:7029392"
    ],
    "placetype": [
      "aat:300008850"
    ],
    "id": 2242135,
    "name:xx": "Clay Point"
  }
}
