{
  "type": "FeatureCollection",
  "features": [
    {
      "geometry": {
        "type": "Point",
        "coordinates": [
          11.333333,
          45.866667
        ]
      },
      "type": "Feature",
      "properties": {
        "hierarchy": [
          "tgn:5003091",
          "tgn:7003170",
          "tgn:1000003",
          "tgn:7003125",
          "tgn:1000080",
          "tgn:7029392"
        ],
        "placetype": [
          "aat:300008347"
        ],
        "id": 5003091,
        "name:xx": "Grotti"
      }
    },
    {
      "geometry": {
        "type": "Point",
        "coordinates": [
          12.65,
          42.7
        ]
      },
      "type": "Feature",
      "properties": {
        "hierarchy": [
          "tgn:5003094",
          "tgn:7003170",
          "tgn:1000003",
          "tgn:7003125",
          "tgn:1000080",
          "tgn:7029392"
        ],
        "placetype": [
          "aat:300008347"
        ],
        "id": 5003094,
        "name:xx": "Icciano"
      }
    },
    {
      "geometry": {
        "type": "Point",
        "coordinates": [
          12.15,
          43.116667
        ]
      },
      "type": "Feature",
      "properties": {
        "hierarchy": [
          "tgn:5003095",
          "tgn:7003170",
          "tgn:1000003",
          "tgn:7003125",
          "tgn:1000080",
          "tgn:7005067",
          "tgn:7029392"
        ],
        "placetype": [
          "aat:300008791"
        ],
        "id": 5003095,
        "name:xx": "Isola Polvese"
      }
    }
  ]
}
