{
  "geometry": {
    "type": "Point",
    "coordinates": [
      74.844444,
      32.680556
    ]
  },
  "type": "Feature",
  "properties": {
    "hierarchy": [
      "tgn:7591789",
      "tgn:1000004",
      "tgn:7000198",
      "tgn:7000799",
      "tgn:7029392"
    ],
    "placetype": [
      "aat:300008347"
    ],
    "name:en": "Rāmbāgh",
    "id": 7591789
  }
}
