{
  "geometry": {
    "type": "Point",
    "coordinates": [
      -110.6167,
      34.55
    ]
  },
  "type": "Feature",
  "properties": {
    "hierarchy": [
      "tgn:2689746",
      "tgn:1000001",
      "tgn:7006451",
      "tgn:7012149",
      "tgn:2000099",
      "tgn:7029392"
    ],
    "placetype": [
      "aat:300008699"
    ],
    "id": 2689746,
    "name:xx": "Squaw Wash"
  }
}
