{
  "geometry": {
    "type": "Point",
    "coordinates": [
      -79.3833,
      34.95
    ]
  },
  "type": "Feature",
  "properties": {
    "hierarchy": [
      "tgn:2553780",
      "tgn:1000001",
      "tgn:7012149",
      "tgn:2001539",
      "tgn:7007709",
      "tgn:7029392"
    ],
    "placetype": [
      "aat:300008347"
    ],
    "id": 2553780,
    "name:xx": "Oak Hill"
  }
}
