{
  "geometry": {
    "type": "Point",
    "coordinates": [
      100.65,
      13.8667
    ]
  },
  "type": "Feature",
  "properties": {
    "hierarchy": [
      "tgn:1085446",
      "tgn:1001365",
      "tgn:7005191",
      "tgn:1000004",
      "tgn:1000142",
      "tgn:7029392"
    ],
    "placetype": [
      "aat:300008347"
    ],
    "id": 1085446,
    "name:xx": "Ban Khok Bao Sao"
  }
}
