{
  "geometry": {
    "type": "Point",
    "coordinates": [
      -117.5667,
      48.4167
    ]
  },
  "type": "Feature",
  "properties": {
    "hierarchy": [
      "tgn:2152613",
      "tgn:1000001",
      "tgn:7012149",
      "tgn:2002250",
      "tgn:7007920",
      "tgn:7029392"
    ],
    "placetype": [
      "aat:300008706"
    ],
    "id": 2152613,
    "name:xx": "Bayley Creek"
  }
}
