{
  "geometry": {
    "type": "Point",
    "coordinates": [
      -73.6167,
      41.1667
    ]
  },
  "type": "Feature",
  "properties": {
    "hierarchy": [
      "tgn:1135342",
      "tgn:1000001",
      "tgn:7012149",
      "tgn:7029392"
    ],
    "placetype": [
      "aat:300008703"
    ],
    "id": 1135342,
    "name:xx": "Piping Brook"
  }
}
