{
  "geometry": {
    "type": "Point",
    "coordinates": [
      -85.7833,
      38.0667
    ]
  },
  "type": "Feature",
  "properties": {
    "hierarchy": [
      "tgn:2702068",
      "tgn:1000001",
      "tgn:7012149",
      "tgn:7007255",
      "tgn:7029392"
    ],
    "placetype": [
      "aat:300008699"
    ],
    "id": 2702068,
    "name:xx": "Sugartree Run"
  }
}
