{
  "geometry": {
    "type": "Point",
    "coordinates": [
      104.5167,
      31.3333
    ]
  },
  "type": "Feature",
  "properties": {
    "hierarchy": [
      "tgn:1070205",
      "tgn:1000004",
      "tgn:7002087",
      "tgn:1000111",
      "tgn:7029392"
    ],
    "placetype": [
      "aat:300008347"
    ],
    "id": 1070205,
    "name:xx": "Luojiang"
  }
}
