{
  "geometry": {
    "type": "Point",
    "coordinates": [
      -85.5333,
      32.9667
    ]
  },
  "type": "Feature",
  "properties": {
    "hierarchy": [
      "tgn:2727823",
      "tgn:7002659",
      "tgn:1000001",
      "tgn:2000008",
      "tgn:7012149",
      "tgn:7029392"
    ],
    "placetype": [
      "aat:300008347"
    ],
    "id": 2727823,
    "name:xx": "Trammel Crossroads"
  }
}
