{
  "geometry": {
    "type": "Point",
    "coordinates": [
      -73.7333,
      41.6167
    ]
  },
  "type": "Feature",
  "properties": {
    "hierarchy": [
      "tgn:2769214",
      "tgn:1000001",
      "tgn:1002347",
      "tgn:7012149",
      "tgn:7007568",
      "tgn:7029392"
    ],
    "placetype": [
      "aat:300008706"
    ],
    "id": 2769214,
    "name:xx": "Whortlekill Creek"
  }
}
