{
  "geometry": {
    "type": "Point",
    "coordinates": [
      -87.2833,
      39.7167
    ]
  },
  "type": "Feature",
  "properties": {
    "hierarchy": [
      "tgn:2191481",
      "tgn:1000001",
      "tgn:7012149",
      "tgn:2000549",
      "tgn:7007252",
      "tgn:7029392"
    ],
    "placetype": [
      "aat:300008347"
    ],
    "id": 2191481,
    "name:xx": "Bradfield Corner"
  }
}
