{
  "geometry": {
    "type": "Point",
    "coordinates": [
      -106.5667,
      39.4833
    ]
  },
  "type": "Feature",
  "properties": {
    "hierarchy": [
      "tgn:2169973",
      "tgn:1000001",
      "tgn:7012149",
      "tgn:2000210",
      "tgn:7007158",
      "tgn:7029392"
    ],
    "placetype": [
      "aat:300008680"
    ],
    "id": 2169973,
    "name:xx": "Big Pine Lake"
  }
}
