{
  "geometry": {
    "type": "Point",
    "coordinates": [
      37.3833,
      55.6333
    ]
  },
  "type": "Feature",
  "properties": {
    "hierarchy": [
      "tgn:1138127",
      "tgn:1000004",
      "tgn:7011573",
      "tgn:7018214",
      "tgn:7002435",
      "tgn:7029392"
    ],
    "placetype": [
      "aat:300008347"
    ],
    "id": 1138127,
    "name:xx": "Orlovo"
  }
}
