{
  "geometry": {
    "type": "Point",
    "coordinates": [
      -110.5833,
      38.2333
    ]
  },
  "type": "Feature",
  "properties": {
    "hierarchy": [
      "tgn:2158327",
      "tgn:1000001",
      "tgn:7012149",
      "tgn:2002128",
      "tgn:7007827",
      "tgn:7029392"
    ],
    "placetype": [
      "aat:300008699"
    ],
    "id": 2158327,
    "name:xx": "Beaver Wash"
  }
}
