{
  "geometry": {
    "type": "Point",
    "coordinates": [
      -80.6167,
      39.45
    ]
  },
  "type": "Feature",
  "properties": {
    "hierarchy": [
      "tgn:2204771",
      "tgn:1000001",
      "tgn:7012149",
      "tgn:2002301",
      "tgn:7013961",
      "tgn:7029392"
    ],
    "placetype": [
      "aat:300008699"
    ],
    "id": 2204771,
    "name:xx": "Buffalo Run"
  }
}
