{
  "geometry": {
    "type": "Point",
    "coordinates": [
      -117.5167,
      48.1833
    ]
  },
  "type": "Feature",
  "properties": {
    "hierarchy": [
      "tgn:2538200",
      "tgn:1000001",
      "tgn:7012149",
      "tgn:2002250",
      "tgn:7007920",
      "tgn:7029392"
    ],
    "placetype": [
      "aat:300008798"
    ],
    "id": 2538200,
    "name:xx": "Nelson Peak"
  }
}
