{
  "geometry": {
    "type": "Point",
    "coordinates": [
      -71.25,
      42.7333
    ]
  },
  "type": "Feature",
  "properties": {
    "hierarchy": [
      "tgn:2593067",
      "tgn:1000001",
      "tgn:7012149",
      "tgn:7029392"
    ],
    "placetype": [
      "aat:300008798"
    ],
    "id": 2593067,
    "name:xx": "Poplar Hill"
  }
}
