{
  "geometry": {
    "type": "Point",
    "coordinates": [
      -78.6833,
      39.8667
    ]
  },
  "type": "Feature",
  "properties": {
    "hierarchy": [
      "tgn:2361274",
      "tgn:1002172",
      "tgn:1000001",
      "tgn:7012149",
      "tgn:7007710",
      "tgn:7029392"
    ],
    "placetype": [
      "aat:300008347"
    ],
    "id": 2361274,
    "name:xx": "Gravel Pit"
  }
}
