{
  "geometry": {
    "type": "Point",
    "coordinates": [
      -78.6833,
      40.9833
    ]
  },
  "type": "Feature",
  "properties": {
    "hierarchy": [
      "tgn:2413806",
      "tgn:1000001",
      "tgn:1002278",
      "tgn:7012149",
      "tgn:7007710",
      "tgn:7029392"
    ],
    "placetype": [
      "aat:300008699"
    ],
    "id": 2413806,
    "name:xx": "Irish Run"
  }
}
