{
  "geometry": {
    "type": "Point",
    "coordinates": [
      -87.5167,
      36.2167
    ]
  },
  "type": "Feature",
  "properties": {
    "hierarchy": [
      "tgn:2202932",
      "tgn:1000001",
      "tgn:7012149",
      "tgn:7007825",
      "tgn:7029392"
    ],
    "placetype": [
      "aat:300008761"
    ],
    "id": 2202932,
    "name:xx": "Buckeye Hollow"
  }
}
