{
  "geometry": {
    "type": "Point",
    "coordinates": [
      -90.0833,
      43.0333
    ]
  },
  "type": "Feature",
  "properties": {
    "hierarchy": [
      "tgn:2373307",
      "tgn:1000001",
      "tgn:7012149",
      "tgn:2002326",
      "tgn:7007922",
      "tgn:7029392"
    ],
    "placetype": [
      "aat:300006191"
    ],
    "id": 2373307,
    "name:xx": "Halverson Lake"
  }
}
