{
  "geometry": {
    "type": "Point",
    "coordinates": [
      -120.1333,
      38.2167
    ]
  },
  "type": "Feature",
  "properties": {
    "hierarchy": [
      "tgn:2674643",
      "tgn:1000001",
      "tgn:7012149",
      "tgn:7007157",
      "tgn:1002957",
      "tgn:7029392"
    ],
    "placetype": [
      "aat:300008706"
    ],
    "id": 2674643,
    "name:xx": "Soap Creek"
  }
}
