{
  "geometry": {
    "type": "Point",
    "coordinates": [
      -82.2833,
      37.3667
    ]
  },
  "type": "Feature",
  "properties": {
    "hierarchy": [
      "tgn:7016270",
      "tgn:1000001",
      "tgn:7012149",
      "tgn:2000837",
      "tgn:7007255",
      "tgn:7029392"
    ],
    "placetype": [
      "aat:300008347",
      "aat:300387016"
    ],
    "id": 7016270,
    "name:xx": "Lick Creek"
  }
}
