{
  "geometry": {
    "type": "Point",
    "coordinates": [
      -120.6333,
      41.8333
    ]
  },
  "type": "Feature",
  "properties": {
    "hierarchy": [
      "tgn:2681127",
      "tgn:1000001",
      "tgn:7012149",
      "tgn:7007157",
      "tgn:2000186",
      "tgn:7029392"
    ],
    "placetype": [
      "aat:300008798"
    ],
    "id": 2681127,
    "name:xx": "South Mountain"
  }
}
