{
  "geometry": {
    "type": "Point",
    "coordinates": [
      44.0333,
      1.0333
    ]
  },
  "type": "Feature",
  "properties": {
    "hierarchy": [
      "tgn:1092616",
      "tgn:7001242",
      "tgn:1001747",
      "tgn:1000192",
      "tgn:7029392"
    ],
    "placetype": [
      "aat:300008347"
    ],
    "id": 1092616,
    "name:xx": "Baraawe"
  }
}
