{
  "geometry": {
    "type": "Point",
    "coordinates": [
      100.6167,
      -0.4333
    ]
  },
  "type": "Feature",
  "properties": {
    "hierarchy": [
      "tgn:1077468",
      "tgn:1000004",
      "tgn:1001553",
      "tgn:1000116",
      "tgn:7029392"
    ],
    "placetype": [
      "aat:300008347"
    ],
    "id": 1077468,
    "name:xx": "Batusangkar"
  }
}
