{
  "geometry": {
    "type": "Point",
    "coordinates": [
      -76.5833,
      37.5167
    ]
  },
  "type": "Feature",
  "properties": {
    "hierarchy": [
      "tgn:2781980",
      "tgn:1000001",
      "tgn:7012149",
      "tgn:1002411",
      "tgn:7007919",
      "tgn:7029392"
    ],
    "placetype": [
      "aat:300008699"
    ],
    "id": 2781980,
    "name:xx": "Woods Mill Swamp"
  }
}
