{
  "geometry": {
    "type": "Point",
    "coordinates": [
      5.4333,
      22.6333
    ]
  },
  "type": "Feature",
  "properties": {
    "hierarchy": [
      "tgn:1087362",
      "tgn:7001242",
      "tgn:7016752",
      "tgn:1000775",
      "tgn:7029392"
    ],
    "placetype": [
      "aat:300008347"
    ],
    "id": 1087362,
    "name:xx": "Amsel"
  }
}
