{
  "geometry": {
    "type": "Point",
    "coordinates": [
      53.6333,
      55.0167
    ]
  },
  "type": "Feature",
  "properties": {
    "hierarchy": [
      "tgn:1057229",
      "tgn:1000004",
      "tgn:7011498",
      "tgn:7002435",
      "tgn:7029392"
    ],
    "placetype": [
      "aat:300008347"
    ],
    "id": 1057229,
    "name:xx": "Mustafino"
  }
}
