{
  "geometry": {
    "type": "Point",
    "coordinates": [
      -119.9167,
      37.4833
    ]
  },
  "type": "Feature",
  "properties": {
    "hierarchy": [
      "tgn:2411794",
      "tgn:1000001",
      "tgn:7012149",
      "tgn:7007157",
      "tgn:7014004",
      "tgn:7029392"
    ],
    "placetype": [
      "aat:300008798"
    ],
    "id": 2411794,
    "name:xx": "Indian Mountain"
  }
}
