{
  "geometry": {
    "type": "Point",
    "coordinates": [
      -73.0333,
      41.8833
    ]
  },
  "type": "Feature",
  "properties": {
    "hierarchy": [
      "tgn:2524092",
      "tgn:1000001",
      "tgn:1002601",
      "tgn:7012149",
      "tgn:7007159",
      "tgn:7029392"
    ],
    "placetype": [
      "aat:300008699"
    ],
    "id": 2524092,
    "name:xx": "Morgan Brook"
  }
}
