{
  "geometry": {
    "type": "Point",
    "coordinates": [
      -108.3333,
      43.7667
    ]
  },
  "type": "Feature",
  "properties": {
    "hierarchy": [
      "tgn:2378315",
      "tgn:1000001",
      "tgn:7012149",
      "tgn:2002373",
      "tgn:7007923",
      "tgn:7029392"
    ],
    "placetype": [
      "aat:300008697"
    ],
    "id": 2378315,
    "name:xx": "Harris Spring"
  }
}
