{
  "geometry": {
    "type": "Point",
    "coordinates": [
      -1.406,
      53.885
    ]
  },
  "type": "Feature",
  "properties": {
    "hierarchy": [
      "tgn:7029927",
      "tgn:7019038",
      "tgn:7002445",
      "tgn:1000003",
      "tgn:7029507",
      "tgn:7008591",
      "tgn:7029392"
    ],
    "placetype": [
      "aat:300008347",
      "aat:300008372"
    ],
    "id": 7029927,
    "name:xx": "Compton",
    "name:ang": "Contone"
  }
}
