{
  "geometry": {
    "type": "Point",
    "coordinates": [
      100.1167,
      14.2333
    ]
  },
  "type": "Feature",
  "properties": {
    "hierarchy": [
      "tgn:1085698",
      "tgn:7005192",
      "tgn:1000004",
      "tgn:7000966",
      "tgn:1000142",
      "tgn:7029392"
    ],
    "placetype": [
      "aat:300008347",
      "aat:300387223"
    ],
    "id": 1085698,
    "name:xx": "Suphan Buri"
  }
}
