{
  "geometry": {
    "type": "Point",
    "coordinates": [
      23.636,
      -29.071
    ]
  },
  "type": "Feature",
  "properties": {
    "hierarchy": [
      "tgn:1131339",
      "tgn:7001242",
      "tgn:7017582",
      "tgn:1000193",
      "tgn:7029392"
    ],
    "placetype": [
      "aat:300008707"
    ],
    "id": 1131339,
    "name:xx": "Vaal"
  }
}
