{
  "geometry": {
    "type": "Point",
    "coordinates": [
      -99.0167,
      28.9167
    ]
  },
  "type": "Feature",
  "properties": {
    "hierarchy": [
      "tgn:2641781",
      "tgn:1000001",
      "tgn:7012149",
      "tgn:2001987",
      "tgn:7007826",
      "tgn:7029392"
    ],
    "placetype": [
      "aat:300008761"
    ],
    "id": 2641781,
    "name:xx": "Sand Hollow"
  }
}
