{
  "type": "FeatureCollection",
  "features": [
    {
      "geometry": {
        "type": "Point",
        "coordinates": [
          -75.8833,
          38.7167
        ]
      },
      "type": "Feature",
      "properties": {
        "hierarchy": [
          "tgn:2047580",
          "tgn:1002234",
          "tgn:1000001",
          "tgn:7012149",
          "tgn:7007516",
          "tgn:7029392"
        ],
        "placetype": [
          "aat:300008347"
        ],
        "id": 2047580,
        "name:xx": "Jonestown"
      }
    },
    {
      "geometry": {
        "type": "Point",
        "coordinates": [
          -76.35,
          39.4333
        ]
      },
      "type": "Feature",
      "properties": {
        "hierarchy": [
          "tgn:2047581",
          "tgn:1000001",
          "tgn:7016102",
          "tgn:7012149",
          "tgn:7007516",
          "tgn:7029392"
        ],
        "placetype": [
          "aat:300008347"
        ],
        "id": 2047581,
        "name:xx": "Joppa"
      }
    },
    {
      "geometry": {
        "type": "Point",
        "coordinates": [
          -76.3,
          39.6
        ]
      },
      "type": "Feature",
      "properties": {
        "hierarchy": [
          "tgn:2047587",
          "tgn:1000001",
          "tgn:7016102",
          "tgn:7012149",
          "tgn:7007516",
          "tgn:7029392"
        ],
        "placetype": [
          "aat:300008347",
          "aat:300387210"
        ],
        "id": 2047587,
        "name:xx": "Kalmia"
      }
    },
    {
      "geometry": {
        "type": "Point",
        "coordinates": [
          -77.7,
          39.4833
        ]
      },
      "type": "Feature",
      "properties": {
        "hierarchy": [
          "tgn:2047589",
          "tgn:1000001",
          "tgn:7016106",
          "tgn:7012149",
          "tgn:7007516",
          "tgn:7029392"
        ],
        "placetype": [
          "aat:300008347"
        ],
        "id": 2047589,
        "name:xx": "Keedysville"
      }
    }
  ]
}
