{
  "geometry": {
    "type": "Point",
    "coordinates": [
      2.6667,
      43.2833
    ]
  },
  "type": "Feature",
  "properties": {
    "hierarchy": [
      "tgn:5001078",
      "tgn:1000003",
      "tgn:7002885",
      "tgn:1000070",
      "tgn:7029392"
    ],
    "placetype": [
      "aat:300008347"
    ],
    "id": 5001078,
    "name:xx": "Azille"
  }
}
