{
  "geometry": {
    "type": "Point",
    "coordinates": [
      59.4667,
      45.85
    ]
  },
  "type": "Feature",
  "properties": {
    "hierarchy": [
      "tgn:1054481",
      "tgn:1000004",
      "tgn:1003384",
      "tgn:7014786",
      "tgn:7029392"
    ],
    "placetype": [
      "aat:300008347"
    ],
    "id": 1054481,
    "name:xx": "Izendy"
  }
}
