{
  "geometry": {
    "type": "Point",
    "coordinates": [
      -70.8833,
      41.6167
    ]
  },
  "type": "Feature",
  "properties": {
    "hierarchy": [
      "tgn:2454983",
      "tgn:1002201",
      "tgn:1000001",
      "tgn:7012149",
      "tgn:7007517",
      "tgn:7029392"
    ],
    "placetype": [
      "aat:300008791"
    ],
    "id": 2454983,
    "name:xx": "Little Egg Island"
  }
}
