{
  "geometry": {
    "type": "Point",
    "coordinates": [
      -111.0167,
      47.75
    ]
  },
  "type": "Feature",
  "properties": {
    "hierarchy": [
      "tgn:2175612",
      "tgn:1000001",
      "tgn:2001267",
      "tgn:7012149",
      "tgn:7007524",
      "tgn:7029392"
    ],
    "placetype": [
      "aat:300008761"
    ],
    "id": 2175612,
    "name:xx": "Black Coulee"
  }
}
