{
  "geometry": {
    "type": "Point",
    "coordinates": [
      -111.4833,
      34.9333
    ]
  },
  "type": "Feature",
  "properties": {
    "hierarchy": [
      "tgn:2293534",
      "tgn:1000001",
      "tgn:7006451",
      "tgn:2000092",
      "tgn:7012149",
      "tgn:7029392"
    ],
    "placetype": [
      "aat:300008697"
    ],
    "id": 2293534,
    "name:xx": "Double Springs"
  }
}
