{
  "geometry": {
    "type": "Point",
    "coordinates": [
      2.1333,
      50.3833
    ]
  },
  "type": "Feature",
  "properties": {
    "hierarchy": [
      "tgn:1033906",
      "tgn:1000003",
      "tgn:7001097",
      "tgn:1000070",
      "tgn:7029392"
    ],
    "placetype": [
      "aat:300008347"
    ],
    "id": 1033906,
    "name:xx": "Parcq, le"
  }
}
