{
  "geometry": {
    "type": "Point",
    "coordinates": [
      -81.5833,
      28.5167
    ]
  },
  "type": "Feature",
  "properties": {
    "hierarchy": [
      "tgn:2721475",
      "tgn:1000001",
      "tgn:7012149",
      "tgn:1002749",
      "tgn:7007240",
      "tgn:7029392"
    ],
    "placetype": [
      "aat:300008680"
    ],
    "id": 2721475,
    "name:xx": "Tilden, Lake"
  }
}
