{
  "type": "FeatureCollection",
  "features": [
    {
      "geometry": {
        "type": "Point",
        "coordinates": [
          -106.0833,
          47.0667
        ]
      },
      "type": "Feature",
      "properties": {
        "hierarchy": [
          "tgn:2157160",
          "tgn:1000001",
          "tgn:7012149",
          "tgn:2001276",
          "tgn:7007524",
          "tgn:7029392"
        ],
        "placetype": [
          "aat:300008761"
        ],
        "id": 2157160,
        "name:xx": "Beaver Coulee"
      }
    },
    {
      "geometry": {
        "type": "Point",
        "coordinates": [
          -114.5667,
          35.2333
        ]
      },
      "type": "Feature",
      "properties": {
        "hierarchy": [
          "tgn:2157161",
          "tgn:1000001",
          "tgn:7006451",
          "tgn:7012149",
          "tgn:2000098",
          "tgn:7029392"
        ],
        "placetype": [
          "aat:300132316"
        ],
        "id": 2157161,
        "name:xx": "Beaver Cove"
      }
    },
    {
      "geometry": {
        "type": "Point",
        "coordinates": [
          -69.55,
          45.5333
        ]
      },
      "type": "Feature",
      "properties": {
        "hierarchy": [
          "tgn:2157162",
          "tgn:1000001",
          "tgn:7012149",
          "tgn:2000928",
          "tgn:7007515",
          "tgn:7029392"
        ],
        "placetype": [
          "aat:300132316"
        ],
        "id": 2157162,
        "name:xx": "Beaver Cove"
      }
    },
    {
      "geometry": {
        "type": "Point",
        "coordinates": [
          -86.3,
          31.0833
        ]
      },
      "type": "Feature",
      "properties": {
        "hierarchy": [
          "tgn:2157163",
          "tgn:7002659",
          "tgn:1000001",
          "tgn:2000019",
          "tgn:7012149",
          "tgn:7029392"
        ],
        "placetype": [
          "aat:300008706"
        ],
        "id": 2157163,
        "name:xx": "Beaver Creek"
      }
    },
    {
      "geometry": {
        "type": "Point",
        "coordinates": [
          -85.4167,
          31.1833
        ]
      },
      "type": "Feature",
      "properties": {
        "hierarchy": [
          "tgn:2157164",
          "tgn:7002659",
          "tgn:1000001",
          "tgn:7012149",
          "tgn:2000034",
          "tgn:7029392"
        ],
        "placetype": [
          "aat:300008706"
        ],
        "id": 2157164,
        "name:xx": "Beaver Creek"
      }
    },
    {
      "geometry": {
        "type": "Point",
        "coordinates": [
          -86.7167,
          31.8333
        ]
      },
      "type": "Feature",
      "properties": {
        "hierarchy": [
          "tgn:2157165",
          "tgn:7002659",
          "tgn:1000001",
          "tgn:2000006",
          "tgn:7012149",
          "tgn:7029392"
        ],
        "placetype": [
          "aat:300008706"
        ],
        "id": 2157165,
        "name:xx": "Beaver Creek"
      }
    },
    {
      "geometry": {
        "type": "Point",
        "coordinates": [
          -86.75,
          32.5
        ]
      },
      "type": "Feature",
      "properties": {
        "hierarchy": [
          "tgn:2157166",
          "tgn:2000000",
          "tgn:7002659",
          "tgn:1000001",
          "tgn:7012149",
          "tgn:7029392"
        ],
        "placetype": [
          "aat:300008706"
        ],
        "id": 2157166,
        "name:xx": "Beaver Creek"
      }
    },
    {
      "geometry": {
        "type": "Point",
        "coordinates": [
          -87.75,
          33.0833
        ]
      },
      "type": "Feature",
      "properties": {
        "hierarchy": [
          "tgn:2157167",
          "tgn:7002659",
          "tgn:1000001",
          "tgn:7012149",
          "tgn:7029392"
        ],
        "placetype": [
          "aat:300008706"
        ],
        "id": 2157167,
        "name:xx": "Beaver Creek"
      }
    },
    {
      "geometry": {
        "type": "Point",
        "coordinates": [
          -87.9667,
          33.4833
        ]
      },
      "type": "Feature",
      "properties": {
        "hierarchy": [
          "tgn:2157168",
          "tgn:7002659",
          "tgn:1000001",
          "tgn:7012149",
          "tgn:2000053",
          "tgn:7029392"
        ],
        "placetype": [
          "aat:300008706"
        ],
        "id": 2157168,
        "name:xx": "Beaver Creek"
      }
    },
    {
      "geometry": {
        "type": "Point",
        "coordinates": [
          -87.3667,
          31.7333
        ]
      },
      "type": "Feature",
      "properties": {
        "hierarchy": [
          "tgn:2157169",
          "tgn:7002659",
          "tgn:1000001",
          "tgn:7012149",
          "tgn:2000049",
          "tgn:7029392"
        ],
        "placetype": [
          "aat:300008706"
        ],
        "id": 2157169,
        "name:xx": "Beaver Creek"
      }
    }
  ]
}
