{
  "geometry": {
    "type": "Point",
    "coordinates": [
      -87.25,
      36.4833
    ]
  },
  "type": "Feature",
  "properties": {
    "hierarchy": [
      "tgn:2781613",
      "tgn:1000001",
      "tgn:7012149",
      "tgn:2001899",
      "tgn:7007825",
      "tgn:7029392"
    ],
    "placetype": [
      "aat:300008347"
    ],
    "id": 2781613,
    "name:xx": "Woodridge Estates"
  }
}
