{
  "geometry": {
    "type": "Point",
    "coordinates": [
      -121.2167,
      39.4833
    ]
  },
  "type": "Feature",
  "properties": {
    "hierarchy": [
      "tgn:2010663",
      "tgn:1000001",
      "tgn:7012149",
      "tgn:7007157",
      "tgn:1003050",
      "tgn:7029392"
    ],
    "placetype": [
      "aat:300008347"
    ],
    "id": 2010663,
    "name:xx": "Challenge"
  }
}
