{
  "geometry": {
    "type": "Point",
    "coordinates": [
      -90.45,
      16.0667
    ]
  },
  "type": "Feature",
  "properties": {
    "hierarchy": [
      "tgn:1122815",
      "tgn:1000001",
      "tgn:7005493",
      "tgn:7029392"
    ],
    "placetype": [
      "aat:300008707"
    ],
    "id": 1122815,
    "name:xx": "Chixoy, Río"
  }
}
