{
  "geometry": {
    "type": "Point",
    "coordinates": [
      -76.8667,
      38.15
    ]
  },
  "type": "Feature",
  "properties": {
    "hierarchy": [
      "tgn:2595916",
      "tgn:1000001",
      "tgn:7012149",
      "tgn:1003018",
      "tgn:7007919",
      "tgn:7029392"
    ],
    "placetype": [
      "aat:300008699"
    ],
    "id": 2595916,
    "name:xx": "Potter Branch"
  }
}
