{
  "geometry": {
    "type": "Point",
    "coordinates": [
      32.88529,
      25.796838
    ]
  },
  "type": "Feature",
  "properties": {
    "hierarchy": [
      "tgn:7523281",
      "tgn:7001242",
      "tgn:7001311",
      "tgn:7016833",
      "tgn:7029392"
    ],
    "placetype": [
      "aat:300008777"
    ],
    "name:en": "Durrī, Jabal ad",
    "id": 7523281
  }
}
