{
  "geometry": {
    "type": "Point",
    "coordinates": [
      30.851803,
      30.969428
    ]
  },
  "type": "Feature",
  "properties": {
    "hierarchy": [
      "tgn:7537936",
      "tgn:7001242",
      "tgn:7016833",
      "tgn:7001312",
      "tgn:7029392"
    ],
    "placetype": [
      "aat:300008347"
    ],
    "name:en": "Mīt Sharīf",
    "id": 7537936
  }
}
