{
  "geometry": {
    "type": "Point",
    "coordinates": [
      -87.9333,
      31.35
    ]
  },
  "type": "Feature",
  "properties": {
    "hierarchy": [
      "tgn:2407206",
      "tgn:7002659",
      "tgn:1000001",
      "tgn:7012149",
      "tgn:2000064",
      "tgn:7029392"
    ],
    "placetype": [
      "aat:300008699"
    ],
    "id": 2407206,
    "name:xx": "Hunters Slough"
  }
}
