{
  "geometry": {
    "type": "Point",
    "coordinates": [
      -82.3333,
      35.5667
    ]
  },
  "type": "Feature",
  "properties": {
    "hierarchy": [
      "tgn:2424494",
      "tgn:1000001",
      "tgn:2001473",
      "tgn:7012149",
      "tgn:7007709",
      "tgn:7029392"
    ],
    "placetype": [
      "aat:300008761"
    ],
    "id": 2424494,
    "name:xx": "Johnson Cove"
  }
}
