{
  "geometry": {
    "type": "Point",
    "coordinates": [
      -111.9167,
      34.1833
    ]
  },
  "type": "Feature",
  "properties": {
    "hierarchy": [
      "tgn:2509437",
      "tgn:1000001",
      "tgn:7006451",
      "tgn:7012149",
      "tgn:2000103",
      "tgn:7029392"
    ],
    "placetype": [
      "aat:300008706"
    ],
    "id": 2509437,
    "name:xx": "Middle Fork Squaw Creek"
  }
}
