{
  "geometry": {
    "type": "Point",
    "coordinates": [
      -102.633333,
      21.85
    ]
  },
  "type": "Feature",
  "properties": {
    "hierarchy": [
      "tgn:7421314",
      "tgn:7005579",
      "tgn:1000001",
      "tgn:7005560",
      "tgn:7029392"
    ],
    "placetype": [
      "aat:300008347"
    ],
    "id": 7421314,
    "name:xx": "San José del Río"
  }
}
