{
  "geometry": {
    "type": "Point",
    "coordinates": [
      -73.35,
      44.95
    ]
  },
  "type": "Feature",
  "properties": {
    "hierarchy": [
      "tgn:2226219",
      "tgn:1000001",
      "tgn:1002284",
      "tgn:7012149",
      "tgn:7007568",
      "tgn:7029392"
    ],
    "placetype": [
      "aat:300132316"
    ],
    "id": 2226219,
    "name:xx": "Catfish Bay"
  }
}
