{
  "geometry": {
    "type": "Point",
    "coordinates": [
      -88.5667,
      42.45
    ]
  },
  "type": "Feature",
  "properties": {
    "hierarchy": [
      "tgn:2519835",
      "tgn:1000001",
      "tgn:7012149",
      "tgn:7019014",
      "tgn:7007251",
      "tgn:7029392"
    ],
    "placetype": [
      "aat:300008706"
    ],
    "id": 2519835,
    "name:xx": "Mokeler Creek"
  }
}
