{
  "geometry": {
    "type": "Point",
    "coordinates": [
      -77.0667,
      38.9833
    ]
  },
  "type": "Feature",
  "properties": {
    "hierarchy": [
      "tgn:2301296",
      "tgn:1000001",
      "tgn:7016104",
      "tgn:7012149",
      "tgn:7007516",
      "tgn:7029392"
    ],
    "placetype": [
      "aat:300008347"
    ],
    "id": 2301296,
    "name:xx": "Dunlops Hills"
  }
}
