{
  "geometry": {
    "type": "Point",
    "coordinates": [
      -95.45,
      31.9833
    ]
  },
  "type": "Feature",
  "properties": {
    "hierarchy": [
      "tgn:2130645",
      "tgn:1002148",
      "tgn:1000001",
      "tgn:7012149",
      "tgn:7007826",
      "tgn:7029392"
    ],
    "placetype": [
      "aat:300008680"
    ],
    "id": 2130645,
    "name:xx": "Alligator Lake"
  }
}
