{
  "geometry": {
    "type": "Point",
    "coordinates": [
      -76.3833,
      42.3333
    ]
  },
  "type": "Feature",
  "properties": {
    "hierarchy": [
      "tgn:2765578",
      "tgn:1000001",
      "tgn:7012149",
      "tgn:1002950",
      "tgn:7007568",
      "tgn:7029392"
    ],
    "placetype": [
      "aat:300008347"
    ],
    "id": 2765578,
    "name:xx": "White Church"
  }
}
