{
  "geometry": {
    "type": "Point",
    "coordinates": [
      17.1167,
      6.4167
    ]
  },
  "type": "Feature",
  "properties": {
    "hierarchy": [
      "tgn:1121574",
      "tgn:7001242",
      "tgn:1000155",
      "tgn:7029392"
    ],
    "placetype": [
      "aat:300008707"
    ],
    "id": 1121574,
    "name:xx": "Baba"
  }
}
