{
  "geometry": {
    "type": "Point",
    "coordinates": [
      122.0167,
      10.7833
    ]
  },
  "type": "Feature",
  "properties": {
    "hierarchy": [
      "tgn:1084646",
      "tgn:1001104",
      "tgn:1000004",
      "tgn:1000135",
      "tgn:7029392"
    ],
    "placetype": [
      "aat:300008347"
    ],
    "id": 1084646,
    "name:xx": "Sibalom"
  }
}
