{
  "geometry": {
    "type": "Point",
    "coordinates": [
      76.543,
      30.16682
    ]
  },
  "type": "Feature",
  "properties": {
    "hierarchy": [
      "tgn:7584247",
      "tgn:1000004",
      "tgn:7000198",
      "tgn:7016883",
      "tgn:7029392"
    ],
    "placetype": [
      "aat:300008347"
    ],
    "name:en": "Hājīpur",
    "id": 7584247
  }
}
