{
  "geometry": {
    "type": "Point",
    "coordinates": [
      -93.965278,
      17.35
    ]
  },
  "type": "Feature",
  "properties": {
    "hierarchy": [
      "tgn:7400223",
      "tgn:1000001",
      "tgn:7005599",
      "tgn:7005560",
      "tgn:7029392"
    ],
    "placetype": [
      "aat:300008347"
    ],
    "id": 7400223,
    "name:xx": "El Desengaño"
  }
}
