{
  "geometry": {
    "type": "Point",
    "coordinates": [
      -79.6667,
      39.8167
    ]
  },
  "type": "Feature",
  "properties": {
    "hierarchy": [
      "tgn:2333852",
      "tgn:1000001",
      "tgn:7012149",
      "tgn:7014185",
      "tgn:7007710",
      "tgn:7029392"
    ],
    "placetype": [
      "aat:300008863"
    ],
    "id": 2333852,
    "name:xx": "Forbes State Forest"
  }
}
