{
  "geometry": {
    "type": "Point",
    "coordinates": [
      74.37771,
      34.497461
    ]
  },
  "type": "Feature",
  "properties": {
    "hierarchy": [
      "tgn:7579206",
      "tgn:1000004",
      "tgn:7000198",
      "tgn:7000799",
      "tgn:7029392"
    ],
    "placetype": [
      "aat:300008347"
    ],
    "name:en": "Sogām",
    "id": 7579206
  }
}
