{
  "geometry": {
    "type": "Point",
    "coordinates": [
      -118.7667,
      44.3333
    ]
  },
  "type": "Feature",
  "properties": {
    "hierarchy": [
      "tgn:2456511",
      "tgn:1000001",
      "tgn:7012149",
      "tgn:2001708",
      "tgn:7007708",
      "tgn:7029392"
    ],
    "placetype": [
      "aat:300008706"
    ],
    "id": 2456511,
    "name:xx": "Little Indian Creek"
  }
}
