{
  "type": "FeatureCollection",
  "features": [
    {
      "geometry": {
        "type": "Point",
        "coordinates": [
          -95.7,
          32.6667
        ]
      },
      "type": "Feature",
      "properties": {
        "hierarchy": [
          "tgn:2104541",
          "tgn:1000001",
          "tgn:7012149",
          "tgn:1002969",
          "tgn:7007826",
          "tgn:7029392"
        ],
        "placetype": [
          "aat:300008347"
        ],
        "id": 2104541,
        "name:xx": "Grand Saline"
      }
    },
    {
      "geometry": {
        "type": "Point",
        "coordinates": [
          -97.1667,
          32.2667
        ]
      },
      "type": "Feature",
      "properties": {
        "hierarchy": [
          "tgn:2104542",
          "tgn:1000001",
          "tgn:7012149",
          "tgn:1002526",
          "tgn:7007826",
          "tgn:7029392"
        ],
        "placetype": [
          "aat:300008347"
        ],
        "id": 2104542,
        "name:xx": "Grandview"
      }
    },
    {
      "geometry": {
        "type": "Point",
        "coordinates": [
          -101.9833,
          32.9
        ]
      },
      "type": "Feature",
      "properties": {
        "hierarchy": [
          "tgn:2104543",
          "tgn:1000001",
          "tgn:7012149",
          "tgn:2001971",
          "tgn:7007826",
          "tgn:7029392"
        ],
        "placetype": [
          "aat:300008347",
          "aat:300387210"
        ],
        "id": 2104543,
        "name:xx": "Grandview"
      }
    },
    {
      "geometry": {
        "type": "Point",
        "coordinates": [
          -97.4333,
          30.7167
        ]
      },
      "type": "Feature",
      "properties": {
        "hierarchy": [
          "tgn:2104546",
          "tgn:1000001",
          "tgn:7012149",
          "tgn:1003026",
          "tgn:7007826",
          "tgn:7029392"
        ],
        "placetype": [
          "aat:300008347"
        ],
        "id": 2104546,
        "name:xx": "Granger"
      }
    },
    {
      "geometry": {
        "type": "Point",
        "coordinates": [
          -95.3167,
          30.25
        ]
      },
      "type": "Feature",
      "properties": {
        "hierarchy": [
          "tgn:2104547",
          "tgn:1000001",
          "tgn:7012149",
          "tgn:1002691",
          "tgn:7007826",
          "tgn:7029392"
        ],
        "placetype": [
          "aat:300008347"
        ],
        "id": 2104547,
        "name:xx": "Grangerland"
      }
    }
  ]
}
