{
  "geometry": {
    "type": "Point",
    "coordinates": [
      -78.8167,
      42.35
    ]
  },
  "type": "Feature",
  "properties": {
    "hierarchy": [
      "tgn:2071523",
      "tgn:1000001",
      "tgn:1002245",
      "tgn:7012149",
      "tgn:7007568",
      "tgn:7029392"
    ],
    "placetype": [
      "aat:300008347"
    ],
    "id": 2071523,
    "name:xx": "Otto"
  }
}
