{
  "geometry": {
    "type": "Point",
    "coordinates": [
      60.4167,
      46.6167
    ]
  },
  "type": "Feature",
  "properties": {
    "hierarchy": [
      "tgn:1059216",
      "tgn:1000004",
      "tgn:1003384",
      "tgn:7014786",
      "tgn:7029392"
    ],
    "placetype": [
      "aat:300008347"
    ],
    "id": 1059216,
    "name:xx": "Sarybasat"
  }
}
