{
  "geometry": {
    "type": "Point",
    "coordinates": [
      -110.5667,
      47.0333
    ]
  },
  "type": "Feature",
  "properties": {
    "hierarchy": [
      "tgn:2534589",
      "tgn:1000001",
      "tgn:7012149",
      "tgn:2001282",
      "tgn:7007524",
      "tgn:7029392"
    ],
    "placetype": [
      "aat:300000390"
    ],
    "id": 2534589,
    "name:xx": "NW SW Section 22 Mine"
  }
}
