{
  "geometry": {
    "type": "Point",
    "coordinates": [
      33.45213,
      26.958008
    ]
  },
  "type": "Feature",
  "properties": {
    "hierarchy": [
      "tgn:7520660",
      "tgn:7001242",
      "tgn:7001311",
      "tgn:7016833",
      "tgn:7029392"
    ],
    "placetype": [
      "aat:300008795"
    ],
    "name:en": "Abu 'Abîd, Gebel",
    "id": 7520660
  }
}
