{
  "geometry": {
    "type": "Point",
    "coordinates": [
      -80.3167,
      32.8833
    ]
  },
  "type": "Feature",
  "properties": {
    "hierarchy": [
      "tgn:2095563",
      "tgn:1000001",
      "tgn:2001742",
      "tgn:7012149",
      "tgn:7007712",
      "tgn:7029392"
    ],
    "placetype": [
      "aat:300008347",
      "aat:300387210"
    ],
    "id": 2095563,
    "name:xx": "Clubhouse Crossroads"
  }
}
