{
  "geometry": {
    "type": "Point",
    "coordinates": [
      -61.116,
      -16.083
    ]
  },
  "type": "Feature",
  "properties": {
    "hierarchy": [
      "tgn:1128384",
      "tgn:1000752",
      "tgn:1000046",
      "tgn:1000002",
      "tgn:7029392"
    ],
    "placetype": [
      "aat:300008707"
    ],
    "id": 1128384,
    "name:xx": "Paraguá, Rio"
  }
}
