{
  "geometry": {
    "type": "Point",
    "coordinates": [
      -108.7667,
      40.8667
    ]
  },
  "type": "Feature",
  "properties": {
    "hierarchy": [
      "tgn:2236463",
      "tgn:1000001",
      "tgn:7012149",
      "tgn:2000232",
      "tgn:7007158",
      "tgn:7029392"
    ],
    "placetype": [
      "aat:300008697"
    ],
    "id": 2236463,
    "name:xx": "Chicken Spring"
  }
}
