{
  "geometry": {
    "type": "Point",
    "coordinates": [
      -90.15,
      38.5333
    ]
  },
  "type": "Feature",
  "properties": {
    "hierarchy": [
      "tgn:2557625",
      "tgn:1000001",
      "tgn:7012149",
      "tgn:7016022",
      "tgn:7007251",
      "tgn:7029392"
    ],
    "placetype": [
      "aat:300008706"
    ],
    "id": 2557625,
    "name:xx": "Old Prairie duPont Creek"
  }
}
