{
  "geometry": {
    "type": "Point",
    "coordinates": [
      -156.4667,
      57.05
    ]
  },
  "type": "Feature",
  "properties": {
    "hierarchy": [
      "tgn:2465767",
      "tgn:7006450",
      "tgn:1000001",
      "tgn:7030517",
      "tgn:7012149",
      "tgn:7029392"
    ],
    "placetype": [
      "aat:300008791"
    ],
    "id": 2465767,
    "name:xx": "Lone Rock"
  }
}
