{
  "geometry": {
    "type": "Point",
    "coordinates": [
      -77.2833,
      37.3667
    ]
  },
  "type": "Feature",
  "properties": {
    "hierarchy": [
      "tgn:2272000",
      "tgn:1000001",
      "tgn:7012149",
      "tgn:1002467",
      "tgn:7007919",
      "tgn:7029392"
    ],
    "placetype": [
      "aat:300008850"
    ],
    "id": 2272000,
    "name:xx": "Curles Neck"
  }
}
