{
  "type": "FeatureCollection",
  "features": [
    {
      "geometry": {
        "type": "Point",
        "coordinates": [
          -113.5667,
          36.15
        ]
      },
      "type": "Feature",
      "properties": {
        "hierarchy": [
          "tgn:2553610",
          "tgn:1000001",
          "tgn:7006451",
          "tgn:7012149",
          "tgn:2000098",
          "tgn:7029392"
        ],
        "placetype": [
          "aat:300008347"
        ],
        "id": 2553610,
        "name:xx": "Oak Grove"
      }
    },
    {
      "geometry": {
        "type": "Point",
        "coordinates": [
          -92.0167,
          33.9333
        ]
      },
      "type": "Feature",
      "properties": {
        "hierarchy": [
          "tgn:2553611",
          "tgn:1000001",
          "tgn:7016172",
          "tgn:2000117",
          "tgn:7012149",
          "tgn:7029392"
        ],
        "placetype": [
          "aat:300008347"
        ],
        "id": 2553611,
        "name:xx": "Oak Grove"
      }
    },
    {
      "geometry": {
        "type": "Point",
        "coordinates": [
          -94.2833,
          35.4167
        ]
      },
      "type": "Feature",
      "properties": {
        "hierarchy": [
          "tgn:2553612",
          "tgn:1000001",
          "tgn:7016172",
          "tgn:2000121",
          "tgn:7012149",
          "tgn:7029392"
        ],
        "placetype": [
          "aat:300008347"
        ],
        "id": 2553612,
        "name:xx": "Oak Grove"
      }
    },
    {
      "geometry": {
        "type": "Point",
        "coordinates": [
          -93.6833,
          35.6
        ]
      },
      "type": "Feature",
      "properties": {
        "hierarchy": [
          "tgn:2553613",
          "tgn:1000001",
          "tgn:7016172",
          "tgn:7012149",
          "tgn:2000140",
          "tgn:7029392"
        ],
        "placetype": [
          "aat:300008347"
        ],
        "id": 2553613,
        "name:xx": "Oak Grove"
      }
    },
    {
      "geometry": {
        "type": "Point",
        "coordinates": [
          -93.2167,
          35.1833
        ]
      },
      "type": "Feature",
      "properties": {
        "hierarchy": [
          "tgn:2553614",
          "tgn:1000001",
          "tgn:7016172",
          "tgn:7012149",
          "tgn:2000179",
          "tgn:7029392"
        ],
        "placetype": [
          "aat:300008347"
        ],
        "id": 2553614,
        "name:xx": "Oak Grove"
      }
    },
    {
      "geometry": {
        "type": "Point",
        "coordinates": [
          -94.0167,
          36.2833
        ]
      },
      "type": "Feature",
      "properties": {
        "hierarchy": [
          "tgn:2553615",
          "tgn:1000001",
          "tgn:2000108",
          "tgn:7016172",
          "tgn:7012149",
          "tgn:7029392"
        ],
        "placetype": [
          "aat:300008347"
        ],
        "id": 2553615,
        "name:xx": "Oak Grove"
      }
    },
    {
      "geometry": {
        "type": "Point",
        "coordinates": [
          -120.8833,
          38.1167
        ]
      },
      "type": "Feature",
      "properties": {
        "hierarchy": [
          "tgn:2553616",
          "tgn:1000001",
          "tgn:1002219",
          "tgn:7012149",
          "tgn:7007157",
          "tgn:7029392"
        ],
        "placetype": [
          "aat:300008347"
        ],
        "id": 2553616,
        "name:xx": "Oak Grove"
      }
    },
    {
      "geometry": {
        "type": "Point",
        "coordinates": [
          -123.4833,
          40.4
        ]
      },
      "type": "Feature",
      "properties": {
        "hierarchy": [
          "tgn:2553617",
          "tgn:1000001",
          "tgn:7012149",
          "tgn:7007157",
          "tgn:2000191",
          "tgn:7029392"
        ],
        "placetype": [
          "aat:300132451"
        ],
        "id": 2553617,
        "name:xx": "Oak Grove"
      }
    },
    {
      "geometry": {
        "type": "Point",
        "coordinates": [
          -118.7833,
          36.45
        ]
      },
      "type": "Feature",
      "properties": {
        "hierarchy": [
          "tgn:2553618",
          "tgn:1000001",
          "tgn:7012149",
          "tgn:7007157",
          "tgn:1002956",
          "tgn:7029392"
        ],
        "placetype": [
          "aat:300008347"
        ],
        "id": 2553618,
        "name:xx": "Oak Grove"
      }
    },
    {
      "geometry": {
        "type": "Point",
        "coordinates": [
          -82.5167,
          32.1167
        ]
      },
      "type": "Feature",
      "properties": {
        "hierarchy": [
          "tgn:2553619",
          "tgn:1000001",
          "tgn:7012149",
          "tgn:2000394",
          "tgn:7007248",
          "tgn:7029392"
        ],
        "placetype": [
          "aat:300008347"
        ],
        "id": 2553619,
        "name:xx": "Oak Grove"
      }
    }
  ]
}
