{
  "geometry": {
    "type": "Point",
    "coordinates": [
      -82.35,
      37.1833
    ]
  },
  "type": "Feature",
  "properties": {
    "hierarchy": [
      "tgn:2711929",
      "tgn:1000001",
      "tgn:7012149",
      "tgn:2002157",
      "tgn:7007919",
      "tgn:7029392"
    ],
    "placetype": [
      "aat:300008699"
    ],
    "id": 2711929,
    "name:xx": "Tarpon Branch"
  }
}
