{
  "geometry": {
    "type": "Point",
    "coordinates": [
      -81.8667,
      27.2167
    ]
  },
  "type": "Feature",
  "properties": {
    "hierarchy": [
      "tgn:2431678",
      "tgn:1000001",
      "tgn:7021603",
      "tgn:7012149",
      "tgn:7007240",
      "tgn:7029392"
    ],
    "placetype": [
      "aat:300008680"
    ],
    "id": 2431678,
    "name:xx": "Katherine, Lake"
  }
}
