{
  "geometry": {
    "type": "Point",
    "coordinates": [
      132.3333,
      62.05
    ]
  },
  "type": "Feature",
  "properties": {
    "hierarchy": [
      "tgn:1051464",
      "tgn:1000004",
      "tgn:7011528",
      "tgn:7002435",
      "tgn:7029392"
    ],
    "placetype": [
      "aat:300008347"
    ],
    "id": 1051464,
    "name:xx": "Churapcha"
  }
}
