{
  "geometry": {
    "type": "Point",
    "coordinates": [
      -91.5667,
      45.75
    ]
  },
  "type": "Feature",
  "properties": {
    "hierarchy": [
      "tgn:2582884",
      "tgn:1000001",
      "tgn:7012149",
      "tgn:2002360",
      "tgn:7007922",
      "tgn:7029392"
    ],
    "placetype": [
      "aat:300008680"
    ],
    "id": 2582884,
    "name:xx": "Pine Island Lake"
  }
}
