{
  "geometry": {
    "type": "Point",
    "coordinates": [
      -105.15,
      37.1333
    ]
  },
  "type": "Feature",
  "properties": {
    "hierarchy": [
      "tgn:2124576",
      "tgn:1000001",
      "tgn:7012149",
      "tgn:7007158",
      "tgn:7029392"
    ],
    "placetype": [
      "aat:300008706"
    ],
    "id": 2124576,
    "name:xx": "Abbot Creek"
  }
}
