{
  "geometry": {
    "type": "Point",
    "coordinates": [
      -88.0833,
      37.3333
    ]
  },
  "type": "Feature",
  "properties": {
    "hierarchy": [
      "tgn:2000784",
      "tgn:1000001",
      "tgn:7012149",
      "tgn:7007255",
      "tgn:7029392"
    ],
    "placetype": [
      "aat:300387145",
      "aat:300000771"
    ],
    "id": 2000784,
    "name:xx": "Crittenden"
  }
}
