{
  "geometry": {
    "type": "Point",
    "coordinates": [
      -113.5667,
      35.4667
    ]
  },
  "type": "Feature",
  "properties": {
    "hierarchy": [
      "tgn:2530309",
      "tgn:1000001",
      "tgn:7006451",
      "tgn:7012149",
      "tgn:2000098",
      "tgn:7029392"
    ],
    "placetype": [
      "aat:300006191"
    ],
    "id": 2530309,
    "name:xx": "Mud Tank"
  }
}
