{
  "geometry": {
    "type": "Point",
    "coordinates": [
      -73.8333,
      -43.95
    ]
  },
  "type": "Feature",
  "properties": {
    "hierarchy": [
      "tgn:1010026",
      "tgn:1001623",
      "tgn:1000049",
      "tgn:1000002",
      "tgn:7029392"
    ],
    "placetype": [
      "aat:300386853"
    ],
    "id": 1010026,
    "name:xx": "Guaitecas, Archipiélago de las"
  }
}
