{
  "geometry": {
    "type": "Point",
    "coordinates": [
      -102.6667,
      41.0333
    ]
  },
  "type": "Feature",
  "properties": {
    "hierarchy": [
      "tgn:7023118",
      "tgn:1000001",
      "tgn:7012149",
      "tgn:7029392"
    ],
    "placetype": [
      "aat:300008761"
    ],
    "id": 7023118,
    "name:xx": "Sedgwick Draw"
  }
}
