{
  "geometry": {
    "type": "Point",
    "coordinates": [
      -116.9167,
      40.2833
    ]
  },
  "type": "Feature",
  "properties": {
    "hierarchy": [
      "tgn:2253796",
      "tgn:1000001",
      "tgn:7012149",
      "tgn:7007526",
      "tgn:7029392"
    ],
    "placetype": [
      "aat:300008706"
    ],
    "id": 2253796,
    "name:xx": "Cooks Creek"
  }
}
