{
  "geometry": {
    "type": "Point",
    "coordinates": [
      -114.3667,
      34.1167
    ]
  },
  "type": "Feature",
  "properties": {
    "hierarchy": [
      "tgn:7020653",
      "tgn:1000001",
      "tgn:7012149",
      "tgn:7007157",
      "tgn:1002857",
      "tgn:7029392"
    ],
    "placetype": [
      "aat:300008791"
    ],
    "id": 7020653,
    "name:xx": "Deer Island"
  }
}
