{
  "geometry": {
    "type": "Point",
    "coordinates": [
      78.827864,
      24.647603
    ]
  },
  "type": "Feature",
  "properties": {
    "hierarchy": [
      "tgn:7585101",
      "tgn:1000004",
      "tgn:7000198",
      "tgn:1001894",
      "tgn:7029392"
    ],
    "placetype": [
      "aat:300008699"
    ],
    "name:en": "Dānka Nāla",
    "id": 7585101
  }
}
