{
  "geometry": {
    "type": "Point",
    "coordinates": [
      -81.7667,
      30.0333
    ]
  },
  "type": "Feature",
  "properties": {
    "hierarchy": [
      "tgn:2513480",
      "tgn:1000001",
      "tgn:2000261",
      "tgn:7012149",
      "tgn:7007240",
      "tgn:7029392"
    ],
    "placetype": [
      "aat:300008706"
    ],
    "id": 2513480,
    "name:xx": "Mill Log Creek"
  }
}
