{
  "geometry": {
    "type": "Point",
    "coordinates": [
      -77.5667,
      37.7333
    ]
  },
  "type": "Feature",
  "properties": {
    "hierarchy": [
      "tgn:2690369",
      "tgn:1000001",
      "tgn:7012149",
      "tgn:1002451",
      "tgn:7007919",
      "tgn:7029392"
    ],
    "placetype": [
      "aat:300008706"
    ],
    "id": 2690369,
    "name:xx": "Stagg Creek"
  }
}
