{
  "geometry": {
    "type": "Point",
    "coordinates": [
      33.978333,
      29.490278
    ]
  },
  "type": "Feature",
  "properties": {
    "hierarchy": [
      "tgn:7536050",
      "tgn:7001242",
      "tgn:7016833",
      "tgn:7001336",
      "tgn:7029392"
    ],
    "placetype": [
      "aat:300379998"
    ],
    "name:en": "Gerâ'a, Wâdi",
    "id": 7536050
  }
}
