{
  "type": "FeatureCollection",
  "features": [
    {
      "geometry": {
        "type": "Point",
        "coordinates": [
          48.35,
          34.2167
        ]
      },
      "type": "Feature",
      "properties": {
        "hierarchy": [
          "tgn:7017472",
          "tgn:1000004",
          "tgn:1001283",
          "tgn:7000231",
          "tgn:7029392"
        ],
        "placetype": [
          "aat:300008347",
          "aat:300000835"
        ],
        "id": 7017472,
        "name:xx": "Nahāvand"
      }
    },
    {
      "geometry": {
        "type": "Point",
        "coordinates": [
          27.2,
          46.3333
        ]
      },
      "type": "Feature",
      "properties": {
        "hierarchy": [
          "tgn:7017477",
          "tgn:1000342",
          "tgn:1000003",
          "tgn:1000091",
          "tgn:7029392"
        ],
        "placetype": [
          "aat:300008347"
        ],
        "id": 7017477,
        "name:xx": "Marginea"
      }
    },
    {
      "geometry": {
        "type": "Point",
        "coordinates": [
          23.916,
          47.15
        ]
      },
      "type": "Feature",
      "properties": {
        "hierarchy": [
          "tgn:7017479",
          "tgn:1000003",
          "tgn:1000091",
          "tgn:7029392"
        ],
        "placetype": [
          "aat:300008707"
        ],
        "id": 7017479,
        "name:xx": "Someșu Mic"
      }
    }
  ]
}
