{
  "geometry": {
    "type": "Point",
    "coordinates": [
      -122.8167,
      45.5333
    ]
  },
  "type": "Feature",
  "properties": {
    "hierarchy": [
      "tgn:2288020",
      "tgn:1000001",
      "tgn:7012149",
      "tgn:1002994",
      "tgn:7007708",
      "tgn:7029392"
    ],
    "placetype": [
      "aat:300006191"
    ],
    "id": 2288020,
    "name:xx": "Dinihanian Reservoir"
  }
}
