{
  "geometry": {
    "type": "Point",
    "coordinates": [
      -114.2167,
      43.9833
    ]
  },
  "type": "Feature",
  "properties": {
    "hierarchy": [
      "tgn:2386509",
      "tgn:1000001",
      "tgn:2000470",
      "tgn:7012149",
      "tgn:7007250",
      "tgn:7029392"
    ],
    "placetype": [
      "aat:300008798"
    ],
    "id": 2386509,
    "name:xx": "Herd Peak"
  }
}
