{
  "geometry": {
    "type": "Point",
    "coordinates": [
      -110.5333,
      41.6667
    ]
  },
  "type": "Feature",
  "properties": {
    "hierarchy": [
      "tgn:2179807",
      "tgn:1000001",
      "tgn:7012149",
      "tgn:2002376",
      "tgn:7007923",
      "tgn:7029392"
    ],
    "placetype": [
      "aat:300000390"
    ],
    "id": 2179807,
    "name:xx": "Blazon Mine"
  }
}
