{
  "geometry": {
    "type": "Point",
    "coordinates": [
      -83.75,
      36.0167
    ]
  },
  "type": "Feature",
  "properties": {
    "hierarchy": [
      "tgn:2634678",
      "tgn:1000001",
      "tgn:7012149",
      "tgn:2001883",
      "tgn:7007825",
      "tgn:7029392"
    ],
    "placetype": [
      "aat:300008699"
    ],
    "id": 2634678,
    "name:xx": "Rutherford Branch"
  }
}
