{
  "geometry": {
    "type": "Point",
    "coordinates": [
      6.1167,
      48.75
    ]
  },
  "type": "Feature",
  "properties": {
    "hierarchy": [
      "tgn:1123675",
      "tgn:1000003",
      "tgn:7029392"
    ],
    "placetype": [
      "aat:300008707"
    ],
    "id": 1123675,
    "name:xx": "Eisch"
  }
}
