{
  "geometry": {
    "type": "Point",
    "coordinates": [
      -85.1167,
      45.0667
    ]
  },
  "type": "Feature",
  "properties": {
    "hierarchy": [
      "tgn:2712730",
      "tgn:2000945",
      "tgn:1000001",
      "tgn:7012149",
      "tgn:7007520",
      "tgn:7029392"
    ],
    "placetype": [
      "aat:300008706"
    ],
    "id": 2712730,
    "name:xx": "Taylor Creek"
  }
}
