{
  "geometry": {
    "type": "Point",
    "coordinates": [
      -94.3167,
      38.8167
    ]
  },
  "type": "Feature",
  "properties": {
    "hierarchy": [
      "tgn:2706584",
      "tgn:1000001",
      "tgn:2001182",
      "tgn:7012149",
      "tgn:7007523",
      "tgn:7029392"
    ],
    "placetype": [
      "aat:300006191"
    ],
    "id": 2706584,
    "name:xx": "Swan Lake"
  }
}
