{
  "type": "FeatureCollection",
  "features": [
    {
      "geometry": {
        "type": "Point",
        "coordinates": [
          -72,
          42.6833
        ]
      },
      "type": "Feature",
      "properties": {
        "hierarchy": [
          "tgn:2050981",
          "tgn:1000001",
          "tgn:7012149",
          "tgn:1003038",
          "tgn:7007517",
          "tgn:7029392"
        ],
        "placetype": [
          "aat:300008347"
        ],
        "id": 2050981,
        "name:xx": "Winchendon Springs"
      }
    },
    {
      "geometry": {
        "type": "Point",
        "coordinates": [
          -71.1333,
          42.4333
        ]
      },
      "type": "Feature",
      "properties": {
        "hierarchy": [
          "tgn:2050984",
          "tgn:1000001",
          "tgn:1002665",
          "tgn:7012149",
          "tgn:7014635",
          "tgn:7007517",
          "tgn:7029392"
        ],
        "placetype": [
          "aat:300000745"
        ],
        "id": 2050984,
        "name:xx": "Symmes Corner"
      }
    },
    {
      "geometry": {
        "type": "Point",
        "coordinates": [
          -71.1333,
          42.4333
        ]
      },
      "type": "Feature",
      "properties": {
        "hierarchy": [
          "tgn:2050985",
          "tgn:1000001",
          "tgn:1002665",
          "tgn:7012149",
          "tgn:7014635",
          "tgn:7007517",
          "tgn:7029392"
        ],
        "placetype": [
          "aat:300000745"
        ],
        "id": 2050985,
        "name:xx": "Wedgemere"
      }
    },
    {
      "geometry": {
        "type": "Point",
        "coordinates": [
          -71.1167,
          42.4667
        ]
      },
      "type": "Feature",
      "properties": {
        "hierarchy": [
          "tgn:2050986",
          "tgn:1000001",
          "tgn:1002665",
          "tgn:7012149",
          "tgn:7014635",
          "tgn:7007517",
          "tgn:7029392"
        ],
        "placetype": [
          "aat:300000745"
        ],
        "id": 2050986,
        "name:xx": "Winchester Highlands"
      }
    },
    {
      "geometry": {
        "type": "Point",
        "coordinates": [
          -73.05,
          42.5
        ]
      },
      "type": "Feature",
      "properties": {
        "hierarchy": [
          "tgn:2050987",
          "tgn:7013388",
          "tgn:1000001",
          "tgn:7012149",
          "tgn:7007517",
          "tgn:7029392"
        ],
        "placetype": [
          "aat:300008347"
        ],
        "id": 2050987,
        "name:xx": "Windsor"
      }
    },
    {
      "geometry": {
        "type": "Point",
        "coordinates": [
          -71.1167,
          41.9667
        ]
      },
      "type": "Feature",
      "properties": {
        "hierarchy": [
          "tgn:2050989",
          "tgn:1002201",
          "tgn:1000001",
          "tgn:7012149",
          "tgn:7007517",
          "tgn:7029392"
        ],
        "placetype": [
          "aat:300008347"
        ],
        "id": 2050989,
        "name:xx": "Winnecunnet"
      }
    }
  ]
}
