{
  "geometry": {
    "type": "Point",
    "coordinates": [
      -114.3167,
      36.0333
    ]
  },
  "type": "Feature",
  "properties": {
    "hierarchy": [
      "tgn:2520579",
      "tgn:1000001",
      "tgn:7006451",
      "tgn:7012149",
      "tgn:2000098",
      "tgn:7029392"
    ],
    "placetype": [
      "aat:300132316"
    ],
    "id": 2520579,
    "name:xx": "Monkey Cove"
  }
}
