{
  "geometry": {
    "type": "Point",
    "coordinates": [
      -119.6333,
      41.3333
    ]
  },
  "type": "Feature",
  "properties": {
    "hierarchy": [
      "tgn:2470143",
      "tgn:1000001",
      "tgn:7012149",
      "tgn:1002999",
      "tgn:7007526",
      "tgn:7029392"
    ],
    "placetype": [
      "aat:300008697"
    ],
    "id": 2470143,
    "name:xx": "Lope Spring"
  }
}
