{
  "geometry": {
    "type": "Point",
    "coordinates": [
      -113.2667,
      34.9333
    ]
  },
  "type": "Feature",
  "properties": {
    "hierarchy": [
      "tgn:2126333",
      "tgn:1000001",
      "tgn:7006451",
      "tgn:7012149",
      "tgn:7029392"
    ],
    "placetype": [
      "aat:300008706"
    ],
    "id": 2126333,
    "name:xx": "Adobe Creek"
  }
}
