{
  "geometry": {
    "type": "Point",
    "coordinates": [
      -111.4667,
      31.5333
    ]
  },
  "type": "Feature",
  "properties": {
    "hierarchy": [
      "tgn:2149209",
      "tgn:1000001",
      "tgn:7006451",
      "tgn:7012149",
      "tgn:2000100",
      "tgn:7029392"
    ],
    "placetype": [
      "aat:300006191"
    ],
    "id": 2149209,
    "name:xx": "Barrel Cactus Tank"
  }
}
