{
  "geometry": {
    "type": "Point",
    "coordinates": [
      -116.5667,
      33.0667
    ]
  },
  "type": "Feature",
  "properties": {
    "hierarchy": [
      "tgn:2475721",
      "tgn:1000001",
      "tgn:7012149",
      "tgn:7007157",
      "tgn:1002858",
      "tgn:7029392"
    ],
    "placetype": [
      "aat:300000390"
    ],
    "id": 2475721,
    "name:xx": "Lucky Pardner Mine"
  }
}
