{
  "type": "FeatureCollection",
  "features": [
    {
      "geometry": {
        "type": "Point",
        "coordinates": [
          9,
          40.916667
        ]
      },
      "type": "Feature",
      "properties": {
        "hierarchy": [
          "tgn:7050510",
          "tgn:7015163",
          "tgn:1000003",
          "tgn:7003121",
          "tgn:1000080",
          "tgn:7029392"
        ],
        "placetype": [
          "aat:300008795"
        ],
        "id": 7050510,
        "name:xx": "Lasana, Monte"
      }
    },
    {
      "geometry": {
        "type": "Point",
        "coordinates": [
          13.716667,
          42.533333
        ]
      },
      "type": "Feature",
      "properties": {
        "hierarchy": [
          "tgn:7050511",
          "tgn:7009084",
          "tgn:7003001",
          "tgn:1000003",
          "tgn:1000080",
          "tgn:7029392"
        ],
        "placetype": [
          "aat:300008347"
        ],
        "id": 7050511,
        "name:xx": "La Salza"
      }
    },
    {
      "geometry": {
        "type": "Point",
        "coordinates": [
          11.916667,
          44.883333
        ]
      },
      "type": "Feature",
      "properties": {
        "hierarchy": [
          "tgn:7050513",
          "tgn:7003128",
          "tgn:1000003",
          "tgn:7008516",
          "tgn:1000080",
          "tgn:7029392"
        ],
        "placetype": [
          "aat:300008347"
        ],
        "id": 7050513,
        "name:xx": "La Salana"
      }
    },
    {
      "geometry": {
        "type": "Point",
        "coordinates": [
          11.3,
          42.8
        ]
      },
      "type": "Feature",
      "properties": {
        "hierarchy": [
          "tgn:7050514",
          "tgn:1003460",
          "tgn:1000003",
          "tgn:7009760",
          "tgn:1000080",
          "tgn:7029392"
        ],
        "placetype": [
          "aat:300008347"
        ],
        "id": 7050514,
        "name:xx": "Sabatina"
      }
    },
    {
      "geometry": {
        "type": "Point",
        "coordinates": [
          9.633333,
          44.95
        ]
      },
      "type": "Feature",
      "properties": {
        "hierarchy": [
          "tgn:7050516",
          "tgn:7003132",
          "tgn:1000003",
          "tgn:7008516",
          "tgn:1000080",
          "tgn:7029392"
        ],
        "placetype": [
          "aat:300008347"
        ],
        "id": 7050516,
        "name:xx": "Larzano"
      }
    },
    {
      "geometry": {
        "type": "Point",
        "coordinates": [
          14.9,
          37.5
        ]
      },
      "type": "Feature",
      "properties": {
        "hierarchy": [
          "tgn:7050517",
          "tgn:1000003",
          "tgn:1001651",
          "tgn:7003122",
          "tgn:1000080",
          "tgn:7029392"
        ],
        "placetype": [
          "aat:300008347"
        ],
        "id": 7050517,
        "name:xx": "La Rotondella"
      }
    },
    {
      "geometry": {
        "type": "Point",
        "coordinates": [
          16.4,
          40.016667
        ]
      },
      "type": "Feature",
      "properties": {
        "hierarchy": [
          "tgn:7050518",
          "tgn:1003450",
          "tgn:7007850",
          "tgn:1000003",
          "tgn:1000080",
          "tgn:7029392"
        ],
        "placetype": [
          "aat:300008795"
        ],
        "id": 7050518,
        "name:xx": "La Rotondella"
      }
    },
    {
      "geometry": {
        "type": "Point",
        "coordinates": [
          14.433333,
          40.583333
        ]
      },
      "type": "Feature",
      "properties": {
        "hierarchy": [
          "tgn:7050519",
          "tgn:7003013",
          "tgn:7003005",
          "tgn:1000003",
          "tgn:1000080",
          "tgn:7029392"
        ],
        "placetype": [
          "aat:300008791"
        ],
        "id": 7050519,
        "name:xx": "La Rotonda"
      }
    }
  ]
}
