{
  "geometry": {
    "type": "Point",
    "coordinates": [
      79.416287,
      26.40609
    ]
  },
  "type": "Feature",
  "properties": {
    "hierarchy": [
      "tgn:7565941",
      "tgn:1000004",
      "tgn:7000198",
      "tgn:7016722",
      "tgn:7029392"
    ],
    "placetype": [
      "aat:300008347"
    ],
    "name:en": "Lārpur Mustaqil",
    "id": 7565941
  }
}
