{
  "geometry": {
    "type": "Point",
    "coordinates": [
      -111.3833,
      43.1833
    ]
  },
  "type": "Feature",
  "properties": {
    "hierarchy": [
      "tgn:2242604",
      "tgn:1000001",
      "tgn:2000461",
      "tgn:7012149",
      "tgn:7007250",
      "tgn:7029392"
    ],
    "placetype": [
      "aat:300008706"
    ],
    "id": 2242604,
    "name:xx": "Clear Creek"
  }
}
