{
  "geometry": {
    "type": "Point",
    "coordinates": [
      -71.7833,
      43.2333
    ]
  },
  "type": "Feature",
  "properties": {
    "hierarchy": [
      "tgn:2146099",
      "tgn:1000001",
      "tgn:2001425",
      "tgn:7012149",
      "tgn:7007564",
      "tgn:7029392"
    ],
    "placetype": [
      "aat:300008699"
    ],
    "id": 2146099,
    "name:xx": "Ballard Brook"
  }
}
