{
  "geometry": {
    "type": "Point",
    "coordinates": [
      -63.6667,
      45.8667
    ]
  },
  "type": "Feature",
  "properties": {
    "hierarchy": [
      "tgn:1014501",
      "tgn:7005685",
      "tgn:1000001",
      "tgn:7005802",
      "tgn:7029392"
    ],
    "placetype": [
      "aat:300008347"
    ],
    "id": 1014501,
    "name:xx": "Pugwash"
  }
}
