{
  "geometry": {
    "type": "Point",
    "coordinates": [
      -82.2667,
      39.6333
    ]
  },
  "type": "Feature",
  "properties": {
    "hierarchy": [
      "tgn:2639262",
      "tgn:1000001",
      "tgn:7012149",
      "tgn:2001620",
      "tgn:7007706",
      "tgn:7029392"
    ],
    "placetype": [
      "aat:300008699"
    ],
    "id": 2639262,
    "name:xx": "Salt Run"
  }
}
