{
  "geometry": {
    "type": "Point",
    "coordinates": [
      -72.75,
      43.6833
    ]
  },
  "type": "Feature",
  "properties": {
    "hierarchy": [
      "tgn:2603927",
      "tgn:1000001",
      "tgn:1002840",
      "tgn:7012149",
      "tgn:7007828",
      "tgn:7029392"
    ],
    "placetype": [
      "aat:300008798"
    ],
    "id": 2603927,
    "name:xx": "Quimby Mountain"
  }
}
