{
  "geometry": {
    "type": "Point",
    "coordinates": [
      -111.2333,
      31.4167
    ]
  },
  "type": "Feature",
  "properties": {
    "hierarchy": [
      "tgn:2264962",
      "tgn:1000001",
      "tgn:7006451",
      "tgn:7012149",
      "tgn:2000102",
      "tgn:7029392"
    ],
    "placetype": [
      "aat:300000390"
    ],
    "id": 2264962,
    "name:xx": "Cramer Mine"
  }
}
