{
  "geometry": {
    "type": "Point",
    "coordinates": [
      -1.9833,
      48.5167
    ]
  },
  "type": "Feature",
  "properties": {
    "hierarchy": [
      "tgn:1128995",
      "tgn:1000003",
      "tgn:7012216",
      "tgn:1000070",
      "tgn:7029392"
    ],
    "placetype": [
      "aat:300008707"
    ],
    "id": 1128995,
    "name:xx": "Rance"
  }
}
