{
  "geometry": {
    "type": "Point",
    "coordinates": [
      -112.15,
      36.55
    ]
  },
  "type": "Feature",
  "properties": {
    "hierarchy": [
      "tgn:2679799",
      "tgn:1000001",
      "tgn:7006451",
      "tgn:2000092",
      "tgn:7012149",
      "tgn:7029392"
    ],
    "placetype": [
      "aat:300008761"
    ],
    "id": 2679799,
    "name:xx": "South Fork Rock Canyon"
  }
}
