{
  "geometry": {
    "type": "Point",
    "coordinates": [
      -89.15,
      39.3667
    ]
  },
  "type": "Feature",
  "properties": {
    "hierarchy": [
      "tgn:2029953",
      "tgn:1000001",
      "tgn:1002268",
      "tgn:7012149",
      "tgn:7007251",
      "tgn:7029392"
    ],
    "placetype": [
      "aat:300008347"
    ],
    "id": 2029953,
    "name:xx": "Rosamond"
  }
}
