{
  "geometry": {
    "type": "Point",
    "coordinates": [
      79.02706,
      33.320496
    ]
  },
  "type": "Feature",
  "properties": {
    "hierarchy": [
      "tgn:7556989",
      "tgn:1000004",
      "tgn:7000198",
      "tgn:7000799",
      "tgn:7029392"
    ],
    "placetype": [
      "aat:300008795"
    ],
    "name:en": "Sājum",
    "id": 7556989
  }
}
