{
  "geometry": {
    "type": "Point",
    "coordinates": [
      -112.7667,
      37.5167
    ]
  },
  "type": "Feature",
  "properties": {
    "hierarchy": [
      "tgn:2536226",
      "tgn:1000001",
      "tgn:7012149",
      "tgn:2002113",
      "tgn:7007827",
      "tgn:7029392"
    ],
    "placetype": [
      "aat:300006191"
    ],
    "id": 2536226,
    "name:xx": "Navajo Lake"
  }
}
