{
  "geometry": {
    "type": "Point",
    "coordinates": [
      -85.6833,
      36.2667
    ]
  },
  "type": "Feature",
  "properties": {
    "hierarchy": [
      "tgn:2488376",
      "tgn:1000001",
      "tgn:7012149",
      "tgn:2001880",
      "tgn:7007825",
      "tgn:7029392"
    ],
    "placetype": [
      "aat:300008746"
    ],
    "id": 2488376,
    "name:xx": "Mahaney Pit"
  }
}
