{
  "geometry": {
    "type": "Point",
    "coordinates": [
      -71.1333,
      44.9333
    ]
  },
  "type": "Feature",
  "properties": {
    "hierarchy": [
      "tgn:2731283",
      "tgn:1002300",
      "tgn:1000001",
      "tgn:7012149",
      "tgn:7007564",
      "tgn:7029392"
    ],
    "placetype": [
      "aat:300008798"
    ],
    "id": 2731283,
    "name:xx": "Tucker, Mount"
  }
}
