{
  "geometry": {
    "type": "Point",
    "coordinates": [
      -2.95,
      53.75
    ]
  },
  "type": "Feature",
  "properties": {
    "hierarchy": [
      "tgn:1030095",
      "tgn:7002445",
      "tgn:1000003",
      "tgn:7008154",
      "tgn:7008591",
      "tgn:7029392"
    ],
    "placetype": [
      "aat:300008347"
    ],
    "name:en": "Moss Side",
    "id": 1030095
  }
}
