{
  "geometry": {
    "type": "Point",
    "coordinates": [
      -149.1333,
      61.0167
    ]
  },
  "type": "Feature",
  "properties": {
    "hierarchy": [
      "tgn:2605346",
      "tgn:2124017",
      "tgn:7006450",
      "tgn:1000001",
      "tgn:7012149",
      "tgn:7029392"
    ],
    "placetype": [
      "aat:300008798"
    ],
    "id": 2605346,
    "name:xx": "Raggedtop Mountain"
  }
}
