{
  "geometry": {
    "type": "Point",
    "coordinates": [
      10.6333,
      55.8167
    ]
  },
  "type": "Feature",
  "properties": {
    "hierarchy": [
      "tgn:1027723",
      "tgn:7594006",
      "tgn:1000003",
      "tgn:1000066",
      "tgn:7029392"
    ],
    "placetype": [
      "aat:300008347"
    ],
    "id": 1027723,
    "name:xx": "Ballen"
  }
}
