{
  "geometry": {
    "type": "Point",
    "coordinates": [
      -122.2333,
      38.5167
    ]
  },
  "type": "Feature",
  "properties": {
    "hierarchy": [
      "tgn:2701969",
      "tgn:1000001",
      "tgn:7012149",
      "tgn:7007157",
      "tgn:1002706",
      "tgn:7029392"
    ],
    "placetype": [
      "aat:300008798"
    ],
    "id": 2701969,
    "name:xx": "Sugarloaf Peak"
  }
}
