{
  "geometry": {
    "type": "Point",
    "coordinates": [
      -118.65,
      46.3833
    ]
  },
  "type": "Feature",
  "properties": {
    "hierarchy": [
      "tgn:2116799",
      "tgn:1000001",
      "tgn:7012149",
      "tgn:2002251",
      "tgn:7007920",
      "tgn:7029392"
    ],
    "placetype": [
      "aat:300387016"
    ],
    "id": 2116799,
    "name:xx": "Simmons"
  }
}
