{
  "geometry": {
    "type": "Point",
    "coordinates": [
      75.31409,
      23.279725
    ]
  },
  "type": "Feature",
  "properties": {
    "hierarchy": [
      "tgn:7549445",
      "tgn:1000004",
      "tgn:7000198",
      "tgn:1001894",
      "tgn:7029392"
    ],
    "placetype": [
      "aat:300008347"
    ],
    "name:en": "Dhānasutha",
    "id": 7549445
  }
}
