{
  "geometry": {
    "type": "Point",
    "coordinates": [
      25.416667,
      35.05
    ]
  },
  "type": "Feature",
  "properties": {
    "hierarchy": [
      "tgn:7017125",
      "tgn:7002690",
      "tgn:7012056",
      "tgn:1000003",
      "tgn:1000074",
      "tgn:7029392"
    ],
    "placetype": [
      "aat:300008347",
      "aat:300008375"
    ],
    "id": 7017125,
    "name:xx": "Áno Viánnos"
  }
}
