{
  "geometry": {
    "type": "Point",
    "coordinates": [
      49.25,
      46.9667
    ]
  },
  "type": "Feature",
  "properties": {
    "hierarchy": [
      "tgn:1059252",
      "tgn:7012908",
      "tgn:1000004",
      "tgn:7014786",
      "tgn:7029392"
    ],
    "placetype": [
      "aat:300008347"
    ],
    "id": 1059252,
    "name:xx": "Sazdy"
  }
}
