{
  "type": "FeatureCollection",
  "features": [
    {
      "geometry": {
        "type": "Point",
        "coordinates": [
          10.883333,
          42.9
        ]
      },
      "type": "Feature",
      "properties": {
        "hierarchy": [
          "tgn:7047250",
          "tgn:1003460",
          "tgn:1000003",
          "tgn:7009760",
          "tgn:1000080",
          "tgn:7029392"
        ],
        "placetype": [
          "aat:300008347"
        ],
        "id": 7047250,
        "name:xx": "Casa Villa"
      }
    },
    {
      "geometry": {
        "type": "Point",
        "coordinates": [
          13.1,
          43.566667
        ]
      },
      "type": "Feature",
      "properties": {
        "hierarchy": [
          "tgn:7047251",
          "tgn:1003429",
          "tgn:1000003",
          "tgn:7003240",
          "tgn:1000080",
          "tgn:7029392"
        ],
        "placetype": [
          "aat:300008347"
        ],
        "id": 7047251,
        "name:xx": "Casa Vici"
      }
    },
    {
      "geometry": {
        "type": "Point",
        "coordinates": [
          7.6,
          43.866667
        ]
      },
      "type": "Feature",
      "properties": {
        "hierarchy": [
          "tgn:7047252",
          "tgn:1000003",
          "tgn:7003141",
          "tgn:7003236",
          "tgn:1000080",
          "tgn:7029392"
        ],
        "placetype": [
          "aat:300008347"
        ],
        "id": 7047252,
        "name:xx": "Casa Verrando"
      }
    },
    {
      "geometry": {
        "type": "Point",
        "coordinates": [
          7.65,
          43.916667
        ]
      },
      "type": "Feature",
      "properties": {
        "hierarchy": [
          "tgn:7047253",
          "tgn:1000003",
          "tgn:7003141",
          "tgn:7003236",
          "tgn:1000080",
          "tgn:7029392"
        ],
        "placetype": [
          "aat:300008347"
        ],
        "id": 7047253,
        "name:xx": "Casa Veragne"
      }
    },
    {
      "geometry": {
        "type": "Point",
        "coordinates": [
          7.45,
          44.933333
        ]
      },
      "type": "Feature",
      "properties": {
        "hierarchy": [
          "tgn:7047254",
          "tgn:7003154",
          "tgn:1000003",
          "tgn:7003120",
          "tgn:1000080",
          "tgn:7029392"
        ],
        "placetype": [
          "aat:300008347"
        ],
        "id": 7047254,
        "name:xx": "Case Vecchie"
      }
    },
    {
      "geometry": {
        "type": "Point",
        "coordinates": [
          12,
          44.066667
        ]
      },
      "type": "Feature",
      "properties": {
        "hierarchy": [
          "tgn:7047255",
          "tgn:7003129",
          "tgn:1000003",
          "tgn:7008516",
          "tgn:1000080",
          "tgn:7029392"
        ],
        "placetype": [
          "aat:300008347"
        ],
        "id": 7047255,
        "name:xx": "Casa Vecchia"
      }
    },
    {
      "geometry": {
        "type": "Point",
        "coordinates": [
          13.316667,
          42.3
        ]
      },
      "type": "Feature",
      "properties": {
        "hierarchy": [
          "tgn:7047256",
          "tgn:7009084",
          "tgn:7004154",
          "tgn:1000003",
          "tgn:1000080",
          "tgn:7029392"
        ],
        "placetype": [
          "aat:300008347"
        ],
        "id": 7047256,
        "name:xx": "Casavecchia"
      }
    },
    {
      "geometry": {
        "type": "Point",
        "coordinates": [
          16.033333,
          38.383333
        ]
      },
      "type": "Feature",
      "properties": {
        "hierarchy": [
          "tgn:7047257",
          "tgn:7007850",
          "tgn:1003491",
          "tgn:1000003",
          "tgn:1000080",
          "tgn:7029392"
        ],
        "placetype": [
          "aat:300008347"
        ],
        "id": 7047257,
        "name:xx": "Casa Vatoni"
      }
    },
    {
      "geometry": {
        "type": "Point",
        "coordinates": [
          13.6,
          42.6
        ]
      },
      "type": "Feature",
      "properties": {
        "hierarchy": [
          "tgn:7047258",
          "tgn:7009084",
          "tgn:7003001",
          "tgn:1000003",
          "tgn:1000080",
          "tgn:7029392"
        ],
        "placetype": [
          "aat:300008347"
        ],
        "id": 7047258,
        "name:xx": "Casa Vernesi"
      }
    },
    {
      "geometry": {
        "type": "Point",
        "coordinates": [
          16.083333,
          38.15
        ]
      },
      "type": "Feature",
      "properties": {
        "hierarchy": [
          "tgn:7047259",
          "tgn:7007850",
          "tgn:1003491",
          "tgn:1000003",
          "tgn:1000080",
          "tgn:7029392"
        ],
        "placetype": [
          "aat:300008347"
        ],
        "id": 7047259,
        "name:xx": "Casa Varet"
      }
    }
  ]
}
