{
  "type": "FeatureCollection",
  "features": [
    {
      "geometry": {
        "type": "Point",
        "coordinates": [
          16.333333,
          38.9
        ]
      },
      "type": "Feature",
      "properties": {
        "hierarchy": [
          "tgn:7051850",
          "tgn:1003447",
          "tgn:7007850",
          "tgn:1000003",
          "tgn:1000080",
          "tgn:7029392"
        ],
        "placetype": [
          "aat:300008699"
        ],
        "id": 7051850,
        "name:xx": "Pesipo, Fiume"
      }
    },
    {
      "geometry": {
        "type": "Point",
        "coordinates": [
          13.898056,
          45.627778
        ]
      },
      "type": "Feature",
      "properties": {
        "hierarchy": [
          "tgn:7051852",
          "tgn:1003505",
          "tgn:1000003",
          "tgn:7002993",
          "tgn:1000080",
          "tgn:7029392"
        ],
        "placetype": [
          "aat:300008347"
        ],
        "id": 7051852,
        "name:xx": "Pese di Grozzana"
      }
    },
    {
      "geometry": {
        "type": "Point",
        "coordinates": [
          13.65,
          41.75
        ]
      },
      "type": "Feature",
      "properties": {
        "hierarchy": [
          "tgn:7051853",
          "tgn:7003135",
          "tgn:1000003",
          "tgn:7003080",
          "tgn:1000080",
          "tgn:7029392"
        ],
        "placetype": [
          "aat:300008347"
        ],
        "id": 7051853,
        "name:xx": "Pescosolido"
      }
    },
    {
      "geometry": {
        "type": "Point",
        "coordinates": [
          13.866667,
          42.233333
        ]
      },
      "type": "Feature",
      "properties": {
        "hierarchy": [
          "tgn:7051854",
          "tgn:7009084",
          "tgn:7004154",
          "tgn:1000003",
          "tgn:1000080",
          "tgn:7029392"
        ],
        "placetype": [
          "aat:300008347"
        ],
        "id": 7051854,
        "name:xx": "Pescosansonesco"
      }
    },
    {
      "geometry": {
        "type": "Point",
        "coordinates": [
          14.3,
          41.883333
        ]
      },
      "type": "Feature",
      "properties": {
        "hierarchy": [
          "tgn:7051857",
          "tgn:7009084",
          "tgn:7003000",
          "tgn:1000003",
          "tgn:1000080",
          "tgn:7029392"
        ],
        "placetype": [
          "aat:300008347"
        ],
        "id": 7051857,
        "name:xx": "Pescopennataro"
      }
    },
    {
      "geometry": {
        "type": "Point",
        "coordinates": [
          13.516667,
          42.35
        ]
      },
      "type": "Feature",
      "properties": {
        "hierarchy": [
          "tgn:7051859",
          "tgn:7009084",
          "tgn:7004154",
          "tgn:1000003",
          "tgn:1000080",
          "tgn:7029392"
        ],
        "placetype": [
          "aat:300008347"
        ],
        "id": 7051859,
        "name:xx": "Pescomaggiore"
      }
    }
  ]
}
