{
  "geometry": {
    "type": "Point",
    "coordinates": [
      -116.7167,
      32.75
    ]
  },
  "type": "Feature",
  "properties": {
    "hierarchy": [
      "tgn:2329543",
      "tgn:1000001",
      "tgn:7012149",
      "tgn:7007157",
      "tgn:1002863",
      "tgn:7029392"
    ],
    "placetype": [
      "aat:300008697"
    ],
    "id": 2329543,
    "name:xx": "Five Willow Spring"
  }
}
