{
  "geometry": {
    "type": "Point",
    "coordinates": [
      5.1667,
      5.5833
    ]
  },
  "type": "Feature",
  "properties": {
    "hierarchy": [
      "tgn:1135765",
      "tgn:7001242",
      "tgn:7015044",
      "tgn:1000182",
      "tgn:7029392"
    ],
    "placetype": [
      "aat:300387055"
    ],
    "id": 1135765,
    "name:xx": "Escravos"
  }
}
