{
  "geometry": {
    "type": "Point",
    "coordinates": [
      -81.05,
      40.8333
    ]
  },
  "type": "Feature",
  "properties": {
    "hierarchy": [
      "tgn:2080016",
      "tgn:1000001",
      "tgn:1002295",
      "tgn:7012149",
      "tgn:7007706",
      "tgn:7029392"
    ],
    "placetype": [
      "aat:300008347"
    ],
    "id": 2080016,
    "name:xx": "Homeworth"
  }
}
