{
  "geometry": {
    "type": "Point",
    "coordinates": [
      10.45,
      49.75
    ]
  },
  "type": "Feature",
  "properties": {
    "hierarchy": [
      "tgn:7200026",
      "tgn:7003669",
      "tgn:1000003",
      "tgn:7000084",
      "tgn:7029392"
    ],
    "placetype": [
      "aat:300008347"
    ],
    "id": 7200026,
    "name:xx": "Dürrnbuch"
  }
}
