{
  "geometry": {
    "type": "Point",
    "coordinates": [
      -116.3333,
      47.4333
    ]
  },
  "type": "Feature",
  "properties": {
    "hierarchy": [
      "tgn:2769651",
      "tgn:1000001",
      "tgn:7012149",
      "tgn:2000479",
      "tgn:7007250",
      "tgn:7029392"
    ],
    "placetype": [
      "aat:300008798"
    ],
    "id": 2769651,
    "name:xx": "Wiessner, Mount"
  }
}
