{
  "geometry": {
    "type": "Point",
    "coordinates": [
      -120.1167,
      34.4667
    ]
  },
  "type": "Feature",
  "properties": {
    "hierarchy": [
      "tgn:2405168",
      "tgn:1000001",
      "tgn:7012149",
      "tgn:7007157",
      "tgn:1002867",
      "tgn:7029392"
    ],
    "placetype": [
      "aat:300008761"
    ],
    "id": 2405168,
    "name:xx": "Huerta, Cañada De La"
  }
}
