{
  "type": "FeatureCollection",
  "features": [
    {
      "geometry": {
        "type": "Point",
        "coordinates": [
          -8.383333,
          43.366667
        ]
      },
      "type": "Feature",
      "properties": {
        "hierarchy": [
          "tgn:7330151",
          "tgn:7002824",
          "tgn:1000003",
          "tgn:7002786",
          "tgn:1000095",
          "tgn:7029392"
        ],
        "placetype": [
          "aat:300386846"
        ],
        "id": 7330151,
        "name:xx": "Hospital, Punta del"
      }
    },
    {
      "geometry": {
        "type": "Point",
        "coordinates": [
          -9.083333,
          42.983333
        ]
      },
      "type": "Feature",
      "properties": {
        "hierarchy": [
          "tgn:7330152",
          "tgn:7002824",
          "tgn:1000003",
          "tgn:7002786",
          "tgn:1000095",
          "tgn:7029392"
        ],
        "placetype": [
          "aat:300008347"
        ],
        "id": 7330152,
        "name:xx": "Hospital"
      }
    },
    {
      "geometry": {
        "type": "Point",
        "coordinates": [
          -7.1,
          42.7
        ]
      },
      "type": "Feature",
      "properties": {
        "hierarchy": [
          "tgn:7330153",
          "tgn:7002829",
          "tgn:1000003",
          "tgn:7002786",
          "tgn:1000095",
          "tgn:7029392"
        ],
        "placetype": [
          "aat:300008347"
        ],
        "id": 7330153,
        "name:xx": "Hospital"
      }
    },
    {
      "geometry": {
        "type": "Point",
        "coordinates": [
          -7.333333,
          42.65
        ]
      },
      "type": "Feature",
      "properties": {
        "hierarchy": [
          "tgn:7330154",
          "tgn:7002829",
          "tgn:1000003",
          "tgn:7002786",
          "tgn:1000095",
          "tgn:7029392"
        ],
        "placetype": [
          "aat:300008347"
        ],
        "id": 7330154,
        "name:xx": "Hospital"
      }
    },
    {
      "geometry": {
        "type": "Point",
        "coordinates": [
          0.160929,
          42.54723
        ]
      },
      "type": "Feature",
      "properties": {
        "hierarchy": [
          "tgn:7330155",
          "tgn:7002759",
          "tgn:7008909",
          "tgn:1000003",
          "tgn:1000095",
          "tgn:7029392"
        ],
        "placetype": [
          "aat:300008347"
        ],
        "id": 7330155,
        "name:xx": "Hospital"
      }
    },
    {
      "geometry": {
        "type": "Point",
        "coordinates": [
          -7.233333,
          42.466667
        ]
      },
      "type": "Feature",
      "properties": {
        "hierarchy": [
          "tgn:7330156",
          "tgn:7002829",
          "tgn:1000003",
          "tgn:7002786",
          "tgn:1000095",
          "tgn:7029392"
        ],
        "placetype": [
          "aat:300008347"
        ],
        "id": 7330156,
        "name:xx": "Hospital"
      }
    },
    {
      "geometry": {
        "type": "Point",
        "coordinates": [
          -14,
          28.433333
        ]
      },
      "type": "Feature",
      "properties": {
        "hierarchy": [
          "tgn:7330157",
          "tgn:7002825",
          "tgn:7016622",
          "tgn:1000003",
          "tgn:1000095",
          "tgn:7029392"
        ],
        "placetype": [
          "aat:300008347"
        ],
        "id": 7330157,
        "name:xx": "Hospinal"
      }
    },
    {
      "geometry": {
        "type": "Point",
        "coordinates": [
          -1.033333,
          39.4
        ]
      },
      "type": "Feature",
      "properties": {
        "hierarchy": [
          "tgn:7330158",
          "tgn:7001165",
          "tgn:1000003",
          "tgn:7002793",
          "tgn:1000095",
          "tgn:7029392"
        ],
        "placetype": [
          "aat:300008347"
        ],
        "id": 7330158,
        "name:xx": "Hortunas de Arriba"
      }
    },
    {
      "geometry": {
        "type": "Point",
        "coordinates": [
          -0.083333,
          40.383333
        ]
      },
      "type": "Feature",
      "properties": {
        "hierarchy": [
          "tgn:7330159",
          "tgn:7002815",
          "tgn:1000003",
          "tgn:7002793",
          "tgn:1000095",
          "tgn:7029392"
        ],
        "placetype": [
          "aat:300266554",
          "aat:300008699"
        ],
        "id": 7330159,
        "name:xx": "Horts, Barranco del"
      }
    }
  ]
}
