{
  "type": "FeatureCollection",
  "features": [
    {
      "geometry": {
        "type": "Point",
        "coordinates": [
          6.483333,
          51.9
        ]
      },
      "type": "Feature",
      "properties": {
        "hierarchy": [
          "tgn:7272800",
          "tgn:7003619",
          "tgn:1000003",
          "tgn:7016845",
          "tgn:7029392"
        ],
        "placetype": [
          "aat:300007836"
        ],
        "name:nl": "Vriezebrug",
        "id": 7272800
      }
    },
    {
      "geometry": {
        "type": "Point",
        "coordinates": [
          4.7,
          52.233333
        ]
      },
      "type": "Feature",
      "properties": {
        "hierarchy": [
          "tgn:7272801",
          "tgn:1000003",
          "tgn:7003632",
          "tgn:7016845",
          "tgn:7029392"
        ],
        "placetype": [
          "aat:300006163"
        ],
        "name:nl": "Vriesekoopsche Polder",
        "id": 7272801
      }
    },
    {
      "geometry": {
        "type": "Point",
        "coordinates": [
          7.116667,
          53.1
        ]
      },
      "type": "Feature",
      "properties": {
        "hierarchy": [
          "tgn:7272802",
          "tgn:1000003",
          "tgn:7003613",
          "tgn:7016845",
          "tgn:7029392"
        ],
        "placetype": [
          "aat:300387200"
        ],
        "name:nl": "Vrieschelooërvennen",
        "id": 7272802
      }
    },
    {
      "geometry": {
        "type": "Point",
        "coordinates": [
          7.116667,
          53.066667
        ]
      },
      "type": "Feature",
      "properties": {
        "hierarchy": [
          "tgn:7272803",
          "tgn:1000003",
          "tgn:7003613",
          "tgn:7016845",
          "tgn:7029392"
        ],
        "placetype": [
          "aat:300008347"
        ],
        "name:nl": "Vriescheloo",
        "id": 7272803
      }
    },
    {
      "geometry": {
        "type": "Point",
        "coordinates": [
          5.966667,
          50.916667
        ]
      },
      "type": "Feature",
      "properties": {
        "hierarchy": [
          "tgn:7272806",
          "tgn:1000003",
          "tgn:7003622",
          "tgn:7016845",
          "tgn:7029392"
        ],
        "placetype": [
          "aat:300000745"
        ],
        "name:nl": "Vrieheide",
        "id": 7272806
      }
    },
    {
      "geometry": {
        "type": "Point",
        "coordinates": [
          5.516667,
          51.55
        ]
      },
      "type": "Feature",
      "properties": {
        "hierarchy": [
          "tgn:7272807",
          "tgn:1000003",
          "tgn:7003624",
          "tgn:7016845",
          "tgn:7029392"
        ],
        "placetype": [
          "aat:300008863"
        ],
        "name:nl": "Vresselsebos",
        "id": 7272807
      }
    },
    {
      "geometry": {
        "type": "Point",
        "coordinates": [
          5.5,
          51.533333
        ]
      },
      "type": "Feature",
      "properties": {
        "hierarchy": [
          "tgn:7272808",
          "tgn:1000003",
          "tgn:7003624",
          "tgn:7016845",
          "tgn:7029392"
        ],
        "placetype": [
          "aat:300008347"
        ],
        "name:nl": "Vressel",
        "id": 7272808
      }
    },
    {
      "geometry": {
        "type": "Point",
        "coordinates": [
          4.516667,
          51.883333
        ]
      },
      "type": "Feature",
      "properties": {
        "hierarchy": [
          "tgn:7272809",
          "tgn:1000003",
          "tgn:7003632",
          "tgn:7016845",
          "tgn:7029392"
        ],
        "placetype": [
          "aat:300000745"
        ],
        "name:nl": "Vreewijk",
        "id": 7272809
      }
    }
  ]
}
