{
  "geometry": {
    "type": "Point",
    "coordinates": [
      39.25,
      47.0167
    ]
  },
  "type": "Feature",
  "properties": {
    "hierarchy": [
      "tgn:1055946",
      "tgn:1000004",
      "tgn:1003405",
      "tgn:7018214",
      "tgn:7002435",
      "tgn:7029392"
    ],
    "placetype": [
      "aat:300008347"
    ],
    "id": 1055946,
    "name:xx": "Krugloye"
  }
}
