{
  "geometry": {
    "type": "Point",
    "coordinates": [
      -123.5667,
      42.2667
    ]
  },
  "type": "Feature",
  "properties": {
    "hierarchy": [
      "tgn:2710141",
      "tgn:1000001",
      "tgn:7012149",
      "tgn:2001713",
      "tgn:7007708",
      "tgn:7029392"
    ],
    "placetype": [
      "aat:300006191"
    ],
    "id": 2710141,
    "name:xx": "Tall Timber Reservoir"
  }
}
