{
  "type": "FeatureCollection",
  "features": [
    {
      "geometry": {
        "type": "Point",
        "coordinates": [
          -67.7833,
          46.0833
        ]
      },
      "type": "Feature",
      "properties": {
        "hierarchy": [
          "tgn:2385510",
          "tgn:2000919",
          "tgn:1000001",
          "tgn:7012149",
          "tgn:7007515",
          "tgn:7029392"
        ],
        "placetype": [
          "aat:300008798"
        ],
        "id": 2385510,
        "name:xx": "Henderson Hill"
      }
    },
    {
      "geometry": {
        "type": "Point",
        "coordinates": [
          -115.3167,
          47.3667
        ]
      },
      "type": "Feature",
      "properties": {
        "hierarchy": [
          "tgn:2385511",
          "tgn:1000001",
          "tgn:7012149",
          "tgn:2001290",
          "tgn:7007524",
          "tgn:7029392"
        ],
        "placetype": [
          "aat:300008798"
        ],
        "id": 2385511,
        "name:xx": "Henderson Hill"
      }
    },
    {
      "geometry": {
        "type": "Point",
        "coordinates": [
          -77.6667,
          42.75
        ]
      },
      "type": "Feature",
      "properties": {
        "hierarchy": [
          "tgn:2385512",
          "tgn:1000001",
          "tgn:7012149",
          "tgn:1002604",
          "tgn:7007568",
          "tgn:7029392"
        ],
        "placetype": [
          "aat:300008798"
        ],
        "id": 2385512,
        "name:xx": "Henderson Hill"
      }
    },
    {
      "geometry": {
        "type": "Point",
        "coordinates": [
          -112.7833,
          37.7667
        ]
      },
      "type": "Feature",
      "properties": {
        "hierarchy": [
          "tgn:2385513",
          "tgn:1000001",
          "tgn:7012149",
          "tgn:2002111",
          "tgn:7007827",
          "tgn:7029392"
        ],
        "placetype": [
          "aat:300008798"
        ],
        "id": 2385513,
        "name:xx": "Henderson Hill"
      }
    },
    {
      "geometry": {
        "type": "Point",
        "coordinates": [
          -100.8,
          48.1833
        ]
      },
      "type": "Feature",
      "properties": {
        "hierarchy": [
          "tgn:2385514",
          "tgn:1000001",
          "tgn:2001581",
          "tgn:7012149",
          "tgn:7007705",
          "tgn:7029392"
        ],
        "placetype": [
          "aat:300386831"
        ],
        "id": 2385514,
        "name:xx": "Henderson Hills"
      }
    },
    {
      "geometry": {
        "type": "Point",
        "coordinates": [
          -91.6167,
          35.8167
        ]
      },
      "type": "Feature",
      "properties": {
        "hierarchy": [
          "tgn:2385515",
          "tgn:1000001",
          "tgn:7016172",
          "tgn:7012149",
          "tgn:2000136",
          "tgn:7029392"
        ],
        "placetype": [
          "aat:300008761"
        ],
        "id": 2385515,
        "name:xx": "Henderson Hollow"
      }
    },
    {
      "geometry": {
        "type": "Point",
        "coordinates": [
          -83.3833,
          38.3667
        ]
      },
      "type": "Feature",
      "properties": {
        "hierarchy": [
          "tgn:2385516",
          "tgn:1000001",
          "tgn:7012149",
          "tgn:1002591",
          "tgn:7007255",
          "tgn:7029392"
        ],
        "placetype": [
          "aat:300008761"
        ],
        "id": 2385516,
        "name:xx": "Henderson Hollow"
      }
    },
    {
      "geometry": {
        "type": "Point",
        "coordinates": [
          -93.4833,
          36.5
        ]
      },
      "type": "Feature",
      "properties": {
        "hierarchy": [
          "tgn:2385517",
          "tgn:1000001",
          "tgn:7012149",
          "tgn:2001249",
          "tgn:7007523",
          "tgn:7029392"
        ],
        "placetype": [
          "aat:300008761"
        ],
        "id": 2385517,
        "name:xx": "Henderson Hollow"
      }
    },
    {
      "geometry": {
        "type": "Point",
        "coordinates": [
          -90.6,
          37.25
        ]
      },
      "type": "Feature",
      "properties": {
        "hierarchy": [
          "tgn:2385518",
          "tgn:1000001",
          "tgn:7012149",
          "tgn:7007523",
          "tgn:7029392"
        ],
        "placetype": [
          "aat:300008761"
        ],
        "id": 2385518,
        "name:xx": "Henderson Hollow"
      }
    },
    {
      "geometry": {
        "type": "Point",
        "coordinates": [
          -121.2333,
          45.4
        ]
      },
      "type": "Feature",
      "properties": {
        "hierarchy": [
          "tgn:2385519",
          "tgn:1000001",
          "tgn:7012149",
          "tgn:1002990",
          "tgn:7007708",
          "tgn:7029392"
        ],
        "placetype": [
          "aat:300008761"
        ],
        "id": 2385519,
        "name:xx": "Henderson Hollow"
      }
    }
  ]
}
