{
  "geometry": {
    "type": "Point",
    "coordinates": [
      -106.0167,
      45.6333
    ]
  },
  "type": "Feature",
  "properties": {
    "hierarchy": [
      "tgn:2276021",
      "tgn:1000001",
      "tgn:7012149",
      "tgn:2001297",
      "tgn:7007524",
      "tgn:7029392"
    ],
    "placetype": [
      "aat:300008761"
    ],
    "id": 2276021,
    "name:xx": "Darling Draw"
  }
}
