{
  "geometry": {
    "type": "Point",
    "coordinates": [
      -102.6667,
      35.5667
    ]
  },
  "type": "Feature",
  "properties": {
    "hierarchy": [
      "tgn:2573788",
      "tgn:1000001",
      "tgn:7012149",
      "tgn:2002051",
      "tgn:7007826",
      "tgn:7029392"
    ],
    "placetype": [
      "aat:300008697"
    ],
    "id": 2573788,
    "name:xx": "Pedarosa Spring"
  }
}
