{
  "geometry": {
    "type": "Point",
    "coordinates": [
      -110.6333,
      47.35
    ]
  },
  "type": "Feature",
  "properties": {
    "hierarchy": [
      "tgn:2772650",
      "tgn:1000001",
      "tgn:7012149",
      "tgn:7007524",
      "tgn:7029392"
    ],
    "placetype": [
      "aat:300008706"
    ],
    "id": 2772650,
    "name:xx": "Williams Creek"
  }
}
