{
  "geometry": {
    "type": "Point",
    "coordinates": [
      -86.9167,
      34.95
    ]
  },
  "type": "Feature",
  "properties": {
    "hierarchy": [
      "tgn:2781188",
      "tgn:7002659",
      "tgn:1000001",
      "tgn:7012149",
      "tgn:2000041",
      "tgn:7029392"
    ],
    "placetype": [
      "aat:300008347"
    ],
    "id": 2781188,
    "name:xx": "Woodfin Mill"
  }
}
