{
  "type": "FeatureCollection",
  "features": [
    {
      "geometry": {
        "type": "Point",
        "coordinates": [
          4.837853,
          50.673447
        ]
      },
      "type": "Feature",
      "properties": {
        "hierarchy": [
          "tgn:7254561",
          "tgn:7003466",
          "tgn:1000003",
          "tgn:1000063",
          "tgn:4012014",
          "tgn:7029392"
        ],
        "placetype": [
          "aat:300008347"
        ],
        "id": 7254561,
        "name:xx": "Thorembisoul"
      }
    },
    {
      "geometry": {
        "type": "Point",
        "coordinates": [
          4.784063,
          50.634854
        ]
      },
      "type": "Feature",
      "properties": {
        "hierarchy": [
          "tgn:7254562",
          "tgn:7018238",
          "tgn:1000003",
          "tgn:1000063",
          "tgn:4012014",
          "tgn:7029392"
        ],
        "placetype": [
          "aat:300008347"
        ],
        "id": 7254562,
        "name:xx": "Thorembais-Saint-Trond"
      }
    },
    {
      "geometry": {
        "type": "Point",
        "coordinates": [
          4.215085,
          51.073644
        ]
      },
      "type": "Feature",
      "properties": {
        "hierarchy": [
          "tgn:7254566",
          "tgn:7003456",
          "tgn:1000003",
          "tgn:1000063",
          "tgn:7018236",
          "tgn:7029392"
        ],
        "placetype": [
          "aat:300008347"
        ],
        "id": 7254566,
        "name:xx": "'t Hoogste"
      }
    },
    {
      "geometry": {
        "type": "Point",
        "coordinates": [
          3.874745,
          51.08341
        ]
      },
      "type": "Feature",
      "properties": {
        "hierarchy": [
          "tgn:7254567",
          "tgn:7003457",
          "tgn:1000003",
          "tgn:1000063",
          "tgn:7018236",
          "tgn:7029392"
        ],
        "placetype": [
          "aat:300005567"
        ],
        "id": 7254567,
        "name:xx": "'t Hooghof"
      }
    },
    {
      "geometry": {
        "type": "Point",
        "coordinates": [
          5.0125,
          50.464177
        ]
      },
      "type": "Feature",
      "properties": {
        "hierarchy": [
          "tgn:7254568",
          "tgn:7003466",
          "tgn:1000003",
          "tgn:1000063",
          "tgn:4012014",
          "tgn:7029392"
        ],
        "placetype": [
          "aat:300008347"
        ],
        "id": 7254568,
        "name:xx": "Thon"
      }
    }
  ]
}
