{
  "type": "FeatureCollection",
  "features": [
    {
      "geometry": {
        "type": "Point",
        "coordinates": [
          16.95,
          -3.0333
        ]
      },
      "type": "Feature",
      "properties": {
        "hierarchy": [
          "tgn:7016700",
          "tgn:7001242",
          "tgn:7029392"
        ],
        "placetype": [
          "aat:300008707"
        ],
        "id": 7016700,
        "name:xx": "Kasai"
      }
    },
    {
      "geometry": {
        "type": "Point",
        "coordinates": [
          100.666667,
          6
        ]
      },
      "type": "Feature",
      "properties": {
        "hierarchy": [
          "tgn:7016702",
          "tgn:7000317",
          "tgn:1000004",
          "tgn:1000128",
          "tgn:7029392"
        ],
        "placetype": [
          "aat:300387145",
          "aat:300000776"
        ],
        "id": 7016702,
        "name:xx": "Kedah"
      }
    },
    {
      "geometry": {
        "type": "Point",
        "coordinates": [
          70.5,
          21.966
        ]
      },
      "type": "Feature",
      "properties": {
        "hierarchy": [
          "tgn:7016703",
          "tgn:1000004",
          "tgn:1001869",
          "tgn:7000198",
          "tgn:7029392"
        ],
        "placetype": [
          "aat:300008804"
        ],
        "name:en": "Kāthiāwār Peninsula",
        "id": 7016703
      }
    },
    {
      "geometry": {
        "type": "Point",
        "coordinates": [
          112.0167,
          -7.75
        ]
      },
      "type": "Feature",
      "properties": {
        "hierarchy": [
          "tgn:7016704",
          "tgn:1000004",
          "tgn:1001323",
          "tgn:1000116",
          "tgn:7029392"
        ],
        "placetype": [
          "aat:300008347"
        ],
        "id": 7016704,
        "name:xx": "Kediri"
      }
    },
    {
      "geometry": {
        "type": "Point",
        "coordinates": [
          101.6667,
          0.85
        ]
      },
      "type": "Feature",
      "properties": {
        "hierarchy": [
          "tgn:7016705",
          "tgn:1000004",
          "tgn:1001502",
          "tgn:1000116",
          "tgn:7029392"
        ],
        "placetype": [
          "aat:300008347"
        ],
        "id": 7016705,
        "name:xx": "Kelantan"
      }
    },
    {
      "geometry": {
        "type": "Point",
        "coordinates": [
          26,
          -9
        ]
      },
      "type": "Feature",
      "properties": {
        "hierarchy": [
          "tgn:7016706",
          "tgn:7001242",
          "tgn:1000159",
          "tgn:7029392"
        ],
        "placetype": [
          "aat:300387064",
          "aat:300000774"
        ],
        "id": 7016706,
        "name:xx": "Katanga"
      }
    },
    {
      "geometry": {
        "type": "Point",
        "coordinates": [
          28,
          -2.5
        ]
      },
      "type": "Feature",
      "properties": {
        "hierarchy": [
          "tgn:7016707",
          "tgn:7001242",
          "tgn:1000159",
          "tgn:7029392"
        ],
        "placetype": [
          "aat:300387064",
          "aat:300386698",
          "aat:300387173"
        ],
        "id": 7016707,
        "name:xx": "lost & found/former Kivu, Région du"
      }
    },
    {
      "geometry": {
        "type": "Point",
        "coordinates": [
          12.4,
          -6.0667
        ]
      },
      "type": "Feature",
      "properties": {
        "hierarchy": [
          "tgn:7016708",
          "tgn:7001242",
          "tgn:7029392"
        ],
        "placetype": [
          "aat:300008707"
        ],
        "name:en": "Congo River",
        "id": 7016708
      }
    },
    {
      "geometry": {
        "type": "Point",
        "coordinates": [
          37.2167,
          50.8333
        ]
      },
      "type": "Feature",
      "properties": {
        "hierarchy": [
          "tgn:7016709",
          "tgn:6000729",
          "tgn:1000004",
          "tgn:7018214",
          "tgn:7002435",
          "tgn:7029392"
        ],
        "placetype": [
          "aat:300008347"
        ],
        "id": 7016709,
        "name:xx": "Korocha"
      }
    }
  ]
}
