{
  "geometry": {
    "type": "Point",
    "coordinates": [
      -116.5167,
      46.1667
    ]
  },
  "type": "Feature",
  "properties": {
    "hierarchy": [
      "tgn:2248907",
      "tgn:1000001",
      "tgn:7012149",
      "tgn:2000482",
      "tgn:7007250",
      "tgn:7029392"
    ],
    "placetype": [
      "aat:300008761"
    ],
    "id": 2248907,
    "name:xx": "Coldsprings Canyon"
  }
}
