{
  "type": "FeatureCollection",
  "features": [
    {
      "geometry": {
        "type": "Point",
        "coordinates": [
          -104.4667,
          29.95
        ]
      },
      "type": "Feature",
      "properties": {
        "hierarchy": [
          "tgn:1104221",
          "tgn:1000001",
          "tgn:7012149",
          "tgn:2002057",
          "tgn:7007826",
          "tgn:7029392"
        ],
        "placetype": [
          "aat:300008795"
        ],
        "id": 1104221,
        "name:xx": "Chinati Peak"
      }
    },
    {
      "geometry": {
        "type": "Point",
        "coordinates": [
          35.7333,
          -16.5
        ]
      },
      "type": "Feature",
      "properties": {
        "hierarchy": [
          "tgn:1104222",
          "tgn:7001242",
          "tgn:1000955",
          "tgn:1000180",
          "tgn:7029392"
        ],
        "placetype": [
          "aat:300008795"
        ],
        "id": 1104222,
        "name:xx": "Chiperone"
      }
    },
    {
      "geometry": {
        "type": "Point",
        "coordinates": [
          -83.5,
          9.4833
        ]
      },
      "type": "Feature",
      "properties": {
        "hierarchy": [
          "tgn:1104223",
          "tgn:1001391",
          "tgn:1000001",
          "tgn:7005364",
          "tgn:7029392"
        ],
        "placetype": [
          "aat:300008795"
        ],
        "id": 1104223,
        "name:xx": "Chirripó, Cerro"
      }
    },
    {
      "geometry": {
        "type": "Point",
        "coordinates": [
          86.6667,
          28.1
        ]
      },
      "type": "Feature",
      "properties": {
        "hierarchy": [
          "tgn:1104225",
          "tgn:1000004",
          "tgn:7029392"
        ],
        "placetype": [
          "aat:300008795"
        ],
        "id": 1104225,
        "name:xx": "Cho Oyu"
      }
    },
    {
      "geometry": {
        "type": "Point",
        "coordinates": [
          88.5167,
          28.0167
        ]
      },
      "type": "Feature",
      "properties": {
        "hierarchy": [
          "tgn:1104227",
          "tgn:1000004",
          "tgn:7029392"
        ],
        "placetype": [
          "aat:300008795"
        ],
        "id": 1104227,
        "name:xx": "Chomiomo"
      }
    },
    {
      "geometry": {
        "type": "Point",
        "coordinates": [
          89.2667,
          27.8333
        ]
      },
      "type": "Feature",
      "properties": {
        "hierarchy": [
          "tgn:1104228",
          "tgn:1000004",
          "tgn:7029392"
        ],
        "placetype": [
          "aat:300008795"
        ],
        "id": 1104228,
        "name:xx": "Cho-mo-la-li Shan"
      }
    },
    {
      "geometry": {
        "type": "Point",
        "coordinates": [
          -3.983333,
          56.45
        ]
      },
      "type": "Feature",
      "properties": {
        "hierarchy": [
          "tgn:1104229",
          "tgn:7002444",
          "tgn:1000003",
          "tgn:7019152",
          "tgn:7008591",
          "tgn:7029392"
        ],
        "placetype": [
          "aat:300008795"
        ],
        "name:en": "Chonzie, Ben",
        "id": 1104229
      }
    }
  ]
}
