{
  "geometry": {
    "type": "Point",
    "coordinates": [
      -80.5833,
      38.65
    ]
  },
  "type": "Feature",
  "properties": {
    "hierarchy": [
      "tgn:2565963",
      "tgn:1000001",
      "tgn:2002256",
      "tgn:7012149",
      "tgn:7013961",
      "tgn:7029392"
    ],
    "placetype": [
      "aat:300008347"
    ],
    "id": 2565963,
    "name:xx": "Palmer"
  }
}
