{
  "geometry": {
    "type": "Point",
    "coordinates": [
      21.6167,
      32.75
    ]
  },
  "type": "Feature",
  "properties": {
    "hierarchy": [
      "tgn:7023996",
      "tgn:7000606",
      "tgn:7001242",
      "tgn:1000172",
      "tgn:7029392"
    ],
    "placetype": [
      "aat:300008347",
      "aat:300000810"
    ],
    "id": 7023996,
    "name:xx": "Massah"
  }
}
