{
  "geometry": {
    "type": "Point",
    "coordinates": [
      -116.3667,
      47.1333
    ]
  },
  "type": "Feature",
  "properties": {
    "hierarchy": [
      "tgn:2623537",
      "tgn:2000456",
      "tgn:1000001",
      "tgn:7012149",
      "tgn:7007250",
      "tgn:7029392"
    ],
    "placetype": [
      "aat:300008706"
    ],
    "id": 2623537,
    "name:xx": "Rock Creek"
  }
}
