{
  "type": "FeatureCollection",
  "features": [
    {
      "geometry": {
        "type": "Point",
        "coordinates": [
          -87.8833,
          42.2833
        ]
      },
      "type": "Feature",
      "properties": {
        "hierarchy": [
          "tgn:2028603",
          "tgn:1000001",
          "tgn:7012149",
          "tgn:7013855",
          "tgn:7007251",
          "tgn:7029392"
        ],
        "placetype": [
          "aat:300008347"
        ],
        "id": 2028603,
        "name:xx": "Knollwood"
      }
    },
    {
      "geometry": {
        "type": "Point",
        "coordinates": [
          -90.2833,
          40.9
        ]
      },
      "type": "Feature",
      "properties": {
        "hierarchy": [
          "tgn:2028604",
          "tgn:1000001",
          "tgn:7012149",
          "tgn:2000516",
          "tgn:7007251",
          "tgn:7029392"
        ],
        "placetype": [
          "aat:300008347"
        ],
        "id": 2028604,
        "name:xx": "Knoxville"
      }
    },
    {
      "geometry": {
        "type": "Point",
        "coordinates": [
          -88.5667,
          40.2833
        ]
      },
      "type": "Feature",
      "properties": {
        "hierarchy": [
          "tgn:2028608",
          "tgn:1000001",
          "tgn:7012149",
          "tgn:7019015",
          "tgn:7007251",
          "tgn:7029392"
        ],
        "placetype": [
          "aat:300387016"
        ],
        "id": 2028608,
        "name:xx": "Kumler"
      }
    },
    {
      "geometry": {
        "type": "Point",
        "coordinates": [
          -88.7,
          38.8667
        ]
      },
      "type": "Feature",
      "properties": {
        "hierarchy": [
          "tgn:2028609",
          "tgn:1000001",
          "tgn:1002369",
          "tgn:7012149",
          "tgn:7007251",
          "tgn:7029392"
        ],
        "placetype": [
          "aat:300008347"
        ],
        "id": 2028609,
        "name:xx": "La Clede"
      }
    }
  ]
}
