{
  "type": "FeatureCollection",
  "features": [
    {
      "geometry": {
        "type": "Point",
        "coordinates": [
          6.2,
          49.5
        ]
      },
      "type": "Feature",
      "properties": {
        "hierarchy": [
          "tgn:1031672",
          "tgn:1000003",
          "tgn:7002888",
          "tgn:1000070",
          "tgn:7029392"
        ],
        "placetype": [
          "aat:300008347"
        ],
        "id": 1031672,
        "name:xx": "Évrange"
      }
    },
    {
      "geometry": {
        "type": "Point",
        "coordinates": [
          2.6333,
          48.65
        ]
      },
      "type": "Feature",
      "properties": {
        "hierarchy": [
          "tgn:1031675",
          "tgn:1000003",
          "tgn:7002883",
          "tgn:1000070",
          "tgn:7029392"
        ],
        "placetype": [
          "aat:300008347"
        ],
        "id": 1031675,
        "name:xx": "Évry-les-Châteaux"
      }
    },
    {
      "geometry": {
        "type": "Point",
        "coordinates": [
          2.3667,
          49.0333
        ]
      },
      "type": "Feature",
      "properties": {
        "hierarchy": [
          "tgn:1031676",
          "tgn:1000003",
          "tgn:7002883",
          "tgn:1000070",
          "tgn:7029392"
        ],
        "placetype": [
          "aat:300008347"
        ],
        "id": 1031676,
        "name:xx": "Ézanville"
      }
    },
    {
      "geometry": {
        "type": "Point",
        "coordinates": [
          1.4167,
          48.8667
        ]
      },
      "type": "Feature",
      "properties": {
        "hierarchy": [
          "tgn:1031677",
          "tgn:1000003",
          "tgn:7002882",
          "tgn:1000070",
          "tgn:7029392"
        ],
        "placetype": [
          "aat:300008347"
        ],
        "id": 1031677,
        "name:xx": "Ézy-sur-Eure"
      }
    },
    {
      "geometry": {
        "type": "Point",
        "coordinates": [
          2.7,
          49.0833
        ]
      },
      "type": "Feature",
      "properties": {
        "hierarchy": [
          "tgn:1031678",
          "tgn:1000003",
          "tgn:7002890",
          "tgn:1000070",
          "tgn:7029392"
        ],
        "placetype": [
          "aat:300008347"
        ],
        "id": 1031678,
        "name:xx": "Ève"
      }
    },
    {
      "geometry": {
        "type": "Point",
        "coordinates": [
          6.3333,
          47.2667
        ]
      },
      "type": "Feature",
      "properties": {
        "hierarchy": [
          "tgn:1031679",
          "tgn:1000003",
          "tgn:7002881",
          "tgn:1000070",
          "tgn:7029392"
        ],
        "placetype": [
          "aat:300008347"
        ],
        "id": 1031679,
        "name:xx": "Aïssey"
      }
    }
  ]
}
