{
  "geometry": {
    "type": "Point",
    "coordinates": [
      27.6833,
      -27.1333
    ]
  },
  "type": "Feature",
  "properties": {
    "hierarchy": [
      "tgn:1093119",
      "tgn:7001242",
      "tgn:7016562",
      "tgn:1000193",
      "tgn:7029392"
    ],
    "placetype": [
      "aat:300008347"
    ],
    "id": 1093119,
    "name:xx": "Greenlands"
  }
}
