{
  "type": "FeatureCollection",
  "features": [
    {
      "geometry": {
        "type": "Point",
        "coordinates": [
          -47.2667,
          -19.3833
        ]
      },
      "type": "Feature",
      "properties": {
        "hierarchy": [
          "tgn:1022430",
          "tgn:7006237",
          "tgn:1000047",
          "tgn:7002457",
          "tgn:1000002",
          "tgn:7029392"
        ],
        "placetype": [
          "aat:300008347"
        ],
        "id": 1022430,
        "name:xx": "Perdizes"
      }
    },
    {
      "geometry": {
        "type": "Point",
        "coordinates": [
          -51.1167,
          -20.65
        ]
      },
      "type": "Feature",
      "properties": {
        "hierarchy": [
          "tgn:1022431",
          "tgn:1001945",
          "tgn:1000047",
          "tgn:7002457",
          "tgn:1000002",
          "tgn:7029392"
        ],
        "placetype": [
          "aat:300008347"
        ],
        "id": 1022431,
        "name:xx": "Pereira Barreto"
      }
    },
    {
      "geometry": {
        "type": "Point",
        "coordinates": [
          -46.4,
          -22.7
        ]
      },
      "type": "Feature",
      "properties": {
        "hierarchy": [
          "tgn:1022432",
          "tgn:7006237",
          "tgn:1000047",
          "tgn:7002457",
          "tgn:1000002",
          "tgn:7029392"
        ],
        "placetype": [
          "aat:300008347"
        ],
        "id": 1022432,
        "name:xx": "Pereiras"
      }
    },
    {
      "geometry": {
        "type": "Point",
        "coordinates": [
          -38.5,
          -5.9833
        ]
      },
      "type": "Feature",
      "properties": {
        "hierarchy": [
          "tgn:1022433",
          "tgn:7006064",
          "tgn:1000047",
          "tgn:7002455",
          "tgn:1000002",
          "tgn:7029392"
        ],
        "placetype": [
          "aat:300008347"
        ],
        "id": 1022433,
        "name:xx": "Pereiro"
      }
    },
    {
      "geometry": {
        "type": "Point",
        "coordinates": [
          -44.9,
          -2.6333
        ]
      },
      "type": "Feature",
      "properties": {
        "hierarchy": [
          "tgn:1022434",
          "tgn:7006246",
          "tgn:1000047",
          "tgn:7002455",
          "tgn:1000002",
          "tgn:7029392"
        ],
        "placetype": [
          "aat:300008347"
        ],
        "id": 1022434,
        "name:xx": "Peri-Mirim"
      }
    },
    {
      "geometry": {
        "type": "Point",
        "coordinates": [
          -44.2833,
          -4.25
        ]
      },
      "type": "Feature",
      "properties": {
        "hierarchy": [
          "tgn:1022435",
          "tgn:7006246",
          "tgn:1000047",
          "tgn:7002455",
          "tgn:1000002",
          "tgn:7029392"
        ],
        "placetype": [
          "aat:300008347"
        ],
        "id": 1022435,
        "name:xx": "Peritoró"
      }
    },
    {
      "geometry": {
        "type": "Point",
        "coordinates": [
          -47,
          -24.3167
        ]
      },
      "type": "Feature",
      "properties": {
        "hierarchy": [
          "tgn:1022436",
          "tgn:1001945",
          "tgn:1000047",
          "tgn:7002457",
          "tgn:1000002",
          "tgn:7029392"
        ],
        "placetype": [
          "aat:300008347"
        ],
        "id": 1022436,
        "name:xx": "Peruíbe"
      }
    },
    {
      "geometry": {
        "type": "Point",
        "coordinates": [
          -36.6333,
          -8.4
        ]
      },
      "type": "Feature",
      "properties": {
        "hierarchy": [
          "tgn:1022437",
          "tgn:7005437",
          "tgn:1000047",
          "tgn:7002455",
          "tgn:1000002",
          "tgn:7029392"
        ],
        "placetype": [
          "aat:300008347"
        ],
        "id": 1022437,
        "name:xx": "Pesqueira"
      }
    },
    {
      "geometry": {
        "type": "Point",
        "coordinates": [
          -38.25,
          -9
        ]
      },
      "type": "Feature",
      "properties": {
        "hierarchy": [
          "tgn:1022439",
          "tgn:7005437",
          "tgn:1000047",
          "tgn:7002455",
          "tgn:1000002",
          "tgn:7029392"
        ],
        "placetype": [
          "aat:300008347"
        ],
        "id": 1022439,
        "name:xx": "Petrolândia"
      }
    }
  ]
}
