{
  "geometry": {
    "type": "Point",
    "coordinates": [
      -15.5833,
      12.2667
    ]
  },
  "type": "Feature",
  "properties": {
    "hierarchy": [
      "tgn:1092320",
      "tgn:7001242",
      "tgn:7014990",
      "tgn:1000183",
      "tgn:7029392"
    ],
    "placetype": [
      "aat:300008347"
    ],
    "id": 1092320,
    "name:xx": "Bissorã"
  }
}
