{
  "type": "FeatureCollection",
  "features": [
    {
      "geometry": {
        "type": "Point",
        "coordinates": [
          -92.4,
          46.0833
        ]
      },
      "type": "Feature",
      "properties": {
        "hierarchy": [
          "tgn:2381540",
          "tgn:1000001",
          "tgn:7012149",
          "tgn:2001056",
          "tgn:7007521",
          "tgn:7029392"
        ],
        "placetype": [
          "aat:300008680"
        ],
        "id": 2381540,
        "name:xx": "Hay Creek Flowage"
      }
    },
    {
      "geometry": {
        "type": "Point",
        "coordinates": [
          -92.6667,
          45.8
        ]
      },
      "type": "Feature",
      "properties": {
        "hierarchy": [
          "tgn:2381541",
          "tgn:1000001",
          "tgn:2002311",
          "tgn:7012149",
          "tgn:7007922",
          "tgn:7029392"
        ],
        "placetype": [
          "aat:300008680"
        ],
        "id": 2381541,
        "name:xx": "Hay Creek Flowage"
      }
    },
    {
      "geometry": {
        "type": "Point",
        "coordinates": [
          -90.25,
          46
        ]
      },
      "type": "Feature",
      "properties": {
        "hierarchy": [
          "tgn:2381542",
          "tgn:1000001",
          "tgn:7012149",
          "tgn:2002327",
          "tgn:7007922",
          "tgn:7029392"
        ],
        "placetype": [
          "aat:300006191"
        ],
        "id": 2381542,
        "name:xx": "Hay Creek Flowage"
      }
    },
    {
      "geometry": {
        "type": "Point",
        "coordinates": [
          -90.8167,
          44.7
        ]
      },
      "type": "Feature",
      "properties": {
        "hierarchy": [
          "tgn:2381543",
          "tgn:1000001",
          "tgn:2002314",
          "tgn:7012149",
          "tgn:7007922",
          "tgn:7029392"
        ],
        "placetype": [
          "aat:300008798"
        ],
        "id": 2381543,
        "name:xx": "Hay Creek Mound"
      }
    },
    {
      "geometry": {
        "type": "Point",
        "coordinates": [
          -120.9333,
          44.6167
        ]
      },
      "type": "Feature",
      "properties": {
        "hierarchy": [
          "tgn:2381544",
          "tgn:1000001",
          "tgn:7012149",
          "tgn:2001712",
          "tgn:7007708",
          "tgn:7029392"
        ],
        "placetype": [
          "aat:300008347"
        ],
        "id": 2381544,
        "name:xx": "Hay Creek Ranch"
      }
    },
    {
      "geometry": {
        "type": "Point",
        "coordinates": [
          -106.7,
          46.45
        ]
      },
      "type": "Feature",
      "properties": {
        "hierarchy": [
          "tgn:2381545",
          "tgn:1000001",
          "tgn:2001268",
          "tgn:7012149",
          "tgn:7007524",
          "tgn:7029392"
        ],
        "placetype": [
          "aat:300006191"
        ],
        "id": 2381545,
        "name:xx": "Hay Creek Reservoir"
      }
    },
    {
      "geometry": {
        "type": "Point",
        "coordinates": [
          -109.2833,
          42.0833
        ]
      },
      "type": "Feature",
      "properties": {
        "hierarchy": [
          "tgn:2381547",
          "tgn:1000001",
          "tgn:7012149",
          "tgn:2002383",
          "tgn:7007923",
          "tgn:7029392"
        ],
        "placetype": [
          "aat:300006075"
        ],
        "id": 2381547,
        "name:xx": "Hay Ditch"
      }
    },
    {
      "geometry": {
        "type": "Point",
        "coordinates": [
          -84.3833,
          43.8833
        ]
      },
      "type": "Feature",
      "properties": {
        "hierarchy": [
          "tgn:2381548",
          "tgn:1000001",
          "tgn:7012149",
          "tgn:2000959",
          "tgn:7007520",
          "tgn:7029392"
        ],
        "placetype": [
          "aat:300006075"
        ],
        "id": 2381548,
        "name:xx": "Hay Drain"
      }
    },
    {
      "geometry": {
        "type": "Point",
        "coordinates": [
          -104.9167,
          45.4333
        ]
      },
      "type": "Feature",
      "properties": {
        "hierarchy": [
          "tgn:2381549",
          "tgn:1000001",
          "tgn:2001265",
          "tgn:7012149",
          "tgn:7007524",
          "tgn:7029392"
        ],
        "placetype": [
          "aat:300008761"
        ],
        "id": 2381549,
        "name:xx": "Hay Draw"
      }
    }
  ]
}
