{
  "geometry": {
    "type": "Point",
    "coordinates": [
      -90.85,
      48.1833
    ]
  },
  "type": "Feature",
  "properties": {
    "hierarchy": [
      "tgn:2597816",
      "tgn:1000001",
      "tgn:2001014",
      "tgn:7012149",
      "tgn:7007521",
      "tgn:7029392"
    ],
    "placetype": [
      "aat:300008680"
    ],
    "id": 2597816,
    "name:xx": "Prayer Lake"
  }
}
