{
  "geometry": {
    "type": "Point",
    "coordinates": [
      -111.4667,
      41.8167
    ]
  },
  "type": "Feature",
  "properties": {
    "hierarchy": [
      "tgn:2464495",
      "tgn:1000001",
      "tgn:7012149",
      "tgn:7007827",
      "tgn:7029392"
    ],
    "placetype": [
      "aat:300266640"
    ],
    "id": 2464495,
    "name:xx": "Log Cabin Ridge"
  }
}
