{
  "geometry": {
    "type": "Point",
    "coordinates": [
      105.2167,
      11.6667
    ]
  },
  "type": "Feature",
  "properties": {
    "hierarchy": [
      "tgn:1066434",
      "tgn:1000004",
      "tgn:7000828",
      "tgn:1000109",
      "tgn:7029392"
    ],
    "placetype": [
      "aat:300008347"
    ],
    "id": 1066434,
    "name:xx": "Snay Pól"
  }
}
