{
  "geometry": {
    "type": "Point",
    "coordinates": [
      97.15,
      5.15
    ]
  },
  "type": "Feature",
  "properties": {
    "hierarchy": [
      "tgn:1078006",
      "tgn:7016479",
      "tgn:1000004",
      "tgn:1000116",
      "tgn:7029392"
    ],
    "placetype": [
      "aat:300008347"
    ],
    "id": 1078006,
    "name:xx": "Lhokseumawe"
  }
}
