{
  "geometry": {
    "type": "Point",
    "coordinates": [
      -83.2167,
      35.2333
    ]
  },
  "type": "Feature",
  "properties": {
    "hierarchy": [
      "tgn:2526357",
      "tgn:1000001",
      "tgn:7012149",
      "tgn:7007709",
      "tgn:7029392"
    ],
    "placetype": [
      "aat:300008798"
    ],
    "id": 2526357,
    "name:xx": "Moss Knob"
  }
}
