{
  "geometry": {
    "type": "Point",
    "coordinates": [
      -90.7667,
      32.0667
    ]
  },
  "type": "Feature",
  "properties": {
    "hierarchy": [
      "tgn:2563102",
      "tgn:1000001",
      "tgn:2001096",
      "tgn:7012149",
      "tgn:7007522",
      "tgn:7029392"
    ],
    "placetype": [
      "aat:300008706"
    ],
    "id": 2563102,
    "name:xx": "Owens Creek"
  }
}
