{
  "type": "FeatureCollection",
  "features": [
    {
      "geometry": {
        "type": "Point",
        "coordinates": [
          151.6667,
          -32.95
        ]
      },
      "type": "Feature",
      "properties": {
        "hierarchy": [
          "tgn:1096531",
          "tgn:7000490",
          "tgn:1000006",
          "tgn:7001828",
          "tgn:7029392"
        ],
        "placetype": [
          "aat:300008347"
        ],
        "id": 1096531,
        "name:xx": "Charlestown"
      }
    },
    {
      "geometry": {
        "type": "Point",
        "coordinates": [
          143.45,
          -36.3
        ]
      },
      "type": "Feature",
      "properties": {
        "hierarchy": [
          "tgn:1096533",
          "tgn:7000490",
          "tgn:1000006",
          "tgn:7006238",
          "tgn:7029392"
        ],
        "placetype": [
          "aat:300008347"
        ],
        "id": 1096533,
        "name:xx": "Charlton"
      }
    },
    {
      "geometry": {
        "type": "Point",
        "coordinates": [
          146.3333,
          -20.0333
        ]
      },
      "type": "Feature",
      "properties": {
        "hierarchy": [
          "tgn:1096534",
          "tgn:7000490",
          "tgn:1000006",
          "tgn:7001830",
          "tgn:7029392"
        ],
        "placetype": [
          "aat:300008347"
        ],
        "id": 1096534,
        "name:xx": "Charters Towers"
      }
    },
    {
      "geometry": {
        "type": "Point",
        "coordinates": [
          151.2,
          -33.8
        ]
      },
      "type": "Feature",
      "properties": {
        "hierarchy": [
          "tgn:1096535",
          "tgn:7000490",
          "tgn:1000006",
          "tgn:7001828",
          "tgn:7029392"
        ],
        "placetype": [
          "aat:300008347"
        ],
        "id": 1096535,
        "name:xx": "Chatswood"
      }
    },
    {
      "geometry": {
        "type": "Point",
        "coordinates": [
          140.25,
          -20
        ]
      },
      "type": "Feature",
      "properties": {
        "hierarchy": [
          "tgn:1096536",
          "tgn:7000490",
          "tgn:1000006",
          "tgn:7001830",
          "tgn:7029392"
        ],
        "placetype": [
          "aat:300008347"
        ],
        "id": 1096536,
        "name:xx": "Chatsworth"
      }
    },
    {
      "geometry": {
        "type": "Point",
        "coordinates": [
          145,
          -26.6
        ]
      },
      "type": "Feature",
      "properties": {
        "hierarchy": [
          "tgn:1096537",
          "tgn:7000490",
          "tgn:1000006",
          "tgn:7001830",
          "tgn:7029392"
        ],
        "placetype": [
          "aat:300008347"
        ],
        "id": 1096537,
        "name:xx": "Cheepie"
      }
    },
    {
      "geometry": {
        "type": "Point",
        "coordinates": [
          145.1167,
          -38.05
        ]
      },
      "type": "Feature",
      "properties": {
        "hierarchy": [
          "tgn:1096538",
          "tgn:7000490",
          "tgn:1000006",
          "tgn:7006238",
          "tgn:7029392"
        ],
        "placetype": [
          "aat:300008347"
        ],
        "id": 1096538,
        "name:xx": "Chelsea"
      }
    },
    {
      "geometry": {
        "type": "Point",
        "coordinates": [
          151.0833,
          -33.7667
        ]
      },
      "type": "Feature",
      "properties": {
        "hierarchy": [
          "tgn:1096539",
          "tgn:7000490",
          "tgn:1000006",
          "tgn:7001828",
          "tgn:7029392"
        ],
        "placetype": [
          "aat:300008347"
        ],
        "id": 1096539,
        "name:xx": "Cheltenham"
      }
    }
  ]
}
