{
  "geometry": {
    "type": "Point",
    "coordinates": [
      -74.4167,
      41.1167
    ]
  },
  "type": "Feature",
  "properties": {
    "hierarchy": [
      "tgn:2741777",
      "tgn:1000001",
      "tgn:1002775",
      "tgn:7012149",
      "tgn:7007565",
      "tgn:7029392"
    ],
    "placetype": [
      "aat:300008347"
    ],
    "id": 2741777,
    "name:xx": "Uttertown"
  }
}
