{
  "geometry": {
    "type": "Point",
    "coordinates": [
      -144.2667,
      60.3333
    ]
  },
  "type": "Feature",
  "properties": {
    "hierarchy": [
      "tgn:2322601",
      "tgn:7006450",
      "tgn:1000001",
      "tgn:7012149",
      "tgn:2000086",
      "tgn:7029392"
    ],
    "placetype": [
      "aat:300008699"
    ],
    "id": 2322601,
    "name:xx": "Falls Eagle"
  }
}
