{
  "geometry": {
    "type": "Point",
    "coordinates": [
      -156.0167,
      65.6333
    ]
  },
  "type": "Feature",
  "properties": {
    "hierarchy": [
      "tgn:2300406",
      "tgn:7006450",
      "tgn:1000001",
      "tgn:7012149",
      "tgn:2000089",
      "tgn:7029392"
    ],
    "placetype": [
      "aat:300008699"
    ],
    "id": 2300406,
    "name:xx": "Dulbi Slough"
  }
}
