{
  "geometry": {
    "type": "Point",
    "coordinates": [
      14.1667,
      50.6667
    ]
  },
  "type": "Feature",
  "properties": {
    "hierarchy": [
      "tgn:1027480",
      "tgn:7593920",
      "tgn:1000003",
      "tgn:1001780",
      "tgn:7029392"
    ],
    "placetype": [
      "aat:300008347"
    ],
    "id": 1027480,
    "name:xx": "Povrly"
  }
}
