{
  "geometry": {
    "type": "Point",
    "coordinates": [
      -90.6167,
      45.3833
    ]
  },
  "type": "Feature",
  "properties": {
    "hierarchy": [
      "tgn:2693972",
      "tgn:1000001",
      "tgn:7012149",
      "tgn:2002348",
      "tgn:7007922",
      "tgn:7029392"
    ],
    "placetype": [
      "aat:300006191"
    ],
    "id": 2693972,
    "name:xx": "Steve Creek Flowage"
  }
}
