{
  "type": "FeatureCollection",
  "features": [
    {
      "geometry": {
        "type": "Point",
        "coordinates": [
          -2.766667,
          54.233333
        ]
      },
      "type": "Feature",
      "properties": {
        "hierarchy": [
          "tgn:7462010",
          "tgn:7002445",
          "tgn:1000003",
          "tgn:7008117",
          "tgn:7008591",
          "tgn:7029392"
        ],
        "placetype": [
          "aat:300008347"
        ],
        "name:en": "Heversham",
        "id": 7462010
      }
    },
    {
      "geometry": {
        "type": "Point",
        "coordinates": [
          0.1,
          51.166667
        ]
      },
      "type": "Feature",
      "properties": {
        "hierarchy": [
          "tgn:7462011",
          "tgn:7002445",
          "tgn:1000003",
          "tgn:7008153",
          "tgn:7008591",
          "tgn:7029392"
        ],
        "placetype": [
          "aat:300008347"
        ],
        "name:en": "Hever",
        "id": 7462011
      }
    },
    {
      "geometry": {
        "type": "Point",
        "coordinates": [
          1.433333,
          52.3
        ]
      },
      "type": "Feature",
      "properties": {
        "hierarchy": [
          "tgn:7462012",
          "tgn:7002445",
          "tgn:1000003",
          "tgn:7008185",
          "tgn:7008591",
          "tgn:7029392"
        ],
        "placetype": [
          "aat:300008347"
        ],
        "name:en": "Heveningham",
        "id": 7462012
      }
    },
    {
      "geometry": {
        "type": "Point",
        "coordinates": [
          -1.366667,
          60.366667
        ]
      },
      "type": "Feature",
      "properties": {
        "hierarchy": [
          "tgn:7462013",
          "tgn:7002444",
          "tgn:1000003",
          "tgn:7029508",
          "tgn:7008591",
          "tgn:7029392"
        ],
        "placetype": [
          "aat:300386846"
        ],
        "name:en": "Hevden Ness",
        "id": 7462013
      }
    },
    {
      "geometry": {
        "type": "Point",
        "coordinates": [
          -1.05,
          60.6
        ]
      },
      "type": "Feature",
      "properties": {
        "hierarchy": [
          "tgn:7462014",
          "tgn:7002444",
          "tgn:1000003",
          "tgn:7029508",
          "tgn:7008591",
          "tgn:7029392"
        ],
        "placetype": [
          "aat:300008850"
        ],
        "name:en": "Hevdagarth, Head of",
        "id": 7462014
      }
    },
    {
      "geometry": {
        "type": "Point",
        "coordinates": [
          -1.433333,
          60.583333
        ]
      },
      "type": "Feature",
      "properties": {
        "hierarchy": [
          "tgn:7462015",
          "tgn:7002444",
          "tgn:1000003",
          "tgn:7029508",
          "tgn:7008591",
          "tgn:7029392"
        ],
        "placetype": [
          "aat:300008850"
        ],
        "name:en": "Hevdadale Head",
        "id": 7462015
      }
    },
    {
      "geometry": {
        "type": "Point",
        "coordinates": [
          -1.175278,
          54.695833
        ]
      },
      "type": "Feature",
      "properties": {
        "hierarchy": [
          "tgn:7462016",
          "tgn:7002445",
          "tgn:1000003",
          "tgn:7019068",
          "tgn:7008591",
          "tgn:7029392"
        ],
        "placetype": [
          "aat:300008850"
        ],
        "name:en": "Heugh, The",
        "id": 7462016
      }
    }
  ]
}
