{
  "geometry": {
    "type": "Point",
    "coordinates": [
      -96.75,
      46.4833
    ]
  },
  "type": "Feature",
  "properties": {
    "hierarchy": [
      "tgn:2317991",
      "tgn:1000001",
      "tgn:2001595",
      "tgn:7012149",
      "tgn:7007705",
      "tgn:7029392"
    ],
    "placetype": [
      "aat:300008347"
    ],
    "id": 2317991,
    "name:xx": "Enloe"
  }
}
