{
  "geometry": {
    "type": "Point",
    "coordinates": [
      -139.05,
      -9.7833
    ]
  },
  "type": "Feature",
  "properties": {
    "hierarchy": [
      "tgn:1098718",
      "tgn:1007413",
      "tgn:7006215",
      "tgn:1000216",
      "tgn:1000006",
      "tgn:7029392"
    ],
    "placetype": [
      "aat:300008347"
    ],
    "id": 1098718,
    "name:xx": "Atuona"
  }
}
