{
  "geometry": {
    "type": "Point",
    "coordinates": [
      -94.3833,
      37.8333
    ]
  },
  "type": "Feature",
  "properties": {
    "hierarchy": [
      "tgn:2380375",
      "tgn:1000001",
      "tgn:7012149",
      "tgn:2001253",
      "tgn:7007523",
      "tgn:7029392"
    ],
    "placetype": [
      "aat:300008699"
    ],
    "id": 2380375,
    "name:xx": "Hattons Slough"
  }
}
