{
  "geometry": {
    "type": "Point",
    "coordinates": [
      -74.5167,
      42.5833
    ]
  },
  "type": "Feature",
  "properties": {
    "hierarchy": [
      "tgn:2567002",
      "tgn:1000001",
      "tgn:7012149",
      "tgn:1002873",
      "tgn:7007568",
      "tgn:7029392"
    ],
    "placetype": [
      "aat:300008706"
    ],
    "id": 2567002,
    "name:xx": "Panther Creek"
  }
}
