{
  "geometry": {
    "type": "Point",
    "coordinates": [
      -43.9167,
      -22.75
    ]
  },
  "type": "Feature",
  "properties": {
    "hierarchy": [
      "tgn:1120370",
      "tgn:1001942",
      "tgn:1000047",
      "tgn:7002457",
      "tgn:1000002",
      "tgn:7029392"
    ],
    "placetype": [
      "aat:300006191"
    ],
    "id": 1120370,
    "name:xx": "Ribeirão das Lajes, Reprêsa do"
  }
}
