{
  "type": "FeatureCollection",
  "features": [
    {
      "geometry": {
        "type": "Point",
        "coordinates": [
          -67.8833,
          47.1167
        ]
      },
      "type": "Feature",
      "properties": {
        "hierarchy": [
          "tgn:2437880",
          "tgn:2000919",
          "tgn:1000001",
          "tgn:7012149",
          "tgn:7007515",
          "tgn:7029392"
        ],
        "placetype": [
          "aat:300008791"
        ],
        "id": 2437880,
        "name:xx": "King Island"
      }
    },
    {
      "geometry": {
        "type": "Point",
        "coordinates": [
          -108.6333,
          47.6167
        ]
      },
      "type": "Feature",
      "properties": {
        "hierarchy": [
          "tgn:2437881",
          "tgn:1000001",
          "tgn:7012149",
          "tgn:2001273",
          "tgn:7007524",
          "tgn:7029392"
        ],
        "placetype": [
          "aat:300008791"
        ],
        "id": 2437881,
        "name:xx": "King Island"
      }
    },
    {
      "geometry": {
        "type": "Point",
        "coordinates": [
          -79.4167,
          41.55
        ]
      },
      "type": "Feature",
      "properties": {
        "hierarchy": [
          "tgn:2437882",
          "tgn:1000001",
          "tgn:7012149",
          "tgn:1002378",
          "tgn:7007710",
          "tgn:7029392"
        ],
        "placetype": [
          "aat:300008791"
        ],
        "id": 2437882,
        "name:xx": "King Island"
      }
    },
    {
      "geometry": {
        "type": "Point",
        "coordinates": [
          -76.8667,
          41.2167
        ]
      },
      "type": "Feature",
      "properties": {
        "hierarchy": [
          "tgn:2437883",
          "tgn:1000001",
          "tgn:7012149",
          "tgn:1002613",
          "tgn:7007710",
          "tgn:7029392"
        ],
        "placetype": [
          "aat:300008791"
        ],
        "id": 2437883,
        "name:xx": "King Island"
      }
    },
    {
      "geometry": {
        "type": "Point",
        "coordinates": [
          -78.1,
          40.0333
        ]
      },
      "type": "Feature",
      "properties": {
        "hierarchy": [
          "tgn:2437884",
          "tgn:1000001",
          "tgn:7012149",
          "tgn:1002399",
          "tgn:7007710",
          "tgn:7029392"
        ],
        "placetype": [
          "aat:300008798"
        ],
        "id": 2437884,
        "name:xx": "King Knob"
      }
    },
    {
      "geometry": {
        "type": "Point",
        "coordinates": [
          -81.05,
          39.1167
        ]
      },
      "type": "Feature",
      "properties": {
        "hierarchy": [
          "tgn:2437885",
          "tgn:1000001",
          "tgn:7012149",
          "tgn:2002292",
          "tgn:7013961",
          "tgn:7029392"
        ],
        "placetype": [
          "aat:300008798"
        ],
        "id": 2437885,
        "name:xx": "King Knob"
      }
    },
    {
      "geometry": {
        "type": "Point",
        "coordinates": [
          -81.05,
          39.1167
        ]
      },
      "type": "Feature",
      "properties": {
        "hierarchy": [
          "tgn:2437886",
          "tgn:1000001",
          "tgn:7012149",
          "tgn:2002292",
          "tgn:7013961",
          "tgn:7029392"
        ],
        "placetype": [
          "aat:300008699"
        ],
        "id": 2437886,
        "name:xx": "King Knob Run"
      }
    },
    {
      "geometry": {
        "type": "Point",
        "coordinates": [
          -88.0333,
          32.85
        ]
      },
      "type": "Feature",
      "properties": {
        "hierarchy": [
          "tgn:2437887",
          "tgn:7002659",
          "tgn:1000001",
          "tgn:7012149",
          "tgn:2000031",
          "tgn:7029392"
        ],
        "placetype": [
          "aat:300008680"
        ],
        "id": 2437887,
        "name:xx": "King Lake"
      }
    },
    {
      "geometry": {
        "type": "Point",
        "coordinates": [
          -150.3167,
          60.8
        ]
      },
      "type": "Feature",
      "properties": {
        "hierarchy": [
          "tgn:2437888",
          "tgn:7006450",
          "tgn:1000001",
          "tgn:7019698",
          "tgn:7012149",
          "tgn:7029392"
        ],
        "placetype": [
          "aat:300008680"
        ],
        "id": 2437888,
        "name:xx": "King Lake"
      }
    },
    {
      "geometry": {
        "type": "Point",
        "coordinates": [
          -91.1167,
          35.2667
        ]
      },
      "type": "Feature",
      "properties": {
        "hierarchy": [
          "tgn:2437889",
          "tgn:1000001",
          "tgn:7016172",
          "tgn:7012149",
          "tgn:2000178",
          "tgn:7029392"
        ],
        "placetype": [
          "aat:300008680"
        ],
        "id": 2437889,
        "name:xx": "King Lake"
      }
    }
  ]
}
