{
  "geometry": {
    "type": "Point",
    "coordinates": [
      -83.5333,
      37.5833
    ]
  },
  "type": "Feature",
  "properties": {
    "hierarchy": [
      "tgn:2199445",
      "tgn:1000001",
      "tgn:7012149",
      "tgn:2000810",
      "tgn:7007255",
      "tgn:7029392"
    ],
    "placetype": [
      "aat:300008706"
    ],
    "id": 2199445,
    "name:xx": "Brush Creek"
  }
}
