{
  "geometry": {
    "type": "Point",
    "coordinates": [
      -6.183333,
      41.75
    ]
  },
  "type": "Feature",
  "properties": {
    "hierarchy": [
      "tgn:7338235",
      "tgn:7001158",
      "tgn:7002850",
      "tgn:1000003",
      "tgn:1000095",
      "tgn:7029392"
    ],
    "placetype": [
      "aat:300008699"
    ],
    "id": 7338235,
    "name:xx": "Cebal, Río"
  }
}
