{
  "geometry": {
    "type": "Point",
    "coordinates": [
      -69.0167,
      44.2833
    ]
  },
  "type": "Feature",
  "properties": {
    "hierarchy": [
      "tgn:2574823",
      "tgn:1000001",
      "tgn:7012149",
      "tgn:2000931",
      "tgn:7007515",
      "tgn:7029392"
    ],
    "placetype": [
      "aat:300008798"
    ],
    "id": 2574823,
    "name:xx": "Pendleton Hill"
  }
}
