{
  "geometry": {
    "type": "Point",
    "coordinates": [
      135.95,
      34.6167
    ]
  },
  "type": "Feature",
  "properties": {
    "hierarchy": [
      "tgn:1081612",
      "tgn:1000004",
      "tgn:1001012",
      "tgn:7000896",
      "tgn:1000120",
      "tgn:7029392"
    ],
    "placetype": [
      "aat:300008347"
    ],
    "id": 1081612,
    "name:xx": "Tsuge"
  }
}
