{
  "geometry": {
    "type": "Point",
    "coordinates": [
      -80.8167,
      33.7667
    ]
  },
  "type": "Feature",
  "properties": {
    "hierarchy": [
      "tgn:2191456",
      "tgn:1000001",
      "tgn:2001733",
      "tgn:7012149",
      "tgn:7007712",
      "tgn:7029392"
    ],
    "placetype": [
      "aat:300008680"
    ],
    "id": 2191456,
    "name:xx": "Braddy Lake"
  }
}
