{
  "geometry": {
    "type": "Point",
    "coordinates": [
      79.008878,
      26.88286
    ]
  },
  "type": "Feature",
  "properties": {
    "hierarchy": [
      "tgn:7560149",
      "tgn:1000004",
      "tgn:7000198",
      "tgn:7016722",
      "tgn:7029392"
    ],
    "placetype": [
      "aat:300008347"
    ],
    "name:en": "Hīrāpur",
    "id": 7560149
  }
}
