{
  "geometry": {
    "type": "Point",
    "coordinates": [
      75.636983,
      25.64037
    ]
  },
  "type": "Feature",
  "properties": {
    "hierarchy": [
      "tgn:7569198",
      "tgn:1000004",
      "tgn:7000198",
      "tgn:7016788",
      "tgn:7029392"
    ],
    "placetype": [
      "aat:300008347"
    ],
    "name:en": "Batwāri ki Dūngariyān",
    "id": 7569198
  }
}
