{
  "type": "FeatureCollection",
  "features": [
    {
      "geometry": {
        "type": "Point",
        "coordinates": [
          -69,
          -18.1167
        ]
      },
      "type": "Feature",
      "properties": {
        "hierarchy": [
          "tgn:1020400",
          "tgn:1000717",
          "tgn:1000046",
          "tgn:1000002",
          "tgn:7029392"
        ],
        "placetype": [
          "aat:300008347"
        ],
        "id": 1020400,
        "name:xx": "Sajama"
      }
    },
    {
      "geometry": {
        "type": "Point",
        "coordinates": [
          -67.7167,
          -19.7
        ]
      },
      "type": "Feature",
      "properties": {
        "hierarchy": [
          "tgn:1020401",
          "tgn:1000717",
          "tgn:1000046",
          "tgn:1000002",
          "tgn:7029392"
        ],
        "placetype": [
          "aat:300008347"
        ],
        "id": 1020401,
        "name:xx": "Salinas de Garci Mendoza"
      }
    },
    {
      "geometry": {
        "type": "Point",
        "coordinates": [
          -63.8833,
          -18.1333
        ]
      },
      "type": "Feature",
      "properties": {
        "hierarchy": [
          "tgn:1020402",
          "tgn:1000752",
          "tgn:1000046",
          "tgn:1000002",
          "tgn:7029392"
        ],
        "placetype": [
          "aat:300008347"
        ],
        "id": 1020402,
        "name:xx": "Samaipata"
      }
    },
    {
      "geometry": {
        "type": "Point",
        "coordinates": [
          -65.9167,
          -17.5167
        ]
      },
      "type": "Feature",
      "properties": {
        "hierarchy": [
          "tgn:1020403",
          "tgn:1000572",
          "tgn:1000046",
          "tgn:1000002",
          "tgn:7029392"
        ],
        "placetype": [
          "aat:300008347"
        ],
        "id": 1020403,
        "name:xx": "San Benito"
      }
    },
    {
      "geometry": {
        "type": "Point",
        "coordinates": [
          -66.8667,
          -14.8333
        ]
      },
      "type": "Feature",
      "properties": {
        "hierarchy": [
          "tgn:1020404",
          "tgn:1000525",
          "tgn:1000046",
          "tgn:1000002",
          "tgn:7029392"
        ],
        "placetype": [
          "aat:300008347"
        ],
        "id": 1020404,
        "name:xx": "San Borja"
      }
    },
    {
      "geometry": {
        "type": "Point",
        "coordinates": [
          -67.6167,
          -14.5
        ]
      },
      "type": "Feature",
      "properties": {
        "hierarchy": [
          "tgn:1020405",
          "tgn:1000662",
          "tgn:1000046",
          "tgn:1000002",
          "tgn:7029392"
        ],
        "placetype": [
          "aat:300008347"
        ],
        "id": 1020405,
        "name:xx": "San Buenaventura"
      }
    },
    {
      "geometry": {
        "type": "Point",
        "coordinates": [
          -65.5833,
          -14.9
        ]
      },
      "type": "Feature",
      "properties": {
        "hierarchy": [
          "tgn:1020406",
          "tgn:1000525",
          "tgn:1000046",
          "tgn:1000002",
          "tgn:7029392"
        ],
        "placetype": [
          "aat:300008347"
        ],
        "id": 1020406,
        "name:xx": "San Ignacio"
      }
    },
    {
      "geometry": {
        "type": "Point",
        "coordinates": [
          -64.75,
          -14.6
        ]
      },
      "type": "Feature",
      "properties": {
        "hierarchy": [
          "tgn:1020407",
          "tgn:1000525",
          "tgn:1000046",
          "tgn:1000002",
          "tgn:7029392"
        ],
        "placetype": [
          "aat:300008347"
        ],
        "id": 1020407,
        "name:xx": "San Javier"
      }
    },
    {
      "geometry": {
        "type": "Point",
        "coordinates": [
          -64.7833,
          -13.1
        ]
      },
      "type": "Feature",
      "properties": {
        "hierarchy": [
          "tgn:1020408",
          "tgn:1000525",
          "tgn:1000046",
          "tgn:1000002",
          "tgn:7029392"
        ],
        "placetype": [
          "aat:300008347"
        ],
        "id": 1020408,
        "name:xx": "San Joaquín"
      }
    },
    {
      "geometry": {
        "type": "Point",
        "coordinates": [
          -68.0833,
          -14.2167
        ]
      },
      "type": "Feature",
      "properties": {
        "hierarchy": [
          "tgn:1020409",
          "tgn:1000662",
          "tgn:1000046",
          "tgn:1000002",
          "tgn:7029392"
        ],
        "placetype": [
          "aat:300008347"
        ],
        "id": 1020409,
        "name:xx": "San José"
      }
    }
  ]
}
