{
  "geometry": {
    "type": "Point",
    "coordinates": [
      -84.5667,
      46.1333
    ]
  },
  "type": "Feature",
  "properties": {
    "hierarchy": [
      "tgn:2387635",
      "tgn:1000001",
      "tgn:7012149",
      "tgn:2000973",
      "tgn:7007520",
      "tgn:7029392"
    ],
    "placetype": [
      "aat:300008699"
    ],
    "id": 2387635,
    "name:xx": "Hiawatha Run"
  }
}
