{
  "geometry": {
    "type": "Point",
    "coordinates": [
      117.7167,
      39.1167
    ]
  },
  "type": "Feature",
  "properties": {
    "hierarchy": [
      "tgn:1125204",
      "tgn:1000004",
      "tgn:1000111",
      "tgn:7029392"
    ],
    "placetype": [
      "aat:300008707"
    ],
    "id": 1125204,
    "name:xx": "Jiyun"
  }
}
