{
  "geometry": {
    "type": "Point",
    "coordinates": [
      -70.9667,
      42.3667
    ]
  },
  "type": "Feature",
  "properties": {
    "hierarchy": [
      "tgn:2777976",
      "tgn:1000001",
      "tgn:1002923",
      "tgn:7012149",
      "tgn:7007517",
      "tgn:7029392"
    ],
    "placetype": [
      "aat:300008347"
    ],
    "id": 2777976,
    "name:xx": "Winthrop Beach"
  }
}
