{
  "geometry": {
    "type": "Point",
    "coordinates": [
      40.1667,
      9.0167
    ]
  },
  "type": "Feature",
  "properties": {
    "hierarchy": [
      "tgn:1089724",
      "tgn:7001242",
      "tgn:1001535",
      "tgn:7000489",
      "tgn:7029392"
    ],
    "placetype": [
      "aat:300008347"
    ],
    "id": 1089724,
    "name:xx": "Āwash"
  }
}
