{
  "geometry": {
    "type": "Point",
    "coordinates": [
      -80.6833,
      41.1833
    ]
  },
  "type": "Feature",
  "properties": {
    "hierarchy": [
      "tgn:2475242",
      "tgn:1000001",
      "tgn:7012149",
      "tgn:1002955",
      "tgn:7007706",
      "tgn:7029392"
    ],
    "placetype": [
      "aat:300008347"
    ],
    "id": 2475242,
    "name:xx": "Loys Corners"
  }
}
