{
  "geometry": {
    "type": "Point",
    "coordinates": [
      -91.2833,
      37.0833
    ]
  },
  "type": "Feature",
  "properties": {
    "hierarchy": [
      "tgn:2626241",
      "tgn:1000001",
      "tgn:7012149",
      "tgn:2001247",
      "tgn:7007523",
      "tgn:7029392"
    ],
    "placetype": [
      "aat:300008863"
    ],
    "id": 2626241,
    "name:xx": "Rocky Creek State Forest"
  }
}
