{
  "geometry": {
    "type": "Point",
    "coordinates": [
      -121.25,
      41.75
    ]
  },
  "type": "Feature",
  "properties": {
    "hierarchy": [
      "tgn:2379426",
      "tgn:1000001",
      "tgn:7012149",
      "tgn:7007157",
      "tgn:2000186",
      "tgn:7029392"
    ],
    "placetype": [
      "aat:300008798"
    ],
    "id": 2379426,
    "name:xx": "Harvey Jones Butte"
  }
}
