{
  "geometry": {
    "type": "Point",
    "coordinates": [
      26.6167,
      60.9333
    ]
  },
  "type": "Feature",
  "properties": {
    "hierarchy": [
      "tgn:1031622",
      "tgn:1000003",
      "tgn:7594395",
      "tgn:1000069",
      "tgn:7029392"
    ],
    "placetype": [
      "aat:300008347"
    ],
    "id": 1031622,
    "name:xx": "Voikka"
  }
}
