{
  "type": "FeatureCollection",
  "features": [
    {
      "geometry": {
        "type": "Point",
        "coordinates": [
          11.366667,
          45.683333
        ]
      },
      "type": "Feature",
      "properties": {
        "hierarchy": [
          "tgn:7039512",
          "tgn:7003008",
          "tgn:1000003",
          "tgn:7002997",
          "tgn:1000080",
          "tgn:7029392"
        ],
        "placetype": [
          "aat:300008347"
        ],
        "id": 7039512,
        "name:xx": "San Vito di Leguzzano"
      }
    },
    {
      "geometry": {
        "type": "Point",
        "coordinates": [
          13.089722,
          46.090556
        ]
      },
      "type": "Feature",
      "properties": {
        "hierarchy": [
          "tgn:7039513",
          "tgn:1003506",
          "tgn:1000003",
          "tgn:7002993",
          "tgn:1000080",
          "tgn:7029392"
        ],
        "placetype": [
          "aat:300008347"
        ],
        "id": 7039513,
        "name:xx": "San Vito di Fagagna"
      }
    },
    {
      "geometry": {
        "type": "Point",
        "coordinates": [
          17.816667,
          40.65
        ]
      },
      "type": "Feature",
      "properties": {
        "hierarchy": [
          "tgn:7039515",
          "tgn:1003442",
          "tgn:1000003",
          "tgn:7010380",
          "tgn:1000080",
          "tgn:7029392"
        ],
        "placetype": [
          "aat:300007783"
        ],
        "id": 7039515,
        "name:xx": "Stazione San Vito dei Normanni"
      }
    },
    {
      "geometry": {
        "type": "Point",
        "coordinates": [
          17.233333,
          40.416667
        ]
      },
      "type": "Feature",
      "properties": {
        "hierarchy": [
          "tgn:7039519",
          "tgn:1003500",
          "tgn:1000003",
          "tgn:7010380",
          "tgn:1000080",
          "tgn:7029392"
        ],
        "placetype": [
          "aat:300004847"
        ],
        "id": 7039519,
        "name:xx": "Torre San Vito"
      }
    }
  ]
}
