{
  "geometry": {
    "type": "Point",
    "coordinates": [
      -88.5667,
      38.2333
    ]
  },
  "type": "Feature",
  "properties": {
    "hierarchy": [
      "tgn:2434718",
      "tgn:1000001",
      "tgn:7012149",
      "tgn:2000508",
      "tgn:7007251",
      "tgn:7029392"
    ],
    "placetype": [
      "aat:300006075"
    ],
    "id": 2434718,
    "name:xx": "Kennedy-Voris Main Drain"
  }
}
