{
  "type": "FeatureCollection",
  "features": [
    {
      "geometry": {
        "type": "Point",
        "coordinates": [
          -103.4333,
          41.7667
        ]
      },
      "type": "Feature",
      "properties": {
        "hierarchy": [
          "tgn:2607440",
          "tgn:1000001",
          "tgn:7012149",
          "tgn:2001394",
          "tgn:7007525",
          "tgn:7029392"
        ],
        "placetype": [
          "aat:300006075"
        ],
        "id": 2607440,
        "name:xx": "Rangler Canal"
      }
    },
    {
      "geometry": {
        "type": "Point",
        "coordinates": [
          -85.8833,
          34.9833
        ]
      },
      "type": "Feature",
      "properties": {
        "hierarchy": [
          "tgn:2607441",
          "tgn:1000001",
          "tgn:7012149",
          "tgn:7029392"
        ],
        "placetype": [
          "aat:300008746"
        ],
        "id": 2607441,
        "name:xx": "Ranie Willis Cave"
      }
    },
    {
      "geometry": {
        "type": "Point",
        "coordinates": [
          -93.6833,
          47.5833
        ]
      },
      "type": "Feature",
      "properties": {
        "hierarchy": [
          "tgn:2607442",
          "tgn:1000001",
          "tgn:7012149",
          "tgn:2001029",
          "tgn:7007521",
          "tgn:7029392"
        ],
        "placetype": [
          "aat:300008680"
        ],
        "id": 2607442,
        "name:xx": "Ranier Lake"
      }
    },
    {
      "geometry": {
        "type": "Point",
        "coordinates": [
          -112,
          33.8
        ]
      },
      "type": "Feature",
      "properties": {
        "hierarchy": [
          "tgn:2607443",
          "tgn:1000001",
          "tgn:7006451",
          "tgn:7012149",
          "tgn:2000097",
          "tgn:7029392"
        ],
        "placetype": [
          "aat:300006191"
        ],
        "id": 2607443,
        "name:xx": "Ranieri Tank"
      }
    },
    {
      "geometry": {
        "type": "Point",
        "coordinates": [
          -111.9833,
          33.8
        ]
      },
      "type": "Feature",
      "properties": {
        "hierarchy": [
          "tgn:2607444",
          "tgn:1000001",
          "tgn:7006451",
          "tgn:7012149",
          "tgn:2000097",
          "tgn:7029392"
        ],
        "placetype": [
          "aat:300008701"
        ],
        "id": 2607444,
        "name:xx": "Ranieri Tank Wash"
      }
    },
    {
      "geometry": {
        "type": "Point",
        "coordinates": [
          -82.3333,
          37.7
        ]
      },
      "type": "Feature",
      "properties": {
        "hierarchy": [
          "tgn:2607445",
          "tgn:1000001",
          "tgn:7012149",
          "tgn:2000837",
          "tgn:7007255",
          "tgn:7029392"
        ],
        "placetype": [
          "aat:300008699"
        ],
        "id": 2607445,
        "name:xx": "Rank Fork"
      }
    },
    {
      "geometry": {
        "type": "Point",
        "coordinates": [
          -88.6667,
          43.6
        ]
      },
      "type": "Feature",
      "properties": {
        "hierarchy": [
          "tgn:2607446",
          "tgn:1000001",
          "tgn:1002337",
          "tgn:7012149",
          "tgn:7007922",
          "tgn:7029392"
        ],
        "placetype": [
          "aat:300008791"
        ],
        "id": 2607446,
        "name:xx": "Rank Island"
      }
    },
    {
      "geometry": {
        "type": "Point",
        "coordinates": [
          -84.9833,
          40.25
        ]
      },
      "type": "Feature",
      "properties": {
        "hierarchy": [
          "tgn:2607447",
          "tgn:1000001",
          "tgn:7012149",
          "tgn:1002818",
          "tgn:7007252",
          "tgn:7029392"
        ],
        "placetype": [
          "aat:300008699"
        ],
        "id": 2607447,
        "name:xx": "Rank Run"
      }
    },
    {
      "geometry": {
        "type": "Point",
        "coordinates": [
          -90.5,
          38.5333
        ]
      },
      "type": "Feature",
      "properties": {
        "hierarchy": [
          "tgn:2607448",
          "tgn:1000001",
          "tgn:7012149",
          "tgn:7016167",
          "tgn:7007523",
          "tgn:7029392"
        ],
        "placetype": [
          "aat:300008347"
        ],
        "id": 2607448,
        "name:xx": "Ranken"
      }
    },
    {
      "geometry": {
        "type": "Point",
        "coordinates": [
          -81.3,
          39.7833
        ]
      },
      "type": "Feature",
      "properties": {
        "hierarchy": [
          "tgn:2607449",
          "tgn:1000001",
          "tgn:7012149",
          "tgn:2001617",
          "tgn:7007706",
          "tgn:7029392"
        ],
        "placetype": [
          "aat:300008798"
        ],
        "id": 2607449,
        "name:xx": "Ranker Knob"
      }
    }
  ]
}
