{
  "geometry": {
    "type": "Point",
    "coordinates": [
      -82.1167,
      35.2333
    ]
  },
  "type": "Feature",
  "properties": {
    "hierarchy": [
      "tgn:2458126",
      "tgn:1000001",
      "tgn:7012149",
      "tgn:2001531",
      "tgn:7007709",
      "tgn:7029392"
    ],
    "placetype": [
      "aat:300008798"
    ],
    "id": 2458126,
    "name:xx": "Little Mountain"
  }
}
