{
  "geometry": {
    "type": "Point",
    "coordinates": [
      -95.9667,
      29.3667
    ]
  },
  "type": "Feature",
  "properties": {
    "hierarchy": [
      "tgn:2572308",
      "tgn:1000001",
      "tgn:7012149",
      "tgn:1003019",
      "tgn:7007826",
      "tgn:7029392"
    ],
    "placetype": [
      "aat:300008798"
    ],
    "id": 2572308,
    "name:xx": "Peach Break"
  }
}
