{
  "geometry": {
    "type": "Point",
    "coordinates": [
      32.24142,
      26.04949
    ]
  },
  "type": "Feature",
  "properties": {
    "hierarchy": [
      "tgn:1095626",
      "tgn:7001242",
      "tgn:7016833",
      "tgn:7000123",
      "tgn:7029392"
    ],
    "placetype": [
      "aat:300008347",
      "aat:300008375"
    ],
    "id": 1095626,
    "name:xx": "Najʻ Ḥammādī"
  }
}
