{
  "geometry": {
    "type": "Point",
    "coordinates": [
      -79.086,
      -1.998
    ]
  },
  "type": "Feature",
  "properties": {
    "hierarchy": [
      "tgn:1024154",
      "tgn:1001155",
      "tgn:7002561",
      "tgn:1000051",
      "tgn:1000002",
      "tgn:7029392"
    ],
    "placetype": [
      "aat:300008347"
    ],
    "id": 1024154,
    "name:xx": "San José"
  }
}
