{
  "geometry": {
    "type": "Point",
    "coordinates": [
      -109.9833,
      40.8333
    ]
  },
  "type": "Feature",
  "properties": {
    "hierarchy": [
      "tgn:2684737",
      "tgn:1000001",
      "tgn:7012149",
      "tgn:7007827",
      "tgn:7029392"
    ],
    "placetype": [
      "aat:300008680"
    ],
    "id": 2684737,
    "name:xx": "Spirit Lake"
  }
}
