{
  "geometry": {
    "type": "Point",
    "coordinates": [
      -88.2333,
      15.7333
    ]
  },
  "type": "Feature",
  "properties": {
    "hierarchy": [
      "tgn:1127387",
      "tgn:1000001",
      "tgn:7029392"
    ],
    "placetype": [
      "aat:300008707"
    ],
    "id": 1127387,
    "name:xx": "Motagua, Río"
  }
}
