{
  "type": "FeatureCollection",
  "features": [
    {
      "geometry": {
        "type": "Point",
        "coordinates": [
          31.15,
          27.2
        ]
      },
      "type": "Feature",
      "properties": {
        "hierarchy": [
          "tgn:7526850",
          "tgn:7001242",
          "tgn:7016833",
          "tgn:1001114",
          "tgn:7029392"
        ],
        "placetype": [
          "aat:300005926"
        ],
        "name:en": "Sīdī Muḩammad al 'Ajamī",
        "id": 7526850
      }
    },
    {
      "geometry": {
        "type": "Point",
        "coordinates": [
          30.833333,
          27.8
        ]
      },
      "type": "Feature",
      "properties": {
        "hierarchy": [
          "tgn:7526851",
          "tgn:7001242",
          "tgn:7016833",
          "tgn:1001088",
          "tgn:7029392"
        ],
        "placetype": [
          "aat:300005926"
        ],
        "name:en": "Sīdī Muḩammad al Aḩrash",
        "id": 7526851
      }
    },
    {
      "geometry": {
        "type": "Point",
        "coordinates": [
          31.05,
          31.2
        ]
      },
      "type": "Feature",
      "properties": {
        "hierarchy": [
          "tgn:7526852",
          "tgn:7001242",
          "tgn:7016833",
          "tgn:1001335",
          "tgn:7029392"
        ],
        "placetype": [
          "aat:300005926"
        ],
        "name:en": "Sīdī Muḩammad adh Dhikkīr",
        "id": 7526852
      }
    },
    {
      "geometry": {
        "type": "Point",
        "coordinates": [
          31.3,
          27.016667
        ]
      },
      "type": "Feature",
      "properties": {
        "hierarchy": [
          "tgn:7526853",
          "tgn:7001242",
          "tgn:7016833",
          "tgn:1001114",
          "tgn:7029392"
        ],
        "placetype": [
          "aat:300005926"
        ],
        "name:en": "Sīdī Muḩammad aḑ Ḑib'ānī",
        "id": 7526853
      }
    },
    {
      "geometry": {
        "type": "Point",
        "coordinates": [
          31.516667,
          31.233333
        ]
      },
      "type": "Feature",
      "properties": {
        "hierarchy": [
          "tgn:7526854",
          "tgn:7001242",
          "tgn:1001059",
          "tgn:7016833",
          "tgn:7029392"
        ],
        "placetype": [
          "aat:300005926"
        ],
        "name:en": "Sīdī Muḩammad ad Dakrūrī",
        "id": 7526854
      }
    },
    {
      "geometry": {
        "type": "Point",
        "coordinates": [
          31.05,
          27.2
        ]
      },
      "type": "Feature",
      "properties": {
        "hierarchy": [
          "tgn:7526855",
          "tgn:7001242",
          "tgn:7016833",
          "tgn:1001114",
          "tgn:7029392"
        ],
        "placetype": [
          "aat:300005926"
        ],
        "name:en": "Sīdī Muḩammad ad Dakrūrī",
        "id": 7526855
      }
    },
    {
      "geometry": {
        "type": "Point",
        "coordinates": [
          31.933333,
          31.383333
        ]
      },
      "type": "Feature",
      "properties": {
        "hierarchy": [
          "tgn:7526856",
          "tgn:7001242",
          "tgn:7016833",
          "tgn:1001225",
          "tgn:7029392"
        ],
        "placetype": [
          "aat:300005926"
        ],
        "name:en": "Manāmat Sīdī Muḩammad ad Dakrūr",
        "id": 7526856
      }
    },
    {
      "geometry": {
        "type": "Point",
        "coordinates": [
          30.95,
          28.9
        ]
      },
      "type": "Feature",
      "properties": {
        "hierarchy": [
          "tgn:7526857",
          "tgn:7001242",
          "tgn:7016833",
          "tgn:1001142",
          "tgn:7029392"
        ],
        "placetype": [
          "aat:300005926"
        ],
        "name:en": "Sīdī Muḩammad aḑ Ḑabūşī",
        "id": 7526857
      }
    },
    {
      "geometry": {
        "type": "Point",
        "coordinates": [
          26.41082,
          31.2199
        ]
      },
      "type": "Feature",
      "properties": {
        "hierarchy": [
          "tgn:7526858",
          "tgn:7001242",
          "tgn:7016833",
          "tgn:1001418",
          "tgn:7029392"
        ],
        "placetype": [
          "aat:300005926"
        ],
        "name:en": "Sīdī Muḩammad Abū Yūsuf",
        "id": 7526858
      }
    },
    {
      "geometry": {
        "type": "Point",
        "coordinates": [
          31.116667,
          29.083333
        ]
      },
      "type": "Feature",
      "properties": {
        "hierarchy": [
          "tgn:7526859",
          "tgn:7001242",
          "tgn:7001105",
          "tgn:7016833",
          "tgn:7029392"
        ],
        "placetype": [
          "aat:300005926"
        ],
        "name:en": "Sīdī Muḩammad Abū 'Ubayd",
        "id": 7526859
      }
    }
  ]
}
