{
  "type": "FeatureCollection",
  "features": [
    {
      "geometry": {
        "type": "Point",
        "coordinates": [
          -116.8667,
          38.7167
        ]
      },
      "type": "Feature",
      "properties": {
        "hierarchy": [
          "tgn:2727390",
          "tgn:1000001",
          "tgn:2001418",
          "tgn:7012149",
          "tgn:7007526",
          "tgn:7029392"
        ],
        "placetype": [
          "aat:300008761"
        ],
        "id": 2727390,
        "name:xx": "Trail Canyon"
      }
    },
    {
      "geometry": {
        "type": "Point",
        "coordinates": [
          -116.6167,
          39.6667
        ]
      },
      "type": "Feature",
      "properties": {
        "hierarchy": [
          "tgn:2727391",
          "tgn:1000001",
          "tgn:2001415",
          "tgn:7012149",
          "tgn:7007526",
          "tgn:7029392"
        ],
        "placetype": [
          "aat:300008761"
        ],
        "id": 2727391,
        "name:xx": "Trail Canyon"
      }
    },
    {
      "geometry": {
        "type": "Point",
        "coordinates": [
          -119.55,
          40.3667
        ]
      },
      "type": "Feature",
      "properties": {
        "hierarchy": [
          "tgn:2727392",
          "tgn:1000001",
          "tgn:7012149",
          "tgn:1002999",
          "tgn:7007526",
          "tgn:7029392"
        ],
        "placetype": [
          "aat:300008761"
        ],
        "id": 2727392,
        "name:xx": "Trail Canyon"
      }
    },
    {
      "geometry": {
        "type": "Point",
        "coordinates": [
          -117.4667,
          40.5
        ]
      },
      "type": "Feature",
      "properties": {
        "hierarchy": [
          "tgn:2727393",
          "tgn:1000001",
          "tgn:2001419",
          "tgn:7012149",
          "tgn:7007526",
          "tgn:7029392"
        ],
        "placetype": [
          "aat:300008761"
        ],
        "id": 2727393,
        "name:xx": "Trail Canyon"
      }
    },
    {
      "geometry": {
        "type": "Point",
        "coordinates": [
          -114.5667,
          39.5333
        ]
      },
      "type": "Feature",
      "properties": {
        "hierarchy": [
          "tgn:2727394",
          "tgn:1000001",
          "tgn:7012149",
          "tgn:2001420",
          "tgn:7007526",
          "tgn:7029392"
        ],
        "placetype": [
          "aat:300008761"
        ],
        "id": 2727394,
        "name:xx": "Trail Canyon"
      }
    },
    {
      "geometry": {
        "type": "Point",
        "coordinates": [
          -115.65,
          36.2833
        ]
      },
      "type": "Feature",
      "properties": {
        "hierarchy": [
          "tgn:2727395",
          "tgn:1000001",
          "tgn:2001410",
          "tgn:7012149",
          "tgn:7007526",
          "tgn:7029392"
        ],
        "placetype": [
          "aat:300008761"
        ],
        "id": 2727395,
        "name:xx": "Trail Canyon"
      }
    },
    {
      "geometry": {
        "type": "Point",
        "coordinates": [
          -105.6,
          32.7167
        ]
      },
      "type": "Feature",
      "properties": {
        "hierarchy": [
          "tgn:2727396",
          "tgn:1000001",
          "tgn:7012149",
          "tgn:2001447",
          "tgn:7007566",
          "tgn:7029392"
        ],
        "placetype": [
          "aat:300008761"
        ],
        "id": 2727396,
        "name:xx": "Trail Canyon"
      }
    },
    {
      "geometry": {
        "type": "Point",
        "coordinates": [
          -107.8167,
          32.85
        ]
      },
      "type": "Feature",
      "properties": {
        "hierarchy": [
          "tgn:2727397",
          "tgn:1000001",
          "tgn:7012149",
          "tgn:2001437",
          "tgn:7007566",
          "tgn:7029392"
        ],
        "placetype": [
          "aat:300008761"
        ],
        "id": 2727397,
        "name:xx": "Trail Canyon"
      }
    },
    {
      "geometry": {
        "type": "Point",
        "coordinates": [
          -107.8,
          33.2
        ]
      },
      "type": "Feature",
      "properties": {
        "hierarchy": [
          "tgn:2727398",
          "tgn:1000001",
          "tgn:7012149",
          "tgn:2001455",
          "tgn:7007566",
          "tgn:7029392"
        ],
        "placetype": [
          "aat:300008761"
        ],
        "id": 2727398,
        "name:xx": "Trail Canyon"
      }
    },
    {
      "geometry": {
        "type": "Point",
        "coordinates": [
          -108.5167,
          33.2333
        ]
      },
      "type": "Feature",
      "properties": {
        "hierarchy": [
          "tgn:2727399",
          "tgn:1000001",
          "tgn:2001429",
          "tgn:7012149",
          "tgn:7007566",
          "tgn:7029392"
        ],
        "placetype": [
          "aat:300008761"
        ],
        "id": 2727399,
        "name:xx": "Trail Canyon"
      }
    }
  ]
}
