{
  "geometry": {
    "type": "Point",
    "coordinates": [
      -121.7333,
      39.45
    ]
  },
  "type": "Feature",
  "properties": {
    "hierarchy": [
      "tgn:2208670",
      "tgn:1000001",
      "tgn:1002218",
      "tgn:7012149",
      "tgn:7007157",
      "tgn:7029392"
    ],
    "placetype": [
      "aat:300006075"
    ],
    "id": 2208670,
    "name:xx": "Burns Government Lateral"
  }
}
