{
  "geometry": {
    "type": "Point",
    "coordinates": [
      121.15,
      30.7333
    ]
  },
  "type": "Feature",
  "properties": {
    "hierarchy": [
      "tgn:1073921",
      "tgn:1000004",
      "tgn:7002076",
      "tgn:1000111",
      "tgn:7029392"
    ],
    "placetype": [
      "aat:300008347"
    ],
    "id": 1073921,
    "name:xx": "Zhaojiaqiao"
  }
}
