{
  "type": "FeatureCollection",
  "features": [
    {
      "geometry": {
        "type": "Point",
        "coordinates": [
          47.75,
          43.9833
        ]
      },
      "type": "Feature",
      "properties": {
        "hierarchy": [
          "tgn:1006145",
          "tgn:1000004",
          "tgn:7011494",
          "tgn:7002435",
          "tgn:7029392"
        ],
        "placetype": [
          "aat:300008791"
        ],
        "id": 1006145,
        "name:xx": "ChechenOstrov"
      }
    },
    {
      "geometry": {
        "type": "Point",
        "coordinates": [
          38.95,
          47.1833
        ]
      },
      "type": "Feature",
      "properties": {
        "hierarchy": [
          "tgn:1006146",
          "tgn:1000004",
          "tgn:1003405",
          "tgn:7018214",
          "tgn:7002435",
          "tgn:7029392"
        ],
        "placetype": [
          "aat:300008791"
        ],
        "id": 1006146,
        "name:xx": "Cherepashka, Ostrov"
      }
    },
    {
      "geometry": {
        "type": "Point",
        "coordinates": [
          16.2833,
          43.5
        ]
      },
      "type": "Feature",
      "properties": {
        "hierarchy": [
          "tgn:1006147",
          "tgn:7017308",
          "tgn:1000003",
          "tgn:7006663",
          "tgn:7029392"
        ],
        "placetype": [
          "aat:300008791"
        ],
        "id": 1006147,
        "name:xx": "Čiovo"
      }
    }
  ]
}
