{
  "geometry": {
    "type": "Point",
    "coordinates": [
      -114.6667,
      48.9167
    ]
  },
  "type": "Feature",
  "properties": {
    "hierarchy": [
      "tgn:2615633",
      "tgn:1000001",
      "tgn:7012149",
      "tgn:7007524",
      "tgn:7029392"
    ],
    "placetype": [
      "aat:300266640"
    ],
    "id": 2615633,
    "name:xx": "Review Mountain"
  }
}
