{
  "geometry": {
    "type": "Point",
    "coordinates": [
      -96.5167,
      32.95
    ]
  },
  "type": "Feature",
  "properties": {
    "hierarchy": [
      "tgn:2105637",
      "tgn:1000001",
      "tgn:7012149",
      "tgn:1002315",
      "tgn:7007826",
      "tgn:7029392"
    ],
    "placetype": [
      "aat:300008347"
    ],
    "id": 2105637,
    "name:xx": "Liberty Grove"
  }
}
