{
  "geometry": {
    "type": "Point",
    "coordinates": [
      -75.7167,
      43.05
    ]
  },
  "type": "Feature",
  "properties": {
    "hierarchy": [
      "tgn:2302366",
      "tgn:1000001",
      "tgn:7012149",
      "tgn:1002624",
      "tgn:7007568",
      "tgn:7029392"
    ],
    "placetype": [
      "aat:300008706"
    ],
    "id": 2302366,
    "name:xx": "Dutch Settlement Creek"
  }
}
