{
  "geometry": {
    "type": "Point",
    "coordinates": [
      -82.9333,
      35.8833
    ]
  },
  "type": "Feature",
  "properties": {
    "hierarchy": [
      "tgn:2623745",
      "tgn:1000001",
      "tgn:7012149",
      "tgn:2001851",
      "tgn:7007825",
      "tgn:7029392"
    ],
    "placetype": [
      "aat:300008706"
    ],
    "id": 2623745,
    "name:xx": "Rock Creek"
  }
}
