{
  "type": "FeatureCollection",
  "features": [
    {
      "geometry": {
        "type": "Point",
        "coordinates": [
          -3.416667,
          56.183333
        ]
      },
      "type": "Feature",
      "properties": {
        "hierarchy": [
          "tgn:7449091",
          "tgn:7002444",
          "tgn:1000003",
          "tgn:7019152",
          "tgn:7008591",
          "tgn:7029392"
        ],
        "placetype": [
          "aat:300008699"
        ],
        "name:en": "South Queich",
        "id": 7449091
      }
    },
    {
      "geometry": {
        "type": "Point",
        "coordinates": [
          -4.383333,
          50.616667
        ]
      },
      "type": "Feature",
      "properties": {
        "hierarchy": [
          "tgn:7449095",
          "tgn:7002445",
          "tgn:7008116",
          "tgn:1000003",
          "tgn:7008591",
          "tgn:7029392"
        ],
        "placetype": [
          "aat:300008347"
        ],
        "name:en": "South Petherwin",
        "id": 7449095
      }
    }
  ]
}
