{
  "geometry": {
    "type": "Point",
    "coordinates": [
      -63.65,
      -37.15
    ]
  },
  "type": "Feature",
  "properties": {
    "hierarchy": [
      "tgn:1019723",
      "tgn:7006477",
      "tgn:1001375",
      "tgn:1000002",
      "tgn:7029392"
    ],
    "placetype": [
      "aat:300008347"
    ],
    "id": 1019723,
    "name:xx": "Macachín"
  }
}
