{
  "geometry": {
    "type": "Point",
    "coordinates": [
      -93.3667,
      41.7333
    ]
  },
  "type": "Feature",
  "properties": {
    "hierarchy": [
      "tgn:2288816",
      "tgn:1000001",
      "tgn:7012149",
      "tgn:2000637",
      "tgn:7007253",
      "tgn:7029392"
    ],
    "placetype": [
      "aat:300006075"
    ],
    "id": 2288816,
    "name:xx": "Ditch Number 38"
  }
}
