{
  "geometry": {
    "type": "Point",
    "coordinates": [
      -100.3833,
      29.2833
    ]
  },
  "type": "Feature",
  "properties": {
    "hierarchy": [
      "tgn:2409990",
      "tgn:1000001",
      "tgn:7012149",
      "tgn:7007826",
      "tgn:7029392"
    ],
    "placetype": [
      "aat:300008706"
    ],
    "id": 2409990,
    "name:xx": "Imperialist Creek"
  }
}
