{
  "geometry": {
    "type": "Point",
    "coordinates": [
      -115.3333,
      36.8333
    ]
  },
  "type": "Feature",
  "properties": {
    "hierarchy": [
      "tgn:2284638",
      "tgn:1000001",
      "tgn:7012149",
      "tgn:7007526",
      "tgn:7029392"
    ],
    "placetype": [
      "aat:300386831"
    ],
    "id": 2284638,
    "name:xx": "Desert Range"
  }
}
