{
  "type": "FeatureCollection",
  "features": [
    {
      "geometry": {
        "type": "Point",
        "coordinates": [
          -99.1333,
          29.9333
        ]
      },
      "type": "Feature",
      "properties": {
        "hierarchy": [
          "tgn:2677680",
          "tgn:1000001",
          "tgn:7012149",
          "tgn:2002018",
          "tgn:7007826",
          "tgn:7029392"
        ],
        "placetype": [
          "aat:300008706"
        ],
        "id": 2677680,
        "name:xx": "South Creek"
      }
    },
    {
      "geometry": {
        "type": "Point",
        "coordinates": [
          -97.95,
          33.4167
        ]
      },
      "type": "Feature",
      "properties": {
        "hierarchy": [
          "tgn:2677681",
          "tgn:1000001",
          "tgn:7012149",
          "tgn:7007826",
          "tgn:7029392"
        ],
        "placetype": [
          "aat:300008706"
        ],
        "id": 2677681,
        "name:xx": "South Creek"
      }
    },
    {
      "geometry": {
        "type": "Point",
        "coordinates": [
          -111.6167,
          39.25
        ]
      },
      "type": "Feature",
      "properties": {
        "hierarchy": [
          "tgn:2677682",
          "tgn:1000001",
          "tgn:7012149",
          "tgn:2002120",
          "tgn:7007827",
          "tgn:7029392"
        ],
        "placetype": [
          "aat:300008706"
        ],
        "id": 2677682,
        "name:xx": "South Creek"
      }
    },
    {
      "geometry": {
        "type": "Point",
        "coordinates": [
          -112.95,
          37.0667
        ]
      },
      "type": "Feature",
      "properties": {
        "hierarchy": [
          "tgn:2677683",
          "tgn:1000001",
          "tgn:7012149",
          "tgn:2002127",
          "tgn:7007827",
          "tgn:7029392"
        ],
        "placetype": [
          "aat:300008706"
        ],
        "id": 2677683,
        "name:xx": "South Creek"
      }
    },
    {
      "geometry": {
        "type": "Point",
        "coordinates": [
          -111.8833,
          37.7833
        ]
      },
      "type": "Feature",
      "properties": {
        "hierarchy": [
          "tgn:2677684",
          "tgn:1000001",
          "tgn:2002109",
          "tgn:7012149",
          "tgn:7007827",
          "tgn:7029392"
        ],
        "placetype": [
          "aat:300008706"
        ],
        "id": 2677684,
        "name:xx": "South Creek"
      }
    },
    {
      "geometry": {
        "type": "Point",
        "coordinates": [
          -112.4667,
          38.15
        ]
      },
      "type": "Feature",
      "properties": {
        "hierarchy": [
          "tgn:2677685",
          "tgn:2002101",
          "tgn:1000001",
          "tgn:7012149",
          "tgn:7007827",
          "tgn:7029392"
        ],
        "placetype": [
          "aat:300008706"
        ],
        "id": 2677685,
        "name:xx": "South Creek"
      }
    },
    {
      "geometry": {
        "type": "Point",
        "coordinates": [
          -113.8,
          41.9167
        ]
      },
      "type": "Feature",
      "properties": {
        "hierarchy": [
          "tgn:2677686",
          "tgn:1000001",
          "tgn:2002102",
          "tgn:7012149",
          "tgn:7007827",
          "tgn:7029392"
        ],
        "placetype": [
          "aat:300008706"
        ],
        "id": 2677686,
        "name:xx": "South Creek"
      }
    },
    {
      "geometry": {
        "type": "Point",
        "coordinates": [
          -78.2667,
          37.7167
        ]
      },
      "type": "Feature",
      "properties": {
        "hierarchy": [
          "tgn:2677687",
          "tgn:1000001",
          "tgn:7012149",
          "tgn:2002159",
          "tgn:7007919",
          "tgn:7029392"
        ],
        "placetype": [
          "aat:300008706"
        ],
        "id": 2677687,
        "name:xx": "South Creek"
      }
    },
    {
      "geometry": {
        "type": "Point",
        "coordinates": [
          -124.5833,
          48.0167
        ]
      },
      "type": "Feature",
      "properties": {
        "hierarchy": [
          "tgn:2677688",
          "tgn:1000001",
          "tgn:1002271",
          "tgn:7012149",
          "tgn:7007920",
          "tgn:7029392"
        ],
        "placetype": [
          "aat:300008706"
        ],
        "id": 2677688,
        "name:xx": "South Creek"
      }
    },
    {
      "geometry": {
        "type": "Point",
        "coordinates": [
          -123.6167,
          46.2667
        ]
      },
      "type": "Feature",
      "properties": {
        "hierarchy": [
          "tgn:2677689",
          "tgn:1000001",
          "tgn:7012149",
          "tgn:1002979",
          "tgn:7007920",
          "tgn:7029392"
        ],
        "placetype": [
          "aat:300008706"
        ],
        "id": 2677689,
        "name:xx": "South Creek"
      }
    }
  ]
}
