{
  "geometry": {
    "type": "Point",
    "coordinates": [
      -148.95,
      66.8667
    ]
  },
  "type": "Feature",
  "properties": {
    "hierarchy": [
      "tgn:2376514",
      "tgn:7006450",
      "tgn:1000001",
      "tgn:7012149",
      "tgn:2000089",
      "tgn:7029392"
    ],
    "placetype": [
      "aat:300008706"
    ],
    "id": 2376514,
    "name:xx": "Hardpac Creek"
  }
}
