{
  "geometry": {
    "type": "Point",
    "coordinates": [
      -94.0167,
      46.4833
    ]
  },
  "type": "Feature",
  "properties": {
    "hierarchy": [
      "tgn:2745723",
      "tgn:1000001",
      "tgn:2001016",
      "tgn:7012149",
      "tgn:7007521",
      "tgn:7029392"
    ],
    "placetype": [
      "aat:300000390"
    ],
    "id": 2745723,
    "name:xx": "Virginia Mine"
  }
}
