{
  "geometry": {
    "type": "Point",
    "coordinates": [
      -90.5167,
      36.8833
    ]
  },
  "type": "Feature",
  "properties": {
    "hierarchy": [
      "tgn:2355525",
      "tgn:1000001",
      "tgn:2001176",
      "tgn:7012149",
      "tgn:7007523",
      "tgn:7029392"
    ],
    "placetype": [
      "aat:300008706"
    ],
    "id": 2355525,
    "name:xx": "Goose Creek"
  }
}
