{
  "geometry": {
    "type": "Point",
    "coordinates": [
      -84.9333,
      30.7167
    ]
  },
  "type": "Feature",
  "properties": {
    "hierarchy": [
      "tgn:2434239",
      "tgn:1000001",
      "tgn:2000273",
      "tgn:7012149",
      "tgn:7007240",
      "tgn:7029392"
    ],
    "placetype": [
      "aat:300008905"
    ],
    "id": 2434239,
    "name:xx": "Kemp Pond"
  }
}
