{
  "geometry": {
    "type": "Point",
    "coordinates": [
      -103.2333,
      29.5167
    ]
  },
  "type": "Feature",
  "properties": {
    "hierarchy": [
      "tgn:2729717",
      "tgn:1000001",
      "tgn:2001945",
      "tgn:7012149",
      "tgn:7007826",
      "tgn:7029392"
    ],
    "placetype": [
      "aat:300008761"
    ],
    "id": 2729717,
    "name:xx": "Trough Canyon"
  }
}
