{
  "geometry": {
    "type": "Point",
    "coordinates": [
      -123.8167,
      43.0667
    ]
  },
  "type": "Feature",
  "properties": {
    "hierarchy": [
      "tgn:2649208",
      "tgn:1000001",
      "tgn:2001702",
      "tgn:7012149",
      "tgn:7007708",
      "tgn:7029392"
    ],
    "placetype": [
      "aat:300008798"
    ],
    "id": 2649208,
    "name:xx": "Scott Mountain"
  }
}
