{
  "geometry": {
    "type": "Point",
    "coordinates": [
      -98.7167,
      30.6333
    ]
  },
  "type": "Feature",
  "properties": {
    "hierarchy": [
      "tgn:2388318",
      "tgn:1000001",
      "tgn:7012149",
      "tgn:2002030",
      "tgn:7007826",
      "tgn:7029392"
    ],
    "placetype": [
      "aat:300008699"
    ],
    "id": 2388318,
    "name:xx": "Hickory Mountain Branch"
  }
}
