{
  "geometry": {
    "type": "Point",
    "coordinates": [
      116.3333,
      30.3667
    ]
  },
  "type": "Feature",
  "properties": {
    "hierarchy": [
      "tgn:1072060",
      "tgn:7002075",
      "tgn:1000004",
      "tgn:1000111",
      "tgn:7029392"
    ],
    "placetype": [
      "aat:300008347"
    ],
    "id": 1072060,
    "name:xx": "Taihu"
  }
}
