{
  "geometry": {
    "type": "Point",
    "coordinates": [
      -84.4833,
      41.2333
    ]
  },
  "type": "Feature",
  "properties": {
    "hierarchy": [
      "tgn:2081577",
      "tgn:1000001",
      "tgn:7012149",
      "tgn:1002776",
      "tgn:7007706",
      "tgn:7029392"
    ],
    "placetype": [
      "aat:300387016"
    ],
    "id": 2081577,
    "name:xx": "Renollet"
  }
}
