{
  "geometry": {
    "type": "Point",
    "coordinates": [
      -85.4333,
      38.1167
    ]
  },
  "type": "Feature",
  "properties": {
    "hierarchy": [
      "tgn:2656398",
      "tgn:1000001",
      "tgn:7012149",
      "tgn:1002516",
      "tgn:7007255",
      "tgn:7029392"
    ],
    "placetype": [
      "aat:300008699"
    ],
    "id": 2656398,
    "name:xx": "Sheckels Run"
  }
}
