{
  "type": "FeatureCollection",
  "features": [
    {
      "geometry": {
        "type": "Point",
        "coordinates": [
          -66.4167,
          -43.6667
        ]
      },
      "type": "Feature",
      "properties": {
        "hierarchy": [
          "tgn:1019390",
          "tgn:7006477",
          "tgn:1001203",
          "tgn:1000002",
          "tgn:7029392"
        ],
        "placetype": [
          "aat:300008347"
        ],
        "id": 1019390,
        "name:xx": "Dique Florentino Ameghino"
      }
    },
    {
      "geometry": {
        "type": "Point",
        "coordinates": [
          -65.7333,
          -43.2667
        ]
      },
      "type": "Feature",
      "properties": {
        "hierarchy": [
          "tgn:1019391",
          "tgn:7006477",
          "tgn:1001203",
          "tgn:1000002",
          "tgn:7029392"
        ],
        "placetype": [
          "aat:300008347"
        ],
        "id": 1019391,
        "name:xx": "Dolavon"
      }
    },
    {
      "geometry": {
        "type": "Point",
        "coordinates": [
          -57.7333,
          -36.3833
        ]
      },
      "type": "Feature",
      "properties": {
        "hierarchy": [
          "tgn:1019392",
          "tgn:1001160",
          "tgn:7006477",
          "tgn:1000002",
          "tgn:7029392"
        ],
        "placetype": [
          "aat:300008347"
        ],
        "id": 1019392,
        "name:xx": "Dolores"
      }
    },
    {
      "geometry": {
        "type": "Point",
        "coordinates": [
          -58.3,
          -35.0667
        ]
      },
      "type": "Feature",
      "properties": {
        "hierarchy": [
          "tgn:1019393",
          "tgn:1001160",
          "tgn:7006477",
          "tgn:1000002",
          "tgn:7029392"
        ],
        "placetype": [
          "aat:300008347"
        ],
        "id": 1019393,
        "name:xx": "Domselaar"
      }
    },
    {
      "geometry": {
        "type": "Point",
        "coordinates": [
          -58.6333,
          -34.5
        ]
      },
      "type": "Feature",
      "properties": {
        "hierarchy": [
          "tgn:1019394",
          "tgn:1001160",
          "tgn:7006477",
          "tgn:1000002",
          "tgn:7029392"
        ],
        "placetype": [
          "aat:300008347"
        ],
        "id": 1019394,
        "name:xx": "Don Torcuato"
      }
    },
    {
      "geometry": {
        "type": "Point",
        "coordinates": [
          -62.7333,
          -26.6
        ]
      },
      "type": "Feature",
      "properties": {
        "hierarchy": [
          "tgn:1019395",
          "tgn:7006477",
          "tgn:1001526",
          "tgn:1000002",
          "tgn:7029392"
        ],
        "placetype": [
          "aat:300008347"
        ],
        "id": 1019395,
        "name:xx": "Donadeu"
      }
    },
    {
      "geometry": {
        "type": "Point",
        "coordinates": [
          -64.3,
          -35.9
        ]
      },
      "type": "Feature",
      "properties": {
        "hierarchy": [
          "tgn:1019396",
          "tgn:7006477",
          "tgn:1001375",
          "tgn:1000002",
          "tgn:7029392"
        ],
        "placetype": [
          "aat:300008347"
        ],
        "id": 1019396,
        "name:xx": "Eduardo Castex"
      }
    },
    {
      "geometry": {
        "type": "Point",
        "coordinates": [
          -59.1,
          -36.9667
        ]
      },
      "type": "Feature",
      "properties": {
        "hierarchy": [
          "tgn:1019397",
          "tgn:1001160",
          "tgn:7006477",
          "tgn:1000002",
          "tgn:7029392"
        ],
        "placetype": [
          "aat:300008347"
        ],
        "id": 1019397,
        "name:xx": "Egaña"
      }
    },
    {
      "geometry": {
        "type": "Point",
        "coordinates": [
          -65.7,
          -23.2
        ]
      },
      "type": "Feature",
      "properties": {
        "hierarchy": [
          "tgn:1019398",
          "tgn:7006477",
          "tgn:1001328",
          "tgn:1000002",
          "tgn:7029392"
        ],
        "placetype": [
          "aat:300008347"
        ],
        "id": 1019398,
        "name:xx": "El Aguilar"
      }
    },
    {
      "geometry": {
        "type": "Point",
        "coordinates": [
          -71.5833,
          -41.9833
        ]
      },
      "type": "Feature",
      "properties": {
        "hierarchy": [
          "tgn:1019399",
          "tgn:7006477",
          "tgn:7006348",
          "tgn:1000002",
          "tgn:7029392"
        ],
        "placetype": [
          "aat:300008347"
        ],
        "id": 1019399,
        "name:xx": "El Bolsón"
      }
    }
  ]
}
