{
  "geometry": {
    "type": "Point",
    "coordinates": [
      -72.7333,
      42.4667
    ]
  },
  "type": "Feature",
  "properties": {
    "hierarchy": [
      "tgn:2368452",
      "tgn:1000001",
      "tgn:7013942",
      "tgn:7012149",
      "tgn:7007517",
      "tgn:7029392"
    ],
    "placetype": [
      "aat:300008761"
    ],
    "id": 2368452,
    "name:xx": "Guinea Gulf"
  }
}
