{
  "type": "FeatureCollection",
  "features": [
    {
      "geometry": {
        "type": "Point",
        "coordinates": [
          -72.15,
          -35.266667
        ]
      },
      "type": "Feature",
      "properties": {
        "hierarchy": [
          "tgn:7319540",
          "tgn:1001705",
          "tgn:1000049",
          "tgn:1000002",
          "tgn:7029392"
        ],
        "placetype": [
          "aat:300008795"
        ],
        "id": 7319540,
        "name:xx": "Alta, Punta"
      }
    },
    {
      "geometry": {
        "type": "Point",
        "coordinates": [
          -71.1,
          -35.133333
        ]
      },
      "type": "Feature",
      "properties": {
        "hierarchy": [
          "tgn:7319541",
          "tgn:1001705",
          "tgn:1000049",
          "tgn:1000002",
          "tgn:7029392"
        ],
        "placetype": [
          "aat:300008795"
        ],
        "id": 7319541,
        "name:xx": "Alta, Punta"
      }
    },
    {
      "geometry": {
        "type": "Point",
        "coordinates": [
          -71.516667,
          -34.6
        ]
      },
      "type": "Feature",
      "properties": {
        "hierarchy": [
          "tgn:7319542",
          "tgn:1001695",
          "tgn:1000049",
          "tgn:1000002",
          "tgn:7029392"
        ],
        "placetype": [
          "aat:300008795"
        ],
        "id": 7319542,
        "name:xx": "Alta, Punta"
      }
    },
    {
      "geometry": {
        "type": "Point",
        "coordinates": [
          -71.05,
          -34.433333
        ]
      },
      "type": "Feature",
      "properties": {
        "hierarchy": [
          "tgn:7319543",
          "tgn:1001695",
          "tgn:1000049",
          "tgn:1000002",
          "tgn:7029392"
        ],
        "placetype": [
          "aat:300008795"
        ],
        "id": 7319543,
        "name:xx": "Alta, Punta"
      }
    },
    {
      "geometry": {
        "type": "Point",
        "coordinates": [
          -71,
          -34.316667
        ]
      },
      "type": "Feature",
      "properties": {
        "hierarchy": [
          "tgn:7319544",
          "tgn:1001695",
          "tgn:1000049",
          "tgn:1000002",
          "tgn:7029392"
        ],
        "placetype": [
          "aat:300008795"
        ],
        "id": 7319544,
        "name:xx": "Alta, Punta"
      }
    },
    {
      "geometry": {
        "type": "Point",
        "coordinates": [
          -70.85,
          -33.933333
        ]
      },
      "type": "Feature",
      "properties": {
        "hierarchy": [
          "tgn:7319545",
          "tgn:1001708",
          "tgn:1000049",
          "tgn:1000002",
          "tgn:7029392"
        ],
        "placetype": [
          "aat:300008795"
        ],
        "id": 7319545,
        "name:xx": "Alta, Punta"
      }
    },
    {
      "geometry": {
        "type": "Point",
        "coordinates": [
          -71.066667,
          -33.633333
        ]
      },
      "type": "Feature",
      "properties": {
        "hierarchy": [
          "tgn:7319546",
          "tgn:1001708",
          "tgn:1000049",
          "tgn:1000002",
          "tgn:7029392"
        ],
        "placetype": [
          "aat:300008795"
        ],
        "id": 7319546,
        "name:xx": "Alta, Punta"
      }
    },
    {
      "geometry": {
        "type": "Point",
        "coordinates": [
          -70.616667,
          -29.233333
        ]
      },
      "type": "Feature",
      "properties": {
        "hierarchy": [
          "tgn:7319547",
          "tgn:1001657",
          "tgn:1000049",
          "tgn:1000002",
          "tgn:7029392"
        ],
        "placetype": [
          "aat:300008795"
        ],
        "id": 7319547,
        "name:xx": "Alta, Punta"
      }
    },
    {
      "geometry": {
        "type": "Point",
        "coordinates": [
          -71.433333,
          -34.633333
        ]
      },
      "type": "Feature",
      "properties": {
        "hierarchy": [
          "tgn:7319548",
          "tgn:1001695",
          "tgn:1000049",
          "tgn:1000002",
          "tgn:7029392"
        ],
        "placetype": [
          "aat:300008777"
        ],
        "id": 7319548,
        "name:xx": "Alta, Punta"
      }
    },
    {
      "geometry": {
        "type": "Point",
        "coordinates": [
          -71.7,
          -34.116667
        ]
      },
      "type": "Feature",
      "properties": {
        "hierarchy": [
          "tgn:7319549",
          "tgn:1001695",
          "tgn:1000049",
          "tgn:1000002",
          "tgn:7029392"
        ],
        "placetype": [
          "aat:300008777"
        ],
        "id": 7319549,
        "name:xx": "Alta, Punta"
      }
    }
  ]
}
