{
  "geometry": {
    "type": "Point",
    "coordinates": [
      -76.2833,
      43.3667
    ]
  },
  "type": "Feature",
  "properties": {
    "hierarchy": [
      "tgn:1133197",
      "tgn:1000001",
      "tgn:7012149",
      "tgn:7007568",
      "tgn:7029392"
    ],
    "placetype": [
      "aat:300008706"
    ],
    "id": 1133197,
    "name:xx": "Fish Creek"
  }
}
