{
  "geometry": {
    "type": "Point",
    "coordinates": [
      -82.6667,
      35.3833
    ]
  },
  "type": "Feature",
  "properties": {
    "hierarchy": [
      "tgn:2129914",
      "tgn:1000001",
      "tgn:7012149",
      "tgn:2001504",
      "tgn:7007709",
      "tgn:7029392"
    ],
    "placetype": [
      "aat:300008761"
    ],
    "id": 2129914,
    "name:xx": "Allen Cove"
  }
}
