{
  "geometry": {
    "type": "Point",
    "coordinates": [
      121.0333,
      9.5833
    ]
  },
  "type": "Feature",
  "properties": {
    "hierarchy": [
      "tgn:1006688",
      "tgn:1000004",
      "tgn:1009904",
      "tgn:1001481",
      "tgn:1000135",
      "tgn:7029392"
    ],
    "placetype": [
      "aat:300008791"
    ],
    "id": 1006688,
    "name:xx": "Calusa Island"
  }
}
