{
  "geometry": {
    "type": "Point",
    "coordinates": [
      -120.3167,
      42.4333
    ]
  },
  "type": "Feature",
  "properties": {
    "hierarchy": [
      "tgn:2189822",
      "tgn:1000001",
      "tgn:7012149",
      "tgn:2001715",
      "tgn:7007708",
      "tgn:7029392"
    ],
    "placetype": [
      "aat:300008680"
    ],
    "id": 2189822,
    "name:xx": "Bowersox Lake"
  }
}
