{
  "geometry": {
    "type": "Point",
    "coordinates": [
      77.45,
      16.383333
    ]
  },
  "type": "Feature",
  "properties": {
    "hierarchy": [
      "tgn:7552758",
      "tgn:1001828",
      "tgn:1000004",
      "tgn:7000198",
      "tgn:7029392"
    ],
    "placetype": [
      "aat:300008347"
    ],
    "name:en": "Mūdumālā",
    "id": 7552758
  }
}
