{
  "geometry": {
    "type": "Point",
    "coordinates": [
      -110.5333,
      33.9333
    ]
  },
  "type": "Feature",
  "properties": {
    "hierarchy": [
      "tgn:2155211",
      "tgn:1000001",
      "tgn:7006451",
      "tgn:2000093",
      "tgn:7012149",
      "tgn:7029392"
    ],
    "placetype": [
      "aat:300008798"
    ],
    "id": 2155211,
    "name:xx": "Bear Mountain"
  }
}
