{
  "type": "FeatureCollection",
  "features": [
    {
      "geometry": {
        "type": "Point",
        "coordinates": [
          -71.033333,
          -33.9
        ]
      },
      "type": "Feature",
      "properties": {
        "hierarchy": [
          "tgn:7292470",
          "tgn:1001708",
          "tgn:1000049",
          "tgn:1000002",
          "tgn:7029392"
        ],
        "placetype": [
          "aat:300008795"
        ],
        "id": 7292470,
        "name:xx": "El Durazno, Cerro"
      }
    },
    {
      "geometry": {
        "type": "Point",
        "coordinates": [
          -70.533333,
          -33.833333
        ]
      },
      "type": "Feature",
      "properties": {
        "hierarchy": [
          "tgn:7292471",
          "tgn:1001708",
          "tgn:1000049",
          "tgn:1000002",
          "tgn:7029392"
        ],
        "placetype": [
          "aat:300008795"
        ],
        "id": 7292471,
        "name:xx": "El Durazno, Cerro"
      }
    },
    {
      "geometry": {
        "type": "Point",
        "coordinates": [
          -71.3,
          -33.216667
        ]
      },
      "type": "Feature",
      "properties": {
        "hierarchy": [
          "tgn:7292472",
          "tgn:1001768",
          "tgn:1000049",
          "tgn:1000002",
          "tgn:7029392"
        ],
        "placetype": [
          "aat:300008795"
        ],
        "id": 7292472,
        "name:xx": "El Durazno, Cerro"
      }
    },
    {
      "geometry": {
        "type": "Point",
        "coordinates": [
          -71.066667,
          -32.533333
        ]
      },
      "type": "Feature",
      "properties": {
        "hierarchy": [
          "tgn:7292473",
          "tgn:1001768",
          "tgn:1000049",
          "tgn:1000002",
          "tgn:7029392"
        ],
        "placetype": [
          "aat:300008798"
        ],
        "id": 7292473,
        "name:xx": "El Durazno, Alto"
      }
    },
    {
      "geometry": {
        "type": "Point",
        "coordinates": [
          -70.616667,
          -32.35
        ]
      },
      "type": "Feature",
      "properties": {
        "hierarchy": [
          "tgn:7292474",
          "tgn:1001768",
          "tgn:1000049",
          "tgn:1000002",
          "tgn:7029392"
        ],
        "placetype": [
          "aat:300008798"
        ],
        "id": 7292474,
        "name:xx": "El Durazno, Alto"
      }
    },
    {
      "geometry": {
        "type": "Point",
        "coordinates": [
          -71.3,
          -30.35
        ]
      },
      "type": "Feature",
      "properties": {
        "hierarchy": [
          "tgn:7292475",
          "tgn:1001657",
          "tgn:1000049",
          "tgn:1000002",
          "tgn:7029392"
        ],
        "placetype": [
          "aat:300387033"
        ],
        "id": 7292475,
        "name:xx": "El Durazno"
      }
    },
    {
      "geometry": {
        "type": "Point",
        "coordinates": [
          -69.65,
          -26.9
        ]
      },
      "type": "Feature",
      "properties": {
        "hierarchy": [
          "tgn:7292476",
          "tgn:1001630",
          "tgn:1000049",
          "tgn:1000002",
          "tgn:7029392"
        ],
        "placetype": [
          "aat:300008697"
        ],
        "id": 7292476,
        "name:xx": "El Durazno"
      }
    },
    {
      "geometry": {
        "type": "Point",
        "coordinates": [
          -70.683333,
          -30.016667
        ]
      },
      "type": "Feature",
      "properties": {
        "hierarchy": [
          "tgn:7292477",
          "tgn:1001657",
          "tgn:1000049",
          "tgn:1000002",
          "tgn:7029392"
        ],
        "placetype": [
          "aat:300007783"
        ],
        "id": 7292477,
        "name:xx": "El Durazno"
      }
    },
    {
      "geometry": {
        "type": "Point",
        "coordinates": [
          -72.566667,
          -36.133333
        ]
      },
      "type": "Feature",
      "properties": {
        "hierarchy": [
          "tgn:7292478",
          "tgn:1001637",
          "tgn:1000049",
          "tgn:1000002",
          "tgn:7029392"
        ],
        "placetype": [
          "aat:300008347"
        ],
        "id": 7292478,
        "name:xx": "El Durazno"
      }
    },
    {
      "geometry": {
        "type": "Point",
        "coordinates": [
          -71.366667,
          -34.15
        ]
      },
      "type": "Feature",
      "properties": {
        "hierarchy": [
          "tgn:7292479",
          "tgn:1001708",
          "tgn:1000049",
          "tgn:1000002",
          "tgn:7029392"
        ],
        "placetype": [
          "aat:300008347"
        ],
        "id": 7292479,
        "name:xx": "El Durazno"
      }
    }
  ]
}
