{
  "type": "FeatureCollection",
  "features": [
    {
      "geometry": {
        "type": "Point",
        "coordinates": [
          -86.85,
          37.9167
        ]
      },
      "type": "Feature",
      "properties": {
        "hierarchy": [
          "tgn:2784880",
          "tgn:1000001",
          "tgn:7012149",
          "tgn:2000795",
          "tgn:7007255",
          "tgn:7029392"
        ],
        "placetype": [
          "aat:300008706"
        ],
        "id": 2784880,
        "name:xx": "Yellow Creek"
      }
    },
    {
      "geometry": {
        "type": "Point",
        "coordinates": [
          -82.4833,
          37.9667
        ]
      },
      "type": "Feature",
      "properties": {
        "hierarchy": [
          "tgn:2784881",
          "tgn:1000001",
          "tgn:7012149",
          "tgn:2000809",
          "tgn:7007255",
          "tgn:7029392"
        ],
        "placetype": [
          "aat:300008706"
        ],
        "id": 2784881,
        "name:xx": "Yellow Creek"
      }
    },
    {
      "geometry": {
        "type": "Point",
        "coordinates": [
          -86.3333,
          42.1333
        ]
      },
      "type": "Feature",
      "properties": {
        "hierarchy": [
          "tgn:2784882",
          "tgn:1000001",
          "tgn:1002182",
          "tgn:7012149",
          "tgn:7007520",
          "tgn:7029392"
        ],
        "placetype": [
          "aat:300008706"
        ],
        "id": 2784882,
        "name:xx": "Yellow Creek"
      }
    },
    {
      "geometry": {
        "type": "Point",
        "coordinates": [
          -88.8167,
          31.7333
        ]
      },
      "type": "Feature",
      "properties": {
        "hierarchy": [
          "tgn:2784883",
          "tgn:1000001",
          "tgn:7012149",
          "tgn:2001162",
          "tgn:7007522",
          "tgn:7029392"
        ],
        "placetype": [
          "aat:300008706"
        ],
        "id": 2784883,
        "name:xx": "Yellow Creek"
      }
    },
    {
      "geometry": {
        "type": "Point",
        "coordinates": [
          -88.9,
          33.1833
        ]
      },
      "type": "Feature",
      "properties": {
        "hierarchy": [
          "tgn:2784884",
          "tgn:1000001",
          "tgn:7012149",
          "tgn:7007522",
          "tgn:7029392"
        ],
        "placetype": [
          "aat:300008706"
        ],
        "id": 2784884,
        "name:xx": "Yellow Creek"
      }
    },
    {
      "geometry": {
        "type": "Point",
        "coordinates": [
          -89.6167,
          32.75
        ]
      },
      "type": "Feature",
      "properties": {
        "hierarchy": [
          "tgn:2784885",
          "tgn:1000001",
          "tgn:7012149",
          "tgn:2001125",
          "tgn:7007522",
          "tgn:7029392"
        ],
        "placetype": [
          "aat:300008706"
        ],
        "id": 2784885,
        "name:xx": "Yellow Creek"
      }
    },
    {
      "geometry": {
        "type": "Point",
        "coordinates": [
          -93.8,
          38.0333
        ]
      },
      "type": "Feature",
      "properties": {
        "hierarchy": [
          "tgn:2784886",
          "tgn:1000001",
          "tgn:7012149",
          "tgn:2001239",
          "tgn:7007523",
          "tgn:7029392"
        ],
        "placetype": [
          "aat:300008706"
        ],
        "id": 2784886,
        "name:xx": "Yellow Creek"
      }
    },
    {
      "geometry": {
        "type": "Point",
        "coordinates": [
          -93.05,
          39.65
        ]
      },
      "type": "Feature",
      "properties": {
        "hierarchy": [
          "tgn:2784887",
          "tgn:1000001",
          "tgn:2001184",
          "tgn:7012149",
          "tgn:7007523",
          "tgn:7029392"
        ],
        "placetype": [
          "aat:300008706"
        ],
        "id": 2784887,
        "name:xx": "Yellow Creek"
      }
    },
    {
      "geometry": {
        "type": "Point",
        "coordinates": [
          -75.1,
          44.2167
        ]
      },
      "type": "Feature",
      "properties": {
        "hierarchy": [
          "tgn:2784888",
          "tgn:1000001",
          "tgn:7012149",
          "tgn:7016021",
          "tgn:7007568",
          "tgn:7029392"
        ],
        "placetype": [
          "aat:300008706"
        ],
        "id": 2784888,
        "name:xx": "Yellow Creek"
      }
    },
    {
      "geometry": {
        "type": "Point",
        "coordinates": [
          -75.1167,
          43.7667
        ]
      },
      "type": "Feature",
      "properties": {
        "hierarchy": [
          "tgn:2784889",
          "tgn:1000001",
          "tgn:7012149",
          "tgn:1002593",
          "tgn:7007568",
          "tgn:7029392"
        ],
        "placetype": [
          "aat:300008706"
        ],
        "id": 2784889,
        "name:xx": "Yellow Creek"
      }
    }
  ]
}
