{
  "geometry": {
    "type": "Point",
    "coordinates": [
      82.433333,
      18.55
    ]
  },
  "type": "Feature",
  "properties": {
    "hierarchy": [
      "tgn:7545108",
      "tgn:1000004",
      "tgn:7000198",
      "tgn:7016694",
      "tgn:7029392"
    ],
    "placetype": [
      "aat:300008347"
    ],
    "name:en": "Bādigarh",
    "id": 7545108
  }
}
