{
  "geometry": {
    "type": "Point",
    "coordinates": [
      -84.9667,
      46.3333
    ]
  },
  "type": "Feature",
  "properties": {
    "hierarchy": [
      "tgn:2699491",
      "tgn:1000001",
      "tgn:2000952",
      "tgn:7012149",
      "tgn:7007520",
      "tgn:7029392"
    ],
    "placetype": [
      "aat:300008347"
    ],
    "id": 2699491,
    "name:xx": "Strongs Corner"
  }
}
