{
  "geometry": {
    "type": "Point",
    "coordinates": [
      -98.15,
      40.7667
    ]
  },
  "type": "Feature",
  "properties": {
    "hierarchy": [
      "tgn:2062177",
      "tgn:1000001",
      "tgn:2001356",
      "tgn:7012149",
      "tgn:7007525",
      "tgn:7029392"
    ],
    "placetype": [
      "aat:300008347"
    ],
    "id": 2062177,
    "name:xx": "Giltner"
  }
}
