{
  "geometry": {
    "type": "Point",
    "coordinates": [
      -82.8333,
      29.7667
    ]
  },
  "type": "Feature",
  "properties": {
    "hierarchy": [
      "tgn:2379283",
      "tgn:1000001",
      "tgn:2000269",
      "tgn:7012149",
      "tgn:7007240",
      "tgn:7029392"
    ],
    "placetype": [
      "aat:300008347"
    ],
    "id": 2379283,
    "name:xx": "Harvard"
  }
}
