{
  "geometry": {
    "type": "Point",
    "coordinates": [
      3.3167,
      43.3167
    ]
  },
  "type": "Feature",
  "properties": {
    "hierarchy": [
      "tgn:4009476",
      "tgn:1000003",
      "tgn:7002885",
      "tgn:1000070",
      "tgn:7029392"
    ],
    "placetype": [
      "aat:300008347"
    ],
    "id": 4009476,
    "name:xx": "Roujan"
  }
}
