{
  "geometry": {
    "type": "Point",
    "coordinates": [
      -77.5667,
      39.9167
    ]
  },
  "type": "Feature",
  "properties": {
    "hierarchy": [
      "tgn:2252848",
      "tgn:1000001",
      "tgn:7012149",
      "tgn:1002387",
      "tgn:7007710",
      "tgn:7029392"
    ],
    "placetype": [
      "aat:300008791"
    ],
    "id": 2252848,
    "name:xx": "Conococheague Island"
  }
}
