{
  "type": "FeatureCollection",
  "features": [
    {
      "geometry": {
        "type": "Point",
        "coordinates": [
          -74.45,
          40.4333
        ]
      },
      "type": "Feature",
      "properties": {
        "hierarchy": [
          "tgn:2064581",
          "tgn:1000001",
          "tgn:2064574",
          "tgn:1002666",
          "tgn:7012149",
          "tgn:7007565",
          "tgn:7029392"
        ],
        "placetype": [
          "aat:300000745"
        ],
        "id": 2064581,
        "name:xx": "Farrington Lake Heights"
      }
    },
    {
      "geometry": {
        "type": "Point",
        "coordinates": [
          -74.3833,
          40.4167
        ]
      },
      "type": "Feature",
      "properties": {
        "hierarchy": [
          "tgn:2064585",
          "tgn:1000001",
          "tgn:2064574",
          "tgn:1002666",
          "tgn:7012149",
          "tgn:7007565",
          "tgn:7029392"
        ],
        "placetype": [
          "aat:300000745"
        ],
        "id": 2064585,
        "name:xx": "Newton Heights"
      }
    },
    {
      "geometry": {
        "type": "Point",
        "coordinates": [
          -74.25,
          40.2667
        ]
      },
      "type": "Feature",
      "properties": {
        "hierarchy": [
          "tgn:2064587",
          "tgn:1000001",
          "tgn:7014090",
          "tgn:7012149",
          "tgn:7007565",
          "tgn:7029392"
        ],
        "placetype": [
          "aat:300008347"
        ],
        "id": 2064587,
        "name:xx": "East Freehold"
      }
    },
    {
      "geometry": {
        "type": "Point",
        "coordinates": [
          -74.35,
          40.8167
        ]
      },
      "type": "Feature",
      "properties": {
        "hierarchy": [
          "tgn:2064588",
          "tgn:1000001",
          "tgn:1002695",
          "tgn:7012149",
          "tgn:7007565",
          "tgn:7029392"
        ],
        "placetype": [
          "aat:300008347"
        ],
        "id": 2064588,
        "name:xx": "East Hanover"
      }
    }
  ]
}
