{
  "geometry": {
    "type": "Point",
    "coordinates": [
      -84.1667,
      44.7333
    ]
  },
  "type": "Feature",
  "properties": {
    "hierarchy": [
      "tgn:2234755",
      "tgn:1000001",
      "tgn:7012149",
      "tgn:2000988",
      "tgn:7007520",
      "tgn:7029392"
    ],
    "placetype": [
      "aat:300008706"
    ],
    "id": 2234755,
    "name:xx": "Cherry Creek"
  }
}
