{
  "geometry": {
    "type": "Point",
    "coordinates": [
      -120.5167,
      42.55
    ]
  },
  "type": "Feature",
  "properties": {
    "hierarchy": [
      "tgn:2328368",
      "tgn:1000001",
      "tgn:7012149",
      "tgn:2001715",
      "tgn:7007708",
      "tgn:7029392"
    ],
    "placetype": [
      "aat:300008706"
    ],
    "id": 2328368,
    "name:xx": "Fisher Creek"
  }
}
