{
  "geometry": {
    "type": "Point",
    "coordinates": [
      -109.25,
      42.65
    ]
  },
  "type": "Feature",
  "properties": {
    "hierarchy": [
      "tgn:2295661",
      "tgn:1000001",
      "tgn:7012149",
      "tgn:2002382",
      "tgn:7007923",
      "tgn:7029392"
    ],
    "placetype": [
      "aat:300008706"
    ],
    "id": 2295661,
    "name:xx": "Driveway Creek"
  }
}
