{
  "type": "FeatureCollection",
  "features": [
    {
      "geometry": {
        "type": "Point",
        "coordinates": [
          -74.3833,
          40.4833
        ]
      },
      "type": "Feature",
      "properties": {
        "hierarchy": [
          "tgn:2064631",
          "tgn:1000001",
          "tgn:2064626",
          "tgn:1002666",
          "tgn:7012149",
          "tgn:7007565",
          "tgn:7029392"
        ],
        "placetype": [
          "aat:300000745"
        ],
        "id": 2064631,
        "name:xx": "Greensand"
      }
    },
    {
      "geometry": {
        "type": "Point",
        "coordinates": [
          -74.3333,
          40.55
        ]
      },
      "type": "Feature",
      "properties": {
        "hierarchy": [
          "tgn:2064632",
          "tgn:1000001",
          "tgn:2064626",
          "tgn:1002666",
          "tgn:7012149",
          "tgn:7007565",
          "tgn:7029392"
        ],
        "placetype": [
          "aat:300000745"
        ],
        "id": 2064632,
        "name:xx": "Menlo Park"
      }
    },
    {
      "geometry": {
        "type": "Point",
        "coordinates": [
          -74.3667,
          40.5
        ]
      },
      "type": "Feature",
      "properties": {
        "hierarchy": [
          "tgn:2064634",
          "tgn:1000001",
          "tgn:2064626",
          "tgn:1002666",
          "tgn:7012149",
          "tgn:7007565",
          "tgn:7029392"
        ],
        "placetype": [
          "aat:300000745"
        ],
        "id": 2064634,
        "name:xx": "Nixon"
      }
    },
    {
      "geometry": {
        "type": "Point",
        "coordinates": [
          -74.3667,
          40.6
        ]
      },
      "type": "Feature",
      "properties": {
        "hierarchy": [
          "tgn:2064635",
          "tgn:1000001",
          "tgn:2064626",
          "tgn:1002666",
          "tgn:7012149",
          "tgn:7007565",
          "tgn:7029392"
        ],
        "placetype": [
          "aat:300000745"
        ],
        "id": 2064635,
        "name:xx": "North Edison"
      }
    },
    {
      "geometry": {
        "type": "Point",
        "coordinates": [
          -74.3667,
          40.5667
        ]
      },
      "type": "Feature",
      "properties": {
        "hierarchy": [
          "tgn:2064636",
          "tgn:1000001",
          "tgn:2064626",
          "tgn:1002666",
          "tgn:7012149",
          "tgn:7007565",
          "tgn:7029392"
        ],
        "placetype": [
          "aat:300000745"
        ],
        "id": 2064636,
        "name:xx": "Oak Tree"
      }
    },
    {
      "geometry": {
        "type": "Point",
        "coordinates": [
          -74.3,
          40.4667
        ]
      },
      "type": "Feature",
      "properties": {
        "hierarchy": [
          "tgn:2064637",
          "tgn:1000001",
          "tgn:2064626",
          "tgn:1002666",
          "tgn:7012149",
          "tgn:7007565",
          "tgn:7029392"
        ],
        "placetype": [
          "aat:300000745"
        ],
        "id": 2064637,
        "name:xx": "Phoenix"
      }
    },
    {
      "geometry": {
        "type": "Point",
        "coordinates": [
          -74.5333,
          40.4
        ]
      },
      "type": "Feature",
      "properties": {
        "hierarchy": [
          "tgn:2064639",
          "tgn:1000001",
          "tgn:2064626",
          "tgn:1002666",
          "tgn:7012149",
          "tgn:7007565",
          "tgn:7029392"
        ],
        "placetype": [
          "aat:300000745"
        ],
        "id": 2064639,
        "name:xx": "Sand Hills"
      }
    }
  ]
}
