{
  "geometry": {
    "type": "Point",
    "coordinates": [
      13.3667,
      -10.0333
    ]
  },
  "type": "Feature",
  "properties": {
    "hierarchy": [
      "tgn:1011124",
      "tgn:1000811",
      "tgn:7001242",
      "tgn:1000149",
      "tgn:7029392"
    ],
    "placetype": [
      "aat:300008850"
    ],
    "id": 1011124,
    "name:xx": "São Braz, Cabo de"
  }
}
