{
  "geometry": {
    "type": "Point",
    "coordinates": [
      -108.85,
      30.55
    ]
  },
  "type": "Feature",
  "properties": {
    "hierarchy": [
      "tgn:7436654",
      "tgn:1000001",
      "tgn:1001960",
      "tgn:7005560",
      "tgn:7029392"
    ],
    "placetype": [
      "aat:300387007"
    ],
    "id": 7436654,
    "name:xx": "Tasábire"
  }
}
