{
  "geometry": {
    "type": "Point",
    "coordinates": [
      69.8167,
      41.7167
    ]
  },
  "type": "Feature",
  "properties": {
    "hierarchy": [
      "tgn:1105764",
      "tgn:1000004",
      "tgn:7012947",
      "tgn:7014786",
      "tgn:7029392"
    ],
    "placetype": [
      "aat:300008795"
    ],
    "id": 1105764,
    "name:xx": "Mynbulak, gora"
  }
}
