{
  "geometry": {
    "type": "Point",
    "coordinates": [
      -107.0667,
      33.9333
    ]
  },
  "type": "Feature",
  "properties": {
    "hierarchy": [
      "tgn:2643174",
      "tgn:1000001",
      "tgn:7012149",
      "tgn:2001456",
      "tgn:7007566",
      "tgn:7029392"
    ],
    "placetype": [
      "aat:300000390"
    ],
    "id": 2643174,
    "name:xx": "Sandy Claims"
  }
}
