{
  "geometry": {
    "type": "Point",
    "coordinates": [
      -81.5167,
      34.4667
    ]
  },
  "type": "Feature",
  "properties": {
    "hierarchy": [
      "tgn:2577240",
      "tgn:1000001",
      "tgn:7012149",
      "tgn:7007712",
      "tgn:7029392"
    ],
    "placetype": [
      "aat:300008706"
    ],
    "id": 2577240,
    "name:xx": "Peters Creek"
  }
}
