{
  "geometry": {
    "type": "Point",
    "coordinates": [
      -122.35,
      48.3833
    ]
  },
  "type": "Feature",
  "properties": {
    "hierarchy": [
      "tgn:2666823",
      "tgn:1000001",
      "tgn:7012149",
      "tgn:7014510",
      "tgn:7007920",
      "tgn:7029392"
    ],
    "placetype": [
      "aat:300008347"
    ],
    "id": 2666823,
    "name:xx": "Skagit City"
  }
}
