{
  "geometry": {
    "type": "Point",
    "coordinates": [
      -85.1333,
      30.1667
    ]
  },
  "type": "Feature",
  "properties": {
    "hierarchy": [
      "tgn:2434550",
      "tgn:1000001",
      "tgn:7012149",
      "tgn:2000278",
      "tgn:7007240",
      "tgn:7029392"
    ],
    "placetype": [
      "aat:300008706"
    ],
    "id": 2434550,
    "name:xx": "Kennedy Creek"
  }
}
