{
  "type": "FeatureCollection",
  "features": [
    {
      "geometry": {
        "type": "Point",
        "coordinates": [
          13.5,
          42.266667
        ]
      },
      "type": "Feature",
      "properties": {
        "hierarchy": [
          "tgn:7046500",
          "tgn:7009084",
          "tgn:7004154",
          "tgn:1000003",
          "tgn:1000080",
          "tgn:7029392"
        ],
        "placetype": [
          "aat:300008347"
        ],
        "id": 7046500,
        "name:xx": "Casentino"
      }
    },
    {
      "geometry": {
        "type": "Point",
        "coordinates": [
          11.483333,
          45.2
        ]
      },
      "type": "Feature",
      "properties": {
        "hierarchy": [
          "tgn:7046503",
          "tgn:7002994",
          "tgn:1000003",
          "tgn:7002997",
          "tgn:1000080",
          "tgn:7029392"
        ],
        "placetype": [
          "aat:300008347"
        ],
        "id": 7046503,
        "name:xx": "Case Negri"
      }
    },
    {
      "geometry": {
        "type": "Point",
        "coordinates": [
          14.95,
          38.083333
        ]
      },
      "type": "Feature",
      "properties": {
        "hierarchy": [
          "tgn:7046504",
          "tgn:1000003",
          "tgn:7003122",
          "tgn:7003157",
          "tgn:1000080",
          "tgn:7029392"
        ],
        "placetype": [
          "aat:300008347"
        ],
        "id": 7046504,
        "name:xx": "Case Nasidi"
      }
    },
    {
      "geometry": {
        "type": "Point",
        "coordinates": [
          16.733333,
          38.933333
        ]
      },
      "type": "Feature",
      "properties": {
        "hierarchy": [
          "tgn:7046505",
          "tgn:1003447",
          "tgn:7007850",
          "tgn:1000003",
          "tgn:1000080",
          "tgn:7029392"
        ],
        "placetype": [
          "aat:300008347"
        ],
        "id": 7046505,
        "name:xx": "Case Mortille"
      }
    },
    {
      "geometry": {
        "type": "Point",
        "coordinates": [
          12.15,
          45.55
        ]
      },
      "type": "Feature",
      "properties": {
        "hierarchy": [
          "tgn:7046506",
          "tgn:7003006",
          "tgn:1000003",
          "tgn:7002997",
          "tgn:1000080",
          "tgn:7029392"
        ],
        "placetype": [
          "aat:300008347"
        ],
        "id": 7046506,
        "name:xx": "Case Morchio"
      }
    },
    {
      "geometry": {
        "type": "Point",
        "coordinates": [
          12.466667,
          37.883333
        ]
      },
      "type": "Feature",
      "properties": {
        "hierarchy": [
          "tgn:7046507",
          "tgn:1000003",
          "tgn:7003122",
          "tgn:1001762",
          "tgn:1000080",
          "tgn:7029392"
        ],
        "placetype": [
          "aat:300008347"
        ],
        "id": 7046507,
        "name:xx": "Case Milazzo"
      }
    },
    {
      "geometry": {
        "type": "Point",
        "coordinates": [
          12,
          45.066667
        ]
      },
      "type": "Feature",
      "properties": {
        "hierarchy": [
          "tgn:7046508",
          "tgn:7002995",
          "tgn:1000003",
          "tgn:7002997",
          "tgn:1000080",
          "tgn:7029392"
        ],
        "placetype": [
          "aat:300008347"
        ],
        "id": 7046508,
        "name:xx": "Case Matte"
      }
    },
    {
      "geometry": {
        "type": "Point",
        "coordinates": [
          12.3,
          42.75
        ]
      },
      "type": "Feature",
      "properties": {
        "hierarchy": [
          "tgn:7046509",
          "tgn:7003170",
          "tgn:1000003",
          "tgn:7003125",
          "tgn:1000080",
          "tgn:7029392"
        ],
        "placetype": [
          "aat:300008347"
        ],
        "id": 7046509,
        "name:xx": "Casemascie"
      }
    }
  ]
}
