{
  "geometry": {
    "type": "Point",
    "coordinates": [
      -91.6833,
      38.1333
    ]
  },
  "type": "Feature",
  "properties": {
    "hierarchy": [
      "tgn:2551797",
      "tgn:1000001",
      "tgn:7012149",
      "tgn:1002629",
      "tgn:7007523",
      "tgn:7029392"
    ],
    "placetype": [
      "aat:300006191"
    ],
    "id": 2551797,
    "name:xx": "Number 69 Lake"
  }
}
