{
  "geometry": {
    "type": "Point",
    "coordinates": [
      -80.6833,
      35.0667
    ]
  },
  "type": "Feature",
  "properties": {
    "hierarchy": [
      "tgn:2277428",
      "tgn:1000001",
      "tgn:7012149",
      "tgn:2001546",
      "tgn:7007709",
      "tgn:7029392"
    ],
    "placetype": [
      "aat:300008706"
    ],
    "id": 2277428,
    "name:xx": "Davis Mine Creek"
  }
}
