{
  "geometry": {
    "type": "Point",
    "coordinates": [
      -108.1667,
      40.1667
    ]
  },
  "type": "Feature",
  "properties": {
    "hierarchy": [
      "tgn:2250691",
      "tgn:1000001",
      "tgn:7012149",
      "tgn:7007158",
      "tgn:2000243",
      "tgn:7029392"
    ],
    "placetype": [
      "aat:300008798"
    ],
    "id": 2250691,
    "name:xx": "Colorow Mountain"
  }
}
