{
  "geometry": {
    "type": "Point",
    "coordinates": [
      -81.7167,
      33.8167
    ]
  },
  "type": "Feature",
  "properties": {
    "hierarchy": [
      "tgn:2618020",
      "tgn:1000001",
      "tgn:7013677",
      "tgn:7012149",
      "tgn:7007712",
      "tgn:7029392"
    ],
    "placetype": [
      "aat:300006191"
    ],
    "id": 2618020,
    "name:xx": "Ridgeview Lake"
  }
}
