{
  "geometry": {
    "type": "Point",
    "coordinates": [
      21.5833,
      44.75
    ]
  },
  "type": "Feature",
  "properties": {
    "hierarchy": [
      "tgn:1128508",
      "tgn:1000003",
      "tgn:7006669",
      "tgn:7029392"
    ],
    "placetype": [
      "aat:300008707"
    ],
    "id": 1128508,
    "name:xx": "Pek"
  }
}
