{
  "geometry": {
    "type": "Point",
    "coordinates": [
      -108.7167,
      45.25
    ]
  },
  "type": "Feature",
  "properties": {
    "hierarchy": [
      "tgn:2678159",
      "tgn:1000001",
      "tgn:2001264",
      "tgn:7012149",
      "tgn:7007524",
      "tgn:7029392"
    ],
    "placetype": [
      "aat:300008706"
    ],
    "id": 2678159,
    "name:xx": "South Fork Bluewater Creek"
  }
}
