{
  "geometry": {
    "type": "Point",
    "coordinates": [
      32.433333,
      30.016667
    ]
  },
  "type": "Feature",
  "properties": {
    "hierarchy": [
      "tgn:7525252",
      "tgn:7001242",
      "tgn:7016833",
      "tgn:1001110",
      "tgn:7029392"
    ],
    "placetype": [
      "aat:300379998"
    ],
    "name:en": "Baḩḩārah, Wādī al",
    "id": 7525252
  }
}
