{
  "geometry": {
    "type": "Point",
    "coordinates": [
      -91.5333,
      36.1833
    ]
  },
  "type": "Feature",
  "properties": {
    "hierarchy": [
      "tgn:2438416",
      "tgn:1000001",
      "tgn:7016172",
      "tgn:7012149",
      "tgn:2000172",
      "tgn:7029392"
    ],
    "placetype": [
      "aat:300008347"
    ],
    "id": 2438416,
    "name:xx": "Kings Mills"
  }
}
