{
  "type": "FeatureCollection",
  "features": [
    {
      "geometry": {
        "type": "Point",
        "coordinates": [
          6.15,
          52.366667
        ]
      },
      "type": "Feature",
      "properties": {
        "hierarchy": [
          "tgn:7268810",
          "tgn:1000003",
          "tgn:7003626",
          "tgn:7016845",
          "tgn:7029392"
        ],
        "placetype": [
          "aat:300007836"
        ],
        "name:nl": "Plattenbergerbrug",
        "id": 7268810
      }
    },
    {
      "geometry": {
        "type": "Point",
        "coordinates": [
          4.3,
          51.4
        ]
      },
      "type": "Feature",
      "properties": {
        "hierarchy": [
          "tgn:7268811",
          "tgn:1000003",
          "tgn:7003624",
          "tgn:7016845",
          "tgn:7029392"
        ],
        "placetype": [
          "aat:300006163"
        ],
        "name:nl": "Noordpolder",
        "id": 7268811
      }
    },
    {
      "geometry": {
        "type": "Point",
        "coordinates": [
          3.816667,
          51.4
        ]
      },
      "type": "Feature",
      "properties": {
        "hierarchy": [
          "tgn:7268812",
          "tgn:1000003",
          "tgn:7003635",
          "tgn:7016845",
          "tgn:7029392"
        ],
        "placetype": [
          "aat:300006163"
        ],
        "name:nl": "Noordpolder",
        "id": 7268812
      }
    },
    {
      "geometry": {
        "type": "Point",
        "coordinates": [
          6.2,
          53.233333
        ]
      },
      "type": "Feature",
      "properties": {
        "hierarchy": [
          "tgn:7268813",
          "tgn:7003616",
          "tgn:1000003",
          "tgn:7016845",
          "tgn:7029392"
        ],
        "placetype": [
          "aat:300387200"
        ],
        "name:nl": "Noordpolder",
        "id": 7268813
      }
    },
    {
      "geometry": {
        "type": "Point",
        "coordinates": [
          4.116667,
          51.683333
        ]
      },
      "type": "Feature",
      "properties": {
        "hierarchy": [
          "tgn:7268814",
          "tgn:1000003",
          "tgn:7003635",
          "tgn:7016845",
          "tgn:7029392"
        ],
        "placetype": [
          "aat:300132350"
        ],
        "name:nl": "Noordplaten",
        "id": 7268814
      }
    },
    {
      "geometry": {
        "type": "Point",
        "coordinates": [
          5.966667,
          51.2
        ]
      },
      "type": "Feature",
      "properties": {
        "hierarchy": [
          "tgn:7268815",
          "tgn:1000003",
          "tgn:7003622",
          "tgn:7016845",
          "tgn:7029392"
        ],
        "placetype": [
          "aat:300008816"
        ],
        "name:nl": "Noordplas",
        "id": 7268815
      }
    },
    {
      "geometry": {
        "type": "Point",
        "coordinates": [
          4.016667,
          51.85
        ]
      },
      "type": "Feature",
      "properties": {
        "hierarchy": [
          "tgn:7268816",
          "tgn:1000003",
          "tgn:7003632",
          "tgn:7016845",
          "tgn:7029392"
        ],
        "placetype": [
          "aat:300387026"
        ],
        "name:nl": "Noord Pampus",
        "id": 7268816
      }
    },
    {
      "geometry": {
        "type": "Point",
        "coordinates": [
          4.516667,
          51.783333
        ]
      },
      "type": "Feature",
      "properties": {
        "hierarchy": [
          "tgn:7268817",
          "tgn:1000003",
          "tgn:7003632",
          "tgn:7016845",
          "tgn:7029392"
        ],
        "placetype": [
          "aat:300387200"
        ],
        "name:nl": "Noord-Oudeland",
        "id": 7268817
      }
    },
    {
      "geometry": {
        "type": "Point",
        "coordinates": [
          5.75,
          52.7
        ]
      },
      "type": "Feature",
      "properties": {
        "hierarchy": [
          "tgn:7268819",
          "tgn:7003615",
          "tgn:1000003",
          "tgn:7016845",
          "tgn:7029392"
        ],
        "placetype": [
          "aat:300006163"
        ],
        "name:nl": "Noordoostpolder",
        "id": 7268819
      }
    }
  ]
}
