{
  "geometry": {
    "type": "Point",
    "coordinates": [
      78.704167,
      29.795
    ]
  },
  "type": "Feature",
  "properties": {
    "hierarchy": [
      "tgn:7567952",
      "tgn:1000004",
      "tgn:7000198",
      "tgn:7031786",
      "tgn:7029392"
    ],
    "placetype": [
      "aat:300008699"
    ],
    "name:en": "Kadūri Gād",
    "id": 7567952
  }
}
