{
  "geometry": {
    "type": "Point",
    "coordinates": [
      -91.1333,
      37.6333
    ]
  },
  "type": "Feature",
  "properties": {
    "hierarchy": [
      "tgn:2611852",
      "tgn:1000001",
      "tgn:7012149",
      "tgn:2001207",
      "tgn:7007523",
      "tgn:7029392"
    ],
    "placetype": [
      "aat:300008347"
    ],
    "id": 2611852,
    "name:xx": "Red Point"
  }
}
