{
  "geometry": {
    "type": "Point",
    "coordinates": [
      4.55,
      52.05
    ]
  },
  "type": "Feature",
  "properties": {
    "hierarchy": [
      "tgn:7260376",
      "tgn:1000003",
      "tgn:7003632",
      "tgn:7016845",
      "tgn:7029392"
    ],
    "placetype": [
      "aat:300008347"
    ],
    "name:nl": "De Kruisweg",
    "id": 7260376
  }
}
