{
  "geometry": {
    "type": "Point",
    "coordinates": [
      -86.2833,
      32.3667
    ]
  },
  "type": "Feature",
  "properties": {
    "hierarchy": [
      "tgn:2264988",
      "tgn:7002659",
      "tgn:1000001",
      "tgn:7012149",
      "tgn:2000050",
      "tgn:7029392"
    ],
    "placetype": [
      "aat:300386845"
    ],
    "id": 2264988,
    "name:xx": "Cramton Bowl"
  }
}
