{
  "type": "FeatureCollection",
  "features": [
    {
      "geometry": {
        "type": "Point",
        "coordinates": [
          -3.333333,
          56.15
        ]
      },
      "type": "Feature",
      "properties": {
        "hierarchy": [
          "tgn:7009600",
          "tgn:7002444",
          "tgn:1000003",
          "tgn:7008076",
          "tgn:7008591",
          "tgn:7029392"
        ],
        "placetype": [
          "aat:300008347",
          "aat:300008375"
        ],
        "name:en": "Ballingry",
        "id": 7009600
      }
    },
    {
      "geometry": {
        "type": "Point",
        "coordinates": [
          -3.9,
          56.1
        ]
      },
      "type": "Feature",
      "properties": {
        "hierarchy": [
          "tgn:7009601",
          "tgn:7002444",
          "tgn:1000003",
          "tgn:7019106",
          "tgn:7008591",
          "tgn:7029392"
        ],
        "placetype": [
          "aat:300000835"
        ],
        "id": 7009601,
        "name:xx": "Bannockburn Battlesite"
      }
    },
    {
      "geometry": {
        "type": "Point",
        "coordinates": [
          -3.766667,
          56
        ]
      },
      "type": "Feature",
      "properties": {
        "hierarchy": [
          "tgn:7009602",
          "tgn:7002444",
          "tgn:1000003",
          "tgn:7019106",
          "tgn:7008591",
          "tgn:7029392"
        ],
        "placetype": [
          "aat:300008347",
          "aat:300000835",
          "aat:300387305",
          "aat:300387220",
          "aat:300008375",
          "aat:300387302"
        ],
        "name:en": "Falkirk",
        "id": 7009602
      }
    },
    {
      "geometry": {
        "type": "Point",
        "coordinates": [
          -2.5,
          43
        ]
      },
      "type": "Feature",
      "properties": {
        "hierarchy": [
          "tgn:7009604",
          "tgn:1000003",
          "tgn:1000095",
          "tgn:7029392"
        ],
        "placetype": [
          "aat:300387064",
          "aat:300387113",
          "aat:300387346"
        ],
        "name:en": "Basque Provinces",
        "id": 7009604,
        "name:es": "País Vasco"
      }
    },
    {
      "geometry": {
        "type": "Point",
        "coordinates": [
          -3.95,
          56.15
        ]
      },
      "type": "Feature",
      "properties": {
        "hierarchy": [
          "tgn:7009605",
          "tgn:7002444",
          "tgn:1000003",
          "tgn:5000460",
          "tgn:7008591",
          "tgn:7029392"
        ],
        "placetype": [
          "aat:300008347"
        ],
        "name:en": "Bridge of Allan",
        "id": 7009605
      }
    },
    {
      "geometry": {
        "type": "Point",
        "coordinates": [
          -3.966667,
          56.2
        ]
      },
      "type": "Feature",
      "properties": {
        "hierarchy": [
          "tgn:7009606",
          "tgn:7002444",
          "tgn:1000003",
          "tgn:5000460",
          "tgn:7008591",
          "tgn:7029392"
        ],
        "placetype": [
          "aat:300008347"
        ],
        "name:en": "Dunblane",
        "id": 7009606
      }
    },
    {
      "geometry": {
        "type": "Point",
        "coordinates": [
          -3.95,
          56.116667
        ]
      },
      "type": "Feature",
      "properties": {
        "hierarchy": [
          "tgn:7009609",
          "tgn:7002444",
          "tgn:1000003",
          "tgn:5000460",
          "tgn:7008591",
          "tgn:7029392"
        ],
        "placetype": [
          "aat:300008347",
          "aat:300387512",
          "aat:300387220",
          "aat:300008375"
        ],
        "name:en": "Stirling",
        "id": 7009609
      }
    }
  ]
}
