{
  "geometry": {
    "type": "Point",
    "coordinates": [
      58.85,
      32.75
    ]
  },
  "type": "Feature",
  "properties": {
    "hierarchy": [
      "tgn:1079087",
      "tgn:1000004",
      "tgn:7016768",
      "tgn:7000231",
      "tgn:7029392"
    ],
    "placetype": [
      "aat:300008347"
    ],
    "id": 1079087,
    "name:xx": "Fedeshk"
  }
}
