{
  "geometry": {
    "type": "Point",
    "coordinates": [
      -75.8333,
      42.6833
    ]
  },
  "type": "Feature",
  "properties": {
    "hierarchy": [
      "tgn:2351326",
      "tgn:1000001",
      "tgn:1002262",
      "tgn:7012149",
      "tgn:7007568",
      "tgn:7029392"
    ],
    "placetype": [
      "aat:300008699"
    ],
    "id": 2351326,
    "name:xx": "Glen Brook"
  }
}
