{
  "geometry": {
    "type": "Point",
    "coordinates": [
      -95.0667,
      30.1667
    ]
  },
  "type": "Feature",
  "properties": {
    "hierarchy": [
      "tgn:2651018",
      "tgn:1000001",
      "tgn:7012149",
      "tgn:1002595",
      "tgn:7007826",
      "tgn:7029392"
    ],
    "placetype": [
      "aat:300008905"
    ],
    "id": 2651018,
    "name:xx": "Second Pond"
  }
}
