{
  "geometry": {
    "type": "Point",
    "coordinates": [
      -84.3833,
      34.1167
    ]
  },
  "type": "Feature",
  "properties": {
    "hierarchy": [
      "tgn:2137636",
      "tgn:1000001",
      "tgn:7012149",
      "tgn:2000351",
      "tgn:7007248",
      "tgn:7029392"
    ],
    "placetype": [
      "aat:300008347"
    ],
    "id": 2137636,
    "name:xx": "Arnold Mill"
  }
}
