{
  "geometry": {
    "type": "Point",
    "coordinates": [
      -83.2333,
      36.3667
    ]
  },
  "type": "Feature",
  "properties": {
    "hierarchy": [
      "tgn:2583532",
      "tgn:1000001",
      "tgn:7012149",
      "tgn:2001873",
      "tgn:7007825",
      "tgn:7029392"
    ],
    "placetype": [
      "aat:300266640"
    ],
    "id": 2583532,
    "name:xx": "Pine Ridge"
  }
}
