{
  "geometry": {
    "type": "Point",
    "coordinates": [
      100.2833,
      31.65
    ]
  },
  "type": "Feature",
  "properties": {
    "hierarchy": [
      "tgn:1073814",
      "tgn:1000004",
      "tgn:7002087",
      "tgn:1000111",
      "tgn:7029392"
    ],
    "placetype": [
      "aat:300008347"
    ],
    "id": 1073814,
    "name:xx": "Zhêhor"
  }
}
