{
  "geometry": {
    "type": "Point",
    "coordinates": [
      -70.4167,
      41.3167
    ]
  },
  "type": "Feature",
  "properties": {
    "hierarchy": [
      "tgn:2533796",
      "tgn:1000001",
      "tgn:1002344",
      "tgn:7012149",
      "tgn:7007517",
      "tgn:7029392"
    ],
    "placetype": [
      "aat:300132348"
    ],
    "id": 2533796,
    "name:xx": "Mutton Shoal"
  }
}
