{
  "geometry": {
    "type": "Point",
    "coordinates": [
      78.256452,
      24.77495
    ]
  },
  "type": "Feature",
  "properties": {
    "hierarchy": [
      "tgn:7582352",
      "tgn:1000004",
      "tgn:7000198",
      "tgn:7016722",
      "tgn:7029392"
    ],
    "placetype": [
      "aat:300008699"
    ],
    "name:en": "Bera Nāla",
    "id": 7582352
  }
}
