{
  "type": "FeatureCollection",
  "features": [
    {
      "geometry": {
        "type": "Point",
        "coordinates": [
          -71.116667,
          -32.616667
        ]
      },
      "type": "Feature",
      "properties": {
        "hierarchy": [
          "tgn:7291501",
          "tgn:1001768",
          "tgn:1000049",
          "tgn:1000002",
          "tgn:7029392"
        ],
        "placetype": [
          "aat:300387200"
        ],
        "id": 7291501,
        "name:xx": "El Que침e"
      }
    },
    {
      "geometry": {
        "type": "Point",
        "coordinates": [
          -70.616667,
          -30.983333
        ]
      },
      "type": "Feature",
      "properties": {
        "hierarchy": [
          "tgn:7291502",
          "tgn:1001657",
          "tgn:1000049",
          "tgn:1000002",
          "tgn:7029392"
        ],
        "placetype": [
          "aat:300387200"
        ],
        "id": 7291502,
        "name:xx": "El Que침e"
      }
    },
    {
      "geometry": {
        "type": "Point",
        "coordinates": [
          -70.966667,
          -31.8
        ]
      },
      "type": "Feature",
      "properties": {
        "hierarchy": [
          "tgn:7291503",
          "tgn:1001657",
          "tgn:1000049",
          "tgn:1000002",
          "tgn:7029392"
        ],
        "placetype": [
          "aat:300000206"
        ],
        "id": 7291503,
        "name:xx": "El Que침e"
      }
    },
    {
      "geometry": {
        "type": "Point",
        "coordinates": [
          -69.533333,
          -27.35
        ]
      },
      "type": "Feature",
      "properties": {
        "hierarchy": [
          "tgn:7291504",
          "tgn:1001630",
          "tgn:1000049",
          "tgn:1000002",
          "tgn:7029392"
        ],
        "placetype": [
          "aat:300008686"
        ],
        "id": 7291504,
        "name:xx": "El Quemado, Vega"
      }
    },
    {
      "geometry": {
        "type": "Point",
        "coordinates": [
          -69.566667,
          -27.35
        ]
      },
      "type": "Feature",
      "properties": {
        "hierarchy": [
          "tgn:7291505",
          "tgn:1001630",
          "tgn:1000049",
          "tgn:1000002",
          "tgn:7029392"
        ],
        "placetype": [
          "aat:300266554",
          "aat:300008699"
        ],
        "id": 7291505,
        "name:xx": "El Quemado, Quebrada"
      }
    },
    {
      "geometry": {
        "type": "Point",
        "coordinates": [
          -72.1,
          -36.9
        ]
      },
      "type": "Feature",
      "properties": {
        "hierarchy": [
          "tgn:7291506",
          "tgn:1001637",
          "tgn:1000049",
          "tgn:1000002",
          "tgn:7029392"
        ],
        "placetype": [
          "aat:300008699"
        ],
        "id": 7291506,
        "name:xx": "El Quemado, Estero"
      }
    },
    {
      "geometry": {
        "type": "Point",
        "coordinates": [
          -70.166667,
          -33.5
        ]
      },
      "type": "Feature",
      "properties": {
        "hierarchy": [
          "tgn:7291507",
          "tgn:1001708",
          "tgn:1000049",
          "tgn:1000002",
          "tgn:7029392"
        ],
        "placetype": [
          "aat:300008699"
        ],
        "id": 7291507,
        "name:xx": "El Quemado, Caj칩n"
      }
    },
    {
      "geometry": {
        "type": "Point",
        "coordinates": [
          -71.633333,
          -33.283333
        ]
      },
      "type": "Feature",
      "properties": {
        "hierarchy": [
          "tgn:7291508",
          "tgn:1001768",
          "tgn:1000049",
          "tgn:1000002",
          "tgn:7029392"
        ],
        "placetype": [
          "aat:300387200"
        ],
        "id": 7291508,
        "name:xx": "El Llano"
      }
    },
    {
      "geometry": {
        "type": "Point",
        "coordinates": [
          -70.816667,
          -34.35
        ]
      },
      "type": "Feature",
      "properties": {
        "hierarchy": [
          "tgn:7291509",
          "tgn:1001695",
          "tgn:1000049",
          "tgn:1000002",
          "tgn:7029392"
        ],
        "placetype": [
          "aat:300000206"
        ],
        "id": 7291509,
        "name:xx": "El Llano"
      }
    }
  ]
}
