{
  "geometry": {
    "type": "Point",
    "coordinates": [
      -83.0167,
      36.55
    ]
  },
  "type": "Feature",
  "properties": {
    "hierarchy": [
      "tgn:2162675",
      "tgn:1000001",
      "tgn:7012149",
      "tgn:2001870",
      "tgn:7007825",
      "tgn:7029392"
    ],
    "placetype": [
      "aat:300008699"
    ],
    "id": 2162675,
    "name:xx": "Bend Branch"
  }
}
