{
  "geometry": {
    "type": "Point",
    "coordinates": [
      -83.1167,
      38.65
    ]
  },
  "type": "Feature",
  "properties": {
    "hierarchy": [
      "tgn:2557611",
      "tgn:1000001",
      "tgn:7012149",
      "tgn:1002877",
      "tgn:7007706",
      "tgn:7029392"
    ],
    "placetype": [
      "aat:300008699"
    ],
    "id": 2557611,
    "name:xx": "Old Pond Run"
  }
}
