{
  "geometry": {
    "type": "Point",
    "coordinates": [
      -119.6167,
      39.4833
    ]
  },
  "type": "Feature",
  "properties": {
    "hierarchy": [
      "tgn:2479269",
      "tgn:1000001",
      "tgn:7012149",
      "tgn:1002921",
      "tgn:7007526",
      "tgn:7029392"
    ],
    "placetype": [
      "aat:300008761"
    ],
    "id": 2479269,
    "name:xx": "Lagomarsino Canyon"
  }
}
