{
  "type": "FeatureCollection",
  "features": [
    {
      "geometry": {
        "type": "Point",
        "coordinates": [
          -99.6833,
          27.75
        ]
      },
      "type": "Feature",
      "properties": {
        "hierarchy": [
          "tgn:2470540",
          "tgn:1000001",
          "tgn:7012149",
          "tgn:2002090",
          "tgn:7007826",
          "tgn:7029392"
        ],
        "placetype": [
          "aat:300008706"
        ],
        "id": 2470540,
        "name:xx": "Los Indios Creek"
      }
    },
    {
      "geometry": {
        "type": "Point",
        "coordinates": [
          -97.9667,
          27.5667
        ]
      },
      "type": "Feature",
      "properties": {
        "hierarchy": [
          "tgn:2470541",
          "tgn:1000001",
          "tgn:7012149",
          "tgn:2002022",
          "tgn:7007826",
          "tgn:7029392"
        ],
        "placetype": [
          "aat:300006191"
        ],
        "id": 2470541,
        "name:xx": "Los Indios Lake"
      }
    },
    {
      "geometry": {
        "type": "Point",
        "coordinates": [
          -106.7167,
          36.2833
        ]
      },
      "type": "Feature",
      "properties": {
        "hierarchy": [
          "tgn:2470542",
          "tgn:1000001",
          "tgn:7012149",
          "tgn:2001449",
          "tgn:7007566",
          "tgn:7029392"
        ],
        "placetype": [
          "aat:300008697"
        ],
        "id": 2470542,
        "name:xx": "Los Indios Spring"
      }
    },
    {
      "geometry": {
        "type": "Point",
        "coordinates": [
          -106.7167,
          36.2833
        ]
      },
      "type": "Feature",
      "properties": {
        "hierarchy": [
          "tgn:2470543",
          "tgn:1000001",
          "tgn:7012149",
          "tgn:2001449",
          "tgn:7007566",
          "tgn:7029392"
        ],
        "placetype": [
          "aat:300008798"
        ],
        "id": 2470543,
        "name:xx": "Los Indios, Mesa"
      }
    },
    {
      "geometry": {
        "type": "Point",
        "coordinates": [
          -107.15,
          35.5667
        ]
      },
      "type": "Feature",
      "properties": {
        "hierarchy": [
          "tgn:2470544",
          "tgn:1000001",
          "tgn:7012149",
          "tgn:2001451",
          "tgn:7007566",
          "tgn:7029392"
        ],
        "placetype": [
          "aat:300008697"
        ],
        "id": 2470544,
        "name:xx": "Los Jaramillos, Ojo de"
      }
    },
    {
      "geometry": {
        "type": "Point",
        "coordinates": [
          -105.5,
          39.9333
        ]
      },
      "type": "Feature",
      "properties": {
        "hierarchy": [
          "tgn:2470545",
          "tgn:1000001",
          "tgn:2000198",
          "tgn:7012149",
          "tgn:7007158",
          "tgn:7029392"
        ],
        "placetype": [
          "aat:300006191"
        ],
        "id": 2470545,
        "name:xx": "Los Lagos Lakes"
      }
    },
    {
      "geometry": {
        "type": "Point",
        "coordinates": [
          -105.5,
          39.9167
        ]
      },
      "type": "Feature",
      "properties": {
        "hierarchy": [
          "tgn:2470546",
          "tgn:1000001",
          "tgn:7012149",
          "tgn:7007158",
          "tgn:7029392"
        ],
        "placetype": [
          "aat:300006191"
        ],
        "id": 2470546,
        "name:xx": "Los Lagos Reservoirs"
      }
    },
    {
      "geometry": {
        "type": "Point",
        "coordinates": [
          -105.5,
          39.9167
        ]
      },
      "type": "Feature",
      "properties": {
        "hierarchy": [
          "tgn:2470547",
          "tgn:1000001",
          "tgn:7012149",
          "tgn:7007158",
          "tgn:7029392"
        ],
        "placetype": [
          "aat:300006191"
        ],
        "id": 2470547,
        "name:xx": "Los Lagos Reservoirs Number 1"
      }
    },
    {
      "geometry": {
        "type": "Point",
        "coordinates": [
          -105.5,
          39.9167
        ]
      },
      "type": "Feature",
      "properties": {
        "hierarchy": [
          "tgn:2470548",
          "tgn:1000001",
          "tgn:7012149",
          "tgn:7007158",
          "tgn:7029392"
        ],
        "placetype": [
          "aat:300006191"
        ],
        "id": 2470548,
        "name:xx": "Los Lagos Reservoirs Number 2"
      }
    },
    {
      "geometry": {
        "type": "Point",
        "coordinates": [
          -105.5,
          39.9167
        ]
      },
      "type": "Feature",
      "properties": {
        "hierarchy": [
          "tgn:2470549",
          "tgn:1000001",
          "tgn:7012149",
          "tgn:7007158",
          "tgn:7029392"
        ],
        "placetype": [
          "aat:300006191"
        ],
        "id": 2470549,
        "name:xx": "Los Lagos Reservoirs Number 3"
      }
    }
  ]
}
