{
  "type": "FeatureCollection",
  "features": [
    {
      "geometry": {
        "type": "Point",
        "coordinates": [
          -1.016667,
          53.7
        ]
      },
      "type": "Feature",
      "properties": {
        "hierarchy": [
          "tgn:1136680",
          "tgn:7002445",
          "tgn:1000003",
          "tgn:7008166",
          "tgn:7008591",
          "tgn:7029392"
        ],
        "placetype": [
          "aat:300008347"
        ],
        "name:en": "Carlton",
        "id": 1136680
      }
    },
    {
      "geometry": {
        "type": "Point",
        "coordinates": [
          -2.183333,
          53.583333
        ]
      },
      "type": "Feature",
      "properties": {
        "hierarchy": [
          "tgn:1136681",
          "tgn:7002445",
          "tgn:1003634",
          "tgn:1000003",
          "tgn:7026570",
          "tgn:7008591",
          "tgn:7029392"
        ],
        "placetype": [
          "aat:300008347"
        ],
        "name:en": "Castleton",
        "id": 1136681
      }
    },
    {
      "geometry": {
        "type": "Point",
        "coordinates": [
          -0.933333,
          54.45
        ]
      },
      "type": "Feature",
      "properties": {
        "hierarchy": [
          "tgn:1136682",
          "tgn:7002445",
          "tgn:1000003",
          "tgn:7008166",
          "tgn:7008591",
          "tgn:7029392"
        ],
        "placetype": [
          "aat:300008347"
        ],
        "name:en": "Castleton",
        "id": 1136682
      }
    },
    {
      "geometry": {
        "type": "Point",
        "coordinates": [
          -2.4,
          53.6333
        ]
      },
      "type": "Feature",
      "properties": {
        "hierarchy": [
          "tgn:1136683",
          "tgn:7002445",
          "tgn:1000003",
          "tgn:7008154",
          "tgn:7008591",
          "tgn:7029392"
        ],
        "placetype": [
          "aat:300008347"
        ],
        "id": 1136683,
        "name:xx": "Chapeltown"
      }
    },
    {
      "geometry": {
        "type": "Point",
        "coordinates": [
          -0.166667,
          51.283333
        ]
      },
      "type": "Feature",
      "properties": {
        "hierarchy": [
          "tgn:1136685",
          "tgn:7002445",
          "tgn:1000003",
          "tgn:7008175",
          "tgn:7008591",
          "tgn:7029392"
        ],
        "placetype": [
          "aat:300008347"
        ],
        "name:en": "Chipstead",
        "id": 1136685
      }
    },
    {
      "geometry": {
        "type": "Point",
        "coordinates": [
          0.4,
          51.383333
        ]
      },
      "type": "Feature",
      "properties": {
        "hierarchy": [
          "tgn:1136686",
          "tgn:7002445",
          "tgn:1000003",
          "tgn:7008153",
          "tgn:7008591",
          "tgn:7029392"
        ],
        "placetype": [
          "aat:300008347"
        ],
        "name:en": "Cobham",
        "id": 1136686
      }
    },
    {
      "geometry": {
        "type": "Point",
        "coordinates": [
          -2.6,
          51.8
        ]
      },
      "type": "Feature",
      "properties": {
        "hierarchy": [
          "tgn:1136687",
          "tgn:7002445",
          "tgn:1000003",
          "tgn:7008132",
          "tgn:7008591",
          "tgn:7029392"
        ],
        "placetype": [
          "aat:300008347"
        ],
        "name:en": "Coleford",
        "id": 1136687
      }
    },
    {
      "geometry": {
        "type": "Point",
        "coordinates": [
          -1.7,
          52.5
        ]
      },
      "type": "Feature",
      "properties": {
        "hierarchy": [
          "tgn:1136688",
          "tgn:7002445",
          "tgn:1000003",
          "tgn:7008178",
          "tgn:7008591",
          "tgn:7029392"
        ],
        "placetype": [
          "aat:300008347"
        ],
        "name:en": "Coleshill",
        "id": 1136688
      }
    },
    {
      "geometry": {
        "type": "Point",
        "coordinates": [
          -2.75,
          53.3667
        ]
      },
      "type": "Feature",
      "properties": {
        "hierarchy": [
          "tgn:1136689",
          "tgn:7002445",
          "tgn:1000003",
          "tgn:1003600",
          "tgn:7008591",
          "tgn:7029392"
        ],
        "placetype": [
          "aat:300008347"
        ],
        "id": 1136689,
        "name:xx": "Ditton"
      }
    }
  ]
}
