{
  "type": "FeatureCollection",
  "features": [
    {
      "geometry": {
        "type": "Point",
        "coordinates": [
          -90.75,
          35.2333
        ]
      },
      "type": "Feature",
      "properties": {
        "hierarchy": [
          "tgn:2410630",
          "tgn:1000001",
          "tgn:7016172",
          "tgn:2000123",
          "tgn:7012149",
          "tgn:7029392"
        ],
        "placetype": [
          "aat:300008706"
        ],
        "id": 2410630,
        "name:xx": "Indian Creek"
      }
    },
    {
      "geometry": {
        "type": "Point",
        "coordinates": [
          -94.45,
          34.3333
        ]
      },
      "type": "Feature",
      "properties": {
        "hierarchy": [
          "tgn:2410631",
          "tgn:1000001",
          "tgn:7016172",
          "tgn:7012149",
          "tgn:2000161",
          "tgn:7029392"
        ],
        "placetype": [
          "aat:300008706"
        ],
        "id": 2410631,
        "name:xx": "Indian Creek"
      }
    },
    {
      "geometry": {
        "type": "Point",
        "coordinates": [
          -93.1167,
          35.7167
        ]
      },
      "type": "Feature",
      "properties": {
        "hierarchy": [
          "tgn:2410632",
          "tgn:1000001",
          "tgn:7016172",
          "tgn:7012149",
          "tgn:2000162",
          "tgn:7029392"
        ],
        "placetype": [
          "aat:300008706"
        ],
        "id": 2410632,
        "name:xx": "Indian Creek"
      }
    },
    {
      "geometry": {
        "type": "Point",
        "coordinates": [
          -92.25,
          35.7167
        ]
      },
      "type": "Feature",
      "properties": {
        "hierarchy": [
          "tgn:2410633",
          "tgn:1000001",
          "tgn:7016172",
          "tgn:7012149",
          "tgn:7029392"
        ],
        "placetype": [
          "aat:300008706"
        ],
        "id": 2410633,
        "name:xx": "Indian Creek"
      }
    },
    {
      "geometry": {
        "type": "Point",
        "coordinates": [
          -91.95,
          36.2333
        ]
      },
      "type": "Feature",
      "properties": {
        "hierarchy": [
          "tgn:2410634",
          "tgn:1000001",
          "tgn:7016172",
          "tgn:7012149",
          "tgn:2000137",
          "tgn:7029392"
        ],
        "placetype": [
          "aat:300008706"
        ],
        "id": 2410634,
        "name:xx": "Indian Creek"
      }
    },
    {
      "geometry": {
        "type": "Point",
        "coordinates": [
          -93.95,
          36.4333
        ]
      },
      "type": "Feature",
      "properties": {
        "hierarchy": [
          "tgn:2410635",
          "tgn:1000001",
          "tgn:2000108",
          "tgn:7016172",
          "tgn:7012149",
          "tgn:7029392"
        ],
        "placetype": [
          "aat:300008706"
        ],
        "id": 2410635,
        "name:xx": "Indian Creek"
      }
    },
    {
      "geometry": {
        "type": "Point",
        "coordinates": [
          -91.9833,
          33.1
        ]
      },
      "type": "Feature",
      "properties": {
        "hierarchy": [
          "tgn:2410636",
          "tgn:2000106",
          "tgn:1000001",
          "tgn:7016172",
          "tgn:7012149",
          "tgn:7029392"
        ],
        "placetype": [
          "aat:300008706"
        ],
        "id": 2410636,
        "name:xx": "Indian Creek"
      }
    },
    {
      "geometry": {
        "type": "Point",
        "coordinates": [
          -92.65,
          33.1
        ]
      },
      "type": "Feature",
      "properties": {
        "hierarchy": [
          "tgn:2410637",
          "tgn:1000001",
          "tgn:7012149",
          "tgn:7029392"
        ],
        "placetype": [
          "aat:300008706"
        ],
        "id": 2410637,
        "name:xx": "Indian Creek"
      }
    },
    {
      "geometry": {
        "type": "Point",
        "coordinates": [
          -118.95,
          36.7667
        ]
      },
      "type": "Feature",
      "properties": {
        "hierarchy": [
          "tgn:2410638",
          "tgn:1000001",
          "tgn:7012149",
          "tgn:1002392",
          "tgn:7007157",
          "tgn:7029392"
        ],
        "placetype": [
          "aat:300008706"
        ],
        "id": 2410638,
        "name:xx": "Indian Creek"
      }
    },
    {
      "geometry": {
        "type": "Point",
        "coordinates": [
          -122.1333,
          37.3167
        ]
      },
      "type": "Feature",
      "properties": {
        "hierarchy": [
          "tgn:2410639",
          "tgn:1000001",
          "tgn:7012149",
          "tgn:7007157",
          "tgn:7014475",
          "tgn:7029392"
        ],
        "placetype": [
          "aat:300008706"
        ],
        "id": 2410639,
        "name:xx": "Indian Creek"
      }
    }
  ]
}
