{
  "type": "FeatureCollection",
  "features": [
    {
      "geometry": {
        "type": "Point",
        "coordinates": [
          -151.55,
          62.3333
        ]
      },
      "type": "Feature",
      "properties": {
        "hierarchy": [
          "tgn:2735490",
          "tgn:7006450",
          "tgn:1000001",
          "tgn:2124053",
          "tgn:7012149",
          "tgn:7029392"
        ],
        "placetype": [
          "aat:300008706"
        ],
        "id": 2735490,
        "name:xx": "Twin Creek"
      }
    },
    {
      "geometry": {
        "type": "Point",
        "coordinates": [
          -148.6,
          65.2167
        ]
      },
      "type": "Feature",
      "properties": {
        "hierarchy": [
          "tgn:2735491",
          "tgn:7006450",
          "tgn:1000001",
          "tgn:7012149",
          "tgn:7029392"
        ],
        "placetype": [
          "aat:300008706"
        ],
        "id": 2735491,
        "name:xx": "Twin Creek"
      }
    },
    {
      "geometry": {
        "type": "Point",
        "coordinates": [
          -92.0333,
          35.9333
        ]
      },
      "type": "Feature",
      "properties": {
        "hierarchy": [
          "tgn:2735492",
          "tgn:1000001",
          "tgn:7016172",
          "tgn:7012149",
          "tgn:2000137",
          "tgn:7029392"
        ],
        "placetype": [
          "aat:300008347"
        ],
        "id": 2735492,
        "name:xx": "Twin Creek"
      }
    },
    {
      "geometry": {
        "type": "Point",
        "coordinates": [
          -92.3167,
          36.1167
        ]
      },
      "type": "Feature",
      "properties": {
        "hierarchy": [
          "tgn:2735493",
          "tgn:2000107",
          "tgn:1000001",
          "tgn:7016172",
          "tgn:7012149",
          "tgn:7029392"
        ],
        "placetype": [
          "aat:300008706"
        ],
        "id": 2735493,
        "name:xx": "Twin Creek"
      }
    },
    {
      "geometry": {
        "type": "Point",
        "coordinates": [
          -93.5833,
          34.4833
        ]
      },
      "type": "Feature",
      "properties": {
        "hierarchy": [
          "tgn:2735494",
          "tgn:1000001",
          "tgn:7016172",
          "tgn:7012149",
          "tgn:2000153",
          "tgn:7029392"
        ],
        "placetype": [
          "aat:300008706"
        ],
        "id": 2735494,
        "name:xx": "Twin Creek"
      }
    },
    {
      "geometry": {
        "type": "Point",
        "coordinates": [
          -92.6167,
          34.8333
        ]
      },
      "type": "Feature",
      "properties": {
        "hierarchy": [
          "tgn:2735495",
          "tgn:1000001",
          "tgn:7016172",
          "tgn:7012149",
          "tgn:2000164",
          "tgn:7029392"
        ],
        "placetype": [
          "aat:300008706"
        ],
        "id": 2735495,
        "name:xx": "Twin Creek"
      }
    },
    {
      "geometry": {
        "type": "Point",
        "coordinates": [
          -124.0667,
          40.4167
        ]
      },
      "type": "Feature",
      "properties": {
        "hierarchy": [
          "tgn:2735496",
          "tgn:1000001",
          "tgn:7012149",
          "tgn:2000181",
          "tgn:7007157",
          "tgn:7029392"
        ],
        "placetype": [
          "aat:300008706"
        ],
        "id": 2735496,
        "name:xx": "Twin Creek"
      }
    },
    {
      "geometry": {
        "type": "Point",
        "coordinates": [
          -107.4167,
          39.2
        ]
      },
      "type": "Feature",
      "properties": {
        "hierarchy": [
          "tgn:2735497",
          "tgn:1000001",
          "tgn:7012149",
          "tgn:2000217",
          "tgn:7007158",
          "tgn:7029392"
        ],
        "placetype": [
          "aat:300008706"
        ],
        "id": 2735497,
        "name:xx": "Twin Creek"
      }
    },
    {
      "geometry": {
        "type": "Point",
        "coordinates": [
          -105.75,
          40.15
        ]
      },
      "type": "Feature",
      "properties": {
        "hierarchy": [
          "tgn:2735498",
          "tgn:1000001",
          "tgn:7012149",
          "tgn:2000216",
          "tgn:7007158",
          "tgn:7029392"
        ],
        "placetype": [
          "aat:300008706"
        ],
        "id": 2735498,
        "name:xx": "Twin Creek"
      }
    },
    {
      "geometry": {
        "type": "Point",
        "coordinates": [
          -105.3667,
          39.2
        ]
      },
      "type": "Feature",
      "properties": {
        "hierarchy": [
          "tgn:2735499",
          "tgn:1000001",
          "tgn:7012149",
          "tgn:2000221",
          "tgn:7007158",
          "tgn:7029392"
        ],
        "placetype": [
          "aat:300008706"
        ],
        "id": 2735499,
        "name:xx": "Twin Creek"
      }
    }
  ]
}
