{
  "geometry": {
    "type": "Point",
    "coordinates": [
      -102.25,
      47.7833
    ]
  },
  "type": "Feature",
  "properties": {
    "hierarchy": [
      "tgn:2475718",
      "tgn:1000001",
      "tgn:2001584",
      "tgn:7012149",
      "tgn:7007705",
      "tgn:7029392"
    ],
    "placetype": [
      "aat:300132316"
    ],
    "id": 2475718,
    "name:xx": "Lucky Mound Creek Bay"
  }
}
