{
  "geometry": {
    "type": "Point",
    "coordinates": [
      -111.0667,
      37.8167
    ]
  },
  "type": "Feature",
  "properties": {
    "hierarchy": [
      "tgn:2747083",
      "tgn:1000001",
      "tgn:2002109",
      "tgn:7012149",
      "tgn:7007827",
      "tgn:7029392"
    ],
    "placetype": [
      "aat:300008798"
    ],
    "id": 2747083,
    "name:xx": "Wagon Box Mesa"
  }
}
