{
  "type": "FeatureCollection",
  "features": [
    {
      "geometry": {
        "type": "Point",
        "coordinates": [
          -123.4833,
          45.5833
        ]
      },
      "type": "Feature",
      "properties": {
        "hierarchy": [
          "tgn:2522810",
          "tgn:1000001",
          "tgn:7012149",
          "tgn:1002943",
          "tgn:7007708",
          "tgn:7029392"
        ],
        "placetype": [
          "aat:300008706"
        ],
        "id": 2522810,
        "name:xx": "Moore Creek"
      }
    },
    {
      "geometry": {
        "type": "Point",
        "coordinates": [
          -121.9667,
          43.65
        ]
      },
      "type": "Feature",
      "properties": {
        "hierarchy": [
          "tgn:2522811",
          "tgn:1000001",
          "tgn:2001705",
          "tgn:7012149",
          "tgn:7007708",
          "tgn:7029392"
        ],
        "placetype": [
          "aat:300008706"
        ],
        "id": 2522811,
        "name:xx": "Moore Creek"
      }
    },
    {
      "geometry": {
        "type": "Point",
        "coordinates": [
          -123.75,
          43.8667
        ]
      },
      "type": "Feature",
      "properties": {
        "hierarchy": [
          "tgn:2522812",
          "tgn:1000001",
          "tgn:7012149",
          "tgn:2001706",
          "tgn:7007708",
          "tgn:7029392"
        ],
        "placetype": [
          "aat:300008706"
        ],
        "id": 2522812,
        "name:xx": "Moore Creek"
      }
    },
    {
      "geometry": {
        "type": "Point",
        "coordinates": [
          -124.2,
          42.0167
        ]
      },
      "type": "Feature",
      "properties": {
        "hierarchy": [
          "tgn:2522813",
          "tgn:1000001",
          "tgn:2001704",
          "tgn:7012149",
          "tgn:7007708",
          "tgn:7029392"
        ],
        "placetype": [
          "aat:300008706"
        ],
        "id": 2522813,
        "name:xx": "Moore Creek"
      }
    },
    {
      "geometry": {
        "type": "Point",
        "coordinates": [
          -123.8667,
          43.2333
        ]
      },
      "type": "Feature",
      "properties": {
        "hierarchy": [
          "tgn:2522814",
          "tgn:1000001",
          "tgn:2001702",
          "tgn:7012149",
          "tgn:7007708",
          "tgn:7029392"
        ],
        "placetype": [
          "aat:300008706"
        ],
        "id": 2522814,
        "name:xx": "Moore Creek"
      }
    },
    {
      "geometry": {
        "type": "Point",
        "coordinates": [
          -81.0833,
          34.4167
        ]
      },
      "type": "Feature",
      "properties": {
        "hierarchy": [
          "tgn:2522815",
          "tgn:1000001",
          "tgn:2001744",
          "tgn:7012149",
          "tgn:7007712",
          "tgn:7029392"
        ],
        "placetype": [
          "aat:300008706"
        ],
        "id": 2522815,
        "name:xx": "Moore Creek"
      }
    },
    {
      "geometry": {
        "type": "Point",
        "coordinates": [
          -85.3167,
          35.7667
        ]
      },
      "type": "Feature",
      "properties": {
        "hierarchy": [
          "tgn:2522816",
          "tgn:1000001",
          "tgn:7012149",
          "tgn:7007825",
          "tgn:7029392"
        ],
        "placetype": [
          "aat:300008706"
        ],
        "id": 2522816,
        "name:xx": "Moore Creek"
      }
    },
    {
      "geometry": {
        "type": "Point",
        "coordinates": [
          -88.3167,
          36
        ]
      },
      "type": "Feature",
      "properties": {
        "hierarchy": [
          "tgn:2522817",
          "tgn:1000001",
          "tgn:7012149",
          "tgn:2001845",
          "tgn:7007825",
          "tgn:7029392"
        ],
        "placetype": [
          "aat:300008706"
        ],
        "id": 2522817,
        "name:xx": "Moore Creek"
      }
    },
    {
      "geometry": {
        "type": "Point",
        "coordinates": [
          -98.65,
          31.8
        ]
      },
      "type": "Feature",
      "properties": {
        "hierarchy": [
          "tgn:2522818",
          "tgn:1000001",
          "tgn:7012149",
          "tgn:2001962",
          "tgn:7007826",
          "tgn:7029392"
        ],
        "placetype": [
          "aat:300008706"
        ],
        "id": 2522818,
        "name:xx": "Moore Creek"
      }
    },
    {
      "geometry": {
        "type": "Point",
        "coordinates": [
          -100.2833,
          32.9
        ]
      },
      "type": "Feature",
      "properties": {
        "hierarchy": [
          "tgn:2522819",
          "tgn:1000001",
          "tgn:7012149",
          "tgn:7007826",
          "tgn:7029392"
        ],
        "placetype": [
          "aat:300008706"
        ],
        "id": 2522819,
        "name:xx": "Moore Creek"
      }
    }
  ]
}
