{
  "geometry": {
    "type": "Point",
    "coordinates": [
      -72.1833,
      44.1167
    ]
  },
  "type": "Feature",
  "properties": {
    "hierarchy": [
      "tgn:2495888",
      "tgn:1000001",
      "tgn:2002134",
      "tgn:7012149",
      "tgn:7007828",
      "tgn:7029392"
    ],
    "placetype": [
      "aat:300008798"
    ],
    "id": 2495888,
    "name:xx": "Mason Mountain"
  }
}
