{
  "geometry": {
    "type": "Point",
    "coordinates": [
      29.930278,
      31.06
    ]
  },
  "type": "Feature",
  "properties": {
    "hierarchy": [
      "tgn:7535631",
      "tgn:7001242",
      "tgn:1001075",
      "tgn:7016833",
      "tgn:7029392"
    ],
    "placetype": [
      "aat:300008777"
    ],
    "name:en": "Ghazāl, Tall al",
    "id": 7535631
  }
}
