{
  "geometry": {
    "type": "Point",
    "coordinates": [
      -83.65,
      43.0667
    ]
  },
  "type": "Feature",
  "properties": {
    "hierarchy": [
      "tgn:2212832",
      "tgn:1000001",
      "tgn:7012149",
      "tgn:1002406",
      "tgn:7007520",
      "tgn:7029392"
    ],
    "placetype": [
      "aat:300006191"
    ],
    "id": 2212832,
    "name:xx": "C S Mott Lake"
  }
}
