{
  "geometry": {
    "type": "Point",
    "coordinates": [
      -133.1167,
      54.9667
    ]
  },
  "type": "Feature",
  "properties": {
    "hierarchy": [
      "tgn:2756330",
      "tgn:7006450",
      "tgn:1000001",
      "tgn:7012149",
      "tgn:2000082",
      "tgn:7029392"
    ],
    "placetype": [
      "aat:300008680"
    ],
    "id": 2756330,
    "name:xx": "Welcome, Lake"
  }
}
