{
  "type": "FeatureCollection",
  "features": [
    {
      "geometry": {
        "type": "Point",
        "coordinates": [
          -4.233333,
          36.933333
        ]
      },
      "type": "Feature",
      "properties": {
        "hierarchy": [
          "tgn:7301290",
          "tgn:7002758",
          "tgn:7002830",
          "tgn:1000003",
          "tgn:1000095",
          "tgn:7029392"
        ],
        "placetype": [
          "aat:300008347"
        ],
        "id": 7301290,
        "name:xx": "Mondr칩n"
      }
    },
    {
      "geometry": {
        "type": "Point",
        "coordinates": [
          -7.45,
          43.116667
        ]
      },
      "type": "Feature",
      "properties": {
        "hierarchy": [
          "tgn:7301291",
          "tgn:7002829",
          "tgn:1000003",
          "tgn:7002786",
          "tgn:1000095",
          "tgn:7029392"
        ],
        "placetype": [
          "aat:300008347"
        ],
        "id": 7301291,
        "name:xx": "Mondriz"
      }
    },
    {
      "geometry": {
        "type": "Point",
        "coordinates": [
          -5.016667,
          42.7
        ]
      },
      "type": "Feature",
      "properties": {
        "hierarchy": [
          "tgn:7301292",
          "tgn:7002826",
          "tgn:7001158",
          "tgn:1000003",
          "tgn:1000095",
          "tgn:7029392"
        ],
        "placetype": [
          "aat:300008347"
        ],
        "id": 7301292,
        "name:xx": "Mondreganes"
      }
    },
    {
      "geometry": {
        "type": "Point",
        "coordinates": [
          -2.483333,
          43.066667
        ]
      },
      "type": "Feature",
      "properties": {
        "hierarchy": [
          "tgn:7301293",
          "tgn:7002849",
          "tgn:1000003",
          "tgn:7009604",
          "tgn:1000095",
          "tgn:7029392"
        ],
        "placetype": [
          "aat:300008347"
        ],
        "id": 7301293,
        "name:xx": "Mondrag칩n"
      }
    },
    {
      "geometry": {
        "type": "Point",
        "coordinates": [
          3.2,
          39.333333
        ]
      },
      "type": "Feature",
      "properties": {
        "hierarchy": [
          "tgn:7301294",
          "tgn:7001122",
          "tgn:1000003",
          "tgn:7002765",
          "tgn:1000095",
          "tgn:7029392"
        ],
        "placetype": [
          "aat:300132317"
        ],
        "id": 7301294,
        "name:xx": "Mondrag칩, Cala"
      }
    },
    {
      "geometry": {
        "type": "Point",
        "coordinates": [
          -8.2,
          43.25
        ]
      },
      "type": "Feature",
      "properties": {
        "hierarchy": [
          "tgn:7301295",
          "tgn:7002824",
          "tgn:1000003",
          "tgn:7002786",
          "tgn:1000095",
          "tgn:7029392"
        ],
        "placetype": [
          "aat:300008347"
        ],
        "id": 7301295,
        "name:xx": "Mondoy"
      }
    },
    {
      "geometry": {
        "type": "Point",
        "coordinates": [
          -16.366667,
          28.366667
        ]
      },
      "type": "Feature",
      "properties": {
        "hierarchy": [
          "tgn:7301296",
          "tgn:7002836",
          "tgn:7016622",
          "tgn:1000003",
          "tgn:1000095",
          "tgn:7029392"
        ],
        "placetype": [
          "aat:300386846"
        ],
        "id": 7301296,
        "name:xx": "Mondongo, Punta"
      }
    },
    {
      "geometry": {
        "type": "Point",
        "coordinates": [
          -7.3,
          43.566667
        ]
      },
      "type": "Feature",
      "properties": {
        "hierarchy": [
          "tgn:7301297",
          "tgn:7002829",
          "tgn:1000003",
          "tgn:7002786",
          "tgn:1000095",
          "tgn:7029392"
        ],
        "placetype": [
          "aat:300008347"
        ],
        "id": 7301297,
        "name:xx": "Mondo침edo"
      }
    }
  ]
}
