{
  "type": "FeatureCollection",
  "features": [
    {
      "geometry": {
        "type": "Point",
        "coordinates": [
          -75.6333,
          39.2
        ]
      },
      "type": "Feature",
      "properties": {
        "hierarchy": [
          "tgn:2712510",
          "tgn:1002538",
          "tgn:1000001",
          "tgn:7012149",
          "tgn:7007239",
          "tgn:7029392"
        ],
        "placetype": [
          "aat:300008699"
        ],
        "id": 2712510,
        "name:xx": "Taylor Branch"
      }
    },
    {
      "geometry": {
        "type": "Point",
        "coordinates": [
          -85.2833,
          30.4833
        ]
      },
      "type": "Feature",
      "properties": {
        "hierarchy": [
          "tgn:2712511",
          "tgn:1000001",
          "tgn:2000260",
          "tgn:7012149",
          "tgn:7007240",
          "tgn:7029392"
        ],
        "placetype": [
          "aat:300008699"
        ],
        "id": 2712511,
        "name:xx": "Taylor Branch"
      }
    },
    {
      "geometry": {
        "type": "Point",
        "coordinates": [
          -81.85,
          31.3
        ]
      },
      "type": "Feature",
      "properties": {
        "hierarchy": [
          "tgn:2712512",
          "tgn:1000001",
          "tgn:2000304",
          "tgn:7012149",
          "tgn:7007248",
          "tgn:7029392"
        ],
        "placetype": [
          "aat:300008699"
        ],
        "id": 2712512,
        "name:xx": "Taylor Branch"
      }
    },
    {
      "geometry": {
        "type": "Point",
        "coordinates": [
          -84.7167,
          31.6833
        ]
      },
      "type": "Feature",
      "properties": {
        "hierarchy": [
          "tgn:2712513",
          "tgn:1000001",
          "tgn:7012149",
          "tgn:2000411",
          "tgn:7007248",
          "tgn:7029392"
        ],
        "placetype": [
          "aat:300008699"
        ],
        "id": 2712513,
        "name:xx": "Taylor Branch"
      }
    },
    {
      "geometry": {
        "type": "Point",
        "coordinates": [
          -83.75,
          34.8667
        ]
      },
      "type": "Feature",
      "properties": {
        "hierarchy": [
          "tgn:2712514",
          "tgn:1000001",
          "tgn:7012149",
          "tgn:2000430",
          "tgn:7007248",
          "tgn:7029392"
        ],
        "placetype": [
          "aat:300008699"
        ],
        "id": 2712514,
        "name:xx": "Taylor Branch"
      }
    },
    {
      "geometry": {
        "type": "Point",
        "coordinates": [
          -88.7833,
          38.1333
        ]
      },
      "type": "Feature",
      "properties": {
        "hierarchy": [
          "tgn:2712515",
          "tgn:1000001",
          "tgn:7012149",
          "tgn:7007251",
          "tgn:7029392"
        ],
        "placetype": [
          "aat:300008699"
        ],
        "id": 2712515,
        "name:xx": "Taylor Branch"
      }
    },
    {
      "geometry": {
        "type": "Point",
        "coordinates": [
          -86.3167,
          39.0167
        ]
      },
      "type": "Feature",
      "properties": {
        "hierarchy": [
          "tgn:2712516",
          "tgn:1000001",
          "tgn:7012149",
          "tgn:1002678",
          "tgn:7007252",
          "tgn:7029392"
        ],
        "placetype": [
          "aat:300008699"
        ],
        "id": 2712516,
        "name:xx": "Taylor Branch"
      }
    },
    {
      "geometry": {
        "type": "Point",
        "coordinates": [
          -85.35,
          39.1333
        ]
      },
      "type": "Feature",
      "properties": {
        "hierarchy": [
          "tgn:2712517",
          "tgn:1000001",
          "tgn:7012149",
          "tgn:1002827",
          "tgn:7007252",
          "tgn:7029392"
        ],
        "placetype": [
          "aat:300008699"
        ],
        "id": 2712517,
        "name:xx": "Taylor Branch"
      }
    },
    {
      "geometry": {
        "type": "Point",
        "coordinates": [
          -94.6167,
          37.3667
        ]
      },
      "type": "Feature",
      "properties": {
        "hierarchy": [
          "tgn:2712518",
          "tgn:1000001",
          "tgn:7012149",
          "tgn:7007254",
          "tgn:7029392"
        ],
        "placetype": [
          "aat:300008699"
        ],
        "id": 2712518,
        "name:xx": "Taylor Branch"
      }
    },
    {
      "geometry": {
        "type": "Point",
        "coordinates": [
          -84.3333,
          36.8833
        ]
      },
      "type": "Feature",
      "properties": {
        "hierarchy": [
          "tgn:2712519",
          "tgn:1000001",
          "tgn:7012149",
          "tgn:2000818",
          "tgn:7007255",
          "tgn:7029392"
        ],
        "placetype": [
          "aat:300008699"
        ],
        "id": 2712519,
        "name:xx": "Taylor Branch"
      }
    }
  ]
}
