{
  "geometry": {
    "type": "Point",
    "coordinates": [
      -110.05,
      43.3167
    ]
  },
  "type": "Feature",
  "properties": {
    "hierarchy": [
      "tgn:2440344",
      "tgn:1000001",
      "tgn:7012149",
      "tgn:2002382",
      "tgn:7007923",
      "tgn:7029392"
    ],
    "placetype": [
      "aat:300008798"
    ],
    "id": 2440344,
    "name:xx": "Klondike Hill"
  }
}
