{
  "geometry": {
    "type": "Point",
    "coordinates": [
      -115.05,
      35.0333
    ]
  },
  "type": "Feature",
  "properties": {
    "hierarchy": [
      "tgn:2172577",
      "tgn:1000001",
      "tgn:7012149",
      "tgn:7007157",
      "tgn:1002857",
      "tgn:7029392"
    ],
    "placetype": [
      "aat:300008798"
    ],
    "id": 2172577,
    "name:xx": "Billie Mountain"
  }
}
