{
  "geometry": {
    "type": "Point",
    "coordinates": [
      -82.7333,
      33.7333
    ]
  },
  "type": "Feature",
  "properties": {
    "hierarchy": [
      "tgn:2626128",
      "tgn:1000001",
      "tgn:7012149",
      "tgn:2000448",
      "tgn:7007248",
      "tgn:7029392"
    ],
    "placetype": [
      "aat:300008706"
    ],
    "id": 2626128,
    "name:xx": "Rocky Creek"
  }
}
