{
  "type": "FeatureCollection",
  "features": [
    {
      "geometry": {
        "type": "Point",
        "coordinates": [
          -83.1167,
          36.4833
        ]
      },
      "type": "Feature",
      "properties": {
        "hierarchy": [
          "tgn:2510270",
          "tgn:1000001",
          "tgn:7012149",
          "tgn:2001873",
          "tgn:7007825",
          "tgn:7029392"
        ],
        "placetype": [
          "aat:300266640"
        ],
        "id": 2510270,
        "name:xx": "Middle Ridge"
      }
    },
    {
      "geometry": {
        "type": "Point",
        "coordinates": [
          -82.55,
          35.9667
        ]
      },
      "type": "Feature",
      "properties": {
        "hierarchy": [
          "tgn:2510271",
          "tgn:1000001",
          "tgn:7012149",
          "tgn:2001922",
          "tgn:7007825",
          "tgn:7029392"
        ],
        "placetype": [
          "aat:300266640"
        ],
        "id": 2510271,
        "name:xx": "Middle Ridge"
      }
    },
    {
      "geometry": {
        "type": "Point",
        "coordinates": [
          -98.5167,
          30.45
        ]
      },
      "type": "Feature",
      "properties": {
        "hierarchy": [
          "tgn:2510272",
          "tgn:1000001",
          "tgn:2001942",
          "tgn:7012149",
          "tgn:7007826",
          "tgn:7029392"
        ],
        "placetype": [
          "aat:300266640"
        ],
        "id": 2510272,
        "name:xx": "Middle Ridge"
      }
    },
    {
      "geometry": {
        "type": "Point",
        "coordinates": [
          -114,
          37.4167
        ]
      },
      "type": "Feature",
      "properties": {
        "hierarchy": [
          "tgn:2510273",
          "tgn:1000001",
          "tgn:7012149",
          "tgn:2002127",
          "tgn:7007827",
          "tgn:7029392"
        ],
        "placetype": [
          "aat:300266640"
        ],
        "id": 2510273,
        "name:xx": "Middle Ridge"
      }
    },
    {
      "geometry": {
        "type": "Point",
        "coordinates": [
          -112.3,
          38.7
        ]
      },
      "type": "Feature",
      "properties": {
        "hierarchy": [
          "tgn:2510274",
          "tgn:1000001",
          "tgn:7012149",
          "tgn:2002114",
          "tgn:7007827",
          "tgn:7029392"
        ],
        "placetype": [
          "aat:300266640"
        ],
        "id": 2510274,
        "name:xx": "Middle Ridge"
      }
    },
    {
      "geometry": {
        "type": "Point",
        "coordinates": [
          -111.95,
          39.7667
        ]
      },
      "type": "Feature",
      "properties": {
        "hierarchy": [
          "tgn:2510275",
          "tgn:1000001",
          "tgn:7012149",
          "tgn:2002112",
          "tgn:7007827",
          "tgn:7029392"
        ],
        "placetype": [
          "aat:300266640"
        ],
        "id": 2510275,
        "name:xx": "Middle Ridge"
      }
    },
    {
      "geometry": {
        "type": "Point",
        "coordinates": [
          -111.3833,
          41.0667
        ]
      },
      "type": "Feature",
      "properties": {
        "hierarchy": [
          "tgn:2510276",
          "tgn:1000001",
          "tgn:7012149",
          "tgn:2002122",
          "tgn:7007827",
          "tgn:7029392"
        ],
        "placetype": [
          "aat:300266640"
        ],
        "id": 2510276,
        "name:xx": "Middle Ridge"
      }
    },
    {
      "geometry": {
        "type": "Point",
        "coordinates": [
          -111.4667,
          41.4167
        ]
      },
      "type": "Feature",
      "properties": {
        "hierarchy": [
          "tgn:2510277",
          "tgn:1000001",
          "tgn:7012149",
          "tgn:2002117",
          "tgn:7007827",
          "tgn:7029392"
        ],
        "placetype": [
          "aat:300266640"
        ],
        "id": 2510277,
        "name:xx": "Middle Ridge"
      }
    },
    {
      "geometry": {
        "type": "Point",
        "coordinates": [
          -112.95,
          37.7333
        ]
      },
      "type": "Feature",
      "properties": {
        "hierarchy": [
          "tgn:2510278",
          "tgn:1000001",
          "tgn:7012149",
          "tgn:2002111",
          "tgn:7007827",
          "tgn:7029392"
        ],
        "placetype": [
          "aat:300266640"
        ],
        "id": 2510278,
        "name:xx": "Middle Ridge"
      }
    },
    {
      "geometry": {
        "type": "Point",
        "coordinates": [
          -82.55,
          36.8333
        ]
      },
      "type": "Feature",
      "properties": {
        "hierarchy": [
          "tgn:2510279",
          "tgn:1000001",
          "tgn:7012149",
          "tgn:2002189",
          "tgn:7007919",
          "tgn:7029392"
        ],
        "placetype": [
          "aat:300266640"
        ],
        "id": 2510279,
        "name:xx": "Middle Ridge"
      }
    }
  ]
}
