{
  "geometry": {
    "type": "Point",
    "coordinates": [
      -91.9333,
      35.35
    ]
  },
  "type": "Feature",
  "properties": {
    "hierarchy": [
      "tgn:2685395",
      "tgn:1000001",
      "tgn:7016172",
      "tgn:2000116",
      "tgn:7012149",
      "tgn:7029392"
    ],
    "placetype": [
      "aat:300008761"
    ],
    "id": 2685395,
    "name:xx": "Spout Springs Hollow"
  }
}
