{
  "geometry": {
    "type": "Point",
    "coordinates": [
      -103.8833,
      44.1833
    ]
  },
  "type": "Feature",
  "properties": {
    "hierarchy": [
      "tgn:2721615",
      "tgn:1000001",
      "tgn:2001810",
      "tgn:7012149",
      "tgn:7007713",
      "tgn:7029392"
    ],
    "placetype": [
      "aat:300008706"
    ],
    "id": 2721615,
    "name:xx": "Tillson Creek"
  }
}
