{
  "geometry": {
    "type": "Point",
    "coordinates": [
      36.2333,
      55.4333
    ]
  },
  "type": "Feature",
  "properties": {
    "hierarchy": [
      "tgn:1137305",
      "tgn:1000004",
      "tgn:7011573",
      "tgn:7018214",
      "tgn:7002435",
      "tgn:7029392"
    ],
    "placetype": [
      "aat:300008347"
    ],
    "id": 1137305,
    "name:xx": "Bogorodskoye"
  }
}
