{
  "geometry": {
    "type": "Point",
    "coordinates": [
      -67.7667,
      44.5167
    ]
  },
  "type": "Feature",
  "properties": {
    "hierarchy": [
      "tgn:2535588",
      "tgn:1000001",
      "tgn:7012149",
      "tgn:7014589",
      "tgn:7007515",
      "tgn:7029392"
    ],
    "placetype": [
      "aat:300008791"
    ],
    "id": 2535588,
    "name:xx": "Narrows Island"
  }
}
