{
  "geometry": {
    "type": "Point",
    "coordinates": [
      79.8503,
      27.142
    ]
  },
  "type": "Feature",
  "properties": {
    "hierarchy": [
      "tgn:7562312",
      "tgn:1000004",
      "tgn:7000198",
      "tgn:7016722",
      "tgn:7029392"
    ],
    "placetype": [
      "aat:300008347"
    ],
    "name:en": "Gauran Purwa",
    "id": 7562312
  }
}
