{
  "type": "FeatureCollection",
  "features": [
    {
      "geometry": {
        "type": "Point",
        "coordinates": [
          -106.5333,
          39.8
        ]
      },
      "type": "Feature",
      "properties": {
        "hierarchy": [
          "tgn:2360010",
          "tgn:1000001",
          "tgn:7012149",
          "tgn:2000210",
          "tgn:7007158",
          "tgn:7029392"
        ],
        "placetype": [
          "aat:300008761"
        ],
        "id": 2360010,
        "name:xx": "Grass Gulch"
      }
    },
    {
      "geometry": {
        "type": "Point",
        "coordinates": [
          -114.65,
          45.6333
        ]
      },
      "type": "Feature",
      "properties": {
        "hierarchy": [
          "tgn:2360011",
          "tgn:1000001",
          "tgn:7012149",
          "tgn:2000476",
          "tgn:7007250",
          "tgn:7029392"
        ],
        "placetype": [
          "aat:300008761"
        ],
        "id": 2360011,
        "name:xx": "Grass Gulch"
      }
    },
    {
      "geometry": {
        "type": "Point",
        "coordinates": [
          -106.5333,
          39.7833
        ]
      },
      "type": "Feature",
      "properties": {
        "hierarchy": [
          "tgn:2360012",
          "tgn:1000001",
          "tgn:7012149",
          "tgn:2000210",
          "tgn:7007158",
          "tgn:7029392"
        ],
        "placetype": [
          "aat:300008697"
        ],
        "id": 2360012,
        "name:xx": "Grass Gulch Spring"
      }
    },
    {
      "geometry": {
        "type": "Point",
        "coordinates": [
          -73.7667,
          40.6167
        ]
      },
      "type": "Feature",
      "properties": {
        "hierarchy": [
          "tgn:2360013",
          "tgn:1000001",
          "tgn:7012149",
          "tgn:7007568",
          "tgn:7029392"
        ],
        "placetype": [
          "aat:300008791"
        ],
        "id": 2360013,
        "name:xx": "Grass Hassock"
      }
    },
    {
      "geometry": {
        "type": "Point",
        "coordinates": [
          -72.1667,
          41.9
        ]
      },
      "type": "Feature",
      "properties": {
        "hierarchy": [
          "tgn:2360014",
          "tgn:1000001",
          "tgn:1003028",
          "tgn:7012149",
          "tgn:7007159",
          "tgn:7029392"
        ],
        "placetype": [
          "aat:300008798"
        ],
        "id": 2360014,
        "name:xx": "Grass Hill"
      }
    },
    {
      "geometry": {
        "type": "Point",
        "coordinates": [
          -72.6833,
          42.4
        ]
      },
      "type": "Feature",
      "properties": {
        "hierarchy": [
          "tgn:2360015",
          "tgn:1000001",
          "tgn:7013942",
          "tgn:7012149",
          "tgn:7007517",
          "tgn:7029392"
        ],
        "placetype": [
          "aat:300008798"
        ],
        "id": 2360015,
        "name:xx": "Grass Hill"
      }
    },
    {
      "geometry": {
        "type": "Point",
        "coordinates": [
          -71.8167,
          42.15
        ]
      },
      "type": "Feature",
      "properties": {
        "hierarchy": [
          "tgn:2360016",
          "tgn:1000001",
          "tgn:7012149",
          "tgn:1003038",
          "tgn:7007517",
          "tgn:7029392"
        ],
        "placetype": [
          "aat:300008798"
        ],
        "id": 2360016,
        "name:xx": "Grass Hill"
      }
    },
    {
      "geometry": {
        "type": "Point",
        "coordinates": [
          -93.9667,
          38.1
        ]
      },
      "type": "Feature",
      "properties": {
        "hierarchy": [
          "tgn:2360017",
          "tgn:1000001",
          "tgn:7012149",
          "tgn:2001239",
          "tgn:7007523",
          "tgn:7029392"
        ],
        "placetype": [
          "aat:300008798"
        ],
        "id": 2360017,
        "name:xx": "Grass Hill"
      }
    },
    {
      "geometry": {
        "type": "Point",
        "coordinates": [
          -112.7333,
          47.7167
        ]
      },
      "type": "Feature",
      "properties": {
        "hierarchy": [
          "tgn:2360018",
          "tgn:1000001",
          "tgn:7012149",
          "tgn:2001309",
          "tgn:7007524",
          "tgn:7029392"
        ],
        "placetype": [
          "aat:300008798"
        ],
        "id": 2360018,
        "name:xx": "Grass Hill"
      }
    },
    {
      "geometry": {
        "type": "Point",
        "coordinates": [
          -77.55,
          42.1667
        ]
      },
      "type": "Feature",
      "properties": {
        "hierarchy": [
          "tgn:2360019",
          "tgn:1000001",
          "tgn:7012149",
          "tgn:1002920",
          "tgn:7007568",
          "tgn:7029392"
        ],
        "placetype": [
          "aat:300008798"
        ],
        "id": 2360019,
        "name:xx": "Grass Hill"
      }
    }
  ]
}
