{
  "geometry": {
    "type": "Point",
    "coordinates": [
      -109.8667,
      40.7667
    ]
  },
  "type": "Feature",
  "properties": {
    "hierarchy": [
      "tgn:2306321",
      "tgn:1000001",
      "tgn:2002105",
      "tgn:7012149",
      "tgn:7007827",
      "tgn:7029392"
    ],
    "placetype": [
      "aat:300008706"
    ],
    "id": 2306321,
    "name:xx": "East Fork Carter Creek"
  }
}
