{
  "geometry": {
    "type": "Point",
    "coordinates": [
      -79.7667,
      34.0333
    ]
  },
  "type": "Feature",
  "properties": {
    "hierarchy": [
      "tgn:2162421",
      "tgn:1000001",
      "tgn:2001745",
      "tgn:7012149",
      "tgn:7007712",
      "tgn:7029392"
    ],
    "placetype": [
      "aat:300008905"
    ],
    "id": 2162421,
    "name:xx": "Ben Gause Bay"
  }
}
