{
  "type": "FeatureCollection",
  "features": [
    {
      "geometry": {
        "type": "Point",
        "coordinates": [
          13.2,
          53.766667
        ]
      },
      "type": "Feature",
      "properties": {
        "hierarchy": [
          "tgn:7185860",
          "tgn:1000003",
          "tgn:7000094",
          "tgn:7000084",
          "tgn:7029392"
        ],
        "placetype": [
          "aat:300000206"
        ],
        "id": 7185860,
        "name:xx": "Glavenhof"
      }
    },
    {
      "geometry": {
        "type": "Point",
        "coordinates": [
          12.3,
          53.6
        ]
      },
      "type": "Feature",
      "properties": {
        "hierarchy": [
          "tgn:7185861",
          "tgn:1000003",
          "tgn:7000094",
          "tgn:7000084",
          "tgn:7029392"
        ],
        "placetype": [
          "aat:300008347"
        ],
        "id": 7185861,
        "name:xx": "Glave"
      }
    },
    {
      "geometry": {
        "type": "Point",
        "coordinates": [
          12,
          51.65
        ]
      },
      "type": "Feature",
      "properties": {
        "hierarchy": [
          "tgn:7185862",
          "tgn:1000003",
          "tgn:7003687",
          "tgn:7000084",
          "tgn:7029392"
        ],
        "placetype": [
          "aat:300008347"
        ],
        "id": 7185862,
        "name:xx": "Glauzig"
      }
    },
    {
      "geometry": {
        "type": "Point",
        "coordinates": [
          13.85,
          51.266667
        ]
      },
      "type": "Feature",
      "properties": {
        "hierarchy": [
          "tgn:7185863",
          "tgn:1000003",
          "tgn:7003685",
          "tgn:7000084",
          "tgn:7029392"
        ],
        "placetype": [
          "aat:300008347"
        ],
        "id": 7185863,
        "name:xx": "Glauschnitz"
      }
    },
    {
      "geometry": {
        "type": "Point",
        "coordinates": [
          13.166667,
          52.25
        ]
      },
      "type": "Feature",
      "properties": {
        "hierarchy": [
          "tgn:7185864",
          "tgn:7000096",
          "tgn:1000003",
          "tgn:7000084",
          "tgn:7029392"
        ],
        "placetype": [
          "aat:300008777"
        ],
        "id": 7185864,
        "name:xx": "Glauer Berge"
      }
    },
    {
      "geometry": {
        "type": "Point",
        "coordinates": [
          12.566667,
          51.566667
        ]
      },
      "type": "Feature",
      "properties": {
        "hierarchy": [
          "tgn:7185866",
          "tgn:1000003",
          "tgn:7003685",
          "tgn:7000084",
          "tgn:7029392"
        ],
        "placetype": [
          "aat:300008347"
        ],
        "id": 7185866,
        "name:xx": "Nieder Glaucha"
      }
    },
    {
      "geometry": {
        "type": "Point",
        "coordinates": [
          13.2,
          51.166667
        ]
      },
      "type": "Feature",
      "properties": {
        "hierarchy": [
          "tgn:7185867",
          "tgn:1000003",
          "tgn:7003685",
          "tgn:7000084",
          "tgn:7029392"
        ],
        "placetype": [
          "aat:300008347"
        ],
        "id": 7185867,
        "name:xx": "Glaucha"
      }
    },
    {
      "geometry": {
        "type": "Point",
        "coordinates": [
          8.966667,
          50.45
        ]
      },
      "type": "Feature",
      "properties": {
        "hierarchy": [
          "tgn:7185868",
          "tgn:1000003",
          "tgn:7003678",
          "tgn:7000084",
          "tgn:7029392"
        ],
        "placetype": [
          "aat:300004792"
        ],
        "id": 7185868,
        "name:xx": "Försterei Glaubzahl"
      }
    }
  ]
}
