{
  "geometry": {
    "type": "Point",
    "coordinates": [
      -118.5167,
      47.6833
    ]
  },
  "type": "Feature",
  "properties": {
    "hierarchy": [
      "tgn:2492408",
      "tgn:1000001",
      "tgn:7012149",
      "tgn:2002247",
      "tgn:7007920",
      "tgn:7029392"
    ],
    "placetype": [
      "aat:300008697"
    ],
    "id": 2492408,
    "name:xx": "Marguette Spring"
  }
}
