{
  "geometry": {
    "type": "Point",
    "coordinates": [
      -110.7833,
      38.0667
    ]
  },
  "type": "Feature",
  "properties": {
    "hierarchy": [
      "tgn:2205526",
      "tgn:1000001",
      "tgn:7012149",
      "tgn:7007827",
      "tgn:7029392"
    ],
    "placetype": [
      "aat:300008706"
    ],
    "id": 2205526,
    "name:xx": "Bull Creek"
  }
}
