{
  "geometry": {
    "type": "Point",
    "coordinates": [
      -79.45,
      34.7333
    ]
  },
  "type": "Feature",
  "properties": {
    "hierarchy": [
      "tgn:2502039",
      "tgn:1000001",
      "tgn:7012149",
      "tgn:2001539",
      "tgn:7007709",
      "tgn:7029392"
    ],
    "placetype": [
      "aat:300008347"
    ],
    "id": 2502039,
    "name:xx": "McKenzie Acres East"
  }
}
