{
  "geometry": {
    "type": "Point",
    "coordinates": [
      -121.55,
      42.3333
    ]
  },
  "type": "Feature",
  "properties": {
    "hierarchy": [
      "tgn:2756885",
      "tgn:1000001",
      "tgn:7012149",
      "tgn:2001714",
      "tgn:7007708",
      "tgn:7029392"
    ],
    "placetype": [
      "aat:300008697"
    ],
    "id": 2756885,
    "name:xx": "Welsh Spring"
  }
}
