{
  "geometry": {
    "type": "Point",
    "coordinates": [
      19.75,
      10.5833
    ]
  },
  "type": "Feature",
  "properties": {
    "hierarchy": [
      "tgn:1001000",
      "tgn:7001242",
      "tgn:1000156",
      "tgn:7029392"
    ],
    "placetype": [
      "aat:300387064",
      "aat:300235099"
    ],
    "id": 1001000,
    "name:xx": "Lac"
  }
}
