{
  "geometry": {
    "type": "Point",
    "coordinates": [
      120.4726,
      23.8233
    ]
  },
  "type": "Feature",
  "properties": {
    "hierarchy": [
      "tgn:7472294",
      "tgn:1000004",
      "tgn:7467799",
      "tgn:1000141",
      "tgn:7029392"
    ],
    "placetype": [
      "aat:300006156"
    ],
    "id": 7472294,
    "name:xx": "Shuiwei Tifang"
  }
}
