{
  "geometry": {
    "type": "Point",
    "coordinates": [
      -98.2333,
      34.8167
    ]
  },
  "type": "Feature",
  "properties": {
    "hierarchy": [
      "tgn:2083225",
      "tgn:1000001",
      "tgn:2001638",
      "tgn:7012149",
      "tgn:7007707",
      "tgn:7029392"
    ],
    "placetype": [
      "aat:300008347"
    ],
    "id": 2083225,
    "name:xx": "Fletcher"
  }
}
