{
  "geometry": {
    "type": "Point",
    "coordinates": [
      -65.7667,
      18.3667
    ]
  },
  "type": "Feature",
  "properties": {
    "hierarchy": [
      "tgn:1018997",
      "tgn:7017442",
      "tgn:1000001",
      "tgn:7004643",
      "tgn:7029392"
    ],
    "placetype": [
      "aat:300008347"
    ],
    "id": 1018997,
    "name:xx": "Palmer"
  }
}
