{
  "geometry": {
    "type": "Point",
    "coordinates": [
      -66.8667,
      10.4833
    ]
  },
  "type": "Feature",
  "properties": {
    "hierarchy": [
      "tgn:1132758",
      "tgn:1001902",
      "tgn:1000002",
      "tgn:1000059",
      "tgn:7029392"
    ],
    "placetype": [
      "aat:300008706"
    ],
    "id": 1132758,
    "name:xx": "Chacaito, Quebrada"
  }
}
