{
  "geometry": {
    "type": "Point",
    "coordinates": [
      -121.9333,
      46.5167
    ]
  },
  "type": "Feature",
  "properties": {
    "hierarchy": [
      "tgn:2348545",
      "tgn:1000001",
      "tgn:7012149",
      "tgn:1002594",
      "tgn:7007920",
      "tgn:7029392"
    ],
    "placetype": [
      "aat:300008680"
    ],
    "id": 2348545,
    "name:xx": "Gibbs Lake"
  }
}
