{
  "geometry": {
    "type": "Point",
    "coordinates": [
      -96.1333,
      29.5333
    ]
  },
  "type": "Feature",
  "properties": {
    "hierarchy": [
      "tgn:2550997",
      "tgn:1000001",
      "tgn:7012149",
      "tgn:1003019",
      "tgn:7007826",
      "tgn:7029392"
    ],
    "placetype": [
      "aat:300008347"
    ],
    "id": 2550997,
    "name:xx": "Nottawa"
  }
}
