{
  "geometry": {
    "type": "Point",
    "coordinates": [
      -97.9667,
      29.65
    ]
  },
  "type": "Feature",
  "properties": {
    "hierarchy": [
      "tgn:2104452",
      "tgn:1000001",
      "tgn:7012149",
      "tgn:1002431",
      "tgn:7007826",
      "tgn:7029392"
    ],
    "placetype": [
      "aat:300008347"
    ],
    "id": 2104452,
    "name:xx": "Geronimo"
  }
}
