{
  "geometry": {
    "type": "Point",
    "coordinates": [
      90.8667,
      23.5167
    ]
  },
  "type": "Feature",
  "properties": {
    "hierarchy": [
      "tgn:1065690",
      "tgn:7000188",
      "tgn:1000004",
      "tgn:1000105",
      "tgn:7029392"
    ],
    "placetype": [
      "aat:300008347"
    ],
    "id": 1065690,
    "name:xx": "Elliotganj"
  }
}
