{
  "geometry": {
    "type": "Point",
    "coordinates": [
      6.1833,
      44.2833
    ]
  },
  "type": "Feature",
  "properties": {
    "hierarchy": [
      "tgn:1105391",
      "tgn:1000003",
      "tgn:1000070",
      "tgn:7002895",
      "tgn:7029392"
    ],
    "placetype": [
      "aat:300008795"
    ],
    "id": 1105391,
    "name:xx": "Monges, les"
  }
}
