{
  "geometry": {
    "type": "Point",
    "coordinates": [
      -104.9333,
      39.6167
    ]
  },
  "type": "Feature",
  "properties": {
    "hierarchy": [
      "tgn:2235097",
      "tgn:2000194",
      "tgn:1000001",
      "tgn:7012149",
      "tgn:7007158",
      "tgn:7029392"
    ],
    "placetype": [
      "aat:300008347"
    ],
    "id": 2235097,
    "name:xx": "Cherry Ridge"
  }
}
