{
  "type": "FeatureCollection",
  "features": [
    {
      "geometry": {
        "type": "Point",
        "coordinates": [
          -110.883333,
          27.9
        ]
      },
      "type": "Feature",
      "properties": {
        "hierarchy": [
          "tgn:7350780",
          "tgn:1000001",
          "tgn:1001960",
          "tgn:7005560",
          "tgn:7029392"
        ],
        "placetype": [
          "aat:300386846"
        ],
        "id": 7350780,
        "name:xx": "Baja, Punta"
      }
    },
    {
      "geometry": {
        "type": "Point",
        "coordinates": [
          -112.416667,
          27.583333
        ]
      },
      "type": "Feature",
      "properties": {
        "hierarchy": [
          "tgn:7350781",
          "tgn:1001836",
          "tgn:1000001",
          "tgn:7005560",
          "tgn:7029392"
        ],
        "placetype": [
          "aat:300386846"
        ],
        "id": 7350781,
        "name:xx": "Baja, Punta"
      }
    },
    {
      "geometry": {
        "type": "Point",
        "coordinates": [
          -111.202778,
          25.801667
        ]
      },
      "type": "Feature",
      "properties": {
        "hierarchy": [
          "tgn:7350782",
          "tgn:1001836",
          "tgn:1000001",
          "tgn:7005560",
          "tgn:7029392"
        ],
        "placetype": [
          "aat:300386846"
        ],
        "id": 7350782,
        "name:xx": "Baja, Punta"
      }
    },
    {
      "geometry": {
        "type": "Point",
        "coordinates": [
          -106.333333,
          21.45
        ]
      },
      "type": "Feature",
      "properties": {
        "hierarchy": [
          "tgn:7350783",
          "tgn:1000001",
          "tgn:1001906",
          "tgn:7005560",
          "tgn:7029392"
        ],
        "placetype": [
          "aat:300386846"
        ],
        "id": 7350783,
        "name:xx": "Baja, Punta"
      }
    },
    {
      "geometry": {
        "type": "Point",
        "coordinates": [
          -97.983333,
          19.883333
        ]
      },
      "type": "Feature",
      "properties": {
        "hierarchy": [
          "tgn:7350784",
          "tgn:1000001",
          "tgn:7005592",
          "tgn:7005560",
          "tgn:7029392"
        ],
        "placetype": [
          "aat:300008795"
        ],
        "id": 7350784,
        "name:xx": "Baja, Loma"
      }
    },
    {
      "geometry": {
        "type": "Point",
        "coordinates": [
          -91.8,
          16.533333
        ]
      },
      "type": "Feature",
      "properties": {
        "hierarchy": [
          "tgn:7350785",
          "tgn:7005580",
          "tgn:1000001",
          "tgn:7005560",
          "tgn:7029392"
        ],
        "placetype": [
          "aat:300008347"
        ],
        "id": 7350785,
        "name:xx": "Baja"
      }
    },
    {
      "geometry": {
        "type": "Point",
        "coordinates": [
          -108.8,
          26.1
        ]
      },
      "type": "Feature",
      "properties": {
        "hierarchy": [
          "tgn:7350787",
          "tgn:1000001",
          "tgn:7005595",
          "tgn:7005560",
          "tgn:7029392"
        ],
        "placetype": [
          "aat:300008795"
        ],
        "id": 7350787,
        "name:xx": "Aquincoari, Cerro"
      }
    },
    {
      "geometry": {
        "type": "Point",
        "coordinates": [
          -111.35,
          31.1
        ]
      },
      "type": "Feature",
      "properties": {
        "hierarchy": [
          "tgn:7350788",
          "tgn:1000001",
          "tgn:1001960",
          "tgn:7005560",
          "tgn:7029392"
        ],
        "placetype": [
          "aat:300000241"
        ],
        "id": 7350788,
        "name:xx": "Rancho Aquimuri"
      }
    },
    {
      "geometry": {
        "type": "Point",
        "coordinates": [
          -98.666667,
          17.55
        ]
      },
      "type": "Feature",
      "properties": {
        "hierarchy": [
          "tgn:7350789",
          "tgn:7005585",
          "tgn:1000001",
          "tgn:7005560",
          "tgn:7029392"
        ],
        "placetype": [
          "aat:300008347"
        ],
        "id": 7350789,
        "name:xx": "Aquilpa"
      }
    }
  ]
}
