{
  "geometry": {
    "type": "Point",
    "coordinates": [
      -109.2667,
      38.25
    ]
  },
  "type": "Feature",
  "properties": {
    "hierarchy": [
      "tgn:2129305",
      "tgn:1000001",
      "tgn:7012149",
      "tgn:2002119",
      "tgn:7007827",
      "tgn:7029392"
    ],
    "placetype": [
      "aat:300000390"
    ],
    "id": 2129305,
    "name:xx": "Alice Mine"
  }
}
