{
  "geometry": {
    "type": "Point",
    "coordinates": [
      -121.45,
      46.7167
    ]
  },
  "type": "Feature",
  "properties": {
    "hierarchy": [
      "tgn:2231290",
      "tgn:1000001",
      "tgn:7012149",
      "tgn:1002594",
      "tgn:7007920",
      "tgn:7029392"
    ],
    "placetype": [
      "aat:300008680"
    ],
    "id": 2231290,
    "name:xx": "Chain Lakes"
  }
}
