{
  "geometry": {
    "type": "Point",
    "coordinates": [
      -114.4167,
      41.4833
    ]
  },
  "type": "Feature",
  "properties": {
    "hierarchy": [
      "tgn:2541841",
      "tgn:1000001",
      "tgn:2001411",
      "tgn:7012149",
      "tgn:7007526",
      "tgn:7029392"
    ],
    "placetype": [
      "aat:300266640"
    ],
    "id": 2541841,
    "name:xx": "Ninemile Ridge"
  }
}
