{
  "geometry": {
    "type": "Point",
    "coordinates": [
      -109.2833,
      46.7667
    ]
  },
  "type": "Feature",
  "properties": {
    "hierarchy": [
      "tgn:2497967",
      "tgn:1000001",
      "tgn:7012149",
      "tgn:2001273",
      "tgn:7007524",
      "tgn:7029392"
    ],
    "placetype": [
      "aat:300008761"
    ],
    "id": 2497967,
    "name:xx": "Maynard Coulee"
  }
}
