{
  "type": "FeatureCollection",
  "features": [
    {
      "geometry": {
        "type": "Point",
        "coordinates": [
          -99.6667,
          27.7167
        ]
      },
      "type": "Feature",
      "properties": {
        "hierarchy": [
          "tgn:2619570",
          "tgn:1000001",
          "tgn:7012149",
          "tgn:2002090",
          "tgn:7007826",
          "tgn:7029392"
        ],
        "placetype": [
          "aat:300006191"
        ],
        "id": 2619570,
        "name:xx": "Rincon Tank"
      }
    },
    {
      "geometry": {
        "type": "Point",
        "coordinates": [
          -98.7167,
          27.9167
        ]
      },
      "type": "Feature",
      "properties": {
        "hierarchy": [
          "tgn:2619571",
          "tgn:1000001",
          "tgn:7012149",
          "tgn:2001977",
          "tgn:7007826",
          "tgn:7029392"
        ],
        "placetype": [
          "aat:300006191"
        ],
        "id": 2619571,
        "name:xx": "Rincon Tank"
      }
    },
    {
      "geometry": {
        "type": "Point",
        "coordinates": [
          -97.3167,
          28.1
        ]
      },
      "type": "Feature",
      "properties": {
        "hierarchy": [
          "tgn:2619572",
          "tgn:1000001",
          "tgn:7012149",
          "tgn:2002068",
          "tgn:7007826",
          "tgn:7029392"
        ],
        "placetype": [
          "aat:300006191"
        ],
        "id": 2619572,
        "name:xx": "Rincon Tank"
      }
    },
    {
      "geometry": {
        "type": "Point",
        "coordinates": [
          -98.5833,
          28.7
        ]
      },
      "type": "Feature",
      "properties": {
        "hierarchy": [
          "tgn:2619573",
          "tgn:1000001",
          "tgn:2001936",
          "tgn:7012149",
          "tgn:7007826",
          "tgn:7029392"
        ],
        "placetype": [
          "aat:300006191"
        ],
        "id": 2619573,
        "name:xx": "Rincon Tank"
      }
    },
    {
      "geometry": {
        "type": "Point",
        "coordinates": [
          -100.2,
          28.7833
        ]
      },
      "type": "Feature",
      "properties": {
        "hierarchy": [
          "tgn:2619574",
          "tgn:1000001",
          "tgn:7012149",
          "tgn:2002038",
          "tgn:7007826",
          "tgn:7029392"
        ],
        "placetype": [
          "aat:300006191"
        ],
        "id": 2619574,
        "name:xx": "Rincon Tank"
      }
    },
    {
      "geometry": {
        "type": "Point",
        "coordinates": [
          -99.9333,
          28.8667
        ]
      },
      "type": "Feature",
      "properties": {
        "hierarchy": [
          "tgn:2619575",
          "tgn:1000001",
          "tgn:7012149",
          "tgn:2002100",
          "tgn:7007826",
          "tgn:7029392"
        ],
        "placetype": [
          "aat:300006191"
        ],
        "id": 2619575,
        "name:xx": "Rincon Tank"
      }
    },
    {
      "geometry": {
        "type": "Point",
        "coordinates": [
          -104.3,
          30.6667
        ]
      },
      "type": "Feature",
      "properties": {
        "hierarchy": [
          "tgn:2619576",
          "tgn:1000001",
          "tgn:7012149",
          "tgn:2002010",
          "tgn:7007826",
          "tgn:7029392"
        ],
        "placetype": [
          "aat:300006191"
        ],
        "id": 2619576,
        "name:xx": "Rincon Tank"
      }
    },
    {
      "geometry": {
        "type": "Point",
        "coordinates": [
          -102.3333,
          35.45
        ]
      },
      "type": "Feature",
      "properties": {
        "hierarchy": [
          "tgn:2619577",
          "tgn:1000001",
          "tgn:7012149",
          "tgn:2002051",
          "tgn:7007826",
          "tgn:7029392"
        ],
        "placetype": [
          "aat:300006191"
        ],
        "id": 2619577,
        "name:xx": "Rincon Tank"
      }
    },
    {
      "geometry": {
        "type": "Point",
        "coordinates": [
          -110.55,
          32.1333
        ]
      },
      "type": "Feature",
      "properties": {
        "hierarchy": [
          "tgn:2619578",
          "tgn:1000001",
          "tgn:7006451",
          "tgn:7012149",
          "tgn:2000100",
          "tgn:7029392"
        ],
        "placetype": [
          "aat:300008761"
        ],
        "id": 2619578,
        "name:xx": "Rincon Valley"
      }
    },
    {
      "geometry": {
        "type": "Point",
        "coordinates": [
          -122.6667,
          38.4667
        ]
      },
      "type": "Feature",
      "properties": {
        "hierarchy": [
          "tgn:2619579",
          "tgn:1000001",
          "tgn:7012149",
          "tgn:7007157",
          "tgn:7014516",
          "tgn:7029392"
        ],
        "placetype": [
          "aat:300386845"
        ],
        "id": 2619579,
        "name:xx": "Rincon Valley"
      }
    }
  ]
}
