{
  "geometry": {
    "type": "Point",
    "coordinates": [
      -85.9833,
      31.7833
    ]
  },
  "type": "Feature",
  "properties": {
    "hierarchy": [
      "tgn:2293167",
      "tgn:7002659",
      "tgn:1000001",
      "tgn:7012149",
      "tgn:2000054",
      "tgn:7029392"
    ],
    "placetype": [
      "aat:300008699"
    ],
    "id": 2293167,
    "name:xx": "Double Branch"
  }
}
