{
  "geometry": {
    "type": "Point",
    "coordinates": [
      73.0875,
      17.958889
    ]
  },
  "type": "Feature",
  "properties": {
    "hierarchy": [
      "tgn:7589250",
      "tgn:1000004",
      "tgn:7000198",
      "tgn:1001895",
      "tgn:7029392"
    ],
    "placetype": [
      "aat:300008777"
    ],
    "name:en": "Kānte Peak",
    "id": 7589250
  }
}
