{
  "type": "FeatureCollection",
  "features": [
    {
      "geometry": {
        "type": "Point",
        "coordinates": [
          20.25,
          44.6667
        ]
      },
      "type": "Feature",
      "properties": {
        "hierarchy": [
          "tgn:7015450",
          "tgn:1000003",
          "tgn:7006669",
          "tgn:7029392"
        ],
        "placetype": [
          "aat:300008707"
        ],
        "id": 7015450,
        "name:xx": "Kolubara"
      }
    },
    {
      "geometry": {
        "type": "Point",
        "coordinates": [
          17,
          43
        ]
      },
      "type": "Feature",
      "properties": {
        "hierarchy": [
          "tgn:7015451",
          "tgn:1000003",
          "tgn:7006663",
          "tgn:7029392"
        ],
        "placetype": [
          "aat:300387346"
        ],
        "name:en": "Dalmatia",
        "id": 7015451
      }
    },
    {
      "geometry": {
        "type": "Point",
        "coordinates": [
          -122.0833,
          38
        ]
      },
      "type": "Feature",
      "properties": {
        "hierarchy": [
          "tgn:7015453",
          "tgn:1000001",
          "tgn:7012149",
          "tgn:1002298",
          "tgn:7007157",
          "tgn:7029392"
        ],
        "placetype": [
          "aat:300008347"
        ],
        "id": 7015453,
        "name:xx": "Vine Hill"
      }
    },
    {
      "geometry": {
        "type": "Point",
        "coordinates": [
          -122.35,
          37.8
        ]
      },
      "type": "Feature",
      "properties": {
        "hierarchy": [
          "tgn:7015454",
          "tgn:1000001",
          "tgn:7012149",
          "tgn:7007157",
          "tgn:1002859",
          "tgn:7029392"
        ],
        "placetype": [
          "aat:300008791"
        ],
        "id": 7015454,
        "name:xx": "Yerba Buena Island"
      }
    },
    {
      "geometry": {
        "type": "Point",
        "coordinates": [
          21.95,
          43
        ]
      },
      "type": "Feature",
      "properties": {
        "hierarchy": [
          "tgn:7015456",
          "tgn:1000003",
          "tgn:7006669",
          "tgn:7029392"
        ],
        "placetype": [
          "aat:300008347",
          "aat:300387308",
          "aat:300008375"
        ],
        "id": 7015456,
        "name:xx": "Leskovac"
      }
    },
    {
      "geometry": {
        "type": "Point",
        "coordinates": [
          -121.8833,
          37.3
        ]
      },
      "type": "Feature",
      "properties": {
        "hierarchy": [
          "tgn:7015459",
          "tgn:1000001",
          "tgn:7012149",
          "tgn:7014457",
          "tgn:7007157",
          "tgn:7014475",
          "tgn:7029392"
        ],
        "placetype": [
          "aat:300000745"
        ],
        "id": 7015459,
        "name:xx": "Willow Glen"
      }
    }
  ]
}
