{
  "geometry": {
    "type": "Point",
    "coordinates": [
      -112.7167,
      35.2333
    ]
  },
  "type": "Feature",
  "properties": {
    "hierarchy": [
      "tgn:2501787",
      "tgn:1000001",
      "tgn:7006451",
      "tgn:7012149",
      "tgn:2000103",
      "tgn:7029392"
    ],
    "placetype": [
      "aat:300006191"
    ],
    "id": 2501787,
    "name:xx": "McIntyre Tank"
  }
}
