{
  "geometry": {
    "type": "Point",
    "coordinates": [
      -98.8167,
      33.85
    ]
  },
  "type": "Feature",
  "properties": {
    "hierarchy": [
      "tgn:2635479",
      "tgn:1000001",
      "tgn:7012149",
      "tgn:2002092",
      "tgn:7007826",
      "tgn:7029392"
    ],
    "placetype": [
      "aat:300006075"
    ],
    "id": 2635479,
    "name:xx": "SJ Lateral"
  }
}
