{
  "type": "FeatureCollection",
  "features": [
    {
      "geometry": {
        "type": "Point",
        "coordinates": [
          -75.9667,
          35.1333
        ]
      },
      "type": "Feature",
      "properties": {
        "hierarchy": [
          "tgn:2403750",
          "tgn:1000001",
          "tgn:7012149",
          "tgn:2001506",
          "tgn:7007709",
          "tgn:7029392"
        ],
        "placetype": [
          "aat:300132348"
        ],
        "id": 2403750,
        "name:xx": "Howard Reef"
      }
    },
    {
      "geometry": {
        "type": "Point",
        "coordinates": [
          -107.95,
          39.0167
        ]
      },
      "type": "Feature",
      "properties": {
        "hierarchy": [
          "tgn:2403751",
          "tgn:1000001",
          "tgn:7012149",
          "tgn:2000206",
          "tgn:7007158",
          "tgn:7029392"
        ],
        "placetype": [
          "aat:300006191"
        ],
        "id": 2403751,
        "name:xx": "Howard Reservoir"
      }
    },
    {
      "geometry": {
        "type": "Point",
        "coordinates": [
          -104.3667,
          40.7
        ]
      },
      "type": "Feature",
      "properties": {
        "hierarchy": [
          "tgn:2403752",
          "tgn:1000001",
          "tgn:7012149",
          "tgn:7007158",
          "tgn:2000253",
          "tgn:7029392"
        ],
        "placetype": [
          "aat:300006191"
        ],
        "id": 2403752,
        "name:xx": "Howard Reservoir"
      }
    },
    {
      "geometry": {
        "type": "Point",
        "coordinates": [
          -72.4667,
          41.7667
        ]
      },
      "type": "Feature",
      "properties": {
        "hierarchy": [
          "tgn:2403753",
          "tgn:1000001",
          "tgn:1002461",
          "tgn:7012149",
          "tgn:7007159",
          "tgn:7029392"
        ],
        "placetype": [
          "aat:300006191"
        ],
        "id": 2403753,
        "name:xx": "Howard Reservoir"
      }
    },
    {
      "geometry": {
        "type": "Point",
        "coordinates": [
          -113.9667,
          43.4333
        ]
      },
      "type": "Feature",
      "properties": {
        "hierarchy": [
          "tgn:2403754",
          "tgn:1000001",
          "tgn:2000458",
          "tgn:7012149",
          "tgn:7007250",
          "tgn:7029392"
        ],
        "placetype": [
          "aat:300006191"
        ],
        "id": 2403754,
        "name:xx": "Howard Reservoir"
      }
    },
    {
      "geometry": {
        "type": "Point",
        "coordinates": [
          -106.0167,
          45.3833
        ]
      },
      "type": "Feature",
      "properties": {
        "hierarchy": [
          "tgn:2403755",
          "tgn:1000001",
          "tgn:7012149",
          "tgn:2001297",
          "tgn:7007524",
          "tgn:7029392"
        ],
        "placetype": [
          "aat:300006191"
        ],
        "id": 2403755,
        "name:xx": "Howard Reservoir"
      }
    },
    {
      "geometry": {
        "type": "Point",
        "coordinates": [
          -96.0167,
          30.6833
        ]
      },
      "type": "Feature",
      "properties": {
        "hierarchy": [
          "tgn:2403756",
          "tgn:1000001",
          "tgn:7012149",
          "tgn:1002429",
          "tgn:7007826",
          "tgn:7029392"
        ],
        "placetype": [
          "aat:300006191"
        ],
        "id": 2403756,
        "name:xx": "Howard Reservoir"
      }
    },
    {
      "geometry": {
        "type": "Point",
        "coordinates": [
          -86.35,
          39.2333
        ]
      },
      "type": "Feature",
      "properties": {
        "hierarchy": [
          "tgn:2403757",
          "tgn:1000001",
          "tgn:7012149",
          "tgn:7007252",
          "tgn:7029392"
        ],
        "placetype": [
          "aat:300266640"
        ],
        "id": 2403757,
        "name:xx": "Howard Ridge"
      }
    },
    {
      "geometry": {
        "type": "Point",
        "coordinates": [
          -67.9,
          45.5333
        ]
      },
      "type": "Feature",
      "properties": {
        "hierarchy": [
          "tgn:2403758",
          "tgn:1000001",
          "tgn:7012149",
          "tgn:7014589",
          "tgn:7007515",
          "tgn:7029392"
        ],
        "placetype": [
          "aat:300266640"
        ],
        "id": 2403758,
        "name:xx": "Howard Ridge"
      }
    },
    {
      "geometry": {
        "type": "Point",
        "coordinates": [
          -82.7,
          38.7167
        ]
      },
      "type": "Feature",
      "properties": {
        "hierarchy": [
          "tgn:2403759",
          "tgn:1000001",
          "tgn:7012149",
          "tgn:7007706",
          "tgn:7029392"
        ],
        "placetype": [
          "aat:300266640"
        ],
        "id": 2403759,
        "name:xx": "Howard Ridge"
      }
    }
  ]
}
