{
  "geometry": {
    "type": "Point",
    "coordinates": [
      -49.6333,
      -16.2167
    ]
  },
  "type": "Feature",
  "properties": {
    "hierarchy": [
      "tgn:1021772",
      "tgn:7012827",
      "tgn:7002454",
      "tgn:1000047",
      "tgn:1000002",
      "tgn:7029392"
    ],
    "placetype": [
      "aat:300008347"
    ],
    "id": 1021772,
    "name:xx": "Itauçu"
  }
}
