{
  "geometry": {
    "type": "Point",
    "coordinates": [
      31.628523,
      31.089138
    ]
  },
  "type": "Feature",
  "properties": {
    "hierarchy": [
      "tgn:7537940",
      "tgn:7001242",
      "tgn:1001059",
      "tgn:7016833",
      "tgn:7029392"
    ],
    "placetype": [
      "aat:300008347"
    ],
    "name:en": "Mīt Sa'dān",
    "id": 7537940
  }
}
