{
  "geometry": {
    "type": "Point",
    "coordinates": [
      -83.85,
      37.3167
    ]
  },
  "type": "Feature",
  "properties": {
    "hierarchy": [
      "tgn:2575118",
      "tgn:1000001",
      "tgn:7012149",
      "tgn:7007255",
      "tgn:7029392"
    ],
    "placetype": [
      "aat:300008699"
    ],
    "id": 2575118,
    "name:xx": "Pennington Fork"
  }
}
