{
  "geometry": {
    "type": "Point",
    "coordinates": [
      -87.4167,
      40.8833
    ]
  },
  "type": "Feature",
  "properties": {
    "hierarchy": [
      "tgn:2238210",
      "tgn:1000001",
      "tgn:7012149",
      "tgn:1002717",
      "tgn:7007252",
      "tgn:7029392"
    ],
    "placetype": [
      "aat:300006075"
    ],
    "id": 2238210,
    "name:xx": "Chizum Ditch"
  }
}
