{
  "geometry": {
    "type": "Point",
    "coordinates": [
      119.7167,
      30.4333
    ]
  },
  "type": "Feature",
  "properties": {
    "hierarchy": [
      "tgn:1071954",
      "tgn:1000004",
      "tgn:7002076",
      "tgn:1000111",
      "tgn:7029392"
    ],
    "placetype": [
      "aat:300008347"
    ],
    "id": 1071954,
    "name:xx": "Songcun"
  }
}
