{
  "geometry": {
    "type": "Point",
    "coordinates": [
      -112.05,
      40.75
    ]
  },
  "type": "Feature",
  "properties": {
    "hierarchy": [
      "tgn:2639301",
      "tgn:1000001",
      "tgn:7012149",
      "tgn:2002118",
      "tgn:7007827",
      "tgn:7029392"
    ],
    "placetype": [
      "aat:300008697"
    ],
    "id": 2639301,
    "name:xx": "Salt Spring"
  }
}
