{
  "type": "FeatureCollection",
  "features": [
    {
      "geometry": {
        "type": "Point",
        "coordinates": [
          -8.916667,
          42.85
        ]
      },
      "type": "Feature",
      "properties": {
        "hierarchy": [
          "tgn:1062510",
          "tgn:7002824",
          "tgn:1000003",
          "tgn:7002786",
          "tgn:1000095",
          "tgn:7029392"
        ],
        "placetype": [
          "aat:300008347"
        ],
        "id": 1062510,
        "name:xx": "Sierra de Outes"
      }
    },
    {
      "geometry": {
        "type": "Point",
        "coordinates": [
          -1,
          42.633333
        ]
      },
      "type": "Feature",
      "properties": {
        "hierarchy": [
          "tgn:1062512",
          "tgn:7002759",
          "tgn:7002845",
          "tgn:1000003",
          "tgn:1000095",
          "tgn:7029392"
        ],
        "placetype": [
          "aat:300008347"
        ],
        "id": 1062512,
        "name:xx": "Sigües"
      }
    },
    {
      "geometry": {
        "type": "Point",
        "coordinates": [
          -2.8,
          39.283333
        ]
      },
      "type": "Feature",
      "properties": {
        "hierarchy": [
          "tgn:1062513",
          "tgn:7002816",
          "tgn:1001647",
          "tgn:1000003",
          "tgn:1000095",
          "tgn:7029392"
        ],
        "placetype": [
          "aat:300008347"
        ],
        "id": 1062513,
        "name:xx": "Socuéllamos"
      }
    },
    {
      "geometry": {
        "type": "Point",
        "coordinates": [
          -3.95,
          39.7
        ]
      },
      "type": "Feature",
      "properties": {
        "hierarchy": [
          "tgn:1062515",
          "tgn:7002847",
          "tgn:1001647",
          "tgn:1000003",
          "tgn:1000095",
          "tgn:7029392"
        ],
        "placetype": [
          "aat:300008347"
        ],
        "id": 1062515,
        "name:xx": "Sonseca"
      }
    },
    {
      "geometry": {
        "type": "Point",
        "coordinates": [
          -2.116667,
          37.116667
        ]
      },
      "type": "Feature",
      "properties": {
        "hierarchy": [
          "tgn:1062516",
          "tgn:7002805",
          "tgn:7002758",
          "tgn:1000003",
          "tgn:1000095",
          "tgn:7029392"
        ],
        "placetype": [
          "aat:300008347"
        ],
        "id": 1062516,
        "name:xx": "Sorbas"
      }
    },
    {
      "geometry": {
        "type": "Point",
        "coordinates": [
          1.130453,
          42.413192
        ]
      },
      "type": "Feature",
      "properties": {
        "hierarchy": [
          "tgn:1062518",
          "tgn:7008912",
          "tgn:7030216",
          "tgn:1000003",
          "tgn:1000095",
          "tgn:7029392"
        ],
        "placetype": [
          "aat:300008347"
        ],
        "id": 1062518,
        "name:xx": "Sort"
      }
    }
  ]
}
