{
  "geometry": {
    "type": "Point",
    "coordinates": [
      -117.35,
      33.45
    ]
  },
  "type": "Feature",
  "properties": {
    "hierarchy": [
      "tgn:2217974",
      "tgn:1000001",
      "tgn:7012149",
      "tgn:7007157",
      "tgn:1002858",
      "tgn:7029392"
    ],
    "placetype": [
      "aat:300008706"
    ],
    "id": 2217974,
    "name:xx": "Camps Creek"
  }
}
