{
  "geometry": {
    "type": "Point",
    "coordinates": [
      -102.0167,
      34.4833
    ]
  },
  "type": "Feature",
  "properties": {
    "hierarchy": [
      "tgn:2682182",
      "tgn:1000001",
      "tgn:7012149",
      "tgn:7007826",
      "tgn:7029392"
    ],
    "placetype": [
      "aat:300008761"
    ],
    "id": 2682182,
    "name:xx": "South Tule Draw"
  }
}
