{
  "type": "FeatureCollection",
  "features": [
    {
      "geometry": {
        "type": "Point",
        "coordinates": [
          -81.0333,
          34.1833
        ]
      },
      "type": "Feature",
      "properties": {
        "hierarchy": [
          "tgn:2587300",
          "tgn:1000001",
          "tgn:7012149",
          "tgn:2001764",
          "tgn:7007712",
          "tgn:7029392"
        ],
        "placetype": [
          "aat:300008347"
        ],
        "id": 2587300,
        "name:xx": "Pleasant"
      }
    },
    {
      "geometry": {
        "type": "Point",
        "coordinates": [
          -83.8167,
          36.4833
        ]
      },
      "type": "Feature",
      "properties": {
        "hierarchy": [
          "tgn:2587301",
          "tgn:1000001",
          "tgn:7012149",
          "tgn:2001849",
          "tgn:7007825",
          "tgn:7029392"
        ],
        "placetype": [
          "aat:300008347"
        ],
        "id": 2587301,
        "name:xx": "Pleasant"
      }
    },
    {
      "geometry": {
        "type": "Point",
        "coordinates": [
          -111.8667,
          40.85
        ]
      },
      "type": "Feature",
      "properties": {
        "hierarchy": [
          "tgn:2587302",
          "tgn:1000001",
          "tgn:2002106",
          "tgn:7012149",
          "tgn:7007827",
          "tgn:7029392"
        ],
        "placetype": [
          "aat:300008347"
        ],
        "id": 2587302,
        "name:xx": "Pleasant"
      }
    },
    {
      "geometry": {
        "type": "Point",
        "coordinates": [
          -86.1,
          39.8833
        ]
      },
      "type": "Feature",
      "properties": {
        "hierarchy": [
          "tgn:2587303",
          "tgn:1000001",
          "tgn:7012149",
          "tgn:1002633",
          "tgn:7007252",
          "tgn:7029392"
        ],
        "placetype": [
          "aat:300008347"
        ],
        "id": 2587303,
        "name:xx": "Pleasant Acres"
      }
    },
    {
      "geometry": {
        "type": "Point",
        "coordinates": [
          -85.9,
          39.85
        ]
      },
      "type": "Feature",
      "properties": {
        "hierarchy": [
          "tgn:2587304",
          "tgn:1000001",
          "tgn:7012149",
          "tgn:1002447",
          "tgn:7007252",
          "tgn:7029392"
        ],
        "placetype": [
          "aat:300008347"
        ],
        "id": 2587304,
        "name:xx": "Pleasant Acres"
      }
    },
    {
      "geometry": {
        "type": "Point",
        "coordinates": [
          -88.8,
          33.4333
        ]
      },
      "type": "Feature",
      "properties": {
        "hierarchy": [
          "tgn:2587305",
          "tgn:1000001",
          "tgn:7012149",
          "tgn:2001138",
          "tgn:7007522",
          "tgn:7029392"
        ],
        "placetype": [
          "aat:300008347"
        ],
        "id": 2587305,
        "name:xx": "Pleasant Acres"
      }
    },
    {
      "geometry": {
        "type": "Point",
        "coordinates": [
          -111.9833,
          41.3167
        ]
      },
      "type": "Feature",
      "properties": {
        "hierarchy": [
          "tgn:2587306",
          "tgn:1000001",
          "tgn:7012149",
          "tgn:2002129",
          "tgn:7007827",
          "tgn:7029392"
        ],
        "placetype": [
          "aat:300008347"
        ],
        "id": 2587306,
        "name:xx": "Pleasant Acres"
      }
    },
    {
      "geometry": {
        "type": "Point",
        "coordinates": [
          -95.1833,
          32.3
        ]
      },
      "type": "Feature",
      "properties": {
        "hierarchy": [
          "tgn:2587307",
          "tgn:1000001",
          "tgn:7012149",
          "tgn:1002898",
          "tgn:7007826",
          "tgn:7029392"
        ],
        "placetype": [
          "aat:300006191"
        ],
        "id": 2587307,
        "name:xx": "Pleasant Acres Lake"
      }
    },
    {
      "geometry": {
        "type": "Point",
        "coordinates": [
          -133.9833,
          57.6333
        ]
      },
      "type": "Feature",
      "properties": {
        "hierarchy": [
          "tgn:2587308",
          "tgn:7006450",
          "tgn:1000001",
          "tgn:7012149",
          "tgn:7019760",
          "tgn:7029392"
        ],
        "placetype": [
          "aat:300132316"
        ],
        "id": 2587308,
        "name:xx": "Pleasant Bay"
      }
    },
    {
      "geometry": {
        "type": "Point",
        "coordinates": [
          -67.7667,
          44.5
        ]
      },
      "type": "Feature",
      "properties": {
        "hierarchy": [
          "tgn:2587309",
          "tgn:1000001",
          "tgn:7012149",
          "tgn:7014589",
          "tgn:7007515",
          "tgn:7029392"
        ],
        "placetype": [
          "aat:300132316"
        ],
        "id": 2587309,
        "name:xx": "Pleasant Bay"
      }
    }
  ]
}
