{
  "geometry": {
    "type": "Point",
    "coordinates": [
      -84.0167,
      35.5333
    ]
  },
  "type": "Feature",
  "properties": {
    "hierarchy": [
      "tgn:2253568",
      "tgn:1000001",
      "tgn:7012149",
      "tgn:2001898",
      "tgn:7007825",
      "tgn:7029392"
    ],
    "placetype": [
      "aat:300008761"
    ],
    "id": 2253568,
    "name:xx": "Cook Hollow"
  }
}
