{
  "geometry": {
    "type": "Point",
    "coordinates": [
      17.95,
      40.65
    ]
  },
  "type": "Feature",
  "properties": {
    "hierarchy": [
      "tgn:7057947",
      "tgn:1003442",
      "tgn:1000003",
      "tgn:7010380",
      "tgn:1000080",
      "tgn:7029392"
    ],
    "placetype": [
      "aat:300132316"
    ],
    "id": 7057947,
    "name:xx": "Brindisi, Porto di"
  }
}
