{
  "geometry": {
    "type": "Point",
    "coordinates": [
      74.9125,
      32.8625
    ]
  },
  "type": "Feature",
  "properties": {
    "hierarchy": [
      "tgn:7589678",
      "tgn:1000004",
      "tgn:7000198",
      "tgn:7000799",
      "tgn:7029392"
    ],
    "placetype": [
      "aat:300008699"
    ],
    "name:en": "Balīn Nāla",
    "id": 7589678
  }
}
