{
  "geometry": {
    "type": "Point",
    "coordinates": [
      -85.15,
      33.2667
    ]
  },
  "type": "Feature",
  "properties": {
    "hierarchy": [
      "tgn:2130341",
      "tgn:1000001",
      "tgn:7012149",
      "tgn:2000365",
      "tgn:7007248",
      "tgn:7029392"
    ],
    "placetype": [
      "aat:300008680"
    ],
    "id": 2130341,
    "name:xx": "Allens Lake"
  }
}
