{
  "type": "FeatureCollection",
  "features": [
    {
      "geometry": {
        "type": "Point",
        "coordinates": [
          -88.1833,
          32.2333
        ]
      },
      "type": "Feature",
      "properties": {
        "hierarchy": [
          "tgn:2232590",
          "tgn:7002659",
          "tgn:1000001",
          "tgn:2000011",
          "tgn:7012149",
          "tgn:7029392"
        ],
        "placetype": [
          "aat:300008347"
        ],
        "id": 2232590,
        "name:xx": "Chapel Hill"
      }
    },
    {
      "geometry": {
        "type": "Point",
        "coordinates": [
          -87.2,
          33.8167
        ]
      },
      "type": "Feature",
      "properties": {
        "hierarchy": [
          "tgn:2232591",
          "tgn:7002659",
          "tgn:1000001",
          "tgn:7012149",
          "tgn:2000063",
          "tgn:7029392"
        ],
        "placetype": [
          "aat:300008347"
        ],
        "id": 2232591,
        "name:xx": "Chapel Hill"
      }
    },
    {
      "geometry": {
        "type": "Point",
        "coordinates": [
          -87.25,
          33.6167
        ]
      },
      "type": "Feature",
      "properties": {
        "hierarchy": [
          "tgn:2232592",
          "tgn:7002659",
          "tgn:1000001",
          "tgn:7012149",
          "tgn:2000063",
          "tgn:7029392"
        ],
        "placetype": [
          "aat:300008798"
        ],
        "id": 2232592,
        "name:xx": "Chapel Hill"
      }
    },
    {
      "geometry": {
        "type": "Point",
        "coordinates": [
          -91.6333,
          35.9
        ]
      },
      "type": "Feature",
      "properties": {
        "hierarchy": [
          "tgn:2232593",
          "tgn:1000001",
          "tgn:7016172",
          "tgn:7012149",
          "tgn:2000136",
          "tgn:7029392"
        ],
        "placetype": [
          "aat:300008798"
        ],
        "id": 2232593,
        "name:xx": "Chapel Hill"
      }
    },
    {
      "geometry": {
        "type": "Point",
        "coordinates": [
          -93.85,
          33.9833
        ]
      },
      "type": "Feature",
      "properties": {
        "hierarchy": [
          "tgn:2232594",
          "tgn:1000001",
          "tgn:7016172",
          "tgn:7012149",
          "tgn:2000135",
          "tgn:7029392"
        ],
        "placetype": [
          "aat:300008347"
        ],
        "id": 2232594,
        "name:xx": "Chapel Hill"
      }
    },
    {
      "geometry": {
        "type": "Point",
        "coordinates": [
          -72.2,
          41.4667
        ]
      },
      "type": "Feature",
      "properties": {
        "hierarchy": [
          "tgn:2232595",
          "tgn:1000001",
          "tgn:1002714",
          "tgn:7012149",
          "tgn:7007159",
          "tgn:7029392"
        ],
        "placetype": [
          "aat:300008798"
        ],
        "id": 2232595,
        "name:xx": "Chapel Hill"
      }
    },
    {
      "geometry": {
        "type": "Point",
        "coordinates": [
          -80.0667,
          26.4833
        ]
      },
      "type": "Feature",
      "properties": {
        "hierarchy": [
          "tgn:2232596",
          "tgn:1000001",
          "tgn:7012149",
          "tgn:1002768",
          "tgn:7007240",
          "tgn:7029392"
        ],
        "placetype": [
          "aat:300008347"
        ],
        "id": 2232596,
        "name:xx": "Chapel Hill"
      }
    },
    {
      "geometry": {
        "type": "Point",
        "coordinates": [
          -86.4333,
          38.9833
        ]
      },
      "type": "Feature",
      "properties": {
        "hierarchy": [
          "tgn:2232597",
          "tgn:1000001",
          "tgn:7012149",
          "tgn:1002678",
          "tgn:7007252",
          "tgn:7029392"
        ],
        "placetype": [
          "aat:300008347"
        ],
        "id": 2232597,
        "name:xx": "Chapel Hill"
      }
    },
    {
      "geometry": {
        "type": "Point",
        "coordinates": [
          -90.6333,
          41.4833
        ]
      },
      "type": "Feature",
      "properties": {
        "hierarchy": [
          "tgn:2232598",
          "tgn:1000001",
          "tgn:7012149",
          "tgn:2000642",
          "tgn:7007253",
          "tgn:7029392"
        ],
        "placetype": [
          "aat:300008347"
        ],
        "id": 2232598,
        "name:xx": "Chapel Hill"
      }
    },
    {
      "geometry": {
        "type": "Point",
        "coordinates": [
          -84.8333,
          36.8833
        ]
      },
      "type": "Feature",
      "properties": {
        "hierarchy": [
          "tgn:2232599",
          "tgn:1000001",
          "tgn:7012149",
          "tgn:2000850",
          "tgn:7007255",
          "tgn:7029392"
        ],
        "placetype": [
          "aat:300008798"
        ],
        "id": 2232599,
        "name:xx": "Chapel Hill"
      }
    }
  ]
}
