{
  "type": "FeatureCollection",
  "features": [
    {
      "geometry": {
        "type": "Point",
        "coordinates": [
          -120.8833,
          39.5333
        ]
      },
      "type": "Feature",
      "properties": {
        "hierarchy": [
          "tgn:2011590",
          "tgn:1000001",
          "tgn:7012149",
          "tgn:7007157",
          "tgn:1002894",
          "tgn:7029392"
        ],
        "placetype": [
          "aat:300008347"
        ],
        "id": 2011590,
        "name:xx": "Goodyears Bar"
      }
    },
    {
      "geometry": {
        "type": "Point",
        "coordinates": [
          -118.85,
          34.7833
        ]
      },
      "type": "Feature",
      "properties": {
        "hierarchy": [
          "tgn:2011592",
          "tgn:1000001",
          "tgn:7012149",
          "tgn:7007157",
          "tgn:1002608",
          "tgn:7029392"
        ],
        "placetype": [
          "aat:300008347"
        ],
        "id": 2011592,
        "name:xx": "Gorman"
      }
    },
    {
      "geometry": {
        "type": "Point",
        "coordinates": [
          -119.0833,
          35.3
        ]
      },
      "type": "Feature",
      "properties": {
        "hierarchy": [
          "tgn:2011593",
          "tgn:1000001",
          "tgn:7012149",
          "tgn:1002545",
          "tgn:7007157",
          "tgn:7029392"
        ],
        "placetype": [
          "aat:300387016"
        ],
        "id": 2011593,
        "name:xx": "Gosford"
      }
    },
    {
      "geometry": {
        "type": "Point",
        "coordinates": [
          -119.4167,
          36.35
        ]
      },
      "type": "Feature",
      "properties": {
        "hierarchy": [
          "tgn:2011594",
          "tgn:1000001",
          "tgn:7012149",
          "tgn:7007157",
          "tgn:1002956",
          "tgn:7029392"
        ],
        "placetype": [
          "aat:300008347"
        ],
        "id": 2011594,
        "name:xx": "Goshen"
      }
    },
    {
      "geometry": {
        "type": "Point",
        "coordinates": [
          -117.3,
          34.0333
        ]
      },
      "type": "Feature",
      "properties": {
        "hierarchy": [
          "tgn:2011598",
          "tgn:1000001",
          "tgn:7012149",
          "tgn:7007157",
          "tgn:1002857",
          "tgn:7029392"
        ],
        "placetype": [
          "aat:300008347"
        ],
        "id": 2011598,
        "name:xx": "Grand Terrace"
      }
    },
    {
      "geometry": {
        "type": "Point",
        "coordinates": [
          -117.1,
          34.8833
        ]
      },
      "type": "Feature",
      "properties": {
        "hierarchy": [
          "tgn:2011599",
          "tgn:1000001",
          "tgn:7012149",
          "tgn:7007157",
          "tgn:1002857",
          "tgn:7029392"
        ],
        "placetype": [
          "aat:300008347"
        ],
        "id": 2011599,
        "name:xx": "Grandview"
      }
    }
  ]
}
