{
  "geometry": {
    "type": "Point",
    "coordinates": [
      -116.7667,
      33.25
    ]
  },
  "type": "Feature",
  "properties": {
    "hierarchy": [
      "tgn:2472614",
      "tgn:1000001",
      "tgn:7012149",
      "tgn:7007157",
      "tgn:1002858",
      "tgn:7029392"
    ],
    "placetype": [
      "aat:300386845"
    ],
    "id": 2472614,
    "name:xx": "Love Valley"
  }
}
