{
  "geometry": {
    "type": "Point",
    "coordinates": [
      -82.05,
      26.9333
    ]
  },
  "type": "Feature",
  "properties": {
    "hierarchy": [
      "tgn:2463007",
      "tgn:1000001",
      "tgn:1002258",
      "tgn:7012149",
      "tgn:7007240",
      "tgn:7029392"
    ],
    "placetype": [
      "aat:300008850"
    ],
    "id": 2463007,
    "name:xx": "Live Oak Point"
  }
}
