{
  "geometry": {
    "type": "Point",
    "coordinates": [
      9.3667,
      56.15
    ]
  },
  "type": "Feature",
  "properties": {
    "hierarchy": [
      "tgn:1136656",
      "tgn:7594006",
      "tgn:1000003",
      "tgn:1000066",
      "tgn:7029392"
    ],
    "placetype": [
      "aat:300008347"
    ],
    "id": 1136656,
    "name:xx": "Pårup"
  }
}
