{
  "geometry": {
    "type": "Point",
    "coordinates": [
      -111.0833,
      34.7333
    ]
  },
  "type": "Feature",
  "properties": {
    "hierarchy": [
      "tgn:2262689",
      "tgn:1000001",
      "tgn:7006451",
      "tgn:2000092",
      "tgn:7012149",
      "tgn:7029392"
    ],
    "placetype": [
      "aat:300006191"
    ],
    "id": 2262689,
    "name:xx": "Cow Trap Tank"
  }
}
