{
  "geometry": {
    "type": "Point",
    "coordinates": [
      -95.2333,
      34.8333
    ]
  },
  "type": "Feature",
  "properties": {
    "hierarchy": [
      "tgn:2184380",
      "tgn:1000001",
      "tgn:7012149",
      "tgn:2001661",
      "tgn:7007707",
      "tgn:7029392"
    ],
    "placetype": [
      "aat:300266640"
    ],
    "id": 2184380,
    "name:xx": "Bobcat Ridge"
  }
}
