{
  "type": "FeatureCollection",
  "features": [
    {
      "geometry": {
        "type": "Point",
        "coordinates": [
          -111.2167,
          42.0667
        ]
      },
      "type": "Feature",
      "properties": {
        "hierarchy": [
          "tgn:2159490",
          "tgn:2000455",
          "tgn:1000001",
          "tgn:7012149",
          "tgn:7007250",
          "tgn:7029392"
        ],
        "placetype": [
          "aat:300008761"
        ],
        "id": 2159490,
        "name:xx": "Bee Hunt Hollow"
      }
    },
    {
      "geometry": {
        "type": "Point",
        "coordinates": [
          -82.25,
          27.25
        ]
      },
      "type": "Feature",
      "properties": {
        "hierarchy": [
          "tgn:2159491",
          "tgn:1000001",
          "tgn:7012149",
          "tgn:7007240",
          "tgn:7029392"
        ],
        "placetype": [
          "aat:300008791"
        ],
        "id": 2159491,
        "name:xx": "Bee Island"
      }
    },
    {
      "geometry": {
        "type": "Point",
        "coordinates": [
          -82.2,
          28.7
        ]
      },
      "type": "Feature",
      "properties": {
        "hierarchy": [
          "tgn:2159492",
          "tgn:1000001",
          "tgn:7012149",
          "tgn:1002929",
          "tgn:7007240",
          "tgn:7029392"
        ],
        "placetype": [
          "aat:300008791"
        ],
        "id": 2159492,
        "name:xx": "Bee Island"
      }
    },
    {
      "geometry": {
        "type": "Point",
        "coordinates": [
          -78.4667,
          34.05
        ]
      },
      "type": "Feature",
      "properties": {
        "hierarchy": [
          "tgn:2159493",
          "tgn:1000001",
          "tgn:2001472",
          "tgn:7012149",
          "tgn:7007709",
          "tgn:7029392"
        ],
        "placetype": [
          "aat:300008905"
        ],
        "id": 2159493,
        "name:xx": "Bee Island Bay"
      }
    },
    {
      "geometry": {
        "type": "Point",
        "coordinates": [
          -93.6833,
          34.8167
        ]
      },
      "type": "Feature",
      "properties": {
        "hierarchy": [
          "tgn:2159494",
          "tgn:1000001",
          "tgn:7016172",
          "tgn:7012149",
          "tgn:2000179",
          "tgn:7029392"
        ],
        "placetype": [
          "aat:300008798"
        ],
        "id": 2159494,
        "name:xx": "Bee Knob"
      }
    },
    {
      "geometry": {
        "type": "Point",
        "coordinates": [
          -84.5333,
          34.75
        ]
      },
      "type": "Feature",
      "properties": {
        "hierarchy": [
          "tgn:2159495",
          "tgn:1000001",
          "tgn:7012149",
          "tgn:2000346",
          "tgn:7007248",
          "tgn:7029392"
        ],
        "placetype": [
          "aat:300008798"
        ],
        "id": 2159495,
        "name:xx": "Bee Knob"
      }
    },
    {
      "geometry": {
        "type": "Point",
        "coordinates": [
          -83.6,
          35.4833
        ]
      },
      "type": "Feature",
      "properties": {
        "hierarchy": [
          "tgn:2159496",
          "tgn:1000001",
          "tgn:7012149",
          "tgn:2001543",
          "tgn:7007709",
          "tgn:7029392"
        ],
        "placetype": [
          "aat:300008798"
        ],
        "id": 2159496,
        "name:xx": "Bee Knob"
      }
    },
    {
      "geometry": {
        "type": "Point",
        "coordinates": [
          -80.9333,
          36.1
        ]
      },
      "type": "Feature",
      "properties": {
        "hierarchy": [
          "tgn:2159497",
          "tgn:1000001",
          "tgn:7012149",
          "tgn:2001553",
          "tgn:7007709",
          "tgn:7029392"
        ],
        "placetype": [
          "aat:300008798"
        ],
        "id": 2159497,
        "name:xx": "Bee Knob"
      }
    },
    {
      "geometry": {
        "type": "Point",
        "coordinates": [
          -80.4167,
          38.0833
        ]
      },
      "type": "Feature",
      "properties": {
        "hierarchy": [
          "tgn:2159498",
          "tgn:1000001",
          "tgn:7012149",
          "tgn:2002264",
          "tgn:7013961",
          "tgn:7029392"
        ],
        "placetype": [
          "aat:300008798"
        ],
        "id": 2159498,
        "name:xx": "Bee Knob"
      }
    },
    {
      "geometry": {
        "type": "Point",
        "coordinates": [
          -80.4167,
          38.4167
        ]
      },
      "type": "Feature",
      "properties": {
        "hierarchy": [
          "tgn:2159499",
          "tgn:1000001",
          "tgn:7012149",
          "tgn:2002300",
          "tgn:7013961",
          "tgn:7029392"
        ],
        "placetype": [
          "aat:300008798"
        ],
        "id": 2159499,
        "name:xx": "Bee Knob"
      }
    }
  ]
}
