{
  "geometry": {
    "type": "Point",
    "coordinates": [
      -94.2667,
      30.8333
    ]
  },
  "type": "Feature",
  "properties": {
    "hierarchy": [
      "tgn:2702505",
      "tgn:1000001",
      "tgn:7012149",
      "tgn:1002959",
      "tgn:7007826",
      "tgn:7029392"
    ],
    "placetype": [
      "aat:300008699"
    ],
    "id": 2702505,
    "name:xx": "Sulphur Branch"
  }
}
