{
  "geometry": {
    "type": "Point",
    "coordinates": [
      -95.55,
      40.3333
    ]
  },
  "type": "Feature",
  "properties": {
    "hierarchy": [
      "tgn:2623849",
      "tgn:2001169",
      "tgn:1000001",
      "tgn:7012149",
      "tgn:7007523",
      "tgn:7029392"
    ],
    "placetype": [
      "aat:300006075"
    ],
    "id": 2623849,
    "name:xx": "Rock Creek Ditch"
  }
}
