{
  "geometry": {
    "type": "Point",
    "coordinates": [
      -115.2333,
      41.8667
    ]
  },
  "type": "Feature",
  "properties": {
    "hierarchy": [
      "tgn:2590576",
      "tgn:1000001",
      "tgn:7012149",
      "tgn:7029392"
    ],
    "placetype": [
      "aat:300008706"
    ],
    "id": 2590576,
    "name:xx": "Pole Creek"
  }
}
