{
  "geometry": {
    "type": "Point",
    "coordinates": [
      -87.3167,
      35.85
    ]
  },
  "type": "Feature",
  "properties": {
    "hierarchy": [
      "tgn:2255140",
      "tgn:1000001",
      "tgn:7012149",
      "tgn:7015666",
      "tgn:7007825",
      "tgn:7029392"
    ],
    "placetype": [
      "aat:300008761"
    ],
    "id": 2255140,
    "name:xx": "Cooper Hollow"
  }
}
