{
  "geometry": {
    "type": "Point",
    "coordinates": [
      -67.8167,
      44.95
    ]
  },
  "type": "Feature",
  "properties": {
    "hierarchy": [
      "tgn:2574608",
      "tgn:1000001",
      "tgn:7012149",
      "tgn:7014589",
      "tgn:7007515",
      "tgn:7029392"
    ],
    "placetype": [
      "aat:300008699"
    ],
    "id": 2574608,
    "name:xx": "Pembroke Stream"
  }
}
