{
  "type": "FeatureCollection",
  "features": [
    {
      "geometry": {
        "type": "Point",
        "coordinates": [
          -127.5,
          54.5
        ]
      },
      "type": "Feature",
      "properties": {
        "hierarchy": [
          "tgn:1109901",
          "tgn:7005735",
          "tgn:7005685",
          "tgn:1000001",
          "tgn:7029392"
        ],
        "placetype": [
          "aat:300386831"
        ],
        "id": 1109901,
        "name:xx": "Bulkley Ranges"
      }
    },
    {
      "geometry": {
        "type": "Point",
        "coordinates": [
          40.6833,
          41.3
        ]
      },
      "type": "Feature",
      "properties": {
        "hierarchy": [
          "tgn:1109902",
          "tgn:7012217",
          "tgn:1000004",
          "tgn:7006653",
          "tgn:7029392"
        ],
        "placetype": [
          "aat:300386831"
        ],
        "id": 1109902,
        "name:xx": "Bzybskiy Khrebet"
      }
    },
    {
      "geometry": {
        "type": "Point",
        "coordinates": [
          110,
          51.5333
        ]
      },
      "type": "Feature",
      "properties": {
        "hierarchy": [
          "tgn:1109903",
          "tgn:1000004",
          "tgn:7002435",
          "tgn:7029392"
        ],
        "placetype": [
          "aat:300386831"
        ],
        "id": 1109903,
        "name:xx": "Cagan-Churtej, chrebet"
      }
    },
    {
      "geometry": {
        "type": "Point",
        "coordinates": [
          -129.75,
          61.1333
        ]
      },
      "type": "Feature",
      "properties": {
        "hierarchy": [
          "tgn:1109904",
          "tgn:7005685",
          "tgn:1000001",
          "tgn:7005806",
          "tgn:7029392"
        ],
        "placetype": [
          "aat:300386831"
        ],
        "id": 1109904,
        "name:xx": "Campbell Range"
      }
    },
    {
      "geometry": {
        "type": "Point",
        "coordinates": [
          -111.1667,
          42.9167
        ]
      },
      "type": "Feature",
      "properties": {
        "hierarchy": [
          "tgn:1109905",
          "tgn:1000001",
          "tgn:7012149",
          "tgn:7029392"
        ],
        "placetype": [
          "aat:300386831"
        ],
        "id": 1109905,
        "name:xx": "Caribou Range"
      }
    },
    {
      "geometry": {
        "type": "Point",
        "coordinates": [
          -119.8667,
          39.1833
        ]
      },
      "type": "Feature",
      "properties": {
        "hierarchy": [
          "tgn:1109906",
          "tgn:1000001",
          "tgn:7012149",
          "tgn:7029392"
        ],
        "placetype": [
          "aat:300386831"
        ],
        "id": 1109906,
        "name:xx": "Carson Range"
      }
    },
    {
      "geometry": {
        "type": "Point",
        "coordinates": [
          -119.3167,
          37.8
        ]
      },
      "type": "Feature",
      "properties": {
        "hierarchy": [
          "tgn:1109909",
          "tgn:1000001",
          "tgn:7012149",
          "tgn:7007157",
          "tgn:7029392"
        ],
        "placetype": [
          "aat:300386831"
        ],
        "id": 1109909,
        "name:xx": "Cathedral Range"
      }
    }
  ]
}
