{
  "geometry": {
    "type": "Point",
    "coordinates": [
      -78.5333,
      36.0667
    ]
  },
  "type": "Feature",
  "properties": {
    "hierarchy": [
      "tgn:2539413",
      "tgn:1000001",
      "tgn:7012149",
      "tgn:7007709",
      "tgn:7029392"
    ],
    "placetype": [
      "aat:300008706"
    ],
    "id": 2539413,
    "name:xx": "New Light Creek"
  }
}
