{
  "type": "FeatureCollection",
  "features": [
    {
      "geometry": {
        "type": "Point",
        "coordinates": [
          -101.283333,
          21.9
        ]
      },
      "type": "Feature",
      "properties": {
        "hierarchy": [
          "tgn:7441100",
          "tgn:1000001",
          "tgn:7005594",
          "tgn:7005560",
          "tgn:7029392"
        ],
        "placetype": [
          "aat:300008347"
        ],
        "id": 7441100,
        "name:xx": "Santa Lucía"
      }
    },
    {
      "geometry": {
        "type": "Point",
        "coordinates": [
          -100.666667,
          21.733333
        ]
      },
      "type": "Feature",
      "properties": {
        "hierarchy": [
          "tgn:7441101",
          "tgn:1000001",
          "tgn:7005594",
          "tgn:7005560",
          "tgn:7029392"
        ],
        "placetype": [
          "aat:300008347"
        ],
        "id": 7441101,
        "name:xx": "Santa Lucía"
      }
    },
    {
      "geometry": {
        "type": "Point",
        "coordinates": [
          -98.7,
          21.166667
        ]
      },
      "type": "Feature",
      "properties": {
        "hierarchy": [
          "tgn:7441102",
          "tgn:7005587",
          "tgn:1000001",
          "tgn:7005560",
          "tgn:7029392"
        ],
        "placetype": [
          "aat:300008347"
        ],
        "id": 7441102,
        "name:xx": "Santa Lucía"
      }
    },
    {
      "geometry": {
        "type": "Point",
        "coordinates": [
          -98.45,
          20.933333
        ]
      },
      "type": "Feature",
      "properties": {
        "hierarchy": [
          "tgn:7441103",
          "tgn:7005587",
          "tgn:1000001",
          "tgn:7005560",
          "tgn:7029392"
        ],
        "placetype": [
          "aat:300008347"
        ],
        "id": 7441103,
        "name:xx": "Santa Lucía"
      }
    },
    {
      "geometry": {
        "type": "Point",
        "coordinates": [
          -105.216667,
          20.866667
        ]
      },
      "type": "Feature",
      "properties": {
        "hierarchy": [
          "tgn:7441104",
          "tgn:1000001",
          "tgn:1001906",
          "tgn:7005560",
          "tgn:7029392"
        ],
        "placetype": [
          "aat:300008347"
        ],
        "id": 7441104,
        "name:xx": "Santa Lucía"
      }
    },
    {
      "geometry": {
        "type": "Point",
        "coordinates": [
          -100.6,
          20.866667
        ]
      },
      "type": "Feature",
      "properties": {
        "hierarchy": [
          "tgn:7441105",
          "tgn:7005584",
          "tgn:1000001",
          "tgn:7005560",
          "tgn:7029392"
        ],
        "placetype": [
          "aat:300008347"
        ],
        "id": 7441105,
        "name:xx": "Santa Lucía"
      }
    },
    {
      "geometry": {
        "type": "Point",
        "coordinates": [
          -103.483333,
          20.8
        ]
      },
      "type": "Feature",
      "properties": {
        "hierarchy": [
          "tgn:7441106",
          "tgn:7005586",
          "tgn:1000001",
          "tgn:7005560",
          "tgn:7029392"
        ],
        "placetype": [
          "aat:300008347"
        ],
        "id": 7441106,
        "name:xx": "Santa Lucía"
      }
    },
    {
      "geometry": {
        "type": "Point",
        "coordinates": [
          -102.366667,
          20.35
        ]
      },
      "type": "Feature",
      "properties": {
        "hierarchy": [
          "tgn:7441107",
          "tgn:7005586",
          "tgn:1000001",
          "tgn:7005560",
          "tgn:7029392"
        ],
        "placetype": [
          "aat:300008347"
        ],
        "id": 7441107,
        "name:xx": "Santa Lucía"
      }
    },
    {
      "geometry": {
        "type": "Point",
        "coordinates": [
          -100.05,
          20.316667
        ]
      },
      "type": "Feature",
      "properties": {
        "hierarchy": [
          "tgn:7441108",
          "tgn:1000001",
          "tgn:7005593",
          "tgn:7005560",
          "tgn:7029392"
        ],
        "placetype": [
          "aat:300008347"
        ],
        "id": 7441108,
        "name:xx": "Santa Lucía"
      }
    },
    {
      "geometry": {
        "type": "Point",
        "coordinates": [
          -99,
          19.75
        ]
      },
      "type": "Feature",
      "properties": {
        "hierarchy": [
          "tgn:7441109",
          "tgn:1000001",
          "tgn:1001893",
          "tgn:7005560",
          "tgn:7029392"
        ],
        "placetype": [
          "aat:300008347"
        ],
        "id": 7441109,
        "name:xx": "Santa Lucía"
      }
    }
  ]
}
