{
  "geometry": {
    "type": "Point",
    "coordinates": [
      -2.6333,
      48.3667
    ]
  },
  "type": "Feature",
  "properties": {
    "hierarchy": [
      "tgn:1034418",
      "tgn:1000003",
      "tgn:7012216",
      "tgn:1000070",
      "tgn:7029392"
    ],
    "placetype": [
      "aat:300008347"
    ],
    "id": 1034418,
    "name:xx": "Moncontour"
  }
}
