{
  "geometry": {
    "type": "Point",
    "coordinates": [
      -4.916667,
      40.85
    ]
  },
  "type": "Feature",
  "properties": {
    "hierarchy": [
      "tgn:7293324",
      "tgn:7002806",
      "tgn:7001158",
      "tgn:1000003",
      "tgn:1000095",
      "tgn:7029392"
    ],
    "placetype": [
      "aat:300008347"
    ],
    "id": 7293324,
    "name:xx": "Viñegra de Moraña"
  }
}
