{
  "geometry": {
    "type": "Point",
    "coordinates": [
      -86.2667,
      32.3333
    ]
  },
  "type": "Feature",
  "properties": {
    "hierarchy": [
      "tgn:2629456",
      "tgn:7002659",
      "tgn:1000001",
      "tgn:7012149",
      "tgn:2000050",
      "tgn:7029392"
    ],
    "placetype": [
      "aat:300008347"
    ],
    "id": 2629456,
    "name:xx": "Rosemond Estates"
  }
}
