{
  "geometry": {
    "type": "Point",
    "coordinates": [
      -110.5833,
      48.0833
    ]
  },
  "type": "Feature",
  "properties": {
    "hierarchy": [
      "tgn:2328313",
      "tgn:1000001",
      "tgn:2001267",
      "tgn:7012149",
      "tgn:7007524",
      "tgn:7029392"
    ],
    "placetype": [
      "aat:300008761"
    ],
    "id": 2328313,
    "name:xx": "Fisher Coulee"
  }
}
