{
  "geometry": {
    "type": "Point",
    "coordinates": [
      -113.9333,
      48.9333
    ]
  },
  "type": "Feature",
  "properties": {
    "hierarchy": [
      "tgn:2419276",
      "tgn:1000001",
      "tgn:7012149",
      "tgn:2001277",
      "tgn:7007524",
      "tgn:7029392"
    ],
    "placetype": [
      "aat:300008680"
    ],
    "id": 2419276,
    "name:xx": "Janet, Lake"
  }
}
