{
  "geometry": {
    "type": "Point",
    "coordinates": [
      -76.0667,
      41.7833
    ]
  },
  "type": "Feature",
  "properties": {
    "hierarchy": [
      "tgn:1135124",
      "tgn:1000001",
      "tgn:7012149",
      "tgn:7007710",
      "tgn:7029392"
    ],
    "placetype": [
      "aat:300008706"
    ],
    "id": 1135124,
    "name:xx": "Wyalusing Creek"
  }
}
