{
  "geometry": {
    "type": "Point",
    "coordinates": [
      -86.25,
      35.7167
    ]
  },
  "type": "Feature",
  "properties": {
    "hierarchy": [
      "tgn:2297034",
      "tgn:1000001",
      "tgn:7012149",
      "tgn:2001911",
      "tgn:7007825",
      "tgn:7029392"
    ],
    "placetype": [
      "aat:300008706"
    ],
    "id": 2297034,
    "name:xx": "Dry Creek"
  }
}
