{
  "type": "FeatureCollection",
  "features": [
    {
      "geometry": {
        "type": "Point",
        "coordinates": [
          30.566702,
          31.08052
        ]
      },
      "type": "Feature",
      "properties": {
        "hierarchy": [
          "tgn:7532830",
          "tgn:7001242",
          "tgn:1001075",
          "tgn:7016833",
          "tgn:7029392"
        ],
        "placetype": [
          "aat:300008347"
        ],
        "name:en": "'Izbat al Hawwārīyah",
        "id": 7532830
      }
    },
    {
      "geometry": {
        "type": "Point",
        "coordinates": [
          30.543917,
          31.078448
        ]
      },
      "type": "Feature",
      "properties": {
        "hierarchy": [
          "tgn:7532831",
          "tgn:7001242",
          "tgn:1001075",
          "tgn:7016833",
          "tgn:7029392"
        ],
        "placetype": [
          "aat:300008347"
        ],
        "name:en": "'Izbat al 'Arab",
        "id": 7532831
      }
    },
    {
      "geometry": {
        "type": "Point",
        "coordinates": [
          30.575359,
          31.071414
        ]
      },
      "type": "Feature",
      "properties": {
        "hierarchy": [
          "tgn:7532832",
          "tgn:7001242",
          "tgn:1001075",
          "tgn:7016833",
          "tgn:7029392"
        ],
        "placetype": [
          "aat:300000206"
        ],
        "name:en": "'Izbat Şaqr",
        "id": 7532832
      }
    },
    {
      "geometry": {
        "type": "Point",
        "coordinates": [
          30.566696,
          31.089237
        ]
      },
      "type": "Feature",
      "properties": {
        "hierarchy": [
          "tgn:7532833",
          "tgn:7001242",
          "tgn:7016833",
          "tgn:1001335",
          "tgn:7029392"
        ],
        "placetype": [
          "aat:300008347"
        ],
        "name:en": "'Izbat al Ḩadīdī",
        "id": 7532833
      }
    },
    {
      "geometry": {
        "type": "Point",
        "coordinates": [
          30.579787,
          31.096922
        ]
      },
      "type": "Feature",
      "properties": {
        "hierarchy": [
          "tgn:7532834",
          "tgn:7001242",
          "tgn:1001075",
          "tgn:7016833",
          "tgn:7029392"
        ],
        "placetype": [
          "aat:300008347"
        ],
        "name:en": "Niz̧ārat al Bannā",
        "id": 7532834
      }
    },
    {
      "geometry": {
        "type": "Point",
        "coordinates": [
          30.57379,
          31.098319
        ]
      },
      "type": "Feature",
      "properties": {
        "hierarchy": [
          "tgn:7532835",
          "tgn:7001242",
          "tgn:7016833",
          "tgn:1001335",
          "tgn:7029392"
        ],
        "placetype": [
          "aat:300008347"
        ],
        "name:en": "'Izbat Abū Jubrān",
        "id": 7532835
      }
    },
    {
      "geometry": {
        "type": "Point",
        "coordinates": [
          30.587424,
          31.102335
        ]
      },
      "type": "Feature",
      "properties": {
        "hierarchy": [
          "tgn:7532836",
          "tgn:7001242",
          "tgn:1001075",
          "tgn:7016833",
          "tgn:7029392"
        ],
        "placetype": [
          "aat:300008347"
        ],
        "name:en": "'Izbat Numrah 23",
        "id": 7532836
      }
    },
    {
      "geometry": {
        "type": "Point",
        "coordinates": [
          30.5725,
          31.116944
        ]
      },
      "type": "Feature",
      "properties": {
        "hierarchy": [
          "tgn:7532837",
          "tgn:7001242",
          "tgn:1001075",
          "tgn:7016833",
          "tgn:7029392"
        ],
        "placetype": [
          "aat:300008347"
        ],
        "name:en": "Al Hābīlah Abū Nuşayr",
        "id": 7532837
      }
    },
    {
      "geometry": {
        "type": "Point",
        "coordinates": [
          30.58092,
          31.145096
        ]
      },
      "type": "Feature",
      "properties": {
        "hierarchy": [
          "tgn:7532838",
          "tgn:7001242",
          "tgn:1001075",
          "tgn:7016833",
          "tgn:7029392"
        ],
        "placetype": [
          "aat:300008347"
        ],
        "name:en": "'Izbat Ad.ham",
        "id": 7532838
      }
    },
    {
      "geometry": {
        "type": "Point",
        "coordinates": [
          30.561294,
          31.144841
        ]
      },
      "type": "Feature",
      "properties": {
        "hierarchy": [
          "tgn:7532839",
          "tgn:7001242",
          "tgn:1001075",
          "tgn:7016833",
          "tgn:7029392"
        ],
        "placetype": [
          "aat:300008347"
        ],
        "name:en": "'Izbat Sulţān",
        "id": 7532839
      }
    }
  ]
}
