{
  "type": "FeatureCollection",
  "features": [
    {
      "geometry": {
        "type": "Point",
        "coordinates": [
          -117.4333,
          45.2833
        ]
      },
      "type": "Feature",
      "properties": {
        "hierarchy": [
          "tgn:2155120",
          "tgn:1000001",
          "tgn:7012149",
          "tgn:2001722",
          "tgn:7007708",
          "tgn:7029392"
        ],
        "placetype": [
          "aat:300008680"
        ],
        "id": 2155120,
        "name:xx": "Bear Lake"
      }
    },
    {
      "geometry": {
        "type": "Point",
        "coordinates": [
          -121.7167,
          45.65
        ]
      },
      "type": "Feature",
      "properties": {
        "hierarchy": [
          "tgn:2155121",
          "tgn:1000001",
          "tgn:7012149",
          "tgn:2001710",
          "tgn:7007708",
          "tgn:7029392"
        ],
        "placetype": [
          "aat:300008680"
        ],
        "id": 2155121,
        "name:xx": "Bear Lake"
      }
    },
    {
      "geometry": {
        "type": "Point",
        "coordinates": [
          -121.8333,
          44.7333
        ]
      },
      "type": "Feature",
      "properties": {
        "hierarchy": [
          "tgn:2155122",
          "tgn:1000001",
          "tgn:7012149",
          "tgn:1002636",
          "tgn:7007708",
          "tgn:7029392"
        ],
        "placetype": [
          "aat:300008680"
        ],
        "id": 2155122,
        "name:xx": "Bear Lake"
      }
    },
    {
      "geometry": {
        "type": "Point",
        "coordinates": [
          -124.1167,
          43.9333
        ]
      },
      "type": "Feature",
      "properties": {
        "hierarchy": [
          "tgn:2155123",
          "tgn:1000001",
          "tgn:7012149",
          "tgn:2001716",
          "tgn:7007708",
          "tgn:7029392"
        ],
        "placetype": [
          "aat:300008680"
        ],
        "id": 2155123,
        "name:xx": "Bear Lake"
      }
    },
    {
      "geometry": {
        "type": "Point",
        "coordinates": [
          -75.6167,
          41.2
        ]
      },
      "type": "Feature",
      "properties": {
        "hierarchy": [
          "tgn:2155124",
          "tgn:1000001",
          "tgn:7012149",
          "tgn:1002564",
          "tgn:7007710",
          "tgn:7029392"
        ],
        "placetype": [
          "aat:300008680"
        ],
        "id": 2155124,
        "name:xx": "Bear Lake"
      }
    },
    {
      "geometry": {
        "type": "Point",
        "coordinates": [
          -79.4667,
          41.9833
        ]
      },
      "type": "Feature",
      "properties": {
        "hierarchy": [
          "tgn:2155125",
          "tgn:1000001",
          "tgn:7012149",
          "tgn:1002988",
          "tgn:7007710",
          "tgn:7029392"
        ],
        "placetype": [
          "aat:300006191"
        ],
        "id": 2155125,
        "name:xx": "Bear Lake"
      }
    },
    {
      "geometry": {
        "type": "Point",
        "coordinates": [
          -95.0833,
          29.8
        ]
      },
      "type": "Feature",
      "properties": {
        "hierarchy": [
          "tgn:2155126",
          "tgn:1000001",
          "tgn:7012149",
          "tgn:1002456",
          "tgn:7007826",
          "tgn:7029392"
        ],
        "placetype": [
          "aat:300008680"
        ],
        "id": 2155126,
        "name:xx": "Bear Lake"
      }
    },
    {
      "geometry": {
        "type": "Point",
        "coordinates": [
          -95.8833,
          31.7667
        ]
      },
      "type": "Feature",
      "properties": {
        "hierarchy": [
          "tgn:2155127",
          "tgn:1002148",
          "tgn:1000001",
          "tgn:7012149",
          "tgn:7007826",
          "tgn:7029392"
        ],
        "placetype": [
          "aat:300008680"
        ],
        "id": 2155127,
        "name:xx": "Bear Lake"
      }
    },
    {
      "geometry": {
        "type": "Point",
        "coordinates": [
          -111.5,
          38.0167
        ]
      },
      "type": "Feature",
      "properties": {
        "hierarchy": [
          "tgn:2155128",
          "tgn:1000001",
          "tgn:2002109",
          "tgn:7012149",
          "tgn:7007827",
          "tgn:7029392"
        ],
        "placetype": [
          "aat:300008680"
        ],
        "id": 2155128,
        "name:xx": "Bear Lake"
      }
    },
    {
      "geometry": {
        "type": "Point",
        "coordinates": [
          -110.6333,
          40.55
        ]
      },
      "type": "Feature",
      "properties": {
        "hierarchy": [
          "tgn:2155129",
          "tgn:1000001",
          "tgn:2002107",
          "tgn:7012149",
          "tgn:7007827",
          "tgn:7029392"
        ],
        "placetype": [
          "aat:300008680"
        ],
        "id": 2155129,
        "name:xx": "Bear Lake"
      }
    }
  ]
}
