{
  "type": "FeatureCollection",
  "features": [
    {
      "geometry": {
        "type": "Point",
        "coordinates": [
          -118.1667,
          34.0167
        ]
      },
      "type": "Feature",
      "properties": {
        "hierarchy": [
          "tgn:2011131",
          "tgn:1000001",
          "tgn:7012149",
          "tgn:7007157",
          "tgn:1002608",
          "tgn:7029392"
        ],
        "placetype": [
          "aat:300008347"
        ],
        "id": 2011131,
        "name:xx": "East Los Angeles"
      }
    },
    {
      "geometry": {
        "type": "Point",
        "coordinates": [
          -118.1667,
          34.0333
        ]
      },
      "type": "Feature",
      "properties": {
        "hierarchy": [
          "tgn:2011133",
          "tgn:1000001",
          "tgn:7012149",
          "tgn:2011131",
          "tgn:7007157",
          "tgn:1002608",
          "tgn:7029392"
        ],
        "placetype": [
          "aat:300000745"
        ],
        "id": 2011133,
        "name:xx": "Belvedere"
      }
    },
    {
      "geometry": {
        "type": "Point",
        "coordinates": [
          -118.1667,
          34.05
        ]
      },
      "type": "Feature",
      "properties": {
        "hierarchy": [
          "tgn:2011135",
          "tgn:1000001",
          "tgn:7012149",
          "tgn:2011131",
          "tgn:7007157",
          "tgn:1002608",
          "tgn:7029392"
        ],
        "placetype": [
          "aat:300000745"
        ],
        "id": 2011135,
        "name:xx": "City Terrace"
      }
    },
    {
      "geometry": {
        "type": "Point",
        "coordinates": [
          -121.5333,
          38.9
        ]
      },
      "type": "Feature",
      "properties": {
        "hierarchy": [
          "tgn:2011139",
          "tgn:1000001",
          "tgn:7012149",
          "tgn:7007157",
          "tgn:1002937",
          "tgn:7029392"
        ],
        "placetype": [
          "aat:300008347"
        ],
        "id": 2011139,
        "name:xx": "East Nicolaus"
      }
    }
  ]
}
