{
  "geometry": {
    "type": "Point",
    "coordinates": [
      -105.55,
      43.0167
    ]
  },
  "type": "Feature",
  "properties": {
    "hierarchy": [
      "tgn:2190452",
      "tgn:1000001",
      "tgn:2002369",
      "tgn:7012149",
      "tgn:7007923",
      "tgn:7029392"
    ],
    "placetype": [
      "aat:300266640"
    ],
    "id": 2190452,
    "name:xx": "Box Creek Divide"
  }
}
