{
  "geometry": {
    "type": "Point",
    "coordinates": [
      -76.8833,
      36.15
    ]
  },
  "type": "Feature",
  "properties": {
    "hierarchy": [
      "tgn:2073886",
      "tgn:1000001",
      "tgn:2001470",
      "tgn:7012149",
      "tgn:7007709",
      "tgn:7029392"
    ],
    "placetype": [
      "aat:300008347",
      "aat:300387210"
    ],
    "id": 2073886,
    "name:xx": "Buzzards Crossroads"
  }
}
