{
  "geometry": {
    "type": "Point",
    "coordinates": [
      -149.7667,
      60.6333
    ]
  },
  "type": "Feature",
  "properties": {
    "hierarchy": [
      "tgn:2126544",
      "tgn:7006450",
      "tgn:1000001",
      "tgn:7019698",
      "tgn:7012149",
      "tgn:7029392"
    ],
    "placetype": [
      "aat:300008706"
    ],
    "id": 2126544,
    "name:xx": "Afanasa Creek"
  }
}
