{
  "geometry": {
    "type": "Point",
    "coordinates": [
      -121.8333,
      48.3333
    ]
  },
  "type": "Feature",
  "properties": {
    "hierarchy": [
      "tgn:2359034",
      "tgn:1000001",
      "tgn:7012149",
      "tgn:7014510",
      "tgn:7007920",
      "tgn:7029392"
    ],
    "placetype": [
      "aat:300008680"
    ],
    "id": 2359034,
    "name:xx": "Granite Lake"
  }
}
