{
  "type": "FeatureCollection",
  "features": [
    {
      "geometry": {
        "type": "Point",
        "coordinates": [
          12.15,
          48.2
        ]
      },
      "type": "Feature",
      "properties": {
        "hierarchy": [
          "tgn:7157020",
          "tgn:7003669",
          "tgn:1000003",
          "tgn:7000084",
          "tgn:7029392"
        ],
        "placetype": [
          "aat:300008347"
        ],
        "id": 7157020,
        "name:xx": "Klaus"
      }
    },
    {
      "geometry": {
        "type": "Point",
        "coordinates": [
          6.833333,
          51.75
        ]
      },
      "type": "Feature",
      "properties": {
        "hierarchy": [
          "tgn:7157021",
          "tgn:1000003",
          "tgn:7003677",
          "tgn:7000084",
          "tgn:7029392"
        ],
        "placetype": [
          "aat:300000206"
        ],
        "id": 7157021,
        "name:xx": "Klaus"
      }
    },
    {
      "geometry": {
        "type": "Point",
        "coordinates": [
          12.183333,
          48.2
        ]
      },
      "type": "Feature",
      "properties": {
        "hierarchy": [
          "tgn:7157022",
          "tgn:7003669",
          "tgn:1000003",
          "tgn:7000084",
          "tgn:7029392"
        ],
        "placetype": [
          "aat:300000206"
        ],
        "id": 7157022,
        "name:xx": "Klaus"
      }
    },
    {
      "geometry": {
        "type": "Point",
        "coordinates": [
          7.8,
          53.25
        ]
      },
      "type": "Feature",
      "properties": {
        "hierarchy": [
          "tgn:7157023",
          "tgn:1000003",
          "tgn:7003676",
          "tgn:7000084",
          "tgn:7029392"
        ],
        "placetype": [
          "aat:300387200"
        ],
        "id": 7157023,
        "name:xx": "Klauhörnermoor"
      }
    },
    {
      "geometry": {
        "type": "Point",
        "coordinates": [
          9.8,
          53.35
        ]
      },
      "type": "Feature",
      "properties": {
        "hierarchy": [
          "tgn:7157024",
          "tgn:1000003",
          "tgn:7003676",
          "tgn:7000084",
          "tgn:7029392"
        ],
        "placetype": [
          "aat:300008347"
        ],
        "id": 7157024,
        "name:xx": "Klauenburg"
      }
    },
    {
      "geometry": {
        "type": "Point",
        "coordinates": [
          11.4,
          53.016667
        ]
      },
      "type": "Feature",
      "properties": {
        "hierarchy": [
          "tgn:7157025",
          "tgn:1000003",
          "tgn:7003676",
          "tgn:7000084",
          "tgn:7029392"
        ],
        "placetype": [
          "aat:300008777"
        ],
        "id": 7157025,
        "name:xx": "Klauen-Berge"
      }
    },
    {
      "geometry": {
        "type": "Point",
        "coordinates": [
          7.933333,
          51.966667
        ]
      },
      "type": "Feature",
      "properties": {
        "hierarchy": [
          "tgn:7157026",
          "tgn:1000003",
          "tgn:7003677",
          "tgn:7000084",
          "tgn:7029392"
        ],
        "placetype": [
          "aat:300007783"
        ],
        "id": 7157026,
        "name:xx": "Haltepunkt Klauenberg"
      }
    },
    {
      "geometry": {
        "type": "Point",
        "coordinates": [
          7.85,
          53.016667
        ]
      },
      "type": "Feature",
      "properties": {
        "hierarchy": [
          "tgn:7157027",
          "tgn:1000003",
          "tgn:7003676",
          "tgn:7000084",
          "tgn:7029392"
        ],
        "placetype": [
          "aat:300008347"
        ],
        "id": 7157027,
        "name:xx": "Klauen"
      }
    },
    {
      "geometry": {
        "type": "Point",
        "coordinates": [
          7.083333,
          51.166667
        ]
      },
      "type": "Feature",
      "properties": {
        "hierarchy": [
          "tgn:7157028",
          "tgn:1000003",
          "tgn:7003677",
          "tgn:7000084",
          "tgn:7029392"
        ],
        "placetype": [
          "aat:300008347"
        ],
        "id": 7157028,
        "name:xx": "Klauberg"
      }
    },
    {
      "geometry": {
        "type": "Point",
        "coordinates": [
          13.25,
          53.7
        ]
      },
      "type": "Feature",
      "properties": {
        "hierarchy": [
          "tgn:7157029",
          "tgn:1000003",
          "tgn:7000094",
          "tgn:7000084",
          "tgn:7029392"
        ],
        "placetype": [
          "aat:300008347"
        ],
        "id": 7157029,
        "name:xx": "Klatzow"
      }
    }
  ]
}
