{
  "geometry": {
    "type": "Point",
    "coordinates": [
      80.27323,
      26.603644
    ]
  },
  "type": "Feature",
  "properties": {
    "hierarchy": [
      "tgn:7548371",
      "tgn:1000004",
      "tgn:7000198",
      "tgn:7016722",
      "tgn:7029392"
    ],
    "placetype": [
      "aat:300007783"
    ],
    "name:en": "Brahmāvart",
    "id": 7548371
  }
}
