{
  "type": "FeatureCollection",
  "features": [
    {
      "geometry": {
        "type": "Point",
        "coordinates": [
          -83.2333,
          35.6833
        ]
      },
      "type": "Feature",
      "properties": {
        "hierarchy": [
          "tgn:2785690",
          "tgn:1000001",
          "tgn:7012149",
          "tgn:7007709",
          "tgn:7029392"
        ],
        "placetype": [
          "aat:300008798"
        ],
        "id": 2785690,
        "name:xx": "Yonaguska, Mount"
      }
    },
    {
      "geometry": {
        "type": "Point",
        "coordinates": [
          -83.75,
          34.6333
        ]
      },
      "type": "Feature",
      "properties": {
        "hierarchy": [
          "tgn:2785691",
          "tgn:1000001",
          "tgn:7012149",
          "tgn:2000445",
          "tgn:7007248",
          "tgn:7029392"
        ],
        "placetype": [
          "aat:300008347"
        ],
        "id": 2785691,
        "name:xx": "Yonah"
      }
    },
    {
      "geometry": {
        "type": "Point",
        "coordinates": [
          -83.7,
          34.6333
        ]
      },
      "type": "Feature",
      "properties": {
        "hierarchy": [
          "tgn:2785693",
          "tgn:1000001",
          "tgn:7012149",
          "tgn:2000445",
          "tgn:7007248",
          "tgn:7029392"
        ],
        "placetype": [
          "aat:300008798"
        ],
        "id": 2785693,
        "name:xx": "Yonah Mountain"
      }
    },
    {
      "geometry": {
        "type": "Point",
        "coordinates": [
          -123.65,
          45.1667
        ]
      },
      "type": "Feature",
      "properties": {
        "hierarchy": [
          "tgn:2785695",
          "tgn:1000001",
          "tgn:7012149",
          "tgn:1003044",
          "tgn:7007708",
          "tgn:7029392"
        ],
        "placetype": [
          "aat:300008706"
        ],
        "id": 2785695,
        "name:xx": "Yoncalla Creek"
      }
    },
    {
      "geometry": {
        "type": "Point",
        "coordinates": [
          -123.3,
          43.5167
        ]
      },
      "type": "Feature",
      "properties": {
        "hierarchy": [
          "tgn:2785696",
          "tgn:1000001",
          "tgn:7012149",
          "tgn:2001706",
          "tgn:7007708",
          "tgn:7029392"
        ],
        "placetype": [
          "aat:300008706"
        ],
        "id": 2785696,
        "name:xx": "Yoncalla Creek"
      }
    },
    {
      "geometry": {
        "type": "Point",
        "coordinates": [
          -123.2667,
          43.6
        ]
      },
      "type": "Feature",
      "properties": {
        "hierarchy": [
          "tgn:2785697",
          "tgn:1000001",
          "tgn:7012149",
          "tgn:2001706",
          "tgn:7007708",
          "tgn:7029392"
        ],
        "placetype": [
          "aat:300006191"
        ],
        "id": 2785697,
        "name:xx": "Yoncalla Log Pond"
      }
    },
    {
      "geometry": {
        "type": "Point",
        "coordinates": [
          -123.2667,
          43.6
        ]
      },
      "type": "Feature",
      "properties": {
        "hierarchy": [
          "tgn:2785698",
          "tgn:1000001",
          "tgn:7012149",
          "tgn:2001706",
          "tgn:7007708",
          "tgn:7029392"
        ],
        "placetype": [
          "aat:300006191"
        ],
        "id": 2785698,
        "name:xx": "Yoncalla Lumber Company Log Pond"
      }
    },
    {
      "geometry": {
        "type": "Point",
        "coordinates": [
          -123.2667,
          43.6
        ]
      },
      "type": "Feature",
      "properties": {
        "hierarchy": [
          "tgn:2785699",
          "tgn:1000001",
          "tgn:7012149",
          "tgn:2001706",
          "tgn:7007708",
          "tgn:7029392"
        ],
        "placetype": [
          "aat:300386845"
        ],
        "id": 2785699,
        "name:xx": "Yoncalla Valley"
      }
    }
  ]
}
