{
  "geometry": {
    "type": "Point",
    "coordinates": [
      88.2833,
      21.9667
    ]
  },
  "type": "Feature",
  "properties": {
    "hierarchy": [
      "tgn:1075194",
      "tgn:1000004",
      "tgn:7000198",
      "tgn:1001977",
      "tgn:7029392"
    ],
    "placetype": [
      "aat:300008347"
    ],
    "id": 1075194,
    "name:xx": "Dighipāra"
  }
}
