{
  "type": "FeatureCollection",
  "features": [
    {
      "geometry": {
        "type": "Point",
        "coordinates": [
          10.35,
          47.6
        ]
      },
      "type": "Feature",
      "properties": {
        "hierarchy": [
          "tgn:7207860",
          "tgn:7003669",
          "tgn:1000003",
          "tgn:7000084",
          "tgn:7029392"
        ],
        "placetype": [
          "aat:300008347"
        ],
        "id": 7207860,
        "name:xx": "Buchenberg"
      }
    },
    {
      "geometry": {
        "type": "Point",
        "coordinates": [
          12.533333,
          49.4
        ]
      },
      "type": "Feature",
      "properties": {
        "hierarchy": [
          "tgn:7207861",
          "tgn:7003669",
          "tgn:1000003",
          "tgn:7000084",
          "tgn:7029392"
        ],
        "placetype": [
          "aat:300008795"
        ],
        "id": 7207861,
        "name:xx": "Buchen-Berg"
      }
    },
    {
      "geometry": {
        "type": "Point",
        "coordinates": [
          12.016667,
          53.85
        ]
      },
      "type": "Feature",
      "properties": {
        "hierarchy": [
          "tgn:7207862",
          "tgn:1000003",
          "tgn:7000094",
          "tgn:7000084",
          "tgn:7029392"
        ],
        "placetype": [
          "aat:300008777"
        ],
        "id": 7207862,
        "name:xx": "Buchenberg"
      }
    },
    {
      "geometry": {
        "type": "Point",
        "coordinates": [
          12.55,
          53.7
        ]
      },
      "type": "Feature",
      "properties": {
        "hierarchy": [
          "tgn:7207863",
          "tgn:1000003",
          "tgn:7000094",
          "tgn:7000084",
          "tgn:7029392"
        ],
        "placetype": [
          "aat:300008777"
        ],
        "id": 7207863,
        "name:xx": "Buchenberg"
      }
    },
    {
      "geometry": {
        "type": "Point",
        "coordinates": [
          12.266667,
          53.616667
        ]
      },
      "type": "Feature",
      "properties": {
        "hierarchy": [
          "tgn:7207864",
          "tgn:1000003",
          "tgn:7000094",
          "tgn:7000084",
          "tgn:7029392"
        ],
        "placetype": [
          "aat:300008777"
        ],
        "id": 7207864,
        "name:xx": "Buchen-Berg"
      }
    },
    {
      "geometry": {
        "type": "Point",
        "coordinates": [
          8.816667,
          52.683333
        ]
      },
      "type": "Feature",
      "properties": {
        "hierarchy": [
          "tgn:7207865",
          "tgn:1000003",
          "tgn:7003676",
          "tgn:7000084",
          "tgn:7029392"
        ],
        "placetype": [
          "aat:300008777"
        ],
        "id": 7207865,
        "name:xx": "Büchen-Berg"
      }
    },
    {
      "geometry": {
        "type": "Point",
        "coordinates": [
          11.55,
          52.583333
        ]
      },
      "type": "Feature",
      "properties": {
        "hierarchy": [
          "tgn:7207866",
          "tgn:1000003",
          "tgn:7003687",
          "tgn:7000084",
          "tgn:7029392"
        ],
        "placetype": [
          "aat:300008777"
        ],
        "id": 7207866,
        "name:xx": "Buchen-Berg"
      }
    },
    {
      "geometry": {
        "type": "Point",
        "coordinates": [
          7.383333,
          52.133333
        ]
      },
      "type": "Feature",
      "properties": {
        "hierarchy": [
          "tgn:7207867",
          "tgn:1000003",
          "tgn:7003677",
          "tgn:7000084",
          "tgn:7029392"
        ],
        "placetype": [
          "aat:300008777"
        ],
        "id": 7207867,
        "name:xx": "Buchen-Berg"
      }
    },
    {
      "geometry": {
        "type": "Point",
        "coordinates": [
          9.9,
          51.966667
        ]
      },
      "type": "Feature",
      "properties": {
        "hierarchy": [
          "tgn:7207868",
          "tgn:1000003",
          "tgn:7003676",
          "tgn:7000084",
          "tgn:7029392"
        ],
        "placetype": [
          "aat:300008777"
        ],
        "id": 7207868,
        "name:xx": "Buchen-Berg"
      }
    },
    {
      "geometry": {
        "type": "Point",
        "coordinates": [
          10.933333,
          51.95
        ]
      },
      "type": "Feature",
      "properties": {
        "hierarchy": [
          "tgn:7207869",
          "tgn:1000003",
          "tgn:7003687",
          "tgn:7000084",
          "tgn:7029392"
        ],
        "placetype": [
          "aat:300008777"
        ],
        "id": 7207869,
        "name:xx": "Buchen-Berg"
      }
    }
  ]
}
