{
  "geometry": {
    "type": "Point",
    "coordinates": [
      -88.0167,
      45.55
    ]
  },
  "type": "Feature",
  "properties": {
    "hierarchy": [
      "tgn:2149148",
      "tgn:1000001",
      "tgn:7012149",
      "tgn:2002337",
      "tgn:7007922",
      "tgn:7029392"
    ],
    "placetype": [
      "aat:300008680"
    ],
    "id": 2149148,
    "name:xx": "Barr Lake"
  }
}
