{
  "geometry": {
    "type": "Point",
    "coordinates": [
      -88.4833,
      41.35
    ]
  },
  "type": "Feature",
  "properties": {
    "hierarchy": [
      "tgn:2030279",
      "tgn:1000001",
      "tgn:7012149",
      "tgn:1002430",
      "tgn:7007251",
      "tgn:7029392"
    ],
    "placetype": [
      "aat:300387016"
    ],
    "id": 2030279,
    "name:xx": "Stockdale"
  }
}
