{
  "type": "FeatureCollection",
  "features": [
    {
      "geometry": {
        "type": "Point",
        "coordinates": [
          -6.95,
          43.433333
        ]
      },
      "type": "Feature",
      "properties": {
        "hierarchy": [
          "tgn:7328030",
          "tgn:7008911",
          "tgn:1000003",
          "tgn:7002763",
          "tgn:1000095",
          "tgn:7029392"
        ],
        "placetype": [
          "aat:300008347"
        ],
        "id": 7328030,
        "name:xx": "Requejo"
      }
    },
    {
      "geometry": {
        "type": "Point",
        "coordinates": [
          -6.15,
          43.366667
        ]
      },
      "type": "Feature",
      "properties": {
        "hierarchy": [
          "tgn:7328031",
          "tgn:7008911",
          "tgn:1000003",
          "tgn:7002763",
          "tgn:1000095",
          "tgn:7029392"
        ],
        "placetype": [
          "aat:300008347"
        ],
        "id": 7328031,
        "name:xx": "Requejo"
      }
    },
    {
      "geometry": {
        "type": "Point",
        "coordinates": [
          -4.116667,
          43
        ]
      },
      "type": "Feature",
      "properties": {
        "hierarchy": [
          "tgn:7328032",
          "tgn:7002760",
          "tgn:1000003",
          "tgn:1000095",
          "tgn:7029392"
        ],
        "placetype": [
          "aat:300008347"
        ],
        "id": 7328032,
        "name:xx": "Requejo"
      }
    },
    {
      "geometry": {
        "type": "Point",
        "coordinates": [
          -6.8,
          42.533333
        ]
      },
      "type": "Feature",
      "properties": {
        "hierarchy": [
          "tgn:7328033",
          "tgn:7002826",
          "tgn:7001158",
          "tgn:1000003",
          "tgn:1000095",
          "tgn:7029392"
        ],
        "placetype": [
          "aat:300008347"
        ],
        "id": 7328033,
        "name:xx": "Requejo"
      }
    },
    {
      "geometry": {
        "type": "Point",
        "coordinates": [
          -7.2,
          42.266667
        ]
      },
      "type": "Feature",
      "properties": {
        "hierarchy": [
          "tgn:7328034",
          "tgn:7002831",
          "tgn:1000003",
          "tgn:7002786",
          "tgn:1000095",
          "tgn:7029392"
        ],
        "placetype": [
          "aat:300008347"
        ],
        "id": 7328034,
        "name:xx": "Requejo"
      }
    },
    {
      "geometry": {
        "type": "Point",
        "coordinates": [
          -6.95,
          42.25
        ]
      },
      "type": "Feature",
      "properties": {
        "hierarchy": [
          "tgn:7328035",
          "tgn:7002831",
          "tgn:1000003",
          "tgn:7002786",
          "tgn:1000095",
          "tgn:7029392"
        ],
        "placetype": [
          "aat:300008347"
        ],
        "id": 7328035,
        "name:xx": "Requejo"
      }
    },
    {
      "geometry": {
        "type": "Point",
        "coordinates": [
          -6.75,
          42.033333
        ]
      },
      "type": "Feature",
      "properties": {
        "hierarchy": [
          "tgn:7328036",
          "tgn:7001158",
          "tgn:7002850",
          "tgn:1000003",
          "tgn:1000095",
          "tgn:7029392"
        ],
        "placetype": [
          "aat:300008347"
        ],
        "id": 7328036,
        "name:xx": "Requejo"
      }
    },
    {
      "geometry": {
        "type": "Point",
        "coordinates": [
          -7.75,
          41.966667
        ]
      },
      "type": "Feature",
      "properties": {
        "hierarchy": [
          "tgn:7328037",
          "tgn:7002831",
          "tgn:1000003",
          "tgn:7002786",
          "tgn:1000095",
          "tgn:7029392"
        ],
        "placetype": [
          "aat:300008777"
        ],
        "id": 7328037,
        "name:xx": "Requejo"
      }
    },
    {
      "geometry": {
        "type": "Point",
        "coordinates": [
          -4.5,
          42.916667
        ]
      },
      "type": "Feature",
      "properties": {
        "hierarchy": [
          "tgn:7328038",
          "tgn:7002832",
          "tgn:7001158",
          "tgn:1000003",
          "tgn:1000095",
          "tgn:7029392"
        ],
        "placetype": [
          "aat:300006191"
        ],
        "id": 7328038,
        "name:xx": "Pantano Requejada"
      }
    },
    {
      "geometry": {
        "type": "Point",
        "coordinates": [
          -4.033333,
          43.4
        ]
      },
      "type": "Feature",
      "properties": {
        "hierarchy": [
          "tgn:7328039",
          "tgn:7002760",
          "tgn:1000003",
          "tgn:1000095",
          "tgn:7029392"
        ],
        "placetype": [
          "aat:300008347"
        ],
        "id": 7328039,
        "name:xx": "Requejada"
      }
    }
  ]
}
