{
  "geometry": {
    "type": "Point",
    "coordinates": [
      -65.1333,
      9.8333
    ]
  },
  "type": "Feature",
  "properties": {
    "hierarchy": [
      "tgn:1124068",
      "tgn:1001829",
      "tgn:1000002",
      "tgn:1000059",
      "tgn:7029392"
    ],
    "placetype": [
      "aat:300008707"
    ],
    "id": 1124068,
    "name:xx": "Güere, Río"
  }
}
