{
  "geometry": {
    "type": "Point",
    "coordinates": [
      -102.05,
      19.083333
    ]
  },
  "type": "Feature",
  "properties": {
    "hierarchy": [
      "tgn:7386246",
      "tgn:1000001",
      "tgn:7005590",
      "tgn:7005560",
      "tgn:7029392"
    ],
    "placetype": [
      "aat:300007783"
    ],
    "id": 7386246,
    "name:xx": "Estación Ralizával"
  }
}
