{
  "geometry": {
    "type": "Point",
    "coordinates": [
      -84.7833,
      41.15
    ]
  },
  "type": "Feature",
  "properties": {
    "hierarchy": [
      "tgn:2325277",
      "tgn:1000001",
      "tgn:7012149",
      "tgn:1002776",
      "tgn:7007706",
      "tgn:7029392"
    ],
    "placetype": [
      "aat:300006075"
    ],
    "id": 2325277,
    "name:xx": "Ferrarre Ditch"
  }
}
