{
  "geometry": {
    "type": "Point",
    "coordinates": [
      -110.5667,
      42.5833
    ]
  },
  "type": "Feature",
  "properties": {
    "hierarchy": [
      "tgn:2510055",
      "tgn:1000001",
      "tgn:7012149",
      "tgn:7007923",
      "tgn:7029392"
    ],
    "placetype": [
      "aat:300008680"
    ],
    "id": 2510055,
    "name:xx": "Middle Piney Lake"
  }
}
