{
  "geometry": {
    "type": "Point",
    "coordinates": [
      19.3667,
      43.6167
    ]
  },
  "type": "Feature",
  "properties": {
    "hierarchy": [
      "tgn:1065231",
      "tgn:7018870",
      "tgn:1000003",
      "tgn:7006664",
      "tgn:7029392"
    ],
    "placetype": [
      "aat:300008347"
    ],
    "id": 1065231,
    "name:xx": "Rudo"
  }
}
