{
  "geometry": {
    "type": "Point",
    "coordinates": [
      -109.1833,
      32.4833
    ]
  },
  "type": "Feature",
  "properties": {
    "hierarchy": [
      "tgn:2642878",
      "tgn:1000001",
      "tgn:7006451",
      "tgn:2000094",
      "tgn:7012149",
      "tgn:7029392"
    ],
    "placetype": [
      "aat:300008761"
    ],
    "id": 2642878,
    "name:xx": "Sands Draw"
  }
}
