{
  "geometry": {
    "type": "Point",
    "coordinates": [
      31.254247,
      30.077771
    ]
  },
  "type": "Feature",
  "properties": {
    "hierarchy": [
      "tgn:7531247",
      "tgn:7001242",
      "tgn:7016833",
      "tgn:1001091",
      "tgn:7029392"
    ],
    "placetype": [
      "aat:300006653"
    ],
    "id": 7531247,
    "name:xx": "Markaz Amrāḑ aş Şadr al Qalb"
  }
}
