{
  "geometry": {
    "type": "Point",
    "coordinates": [
      -108.5167,
      38.45
    ]
  },
  "type": "Feature",
  "properties": {
    "hierarchy": [
      "tgn:2547565",
      "tgn:1000001",
      "tgn:7012149",
      "tgn:2000234",
      "tgn:7007158",
      "tgn:7029392"
    ],
    "placetype": [
      "aat:300008706"
    ],
    "id": 2547565,
    "name:xx": "North Fork Tabeguache Creek"
  }
}
