{
  "geometry": {
    "type": "Point",
    "coordinates": [
      -91.3167,
      36.5833
    ]
  },
  "type": "Feature",
  "properties": {
    "hierarchy": [
      "tgn:2058860",
      "tgn:1000001",
      "tgn:7012149",
      "tgn:2001225",
      "tgn:7007523",
      "tgn:7029392"
    ],
    "placetype": [
      "aat:300008347",
      "aat:300387210"
    ],
    "id": 2058860,
    "name:xx": "Garfield"
  }
}
