{
  "geometry": {
    "type": "Point",
    "coordinates": [
      79.9415,
      27.0588
    ]
  },
  "type": "Feature",
  "properties": {
    "hierarchy": [
      "tgn:7563281",
      "tgn:1000004",
      "tgn:7000198",
      "tgn:7016722",
      "tgn:7029392"
    ],
    "placetype": [
      "aat:300008347"
    ],
    "name:en": "Daryāpurpatti",
    "id": 7563281
  }
}
