{
  "geometry": {
    "type": "Point",
    "coordinates": [
      -110.2667,
      36.4333
    ]
  },
  "type": "Feature",
  "properties": {
    "hierarchy": [
      "tgn:2766114",
      "tgn:1000001",
      "tgn:7006451",
      "tgn:7012149",
      "tgn:2000099",
      "tgn:7029392"
    ],
    "placetype": [
      "aat:300008761"
    ],
    "id": 2766114,
    "name:xx": "White House Valley"
  }
}
