{
  "geometry": {
    "type": "Point",
    "coordinates": [
      -81.15,
      35.3167
    ]
  },
  "type": "Feature",
  "properties": {
    "hierarchy": [
      "tgn:2320089",
      "tgn:1000001",
      "tgn:7012149",
      "tgn:2001496",
      "tgn:7007709",
      "tgn:7029392"
    ],
    "placetype": [
      "aat:300008680"
    ],
    "id": 2320089,
    "name:xx": "Evans Lake"
  }
}
