{
  "geometry": {
    "type": "Point",
    "coordinates": [
      31.831282,
      30.533875
    ]
  },
  "type": "Feature",
  "properties": {
    "hierarchy": [
      "tgn:7520615",
      "tgn:7001242",
      "tgn:7016833",
      "tgn:1001080",
      "tgn:7029392"
    ],
    "placetype": [
      "aat:300008347"
    ],
    "name:en": "Al Jazīrah al Khaḑrā'",
    "id": 7520615
  }
}
