{
  "geometry": {
    "type": "Point",
    "coordinates": [
      -106.5667,
      40.4333
    ]
  },
  "type": "Feature",
  "properties": {
    "hierarchy": [
      "tgn:2775233",
      "tgn:1000001",
      "tgn:7012149",
      "tgn:2000220",
      "tgn:7007158",
      "tgn:7029392"
    ],
    "placetype": [
      "aat:300008706"
    ],
    "id": 2775233,
    "name:xx": "Wilset Creek"
  }
}
