{
  "geometry": {
    "type": "Point",
    "coordinates": [
      -105.85,
      31.9667
    ]
  },
  "type": "Feature",
  "properties": {
    "hierarchy": [
      "tgn:2305929",
      "tgn:1000001",
      "tgn:7012149",
      "tgn:2002005",
      "tgn:7007826",
      "tgn:7029392"
    ],
    "placetype": [
      "aat:300006191"
    ],
    "id": 2305929,
    "name:xx": "East Elevenmile Tank"
  }
}
