{
  "geometry": {
    "type": "Point",
    "coordinates": [
      8.35,
      46.75
    ]
  },
  "type": "Feature",
  "properties": {
    "hierarchy": [
      "tgn:1064067",
      "tgn:7003742",
      "tgn:1000003",
      "tgn:7011731",
      "tgn:7029392"
    ],
    "placetype": [
      "aat:300008347"
    ],
    "id": 1064067,
    "name:xx": "Gadmen"
  }
}
