{
  "type": "FeatureCollection",
  "features": [
    {
      "geometry": {
        "type": "Point",
        "coordinates": [
          5.4,
          51.55
        ]
      },
      "type": "Feature",
      "properties": {
        "hierarchy": [
          "tgn:7256180",
          "tgn:1000003",
          "tgn:7003624",
          "tgn:7016845",
          "tgn:7029392"
        ],
        "placetype": [
          "aat:300008699"
        ],
        "name:nl": "Berkenloop",
        "id": 7256180
      }
    },
    {
      "geometry": {
        "type": "Point",
        "coordinates": [
          6.05,
          51.633333
        ]
      },
      "type": "Feature",
      "properties": {
        "hierarchy": [
          "tgn:7256181",
          "tgn:1000003",
          "tgn:7003622",
          "tgn:7016845",
          "tgn:7029392"
        ],
        "placetype": [
          "aat:300387200"
        ],
        "name:nl": "Berkenkamp",
        "id": 7256181
      }
    },
    {
      "geometry": {
        "type": "Point",
        "coordinates": [
          5.983333,
          51.733333
        ]
      },
      "type": "Feature",
      "properties": {
        "hierarchy": [
          "tgn:7256183",
          "tgn:1000003",
          "tgn:7003622",
          "tgn:7016845",
          "tgn:7029392"
        ],
        "placetype": [
          "aat:300000206"
        ],
        "name:nl": "Berkenhoeve",
        "id": 7256183
      }
    },
    {
      "geometry": {
        "type": "Point",
        "coordinates": [
          6.3,
          52.883333
        ]
      },
      "type": "Feature",
      "properties": {
        "hierarchy": [
          "tgn:7256184",
          "tgn:7003614",
          "tgn:1000003",
          "tgn:7016845",
          "tgn:7029392"
        ],
        "placetype": [
          "aat:300008863"
        ],
        "name:nl": "Berkenheuvel",
        "id": 7256184
      }
    },
    {
      "geometry": {
        "type": "Point",
        "coordinates": [
          4.35,
          52.016667
        ]
      },
      "type": "Feature",
      "properties": {
        "hierarchy": [
          "tgn:7256185",
          "tgn:1000003",
          "tgn:7003632",
          "tgn:7016845",
          "tgn:7029392"
        ],
        "placetype": [
          "aat:300006075"
        ],
        "name:nl": "Berkelsche Zweth",
        "id": 7256185
      }
    },
    {
      "geometry": {
        "type": "Point",
        "coordinates": [
          5.866667,
          51.116667
        ]
      },
      "type": "Feature",
      "properties": {
        "hierarchy": [
          "tgn:7256188",
          "tgn:1000003",
          "tgn:7003622",
          "tgn:7016845",
          "tgn:7029392"
        ],
        "placetype": [
          "aat:300008347"
        ],
        "name:nl": "Berkelaar",
        "id": 7256188
      }
    },
    {
      "geometry": {
        "type": "Point",
        "coordinates": [
          6.2,
          52.133333
        ]
      },
      "type": "Feature",
      "properties": {
        "hierarchy": [
          "tgn:7256189",
          "tgn:7003619",
          "tgn:1000003",
          "tgn:7016845",
          "tgn:7029392"
        ],
        "placetype": [
          "aat:300008699"
        ],
        "name:nl": "Berkel",
        "id": 7256189
      }
    }
  ]
}
