{
  "geometry": {
    "type": "Point",
    "coordinates": [
      5.8333,
      47.2667
    ]
  },
  "type": "Feature",
  "properties": {
    "hierarchy": [
      "tgn:1035052",
      "tgn:1000003",
      "tgn:7002881",
      "tgn:1000070",
      "tgn:7029392"
    ],
    "placetype": [
      "aat:300008347"
    ],
    "id": 1035052,
    "name:xx": "Recologne"
  }
}
