{
  "geometry": {
    "type": "Point",
    "coordinates": [
      -76.4667,
      37.9167
    ]
  },
  "type": "Feature",
  "properties": {
    "hierarchy": [
      "tgn:7022087",
      "tgn:1000001",
      "tgn:7012149",
      "tgn:1002733",
      "tgn:7007919",
      "tgn:7029392"
    ],
    "placetype": [
      "aat:300006191"
    ],
    "id": 7022087,
    "name:xx": "Clark Millpond"
  }
}
