{
  "geometry": {
    "type": "Point",
    "coordinates": [
      -88.7333,
      39.0833
    ]
  },
  "type": "Feature",
  "properties": {
    "hierarchy": [
      "tgn:2650788",
      "tgn:1000001",
      "tgn:1002349",
      "tgn:7012149",
      "tgn:7007251",
      "tgn:7029392"
    ],
    "placetype": [
      "aat:300008706"
    ],
    "id": 2650788,
    "name:xx": "Second Creek"
  }
}
