{
  "geometry": {
    "type": "Point",
    "coordinates": [
      79.441393,
      27.10607
    ]
  },
  "type": "Feature",
  "properties": {
    "hierarchy": [
      "tgn:7561055",
      "tgn:1000004",
      "tgn:7000198",
      "tgn:7016722",
      "tgn:7029392"
    ],
    "placetype": [
      "aat:300008347"
    ],
    "name:en": "Nagla Khamaria",
    "id": 7561055
  }
}
