{
  "geometry": {
    "type": "Point",
    "coordinates": [
      -90.8167,
      37.2167
    ]
  },
  "type": "Feature",
  "properties": {
    "hierarchy": [
      "tgn:2287646",
      "tgn:1000001",
      "tgn:7012149",
      "tgn:2001236",
      "tgn:7007523",
      "tgn:7029392"
    ],
    "placetype": [
      "aat:300008761"
    ],
    "id": 2287646,
    "name:xx": "Dill Hollow"
  }
}
