{
  "geometry": {
    "type": "Point",
    "coordinates": [
      31.29686,
      30.070866
    ]
  },
  "type": "Feature",
  "properties": {
    "hierarchy": [
      "tgn:7526323",
      "tgn:7001242",
      "tgn:7016833",
      "tgn:1001091",
      "tgn:7029392"
    ],
    "placetype": [
      "aat:300004792"
    ],
    "id": 7526323,
    "name:xx": "Wizārat al Istithmār"
  }
}
