{
  "geometry": {
    "type": "Point",
    "coordinates": [
      -104.1667,
      30.0167
    ]
  },
  "type": "Feature",
  "properties": {
    "hierarchy": [
      "tgn:2301298",
      "tgn:1000001",
      "tgn:7012149",
      "tgn:2002057",
      "tgn:7007826",
      "tgn:7029392"
    ],
    "placetype": [
      "aat:300008706"
    ],
    "id": 2301298,
    "name:xx": "Dunman Creek"
  }
}
