{
  "geometry": {
    "type": "Point",
    "coordinates": [
      -108.4167,
      43.4333
    ]
  },
  "type": "Feature",
  "properties": {
    "hierarchy": [
      "tgn:2507363",
      "tgn:1000001",
      "tgn:7012149",
      "tgn:2002371",
      "tgn:7007923",
      "tgn:7029392"
    ],
    "placetype": [
      "aat:300008347"
    ],
    "id": 2507363,
    "name:xx": "Mexican Place"
  }
}
