{
  "geometry": {
    "type": "Point",
    "coordinates": [
      -91.2167,
      40.15
    ]
  },
  "type": "Feature",
  "properties": {
    "hierarchy": [
      "tgn:2028854",
      "tgn:1002134",
      "tgn:1000001",
      "tgn:7012149",
      "tgn:7007251",
      "tgn:7029392"
    ],
    "placetype": [
      "aat:300008347"
    ],
    "id": 2028854,
    "name:xx": "Loraine"
  }
}
