{
  "geometry": {
    "type": "Point",
    "coordinates": [
      -150.55,
      60.1167
    ]
  },
  "type": "Feature",
  "properties": {
    "hierarchy": [
      "tgn:2317208",
      "tgn:7006450",
      "tgn:1000001",
      "tgn:7019698",
      "tgn:7012149",
      "tgn:7029392"
    ],
    "placetype": [
      "aat:300008680"
    ],
    "id": 2317208,
    "name:xx": "Emma, Lake"
  }
}
