{
  "geometry": {
    "type": "Point",
    "coordinates": [
      -91.6833,
      38.9167
    ]
  },
  "type": "Feature",
  "properties": {
    "hierarchy": [
      "tgn:2423489",
      "tgn:1000001",
      "tgn:1002223",
      "tgn:7012149",
      "tgn:7007523",
      "tgn:7029392"
    ],
    "placetype": [
      "aat:300006191"
    ],
    "id": 2423489,
    "name:xx": "John Gasper Lake"
  }
}
