{
  "geometry": {
    "type": "Point",
    "coordinates": [
      4.75,
      52.65
    ]
  },
  "type": "Feature",
  "properties": {
    "hierarchy": [
      "tgn:7265226",
      "tgn:1000003",
      "tgn:7006951",
      "tgn:7016845",
      "tgn:7029392"
    ],
    "placetype": [
      "aat:300008347"
    ],
    "name:nl": "Huiswaard",
    "id": 7265226
  }
}
