{
  "geometry": {
    "type": "Point",
    "coordinates": [
      31.363865,
      30.052547
    ]
  },
  "type": "Feature",
  "properties": {
    "hierarchy": [
      "tgn:7531700",
      "tgn:7001242",
      "tgn:7016833",
      "tgn:1001091",
      "tgn:7029392"
    ],
    "placetype": [
      "aat:300004792"
    ],
    "id": 7531700,
    "name:xx": "Al Hay'ah al Qawmīyah lil Ta'mīnāt al Ijtimā'īyah"
  }
}
