{
  "geometry": {
    "type": "Point",
    "coordinates": [
      -107.6833,
      39.0333
    ]
  },
  "type": "Feature",
  "properties": {
    "hierarchy": [
      "tgn:2582058",
      "tgn:1000001",
      "tgn:7012149",
      "tgn:2000206",
      "tgn:7007158",
      "tgn:7029392"
    ],
    "placetype": [
      "aat:300006191"
    ],
    "id": 2582058,
    "name:xx": "Pine Cone Reservoir"
  }
}
