{
  "geometry": {
    "type": "Point",
    "coordinates": [
      -111.9333,
      35.0667
    ]
  },
  "type": "Feature",
  "properties": {
    "hierarchy": [
      "tgn:2348110",
      "tgn:1000001",
      "tgn:7006451",
      "tgn:2000092",
      "tgn:7012149",
      "tgn:7029392"
    ],
    "placetype": [
      "aat:300008697"
    ],
    "id": 2348110,
    "name:xx": "Geronimo Spring"
  }
}
