{
  "geometry": {
    "type": "Point",
    "coordinates": [
      -110.2833,
      45.5667
    ]
  },
  "type": "Feature",
  "properties": {
    "hierarchy": [
      "tgn:2757511",
      "tgn:1000001",
      "tgn:7012149",
      "tgn:2001293",
      "tgn:7007524",
      "tgn:7029392"
    ],
    "placetype": [
      "aat:300266640"
    ],
    "id": 2757511,
    "name:xx": "West Boulder Divide"
  }
}
