{
  "geometry": {
    "type": "Point",
    "coordinates": [
      -84.083,
      11.75
    ]
  },
  "type": "Feature",
  "properties": {
    "hierarchy": [
      "tgn:1109829",
      "tgn:7593359",
      "tgn:1000001",
      "tgn:7005562",
      "tgn:7029392"
    ],
    "placetype": [
      "aat:300266640"
    ],
    "id": 1109829,
    "name:xx": "Yolaina, Serranías de"
  }
}
