{
  "geometry": {
    "type": "Point",
    "coordinates": [
      74.820833,
      34.063889
    ]
  },
  "type": "Feature",
  "properties": {
    "hierarchy": [
      "tgn:7587620",
      "tgn:1000004",
      "tgn:7000198",
      "tgn:7000799",
      "tgn:7029392"
    ],
    "placetype": [
      "aat:300008347"
    ],
    "name:en": "Yekrājpur",
    "id": 7587620
  }
}
