{
  "type": "FeatureCollection",
  "features": [
    {
      "geometry": {
        "type": "Point",
        "coordinates": [
          -122.2,
          37.9
        ]
      },
      "type": "Feature",
      "properties": {
        "hierarchy": [
          "tgn:1119510",
          "tgn:1000001",
          "tgn:7012149",
          "tgn:1002298",
          "tgn:7007157",
          "tgn:7029392"
        ],
        "placetype": [
          "aat:300006191"
        ],
        "id": 1119510,
        "name:xx": "Briones Reservoir"
      }
    },
    {
      "geometry": {
        "type": "Point",
        "coordinates": [
          -71.05,
          42.1
        ]
      },
      "type": "Feature",
      "properties": {
        "hierarchy": [
          "tgn:1119511",
          "tgn:1000001",
          "tgn:1002724",
          "tgn:7012149",
          "tgn:7007517",
          "tgn:7029392"
        ],
        "placetype": [
          "aat:300006191"
        ],
        "id": 1119511,
        "name:xx": "Brockton Reservoir"
      }
    },
    {
      "geometry": {
        "type": "Point",
        "coordinates": [
          -94.6667,
          34.1333
        ]
      },
      "type": "Feature",
      "properties": {
        "hierarchy": [
          "tgn:1119512",
          "tgn:1000001",
          "tgn:7012149",
          "tgn:2001667",
          "tgn:7007707",
          "tgn:7029392"
        ],
        "placetype": [
          "aat:300006191"
        ],
        "id": 1119512,
        "name:xx": "Broken Bow Lake"
      }
    },
    {
      "geometry": {
        "type": "Point",
        "coordinates": [
          28.6833,
          -25.9167
        ]
      },
      "type": "Feature",
      "properties": {
        "hierarchy": [
          "tgn:1119513",
          "tgn:7001242",
          "tgn:7017576",
          "tgn:1000193",
          "tgn:7029392"
        ],
        "placetype": [
          "aat:300006191"
        ],
        "id": 1119513,
        "name:xx": "Bronkhorstspruitdam"
      }
    },
    {
      "geometry": {
        "type": "Point",
        "coordinates": [
          -99,
          31.8333
        ]
      },
      "type": "Feature",
      "properties": {
        "hierarchy": [
          "tgn:1119516",
          "tgn:1000001",
          "tgn:2001948",
          "tgn:7012149",
          "tgn:7007826",
          "tgn:7029392"
        ],
        "placetype": [
          "aat:300008680",
          "aat:300006191"
        ],
        "id": 1119516,
        "name:xx": "Brownwood, Lake"
      }
    },
    {
      "geometry": {
        "type": "Point",
        "coordinates": [
          -2.716667,
          40.416667
        ]
      },
      "type": "Feature",
      "properties": {
        "hierarchy": [
          "tgn:1119518",
          "tgn:1001647",
          "tgn:1000003",
          "tgn:1000095",
          "tgn:7029392"
        ],
        "placetype": [
          "aat:300006191"
        ],
        "id": 1119518,
        "name:xx": "Buendia, Embalse de"
      }
    },
    {
      "geometry": {
        "type": "Point",
        "coordinates": [
          -109.2167,
          44.4833
        ]
      },
      "type": "Feature",
      "properties": {
        "hierarchy": [
          "tgn:1119519",
          "tgn:1000001",
          "tgn:7012149",
          "tgn:2002379",
          "tgn:7007923",
          "tgn:7029392"
        ],
        "placetype": [
          "aat:300006191"
        ],
        "id": 1119519,
        "name:xx": "Buffalo Bill Reservoir"
      }
    }
  ]
}
