{
  "geometry": {
    "type": "Point",
    "coordinates": [
      73.477152,
      27.218846
    ]
  },
  "type": "Feature",
  "properties": {
    "hierarchy": [
      "tgn:7573572",
      "tgn:1000004",
      "tgn:7000198",
      "tgn:7016788",
      "tgn:7029392"
    ],
    "placetype": [
      "aat:300008347"
    ],
    "name:en": "Gura Bhagwāndās",
    "id": 7573572
  }
}
