{
  "geometry": {
    "type": "Point",
    "coordinates": [
      -106.6167,
      44.3667
    ]
  },
  "type": "Feature",
  "properties": {
    "hierarchy": [
      "tgn:2612862",
      "tgn:1000001",
      "tgn:7012149",
      "tgn:2002374",
      "tgn:7007923",
      "tgn:7029392"
    ],
    "placetype": [
      "aat:300006075"
    ],
    "id": 2612862,
    "name:xx": "Redman Ditch"
  }
}
