{
  "geometry": {
    "type": "Point",
    "coordinates": [
      -112.35,
      35.3167
    ]
  },
  "type": "Feature",
  "properties": {
    "hierarchy": [
      "tgn:2591412",
      "tgn:1000001",
      "tgn:7006451",
      "tgn:2000092",
      "tgn:7012149",
      "tgn:7029392"
    ],
    "placetype": [
      "aat:300008761"
    ],
    "id": 2591412,
    "name:xx": "Polson Dam Draw"
  }
}
