{
  "geometry": {
    "type": "Point",
    "coordinates": [
      -100.8667,
      29.3667
    ]
  },
  "type": "Feature",
  "properties": {
    "hierarchy": [
      "tgn:2640367",
      "tgn:1000001",
      "tgn:7012149",
      "tgn:2002088",
      "tgn:7007826",
      "tgn:7029392"
    ],
    "placetype": [
      "aat:300008697"
    ],
    "id": 2640367,
    "name:xx": "San Felipe Springs"
  }
}
