{
  "geometry": {
    "type": "Point",
    "coordinates": [
      -109.4833,
      45.0167
    ]
  },
  "type": "Feature",
  "properties": {
    "hierarchy": [
      "tgn:2479052",
      "tgn:1000001",
      "tgn:7012149",
      "tgn:7029392"
    ],
    "placetype": [
      "aat:300008706"
    ],
    "id": 2479052,
    "name:xx": "Laduala Creek"
  }
}
