{
  "geometry": {
    "type": "Point",
    "coordinates": [
      -90.0833,
      35.5167
    ]
  },
  "type": "Feature",
  "properties": {
    "hierarchy": [
      "tgn:2551388",
      "tgn:1000001",
      "tgn:7016172",
      "tgn:7012149",
      "tgn:2000151",
      "tgn:7029392"
    ],
    "placetype": [
      "aat:300006075"
    ],
    "id": 2551388,
    "name:xx": "Number 1, Ditch"
  }
}
