{
  "geometry": {
    "type": "Point",
    "coordinates": [
      -109.8833,
      43.8167
    ]
  },
  "type": "Feature",
  "properties": {
    "hierarchy": [
      "tgn:2270844",
      "tgn:1000001",
      "tgn:7012149",
      "tgn:7007923",
      "tgn:7029392"
    ],
    "placetype": [
      "aat:300008706"
    ],
    "id": 2270844,
    "name:xx": "Cub Creek"
  }
}
