{
  "geometry": {
    "type": "Point",
    "coordinates": [
      -98.6833,
      31.0833
    ]
  },
  "type": "Feature",
  "properties": {
    "hierarchy": [
      "tgn:2440313",
      "tgn:1000001",
      "tgn:7012149",
      "tgn:2002069",
      "tgn:7007826",
      "tgn:7029392"
    ],
    "placetype": [
      "aat:300008699"
    ],
    "id": 2440313,
    "name:xx": "Klondike Branch"
  }
}
