{
  "geometry": {
    "type": "Point",
    "coordinates": [
      -82.0833,
      37.9167
    ]
  },
  "type": "Feature",
  "properties": {
    "hierarchy": [
      "tgn:2156563",
      "tgn:1000001",
      "tgn:7012149",
      "tgn:2002273",
      "tgn:7013961",
      "tgn:7029392"
    ],
    "placetype": [
      "aat:300008699"
    ],
    "id": 2156563,
    "name:xx": "Bearwallow Branch"
  }
}
