{
  "geometry": {
    "type": "Point",
    "coordinates": [
      -90.1667,
      35.6833
    ]
  },
  "type": "Feature",
  "properties": {
    "hierarchy": [
      "tgn:2007638",
      "tgn:1000001",
      "tgn:7016172",
      "tgn:7012149",
      "tgn:2000151",
      "tgn:7029392"
    ],
    "placetype": [
      "aat:300008347",
      "aat:300387210"
    ],
    "id": 2007638,
    "name:xx": "Athelstan"
  }
}
