{
  "geometry": {
    "type": "Point",
    "coordinates": [
      44.9167,
      54.0667
    ]
  },
  "type": "Feature",
  "properties": {
    "hierarchy": [
      "tgn:1138340",
      "tgn:1000004",
      "tgn:7011523",
      "tgn:7002435",
      "tgn:7029392"
    ],
    "placetype": [
      "aat:300008347"
    ],
    "id": 1138340,
    "name:xx": "Ruzayevka"
  }
}
