{
  "geometry": {
    "type": "Point",
    "coordinates": [
      -103.5167,
      46.2333
    ]
  },
  "type": "Feature",
  "properties": {
    "hierarchy": [
      "tgn:2306506",
      "tgn:1000001",
      "tgn:7012149",
      "tgn:7007705",
      "tgn:7029392"
    ],
    "placetype": [
      "aat:300008706"
    ],
    "id": 2306506,
    "name:xx": "East Fork Deep Creek"
  }
}
