{
  "geometry": {
    "type": "Point",
    "coordinates": [
      -83.55,
      37.3167
    ]
  },
  "type": "Feature",
  "properties": {
    "hierarchy": [
      "tgn:2318046",
      "tgn:1000001",
      "tgn:7012149",
      "tgn:2000836",
      "tgn:7007255",
      "tgn:7029392"
    ],
    "placetype": [
      "aat:300008699"
    ],
    "id": 2318046,
    "name:xx": "Enoch Fork"
  }
}
