{
  "geometry": {
    "type": "Point",
    "coordinates": [
      12.55,
      48.466667
    ]
  },
  "type": "Feature",
  "properties": {
    "hierarchy": [
      "tgn:7117861",
      "tgn:7003669",
      "tgn:1000003",
      "tgn:7000084",
      "tgn:7029392"
    ],
    "placetype": [
      "aat:300000206"
    ],
    "id": 7117861,
    "name:xx": "Ödenkatzbach"
  }
}
