{
  "geometry": {
    "type": "Point",
    "coordinates": [
      -88.3333,
      35.8333
    ]
  },
  "type": "Feature",
  "properties": {
    "hierarchy": [
      "tgn:2102203",
      "tgn:1000001",
      "tgn:7012149",
      "tgn:2001845",
      "tgn:7007825",
      "tgn:7029392"
    ],
    "placetype": [
      "aat:300008347"
    ],
    "id": 2102203,
    "name:xx": "Yuma"
  }
}
