{
  "geometry": {
    "type": "Point",
    "coordinates": [
      -79.6833,
      41.4667
    ]
  },
  "type": "Feature",
  "properties": {
    "hierarchy": [
      "tgn:2092656",
      "tgn:1000001",
      "tgn:7012149",
      "tgn:1002971",
      "tgn:7007710",
      "tgn:7029392"
    ],
    "placetype": [
      "aat:300008347"
    ],
    "id": 2092656,
    "name:xx": "Rouseville"
  }
}
