{
  "geometry": {
    "type": "Point",
    "coordinates": [
      -70.0167,
      44.4333
    ]
  },
  "type": "Feature",
  "properties": {
    "hierarchy": [
      "tgn:2310539",
      "tgn:1000001",
      "tgn:2000923",
      "tgn:7012149",
      "tgn:7007515",
      "tgn:7029392"
    ],
    "placetype": [
      "aat:300008680"
    ],
    "id": 2310539,
    "name:xx": "Echo Lake"
  }
}
