{
  "geometry": {
    "type": "Point",
    "coordinates": [
      -122.7167,
      41.0167
    ]
  },
  "type": "Feature",
  "properties": {
    "hierarchy": [
      "tgn:2199356",
      "tgn:1000001",
      "tgn:7012149",
      "tgn:7007157",
      "tgn:2000191",
      "tgn:7029392"
    ],
    "placetype": [
      "aat:300008706"
    ],
    "id": 2199356,
    "name:xx": "Brush Creek"
  }
}
