{
  "type": "FeatureCollection",
  "features": [
    {
      "geometry": {
        "type": "Point",
        "coordinates": [
          -97.35,
          32.85
        ]
      },
      "type": "Feature",
      "properties": {
        "hierarchy": [
          "tgn:2107330",
          "tgn:1000001",
          "tgn:7012149",
          "tgn:1002939",
          "tgn:7007826",
          "tgn:7029392"
        ],
        "placetype": [
          "aat:300008347"
        ],
        "id": 2107330,
        "name:xx": "Saginaw"
      }
    },
    {
      "geometry": {
        "type": "Point",
        "coordinates": [
          -101.6167,
          35.25
        ]
      },
      "type": "Feature",
      "properties": {
        "hierarchy": [
          "tgn:2107332",
          "tgn:1000001",
          "tgn:7012149",
          "tgn:2002056",
          "tgn:7007826",
          "tgn:7029392"
        ],
        "placetype": [
          "aat:300008347",
          "aat:300387210"
        ],
        "id": 2107332,
        "name:xx": "Saint Francis"
      }
    },
    {
      "geometry": {
        "type": "Point",
        "coordinates": [
          -98.1833,
          29.4
        ]
      },
      "type": "Feature",
      "properties": {
        "hierarchy": [
          "tgn:2107334",
          "tgn:1000001",
          "tgn:2001941",
          "tgn:7012149",
          "tgn:7007826",
          "tgn:7029392"
        ],
        "placetype": [
          "aat:300008347"
        ],
        "id": 2107334,
        "name:xx": "Saint Hedwig"
      }
    },
    {
      "geometry": {
        "type": "Point",
        "coordinates": [
          -97.5167,
          33.6833
        ]
      },
      "type": "Feature",
      "properties": {
        "hierarchy": [
          "tgn:2107335",
          "tgn:1000001",
          "tgn:7012149",
          "tgn:2002044",
          "tgn:7007826",
          "tgn:7029392"
        ],
        "placetype": [
          "aat:300008347"
        ],
        "id": 2107335,
        "name:xx": "Saint Jo"
      }
    },
    {
      "geometry": {
        "type": "Point",
        "coordinates": [
          -96.95,
          29.6167
        ]
      },
      "type": "Feature",
      "properties": {
        "hierarchy": [
          "tgn:2107336",
          "tgn:1000001",
          "tgn:7012149",
          "tgn:1002374",
          "tgn:7007826",
          "tgn:7029392"
        ],
        "placetype": [
          "aat:300008347"
        ],
        "id": 2107336,
        "name:xx": "Saint John"
      }
    },
    {
      "geometry": {
        "type": "Point",
        "coordinates": [
          -101.5333,
          31.7
        ]
      },
      "type": "Feature",
      "properties": {
        "hierarchy": [
          "tgn:2107338",
          "tgn:1000001",
          "tgn:7012149",
          "tgn:2001991",
          "tgn:7007826",
          "tgn:7029392"
        ],
        "placetype": [
          "aat:300008347",
          "aat:300387210"
        ],
        "id": 2107338,
        "name:xx": "Saint Lawrence"
      }
    }
  ]
}
