{
  "geometry": {
    "type": "Point",
    "coordinates": [
      -98.5167,
      37.3833
    ]
  },
  "type": "Feature",
  "properties": {
    "hierarchy": [
      "tgn:2696181",
      "tgn:2000663",
      "tgn:1000001",
      "tgn:7012149",
      "tgn:7007254",
      "tgn:7029392"
    ],
    "placetype": [
      "aat:300008706"
    ],
    "id": 2696181,
    "name:xx": "Stolp Creek"
  }
}
