{
  "geometry": {
    "type": "Point",
    "coordinates": [
      -122.55,
      46.55
    ]
  },
  "type": "Feature",
  "properties": {
    "hierarchy": [
      "tgn:1134598",
      "tgn:1000001",
      "tgn:7012149",
      "tgn:1002594",
      "tgn:7007920",
      "tgn:7029392"
    ],
    "placetype": [
      "aat:300008706"
    ],
    "id": 1134598,
    "name:xx": "Silver Creek"
  }
}
