{
  "geometry": {
    "type": "Point",
    "coordinates": [
      120.8635,
      24.4177
    ]
  },
  "type": "Feature",
  "properties": {
    "hierarchy": [
      "tgn:7502775",
      "tgn:7487020",
      "tgn:1000004",
      "tgn:1000141",
      "tgn:7029392"
    ],
    "placetype": [
      "aat:300008347"
    ],
    "id": 7502775,
    "name:xx": "Guishan"
  }
}
