{
  "geometry": {
    "type": "Point",
    "coordinates": [
      93.733333,
      25.866667
    ]
  },
  "type": "Feature",
  "properties": {
    "hierarchy": [
      "tgn:1099889",
      "tgn:1000004",
      "tgn:1001832",
      "tgn:7000198",
      "tgn:7029392"
    ],
    "placetype": [
      "aat:300008347",
      "aat:300167671"
    ],
    "name:en": "Rājbāri",
    "id": 1099889
  }
}
