{
  "type": "FeatureCollection",
  "features": [
    {
      "geometry": {
        "type": "Point",
        "coordinates": [
          -83.9,
          41.1
        ]
      },
      "type": "Feature",
      "properties": {
        "hierarchy": [
          "tgn:2082254",
          "tgn:1000001",
          "tgn:7012149",
          "tgn:1002811",
          "tgn:7007706",
          "tgn:7029392"
        ],
        "placetype": [
          "aat:300008347"
        ],
        "id": 2082254,
        "name:xx": "Townwood"
      }
    },
    {
      "geometry": {
        "type": "Point",
        "coordinates": [
          -83.4833,
          39.9833
        ]
      },
      "type": "Feature",
      "properties": {
        "hierarchy": [
          "tgn:2082255",
          "tgn:1000001",
          "tgn:7012149",
          "tgn:1002625",
          "tgn:7007706",
          "tgn:7029392"
        ],
        "placetype": [
          "aat:300008347",
          "aat:300387210"
        ],
        "id": 2082255,
        "name:xx": "Tradersville"
      }
    },
    {
      "geometry": {
        "type": "Point",
        "coordinates": [
          -81.7,
          40.5833
        ]
      },
      "type": "Feature",
      "properties": {
        "hierarchy": [
          "tgn:2082256",
          "tgn:1000001",
          "tgn:7012149",
          "tgn:1002482",
          "tgn:7007706",
          "tgn:7029392"
        ],
        "placetype": [
          "aat:300008347"
        ],
        "id": 2082256,
        "name:xx": "Trail"
      }
    },
    {
      "geometry": {
        "type": "Point",
        "coordinates": [
          -81.0333,
          39.6167
        ]
      },
      "type": "Feature",
      "properties": {
        "hierarchy": [
          "tgn:2082257",
          "tgn:1000001",
          "tgn:7012149",
          "tgn:2001617",
          "tgn:7007706",
          "tgn:7029392"
        ],
        "placetype": [
          "aat:300008347",
          "aat:300387210"
        ],
        "id": 2082257,
        "name:xx": "Trail Run"
      }
    },
    {
      "geometry": {
        "type": "Point",
        "coordinates": [
          -83.5167,
          38.95
        ]
      },
      "type": "Feature",
      "properties": {
        "hierarchy": [
          "tgn:2082258",
          "tgn:1002136",
          "tgn:1000001",
          "tgn:7012149",
          "tgn:7007706",
          "tgn:7029392"
        ],
        "placetype": [
          "aat:300008347"
        ],
        "id": 2082258,
        "name:xx": "Tranquility"
      }
    }
  ]
}
