{
  "geometry": {
    "type": "Point",
    "coordinates": [
      -119.9167,
      48.3833
    ]
  },
  "type": "Feature",
  "properties": {
    "hierarchy": [
      "tgn:2452674",
      "tgn:1000001",
      "tgn:7012149",
      "tgn:1002742",
      "tgn:7007920",
      "tgn:7029392"
    ],
    "placetype": [
      "aat:300008798"
    ],
    "id": 2452674,
    "name:xx": "Little Buck Mountain"
  }
}
