{
  "geometry": {
    "type": "Point",
    "coordinates": [
      75.302412,
      28.286866
    ]
  },
  "type": "Feature",
  "properties": {
    "hierarchy": [
      "tgn:7583727",
      "tgn:1000004",
      "tgn:7000198",
      "tgn:7016788",
      "tgn:7029392"
    ],
    "placetype": [
      "aat:300008347"
    ],
    "name:en": "Gh훮s카r훮m ka B훮s",
    "id": 7583727
  }
}
