{
  "geometry": {
    "type": "Point",
    "coordinates": [
      -83.65,
      34.85
    ]
  },
  "type": "Feature",
  "properties": {
    "hierarchy": [
      "tgn:7023060",
      "tgn:1000001",
      "tgn:7012149",
      "tgn:7029392"
    ],
    "placetype": [
      "aat:300008699"
    ],
    "id": 7023060,
    "name:xx": "Sassafras Branch"
  }
}
