{
  "geometry": {
    "type": "Point",
    "coordinates": [
      -61.5833,
      -3.5167
    ]
  },
  "type": "Feature",
  "properties": {
    "hierarchy": [
      "tgn:1115417",
      "tgn:1001826",
      "tgn:1000047",
      "tgn:7002456",
      "tgn:1000002",
      "tgn:7029392"
    ],
    "placetype": [
      "aat:300008680"
    ],
    "id": 1115417,
    "name:xx": "Anamã, Lago"
  }
}
