{
  "geometry": {
    "type": "Point",
    "coordinates": [
      -4.35,
      51.966667
    ]
  },
  "type": "Feature",
  "properties": {
    "hierarchy": [
      "tgn:7455729",
      "tgn:7002443",
      "tgn:5000552",
      "tgn:1000003",
      "tgn:7008591",
      "tgn:7029392"
    ],
    "placetype": [
      "aat:300008777"
    ],
    "name:en": "Crug Fâch",
    "id": 7455729
  }
}
