{
  "geometry": {
    "type": "Point",
    "coordinates": [
      -75.0667,
      38.6167
    ]
  },
  "type": "Feature",
  "properties": {
    "hierarchy": [
      "tgn:2646154",
      "tgn:1002933",
      "tgn:1000001",
      "tgn:7012149",
      "tgn:7007239",
      "tgn:7029392"
    ],
    "placetype": [
      "aat:300132316"
    ],
    "id": 2646154,
    "name:xx": "Sawpit Cove"
  }
}
