{
  "type": "FeatureCollection",
  "features": [
    {
      "geometry": {
        "type": "Point",
        "coordinates": [
          14.233333,
          50.916667
        ]
      },
      "type": "Feature",
      "properties": {
        "hierarchy": [
          "tgn:7208580",
          "tgn:1000003",
          "tgn:7003685",
          "tgn:7000084",
          "tgn:7029392"
        ],
        "placetype": [
          "aat:300008863"
        ],
        "id": 7208580,
        "name:xx": "Bad Schandau, Forst"
      }
    },
    {
      "geometry": {
        "type": "Point",
        "coordinates": [
          9.666667,
          47.55
        ]
      },
      "type": "Feature",
      "properties": {
        "hierarchy": [
          "tgn:7208582",
          "tgn:7003669",
          "tgn:1000003",
          "tgn:7000084",
          "tgn:7029392"
        ],
        "placetype": [
          "aat:300008347"
        ],
        "id": 7208582,
        "name:xx": "Bad Schachen"
      }
    },
    {
      "geometry": {
        "type": "Point",
        "coordinates": [
          8.166667,
          51.583333
        ]
      },
      "type": "Feature",
      "properties": {
        "hierarchy": [
          "tgn:7208583",
          "tgn:1000003",
          "tgn:7003677",
          "tgn:7000084",
          "tgn:7029392"
        ],
        "placetype": [
          "aat:300007783"
        ],
        "id": 7208583,
        "name:xx": "Bahnhof Bad Sassendorf"
      }
    },
    {
      "geometry": {
        "type": "Point",
        "coordinates": [
          8.616667,
          54.316667
        ]
      },
      "type": "Feature",
      "properties": {
        "hierarchy": [
          "tgn:7208585",
          "tgn:1000003",
          "tgn:7003688",
          "tgn:7000084",
          "tgn:7029392"
        ],
        "placetype": [
          "aat:300007783"
        ],
        "id": 7208585,
        "name:xx": "Bahnhof Bad Sankt Peter-Ording"
      }
    }
  ]
}
