{
  "geometry": {
    "type": "Point",
    "coordinates": [
      -157.5167,
      62.5167
    ]
  },
  "type": "Feature",
  "properties": {
    "hierarchy": [
      "tgn:1123429",
      "tgn:7006450",
      "tgn:1000001",
      "tgn:7012149",
      "tgn:2000089",
      "tgn:7029392"
    ],
    "placetype": [
      "aat:300008707"
    ],
    "id": 1123429,
    "name:xx": "Dishna River"
  }
}
