{
  "geometry": {
    "type": "Point",
    "coordinates": [
      -70.3167,
      45.85
    ]
  },
  "type": "Feature",
  "properties": {
    "hierarchy": [
      "tgn:2336790",
      "tgn:1000001",
      "tgn:7012149",
      "tgn:2000930",
      "tgn:7007515",
      "tgn:7029392"
    ],
    "placetype": [
      "aat:300008699"
    ],
    "id": 2336790,
    "name:xx": "Fourmile Brook"
  }
}
