{
  "geometry": {
    "type": "Point",
    "coordinates": [
      79.64897,
      27.739582
    ]
  },
  "type": "Feature",
  "properties": {
    "hierarchy": [
      "tgn:7559708",
      "tgn:1000004",
      "tgn:7000198",
      "tgn:7016722",
      "tgn:7029392"
    ],
    "placetype": [
      "aat:300008347"
    ],
    "name:en": "Sarāi Sādhu",
    "id": 7559708
  }
}
