{
  "geometry": {
    "type": "Point",
    "coordinates": [
      -112.1167,
      45.4667
    ]
  },
  "type": "Feature",
  "properties": {
    "hierarchy": [
      "tgn:2330192",
      "tgn:1000001",
      "tgn:7012149",
      "tgn:2001288",
      "tgn:7007524",
      "tgn:7029392"
    ],
    "placetype": [
      "aat:300000390"
    ],
    "id": 2330192,
    "name:xx": "Flamm Ranch Number 2 Mine"
  }
}
