{
  "geometry": {
    "type": "Point",
    "coordinates": [
      -121.3333,
      39.6833
    ]
  },
  "type": "Feature",
  "properties": {
    "hierarchy": [
      "tgn:2199347",
      "tgn:1000001",
      "tgn:1002218",
      "tgn:7012149",
      "tgn:7007157",
      "tgn:7029392"
    ],
    "placetype": [
      "aat:300008347"
    ],
    "id": 2199347,
    "name:xx": "Brush Creek"
  }
}
