{
  "geometry": {
    "type": "Point",
    "coordinates": [
      -56.3667,
      49.95
    ]
  },
  "type": "Feature",
  "properties": {
    "hierarchy": [
      "tgn:1014321",
      "tgn:7005685",
      "tgn:7005807",
      "tgn:1000001",
      "tgn:7005801",
      "tgn:7029392"
    ],
    "placetype": [
      "aat:300008347"
    ],
    "id": 1014321,
    "name:xx": "Seal Cove"
  }
}
