{
  "geometry": {
    "type": "Point",
    "coordinates": [
      -82.6167,
      36.0667
    ]
  },
  "type": "Feature",
  "properties": {
    "hierarchy": [
      "tgn:2759237",
      "tgn:1000001",
      "tgn:7012149",
      "tgn:2001866",
      "tgn:7007825",
      "tgn:7029392"
    ],
    "placetype": [
      "aat:300008706"
    ],
    "id": 2759237,
    "name:xx": "West Fork Cassi Creek"
  }
}
