{
  "geometry": {
    "type": "Point",
    "coordinates": [
      -82.7667,
      39.35
    ]
  },
  "type": "Feature",
  "properties": {
    "hierarchy": [
      "tgn:2711634",
      "tgn:1000001",
      "tgn:7012149",
      "tgn:7007706",
      "tgn:7029392"
    ],
    "placetype": [
      "aat:300008863"
    ],
    "id": 2711634,
    "name:xx": "Tar Hollow State Forest"
  }
}
