{
  "geometry": {
    "type": "Point",
    "coordinates": [
      -91.7167,
      33.7667
    ]
  },
  "type": "Feature",
  "properties": {
    "hierarchy": [
      "tgn:2143801",
      "tgn:1000001",
      "tgn:7016172",
      "tgn:7012149",
      "tgn:7029392"
    ],
    "placetype": [
      "aat:300008699"
    ],
    "id": 2143801,
    "name:xx": "Baker Branch"
  }
}
