{
  "type": "FeatureCollection",
  "features": [
    {
      "geometry": {
        "type": "Point",
        "coordinates": [
          -94.8167,
          44.95
        ]
      },
      "type": "Feature",
      "properties": {
        "hierarchy": [
          "tgn:2290930",
          "tgn:1000001",
          "tgn:7012149",
          "tgn:2001032",
          "tgn:7007521",
          "tgn:7029392"
        ],
        "placetype": [
          "aat:300008905"
        ],
        "id": 2290930,
        "name:xx": "Dog Lake"
      }
    },
    {
      "geometry": {
        "type": "Point",
        "coordinates": [
          -114.6,
          48.5667
        ]
      },
      "type": "Feature",
      "properties": {
        "hierarchy": [
          "tgn:2290931",
          "tgn:1000001",
          "tgn:7012149",
          "tgn:2001274",
          "tgn:7007524",
          "tgn:7029392"
        ],
        "placetype": [
          "aat:300008680"
        ],
        "id": 2290931,
        "name:xx": "Dog Lake"
      }
    },
    {
      "geometry": {
        "type": "Point",
        "coordinates": [
          -108.7167,
          34.6167
        ]
      },
      "type": "Feature",
      "properties": {
        "hierarchy": [
          "tgn:2290932",
          "tgn:1000001",
          "tgn:2001431",
          "tgn:7012149",
          "tgn:7007566",
          "tgn:7029392"
        ],
        "placetype": [
          "aat:300008680"
        ],
        "id": 2290932,
        "name:xx": "Dog Lake"
      }
    },
    {
      "geometry": {
        "type": "Point",
        "coordinates": [
          -120.7,
          42.0667
        ]
      },
      "type": "Feature",
      "properties": {
        "hierarchy": [
          "tgn:2290933",
          "tgn:1000001",
          "tgn:7012149",
          "tgn:2001715",
          "tgn:7007708",
          "tgn:7029392"
        ],
        "placetype": [
          "aat:300008680"
        ],
        "id": 2290933,
        "name:xx": "Dog Lake"
      }
    },
    {
      "geometry": {
        "type": "Point",
        "coordinates": [
          -79.3833,
          33.8833
        ]
      },
      "type": "Feature",
      "properties": {
        "hierarchy": [
          "tgn:2290934",
          "tgn:1000001",
          "tgn:7012149",
          "tgn:2001758",
          "tgn:7007712",
          "tgn:7029392"
        ],
        "placetype": [
          "aat:300008680"
        ],
        "id": 2290934,
        "name:xx": "Dog Lake"
      }
    },
    {
      "geometry": {
        "type": "Point",
        "coordinates": [
          -112,
          39.6
        ]
      },
      "type": "Feature",
      "properties": {
        "hierarchy": [
          "tgn:2290935",
          "tgn:1000001",
          "tgn:2002109",
          "tgn:7012149",
          "tgn:7007827",
          "tgn:7029392"
        ],
        "placetype": [
          "aat:300008680"
        ],
        "id": 2290935,
        "name:xx": "Dog Lake"
      }
    },
    {
      "geometry": {
        "type": "Point",
        "coordinates": [
          -111.8833,
          38.3
        ]
      },
      "type": "Feature",
      "properties": {
        "hierarchy": [
          "tgn:2290936",
          "tgn:1000001",
          "tgn:7012149",
          "tgn:2002116",
          "tgn:7007827",
          "tgn:7029392"
        ],
        "placetype": [
          "aat:300008680"
        ],
        "id": 2290936,
        "name:xx": "Dog Lake"
      }
    },
    {
      "geometry": {
        "type": "Point",
        "coordinates": [
          -111.5833,
          40.5833
        ]
      },
      "type": "Feature",
      "properties": {
        "hierarchy": [
          "tgn:2290937",
          "tgn:1000001",
          "tgn:7012149",
          "tgn:2002118",
          "tgn:7007827",
          "tgn:7029392"
        ],
        "placetype": [
          "aat:300008680"
        ],
        "id": 2290937,
        "name:xx": "Dog Lake"
      }
    },
    {
      "geometry": {
        "type": "Point",
        "coordinates": [
          -121.35,
          46.65
        ]
      },
      "type": "Feature",
      "properties": {
        "hierarchy": [
          "tgn:2290938",
          "tgn:1000001",
          "tgn:7012149",
          "tgn:1003042",
          "tgn:7007920",
          "tgn:7029392"
        ],
        "placetype": [
          "aat:300008680"
        ],
        "id": 2290938,
        "name:xx": "Dog Lake"
      }
    },
    {
      "geometry": {
        "type": "Point",
        "coordinates": [
          -89.0667,
          43.7
        ]
      },
      "type": "Feature",
      "properties": {
        "hierarchy": [
          "tgn:2290939",
          "tgn:1000001",
          "tgn:2002325",
          "tgn:7012149",
          "tgn:7007922",
          "tgn:7029392"
        ],
        "placetype": [
          "aat:300008680"
        ],
        "id": 2290939,
        "name:xx": "Dog Lake"
      }
    }
  ]
}
