{
  "geometry": {
    "type": "Point",
    "coordinates": [
      -100.6667,
      43.8167
    ]
  },
  "type": "Feature",
  "properties": {
    "hierarchy": [
      "tgn:2381501",
      "tgn:1000001",
      "tgn:2001807",
      "tgn:7012149",
      "tgn:7007713",
      "tgn:7029392"
    ],
    "placetype": [
      "aat:300008706"
    ],
    "id": 2381501,
    "name:xx": "Hay Creek"
  }
}
