{
  "geometry": {
    "type": "Point",
    "coordinates": [
      -83.5167,
      34.75
    ]
  },
  "type": "Feature",
  "properties": {
    "hierarchy": [
      "tgn:2466453",
      "tgn:1000001",
      "tgn:7012149",
      "tgn:2000410",
      "tgn:7007248",
      "tgn:7029392"
    ],
    "placetype": [
      "aat:300008699"
    ],
    "id": 2466453,
    "name:xx": "Long Branch"
  }
}
