{
  "geometry": {
    "type": "Point",
    "coordinates": [
      -110.35,
      34.0167
    ]
  },
  "type": "Feature",
  "properties": {
    "hierarchy": [
      "tgn:2239717",
      "tgn:1000001",
      "tgn:7006451",
      "tgn:7012149",
      "tgn:7029392"
    ],
    "placetype": [
      "aat:300008761"
    ],
    "id": 2239717,
    "name:xx": "Cibecue Canyon"
  }
}
