{
  "geometry": {
    "type": "Point",
    "coordinates": [
      -107.3833,
      44.45
    ]
  },
  "type": "Feature",
  "properties": {
    "hierarchy": [
      "tgn:2298225",
      "tgn:1000001",
      "tgn:2002366",
      "tgn:7012149",
      "tgn:7007923",
      "tgn:7029392"
    ],
    "placetype": [
      "aat:300008706"
    ],
    "id": 2298225,
    "name:xx": "Dry Medicine Lodge Creek"
  }
}
