{
  "geometry": {
    "type": "Point",
    "coordinates": [
      -96.1667,
      46.7667
    ]
  },
  "type": "Feature",
  "properties": {
    "hierarchy": [
      "tgn:2467980",
      "tgn:2001001",
      "tgn:1000001",
      "tgn:7012149",
      "tgn:7007521",
      "tgn:7029392"
    ],
    "placetype": [
      "aat:300008680"
    ],
    "id": 2467980,
    "name:xx": "Long Lake"
  }
}
