{
  "geometry": {
    "type": "Point",
    "coordinates": [
      -90.9833,
      39.35
    ]
  },
  "type": "Feature",
  "properties": {
    "hierarchy": [
      "tgn:2467793",
      "tgn:1000001",
      "tgn:7012149",
      "tgn:1002787",
      "tgn:7007523",
      "tgn:7029392"
    ],
    "placetype": [
      "aat:300008798"
    ],
    "id": 2467793,
    "name:xx": "Long Knob"
  }
}
