{
  "geometry": {
    "type": "Point",
    "coordinates": [
      -81.0333,
      32.4333
    ]
  },
  "type": "Feature",
  "properties": {
    "hierarchy": [
      "tgn:2708244",
      "tgn:1000001",
      "tgn:7012149",
      "tgn:2001751",
      "tgn:7007712",
      "tgn:7029392"
    ],
    "placetype": [
      "aat:300006075"
    ],
    "id": 2708244,
    "name:xx": "Switzerland Canal"
  }
}
