{
  "geometry": {
    "type": "Point",
    "coordinates": [
      -87.4833,
      34.9833
    ]
  },
  "type": "Feature",
  "properties": {
    "hierarchy": [
      "tgn:2245430",
      "tgn:7002659",
      "tgn:1000001",
      "tgn:7012149",
      "tgn:2000038",
      "tgn:7029392"
    ],
    "placetype": [
      "aat:300008746"
    ],
    "id": 2245430,
    "name:xx": "Clyde McCluskey Cave"
  }
}
