{
  "geometry": {
    "type": "Point",
    "coordinates": [
      -73.0167,
      40.7833
    ]
  },
  "type": "Feature",
  "properties": {
    "hierarchy": [
      "tgn:1115783",
      "tgn:1000001",
      "tgn:7012149",
      "tgn:1002924",
      "tgn:7007568",
      "tgn:7029392"
    ],
    "placetype": [
      "aat:300008680"
    ],
    "id": 1115783,
    "name:xx": "Canaan Lake"
  }
}
