{
  "geometry": {
    "type": "Point",
    "coordinates": [
      -88.65,
      45.4667
    ]
  },
  "type": "Feature",
  "properties": {
    "hierarchy": [
      "tgn:2730590",
      "tgn:1000001",
      "tgn:2002323",
      "tgn:7012149",
      "tgn:7007922",
      "tgn:7029392"
    ],
    "placetype": [
      "aat:300008680"
    ],
    "id": 2730590,
    "name:xx": "Trump Lake"
  }
}
