{
  "geometry": {
    "type": "Point",
    "coordinates": [
      -110.0667,
      38.2333
    ]
  },
  "type": "Feature",
  "properties": {
    "hierarchy": [
      "tgn:2399941",
      "tgn:1000001",
      "tgn:7012149",
      "tgn:2002128",
      "tgn:7007827",
      "tgn:7029392"
    ],
    "placetype": [
      "aat:300008761"
    ],
    "id": 2399941,
    "name:xx": "Horse Canyon"
  }
}
