{
  "type": "FeatureCollection",
  "features": [
    {
      "geometry": {
        "type": "Point",
        "coordinates": [
          -121.9667,
          37.5667
        ]
      },
      "type": "Feature",
      "properties": {
        "hierarchy": [
          "tgn:2011453",
          "tgn:1002138",
          "tgn:1000001",
          "tgn:2011439",
          "tgn:7012149",
          "tgn:7007157",
          "tgn:7029392"
        ],
        "placetype": [
          "aat:300000745",
          "aat:300387205"
        ],
        "id": 2011453,
        "name:xx": "Niles Junction"
      }
    },
    {
      "geometry": {
        "type": "Point",
        "coordinates": [
          -121.9667,
          37.5667
        ]
      },
      "type": "Feature",
      "properties": {
        "hierarchy": [
          "tgn:2011455",
          "tgn:1002138",
          "tgn:1000001",
          "tgn:2011439",
          "tgn:7012149",
          "tgn:7007157",
          "tgn:7029392"
        ],
        "placetype": [
          "aat:300000745",
          "aat:300387205"
        ],
        "id": 2011455,
        "name:xx": "Shinn"
      }
    },
    {
      "geometry": {
        "type": "Point",
        "coordinates": [
          -121.9333,
          37.5
        ]
      },
      "type": "Feature",
      "properties": {
        "hierarchy": [
          "tgn:2011456",
          "tgn:1002138",
          "tgn:1000001",
          "tgn:2011439",
          "tgn:7012149",
          "tgn:7007157",
          "tgn:7029392"
        ],
        "placetype": [
          "aat:300000745",
          "aat:300387205"
        ],
        "id": 2011456,
        "name:xx": "Snoboy"
      }
    },
    {
      "geometry": {
        "type": "Point",
        "coordinates": [
          -121.2667,
          37.8833
        ]
      },
      "type": "Feature",
      "properties": {
        "hierarchy": [
          "tgn:2011458",
          "tgn:1000001",
          "tgn:7012149",
          "tgn:7007157",
          "tgn:1002861",
          "tgn:7029392"
        ],
        "placetype": [
          "aat:300008347"
        ],
        "id": 2011458,
        "name:xx": "French Camp"
      }
    },
    {
      "geometry": {
        "type": "Point",
        "coordinates": [
          -121.15,
          39.3
        ]
      },
      "type": "Feature",
      "properties": {
        "hierarchy": [
          "tgn:2011459",
          "tgn:1000001",
          "tgn:7012149",
          "tgn:7007157",
          "tgn:1002710",
          "tgn:7029392"
        ],
        "placetype": [
          "aat:300008347",
          "aat:300387210"
        ],
        "id": 2011459,
        "name:xx": "French Corral"
      }
    }
  ]
}
