{
  "type": "FeatureCollection",
  "features": [
    {
      "geometry": {
        "type": "Point",
        "coordinates": [
          6.083333,
          50.566667
        ]
      },
      "type": "Feature",
      "properties": {
        "hierarchy": [
          "tgn:7242490",
          "tgn:7003460",
          "tgn:1000003",
          "tgn:1000063",
          "tgn:4012014",
          "tgn:7029392"
        ],
        "placetype": [
          "aat:300008347"
        ],
        "id": 7242490,
        "name:xx": "Longchamps"
      }
    },
    {
      "geometry": {
        "type": "Point",
        "coordinates": [
          4.89683,
          50.577115
        ]
      },
      "type": "Feature",
      "properties": {
        "hierarchy": [
          "tgn:7242491",
          "tgn:7003466",
          "tgn:1000003",
          "tgn:1000063",
          "tgn:4012014",
          "tgn:7029392"
        ],
        "placetype": [
          "aat:300008347"
        ],
        "id": 7242491,
        "name:xx": "Longchamps"
      }
    },
    {
      "geometry": {
        "type": "Point",
        "coordinates": [
          5.921111,
          50.226389
        ]
      },
      "type": "Feature",
      "properties": {
        "hierarchy": [
          "tgn:7242492",
          "tgn:7003465",
          "tgn:1000003",
          "tgn:1000063",
          "tgn:4012014",
          "tgn:7029392"
        ],
        "placetype": [
          "aat:300008347"
        ],
        "id": 7242492,
        "name:xx": "Longchamps"
      }
    },
    {
      "geometry": {
        "type": "Point",
        "coordinates": [
          5.616667,
          50.9
        ]
      },
      "type": "Feature",
      "properties": {
        "hierarchy": [
          "tgn:7242494",
          "tgn:7003461",
          "tgn:1000003",
          "tgn:1000063",
          "tgn:7018236",
          "tgn:7029392"
        ],
        "placetype": [
          "aat:300008347"
        ],
        "id": 7242494,
        "name:xx": "Lanakerheide"
      }
    },
    {
      "geometry": {
        "type": "Point",
        "coordinates": [
          3.497855,
          50.573996
        ]
      },
      "type": "Feature",
      "properties": {
        "hierarchy": [
          "tgn:7242497",
          "tgn:7007877",
          "tgn:1000003",
          "tgn:1000063",
          "tgn:4012014",
          "tgn:7029392"
        ],
        "placetype": [
          "aat:300008347"
        ],
        "id": 7242497,
        "name:xx": "La Muche"
      }
    },
    {
      "geometry": {
        "type": "Point",
        "coordinates": [
          5.283333,
          50.15
        ]
      },
      "type": "Feature",
      "properties": {
        "hierarchy": [
          "tgn:7242498",
          "tgn:7003465",
          "tgn:1000003",
          "tgn:1000063",
          "tgn:4012014",
          "tgn:7029392"
        ],
        "placetype": [
          "aat:300008863"
        ],
        "id": 7242498,
        "name:xx": "Lamsoul, Bois de"
      }
    },
    {
      "geometry": {
        "type": "Point",
        "coordinates": [
          5.266667,
          50.15
        ]
      },
      "type": "Feature",
      "properties": {
        "hierarchy": [
          "tgn:7242499",
          "tgn:7003466",
          "tgn:1000003",
          "tgn:1000063",
          "tgn:4012014",
          "tgn:7029392"
        ],
        "placetype": [
          "aat:300000206"
        ],
        "id": 7242499,
        "name:xx": "Lamsoul"
      }
    }
  ]
}
