{
  "geometry": {
    "type": "Point",
    "coordinates": [
      -68.4667,
      -33.0833
    ]
  },
  "type": "Feature",
  "properties": {
    "hierarchy": [
      "tgn:1136464",
      "tgn:7006477",
      "tgn:1001427",
      "tgn:1000002",
      "tgn:7029392"
    ],
    "placetype": [
      "aat:300008347"
    ],
    "id": 1136464,
    "name:xx": "San Martín"
  }
}
