{
  "geometry": {
    "type": "Point",
    "coordinates": [
      -38.9667,
      -8.7333
    ]
  },
  "type": "Feature",
  "properties": {
    "hierarchy": [
      "tgn:1020820",
      "tgn:7005437",
      "tgn:1000047",
      "tgn:7002455",
      "tgn:1000002",
      "tgn:7029392"
    ],
    "placetype": [
      "aat:300008347"
    ],
    "id": 1020820,
    "name:xx": "Belém de São Francisco"
  }
}
