{
  "geometry": {
    "type": "Point",
    "coordinates": [
      -76.5833,
      35.2333
    ]
  },
  "type": "Feature",
  "properties": {
    "hierarchy": [
      "tgn:2386002",
      "tgn:1000001",
      "tgn:7012149",
      "tgn:2001526",
      "tgn:7007709",
      "tgn:7029392"
    ],
    "placetype": [
      "aat:300008706"
    ],
    "id": 2386002,
    "name:xx": "Henry Creek"
  }
}
