{
  "geometry": {
    "type": "Point",
    "coordinates": [
      -50.95,
      -19.45
    ]
  },
  "type": "Feature",
  "properties": {
    "hierarchy": [
      "tgn:1121279",
      "tgn:7012827",
      "tgn:7002454",
      "tgn:1000047",
      "tgn:1000002",
      "tgn:7029392"
    ],
    "placetype": [
      "aat:300008707"
    ],
    "id": 1121279,
    "name:xx": "Aporé"
  }
}
