{
  "type": "FeatureCollection",
  "features": [
    {
      "geometry": {
        "type": "Point",
        "coordinates": [
          8.1667,
          -40.8
        ]
      },
      "type": "Feature",
      "properties": {
        "hierarchy": [
          "tgn:1010920",
          "tgn:1001730",
          "tgn:1000003",
          "tgn:7003121",
          "tgn:1000080",
          "tgn:7029392"
        ],
        "placetype": [
          "aat:300008850"
        ],
        "id": 1010920,
        "name:xx": "Mannu, Capo"
      }
    },
    {
      "geometry": {
        "type": "Point",
        "coordinates": [
          8.3833,
          40.3333
        ]
      },
      "type": "Feature",
      "properties": {
        "hierarchy": [
          "tgn:1010922",
          "tgn:1001724",
          "tgn:1000003",
          "tgn:7003121",
          "tgn:1000080",
          "tgn:7029392"
        ],
        "placetype": [
          "aat:300008850"
        ],
        "id": 1010922,
        "name:xx": "Marargiu, Capo"
      }
    },
    {
      "geometry": {
        "type": "Point",
        "coordinates": [
          172.65,
          -34.466667
        ]
      },
      "type": "Feature",
      "properties": {
        "hierarchy": [
          "tgn:1010923",
          "tgn:1008380",
          "tgn:7000507",
          "tgn:1000226",
          "tgn:1000006",
          "tgn:7029392"
        ],
        "placetype": [
          "aat:300008850"
        ],
        "id": 1010923,
        "name:xx": "Maria van Diemen, Cape"
      }
    },
    {
      "geometry": {
        "type": "Point",
        "coordinates": [
          -60.9,
          14.05
        ]
      },
      "type": "Feature",
      "properties": {
        "hierarchy": [
          "tgn:1010924",
          "tgn:7593585",
          "tgn:1000001",
          "tgn:7004772",
          "tgn:7029392"
        ],
        "placetype": [
          "aat:300008850"
        ],
        "id": 1010924,
        "name:xx": "Marquis, Cape"
      }
    },
    {
      "geometry": {
        "type": "Point",
        "coordinates": [
          32.719722,
          29.449444
        ]
      },
      "type": "Feature",
      "properties": {
        "hierarchy": [
          "tgn:1010928",
          "tgn:7001242",
          "tgn:7016833",
          "tgn:7001336",
          "tgn:7029392"
        ],
        "placetype": [
          "aat:300008850"
        ],
        "id": 1010928,
        "name:xx": "Maţārimah, Ra's"
      }
    }
  ]
}
