{
  "geometry": {
    "type": "Point",
    "coordinates": [
      -75.15,
      38.55
    ]
  },
  "type": "Feature",
  "properties": {
    "hierarchy": [
      "tgn:2178855",
      "tgn:1002933",
      "tgn:1000001",
      "tgn:7012149",
      "tgn:7007239",
      "tgn:7029392"
    ],
    "placetype": [
      "aat:300008347"
    ],
    "id": 2178855,
    "name:xx": "Blackwater Village"
  }
}
