{
  "geometry": {
    "type": "Point",
    "coordinates": [
      -98.05,
      42.7667
    ]
  },
  "type": "Feature",
  "properties": {
    "hierarchy": [
      "tgn:2426608",
      "tgn:2001774",
      "tgn:1000001",
      "tgn:7012149",
      "tgn:7007713",
      "tgn:7029392"
    ],
    "placetype": [
      "aat:300008791"
    ],
    "id": 2426608,
    "name:xx": "Jones Island"
  }
}
