{
  "geometry": {
    "type": "Point",
    "coordinates": [
      -94.4167,
      45.2833
    ]
  },
  "type": "Feature",
  "properties": {
    "hierarchy": [
      "tgn:2260553",
      "tgn:1000001",
      "tgn:7012149",
      "tgn:2001045",
      "tgn:7007521",
      "tgn:7029392"
    ],
    "placetype": [
      "aat:300006075"
    ],
    "id": 2260553,
    "name:xx": "County Ditch Number Fortyfour"
  }
}
