{
  "geometry": {
    "type": "Point",
    "coordinates": [
      -80.95,
      36.1333
    ]
  },
  "type": "Feature",
  "properties": {
    "hierarchy": [
      "tgn:2362206",
      "tgn:1000001",
      "tgn:7012149",
      "tgn:2001553",
      "tgn:7007709",
      "tgn:7029392"
    ],
    "placetype": [
      "aat:300008706"
    ],
    "id": 2362206,
    "name:xx": "Grays Creek"
  }
}
