{
  "geometry": {
    "type": "Point",
    "coordinates": [
      79.8559,
      27.235
    ]
  },
  "type": "Feature",
  "properties": {
    "hierarchy": [
      "tgn:7561569",
      "tgn:1000004",
      "tgn:7000198",
      "tgn:7016722",
      "tgn:7029392"
    ],
    "placetype": [
      "aat:300008347"
    ],
    "name:en": "Harnāmau",
    "id": 7561569
  }
}
