{
  "geometry": {
    "type": "Point",
    "coordinates": [
      -118.7833,
      55.2667
    ]
  },
  "type": "Feature",
  "properties": {
    "hierarchy": [
      "tgn:1013111",
      "tgn:7005694",
      "tgn:7005685",
      "tgn:1000001",
      "tgn:7029392"
    ],
    "placetype": [
      "aat:300008347"
    ],
    "id": 1013111,
    "name:xx": "Clairmont"
  }
}
