{
  "geometry": {
    "type": "Point",
    "coordinates": [
      -86.6833,
      33.6333
    ]
  },
  "type": "Feature",
  "properties": {
    "hierarchy": [
      "tgn:2711952",
      "tgn:7002659",
      "tgn:1000001",
      "tgn:7012149",
      "tgn:2000036",
      "tgn:7029392"
    ],
    "placetype": [
      "aat:300008699"
    ],
    "id": 2711952,
    "name:xx": "Tarrant Spring Branch"
  }
}
