{
  "type": "FeatureCollection",
  "features": [
    {
      "geometry": {
        "type": "Point",
        "coordinates": [
          -94.6833,
          32.3833
        ]
      },
      "type": "Feature",
      "properties": {
        "hierarchy": [
          "tgn:2496090",
          "tgn:1000001",
          "tgn:7012149",
          "tgn:7007826",
          "tgn:7029392"
        ],
        "placetype": [
          "aat:300008699"
        ],
        "id": 2496090,
        "name:xx": "Massey Branch"
      }
    },
    {
      "geometry": {
        "type": "Point",
        "coordinates": [
          -87.1,
          35.1
        ]
      },
      "type": "Feature",
      "properties": {
        "hierarchy": [
          "tgn:2496091",
          "tgn:1000001",
          "tgn:7012149",
          "tgn:2001864",
          "tgn:7007825",
          "tgn:7029392"
        ],
        "placetype": [
          "aat:300008746"
        ],
        "id": 2496091,
        "name:xx": "Massey Cave"
      }
    },
    {
      "geometry": {
        "type": "Point",
        "coordinates": [
          -87.7,
          34.3833
        ]
      },
      "type": "Feature",
      "properties": {
        "hierarchy": [
          "tgn:2496092",
          "tgn:7002659",
          "tgn:1000001",
          "tgn:7012149",
          "tgn:2000029",
          "tgn:7029392"
        ],
        "placetype": [
          "aat:300008706"
        ],
        "id": 2496092,
        "name:xx": "Massey Creek"
      }
    },
    {
      "geometry": {
        "type": "Point",
        "coordinates": [
          -91.9,
          35.85
        ]
      },
      "type": "Feature",
      "properties": {
        "hierarchy": [
          "tgn:2496093",
          "tgn:1000001",
          "tgn:7016172",
          "tgn:7012149",
          "tgn:2000173",
          "tgn:7029392"
        ],
        "placetype": [
          "aat:300008706"
        ],
        "id": 2496093,
        "name:xx": "Massey Creek"
      }
    },
    {
      "geometry": {
        "type": "Point",
        "coordinates": [
          -85.5833,
          40.6
        ]
      },
      "type": "Feature",
      "properties": {
        "hierarchy": [
          "tgn:2496094",
          "tgn:1000001",
          "tgn:7012149",
          "tgn:1002416",
          "tgn:7007252",
          "tgn:7029392"
        ],
        "placetype": [
          "aat:300008706"
        ],
        "id": 2496094,
        "name:xx": "Massey Creek"
      }
    },
    {
      "geometry": {
        "type": "Point",
        "coordinates": [
          -86.5833,
          38.1333
        ]
      },
      "type": "Feature",
      "properties": {
        "hierarchy": [
          "tgn:2496095",
          "tgn:1000001",
          "tgn:7012149",
          "tgn:2000550",
          "tgn:7007252",
          "tgn:7029392"
        ],
        "placetype": [
          "aat:300008706"
        ],
        "id": 2496095,
        "name:xx": "Massey Creek"
      }
    },
    {
      "geometry": {
        "type": "Point",
        "coordinates": [
          -75.8333,
          37.95
        ]
      },
      "type": "Feature",
      "properties": {
        "hierarchy": [
          "tgn:2496096",
          "tgn:1000001",
          "tgn:1002902",
          "tgn:7012149",
          "tgn:7007516",
          "tgn:7029392"
        ],
        "placetype": [
          "aat:300008706"
        ],
        "id": 2496096,
        "name:xx": "Massey Creek"
      }
    },
    {
      "geometry": {
        "type": "Point",
        "coordinates": [
          -88.7167,
          34.0167
        ]
      },
      "type": "Feature",
      "properties": {
        "hierarchy": [
          "tgn:2496097",
          "tgn:1000001",
          "tgn:7012149",
          "tgn:2001133",
          "tgn:7007522",
          "tgn:7029392"
        ],
        "placetype": [
          "aat:300008706"
        ],
        "id": 2496097,
        "name:xx": "Massey Creek"
      }
    },
    {
      "geometry": {
        "type": "Point",
        "coordinates": [
          -94.5167,
          38.6667
        ]
      },
      "type": "Feature",
      "properties": {
        "hierarchy": [
          "tgn:2496098",
          "tgn:1000001",
          "tgn:7012149",
          "tgn:7029392"
        ],
        "placetype": [
          "aat:300008706"
        ],
        "id": 2496098,
        "name:xx": "Massey Creek"
      }
    },
    {
      "geometry": {
        "type": "Point",
        "coordinates": [
          -112.75,
          47.9667
        ]
      },
      "type": "Feature",
      "properties": {
        "hierarchy": [
          "tgn:2496099",
          "tgn:1000001",
          "tgn:7012149",
          "tgn:2001309",
          "tgn:7007524",
          "tgn:7029392"
        ],
        "placetype": [
          "aat:300008706"
        ],
        "id": 2496099,
        "name:xx": "Massey Creek"
      }
    }
  ]
}
