{
  "geometry": {
    "type": "Point",
    "coordinates": [
      -108.85,
      42.1333
    ]
  },
  "type": "Feature",
  "properties": {
    "hierarchy": [
      "tgn:2416747",
      "tgn:1000001",
      "tgn:7012149",
      "tgn:2002383",
      "tgn:7007923",
      "tgn:7029392"
    ],
    "placetype": [
      "aat:300008706"
    ],
    "id": 2416747,
    "name:xx": "Jack Parnell Creek"
  }
}
