{
  "geometry": {
    "type": "Point",
    "coordinates": [
      30.8167,
      63.8333
    ]
  },
  "type": "Feature",
  "properties": {
    "hierarchy": [
      "tgn:1058905",
      "tgn:1000004",
      "tgn:7011509",
      "tgn:7002435",
      "tgn:7029392"
    ],
    "placetype": [
      "aat:300008347"
    ],
    "id": 1058905,
    "name:xx": "Reboly"
  }
}
