{
  "geometry": {
    "type": "Point",
    "coordinates": [
      -95.3667,
      44.0167
    ]
  },
  "type": "Feature",
  "properties": {
    "hierarchy": [
      "tgn:2260605",
      "tgn:1000001",
      "tgn:2001015",
      "tgn:7012149",
      "tgn:7007521",
      "tgn:7029392"
    ],
    "placetype": [
      "aat:300006075"
    ],
    "id": 2260605,
    "name:xx": "County Ditch Number Fortytwo"
  }
}
