{
  "geometry": {
    "type": "Point",
    "coordinates": [
      -91.3167,
      35.45
    ]
  },
  "type": "Feature",
  "properties": {
    "hierarchy": [
      "tgn:2279593",
      "tgn:1000001",
      "tgn:7016172",
      "tgn:7012149",
      "tgn:2000138",
      "tgn:7029392"
    ],
    "placetype": [
      "aat:300008699"
    ],
    "id": 2279593,
    "name:xx": "Deadman Slough"
  }
}
