{
  "geometry": {
    "type": "Point",
    "coordinates": [
      25.4333,
      46.0333
    ]
  },
  "type": "Feature",
  "properties": {
    "hierarchy": [
      "tgn:1050258",
      "tgn:1000351",
      "tgn:1000003",
      "tgn:1000091",
      "tgn:7029392"
    ],
    "placetype": [
      "aat:300008347"
    ],
    "id": 1050258,
    "name:xx": "Rupea"
  }
}
