{
  "geometry": {
    "type": "Point",
    "coordinates": [
      35.6333,
      30.45
    ]
  },
  "type": "Feature",
  "properties": {
    "hierarchy": [
      "tgn:1103633",
      "tgn:1000004",
      "tgn:1000121",
      "tgn:1002092",
      "tgn:7029392"
    ],
    "placetype": [
      "aat:300008795"
    ],
    "id": 1103633,
    "name:xx": "Abū al-Ḥamām, Jabal"
  }
}
