{
  "geometry": {
    "type": "Point",
    "coordinates": [
      -114.3667,
      38.2333
    ]
  },
  "type": "Feature",
  "properties": {
    "hierarchy": [
      "tgn:2775533",
      "tgn:1000001",
      "tgn:2001416",
      "tgn:7012149",
      "tgn:7007526",
      "tgn:7029392"
    ],
    "placetype": [
      "aat:300008706"
    ],
    "id": 2775533,
    "name:xx": "Wilson Creek"
  }
}
