{
  "geometry": {
    "type": "Point",
    "coordinates": [
      -83.0667,
      37.6167
    ]
  },
  "type": "Feature",
  "properties": {
    "hierarchy": [
      "tgn:2167021",
      "tgn:1000001",
      "tgn:2000772",
      "tgn:7012149",
      "tgn:7007255",
      "tgn:7029392"
    ],
    "placetype": [
      "aat:300008706"
    ],
    "id": 2167021,
    "name:xx": "Big Caney Creek"
  }
}
