{
  "geometry": {
    "type": "Point",
    "coordinates": [
      31.35362,
      30.79074
    ]
  },
  "type": "Feature",
  "properties": {
    "hierarchy": [
      "tgn:1095685",
      "tgn:7001242",
      "tgn:1001059",
      "tgn:7016833",
      "tgn:7029392"
    ],
    "placetype": [
      "aat:300008347"
    ],
    "name:en": "Sanafā",
    "id": 1095685
  }
}
