{
  "geometry": {
    "type": "Point",
    "coordinates": [
      -1.35,
      42.75
    ]
  },
  "type": "Feature",
  "properties": {
    "hierarchy": [
      "tgn:7302540",
      "tgn:7001155",
      "tgn:1000003",
      "tgn:7002790",
      "tgn:1000095",
      "tgn:7029392"
    ],
    "placetype": [
      "aat:300008347"
    ],
    "id": 7302540,
    "name:xx": "Murillo de Lónguida"
  }
}
