{
  "type": "FeatureCollection",
  "features": [
    {
      "geometry": {
        "type": "Point",
        "coordinates": [
          121.5167,
          31.4
        ]
      },
      "type": "Feature",
      "properties": {
        "hierarchy": [
          "tgn:1124720",
          "tgn:1000004",
          "tgn:1000111",
          "tgn:7029392"
        ],
        "placetype": [
          "aat:300008707"
        ],
        "id": 1124720,
        "name:xx": "Huangpu"
      }
    },
    {
      "geometry": {
        "type": "Point",
        "coordinates": [
          120.3333,
          32
        ]
      },
      "type": "Feature",
      "properties": {
        "hierarchy": [
          "tgn:1124721",
          "tgn:1000004",
          "tgn:7002081",
          "tgn:1000111",
          "tgn:7029392"
        ],
        "placetype": [
          "aat:300008707"
        ],
        "id": 1124721,
        "name:xx": "Huangqiao He"
      }
    },
    {
      "geometry": {
        "type": "Point",
        "coordinates": [
          116.5167,
          24.8
        ]
      },
      "type": "Feature",
      "properties": {
        "hierarchy": [
          "tgn:1124722",
          "tgn:1000004",
          "tgn:7001796",
          "tgn:1000111",
          "tgn:7029392"
        ],
        "placetype": [
          "aat:300008707"
        ],
        "id": 1124722,
        "name:xx": "Huangtan"
      }
    },
    {
      "geometry": {
        "type": "Point",
        "coordinates": [
          117.7167,
          39.5333
        ]
      },
      "type": "Feature",
      "properties": {
        "hierarchy": [
          "tgn:1124723",
          "tgn:1000004",
          "tgn:1000111",
          "tgn:7029392"
        ],
        "placetype": [
          "aat:300008707"
        ],
        "id": 1124723,
        "name:xx": "Huanxiang He"
      }
    },
    {
      "geometry": {
        "type": "Point",
        "coordinates": [
          -76.4167,
          -3.6667
        ]
      },
      "type": "Feature",
      "properties": {
        "hierarchy": [
          "tgn:1124724",
          "tgn:1000002",
          "tgn:7029392"
        ],
        "placetype": [
          "aat:300008707"
        ],
        "id": 1124724,
        "name:xx": "Huasaga"
      }
    },
    {
      "geometry": {
        "type": "Point",
        "coordinates": [
          -71.209167,
          -28.453333
        ]
      },
      "type": "Feature",
      "properties": {
        "hierarchy": [
          "tgn:1124725",
          "tgn:1001630",
          "tgn:1000049",
          "tgn:1000002",
          "tgn:7029392"
        ],
        "placetype": [
          "aat:300008707",
          "aat:300008699"
        ],
        "id": 1124725,
        "name:xx": "Huasco"
      }
    },
    {
      "geometry": {
        "type": "Point",
        "coordinates": [
          -83.6333,
          34.4
        ]
      },
      "type": "Feature",
      "properties": {
        "hierarchy": [
          "tgn:1124727",
          "tgn:1000001",
          "tgn:7012149",
          "tgn:7007248",
          "tgn:7029392"
        ],
        "placetype": [
          "aat:300008707"
        ],
        "id": 1124727,
        "name:xx": "Hudson"
      }
    }
  ]
}
