{
  "geometry": {
    "type": "Point",
    "coordinates": [
      94.9167,
      36.3667
    ]
  },
  "type": "Feature",
  "properties": {
    "hierarchy": [
      "tgn:1068307",
      "tgn:1000004",
      "tgn:7002088",
      "tgn:1000111",
      "tgn:7029392"
    ],
    "placetype": [
      "aat:300008347"
    ],
    "id": 1068307,
    "name:xx": "Golmud"
  }
}
