{
  "geometry": {
    "type": "Point",
    "coordinates": [
      32.16229,
      25.939939
    ]
  },
  "type": "Feature",
  "properties": {
    "hierarchy": [
      "tgn:7520993",
      "tgn:7001242",
      "tgn:7016833",
      "tgn:7001334",
      "tgn:7029392"
    ],
    "placetype": [
      "aat:300008795"
    ],
    "name:en": "Abū an Nūr, Jabal",
    "id": 7520993
  }
}
