{
  "geometry": {
    "type": "Point",
    "coordinates": [
      -117.5667,
      46.25
    ]
  },
  "type": "Feature",
  "properties": {
    "hierarchy": [
      "tgn:2128637",
      "tgn:1000001",
      "tgn:2002245",
      "tgn:7012149",
      "tgn:7007920",
      "tgn:7029392"
    ],
    "placetype": [
      "aat:300008697"
    ],
    "id": 2128637,
    "name:xx": "Alder Thicket Spring"
  }
}
