{
  "geometry": {
    "type": "Point",
    "coordinates": [
      -87.9167,
      30.7667
    ]
  },
  "type": "Feature",
  "properties": {
    "hierarchy": [
      "tgn:2503437",
      "tgn:2000001",
      "tgn:7002659",
      "tgn:1000001",
      "tgn:7012149",
      "tgn:7029392"
    ],
    "placetype": [
      "aat:300008680"
    ],
    "id": 2503437,
    "name:xx": "McVoys Lake"
  }
}
