{
  "geometry": {
    "type": "Point",
    "coordinates": [
      -119.35,
      41.1667
    ]
  },
  "type": "Feature",
  "properties": {
    "hierarchy": [
      "tgn:2499626",
      "tgn:1000001",
      "tgn:7012149",
      "tgn:7007526",
      "tgn:7029392"
    ],
    "placetype": [
      "aat:300008761"
    ],
    "id": 2499626,
    "name:xx": "McConnel Canyon"
  }
}
