{
  "geometry": {
    "type": "Point",
    "coordinates": [
      7.4167,
      48.7833
    ]
  },
  "type": "Feature",
  "properties": {
    "hierarchy": [
      "tgn:1035784",
      "tgn:7002870",
      "tgn:1000003",
      "tgn:1000070",
      "tgn:7029392"
    ],
    "placetype": [
      "aat:300008347"
    ],
    "id": 1035784,
    "name:xx": "Steinbourg"
  }
}
