{
  "geometry": {
    "type": "Point",
    "coordinates": [
      -3.5167,
      9.0167
    ]
  },
  "type": "Feature",
  "properties": {
    "hierarchy": [
      "tgn:1101640",
      "tgn:7001242",
      "tgn:1000168",
      "tgn:7029392"
    ],
    "placetype": [
      "aat:300008189"
    ],
    "id": 1101640,
    "name:xx": "Komoé, Parc National de la"
  }
}
