{
  "geometry": {
    "type": "Point",
    "coordinates": [
      98.35,
      56.4167
    ]
  },
  "type": "Feature",
  "properties": {
    "hierarchy": [
      "tgn:1051691",
      "tgn:1003373",
      "tgn:1000004",
      "tgn:7018214",
      "tgn:7002435",
      "tgn:7029392"
    ],
    "placetype": [
      "aat:300008347"
    ],
    "id": 1051691,
    "name:xx": "Shitkino"
  }
}
