{
  "geometry": {
    "type": "Point",
    "coordinates": [
      77.38586,
      30.927579
    ]
  },
  "type": "Feature",
  "properties": {
    "hierarchy": [
      "tgn:7552112",
      "tgn:1000004",
      "tgn:7000198",
      "tgn:1001996",
      "tgn:7029392"
    ],
    "placetype": [
      "aat:300008347"
    ],
    "name:en": "Pāīn Kūfar",
    "id": 7552112
  }
}
