{
  "geometry": {
    "type": "Point",
    "coordinates": [
      -161.6833,
      58.8833
    ]
  },
  "type": "Feature",
  "properties": {
    "hierarchy": [
      "tgn:2134158",
      "tgn:7006450",
      "tgn:2000069",
      "tgn:1000001",
      "tgn:7012149",
      "tgn:7029392"
    ],
    "placetype": [
      "aat:300008706"
    ],
    "id": 2134158,
    "name:xx": "Anita Creek"
  }
}
