{
  "geometry": {
    "type": "Point",
    "coordinates": [
      143.9333,
      -36.5833
    ]
  },
  "type": "Feature",
  "properties": {
    "hierarchy": [
      "tgn:1140982",
      "tgn:7000490",
      "tgn:1000006",
      "tgn:7006238",
      "tgn:7029392"
    ],
    "placetype": [
      "aat:300008347"
    ],
    "id": 1140982,
    "name:xx": "Inglewood"
  }
}
