{
  "geometry": {
    "type": "Point",
    "coordinates": [
      -95.3667,
      32.5167
    ]
  },
  "type": "Feature",
  "properties": {
    "hierarchy": [
      "tgn:2132114",
      "tgn:1000001",
      "tgn:7012149",
      "tgn:1002898",
      "tgn:7007826",
      "tgn:7029392"
    ],
    "placetype": [
      "aat:300006191"
    ],
    "id": 2132114,
    "name:xx": "American Legion Lake"
  }
}
