{
  "geometry": {
    "type": "Point",
    "coordinates": [
      -104.7667,
      35.8167
    ]
  },
  "type": "Feature",
  "properties": {
    "hierarchy": [
      "tgn:2415490",
      "tgn:1000001",
      "tgn:7012149",
      "tgn:2001446",
      "tgn:7007566",
      "tgn:7029392"
    ],
    "placetype": [
      "aat:300008798"
    ],
    "id": 2415490,
    "name:xx": "Island, The"
  }
}
