{
  "type": "FeatureCollection",
  "features": [
    {
      "geometry": {
        "type": "Point",
        "coordinates": [
          -97.6167,
          27.85
        ]
      },
      "type": "Feature",
      "properties": {
        "hierarchy": [
          "tgn:2329480",
          "tgn:1000001",
          "tgn:7012149",
          "tgn:2002049",
          "tgn:7007826",
          "tgn:7029392"
        ],
        "placetype": [
          "aat:300008347"
        ],
        "id": 2329480,
        "name:xx": "Five Points"
      }
    },
    {
      "geometry": {
        "type": "Point",
        "coordinates": [
          -111.9667,
          41.25
        ]
      },
      "type": "Feature",
      "properties": {
        "hierarchy": [
          "tgn:2329481",
          "tgn:1000001",
          "tgn:7012149",
          "tgn:2002129",
          "tgn:7007827",
          "tgn:7029392"
        ],
        "placetype": [
          "aat:300008347"
        ],
        "id": 2329481,
        "name:xx": "Five Points"
      }
    },
    {
      "geometry": {
        "type": "Point",
        "coordinates": [
          -118.1,
          46.0667
        ]
      },
      "type": "Feature",
      "properties": {
        "hierarchy": [
          "tgn:2329482",
          "tgn:1000001",
          "tgn:7012149",
          "tgn:2002251",
          "tgn:7007920",
          "tgn:7029392"
        ],
        "placetype": [
          "aat:300008347"
        ],
        "id": 2329482,
        "name:xx": "Five Points"
      }
    },
    {
      "geometry": {
        "type": "Point",
        "coordinates": [
          -90.8,
          42.8
        ]
      },
      "type": "Feature",
      "properties": {
        "hierarchy": [
          "tgn:2329483",
          "tgn:1000001",
          "tgn:2002324",
          "tgn:7012149",
          "tgn:7007922",
          "tgn:7029392"
        ],
        "placetype": [
          "aat:300008347"
        ],
        "id": 2329483,
        "name:xx": "Five Points"
      }
    },
    {
      "geometry": {
        "type": "Point",
        "coordinates": [
          -89.5167,
          43
        ]
      },
      "type": "Feature",
      "properties": {
        "hierarchy": [
          "tgn:2329484",
          "tgn:1000001",
          "tgn:1002316",
          "tgn:7012149",
          "tgn:7007922",
          "tgn:7029392"
        ],
        "placetype": [
          "aat:300008347"
        ],
        "id": 2329484,
        "name:xx": "Five Points"
      }
    },
    {
      "geometry": {
        "type": "Point",
        "coordinates": [
          -90.5833,
          43.3167
        ]
      },
      "type": "Feature",
      "properties": {
        "hierarchy": [
          "tgn:2329485",
          "tgn:1000001",
          "tgn:7012149",
          "tgn:2002349",
          "tgn:7007922",
          "tgn:7029392"
        ],
        "placetype": [
          "aat:300008347"
        ],
        "id": 2329485,
        "name:xx": "Five Points"
      }
    },
    {
      "geometry": {
        "type": "Point",
        "coordinates": [
          -84.8333,
          42.5
        ]
      },
      "type": "Feature",
      "properties": {
        "hierarchy": [
          "tgn:2329486",
          "tgn:1000001",
          "tgn:2000957",
          "tgn:7012149",
          "tgn:7007520",
          "tgn:7029392"
        ],
        "placetype": [
          "aat:300008347"
        ],
        "id": 2329486,
        "name:xx": "Five Points Corner"
      }
    },
    {
      "geometry": {
        "type": "Point",
        "coordinates": [
          -114.7833,
          43.5167
        ]
      },
      "type": "Feature",
      "properties": {
        "hierarchy": [
          "tgn:2329487",
          "tgn:1000001",
          "tgn:2000464",
          "tgn:7012149",
          "tgn:7007250",
          "tgn:7029392"
        ],
        "placetype": [
          "aat:300008706"
        ],
        "id": 2329487,
        "name:xx": "Five Points Creek"
      }
    },
    {
      "geometry": {
        "type": "Point",
        "coordinates": [
          -116.9167,
          45.8167
        ]
      },
      "type": "Feature",
      "properties": {
        "hierarchy": [
          "tgn:2329488",
          "tgn:1000001",
          "tgn:7012149",
          "tgn:2001722",
          "tgn:7007708",
          "tgn:7029392"
        ],
        "placetype": [
          "aat:300008706"
        ],
        "id": 2329488,
        "name:xx": "Five Points Creek"
      }
    },
    {
      "geometry": {
        "type": "Point",
        "coordinates": [
          -118.1333,
          45.4667
        ]
      },
      "type": "Feature",
      "properties": {
        "hierarchy": [
          "tgn:2329489",
          "tgn:1000001",
          "tgn:7012149",
          "tgn:7007708",
          "tgn:7029392"
        ],
        "placetype": [
          "aat:300008706"
        ],
        "id": 2329489,
        "name:xx": "Five Points Creek"
      }
    }
  ]
}
