{
  "geometry": {
    "type": "Point",
    "coordinates": [
      -116.1833,
      48.8667
    ]
  },
  "type": "Feature",
  "properties": {
    "hierarchy": [
      "tgn:2601333",
      "tgn:1000001",
      "tgn:2000462",
      "tgn:7012149",
      "tgn:7007250",
      "tgn:7029392"
    ],
    "placetype": [
      "aat:300386831"
    ],
    "id": 2601333,
    "name:xx": "Purcell Mountains"
  }
}
