{
  "type": "FeatureCollection",
  "features": [
    {
      "geometry": {
        "type": "Point",
        "coordinates": [
          21.883333,
          40.816667
        ]
      },
      "type": "Feature",
      "properties": {
        "hierarchy": [
          "tgn:7229430",
          "tgn:7002728",
          "tgn:7002715",
          "tgn:1000003",
          "tgn:1000074",
          "tgn:7029392"
        ],
        "placetype": [
          "aat:300008795"
        ],
        "id": 7229430,
        "name:xx": "Kipisóri"
      }
    },
    {
      "geometry": {
        "type": "Point",
        "coordinates": [
          24.2,
          40.883333
        ]
      },
      "type": "Feature",
      "properties": {
        "hierarchy": [
          "tgn:7229431",
          "tgn:7011170",
          "tgn:7002715",
          "tgn:1000003",
          "tgn:1000074",
          "tgn:7029392"
        ],
        "placetype": [
          "aat:300008347"
        ],
        "id": 7229431,
        "name:xx": "Kipía"
      }
    },
    {
      "geometry": {
        "type": "Point",
        "coordinates": [
          24.833333,
          36.666667
        ]
      },
      "type": "Feature",
      "properties": {
        "hierarchy": [
          "tgn:7229432",
          "tgn:7011270",
          "tgn:7002674",
          "tgn:1000003",
          "tgn:1000074",
          "tgn:7029392"
        ],
        "placetype": [
          "aat:300008850"
        ],
        "id": 7229432,
        "name:xx": "Kipárissos, Ákra"
      }
    },
    {
      "geometry": {
        "type": "Point",
        "coordinates": [
          22.55,
          39.516667
        ]
      },
      "type": "Feature",
      "properties": {
        "hierarchy": [
          "tgn:7229433",
          "tgn:7002750",
          "tgn:7001399",
          "tgn:1000003",
          "tgn:1000074",
          "tgn:7029392"
        ],
        "placetype": [
          "aat:300008347"
        ],
        "id": 7229433,
        "name:xx": "Kipárissos"
      }
    },
    {
      "geometry": {
        "type": "Point",
        "coordinates": [
          22.35,
          39.45
        ]
      },
      "type": "Feature",
      "properties": {
        "hierarchy": [
          "tgn:7229434",
          "tgn:7002748",
          "tgn:7001399",
          "tgn:1000003",
          "tgn:1000074",
          "tgn:7029392"
        ],
        "placetype": [
          "aat:300008347"
        ],
        "id": 7229434,
        "name:xx": "Kipárissos"
      }
    },
    {
      "geometry": {
        "type": "Point",
        "coordinates": [
          21.483333,
          38.766667
        ]
      },
      "type": "Feature",
      "properties": {
        "hierarchy": [
          "tgn:7229435",
          "tgn:4003773",
          "tgn:7001395",
          "tgn:1000003",
          "tgn:1000074",
          "tgn:7029392"
        ],
        "placetype": [
          "aat:300008347"
        ],
        "id": 7229435,
        "name:xx": "Kipárissos"
      }
    },
    {
      "geometry": {
        "type": "Point",
        "coordinates": [
          22.433333,
          36.466667
        ]
      },
      "type": "Feature",
      "properties": {
        "hierarchy": [
          "tgn:7229436",
          "tgn:7002745",
          "tgn:7017076",
          "tgn:1000003",
          "tgn:1000074",
          "tgn:7029392"
        ],
        "placetype": [
          "aat:300008347"
        ],
        "id": 7229436,
        "name:xx": "Kipárissos"
      }
    },
    {
      "geometry": {
        "type": "Point",
        "coordinates": [
          23.85,
          35.5
        ]
      },
      "type": "Feature",
      "properties": {
        "hierarchy": [
          "tgn:7229437",
          "tgn:7002690",
          "tgn:7012056",
          "tgn:1000003",
          "tgn:1000074",
          "tgn:7029392"
        ],
        "placetype": [
          "aat:300008347"
        ],
        "id": 7229437,
        "name:xx": "Kipárissos"
      }
    },
    {
      "geometry": {
        "type": "Point",
        "coordinates": [
          25.083333,
          35.2
        ]
      },
      "type": "Feature",
      "properties": {
        "hierarchy": [
          "tgn:7229438",
          "tgn:7002690",
          "tgn:7012056",
          "tgn:1000003",
          "tgn:1000074",
          "tgn:7029392"
        ],
        "placetype": [
          "aat:300008347"
        ],
        "id": 7229438,
        "name:xx": "Kipárissos"
      }
    },
    {
      "geometry": {
        "type": "Point",
        "coordinates": [
          22.85,
          38.983333
        ]
      },
      "type": "Feature",
      "properties": {
        "hierarchy": [
          "tgn:7229439",
          "tgn:7002751",
          "tgn:7001399",
          "tgn:1000003",
          "tgn:1000074",
          "tgn:7029392"
        ],
        "placetype": [
          "aat:300008347"
        ],
        "id": 7229439,
        "name:xx": "Kiparissón"
      }
    }
  ]
}
