{
  "geometry": {
    "type": "Point",
    "coordinates": [
      -75.65,
      35.8167
    ]
  },
  "type": "Feature",
  "properties": {
    "hierarchy": [
      "tgn:2228058",
      "tgn:1000001",
      "tgn:7012149",
      "tgn:2001488",
      "tgn:7007709",
      "tgn:7029392"
    ],
    "placetype": [
      "aat:300132316"
    ],
    "id": 2228058,
    "name:xx": "Cedar Bush Bay"
  }
}
