{
  "geometry": {
    "type": "Point",
    "coordinates": [
      -87.4167,
      36.5333
    ]
  },
  "type": "Feature",
  "properties": {
    "hierarchy": [
      "tgn:2292143",
      "tgn:1000001",
      "tgn:7012149",
      "tgn:2001899",
      "tgn:7007825",
      "tgn:7029392"
    ],
    "placetype": [
      "aat:300008706"
    ],
    "id": 2292143,
    "name:xx": "Donaldson Creek"
  }
}
