{
  "geometry": {
    "type": "Point",
    "coordinates": [
      -85.55,
      40.1167
    ]
  },
  "type": "Feature",
  "properties": {
    "hierarchy": [
      "tgn:2031557",
      "tgn:1000001",
      "tgn:1002327",
      "tgn:7012149",
      "tgn:7007252",
      "tgn:7029392"
    ],
    "placetype": [
      "aat:300008347"
    ],
    "id": 2031557,
    "name:xx": "Daleville"
  }
}
