{
  "geometry": {
    "type": "Point",
    "coordinates": [
      -78.2167,
      39.3667
    ]
  },
  "type": "Feature",
  "properties": {
    "hierarchy": [
      "tgn:2458202",
      "tgn:1000001",
      "tgn:7012149",
      "tgn:2002161",
      "tgn:7007919",
      "tgn:7029392"
    ],
    "placetype": [
      "aat:300008798"
    ],
    "id": 2458202,
    "name:xx": "Little Mountain"
  }
}
