{
  "geometry": {
    "type": "Point",
    "coordinates": [
      -74.8667,
      40.0167
    ]
  },
  "type": "Feature",
  "properties": {
    "hierarchy": [
      "tgn:2345229",
      "tgn:1002215",
      "tgn:1000001",
      "tgn:7012149",
      "tgn:7007565",
      "tgn:7029392"
    ],
    "placetype": [
      "aat:300008347"
    ],
    "id": 2345229,
    "name:xx": "Garfield Park East"
  }
}
