{
  "geometry": {
    "type": "Point",
    "coordinates": [
      -83.9167,
      15.3833
    ]
  },
  "type": "Feature",
  "properties": {
    "hierarchy": [
      "tgn:1114722",
      "tgn:1000617",
      "tgn:1000001",
      "tgn:7005554",
      "tgn:7029392"
    ],
    "placetype": [
      "aat:300008679"
    ],
    "id": 1114722,
    "name:xx": "Caratasca, Laguna de"
  }
}
