{
  "geometry": {
    "type": "Point",
    "coordinates": [
      -106.8167,
      37.3167
    ]
  },
  "type": "Feature",
  "properties": {
    "hierarchy": [
      "tgn:2245693",
      "tgn:2000195",
      "tgn:1000001",
      "tgn:7012149",
      "tgn:7007158",
      "tgn:7029392"
    ],
    "placetype": [
      "aat:300008706"
    ],
    "id": 2245693,
    "name:xx": "Coal Creek"
  }
}
