{
  "geometry": {
    "type": "Point",
    "coordinates": [
      -8.427,
      41.59
    ]
  },
  "type": "Feature",
  "properties": {
    "hierarchy": [
      "tgn:4008431",
      "tgn:7010776",
      "tgn:1000003",
      "tgn:1000090",
      "tgn:7029392"
    ],
    "placetype": [
      "aat:300008347"
    ],
    "id": 4008431,
    "name:xx": "Palmeira"
  }
}
