{
  "geometry": {
    "type": "Point",
    "coordinates": [
      -81.9333,
      36.7833
    ]
  },
  "type": "Feature",
  "properties": {
    "hierarchy": [
      "tgn:2385044",
      "tgn:1000001",
      "tgn:7012149",
      "tgn:2002194",
      "tgn:7007919",
      "tgn:7029392"
    ],
    "placetype": [
      "aat:300008761"
    ],
    "id": 2385044,
    "name:xx": "Helton Hollow"
  }
}
