{
  "geometry": {
    "type": "Point",
    "coordinates": [
      -112.0167,
      39.3667
    ]
  },
  "type": "Feature",
  "properties": {
    "hierarchy": [
      "tgn:7023122",
      "tgn:1000001",
      "tgn:7012149",
      "tgn:7007827",
      "tgn:7029392"
    ],
    "placetype": [
      "aat:300006191"
    ],
    "id": 7023122,
    "name:xx": "Sevier Bridge Reservoir"
  }
}
