{
  "geometry": {
    "type": "Point",
    "coordinates": [
      -107.4333,
      34.5833
    ]
  },
  "type": "Feature",
  "properties": {
    "hierarchy": [
      "tgn:2510515",
      "tgn:1000001",
      "tgn:2001431",
      "tgn:7012149",
      "tgn:7007566",
      "tgn:7029392"
    ],
    "placetype": [
      "aat:300006191"
    ],
    "id": 2510515,
    "name:xx": "Middle Tank"
  }
}
