{
  "geometry": {
    "type": "Point",
    "coordinates": [
      -16.35,
      28.35
    ]
  },
  "type": "Feature",
  "properties": {
    "hierarchy": [
      "tgn:7305627",
      "tgn:7002836",
      "tgn:7016622",
      "tgn:1000003",
      "tgn:1000095",
      "tgn:7029392"
    ],
    "placetype": [
      "aat:300386846"
    ],
    "id": 7305627,
    "name:xx": "Larga, Punta"
  }
}
