{
  "geometry": {
    "type": "Point",
    "coordinates": [
      -122.5333,
      40.9667
    ]
  },
  "type": "Feature",
  "properties": {
    "hierarchy": [
      "tgn:2680005",
      "tgn:1000001",
      "tgn:7012149",
      "tgn:7007157",
      "tgn:2000188",
      "tgn:7029392"
    ],
    "placetype": [
      "aat:300008706"
    ],
    "id": 2680005,
    "name:xx": "South Fork Slate Creek"
  }
}
