{
  "geometry": {
    "type": "Point",
    "coordinates": [
      -81.0167,
      28.5333
    ]
  },
  "type": "Feature",
  "properties": {
    "hierarchy": [
      "tgn:2018890",
      "tgn:1000001",
      "tgn:7012149",
      "tgn:1002749",
      "tgn:7007240",
      "tgn:7029392"
    ],
    "placetype": [
      "aat:300008347"
    ],
    "id": 2018890,
    "name:xx": "Christmas"
  }
}
