{
  "type": "FeatureCollection",
  "features": [
    {
      "geometry": {
        "type": "Point",
        "coordinates": [
          -88.2333,
          38.0667
        ]
      },
      "type": "Feature",
      "properties": {
        "hierarchy": [
          "tgn:2330220",
          "tgn:1000001",
          "tgn:7012149",
          "tgn:2000537",
          "tgn:7007251",
          "tgn:7029392"
        ],
        "placetype": [
          "aat:300008706"
        ],
        "id": 2330220,
        "name:xx": "Flanders Creek"
      }
    },
    {
      "geometry": {
        "type": "Point",
        "coordinates": [
          -110.9333,
          45.4167
        ]
      },
      "type": "Feature",
      "properties": {
        "hierarchy": [
          "tgn:2330221",
          "tgn:1000001",
          "tgn:7012149",
          "tgn:2001293",
          "tgn:7007524",
          "tgn:7029392"
        ],
        "placetype": [
          "aat:300008706"
        ],
        "id": 2330221,
        "name:xx": "Flanders Creek"
      }
    },
    {
      "geometry": {
        "type": "Point",
        "coordinates": [
          -69.3167,
          45.15
        ]
      },
      "type": "Feature",
      "properties": {
        "hierarchy": [
          "tgn:2330222",
          "tgn:1000001",
          "tgn:7012149",
          "tgn:2000928",
          "tgn:7007515",
          "tgn:7029392"
        ],
        "placetype": [
          "aat:300008798"
        ],
        "id": 2330222,
        "name:xx": "Flanders Hill"
      }
    },
    {
      "geometry": {
        "type": "Point",
        "coordinates": [
          -72.6,
          40.8667
        ]
      },
      "type": "Feature",
      "properties": {
        "hierarchy": [
          "tgn:2330223",
          "tgn:1000001",
          "tgn:7012149",
          "tgn:1002924",
          "tgn:7007568",
          "tgn:7029392"
        ],
        "placetype": [
          "aat:300008798"
        ],
        "id": 2330223,
        "name:xx": "Flanders Hill"
      }
    },
    {
      "geometry": {
        "type": "Point",
        "coordinates": [
          -72.3,
          43.7167
        ]
      },
      "type": "Feature",
      "properties": {
        "hierarchy": [
          "tgn:2330224",
          "tgn:1000001",
          "tgn:2002136",
          "tgn:7012149",
          "tgn:7007828",
          "tgn:7029392"
        ],
        "placetype": [
          "aat:300008798"
        ],
        "id": 2330224,
        "name:xx": "Flanders Hill"
      }
    },
    {
      "geometry": {
        "type": "Point",
        "coordinates": [
          -79.6167,
          33.2833
        ]
      },
      "type": "Feature",
      "properties": {
        "hierarchy": [
          "tgn:2330225",
          "tgn:2001732",
          "tgn:1000001",
          "tgn:7012149",
          "tgn:7007712",
          "tgn:7029392"
        ],
        "placetype": [
          "aat:300008680"
        ],
        "id": 2330225,
        "name:xx": "Flanders Hole"
      }
    },
    {
      "geometry": {
        "type": "Point",
        "coordinates": [
          -82.8167,
          32.0667
        ]
      },
      "type": "Feature",
      "properties": {
        "hierarchy": [
          "tgn:2330226",
          "tgn:1000001",
          "tgn:7012149",
          "tgn:2000444",
          "tgn:7007248",
          "tgn:7029392"
        ],
        "placetype": [
          "aat:300006191"
        ],
        "id": 2330226,
        "name:xx": "Flanders Lake"
      }
    },
    {
      "geometry": {
        "type": "Point",
        "coordinates": [
          -83.4,
          42.5833
        ]
      },
      "type": "Feature",
      "properties": {
        "hierarchy": [
          "tgn:2330227",
          "tgn:1000001",
          "tgn:7012149",
          "tgn:1002737",
          "tgn:7007520",
          "tgn:7029392"
        ],
        "placetype": [
          "aat:300008680"
        ],
        "id": 2330227,
        "name:xx": "Flanders Lake"
      }
    },
    {
      "geometry": {
        "type": "Point",
        "coordinates": [
          -86,
          43.6333
        ]
      },
      "type": "Feature",
      "properties": {
        "hierarchy": [
          "tgn:2330228",
          "tgn:1000001",
          "tgn:7012149",
          "tgn:7007520",
          "tgn:7029392"
        ],
        "placetype": [
          "aat:300008680"
        ],
        "id": 2330228,
        "name:xx": "Flanders Lake"
      }
    },
    {
      "geometry": {
        "type": "Point",
        "coordinates": [
          -94.0833,
          46.5833
        ]
      },
      "type": "Feature",
      "properties": {
        "hierarchy": [
          "tgn:2330229",
          "tgn:1000001",
          "tgn:2001016",
          "tgn:7012149",
          "tgn:7007521",
          "tgn:7029392"
        ],
        "placetype": [
          "aat:300008680"
        ],
        "id": 2330229,
        "name:xx": "Flanders Lake"
      }
    }
  ]
}
