{
  "geometry": {
    "type": "Point",
    "coordinates": [
      -77.4833,
      40.7833
    ]
  },
  "type": "Feature",
  "properties": {
    "hierarchy": [
      "tgn:2567151",
      "tgn:1000001",
      "tgn:7012149",
      "tgn:1002669",
      "tgn:7007710",
      "tgn:7029392"
    ],
    "placetype": [
      "aat:300008761"
    ],
    "id": 2567151,
    "name:xx": "Panther Hollow"
  }
}
