{
  "type": "FeatureCollection",
  "features": [
    {
      "geometry": {
        "type": "Point",
        "coordinates": [
          -7.2,
          54.4
        ]
      },
      "type": "Feature",
      "properties": {
        "hierarchy": [
          "tgn:7450120",
          "tgn:7002448",
          "tgn:7019203",
          "tgn:1000003",
          "tgn:7008591",
          "tgn:7029392"
        ],
        "placetype": [
          "aat:300008347"
        ],
        "name:en": "Findermore",
        "id": 7450120
      }
    },
    {
      "geometry": {
        "type": "Point",
        "coordinates": [
          -0.166667,
          51.6
        ]
      },
      "type": "Feature",
      "properties": {
        "hierarchy": [
          "tgn:7450121",
          "tgn:7026508",
          "tgn:7002445",
          "tgn:1000003",
          "tgn:7008136",
          "tgn:7008591",
          "tgn:7029392"
        ],
        "placetype": [
          "aat:300008347"
        ],
        "name:en": "Finchley",
        "id": 7450121
      }
    },
    {
      "geometry": {
        "type": "Point",
        "coordinates": [
          -5.333333,
          56.183333
        ]
      },
      "type": "Feature",
      "properties": {
        "hierarchy": [
          "tgn:7450123",
          "tgn:7019094",
          "tgn:7002444",
          "tgn:1000003",
          "tgn:7008591",
          "tgn:7029392"
        ],
        "placetype": [
          "aat:300008680"
        ],
        "name:en": "Fincharn Loch",
        "id": 7450123
      }
    },
    {
      "geometry": {
        "type": "Point",
        "coordinates": [
          -5.383333,
          56.183333
        ]
      },
      "type": "Feature",
      "properties": {
        "hierarchy": [
          "tgn:7450124",
          "tgn:7019094",
          "tgn:7002444",
          "tgn:1000003",
          "tgn:7008591",
          "tgn:7029392"
        ],
        "placetype": [
          "aat:300008057"
        ],
        "name:en": "Fincharn Castle",
        "id": 7450124
      }
    },
    {
      "geometry": {
        "type": "Point",
        "coordinates": [
          -3.833333,
          56.716667
        ]
      },
      "type": "Feature",
      "properties": {
        "hierarchy": [
          "tgn:7450127",
          "tgn:7002444",
          "tgn:1000003",
          "tgn:7019152",
          "tgn:7008591",
          "tgn:7029392"
        ],
        "placetype": [
          "aat:300004792"
        ],
        "name:en": "Fincastle House",
        "id": 7450127
      }
    },
    {
      "geometry": {
        "type": "Point",
        "coordinates": [
          -4.9,
          56.05
        ]
      },
      "type": "Feature",
      "properties": {
        "hierarchy": [
          "tgn:7450128",
          "tgn:7019094",
          "tgn:7002444",
          "tgn:1000003",
          "tgn:7008591",
          "tgn:7029392"
        ],
        "placetype": [
          "aat:300132316"
        ],
        "name:en": "Finart Bay",
        "id": 7450128
      }
    },
    {
      "geometry": {
        "type": "Point",
        "coordinates": [
          -4.933333,
          56.066667
        ]
      },
      "type": "Feature",
      "properties": {
        "hierarchy": [
          "tgn:7450129",
          "tgn:7019094",
          "tgn:7002444",
          "tgn:1000003",
          "tgn:7008591",
          "tgn:7029392"
        ],
        "placetype": [
          "aat:300008761"
        ],
        "name:en": "Finart, Glen",
        "id": 7450129
      }
    }
  ]
}
