{
  "type": "FeatureCollection",
  "features": [
    {
      "geometry": {
        "type": "Point",
        "coordinates": [
          -75.9333,
          39.2333
        ]
      },
      "type": "Feature",
      "properties": {
        "hierarchy": [
          "tgn:2233670",
          "tgn:1000001",
          "tgn:1002539",
          "tgn:7012149",
          "tgn:7007516",
          "tgn:7029392"
        ],
        "placetype": [
          "aat:300008791"
        ],
        "id": 2233670,
        "name:xx": "Chase Island"
      }
    },
    {
      "geometry": {
        "type": "Point",
        "coordinates": [
          -92.9333,
          48.4333
        ]
      },
      "type": "Feature",
      "properties": {
        "hierarchy": [
          "tgn:2233671",
          "tgn:1000001",
          "tgn:7012149",
          "tgn:2001067",
          "tgn:7007521",
          "tgn:7029392"
        ],
        "placetype": [
          "aat:300008791"
        ],
        "id": 2233671,
        "name:xx": "Chase Island"
      }
    },
    {
      "geometry": {
        "type": "Point",
        "coordinates": [
          -71.2,
          42.85
        ]
      },
      "type": "Feature",
      "properties": {
        "hierarchy": [
          "tgn:2233672",
          "tgn:1000001",
          "tgn:7014352",
          "tgn:7012149",
          "tgn:7007564",
          "tgn:7029392"
        ],
        "placetype": [
          "aat:300008791"
        ],
        "id": 2233672,
        "name:xx": "Chase Island"
      }
    },
    {
      "geometry": {
        "type": "Point",
        "coordinates": [
          -72.3833,
          43.45
        ]
      },
      "type": "Feature",
      "properties": {
        "hierarchy": [
          "tgn:2233673",
          "tgn:1000001",
          "tgn:2001427",
          "tgn:7012149",
          "tgn:7007564",
          "tgn:7029392"
        ],
        "placetype": [
          "aat:300008791"
        ],
        "id": 2233673,
        "name:xx": "Chase Island"
      }
    },
    {
      "geometry": {
        "type": "Point",
        "coordinates": [
          -84.05,
          32.2833
        ]
      },
      "type": "Feature",
      "properties": {
        "hierarchy": [
          "tgn:2233674",
          "tgn:1000001",
          "tgn:7012149",
          "tgn:2000387",
          "tgn:7007248",
          "tgn:7029392"
        ],
        "placetype": [
          "aat:300006191"
        ],
        "id": 2233674,
        "name:xx": "Chase Lake"
      }
    },
    {
      "geometry": {
        "type": "Point",
        "coordinates": [
          -116.8167,
          48.45
        ]
      },
      "type": "Feature",
      "properties": {
        "hierarchy": [
          "tgn:2233675",
          "tgn:1000001",
          "tgn:2000460",
          "tgn:7012149",
          "tgn:7007250",
          "tgn:7029392"
        ],
        "placetype": [
          "aat:300008680"
        ],
        "id": 2233675,
        "name:xx": "Chase Lake"
      }
    },
    {
      "geometry": {
        "type": "Point",
        "coordinates": [
          -87.35,
          37.95
        ]
      },
      "type": "Feature",
      "properties": {
        "hierarchy": [
          "tgn:2233676",
          "tgn:1000001",
          "tgn:7012149",
          "tgn:2000560",
          "tgn:7007252",
          "tgn:7029392"
        ],
        "placetype": [
          "aat:300006191"
        ],
        "id": 2233676,
        "name:xx": "Chase Lake"
      }
    },
    {
      "geometry": {
        "type": "Point",
        "coordinates": [
          -69.0333,
          46.4
        ]
      },
      "type": "Feature",
      "properties": {
        "hierarchy": [
          "tgn:2233677",
          "tgn:1000001",
          "tgn:7012149",
          "tgn:2000928",
          "tgn:7007515",
          "tgn:7029392"
        ],
        "placetype": [
          "aat:300008680"
        ],
        "id": 2233677,
        "name:xx": "Chase Lake"
      }
    },
    {
      "geometry": {
        "type": "Point",
        "coordinates": [
          -85.9333,
          42.3
        ]
      },
      "type": "Feature",
      "properties": {
        "hierarchy": [
          "tgn:2233678",
          "tgn:1000001",
          "tgn:7012149",
          "tgn:1002967",
          "tgn:7007520",
          "tgn:7029392"
        ],
        "placetype": [
          "aat:300008680"
        ],
        "id": 2233678,
        "name:xx": "Chase Lake"
      }
    },
    {
      "geometry": {
        "type": "Point",
        "coordinates": [
          -84.0167,
          42.7
        ]
      },
      "type": "Feature",
      "properties": {
        "hierarchy": [
          "tgn:2233679",
          "tgn:1000001",
          "tgn:7012149",
          "tgn:1002603",
          "tgn:7007520",
          "tgn:7029392"
        ],
        "placetype": [
          "aat:300008680"
        ],
        "id": 2233679,
        "name:xx": "Chase Lake"
      }
    }
  ]
}
