{
  "geometry": {
    "type": "Point",
    "coordinates": [
      -103.8167,
      38.1667
    ]
  },
  "type": "Feature",
  "properties": {
    "hierarchy": [
      "tgn:2269625",
      "tgn:1000001",
      "tgn:7012149",
      "tgn:2000204",
      "tgn:7007158",
      "tgn:7029392"
    ],
    "placetype": [
      "aat:300006075"
    ],
    "id": 2269625,
    "name:xx": "Crowley Drain Canal"
  }
}
