{
  "geometry": {
    "type": "Point",
    "coordinates": [
      -106.4333,
      42.0667
    ]
  },
  "type": "Feature",
  "properties": {
    "hierarchy": [
      "tgn:2753777",
      "tgn:1000001",
      "tgn:2002368",
      "tgn:7012149",
      "tgn:7007923",
      "tgn:7029392"
    ],
    "placetype": [
      "aat:300008761"
    ],
    "id": 2753777,
    "name:xx": "Watkins Draw"
  }
}
