{
  "type": "FeatureCollection",
  "features": [
    {
      "geometry": {
        "type": "Point",
        "coordinates": [
          5.5,
          51.516667
        ]
      },
      "type": "Feature",
      "properties": {
        "hierarchy": [
          "tgn:7271031",
          "tgn:1000003",
          "tgn:7003624",
          "tgn:7016845",
          "tgn:7029392"
        ],
        "placetype": [
          "aat:300008347"
        ],
        "name:nl": "Son en Breugel",
        "id": 7271031
      }
    },
    {
      "geometry": {
        "type": "Point",
        "coordinates": [
          5.633333,
          52.866667
        ]
      },
      "type": "Feature",
      "properties": {
        "hierarchy": [
          "tgn:7271032",
          "tgn:7003616",
          "tgn:1000003",
          "tgn:7016845",
          "tgn:7029392"
        ],
        "placetype": [
          "aat:300387200"
        ],
        "name:nl": "Sondelerwarren",
        "id": 7271032
      }
    },
    {
      "geometry": {
        "type": "Point",
        "coordinates": [
          5.616667,
          52.866667
        ]
      },
      "type": "Feature",
      "properties": {
        "hierarchy": [
          "tgn:7271033",
          "tgn:7003616",
          "tgn:1000003",
          "tgn:7016845",
          "tgn:7029392"
        ],
        "placetype": [
          "aat:300008680"
        ],
        "name:nl": "Sondelerleien",
        "id": 7271033
      }
    },
    {
      "geometry": {
        "type": "Point",
        "coordinates": [
          5.583333,
          52.866667
        ]
      },
      "type": "Feature",
      "properties": {
        "hierarchy": [
          "tgn:7271034",
          "tgn:7003616",
          "tgn:1000003",
          "tgn:7016845",
          "tgn:7029392"
        ],
        "placetype": [
          "aat:300387200"
        ],
        "name:nl": "Sondelergaast",
        "id": 7271034
      }
    },
    {
      "geometry": {
        "type": "Point",
        "coordinates": [
          5.6,
          52.866667
        ]
      },
      "type": "Feature",
      "properties": {
        "hierarchy": [
          "tgn:7271035",
          "tgn:7003616",
          "tgn:1000003",
          "tgn:7016845",
          "tgn:7029392"
        ],
        "placetype": [
          "aat:300008347"
        ],
        "name:nl": "Sondel",
        "id": 7271035
      }
    },
    {
      "geometry": {
        "type": "Point",
        "coordinates": [
          5.5,
          51.516667
        ]
      },
      "type": "Feature",
      "properties": {
        "hierarchy": [
          "tgn:7271036",
          "tgn:1000003",
          "tgn:7003624",
          "tgn:7016845",
          "tgn:7029392"
        ],
        "placetype": [
          "aat:300000745"
        ],
        "name:nl": "Son",
        "id": 7271036
      }
    },
    {
      "geometry": {
        "type": "Point",
        "coordinates": [
          5.65,
          51.366667
        ]
      },
      "type": "Feature",
      "properties": {
        "hierarchy": [
          "tgn:7271038",
          "tgn:1000003",
          "tgn:7003624",
          "tgn:7016845",
          "tgn:7029392"
        ],
        "placetype": [
          "aat:300386887"
        ],
        "name:nl": "Somerenseheide",
        "id": 7271038
      }
    },
    {
      "geometry": {
        "type": "Point",
        "coordinates": [
          5.7,
          51.35
        ]
      },
      "type": "Feature",
      "properties": {
        "hierarchy": [
          "tgn:7271039",
          "tgn:1000003",
          "tgn:7003624",
          "tgn:7016845",
          "tgn:7029392"
        ],
        "placetype": [
          "aat:300008347"
        ],
        "name:nl": "Someren-Heide",
        "id": 7271039
      }
    }
  ]
}
