{
  "geometry": {
    "type": "Point",
    "coordinates": [
      -110.4833,
      35.7833
    ]
  },
  "type": "Feature",
  "properties": {
    "hierarchy": [
      "tgn:2257028",
      "tgn:1000001",
      "tgn:7006451",
      "tgn:7012149",
      "tgn:2000099",
      "tgn:7029392"
    ],
    "placetype": [
      "aat:300008798"
    ],
    "id": 2257028,
    "name:xx": "Corn Rock"
  }
}
