{
  "type": "FeatureCollection",
  "features": [
    {
      "geometry": {
        "type": "Point",
        "coordinates": [
          -105.072222,
          22.036667
        ]
      },
      "type": "Feature",
      "properties": {
        "hierarchy": [
          "tgn:7397150",
          "tgn:1000001",
          "tgn:1001906",
          "tgn:7005560",
          "tgn:7029392"
        ],
        "placetype": [
          "aat:300008347"
        ],
        "id": 7397150,
        "name:xx": "Santa Fe"
      }
    },
    {
      "geometry": {
        "type": "Point",
        "coordinates": [
          -104.4,
          21.266667
        ]
      },
      "type": "Feature",
      "properties": {
        "hierarchy": [
          "tgn:7397151",
          "tgn:1000001",
          "tgn:1001906",
          "tgn:7005560",
          "tgn:7029392"
        ],
        "placetype": [
          "aat:300008347"
        ],
        "id": 7397151,
        "name:xx": "Santa Fe"
      }
    },
    {
      "geometry": {
        "type": "Point",
        "coordinates": [
          -100.85,
          21.183333
        ]
      },
      "type": "Feature",
      "properties": {
        "hierarchy": [
          "tgn:7397152",
          "tgn:7005584",
          "tgn:1000001",
          "tgn:7005560",
          "tgn:7029392"
        ],
        "placetype": [
          "aat:300008347"
        ],
        "id": 7397152,
        "name:xx": "Santa Fe"
      }
    },
    {
      "geometry": {
        "type": "Point",
        "coordinates": [
          -103.983333,
          20.816667
        ]
      },
      "type": "Feature",
      "properties": {
        "hierarchy": [
          "tgn:7397153",
          "tgn:7005586",
          "tgn:1000001",
          "tgn:7005560",
          "tgn:7029392"
        ],
        "placetype": [
          "aat:300008347"
        ],
        "id": 7397153,
        "name:xx": "Santa Fe"
      }
    },
    {
      "geometry": {
        "type": "Point",
        "coordinates": [
          -104.283333,
          20
        ]
      },
      "type": "Feature",
      "properties": {
        "hierarchy": [
          "tgn:7397154",
          "tgn:7005586",
          "tgn:1000001",
          "tgn:7005560",
          "tgn:7029392"
        ],
        "placetype": [
          "aat:300008347"
        ],
        "id": 7397154,
        "name:xx": "Santa Fe"
      }
    },
    {
      "geometry": {
        "type": "Point",
        "coordinates": [
          -99.25,
          19.383333
        ]
      },
      "type": "Feature",
      "properties": {
        "hierarchy": [
          "tgn:7397155",
          "tgn:7005575",
          "tgn:1000001",
          "tgn:7005560",
          "tgn:7029392"
        ],
        "placetype": [
          "aat:300008347"
        ],
        "id": 7397155,
        "name:xx": "Santa Fe"
      }
    },
    {
      "geometry": {
        "type": "Point",
        "coordinates": [
          -90.233333,
          19.033333
        ]
      },
      "type": "Feature",
      "properties": {
        "hierarchy": [
          "tgn:7397156",
          "tgn:7005578",
          "tgn:1000001",
          "tgn:7005560",
          "tgn:7029392"
        ],
        "placetype": [
          "aat:300008347"
        ],
        "id": 7397156,
        "name:xx": "Santa Fe"
      }
    },
    {
      "geometry": {
        "type": "Point",
        "coordinates": [
          -95.65,
          18.716667
        ]
      },
      "type": "Feature",
      "properties": {
        "hierarchy": [
          "tgn:7397157",
          "tgn:1000001",
          "tgn:7005599",
          "tgn:7005560",
          "tgn:7029392"
        ],
        "placetype": [
          "aat:300008347"
        ],
        "id": 7397157,
        "name:xx": "Santa Fe"
      }
    },
    {
      "geometry": {
        "type": "Point",
        "coordinates": [
          -95.7,
          18.583333
        ]
      },
      "type": "Feature",
      "properties": {
        "hierarchy": [
          "tgn:7397158",
          "tgn:1000001",
          "tgn:7005599",
          "tgn:7005560",
          "tgn:7029392"
        ],
        "placetype": [
          "aat:300008347"
        ],
        "id": 7397158,
        "name:xx": "Santa Fe"
      }
    },
    {
      "geometry": {
        "type": "Point",
        "coordinates": [
          -95.533333,
          18.033333
        ]
      },
      "type": "Feature",
      "properties": {
        "hierarchy": [
          "tgn:7397159",
          "tgn:1000001",
          "tgn:7005599",
          "tgn:7005560",
          "tgn:7029392"
        ],
        "placetype": [
          "aat:300008347"
        ],
        "id": 7397159,
        "name:xx": "Santa Fe"
      }
    }
  ]
}
