{
  "geometry": {
    "type": "Point",
    "coordinates": [
      -5.25,
      42.683333
    ]
  },
  "type": "Feature",
  "properties": {
    "hierarchy": [
      "tgn:7333281",
      "tgn:7002826",
      "tgn:7001158",
      "tgn:1000003",
      "tgn:1000095",
      "tgn:7029392"
    ],
    "placetype": [
      "aat:300008347"
    ],
    "id": 7333281,
    "name:xx": "Garfín"
  }
}
