{
  "type": "FeatureCollection",
  "features": [
    {
      "geometry": {
        "type": "Point",
        "coordinates": [
          6.9,
          52.866667
        ]
      },
      "type": "Feature",
      "properties": {
        "hierarchy": [
          "tgn:7261360",
          "tgn:7003614",
          "tgn:1000003",
          "tgn:7016845",
          "tgn:7029392"
        ],
        "placetype": [
          "aat:300006075"
        ],
        "name:nl": "Dwarsdiep",
        "id": 7261360
      }
    },
    {
      "geometry": {
        "type": "Point",
        "coordinates": [
          5.433333,
          51.716667
        ]
      },
      "type": "Feature",
      "properties": {
        "hierarchy": [
          "tgn:7261361",
          "tgn:1000003",
          "tgn:7003624",
          "tgn:7016845",
          "tgn:7029392"
        ],
        "placetype": [
          "aat:300008347"
        ],
        "name:nl": "Duyn en Dael",
        "id": 7261361
      }
    },
    {
      "geometry": {
        "type": "Point",
        "coordinates": [
          4.1,
          51.5
        ]
      },
      "type": "Feature",
      "properties": {
        "hierarchy": [
          "tgn:7261362",
          "tgn:1000003",
          "tgn:7003635",
          "tgn:7016845",
          "tgn:7029392"
        ],
        "placetype": [
          "aat:300387036"
        ],
        "name:nl": "Duvenee",
        "id": 7261362
      }
    },
    {
      "geometry": {
        "type": "Point",
        "coordinates": [
          6.75,
          53.233333
        ]
      },
      "type": "Feature",
      "properties": {
        "hierarchy": [
          "tgn:7261363",
          "tgn:1000003",
          "tgn:7003613",
          "tgn:7016845",
          "tgn:7029392"
        ],
        "placetype": [
          "aat:300006075"
        ],
        "name:nl": "Afwateringskanaal van Duurswold",
        "id": 7261363
      }
    },
    {
      "geometry": {
        "type": "Point",
        "coordinates": [
          6.116667,
          52.366667
        ]
      },
      "type": "Feature",
      "properties": {
        "hierarchy": [
          "tgn:7261365",
          "tgn:1000003",
          "tgn:7003626",
          "tgn:7016845",
          "tgn:7029392"
        ],
        "placetype": [
          "aat:300008187"
        ],
        "name:nl": "Duurse Waarden",
        "id": 7261365
      }
    },
    {
      "geometry": {
        "type": "Point",
        "coordinates": [
          6.766667,
          53
        ]
      },
      "type": "Feature",
      "properties": {
        "hierarchy": [
          "tgn:7261366",
          "tgn:7003614",
          "tgn:1000003",
          "tgn:7016845",
          "tgn:7029392"
        ],
        "placetype": [
          "aat:300387200"
        ],
        "name:nl": "Duurschen",
        "id": 7261366
      }
    },
    {
      "geometry": {
        "type": "Point",
        "coordinates": [
          6.9,
          53.15
        ]
      },
      "type": "Feature",
      "properties": {
        "hierarchy": [
          "tgn:7261367",
          "tgn:1000003",
          "tgn:7003613",
          "tgn:7016845",
          "tgn:7029392"
        ],
        "placetype": [
          "aat:300008347"
        ],
        "name:nl": "Duurkenakker",
        "id": 7261367
      }
    },
    {
      "geometry": {
        "type": "Point",
        "coordinates": [
          5.6,
          51.783333
        ]
      },
      "type": "Feature",
      "properties": {
        "hierarchy": [
          "tgn:7261368",
          "tgn:1000003",
          "tgn:7003624",
          "tgn:7016845",
          "tgn:7029392"
        ],
        "placetype": [
          "aat:300008347"
        ],
        "name:nl": "Duurendseind",
        "id": 7261368
      }
    },
    {
      "geometry": {
        "type": "Point",
        "coordinates": [
          6.116667,
          52.366667
        ]
      },
      "type": "Feature",
      "properties": {
        "hierarchy": [
          "tgn:7261369",
          "tgn:1000003",
          "tgn:7003626",
          "tgn:7016845",
          "tgn:7029392"
        ],
        "placetype": [
          "aat:300008347"
        ],
        "name:nl": "Duur",
        "id": 7261369
      }
    }
  ]
}
