{
  "geometry": {
    "type": "Point",
    "coordinates": [
      45.15,
      43.9333
    ]
  },
  "type": "Feature",
  "properties": {
    "hierarchy": [
      "tgn:1057715",
      "tgn:1000004",
      "tgn:7018212",
      "tgn:7002435",
      "tgn:7029392"
    ],
    "placetype": [
      "aat:300008347"
    ],
    "id": 1057715,
    "name:xx": "Novomelnikoye"
  }
}
