{
  "type": "FeatureCollection",
  "features": [
    {
      "geometry": {
        "type": "Point",
        "coordinates": [
          -84.9833,
          35.95
        ]
      },
      "type": "Feature",
      "properties": {
        "hierarchy": [
          "tgn:2390390",
          "tgn:1000001",
          "tgn:7012149",
          "tgn:2001854",
          "tgn:7007825",
          "tgn:7029392"
        ],
        "placetype": [
          "aat:300008347"
        ],
        "id": 2390390,
        "name:xx": "Highland Homesite Addition"
      }
    },
    {
      "geometry": {
        "type": "Point",
        "coordinates": [
          -120.2333,
          38.95
        ]
      },
      "type": "Feature",
      "properties": {
        "hierarchy": [
          "tgn:2390392",
          "tgn:1000001",
          "tgn:7012149",
          "tgn:1002350",
          "tgn:7007157",
          "tgn:7029392"
        ],
        "placetype": [
          "aat:300008680"
        ],
        "id": 2390392,
        "name:xx": "Highland Lake"
      }
    },
    {
      "geometry": {
        "type": "Point",
        "coordinates": [
          -105,
          40.2333
        ]
      },
      "type": "Feature",
      "properties": {
        "hierarchy": [
          "tgn:2390393",
          "tgn:1000001",
          "tgn:7012149",
          "tgn:7007158",
          "tgn:2000253",
          "tgn:7029392"
        ],
        "placetype": [
          "aat:300006191"
        ],
        "id": 2390393,
        "name:xx": "Highland Lake"
      }
    },
    {
      "geometry": {
        "type": "Point",
        "coordinates": [
          -81.95,
          27.95
        ]
      },
      "type": "Feature",
      "properties": {
        "hierarchy": [
          "tgn:2390394",
          "tgn:1000001",
          "tgn:7012149",
          "tgn:1002793",
          "tgn:7007240",
          "tgn:7029392"
        ],
        "placetype": [
          "aat:300008680"
        ],
        "id": 2390394,
        "name:xx": "Highland Lake"
      }
    },
    {
      "geometry": {
        "type": "Point",
        "coordinates": [
          -84.4167,
          34.0333
        ]
      },
      "type": "Feature",
      "properties": {
        "hierarchy": [
          "tgn:2390395",
          "tgn:1000001",
          "tgn:2000324",
          "tgn:7012149",
          "tgn:7007248",
          "tgn:7029392"
        ],
        "placetype": [
          "aat:300006191"
        ],
        "id": 2390395,
        "name:xx": "Highland Lake"
      }
    },
    {
      "geometry": {
        "type": "Point",
        "coordinates": [
          -98.3833,
          38.9167
        ]
      },
      "type": "Feature",
      "properties": {
        "hierarchy": [
          "tgn:2390396",
          "tgn:1000001",
          "tgn:7012149",
          "tgn:2000712",
          "tgn:7007254",
          "tgn:7029392"
        ],
        "placetype": [
          "aat:300006191"
        ],
        "id": 2390396,
        "name:xx": "Highland Lake"
      }
    },
    {
      "geometry": {
        "type": "Point",
        "coordinates": [
          -70.35,
          43.7667
        ]
      },
      "type": "Feature",
      "properties": {
        "hierarchy": [
          "tgn:2390397",
          "tgn:1000001",
          "tgn:2000920",
          "tgn:7012149",
          "tgn:7007515",
          "tgn:7029392"
        ],
        "placetype": [
          "aat:300008680"
        ],
        "id": 2390397,
        "name:xx": "Highland Lake"
      }
    },
    {
      "geometry": {
        "type": "Point",
        "coordinates": [
          -71.3,
          42.1167
        ]
      },
      "type": "Feature",
      "properties": {
        "hierarchy": [
          "tgn:2390398",
          "tgn:1000001",
          "tgn:1002724",
          "tgn:7012149",
          "tgn:7007517",
          "tgn:7029392"
        ],
        "placetype": [
          "aat:300008680"
        ],
        "id": 2390398,
        "name:xx": "Highland Lake"
      }
    },
    {
      "geometry": {
        "type": "Point",
        "coordinates": [
          -83.6333,
          42.65
        ]
      },
      "type": "Feature",
      "properties": {
        "hierarchy": [
          "tgn:2390399",
          "tgn:1000001",
          "tgn:7012149",
          "tgn:1002737",
          "tgn:7007520",
          "tgn:7029392"
        ],
        "placetype": [
          "aat:300008680"
        ],
        "id": 2390399,
        "name:xx": "Highland Lake"
      }
    }
  ]
}
