{
  "type": "FeatureCollection",
  "features": [
    {
      "geometry": {
        "type": "Point",
        "coordinates": [
          -112.1,
          41.55
        ]
      },
      "type": "Feature",
      "properties": {
        "hierarchy": [
          "tgn:2108792",
          "tgn:1000001",
          "tgn:2002102",
          "tgn:7012149",
          "tgn:7007827",
          "tgn:7029392"
        ],
        "placetype": [
          "aat:300008347"
        ],
        "id": 2108792,
        "name:xx": "Corinne"
      }
    },
    {
      "geometry": {
        "type": "Point",
        "coordinates": [
          -111.95,
          41.9667
        ]
      },
      "type": "Feature",
      "properties": {
        "hierarchy": [
          "tgn:2108793",
          "tgn:1000001",
          "tgn:2002103",
          "tgn:7012149",
          "tgn:7007827",
          "tgn:7029392"
        ],
        "placetype": [
          "aat:300008347"
        ],
        "id": 2108793,
        "name:xx": "Cornish"
      }
    },
    {
      "geometry": {
        "type": "Point",
        "coordinates": [
          -111.9333,
          41.9
        ]
      },
      "type": "Feature",
      "properties": {
        "hierarchy": [
          "tgn:2108796",
          "tgn:1000001",
          "tgn:2002103",
          "tgn:7012149",
          "tgn:7007827",
          "tgn:7029392"
        ],
        "placetype": [
          "aat:300387016"
        ],
        "id": 2108796,
        "name:xx": "Cottle"
      }
    },
    {
      "geometry": {
        "type": "Point",
        "coordinates": [
          -111.8333,
          40.65
        ]
      },
      "type": "Feature",
      "properties": {
        "hierarchy": [
          "tgn:2108797",
          "tgn:1000001",
          "tgn:7012149",
          "tgn:2002118",
          "tgn:7007827",
          "tgn:7029392"
        ],
        "placetype": [
          "aat:300008347"
        ],
        "id": 2108797,
        "name:xx": "Cottonwood"
      }
    },
    {
      "geometry": {
        "type": "Point",
        "coordinates": [
          -111.8,
          40.6167
        ]
      },
      "type": "Feature",
      "properties": {
        "hierarchy": [
          "tgn:2108798",
          "tgn:1000001",
          "tgn:7012149",
          "tgn:2002118",
          "tgn:7007827",
          "tgn:7029392"
        ],
        "placetype": [
          "aat:300008347"
        ],
        "id": 2108798,
        "name:xx": "Cottonwood Heights"
      }
    }
  ]
}
