{
  "geometry": {
    "type": "Point",
    "coordinates": [
      -105.7667,
      34.1833
    ]
  },
  "type": "Feature",
  "properties": {
    "hierarchy": [
      "tgn:2477612",
      "tgn:1000001",
      "tgn:7012149",
      "tgn:2001442",
      "tgn:7007566",
      "tgn:7029392"
    ],
    "placetype": [
      "aat:300000390"
    ],
    "id": 2477612,
    "name:xx": "M and E Number 13"
  }
}
