{
  "geometry": {
    "type": "Point",
    "coordinates": [
      -122.5333,
      41.8167
    ]
  },
  "type": "Feature",
  "properties": {
    "hierarchy": [
      "tgn:2772581",
      "tgn:1000001",
      "tgn:7012149",
      "tgn:7007157",
      "tgn:2000189",
      "tgn:7029392"
    ],
    "placetype": [
      "aat:300008706"
    ],
    "id": 2772581,
    "name:xx": "Williams Creek"
  }
}
