{
  "geometry": {
    "type": "Point",
    "coordinates": [
      -117.4833,
      44.4667
    ]
  },
  "type": "Feature",
  "properties": {
    "hierarchy": [
      "tgn:2545064",
      "tgn:7013349",
      "tgn:1000001",
      "tgn:7012149",
      "tgn:7007708",
      "tgn:7029392"
    ],
    "placetype": [
      "aat:300006075"
    ],
    "id": 2545064,
    "name:xx": "North Dixie Ditch"
  }
}
