{
  "type": "FeatureCollection",
  "features": [
    {
      "geometry": {
        "type": "Point",
        "coordinates": [
          -89.9,
          33.0833
        ]
      },
      "type": "Feature",
      "properties": {
        "hierarchy": [
          "tgn:2190440",
          "tgn:1000001",
          "tgn:7012149",
          "tgn:2001111",
          "tgn:7007522",
          "tgn:7029392"
        ],
        "placetype": [
          "aat:300008706"
        ],
        "id": 2190440,
        "name:xx": "Box Creek"
      }
    },
    {
      "geometry": {
        "type": "Point",
        "coordinates": [
          -89.1,
          34.6333
        ]
      },
      "type": "Feature",
      "properties": {
        "hierarchy": [
          "tgn:2190441",
          "tgn:1000001",
          "tgn:7012149",
          "tgn:7007522",
          "tgn:7029392"
        ],
        "placetype": [
          "aat:300008706"
        ],
        "id": 2190441,
        "name:xx": "Box Creek"
      }
    },
    {
      "geometry": {
        "type": "Point",
        "coordinates": [
          -113.25,
          48.3167
        ]
      },
      "type": "Feature",
      "properties": {
        "hierarchy": [
          "tgn:2190442",
          "tgn:1000001",
          "tgn:7012149",
          "tgn:2001277",
          "tgn:7007524",
          "tgn:7029392"
        ],
        "placetype": [
          "aat:300008706"
        ],
        "id": 2190442,
        "name:xx": "Box Creek"
      }
    },
    {
      "geometry": {
        "type": "Point",
        "coordinates": [
          -76.5167,
          35.4
        ]
      },
      "type": "Feature",
      "properties": {
        "hierarchy": [
          "tgn:2190443",
          "tgn:1000001",
          "tgn:7012149",
          "tgn:2001506",
          "tgn:7007709",
          "tgn:7029392"
        ],
        "placetype": [
          "aat:300008706"
        ],
        "id": 2190443,
        "name:xx": "Box Creek"
      }
    },
    {
      "geometry": {
        "type": "Point",
        "coordinates": [
          -81.9333,
          35.5333
        ]
      },
      "type": "Feature",
      "properties": {
        "hierarchy": [
          "tgn:2190444",
          "tgn:1000001",
          "tgn:7012149",
          "tgn:7007709",
          "tgn:7029392"
        ],
        "placetype": [
          "aat:300008706"
        ],
        "id": 2190444,
        "name:xx": "Box Creek"
      }
    },
    {
      "geometry": {
        "type": "Point",
        "coordinates": [
          -96.9167,
          35.1333
        ]
      },
      "type": "Feature",
      "properties": {
        "hierarchy": [
          "tgn:2190445",
          "tgn:1000001",
          "tgn:7012149",
          "tgn:2001685",
          "tgn:7007707",
          "tgn:7029392"
        ],
        "placetype": [
          "aat:300008706"
        ],
        "id": 2190445,
        "name:xx": "Box Creek"
      }
    },
    {
      "geometry": {
        "type": "Point",
        "coordinates": [
          -122.5333,
          42.6
        ]
      },
      "type": "Feature",
      "properties": {
        "hierarchy": [
          "tgn:2190446",
          "tgn:1000001",
          "tgn:7012149",
          "tgn:2001711",
          "tgn:7007708",
          "tgn:7029392"
        ],
        "placetype": [
          "aat:300008706"
        ],
        "id": 2190446,
        "name:xx": "Box Creek"
      }
    },
    {
      "geometry": {
        "type": "Point",
        "coordinates": [
          -119.75,
          42.3833
        ]
      },
      "type": "Feature",
      "properties": {
        "hierarchy": [
          "tgn:2190447",
          "tgn:1000001",
          "tgn:7012149",
          "tgn:2001715",
          "tgn:7007708",
          "tgn:7029392"
        ],
        "placetype": [
          "aat:300008706"
        ],
        "id": 2190447,
        "name:xx": "Box Creek"
      }
    },
    {
      "geometry": {
        "type": "Point",
        "coordinates": [
          -112.0333,
          38.4833
        ]
      },
      "type": "Feature",
      "properties": {
        "hierarchy": [
          "tgn:2190448",
          "tgn:1000001",
          "tgn:7012149",
          "tgn:2002116",
          "tgn:7007827",
          "tgn:7029392"
        ],
        "placetype": [
          "aat:300008706"
        ],
        "id": 2190448,
        "name:xx": "Box Creek"
      }
    },
    {
      "geometry": {
        "type": "Point",
        "coordinates": [
          -120.8,
          48.1
        ]
      },
      "type": "Feature",
      "properties": {
        "hierarchy": [
          "tgn:2190449",
          "tgn:1000001",
          "tgn:1002260",
          "tgn:7012149",
          "tgn:7007920",
          "tgn:7029392"
        ],
        "placetype": [
          "aat:300008706"
        ],
        "id": 2190449,
        "name:xx": "Box Creek"
      }
    }
  ]
}
