{
  "geometry": {
    "type": "Point",
    "coordinates": [
      -100.5833,
      50.4667
    ]
  },
  "type": "Feature",
  "properties": {
    "hierarchy": [
      "tgn:1014009",
      "tgn:7005685",
      "tgn:1000001",
      "tgn:7005734",
      "tgn:7029392"
    ],
    "placetype": [
      "aat:300008347"
    ],
    "id": 1014009,
    "name:xx": "Shoal Lake"
  }
}
