{
  "geometry": {
    "type": "Point",
    "coordinates": [
      31.599722,
      30.837222
    ]
  },
  "type": "Feature",
  "properties": {
    "hierarchy": [
      "tgn:7525548",
      "tgn:7001242",
      "tgn:1001059",
      "tgn:7016833",
      "tgn:7029392"
    ],
    "placetype": [
      "aat:300387086"
    ],
    "name:en": "Baḩr Şafţ, Maşríf",
    "id": 7525548
  }
}
