{
  "geometry": {
    "type": "Point",
    "coordinates": [
      -100.3167,
      28.9333
    ]
  },
  "type": "Feature",
  "properties": {
    "hierarchy": [
      "tgn:2729591",
      "tgn:1000001",
      "tgn:7012149",
      "tgn:2002038",
      "tgn:7007826",
      "tgn:7029392"
    ],
    "placetype": [
      "aat:300006191"
    ],
    "id": 2729591,
    "name:xx": "Trosado Tank"
  }
}
