{
  "geometry": {
    "type": "Point",
    "coordinates": [
      29.934167,
      31.221944
    ]
  },
  "type": "Feature",
  "properties": {
    "hierarchy": [
      "tgn:7526253",
      "tgn:7001242",
      "tgn:7016833",
      "tgn:1001079",
      "tgn:7029392"
    ],
    "placetype": [
      "aat:300000745"
    ],
    "name:en": "Sīdī Jābir",
    "id": 7526253
  }
}
