{
  "geometry": {
    "type": "Point",
    "coordinates": [
      19.5667,
      -28.1833
    ]
  },
  "type": "Feature",
  "properties": {
    "hierarchy": [
      "tgn:1124539",
      "tgn:7001242",
      "tgn:7030585",
      "tgn:1000198",
      "tgn:7029392"
    ],
    "placetype": [
      "aat:300008707"
    ],
    "id": 1124539,
    "name:xx": "Hamrivier"
  }
}
