{
  "geometry": {
    "type": "Point",
    "coordinates": [
      -111.8833,
      33.9333
    ]
  },
  "type": "Feature",
  "properties": {
    "hierarchy": [
      "tgn:2496892",
      "tgn:1000001",
      "tgn:7006451",
      "tgn:7012149",
      "tgn:2000097",
      "tgn:7029392"
    ],
    "placetype": [
      "aat:300008699"
    ],
    "id": 2496892,
    "name:xx": "Mattys Fork"
  }
}
