{
  "geometry": {
    "type": "Point",
    "coordinates": [
      -116.7333,
      42.55
    ]
  },
  "type": "Feature",
  "properties": {
    "hierarchy": [
      "tgn:2422451",
      "tgn:1000001",
      "tgn:7012149",
      "tgn:2000488",
      "tgn:7007250",
      "tgn:7029392"
    ],
    "placetype": [
      "aat:300006191"
    ],
    "id": 2422451,
    "name:xx": "Jims Reservoir"
  }
}
