{
  "type": "FeatureCollection",
  "features": [
    {
      "geometry": {
        "type": "Point",
        "coordinates": [
          14.233333,
          51.133333
        ]
      },
      "type": "Feature",
      "properties": {
        "hierarchy": [
          "tgn:7123310",
          "tgn:1000003",
          "tgn:7003685",
          "tgn:7000084",
          "tgn:7029392"
        ],
        "placetype": [
          "aat:300008347"
        ],
        "id": 7123310,
        "name:xx": "Neue Häuser"
      }
    },
    {
      "geometry": {
        "type": "Point",
        "coordinates": [
          14.216667,
          51
        ]
      },
      "type": "Feature",
      "properties": {
        "hierarchy": [
          "tgn:7123311",
          "tgn:1000003",
          "tgn:7003685",
          "tgn:7000084",
          "tgn:7029392"
        ],
        "placetype": [
          "aat:300008347"
        ],
        "id": 7123311,
        "name:xx": "Neue Häuser"
      }
    },
    {
      "geometry": {
        "type": "Point",
        "coordinates": [
          13.766667,
          50.883333
        ]
      },
      "type": "Feature",
      "properties": {
        "hierarchy": [
          "tgn:7123312",
          "tgn:1000003",
          "tgn:7003685",
          "tgn:7000084",
          "tgn:7029392"
        ],
        "placetype": [
          "aat:300008347"
        ],
        "id": 7123312,
        "name:xx": "Neue Häuser"
      }
    },
    {
      "geometry": {
        "type": "Point",
        "coordinates": [
          13.1,
          50.616667
        ]
      },
      "type": "Feature",
      "properties": {
        "hierarchy": [
          "tgn:7123313",
          "tgn:1000003",
          "tgn:7003685",
          "tgn:7000084",
          "tgn:7029392"
        ],
        "placetype": [
          "aat:300008347"
        ],
        "id": 7123313,
        "name:xx": "Neue Häuser"
      }
    },
    {
      "geometry": {
        "type": "Point",
        "coordinates": [
          7.633333,
          51.733333
        ]
      },
      "type": "Feature",
      "properties": {
        "hierarchy": [
          "tgn:7123315",
          "tgn:1000003",
          "tgn:7003677",
          "tgn:7000084",
          "tgn:7029392"
        ],
        "placetype": [
          "aat:300000206"
        ],
        "id": 7123315,
        "name:xx": "Neue Häuser"
      }
    },
    {
      "geometry": {
        "type": "Point",
        "coordinates": [
          13.083333,
          50.766667
        ]
      },
      "type": "Feature",
      "properties": {
        "hierarchy": [
          "tgn:7123316",
          "tgn:1000003",
          "tgn:7003685",
          "tgn:7000084",
          "tgn:7029392"
        ],
        "placetype": [
          "aat:300000206"
        ],
        "id": 7123316,
        "name:xx": "Neue Häuser"
      }
    },
    {
      "geometry": {
        "type": "Point",
        "coordinates": [
          11.533333,
          53.066667
        ]
      },
      "type": "Feature",
      "properties": {
        "hierarchy": [
          "tgn:7123317",
          "tgn:7000096",
          "tgn:1000003",
          "tgn:7000084",
          "tgn:7029392"
        ],
        "placetype": [
          "aat:300000206"
        ],
        "id": 7123317,
        "name:xx": "Neuehaus"
      }
    },
    {
      "geometry": {
        "type": "Point",
        "coordinates": [
          9.633333,
          51.4
        ]
      },
      "type": "Feature",
      "properties": {
        "hierarchy": [
          "tgn:7123318",
          "tgn:1000003",
          "tgn:7003676",
          "tgn:7000084",
          "tgn:7029392"
        ],
        "placetype": [
          "aat:300000206"
        ],
        "id": 7123318,
        "name:xx": "Neuehaus"
      }
    },
    {
      "geometry": {
        "type": "Point",
        "coordinates": [
          11.766667,
          51.233333
        ]
      },
      "type": "Feature",
      "properties": {
        "hierarchy": [
          "tgn:7123319",
          "tgn:1000003",
          "tgn:7003687",
          "tgn:7000084",
          "tgn:7029392"
        ],
        "placetype": [
          "aat:300055621"
        ],
        "id": 7123319,
        "name:xx": "Neue Göhle"
      }
    }
  ]
}
