{
  "geometry": {
    "type": "Point",
    "coordinates": [
      -113.8333,
      47.2667
    ]
  },
  "type": "Feature",
  "properties": {
    "hierarchy": [
      "tgn:2178753",
      "tgn:1000001",
      "tgn:7012149",
      "tgn:7007524",
      "tgn:7029392"
    ],
    "placetype": [
      "aat:300008798"
    ],
    "id": 2178753,
    "name:xx": "Blacktail Peak"
  }
}
