{
  "geometry": {
    "type": "Point",
    "coordinates": [
      50.8333,
      57.8333
    ]
  },
  "type": "Feature",
  "properties": {
    "hierarchy": [
      "tgn:1137306",
      "tgn:1000004",
      "tgn:1003379",
      "tgn:7018214",
      "tgn:7002435",
      "tgn:7029392"
    ],
    "placetype": [
      "aat:300008347"
    ],
    "id": 1137306,
    "name:xx": "Bogorodskoye"
  }
}
