{
  "geometry": {
    "type": "Point",
    "coordinates": [
      -80.5333,
      39.3333
    ]
  },
  "type": "Feature",
  "properties": {
    "hierarchy": [
      "tgn:2412147",
      "tgn:1000001",
      "tgn:7012149",
      "tgn:2002267",
      "tgn:7013961",
      "tgn:7029392"
    ],
    "placetype": [
      "aat:300008699"
    ],
    "id": 2412147,
    "name:xx": "Indian Run"
  }
}
