{
  "type": "FeatureCollection",
  "features": [
    {
      "geometry": {
        "type": "Point",
        "coordinates": [
          -86.85,
          34.55
        ]
      },
      "type": "Feature",
      "properties": {
        "hierarchy": [
          "tgn:2657710",
          "tgn:7002659",
          "tgn:1000001",
          "tgn:7012149",
          "tgn:2000041",
          "tgn:7029392"
        ],
        "placetype": [
          "aat:300008746"
        ],
        "id": 2657710,
        "name:xx": "Shelf Cave"
      }
    },
    {
      "geometry": {
        "type": "Point",
        "coordinates": [
          -93.3167,
          37.0833
        ]
      },
      "type": "Feature",
      "properties": {
        "hierarchy": [
          "tgn:2657711",
          "tgn:1000001",
          "tgn:2001185",
          "tgn:7012149",
          "tgn:7007523",
          "tgn:7029392"
        ],
        "placetype": [
          "aat:300008746"
        ],
        "id": 2657711,
        "name:xx": "Shelf Cave"
      }
    },
    {
      "geometry": {
        "type": "Point",
        "coordinates": [
          -145.4333,
          63.7833
        ]
      },
      "type": "Feature",
      "properties": {
        "hierarchy": [
          "tgn:2657712",
          "tgn:7006450",
          "tgn:1000001",
          "tgn:7012149",
          "tgn:2000085",
          "tgn:7029392"
        ],
        "placetype": [
          "aat:300008706"
        ],
        "id": 2657712,
        "name:xx": "Shelf Creek"
      }
    },
    {
      "geometry": {
        "type": "Point",
        "coordinates": [
          -105.65,
          40.2667
        ]
      },
      "type": "Feature",
      "properties": {
        "hierarchy": [
          "tgn:2657713",
          "tgn:1000001",
          "tgn:7012149",
          "tgn:2000226",
          "tgn:7007158",
          "tgn:7029392"
        ],
        "placetype": [
          "aat:300008706"
        ],
        "id": 2657713,
        "name:xx": "Shelf Creek"
      }
    },
    {
      "geometry": {
        "type": "Point",
        "coordinates": [
          -152.7167,
          62.45
        ]
      },
      "type": "Feature",
      "properties": {
        "hierarchy": [
          "tgn:2657714",
          "tgn:7006450",
          "tgn:1000001",
          "tgn:2124053",
          "tgn:7012149",
          "tgn:7029392"
        ],
        "placetype": [
          "aat:300008835"
        ],
        "id": 2657714,
        "name:xx": "Shelf Glacier"
      }
    },
    {
      "geometry": {
        "type": "Point",
        "coordinates": [
          -118.95,
          37.4167
        ]
      },
      "type": "Feature",
      "properties": {
        "hierarchy": [
          "tgn:2657715",
          "tgn:1000001",
          "tgn:7012149",
          "tgn:1002392",
          "tgn:7007157",
          "tgn:7029392"
        ],
        "placetype": [
          "aat:300008680"
        ],
        "id": 2657715,
        "name:xx": "Shelf Lake"
      }
    },
    {
      "geometry": {
        "type": "Point",
        "coordinates": [
          -105.6333,
          40.2667
        ]
      },
      "type": "Feature",
      "properties": {
        "hierarchy": [
          "tgn:2657716",
          "tgn:1000001",
          "tgn:7012149",
          "tgn:2000226",
          "tgn:7007158",
          "tgn:7029392"
        ],
        "placetype": [
          "aat:300008680"
        ],
        "id": 2657716,
        "name:xx": "Shelf Lake"
      }
    },
    {
      "geometry": {
        "type": "Point",
        "coordinates": [
          -105.7833,
          39.5833
        ]
      },
      "type": "Feature",
      "properties": {
        "hierarchy": [
          "tgn:2657717",
          "tgn:1000001",
          "tgn:2000201",
          "tgn:7012149",
          "tgn:7007158",
          "tgn:7029392"
        ],
        "placetype": [
          "aat:300008680"
        ],
        "id": 2657717,
        "name:xx": "Shelf Lake"
      }
    },
    {
      "geometry": {
        "type": "Point",
        "coordinates": [
          -114.5667,
          44.0667
        ]
      },
      "type": "Feature",
      "properties": {
        "hierarchy": [
          "tgn:2657718",
          "tgn:1000001",
          "tgn:2000470",
          "tgn:7012149",
          "tgn:7007250",
          "tgn:7029392"
        ],
        "placetype": [
          "aat:300008680"
        ],
        "id": 2657718,
        "name:xx": "Shelf Lake"
      }
    },
    {
      "geometry": {
        "type": "Point",
        "coordinates": [
          -116.5333,
          45.3333
        ]
      },
      "type": "Feature",
      "properties": {
        "hierarchy": [
          "tgn:2657719",
          "tgn:1000001",
          "tgn:7012149",
          "tgn:2000476",
          "tgn:7007250",
          "tgn:7029392"
        ],
        "placetype": [
          "aat:300008680"
        ],
        "id": 2657719,
        "name:xx": "Shelf Lake"
      }
    }
  ]
}
