{
  "geometry": {
    "type": "Point",
    "coordinates": [
      -113.0333,
      39.1167
    ]
  },
  "type": "Feature",
  "properties": {
    "hierarchy": [
      "tgn:2653648",
      "tgn:1000001",
      "tgn:7012149",
      "tgn:2002114",
      "tgn:7007827",
      "tgn:7029392"
    ],
    "placetype": [
      "aat:300006191"
    ],
    "id": 2653648,
    "name:xx": "Sevier Lake Reservoir Number 5"
  }
}
