{
  "geometry": {
    "type": "Point",
    "coordinates": [
      115.35,
      36.4833
    ]
  },
  "type": "Feature",
  "properties": {
    "hierarchy": [
      "tgn:1139021",
      "tgn:1000004",
      "tgn:7002085",
      "tgn:1000111",
      "tgn:7029392"
    ],
    "placetype": [
      "aat:300008347"
    ],
    "id": 1139021,
    "name:xx": "Guan Xian"
  }
}
