{
  "geometry": {
    "type": "Point",
    "coordinates": [
      -96.6333,
      30.8333
    ]
  },
  "type": "Feature",
  "properties": {
    "hierarchy": [
      "tgn:2108200",
      "tgn:1000001",
      "tgn:7012149",
      "tgn:1002830",
      "tgn:7007826",
      "tgn:7029392"
    ],
    "placetype": [
      "aat:300387016"
    ],
    "id": 2108200,
    "name:xx": "Valley Junction"
  }
}
