{
  "geometry": {
    "type": "Point",
    "coordinates": [
      80.05,
      27.95
    ]
  },
  "type": "Feature",
  "properties": {
    "hierarchy": [
      "tgn:7577858",
      "tgn:1000004",
      "tgn:7000198",
      "tgn:7016722",
      "tgn:7029392"
    ],
    "placetype": [
      "aat:300006075"
    ],
    "name:en": "Lucknow Branch",
    "id": 7577858
  }
}
