{
  "type": "FeatureCollection",
  "features": [
    {
      "geometry": {
        "type": "Point",
        "coordinates": [
          -72.7,
          40.8
        ]
      },
      "type": "Feature",
      "properties": {
        "hierarchy": [
          "tgn:7017840",
          "tgn:1000001",
          "tgn:7012149",
          "tgn:1002924",
          "tgn:7007568",
          "tgn:7029392"
        ],
        "placetype": [
          "aat:300008347"
        ],
        "id": 7017840,
        "name:xx": "Remsenburg"
      }
    },
    {
      "geometry": {
        "type": "Point",
        "coordinates": [
          -73.9167,
          40.7833
        ]
      },
      "type": "Feature",
      "properties": {
        "hierarchy": [
          "tgn:7017842",
          "tgn:7022657",
          "tgn:1000001",
          "tgn:7012149",
          "tgn:7007567",
          "tgn:7007568",
          "tgn:7029392"
        ],
        "placetype": [
          "aat:300008791"
        ],
        "id": 7017842,
        "name:xx": "Wards Island"
      }
    },
    {
      "geometry": {
        "type": "Point",
        "coordinates": [
          -97.7667,
          31.1333
        ]
      },
      "type": "Feature",
      "properties": {
        "hierarchy": [
          "tgn:7017843",
          "tgn:1000001",
          "tgn:1002174",
          "tgn:7012149",
          "tgn:7007826",
          "tgn:7029392"
        ],
        "placetype": [
          "aat:300386994"
        ],
        "id": 7017843,
        "name:xx": "Fort Hood"
      }
    },
    {
      "geometry": {
        "type": "Point",
        "coordinates": [
          -96.1,
          29.7833
        ]
      },
      "type": "Feature",
      "properties": {
        "hierarchy": [
          "tgn:7017845",
          "tgn:1000001",
          "tgn:1002161",
          "tgn:7012149",
          "tgn:7007826",
          "tgn:7029392"
        ],
        "placetype": [
          "aat:300008347",
          "aat:300387210",
          "aat:300008375"
        ],
        "id": 7017845,
        "name:xx": "San Felipe"
      }
    },
    {
      "geometry": {
        "type": "Point",
        "coordinates": [
          -76.4667,
          39.2167
        ]
      },
      "type": "Feature",
      "properties": {
        "hierarchy": [
          "tgn:7017846",
          "tgn:7016099",
          "tgn:1000001",
          "tgn:7012149",
          "tgn:7007516",
          "tgn:7029392"
        ],
        "placetype": [
          "aat:300008347"
        ],
        "id": 7017846,
        "name:xx": "Sparrows Point"
      }
    },
    {
      "geometry": {
        "type": "Point",
        "coordinates": [
          -95.25,
          34.0167
        ]
      },
      "type": "Feature",
      "properties": {
        "hierarchy": [
          "tgn:7017848",
          "tgn:1000001",
          "tgn:2001634",
          "tgn:7012149",
          "tgn:7007707",
          "tgn:7029392"
        ],
        "placetype": [
          "aat:300008347",
          "aat:300006909",
          "aat:300008375"
        ],
        "id": 7017848,
        "name:xx": "Fort Towson"
      }
    }
  ]
}
