{
  "geometry": {
    "type": "Point",
    "coordinates": [
      120.564722,
      23.5875
    ]
  },
  "type": "Feature",
  "properties": {
    "hierarchy": [
      "tgn:7482632",
      "tgn:7468018",
      "tgn:1000004",
      "tgn:1000141",
      "tgn:7029392"
    ],
    "placetype": [
      "aat:300007836"
    ],
    "id": 7482632,
    "name:xx": "Xindi Qiao"
  }
}
