{
  "geometry": {
    "type": "Point",
    "coordinates": [
      44.0833,
      53.6667
    ]
  },
  "type": "Feature",
  "properties": {
    "hierarchy": [
      "tgn:1054038",
      "tgn:1000004",
      "tgn:1003399",
      "tgn:7018214",
      "tgn:7002435",
      "tgn:7029392"
    ],
    "placetype": [
      "aat:300008347"
    ],
    "id": 1054038,
    "name:xx": "Golitsyno"
  }
}
