{
  "geometry": {
    "type": "Point",
    "coordinates": [
      79.25789,
      26.11315
    ]
  },
  "type": "Feature",
  "properties": {
    "hierarchy": [
      "tgn:7565684",
      "tgn:1000004",
      "tgn:7000198",
      "tgn:7016722",
      "tgn:7029392"
    ],
    "placetype": [
      "aat:300008347"
    ],
    "name:en": "Sikri Rāja",
    "id": 7565684
  }
}
