{
  "geometry": {
    "type": "Point",
    "coordinates": [
      -78.0333,
      39.5667
    ]
  },
  "type": "Feature",
  "properties": {
    "hierarchy": [
      "tgn:2118756",
      "tgn:1000001",
      "tgn:2002254",
      "tgn:7012149",
      "tgn:7013961",
      "tgn:7029392"
    ],
    "placetype": [
      "aat:300008347",
      "aat:300387210"
    ],
    "id": 2118756,
    "name:xx": "Johnsontown"
  }
}
