{
  "geometry": {
    "type": "Point",
    "coordinates": [
      -78.9667,
      35.2833
    ]
  },
  "type": "Feature",
  "properties": {
    "hierarchy": [
      "tgn:2681501",
      "tgn:1000001",
      "tgn:7012149",
      "tgn:2001502",
      "tgn:7007709",
      "tgn:7029392"
    ],
    "placetype": [
      "aat:300008706"
    ],
    "id": 2681501,
    "name:xx": "South Prong Anderson Creek"
  }
}
