{
  "geometry": {
    "type": "Point",
    "coordinates": [
      -52.2667,
      4.7333
    ]
  },
  "type": "Feature",
  "properties": {
    "hierarchy": [
      "tgn:1024197",
      "tgn:1002072",
      "tgn:1000053",
      "tgn:1000002",
      "tgn:7029392"
    ],
    "placetype": [
      "aat:300008347"
    ],
    "id": 1024197,
    "name:xx": "Roura"
  }
}
