{
  "geometry": {
    "type": "Point",
    "coordinates": [
      -79.4167,
      40.1833
    ]
  },
  "type": "Feature",
  "properties": {
    "hierarchy": [
      "tgn:2593427",
      "tgn:1000001",
      "tgn:7012149",
      "tgn:1003017",
      "tgn:7007710",
      "tgn:7029392"
    ],
    "placetype": [
      "aat:300000390"
    ],
    "id": 2593427,
    "name:xx": "Porch Mine"
  }
}
