{
  "geometry": {
    "type": "Point",
    "coordinates": [
      10.95,
      48.55
    ]
  },
  "type": "Feature",
  "properties": {
    "hierarchy": [
      "tgn:7199998",
      "tgn:7003669",
      "tgn:1000003",
      "tgn:7000084",
      "tgn:7029392"
    ],
    "placetype": [
      "aat:300008347"
    ],
    "id": 7199998,
    "name:xx": "Edenhausen"
  }
}
