{
  "geometry": {
    "type": "Point",
    "coordinates": [
      -83.3833,
      38.0833
    ]
  },
  "type": "Feature",
  "properties": {
    "hierarchy": [
      "tgn:2717572",
      "tgn:1000001",
      "tgn:7012149",
      "tgn:1002837",
      "tgn:7007255",
      "tgn:7029392"
    ],
    "placetype": [
      "aat:300008699"
    ],
    "id": 2717572,
    "name:xx": "Thomas Cave Branch"
  }
}
