{
  "geometry": {
    "type": "Point",
    "coordinates": [
      -87.9833,
      31.9833
    ]
  },
  "type": "Feature",
  "properties": {
    "hierarchy": [
      "tgn:2004575",
      "tgn:7002659",
      "tgn:1000001",
      "tgn:2000012",
      "tgn:7012149",
      "tgn:7029392"
    ],
    "placetype": [
      "aat:300008347"
    ],
    "id": 2004575,
    "name:xx": "Morvin"
  }
}
