{
  "geometry": {
    "type": "Point",
    "coordinates": [
      -78.35,
      35.9167
    ]
  },
  "type": "Feature",
  "properties": {
    "hierarchy": [
      "tgn:2076352",
      "tgn:1000001",
      "tgn:7012149",
      "tgn:7013940",
      "tgn:7007709",
      "tgn:7029392"
    ],
    "placetype": [
      "aat:300008347",
      "aat:300387210"
    ],
    "id": 2076352,
    "name:xx": "Riley"
  }
}
