{
  "geometry": {
    "type": "Point",
    "coordinates": [
      -97.4167,
      27.25
    ]
  },
  "type": "Feature",
  "properties": {
    "hierarchy": [
      "tgn:2574686",
      "tgn:1000001",
      "tgn:7012149",
      "tgn:2002016",
      "tgn:7007826",
      "tgn:7029392"
    ],
    "placetype": [
      "aat:300008850"
    ],
    "id": 2574686,
    "name:xx": "Penascal, Point"
  }
}
