{
  "geometry": {
    "type": "Point",
    "coordinates": [
      39.9333,
      47.1833
    ]
  },
  "type": "Feature",
  "properties": {
    "hierarchy": [
      "tgn:1138112",
      "tgn:1000004",
      "tgn:1003405",
      "tgn:7018214",
      "tgn:7002435",
      "tgn:7029392"
    ],
    "placetype": [
      "aat:300008347"
    ],
    "id": 1138112,
    "name:xx": "Olginskaya"
  }
}
