{
  "geometry": {
    "type": "Point",
    "coordinates": [
      -120.05,
      38.9167
    ]
  },
  "type": "Feature",
  "properties": {
    "hierarchy": [
      "tgn:2712691",
      "tgn:1000001",
      "tgn:7012149",
      "tgn:1002350",
      "tgn:7007157",
      "tgn:7029392"
    ],
    "placetype": [
      "aat:300008706"
    ],
    "id": 2712691,
    "name:xx": "Taylor Creek"
  }
}
