{
  "geometry": {
    "type": "Point",
    "coordinates": [
      -115.0333,
      39.2667
    ]
  },
  "type": "Feature",
  "properties": {
    "hierarchy": [
      "tgn:2188404",
      "tgn:1000001",
      "tgn:7012149",
      "tgn:2001420",
      "tgn:7007526",
      "tgn:7029392"
    ],
    "placetype": [
      "aat:300000390"
    ],
    "id": 2188404,
    "name:xx": "Boston-Ely Shaft"
  }
}
