{
  "geometry": {
    "type": "Point",
    "coordinates": [
      -99.3875,
      20.65
    ]
  },
  "type": "Feature",
  "properties": {
    "hierarchy": [
      "tgn:7410910",
      "tgn:7005587",
      "tgn:1000001",
      "tgn:7005560",
      "tgn:7029392"
    ],
    "placetype": [
      "aat:300008347"
    ],
    "id": 7410910,
    "name:es": "Tzijay"
  }
}
