{
  "type": "FeatureCollection",
  "features": [
    {
      "geometry": {
        "type": "Point",
        "coordinates": [
          -91,
          71
        ]
      },
      "type": "Feature",
      "properties": {
        "hierarchy": [
          "tgn:1112350",
          "tgn:7005685",
          "tgn:1000001",
          "tgn:7024197",
          "tgn:7029392"
        ],
        "placetype": [
          "aat:300132315"
        ],
        "id": 1112350,
        "name:xx": "Boothia, Gulf of"
      }
    },
    {
      "geometry": {
        "type": "Point",
        "coordinates": [
          23.1,
          32.4167
        ]
      },
      "type": "Feature",
      "properties": {
        "hierarchy": [
          "tgn:1112354",
          "tgn:7001242",
          "tgn:7000605",
          "tgn:1000172",
          "tgn:7029392"
        ],
        "placetype": [
          "aat:300132315"
        ],
        "id": 1112354,
        "name:xx": "Bumbah, Khalīj"
      }
    },
    {
      "geometry": {
        "type": "Point",
        "coordinates": [
          9.183333,
          39.133333
        ]
      },
      "type": "Feature",
      "properties": {
        "hierarchy": [
          "tgn:1112356",
          "tgn:1001641",
          "tgn:1000003",
          "tgn:7003121",
          "tgn:1000080",
          "tgn:7029392"
        ],
        "placetype": [
          "aat:300132316",
          "aat:300132315"
        ],
        "id": 1112356,
        "name:xx": "Cagliari, Golfo di"
      }
    },
    {
      "geometry": {
        "type": "Point",
        "coordinates": [
          -112,
          28
        ]
      },
      "type": "Feature",
      "properties": {
        "hierarchy": [
          "tgn:1112357",
          "tgn:1000001",
          "tgn:7029392"
        ],
        "placetype": [
          "aat:300132315"
        ],
        "id": 1112357,
        "name:xx": "California, Gulf of"
      }
    },
    {
      "geometry": {
        "type": "Point",
        "coordinates": [
          8.7833,
          42.5833
        ]
      },
      "type": "Feature",
      "properties": {
        "hierarchy": [
          "tgn:1112358",
          "tgn:1000003",
          "tgn:7594273",
          "tgn:1000070",
          "tgn:7029392"
        ],
        "placetype": [
          "aat:300132315"
        ],
        "id": 1112358,
        "name:xx": "Calvi, Golfe de"
      }
    }
  ]
}
