{
  "type": "FeatureCollection",
  "features": [
    {
      "geometry": {
        "type": "Point",
        "coordinates": [
          4.915639,
          50.638471
        ]
      },
      "type": "Feature",
      "properties": {
        "hierarchy": [
          "tgn:6004920",
          "tgn:7018238",
          "tgn:1000003",
          "tgn:1000063",
          "tgn:4012014",
          "tgn:7029392"
        ],
        "placetype": [
          "aat:300008347",
          "aat:300008372"
        ],
        "id": 6004920,
        "name:xx": "Ramillies-Offus"
      }
    },
    {
      "geometry": {
        "type": "Point",
        "coordinates": [
          175.166667,
          -37.433333
        ]
      },
      "type": "Feature",
      "properties": {
        "hierarchy": [
          "tgn:6004926",
          "tgn:1008380",
          "tgn:1000226",
          "tgn:7018426",
          "tgn:1000006",
          "tgn:7029392"
        ],
        "placetype": [
          "aat:300008347",
          "aat:300000835"
        ],
        "name:en": "Rangiriri",
        "id": 6004926
      }
    }
  ]
}
