{
  "type": "FeatureCollection",
  "features": [
    {
      "geometry": {
        "type": "Point",
        "coordinates": [
          10.766667,
          48.1
        ]
      },
      "type": "Feature",
      "properties": {
        "hierarchy": [
          "tgn:7093520",
          "tgn:7003669",
          "tgn:1000003",
          "tgn:7000084",
          "tgn:7029392"
        ],
        "placetype": [
          "aat:300008347"
        ],
        "id": 7093520,
        "name:xx": "Schwabm체hlhausen"
      }
    },
    {
      "geometry": {
        "type": "Point",
        "coordinates": [
          9.266667,
          47.966667
        ]
      },
      "type": "Feature",
      "properties": {
        "hierarchy": [
          "tgn:7093521",
          "tgn:7003692",
          "tgn:1000003",
          "tgn:7000084",
          "tgn:7029392"
        ],
        "placetype": [
          "aat:300008347"
        ],
        "id": 7093521,
        "name:xx": "Schw채blishausen"
      }
    },
    {
      "geometry": {
        "type": "Point",
        "coordinates": [
          10.716667,
          47.966667
        ]
      },
      "type": "Feature",
      "properties": {
        "hierarchy": [
          "tgn:7093522",
          "tgn:7003669",
          "tgn:1000003",
          "tgn:7000084",
          "tgn:7029392"
        ],
        "placetype": [
          "aat:300008347"
        ],
        "id": 7093522,
        "name:xx": "Schw채bishofen"
      }
    },
    {
      "geometry": {
        "type": "Point",
        "coordinates": [
          9.5,
          48.416667
        ]
      },
      "type": "Feature",
      "properties": {
        "hierarchy": [
          "tgn:7093525",
          "tgn:7003692",
          "tgn:1000003",
          "tgn:7000084",
          "tgn:7029392"
        ],
        "placetype": [
          "aat:300008795"
        ],
        "id": 7093525,
        "name:xx": "Schw채bische Alb"
      }
    },
    {
      "geometry": {
        "type": "Point",
        "coordinates": [
          11.666667,
          48.25
        ]
      },
      "type": "Feature",
      "properties": {
        "hierarchy": [
          "tgn:7093526",
          "tgn:7003669",
          "tgn:1000003",
          "tgn:7000084",
          "tgn:7029392"
        ],
        "placetype": [
          "aat:300008699"
        ],
        "id": 7093526,
        "name:xx": "Schwabinger Bach"
      }
    },
    {
      "geometry": {
        "type": "Point",
        "coordinates": [
          10.95,
          48.333333
        ]
      },
      "type": "Feature",
      "properties": {
        "hierarchy": [
          "tgn:7093528",
          "tgn:7003669",
          "tgn:1000003",
          "tgn:7000084",
          "tgn:7029392"
        ],
        "placetype": [
          "aat:300008347"
        ],
        "id": 7093528,
        "name:xx": "Schwabhof"
      }
    },
    {
      "geometry": {
        "type": "Point",
        "coordinates": [
          11,
          48.083333
        ]
      },
      "type": "Feature",
      "properties": {
        "hierarchy": [
          "tgn:7093529",
          "tgn:7003669",
          "tgn:1000003",
          "tgn:7000084",
          "tgn:7029392"
        ],
        "placetype": [
          "aat:300008863"
        ],
        "id": 7093529,
        "name:xx": "Schwabhauserweg-Holz"
      }
    }
  ]
}
