{
  "geometry": {
    "type": "Point",
    "coordinates": [
      -114.25,
      47.3333
    ]
  },
  "type": "Feature",
  "properties": {
    "hierarchy": [
      "tgn:2204787",
      "tgn:1000001",
      "tgn:7012149",
      "tgn:2001304",
      "tgn:7007524",
      "tgn:7029392"
    ],
    "placetype": [
      "aat:300008697"
    ],
    "id": 2204787,
    "name:xx": "Buffalo Spring"
  }
}
