{
  "geometry": {
    "type": "Point",
    "coordinates": [
      -76.8167,
      38.2833
    ]
  },
  "type": "Feature",
  "properties": {
    "hierarchy": [
      "tgn:2766942",
      "tgn:1000001",
      "tgn:7016098",
      "tgn:7012149",
      "tgn:7007516",
      "tgn:7029392"
    ],
    "placetype": [
      "aat:300132348"
    ],
    "id": 2766942,
    "name:xx": "White Point Bar"
  }
}
