{
  "geometry": {
    "type": "Point",
    "coordinates": [
      -101.3167,
      32.1167
    ]
  },
  "type": "Feature",
  "properties": {
    "hierarchy": [
      "tgn:2285370",
      "tgn:1000001",
      "tgn:7012149",
      "tgn:2002004",
      "tgn:7007826",
      "tgn:7029392"
    ],
    "placetype": [
      "aat:300008706"
    ],
    "id": 2285370,
    "name:xx": "Devils Creek"
  }
}
