{
  "geometry": {
    "type": "Point",
    "coordinates": [
      -84.9167,
      38.2667
    ]
  },
  "type": "Feature",
  "properties": {
    "hierarchy": [
      "tgn:2330530",
      "tgn:1000001",
      "tgn:7012149",
      "tgn:1002382",
      "tgn:7007255",
      "tgn:7029392"
    ],
    "placetype": [
      "aat:300008706"
    ],
    "id": 2330530,
    "name:xx": "Flat Creek"
  }
}
