{
  "type": "FeatureCollection",
  "features": [
    {
      "geometry": {
        "type": "Point",
        "coordinates": [
          -96,
          52.6333
        ]
      },
      "type": "Feature",
      "properties": {
        "hierarchy": [
          "tgn:1116570",
          "tgn:7005685",
          "tgn:1000001",
          "tgn:7005734",
          "tgn:7029392"
        ],
        "placetype": [
          "aat:300008680"
        ],
        "id": 1116570,
        "name:xx": "Harrop Lake"
      }
    },
    {
      "geometry": {
        "type": "Point",
        "coordinates": [
          -119.8333,
          42.4333
        ]
      },
      "type": "Feature",
      "properties": {
        "hierarchy": [
          "tgn:1116571",
          "tgn:1000001",
          "tgn:7012149",
          "tgn:2001715",
          "tgn:7007708",
          "tgn:7029392"
        ],
        "placetype": [
          "aat:300008680"
        ],
        "id": 1116571,
        "name:xx": "Hart Lake"
      }
    },
    {
      "geometry": {
        "type": "Point",
        "coordinates": [
          -81.2,
          28.3667
        ]
      },
      "type": "Feature",
      "properties": {
        "hierarchy": [
          "tgn:1116572",
          "tgn:1000001",
          "tgn:7012149",
          "tgn:1002749",
          "tgn:7007240",
          "tgn:7029392"
        ],
        "placetype": [
          "aat:300008680"
        ],
        "id": 1116572,
        "name:xx": "Hart, Lake"
      }
    },
    {
      "geometry": {
        "type": "Point",
        "coordinates": [
          -81.4167,
          28.0167
        ]
      },
      "type": "Feature",
      "properties": {
        "hierarchy": [
          "tgn:1116573",
          "tgn:1000001",
          "tgn:7012149",
          "tgn:1002756",
          "tgn:7007240",
          "tgn:7029392"
        ],
        "placetype": [
          "aat:300008680"
        ],
        "id": 1116573,
        "name:xx": "Hatchineha, Lake"
      }
    },
    {
      "geometry": {
        "type": "Point",
        "coordinates": [
          -122.2333,
          49.1667
        ]
      },
      "type": "Feature",
      "properties": {
        "hierarchy": [
          "tgn:1116574",
          "tgn:7005735",
          "tgn:7005685",
          "tgn:1000001",
          "tgn:7029392"
        ],
        "placetype": [
          "aat:300008680"
        ],
        "id": 1116574,
        "name:xx": "Hatzic Lake"
      }
    },
    {
      "geometry": {
        "type": "Point",
        "coordinates": [
          28.466667,
          62.1
        ]
      },
      "type": "Feature",
      "properties": {
        "hierarchy": [
          "tgn:1116575",
          "tgn:7594381",
          "tgn:1000003",
          "tgn:1000069",
          "tgn:7029392"
        ],
        "placetype": [
          "aat:300008680"
        ],
        "id": 1116575,
        "name:xx": "Haukivesi"
      }
    },
    {
      "geometry": {
        "type": "Point",
        "coordinates": [
          167.333333,
          -46
        ]
      },
      "type": "Feature",
      "properties": {
        "hierarchy": [
          "tgn:1116576",
          "tgn:1009227",
          "tgn:1000226",
          "tgn:7016822",
          "tgn:1000006",
          "tgn:7029392"
        ],
        "placetype": [
          "aat:300008680"
        ],
        "name:en": "Hauroko, Lake",
        "id": 1116576
      }
    },
    {
      "geometry": {
        "type": "Point",
        "coordinates": [
          13.633333,
          52.55
        ]
      },
      "type": "Feature",
      "properties": {
        "hierarchy": [
          "tgn:1116577",
          "tgn:7000096",
          "tgn:1000003",
          "tgn:7000084",
          "tgn:7029392"
        ],
        "placetype": [
          "aat:300008680"
        ],
        "id": 1116577,
        "name:xx": "Haussee"
      }
    },
    {
      "geometry": {
        "type": "Point",
        "coordinates": [
          169.283333,
          -44.5
        ]
      },
      "type": "Feature",
      "properties": {
        "hierarchy": [
          "tgn:1116579",
          "tgn:1009227",
          "tgn:1000226",
          "tgn:7018437",
          "tgn:1000006",
          "tgn:7029392"
        ],
        "placetype": [
          "aat:300008680"
        ],
        "name:en": "Hawea, Lake",
        "id": 1116579
      }
    }
  ]
}
