{
  "geometry": {
    "type": "Point",
    "coordinates": [
      -93.3167,
      36.0167
    ]
  },
  "type": "Feature",
  "properties": {
    "hierarchy": [
      "tgn:2626493",
      "tgn:1000001",
      "tgn:7016172",
      "tgn:7012149",
      "tgn:2000155",
      "tgn:7029392"
    ],
    "placetype": [
      "aat:300008761"
    ],
    "id": 2626493,
    "name:xx": "Rocky Hollow"
  }
}
