{
  "geometry": {
    "type": "Point",
    "coordinates": [
      -76.7167,
      42.7833
    ]
  },
  "type": "Feature",
  "properties": {
    "hierarchy": [
      "tgn:2315630",
      "tgn:1000001",
      "tgn:1002246",
      "tgn:7012149",
      "tgn:7007568",
      "tgn:7029392"
    ],
    "placetype": [
      "aat:300008850"
    ],
    "id": 2315630,
    "name:xx": "Ellis Point"
  }
}
