{
  "geometry": {
    "type": "Point",
    "coordinates": [
      -116.05,
      36.45
    ]
  },
  "type": "Feature",
  "properties": {
    "hierarchy": [
      "tgn:2444156",
      "tgn:1000001",
      "tgn:2001418",
      "tgn:7012149",
      "tgn:7007526",
      "tgn:7029392"
    ],
    "placetype": [
      "aat:300000390"
    ],
    "id": 2444156,
    "name:xx": "Labbe Mine"
  }
}
