{
  "geometry": {
    "type": "Point",
    "coordinates": [
      -71.616,
      9.066
    ]
  },
  "type": "Feature",
  "properties": {
    "hierarchy": [
      "tgn:1122658",
      "tgn:1001985",
      "tgn:1000002",
      "tgn:1000059",
      "tgn:7029392"
    ],
    "placetype": [
      "aat:300008707"
    ],
    "id": 1122658,
    "name:xx": "Chama, Río"
  }
}
