{
  "geometry": {
    "type": "Point",
    "coordinates": [
      5.7833,
      46.9167
    ]
  },
  "type": "Feature",
  "properties": {
    "hierarchy": [
      "tgn:7008644",
      "tgn:1000003",
      "tgn:7002881",
      "tgn:1000070",
      "tgn:7029392"
    ],
    "placetype": [
      "aat:300008347"
    ],
    "id": 7008644,
    "name:xx": "Arbois"
  }
}
