{
  "geometry": {
    "type": "Point",
    "coordinates": [
      32.396551,
      25.303386
    ]
  },
  "type": "Feature",
  "properties": {
    "hierarchy": [
      "tgn:7523709",
      "tgn:7001242",
      "tgn:7016833",
      "tgn:7001334",
      "tgn:7029392"
    ],
    "placetype": [
      "aat:300008795"
    ],
    "name:en": "Al Ḩumrah ash Shāmikhah",
    "id": 7523709
  }
}
