{
  "geometry": {
    "type": "Point",
    "coordinates": [
      -91.0667,
      39.2667
    ]
  },
  "type": "Feature",
  "properties": {
    "hierarchy": [
      "tgn:2204412",
      "tgn:1000001",
      "tgn:7012149",
      "tgn:1002787",
      "tgn:7007523",
      "tgn:7029392"
    ],
    "placetype": [
      "aat:300008706"
    ],
    "id": 2204412,
    "name:xx": "Buffalo Creek"
  }
}
