{
  "geometry": {
    "type": "Point",
    "coordinates": [
      -78.2667,
      38.75
    ]
  },
  "type": "Feature",
  "properties": {
    "hierarchy": [
      "tgn:2584638",
      "tgn:1000001",
      "tgn:7012149",
      "tgn:2002184",
      "tgn:7007919",
      "tgn:7029392"
    ],
    "placetype": [
      "aat:300008707"
    ],
    "id": 2584638,
    "name:xx": "Piney River"
  }
}
