{
  "geometry": {
    "type": "Point",
    "coordinates": [
      -82.4667,
      38.9667
    ]
  },
  "type": "Feature",
  "properties": {
    "hierarchy": [
      "tgn:2443164",
      "tgn:1000001",
      "tgn:7012149",
      "tgn:7007706",
      "tgn:7029392"
    ],
    "placetype": [
      "aat:300008699"
    ],
    "id": 2443164,
    "name:xx": "Kyger Run"
  }
}
