{
  "type": "FeatureCollection",
  "features": [
    {
      "geometry": {
        "type": "Point",
        "coordinates": [
          -111.2,
          38.1
        ]
      },
      "type": "Feature",
      "properties": {
        "hierarchy": [
          "tgn:2605800",
          "tgn:1000001",
          "tgn:2002109",
          "tgn:7012149",
          "tgn:7007827",
          "tgn:7029392"
        ],
        "placetype": [
          "aat:300008761"
        ],
        "id": 2605800,
        "name:xx": "Rainbow Draw"
      }
    },
    {
      "geometry": {
        "type": "Point",
        "coordinates": [
          -122.7,
          45.4167
        ]
      },
      "type": "Feature",
      "properties": {
        "hierarchy": [
          "tgn:2605801",
          "tgn:1000001",
          "tgn:1002270",
          "tgn:7012149",
          "tgn:7007708",
          "tgn:7029392"
        ],
        "placetype": [
          "aat:300006191"
        ],
        "id": 2605801,
        "name:xx": "Rainbow End Lake"
      }
    },
    {
      "geometry": {
        "type": "Point",
        "coordinates": [
          -115.6,
          33.85
        ]
      },
      "type": "Feature",
      "properties": {
        "hierarchy": [
          "tgn:2605802",
          "tgn:1000001",
          "tgn:7012149",
          "tgn:7007157",
          "tgn:1002828",
          "tgn:7029392"
        ],
        "placetype": [
          "aat:300000390"
        ],
        "id": 2605802,
        "name:xx": "Rainbow End Mine"
      }
    },
    {
      "geometry": {
        "type": "Point",
        "coordinates": [
          -110.7833,
          32.6
        ]
      },
      "type": "Feature",
      "properties": {
        "hierarchy": [
          "tgn:2605803",
          "tgn:1000001",
          "tgn:7006451",
          "tgn:7012149",
          "tgn:2000101",
          "tgn:7029392"
        ],
        "placetype": [
          "aat:300008699"
        ],
        "id": 2605803,
        "name:xx": "Rainbow End Wash"
      }
    },
    {
      "geometry": {
        "type": "Point",
        "coordinates": [
          -78.7667,
          35.7833
        ]
      },
      "type": "Feature",
      "properties": {
        "hierarchy": [
          "tgn:2605804",
          "tgn:1000001",
          "tgn:7012149",
          "tgn:2001548",
          "tgn:7007709",
          "tgn:7029392"
        ],
        "placetype": [
          "aat:300008347"
        ],
        "id": 2605804,
        "name:xx": "Rainbow Estates"
      }
    },
    {
      "geometry": {
        "type": "Point",
        "coordinates": [
          -120.8333,
          39.45
        ]
      },
      "type": "Feature",
      "properties": {
        "hierarchy": [
          "tgn:2605805",
          "tgn:1000001",
          "tgn:7012149",
          "tgn:7007157",
          "tgn:1002894",
          "tgn:7029392"
        ],
        "placetype": [
          "aat:300000390"
        ],
        "id": 2605805,
        "name:xx": "Rainbow Extension Mine"
      }
    },
    {
      "geometry": {
        "type": "Point",
        "coordinates": [
          -82.4333,
          29.1
        ]
      },
      "type": "Feature",
      "properties": {
        "hierarchy": [
          "tgn:2605806",
          "tgn:1000001",
          "tgn:7012149",
          "tgn:1002631",
          "tgn:7007240",
          "tgn:7029392"
        ],
        "placetype": [
          "aat:300008347"
        ],
        "id": 2605806,
        "name:xx": "Rainbow Falls"
      }
    },
    {
      "geometry": {
        "type": "Point",
        "coordinates": [
          -81.8667,
          33.5667
        ]
      },
      "type": "Feature",
      "properties": {
        "hierarchy": [
          "tgn:2605807",
          "tgn:2001726",
          "tgn:1000001",
          "tgn:7012149",
          "tgn:7007712",
          "tgn:7029392"
        ],
        "placetype": [
          "aat:300008347"
        ],
        "id": 2605807,
        "name:xx": "Rainbow Falls"
      }
    },
    {
      "geometry": {
        "type": "Point",
        "coordinates": [
          -80.4,
          33.9
        ]
      },
      "type": "Feature",
      "properties": {
        "hierarchy": [
          "tgn:2605808",
          "tgn:1000001",
          "tgn:7012149",
          "tgn:2001767",
          "tgn:7007712",
          "tgn:7029392"
        ],
        "placetype": [
          "aat:300008347"
        ],
        "id": 2605808,
        "name:xx": "Rainbow Falls"
      }
    }
  ]
}
