{
  "geometry": {
    "type": "Point",
    "coordinates": [
      -91.35,
      29.9333
    ]
  },
  "type": "Feature",
  "properties": {
    "hierarchy": [
      "tgn:2759009",
      "tgn:1000001",
      "tgn:7012149",
      "tgn:2000903",
      "tgn:7007256",
      "tgn:7029392"
    ],
    "placetype": [
      "aat:300008699"
    ],
    "id": 2759009,
    "name:xx": "West Fork Bayou Long"
  }
}
