{
  "geometry": {
    "type": "Point",
    "coordinates": [
      -81.3333,
      40.8167
    ]
  },
  "type": "Feature",
  "properties": {
    "hierarchy": [
      "tgn:2081437",
      "tgn:1000001",
      "tgn:7012149",
      "tgn:1002917",
      "tgn:7007706",
      "tgn:7029392"
    ],
    "placetype": [
      "aat:300008347",
      "aat:300387210"
    ],
    "id": 2081437,
    "name:xx": "Pleasant View"
  }
}
