{
  "geometry": {
    "type": "Point",
    "coordinates": [
      -106.2167,
      38.4167
    ]
  },
  "type": "Feature",
  "properties": {
    "hierarchy": [
      "tgn:2453532",
      "tgn:1000001",
      "tgn:2000199",
      "tgn:7012149",
      "tgn:7007158",
      "tgn:7029392"
    ],
    "placetype": [
      "aat:300008706"
    ],
    "id": 2453532,
    "name:xx": "Little Cochetopa Creek"
  }
}
