{
  "geometry": {
    "type": "Point",
    "coordinates": [
      74.833333,
      32.616667
    ]
  },
  "type": "Feature",
  "properties": {
    "hierarchy": [
      "tgn:7555159",
      "tgn:1000004",
      "tgn:7000198",
      "tgn:7000799",
      "tgn:7029392"
    ],
    "placetype": [
      "aat:300007783"
    ],
    "name:en": "Mirān Sāhib",
    "id": 7555159
  }
}
