{
  "geometry": {
    "type": "Point",
    "coordinates": [
      -98.8667,
      30.4833
    ]
  },
  "type": "Feature",
  "properties": {
    "hierarchy": [
      "tgn:7022673",
      "tgn:1000001",
      "tgn:7012149",
      "tgn:7007826",
      "tgn:7029392"
    ],
    "placetype": [
      "aat:300008706"
    ],
    "id": 7022673,
    "name:xx": "Walnut Spring Creek"
  }
}
