{
  "geometry": {
    "type": "Point",
    "coordinates": [
      -85.7333,
      44.7167
    ]
  },
  "type": "Feature",
  "properties": {
    "hierarchy": [
      "tgn:2579743",
      "tgn:1000001",
      "tgn:7012149",
      "tgn:2000961",
      "tgn:7007520",
      "tgn:7029392"
    ],
    "placetype": [
      "aat:300008791"
    ],
    "id": 2579743,
    "name:xx": "Picnic Island"
  }
}
