{
  "geometry": {
    "type": "Point",
    "coordinates": [
      -77.6667,
      39.0667
    ]
  },
  "type": "Feature",
  "properties": {
    "hierarchy": [
      "tgn:2438618",
      "tgn:1000001",
      "tgn:7012149",
      "tgn:7015770",
      "tgn:7007919",
      "tgn:7029392"
    ],
    "placetype": [
      "aat:300006191"
    ],
    "id": 2438618,
    "name:xx": "Kingsley Lake"
  }
}
