{
  "geometry": {
    "type": "Point",
    "coordinates": [
      -82.3667,
      35.8167
    ]
  },
  "type": "Feature",
  "properties": {
    "hierarchy": [
      "tgn:2491020",
      "tgn:1000001",
      "tgn:7012149",
      "tgn:2001556",
      "tgn:7007709",
      "tgn:7029392"
    ],
    "placetype": [
      "aat:300008699"
    ],
    "id": 2491020,
    "name:xx": "Manuel Branch"
  }
}
