{
  "geometry": {
    "type": "Point",
    "coordinates": [
      -138.4667,
      58.2667
    ]
  },
  "type": "Feature",
  "properties": {
    "hierarchy": [
      "tgn:2321777",
      "tgn:7006450",
      "tgn:1000001",
      "tgn:7012149",
      "tgn:7019760",
      "tgn:7029392"
    ],
    "placetype": [
      "aat:300132348"
    ],
    "id": 2321777,
    "name:xx": "Fairweather Ground"
  }
}
