{
  "geometry": {
    "type": "Point",
    "coordinates": [
      -82.85,
      37.9333
    ]
  },
  "type": "Feature",
  "properties": {
    "hierarchy": [
      "tgn:2042004",
      "tgn:1000001",
      "tgn:7012149",
      "tgn:2000804",
      "tgn:7007255",
      "tgn:7029392"
    ],
    "placetype": [
      "aat:300008347",
      "aat:300387210"
    ],
    "id": 2042004,
    "name:xx": "Winifred"
  }
}
