{
  "geometry": {
    "type": "Point",
    "coordinates": [
      -91.3167,
      37.8167
    ]
  },
  "type": "Feature",
  "properties": {
    "hierarchy": [
      "tgn:2146143",
      "tgn:1000001",
      "tgn:7012149",
      "tgn:2001190",
      "tgn:7007523",
      "tgn:7029392"
    ],
    "placetype": [
      "aat:300006191"
    ],
    "id": 2146143,
    "name:xx": "Ballard Lake Section 14"
  }
}
