{
  "type": "FeatureCollection",
  "features": [
    {
      "geometry": {
        "type": "Point",
        "coordinates": [
          1.366667,
          51.35
        ]
      },
      "type": "Feature",
      "properties": {
        "hierarchy": [
          "tgn:7457500",
          "tgn:7002445",
          "tgn:1000003",
          "tgn:7008153",
          "tgn:7008591",
          "tgn:7029392"
        ],
        "placetype": [
          "aat:300008347"
        ],
        "name:en": "Manston",
        "id": 7457500
      }
    },
    {
      "geometry": {
        "type": "Point",
        "coordinates": [
          -4.3,
          55.816667
        ]
      },
      "type": "Feature",
      "properties": {
        "hierarchy": [
          "tgn:7457504",
          "tgn:7002444",
          "tgn:1000003",
          "tgn:7019097",
          "tgn:7008591",
          "tgn:7029392"
        ],
        "placetype": [
          "aat:300000745"
        ],
        "name:en": "Mansewood",
        "id": 7457504
      }
    },
    {
      "geometry": {
        "type": "Point",
        "coordinates": [
          -2.9,
          58.8
        ]
      },
      "type": "Feature",
      "properties": {
        "hierarchy": [
          "tgn:7457506",
          "tgn:7002444",
          "tgn:1000003",
          "tgn:7009907",
          "tgn:7008591",
          "tgn:7029392"
        ],
        "placetype": [
          "aat:300132316"
        ],
        "name:en": "Manse Bay",
        "id": 7457506
      }
    },
    {
      "geometry": {
        "type": "Point",
        "coordinates": [
          -3.233333,
          55.633333
        ]
      },
      "type": "Feature",
      "properties": {
        "hierarchy": [
          "tgn:7457507",
          "tgn:7002444",
          "tgn:1000003",
          "tgn:7008072",
          "tgn:7008591",
          "tgn:7029392"
        ],
        "placetype": [
          "aat:300008699"
        ],
        "name:en": "Manor Water",
        "id": 7457507
      }
    },
    {
      "geometry": {
        "type": "Point",
        "coordinates": [
          -5.0075,
          51.988333
        ]
      },
      "type": "Feature",
      "properties": {
        "hierarchy": [
          "tgn:7457508",
          "tgn:7002443",
          "tgn:1000003",
          "tgn:7018993",
          "tgn:7008591",
          "tgn:7029392"
        ],
        "placetype": [
          "aat:300008347"
        ],
        "name:en": "Manorowen",
        "id": 7457508
      }
    },
    {
      "geometry": {
        "type": "Point",
        "coordinates": [
          -4.583333,
          52.05
        ]
      },
      "type": "Feature",
      "properties": {
        "hierarchy": [
          "tgn:7457509",
          "tgn:7002443",
          "tgn:1000003",
          "tgn:7018993",
          "tgn:7008591",
          "tgn:7029392"
        ],
        "placetype": [
          "aat:300008347"
        ],
        "name:en": "Manordeifi",
        "id": 7457509
      }
    }
  ]
}
