{
  "type": "FeatureCollection",
  "features": [
    {
      "geometry": {
        "type": "Point",
        "coordinates": [
          -115.5,
          46.1667
        ]
      },
      "type": "Feature",
      "properties": {
        "hierarchy": [
          "tgn:7020940",
          "tgn:1000001",
          "tgn:7012149",
          "tgn:2000476",
          "tgn:7007250",
          "tgn:7029392"
        ],
        "placetype": [
          "aat:300008706"
        ],
        "id": 7020940,
        "name:xx": "Handy Creek"
      }
    },
    {
      "geometry": {
        "type": "Point",
        "coordinates": [
          -115.7,
          45.7333
        ]
      },
      "type": "Feature",
      "properties": {
        "hierarchy": [
          "tgn:7020941",
          "tgn:1000001",
          "tgn:7012149",
          "tgn:2000476",
          "tgn:7007250",
          "tgn:7029392"
        ],
        "placetype": [
          "aat:300008706"
        ],
        "id": 7020941,
        "name:xx": "Mackey Creek"
      }
    },
    {
      "geometry": {
        "type": "Point",
        "coordinates": [
          -115.2,
          45.5
        ]
      },
      "type": "Feature",
      "properties": {
        "hierarchy": [
          "tgn:7020942",
          "tgn:1000001",
          "tgn:7012149",
          "tgn:2000476",
          "tgn:7007250",
          "tgn:7029392"
        ],
        "placetype": [
          "aat:300008706"
        ],
        "id": 7020942,
        "name:xx": "Magpie Creek"
      }
    },
    {
      "geometry": {
        "type": "Point",
        "coordinates": [
          -114.4,
          46.4667
        ]
      },
      "type": "Feature",
      "properties": {
        "hierarchy": [
          "tgn:7020943",
          "tgn:1000001",
          "tgn:7012149",
          "tgn:2000476",
          "tgn:7007250",
          "tgn:7029392"
        ],
        "placetype": [
          "aat:300008680"
        ],
        "id": 7020943,
        "name:xx": "Maud Lake"
      }
    },
    {
      "geometry": {
        "type": "Point",
        "coordinates": [
          -116.4,
          45.9667
        ]
      },
      "type": "Feature",
      "properties": {
        "hierarchy": [
          "tgn:7020944",
          "tgn:1000001",
          "tgn:7012149",
          "tgn:2000476",
          "tgn:7007250",
          "tgn:7029392"
        ],
        "placetype": [
          "aat:300008706"
        ],
        "id": 7020944,
        "name:xx": "Packers Creek"
      }
    },
    {
      "geometry": {
        "type": "Point",
        "coordinates": [
          -116.1,
          45.3333
        ]
      },
      "type": "Feature",
      "properties": {
        "hierarchy": [
          "tgn:7020945",
          "tgn:1000001",
          "tgn:7012149",
          "tgn:2000476",
          "tgn:7007250",
          "tgn:7029392"
        ],
        "placetype": [
          "aat:300008706"
        ],
        "id": 7020945,
        "name:xx": "Sands Creek"
      }
    },
    {
      "geometry": {
        "type": "Point",
        "coordinates": [
          -116.5833,
          47.7333
        ]
      },
      "type": "Feature",
      "properties": {
        "hierarchy": [
          "tgn:7020946",
          "tgn:1000001",
          "tgn:7012149",
          "tgn:2000479",
          "tgn:7007250",
          "tgn:7029392"
        ],
        "placetype": [
          "aat:300008798"
        ],
        "id": 7020946,
        "name:xx": "Huckleberry Mountain"
      }
    },
    {
      "geometry": {
        "type": "Point",
        "coordinates": [
          -88.9333,
          31.2333
        ]
      },
      "type": "Feature",
      "properties": {
        "hierarchy": [
          "tgn:7020947",
          "tgn:1000001",
          "tgn:7012149",
          "tgn:2001141",
          "tgn:7007522",
          "tgn:7029392"
        ],
        "placetype": [
          "aat:300006191"
        ],
        "id": 7020947,
        "name:xx": "Crane Lake"
      }
    },
    {
      "geometry": {
        "type": "Point",
        "coordinates": [
          -116.5167,
          47.85
        ]
      },
      "type": "Feature",
      "properties": {
        "hierarchy": [
          "tgn:7020948",
          "tgn:1000001",
          "tgn:7012149",
          "tgn:2000479",
          "tgn:7007250",
          "tgn:7029392"
        ],
        "placetype": [
          "aat:300008706"
        ],
        "id": 7020948,
        "name:xx": "Lewelling Creek"
      }
    },
    {
      "geometry": {
        "type": "Point",
        "coordinates": [
          -114.3333,
          45.1167
        ]
      },
      "type": "Feature",
      "properties": {
        "hierarchy": [
          "tgn:7020949",
          "tgn:1000001",
          "tgn:7012149",
          "tgn:2000481",
          "tgn:7007250",
          "tgn:7029392"
        ],
        "placetype": [
          "aat:300000390"
        ],
        "id": 7020949,
        "name:xx": "Blackbird Mines"
      }
    }
  ]
}
