{
  "geometry": {
    "type": "Point",
    "coordinates": [
      -93.4833,
      38.7667
    ]
  },
  "type": "Feature",
  "properties": {
    "hierarchy": [
      "tgn:2678144",
      "tgn:1000001",
      "tgn:7012149",
      "tgn:7007523",
      "tgn:7029392"
    ],
    "placetype": [
      "aat:300008707"
    ],
    "id": 2678144,
    "name:xx": "South Fork Blackwater River"
  }
}
