{
  "type": "FeatureCollection",
  "features": [
    {
      "geometry": {
        "type": "Point",
        "coordinates": [
          -118.7,
          37.5167
        ]
      },
      "type": "Feature",
      "properties": {
        "hierarchy": [
          "tgn:2641130",
          "tgn:1000001",
          "tgn:7012149",
          "tgn:7007157",
          "tgn:1002675",
          "tgn:7029392"
        ],
        "placetype": [
          "aat:300008761"
        ],
        "id": 2641130,
        "name:xx": "Sand Canyon"
      }
    },
    {
      "geometry": {
        "type": "Point",
        "coordinates": [
          -117.0833,
          34.0333
        ]
      },
      "type": "Feature",
      "properties": {
        "hierarchy": [
          "tgn:2641131",
          "tgn:1000001",
          "tgn:7012149",
          "tgn:7007157",
          "tgn:1002857",
          "tgn:7029392"
        ],
        "placetype": [
          "aat:300008761"
        ],
        "id": 2641131,
        "name:xx": "Sand Canyon"
      }
    },
    {
      "geometry": {
        "type": "Point",
        "coordinates": [
          -118.5167,
          34.7
        ]
      },
      "type": "Feature",
      "properties": {
        "hierarchy": [
          "tgn:2641132",
          "tgn:1000001",
          "tgn:7012149",
          "tgn:7007157",
          "tgn:1002608",
          "tgn:7029392"
        ],
        "placetype": [
          "aat:300008761"
        ],
        "id": 2641132,
        "name:xx": "Sand Canyon"
      }
    },
    {
      "geometry": {
        "type": "Point",
        "coordinates": [
          -118.9167,
          35.65
        ]
      },
      "type": "Feature",
      "properties": {
        "hierarchy": [
          "tgn:2641133",
          "tgn:1000001",
          "tgn:7012149",
          "tgn:1002545",
          "tgn:7007157",
          "tgn:7029392"
        ],
        "placetype": [
          "aat:300008761"
        ],
        "id": 2641133,
        "name:xx": "Sand Canyon"
      }
    },
    {
      "geometry": {
        "type": "Point",
        "coordinates": [
          -118,
          35.7833
        ]
      },
      "type": "Feature",
      "properties": {
        "hierarchy": [
          "tgn:2641134",
          "tgn:1000001",
          "tgn:7012149",
          "tgn:7007157",
          "tgn:7029392"
        ],
        "placetype": [
          "aat:300008761"
        ],
        "id": 2641134,
        "name:xx": "Sand Canyon"
      }
    },
    {
      "geometry": {
        "type": "Point",
        "coordinates": [
          -109.0167,
          40.4667
        ]
      },
      "type": "Feature",
      "properties": {
        "hierarchy": [
          "tgn:2641135",
          "tgn:1000001",
          "tgn:7012149",
          "tgn:2000232",
          "tgn:7007158",
          "tgn:7029392"
        ],
        "placetype": [
          "aat:300008761"
        ],
        "id": 2641135,
        "name:xx": "Sand Canyon"
      }
    },
    {
      "geometry": {
        "type": "Point",
        "coordinates": [
          -103.4667,
          40.9833
        ]
      },
      "type": "Feature",
      "properties": {
        "hierarchy": [
          "tgn:2641136",
          "tgn:1000001",
          "tgn:7012149",
          "tgn:2000229",
          "tgn:7007158",
          "tgn:7029392"
        ],
        "placetype": [
          "aat:300008761"
        ],
        "id": 2641136,
        "name:xx": "Sand Canyon"
      }
    },
    {
      "geometry": {
        "type": "Point",
        "coordinates": [
          -108.75,
          37.3833
        ]
      },
      "type": "Feature",
      "properties": {
        "hierarchy": [
          "tgn:2641137",
          "tgn:1000001",
          "tgn:7012149",
          "tgn:2000233",
          "tgn:7007158",
          "tgn:7029392"
        ],
        "placetype": [
          "aat:300008761"
        ],
        "id": 2641137,
        "name:xx": "Sand Canyon"
      }
    },
    {
      "geometry": {
        "type": "Point",
        "coordinates": [
          -104.3667,
          40.1833
        ]
      },
      "type": "Feature",
      "properties": {
        "hierarchy": [
          "tgn:2641138",
          "tgn:1000001",
          "tgn:7012149",
          "tgn:7007158",
          "tgn:2000253",
          "tgn:7029392"
        ],
        "placetype": [
          "aat:300008761"
        ],
        "id": 2641138,
        "name:xx": "Sand Canyon"
      }
    },
    {
      "geometry": {
        "type": "Point",
        "coordinates": [
          -104.8167,
          38.6333
        ]
      },
      "type": "Feature",
      "properties": {
        "hierarchy": [
          "tgn:2641139",
          "tgn:1000001",
          "tgn:7012149",
          "tgn:7014097",
          "tgn:7007158",
          "tgn:7029392"
        ],
        "placetype": [
          "aat:300008761"
        ],
        "id": 2641139,
        "name:xx": "Sand Canyon"
      }
    }
  ]
}
