{
  "geometry": {
    "type": "Point",
    "coordinates": [
      114.3833,
      -7.9333
    ]
  },
  "type": "Feature",
  "properties": {
    "hierarchy": [
      "tgn:1077396",
      "tgn:1000004",
      "tgn:1001323",
      "tgn:1000116",
      "tgn:7029392"
    ],
    "placetype": [
      "aat:300008347"
    ],
    "id": 1077396,
    "name:xx": "Bajulmati"
  }
}
