{
  "type": "FeatureCollection",
  "features": [
    {
      "geometry": {
        "type": "Point",
        "coordinates": [
          -100.133333,
          25.1
        ]
      },
      "type": "Feature",
      "properties": {
        "hierarchy": [
          "tgn:7391870",
          "tgn:1000001",
          "tgn:7005589",
          "tgn:7005560",
          "tgn:7029392"
        ],
        "placetype": [
          "aat:300008347"
        ],
        "id": 7391870,
        "name:xx": "Rancho El Carrillo"
      }
    },
    {
      "geometry": {
        "type": "Point",
        "coordinates": [
          -99.066667,
          24.316667
        ]
      },
      "type": "Feature",
      "properties": {
        "hierarchy": [
          "tgn:7391871",
          "tgn:1000001",
          "tgn:7005597",
          "tgn:7005560",
          "tgn:7029392"
        ],
        "placetype": [
          "aat:300008347"
        ],
        "id": 7391871,
        "name:xx": "Rancho El Carricito"
      }
    },
    {
      "geometry": {
        "type": "Point",
        "coordinates": [
          -104.266667,
          26.533333
        ]
      },
      "type": "Feature",
      "properties": {
        "hierarchy": [
          "tgn:7391872",
          "tgn:7005583",
          "tgn:1000001",
          "tgn:7005560",
          "tgn:7029392"
        ],
        "placetype": [
          "aat:300008347"
        ],
        "id": 7391872,
        "name:xx": "Rancho El Carmen"
      }
    },
    {
      "geometry": {
        "type": "Point",
        "coordinates": [
          -116.4,
          32.483333
        ]
      },
      "type": "Feature",
      "properties": {
        "hierarchy": [
          "tgn:7391873",
          "tgn:1001835",
          "tgn:1000001",
          "tgn:7005560",
          "tgn:7029392"
        ],
        "placetype": [
          "aat:300000241"
        ],
        "id": 7391873,
        "name:xx": "Rancho Rosas"
      }
    },
    {
      "geometry": {
        "type": "Point",
        "coordinates": [
          -106.383333,
          28.366667
        ]
      },
      "type": "Feature",
      "properties": {
        "hierarchy": [
          "tgn:7391874",
          "tgn:7005581",
          "tgn:1000001",
          "tgn:7005560",
          "tgn:7029392"
        ],
        "placetype": [
          "aat:300008347"
        ],
        "id": 7391874,
        "name:xx": "Rosas"
      }
    },
    {
      "geometry": {
        "type": "Point",
        "coordinates": [
          -105.6,
          26.733333
        ]
      },
      "type": "Feature",
      "properties": {
        "hierarchy": [
          "tgn:7391875",
          "tgn:7005581",
          "tgn:1000001",
          "tgn:7005560",
          "tgn:7029392"
        ],
        "placetype": [
          "aat:300008347"
        ],
        "id": 7391875,
        "name:xx": "Rosas"
      }
    },
    {
      "geometry": {
        "type": "Point",
        "coordinates": [
          -100.183333,
          17.7
        ]
      },
      "type": "Feature",
      "properties": {
        "hierarchy": [
          "tgn:7391877",
          "tgn:7005585",
          "tgn:1000001",
          "tgn:7005560",
          "tgn:7029392"
        ],
        "placetype": [
          "aat:300008347"
        ],
        "id": 7391877,
        "name:xx": "Rosas"
      }
    },
    {
      "geometry": {
        "type": "Point",
        "coordinates": [
          -114.166667,
          28.566667
        ]
      },
      "type": "Feature",
      "properties": {
        "hierarchy": [
          "tgn:7391878",
          "tgn:1001835",
          "tgn:1000001",
          "tgn:7005560",
          "tgn:7029392"
        ],
        "placetype": [
          "aat:300386846"
        ],
        "id": 7391878,
        "name:xx": "Rosarito, Punta"
      }
    }
  ]
}
