{
  "geometry": {
    "type": "Point",
    "coordinates": [
      -122.05,
      40.7667
    ]
  },
  "type": "Feature",
  "properties": {
    "hierarchy": [
      "tgn:2693347",
      "tgn:1000001",
      "tgn:7012149",
      "tgn:7007157",
      "tgn:2000188",
      "tgn:7029392"
    ],
    "placetype": [
      "aat:300008706"
    ],
    "id": 2693347,
    "name:xx": "Stein Creek"
  }
}
