{
  "geometry": {
    "type": "Point",
    "coordinates": [
      -123.3667,
      41.15
    ]
  },
  "type": "Feature",
  "properties": {
    "hierarchy": [
      "tgn:2441292",
      "tgn:1000001",
      "tgn:7012149",
      "tgn:7007157",
      "tgn:2000189",
      "tgn:7029392"
    ],
    "placetype": [
      "aat:300008680"
    ],
    "id": 2441292,
    "name:xx": "Knownothing Lake"
  }
}
