{
  "type": "FeatureCollection",
  "features": [
    {
      "geometry": {
        "type": "Point",
        "coordinates": [
          -82,
          27.0833
        ]
      },
      "type": "Feature",
      "properties": {
        "hierarchy": [
          "tgn:2020923",
          "tgn:1000001",
          "tgn:7021603",
          "tgn:7012149",
          "tgn:7007240",
          "tgn:7029392"
        ],
        "placetype": [
          "aat:300008347",
          "aat:300387210"
        ],
        "id": 2020923,
        "name:xx": "Platt"
      }
    },
    {
      "geometry": {
        "type": "Point",
        "coordinates": [
          -80.2,
          26.05
        ]
      },
      "type": "Feature",
      "properties": {
        "hierarchy": [
          "tgn:2020924",
          "tgn:1000001",
          "tgn:1002207",
          "tgn:7012149",
          "tgn:7007240",
          "tgn:7029392"
        ],
        "placetype": [
          "aat:300008347"
        ],
        "id": 2020924,
        "name:xx": "Playland Isles"
      }
    },
    {
      "geometry": {
        "type": "Point",
        "coordinates": [
          -86.35,
          30.9667
        ]
      },
      "type": "Feature",
      "properties": {
        "hierarchy": [
          "tgn:2020925",
          "tgn:1000001",
          "tgn:7012149",
          "tgn:2000290",
          "tgn:7007240",
          "tgn:7029392"
        ],
        "placetype": [
          "aat:300008347"
        ],
        "id": 2020925,
        "name:xx": "Pleasant Grove"
      }
    },
    {
      "geometry": {
        "type": "Point",
        "coordinates": [
          -87.3333,
          30.35
        ]
      },
      "type": "Feature",
      "properties": {
        "hierarchy": [
          "tgn:2020926",
          "tgn:1000001",
          "tgn:2000265",
          "tgn:7012149",
          "tgn:7007240",
          "tgn:7029392"
        ],
        "placetype": [
          "aat:300008347"
        ],
        "id": 2020926,
        "name:xx": "Pleasant Grove"
      }
    },
    {
      "geometry": {
        "type": "Point",
        "coordinates": [
          -86.1667,
          30.6833
        ]
      },
      "type": "Feature",
      "properties": {
        "hierarchy": [
          "tgn:2020927",
          "tgn:1000001",
          "tgn:7012149",
          "tgn:2000290",
          "tgn:7007240",
          "tgn:7029392"
        ],
        "placetype": [
          "aat:300008347"
        ],
        "id": 2020927,
        "name:xx": "Pleasant Ridge"
      }
    },
    {
      "geometry": {
        "type": "Point",
        "coordinates": [
          -81.5333,
          28.6833
        ]
      },
      "type": "Feature",
      "properties": {
        "hierarchy": [
          "tgn:2020928",
          "tgn:1000001",
          "tgn:7012149",
          "tgn:1002749",
          "tgn:7007240",
          "tgn:7029392"
        ],
        "placetype": [
          "aat:300008347"
        ],
        "id": 2020928,
        "name:xx": "Plymouth"
      }
    }
  ]
}
