{
  "geometry": {
    "type": "Point",
    "coordinates": [
      41.4333,
      51.45
    ]
  },
  "type": "Feature",
  "properties": {
    "hierarchy": [
      "tgn:1137387",
      "tgn:1000004",
      "tgn:1003424",
      "tgn:7018214",
      "tgn:7002435",
      "tgn:7029392"
    ],
    "placetype": [
      "aat:300008347"
    ],
    "id": 1137387,
    "name:xx": "Dubovka"
  }
}
