{
  "type": "FeatureCollection",
  "features": [
    {
      "geometry": {
        "type": "Point",
        "coordinates": [
          10.133333,
          51.75
        ]
      },
      "type": "Feature",
      "properties": {
        "hierarchy": [
          "tgn:7082990",
          "tgn:1000003",
          "tgn:7003676",
          "tgn:7000084",
          "tgn:7029392"
        ],
        "placetype": [
          "aat:300008863"
        ],
        "id": 7082990,
        "name:xx": "Westerhof, Forst"
      }
    },
    {
      "geometry": {
        "type": "Point",
        "coordinates": [
          9.916667,
          53.4
        ]
      },
      "type": "Feature",
      "properties": {
        "hierarchy": [
          "tgn:7082991",
          "tgn:1000003",
          "tgn:7003676",
          "tgn:7000084",
          "tgn:7029392"
        ],
        "placetype": [
          "aat:300008347"
        ],
        "id": 7082991,
        "name:xx": "Westerhof"
      }
    },
    {
      "geometry": {
        "type": "Point",
        "coordinates": [
          10.116667,
          51.766667
        ]
      },
      "type": "Feature",
      "properties": {
        "hierarchy": [
          "tgn:7082992",
          "tgn:1000003",
          "tgn:7003676",
          "tgn:7000084",
          "tgn:7029392"
        ],
        "placetype": [
          "aat:300008347"
        ],
        "id": 7082992,
        "name:xx": "Westerhof"
      }
    },
    {
      "geometry": {
        "type": "Point",
        "coordinates": [
          8.9,
          54.883333
        ]
      },
      "type": "Feature",
      "properties": {
        "hierarchy": [
          "tgn:7082993",
          "tgn:1000003",
          "tgn:7003688",
          "tgn:7000084",
          "tgn:7029392"
        ],
        "placetype": [
          "aat:300000206"
        ],
        "id": 7082993,
        "name:xx": "Westerhof"
      }
    },
    {
      "geometry": {
        "type": "Point",
        "coordinates": [
          8.766667,
          54.766667
        ]
      },
      "type": "Feature",
      "properties": {
        "hierarchy": [
          "tgn:7082994",
          "tgn:1000003",
          "tgn:7003688",
          "tgn:7000084",
          "tgn:7029392"
        ],
        "placetype": [
          "aat:300000206"
        ],
        "id": 7082994,
        "name:xx": "Westerhof"
      }
    },
    {
      "geometry": {
        "type": "Point",
        "coordinates": [
          8.7,
          54.4
        ]
      },
      "type": "Feature",
      "properties": {
        "hierarchy": [
          "tgn:7082995",
          "tgn:1000003",
          "tgn:7003688",
          "tgn:7000084",
          "tgn:7029392"
        ],
        "placetype": [
          "aat:300000206"
        ],
        "id": 7082995,
        "name:xx": "Westerhof"
      }
    },
    {
      "geometry": {
        "type": "Point",
        "coordinates": [
          8.716667,
          54.3
        ]
      },
      "type": "Feature",
      "properties": {
        "hierarchy": [
          "tgn:7082996",
          "tgn:1000003",
          "tgn:7003688",
          "tgn:7000084",
          "tgn:7029392"
        ],
        "placetype": [
          "aat:300000206"
        ],
        "id": 7082996,
        "name:xx": "Westerhof"
      }
    },
    {
      "geometry": {
        "type": "Point",
        "coordinates": [
          10.766667,
          47.766667
        ]
      },
      "type": "Feature",
      "properties": {
        "hierarchy": [
          "tgn:7082997",
          "tgn:7003669",
          "tgn:1000003",
          "tgn:7000084",
          "tgn:7029392"
        ],
        "placetype": [
          "aat:300000206"
        ],
        "id": 7082997,
        "name:xx": "Westerhof"
      }
    },
    {
      "geometry": {
        "type": "Point",
        "coordinates": [
          11.766667,
          47.716667
        ]
      },
      "type": "Feature",
      "properties": {
        "hierarchy": [
          "tgn:7082998",
          "tgn:7003669",
          "tgn:1000003",
          "tgn:7000084",
          "tgn:7029392"
        ],
        "placetype": [
          "aat:300000206"
        ],
        "id": 7082998,
        "name:xx": "Westerhof"
      }
    },
    {
      "geometry": {
        "type": "Point",
        "coordinates": [
          8.633333,
          54.383333
        ]
      },
      "type": "Feature",
      "properties": {
        "hierarchy": [
          "tgn:7082999",
          "tgn:1000003",
          "tgn:7003688",
          "tgn:7000084",
          "tgn:7029392"
        ],
        "placetype": [
          "aat:300386885"
        ],
        "id": 7082999,
        "name:xx": "Westerhever Sand"
      }
    }
  ]
}
