{
  "geometry": {
    "type": "Point",
    "coordinates": [
      -97.15,
      33.9667
    ]
  },
  "type": "Feature",
  "properties": {
    "hierarchy": [
      "tgn:2659235",
      "tgn:1000001",
      "tgn:7012149",
      "tgn:2001665",
      "tgn:7007707",
      "tgn:7029392"
    ],
    "placetype": [
      "aat:300008706"
    ],
    "id": 2659235,
    "name:xx": "Shiggin Creek"
  }
}
