{
  "geometry": {
    "type": "Point",
    "coordinates": [
      18.2667,
      59.65
    ]
  },
  "type": "Feature",
  "properties": {
    "hierarchy": [
      "tgn:1063191",
      "tgn:1000003",
      "tgn:7003777",
      "tgn:1000097",
      "tgn:7029392"
    ],
    "placetype": [
      "aat:300008347"
    ],
    "id": 1063191,
    "name:xx": "Kårsta"
  }
}
