{
  "geometry": {
    "type": "Point",
    "coordinates": [
      -88.7167,
      45.3333
    ]
  },
  "type": "Feature",
  "properties": {
    "hierarchy": [
      "tgn:2541767",
      "tgn:1000001",
      "tgn:7012149",
      "tgn:2002333",
      "tgn:7007922",
      "tgn:7029392"
    ],
    "placetype": [
      "aat:300008706"
    ],
    "id": 2541767,
    "name:xx": "Ninemile Creek"
  }
}
