{
  "type": "FeatureCollection",
  "features": [
    {
      "geometry": {
        "type": "Point",
        "coordinates": [
          -106.85,
          36.0333
        ]
      },
      "type": "Feature",
      "properties": {
        "hierarchy": [
          "tgn:2640420",
          "tgn:1000001",
          "tgn:7012149",
          "tgn:2001449",
          "tgn:7007566",
          "tgn:7029392"
        ],
        "placetype": [
          "aat:300006191"
        ],
        "id": 2640420,
        "name:xx": "San Gregorio Reservoir"
      }
    },
    {
      "geometry": {
        "type": "Point",
        "coordinates": [
          -119.1,
          34.6833
        ]
      },
      "type": "Feature",
      "properties": {
        "hierarchy": [
          "tgn:2640421",
          "tgn:1000001",
          "tgn:7012149",
          "tgn:7007157",
          "tgn:1002972",
          "tgn:7029392"
        ],
        "placetype": [
          "aat:300008706"
        ],
        "id": 2640421,
        "name:xx": "San Guillermo Creek"
      }
    },
    {
      "geometry": {
        "type": "Point",
        "coordinates": [
          -119.1333,
          34.6833
        ]
      },
      "type": "Feature",
      "properties": {
        "hierarchy": [
          "tgn:2640422",
          "tgn:1000001",
          "tgn:7012149",
          "tgn:7007157",
          "tgn:1002972",
          "tgn:7029392"
        ],
        "placetype": [
          "aat:300008798"
        ],
        "id": 2640422,
        "name:xx": "San Guillermo Mountain"
      }
    },
    {
      "geometry": {
        "type": "Point",
        "coordinates": [
          -99.4333,
          27.45
        ]
      },
      "type": "Feature",
      "properties": {
        "hierarchy": [
          "tgn:2640424",
          "tgn:1000001",
          "tgn:7012149",
          "tgn:2002090",
          "tgn:7007826",
          "tgn:7029392"
        ],
        "placetype": [
          "aat:300008706"
        ],
        "id": 2640424,
        "name:xx": "San Idelfonso Creek"
      }
    },
    {
      "geometry": {
        "type": "Point",
        "coordinates": [
          -98.8,
          26.6167
        ]
      },
      "type": "Feature",
      "properties": {
        "hierarchy": [
          "tgn:2640425",
          "tgn:1000001",
          "tgn:7012149",
          "tgn:2002075",
          "tgn:7007826",
          "tgn:7029392"
        ],
        "placetype": [
          "aat:300006191"
        ],
        "id": 2640425,
        "name:xx": "San Idelfonso Tank"
      }
    },
    {
      "geometry": {
        "type": "Point",
        "coordinates": [
          -116.5167,
          33.3
        ]
      },
      "type": "Feature",
      "properties": {
        "hierarchy": [
          "tgn:2640426",
          "tgn:1000001",
          "tgn:7012149",
          "tgn:7007157",
          "tgn:1002858",
          "tgn:7029392"
        ],
        "placetype": [
          "aat:300008347"
        ],
        "id": 2640426,
        "name:xx": "San Ignacio"
      }
    },
    {
      "geometry": {
        "type": "Point",
        "coordinates": [
          -104.9333,
          34.9
        ]
      },
      "type": "Feature",
      "properties": {
        "hierarchy": [
          "tgn:2640427",
          "tgn:1000001",
          "tgn:7012149",
          "tgn:2001438",
          "tgn:7007566",
          "tgn:7029392"
        ],
        "placetype": [
          "aat:300008347"
        ],
        "id": 2640427,
        "name:xx": "San Ignacio"
      }
    },
    {
      "geometry": {
        "type": "Point",
        "coordinates": [
          -108.1833,
          34.2
        ]
      },
      "type": "Feature",
      "properties": {
        "hierarchy": [
          "tgn:2640429",
          "tgn:1000001",
          "tgn:2001429",
          "tgn:7012149",
          "tgn:7007566",
          "tgn:7029392"
        ],
        "placetype": [
          "aat:300008706"
        ],
        "id": 2640429,
        "name:xx": "San Ignacio Creek"
      }
    }
  ]
}
