{
  "geometry": {
    "type": "Point",
    "coordinates": [
      30.348785,
      30.386422
    ]
  },
  "type": "Feature",
  "properties": {
    "hierarchy": [
      "tgn:7544143",
      "tgn:7001242",
      "tgn:1001075",
      "tgn:7016833",
      "tgn:7029392"
    ],
    "placetype": [
      "aat:300008347"
    ],
    "name:en": "Madīnat Wādī an Naţrūn",
    "id": 7544143
  }
}
