{
  "type": "FeatureCollection",
  "features": [
    {
      "geometry": {
        "type": "Point",
        "coordinates": [
          12.183333,
          47.75
        ]
      },
      "type": "Feature",
      "properties": {
        "hierarchy": [
          "tgn:7134770",
          "tgn:7003669",
          "tgn:1000003",
          "tgn:7000084",
          "tgn:7029392"
        ],
        "placetype": [
          "aat:300008347"
        ],
        "id": 7134770,
        "name:xx": "Muhltal"
      }
    },
    {
      "geometry": {
        "type": "Point",
        "coordinates": [
          12.65,
          48.15
        ]
      },
      "type": "Feature",
      "properties": {
        "hierarchy": [
          "tgn:7134771",
          "tgn:7003669",
          "tgn:1000003",
          "tgn:7000084",
          "tgn:7029392"
        ],
        "placetype": [
          "aat:300000206"
        ],
        "id": 7134771,
        "name:xx": "Mühlthal"
      }
    },
    {
      "geometry": {
        "type": "Point",
        "coordinates": [
          12.783333,
          48.033333
        ]
      },
      "type": "Feature",
      "properties": {
        "hierarchy": [
          "tgn:7134772",
          "tgn:7003669",
          "tgn:1000003",
          "tgn:7000084",
          "tgn:7029392"
        ],
        "placetype": [
          "aat:300000206"
        ],
        "id": 7134772,
        "name:xx": "Mühlthal"
      }
    },
    {
      "geometry": {
        "type": "Point",
        "coordinates": [
          12.633333,
          47.9
        ]
      },
      "type": "Feature",
      "properties": {
        "hierarchy": [
          "tgn:7134773",
          "tgn:7003669",
          "tgn:1000003",
          "tgn:7000084",
          "tgn:7029392"
        ],
        "placetype": [
          "aat:300000206"
        ],
        "id": 7134773,
        "name:xx": "Mühlthal"
      }
    },
    {
      "geometry": {
        "type": "Point",
        "coordinates": [
          12.716667,
          51.3
        ]
      },
      "type": "Feature",
      "properties": {
        "hierarchy": [
          "tgn:7134774",
          "tgn:1000003",
          "tgn:7003685",
          "tgn:7000084",
          "tgn:7029392"
        ],
        "placetype": [
          "aat:300008688"
        ],
        "id": 7134774,
        "name:xx": "Mühl-Teich"
      }
    },
    {
      "geometry": {
        "type": "Point",
        "coordinates": [
          14.366667,
          51.233333
        ]
      },
      "type": "Feature",
      "properties": {
        "hierarchy": [
          "tgn:7134776",
          "tgn:1000003",
          "tgn:7003685",
          "tgn:7000084",
          "tgn:7029392"
        ],
        "placetype": [
          "aat:300008688"
        ],
        "id": 7134776,
        "name:xx": "Mühl-Teich"
      }
    },
    {
      "geometry": {
        "type": "Point",
        "coordinates": [
          11.033333,
          50.266667
        ]
      },
      "type": "Feature",
      "properties": {
        "hierarchy": [
          "tgn:7134777",
          "tgn:7003669",
          "tgn:1000003",
          "tgn:7000084",
          "tgn:7029392"
        ],
        "placetype": [
          "aat:300008688"
        ],
        "id": 7134777,
        "name:xx": "Mühl-Teich"
      }
    },
    {
      "geometry": {
        "type": "Point",
        "coordinates": [
          11.233333,
          50.25
        ]
      },
      "type": "Feature",
      "properties": {
        "hierarchy": [
          "tgn:7134778",
          "tgn:7003669",
          "tgn:1000003",
          "tgn:7000084",
          "tgn:7029392"
        ],
        "placetype": [
          "aat:300008688"
        ],
        "id": 7134778,
        "name:xx": "Mühl-Teich"
      }
    },
    {
      "geometry": {
        "type": "Point",
        "coordinates": [
          11.55,
          50.95
        ]
      },
      "type": "Feature",
      "properties": {
        "hierarchy": [
          "tgn:7134779",
          "tgn:1000003",
          "tgn:7003689",
          "tgn:7000084",
          "tgn:7029392"
        ],
        "placetype": [
          "aat:300008761"
        ],
        "id": 7134779,
        "name:xx": "Mühltal"
      }
    }
  ]
}
