{
  "geometry": {
    "type": "Point",
    "coordinates": [
      -102.1833,
      46.55
    ]
  },
  "type": "Feature",
  "properties": {
    "hierarchy": [
      "tgn:2204445",
      "tgn:1000001",
      "tgn:7012149",
      "tgn:7007705",
      "tgn:7029392"
    ],
    "placetype": [
      "aat:300008706"
    ],
    "id": 2204445,
    "name:xx": "Buffalo Creek"
  }
}
