{
  "geometry": {
    "type": "Point",
    "coordinates": [
      -119.95,
      39.9167
    ]
  },
  "type": "Feature",
  "properties": {
    "hierarchy": [
      "tgn:2653103",
      "tgn:1000001",
      "tgn:7012149",
      "tgn:7029392"
    ],
    "placetype": [
      "aat:300008798"
    ],
    "id": 2653103,
    "name:xx": "Seven Lakes Mountain"
  }
}
