{
  "geometry": {
    "type": "Point",
    "coordinates": [
      -107.8333,
      37.8667
    ]
  },
  "type": "Feature",
  "properties": {
    "hierarchy": [
      "tgn:2700759",
      "tgn:1000001",
      "tgn:7012149",
      "tgn:7007158",
      "tgn:2000248",
      "tgn:7029392"
    ],
    "placetype": [
      "aat:300000390"
    ],
    "id": 2700759,
    "name:xx": "Suffolk Mine"
  }
}
