{
  "type": "FeatureCollection",
  "features": [
    {
      "geometry": {
        "type": "Point",
        "coordinates": [
          -72.5,
          44.4667
        ]
      },
      "type": "Feature",
      "properties": {
        "hierarchy": [
          "tgn:2376700",
          "tgn:1000001",
          "tgn:2002133",
          "tgn:7012149",
          "tgn:7007828",
          "tgn:7029392"
        ],
        "placetype": [
          "aat:300008680"
        ],
        "id": 2376700,
        "name:xx": "Hardwood Pond"
      }
    },
    {
      "geometry": {
        "type": "Point",
        "coordinates": [
          -68.2833,
          44.8167
        ]
      },
      "type": "Feature",
      "properties": {
        "hierarchy": [
          "tgn:2376701",
          "tgn:1000001",
          "tgn:2000922",
          "tgn:7012149",
          "tgn:7007515",
          "tgn:7029392"
        ],
        "placetype": [
          "aat:300266640"
        ],
        "id": 2376701,
        "name:xx": "Hardwood Ridge"
      }
    },
    {
      "geometry": {
        "type": "Point",
        "coordinates": [
          -67.95,
          45.6333
        ]
      },
      "type": "Feature",
      "properties": {
        "hierarchy": [
          "tgn:2376702",
          "tgn:1000001",
          "tgn:7012149",
          "tgn:7014589",
          "tgn:7007515",
          "tgn:7029392"
        ],
        "placetype": [
          "aat:300266640"
        ],
        "id": 2376702,
        "name:xx": "Hardwood Ridge"
      }
    },
    {
      "geometry": {
        "type": "Point",
        "coordinates": [
          -71.6333,
          44.0833
        ]
      },
      "type": "Feature",
      "properties": {
        "hierarchy": [
          "tgn:2376703",
          "tgn:1000001",
          "tgn:2001424",
          "tgn:7012149",
          "tgn:7007564",
          "tgn:7029392"
        ],
        "placetype": [
          "aat:300266640"
        ],
        "id": 2376703,
        "name:xx": "Hardwood Ridge"
      }
    },
    {
      "geometry": {
        "type": "Point",
        "coordinates": [
          -71.4,
          44.3333
        ]
      },
      "type": "Feature",
      "properties": {
        "hierarchy": [
          "tgn:2376704",
          "tgn:1002300",
          "tgn:1000001",
          "tgn:7012149",
          "tgn:7007564",
          "tgn:7029392"
        ],
        "placetype": [
          "aat:300266640"
        ],
        "id": 2376704,
        "name:xx": "Hardwood Ridge"
      }
    },
    {
      "geometry": {
        "type": "Point",
        "coordinates": [
          -74.1167,
          43.85
        ]
      },
      "type": "Feature",
      "properties": {
        "hierarchy": [
          "tgn:2376705",
          "tgn:1000001",
          "tgn:7012149",
          "tgn:2001461",
          "tgn:7007568",
          "tgn:7029392"
        ],
        "placetype": [
          "aat:300266640"
        ],
        "id": 2376705,
        "name:xx": "Hardwood Ridge"
      }
    },
    {
      "geometry": {
        "type": "Point",
        "coordinates": [
          -74.8333,
          44.3667
        ]
      },
      "type": "Feature",
      "properties": {
        "hierarchy": [
          "tgn:2376706",
          "tgn:1000001",
          "tgn:7012149",
          "tgn:7016021",
          "tgn:7007568",
          "tgn:7029392"
        ],
        "placetype": [
          "aat:300266640"
        ],
        "id": 2376706,
        "name:xx": "Hardwood Ridge"
      }
    },
    {
      "geometry": {
        "type": "Point",
        "coordinates": [
          -72.3167,
          44.2667
        ]
      },
      "type": "Feature",
      "properties": {
        "hierarchy": [
          "tgn:2376707",
          "tgn:1000001",
          "tgn:2002135",
          "tgn:7012149",
          "tgn:7007828",
          "tgn:7029392"
        ],
        "placetype": [
          "aat:300266640"
        ],
        "id": 2376707,
        "name:xx": "Hardwood Ridge"
      }
    },
    {
      "geometry": {
        "type": "Point",
        "coordinates": [
          -84.9167,
          45.45
        ]
      },
      "type": "Feature",
      "properties": {
        "hierarchy": [
          "tgn:2376708",
          "tgn:1000001",
          "tgn:7012149",
          "tgn:7007520",
          "tgn:7029392"
        ],
        "placetype": [
          "aat:300008863"
        ],
        "id": 2376708,
        "name:xx": "Hardwood State Forest"
      }
    },
    {
      "geometry": {
        "type": "Point",
        "coordinates": [
          -106.2167,
          40.9167
        ]
      },
      "type": "Feature",
      "properties": {
        "hierarchy": [
          "tgn:2376709",
          "tgn:1000001",
          "tgn:7012149",
          "tgn:2000220",
          "tgn:7007158",
          "tgn:7029392"
        ],
        "placetype": [
          "aat:300006075"
        ],
        "id": 2376709,
        "name:xx": "Hardwork Ditch"
      }
    }
  ]
}
