{
  "geometry": {
    "type": "Point",
    "coordinates": [
      112.1667,
      30.0333
    ]
  },
  "type": "Feature",
  "properties": {
    "hierarchy": [
      "tgn:1068308",
      "tgn:1000004",
      "tgn:7002078",
      "tgn:1000111",
      "tgn:7029392"
    ],
    "placetype": [
      "aat:300008347"
    ],
    "id": 1068308,
    "name:xx": "Gong'an"
  }
}
