{
  "geometry": {
    "type": "Point",
    "coordinates": [
      -94.6333,
      34.4167
    ]
  },
  "type": "Feature",
  "properties": {
    "hierarchy": [
      "tgn:2535203",
      "tgn:1000001",
      "tgn:7012149",
      "tgn:2001667",
      "tgn:7007707",
      "tgn:7029392"
    ],
    "placetype": [
      "aat:300008347"
    ],
    "id": 2535203,
    "name:xx": "Nani-chito"
  }
}
