{
  "geometry": {
    "type": "Point",
    "coordinates": [
      -86.1833,
      30.8667
    ]
  },
  "type": "Feature",
  "properties": {
    "hierarchy": [
      "tgn:2273411",
      "tgn:1000001",
      "tgn:7012149",
      "tgn:2000290",
      "tgn:7007240",
      "tgn:7029392"
    ],
    "placetype": [
      "aat:300008905"
    ],
    "id": 2273411,
    "name:xx": "Cypress Drains"
  }
}
