{
  "geometry": {
    "type": "Point",
    "coordinates": [
      -109.0667,
      31.55
    ]
  },
  "type": "Feature",
  "properties": {
    "hierarchy": [
      "tgn:2171597",
      "tgn:1000001",
      "tgn:7006451",
      "tgn:2000091",
      "tgn:7012149",
      "tgn:7029392"
    ],
    "placetype": [
      "aat:300006191"
    ],
    "id": 2171597,
    "name:xx": "Big Tank"
  }
}
