{
  "geometry": {
    "type": "Point",
    "coordinates": [
      -104.35,
      37.0833
    ]
  },
  "type": "Feature",
  "properties": {
    "hierarchy": [
      "tgn:2465171",
      "tgn:1000001",
      "tgn:7012149",
      "tgn:2000227",
      "tgn:7007158",
      "tgn:7029392"
    ],
    "placetype": [
      "aat:300266640"
    ],
    "id": 2465171,
    "name:xx": "Loma de los Conejos"
  }
}
