{
  "geometry": {
    "type": "Point",
    "coordinates": [
      74.35,
      19.333333
    ]
  },
  "type": "Feature",
  "properties": {
    "hierarchy": [
      "tgn:7555787",
      "tgn:1000004",
      "tgn:7000198",
      "tgn:1001895",
      "tgn:7029392"
    ],
    "placetype": [
      "aat:300008347"
    ],
    "name:en": "Māndwe Budrukh",
    "id": 7555787
  }
}
