{
  "geometry": {
    "type": "Point",
    "coordinates": [
      -88.5167,
      43.9667
    ]
  },
  "type": "Feature",
  "properties": {
    "hierarchy": [
      "tgn:2571305",
      "tgn:1000001",
      "tgn:7012149",
      "tgn:2002363",
      "tgn:7007922",
      "tgn:7029392"
    ],
    "placetype": [
      "aat:300008347"
    ],
    "id": 2571305,
    "name:xx": "Paukotuk"
  }
}
