{
  "geometry": {
    "type": "Point",
    "coordinates": [
      31.113889,
      29.289722
    ]
  },
  "type": "Feature",
  "properties": {
    "hierarchy": [
      "tgn:7535937",
      "tgn:7001242",
      "tgn:7001105",
      "tgn:7016833",
      "tgn:7029392"
    ],
    "placetype": [
      "aat:300008347"
    ],
    "name:en": "Infasţ Banī Ḩibbīn",
    "id": 7535937
  }
}
