{
  "geometry": {
    "type": "Point",
    "coordinates": [
      -86.1167,
      30.75
    ]
  },
  "type": "Feature",
  "properties": {
    "hierarchy": [
      "tgn:2429482",
      "tgn:1000001",
      "tgn:7012149",
      "tgn:2000290",
      "tgn:7007240",
      "tgn:7029392"
    ],
    "placetype": [
      "aat:300006191"
    ],
    "id": 2429482,
    "name:xx": "Juniper Lake"
  }
}
