{
  "type": "FeatureCollection",
  "features": [
    {
      "geometry": {
        "type": "Point",
        "coordinates": [
          -81.9,
          8.9833
        ]
      },
      "type": "Feature",
      "properties": {
        "hierarchy": [
          "tgn:1123140",
          "tgn:7593354",
          "tgn:1000001",
          "tgn:7005565",
          "tgn:7029392"
        ],
        "placetype": [
          "aat:300008707"
        ],
        "id": 1123140,
        "name:xx": "Cricamola, Río"
      }
    },
    {
      "geometry": {
        "type": "Point",
        "coordinates": [
          -50.4333,
          -10.3167
        ]
      },
      "type": "Feature",
      "properties": {
        "hierarchy": [
          "tgn:1123141",
          "tgn:7012827",
          "tgn:7002454",
          "tgn:1000047",
          "tgn:1000002",
          "tgn:7029392"
        ],
        "placetype": [
          "aat:300008707"
        ],
        "id": 1123141,
        "name:xx": "Crisóstomo, Ribeirão"
      }
    },
    {
      "geometry": {
        "type": "Point",
        "coordinates": [
          -50.6667,
          -12.6333
        ]
      },
      "type": "Feature",
      "properties": {
        "hierarchy": [
          "tgn:1123142",
          "tgn:7006260",
          "tgn:7002454",
          "tgn:1000047",
          "tgn:1000002",
          "tgn:7029392"
        ],
        "placetype": [
          "aat:300008707"
        ],
        "id": 1123142,
        "name:xx": "Cristalino"
      }
    },
    {
      "geometry": {
        "type": "Point",
        "coordinates": [
          -48.5667,
          -11.0333
        ]
      },
      "type": "Feature",
      "properties": {
        "hierarchy": [
          "tgn:1123143",
          "tgn:7012828",
          "tgn:7002454",
          "tgn:1000047",
          "tgn:1000002",
          "tgn:7029392"
        ],
        "placetype": [
          "aat:300008707"
        ],
        "id": 1123143,
        "name:xx": "Crixás"
      }
    },
    {
      "geometry": {
        "type": "Point",
        "coordinates": [
          -50.6,
          -13.3167
        ]
      },
      "type": "Feature",
      "properties": {
        "hierarchy": [
          "tgn:1123144",
          "tgn:7012827",
          "tgn:7002454",
          "tgn:1000047",
          "tgn:1000002",
          "tgn:7029392"
        ],
        "placetype": [
          "aat:300008707"
        ],
        "id": 1123144,
        "name:xx": "Crixás Açu"
      }
    },
    {
      "geometry": {
        "type": "Point",
        "coordinates": [
          -50.5,
          -13.5
        ]
      },
      "type": "Feature",
      "properties": {
        "hierarchy": [
          "tgn:1123145",
          "tgn:7012827",
          "tgn:7002454",
          "tgn:1000047",
          "tgn:1000002",
          "tgn:7029392"
        ],
        "placetype": [
          "aat:300008707"
        ],
        "id": 1123145,
        "name:xx": "Crixás Mirim"
      }
    },
    {
      "geometry": {
        "type": "Point",
        "coordinates": [
          -2.3833,
          53.55
        ]
      },
      "type": "Feature",
      "properties": {
        "hierarchy": [
          "tgn:1123147",
          "tgn:1003566",
          "tgn:7002445",
          "tgn:1000003",
          "tgn:7026570",
          "tgn:7008591",
          "tgn:7029392"
        ],
        "placetype": [
          "aat:300008707"
        ],
        "id": 1123147,
        "name:xx": "Croal"
      }
    },
    {
      "geometry": {
        "type": "Point",
        "coordinates": [
          -94.2667,
          39.5
        ]
      },
      "type": "Feature",
      "properties": {
        "hierarchy": [
          "tgn:1123148",
          "tgn:1000001",
          "tgn:7012149",
          "tgn:7007523",
          "tgn:7029392"
        ],
        "placetype": [
          "aat:300008707"
        ],
        "id": 1123148,
        "name:xx": "Crooked"
      }
    },
    {
      "geometry": {
        "type": "Point",
        "coordinates": [
          -120.05,
          44.1
        ]
      },
      "type": "Feature",
      "properties": {
        "hierarchy": [
          "tgn:1123149",
          "tgn:1000001",
          "tgn:7012149",
          "tgn:7007708",
          "tgn:7029392"
        ],
        "placetype": [
          "aat:300008707"
        ],
        "id": 1123149,
        "name:xx": "Crooked"
      }
    }
  ]
}
