{
  "geometry": {
    "type": "Point",
    "coordinates": [
      -77.0667,
      42.7833
    ]
  },
  "type": "Feature",
  "properties": {
    "hierarchy": [
      "tgn:2069538",
      "tgn:1000001",
      "tgn:7012149",
      "tgn:1002747",
      "tgn:7007568",
      "tgn:7029392"
    ],
    "placetype": [
      "aat:300008347"
    ],
    "id": 2069538,
    "name:xx": "Hall"
  }
}
