{
  "geometry": {
    "type": "Point",
    "coordinates": [
      30.680556,
      30.676111
    ]
  },
  "type": "Feature",
  "properties": {
    "hierarchy": [
      "tgn:7540984",
      "tgn:7001242",
      "tgn:1001075",
      "tgn:7016833",
      "tgn:7029392"
    ],
    "placetype": [
      "aat:300008347"
    ],
    "name:en": "Qaryat Ḩirā'",
    "id": 7540984
  }
}
