{
  "geometry": {
    "type": "Point",
    "coordinates": [
      -79.85,
      37.9167
    ]
  },
  "type": "Feature",
  "properties": {
    "hierarchy": [
      "tgn:1103847",
      "tgn:2002143",
      "tgn:1000001",
      "tgn:7012149",
      "tgn:7007919",
      "tgn:7029392"
    ],
    "placetype": [
      "aat:300008795"
    ],
    "id": 1103847,
    "name:xx": "Bald Knob"
  }
}
