{
  "geometry": {
    "type": "Point",
    "coordinates": [
      30.3333,
      8.1667
    ]
  },
  "type": "Feature",
  "properties": {
    "hierarchy": [
      "tgn:1094106",
      "tgn:7001242",
      "tgn:7441557",
      "tgn:7441551",
      "tgn:7029392"
    ],
    "placetype": [
      "aat:300008347"
    ],
    "id": 1094106,
    "name:xx": "Adok"
  }
}
