{
  "geometry": {
    "type": "Point",
    "coordinates": [
      -104.05,
      37.7333
    ]
  },
  "type": "Feature",
  "properties": {
    "hierarchy": [
      "tgn:2392559",
      "tgn:1000001",
      "tgn:7012149",
      "tgn:7007158",
      "tgn:2000242",
      "tgn:7029392"
    ],
    "placetype": [
      "aat:300008697"
    ],
    "id": 2392559,
    "name:xx": "Hixon Spring"
  }
}
