{
  "geometry": {
    "type": "Point",
    "coordinates": [
      -84.6833,
      32.9333
    ]
  },
  "type": "Feature",
  "properties": {
    "hierarchy": [
      "tgn:2218680",
      "tgn:1000001",
      "tgn:7012149",
      "tgn:2000390",
      "tgn:7007248",
      "tgn:7029392"
    ],
    "placetype": [
      "aat:300006191"
    ],
    "id": 2218680,
    "name:xx": "Cane Creek Structure Number Three Lake"
  }
}
