{
  "type": "FeatureCollection",
  "features": [
    {
      "geometry": {
        "type": "Point",
        "coordinates": [
          14.5833,
          47.6167
        ]
      },
      "type": "Feature",
      "properties": {
        "hierarchy": [
          "tgn:1109010",
          "tgn:7003028",
          "tgn:1000003",
          "tgn:1000062",
          "tgn:7029392"
        ],
        "placetype": [
          "aat:300008795"
        ],
        "id": 1109010,
        "name:xx": "Ennstaler Alpen"
      }
    },
    {
      "geometry": {
        "type": "Point",
        "coordinates": [
          -120.5333,
          47.7667
        ]
      },
      "type": "Feature",
      "properties": {
        "hierarchy": [
          "tgn:1109011",
          "tgn:1000001",
          "tgn:1002260",
          "tgn:7012149",
          "tgn:7007920",
          "tgn:7029392"
        ],
        "placetype": [
          "aat:300008795"
        ],
        "id": 1109011,
        "name:xx": "Entiat Mountains"
      }
    },
    {
      "geometry": {
        "type": "Point",
        "coordinates": [
          -85.6167,
          14.0833
        ]
      },
      "type": "Feature",
      "properties": {
        "hierarchy": [
          "tgn:1109012",
          "tgn:1000715",
          "tgn:1000001",
          "tgn:7005554",
          "tgn:7029392"
        ],
        "placetype": [
          "aat:300386831"
        ],
        "id": 1109012,
        "name:xx": "Entre Ríos, Cordillera"
      }
    },
    {
      "geometry": {
        "type": "Point",
        "coordinates": [
          113.5,
          50
        ]
      },
      "type": "Feature",
      "properties": {
        "hierarchy": [
          "tgn:1109014",
          "tgn:1000004",
          "tgn:7029392"
        ],
        "placetype": [
          "aat:300008795"
        ],
        "id": 1109014,
        "name:xx": "Ermana, Khrebet"
      }
    },
    {
      "geometry": {
        "type": "Point",
        "coordinates": [
          13.3667,
          41.8
        ]
      },
      "type": "Feature",
      "properties": {
        "hierarchy": [
          "tgn:1109015",
          "tgn:7003135",
          "tgn:1000003",
          "tgn:7003080",
          "tgn:1000080",
          "tgn:7029392"
        ],
        "placetype": [
          "aat:300386831"
        ],
        "id": 1109015,
        "name:xx": "Ernici, Monti"
      }
    },
    {
      "geometry": {
        "type": "Point",
        "coordinates": [
          15.6667,
          -21.6667
        ]
      },
      "type": "Feature",
      "properties": {
        "hierarchy": [
          "tgn:1109016",
          "tgn:7001242",
          "tgn:7030583",
          "tgn:1000198",
          "tgn:7029392"
        ],
        "placetype": [
          "aat:300008795"
        ],
        "id": 1109016,
        "name:xx": "Erongo"
      }
    },
    {
      "geometry": {
        "type": "Point",
        "coordinates": [
          -43.5,
          -17.5
        ]
      },
      "type": "Feature",
      "properties": {
        "hierarchy": [
          "tgn:1109019",
          "tgn:1000047",
          "tgn:1000002",
          "tgn:7029392"
        ],
        "placetype": [
          "aat:300008795"
        ],
        "id": 1109019,
        "name:xx": "Espinhaço, Serra do"
      }
    }
  ]
}
