{
  "geometry": {
    "type": "Point",
    "coordinates": [
      141.5833,
      45.1667
    ]
  },
  "type": "Feature",
  "properties": {
    "hierarchy": [
      "tgn:1101821",
      "tgn:1000985",
      "tgn:7016529",
      "tgn:7016531",
      "tgn:1000004",
      "tgn:1000120",
      "tgn:7029392"
    ],
    "placetype": [
      "aat:300008189"
    ],
    "id": 1101821,
    "name:xx": "Rishiri-Rebun-Sarobetsu-kokuritsu-kōen"
  }
}
