{
  "geometry": {
    "type": "Point",
    "coordinates": [
      -104.0333,
      44.3667
    ]
  },
  "type": "Feature",
  "properties": {
    "hierarchy": [
      "tgn:2432700",
      "tgn:1000001",
      "tgn:2001810",
      "tgn:7012149",
      "tgn:7007713",
      "tgn:7029392"
    ],
    "placetype": [
      "aat:300000390"
    ],
    "id": 2432700,
    "name:xx": "Keenan Properties Mine"
  }
}
