{
  "geometry": {
    "type": "Point",
    "coordinates": [
      -122.95,
      41.5667
    ]
  },
  "type": "Feature",
  "properties": {
    "hierarchy": [
      "tgn:2525375",
      "tgn:1000001",
      "tgn:7012149",
      "tgn:7007157",
      "tgn:2000189",
      "tgn:7029392"
    ],
    "placetype": [
      "aat:300000390"
    ],
    "id": 2525375,
    "name:xx": "Morrison-Carlock Mine"
  }
}
