{
  "geometry": {
    "type": "Point",
    "coordinates": [
      -120.6667,
      35.3167
    ]
  },
  "type": "Feature",
  "properties": {
    "hierarchy": [
      "tgn:2238563",
      "tgn:1000001",
      "tgn:7012149",
      "tgn:7007157",
      "tgn:1002863",
      "tgn:7029392"
    ],
    "placetype": [
      "aat:300008347"
    ],
    "id": 2238563,
    "name:xx": "Chorro"
  }
}
