{
  "geometry": {
    "type": "Point",
    "coordinates": [
      33.55,
      38.25
    ]
  },
  "type": "Feature",
  "properties": {
    "hierarchy": [
      "tgn:1086889",
      "tgn:1001442",
      "tgn:1000004",
      "tgn:7018453",
      "tgn:1000144",
      "tgn:7029392"
    ],
    "placetype": [
      "aat:300008347"
    ],
    "id": 1086889,
    "name:xx": "Sultanhanı"
  }
}
