{
  "geometry": {
    "type": "Point",
    "coordinates": [
      -122.9333,
      42.7833
    ]
  },
  "type": "Feature",
  "properties": {
    "hierarchy": [
      "tgn:2295238",
      "tgn:1000001",
      "tgn:7012149",
      "tgn:2001706",
      "tgn:7007708",
      "tgn:7029392"
    ],
    "placetype": [
      "aat:300008680"
    ],
    "id": 2295238,
    "name:xx": "Drew Lake"
  }
}
