{
  "geometry": {
    "type": "Point",
    "coordinates": [
      -75.9833,
      41.7333
    ]
  },
  "type": "Feature",
  "properties": {
    "hierarchy": [
      "tgn:2619146",
      "tgn:1000001",
      "tgn:7012149",
      "tgn:7007710",
      "tgn:7029392"
    ],
    "placetype": [
      "aat:300008706"
    ],
    "id": 2619146,
    "name:xx": "Riley Creek"
  }
}
