{
  "type": "FeatureCollection",
  "features": [
    {
      "geometry": {
        "type": "Point",
        "coordinates": [
          6.8,
          49.616667
        ]
      },
      "type": "Feature",
      "properties": {
        "hierarchy": [
          "tgn:7086070",
          "tgn:1000003",
          "tgn:7003682",
          "tgn:7000084",
          "tgn:7029392"
        ],
        "placetype": [
          "aat:300008347"
        ],
        "id": 7086070,
        "name:xx": "Waldweiler"
      }
    },
    {
      "geometry": {
        "type": "Point",
        "coordinates": [
          6.983333,
          51.883333
        ]
      },
      "type": "Feature",
      "properties": {
        "hierarchy": [
          "tgn:7086071",
          "tgn:1000003",
          "tgn:7003677",
          "tgn:7000084",
          "tgn:7029392"
        ],
        "placetype": [
          "aat:300008347"
        ],
        "id": 7086071,
        "name:xx": "Waldvelen"
      }
    },
    {
      "geometry": {
        "type": "Point",
        "coordinates": [
          8.1,
          48.583333
        ]
      },
      "type": "Feature",
      "properties": {
        "hierarchy": [
          "tgn:7086072",
          "tgn:7003692",
          "tgn:1000003",
          "tgn:7000084",
          "tgn:7029392"
        ],
        "placetype": [
          "aat:300008347"
        ],
        "id": 7086072,
        "name:xx": "Waldulm"
      }
    },
    {
      "geometry": {
        "type": "Point",
        "coordinates": [
          6.8,
          51.533333
        ]
      },
      "type": "Feature",
      "properties": {
        "hierarchy": [
          "tgn:7086074",
          "tgn:1000003",
          "tgn:7003677",
          "tgn:7000084",
          "tgn:7029392"
        ],
        "placetype": [
          "aat:300000745"
        ],
        "id": 7086074,
        "name:xx": "Waldteich"
      }
    },
    {
      "geometry": {
        "type": "Point",
        "coordinates": [
          13,
          51.4
        ]
      },
      "type": "Feature",
      "properties": {
        "hierarchy": [
          "tgn:7086075",
          "tgn:1000003",
          "tgn:7003685",
          "tgn:7000084",
          "tgn:7029392"
        ],
        "placetype": [
          "aat:300008688"
        ],
        "id": 7086075,
        "name:xx": "Wald-Teich"
      }
    },
    {
      "geometry": {
        "type": "Point",
        "coordinates": [
          14.183333,
          51.483333
        ]
      },
      "type": "Feature",
      "properties": {
        "hierarchy": [
          "tgn:7086076",
          "tgn:1000003",
          "tgn:7003685",
          "tgn:7000084",
          "tgn:7029392"
        ],
        "placetype": [
          "aat:300387087"
        ],
        "id": 7086076,
        "name:xx": "Wald Teich"
      }
    },
    {
      "geometry": {
        "type": "Point",
        "coordinates": [
          10.183333,
          49.133333
        ]
      },
      "type": "Feature",
      "properties": {
        "hierarchy": [
          "tgn:7086077",
          "tgn:7003692",
          "tgn:1000003",
          "tgn:7000084",
          "tgn:7029392"
        ],
        "placetype": [
          "aat:300008347"
        ],
        "id": 7086077,
        "name:xx": "Waldtann"
      }
    },
    {
      "geometry": {
        "type": "Point",
        "coordinates": [
          10.233333,
          50.066667
        ]
      },
      "type": "Feature",
      "properties": {
        "hierarchy": [
          "tgn:7086079",
          "tgn:7003669",
          "tgn:1000003",
          "tgn:7000084",
          "tgn:7029392"
        ],
        "placetype": [
          "aat:300007783"
        ],
        "id": 7086079,
        "name:xx": "Bahnhof Waldstraße"
      }
    }
  ]
}
