{
  "geometry": {
    "type": "Point",
    "coordinates": [
      -92.0833,
      35.6667
    ]
  },
  "type": "Feature",
  "properties": {
    "hierarchy": [
      "tgn:2211020",
      "tgn:1000001",
      "tgn:7016172",
      "tgn:2000116",
      "tgn:7012149",
      "tgn:7029392"
    ],
    "placetype": [
      "aat:300008761"
    ],
    "id": 2211020,
    "name:xx": "Butler Hollow"
  }
}
