{
  "geometry": {
    "type": "Point",
    "coordinates": [
      30.65,
      28.35
    ]
  },
  "type": "Feature",
  "properties": {
    "hierarchy": [
      "tgn:7538162",
      "tgn:7001242",
      "tgn:7016833",
      "tgn:1001088",
      "tgn:7029392"
    ],
    "placetype": [
      "aat:300008347"
    ],
    "name:en": "Nazlat aş Şurmānī",
    "id": 7538162
  }
}
