{
  "geometry": {
    "type": "Point",
    "coordinates": [
      -76.25,
      35.3667
    ]
  },
  "type": "Feature",
  "properties": {
    "hierarchy": [
      "tgn:2429342",
      "tgn:1000001",
      "tgn:7012149",
      "tgn:2001506",
      "tgn:7007709",
      "tgn:7029392"
    ],
    "placetype": [
      "aat:300132316"
    ],
    "id": 2429342,
    "name:xx": "Juniper Bay"
  }
}
