{
  "geometry": {
    "type": "Point",
    "coordinates": [
      -78.3333,
      35.65
    ]
  },
  "type": "Feature",
  "properties": {
    "hierarchy": [
      "tgn:2332745",
      "tgn:1000001",
      "tgn:7012149",
      "tgn:2001509",
      "tgn:7007709",
      "tgn:7029392"
    ],
    "placetype": [
      "aat:300008347"
    ],
    "id": 2332745,
    "name:xx": "Flowers"
  }
}
