{
  "geometry": {
    "type": "Point",
    "coordinates": [
      -85.8667,
      38.2667
    ]
  },
  "type": "Feature",
  "properties": {
    "hierarchy": [
      "tgn:2621074",
      "tgn:1000001",
      "tgn:7012149",
      "tgn:1002376",
      "tgn:7007252",
      "tgn:7029392"
    ],
    "placetype": [
      "aat:300008761"
    ],
    "id": 2621074,
    "name:xx": "Road Hollow"
  }
}
