{
  "geometry": {
    "type": "Point",
    "coordinates": [
      -108.15,
      47.2667
    ]
  },
  "type": "Feature",
  "properties": {
    "hierarchy": [
      "tgn:2301436",
      "tgn:1000001",
      "tgn:7012149",
      "tgn:2001294",
      "tgn:7007524",
      "tgn:7029392"
    ],
    "placetype": [
      "aat:300266640"
    ],
    "id": 2301436,
    "name:xx": "Dunn Ridge"
  }
}
