{
  "geometry": {
    "type": "Point",
    "coordinates": [
      -81.9333,
      28.6833
    ]
  },
  "type": "Feature",
  "properties": {
    "hierarchy": [
      "tgn:2147088",
      "tgn:1000001",
      "tgn:7012149",
      "tgn:1002567",
      "tgn:7007240",
      "tgn:7029392"
    ],
    "placetype": [
      "aat:300008680"
    ],
    "id": 2147088,
    "name:xx": "Baptising Pond"
  }
}
