{
  "geometry": {
    "type": "Point",
    "coordinates": [
      -90.3333,
      42.1833
    ]
  },
  "type": "Feature",
  "properties": {
    "hierarchy": [
      "tgn:2147262",
      "tgn:1000001",
      "tgn:7012149",
      "tgn:2000609",
      "tgn:7007253",
      "tgn:7029392"
    ],
    "placetype": [
      "aat:300008699"
    ],
    "id": 2147262,
    "name:xx": "Bar Slough"
  }
}
