{
  "geometry": {
    "type": "Point",
    "coordinates": [
      31.884753,
      31.173039
    ]
  },
  "type": "Feature",
  "properties": {
    "hierarchy": [
      "tgn:7521945",
      "tgn:7001242",
      "tgn:1001059",
      "tgn:7016833",
      "tgn:7029392"
    ],
    "placetype": [
      "aat:300008347"
    ],
    "name:en": "Al Buşrāţ",
    "id": 7521945
  }
}
