{
  "type": "FeatureCollection",
  "features": [
    {
      "geometry": {
        "type": "Point",
        "coordinates": [
          4.20914,
          50.871199
        ]
      },
      "type": "Feature",
      "properties": {
        "hierarchy": [
          "tgn:7251061",
          "tgn:7018239",
          "tgn:1000003",
          "tgn:1000063",
          "tgn:7018236",
          "tgn:7029392"
        ],
        "placetype": [
          "aat:300008347"
        ],
        "id": 7251061,
        "name:xx": "Oosthoek"
      }
    },
    {
      "geometry": {
        "type": "Point",
        "coordinates": [
          2.75,
          50.866667
        ]
      },
      "type": "Feature",
      "properties": {
        "hierarchy": [
          "tgn:7251062",
          "tgn:7003458",
          "tgn:1000003",
          "tgn:1000063",
          "tgn:7018236",
          "tgn:7029392"
        ],
        "placetype": [
          "aat:300008347"
        ],
        "id": 7251062,
        "name:xx": "Oosthoek"
      }
    },
    {
      "geometry": {
        "type": "Point",
        "coordinates": [
          3.042148,
          50.856853
        ]
      },
      "type": "Feature",
      "properties": {
        "hierarchy": [
          "tgn:7251063",
          "tgn:7003458",
          "tgn:1000003",
          "tgn:1000063",
          "tgn:7018236",
          "tgn:7029392"
        ],
        "placetype": [
          "aat:300008347"
        ],
        "id": 7251063,
        "name:xx": "Oosthoek"
      }
    },
    {
      "geometry": {
        "type": "Point",
        "coordinates": [
          2.9,
          50.8
        ]
      },
      "type": "Feature",
      "properties": {
        "hierarchy": [
          "tgn:7251064",
          "tgn:7003458",
          "tgn:1000003",
          "tgn:1000063",
          "tgn:7018236",
          "tgn:7029392"
        ],
        "placetype": [
          "aat:300008347"
        ],
        "id": 7251064,
        "name:xx": "Oosthoek"
      }
    },
    {
      "geometry": {
        "type": "Point",
        "coordinates": [
          5.166667,
          51.1
        ]
      },
      "type": "Feature",
      "properties": {
        "hierarchy": [
          "tgn:7251065",
          "tgn:7003461",
          "tgn:1000003",
          "tgn:1000063",
          "tgn:7018236",
          "tgn:7029392"
        ],
        "placetype": [
          "aat:300008347"
        ],
        "id": 7251065,
        "name:xx": "Oostham"
      }
    },
    {
      "geometry": {
        "type": "Point",
        "coordinates": [
          4.866667,
          51.133333
        ]
      },
      "type": "Feature",
      "properties": {
        "hierarchy": [
          "tgn:7251069",
          "tgn:7003456",
          "tgn:1000003",
          "tgn:1000063",
          "tgn:7018236",
          "tgn:7029392"
        ],
        "placetype": [
          "aat:300008347"
        ],
        "id": 7251069,
        "name:xx": "Oosterwijk"
      }
    }
  ]
}
