{
  "geometry": {
    "type": "Point",
    "coordinates": [
      50.0333,
      8.1333
    ]
  },
  "type": "Feature",
  "properties": {
    "hierarchy": [
      "tgn:1092697",
      "tgn:7001242",
      "tgn:1001723",
      "tgn:1000192",
      "tgn:7029392"
    ],
    "placetype": [
      "aat:300008347"
    ],
    "id": 1092697,
    "name:xx": "Gabah"
  }
}
