{
  "geometry": {
    "type": "Point",
    "coordinates": [
      -90.3333,
      34.4667
    ]
  },
  "type": "Feature",
  "properties": {
    "hierarchy": [
      "tgn:2296014",
      "tgn:1000001",
      "tgn:7012149",
      "tgn:2001157",
      "tgn:7007522",
      "tgn:7029392"
    ],
    "placetype": [
      "aat:300008699"
    ],
    "id": 2296014,
    "name:xx": "Dry Bayou"
  }
}
