{
  "geometry": {
    "type": "Point",
    "coordinates": [
      -88.45,
      48.1667
    ]
  },
  "type": "Feature",
  "properties": {
    "hierarchy": [
      "tgn:2612097",
      "tgn:1000001",
      "tgn:7012149",
      "tgn:2000969",
      "tgn:7007520",
      "tgn:7029392"
    ],
    "placetype": [
      "aat:300008850"
    ],
    "id": 2612097,
    "name:xx": "Red Rock Point"
  }
}
