{
  "type": "FeatureCollection",
  "features": [
    {
      "geometry": {
        "type": "Point",
        "coordinates": [
          -105.1667,
          39.4
        ]
      },
      "type": "Feature",
      "properties": {
        "hierarchy": [
          "tgn:2016331",
          "tgn:1000001",
          "tgn:7012149",
          "tgn:2000221",
          "tgn:7007158",
          "tgn:7029392"
        ],
        "placetype": [
          "aat:300008347"
        ],
        "id": 2016331,
        "name:xx": "South Platte"
      }
    },
    {
      "geometry": {
        "type": "Point",
        "coordinates": [
          -104.3333,
          40.1
        ]
      },
      "type": "Feature",
      "properties": {
        "hierarchy": [
          "tgn:2016332",
          "tgn:1000001",
          "tgn:7012149",
          "tgn:7007158",
          "tgn:2000253",
          "tgn:7029392"
        ],
        "placetype": [
          "aat:300008347"
        ],
        "id": 2016332,
        "name:xx": "South Roggen"
      }
    },
    {
      "geometry": {
        "type": "Point",
        "coordinates": [
          -104.5333,
          40.3833
        ]
      },
      "type": "Feature",
      "properties": {
        "hierarchy": [
          "tgn:2016336",
          "tgn:1000001",
          "tgn:7012149",
          "tgn:7007158",
          "tgn:2000253",
          "tgn:7029392"
        ],
        "placetype": [
          "aat:300008347"
        ],
        "id": 2016336,
        "name:xx": "Spanish Village"
      }
    },
    {
      "geometry": {
        "type": "Point",
        "coordinates": [
          -106.9667,
          37.7
        ]
      },
      "type": "Feature",
      "properties": {
        "hierarchy": [
          "tgn:2016337",
          "tgn:1000001",
          "tgn:7012149",
          "tgn:2000231",
          "tgn:7007158",
          "tgn:7029392"
        ],
        "placetype": [
          "aat:300008347"
        ],
        "id": 2016337,
        "name:xx": "Spar City"
      }
    },
    {
      "geometry": {
        "type": "Point",
        "coordinates": [
          -108.8,
          40.9167
        ]
      },
      "type": "Feature",
      "properties": {
        "hierarchy": [
          "tgn:2016338",
          "tgn:1000001",
          "tgn:7012149",
          "tgn:2000232",
          "tgn:7007158",
          "tgn:7029392"
        ],
        "placetype": [
          "aat:300008347",
          "aat:300387210"
        ],
        "id": 2016338,
        "name:xx": "Sparks"
      }
    },
    {
      "geometry": {
        "type": "Point",
        "coordinates": [
          -105.3,
          39.4167
        ]
      },
      "type": "Feature",
      "properties": {
        "hierarchy": [
          "tgn:2016339",
          "tgn:1000001",
          "tgn:7012149",
          "tgn:2000221",
          "tgn:7007158",
          "tgn:7029392"
        ],
        "placetype": [
          "aat:300008347"
        ],
        "id": 2016339,
        "name:xx": "Sphinx Park"
      }
    }
  ]
}
