{
  "geometry": {
    "type": "Point",
    "coordinates": [
      16.9167,
      48.2833
    ]
  },
  "type": "Feature",
  "properties": {
    "hierarchy": [
      "tgn:1025823",
      "tgn:7003025",
      "tgn:1000003",
      "tgn:1000062",
      "tgn:7029392"
    ],
    "placetype": [
      "aat:300008347"
    ],
    "id": 1025823,
    "name:xx": "Marchegg"
  }
}
