{
  "geometry": {
    "type": "Point",
    "coordinates": [
      -87.7333,
      34.25
    ]
  },
  "type": "Feature",
  "properties": {
    "hierarchy": [
      "tgn:2537028",
      "tgn:7002659",
      "tgn:1000001",
      "tgn:7012149",
      "tgn:2000046",
      "tgn:7029392"
    ],
    "placetype": [
      "aat:300008699"
    ],
    "id": 2537028,
    "name:xx": "Neeley Branch"
  }
}
