{
  "geometry": {
    "type": "Point",
    "coordinates": [
      11.3333,
      49.7667
    ]
  },
  "type": "Feature",
  "properties": {
    "hierarchy": [
      "tgn:1039169",
      "tgn:7003669",
      "tgn:1000003",
      "tgn:7000084",
      "tgn:7029392"
    ],
    "placetype": [
      "aat:300008347"
    ],
    "id": 1039169,
    "name:xx": "Gössweinstein"
  }
}
