{
  "geometry": {
    "type": "Point",
    "coordinates": [
      -108.6667,
      33.8667
    ]
  },
  "type": "Feature",
  "properties": {
    "hierarchy": [
      "tgn:2740897",
      "tgn:1000001",
      "tgn:2001429",
      "tgn:7012149",
      "tgn:7007566",
      "tgn:7029392"
    ],
    "placetype": [
      "aat:300006191"
    ],
    "id": 2740897,
    "name:xx": "Upper Sawmill Tank"
  }
}
