{
  "geometry": {
    "type": "Point",
    "coordinates": [
      -78.8833,
      40.7833
    ]
  },
  "type": "Feature",
  "properties": {
    "hierarchy": [
      "tgn:2356772",
      "tgn:1000001",
      "tgn:7012149",
      "tgn:1002501",
      "tgn:7007710",
      "tgn:7029392"
    ],
    "placetype": [
      "aat:300008347"
    ],
    "id": 2356772,
    "name:xx": "Gorman Summit"
  }
}
