{
  "geometry": {
    "type": "Point",
    "coordinates": [
      -121.0667,
      39.5167
    ]
  },
  "type": "Feature",
  "properties": {
    "hierarchy": [
      "tgn:2668628",
      "tgn:1000001",
      "tgn:7012149",
      "tgn:7007157",
      "tgn:1003050",
      "tgn:7029392"
    ],
    "placetype": [
      "aat:300132348"
    ],
    "id": 2668628,
    "name:xx": "Slate Range Bar"
  }
}
