{
  "geometry": {
    "type": "Point",
    "coordinates": [
      121.2667,
      42.0167
    ]
  },
  "type": "Feature",
  "properties": {
    "hierarchy": [
      "tgn:1074192",
      "tgn:1000004",
      "tgn:1001390",
      "tgn:1000111",
      "tgn:7029392"
    ],
    "placetype": [
      "aat:300008347"
    ],
    "id": 1074192,
    "name:xx": "Zigutaicun"
  }
}
