{
  "geometry": {
    "type": "Point",
    "coordinates": [
      -83.0333,
      39.2333
    ]
  },
  "type": "Feature",
  "properties": {
    "hierarchy": [
      "tgn:2397400",
      "tgn:1000001",
      "tgn:7012149",
      "tgn:1002835",
      "tgn:7007706",
      "tgn:7029392"
    ],
    "placetype": [
      "aat:300008706"
    ],
    "id": 2397400,
    "name:xx": "Honey Creek"
  }
}
