{
  "type": "FeatureCollection",
  "features": [
    {
      "geometry": {
        "type": "Point",
        "coordinates": [
          9.45,
          46.75
        ]
      },
      "type": "Feature",
      "properties": {
        "hierarchy": [
          "tgn:4008472",
          "tgn:7003748",
          "tgn:1000003",
          "tgn:7011731",
          "tgn:7029392"
        ],
        "placetype": [
          "aat:300008347"
        ],
        "id": 4008472,
        "name:xx": "Paspels"
      }
    },
    {
      "geometry": {
        "type": "Point",
        "coordinates": [
          13.010556,
          45.948333
        ]
      },
      "type": "Feature",
      "properties": {
        "hierarchy": [
          "tgn:4008473",
          "tgn:1003506",
          "tgn:1000003",
          "tgn:7002993",
          "tgn:1000080",
          "tgn:7029392"
        ],
        "placetype": [
          "aat:300008347"
        ],
        "id": 4008473,
        "name:xx": "Passariano"
      }
    },
    {
      "geometry": {
        "type": "Point",
        "coordinates": [
          13.333333,
          43.283333
        ]
      },
      "type": "Feature",
      "properties": {
        "hierarchy": [
          "tgn:4008475",
          "tgn:1003471",
          "tgn:1000003",
          "tgn:7003240",
          "tgn:1000080",
          "tgn:7029392"
        ],
        "placetype": [
          "aat:300008347"
        ],
        "id": 4008475,
        "name:xx": "Passo di Treia"
      }
    },
    {
      "geometry": {
        "type": "Point",
        "coordinates": [
          20.7833,
          49.6333
        ]
      },
      "type": "Feature",
      "properties": {
        "hierarchy": [
          "tgn:4008478",
          "tgn:1000003",
          "tgn:7024127",
          "tgn:7006366",
          "tgn:7029392"
        ],
        "placetype": [
          "aat:300008347"
        ],
        "id": 4008478,
        "name:xx": "Paszyn"
      }
    }
  ]
}
