{
  "geometry": {
    "type": "Point",
    "coordinates": [
      -95.75,
      32.5667
    ]
  },
  "type": "Feature",
  "properties": {
    "hierarchy": [
      "tgn:2106428",
      "tgn:1000001",
      "tgn:7012149",
      "tgn:1002969",
      "tgn:7007826",
      "tgn:7029392"
    ],
    "placetype": [
      "aat:300008347",
      "aat:300387210"
    ],
    "id": 2106428,
    "name:xx": "Oakland"
  }
}
