{
  "geometry": {
    "type": "Point",
    "coordinates": [
      -87.4667,
      41.6333
    ]
  },
  "type": "Feature",
  "properties": {
    "hierarchy": [
      "tgn:2334962",
      "tgn:1000001",
      "tgn:7012149",
      "tgn:1002569",
      "tgn:7007252",
      "tgn:7029392"
    ],
    "placetype": [
      "aat:300008678"
    ],
    "id": 2334962,
    "name:xx": "Forks, The"
  }
}
