{
  "geometry": {
    "type": "Point",
    "coordinates": [
      -90.3667,
      45.3167
    ]
  },
  "type": "Feature",
  "properties": {
    "hierarchy": [
      "tgn:2654248",
      "tgn:1000001",
      "tgn:7012149",
      "tgn:2002356",
      "tgn:7007922",
      "tgn:7029392"
    ],
    "placetype": [
      "aat:300008699"
    ],
    "id": 2654248,
    "name:xx": "Shady Brook"
  }
}
