{
  "geometry": {
    "type": "Point",
    "coordinates": [
      -90.6667,
      36.0333
    ]
  },
  "type": "Feature",
  "properties": {
    "hierarchy": [
      "tgn:2747904",
      "tgn:1000001",
      "tgn:7016172",
      "tgn:7012149",
      "tgn:2000132",
      "tgn:7029392"
    ],
    "placetype": [
      "aat:300006191"
    ],
    "id": 2747904,
    "name:xx": "Walcott Lake"
  }
}
