{
  "geometry": {
    "type": "Point",
    "coordinates": [
      -84.05,
      31.25
    ]
  },
  "type": "Feature",
  "properties": {
    "hierarchy": [
      "tgn:2470905",
      "tgn:1000001",
      "tgn:7012149",
      "tgn:7007248",
      "tgn:7029392"
    ],
    "placetype": [
      "aat:300008706"
    ],
    "id": 2470905,
    "name:xx": "Lost Creek"
  }
}
