{
  "geometry": {
    "type": "Point",
    "coordinates": [
      -103.8833,
      37.1667
    ]
  },
  "type": "Feature",
  "properties": {
    "hierarchy": [
      "tgn:2585270",
      "tgn:1000001",
      "tgn:7012149",
      "tgn:2000227",
      "tgn:7007158",
      "tgn:7029392"
    ],
    "placetype": [
      "aat:300266640"
    ],
    "id": 2585270,
    "name:xx": "Piñon Ridge"
  }
}
