{
  "geometry": {
    "type": "Point",
    "coordinates": [
      -94.35,
      46.75
    ]
  },
  "type": "Feature",
  "properties": {
    "hierarchy": [
      "tgn:2463286",
      "tgn:1000001",
      "tgn:2001009",
      "tgn:7012149",
      "tgn:7007521",
      "tgn:7029392"
    ],
    "placetype": [
      "aat:300008680"
    ],
    "id": 2463286,
    "name:xx": "Lizotte Lake"
  }
}
