{
  "geometry": {
    "type": "Point",
    "coordinates": [
      -119.95,
      45.0167
    ]
  },
  "type": "Feature",
  "properties": {
    "hierarchy": [
      "tgn:2471973",
      "tgn:1000001",
      "tgn:7012149",
      "tgn:7007708",
      "tgn:7029392"
    ],
    "placetype": [
      "aat:300008706"
    ],
    "id": 2471973,
    "name:xx": "Lost Valley Creek"
  }
}
