{
  "geometry": {
    "type": "Point",
    "coordinates": [
      -75.4667,
      39.2667
    ]
  },
  "type": "Feature",
  "properties": {
    "hierarchy": [
      "tgn:2656364",
      "tgn:1002538",
      "tgn:1000001",
      "tgn:7012149",
      "tgn:7007239",
      "tgn:7029392"
    ],
    "placetype": [
      "aat:300006191"
    ],
    "id": 2656364,
    "name:xx": "Shearness Pool"
  }
}
