{
  "geometry": {
    "type": "Point",
    "coordinates": [
      -93.7167,
      31.9667
    ]
  },
  "type": "Feature",
  "properties": {
    "hierarchy": [
      "tgn:2261982",
      "tgn:1000001",
      "tgn:7012149",
      "tgn:7007256",
      "tgn:7029392"
    ],
    "placetype": [
      "aat:300008699"
    ],
    "id": 2261982,
    "name:xx": "Cow Bayou"
  }
}
