{
  "geometry": {
    "type": "Point",
    "coordinates": [
      -120.5667,
      39.4833
    ]
  },
  "type": "Feature",
  "properties": {
    "hierarchy": [
      "tgn:2306457",
      "tgn:1000001",
      "tgn:7012149",
      "tgn:7007157",
      "tgn:7029392"
    ],
    "placetype": [
      "aat:300008706"
    ],
    "id": 2306457,
    "name:xx": "East Fork Creek"
  }
}
