{
  "geometry": {
    "type": "Point",
    "coordinates": [
      -72.0167,
      42.3667
    ]
  },
  "type": "Feature",
  "properties": {
    "hierarchy": [
      "tgn:2530726",
      "tgn:1000001",
      "tgn:7012149",
      "tgn:1003038",
      "tgn:7007517",
      "tgn:7029392"
    ],
    "placetype": [
      "aat:300008680"
    ],
    "id": 2530726,
    "name:xx": "Muddy Pond"
  }
}
