{
  "geometry": {
    "type": "Point",
    "coordinates": [
      -107.9333,
      39.3667
    ]
  },
  "type": "Feature",
  "properties": {
    "hierarchy": [
      "tgn:2151842",
      "tgn:1000001",
      "tgn:7012149",
      "tgn:2000214",
      "tgn:7007158",
      "tgn:7029392"
    ],
    "placetype": [
      "aat:300006191"
    ],
    "id": 2151842,
    "name:xx": "Battlement Number 3 Reservoir"
  }
}
