{
  "geometry": {
    "type": "Point",
    "coordinates": [
      28.083333,
      28.65
    ]
  },
  "type": "Feature",
  "properties": {
    "hierarchy": [
      "tgn:7534348",
      "tgn:7001242",
      "tgn:7016833",
      "tgn:1001418",
      "tgn:7029392"
    ],
    "placetype": [
      "aat:300008749"
    ],
    "name:en": "Jūdī, Minqār",
    "id": 7534348
  }
}
