{
  "geometry": {
    "type": "Point",
    "coordinates": [
      -86.4667,
      33.8833
    ]
  },
  "type": "Feature",
  "properties": {
    "hierarchy": [
      "tgn:2163157",
      "tgn:7002659",
      "tgn:1000001",
      "tgn:2000004",
      "tgn:7012149",
      "tgn:7029392"
    ],
    "placetype": [
      "aat:300000390"
    ],
    "id": 2163157,
    "name:xx": "Bennett Mine"
  }
}
