{
  "type": "FeatureCollection",
  "features": [
    {
      "geometry": {
        "type": "Point",
        "coordinates": [
          -79.4167,
          40.1167
        ]
      },
      "type": "Feature",
      "properties": {
        "hierarchy": [
          "tgn:2085860",
          "tgn:1000001",
          "tgn:7012149",
          "tgn:1003017",
          "tgn:7007710",
          "tgn:7029392"
        ],
        "placetype": [
          "aat:300008347"
        ],
        "id": 2085860,
        "name:xx": "Acme"
      }
    },
    {
      "geometry": {
        "type": "Point",
        "coordinates": [
          -79.8,
          40.5333
        ]
      },
      "type": "Feature",
      "properties": {
        "hierarchy": [
          "tgn:2085862",
          "tgn:7013272",
          "tgn:1000001",
          "tgn:7012149",
          "tgn:7007710",
          "tgn:7029392"
        ],
        "placetype": [
          "aat:300008347"
        ],
        "id": 2085862,
        "name:xx": "Acmetonia"
      }
    },
    {
      "geometry": {
        "type": "Point",
        "coordinates": [
          -79.0667,
          40.1
        ]
      },
      "type": "Feature",
      "properties": {
        "hierarchy": [
          "tgn:2085863",
          "tgn:1000001",
          "tgn:7012149",
          "tgn:1002904",
          "tgn:7007710",
          "tgn:7029392"
        ],
        "placetype": [
          "aat:300008347"
        ],
        "id": 2085863,
        "name:xx": "Acosta"
      }
    },
    {
      "geometry": {
        "type": "Point",
        "coordinates": [
          -75.7,
          41.7167
        ]
      },
      "type": "Feature",
      "properties": {
        "hierarchy": [
          "tgn:2085864",
          "tgn:1000001",
          "tgn:7012149",
          "tgn:1002932",
          "tgn:7007710",
          "tgn:7029392"
        ],
        "placetype": [
          "aat:300008680"
        ],
        "id": 2085864,
        "name:xx": "Acre Pond"
      }
    },
    {
      "geometry": {
        "type": "Point",
        "coordinates": [
          -79.9167,
          39.8833
        ]
      },
      "type": "Feature",
      "properties": {
        "hierarchy": [
          "tgn:2085865",
          "tgn:1000001",
          "tgn:7012149",
          "tgn:7014185",
          "tgn:7007710",
          "tgn:7029392"
        ],
        "placetype": [
          "aat:300008347"
        ],
        "id": 2085865,
        "name:xx": "Adah"
      }
    },
    {
      "geometry": {
        "type": "Point",
        "coordinates": [
          -79.6333,
          40.9333
        ]
      },
      "type": "Feature",
      "properties": {
        "hierarchy": [
          "tgn:2085866",
          "tgn:1002153",
          "tgn:1000001",
          "tgn:7012149",
          "tgn:7007710",
          "tgn:7029392"
        ],
        "placetype": [
          "aat:300008347"
        ],
        "id": 2085866,
        "name:xx": "Adams"
      }
    },
    {
      "geometry": {
        "type": "Point",
        "coordinates": [
          -79.65,
          40.3
        ]
      },
      "type": "Feature",
      "properties": {
        "hierarchy": [
          "tgn:2085868",
          "tgn:1000001",
          "tgn:7012149",
          "tgn:1003017",
          "tgn:7007710",
          "tgn:7029392"
        ],
        "placetype": [
          "aat:300008347"
        ],
        "id": 2085868,
        "name:xx": "Adamsburg"
      }
    }
  ]
}
