{
  "type": "FeatureCollection",
  "features": [
    {
      "geometry": {
        "type": "Point",
        "coordinates": [
          -80.7667,
          37.4833
        ]
      },
      "type": "Feature",
      "properties": {
        "hierarchy": [
          "tgn:2767533",
          "tgn:1000001",
          "tgn:7012149",
          "tgn:2002282",
          "tgn:7013961",
          "tgn:7029392"
        ],
        "placetype": [
          "aat:300008798"
        ],
        "id": 2767533,
        "name:xx": "White Tree Hill"
      }
    },
    {
      "geometry": {
        "type": "Point",
        "coordinates": [
          -82.4833,
          28.0333
        ]
      },
      "type": "Feature",
      "properties": {
        "hierarchy": [
          "tgn:2767534",
          "tgn:1000001",
          "tgn:1002479",
          "tgn:7012149",
          "tgn:7007240",
          "tgn:7029392"
        ],
        "placetype": [
          "aat:300008680"
        ],
        "id": 2767534,
        "name:xx": "White Trout Lake"
      }
    },
    {
      "geometry": {
        "type": "Point",
        "coordinates": [
          -110.2667,
          36.1333
        ]
      },
      "type": "Feature",
      "properties": {
        "hierarchy": [
          "tgn:2767535",
          "tgn:1000001",
          "tgn:7006451",
          "tgn:7012149",
          "tgn:2000099",
          "tgn:7029392"
        ],
        "placetype": [
          "aat:300008761"
        ],
        "id": 2767535,
        "name:xx": "White Valley"
      }
    },
    {
      "geometry": {
        "type": "Point",
        "coordinates": [
          -112.6167,
          42.2167
        ]
      },
      "type": "Feature",
      "properties": {
        "hierarchy": [
          "tgn:2767536",
          "tgn:1000001",
          "tgn:7012149",
          "tgn:2000487",
          "tgn:7007250",
          "tgn:7029392"
        ],
        "placetype": [
          "aat:300008761"
        ],
        "id": 2767536,
        "name:xx": "White Valley"
      }
    },
    {
      "geometry": {
        "type": "Point",
        "coordinates": [
          -72.0667,
          42.3833
        ]
      },
      "type": "Feature",
      "properties": {
        "hierarchy": [
          "tgn:2767537",
          "tgn:1000001",
          "tgn:7012149",
          "tgn:1003038",
          "tgn:7007517",
          "tgn:7029392"
        ],
        "placetype": [
          "aat:300008347"
        ],
        "id": 2767537,
        "name:xx": "White Valley"
      }
    },
    {
      "geometry": {
        "type": "Point",
        "coordinates": [
          -102.0167,
          42.4667
        ]
      },
      "type": "Feature",
      "properties": {
        "hierarchy": [
          "tgn:2767538",
          "tgn:1000001",
          "tgn:2001331",
          "tgn:7012149",
          "tgn:7007525",
          "tgn:7029392"
        ],
        "placetype": [
          "aat:300386845"
        ],
        "id": 2767538,
        "name:xx": "White Valley"
      }
    },
    {
      "geometry": {
        "type": "Point",
        "coordinates": [
          -114.4333,
          44.6
        ]
      },
      "type": "Feature",
      "properties": {
        "hierarchy": [
          "tgn:2767539",
          "tgn:1000001",
          "tgn:2000470",
          "tgn:7012149",
          "tgn:7007250",
          "tgn:7029392"
        ],
        "placetype": [
          "aat:300008706"
        ],
        "id": 2767539,
        "name:xx": "White Valley Creek"
      }
    }
  ]
}
