{
  "geometry": {
    "type": "Point",
    "coordinates": [
      -93.8667,
      39.0333
    ]
  },
  "type": "Feature",
  "properties": {
    "hierarchy": [
      "tgn:2199468",
      "tgn:1000001",
      "tgn:7012149",
      "tgn:2001212",
      "tgn:7007523",
      "tgn:7029392"
    ],
    "placetype": [
      "aat:300008706"
    ],
    "id": 2199468,
    "name:xx": "Brush Creek"
  }
}
