{
  "type": "FeatureCollection",
  "features": [
    {
      "geometry": {
        "type": "Point",
        "coordinates": [
          -3.1,
          56.116667
        ]
      },
      "type": "Feature",
      "properties": {
        "hierarchy": [
          "tgn:7445530",
          "tgn:7002444",
          "tgn:1000003",
          "tgn:7008076",
          "tgn:7008591",
          "tgn:7029392"
        ],
        "placetype": [
          "aat:300008808"
        ],
        "name:en": "Rockheads, The",
        "id": 7445530
      }
    },
    {
      "geometry": {
        "type": "Point",
        "coordinates": [
          -3.483333,
          55.05
        ]
      },
      "type": "Feature",
      "properties": {
        "hierarchy": [
          "tgn:7445531",
          "tgn:7002444",
          "tgn:7008074",
          "tgn:1000003",
          "tgn:7008591",
          "tgn:7029392"
        ],
        "placetype": [
          "aat:300387502"
        ],
        "name:en": "Rock Hall",
        "id": 7445531
      }
    },
    {
      "geometry": {
        "type": "Point",
        "coordinates": [
          -3.033333,
          53.433333
        ]
      },
      "type": "Feature",
      "properties": {
        "hierarchy": [
          "tgn:7445532",
          "tgn:7002445",
          "tgn:1003666",
          "tgn:1000003",
          "tgn:7029504",
          "tgn:7008591",
          "tgn:7029392"
        ],
        "placetype": [
          "aat:300006909"
        ],
        "name:en": "Rock Fort",
        "id": 7445532
      }
    },
    {
      "geometry": {
        "type": "Point",
        "coordinates": [
          -3.816667,
          57.816667
        ]
      },
      "type": "Feature",
      "properties": {
        "hierarchy": [
          "tgn:7445533",
          "tgn:7002444",
          "tgn:1000003",
          "tgn:7008082",
          "tgn:7008591",
          "tgn:7029392"
        ],
        "placetype": [
          "aat:300008347"
        ],
        "name:en": "Rockfield",
        "id": 7445533
      }
    },
    {
      "geometry": {
        "type": "Point",
        "coordinates": [
          -2.75,
          51.833333
        ]
      },
      "type": "Feature",
      "properties": {
        "hierarchy": [
          "tgn:7445534",
          "tgn:7002443",
          "tgn:1000003",
          "tgn:5000560",
          "tgn:7008591",
          "tgn:7029392"
        ],
        "placetype": [
          "aat:300008347"
        ],
        "name:en": "Rockfield",
        "id": 7445534
      }
    },
    {
      "geometry": {
        "type": "Point",
        "coordinates": [
          -1.5,
          55.133333
        ]
      },
      "type": "Feature",
      "properties": {
        "hierarchy": [
          "tgn:7445536",
          "tgn:7002445",
          "tgn:1000003",
          "tgn:7008165",
          "tgn:7008591",
          "tgn:7029392"
        ],
        "placetype": [
          "aat:300008808"
        ],
        "name:en": "Rockers, The",
        "id": 7445536
      }
    },
    {
      "geometry": {
        "type": "Point",
        "coordinates": [
          -6.8,
          54.6
        ]
      },
      "type": "Feature",
      "properties": {
        "hierarchy": [
          "tgn:7445537",
          "tgn:7002448",
          "tgn:7019204",
          "tgn:1000003",
          "tgn:7008591",
          "tgn:7029392"
        ],
        "placetype": [
          "aat:300387502"
        ],
        "name:en": "Rockdale House",
        "id": 7445537
      }
    },
    {
      "geometry": {
        "type": "Point",
        "coordinates": [
          -3.8,
          54.85
        ]
      },
      "type": "Feature",
      "properties": {
        "hierarchy": [
          "tgn:7445539",
          "tgn:7002444",
          "tgn:7008074",
          "tgn:1000003",
          "tgn:7008591",
          "tgn:7029392"
        ],
        "placetype": [
          "aat:300008347"
        ],
        "name:en": "Rockcliffe",
        "id": 7445539
      }
    }
  ]
}
