{
  "geometry": {
    "type": "Point",
    "coordinates": [
      -109.35,
      32.9667
    ]
  },
  "type": "Feature",
  "properties": {
    "hierarchy": [
      "tgn:2491772",
      "tgn:1000001",
      "tgn:7006451",
      "tgn:2000095",
      "tgn:7012149",
      "tgn:7029392"
    ],
    "placetype": [
      "aat:300008347"
    ],
    "id": 2491772,
    "name:xx": "Maques Place"
  }
}
