{
  "geometry": {
    "type": "Point",
    "coordinates": [
      -111.5833,
      36.8667
    ]
  },
  "type": "Feature",
  "properties": {
    "hierarchy": [
      "tgn:2231349",
      "tgn:1000001",
      "tgn:7006451",
      "tgn:2000092",
      "tgn:7012149",
      "tgn:7029392"
    ],
    "placetype": [
      "aat:300008347"
    ],
    "id": 2231349,
    "name:xx": "Chair Crossing"
  }
}
