{
  "geometry": {
    "type": "Point",
    "coordinates": [
      -105.9333,
      45.4333
    ]
  },
  "type": "Feature",
  "properties": {
    "hierarchy": [
      "tgn:2556915",
      "tgn:1000001",
      "tgn:7012149",
      "tgn:2001297",
      "tgn:7007524",
      "tgn:7029392"
    ],
    "placetype": [
      "aat:300008697"
    ],
    "id": 2556915,
    "name:xx": "Old Faithful Spring"
  }
}
