{
  "geometry": {
    "type": "Point",
    "coordinates": [
      -75.4333,
      39.45
    ]
  },
  "type": "Feature",
  "properties": {
    "hierarchy": [
      "tgn:2478418",
      "tgn:1000001",
      "tgn:7014449",
      "tgn:7012149",
      "tgn:7007565",
      "tgn:7029392"
    ],
    "placetype": [
      "aat:300008706"
    ],
    "id": 2478418,
    "name:xx": "Mad Horse Creek"
  }
}
