{
  "geometry": {
    "type": "Point",
    "coordinates": [
      -116.65,
      43.65
    ]
  },
  "type": "Feature",
  "properties": {
    "hierarchy": [
      "tgn:2124297",
      "tgn:1000001",
      "tgn:2000465",
      "tgn:7012149",
      "tgn:7007250",
      "tgn:7029392"
    ],
    "placetype": [
      "aat:300006075"
    ],
    "id": 2124297,
    "name:xx": "A Drain"
  }
}
