{
  "type": "FeatureCollection",
  "features": [
    {
      "geometry": {
        "type": "Point",
        "coordinates": [
          6.016667,
          51.5
        ]
      },
      "type": "Feature",
      "properties": {
        "hierarchy": [
          "tgn:7264520",
          "tgn:1000003",
          "tgn:7003622",
          "tgn:7016845",
          "tgn:7029392"
        ],
        "placetype": [
          "aat:300008347"
        ],
        "name:nl": "Hoogriebroek",
        "id": 7264520
      }
    },
    {
      "geometry": {
        "type": "Point",
        "coordinates": [
          5.116667,
          52.066667
        ]
      },
      "type": "Feature",
      "properties": {
        "hierarchy": [
          "tgn:7264521",
          "tgn:1000003",
          "tgn:7003627",
          "tgn:7016845",
          "tgn:7029392"
        ],
        "placetype": [
          "aat:300000745"
        ],
        "name:nl": "Hoograven",
        "id": 7264521
      }
    },
    {
      "geometry": {
        "type": "Point",
        "coordinates": [
          4.6,
          52.466667
        ]
      },
      "type": "Feature",
      "properties": {
        "hierarchy": [
          "tgn:7264522",
          "tgn:1000003",
          "tgn:7006951",
          "tgn:7016845",
          "tgn:7029392"
        ],
        "placetype": [
          "aat:300120801"
        ],
        "name:nl": "Hoogovenhaven",
        "id": 7264522
      }
    },
    {
      "geometry": {
        "type": "Point",
        "coordinates": [
          5,
          51.916667
        ]
      },
      "type": "Feature",
      "properties": {
        "hierarchy": [
          "tgn:7264523",
          "tgn:1000003",
          "tgn:7003632",
          "tgn:7016845",
          "tgn:7029392"
        ],
        "placetype": [
          "aat:300007836"
        ],
        "name:nl": "Kraneschipbrug",
        "id": 7264523
      }
    },
    {
      "geometry": {
        "type": "Point",
        "coordinates": [
          5.633333,
          51.4
        ]
      },
      "type": "Feature",
      "properties": {
        "hierarchy": [
          "tgn:7264524",
          "tgn:1000003",
          "tgn:7003624",
          "tgn:7016845",
          "tgn:7029392"
        ],
        "placetype": [
          "aat:300008680"
        ],
        "name:nl": "Kranenmeer",
        "id": 7264524
      }
    },
    {
      "geometry": {
        "type": "Point",
        "coordinates": [
          6.116667,
          52.55
        ]
      },
      "type": "Feature",
      "properties": {
        "hierarchy": [
          "tgn:7264525",
          "tgn:1000003",
          "tgn:7003626",
          "tgn:7016845",
          "tgn:7029392"
        ],
        "placetype": [
          "aat:300008688"
        ],
        "name:nl": "Kranenkolk",
        "id": 7264525
      }
    },
    {
      "geometry": {
        "type": "Point",
        "coordinates": [
          4.25,
          51.683333
        ]
      },
      "type": "Feature",
      "properties": {
        "hierarchy": [
          "tgn:7264526",
          "tgn:1000003",
          "tgn:7003632",
          "tgn:7016845",
          "tgn:7029392"
        ],
        "placetype": [
          "aat:300008347"
        ],
        "name:nl": "Kranendijk",
        "id": 7264526
      }
    },
    {
      "geometry": {
        "type": "Point",
        "coordinates": [
          6.366667,
          52.1
        ]
      },
      "type": "Feature",
      "properties": {
        "hierarchy": [
          "tgn:7264527",
          "tgn:7003619",
          "tgn:1000003",
          "tgn:7016845",
          "tgn:7029392"
        ],
        "placetype": [
          "aat:300008347"
        ],
        "name:nl": "Kranenburg",
        "id": 7264527
      }
    },
    {
      "geometry": {
        "type": "Point",
        "coordinates": [
          5.6,
          51.466667
        ]
      },
      "type": "Feature",
      "properties": {
        "hierarchy": [
          "tgn:7264528",
          "tgn:1000003",
          "tgn:7003624",
          "tgn:7016845",
          "tgn:7029392"
        ],
        "placetype": [
          "aat:300008347"
        ],
        "name:nl": "Kranenbroek",
        "id": 7264528
      }
    },
    {
      "geometry": {
        "type": "Point",
        "coordinates": [
          4.5,
          51.516667
        ]
      },
      "type": "Feature",
      "properties": {
        "hierarchy": [
          "tgn:7264529",
          "tgn:1000003",
          "tgn:7003624",
          "tgn:7016845",
          "tgn:7029392"
        ],
        "placetype": [
          "aat:300006075"
        ],
        "name:nl": "Krampenloop",
        "id": 7264529
      }
    }
  ]
}
