{
  "geometry": {
    "type": "Point",
    "coordinates": [
      -123.4667,
      43.0167
    ]
  },
  "type": "Feature",
  "properties": {
    "hierarchy": [
      "tgn:2212664",
      "tgn:1000001",
      "tgn:7012149",
      "tgn:2001706",
      "tgn:7007708",
      "tgn:7029392"
    ],
    "placetype": [
      "aat:300008706"
    ],
    "id": 2212664,
    "name:xx": "Byron Creek"
  }
}
