{
  "geometry": {
    "type": "Point",
    "coordinates": [
      -87.6833,
      35.55
    ]
  },
  "type": "Feature",
  "properties": {
    "hierarchy": [
      "tgn:2733633",
      "tgn:1000001",
      "tgn:7012149",
      "tgn:2001887",
      "tgn:7007825",
      "tgn:7029392"
    ],
    "placetype": [
      "aat:300008761"
    ],
    "id": 2733633,
    "name:xx": "Turnbow Hollow"
  }
}
