{
  "geometry": {
    "type": "Point",
    "coordinates": [
      -78.3667,
      39.0667
    ]
  },
  "type": "Feature",
  "properties": {
    "hierarchy": [
      "tgn:2115021",
      "tgn:1000001",
      "tgn:7012149",
      "tgn:2002190",
      "tgn:7007919",
      "tgn:7029392"
    ],
    "placetype": [
      "aat:300008347"
    ],
    "id": 2115021,
    "name:xx": "Wheatfield"
  }
}
