{
  "geometry": {
    "type": "Point",
    "coordinates": [
      -93.7833,
      40.9333
    ]
  },
  "type": "Feature",
  "properties": {
    "hierarchy": [
      "tgn:2445842",
      "tgn:1000001",
      "tgn:7019178",
      "tgn:7012149",
      "tgn:7007253",
      "tgn:7029392"
    ],
    "placetype": [
      "aat:300008347"
    ],
    "id": 2445842,
    "name:xx": "Leslie"
  }
}
