{
  "geometry": {
    "type": "Point",
    "coordinates": [
      -123.5667,
      45.15
    ]
  },
  "type": "Feature",
  "properties": {
    "hierarchy": [
      "tgn:2210114",
      "tgn:1000001",
      "tgn:7012149",
      "tgn:1003044",
      "tgn:7007708",
      "tgn:7029392"
    ],
    "placetype": [
      "aat:300266640"
    ],
    "id": 2210114,
    "name:xx": "Burton Ridge"
  }
}
