{
  "geometry": {
    "type": "Point",
    "coordinates": [
      -74.2833,
      43.2833
    ]
  },
  "type": "Feature",
  "properties": {
    "hierarchy": [
      "tgn:1104170",
      "tgn:1000001",
      "tgn:7012149",
      "tgn:1002440",
      "tgn:7007568",
      "tgn:7029392"
    ],
    "placetype": [
      "aat:300008795"
    ],
    "id": 1104170,
    "name:xx": "Cathead Mountain"
  }
}
