{
  "geometry": {
    "type": "Point",
    "coordinates": [
      -111.7333,
      46.2667
    ]
  },
  "type": "Feature",
  "properties": {
    "hierarchy": [
      "tgn:2128733",
      "tgn:1000001",
      "tgn:2001263",
      "tgn:7012149",
      "tgn:7007524",
      "tgn:7029392"
    ],
    "placetype": [
      "aat:300008697"
    ],
    "id": 2128733,
    "name:xx": "Aldrich Spring"
  }
}
