{
  "geometry": {
    "type": "Point",
    "coordinates": [
      113.35,
      -8.1167
    ]
  },
  "type": "Feature",
  "properties": {
    "hierarchy": [
      "tgn:1077742",
      "tgn:1000004",
      "tgn:1001323",
      "tgn:1000116",
      "tgn:7029392"
    ],
    "placetype": [
      "aat:300008347"
    ],
    "id": 1077742,
    "name:xx": "Jatiroto"
  }
}
