{
  "geometry": {
    "type": "Point",
    "coordinates": [
      -98.0667,
      48.4167
    ]
  },
  "type": "Feature",
  "properties": {
    "hierarchy": [
      "tgn:2077375",
      "tgn:1000001",
      "tgn:7012149",
      "tgn:2001606",
      "tgn:7007705",
      "tgn:7029392"
    ],
    "placetype": [
      "aat:300008347"
    ],
    "id": 2077375,
    "name:xx": "Adams"
  }
}
