{
  "type": "FeatureCollection",
  "features": [
    {
      "geometry": {
        "type": "Point",
        "coordinates": [
          -90.2167,
          29.9
        ]
      },
      "type": "Feature",
      "properties": {
        "hierarchy": [
          "tgn:2043130",
          "tgn:1000001",
          "tgn:7012149",
          "tgn:2000879",
          "tgn:7007256",
          "tgn:7029392"
        ],
        "placetype": [
          "aat:300008347"
        ],
        "id": 2043130,
        "name:xx": "Kennedy Heights"
      }
    },
    {
      "geometry": {
        "type": "Point",
        "coordinates": [
          -90.2333,
          29.9833
        ]
      },
      "type": "Feature",
      "properties": {
        "hierarchy": [
          "tgn:2043131",
          "tgn:1000001",
          "tgn:7012149",
          "tgn:2000879",
          "tgn:7007256",
          "tgn:7029392"
        ],
        "placetype": [
          "aat:300008347"
        ],
        "id": 2043131,
        "name:xx": "Kenner"
      }
    }
  ]
}
