{
  "type": "FeatureCollection",
  "features": [
    {
      "geometry": {
        "type": "Point",
        "coordinates": [
          -2.7,
          41.2
        ]
      },
      "type": "Feature",
      "properties": {
        "hierarchy": [
          "tgn:7323941",
          "tgn:7002822",
          "tgn:1001647",
          "tgn:1000003",
          "tgn:1000095",
          "tgn:7029392"
        ],
        "placetype": [
          "aat:300008347"
        ],
        "id": 7323941,
        "name:xx": "Riba de Santiuste"
      }
    },
    {
      "geometry": {
        "type": "Point",
        "coordinates": [
          -2.283333,
          40.916667
        ]
      },
      "type": "Feature",
      "properties": {
        "hierarchy": [
          "tgn:7323942",
          "tgn:7002822",
          "tgn:1001647",
          "tgn:1000003",
          "tgn:1000095",
          "tgn:7029392"
        ],
        "placetype": [
          "aat:300008347"
        ],
        "id": 7323942,
        "name:xx": "Riba de Saelices"
      }
    },
    {
      "geometry": {
        "type": "Point",
        "coordinates": [
          -7.033333,
          43.55
        ]
      },
      "type": "Feature",
      "properties": {
        "hierarchy": [
          "tgn:7323943",
          "tgn:7002829",
          "tgn:1000003",
          "tgn:7002786",
          "tgn:1000095",
          "tgn:7029392"
        ],
        "placetype": [
          "aat:300266571"
        ],
        "id": 7323943,
        "name:xx": "Ribadeo, Ría de"
      }
    },
    {
      "geometry": {
        "type": "Point",
        "coordinates": [
          -7.3,
          42.883333
        ]
      },
      "type": "Feature",
      "properties": {
        "hierarchy": [
          "tgn:7323945",
          "tgn:7002829",
          "tgn:1000003",
          "tgn:7002786",
          "tgn:1000095",
          "tgn:7029392"
        ],
        "placetype": [
          "aat:300008347"
        ],
        "id": 7323945,
        "name:xx": "Riba de Neira"
      }
    },
    {
      "geometry": {
        "type": "Point",
        "coordinates": [
          -8.633333,
          42.1
        ]
      },
      "type": "Feature",
      "properties": {
        "hierarchy": [
          "tgn:7323946",
          "tgn:7002834",
          "tgn:1000003",
          "tgn:7002786",
          "tgn:1000095",
          "tgn:7029392"
        ],
        "placetype": [
          "aat:300008347"
        ],
        "id": 7323946,
        "name:xx": "Ribadelouro"
      }
    },
    {
      "geometry": {
        "type": "Point",
        "coordinates": [
          -6.75,
          42.133333
        ]
      },
      "type": "Feature",
      "properties": {
        "hierarchy": [
          "tgn:7323947",
          "tgn:7001158",
          "tgn:7002850",
          "tgn:1000003",
          "tgn:1000095",
          "tgn:7029392"
        ],
        "placetype": [
          "aat:300008347"
        ],
        "id": 7323947,
        "name:xx": "Ribadelago"
      }
    },
    {
      "geometry": {
        "type": "Point",
        "coordinates": [
          -2.917996,
          42.711885
        ]
      },
      "type": "Feature",
      "properties": {
        "hierarchy": [
          "tgn:7323949",
          "tgn:7007088",
          "tgn:1000003",
          "tgn:7009604",
          "tgn:1000095",
          "tgn:7029392"
        ],
        "placetype": [
          "aat:300008347"
        ],
        "id": 7323949,
        "name:xx": "Ribabellosa"
      }
    }
  ]
}
