{
  "geometry": {
    "type": "Point",
    "coordinates": [
      -112.9167,
      48.8167
    ]
  },
  "type": "Feature",
  "properties": {
    "hierarchy": [
      "tgn:2610402",
      "tgn:1000001",
      "tgn:7012149",
      "tgn:2001277",
      "tgn:7007524",
      "tgn:7029392"
    ],
    "placetype": [
      "aat:300008798"
    ],
    "id": 2610402,
    "name:xx": "Red Buttes"
  }
}
