{
  "geometry": {
    "type": "Point",
    "coordinates": [
      -121.7167,
      46.8167
    ]
  },
  "type": "Feature",
  "properties": {
    "hierarchy": [
      "tgn:2522337",
      "tgn:1000001",
      "tgn:7012149",
      "tgn:1002785",
      "tgn:7007920",
      "tgn:7029392"
    ],
    "placetype": [
      "aat:300266640"
    ],
    "id": 2522337,
    "name:xx": "Moon Rocks"
  }
}
