{
  "geometry": {
    "type": "Point",
    "coordinates": [
      -84.05,
      40.4167
    ]
  },
  "type": "Feature",
  "properties": {
    "hierarchy": [
      "tgn:2417568",
      "tgn:1000001",
      "tgn:7012149",
      "tgn:1002889",
      "tgn:7007706",
      "tgn:7029392"
    ],
    "placetype": [
      "aat:300008706"
    ],
    "id": 2417568,
    "name:xx": "Jackson Center Creek"
  }
}
