{
  "geometry": {
    "type": "Point",
    "coordinates": [
      -77.4333,
      37.8833
    ]
  },
  "type": "Feature",
  "properties": {
    "hierarchy": [
      "tgn:2222301",
      "tgn:1000001",
      "tgn:1002235",
      "tgn:7012149",
      "tgn:7007919",
      "tgn:7029392"
    ],
    "placetype": [
      "aat:300008347"
    ],
    "id": 2222301,
    "name:xx": "Caroline Pines"
  }
}
