{
  "geometry": {
    "type": "Point",
    "coordinates": [
      23.266515,
      37.44689
    ]
  },
  "type": "Feature",
  "properties": {
    "hierarchy": [
      "tgn:7232924",
      "tgn:7002681",
      "tgn:7001395",
      "tgn:1000003",
      "tgn:1000074",
      "tgn:7029392"
    ],
    "placetype": [
      "aat:300008347"
    ],
    "id": 7232924,
    "name:xx": "Iliókastron"
  }
}
