{
  "geometry": {
    "type": "Point",
    "coordinates": [
      -85.2833,
      39.1667
    ]
  },
  "type": "Feature",
  "properties": {
    "hierarchy": [
      "tgn:2421063",
      "tgn:1000001",
      "tgn:7012149",
      "tgn:1002827",
      "tgn:7007252",
      "tgn:7029392"
    ],
    "placetype": [
      "aat:300008706"
    ],
    "id": 2421063,
    "name:xx": "Jericho Creek"
  }
}
