{
  "geometry": {
    "type": "Point",
    "coordinates": [
      -89.6667,
      40.7667
    ]
  },
  "type": "Feature",
  "properties": {
    "hierarchy": [
      "tgn:2477275",
      "tgn:1000001",
      "tgn:7012149",
      "tgn:2000521",
      "tgn:7007251",
      "tgn:7029392"
    ],
    "placetype": [
      "aat:300006191"
    ],
    "id": 2477275,
    "name:xx": "Lynnhurst, Lake"
  }
}
