{
  "geometry": {
    "type": "Point",
    "coordinates": [
      -121.0167,
      44.55
    ]
  },
  "type": "Feature",
  "properties": {
    "hierarchy": [
      "tgn:2174529",
      "tgn:1000001",
      "tgn:7012149",
      "tgn:2001712",
      "tgn:7007708",
      "tgn:7029392"
    ],
    "placetype": [
      "aat:300008697"
    ],
    "id": 2174529,
    "name:xx": "Bishop Spring"
  }
}
