{
  "geometry": {
    "type": "Point",
    "coordinates": [
      -1.0833,
      49.3333
    ]
  },
  "type": "Feature",
  "properties": {
    "hierarchy": [
      "tgn:1131489",
      "tgn:7002872",
      "tgn:1000003",
      "tgn:1000070",
      "tgn:7029392"
    ],
    "placetype": [
      "aat:300008707"
    ],
    "id": 1131489,
    "name:xx": "Vire"
  }
}
