{
  "geometry": {
    "type": "Point",
    "coordinates": [
      -147.8667,
      60.3167
    ]
  },
  "type": "Feature",
  "properties": {
    "hierarchy": [
      "tgn:2626746",
      "tgn:7006450",
      "tgn:1000001",
      "tgn:7012149",
      "tgn:2000086",
      "tgn:7029392"
    ],
    "placetype": [
      "aat:300008850"
    ],
    "id": 2626746,
    "name:xx": "Rocky Point"
  }
}
