{
  "type": "FeatureCollection",
  "features": [
    {
      "geometry": {
        "type": "Point",
        "coordinates": [
          1.5,
          45.1667
        ]
      },
      "type": "Feature",
      "properties": {
        "hierarchy": [
          "tgn:1123070",
          "tgn:1000003",
          "tgn:7001095",
          "tgn:1000070",
          "tgn:7029392"
        ],
        "placetype": [
          "aat:300008707"
        ],
        "id": 1123070,
        "name:xx": "Corrèze"
      }
    },
    {
      "geometry": {
        "type": "Point",
        "coordinates": [
          -42.1833,
          -4.3
        ]
      },
      "type": "Feature",
      "properties": {
        "hierarchy": [
          "tgn:1123071",
          "tgn:1001834",
          "tgn:1000047",
          "tgn:7002455",
          "tgn:1000002",
          "tgn:7029392"
        ],
        "placetype": [
          "aat:300008707"
        ],
        "id": 1123071,
        "name:xx": "Corrente"
      }
    },
    {
      "geometry": {
        "type": "Point",
        "coordinates": [
          -55.1333,
          -17.6333
        ]
      },
      "type": "Feature",
      "properties": {
        "hierarchy": [
          "tgn:1123072",
          "tgn:7006252",
          "tgn:1000047",
          "tgn:7002455",
          "tgn:1000002",
          "tgn:7029392"
        ],
        "placetype": [
          "aat:300008707"
        ],
        "id": 1123072,
        "name:xx": "Correntes"
      }
    },
    {
      "geometry": {
        "type": "Point",
        "coordinates": [
          -58.8,
          -27.5
        ]
      },
      "type": "Feature",
      "properties": {
        "hierarchy": [
          "tgn:1123073",
          "tgn:7006477",
          "tgn:1001210",
          "tgn:1000002",
          "tgn:7029392"
        ],
        "placetype": [
          "aat:300008707"
        ],
        "id": 1123073,
        "name:xx": "Corrientes"
      }
    },
    {
      "geometry": {
        "type": "Point",
        "coordinates": [
          -74.6667,
          -3.6667
        ]
      },
      "type": "Feature",
      "properties": {
        "hierarchy": [
          "tgn:1123074",
          "tgn:1000002",
          "tgn:7029392"
        ],
        "placetype": [
          "aat:300008707"
        ],
        "id": 1123074,
        "name:xx": "Corrientes"
      }
    },
    {
      "geometry": {
        "type": "Point",
        "coordinates": [
          -43.4167,
          -23
        ]
      },
      "type": "Feature",
      "properties": {
        "hierarchy": [
          "tgn:1123075",
          "tgn:1001942",
          "tgn:1000047",
          "tgn:7002457",
          "tgn:1000002",
          "tgn:7017095",
          "tgn:7029392"
        ],
        "placetype": [
          "aat:300008707"
        ],
        "id": 1123075,
        "name:xx": "Cortado, Rio do"
      }
    },
    {
      "geometry": {
        "type": "Point",
        "coordinates": [
          -48.9167,
          -18.3167
        ]
      },
      "type": "Feature",
      "properties": {
        "hierarchy": [
          "tgn:1123077",
          "tgn:7012827",
          "tgn:7002454",
          "tgn:1000047",
          "tgn:1000002",
          "tgn:7029392"
        ],
        "placetype": [
          "aat:300008707"
        ],
        "id": 1123077,
        "name:xx": "Corumbá"
      }
    },
    {
      "geometry": {
        "type": "Point",
        "coordinates": [
          -51.95,
          -23.9167
        ]
      },
      "type": "Feature",
      "properties": {
        "hierarchy": [
          "tgn:1123078",
          "tgn:1001925",
          "tgn:1000047",
          "tgn:7002458",
          "tgn:1000002",
          "tgn:7029392"
        ],
        "placetype": [
          "aat:300008707"
        ],
        "id": 1123078,
        "name:xx": "Corumbataí"
      }
    },
    {
      "geometry": {
        "type": "Point",
        "coordinates": [
          -62.1,
          -13.2167
        ]
      },
      "type": "Feature",
      "properties": {
        "hierarchy": [
          "tgn:1123079",
          "tgn:1001944",
          "tgn:1000047",
          "tgn:7002456",
          "tgn:1000002",
          "tgn:7029392"
        ],
        "placetype": [
          "aat:300008707"
        ],
        "id": 1123079,
        "name:xx": "Corumbiara"
      }
    }
  ]
}
