{
  "geometry": {
    "type": "Point",
    "coordinates": [
      83.9167,
      57.3333
    ]
  },
  "type": "Feature",
  "properties": {
    "hierarchy": [
      "tgn:1055928",
      "tgn:1000004",
      "tgn:7011604",
      "tgn:7018214",
      "tgn:7002435",
      "tgn:7029392"
    ],
    "placetype": [
      "aat:300008347"
    ],
    "id": 1055928,
    "name:xx": "Krivosheino"
  }
}
