{
  "geometry": {
    "type": "Point",
    "coordinates": [
      -87.2167,
      34.5833
    ]
  },
  "type": "Feature",
  "properties": {
    "hierarchy": [
      "tgn:2330892",
      "tgn:7002659",
      "tgn:1000001",
      "tgn:7012149",
      "tgn:2000039",
      "tgn:7029392"
    ],
    "placetype": [
      "aat:300008798"
    ],
    "id": 2330892,
    "name:xx": "Flat Rock"
  }
}
