{
  "geometry": {
    "type": "Point",
    "coordinates": [
      -97.75,
      32.5667
    ]
  },
  "type": "Feature",
  "properties": {
    "hierarchy": [
      "tgn:2529027",
      "tgn:1000001",
      "tgn:7012149",
      "tgn:1002771",
      "tgn:7007826",
      "tgn:7029392"
    ],
    "placetype": [
      "aat:300008706"
    ],
    "id": 2529027,
    "name:xx": "Mud Creek"
  }
}
