{
  "geometry": {
    "type": "Point",
    "coordinates": [
      -89.2833,
      37.6333
    ]
  },
  "type": "Feature",
  "properties": {
    "hierarchy": [
      "tgn:2302342",
      "tgn:1000001",
      "tgn:7012149",
      "tgn:2000512",
      "tgn:7007251",
      "tgn:7029392"
    ],
    "placetype": [
      "aat:300266640"
    ],
    "id": 2302342,
    "name:xx": "Dutch Ridge"
  }
}
