{
  "geometry": {
    "type": "Point",
    "coordinates": [
      -83.05,
      41.4167
    ]
  },
  "type": "Feature",
  "properties": {
    "hierarchy": [
      "tgn:2082588",
      "tgn:1000001",
      "tgn:7012149",
      "tgn:1002865",
      "tgn:7007706",
      "tgn:7029392"
    ],
    "placetype": [
      "aat:300008347"
    ],
    "id": 2082588,
    "name:xx": "Wightmans Grove"
  }
}
