{
  "geometry": {
    "type": "Point",
    "coordinates": [
      -79.0667,
      35.8667
    ]
  },
  "type": "Feature",
  "properties": {
    "hierarchy": [
      "tgn:2322785",
      "tgn:1000001",
      "tgn:7012149",
      "tgn:2001525",
      "tgn:7007709",
      "tgn:7029392"
    ],
    "placetype": [
      "aat:300008699"
    ],
    "id": 2322785,
    "name:xx": "Fan Branch"
  }
}
