{
  "geometry": {
    "type": "Point",
    "coordinates": [
      -87.9167,
      30.7833
    ]
  },
  "type": "Feature",
  "properties": {
    "hierarchy": [
      "tgn:2361762",
      "tgn:2000001",
      "tgn:7002659",
      "tgn:1000001",
      "tgn:7012149",
      "tgn:7029392"
    ],
    "placetype": [
      "aat:300008791"
    ],
    "id": 2361762,
    "name:xx": "Gravine Island"
  }
}
