{
  "type": "FeatureCollection",
  "features": [
    {
      "geometry": {
        "type": "Point",
        "coordinates": [
          -75.116667,
          -51.533333
        ]
      },
      "type": "Feature",
      "properties": {
        "hierarchy": [
          "tgn:7291430",
          "tgn:1001702",
          "tgn:1000049",
          "tgn:1000002",
          "tgn:7029392"
        ],
        "placetype": [
          "aat:300387026"
        ],
        "id": 7291430,
        "name:xx": "Errázuriz, Paso"
      }
    },
    {
      "geometry": {
        "type": "Point",
        "coordinates": [
          -73.833333,
          -45.6
        ]
      },
      "type": "Feature",
      "properties": {
        "hierarchy": [
          "tgn:7291431",
          "tgn:1001623",
          "tgn:1000049",
          "tgn:1000002",
          "tgn:7029392"
        ],
        "placetype": [
          "aat:300387026"
        ],
        "id": 7291431,
        "name:xx": "Errázuriz, Canal"
      }
    },
    {
      "geometry": {
        "type": "Point",
        "coordinates": [
          -70.6,
          -23.466667
        ]
      },
      "type": "Feature",
      "properties": {
        "hierarchy": [
          "tgn:7291432",
          "tgn:7016598",
          "tgn:1000049",
          "tgn:1000002",
          "tgn:7029392"
        ],
        "placetype": [
          "aat:300132317"
        ],
        "id": 7291432,
        "name:xx": "Errázuriz, Caleta"
      }
    },
    {
      "geometry": {
        "type": "Point",
        "coordinates": [
          -73.55,
          -43.266667
        ]
      },
      "type": "Feature",
      "properties": {
        "hierarchy": [
          "tgn:7291433",
          "tgn:1001699",
          "tgn:1000049",
          "tgn:1000002",
          "tgn:7029392"
        ],
        "placetype": [
          "aat:300387036"
        ],
        "id": 7291433,
        "name:xx": "Errázuriz, Bajo"
      }
    },
    {
      "geometry": {
        "type": "Point",
        "coordinates": [
          -70.733333,
          -33.5
        ]
      },
      "type": "Feature",
      "properties": {
        "hierarchy": [
          "tgn:7291434",
          "tgn:1001708",
          "tgn:1000049",
          "tgn:1000002",
          "tgn:7029392"
        ],
        "placetype": [
          "aat:300008347"
        ],
        "id": 7291434,
        "name:xx": "Errázuriz"
      }
    },
    {
      "geometry": {
        "type": "Point",
        "coordinates": [
          -74.383333,
          -47.8
        ]
      },
      "type": "Feature",
      "properties": {
        "hierarchy": [
          "tgn:7291435",
          "tgn:1001623",
          "tgn:1000049",
          "tgn:1000002",
          "tgn:7029392"
        ],
        "placetype": [
          "aat:300386846"
        ],
        "id": 7291435,
        "name:xx": "Eros, Punta"
      }
    },
    {
      "geometry": {
        "type": "Point",
        "coordinates": [
          -71.966667,
          -53.083333
        ]
      },
      "type": "Feature",
      "properties": {
        "hierarchy": [
          "tgn:7291436",
          "tgn:1001702",
          "tgn:1000049",
          "tgn:1000002",
          "tgn:7029392"
        ],
        "placetype": [
          "aat:300008791"
        ],
        "id": 7291436,
        "name:xx": "Eros, Islotes"
      }
    },
    {
      "geometry": {
        "type": "Point",
        "coordinates": [
          -70.883333,
          -54.333333
        ]
      },
      "type": "Feature",
      "properties": {
        "hierarchy": [
          "tgn:7291437",
          "tgn:1001702",
          "tgn:1000049",
          "tgn:1000002",
          "tgn:7029392"
        ],
        "placetype": [
          "aat:300386846"
        ],
        "id": 7291437,
        "name:xx": "Ernesto, Punta"
      }
    },
    {
      "geometry": {
        "type": "Point",
        "coordinates": [
          -72.366667,
          -54.05
        ]
      },
      "type": "Feature",
      "properties": {
        "hierarchy": [
          "tgn:7291438",
          "tgn:1001702",
          "tgn:1000049",
          "tgn:1000002",
          "tgn:7029392"
        ],
        "placetype": [
          "aat:300386846"
        ],
        "id": 7291438,
        "name:xx": "Ernesto, Punta"
      }
    },
    {
      "geometry": {
        "type": "Point",
        "coordinates": [
          -75.3,
          -48.75
        ]
      },
      "type": "Feature",
      "properties": {
        "hierarchy": [
          "tgn:7291439",
          "tgn:1001623",
          "tgn:1000049",
          "tgn:1000002",
          "tgn:7029392"
        ],
        "placetype": [
          "aat:300008791"
        ],
        "id": 7291439,
        "name:xx": "Ernesto, Isla"
      }
    }
  ]
}
