{
  "geometry": {
    "type": "Point",
    "coordinates": [
      -103.9667,
      31.6333
    ]
  },
  "type": "Feature",
  "properties": {
    "hierarchy": [
      "tgn:2720156",
      "tgn:1000001",
      "tgn:7012149",
      "tgn:2002062",
      "tgn:7007826",
      "tgn:7029392"
    ],
    "placetype": [
      "aat:300008761"
    ],
    "id": 2720156,
    "name:xx": "Threemile Draw"
  }
}
