{
  "type": "FeatureCollection",
  "features": [
    {
      "geometry": {
        "type": "Point",
        "coordinates": [
          120.313333,
          22.879722
        ]
      },
      "type": "Feature",
      "properties": {
        "hierarchy": [
          "tgn:7470250",
          "tgn:1000004",
          "tgn:7490934",
          "tgn:1000141",
          "tgn:7029392"
        ],
        "placetype": [
          "aat:300008347"
        ],
        "id": 7470250,
        "name:xx": "Zhuzijiao"
      }
    },
    {
      "geometry": {
        "type": "Point",
        "coordinates": [
          121.133333,
          24.716667
        ]
      },
      "type": "Feature",
      "properties": {
        "hierarchy": [
          "tgn:7470251",
          "tgn:1000004",
          "tgn:7471332",
          "tgn:1000141",
          "tgn:7029392"
        ],
        "placetype": [
          "aat:300387173"
        ],
        "id": 7470251,
        "name:xx": "Hengshan Xiang"
      }
    },
    {
      "geometry": {
        "type": "Point",
        "coordinates": [
          121.129722,
          24.791111
        ]
      },
      "type": "Feature",
      "properties": {
        "hierarchy": [
          "tgn:7470252",
          "tgn:1000004",
          "tgn:7471332",
          "tgn:1000141",
          "tgn:7029392"
        ],
        "placetype": [
          "aat:300008347"
        ],
        "id": 7470252,
        "name:xx": "Hengshan"
      }
    },
    {
      "geometry": {
        "type": "Point",
        "coordinates": [
          121.212979,
          25.030939
        ]
      },
      "type": "Feature",
      "properties": {
        "hierarchy": [
          "tgn:7470254",
          "tgn:1000004",
          "tgn:7001013",
          "tgn:1000141",
          "tgn:7029392"
        ],
        "placetype": [
          "aat:300008347"
        ],
        "id": 7470254,
        "name:xx": "Hengshan"
      }
    },
    {
      "geometry": {
        "type": "Point",
        "coordinates": [
          121.766194,
          24.441995
        ]
      },
      "type": "Feature",
      "properties": {
        "hierarchy": [
          "tgn:7470256",
          "tgn:1000004",
          "tgn:7489179",
          "tgn:1000141",
          "tgn:7029392"
        ],
        "placetype": [
          "aat:300008347"
        ],
        "id": 7470256,
        "name:xx": "Hengshan"
      }
    },
    {
      "geometry": {
        "type": "Point",
        "coordinates": [
          120.629509,
          24.20965
        ]
      },
      "type": "Feature",
      "properties": {
        "hierarchy": [
          "tgn:7470257",
          "tgn:1000004",
          "tgn:7001009",
          "tgn:1000141",
          "tgn:7029392"
        ],
        "placetype": [
          "aat:300008347"
        ],
        "id": 7470257,
        "name:xx": "Shanghengshan"
      }
    },
    {
      "geometry": {
        "type": "Point",
        "coordinates": [
          120.638984,
          23.893282
        ]
      },
      "type": "Feature",
      "properties": {
        "hierarchy": [
          "tgn:7470258",
          "tgn:7488858",
          "tgn:1000004",
          "tgn:1000141",
          "tgn:7029392"
        ],
        "placetype": [
          "aat:300008347"
        ],
        "id": 7470258,
        "name:xx": "Hengshan"
      }
    },
    {
      "geometry": {
        "type": "Point",
        "coordinates": [
          120.463056,
          22.961389
        ]
      },
      "type": "Feature",
      "properties": {
        "hierarchy": [
          "tgn:7470259",
          "tgn:7001004",
          "tgn:1000004",
          "tgn:1000141",
          "tgn:7029392"
        ],
        "placetype": [
          "aat:300008347"
        ],
        "id": 7470259,
        "name:xx": "Hengshan"
      }
    }
  ]
}
