{
  "geometry": {
    "type": "Point",
    "coordinates": [
      -91.5833,
      42.8833
    ]
  },
  "type": "Feature",
  "properties": {
    "hierarchy": [
      "tgn:2390285",
      "tgn:1000001",
      "tgn:2000582",
      "tgn:7012149",
      "tgn:7007253",
      "tgn:7029392"
    ],
    "placetype": [
      "aat:300008347"
    ],
    "id": 2390285,
    "name:xx": "Highland"
  }
}
