{
  "geometry": {
    "type": "Point",
    "coordinates": [
      -84.55,
      38.5833
    ]
  },
  "type": "Feature",
  "properties": {
    "hierarchy": [
      "tgn:2659703",
      "tgn:1000001",
      "tgn:7012149",
      "tgn:1002417",
      "tgn:7007255",
      "tgn:7029392"
    ],
    "placetype": [
      "aat:300008706"
    ],
    "id": 2659703,
    "name:xx": "Shinkle Creek"
  }
}
