{
  "geometry": {
    "type": "Point",
    "coordinates": [
      -81.0833,
      28.2167
    ]
  },
  "type": "Feature",
  "properties": {
    "hierarchy": [
      "tgn:2225855",
      "tgn:1000001",
      "tgn:7012149",
      "tgn:1002756",
      "tgn:7007240",
      "tgn:7029392"
    ],
    "placetype": [
      "aat:300008905"
    ],
    "id": 2225855,
    "name:xx": "Cat Island Swamp"
  }
}
