{
  "geometry": {
    "type": "Point",
    "coordinates": [
      31.01225,
      29.139434
    ]
  },
  "type": "Feature",
  "properties": {
    "hierarchy": [
      "tgn:7525263",
      "tgn:7001242",
      "tgn:7001105",
      "tgn:7016833",
      "tgn:7029392"
    ],
    "placetype": [
      "aat:300008347"
    ],
    "name:en": "Bāhā",
    "id": 7525263
  }
}
