{
  "geometry": {
    "type": "Point",
    "coordinates": [
      -86.6667,
      33.8167
    ]
  },
  "type": "Feature",
  "properties": {
    "hierarchy": [
      "tgn:2005245",
      "tgn:7002659",
      "tgn:1000001",
      "tgn:2000004",
      "tgn:7012149",
      "tgn:7029392"
    ],
    "placetype": [
      "aat:300008347"
    ],
    "id": 2005245,
    "name:xx": "Selfville"
  }
}
