{
  "geometry": {
    "type": "Point",
    "coordinates": [
      16.6333,
      59.9167
    ]
  },
  "type": "Feature",
  "properties": {
    "hierarchy": [
      "tgn:1063557",
      "tgn:1000003",
      "tgn:7003780",
      "tgn:1000097",
      "tgn:7029392"
    ],
    "placetype": [
      "aat:300008347"
    ],
    "id": 1063557,
    "name:xx": "Sala"
  }
}
