{
  "geometry": {
    "type": "Point",
    "coordinates": [
      -110.2833,
      32.5167
    ]
  },
  "type": "Feature",
  "properties": {
    "hierarchy": [
      "tgn:2491617",
      "tgn:1000001",
      "tgn:7006451",
      "tgn:2000094",
      "tgn:7012149",
      "tgn:7029392"
    ],
    "placetype": [
      "aat:300008697"
    ],
    "id": 2491617,
    "name:xx": "Maple Spring"
  }
}
