{
  "geometry": {
    "type": "Point",
    "coordinates": [
      4.1667,
      46.1667
    ]
  },
  "type": "Feature",
  "properties": {
    "hierarchy": [
      "tgn:7008758",
      "tgn:1000003",
      "tgn:1000070",
      "tgn:7002897",
      "tgn:7029392"
    ],
    "placetype": [
      "aat:300008347"
    ],
    "id": 7008758,
    "name:xx": "Charlieu"
  }
}
