{
  "geometry": {
    "type": "Point",
    "coordinates": [
      -90.0333,
      32.0833
    ]
  },
  "type": "Feature",
  "properties": {
    "hierarchy": [
      "tgn:2057540",
      "tgn:1000001",
      "tgn:7012149",
      "tgn:2001146",
      "tgn:7007522",
      "tgn:7029392"
    ],
    "placetype": [
      "aat:300008347"
    ],
    "id": 2057540,
    "name:xx": "Star"
  }
}
