{
  "geometry": {
    "type": "Point",
    "coordinates": [
      -88.2833,
      31.6833
    ]
  },
  "type": "Feature",
  "properties": {
    "hierarchy": [
      "tgn:2461940",
      "tgn:7002659",
      "tgn:1000001",
      "tgn:7012149",
      "tgn:7029392"
    ],
    "placetype": [
      "aat:300008706"
    ],
    "id": 2461940,
    "name:xx": "Little Turkey Creek"
  }
}
