{
  "type": "FeatureCollection",
  "features": [
    {
      "geometry": {
        "type": "Point",
        "coordinates": [
          -89.2167,
          31.2667
        ]
      },
      "type": "Feature",
      "properties": {
        "hierarchy": [
          "tgn:2665170",
          "tgn:1000001",
          "tgn:7012149",
          "tgn:2001103",
          "tgn:7007522",
          "tgn:7029392"
        ],
        "placetype": [
          "aat:300008680"
        ],
        "id": 2665170,
        "name:xx": "Sims Lake"
      }
    },
    {
      "geometry": {
        "type": "Point",
        "coordinates": [
          -89.8333,
          33.05
        ]
      },
      "type": "Feature",
      "properties": {
        "hierarchy": [
          "tgn:2665171",
          "tgn:1000001",
          "tgn:7012149",
          "tgn:2001111",
          "tgn:7007522",
          "tgn:7029392"
        ],
        "placetype": [
          "aat:300008680"
        ],
        "id": 2665171,
        "name:xx": "Sims Lake"
      }
    },
    {
      "geometry": {
        "type": "Point",
        "coordinates": [
          -95.4,
          40.15
        ]
      },
      "type": "Feature",
      "properties": {
        "hierarchy": [
          "tgn:2665172",
          "tgn:1000001",
          "tgn:7012149",
          "tgn:2001204",
          "tgn:7007523",
          "tgn:7029392"
        ],
        "placetype": [
          "aat:300008905"
        ],
        "id": 2665172,
        "name:xx": "Sims Lake"
      }
    },
    {
      "geometry": {
        "type": "Point",
        "coordinates": [
          -94.4,
          38.7833
        ]
      },
      "type": "Feature",
      "properties": {
        "hierarchy": [
          "tgn:2665173",
          "tgn:1000001",
          "tgn:2001182",
          "tgn:7012149",
          "tgn:7007523",
          "tgn:7029392"
        ],
        "placetype": [
          "aat:300006191"
        ],
        "id": 2665173,
        "name:xx": "Sims Lake"
      }
    },
    {
      "geometry": {
        "type": "Point",
        "coordinates": [
          -118.0167,
          47.1
        ]
      },
      "type": "Feature",
      "properties": {
        "hierarchy": [
          "tgn:2665174",
          "tgn:2002238",
          "tgn:1000001",
          "tgn:7012149",
          "tgn:7007920",
          "tgn:7029392"
        ],
        "placetype": [
          "aat:300008680"
        ],
        "id": 2665174,
        "name:xx": "Sims Lake"
      }
    },
    {
      "geometry": {
        "type": "Point",
        "coordinates": [
          -86.3,
          32.2167
        ]
      },
      "type": "Feature",
      "properties": {
        "hierarchy": [
          "tgn:2665175",
          "tgn:7002659",
          "tgn:1000001",
          "tgn:7012149",
          "tgn:2000050",
          "tgn:7029392"
        ],
        "placetype": [
          "aat:300006191"
        ],
        "id": 2665175,
        "name:xx": "Sims Lake Number One"
      }
    },
    {
      "geometry": {
        "type": "Point",
        "coordinates": [
          -86.3,
          32.2167
        ]
      },
      "type": "Feature",
      "properties": {
        "hierarchy": [
          "tgn:2665176",
          "tgn:7002659",
          "tgn:1000001",
          "tgn:7012149",
          "tgn:2000050",
          "tgn:7029392"
        ],
        "placetype": [
          "aat:300006191"
        ],
        "id": 2665176,
        "name:xx": "Sims Lake Number Two"
      }
    },
    {
      "geometry": {
        "type": "Point",
        "coordinates": [
          -107.8667,
          38.3667
        ]
      },
      "type": "Feature",
      "properties": {
        "hierarchy": [
          "tgn:2665177",
          "tgn:1000001",
          "tgn:7012149",
          "tgn:2000234",
          "tgn:7007158",
          "tgn:7029392"
        ],
        "placetype": [
          "aat:300008798"
        ],
        "id": 2665177,
        "name:xx": "Sims Mesa"
      }
    },
    {
      "geometry": {
        "type": "Point",
        "coordinates": [
          -86.4333,
          31.5
        ]
      },
      "type": "Feature",
      "properties": {
        "hierarchy": [
          "tgn:2665178",
          "tgn:7002659",
          "tgn:1000001",
          "tgn:2000019",
          "tgn:7012149",
          "tgn:7029392"
        ],
        "placetype": [
          "aat:300008706"
        ],
        "id": 2665178,
        "name:xx": "Sims Mill Creek"
      }
    },
    {
      "geometry": {
        "type": "Point",
        "coordinates": [
          -88.6667,
          30.6667
        ]
      },
      "type": "Feature",
      "properties": {
        "hierarchy": [
          "tgn:2665179",
          "tgn:1000001",
          "tgn:7012149",
          "tgn:2001115",
          "tgn:7007522",
          "tgn:7029392"
        ],
        "placetype": [
          "aat:300008680"
        ],
        "id": 2665179,
        "name:xx": "Sims Mill Pond"
      }
    }
  ]
}
