{
  "geometry": {
    "type": "Point",
    "coordinates": [
      -87.45,
      46.6333
    ]
  },
  "type": "Feature",
  "properties": {
    "hierarchy": [
      "tgn:2359160",
      "tgn:1000001",
      "tgn:7012149",
      "tgn:2000975",
      "tgn:7007520",
      "tgn:7029392"
    ],
    "placetype": [
      "aat:300008850"
    ],
    "id": 2359160,
    "name:xx": "Granite Point"
  }
}
