{
  "geometry": {
    "type": "Point",
    "coordinates": [
      83.85455,
      25.856909
    ]
  },
  "type": "Feature",
  "properties": {
    "hierarchy": [
      "tgn:1076753",
      "tgn:1000004",
      "tgn:7000198",
      "tgn:7016722",
      "tgn:7029392"
    ],
    "placetype": [
      "aat:300008347"
    ],
    "name:en": "Rasrā",
    "id": 1076753
  }
}
