{
  "type": "FeatureCollection",
  "features": [
    {
      "geometry": {
        "type": "Point",
        "coordinates": [
          -91.783333,
          16.85
        ]
      },
      "type": "Feature",
      "properties": {
        "hierarchy": [
          "tgn:1131180",
          "tgn:7005580",
          "tgn:1000001",
          "tgn:7005560",
          "tgn:7029392"
        ],
        "placetype": [
          "aat:300008707",
          "aat:300008699"
        ],
        "id": 1131180,
        "name:xx": "Tzanconeja, Río"
      }
    },
    {
      "geometry": {
        "type": "Point",
        "coordinates": [
          28.9167,
          54
        ]
      },
      "type": "Feature",
      "properties": {
        "hierarchy": [
          "tgn:1131183",
          "tgn:1003391",
          "tgn:1000003",
          "tgn:7006657",
          "tgn:7029392"
        ],
        "placetype": [
          "aat:300008707"
        ],
        "id": 1131183,
        "name:xx": "Usha"
      }
    },
    {
      "geometry": {
        "type": "Point",
        "coordinates": [
          28.5,
          55.5333
        ]
      },
      "type": "Feature",
      "properties": {
        "hierarchy": [
          "tgn:1131184",
          "tgn:7011701",
          "tgn:1000003",
          "tgn:7006657",
          "tgn:7029392"
        ],
        "placetype": [
          "aat:300008707"
        ],
        "id": 1131184,
        "name:xx": "Ušač'"
      }
    },
    {
      "geometry": {
        "type": "Point",
        "coordinates": [
          69.65,
          43.9167
        ]
      },
      "type": "Feature",
      "properties": {
        "hierarchy": [
          "tgn:1131185",
          "tgn:1000004",
          "tgn:7014786",
          "tgn:7029392"
        ],
        "placetype": [
          "aat:300008707"
        ],
        "id": 1131185,
        "name:xx": "Ušbas"
      }
    }
  ]
}
