{
  "type": "FeatureCollection",
  "features": [
    {
      "geometry": {
        "type": "Point",
        "coordinates": [
          -107.9833,
          37.6
        ]
      },
      "type": "Feature",
      "properties": {
        "hierarchy": [
          "tgn:2465820",
          "tgn:1000001",
          "tgn:7012149",
          "tgn:2000225",
          "tgn:7007158",
          "tgn:7029392"
        ],
        "placetype": [
          "aat:300008761"
        ],
        "id": 2465820,
        "name:xx": "Lone Spruce Draw"
      }
    },
    {
      "geometry": {
        "type": "Point",
        "coordinates": [
          -83.1667,
          36.7833
        ]
      },
      "type": "Feature",
      "properties": {
        "hierarchy": [
          "tgn:2465821",
          "tgn:1000001",
          "tgn:7012149",
          "tgn:2000797",
          "tgn:7007255",
          "tgn:7029392"
        ],
        "placetype": [
          "aat:300266640"
        ],
        "id": 2465821,
        "name:xx": "Lone Spur"
      }
    },
    {
      "geometry": {
        "type": "Point",
        "coordinates": [
          -92.7833,
          48.4333
        ]
      },
      "type": "Feature",
      "properties": {
        "hierarchy": [
          "tgn:2465822",
          "tgn:1000001",
          "tgn:7012149",
          "tgn:2001067",
          "tgn:7007521",
          "tgn:7029392"
        ],
        "placetype": [
          "aat:300008791"
        ],
        "id": 2465822,
        "name:xx": "Lone Squaw Island"
      }
    },
    {
      "geometry": {
        "type": "Point",
        "coordinates": [
          -91.9833,
          36
        ]
      },
      "type": "Feature",
      "properties": {
        "hierarchy": [
          "tgn:2465823",
          "tgn:1000001",
          "tgn:7016172",
          "tgn:7012149",
          "tgn:2000137",
          "tgn:7029392"
        ],
        "placetype": [
          "aat:300008347"
        ],
        "id": 2465823,
        "name:xx": "Lone Star"
      }
    },
    {
      "geometry": {
        "type": "Point",
        "coordinates": [
          -93.75,
          36.3333
        ]
      },
      "type": "Feature",
      "properties": {
        "hierarchy": [
          "tgn:2465824",
          "tgn:1000001",
          "tgn:7016172",
          "tgn:2000112",
          "tgn:7012149",
          "tgn:7029392"
        ],
        "placetype": [
          "aat:300008347"
        ],
        "id": 2465824,
        "name:xx": "Lone Star"
      }
    },
    {
      "geometry": {
        "type": "Point",
        "coordinates": [
          -122.8,
          39.7
        ]
      },
      "type": "Feature",
      "properties": {
        "hierarchy": [
          "tgn:2465825",
          "tgn:1000001",
          "tgn:7012149",
          "tgn:1002409",
          "tgn:7007157",
          "tgn:7029392"
        ],
        "placetype": [
          "aat:300008347"
        ],
        "id": 2465825,
        "name:xx": "Lone Star"
      }
    },
    {
      "geometry": {
        "type": "Point",
        "coordinates": [
          -102.85,
          40.35
        ]
      },
      "type": "Feature",
      "properties": {
        "hierarchy": [
          "tgn:2465826",
          "tgn:1000001",
          "tgn:7012149",
          "tgn:7007158",
          "tgn:2000252",
          "tgn:7029392"
        ],
        "placetype": [
          "aat:300008347"
        ],
        "id": 2465826,
        "name:xx": "Lone Star"
      }
    },
    {
      "geometry": {
        "type": "Point",
        "coordinates": [
          -75.5333,
          39.1
        ]
      },
      "type": "Feature",
      "properties": {
        "hierarchy": [
          "tgn:2465827",
          "tgn:1002538",
          "tgn:1000001",
          "tgn:7012149",
          "tgn:7007239",
          "tgn:7029392"
        ],
        "placetype": [
          "aat:300008347"
        ],
        "id": 2465827,
        "name:xx": "Lone Star"
      }
    },
    {
      "geometry": {
        "type": "Point",
        "coordinates": [
          -89.7333,
          31.6333
        ]
      },
      "type": "Feature",
      "properties": {
        "hierarchy": [
          "tgn:2465828",
          "tgn:1000001",
          "tgn:2001101",
          "tgn:7012149",
          "tgn:7007522",
          "tgn:7029392"
        ],
        "placetype": [
          "aat:300008347"
        ],
        "id": 2465828,
        "name:xx": "Lone Star"
      }
    },
    {
      "geometry": {
        "type": "Point",
        "coordinates": [
          -94.25,
          40.3333
        ]
      },
      "type": "Feature",
      "properties": {
        "hierarchy": [
          "tgn:2465829",
          "tgn:1000001",
          "tgn:7012149",
          "tgn:2001198",
          "tgn:7007523",
          "tgn:7029392"
        ],
        "placetype": [
          "aat:300008347"
        ],
        "id": 2465829,
        "name:xx": "Lone Star"
      }
    }
  ]
}
