{
  "geometry": {
    "type": "Point",
    "coordinates": [
      -115.3167,
      47.5667
    ]
  },
  "type": "Feature",
  "properties": {
    "hierarchy": [
      "tgn:2496003",
      "tgn:1000001",
      "tgn:7012149",
      "tgn:2001304",
      "tgn:7007524",
      "tgn:7029392"
    ],
    "placetype": [
      "aat:300008697"
    ],
    "id": 2496003,
    "name:xx": "Mass Spring"
  }
}
