{
  "geometry": {
    "type": "Point",
    "coordinates": [
      -89.2167,
      40.5333
    ]
  },
  "type": "Feature",
  "properties": {
    "hierarchy": [
      "tgn:2769051",
      "tgn:1000001",
      "tgn:7012149",
      "tgn:7007251",
      "tgn:7029392"
    ],
    "placetype": [
      "aat:300008699"
    ],
    "id": 2769051,
    "name:xx": "Whitten Branch"
  }
}
