{
  "geometry": {
    "type": "Point",
    "coordinates": [
      27.2167,
      38.9333
    ]
  },
  "type": "Feature",
  "properties": {
    "hierarchy": [
      "tgn:1085891",
      "tgn:1001053",
      "tgn:1000004",
      "tgn:7018451",
      "tgn:1000144",
      "tgn:7029392"
    ],
    "placetype": [
      "aat:300008347"
    ],
    "id": 1085891,
    "name:xx": "Ismailli"
  }
}
