{
  "type": "FeatureCollection",
  "features": [
    {
      "geometry": {
        "type": "Point",
        "coordinates": [
          78.75,
          33.8333
        ]
      },
      "type": "Feature",
      "properties": {
        "hierarchy": [
          "tgn:1117660",
          "tgn:1000004",
          "tgn:7029392"
        ],
        "placetype": [
          "aat:300008680"
        ],
        "id": 1117660,
        "name:xx": "Bangong Co"
      }
    },
    {
      "geometry": {
        "type": "Point",
        "coordinates": [
          -72.216667,
          -39.716667
        ]
      },
      "type": "Feature",
      "properties": {
        "hierarchy": [
          "tgn:1117661",
          "tgn:7593328",
          "tgn:1000049",
          "tgn:1000002",
          "tgn:7029392"
        ],
        "placetype": [
          "aat:300008680"
        ],
        "id": 1117661,
        "name:xx": "Panguipulli, Lago"
      }
    },
    {
      "geometry": {
        "type": "Point",
        "coordinates": [
          -64.1167,
          44.8
        ]
      },
      "type": "Feature",
      "properties": {
        "hierarchy": [
          "tgn:1117663",
          "tgn:7005685",
          "tgn:1000001",
          "tgn:7005802",
          "tgn:7029392"
        ],
        "placetype": [
          "aat:300008680"
        ],
        "id": 1117663,
        "name:xx": "Panuke Lake"
      }
    },
    {
      "geometry": {
        "type": "Point",
        "coordinates": [
          -77.8333,
          45.3333
        ]
      },
      "type": "Feature",
      "properties": {
        "hierarchy": [
          "tgn:1117666",
          "tgn:7005685",
          "tgn:1000001",
          "tgn:7013154",
          "tgn:7029392"
        ],
        "placetype": [
          "aat:300008680"
        ],
        "id": 1117666,
        "name:xx": "Papineau Lake"
      }
    }
  ]
}
