{
  "geometry": {
    "type": "Point",
    "coordinates": [
      -120.0667,
      41.25
    ]
  },
  "type": "Feature",
  "properties": {
    "hierarchy": [
      "tgn:2505760",
      "tgn:1000001",
      "tgn:7012149",
      "tgn:7007157",
      "tgn:2000186",
      "tgn:7029392"
    ],
    "placetype": [
      "aat:300008347"
    ],
    "id": 2505760,
    "name:xx": "Menlo Baths"
  }
}
