{
  "geometry": {
    "type": "Point",
    "coordinates": [
      -117.5333,
      48.8833
    ]
  },
  "type": "Feature",
  "properties": {
    "hierarchy": [
      "tgn:2350918",
      "tgn:1000001",
      "tgn:7012149",
      "tgn:2002250",
      "tgn:7007920",
      "tgn:7029392"
    ],
    "placetype": [
      "aat:300000390"
    ],
    "id": 2350918,
    "name:xx": "Gladstone Mine"
  }
}
