{
  "geometry": {
    "type": "Point",
    "coordinates": [
      -83.95,
      32.7167
    ]
  },
  "type": "Feature",
  "properties": {
    "hierarchy": [
      "tgn:2157236",
      "tgn:1000001",
      "tgn:7012149",
      "tgn:2000330",
      "tgn:7007248",
      "tgn:7029392"
    ],
    "placetype": [
      "aat:300008706"
    ],
    "id": 2157236,
    "name:xx": "Beaver Creek"
  }
}
