{
  "geometry": {
    "type": "Point",
    "coordinates": [
      -82.9333,
      39.2333
    ]
  },
  "type": "Feature",
  "properties": {
    "hierarchy": [
      "tgn:2466820",
      "tgn:1000001",
      "tgn:7012149",
      "tgn:1002835",
      "tgn:7007706",
      "tgn:7029392"
    ],
    "placetype": [
      "aat:300008761"
    ],
    "id": 2466820,
    "name:xx": "Long Branch Hollow"
  }
}
