{
  "geometry": {
    "type": "Point",
    "coordinates": [
      -80.3667,
      38.5833
    ]
  },
  "type": "Feature",
  "properties": {
    "hierarchy": [
      "tgn:2392992",
      "tgn:1000001",
      "tgn:7012149",
      "tgn:2002300",
      "tgn:7013961",
      "tgn:7029392"
    ],
    "placetype": [
      "aat:300008706"
    ],
    "id": 2392992,
    "name:xx": "Hodam Creek"
  }
}
