{
  "geometry": {
    "type": "Point",
    "coordinates": [
      -73.7833,
      40.8333
    ]
  },
  "type": "Feature",
  "properties": {
    "hierarchy": [
      "tgn:7015847",
      "tgn:7022658",
      "tgn:1000001",
      "tgn:7012149",
      "tgn:7007567",
      "tgn:7007568",
      "tgn:7029392"
    ],
    "placetype": [
      "aat:300000745",
      "aat:300008791"
    ],
    "id": 7015847,
    "name:xx": "City Island"
  }
}
