{
  "geometry": {
    "type": "Point",
    "coordinates": [
      -75.5167,
      40.45
    ]
  },
  "type": "Feature",
  "properties": {
    "hierarchy": [
      "tgn:2092208",
      "tgn:1000001",
      "tgn:7012149",
      "tgn:1002586",
      "tgn:7007710",
      "tgn:7029392"
    ],
    "placetype": [
      "aat:300008347",
      "aat:300387210"
    ],
    "id": 2092208,
    "name:xx": "Powder Valley"
  }
}
