{
  "geometry": {
    "type": "Point",
    "coordinates": [
      119.8167,
      16.1167
    ]
  },
  "type": "Feature",
  "properties": {
    "hierarchy": [
      "tgn:1083928",
      "tgn:1000004",
      "tgn:1001484",
      "tgn:1000135",
      "tgn:7029392"
    ],
    "placetype": [
      "aat:300008347"
    ],
    "id": 1083928,
    "name:xx": "Agno"
  }
}
