{
  "geometry": {
    "type": "Point",
    "coordinates": [
      -68.4333,
      46.1833
    ]
  },
  "type": "Feature",
  "properties": {
    "hierarchy": [
      "tgn:2481942",
      "tgn:1000001",
      "tgn:7012149",
      "tgn:2000927",
      "tgn:7007515",
      "tgn:7029392"
    ],
    "placetype": [
      "aat:300008680"
    ],
    "id": 2481942,
    "name:xx": "Lane Brook Pond"
  }
}
