{
  "type": "FeatureCollection",
  "features": [
    {
      "geometry": {
        "type": "Point",
        "coordinates": [
          -104.1,
          36.2
        ]
      },
      "type": "Feature",
      "properties": {
        "hierarchy": [
          "tgn:2624320",
          "tgn:1000001",
          "tgn:7012149",
          "tgn:2001439",
          "tgn:7007566",
          "tgn:7029392"
        ],
        "placetype": [
          "aat:300008680"
        ],
        "id": 2624320,
        "name:xx": "Rock Lake"
      }
    },
    {
      "geometry": {
        "type": "Point",
        "coordinates": [
          -74.4,
          43.25
        ]
      },
      "type": "Feature",
      "properties": {
        "hierarchy": [
          "tgn:2624321",
          "tgn:1000001",
          "tgn:7012149",
          "tgn:1002440",
          "tgn:7007568",
          "tgn:7029392"
        ],
        "placetype": [
          "aat:300008680"
        ],
        "id": 2624321,
        "name:xx": "Rock Lake"
      }
    },
    {
      "geometry": {
        "type": "Point",
        "coordinates": [
          -75,
          44
        ]
      },
      "type": "Feature",
      "properties": {
        "hierarchy": [
          "tgn:2624322",
          "tgn:1000001",
          "tgn:7012149",
          "tgn:1002472",
          "tgn:7007568",
          "tgn:7029392"
        ],
        "placetype": [
          "aat:300008680"
        ],
        "id": 2624322,
        "name:xx": "Rock Lake"
      }
    },
    {
      "geometry": {
        "type": "Point",
        "coordinates": [
          -75.1333,
          44.1667
        ]
      },
      "type": "Feature",
      "properties": {
        "hierarchy": [
          "tgn:2624323",
          "tgn:1000001",
          "tgn:7012149",
          "tgn:7016021",
          "tgn:7007568",
          "tgn:7029392"
        ],
        "placetype": [
          "aat:300008680"
        ],
        "id": 2624323,
        "name:xx": "Rock Lake"
      }
    },
    {
      "geometry": {
        "type": "Point",
        "coordinates": [
          -74.9833,
          41.55
        ]
      },
      "type": "Feature",
      "properties": {
        "hierarchy": [
          "tgn:2624324",
          "tgn:1000001",
          "tgn:7012149",
          "tgn:1002926",
          "tgn:7007568",
          "tgn:7029392"
        ],
        "placetype": [
          "aat:300008680"
        ],
        "id": 2624324,
        "name:xx": "Rock Lake"
      }
    },
    {
      "geometry": {
        "type": "Point",
        "coordinates": [
          -100.7167,
          48.3
        ]
      },
      "type": "Feature",
      "properties": {
        "hierarchy": [
          "tgn:2624325",
          "tgn:1000001",
          "tgn:2001581",
          "tgn:7012149",
          "tgn:7007705",
          "tgn:7029392"
        ],
        "placetype": [
          "aat:300008680"
        ],
        "id": 2624325,
        "name:xx": "Rock Lake"
      }
    },
    {
      "geometry": {
        "type": "Point",
        "coordinates": [
          -96.3333,
          35.6167
        ]
      },
      "type": "Feature",
      "properties": {
        "hierarchy": [
          "tgn:2624326",
          "tgn:1000001",
          "tgn:7012149",
          "tgn:2001676",
          "tgn:7007707",
          "tgn:7029392"
        ],
        "placetype": [
          "aat:300008680"
        ],
        "id": 2624326,
        "name:xx": "Rock Lake"
      }
    },
    {
      "geometry": {
        "type": "Point",
        "coordinates": [
          -119.3667,
          43.4833
        ]
      },
      "type": "Feature",
      "properties": {
        "hierarchy": [
          "tgn:2624327",
          "tgn:1000001",
          "tgn:7012149",
          "tgn:2001709",
          "tgn:7007708",
          "tgn:7029392"
        ],
        "placetype": [
          "aat:300008680"
        ],
        "id": 2624327,
        "name:xx": "Rock Lake"
      }
    },
    {
      "geometry": {
        "type": "Point",
        "coordinates": [
          -121.95,
          43.9333
        ]
      },
      "type": "Feature",
      "properties": {
        "hierarchy": [
          "tgn:2624328",
          "tgn:1000001",
          "tgn:7012149",
          "tgn:2001716",
          "tgn:7007708",
          "tgn:7029392"
        ],
        "placetype": [
          "aat:300008680"
        ],
        "id": 2624328,
        "name:xx": "Rock Lake"
      }
    },
    {
      "geometry": {
        "type": "Point",
        "coordinates": [
          -121.8,
          44.7
        ]
      },
      "type": "Feature",
      "properties": {
        "hierarchy": [
          "tgn:2624329",
          "tgn:1000001",
          "tgn:7012149",
          "tgn:1002636",
          "tgn:7007708",
          "tgn:7029392"
        ],
        "placetype": [
          "aat:300008680"
        ],
        "id": 2624329,
        "name:xx": "Rock Lake"
      }
    }
  ]
}
