{
  "type": "FeatureCollection",
  "features": [
    {
      "geometry": {
        "type": "Point",
        "coordinates": [
          -112.3167,
          46.8167
        ]
      },
      "type": "Feature",
      "properties": {
        "hierarchy": [
          "tgn:2534450",
          "tgn:1000001",
          "tgn:7012149",
          "tgn:2001281",
          "tgn:7007524",
          "tgn:7029392"
        ],
        "placetype": [
          "aat:300000390"
        ],
        "id": 2534450,
        "name:xx": "NE SW Section 23 Mine"
      }
    },
    {
      "geometry": {
        "type": "Point",
        "coordinates": [
          -111.9167,
          45.8
        ]
      },
      "type": "Feature",
      "properties": {
        "hierarchy": [
          "tgn:2534451",
          "tgn:1000001",
          "tgn:7012149",
          "tgn:2001288",
          "tgn:7007524",
          "tgn:7029392"
        ],
        "placetype": [
          "aat:300000390"
        ],
        "id": 2534451,
        "name:xx": "NE SW Section 25 Mine"
      }
    },
    {
      "geometry": {
        "type": "Point",
        "coordinates": [
          -111.4333,
          46.5833
        ]
      },
      "type": "Feature",
      "properties": {
        "hierarchy": [
          "tgn:2534452",
          "tgn:1000001",
          "tgn:2001263",
          "tgn:7012149",
          "tgn:7007524",
          "tgn:7029392"
        ],
        "placetype": [
          "aat:300000390"
        ],
        "id": 2534452,
        "name:xx": "NE SW Section 26 Mine"
      }
    },
    {
      "geometry": {
        "type": "Point",
        "coordinates": [
          -111.95,
          45.45
        ]
      },
      "type": "Feature",
      "properties": {
        "hierarchy": [
          "tgn:2534454",
          "tgn:1000001",
          "tgn:7012149",
          "tgn:2001288",
          "tgn:7007524",
          "tgn:7029392"
        ],
        "placetype": [
          "aat:300000390"
        ],
        "id": 2534454,
        "name:xx": "NE SW Section 27 Mine"
      }
    },
    {
      "geometry": {
        "type": "Point",
        "coordinates": [
          -112.1833,
          45.8
        ]
      },
      "type": "Feature",
      "properties": {
        "hierarchy": [
          "tgn:2534455",
          "tgn:1000001",
          "tgn:7012149",
          "tgn:2001288",
          "tgn:7007524",
          "tgn:7029392"
        ],
        "placetype": [
          "aat:300000390"
        ],
        "id": 2534455,
        "name:xx": "NE SW Section 29 Mine"
      }
    },
    {
      "geometry": {
        "type": "Point",
        "coordinates": [
          -112.5,
          46.6667
        ]
      },
      "type": "Feature",
      "properties": {
        "hierarchy": [
          "tgn:2534456",
          "tgn:1000001",
          "tgn:7012149",
          "tgn:2001298",
          "tgn:7007524",
          "tgn:7029392"
        ],
        "placetype": [
          "aat:300000390"
        ],
        "id": 2534456,
        "name:xx": "NE SW Section 29 Mine"
      }
    },
    {
      "geometry": {
        "type": "Point",
        "coordinates": [
          -112.2,
          46.0333
        ]
      },
      "type": "Feature",
      "properties": {
        "hierarchy": [
          "tgn:2534457",
          "tgn:1000001",
          "tgn:7012149",
          "tgn:2001281",
          "tgn:7007524",
          "tgn:7029392"
        ],
        "placetype": [
          "aat:300000390"
        ],
        "id": 2534457,
        "name:xx": "NE SW Section 3 Mine"
      }
    },
    {
      "geometry": {
        "type": "Point",
        "coordinates": [
          -112.0167,
          45.45
        ]
      },
      "type": "Feature",
      "properties": {
        "hierarchy": [
          "tgn:2534458",
          "tgn:1000001",
          "tgn:7012149",
          "tgn:2001288",
          "tgn:7007524",
          "tgn:7029392"
        ],
        "placetype": [
          "aat:300000390"
        ],
        "id": 2534458,
        "name:xx": "NE SW Section 30 Mine"
      }
    },
    {
      "geometry": {
        "type": "Point",
        "coordinates": [
          -112.6333,
          45.7
        ]
      },
      "type": "Feature",
      "properties": {
        "hierarchy": [
          "tgn:2534459",
          "tgn:1000001",
          "tgn:7012149",
          "tgn:2001306",
          "tgn:7007524",
          "tgn:7029392"
        ],
        "placetype": [
          "aat:300000390"
        ],
        "id": 2534459,
        "name:xx": "NE SW Section 31 Mine"
      }
    }
  ]
}
