{
  "geometry": {
    "type": "Point",
    "coordinates": [
      30.733333,
      29.133333
    ]
  },
  "type": "Feature",
  "properties": {
    "hierarchy": [
      "tgn:7528741",
      "tgn:7001242",
      "tgn:7001105",
      "tgn:7016833",
      "tgn:7029392"
    ],
    "placetype": [
      "aat:300005926"
    ],
    "name:en": "Manāmat Sīdī 'Abd al Wāḩid al Arba'īn",
    "id": 7528741
  }
}
