{
  "geometry": {
    "type": "Point",
    "coordinates": [
      31.416896,
      30.04619
    ]
  },
  "type": "Feature",
  "properties": {
    "hierarchy": [
      "tgn:7531196",
      "tgn:7001242",
      "tgn:7016833",
      "tgn:1001091",
      "tgn:7029392"
    ],
    "placetype": [
      "aat:300006495"
    ],
    "id": 7531196,
    "name:xx": "Ak훮d카m카yat Mub훮rak lil Amn"
  }
}
