{
  "geometry": {
    "type": "Point",
    "coordinates": [
      -68.0167,
      46.0833
    ]
  },
  "type": "Feature",
  "properties": {
    "hierarchy": [
      "tgn:2504928",
      "tgn:2000919",
      "tgn:1000001",
      "tgn:7012149",
      "tgn:7007515",
      "tgn:7029392"
    ],
    "placetype": [
      "aat:300008680"
    ],
    "id": 2504928,
    "name:xx": "Meduxnekeag Lake"
  }
}
