{
  "geometry": {
    "type": "Point",
    "coordinates": [
      -117.3667,
      47.2333
    ]
  },
  "type": "Feature",
  "properties": {
    "hierarchy": [
      "tgn:2116652",
      "tgn:1000001",
      "tgn:7012149",
      "tgn:2002252",
      "tgn:7007920",
      "tgn:7029392"
    ],
    "placetype": [
      "aat:300008347"
    ],
    "id": 2116652,
    "name:xx": "Rosalia"
  }
}
