{
  "geometry": {
    "type": "Point",
    "coordinates": [
      -78.3333,
      39.5667
    ]
  },
  "type": "Feature",
  "properties": {
    "hierarchy": [
      "tgn:2621124",
      "tgn:1000001",
      "tgn:7012149",
      "tgn:2002283",
      "tgn:7013961",
      "tgn:7029392"
    ],
    "placetype": [
      "aat:300266640"
    ],
    "id": 2621124,
    "name:xx": "Road Ridge"
  }
}
