{
  "geometry": {
    "type": "Point",
    "coordinates": [
      -121.4167,
      40.4833
    ]
  },
  "type": "Feature",
  "properties": {
    "hierarchy": [
      "tgn:2703354",
      "tgn:1000001",
      "tgn:7012149",
      "tgn:7007157",
      "tgn:2000188",
      "tgn:7029392"
    ],
    "placetype": [
      "aat:300008706"
    ],
    "id": 2703354,
    "name:xx": "Summit Creek"
  }
}
