{
  "geometry": {
    "type": "Point",
    "coordinates": [
      -89.4667,
      45.5167
    ]
  },
  "type": "Feature",
  "properties": {
    "hierarchy": [
      "tgn:2391962",
      "tgn:1000001",
      "tgn:7012149",
      "tgn:2002334",
      "tgn:7007922",
      "tgn:7029392"
    ],
    "placetype": [
      "aat:300008680"
    ],
    "id": 2391962,
    "name:xx": "Hilts Lake"
  }
}
