{
  "geometry": {
    "type": "Point",
    "coordinates": [
      -104.6333,
      40.3667
    ]
  },
  "type": "Feature",
  "properties": {
    "hierarchy": [
      "tgn:2474104",
      "tgn:1000001",
      "tgn:7012149",
      "tgn:7007158",
      "tgn:2000253",
      "tgn:7029392"
    ],
    "placetype": [
      "aat:300006075"
    ],
    "id": 2474104,
    "name:xx": "Lower Latham Outlet"
  }
}
