{
  "geometry": {
    "type": "Point",
    "coordinates": [
      -59.1333,
      -35.1833
    ]
  },
  "type": "Feature",
  "properties": {
    "hierarchy": [
      "tgn:1019695",
      "tgn:1001160",
      "tgn:7006477",
      "tgn:1000002",
      "tgn:7029392"
    ],
    "placetype": [
      "aat:300008347"
    ],
    "id": 1019695,
    "name:xx": "Lobos"
  }
}
