{
  "geometry": {
    "type": "Point",
    "coordinates": [
      33.016667,
      24.433333
    ]
  },
  "type": "Feature",
  "properties": {
    "hierarchy": [
      "tgn:7537046",
      "tgn:7001242",
      "tgn:7001311",
      "tgn:7016833",
      "tgn:7029392"
    ],
    "placetype": [
      "aat:300379998"
    ],
    "name:en": "L훮w카, W훮d카 al",
    "id": 7537046
  }
}
