{
  "geometry": {
    "type": "Point",
    "coordinates": [
      -108.1333,
      42.7167
    ]
  },
  "type": "Feature",
  "properties": {
    "hierarchy": [
      "tgn:2460432",
      "tgn:1000001",
      "tgn:7012149",
      "tgn:2002371",
      "tgn:7007923",
      "tgn:7029392"
    ],
    "placetype": [
      "aat:300008761"
    ],
    "id": 2460432,
    "name:xx": "Little Sand Draw"
  }
}
