{
  "geometry": {
    "type": "Point",
    "coordinates": [
      -105.3167,
      36.2667
    ]
  },
  "type": "Feature",
  "properties": {
    "hierarchy": [
      "tgn:1127340",
      "tgn:1000001",
      "tgn:7012149",
      "tgn:7007566",
      "tgn:7029392"
    ],
    "placetype": [
      "aat:300008707"
    ],
    "id": 1127340,
    "name:xx": "Mora"
  }
}
