{
  "geometry": {
    "type": "Point",
    "coordinates": [
      -120.5833,
      39.95
    ]
  },
  "type": "Feature",
  "properties": {
    "hierarchy": [
      "tgn:2733953",
      "tgn:1000001",
      "tgn:7012149",
      "tgn:7007157",
      "tgn:2000187",
      "tgn:7029392"
    ],
    "placetype": [
      "aat:300266640"
    ],
    "id": 2733953,
    "name:xx": "Turner Ridge"
  }
}
