{
  "geometry": {
    "type": "Point",
    "coordinates": [
      39.2833,
      47.05
    ]
  },
  "type": "Feature",
  "properties": {
    "hierarchy": [
      "tgn:1123466",
      "tgn:1000004",
      "tgn:7002435",
      "tgn:7029392"
    ],
    "placetype": [
      "aat:300008707"
    ],
    "id": 1123466,
    "name:xx": "Don"
  }
}
