{
  "type": "FeatureCollection",
  "features": [
    {
      "geometry": {
        "type": "Point",
        "coordinates": [
          4.4,
          50.216667
        ]
      },
      "type": "Feature",
      "properties": {
        "hierarchy": [
          "tgn:7251192",
          "tgn:7003466",
          "tgn:1000003",
          "tgn:1000063",
          "tgn:4012014",
          "tgn:7029392"
        ],
        "placetype": [
          "aat:300008347"
        ],
        "id": 7251192,
        "name:xx": "Nazareth"
      }
    },
    {
      "geometry": {
        "type": "Point",
        "coordinates": [
          4.916667,
          51.333333
        ]
      },
      "type": "Feature",
      "properties": {
        "hierarchy": [
          "tgn:7251194",
          "tgn:7003456",
          "tgn:1000003",
          "tgn:1000063",
          "tgn:7018236",
          "tgn:7029392"
        ],
        "placetype": [
          "aat:300008347"
        ],
        "id": 7251194,
        "name:xx": "Nazaret"
      }
    },
    {
      "geometry": {
        "type": "Point",
        "coordinates": [
          4.6,
          50.133333
        ]
      },
      "type": "Feature",
      "properties": {
        "hierarchy": [
          "tgn:7251195",
          "tgn:7003466",
          "tgn:1000003",
          "tgn:1000063",
          "tgn:4012014",
          "tgn:7029392"
        ],
        "placetype": [
          "aat:300008863"
        ],
        "id": 7251195,
        "name:xx": "Naye Jean Lespoir, Bois"
      }
    },
    {
      "geometry": {
        "type": "Point",
        "coordinates": [
          5.933333,
          50.533333
        ]
      },
      "type": "Feature",
      "properties": {
        "hierarchy": [
          "tgn:7251196",
          "tgn:7003460",
          "tgn:1000003",
          "tgn:1000063",
          "tgn:4012014",
          "tgn:7029392"
        ],
        "placetype": [
          "aat:300008863"
        ],
        "id": 7251196,
        "name:xx": "Rasouster, Bois de"
      }
    },
    {
      "geometry": {
        "type": "Point",
        "coordinates": [
          3.983333,
          50.7
        ]
      },
      "type": "Feature",
      "properties": {
        "hierarchy": [
          "tgn:7251197",
          "tgn:7003457",
          "tgn:1000003",
          "tgn:1000063",
          "tgn:7018236",
          "tgn:7029392"
        ],
        "placetype": [
          "aat:300008347"
        ],
        "id": 7251197,
        "name:xx": "Rasbeek"
      }
    },
    {
      "geometry": {
        "type": "Point",
        "coordinates": [
          4.35,
          50.616667
        ]
      },
      "type": "Feature",
      "properties": {
        "hierarchy": [
          "tgn:7251198",
          "tgn:7007877",
          "tgn:1000003",
          "tgn:1000063",
          "tgn:4012014",
          "tgn:7029392"
        ],
        "placetype": [
          "aat:300000206"
        ],
        "id": 7251198,
        "name:xx": "Petit Merly"
      }
    },
    {
      "geometry": {
        "type": "Point",
        "coordinates": [
          4.233333,
          50.566667
        ]
      },
      "type": "Feature",
      "properties": {
        "hierarchy": [
          "tgn:7251199",
          "tgn:7007877",
          "tgn:1000003",
          "tgn:1000063",
          "tgn:4012014",
          "tgn:7029392"
        ],
        "placetype": [
          "aat:300000206"
        ],
        "id": 7251199,
        "name:xx": "Petit Mariemont"
      }
    }
  ]
}
