{
  "geometry": {
    "type": "Point",
    "coordinates": [
      -79.2167,
      39.5333
    ]
  },
  "type": "Feature",
  "properties": {
    "hierarchy": [
      "tgn:2293413",
      "tgn:1000001",
      "tgn:2000935",
      "tgn:7012149",
      "tgn:7007516",
      "tgn:7029392"
    ],
    "placetype": [
      "aat:300008699"
    ],
    "id": 2293413,
    "name:xx": "Double Lick Run"
  }
}
