{
  "geometry": {
    "type": "Point",
    "coordinates": [
      -110.6833,
      41.8667
    ]
  },
  "type": "Feature",
  "properties": {
    "hierarchy": [
      "tgn:7019952",
      "tgn:1000001",
      "tgn:7012149",
      "tgn:2002376",
      "tgn:7007923",
      "tgn:7029392"
    ],
    "placetype": [
      "aat:300006191"
    ],
    "id": 7019952,
    "name:xx": "Rich Reservoir"
  }
}
