{
  "geometry": {
    "type": "Point",
    "coordinates": [
      -107.65,
      39.1333
    ]
  },
  "type": "Feature",
  "properties": {
    "hierarchy": [
      "tgn:2212025",
      "tgn:1000001",
      "tgn:7012149",
      "tgn:2000230",
      "tgn:7007158",
      "tgn:7029392"
    ],
    "placetype": [
      "aat:300008706"
    ],
    "id": 2212025,
    "name:xx": "Buzzard Creek"
  }
}
