{
  "geometry": {
    "type": "Point",
    "coordinates": [
      33.557171,
      30.086659
    ]
  },
  "type": "Feature",
  "properties": {
    "hierarchy": [
      "tgn:7521775",
      "tgn:7001242",
      "tgn:7016833",
      "tgn:7001335",
      "tgn:7029392"
    ],
    "placetype": [
      "aat:300008777"
    ],
    "name:en": "Abū Kanādū, Jabal",
    "id": 7521775
  }
}
