{
  "geometry": {
    "type": "Point",
    "coordinates": [
      37.916,
      32.333
    ]
  },
  "type": "Feature",
  "properties": {
    "hierarchy": [
      "tgn:7018394",
      "tgn:1000004",
      "tgn:1000121",
      "tgn:7029392"
    ],
    "placetype": [
      "aat:300387064",
      "aat:300235093"
    ],
    "id": 7018394,
    "name:xx": "Al Mafraq"
  }
}
