{
  "geometry": {
    "type": "Point",
    "coordinates": [
      -76.55,
      38.2167
    ]
  },
  "type": "Feature",
  "properties": {
    "hierarchy": [
      "tgn:2424037",
      "tgn:1000001",
      "tgn:7016098",
      "tgn:7012149",
      "tgn:7007516",
      "tgn:7029392"
    ],
    "placetype": [
      "aat:300008706"
    ],
    "id": 2424037,
    "name:xx": "Johns Creek"
  }
}
