{
  "geometry": {
    "type": "Point",
    "coordinates": [
      -105.7333,
      43.9833
    ]
  },
  "type": "Feature",
  "properties": {
    "hierarchy": [
      "tgn:2543772",
      "tgn:1000001",
      "tgn:2002367",
      "tgn:7012149",
      "tgn:7007923",
      "tgn:7029392"
    ],
    "placetype": [
      "aat:300008706"
    ],
    "id": 2543772,
    "name:xx": "North Beaver Creek"
  }
}
