{
  "geometry": {
    "type": "Point",
    "coordinates": [
      25.6167,
      48.3833
    ]
  },
  "type": "Feature",
  "properties": {
    "hierarchy": [
      "tgn:1120817",
      "tgn:1000003",
      "tgn:7006660",
      "tgn:7029392"
    ],
    "placetype": [
      "aat:300008707"
    ],
    "id": 1120817,
    "name:xx": "Čeremoš"
  }
}
