{
  "geometry": {
    "type": "Point",
    "coordinates": [
      76.5333,
      32.85
    ]
  },
  "type": "Feature",
  "properties": {
    "hierarchy": [
      "tgn:1103837",
      "tgn:1000004",
      "tgn:7000198",
      "tgn:1001996",
      "tgn:7029392"
    ],
    "placetype": [
      "aat:300008795"
    ],
    "id": 1103837,
    "name:xx": "Baihāli Jot"
  }
}
