{
  "geometry": {
    "type": "Point",
    "coordinates": [
      28.0333,
      51.1167
    ]
  },
  "type": "Feature",
  "properties": {
    "hierarchy": [
      "tgn:1057573",
      "tgn:1000003",
      "tgn:7011671",
      "tgn:7006660",
      "tgn:7029392"
    ],
    "placetype": [
      "aat:300008347"
    ],
    "id": 1057573,
    "name:xx": "Novi Bilokorovychi"
  }
}
