{
  "geometry": {
    "type": "Point",
    "coordinates": [
      -95.1667,
      43.45
    ]
  },
  "type": "Feature",
  "properties": {
    "hierarchy": [
      "tgn:2756868",
      "tgn:1000001",
      "tgn:2000590",
      "tgn:7012149",
      "tgn:7007253",
      "tgn:7029392"
    ],
    "placetype": [
      "aat:300008680"
    ],
    "id": 2756868,
    "name:xx": "Welsh Lake"
  }
}
