{
  "geometry": {
    "type": "Point",
    "coordinates": [
      -72.35,
      41.05
    ]
  },
  "type": "Feature",
  "properties": {
    "hierarchy": [
      "tgn:2662996",
      "tgn:1000001",
      "tgn:7012149",
      "tgn:1002924",
      "tgn:7007568",
      "tgn:7029392"
    ],
    "placetype": [
      "aat:300008347"
    ],
    "id": 2662996,
    "name:xx": "Silver Beach"
  }
}
