{
  "geometry": {
    "type": "Point",
    "coordinates": [
      -70.7667,
      -6.8333
    ]
  },
  "type": "Feature",
  "properties": {
    "hierarchy": [
      "tgn:1124367",
      "tgn:1001826",
      "tgn:1000047",
      "tgn:7002456",
      "tgn:1000002",
      "tgn:7029392"
    ],
    "placetype": [
      "aat:300008707"
    ],
    "id": 1124367,
    "name:xx": "Gregório"
  }
}
