{
  "type": "FeatureCollection",
  "features": [
    {
      "geometry": {
        "type": "Point",
        "coordinates": [
          14.8,
          38.116667
        ]
      },
      "type": "Feature",
      "properties": {
        "hierarchy": [
          "tgn:7046450",
          "tgn:1000003",
          "tgn:7003122",
          "tgn:7003157",
          "tgn:1000080",
          "tgn:7029392"
        ],
        "placetype": [
          "aat:300008347"
        ],
        "id": 7046450,
        "name:xx": "Sant'Antonino"
      }
    },
    {
      "geometry": {
        "type": "Point",
        "coordinates": [
          16.533333,
          38.833333
        ]
      },
      "type": "Feature",
      "properties": {
        "hierarchy": [
          "tgn:7046451",
          "tgn:1003447",
          "tgn:7007850",
          "tgn:1000003",
          "tgn:1000080",
          "tgn:7029392"
        ],
        "placetype": [
          "aat:300008347"
        ],
        "id": 7046451,
        "name:xx": "Case Sansone"
      }
    },
    {
      "geometry": {
        "type": "Point",
        "coordinates": [
          14.85,
          37.25
        ]
      },
      "type": "Feature",
      "properties": {
        "hierarchy": [
          "tgn:7046452",
          "tgn:1000003",
          "tgn:7003122",
          "tgn:1001753",
          "tgn:1000080",
          "tgn:7029392"
        ],
        "placetype": [
          "aat:300008347"
        ],
        "id": 7046452,
        "name:xx": "Case San Leo"
      }
    },
    {
      "geometry": {
        "type": "Point",
        "coordinates": [
          14.633333,
          38.05
        ]
      },
      "type": "Feature",
      "properties": {
        "hierarchy": [
          "tgn:7046453",
          "tgn:1000003",
          "tgn:7003122",
          "tgn:7003157",
          "tgn:1000080",
          "tgn:7029392"
        ],
        "placetype": [
          "aat:300008347"
        ],
        "id": 7046453,
        "name:xx": "Case San Giovanni"
      }
    },
    {
      "geometry": {
        "type": "Point",
        "coordinates": [
          16.583333,
          39.6
        ]
      },
      "type": "Feature",
      "properties": {
        "hierarchy": [
          "tgn:7046454",
          "tgn:1003450",
          "tgn:7007850",
          "tgn:1000003",
          "tgn:1000080",
          "tgn:7029392"
        ],
        "placetype": [
          "aat:300008347"
        ],
        "id": 7046454,
        "name:xx": "Case San Francesco"
      }
    },
    {
      "geometry": {
        "type": "Point",
        "coordinates": [
          17.05,
          39.233333
        ]
      },
      "type": "Feature",
      "properties": {
        "hierarchy": [
          "tgn:7046455",
          "tgn:1003447",
          "tgn:7007850",
          "tgn:1000003",
          "tgn:1000080",
          "tgn:7029392"
        ],
        "placetype": [
          "aat:300008347"
        ],
        "id": 7046455,
        "name:xx": "Case Salinella"
      }
    },
    {
      "geometry": {
        "type": "Point",
        "coordinates": [
          12.483333,
          37.7
        ]
      },
      "type": "Feature",
      "properties": {
        "hierarchy": [
          "tgn:7046456",
          "tgn:1000003",
          "tgn:7003122",
          "tgn:1001762",
          "tgn:1000080",
          "tgn:7029392"
        ],
        "placetype": [
          "aat:300008347"
        ],
        "id": 7046456,
        "name:xx": "Case Ruccione"
      }
    }
  ]
}
