{
  "geometry": {
    "type": "Point",
    "coordinates": [
      53.1667,
      46.8167
    ]
  },
  "type": "Feature",
  "properties": {
    "hierarchy": [
      "tgn:1051834",
      "tgn:7012908",
      "tgn:1000004",
      "tgn:7014786",
      "tgn:7029392"
    ],
    "placetype": [
      "aat:300008347"
    ],
    "id": 1051834,
    "name:xx": "Zhilaya Kosa"
  }
}
