{
  "geometry": {
    "type": "Point",
    "coordinates": [
      36.5833,
      46.85
    ]
  },
  "type": "Feature",
  "properties": {
    "hierarchy": [
      "tgn:1137369",
      "tgn:1000003",
      "tgn:7011670",
      "tgn:7006660",
      "tgn:7029392"
    ],
    "placetype": [
      "aat:300008347"
    ],
    "id": 1137369,
    "name:xx": "Dmytrivka"
  }
}
