{
  "geometry": {
    "type": "Point",
    "coordinates": [
      -107.1833,
      34.0833
    ]
  },
  "type": "Feature",
  "properties": {
    "hierarchy": [
      "tgn:2428051",
      "tgn:1000001",
      "tgn:7012149",
      "tgn:2001456",
      "tgn:7007566",
      "tgn:7029392"
    ],
    "placetype": [
      "aat:300000390"
    ],
    "id": 2428051,
    "name:xx": "Juanita Tunnel"
  }
}
