{
  "geometry": {
    "type": "Point",
    "coordinates": [
      -75.5167,
      39.2833
    ]
  },
  "type": "Feature",
  "properties": {
    "hierarchy": [
      "tgn:2380944",
      "tgn:1002538",
      "tgn:1000001",
      "tgn:7012149",
      "tgn:7007239",
      "tgn:7029392"
    ],
    "placetype": [
      "aat:300008699"
    ],
    "id": 2380944,
    "name:xx": "Hawkey Branch"
  }
}
