{
  "geometry": {
    "type": "Point",
    "coordinates": [
      30.742474,
      27.84143
    ]
  },
  "type": "Feature",
  "properties": {
    "hierarchy": [
      "tgn:7535703",
      "tgn:7001242",
      "tgn:7016833",
      "tgn:1001088",
      "tgn:7029392"
    ],
    "placetype": [
      "aat:300008347"
    ],
    "name:en": "Ibshādāt",
    "id": 7535703
  }
}
