{
  "geometry": {
    "type": "Point",
    "coordinates": [
      -82.5833,
      42.6167
    ]
  },
  "type": "Feature",
  "properties": {
    "hierarchy": [
      "tgn:2052960",
      "tgn:1000001",
      "tgn:7012149",
      "tgn:7016056",
      "tgn:7007520",
      "tgn:7029392"
    ],
    "placetype": [
      "aat:300008347"
    ],
    "id": 2052960,
    "name:xx": "Pearl Beach"
  }
}
