{
  "geometry": {
    "type": "Point",
    "coordinates": [
      -119.6167,
      39.1167
    ]
  },
  "type": "Feature",
  "properties": {
    "hierarchy": [
      "tgn:2370757",
      "tgn:1000001",
      "tgn:7012149",
      "tgn:7007526",
      "tgn:7029392"
    ],
    "placetype": [
      "aat:300008761"
    ],
    "id": 2370757,
    "name:xx": "Hackett Canyon"
  }
}
