{
  "geometry": {
    "type": "Point",
    "coordinates": [
      33.874812,
      30.24254
    ]
  },
  "type": "Feature",
  "properties": {
    "hierarchy": [
      "tgn:7544418",
      "tgn:7001242",
      "tgn:7016833",
      "tgn:7001335",
      "tgn:7029392"
    ],
    "placetype": [
      "aat:300379998"
    ],
    "name:en": "Khubayţ al Kabīr, Wādī",
    "id": 7544418
  }
}
