{
  "geometry": {
    "type": "Point",
    "coordinates": [
      -83.7333,
      37.0167
    ]
  },
  "type": "Feature",
  "properties": {
    "hierarchy": [
      "tgn:2634079",
      "tgn:1000001",
      "tgn:2000782",
      "tgn:7012149",
      "tgn:7007255",
      "tgn:7029392"
    ],
    "placetype": [
      "aat:300008699"
    ],
    "id": 2634079,
    "name:xx": "Russell Branch"
  }
}
