{
  "geometry": {
    "type": "Point",
    "coordinates": [
      -75.5833,
      39.05
    ]
  },
  "type": "Feature",
  "properties": {
    "hierarchy": [
      "tgn:2386887",
      "tgn:1002538",
      "tgn:1000001",
      "tgn:7012149",
      "tgn:7007239",
      "tgn:7029392"
    ],
    "placetype": [
      "aat:300008699"
    ],
    "id": 2386887,
    "name:xx": "Heron Drain"
  }
}
