{
  "geometry": {
    "type": "Point",
    "coordinates": [
      10.366667,
      51.85
    ]
  },
  "type": "Feature",
  "properties": {
    "hierarchy": [
      "tgn:7174566",
      "tgn:1000003",
      "tgn:7003676",
      "tgn:7000084",
      "tgn:7029392"
    ],
    "placetype": [
      "aat:300008688"
    ],
    "id": 7174566,
    "name:xx": "Großer Kellerhals Teich"
  }
}
