{
  "geometry": {
    "type": "Point",
    "coordinates": [
      -100.125,
      21.0625
    ]
  },
  "type": "Feature",
  "properties": {
    "hierarchy": [
      "tgn:7419106",
      "tgn:7005584",
      "tgn:1000001",
      "tgn:7005560",
      "tgn:7029392"
    ],
    "placetype": [
      "aat:300008811"
    ],
    "id": 7419106,
    "name:xx": "Los Gallos, Mesa"
  }
}
