{
  "type": "FeatureCollection",
  "features": [
    {
      "geometry": {
        "type": "Point",
        "coordinates": [
          25.159858,
          29.317215
        ]
      },
      "type": "Feature",
      "properties": {
        "hierarchy": [
          "tgn:7533940",
          "tgn:7001242",
          "tgn:7016833",
          "tgn:1001418",
          "tgn:7029392"
        ],
        "placetype": [
          "aat:300386891"
        ],
        "name:en": "Maghāribah, Ḩaţīyat al",
        "id": 7533940
      }
    },
    {
      "geometry": {
        "type": "Point",
        "coordinates": [
          33.376648,
          30.702323
        ]
      },
      "type": "Feature",
      "properties": {
        "hierarchy": [
          "tgn:7533941",
          "tgn:7001242",
          "tgn:7016833",
          "tgn:7001335",
          "tgn:7029392"
        ],
        "placetype": [
          "aat:300266640"
        ],
        "name:en": "Maghārah, Jabal al",
        "id": 7533941
      }
    },
    {
      "geometry": {
        "type": "Point",
        "coordinates": [
          33.391667,
          30.696389
        ]
      },
      "type": "Feature",
      "properties": {
        "hierarchy": [
          "tgn:7533942",
          "tgn:7001242",
          "tgn:7016833",
          "tgn:7001335",
          "tgn:7029392"
        ],
        "placetype": [
          "aat:300006207"
        ],
        "name:en": "Bi'r al Maghārah",
        "id": 7533942
      }
    },
    {
      "geometry": {
        "type": "Point",
        "coordinates": [
          25.466667,
          29.216667
        ]
      },
      "type": "Feature",
      "properties": {
        "hierarchy": [
          "tgn:7533943",
          "tgn:7001242",
          "tgn:7016833",
          "tgn:1001418",
          "tgn:7029392"
        ],
        "placetype": [
          "aat:300008697"
        ],
        "name:en": "Maghārah, 'Ayn al",
        "id": 7533943
      }
    },
    {
      "geometry": {
        "type": "Point",
        "coordinates": [
          33.468032,
          30.748225
        ]
      },
      "type": "Feature",
      "properties": {
        "hierarchy": [
          "tgn:7533944",
          "tgn:7001242",
          "tgn:7016833",
          "tgn:7001335",
          "tgn:7029392"
        ],
        "placetype": [
          "aat:300379998"
        ],
        "name:en": "Maghārah, Wādī al",
        "id": 7533944
      }
    },
    {
      "geometry": {
        "type": "Point",
        "coordinates": [
          33.359769,
          28.900745
        ]
      },
      "type": "Feature",
      "properties": {
        "hierarchy": [
          "tgn:7533945",
          "tgn:7001242",
          "tgn:7016833",
          "tgn:7001336",
          "tgn:7029392"
        ],
        "placetype": [
          "aat:300008795"
        ],
        "id": 7533945,
        "name:xx": "Maghārah, Jabal al"
      }
    },
    {
      "geometry": {
        "type": "Point",
        "coordinates": [
          30.866667,
          28.65
        ]
      },
      "type": "Feature",
      "properties": {
        "hierarchy": [
          "tgn:7533947",
          "tgn:7001242",
          "tgn:7016833",
          "tgn:1001088",
          "tgn:7029392"
        ],
        "placetype": [
          "aat:300008791"
        ],
        "name:en": "Maghāghah, Jazīrat",
        "id": 7533947
      }
    },
    {
      "geometry": {
        "type": "Point",
        "coordinates": [
          34.179795,
          28.307126
        ]
      },
      "type": "Feature",
      "properties": {
        "hierarchy": [
          "tgn:7533949",
          "tgn:7001242",
          "tgn:7016833",
          "tgn:7001336",
          "tgn:7029392"
        ],
        "placetype": [
          "aat:300379998"
        ],
        "name:en": "Mujayrāt, Wādī",
        "id": 7533949
      }
    }
  ]
}
