{
  "geometry": {
    "type": "Point",
    "coordinates": [
      -81.4167,
      28.5833
    ]
  },
  "type": "Feature",
  "properties": {
    "hierarchy": [
      "tgn:2756159",
      "tgn:1000001",
      "tgn:7012149",
      "tgn:1002749",
      "tgn:7007240",
      "tgn:7029392"
    ],
    "placetype": [
      "aat:300008680"
    ],
    "id": 2756159,
    "name:xx": "Wekiva, Lake"
  }
}
