{
  "geometry": {
    "type": "Point",
    "coordinates": [
      -82.7167,
      37.7333
    ]
  },
  "type": "Feature",
  "properties": {
    "hierarchy": [
      "tgn:2286163",
      "tgn:1000001",
      "tgn:7012149",
      "tgn:2000789",
      "tgn:7007255",
      "tgn:7029392"
    ],
    "placetype": [
      "aat:300006191"
    ],
    "id": 2286163,
    "name:xx": "Dewey Lake"
  }
}
