{
  "geometry": {
    "type": "Point",
    "coordinates": [
      -122.8833,
      42.0333
    ]
  },
  "type": "Feature",
  "properties": {
    "hierarchy": [
      "tgn:2302505",
      "tgn:1000001",
      "tgn:7012149",
      "tgn:2001711",
      "tgn:7007708",
      "tgn:7029392"
    ],
    "placetype": [
      "aat:300008697"
    ],
    "id": 2302505,
    "name:xx": "Dutchman Spring"
  }
}
