{
  "geometry": {
    "type": "Point",
    "coordinates": [
      -74.0333,
      41.2667
    ]
  },
  "type": "Feature",
  "properties": {
    "hierarchy": [
      "tgn:2563496",
      "tgn:1000001",
      "tgn:7012149",
      "tgn:1002833",
      "tgn:7007568",
      "tgn:7029392"
    ],
    "placetype": [
      "aat:300008680"
    ],
    "id": 2563496,
    "name:xx": "Owl Lake"
  }
}
