{
  "geometry": {
    "type": "Point",
    "coordinates": [
      151.75,
      -32.7833
    ]
  },
  "type": "Feature",
  "properties": {
    "hierarchy": [
      "tgn:1098040",
      "tgn:7000490",
      "tgn:1000006",
      "tgn:7001828",
      "tgn:7029392"
    ],
    "placetype": [
      "aat:300008347"
    ],
    "id": 1098040,
    "name:xx": "Raymond Terrace"
  }
}
