{
  "geometry": {
    "type": "Point",
    "coordinates": [
      88.2667,
      22.5333
    ]
  },
  "type": "Feature",
  "properties": {
    "hierarchy": [
      "tgn:1076476",
      "tgn:1000004",
      "tgn:7000198",
      "tgn:1001977",
      "tgn:7029392"
    ],
    "placetype": [
      "aat:300008347"
    ],
    "id": 1076476,
    "name:xx": "Pānchur"
  }
}
