{
  "geometry": {
    "type": "Point",
    "coordinates": [
      -58.8833,
      -32.6833
    ]
  },
  "type": "Feature",
  "properties": {
    "hierarchy": [
      "tgn:1020132",
      "tgn:7006477",
      "tgn:1001237",
      "tgn:1000002",
      "tgn:7029392"
    ],
    "placetype": [
      "aat:300008347"
    ],
    "id": 1020132,
    "name:xx": "Urdinarrain"
  }
}
