{
  "geometry": {
    "type": "Point",
    "coordinates": [
      -121.0333,
      47.85
    ]
  },
  "type": "Feature",
  "properties": {
    "hierarchy": [
      "tgn:2444214",
      "tgn:1000001",
      "tgn:1002260",
      "tgn:7012149",
      "tgn:7007920",
      "tgn:7029392"
    ],
    "placetype": [
      "aat:300008798"
    ],
    "id": 2444214,
    "name:xx": "Labyrinth Mountain"
  }
}
