{
  "geometry": {
    "type": "Point",
    "coordinates": [
      -79.2833,
      40.8167
    ]
  },
  "type": "Feature",
  "properties": {
    "hierarchy": [
      "tgn:2086806",
      "tgn:1002153",
      "tgn:1000001",
      "tgn:7012149",
      "tgn:7007710",
      "tgn:7029392"
    ],
    "placetype": [
      "aat:300008347"
    ],
    "id": 2086806,
    "name:xx": "Bryan"
  }
}
