{
  "geometry": {
    "type": "Point",
    "coordinates": [
      -75.3667,
      41.45
    ]
  },
  "type": "Feature",
  "properties": {
    "hierarchy": [
      "tgn:2136928",
      "tgn:1000001",
      "tgn:7012149",
      "tgn:1003008",
      "tgn:7007710",
      "tgn:7029392"
    ],
    "placetype": [
      "aat:300008706"
    ],
    "id": 2136928,
    "name:xx": "Ariel Creek"
  }
}
