{
  "type": "FeatureCollection",
  "features": [
    {
      "geometry": {
        "type": "Point",
        "coordinates": [
          -147.5833,
          65
        ]
      },
      "type": "Feature",
      "properties": {
        "hierarchy": [
          "tgn:2337700",
          "tgn:7006450",
          "tgn:1000001",
          "tgn:7019674",
          "tgn:7012149",
          "tgn:7029392"
        ],
        "placetype": [
          "aat:300008706"
        ],
        "id": 2337700,
        "name:xx": "Fox Creek"
      }
    },
    {
      "geometry": {
        "type": "Point",
        "coordinates": [
          -176.0833,
          52.0333
        ]
      },
      "type": "Feature",
      "properties": {
        "hierarchy": [
          "tgn:2337701",
          "tgn:7030516",
          "tgn:7006450",
          "tgn:1000001",
          "tgn:7012149",
          "tgn:7029392"
        ],
        "placetype": [
          "aat:300008706"
        ],
        "id": 2337701,
        "name:xx": "Fox Creek"
      }
    },
    {
      "geometry": {
        "type": "Point",
        "coordinates": [
          -90.3833,
          36.2667
        ]
      },
      "type": "Feature",
      "properties": {
        "hierarchy": [
          "tgn:2337702",
          "tgn:1000001",
          "tgn:7016172",
          "tgn:7012149",
          "tgn:7029392"
        ],
        "placetype": [
          "aat:300008706"
        ],
        "id": 2337702,
        "name:xx": "Fox Creek"
      }
    },
    {
      "geometry": {
        "type": "Point",
        "coordinates": [
          -121.3167,
          39.75
        ]
      },
      "type": "Feature",
      "properties": {
        "hierarchy": [
          "tgn:2337703",
          "tgn:1000001",
          "tgn:1002218",
          "tgn:7012149",
          "tgn:7007157",
          "tgn:7029392"
        ],
        "placetype": [
          "aat:300008706"
        ],
        "id": 2337703,
        "name:xx": "Fox Creek"
      }
    },
    {
      "geometry": {
        "type": "Point",
        "coordinates": [
          -121.8167,
          40.9833
        ]
      },
      "type": "Feature",
      "properties": {
        "hierarchy": [
          "tgn:2337704",
          "tgn:1000001",
          "tgn:7012149",
          "tgn:7007157",
          "tgn:2000188",
          "tgn:7029392"
        ],
        "placetype": [
          "aat:300008706"
        ],
        "id": 2337704,
        "name:xx": "Fox Creek"
      }
    },
    {
      "geometry": {
        "type": "Point",
        "coordinates": [
          -123.6,
          39.7333
        ]
      },
      "type": "Feature",
      "properties": {
        "hierarchy": [
          "tgn:2337705",
          "tgn:1000001",
          "tgn:7012149",
          "tgn:7007157",
          "tgn:2000185",
          "tgn:7029392"
        ],
        "placetype": [
          "aat:300008706"
        ],
        "id": 2337705,
        "name:xx": "Fox Creek"
      }
    },
    {
      "geometry": {
        "type": "Point",
        "coordinates": [
          -123.95,
          40.5167
        ]
      },
      "type": "Feature",
      "properties": {
        "hierarchy": [
          "tgn:2337706",
          "tgn:1000001",
          "tgn:7012149",
          "tgn:2000181",
          "tgn:7007157",
          "tgn:7029392"
        ],
        "placetype": [
          "aat:300008706"
        ],
        "id": 2337706,
        "name:xx": "Fox Creek"
      }
    },
    {
      "geometry": {
        "type": "Point",
        "coordinates": [
          -122.8333,
          41.2
        ]
      },
      "type": "Feature",
      "properties": {
        "hierarchy": [
          "tgn:2337707",
          "tgn:1000001",
          "tgn:7012149",
          "tgn:7007157",
          "tgn:2000189",
          "tgn:7029392"
        ],
        "placetype": [
          "aat:300008706"
        ],
        "id": 2337707,
        "name:xx": "Fox Creek"
      }
    },
    {
      "geometry": {
        "type": "Point",
        "coordinates": [
          -119.8,
          37.5167
        ]
      },
      "type": "Feature",
      "properties": {
        "hierarchy": [
          "tgn:2337708",
          "tgn:1000001",
          "tgn:7012149",
          "tgn:7007157",
          "tgn:7014004",
          "tgn:7029392"
        ],
        "placetype": [
          "aat:300008706"
        ],
        "id": 2337708,
        "name:xx": "Fox Creek"
      }
    },
    {
      "geometry": {
        "type": "Point",
        "coordinates": [
          -118.1667,
          34.3667
        ]
      },
      "type": "Feature",
      "properties": {
        "hierarchy": [
          "tgn:2337709",
          "tgn:1000001",
          "tgn:7012149",
          "tgn:7007157",
          "tgn:1002608",
          "tgn:7029392"
        ],
        "placetype": [
          "aat:300008706"
        ],
        "id": 2337709,
        "name:xx": "Fox Creek"
      }
    }
  ]
}
