{
  "type": "FeatureCollection",
  "features": [
    {
      "geometry": {
        "type": "Point",
        "coordinates": [
          -105.1167,
          36.2833
        ]
      },
      "type": "Feature",
      "properties": {
        "hierarchy": [
          "tgn:2155110",
          "tgn:1000001",
          "tgn:2001432",
          "tgn:7012149",
          "tgn:7007566",
          "tgn:7029392"
        ],
        "placetype": [
          "aat:300008680"
        ],
        "id": 2155110,
        "name:xx": "Bear Lake"
      }
    },
    {
      "geometry": {
        "type": "Point",
        "coordinates": [
          -105.4167,
          36.5333
        ]
      },
      "type": "Feature",
      "properties": {
        "hierarchy": [
          "tgn:2155111",
          "tgn:1000001",
          "tgn:7012149",
          "tgn:2001457",
          "tgn:7007566",
          "tgn:7029392"
        ],
        "placetype": [
          "aat:300008680"
        ],
        "id": 2155111,
        "name:xx": "Bear Lake"
      }
    },
    {
      "geometry": {
        "type": "Point",
        "coordinates": [
          -107.0333,
          36.3167
        ]
      },
      "type": "Feature",
      "properties": {
        "hierarchy": [
          "tgn:2155112",
          "tgn:1000001",
          "tgn:7012149",
          "tgn:2001449",
          "tgn:7007566",
          "tgn:7029392"
        ],
        "placetype": [
          "aat:300006191"
        ],
        "id": 2155112,
        "name:xx": "Bear Lake"
      }
    },
    {
      "geometry": {
        "type": "Point",
        "coordinates": [
          -79.3833,
          42.3333
        ]
      },
      "type": "Feature",
      "properties": {
        "hierarchy": [
          "tgn:2155113",
          "tgn:1000001",
          "tgn:1002259",
          "tgn:7012149",
          "tgn:7007568",
          "tgn:7029392"
        ],
        "placetype": [
          "aat:300008680"
        ],
        "id": 2155113,
        "name:xx": "Bear Lake"
      }
    },
    {
      "geometry": {
        "type": "Point",
        "coordinates": [
          -74.7,
          43.4667
        ]
      },
      "type": "Feature",
      "properties": {
        "hierarchy": [
          "tgn:2155114",
          "tgn:1000001",
          "tgn:7012149",
          "tgn:1002440",
          "tgn:7007568",
          "tgn:7029392"
        ],
        "placetype": [
          "aat:300008680"
        ],
        "id": 2155114,
        "name:xx": "Bear Lake"
      }
    },
    {
      "geometry": {
        "type": "Point",
        "coordinates": [
          -75.05,
          43.5833
        ]
      },
      "type": "Feature",
      "properties": {
        "hierarchy": [
          "tgn:2155115",
          "tgn:1000001",
          "tgn:7012149",
          "tgn:1002472",
          "tgn:7007568",
          "tgn:7029392"
        ],
        "placetype": [
          "aat:300008680"
        ],
        "id": 2155115,
        "name:xx": "Bear Lake"
      }
    },
    {
      "geometry": {
        "type": "Point",
        "coordinates": [
          -75.15,
          44.15
        ]
      },
      "type": "Feature",
      "properties": {
        "hierarchy": [
          "tgn:2155116",
          "tgn:1000001",
          "tgn:7012149",
          "tgn:7016021",
          "tgn:7007568",
          "tgn:7029392"
        ],
        "placetype": [
          "aat:300008680"
        ],
        "id": 2155116,
        "name:xx": "Bear Lake"
      }
    },
    {
      "geometry": {
        "type": "Point",
        "coordinates": [
          -100.3,
          48.8667
        ]
      },
      "type": "Feature",
      "properties": {
        "hierarchy": [
          "tgn:2155117",
          "tgn:7020393",
          "tgn:1000001",
          "tgn:7012149",
          "tgn:7007705",
          "tgn:7029392"
        ],
        "placetype": [
          "aat:300008680"
        ],
        "id": 2155117,
        "name:xx": "Bear Lake"
      }
    },
    {
      "geometry": {
        "type": "Point",
        "coordinates": [
          -122.0333,
          44.65
        ]
      },
      "type": "Feature",
      "properties": {
        "hierarchy": [
          "tgn:2155118",
          "tgn:1000001",
          "tgn:7012149",
          "tgn:2001717",
          "tgn:7007708",
          "tgn:7029392"
        ],
        "placetype": [
          "aat:300008680"
        ],
        "id": 2155118,
        "name:xx": "Bear Lake"
      }
    },
    {
      "geometry": {
        "type": "Point",
        "coordinates": [
          -117.3333,
          45.1
        ]
      },
      "type": "Feature",
      "properties": {
        "hierarchy": [
          "tgn:2155119",
          "tgn:1000001",
          "tgn:7012149",
          "tgn:2001721",
          "tgn:7007708",
          "tgn:7029392"
        ],
        "placetype": [
          "aat:300008680"
        ],
        "id": 2155119,
        "name:xx": "Bear Lake"
      }
    }
  ]
}
