{
  "geometry": {
    "type": "Point",
    "coordinates": [
      -94.75,
      39.6167
    ]
  },
  "type": "Feature",
  "properties": {
    "hierarchy": [
      "tgn:2240884",
      "tgn:1000001",
      "tgn:2001175",
      "tgn:7012149",
      "tgn:7007523",
      "tgn:7029392"
    ],
    "placetype": [
      "aat:300006191"
    ],
    "id": 2240884,
    "name:xx": "Clarence Jones East Lake"
  }
}
