{
  "geometry": {
    "type": "Point",
    "coordinates": [
      30.341193,
      30.371835
    ]
  },
  "type": "Feature",
  "properties": {
    "hierarchy": [
      "tgn:7544144",
      "tgn:7001242",
      "tgn:1001075",
      "tgn:7016833",
      "tgn:7029392"
    ],
    "placetype": [
      "aat:300008680"
    ],
    "name:en": "Abū Jiyād, Buḩayrat",
    "id": 7544144
  }
}
