{
  "geometry": {
    "type": "Point",
    "coordinates": [
      14.266667,
      52.25
    ]
  },
  "type": "Feature",
  "properties": {
    "hierarchy": [
      "tgn:7184915",
      "tgn:7000096",
      "tgn:1000003",
      "tgn:7000084",
      "tgn:7029392"
    ],
    "placetype": [
      "aat:300055621"
    ],
    "id": 7184915,
    "name:xx": "Görziger Dorfstelle"
  }
}
