{
  "geometry": {
    "type": "Point",
    "coordinates": [
      -83.0333,
      40.3333
    ]
  },
  "type": "Feature",
  "properties": {
    "hierarchy": [
      "tgn:2351252",
      "tgn:1000001",
      "tgn:1002329",
      "tgn:7012149",
      "tgn:7007706",
      "tgn:7029392"
    ],
    "placetype": [
      "aat:300006191"
    ],
    "id": 2351252,
    "name:xx": "Gleasonkamp Pond"
  }
}
