{
  "geometry": {
    "type": "Point",
    "coordinates": [
      -118.6167,
      48.1333
    ]
  },
  "type": "Feature",
  "properties": {
    "hierarchy": [
      "tgn:2654991",
      "tgn:1000001",
      "tgn:2002243",
      "tgn:7012149",
      "tgn:7007920",
      "tgn:7029392"
    ],
    "placetype": [
      "aat:300000390"
    ],
    "id": 2654991,
    "name:xx": "Shamrock Mine"
  }
}
