{
  "geometry": {
    "type": "Point",
    "coordinates": [
      -72.7833,
      43.4833
    ]
  },
  "type": "Feature",
  "properties": {
    "hierarchy": [
      "tgn:2634104",
      "tgn:1000001",
      "tgn:1002840",
      "tgn:7012149",
      "tgn:7007828",
      "tgn:7029392"
    ],
    "placetype": [
      "aat:300008699"
    ],
    "id": 2634104,
    "name:xx": "Russell Brook"
  }
}
