{
  "geometry": {
    "type": "Point",
    "coordinates": [
      -83.8167,
      39.7833
    ]
  },
  "type": "Feature",
  "properties": {
    "hierarchy": [
      "tgn:2244294",
      "tgn:1000001",
      "tgn:1002274",
      "tgn:7012149",
      "tgn:7007706",
      "tgn:7029392"
    ],
    "placetype": [
      "aat:300008761"
    ],
    "id": 2244294,
    "name:xx": "Clifton Gorge"
  }
}
