{
  "geometry": {
    "type": "Point",
    "coordinates": [
      -76.3667,
      3.2667
    ]
  },
  "type": "Feature",
  "properties": {
    "hierarchy": [
      "tgn:1023945",
      "tgn:1000554",
      "tgn:1000050",
      "tgn:1000002",
      "tgn:7029392"
    ],
    "placetype": [
      "aat:300008347"
    ],
    "id": 1023945,
    "name:xx": "Puerto Tejada"
  }
}
