{
  "geometry": {
    "type": "Point",
    "coordinates": [
      -91.1167,
      42.0833
    ]
  },
  "type": "Feature",
  "properties": {
    "hierarchy": [
      "tgn:2160467",
      "tgn:1000001",
      "tgn:7012149",
      "tgn:7007253",
      "tgn:7029392"
    ],
    "placetype": [
      "aat:300008706"
    ],
    "id": 2160467,
    "name:xx": "Beers Creek"
  }
}
