{
  "geometry": {
    "type": "Point",
    "coordinates": [
      -83.4333,
      44.4167
    ]
  },
  "type": "Feature",
  "properties": {
    "hierarchy": [
      "tgn:2051936",
      "tgn:1000001",
      "tgn:7012149",
      "tgn:2000965",
      "tgn:7007520",
      "tgn:7029392"
    ],
    "placetype": [
      "aat:300008347"
    ],
    "id": 2051936,
    "name:xx": "Foote Site Village"
  }
}
