{
  "geometry": {
    "type": "Point",
    "coordinates": [
      74.164137,
      33.119854
    ]
  },
  "type": "Feature",
  "properties": {
    "hierarchy": [
      "tgn:7589032",
      "tgn:1000004",
      "tgn:7000198",
      "tgn:7000799",
      "tgn:7029392"
    ],
    "placetype": [
      "aat:300008347"
    ],
    "name:en": "Bhāla Khatar",
    "id": 7589032
  }
}
