{
  "geometry": {
    "type": "Point",
    "coordinates": [
      -112.2167,
      34.75
    ]
  },
  "type": "Feature",
  "properties": {
    "hierarchy": [
      "tgn:2212953",
      "tgn:1000001",
      "tgn:7006451",
      "tgn:7012149",
      "tgn:2000103",
      "tgn:7029392"
    ],
    "placetype": [
      "aat:300006191"
    ],
    "id": 2212953,
    "name:xx": "CCC Tank"
  }
}
