{
  "geometry": {
    "type": "Point",
    "coordinates": [
      -123.8167,
      40.2333
    ]
  },
  "type": "Feature",
  "properties": {
    "hierarchy": [
      "tgn:2693645",
      "tgn:1000001",
      "tgn:7012149",
      "tgn:2000181",
      "tgn:7007157",
      "tgn:7029392"
    ],
    "placetype": [
      "aat:300132451"
    ],
    "id": 2693645,
    "name:xx": "Stephens Grove"
  }
}
