{
  "geometry": {
    "type": "Point",
    "coordinates": [
      -58.4667,
      -34.4667
    ]
  },
  "type": "Feature",
  "properties": {
    "hierarchy": [
      "tgn:1136206",
      "tgn:1001160",
      "tgn:7006477",
      "tgn:1000002",
      "tgn:7029392"
    ],
    "placetype": [
      "aat:300386965"
    ],
    "id": 1136206,
    "name:xx": "Costanero, Canal"
  }
}
