{
  "geometry": {
    "type": "Point",
    "coordinates": [
      169.45,
      -43.75
    ]
  },
  "type": "Feature",
  "properties": {
    "hierarchy": [
      "tgn:7517737",
      "tgn:1009227",
      "tgn:1000226",
      "tgn:1000006",
      "tgn:7016850",
      "tgn:7029392"
    ],
    "placetype": [
      "aat:300008795"
    ],
    "name:en": "Kinnaird, Mount",
    "id": 7517737
  }
}
