{
  "geometry": {
    "type": "Point",
    "coordinates": [
      -79.3833,
      33.0167
    ]
  },
  "type": "Feature",
  "properties": {
    "hierarchy": [
      "tgn:2448081",
      "tgn:1000001",
      "tgn:2001734",
      "tgn:7012149",
      "tgn:7007712",
      "tgn:7029392"
    ],
    "placetype": [
      "aat:300008791"
    ],
    "id": 2448081,
    "name:xx": "Lighthouse Island"
  }
}
