{
  "geometry": {
    "type": "Point",
    "coordinates": [
      7.3333,
      47.85
    ]
  },
  "type": "Feature",
  "properties": {
    "hierarchy": [
      "tgn:7009159",
      "tgn:7002870",
      "tgn:1000003",
      "tgn:1000070",
      "tgn:7029392"
    ],
    "placetype": [
      "aat:300008347"
    ],
    "id": 7009159,
    "name:xx": "Ensisheim"
  }
}
