{
  "type": "FeatureCollection",
  "features": [
    {
      "geometry": {
        "type": "Point",
        "coordinates": [
          -99.566667,
          17.116667
        ]
      },
      "type": "Feature",
      "properties": {
        "hierarchy": [
          "tgn:7382750",
          "tgn:7005585",
          "tgn:1000001",
          "tgn:7005560",
          "tgn:7029392"
        ],
        "placetype": [
          "aat:300008347"
        ],
        "id": 7382750,
        "name:xx": "Omitlán"
      }
    },
    {
      "geometry": {
        "type": "Point",
        "coordinates": [
          -99.666667,
          17.5
        ]
      },
      "type": "Feature",
      "properties": {
        "hierarchy": [
          "tgn:7382751",
          "tgn:7005585",
          "tgn:1000001",
          "tgn:7005560",
          "tgn:7029392"
        ],
        "placetype": [
          "aat:300008347"
        ],
        "id": 7382751,
        "name:xx": "Omiltemi"
      }
    },
    {
      "geometry": {
        "type": "Point",
        "coordinates": [
          -98.316667,
          19.1
        ]
      },
      "type": "Feature",
      "properties": {
        "hierarchy": [
          "tgn:7382752",
          "tgn:1000001",
          "tgn:7005592",
          "tgn:7005560",
          "tgn:7029392"
        ],
        "placetype": [
          "aat:300008347"
        ],
        "id": 7382752,
        "name:xx": "Ometoxtla"
      }
    },
    {
      "geometry": {
        "type": "Point",
        "coordinates": [
          -98.483333,
          16.583333
        ]
      },
      "type": "Feature",
      "properties": {
        "hierarchy": [
          "tgn:7382753",
          "tgn:7005585",
          "tgn:1000001",
          "tgn:7005560",
          "tgn:7029392"
        ],
        "placetype": [
          "aat:300008699"
        ],
        "id": 7382753,
        "name:xx": "Ometepec, Río"
      }
    },
    {
      "geometry": {
        "type": "Point",
        "coordinates": [
          -114.916667,
          31.5
        ]
      },
      "type": "Feature",
      "properties": {
        "hierarchy": [
          "tgn:7382754",
          "tgn:1001835",
          "tgn:1000001",
          "tgn:7005560",
          "tgn:7029392"
        ],
        "placetype": [
          "aat:300132316"
        ],
        "id": 7382754,
        "name:xx": "Ometepec, Bahía"
      }
    },
    {
      "geometry": {
        "type": "Point",
        "coordinates": [
          -97.833333,
          18.85
        ]
      },
      "type": "Feature",
      "properties": {
        "hierarchy": [
          "tgn:7382755",
          "tgn:1000001",
          "tgn:7005592",
          "tgn:7005560",
          "tgn:7029392"
        ],
        "placetype": [
          "aat:300008347"
        ],
        "id": 7382755,
        "name:xx": "Ometepec"
      }
    },
    {
      "geometry": {
        "type": "Point",
        "coordinates": [
          -100.85,
          27.9
        ]
      },
      "type": "Feature",
      "properties": {
        "hierarchy": [
          "tgn:7382757",
          "tgn:1001853",
          "tgn:1000001",
          "tgn:7005560",
          "tgn:7029392"
        ],
        "placetype": [
          "aat:300387002"
        ],
        "id": 7382757,
        "name:xx": "Omerio de Peyotes"
      }
    },
    {
      "geometry": {
        "type": "Point",
        "coordinates": [
          -95.316667,
          18.35
        ]
      },
      "type": "Feature",
      "properties": {
        "hierarchy": [
          "tgn:7382758",
          "tgn:1000001",
          "tgn:7005599",
          "tgn:7005560",
          "tgn:7029392"
        ],
        "placetype": [
          "aat:300008347"
        ],
        "id": 7382758,
        "name:xx": "Omeapan"
      }
    },
    {
      "geometry": {
        "type": "Point",
        "coordinates": [
          -97.016667,
          19.7
        ]
      },
      "type": "Feature",
      "properties": {
        "hierarchy": [
          "tgn:7382759",
          "tgn:1000001",
          "tgn:7005599",
          "tgn:7005560",
          "tgn:7029392"
        ],
        "placetype": [
          "aat:300008347"
        ],
        "id": 7382759,
        "name:xx": "Omeapa"
      }
    }
  ]
}
