{
  "geometry": {
    "type": "Point",
    "coordinates": [
      -99.3667,
      33.95
    ]
  },
  "type": "Feature",
  "properties": {
    "hierarchy": [
      "tgn:2227955",
      "tgn:1000001",
      "tgn:7012149",
      "tgn:2002093",
      "tgn:7007826",
      "tgn:7029392"
    ],
    "placetype": [
      "aat:300006191"
    ],
    "id": 2227955,
    "name:xx": "Cedar Bluff Tank"
  }
}
