{
  "geometry": {
    "type": "Point",
    "coordinates": [
      -90.1833,
      41.5667
    ]
  },
  "type": "Feature",
  "properties": {
    "hierarchy": [
      "tgn:2427816",
      "tgn:1000001",
      "tgn:7012149",
      "tgn:2000528",
      "tgn:7007251",
      "tgn:7029392"
    ],
    "placetype": [
      "aat:300008699"
    ],
    "id": 2427816,
    "name:xx": "Joslin Slough"
  }
}
