{
  "geometry": {
    "type": "Point",
    "coordinates": [
      30.3167,
      58.65
    ]
  },
  "type": "Feature",
  "properties": {
    "hierarchy": [
      "tgn:1052574",
      "tgn:1000004",
      "tgn:4008031",
      "tgn:7018214",
      "tgn:7002435",
      "tgn:7029392"
    ],
    "placetype": [
      "aat:300008347"
    ],
    "id": 1052574,
    "name:xx": "Batetskiy"
  }
}
