{
  "geometry": {
    "type": "Point",
    "coordinates": [
      -82.6833,
      27.7167
    ]
  },
  "type": "Feature",
  "properties": {
    "hierarchy": [
      "tgn:2226656",
      "tgn:1000001",
      "tgn:7012149",
      "tgn:1002790",
      "tgn:7007240",
      "tgn:7029392"
    ],
    "placetype": [
      "aat:300008850"
    ],
    "id": 2226656,
    "name:xx": "Cats Point"
  }
}
