{
  "geometry": {
    "type": "Point",
    "coordinates": [
      -159.7833,
      22.0167
    ]
  },
  "type": "Feature",
  "properties": {
    "hierarchy": [
      "tgn:2747513",
      "tgn:1007657",
      "tgn:1002534",
      "tgn:1000001",
      "tgn:7012149",
      "tgn:7007249",
      "tgn:7029392"
    ],
    "placetype": [
      "aat:300008699"
    ],
    "id": 2747513,
    "name:xx": "Waieli Draw"
  }
}
