{
  "geometry": {
    "type": "Point",
    "coordinates": [
      30.35,
      31.25
    ]
  },
  "type": "Feature",
  "properties": {
    "hierarchy": [
      "tgn:7539668",
      "tgn:7001242",
      "tgn:1001075",
      "tgn:7016833",
      "tgn:7029392"
    ],
    "placetype": [
      "aat:300008791"
    ],
    "name:en": "Qar'ah, Jazīrat al",
    "id": 7539668
  }
}
