{
  "geometry": {
    "type": "Point",
    "coordinates": [
      -95.5167,
      44.3333
    ]
  },
  "type": "Feature",
  "properties": {
    "hierarchy": [
      "tgn:2428369",
      "tgn:1000001",
      "tgn:7012149",
      "tgn:2001062",
      "tgn:7007521",
      "tgn:7029392"
    ],
    "placetype": [
      "aat:300006075"
    ],
    "id": 2428369,
    "name:xx": "Judicial Ditch Number Twelve"
  }
}
