{
  "geometry": {
    "type": "Point",
    "coordinates": [
      -78.4167,
      34.4167
    ]
  },
  "type": "Feature",
  "properties": {
    "hierarchy": [
      "tgn:2442701",
      "tgn:1000001",
      "tgn:2001471",
      "tgn:7012149",
      "tgn:7007709",
      "tgn:7029392"
    ],
    "placetype": [
      "aat:300008699"
    ],
    "id": 2442701,
    "name:xx": "Kuhns"
  }
}
