{
  "geometry": {
    "type": "Point",
    "coordinates": [
      -110.8333,
      41.9333
    ]
  },
  "type": "Feature",
  "properties": {
    "hierarchy": [
      "tgn:2623892",
      "tgn:1000001",
      "tgn:7012149",
      "tgn:2002376",
      "tgn:7007923",
      "tgn:7029392"
    ],
    "placetype": [
      "aat:300266640"
    ],
    "id": 2623892,
    "name:xx": "Rock Creek Ridge"
  }
}
