{
  "geometry": {
    "type": "Point",
    "coordinates": [
      -98.25,
      31.5167
    ]
  },
  "type": "Feature",
  "properties": {
    "hierarchy": [
      "tgn:2377840",
      "tgn:1000001",
      "tgn:7012149",
      "tgn:2001996",
      "tgn:7007826",
      "tgn:7029392"
    ],
    "placetype": [
      "aat:300386845"
    ],
    "id": 2377840,
    "name:xx": "Harrington Cove"
  }
}
