{
  "geometry": {
    "type": "Point",
    "coordinates": [
      -92.9167,
      29.9333
    ]
  },
  "type": "Feature",
  "properties": {
    "hierarchy": [
      "tgn:2181506",
      "tgn:1000001",
      "tgn:7020676",
      "tgn:7012149",
      "tgn:7007256",
      "tgn:7029392"
    ],
    "placetype": [
      "aat:300008791"
    ],
    "id": 2181506,
    "name:xx": "Blue Grove"
  }
}
