{
  "geometry": {
    "type": "Point",
    "coordinates": [
      -0.2167,
      7.7667
    ]
  },
  "type": "Feature",
  "properties": {
    "hierarchy": [
      "tgn:1001640",
      "tgn:7001242",
      "tgn:1000166",
      "tgn:7029392"
    ],
    "placetype": [
      "aat:300387064",
      "aat:300236112"
    ],
    "id": 1001640,
    "name:xx": "Brong-Ahafo"
  }
}
