{
  "geometry": {
    "type": "Point",
    "coordinates": [
      -91.8667,
      35.85
    ]
  },
  "type": "Feature",
  "properties": {
    "hierarchy": [
      "tgn:2318010",
      "tgn:1000001",
      "tgn:7016172",
      "tgn:7012149",
      "tgn:2000173",
      "tgn:7029392"
    ],
    "placetype": [
      "aat:300008746"
    ],
    "id": 2318010,
    "name:xx": "Ennis Cave"
  }
}
