{
  "geometry": {
    "type": "Point",
    "coordinates": [
      -104.0333,
      36.9167
    ]
  },
  "type": "Feature",
  "properties": {
    "hierarchy": [
      "tgn:1134879",
      "tgn:1000001",
      "tgn:7012149",
      "tgn:7029392"
    ],
    "placetype": [
      "aat:300008706"
    ],
    "id": 1134879,
    "name:xx": "Trinchera Creek"
  }
}
