{
  "geometry": {
    "type": "Point",
    "coordinates": [
      -91.2167,
      45.7667
    ]
  },
  "type": "Feature",
  "properties": {
    "hierarchy": [
      "tgn:2122205",
      "tgn:1000001",
      "tgn:7012149",
      "tgn:2002353",
      "tgn:7007922",
      "tgn:7029392"
    ],
    "placetype": [
      "aat:300008347"
    ],
    "id": 2122205,
    "name:xx": "Radisson"
  }
}
