{
  "type": "FeatureCollection",
  "features": [
    {
      "geometry": {
        "type": "Point",
        "coordinates": [
          -92.9167,
          47.45
        ]
      },
      "type": "Feature",
      "properties": {
        "hierarchy": [
          "tgn:2755210",
          "tgn:1000001",
          "tgn:7012149",
          "tgn:2001067",
          "tgn:7007521",
          "tgn:7029392"
        ],
        "placetype": [
          "aat:300000390"
        ],
        "id": 2755210,
        "name:xx": "Webb Mine"
      }
    },
    {
      "geometry": {
        "type": "Point",
        "coordinates": [
          -84.5333,
          35.5833
        ]
      },
      "type": "Feature",
      "properties": {
        "hierarchy": [
          "tgn:2755211",
          "tgn:1000001",
          "tgn:7012149",
          "tgn:7022542",
          "tgn:7007825",
          "tgn:7029392"
        ],
        "placetype": [
          "aat:300000390"
        ],
        "id": 2755211,
        "name:xx": "Webb Mine"
      }
    },
    {
      "geometry": {
        "type": "Point",
        "coordinates": [
          -112.8833,
          33.2167
        ]
      },
      "type": "Feature",
      "properties": {
        "hierarchy": [
          "tgn:2755212",
          "tgn:1000001",
          "tgn:7006451",
          "tgn:7012149",
          "tgn:2000097",
          "tgn:7029392"
        ],
        "placetype": [
          "aat:300008798"
        ],
        "id": 2755212,
        "name:xx": "Webb Mountain"
      }
    },
    {
      "geometry": {
        "type": "Point",
        "coordinates": [
          -115.3333,
          48.8167
        ]
      },
      "type": "Feature",
      "properties": {
        "hierarchy": [
          "tgn:2755213",
          "tgn:1000001",
          "tgn:7012149",
          "tgn:2001286",
          "tgn:7007524",
          "tgn:7029392"
        ],
        "placetype": [
          "aat:300008798"
        ],
        "id": 2755213,
        "name:xx": "Webb Mountain"
      }
    },
    {
      "geometry": {
        "type": "Point",
        "coordinates": [
          -74.7833,
          44
        ]
      },
      "type": "Feature",
      "properties": {
        "hierarchy": [
          "tgn:2755214",
          "tgn:1000001",
          "tgn:7012149",
          "tgn:1002440",
          "tgn:7007568",
          "tgn:7029392"
        ],
        "placetype": [
          "aat:300008798"
        ],
        "id": 2755214,
        "name:xx": "Webb Mountain"
      }
    },
    {
      "geometry": {
        "type": "Point",
        "coordinates": [
          -88.6333,
          35.9667
        ]
      },
      "type": "Feature",
      "properties": {
        "hierarchy": [
          "tgn:2755215",
          "tgn:1000001",
          "tgn:7012149",
          "tgn:2001845",
          "tgn:7007825",
          "tgn:7029392"
        ],
        "placetype": [
          "aat:300008798"
        ],
        "id": 2755215,
        "name:xx": "Webb Mountain"
      }
    },
    {
      "geometry": {
        "type": "Point",
        "coordinates": [
          -83.35,
          35.7833
        ]
      },
      "type": "Feature",
      "properties": {
        "hierarchy": [
          "tgn:2755216",
          "tgn:1000001",
          "tgn:7012149",
          "tgn:2001914",
          "tgn:7007825",
          "tgn:7029392"
        ],
        "placetype": [
          "aat:300008798"
        ],
        "id": 2755216,
        "name:xx": "Webb Mountain"
      }
    },
    {
      "geometry": {
        "type": "Point",
        "coordinates": [
          -81.9333,
          36.9333
        ]
      },
      "type": "Feature",
      "properties": {
        "hierarchy": [
          "tgn:2755217",
          "tgn:1000001",
          "tgn:7012149",
          "tgn:2002188",
          "tgn:7007919",
          "tgn:7029392"
        ],
        "placetype": [
          "aat:300008798"
        ],
        "id": 2755217,
        "name:xx": "Webb Mountain"
      }
    },
    {
      "geometry": {
        "type": "Point",
        "coordinates": [
          -123.0167,
          47.6167
        ]
      },
      "type": "Feature",
      "properties": {
        "hierarchy": [
          "tgn:2755218",
          "tgn:1000001",
          "tgn:7012149",
          "tgn:1002645",
          "tgn:7007920",
          "tgn:7029392"
        ],
        "placetype": [
          "aat:300008798"
        ],
        "id": 2755218,
        "name:xx": "Webb Mountain"
      }
    },
    {
      "geometry": {
        "type": "Point",
        "coordinates": [
          -109.9667,
          32.8
        ]
      },
      "type": "Feature",
      "properties": {
        "hierarchy": [
          "tgn:2755219",
          "tgn:1000001",
          "tgn:7006451",
          "tgn:2000094",
          "tgn:7012149",
          "tgn:7029392"
        ],
        "placetype": [
          "aat:300006191"
        ],
        "id": 2755219,
        "name:xx": "Webb One Tank"
      }
    }
  ]
}
