{
  "type": "FeatureCollection",
  "features": [
    {
      "geometry": {
        "type": "Point",
        "coordinates": [
          -88.05,
          32.6833
        ]
      },
      "type": "Feature",
      "properties": {
        "hierarchy": [
          "tgn:2185870",
          "tgn:7002659",
          "tgn:1000001",
          "tgn:7012149",
          "tgn:2000059",
          "tgn:7029392"
        ],
        "placetype": [
          "aat:300132348"
        ],
        "id": 2185870,
        "name:xx": "Boligee Lower Bar"
      }
    },
    {
      "geometry": {
        "type": "Point",
        "coordinates": [
          -87.9667,
          34.4167
        ]
      },
      "type": "Feature",
      "properties": {
        "hierarchy": [
          "tgn:2185871",
          "tgn:7002659",
          "tgn:1000001",
          "tgn:7012149",
          "tgn:2000029",
          "tgn:7029392"
        ],
        "placetype": [
          "aat:300008699"
        ],
        "id": 2185871,
        "name:xx": "Bolin Branch"
      }
    },
    {
      "geometry": {
        "type": "Point",
        "coordinates": [
          -88.4667,
          39.65
        ]
      },
      "type": "Feature",
      "properties": {
        "hierarchy": [
          "tgn:2185872",
          "tgn:1000001",
          "tgn:7012149",
          "tgn:7007251",
          "tgn:7029392"
        ],
        "placetype": [
          "aat:300008699"
        ],
        "id": 2185872,
        "name:xx": "Bolin Branch"
      }
    },
    {
      "geometry": {
        "type": "Point",
        "coordinates": [
          -83.15,
          37.9
        ]
      },
      "type": "Feature",
      "properties": {
        "hierarchy": [
          "tgn:2185873",
          "tgn:1000001",
          "tgn:7012149",
          "tgn:2000831",
          "tgn:7007255",
          "tgn:7029392"
        ],
        "placetype": [
          "aat:300008699"
        ],
        "id": 2185873,
        "name:xx": "Bolin Branch"
      }
    },
    {
      "geometry": {
        "type": "Point",
        "coordinates": [
          -82.85,
          37.4667
        ]
      },
      "type": "Feature",
      "properties": {
        "hierarchy": [
          "tgn:2185874",
          "tgn:1000001",
          "tgn:7012149",
          "tgn:2000789",
          "tgn:7007255",
          "tgn:7029392"
        ],
        "placetype": [
          "aat:300008699"
        ],
        "id": 2185874,
        "name:xx": "Bolin Branch"
      }
    },
    {
      "geometry": {
        "type": "Point",
        "coordinates": [
          -79.5167,
          36.8
        ]
      },
      "type": "Feature",
      "properties": {
        "hierarchy": [
          "tgn:2185875",
          "tgn:1000001",
          "tgn:7012149",
          "tgn:2002180",
          "tgn:7007919",
          "tgn:7029392"
        ],
        "placetype": [
          "aat:300008699"
        ],
        "id": 2185875,
        "name:xx": "Bolin Branch"
      }
    },
    {
      "geometry": {
        "type": "Point",
        "coordinates": [
          -79.1167,
          35.9667
        ]
      },
      "type": "Feature",
      "properties": {
        "hierarchy": [
          "tgn:2185876",
          "tgn:1000001",
          "tgn:7012149",
          "tgn:2001525",
          "tgn:7007709",
          "tgn:7029392"
        ],
        "placetype": [
          "aat:300008706"
        ],
        "id": 2185876,
        "name:xx": "Bolin Creek"
      }
    },
    {
      "geometry": {
        "type": "Point",
        "coordinates": [
          -122.2,
          45.8
        ]
      },
      "type": "Feature",
      "properties": {
        "hierarchy": [
          "tgn:2185877",
          "tgn:1000001",
          "tgn:7012149",
          "tgn:1002897",
          "tgn:7007920",
          "tgn:7029392"
        ],
        "placetype": [
          "aat:300008706"
        ],
        "id": 2185877,
        "name:xx": "Bolin Creek"
      }
    },
    {
      "geometry": {
        "type": "Point",
        "coordinates": [
          -86.6667,
          38.0167
        ]
      },
      "type": "Feature",
      "properties": {
        "hierarchy": [
          "tgn:2185878",
          "tgn:1000001",
          "tgn:7012149",
          "tgn:2000550",
          "tgn:7007252",
          "tgn:7029392"
        ],
        "placetype": [
          "aat:300008761"
        ],
        "id": 2185878,
        "name:xx": "Bolin Hollow"
      }
    },
    {
      "geometry": {
        "type": "Point",
        "coordinates": [
          -94.8167,
          35.6667
        ]
      },
      "type": "Feature",
      "properties": {
        "hierarchy": [
          "tgn:2185879",
          "tgn:1000001",
          "tgn:2001633",
          "tgn:7012149",
          "tgn:7007707",
          "tgn:7029392"
        ],
        "placetype": [
          "aat:300008761"
        ],
        "id": 2185879,
        "name:xx": "Bolin Hollow"
      }
    }
  ]
}
