{
  "geometry": {
    "type": "Point",
    "coordinates": [
      -122.8667,
      45.7333
    ]
  },
  "type": "Feature",
  "properties": {
    "hierarchy": [
      "tgn:2085552",
      "tgn:1000001",
      "tgn:1002293",
      "tgn:7012149",
      "tgn:7007708",
      "tgn:7029392"
    ],
    "placetype": [
      "aat:300008347"
    ],
    "id": 2085552,
    "name:xx": "South Scappoose"
  }
}
