{
  "geometry": {
    "type": "Point",
    "coordinates": [
      -86.9833,
      37.6833
    ]
  },
  "type": "Feature",
  "properties": {
    "hierarchy": [
      "tgn:2039207",
      "tgn:1000001",
      "tgn:7012149",
      "tgn:2000786",
      "tgn:7007255",
      "tgn:7029392"
    ],
    "placetype": [
      "aat:300008347"
    ],
    "id": 2039207,
    "name:xx": "Habit"
  }
}
