{
  "geometry": {
    "type": "Point",
    "coordinates": [
      -87.9833,
      34.95
    ]
  },
  "type": "Feature",
  "properties": {
    "hierarchy": [
      "tgn:2472014",
      "tgn:7002659",
      "tgn:1000001",
      "tgn:7012149",
      "tgn:2000038",
      "tgn:7029392"
    ],
    "placetype": [
      "aat:300008761"
    ],
    "id": 2472014,
    "name:xx": "Lot Hollow"
  }
}
