{
  "geometry": {
    "type": "Point",
    "coordinates": [
      -104.8333,
      42.1667
    ]
  },
  "type": "Feature",
  "properties": {
    "hierarchy": [
      "tgn:2170664",
      "tgn:1000001",
      "tgn:7012149",
      "tgn:2002380",
      "tgn:7007923",
      "tgn:7029392"
    ],
    "placetype": [
      "aat:300008761"
    ],
    "id": 2170664,
    "name:xx": "Big Sand Draw"
  }
}
