{
  "geometry": {
    "type": "Point",
    "coordinates": [
      -123.9333,
      42.7667
    ]
  },
  "type": "Feature",
  "properties": {
    "hierarchy": [
      "tgn:2138788",
      "tgn:1000001",
      "tgn:2001702",
      "tgn:7012149",
      "tgn:7007708",
      "tgn:7029392"
    ],
    "placetype": [
      "aat:300008905"
    ],
    "id": 2138788,
    "name:xx": "Ash Swamp"
  }
}
