{
  "geometry": {
    "type": "Point",
    "coordinates": [
      -94.0333,
      37.7667
    ]
  },
  "type": "Feature",
  "properties": {
    "hierarchy": [
      "tgn:2451618",
      "tgn:1000001",
      "tgn:2001183",
      "tgn:7012149",
      "tgn:7007523",
      "tgn:7029392"
    ],
    "placetype": [
      "aat:300008706"
    ],
    "id": 2451618,
    "name:xx": "Little Bear Creek"
  }
}
