{
  "geometry": {
    "type": "Point",
    "coordinates": [
      -123.5667,
      47.3333
    ]
  },
  "type": "Feature",
  "properties": {
    "hierarchy": [
      "tgn:2533186",
      "tgn:1000001",
      "tgn:7012149",
      "tgn:1002418",
      "tgn:7007920",
      "tgn:7029392"
    ],
    "placetype": [
      "aat:300008706"
    ],
    "id": 2533186,
    "name:xx": "Musgrove Creek"
  }
}
