{
  "geometry": {
    "type": "Point",
    "coordinates": [
      22.4167,
      61.7833
    ]
  },
  "type": "Feature",
  "properties": {
    "hierarchy": [
      "tgn:1031343",
      "tgn:7024077",
      "tgn:1000003",
      "tgn:1000069",
      "tgn:7029392"
    ],
    "placetype": [
      "aat:300008347"
    ],
    "id": 1031343,
    "name:xx": "Kankaanpää"
  }
}
