{
  "geometry": {
    "type": "Point",
    "coordinates": [
      -93.35,
      17.225
    ]
  },
  "type": "Feature",
  "properties": {
    "hierarchy": [
      "tgn:7414408",
      "tgn:7005580",
      "tgn:1000001",
      "tgn:7005560",
      "tgn:7029392"
    ],
    "placetype": [
      "aat:300008347"
    ],
    "id": 7414408,
    "name:xx": "Emiliano Zapata"
  }
}
