{
  "geometry": {
    "type": "Point",
    "coordinates": [
      90.8833,
      23.7167
    ]
  },
  "type": "Feature",
  "properties": {
    "hierarchy": [
      "tgn:1065585",
      "tgn:7000188",
      "tgn:1000004",
      "tgn:1000105",
      "tgn:7029392"
    ],
    "placetype": [
      "aat:300008347"
    ],
    "id": 1065585,
    "name:xx": "Bākhrābād"
  }
}
