{
  "geometry": {
    "type": "Point",
    "coordinates": [
      101.6667,
      28.6333
    ]
  },
  "type": "Feature",
  "properties": {
    "hierarchy": [
      "tgn:1072652",
      "tgn:1000004",
      "tgn:7002087",
      "tgn:1000111",
      "tgn:7029392"
    ],
    "placetype": [
      "aat:300008347"
    ],
    "id": 1072652,
    "name:xx": "Wulaxi"
  }
}
