{
  "geometry": {
    "type": "Point",
    "coordinates": [
      -93.7167,
      40.1833
    ]
  },
  "type": "Feature",
  "properties": {
    "hierarchy": [
      "tgn:2556734",
      "tgn:1000001",
      "tgn:7012149",
      "tgn:2001200",
      "tgn:7007523",
      "tgn:7029392"
    ],
    "placetype": [
      "aat:300008707"
    ],
    "id": 2556734,
    "name:xx": "Old Channel Thompson River"
  }
}
