{
  "geometry": {
    "type": "Point",
    "coordinates": [
      -82.9833,
      37.8833
    ]
  },
  "type": "Feature",
  "properties": {
    "hierarchy": [
      "tgn:2565303",
      "tgn:1000001",
      "tgn:7012149",
      "tgn:7007255",
      "tgn:7029392"
    ],
    "placetype": [
      "aat:300008706"
    ],
    "id": 2565303,
    "name:xx": "Paint Creek"
  }
}
