{
  "geometry": {
    "type": "Point",
    "coordinates": [
      -83.0167,
      42.8333
    ]
  },
  "type": "Feature",
  "properties": {
    "hierarchy": [
      "tgn:2775648",
      "tgn:1000001",
      "tgn:7012149",
      "tgn:1002617",
      "tgn:7007520",
      "tgn:7029392"
    ],
    "placetype": [
      "aat:300008699"
    ],
    "id": 2775648,
    "name:xx": "Wilson Drain"
  }
}
