{
  "geometry": {
    "type": "Point",
    "coordinates": [
      -100.008333,
      20.9375
    ]
  },
  "type": "Feature",
  "properties": {
    "hierarchy": [
      "tgn:7399686",
      "tgn:1000001",
      "tgn:7005593",
      "tgn:7005560",
      "tgn:7029392"
    ],
    "placetype": [
      "aat:300008347"
    ],
    "id": 7399686,
    "name:xx": "El Madroño"
  }
}
