{
  "type": "FeatureCollection",
  "features": [
    {
      "geometry": {
        "type": "Point",
        "coordinates": [
          8,
          45.516667
        ]
      },
      "type": "Feature",
      "properties": {
        "hierarchy": [
          "tgn:1045450",
          "tgn:7024833",
          "tgn:1000003",
          "tgn:7003120",
          "tgn:1000080",
          "tgn:7029392"
        ],
        "placetype": [
          "aat:300008347"
        ],
        "id": 1045450,
        "name:xx": "Mongrando"
      }
    },
    {
      "geometry": {
        "type": "Point",
        "coordinates": [
          12.110833,
          46.758611
        ]
      },
      "type": "Feature",
      "properties": {
        "hierarchy": [
          "tgn:1045451",
          "tgn:1003440",
          "tgn:1000003",
          "tgn:7003124",
          "tgn:1000080",
          "tgn:7029392"
        ],
        "placetype": [
          "aat:300008347"
        ],
        "id": 1045451,
        "name:xx": "Monguelfo"
      }
    },
    {
      "geometry": {
        "type": "Point",
        "coordinates": [
          9.139722,
          39.256111
        ]
      },
      "type": "Feature",
      "properties": {
        "hierarchy": [
          "tgn:1045455",
          "tgn:1001641",
          "tgn:1000003",
          "tgn:7003121",
          "tgn:1000080",
          "tgn:7029392"
        ],
        "placetype": [
          "aat:300008347"
        ],
        "id": 1045455,
        "name:xx": "Monserrato"
      }
    },
    {
      "geometry": {
        "type": "Point",
        "coordinates": [
          7.95,
          44.8
        ]
      },
      "type": "Feature",
      "properties": {
        "hierarchy": [
          "tgn:1045457",
          "tgn:7005126",
          "tgn:1000003",
          "tgn:7003120",
          "tgn:1000080",
          "tgn:7029392"
        ],
        "placetype": [
          "aat:300008347"
        ],
        "id": 1045457,
        "name:xx": "Montà"
      }
    },
    {
      "geometry": {
        "type": "Point",
        "coordinates": [
          14.666667,
          41.65
        ]
      },
      "type": "Feature",
      "properties": {
        "hierarchy": [
          "tgn:1045458",
          "tgn:1003444",
          "tgn:1000003",
          "tgn:7003241",
          "tgn:1000080",
          "tgn:7029392"
        ],
        "placetype": [
          "aat:300008347"
        ],
        "id": 1045458,
        "name:xx": "Montágano"
      }
    }
  ]
}
