{
  "geometry": {
    "type": "Point",
    "coordinates": [
      -103.3833,
      38.15
    ]
  },
  "type": "Feature",
  "properties": {
    "hierarchy": [
      "tgn:2400265",
      "tgn:1000001",
      "tgn:7012149",
      "tgn:7007158",
      "tgn:7029392"
    ],
    "placetype": [
      "aat:300008680"
    ],
    "id": 2400265,
    "name:xx": "Horse Creek Reservoir"
  }
}
