{
  "geometry": {
    "type": "Point",
    "coordinates": [
      -104.0333,
      39.05
    ]
  },
  "type": "Feature",
  "properties": {
    "hierarchy": [
      "tgn:2681769",
      "tgn:1000001",
      "tgn:7012149",
      "tgn:7007158",
      "tgn:7029392"
    ],
    "placetype": [
      "aat:300008706"
    ],
    "id": 2681769,
    "name:xx": "South Rush Creek"
  }
}
