{
  "geometry": {
    "type": "Point",
    "coordinates": [
      -85.35,
      37.4167
    ]
  },
  "type": "Feature",
  "properties": {
    "hierarchy": [
      "tgn:2510059",
      "tgn:1000001",
      "tgn:7012149",
      "tgn:7007255",
      "tgn:7029392"
    ],
    "placetype": [
      "aat:300008706"
    ],
    "id": 2510059,
    "name:xx": "Middle Pitman Creek"
  }
}
