{
  "geometry": {
    "type": "Point",
    "coordinates": [
      -112.7833,
      38.4333
    ]
  },
  "type": "Feature",
  "properties": {
    "hierarchy": [
      "tgn:2771505",
      "tgn:2002101",
      "tgn:1000001",
      "tgn:7012149",
      "tgn:7007827",
      "tgn:7029392"
    ],
    "placetype": [
      "aat:300008798"
    ],
    "id": 2771505,
    "name:xx": "Wildhorse Mountain"
  }
}
