{
  "geometry": {
    "type": "Point",
    "coordinates": [
      121.29763,
      24.911883
    ]
  },
  "type": "Feature",
  "properties": {
    "hierarchy": [
      "tgn:7496263",
      "tgn:1000004",
      "tgn:7001013",
      "tgn:1000141",
      "tgn:7029392"
    ],
    "placetype": [
      "aat:300008347"
    ],
    "id": 7496263,
    "name:xx": "Shijia"
  }
}
