{
  "geometry": {
    "type": "Point",
    "coordinates": [
      -92.1667,
      44.95
    ]
  },
  "type": "Feature",
  "properties": {
    "hierarchy": [
      "tgn:2122712",
      "tgn:1000001",
      "tgn:7012149",
      "tgn:2002351",
      "tgn:7007922",
      "tgn:7029392"
    ],
    "placetype": [
      "aat:300008347"
    ],
    "id": 2122712,
    "name:xx": "Wilson"
  }
}
