{
  "geometry": {
    "type": "Point",
    "coordinates": [
      73.6667,
      30.1667
    ]
  },
  "type": "Feature",
  "properties": {
    "hierarchy": [
      "tgn:1083656",
      "tgn:1000004",
      "tgn:1001490",
      "tgn:1000133",
      "tgn:7029392"
    ],
    "placetype": [
      "aat:300008347"
    ],
    "id": 1083656,
    "name:xx": "Minchinabad"
  }
}
