{
  "type": "FeatureCollection",
  "features": [
    {
      "geometry": {
        "type": "Point",
        "coordinates": [
          22.066667,
          37.283333
        ]
      },
      "type": "Feature",
      "properties": {
        "hierarchy": [
          "tgn:7230510",
          "tgn:7002735",
          "tgn:7017076",
          "tgn:1000003",
          "tgn:1000074",
          "tgn:7029392"
        ],
        "placetype": [
          "aat:300008347"
        ],
        "id": 7230510,
        "name:xx": "Khirádhes"
      }
    },
    {
      "geometry": {
        "type": "Point",
        "coordinates": [
          21.383333,
          38.2
        ]
      },
      "type": "Feature",
      "properties": {
        "hierarchy": [
          "tgn:7230511",
          "tgn:7002680",
          "tgn:7001395",
          "tgn:1000003",
          "tgn:1000074",
          "tgn:7029392"
        ],
        "placetype": [
          "aat:300008777"
        ],
        "id": 7230511,
        "name:xx": "Khirá"
      }
    },
    {
      "geometry": {
        "type": "Point",
        "coordinates": [
          26.2,
          38.333333
        ]
      },
      "type": "Feature",
      "properties": {
        "hierarchy": [
          "tgn:7230513",
          "tgn:7011161",
          "tgn:7002674",
          "tgn:1000003",
          "tgn:1000074",
          "tgn:7029392"
        ],
        "placetype": [
          "aat:300266559"
        ],
        "id": 7230513,
        "name:xx": "Chíou, Díavlos"
      }
    },
    {
      "geometry": {
        "type": "Point",
        "coordinates": [
          22.933333,
          36.95
        ]
      },
      "type": "Feature",
      "properties": {
        "hierarchy": [
          "tgn:7230516",
          "tgn:7002735",
          "tgn:7017076",
          "tgn:1000003",
          "tgn:1000074",
          "tgn:7029392"
        ],
        "placetype": [
          "aat:300008795"
        ],
        "id": 7230516,
        "name:xx": "Khionovoúni"
      }
    },
    {
      "geometry": {
        "type": "Point",
        "coordinates": [
          24.083333,
          41.3
        ]
      },
      "type": "Feature",
      "properties": {
        "hierarchy": [
          "tgn:7230517",
          "tgn:7011170",
          "tgn:7002715",
          "tgn:1000003",
          "tgn:1000074",
          "tgn:7029392"
        ],
        "placetype": [
          "aat:300008798"
        ],
        "id": 7230517,
        "name:xx": "Khionótripa"
      }
    },
    {
      "geometry": {
        "type": "Point",
        "coordinates": [
          23.65,
          41.116667
        ]
      },
      "type": "Feature",
      "properties": {
        "hierarchy": [
          "tgn:7230518",
          "tgn:7002725",
          "tgn:7002715",
          "tgn:1000003",
          "tgn:1000074",
          "tgn:7029392"
        ],
        "placetype": [
          "aat:300008347"
        ],
        "id": 7230518,
        "name:xx": "Khionokhórion"
      }
    },
    {
      "geometry": {
        "type": "Point",
        "coordinates": [
          22.283333,
          38.566667
        ]
      },
      "type": "Feature",
      "properties": {
        "hierarchy": [
          "tgn:7230519",
          "tgn:4003773",
          "tgn:7001395",
          "tgn:1000003",
          "tgn:1000074",
          "tgn:7029392"
        ],
        "placetype": [
          "aat:300008798"
        ],
        "id": 7230519,
        "name:xx": "Khioniás"
      }
    }
  ]
}
