{
  "geometry": {
    "type": "Point",
    "coordinates": [
      -71.3667,
      43.6167
    ]
  },
  "type": "Feature",
  "properties": {
    "hierarchy": [
      "tgn:2425857",
      "tgn:1000001",
      "tgn:7012149",
      "tgn:7007564",
      "tgn:7029392"
    ],
    "placetype": [
      "aat:300008791"
    ],
    "id": 2425857,
    "name:xx": "Jolly Island"
  }
}
