{
  "geometry": {
    "type": "Point",
    "coordinates": [
      -83.1167,
      36.3667
    ]
  },
  "type": "Feature",
  "properties": {
    "hierarchy": [
      "tgn:2598549",
      "tgn:1000001",
      "tgn:7012149",
      "tgn:2001873",
      "tgn:7007825",
      "tgn:7029392"
    ],
    "placetype": [
      "aat:300000390"
    ],
    "id": 2598549,
    "name:xx": "Price Quarry"
  }
}
