{
  "geometry": {
    "type": "Point",
    "coordinates": [
      73.73526,
      29.758833
    ]
  },
  "type": "Feature",
  "properties": {
    "hierarchy": [
      "tgn:7558837",
      "tgn:1000004",
      "tgn:7000198",
      "tgn:7016788",
      "tgn:7029392"
    ],
    "placetype": [
      "aat:300008347"
    ],
    "name:en": "Retwāla",
    "id": 7558837
  }
}
