{
  "geometry": {
    "type": "Point",
    "coordinates": [
      -102.3833,
      31.6833
    ]
  },
  "type": "Feature",
  "properties": {
    "hierarchy": [
      "tgn:2481842",
      "tgn:1000001",
      "tgn:7012149",
      "tgn:7007826",
      "tgn:7029392"
    ],
    "placetype": [
      "aat:300008761"
    ],
    "id": 2481842,
    "name:xx": "Landreth Draw"
  }
}
