{
  "geometry": {
    "type": "Point",
    "coordinates": [
      -77.4167,
      41.7333
    ]
  },
  "type": "Feature",
  "properties": {
    "hierarchy": [
      "tgn:2582321",
      "tgn:1000001",
      "tgn:7012149",
      "tgn:7007710",
      "tgn:7029392"
    ],
    "placetype": [
      "aat:300008761"
    ],
    "id": 2582321,
    "name:xx": "Pine Creek Gorge"
  }
}
