{
  "geometry": {
    "type": "Point",
    "coordinates": [
      -85.75,
      35.5833
    ]
  },
  "type": "Feature",
  "properties": {
    "hierarchy": [
      "tgn:2392745",
      "tgn:1000001",
      "tgn:7012149",
      "tgn:2001925",
      "tgn:7007825",
      "tgn:7029392"
    ],
    "placetype": [
      "aat:300008746"
    ],
    "id": 2392745,
    "name:xx": "Hobbs Cave"
  }
}
