{
  "geometry": {
    "type": "Point",
    "coordinates": [
      -111.9167,
      45.45
    ]
  },
  "type": "Feature",
  "properties": {
    "hierarchy": [
      "tgn:2681051",
      "tgn:1000001",
      "tgn:7012149",
      "tgn:2001288",
      "tgn:7007524",
      "tgn:7029392"
    ],
    "placetype": [
      "aat:300008680"
    ],
    "id": 2681051,
    "name:xx": "South Meadow Creek Lake"
  }
}
