{
  "geometry": {
    "type": "Point",
    "coordinates": [
      -116.5667,
      42.1667
    ]
  },
  "type": "Feature",
  "properties": {
    "hierarchy": [
      "tgn:2564659",
      "tgn:1000001",
      "tgn:7012149",
      "tgn:2000488",
      "tgn:7007250",
      "tgn:7029392"
    ],
    "placetype": [
      "aat:300006191"
    ],
    "id": 2564659,
    "name:xx": "Packsaddle Reservoir"
  }
}
