{
  "geometry": {
    "type": "Point",
    "coordinates": [
      -43.1833,
      -21.8333
    ]
  },
  "type": "Feature",
  "properties": {
    "hierarchy": [
      "tgn:1023041",
      "tgn:7006237",
      "tgn:1000047",
      "tgn:7002457",
      "tgn:1000002",
      "tgn:7029392"
    ],
    "placetype": [
      "aat:300008347"
    ],
    "id": 1023041,
    "name:xx": "Sarandira"
  }
}
