{
  "geometry": {
    "type": "Point",
    "coordinates": [
      78.213136,
      29.586428
    ]
  },
  "type": "Feature",
  "properties": {
    "hierarchy": [
      "tgn:7552791",
      "tgn:1000004",
      "tgn:7000198",
      "tgn:7016722",
      "tgn:7029392"
    ],
    "placetype": [
      "aat:300008347"
    ],
    "name:en": "Muāzzampur Nārāyan",
    "id": 7552791
  }
}
