{
  "type": "FeatureCollection",
  "features": [
    {
      "geometry": {
        "type": "Point",
        "coordinates": [
          9.4,
          45
        ]
      },
      "type": "Feature",
      "properties": {
        "hierarchy": [
          "tgn:7036511",
          "tgn:7003132",
          "tgn:1000003",
          "tgn:7008516",
          "tgn:1000080",
          "tgn:7029392"
        ],
        "placetype": [
          "aat:300008347"
        ],
        "id": 7036511,
        "name:xx": "Ziano Piacentino"
      }
    },
    {
      "geometry": {
        "type": "Point",
        "coordinates": [
          12.163333,
          45.601944
        ]
      },
      "type": "Feature",
      "properties": {
        "hierarchy": [
          "tgn:7036515",
          "tgn:7003006",
          "tgn:1000003",
          "tgn:7002997",
          "tgn:1000080",
          "tgn:7029392"
        ],
        "placetype": [
          "aat:300008347"
        ],
        "id": 7036515,
        "name:xx": "Zero Branco"
      }
    },
    {
      "geometry": {
        "type": "Point",
        "coordinates": [
          11.366667,
          45.466667
        ]
      },
      "type": "Feature",
      "properties": {
        "hierarchy": [
          "tgn:7036517",
          "tgn:7003008",
          "tgn:1000003",
          "tgn:7002997",
          "tgn:1000080",
          "tgn:7029392"
        ],
        "placetype": [
          "aat:300008347"
        ],
        "id": 7036517,
        "name:xx": "Zermeghedo"
      }
    },
    {
      "geometry": {
        "type": "Point",
        "coordinates": [
          12.268333,
          45.579444
        ]
      },
      "type": "Feature",
      "properties": {
        "hierarchy": [
          "tgn:7036518",
          "tgn:7003006",
          "tgn:1000003",
          "tgn:7002997",
          "tgn:1000080",
          "tgn:7029392"
        ],
        "placetype": [
          "aat:300008347"
        ],
        "id": 7036518,
        "name:xx": "Zerman"
      }
    },
    {
      "geometry": {
        "type": "Point",
        "coordinates": [
          12.104722,
          45.627222
        ]
      },
      "type": "Feature",
      "properties": {
        "hierarchy": [
          "tgn:7036519",
          "tgn:7003006",
          "tgn:1000003",
          "tgn:7002997",
          "tgn:1000080",
          "tgn:7029392"
        ],
        "placetype": [
          "aat:300008347"
        ],
        "id": 7036519,
        "name:xx": "Zeriolo"
      }
    }
  ]
}
