{
  "geometry": {
    "type": "Point",
    "coordinates": [
      -86.2333,
      39.8833
    ]
  },
  "type": "Feature",
  "properties": {
    "hierarchy": [
      "tgn:2140262",
      "tgn:1000001",
      "tgn:7012149",
      "tgn:1002633",
      "tgn:7007252",
      "tgn:7029392"
    ],
    "placetype": [
      "aat:300008699"
    ],
    "id": 2140262,
    "name:xx": "Augusta Branch"
  }
}
