{
  "geometry": {
    "type": "Point",
    "coordinates": [
      -75.9167,
      43.1167
    ]
  },
  "type": "Feature",
  "properties": {
    "hierarchy": [
      "tgn:2754879",
      "tgn:1000001",
      "tgn:7012149",
      "tgn:1002624",
      "tgn:7007568",
      "tgn:7029392"
    ],
    "placetype": [
      "aat:300008347"
    ],
    "id": 2754879,
    "name:xx": "Weaver Corner"
  }
}
