{
  "geometry": {
    "type": "Point",
    "coordinates": [
      101.516,
      50.766
    ]
  },
  "type": "Feature",
  "properties": {
    "hierarchy": [
      "tgn:1120791",
      "tgn:1000004",
      "tgn:1001192",
      "tgn:7029379",
      "tgn:7029392"
    ],
    "placetype": [
      "aat:300008707"
    ],
    "id": 1120791,
    "name:xx": "Üür Gol"
  }
}
