{
  "geometry": {
    "type": "Point",
    "coordinates": [
      -89.4833,
      32.35
    ]
  },
  "type": "Feature",
  "properties": {
    "hierarchy": [
      "tgn:7023727",
      "tgn:1000001",
      "tgn:7012149",
      "tgn:7007522",
      "tgn:7029392"
    ],
    "placetype": [
      "aat:300008699"
    ],
    "id": 7023727,
    "name:xx": "Tallabogue"
  }
}
