{
  "geometry": {
    "type": "Point",
    "coordinates": [
      -94.7333,
      31.2333
    ]
  },
  "type": "Feature",
  "properties": {
    "hierarchy": [
      "tgn:2698064",
      "tgn:1002149",
      "tgn:1000001",
      "tgn:7012149",
      "tgn:7007826",
      "tgn:7029392"
    ],
    "placetype": [
      "aat:300008706"
    ],
    "id": 2698064,
    "name:xx": "Stovall Creek"
  }
}
