{
  "geometry": {
    "type": "Point",
    "coordinates": [
      72.916667,
      19.05
    ]
  },
  "type": "Feature",
  "properties": {
    "hierarchy": [
      "tgn:7572795",
      "tgn:1000004",
      "tgn:7000198",
      "tgn:1001895",
      "tgn:7029392"
    ],
    "placetype": [
      "aat:300055621"
    ],
    "name:en": "Govind Devnār",
    "id": 7572795
  }
}
