{
  "geometry": {
    "type": "Point",
    "coordinates": [
      79.488209,
      27.94271
    ]
  },
  "type": "Feature",
  "properties": {
    "hierarchy": [
      "tgn:7562333",
      "tgn:1000004",
      "tgn:7000198",
      "tgn:7016722",
      "tgn:7029392"
    ],
    "placetype": [
      "aat:300008347"
    ],
    "name:en": "Majhara Khās",
    "id": 7562333
  }
}
