{
  "geometry": {
    "type": "Point",
    "coordinates": [
      31.6333,
      31.2167
    ]
  },
  "type": "Feature",
  "properties": {
    "hierarchy": [
      "tgn:1095336",
      "tgn:7001242",
      "tgn:7016833",
      "tgn:1001225",
      "tgn:7029392"
    ],
    "placetype": [
      "aat:300008347"
    ],
    "name:en": "Az Zarqā",
    "id": 1095336
  }
}
