{
  "geometry": {
    "type": "Point",
    "coordinates": [
      -99.0333,
      31.2667
    ]
  },
  "type": "Feature",
  "properties": {
    "hierarchy": [
      "tgn:2353066",
      "tgn:1000001",
      "tgn:7012149",
      "tgn:2002069",
      "tgn:7007826",
      "tgn:7029392"
    ],
    "placetype": [
      "aat:300008706"
    ],
    "id": 2353066,
    "name:xx": "Goens Creek"
  }
}
