{
  "geometry": {
    "type": "Point",
    "coordinates": [
      -111.9167,
      35.2333
    ]
  },
  "type": "Feature",
  "properties": {
    "hierarchy": [
      "tgn:2746099",
      "tgn:1000001",
      "tgn:7006451",
      "tgn:2000092",
      "tgn:7012149",
      "tgn:7029392"
    ],
    "placetype": [
      "aat:300006191"
    ],
    "id": 2746099,
    "name:xx": "Volunteer Tank"
  }
}
