{
  "geometry": {
    "type": "Point",
    "coordinates": [
      77.15,
      16.316667
    ]
  },
  "type": "Feature",
  "properties": {
    "hierarchy": [
      "tgn:7571997",
      "tgn:1000004",
      "tgn:7000198",
      "tgn:1001882",
      "tgn:7029392"
    ],
    "placetype": [
      "aat:300008347"
    ],
    "name:en": "Gabūr",
    "id": 7571997
  }
}
