{
  "type": "FeatureCollection",
  "features": [
    {
      "geometry": {
        "type": "Point",
        "coordinates": [
          -96.25,
          32.1667
        ]
      },
      "type": "Feature",
      "properties": {
        "hierarchy": [
          "tgn:2410990",
          "tgn:1000001",
          "tgn:7012149",
          "tgn:1002709",
          "tgn:7007826",
          "tgn:7029392"
        ],
        "placetype": [
          "aat:300008706"
        ],
        "id": 2410990,
        "name:xx": "Indian Creek"
      }
    },
    {
      "geometry": {
        "type": "Point",
        "coordinates": [
          -98.1167,
          32.2
        ]
      },
      "type": "Feature",
      "properties": {
        "hierarchy": [
          "tgn:2410991",
          "tgn:1000001",
          "tgn:7012149",
          "tgn:2001982",
          "tgn:7007826",
          "tgn:7029392"
        ],
        "placetype": [
          "aat:300008706"
        ],
        "id": 2410991,
        "name:xx": "Indian Creek"
      }
    },
    {
      "geometry": {
        "type": "Point",
        "coordinates": [
          -95.3167,
          32.3167
        ]
      },
      "type": "Feature",
      "properties": {
        "hierarchy": [
          "tgn:2410992",
          "tgn:1000001",
          "tgn:7012149",
          "tgn:7007826",
          "tgn:7029392"
        ],
        "placetype": [
          "aat:300008706"
        ],
        "id": 2410992,
        "name:xx": "Indian Creek"
      }
    },
    {
      "geometry": {
        "type": "Point",
        "coordinates": [
          -99.3167,
          32.6167
        ]
      },
      "type": "Feature",
      "properties": {
        "hierarchy": [
          "tgn:2410993",
          "tgn:1000001",
          "tgn:7012149",
          "tgn:2002072",
          "tgn:7007826",
          "tgn:7029392"
        ],
        "placetype": [
          "aat:300008706"
        ],
        "id": 2410993,
        "name:xx": "Indian Creek"
      }
    },
    {
      "geometry": {
        "type": "Point",
        "coordinates": [
          -95.2167,
          33
        ]
      },
      "type": "Feature",
      "properties": {
        "hierarchy": [
          "tgn:2410994",
          "tgn:1000001",
          "tgn:7012149",
          "tgn:1002388",
          "tgn:7007826",
          "tgn:7029392"
        ],
        "placetype": [
          "aat:300008706"
        ],
        "id": 2410994,
        "name:xx": "Indian Creek"
      }
    },
    {
      "geometry": {
        "type": "Point",
        "coordinates": [
          -99.7167,
          29.7833
        ]
      },
      "type": "Feature",
      "properties": {
        "hierarchy": [
          "tgn:2410995",
          "tgn:1000001",
          "tgn:7012149",
          "tgn:2002060",
          "tgn:7007826",
          "tgn:7029392"
        ],
        "placetype": [
          "aat:300008706"
        ],
        "id": 2410995,
        "name:xx": "Indian Creek"
      }
    },
    {
      "geometry": {
        "type": "Point",
        "coordinates": [
          -101.0667,
          29.8167
        ]
      },
      "type": "Feature",
      "properties": {
        "hierarchy": [
          "tgn:2410996",
          "tgn:1000001",
          "tgn:7012149",
          "tgn:2002088",
          "tgn:7007826",
          "tgn:7029392"
        ],
        "placetype": [
          "aat:300008706"
        ],
        "id": 2410996,
        "name:xx": "Indian Creek"
      }
    },
    {
      "geometry": {
        "type": "Point",
        "coordinates": [
          -99.0667,
          30.3667
        ]
      },
      "type": "Feature",
      "properties": {
        "hierarchy": [
          "tgn:2410997",
          "tgn:1000001",
          "tgn:7012149",
          "tgn:2001990",
          "tgn:7007826",
          "tgn:7029392"
        ],
        "placetype": [
          "aat:300008706"
        ],
        "id": 2410997,
        "name:xx": "Indian Creek"
      }
    },
    {
      "geometry": {
        "type": "Point",
        "coordinates": [
          -103.7167,
          30.6333
        ]
      },
      "type": "Feature",
      "properties": {
        "hierarchy": [
          "tgn:2410998",
          "tgn:1000001",
          "tgn:7012149",
          "tgn:2002010",
          "tgn:7007826",
          "tgn:7029392"
        ],
        "placetype": [
          "aat:300008706"
        ],
        "id": 2410998,
        "name:xx": "Indian Creek"
      }
    },
    {
      "geometry": {
        "type": "Point",
        "coordinates": [
          -98.2,
          31.25
        ]
      },
      "type": "Feature",
      "properties": {
        "hierarchy": [
          "tgn:2410999",
          "tgn:1000001",
          "tgn:7012149",
          "tgn:2002026",
          "tgn:7007826",
          "tgn:7029392"
        ],
        "placetype": [
          "aat:300008706"
        ],
        "id": 2410999,
        "name:xx": "Indian Creek"
      }
    }
  ]
}
