{
  "geometry": {
    "type": "Point",
    "coordinates": [
      -117.7167,
      33.75
    ]
  },
  "type": "Feature",
  "properties": {
    "hierarchy": [
      "tgn:1110684",
      "tgn:1000001",
      "tgn:7012149",
      "tgn:7007157",
      "tgn:1002748",
      "tgn:7029392"
    ],
    "placetype": [
      "aat:300266640"
    ],
    "id": 1110684,
    "name:xx": "Loma Ridge"
  }
}
