{
  "geometry": {
    "type": "Point",
    "coordinates": [
      -106.9167,
      37.8833
    ]
  },
  "type": "Feature",
  "properties": {
    "hierarchy": [
      "tgn:2396695",
      "tgn:1000001",
      "tgn:7012149",
      "tgn:2000231",
      "tgn:7007158",
      "tgn:7029392"
    ],
    "placetype": [
      "aat:300000390"
    ],
    "id": 2396695,
    "name:xx": "Holy Moses Mine"
  }
}
