{
  "geometry": {
    "type": "Point",
    "coordinates": [
      -74.2833,
      40.6833
    ]
  },
  "type": "Feature",
  "properties": {
    "hierarchy": [
      "tgn:2757724",
      "tgn:1000001",
      "tgn:1002963",
      "tgn:7012149",
      "tgn:7007565",
      "tgn:7029392"
    ],
    "placetype": [
      "aat:300008707"
    ],
    "id": 2757724,
    "name:xx": "West Branch Elizabeth River"
  }
}
