{
  "type": "FeatureCollection",
  "features": [
    {
      "geometry": {
        "type": "Point",
        "coordinates": [
          -96.9667,
          30.35
        ]
      },
      "type": "Feature",
      "properties": {
        "hierarchy": [
          "tgn:2520170",
          "tgn:1000001",
          "tgn:7012149",
          "tgn:1002584",
          "tgn:7007826",
          "tgn:7029392"
        ],
        "placetype": [
          "aat:300008905"
        ],
        "id": 2520170,
        "name:xx": "Molty Smith Lake"
      }
    },
    {
      "geometry": {
        "type": "Point",
        "coordinates": [
          -96.9833,
          44.1833
        ]
      },
      "type": "Feature",
      "properties": {
        "hierarchy": [
          "tgn:2520171",
          "tgn:1000001",
          "tgn:7012149",
          "tgn:7007713",
          "tgn:7029392"
        ],
        "placetype": [
          "aat:300008680"
        ],
        "id": 2520171,
        "name:xx": "Molumby Slough"
      }
    },
    {
      "geometry": {
        "type": "Point",
        "coordinates": [
          -68.3,
          45.6667
        ]
      },
      "type": "Feature",
      "properties": {
        "hierarchy": [
          "tgn:2520172",
          "tgn:2000919",
          "tgn:1000001",
          "tgn:7012149",
          "tgn:7007515",
          "tgn:7029392"
        ],
        "placetype": [
          "aat:300008680"
        ],
        "id": 2520172,
        "name:xx": "Molunkus Lake"
      }
    },
    {
      "geometry": {
        "type": "Point",
        "coordinates": [
          -68.4,
          45.8833
        ]
      },
      "type": "Feature",
      "properties": {
        "hierarchy": [
          "tgn:2520173",
          "tgn:1000001",
          "tgn:7012149",
          "tgn:7007515",
          "tgn:7029392"
        ],
        "placetype": [
          "aat:300008699"
        ],
        "id": 2520173,
        "name:xx": "Molunkus Stream"
      }
    },
    {
      "geometry": {
        "type": "Point",
        "coordinates": [
          -132.6833,
          56.2333
        ]
      },
      "type": "Feature",
      "properties": {
        "hierarchy": [
          "tgn:2520174",
          "tgn:7006450",
          "tgn:1000001",
          "tgn:7012149",
          "tgn:2000088",
          "tgn:7029392"
        ],
        "placetype": [
          "aat:300008791"
        ],
        "id": 2520174,
        "name:xx": "Molver Island"
      }
    },
    {
      "geometry": {
        "type": "Point",
        "coordinates": [
          -105.4833,
          36.6833
        ]
      },
      "type": "Feature",
      "properties": {
        "hierarchy": [
          "tgn:2520175",
          "tgn:1000001",
          "tgn:7012149",
          "tgn:2001457",
          "tgn:7007566",
          "tgn:7029392"
        ],
        "placetype": [
          "aat:300008347"
        ],
        "id": 2520175,
        "name:xx": "Moly"
      }
    },
    {
      "geometry": {
        "type": "Point",
        "coordinates": [
          -119.45,
          38.2
        ]
      },
      "type": "Feature",
      "properties": {
        "hierarchy": [
          "tgn:2520176",
          "tgn:1000001",
          "tgn:7012149",
          "tgn:7007157",
          "tgn:1002675",
          "tgn:7029392"
        ],
        "placetype": [
          "aat:300008706"
        ],
        "id": 2520176,
        "name:xx": "Molybdenite Creek"
      }
    },
    {
      "geometry": {
        "type": "Point",
        "coordinates": [
          -117.25,
          48.7
        ]
      },
      "type": "Feature",
      "properties": {
        "hierarchy": [
          "tgn:2520177",
          "tgn:1000001",
          "tgn:7012149",
          "tgn:2002248",
          "tgn:7007920",
          "tgn:7029392"
        ],
        "placetype": [
          "aat:300008798"
        ],
        "id": 2520177,
        "name:xx": "Molybdenite Mountain"
      }
    },
    {
      "geometry": {
        "type": "Point",
        "coordinates": [
          -159.2333,
          61.8
        ]
      },
      "type": "Feature",
      "properties": {
        "hierarchy": [
          "tgn:2520178",
          "tgn:7006450",
          "tgn:2000069",
          "tgn:1000001",
          "tgn:7012149",
          "tgn:7029392"
        ],
        "placetype": [
          "aat:300008798"
        ],
        "id": 2520178,
        "name:xx": "Molybdenum Mountain"
      }
    },
    {
      "geometry": {
        "type": "Point",
        "coordinates": [
          -78.7833,
          43.2
        ]
      },
      "type": "Feature",
      "properties": {
        "hierarchy": [
          "tgn:2520179",
          "tgn:1000001",
          "tgn:7012149",
          "tgn:1002718",
          "tgn:7007568",
          "tgn:7029392"
        ],
        "placetype": [
          "aat:300008347"
        ],
        "id": 2520179,
        "name:xx": "Molyneaux Corners"
      }
    }
  ]
}
