{
  "geometry": {
    "type": "Point",
    "coordinates": [
      119.9167,
      40.45
    ]
  },
  "type": "Feature",
  "properties": {
    "hierarchy": [
      "tgn:1068296",
      "tgn:1000004",
      "tgn:1001390",
      "tgn:1000111",
      "tgn:7029392"
    ],
    "placetype": [
      "aat:300008347"
    ],
    "id": 1068296,
    "name:xx": "Gejiatun"
  }
}
