{
  "geometry": {
    "type": "Point",
    "coordinates": [
      -9.26,
      38.777
    ]
  },
  "type": "Feature",
  "properties": {
    "hierarchy": [
      "tgn:1049716",
      "tgn:1000882",
      "tgn:1000003",
      "tgn:1000090",
      "tgn:7029392"
    ],
    "placetype": [
      "aat:300008347"
    ],
    "id": 1049716,
    "name:xx": "Belas"
  }
}
