{
  "geometry": {
    "type": "Point",
    "coordinates": [
      61.55,
      51.6167
    ]
  },
  "type": "Feature",
  "properties": {
    "hierarchy": [
      "tgn:1137113",
      "tgn:1000004",
      "tgn:7012922",
      "tgn:7014786",
      "tgn:7029392"
    ],
    "placetype": [
      "aat:300008347"
    ],
    "id": 1137113,
    "name:xx": "Zhailma"
  }
}
