{
  "type": "FeatureCollection",
  "features": [
    {
      "geometry": {
        "type": "Point",
        "coordinates": [
          -106.65,
          39.15
        ]
      },
      "type": "Feature",
      "properties": {
        "hierarchy": [
          "tgn:2511030",
          "tgn:1000001",
          "tgn:7012149",
          "tgn:7007158",
          "tgn:2000240",
          "tgn:7029392"
        ],
        "placetype": [
          "aat:300008706"
        ],
        "id": 2511030,
        "name:xx": "Midway Creek"
      }
    },
    {
      "geometry": {
        "type": "Point",
        "coordinates": [
          -87.5333,
          46.5333
        ]
      },
      "type": "Feature",
      "properties": {
        "hierarchy": [
          "tgn:2511031",
          "tgn:1000001",
          "tgn:7012149",
          "tgn:2000975",
          "tgn:7007520",
          "tgn:7029392"
        ],
        "placetype": [
          "aat:300008706"
        ],
        "id": 2511031,
        "name:xx": "Midway Creek"
      }
    },
    {
      "geometry": {
        "type": "Point",
        "coordinates": [
          -83.6833,
          35.9833
        ]
      },
      "type": "Feature",
      "properties": {
        "hierarchy": [
          "tgn:2511032",
          "tgn:1000001",
          "tgn:7012149",
          "tgn:2001883",
          "tgn:7007825",
          "tgn:7029392"
        ],
        "placetype": [
          "aat:300008706"
        ],
        "id": 2511032,
        "name:xx": "Midway Creek"
      }
    },
    {
      "geometry": {
        "type": "Point",
        "coordinates": [
          -112.85,
          37.5667
        ]
      },
      "type": "Feature",
      "properties": {
        "hierarchy": [
          "tgn:2511033",
          "tgn:1000001",
          "tgn:7012149",
          "tgn:7007827",
          "tgn:7029392"
        ],
        "placetype": [
          "aat:300008706"
        ],
        "id": 2511033,
        "name:xx": "Midway Creek"
      }
    },
    {
      "geometry": {
        "type": "Point",
        "coordinates": [
          -76.55,
          37.7333
        ]
      },
      "type": "Feature",
      "properties": {
        "hierarchy": [
          "tgn:2511034",
          "tgn:1000001",
          "tgn:7012149",
          "tgn:1002575",
          "tgn:7007919",
          "tgn:7029392"
        ],
        "placetype": [
          "aat:300008706"
        ],
        "id": 2511034,
        "name:xx": "Midway Creek"
      }
    },
    {
      "geometry": {
        "type": "Point",
        "coordinates": [
          -121.5,
          46.35
        ]
      },
      "type": "Feature",
      "properties": {
        "hierarchy": [
          "tgn:2511035",
          "tgn:1000001",
          "tgn:7012149",
          "tgn:7007920",
          "tgn:7029392"
        ],
        "placetype": [
          "aat:300008706"
        ],
        "id": 2511035,
        "name:xx": "Midway Creek"
      }
    },
    {
      "geometry": {
        "type": "Point",
        "coordinates": [
          -123.1667,
          46.2833
        ]
      },
      "type": "Feature",
      "properties": {
        "hierarchy": [
          "tgn:2511036",
          "tgn:1000001",
          "tgn:1002305",
          "tgn:7012149",
          "tgn:7007920",
          "tgn:7029392"
        ],
        "placetype": [
          "aat:300008706"
        ],
        "id": 2511036,
        "name:xx": "Midway Creek"
      }
    },
    {
      "geometry": {
        "type": "Point",
        "coordinates": [
          -122.1833,
          46.7833
        ]
      },
      "type": "Feature",
      "properties": {
        "hierarchy": [
          "tgn:2511037",
          "tgn:1000001",
          "tgn:7012149",
          "tgn:1002785",
          "tgn:7007920",
          "tgn:7029392"
        ],
        "placetype": [
          "aat:300008706"
        ],
        "id": 2511037,
        "name:xx": "Midway Creek"
      }
    },
    {
      "geometry": {
        "type": "Point",
        "coordinates": [
          -89.7333,
          36.0167
        ]
      },
      "type": "Feature",
      "properties": {
        "hierarchy": [
          "tgn:2511038",
          "tgn:1000001",
          "tgn:7012149",
          "tgn:2001227",
          "tgn:7007523",
          "tgn:7029392"
        ],
        "placetype": [
          "aat:300008761"
        ],
        "id": 2511038,
        "name:xx": "Midway Crevasse"
      }
    },
    {
      "geometry": {
        "type": "Point",
        "coordinates": [
          -76.2667,
          41.3167
        ]
      },
      "type": "Feature",
      "properties": {
        "hierarchy": [
          "tgn:2511039",
          "tgn:1000001",
          "tgn:7012149",
          "tgn:1002612",
          "tgn:7007710",
          "tgn:7029392"
        ],
        "placetype": [
          "aat:300008761"
        ],
        "id": 2511039,
        "name:xx": "Midway Crevasse"
      }
    }
  ]
}
