{
  "geometry": {
    "type": "Point",
    "coordinates": [
      -75.6167,
      2.2333
    ]
  },
  "type": "Feature",
  "properties": {
    "hierarchy": [
      "tgn:1023824",
      "tgn:1000640",
      "tgn:1000050",
      "tgn:1000002",
      "tgn:7029392"
    ],
    "placetype": [
      "aat:300008347"
    ],
    "id": 1023824,
    "name:xx": "Garzón"
  }
}
