{
  "geometry": {
    "type": "Point",
    "coordinates": [
      -76.3667,
      39.8667
    ]
  },
  "type": "Feature",
  "properties": {
    "hierarchy": [
      "tgn:2741492",
      "tgn:1000001",
      "tgn:7012149",
      "tgn:7013867",
      "tgn:7007710",
      "tgn:7029392"
    ],
    "placetype": [
      "aat:300386853"
    ],
    "id": 2741492,
    "name:xx": "Urey Islands"
  }
}
