{
  "geometry": {
    "type": "Point",
    "coordinates": [
      -118.6333,
      41.7833
    ]
  },
  "type": "Feature",
  "properties": {
    "hierarchy": [
      "tgn:2131261",
      "tgn:1000001",
      "tgn:2001414",
      "tgn:7012149",
      "tgn:7007526",
      "tgn:7029392"
    ],
    "placetype": [
      "aat:300386845"
    ],
    "id": 2131261,
    "name:xx": "Alta Creek Basin"
  }
}
