{
  "geometry": {
    "type": "Point",
    "coordinates": [
      -76.1333,
      39.3333
    ]
  },
  "type": "Feature",
  "properties": {
    "hierarchy": [
      "tgn:2505024",
      "tgn:1000001",
      "tgn:1002539",
      "tgn:7012149",
      "tgn:7007516",
      "tgn:7029392"
    ],
    "placetype": [
      "aat:300008850"
    ],
    "id": 2505024,
    "name:xx": "Meeks Point"
  }
}
