{
  "geometry": {
    "type": "Point",
    "coordinates": [
      -92.0833,
      37.8167
    ]
  },
  "type": "Feature",
  "properties": {
    "hierarchy": [
      "tgn:2471228",
      "tgn:1000001",
      "tgn:7012149",
      "tgn:2001233",
      "tgn:7007523",
      "tgn:7029392"
    ],
    "placetype": [
      "aat:300008798"
    ],
    "id": 2471228,
    "name:xx": "Lost Hill"
  }
}
