{
  "geometry": {
    "type": "Point",
    "coordinates": [
      -117.75,
      34.3667
    ]
  },
  "type": "Feature",
  "properties": {
    "hierarchy": [
      "tgn:2481380",
      "tgn:1000001",
      "tgn:7012149",
      "tgn:7007157",
      "tgn:1002608",
      "tgn:7029392"
    ],
    "placetype": [
      "aat:300008697"
    ],
    "id": 2481380,
    "name:xx": "Lamel Spring"
  }
}
