{
  "geometry": {
    "type": "Point",
    "coordinates": [
      120.6304,
      24.1563
    ]
  },
  "type": "Feature",
  "properties": {
    "hierarchy": [
      "tgn:7500561",
      "tgn:1000004",
      "tgn:7001009",
      "tgn:1000141",
      "tgn:7029392"
    ],
    "placetype": [
      "aat:300000498"
    ],
    "id": 7500561,
    "name:xx": "Liming Xincun"
  }
}
