{
  "geometry": {
    "type": "Point",
    "coordinates": [
      -92.35,
      31.7833
    ]
  },
  "type": "Feature",
  "properties": {
    "hierarchy": [
      "tgn:1123562",
      "tgn:1000001",
      "tgn:7012149",
      "tgn:2000917",
      "tgn:7007256",
      "tgn:7029392"
    ],
    "placetype": [
      "aat:300008707"
    ],
    "id": 1123562,
    "name:xx": "Dugdemona"
  }
}
