{
  "geometry": {
    "type": "Point",
    "coordinates": [
      -90.9667,
      39.3667
    ]
  },
  "type": "Feature",
  "properties": {
    "hierarchy": [
      "tgn:2565023",
      "tgn:1000001",
      "tgn:7012149",
      "tgn:1002787",
      "tgn:7007523",
      "tgn:7029392"
    ],
    "placetype": [
      "aat:300008798"
    ],
    "id": 2565023,
    "name:xx": "Page Knob"
  }
}
