{
  "geometry": {
    "type": "Point",
    "coordinates": [
      -71.35,
      44.4167
    ]
  },
  "type": "Feature",
  "properties": {
    "hierarchy": [
      "tgn:2591772",
      "tgn:1002300",
      "tgn:1000001",
      "tgn:7012149",
      "tgn:7007564",
      "tgn:7029392"
    ],
    "placetype": [
      "aat:300008798"
    ],
    "id": 2591772,
    "name:xx": "Pond Hill"
  }
}
