{
  "geometry": {
    "type": "Point",
    "coordinates": [
      31.03926,
      30.626471
    ]
  },
  "type": "Feature",
  "properties": {
    "hierarchy": [
      "tgn:7533686",
      "tgn:7001242",
      "tgn:7016833",
      "tgn:1001087",
      "tgn:7029392"
    ],
    "placetype": [
      "aat:300008347"
    ],
    "name:en": "Kafr Milīj",
    "id": 7533686
  }
}
