{
  "geometry": {
    "type": "Point",
    "coordinates": [
      -122.25,
      41.0333
    ]
  },
  "type": "Feature",
  "properties": {
    "hierarchy": [
      "tgn:2724682",
      "tgn:1000001",
      "tgn:7012149",
      "tgn:7007157",
      "tgn:2000188",
      "tgn:7029392"
    ],
    "placetype": [
      "aat:300008798"
    ],
    "id": 2724682,
    "name:xx": "Tombstone Mountain"
  }
}
