{
  "geometry": {
    "type": "Point",
    "coordinates": [
      -83.3667,
      35.6333
    ]
  },
  "type": "Feature",
  "properties": {
    "hierarchy": [
      "tgn:2406883",
      "tgn:1000001",
      "tgn:7012149",
      "tgn:2001543",
      "tgn:7007709",
      "tgn:7029392"
    ],
    "placetype": [
      "aat:300008706"
    ],
    "id": 2406883,
    "name:xx": "Hunter Creek"
  }
}
