{
  "geometry": {
    "type": "Point",
    "coordinates": [
      -82.8833,
      36.7667
    ]
  },
  "type": "Feature",
  "properties": {
    "hierarchy": [
      "tgn:2143556",
      "tgn:1000001",
      "tgn:7012149",
      "tgn:2002169",
      "tgn:7007919",
      "tgn:7029392"
    ],
    "placetype": [
      "aat:300008746"
    ],
    "id": 2143556,
    "name:xx": "Baileys Cave"
  }
}
