{
  "geometry": {
    "type": "Point",
    "coordinates": [
      -74.7333,
      43.5833
    ]
  },
  "type": "Feature",
  "properties": {
    "hierarchy": [
      "tgn:2223775",
      "tgn:1000001",
      "tgn:7012149",
      "tgn:1002440",
      "tgn:7007568",
      "tgn:7029392"
    ],
    "placetype": [
      "aat:300008905"
    ],
    "id": 2223775,
    "name:xx": "Carter Mudhole"
  }
}
