{
  "geometry": {
    "type": "Point",
    "coordinates": [
      -106.1333,
      38.2833
    ]
  },
  "type": "Feature",
  "properties": {
    "hierarchy": [
      "tgn:2447051",
      "tgn:1000001",
      "tgn:7012149",
      "tgn:7007158",
      "tgn:2000246",
      "tgn:7029392"
    ],
    "placetype": [
      "aat:300000390"
    ],
    "id": 2447051,
    "name:xx": "Liberty Mine"
  }
}
