{
  "geometry": {
    "type": "Point",
    "coordinates": [
      77.759167,
      30.045
    ]
  },
  "type": "Feature",
  "properties": {
    "hierarchy": [
      "tgn:7573221",
      "tgn:1000004",
      "tgn:7000198",
      "tgn:7016722",
      "tgn:7029392"
    ],
    "placetype": [
      "aat:300008347"
    ],
    "name:en": "Mādo",
    "id": 7573221
  }
}
