{
  "geometry": {
    "type": "Point",
    "coordinates": [
      -97.1167,
      38.9333
    ]
  },
  "type": "Feature",
  "properties": {
    "hierarchy": [
      "tgn:2036269",
      "tgn:1000001",
      "tgn:2000680",
      "tgn:7012149",
      "tgn:7007254",
      "tgn:7029392"
    ],
    "placetype": [
      "aat:300008347"
    ],
    "id": 2036269,
    "name:xx": "Detroit"
  }
}
