{
  "type": "FeatureCollection",
  "features": [
    {
      "geometry": {
        "type": "Point",
        "coordinates": [
          -76.3,
          38.9333
        ]
      },
      "type": "Feature",
      "properties": {
        "hierarchy": [
          "tgn:1007672",
          "tgn:1000001",
          "tgn:2124025",
          "tgn:7012149",
          "tgn:7007516",
          "tgn:7029392"
        ],
        "placetype": [
          "aat:300008791"
        ],
        "id": 1007672,
        "name:xx": "Kent Island"
      }
    },
    {
      "geometry": {
        "type": "Point",
        "coordinates": [
          -5.566667,
          56.383333
        ]
      },
      "type": "Feature",
      "properties": {
        "hierarchy": [
          "tgn:1007674",
          "tgn:7019094",
          "tgn:7002444",
          "tgn:1000003",
          "tgn:7008591",
          "tgn:7029392"
        ],
        "placetype": [
          "aat:300008791"
        ],
        "name:en": "Kerrera",
        "id": 1007674
      }
    },
    {
      "geometry": {
        "type": "Point",
        "coordinates": [
          103.95,
          1.4
        ]
      },
      "type": "Feature",
      "properties": {
        "hierarchy": [
          "tgn:1007675",
          "tgn:1000004",
          "tgn:7000381",
          "tgn:7029392"
        ],
        "placetype": [
          "aat:300008791"
        ],
        "id": 1007675,
        "name:xx": "Ketam"
      }
    },
    {
      "geometry": {
        "type": "Point",
        "coordinates": [
          152.4833,
          47.35
        ]
      },
      "type": "Feature",
      "properties": {
        "hierarchy": [
          "tgn:1007676",
          "tgn:7016712",
          "tgn:1000004",
          "tgn:1003406",
          "tgn:7018214",
          "tgn:7002435",
          "tgn:7029392"
        ],
        "placetype": [
          "aat:300008791"
        ],
        "id": 1007676,
        "name:xx": "Ketoy, Ostrov"
      }
    },
    {
      "geometry": {
        "type": "Point",
        "coordinates": [
          -80.4667,
          25.1167
        ]
      },
      "type": "Feature",
      "properties": {
        "hierarchy": [
          "tgn:1007677",
          "tgn:1000001",
          "tgn:7021534",
          "tgn:7012149",
          "tgn:1002676",
          "tgn:7007240",
          "tgn:7029392"
        ],
        "placetype": [
          "aat:300008791"
        ],
        "id": 1007677,
        "name:xx": "Key Largo"
      }
    }
  ]
}
