{
  "geometry": {
    "type": "Point",
    "coordinates": [
      -86.15,
      42.0667
    ]
  },
  "type": "Feature",
  "properties": {
    "hierarchy": [
      "tgn:2663238",
      "tgn:1000001",
      "tgn:1002243",
      "tgn:7012149",
      "tgn:7007520",
      "tgn:7029392"
    ],
    "placetype": [
      "aat:300008706"
    ],
    "id": 2663238,
    "name:xx": "Silver Creek"
  }
}
