{
  "geometry": {
    "type": "Point",
    "coordinates": [
      -87.3833,
      15.55
    ]
  },
  "type": "Feature",
  "properties": {
    "hierarchy": [
      "tgn:1016808",
      "tgn:1000512",
      "tgn:1000001",
      "tgn:7005554",
      "tgn:7029392"
    ],
    "placetype": [
      "aat:300008347"
    ],
    "id": 1016808,
    "name:xx": "Mezapa"
  }
}
