{
  "geometry": {
    "type": "Point",
    "coordinates": [
      -101.333333,
      23.25
    ]
  },
  "type": "Feature",
  "properties": {
    "hierarchy": [
      "tgn:7427465",
      "tgn:1000001",
      "tgn:7005594",
      "tgn:7005560",
      "tgn:7029392"
    ],
    "placetype": [
      "aat:300008699"
    ],
    "id": 7427465,
    "name:xx": "La Barranca, Río"
  }
}
