{
  "geometry": {
    "type": "Point",
    "coordinates": [
      -76.4833,
      38.9833
    ]
  },
  "type": "Feature",
  "properties": {
    "hierarchy": [
      "tgn:2751030",
      "tgn:7014651",
      "tgn:1000001",
      "tgn:7012149",
      "tgn:7007516",
      "tgn:7029392"
    ],
    "placetype": [
      "aat:300008347"
    ],
    "id": 2751030,
    "name:xx": "Wardour Bluffs"
  }
}
