{
  "geometry": {
    "type": "Point",
    "coordinates": [
      27.2333,
      37.35
    ]
  },
  "type": "Feature",
  "properties": {
    "hierarchy": [
      "tgn:7002494",
      "tgn:1001117",
      "tgn:1000004",
      "tgn:7018451",
      "tgn:1000144",
      "tgn:7029392"
    ],
    "placetype": [
      "aat:300000810",
      "aat:300387272",
      "aat:300000833"
    ],
    "id": 7002494,
    "name:xx": "Didyma"
  }
}
