{
  "geometry": {
    "type": "Point",
    "coordinates": [
      -85.45,
      37.7167
    ]
  },
  "type": "Feature",
  "properties": {
    "hierarchy": [
      "tgn:2604126",
      "tgn:1000001",
      "tgn:7012149",
      "tgn:2000833",
      "tgn:7007255",
      "tgn:7029392"
    ],
    "placetype": [
      "aat:300008699"
    ],
    "id": 2604126,
    "name:xx": "Quirks Branch"
  }
}
