{
  "geometry": {
    "type": "Point",
    "coordinates": [
      -149.6167,
      -17.5667
    ]
  },
  "type": "Feature",
  "properties": {
    "hierarchy": [
      "tgn:1012553",
      "tgn:7006218",
      "tgn:7006211",
      "tgn:1000216",
      "tgn:1000006",
      "tgn:7029392"
    ],
    "placetype": [
      "aat:300386846"
    ],
    "id": 1012553,
    "name:xx": "Tataa, Pointe"
  }
}
