{
  "geometry": {
    "type": "Point",
    "coordinates": [
      -111.4667,
      35.0833
    ]
  },
  "type": "Feature",
  "properties": {
    "hierarchy": [
      "tgn:2786295",
      "tgn:1000001",
      "tgn:7006451",
      "tgn:2000092",
      "tgn:7012149",
      "tgn:7029392"
    ],
    "placetype": [
      "aat:300008680"
    ],
    "id": 2786295,
    "name:xx": "Youngs Lake"
  }
}
