{
  "geometry": {
    "type": "Point",
    "coordinates": [
      -85.1667,
      32.5833
    ]
  },
  "type": "Feature",
  "properties": {
    "hierarchy": [
      "tgn:2768147",
      "tgn:7002659",
      "tgn:1000001",
      "tgn:7012149",
      "tgn:2000040",
      "tgn:7029392"
    ],
    "placetype": [
      "aat:300008706"
    ],
    "id": 2768147,
    "name:xx": "Whites Creek"
  }
}
