{
  "geometry": {
    "type": "Point",
    "coordinates": [
      -78.75,
      39.9333
    ]
  },
  "type": "Feature",
  "properties": {
    "hierarchy": [
      "tgn:2462618",
      "tgn:1000001",
      "tgn:7012149",
      "tgn:7007710",
      "tgn:7029392"
    ],
    "placetype": [
      "aat:300008706"
    ],
    "id": 2462618,
    "name:xx": "Little Wills Creek"
  }
}
