{
  "geometry": {
    "type": "Point",
    "coordinates": [
      -117.8167,
      40.65
    ]
  },
  "type": "Feature",
  "properties": {
    "hierarchy": [
      "tgn:2332887",
      "tgn:1000001",
      "tgn:2001419",
      "tgn:7012149",
      "tgn:7007526",
      "tgn:7029392"
    ],
    "placetype": [
      "aat:300000390"
    ],
    "id": 2332887,
    "name:xx": "Floyds Shaft"
  }
}
