{
  "geometry": {
    "type": "Point",
    "coordinates": [
      74.8833,
      32.3333
    ]
  },
  "type": "Feature",
  "properties": {
    "hierarchy": [
      "tgn:1083865",
      "tgn:1000004",
      "tgn:1001490",
      "tgn:1000133",
      "tgn:7029392"
    ],
    "placetype": [
      "aat:300008347"
    ],
    "id": 1083865,
    "name:xx": "Zafarwal"
  }
}
