{
  "geometry": {
    "type": "Point",
    "coordinates": [
      120.4548,
      23.7644
    ]
  },
  "type": "Feature",
  "properties": {
    "hierarchy": [
      "tgn:7490023",
      "tgn:1000004",
      "tgn:7001014",
      "tgn:1000141",
      "tgn:7029392"
    ],
    "placetype": [
      "aat:300008347"
    ],
    "id": 7490023,
    "name:xx": "Jinglun"
  }
}
