{
  "geometry": {
    "type": "Point",
    "coordinates": [
      72.5667,
      41.9167
    ]
  },
  "type": "Feature",
  "properties": {
    "hierarchy": [
      "tgn:1056876",
      "tgn:7011476",
      "tgn:1000004",
      "tgn:7006655",
      "tgn:7029392"
    ],
    "placetype": [
      "aat:300008347"
    ],
    "id": 1056876,
    "name:xx": "Mazarsu"
  }
}
