{
  "geometry": {
    "type": "Point",
    "coordinates": [
      -112.4667,
      45.7167
    ]
  },
  "type": "Feature",
  "properties": {
    "hierarchy": [
      "tgn:2390448",
      "tgn:1000001",
      "tgn:7012149",
      "tgn:7007524",
      "tgn:7029392"
    ],
    "placetype": [
      "aat:300008798"
    ],
    "id": 2390448,
    "name:xx": "Highland Mountains"
  }
}
