{
  "geometry": {
    "type": "Point",
    "coordinates": [
      -121.5667,
      36.0167
    ]
  },
  "type": "Feature",
  "properties": {
    "hierarchy": [
      "tgn:2470189",
      "tgn:1000001",
      "tgn:7012149",
      "tgn:7007157",
      "tgn:1002684",
      "tgn:7029392"
    ],
    "placetype": [
      "aat:300008791"
    ],
    "id": 2470189,
    "name:xx": "Lopez Rock"
  }
}
