{
  "type": "FeatureCollection",
  "features": [
    {
      "geometry": {
        "type": "Point",
        "coordinates": [
          22.55,
          39.333333
        ]
      },
      "type": "Feature",
      "properties": {
        "hierarchy": [
          "tgn:7236050",
          "tgn:7002750",
          "tgn:7001399",
          "tgn:1000003",
          "tgn:1000074",
          "tgn:7029392"
        ],
        "placetype": [
          "aat:300008347"
        ],
        "id": 7236050,
        "name:xx": "Áno Vasiliká"
      }
    },
    {
      "geometry": {
        "type": "Point",
        "coordinates": [
          23.8,
          38.133333
        ]
      },
      "type": "Feature",
      "properties": {
        "hierarchy": [
          "tgn:7236051",
          "tgn:7002681",
          "tgn:7001395",
          "tgn:1000003",
          "tgn:1000074",
          "tgn:7029392"
        ],
        "placetype": [
          "aat:300008347"
        ],
        "id": 7236051,
        "name:xx": "Áno Varibóbi"
      }
    },
    {
      "geometry": {
        "type": "Point",
        "coordinates": [
          22.416667,
          38.8
        ]
      },
      "type": "Feature",
      "properties": {
        "hierarchy": [
          "tgn:7236052",
          "tgn:4003773",
          "tgn:7001395",
          "tgn:1000003",
          "tgn:1000074",
          "tgn:7029392"
        ],
        "placetype": [
          "aat:300008347"
        ],
        "id": 7236052,
        "name:xx": "Áno Vardhátai"
      }
    },
    {
      "geometry": {
        "type": "Point",
        "coordinates": [
          20.75,
          38.1
        ]
      },
      "type": "Feature",
      "properties": {
        "hierarchy": [
          "tgn:7236053",
          "tgn:7011167",
          "tgn:7001338",
          "tgn:1000003",
          "tgn:1000074",
          "tgn:7029392"
        ],
        "placetype": [
          "aat:300008347"
        ],
        "id": 7236053,
        "name:xx": "Áno Váltai"
      }
    },
    {
      "geometry": {
        "type": "Point",
        "coordinates": [
          23.75,
          35.5
        ]
      },
      "type": "Feature",
      "properties": {
        "hierarchy": [
          "tgn:7236055",
          "tgn:7002690",
          "tgn:7012056",
          "tgn:1000003",
          "tgn:1000074",
          "tgn:7029392"
        ],
        "placetype": [
          "aat:300008347"
        ],
        "id": 7236055,
        "name:xx": "Áno Tzinerianá"
      }
    },
    {
      "geometry": {
        "type": "Point",
        "coordinates": [
          24.683333,
          35.333333
        ]
      },
      "type": "Feature",
      "properties": {
        "hierarchy": [
          "tgn:7236056",
          "tgn:7002690",
          "tgn:7012056",
          "tgn:1000003",
          "tgn:1000074",
          "tgn:7029392"
        ],
        "placetype": [
          "aat:300008347"
        ],
        "id": 7236056,
        "name:xx": "Áno Tripódhon"
      }
    },
    {
      "geometry": {
        "type": "Point",
        "coordinates": [
          24.966667,
          41.366667
        ]
      },
      "type": "Feature",
      "properties": {
        "hierarchy": [
          "tgn:7236057",
          "tgn:7011170",
          "tgn:7002715",
          "tgn:1000003",
          "tgn:1000074",
          "tgn:7029392"
        ],
        "placetype": [
          "aat:300000745"
        ],
        "id": 7236057,
        "name:xx": "Áno Thérmai"
      }
    },
    {
      "geometry": {
        "type": "Point",
        "coordinates": [
          23.016667,
          41.166667
        ]
      },
      "type": "Feature",
      "properties": {
        "hierarchy": [
          "tgn:7236058",
          "tgn:7002725",
          "tgn:7002715",
          "tgn:1000003",
          "tgn:1000074",
          "tgn:7029392"
        ],
        "placetype": [
          "aat:300008347"
        ],
        "id": 7236058,
        "name:xx": "Áno Theodhorákion"
      }
    },
    {
      "geometry": {
        "type": "Point",
        "coordinates": [
          22.366667,
          38
        ]
      },
      "type": "Feature",
      "properties": {
        "hierarchy": [
          "tgn:7236059",
          "tgn:7002741",
          "tgn:7017076",
          "tgn:1000003",
          "tgn:1000074",
          "tgn:7029392"
        ],
        "placetype": [
          "aat:300008347"
        ],
        "id": 7236059,
        "name:xx": "Áno Tarsinón"
      }
    }
  ]
}
