{
  "type": "FeatureCollection",
  "features": [
    {
      "geometry": {
        "type": "Point",
        "coordinates": [
          -0.233333,
          51.2
        ]
      },
      "type": "Feature",
      "properties": {
        "hierarchy": [
          "tgn:7463710",
          "tgn:7002445",
          "tgn:1000003",
          "tgn:7008175",
          "tgn:7008591",
          "tgn:7029392"
        ],
        "placetype": [
          "aat:300008347"
        ],
        "name:en": "Leigh",
        "id": 7463710
      }
    },
    {
      "geometry": {
        "type": "Point",
        "coordinates": [
          -2.55,
          50.866667
        ]
      },
      "type": "Feature",
      "properties": {
        "hierarchy": [
          "tgn:7463712",
          "tgn:7002445",
          "tgn:1000003",
          "tgn:7011961",
          "tgn:7008591",
          "tgn:7029392"
        ],
        "placetype": [
          "aat:300008347"
        ],
        "name:en": "Leigh",
        "id": 7463712
      }
    },
    {
      "geometry": {
        "type": "Point",
        "coordinates": [
          -5.983333,
          54.616667
        ]
      },
      "type": "Feature",
      "properties": {
        "hierarchy": [
          "tgn:7463716",
          "tgn:7002448",
          "tgn:7019168",
          "tgn:1000003",
          "tgn:7008591",
          "tgn:7029392"
        ],
        "placetype": [
          "aat:300008347"
        ],
        "name:en": "Legoniel",
        "id": 7463716
      }
    },
    {
      "geometry": {
        "type": "Point",
        "coordinates": [
          -2.85,
          52.216667
        ]
      },
      "type": "Feature",
      "properties": {
        "hierarchy": [
          "tgn:7463717",
          "tgn:7002445",
          "tgn:1000003",
          "tgn:7008143",
          "tgn:7008591",
          "tgn:7029392"
        ],
        "placetype": [
          "aat:300008347"
        ],
        "name:en": "Legion Cross",
        "id": 7463717
      }
    },
    {
      "geometry": {
        "type": "Point",
        "coordinates": [
          -2.666667,
          55.683333
        ]
      },
      "type": "Feature",
      "properties": {
        "hierarchy": [
          "tgn:7463718",
          "tgn:7002444",
          "tgn:1000003",
          "tgn:7008072",
          "tgn:7008591",
          "tgn:7029392"
        ],
        "placetype": [
          "aat:300008347"
        ],
        "name:en": "Legerwood",
        "id": 7463718
      }
    }
  ]
}
