{
  "geometry": {
    "type": "Point",
    "coordinates": [
      79.142667,
      24.080139
    ]
  },
  "type": "Feature",
  "properties": {
    "hierarchy": [
      "tgn:7563359",
      "tgn:1000004",
      "tgn:7000198",
      "tgn:1001894",
      "tgn:7029392"
    ],
    "placetype": [
      "aat:300008865"
    ],
    "name:en": "Āmākoi Reserved Forest",
    "id": 7563359
  }
}
