{
  "type": "FeatureCollection",
  "features": [
    {
      "geometry": {
        "type": "Point",
        "coordinates": [
          -77.8667,
          44.5
        ]
      },
      "type": "Feature",
      "properties": {
        "hierarchy": [
          "tgn:1117940",
          "tgn:7005685",
          "tgn:1000001",
          "tgn:7013154",
          "tgn:7029392"
        ],
        "placetype": [
          "aat:300008680"
        ],
        "id": 1117940,
        "name:xx": "Round Lake"
      }
    },
    {
      "geometry": {
        "type": "Point",
        "coordinates": [
          -102.3833,
          50.55
        ]
      },
      "type": "Feature",
      "properties": {
        "hierarchy": [
          "tgn:1117941",
          "tgn:7005685",
          "tgn:1000001",
          "tgn:7005805",
          "tgn:7029392"
        ],
        "placetype": [
          "aat:300008680"
        ],
        "id": 1117941,
        "name:xx": "Round Lake"
      }
    },
    {
      "geometry": {
        "type": "Point",
        "coordinates": [
          -56,
          48.1667
        ]
      },
      "type": "Feature",
      "properties": {
        "hierarchy": [
          "tgn:1117942",
          "tgn:7005685",
          "tgn:7005807",
          "tgn:1000001",
          "tgn:7005801",
          "tgn:7029392"
        ],
        "placetype": [
          "aat:300008680"
        ],
        "id": 1117942,
        "name:xx": "Round Pond"
      }
    },
    {
      "geometry": {
        "type": "Point",
        "coordinates": [
          -93.4167,
          49.25
        ]
      },
      "type": "Feature",
      "properties": {
        "hierarchy": [
          "tgn:1117944",
          "tgn:7005685",
          "tgn:1000001",
          "tgn:7013154",
          "tgn:7029392"
        ],
        "placetype": [
          "aat:300008680"
        ],
        "id": 1117944,
        "name:xx": "Rowan Lake"
      }
    },
    {
      "geometry": {
        "type": "Point",
        "coordinates": [
          27.0333,
          56.1833
        ]
      },
      "type": "Feature",
      "properties": {
        "hierarchy": [
          "tgn:1117946",
          "tgn:7012152",
          "tgn:1000003",
          "tgn:7006541",
          "tgn:7029392"
        ],
        "placetype": [
          "aat:300008680"
        ],
        "id": 1117946,
        "name:xx": "Rusons"
      }
    },
    {
      "geometry": {
        "type": "Point",
        "coordinates": [
          -3.933333,
          58.3
        ]
      },
      "type": "Feature",
      "properties": {
        "hierarchy": [
          "tgn:1117947",
          "tgn:7002444",
          "tgn:1000003",
          "tgn:7008082",
          "tgn:7008591",
          "tgn:7029392"
        ],
        "placetype": [
          "aat:300008680"
        ],
        "name:en": "Ruathair, Loch an",
        "id": 1117947
      }
    },
    {
      "geometry": {
        "type": "Point",
        "coordinates": [
          36,
          3.5
        ]
      },
      "type": "Feature",
      "properties": {
        "hierarchy": [
          "tgn:1117948",
          "tgn:7001242",
          "tgn:7029392"
        ],
        "placetype": [
          "aat:300008680"
        ],
        "id": 1117948,
        "name:xx": "Rudolf, Lake"
      }
    }
  ]
}
