{
  "geometry": {
    "type": "Point",
    "coordinates": [
      -108.95,
      35.7833
    ]
  },
  "type": "Feature",
  "properties": {
    "hierarchy": [
      "tgn:2545639",
      "tgn:1000001",
      "tgn:7012149",
      "tgn:7019676",
      "tgn:7007566",
      "tgn:7029392"
    ],
    "placetype": [
      "aat:300008699"
    ],
    "id": 2545639,
    "name:xx": "North Fork Catron Wash"
  }
}
