{
  "geometry": {
    "type": "Point",
    "coordinates": [
      -112.6833,
      34.4833
    ]
  },
  "type": "Feature",
  "properties": {
    "hierarchy": [
      "tgn:2667720",
      "tgn:1000001",
      "tgn:7006451",
      "tgn:7012149",
      "tgn:2000103",
      "tgn:7029392"
    ],
    "placetype": [
      "aat:300008699"
    ],
    "id": 2667720,
    "name:xx": "Skull Valley Wash"
  }
}
