{
  "geometry": {
    "type": "Point",
    "coordinates": [
      -103.4833,
      37.6667
    ]
  },
  "type": "Feature",
  "properties": {
    "hierarchy": [
      "tgn:2399899",
      "tgn:1000001",
      "tgn:7012149",
      "tgn:2000236",
      "tgn:7007158",
      "tgn:7029392"
    ],
    "placetype": [
      "aat:300008761"
    ],
    "id": 2399899,
    "name:xx": "Horse Canyon"
  }
}
