{
  "geometry": {
    "type": "Point",
    "coordinates": [
      -72.2333,
      41.9333
    ]
  },
  "type": "Feature",
  "properties": {
    "hierarchy": [
      "tgn:2632678",
      "tgn:1000001",
      "tgn:1002949",
      "tgn:7012149",
      "tgn:7007159",
      "tgn:7029392"
    ],
    "placetype": [
      "aat:300008699"
    ],
    "id": 2632678,
    "name:xx": "Ruby Brook"
  }
}
