{
  "type": "FeatureCollection",
  "features": [
    {
      "geometry": {
        "type": "Point",
        "coordinates": [
          -102.533333,
          27.666667
        ]
      },
      "type": "Feature",
      "properties": {
        "hierarchy": [
          "tgn:7389820",
          "tgn:1001853",
          "tgn:1000001",
          "tgn:7005560",
          "tgn:7029392"
        ],
        "placetype": [
          "aat:300008347"
        ],
        "id": 7389820,
        "name:xx": "Rancho El Vaciero"
      }
    },
    {
      "geometry": {
        "type": "Point",
        "coordinates": [
          -106.2,
          30.133333
        ]
      },
      "type": "Feature",
      "properties": {
        "hierarchy": [
          "tgn:7389821",
          "tgn:7005581",
          "tgn:1000001",
          "tgn:7005560",
          "tgn:7029392"
        ],
        "placetype": [
          "aat:300008347"
        ],
        "id": 7389821,
        "name:xx": "Rancho El Uno"
      }
    },
    {
      "geometry": {
        "type": "Point",
        "coordinates": [
          -107.316667,
          25.383333
        ]
      },
      "type": "Feature",
      "properties": {
        "hierarchy": [
          "tgn:7389822",
          "tgn:1000001",
          "tgn:7005595",
          "tgn:7005560",
          "tgn:7029392"
        ],
        "placetype": [
          "aat:300008347"
        ],
        "id": 7389822,
        "name:xx": "Rancho El Turarillo"
      }
    },
    {
      "geometry": {
        "type": "Point",
        "coordinates": [
          -100.083333,
          24.7
        ]
      },
      "type": "Feature",
      "properties": {
        "hierarchy": [
          "tgn:7389823",
          "tgn:1000001",
          "tgn:7005589",
          "tgn:7005560",
          "tgn:7029392"
        ],
        "placetype": [
          "aat:300008347"
        ],
        "id": 7389823,
        "name:xx": "Rancho El Tunal"
      }
    },
    {
      "geometry": {
        "type": "Point",
        "coordinates": [
          -101.6,
          27.316667
        ]
      },
      "type": "Feature",
      "properties": {
        "hierarchy": [
          "tgn:7389824",
          "tgn:1001853",
          "tgn:1000001",
          "tgn:7005560",
          "tgn:7029392"
        ],
        "placetype": [
          "aat:300008347"
        ],
        "id": 7389824,
        "name:xx": "Rancho El Tulillo"
      }
    },
    {
      "geometry": {
        "type": "Point",
        "coordinates": [
          -101.116667,
          27.2
        ]
      },
      "type": "Feature",
      "properties": {
        "hierarchy": [
          "tgn:7389825",
          "tgn:1001853",
          "tgn:1000001",
          "tgn:7005560",
          "tgn:7029392"
        ],
        "placetype": [
          "aat:300008347"
        ],
        "id": 7389825,
        "name:xx": "Rancho El Tulillo"
      }
    },
    {
      "geometry": {
        "type": "Point",
        "coordinates": [
          -101.416667,
          25.65
        ]
      },
      "type": "Feature",
      "properties": {
        "hierarchy": [
          "tgn:7389826",
          "tgn:1001853",
          "tgn:1000001",
          "tgn:7005560",
          "tgn:7029392"
        ],
        "placetype": [
          "aat:300008347"
        ],
        "id": 7389826,
        "name:xx": "Rancho El Tulillo"
      }
    },
    {
      "geometry": {
        "type": "Point",
        "coordinates": [
          -116.483333,
          31.9
        ]
      },
      "type": "Feature",
      "properties": {
        "hierarchy": [
          "tgn:7389827",
          "tgn:1001835",
          "tgn:1000001",
          "tgn:7005560",
          "tgn:7029392"
        ],
        "placetype": [
          "aat:300008347"
        ],
        "id": 7389827,
        "name:xx": "Rancho El Tule"
      }
    },
    {
      "geometry": {
        "type": "Point",
        "coordinates": [
          -109.366667,
          29.9
        ]
      },
      "type": "Feature",
      "properties": {
        "hierarchy": [
          "tgn:7389828",
          "tgn:1000001",
          "tgn:1001960",
          "tgn:7005560",
          "tgn:7029392"
        ],
        "placetype": [
          "aat:300008347"
        ],
        "id": 7389828,
        "name:xx": "Rancho El Tule"
      }
    },
    {
      "geometry": {
        "type": "Point",
        "coordinates": [
          -101.016667,
          28.616667
        ]
      },
      "type": "Feature",
      "properties": {
        "hierarchy": [
          "tgn:7389829",
          "tgn:1001853",
          "tgn:1000001",
          "tgn:7005560",
          "tgn:7029392"
        ],
        "placetype": [
          "aat:300008347"
        ],
        "id": 7389829,
        "name:xx": "Rancho El Tule"
      }
    }
  ]
}
