{
  "geometry": {
    "type": "Point",
    "coordinates": [
      -122.8667,
      41.7167
    ]
  },
  "type": "Feature",
  "properties": {
    "hierarchy": [
      "tgn:2435075",
      "tgn:1000001",
      "tgn:7012149",
      "tgn:7007157",
      "tgn:2000189",
      "tgn:7029392"
    ],
    "placetype": [
      "aat:300008761"
    ],
    "id": 2435075,
    "name:xx": "Kentuck Gulch"
  }
}
