{
  "geometry": {
    "type": "Point",
    "coordinates": [
      36.6167,
      32.75
    ]
  },
  "type": "Feature",
  "properties": {
    "hierarchy": [
      "tgn:7002302",
      "tgn:1002066",
      "tgn:1000004",
      "tgn:1000140",
      "tgn:7029392"
    ],
    "placetype": [
      "aat:300008347",
      "aat:300000810",
      "aat:300008375"
    ],
    "id": 7002302,
    "name:xx": "Qanawat"
  }
}
