{
  "geometry": {
    "type": "Point",
    "coordinates": [
      -70.85,
      43.0167
    ]
  },
  "type": "Feature",
  "properties": {
    "hierarchy": [
      "tgn:2655887",
      "tgn:1000001",
      "tgn:7014352",
      "tgn:7012149",
      "tgn:7007564",
      "tgn:7029392"
    ],
    "placetype": [
      "aat:300008699"
    ],
    "id": 2655887,
    "name:xx": "Shaw Brook"
  }
}
