{
  "geometry": {
    "type": "Point",
    "coordinates": [
      -81.6833,
      32.1833
    ]
  },
  "type": "Feature",
  "properties": {
    "hierarchy": [
      "tgn:2342942",
      "tgn:1000001",
      "tgn:2000307",
      "tgn:7012149",
      "tgn:7007248",
      "tgn:7029392"
    ],
    "placetype": [
      "aat:300008699"
    ],
    "id": 2342942,
    "name:xx": "Futch Branch"
  }
}
