{
  "geometry": {
    "type": "Point",
    "coordinates": [
      -71.05,
      44.9167
    ]
  },
  "type": "Feature",
  "properties": {
    "hierarchy": [
      "tgn:2163020",
      "tgn:1000001",
      "tgn:7012149",
      "tgn:7029392"
    ],
    "placetype": [
      "aat:300008699"
    ],
    "id": 2163020,
    "name:xx": "Bennett Brook"
  }
}
