{
  "geometry": {
    "type": "Point",
    "coordinates": [
      22.6333,
      55.4667
    ]
  },
  "type": "Feature",
  "properties": {
    "hierarchy": [
      "tgn:1059461",
      "tgn:1000003",
      "tgn:7006611",
      "tgn:7006542",
      "tgn:7029392"
    ],
    "placetype": [
      "aat:300008347"
    ],
    "id": 1059461,
    "name:xx": "Skaudvilė"
  }
}
