{
  "type": "FeatureCollection",
  "features": [
    {
      "geometry": {
        "type": "Point",
        "coordinates": [
          -3.0167,
          51.6667
        ]
      },
      "type": "Feature",
      "properties": {
        "hierarchy": [
          "tgn:6004772",
          "tgn:7002443",
          "tgn:1000003",
          "tgn:7018957",
          "tgn:7008591",
          "tgn:7029392"
        ],
        "placetype": [
          "aat:300008347",
          "aat:300000745",
          "aat:300000810",
          "aat:300387308",
          "aat:300008375"
        ],
        "name:en": "Pontnewydd",
        "id": 6004772
      }
    },
    {
      "geometry": {
        "type": "Point",
        "coordinates": [
          23.1573,
          47.1793
        ]
      },
      "type": "Feature",
      "properties": {
        "hierarchy": [
          "tgn:6004778",
          "tgn:1000003",
          "tgn:1000441",
          "tgn:1000091",
          "tgn:7029392"
        ],
        "placetype": [
          "aat:300008347",
          "aat:300000810",
          "aat:300167671",
          "aat:300387275"
        ],
        "id": 6004778,
        "name:xx": "Porolissum"
      }
    }
  ]
}
