{
  "geometry": {
    "type": "Point",
    "coordinates": [
      121.8093,
      24.6699
    ]
  },
  "type": "Feature",
  "properties": {
    "hierarchy": [
      "tgn:7478689",
      "tgn:1000004",
      "tgn:7489179",
      "tgn:1000141",
      "tgn:7029392"
    ],
    "placetype": [
      "aat:300007836"
    ],
    "id": 7478689,
    "name:xx": "Jiuhao Qiao"
  }
}
