{
  "geometry": {
    "type": "Point",
    "coordinates": [
      -114.3833,
      36.25
    ]
  },
  "type": "Feature",
  "properties": {
    "hierarchy": [
      "tgn:2369635",
      "tgn:1000001",
      "tgn:2001410",
      "tgn:7012149",
      "tgn:2562899",
      "tgn:7007526",
      "tgn:7029392"
    ],
    "placetype": [
      "aat:300386851",
      "aat:300008791"
    ],
    "id": 2369635,
    "name:xx": "Gunsight"
  }
}
