{
  "geometry": {
    "type": "Point",
    "coordinates": [
      -82.9667,
      39.3667
    ]
  },
  "type": "Feature",
  "properties": {
    "hierarchy": [
      "tgn:2080024",
      "tgn:1000001",
      "tgn:7012149",
      "tgn:1002835",
      "tgn:7007706",
      "tgn:7029392"
    ],
    "placetype": [
      "aat:300008347"
    ],
    "id": 2080024,
    "name:xx": "Hopetown"
  }
}
