{
  "type": "FeatureCollection",
  "features": [
    {
      "geometry": {
        "type": "Point",
        "coordinates": [
          -124.1,
          43.9667
        ]
      },
      "type": "Feature",
      "properties": {
        "hierarchy": [
          "tgn:2149550",
          "tgn:1000001",
          "tgn:7012149",
          "tgn:2001716",
          "tgn:7007708",
          "tgn:7029392"
        ],
        "placetype": [
          "aat:300008680"
        ],
        "id": 2149550,
        "name:xx": "Barrette Lake"
      }
    },
    {
      "geometry": {
        "type": "Point",
        "coordinates": [
          -73.8833,
          40.8
        ]
      },
      "type": "Feature",
      "properties": {
        "hierarchy": [
          "tgn:2149551",
          "tgn:1000001",
          "tgn:7012149",
          "tgn:1002715",
          "tgn:7007568",
          "tgn:7029392"
        ],
        "placetype": [
          "aat:300132316"
        ],
        "id": 2149551,
        "name:xx": "Barretto Cove"
      }
    },
    {
      "geometry": {
        "type": "Point",
        "coordinates": [
          -73.8833,
          40.8
        ]
      },
      "type": "Feature",
      "properties": {
        "hierarchy": [
          "tgn:2149552",
          "tgn:1000001",
          "tgn:1002204",
          "tgn:7012149",
          "tgn:7007568",
          "tgn:7029392"
        ],
        "placetype": [
          "aat:300008850"
        ],
        "id": 2149552,
        "name:xx": "Barretto Point"
      }
    },
    {
      "geometry": {
        "type": "Point",
        "coordinates": [
          -68,
          46.8833
        ]
      },
      "type": "Feature",
      "properties": {
        "hierarchy": [
          "tgn:2149553",
          "tgn:2000919",
          "tgn:1000001",
          "tgn:7012149",
          "tgn:7007515",
          "tgn:7029392"
        ],
        "placetype": [
          "aat:300008347"
        ],
        "id": 2149553,
        "name:xx": "Barretts"
      }
    },
    {
      "geometry": {
        "type": "Point",
        "coordinates": [
          -73.45,
          41.25
        ]
      },
      "type": "Feature",
      "properties": {
        "hierarchy": [
          "tgn:2149554",
          "tgn:1002366",
          "tgn:1000001",
          "tgn:7012149",
          "tgn:7007159",
          "tgn:7029392"
        ],
        "placetype": [
          "aat:300008699"
        ],
        "id": 2149554,
        "name:xx": "Barretts Brook"
      }
    },
    {
      "geometry": {
        "type": "Point",
        "coordinates": [
          -81.8667,
          36.6167
        ]
      },
      "type": "Feature",
      "properties": {
        "hierarchy": [
          "tgn:2149555",
          "tgn:1000001",
          "tgn:7012149",
          "tgn:2002194",
          "tgn:7007919",
          "tgn:7029392"
        ],
        "placetype": [
          "aat:300008746"
        ],
        "id": 2149555,
        "name:xx": "Barretts Cave"
      }
    },
    {
      "geometry": {
        "type": "Point",
        "coordinates": [
          -77.05,
          36.4667
        ]
      },
      "type": "Feature",
      "properties": {
        "hierarchy": [
          "tgn:2149556",
          "tgn:1000001",
          "tgn:7012149",
          "tgn:1002474",
          "tgn:7007709",
          "tgn:7029392"
        ],
        "placetype": [
          "aat:300008347"
        ],
        "id": 2149556,
        "name:xx": "Barretts Crossroads"
      }
    },
    {
      "geometry": {
        "type": "Point",
        "coordinates": [
          -71.5667,
          42.4
        ]
      },
      "type": "Feature",
      "properties": {
        "hierarchy": [
          "tgn:2149557",
          "tgn:1000001",
          "tgn:7012149",
          "tgn:1003038",
          "tgn:7007517",
          "tgn:7029392"
        ],
        "placetype": [
          "aat:300008798"
        ],
        "id": 2149557,
        "name:xx": "Barretts Hill"
      }
    },
    {
      "geometry": {
        "type": "Point",
        "coordinates": [
          -83.35,
          34
        ]
      },
      "type": "Feature",
      "properties": {
        "hierarchy": [
          "tgn:2149558",
          "tgn:1000001",
          "tgn:2000320",
          "tgn:7012149",
          "tgn:7007248",
          "tgn:7029392"
        ],
        "placetype": [
          "aat:300008347"
        ],
        "id": 2149558,
        "name:xx": "Barretts Mill"
      }
    },
    {
      "geometry": {
        "type": "Point",
        "coordinates": [
          -87.75,
          44.65
        ]
      },
      "type": "Feature",
      "properties": {
        "hierarchy": [
          "tgn:2149559",
          "tgn:1000001",
          "tgn:7012149",
          "tgn:2002330",
          "tgn:7007922",
          "tgn:7029392"
        ],
        "placetype": [
          "aat:300008850"
        ],
        "id": 2149559,
        "name:xx": "Barretts Point"
      }
    }
  ]
}
