{
  "geometry": {
    "type": "Point",
    "coordinates": [
      -112.1333,
      46.25
    ]
  },
  "type": "Feature",
  "properties": {
    "hierarchy": [
      "tgn:2339677",
      "tgn:1000001",
      "tgn:7012149",
      "tgn:2001281",
      "tgn:7007524",
      "tgn:7029392"
    ],
    "placetype": [
      "aat:300000390"
    ],
    "id": 2339677,
    "name:xx": "Free Enterprise Mine"
  }
}
