{
  "geometry": {
    "type": "Point",
    "coordinates": [
      -90.0833,
      34.4833
    ]
  },
  "type": "Feature",
  "properties": {
    "hierarchy": [
      "tgn:2211439",
      "tgn:1000001",
      "tgn:7012149",
      "tgn:7007522",
      "tgn:7029392"
    ],
    "placetype": [
      "aat:300008706"
    ],
    "id": 2211439,
    "name:xx": "Butterbowl Creek"
  }
}
