{
  "geometry": {
    "type": "Point",
    "coordinates": [
      -101.0167,
      31.15
    ]
  },
  "type": "Feature",
  "properties": {
    "hierarchy": [
      "tgn:2302386",
      "tgn:1000001",
      "tgn:7012149",
      "tgn:2002007",
      "tgn:7007826",
      "tgn:7029392"
    ],
    "placetype": [
      "aat:300008761"
    ],
    "id": 2302386,
    "name:xx": "Dutch Woman Draw"
  }
}
