{
  "geometry": {
    "type": "Point",
    "coordinates": [
      -110.1167,
      35.4167
    ]
  },
  "type": "Feature",
  "properties": {
    "hierarchy": [
      "tgn:2563544",
      "tgn:1000001",
      "tgn:7006451",
      "tgn:7012149",
      "tgn:2000099",
      "tgn:7029392"
    ],
    "placetype": [
      "aat:300008697"
    ],
    "id": 2563544,
    "name:xx": "Owl Spring"
  }
}
