{
  "geometry": {
    "type": "Point",
    "coordinates": [
      -118.7333,
      36.3833
    ]
  },
  "type": "Feature",
  "properties": {
    "hierarchy": [
      "tgn:2311001",
      "tgn:1000001",
      "tgn:7012149",
      "tgn:7007157",
      "tgn:1002956",
      "tgn:7029392"
    ],
    "placetype": [
      "aat:300008706"
    ],
    "id": 2311001,
    "name:xx": "Eden Creek"
  }
}
