{
  "geometry": {
    "type": "Point",
    "coordinates": [
      -85.9833,
      40.4667
    ]
  },
  "type": "Feature",
  "properties": {
    "hierarchy": [
      "tgn:2671206",
      "tgn:1000001",
      "tgn:7012149",
      "tgn:1002487",
      "tgn:7007252",
      "tgn:7029392"
    ],
    "placetype": [
      "aat:300006075"
    ],
    "id": 2671206,
    "name:xx": "Smith Ditch"
  }
}
