{
  "geometry": {
    "type": "Point",
    "coordinates": [
      -82.6667,
      43.1833
    ]
  },
  "type": "Feature",
  "properties": {
    "hierarchy": [
      "tgn:2772295",
      "tgn:1000001",
      "tgn:7012149",
      "tgn:2000995",
      "tgn:7007520",
      "tgn:7029392"
    ],
    "placetype": [
      "aat:300006075"
    ],
    "id": 2772295,
    "name:xx": "Willey Drain"
  }
}
