{
  "geometry": {
    "type": "Point",
    "coordinates": [
      -75.8333,
      41.9167
    ]
  },
  "type": "Feature",
  "properties": {
    "hierarchy": [
      "tgn:2088585",
      "tgn:1000001",
      "tgn:7012149",
      "tgn:1002932",
      "tgn:7007710",
      "tgn:7029392"
    ],
    "placetype": [
      "aat:300008347"
    ],
    "id": 2088585,
    "name:xx": "Franklin Forks"
  }
}
