{
  "type": "FeatureCollection",
  "features": [
    {
      "geometry": {
        "type": "Point",
        "coordinates": [
          -82.6,
          36.4167
        ]
      },
      "type": "Feature",
      "properties": {
        "hierarchy": [
          "tgn:2144800",
          "tgn:1000001",
          "tgn:7012149",
          "tgn:2001926",
          "tgn:7007825",
          "tgn:7029392"
        ],
        "placetype": [
          "aat:300008798"
        ],
        "id": 2144800,
        "name:xx": "Bald Hill"
      }
    },
    {
      "geometry": {
        "type": "Point",
        "coordinates": [
          -82.55,
          36.45
        ]
      },
      "type": "Feature",
      "properties": {
        "hierarchy": [
          "tgn:2144801",
          "tgn:1000001",
          "tgn:7012149",
          "tgn:2001918",
          "tgn:7007825",
          "tgn:7029392"
        ],
        "placetype": [
          "aat:300008798"
        ],
        "id": 2144801,
        "name:xx": "Bald Hill"
      }
    },
    {
      "geometry": {
        "type": "Point",
        "coordinates": [
          -83.55,
          36.4833
        ]
      },
      "type": "Feature",
      "properties": {
        "hierarchy": [
          "tgn:2144802",
          "tgn:1000001",
          "tgn:7012149",
          "tgn:2001849",
          "tgn:7007825",
          "tgn:7029392"
        ],
        "placetype": [
          "aat:300008347"
        ],
        "id": 2144802,
        "name:xx": "Bald Hill"
      }
    },
    {
      "geometry": {
        "type": "Point",
        "coordinates": [
          -96.5333,
          31.7667
        ]
      },
      "type": "Feature",
      "properties": {
        "hierarchy": [
          "tgn:2144803",
          "tgn:1000001",
          "tgn:7012149",
          "tgn:1002597",
          "tgn:7007826",
          "tgn:7029392"
        ],
        "placetype": [
          "aat:300008798"
        ],
        "id": 2144803,
        "name:xx": "Bald Hill"
      }
    },
    {
      "geometry": {
        "type": "Point",
        "coordinates": [
          -93.9833,
          30.8333
        ]
      },
      "type": "Feature",
      "properties": {
        "hierarchy": [
          "tgn:2144804",
          "tgn:1000001",
          "tgn:7012149",
          "tgn:2002009",
          "tgn:7007826",
          "tgn:7029392"
        ],
        "placetype": [
          "aat:300008798"
        ],
        "id": 2144804,
        "name:xx": "Bald Hill"
      }
    },
    {
      "geometry": {
        "type": "Point",
        "coordinates": [
          -94.45,
          31.1667
        ]
      },
      "type": "Feature",
      "properties": {
        "hierarchy": [
          "tgn:2144805",
          "tgn:1002149",
          "tgn:1000001",
          "tgn:7012149",
          "tgn:7007826",
          "tgn:7029392"
        ],
        "placetype": [
          "aat:300008798"
        ],
        "id": 2144805,
        "name:xx": "Bald Hill"
      }
    },
    {
      "geometry": {
        "type": "Point",
        "coordinates": [
          -96.8,
          31.2833
        ]
      },
      "type": "Feature",
      "properties": {
        "hierarchy": [
          "tgn:2144806",
          "tgn:1000001",
          "tgn:7012149",
          "tgn:1002367",
          "tgn:7007826",
          "tgn:7029392"
        ],
        "placetype": [
          "aat:300008798"
        ],
        "id": 2144806,
        "name:xx": "Bald Hill"
      }
    },
    {
      "geometry": {
        "type": "Point",
        "coordinates": [
          -113.3333,
          37.5
        ]
      },
      "type": "Feature",
      "properties": {
        "hierarchy": [
          "tgn:2144807",
          "tgn:1000001",
          "tgn:7012149",
          "tgn:2002127",
          "tgn:7007827",
          "tgn:7029392"
        ],
        "placetype": [
          "aat:300008798"
        ],
        "id": 2144807,
        "name:xx": "Bald Hill"
      }
    },
    {
      "geometry": {
        "type": "Point",
        "coordinates": [
          -112.35,
          37.6667
        ]
      },
      "type": "Feature",
      "properties": {
        "hierarchy": [
          "tgn:2144808",
          "tgn:1000001",
          "tgn:7012149",
          "tgn:2002121",
          "tgn:7007827",
          "tgn:7029392"
        ],
        "placetype": [
          "aat:300008798"
        ],
        "id": 2144808,
        "name:xx": "Bald Hill"
      }
    },
    {
      "geometry": {
        "type": "Point",
        "coordinates": [
          -72.45,
          43.1
        ]
      },
      "type": "Feature",
      "properties": {
        "hierarchy": [
          "tgn:2144809",
          "tgn:1000001",
          "tgn:1003029",
          "tgn:7012149",
          "tgn:7007828",
          "tgn:7029392"
        ],
        "placetype": [
          "aat:300008798"
        ],
        "id": 2144809,
        "name:xx": "Bald Hill"
      }
    }
  ]
}
