{
  "geometry": {
    "type": "Point",
    "coordinates": [
      -110.7667,
      39.0333
    ]
  },
  "type": "Feature",
  "properties": {
    "hierarchy": [
      "tgn:2662317",
      "tgn:1000001",
      "tgn:2002108",
      "tgn:7012149",
      "tgn:7007827",
      "tgn:7029392"
    ],
    "placetype": [
      "aat:300008798"
    ],
    "id": 2662317,
    "name:xx": "Sids Mountain"
  }
}
