{
  "geometry": {
    "type": "Point",
    "coordinates": [
      -91.7167,
      30.3333
    ]
  },
  "type": "Feature",
  "properties": {
    "hierarchy": [
      "tgn:2139647",
      "tgn:1000001",
      "tgn:7012149",
      "tgn:2000903",
      "tgn:7007256",
      "tgn:7029392"
    ],
    "placetype": [
      "aat:300008347"
    ],
    "id": 2139647,
    "name:xx": "Atchafalaya"
  }
}
