{
  "geometry": {
    "type": "Point",
    "coordinates": [
      -85.15,
      43.7833
    ]
  },
  "type": "Feature",
  "properties": {
    "hierarchy": [
      "tgn:2356785",
      "tgn:1000001",
      "tgn:7012149",
      "tgn:2000977",
      "tgn:7007520",
      "tgn:7029392"
    ],
    "placetype": [
      "aat:300008680"
    ],
    "id": 2356785,
    "name:xx": "Gorrel Lake"
  }
}
