{
  "type": "FeatureCollection",
  "features": [
    {
      "geometry": {
        "type": "Point",
        "coordinates": [
          0.4,
          45.7333
        ]
      },
      "type": "Feature",
      "properties": {
        "hierarchy": [
          "tgn:1033701",
          "tgn:1000003",
          "tgn:7002892",
          "tgn:1000070",
          "tgn:7029392"
        ],
        "placetype": [
          "aat:300008347"
        ],
        "id": 1033701,
        "name:xx": "Rochefoucauld, la"
      }
    },
    {
      "geometry": {
        "type": "Point",
        "coordinates": [
          6.1167,
          45.4667
        ]
      },
      "type": "Feature",
      "properties": {
        "hierarchy": [
          "tgn:1033703",
          "tgn:1000003",
          "tgn:1000070",
          "tgn:7002897",
          "tgn:7029392"
        ],
        "placetype": [
          "aat:300008347"
        ],
        "id": 1033703,
        "name:xx": "La Rochette"
      }
    },
    {
      "geometry": {
        "type": "Point",
        "coordinates": [
          5.9667,
          43.3333
        ]
      },
      "type": "Feature",
      "properties": {
        "hierarchy": [
          "tgn:1033704",
          "tgn:1000003",
          "tgn:1000070",
          "tgn:7002895",
          "tgn:7029392"
        ],
        "placetype": [
          "aat:300008347"
        ],
        "id": 1033704,
        "name:xx": "Roquebrussanne, la"
      }
    },
    {
      "geometry": {
        "type": "Point",
        "coordinates": [
          2.7833,
          48.8
        ]
      },
      "type": "Feature",
      "properties": {
        "hierarchy": [
          "tgn:1033705",
          "tgn:1000003",
          "tgn:7002883",
          "tgn:1000070",
          "tgn:7029392"
        ],
        "placetype": [
          "aat:300008347"
        ],
        "id": 1033705,
        "name:xx": "Route, la"
      }
    },
    {
      "geometry": {
        "type": "Point",
        "coordinates": [
          5.9833,
          44.8333
        ]
      },
      "type": "Feature",
      "properties": {
        "hierarchy": [
          "tgn:1033706",
          "tgn:1000003",
          "tgn:1000070",
          "tgn:7002897",
          "tgn:7029392"
        ],
        "placetype": [
          "aat:300008347"
        ],
        "id": 1033706,
        "name:xx": "Salette-Fallavaux, la"
      }
    },
    {
      "geometry": {
        "type": "Point",
        "coordinates": [
          6,
          44.4167
        ]
      },
      "type": "Feature",
      "properties": {
        "hierarchy": [
          "tgn:1033707",
          "tgn:1000003",
          "tgn:1000070",
          "tgn:7002895",
          "tgn:7029392"
        ],
        "placetype": [
          "aat:300008347"
        ],
        "id": 1033707,
        "name:xx": "Saulce, la"
      }
    }
  ]
}
