{
  "geometry": {
    "type": "Point",
    "coordinates": [
      14.2333,
      50.8667
    ]
  },
  "type": "Feature",
  "properties": {
    "hierarchy": [
      "tgn:1027179",
      "tgn:7593920",
      "tgn:1000003",
      "tgn:1001780",
      "tgn:7029392"
    ],
    "placetype": [
      "aat:300008347"
    ],
    "id": 1027179,
    "name:xx": "Hřensko"
  }
}
