{
  "geometry": {
    "type": "Point",
    "coordinates": [
      -120.6833,
      41.1667
    ]
  },
  "type": "Feature",
  "properties": {
    "hierarchy": [
      "tgn:2441358",
      "tgn:1000001",
      "tgn:7012149",
      "tgn:7007157",
      "tgn:2000184",
      "tgn:7029392"
    ],
    "placetype": [
      "aat:300008798"
    ],
    "id": 2441358,
    "name:xx": "Knox Mountain"
  }
}
