{
  "geometry": {
    "type": "Point",
    "coordinates": [
      -71.3167,
      43.2167
    ]
  },
  "type": "Feature",
  "properties": {
    "hierarchy": [
      "tgn:2174886",
      "tgn:1000001",
      "tgn:2001425",
      "tgn:7012149",
      "tgn:7007564",
      "tgn:7029392"
    ],
    "placetype": [
      "aat:300006191"
    ],
    "id": 2174886,
    "name:xx": "Bixby Pond"
  }
}
