{
  "geometry": {
    "type": "Point",
    "coordinates": [
      -88.1333,
      36.85
    ]
  },
  "type": "Feature",
  "properties": {
    "hierarchy": [
      "tgn:2700768",
      "tgn:1000001",
      "tgn:7012149",
      "tgn:2000846",
      "tgn:7007255",
      "tgn:7029392"
    ],
    "placetype": [
      "aat:300132316"
    ],
    "id": 2700768,
    "name:xx": "Sugar Bay"
  }
}
