{
  "geometry": {
    "type": "Point",
    "coordinates": [
      -87.4833,
      31.45
    ]
  },
  "type": "Feature",
  "properties": {
    "hierarchy": [
      "tgn:2523236",
      "tgn:7002659",
      "tgn:1000001",
      "tgn:7012149",
      "tgn:2000049",
      "tgn:7029392"
    ],
    "placetype": [
      "aat:300008680"
    ],
    "id": 2523236,
    "name:xx": "Moores Pond"
  }
}
