{
  "geometry": {
    "type": "Point",
    "coordinates": [
      -77.3333,
      36.0667
    ]
  },
  "type": "Feature",
  "properties": {
    "hierarchy": [
      "tgn:2252855",
      "tgn:1000001",
      "tgn:7012149",
      "tgn:7007709",
      "tgn:7029392"
    ],
    "placetype": [
      "aat:300008706"
    ],
    "id": 2252855,
    "name:xx": "Conoho Creek"
  }
}
