{
  "geometry": {
    "type": "Point",
    "coordinates": [
      79.7564,
      27.239
    ]
  },
  "type": "Feature",
  "properties": {
    "hierarchy": [
      "tgn:7561230",
      "tgn:1000004",
      "tgn:7000198",
      "tgn:7016722",
      "tgn:7029392"
    ],
    "placetype": [
      "aat:300008347"
    ],
    "name:en": "Jasa Purwa",
    "id": 7561230
  }
}
