{
  "geometry": {
    "type": "Point",
    "coordinates": [
      -70.75,
      -13.8333
    ]
  },
  "type": "Feature",
  "properties": {
    "hierarchy": [
      "tgn:1108861",
      "tgn:1000002",
      "tgn:1000056",
      "tgn:7029392"
    ],
    "placetype": [
      "aat:300386831"
    ],
    "id": 1108861,
    "name:xx": "Carabaya, Cordillera de"
  }
}
