{
  "geometry": {
    "type": "Point",
    "coordinates": [
      -81.6667,
      39.3167
    ]
  },
  "type": "Feature",
  "properties": {
    "hierarchy": [
      "tgn:2466841",
      "tgn:1000001",
      "tgn:7012149",
      "tgn:2001622",
      "tgn:7007706",
      "tgn:7029392"
    ],
    "placetype": [
      "aat:300008699"
    ],
    "id": 2466841,
    "name:xx": "Long Brook"
  }
}
