{
  "geometry": {
    "type": "Point",
    "coordinates": [
      -100.0667,
      45.6167
    ]
  },
  "type": "Feature",
  "properties": {
    "hierarchy": [
      "tgn:2641917",
      "tgn:1000001",
      "tgn:2001780",
      "tgn:7012149",
      "tgn:7007713",
      "tgn:7029392"
    ],
    "placetype": [
      "aat:300008680"
    ],
    "id": 2641917,
    "name:xx": "Sand Lake"
  }
}
