{
  "geometry": {
    "type": "Point",
    "coordinates": [
      -96.4667,
      30.4167
    ]
  },
  "type": "Feature",
  "properties": {
    "hierarchy": [
      "tgn:2147681",
      "tgn:1000001",
      "tgn:7012149",
      "tgn:1002214",
      "tgn:7007826",
      "tgn:7029392"
    ],
    "placetype": [
      "aat:300008699"
    ],
    "id": 2147681,
    "name:xx": "Bare Branch"
  }
}
