{
  "geometry": {
    "type": "Point",
    "coordinates": [
      -82.5833,
      36.85
    ]
  },
  "type": "Feature",
  "properties": {
    "hierarchy": [
      "tgn:2237246",
      "tgn:1000001",
      "tgn:7012149",
      "tgn:2002189",
      "tgn:7007919",
      "tgn:7029392"
    ],
    "placetype": [
      "aat:300008798"
    ],
    "id": 2237246,
    "name:xx": "Chimney Rock"
  }
}
