{
  "type": "FeatureCollection",
  "features": [
    {
      "geometry": {
        "type": "Point",
        "coordinates": [
          -106.7167,
          39.4667
        ]
      },
      "type": "Feature",
      "properties": {
        "hierarchy": [
          "tgn:2708720",
          "tgn:1000001",
          "tgn:7012149",
          "tgn:2000210",
          "tgn:7007158",
          "tgn:7029392"
        ],
        "placetype": [
          "aat:300008680"
        ],
        "id": 2708720,
        "name:xx": "Sylvan Lake"
      }
    },
    {
      "geometry": {
        "type": "Point",
        "coordinates": [
          -106.7333,
          39.4667
        ]
      },
      "type": "Feature",
      "properties": {
        "hierarchy": [
          "tgn:2708721",
          "tgn:1000001",
          "tgn:7012149",
          "tgn:2000210",
          "tgn:7007158",
          "tgn:7029392"
        ],
        "placetype": [
          "aat:300006191"
        ],
        "id": 2708721,
        "name:xx": "Sylvan Lake"
      }
    },
    {
      "geometry": {
        "type": "Point",
        "coordinates": [
          -73.0667,
          41.5833
        ]
      },
      "type": "Feature",
      "properties": {
        "hierarchy": [
          "tgn:2708722",
          "tgn:1000001",
          "tgn:1002601",
          "tgn:7012149",
          "tgn:7007159",
          "tgn:7029392"
        ],
        "placetype": [
          "aat:300008680"
        ],
        "id": 2708722,
        "name:xx": "Sylvan Lake"
      }
    },
    {
      "geometry": {
        "type": "Point",
        "coordinates": [
          -81.3667,
          28.8
        ]
      },
      "type": "Feature",
      "properties": {
        "hierarchy": [
          "tgn:2708723",
          "tgn:1000001",
          "tgn:7012149",
          "tgn:1002881",
          "tgn:7007240",
          "tgn:7029392"
        ],
        "placetype": [
          "aat:300008680"
        ],
        "id": 2708723,
        "name:xx": "Sylvan Lake"
      }
    },
    {
      "geometry": {
        "type": "Point",
        "coordinates": [
          -83.6,
          32.5
        ]
      },
      "type": "Feature",
      "properties": {
        "hierarchy": [
          "tgn:2708724",
          "tgn:1000001",
          "tgn:7012149",
          "tgn:2000367",
          "tgn:7007248",
          "tgn:7029392"
        ],
        "placetype": [
          "aat:300008680"
        ],
        "id": 2708724,
        "name:xx": "Sylvan Lake"
      }
    },
    {
      "geometry": {
        "type": "Point",
        "coordinates": [
          -83.6,
          32.5
        ]
      },
      "type": "Feature",
      "properties": {
        "hierarchy": [
          "tgn:2708725",
          "tgn:1000001",
          "tgn:7012149",
          "tgn:2000367",
          "tgn:7007248",
          "tgn:7029392"
        ],
        "placetype": [
          "aat:300006191"
        ],
        "id": 2708725,
        "name:xx": "Sylvan Lake"
      }
    },
    {
      "geometry": {
        "type": "Point",
        "coordinates": [
          -88.0333,
          42.2333
        ]
      },
      "type": "Feature",
      "properties": {
        "hierarchy": [
          "tgn:2708726",
          "tgn:1000001",
          "tgn:7012149",
          "tgn:7013855",
          "tgn:7007251",
          "tgn:7029392"
        ],
        "placetype": [
          "aat:300008680"
        ],
        "id": 2708726,
        "name:xx": "Sylvan Lake"
      }
    },
    {
      "geometry": {
        "type": "Point",
        "coordinates": [
          -95.25,
          43.35
        ]
      },
      "type": "Feature",
      "properties": {
        "hierarchy": [
          "tgn:2708727",
          "tgn:1000001",
          "tgn:2000590",
          "tgn:7012149",
          "tgn:7007253",
          "tgn:7029392"
        ],
        "placetype": [
          "aat:300008680"
        ],
        "id": 2708727,
        "name:xx": "Sylvan Lake"
      }
    },
    {
      "geometry": {
        "type": "Point",
        "coordinates": [
          -71.0167,
          42.15
        ]
      },
      "type": "Feature",
      "properties": {
        "hierarchy": [
          "tgn:2708728",
          "tgn:1000001",
          "tgn:1002724",
          "tgn:7012149",
          "tgn:7007517",
          "tgn:7029392"
        ],
        "placetype": [
          "aat:300008680"
        ],
        "id": 2708728,
        "name:xx": "Sylvan Lake"
      }
    },
    {
      "geometry": {
        "type": "Point",
        "coordinates": [
          -85.7833,
          43.45
        ]
      },
      "type": "Feature",
      "properties": {
        "hierarchy": [
          "tgn:2708729",
          "tgn:1000001",
          "tgn:7012149",
          "tgn:2000983",
          "tgn:7007520",
          "tgn:7029392"
        ],
        "placetype": [
          "aat:300008680"
        ],
        "id": 2708729,
        "name:xx": "Sylvan Lake"
      }
    }
  ]
}
