{
  "geometry": {
    "type": "Point",
    "coordinates": [
      10.6167,
      47.4833
    ]
  },
  "type": "Feature",
  "properties": {
    "hierarchy": [
      "tgn:1025875",
      "tgn:7003029",
      "tgn:1000003",
      "tgn:1000062",
      "tgn:7029392"
    ],
    "placetype": [
      "aat:300008347"
    ],
    "id": 1025875,
    "name:xx": "Nesselwängle"
  }
}
