{
  "geometry": {
    "type": "Point",
    "coordinates": [
      -76.95,
      43.1667
    ]
  },
  "type": "Feature",
  "properties": {
    "hierarchy": [
      "tgn:2717083",
      "tgn:1000001",
      "tgn:7012149",
      "tgn:7014600",
      "tgn:7007568",
      "tgn:7029392"
    ],
    "placetype": [
      "aat:300008706"
    ],
    "id": 2717083,
    "name:xx": "Third Creek"
  }
}
