{
  "type": "FeatureCollection",
  "features": [
    {
      "geometry": {
        "type": "Point",
        "coordinates": [
          -156.55,
          20.9
        ]
      },
      "type": "Feature",
      "properties": {
        "hierarchy": [
          "tgn:2432250",
          "tgn:1002648",
          "tgn:1000001",
          "tgn:7019158",
          "tgn:7012149",
          "tgn:7007249",
          "tgn:7029392"
        ],
        "placetype": [
          "aat:300008798"
        ],
        "id": 2432250,
        "name:xx": "Keahialoa"
      }
    },
    {
      "geometry": {
        "type": "Point",
        "coordinates": [
          -156.6,
          20.9667
        ]
      },
      "type": "Feature",
      "properties": {
        "hierarchy": [
          "tgn:2432251",
          "tgn:1002648",
          "tgn:1000001",
          "tgn:7019158",
          "tgn:7012149",
          "tgn:7007249",
          "tgn:7029392"
        ],
        "placetype": [
          "aat:300008798"
        ],
        "id": 2432251,
        "name:xx": "Keahikano"
      }
    },
    {
      "geometry": {
        "type": "Point",
        "coordinates": [
          -156.3833,
          20.85
        ]
      },
      "type": "Feature",
      "properties": {
        "hierarchy": [
          "tgn:2432254",
          "tgn:1002648",
          "tgn:1000001",
          "tgn:7019158",
          "tgn:7012149",
          "tgn:7007249",
          "tgn:7029392"
        ],
        "placetype": [
          "aat:300008347"
        ],
        "id": 2432254,
        "name:xx": "Keahua"
      }
    },
    {
      "geometry": {
        "type": "Point",
        "coordinates": [
          -159.4333,
          22.1167
        ]
      },
      "type": "Feature",
      "properties": {
        "hierarchy": [
          "tgn:2432255",
          "tgn:1007657",
          "tgn:1002534",
          "tgn:1000001",
          "tgn:7012149",
          "tgn:7007249",
          "tgn:7029392"
        ],
        "placetype": [
          "aat:300008798"
        ],
        "id": 2432255,
        "name:xx": "Keahua"
      }
    },
    {
      "geometry": {
        "type": "Point",
        "coordinates": [
          -159.4333,
          22.1
        ]
      },
      "type": "Feature",
      "properties": {
        "hierarchy": [
          "tgn:2432257",
          "tgn:1007657",
          "tgn:1002534",
          "tgn:1000001",
          "tgn:7012149",
          "tgn:7007249",
          "tgn:7029392"
        ],
        "placetype": [
          "aat:300008699"
        ],
        "id": 2432257,
        "name:xx": "Keahua Stream"
      }
    },
    {
      "geometry": {
        "type": "Point",
        "coordinates": [
          -156.2667,
          20.7167
        ]
      },
      "type": "Feature",
      "properties": {
        "hierarchy": [
          "tgn:2432258",
          "tgn:1002648",
          "tgn:1000001",
          "tgn:7019158",
          "tgn:7012149",
          "tgn:7007249",
          "tgn:7029392"
        ],
        "placetype": [
          "aat:300008761"
        ],
        "id": 2432258,
        "name:xx": "Keahuaiwi Gulch"
      }
    },
    {
      "geometry": {
        "type": "Point",
        "coordinates": [
          -156.7667,
          21.1333
        ]
      },
      "type": "Feature",
      "properties": {
        "hierarchy": [
          "tgn:2432259",
          "tgn:1002648",
          "tgn:1000001",
          "tgn:1008191",
          "tgn:7012149",
          "tgn:7007249",
          "tgn:7029392"
        ],
        "placetype": [
          "aat:300008798"
        ],
        "id": 2432259,
        "name:xx": "Keahuoku"
      }
    }
  ]
}
