{
  "geometry": {
    "type": "Point",
    "coordinates": [
      -78.3667,
      37.0833
    ]
  },
  "type": "Feature",
  "properties": {
    "hierarchy": [
      "tgn:2198983",
      "tgn:1000001",
      "tgn:7012149",
      "tgn:2002182",
      "tgn:7007919",
      "tgn:7029392"
    ],
    "placetype": [
      "aat:300008347"
    ],
    "id": 2198983,
    "name:xx": "Bruceville"
  }
}
