{
  "geometry": {
    "type": "Point",
    "coordinates": [
      -81.3167,
      35.2167
    ]
  },
  "type": "Feature",
  "properties": {
    "hierarchy": [
      "tgn:2269545",
      "tgn:1000001",
      "tgn:7012149",
      "tgn:7029392"
    ],
    "placetype": [
      "aat:300008706"
    ],
    "id": 2269545,
    "name:xx": "Crowders Creek"
  }
}
