{
  "geometry": {
    "type": "Point",
    "coordinates": [
      76.650045,
      30.104145
    ]
  },
  "type": "Feature",
  "properties": {
    "hierarchy": [
      "tgn:7584957",
      "tgn:1000004",
      "tgn:1001871",
      "tgn:7000198",
      "tgn:7029392"
    ],
    "placetype": [
      "aat:300008347"
    ],
    "name:en": "Thāndrān",
    "id": 7584957
  }
}
