{
  "geometry": {
    "type": "Point",
    "coordinates": [
      -91.8833,
      44.9333
    ]
  },
  "type": "Feature",
  "properties": {
    "hierarchy": [
      "tgn:2709884",
      "tgn:1000001",
      "tgn:2002319",
      "tgn:7012149",
      "tgn:7007922",
      "tgn:7029392"
    ],
    "placetype": [
      "aat:300006191"
    ],
    "id": 2709884,
    "name:xx": "Tainter Lake"
  }
}
