{
  "geometry": {
    "type": "Point",
    "coordinates": [
      39.9333,
      40.05
    ]
  },
  "type": "Feature",
  "properties": {
    "hierarchy": [
      "tgn:1109439",
      "tgn:1000004",
      "tgn:1000144",
      "tgn:7029392"
    ],
    "placetype": [
      "aat:300008795"
    ],
    "id": 1109439,
    "name:xx": "Otlukbe Dağları"
  }
}
