{
  "geometry": {
    "type": "Point",
    "coordinates": [
      -103.3833,
      43.95
    ]
  },
  "type": "Feature",
  "properties": {
    "hierarchy": [
      "tgn:2188910",
      "tgn:1000001",
      "tgn:7012149",
      "tgn:2001821",
      "tgn:7007713",
      "tgn:7029392"
    ],
    "placetype": [
      "aat:300008798"
    ],
    "id": 2188910,
    "name:xx": "Boulder Hill"
  }
}
