{
  "geometry": {
    "type": "Point",
    "coordinates": [
      -94.7333,
      39.8667
    ]
  },
  "type": "Feature",
  "properties": {
    "hierarchy": [
      "tgn:2550470",
      "tgn:1000001",
      "tgn:7012149",
      "tgn:7007523",
      "tgn:7029392"
    ],
    "placetype": [
      "aat:300055621"
    ],
    "id": 2550470,
    "name:xx": "Northwestern Loess Hills"
  }
}
