{
  "geometry": {
    "type": "Point",
    "coordinates": [
      -88.3667,
      42.75
    ]
  },
  "type": "Feature",
  "properties": {
    "hierarchy": [
      "tgn:2686752",
      "tgn:1000001",
      "tgn:7012149",
      "tgn:1002982",
      "tgn:7007922",
      "tgn:7029392"
    ],
    "placetype": [
      "aat:300008706"
    ],
    "id": 2686752,
    "name:xx": "Spring Creek"
  }
}
