{
  "geometry": {
    "type": "Point",
    "coordinates": [
      87.388181,
      22.155915
    ]
  },
  "type": "Feature",
  "properties": {
    "hierarchy": [
      "tgn:1075781",
      "tgn:1000004",
      "tgn:7000198",
      "tgn:1001977",
      "tgn:7029392"
    ],
    "placetype": [
      "aat:300008347"
    ],
    "name:en": "Kasba Nārāyangarh",
    "id": 1075781
  }
}
