{
  "type": "FeatureCollection",
  "features": [
    {
      "geometry": {
        "type": "Point",
        "coordinates": [
          172.783333,
          -41.316667
        ]
      },
      "type": "Feature",
      "properties": {
        "hierarchy": [
          "tgn:7504190",
          "tgn:1009227",
          "tgn:1000226",
          "tgn:7520095",
          "tgn:1000006",
          "tgn:7029392"
        ],
        "placetype": [
          "aat:300008699"
        ],
        "name:en": "Wangapeka River",
        "id": 7504190
      }
    },
    {
      "geometry": {
        "type": "Point",
        "coordinates": [
          172.65,
          -41.416667
        ]
      },
      "type": "Feature",
      "properties": {
        "hierarchy": [
          "tgn:7504191",
          "tgn:1009227",
          "tgn:1000226",
          "tgn:7520095",
          "tgn:1000006",
          "tgn:7029392"
        ],
        "placetype": [
          "aat:300008347"
        ],
        "name:en": "Wangapeka",
        "id": 7504191
      }
    },
    {
      "geometry": {
        "type": "Point",
        "coordinates": [
          175,
          -39.933333
        ]
      },
      "type": "Feature",
      "properties": {
        "hierarchy": [
          "tgn:7504193",
          "tgn:1008380",
          "tgn:7520093",
          "tgn:1000226",
          "tgn:1000006",
          "tgn:7029392"
        ],
        "placetype": [
          "aat:300008699"
        ],
        "name:en": "Wanganui River",
        "id": 7504193
      }
    },
    {
      "geometry": {
        "type": "Point",
        "coordinates": [
          170.5,
          -43.016667
        ]
      },
      "type": "Feature",
      "properties": {
        "hierarchy": [
          "tgn:7504195",
          "tgn:1009227",
          "tgn:1000226",
          "tgn:1000006",
          "tgn:7016850",
          "tgn:7029392"
        ],
        "placetype": [
          "aat:300008749"
        ],
        "name:en": "Wanganui Bluff",
        "id": 7504195
      }
    },
    {
      "geometry": {
        "type": "Point",
        "coordinates": [
          173.45,
          -41.216667
        ]
      },
      "type": "Feature",
      "properties": {
        "hierarchy": [
          "tgn:7504198",
          "tgn:1009227",
          "tgn:1000226",
          "tgn:7016729",
          "tgn:1000006",
          "tgn:7029392"
        ],
        "placetype": [
          "aat:300259572"
        ],
        "name:en": "Wangamoa Saddle",
        "id": 7504198
      }
    },
    {
      "geometry": {
        "type": "Point",
        "coordinates": [
          170,
          -46.25
        ]
      },
      "type": "Feature",
      "properties": {
        "hierarchy": [
          "tgn:7504199",
          "tgn:1009227",
          "tgn:1000226",
          "tgn:7018437",
          "tgn:1000006",
          "tgn:7029392"
        ],
        "placetype": [
          "aat:300008699"
        ],
        "name:en": "Wangaloa Creek",
        "id": 7504199
      }
    }
  ]
}
