{
  "type": "FeatureCollection",
  "features": [
    {
      "geometry": {
        "type": "Point",
        "coordinates": [
          -77.85,
          39.2
        ]
      },
      "type": "Feature",
      "properties": {
        "hierarchy": [
          "tgn:2119191",
          "tgn:1000001",
          "tgn:7012149",
          "tgn:2002269",
          "tgn:7013961",
          "tgn:7029392"
        ],
        "placetype": [
          "aat:300008347"
        ],
        "id": 2119191,
        "name:xx": "Meyerstown"
      }
    },
    {
      "geometry": {
        "type": "Point",
        "coordinates": [
          -81.4333,
          38.15
        ]
      },
      "type": "Feature",
      "properties": {
        "hierarchy": [
          "tgn:2119192",
          "tgn:1000001",
          "tgn:7012149",
          "tgn:2002270",
          "tgn:7013961",
          "tgn:7029392"
        ],
        "placetype": [
          "aat:300008347"
        ],
        "id": 2119192,
        "name:xx": "Miami"
      }
    },
    {
      "geometry": {
        "type": "Point",
        "coordinates": [
          -80.9,
          39.4833
        ]
      },
      "type": "Feature",
      "properties": {
        "hierarchy": [
          "tgn:2119193",
          "tgn:1000001",
          "tgn:7012149",
          "tgn:2002297",
          "tgn:7013961",
          "tgn:7029392"
        ],
        "placetype": [
          "aat:300008347"
        ],
        "id": 2119193,
        "name:xx": "Middlebourne"
      }
    },
    {
      "geometry": {
        "type": "Point",
        "coordinates": [
          -80.8,
          38.5833
        ]
      },
      "type": "Feature",
      "properties": {
        "hierarchy": [
          "tgn:2119195",
          "tgn:1000001",
          "tgn:2002256",
          "tgn:7012149",
          "tgn:7013961",
          "tgn:7029392"
        ],
        "placetype": [
          "aat:300008347",
          "aat:300387210"
        ],
        "id": 2119195,
        "name:xx": "Middle Run"
      }
    },
    {
      "geometry": {
        "type": "Point",
        "coordinates": [
          -82.1667,
          38.1667
        ]
      },
      "type": "Feature",
      "properties": {
        "hierarchy": [
          "tgn:2119197",
          "tgn:1000001",
          "tgn:7012149",
          "tgn:2002272",
          "tgn:7013961",
          "tgn:7029392"
        ],
        "placetype": [
          "aat:300008347"
        ],
        "id": 2119197,
        "name:xx": "Midkiff"
      }
    },
    {
      "geometry": {
        "type": "Point",
        "coordinates": [
          -79.8333,
          38.8833
        ]
      },
      "type": "Feature",
      "properties": {
        "hierarchy": [
          "tgn:2119198",
          "tgn:1000001",
          "tgn:7012149",
          "tgn:2002291",
          "tgn:7013961",
          "tgn:7029392"
        ],
        "placetype": [
          "aat:300008347"
        ],
        "id": 2119198,
        "name:xx": "Midland"
      }
    }
  ]
}
