{
  "geometry": {
    "type": "Point",
    "coordinates": [
      -115.3667,
      44.45
    ]
  },
  "type": "Feature",
  "properties": {
    "hierarchy": [
      "tgn:2714983",
      "tgn:1000001",
      "tgn:7012149",
      "tgn:2000494",
      "tgn:7007250",
      "tgn:7029392"
    ],
    "placetype": [
      "aat:300008706"
    ],
    "id": 2714983,
    "name:xx": "Tennessee Creek"
  }
}
