{
  "geometry": {
    "type": "Point",
    "coordinates": [
      -67.0667,
      44.9167
    ]
  },
  "type": "Feature",
  "properties": {
    "hierarchy": [
      "tgn:2449535",
      "tgn:1000001",
      "tgn:7012149",
      "tgn:7014589",
      "tgn:7007515",
      "tgn:7029392"
    ],
    "placetype": [
      "aat:300132316"
    ],
    "id": 2449535,
    "name:xx": "Lincoln Cove"
  }
}
