{
  "geometry": {
    "type": "Point",
    "coordinates": [
      -72.7333,
      41.9333
    ]
  },
  "type": "Feature",
  "properties": {
    "hierarchy": [
      "tgn:2640877",
      "tgn:1000001",
      "tgn:1002461",
      "tgn:7012149",
      "tgn:7007159",
      "tgn:7029392"
    ],
    "placetype": [
      "aat:300008699"
    ],
    "id": 2640877,
    "name:xx": "Sanborn Brook"
  }
}
