{
  "type": "FeatureCollection",
  "features": [
    {
      "geometry": {
        "type": "Point",
        "coordinates": [
          -116.1667,
          44.6
        ]
      },
      "type": "Feature",
      "properties": {
        "hierarchy": [
          "tgn:2348700",
          "tgn:1000001",
          "tgn:7012149",
          "tgn:2000494",
          "tgn:7007250",
          "tgn:7029392"
        ],
        "placetype": [
          "aat:300008706"
        ],
        "id": 2348700,
        "name:xx": "Gibson Creek"
      }
    },
    {
      "geometry": {
        "type": "Point",
        "coordinates": [
          -111.5167,
          43.4
        ]
      },
      "type": "Feature",
      "properties": {
        "hierarchy": [
          "tgn:2348701",
          "tgn:1000001",
          "tgn:2000461",
          "tgn:7012149",
          "tgn:7007250",
          "tgn:7029392"
        ],
        "placetype": [
          "aat:300008706"
        ],
        "id": 2348701,
        "name:xx": "Gibson Creek"
      }
    },
    {
      "geometry": {
        "type": "Point",
        "coordinates": [
          -100.0667,
          38.7333
        ]
      },
      "type": "Feature",
      "properties": {
        "hierarchy": [
          "tgn:2348702",
          "tgn:1000001",
          "tgn:7012149",
          "tgn:2000757",
          "tgn:7007254",
          "tgn:7029392"
        ],
        "placetype": [
          "aat:300008706"
        ],
        "id": 2348702,
        "name:xx": "Gibson Creek"
      }
    },
    {
      "geometry": {
        "type": "Point",
        "coordinates": [
          -88.3833,
          36.8167
        ]
      },
      "type": "Feature",
      "properties": {
        "hierarchy": [
          "tgn:2348703",
          "tgn:1000001",
          "tgn:7012149",
          "tgn:2000823",
          "tgn:7007255",
          "tgn:7029392"
        ],
        "placetype": [
          "aat:300008706"
        ],
        "id": 2348703,
        "name:xx": "Gibson Creek"
      }
    },
    {
      "geometry": {
        "type": "Point",
        "coordinates": [
          -82.85,
          37.3833
        ]
      },
      "type": "Feature",
      "properties": {
        "hierarchy": [
          "tgn:2348704",
          "tgn:1000001",
          "tgn:7012149",
          "tgn:2000805",
          "tgn:7007255",
          "tgn:7029392"
        ],
        "placetype": [
          "aat:300008706"
        ],
        "id": 2348704,
        "name:xx": "Gibson Creek"
      }
    },
    {
      "geometry": {
        "type": "Point",
        "coordinates": [
          -84.3167,
          38.7833
        ]
      },
      "type": "Feature",
      "properties": {
        "hierarchy": [
          "tgn:2348705",
          "tgn:1000001",
          "tgn:7012149",
          "tgn:1002778",
          "tgn:7007255",
          "tgn:7029392"
        ],
        "placetype": [
          "aat:300008706"
        ],
        "id": 2348705,
        "name:xx": "Gibson Creek"
      }
    },
    {
      "geometry": {
        "type": "Point",
        "coordinates": [
          -90.8833,
          38.2333
        ]
      },
      "type": "Feature",
      "properties": {
        "hierarchy": [
          "tgn:2348706",
          "tgn:1000001",
          "tgn:7012149",
          "tgn:1002384",
          "tgn:7007523",
          "tgn:7029392"
        ],
        "placetype": [
          "aat:300008706"
        ],
        "id": 2348706,
        "name:xx": "Gibson Creek"
      }
    },
    {
      "geometry": {
        "type": "Point",
        "coordinates": [
          -111.2167,
          45.7833
        ]
      },
      "type": "Feature",
      "properties": {
        "hierarchy": [
          "tgn:2348707",
          "tgn:1000001",
          "tgn:7012149",
          "tgn:2001275",
          "tgn:7007524",
          "tgn:7029392"
        ],
        "placetype": [
          "aat:300008706"
        ],
        "id": 2348707,
        "name:xx": "Gibson Creek"
      }
    },
    {
      "geometry": {
        "type": "Point",
        "coordinates": [
          -74.7833,
          39.3667
        ]
      },
      "type": "Feature",
      "properties": {
        "hierarchy": [
          "tgn:2348708",
          "tgn:1002157",
          "tgn:1000001",
          "tgn:7012149",
          "tgn:7007565",
          "tgn:7029392"
        ],
        "placetype": [
          "aat:300008706"
        ],
        "id": 2348708,
        "name:xx": "Gibson Creek"
      }
    },
    {
      "geometry": {
        "type": "Point",
        "coordinates": [
          -83.15,
          41.0667
        ]
      },
      "type": "Feature",
      "properties": {
        "hierarchy": [
          "tgn:2348709",
          "tgn:1000001",
          "tgn:7012149",
          "tgn:1002883",
          "tgn:7007706",
          "tgn:7029392"
        ],
        "placetype": [
          "aat:300008706"
        ],
        "id": 2348709,
        "name:xx": "Gibson Creek"
      }
    }
  ]
}
