{
  "geometry": {
    "type": "Point",
    "coordinates": [
      28.85,
      40.9667
    ]
  },
  "type": "Feature",
  "properties": {
    "hierarchy": [
      "tgn:1120779",
      "tgn:1001052",
      "tgn:1000004",
      "tgn:7018450",
      "tgn:1000144",
      "tgn:7029392"
    ],
    "placetype": [
      "aat:300008707"
    ],
    "id": 1120779,
    "name:xx": "Çavuşbaşı"
  }
}
