{
  "type": "FeatureCollection",
  "features": [
    {
      "geometry": {
        "type": "Point",
        "coordinates": [
          14.333333,
          51.05
        ]
      },
      "type": "Feature",
      "properties": {
        "hierarchy": [
          "tgn:7163390",
          "tgn:1000003",
          "tgn:7003685",
          "tgn:7000084",
          "tgn:7029392"
        ],
        "placetype": [
          "aat:300008777"
        ],
        "id": 7163390,
        "name:xx": "Hut-Berg"
      }
    },
    {
      "geometry": {
        "type": "Point",
        "coordinates": [
          14.75,
          51.016667
        ]
      },
      "type": "Feature",
      "properties": {
        "hierarchy": [
          "tgn:7163392",
          "tgn:1000003",
          "tgn:7003685",
          "tgn:7000084",
          "tgn:7029392"
        ],
        "placetype": [
          "aat:300008777"
        ],
        "id": 7163392,
        "name:xx": "Hut-Berg"
      }
    },
    {
      "geometry": {
        "type": "Point",
        "coordinates": [
          14.85,
          50.933333
        ]
      },
      "type": "Feature",
      "properties": {
        "hierarchy": [
          "tgn:7163395",
          "tgn:1000003",
          "tgn:7003685",
          "tgn:7000084",
          "tgn:7029392"
        ],
        "placetype": [
          "aat:300008777"
        ],
        "id": 7163395,
        "name:xx": "Hut-Berg"
      }
    },
    {
      "geometry": {
        "type": "Point",
        "coordinates": [
          13.4,
          50.75
        ]
      },
      "type": "Feature",
      "properties": {
        "hierarchy": [
          "tgn:7163396",
          "tgn:1000003",
          "tgn:7003685",
          "tgn:7000084",
          "tgn:7029392"
        ],
        "placetype": [
          "aat:300008777"
        ],
        "id": 7163396,
        "name:xx": "Hutberg"
      }
    },
    {
      "geometry": {
        "type": "Point",
        "coordinates": [
          11.216667,
          49.4
        ]
      },
      "type": "Feature",
      "properties": {
        "hierarchy": [
          "tgn:7163397",
          "tgn:7003669",
          "tgn:1000003",
          "tgn:7000084",
          "tgn:7029392"
        ],
        "placetype": [
          "aat:300008777"
        ],
        "id": 7163397,
        "name:xx": "Hutberg"
      }
    },
    {
      "geometry": {
        "type": "Point",
        "coordinates": [
          11.55,
          49.216667
        ]
      },
      "type": "Feature",
      "properties": {
        "hierarchy": [
          "tgn:7163398",
          "tgn:7003669",
          "tgn:1000003",
          "tgn:7000084",
          "tgn:7029392"
        ],
        "placetype": [
          "aat:300008777"
        ],
        "id": 7163398,
        "name:xx": "Hutberg"
      }
    },
    {
      "geometry": {
        "type": "Point",
        "coordinates": [
          7.883333,
          53.55
        ]
      },
      "type": "Feature",
      "properties": {
        "hierarchy": [
          "tgn:7163399",
          "tgn:1000003",
          "tgn:7003676",
          "tgn:7000084",
          "tgn:7029392"
        ],
        "placetype": [
          "aat:300000206"
        ],
        "id": 7163399,
        "name:xx": "Husumerfeld"
      }
    }
  ]
}
