{
  "geometry": {
    "type": "Point",
    "coordinates": [
      -83.2167,
      35.6167
    ]
  },
  "type": "Feature",
  "properties": {
    "hierarchy": [
      "tgn:2359958",
      "tgn:1000001",
      "tgn:7012149",
      "tgn:2001543",
      "tgn:7007709",
      "tgn:7029392"
    ],
    "placetype": [
      "aat:300008699"
    ],
    "id": 2359958,
    "name:xx": "Grass Branch"
  }
}
