{
  "geometry": {
    "type": "Point",
    "coordinates": [
      -108.85,
      46.7333
    ]
  },
  "type": "Feature",
  "properties": {
    "hierarchy": [
      "tgn:2171087",
      "tgn:1000001",
      "tgn:7012149",
      "tgn:2001292",
      "tgn:7007524",
      "tgn:7029392"
    ],
    "placetype": [
      "aat:300008697"
    ],
    "id": 2171087,
    "name:xx": "Big Spring"
  }
}
