{
  "geometry": {
    "type": "Point",
    "coordinates": [
      -99.6833,
      28.75
    ]
  },
  "type": "Feature",
  "properties": {
    "hierarchy": [
      "tgn:2725944",
      "tgn:1000001",
      "tgn:7012149",
      "tgn:2002100",
      "tgn:7007826",
      "tgn:7029392"
    ],
    "placetype": [
      "aat:300006191"
    ],
    "id": 2725944,
    "name:xx": "Tortuga Tank"
  }
}
