{
  "geometry": {
    "type": "Point",
    "coordinates": [
      102.45,
      18.9333
    ]
  },
  "type": "Feature",
  "properties": {
    "hierarchy": [
      "tgn:1082531",
      "tgn:1000004",
      "tgn:7000851",
      "tgn:1000125",
      "tgn:7029392"
    ],
    "placetype": [
      "aat:300008347"
    ],
    "id": 1082531,
    "name:xx": "Muang Vangviang"
  }
}
