{
  "geometry": {
    "type": "Point",
    "coordinates": [
      35.2833,
      10.2667
    ]
  },
  "type": "Feature",
  "properties": {
    "hierarchy": [
      "tgn:1089831",
      "tgn:7001242",
      "tgn:1001266",
      "tgn:7000489",
      "tgn:7029392"
    ],
    "placetype": [
      "aat:300008347"
    ],
    "id": 1089831,
    "name:xx": "Guba"
  }
}
