{
  "type": "FeatureCollection",
  "features": [
    {
      "geometry": {
        "type": "Point",
        "coordinates": [
          -96.5333,
          32
        ]
      },
      "type": "Feature",
      "properties": {
        "hierarchy": [
          "tgn:2103432",
          "tgn:1000001",
          "tgn:7012149",
          "tgn:1002709",
          "tgn:7007826",
          "tgn:7029392"
        ],
        "placetype": [
          "aat:300008347"
        ],
        "id": 2103432,
        "name:xx": "Corbet"
      }
    },
    {
      "geometry": {
        "type": "Point",
        "coordinates": [
          -98.2333,
          29.6333
        ]
      },
      "type": "Feature",
      "properties": {
        "hierarchy": [
          "tgn:2103433",
          "tgn:1000001",
          "tgn:7012149",
          "tgn:2001961",
          "tgn:7007826",
          "tgn:7029392"
        ],
        "placetype": [
          "aat:300387016"
        ],
        "id": 2103433,
        "name:xx": "Corbyn"
      }
    },
    {
      "geometry": {
        "type": "Point",
        "coordinates": [
          -96.6167,
          29.1333
        ]
      },
      "type": "Feature",
      "properties": {
        "hierarchy": [
          "tgn:2103434",
          "tgn:1000001",
          "tgn:7012149",
          "tgn:1002510",
          "tgn:7007826",
          "tgn:7029392"
        ],
        "placetype": [
          "aat:300008347",
          "aat:300387210"
        ],
        "id": 2103434,
        "name:xx": "Cordele"
      }
    },
    {
      "geometry": {
        "type": "Point",
        "coordinates": [
          -99.8667,
          32.85
        ]
      },
      "type": "Feature",
      "properties": {
        "hierarchy": [
          "tgn:2103436",
          "tgn:1000001",
          "tgn:7012149",
          "tgn:2002014",
          "tgn:7007826",
          "tgn:7029392"
        ],
        "placetype": [
          "aat:300008347",
          "aat:300387210"
        ],
        "id": 2103436,
        "name:xx": "Corinth"
      }
    },
    {
      "geometry": {
        "type": "Point",
        "coordinates": [
          -96,
          31.3667
        ]
      },
      "type": "Feature",
      "properties": {
        "hierarchy": [
          "tgn:2103439",
          "tgn:1000001",
          "tgn:7012149",
          "tgn:1002590",
          "tgn:7007826",
          "tgn:7029392"
        ],
        "placetype": [
          "aat:300008347",
          "aat:300387210"
        ],
        "id": 2103439,
        "name:xx": "Corinth"
      }
    }
  ]
}
