{
  "geometry": {
    "type": "Point",
    "coordinates": [
      1.55,
      44.0833
    ]
  },
  "type": "Feature",
  "properties": {
    "hierarchy": [
      "tgn:4001539",
      "tgn:1000003",
      "tgn:7002889",
      "tgn:1000070",
      "tgn:7029392"
    ],
    "placetype": [
      "aat:300008347"
    ],
    "id": 4001539,
    "name:xx": "Bioule"
  }
}
