{
  "geometry": {
    "type": "Point",
    "coordinates": [
      -80.3833,
      39.4667
    ]
  },
  "type": "Feature",
  "properties": {
    "hierarchy": [
      "tgn:2264443",
      "tgn:1000001",
      "tgn:7012149",
      "tgn:2002275",
      "tgn:7013961",
      "tgn:7029392"
    ],
    "placetype": [
      "aat:300008699"
    ],
    "id": 2264443,
    "name:xx": "Crabapple Run"
  }
}
