{
  "geometry": {
    "type": "Point",
    "coordinates": [
      -71.2167,
      -13.7833
    ]
  },
  "type": "Feature",
  "properties": {
    "hierarchy": [
      "tgn:1103800",
      "tgn:1000584",
      "tgn:1000002",
      "tgn:1000056",
      "tgn:7029392"
    ],
    "placetype": [
      "aat:300008795"
    ],
    "id": 1103800,
    "name:xx": "Auzangate, Nevado"
  }
}
