{
  "geometry": {
    "type": "Point",
    "coordinates": [
      13.3333,
      47.0333
    ]
  },
  "type": "Feature",
  "properties": {
    "hierarchy": [
      "tgn:1107306",
      "tgn:7003024",
      "tgn:1000003",
      "tgn:1000062",
      "tgn:7029392"
    ],
    "placetype": [
      "aat:300008798"
    ],
    "id": 1107306,
    "name:xx": "Hochalm  Spitze"
  }
}
