{
  "geometry": {
    "type": "Point",
    "coordinates": [
      26.076131,
      31.476512
    ]
  },
  "type": "Feature",
  "properties": {
    "hierarchy": [
      "tgn:7540089",
      "tgn:7001242",
      "tgn:7016833",
      "tgn:1001418",
      "tgn:7029392"
    ],
    "placetype": [
      "aat:300006207"
    ],
    "name:en": "Sāniyat al Qaţīfah",
    "id": 7540089
  }
}
