{
  "geometry": {
    "type": "Point",
    "coordinates": [
      -93.4167,
      45.1667
    ]
  },
  "type": "Feature",
  "properties": {
    "hierarchy": [
      "tgn:2381819",
      "tgn:1000001",
      "tgn:2001025",
      "tgn:7012149",
      "tgn:7007521",
      "tgn:7029392"
    ],
    "placetype": [
      "aat:300008680"
    ],
    "id": 2381819,
    "name:xx": "Hayden Lake"
  }
}
