{
  "geometry": {
    "type": "Point",
    "coordinates": [
      -121.25,
      48.4333
    ]
  },
  "type": "Feature",
  "properties": {
    "hierarchy": [
      "tgn:2336304",
      "tgn:1000001",
      "tgn:7012149",
      "tgn:7014510",
      "tgn:7007920",
      "tgn:7029392"
    ],
    "placetype": [
      "aat:300008706"
    ],
    "id": 2336304,
    "name:xx": "Found Creek"
  }
}
