{
  "geometry": {
    "type": "Point",
    "coordinates": [
      -80.0833,
      38.55
    ]
  },
  "type": "Feature",
  "properties": {
    "hierarchy": [
      "tgn:2315061",
      "tgn:1000001",
      "tgn:7012149",
      "tgn:2002291",
      "tgn:7013961",
      "tgn:7029392"
    ],
    "placetype": [
      "aat:300008699"
    ],
    "id": 2315061,
    "name:xx": "Elkwater Fork"
  }
}
