{
  "geometry": {
    "type": "Point",
    "coordinates": [
      -112.1333,
      40.4333
    ]
  },
  "type": "Feature",
  "properties": {
    "hierarchy": [
      "tgn:2657166",
      "tgn:1000001",
      "tgn:7012149",
      "tgn:2002125",
      "tgn:7007827",
      "tgn:7029392"
    ],
    "placetype": [
      "aat:300266640"
    ],
    "id": 2657166,
    "name:xx": "Sheep Ridge"
  }
}
