{
  "geometry": {
    "type": "Point",
    "coordinates": [
      -121.7833,
      37.2833
    ]
  },
  "type": "Feature",
  "properties": {
    "hierarchy": [
      "tgn:2320381",
      "tgn:1000001",
      "tgn:7012149",
      "tgn:7007157",
      "tgn:7014475",
      "tgn:7029392"
    ],
    "placetype": [
      "aat:300006075"
    ],
    "id": 2320381,
    "name:xx": "Evergreen Canal"
  }
}
