{
  "geometry": {
    "type": "Point",
    "coordinates": [
      -75.7667,
      41.6167
    ]
  },
  "type": "Feature",
  "properties": {
    "hierarchy": [
      "tgn:2091337",
      "tgn:1000001",
      "tgn:7012149",
      "tgn:1003041",
      "tgn:7007710",
      "tgn:7029392"
    ],
    "placetype": [
      "aat:300008347"
    ],
    "id": 2091337,
    "name:xx": "Nicholson"
  }
}
