{
  "geometry": {
    "type": "Point",
    "coordinates": [
      -102.4833,
      42.2833
    ]
  },
  "type": "Feature",
  "properties": {
    "hierarchy": [
      "tgn:2128171",
      "tgn:1000001",
      "tgn:7012149",
      "tgn:2001396",
      "tgn:7007525",
      "tgn:7029392"
    ],
    "placetype": [
      "aat:300008680"
    ],
    "id": 2128171,
    "name:xx": "Albrecht Lake"
  }
}
