{
  "type": "FeatureCollection",
  "features": [
    {
      "geometry": {
        "type": "Point",
        "coordinates": [
          -70.933333,
          -28.983333
        ]
      },
      "type": "Feature",
      "properties": {
        "hierarchy": [
          "tgn:7318850",
          "tgn:1001630",
          "tgn:1000049",
          "tgn:1000002",
          "tgn:7029392"
        ],
        "placetype": [
          "aat:300008699"
        ],
        "id": 7318850,
        "name:xx": "Barrancones, Quebrada"
      }
    },
    {
      "geometry": {
        "type": "Point",
        "coordinates": [
          -71.333333,
          -29.4
        ]
      },
      "type": "Feature",
      "properties": {
        "hierarchy": [
          "tgn:7318851",
          "tgn:1001657",
          "tgn:1000049",
          "tgn:1000002",
          "tgn:7029392"
        ],
        "placetype": [
          "aat:300386846"
        ],
        "id": 7318851,
        "name:xx": "Barrancones, Punta"
      }
    },
    {
      "geometry": {
        "type": "Point",
        "coordinates": [
          -70.95,
          -33.333333
        ]
      },
      "type": "Feature",
      "properties": {
        "hierarchy": [
          "tgn:7318852",
          "tgn:1001708",
          "tgn:1000049",
          "tgn:1000002",
          "tgn:7029392"
        ],
        "placetype": [
          "aat:300008699"
        ],
        "id": 7318852,
        "name:xx": "Barrancones"
      }
    },
    {
      "geometry": {
        "type": "Point",
        "coordinates": [
          -72.783333,
          -50.716667
        ]
      },
      "type": "Feature",
      "properties": {
        "hierarchy": [
          "tgn:7318853",
          "tgn:1001702",
          "tgn:1000049",
          "tgn:1000002",
          "tgn:7029392"
        ],
        "placetype": [
          "aat:300008699"
        ],
        "id": 7318853,
        "name:xx": "Barranco, Río"
      }
    },
    {
      "geometry": {
        "type": "Point",
        "coordinates": [
          -71.966667,
          -41.55
        ]
      },
      "type": "Feature",
      "properties": {
        "hierarchy": [
          "tgn:7318854",
          "tgn:1001699",
          "tgn:1000049",
          "tgn:1000002",
          "tgn:7029392"
        ],
        "placetype": [
          "aat:300008699"
        ],
        "id": 7318854,
        "name:xx": "Barranco, Río"
      }
    },
    {
      "geometry": {
        "type": "Point",
        "coordinates": [
          -68.7,
          -20.616667
        ]
      },
      "type": "Feature",
      "properties": {
        "hierarchy": [
          "tgn:7318855",
          "tgn:7002464",
          "tgn:1000049",
          "tgn:1000002",
          "tgn:7029392"
        ],
        "placetype": [
          "aat:300266554",
          "aat:300008699"
        ],
        "id": 7318855,
        "name:xx": "Barranco, Quebrada"
      }
    },
    {
      "geometry": {
        "type": "Point",
        "coordinates": [
          -70.366667,
          -52.95
        ]
      },
      "type": "Feature",
      "properties": {
        "hierarchy": [
          "tgn:7318856",
          "tgn:1001702",
          "tgn:1000049",
          "tgn:1000002",
          "tgn:7029392"
        ],
        "placetype": [
          "aat:300386846"
        ],
        "id": 7318856,
        "name:xx": "Barranco, Punta"
      }
    },
    {
      "geometry": {
        "type": "Point",
        "coordinates": [
          -72.85,
          -52.616667
        ]
      },
      "type": "Feature",
      "properties": {
        "hierarchy": [
          "tgn:7318857",
          "tgn:1001702",
          "tgn:1000049",
          "tgn:1000002",
          "tgn:7029392"
        ],
        "placetype": [
          "aat:300386846"
        ],
        "id": 7318857,
        "name:xx": "Barranco, Punta"
      }
    },
    {
      "geometry": {
        "type": "Point",
        "coordinates": [
          -73.1,
          -52.116667
        ]
      },
      "type": "Feature",
      "properties": {
        "hierarchy": [
          "tgn:7318858",
          "tgn:1001702",
          "tgn:1000049",
          "tgn:1000002",
          "tgn:7029392"
        ],
        "placetype": [
          "aat:300386846"
        ],
        "id": 7318858,
        "name:xx": "Barranco, Punta"
      }
    },
    {
      "geometry": {
        "type": "Point",
        "coordinates": [
          -74.327778,
          -43.113056
        ]
      },
      "type": "Feature",
      "properties": {
        "hierarchy": [
          "tgn:7318859",
          "tgn:1001699",
          "tgn:1000049",
          "tgn:1000002",
          "tgn:7029392"
        ],
        "placetype": [
          "aat:300386846"
        ],
        "id": 7318859,
        "name:xx": "Barranco, Punta"
      }
    }
  ]
}
