{
  "geometry": {
    "type": "Point",
    "coordinates": [
      -85.05,
      35.85
    ]
  },
  "type": "Feature",
  "properties": {
    "hierarchy": [
      "tgn:2711303",
      "tgn:1000001",
      "tgn:7012149",
      "tgn:2001854",
      "tgn:7007825",
      "tgn:7029392"
    ],
    "placetype": [
      "aat:300006191"
    ],
    "id": 2711303,
    "name:xx": "Tansi, Lake"
  }
}
