{
  "geometry": {
    "type": "Point",
    "coordinates": [
      -90.0833,
      38.7667
    ]
  },
  "type": "Feature",
  "properties": {
    "hierarchy": [
      "tgn:2467881",
      "tgn:1000001",
      "tgn:7012149",
      "tgn:1002622",
      "tgn:7007251",
      "tgn:7029392"
    ],
    "placetype": [
      "aat:300008680"
    ],
    "id": 2467881,
    "name:xx": "Long Lake"
  }
}
