{
  "geometry": {
    "type": "Point",
    "coordinates": [
      -97.3167,
      39.1167
    ]
  },
  "type": "Feature",
  "properties": {
    "hierarchy": [
      "tgn:2528866",
      "tgn:1000001",
      "tgn:2000680",
      "tgn:7012149",
      "tgn:7007254",
      "tgn:7029392"
    ],
    "placetype": [
      "aat:300008706"
    ],
    "id": 2528866,
    "name:xx": "Mud Creek"
  }
}
