{
  "geometry": {
    "type": "Point",
    "coordinates": [
      -155.95,
      60.0667
    ]
  },
  "type": "Feature",
  "properties": {
    "hierarchy": [
      "tgn:2706731",
      "tgn:7006450",
      "tgn:1000001",
      "tgn:2000071",
      "tgn:7012149",
      "tgn:7029392"
    ],
    "placetype": [
      "aat:300008707"
    ],
    "id": 2706731,
    "name:xx": "Swan River"
  }
}
