{
  "geometry": {
    "type": "Point",
    "coordinates": [
      -91.35,
      39.15
    ]
  },
  "type": "Feature",
  "properties": {
    "hierarchy": [
      "tgn:2169411",
      "tgn:1000001",
      "tgn:7012149",
      "tgn:7007523",
      "tgn:7029392"
    ],
    "placetype": [
      "aat:300008706"
    ],
    "id": 2169411,
    "name:xx": "Big Lead Creek"
  }
}
