{
  "geometry": {
    "type": "Point",
    "coordinates": [
      -82.6333,
      38.7333
    ]
  },
  "type": "Feature",
  "properties": {
    "hierarchy": [
      "tgn:2078649",
      "tgn:1000001",
      "tgn:7012149",
      "tgn:2001615",
      "tgn:7007706",
      "tgn:7029392"
    ],
    "placetype": [
      "aat:300008347",
      "aat:300387210"
    ],
    "id": 2078649,
    "name:xx": "Buckhorn"
  }
}
