{
  "geometry": {
    "type": "Point",
    "coordinates": [
      -75.4333,
      42.1167
    ]
  },
  "type": "Feature",
  "properties": {
    "hierarchy": [
      "tgn:2168702",
      "tgn:1000001",
      "tgn:7012149",
      "tgn:7007568",
      "tgn:7029392"
    ],
    "placetype": [
      "aat:300008761"
    ],
    "id": 2168702,
    "name:xx": "Big Hollow"
  }
}
