{
  "geometry": {
    "type": "Point",
    "coordinates": [
      99.4167,
      26.4167
    ]
  },
  "type": "Feature",
  "properties": {
    "hierarchy": [
      "tgn:1069658",
      "tgn:1000004",
      "tgn:7018118",
      "tgn:1000111",
      "tgn:7029392"
    ],
    "placetype": [
      "aat:300008347"
    ],
    "id": 1069658,
    "name:xx": "Lanping"
  }
}
