{
  "geometry": {
    "type": "Point",
    "coordinates": [
      -67.8833,
      46.35
    ]
  },
  "type": "Feature",
  "properties": {
    "hierarchy": [
      "tgn:2701273",
      "tgn:2000919",
      "tgn:1000001",
      "tgn:7012149",
      "tgn:7007515",
      "tgn:7029392"
    ],
    "placetype": [
      "aat:300008798"
    ],
    "id": 2701273,
    "name:xx": "Sugar Loaf"
  }
}
