{
  "geometry": {
    "type": "Point",
    "coordinates": [
      74.37373,
      33.782169
    ]
  },
  "type": "Feature",
  "properties": {
    "hierarchy": [
      "tgn:7590598",
      "tgn:1000004",
      "tgn:7000198",
      "tgn:7000799",
      "tgn:7029392"
    ],
    "placetype": [
      "aat:300008347"
    ],
    "name:en": "Nainsukh",
    "id": 7590598
  }
}
