{
  "geometry": {
    "type": "Point",
    "coordinates": [
      7.85,
      47.5667
    ]
  },
  "type": "Feature",
  "properties": {
    "hierarchy": [
      "tgn:1064211",
      "tgn:7003739",
      "tgn:1000003",
      "tgn:7011731",
      "tgn:7029392"
    ],
    "placetype": [
      "aat:300008347"
    ],
    "id": 1064211,
    "name:xx": "Möhlin"
  }
}
