{
  "geometry": {
    "type": "Point",
    "coordinates": [
      -114.55,
      47.2667
    ]
  },
  "type": "Feature",
  "properties": {
    "hierarchy": [
      "tgn:2621489",
      "tgn:1000001",
      "tgn:7012149",
      "tgn:2001304",
      "tgn:7007524",
      "tgn:7029392"
    ],
    "placetype": [
      "aat:300008706"
    ],
    "id": 2621489,
    "name:xx": "Roaring Fork Seepay Creek"
  }
}
