{
  "geometry": {
    "type": "Point",
    "coordinates": [
      -81.3167,
      42.7167
    ]
  },
  "type": "Feature",
  "properties": {
    "hierarchy": [
      "tgn:1014766",
      "tgn:7005685",
      "tgn:1000001",
      "tgn:7013154",
      "tgn:7029392"
    ],
    "placetype": [
      "aat:300008347"
    ],
    "id": 1014766,
    "name:xx": "Fingal"
  }
}
