{
  "geometry": {
    "type": "Point",
    "coordinates": [
      -93.7167,
      42.9333
    ]
  },
  "type": "Feature",
  "properties": {
    "hierarchy": [
      "tgn:2762402",
      "tgn:1000001",
      "tgn:2000601",
      "tgn:7012149",
      "tgn:7007253",
      "tgn:7029392"
    ],
    "placetype": [
      "aat:300008680"
    ],
    "id": 2762402,
    "name:xx": "West Twin Lake"
  }
}
