{
  "type": "FeatureCollection",
  "features": [
    {
      "geometry": {
        "type": "Point",
        "coordinates": [
          -96.3,
          18.9
        ]
      },
      "type": "Feature",
      "properties": {
        "hierarchy": [
          "tgn:7441110",
          "tgn:1000001",
          "tgn:7005599",
          "tgn:7005560",
          "tgn:7029392"
        ],
        "placetype": [
          "aat:300008347"
        ],
        "id": 7441110,
        "name:xx": "Santa Lucía"
      }
    },
    {
      "geometry": {
        "type": "Point",
        "coordinates": [
          -99.816667,
          18.566667
        ]
      },
      "type": "Feature",
      "properties": {
        "hierarchy": [
          "tgn:7441111",
          "tgn:7005585",
          "tgn:1000001",
          "tgn:7005560",
          "tgn:7029392"
        ],
        "placetype": [
          "aat:300008347"
        ],
        "id": 7441111,
        "name:xx": "Santa Lucía"
      }
    },
    {
      "geometry": {
        "type": "Point",
        "coordinates": [
          -102.1,
          18
        ]
      },
      "type": "Feature",
      "properties": {
        "hierarchy": [
          "tgn:7441112",
          "tgn:7005585",
          "tgn:1000001",
          "tgn:7005560",
          "tgn:7029392"
        ],
        "placetype": [
          "aat:300008347"
        ],
        "id": 7441112,
        "name:xx": "Santa Lucía"
      }
    },
    {
      "geometry": {
        "type": "Point",
        "coordinates": [
          -93.383333,
          17.833333
        ]
      },
      "type": "Feature",
      "properties": {
        "hierarchy": [
          "tgn:7441113",
          "tgn:1000001",
          "tgn:7005596",
          "tgn:7005560",
          "tgn:7029392"
        ],
        "placetype": [
          "aat:300008347"
        ],
        "id": 7441113,
        "name:xx": "Santa Lucía"
      }
    },
    {
      "geometry": {
        "type": "Point",
        "coordinates": [
          -91.75,
          17.7
        ]
      },
      "type": "Feature",
      "properties": {
        "hierarchy": [
          "tgn:7441114",
          "tgn:7005580",
          "tgn:1000001",
          "tgn:7005560",
          "tgn:7029392"
        ],
        "placetype": [
          "aat:300008347"
        ],
        "id": 7441114,
        "name:xx": "Santa Lucía"
      }
    },
    {
      "geometry": {
        "type": "Point",
        "coordinates": [
          -96.6875,
          17.0625
        ]
      },
      "type": "Feature",
      "properties": {
        "hierarchy": [
          "tgn:7441115",
          "tgn:1000001",
          "tgn:7005591",
          "tgn:7005560",
          "tgn:7029392"
        ],
        "placetype": [
          "aat:300008347"
        ],
        "id": 7441115,
        "name:es": "Santa Lucía"
      }
    },
    {
      "geometry": {
        "type": "Point",
        "coordinates": [
          -93.633333,
          16.583333
        ]
      },
      "type": "Feature",
      "properties": {
        "hierarchy": [
          "tgn:7441116",
          "tgn:7005580",
          "tgn:1000001",
          "tgn:7005560",
          "tgn:7029392"
        ],
        "placetype": [
          "aat:300008347"
        ],
        "id": 7441116,
        "name:xx": "Santa Lucía"
      }
    },
    {
      "geometry": {
        "type": "Point",
        "coordinates": [
          -95.333333,
          16.166667
        ]
      },
      "type": "Feature",
      "properties": {
        "hierarchy": [
          "tgn:7441117",
          "tgn:1000001",
          "tgn:7005591",
          "tgn:7005560",
          "tgn:7029392"
        ],
        "placetype": [
          "aat:300008347"
        ],
        "id": 7441117,
        "name:xx": "Santa Lucía"
      }
    },
    {
      "geometry": {
        "type": "Point",
        "coordinates": [
          -92.766667,
          16.166667
        ]
      },
      "type": "Feature",
      "properties": {
        "hierarchy": [
          "tgn:7441118",
          "tgn:7005580",
          "tgn:1000001",
          "tgn:7005560",
          "tgn:7029392"
        ],
        "placetype": [
          "aat:300008347"
        ],
        "id": 7441118,
        "name:xx": "Santa Lucía"
      }
    },
    {
      "geometry": {
        "type": "Point",
        "coordinates": [
          -96.466667,
          15.933333
        ]
      },
      "type": "Feature",
      "properties": {
        "hierarchy": [
          "tgn:7441119",
          "tgn:1000001",
          "tgn:7005591",
          "tgn:7005560",
          "tgn:7029392"
        ],
        "placetype": [
          "aat:300008347"
        ],
        "id": 7441119,
        "name:xx": "Santa Lucía"
      }
    }
  ]
}
