{
  "type": "FeatureCollection",
  "features": [
    {
      "geometry": {
        "type": "Point",
        "coordinates": [
          -5.55,
          56.233333
        ]
      },
      "type": "Feature",
      "properties": {
        "hierarchy": [
          "tgn:7465222",
          "tgn:7019094",
          "tgn:7002444",
          "tgn:1000003",
          "tgn:7008591",
          "tgn:7029392"
        ],
        "placetype": [
          "aat:300132316"
        ],
        "name:en": "Asknish Bay",
        "id": 7465222
      }
    },
    {
      "geometry": {
        "type": "Point",
        "coordinates": [
          -2.75,
          54.6
        ]
      },
      "type": "Feature",
      "properties": {
        "hierarchy": [
          "tgn:7465225",
          "tgn:7002445",
          "tgn:1000003",
          "tgn:7008117",
          "tgn:7008591",
          "tgn:7029392"
        ],
        "placetype": [
          "aat:300008347"
        ],
        "name:en": "Askham",
        "id": 7465225
      }
    },
    {
      "geometry": {
        "type": "Point",
        "coordinates": [
          -7.416667,
          57.2
        ]
      },
      "type": "Feature",
      "properties": {
        "hierarchy": [
          "tgn:7465228",
          "tgn:7002444",
          "tgn:1000003",
          "tgn:7008094",
          "tgn:7008591",
          "tgn:7029392"
        ],
        "placetype": [
          "aat:300004792"
        ],
        "name:en": "Askernish House",
        "id": 7465228
      }
    }
  ]
}
