{
  "type": "FeatureCollection",
  "features": [
    {
      "geometry": {
        "type": "Point",
        "coordinates": [
          -118.0333,
          33.95
        ]
      },
      "type": "Feature",
      "properties": {
        "hierarchy": [
          "tgn:2014380",
          "tgn:1000001",
          "tgn:7012149",
          "tgn:7007157",
          "tgn:1002608",
          "tgn:7029392"
        ],
        "placetype": [
          "aat:300008347"
        ],
        "id": 2014380,
        "name:xx": "South Whittier"
      }
    },
    {
      "geometry": {
        "type": "Point",
        "coordinates": [
          -117.45,
          35.5333
        ]
      },
      "type": "Feature",
      "properties": {
        "hierarchy": [
          "tgn:2014387",
          "tgn:1000001",
          "tgn:7012149",
          "tgn:7007157",
          "tgn:1002857",
          "tgn:7029392"
        ],
        "placetype": [
          "aat:300387016"
        ],
        "id": 2014387,
        "name:xx": "Spangler"
      }
    },
    {
      "geometry": {
        "type": "Point",
        "coordinates": [
          -122.2167,
          38.5333
        ]
      },
      "type": "Feature",
      "properties": {
        "hierarchy": [
          "tgn:2014388",
          "tgn:1000001",
          "tgn:7012149",
          "tgn:7007157",
          "tgn:1002706",
          "tgn:7029392"
        ],
        "placetype": [
          "aat:300008347"
        ],
        "id": 2014388,
        "name:xx": "Spanish Flat"
      }
    },
    {
      "geometry": {
        "type": "Point",
        "coordinates": [
          -120.8,
          38.8167
        ]
      },
      "type": "Feature",
      "properties": {
        "hierarchy": [
          "tgn:2014389",
          "tgn:1000001",
          "tgn:7012149",
          "tgn:1002350",
          "tgn:7007157",
          "tgn:7029392"
        ],
        "placetype": [
          "aat:300008347",
          "aat:300387210"
        ],
        "id": 2014389,
        "name:xx": "Spanish Flat"
      }
    }
  ]
}
