{
  "geometry": {
    "type": "Point",
    "coordinates": [
      -123.8833,
      41.8833
    ]
  },
  "type": "Feature",
  "properties": {
    "hierarchy": [
      "tgn:2312284",
      "tgn:1000001",
      "tgn:7012149",
      "tgn:2000180",
      "tgn:7007157",
      "tgn:7029392"
    ],
    "placetype": [
      "aat:300008706"
    ],
    "id": 2312284,
    "name:xx": "Eighteenmile Creek"
  }
}
