{
  "geometry": {
    "type": "Point",
    "coordinates": [
      -118.65,
      45.8333
    ]
  },
  "type": "Feature",
  "properties": {
    "hierarchy": [
      "tgn:2084879",
      "tgn:1000001",
      "tgn:7012149",
      "tgn:2001720",
      "tgn:7007708",
      "tgn:7029392"
    ],
    "placetype": [
      "aat:300008347"
    ],
    "id": 2084879,
    "name:xx": "Helix"
  }
}
