{
  "geometry": {
    "type": "Point",
    "coordinates": [
      -100.1667,
      34.4167
    ]
  },
  "type": "Feature",
  "properties": {
    "hierarchy": [
      "tgn:2547972",
      "tgn:1000001",
      "tgn:7012149",
      "tgn:7007826",
      "tgn:7029392"
    ],
    "placetype": [
      "aat:300008706"
    ],
    "id": 2547972,
    "name:xx": "North Groesbeck Creek"
  }
}
