{
  "type": "FeatureCollection",
  "features": [
    {
      "geometry": {
        "type": "Point",
        "coordinates": [
          -76.8833,
          39.05
        ]
      },
      "type": "Feature",
      "properties": {
        "hierarchy": [
          "tgn:2048030",
          "tgn:1000001",
          "tgn:2124001",
          "tgn:7012149",
          "tgn:7007516",
          "tgn:7029392"
        ],
        "placetype": [
          "aat:300008347"
        ],
        "id": 2048030,
        "name:xx": "Muirkirk"
      }
    },
    {
      "geometry": {
        "type": "Point",
        "coordinates": [
          -77.5667,
          39.5
        ]
      },
      "type": "Feature",
      "properties": {
        "hierarchy": [
          "tgn:2048033",
          "tgn:1000001",
          "tgn:7016101",
          "tgn:7012149",
          "tgn:7007516",
          "tgn:7029392"
        ],
        "placetype": [
          "aat:300008347"
        ],
        "id": 2048033,
        "name:xx": "Myersville"
      }
    },
    {
      "geometry": {
        "type": "Point",
        "coordinates": [
          -77.2167,
          38.45
        ]
      },
      "type": "Feature",
      "properties": {
        "hierarchy": [
          "tgn:2048034",
          "tgn:7016100",
          "tgn:1000001",
          "tgn:7012149",
          "tgn:7007516",
          "tgn:7029392"
        ],
        "placetype": [
          "aat:300008347"
        ],
        "id": 2048034,
        "name:xx": "Nanjemoy"
      }
    },
    {
      "geometry": {
        "type": "Point",
        "coordinates": [
          -75.9,
          38.2667
        ]
      },
      "type": "Feature",
      "properties": {
        "hierarchy": [
          "tgn:2048035",
          "tgn:1000001",
          "tgn:1003023",
          "tgn:7012149",
          "tgn:7007516",
          "tgn:7029392"
        ],
        "placetype": [
          "aat:300008347"
        ],
        "id": 2048035,
        "name:xx": "Nanticoke"
      }
    },
    {
      "geometry": {
        "type": "Point",
        "coordinates": [
          -76.2333,
          38.9667
        ]
      },
      "type": "Feature",
      "properties": {
        "hierarchy": [
          "tgn:2048036",
          "tgn:1000001",
          "tgn:2124025",
          "tgn:7012149",
          "tgn:7007516",
          "tgn:7029392"
        ],
        "placetype": [
          "aat:300008347"
        ],
        "id": 2048036,
        "name:xx": "Narrows"
      }
    },
    {
      "geometry": {
        "type": "Point",
        "coordinates": [
          -77.0833,
          39
        ]
      },
      "type": "Feature",
      "properties": {
        "hierarchy": [
          "tgn:2048037",
          "tgn:1000001",
          "tgn:7016104",
          "tgn:7012149",
          "tgn:7007516",
          "tgn:7029392"
        ],
        "placetype": [
          "aat:300386994"
        ],
        "id": 2048037,
        "name:xx": "National Naval Medical Center"
      }
    }
  ]
}
