{
  "geometry": {
    "type": "Point",
    "coordinates": [
      -6.25,
      56.966667
    ]
  },
  "type": "Feature",
  "properties": {
    "hierarchy": [
      "tgn:7459525",
      "tgn:7002444",
      "tgn:1000003",
      "tgn:7008082",
      "tgn:7008591",
      "tgn:7029392"
    ],
    "placetype": [
      "aat:300011692"
    ],
    "name:en": "Mhàim-ard, Sgeir a'",
    "id": 7459525
  }
}
