{
  "geometry": {
    "type": "Point",
    "coordinates": [
      31.238395,
      30.01514
    ]
  },
  "type": "Feature",
  "properties": {
    "hierarchy": [
      "tgn:7529819",
      "tgn:7001242",
      "tgn:7016833",
      "tgn:1001091",
      "tgn:7029392"
    ],
    "placetype": [
      "aat:300007544"
    ],
    "id": 7529819,
    "name:xx": "Masjid Abū as Su'ūd al Jārḩī"
  }
}
