{
  "geometry": {
    "type": "Point",
    "coordinates": [
      55.8166,
      -21.1833
    ]
  },
  "type": "Feature",
  "properties": {
    "hierarchy": [
      "tgn:7032234",
      "tgn:7001680",
      "tgn:7001242",
      "tgn:1000184",
      "tgn:7029392"
    ],
    "placetype": [
      "aat:300008347"
    ],
    "name:fr": "Bois-Blanc",
    "id": 7032234
  }
}
