{
  "type": "FeatureCollection",
  "features": [
    {
      "geometry": {
        "type": "Point",
        "coordinates": [
          2.766667,
          42.116667
        ]
      },
      "type": "Feature",
      "properties": {
        "hierarchy": [
          "tgn:5003414",
          "tgn:7002820",
          "tgn:7030216",
          "tgn:1000003",
          "tgn:1000095",
          "tgn:7029392"
        ],
        "placetype": [
          "aat:300008347"
        ],
        "id": 5003414,
        "name:xx": "Porqueras"
      }
    },
    {
      "geometry": {
        "type": "Point",
        "coordinates": [
          -2.446194,
          43.08143
        ]
      },
      "type": "Feature",
      "properties": {
        "hierarchy": [
          "tgn:5003418",
          "tgn:7007780",
          "tgn:1000003",
          "tgn:7009604",
          "tgn:1000095",
          "tgn:7029392"
        ],
        "placetype": [
          "aat:300008347"
        ],
        "id": 5003418,
        "name:xx": "San Prudencio"
      }
    },
    {
      "geometry": {
        "type": "Point",
        "coordinates": [
          -0.464425,
          42.62588
        ]
      },
      "type": "Feature",
      "properties": {
        "hierarchy": [
          "tgn:5003419",
          "tgn:7002759",
          "tgn:7008909",
          "tgn:1000003",
          "tgn:1000095",
          "tgn:7029392"
        ],
        "placetype": [
          "aat:300008347"
        ],
        "id": 5003419,
        "name:xx": "Acín"
      }
    }
  ]
}
