{
  "type": "FeatureCollection",
  "features": [
    {
      "geometry": {
        "type": "Point",
        "coordinates": [
          -101.9667,
          32.4833
        ]
      },
      "type": "Feature",
      "properties": {
        "hierarchy": [
          "tgn:2108040",
          "tgn:1000001",
          "tgn:7012149",
          "tgn:2002036",
          "tgn:7007826",
          "tgn:7029392"
        ],
        "placetype": [
          "aat:300008347",
          "aat:300387210"
        ],
        "id": 2108040,
        "name:xx": "Three Leagues"
      }
    },
    {
      "geometry": {
        "type": "Point",
        "coordinates": [
          -98.1667,
          28.45
        ]
      },
      "type": "Feature",
      "properties": {
        "hierarchy": [
          "tgn:2108042",
          "tgn:1000001",
          "tgn:7012149",
          "tgn:2002029",
          "tgn:7007826",
          "tgn:7029392"
        ],
        "placetype": [
          "aat:300008347"
        ],
        "id": 2108042,
        "name:xx": "Three Rivers"
      }
    },
    {
      "geometry": {
        "type": "Point",
        "coordinates": [
          -99.1167,
          31.8
        ]
      },
      "type": "Feature",
      "properties": {
        "hierarchy": [
          "tgn:2108043",
          "tgn:1000001",
          "tgn:2001948",
          "tgn:7012149",
          "tgn:7007826",
          "tgn:7029392"
        ],
        "placetype": [
          "aat:300008347",
          "aat:300387210"
        ],
        "id": 2108043,
        "name:xx": "Thrifty"
      }
    },
    {
      "geometry": {
        "type": "Point",
        "coordinates": [
          -99.1667,
          33.1667
        ]
      },
      "type": "Feature",
      "properties": {
        "hierarchy": [
          "tgn:2108044",
          "tgn:1000001",
          "tgn:7012149",
          "tgn:2002084",
          "tgn:7007826",
          "tgn:7029392"
        ],
        "placetype": [
          "aat:300008347"
        ],
        "id": 2108044,
        "name:xx": "Throckmorton"
      }
    },
    {
      "geometry": {
        "type": "Point",
        "coordinates": [
          -98.4167,
          32.5
        ]
      },
      "type": "Feature",
      "properties": {
        "hierarchy": [
          "tgn:2108045",
          "tgn:1000001",
          "tgn:7012149",
          "tgn:2001982",
          "tgn:7007826",
          "tgn:7029392"
        ],
        "placetype": [
          "aat:300008347",
          "aat:300387210"
        ],
        "id": 2108045,
        "name:xx": "Thurber"
      }
    },
    {
      "geometry": {
        "type": "Point",
        "coordinates": [
          -96.1,
          33.2
        ]
      },
      "type": "Feature",
      "properties": {
        "hierarchy": [
          "tgn:2108046",
          "tgn:1000001",
          "tgn:7012149",
          "tgn:1002492",
          "tgn:7007826",
          "tgn:7029392"
        ],
        "placetype": [
          "aat:300008347",
          "aat:300387210"
        ],
        "id": 2108046,
        "name:xx": "Tidwell"
      }
    },
    {
      "geometry": {
        "type": "Point",
        "coordinates": [
          -96.65,
          31.0833
        ]
      },
      "type": "Feature",
      "properties": {
        "hierarchy": [
          "tgn:2108047",
          "tgn:1000001",
          "tgn:7012149",
          "tgn:1002830",
          "tgn:7007826",
          "tgn:7029392"
        ],
        "placetype": [
          "aat:300008347",
          "aat:300387210"
        ],
        "id": 2108047,
        "name:xx": "Tidwell Prairie"
      }
    },
    {
      "geometry": {
        "type": "Point",
        "coordinates": [
          -95.8,
          33.7
        ]
      },
      "type": "Feature",
      "properties": {
        "hierarchy": [
          "tgn:2108048",
          "tgn:1000001",
          "tgn:7012149",
          "tgn:2002024",
          "tgn:7007826",
          "tgn:7029392"
        ],
        "placetype": [
          "aat:300008347"
        ],
        "id": 2108048,
        "name:xx": "Tigertown"
      }
    }
  ]
}
