{
  "geometry": {
    "type": "Point",
    "coordinates": [
      78.404709,
      28.2639
    ]
  },
  "type": "Feature",
  "properties": {
    "hierarchy": [
      "tgn:7544971",
      "tgn:1000004",
      "tgn:7000198",
      "tgn:7016722",
      "tgn:7029392"
    ],
    "placetype": [
      "aat:300008347"
    ],
    "name:en": "Babrāla",
    "id": 7544971
  }
}
