{
  "geometry": {
    "type": "Point",
    "coordinates": [
      -82.9167,
      37.9833
    ]
  },
  "type": "Feature",
  "properties": {
    "hierarchy": [
      "tgn:2471996",
      "tgn:1000001",
      "tgn:7012149",
      "tgn:7007255",
      "tgn:7029392"
    ],
    "placetype": [
      "aat:300008699"
    ],
    "id": 2471996,
    "name:xx": "Lostlick Branch"
  }
}
