{
  "geometry": {
    "type": "Point",
    "coordinates": [
      74.963889,
      34.325
    ]
  },
  "type": "Feature",
  "properties": {
    "hierarchy": [
      "tgn:7586187",
      "tgn:1000004",
      "tgn:7000198",
      "tgn:7000799",
      "tgn:7029392"
    ],
    "placetype": [
      "aat:300008347"
    ],
    "name:en": "Gulābpathar",
    "id": 7586187
  }
}
