{
  "type": "FeatureCollection",
  "features": [
    {
      "geometry": {
        "type": "Point",
        "coordinates": [
          -103.116667,
          25.533333
        ]
      },
      "type": "Feature",
      "properties": {
        "hierarchy": [
          "tgn:7368580",
          "tgn:1001853",
          "tgn:1000001",
          "tgn:7005560",
          "tgn:7029392"
        ],
        "placetype": [
          "aat:300008347"
        ],
        "id": 7368580,
        "name:xx": "Hidalgo"
      }
    },
    {
      "geometry": {
        "type": "Point",
        "coordinates": [
          -97.133333,
          20.183333
        ]
      },
      "type": "Feature",
      "properties": {
        "hierarchy": [
          "tgn:7368583",
          "tgn:1000001",
          "tgn:7005599",
          "tgn:7005560",
          "tgn:7029392"
        ],
        "placetype": [
          "aat:300008347"
        ],
        "id": 7368583,
        "name:xx": "Hidalgo"
      }
    },
    {
      "geometry": {
        "type": "Point",
        "coordinates": [
          -96.866667,
          19.966667
        ]
      },
      "type": "Feature",
      "properties": {
        "hierarchy": [
          "tgn:7368584",
          "tgn:1000001",
          "tgn:7005599",
          "tgn:7005560",
          "tgn:7029392"
        ],
        "placetype": [
          "aat:300008347"
        ],
        "id": 7368584,
        "name:xx": "Hidalgo"
      }
    },
    {
      "geometry": {
        "type": "Point",
        "coordinates": [
          -90.883333,
          19.066667
        ]
      },
      "type": "Feature",
      "properties": {
        "hierarchy": [
          "tgn:7368585",
          "tgn:7005578",
          "tgn:1000001",
          "tgn:7005560",
          "tgn:7029392"
        ],
        "placetype": [
          "aat:300008347"
        ],
        "id": 7368585,
        "name:xx": "Hidalgo"
      }
    },
    {
      "geometry": {
        "type": "Point",
        "coordinates": [
          -91.05,
          18.533333
        ]
      },
      "type": "Feature",
      "properties": {
        "hierarchy": [
          "tgn:7368586",
          "tgn:7005578",
          "tgn:1000001",
          "tgn:7005560",
          "tgn:7029392"
        ],
        "placetype": [
          "aat:300008347"
        ],
        "id": 7368586,
        "name:xx": "Hidalgo"
      }
    },
    {
      "geometry": {
        "type": "Point",
        "coordinates": [
          -92.966667,
          18.383333
        ]
      },
      "type": "Feature",
      "properties": {
        "hierarchy": [
          "tgn:7368587",
          "tgn:1000001",
          "tgn:7005596",
          "tgn:7005560",
          "tgn:7029392"
        ],
        "placetype": [
          "aat:300008347"
        ],
        "id": 7368587,
        "name:xx": "Hidalgo"
      }
    },
    {
      "geometry": {
        "type": "Point",
        "coordinates": [
          -98.133333,
          17.8
        ]
      },
      "type": "Feature",
      "properties": {
        "hierarchy": [
          "tgn:7368588",
          "tgn:1000001",
          "tgn:7005591",
          "tgn:7005560",
          "tgn:7029392"
        ],
        "placetype": [
          "aat:300008347"
        ],
        "id": 7368588,
        "name:xx": "Hidalgo"
      }
    },
    {
      "geometry": {
        "type": "Point",
        "coordinates": [
          -93.566667,
          18.116667
        ]
      },
      "type": "Feature",
      "properties": {
        "hierarchy": [
          "tgn:7368589",
          "tgn:1000001",
          "tgn:7005596",
          "tgn:7005560",
          "tgn:7029392"
        ],
        "placetype": [
          "aat:300008347"
        ],
        "id": 7368589,
        "name:xx": "Guadalupe"
      }
    }
  ]
}
