{
  "geometry": {
    "type": "Point",
    "coordinates": [
      -122.5333,
      47.0667
    ]
  },
  "type": "Feature",
  "properties": {
    "hierarchy": [
      "tgn:2180984",
      "tgn:1000001",
      "tgn:7012149",
      "tgn:1002785",
      "tgn:7007920",
      "tgn:7029392"
    ],
    "placetype": [
      "aat:300132451"
    ],
    "id": 2180984,
    "name:xx": "Bloyd Woods"
  }
}
