{
  "type": "FeatureCollection",
  "features": [
    {
      "geometry": {
        "type": "Point",
        "coordinates": [
          -6.3,
          56.316667
        ]
      },
      "type": "Feature",
      "properties": {
        "hierarchy": [
          "tgn:7466200",
          "tgn:7019094",
          "tgn:7002444",
          "tgn:1000003",
          "tgn:7008591",
          "tgn:7029392"
        ],
        "placetype": [
          "aat:300008347"
        ],
        "name:en": "Ardfenaig",
        "id": 7466200
      }
    },
    {
      "geometry": {
        "type": "Point",
        "coordinates": [
          -7.666667,
          54.516667
        ]
      },
      "type": "Feature",
      "properties": {
        "hierarchy": [
          "tgn:7466201",
          "tgn:7002448",
          "tgn:7008700",
          "tgn:1000003",
          "tgn:7008591",
          "tgn:7029392"
        ],
        "placetype": [
          "aat:300008347"
        ],
        "name:en": "Ardess",
        "id": 7466201
      }
    },
    {
      "geometry": {
        "type": "Point",
        "coordinates": [
          -3.366667,
          57.45
        ]
      },
      "type": "Feature",
      "properties": {
        "hierarchy": [
          "tgn:7466203",
          "tgn:7002444",
          "tgn:1000003",
          "tgn:5000451",
          "tgn:7008591",
          "tgn:7029392"
        ],
        "placetype": [
          "aat:300008699"
        ],
        "name:en": "Arder, Allt",
        "id": 7466203
      }
    },
    {
      "geometry": {
        "type": "Point",
        "coordinates": [
          -4.166667,
          56.483333
        ]
      },
      "type": "Feature",
      "properties": {
        "hierarchy": [
          "tgn:7466204",
          "tgn:7002444",
          "tgn:1000003",
          "tgn:5000460",
          "tgn:7008591",
          "tgn:7029392"
        ],
        "placetype": [
          "aat:300008347"
        ],
        "name:en": "Ardeonaig",
        "id": 7466204
      }
    },
    {
      "geometry": {
        "type": "Point",
        "coordinates": [
          -5.616667,
          56.3
        ]
      },
      "type": "Feature",
      "properties": {
        "hierarchy": [
          "tgn:7466206",
          "tgn:7019094",
          "tgn:7002444",
          "tgn:1000003",
          "tgn:7008591",
          "tgn:7029392"
        ],
        "placetype": [
          "aat:300387502"
        ],
        "name:en": "Ardencaple House",
        "id": 7466206
      }
    },
    {
      "geometry": {
        "type": "Point",
        "coordinates": [
          -5.6,
          56.316667
        ]
      },
      "type": "Feature",
      "properties": {
        "hierarchy": [
          "tgn:7466207",
          "tgn:7019094",
          "tgn:7002444",
          "tgn:1000003",
          "tgn:7008591",
          "tgn:7029392"
        ],
        "placetype": [
          "aat:300132316"
        ],
        "name:en": "Ardencaple Bay",
        "id": 7466207
      }
    },
    {
      "geometry": {
        "type": "Point",
        "coordinates": [
          -4.75,
          55.633333
        ]
      },
      "type": "Feature",
      "properties": {
        "hierarchy": [
          "tgn:7466209",
          "tgn:7002444",
          "tgn:1000003",
          "tgn:7019091",
          "tgn:7008591",
          "tgn:7029392"
        ],
        "placetype": [
          "aat:300008347"
        ],
        "name:en": "Ardeer Square",
        "id": 7466209
      }
    }
  ]
}
