{
  "geometry": {
    "type": "Point",
    "coordinates": [
      -142.4667,
      63.3667
    ]
  },
  "type": "Feature",
  "properties": {
    "hierarchy": [
      "tgn:2593471",
      "tgn:7006450",
      "tgn:1000001",
      "tgn:7012149",
      "tgn:2000085",
      "tgn:7029392"
    ],
    "placetype": [
      "aat:300008706"
    ],
    "id": 2593471,
    "name:xx": "Porcupine Creek"
  }
}
