{
  "geometry": {
    "type": "Point",
    "coordinates": [
      -84.4167,
      36.55
    ]
  },
  "type": "Feature",
  "properties": {
    "hierarchy": [
      "tgn:2098508",
      "tgn:1000001",
      "tgn:7012149",
      "tgn:2001912",
      "tgn:7007825",
      "tgn:7029392"
    ],
    "placetype": [
      "aat:300008347",
      "aat:300387210"
    ],
    "id": 2098508,
    "name:xx": "Clay Hill"
  }
}
