{
  "geometry": {
    "type": "Point",
    "coordinates": [
      -72.0667,
      21.9167
    ]
  },
  "type": "Feature",
  "properties": {
    "hierarchy": [
      "tgn:1019101",
      "tgn:1009905",
      "tgn:1008375",
      "tgn:1000001",
      "tgn:7004630",
      "tgn:7029392"
    ],
    "placetype": [
      "aat:300008347"
    ],
    "id": 1019101,
    "name:xx": "Kew"
  }
}
