{
  "geometry": {
    "type": "Point",
    "coordinates": [
      -108.55,
      38.1333
    ]
  },
  "type": "Feature",
  "properties": {
    "hierarchy": [
      "tgn:2192157",
      "tgn:1000001",
      "tgn:7012149",
      "tgn:7007158",
      "tgn:7029392"
    ],
    "placetype": [
      "aat:300008761"
    ],
    "id": 2192157,
    "name:xx": "Bramiers Draw"
  }
}
