{
  "geometry": {
    "type": "Point",
    "coordinates": [
      -79.0167,
      39.3667
    ]
  },
  "type": "Feature",
  "properties": {
    "hierarchy": [
      "tgn:2119371",
      "tgn:1000001",
      "tgn:7012149",
      "tgn:2002279",
      "tgn:7013961",
      "tgn:7029392"
    ],
    "placetype": [
      "aat:300008347"
    ],
    "id": 2119371,
    "name:xx": "New Creek"
  }
}
