{
  "geometry": {
    "type": "Point",
    "coordinates": [
      -108.85,
      33.3167
    ]
  },
  "type": "Feature",
  "properties": {
    "hierarchy": [
      "tgn:2474794",
      "tgn:1000001",
      "tgn:2001429",
      "tgn:7012149",
      "tgn:7007566",
      "tgn:7029392"
    ],
    "placetype": [
      "aat:300006191"
    ],
    "id": 2474794,
    "name:xx": "Lower Tank"
  }
}
