{
  "type": "FeatureCollection",
  "features": [
    {
      "geometry": {
        "type": "Point",
        "coordinates": [
          -107.3833,
          43.6833
        ]
      },
      "type": "Feature",
      "properties": {
        "hierarchy": [
          "tgn:2630500",
          "tgn:1000001",
          "tgn:7012149",
          "tgn:2002386",
          "tgn:7007923",
          "tgn:7029392"
        ],
        "placetype": [
          "aat:300006191"
        ],
        "id": 2630500,
        "name:xx": "Round Corral Reservoir"
      }
    },
    {
      "geometry": {
        "type": "Point",
        "coordinates": [
          -107.4333,
          38.4167
        ]
      },
      "type": "Feature",
      "properties": {
        "hierarchy": [
          "tgn:2630501",
          "tgn:1000001",
          "tgn:7012149",
          "tgn:2000234",
          "tgn:7007158",
          "tgn:7029392"
        ],
        "placetype": [
          "aat:300008697"
        ],
        "id": 2630501,
        "name:xx": "Round Corral Spring"
      }
    },
    {
      "geometry": {
        "type": "Point",
        "coordinates": [
          -176.0167,
          51.8167
        ]
      },
      "type": "Feature",
      "properties": {
        "hierarchy": [
          "tgn:2630503",
          "tgn:7030516",
          "tgn:7006450",
          "tgn:1000001",
          "tgn:7012149",
          "tgn:7029392"
        ],
        "placetype": [
          "aat:300132316"
        ],
        "id": 2630503,
        "name:xx": "Round Cove"
      }
    },
    {
      "geometry": {
        "type": "Point",
        "coordinates": [
          -67.5,
          44.6333
        ]
      },
      "type": "Feature",
      "properties": {
        "hierarchy": [
          "tgn:2630504",
          "tgn:1000001",
          "tgn:7012149",
          "tgn:7014589",
          "tgn:7007515",
          "tgn:7029392"
        ],
        "placetype": [
          "aat:300132316"
        ],
        "id": 2630504,
        "name:xx": "Round Cove"
      }
    },
    {
      "geometry": {
        "type": "Point",
        "coordinates": [
          -69.7167,
          43.85
        ]
      },
      "type": "Feature",
      "properties": {
        "hierarchy": [
          "tgn:2630505",
          "tgn:1000001",
          "tgn:2000925",
          "tgn:7012149",
          "tgn:7007515",
          "tgn:7029392"
        ],
        "placetype": [
          "aat:300132316"
        ],
        "id": 2630505,
        "name:xx": "Round Cove"
      }
    },
    {
      "geometry": {
        "type": "Point",
        "coordinates": [
          -83.8833,
          35.1333
        ]
      },
      "type": "Feature",
      "properties": {
        "hierarchy": [
          "tgn:2630506",
          "tgn:1000001",
          "tgn:2001481",
          "tgn:7012149",
          "tgn:7007709",
          "tgn:7029392"
        ],
        "placetype": [
          "aat:300008761"
        ],
        "id": 2630506,
        "name:xx": "Round Cove"
      }
    },
    {
      "geometry": {
        "type": "Point",
        "coordinates": [
          -82.6167,
          36.0333
        ]
      },
      "type": "Feature",
      "properties": {
        "hierarchy": [
          "tgn:2630507",
          "tgn:1000001",
          "tgn:7012149",
          "tgn:2001516",
          "tgn:7007709",
          "tgn:7029392"
        ],
        "placetype": [
          "aat:300008761"
        ],
        "id": 2630507,
        "name:xx": "Round Cove"
      }
    },
    {
      "geometry": {
        "type": "Point",
        "coordinates": [
          -85.35,
          36.0667
        ]
      },
      "type": "Feature",
      "properties": {
        "hierarchy": [
          "tgn:2630508",
          "tgn:1000001",
          "tgn:7012149",
          "tgn:2001907",
          "tgn:7007825",
          "tgn:7029392"
        ],
        "placetype": [
          "aat:300386845"
        ],
        "id": 2630508,
        "name:xx": "Round Cove"
      }
    }
  ]
}
