{
  "geometry": {
    "type": "Point",
    "coordinates": [
      -85.4833,
      44.0833
    ]
  },
  "type": "Feature",
  "properties": {
    "hierarchy": [
      "tgn:2286604",
      "tgn:1000001",
      "tgn:7012149",
      "tgn:2000987",
      "tgn:7007520",
      "tgn:7029392"
    ],
    "placetype": [
      "aat:300008680"
    ],
    "id": 2286604,
    "name:xx": "Diamond Lake"
  }
}
