{
  "geometry": {
    "type": "Point",
    "coordinates": [
      -3.7333,
      40.45
    ]
  },
  "type": "Feature",
  "properties": {
    "hierarchy": [
      "tgn:1004294",
      "tgn:7010420",
      "tgn:1000003",
      "tgn:7002795",
      "tgn:1000095",
      "tgn:7010413",
      "tgn:7029392"
    ],
    "placetype": [
      "aat:300000745"
    ],
    "id": 1004294,
    "name:xx": "Ciudad Universitaria"
  }
}
