{
  "geometry": {
    "type": "Point",
    "coordinates": [
      29.590536,
      30.551411
    ]
  },
  "type": "Feature",
  "properties": {
    "hierarchy": [
      "tgn:7521621",
      "tgn:7001242",
      "tgn:7016833",
      "tgn:1001418",
      "tgn:7029392"
    ],
    "placetype": [
      "aat:300008777"
    ],
    "name:en": "Abū 'Īsá, 'Alam",
    "id": 7521621
  }
}
