{
  "geometry": {
    "type": "Point",
    "coordinates": [
      -92.0833,
      36.95
    ]
  },
  "type": "Feature",
  "properties": {
    "hierarchy": [
      "tgn:2625349",
      "tgn:1000001",
      "tgn:7012149",
      "tgn:2001196",
      "tgn:7007523",
      "tgn:7029392"
    ],
    "placetype": [
      "aat:300008761"
    ],
    "id": 2625349,
    "name:xx": "Rockhouse Hollow"
  }
}
