{
  "geometry": {
    "type": "Point",
    "coordinates": [
      -97.0333,
      32.0667
    ]
  },
  "type": "Feature",
  "properties": {
    "hierarchy": [
      "tgn:2573472",
      "tgn:1000001",
      "tgn:7012149",
      "tgn:1002478",
      "tgn:7007826",
      "tgn:7029392"
    ],
    "placetype": [
      "aat:300008706"
    ],
    "id": 2573472,
    "name:xx": "Pecan Creek"
  }
}
