{
  "geometry": {
    "type": "Point",
    "coordinates": [
      89.852618,
      26.268562
    ]
  },
  "type": "Feature",
  "properties": {
    "hierarchy": [
      "tgn:7566592",
      "tgn:1000004",
      "tgn:1001832",
      "tgn:7000198",
      "tgn:7029392"
    ],
    "placetype": [
      "aat:300008699"
    ],
    "name:en": "Tāmā Nadi",
    "id": 7566592
  }
}
