{
  "geometry": {
    "type": "Point",
    "coordinates": [
      -112.45,
      48.6333
    ]
  },
  "type": "Feature",
  "properties": {
    "hierarchy": [
      "tgn:2061375",
      "tgn:1000001",
      "tgn:7012149",
      "tgn:2001277",
      "tgn:7007524",
      "tgn:7029392"
    ],
    "placetype": [
      "aat:300387016"
    ],
    "id": 2061375,
    "name:xx": "Gunsight"
  }
}
