{
  "geometry": {
    "type": "Point",
    "coordinates": [
      -108.85,
      33.8167
    ]
  },
  "type": "Feature",
  "properties": {
    "hierarchy": [
      "tgn:2429546",
      "tgn:1000001",
      "tgn:2001429",
      "tgn:7012149",
      "tgn:7007566",
      "tgn:7029392"
    ],
    "placetype": [
      "aat:300266640"
    ],
    "id": 2429546,
    "name:xx": "Juniper Ridge"
  }
}
