{
  "geometry": {
    "type": "Point",
    "coordinates": [
      -114.5833,
      48.7667
    ]
  },
  "type": "Feature",
  "properties": {
    "hierarchy": [
      "tgn:2480174",
      "tgn:1000001",
      "tgn:7012149",
      "tgn:2001274",
      "tgn:7007524",
      "tgn:7029392"
    ],
    "placetype": [
      "aat:300008798"
    ],
    "id": 2480174,
    "name:xx": "Lake Mountain"
  }
}
