{
  "geometry": {
    "type": "Point",
    "coordinates": [
      96.9167,
      51.25
    ]
  },
  "type": "Feature",
  "properties": {
    "hierarchy": [
      "tgn:1121644",
      "tgn:1000004",
      "tgn:7002435",
      "tgn:7014829",
      "tgn:7029392"
    ],
    "placetype": [
      "aat:300008707"
    ],
    "id": 1121644,
    "name:xx": "Balyktyg Khem"
  }
}
