{
  "geometry": {
    "type": "Point",
    "coordinates": [
      135.0833,
      48.4167
    ]
  },
  "type": "Feature",
  "properties": {
    "hierarchy": [
      "tgn:7014478",
      "tgn:1000004",
      "tgn:7029392"
    ],
    "placetype": [
      "aat:300008707"
    ],
    "id": 7014478,
    "name:xx": "Ussuri"
  }
}
