{
  "geometry": {
    "type": "Point",
    "coordinates": [
      -99.1333,
      29.5833
    ]
  },
  "type": "Feature",
  "properties": {
    "hierarchy": [
      "tgn:2494441",
      "tgn:1000001",
      "tgn:7012149",
      "tgn:2002039",
      "tgn:7007826",
      "tgn:7029392"
    ],
    "placetype": [
      "aat:300008706"
    ],
    "id": 2494441,
    "name:xx": "Martin Creek"
  }
}
