{
  "geometry": {
    "type": "Point",
    "coordinates": [
      -80.7167,
      38.7333
    ]
  },
  "type": "Feature",
  "properties": {
    "hierarchy": [
      "tgn:2744000",
      "tgn:1000001",
      "tgn:2002256",
      "tgn:7012149",
      "tgn:7013961",
      "tgn:7029392"
    ],
    "placetype": [
      "aat:300008699"
    ],
    "id": 2744000,
    "name:xx": "Venison Fork"
  }
}
