{
  "type": "FeatureCollection",
  "features": [
    {
      "geometry": {
        "type": "Point",
        "coordinates": [
          7.4333,
          47.0667
        ]
      },
      "type": "Feature",
      "properties": {
        "hierarchy": [
          "tgn:4009110",
          "tgn:7003742",
          "tgn:1000003",
          "tgn:7011731",
          "tgn:7029392"
        ],
        "placetype": [
          "aat:300008347"
        ],
        "id": 4009110,
        "name:xx": "Rapperswil"
      }
    },
    {
      "geometry": {
        "type": "Point",
        "coordinates": [
          8.304,
          53.802
        ]
      },
      "type": "Feature",
      "properties": {
        "hierarchy": [
          "tgn:4009117",
          "tgn:7001198",
          "tgn:7003482",
          "tgn:1000003",
          "tgn:1000078",
          "tgn:7029392"
        ],
        "placetype": [
          "aat:300008347",
          "aat:300000810",
          "aat:300167671",
          "aat:300006891"
        ],
        "id": 4009117,
        "name:xx": "Rathcroghan"
      }
    },
    {
      "geometry": {
        "type": "Point",
        "coordinates": [
          -6.3,
          53.3
        ]
      },
      "type": "Feature",
      "properties": {
        "hierarchy": [
          "tgn:4009119",
          "tgn:7003487",
          "tgn:7001199",
          "tgn:1000003",
          "tgn:1000078",
          "tgn:7029392"
        ],
        "placetype": [
          "aat:300008347"
        ],
        "id": 4009119,
        "name:xx": "Rathfarnham"
      }
    }
  ]
}
