{
  "type": "FeatureCollection",
  "features": [
    {
      "geometry": {
        "type": "Point",
        "coordinates": [
          -72.2333,
          41.45
        ]
      },
      "type": "Feature",
      "properties": {
        "hierarchy": [
          "tgn:2723240",
          "tgn:1000001",
          "tgn:1002714",
          "tgn:7012149",
          "tgn:7007159",
          "tgn:7029392"
        ],
        "placetype": [
          "aat:300008761"
        ],
        "id": 2723240,
        "name:xx": "Toad Hollow"
      }
    },
    {
      "geometry": {
        "type": "Point",
        "coordinates": [
          -95.9,
          39.15
        ]
      },
      "type": "Feature",
      "properties": {
        "hierarchy": [
          "tgn:2723241",
          "tgn:1000001",
          "tgn:7012149",
          "tgn:2000748",
          "tgn:7007254",
          "tgn:7029392"
        ],
        "placetype": [
          "aat:300008761"
        ],
        "id": 2723241,
        "name:xx": "Toad Hollow"
      }
    },
    {
      "geometry": {
        "type": "Point",
        "coordinates": [
          -94.95,
          40.4167
        ]
      },
      "type": "Feature",
      "properties": {
        "hierarchy": [
          "tgn:2723242",
          "tgn:1000001",
          "tgn:7012149",
          "tgn:2001224",
          "tgn:7007523",
          "tgn:7029392"
        ],
        "placetype": [
          "aat:300008761"
        ],
        "id": 2723242,
        "name:xx": "Toad Hollow"
      }
    },
    {
      "geometry": {
        "type": "Point",
        "coordinates": [
          -78.8,
          42.2833
        ]
      },
      "type": "Feature",
      "properties": {
        "hierarchy": [
          "tgn:2723243",
          "tgn:1000001",
          "tgn:1002245",
          "tgn:7012149",
          "tgn:7007568",
          "tgn:7029392"
        ],
        "placetype": [
          "aat:300008761"
        ],
        "id": 2723243,
        "name:xx": "Toad Hollow"
      }
    },
    {
      "geometry": {
        "type": "Point",
        "coordinates": [
          -74.5,
          42.3167
        ]
      },
      "type": "Feature",
      "properties": {
        "hierarchy": [
          "tgn:2723244",
          "tgn:1000001",
          "tgn:1002328",
          "tgn:7012149",
          "tgn:7007568",
          "tgn:7029392"
        ],
        "placetype": [
          "aat:300008761"
        ],
        "id": 2723244,
        "name:xx": "Toad Hollow"
      }
    },
    {
      "geometry": {
        "type": "Point",
        "coordinates": [
          -82.95,
          39.2667
        ]
      },
      "type": "Feature",
      "properties": {
        "hierarchy": [
          "tgn:2723245",
          "tgn:1000001",
          "tgn:7012149",
          "tgn:1002835",
          "tgn:7007706",
          "tgn:7029392"
        ],
        "placetype": [
          "aat:300008761"
        ],
        "id": 2723245,
        "name:xx": "Toad Hollow"
      }
    },
    {
      "geometry": {
        "type": "Point",
        "coordinates": [
          -82.6,
          39.4833
        ]
      },
      "type": "Feature",
      "properties": {
        "hierarchy": [
          "tgn:2723246",
          "tgn:1000001",
          "tgn:7012149",
          "tgn:2001613",
          "tgn:7007706",
          "tgn:7029392"
        ],
        "placetype": [
          "aat:300008761"
        ],
        "id": 2723246,
        "name:xx": "Toad Hollow"
      }
    },
    {
      "geometry": {
        "type": "Point",
        "coordinates": [
          -81.3667,
          40.3333
        ]
      },
      "type": "Feature",
      "properties": {
        "hierarchy": [
          "tgn:2723247",
          "tgn:1000001",
          "tgn:7012149",
          "tgn:1002958",
          "tgn:7007706",
          "tgn:7029392"
        ],
        "placetype": [
          "aat:300008761"
        ],
        "id": 2723247,
        "name:xx": "Toad Hollow"
      }
    },
    {
      "geometry": {
        "type": "Point",
        "coordinates": [
          -82.6833,
          38.5833
        ]
      },
      "type": "Feature",
      "properties": {
        "hierarchy": [
          "tgn:2723248",
          "tgn:1000001",
          "tgn:7012149",
          "tgn:2001615",
          "tgn:7007706",
          "tgn:7029392"
        ],
        "placetype": [
          "aat:300008761"
        ],
        "id": 2723248,
        "name:xx": "Toad Hollow"
      }
    },
    {
      "geometry": {
        "type": "Point",
        "coordinates": [
          -77.0333,
          40.5667
        ]
      },
      "type": "Feature",
      "properties": {
        "hierarchy": [
          "tgn:2723249",
          "tgn:1000001",
          "tgn:7012149",
          "tgn:1002779",
          "tgn:7007710",
          "tgn:7029392"
        ],
        "placetype": [
          "aat:300008761"
        ],
        "id": 2723249,
        "name:xx": "Toad Hollow"
      }
    }
  ]
}
