{
  "geometry": {
    "type": "Point",
    "coordinates": [
      -72.0167,
      43.8833
    ]
  },
  "type": "Feature",
  "properties": {
    "hierarchy": [
      "tgn:2527778",
      "tgn:1000001",
      "tgn:2001424",
      "tgn:7012149",
      "tgn:7007564",
      "tgn:7029392"
    ],
    "placetype": [
      "aat:300008798"
    ],
    "id": 2527778,
    "name:xx": "Mountain Cube"
  }
}
