{
  "geometry": {
    "type": "Point",
    "coordinates": [
      103.55,
      25.8833
    ]
  },
  "type": "Feature",
  "properties": {
    "hierarchy": [
      "tgn:1070149",
      "tgn:1000004",
      "tgn:7018118",
      "tgn:1000111",
      "tgn:7029392"
    ],
    "placetype": [
      "aat:300008347"
    ],
    "id": 1070149,
    "name:xx": "Ludonghe"
  }
}
