{
  "geometry": {
    "type": "Point",
    "coordinates": [
      -94.1167,
      32.8667
    ]
  },
  "type": "Feature",
  "properties": {
    "hierarchy": [
      "tgn:2418812",
      "tgn:1000001",
      "tgn:7012149",
      "tgn:7029392"
    ],
    "placetype": [
      "aat:300008699"
    ],
    "id": 2418812,
    "name:xx": "James Bayou"
  }
}
