{
  "geometry": {
    "type": "Point",
    "coordinates": [
      -83.3167,
      37.55
    ]
  },
  "type": "Feature",
  "properties": {
    "hierarchy": [
      "tgn:2144736",
      "tgn:1000001",
      "tgn:2000772",
      "tgn:7012149",
      "tgn:7007255",
      "tgn:7029392"
    ],
    "placetype": [
      "aat:300008798"
    ],
    "id": 2144736,
    "name:xx": "Bald Hill"
  }
}
