{
  "geometry": {
    "type": "Point",
    "coordinates": [
      76.794337,
      21.317982
    ]
  },
  "type": "Feature",
  "properties": {
    "hierarchy": [
      "tgn:7557701",
      "tgn:1000004",
      "tgn:7000198",
      "tgn:1001895",
      "tgn:7029392"
    ],
    "placetype": [
      "aat:300008347"
    ],
    "name:en": "Rānīgohān",
    "id": 7557701
  }
}
