{
  "geometry": {
    "type": "Point",
    "coordinates": [
      -83.2167,
      40.8167
    ]
  },
  "type": "Feature",
  "properties": {
    "hierarchy": [
      "tgn:2294012",
      "tgn:1000001",
      "tgn:7012149",
      "tgn:1003039",
      "tgn:7007706",
      "tgn:7029392"
    ],
    "placetype": [
      "aat:300008347"
    ],
    "id": 2294012,
    "name:xx": "Douglass"
  }
}
