{
  "geometry": {
    "type": "Point",
    "coordinates": [
      -116.4167,
      37.9167
    ]
  },
  "type": "Feature",
  "properties": {
    "hierarchy": [
      "tgn:1110033",
      "tgn:1000001",
      "tgn:2001418",
      "tgn:7012149",
      "tgn:7007526",
      "tgn:7029392"
    ],
    "placetype": [
      "aat:300386831"
    ],
    "id": 1110033,
    "name:xx": "Kawich Range"
  }
}
