{
  "geometry": {
    "type": "Point",
    "coordinates": [
      33.1167,
      48.6667
    ]
  },
  "type": "Feature",
  "properties": {
    "hierarchy": [
      "tgn:1052083",
      "tgn:1000003",
      "tgn:7011662",
      "tgn:7006660",
      "tgn:7029392"
    ],
    "placetype": [
      "aat:300008347"
    ],
    "id": 1052083,
    "name:xx": "Aleksandrija"
  }
}
