{
  "geometry": {
    "type": "Point",
    "coordinates": [
      -77.4333,
      36.5667
    ]
  },
  "type": "Feature",
  "properties": {
    "hierarchy": [
      "tgn:7023735",
      "tgn:1000001",
      "tgn:7012149",
      "tgn:7029392"
    ],
    "placetype": [
      "aat:300006191"
    ],
    "id": 7023735,
    "name:xx": "Taylors Millpond"
  }
}
