{
  "type": "FeatureCollection",
  "features": [
    {
      "geometry": {
        "type": "Point",
        "coordinates": [
          -103.016667,
          19.966667
        ]
      },
      "type": "Feature",
      "properties": {
        "hierarchy": [
          "tgn:7392340",
          "tgn:1000001",
          "tgn:7005590",
          "tgn:7005560",
          "tgn:7029392"
        ],
        "placetype": [
          "aat:300008347"
        ],
        "id": 7392340,
        "name:xx": "Sabinas"
      }
    },
    {
      "geometry": {
        "type": "Point",
        "coordinates": [
          -107.566667,
          30.866667
        ]
      },
      "type": "Feature",
      "properties": {
        "hierarchy": [
          "tgn:7392341",
          "tgn:7005581",
          "tgn:1000001",
          "tgn:7005560",
          "tgn:7029392"
        ],
        "placetype": [
          "aat:300008795"
        ],
        "id": 7392341,
        "name:xx": "Sabinal, Sierra"
      }
    },
    {
      "geometry": {
        "type": "Point",
        "coordinates": [
          -99.916667,
          25.7
        ]
      },
      "type": "Feature",
      "properties": {
        "hierarchy": [
          "tgn:7392342",
          "tgn:1000001",
          "tgn:7005589",
          "tgn:7005560",
          "tgn:7029392"
        ],
        "placetype": [
          "aat:300266554",
          "aat:300008699"
        ],
        "id": 7392342,
        "name:xx": "Sabinal, Arroyo del"
      }
    },
    {
      "geometry": {
        "type": "Point",
        "coordinates": [
          -108.7,
          29.533333
        ]
      },
      "type": "Feature",
      "properties": {
        "hierarchy": [
          "tgn:7392343",
          "tgn:1000001",
          "tgn:1001960",
          "tgn:7005560",
          "tgn:7029392"
        ],
        "placetype": [
          "aat:300008699"
        ],
        "id": 7392343,
        "name:xx": "Sabinal, Arroyo"
      }
    },
    {
      "geometry": {
        "type": "Point",
        "coordinates": [
          -92.45,
          15.766667
        ]
      },
      "type": "Feature",
      "properties": {
        "hierarchy": [
          "tgn:7392344",
          "tgn:7005580",
          "tgn:1000001",
          "tgn:7005560",
          "tgn:7029392"
        ],
        "placetype": [
          "aat:300266554",
          "aat:300008699"
        ],
        "id": 7392344,
        "name:xx": "Sabinal"
      }
    },
    {
      "geometry": {
        "type": "Point",
        "coordinates": [
          -107.5,
          30.95
        ]
      },
      "type": "Feature",
      "properties": {
        "hierarchy": [
          "tgn:7392345",
          "tgn:7005581",
          "tgn:1000001",
          "tgn:7005560",
          "tgn:7029392"
        ],
        "placetype": [
          "aat:300007783"
        ],
        "id": 7392345,
        "name:xx": "Sabinal"
      }
    },
    {
      "geometry": {
        "type": "Point",
        "coordinates": [
          -107.633333,
          30.916667
        ]
      },
      "type": "Feature",
      "properties": {
        "hierarchy": [
          "tgn:7392346",
          "tgn:7005581",
          "tgn:1000001",
          "tgn:7005560",
          "tgn:7029392"
        ],
        "placetype": [
          "aat:300008347"
        ],
        "id": 7392346,
        "name:xx": "Sabinal"
      }
    },
    {
      "geometry": {
        "type": "Point",
        "coordinates": [
          -99.983333,
          25.7
        ]
      },
      "type": "Feature",
      "properties": {
        "hierarchy": [
          "tgn:7392347",
          "tgn:1000001",
          "tgn:7005589",
          "tgn:7005560",
          "tgn:7029392"
        ],
        "placetype": [
          "aat:300008347"
        ],
        "id": 7392347,
        "name:xx": "Sabinal"
      }
    },
    {
      "geometry": {
        "type": "Point",
        "coordinates": [
          -99.116667,
          21.75
        ]
      },
      "type": "Feature",
      "properties": {
        "hierarchy": [
          "tgn:7392348",
          "tgn:1000001",
          "tgn:7005594",
          "tgn:7005560",
          "tgn:7029392"
        ],
        "placetype": [
          "aat:300008347"
        ],
        "id": 7392348,
        "name:xx": "Sabinal"
      }
    },
    {
      "geometry": {
        "type": "Point",
        "coordinates": [
          -92.533333,
          15.783333
        ]
      },
      "type": "Feature",
      "properties": {
        "hierarchy": [
          "tgn:7392349",
          "tgn:7005580",
          "tgn:1000001",
          "tgn:7005560",
          "tgn:7029392"
        ],
        "placetype": [
          "aat:300008347"
        ],
        "id": 7392349,
        "name:xx": "Sabinal"
      }
    }
  ]
}
