{
  "geometry": {
    "type": "Point",
    "coordinates": [
      -87.0667,
      33.4667
    ]
  },
  "type": "Feature",
  "properties": {
    "hierarchy": [
      "tgn:2457352",
      "tgn:7002659",
      "tgn:1000001",
      "tgn:7012149",
      "tgn:2000036",
      "tgn:7029392"
    ],
    "placetype": [
      "aat:300008706"
    ],
    "id": 2457352,
    "name:xx": "Little Lick Creek"
  }
}
