{
  "geometry": {
    "type": "Point",
    "coordinates": [
      -103.6167,
      36.2333
    ]
  },
  "type": "Feature",
  "properties": {
    "hierarchy": [
      "tgn:2124624",
      "tgn:1000001",
      "tgn:7012149",
      "tgn:2001459",
      "tgn:7007566",
      "tgn:7029392"
    ],
    "placetype": [
      "aat:300008706"
    ],
    "id": 2124624,
    "name:xx": "Abbott Creek"
  }
}
