{
  "geometry": {
    "type": "Point",
    "coordinates": [
      -87.6167,
      36.2333
    ]
  },
  "type": "Feature",
  "properties": {
    "hierarchy": [
      "tgn:2372059",
      "tgn:1000001",
      "tgn:7012149",
      "tgn:2001878",
      "tgn:7007825",
      "tgn:7029392"
    ],
    "placetype": [
      "aat:300008699"
    ],
    "id": 2372059,
    "name:xx": "Half Pone Branch"
  }
}
