{
  "geometry": {
    "type": "Point",
    "coordinates": [
      -97.2833,
      44.3333
    ]
  },
  "type": "Feature",
  "properties": {
    "hierarchy": [
      "tgn:1118718",
      "tgn:1000001",
      "tgn:2001808",
      "tgn:7012149",
      "tgn:7007713",
      "tgn:7029392"
    ],
    "placetype": [
      "aat:300008680"
    ],
    "id": 1118718,
    "name:xx": "Whitewood, Lake"
  }
}
