{
  "geometry": {
    "type": "Point",
    "coordinates": [
      -80.2667,
      38.85
    ]
  },
  "type": "Feature",
  "properties": {
    "hierarchy": [
      "tgn:2439884",
      "tgn:1000001",
      "tgn:7012149",
      "tgn:2002298",
      "tgn:7013961",
      "tgn:7029392"
    ],
    "placetype": [
      "aat:300008699"
    ],
    "id": 2439884,
    "name:xx": "Kittle Run"
  }
}
