{
  "geometry": {
    "type": "Point",
    "coordinates": [
      -75.3833,
      39.6167
    ]
  },
  "type": "Feature",
  "properties": {
    "hierarchy": [
      "tgn:2271301",
      "tgn:1000001",
      "tgn:7014449",
      "tgn:7012149",
      "tgn:7007565",
      "tgn:7029392"
    ],
    "placetype": [
      "aat:300008699"
    ],
    "id": 2271301,
    "name:xx": "Culliers Run"
  }
}
