{
  "type": "FeatureCollection",
  "features": [
    {
      "geometry": {
        "type": "Point",
        "coordinates": [
          -2.883333,
          41.5
        ]
      },
      "type": "Feature",
      "properties": {
        "hierarchy": [
          "tgn:7333760",
          "tgn:7002842",
          "tgn:7001158",
          "tgn:1000003",
          "tgn:1000095",
          "tgn:7029392"
        ],
        "placetype": [
          "aat:300008699"
        ],
        "id": 7333760,
        "name:xx": "Escalote, Río"
      }
    },
    {
      "geometry": {
        "type": "Point",
        "coordinates": [
          -4.6,
          40.766667
        ]
      },
      "type": "Feature",
      "properties": {
        "hierarchy": [
          "tgn:7333761",
          "tgn:7002806",
          "tgn:7001158",
          "tgn:1000003",
          "tgn:1000095",
          "tgn:7029392"
        ],
        "placetype": [
          "aat:300008347"
        ],
        "id": 7333761,
        "name:xx": "Escalonilla"
      }
    },
    {
      "geometry": {
        "type": "Point",
        "coordinates": [
          -4.783333,
          40.55
        ]
      },
      "type": "Feature",
      "properties": {
        "hierarchy": [
          "tgn:7333762",
          "tgn:7002806",
          "tgn:7001158",
          "tgn:1000003",
          "tgn:1000095",
          "tgn:7029392"
        ],
        "placetype": [
          "aat:300008347"
        ],
        "id": 7333762,
        "name:xx": "Escalonilla"
      }
    },
    {
      "geometry": {
        "type": "Point",
        "coordinates": [
          -4.35,
          39.933333
        ]
      },
      "type": "Feature",
      "properties": {
        "hierarchy": [
          "tgn:7333763",
          "tgn:7002847",
          "tgn:1001647",
          "tgn:1000003",
          "tgn:1000095",
          "tgn:7029392"
        ],
        "placetype": [
          "aat:300008347"
        ],
        "id": 7333763,
        "name:xx": "Escalonilla"
      }
    },
    {
      "geometry": {
        "type": "Point",
        "coordinates": [
          -4.116667,
          41.166667
        ]
      },
      "type": "Feature",
      "properties": {
        "hierarchy": [
          "tgn:7333764",
          "tgn:7002839",
          "tgn:7001158",
          "tgn:1000003",
          "tgn:1000095",
          "tgn:7029392"
        ],
        "placetype": [
          "aat:300008347"
        ],
        "id": 7333764,
        "name:xx": "Escalona del Prado"
      }
    },
    {
      "geometry": {
        "type": "Point",
        "coordinates": [
          -0.916667,
          37.933333
        ]
      },
      "type": "Feature",
      "properties": {
        "hierarchy": [
          "tgn:7333765",
          "tgn:7002804",
          "tgn:1000003",
          "tgn:7002793",
          "tgn:1000095",
          "tgn:7029392"
        ],
        "placetype": [
          "aat:300266640"
        ],
        "id": 7333765,
        "name:xx": "Escalona, Sierra de"
      }
    },
    {
      "geometry": {
        "type": "Point",
        "coordinates": [
          -0.65,
          39.133333
        ]
      },
      "type": "Feature",
      "properties": {
        "hierarchy": [
          "tgn:7333766",
          "tgn:7001165",
          "tgn:1000003",
          "tgn:7002793",
          "tgn:1000095",
          "tgn:7029392"
        ],
        "placetype": [
          "aat:300008699"
        ],
        "id": 7333766,
        "name:xx": "Escalona, Río"
      }
    },
    {
      "geometry": {
        "type": "Point",
        "coordinates": [
          0.033333,
          40.733333
        ]
      },
      "type": "Feature",
      "properties": {
        "hierarchy": [
          "tgn:7333767",
          "tgn:7002815",
          "tgn:1000003",
          "tgn:7002793",
          "tgn:1000095",
          "tgn:7029392"
        ],
        "placetype": [
          "aat:300266554",
          "aat:300008699"
        ],
        "id": 7333767,
        "name:xx": "Escalona, Barranco de"
      }
    },
    {
      "geometry": {
        "type": "Point",
        "coordinates": [
          0.142898,
          42.49845
        ]
      },
      "type": "Feature",
      "properties": {
        "hierarchy": [
          "tgn:7333768",
          "tgn:7002759",
          "tgn:7008909",
          "tgn:1000003",
          "tgn:1000095",
          "tgn:7029392"
        ],
        "placetype": [
          "aat:300008347"
        ],
        "id": 7333768,
        "name:xx": "Escalona"
      }
    }
  ]
}
