{
  "geometry": {
    "type": "Point",
    "coordinates": [
      -83.5333,
      13.55
    ]
  },
  "type": "Feature",
  "properties": {
    "hierarchy": [
      "tgn:1018801",
      "tgn:7593358",
      "tgn:1000001",
      "tgn:7005562",
      "tgn:7029392"
    ],
    "placetype": [
      "aat:300008347"
    ],
    "id": 1018801,
    "name:xx": "Wounta"
  }
}
