{
  "geometry": {
    "type": "Point",
    "coordinates": [
      -91.95,
      30.0333
    ]
  },
  "type": "Feature",
  "properties": {
    "hierarchy": [
      "tgn:2043345",
      "tgn:1000001",
      "tgn:7012149",
      "tgn:2000876",
      "tgn:7007256",
      "tgn:7029392"
    ],
    "placetype": [
      "aat:300008347",
      "aat:300387210"
    ],
    "id": 2043345,
    "name:xx": "Lozes"
  }
}
