{
  "geometry": {
    "type": "Point",
    "coordinates": [
      -82.5333,
      29.7333
    ]
  },
  "type": "Feature",
  "properties": {
    "hierarchy": [
      "tgn:2213899",
      "tgn:2000256",
      "tgn:1000001",
      "tgn:7012149",
      "tgn:7007240",
      "tgn:7029392"
    ],
    "placetype": [
      "aat:300008347"
    ],
    "id": 2213899,
    "name:xx": "Cadillac"
  }
}
