{
  "geometry": {
    "type": "Point",
    "coordinates": [
      -114.75,
      41.7667
    ]
  },
  "type": "Feature",
  "properties": {
    "hierarchy": [
      "tgn:2181080",
      "tgn:1000001",
      "tgn:2001411",
      "tgn:7012149",
      "tgn:7007526",
      "tgn:7029392"
    ],
    "placetype": [
      "aat:300000390"
    ],
    "id": 2181080,
    "name:xx": "Blue Bird Mine"
  }
}
