{
  "geometry": {
    "type": "Point",
    "coordinates": [
      -98.7833,
      30.2167
    ]
  },
  "type": "Feature",
  "properties": {
    "hierarchy": [
      "tgn:2626463",
      "tgn:1000001",
      "tgn:7012149",
      "tgn:2001990",
      "tgn:7007826",
      "tgn:7029392"
    ],
    "placetype": [
      "aat:300008347"
    ],
    "id": 2626463,
    "name:xx": "Rocky Hill"
  }
}
