{
  "geometry": {
    "type": "Point",
    "coordinates": [
      -92.8333,
      39.3833
    ]
  },
  "type": "Feature",
  "properties": {
    "hierarchy": [
      "tgn:2655237",
      "tgn:1000001",
      "tgn:2001184",
      "tgn:7012149",
      "tgn:7007523",
      "tgn:7029392"
    ],
    "placetype": [
      "aat:300008699"
    ],
    "id": 2655237,
    "name:xx": "Shannondale Branch"
  }
}
