{
  "geometry": {
    "type": "Point",
    "coordinates": [
      -94.55,
      47.2833
    ]
  },
  "type": "Feature",
  "properties": {
    "hierarchy": [
      "tgn:2462032",
      "tgn:1000001",
      "tgn:2001009",
      "tgn:7012149",
      "tgn:7007521",
      "tgn:7029392"
    ],
    "placetype": [
      "aat:300008680"
    ],
    "id": 2462032,
    "name:xx": "Little Twin Lake"
  }
}
