{
  "geometry": {
    "type": "Point",
    "coordinates": [
      -85.75,
      33.2167
    ]
  },
  "type": "Feature",
  "properties": {
    "hierarchy": [
      "tgn:2395021",
      "tgn:7002659",
      "tgn:1000001",
      "tgn:2000013",
      "tgn:7012149",
      "tgn:7029392"
    ],
    "placetype": [
      "aat:300008699"
    ],
    "id": 2395021,
    "name:xx": "Holdridge Branch"
  }
}
