{
  "geometry": {
    "type": "Point",
    "coordinates": [
      -111.35,
      31.75
    ]
  },
  "type": "Feature",
  "properties": {
    "hierarchy": [
      "tgn:2328191",
      "tgn:1000001",
      "tgn:7006451",
      "tgn:7012149",
      "tgn:2000100",
      "tgn:7029392"
    ],
    "placetype": [
      "aat:300006191"
    ],
    "id": 2328191,
    "name:xx": "Fish Tank"
  }
}
