{
  "geometry": {
    "type": "Point",
    "coordinates": [
      129.95,
      42.0167
    ]
  },
  "type": "Feature",
  "properties": {
    "hierarchy": [
      "tgn:1082084",
      "tgn:1001285",
      "tgn:1000004",
      "tgn:1000122",
      "tgn:7029392"
    ],
    "placetype": [
      "aat:300008347"
    ],
    "id": 1082084,
    "name:xx": "Pugŏ-ri"
  }
}
