{
  "geometry": {
    "type": "Point",
    "coordinates": [
      -105.1833,
      38.0333
    ]
  },
  "type": "Feature",
  "properties": {
    "hierarchy": [
      "tgn:2455461",
      "tgn:1000001",
      "tgn:7012149",
      "tgn:2000205",
      "tgn:7007158",
      "tgn:7029392"
    ],
    "placetype": [
      "aat:300008706"
    ],
    "id": 2455461,
    "name:xx": "Little Froze Creek"
  }
}
