{
  "geometry": {
    "type": "Point",
    "coordinates": [
      -102.95,
      25.95
    ]
  },
  "type": "Feature",
  "properties": {
    "hierarchy": [
      "tgn:7436789",
      "tgn:1001853",
      "tgn:1000001",
      "tgn:7005560",
      "tgn:7029392"
    ],
    "placetype": [
      "aat:300008795"
    ],
    "id": 7436789,
    "name:xx": "Santiago, Cerro"
  }
}
