{
  "type": "FeatureCollection",
  "features": [
    {
      "geometry": {
        "type": "Point",
        "coordinates": [
          11.316667,
          53.75
        ]
      },
      "type": "Feature",
      "properties": {
        "hierarchy": [
          "tgn:7175990",
          "tgn:1000003",
          "tgn:7000094",
          "tgn:7000084",
          "tgn:7029392"
        ],
        "placetype": [
          "aat:300008347"
        ],
        "id": 7175990,
        "name:xx": "Grevenhagen"
      }
    },
    {
      "geometry": {
        "type": "Point",
        "coordinates": [
          8.983333,
          51.8
        ]
      },
      "type": "Feature",
      "properties": {
        "hierarchy": [
          "tgn:7175991",
          "tgn:1000003",
          "tgn:7003677",
          "tgn:7000084",
          "tgn:7029392"
        ],
        "placetype": [
          "aat:300008347"
        ],
        "id": 7175991,
        "name:xx": "Grevenhagen"
      }
    },
    {
      "geometry": {
        "type": "Point",
        "coordinates": [
          9.183333,
          51.85
        ]
      },
      "type": "Feature",
      "properties": {
        "hierarchy": [
          "tgn:7175992",
          "tgn:1000003",
          "tgn:7003677",
          "tgn:7000084",
          "tgn:7029392"
        ],
        "placetype": [
          "aat:300000206"
        ],
        "id": 7175992,
        "name:xx": "Grevenburg"
      }
    },
    {
      "geometry": {
        "type": "Point",
        "coordinates": [
          8.016667,
          51.133333
        ]
      },
      "type": "Feature",
      "properties": {
        "hierarchy": [
          "tgn:7175993",
          "tgn:1000003",
          "tgn:7003677",
          "tgn:7000084",
          "tgn:7029392"
        ],
        "placetype": [
          "aat:300008347"
        ],
        "id": 7175993,
        "name:xx": "Grevenbrück"
      }
    },
    {
      "geometry": {
        "type": "Point",
        "coordinates": [
          11.983333,
          53.483333
        ]
      },
      "type": "Feature",
      "properties": {
        "hierarchy": [
          "tgn:7175995",
          "tgn:1000003",
          "tgn:7000094",
          "tgn:7000084",
          "tgn:7029392"
        ],
        "placetype": [
          "aat:300008347"
        ],
        "id": 7175995,
        "name:xx": "Greven"
      }
    },
    {
      "geometry": {
        "type": "Point",
        "coordinates": [
          10.8,
          53.483333
        ]
      },
      "type": "Feature",
      "properties": {
        "hierarchy": [
          "tgn:7175996",
          "tgn:1000003",
          "tgn:7000094",
          "tgn:7000084",
          "tgn:7029392"
        ],
        "placetype": [
          "aat:300008347"
        ],
        "id": 7175996,
        "name:xx": "Greven"
      }
    },
    {
      "geometry": {
        "type": "Point",
        "coordinates": [
          8.133333,
          52.5
        ]
      },
      "type": "Feature",
      "properties": {
        "hierarchy": [
          "tgn:7175997",
          "tgn:1000003",
          "tgn:7003676",
          "tgn:7000084",
          "tgn:7029392"
        ],
        "placetype": [
          "aat:300008347"
        ],
        "id": 7175997,
        "name:xx": "Greven"
      }
    },
    {
      "geometry": {
        "type": "Point",
        "coordinates": [
          8.133333,
          52.483333
        ]
      },
      "type": "Feature",
      "properties": {
        "hierarchy": [
          "tgn:7175999",
          "tgn:1000003",
          "tgn:7003676",
          "tgn:7000084",
          "tgn:7029392"
        ],
        "placetype": [
          "aat:300000206"
        ],
        "id": 7175999,
        "name:xx": "Greven"
      }
    }
  ]
}
