{
  "geometry": {
    "type": "Point",
    "coordinates": [
      120.3833,
      26.6833
    ]
  },
  "type": "Feature",
  "properties": {
    "hierarchy": [
      "tgn:1010300",
      "tgn:1000004",
      "tgn:7001796",
      "tgn:1000111",
      "tgn:7029392"
    ],
    "placetype": [
      "aat:300008791"
    ],
    "id": 1010300,
    "name:xx": "Sishuang Liedao"
  }
}
