{
  "geometry": {
    "type": "Point",
    "coordinates": [
      20.5333,
      41.0667
    ]
  },
  "type": "Feature",
  "properties": {
    "hierarchy": [
      "tgn:1025358",
      "tgn:7006427",
      "tgn:1000003",
      "tgn:7006417",
      "tgn:7029392"
    ],
    "placetype": [
      "aat:300008347"
    ],
    "id": 1025358,
    "name:xx": "Përrenjas"
  }
}
