{
  "geometry": {
    "type": "Point",
    "coordinates": [
      -87.7167,
      35.65
    ]
  },
  "type": "Feature",
  "properties": {
    "hierarchy": [
      "tgn:2718390",
      "tgn:1000001",
      "tgn:7012149",
      "tgn:7015666",
      "tgn:7007825",
      "tgn:7029392"
    ],
    "placetype": [
      "aat:300008761"
    ],
    "id": 2718390,
    "name:xx": "Thompson Hollow"
  }
}
