{
  "geometry": {
    "type": "Point",
    "coordinates": [
      -116.9167,
      43.1667
    ]
  },
  "type": "Feature",
  "properties": {
    "hierarchy": [
      "tgn:2137899",
      "tgn:1000001",
      "tgn:7012149",
      "tgn:2000488",
      "tgn:7007250",
      "tgn:7029392"
    ],
    "placetype": [
      "aat:300008697"
    ],
    "id": 2137899,
    "name:xx": "Arrow Spring"
  }
}
