{
  "type": "FeatureCollection",
  "features": [
    {
      "geometry": {
        "type": "Point",
        "coordinates": [
          -80.3,
          25.9
        ]
      },
      "type": "Feature",
      "properties": {
        "hierarchy": [
          "tgn:2020380",
          "tgn:1000001",
          "tgn:7012149",
          "tgn:1002314",
          "tgn:7007240",
          "tgn:7029392"
        ],
        "placetype": [
          "aat:300008347"
        ],
        "id": 2020380,
        "name:xx": "Miami Lakes"
      }
    },
    {
      "geometry": {
        "type": "Point",
        "coordinates": [
          -80.1833,
          25.85
        ]
      },
      "type": "Feature",
      "properties": {
        "hierarchy": [
          "tgn:2020382",
          "tgn:1000001",
          "tgn:7012149",
          "tgn:1002314",
          "tgn:7007240",
          "tgn:7029392"
        ],
        "placetype": [
          "aat:300008347"
        ],
        "id": 2020382,
        "name:xx": "Miami Shores"
      }
    },
    {
      "geometry": {
        "type": "Point",
        "coordinates": [
          -80.2833,
          25.8167
        ]
      },
      "type": "Feature",
      "properties": {
        "hierarchy": [
          "tgn:2020385",
          "tgn:1000001",
          "tgn:7012149",
          "tgn:1002314",
          "tgn:7007240",
          "tgn:7029392"
        ],
        "placetype": [
          "aat:300008347"
        ],
        "id": 2020385,
        "name:xx": "Miami Springs"
      }
    },
    {
      "geometry": {
        "type": "Point",
        "coordinates": [
          -82.2667,
          29.5
        ]
      },
      "type": "Feature",
      "properties": {
        "hierarchy": [
          "tgn:2020386",
          "tgn:2000256",
          "tgn:1000001",
          "tgn:7012149",
          "tgn:7007240",
          "tgn:7029392"
        ],
        "placetype": [
          "aat:300008347"
        ],
        "id": 2020386,
        "name:xx": "Micanopy"
      }
    },
    {
      "geometry": {
        "type": "Point",
        "coordinates": [
          -80.5,
          27.8667
        ]
      },
      "type": "Feature",
      "properties": {
        "hierarchy": [
          "tgn:2020387",
          "tgn:1000001",
          "tgn:1002200",
          "tgn:7012149",
          "tgn:7007240",
          "tgn:7029392"
        ],
        "placetype": [
          "aat:300008347"
        ],
        "id": 2020387,
        "name:xx": "Micco"
      }
    }
  ]
}
