{
  "geometry": {
    "type": "Point",
    "coordinates": [
      87.75,
      24.966667
    ]
  },
  "type": "Feature",
  "properties": {
    "hierarchy": [
      "tgn:7553971",
      "tgn:1000004",
      "tgn:7000198",
      "tgn:7031783",
      "tgn:7029392"
    ],
    "placetype": [
      "aat:300008347"
    ],
    "name:en": "Nimgāchi",
    "id": 7553971
  }
}
