{
  "type": "FeatureCollection",
  "features": [
    {
      "geometry": {
        "type": "Point",
        "coordinates": [
          -100.65,
          20.766667
        ]
      },
      "type": "Feature",
      "properties": {
        "hierarchy": [
          "tgn:7367670",
          "tgn:7005584",
          "tgn:1000001",
          "tgn:7005560",
          "tgn:7029392"
        ],
        "placetype": [
          "aat:300008347"
        ],
        "id": 7367670,
        "name:xx": "El Potrero"
      }
    },
    {
      "geometry": {
        "type": "Point",
        "coordinates": [
          -98.066667,
          20.65
        ]
      },
      "type": "Feature",
      "properties": {
        "hierarchy": [
          "tgn:7367671",
          "tgn:7005587",
          "tgn:1000001",
          "tgn:7005560",
          "tgn:7029392"
        ],
        "placetype": [
          "aat:300008347"
        ],
        "id": 7367671,
        "name:xx": "El Potrero"
      }
    },
    {
      "geometry": {
        "type": "Point",
        "coordinates": [
          -98.05,
          19.566667
        ]
      },
      "type": "Feature",
      "properties": {
        "hierarchy": [
          "tgn:7367672",
          "tgn:1000001",
          "tgn:7005598",
          "tgn:7005560",
          "tgn:7029392"
        ],
        "placetype": [
          "aat:300008347"
        ],
        "id": 7367672,
        "name:xx": "El Potrero"
      }
    },
    {
      "geometry": {
        "type": "Point",
        "coordinates": [
          -100.716667,
          18.4
        ]
      },
      "type": "Feature",
      "properties": {
        "hierarchy": [
          "tgn:7367673",
          "tgn:1000001",
          "tgn:7005590",
          "tgn:7005560",
          "tgn:7029392"
        ],
        "placetype": [
          "aat:300008347"
        ],
        "id": 7367673,
        "name:xx": "El Potrero"
      }
    },
    {
      "geometry": {
        "type": "Point",
        "coordinates": [
          -95.6,
          16.316667
        ]
      },
      "type": "Feature",
      "properties": {
        "hierarchy": [
          "tgn:7367674",
          "tgn:1000001",
          "tgn:7005591",
          "tgn:7005560",
          "tgn:7029392"
        ],
        "placetype": [
          "aat:300008347"
        ],
        "id": 7367674,
        "name:xx": "El Potrero"
      }
    },
    {
      "geometry": {
        "type": "Point",
        "coordinates": [
          -93.683333,
          16.133333
        ]
      },
      "type": "Feature",
      "properties": {
        "hierarchy": [
          "tgn:7367675",
          "tgn:7005580",
          "tgn:1000001",
          "tgn:7005560",
          "tgn:7029392"
        ],
        "placetype": [
          "aat:300008347"
        ],
        "id": 7367675,
        "name:xx": "El Potrero"
      }
    },
    {
      "geometry": {
        "type": "Point",
        "coordinates": [
          -97.933333,
          16.083333
        ]
      },
      "type": "Feature",
      "properties": {
        "hierarchy": [
          "tgn:7367676",
          "tgn:1000001",
          "tgn:7005591",
          "tgn:7005560",
          "tgn:7029392"
        ],
        "placetype": [
          "aat:300008347"
        ],
        "id": 7367676,
        "name:xx": "El Potrero"
      }
    },
    {
      "geometry": {
        "type": "Point",
        "coordinates": [
          -108.316667,
          29.483333
        ]
      },
      "type": "Feature",
      "properties": {
        "hierarchy": [
          "tgn:7367677",
          "tgn:7005581",
          "tgn:1000001",
          "tgn:7005560",
          "tgn:7029392"
        ],
        "placetype": [
          "aat:300000241"
        ],
        "id": 7367677,
        "name:xx": "Rancho El Potrerito"
      }
    },
    {
      "geometry": {
        "type": "Point",
        "coordinates": [
          -102.95,
          20.916667
        ]
      },
      "type": "Feature",
      "properties": {
        "hierarchy": [
          "tgn:7367678",
          "tgn:7005586",
          "tgn:1000001",
          "tgn:7005560",
          "tgn:7029392"
        ],
        "placetype": [
          "aat:300008347"
        ],
        "id": 7367678,
        "name:xx": "El Potrerito"
      }
    },
    {
      "geometry": {
        "type": "Point",
        "coordinates": [
          -109.333333,
          27.583333
        ]
      },
      "type": "Feature",
      "properties": {
        "hierarchy": [
          "tgn:7367679",
          "tgn:1000001",
          "tgn:1001960",
          "tgn:7005560",
          "tgn:7029392"
        ],
        "placetype": [
          "aat:300000241"
        ],
        "id": 7367679,
        "name:xx": "Rancho El Potrerillo"
      }
    }
  ]
}
