{
  "geometry": {
    "type": "Point",
    "coordinates": [
      49.3167,
      53.3667
    ]
  },
  "type": "Feature",
  "properties": {
    "hierarchy": [
      "tgn:1051831",
      "tgn:1000004",
      "tgn:1003407",
      "tgn:7018214",
      "tgn:7002435",
      "tgn:7029392"
    ],
    "placetype": [
      "aat:300008347"
    ],
    "id": 1051831,
    "name:xx": "Žiguli"
  }
}
