{
  "geometry": {
    "type": "Point",
    "coordinates": [
      -76.85,
      36.8167
    ]
  },
  "type": "Feature",
  "properties": {
    "hierarchy": [
      "tgn:2400992",
      "tgn:1000001",
      "tgn:7012149",
      "tgn:1002506",
      "tgn:7007919",
      "tgn:7029392"
    ],
    "placetype": [
      "aat:300008905"
    ],
    "id": 2400992,
    "name:xx": "Horse Swamp"
  }
}
