{
  "geometry": {
    "type": "Point",
    "coordinates": [
      -97.35,
      45.4167
    ]
  },
  "type": "Feature",
  "properties": {
    "hierarchy": [
      "tgn:2777323",
      "tgn:1000001",
      "tgn:2001788",
      "tgn:7012149",
      "tgn:7007713",
      "tgn:7029392"
    ],
    "placetype": [
      "aat:300132316"
    ],
    "id": 2777323,
    "name:xx": "Wingate Arm"
  }
}
