{
  "geometry": {
    "type": "Point",
    "coordinates": [
      -73.0167,
      43.6333
    ]
  },
  "type": "Feature",
  "properties": {
    "hierarchy": [
      "tgn:2615943",
      "tgn:1000001",
      "tgn:1002840",
      "tgn:7012149",
      "tgn:7007828",
      "tgn:7029392"
    ],
    "placetype": [
      "aat:300006191"
    ],
    "id": 2615943,
    "name:xx": "Reynolds Reservoir"
  }
}
