{
  "geometry": {
    "type": "Point",
    "coordinates": [
      -91.5833,
      15.6667
    ]
  },
  "type": "Feature",
  "properties": {
    "hierarchy": [
      "tgn:1000639",
      "tgn:1000001",
      "tgn:7005493",
      "tgn:7029392"
    ],
    "placetype": [
      "aat:300008631",
      "aat:300387064",
      "aat:300000772"
    ],
    "id": 1000639,
    "name:xx": "Huehuetenango"
  }
}
