{
  "geometry": {
    "type": "Point",
    "coordinates": [
      -67.8667,
      45.9167
    ]
  },
  "type": "Feature",
  "properties": {
    "hierarchy": [
      "tgn:2503746",
      "tgn:2000919",
      "tgn:1000001",
      "tgn:7012149",
      "tgn:7007515",
      "tgn:7029392"
    ],
    "placetype": [
      "aat:300008699"
    ],
    "id": 2503746,
    "name:xx": "Meadow Brook"
  }
}
