{
  "geometry": {
    "type": "Point",
    "coordinates": [
      19.6833,
      -1.9333
    ]
  },
  "type": "Feature",
  "properties": {
    "hierarchy": [
      "tgn:1089432",
      "tgn:1001143",
      "tgn:7001242",
      "tgn:1000159",
      "tgn:7029392"
    ],
    "placetype": [
      "aat:300008347"
    ],
    "id": 1089432,
    "name:xx": "Nkoto"
  }
}
