{
  "type": "FeatureCollection",
  "features": [
    {
      "geometry": {
        "type": "Point",
        "coordinates": [
          9.3,
          53.766667
        ]
      },
      "type": "Feature",
      "properties": {
        "hierarchy": [
          "tgn:7122100",
          "tgn:1000003",
          "tgn:7003676",
          "tgn:7000084",
          "tgn:7029392"
        ],
        "placetype": [
          "aat:300387200"
        ],
        "id": 7122100,
        "name:xx": "Neulandermoor"
      }
    },
    {
      "geometry": {
        "type": "Point",
        "coordinates": [
          9.3,
          53.683333
        ]
      },
      "type": "Feature",
      "properties": {
        "hierarchy": [
          "tgn:7122101",
          "tgn:1000003",
          "tgn:7003676",
          "tgn:7000084",
          "tgn:7029392"
        ],
        "placetype": [
          "aat:300008347"
        ],
        "id": 7122101,
        "name:xx": "Neuland am Moore"
      }
    },
    {
      "geometry": {
        "type": "Point",
        "coordinates": [
          13.8,
          53.1
        ]
      },
      "type": "Feature",
      "properties": {
        "hierarchy": [
          "tgn:7122102",
          "tgn:7000096",
          "tgn:1000003",
          "tgn:7000084",
          "tgn:7029392"
        ],
        "placetype": [
          "aat:300004792"
        ],
        "id": 7122102,
        "name:xx": "Försterei Neuland"
      }
    },
    {
      "geometry": {
        "type": "Point",
        "coordinates": [
          9.283333,
          53.666667
        ]
      },
      "type": "Feature",
      "properties": {
        "hierarchy": [
          "tgn:7122103",
          "tgn:1000003",
          "tgn:7003676",
          "tgn:7000084",
          "tgn:7029392"
        ],
        "placetype": [
          "aat:300008347"
        ],
        "id": 7122103,
        "name:xx": "Neuland"
      }
    },
    {
      "geometry": {
        "type": "Point",
        "coordinates": [
          9.7,
          53.483333
        ]
      },
      "type": "Feature",
      "properties": {
        "hierarchy": [
          "tgn:7122105",
          "tgn:1000003",
          "tgn:7003676",
          "tgn:7000084",
          "tgn:7029392"
        ],
        "placetype": [
          "aat:300008347"
        ],
        "id": 7122105,
        "name:xx": "Neuland"
      }
    },
    {
      "geometry": {
        "type": "Point",
        "coordinates": [
          10.033333,
          53.466667
        ]
      },
      "type": "Feature",
      "properties": {
        "hierarchy": [
          "tgn:7122106",
          "tgn:1000003",
          "tgn:7003673",
          "tgn:7000084",
          "tgn:7029392"
        ],
        "placetype": [
          "aat:300008347"
        ],
        "id": 7122106,
        "name:xx": "Neuland"
      }
    },
    {
      "geometry": {
        "type": "Point",
        "coordinates": [
          10.15,
          53.4
        ]
      },
      "type": "Feature",
      "properties": {
        "hierarchy": [
          "tgn:7122107",
          "tgn:1000003",
          "tgn:7003676",
          "tgn:7000084",
          "tgn:7029392"
        ],
        "placetype": [
          "aat:300006163"
        ],
        "id": 7122107,
        "name:xx": "Neuland"
      }
    },
    {
      "geometry": {
        "type": "Point",
        "coordinates": [
          8.35,
          54.966667
        ]
      },
      "type": "Feature",
      "properties": {
        "hierarchy": [
          "tgn:7122108",
          "tgn:1000003",
          "tgn:7003688",
          "tgn:7000084",
          "tgn:7029392"
        ],
        "placetype": [
          "aat:300386990"
        ],
        "id": 7122108,
        "name:xx": "Nie Lönn"
      }
    },
    {
      "geometry": {
        "type": "Point",
        "coordinates": [
          8.966667,
          54.883333
        ]
      },
      "type": "Feature",
      "properties": {
        "hierarchy": [
          "tgn:7122109",
          "tgn:1000003",
          "tgn:7003688",
          "tgn:7000084",
          "tgn:7029392"
        ],
        "placetype": [
          "aat:300000206"
        ],
        "id": 7122109,
        "name:xx": "Neuland"
      }
    }
  ]
}
