{
  "geometry": {
    "type": "Point",
    "coordinates": [
      -83.2333,
      30.15
    ]
  },
  "type": "Feature",
  "properties": {
    "hierarchy": [
      "tgn:2130156",
      "tgn:1000001",
      "tgn:2000275",
      "tgn:7012149",
      "tgn:7007240",
      "tgn:7029392"
    ],
    "placetype": [
      "aat:300008680"
    ],
    "id": 2130156,
    "name:xx": "Allen Mill Pond"
  }
}
