{
  "geometry": {
    "type": "Point",
    "coordinates": [
      -76.35,
      39.35
    ]
  },
  "type": "Feature",
  "properties": {
    "hierarchy": [
      "tgn:2271883",
      "tgn:7016099",
      "tgn:1000001",
      "tgn:7012149",
      "tgn:7007516",
      "tgn:7029392"
    ],
    "placetype": [
      "aat:300008347"
    ],
    "id": 2271883,
    "name:xx": "Cunninghill Cove"
  }
}
