{
  "geometry": {
    "type": "Point",
    "coordinates": [
      -77.1167,
      37.25
    ]
  },
  "type": "Feature",
  "properties": {
    "hierarchy": [
      "tgn:2542659",
      "tgn:1000001",
      "tgn:7012149",
      "tgn:1002805",
      "tgn:7007919",
      "tgn:7029392"
    ],
    "placetype": [
      "aat:300008699"
    ],
    "id": 2542659,
    "name:xx": "Nobles Swamp"
  }
}
