{
  "geometry": {
    "type": "Point",
    "coordinates": [
      -90.65,
      39.1667
    ]
  },
  "type": "Feature",
  "properties": {
    "hierarchy": [
      "tgn:1002221",
      "tgn:1000001",
      "tgn:7012149",
      "tgn:7007251",
      "tgn:7029392"
    ],
    "placetype": [
      "aat:300387145",
      "aat:300000771"
    ],
    "id": 1002221,
    "name:xx": "Calhoun"
  }
}
