{
  "type": "FeatureCollection",
  "features": [
    {
      "geometry": {
        "type": "Point",
        "coordinates": [
          -112.4167,
          33.9333
        ]
      },
      "type": "Feature",
      "properties": {
        "hierarchy": [
          "tgn:2400010",
          "tgn:1000001",
          "tgn:7006451",
          "tgn:7012149",
          "tgn:2000103",
          "tgn:7029392"
        ],
        "placetype": [
          "aat:300008706"
        ],
        "id": 2400010,
        "name:xx": "Horse Creek"
      }
    },
    {
      "geometry": {
        "type": "Point",
        "coordinates": [
          -94.45,
          36.4167
        ]
      },
      "type": "Feature",
      "properties": {
        "hierarchy": [
          "tgn:2400011",
          "tgn:1000001",
          "tgn:2000108",
          "tgn:7016172",
          "tgn:7012149",
          "tgn:7029392"
        ],
        "placetype": [
          "aat:300008706"
        ],
        "id": 2400011,
        "name:xx": "Horse Creek"
      }
    },
    {
      "geometry": {
        "type": "Point",
        "coordinates": [
          -90.2667,
          36.4333
        ]
      },
      "type": "Feature",
      "properties": {
        "hierarchy": [
          "tgn:2400012",
          "tgn:1000001",
          "tgn:7016172",
          "tgn:2000115",
          "tgn:7012149",
          "tgn:7029392"
        ],
        "placetype": [
          "aat:300008706"
        ],
        "id": 2400012,
        "name:xx": "Horse Creek"
      }
    },
    {
      "geometry": {
        "type": "Point",
        "coordinates": [
          -92.9833,
          35.85
        ]
      },
      "type": "Feature",
      "properties": {
        "hierarchy": [
          "tgn:2400013",
          "tgn:1000001",
          "tgn:7016172",
          "tgn:7012149",
          "tgn:2000155",
          "tgn:7029392"
        ],
        "placetype": [
          "aat:300008706"
        ],
        "id": 2400013,
        "name:xx": "Horse Creek"
      }
    },
    {
      "geometry": {
        "type": "Point",
        "coordinates": [
          -123.6333,
          40.3667
        ]
      },
      "type": "Feature",
      "properties": {
        "hierarchy": [
          "tgn:2400014",
          "tgn:1000001",
          "tgn:7012149",
          "tgn:2000181",
          "tgn:7007157",
          "tgn:7029392"
        ],
        "placetype": [
          "aat:300008706"
        ],
        "id": 2400014,
        "name:xx": "Horse Creek"
      }
    },
    {
      "geometry": {
        "type": "Point",
        "coordinates": [
          -122.0333,
          41.0167
        ]
      },
      "type": "Feature",
      "properties": {
        "hierarchy": [
          "tgn:2400015",
          "tgn:1000001",
          "tgn:7012149",
          "tgn:7007157",
          "tgn:2000188",
          "tgn:7029392"
        ],
        "placetype": [
          "aat:300008706"
        ],
        "id": 2400015,
        "name:xx": "Horse Creek"
      }
    },
    {
      "geometry": {
        "type": "Point",
        "coordinates": [
          -123.2333,
          41.1667
        ]
      },
      "type": "Feature",
      "properties": {
        "hierarchy": [
          "tgn:2400016",
          "tgn:1000001",
          "tgn:7012149",
          "tgn:7007157",
          "tgn:2000189",
          "tgn:7029392"
        ],
        "placetype": [
          "aat:300008706"
        ],
        "id": 2400016,
        "name:xx": "Horse Creek"
      }
    },
    {
      "geometry": {
        "type": "Point",
        "coordinates": [
          -122.7167,
          41.1833
        ]
      },
      "type": "Feature",
      "properties": {
        "hierarchy": [
          "tgn:2400017",
          "tgn:1000001",
          "tgn:7012149",
          "tgn:7007157",
          "tgn:2000191",
          "tgn:7029392"
        ],
        "placetype": [
          "aat:300008706"
        ],
        "id": 2400017,
        "name:xx": "Horse Creek"
      }
    },
    {
      "geometry": {
        "type": "Point",
        "coordinates": [
          -123.8667,
          41.6333
        ]
      },
      "type": "Feature",
      "properties": {
        "hierarchy": [
          "tgn:2400018",
          "tgn:1000001",
          "tgn:7012149",
          "tgn:2000180",
          "tgn:7007157",
          "tgn:7029392"
        ],
        "placetype": [
          "aat:300008706"
        ],
        "id": 2400018,
        "name:xx": "Horse Creek"
      }
    },
    {
      "geometry": {
        "type": "Point",
        "coordinates": [
          -119.9,
          37.4
        ]
      },
      "type": "Feature",
      "properties": {
        "hierarchy": [
          "tgn:2400019",
          "tgn:1000001",
          "tgn:7012149",
          "tgn:7007157",
          "tgn:7014004",
          "tgn:7029392"
        ],
        "placetype": [
          "aat:300008706"
        ],
        "id": 2400019,
        "name:xx": "Horse Creek"
      }
    }
  ]
}
