{
  "geometry": {
    "type": "Point",
    "coordinates": [
      -86.75,
      33.5833
    ]
  },
  "type": "Feature",
  "properties": {
    "hierarchy": [
      "tgn:2187803",
      "tgn:7002659",
      "tgn:1000001",
      "tgn:7012149",
      "tgn:2000036",
      "tgn:7029392"
    ],
    "placetype": [
      "aat:300008746"
    ],
    "id": 2187803,
    "name:xx": "Bootleggers Cave"
  }
}
