{
  "geometry": {
    "type": "Point",
    "coordinates": [
      -109.5667,
      33.8833
    ]
  },
  "type": "Feature",
  "properties": {
    "hierarchy": [
      "tgn:1132419",
      "tgn:1000001",
      "tgn:7006451",
      "tgn:7012149",
      "tgn:7029392"
    ],
    "placetype": [
      "aat:300008706"
    ],
    "id": 1132419,
    "name:xx": "Big Bonito Creek"
  }
}
