{
  "geometry": {
    "type": "Point",
    "coordinates": [
      78.404446,
      24.84349
    ]
  },
  "type": "Feature",
  "properties": {
    "hierarchy": [
      "tgn:7582061",
      "tgn:1000004",
      "tgn:7000198",
      "tgn:7016722",
      "tgn:7029392"
    ],
    "placetype": [
      "aat:300008347"
    ],
    "name:en": "Arwāho",
    "id": 7582061
  }
}
