{
  "geometry": {
    "type": "Point",
    "coordinates": [
      -73.0167,
      42.5667
    ]
  },
  "type": "Feature",
  "properties": {
    "hierarchy": [
      "tgn:1131725",
      "tgn:1000001",
      "tgn:7012149",
      "tgn:7007517",
      "tgn:7029392"
    ],
    "placetype": [
      "aat:300008707"
    ],
    "id": 1131725,
    "name:xx": "Westfield"
  }
}
