{
  "geometry": {
    "type": "Point",
    "coordinates": [
      -124.4667,
      47.7333
    ]
  },
  "type": "Feature",
  "properties": {
    "hierarchy": [
      "tgn:2549255",
      "tgn:1000001",
      "tgn:7012149",
      "tgn:1002521",
      "tgn:7007920",
      "tgn:7029392"
    ],
    "placetype": [
      "aat:300132348"
    ],
    "id": 2549255,
    "name:xx": "North Rock"
  }
}
