{
  "geometry": {
    "type": "Point",
    "coordinates": [
      -110.0833,
      33.9333
    ]
  },
  "type": "Feature",
  "properties": {
    "hierarchy": [
      "tgn:2408969",
      "tgn:1000001",
      "tgn:7006451",
      "tgn:2000093",
      "tgn:7012149",
      "tgn:7029392"
    ],
    "placetype": [
      "aat:300008697"
    ],
    "id": 2408969,
    "name:xx": "I-nineteen Springs"
  }
}
