{
  "geometry": {
    "type": "Point",
    "coordinates": [
      74.841235,
      32.69481
    ]
  },
  "type": "Feature",
  "properties": {
    "hierarchy": [
      "tgn:7592030",
      "tgn:1000004",
      "tgn:7000198",
      "tgn:7000799",
      "tgn:7029392"
    ],
    "placetype": [
      "aat:300008347"
    ],
    "name:en": "Satwāri",
    "id": 7592030
  }
}
