{
  "type": "FeatureCollection",
  "features": [
    {
      "geometry": {
        "type": "Point",
        "coordinates": [
          -87.1667,
          34.4
        ]
      },
      "type": "Feature",
      "properties": {
        "hierarchy": [
          "tgn:2201330",
          "tgn:7002659",
          "tgn:1000001",
          "tgn:7012149",
          "tgn:2000039",
          "tgn:7029392"
        ],
        "placetype": [
          "aat:300008699"
        ],
        "id": 2201330,
        "name:xx": "Buck Branch"
      }
    },
    {
      "geometry": {
        "type": "Point",
        "coordinates": [
          -88.0333,
          34.8167
        ]
      },
      "type": "Feature",
      "properties": {
        "hierarchy": [
          "tgn:2201331",
          "tgn:7002659",
          "tgn:1000001",
          "tgn:2000016",
          "tgn:7012149",
          "tgn:7029392"
        ],
        "placetype": [
          "aat:300008699"
        ],
        "id": 2201331,
        "name:xx": "Buck Branch"
      }
    },
    {
      "geometry": {
        "type": "Point",
        "coordinates": [
          -85.6667,
          31.6167
        ]
      },
      "type": "Feature",
      "properties": {
        "hierarchy": [
          "tgn:2201332",
          "tgn:7002659",
          "tgn:1000001",
          "tgn:7012149",
          "tgn:7029392"
        ],
        "placetype": [
          "aat:300008699"
        ],
        "id": 2201332,
        "name:xx": "Buck Branch"
      }
    },
    {
      "geometry": {
        "type": "Point",
        "coordinates": [
          -86.7333,
          34.2667
        ]
      },
      "type": "Feature",
      "properties": {
        "hierarchy": [
          "tgn:2201333",
          "tgn:7002659",
          "tgn:1000001",
          "tgn:7012149",
          "tgn:2000021",
          "tgn:7029392"
        ],
        "placetype": [
          "aat:300008699"
        ],
        "id": 2201333,
        "name:xx": "Buck Branch"
      }
    },
    {
      "geometry": {
        "type": "Point",
        "coordinates": [
          -86,
          31.3833
        ]
      },
      "type": "Feature",
      "properties": {
        "hierarchy": [
          "tgn:2201334",
          "tgn:7002659",
          "tgn:1000001",
          "tgn:2000015",
          "tgn:7012149",
          "tgn:7029392"
        ],
        "placetype": [
          "aat:300008699"
        ],
        "id": 2201334,
        "name:xx": "Buck Branch"
      }
    },
    {
      "geometry": {
        "type": "Point",
        "coordinates": [
          -93.8667,
          34.3333
        ]
      },
      "type": "Feature",
      "properties": {
        "hierarchy": [
          "tgn:2201335",
          "tgn:1000001",
          "tgn:7016172",
          "tgn:7012149",
          "tgn:2000159",
          "tgn:7029392"
        ],
        "placetype": [
          "aat:300008699"
        ],
        "id": 2201335,
        "name:xx": "Buck Branch"
      }
    },
    {
      "geometry": {
        "type": "Point",
        "coordinates": [
          -92.7333,
          34.3167
        ]
      },
      "type": "Feature",
      "properties": {
        "hierarchy": [
          "tgn:2201336",
          "tgn:1000001",
          "tgn:7016172",
          "tgn:7012149",
          "tgn:7029392"
        ],
        "placetype": [
          "aat:300008699"
        ],
        "id": 2201336,
        "name:xx": "Buck Branch"
      }
    },
    {
      "geometry": {
        "type": "Point",
        "coordinates": [
          -91.4333,
          34.7333
        ]
      },
      "type": "Feature",
      "properties": {
        "hierarchy": [
          "tgn:2201337",
          "tgn:1000001",
          "tgn:7016172",
          "tgn:7012149",
          "tgn:2000163",
          "tgn:7029392"
        ],
        "placetype": [
          "aat:300008699"
        ],
        "id": 2201337,
        "name:xx": "Buck Branch"
      }
    },
    {
      "geometry": {
        "type": "Point",
        "coordinates": [
          -91.8333,
          33.2667
        ]
      },
      "type": "Feature",
      "properties": {
        "hierarchy": [
          "tgn:2201338",
          "tgn:2000106",
          "tgn:1000001",
          "tgn:7016172",
          "tgn:7012149",
          "tgn:7029392"
        ],
        "placetype": [
          "aat:300008699"
        ],
        "id": 2201338,
        "name:xx": "Buck Branch"
      }
    },
    {
      "geometry": {
        "type": "Point",
        "coordinates": [
          -92.5833,
          35.35
        ]
      },
      "type": "Feature",
      "properties": {
        "hierarchy": [
          "tgn:2201339",
          "tgn:1000001",
          "tgn:7016172",
          "tgn:2000119",
          "tgn:7012149",
          "tgn:7029392"
        ],
        "placetype": [
          "aat:300008699"
        ],
        "id": 2201339,
        "name:xx": "Buck Branch"
      }
    }
  ]
}
