{
  "geometry": {
    "type": "Point",
    "coordinates": [
      -50.4667,
      -1.1167
    ]
  },
  "type": "Feature",
  "properties": {
    "hierarchy": [
      "tgn:1022875",
      "tgn:7006247",
      "tgn:1000047",
      "tgn:7002456",
      "tgn:1000002",
      "tgn:7029392"
    ],
    "placetype": [
      "aat:300008347"
    ],
    "id": 1022875,
    "name:xx": "São Miguel dos Macacos"
  }
}
