{
  "geometry": {
    "type": "Point",
    "coordinates": [
      -88.0667,
      40.15
    ]
  },
  "type": "Feature",
  "properties": {
    "hierarchy": [
      "tgn:2691201",
      "tgn:1000001",
      "tgn:1002253",
      "tgn:7012149",
      "tgn:7007251",
      "tgn:7029392"
    ],
    "placetype": [
      "aat:300006075"
    ],
    "id": 2691201,
    "name:xx": "Stanton Special Drainage Ditch"
  }
}
