{
  "geometry": {
    "type": "Point",
    "coordinates": [
      36.25,
      6.3167
    ]
  },
  "type": "Feature",
  "properties": {
    "hierarchy": [
      "tgn:1089790",
      "tgn:7001242",
      "tgn:1001260",
      "tgn:7000489",
      "tgn:7029392"
    ],
    "placetype": [
      "aat:300008347"
    ],
    "id": 1089790,
    "name:xx": "Dimē"
  }
}
