{
  "geometry": {
    "type": "Point",
    "coordinates": [
      30.75,
      28.116667
    ]
  },
  "type": "Feature",
  "properties": {
    "hierarchy": [
      "tgn:7520425",
      "tgn:7001242",
      "tgn:7016833",
      "tgn:1001088",
      "tgn:7029392"
    ],
    "placetype": [
      "aat:300008347"
    ],
    "name:en": "Al Ikhşāş",
    "id": 7520425
  }
}
