{
  "type": "FeatureCollection",
  "features": [
    {
      "geometry": {
        "type": "Point",
        "coordinates": [
          -85.3333,
          39.9833
        ]
      },
      "type": "Feature",
      "properties": {
        "hierarchy": [
          "tgn:2612170",
          "tgn:1000001",
          "tgn:7012149",
          "tgn:1002468",
          "tgn:7007252",
          "tgn:7029392"
        ],
        "placetype": [
          "aat:300008699"
        ],
        "id": 2612170,
        "name:xx": "Red Run"
      }
    },
    {
      "geometry": {
        "type": "Point",
        "coordinates": [
          -79.35,
          39.4833
        ]
      },
      "type": "Feature",
      "properties": {
        "hierarchy": [
          "tgn:2612171",
          "tgn:1000001",
          "tgn:2000935",
          "tgn:7012149",
          "tgn:7007516",
          "tgn:7029392"
        ],
        "placetype": [
          "aat:300008699"
        ],
        "id": 2612171,
        "name:xx": "Red Run"
      }
    },
    {
      "geometry": {
        "type": "Point",
        "coordinates": [
          -85.65,
          42.7333
        ]
      },
      "type": "Feature",
      "properties": {
        "hierarchy": [
          "tgn:2612172",
          "tgn:1002140",
          "tgn:1000001",
          "tgn:7012149",
          "tgn:7007520",
          "tgn:7029392"
        ],
        "placetype": [
          "aat:300008699"
        ],
        "id": 2612172,
        "name:xx": "Red Run"
      }
    },
    {
      "geometry": {
        "type": "Point",
        "coordinates": [
          -78.2167,
          34.0833
        ]
      },
      "type": "Feature",
      "properties": {
        "hierarchy": [
          "tgn:2612173",
          "tgn:1000001",
          "tgn:2001472",
          "tgn:7012149",
          "tgn:7007709",
          "tgn:7029392"
        ],
        "placetype": [
          "aat:300008699"
        ],
        "id": 2612173,
        "name:xx": "Red Run"
      }
    },
    {
      "geometry": {
        "type": "Point",
        "coordinates": [
          -82.8333,
          40.9167
        ]
      },
      "type": "Feature",
      "properties": {
        "hierarchy": [
          "tgn:2612174",
          "tgn:1000001",
          "tgn:1002307",
          "tgn:7012149",
          "tgn:7007706",
          "tgn:7029392"
        ],
        "placetype": [
          "aat:300008699"
        ],
        "id": 2612174,
        "name:xx": "Red Run"
      }
    },
    {
      "geometry": {
        "type": "Point",
        "coordinates": [
          -81.65,
          40.9
        ]
      },
      "type": "Feature",
      "properties": {
        "hierarchy": [
          "tgn:2612175",
          "tgn:1000001",
          "tgn:7012149",
          "tgn:1003007",
          "tgn:7007706",
          "tgn:7029392"
        ],
        "placetype": [
          "aat:300008699"
        ],
        "id": 2612175,
        "name:xx": "Red Run"
      }
    },
    {
      "geometry": {
        "type": "Point",
        "coordinates": [
          -76.0667,
          40.1833
        ]
      },
      "type": "Feature",
      "properties": {
        "hierarchy": [
          "tgn:2612177",
          "tgn:1000001",
          "tgn:7012149",
          "tgn:7013867",
          "tgn:7007710",
          "tgn:7029392"
        ],
        "placetype": [
          "aat:300008347"
        ],
        "id": 2612177,
        "name:xx": "Red Run"
      }
    },
    {
      "geometry": {
        "type": "Point",
        "coordinates": [
          -77.5167,
          39.8167
        ]
      },
      "type": "Feature",
      "properties": {
        "hierarchy": [
          "tgn:2612178",
          "tgn:1000001",
          "tgn:7012149",
          "tgn:1002387",
          "tgn:7007710",
          "tgn:7029392"
        ],
        "placetype": [
          "aat:300008699"
        ],
        "id": 2612178,
        "name:xx": "Red Run"
      }
    },
    {
      "geometry": {
        "type": "Point",
        "coordinates": [
          -78.9167,
          40.4
        ]
      },
      "type": "Feature",
      "properties": {
        "hierarchy": [
          "tgn:2612179",
          "tgn:1000001",
          "tgn:1002225",
          "tgn:7012149",
          "tgn:7007710",
          "tgn:7029392"
        ],
        "placetype": [
          "aat:300008699"
        ],
        "id": 2612179,
        "name:xx": "Red Run"
      }
    }
  ]
}
