{
  "geometry": {
    "type": "Point",
    "coordinates": [
      -75.4833,
      39.0167
    ]
  },
  "type": "Feature",
  "properties": {
    "hierarchy": [
      "tgn:2686280",
      "tgn:1002538",
      "tgn:1000001",
      "tgn:7012149",
      "tgn:7007239",
      "tgn:7029392"
    ],
    "placetype": [
      "aat:300008706"
    ],
    "id": 2686280,
    "name:xx": "Spring Creek"
  }
}
