{
  "type": "FeatureCollection",
  "features": [
    {
      "geometry": {
        "type": "Point",
        "coordinates": [
          -110.9667,
          34.8167
        ]
      },
      "type": "Feature",
      "properties": {
        "hierarchy": [
          "tgn:2214910",
          "tgn:1000001",
          "tgn:7006451",
          "tgn:2000092",
          "tgn:7012149",
          "tgn:7029392"
        ],
        "placetype": [
          "aat:300006191"
        ],
        "id": 2214910,
        "name:xx": "Caliche Tank"
      }
    },
    {
      "geometry": {
        "type": "Point",
        "coordinates": [
          -106.8833,
          32.7333
        ]
      },
      "type": "Feature",
      "properties": {
        "hierarchy": [
          "tgn:2214911",
          "tgn:1000001",
          "tgn:2001435",
          "tgn:7012149",
          "tgn:7007566",
          "tgn:7029392"
        ],
        "placetype": [
          "aat:300006191"
        ],
        "id": 2214911,
        "name:xx": "Caliche Tank"
      }
    },
    {
      "geometry": {
        "type": "Point",
        "coordinates": [
          -107.35,
          33.8333
        ]
      },
      "type": "Feature",
      "properties": {
        "hierarchy": [
          "tgn:2214912",
          "tgn:1000001",
          "tgn:7012149",
          "tgn:2001456",
          "tgn:7007566",
          "tgn:7029392"
        ],
        "placetype": [
          "aat:300006191"
        ],
        "id": 2214912,
        "name:xx": "Caliche Tank"
      }
    },
    {
      "geometry": {
        "type": "Point",
        "coordinates": [
          -98.25,
          28.1833
        ]
      },
      "type": "Feature",
      "properties": {
        "hierarchy": [
          "tgn:2214913",
          "tgn:1000001",
          "tgn:7012149",
          "tgn:2002029",
          "tgn:7007826",
          "tgn:7029392"
        ],
        "placetype": [
          "aat:300006191"
        ],
        "id": 2214913,
        "name:xx": "Caliche Tank"
      }
    },
    {
      "geometry": {
        "type": "Point",
        "coordinates": [
          -100.8833,
          32.05
        ]
      },
      "type": "Feature",
      "properties": {
        "hierarchy": [
          "tgn:2214914",
          "tgn:1000001",
          "tgn:7012149",
          "tgn:2002077",
          "tgn:7007826",
          "tgn:7029392"
        ],
        "placetype": [
          "aat:300006191"
        ],
        "id": 2214914,
        "name:xx": "Caliche Tank"
      }
    },
    {
      "geometry": {
        "type": "Point",
        "coordinates": [
          -100.3667,
          28.8833
        ]
      },
      "type": "Feature",
      "properties": {
        "hierarchy": [
          "tgn:2214915",
          "tgn:1000001",
          "tgn:7012149",
          "tgn:2002038",
          "tgn:7007826",
          "tgn:7029392"
        ],
        "placetype": [
          "aat:300006191"
        ],
        "id": 2214915,
        "name:xx": "Caliche Tank"
      }
    },
    {
      "geometry": {
        "type": "Point",
        "coordinates": [
          -99.9167,
          28.9667
        ]
      },
      "type": "Feature",
      "properties": {
        "hierarchy": [
          "tgn:2214916",
          "tgn:1000001",
          "tgn:7012149",
          "tgn:2002100",
          "tgn:7007826",
          "tgn:7029392"
        ],
        "placetype": [
          "aat:300006191"
        ],
        "id": 2214916,
        "name:xx": "Caliche Tank"
      }
    },
    {
      "geometry": {
        "type": "Point",
        "coordinates": [
          -99.75,
          29.0833
        ]
      },
      "type": "Feature",
      "properties": {
        "hierarchy": [
          "tgn:2214917",
          "tgn:1000001",
          "tgn:7012149",
          "tgn:2002087",
          "tgn:7007826",
          "tgn:7029392"
        ],
        "placetype": [
          "aat:300006191"
        ],
        "id": 2214917,
        "name:xx": "Caliche Tank"
      }
    },
    {
      "geometry": {
        "type": "Point",
        "coordinates": [
          -105.8333,
          31.4667
        ]
      },
      "type": "Feature",
      "properties": {
        "hierarchy": [
          "tgn:2214918",
          "tgn:1000001",
          "tgn:7012149",
          "tgn:2002005",
          "tgn:7007826",
          "tgn:7029392"
        ],
        "placetype": [
          "aat:300006191"
        ],
        "id": 2214918,
        "name:xx": "Caliche Tank"
      }
    },
    {
      "geometry": {
        "type": "Point",
        "coordinates": [
          -102.3,
          35.4833
        ]
      },
      "type": "Feature",
      "properties": {
        "hierarchy": [
          "tgn:2214919",
          "tgn:1000001",
          "tgn:7012149",
          "tgn:2002051",
          "tgn:7007826",
          "tgn:7029392"
        ],
        "placetype": [
          "aat:300006191"
        ],
        "id": 2214919,
        "name:xx": "Caliche Tank"
      }
    }
  ]
}
