{
  "geometry": {
    "type": "Point",
    "coordinates": [
      -106.35,
      45.2667
    ]
  },
  "type": "Feature",
  "properties": {
    "hierarchy": [
      "tgn:2609884",
      "tgn:1000001",
      "tgn:7012149",
      "tgn:2001303",
      "tgn:7007524",
      "tgn:7029392"
    ],
    "placetype": [
      "aat:300006191"
    ],
    "id": 2609884,
    "name:xx": "Reavis Reservoir"
  }
}
