{
  "geometry": {
    "type": "Point",
    "coordinates": [
      -115.7167,
      43.4833
    ]
  },
  "type": "Feature",
  "properties": {
    "hierarchy": [
      "tgn:2168841",
      "tgn:1000001",
      "tgn:7012149",
      "tgn:2000471",
      "tgn:7007250",
      "tgn:7029392"
    ],
    "placetype": [
      "aat:300008706"
    ],
    "id": 2168841,
    "name:xx": "Big Horse Creek"
  }
}
