{
  "geometry": {
    "type": "Point",
    "coordinates": [
      109.15,
      18.7167
    ]
  },
  "type": "Feature",
  "properties": {
    "hierarchy": [
      "tgn:1069709",
      "tgn:1000004",
      "tgn:7001800",
      "tgn:1000111",
      "tgn:7029392"
    ],
    "placetype": [
      "aat:300008347"
    ],
    "id": 1069709,
    "name:xx": "Ledong"
  }
}
