{
  "geometry": {
    "type": "Point",
    "coordinates": [
      115.1667,
      22.6667
    ]
  },
  "type": "Feature",
  "properties": {
    "hierarchy": [
      "tgn:1113144",
      "tgn:1000004",
      "tgn:7005232",
      "tgn:1000111",
      "tgn:7029392"
    ],
    "placetype": [
      "aat:300132316"
    ],
    "id": 1113144,
    "name:xx": "Honghai Wan"
  }
}
