{
  "geometry": {
    "type": "Point",
    "coordinates": [
      24.1667,
      60.5333
    ]
  },
  "type": "Feature",
  "properties": {
    "hierarchy": [
      "tgn:1031349",
      "tgn:1000003",
      "tgn:7594395",
      "tgn:1000069",
      "tgn:7029392"
    ],
    "placetype": [
      "aat:300008347"
    ],
    "id": 1031349,
    "name:xx": "Karkkila"
  }
}
