{
  "geometry": {
    "type": "Point",
    "coordinates": [
      32.100015,
      29.60972
    ]
  },
  "type": "Feature",
  "properties": {
    "hierarchy": [
      "tgn:7544235",
      "tgn:7001242",
      "tgn:7016833",
      "tgn:1001110",
      "tgn:7029392"
    ],
    "placetype": [
      "aat:300379998"
    ],
    "id": 7544235,
    "name:xx": "Ab큰 Diy훮bah, W훮d카"
  }
}
