{
  "geometry": {
    "type": "Point",
    "coordinates": [
      -117.4333,
      43.2167
    ]
  },
  "type": "Feature",
  "properties": {
    "hierarchy": [
      "tgn:2241844",
      "tgn:1000001",
      "tgn:7012149",
      "tgn:2001718",
      "tgn:7007708",
      "tgn:7029392"
    ],
    "placetype": [
      "aat:300006191"
    ],
    "id": 2241844,
    "name:xx": "Claude Reservoir"
  }
}
