{
  "type": "FeatureCollection",
  "features": [
    {
      "geometry": {
        "type": "Point",
        "coordinates": [
          99.9833,
          54.6
        ]
      },
      "type": "Feature",
      "properties": {
        "hierarchy": [
          "tgn:1051590",
          "tgn:1003373",
          "tgn:1000004",
          "tgn:7018214",
          "tgn:7002435",
          "tgn:7029392"
        ],
        "placetype": [
          "aat:300008347"
        ],
        "id": 1051590,
        "name:xx": "Sheberta"
      }
    },
    {
      "geometry": {
        "type": "Point",
        "coordinates": [
          141.8333,
          46.4
        ]
      },
      "type": "Feature",
      "properties": {
        "hierarchy": [
          "tgn:1051591",
          "tgn:7019034",
          "tgn:1000004",
          "tgn:1003406",
          "tgn:7018214",
          "tgn:7002435",
          "tgn:7029392"
        ],
        "placetype": [
          "aat:300008347"
        ],
        "id": 1051591,
        "name:xx": "Shebunino"
      }
    },
    {
      "geometry": {
        "type": "Point",
        "coordinates": [
          40.45,
          52.5333
        ]
      },
      "type": "Feature",
      "properties": {
        "hierarchy": [
          "tgn:1051592",
          "tgn:1000004",
          "tgn:1003417",
          "tgn:7018214",
          "tgn:7002435",
          "tgn:7029392"
        ],
        "placetype": [
          "aat:300008347"
        ],
        "id": 1051592,
        "name:xx": "Shekhman"
      }
    },
    {
      "geometry": {
        "type": "Point",
        "coordinates": [
          40.8333,
          44.2167
        ]
      },
      "type": "Feature",
      "properties": {
        "hierarchy": [
          "tgn:1051593",
          "tgn:1000004",
          "tgn:7011531",
          "tgn:7018214",
          "tgn:7002435",
          "tgn:7029392"
        ],
        "placetype": [
          "aat:300008347"
        ],
        "id": 1051593,
        "name:xx": "Shedok"
      }
    },
    {
      "geometry": {
        "type": "Point",
        "coordinates": [
          23.7667,
          55.7
        ]
      },
      "type": "Feature",
      "properties": {
        "hierarchy": [
          "tgn:1051594",
          "tgn:1000003",
          "tgn:7006600",
          "tgn:7006542",
          "tgn:7029392"
        ],
        "placetype": [
          "aat:300008347"
        ],
        "id": 1051594,
        "name:xx": "Šeduva"
      }
    },
    {
      "geometry": {
        "type": "Point",
        "coordinates": [
          49.3,
          64.6667
        ]
      },
      "type": "Feature",
      "properties": {
        "hierarchy": [
          "tgn:1051595",
          "tgn:4000818",
          "tgn:1000004",
          "tgn:7018214",
          "tgn:7002435",
          "tgn:7029392"
        ],
        "placetype": [
          "aat:300008347"
        ],
        "id": 1051595,
        "name:xx": "Shegmas"
      }
    },
    {
      "geometry": {
        "type": "Point",
        "coordinates": [
          42.9833,
          62.3833
        ]
      },
      "type": "Feature",
      "properties": {
        "hierarchy": [
          "tgn:1051596",
          "tgn:4000818",
          "tgn:1000004",
          "tgn:7018214",
          "tgn:7002435",
          "tgn:7029392"
        ],
        "placetype": [
          "aat:300008347"
        ],
        "id": 1051596,
        "name:xx": "Shegovary"
      }
    },
    {
      "geometry": {
        "type": "Point",
        "coordinates": [
          43.2,
          53.3667
        ]
      },
      "type": "Feature",
      "properties": {
        "hierarchy": [
          "tgn:1051597",
          "tgn:1000004",
          "tgn:1003399",
          "tgn:7018214",
          "tgn:7002435",
          "tgn:7029392"
        ],
        "placetype": [
          "aat:300008347"
        ],
        "id": 1051597,
        "name:xx": "Sheyno"
      }
    },
    {
      "geometry": {
        "type": "Point",
        "coordinates": [
          45.1833,
          58.35
        ]
      },
      "type": "Feature",
      "properties": {
        "hierarchy": [
          "tgn:1051598",
          "tgn:1000004",
          "tgn:4005827",
          "tgn:7018214",
          "tgn:7002435",
          "tgn:7029392"
        ],
        "placetype": [
          "aat:300008347"
        ],
        "id": 1051598,
        "name:xx": "Shekshema"
      }
    },
    {
      "geometry": {
        "type": "Point",
        "coordinates": [
          47.1667,
          41.2
        ]
      },
      "type": "Feature",
      "properties": {
        "hierarchy": [
          "tgn:1051599",
          "tgn:7011438",
          "tgn:1000004",
          "tgn:7006646",
          "tgn:7029392"
        ],
        "placetype": [
          "aat:300008347"
        ],
        "name:en": "Saki",
        "id": 1051599
      }
    }
  ]
}
