{
  "geometry": {
    "type": "Point",
    "coordinates": [
      53.95,
      43.7167
    ]
  },
  "type": "Feature",
  "properties": {
    "hierarchy": [
      "tgn:1108073",
      "tgn:1000004",
      "tgn:7012911",
      "tgn:7014786",
      "tgn:7029392"
    ],
    "placetype": [
      "aat:300008777"
    ],
    "id": 1108073,
    "name:xx": "Kil'baj, gora"
  }
}
