{
  "geometry": {
    "type": "Point",
    "coordinates": [
      -58.7667,
      -17.95
    ]
  },
  "type": "Feature",
  "properties": {
    "hierarchy": [
      "tgn:1020429",
      "tgn:1000752",
      "tgn:1000046",
      "tgn:1000002",
      "tgn:7029392"
    ],
    "placetype": [
      "aat:300008347"
    ],
    "id": 1020429,
    "name:xx": "Santo Corazón"
  }
}
