{
  "geometry": {
    "type": "Point",
    "coordinates": [
      -56.25,
      5.583
    ]
  },
  "type": "Feature",
  "properties": {
    "hierarchy": [
      "tgn:1000831",
      "tgn:1000002",
      "tgn:7015386",
      "tgn:7029392"
    ],
    "placetype": [
      "aat:300387064",
      "aat:300387081"
    ],
    "id": 1000831,
    "name:xx": "Coronie"
  }
}
