{
  "geometry": {
    "type": "Point",
    "coordinates": [
      107.8333,
      15.6667
    ]
  },
  "type": "Feature",
  "properties": {
    "hierarchy": [
      "tgn:7001056",
      "tgn:1000004",
      "tgn:1000145",
      "tgn:7029392"
    ],
    "placetype": [
      "aat:300387064",
      "aat:300000774"
    ],
    "id": 7001056,
    "name:xx": "Quảng Nam-Ḍà Nẵng, Tỉnh"
  }
}
