{
  "geometry": {
    "type": "Point",
    "coordinates": [
      -9.75,
      10.15
    ]
  },
  "type": "Feature",
  "properties": {
    "hierarchy": [
      "tgn:1125729",
      "tgn:7001242",
      "tgn:1000167",
      "tgn:7029392"
    ],
    "placetype": [
      "aat:300008707"
    ],
    "id": 1125729,
    "name:xx": "Kouya"
  }
}
