{
  "geometry": {
    "type": "Point",
    "coordinates": [
      -78.3333,
      39.2833
    ]
  },
  "type": "Feature",
  "properties": {
    "hierarchy": [
      "tgn:2168750",
      "tgn:1000001",
      "tgn:7012149",
      "tgn:2002161",
      "tgn:7007919",
      "tgn:7029392"
    ],
    "placetype": [
      "aat:300008761"
    ],
    "id": 2168750,
    "name:xx": "Big Hollow"
  }
}
