{
  "type": "FeatureCollection",
  "features": [
    {
      "geometry": {
        "type": "Point",
        "coordinates": [
          4.283333,
          51.2
        ]
      },
      "type": "Feature",
      "properties": {
        "hierarchy": [
          "tgn:7239272",
          "tgn:7003457",
          "tgn:1000003",
          "tgn:1000063",
          "tgn:7018236",
          "tgn:7029392"
        ],
        "placetype": [
          "aat:300008347"
        ],
        "id": 7239272,
        "name:xx": "Gentstraat"
      }
    },
    {
      "geometry": {
        "type": "Point",
        "coordinates": [
          3.633333,
          51.183333
        ]
      },
      "type": "Feature",
      "properties": {
        "hierarchy": [
          "tgn:7239273",
          "tgn:7003457",
          "tgn:1000003",
          "tgn:1000063",
          "tgn:7018236",
          "tgn:7029392"
        ],
        "placetype": [
          "aat:300008347"
        ],
        "id": 7239273,
        "name:xx": "Gentstraat"
      }
    },
    {
      "geometry": {
        "type": "Point",
        "coordinates": [
          4.1,
          51.166667
        ]
      },
      "type": "Feature",
      "properties": {
        "hierarchy": [
          "tgn:7239274",
          "tgn:7003457",
          "tgn:1000003",
          "tgn:1000063",
          "tgn:7018236",
          "tgn:7029392"
        ],
        "placetype": [
          "aat:300008347"
        ],
        "id": 7239274,
        "name:xx": "Gentstraat"
      }
    },
    {
      "geometry": {
        "type": "Point",
        "coordinates": [
          3.733333,
          51.066667
        ]
      },
      "type": "Feature",
      "properties": {
        "hierarchy": [
          "tgn:7239275",
          "tgn:7003457",
          "tgn:1000003",
          "tgn:1000063",
          "tgn:7018236",
          "tgn:7029392"
        ],
        "placetype": [
          "aat:300006075"
        ],
        "id": 7239275,
        "name:xx": "Kanaal van Gent naar Terneuzen"
      }
    },
    {
      "geometry": {
        "type": "Point",
        "coordinates": [
          4.566667,
          50.566667
        ]
      },
      "type": "Feature",
      "properties": {
        "hierarchy": [
          "tgn:7239276",
          "tgn:7003466",
          "tgn:1000003",
          "tgn:1000063",
          "tgn:4012014",
          "tgn:7029392"
        ],
        "placetype": [
          "aat:300008347"
        ],
        "id": 7239276,
        "name:xx": "Gentissart"
      }
    },
    {
      "geometry": {
        "type": "Point",
        "coordinates": [
          4.616667,
          50.616667
        ]
      },
      "type": "Feature",
      "properties": {
        "hierarchy": [
          "tgn:7239277",
          "tgn:7003466",
          "tgn:1000003",
          "tgn:1000063",
          "tgn:4012014",
          "tgn:7029392"
        ],
        "placetype": [
          "aat:300008699"
        ],
        "id": 7239277,
        "name:xx": "Gentinnes"
      }
    },
    {
      "geometry": {
        "type": "Point",
        "coordinates": [
          4.6,
          50.583333
        ]
      },
      "type": "Feature",
      "properties": {
        "hierarchy": [
          "tgn:7239278",
          "tgn:7018238",
          "tgn:1000003",
          "tgn:1000063",
          "tgn:4012014",
          "tgn:7029392"
        ],
        "placetype": [
          "aat:300008347"
        ],
        "id": 7239278,
        "name:xx": "Gentinnes"
      }
    }
  ]
}
