{
  "geometry": {
    "type": "Point",
    "coordinates": [
      39.05,
      9.65
    ]
  },
  "type": "Feature",
  "properties": {
    "hierarchy": [
      "tgn:1089976",
      "tgn:7001242",
      "tgn:1001535",
      "tgn:7000489",
      "tgn:7029392"
    ],
    "placetype": [
      "aat:300008347"
    ],
    "id": 1089976,
    "name:xx": "Weberī Bekera"
  }
}
