{
  "geometry": {
    "type": "Point",
    "coordinates": [
      -68.7167,
      46.75
    ]
  },
  "type": "Feature",
  "properties": {
    "hierarchy": [
      "tgn:2222782",
      "tgn:2000919",
      "tgn:1000001",
      "tgn:7012149",
      "tgn:7007515",
      "tgn:7029392"
    ],
    "placetype": [
      "aat:300008680"
    ],
    "id": 2222782,
    "name:xx": "Carr Pond"
  }
}
