{
  "geometry": {
    "type": "Point",
    "coordinates": [
      14.9833,
      44.8167
    ]
  },
  "type": "Feature",
  "properties": {
    "hierarchy": [
      "tgn:1105508",
      "tgn:7017300",
      "tgn:1000003",
      "tgn:7006663",
      "tgn:7029392"
    ],
    "placetype": [
      "aat:300008795"
    ],
    "id": 1105508,
    "name:xx": "Mali Rajinac"
  }
}
