{
  "geometry": {
    "type": "Point",
    "coordinates": [
      -93.7667,
      37.0167
    ]
  },
  "type": "Feature",
  "properties": {
    "hierarchy": [
      "tgn:2559628",
      "tgn:1000001",
      "tgn:7012149",
      "tgn:2001213",
      "tgn:7007523",
      "tgn:7029392"
    ],
    "placetype": [
      "aat:300008347"
    ],
    "id": 2559628,
    "name:xx": "Opal"
  }
}
