{
  "geometry": {
    "type": "Point",
    "coordinates": [
      5.5833,
      44.8833
    ]
  },
  "type": "Feature",
  "properties": {
    "hierarchy": [
      "tgn:1033341",
      "tgn:1000003",
      "tgn:1000070",
      "tgn:7002897",
      "tgn:7029392"
    ],
    "placetype": [
      "aat:300008347"
    ],
    "id": 1033341,
    "name:xx": "Gresse-en-Vercors"
  }
}
