{
  "geometry": {
    "type": "Point",
    "coordinates": [
      -98.2333,
      38.25
    ]
  },
  "type": "Feature",
  "properties": {
    "hierarchy": [
      "tgn:2205428",
      "tgn:1000001",
      "tgn:7012149",
      "tgn:7007254",
      "tgn:7029392"
    ],
    "placetype": [
      "aat:300008706"
    ],
    "id": 2205428,
    "name:xx": "Bull Creek"
  }
}
