{
  "geometry": {
    "type": "Point",
    "coordinates": [
      -87.1167,
      35.45
    ]
  },
  "type": "Feature",
  "properties": {
    "hierarchy": [
      "tgn:2785653",
      "tgn:1000001",
      "tgn:7012149",
      "tgn:2001864",
      "tgn:7007825",
      "tgn:7029392"
    ],
    "placetype": [
      "aat:300008706"
    ],
    "id": 2785653,
    "name:xx": "Yokley Creek"
  }
}
