{
  "geometry": {
    "type": "Point",
    "coordinates": [
      -86.2333,
      35.6833
    ]
  },
  "type": "Feature",
  "properties": {
    "hierarchy": [
      "tgn:2594910",
      "tgn:1000001",
      "tgn:7012149",
      "tgn:2001852",
      "tgn:7007825",
      "tgn:7029392"
    ],
    "placetype": [
      "aat:300008699"
    ],
    "id": 2594910,
    "name:xx": "Possumpaw Branch"
  }
}
