{
  "type": "FeatureCollection",
  "features": [
    {
      "geometry": {
        "type": "Point",
        "coordinates": [
          12.107778,
          46.9225
        ]
      },
      "type": "Feature",
      "properties": {
        "hierarchy": [
          "tgn:7048700",
          "tgn:1003440",
          "tgn:1000003",
          "tgn:7003124",
          "tgn:1000080",
          "tgn:7029392"
        ],
        "placetype": [
          "aat:300008835"
        ],
        "id": 7048700,
        "name:xx": "Giganti, Vedrette"
      }
    },
    {
      "geometry": {
        "type": "Point",
        "coordinates": [
          13.95,
          37.3
        ]
      },
      "type": "Feature",
      "properties": {
        "hierarchy": [
          "tgn:7048704",
          "tgn:1001622",
          "tgn:1000003",
          "tgn:7003122",
          "tgn:1000080",
          "tgn:7029392"
        ],
        "placetype": [
          "aat:300008347"
        ],
        "id": 7048704,
        "name:xx": "Gibbesi Vecchio"
      }
    },
    {
      "geometry": {
        "type": "Point",
        "coordinates": [
          14.016667,
          37.283333
        ]
      },
      "type": "Feature",
      "properties": {
        "hierarchy": [
          "tgn:7048705",
          "tgn:1000003",
          "tgn:7003122",
          "tgn:1000080",
          "tgn:7029392"
        ],
        "placetype": [
          "aat:300008699"
        ],
        "id": 7048705,
        "name:xx": "Gibbesi, Fiume"
      }
    },
    {
      "geometry": {
        "type": "Point",
        "coordinates": [
          11.1,
          45.866667
        ]
      },
      "type": "Feature",
      "properties": {
        "hierarchy": [
          "tgn:7048707",
          "tgn:7003158",
          "tgn:1000003",
          "tgn:7003124",
          "tgn:1000080",
          "tgn:7029392"
        ],
        "placetype": [
          "aat:300008347"
        ],
        "id": 7048707,
        "name:xx": "Giazzera"
      }
    },
    {
      "geometry": {
        "type": "Point",
        "coordinates": [
          11.333333,
          45.283333
        ]
      },
      "type": "Feature",
      "properties": {
        "hierarchy": [
          "tgn:7048709",
          "tgn:7003007",
          "tgn:1000003",
          "tgn:7002997",
          "tgn:1000080",
          "tgn:7029392"
        ],
        "placetype": [
          "aat:300008347"
        ],
        "id": 7048709,
        "name:xx": "Giavone"
      }
    }
  ]
}
