{
  "geometry": {
    "type": "Point",
    "coordinates": [
      -70.8833,
      43.2167
    ]
  },
  "type": "Feature",
  "properties": {
    "hierarchy": [
      "tgn:2772145",
      "tgn:1000001",
      "tgn:2001426",
      "tgn:7012149",
      "tgn:7007564",
      "tgn:7029392"
    ],
    "placetype": [
      "aat:300008680"
    ],
    "id": 2772145,
    "name:xx": "Willand Pond"
  }
}
