{
  "geometry": {
    "type": "Point",
    "coordinates": [
      -71.6833,
      42.0333
    ]
  },
  "type": "Feature",
  "properties": {
    "hierarchy": [
      "tgn:2484321",
      "tgn:1000001",
      "tgn:7012149",
      "tgn:1003038",
      "tgn:7007517",
      "tgn:7029392"
    ],
    "placetype": [
      "aat:300008699"
    ],
    "id": 2484321,
    "name:xx": "Laurel Brook"
  }
}
