{
  "geometry": {
    "type": "Point",
    "coordinates": [
      -78.1833,
      42.3667
    ]
  },
  "type": "Feature",
  "properties": {
    "hierarchy": [
      "tgn:2137919",
      "tgn:1002141",
      "tgn:1000001",
      "tgn:7012149",
      "tgn:7007568",
      "tgn:7029392"
    ],
    "placetype": [
      "aat:300132316"
    ],
    "id": 2137919,
    "name:xx": "Arrowhead Bay"
  }
}
