{
  "geometry": {
    "type": "Point",
    "coordinates": [
      -105.15,
      40.0667
    ]
  },
  "type": "Feature",
  "properties": {
    "hierarchy": [
      "tgn:2369412",
      "tgn:1000001",
      "tgn:2000198",
      "tgn:7012149",
      "tgn:7007158",
      "tgn:7029392"
    ],
    "placetype": [
      "aat:300008798"
    ],
    "id": 2369412,
    "name:xx": "Gun Barrel Hill"
  }
}
