{
  "geometry": {
    "type": "Point",
    "coordinates": [
      17.0833,
      43.8667
    ]
  },
  "type": "Feature",
  "properties": {
    "hierarchy": [
      "tgn:1104247",
      "tgn:7018774",
      "tgn:1000003",
      "tgn:7006664",
      "tgn:7029392"
    ],
    "placetype": [
      "aat:300008795"
    ],
    "id": 1104247,
    "name:xx": "Cincar"
  }
}
