{
  "geometry": {
    "type": "Point",
    "coordinates": [
      -90.0667,
      46.3167
    ]
  },
  "type": "Feature",
  "properties": {
    "hierarchy": [
      "tgn:2762668",
      "tgn:1000001",
      "tgn:7012149",
      "tgn:7029392"
    ],
    "placetype": [
      "aat:300008706"
    ],
    "id": 2762668,
    "name:xx": "Wester Creek"
  }
}
