{
  "geometry": {
    "type": "Point",
    "coordinates": [
      -75.9167,
      35.8333
    ]
  },
  "type": "Feature",
  "properties": {
    "hierarchy": [
      "tgn:2204338",
      "tgn:1000001",
      "tgn:7012149",
      "tgn:2001488",
      "tgn:7007709",
      "tgn:7029392"
    ],
    "placetype": [
      "aat:300008347"
    ],
    "id": 2204338,
    "name:xx": "Buffalo City"
  }
}
