{
  "geometry": {
    "type": "Point",
    "coordinates": [
      -123.65,
      43.0833
    ]
  },
  "type": "Feature",
  "properties": {
    "hierarchy": [
      "tgn:2147180",
      "tgn:1000001",
      "tgn:7012149",
      "tgn:2001706",
      "tgn:7007708",
      "tgn:7029392"
    ],
    "placetype": [
      "aat:300008706"
    ],
    "id": 2147180,
    "name:xx": "Bar Creek"
  }
}
