{
  "geometry": {
    "type": "Point",
    "coordinates": [
      -46.8833,
      -13.05
    ]
  },
  "type": "Feature",
  "properties": {
    "hierarchy": [
      "tgn:1021029",
      "tgn:7012827",
      "tgn:7002454",
      "tgn:1000047",
      "tgn:1000002",
      "tgn:7029392"
    ],
    "placetype": [
      "aat:300008347"
    ],
    "id": 1021029,
    "name:xx": "Campos Belos"
  }
}
