{
  "type": "FeatureCollection",
  "features": [
    {
      "geometry": {
        "type": "Point",
        "coordinates": [
          -96.7,
          17.033333
        ]
      },
      "type": "Feature",
      "properties": {
        "hierarchy": [
          "tgn:7391910",
          "tgn:1000001",
          "tgn:7005591",
          "tgn:7005560",
          "tgn:7029392"
        ],
        "placetype": [
          "aat:300008347"
        ],
        "id": 7391910,
        "name:xx": "Rosario"
      }
    },
    {
      "geometry": {
        "type": "Point",
        "coordinates": [
          -94.333333,
          16.516667
        ]
      },
      "type": "Feature",
      "properties": {
        "hierarchy": [
          "tgn:7391911",
          "tgn:1000001",
          "tgn:7005591",
          "tgn:7005560",
          "tgn:7029392"
        ],
        "placetype": [
          "aat:300008347"
        ],
        "id": 7391911,
        "name:xx": "Rosario"
      }
    },
    {
      "geometry": {
        "type": "Point",
        "coordinates": [
          -95.75,
          16.25
        ]
      },
      "type": "Feature",
      "properties": {
        "hierarchy": [
          "tgn:7391912",
          "tgn:1000001",
          "tgn:7005591",
          "tgn:7005560",
          "tgn:7029392"
        ],
        "placetype": [
          "aat:300008347"
        ],
        "id": 7391912,
        "name:xx": "Rosario"
      }
    },
    {
      "geometry": {
        "type": "Point",
        "coordinates": [
          -91.75,
          16.083333
        ]
      },
      "type": "Feature",
      "properties": {
        "hierarchy": [
          "tgn:7391913",
          "tgn:7005580",
          "tgn:1000001",
          "tgn:7005560",
          "tgn:7029392"
        ],
        "placetype": [
          "aat:300008347"
        ],
        "id": 7391913,
        "name:xx": "Rosario"
      }
    },
    {
      "geometry": {
        "type": "Point",
        "coordinates": [
          -91.983333,
          16.033333
        ]
      },
      "type": "Feature",
      "properties": {
        "hierarchy": [
          "tgn:7391914",
          "tgn:7005580",
          "tgn:1000001",
          "tgn:7005560",
          "tgn:7029392"
        ],
        "placetype": [
          "aat:300008347"
        ],
        "id": 7391914,
        "name:xx": "Rosario"
      }
    },
    {
      "geometry": {
        "type": "Point",
        "coordinates": [
          -92.583333,
          16.016667
        ]
      },
      "type": "Feature",
      "properties": {
        "hierarchy": [
          "tgn:7391915",
          "tgn:7005580",
          "tgn:1000001",
          "tgn:7005560",
          "tgn:7029392"
        ],
        "placetype": [
          "aat:300008347"
        ],
        "id": 7391915,
        "name:xx": "Rosario"
      }
    },
    {
      "geometry": {
        "type": "Point",
        "coordinates": [
          -102.1,
          28.25
        ]
      },
      "type": "Feature",
      "properties": {
        "hierarchy": [
          "tgn:7391916",
          "tgn:1001853",
          "tgn:1000001",
          "tgn:7005560",
          "tgn:7029392"
        ],
        "placetype": [
          "aat:300008763"
        ],
        "id": 7391916,
        "name:xx": "Rosaria, Cañón de la"
      }
    },
    {
      "geometry": {
        "type": "Point",
        "coordinates": [
          -108.35,
          25.416667
        ]
      },
      "type": "Feature",
      "properties": {
        "hierarchy": [
          "tgn:7391917",
          "tgn:1000001",
          "tgn:7005595",
          "tgn:7005560",
          "tgn:7029392"
        ],
        "placetype": [
          "aat:300008347"
        ],
        "id": 7391917,
        "name:xx": "Rosa Morada"
      }
    },
    {
      "geometry": {
        "type": "Point",
        "coordinates": [
          -107.85,
          25.4
        ]
      },
      "type": "Feature",
      "properties": {
        "hierarchy": [
          "tgn:7391918",
          "tgn:1000001",
          "tgn:7005595",
          "tgn:7005560",
          "tgn:7029392"
        ],
        "placetype": [
          "aat:300008347"
        ],
        "id": 7391918,
        "name:xx": "Rosa Morada"
      }
    }
  ]
}
