{
  "geometry": {
    "type": "Point",
    "coordinates": [
      -107.45,
      41.1167
    ]
  },
  "type": "Feature",
  "properties": {
    "hierarchy": [
      "tgn:2302261",
      "tgn:1000001",
      "tgn:2002368",
      "tgn:7012149",
      "tgn:7007923",
      "tgn:7029392"
    ],
    "placetype": [
      "aat:300008706"
    ],
    "id": 2302261,
    "name:xx": "Dutch Joe Creek"
  }
}
