{
  "type": "FeatureCollection",
  "features": [
    {
      "geometry": {
        "type": "Point",
        "coordinates": [
          -104.5333,
          31.2
        ]
      },
      "type": "Feature",
      "properties": {
        "hierarchy": [
          "tgn:2352310",
          "tgn:1000001",
          "tgn:7012149",
          "tgn:2001969",
          "tgn:7007826",
          "tgn:7029392"
        ],
        "placetype": [
          "aat:300008761"
        ],
        "id": 2352310,
        "name:xx": "Goat Canyon"
      }
    },
    {
      "geometry": {
        "type": "Point",
        "coordinates": [
          -104.1667,
          30.6333
        ]
      },
      "type": "Feature",
      "properties": {
        "hierarchy": [
          "tgn:2352311",
          "tgn:1000001",
          "tgn:7012149",
          "tgn:2002010",
          "tgn:7007826",
          "tgn:7029392"
        ],
        "placetype": [
          "aat:300008761"
        ],
        "id": 2352311,
        "name:xx": "Goat Canyon"
      }
    },
    {
      "geometry": {
        "type": "Point",
        "coordinates": [
          -113.5333,
          37.35
        ]
      },
      "type": "Feature",
      "properties": {
        "hierarchy": [
          "tgn:2352312",
          "tgn:1000001",
          "tgn:7012149",
          "tgn:2002127",
          "tgn:7007827",
          "tgn:7029392"
        ],
        "placetype": [
          "aat:300008761"
        ],
        "id": 2352312,
        "name:xx": "Goat Canyon"
      }
    },
    {
      "geometry": {
        "type": "Point",
        "coordinates": [
          -107.9167,
          37.1333
        ]
      },
      "type": "Feature",
      "properties": {
        "hierarchy": [
          "tgn:2352313",
          "tgn:1000001",
          "tgn:7012149",
          "tgn:2000225",
          "tgn:7007158",
          "tgn:7029392"
        ],
        "placetype": [
          "aat:300006191"
        ],
        "id": 2352313,
        "name:xx": "Goat Canyon Reservoir"
      }
    },
    {
      "geometry": {
        "type": "Point",
        "coordinates": [
          -105.7167,
          33.2
        ]
      },
      "type": "Feature",
      "properties": {
        "hierarchy": [
          "tgn:2352314",
          "tgn:1000001",
          "tgn:7012149",
          "tgn:2001447",
          "tgn:7007566",
          "tgn:7029392"
        ],
        "placetype": [
          "aat:300006191"
        ],
        "id": 2352314,
        "name:xx": "Goat Canyon Tank"
      }
    },
    {
      "geometry": {
        "type": "Point",
        "coordinates": [
          -87.85,
          34.45
        ]
      },
      "type": "Feature",
      "properties": {
        "hierarchy": [
          "tgn:2352315",
          "tgn:7002659",
          "tgn:1000001",
          "tgn:7012149",
          "tgn:2000029",
          "tgn:7029392"
        ],
        "placetype": [
          "aat:300008746"
        ],
        "id": 2352315,
        "name:xx": "Goat Cave"
      }
    },
    {
      "geometry": {
        "type": "Point",
        "coordinates": [
          -86.4,
          34.65
        ]
      },
      "type": "Feature",
      "properties": {
        "hierarchy": [
          "tgn:2352316",
          "tgn:7002659",
          "tgn:1000001",
          "tgn:7012149",
          "tgn:2000044",
          "tgn:7029392"
        ],
        "placetype": [
          "aat:300008746"
        ],
        "id": 2352316,
        "name:xx": "Goat Cave"
      }
    },
    {
      "geometry": {
        "type": "Point",
        "coordinates": [
          -104.5667,
          32.1333
        ]
      },
      "type": "Feature",
      "properties": {
        "hierarchy": [
          "tgn:2352318",
          "tgn:1000001",
          "tgn:2001436",
          "tgn:7012149",
          "tgn:7007566",
          "tgn:7029392"
        ],
        "placetype": [
          "aat:300008746"
        ],
        "id": 2352318,
        "name:xx": "Goat Cave"
      }
    },
    {
      "geometry": {
        "type": "Point",
        "coordinates": [
          -85.9,
          35.9333
        ]
      },
      "type": "Feature",
      "properties": {
        "hierarchy": [
          "tgn:2352319",
          "tgn:1000001",
          "tgn:7012149",
          "tgn:7022246",
          "tgn:7007825",
          "tgn:7029392"
        ],
        "placetype": [
          "aat:300008746"
        ],
        "id": 2352319,
        "name:xx": "Goat Cave"
      }
    }
  ]
}
