{
  "geometry": {
    "type": "Point",
    "coordinates": [
      -87.0167,
      34.3167
    ]
  },
  "type": "Feature",
  "properties": {
    "hierarchy": [
      "tgn:2691184",
      "tgn:7002659",
      "tgn:1000001",
      "tgn:7012149",
      "tgn:2000051",
      "tgn:7029392"
    ],
    "placetype": [
      "aat:300008798"
    ],
    "id": 2691184,
    "name:xx": "Stanton Hill"
  }
}
