{
  "type": "FeatureCollection",
  "features": [
    {
      "geometry": {
        "type": "Point",
        "coordinates": [
          0.5,
          48.0667
        ]
      },
      "type": "Feature",
      "properties": {
        "hierarchy": [
          "tgn:1032750",
          "tgn:1000003",
          "tgn:7002893",
          "tgn:1000070",
          "tgn:7029392"
        ],
        "placetype": [
          "aat:300008347"
        ],
        "id": 1032750,
        "name:xx": "Connerré"
      }
    },
    {
      "geometry": {
        "type": "Point",
        "coordinates": [
          7.3,
          43.8
        ]
      },
      "type": "Feature",
      "properties": {
        "hierarchy": [
          "tgn:1032751",
          "tgn:1000003",
          "tgn:1000070",
          "tgn:7002895",
          "tgn:7029392"
        ],
        "placetype": [
          "aat:300008347"
        ],
        "id": 1032751,
        "name:xx": "Contes"
      }
    },
    {
      "geometry": {
        "type": "Point",
        "coordinates": [
          1.4333,
          47.4333
        ]
      },
      "type": "Feature",
      "properties": {
        "hierarchy": [
          "tgn:1032752",
          "tgn:1000003",
          "tgn:7002877",
          "tgn:1000070",
          "tgn:7029392"
        ],
        "placetype": [
          "aat:300008347"
        ],
        "id": 1032752,
        "name:xx": "Contres"
      }
    },
    {
      "geometry": {
        "type": "Point",
        "coordinates": [
          5.9,
          48.1667
        ]
      },
      "type": "Feature",
      "properties": {
        "hierarchy": [
          "tgn:1032753",
          "tgn:1000003",
          "tgn:7002888",
          "tgn:1000070",
          "tgn:7029392"
        ],
        "placetype": [
          "aat:300008347"
        ],
        "id": 1032753,
        "name:xx": "Contrexéville"
      }
    },
    {
      "geometry": {
        "type": "Point",
        "coordinates": [
          4.95,
          48.8
        ]
      },
      "type": "Feature",
      "properties": {
        "hierarchy": [
          "tgn:1032754",
          "tgn:1000003",
          "tgn:7002888",
          "tgn:1000070",
          "tgn:7029392"
        ],
        "placetype": [
          "aat:300008347"
        ],
        "id": 1032754,
        "name:xx": "Contrisson"
      }
    },
    {
      "geometry": {
        "type": "Point",
        "coordinates": [
          2.1333,
          49.7333
        ]
      },
      "type": "Feature",
      "properties": {
        "hierarchy": [
          "tgn:1032755",
          "tgn:1000003",
          "tgn:7002890",
          "tgn:1000070",
          "tgn:7029392"
        ],
        "placetype": [
          "aat:300008347"
        ],
        "id": 1032755,
        "name:xx": "Conty"
      }
    },
    {
      "geometry": {
        "type": "Point",
        "coordinates": [
          6.35,
          49.45
        ]
      },
      "type": "Feature",
      "properties": {
        "hierarchy": [
          "tgn:1032756",
          "tgn:1000003",
          "tgn:7002888",
          "tgn:1000070",
          "tgn:7029392"
        ],
        "placetype": [
          "aat:300008347"
        ],
        "id": 1032756,
        "name:xx": "Contz-les-Bains"
      }
    },
    {
      "geometry": {
        "type": "Point",
        "coordinates": [
          6.3333,
          47.9
        ]
      },
      "type": "Feature",
      "properties": {
        "hierarchy": [
          "tgn:1032758",
          "tgn:1000003",
          "tgn:7002881",
          "tgn:1000070",
          "tgn:7029392"
        ],
        "placetype": [
          "aat:300008347"
        ],
        "id": 1032758,
        "name:xx": "Corbenay"
      }
    },
    {
      "geometry": {
        "type": "Point",
        "coordinates": [
          3.8333,
          49.4667
        ]
      },
      "type": "Feature",
      "properties": {
        "hierarchy": [
          "tgn:1032759",
          "tgn:1000003",
          "tgn:7002890",
          "tgn:1000070",
          "tgn:7029392"
        ],
        "placetype": [
          "aat:300008347"
        ],
        "id": 1032759,
        "name:xx": "Corbeny"
      }
    }
  ]
}
