{
  "geometry": {
    "type": "Point",
    "coordinates": [
      -74.9667,
      40.8667
    ]
  },
  "type": "Feature",
  "properties": {
    "hierarchy": [
      "tgn:2420873",
      "tgn:1000001",
      "tgn:1002985",
      "tgn:7012149",
      "tgn:7007565",
      "tgn:7029392"
    ],
    "placetype": [
      "aat:300008699"
    ],
    "id": 2420873,
    "name:xx": "Jenny Jump Brook"
  }
}
