{
  "geometry": {
    "type": "Point",
    "coordinates": [
      112.7833,
      -7.5667
    ]
  },
  "type": "Feature",
  "properties": {
    "hierarchy": [
      "tgn:1077422",
      "tgn:1000004",
      "tgn:1001323",
      "tgn:1000116",
      "tgn:7029392"
    ],
    "placetype": [
      "aat:300008347"
    ],
    "id": 1077422,
    "name:xx": "Bangil"
  }
}
