{
  "geometry": {
    "type": "Point",
    "coordinates": [
      -91.2833,
      30.65
    ]
  },
  "type": "Feature",
  "properties": {
    "hierarchy": [
      "tgn:2593869",
      "tgn:1000001",
      "tgn:2000870",
      "tgn:7012149",
      "tgn:7007256",
      "tgn:7029392"
    ],
    "placetype": [
      "aat:300008347"
    ],
    "id": 2593869,
    "name:xx": "Port Hickey Landing"
  }
}
