{
  "geometry": {
    "type": "Point",
    "coordinates": [
      31.096556,
      30.530362
    ]
  },
  "type": "Feature",
  "properties": {
    "hierarchy": [
      "tgn:7529250",
      "tgn:7001242",
      "tgn:7016833",
      "tgn:1001087",
      "tgn:7029392"
    ],
    "placetype": [
      "aat:300008347"
    ],
    "name:en": "Ţaḩā' Shubrā",
    "id": 7529250
  }
}
