{
  "geometry": {
    "type": "Point",
    "coordinates": [
      -87.5333,
      41.15
    ]
  },
  "type": "Feature",
  "properties": {
    "hierarchy": [
      "tgn:2781278",
      "tgn:1000001",
      "tgn:7012149",
      "tgn:1002532",
      "tgn:7007251",
      "tgn:7029392"
    ],
    "placetype": [
      "aat:300008347"
    ],
    "id": 2781278,
    "name:xx": "Woodland"
  }
}
