{
  "geometry": {
    "type": "Point",
    "coordinates": [
      -123.15,
      42.0667
    ]
  },
  "type": "Feature",
  "properties": {
    "hierarchy": [
      "tgn:2237495",
      "tgn:1000001",
      "tgn:7012149",
      "tgn:2001711",
      "tgn:7007708",
      "tgn:7029392"
    ],
    "placetype": [
      "aat:300008761"
    ],
    "id": 2237495,
    "name:xx": "China Gulch"
  }
}
