{
  "geometry": {
    "type": "Point",
    "coordinates": [
      -105.4333,
      32.9333
    ]
  },
  "type": "Feature",
  "properties": {
    "hierarchy": [
      "tgn:2483892",
      "tgn:1000001",
      "tgn:7012149",
      "tgn:2001447",
      "tgn:7007566",
      "tgn:7029392"
    ],
    "placetype": [
      "aat:300006191"
    ],
    "id": 2483892,
    "name:xx": "Latham Gap Tank"
  }
}
