{
  "geometry": {
    "type": "Point",
    "coordinates": [
      -37.284,
      -11.016
    ]
  },
  "type": "Feature",
  "properties": {
    "hierarchy": [
      "tgn:1131394",
      "tgn:1000047",
      "tgn:1000002",
      "tgn:7029392"
    ],
    "placetype": [
      "aat:300008707"
    ],
    "id": 1131394,
    "name:xx": "Vasa Barris, Rio"
  }
}
