{
  "geometry": {
    "type": "Point",
    "coordinates": [
      -111.8833,
      38.65
    ]
  },
  "type": "Feature",
  "properties": {
    "hierarchy": [
      "tgn:2155934",
      "tgn:1000001",
      "tgn:7012149",
      "tgn:2002121",
      "tgn:7007827",
      "tgn:7029392"
    ],
    "placetype": [
      "aat:300006191"
    ],
    "id": 2155934,
    "name:xx": "Bear Valley Reservoir"
  }
}
