{
  "type": "FeatureCollection",
  "features": [
    {
      "geometry": {
        "type": "Point",
        "coordinates": [
          -4.333333,
          57.083333
        ]
      },
      "type": "Feature",
      "properties": {
        "hierarchy": [
          "tgn:7457250",
          "tgn:7002444",
          "tgn:1000003",
          "tgn:7008082",
          "tgn:7008591",
          "tgn:7029392"
        ],
        "placetype": [
          "aat:300008761"
        ],
        "name:en": "Markie, Glen",
        "id": 7457250
      }
    },
    {
      "geometry": {
        "type": "Point",
        "coordinates": [
          0.916667,
          52.366667
        ]
      },
      "type": "Feature",
      "properties": {
        "hierarchy": [
          "tgn:7457252",
          "tgn:7002445",
          "tgn:1000003",
          "tgn:7008185",
          "tgn:7008591",
          "tgn:7029392"
        ],
        "placetype": [
          "aat:300008347"
        ],
        "name:en": "Market Weston",
        "id": 7457252
      }
    },
    {
      "geometry": {
        "type": "Point",
        "coordinates": [
          -1.15,
          53.2
        ]
      },
      "type": "Feature",
      "properties": {
        "hierarchy": [
          "tgn:7457254",
          "tgn:7002445",
          "tgn:1000003",
          "tgn:7008167",
          "tgn:7008591",
          "tgn:7029392"
        ],
        "placetype": [
          "aat:300008347"
        ],
        "name:en": "Market Warsop",
        "id": 7457254
      }
    },
    {
      "geometry": {
        "type": "Point",
        "coordinates": [
          -0.683333,
          52.716667
        ]
      },
      "type": "Feature",
      "properties": {
        "hierarchy": [
          "tgn:7457256",
          "tgn:7002445",
          "tgn:1000003",
          "tgn:5000748",
          "tgn:7008591",
          "tgn:7029392"
        ],
        "placetype": [
          "aat:300008347",
          "aat:300387092"
        ],
        "name:en": "Market Overton",
        "id": 7457256
      }
    }
  ]
}
