{
  "geometry": {
    "type": "Point",
    "coordinates": [
      -117.85,
      44.5667
    ]
  },
  "type": "Feature",
  "properties": {
    "hierarchy": [
      "tgn:2694795",
      "tgn:7013349",
      "tgn:1000001",
      "tgn:7012149",
      "tgn:7007708",
      "tgn:7029392"
    ],
    "placetype": [
      "aat:300008761"
    ],
    "id": 2694795,
    "name:xx": "Stices Gulch"
  }
}
