{
  "geometry": {
    "type": "Point",
    "coordinates": [
      -86.8667,
      33.4833
    ]
  },
  "type": "Feature",
  "properties": {
    "hierarchy": [
      "tgn:2230852",
      "tgn:7002659",
      "tgn:1000001",
      "tgn:7012149",
      "tgn:2000036",
      "tgn:7029392"
    ],
    "placetype": [
      "aat:300008347"
    ],
    "id": 2230852,
    "name:xx": "Central Park Highlands"
  }
}
