{
  "geometry": {
    "type": "Point",
    "coordinates": [
      -39.6167,
      -14.6167
    ]
  },
  "type": "Feature",
  "properties": {
    "hierarchy": [
      "tgn:1021171",
      "tgn:1001834",
      "tgn:1000047",
      "tgn:7002455",
      "tgn:1000002",
      "tgn:7029392"
    ],
    "placetype": [
      "aat:300008347"
    ],
    "id": 1021171,
    "name:xx": "Coaraci"
  }
}
