{
  "geometry": {
    "type": "Point",
    "coordinates": [
      103.8667,
      18.0167
    ]
  },
  "type": "Feature",
  "properties": {
    "hierarchy": [
      "tgn:1085461",
      "tgn:7005193",
      "tgn:1000004",
      "tgn:7000936",
      "tgn:1000142",
      "tgn:7029392"
    ],
    "placetype": [
      "aat:300008347"
    ],
    "id": 1085461,
    "name:xx": "Ban Nam Chan"
  }
}
