{
  "geometry": {
    "type": "Point",
    "coordinates": [
      -118.5833,
      37.6833
    ]
  },
  "type": "Feature",
  "properties": {
    "hierarchy": [
      "tgn:2146968",
      "tgn:1000001",
      "tgn:7012149",
      "tgn:7007157",
      "tgn:1002675",
      "tgn:7029392"
    ],
    "placetype": [
      "aat:300008697"
    ],
    "id": 2146968,
    "name:xx": "Banner Springs"
  }
}
