{
  "geometry": {
    "type": "Point",
    "coordinates": [
      -77.9167,
      42.1833
    ]
  },
  "type": "Feature",
  "properties": {
    "hierarchy": [
      "tgn:2601630",
      "tgn:1002141",
      "tgn:1000001",
      "tgn:7012149",
      "tgn:7007568",
      "tgn:7029392"
    ],
    "placetype": [
      "aat:300008699"
    ],
    "id": 2601630,
    "name:xx": "Put Brook"
  }
}
