{
  "geometry": {
    "type": "Point",
    "coordinates": [
      -75.5167,
      41.4833
    ]
  },
  "type": "Feature",
  "properties": {
    "hierarchy": [
      "tgn:2484790",
      "tgn:1000001",
      "tgn:7012149",
      "tgn:1002564",
      "tgn:7007710",
      "tgn:7029392"
    ],
    "placetype": [
      "aat:300006191"
    ],
    "id": 2484790,
    "name:xx": "Laurel Run Reservoir"
  }
}
