{
  "geometry": {
    "type": "Point",
    "coordinates": [
      -80.6833,
      28.1333
    ]
  },
  "type": "Feature",
  "properties": {
    "hierarchy": [
      "tgn:2140421",
      "tgn:1000001",
      "tgn:1002200",
      "tgn:7012149",
      "tgn:7007240",
      "tgn:7029392"
    ],
    "placetype": [
      "aat:300008347"
    ],
    "id": 2140421,
    "name:xx": "Aurora"
  }
}
