{
  "geometry": {
    "type": "Point",
    "coordinates": [
      39.25,
      40.4667
    ]
  },
  "type": "Feature",
  "properties": {
    "hierarchy": [
      "tgn:1108761",
      "tgn:1001256",
      "tgn:1000004",
      "tgn:7018454",
      "tgn:1000144",
      "tgn:7029392"
    ],
    "placetype": [
      "aat:300008795"
    ],
    "id": 1108761,
    "name:xx": "Balabandaglari"
  }
}
