{
  "type": "FeatureCollection",
  "features": [
    {
      "geometry": {
        "type": "Point",
        "coordinates": [
          -83.65,
          32.2833
        ]
      },
      "type": "Feature",
      "properties": {
        "hierarchy": [
          "tgn:2701140",
          "tgn:1000001",
          "tgn:7012149",
          "tgn:7007248",
          "tgn:7029392"
        ],
        "placetype": [
          "aat:300008798"
        ],
        "id": 2701140,
        "name:xx": "Sugar Hill"
      }
    },
    {
      "geometry": {
        "type": "Point",
        "coordinates": [
          -84.6833,
          34.3
        ]
      },
      "type": "Feature",
      "properties": {
        "hierarchy": [
          "tgn:2701141",
          "tgn:1000001",
          "tgn:2000299",
          "tgn:7012149",
          "tgn:7007248",
          "tgn:7029392"
        ],
        "placetype": [
          "aat:300008798"
        ],
        "id": 2701141,
        "name:xx": "Sugar Hill"
      }
    },
    {
      "geometry": {
        "type": "Point",
        "coordinates": [
          -84.1667,
          34.7667
        ]
      },
      "type": "Feature",
      "properties": {
        "hierarchy": [
          "tgn:2701142",
          "tgn:1000001",
          "tgn:7012149",
          "tgn:2000346",
          "tgn:7007248",
          "tgn:7029392"
        ],
        "placetype": [
          "aat:300008347"
        ],
        "id": 2701142,
        "name:xx": "Sugar Hill"
      }
    },
    {
      "geometry": {
        "type": "Point",
        "coordinates": [
          -84.6833,
          34.3
        ]
      },
      "type": "Feature",
      "properties": {
        "hierarchy": [
          "tgn:2701143",
          "tgn:1000001",
          "tgn:2000299",
          "tgn:7012149",
          "tgn:7007248",
          "tgn:7029392"
        ],
        "placetype": [
          "aat:300008347"
        ],
        "id": 2701143,
        "name:xx": "Sugar Hill"
      }
    },
    {
      "geometry": {
        "type": "Point",
        "coordinates": [
          -89.45,
          37.9333
        ]
      },
      "type": "Feature",
      "properties": {
        "hierarchy": [
          "tgn:2701144",
          "tgn:1000001",
          "tgn:7012149",
          "tgn:2000512",
          "tgn:7007251",
          "tgn:7029392"
        ],
        "placetype": [
          "aat:300008798"
        ],
        "id": 2701144,
        "name:xx": "Sugar Hill"
      }
    },
    {
      "geometry": {
        "type": "Point",
        "coordinates": [
          -85.7,
          41.4833
        ]
      },
      "type": "Feature",
      "properties": {
        "hierarchy": [
          "tgn:2701145",
          "tgn:1000001",
          "tgn:7012149",
          "tgn:1002353",
          "tgn:7007252",
          "tgn:7029392"
        ],
        "placetype": [
          "aat:300008798"
        ],
        "id": 2701145,
        "name:xx": "Sugar Hill"
      }
    },
    {
      "geometry": {
        "type": "Point",
        "coordinates": [
          -67.8,
          46.4333
        ]
      },
      "type": "Feature",
      "properties": {
        "hierarchy": [
          "tgn:2701146",
          "tgn:2000919",
          "tgn:1000001",
          "tgn:7012149",
          "tgn:7007515",
          "tgn:7029392"
        ],
        "placetype": [
          "aat:300008347"
        ],
        "id": 2701146,
        "name:xx": "Sugar Hill"
      }
    },
    {
      "geometry": {
        "type": "Point",
        "coordinates": [
          -68.2167,
          44.6833
        ]
      },
      "type": "Feature",
      "properties": {
        "hierarchy": [
          "tgn:2701147",
          "tgn:1000001",
          "tgn:2000922",
          "tgn:7012149",
          "tgn:7007515",
          "tgn:7029392"
        ],
        "placetype": [
          "aat:300008798"
        ],
        "id": 2701147,
        "name:xx": "Sugar Hill"
      }
    },
    {
      "geometry": {
        "type": "Point",
        "coordinates": [
          -67.7167,
          44.7167
        ]
      },
      "type": "Feature",
      "properties": {
        "hierarchy": [
          "tgn:2701148",
          "tgn:1000001",
          "tgn:7012149",
          "tgn:7014589",
          "tgn:7007515",
          "tgn:7029392"
        ],
        "placetype": [
          "aat:300008798"
        ],
        "id": 2701148,
        "name:xx": "Sugar Hill"
      }
    },
    {
      "geometry": {
        "type": "Point",
        "coordinates": [
          -69.5,
          45
        ]
      },
      "type": "Feature",
      "properties": {
        "hierarchy": [
          "tgn:2701149",
          "tgn:1000001",
          "tgn:7012149",
          "tgn:2000930",
          "tgn:7007515",
          "tgn:7029392"
        ],
        "placetype": [
          "aat:300008905"
        ],
        "id": 2701149,
        "name:xx": "Sugar Hill"
      }
    }
  ]
}
