{
  "geometry": {
    "type": "Point",
    "coordinates": [
      14.4333,
      59.2333
    ]
  },
  "type": "Feature",
  "properties": {
    "hierarchy": [
      "tgn:1062903",
      "tgn:1000003",
      "tgn:1000331",
      "tgn:1000097",
      "tgn:7029392"
    ],
    "placetype": [
      "aat:300008347"
    ],
    "id": 1062903,
    "name:xx": "Degerfors"
  }
}
