{
  "geometry": {
    "type": "Point",
    "coordinates": [
      -95.3667,
      39.8833
    ]
  },
  "type": "Feature",
  "properties": {
    "hierarchy": [
      "tgn:2471816",
      "tgn:1000001",
      "tgn:2000666",
      "tgn:7012149",
      "tgn:7007254",
      "tgn:7029392"
    ],
    "placetype": [
      "aat:300008706"
    ],
    "id": 2471816,
    "name:xx": "Lost Shirt Creek"
  }
}
