{
  "geometry": {
    "type": "Point",
    "coordinates": [
      -77.3667,
      40.65
    ]
  },
  "type": "Feature",
  "properties": {
    "hierarchy": [
      "tgn:2256298",
      "tgn:1000001",
      "tgn:7012149",
      "tgn:1002528",
      "tgn:7007710",
      "tgn:7029392"
    ],
    "placetype": [
      "aat:300008761"
    ],
    "id": 2256298,
    "name:xx": "Copperhead Hollow"
  }
}
