{
  "geometry": {
    "type": "Point",
    "coordinates": [
      -107.0667,
      39.15
    ]
  },
  "type": "Feature",
  "properties": {
    "hierarchy": [
      "tgn:2220734",
      "tgn:1000001",
      "tgn:7012149",
      "tgn:7007158",
      "tgn:2000240",
      "tgn:7029392"
    ],
    "placetype": [
      "aat:300006191"
    ],
    "id": 2220734,
    "name:xx": "Capitol Lkae"
  }
}
