{
  "geometry": {
    "type": "Point",
    "coordinates": [
      -95.9333,
      30.4833
    ]
  },
  "type": "Feature",
  "properties": {
    "hierarchy": [
      "tgn:2395428",
      "tgn:1000001",
      "tgn:7012149",
      "tgn:1002429",
      "tgn:7007826",
      "tgn:7029392"
    ],
    "placetype": [
      "aat:300008706"
    ],
    "id": 2395428,
    "name:xx": "Holland Creek"
  }
}
