{
  "geometry": {
    "type": "Point",
    "coordinates": [
      15.65,
      56.9667
    ]
  },
  "type": "Feature",
  "properties": {
    "hierarchy": [
      "tgn:1063132",
      "tgn:1000003",
      "tgn:1000405",
      "tgn:1000097",
      "tgn:7029392"
    ],
    "placetype": [
      "aat:300008347"
    ],
    "id": 1063132,
    "name:xx": "Hohultslätt"
  }
}
