{
  "geometry": {
    "type": "Point",
    "coordinates": [
      -73.5333,
      43.6667
    ]
  },
  "type": "Feature",
  "properties": {
    "hierarchy": [
      "tgn:2180667",
      "tgn:1000001",
      "tgn:7012149",
      "tgn:1002986",
      "tgn:7007568",
      "tgn:7029392"
    ],
    "placetype": [
      "aat:300008798"
    ],
    "id": 2180667,
    "name:xx": "Bloomer Mountain"
  }
}
