{
  "geometry": {
    "type": "Point",
    "coordinates": [
      -94.7333,
      46.2167
    ]
  },
  "type": "Feature",
  "properties": {
    "hierarchy": [
      "tgn:2607895",
      "tgn:1000001",
      "tgn:7012149",
      "tgn:2001075",
      "tgn:7007521",
      "tgn:7029392"
    ],
    "placetype": [
      "aat:300008680"
    ],
    "id": 2607895,
    "name:xx": "Rat Lake"
  }
}
