{
  "geometry": {
    "type": "Point",
    "coordinates": [
      30.783333,
      29.45
    ]
  },
  "type": "Feature",
  "properties": {
    "hierarchy": [
      "tgn:7526693",
      "tgn:7001242",
      "tgn:7001105",
      "tgn:7016833",
      "tgn:7029392"
    ],
    "placetype": [
      "aat:300005926"
    ],
    "name:en": "Sīdī Mişbāḩ",
    "id": 7526693
  }
}
