{
  "geometry": {
    "type": "Point",
    "coordinates": [
      -115.0833,
      44.7333
    ]
  },
  "type": "Feature",
  "properties": {
    "hierarchy": [
      "tgn:2560689",
      "tgn:1000001",
      "tgn:2000470",
      "tgn:7012149",
      "tgn:7007250",
      "tgn:7029392"
    ],
    "placetype": [
      "aat:300008706"
    ],
    "id": 2560689,
    "name:xx": "Orelano Creek"
  }
}
