{
  "geometry": {
    "type": "Point",
    "coordinates": [
      -1.05,
      48.5667
    ]
  },
  "type": "Feature",
  "properties": {
    "hierarchy": [
      "tgn:7009678",
      "tgn:1000003",
      "tgn:7002877",
      "tgn:1000070",
      "tgn:7029392"
    ],
    "placetype": [
      "aat:300008347"
    ],
    "id": 7009678,
    "name:xx": "Senonches"
  }
}
