{
  "geometry": {
    "type": "Point",
    "coordinates": [
      14.1833,
      12.3333
    ]
  },
  "type": "Feature",
  "properties": {
    "hierarchy": [
      "tgn:1092186",
      "tgn:7001242",
      "tgn:7000542",
      "tgn:1000182",
      "tgn:7029392"
    ],
    "placetype": [
      "aat:300008347"
    ],
    "id": 1092186,
    "name:xx": "Ngala"
  }
}
