{
  "geometry": {
    "type": "Point",
    "coordinates": [
      -91.5667,
      35.4167
    ]
  },
  "type": "Feature",
  "properties": {
    "hierarchy": [
      "tgn:2582089",
      "tgn:1000001",
      "tgn:7016172",
      "tgn:7012149",
      "tgn:2000177",
      "tgn:7029392"
    ],
    "placetype": [
      "aat:300008706"
    ],
    "id": 2582089,
    "name:xx": "Pine Creek"
  }
}
