{
  "geometry": {
    "type": "Point",
    "coordinates": [
      -122.9833,
      44.1833
    ]
  },
  "type": "Feature",
  "properties": {
    "hierarchy": [
      "tgn:2501376",
      "tgn:1000001",
      "tgn:7012149",
      "tgn:2001716",
      "tgn:7007708",
      "tgn:7029392"
    ],
    "placetype": [
      "aat:300008706"
    ],
    "id": 2501376,
    "name:xx": "McGowan Creek"
  }
}
