{
  "geometry": {
    "type": "Point",
    "coordinates": [
      -116.3333,
      47.9833
    ]
  },
  "type": "Feature",
  "properties": {
    "hierarchy": [
      "tgn:2688316",
      "tgn:1000001",
      "tgn:7012149",
      "tgn:7007250",
      "tgn:7029392"
    ],
    "placetype": [
      "aat:300008706"
    ],
    "id": 2688316,
    "name:xx": "Spruce Creek"
  }
}
