{
  "geometry": {
    "type": "Point",
    "coordinates": [
      -113.9333,
      37.4833
    ]
  },
  "type": "Feature",
  "properties": {
    "hierarchy": [
      "tgn:2668843",
      "tgn:1000001",
      "tgn:7012149",
      "tgn:2002127",
      "tgn:7007827",
      "tgn:7029392"
    ],
    "placetype": [
      "aat:300008706"
    ],
    "id": 2668843,
    "name:xx": "Slaughter Creek"
  }
}
