{
  "geometry": {
    "type": "Point",
    "coordinates": [
      79.489486,
      27.11845
    ]
  },
  "type": "Feature",
  "properties": {
    "hierarchy": [
      "tgn:7561077",
      "tgn:1000004",
      "tgn:7000198",
      "tgn:7016722",
      "tgn:7029392"
    ],
    "placetype": [
      "aat:300008347"
    ],
    "name:en": "Randhīrpur",
    "id": 7561077
  }
}
