{
  "geometry": {
    "type": "Point",
    "coordinates": [
      -92.3667,
      39.85
    ]
  },
  "type": "Feature",
  "properties": {
    "hierarchy": [
      "tgn:2355148",
      "tgn:1000001",
      "tgn:7012149",
      "tgn:7007523",
      "tgn:7029392"
    ],
    "placetype": [
      "aat:300008699"
    ],
    "id": 2355148,
    "name:xx": "Goodson Branch"
  }
}
