{
  "geometry": {
    "type": "Point",
    "coordinates": [
      -155.5667,
      19.0167
    ]
  },
  "type": "Feature",
  "properties": {
    "hierarchy": [
      "tgn:2490130",
      "tgn:7023902",
      "tgn:1000001",
      "tgn:7012149",
      "tgn:7007249",
      "tgn:7029392"
    ],
    "placetype": [
      "aat:300008850"
    ],
    "id": 2490130,
    "name:xx": "Manakaa Point"
  }
}
