{
  "geometry": {
    "type": "Point",
    "coordinates": [
      -91.7333,
      44.6167
    ]
  },
  "type": "Feature",
  "properties": {
    "hierarchy": [
      "tgn:2379405",
      "tgn:1000001",
      "tgn:7012149",
      "tgn:7007922",
      "tgn:7029392"
    ],
    "placetype": [
      "aat:300008706"
    ],
    "id": 2379405,
    "name:xx": "Harvey Creek"
  }
}
