{
  "geometry": {
    "type": "Point",
    "coordinates": [
      -80.7667,
      39.6333
    ]
  },
  "type": "Feature",
  "properties": {
    "hierarchy": [
      "tgn:7021488",
      "tgn:1000001",
      "tgn:7012149",
      "tgn:2002301",
      "tgn:7013961",
      "tgn:7029392"
    ],
    "placetype": [
      "aat:300008699"
    ],
    "id": 7021488,
    "name:xx": "Long Run"
  }
}
