{
  "geometry": {
    "type": "Point",
    "coordinates": [
      -109.8167,
      45.55
    ]
  },
  "type": "Feature",
  "properties": {
    "hierarchy": [
      "tgn:2156507",
      "tgn:1000001",
      "tgn:7012149",
      "tgn:7007524",
      "tgn:7029392"
    ],
    "placetype": [
      "aat:300008761"
    ],
    "id": 2156507,
    "name:xx": "Beartrap Draw"
  }
}
