{
  "type": "FeatureCollection",
  "features": [
    {
      "geometry": {
        "type": "Point",
        "coordinates": [
          -122.8833,
          42.25
        ]
      },
      "type": "Feature",
      "properties": {
        "hierarchy": [
          "tgn:2275830",
          "tgn:1000001",
          "tgn:7012149",
          "tgn:2001711",
          "tgn:7007708",
          "tgn:7029392"
        ],
        "placetype": [
          "aat:300008761"
        ],
        "id": 2275830,
        "name:xx": "Dark Hollow"
      }
    },
    {
      "geometry": {
        "type": "Point",
        "coordinates": [
          -77.4667,
          39.9333
        ]
      },
      "type": "Feature",
      "properties": {
        "hierarchy": [
          "tgn:2275831",
          "tgn:1000001",
          "tgn:7012149",
          "tgn:1002387",
          "tgn:7007710",
          "tgn:7029392"
        ],
        "placetype": [
          "aat:300008761"
        ],
        "id": 2275831,
        "name:xx": "Dark Hollow"
      }
    },
    {
      "geometry": {
        "type": "Point",
        "coordinates": [
          -78.3667,
          40.1667
        ]
      },
      "type": "Feature",
      "properties": {
        "hierarchy": [
          "tgn:2275832",
          "tgn:1002172",
          "tgn:1000001",
          "tgn:7012149",
          "tgn:7007710",
          "tgn:7029392"
        ],
        "placetype": [
          "aat:300008761"
        ],
        "id": 2275832,
        "name:xx": "Dark Hollow"
      }
    },
    {
      "geometry": {
        "type": "Point",
        "coordinates": [
          -79.25,
          40.3167
        ]
      },
      "type": "Feature",
      "properties": {
        "hierarchy": [
          "tgn:2275833",
          "tgn:1000001",
          "tgn:7012149",
          "tgn:1003017",
          "tgn:7007710",
          "tgn:7029392"
        ],
        "placetype": [
          "aat:300008761"
        ],
        "id": 2275833,
        "name:xx": "Dark Hollow"
      }
    },
    {
      "geometry": {
        "type": "Point",
        "coordinates": [
          -77.1333,
          40.4
        ]
      },
      "type": "Feature",
      "properties": {
        "hierarchy": [
          "tgn:2275834",
          "tgn:1000001",
          "tgn:7012149",
          "tgn:1002779",
          "tgn:7007710",
          "tgn:7029392"
        ],
        "placetype": [
          "aat:300008761"
        ],
        "id": 2275834,
        "name:xx": "Dark Hollow"
      }
    },
    {
      "geometry": {
        "type": "Point",
        "coordinates": [
          -78.0667,
          41.2667
        ]
      },
      "type": "Feature",
      "properties": {
        "hierarchy": [
          "tgn:2275835",
          "tgn:1000001",
          "tgn:1002229",
          "tgn:7012149",
          "tgn:7007710",
          "tgn:7029392"
        ],
        "placetype": [
          "aat:300008761"
        ],
        "id": 2275835,
        "name:xx": "Dark Hollow"
      }
    },
    {
      "geometry": {
        "type": "Point",
        "coordinates": [
          -75.7,
          41.3
        ]
      },
      "type": "Feature",
      "properties": {
        "hierarchy": [
          "tgn:2275836",
          "tgn:1000001",
          "tgn:7012149",
          "tgn:1002612",
          "tgn:7007710",
          "tgn:7029392"
        ],
        "placetype": [
          "aat:300008761"
        ],
        "id": 2275836,
        "name:xx": "Dark Hollow"
      }
    },
    {
      "geometry": {
        "type": "Point",
        "coordinates": [
          -79.0833,
          41.3667
        ]
      },
      "type": "Feature",
      "properties": {
        "hierarchy": [
          "tgn:2275837",
          "tgn:1000001",
          "tgn:7012149",
          "tgn:1002352",
          "tgn:7007710",
          "tgn:7029392"
        ],
        "placetype": [
          "aat:300008761"
        ],
        "id": 2275837,
        "name:xx": "Dark Hollow"
      }
    },
    {
      "geometry": {
        "type": "Point",
        "coordinates": [
          -77.75,
          41.4167
        ]
      },
      "type": "Feature",
      "properties": {
        "hierarchy": [
          "tgn:2275838",
          "tgn:1000001",
          "tgn:1002286",
          "tgn:7012149",
          "tgn:7007710",
          "tgn:7029392"
        ],
        "placetype": [
          "aat:300008761"
        ],
        "id": 2275838,
        "name:xx": "Dark Hollow"
      }
    },
    {
      "geometry": {
        "type": "Point",
        "coordinates": [
          -77.5667,
          41.6
        ]
      },
      "type": "Feature",
      "properties": {
        "hierarchy": [
          "tgn:2275839",
          "tgn:1000001",
          "tgn:7012149",
          "tgn:1002945",
          "tgn:7007710",
          "tgn:7029392"
        ],
        "placetype": [
          "aat:300008761"
        ],
        "id": 2275839,
        "name:xx": "Dark Hollow"
      }
    }
  ]
}
