{
  "geometry": {
    "type": "Point",
    "coordinates": [
      -100.3333,
      37.3667
    ]
  },
  "type": "Feature",
  "properties": {
    "hierarchy": [
      "tgn:2271078",
      "tgn:1000001",
      "tgn:7012149",
      "tgn:2000719",
      "tgn:7007254",
      "tgn:7029392"
    ],
    "placetype": [
      "aat:300000390"
    ],
    "id": 2271078,
    "name:xx": "Cudahay Mine"
  }
}
