{
  "type": "FeatureCollection",
  "features": [
    {
      "geometry": {
        "type": "Point",
        "coordinates": [
          -0.1833,
          51.5
        ]
      },
      "type": "Feature",
      "properties": {
        "hierarchy": [
          "tgn:1100471",
          "tgn:7002445",
          "tgn:1004847",
          "tgn:7011781",
          "tgn:1000003",
          "tgn:7008136",
          "tgn:7008591",
          "tgn:7029392"
        ],
        "placetype": [
          "aat:300004792"
        ],
        "id": 1100471,
        "name:xx": "Royal Albert Hall"
      }
    },
    {
      "geometry": {
        "type": "Point",
        "coordinates": [
          -0.1167,
          51.5
        ]
      },
      "type": "Feature",
      "properties": {
        "hierarchy": [
          "tgn:1100472",
          "tgn:7002445",
          "tgn:7018923",
          "tgn:7011781",
          "tgn:1000003",
          "tgn:7008136",
          "tgn:7008591",
          "tgn:7029392"
        ],
        "placetype": [
          "aat:300004792"
        ],
        "id": 1100472,
        "name:xx": "Royal Festival Hall"
      }
    },
    {
      "geometry": {
        "type": "Point",
        "coordinates": [
          2.35,
          48.7667
        ]
      },
      "type": "Feature",
      "properties": {
        "hierarchy": [
          "tgn:1100473",
          "tgn:1000003",
          "tgn:7002883",
          "tgn:1000070",
          "tgn:7029392"
        ],
        "placetype": [
          "aat:300004792"
        ],
        "id": 1100473,
        "name:xx": "Rungis-Halles, Marché de"
      }
    },
    {
      "geometry": {
        "type": "Point",
        "coordinates": [
          -2.4167,
          53.6333
        ]
      },
      "type": "Feature",
      "properties": {
        "hierarchy": [
          "tgn:1100477",
          "tgn:7002445",
          "tgn:1000003",
          "tgn:7008154",
          "tgn:7008591",
          "tgn:7029392"
        ],
        "placetype": [
          "aat:300005433"
        ],
        "id": 1100477,
        "name:xx": "Turton Tower"
      }
    }
  ]
}
