{
  "geometry": {
    "type": "Point",
    "coordinates": [
      79.578107,
      26.792327
    ]
  },
  "type": "Feature",
  "properties": {
    "hierarchy": [
      "tgn:7565586",
      "tgn:1000004",
      "tgn:7000198",
      "tgn:7016722",
      "tgn:7029392"
    ],
    "placetype": [
      "aat:300008347"
    ],
    "name:en": "Chānda",
    "id": 7565586
  }
}
