{
  "type": "FeatureCollection",
  "features": [
    {
      "geometry": {
        "type": "Point",
        "coordinates": [
          -102.916667,
          19.633333
        ]
      },
      "type": "Feature",
      "properties": {
        "hierarchy": [
          "tgn:7377810",
          "tgn:7005586",
          "tgn:1000001",
          "tgn:7005560",
          "tgn:7029392"
        ],
        "placetype": [
          "aat:300008347"
        ],
        "id": 7377810,
        "name:xx": "Las Canoas"
      }
    },
    {
      "geometry": {
        "type": "Point",
        "coordinates": [
          -103.466667,
          19.6
        ]
      },
      "type": "Feature",
      "properties": {
        "hierarchy": [
          "tgn:7377811",
          "tgn:7005586",
          "tgn:1000001",
          "tgn:7005560",
          "tgn:7029392"
        ],
        "placetype": [
          "aat:300008347"
        ],
        "id": 7377811,
        "name:xx": "Las Canoas"
      }
    },
    {
      "geometry": {
        "type": "Point",
        "coordinates": [
          -104.1,
          19.283333
        ]
      },
      "type": "Feature",
      "properties": {
        "hierarchy": [
          "tgn:7377813",
          "tgn:7016644",
          "tgn:1000001",
          "tgn:7005560",
          "tgn:7029392"
        ],
        "placetype": [
          "aat:300008347"
        ],
        "id": 7377813,
        "name:xx": "Las Canoas"
      }
    },
    {
      "geometry": {
        "type": "Point",
        "coordinates": [
          -112.15,
          31.35
        ]
      },
      "type": "Feature",
      "properties": {
        "hierarchy": [
          "tgn:7377814",
          "tgn:1000001",
          "tgn:1001960",
          "tgn:7005560",
          "tgn:7029392"
        ],
        "placetype": [
          "aat:300006191"
        ],
        "id": 7377814,
        "name:xx": "Presa Las Canelillas"
      }
    },
    {
      "geometry": {
        "type": "Point",
        "coordinates": [
          -108.633333,
          26.45
        ]
      },
      "type": "Feature",
      "properties": {
        "hierarchy": [
          "tgn:7377815",
          "tgn:1000001",
          "tgn:7005595",
          "tgn:7005560",
          "tgn:7029392"
        ],
        "placetype": [
          "aat:300008347"
        ],
        "id": 7377815,
        "name:xx": "Las Cañas"
      }
    },
    {
      "geometry": {
        "type": "Point",
        "coordinates": [
          -106.783333,
          24.75
        ]
      },
      "type": "Feature",
      "properties": {
        "hierarchy": [
          "tgn:7377816",
          "tgn:7005583",
          "tgn:1000001",
          "tgn:7005560",
          "tgn:7029392"
        ],
        "placetype": [
          "aat:300008347"
        ],
        "id": 7377816,
        "name:xx": "Las Cañas"
      }
    },
    {
      "geometry": {
        "type": "Point",
        "coordinates": [
          -103.266667,
          22.3
        ]
      },
      "type": "Feature",
      "properties": {
        "hierarchy": [
          "tgn:7377817",
          "tgn:7005586",
          "tgn:1000001",
          "tgn:7005560",
          "tgn:7029392"
        ],
        "placetype": [
          "aat:300008347"
        ],
        "id": 7377817,
        "name:xx": "Las Cañas"
      }
    },
    {
      "geometry": {
        "type": "Point",
        "coordinates": [
          -100.733333,
          21.033333
        ]
      },
      "type": "Feature",
      "properties": {
        "hierarchy": [
          "tgn:7377818",
          "tgn:7005584",
          "tgn:1000001",
          "tgn:7005560",
          "tgn:7029392"
        ],
        "placetype": [
          "aat:300008347"
        ],
        "id": 7377818,
        "name:xx": "Las Cañas"
      }
    },
    {
      "geometry": {
        "type": "Point",
        "coordinates": [
          -97.566667,
          20.833333
        ]
      },
      "type": "Feature",
      "properties": {
        "hierarchy": [
          "tgn:7377819",
          "tgn:1000001",
          "tgn:7005599",
          "tgn:7005560",
          "tgn:7029392"
        ],
        "placetype": [
          "aat:300008347"
        ],
        "id": 7377819,
        "name:xx": "Las Cañas"
      }
    }
  ]
}
