{
  "geometry": {
    "type": "Point",
    "coordinates": [
      -108.85,
      41.9167
    ]
  },
  "type": "Feature",
  "properties": {
    "hierarchy": [
      "tgn:2362417",
      "tgn:1000001",
      "tgn:7012149",
      "tgn:2002383",
      "tgn:7007923",
      "tgn:7029392"
    ],
    "placetype": [
      "aat:300006191"
    ],
    "id": 2362417,
    "name:xx": "Greasewood Reservoir"
  }
}
