{
  "geometry": {
    "type": "Point",
    "coordinates": [
      -110.15,
      40.6333
    ]
  },
  "type": "Feature",
  "properties": {
    "hierarchy": [
      "tgn:2672418",
      "tgn:1000001",
      "tgn:2002107",
      "tgn:7012149",
      "tgn:7007827",
      "tgn:7029392"
    ],
    "placetype": [
      "aat:300008697"
    ],
    "id": 2672418,
    "name:xx": "Smokey Spring"
  }
}
