{
  "geometry": {
    "type": "Point",
    "coordinates": [
      -87.0667,
      35.2333
    ]
  },
  "type": "Feature",
  "properties": {
    "hierarchy": [
      "tgn:2101983",
      "tgn:1000001",
      "tgn:7012149",
      "tgn:2001864",
      "tgn:7007825",
      "tgn:7029392"
    ],
    "placetype": [
      "aat:300008347",
      "aat:300387210"
    ],
    "id": 2101983,
    "name:xx": "Wales"
  }
}
