{
  "geometry": {
    "type": "Point",
    "coordinates": [
      -98.25,
      32.5333
    ]
  },
  "type": "Feature",
  "properties": {
    "hierarchy": [
      "tgn:2634046",
      "tgn:1000001",
      "tgn:7012149",
      "tgn:2002053",
      "tgn:7007826",
      "tgn:7029392"
    ],
    "placetype": [
      "aat:300008798"
    ],
    "id": 2634046,
    "name:xx": "Russel Mountain"
  }
}
