{
  "geometry": {
    "type": "Point",
    "coordinates": [
      -73.4833,
      43.7667
    ]
  },
  "type": "Feature",
  "properties": {
    "hierarchy": [
      "tgn:2069843",
      "tgn:1000001",
      "tgn:7012149",
      "tgn:1002986",
      "tgn:7007568",
      "tgn:7029392"
    ],
    "placetype": [
      "aat:300008347",
      "aat:300387210"
    ],
    "id": 2069843,
    "name:xx": "Indian Kettles"
  }
}
