{
  "geometry": {
    "type": "Point",
    "coordinates": [
      42.25,
      17.7333
    ]
  },
  "type": "Feature",
  "properties": {
    "hierarchy": [
      "tgn:1084795",
      "tgn:7000682",
      "tgn:7003875",
      "tgn:1000004",
      "tgn:1000137",
      "tgn:7029392"
    ],
    "placetype": [
      "aat:300008347"
    ],
    "id": 1084795,
    "name:xx": "Ad-Darb"
  }
}
