{
  "geometry": {
    "type": "Point",
    "coordinates": [
      -113.4833,
      41.8333
    ]
  },
  "type": "Feature",
  "properties": {
    "hierarchy": [
      "tgn:2289972",
      "tgn:1000001",
      "tgn:2002102",
      "tgn:7012149",
      "tgn:7007827",
      "tgn:7029392"
    ],
    "placetype": [
      "aat:300008697"
    ],
    "id": 2289972,
    "name:xx": "Docken Corral Spring"
  }
}
