{
  "geometry": {
    "type": "Point",
    "coordinates": [
      -72.4167,
      43.5333
    ]
  },
  "type": "Feature",
  "properties": {
    "hierarchy": [
      "tgn:2109702",
      "tgn:1000001",
      "tgn:2002136",
      "tgn:7012149",
      "tgn:7007828",
      "tgn:7029392"
    ],
    "placetype": [
      "aat:300008347"
    ],
    "id": 2109702,
    "name:xx": "Hartland Four Corners"
  }
}
