{
  "geometry": {
    "type": "Point",
    "coordinates": [
      31.45,
      30.55
    ]
  },
  "type": "Feature",
  "properties": {
    "hierarchy": [
      "tgn:7525004",
      "tgn:7001242",
      "tgn:7016833",
      "tgn:1001113",
      "tgn:7029392"
    ],
    "placetype": [
      "aat:300007783"
    ],
    "name:en": "Az Zankalūn",
    "id": 7525004
  }
}
