{
  "geometry": {
    "type": "Point",
    "coordinates": [
      -105.5833,
      48.85
    ]
  },
  "type": "Feature",
  "properties": {
    "hierarchy": [
      "tgn:2443868",
      "tgn:1000001",
      "tgn:2001269",
      "tgn:7012149",
      "tgn:7007524",
      "tgn:7029392"
    ],
    "placetype": [
      "aat:300008761"
    ],
    "id": 2443868,
    "name:xx": "La Pierre Coulee"
  }
}
