{
  "geometry": {
    "type": "Point",
    "coordinates": [
      -122.45,
      46.8333
    ]
  },
  "type": "Feature",
  "properties": {
    "hierarchy": [
      "tgn:2313153",
      "tgn:1000001",
      "tgn:7012149",
      "tgn:1002942",
      "tgn:7007920",
      "tgn:7029392"
    ],
    "placetype": [
      "aat:300008680"
    ],
    "id": 2313153,
    "name:xx": "Elbow Lake"
  }
}
