{
  "geometry": {
    "type": "Point",
    "coordinates": [
      79.27053,
      26.43089
    ]
  },
  "type": "Feature",
  "properties": {
    "hierarchy": [
      "tgn:7560839",
      "tgn:1000004",
      "tgn:7000198",
      "tgn:7016722",
      "tgn:7029392"
    ],
    "placetype": [
      "aat:300008347"
    ],
    "name:en": "Gudha",
    "id": 7560839
  }
}
