{
  "geometry": {
    "type": "Point",
    "coordinates": [
      -93.9167,
      31.3667
    ]
  },
  "type": "Feature",
  "properties": {
    "hierarchy": [
      "tgn:2629610",
      "tgn:1000001",
      "tgn:7012149",
      "tgn:2002066",
      "tgn:7007826",
      "tgn:7029392"
    ],
    "placetype": [
      "aat:300266640"
    ],
    "id": 2629610,
    "name:xx": "Rosin Ridge"
  }
}
