{
  "type": "FeatureCollection",
  "features": [
    {
      "geometry": {
        "type": "Point",
        "coordinates": [
          -82.8167,
          38.5667
        ]
      },
      "type": "Feature",
      "properties": {
        "hierarchy": [
          "tgn:2039171",
          "tgn:1000001",
          "tgn:7012149",
          "tgn:1002426",
          "tgn:7007255",
          "tgn:7029392"
        ],
        "placetype": [
          "aat:300008347"
        ],
        "id": 2039171,
        "name:xx": "Greenup"
      }
    },
    {
      "geometry": {
        "type": "Point",
        "coordinates": [
          -87.1667,
          37.2
        ]
      },
      "type": "Feature",
      "properties": {
        "hierarchy": [
          "tgn:2039174",
          "tgn:1000001",
          "tgn:7012149",
          "tgn:2000832",
          "tgn:7007255",
          "tgn:7029392"
        ],
        "placetype": [
          "aat:300008347"
        ],
        "id": 2039174,
        "name:xx": "Greenville"
      }
    },
    {
      "geometry": {
        "type": "Point",
        "coordinates": [
          -86.4167,
          36.9333
        ]
      },
      "type": "Feature",
      "properties": {
        "hierarchy": [
          "tgn:2039175",
          "tgn:1000001",
          "tgn:7012149",
          "tgn:2000848",
          "tgn:7007255",
          "tgn:7029392"
        ],
        "placetype": [
          "aat:300008347"
        ],
        "id": 2039175,
        "name:xx": "Greenwood"
      }
    },
    {
      "geometry": {
        "type": "Point",
        "coordinates": [
          -84.3833,
          38.75
        ]
      },
      "type": "Feature",
      "properties": {
        "hierarchy": [
          "tgn:2039176",
          "tgn:1000001",
          "tgn:7012149",
          "tgn:1002778",
          "tgn:7007255",
          "tgn:7029392"
        ],
        "placetype": [
          "aat:300008347",
          "aat:300387210"
        ],
        "id": 2039176,
        "name:xx": "Greenwood"
      }
    },
    {
      "geometry": {
        "type": "Point",
        "coordinates": [
          -84.4833,
          36.8667
        ]
      },
      "type": "Feature",
      "properties": {
        "hierarchy": [
          "tgn:2039177",
          "tgn:1000001",
          "tgn:7012149",
          "tgn:2000818",
          "tgn:7007255",
          "tgn:7029392"
        ],
        "placetype": [
          "aat:300008347"
        ],
        "id": 2039177,
        "name:xx": "Greenwood"
      }
    },
    {
      "geometry": {
        "type": "Point",
        "coordinates": [
          -84.7,
          36.8167
        ]
      },
      "type": "Feature",
      "properties": {
        "hierarchy": [
          "tgn:2039179",
          "tgn:1000001",
          "tgn:7012149",
          "tgn:2000850",
          "tgn:7007255",
          "tgn:7029392"
        ],
        "placetype": [
          "aat:300008347",
          "aat:300387210"
        ],
        "id": 2039179,
        "name:xx": "Gregory"
      }
    }
  ]
}
