{
  "type": "FeatureCollection",
  "features": [
    {
      "geometry": {
        "type": "Point",
        "coordinates": [
          -104.5,
          21.016667
        ]
      },
      "type": "Feature",
      "properties": {
        "hierarchy": [
          "tgn:7365080",
          "tgn:1000001",
          "tgn:1001906",
          "tgn:7005560",
          "tgn:7029392"
        ],
        "placetype": [
          "aat:300008347"
        ],
        "id": 7365080,
        "name:xx": "El Ranchito"
      }
    },
    {
      "geometry": {
        "type": "Point",
        "coordinates": [
          -102.85,
          20.916667
        ]
      },
      "type": "Feature",
      "properties": {
        "hierarchy": [
          "tgn:7365081",
          "tgn:7005586",
          "tgn:1000001",
          "tgn:7005560",
          "tgn:7029392"
        ],
        "placetype": [
          "aat:300008347"
        ],
        "id": 7365081,
        "name:xx": "El Ranchito"
      }
    },
    {
      "geometry": {
        "type": "Point",
        "coordinates": [
          -105.15,
          20.716667
        ]
      },
      "type": "Feature",
      "properties": {
        "hierarchy": [
          "tgn:7365082",
          "tgn:7005586",
          "tgn:1000001",
          "tgn:7005560",
          "tgn:7029392"
        ],
        "placetype": [
          "aat:300008347"
        ],
        "id": 7365082,
        "name:xx": "El Ranchito"
      }
    },
    {
      "geometry": {
        "type": "Point",
        "coordinates": [
          -105.466667,
          19.983333
        ]
      },
      "type": "Feature",
      "properties": {
        "hierarchy": [
          "tgn:7365083",
          "tgn:7005586",
          "tgn:1000001",
          "tgn:7005560",
          "tgn:7029392"
        ],
        "placetype": [
          "aat:300008347"
        ],
        "id": 7365083,
        "name:xx": "El Ranchito"
      }
    },
    {
      "geometry": {
        "type": "Point",
        "coordinates": [
          -104.716667,
          19.65
        ]
      },
      "type": "Feature",
      "properties": {
        "hierarchy": [
          "tgn:7365084",
          "tgn:7005586",
          "tgn:1000001",
          "tgn:7005560",
          "tgn:7029392"
        ],
        "placetype": [
          "aat:300008347"
        ],
        "id": 7365084,
        "name:xx": "El Ranchito"
      }
    },
    {
      "geometry": {
        "type": "Point",
        "coordinates": [
          -103.833333,
          19.233333
        ]
      },
      "type": "Feature",
      "properties": {
        "hierarchy": [
          "tgn:7365085",
          "tgn:7016644",
          "tgn:1000001",
          "tgn:7005560",
          "tgn:7029392"
        ],
        "placetype": [
          "aat:300008347"
        ],
        "id": 7365085,
        "name:xx": "El Ranchito"
      }
    },
    {
      "geometry": {
        "type": "Point",
        "coordinates": [
          -103.533333,
          28.766667
        ]
      },
      "type": "Feature",
      "properties": {
        "hierarchy": [
          "tgn:7365087",
          "tgn:7005581",
          "tgn:1000001",
          "tgn:7005560",
          "tgn:7029392"
        ],
        "placetype": [
          "aat:300000206"
        ],
        "id": 7365087,
        "name:xx": "El Ranchito"
      }
    },
    {
      "geometry": {
        "type": "Point",
        "coordinates": [
          -91.016667,
          17.683333
        ]
      },
      "type": "Feature",
      "properties": {
        "hierarchy": [
          "tgn:7365088",
          "tgn:1000001",
          "tgn:7005596",
          "tgn:7005560",
          "tgn:7029392"
        ],
        "placetype": [
          "aat:300008347"
        ],
        "id": 7365088,
        "name:xx": "El Ramonal"
      }
    },
    {
      "geometry": {
        "type": "Point",
        "coordinates": [
          -99.4,
          26.983333
        ]
      },
      "type": "Feature",
      "properties": {
        "hierarchy": [
          "tgn:7365089",
          "tgn:1000001",
          "tgn:7005597",
          "tgn:7005560",
          "tgn:7029392"
        ],
        "placetype": [
          "aat:300008347"
        ],
        "id": 7365089,
        "name:xx": "El Ramireño"
      }
    }
  ]
}
