{
  "type": "FeatureCollection",
  "features": [
    {
      "geometry": {
        "type": "Point",
        "coordinates": [
          11.333333,
          52
        ]
      },
      "type": "Feature",
      "properties": {
        "hierarchy": [
          "tgn:7147000",
          "tgn:1000003",
          "tgn:7003687",
          "tgn:7000084",
          "tgn:7029392"
        ],
        "placetype": [
          "aat:300008347"
        ],
        "id": 7147000,
        "name:xx": "Klein Oschersleben"
      }
    },
    {
      "geometry": {
        "type": "Point",
        "coordinates": [
          12.433333,
          48
        ]
      },
      "type": "Feature",
      "properties": {
        "hierarchy": [
          "tgn:7147001",
          "tgn:7003669",
          "tgn:1000003",
          "tgn:7000084",
          "tgn:7029392"
        ],
        "placetype": [
          "aat:300008347"
        ],
        "id": 7147001,
        "name:xx": "Kleinornach"
      }
    },
    {
      "geometry": {
        "type": "Point",
        "coordinates": [
          13.6,
          51
        ]
      },
      "type": "Feature",
      "properties": {
        "hierarchy": [
          "tgn:7147002",
          "tgn:1000003",
          "tgn:7003685",
          "tgn:7000084",
          "tgn:7029392"
        ],
        "placetype": [
          "aat:300008347"
        ],
        "id": 7147002,
        "name:xx": "Kleinopitz"
      }
    },
    {
      "geometry": {
        "type": "Point",
        "coordinates": [
          8.916667,
          54.3
        ]
      },
      "type": "Feature",
      "properties": {
        "hierarchy": [
          "tgn:7147003",
          "tgn:1000003",
          "tgn:7003688",
          "tgn:7000084",
          "tgn:7029392"
        ],
        "placetype": [
          "aat:300008347"
        ],
        "id": 7147003,
        "name:xx": "Klein Olversum"
      }
    },
    {
      "geometry": {
        "type": "Point",
        "coordinates": [
          7.866667,
          53.616667
        ]
      },
      "type": "Feature",
      "properties": {
        "hierarchy": [
          "tgn:7147004",
          "tgn:1000003",
          "tgn:7003676",
          "tgn:7000084",
          "tgn:7029392"
        ],
        "placetype": [
          "aat:300000206"
        ],
        "id": 7147004,
        "name:xx": "Klein Ollacker"
      }
    },
    {
      "geometry": {
        "type": "Point",
        "coordinates": [
          7.733333,
          53.333333
        ]
      },
      "type": "Feature",
      "properties": {
        "hierarchy": [
          "tgn:7147005",
          "tgn:1000003",
          "tgn:7003676",
          "tgn:7000084",
          "tgn:7029392"
        ],
        "placetype": [
          "aat:300008347"
        ],
        "id": 7147005,
        "name:xx": "Kleinoldendorf"
      }
    },
    {
      "geometry": {
        "type": "Point",
        "coordinates": [
          12.916667,
          48.333333
        ]
      },
      "type": "Feature",
      "properties": {
        "hierarchy": [
          "tgn:7147006",
          "tgn:7003669",
          "tgn:1000003",
          "tgn:7000084",
          "tgn:7029392"
        ],
        "placetype": [
          "aat:300000206"
        ],
        "id": 7147006,
        "name:xx": "Kleinölbrunn"
      }
    },
    {
      "geometry": {
        "type": "Point",
        "coordinates": [
          13.016667,
          50.8
        ]
      },
      "type": "Feature",
      "properties": {
        "hierarchy": [
          "tgn:7147007",
          "tgn:1000003",
          "tgn:7003685",
          "tgn:7000084",
          "tgn:7029392"
        ],
        "placetype": [
          "aat:300008347"
        ],
        "id": 7147007,
        "name:xx": "Kleinolbersdorf"
      }
    },
    {
      "geometry": {
        "type": "Point",
        "coordinates": [
          10.433333,
          49.133333
        ]
      },
      "type": "Feature",
      "properties": {
        "hierarchy": [
          "tgn:7147008",
          "tgn:7003669",
          "tgn:1000003",
          "tgn:7000084",
          "tgn:7029392"
        ],
        "placetype": [
          "aat:300008347"
        ],
        "id": 7147008,
        "name:xx": "Kleinohrenbronn"
      }
    },
    {
      "geometry": {
        "type": "Point",
        "coordinates": [
          9.7,
          53.8
        ]
      },
      "type": "Feature",
      "properties": {
        "hierarchy": [
          "tgn:7147009",
          "tgn:1000003",
          "tgn:7003688",
          "tgn:7000084",
          "tgn:7029392"
        ],
        "placetype": [
          "aat:300000745"
        ],
        "id": 7147009,
        "name:xx": "Klein Offenseth"
      }
    }
  ]
}
