{
  "geometry": {
    "type": "Point",
    "coordinates": [
      -87.3167,
      35.05
    ]
  },
  "type": "Feature",
  "properties": {
    "hierarchy": [
      "tgn:2259585",
      "tgn:1000001",
      "tgn:7012149",
      "tgn:7029392"
    ],
    "placetype": [
      "aat:300008706"
    ],
    "id": 2259585,
    "name:xx": "Cotts Creek"
  }
}
