{
  "geometry": {
    "type": "Point",
    "coordinates": [
      -106.5667,
      37.9167
    ]
  },
  "type": "Feature",
  "properties": {
    "hierarchy": [
      "tgn:2443635",
      "tgn:1000001",
      "tgn:7012149",
      "tgn:7007158",
      "tgn:2000246",
      "tgn:7029392"
    ],
    "placetype": [
      "aat:300008706"
    ],
    "id": 2443635,
    "name:xx": "La Garita Creek"
  }
}
