{
  "type": "FeatureCollection",
  "features": [
    {
      "geometry": {
        "type": "Point",
        "coordinates": [
          -104.6,
          45.0167
        ]
      },
      "type": "Feature",
      "properties": {
        "hierarchy": [
          "tgn:2783900",
          "tgn:1000001",
          "tgn:2001265",
          "tgn:7012149",
          "tgn:7007524",
          "tgn:7029392"
        ],
        "placetype": [
          "aat:300000390"
        ],
        "id": 2783900,
        "name:xx": "X58-27-4 Mine"
      }
    },
    {
      "geometry": {
        "type": "Point",
        "coordinates": [
          -104.6,
          45
        ]
      },
      "type": "Feature",
      "properties": {
        "hierarchy": [
          "tgn:2783901",
          "tgn:1000001",
          "tgn:2001265",
          "tgn:7012149",
          "tgn:7007524",
          "tgn:7029392"
        ],
        "placetype": [
          "aat:300000390"
        ],
        "id": 2783901,
        "name:xx": "X58-33-3 Mine"
      }
    },
    {
      "geometry": {
        "type": "Point",
        "coordinates": [
          -109.3167,
          33.1833
        ]
      },
      "type": "Feature",
      "properties": {
        "hierarchy": [
          "tgn:2783902",
          "tgn:1000001",
          "tgn:7006451",
          "tgn:2000095",
          "tgn:7012149",
          "tgn:7029392"
        ],
        "placetype": [
          "aat:300008697"
        ],
        "id": 2783902,
        "name:xx": "XA Spring"
      }
    },
    {
      "geometry": {
        "type": "Point",
        "coordinates": [
          -105.1,
          42.7333
        ]
      },
      "type": "Feature",
      "properties": {
        "hierarchy": [
          "tgn:2783904",
          "tgn:1000001",
          "tgn:2002369",
          "tgn:7012149",
          "tgn:7007923",
          "tgn:7029392"
        ],
        "placetype": [
          "aat:300008347"
        ],
        "id": 2783904,
        "name:xx": "XH Crossing"
      }
    },
    {
      "geometry": {
        "type": "Point",
        "coordinates": [
          -119.05,
          43.9333
        ]
      },
      "type": "Feature",
      "properties": {
        "hierarchy": [
          "tgn:2783905",
          "tgn:1000001",
          "tgn:7012149",
          "tgn:2001709",
          "tgn:7007708",
          "tgn:7029392"
        ],
        "placetype": [
          "aat:300008697"
        ],
        "id": 2783905,
        "name:xx": "XI Spring"
      }
    },
    {
      "geometry": {
        "type": "Point",
        "coordinates": [
          -110.3333,
          34.3833
        ]
      },
      "type": "Feature",
      "properties": {
        "hierarchy": [
          "tgn:2783906",
          "tgn:1000001",
          "tgn:7006451",
          "tgn:7012149",
          "tgn:2000099",
          "tgn:7029392"
        ],
        "placetype": [
          "aat:300006191"
        ],
        "id": 2783906,
        "name:xx": "XIL Tank"
      }
    },
    {
      "geometry": {
        "type": "Point",
        "coordinates": [
          -120.2167,
          42.7667
        ]
      },
      "type": "Feature",
      "properties": {
        "hierarchy": [
          "tgn:2783907",
          "tgn:1000001",
          "tgn:7012149",
          "tgn:2001715",
          "tgn:7007708",
          "tgn:7029392"
        ],
        "placetype": [
          "aat:300008697"
        ],
        "id": 2783907,
        "name:xx": "XL Spring"
      }
    },
    {
      "geometry": {
        "type": "Point",
        "coordinates": [
          -104.6167,
          32
        ]
      },
      "type": "Feature",
      "properties": {
        "hierarchy": [
          "tgn:2783908",
          "tgn:1000001",
          "tgn:2001436",
          "tgn:7012149",
          "tgn:7007566",
          "tgn:7029392"
        ],
        "placetype": [
          "aat:300008761"
        ],
        "id": 2783908,
        "name:xx": "XT Draw"
      }
    },
    {
      "geometry": {
        "type": "Point",
        "coordinates": [
          -104.6167,
          32
        ]
      },
      "type": "Feature",
      "properties": {
        "hierarchy": [
          "tgn:2783909",
          "tgn:1000001",
          "tgn:2001436",
          "tgn:7012149",
          "tgn:7007566",
          "tgn:7029392"
        ],
        "placetype": [
          "aat:300008697"
        ],
        "id": 2783909,
        "name:xx": "XT Spring"
      }
    }
  ]
}
