{
  "geometry": {
    "type": "Point",
    "coordinates": [
      -73.95,
      43.2333
    ]
  },
  "type": "Feature",
  "properties": {
    "hierarchy": [
      "tgn:2541117",
      "tgn:1000001",
      "tgn:7012149",
      "tgn:1002871",
      "tgn:7007568",
      "tgn:7029392"
    ],
    "placetype": [
      "aat:300008798"
    ],
    "id": 2541117,
    "name:xx": "Nick Mountain"
  }
}
