{
  "geometry": {
    "type": "Point",
    "coordinates": [
      -94.216667,
      17.55
    ]
  },
  "type": "Feature",
  "properties": {
    "hierarchy": [
      "tgn:7400279",
      "tgn:1000001",
      "tgn:7005599",
      "tgn:7005560",
      "tgn:7029392"
    ],
    "placetype": [
      "aat:300008699"
    ],
    "id": 7400279,
    "name:xx": "El Burro, Río"
  }
}
