{
  "geometry": {
    "type": "Point",
    "coordinates": [
      132.9667,
      33.0333
    ]
  },
  "type": "Feature",
  "properties": {
    "hierarchy": [
      "tgn:7004737",
      "tgn:1000991",
      "tgn:1000004",
      "tgn:7000903",
      "tgn:1000120",
      "tgn:7029392"
    ],
    "placetype": [
      "aat:300008347"
    ],
    "id": 7004737,
    "name:xx": "Nakamura"
  }
}
