{
  "geometry": {
    "type": "Point",
    "coordinates": [
      -108.6667,
      35.3167
    ]
  },
  "type": "Feature",
  "properties": {
    "hierarchy": [
      "tgn:2584084",
      "tgn:1000001",
      "tgn:7012149",
      "tgn:7019676",
      "tgn:7007566",
      "tgn:7029392"
    ],
    "placetype": [
      "aat:300008347"
    ],
    "id": 2584084,
    "name:xx": "Pinehaven"
  }
}
