{
  "geometry": {
    "type": "Point",
    "coordinates": [
      82.56989,
      25.480776
    ]
  },
  "type": "Feature",
  "properties": {
    "hierarchy": [
      "tgn:7557174",
      "tgn:1000004",
      "tgn:7000198",
      "tgn:7016722",
      "tgn:7029392"
    ],
    "placetype": [
      "aat:300008347"
    ],
    "name:en": "Rāmpur",
    "id": 7557174
  }
}
