{
  "geometry": {
    "type": "Point",
    "coordinates": [
      153.169,
      -25.25
    ]
  },
  "type": "Feature",
  "properties": {
    "hierarchy": [
      "tgn:1007131",
      "tgn:7000490",
      "tgn:1000006",
      "tgn:7001830",
      "tgn:7029392"
    ],
    "placetype": [
      "aat:300008791",
      "aat:300263063"
    ],
    "id": 1007131,
    "name:xx": "Fraser Island"
  }
}
