{
  "geometry": {
    "type": "Point",
    "coordinates": [
      27.7667,
      -18.9333
    ]
  },
  "type": "Feature",
  "properties": {
    "hierarchy": [
      "tgn:1092411",
      "tgn:7001242",
      "tgn:1001422",
      "tgn:1000185",
      "tgn:7029392"
    ],
    "placetype": [
      "aat:300008347"
    ],
    "id": 1092411,
    "name:xx": "Lupani"
  }
}
