{
  "type": "FeatureCollection",
  "features": [
    {
      "geometry": {
        "type": "Point",
        "coordinates": [
          94.316778,
          25.718212
        ]
      },
      "type": "Feature",
      "properties": {
        "hierarchy": [
          "tgn:7549370",
          "tgn:1000004",
          "tgn:7000198",
          "tgn:1001905",
          "tgn:7029392"
        ],
        "placetype": [
          "aat:300008347"
        ],
        "name:en": "Chozumi",
        "id": 7549370
      }
    },
    {
      "geometry": {
        "type": "Point",
        "coordinates": [
          88.186885,
          23.942479
        ]
      },
      "type": "Feature",
      "properties": {
        "hierarchy": [
          "tgn:7549371",
          "tgn:1000004",
          "tgn:7000198",
          "tgn:1001977",
          "tgn:7029392"
        ],
        "placetype": [
          "aat:300007783"
        ],
        "name:en": "Chowrig훮cha",
        "id": 7549371
      }
    },
    {
      "geometry": {
        "type": "Point",
        "coordinates": [
          93.033333,
          8.45
        ]
      },
      "type": "Feature",
      "properties": {
        "hierarchy": [
          "tgn:7549372",
          "tgn:7016678",
          "tgn:7000204",
          "tgn:1000004",
          "tgn:7000198",
          "tgn:7029392"
        ],
        "placetype": [
          "aat:300008791"
        ],
        "name:en": "Chowra Island",
        "id": 7549372
      }
    },
    {
      "geometry": {
        "type": "Point",
        "coordinates": [
          89.316667,
          26.1
        ]
      },
      "type": "Feature",
      "properties": {
        "hierarchy": [
          "tgn:7549373",
          "tgn:1000004",
          "tgn:7000198",
          "tgn:1001977",
          "tgn:7029392"
        ],
        "placetype": [
          "aat:300008699"
        ],
        "name:en": "Chotona",
        "id": 7549373
      }
    },
    {
      "geometry": {
        "type": "Point",
        "coordinates": [
          75.790393,
          29.845851
        ]
      },
      "type": "Feature",
      "properties": {
        "hierarchy": [
          "tgn:7549375",
          "tgn:1000004",
          "tgn:7000198",
          "tgn:7016883",
          "tgn:7029392"
        ],
        "placetype": [
          "aat:300008347"
        ],
        "name:en": "Choti훮n",
        "id": 7549375
      }
    },
    {
      "geometry": {
        "type": "Point",
        "coordinates": [
          85,
          23
        ]
      },
      "type": "Feature",
      "properties": {
        "hierarchy": [
          "tgn:7549376",
          "tgn:1000004",
          "tgn:7000198",
          "tgn:7031783",
          "tgn:7029392"
        ],
        "placetype": [
          "aat:300132339"
        ],
        "name:en": "Chota N훮gpur Plateau",
        "id": 7549376
      }
    },
    {
      "geometry": {
        "type": "Point",
        "coordinates": [
          88.9,
          22.216667
        ]
      },
      "type": "Feature",
      "properties": {
        "hierarchy": [
          "tgn:7549377",
          "tgn:1000004",
          "tgn:7000198",
          "tgn:1001977",
          "tgn:7029392"
        ],
        "placetype": [
          "aat:300008347"
        ],
        "name:en": "Chota Mollakh훮li",
        "id": 7549377
      }
    },
    {
      "geometry": {
        "type": "Point",
        "coordinates": [
          83.2,
          22.916667
        ]
      },
      "type": "Feature",
      "properties": {
        "hierarchy": [
          "tgn:7549378",
          "tgn:1000004",
          "tgn:7031781",
          "tgn:7000198",
          "tgn:7029392"
        ],
        "placetype": [
          "aat:300008347"
        ],
        "name:en": "Chota Damali",
        "id": 7549378
      }
    },
    {
      "geometry": {
        "type": "Point",
        "coordinates": [
          74.3,
          23.15
        ]
      },
      "type": "Feature",
      "properties": {
        "hierarchy": [
          "tgn:7549379",
          "tgn:1000004",
          "tgn:7000198",
          "tgn:7016788",
          "tgn:7029392"
        ],
        "placetype": [
          "aat:300008347"
        ],
        "name:en": "Chota",
        "id": 7549379
      }
    }
  ]
}
