{
  "geometry": {
    "type": "Point",
    "coordinates": [
      -147.9833,
      63.2167
    ]
  },
  "type": "Feature",
  "properties": {
    "hierarchy": [
      "tgn:2211236",
      "tgn:7006450",
      "tgn:1000001",
      "tgn:2124053",
      "tgn:7012149",
      "tgn:7029392"
    ],
    "placetype": [
      "aat:300008706"
    ],
    "id": 2211236,
    "name:xx": "Butte Creek"
  }
}
