{
  "geometry": {
    "type": "Point",
    "coordinates": [
      -93.75,
      34.0333
    ]
  },
  "type": "Feature",
  "properties": {
    "hierarchy": [
      "tgn:2387979",
      "tgn:1000001",
      "tgn:7016172",
      "tgn:7012149",
      "tgn:7029392"
    ],
    "placetype": [
      "aat:300008706"
    ],
    "id": 2387979,
    "name:xx": "Hickory Creek"
  }
}
