{
  "geometry": {
    "type": "Point",
    "coordinates": [
      79.466402,
      26.466403
    ]
  },
  "type": "Feature",
  "properties": {
    "hierarchy": [
      "tgn:7565329",
      "tgn:1000004",
      "tgn:7000198",
      "tgn:7016722",
      "tgn:7029392"
    ],
    "placetype": [
      "aat:300008347"
    ],
    "name:en": "Gohānān",
    "id": 7565329
  }
}
