{
  "geometry": {
    "type": "Point",
    "coordinates": [
      -77.2333,
      37.85
    ]
  },
  "type": "Feature",
  "properties": {
    "hierarchy": [
      "tgn:2111522",
      "tgn:1000001",
      "tgn:7012149",
      "tgn:1002548",
      "tgn:7007919",
      "tgn:7029392"
    ],
    "placetype": [
      "aat:300008347",
      "aat:300387210"
    ],
    "id": 2111522,
    "name:xx": "Duane"
  }
}
