{
  "geometry": {
    "type": "Point",
    "coordinates": [
      -77.7667,
      40.3833
    ]
  },
  "type": "Feature",
  "properties": {
    "hierarchy": [
      "tgn:2763754",
      "tgn:1000001",
      "tgn:7012149",
      "tgn:1002669",
      "tgn:7007710",
      "tgn:7029392"
    ],
    "placetype": [
      "aat:300008699"
    ],
    "id": 2763754,
    "name:xx": "Wharton Run"
  }
}
