{
  "geometry": {
    "type": "Point",
    "coordinates": [
      -110.6333,
      34.0667
    ]
  },
  "type": "Feature",
  "properties": {
    "hierarchy": [
      "tgn:2360385",
      "tgn:1000001",
      "tgn:7006451",
      "tgn:7012149",
      "tgn:2000099",
      "tgn:7029392"
    ],
    "placetype": [
      "aat:300006191"
    ],
    "id": 2360385,
    "name:xx": "Grasshopper Tank Number Two"
  }
}
