{
  "geometry": {
    "type": "Point",
    "coordinates": [
      -73.3667,
      43.7333
    ]
  },
  "type": "Feature",
  "properties": {
    "hierarchy": [
      "tgn:2601669",
      "tgn:1000001",
      "tgn:7012149",
      "tgn:1002993",
      "tgn:7007568",
      "tgn:7029392"
    ],
    "placetype": [
      "aat:300008347"
    ],
    "id": 2601669,
    "name:xx": "Putnam"
  }
}
