{
  "geometry": {
    "type": "Point",
    "coordinates": [
      -113.8333,
      44.0833
    ]
  },
  "type": "Feature",
  "properties": {
    "hierarchy": [
      "tgn:2764936",
      "tgn:1000001",
      "tgn:2000470",
      "tgn:7012149",
      "tgn:7007250",
      "tgn:7029392"
    ],
    "placetype": [
      "aat:300008697"
    ],
    "id": 2764936,
    "name:xx": "Whiskey Springs"
  }
}
