{
  "type": "FeatureCollection",
  "features": [
    {
      "geometry": {
        "type": "Point",
        "coordinates": [
          -95.3167,
          38.8
        ]
      },
      "type": "Feature",
      "properties": {
        "hierarchy": [
          "tgn:2236330",
          "tgn:1000001",
          "tgn:2000682",
          "tgn:7012149",
          "tgn:7007254",
          "tgn:7029392"
        ],
        "placetype": [
          "aat:300008706"
        ],
        "id": 2236330,
        "name:xx": "Chicken Creek"
      }
    },
    {
      "geometry": {
        "type": "Point",
        "coordinates": [
          -95.6667,
          38.5667
        ]
      },
      "type": "Feature",
      "properties": {
        "hierarchy": [
          "tgn:2236331",
          "tgn:1000001",
          "tgn:7012149",
          "tgn:2000729",
          "tgn:7007254",
          "tgn:7029392"
        ],
        "placetype": [
          "aat:300008706"
        ],
        "id": 2236331,
        "name:xx": "Chicken Creek"
      }
    },
    {
      "geometry": {
        "type": "Point",
        "coordinates": [
          -86,
          44.3333
        ]
      },
      "type": "Feature",
      "properties": {
        "hierarchy": [
          "tgn:2236332",
          "tgn:1000001",
          "tgn:7012149",
          "tgn:2000974",
          "tgn:7007520",
          "tgn:7029392"
        ],
        "placetype": [
          "aat:300008706"
        ],
        "id": 2236332,
        "name:xx": "Chicken Creek"
      }
    },
    {
      "geometry": {
        "type": "Point",
        "coordinates": [
          -92.4,
          47.0167
        ]
      },
      "type": "Feature",
      "properties": {
        "hierarchy": [
          "tgn:2236333",
          "tgn:1000001",
          "tgn:7012149",
          "tgn:2001067",
          "tgn:7007521",
          "tgn:7029392"
        ],
        "placetype": [
          "aat:300008706"
        ],
        "id": 2236333,
        "name:xx": "Chicken Creek"
      }
    },
    {
      "geometry": {
        "type": "Point",
        "coordinates": [
          -110.4667,
          45.6333
        ]
      },
      "type": "Feature",
      "properties": {
        "hierarchy": [
          "tgn:2236334",
          "tgn:1000001",
          "tgn:7012149",
          "tgn:2001293",
          "tgn:7007524",
          "tgn:7029392"
        ],
        "placetype": [
          "aat:300008706"
        ],
        "id": 2236334,
        "name:xx": "Chicken Creek"
      }
    },
    {
      "geometry": {
        "type": "Point",
        "coordinates": [
          -110.1833,
          45.65
        ]
      },
      "type": "Feature",
      "properties": {
        "hierarchy": [
          "tgn:2236335",
          "tgn:1000001",
          "tgn:7012149",
          "tgn:2001308",
          "tgn:7007524",
          "tgn:7029392"
        ],
        "placetype": [
          "aat:300008706"
        ],
        "id": 2236335,
        "name:xx": "Chicken Creek"
      }
    },
    {
      "geometry": {
        "type": "Point",
        "coordinates": [
          -112.8,
          46.85
        ]
      },
      "type": "Feature",
      "properties": {
        "hierarchy": [
          "tgn:2236336",
          "tgn:1000001",
          "tgn:7012149",
          "tgn:2001298",
          "tgn:7007524",
          "tgn:7029392"
        ],
        "placetype": [
          "aat:300008706"
        ],
        "id": 2236336,
        "name:xx": "Chicken Creek"
      }
    },
    {
      "geometry": {
        "type": "Point",
        "coordinates": [
          -114.5,
          48.6333
        ]
      },
      "type": "Feature",
      "properties": {
        "hierarchy": [
          "tgn:2236337",
          "tgn:1000001",
          "tgn:7012149",
          "tgn:2001274",
          "tgn:7007524",
          "tgn:7029392"
        ],
        "placetype": [
          "aat:300008706"
        ],
        "id": 2236337,
        "name:xx": "Chicken Creek"
      }
    },
    {
      "geometry": {
        "type": "Point",
        "coordinates": [
          -114.4167,
          45.6333
        ]
      },
      "type": "Feature",
      "properties": {
        "hierarchy": [
          "tgn:2236338",
          "tgn:1000001",
          "tgn:7012149",
          "tgn:2001300",
          "tgn:7007524",
          "tgn:7029392"
        ],
        "placetype": [
          "aat:300008706"
        ],
        "id": 2236338,
        "name:xx": "Chicken Creek"
      }
    },
    {
      "geometry": {
        "type": "Point",
        "coordinates": [
          -114.7167,
          46.95
        ]
      },
      "type": "Feature",
      "properties": {
        "hierarchy": [
          "tgn:2236339",
          "tgn:1000001",
          "tgn:7012149",
          "tgn:2001290",
          "tgn:7007524",
          "tgn:7029392"
        ],
        "placetype": [
          "aat:300008706"
        ],
        "id": 2236339,
        "name:xx": "Chicken Creek"
      }
    }
  ]
}
