{
  "geometry": {
    "type": "Point",
    "coordinates": [
      -86.25,
      40.55
    ]
  },
  "type": "Feature",
  "properties": {
    "hierarchy": [
      "tgn:2379094",
      "tgn:1000001",
      "tgn:7012149",
      "tgn:1002487",
      "tgn:7007252",
      "tgn:7029392"
    ],
    "placetype": [
      "aat:300006075"
    ],
    "id": 2379094,
    "name:xx": "Hartman Ditch"
  }
}
