{
  "geometry": {
    "type": "Point",
    "coordinates": [
      -100.5667,
      42.95
    ]
  },
  "type": "Feature",
  "properties": {
    "hierarchy": [
      "tgn:2357331",
      "tgn:1000001",
      "tgn:2001331",
      "tgn:7012149",
      "tgn:7007525",
      "tgn:7029392"
    ],
    "placetype": [
      "aat:300008761"
    ],
    "id": 2357331,
    "name:xx": "Government Canyon"
  }
}
