{
  "geometry": {
    "type": "Point",
    "coordinates": [
      -90.1833,
      41.6667
    ]
  },
  "type": "Feature",
  "properties": {
    "hierarchy": [
      "tgn:2505995",
      "tgn:1000001",
      "tgn:7012149",
      "tgn:7007251",
      "tgn:7029392"
    ],
    "placetype": [
      "aat:300006075"
    ],
    "id": 2505995,
    "name:xx": "Meredosia Ditch"
  }
}
