{
  "geometry": {
    "type": "Point",
    "coordinates": [
      -110.4333,
      46.05
    ]
  },
  "type": "Feature",
  "properties": {
    "hierarchy": [
      "tgn:2546397",
      "tgn:1000001",
      "tgn:7012149",
      "tgn:2001293",
      "tgn:7007524",
      "tgn:7029392"
    ],
    "placetype": [
      "aat:300008706"
    ],
    "id": 2546397,
    "name:xx": "North Fork Horse Creek"
  }
}
