{
  "geometry": {
    "type": "Point",
    "coordinates": [
      -71.8333,
      46.5667
    ]
  },
  "type": "Feature",
  "properties": {
    "hierarchy": [
      "tgn:1015588",
      "tgn:7005685",
      "tgn:1000001",
      "tgn:7005804",
      "tgn:7029392"
    ],
    "placetype": [
      "aat:300008347"
    ],
    "id": 1015588,
    "name:xx": "Rivière-Bois-Clair"
  }
}
