{
  "geometry": {
    "type": "Point",
    "coordinates": [
      -104.1833,
      44.8833
    ]
  },
  "type": "Feature",
  "properties": {
    "hierarchy": [
      "tgn:2437112",
      "tgn:1000001",
      "tgn:2002370",
      "tgn:7012149",
      "tgn:7007923",
      "tgn:7029392"
    ],
    "placetype": [
      "aat:300008706"
    ],
    "id": 2437112,
    "name:xx": "Kilpatrick Creek"
  }
}
