{
  "geometry": {
    "type": "Point",
    "coordinates": [
      -75.35,
      41.1333
    ]
  },
  "type": "Feature",
  "properties": {
    "hierarchy": [
      "tgn:2533218",
      "tgn:1000001",
      "tgn:7012149",
      "tgn:1002682",
      "tgn:7007710",
      "tgn:7029392"
    ],
    "placetype": [
      "aat:300008347"
    ],
    "id": 2533218,
    "name:xx": "Mushroom Farms"
  }
}
