{
  "geometry": {
    "type": "Point",
    "coordinates": [
      -74.3833,
      41.9667
    ]
  },
  "type": "Feature",
  "properties": {
    "hierarchy": [
      "tgn:2465528",
      "tgn:1000001",
      "tgn:7012149",
      "tgn:1002961",
      "tgn:7007568",
      "tgn:7029392"
    ],
    "placetype": [
      "aat:300008798"
    ],
    "id": 2465528,
    "name:xx": "Lone Mountain"
  }
}
