{
  "geometry": {
    "type": "Point",
    "coordinates": [
      -112.9833,
      37.5167
    ]
  },
  "type": "Feature",
  "properties": {
    "hierarchy": [
      "tgn:2151929",
      "tgn:1000001",
      "tgn:7012149",
      "tgn:2002111",
      "tgn:7007827",
      "tgn:7029392"
    ],
    "placetype": [
      "aat:300008850"
    ],
    "id": 2151929,
    "name:xx": "Bauer Point"
  }
}
