{
  "geometry": {
    "type": "Point",
    "coordinates": [
      38.9667,
      38.7667
    ]
  },
  "type": "Feature",
  "properties": {
    "hierarchy": [
      "tgn:1086158",
      "tgn:1001236",
      "tgn:1000004",
      "tgn:7018455",
      "tgn:1000144",
      "tgn:7029392"
    ],
    "placetype": [
      "aat:300008347"
    ],
    "id": 1086158,
    "name:xx": "Hidirbaba"
  }
}
