{
  "geometry": {
    "type": "Point",
    "coordinates": [
      -122.6667,
      42.3667
    ]
  },
  "type": "Feature",
  "properties": {
    "hierarchy": [
      "tgn:2784246",
      "tgn:1000001",
      "tgn:7012149",
      "tgn:2001711",
      "tgn:7007708",
      "tgn:7029392"
    ],
    "placetype": [
      "aat:300008706"
    ],
    "id": 2784246,
    "name:xx": "Yankee Creek"
  }
}
