{
  "geometry": {
    "type": "Point",
    "coordinates": [
      -115.7833,
      44.1167
    ]
  },
  "type": "Feature",
  "properties": {
    "hierarchy": [
      "tgn:2132948",
      "tgn:1000001",
      "tgn:2000459",
      "tgn:7012149",
      "tgn:7007250",
      "tgn:7029392"
    ],
    "placetype": [
      "aat:300008706"
    ],
    "id": 2132948,
    "name:xx": "Anderson Creek"
  }
}
