{
  "type": "FeatureCollection",
  "features": [
    {
      "geometry": {
        "type": "Point",
        "coordinates": [
          -77.1,
          35.7167
        ]
      },
      "type": "Feature",
      "properties": {
        "hierarchy": [
          "tgn:2154650",
          "tgn:1000001",
          "tgn:7012149",
          "tgn:7007709",
          "tgn:7029392"
        ],
        "placetype": [
          "aat:300008699"
        ],
        "id": 2154650,
        "name:xx": "Bear Grass Swamp"
      }
    },
    {
      "geometry": {
        "type": "Point",
        "coordinates": [
          -110.4833,
          33.8333
        ]
      },
      "type": "Feature",
      "properties": {
        "hierarchy": [
          "tgn:2154651",
          "tgn:1000001",
          "tgn:7006451",
          "tgn:2000093",
          "tgn:7012149",
          "tgn:7029392"
        ],
        "placetype": [
          "aat:300006191"
        ],
        "id": 2154651,
        "name:xx": "Bear Grass Tank"
      }
    },
    {
      "geometry": {
        "type": "Point",
        "coordinates": [
          -111.7833,
          34.4
        ]
      },
      "type": "Feature",
      "properties": {
        "hierarchy": [
          "tgn:2154652",
          "tgn:1000001",
          "tgn:7006451",
          "tgn:7012149",
          "tgn:2000103",
          "tgn:7029392"
        ],
        "placetype": [
          "aat:300006191"
        ],
        "id": 2154652,
        "name:xx": "Bear Grass Tank"
      }
    },
    {
      "geometry": {
        "type": "Point",
        "coordinates": [
          -111.1833,
          31.55
        ]
      },
      "type": "Feature",
      "properties": {
        "hierarchy": [
          "tgn:2154653",
          "tgn:1000001",
          "tgn:7006451",
          "tgn:7012149",
          "tgn:2000100",
          "tgn:7029392"
        ],
        "placetype": [
          "aat:300006191"
        ],
        "id": 2154653,
        "name:xx": "Bear Grass Tank"
      }
    },
    {
      "geometry": {
        "type": "Point",
        "coordinates": [
          -101.0667,
          33.15
        ]
      },
      "type": "Feature",
      "properties": {
        "hierarchy": [
          "tgn:2154654",
          "tgn:1000001",
          "tgn:7012149",
          "tgn:2001989",
          "tgn:7007826",
          "tgn:7029392"
        ],
        "placetype": [
          "aat:300006191"
        ],
        "id": 2154654,
        "name:xx": "Bear Grass Tank"
      }
    },
    {
      "geometry": {
        "type": "Point",
        "coordinates": [
          -155.4667,
          64.4333
        ]
      },
      "type": "Feature",
      "properties": {
        "hierarchy": [
          "tgn:2154655",
          "tgn:7006450",
          "tgn:1000001",
          "tgn:7012149",
          "tgn:2000089",
          "tgn:7029392"
        ],
        "placetype": [
          "aat:300008761"
        ],
        "id": 2154655,
        "name:xx": "Bear Gulch"
      }
    },
    {
      "geometry": {
        "type": "Point",
        "coordinates": [
          -109.4,
          32.1333
        ]
      },
      "type": "Feature",
      "properties": {
        "hierarchy": [
          "tgn:2154656",
          "tgn:1000001",
          "tgn:7006451",
          "tgn:2000091",
          "tgn:7012149",
          "tgn:7029392"
        ],
        "placetype": [
          "aat:300008761"
        ],
        "id": 2154656,
        "name:xx": "Bear Gulch"
      }
    },
    {
      "geometry": {
        "type": "Point",
        "coordinates": [
          -121.1667,
          37.2
        ]
      },
      "type": "Feature",
      "properties": {
        "hierarchy": [
          "tgn:2154657",
          "tgn:1000001",
          "tgn:7012149",
          "tgn:7007157",
          "tgn:1002915",
          "tgn:7029392"
        ],
        "placetype": [
          "aat:300008761"
        ],
        "id": 2154657,
        "name:xx": "Bear Gulch"
      }
    },
    {
      "geometry": {
        "type": "Point",
        "coordinates": [
          -122.3167,
          37.4167
        ]
      },
      "type": "Feature",
      "properties": {
        "hierarchy": [
          "tgn:2154658",
          "tgn:1000001",
          "tgn:7012149",
          "tgn:7007157",
          "tgn:1002864",
          "tgn:7029392"
        ],
        "placetype": [
          "aat:300008761"
        ],
        "id": 2154658,
        "name:xx": "Bear Gulch"
      }
    },
    {
      "geometry": {
        "type": "Point",
        "coordinates": [
          -121.6833,
          37.4667
        ]
      },
      "type": "Feature",
      "properties": {
        "hierarchy": [
          "tgn:2154659",
          "tgn:1000001",
          "tgn:7012149",
          "tgn:7007157",
          "tgn:7029392"
        ],
        "placetype": [
          "aat:300008761"
        ],
        "id": 2154659,
        "name:xx": "Bear Gulch"
      }
    }
  ]
}
