{
  "geometry": {
    "type": "Point",
    "coordinates": [
      -89.65,
      41.65
    ]
  },
  "type": "Feature",
  "properties": {
    "hierarchy": [
      "tgn:2777501",
      "tgn:1000001",
      "tgn:7012149",
      "tgn:7007251",
      "tgn:7029392"
    ],
    "placetype": [
      "aat:300006075"
    ],
    "id": 2777501,
    "name:xx": "Winnebago Ditch"
  }
}
