{
  "geometry": {
    "type": "Point",
    "coordinates": [
      11.55,
      50.25
    ]
  },
  "type": "Feature",
  "properties": {
    "hierarchy": [
      "tgn:7187959",
      "tgn:7003669",
      "tgn:1000003",
      "tgn:7000084",
      "tgn:7029392"
    ],
    "placetype": [
      "aat:300008777"
    ],
    "id": 7187959,
    "name:xx": "Elbersreuther Höhe"
  }
}
