{
  "geometry": {
    "type": "Point",
    "coordinates": [
      79.285834,
      27.19444
    ]
  },
  "type": "Feature",
  "properties": {
    "hierarchy": [
      "tgn:7560196",
      "tgn:1000004",
      "tgn:7000198",
      "tgn:7016722",
      "tgn:7029392"
    ],
    "placetype": [
      "aat:300008347"
    ],
    "name:en": "Khajūria",
    "id": 7560196
  }
}
