{
  "geometry": {
    "type": "Point",
    "coordinates": [
      49.1333,
      24.3667
    ]
  },
  "type": "Feature",
  "properties": {
    "hierarchy": [
      "tgn:1084777",
      "tgn:7000684",
      "tgn:1000004",
      "tgn:1111881",
      "tgn:1000137",
      "tgn:7029392"
    ],
    "placetype": [
      "aat:300008347"
    ],
    "id": 1084777,
    "name:xx": "Ḥaraḍ"
  }
}
