{
  "geometry": {
    "type": "Point",
    "coordinates": [
      -112.35,
      45.9333
    ]
  },
  "type": "Feature",
  "properties": {
    "hierarchy": [
      "tgn:2534469",
      "tgn:1000001",
      "tgn:7012149",
      "tgn:2001281",
      "tgn:7007524",
      "tgn:7029392"
    ],
    "placetype": [
      "aat:300000390"
    ],
    "id": 2534469,
    "name:xx": "NE SW Section 9 Mine"
  }
}
