{
  "geometry": {
    "type": "Point",
    "coordinates": [
      -77.15,
      39.85
    ]
  },
  "type": "Feature",
  "properties": {
    "hierarchy": [
      "tgn:2358980",
      "tgn:1002137",
      "tgn:1000001",
      "tgn:7012149",
      "tgn:7007710",
      "tgn:7029392"
    ],
    "placetype": [
      "aat:300008798"
    ],
    "id": 2358980,
    "name:xx": "Granite Hill"
  }
}
