{
  "geometry": {
    "type": "Point",
    "coordinates": [
      40.95,
      58.7667
    ]
  },
  "type": "Feature",
  "properties": {
    "hierarchy": [
      "tgn:1059401",
      "tgn:1000004",
      "tgn:7017317",
      "tgn:7018214",
      "tgn:7002435",
      "tgn:7029392"
    ],
    "placetype": [
      "aat:300008347"
    ],
    "id": 1059401,
    "name:xx": "Sidorovo"
  }
}
