{
  "type": "FeatureCollection",
  "features": [
    {
      "geometry": {
        "type": "Point",
        "coordinates": [
          -104.533333,
          25.116667
        ]
      },
      "type": "Feature",
      "properties": {
        "hierarchy": [
          "tgn:7368570",
          "tgn:7005583",
          "tgn:1000001",
          "tgn:7005560",
          "tgn:7029392"
        ],
        "placetype": [
          "aat:300008347"
        ],
        "id": 7368570,
        "name:xx": "Hidalgo de San Antonio"
      }
    },
    {
      "geometry": {
        "type": "Point",
        "coordinates": [
          -116.266667,
          31.333333
        ]
      },
      "type": "Feature",
      "properties": {
        "hierarchy": [
          "tgn:7368573",
          "tgn:1001835",
          "tgn:1000001",
          "tgn:7005560",
          "tgn:7029392"
        ],
        "placetype": [
          "aat:300006495"
        ],
        "id": 7368573,
        "name:xx": "Escuela Hidalgo"
      }
    },
    {
      "geometry": {
        "type": "Point",
        "coordinates": [
          -109.65,
          30.483333
        ]
      },
      "type": "Feature",
      "properties": {
        "hierarchy": [
          "tgn:7368574",
          "tgn:1000001",
          "tgn:1001960",
          "tgn:7005560",
          "tgn:7029392"
        ],
        "placetype": [
          "aat:300007783"
        ],
        "id": 7368574,
        "name:xx": "Hidalgo"
      }
    },
    {
      "geometry": {
        "type": "Point",
        "coordinates": [
          -100.45,
          25.966667
        ]
      },
      "type": "Feature",
      "properties": {
        "hierarchy": [
          "tgn:7368575",
          "tgn:1000001",
          "tgn:7005589",
          "tgn:7005560",
          "tgn:7029392"
        ],
        "placetype": [
          "aat:300007783"
        ],
        "id": 7368575,
        "name:xx": "Hidalgo"
      }
    },
    {
      "geometry": {
        "type": "Point",
        "coordinates": [
          -98.2,
          26.05
        ]
      },
      "type": "Feature",
      "properties": {
        "hierarchy": [
          "tgn:7368577",
          "tgn:1000001",
          "tgn:7005597",
          "tgn:7005560",
          "tgn:7029392"
        ],
        "placetype": [
          "aat:300008347"
        ],
        "id": 7368577,
        "name:xx": "Hidalgo"
      }
    },
    {
      "geometry": {
        "type": "Point",
        "coordinates": [
          -99.083333,
          25.95
        ]
      },
      "type": "Feature",
      "properties": {
        "hierarchy": [
          "tgn:7368578",
          "tgn:1000001",
          "tgn:7005589",
          "tgn:7005560",
          "tgn:7029392"
        ],
        "placetype": [
          "aat:300008347"
        ],
        "id": 7368578,
        "name:xx": "Hidalgo"
      }
    },
    {
      "geometry": {
        "type": "Point",
        "coordinates": [
          -103.283333,
          25.816667
        ]
      },
      "type": "Feature",
      "properties": {
        "hierarchy": [
          "tgn:7368579",
          "tgn:1001853",
          "tgn:1000001",
          "tgn:7005560",
          "tgn:7029392"
        ],
        "placetype": [
          "aat:300008347"
        ],
        "id": 7368579,
        "name:xx": "Hidalgo"
      }
    }
  ]
}
