{
  "geometry": {
    "type": "Point",
    "coordinates": [
      -80.4167,
      38.8833
    ]
  },
  "type": "Feature",
  "properties": {
    "hierarchy": [
      "tgn:2265313",
      "tgn:1000001",
      "tgn:7012149",
      "tgn:2002271",
      "tgn:7013961",
      "tgn:7029392"
    ],
    "placetype": [
      "aat:300008699"
    ],
    "id": 2265313,
    "name:xx": "Crane Camp Run"
  }
}
