{
  "type": "FeatureCollection",
  "features": [
    {
      "geometry": {
        "type": "Point",
        "coordinates": [
          126.9333,
          42.2
        ]
      },
      "type": "Feature",
      "properties": {
        "hierarchy": [
          "tgn:1071961",
          "tgn:1000004",
          "tgn:7002372",
          "tgn:1000111",
          "tgn:7029392"
        ],
        "placetype": [
          "aat:300008347"
        ],
        "id": 1071961,
        "name:xx": "Songjiangzhen"
      }
    },
    {
      "geometry": {
        "type": "Point",
        "coordinates": [
          104.7333,
          29.6333
        ]
      },
      "type": "Feature",
      "properties": {
        "hierarchy": [
          "tgn:1071962",
          "tgn:1000004",
          "tgn:7002087",
          "tgn:1000111",
          "tgn:7029392"
        ],
        "placetype": [
          "aat:300008347"
        ],
        "id": 1071962,
        "name:xx": "Songjiapu"
      }
    },
    {
      "geometry": {
        "type": "Point",
        "coordinates": [
          115.3,
          40.65
        ]
      },
      "type": "Feature",
      "properties": {
        "hierarchy": [
          "tgn:1071963",
          "tgn:1000004",
          "tgn:7002077",
          "tgn:1000111",
          "tgn:7029392"
        ],
        "placetype": [
          "aat:300008347"
        ],
        "id": 1071963,
        "name:xx": "Songjiaying"
      }
    },
    {
      "geometry": {
        "type": "Point",
        "coordinates": [
          106.8333,
          28.55
        ]
      },
      "type": "Feature",
      "properties": {
        "hierarchy": [
          "tgn:1071964",
          "tgn:1000004",
          "tgn:7002080",
          "tgn:1000111",
          "tgn:7029392"
        ],
        "placetype": [
          "aat:300008347"
        ],
        "id": 1071964,
        "name:xx": "Songkan"
      }
    },
    {
      "geometry": {
        "type": "Point",
        "coordinates": [
          116.4,
          24.4667
        ]
      },
      "type": "Feature",
      "properties": {
        "hierarchy": [
          "tgn:1071965",
          "tgn:1000004",
          "tgn:7005232",
          "tgn:1000111",
          "tgn:7029392"
        ],
        "placetype": [
          "aat:300008347"
        ],
        "id": 1071965,
        "name:xx": "Songkou"
      }
    },
    {
      "geometry": {
        "type": "Point",
        "coordinates": [
          115.9833,
          24
        ]
      },
      "type": "Feature",
      "properties": {
        "hierarchy": [
          "tgn:1071966",
          "tgn:1000004",
          "tgn:7005232",
          "tgn:1000111",
          "tgn:7029392"
        ],
        "placetype": [
          "aat:300008347"
        ],
        "id": 1071966,
        "name:xx": "Songlinba"
      }
    },
    {
      "geometry": {
        "type": "Point",
        "coordinates": [
          115.9,
          39.4167
        ]
      },
      "type": "Feature",
      "properties": {
        "hierarchy": [
          "tgn:1071967",
          "tgn:1000004",
          "tgn:7002077",
          "tgn:1000111",
          "tgn:7029392"
        ],
        "placetype": [
          "aat:300008347"
        ],
        "id": 1071967,
        "name:xx": "Songlindian"
      }
    },
    {
      "geometry": {
        "type": "Point",
        "coordinates": [
          121.0833,
          48
        ]
      },
      "type": "Feature",
      "properties": {
        "hierarchy": [
          "tgn:1071968",
          "tgn:1000004",
          "tgn:7001838",
          "tgn:1000111",
          "tgn:7029392"
        ],
        "placetype": [
          "aat:300008347"
        ],
        "id": 1071968,
        "name:xx": "Songling"
      }
    },
    {
      "geometry": {
        "type": "Point",
        "coordinates": [
          84.8167,
          29.25
        ]
      },
      "type": "Feature",
      "properties": {
        "hierarchy": [
          "tgn:1071969",
          "tgn:1000004",
          "tgn:7001319",
          "tgn:1000111",
          "tgn:7029392"
        ],
        "placetype": [
          "aat:300008347"
        ],
        "id": 1071969,
        "name:xx": "Songlukelujia"
      }
    }
  ]
}
