{
  "type": "FeatureCollection",
  "features": [
    {
      "geometry": {
        "type": "Point",
        "coordinates": [
          -72.566667,
          -44.316667
        ]
      },
      "type": "Feature",
      "properties": {
        "hierarchy": [
          "tgn:7283170",
          "tgn:1001699",
          "tgn:1000049",
          "tgn:1000002",
          "tgn:7029392"
        ],
        "placetype": [
          "aat:300008699"
        ],
        "id": 7283170,
        "name:xx": "Pascua, Río"
      }
    },
    {
      "geometry": {
        "type": "Point",
        "coordinates": [
          -74.383333,
          -49.1
        ]
      },
      "type": "Feature",
      "properties": {
        "hierarchy": [
          "tgn:7283171",
          "tgn:1001702",
          "tgn:1000049",
          "tgn:1000002",
          "tgn:7029392"
        ],
        "placetype": [
          "aat:300386846"
        ],
        "id": 7283171,
        "name:xx": "Pascua, Punta"
      }
    },
    {
      "geometry": {
        "type": "Point",
        "coordinates": [
          -74.8,
          -51.2
        ]
      },
      "type": "Feature",
      "properties": {
        "hierarchy": [
          "tgn:7283172",
          "tgn:1001702",
          "tgn:1000049",
          "tgn:1000002",
          "tgn:7029392"
        ],
        "placetype": [
          "aat:300387026"
        ],
        "id": 7283172,
        "name:xx": "Pascua, Paso"
      }
    },
    {
      "geometry": {
        "type": "Point",
        "coordinates": [
          -69.233333,
          -24.083333
        ]
      },
      "type": "Feature",
      "properties": {
        "hierarchy": [
          "tgn:7283173",
          "tgn:7016598",
          "tgn:1000049",
          "tgn:1000002",
          "tgn:7029392"
        ],
        "placetype": [
          "aat:300008795"
        ],
        "id": 7283173,
        "name:xx": "Pascua, Cerro"
      }
    },
    {
      "geometry": {
        "type": "Point",
        "coordinates": [
          -74.4,
          -49.116667
        ]
      },
      "type": "Feature",
      "properties": {
        "hierarchy": [
          "tgn:7283174",
          "tgn:1001702",
          "tgn:1000049",
          "tgn:1000002",
          "tgn:7029392"
        ],
        "placetype": [
          "aat:300008808"
        ],
        "id": 7283174,
        "name:xx": "Pascua, Bajo"
      }
    },
    {
      "geometry": {
        "type": "Point",
        "coordinates": [
          -73.883333,
          -51.733333
        ]
      },
      "type": "Feature",
      "properties": {
        "hierarchy": [
          "tgn:7283175",
          "tgn:1001702",
          "tgn:1000049",
          "tgn:1000002",
          "tgn:7029392"
        ],
        "placetype": [
          "aat:300132316"
        ],
        "id": 7283175,
        "name:xx": "Pascoe, Bahía"
      }
    },
    {
      "geometry": {
        "type": "Point",
        "coordinates": [
          -72.2,
          -53.633333
        ]
      },
      "type": "Feature",
      "properties": {
        "hierarchy": [
          "tgn:7283176",
          "tgn:1001702",
          "tgn:1000049",
          "tgn:1000002",
          "tgn:7029392"
        ],
        "placetype": [
          "aat:300386846"
        ],
        "id": 7283176,
        "name:xx": "Pasaje, Punta"
      }
    },
    {
      "geometry": {
        "type": "Point",
        "coordinates": [
          -73.033333,
          -52.083333
        ]
      },
      "type": "Feature",
      "properties": {
        "hierarchy": [
          "tgn:7283177",
          "tgn:1001702",
          "tgn:1000049",
          "tgn:1000002",
          "tgn:7029392"
        ],
        "placetype": [
          "aat:300386846"
        ],
        "id": 7283177,
        "name:xx": "Pasaje, Punta"
      }
    },
    {
      "geometry": {
        "type": "Point",
        "coordinates": [
          -73.797222,
          -41.869722
        ]
      },
      "type": "Feature",
      "properties": {
        "hierarchy": [
          "tgn:7283178",
          "tgn:1001699",
          "tgn:1000049",
          "tgn:1000002",
          "tgn:7029392"
        ],
        "placetype": [
          "aat:300386846"
        ],
        "id": 7283178,
        "name:xx": "Pasaje, Punta"
      }
    },
    {
      "geometry": {
        "type": "Point",
        "coordinates": [
          -73.483333,
          -52.966667
        ]
      },
      "type": "Feature",
      "properties": {
        "hierarchy": [
          "tgn:7283179",
          "tgn:1001702",
          "tgn:1000049",
          "tgn:1000002",
          "tgn:7029392"
        ],
        "placetype": [
          "aat:300008791"
        ],
        "id": 7283179,
        "name:xx": "Pasaje, Islas"
      }
    }
  ]
}
