{
  "type": "FeatureCollection",
  "features": [
    {
      "geometry": {
        "type": "Point",
        "coordinates": [
          -91.7167,
          41.05
        ]
      },
      "type": "Feature",
      "properties": {
        "hierarchy": [
          "tgn:2687610",
          "tgn:1000001",
          "tgn:7012149",
          "tgn:2000611",
          "tgn:7007253",
          "tgn:7029392"
        ],
        "placetype": [
          "aat:300008680"
        ],
        "id": 2687610,
        "name:xx": "Spring Pond"
      }
    },
    {
      "geometry": {
        "type": "Point",
        "coordinates": [
          -68.5667,
          46.1667
        ]
      },
      "type": "Feature",
      "properties": {
        "hierarchy": [
          "tgn:2687611",
          "tgn:1000001",
          "tgn:7012149",
          "tgn:2000927",
          "tgn:7007515",
          "tgn:7029392"
        ],
        "placetype": [
          "aat:300008680"
        ],
        "id": 2687611,
        "name:xx": "Spring Pond"
      }
    },
    {
      "geometry": {
        "type": "Point",
        "coordinates": [
          -69.0333,
          46.3
        ]
      },
      "type": "Feature",
      "properties": {
        "hierarchy": [
          "tgn:2687612",
          "tgn:1000001",
          "tgn:7012149",
          "tgn:2000928",
          "tgn:7007515",
          "tgn:7029392"
        ],
        "placetype": [
          "aat:300008680"
        ],
        "id": 2687612,
        "name:xx": "Spring Pond"
      }
    },
    {
      "geometry": {
        "type": "Point",
        "coordinates": [
          -71.4,
          42.0667
        ]
      },
      "type": "Feature",
      "properties": {
        "hierarchy": [
          "tgn:2687613",
          "tgn:1000001",
          "tgn:1002724",
          "tgn:7012149",
          "tgn:7007517",
          "tgn:7029392"
        ],
        "placetype": [
          "aat:300006191"
        ],
        "id": 2687613,
        "name:xx": "Spring Pond"
      }
    },
    {
      "geometry": {
        "type": "Point",
        "coordinates": [
          -71.05,
          42.4667
        ]
      },
      "type": "Feature",
      "properties": {
        "hierarchy": [
          "tgn:2687614",
          "tgn:1000001",
          "tgn:1002359",
          "tgn:7012149",
          "tgn:7007517",
          "tgn:7029392"
        ],
        "placetype": [
          "aat:300008680"
        ],
        "id": 2687614,
        "name:xx": "Spring Pond"
      }
    },
    {
      "geometry": {
        "type": "Point",
        "coordinates": [
          -70.7167,
          41.9
        ]
      },
      "type": "Feature",
      "properties": {
        "hierarchy": [
          "tgn:2687615",
          "tgn:1000001",
          "tgn:7014423",
          "tgn:7012149",
          "tgn:7007517",
          "tgn:7029392"
        ],
        "placetype": [
          "aat:300008680"
        ],
        "id": 2687615,
        "name:xx": "Spring Pond"
      }
    },
    {
      "geometry": {
        "type": "Point",
        "coordinates": [
          -85.5167,
          43.3167
        ]
      },
      "type": "Feature",
      "properties": {
        "hierarchy": [
          "tgn:2687616",
          "tgn:1000001",
          "tgn:7012149",
          "tgn:2000981",
          "tgn:7007520",
          "tgn:7029392"
        ],
        "placetype": [
          "aat:300008680"
        ],
        "id": 2687616,
        "name:xx": "Spring Pond"
      }
    },
    {
      "geometry": {
        "type": "Point",
        "coordinates": [
          -83.7167,
          46
        ]
      },
      "type": "Feature",
      "properties": {
        "hierarchy": [
          "tgn:2687617",
          "tgn:1000001",
          "tgn:2000952",
          "tgn:7012149",
          "tgn:7007520",
          "tgn:7029392"
        ],
        "placetype": [
          "aat:300008680"
        ],
        "id": 2687617,
        "name:xx": "Spring Pond"
      }
    },
    {
      "geometry": {
        "type": "Point",
        "coordinates": [
          -86.05,
          46.4667
        ]
      },
      "type": "Feature",
      "properties": {
        "hierarchy": [
          "tgn:2687618",
          "tgn:1000001",
          "tgn:7012149",
          "tgn:2000996",
          "tgn:7007520",
          "tgn:7029392"
        ],
        "placetype": [
          "aat:300008680"
        ],
        "id": 2687618,
        "name:xx": "Spring Pond"
      }
    },
    {
      "geometry": {
        "type": "Point",
        "coordinates": [
          -74.2833,
          40.9833
        ]
      },
      "type": "Feature",
      "properties": {
        "hierarchy": [
          "tgn:2687619",
          "tgn:1000001",
          "tgn:1002775",
          "tgn:7012149",
          "tgn:7007565",
          "tgn:7029392"
        ],
        "placetype": [
          "aat:300008680"
        ],
        "id": 2687619,
        "name:xx": "Spring Pond"
      }
    }
  ]
}
