{
  "geometry": {
    "type": "Point",
    "coordinates": [
      -78.1833,
      41.8833
    ]
  },
  "type": "Feature",
  "properties": {
    "hierarchy": [
      "tgn:2161447",
      "tgn:1000001",
      "tgn:7012149",
      "tgn:7007710",
      "tgn:7029392"
    ],
    "placetype": [
      "aat:300008699"
    ],
    "id": 2161447,
    "name:xx": "Bell Run"
  }
}
