{
  "geometry": {
    "type": "Point",
    "coordinates": [
      -88.9167,
      30.4167
    ]
  },
  "type": "Feature",
  "properties": {
    "hierarchy": [
      "tgn:2488104",
      "tgn:1000001",
      "tgn:7012149",
      "tgn:2001109",
      "tgn:7007522",
      "tgn:7029392"
    ],
    "placetype": [
      "aat:300132316"
    ],
    "id": 2488104,
    "name:xx": "Magnolia Bend"
  }
}
