{
  "geometry": {
    "type": "Point",
    "coordinates": [
      31.315003,
      30.078252
    ]
  },
  "type": "Feature",
  "properties": {
    "hierarchy": [
      "tgn:7529633",
      "tgn:7001242",
      "tgn:7016833",
      "tgn:1001091",
      "tgn:7029392"
    ],
    "placetype": [
      "aat:300004792"
    ],
    "id": 7529633,
    "name:xx": "Wizārat at Takhţīţ"
  }
}
