{
  "type": "FeatureCollection",
  "features": [
    {
      "geometry": {
        "type": "Point",
        "coordinates": [
          -5.316667,
          42.533333
        ]
      },
      "type": "Feature",
      "properties": {
        "hierarchy": [
          "tgn:7296650",
          "tgn:7002826",
          "tgn:7001158",
          "tgn:1000003",
          "tgn:1000095",
          "tgn:7029392"
        ],
        "placetype": [
          "aat:300008347"
        ],
        "id": 7296650,
        "name:xx": "Villalquite"
      }
    },
    {
      "geometry": {
        "type": "Point",
        "coordinates": [
          -1.633333,
          39.466667
        ]
      },
      "type": "Feature",
      "properties": {
        "hierarchy": [
          "tgn:7296651",
          "tgn:7002818",
          "tgn:1001647",
          "tgn:1000003",
          "tgn:1000095",
          "tgn:7029392"
        ],
        "placetype": [
          "aat:300008347"
        ],
        "id": 7296651,
        "name:xx": "Villalpardo"
      }
    },
    {
      "geometry": {
        "type": "Point",
        "coordinates": [
          -7.5,
          42.583333
        ]
      },
      "type": "Feature",
      "properties": {
        "hierarchy": [
          "tgn:7296652",
          "tgn:7002829",
          "tgn:1000003",
          "tgn:7002786",
          "tgn:1000095",
          "tgn:7029392"
        ],
        "placetype": [
          "aat:300008347"
        ],
        "id": 7296652,
        "name:xx": "Villalpape"
      }
    },
    {
      "geometry": {
        "type": "Point",
        "coordinates": [
          -5.3,
          41.6
        ]
      },
      "type": "Feature",
      "properties": {
        "hierarchy": [
          "tgn:7296654",
          "tgn:7001158",
          "tgn:7002850",
          "tgn:1000003",
          "tgn:1000095",
          "tgn:7029392"
        ],
        "placetype": [
          "aat:300008347"
        ],
        "id": 7296654,
        "name:xx": "Villalonso"
      }
    },
    {
      "geometry": {
        "type": "Point",
        "coordinates": [
          -3.766667,
          42.35
        ]
      },
      "type": "Feature",
      "properties": {
        "hierarchy": [
          "tgn:7296655",
          "tgn:7002810",
          "tgn:7001158",
          "tgn:1000003",
          "tgn:1000095",
          "tgn:7029392"
        ],
        "placetype": [
          "aat:300008347"
        ],
        "id": 7296655,
        "name:xx": "Villalonquéjar"
      }
    },
    {
      "geometry": {
        "type": "Point",
        "coordinates": [
          -6.716667,
          43.55
        ]
      },
      "type": "Feature",
      "properties": {
        "hierarchy": [
          "tgn:7296656",
          "tgn:7008911",
          "tgn:1000003",
          "tgn:7002763",
          "tgn:1000095",
          "tgn:7029392"
        ],
        "placetype": [
          "aat:300008347"
        ],
        "id": 7296656,
        "name:xx": "Villalonga"
      }
    },
    {
      "geometry": {
        "type": "Point",
        "coordinates": [
          -8.783333,
          42.4
        ]
      },
      "type": "Feature",
      "properties": {
        "hierarchy": [
          "tgn:7296657",
          "tgn:7002834",
          "tgn:1000003",
          "tgn:7002786",
          "tgn:1000095",
          "tgn:7029392"
        ],
        "placetype": [
          "aat:300008347"
        ],
        "id": 7296657,
        "name:xx": "Villalonga"
      }
    },
    {
      "geometry": {
        "type": "Point",
        "coordinates": [
          -0.2,
          38.883333
        ]
      },
      "type": "Feature",
      "properties": {
        "hierarchy": [
          "tgn:7296658",
          "tgn:7001165",
          "tgn:1000003",
          "tgn:7002793",
          "tgn:1000095",
          "tgn:7029392"
        ],
        "placetype": [
          "aat:300008347"
        ],
        "id": 7296658,
        "name:xx": "Villalonga"
      }
    }
  ]
}
