{
  "geometry": {
    "type": "Point",
    "coordinates": [
      -103.9167,
      35.2333
    ]
  },
  "type": "Feature",
  "properties": {
    "hierarchy": [
      "tgn:2397232",
      "tgn:1000001",
      "tgn:7012149",
      "tgn:2001453",
      "tgn:7007566",
      "tgn:7029392"
    ],
    "placetype": [
      "aat:300006191"
    ],
    "id": 2397232,
    "name:xx": "Hondo Tank"
  }
}
