{
  "geometry": {
    "type": "Point",
    "coordinates": [
      4.8333,
      47.0333
    ]
  },
  "type": "Feature",
  "properties": {
    "hierarchy": [
      "tgn:7008221",
      "tgn:1000003",
      "tgn:7002875",
      "tgn:1000070",
      "tgn:7029392"
    ],
    "placetype": [
      "aat:300008347"
    ],
    "id": 7008221,
    "name:xx": "Beaune"
  }
}
