{
  "geometry": {
    "type": "Point",
    "coordinates": [
      -84.1333,
      44.9333
    ]
  },
  "type": "Feature",
  "properties": {
    "hierarchy": [
      "tgn:2231160",
      "tgn:1000001",
      "tgn:7012149",
      "tgn:2000982",
      "tgn:7007520",
      "tgn:7029392"
    ],
    "placetype": [
      "aat:300008706"
    ],
    "id": 2231160,
    "name:xx": "Chadwick Creek"
  }
}
