{
  "geometry": {
    "type": "Point",
    "coordinates": [
      -89.8833,
      45.7833
    ]
  },
  "type": "Feature",
  "properties": {
    "hierarchy": [
      "tgn:2671637",
      "tgn:1000001",
      "tgn:7012149",
      "tgn:2002342",
      "tgn:7007922",
      "tgn:7029392"
    ],
    "placetype": [
      "aat:300008680"
    ],
    "id": 2671637,
    "name:xx": "Smith Lake"
  }
}
