{
  "geometry": {
    "type": "Point",
    "coordinates": [
      -74.2167,
      43.5333
    ]
  },
  "type": "Feature",
  "properties": {
    "hierarchy": [
      "tgn:2470995",
      "tgn:1000001",
      "tgn:7012149",
      "tgn:1002440",
      "tgn:7007568",
      "tgn:7029392"
    ],
    "placetype": [
      "aat:300008706"
    ],
    "id": 2470995,
    "name:xx": "Lost Creek"
  }
}
