{
  "geometry": {
    "type": "Point",
    "coordinates": [
      -114.05,
      37.95
    ]
  },
  "type": "Feature",
  "properties": {
    "hierarchy": [
      "tgn:2752924",
      "tgn:1000001",
      "tgn:2001416",
      "tgn:7012149",
      "tgn:7007526",
      "tgn:7029392"
    ],
    "placetype": [
      "aat:300008697"
    ],
    "id": 2752924,
    "name:xx": "Water Canyon Spring"
  }
}
