{
  "geometry": {
    "type": "Point",
    "coordinates": [
      78.933333,
      13.65
    ]
  },
  "type": "Feature",
  "properties": {
    "hierarchy": [
      "tgn:7556697",
      "tgn:1001828",
      "tgn:1000004",
      "tgn:7000198",
      "tgn:7029392"
    ],
    "placetype": [
      "aat:300008347"
    ],
    "name:en": "Pīleru",
    "id": 7556697
  }
}
