{
  "geometry": {
    "type": "Point",
    "coordinates": [
      -115.0833,
      48.55
    ]
  },
  "type": "Feature",
  "properties": {
    "hierarchy": [
      "tgn:2546191",
      "tgn:1000001",
      "tgn:7012149",
      "tgn:2001286",
      "tgn:7007524",
      "tgn:7029392"
    ],
    "placetype": [
      "aat:300008706"
    ],
    "id": 2546191,
    "name:xx": "North Fork Fivemile Creek"
  }
}
