{
  "geometry": {
    "type": "Point",
    "coordinates": [
      -75.2833,
      42.8167
    ]
  },
  "type": "Feature",
  "properties": {
    "hierarchy": [
      "tgn:2211775",
      "tgn:1000001",
      "tgn:7012149",
      "tgn:7007568",
      "tgn:7029392"
    ],
    "placetype": [
      "aat:300008706"
    ],
    "id": 2211775,
    "name:xx": "Button Creek"
  }
}
