{
  "geometry": {
    "type": "Point",
    "coordinates": [
      -85.1333,
      34.6833
    ]
  },
  "type": "Feature",
  "properties": {
    "hierarchy": [
      "tgn:2243570",
      "tgn:1000001",
      "tgn:7012149",
      "tgn:2000437",
      "tgn:7007248",
      "tgn:7029392"
    ],
    "placetype": [
      "aat:300008697"
    ],
    "id": 2243570,
    "name:xx": "Cleghorn Spring"
  }
}
