{
  "geometry": {
    "type": "Point",
    "coordinates": [
      -84.8333,
      34.7167
    ]
  },
  "type": "Feature",
  "properties": {
    "hierarchy": [
      "tgn:2626309",
      "tgn:1000001",
      "tgn:7012149",
      "tgn:2000396",
      "tgn:7007248",
      "tgn:7029392"
    ],
    "placetype": [
      "aat:300008699"
    ],
    "id": 2626309,
    "name:xx": "Rocky Ford Branch"
  }
}
