{
  "geometry": {
    "type": "Point",
    "coordinates": [
      22.8333,
      -26.5833
    ]
  },
  "type": "Feature",
  "properties": {
    "hierarchy": [
      "tgn:1127375",
      "tgn:7001242",
      "tgn:7029392"
    ],
    "placetype": [
      "aat:300008707"
    ],
    "id": 1127375,
    "name:xx": "Moshaweng"
  }
}
