{
  "geometry": {
    "type": "Point",
    "coordinates": [
      -82.5167,
      36.0833
    ]
  },
  "type": "Feature",
  "properties": {
    "hierarchy": [
      "tgn:2616892",
      "tgn:1000001",
      "tgn:7012149",
      "tgn:7007825",
      "tgn:7029392"
    ],
    "placetype": [
      "aat:300266640"
    ],
    "id": 2616892,
    "name:xx": "Rich Mountain"
  }
}
