{
  "geometry": {
    "type": "Point",
    "coordinates": [
      -61.8167,
      7.3167
    ]
  },
  "type": "Feature",
  "properties": {
    "hierarchy": [
      "tgn:1025120",
      "tgn:1001843",
      "tgn:1000002",
      "tgn:1000059",
      "tgn:7029392"
    ],
    "placetype": [
      "aat:300008347"
    ],
    "id": 1025120,
    "name:xx": "El Perú"
  }
}
