{
  "geometry": {
    "type": "Point",
    "coordinates": [
      -122.9333,
      47.2333
    ]
  },
  "type": "Feature",
  "properties": {
    "hierarchy": [
      "tgn:2358039",
      "tgn:1000001",
      "tgn:7012149",
      "tgn:1002645",
      "tgn:7007920",
      "tgn:7029392"
    ],
    "placetype": [
      "aat:300008347"
    ],
    "id": 2358039,
    "name:xx": "Graham Point"
  }
}
