{
  "geometry": {
    "type": "Point",
    "coordinates": [
      29.033333,
      30.55
    ]
  },
  "type": "Feature",
  "properties": {
    "hierarchy": [
      "tgn:7537242",
      "tgn:7001242",
      "tgn:7016833",
      "tgn:1001418",
      "tgn:7029392"
    ],
    "placetype": [
      "aat:300055621"
    ],
    "name:en": "Mirbâṭ 'Aza",
    "id": 7537242
  }
}
