{
  "type": "FeatureCollection",
  "features": [
    {
      "geometry": {
        "type": "Point",
        "coordinates": [
          -1.783333,
          51.65
        ]
      },
      "type": "Feature",
      "properties": {
        "hierarchy": [
          "tgn:7455600",
          "tgn:7002445",
          "tgn:1000003",
          "tgn:7026532",
          "tgn:7008591",
          "tgn:7029392"
        ],
        "placetype": [
          "aat:300008347"
        ],
        "name:en": "Castle Eaton",
        "id": 7455600
      }
    },
    {
      "geometry": {
        "type": "Point",
        "coordinates": [
          -5.75,
          54.733333
        ]
      },
      "type": "Feature",
      "properties": {
        "hierarchy": [
          "tgn:7455603",
          "tgn:7002448",
          "tgn:7019165",
          "tgn:1000003",
          "tgn:7008591",
          "tgn:7029392"
        ],
        "placetype": [
          "aat:300387502"
        ],
        "name:en": "Castle Dobbs",
        "id": 7455603
      }
    },
    {
      "geometry": {
        "type": "Point",
        "coordinates": [
          -6.616667,
          54.366667
        ]
      },
      "type": "Feature",
      "properties": {
        "hierarchy": [
          "tgn:7455604",
          "tgn:7008696",
          "tgn:7002448",
          "tgn:1000003",
          "tgn:7008591",
          "tgn:7029392"
        ],
        "placetype": [
          "aat:300387502"
        ],
        "name:en": "Castle Dillon House",
        "id": 7455604
      }
    },
    {
      "geometry": {
        "type": "Point",
        "coordinates": [
          -7.6,
          54.333333
        ]
      },
      "type": "Feature",
      "properties": {
        "hierarchy": [
          "tgn:7455607",
          "tgn:7002448",
          "tgn:7008700",
          "tgn:1000003",
          "tgn:7008591",
          "tgn:7029392"
        ],
        "placetype": [
          "aat:300387502"
        ],
        "name:en": "Castle Coole",
        "id": 7455607
      }
    },
    {
      "geometry": {
        "type": "Point",
        "coordinates": [
          -2.225556,
          51.494444
        ]
      },
      "type": "Feature",
      "properties": {
        "hierarchy": [
          "tgn:7455608",
          "tgn:7002445",
          "tgn:1000003",
          "tgn:7008180",
          "tgn:7008591",
          "tgn:7029392"
        ],
        "placetype": [
          "aat:300008347"
        ],
        "name:en": "Castle Combe",
        "id": 7455608
      }
    },
    {
      "geometry": {
        "type": "Point",
        "coordinates": [
          -5.7,
          54.75
        ]
      },
      "type": "Feature",
      "properties": {
        "hierarchy": [
          "tgn:7455609",
          "tgn:7002448",
          "tgn:7019165",
          "tgn:1000003",
          "tgn:7008591",
          "tgn:7029392"
        ],
        "placetype": [
          "aat:300387007"
        ],
        "name:en": "Castle Chichester",
        "id": 7455609
      }
    }
  ]
}
