{
  "geometry": {
    "type": "Point",
    "coordinates": [
      -78.25,
      38.5667
    ]
  },
  "type": "Feature",
  "properties": {
    "hierarchy": [
      "tgn:2436829",
      "tgn:1000001",
      "tgn:7012149",
      "tgn:2002184",
      "tgn:7007919",
      "tgn:7029392"
    ],
    "placetype": [
      "aat:300008706"
    ],
    "id": 2436829,
    "name:xx": "Kilbys Creek"
  }
}
