{
  "geometry": {
    "type": "Point",
    "coordinates": [
      -145.4833,
      65.1333
    ]
  },
  "type": "Feature",
  "properties": {
    "hierarchy": [
      "tgn:2245364",
      "tgn:7006450",
      "tgn:1000001",
      "tgn:7012149",
      "tgn:2000089",
      "tgn:7029392"
    ],
    "placetype": [
      "aat:300008699"
    ],
    "id": 2245364,
    "name:xx": "Clums Fork"
  }
}
