{
  "geometry": {
    "type": "Point",
    "coordinates": [
      -89.25,
      43.9833
    ]
  },
  "type": "Feature",
  "properties": {
    "hierarchy": [
      "tgn:2475700",
      "tgn:1000001",
      "tgn:7012149",
      "tgn:2002362",
      "tgn:7007922",
      "tgn:7029392"
    ],
    "placetype": [
      "aat:300008680"
    ],
    "id": 2475700,
    "name:xx": "Lucky Lake"
  }
}
