{
  "geometry": {
    "type": "Point",
    "coordinates": [
      -120.25,
      39.3167
    ]
  },
  "type": "Feature",
  "properties": {
    "hierarchy": [
      "tgn:2237411",
      "tgn:1000001",
      "tgn:7012149",
      "tgn:7007157",
      "tgn:1002710",
      "tgn:7029392"
    ],
    "placetype": [
      "aat:300132316"
    ],
    "id": 2237411,
    "name:xx": "China Cove"
  }
}
