{
  "geometry": {
    "type": "Point",
    "coordinates": [
      -120.0667,
      48.7333
    ]
  },
  "type": "Feature",
  "properties": {
    "hierarchy": [
      "tgn:2428757",
      "tgn:1000001",
      "tgn:7012149",
      "tgn:1002742",
      "tgn:7007920",
      "tgn:7029392"
    ],
    "placetype": [
      "aat:300008706"
    ],
    "id": 2428757,
    "name:xx": "July Creek"
  }
}
