{
  "geometry": {
    "type": "Point",
    "coordinates": [
      -91.1167,
      45.9333
    ]
  },
  "type": "Feature",
  "properties": {
    "hierarchy": [
      "tgn:2658720",
      "tgn:1000001",
      "tgn:7012149",
      "tgn:2002353",
      "tgn:7007922",
      "tgn:7029392"
    ],
    "placetype": [
      "aat:300132316"
    ],
    "id": 2658720,
    "name:xx": "Sherman Bay"
  }
}
