{
  "geometry": {
    "type": "Point",
    "coordinates": [
      21.6167,
      2.1333
    ]
  },
  "type": "Feature",
  "properties": {
    "hierarchy": [
      "tgn:7000593",
      "tgn:7001242",
      "tgn:7016654",
      "tgn:1000159",
      "tgn:7029392"
    ],
    "placetype": [
      "aat:300008347"
    ],
    "id": 7000593,
    "name:xx": "Lisala"
  }
}
