{
  "geometry": {
    "type": "Point",
    "coordinates": [
      -113.7667,
      38.0833
    ]
  },
  "type": "Feature",
  "properties": {
    "hierarchy": [
      "tgn:2634542",
      "tgn:1000001",
      "tgn:7012149",
      "tgn:2002111",
      "tgn:7007827",
      "tgn:7029392"
    ],
    "placetype": [
      "aat:300008761"
    ],
    "id": 2634542,
    "name:xx": "Rustlers Draw"
  }
}
