{
  "geometry": {
    "type": "Point",
    "coordinates": [
      -79.5167,
      37.5333
    ]
  },
  "type": "Feature",
  "properties": {
    "hierarchy": [
      "tgn:2314258",
      "tgn:1000001",
      "tgn:7012149",
      "tgn:7007919",
      "tgn:7029392"
    ],
    "placetype": [
      "aat:300008706"
    ],
    "id": 2314258,
    "name:xx": "Elk Creek"
  }
}
