{
  "geometry": {
    "type": "Point",
    "coordinates": [
      -107.9333,
      41.0167
    ]
  },
  "type": "Feature",
  "properties": {
    "hierarchy": [
      "tgn:2298373",
      "tgn:1000001",
      "tgn:7012149",
      "tgn:2002383",
      "tgn:7007923",
      "tgn:7029392"
    ],
    "placetype": [
      "aat:300006191"
    ],
    "id": 2298373,
    "name:xx": "Dry Reservoir"
  }
}
