{
  "geometry": {
    "type": "Point",
    "coordinates": [
      -86.6333,
      32.8667
    ]
  },
  "type": "Feature",
  "properties": {
    "hierarchy": [
      "tgn:2177615",
      "tgn:7002659",
      "tgn:1000001",
      "tgn:2000010",
      "tgn:7012149",
      "tgn:7029392"
    ],
    "placetype": [
      "aat:300008706"
    ],
    "id": 2177615,
    "name:xx": "Black Snake Creek"
  }
}
