{
  "geometry": {
    "type": "Point",
    "coordinates": [
      -105.6333,
      36.0333
    ]
  },
  "type": "Feature",
  "properties": {
    "hierarchy": [
      "tgn:2238015",
      "tgn:1000001",
      "tgn:7012149",
      "tgn:7007566",
      "tgn:7029392"
    ],
    "placetype": [
      "aat:300008699"
    ],
    "id": 2238015,
    "name:xx": "Chiquito, Rio"
  }
}
