{
  "geometry": {
    "type": "Point",
    "coordinates": [
      30.960185,
      30.556139
    ]
  },
  "type": "Feature",
  "properties": {
    "hierarchy": [
      "tgn:7540403",
      "tgn:7001242",
      "tgn:7016833",
      "tgn:1001087",
      "tgn:7029392"
    ],
    "placetype": [
      "aat:300008347"
    ],
    "name:en": "Minshāt ash Sharīkayn",
    "id": 7540403
  }
}
