{
  "geometry": {
    "type": "Point",
    "coordinates": [
      -89.2833,
      38.15
    ]
  },
  "type": "Feature",
  "properties": {
    "hierarchy": [
      "tgn:2623222",
      "tgn:1000001",
      "tgn:7012149",
      "tgn:2000522",
      "tgn:7007251",
      "tgn:7029392"
    ],
    "placetype": [
      "aat:300008699"
    ],
    "id": 2623222,
    "name:xx": "Rock Branch"
  }
}
