{
  "geometry": {
    "type": "Point",
    "coordinates": [
      -92.6167,
      35.9667
    ]
  },
  "type": "Feature",
  "properties": {
    "hierarchy": [
      "tgn:2150565",
      "tgn:1000001",
      "tgn:7016172",
      "tgn:7012149",
      "tgn:2000169",
      "tgn:7029392"
    ],
    "placetype": [
      "aat:300386845"
    ],
    "id": 2150565,
    "name:xx": "Basin, The"
  }
}
