{
  "geometry": {
    "type": "Point",
    "coordinates": [
      79.28808,
      26.244588
    ]
  },
  "type": "Feature",
  "properties": {
    "hierarchy": [
      "tgn:7565498",
      "tgn:1000004",
      "tgn:7000198",
      "tgn:7016722",
      "tgn:7029392"
    ],
    "placetype": [
      "aat:300008347"
    ],
    "name:en": "Sarāwan",
    "id": 7565498
  }
}
