{
  "geometry": {
    "type": "Point",
    "coordinates": [
      -112.9167,
      34.45
    ]
  },
  "type": "Feature",
  "properties": {
    "hierarchy": [
      "tgn:2130868",
      "tgn:1000001",
      "tgn:7006451",
      "tgn:7012149",
      "tgn:2000103",
      "tgn:7029392"
    ],
    "placetype": [
      "aat:300008699"
    ],
    "id": 2130868,
    "name:xx": "Ally Wash"
  }
}
