{
  "type": "FeatureCollection",
  "features": [
    {
      "geometry": {
        "type": "Point",
        "coordinates": [
          -106.1833,
          39.4167
        ]
      },
      "type": "Feature",
      "properties": {
        "hierarchy": [
          "tgn:2714780",
          "tgn:1000001",
          "tgn:7012149",
          "tgn:7007158",
          "tgn:2000250",
          "tgn:7029392"
        ],
        "placetype": [
          "aat:300008706"
        ],
        "id": 2714780,
        "name:xx": "Tenmile Creek"
      }
    },
    {
      "geometry": {
        "type": "Point",
        "coordinates": [
          -105.95,
          39.9833
        ]
      },
      "type": "Feature",
      "properties": {
        "hierarchy": [
          "tgn:2714781",
          "tgn:1000001",
          "tgn:7012149",
          "tgn:2000216",
          "tgn:7007158",
          "tgn:7029392"
        ],
        "placetype": [
          "aat:300008706"
        ],
        "id": 2714781,
        "name:xx": "Tenmile Creek"
      }
    },
    {
      "geometry": {
        "type": "Point",
        "coordinates": [
          -107.5667,
          37.65
        ]
      },
      "type": "Feature",
      "properties": {
        "hierarchy": [
          "tgn:2714782",
          "tgn:1000001",
          "tgn:7012149",
          "tgn:7007158",
          "tgn:2000247",
          "tgn:7029392"
        ],
        "placetype": [
          "aat:300008706"
        ],
        "id": 2714782,
        "name:xx": "Tenmile Creek"
      }
    },
    {
      "geometry": {
        "type": "Point",
        "coordinates": [
          -87.1833,
          30.7
        ]
      },
      "type": "Feature",
      "properties": {
        "hierarchy": [
          "tgn:2714783",
          "tgn:1000001",
          "tgn:7012149",
          "tgn:2000285",
          "tgn:7007240",
          "tgn:7029392"
        ],
        "placetype": [
          "aat:300008706"
        ],
        "id": 2714783,
        "name:xx": "Tenmile Creek"
      }
    },
    {
      "geometry": {
        "type": "Point",
        "coordinates": [
          -80.4667,
          27.3833
        ]
      },
      "type": "Feature",
      "properties": {
        "hierarchy": [
          "tgn:2714784",
          "tgn:1000001",
          "tgn:7012149",
          "tgn:7016124",
          "tgn:7007240",
          "tgn:7029392"
        ],
        "placetype": [
          "aat:300008706"
        ],
        "id": 2714784,
        "name:xx": "Tenmile Creek"
      }
    },
    {
      "geometry": {
        "type": "Point",
        "coordinates": [
          -80.9167,
          27.8667
        ]
      },
      "type": "Feature",
      "properties": {
        "hierarchy": [
          "tgn:2714785",
          "tgn:1000001",
          "tgn:7012149",
          "tgn:7007240",
          "tgn:7029392"
        ],
        "placetype": [
          "aat:300008706"
        ],
        "id": 2714785,
        "name:xx": "Tenmile Creek"
      }
    },
    {
      "geometry": {
        "type": "Point",
        "coordinates": [
          -85.4833,
          30.5667
        ]
      },
      "type": "Feature",
      "properties": {
        "hierarchy": [
          "tgn:2714786",
          "tgn:1000001",
          "tgn:7012149",
          "tgn:2000291",
          "tgn:7007240",
          "tgn:7029392"
        ],
        "placetype": [
          "aat:300008706"
        ],
        "id": 2714786,
        "name:xx": "Tenmile Creek"
      }
    },
    {
      "geometry": {
        "type": "Point",
        "coordinates": [
          -86.4833,
          30.5833
        ]
      },
      "type": "Feature",
      "properties": {
        "hierarchy": [
          "tgn:2714787",
          "tgn:1000001",
          "tgn:7012149",
          "tgn:2000281",
          "tgn:7007240",
          "tgn:7029392"
        ],
        "placetype": [
          "aat:300008706"
        ],
        "id": 2714787,
        "name:xx": "Tenmile Creek"
      }
    },
    {
      "geometry": {
        "type": "Point",
        "coordinates": [
          -85.3667,
          30.5333
        ]
      },
      "type": "Feature",
      "properties": {
        "hierarchy": [
          "tgn:2714788",
          "tgn:1000001",
          "tgn:2000260",
          "tgn:7012149",
          "tgn:7007240",
          "tgn:7029392"
        ],
        "placetype": [
          "aat:300008706"
        ],
        "id": 2714788,
        "name:xx": "Tenmile Creek"
      }
    },
    {
      "geometry": {
        "type": "Point",
        "coordinates": [
          -83.1833,
          31.2667
        ]
      },
      "type": "Feature",
      "properties": {
        "hierarchy": [
          "tgn:2714789",
          "tgn:1000001",
          "tgn:7012149",
          "tgn:7007248",
          "tgn:7029392"
        ],
        "placetype": [
          "aat:300008706"
        ],
        "id": 2714789,
        "name:xx": "Tenmile Creek"
      }
    }
  ]
}
