{
  "geometry": {
    "type": "Point",
    "coordinates": [
      -93.4333,
      31.85
    ]
  },
  "type": "Feature",
  "properties": {
    "hierarchy": [
      "tgn:2199913",
      "tgn:1000001",
      "tgn:7012149",
      "tgn:2000888",
      "tgn:7007256",
      "tgn:7029392"
    ],
    "placetype": [
      "aat:300008699"
    ],
    "id": 2199913,
    "name:xx": "Brushy Bayou"
  }
}
