{
  "type": "FeatureCollection",
  "features": [
    {
      "geometry": {
        "type": "Point",
        "coordinates": [
          30.033333,
          31.283333
        ]
      },
      "type": "Feature",
      "properties": {
        "hierarchy": [
          "tgn:7534520",
          "tgn:7001242",
          "tgn:7016833",
          "tgn:1001079",
          "tgn:7029392"
        ],
        "placetype": [
          "aat:300000206"
        ],
        "name:en": "'Izbat al Hilālīyah",
        "id": 7534520
      }
    },
    {
      "geometry": {
        "type": "Point",
        "coordinates": [
          32.887557,
          25.184189
        ]
      },
      "type": "Feature",
      "properties": {
        "hierarchy": [
          "tgn:7534521",
          "tgn:7001242",
          "tgn:7001311",
          "tgn:7016833",
          "tgn:7029392"
        ],
        "placetype": [
          "aat:300379998"
        ],
        "name:en": "Hilāl, Wādī",
        "id": 7534521
      }
    },
    {
      "geometry": {
        "type": "Point",
        "coordinates": [
          31.121111,
          31.570556
        ]
      },
      "type": "Feature",
      "properties": {
        "hierarchy": [
          "tgn:7534522",
          "tgn:7001242",
          "tgn:7016833",
          "tgn:1001335",
          "tgn:7029392"
        ],
        "placetype": [
          "aat:300387086",
          "aat:300266556"
        ],
        "name:en": "Hilāl, Mallāḩat",
        "id": 7534522
      }
    },
    {
      "geometry": {
        "type": "Point",
        "coordinates": [
          33.544622,
          28.827924
        ]
      },
      "type": "Feature",
      "properties": {
        "hierarchy": [
          "tgn:7534524",
          "tgn:7001242",
          "tgn:7016833",
          "tgn:7001336",
          "tgn:7029392"
        ],
        "placetype": [
          "aat:300008795"
        ],
        "name:en": "Hilāl, Jabal",
        "id": 7534524
      }
    },
    {
      "geometry": {
        "type": "Point",
        "coordinates": [
          29.27983,
          30.351678
        ]
      },
      "type": "Feature",
      "properties": {
        "hierarchy": [
          "tgn:7534525",
          "tgn:7001242",
          "tgn:7016833",
          "tgn:1001418",
          "tgn:7029392"
        ],
        "placetype": [
          "aat:300008777"
        ],
        "name:en": "Hilāb, Qūr al",
        "id": 7534525
      }
    },
    {
      "geometry": {
        "type": "Point",
        "coordinates": [
          28.017467,
          31.152285
        ]
      },
      "type": "Feature",
      "properties": {
        "hierarchy": [
          "tgn:7534527",
          "tgn:7001242",
          "tgn:7016833",
          "tgn:1001418",
          "tgn:7029392"
        ],
        "placetype": [
          "aat:300132315"
        ],
        "name:en": "Ḩikmah, Khalīj al",
        "id": 7534527
      }
    },
    {
      "geometry": {
        "type": "Point",
        "coordinates": [
          32.75,
          25.15
        ]
      },
      "type": "Feature",
      "properties": {
        "hierarchy": [
          "tgn:7534528",
          "tgn:7001242",
          "tgn:7016833",
          "tgn:7000122",
          "tgn:7029392"
        ],
        "placetype": [
          "aat:300008791"
        ],
        "name:en": "Ḩijz, Jazīrat al",
        "id": 7534528
      }
    },
    {
      "geometry": {
        "type": "Point",
        "coordinates": [
          31.966667,
          26.233333
        ]
      },
      "type": "Feature",
      "properties": {
        "hierarchy": [
          "tgn:7534529",
          "tgn:7001242",
          "tgn:7016833",
          "tgn:7000123",
          "tgn:7029392"
        ],
        "placetype": [
          "aat:300343519"
        ],
        "name:en": "Ḩijz, Ḩawḑ al",
        "id": 7534529
      }
    }
  ]
}
