{
  "geometry": {
    "type": "Point",
    "coordinates": [
      -67.9833,
      45.8167
    ]
  },
  "type": "Feature",
  "properties": {
    "hierarchy": [
      "tgn:2044952",
      "tgn:2000919",
      "tgn:1000001",
      "tgn:7012149",
      "tgn:7007515",
      "tgn:7029392"
    ],
    "placetype": [
      "aat:300008347"
    ],
    "id": 2044952,
    "name:xx": "Haynesville"
  }
}
