{
  "type": "FeatureCollection",
  "features": [
    {
      "geometry": {
        "type": "Point",
        "coordinates": [
          -143.4167,
          61.7167
        ]
      },
      "type": "Feature",
      "properties": {
        "hierarchy": [
          "tgn:1103981",
          "tgn:7006450",
          "tgn:1000001",
          "tgn:7012149",
          "tgn:2000086",
          "tgn:7029392"
        ],
        "placetype": [
          "aat:300008795"
        ],
        "id": 1103981,
        "name:xx": "Blackburn, Mount"
      }
    },
    {
      "geometry": {
        "type": "Point",
        "coordinates": [
          -4.133333,
          55.316667
        ]
      },
      "type": "Feature",
      "properties": {
        "hierarchy": [
          "tgn:1103982",
          "tgn:7002444",
          "tgn:7019088",
          "tgn:1000003",
          "tgn:7008591",
          "tgn:7029392"
        ],
        "placetype": [
          "aat:300008777",
          "aat:300008795"
        ],
        "name:en": "Blackcraig Hill",
        "id": 1103982
      }
    },
    {
      "geometry": {
        "type": "Point",
        "coordinates": [
          -106.6833,
          41.0333
        ]
      },
      "type": "Feature",
      "properties": {
        "hierarchy": [
          "tgn:1103983",
          "tgn:1000001",
          "tgn:2002368",
          "tgn:7012149",
          "tgn:7007923",
          "tgn:7029392"
        ],
        "placetype": [
          "aat:300008795"
        ],
        "id": 1103983,
        "name:xx": "Blackhall Mountain"
      }
    },
    {
      "geometry": {
        "type": "Point",
        "coordinates": [
          -111,
          45.4333
        ]
      },
      "type": "Feature",
      "properties": {
        "hierarchy": [
          "tgn:1103986",
          "tgn:1000001",
          "tgn:7012149",
          "tgn:2001275",
          "tgn:7007524",
          "tgn:7029392"
        ],
        "placetype": [
          "aat:300008795"
        ],
        "id": 1103986,
        "name:xx": "Blackmore, Mount"
      }
    },
    {
      "geometry": {
        "type": "Point",
        "coordinates": [
          -66.8667,
          48.7833
        ]
      },
      "type": "Feature",
      "properties": {
        "hierarchy": [
          "tgn:1103989",
          "tgn:7005685",
          "tgn:1000001",
          "tgn:7005804",
          "tgn:7029392"
        ],
        "placetype": [
          "aat:300008795"
        ],
        "id": 1103989,
        "name:xx": "Blanc, Mont"
      }
    }
  ]
}
