{
  "geometry": {
    "type": "Point",
    "coordinates": [
      -119.8667,
      39.15
    ]
  },
  "type": "Feature",
  "properties": {
    "hierarchy": [
      "tgn:2674027",
      "tgn:1000001",
      "tgn:7012149",
      "tgn:7007526",
      "tgn:7029392"
    ],
    "placetype": [
      "aat:300008761"
    ],
    "id": 2674027,
    "name:xx": "Snow Valley"
  }
}
