{
  "geometry": {
    "type": "Point",
    "coordinates": [
      78.454952,
      24.97657
    ]
  },
  "type": "Feature",
  "properties": {
    "hierarchy": [
      "tgn:7585280",
      "tgn:1000004",
      "tgn:7000198",
      "tgn:7016722",
      "tgn:7029392"
    ],
    "placetype": [
      "aat:300008347"
    ],
    "name:en": "Kakrāri",
    "id": 7585280
  }
}
