{
  "geometry": {
    "type": "Point",
    "coordinates": [
      -109.2333,
      44.6167
    ]
  },
  "type": "Feature",
  "properties": {
    "hierarchy": [
      "tgn:2297183",
      "tgn:1000001",
      "tgn:7012149",
      "tgn:2002379",
      "tgn:7007923",
      "tgn:7029392"
    ],
    "placetype": [
      "aat:300008706"
    ],
    "id": 2297183,
    "name:xx": "Dry Creek"
  }
}
