{
  "geometry": {
    "type": "Point",
    "coordinates": [
      -96.3333,
      38.1167
    ]
  },
  "type": "Feature",
  "properties": {
    "hierarchy": [
      "tgn:2434310",
      "tgn:1000001",
      "tgn:2000696",
      "tgn:7012149",
      "tgn:7007254",
      "tgn:7029392"
    ],
    "placetype": [
      "aat:300008347"
    ],
    "id": 2434310,
    "name:xx": "Kenbro"
  }
}
