{
  "geometry": {
    "type": "Point",
    "coordinates": [
      -109.3333,
      34.0167
    ]
  },
  "type": "Feature",
  "properties": {
    "hierarchy": [
      "tgn:2212910",
      "tgn:2000090",
      "tgn:1000001",
      "tgn:7006451",
      "tgn:7012149",
      "tgn:7029392"
    ],
    "placetype": [
      "aat:300006191"
    ],
    "id": 2212910,
    "name:xx": "CB Tank Number Two"
  }
}
