{
  "type": "FeatureCollection",
  "features": [
    {
      "geometry": {
        "type": "Point",
        "coordinates": [
          5.883333,
          51.883333
        ]
      },
      "type": "Feature",
      "properties": {
        "hierarchy": [
          "tgn:7271980",
          "tgn:7003619",
          "tgn:1000003",
          "tgn:7016845",
          "tgn:7029392"
        ],
        "placetype": [
          "aat:300008347"
        ],
        "name:nl": "'t Zand",
        "id": 7271980
      }
    },
    {
      "geometry": {
        "type": "Point",
        "coordinates": [
          4.966667,
          51.816667
        ]
      },
      "type": "Feature",
      "properties": {
        "hierarchy": [
          "tgn:7271981",
          "tgn:1000003",
          "tgn:7003624",
          "tgn:7016845",
          "tgn:7029392"
        ],
        "placetype": [
          "aat:300008347"
        ],
        "name:nl": "'t Zand",
        "id": 7271981
      }
    },
    {
      "geometry": {
        "type": "Point",
        "coordinates": [
          5.5,
          51.65
        ]
      },
      "type": "Feature",
      "properties": {
        "hierarchy": [
          "tgn:7271982",
          "tgn:1000003",
          "tgn:7003624",
          "tgn:7016845",
          "tgn:7029392"
        ],
        "placetype": [
          "aat:300008347"
        ],
        "name:nl": "'t Zand",
        "id": 7271982
      }
    },
    {
      "geometry": {
        "type": "Point",
        "coordinates": [
          6.7,
          52.133333
        ]
      },
      "type": "Feature",
      "properties": {
        "hierarchy": [
          "tgn:7271983",
          "tgn:1000003",
          "tgn:7003626",
          "tgn:7016845",
          "tgn:7029392"
        ],
        "placetype": [
          "aat:300386887"
        ],
        "name:nl": "'t Zand",
        "id": 7271983
      }
    },
    {
      "geometry": {
        "type": "Point",
        "coordinates": [
          5.85,
          53.083333
        ]
      },
      "type": "Feature",
      "properties": {
        "hierarchy": [
          "tgn:7271984",
          "tgn:7003616",
          "tgn:1000003",
          "tgn:7016845",
          "tgn:7029392"
        ],
        "placetype": [
          "aat:300386965"
        ],
        "name:nl": "Tynje",
        "id": 7271984
      }
    },
    {
      "geometry": {
        "type": "Point",
        "coordinates": [
          6.6,
          53.083333
        ]
      },
      "type": "Feature",
      "properties": {
        "hierarchy": [
          "tgn:7271985",
          "tgn:7003614",
          "tgn:1000003",
          "tgn:7016845",
          "tgn:7029392"
        ],
        "placetype": [
          "aat:300008347"
        ],
        "name:nl": "Tynaarlo",
        "id": 7271985
      }
    },
    {
      "geometry": {
        "type": "Point",
        "coordinates": [
          4.283333,
          52
        ]
      },
      "type": "Feature",
      "properties": {
        "hierarchy": [
          "tgn:7271986",
          "tgn:1000003",
          "tgn:7003632",
          "tgn:7016845",
          "tgn:7029392"
        ],
        "placetype": [
          "aat:300008347"
        ],
        "name:nl": "'t Woudt",
        "id": 7271986
      }
    },
    {
      "geometry": {
        "type": "Point",
        "coordinates": [
          5.55,
          52.2
        ]
      },
      "type": "Feature",
      "properties": {
        "hierarchy": [
          "tgn:7271987",
          "tgn:7003619",
          "tgn:1000003",
          "tgn:7016845",
          "tgn:7029392"
        ],
        "placetype": [
          "aat:300008347"
        ],
        "name:nl": "'t Woud",
        "id": 7271987
      }
    },
    {
      "geometry": {
        "type": "Point",
        "coordinates": [
          5.416667,
          51.4
        ]
      },
      "type": "Feature",
      "properties": {
        "hierarchy": [
          "tgn:7271988",
          "tgn:1000003",
          "tgn:7003624",
          "tgn:7016845",
          "tgn:7029392"
        ],
        "placetype": [
          "aat:300387200"
        ],
        "name:nl": "'t Witven",
        "id": 7271988
      }
    },
    {
      "geometry": {
        "type": "Point",
        "coordinates": [
          6.55,
          52.45
        ]
      },
      "type": "Feature",
      "properties": {
        "hierarchy": [
          "tgn:7271989",
          "tgn:1000003",
          "tgn:7003626",
          "tgn:7016845",
          "tgn:7029392"
        ],
        "placetype": [
          "aat:300007836"
        ],
        "name:nl": "Twistbrug",
        "id": 7271989
      }
    }
  ]
}
