{
  "geometry": {
    "type": "Point",
    "coordinates": [
      -112.8667,
      37.1167
    ]
  },
  "type": "Feature",
  "properties": {
    "hierarchy": [
      "tgn:2482369",
      "tgn:1000001",
      "tgn:7012149",
      "tgn:2002113",
      "tgn:7007827",
      "tgn:7029392"
    ],
    "placetype": [
      "aat:300008697"
    ],
    "id": 2482369,
    "name:xx": "Langston-Willow Spring"
  }
}
