{
  "geometry": {
    "type": "Point",
    "coordinates": [
      30.716667,
      24.55
    ]
  },
  "type": "Feature",
  "properties": {
    "hierarchy": [
      "tgn:7539663",
      "tgn:7001242",
      "tgn:7016833",
      "tgn:7001334",
      "tgn:7029392"
    ],
    "placetype": [
      "aat:300008697"
    ],
    "name:en": "Qārah ash Sharqīyah, 'Ayn al",
    "id": 7539663
  }
}
