{
  "geometry": {
    "type": "Point",
    "coordinates": [
      -118.6333,
      35.85
    ]
  },
  "type": "Feature",
  "properties": {
    "hierarchy": [
      "tgn:2509428",
      "tgn:1000001",
      "tgn:7012149",
      "tgn:7007157",
      "tgn:1002956",
      "tgn:7029392"
    ],
    "placetype": [
      "aat:300008697"
    ],
    "id": 2509428,
    "name:xx": "Middle Fork Spring"
  }
}
