{
  "geometry": {
    "type": "Point",
    "coordinates": [
      -80.3667,
      39.8167
    ]
  },
  "type": "Feature",
  "properties": {
    "hierarchy": [
      "tgn:2283469",
      "tgn:1000001",
      "tgn:7012149",
      "tgn:2001724",
      "tgn:7007710",
      "tgn:7029392"
    ],
    "placetype": [
      "aat:300008347"
    ],
    "id": 2283469,
    "name:xx": "Delphene"
  }
}
