{
  "geometry": {
    "type": "Point",
    "coordinates": [
      -85.3833,
      38.7833
    ]
  },
  "type": "Feature",
  "properties": {
    "hierarchy": [
      "tgn:2453500",
      "tgn:1000001",
      "tgn:7012149",
      "tgn:1002515",
      "tgn:7007252",
      "tgn:7029392"
    ],
    "placetype": [
      "aat:300008706"
    ],
    "id": 2453500,
    "name:xx": "Little Clifty Creek"
  }
}
