{
  "geometry": {
    "type": "Point",
    "coordinates": [
      -80.8167,
      35.1667
    ]
  },
  "type": "Feature",
  "properties": {
    "hierarchy": [
      "tgn:2338340",
      "tgn:1000001",
      "tgn:7012149",
      "tgn:7014021",
      "tgn:7007709",
      "tgn:7029392"
    ],
    "placetype": [
      "aat:300008347"
    ],
    "id": 2338340,
    "name:xx": "Foxcroft"
  }
}
