{
  "type": "FeatureCollection",
  "features": [
    {
      "geometry": {
        "type": "Point",
        "coordinates": [
          -123.4167,
          45.7
        ]
      },
      "type": "Feature",
      "properties": {
        "hierarchy": [
          "tgn:2145530",
          "tgn:1000001",
          "tgn:7012149",
          "tgn:7007708",
          "tgn:7029392"
        ],
        "placetype": [
          "aat:300008706"
        ],
        "id": 2145530,
        "name:xx": "Baldwin Creek"
      }
    },
    {
      "geometry": {
        "type": "Point",
        "coordinates": [
          -76.0333,
          41.9167
        ]
      },
      "type": "Feature",
      "properties": {
        "hierarchy": [
          "tgn:2145531",
          "tgn:1000001",
          "tgn:7012149",
          "tgn:1002932",
          "tgn:7007710",
          "tgn:7029392"
        ],
        "placetype": [
          "aat:300008706"
        ],
        "id": 2145531,
        "name:xx": "Baldwin Creek"
      }
    },
    {
      "geometry": {
        "type": "Point",
        "coordinates": [
          -77.2,
          41.9333
        ]
      },
      "type": "Feature",
      "properties": {
        "hierarchy": [
          "tgn:2145532",
          "tgn:1000001",
          "tgn:7012149",
          "tgn:1002945",
          "tgn:7007710",
          "tgn:7029392"
        ],
        "placetype": [
          "aat:300008706"
        ],
        "id": 2145532,
        "name:xx": "Baldwin Creek"
      }
    },
    {
      "geometry": {
        "type": "Point",
        "coordinates": [
          -79.0167,
          40.3333
        ]
      },
      "type": "Feature",
      "properties": {
        "hierarchy": [
          "tgn:2145533",
          "tgn:1000001",
          "tgn:7012149",
          "tgn:1003017",
          "tgn:7007710",
          "tgn:7029392"
        ],
        "placetype": [
          "aat:300008706"
        ],
        "id": 2145533,
        "name:xx": "Baldwin Creek"
      }
    },
    {
      "geometry": {
        "type": "Point",
        "coordinates": [
          -95.55,
          30.75
        ]
      },
      "type": "Feature",
      "properties": {
        "hierarchy": [
          "tgn:2145534",
          "tgn:1000001",
          "tgn:7012149",
          "tgn:1002980",
          "tgn:7007826",
          "tgn:7029392"
        ],
        "placetype": [
          "aat:300008706"
        ],
        "id": 2145534,
        "name:xx": "Baldwin Creek"
      }
    },
    {
      "geometry": {
        "type": "Point",
        "coordinates": [
          -72.9333,
          44.1667
        ]
      },
      "type": "Feature",
      "properties": {
        "hierarchy": [
          "tgn:2145535",
          "tgn:1000001",
          "tgn:7012149",
          "tgn:7007828",
          "tgn:7029392"
        ],
        "placetype": [
          "aat:300008706"
        ],
        "id": 2145535,
        "name:xx": "Baldwin Creek"
      }
    },
    {
      "geometry": {
        "type": "Point",
        "coordinates": [
          -88.4167,
          45.2
        ]
      },
      "type": "Feature",
      "properties": {
        "hierarchy": [
          "tgn:2145536",
          "tgn:1000001",
          "tgn:7012149",
          "tgn:2002341",
          "tgn:7007922",
          "tgn:7029392"
        ],
        "placetype": [
          "aat:300008706"
        ],
        "id": 2145536,
        "name:xx": "Baldwin Creek"
      }
    },
    {
      "geometry": {
        "type": "Point",
        "coordinates": [
          -90.1167,
          45.1333
        ]
      },
      "type": "Feature",
      "properties": {
        "hierarchy": [
          "tgn:2145537",
          "tgn:1000001",
          "tgn:7012149",
          "tgn:7007922",
          "tgn:7029392"
        ],
        "placetype": [
          "aat:300008706"
        ],
        "id": 2145537,
        "name:xx": "Baldwin Creek"
      }
    },
    {
      "geometry": {
        "type": "Point",
        "coordinates": [
          -107.1,
          43.7833
        ]
      },
      "type": "Feature",
      "properties": {
        "hierarchy": [
          "tgn:2145538",
          "tgn:1000001",
          "tgn:7012149",
          "tgn:2002374",
          "tgn:7007923",
          "tgn:7029392"
        ],
        "placetype": [
          "aat:300008706"
        ],
        "id": 2145538,
        "name:xx": "Baldwin Creek"
      }
    },
    {
      "geometry": {
        "type": "Point",
        "coordinates": [
          -108.95,
          42.7833
        ]
      },
      "type": "Feature",
      "properties": {
        "hierarchy": [
          "tgn:2145539",
          "tgn:1000001",
          "tgn:7012149",
          "tgn:2002371",
          "tgn:7007923",
          "tgn:7029392"
        ],
        "placetype": [
          "aat:300008706"
        ],
        "id": 2145539,
        "name:xx": "Baldwin Creek"
      }
    }
  ]
}
