{
  "type": "FeatureCollection",
  "features": [
    {
      "geometry": {
        "type": "Point",
        "coordinates": [
          9.183333,
          41.2
        ]
      },
      "type": "Feature",
      "properties": {
        "hierarchy": [
          "tgn:7050921",
          "tgn:7015163",
          "tgn:1000003",
          "tgn:7003121",
          "tgn:1000080",
          "tgn:7029392"
        ],
        "placetype": [
          "aat:300008347"
        ],
        "id": 7050921,
        "name:xx": "La Murta"
      }
    },
    {
      "geometry": {
        "type": "Point",
        "coordinates": [
          11.416667,
          44.45
        ]
      },
      "type": "Feature",
      "properties": {
        "hierarchy": [
          "tgn:7050922",
          "tgn:7003127",
          "tgn:1000003",
          "tgn:7008516",
          "tgn:1000080",
          "tgn:7029392"
        ],
        "placetype": [
          "aat:300008347"
        ],
        "id": 7050922,
        "name:xx": "Ospizio San Carlo"
      }
    },
    {
      "geometry": {
        "type": "Point",
        "coordinates": [
          15.983333,
          39.7
        ]
      },
      "type": "Feature",
      "properties": {
        "hierarchy": [
          "tgn:7050923",
          "tgn:1003450",
          "tgn:7007850",
          "tgn:1000003",
          "tgn:1000080",
          "tgn:7029392"
        ],
        "placetype": [
          "aat:300008795"
        ],
        "id": 7050923,
        "name:xx": "La Mula"
      }
    },
    {
      "geometry": {
        "type": "Point",
        "coordinates": [
          12.103889,
          46.250556
        ]
      },
      "type": "Feature",
      "properties": {
        "hierarchy": [
          "tgn:7050924",
          "tgn:7002991",
          "tgn:1000003",
          "tgn:7002997",
          "tgn:1000080",
          "tgn:7029392"
        ],
        "placetype": [
          "aat:300008347"
        ],
        "id": 7050924,
        "name:xx": "Muda"
      }
    },
    {
      "geometry": {
        "type": "Point",
        "coordinates": [
          8.1,
          45.233333
        ]
      },
      "type": "Feature",
      "properties": {
        "hierarchy": [
          "tgn:7050925",
          "tgn:7003154",
          "tgn:1000003",
          "tgn:7003120",
          "tgn:1000080",
          "tgn:7029392"
        ],
        "placetype": [
          "aat:300008347"
        ],
        "id": 7050925,
        "name:xx": "Lamporo"
      }
    },
    {
      "geometry": {
        "type": "Point",
        "coordinates": [
          15.833333,
          41.116667
        ]
      },
      "type": "Feature",
      "properties": {
        "hierarchy": [
          "tgn:7050928",
          "tgn:1003489",
          "tgn:7004610",
          "tgn:1000003",
          "tgn:1000080",
          "tgn:7029392"
        ],
        "placetype": [
          "aat:300008699"
        ],
        "id": 7050928,
        "name:xx": "Lampeggiano, Torrente"
      }
    }
  ]
}
