{
  "geometry": {
    "type": "Point",
    "coordinates": [
      74.95481,
      21.257079
    ]
  },
  "type": "Feature",
  "properties": {
    "hierarchy": [
      "tgn:7580050",
      "tgn:1000004",
      "tgn:7000198",
      "tgn:1001895",
      "tgn:7029392"
    ],
    "placetype": [
      "aat:300008347"
    ],
    "name:en": "Thālner",
    "id": 7580050
  }
}
