{
  "geometry": {
    "type": "Point",
    "coordinates": [
      86.827,
      23.69
    ]
  },
  "type": "Feature",
  "properties": {
    "hierarchy": [
      "tgn:1075204",
      "tgn:1000004",
      "tgn:7000198",
      "tgn:1001977",
      "tgn:7029392"
    ],
    "placetype": [
      "aat:300008347"
    ],
    "name:en": "Dishergarh",
    "id": 1075204
  }
}
