{
  "geometry": {
    "type": "Point",
    "coordinates": [
      106.2667,
      29.7833
    ]
  },
  "type": "Feature",
  "properties": {
    "hierarchy": [
      "tgn:1071138",
      "tgn:1000004",
      "tgn:7002087",
      "tgn:1000111",
      "tgn:7029392"
    ],
    "placetype": [
      "aat:300008347"
    ],
    "id": 1071138,
    "name:xx": "Qitangzhen"
  }
}
