{
  "geometry": {
    "type": "Point",
    "coordinates": [
      30.835962,
      28.900491
    ]
  },
  "type": "Feature",
  "properties": {
    "hierarchy": [
      "tgn:7541411",
      "tgn:7001242",
      "tgn:7016833",
      "tgn:1001142",
      "tgn:7029392"
    ],
    "placetype": [
      "aat:300008347"
    ],
    "name:en": "Al Muḩmūdīyah",
    "id": 7541411
  }
}
