{
  "geometry": {
    "type": "Point",
    "coordinates": [
      -72.3333,
      44.1833
    ]
  },
  "type": "Feature",
  "properties": {
    "hierarchy": [
      "tgn:2747769",
      "tgn:1000001",
      "tgn:7012149",
      "tgn:7029392"
    ],
    "placetype": [
      "aat:300008707"
    ],
    "id": 2747769,
    "name:xx": "Waits River"
  }
}
