{
  "geometry": {
    "type": "Point",
    "coordinates": [
      -131.8167,
      55.4667
    ]
  },
  "type": "Feature",
  "properties": {
    "hierarchy": [
      "tgn:2601273",
      "tgn:7006450",
      "tgn:1000001",
      "tgn:2124076",
      "tgn:7012149",
      "tgn:7029392"
    ],
    "placetype": [
      "aat:300008791"
    ],
    "id": 2601273,
    "name:xx": "Pup Island"
  }
}
