{
  "geometry": {
    "type": "Point",
    "coordinates": [
      117.85,
      -32.3333
    ]
  },
  "type": "Feature",
  "properties": {
    "hierarchy": [
      "tgn:1096650",
      "tgn:7000490",
      "tgn:1000006",
      "tgn:7001834",
      "tgn:7029392"
    ],
    "placetype": [
      "aat:300008347"
    ],
    "id": 1096650,
    "name:xx": "Corrigin"
  }
}
