{
  "geometry": {
    "type": "Point",
    "coordinates": [
      -11.5667,
      6.9833
    ]
  },
  "type": "Feature",
  "properties": {
    "hierarchy": [
      "tgn:1092596",
      "tgn:7001242",
      "tgn:1001543",
      "tgn:1000191",
      "tgn:7029392"
    ],
    "placetype": [
      "aat:300008347"
    ],
    "id": 1092596,
    "name:xx": "Sulima"
  }
}
