{
  "geometry": {
    "type": "Point",
    "coordinates": [
      -82.2667,
      31.05
    ]
  },
  "type": "Feature",
  "properties": {
    "hierarchy": [
      "tgn:2667676",
      "tgn:1000001",
      "tgn:7012149",
      "tgn:2000439",
      "tgn:7007248",
      "tgn:7029392"
    ],
    "placetype": [
      "aat:300008680"
    ],
    "id": 2667676,
    "name:xx": "Skull Lake"
  }
}
