{
  "geometry": {
    "type": "Point",
    "coordinates": [
      -83.4833,
      37.1833
    ]
  },
  "type": "Feature",
  "properties": {
    "hierarchy": [
      "tgn:2206788",
      "tgn:1000001",
      "tgn:2000782",
      "tgn:7012149",
      "tgn:7007255",
      "tgn:7029392"
    ],
    "placetype": [
      "aat:300008706"
    ],
    "id": 2206788,
    "name:xx": "Bullskin Creek"
  }
}
