{
  "geometry": {
    "type": "Point",
    "coordinates": [
      -91.6167,
      38.7333
    ]
  },
  "type": "Feature",
  "properties": {
    "hierarchy": [
      "tgn:2708895",
      "tgn:1000001",
      "tgn:7012149",
      "tgn:1002687",
      "tgn:7007523",
      "tgn:7029392"
    ],
    "placetype": [
      "aat:300008706"
    ],
    "id": 2708895,
    "name:xx": "Synthianna Creek"
  }
}
