{
  "geometry": {
    "type": "Point",
    "coordinates": [
      -116.85,
      32.9667
    ]
  },
  "type": "Feature",
  "properties": {
    "hierarchy": [
      "tgn:2274639",
      "tgn:1000001",
      "tgn:7012149",
      "tgn:7007157",
      "tgn:1002858",
      "tgn:7029392"
    ],
    "placetype": [
      "aat:300008706"
    ],
    "id": 2274639,
    "name:xx": "Daly Creek"
  }
}
