{
  "geometry": {
    "type": "Point",
    "coordinates": [
      -84.1333,
      37.2167
    ]
  },
  "type": "Feature",
  "properties": {
    "hierarchy": [
      "tgn:2138232",
      "tgn:1000001",
      "tgn:7012149",
      "tgn:2000808",
      "tgn:7007255",
      "tgn:7029392"
    ],
    "placetype": [
      "aat:300266640"
    ],
    "id": 2138232,
    "name:xx": "Arthur Ridge"
  }
}
