{
  "geometry": {
    "type": "Point",
    "coordinates": [
      -107.1333,
      39.8667
    ]
  },
  "type": "Feature",
  "properties": {
    "hierarchy": [
      "tgn:2746388",
      "tgn:1000001",
      "tgn:7012149",
      "tgn:2000214",
      "tgn:7007158",
      "tgn:7029392"
    ],
    "placetype": [
      "aat:300008798"
    ],
    "id": 2746388,
    "name:xx": "W Mountain"
  }
}
