{
  "geometry": {
    "type": "Point",
    "coordinates": [
      79.175069,
      26.997905
    ]
  },
  "type": "Feature",
  "properties": {
    "hierarchy": [
      "tgn:7559888",
      "tgn:1000004",
      "tgn:7000198",
      "tgn:7016722",
      "tgn:7029392"
    ],
    "placetype": [
      "aat:300008347"
    ],
    "name:en": "Jagannāthpur",
    "id": 7559888
  }
}
