{
  "type": "FeatureCollection",
  "features": [
    {
      "geometry": {
        "type": "Point",
        "coordinates": [
          -71.033333,
          -34.2
        ]
      },
      "type": "Feature",
      "properties": {
        "hierarchy": [
          "tgn:7282190",
          "tgn:1001695",
          "tgn:1000049",
          "tgn:1000002",
          "tgn:7029392"
        ],
        "placetype": [
          "aat:300008777"
        ],
        "id": 7282190,
        "name:xx": "Sarateo, Loma"
      }
    },
    {
      "geometry": {
        "type": "Point",
        "coordinates": [
          -69.183333,
          -18.083333
        ]
      },
      "type": "Feature",
      "properties": {
        "hierarchy": [
          "tgn:7282191",
          "tgn:7002464",
          "tgn:1000049",
          "tgn:1000002",
          "tgn:7029392"
        ],
        "placetype": [
          "aat:300008347"
        ],
        "id": 7282191,
        "name:xx": "Saracota"
      }
    },
    {
      "geometry": {
        "type": "Point",
        "coordinates": [
          -73.783333,
          -52.433333
        ]
      },
      "type": "Feature",
      "properties": {
        "hierarchy": [
          "tgn:7282192",
          "tgn:1001702",
          "tgn:1000049",
          "tgn:1000002",
          "tgn:7029392"
        ],
        "placetype": [
          "aat:300011692"
        ],
        "id": 7282192,
        "name:xx": "Sara, Roca"
      }
    },
    {
      "geometry": {
        "type": "Point",
        "coordinates": [
          -70.45,
          -53.316667
        ]
      },
      "type": "Feature",
      "properties": {
        "hierarchy": [
          "tgn:7282193",
          "tgn:1001702",
          "tgn:1000049",
          "tgn:1000002",
          "tgn:7029392"
        ],
        "placetype": [
          "aat:300386846"
        ],
        "id": 7282193,
        "name:xx": "Sara, Punta"
      }
    },
    {
      "geometry": {
        "type": "Point",
        "coordinates": [
          -73.766667,
          -53.283333
        ]
      },
      "type": "Feature",
      "properties": {
        "hierarchy": [
          "tgn:7282194",
          "tgn:1001702",
          "tgn:1000049",
          "tgn:1000002",
          "tgn:7029392"
        ],
        "placetype": [
          "aat:300008791"
        ],
        "id": 7282194,
        "name:xx": "Sara, Isla"
      }
    },
    {
      "geometry": {
        "type": "Point",
        "coordinates": [
          -70.9,
          -32.7
        ]
      },
      "type": "Feature",
      "properties": {
        "hierarchy": [
          "tgn:7282195",
          "tgn:1001768",
          "tgn:1000049",
          "tgn:1000002",
          "tgn:7029392"
        ],
        "placetype": [
          "aat:300008795"
        ],
        "id": 7282195,
        "name:xx": "Sara, Cerro"
      }
    },
    {
      "geometry": {
        "type": "Point",
        "coordinates": [
          -69.333333,
          -52.733333
        ]
      },
      "type": "Feature",
      "properties": {
        "hierarchy": [
          "tgn:7282196",
          "tgn:1001702",
          "tgn:1000049",
          "tgn:1000002",
          "tgn:7029392"
        ],
        "placetype": [
          "aat:300000241"
        ],
        "id": 7282196,
        "name:xx": "Sara"
      }
    },
    {
      "geometry": {
        "type": "Point",
        "coordinates": [
          -69.883333,
          -25.35
        ]
      },
      "type": "Feature",
      "properties": {
        "hierarchy": [
          "tgn:7282197",
          "tgn:7016598",
          "tgn:1000049",
          "tgn:1000002",
          "tgn:7029392"
        ],
        "placetype": [
          "aat:300008347"
        ],
        "id": 7282197,
        "name:xx": "Sara"
      }
    },
    {
      "geometry": {
        "type": "Point",
        "coordinates": [
          -68.7,
          -21.333333
        ]
      },
      "type": "Feature",
      "properties": {
        "hierarchy": [
          "tgn:7282198",
          "tgn:7016598",
          "tgn:1000049",
          "tgn:1000002",
          "tgn:7029392"
        ],
        "placetype": [
          "aat:300266554",
          "aat:300008699"
        ],
        "id": 7282198,
        "name:xx": "Sapunta, Quebrada de"
      }
    },
    {
      "geometry": {
        "type": "Point",
        "coordinates": [
          -68.783333,
          -21.3
        ]
      },
      "type": "Feature",
      "properties": {
        "hierarchy": [
          "tgn:7282199",
          "tgn:7016598",
          "tgn:1000049",
          "tgn:1000002",
          "tgn:7029392"
        ],
        "placetype": [
          "aat:300008795"
        ],
        "id": 7282199,
        "name:xx": "Sapunta, Cerro"
      }
    }
  ]
}
