{
  "geometry": {
    "type": "Point",
    "coordinates": [
      -8.25,
      42.433333
    ]
  },
  "type": "Feature",
  "properties": {
    "hierarchy": [
      "tgn:7339126",
      "tgn:7002831",
      "tgn:1000003",
      "tgn:7002786",
      "tgn:1000095",
      "tgn:7029392"
    ],
    "placetype": [
      "aat:300008347"
    ],
    "id": 7339126,
    "name:xx": "Córcores"
  }
}
