{
  "geometry": {
    "type": "Point",
    "coordinates": [
      -86.2833,
      35.2833
    ]
  },
  "type": "Feature",
  "properties": {
    "hierarchy": [
      "tgn:2711076",
      "tgn:1000001",
      "tgn:7012149",
      "tgn:2001900",
      "tgn:7007825",
      "tgn:7029392"
    ],
    "placetype": [
      "aat:300266640"
    ],
    "id": 2711076,
    "name:xx": "Tankersley Ridge"
  }
}
