{
  "geometry": {
    "type": "Point",
    "coordinates": [
      -86.6833,
      41.4333
    ]
  },
  "type": "Feature",
  "properties": {
    "hierarchy": [
      "tgn:2497086",
      "tgn:1000001",
      "tgn:7012149",
      "tgn:1002561",
      "tgn:7007252",
      "tgn:7029392"
    ],
    "placetype": [
      "aat:300006075"
    ],
    "id": 2497086,
    "name:xx": "Maurey Ditch"
  }
}
