{
  "geometry": {
    "type": "Point",
    "coordinates": [
      -161.2333,
      65.4167
    ]
  },
  "type": "Feature",
  "properties": {
    "hierarchy": [
      "tgn:1141126",
      "tgn:7006450",
      "tgn:1000001",
      "tgn:7012149",
      "tgn:7029392"
    ],
    "placetype": [
      "aat:300008795"
    ],
    "id": 1141126,
    "name:xx": "Granite Mountain"
  }
}
