{
  "type": "FeatureCollection",
  "features": [
    {
      "geometry": {
        "type": "Point",
        "coordinates": [
          -1.316667,
          54.8
        ]
      },
      "type": "Feature",
      "properties": {
        "hierarchy": [
          "tgn:7452062",
          "tgn:7002445",
          "tgn:1000003",
          "tgn:7008127",
          "tgn:7008591",
          "tgn:7029392"
        ],
        "placetype": [
          "aat:300132316"
        ],
        "name:en": "Hawthorn Hive",
        "id": 7452062
      }
    },
    {
      "geometry": {
        "type": "Point",
        "coordinates": [
          -3.133333,
          55.85
        ]
      },
      "type": "Feature",
      "properties": {
        "hierarchy": [
          "tgn:7452063",
          "tgn:7002444",
          "tgn:1000003",
          "tgn:7019123",
          "tgn:7008591",
          "tgn:7029392"
        ],
        "placetype": [
          "aat:300008347"
        ],
        "name:en": "Hawthornden",
        "id": 7452063
      }
    },
    {
      "geometry": {
        "type": "Point",
        "coordinates": [
          -1.316667,
          54.8
        ]
      },
      "type": "Feature",
      "properties": {
        "hierarchy": [
          "tgn:7452064",
          "tgn:7002445",
          "tgn:1000003",
          "tgn:7008127",
          "tgn:7008591",
          "tgn:7029392"
        ],
        "placetype": [
          "aat:300008699"
        ],
        "name:en": "Hawthorn Burn",
        "id": 7452064
      }
    },
    {
      "geometry": {
        "type": "Point",
        "coordinates": [
          -1.35,
          54.8
        ]
      },
      "type": "Feature",
      "properties": {
        "hierarchy": [
          "tgn:7452065",
          "tgn:7002445",
          "tgn:1000003",
          "tgn:7008127",
          "tgn:7008591",
          "tgn:7029392"
        ],
        "placetype": [
          "aat:300008347"
        ],
        "name:en": "Hawthorn",
        "id": 7452065
      }
    },
    {
      "geometry": {
        "type": "Point",
        "coordinates": [
          -2.223611,
          51.424167
        ]
      },
      "type": "Feature",
      "properties": {
        "hierarchy": [
          "tgn:7452066",
          "tgn:7002445",
          "tgn:1000003",
          "tgn:7008180",
          "tgn:7008591",
          "tgn:7029392"
        ],
        "placetype": [
          "aat:300008347"
        ],
        "name:en": "Hawthorn",
        "id": 7452066
      }
    },
    {
      "geometry": {
        "type": "Point",
        "coordinates": [
          -0.566667,
          54.45
        ]
      },
      "type": "Feature",
      "properties": {
        "hierarchy": [
          "tgn:7452067",
          "tgn:7002445",
          "tgn:1000003",
          "tgn:7008166",
          "tgn:7008591",
          "tgn:7029392"
        ],
        "placetype": [
          "aat:300008347"
        ],
        "name:en": "Hawsker",
        "id": 7452067
      }
    },
    {
      "geometry": {
        "type": "Point",
        "coordinates": [
          -0.6,
          51.733333
        ]
      },
      "type": "Feature",
      "properties": {
        "hierarchy": [
          "tgn:7452068",
          "tgn:7002445",
          "tgn:7008104",
          "tgn:1000003",
          "tgn:7008591",
          "tgn:7029392"
        ],
        "placetype": [
          "aat:300008347"
        ],
        "name:en": "Hawridge",
        "id": 7452068
      }
    }
  ]
}
