{
  "type": "FeatureCollection",
  "features": [
    {
      "geometry": {
        "type": "Point",
        "coordinates": [
          -3.916667,
          50.583333
        ]
      },
      "type": "Feature",
      "properties": {
        "hierarchy": [
          "tgn:7454554",
          "tgn:7002445",
          "tgn:1000003",
          "tgn:7012077",
          "tgn:7008591",
          "tgn:7029392"
        ],
        "placetype": [
          "aat:300386856"
        ],
        "name:en": "Dartmoor Forest",
        "id": 7454554
      }
    },
    {
      "geometry": {
        "type": "Point",
        "coordinates": [
          1.533333,
          52.266667
        ]
      },
      "type": "Feature",
      "properties": {
        "hierarchy": [
          "tgn:7454557",
          "tgn:7002445",
          "tgn:1000003",
          "tgn:7008185",
          "tgn:7008591",
          "tgn:7029392"
        ],
        "placetype": [
          "aat:300008347"
        ],
        "name:en": "Darsham",
        "id": 7454557
      }
    },
    {
      "geometry": {
        "type": "Point",
        "coordinates": [
          -3.133333,
          56.95
        ]
      },
      "type": "Feature",
      "properties": {
        "hierarchy": [
          "tgn:7454559",
          "tgn:5000432",
          "tgn:7002444",
          "tgn:1000003",
          "tgn:7008591",
          "tgn:7029392"
        ],
        "placetype": [
          "aat:300008699"
        ],
        "name:en": "Darrarie, Allt",
        "id": 7454559
      }
    }
  ]
}
