{
  "geometry": {
    "type": "Point",
    "coordinates": [
      -76.7667,
      34.7167
    ]
  },
  "type": "Feature",
  "properties": {
    "hierarchy": [
      "tgn:2073764",
      "tgn:1000001",
      "tgn:2001477",
      "tgn:7012149",
      "tgn:7007709",
      "tgn:7029392"
    ],
    "placetype": [
      "aat:300008347"
    ],
    "id": 2073764,
    "name:xx": "Bonham Heights"
  }
}
