{
  "geometry": {
    "type": "Point",
    "coordinates": [
      -77.7667,
      42.1167
    ]
  },
  "type": "Feature",
  "properties": {
    "hierarchy": [
      "tgn:2164913",
      "tgn:1002141",
      "tgn:1000001",
      "tgn:7012149",
      "tgn:7007568",
      "tgn:7029392"
    ],
    "placetype": [
      "aat:300008761"
    ],
    "id": 2164913,
    "name:xx": "Best Hollow"
  }
}
