{
  "geometry": {
    "type": "Point",
    "coordinates": [
      -122.95,
      47.6167
    ]
  },
  "type": "Feature",
  "properties": {
    "hierarchy": [
      "tgn:2500308",
      "tgn:1000001",
      "tgn:7012149",
      "tgn:1002521",
      "tgn:7007920",
      "tgn:7029392"
    ],
    "placetype": [
      "aat:300132316"
    ],
    "id": 2500308,
    "name:xx": "McDaniel Cove"
  }
}
