{
  "geometry": {
    "type": "Point",
    "coordinates": [
      84.64884,
      26.45987
    ]
  },
  "type": "Feature",
  "properties": {
    "hierarchy": [
      "tgn:7557412",
      "tgn:1000004",
      "tgn:1001842",
      "tgn:7000198",
      "tgn:7029392"
    ],
    "placetype": [
      "aat:300008347"
    ],
    "name:en": "Salīmpur",
    "id": 7557412
  }
}
