{
  "geometry": {
    "type": "Point",
    "coordinates": [
      -84.2167,
      35.1833
    ]
  },
  "type": "Feature",
  "properties": {
    "hierarchy": [
      "tgn:2077044",
      "tgn:1000001",
      "tgn:2001481",
      "tgn:7012149",
      "tgn:7007709",
      "tgn:7029392"
    ],
    "placetype": [
      "aat:300008347",
      "aat:300387210"
    ],
    "id": 2077044,
    "name:xx": "Violet"
  }
}
