{
  "type": "FeatureCollection",
  "features": [
    {
      "geometry": {
        "type": "Point",
        "coordinates": [
          10.433333,
          51.9
        ]
      },
      "type": "Feature",
      "properties": {
        "hierarchy": [
          "tgn:7005630",
          "tgn:1000003",
          "tgn:7003676",
          "tgn:7000084",
          "tgn:7029392"
        ],
        "placetype": [
          "aat:300008347",
          "aat:300387264",
          "aat:300387239",
          "aat:300008389",
          "aat:300387308",
          "aat:300387265",
          "aat:300343603",
          "aat:300387291"
        ],
        "id": 7005630,
        "name:de": "Goslar"
      }
    },
    {
      "geometry": {
        "type": "Point",
        "coordinates": [
          10.3,
          51.833333
        ]
      },
      "type": "Feature",
      "properties": {
        "hierarchy": [
          "tgn:7005631",
          "tgn:1000003",
          "tgn:7003676",
          "tgn:7000084",
          "tgn:7029392"
        ],
        "placetype": [
          "aat:300008347"
        ],
        "id": 7005631,
        "name:xx": "Wildemann"
      }
    },
    {
      "geometry": {
        "type": "Point",
        "coordinates": [
          10.3,
          51.866667
        ]
      },
      "type": "Feature",
      "properties": {
        "hierarchy": [
          "tgn:7005632",
          "tgn:1000003",
          "tgn:7003676",
          "tgn:7000084",
          "tgn:7029392"
        ],
        "placetype": [
          "aat:300008347"
        ],
        "id": 7005632,
        "name:xx": "Lautenthal"
      }
    },
    {
      "geometry": {
        "type": "Point",
        "coordinates": [
          10.033333,
          51.866667
        ]
      },
      "type": "Feature",
      "properties": {
        "hierarchy": [
          "tgn:7005633",
          "tgn:1000003",
          "tgn:7003676",
          "tgn:7000084",
          "tgn:7029392"
        ],
        "placetype": [
          "aat:300008347"
        ],
        "id": 7005633,
        "name:xx": "Bad Gandersheim"
      }
    },
    {
      "geometry": {
        "type": "Point",
        "coordinates": [
          9.683333,
          51.8
        ]
      },
      "type": "Feature",
      "properties": {
        "hierarchy": [
          "tgn:7005634",
          "tgn:1000003",
          "tgn:7003676",
          "tgn:7000084",
          "tgn:7029392"
        ],
        "placetype": [
          "aat:300008347"
        ],
        "id": 7005634,
        "name:xx": "Dassel"
      }
    },
    {
      "geometry": {
        "type": "Point",
        "coordinates": [
          9.866667,
          51.816667
        ]
      },
      "type": "Feature",
      "properties": {
        "hierarchy": [
          "tgn:7005635",
          "tgn:1000003",
          "tgn:7003676",
          "tgn:7000084",
          "tgn:7029392"
        ],
        "placetype": [
          "aat:300008347"
        ],
        "id": 7005635,
        "name:xx": "Einbeck"
      }
    },
    {
      "geometry": {
        "type": "Point",
        "coordinates": [
          9.65,
          51.666667
        ]
      },
      "type": "Feature",
      "properties": {
        "hierarchy": [
          "tgn:7005636",
          "tgn:1000003",
          "tgn:7003676",
          "tgn:7000084",
          "tgn:7029392"
        ],
        "placetype": [
          "aat:300008347"
        ],
        "id": 7005636,
        "name:xx": "Uslar"
      }
    },
    {
      "geometry": {
        "type": "Point",
        "coordinates": [
          -58,
          -5
        ]
      },
      "type": "Feature",
      "properties": {
        "hierarchy": [
          "tgn:7005637",
          "tgn:1000002",
          "tgn:7029392"
        ],
        "placetype": [
          "aat:300008707"
        ],
        "id": 7005637,
        "name:xx": "Corantijn"
      }
    },
    {
      "geometry": {
        "type": "Point",
        "coordinates": [
          -54,
          5.5
        ]
      },
      "type": "Feature",
      "properties": {
        "hierarchy": [
          "tgn:7005638",
          "tgn:1000002",
          "tgn:7029392"
        ],
        "placetype": [
          "aat:300008707"
        ],
        "id": 7005638,
        "name:xx": "Maroni"
      }
    }
  ]
}
