{
  "geometry": {
    "type": "Point",
    "coordinates": [
      128.7667,
      41.15
    ]
  },
  "type": "Feature",
  "properties": {
    "hierarchy": [
      "tgn:1106841",
      "tgn:1001284",
      "tgn:1000004",
      "tgn:1000122",
      "tgn:7029392"
    ],
    "placetype": [
      "aat:300008795"
    ],
    "id": 1106841,
    "name:xx": "Turyu-san"
  }
}
