{
  "geometry": {
    "type": "Point",
    "coordinates": [
      24.5833,
      49.75
    ]
  },
  "type": "Feature",
  "properties": {
    "hierarchy": [
      "tgn:1109985",
      "tgn:1000003",
      "tgn:7011664",
      "tgn:7006660",
      "tgn:7029392"
    ],
    "placetype": [
      "aat:300386831"
    ],
    "id": 1109985,
    "name:xx": "Holohory"
  }
}
