{
  "geometry": {
    "type": "Point",
    "coordinates": [
      79.249166,
      27.787957
    ]
  },
  "type": "Feature",
  "properties": {
    "hierarchy": [
      "tgn:7562874",
      "tgn:1000004",
      "tgn:7000198",
      "tgn:7016722",
      "tgn:7029392"
    ],
    "placetype": [
      "aat:300008347"
    ],
    "name:en": "Shāhpur",
    "id": 7562874
  }
}
