{
  "geometry": {
    "type": "Point",
    "coordinates": [
      -75.8333,
      44.2333
    ]
  },
  "type": "Feature",
  "properties": {
    "hierarchy": [
      "tgn:2408741",
      "tgn:1000001",
      "tgn:7012149",
      "tgn:1002518",
      "tgn:7007568",
      "tgn:7029392"
    ],
    "placetype": [
      "aat:300008706"
    ],
    "id": 2408741,
    "name:xx": "Hyde Creek"
  }
}
