{
  "geometry": {
    "type": "Point",
    "coordinates": [
      -107.8833,
      46.7333
    ]
  },
  "type": "Feature",
  "properties": {
    "hierarchy": [
      "tgn:2365811",
      "tgn:1000001",
      "tgn:7012149",
      "tgn:2001292",
      "tgn:7007524",
      "tgn:7029392"
    ],
    "placetype": [
      "aat:300008761"
    ],
    "id": 2365811,
    "name:xx": "Gremmert Coulee"
  }
}
