{
  "geometry": {
    "type": "Point",
    "coordinates": [
      77.93446,
      30.394682
    ]
  },
  "type": "Feature",
  "properties": {
    "hierarchy": [
      "tgn:7591700",
      "tgn:1000004",
      "tgn:7000198",
      "tgn:7031786",
      "tgn:7029392"
    ],
    "placetype": [
      "aat:300008347"
    ],
    "name:en": "Naugāwān",
    "id": 7591700
  }
}
