{
  "geometry": {
    "type": "Point",
    "coordinates": [
      -87.45,
      30.3833
    ]
  },
  "type": "Feature",
  "properties": {
    "hierarchy": [
      "tgn:2438937",
      "tgn:2000001",
      "tgn:7002659",
      "tgn:1000001",
      "tgn:7012149",
      "tgn:7029392"
    ],
    "placetype": [
      "aat:300132316"
    ],
    "id": 2438937,
    "name:xx": "Kinsey Bayou"
  }
}
