{
  "geometry": {
    "type": "Point",
    "coordinates": [
      -85.2333,
      34.3333
    ]
  },
  "type": "Feature",
  "properties": {
    "hierarchy": [
      "tgn:2485059",
      "tgn:1000001",
      "tgn:7012149",
      "tgn:2000348",
      "tgn:7007248",
      "tgn:7029392"
    ],
    "placetype": [
      "aat:300008798"
    ],
    "id": 2485059,
    "name:xx": "Lavender Mountain"
  }
}
