{
  "geometry": {
    "type": "Point",
    "coordinates": [
      -91.5667,
      38.9167
    ]
  },
  "type": "Feature",
  "properties": {
    "hierarchy": [
      "tgn:2184168",
      "tgn:1000001",
      "tgn:7012149",
      "tgn:1002687",
      "tgn:7007523",
      "tgn:7029392"
    ],
    "placetype": [
      "aat:300006191"
    ],
    "id": 2184168,
    "name:xx": "Bob Hoffman Lake"
  }
}
