{
  "geometry": {
    "type": "Point",
    "coordinates": [
      -87.9667,
      37.95
    ]
  },
  "type": "Feature",
  "properties": {
    "hierarchy": [
      "tgn:2764524",
      "tgn:1000001",
      "tgn:7012149",
      "tgn:2000552",
      "tgn:7007252",
      "tgn:7029392"
    ],
    "placetype": [
      "aat:300006075"
    ],
    "id": 2764524,
    "name:xx": "Whipple Ditch"
  }
}
