{
  "geometry": {
    "type": "Point",
    "coordinates": [
      81.75,
      21.766667
    ]
  },
  "type": "Feature",
  "properties": {
    "hierarchy": [
      "tgn:7570778",
      "tgn:1000004",
      "tgn:7031781",
      "tgn:7000198",
      "tgn:7029392"
    ],
    "placetype": [
      "aat:300008699"
    ],
    "name:en": "Hānp River",
    "id": 7570778
  }
}
