{
  "geometry": {
    "type": "Point",
    "coordinates": [
      -111.05,
      37.9667
    ]
  },
  "type": "Feature",
  "properties": {
    "hierarchy": [
      "tgn:2174751",
      "tgn:1000001",
      "tgn:2002109",
      "tgn:7012149",
      "tgn:7007827",
      "tgn:7029392"
    ],
    "placetype": [
      "aat:300266640"
    ],
    "id": 2174751,
    "name:xx": "Bitter Creek Divide"
  }
}
