{
  "geometry": {
    "type": "Point",
    "coordinates": [
      -84.3333,
      38.5167
    ]
  },
  "type": "Feature",
  "properties": {
    "hierarchy": [
      "tgn:2529691",
      "tgn:1000001",
      "tgn:7012149",
      "tgn:1002458",
      "tgn:7007255",
      "tgn:7029392"
    ],
    "placetype": [
      "aat:300008699"
    ],
    "id": 2529691,
    "name:xx": "Mud Lick Branch"
  }
}
