{
  "geometry": {
    "type": "Point",
    "coordinates": [
      -111.4833,
      41.8333
    ]
  },
  "type": "Feature",
  "properties": {
    "hierarchy": [
      "tgn:2384870",
      "tgn:1000001",
      "tgn:2002103",
      "tgn:7012149",
      "tgn:7007827",
      "tgn:7029392"
    ],
    "placetype": [
      "aat:300008761"
    ],
    "id": 2384870,
    "name:xx": "Hells Hollow"
  }
}
