{
  "type": "FeatureCollection",
  "features": [
    {
      "geometry": {
        "type": "Point",
        "coordinates": [
          -99.6,
          33.7333
        ]
      },
      "type": "Feature",
      "properties": {
        "hierarchy": [
          "tgn:2533590",
          "tgn:1000001",
          "tgn:7012149",
          "tgn:2002023",
          "tgn:7007826",
          "tgn:7029392"
        ],
        "placetype": [
          "aat:300008706"
        ],
        "id": 2533590,
        "name:xx": "Mustang Creek"
      }
    },
    {
      "geometry": {
        "type": "Point",
        "coordinates": [
          -98.8833,
          28.6833
        ]
      },
      "type": "Feature",
      "properties": {
        "hierarchy": [
          "tgn:2533591",
          "tgn:1000001",
          "tgn:7012149",
          "tgn:2001987",
          "tgn:7007826",
          "tgn:7029392"
        ],
        "placetype": [
          "aat:300008706"
        ],
        "id": 2533591,
        "name:xx": "Mustang Creek"
      }
    },
    {
      "geometry": {
        "type": "Point",
        "coordinates": [
          -100.35,
          28.9
        ]
      },
      "type": "Feature",
      "properties": {
        "hierarchy": [
          "tgn:2533592",
          "tgn:1000001",
          "tgn:7012149",
          "tgn:2002038",
          "tgn:7007826",
          "tgn:7029392"
        ],
        "placetype": [
          "aat:300008706"
        ],
        "id": 2533592,
        "name:xx": "Mustang Creek"
      }
    },
    {
      "geometry": {
        "type": "Point",
        "coordinates": [
          -96.4333,
          29.05
        ]
      },
      "type": "Feature",
      "properties": {
        "hierarchy": [
          "tgn:2533593",
          "tgn:1000001",
          "tgn:7012149",
          "tgn:1002510",
          "tgn:7007826",
          "tgn:7029392"
        ],
        "placetype": [
          "aat:300008706"
        ],
        "id": 2533593,
        "name:xx": "Mustang Creek"
      }
    },
    {
      "geometry": {
        "type": "Point",
        "coordinates": [
          -97.75,
          29.1333
        ]
      },
      "type": "Feature",
      "properties": {
        "hierarchy": [
          "tgn:2533594",
          "tgn:1000001",
          "tgn:7012149",
          "tgn:1002533",
          "tgn:7007826",
          "tgn:7029392"
        ],
        "placetype": [
          "aat:300008706"
        ],
        "id": 2533594,
        "name:xx": "Mustang Creek"
      }
    },
    {
      "geometry": {
        "type": "Point",
        "coordinates": [
          -97.5667,
          30.5833
        ]
      },
      "type": "Feature",
      "properties": {
        "hierarchy": [
          "tgn:2533595",
          "tgn:1000001",
          "tgn:7012149",
          "tgn:1003026",
          "tgn:7007826",
          "tgn:7029392"
        ],
        "placetype": [
          "aat:300008706"
        ],
        "id": 2533595,
        "name:xx": "Mustang Creek"
      }
    },
    {
      "geometry": {
        "type": "Point",
        "coordinates": [
          -96.8667,
          30.7
        ]
      },
      "type": "Feature",
      "properties": {
        "hierarchy": [
          "tgn:2533596",
          "tgn:1000001",
          "tgn:7012149",
          "tgn:1002670",
          "tgn:7007826",
          "tgn:7029392"
        ],
        "placetype": [
          "aat:300008706"
        ],
        "id": 2533596,
        "name:xx": "Mustang Creek"
      }
    },
    {
      "geometry": {
        "type": "Point",
        "coordinates": [
          -97.65,
          30.9667
        ]
      },
      "type": "Feature",
      "properties": {
        "hierarchy": [
          "tgn:2533597",
          "tgn:1000001",
          "tgn:1002174",
          "tgn:7012149",
          "tgn:7007826",
          "tgn:7029392"
        ],
        "placetype": [
          "aat:300008706"
        ],
        "id": 2533597,
        "name:xx": "Mustang Creek"
      }
    },
    {
      "geometry": {
        "type": "Point",
        "coordinates": [
          -98.5167,
          31.5167
        ]
      },
      "type": "Feature",
      "properties": {
        "hierarchy": [
          "tgn:2533598",
          "tgn:1000001",
          "tgn:7012149",
          "tgn:2002042",
          "tgn:7007826",
          "tgn:7029392"
        ],
        "placetype": [
          "aat:300008706"
        ],
        "id": 2533598,
        "name:xx": "Mustang Creek"
      }
    },
    {
      "geometry": {
        "type": "Point",
        "coordinates": [
          -96.8,
          31.65
        ]
      },
      "type": "Feature",
      "properties": {
        "hierarchy": [
          "tgn:2533599",
          "tgn:1000001",
          "tgn:7012149",
          "tgn:1002597",
          "tgn:7007826",
          "tgn:7029392"
        ],
        "placetype": [
          "aat:300008706"
        ],
        "id": 2533599,
        "name:xx": "Mustang Creek"
      }
    }
  ]
}
