{
  "geometry": {
    "type": "Point",
    "coordinates": [
      33.781671,
      26.677486
    ]
  },
  "type": "Feature",
  "properties": {
    "hierarchy": [
      "tgn:7529264",
      "tgn:7001242",
      "tgn:7001311",
      "tgn:7016833",
      "tgn:7029392"
    ],
    "placetype": [
      "aat:300008795"
    ],
    "name:en": "Umm Tāghir at Taḩtānī, Jabal",
    "id": 7529264
  }
}
