{
  "type": "FeatureCollection",
  "features": [
    {
      "geometry": {
        "type": "Point",
        "coordinates": [
          -108.8833,
          35.9
        ]
      },
      "type": "Feature",
      "properties": {
        "hierarchy": [
          "tgn:2067571",
          "tgn:1000001",
          "tgn:7012149",
          "tgn:7019676",
          "tgn:7007566",
          "tgn:7029392"
        ],
        "placetype": [
          "aat:300387210",
          "aat:300008697"
        ],
        "id": 2067571,
        "name:xx": "Squirrel Springs"
      }
    },
    {
      "geometry": {
        "type": "Point",
        "coordinates": [
          -108.35,
          35.8
        ]
      },
      "type": "Feature",
      "properties": {
        "hierarchy": [
          "tgn:2067572",
          "tgn:1000001",
          "tgn:7012149",
          "tgn:7019676",
          "tgn:7007566",
          "tgn:7029392"
        ],
        "placetype": [
          "aat:300008347",
          "aat:300387210"
        ],
        "id": 2067572,
        "name:xx": "Standing Rock"
      }
    },
    {
      "geometry": {
        "type": "Point",
        "coordinates": [
          -105.9667,
          35.1333
        ]
      },
      "type": "Feature",
      "properties": {
        "hierarchy": [
          "tgn:2067573",
          "tgn:1000001",
          "tgn:7012149",
          "tgn:2001454",
          "tgn:7007566",
          "tgn:7029392"
        ],
        "placetype": [
          "aat:300008347"
        ],
        "id": 2067573,
        "name:xx": "Stanley"
      }
    },
    {
      "geometry": {
        "type": "Point",
        "coordinates": [
          -103.6667,
          36.6
        ]
      },
      "type": "Feature",
      "properties": {
        "hierarchy": [
          "tgn:2067576",
          "tgn:1000001",
          "tgn:7012149",
          "tgn:2001459",
          "tgn:7007566",
          "tgn:7029392"
        ],
        "placetype": [
          "aat:300008347",
          "aat:300167671",
          "aat:300006036",
          "aat:300387016"
        ],
        "id": 2067576,
        "name:xx": "Staunton"
      }
    },
    {
      "geometry": {
        "type": "Point",
        "coordinates": [
          -103.2,
          36.1
        ]
      },
      "type": "Feature",
      "properties": {
        "hierarchy": [
          "tgn:2067577",
          "tgn:1000001",
          "tgn:7012149",
          "tgn:2001459",
          "tgn:7007566",
          "tgn:7029392"
        ],
        "placetype": [
          "aat:300008347"
        ],
        "id": 2067577,
        "name:xx": "Stead"
      }
    },
    {
      "geometry": {
        "type": "Point",
        "coordinates": [
          -108.9833,
          32.2167
        ]
      },
      "type": "Feature",
      "properties": {
        "hierarchy": [
          "tgn:2067578",
          "tgn:1000001",
          "tgn:7012149",
          "tgn:2001440",
          "tgn:7007566",
          "tgn:7029392"
        ],
        "placetype": [
          "aat:300387016"
        ],
        "id": 2067578,
        "name:xx": "Steins"
      }
    },
    {
      "geometry": {
        "type": "Point",
        "coordinates": [
          -106.6833,
          31.85
        ]
      },
      "type": "Feature",
      "properties": {
        "hierarchy": [
          "tgn:2067579",
          "tgn:1000001",
          "tgn:2001435",
          "tgn:7012149",
          "tgn:7007566",
          "tgn:7029392"
        ],
        "placetype": [
          "aat:300387016"
        ],
        "id": 2067579,
        "name:xx": "Strauss"
      }
    }
  ]
}
