{
  "geometry": {
    "type": "Point",
    "coordinates": [
      -93.4333,
      44.3167
    ]
  },
  "type": "Feature",
  "properties": {
    "hierarchy": [
      "tgn:2406717",
      "tgn:1000001",
      "tgn:7012149",
      "tgn:2001064",
      "tgn:7007521",
      "tgn:7029392"
    ],
    "placetype": [
      "aat:300008680"
    ],
    "id": 2406717,
    "name:xx": "Hunt Lake"
  }
}
