{
  "geometry": {
    "type": "Point",
    "coordinates": [
      107.9667,
      26.5667
    ]
  },
  "type": "Feature",
  "properties": {
    "hierarchy": [
      "tgn:1069493",
      "tgn:1000004",
      "tgn:7002080",
      "tgn:1000111",
      "tgn:7029392"
    ],
    "placetype": [
      "aat:300008347"
    ],
    "id": 1069493,
    "name:xx": "Kaili"
  }
}
