{
  "geometry": {
    "type": "Point",
    "coordinates": [
      -130.9833,
      55.4167
    ]
  },
  "type": "Feature",
  "properties": {
    "hierarchy": [
      "tgn:2752636",
      "tgn:7006450",
      "tgn:1000001",
      "tgn:2124076",
      "tgn:7012149",
      "tgn:7029392"
    ],
    "placetype": [
      "aat:300132316"
    ],
    "id": 2752636,
    "name:xx": "Wasp Cove"
  }
}
