{
  "geometry": {
    "type": "Point",
    "coordinates": [
      -82.9333,
      37.9667
    ]
  },
  "type": "Feature",
  "properties": {
    "hierarchy": [
      "tgn:2477414",
      "tgn:1000001",
      "tgn:7012149",
      "tgn:2000804",
      "tgn:7007255",
      "tgn:7029392"
    ],
    "placetype": [
      "aat:300008699"
    ],
    "id": 2477414,
    "name:xx": "Lyons Branch"
  }
}
