{
  "geometry": {
    "type": "Point",
    "coordinates": [
      144.9833,
      -37.8833
    ]
  },
  "type": "Feature",
  "properties": {
    "hierarchy": [
      "tgn:1096839",
      "tgn:7000490",
      "tgn:1000006",
      "tgn:7006238",
      "tgn:7029392"
    ],
    "placetype": [
      "aat:300008347"
    ],
    "id": 1096839,
    "name:xx": "Elwood"
  }
}
