{
  "geometry": {
    "type": "Point",
    "coordinates": [
      -87.0833,
      40.25
    ]
  },
  "type": "Feature",
  "properties": {
    "hierarchy": [
      "tgn:2749086",
      "tgn:1000001",
      "tgn:7012149",
      "tgn:7007252",
      "tgn:7029392"
    ],
    "placetype": [
      "aat:300006075"
    ],
    "id": 2749086,
    "name:xx": "Wallace Ditch"
  }
}
