{
  "geometry": {
    "type": "Point",
    "coordinates": [
      -118.1667,
      38.1667
    ]
  },
  "type": "Feature",
  "properties": {
    "hierarchy": [
      "tgn:2218376",
      "tgn:1000001",
      "tgn:2001417",
      "tgn:7012149",
      "tgn:7007526",
      "tgn:7029392"
    ],
    "placetype": [
      "aat:300008347"
    ],
    "id": 2218376,
    "name:xx": "Candelaria Junction"
  }
}
