{
  "geometry": {
    "type": "Point",
    "coordinates": [
      30.81617,
      31.155919
    ]
  },
  "type": "Feature",
  "properties": {
    "hierarchy": [
      "tgn:7533005",
      "tgn:7001242",
      "tgn:7016833",
      "tgn:1001335",
      "tgn:7029392"
    ],
    "placetype": [
      "aat:300006075"
    ],
    "name:en": "Muḩayţ Shābah al Gharbī",
    "id": 7533005
  }
}
