{
  "geometry": {
    "type": "Point",
    "coordinates": [
      -108.6667,
      38.8833
    ]
  },
  "type": "Feature",
  "properties": {
    "hierarchy": [
      "tgn:2438023",
      "tgn:1000001",
      "tgn:7012149",
      "tgn:2000230",
      "tgn:7007158",
      "tgn:7029392"
    ],
    "placetype": [
      "aat:300006191"
    ],
    "id": 2438023,
    "name:xx": "King Reservoir"
  }
}
