{
  "geometry": {
    "type": "Point",
    "coordinates": [
      -64.1167,
      -13.3667
    ]
  },
  "type": "Feature",
  "properties": {
    "hierarchy": [
      "tgn:1020340",
      "tgn:1000525",
      "tgn:1000046",
      "tgn:1000002",
      "tgn:7029392"
    ],
    "placetype": [
      "aat:300008347"
    ],
    "id": 1020340,
    "name:xx": "Magdalena"
  }
}
