{
  "geometry": {
    "type": "Point",
    "coordinates": [
      -81.7667,
      32.7667
    ]
  },
  "type": "Feature",
  "properties": {
    "hierarchy": [
      "tgn:2456281",
      "tgn:1000001",
      "tgn:7012149",
      "tgn:2000415",
      "tgn:7007248",
      "tgn:7029392"
    ],
    "placetype": [
      "aat:300008706"
    ],
    "id": 2456281,
    "name:xx": "Little Horse Creek"
  }
}
