{
  "geometry": {
    "type": "Point",
    "coordinates": [
      -80.5167,
      36.0333
    ]
  },
  "type": "Feature",
  "properties": {
    "hierarchy": [
      "tgn:2764495",
      "tgn:1000001",
      "tgn:7012149",
      "tgn:2001490",
      "tgn:7007709",
      "tgn:7029392"
    ],
    "placetype": [
      "aat:300006191"
    ],
    "id": 2764495,
    "name:xx": "Whip-O-Will Farms Number One Lake"
  }
}
