{
  "geometry": {
    "type": "Point",
    "coordinates": [
      -116.85,
      41.0833
    ]
  },
  "type": "Feature",
  "properties": {
    "hierarchy": [
      "tgn:2626044",
      "tgn:1000001",
      "tgn:2001411",
      "tgn:7012149",
      "tgn:7007526",
      "tgn:7029392"
    ],
    "placetype": [
      "aat:300008697"
    ],
    "id": 2626044,
    "name:xx": "Rocky Canyon Spring"
  }
}
