{
  "geometry": {
    "type": "Point",
    "coordinates": [
      13.5833,
      50.5667
    ]
  },
  "type": "Feature",
  "properties": {
    "hierarchy": [
      "tgn:1027155",
      "tgn:7593920",
      "tgn:1000003",
      "tgn:1001780",
      "tgn:7029392"
    ],
    "placetype": [
      "aat:300008347"
    ],
    "id": 1027155,
    "name:xx": "Dolní Jiřetin"
  }
}
