{
  "geometry": {
    "type": "Point",
    "coordinates": [
      -76.6167,
      -6.4333
    ]
  },
  "type": "Feature",
  "properties": {
    "hierarchy": [
      "tgn:1024782",
      "tgn:1000749",
      "tgn:1000002",
      "tgn:1000056",
      "tgn:7029392"
    ],
    "placetype": [
      "aat:300008347"
    ],
    "id": 1024782,
    "name:xx": "Tabalosos"
  }
}
