{
  "type": "FeatureCollection",
  "features": [
    {
      "geometry": {
        "type": "Point",
        "coordinates": [
          -84.3833,
          44.5167
        ]
      },
      "type": "Feature",
      "properties": {
        "hierarchy": [
          "tgn:2761100",
          "tgn:1000001",
          "tgn:2000954",
          "tgn:7012149",
          "tgn:7007520",
          "tgn:7029392"
        ],
        "placetype": [
          "aat:300008680"
        ],
        "id": 2761100,
        "name:xx": "West Lake"
      }
    },
    {
      "geometry": {
        "type": "Point",
        "coordinates": [
          -84.7833,
          45.05
        ]
      },
      "type": "Feature",
      "properties": {
        "hierarchy": [
          "tgn:2761101",
          "tgn:1000001",
          "tgn:7012149",
          "tgn:2000989",
          "tgn:7007520",
          "tgn:7029392"
        ],
        "placetype": [
          "aat:300008680"
        ],
        "id": 2761101,
        "name:xx": "West Lake"
      }
    },
    {
      "geometry": {
        "type": "Point",
        "coordinates": [
          -86.5,
          46
        ]
      },
      "type": "Feature",
      "properties": {
        "hierarchy": [
          "tgn:2761102",
          "tgn:1000001",
          "tgn:2000955",
          "tgn:7012149",
          "tgn:7007520",
          "tgn:7029392"
        ],
        "placetype": [
          "aat:300008680"
        ],
        "id": 2761102,
        "name:xx": "West Lake"
      }
    },
    {
      "geometry": {
        "type": "Point",
        "coordinates": [
          -84.9833,
          46.3167
        ]
      },
      "type": "Feature",
      "properties": {
        "hierarchy": [
          "tgn:2761103",
          "tgn:1000001",
          "tgn:2000952",
          "tgn:7012149",
          "tgn:7007520",
          "tgn:7029392"
        ],
        "placetype": [
          "aat:300008680"
        ],
        "id": 2761103,
        "name:xx": "West Lake"
      }
    },
    {
      "geometry": {
        "type": "Point",
        "coordinates": [
          -94.6667,
          45.3
        ]
      },
      "type": "Feature",
      "properties": {
        "hierarchy": [
          "tgn:2761104",
          "tgn:1000001",
          "tgn:7012149",
          "tgn:2001045",
          "tgn:7007521",
          "tgn:7029392"
        ],
        "placetype": [
          "aat:300008680"
        ],
        "id": 2761104,
        "name:xx": "West Lake"
      }
    },
    {
      "geometry": {
        "type": "Point",
        "coordinates": [
          -93.9167,
          45.3167
        ]
      },
      "type": "Feature",
      "properties": {
        "hierarchy": [
          "tgn:2761105",
          "tgn:1000001",
          "tgn:7012149",
          "tgn:2001084",
          "tgn:7007521",
          "tgn:7029392"
        ],
        "placetype": [
          "aat:300008680"
        ],
        "id": 2761105,
        "name:xx": "West Lake"
      }
    },
    {
      "geometry": {
        "type": "Point",
        "coordinates": [
          -93.4,
          45.7
        ]
      },
      "type": "Feature",
      "properties": {
        "hierarchy": [
          "tgn:2761106",
          "tgn:1000001",
          "tgn:7012149",
          "tgn:2001028",
          "tgn:7007521",
          "tgn:7029392"
        ],
        "placetype": [
          "aat:300008680"
        ],
        "id": 2761106,
        "name:xx": "West Lake"
      }
    },
    {
      "geometry": {
        "type": "Point",
        "coordinates": [
          -96.0667,
          46.8
        ]
      },
      "type": "Feature",
      "properties": {
        "hierarchy": [
          "tgn:2761107",
          "tgn:2001001",
          "tgn:1000001",
          "tgn:7012149",
          "tgn:7007521",
          "tgn:7029392"
        ],
        "placetype": [
          "aat:300008680"
        ],
        "id": 2761107,
        "name:xx": "West Lake"
      }
    },
    {
      "geometry": {
        "type": "Point",
        "coordinates": [
          -93.6333,
          46.7333
        ]
      },
      "type": "Feature",
      "properties": {
        "hierarchy": [
          "tgn:2761108",
          "tgn:2000999",
          "tgn:1000001",
          "tgn:7012149",
          "tgn:7007521",
          "tgn:7029392"
        ],
        "placetype": [
          "aat:300008680"
        ],
        "id": 2761108,
        "name:xx": "West Lake"
      }
    }
  ]
}
