{
  "type": "FeatureCollection",
  "features": [
    {
      "geometry": {
        "type": "Point",
        "coordinates": [
          -94.1833,
          36
        ]
      },
      "type": "Feature",
      "properties": {
        "hierarchy": [
          "tgn:2125860",
          "tgn:1000001",
          "tgn:7016172",
          "tgn:7012149",
          "tgn:2000176",
          "tgn:7029392"
        ],
        "placetype": [
          "aat:300006191"
        ],
        "id": 2125860,
        "name:xx": "Adams Lake"
      }
    },
    {
      "geometry": {
        "type": "Point",
        "coordinates": [
          -92.3833,
          35
        ]
      },
      "type": "Feature",
      "properties": {
        "hierarchy": [
          "tgn:2125861",
          "tgn:1000001",
          "tgn:7016172",
          "tgn:7012149",
          "tgn:2000127",
          "tgn:7029392"
        ],
        "placetype": [
          "aat:300008680",
          "aat:300387018"
        ],
        "id": 2125861,
        "name:xx": "Adams Lake"
      }
    },
    {
      "geometry": {
        "type": "Point",
        "coordinates": [
          -122.95,
          41.1
        ]
      },
      "type": "Feature",
      "properties": {
        "hierarchy": [
          "tgn:2125862",
          "tgn:1000001",
          "tgn:7012149",
          "tgn:7007157",
          "tgn:2000191",
          "tgn:7029392"
        ],
        "placetype": [
          "aat:300008680"
        ],
        "id": 2125862,
        "name:xx": "Adams Lake"
      }
    },
    {
      "geometry": {
        "type": "Point",
        "coordinates": [
          -107.4,
          39.7333
        ]
      },
      "type": "Feature",
      "properties": {
        "hierarchy": [
          "tgn:2125863",
          "tgn:1000001",
          "tgn:7012149",
          "tgn:2000214",
          "tgn:7007158",
          "tgn:7029392"
        ],
        "placetype": [
          "aat:300008680"
        ],
        "id": 2125863,
        "name:xx": "Adams Lake"
      }
    },
    {
      "geometry": {
        "type": "Point",
        "coordinates": [
          -105.7167,
          40.1667
        ]
      },
      "type": "Feature",
      "properties": {
        "hierarchy": [
          "tgn:2125864",
          "tgn:1000001",
          "tgn:7012149",
          "tgn:2000216",
          "tgn:7007158",
          "tgn:7029392"
        ],
        "placetype": [
          "aat:300008680"
        ],
        "id": 2125864,
        "name:xx": "Adams Lake"
      }
    },
    {
      "geometry": {
        "type": "Point",
        "coordinates": [
          -105.85,
          37.4
        ]
      },
      "type": "Feature",
      "properties": {
        "hierarchy": [
          "tgn:2125865",
          "tgn:2000193",
          "tgn:1000001",
          "tgn:7012149",
          "tgn:7007158",
          "tgn:7029392"
        ],
        "placetype": [
          "aat:300006191"
        ],
        "id": 2125865,
        "name:xx": "Adams Lake"
      }
    },
    {
      "geometry": {
        "type": "Point",
        "coordinates": [
          -81.55,
          28.7833
        ]
      },
      "type": "Feature",
      "properties": {
        "hierarchy": [
          "tgn:2125866",
          "tgn:1000001",
          "tgn:7012149",
          "tgn:1002567",
          "tgn:7007240",
          "tgn:7029392"
        ],
        "placetype": [
          "aat:300008680"
        ],
        "id": 2125866,
        "name:xx": "Adams Lake"
      }
    },
    {
      "geometry": {
        "type": "Point",
        "coordinates": [
          -81.45,
          29.0667
        ]
      },
      "type": "Feature",
      "properties": {
        "hierarchy": [
          "tgn:2125867",
          "tgn:1000001",
          "tgn:7012149",
          "tgn:1002977",
          "tgn:7007240",
          "tgn:7029392"
        ],
        "placetype": [
          "aat:300008680"
        ],
        "id": 2125867,
        "name:xx": "Adams Lake"
      }
    },
    {
      "geometry": {
        "type": "Point",
        "coordinates": [
          -83.05,
          29.7167
        ]
      },
      "type": "Feature",
      "properties": {
        "hierarchy": [
          "tgn:2125868",
          "tgn:1000001",
          "tgn:2000263",
          "tgn:7012149",
          "tgn:7007240",
          "tgn:7029392"
        ],
        "placetype": [
          "aat:300008680"
        ],
        "id": 2125868,
        "name:xx": "Adams Lake"
      }
    },
    {
      "geometry": {
        "type": "Point",
        "coordinates": [
          -83.0333,
          29.9667
        ]
      },
      "type": "Feature",
      "properties": {
        "hierarchy": [
          "tgn:2125869",
          "tgn:1000001",
          "tgn:2000275",
          "tgn:7012149",
          "tgn:7007240",
          "tgn:7029392"
        ],
        "placetype": [
          "aat:300008680"
        ],
        "id": 2125869,
        "name:xx": "Adams Lake"
      }
    }
  ]
}
