{
  "geometry": {
    "type": "Point",
    "coordinates": [
      -85.3833,
      30.0333
    ]
  },
  "type": "Feature",
  "properties": {
    "hierarchy": [
      "tgn:2401433",
      "tgn:2000258",
      "tgn:1000001",
      "tgn:7012149",
      "tgn:7007240",
      "tgn:7029392"
    ],
    "placetype": [
      "aat:300132316"
    ],
    "id": 2401433,
    "name:xx": "Horseshoe Bayou"
  }
}
