{
  "geometry": {
    "type": "Point",
    "coordinates": [
      -109.1333,
      33.6167
    ]
  },
  "type": "Feature",
  "properties": {
    "hierarchy": [
      "tgn:2333739",
      "tgn:1000001",
      "tgn:7006451",
      "tgn:2000095",
      "tgn:7012149",
      "tgn:7029392"
    ],
    "placetype": [
      "aat:300008798"
    ],
    "id": 2333739,
    "name:xx": "Foote Creek Mesa"
  }
}
