{
  "type": "FeatureCollection",
  "features": [
    {
      "geometry": {
        "type": "Point",
        "coordinates": [
          30.853611,
          30.933056
        ]
      },
      "type": "Feature",
      "properties": {
        "hierarchy": [
          "tgn:7531330",
          "tgn:7001242",
          "tgn:7016833",
          "tgn:7001312",
          "tgn:7029392"
        ],
        "placetype": [
          "aat:300006075"
        ],
        "name:en": "Tur'at Mashāl",
        "id": 7531330
      }
    },
    {
      "geometry": {
        "type": "Point",
        "coordinates": [
          30.809796,
          30.899799
        ]
      },
      "type": "Feature",
      "properties": {
        "hierarchy": [
          "tgn:7531331",
          "tgn:7001242",
          "tgn:7016833",
          "tgn:7001312",
          "tgn:7029392"
        ],
        "placetype": [
          "aat:300006075"
        ],
        "name:en": "Tur'at Nashart",
        "id": 7531331
      }
    },
    {
      "geometry": {
        "type": "Point",
        "coordinates": [
          30.814722,
          30.958056
        ]
      },
      "type": "Feature",
      "properties": {
        "hierarchy": [
          "tgn:7531332",
          "tgn:7001242",
          "tgn:7016833",
          "tgn:7001312",
          "tgn:7029392"
        ],
        "placetype": [
          "aat:300006075"
        ],
        "name:en": "Tur'at al Basyūnī",
        "id": 7531332
      }
    },
    {
      "geometry": {
        "type": "Point",
        "coordinates": [
          30.809574,
          30.900011
        ]
      },
      "type": "Feature",
      "properties": {
        "hierarchy": [
          "tgn:7531333",
          "tgn:7001242",
          "tgn:7016833",
          "tgn:7001312",
          "tgn:7029392"
        ],
        "placetype": [
          "aat:300006075"
        ],
        "name:en": "Baḩr al Quţnī",
        "id": 7531333
      }
    },
    {
      "geometry": {
        "type": "Point",
        "coordinates": [
          30.913429,
          30.971469
        ]
      },
      "type": "Feature",
      "properties": {
        "hierarchy": [
          "tgn:7531334",
          "tgn:7001242",
          "tgn:7016833",
          "tgn:7001312",
          "tgn:7029392"
        ],
        "placetype": [
          "aat:300006075"
        ],
        "name:en": "Tur'at Qutūr",
        "id": 7531334
      }
    },
    {
      "geometry": {
        "type": "Point",
        "coordinates": [
          30.920829,
          30.935567
        ]
      },
      "type": "Feature",
      "properties": {
        "hierarchy": [
          "tgn:7531335",
          "tgn:7001242",
          "tgn:7016833",
          "tgn:7001312",
          "tgn:7029392"
        ],
        "placetype": [
          "aat:300006075"
        ],
        "name:en": "Tur'at Damāţ",
        "id": 7531335
      }
    },
    {
      "geometry": {
        "type": "Point",
        "coordinates": [
          31.027376,
          30.729119
        ]
      },
      "type": "Feature",
      "properties": {
        "hierarchy": [
          "tgn:7531336",
          "tgn:7001242",
          "tgn:7016833",
          "tgn:7001312",
          "tgn:7029392"
        ],
        "placetype": [
          "aat:300006075"
        ],
        "name:en": "Tur'at al Qāşid",
        "id": 7531336
      }
    },
    {
      "geometry": {
        "type": "Point",
        "coordinates": [
          30.971908,
          30.791935
        ]
      },
      "type": "Feature",
      "properties": {
        "hierarchy": [
          "tgn:7531337",
          "tgn:7001242",
          "tgn:7016833",
          "tgn:7029392"
        ],
        "placetype": [
          "aat:300006075"
        ],
        "name:en": "Tur'at Umm 'Abdallah",
        "id": 7531337
      }
    },
    {
      "geometry": {
        "type": "Point",
        "coordinates": [
          30.937472,
          30.780054
        ]
      },
      "type": "Feature",
      "properties": {
        "hierarchy": [
          "tgn:7531338",
          "tgn:7001242",
          "tgn:7016833",
          "tgn:7001312",
          "tgn:7029392"
        ],
        "placetype": [
          "aat:300008347"
        ],
        "name:en": "'Izbat al 'Awāyisah",
        "id": 7531338
      }
    },
    {
      "geometry": {
        "type": "Point",
        "coordinates": [
          30.890566,
          30.674783
        ]
      },
      "type": "Feature",
      "properties": {
        "hierarchy": [
          "tgn:7531339",
          "tgn:7001242",
          "tgn:7016833",
          "tgn:7001312",
          "tgn:7029392"
        ],
        "placetype": [
          "aat:300008347"
        ],
        "name:en": "'Izbat al Aqra'",
        "id": 7531339
      }
    }
  ]
}
