{
  "geometry": {
    "type": "Point",
    "coordinates": [
      -105.1833,
      42.4833
    ]
  },
  "type": "Feature",
  "properties": {
    "hierarchy": [
      "tgn:2764819",
      "tgn:1000001",
      "tgn:7012149",
      "tgn:2002380",
      "tgn:7007923",
      "tgn:7029392"
    ],
    "placetype": [
      "aat:300008761"
    ],
    "id": 2764819,
    "name:xx": "Whiskey Gulch"
  }
}
