{
  "geometry": {
    "type": "Point",
    "coordinates": [
      -108.7667,
      35.5833
    ]
  },
  "type": "Feature",
  "properties": {
    "hierarchy": [
      "tgn:2237573",
      "tgn:1000001",
      "tgn:7012149",
      "tgn:7019676",
      "tgn:7007566",
      "tgn:7029392"
    ],
    "placetype": [
      "aat:300008697"
    ],
    "id": 2237573,
    "name:xx": "China Springs"
  }
}
