{
  "geometry": {
    "type": "Point",
    "coordinates": [
      -106.2333,
      38.8167
    ]
  },
  "type": "Feature",
  "properties": {
    "hierarchy": [
      "tgn:2661073",
      "tgn:1000001",
      "tgn:2000199",
      "tgn:7012149",
      "tgn:7007158",
      "tgn:7029392"
    ],
    "placetype": [
      "aat:300008761"
    ],
    "id": 2661073,
    "name:xx": "Short Gulch"
  }
}
