{
  "geometry": {
    "type": "Point",
    "coordinates": [
      -90.1333,
      39.6167
    ]
  },
  "type": "Feature",
  "properties": {
    "hierarchy": [
      "tgn:2451143",
      "tgn:1000001",
      "tgn:7012149",
      "tgn:7007251",
      "tgn:7029392"
    ],
    "placetype": [
      "aat:300008706"
    ],
    "id": 2451143,
    "name:xx": "Little Apple Creek"
  }
}
