{
  "geometry": {
    "type": "Point",
    "coordinates": [
      1.45,
      14.2167
    ]
  },
  "type": "Feature",
  "properties": {
    "hierarchy": [
      "tgn:1091813",
      "tgn:7001242",
      "tgn:7032820",
      "tgn:1000181",
      "tgn:7029392"
    ],
    "placetype": [
      "aat:300008347"
    ],
    "id": 1091813,
    "name:xx": "Tillabéri"
  }
}
