{
  "type": "FeatureCollection",
  "features": [
    {
      "geometry": {
        "type": "Point",
        "coordinates": [
          -100.4,
          37.9167
        ]
      },
      "type": "Feature",
      "properties": {
        "hierarchy": [
          "tgn:1132610",
          "tgn:1000001",
          "tgn:7012149",
          "tgn:7007254",
          "tgn:7029392"
        ],
        "placetype": [
          "aat:300008706"
        ],
        "id": 1132610,
        "name:xx": "Buckner Creek"
      }
    },
    {
      "geometry": {
        "type": "Point",
        "coordinates": [
          -97.2333,
          29.8833
        ]
      },
      "type": "Feature",
      "properties": {
        "hierarchy": [
          "tgn:1132611",
          "tgn:1000001",
          "tgn:7012149",
          "tgn:7007826",
          "tgn:7029392"
        ],
        "placetype": [
          "aat:300008706"
        ],
        "id": 1132611,
        "name:xx": "Buckners Creek"
      }
    },
    {
      "geometry": {
        "type": "Point",
        "coordinates": [
          -84.5333,
          41.3167
        ]
      },
      "type": "Feature",
      "properties": {
        "hierarchy": [
          "tgn:1132612",
          "tgn:1000001",
          "tgn:1002326",
          "tgn:7012149",
          "tgn:7007706",
          "tgn:7029392"
        ],
        "placetype": [
          "aat:300008706"
        ],
        "id": 1132612,
        "name:xx": "Buckskin Creek"
      }
    },
    {
      "geometry": {
        "type": "Point",
        "coordinates": [
          -89.5667,
          42.0167
        ]
      },
      "type": "Feature",
      "properties": {
        "hierarchy": [
          "tgn:1132613",
          "tgn:1000001",
          "tgn:7012149",
          "tgn:7007251",
          "tgn:7029392"
        ],
        "placetype": [
          "aat:300008706"
        ],
        "id": 1132613,
        "name:xx": "Buffalo Creek"
      }
    },
    {
      "geometry": {
        "type": "Point",
        "coordinates": [
          -93.7667,
          43.2667
        ]
      },
      "type": "Feature",
      "properties": {
        "hierarchy": [
          "tgn:1132614",
          "tgn:1000001",
          "tgn:7012149",
          "tgn:7007253",
          "tgn:7029392"
        ],
        "placetype": [
          "aat:300008706"
        ],
        "id": 1132614,
        "name:xx": "Buffalo Creek"
      }
    },
    {
      "geometry": {
        "type": "Point",
        "coordinates": [
          -98.1333,
          39.6667
        ]
      },
      "type": "Feature",
      "properties": {
        "hierarchy": [
          "tgn:1132615",
          "tgn:1000001",
          "tgn:7012149",
          "tgn:7007254",
          "tgn:7029392"
        ],
        "placetype": [
          "aat:300008706"
        ],
        "id": 1132615,
        "name:xx": "Buffalo Creek"
      }
    },
    {
      "geometry": {
        "type": "Point",
        "coordinates": [
          -83.9333,
          36.7333
        ]
      },
      "type": "Feature",
      "properties": {
        "hierarchy": [
          "tgn:1132616",
          "tgn:1000001",
          "tgn:7012149",
          "tgn:7007255",
          "tgn:7029392"
        ],
        "placetype": [
          "aat:300008706"
        ],
        "id": 1132616,
        "name:xx": "Buffalo Creek"
      }
    },
    {
      "geometry": {
        "type": "Point",
        "coordinates": [
          -94.9833,
          44.9167
        ]
      },
      "type": "Feature",
      "properties": {
        "hierarchy": [
          "tgn:1132617",
          "tgn:1000001",
          "tgn:7012149",
          "tgn:7007521",
          "tgn:7029392"
        ],
        "placetype": [
          "aat:300008706"
        ],
        "id": 1132617,
        "name:xx": "Buffalo Creek"
      }
    },
    {
      "geometry": {
        "type": "Point",
        "coordinates": [
          -78.4667,
          42.5833
        ]
      },
      "type": "Feature",
      "properties": {
        "hierarchy": [
          "tgn:1132618",
          "tgn:1000001",
          "tgn:7012149",
          "tgn:7007568",
          "tgn:7029392"
        ],
        "placetype": [
          "aat:300008706"
        ],
        "id": 1132618,
        "name:xx": "Buffalo Creek"
      }
    },
    {
      "geometry": {
        "type": "Point",
        "coordinates": [
          -95.1167,
          34.7667
        ]
      },
      "type": "Feature",
      "properties": {
        "hierarchy": [
          "tgn:1132619",
          "tgn:1000001",
          "tgn:7012149",
          "tgn:7007707",
          "tgn:7029392"
        ],
        "placetype": [
          "aat:300008706"
        ],
        "id": 1132619,
        "name:xx": "Buffalo Creek"
      }
    }
  ]
}
