{
  "geometry": {
    "type": "Point",
    "coordinates": [
      -96.45,
      45.55
    ]
  },
  "type": "Feature",
  "properties": {
    "hierarchy": [
      "tgn:2762339",
      "tgn:2001004",
      "tgn:1000001",
      "tgn:7012149",
      "tgn:7007521",
      "tgn:7029392"
    ],
    "placetype": [
      "aat:300008680"
    ],
    "id": 2762339,
    "name:xx": "West Toqua Lake"
  }
}
