{
  "geometry": {
    "type": "Point",
    "coordinates": [
      -122.85,
      47.55
    ]
  },
  "type": "Feature",
  "properties": {
    "hierarchy": [
      "tgn:2166263",
      "tgn:1000001",
      "tgn:7012149",
      "tgn:1002552",
      "tgn:7007920",
      "tgn:7029392"
    ],
    "placetype": [
      "aat:300008706"
    ],
    "id": 2166263,
    "name:xx": "Big Beef Creek"
  }
}
