{
  "geometry": {
    "type": "Point",
    "coordinates": [
      -77.0333,
      41.9833
    ]
  },
  "type": "Feature",
  "properties": {
    "hierarchy": [
      "tgn:2128592",
      "tgn:1000001",
      "tgn:7012149",
      "tgn:1002945",
      "tgn:7007710",
      "tgn:7029392"
    ],
    "placetype": [
      "aat:300008699"
    ],
    "id": 2128592,
    "name:xx": "Alder Run"
  }
}
