{
  "geometry": {
    "type": "Point",
    "coordinates": [
      -76.6667,
      37.7667
    ]
  },
  "type": "Feature",
  "properties": {
    "hierarchy": [
      "tgn:2501817",
      "tgn:1000001",
      "tgn:7012149",
      "tgn:7007919",
      "tgn:7029392"
    ],
    "placetype": [
      "aat:300132316"
    ],
    "id": 2501817,
    "name:xx": "McKans Bay"
  }
}
