{
  "geometry": {
    "type": "Point",
    "coordinates": [
      -72.75,
      40.7667
    ]
  },
  "type": "Feature",
  "properties": {
    "hierarchy": [
      "tgn:2605095",
      "tgn:1000001",
      "tgn:7012149",
      "tgn:1002924",
      "tgn:7007568",
      "tgn:7029392"
    ],
    "placetype": [
      "aat:300008850"
    ],
    "id": 2605095,
    "name:xx": "Radio Point"
  }
}
