{
  "geometry": {
    "type": "Point",
    "coordinates": [
      -85.5833,
      40.4167
    ]
  },
  "type": "Feature",
  "properties": {
    "hierarchy": [
      "tgn:2343470",
      "tgn:1000001",
      "tgn:7012149",
      "tgn:1002416",
      "tgn:7007252",
      "tgn:7029392"
    ],
    "placetype": [
      "aat:300006075"
    ],
    "id": 2343470,
    "name:xx": "Galatia Ditch"
  }
}
