{
  "geometry": {
    "type": "Point",
    "coordinates": [
      -112.7667,
      41.85
    ]
  },
  "type": "Feature",
  "properties": {
    "hierarchy": [
      "tgn:2424891",
      "tgn:1000001",
      "tgn:2002102",
      "tgn:7012149",
      "tgn:7007827",
      "tgn:7029392"
    ],
    "placetype": [
      "aat:300008798"
    ],
    "id": 2424891,
    "name:xx": "Johnson Hill"
  }
}
