{
  "geometry": {
    "type": "Point",
    "coordinates": [
      2.8833,
      48.9833
    ]
  },
  "type": "Feature",
  "properties": {
    "hierarchy": [
      "tgn:1032831",
      "tgn:1000003",
      "tgn:7002883",
      "tgn:1000070",
      "tgn:7029392"
    ],
    "placetype": [
      "aat:300008347"
    ],
    "id": 1032831,
    "name:xx": "Crégy-lès-Meaux"
  }
}
