{
  "geometry": {
    "type": "Point",
    "coordinates": [
      -110.15,
      45.2667
    ]
  },
  "type": "Feature",
  "properties": {
    "hierarchy": [
      "tgn:2741382",
      "tgn:1000001",
      "tgn:7012149",
      "tgn:7007524",
      "tgn:7029392"
    ],
    "placetype": [
      "aat:300008706"
    ],
    "id": 2741382,
    "name:xx": "Upsidedown Creek"
  }
}
