{
  "geometry": {
    "type": "Point",
    "coordinates": [
      -84.4833,
      33.0333
    ]
  },
  "type": "Feature",
  "properties": {
    "hierarchy": [
      "tgn:2694941",
      "tgn:1000001",
      "tgn:7012149",
      "tgn:2000405",
      "tgn:7007248",
      "tgn:7029392"
    ],
    "placetype": [
      "aat:300008699"
    ],
    "id": 2694941,
    "name:xx": "Still Branch"
  }
}
