{
  "geometry": {
    "type": "Point",
    "coordinates": [
      -85.6667,
      43.65
    ]
  },
  "type": "Feature",
  "properties": {
    "hierarchy": [
      "tgn:2053771",
      "tgn:1000001",
      "tgn:7012149",
      "tgn:2000983",
      "tgn:7007520",
      "tgn:7029392"
    ],
    "placetype": [
      "aat:300008347"
    ],
    "id": 2053771,
    "name:xx": "Woodville"
  }
}
