{
  "geometry": {
    "type": "Point",
    "coordinates": [
      -81.6667,
      29.3333
    ]
  },
  "type": "Feature",
  "properties": {
    "hierarchy": [
      "tgn:2638777",
      "tgn:1000001",
      "tgn:7012149",
      "tgn:2000282",
      "tgn:7007240",
      "tgn:7029392"
    ],
    "placetype": [
      "aat:300132316"
    ],
    "id": 2638777,
    "name:xx": "Salt Cove"
  }
}
