{
  "geometry": {
    "type": "Point",
    "coordinates": [
      -75.25,
      43.8167
    ]
  },
  "type": "Feature",
  "properties": {
    "hierarchy": [
      "tgn:2372173",
      "tgn:1000001",
      "tgn:7012149",
      "tgn:1002593",
      "tgn:7007568",
      "tgn:7029392"
    ],
    "placetype": [
      "aat:300008680"
    ],
    "id": 2372173,
    "name:xx": "Halfmoon Lake"
  }
}
