{
  "geometry": {
    "type": "Point",
    "coordinates": [
      89.5167,
      23.5333
    ]
  },
  "type": "Feature",
  "properties": {
    "hierarchy": [
      "tgn:1135769",
      "tgn:1000004",
      "tgn:1000105",
      "tgn:7029392"
    ],
    "placetype": [
      "aat:300387055"
    ],
    "id": 1135769,
    "name:xx": "Garai"
  }
}
