{
  "geometry": {
    "type": "Point",
    "coordinates": [
      -121.4167,
      45.0667
    ]
  },
  "type": "Feature",
  "properties": {
    "hierarchy": [
      "tgn:2357465",
      "tgn:1000001",
      "tgn:7012149",
      "tgn:1002990",
      "tgn:7007708",
      "tgn:7029392"
    ],
    "placetype": [
      "aat:300008697"
    ],
    "id": 2357465,
    "name:xx": "Government Spring"
  }
}
