{
  "geometry": {
    "type": "Point",
    "coordinates": [
      10.1667,
      47.1667
    ]
  },
  "type": "Feature",
  "properties": {
    "hierarchy": [
      "tgn:1026252",
      "tgn:7018001",
      "tgn:1000003",
      "tgn:1000062",
      "tgn:7029392"
    ],
    "placetype": [
      "aat:300008347"
    ],
    "id": 1026252,
    "name:xx": "Zürs"
  }
}
