{
  "geometry": {
    "type": "Point",
    "coordinates": [
      79.2437,
      26.32294
    ]
  },
  "type": "Feature",
  "properties": {
    "hierarchy": [
      "tgn:7563060",
      "tgn:1000004",
      "tgn:7000198",
      "tgn:7016722",
      "tgn:7029392"
    ],
    "placetype": [
      "aat:300008347"
    ],
    "name:en": "Delpura",
    "id": 7563060
  }
}
