{
  "type": "FeatureCollection",
  "features": [
    {
      "geometry": {
        "type": "Point",
        "coordinates": [
          12.466667,
          51.533333
        ]
      },
      "type": "Feature",
      "properties": {
        "hierarchy": [
          "tgn:7087420",
          "tgn:1000003",
          "tgn:7003685",
          "tgn:7000084",
          "tgn:7029392"
        ],
        "placetype": [
          "aat:300008347"
        ],
        "id": 7087420,
        "name:xx": "Brinnis-Wannewitz"
      }
    },
    {
      "geometry": {
        "type": "Point",
        "coordinates": [
          11.316667,
          52.383333
        ]
      },
      "type": "Feature",
      "properties": {
        "hierarchy": [
          "tgn:7087421",
          "tgn:1000003",
          "tgn:7003687",
          "tgn:7000084",
          "tgn:7029392"
        ],
        "placetype": [
          "aat:300008347"
        ],
        "id": 7087421,
        "name:xx": "Wannewehmühle"
      }
    },
    {
      "geometry": {
        "type": "Point",
        "coordinates": [
          11.316667,
          52.383333
        ]
      },
      "type": "Feature",
      "properties": {
        "hierarchy": [
          "tgn:7087422",
          "tgn:1000003",
          "tgn:7003687",
          "tgn:7000084",
          "tgn:7029392"
        ],
        "placetype": [
          "aat:300008699"
        ],
        "id": 7087422,
        "name:xx": "Wanneweh"
      }
    },
    {
      "geometry": {
        "type": "Point",
        "coordinates": [
          8.383333,
          48.3
        ]
      },
      "type": "Feature",
      "properties": {
        "hierarchy": [
          "tgn:7087426",
          "tgn:7003692",
          "tgn:1000003",
          "tgn:7000084",
          "tgn:7029392"
        ],
        "placetype": [
          "aat:300008347"
        ],
        "id": 7087426,
        "name:xx": "Waldenbrunn"
      }
    },
    {
      "geometry": {
        "type": "Point",
        "coordinates": [
          9.316667,
          48.75
        ]
      },
      "type": "Feature",
      "properties": {
        "hierarchy": [
          "tgn:7087427",
          "tgn:7003692",
          "tgn:1000003",
          "tgn:7000084",
          "tgn:7029392"
        ],
        "placetype": [
          "aat:300008347"
        ],
        "id": 7087427,
        "name:xx": "Wäldenbronn"
      }
    },
    {
      "geometry": {
        "type": "Point",
        "coordinates": [
          9.8,
          53.616667
        ]
      },
      "type": "Feature",
      "properties": {
        "hierarchy": [
          "tgn:7087428",
          "tgn:1000003",
          "tgn:7003688",
          "tgn:7000084",
          "tgn:7029392"
        ],
        "placetype": [
          "aat:300008347"
        ],
        "id": 7087428,
        "name:xx": "Waldenau-Datum"
      }
    },
    {
      "geometry": {
        "type": "Point",
        "coordinates": [
          9.8,
          53.616667
        ]
      },
      "type": "Feature",
      "properties": {
        "hierarchy": [
          "tgn:7087429",
          "tgn:1000003",
          "tgn:7003688",
          "tgn:7000084",
          "tgn:7029392"
        ],
        "placetype": [
          "aat:300000745"
        ],
        "id": 7087429,
        "name:xx": "Waldenau"
      }
    }
  ]
}
