{
  "geometry": {
    "type": "Point",
    "coordinates": [
      31.25,
      65.8667
    ]
  },
  "type": "Feature",
  "properties": {
    "hierarchy": [
      "tgn:1059557",
      "tgn:1000004",
      "tgn:7011509",
      "tgn:7002435",
      "tgn:7029392"
    ],
    "placetype": [
      "aat:300008347"
    ],
    "id": 1059557,
    "name:xx": "Sof'yanga"
  }
}
