{
  "geometry": {
    "type": "Point",
    "coordinates": [
      -113.8833,
      32.3667
    ]
  },
  "type": "Feature",
  "properties": {
    "hierarchy": [
      "tgn:2202354",
      "tgn:1000001",
      "tgn:7006451",
      "tgn:7012149",
      "tgn:2000104",
      "tgn:7029392"
    ],
    "placetype": [
      "aat:300008798"
    ],
    "id": 2202354,
    "name:xx": "Buck Peak"
  }
}
