{
  "type": "FeatureCollection",
  "features": [
    {
      "geometry": {
        "type": "Point",
        "coordinates": [
          -119.3667,
          44.1333
        ]
      },
      "type": "Feature",
      "properties": {
        "hierarchy": [
          "tgn:2257660",
          "tgn:1000001",
          "tgn:7012149",
          "tgn:2001708",
          "tgn:7007708",
          "tgn:7029392"
        ],
        "placetype": [
          "aat:300008706"
        ],
        "id": 2257660,
        "name:xx": "Corral Creek"
      }
    },
    {
      "geometry": {
        "type": "Point",
        "coordinates": [
          -123.55,
          42.85
        ]
      },
      "type": "Feature",
      "properties": {
        "hierarchy": [
          "tgn:2257661",
          "tgn:1000001",
          "tgn:7012149",
          "tgn:2001706",
          "tgn:7007708",
          "tgn:7029392"
        ],
        "placetype": [
          "aat:300008706"
        ],
        "id": 2257661,
        "name:xx": "Corral Creek"
      }
    },
    {
      "geometry": {
        "type": "Point",
        "coordinates": [
          -122.8,
          45.2833
        ]
      },
      "type": "Feature",
      "properties": {
        "hierarchy": [
          "tgn:2257662",
          "tgn:1000001",
          "tgn:1002270",
          "tgn:7012149",
          "tgn:7007708",
          "tgn:7029392"
        ],
        "placetype": [
          "aat:300008347"
        ],
        "id": 2257662,
        "name:xx": "Corral Creek"
      }
    },
    {
      "geometry": {
        "type": "Point",
        "coordinates": [
          -103.6833,
          44.2333
        ]
      },
      "type": "Feature",
      "properties": {
        "hierarchy": [
          "tgn:2257663",
          "tgn:1000001",
          "tgn:2001810",
          "tgn:7012149",
          "tgn:7007713",
          "tgn:7029392"
        ],
        "placetype": [
          "aat:300008706"
        ],
        "id": 2257663,
        "name:xx": "Corral Creek"
      }
    },
    {
      "geometry": {
        "type": "Point",
        "coordinates": [
          -100.6667,
          44.95
        ]
      },
      "type": "Feature",
      "properties": {
        "hierarchy": [
          "tgn:2257664",
          "tgn:1000001",
          "tgn:2001790",
          "tgn:7012149",
          "tgn:7007713",
          "tgn:7029392"
        ],
        "placetype": [
          "aat:300008706"
        ],
        "id": 2257664,
        "name:xx": "Corral Creek"
      }
    },
    {
      "geometry": {
        "type": "Point",
        "coordinates": [
          -97.7167,
          29.1333
        ]
      },
      "type": "Feature",
      "properties": {
        "hierarchy": [
          "tgn:2257665",
          "tgn:1000001",
          "tgn:7012149",
          "tgn:1002533",
          "tgn:7007826",
          "tgn:7029392"
        ],
        "placetype": [
          "aat:300008706"
        ],
        "id": 2257665,
        "name:xx": "Corral Creek"
      }
    },
    {
      "geometry": {
        "type": "Point",
        "coordinates": [
          -94.1,
          33.3833
        ]
      },
      "type": "Feature",
      "properties": {
        "hierarchy": [
          "tgn:2257666",
          "tgn:1000001",
          "tgn:2001944",
          "tgn:7012149",
          "tgn:7007826",
          "tgn:7029392"
        ],
        "placetype": [
          "aat:300008706"
        ],
        "id": 2257666,
        "name:xx": "Corral Creek"
      }
    },
    {
      "geometry": {
        "type": "Point",
        "coordinates": [
          -100.2333,
          35.0833
        ]
      },
      "type": "Feature",
      "properties": {
        "hierarchy": [
          "tgn:2257667",
          "tgn:1000001",
          "tgn:7012149",
          "tgn:2001960",
          "tgn:7007826",
          "tgn:7029392"
        ],
        "placetype": [
          "aat:300008706"
        ],
        "id": 2257667,
        "name:xx": "Corral Creek"
      }
    },
    {
      "geometry": {
        "type": "Point",
        "coordinates": [
          -101.9833,
          35.6
        ]
      },
      "type": "Feature",
      "properties": {
        "hierarchy": [
          "tgn:2257668",
          "tgn:1000001",
          "tgn:7012149",
          "tgn:2002056",
          "tgn:7007826",
          "tgn:7029392"
        ],
        "placetype": [
          "aat:300008706"
        ],
        "id": 2257668,
        "name:xx": "Corral Creek"
      }
    },
    {
      "geometry": {
        "type": "Point",
        "coordinates": [
          -101.3667,
          31.6333
        ]
      },
      "type": "Feature",
      "properties": {
        "hierarchy": [
          "tgn:2257669",
          "tgn:1000001",
          "tgn:7012149",
          "tgn:2002059",
          "tgn:7007826",
          "tgn:7029392"
        ],
        "placetype": [
          "aat:300008706"
        ],
        "id": 2257669,
        "name:xx": "Corral Creek"
      }
    }
  ]
}
