{
  "geometry": {
    "type": "Point",
    "coordinates": [
      45.3167,
      49.6667
    ]
  },
  "type": "Feature",
  "properties": {
    "hierarchy": [
      "tgn:1053212",
      "tgn:1000004",
      "tgn:7013207",
      "tgn:7018214",
      "tgn:7002435",
      "tgn:7029392"
    ],
    "placetype": [
      "aat:300008347"
    ],
    "id": 1053212,
    "name:xx": "Bykovo"
  }
}
