{
  "geometry": {
    "type": "Point",
    "coordinates": [
      -83.0167,
      43.7667
    ]
  },
  "type": "Feature",
  "properties": {
    "hierarchy": [
      "tgn:2250385",
      "tgn:1000001",
      "tgn:7012149",
      "tgn:2000964",
      "tgn:7007520",
      "tgn:7029392"
    ],
    "placetype": [
      "aat:300006075"
    ],
    "id": 2250385,
    "name:xx": "Colona Drain"
  }
}
