{
  "geometry": {
    "type": "Point",
    "coordinates": [
      -121.6167,
      39.7167
    ]
  },
  "type": "Feature",
  "properties": {
    "hierarchy": [
      "tgn:2767405",
      "tgn:1000001",
      "tgn:1002218",
      "tgn:7012149",
      "tgn:7007157",
      "tgn:7029392"
    ],
    "placetype": [
      "aat:300266640"
    ],
    "id": 2767405,
    "name:xx": "White Spring Ridge"
  }
}
