{
  "geometry": {
    "type": "Point",
    "coordinates": [
      74.28622,
      34.380142
    ]
  },
  "type": "Feature",
  "properties": {
    "hierarchy": [
      "tgn:7586043",
      "tgn:1000004",
      "tgn:7000198",
      "tgn:7000799",
      "tgn:7029392"
    ],
    "placetype": [
      "aat:300008347"
    ],
    "name:en": "Mārotgain",
    "id": 7586043
  }
}
