{
  "geometry": {
    "type": "Point",
    "coordinates": [
      -90.3833,
      35.7167
    ]
  },
  "type": "Feature",
  "properties": {
    "hierarchy": [
      "tgn:2007851",
      "tgn:1000001",
      "tgn:7016172",
      "tgn:2000120",
      "tgn:7012149",
      "tgn:7029392"
    ],
    "placetype": [
      "aat:300008347",
      "aat:300387210"
    ],
    "id": 2007851,
    "name:xx": "Bunney"
  }
}
