{
  "geometry": {
    "type": "Point",
    "coordinates": [
      -105.9667,
      38.45
    ]
  },
  "type": "Feature",
  "properties": {
    "hierarchy": [
      "tgn:2784240",
      "tgn:1000001",
      "tgn:7012149",
      "tgn:7007158",
      "tgn:2000246",
      "tgn:7029392"
    ],
    "placetype": [
      "aat:300008706"
    ],
    "id": 2784240,
    "name:xx": "Yankee Creek"
  }
}
