{
  "geometry": {
    "type": "Point",
    "coordinates": [
      -94.0667,
      37.0333
    ]
  },
  "type": "Feature",
  "properties": {
    "hierarchy": [
      "tgn:2450427",
      "tgn:1000001",
      "tgn:7012149",
      "tgn:2001223",
      "tgn:7007523",
      "tgn:7029392"
    ],
    "placetype": [
      "aat:300008697"
    ],
    "id": 2450427,
    "name:xx": "Linn Spring"
  }
}
