{
  "geometry": {
    "type": "Point",
    "coordinates": [
      -77.2333,
      42.1833
    ]
  },
  "type": "Feature",
  "properties": {
    "hierarchy": [
      "tgn:2209556",
      "tgn:1000001",
      "tgn:7012149",
      "tgn:1002920",
      "tgn:7007568",
      "tgn:7029392"
    ],
    "placetype": [
      "aat:300008761"
    ],
    "id": 2209556,
    "name:xx": "Burr Hollow"
  }
}
