{
  "geometry": {
    "type": "Point",
    "coordinates": [
      -89.95,
      43.3333
    ]
  },
  "type": "Feature",
  "properties": {
    "hierarchy": [
      "tgn:2445051",
      "tgn:1000001",
      "tgn:7012149",
      "tgn:2002352",
      "tgn:7007922",
      "tgn:7029392"
    ],
    "placetype": [
      "aat:300006191"
    ],
    "id": 2445051,
    "name:xx": "Leland Millpond"
  }
}
