{
  "geometry": {
    "type": "Point",
    "coordinates": [
      -84.4833,
      37.5667
    ]
  },
  "type": "Feature",
  "properties": {
    "hierarchy": [
      "tgn:2306066",
      "tgn:1000001",
      "tgn:7012149",
      "tgn:2000791",
      "tgn:7007255",
      "tgn:7029392"
    ],
    "placetype": [
      "aat:300008706"
    ],
    "id": 2306066,
    "name:xx": "East Fork Back Creek"
  }
}
