{
  "geometry": {
    "type": "Point",
    "coordinates": [
      -149.0333,
      64.6333
    ]
  },
  "type": "Feature",
  "properties": {
    "hierarchy": [
      "tgn:2006224",
      "tgn:7006450",
      "tgn:1000001",
      "tgn:7012149",
      "tgn:2000089",
      "tgn:7029392"
    ],
    "placetype": [
      "aat:300387016"
    ],
    "id": 2006224,
    "name:xx": "Berg"
  }
}
