{
  "type": "FeatureCollection",
  "features": [
    {
      "geometry": {
        "type": "Point",
        "coordinates": [
          -88.9667,
          31.0167
        ]
      },
      "type": "Feature",
      "properties": {
        "hierarchy": [
          "tgn:2717530",
          "tgn:1000001",
          "tgn:7012149",
          "tgn:2001141",
          "tgn:7007522",
          "tgn:7029392"
        ],
        "placetype": [
          "aat:300008699"
        ],
        "id": 2717530,
        "name:xx": "Thomas Branch"
      }
    },
    {
      "geometry": {
        "type": "Point",
        "coordinates": [
          -92.8,
          38.9333
        ]
      },
      "type": "Feature",
      "properties": {
        "hierarchy": [
          "tgn:2717531",
          "tgn:1000001",
          "tgn:7012149",
          "tgn:2001189",
          "tgn:7007523",
          "tgn:7029392"
        ],
        "placetype": [
          "aat:300008699"
        ],
        "id": 2717531,
        "name:xx": "Thomas Branch"
      }
    },
    {
      "geometry": {
        "type": "Point",
        "coordinates": [
          -92.0333,
          39.9167
        ]
      },
      "type": "Feature",
      "properties": {
        "hierarchy": [
          "tgn:2717532",
          "tgn:1000001",
          "tgn:7012149",
          "tgn:1002888",
          "tgn:7007523",
          "tgn:7029392"
        ],
        "placetype": [
          "aat:300008699"
        ],
        "id": 2717532,
        "name:xx": "Thomas Branch"
      }
    },
    {
      "geometry": {
        "type": "Point",
        "coordinates": [
          -83.5,
          35.05
        ]
      },
      "type": "Feature",
      "properties": {
        "hierarchy": [
          "tgn:2717533",
          "tgn:1000001",
          "tgn:7012149",
          "tgn:2001515",
          "tgn:7007709",
          "tgn:7029392"
        ],
        "placetype": [
          "aat:300008699"
        ],
        "id": 2717533,
        "name:xx": "Thomas Branch"
      }
    },
    {
      "geometry": {
        "type": "Point",
        "coordinates": [
          -82.7167,
          35.85
        ]
      },
      "type": "Feature",
      "properties": {
        "hierarchy": [
          "tgn:2717534",
          "tgn:1000001",
          "tgn:7012149",
          "tgn:2001516",
          "tgn:7007709",
          "tgn:7029392"
        ],
        "placetype": [
          "aat:300008699"
        ],
        "id": 2717534,
        "name:xx": "Thomas Branch"
      }
    },
    {
      "geometry": {
        "type": "Point",
        "coordinates": [
          -80.55,
          34.2667
        ]
      },
      "type": "Feature",
      "properties": {
        "hierarchy": [
          "tgn:2717535",
          "tgn:1000001",
          "tgn:7012149",
          "tgn:2001752",
          "tgn:7007712",
          "tgn:7029392"
        ],
        "placetype": [
          "aat:300008699"
        ],
        "id": 2717535,
        "name:xx": "Thomas Branch"
      }
    },
    {
      "geometry": {
        "type": "Point",
        "coordinates": [
          -81.9167,
          34.7667
        ]
      },
      "type": "Feature",
      "properties": {
        "hierarchy": [
          "tgn:2717536",
          "tgn:1000001",
          "tgn:7012149",
          "tgn:2001766",
          "tgn:7007712",
          "tgn:7029392"
        ],
        "placetype": [
          "aat:300008699"
        ],
        "id": 2717536,
        "name:xx": "Thomas Branch"
      }
    },
    {
      "geometry": {
        "type": "Point",
        "coordinates": [
          -85.3167,
          35.3833
        ]
      },
      "type": "Feature",
      "properties": {
        "hierarchy": [
          "tgn:2717537",
          "tgn:1000001",
          "tgn:7012149",
          "tgn:2001913",
          "tgn:7007825",
          "tgn:7029392"
        ],
        "placetype": [
          "aat:300008699"
        ],
        "id": 2717537,
        "name:xx": "Thomas Branch"
      }
    },
    {
      "geometry": {
        "type": "Point",
        "coordinates": [
          -86.8333,
          35.4167
        ]
      },
      "type": "Feature",
      "properties": {
        "hierarchy": [
          "tgn:2717538",
          "tgn:1000001",
          "tgn:7012149",
          "tgn:2001895",
          "tgn:7007825",
          "tgn:7029392"
        ],
        "placetype": [
          "aat:300008699"
        ],
        "id": 2717538,
        "name:xx": "Thomas Branch"
      }
    },
    {
      "geometry": {
        "type": "Point",
        "coordinates": [
          -88.1,
          35.7333
        ]
      },
      "type": "Feature",
      "properties": {
        "hierarchy": [
          "tgn:2717539",
          "tgn:1000001",
          "tgn:7012149",
          "tgn:2001856",
          "tgn:7007825",
          "tgn:7029392"
        ],
        "placetype": [
          "aat:300008699"
        ],
        "id": 2717539,
        "name:xx": "Thomas Branch"
      }
    }
  ]
}
