{
  "geometry": {
    "type": "Point",
    "coordinates": [
      -76.1167,
      43.95
    ]
  },
  "type": "Feature",
  "properties": {
    "hierarchy": [
      "tgn:2536316",
      "tgn:1000001",
      "tgn:7012149",
      "tgn:1002518",
      "tgn:7007568",
      "tgn:7029392"
    ],
    "placetype": [
      "aat:300008850"
    ],
    "id": 2536316,
    "name:xx": "Navy Point"
  }
}
