{
  "geometry": {
    "type": "Point",
    "coordinates": [
      41.5333,
      38.25
    ]
  },
  "type": "Feature",
  "properties": {
    "hierarchy": [
      "tgn:1109594",
      "tgn:1000004",
      "tgn:1000144",
      "tgn:7029392"
    ],
    "placetype": [
      "aat:300008795"
    ],
    "id": 1109594,
    "name:xx": "Aydınlık Dağları"
  }
}
