{
  "geometry": {
    "type": "Point",
    "coordinates": [
      -113.3333,
      36.7167
    ]
  },
  "type": "Feature",
  "properties": {
    "hierarchy": [
      "tgn:2623907",
      "tgn:1000001",
      "tgn:7006451",
      "tgn:7012149",
      "tgn:2000098",
      "tgn:7029392"
    ],
    "placetype": [
      "aat:300006191"
    ],
    "id": 2623907,
    "name:xx": "Rock Crossing Reservoir"
  }
}
