{
  "geometry": {
    "type": "Point",
    "coordinates": [
      20.7167,
      45.7833
    ]
  },
  "type": "Feature",
  "properties": {
    "hierarchy": [
      "tgn:1050166",
      "tgn:1000003",
      "tgn:7002701",
      "tgn:1000091",
      "tgn:7029392"
    ],
    "placetype": [
      "aat:300008347"
    ],
    "id": 1050166,
    "name:xx": "Jimbolia"
  }
}
