{
  "geometry": {
    "type": "Point",
    "coordinates": [
      -81.45,
      25.8667
    ]
  },
  "type": "Feature",
  "properties": {
    "hierarchy": [
      "tgn:2346133",
      "tgn:1000001",
      "tgn:1002289",
      "tgn:7012149",
      "tgn:7007240",
      "tgn:7029392"
    ],
    "placetype": [
      "aat:300132316"
    ],
    "id": 2346133,
    "name:xx": "Gate Bay"
  }
}
