{
  "geometry": {
    "type": "Point",
    "coordinates": [
      -80.5667,
      40.05
    ]
  },
  "type": "Feature",
  "properties": {
    "hierarchy": [
      "tgn:2493198",
      "tgn:1000001",
      "tgn:7012149",
      "tgn:2002276",
      "tgn:7013961",
      "tgn:7029392"
    ],
    "placetype": [
      "aat:300008699"
    ],
    "id": 2493198,
    "name:xx": "Marlow Run"
  }
}
