{
  "type": "FeatureCollection",
  "features": [
    {
      "geometry": {
        "type": "Point",
        "coordinates": [
          -147.3333,
          65.15
        ]
      },
      "type": "Feature",
      "properties": {
        "hierarchy": [
          "tgn:2508630",
          "tgn:7006450",
          "tgn:1000001",
          "tgn:7019674",
          "tgn:7012149",
          "tgn:7029392"
        ],
        "placetype": [
          "aat:300006075"
        ],
        "id": 2508630,
        "name:xx": "Middle Ditch"
      }
    },
    {
      "geometry": {
        "type": "Point",
        "coordinates": [
          -120.6667,
          37.1333
        ]
      },
      "type": "Feature",
      "properties": {
        "hierarchy": [
          "tgn:2508631",
          "tgn:1000001",
          "tgn:7012149",
          "tgn:7007157",
          "tgn:1002656",
          "tgn:7029392"
        ],
        "placetype": [
          "aat:300006075"
        ],
        "id": 2508631,
        "name:xx": "Middle Ditch"
      }
    },
    {
      "geometry": {
        "type": "Point",
        "coordinates": [
          -111.8,
          42.05
        ]
      },
      "type": "Feature",
      "properties": {
        "hierarchy": [
          "tgn:2508632",
          "tgn:1000001",
          "tgn:7012149",
          "tgn:2000472",
          "tgn:7007250",
          "tgn:7029392"
        ],
        "placetype": [
          "aat:300006075"
        ],
        "id": 2508632,
        "name:xx": "Middle Ditch"
      }
    },
    {
      "geometry": {
        "type": "Point",
        "coordinates": [
          -119.7833,
          38.9833
        ]
      },
      "type": "Feature",
      "properties": {
        "hierarchy": [
          "tgn:2508633",
          "tgn:1000001",
          "tgn:1002340",
          "tgn:7012149",
          "tgn:7007526",
          "tgn:7029392"
        ],
        "placetype": [
          "aat:300006075"
        ],
        "id": 2508633,
        "name:xx": "Middle Ditch"
      }
    },
    {
      "geometry": {
        "type": "Point",
        "coordinates": [
          -106.6833,
          34.8167
        ]
      },
      "type": "Feature",
      "properties": {
        "hierarchy": [
          "tgn:2508634",
          "tgn:1000001",
          "tgn:7012149",
          "tgn:2001460",
          "tgn:7007566",
          "tgn:7029392"
        ],
        "placetype": [
          "aat:300006075"
        ],
        "id": 2508634,
        "name:xx": "Middle Ditch"
      }
    },
    {
      "geometry": {
        "type": "Point",
        "coordinates": [
          -107.95,
          35.2333
        ]
      },
      "type": "Feature",
      "properties": {
        "hierarchy": [
          "tgn:2508635",
          "tgn:1000001",
          "tgn:2001431",
          "tgn:7012149",
          "tgn:7007566",
          "tgn:7029392"
        ],
        "placetype": [
          "aat:300006075"
        ],
        "id": 2508635,
        "name:xx": "Middle Ditch"
      }
    },
    {
      "geometry": {
        "type": "Point",
        "coordinates": [
          -116.95,
          44.15
        ]
      },
      "type": "Feature",
      "properties": {
        "hierarchy": [
          "tgn:2508636",
          "tgn:1000001",
          "tgn:7012149",
          "tgn:2001718",
          "tgn:7007708",
          "tgn:7029392"
        ],
        "placetype": [
          "aat:300006075"
        ],
        "id": 2508636,
        "name:xx": "Middle Ditch"
      }
    },
    {
      "geometry": {
        "type": "Point",
        "coordinates": [
          -111.4167,
          40.5167
        ]
      },
      "type": "Feature",
      "properties": {
        "hierarchy": [
          "tgn:2508637",
          "tgn:1000001",
          "tgn:7012149",
          "tgn:2002126",
          "tgn:7007827",
          "tgn:7029392"
        ],
        "placetype": [
          "aat:300006075"
        ],
        "id": 2508637,
        "name:xx": "Middle Ditch"
      }
    },
    {
      "geometry": {
        "type": "Point",
        "coordinates": [
          -76.5,
          36.65
        ]
      },
      "type": "Feature",
      "properties": {
        "hierarchy": [
          "tgn:2508638",
          "tgn:1000001",
          "tgn:7012149",
          "tgn:7022217",
          "tgn:7007919",
          "tgn:7029392"
        ],
        "placetype": [
          "aat:300006075"
        ],
        "id": 2508638,
        "name:xx": "Middle Ditch"
      }
    },
    {
      "geometry": {
        "type": "Point",
        "coordinates": [
          -106.5667,
          41.9333
        ]
      },
      "type": "Feature",
      "properties": {
        "hierarchy": [
          "tgn:2508639",
          "tgn:1000001",
          "tgn:2002368",
          "tgn:7012149",
          "tgn:7007923",
          "tgn:7029392"
        ],
        "placetype": [
          "aat:300008699"
        ],
        "id": 2508639,
        "name:xx": "Middle Ditch"
      }
    }
  ]
}
