{
  "type": "FeatureCollection",
  "features": [
    {
      "geometry": {
        "type": "Point",
        "coordinates": [
          -99.65,
          19.8
        ]
      },
      "type": "Feature",
      "properties": {
        "hierarchy": [
          "tgn:7440182",
          "tgn:1000001",
          "tgn:1001893",
          "tgn:7005560",
          "tgn:7029392"
        ],
        "placetype": [
          "aat:300008347"
        ],
        "id": 7440182,
        "name:xx": "San Marcos"
      }
    },
    {
      "geometry": {
        "type": "Point",
        "coordinates": [
          -102.483333,
          19.633333
        ]
      },
      "type": "Feature",
      "properties": {
        "hierarchy": [
          "tgn:7440183",
          "tgn:1000001",
          "tgn:7005590",
          "tgn:7005560",
          "tgn:7029392"
        ],
        "placetype": [
          "aat:300008347"
        ],
        "id": 7440183,
        "name:xx": "San Marcos"
      }
    },
    {
      "geometry": {
        "type": "Point",
        "coordinates": [
          -103.466667,
          19.416667
        ]
      },
      "type": "Feature",
      "properties": {
        "hierarchy": [
          "tgn:7440184",
          "tgn:7016644",
          "tgn:1000001",
          "tgn:7005560",
          "tgn:7029392"
        ],
        "placetype": [
          "aat:300008347"
        ],
        "id": 7440184,
        "name:xx": "San Marcos"
      }
    },
    {
      "geometry": {
        "type": "Point",
        "coordinates": [
          -96.95,
          19.416667
        ]
      },
      "type": "Feature",
      "properties": {
        "hierarchy": [
          "tgn:7440186",
          "tgn:1000001",
          "tgn:7005599",
          "tgn:7005560",
          "tgn:7029392"
        ],
        "placetype": [
          "aat:300008347"
        ],
        "id": 7440186,
        "name:xx": "San Marcos"
      }
    },
    {
      "geometry": {
        "type": "Point",
        "coordinates": [
          -101.966667,
          19.3
        ]
      },
      "type": "Feature",
      "properties": {
        "hierarchy": [
          "tgn:7440187",
          "tgn:1000001",
          "tgn:7005590",
          "tgn:7005560",
          "tgn:7029392"
        ],
        "placetype": [
          "aat:300008347"
        ],
        "id": 7440187,
        "name:xx": "San Marcos"
      }
    },
    {
      "geometry": {
        "type": "Point",
        "coordinates": [
          -100.266667,
          18.716667
        ]
      },
      "type": "Feature",
      "properties": {
        "hierarchy": [
          "tgn:7440188",
          "tgn:1000001",
          "tgn:1001893",
          "tgn:7005560",
          "tgn:7029392"
        ],
        "placetype": [
          "aat:300008347"
        ],
        "id": 7440188,
        "name:xx": "San Marcos"
      }
    },
    {
      "geometry": {
        "type": "Point",
        "coordinates": [
          -97.35,
          18.4
        ]
      },
      "type": "Feature",
      "properties": {
        "hierarchy": [
          "tgn:7440189",
          "tgn:1000001",
          "tgn:7005592",
          "tgn:7005560",
          "tgn:7029392"
        ],
        "placetype": [
          "aat:300008347"
        ],
        "id": 7440189,
        "name:xx": "San Marcos"
      }
    }
  ]
}
