{
  "geometry": {
    "type": "Point",
    "coordinates": [
      -83.9167,
      44.1833
    ]
  },
  "type": "Feature",
  "properties": {
    "hierarchy": [
      "tgn:2053073",
      "tgn:1000001",
      "tgn:7012149",
      "tgn:2000985",
      "tgn:7007520",
      "tgn:7029392"
    ],
    "placetype": [
      "aat:300008347"
    ],
    "id": 2053073,
    "name:xx": "Prescott"
  }
}
