{
  "geometry": {
    "type": "Point",
    "coordinates": [
      78.557778,
      17.13
    ]
  },
  "type": "Feature",
  "properties": {
    "hierarchy": [
      "tgn:7569785",
      "tgn:1001828",
      "tgn:1000004",
      "tgn:7000198",
      "tgn:7029392"
    ],
    "placetype": [
      "aat:300008347"
    ],
    "name:en": "Timmāpur",
    "id": 7569785
  }
}
