{
  "geometry": {
    "type": "Point",
    "coordinates": [
      129.2833,
      43.85
    ]
  },
  "type": "Feature",
  "properties": {
    "hierarchy": [
      "tgn:1070146",
      "tgn:1000004",
      "tgn:1001290",
      "tgn:1000111",
      "tgn:7029392"
    ],
    "placetype": [
      "aat:300008347"
    ],
    "id": 1070146,
    "name:xx": "Ludao"
  }
}
