{
  "type": "FeatureCollection",
  "features": [
    {
      "geometry": {
        "type": "Point",
        "coordinates": [
          -82.7833,
          36.6
        ]
      },
      "type": "Feature",
      "properties": {
        "hierarchy": [
          "tgn:2426110",
          "tgn:1000001",
          "tgn:7012149",
          "tgn:2002189",
          "tgn:7007919",
          "tgn:7029392"
        ],
        "placetype": [
          "aat:300008699"
        ],
        "id": 2426110,
        "name:xx": "Jones Branch"
      }
    },
    {
      "geometry": {
        "type": "Point",
        "coordinates": [
          -81.3667,
          38.15
        ]
      },
      "type": "Feature",
      "properties": {
        "hierarchy": [
          "tgn:2426111",
          "tgn:1000001",
          "tgn:7012149",
          "tgn:2002270",
          "tgn:7013961",
          "tgn:7029392"
        ],
        "placetype": [
          "aat:300008699"
        ],
        "id": 2426111,
        "name:xx": "Jones Branch"
      }
    },
    {
      "geometry": {
        "type": "Point",
        "coordinates": [
          -82.2333,
          38.05
        ]
      },
      "type": "Feature",
      "properties": {
        "hierarchy": [
          "tgn:2426113",
          "tgn:1000001",
          "tgn:7012149",
          "tgn:2002299",
          "tgn:7013961",
          "tgn:7029392"
        ],
        "placetype": [
          "aat:300008699"
        ],
        "id": 2426113,
        "name:xx": "Jones Branch"
      }
    },
    {
      "geometry": {
        "type": "Point",
        "coordinates": [
          -90.35,
          42.7667
        ]
      },
      "type": "Feature",
      "properties": {
        "hierarchy": [
          "tgn:2426114",
          "tgn:1000001",
          "tgn:7012149",
          "tgn:2002332",
          "tgn:7007922",
          "tgn:7029392"
        ],
        "placetype": [
          "aat:300008699"
        ],
        "id": 2426114,
        "name:xx": "Jones Branch"
      }
    },
    {
      "geometry": {
        "type": "Point",
        "coordinates": [
          -84.8,
          41.05
        ]
      },
      "type": "Feature",
      "properties": {
        "hierarchy": [
          "tgn:2426115",
          "tgn:1002143",
          "tgn:1000001",
          "tgn:7012149",
          "tgn:7007252",
          "tgn:7029392"
        ],
        "placetype": [
          "aat:300006075"
        ],
        "id": 2426115,
        "name:xx": "Jones Branch Ditch"
      }
    },
    {
      "geometry": {
        "type": "Point",
        "coordinates": [
          -70.8333,
          43.55
        ]
      },
      "type": "Feature",
      "properties": {
        "hierarchy": [
          "tgn:2426116",
          "tgn:1000001",
          "tgn:7012149",
          "tgn:2000933",
          "tgn:7007515",
          "tgn:7029392"
        ],
        "placetype": [
          "aat:300008699"
        ],
        "id": 2426116,
        "name:xx": "Jones Brook"
      }
    },
    {
      "geometry": {
        "type": "Point",
        "coordinates": [
          -69.4167,
          44.2833
        ]
      },
      "type": "Feature",
      "properties": {
        "hierarchy": [
          "tgn:2426117",
          "tgn:1000001",
          "tgn:7012149",
          "tgn:7007515",
          "tgn:7029392"
        ],
        "placetype": [
          "aat:300008699"
        ],
        "id": 2426117,
        "name:xx": "Jones Brook"
      }
    },
    {
      "geometry": {
        "type": "Point",
        "coordinates": [
          -70,
          44.3667
        ]
      },
      "type": "Feature",
      "properties": {
        "hierarchy": [
          "tgn:2426118",
          "tgn:1000001",
          "tgn:2000923",
          "tgn:7012149",
          "tgn:7007515",
          "tgn:7029392"
        ],
        "placetype": [
          "aat:300008699"
        ],
        "id": 2426118,
        "name:xx": "Jones Brook"
      }
    },
    {
      "geometry": {
        "type": "Point",
        "coordinates": [
          -69.8,
          44.7333
        ]
      },
      "type": "Feature",
      "properties": {
        "hierarchy": [
          "tgn:2426119",
          "tgn:1000001",
          "tgn:7012149",
          "tgn:2000930",
          "tgn:7007515",
          "tgn:7029392"
        ],
        "placetype": [
          "aat:300008699"
        ],
        "id": 2426119,
        "name:xx": "Jones Brook"
      }
    }
  ]
}
