{
  "geometry": {
    "type": "Point",
    "coordinates": [
      -83.3833,
      37.5333
    ]
  },
  "type": "Feature",
  "properties": {
    "hierarchy": [
      "tgn:2267307",
      "tgn:1000001",
      "tgn:2000772",
      "tgn:7012149",
      "tgn:7007255",
      "tgn:7029392"
    ],
    "placetype": [
      "aat:300008706"
    ],
    "id": 2267307,
    "name:xx": "Cripple Creek"
  }
}
