{
  "geometry": {
    "type": "Point",
    "coordinates": [
      -81.3167,
      28.8167
    ]
  },
  "type": "Feature",
  "properties": {
    "hierarchy": [
      "tgn:2187256",
      "tgn:1000001",
      "tgn:7012149",
      "tgn:1002881",
      "tgn:7007240",
      "tgn:7029392"
    ],
    "placetype": [
      "aat:300008347"
    ],
    "id": 2187256,
    "name:xx": "Bookertown"
  }
}
