{
  "geometry": {
    "type": "Point",
    "coordinates": [
      116.8333,
      -1.25
    ]
  },
  "type": "Feature",
  "properties": {
    "hierarchy": [
      "tgn:7015957",
      "tgn:1000004",
      "tgn:1001339",
      "tgn:1000116",
      "tgn:7029392"
    ],
    "placetype": [
      "aat:300008347"
    ],
    "id": 7015957,
    "name:xx": "Balikpapan"
  }
}
