{
  "geometry": {
    "type": "Point",
    "coordinates": [
      44.9833,
      43.05
    ]
  },
  "type": "Feature",
  "properties": {
    "hierarchy": [
      "tgn:1057186",
      "tgn:1000004",
      "tgn:7018213",
      "tgn:7002435",
      "tgn:7029392"
    ],
    "placetype": [
      "aat:300008347"
    ],
    "id": 1057186,
    "name:xx": "Mužiči"
  }
}
