{
  "geometry": {
    "type": "Point",
    "coordinates": [
      -134.2333,
      57.1833
    ]
  },
  "type": "Feature",
  "properties": {
    "hierarchy": [
      "tgn:2183482",
      "tgn:7006450",
      "tgn:1000001",
      "tgn:7012149",
      "tgn:7019760",
      "tgn:7029392"
    ],
    "placetype": [
      "aat:300008850"
    ],
    "id": 2183482,
    "name:xx": "Bluff Point"
  }
}
