{
  "geometry": {
    "type": "Point",
    "coordinates": [
      -86.5667,
      32.0167
    ]
  },
  "type": "Feature",
  "properties": {
    "hierarchy": [
      "tgn:2379069",
      "tgn:7002659",
      "tgn:1000001",
      "tgn:7012149",
      "tgn:2000042",
      "tgn:7029392"
    ],
    "placetype": [
      "aat:300006191"
    ],
    "id": 2379069,
    "name:xx": "Hartleys Pond"
  }
}
