{
  "geometry": {
    "type": "Point",
    "coordinates": [
      -47.7167,
      -18.75
    ]
  },
  "type": "Feature",
  "properties": {
    "hierarchy": [
      "tgn:1021404",
      "tgn:7006237",
      "tgn:1000047",
      "tgn:7002457",
      "tgn:1000002",
      "tgn:7029392"
    ],
    "placetype": [
      "aat:300008347"
    ],
    "id": 1021404,
    "name:xx": "Estrêla do Sul"
  }
}
