{
  "geometry": {
    "type": "Point",
    "coordinates": [
      136.6667,
      35.4833
    ]
  },
  "type": "Feature",
  "properties": {
    "hierarchy": [
      "tgn:1080868",
      "tgn:7000895",
      "tgn:1000004",
      "tgn:1000977",
      "tgn:1000120",
      "tgn:7029392"
    ],
    "placetype": [
      "aat:300008347"
    ],
    "id": 1080868,
    "name:xx": "Motosu"
  }
}
