{
  "geometry": {
    "type": "Point",
    "coordinates": [
      -97.7333,
      26.0333
    ]
  },
  "type": "Feature",
  "properties": {
    "hierarchy": [
      "tgn:2105756",
      "tgn:1000001",
      "tgn:7012149",
      "tgn:2001952",
      "tgn:7007826",
      "tgn:7029392"
    ],
    "placetype": [
      "aat:300008347"
    ],
    "id": 2105756,
    "name:xx": "Los Indios"
  }
}
