{
  "geometry": {
    "type": "Point",
    "coordinates": [
      -116.8667,
      42.05
    ]
  },
  "type": "Feature",
  "properties": {
    "hierarchy": [
      "tgn:2747902",
      "tgn:1000001",
      "tgn:7012149",
      "tgn:2000488",
      "tgn:7007250",
      "tgn:7029392"
    ],
    "placetype": [
      "aat:300386845"
    ],
    "id": 2747902,
    "name:xx": "Walcot Basin"
  }
}
