{
  "geometry": {
    "type": "Point",
    "coordinates": [
      46.3167,
      40.6667
    ]
  },
  "type": "Feature",
  "properties": {
    "hierarchy": [
      "tgn:7017286",
      "tgn:7011438",
      "tgn:1000004",
      "tgn:7006646",
      "tgn:7029392"
    ],
    "placetype": [
      "aat:300008347",
      "aat:300008375"
    ],
    "name:en": "Gäncä",
    "id": 7017286
  }
}
