{
  "geometry": {
    "type": "Point",
    "coordinates": [
      -84.0167,
      40.5833
    ]
  },
  "type": "Feature",
  "properties": {
    "hierarchy": [
      "tgn:2469826",
      "tgn:1002159",
      "tgn:1000001",
      "tgn:7012149",
      "tgn:7007706",
      "tgn:7029392"
    ],
    "placetype": [
      "aat:300008798"
    ],
    "id": 2469826,
    "name:xx": "Lookout, Mount"
  }
}
