{
  "geometry": {
    "type": "Point",
    "coordinates": [
      -76.2667,
      38.4333
    ]
  },
  "type": "Feature",
  "properties": {
    "hierarchy": [
      "tgn:2622858",
      "tgn:1002338",
      "tgn:1000001",
      "tgn:7012149",
      "tgn:7007516",
      "tgn:7029392"
    ],
    "placetype": [
      "aat:300008850"
    ],
    "id": 2622858,
    "name:xx": "Robinson Neck"
  }
}
