{
  "geometry": {
    "type": "Point",
    "coordinates": [
      6.1833,
      45.0667
    ]
  },
  "type": "Feature",
  "properties": {
    "hierarchy": [
      "tgn:7008137",
      "tgn:7002878",
      "tgn:1000003",
      "tgn:1000070",
      "tgn:7029392"
    ],
    "placetype": [
      "aat:300008347"
    ],
    "id": 7008137,
    "name:xx": "Besse"
  }
}
