{
  "geometry": {
    "type": "Point",
    "coordinates": [
      40.3333,
      36.4167
    ]
  },
  "type": "Feature",
  "properties": {
    "hierarchy": [
      "tgn:1108647",
      "tgn:1002056",
      "tgn:1000004",
      "tgn:1000140",
      "tgn:7029392"
    ],
    "placetype": [
      "aat:300008795"
    ],
    "id": 1108647,
    "name:xx": "ʻAbd al-ʻAzīz, Jabal"
  }
}
