{
  "type": "FeatureCollection",
  "features": [
    {
      "geometry": {
        "type": "Point",
        "coordinates": [
          -104.0333,
          36.85
        ]
      },
      "type": "Feature",
      "properties": {
        "hierarchy": [
          "tgn:2735390",
          "tgn:1000001",
          "tgn:2001432",
          "tgn:7012149",
          "tgn:7007566",
          "tgn:7029392"
        ],
        "placetype": [
          "aat:300008798"
        ],
        "id": 2735390,
        "name:xx": "Twin Buttes"
      }
    },
    {
      "geometry": {
        "type": "Point",
        "coordinates": [
          -106.1167,
          32.7
        ]
      },
      "type": "Feature",
      "properties": {
        "hierarchy": [
          "tgn:2735391",
          "tgn:1000001",
          "tgn:7012149",
          "tgn:2001447",
          "tgn:7007566",
          "tgn:7029392"
        ],
        "placetype": [
          "aat:300008798"
        ],
        "id": 2735391,
        "name:xx": "Twin Buttes"
      }
    },
    {
      "geometry": {
        "type": "Point",
        "coordinates": [
          -102.6,
          47.1667
        ]
      },
      "type": "Feature",
      "properties": {
        "hierarchy": [
          "tgn:2735392",
          "tgn:1000001",
          "tgn:2001569",
          "tgn:7012149",
          "tgn:7007705",
          "tgn:7029392"
        ],
        "placetype": [
          "aat:300386831"
        ],
        "id": 2735392,
        "name:xx": "Twin Buttes"
      }
    },
    {
      "geometry": {
        "type": "Point",
        "coordinates": [
          -101.4667,
          48.1167
        ]
      },
      "type": "Feature",
      "properties": {
        "hierarchy": [
          "tgn:2735393",
          "tgn:1000001",
          "tgn:7012149",
          "tgn:2001607",
          "tgn:7007705",
          "tgn:7029392"
        ],
        "placetype": [
          "aat:300386831"
        ],
        "id": 2735393,
        "name:xx": "Twin Buttes"
      }
    },
    {
      "geometry": {
        "type": "Point",
        "coordinates": [
          -102.35,
          46.0333
        ]
      },
      "type": "Feature",
      "properties": {
        "hierarchy": [
          "tgn:2735394",
          "tgn:2001557",
          "tgn:1000001",
          "tgn:7012149",
          "tgn:7007705",
          "tgn:7029392"
        ],
        "placetype": [
          "aat:300008798"
        ],
        "id": 2735394,
        "name:xx": "Twin Buttes"
      }
    },
    {
      "geometry": {
        "type": "Point",
        "coordinates": [
          -103.3833,
          46.2
        ]
      },
      "type": "Feature",
      "properties": {
        "hierarchy": [
          "tgn:2735395",
          "tgn:2001562",
          "tgn:1000001",
          "tgn:7012149",
          "tgn:7007705",
          "tgn:7029392"
        ],
        "placetype": [
          "aat:300008798"
        ],
        "id": 2735395,
        "name:xx": "Twin Buttes"
      }
    },
    {
      "geometry": {
        "type": "Point",
        "coordinates": [
          -100.6167,
          46.3833
        ]
      },
      "type": "Feature",
      "properties": {
        "hierarchy": [
          "tgn:2735396",
          "tgn:1000001",
          "tgn:2001599",
          "tgn:7012149",
          "tgn:7007705",
          "tgn:7029392"
        ],
        "placetype": [
          "aat:300008798"
        ],
        "id": 2735396,
        "name:xx": "Twin Buttes"
      }
    },
    {
      "geometry": {
        "type": "Point",
        "coordinates": [
          -100.7,
          46.6833
        ]
      },
      "type": "Feature",
      "properties": {
        "hierarchy": [
          "tgn:2735397",
          "tgn:2001564",
          "tgn:1000001",
          "tgn:7012149",
          "tgn:7007705",
          "tgn:7029392"
        ],
        "placetype": [
          "aat:300008798"
        ],
        "id": 2735397,
        "name:xx": "Twin Buttes"
      }
    },
    {
      "geometry": {
        "type": "Point",
        "coordinates": [
          -101.7,
          46.8333
        ]
      },
      "type": "Feature",
      "properties": {
        "hierarchy": [
          "tgn:2735398",
          "tgn:1000001",
          "tgn:2001586",
          "tgn:7012149",
          "tgn:7007705",
          "tgn:7029392"
        ],
        "placetype": [
          "aat:300008798"
        ],
        "id": 2735398,
        "name:xx": "Twin Buttes"
      }
    },
    {
      "geometry": {
        "type": "Point",
        "coordinates": [
          -101.4667,
          48.1167
        ]
      },
      "type": "Feature",
      "properties": {
        "hierarchy": [
          "tgn:2735399",
          "tgn:1000001",
          "tgn:7012149",
          "tgn:2001607",
          "tgn:7007705",
          "tgn:7029392"
        ],
        "placetype": [
          "aat:300008798"
        ],
        "id": 2735399,
        "name:xx": "Twin Buttes"
      }
    }
  ]
}
