{
  "geometry": {
    "type": "Point",
    "coordinates": [
      -80.1167,
      34.5833
    ]
  },
  "type": "Feature",
  "properties": {
    "hierarchy": [
      "tgn:2401970",
      "tgn:1000001",
      "tgn:2001737",
      "tgn:7012149",
      "tgn:7007712",
      "tgn:7029392"
    ],
    "placetype": [
      "aat:300008798"
    ],
    "id": 2401970,
    "name:xx": "Horseshoe Mountain"
  }
}
