{
  "geometry": {
    "type": "Point",
    "coordinates": [
      -71.4333,
      42.1833
    ]
  },
  "type": "Feature",
  "properties": {
    "hierarchy": [
      "tgn:2507080",
      "tgn:1000001",
      "tgn:1002665",
      "tgn:7012149",
      "tgn:7007517",
      "tgn:7029392"
    ],
    "placetype": [
      "aat:300008347"
    ],
    "id": 2507080,
    "name:xx": "Metcalf"
  }
}
