{
  "geometry": {
    "type": "Point",
    "coordinates": [
      -77.5667,
      40.6167
    ]
  },
  "type": "Feature",
  "properties": {
    "hierarchy": [
      "tgn:2390476",
      "tgn:1000001",
      "tgn:7012149",
      "tgn:1002669",
      "tgn:7007710",
      "tgn:7029392"
    ],
    "placetype": [
      "aat:300008746"
    ],
    "id": 2390476,
    "name:xx": "Highland Park Cave"
  }
}
