{
  "geometry": {
    "type": "Point",
    "coordinates": [
      74.801964,
      32.4964
    ]
  },
  "type": "Feature",
  "properties": {
    "hierarchy": [
      "tgn:7564962",
      "tgn:1000004",
      "tgn:7000198",
      "tgn:7000799",
      "tgn:7029392"
    ],
    "placetype": [
      "aat:300008347"
    ],
    "name:en": "Kadwāl",
    "id": 7564962
  }
}
