{
  "geometry": {
    "type": "Point",
    "coordinates": [
      -94.0333,
      33.2667
    ]
  },
  "type": "Feature",
  "properties": {
    "hierarchy": [
      "tgn:2369172",
      "tgn:1000001",
      "tgn:7016172",
      "tgn:7012149",
      "tgn:2000150",
      "tgn:7029392"
    ],
    "placetype": [
      "aat:300266640"
    ],
    "id": 2369172,
    "name:xx": "Gum Ridge"
  }
}
