{
  "geometry": {
    "type": "Point",
    "coordinates": [
      75.926232,
      30.865254
    ]
  },
  "type": "Feature",
  "properties": {
    "hierarchy": [
      "tgn:7549435",
      "tgn:1000004",
      "tgn:7000198",
      "tgn:7016883",
      "tgn:7029392"
    ],
    "placetype": [
      "aat:300007783"
    ],
    "name:en": "Dhandāri Kalān",
    "id": 7549435
  }
}
