{
  "geometry": {
    "type": "Point",
    "coordinates": [
      -87.0167,
      39.95
    ]
  },
  "type": "Feature",
  "properties": {
    "hierarchy": [
      "tgn:2670700",
      "tgn:1000001",
      "tgn:7012149",
      "tgn:2000547",
      "tgn:7007252",
      "tgn:7029392"
    ],
    "placetype": [
      "aat:300008699"
    ],
    "id": 2670700,
    "name:xx": "Smith Branch"
  }
}
