{
  "geometry": {
    "type": "Point",
    "coordinates": [
      -90.2333,
      34.15
    ]
  },
  "type": "Feature",
  "properties": {
    "hierarchy": [
      "tgn:2415229",
      "tgn:1000001",
      "tgn:7012149",
      "tgn:2001145",
      "tgn:7007522",
      "tgn:7029392"
    ],
    "placetype": [
      "aat:300008680"
    ],
    "id": 2415229,
    "name:xx": "Island Lake"
  }
}
