{
  "geometry": {
    "type": "Point",
    "coordinates": [
      103.55,
      13.75
    ]
  },
  "type": "Feature",
  "properties": {
    "hierarchy": [
      "tgn:1066405",
      "tgn:1000004",
      "tgn:7024193",
      "tgn:1000109",
      "tgn:7029392"
    ],
    "placetype": [
      "aat:300008347"
    ],
    "id": 1066405,
    "name:xx": "Phumĭ Moŭng"
  }
}
