{
  "geometry": {
    "type": "Point",
    "coordinates": [
      152.5833,
      -27.4667
    ]
  },
  "type": "Feature",
  "properties": {
    "hierarchy": [
      "tgn:1097417",
      "tgn:7000490",
      "tgn:1000006",
      "tgn:7001830",
      "tgn:7029392"
    ],
    "placetype": [
      "aat:300008347"
    ],
    "id": 1097417,
    "name:xx": "Lowood"
  }
}
