{
  "geometry": {
    "type": "Point",
    "coordinates": [
      -77.9333,
      37.5667
    ]
  },
  "type": "Feature",
  "properties": {
    "hierarchy": [
      "tgn:2675643",
      "tgn:1000001",
      "tgn:7012149",
      "tgn:2002181",
      "tgn:7007919",
      "tgn:7029392"
    ],
    "placetype": [
      "aat:300008706"
    ],
    "id": 2675643,
    "name:xx": "Solomons Creek"
  }
}
