{
  "geometry": {
    "type": "Point",
    "coordinates": [
      -123.5333,
      39.4833
    ]
  },
  "type": "Feature",
  "properties": {
    "hierarchy": [
      "tgn:2286071",
      "tgn:1000001",
      "tgn:7012149",
      "tgn:7007157",
      "tgn:2000185",
      "tgn:7029392"
    ],
    "placetype": [
      "aat:300008706"
    ],
    "id": 2286071,
    "name:xx": "Dewarren Creek"
  }
}
