{
  "geometry": {
    "type": "Point",
    "coordinates": [
      -82.2167,
      29.4333
    ]
  },
  "type": "Feature",
  "properties": {
    "hierarchy": [
      "tgn:2020242",
      "tgn:1000001",
      "tgn:7012149",
      "tgn:1002631",
      "tgn:7007240",
      "tgn:7029392"
    ],
    "placetype": [
      "aat:300008347"
    ],
    "id": 2020242,
    "name:xx": "McIntosh"
  }
}
