{
  "geometry": {
    "type": "Point",
    "coordinates": [
      -93.4833,
      30.6667
    ]
  },
  "type": "Feature",
  "properties": {
    "hierarchy": [
      "tgn:2604662",
      "tgn:1000001",
      "tgn:2000859",
      "tgn:7012149",
      "tgn:7007256",
      "tgn:7029392"
    ],
    "placetype": [
      "aat:300008699"
    ],
    "id": 2604662,
    "name:xx": "Raccoon Branch"
  }
}
