{
  "geometry": {
    "type": "Point",
    "coordinates": [
      79.11741,
      26.796174
    ]
  },
  "type": "Feature",
  "properties": {
    "hierarchy": [
      "tgn:7562194",
      "tgn:1000004",
      "tgn:7000198",
      "tgn:7016722",
      "tgn:7029392"
    ],
    "placetype": [
      "aat:300008699"
    ],
    "name:en": "Khāki Nāla",
    "id": 7562194
  }
}
