{
  "geometry": {
    "type": "Point",
    "coordinates": [
      -82.1167,
      41.0333
    ]
  },
  "type": "Feature",
  "properties": {
    "hierarchy": [
      "tgn:2080006",
      "tgn:1000001",
      "tgn:7012149",
      "tgn:1002654",
      "tgn:7007706",
      "tgn:7029392"
    ],
    "placetype": [
      "aat:300387016"
    ],
    "id": 2080006,
    "name:xx": "Homer"
  }
}
