{
  "type": "FeatureCollection",
  "features": [
    {
      "geometry": {
        "type": "Point",
        "coordinates": [
          -4.616667,
          36.533333
        ]
      },
      "type": "Feature",
      "properties": {
        "hierarchy": [
          "tgn:4004127",
          "tgn:7002758",
          "tgn:7002830",
          "tgn:1000003",
          "tgn:1000095",
          "tgn:7029392"
        ],
        "placetype": [
          "aat:300008347"
        ],
        "id": 4004127,
        "name:xx": "Fuengirola"
      }
    },
    {
      "geometry": {
        "type": "Point",
        "coordinates": [
          -2.066667,
          39.233333
        ]
      },
      "type": "Feature",
      "properties": {
        "hierarchy": [
          "tgn:4004128",
          "tgn:7002803",
          "tgn:1001647",
          "tgn:1000003",
          "tgn:1000095",
          "tgn:7029392"
        ],
        "placetype": [
          "aat:300008347"
        ],
        "id": 4004128,
        "name:xx": "Fuensanta"
      }
    },
    {
      "geometry": {
        "type": "Point",
        "coordinates": [
          -5.033333,
          38.416667
        ]
      },
      "type": "Feature",
      "properties": {
        "hierarchy": [
          "tgn:4004129",
          "tgn:7002758",
          "tgn:7002817",
          "tgn:1000003",
          "tgn:1000095",
          "tgn:7029392"
        ],
        "placetype": [
          "aat:300008347"
        ],
        "id": 4004129,
        "name:xx": "Fuente la Lancha"
      }
    }
  ]
}
