{
  "geometry": {
    "type": "Point",
    "coordinates": [
      -92.6333,
      40.9667
    ]
  },
  "type": "Feature",
  "properties": {
    "hierarchy": [
      "tgn:2154131",
      "tgn:1000001",
      "tgn:7012149",
      "tgn:2000650",
      "tgn:7007253",
      "tgn:7029392"
    ],
    "placetype": [
      "aat:300008706"
    ],
    "id": 2154131,
    "name:xx": "Bear Creek"
  }
}
