{
  "geometry": {
    "type": "Point",
    "coordinates": [
      -83.4667,
      35.1833
    ]
  },
  "type": "Feature",
  "properties": {
    "hierarchy": [
      "tgn:2145517",
      "tgn:1000001",
      "tgn:7012149",
      "tgn:2001515",
      "tgn:7007709",
      "tgn:7029392"
    ],
    "placetype": [
      "aat:300008761"
    ],
    "id": 2145517,
    "name:xx": "Baldwin Cove"
  }
}
