{
  "geometry": {
    "type": "Point",
    "coordinates": [
      -60.1167,
      -3.6333
    ]
  },
  "type": "Feature",
  "properties": {
    "hierarchy": [
      "tgn:1117180",
      "tgn:1001826",
      "tgn:1000047",
      "tgn:7002456",
      "tgn:1000002",
      "tgn:7029392"
    ],
    "placetype": [
      "aat:300008680"
    ],
    "id": 1117180,
    "name:xx": "Mamori, Lago"
  }
}
