{
  "geometry": {
    "type": "Point",
    "coordinates": [
      -82.9833,
      35.9333
    ]
  },
  "type": "Feature",
  "properties": {
    "hierarchy": [
      "tgn:2353704",
      "tgn:1000001",
      "tgn:7012149",
      "tgn:2001851",
      "tgn:7007825",
      "tgn:7029392"
    ],
    "placetype": [
      "aat:300266640"
    ],
    "id": 2353704,
    "name:xx": "Gold Mine Ridge"
  }
}
