{
  "geometry": {
    "type": "Point",
    "coordinates": [
      -111.4833,
      35.35
    ]
  },
  "type": "Feature",
  "properties": {
    "hierarchy": [
      "tgn:2430871",
      "tgn:1000001",
      "tgn:7006451",
      "tgn:2000092",
      "tgn:7012149",
      "tgn:7029392"
    ],
    "placetype": [
      "aat:300008701"
    ],
    "id": 2430871,
    "name:xx": "Kanaa Wash"
  }
}
