{
  "geometry": {
    "type": "Point",
    "coordinates": [
      76.9833,
      28.65
    ]
  },
  "type": "Feature",
  "properties": {
    "hierarchy": [
      "tgn:1004364",
      "tgn:1000004",
      "tgn:7000201",
      "tgn:7000198",
      "tgn:7029392"
    ],
    "placetype": [
      "aat:300008347",
      "aat:300000745"
    ],
    "name:en": "Dichāon Kalān",
    "id": 1004364
  }
}
