{
  "geometry": {
    "type": "Point",
    "coordinates": [
      -81.95,
      36.25
    ]
  },
  "type": "Feature",
  "properties": {
    "hierarchy": [
      "tgn:2461301",
      "tgn:1000001",
      "tgn:7012149",
      "tgn:7007825",
      "tgn:7029392"
    ],
    "placetype": [
      "aat:300008798"
    ],
    "id": 2461301,
    "name:xx": "Little Stone Mountain"
  }
}
