{
  "geometry": {
    "type": "Point",
    "coordinates": [
      -109.5167,
      31.6333
    ]
  },
  "type": "Feature",
  "properties": {
    "hierarchy": [
      "tgn:2349061",
      "tgn:1000001",
      "tgn:7006451",
      "tgn:2000091",
      "tgn:7012149",
      "tgn:7029392"
    ],
    "placetype": [
      "aat:300008761"
    ],
    "id": 2349061,
    "name:xx": "Gila Monster Canyon"
  }
}
