{
  "geometry": {
    "type": "Point",
    "coordinates": [
      -87.6833,
      38.45
    ]
  },
  "type": "Feature",
  "properties": {
    "hierarchy": [
      "tgn:2561100",
      "tgn:1000001",
      "tgn:7012149",
      "tgn:2000545",
      "tgn:7007252",
      "tgn:7029392"
    ],
    "placetype": [
      "aat:300008347"
    ],
    "id": 2561100,
    "name:xx": "Orrville"
  }
}
