{
  "geometry": {
    "type": "Point",
    "coordinates": [
      -82.6667,
      28.4333
    ]
  },
  "type": "Feature",
  "properties": {
    "hierarchy": [
      "tgn:2369443",
      "tgn:1000001",
      "tgn:1002473",
      "tgn:7012149",
      "tgn:7007240",
      "tgn:7029392"
    ],
    "placetype": [
      "aat:300008850"
    ],
    "id": 2369443,
    "name:xx": "Gun Point"
  }
}
