{
  "geometry": {
    "type": "Point",
    "coordinates": [
      -98.4667,
      42.9333
    ]
  },
  "type": "Feature",
  "properties": {
    "hierarchy": [
      "tgn:2556486",
      "tgn:1000001",
      "tgn:2001323",
      "tgn:7012149",
      "tgn:7007525",
      "tgn:7029392"
    ],
    "placetype": [
      "aat:300008798"
    ],
    "id": 2556486,
    "name:xx": "Old Baldy"
  }
}
