{
  "geometry": {
    "type": "Point",
    "coordinates": [
      -106.7333,
      42.5833
    ]
  },
  "type": "Feature",
  "properties": {
    "hierarchy": [
      "tgn:2528444",
      "tgn:1000001",
      "tgn:7012149",
      "tgn:2002377",
      "tgn:7007923",
      "tgn:7029392"
    ],
    "placetype": [
      "aat:300008761"
    ],
    "id": 2528444,
    "name:xx": "Mowry Draw"
  }
}
