{
  "geometry": {
    "type": "Point",
    "coordinates": [
      31.179,
      31.050694
    ]
  },
  "type": "Feature",
  "properties": {
    "hierarchy": [
      "tgn:7530977",
      "tgn:7001242",
      "tgn:7016833",
      "tgn:7001312",
      "tgn:7029392"
    ],
    "placetype": [
      "aat:300006075"
    ],
    "name:en": "Baḩr al Mallāḩ",
    "id": 7530977
  }
}
