{
  "geometry": {
    "type": "Point",
    "coordinates": [
      -58.1833,
      -34.7833
    ]
  },
  "type": "Feature",
  "properties": {
    "hierarchy": [
      "tgn:1019864",
      "tgn:1001160",
      "tgn:7006477",
      "tgn:1000002",
      "tgn:7029392"
    ],
    "placetype": [
      "aat:300008347"
    ],
    "id": 1019864,
    "name:xx": "Plátanos"
  }
}
