{
  "type": "FeatureCollection",
  "features": [
    {
      "geometry": {
        "type": "Point",
        "coordinates": [
          31.366479,
          31.345259
        ]
      },
      "type": "Feature",
      "properties": {
        "hierarchy": [
          "tgn:7541030",
          "tgn:7001242",
          "tgn:1001059",
          "tgn:7016833",
          "tgn:7029392"
        ],
        "placetype": [
          "aat:300006075"
        ],
        "id": 7541030,
        "name:xx": "Tur'at as Satāmūnī"
      }
    },
    {
      "geometry": {
        "type": "Point",
        "coordinates": [
          31.33164,
          31.347733
        ]
      },
      "type": "Feature",
      "properties": {
        "hierarchy": [
          "tgn:7541031",
          "tgn:7001242",
          "tgn:1001059",
          "tgn:7016833",
          "tgn:7029392"
        ],
        "placetype": [
          "aat:300008347"
        ],
        "id": 7541031,
        "name:xx": "Qaryat Jālyah al Ūlá"
      }
    },
    {
      "geometry": {
        "type": "Point",
        "coordinates": [
          31.219698,
          31.364279
        ]
      },
      "type": "Feature",
      "properties": {
        "hierarchy": [
          "tgn:7541032",
          "tgn:7001242",
          "tgn:7016833",
          "tgn:7029392"
        ],
        "placetype": [
          "aat:300006075"
        ],
        "id": 7541032,
        "name:xx": "Tur'at al Işlāḩ"
      }
    },
    {
      "geometry": {
        "type": "Point",
        "coordinates": [
          31.472387,
          31.335321
        ]
      },
      "type": "Feature",
      "properties": {
        "hierarchy": [
          "tgn:7541033",
          "tgn:7001242",
          "tgn:7016833",
          "tgn:7029392"
        ],
        "placetype": [
          "aat:300006075"
        ],
        "id": 7541033,
        "name:xx": "Tur'at al Mawārith"
      }
    },
    {
      "geometry": {
        "type": "Point",
        "coordinates": [
          31.463186,
          31.361158
        ]
      },
      "type": "Feature",
      "properties": {
        "hierarchy": [
          "tgn:7541034",
          "tgn:7001242",
          "tgn:1001059",
          "tgn:7016833",
          "tgn:7029392"
        ],
        "placetype": [
          "aat:300008347"
        ],
        "id": 7541034,
        "name:xx": "'Izbat al Quţn aş Şaghīrah"
      }
    },
    {
      "geometry": {
        "type": "Point",
        "coordinates": [
          31.459072,
          31.353756
        ]
      },
      "type": "Feature",
      "properties": {
        "hierarchy": [
          "tgn:7541035",
          "tgn:7001242",
          "tgn:1001059",
          "tgn:7016833",
          "tgn:7029392"
        ],
        "placetype": [
          "aat:300008347"
        ],
        "id": 7541035,
        "name:xx": "'Izbat al Quţn"
      }
    },
    {
      "geometry": {
        "type": "Point",
        "coordinates": [
          31.362441,
          31.27586
        ]
      },
      "type": "Feature",
      "properties": {
        "hierarchy": [
          "tgn:7541036",
          "tgn:7001242",
          "tgn:1001059",
          "tgn:7016833",
          "tgn:7029392"
        ],
        "placetype": [
          "aat:300006075"
        ],
        "id": 7541036,
        "name:xx": "Tur'at ash Shawāmī"
      }
    },
    {
      "geometry": {
        "type": "Point",
        "coordinates": [
          31.441884,
          31.363169
        ]
      },
      "type": "Feature",
      "properties": {
        "hierarchy": [
          "tgn:7541037",
          "tgn:7001242",
          "tgn:1001059",
          "tgn:7016833",
          "tgn:7029392"
        ],
        "placetype": [
          "aat:300008347"
        ],
        "id": 7541037,
        "name:xx": "'Izbat Qā'im al 'Abd"
      }
    },
    {
      "geometry": {
        "type": "Point",
        "coordinates": [
          31.423186,
          31.36199
        ]
      },
      "type": "Feature",
      "properties": {
        "hierarchy": [
          "tgn:7541038",
          "tgn:7001242",
          "tgn:1001059",
          "tgn:7016833",
          "tgn:7029392"
        ],
        "placetype": [
          "aat:300008347"
        ],
        "id": 7541038,
        "name:xx": "'Izbat Mubārak"
      }
    },
    {
      "geometry": {
        "type": "Point",
        "coordinates": [
          30.787846,
          29.454194
        ]
      },
      "type": "Feature",
      "properties": {
        "hierarchy": [
          "tgn:7541039",
          "tgn:7001242",
          "tgn:7001105",
          "tgn:7016833",
          "tgn:7029392"
        ],
        "placetype": [
          "aat:300008347"
        ],
        "name:en": "'Izbat Muḩammad Yūsif",
        "id": 7541039
      }
    }
  ]
}
