{
  "geometry": {
    "type": "Point",
    "coordinates": [
      -128.5333,
      52.5833
    ]
  },
  "type": "Feature",
  "properties": {
    "hierarchy": [
      "tgn:1013587",
      "tgn:7005735",
      "tgn:7005685",
      "tgn:1000001",
      "tgn:1009314",
      "tgn:7029392"
    ],
    "placetype": [
      "aat:300008347"
    ],
    "id": 1013587,
    "name:xx": "Klemtu"
  }
}
