{
  "geometry": {
    "type": "Point",
    "coordinates": [
      -78.4333,
      38.5167
    ]
  },
  "type": "Feature",
  "properties": {
    "hierarchy": [
      "tgn:2169600",
      "tgn:1000001",
      "tgn:7012149",
      "tgn:2002172",
      "tgn:7007919",
      "tgn:7029392"
    ],
    "placetype": [
      "aat:300008347"
    ],
    "id": 2169600,
    "name:xx": "Big Meadows"
  }
}
