{
  "geometry": {
    "type": "Point",
    "coordinates": [
      127.2667,
      45.1167
    ]
  },
  "type": "Feature",
  "properties": {
    "hierarchy": [
      "tgn:1067941",
      "tgn:1000004",
      "tgn:1001290",
      "tgn:1000111",
      "tgn:7029392"
    ],
    "placetype": [
      "aat:300008347"
    ],
    "id": 1067941,
    "name:xx": "Erdaohezi"
  }
}
