{
  "geometry": {
    "type": "Point",
    "coordinates": [
      -122.9833,
      44.3333
    ]
  },
  "type": "Feature",
  "properties": {
    "hierarchy": [
      "tgn:2288146",
      "tgn:1000001",
      "tgn:7012149",
      "tgn:2001717",
      "tgn:7007708",
      "tgn:7029392"
    ],
    "placetype": [
      "aat:300008761"
    ],
    "id": 2288146,
    "name:xx": "Dinwiddie Valley"
  }
}
