{
  "geometry": {
    "type": "Point",
    "coordinates": [
      32.783333,
      26.083333
    ]
  },
  "type": "Feature",
  "properties": {
    "hierarchy": [
      "tgn:7521530",
      "tgn:7001242",
      "tgn:7016833",
      "tgn:7000123",
      "tgn:7029392"
    ],
    "placetype": [
      "aat:300007783"
    ],
    "name:en": "Maḩaţţat al Ashrāf",
    "id": 7521530
  }
}
