{
  "type": "FeatureCollection",
  "features": [
    {
      "geometry": {
        "type": "Point",
        "coordinates": [
          -80.1667,
          34.6333
        ]
      },
      "type": "Feature",
      "properties": {
        "hierarchy": [
          "tgn:2217540",
          "tgn:1000001",
          "tgn:2001737",
          "tgn:7012149",
          "tgn:7007712",
          "tgn:7029392"
        ],
        "placetype": [
          "aat:300008347"
        ],
        "id": 2217540,
        "name:xx": "Campbell Crossroads"
      }
    },
    {
      "geometry": {
        "type": "Point",
        "coordinates": [
          -101.6,
          44.8333
        ]
      },
      "type": "Feature",
      "properties": {
        "hierarchy": [
          "tgn:2217541",
          "tgn:1000001",
          "tgn:7012149",
          "tgn:2001836",
          "tgn:7007713",
          "tgn:7029392"
        ],
        "placetype": [
          "aat:300006191"
        ],
        "id": 2217541,
        "name:xx": "Campbell Dam"
      }
    },
    {
      "geometry": {
        "type": "Point",
        "coordinates": [
          -91.2333,
          35.6833
        ]
      },
      "type": "Feature",
      "properties": {
        "hierarchy": [
          "tgn:2217542",
          "tgn:1000001",
          "tgn:7016172",
          "tgn:7012149",
          "tgn:2000138",
          "tgn:7029392"
        ],
        "placetype": [
          "aat:300006075"
        ],
        "id": 2217542,
        "name:xx": "Campbell Ditch"
      }
    },
    {
      "geometry": {
        "type": "Point",
        "coordinates": [
          -119.4333,
          36.7
        ]
      },
      "type": "Feature",
      "properties": {
        "hierarchy": [
          "tgn:2217543",
          "tgn:1000001",
          "tgn:7012149",
          "tgn:1002392",
          "tgn:7007157",
          "tgn:7029392"
        ],
        "placetype": [
          "aat:300006075"
        ],
        "id": 2217543,
        "name:xx": "Campbell Ditch"
      }
    },
    {
      "geometry": {
        "type": "Point",
        "coordinates": [
          -106.95,
          40.65
        ]
      },
      "type": "Feature",
      "properties": {
        "hierarchy": [
          "tgn:2217544",
          "tgn:1000001",
          "tgn:7012149",
          "tgn:7007158",
          "tgn:2000245",
          "tgn:7029392"
        ],
        "placetype": [
          "aat:300006075"
        ],
        "id": 2217544,
        "name:xx": "Campbell Ditch"
      }
    },
    {
      "geometry": {
        "type": "Point",
        "coordinates": [
          -107,
          38.7
        ]
      },
      "type": "Feature",
      "properties": {
        "hierarchy": [
          "tgn:2217545",
          "tgn:1000001",
          "tgn:7012149",
          "tgn:2000217",
          "tgn:7007158",
          "tgn:7029392"
        ],
        "placetype": [
          "aat:300006075"
        ],
        "id": 2217545,
        "name:xx": "Campbell Ditch"
      }
    },
    {
      "geometry": {
        "type": "Point",
        "coordinates": [
          -112.1,
          43.5
        ]
      },
      "type": "Feature",
      "properties": {
        "hierarchy": [
          "tgn:2217546",
          "tgn:1000001",
          "tgn:7012149",
          "tgn:7007250",
          "tgn:7029392"
        ],
        "placetype": [
          "aat:300006075"
        ],
        "id": 2217546,
        "name:xx": "Campbell Ditch"
      }
    },
    {
      "geometry": {
        "type": "Point",
        "coordinates": [
          -86.0833,
          40.2833
        ]
      },
      "type": "Feature",
      "properties": {
        "hierarchy": [
          "tgn:2217547",
          "tgn:1000001",
          "tgn:7012149",
          "tgn:1002947",
          "tgn:7007252",
          "tgn:7029392"
        ],
        "placetype": [
          "aat:300006075"
        ],
        "id": 2217547,
        "name:xx": "Campbell Ditch"
      }
    },
    {
      "geometry": {
        "type": "Point",
        "coordinates": [
          -85.9833,
          39.5833
        ]
      },
      "type": "Feature",
      "properties": {
        "hierarchy": [
          "tgn:2217548",
          "tgn:1000001",
          "tgn:7012149",
          "tgn:1002525",
          "tgn:7007252",
          "tgn:7029392"
        ],
        "placetype": [
          "aat:300006075"
        ],
        "id": 2217548,
        "name:xx": "Campbell Ditch"
      }
    },
    {
      "geometry": {
        "type": "Point",
        "coordinates": [
          -86.3167,
          40.1167
        ]
      },
      "type": "Feature",
      "properties": {
        "hierarchy": [
          "tgn:2217549",
          "tgn:1000001",
          "tgn:1002188",
          "tgn:7012149",
          "tgn:7007252",
          "tgn:7029392"
        ],
        "placetype": [
          "aat:300006075"
        ],
        "id": 2217549,
        "name:xx": "Campbell Ditch"
      }
    }
  ]
}
