{
  "geometry": {
    "type": "Point",
    "coordinates": [
      145.1667,
      -37.8167
    ]
  },
  "type": "Feature",
  "properties": {
    "hierarchy": [
      "tgn:1097835",
      "tgn:7000490",
      "tgn:1000006",
      "tgn:7006238",
      "tgn:7029392"
    ],
    "placetype": [
      "aat:300008347",
      "aat:300008389"
    ],
    "id": 1097835,
    "name:xx": "Nunawading"
  }
}
