{
  "geometry": {
    "type": "Point",
    "coordinates": [
      -77.7667,
      45.5167
    ]
  },
  "type": "Feature",
  "properties": {
    "hierarchy": [
      "tgn:1115820",
      "tgn:7005685",
      "tgn:1000001",
      "tgn:7013154",
      "tgn:7029392"
    ],
    "placetype": [
      "aat:300008680"
    ],
    "id": 1115820,
    "name:xx": "Carson Lake"
  }
}
