{
  "geometry": {
    "type": "Point",
    "coordinates": [
      -92.6833,
      33.75
    ]
  },
  "type": "Feature",
  "properties": {
    "hierarchy": [
      "tgn:2646652",
      "tgn:1000001",
      "tgn:7016172",
      "tgn:7012149",
      "tgn:2000156",
      "tgn:7029392"
    ],
    "placetype": [
      "aat:300008697"
    ],
    "id": 2646652,
    "name:xx": "Scale Springs"
  }
}
