{
  "geometry": {
    "type": "Point",
    "coordinates": [
      29.983611,
      31.2375
    ]
  },
  "type": "Feature",
  "properties": {
    "hierarchy": [
      "tgn:7529061",
      "tgn:7001242",
      "tgn:7016833",
      "tgn:1001079",
      "tgn:7029392"
    ],
    "placetype": [
      "aat:300387200"
    ],
    "name:en": "Taftīsh as Suyūf",
    "id": 7529061
  }
}
