{
  "geometry": {
    "type": "Point",
    "coordinates": [
      113.8667,
      29.3833
    ]
  },
  "type": "Feature",
  "properties": {
    "hierarchy": [
      "tgn:1067551",
      "tgn:1000004",
      "tgn:7002078",
      "tgn:1000111",
      "tgn:7029392"
    ],
    "placetype": [
      "aat:300008347"
    ],
    "id": 1067551,
    "name:xx": "Dashaping"
  }
}
