{
  "type": "FeatureCollection",
  "features": [
    {
      "geometry": {
        "type": "Point",
        "coordinates": [
          120.752215,
          23.88246
        ]
      },
      "type": "Feature",
      "properties": {
        "hierarchy": [
          "tgn:7488541",
          "tgn:7488858",
          "tgn:1000004",
          "tgn:1000141",
          "tgn:7029392"
        ],
        "placetype": [
          "aat:300008777",
          "aat:300008795"
        ],
        "id": 7488541,
        "name:xx": "Guanyin Shan"
      }
    },
    {
      "geometry": {
        "type": "Point",
        "coordinates": [
          121.358876,
          23.391864
        ]
      },
      "type": "Feature",
      "properties": {
        "hierarchy": [
          "tgn:7488544",
          "tgn:7001010",
          "tgn:1000004",
          "tgn:1000141",
          "tgn:7029392"
        ],
        "placetype": [
          "aat:300008777"
        ],
        "id": 7488544,
        "name:xx": "Guanyin Shan"
      }
    },
    {
      "geometry": {
        "type": "Point",
        "coordinates": [
          120.377894,
          23.004232
        ]
      },
      "type": "Feature",
      "properties": {
        "hierarchy": [
          "tgn:7488545",
          "tgn:1000004",
          "tgn:7490934",
          "tgn:1000141",
          "tgn:7029392"
        ],
        "placetype": [
          "aat:300008777"
        ],
        "id": 7488545,
        "name:xx": "Guanyin Shan"
      }
    },
    {
      "geometry": {
        "type": "Point",
        "coordinates": [
          120.37353,
          22.727491
        ]
      },
      "type": "Feature",
      "properties": {
        "hierarchy": [
          "tgn:7488546",
          "tgn:7001004",
          "tgn:1000004",
          "tgn:1000141",
          "tgn:7029392"
        ],
        "placetype": [
          "aat:300008777"
        ],
        "id": 7488546,
        "name:xx": "Guanyin Shan"
      }
    },
    {
      "geometry": {
        "type": "Point",
        "coordinates": [
          120.886667,
          22.233333
        ]
      },
      "type": "Feature",
      "properties": {
        "hierarchy": [
          "tgn:7488547",
          "tgn:1000004",
          "tgn:7491221",
          "tgn:1000141",
          "tgn:7029392"
        ],
        "placetype": [
          "aat:300008798"
        ],
        "id": 7488547,
        "name:xx": "Guanyin Shan"
      }
    },
    {
      "geometry": {
        "type": "Point",
        "coordinates": [
          120.898889,
          22.230556
        ]
      },
      "type": "Feature",
      "properties": {
        "hierarchy": [
          "tgn:7488548",
          "tgn:1000004",
          "tgn:7491221",
          "tgn:1000141",
          "tgn:7029392"
        ],
        "placetype": [
          "aat:300386846"
        ],
        "id": 7488548,
        "name:xx": "Kannon, Cape"
      }
    },
    {
      "geometry": {
        "type": "Point",
        "coordinates": [
          121.116667,
          25.033333
        ]
      },
      "type": "Feature",
      "properties": {
        "hierarchy": [
          "tgn:7488549",
          "tgn:1000004",
          "tgn:7001013",
          "tgn:1000141",
          "tgn:7029392"
        ],
        "placetype": [
          "aat:300387173"
        ],
        "id": 7488549,
        "name:xx": "Guanyin Xiang"
      }
    }
  ]
}
