{
  "geometry": {
    "type": "Point",
    "coordinates": [
      -79.943,
      -4.381
    ]
  },
  "type": "Feature",
  "properties": {
    "hierarchy": [
      "tgn:1024121",
      "tgn:1001395",
      "tgn:7002561",
      "tgn:1000051",
      "tgn:1000002",
      "tgn:7029392"
    ],
    "placetype": [
      "aat:300008347"
    ],
    "id": 1024121,
    "name:xx": "Macará"
  }
}
