{
  "geometry": {
    "type": "Point",
    "coordinates": [
      -109.0833,
      37.6667
    ]
  },
  "type": "Feature",
  "properties": {
    "hierarchy": [
      "tgn:2521727",
      "tgn:1000001",
      "tgn:7012149",
      "tgn:7029392"
    ],
    "placetype": [
      "aat:300008706"
    ],
    "id": 2521727,
    "name:xx": "Monument Creek"
  }
}
