{
  "geometry": {
    "type": "Point",
    "coordinates": [
      2.55,
      48.8667
    ]
  },
  "type": "Feature",
  "properties": {
    "hierarchy": [
      "tgn:1034646",
      "tgn:1000003",
      "tgn:7002883",
      "tgn:1000070",
      "tgn:7029392"
    ],
    "placetype": [
      "aat:300008347"
    ],
    "id": 1034646,
    "name:xx": "Neuilly-sur-Marne"
  }
}
