{
  "geometry": {
    "type": "Point",
    "coordinates": [
      34.2667,
      52.5833
    ]
  },
  "type": "Feature",
  "properties": {
    "hierarchy": [
      "tgn:1055482",
      "tgn:7011551",
      "tgn:1000004",
      "tgn:7018214",
      "tgn:7002435",
      "tgn:7029392"
    ],
    "placetype": [
      "aat:300008347"
    ],
    "id": 1055482,
    "name:xx": "Kokorevka"
  }
}
