{
  "geometry": {
    "type": "Point",
    "coordinates": [
      26.916356,
      30.651101
    ]
  },
  "type": "Feature",
  "properties": {
    "hierarchy": [
      "tgn:7539643",
      "tgn:7001242",
      "tgn:7016833",
      "tgn:1001418",
      "tgn:7029392"
    ],
    "placetype": [
      "aat:300008777"
    ],
    "name:en": "Şalī'āt, Qārāt aş",
    "id": 7539643
  }
}
