{
  "geometry": {
    "type": "Point",
    "coordinates": [
      -73.2333,
      44.9167
    ]
  },
  "type": "Feature",
  "properties": {
    "hierarchy": [
      "tgn:2697514",
      "tgn:1000001",
      "tgn:1002415",
      "tgn:7012149",
      "tgn:7007828",
      "tgn:7029392"
    ],
    "placetype": [
      "aat:300008850"
    ],
    "id": 2697514,
    "name:xx": "Stony Point"
  }
}
