{
  "geometry": {
    "type": "Point",
    "coordinates": [
      -83.2167,
      38.6333
    ]
  },
  "type": "Feature",
  "properties": {
    "hierarchy": [
      "tgn:2501074",
      "tgn:1000001",
      "tgn:7012149",
      "tgn:1002877",
      "tgn:7007706",
      "tgn:7029392"
    ],
    "placetype": [
      "aat:300008347"
    ],
    "id": 2501074,
    "name:xx": "McGaw"
  }
}
