{
  "geometry": {
    "type": "Point",
    "coordinates": [
      12.75,
      51.616667
    ]
  },
  "type": "Feature",
  "properties": {
    "hierarchy": [
      "tgn:7120321",
      "tgn:1000003",
      "tgn:7003685",
      "tgn:7000084",
      "tgn:7029392"
    ],
    "placetype": [
      "aat:300004792"
    ],
    "id": 7120321,
    "name:xx": "Försterei Pechhütte"
  }
}
