{
  "geometry": {
    "type": "Point",
    "coordinates": [
      -84.3333,
      40.3333
    ]
  },
  "type": "Feature",
  "properties": {
    "hierarchy": [
      "tgn:2312520",
      "tgn:1000001",
      "tgn:7012149",
      "tgn:1002889",
      "tgn:7007706",
      "tgn:7029392"
    ],
    "placetype": [
      "aat:300006075"
    ],
    "id": 2312520,
    "name:xx": "Eilerman Ditch"
  }
}
