{
  "type": "FeatureCollection",
  "features": [
    {
      "geometry": {
        "type": "Point",
        "coordinates": [
          -108.366667,
          27.416667
        ]
      },
      "type": "Feature",
      "properties": {
        "hierarchy": [
          "tgn:7362780",
          "tgn:7005581",
          "tgn:1000001",
          "tgn:7005560",
          "tgn:7029392"
        ],
        "placetype": [
          "aat:300008347"
        ],
        "id": 7362780,
        "name:xx": "El Álamo"
      }
    },
    {
      "geometry": {
        "type": "Point",
        "coordinates": [
          -106.233333,
          27.116667
        ]
      },
      "type": "Feature",
      "properties": {
        "hierarchy": [
          "tgn:7362781",
          "tgn:7005581",
          "tgn:1000001",
          "tgn:7005560",
          "tgn:7029392"
        ],
        "placetype": [
          "aat:300008347"
        ],
        "id": 7362781,
        "name:xx": "El Alamo"
      }
    },
    {
      "geometry": {
        "type": "Point",
        "coordinates": [
          -106.116667,
          27.033333
        ]
      },
      "type": "Feature",
      "properties": {
        "hierarchy": [
          "tgn:7362782",
          "tgn:7005581",
          "tgn:1000001",
          "tgn:7005560",
          "tgn:7029392"
        ],
        "placetype": [
          "aat:300008347"
        ],
        "id": 7362782,
        "name:xx": "El Álamo"
      }
    },
    {
      "geometry": {
        "type": "Point",
        "coordinates": [
          -105.75,
          26.716667
        ]
      },
      "type": "Feature",
      "properties": {
        "hierarchy": [
          "tgn:7362783",
          "tgn:7005581",
          "tgn:1000001",
          "tgn:7005560",
          "tgn:7029392"
        ],
        "placetype": [
          "aat:300008347"
        ],
        "id": 7362783,
        "name:xx": "El Alamo"
      }
    },
    {
      "geometry": {
        "type": "Point",
        "coordinates": [
          -108.55,
          25.983333
        ]
      },
      "type": "Feature",
      "properties": {
        "hierarchy": [
          "tgn:7362785",
          "tgn:1000001",
          "tgn:7005595",
          "tgn:7005560",
          "tgn:7029392"
        ],
        "placetype": [
          "aat:300008347"
        ],
        "id": 7362785,
        "name:xx": "El Álamo"
      }
    },
    {
      "geometry": {
        "type": "Point",
        "coordinates": [
          -107.75,
          25.816667
        ]
      },
      "type": "Feature",
      "properties": {
        "hierarchy": [
          "tgn:7362786",
          "tgn:1000001",
          "tgn:7005595",
          "tgn:7005560",
          "tgn:7029392"
        ],
        "placetype": [
          "aat:300008347"
        ],
        "id": 7362786,
        "name:xx": "El Alamo"
      }
    },
    {
      "geometry": {
        "type": "Point",
        "coordinates": [
          -107.766667,
          25.5
        ]
      },
      "type": "Feature",
      "properties": {
        "hierarchy": [
          "tgn:7362787",
          "tgn:1000001",
          "tgn:7005595",
          "tgn:7005560",
          "tgn:7029392"
        ],
        "placetype": [
          "aat:300008347"
        ],
        "id": 7362787,
        "name:xx": "El Alamo"
      }
    },
    {
      "geometry": {
        "type": "Point",
        "coordinates": [
          -101.5,
          25.433333
        ]
      },
      "type": "Feature",
      "properties": {
        "hierarchy": [
          "tgn:7362788",
          "tgn:1001853",
          "tgn:1000001",
          "tgn:7005560",
          "tgn:7029392"
        ],
        "placetype": [
          "aat:300008347"
        ],
        "id": 7362788,
        "name:xx": "El Álamo"
      }
    },
    {
      "geometry": {
        "type": "Point",
        "coordinates": [
          -100.366667,
          25.4
        ]
      },
      "type": "Feature",
      "properties": {
        "hierarchy": [
          "tgn:7362789",
          "tgn:1000001",
          "tgn:7005589",
          "tgn:7005560",
          "tgn:7029392"
        ],
        "placetype": [
          "aat:300008347"
        ],
        "id": 7362789,
        "name:xx": "El Álamo"
      }
    }
  ]
}
