{
  "geometry": {
    "type": "Point",
    "coordinates": [
      -70.5167,
      44.7667
    ]
  },
  "type": "Feature",
  "properties": {
    "hierarchy": [
      "tgn:2695848",
      "tgn:1000001",
      "tgn:7012149",
      "tgn:7007515",
      "tgn:7029392"
    ],
    "placetype": [
      "aat:300008699"
    ],
    "id": 2695848,
    "name:xx": "Stockbridge Branch"
  }
}
