{
  "type": "FeatureCollection",
  "features": [
    {
      "geometry": {
        "type": "Point",
        "coordinates": [
          -91.216667,
          17.75
        ]
      },
      "type": "Feature",
      "properties": {
        "hierarchy": [
          "tgn:7372170",
          "tgn:1000001",
          "tgn:7005596",
          "tgn:7005560",
          "tgn:7029392"
        ],
        "placetype": [
          "aat:300008347"
        ],
        "id": 7372170,
        "name:xx": "La Esperanza"
      }
    },
    {
      "geometry": {
        "type": "Point",
        "coordinates": [
          -99.2,
          17.7
        ]
      },
      "type": "Feature",
      "properties": {
        "hierarchy": [
          "tgn:7372171",
          "tgn:7005585",
          "tgn:1000001",
          "tgn:7005560",
          "tgn:7029392"
        ],
        "placetype": [
          "aat:300008347"
        ],
        "id": 7372171,
        "name:xx": "La Esperanza"
      }
    },
    {
      "geometry": {
        "type": "Point",
        "coordinates": [
          -93.433333,
          17.683333
        ]
      },
      "type": "Feature",
      "properties": {
        "hierarchy": [
          "tgn:7372172",
          "tgn:1000001",
          "tgn:7005596",
          "tgn:7005560",
          "tgn:7029392"
        ],
        "placetype": [
          "aat:300008347"
        ],
        "id": 7372172,
        "name:xx": "La Esperanza"
      }
    },
    {
      "geometry": {
        "type": "Point",
        "coordinates": [
          -97.85,
          16.666667
        ]
      },
      "type": "Feature",
      "properties": {
        "hierarchy": [
          "tgn:7372173",
          "tgn:1000001",
          "tgn:7005591",
          "tgn:7005560",
          "tgn:7029392"
        ],
        "placetype": [
          "aat:300008347"
        ],
        "id": 7372173,
        "name:xx": "La Esperanza"
      }
    },
    {
      "geometry": {
        "type": "Point",
        "coordinates": [
          -93.3,
          16.4
        ]
      },
      "type": "Feature",
      "properties": {
        "hierarchy": [
          "tgn:7372174",
          "tgn:7005580",
          "tgn:1000001",
          "tgn:7005560",
          "tgn:7029392"
        ],
        "placetype": [
          "aat:300008347"
        ],
        "id": 7372174,
        "name:xx": "La Esperanza"
      }
    },
    {
      "geometry": {
        "type": "Point",
        "coordinates": [
          -92.816667,
          15.383333
        ]
      },
      "type": "Feature",
      "properties": {
        "hierarchy": [
          "tgn:7372175",
          "tgn:7005580",
          "tgn:1000001",
          "tgn:7005560",
          "tgn:7029392"
        ],
        "placetype": [
          "aat:300008347"
        ],
        "id": 7372175,
        "name:xx": "La Esperanza"
      }
    },
    {
      "geometry": {
        "type": "Point",
        "coordinates": [
          -92.416667,
          15.3
        ]
      },
      "type": "Feature",
      "properties": {
        "hierarchy": [
          "tgn:7372176",
          "tgn:7005580",
          "tgn:1000001",
          "tgn:7005560",
          "tgn:7029392"
        ],
        "placetype": [
          "aat:300008347"
        ],
        "id": 7372176,
        "name:xx": "La Esperanza"
      }
    },
    {
      "geometry": {
        "type": "Point",
        "coordinates": [
          -92.75,
          15.2
        ]
      },
      "type": "Feature",
      "properties": {
        "hierarchy": [
          "tgn:7372177",
          "tgn:7005580",
          "tgn:1000001",
          "tgn:7005560",
          "tgn:7029392"
        ],
        "placetype": [
          "aat:300008347"
        ],
        "id": 7372177,
        "name:xx": "La Esperanza"
      }
    },
    {
      "geometry": {
        "type": "Point",
        "coordinates": [
          -92.266667,
          14.933333
        ]
      },
      "type": "Feature",
      "properties": {
        "hierarchy": [
          "tgn:7372178",
          "tgn:7005580",
          "tgn:1000001",
          "tgn:7005560",
          "tgn:7029392"
        ],
        "placetype": [
          "aat:300008347"
        ],
        "id": 7372178,
        "name:xx": "La Esperanza"
      }
    },
    {
      "geometry": {
        "type": "Point",
        "coordinates": [
          -92.183333,
          14.9
        ]
      },
      "type": "Feature",
      "properties": {
        "hierarchy": [
          "tgn:7372179",
          "tgn:7005580",
          "tgn:1000001",
          "tgn:7005560",
          "tgn:7029392"
        ],
        "placetype": [
          "aat:300008347"
        ],
        "id": 7372179,
        "name:xx": "La Esperanza"
      }
    }
  ]
}
