{
  "type": "FeatureCollection",
  "features": [
    {
      "geometry": {
        "type": "Point",
        "coordinates": [
          -108.2333,
          36.85
        ]
      },
      "type": "Feature",
      "properties": {
        "hierarchy": [
          "tgn:2440770",
          "tgn:1000001",
          "tgn:7012149",
          "tgn:2001452",
          "tgn:7007566",
          "tgn:7029392"
        ],
        "placetype": [
          "aat:300008697"
        ],
        "id": 2440770,
        "name:xx": "Knight Spring"
      }
    },
    {
      "geometry": {
        "type": "Point",
        "coordinates": [
          -108.9,
          34
        ]
      },
      "type": "Feature",
      "properties": {
        "hierarchy": [
          "tgn:2440771",
          "tgn:1000001",
          "tgn:2001429",
          "tgn:7012149",
          "tgn:7007566",
          "tgn:7029392"
        ],
        "placetype": [
          "aat:300008697"
        ],
        "id": 2440771,
        "name:xx": "Knight Spring"
      }
    },
    {
      "geometry": {
        "type": "Point",
        "coordinates": [
          -104.0167,
          44.45
        ]
      },
      "type": "Feature",
      "properties": {
        "hierarchy": [
          "tgn:2440772",
          "tgn:1000001",
          "tgn:2001810",
          "tgn:7012149",
          "tgn:7007713",
          "tgn:7029392"
        ],
        "placetype": [
          "aat:300008697"
        ],
        "id": 2440772,
        "name:xx": "Knight Spring"
      }
    },
    {
      "geometry": {
        "type": "Point",
        "coordinates": [
          -84.0667,
          36
        ]
      },
      "type": "Feature",
      "properties": {
        "hierarchy": [
          "tgn:2440773",
          "tgn:1000001",
          "tgn:7012149",
          "tgn:2001883",
          "tgn:7007825",
          "tgn:7029392"
        ],
        "placetype": [
          "aat:300008697"
        ],
        "id": 2440773,
        "name:xx": "Knight Spring"
      }
    },
    {
      "geometry": {
        "type": "Point",
        "coordinates": [
          -87.7833,
          36.15
        ]
      },
      "type": "Feature",
      "properties": {
        "hierarchy": [
          "tgn:2440774",
          "tgn:1000001",
          "tgn:7012149",
          "tgn:2001879",
          "tgn:7007825",
          "tgn:7029392"
        ],
        "placetype": [
          "aat:300008697"
        ],
        "id": 2440774,
        "name:xx": "Knight Spring"
      }
    },
    {
      "geometry": {
        "type": "Point",
        "coordinates": [
          -111.5667,
          40.2167
        ]
      },
      "type": "Feature",
      "properties": {
        "hierarchy": [
          "tgn:2440775",
          "tgn:1000001",
          "tgn:7012149",
          "tgn:2002125",
          "tgn:7007827",
          "tgn:7029392"
        ],
        "placetype": [
          "aat:300008697"
        ],
        "id": 2440775,
        "name:xx": "Knight Spring"
      }
    },
    {
      "geometry": {
        "type": "Point",
        "coordinates": [
          -108.5833,
          43.6833
        ]
      },
      "type": "Feature",
      "properties": {
        "hierarchy": [
          "tgn:2440776",
          "tgn:1000001",
          "tgn:7012149",
          "tgn:2002373",
          "tgn:7007923",
          "tgn:7029392"
        ],
        "placetype": [
          "aat:300008697"
        ],
        "id": 2440776,
        "name:xx": "Knight Spring"
      }
    },
    {
      "geometry": {
        "type": "Point",
        "coordinates": [
          -108.1667,
          37.6833
        ]
      },
      "type": "Feature",
      "properties": {
        "hierarchy": [
          "tgn:2440777",
          "tgn:1000001",
          "tgn:7012149",
          "tgn:2000208",
          "tgn:7007158",
          "tgn:7029392"
        ],
        "placetype": [
          "aat:300006191"
        ],
        "id": 2440777,
        "name:xx": "Knight Spring Reservoir"
      }
    },
    {
      "geometry": {
        "type": "Point",
        "coordinates": [
          -112.8833,
          34.0333
        ]
      },
      "type": "Feature",
      "properties": {
        "hierarchy": [
          "tgn:2440778",
          "tgn:1000001",
          "tgn:7006451",
          "tgn:7012149",
          "tgn:2000103",
          "tgn:7029392"
        ],
        "placetype": [
          "aat:300006191"
        ],
        "id": 2440778,
        "name:xx": "Knight Tank"
      }
    }
  ]
}
