{
  "type": "FeatureCollection",
  "features": [
    {
      "geometry": {
        "type": "Point",
        "coordinates": [
          -96.566667,
          19.55
        ]
      },
      "type": "Feature",
      "properties": {
        "hierarchy": [
          "tgn:7388720",
          "tgn:1000001",
          "tgn:7005599",
          "tgn:7005560",
          "tgn:7029392"
        ],
        "placetype": [
          "aat:300008347"
        ],
        "id": 7388720,
        "name:xx": "Pastoría"
      }
    },
    {
      "geometry": {
        "type": "Point",
        "coordinates": [
          -102.116667,
          19.133333
        ]
      },
      "type": "Feature",
      "properties": {
        "hierarchy": [
          "tgn:7388721",
          "tgn:1000001",
          "tgn:7005590",
          "tgn:7005560",
          "tgn:7029392"
        ],
        "placetype": [
          "aat:300008347"
        ],
        "id": 7388721,
        "name:xx": "Pastoría"
      }
    },
    {
      "geometry": {
        "type": "Point",
        "coordinates": [
          -104.883333,
          27.633333
        ]
      },
      "type": "Feature",
      "properties": {
        "hierarchy": [
          "tgn:7388722",
          "tgn:7005581",
          "tgn:1000001",
          "tgn:7005560",
          "tgn:7029392"
        ],
        "placetype": [
          "aat:300008680"
        ],
        "id": 7388722,
        "name:xx": "Pastores, Laguna"
      }
    },
    {
      "geometry": {
        "type": "Point",
        "coordinates": [
          -105.116667,
          25.733333
        ]
      },
      "type": "Feature",
      "properties": {
        "hierarchy": [
          "tgn:7388723",
          "tgn:7005583",
          "tgn:1000001",
          "tgn:7005560",
          "tgn:7029392"
        ],
        "placetype": [
          "aat:300008347"
        ],
        "id": 7388723,
        "name:xx": "Pastores"
      }
    },
    {
      "geometry": {
        "type": "Point",
        "coordinates": [
          -102.933333,
          21.133333
        ]
      },
      "type": "Feature",
      "properties": {
        "hierarchy": [
          "tgn:7388724",
          "tgn:7005586",
          "tgn:1000001",
          "tgn:7005560",
          "tgn:7029392"
        ],
        "placetype": [
          "aat:300008347"
        ],
        "id": 7388724,
        "name:xx": "Pastores"
      }
    },
    {
      "geometry": {
        "type": "Point",
        "coordinates": [
          -101.05,
          20.2
        ]
      },
      "type": "Feature",
      "properties": {
        "hierarchy": [
          "tgn:7388725",
          "tgn:7005584",
          "tgn:1000001",
          "tgn:7005560",
          "tgn:7029392"
        ],
        "placetype": [
          "aat:300008347"
        ],
        "id": 7388725,
        "name:xx": "Pastores"
      }
    },
    {
      "geometry": {
        "type": "Point",
        "coordinates": [
          -103.516667,
          25.666667
        ]
      },
      "type": "Feature",
      "properties": {
        "hierarchy": [
          "tgn:7388726",
          "tgn:7005583",
          "tgn:1000001",
          "tgn:7005560",
          "tgn:7029392"
        ],
        "placetype": [
          "aat:300008347"
        ],
        "id": 7388726,
        "name:xx": "Pastor Boulix"
      }
    },
    {
      "geometry": {
        "type": "Point",
        "coordinates": [
          -100.716667,
          27.3
        ]
      },
      "type": "Feature",
      "properties": {
        "hierarchy": [
          "tgn:7388727",
          "tgn:1000001",
          "tgn:1001893",
          "tgn:7005560",
          "tgn:7029392"
        ],
        "placetype": [
          "aat:300266640"
        ],
        "id": 7388727,
        "name:xx": "Pastora, Cuesta de la"
      }
    },
    {
      "geometry": {
        "type": "Point",
        "coordinates": [
          -104.083333,
          19.7
        ]
      },
      "type": "Feature",
      "properties": {
        "hierarchy": [
          "tgn:7388728",
          "tgn:7005586",
          "tgn:1000001",
          "tgn:7005560",
          "tgn:7029392"
        ],
        "placetype": [
          "aat:300008795"
        ],
        "id": 7388728,
        "name:xx": "Pastora, Cerro la"
      }
    },
    {
      "geometry": {
        "type": "Point",
        "coordinates": [
          -107.15,
          29.866667
        ]
      },
      "type": "Feature",
      "properties": {
        "hierarchy": [
          "tgn:7388729",
          "tgn:7005581",
          "tgn:1000001",
          "tgn:7005560",
          "tgn:7029392"
        ],
        "placetype": [
          "aat:300008795"
        ],
        "id": 7388729,
        "name:xx": "Pastora, Cerro de la"
      }
    }
  ]
}
