{
  "geometry": {
    "type": "Point",
    "coordinates": [
      -114.0667,
      40.7667
    ]
  },
  "type": "Feature",
  "properties": {
    "hierarchy": [
      "tgn:2445768",
      "tgn:1000001",
      "tgn:2001411",
      "tgn:7012149",
      "tgn:7007526",
      "tgn:7029392"
    ],
    "placetype": [
      "aat:300008798"
    ],
    "id": 2445768,
    "name:xx": "Leppy Peak"
  }
}
