{
  "geometry": {
    "type": "Point",
    "coordinates": [
      -110.6333,
      44.9333
    ]
  },
  "type": "Feature",
  "properties": {
    "hierarchy": [
      "tgn:2484954",
      "tgn:1000001",
      "tgn:7012149",
      "tgn:2002379",
      "tgn:7007923",
      "tgn:7029392"
    ],
    "placetype": [
      "aat:300008761"
    ],
    "id": 2484954,
    "name:xx": "Lava Creek Canyon"
  }
}
