{
  "type": "FeatureCollection",
  "features": [
    {
      "geometry": {
        "type": "Point",
        "coordinates": [
          -104.566667,
          20.25
        ]
      },
      "type": "Feature",
      "properties": {
        "hierarchy": [
          "tgn:7440520",
          "tgn:7005586",
          "tgn:1000001",
          "tgn:7005560",
          "tgn:7029392"
        ],
        "placetype": [
          "aat:300008699"
        ],
        "id": 7440520,
        "name:xx": "Santa Bárbara"
      }
    },
    {
      "geometry": {
        "type": "Point",
        "coordinates": [
          -110.766667,
          31.233333
        ]
      },
      "type": "Feature",
      "properties": {
        "hierarchy": [
          "tgn:7440521",
          "tgn:1000001",
          "tgn:1001960",
          "tgn:7005560",
          "tgn:7029392"
        ],
        "placetype": [
          "aat:300007783"
        ],
        "id": 7440521,
        "name:xx": "Santa Bárbara"
      }
    },
    {
      "geometry": {
        "type": "Point",
        "coordinates": [
          -98.9,
          19.316667
        ]
      },
      "type": "Feature",
      "properties": {
        "hierarchy": [
          "tgn:7440522",
          "tgn:1000001",
          "tgn:1001893",
          "tgn:7005560",
          "tgn:7029392"
        ],
        "placetype": [
          "aat:300007783"
        ],
        "id": 7440522,
        "name:xx": "Santa Bárbara"
      }
    },
    {
      "geometry": {
        "type": "Point",
        "coordinates": [
          -110.766667,
          31.233333
        ]
      },
      "type": "Feature",
      "properties": {
        "hierarchy": [
          "tgn:7440523",
          "tgn:1000001",
          "tgn:1001960",
          "tgn:7005560",
          "tgn:7029392"
        ],
        "placetype": [
          "aat:300008347"
        ],
        "id": 7440523,
        "name:xx": "Santa Bárbara"
      }
    },
    {
      "geometry": {
        "type": "Point",
        "coordinates": [
          -110.883333,
          30.433333
        ]
      },
      "type": "Feature",
      "properties": {
        "hierarchy": [
          "tgn:7440525",
          "tgn:1000001",
          "tgn:1001960",
          "tgn:7005560",
          "tgn:7029392"
        ],
        "placetype": [
          "aat:300008347"
        ],
        "id": 7440525,
        "name:xx": "Santa Bárbara"
      }
    },
    {
      "geometry": {
        "type": "Point",
        "coordinates": [
          -104.7,
          29.966667
        ]
      },
      "type": "Feature",
      "properties": {
        "hierarchy": [
          "tgn:7440526",
          "tgn:7005581",
          "tgn:1000001",
          "tgn:7005560",
          "tgn:7029392"
        ],
        "placetype": [
          "aat:300008347"
        ],
        "id": 7440526,
        "name:xx": "Santa Bárbara"
      }
    },
    {
      "geometry": {
        "type": "Point",
        "coordinates": [
          -110.066667,
          29.75
        ]
      },
      "type": "Feature",
      "properties": {
        "hierarchy": [
          "tgn:7440527",
          "tgn:1000001",
          "tgn:1001960",
          "tgn:7005560",
          "tgn:7029392"
        ],
        "placetype": [
          "aat:300008347"
        ],
        "id": 7440527,
        "name:xx": "Santa Bárbara"
      }
    },
    {
      "geometry": {
        "type": "Point",
        "coordinates": [
          -109.833333,
          28.75
        ]
      },
      "type": "Feature",
      "properties": {
        "hierarchy": [
          "tgn:7440528",
          "tgn:1000001",
          "tgn:1001960",
          "tgn:7005560",
          "tgn:7029392"
        ],
        "placetype": [
          "aat:300008347"
        ],
        "id": 7440528,
        "name:xx": "Santa Bárbara"
      }
    },
    {
      "geometry": {
        "type": "Point",
        "coordinates": [
          -107.383333,
          28.433333
        ]
      },
      "type": "Feature",
      "properties": {
        "hierarchy": [
          "tgn:7440529",
          "tgn:7005581",
          "tgn:1000001",
          "tgn:7005560",
          "tgn:7029392"
        ],
        "placetype": [
          "aat:300008347"
        ],
        "id": 7440529,
        "name:xx": "Santa Bárbara"
      }
    }
  ]
}
