{
  "geometry": {
    "type": "Point",
    "coordinates": [
      38.7667,
      49.4167
    ]
  },
  "type": "Feature",
  "properties": {
    "hierarchy": [
      "tgn:1137176",
      "tgn:1000003",
      "tgn:7012067",
      "tgn:7006660",
      "tgn:7029392"
    ],
    "placetype": [
      "aat:300008347",
      "aat:300008375"
    ],
    "id": 1137176,
    "name:xx": "Aleksejev"
  }
}
