{
  "geometry": {
    "type": "Point",
    "coordinates": [
      -71.1667,
      42.1333
    ]
  },
  "type": "Feature",
  "properties": {
    "hierarchy": [
      "tgn:2235618",
      "tgn:1000001",
      "tgn:1002724",
      "tgn:7012149",
      "tgn:7007517",
      "tgn:7029392"
    ],
    "placetype": [
      "aat:300008798"
    ],
    "id": 2235618,
    "name:xx": "Chestnut Hill"
  }
}
