{
  "geometry": {
    "type": "Point",
    "coordinates": [
      -117.8167,
      36.1667
    ]
  },
  "type": "Feature",
  "properties": {
    "hierarchy": [
      "tgn:2718930",
      "tgn:1000001",
      "tgn:7012149",
      "tgn:2000183",
      "tgn:7007157",
      "tgn:7029392"
    ],
    "placetype": [
      "aat:300000390"
    ],
    "id": 2718930,
    "name:xx": "Thorndyke Mine"
  }
}
