{
  "geometry": {
    "type": "Point",
    "coordinates": [
      121.57842,
      25.02698
    ]
  },
  "type": "Feature",
  "properties": {
    "hierarchy": [
      "tgn:7496935",
      "tgn:1000004",
      "tgn:1000959",
      "tgn:1000141",
      "tgn:7029392"
    ],
    "placetype": [
      "aat:300007595"
    ],
    "id": 7496935,
    "name:xx": "Wuyin Si"
  }
}
