{
  "geometry": {
    "type": "Point",
    "coordinates": [
      -111.65,
      37.0667
    ]
  },
  "type": "Feature",
  "properties": {
    "hierarchy": [
      "tgn:2351339",
      "tgn:1000001",
      "tgn:7012149",
      "tgn:2002113",
      "tgn:7007827",
      "tgn:7029392"
    ],
    "placetype": [
      "aat:300008347"
    ],
    "id": 2351339,
    "name:xx": "Glen Canyon City"
  }
}
