{
  "geometry": {
    "type": "Point",
    "coordinates": [
      35.45,
      31.0833
    ]
  },
  "type": "Feature",
  "properties": {
    "hierarchy": [
      "tgn:1111434",
      "tgn:1002058",
      "tgn:1000004",
      "tgn:1000121",
      "tgn:7029392"
    ],
    "placetype": [
      "aat:300008773",
      "aat:300379998"
    ],
    "id": 1111434,
    "name:xx": "Ḥasā, Wādī al-"
  }
}
