{
  "geometry": {
    "type": "Point",
    "coordinates": [
      -78.4667,
      40.65
    ]
  },
  "type": "Feature",
  "properties": {
    "hierarchy": [
      "tgn:2643695",
      "tgn:1000001",
      "tgn:1002225",
      "tgn:7012149",
      "tgn:7007710",
      "tgn:7029392"
    ],
    "placetype": [
      "aat:300006191"
    ],
    "id": 2643695,
    "name:xx": "Sandy Run Reservoir"
  }
}
