{
  "geometry": {
    "type": "Point",
    "coordinates": [
      35.6333,
      31.0333
    ]
  },
  "type": "Feature",
  "properties": {
    "hierarchy": [
      "tgn:1103609",
      "tgn:1002058",
      "tgn:1000004",
      "tgn:1000121",
      "tgn:7029392"
    ],
    "placetype": [
      "aat:300008795"
    ],
    "id": 1103609,
    "name:xx": "Ḍabāb, Jabal aḍ-"
  }
}
