{
  "geometry": {
    "type": "Point",
    "coordinates": [
      -106.9833,
      41.2167
    ]
  },
  "type": "Feature",
  "properties": {
    "hierarchy": [
      "tgn:2307551",
      "tgn:1000001",
      "tgn:2002368",
      "tgn:7012149",
      "tgn:7007923",
      "tgn:7029392"
    ],
    "placetype": [
      "aat:300008706"
    ],
    "id": 2307551,
    "name:xx": "East Fork South Spring Creek"
  }
}
