{
  "geometry": {
    "type": "Point",
    "coordinates": [
      -89.9333,
      36.3333
    ]
  },
  "type": "Feature",
  "properties": {
    "hierarchy": [
      "tgn:2288902",
      "tgn:1000001",
      "tgn:7012149",
      "tgn:2001227",
      "tgn:7007523",
      "tgn:7029392"
    ],
    "placetype": [
      "aat:300006075"
    ],
    "id": 2288902,
    "name:xx": "Ditch Number 84"
  }
}
