{
  "geometry": {
    "type": "Point",
    "coordinates": [
      -107.55,
      36.6333
    ]
  },
  "type": "Feature",
  "properties": {
    "hierarchy": [
      "tgn:2283262",
      "tgn:1000001",
      "tgn:7012149",
      "tgn:2001449",
      "tgn:7007566",
      "tgn:7029392"
    ],
    "placetype": [
      "aat:300008798"
    ],
    "id": 2283262,
    "name:xx": "Delgadita Mesa"
  }
}
