{
  "type": "FeatureCollection",
  "features": [
    {
      "geometry": {
        "type": "Point",
        "coordinates": [
          35,
          24.316667
        ]
      },
      "type": "Feature",
      "properties": {
        "hierarchy": [
          "tgn:7536810",
          "tgn:7001242",
          "tgn:7001311",
          "tgn:7016833",
          "tgn:7029392"
        ],
        "placetype": [
          "aat:300006207"
        ],
        "name:en": "Bîr Kul Oteît",
        "id": 7536810
      }
    },
    {
      "geometry": {
        "type": "Point",
        "coordinates": [
          29.978979,
          31.248543
        ]
      },
      "type": "Feature",
      "properties": {
        "hierarchy": [
          "tgn:7536811",
          "tgn:7001242",
          "tgn:7016833",
          "tgn:1001079",
          "tgn:7029392"
        ],
        "placetype": [
          "aat:300007783"
        ],
        "name:en": "Victoria Station",
        "id": 7536811
      }
    },
    {
      "geometry": {
        "type": "Point",
        "coordinates": [
          34.594464,
          29.872089
        ]
      },
      "type": "Feature",
      "properties": {
        "hierarchy": [
          "tgn:7536812",
          "tgn:7001242",
          "tgn:7016833",
          "tgn:7001336",
          "tgn:7029392"
        ],
        "placetype": [
          "aat:300379998"
        ],
        "name:en": "Kulaybī, Wādī al",
        "id": 7536812
      }
    },
    {
      "geometry": {
        "type": "Point",
        "coordinates": [
          32.789857,
          29.684645
        ]
      },
      "type": "Feature",
      "properties": {
        "hierarchy": [
          "tgn:7536814",
          "tgn:7001242",
          "tgn:7016833",
          "tgn:7001336",
          "tgn:7029392"
        ],
        "placetype": [
          "aat:300379998"
        ],
        "id": 7536814,
        "name:xx": "Kuḩlī, Wādī"
      }
    },
    {
      "geometry": {
        "type": "Point",
        "coordinates": [
          31.7,
          22.4
        ]
      },
      "type": "Feature",
      "properties": {
        "hierarchy": [
          "tgn:7536815",
          "tgn:7001242",
          "tgn:7016833",
          "tgn:1001079",
          "tgn:7029392"
        ],
        "placetype": [
          "aat:300008057"
        ],
        "name:en": "'Izbat Timit",
        "id": 7536815
      }
    },
    {
      "geometry": {
        "type": "Point",
        "coordinates": [
          25.566667,
          29.183333
        ]
      },
      "type": "Feature",
      "properties": {
        "hierarchy": [
          "tgn:7536816",
          "tgn:7001242",
          "tgn:7016833",
          "tgn:1001418",
          "tgn:7029392"
        ],
        "placetype": [
          "aat:300008347"
        ],
        "name:en": "'Izbat Ţanāţī",
        "id": 7536816
      }
    },
    {
      "geometry": {
        "type": "Point",
        "coordinates": [
          31.1,
          29.05
        ]
      },
      "type": "Feature",
      "properties": {
        "hierarchy": [
          "tgn:7536817",
          "tgn:7001242",
          "tgn:7016833",
          "tgn:1001142",
          "tgn:7029392"
        ],
        "placetype": [
          "aat:300008347"
        ],
        "name:en": "'Izbat Tall Abū Nārūz",
        "id": 7536817
      }
    },
    {
      "geometry": {
        "type": "Point",
        "coordinates": [
          30.266667,
          31.066667
        ]
      },
      "type": "Feature",
      "properties": {
        "hierarchy": [
          "tgn:7536818",
          "tgn:7001242",
          "tgn:1001075",
          "tgn:7016833",
          "tgn:7029392"
        ],
        "placetype": [
          "aat:300008347"
        ],
        "name:en": "'Izbat Ţāhir Bey al Mişrī",
        "id": 7536818
      }
    },
    {
      "geometry": {
        "type": "Point",
        "coordinates": [
          30.185717,
          31.132805
        ]
      },
      "type": "Feature",
      "properties": {
        "hierarchy": [
          "tgn:7536819",
          "tgn:7001242",
          "tgn:1001075",
          "tgn:7016833",
          "tgn:7029392"
        ],
        "placetype": [
          "aat:300008347"
        ],
        "name:en": "'Izbat Şīrah",
        "id": 7536819
      }
    }
  ]
}
