{
  "geometry": {
    "type": "Point",
    "coordinates": [
      -123.5833,
      44.0667
    ]
  },
  "type": "Feature",
  "properties": {
    "hierarchy": [
      "tgn:2538194",
      "tgn:1000001",
      "tgn:7012149",
      "tgn:2001716",
      "tgn:7007708",
      "tgn:7029392"
    ],
    "placetype": [
      "aat:300008798"
    ],
    "id": 2538194,
    "name:xx": "Nelson Mountain"
  }
}
