{
  "geometry": {
    "type": "Point",
    "coordinates": [
      -68.0667,
      44.8167
    ]
  },
  "type": "Feature",
  "properties": {
    "hierarchy": [
      "tgn:2231575",
      "tgn:1000001",
      "tgn:7012149",
      "tgn:7007515",
      "tgn:7029392"
    ],
    "placetype": [
      "aat:300008680"
    ],
    "id": 2231575,
    "name:xx": "Chalk Pond"
  }
}
