{
  "geometry": {
    "type": "Point",
    "coordinates": [
      -50.6833,
      -24.9833
    ]
  },
  "type": "Feature",
  "properties": {
    "hierarchy": [
      "tgn:1136530",
      "tgn:1001925",
      "tgn:1000047",
      "tgn:7002458",
      "tgn:1000002",
      "tgn:7029392"
    ],
    "placetype": [
      "aat:300008347"
    ],
    "id": 1136530,
    "name:xx": "Ipiranga"
  }
}
