{
  "geometry": {
    "type": "Point",
    "coordinates": [
      -85.5667,
      33.4333
    ]
  },
  "type": "Feature",
  "properties": {
    "hierarchy": [
      "tgn:2771591",
      "tgn:7002659",
      "tgn:1000001",
      "tgn:7012149",
      "tgn:2000055",
      "tgn:7029392"
    ],
    "placetype": [
      "aat:300008347"
    ],
    "id": 2771591,
    "name:xx": "Wildwood"
  }
}
