{
  "geometry": {
    "type": "Point",
    "coordinates": [
      6.85,
      53.25
    ]
  },
  "type": "Feature",
  "properties": {
    "hierarchy": [
      "tgn:7270715",
      "tgn:1000003",
      "tgn:7003613",
      "tgn:7016845",
      "tgn:7029392"
    ],
    "placetype": [
      "aat:300006075"
    ],
    "name:nl": "Siddebuursterschipsloot",
    "id": 7270715
  }
}
