{
  "geometry": {
    "type": "Point",
    "coordinates": [
      7.5667,
      43.9833
    ]
  },
  "type": "Feature",
  "properties": {
    "hierarchy": [
      "tgn:7009666",
      "tgn:1000003",
      "tgn:1000070",
      "tgn:7002895",
      "tgn:7029392"
    ],
    "placetype": [
      "aat:300008347"
    ],
    "id": 7009666,
    "name:xx": "Saorge"
  }
}
