{
  "geometry": {
    "type": "Point",
    "coordinates": [
      -93.4167,
      38.6667
    ]
  },
  "type": "Feature",
  "properties": {
    "hierarchy": [
      "tgn:2316028",
      "tgn:1000001",
      "tgn:7012149",
      "tgn:2001229",
      "tgn:7007523",
      "tgn:7029392"
    ],
    "placetype": [
      "aat:300008699"
    ],
    "id": 2316028,
    "name:xx": "Elm Fork"
  }
}
