{
  "geometry": {
    "type": "Point",
    "coordinates": [
      -80.6667,
      35.9167
    ]
  },
  "type": "Feature",
  "properties": {
    "hierarchy": [
      "tgn:2214337",
      "tgn:1000001",
      "tgn:7012149",
      "tgn:2001490",
      "tgn:7007709",
      "tgn:7029392"
    ],
    "placetype": [
      "aat:300008798"
    ],
    "id": 2214337,
    "name:xx": "Calahaln Mountain"
  }
}
