{
  "geometry": {
    "type": "Point",
    "coordinates": [
      -87.6167,
      34.1833
    ]
  },
  "type": "Feature",
  "properties": {
    "hierarchy": [
      "tgn:2211213",
      "tgn:1000001",
      "tgn:7012149",
      "tgn:7029392"
    ],
    "placetype": [
      "aat:300008707"
    ],
    "id": 2211213,
    "name:xx": "Buttahatchee River"
  }
}
