{
  "type": "FeatureCollection",
  "features": [
    {
      "geometry": {
        "type": "Point",
        "coordinates": [
          -2.016667,
          50.866667
        ]
      },
      "type": "Feature",
      "properties": {
        "hierarchy": [
          "tgn:7452960",
          "tgn:7002445",
          "tgn:1000003",
          "tgn:7011961",
          "tgn:7008591",
          "tgn:7029392"
        ],
        "placetype": [
          "aat:300387502"
        ],
        "name:en": "Crichel House",
        "id": 7452960
      }
    },
    {
      "geometry": {
        "type": "Point",
        "coordinates": [
          -4.166667,
          52.133333
        ]
      },
      "type": "Feature",
      "properties": {
        "hierarchy": [
          "tgn:7452963",
          "tgn:7002443",
          "tgn:7017242",
          "tgn:1000003",
          "tgn:7008591",
          "tgn:7029392"
        ],
        "placetype": [
          "aat:300008347"
        ],
        "name:en": "Cribyn",
        "id": 7452963
      }
    },
    {
      "geometry": {
        "type": "Point",
        "coordinates": [
          -4.566667,
          52.15
        ]
      },
      "type": "Feature",
      "properties": {
        "hierarchy": [
          "tgn:7452964",
          "tgn:7002443",
          "tgn:7017242",
          "tgn:1000003",
          "tgn:7008591",
          "tgn:7029392"
        ],
        "placetype": [
          "aat:300008850"
        ],
        "name:en": "Cribach, Pen",
        "id": 7452964
      }
    },
    {
      "geometry": {
        "type": "Point",
        "coordinates": [
          -7.533333,
          54.716667
        ]
      },
      "type": "Feature",
      "properties": {
        "hierarchy": [
          "tgn:7452966",
          "tgn:7002448",
          "tgn:1000003",
          "tgn:7019208",
          "tgn:7008591",
          "tgn:7029392"
        ],
        "placetype": [
          "aat:300008347"
        ],
        "name:en": "Crew Upper",
        "id": 7452966
      }
    },
    {
      "geometry": {
        "type": "Point",
        "coordinates": [
          -7.516667,
          54.7
        ]
      },
      "type": "Feature",
      "properties": {
        "hierarchy": [
          "tgn:7452967",
          "tgn:7002448",
          "tgn:1000003",
          "tgn:7019208",
          "tgn:7008591",
          "tgn:7029392"
        ],
        "placetype": [
          "aat:300008347"
        ],
        "name:en": "Crew Lower",
        "id": 7452967
      }
    },
    {
      "geometry": {
        "type": "Point",
        "coordinates": [
          -2.4,
          53.083333
        ]
      },
      "type": "Feature",
      "properties": {
        "hierarchy": [
          "tgn:7452969",
          "tgn:7002445",
          "tgn:7008114",
          "tgn:1000003",
          "tgn:7008591",
          "tgn:7029392"
        ],
        "placetype": [
          "aat:300387502"
        ],
        "name:en": "Crewe Hall",
        "id": 7452969
      }
    }
  ]
}
