{
  "geometry": {
    "type": "Point",
    "coordinates": [
      -108.7333,
      42.7167
    ]
  },
  "type": "Feature",
  "properties": {
    "hierarchy": [
      "tgn:2379338",
      "tgn:1000001",
      "tgn:7012149",
      "tgn:2002371",
      "tgn:7007923",
      "tgn:7029392"
    ],
    "placetype": [
      "aat:300386845"
    ],
    "id": 2379338,
    "name:xx": "Harvey Basin"
  }
}
