{
  "geometry": {
    "type": "Point",
    "coordinates": [
      -89.3667,
      38.3333
    ]
  },
  "type": "Feature",
  "properties": {
    "hierarchy": [
      "tgn:2029241",
      "tgn:1000001",
      "tgn:7012149",
      "tgn:1002991",
      "tgn:7007251",
      "tgn:7029392"
    ],
    "placetype": [
      "aat:300008347"
    ],
    "id": 2029241,
    "name:xx": "Nashville"
  }
}
