{
  "geometry": {
    "type": "Point",
    "coordinates": [
      -73.7667,
      42.4667
    ]
  },
  "type": "Feature",
  "properties": {
    "hierarchy": [
      "tgn:2531677",
      "tgn:1000001",
      "tgn:7012149",
      "tgn:1002821",
      "tgn:7007568",
      "tgn:7029392"
    ],
    "placetype": [
      "aat:300008791"
    ],
    "id": 2531677,
    "name:xx": "Mull Island"
  }
}
