{
  "geometry": {
    "type": "Point",
    "coordinates": [
      32.933333,
      24.716667
    ]
  },
  "type": "Feature",
  "properties": {
    "hierarchy": [
      "tgn:7524374",
      "tgn:7001242",
      "tgn:7016833",
      "tgn:7000122",
      "tgn:7029392"
    ],
    "placetype": [
      "aat:300008791"
    ],
    "name:en": "Bisāwī, Jazīrat",
    "id": 7524374
  }
}
