{
  "geometry": {
    "type": "Point",
    "coordinates": [
      -104.9667,
      36.8833
    ]
  },
  "type": "Feature",
  "properties": {
    "hierarchy": [
      "tgn:2613279",
      "tgn:1000001",
      "tgn:2001432",
      "tgn:7012149",
      "tgn:7007566",
      "tgn:7029392"
    ],
    "placetype": [
      "aat:300008761"
    ],
    "id": 2613279,
    "name:xx": "Reed Canyon"
  }
}
