{
  "geometry": {
    "type": "Point",
    "coordinates": [
      -5.29,
      35.11
    ]
  },
  "type": "Feature",
  "properties": {
    "hierarchy": [
      "tgn:1091372",
      "tgn:7001242",
      "tgn:1000179",
      "tgn:7593695",
      "tgn:7029392"
    ],
    "placetype": [
      "aat:300008347"
    ],
    "id": 1091372,
    "name:xx": "Derdara"
  }
}
