{
  "type": "FeatureCollection",
  "features": [
    {
      "geometry": {
        "type": "Point",
        "coordinates": [
          -92.7333,
          31.8
        ]
      },
      "type": "Feature",
      "properties": {
        "hierarchy": [
          "tgn:2042190",
          "tgn:1000001",
          "tgn:7012149",
          "tgn:2000917",
          "tgn:7007256",
          "tgn:7029392"
        ],
        "placetype": [
          "aat:300008347"
        ],
        "id": 2042190,
        "name:xx": "Atlanta"
      }
    },
    {
      "geometry": {
        "type": "Point",
        "coordinates": [
          -91.1,
          29.85
        ]
      },
      "type": "Feature",
      "properties": {
        "hierarchy": [
          "tgn:2042191",
          "tgn:2000857",
          "tgn:1000001",
          "tgn:7012149",
          "tgn:7007256",
          "tgn:7029392"
        ],
        "placetype": [
          "aat:300008347",
          "aat:300387210"
        ],
        "id": 2042191,
        "name:xx": "Attakapas Landing"
      }
    },
    {
      "geometry": {
        "type": "Point",
        "coordinates": [
          -91.0667,
          30.3833
        ]
      },
      "type": "Feature",
      "properties": {
        "hierarchy": [
          "tgn:2042192",
          "tgn:1000001",
          "tgn:2000870",
          "tgn:7012149",
          "tgn:7007256",
          "tgn:7029392"
        ],
        "placetype": [
          "aat:300008347"
        ],
        "id": 2042192,
        "name:xx": "Audubon Terrace"
      }
    },
    {
      "geometry": {
        "type": "Point",
        "coordinates": [
          -91.2,
          30.1833
        ]
      },
      "type": "Feature",
      "properties": {
        "hierarchy": [
          "tgn:2042193",
          "tgn:1000001",
          "tgn:7012149",
          "tgn:2000877",
          "tgn:7007256",
          "tgn:7029392"
        ],
        "placetype": [
          "aat:300008347",
          "aat:300387210"
        ],
        "id": 2042193,
        "name:xx": "Augusta"
      }
    },
    {
      "geometry": {
        "type": "Point",
        "coordinates": [
          -91.3167,
          29.7167
        ]
      },
      "type": "Feature",
      "properties": {
        "hierarchy": [
          "tgn:2042194",
          "tgn:1000001",
          "tgn:7012149",
          "tgn:2000904",
          "tgn:7007256",
          "tgn:7029392"
        ],
        "placetype": [
          "aat:300008347",
          "aat:300387210"
        ],
        "id": 2042194,
        "name:xx": "Avalon"
      }
    },
    {
      "geometry": {
        "type": "Point",
        "coordinates": [
          -91.9,
          29.9
        ]
      },
      "type": "Feature",
      "properties": {
        "hierarchy": [
          "tgn:2042196",
          "tgn:1000001",
          "tgn:7012149",
          "tgn:2000876",
          "tgn:7007256",
          "tgn:7029392"
        ],
        "placetype": [
          "aat:300008347"
        ],
        "id": 2042196,
        "name:xx": "Avery Island"
      }
    },
    {
      "geometry": {
        "type": "Point",
        "coordinates": [
          -90.2,
          29.9
        ]
      },
      "type": "Feature",
      "properties": {
        "hierarchy": [
          "tgn:2042199",
          "tgn:1000001",
          "tgn:7012149",
          "tgn:2000879",
          "tgn:7007256",
          "tgn:7029392"
        ],
        "placetype": [
          "aat:300008347"
        ],
        "id": 2042199,
        "name:xx": "Avondale"
      }
    }
  ]
}
