{
  "geometry": {
    "type": "Point",
    "coordinates": [
      -122.8833,
      40.2333
    ]
  },
  "type": "Feature",
  "properties": {
    "hierarchy": [
      "tgn:2713859",
      "tgn:1000001",
      "tgn:7012149",
      "tgn:7007157",
      "tgn:2000190",
      "tgn:7029392"
    ],
    "placetype": [
      "aat:300008798"
    ],
    "id": 2713859,
    "name:xx": "Tedoc Mountain"
  }
}
