{
  "type": "FeatureCollection",
  "features": [
    {
      "geometry": {
        "type": "Point",
        "coordinates": [
          25.383333,
          35.25
        ]
      },
      "type": "Feature",
      "properties": {
        "hierarchy": [
          "tgn:7221930",
          "tgn:7002692",
          "tgn:7012056",
          "tgn:1000003",
          "tgn:1000074",
          "tgn:7029392"
        ],
        "placetype": [
          "aat:300008347"
        ],
        "id": 7221930,
        "name:xx": "Potamiaí"
      }
    },
    {
      "geometry": {
        "type": "Point",
        "coordinates": [
          21.366667,
          40.1
        ]
      },
      "type": "Feature",
      "properties": {
        "hierarchy": [
          "tgn:7221931",
          "tgn:7002721",
          "tgn:7002715",
          "tgn:1000003",
          "tgn:1000074",
          "tgn:7029392"
        ],
        "placetype": [
          "aat:300008699"
        ],
        "id": 7221931,
        "name:xx": "Potamiá"
      }
    },
    {
      "geometry": {
        "type": "Point",
        "coordinates": [
          21.981667,
          39.963889
        ]
      },
      "type": "Feature",
      "properties": {
        "hierarchy": [
          "tgn:7221932",
          "tgn:7002752",
          "tgn:7001399",
          "tgn:1000003",
          "tgn:1000074",
          "tgn:7029392"
        ],
        "placetype": [
          "aat:300008699"
        ],
        "id": 7221932,
        "name:xx": "Potamiá"
      }
    },
    {
      "geometry": {
        "type": "Point",
        "coordinates": [
          22.65,
          38.833333
        ]
      },
      "type": "Feature",
      "properties": {
        "hierarchy": [
          "tgn:7221933",
          "tgn:7002751",
          "tgn:7001399",
          "tgn:1000003",
          "tgn:1000074",
          "tgn:7029392"
        ],
        "placetype": [
          "aat:300008699"
        ],
        "id": 7221933,
        "name:xx": "Potamiá"
      }
    },
    {
      "geometry": {
        "type": "Point",
        "coordinates": [
          25.033333,
          41.033333
        ]
      },
      "type": "Feature",
      "properties": {
        "hierarchy": [
          "tgn:7221934",
          "tgn:7011170",
          "tgn:7002715",
          "tgn:1000003",
          "tgn:1000074",
          "tgn:7029392"
        ],
        "placetype": [
          "aat:300008347"
        ],
        "id": 7221934,
        "name:xx": "Potamiá"
      }
    },
    {
      "geometry": {
        "type": "Point",
        "coordinates": [
          24.733333,
          40.716667
        ]
      },
      "type": "Feature",
      "properties": {
        "hierarchy": [
          "tgn:7221935",
          "tgn:7011170",
          "tgn:7002715",
          "tgn:1000003",
          "tgn:1000074",
          "tgn:7029392"
        ],
        "placetype": [
          "aat:300008347"
        ],
        "id": 7221935,
        "name:xx": "Potamiá"
      }
    },
    {
      "geometry": {
        "type": "Point",
        "coordinates": [
          22.783333,
          39.666667
        ]
      },
      "type": "Feature",
      "properties": {
        "hierarchy": [
          "tgn:7221936",
          "tgn:7002750",
          "tgn:7001399",
          "tgn:1000003",
          "tgn:1000074",
          "tgn:7029392"
        ],
        "placetype": [
          "aat:300008347"
        ],
        "id": 7221936,
        "name:xx": "Potamiá"
      }
    },
    {
      "geometry": {
        "type": "Point",
        "coordinates": [
          20.883889,
          39.367778
        ]
      },
      "type": "Feature",
      "properties": {
        "hierarchy": [
          "tgn:7221937",
          "tgn:7002707",
          "tgn:7002705",
          "tgn:1000003",
          "tgn:1000074",
          "tgn:7029392"
        ],
        "placetype": [
          "aat:300008347"
        ],
        "id": 7221937,
        "name:xx": "Potamiá"
      }
    },
    {
      "geometry": {
        "type": "Point",
        "coordinates": [
          21.176667,
          39.343889
        ]
      },
      "type": "Feature",
      "properties": {
        "hierarchy": [
          "tgn:7221938",
          "tgn:7002706",
          "tgn:7002705",
          "tgn:1000003",
          "tgn:1000074",
          "tgn:7029392"
        ],
        "placetype": [
          "aat:300008347"
        ],
        "id": 7221938,
        "name:xx": "Potamiá"
      }
    },
    {
      "geometry": {
        "type": "Point",
        "coordinates": [
          20.589167,
          39.318056
        ]
      },
      "type": "Feature",
      "properties": {
        "hierarchy": [
          "tgn:7221939",
          "tgn:7002709",
          "tgn:7002705",
          "tgn:1000003",
          "tgn:1000074",
          "tgn:7029392"
        ],
        "placetype": [
          "aat:300008347"
        ],
        "id": 7221939,
        "name:xx": "Potamiá"
      }
    }
  ]
}
