{
  "geometry": {
    "type": "Point",
    "coordinates": [
      -113.85,
      43.95
    ]
  },
  "type": "Feature",
  "properties": {
    "hierarchy": [
      "tgn:2780761",
      "tgn:1000001",
      "tgn:2000470",
      "tgn:7012149",
      "tgn:7007250",
      "tgn:7029392"
    ],
    "placetype": [
      "aat:300008697"
    ],
    "id": 2780761,
    "name:xx": "Wood Road Spring"
  }
}
