{
  "geometry": {
    "type": "Point",
    "coordinates": [
      120.6833,
      40.8333
    ]
  },
  "type": "Feature",
  "properties": {
    "hierarchy": [
      "tgn:1068827",
      "tgn:1000004",
      "tgn:1001390",
      "tgn:1000111",
      "tgn:7029392"
    ],
    "placetype": [
      "aat:300008347"
    ],
    "id": 1068827,
    "name:xx": "Houqianjiayu"
  }
}
