{
  "geometry": {
    "type": "Point",
    "coordinates": [
      -113.4667,
      35.4667
    ]
  },
  "type": "Feature",
  "properties": {
    "hierarchy": [
      "tgn:2234608",
      "tgn:1000001",
      "tgn:7006451",
      "tgn:7012149",
      "tgn:2000098",
      "tgn:7029392"
    ],
    "placetype": [
      "aat:300008701"
    ],
    "id": 2234608,
    "name:xx": "Cherokee Wash"
  }
}
