{
  "geometry": {
    "type": "Point",
    "coordinates": [
      -81.6667,
      28.8167
    ]
  },
  "type": "Feature",
  "properties": {
    "hierarchy": [
      "tgn:2286899",
      "tgn:1000001",
      "tgn:7012149",
      "tgn:1002567",
      "tgn:7007240",
      "tgn:7029392"
    ],
    "placetype": [
      "aat:300008680"
    ],
    "id": 2286899,
    "name:xx": "Dicie, Lake"
  }
}
