{
  "geometry": {
    "type": "Point",
    "coordinates": [
      -91.0667,
      37.3833
    ]
  },
  "type": "Feature",
  "properties": {
    "hierarchy": [
      "tgn:2257884",
      "tgn:1000001",
      "tgn:7012149",
      "tgn:2001236",
      "tgn:7007523",
      "tgn:7029392"
    ],
    "placetype": [
      "aat:300008761"
    ],
    "id": 2257884,
    "name:xx": "Corridon Hollow"
  }
}
