{
  "geometry": {
    "type": "Point",
    "coordinates": [
      -114.55,
      42.55
    ]
  },
  "type": "Feature",
  "properties": {
    "hierarchy": [
      "tgn:2025545",
      "tgn:1000001",
      "tgn:7012149",
      "tgn:2000493",
      "tgn:7007250",
      "tgn:7029392"
    ],
    "placetype": [
      "aat:300008347",
      "aat:300387210"
    ],
    "id": 2025545,
    "name:xx": "Curry"
  }
}
