{
  "geometry": {
    "type": "Point",
    "coordinates": [
      36.85,
      66.25
    ]
  },
  "type": "Feature",
  "properties": {
    "hierarchy": [
      "tgn:1137817",
      "tgn:1000004",
      "tgn:7011584",
      "tgn:7018214",
      "tgn:7002435",
      "tgn:7029392"
    ],
    "placetype": [
      "aat:300008347"
    ],
    "id": 1137817,
    "name:xx": "Kuzomen"
  }
}
