{
  "type": "FeatureCollection",
  "features": [
    {
      "geometry": {
        "type": "Point",
        "coordinates": [
          -110.9167,
          45.1333
        ]
      },
      "type": "Feature",
      "properties": {
        "hierarchy": [
          "tgn:2490840",
          "tgn:1000001",
          "tgn:7012149",
          "tgn:2001293",
          "tgn:7007524",
          "tgn:7029392"
        ],
        "placetype": [
          "aat:300008798"
        ],
        "id": 2490840,
        "name:xx": "Mans Foot Mountain"
      }
    },
    {
      "geometry": {
        "type": "Point",
        "coordinates": [
          -81.85,
          39.7667
        ]
      },
      "type": "Feature",
      "properties": {
        "hierarchy": [
          "tgn:2490841",
          "tgn:1000001",
          "tgn:7012149",
          "tgn:7007706",
          "tgn:7029392"
        ],
        "placetype": [
          "aat:300008699"
        ],
        "id": 2490841,
        "name:xx": "Mans Fork"
      }
    },
    {
      "geometry": {
        "type": "Point",
        "coordinates": [
          -109.3333,
          48.3
        ]
      },
      "type": "Feature",
      "properties": {
        "hierarchy": [
          "tgn:2490842",
          "tgn:1000001",
          "tgn:2001262",
          "tgn:7012149",
          "tgn:7007524",
          "tgn:7029392"
        ],
        "placetype": [
          "aat:300008798"
        ],
        "id": 2490842,
        "name:xx": "Mans Head Rock"
      }
    },
    {
      "geometry": {
        "type": "Point",
        "coordinates": [
          -84.6167,
          35.75
        ]
      },
      "type": "Feature",
      "properties": {
        "hierarchy": [
          "tgn:2490843",
          "tgn:1000001",
          "tgn:7012149",
          "tgn:2001909",
          "tgn:7007825",
          "tgn:7029392"
        ],
        "placetype": [
          "aat:300008761"
        ],
        "id": 2490843,
        "name:xx": "Mans Hollow"
      }
    },
    {
      "geometry": {
        "type": "Point",
        "coordinates": [
          -90.9333,
          36.7
        ]
      },
      "type": "Feature",
      "properties": {
        "hierarchy": [
          "tgn:2490844",
          "tgn:1000001",
          "tgn:7012149",
          "tgn:2001237",
          "tgn:7007523",
          "tgn:7029392"
        ],
        "placetype": [
          "aat:300008761"
        ],
        "id": 2490844,
        "name:xx": "Mansco Hollow"
      }
    },
    {
      "geometry": {
        "type": "Point",
        "coordinates": [
          -115.9,
          36.15
        ]
      },
      "type": "Feature",
      "properties": {
        "hierarchy": [
          "tgn:2490845",
          "tgn:1000001",
          "tgn:2001418",
          "tgn:7012149",
          "tgn:7007526",
          "tgn:7029392"
        ],
        "placetype": [
          "aat:300008347"
        ],
        "id": 2490845,
        "name:xx": "Manse"
      }
    },
    {
      "geometry": {
        "type": "Point",
        "coordinates": [
          -83.2,
          35.65
        ]
      },
      "type": "Feature",
      "properties": {
        "hierarchy": [
          "tgn:2490846",
          "tgn:1000001",
          "tgn:7012149",
          "tgn:2001543",
          "tgn:7007709",
          "tgn:7029392"
        ],
        "placetype": [
          "aat:300008699"
        ],
        "id": 2490846,
        "name:xx": "Manse Branch"
      }
    },
    {
      "geometry": {
        "type": "Point",
        "coordinates": [
          -105.7667,
          42.4
        ]
      },
      "type": "Feature",
      "properties": {
        "hierarchy": [
          "tgn:2490847",
          "tgn:2002365",
          "tgn:1000001",
          "tgn:7012149",
          "tgn:7007923",
          "tgn:7029392"
        ],
        "placetype": [
          "aat:300008706"
        ],
        "id": 2490847,
        "name:xx": "Manse Creek"
      }
    },
    {
      "geometry": {
        "type": "Point",
        "coordinates": [
          -115.8833,
          36.15
        ]
      },
      "type": "Feature",
      "properties": {
        "hierarchy": [
          "tgn:2490848",
          "tgn:1000001",
          "tgn:2001418",
          "tgn:7012149",
          "tgn:7007526",
          "tgn:7029392"
        ],
        "placetype": [
          "aat:300008697"
        ],
        "id": 2490848,
        "name:xx": "Manse Ranch Springs"
      }
    }
  ]
}
