{
  "type": "FeatureCollection",
  "features": [
    {
      "geometry": {
        "type": "Point",
        "coordinates": [
          -122.9,
          54.8333
        ]
      },
      "type": "Feature",
      "properties": {
        "hierarchy": [
          "tgn:1123150",
          "tgn:7005735",
          "tgn:7005685",
          "tgn:1000001",
          "tgn:7029392"
        ],
        "placetype": [
          "aat:300008707"
        ],
        "id": 1123150,
        "name:xx": "Crooked River"
      }
    },
    {
      "geometry": {
        "type": "Point",
        "coordinates": [
          8.35,
          4.7
        ]
      },
      "type": "Feature",
      "properties": {
        "hierarchy": [
          "tgn:1123151",
          "tgn:7001242",
          "tgn:7029392"
        ],
        "placetype": [
          "aat:300008707"
        ],
        "id": 1123151,
        "name:xx": "Cross"
      }
    },
    {
      "geometry": {
        "type": "Point",
        "coordinates": [
          10.633333,
          44.916667
        ]
      },
      "type": "Feature",
      "properties": {
        "hierarchy": [
          "tgn:1123153",
          "tgn:7003134",
          "tgn:1000003",
          "tgn:7008516",
          "tgn:1000080",
          "tgn:7029392"
        ],
        "placetype": [
          "aat:300008707",
          "aat:300008699"
        ],
        "id": 1123153,
        "name:xx": "Crostolo"
      }
    },
    {
      "geometry": {
        "type": "Point",
        "coordinates": [
          0.883333,
          51.616667
        ]
      },
      "type": "Feature",
      "properties": {
        "hierarchy": [
          "tgn:1123154",
          "tgn:7002445",
          "tgn:1000003",
          "tgn:7008131",
          "tgn:7008591",
          "tgn:7029392"
        ],
        "placetype": [
          "aat:300008707",
          "aat:300008699"
        ],
        "name:en": "Crouch",
        "id": 1123154
      }
    },
    {
      "geometry": {
        "type": "Point",
        "coordinates": [
          -93.75,
          45.0667
        ]
      },
      "type": "Feature",
      "properties": {
        "hierarchy": [
          "tgn:1123155",
          "tgn:1000001",
          "tgn:7012149",
          "tgn:7007521",
          "tgn:7029392"
        ],
        "placetype": [
          "aat:300008707"
        ],
        "id": 1123155,
        "name:xx": "Crow"
      }
    },
    {
      "geometry": {
        "type": "Point",
        "coordinates": [
          -94.7333,
          47
        ]
      },
      "type": "Feature",
      "properties": {
        "hierarchy": [
          "tgn:1123156",
          "tgn:1000001",
          "tgn:7012149",
          "tgn:7007521",
          "tgn:7029392"
        ],
        "placetype": [
          "aat:300008707"
        ],
        "id": 1123156,
        "name:xx": "Crow Wing"
      }
    },
    {
      "geometry": {
        "type": "Point",
        "coordinates": [
          -77.7667,
          44.3667
        ]
      },
      "type": "Feature",
      "properties": {
        "hierarchy": [
          "tgn:1123159",
          "tgn:7005685",
          "tgn:1000001",
          "tgn:7013154",
          "tgn:7029392"
        ],
        "placetype": [
          "aat:300008707"
        ],
        "id": 1123159,
        "name:xx": "Crowe"
      }
    }
  ]
}
