{
  "geometry": {
    "type": "Point",
    "coordinates": [
      -106.4167,
      38.7333
    ]
  },
  "type": "Feature",
  "properties": {
    "hierarchy": [
      "tgn:2517749",
      "tgn:1000001",
      "tgn:7012149",
      "tgn:2000217",
      "tgn:7007158",
      "tgn:7029392"
    ],
    "placetype": [
      "aat:300008680"
    ],
    "id": 2517749,
    "name:xx": "Mirror Lake"
  }
}
