{
  "geometry": {
    "type": "Point",
    "coordinates": [
      64.1667,
      67.05
    ]
  },
  "type": "Feature",
  "properties": {
    "hierarchy": [
      "tgn:1054669",
      "tgn:1000004",
      "tgn:6003149",
      "tgn:7002435",
      "tgn:7029392"
    ],
    "placetype": [
      "aat:300008347"
    ],
    "id": 1054669,
    "name:xx": "Jeleckij"
  }
}
