{
  "geometry": {
    "type": "Point",
    "coordinates": [
      -116.3333,
      47.9333
    ]
  },
  "type": "Feature",
  "properties": {
    "hierarchy": [
      "tgn:2705385",
      "tgn:1000001",
      "tgn:7012149",
      "tgn:7007250",
      "tgn:7029392"
    ],
    "placetype": [
      "aat:300008706"
    ],
    "id": 2705385,
    "name:xx": "Surprise Creek"
  }
}
