{
  "geometry": {
    "type": "Point",
    "coordinates": [
      -88.3167,
      36.7833
    ]
  },
  "type": "Feature",
  "properties": {
    "hierarchy": [
      "tgn:2255480",
      "tgn:1000001",
      "tgn:7012149",
      "tgn:2000823",
      "tgn:7007255",
      "tgn:7029392"
    ],
    "placetype": [
      "aat:300008706"
    ],
    "id": 2255480,
    "name:xx": "Cope Creek"
  }
}
