{
  "geometry": {
    "type": "Point",
    "coordinates": [
      -105.1333,
      38.9333
    ]
  },
  "type": "Feature",
  "properties": {
    "hierarchy": [
      "tgn:2259913",
      "tgn:1000001",
      "tgn:7012149",
      "tgn:7007158",
      "tgn:2000251",
      "tgn:7029392"
    ],
    "placetype": [
      "aat:300006191"
    ],
    "id": 2259913,
    "name:xx": "Coulson Lake"
  }
}
