{
  "geometry": {
    "type": "Point",
    "coordinates": [
      -87.3667,
      13.5833
    ]
  },
  "type": "Feature",
  "properties": {
    "hierarchy": [
      "tgn:1016818",
      "tgn:1000569",
      "tgn:1000001",
      "tgn:7005554",
      "tgn:7029392"
    ],
    "placetype": [
      "aat:300008347"
    ],
    "id": 1016818,
    "name:xx": "Pespire"
  }
}
