{
  "geometry": {
    "type": "Point",
    "coordinates": [
      -2.25,
      53.4833
    ]
  },
  "type": "Feature",
  "properties": {
    "hierarchy": [
      "tgn:7027477",
      "tgn:7002445",
      "tgn:1000003",
      "tgn:7026570",
      "tgn:7008591",
      "tgn:7029392"
    ],
    "placetype": [
      "aat:300387337"
    ],
    "id": 7027477,
    "name:xx": "Manchester"
  }
}
