{
  "geometry": {
    "type": "Point",
    "coordinates": [
      -3.75,
      57.8667
    ]
  },
  "type": "Feature",
  "properties": {
    "hierarchy": [
      "tgn:1051156",
      "tgn:7002444",
      "tgn:1000003",
      "tgn:7008082",
      "tgn:7008591",
      "tgn:7029392"
    ],
    "placetype": [
      "aat:300008347"
    ],
    "id": 1051156,
    "name:xx": "Wilkhaven"
  }
}
