{
  "geometry": {
    "type": "Point",
    "coordinates": [
      -73.35,
      44.65
    ]
  },
  "type": "Feature",
  "properties": {
    "hierarchy": [
      "tgn:2646368",
      "tgn:1000001",
      "tgn:1002415",
      "tgn:7012149",
      "tgn:7007828",
      "tgn:7029392"
    ],
    "placetype": [
      "aat:300008791"
    ],
    "id": 2646368,
    "name:xx": "Sawyer Island"
  }
}
