{
  "geometry": {
    "type": "Point",
    "coordinates": [
      -103.7167,
      46.35
    ]
  },
  "type": "Feature",
  "properties": {
    "hierarchy": [
      "tgn:2410906",
      "tgn:1000001",
      "tgn:2001600",
      "tgn:7012149",
      "tgn:7007705",
      "tgn:7029392"
    ],
    "placetype": [
      "aat:300008706"
    ],
    "id": 2410906,
    "name:xx": "Indian Creek"
  }
}
