{
  "type": "FeatureCollection",
  "features": [
    {
      "geometry": {
        "type": "Point",
        "coordinates": [
          -116.8,
          47.65
        ]
      },
      "type": "Feature",
      "properties": {
        "hierarchy": [
          "tgn:2224460",
          "tgn:1000001",
          "tgn:7012149",
          "tgn:2000479",
          "tgn:7007250",
          "tgn:7029392"
        ],
        "placetype": [
          "aat:300132316"
        ],
        "id": 2224460,
        "name:xx": "Casco Bay"
      }
    },
    {
      "geometry": {
        "type": "Point",
        "coordinates": [
          173.15,
          52.8
        ]
      },
      "type": "Feature",
      "properties": {
        "hierarchy": [
          "tgn:2224461",
          "tgn:7030516",
          "tgn:7006450",
          "tgn:1000001",
          "tgn:7012149",
          "tgn:7029392"
        ],
        "placetype": [
          "aat:300132316"
        ],
        "id": 2224461,
        "name:xx": "Casco Cove"
      }
    },
    {
      "geometry": {
        "type": "Point",
        "coordinates": [
          -87.5833,
          44.5833
        ]
      },
      "type": "Feature",
      "properties": {
        "hierarchy": [
          "tgn:2224462",
          "tgn:1000001",
          "tgn:7012149",
          "tgn:2002330",
          "tgn:7007922",
          "tgn:7029392"
        ],
        "placetype": [
          "aat:300008706"
        ],
        "id": 2224462,
        "name:xx": "Casco Creek"
      }
    },
    {
      "geometry": {
        "type": "Point",
        "coordinates": [
          -87.6,
          44.55
        ]
      },
      "type": "Feature",
      "properties": {
        "hierarchy": [
          "tgn:2224463",
          "tgn:1000001",
          "tgn:7012149",
          "tgn:2002330",
          "tgn:7007922",
          "tgn:7029392"
        ],
        "placetype": [
          "aat:300006191"
        ],
        "id": 2224463,
        "name:xx": "Casco Millpond"
      }
    },
    {
      "geometry": {
        "type": "Point",
        "coordinates": [
          -106.4833,
          39.1
        ]
      },
      "type": "Feature",
      "properties": {
        "hierarchy": [
          "tgn:2224464",
          "tgn:1000001",
          "tgn:7012149",
          "tgn:2000224",
          "tgn:7007158",
          "tgn:7029392"
        ],
        "placetype": [
          "aat:300008798"
        ],
        "id": 2224464,
        "name:xx": "Casco Peak"
      }
    },
    {
      "geometry": {
        "type": "Point",
        "coordinates": [
          -93.6,
          44.9167
        ]
      },
      "type": "Feature",
      "properties": {
        "hierarchy": [
          "tgn:2224465",
          "tgn:1000001",
          "tgn:2001025",
          "tgn:7012149",
          "tgn:7007521",
          "tgn:7029392"
        ],
        "placetype": [
          "aat:300008850"
        ],
        "id": 2224465,
        "name:xx": "Casco Point"
      }
    },
    {
      "geometry": {
        "type": "Point",
        "coordinates": [
          -90.75,
          36.2
        ]
      },
      "type": "Feature",
      "properties": {
        "hierarchy": [
          "tgn:2224466",
          "tgn:1000001",
          "tgn:7016172",
          "tgn:7012149",
          "tgn:2000132",
          "tgn:7029392"
        ],
        "placetype": [
          "aat:300008347"
        ],
        "id": 2224466,
        "name:xx": "Case"
      }
    },
    {
      "geometry": {
        "type": "Point",
        "coordinates": [
          -92.75,
          37.8333
        ]
      },
      "type": "Feature",
      "properties": {
        "hierarchy": [
          "tgn:2224467",
          "tgn:1000001",
          "tgn:7012149",
          "tgn:2001211",
          "tgn:7007523",
          "tgn:7029392"
        ],
        "placetype": [
          "aat:300008347"
        ],
        "id": 2224467,
        "name:xx": "Case"
      }
    },
    {
      "geometry": {
        "type": "Point",
        "coordinates": [
          -90.5167,
          36.6667
        ]
      },
      "type": "Feature",
      "properties": {
        "hierarchy": [
          "tgn:2224468",
          "tgn:1000001",
          "tgn:2001176",
          "tgn:7012149",
          "tgn:7007523",
          "tgn:7029392"
        ],
        "placetype": [
          "aat:300008699"
        ],
        "id": 2224468,
        "name:xx": "Case Bolt Branch"
      }
    },
    {
      "geometry": {
        "type": "Point",
        "coordinates": [
          -82.6667,
          35.35
        ]
      },
      "type": "Feature",
      "properties": {
        "hierarchy": [
          "tgn:2224469",
          "tgn:1000001",
          "tgn:7012149",
          "tgn:2001504",
          "tgn:7007709",
          "tgn:7029392"
        ],
        "placetype": [
          "aat:300008699"
        ],
        "id": 2224469,
        "name:xx": "Case Branch"
      }
    }
  ]
}
