{
  "geometry": {
    "type": "Point",
    "coordinates": [
      -90.2167,
      33.9167
    ]
  },
  "type": "Feature",
  "properties": {
    "hierarchy": [
      "tgn:2496732",
      "tgn:1000001",
      "tgn:7012149",
      "tgn:2001153",
      "tgn:7007522",
      "tgn:7029392"
    ],
    "placetype": [
      "aat:300008699"
    ],
    "id": 2496732,
    "name:xx": "Matthews Bayou"
  }
}
