{
  "geometry": {
    "type": "Point",
    "coordinates": [
      -103.8833,
      30.8167
    ]
  },
  "type": "Feature",
  "properties": {
    "hierarchy": [
      "tgn:2451018",
      "tgn:1000001",
      "tgn:7012149",
      "tgn:2002010",
      "tgn:7007826",
      "tgn:7029392"
    ],
    "placetype": [
      "aat:300008798"
    ],
    "id": 2451018,
    "name:xx": "Little Aguja Mountain"
  }
}
