{
  "type": "FeatureCollection",
  "features": [
    {
      "geometry": {
        "type": "Point",
        "coordinates": [
          -117.7,
          44.7
        ]
      },
      "type": "Feature",
      "properties": {
        "hierarchy": [
          "tgn:2550550",
          "tgn:7013349",
          "tgn:1000001",
          "tgn:7012149",
          "tgn:7007708",
          "tgn:7029392"
        ],
        "placetype": [
          "aat:300008347"
        ],
        "id": 2550550,
        "name:xx": "Norton"
      }
    },
    {
      "geometry": {
        "type": "Point",
        "coordinates": [
          -78.9667,
          34.2
        ]
      },
      "type": "Feature",
      "properties": {
        "hierarchy": [
          "tgn:2550551",
          "tgn:1000001",
          "tgn:7012149",
          "tgn:2001750",
          "tgn:7007712",
          "tgn:7029392"
        ],
        "placetype": [
          "aat:300008347"
        ],
        "id": 2550551,
        "name:xx": "Norton"
      }
    },
    {
      "geometry": {
        "type": "Point",
        "coordinates": [
          -83.75,
          30.8
        ]
      },
      "type": "Feature",
      "properties": {
        "hierarchy": [
          "tgn:2550552",
          "tgn:1000001",
          "tgn:7012149",
          "tgn:7014371",
          "tgn:7007248",
          "tgn:7029392"
        ],
        "placetype": [
          "aat:300008699"
        ],
        "id": 2550552,
        "name:xx": "Norton Branch"
      }
    },
    {
      "geometry": {
        "type": "Point",
        "coordinates": [
          -83.8,
          34.9333
        ]
      },
      "type": "Feature",
      "properties": {
        "hierarchy": [
          "tgn:2550553",
          "tgn:1000001",
          "tgn:7012149",
          "tgn:2000430",
          "tgn:7007248",
          "tgn:7029392"
        ],
        "placetype": [
          "aat:300008699"
        ],
        "id": 2550553,
        "name:xx": "Norton Branch"
      }
    },
    {
      "geometry": {
        "type": "Point",
        "coordinates": [
          -82.8167,
          38.3333
        ]
      },
      "type": "Feature",
      "properties": {
        "hierarchy": [
          "tgn:2550554",
          "tgn:1000001",
          "tgn:1002240",
          "tgn:7012149",
          "tgn:7007255",
          "tgn:7029392"
        ],
        "placetype": [
          "aat:300008699"
        ],
        "id": 2550554,
        "name:xx": "Norton Branch"
      }
    },
    {
      "geometry": {
        "type": "Point",
        "coordinates": [
          -83.15,
          35.0167
        ]
      },
      "type": "Feature",
      "properties": {
        "hierarchy": [
          "tgn:2550555",
          "tgn:1000001",
          "tgn:7012149",
          "tgn:2001515",
          "tgn:7007709",
          "tgn:7029392"
        ],
        "placetype": [
          "aat:300008699"
        ],
        "id": 2550555,
        "name:xx": "Norton Branch"
      }
    },
    {
      "geometry": {
        "type": "Point",
        "coordinates": [
          -87.25,
          35.1
        ]
      },
      "type": "Feature",
      "properties": {
        "hierarchy": [
          "tgn:2550556",
          "tgn:1000001",
          "tgn:7012149",
          "tgn:2001886",
          "tgn:7007825",
          "tgn:7029392"
        ],
        "placetype": [
          "aat:300008699"
        ],
        "id": 2550556,
        "name:xx": "Norton Branch"
      }
    },
    {
      "geometry": {
        "type": "Point",
        "coordinates": [
          -86.1667,
          35.6333
        ]
      },
      "type": "Feature",
      "properties": {
        "hierarchy": [
          "tgn:2550557",
          "tgn:1000001",
          "tgn:7012149",
          "tgn:2001852",
          "tgn:7007825",
          "tgn:7029392"
        ],
        "placetype": [
          "aat:300008699"
        ],
        "id": 2550557,
        "name:xx": "Norton Branch"
      }
    },
    {
      "geometry": {
        "type": "Point",
        "coordinates": [
          -83.6,
          35.8333
        ]
      },
      "type": "Feature",
      "properties": {
        "hierarchy": [
          "tgn:2550558",
          "tgn:1000001",
          "tgn:7012149",
          "tgn:2001914",
          "tgn:7007825",
          "tgn:7029392"
        ],
        "placetype": [
          "aat:300008699"
        ],
        "id": 2550558,
        "name:xx": "Norton Branch"
      }
    },
    {
      "geometry": {
        "type": "Point",
        "coordinates": [
          -98.75,
          32.85
        ]
      },
      "type": "Feature",
      "properties": {
        "hierarchy": [
          "tgn:2550559",
          "tgn:1000001",
          "tgn:7012149",
          "tgn:2002076",
          "tgn:7007826",
          "tgn:7029392"
        ],
        "placetype": [
          "aat:300008699"
        ],
        "id": 2550559,
        "name:xx": "Norton Branch"
      }
    }
  ]
}
