{
  "geometry": {
    "type": "Point",
    "coordinates": [
      -81.4833,
      36.6333
    ]
  },
  "type": "Feature",
  "properties": {
    "hierarchy": [
      "tgn:2769956",
      "tgn:1000001",
      "tgn:7012149",
      "tgn:2002164",
      "tgn:7007919",
      "tgn:7029392"
    ],
    "placetype": [
      "aat:300266640"
    ],
    "id": 2769956,
    "name:xx": "Wilburn Ridge"
  }
}
