{
  "geometry": {
    "type": "Point",
    "coordinates": [
      -84.6833,
      29.8333
    ]
  },
  "type": "Feature",
  "properties": {
    "hierarchy": [
      "tgn:2185238",
      "tgn:1000001",
      "tgn:2000267",
      "tgn:7012149",
      "tgn:7007240",
      "tgn:7029392"
    ],
    "placetype": [
      "aat:300008699"
    ],
    "id": 2185238,
    "name:xx": "Boggy Jordan Bayou"
  }
}
