{
  "geometry": {
    "type": "Point",
    "coordinates": [
      -89.3167,
      45.9167
    ]
  },
  "type": "Feature",
  "properties": {
    "hierarchy": [
      "tgn:2472108",
      "tgn:1000001",
      "tgn:7012149",
      "tgn:2002359",
      "tgn:7007922",
      "tgn:7029392"
    ],
    "placetype": [
      "aat:300008680"
    ],
    "id": 2472108,
    "name:xx": "Lotus Lake"
  }
}
