{
  "geometry": {
    "type": "Point",
    "coordinates": [
      -94.3333,
      32.15
    ]
  },
  "type": "Feature",
  "properties": {
    "hierarchy": [
      "tgn:2398091",
      "tgn:1000001",
      "tgn:7012149",
      "tgn:1002769",
      "tgn:7007826",
      "tgn:7029392"
    ],
    "placetype": [
      "aat:300008699"
    ],
    "id": 2398091,
    "name:xx": "Hooker Branch"
  }
}
