{
  "geometry": {
    "type": "Point",
    "coordinates": [
      -78.5167,
      34.35
    ]
  },
  "type": "Feature",
  "properties": {
    "hierarchy": [
      "tgn:2266486",
      "tgn:1000001",
      "tgn:2001485",
      "tgn:7012149",
      "tgn:7007709",
      "tgn:7029392"
    ],
    "placetype": [
      "aat:300008699"
    ],
    "id": 2266486,
    "name:xx": "Creek Branch"
  }
}
