{
  "geometry": {
    "type": "Point",
    "coordinates": [
      -100.4667,
      37.05
    ]
  },
  "type": "Feature",
  "properties": {
    "hierarchy": [
      "tgn:2667963",
      "tgn:1000001",
      "tgn:7012149",
      "tgn:2000719",
      "tgn:7007254",
      "tgn:7029392"
    ],
    "placetype": [
      "aat:300008699"
    ],
    "id": 2667963,
    "name:xx": "Skunkie Arroyo"
  }
}
