{
  "geometry": {
    "type": "Point",
    "coordinates": [
      -108.85,
      31.4667
    ]
  },
  "type": "Feature",
  "properties": {
    "hierarchy": [
      "tgn:2648151",
      "tgn:1000001",
      "tgn:7012149",
      "tgn:2001440",
      "tgn:7007566",
      "tgn:7029392"
    ],
    "placetype": [
      "aat:300006191"
    ],
    "id": 2648151,
    "name:xx": "Schoolhouse Tank"
  }
}
