{
  "geometry": {
    "type": "Point",
    "coordinates": [
      -136.4667,
      58.75
    ]
  },
  "type": "Feature",
  "properties": {
    "hierarchy": [
      "tgn:2405425",
      "tgn:7006450",
      "tgn:1000001",
      "tgn:7012149",
      "tgn:7019760",
      "tgn:7029392"
    ],
    "placetype": [
      "aat:300132316"
    ],
    "id": 2405425,
    "name:xx": "Hugh Miller Inlet"
  }
}
