{
  "geometry": {
    "type": "Point",
    "coordinates": [
      -109.1333,
      33.25
    ]
  },
  "type": "Feature",
  "properties": {
    "hierarchy": [
      "tgn:2298362",
      "tgn:1000001",
      "tgn:7006451",
      "tgn:2000095",
      "tgn:7012149",
      "tgn:7029392"
    ],
    "placetype": [
      "aat:300008697"
    ],
    "id": 2298362,
    "name:xx": "Dry Prong Seep"
  }
}
