{
  "geometry": {
    "type": "Point",
    "coordinates": [
      30.85,
      30.45
    ]
  },
  "type": "Feature",
  "properties": {
    "hierarchy": [
      "tgn:7526204",
      "tgn:7001242",
      "tgn:1001075",
      "tgn:7016833",
      "tgn:7029392"
    ],
    "placetype": [
      "aat:300008791"
    ],
    "name:en": "Ţarrānah, Jazīrat aţ",
    "id": 7526204
  }
}
