{
  "geometry": {
    "type": "Point",
    "coordinates": [
      -76.3667,
      41.6667
    ]
  },
  "type": "Feature",
  "properties": {
    "hierarchy": [
      "tgn:2125341",
      "tgn:1000001",
      "tgn:1002194",
      "tgn:7012149",
      "tgn:7007710",
      "tgn:7029392"
    ],
    "placetype": [
      "aat:300006191"
    ],
    "id": 2125341,
    "name:xx": "Ackleys Pond"
  }
}
