{
  "geometry": {
    "type": "Point",
    "coordinates": [
      -106.8833,
      44.8167
    ]
  },
  "type": "Feature",
  "properties": {
    "hierarchy": [
      "tgn:2123220",
      "tgn:1000001",
      "tgn:7012149",
      "tgn:2002381",
      "tgn:7007923",
      "tgn:7029392"
    ],
    "placetype": [
      "aat:300387016"
    ],
    "id": 2123220,
    "name:xx": "Wakeley"
  }
}
