{
  "type": "FeatureCollection",
  "features": [
    {
      "geometry": {
        "type": "Point",
        "coordinates": [
          -75.0667,
          39.8
        ]
      },
      "type": "Feature",
      "properties": {
        "hierarchy": [
          "tgn:2064130",
          "tgn:1002227",
          "tgn:1000001",
          "tgn:7012149",
          "tgn:7007565",
          "tgn:7029392"
        ],
        "placetype": [
          "aat:300008347"
        ],
        "id": 2064130,
        "name:xx": "Blenheim"
      }
    },
    {
      "geometry": {
        "type": "Point",
        "coordinates": [
          -74.1833,
          40.8
        ]
      },
      "type": "Feature",
      "properties": {
        "hierarchy": [
          "tgn:2064131",
          "tgn:1000001",
          "tgn:1002360",
          "tgn:7012149",
          "tgn:7007565",
          "tgn:7029392"
        ],
        "placetype": [
          "aat:300008347"
        ],
        "id": 2064131,
        "name:xx": "Bloomfield"
      }
    },
    {
      "geometry": {
        "type": "Point",
        "coordinates": [
          -74.25,
          40.7833
        ]
      },
      "type": "Feature",
      "properties": {
        "hierarchy": [
          "tgn:2064134",
          "tgn:2064131",
          "tgn:1000001",
          "tgn:1002360",
          "tgn:7012149",
          "tgn:7007565",
          "tgn:7029392"
        ],
        "placetype": [
          "aat:300008187"
        ],
        "id": 2064134,
        "name:xx": "Grove"
      }
    },
    {
      "geometry": {
        "type": "Point",
        "coordinates": [
          -74.2,
          40.7833
        ]
      },
      "type": "Feature",
      "properties": {
        "hierarchy": [
          "tgn:2064137",
          "tgn:2064131",
          "tgn:1000001",
          "tgn:1002360",
          "tgn:7012149",
          "tgn:7007565",
          "tgn:7029392"
        ],
        "placetype": [
          "aat:300008187"
        ],
        "id": 2064137,
        "name:xx": "Watsessing"
      }
    },
    {
      "geometry": {
        "type": "Point",
        "coordinates": [
          -74.3167,
          41
        ]
      },
      "type": "Feature",
      "properties": {
        "hierarchy": [
          "tgn:2064138",
          "tgn:1000001",
          "tgn:1002775",
          "tgn:7012149",
          "tgn:7007565",
          "tgn:7029392"
        ],
        "placetype": [
          "aat:300008347"
        ],
        "id": 2064138,
        "name:xx": "Bloomingdale"
      }
    }
  ]
}
