{
  "geometry": {
    "type": "Point",
    "coordinates": [
      30.0609,
      31.192636
    ]
  },
  "type": "Feature",
  "properties": {
    "hierarchy": [
      "tgn:7530369",
      "tgn:7001242",
      "tgn:7016833",
      "tgn:7029392"
    ],
    "placetype": [
      "aat:300006075"
    ],
    "name:en": "Tur'at al Wasţānī",
    "id": 7530369
  }
}
