{
  "geometry": {
    "type": "Point",
    "coordinates": [
      -104.0333,
      41.9333
    ]
  },
  "type": "Feature",
  "properties": {
    "hierarchy": [
      "tgn:7022908",
      "tgn:1000001",
      "tgn:7012149",
      "tgn:7029392"
    ],
    "placetype": [
      "aat:300006075"
    ],
    "id": 7022908,
    "name:xx": "East Springer Main Lateral"
  }
}
