{
  "geometry": {
    "type": "Point",
    "coordinates": [
      13.15,
      52.216667
    ]
  },
  "type": "Feature",
  "properties": {
    "hierarchy": [
      "tgn:7094462",
      "tgn:7000096",
      "tgn:1000003",
      "tgn:7000084",
      "tgn:7029392"
    ],
    "placetype": [
      "aat:300008347"
    ],
    "id": 7094462,
    "name:xx": "Schönhagen"
  }
}
