{
  "type": "FeatureCollection",
  "features": [
    {
      "geometry": {
        "type": "Point",
        "coordinates": [
          -99.452222,
          24.071111
        ]
      },
      "type": "Feature",
      "properties": {
        "hierarchy": [
          "tgn:7392400",
          "tgn:1000001",
          "tgn:7005597",
          "tgn:7005560",
          "tgn:7029392"
        ],
        "placetype": [
          "aat:300008347"
        ],
        "id": 7392400,
        "name:xx": "Rancho El Mirador"
      }
    },
    {
      "geometry": {
        "type": "Point",
        "coordinates": [
          -104.9,
          26
        ]
      },
      "type": "Feature",
      "properties": {
        "hierarchy": [
          "tgn:7392401",
          "tgn:7005583",
          "tgn:1000001",
          "tgn:7005560",
          "tgn:7029392"
        ],
        "placetype": [
          "aat:300008347"
        ],
        "id": 7392401,
        "name:xx": "Rancho El Mimbre"
      }
    },
    {
      "geometry": {
        "type": "Point",
        "coordinates": [
          -110.1,
          30.866667
        ]
      },
      "type": "Feature",
      "properties": {
        "hierarchy": [
          "tgn:7392402",
          "tgn:1000001",
          "tgn:1001960",
          "tgn:7005560",
          "tgn:7029392"
        ],
        "placetype": [
          "aat:300008347"
        ],
        "id": 7392402,
        "name:xx": "Rancho El Miller"
      }
    },
    {
      "geometry": {
        "type": "Point",
        "coordinates": [
          -102.733333,
          28.816667
        ]
      },
      "type": "Feature",
      "properties": {
        "hierarchy": [
          "tgn:7392403",
          "tgn:1001853",
          "tgn:1000001",
          "tgn:7005560",
          "tgn:7029392"
        ],
        "placetype": [
          "aat:300008347"
        ],
        "id": 7392403,
        "name:xx": "Rancho El Milagro"
      }
    },
    {
      "geometry": {
        "type": "Point",
        "coordinates": [
          -101.6,
          28.233333
        ]
      },
      "type": "Feature",
      "properties": {
        "hierarchy": [
          "tgn:7392404",
          "tgn:1001853",
          "tgn:1000001",
          "tgn:7005560",
          "tgn:7029392"
        ],
        "placetype": [
          "aat:300008347"
        ],
        "id": 7392404,
        "name:xx": "Rancho El Milagro"
      }
    },
    {
      "geometry": {
        "type": "Point",
        "coordinates": [
          -101.15,
          28.016667
        ]
      },
      "type": "Feature",
      "properties": {
        "hierarchy": [
          "tgn:7392405",
          "tgn:1001853",
          "tgn:1000001",
          "tgn:7005560",
          "tgn:7029392"
        ],
        "placetype": [
          "aat:300008347"
        ],
        "id": 7392405,
        "name:xx": "Rancho El Milagro"
      }
    },
    {
      "geometry": {
        "type": "Point",
        "coordinates": [
          -105.05,
          27.516667
        ]
      },
      "type": "Feature",
      "properties": {
        "hierarchy": [
          "tgn:7392406",
          "tgn:7005581",
          "tgn:1000001",
          "tgn:7005560",
          "tgn:7029392"
        ],
        "placetype": [
          "aat:300008347"
        ],
        "id": 7392406,
        "name:xx": "Rancho El Milagro"
      }
    },
    {
      "geometry": {
        "type": "Point",
        "coordinates": [
          -100.016667,
          27.066667
        ]
      },
      "type": "Feature",
      "properties": {
        "hierarchy": [
          "tgn:7392407",
          "tgn:1000001",
          "tgn:7005589",
          "tgn:7005560",
          "tgn:7029392"
        ],
        "placetype": [
          "aat:300008347"
        ],
        "id": 7392407,
        "name:xx": "Rancho El Milagro"
      }
    },
    {
      "geometry": {
        "type": "Point",
        "coordinates": [
          -100.816667,
          25.133333
        ]
      },
      "type": "Feature",
      "properties": {
        "hierarchy": [
          "tgn:7392408",
          "tgn:1000001",
          "tgn:7005589",
          "tgn:7005560",
          "tgn:7029392"
        ],
        "placetype": [
          "aat:300008347"
        ],
        "id": 7392408,
        "name:xx": "Rancho El Milagro"
      }
    },
    {
      "geometry": {
        "type": "Point",
        "coordinates": [
          -98.6,
          24.883333
        ]
      },
      "type": "Feature",
      "properties": {
        "hierarchy": [
          "tgn:7392409",
          "tgn:1000001",
          "tgn:7005597",
          "tgn:7005560",
          "tgn:7029392"
        ],
        "placetype": [
          "aat:300008347"
        ],
        "id": 7392409,
        "name:xx": "Rancho El Milagro"
      }
    }
  ]
}
