{
  "geometry": {
    "type": "Point",
    "coordinates": [
      -88.15,
      42.7667
    ]
  },
  "type": "Feature",
  "properties": {
    "hierarchy": [
      "tgn:2776423",
      "tgn:1000001",
      "tgn:7012149",
      "tgn:1002815",
      "tgn:7007922",
      "tgn:7029392"
    ],
    "placetype": [
      "aat:300006075"
    ],
    "id": 2776423,
    "name:xx": "Wind Lake Drainage Canal"
  }
}
