{
  "geometry": {
    "type": "Point",
    "coordinates": [
      79.61202,
      26.78489
    ]
  },
  "type": "Feature",
  "properties": {
    "hierarchy": [
      "tgn:7565849",
      "tgn:1000004",
      "tgn:7000198",
      "tgn:7016722",
      "tgn:7029392"
    ],
    "placetype": [
      "aat:300008347"
    ],
    "name:en": "Bandariāpur",
    "id": 7565849
  }
}
