{
  "geometry": {
    "type": "Point",
    "coordinates": [
      -113.35,
      39.8333
    ]
  },
  "type": "Feature",
  "properties": {
    "hierarchy": [
      "tgn:2141032",
      "tgn:1000001",
      "tgn:7012149",
      "tgn:2002112",
      "tgn:7007827",
      "tgn:7029392"
    ],
    "placetype": [
      "aat:300006191"
    ],
    "id": 2141032,
    "name:xx": "Avocet Pool"
  }
}
