{
  "geometry": {
    "type": "Point",
    "coordinates": [
      -123.0667,
      40.7833
    ]
  },
  "type": "Feature",
  "properties": {
    "hierarchy": [
      "tgn:2546820",
      "tgn:1000001",
      "tgn:7012149",
      "tgn:2000181",
      "tgn:7007157",
      "tgn:7029392"
    ],
    "placetype": [
      "aat:300008706"
    ],
    "id": 2546820,
    "name:xx": "North Fork Mingo Creek"
  }
}
