{
  "geometry": {
    "type": "Point",
    "coordinates": [
      31.783333,
      26.55
    ]
  },
  "type": "Feature",
  "properties": {
    "hierarchy": [
      "tgn:7533908",
      "tgn:7001242",
      "tgn:7016833",
      "tgn:7000124",
      "tgn:7029392"
    ],
    "placetype": [
      "aat:300343519"
    ],
    "name:en": "Jazīrat al Muntaşir, Ḩawḑ",
    "id": 7533908
  }
}
