{
  "geometry": {
    "type": "Point",
    "coordinates": [
      -82.4167,
      23.0667
    ]
  },
  "type": "Feature",
  "properties": {
    "hierarchy": [
      "tgn:1005044",
      "tgn:7006453",
      "tgn:1001206",
      "tgn:1000001",
      "tgn:7004624",
      "tgn:7029392"
    ],
    "placetype": [
      "aat:300000745"
    ],
    "id": 1005044,
    "name:xx": "Marianao"
  }
}
