{
  "geometry": {
    "type": "Point",
    "coordinates": [
      81.033333,
      18.75
    ]
  },
  "type": "Feature",
  "properties": {
    "hierarchy": [
      "tgn:7572974",
      "tgn:1000004",
      "tgn:7031781",
      "tgn:7000198",
      "tgn:7029392"
    ],
    "placetype": [
      "aat:300008347"
    ],
    "name:en": "Gangalūr",
    "id": 7572974
  }
}
