{
  "geometry": {
    "type": "Point",
    "coordinates": [
      -118.9167,
      44.0333
    ]
  },
  "type": "Feature",
  "properties": {
    "hierarchy": [
      "tgn:2233434",
      "tgn:1000001",
      "tgn:7012149",
      "tgn:2001708",
      "tgn:7007708",
      "tgn:7029392"
    ],
    "placetype": [
      "aat:300006191"
    ],
    "id": 2233434,
    "name:xx": "Charlie Smith Reservoir"
  }
}
