{
  "geometry": {
    "type": "Point",
    "coordinates": [
      -71.9333,
      42.65
    ]
  },
  "type": "Feature",
  "properties": {
    "hierarchy": [
      "tgn:2740500",
      "tgn:1000001",
      "tgn:7012149",
      "tgn:1003038",
      "tgn:7007517",
      "tgn:7029392"
    ],
    "placetype": [
      "aat:300006191"
    ],
    "id": 2740500,
    "name:xx": "Upper Naukeag Lake"
  }
}
