{
  "geometry": {
    "type": "Point",
    "coordinates": [
      -111.6333,
      46.7333
    ]
  },
  "type": "Feature",
  "properties": {
    "hierarchy": [
      "tgn:2383929",
      "tgn:1000001",
      "tgn:7012149",
      "tgn:2001284",
      "tgn:7007524",
      "tgn:7029392"
    ],
    "placetype": [
      "aat:300008798"
    ],
    "id": 2383929,
    "name:xx": "Hedges Mountain"
  }
}
