{
  "geometry": {
    "type": "Point",
    "coordinates": [
      -110.8333,
      33.25
    ]
  },
  "type": "Feature",
  "properties": {
    "hierarchy": [
      "tgn:1132740",
      "tgn:1000001",
      "tgn:7006451",
      "tgn:7012149",
      "tgn:7029392"
    ],
    "placetype": [
      "aat:300008706"
    ],
    "id": 1132740,
    "name:xx": "Cedar Creek"
  }
}
