{
  "geometry": {
    "type": "Point",
    "coordinates": [
      -120.3333,
      39.05
    ]
  },
  "type": "Feature",
  "properties": {
    "hierarchy": [
      "tgn:2502393",
      "tgn:1000001",
      "tgn:7012149",
      "tgn:7007157",
      "tgn:1002791",
      "tgn:7029392"
    ],
    "placetype": [
      "aat:300008798"
    ],
    "id": 2502393,
    "name:xx": "McKinstry Peak"
  }
}
