{
  "geometry": {
    "type": "Point",
    "coordinates": [
      -99.25,
      35.6167
    ]
  },
  "type": "Feature",
  "properties": {
    "hierarchy": [
      "tgn:2335884",
      "tgn:1000001",
      "tgn:2001642",
      "tgn:7012149",
      "tgn:7007707",
      "tgn:7029392"
    ],
    "placetype": [
      "aat:300006191"
    ],
    "id": 2335884,
    "name:xx": "Foss Reservoir"
  }
}
