{
  "geometry": {
    "type": "Point",
    "coordinates": [
      -119.1167,
      42.9167
    ]
  },
  "type": "Feature",
  "properties": {
    "hierarchy": [
      "tgn:2148963",
      "tgn:1000001",
      "tgn:7012149",
      "tgn:2001709",
      "tgn:7007708",
      "tgn:7029392"
    ],
    "placetype": [
      "aat:300008680"
    ],
    "id": 2148963,
    "name:xx": "Barneys Butte Waterhole"
  }
}
