{
  "geometry": {
    "type": "Point",
    "coordinates": [
      120.5667,
      -10.2333
    ]
  },
  "type": "Feature",
  "properties": {
    "hierarchy": [
      "tgn:1077393",
      "tgn:1000004",
      "tgn:1009293",
      "tgn:1001467",
      "tgn:1000116",
      "tgn:7029392"
    ],
    "placetype": [
      "aat:300008347"
    ],
    "id": 1077393,
    "name:xx": "Baing"
  }
}
