{
  "type": "FeatureCollection",
  "features": [
    {
      "geometry": {
        "type": "Point",
        "coordinates": [
          -150.7167,
          61.4833
        ]
      },
      "type": "Feature",
      "properties": {
        "hierarchy": [
          "tgn:2358880",
          "tgn:7006450",
          "tgn:1000001",
          "tgn:2124053",
          "tgn:7012149",
          "tgn:7029392"
        ],
        "placetype": [
          "aat:300008706"
        ],
        "id": 2358880,
        "name:xx": "Granite Creek"
      }
    },
    {
      "geometry": {
        "type": "Point",
        "coordinates": [
          -157.9,
          62.4667
        ]
      },
      "type": "Feature",
      "properties": {
        "hierarchy": [
          "tgn:2358881",
          "tgn:7006450",
          "tgn:1000001",
          "tgn:7012149",
          "tgn:2000089",
          "tgn:7029392"
        ],
        "placetype": [
          "aat:300008706"
        ],
        "id": 2358881,
        "name:xx": "Granite Creek"
      }
    },
    {
      "geometry": {
        "type": "Point",
        "coordinates": [
          -144.2167,
          64.4
        ]
      },
      "type": "Feature",
      "properties": {
        "hierarchy": [
          "tgn:2358882",
          "tgn:7006450",
          "tgn:1000001",
          "tgn:7012149",
          "tgn:2000085",
          "tgn:7029392"
        ],
        "placetype": [
          "aat:300008706"
        ],
        "id": 2358882,
        "name:xx": "Granite Creek"
      }
    },
    {
      "geometry": {
        "type": "Point",
        "coordinates": [
          -166.1,
          64.9333
        ]
      },
      "type": "Feature",
      "properties": {
        "hierarchy": [
          "tgn:2358883",
          "tgn:7006450",
          "tgn:1000001",
          "tgn:7012149",
          "tgn:2000079",
          "tgn:7029392"
        ],
        "placetype": [
          "aat:300008706"
        ],
        "id": 2358883,
        "name:xx": "Granite Creek"
      }
    },
    {
      "geometry": {
        "type": "Point",
        "coordinates": [
          -134.3,
          58.3167
        ]
      },
      "type": "Feature",
      "properties": {
        "hierarchy": [
          "tgn:2358884",
          "tgn:7006450",
          "tgn:1000001",
          "tgn:2124089",
          "tgn:7012149",
          "tgn:7029392"
        ],
        "placetype": [
          "aat:300008706"
        ],
        "id": 2358884,
        "name:xx": "Granite Creek"
      }
    },
    {
      "geometry": {
        "type": "Point",
        "coordinates": [
          -149.2,
          60.8
        ]
      },
      "type": "Feature",
      "properties": {
        "hierarchy": [
          "tgn:2358885",
          "tgn:7006450",
          "tgn:1000001",
          "tgn:7019698",
          "tgn:7012149",
          "tgn:7029392"
        ],
        "placetype": [
          "aat:300008706"
        ],
        "id": 2358885,
        "name:xx": "Granite Creek"
      }
    },
    {
      "geometry": {
        "type": "Point",
        "coordinates": [
          -147.5,
          65.0167
        ]
      },
      "type": "Feature",
      "properties": {
        "hierarchy": [
          "tgn:2358886",
          "tgn:7006450",
          "tgn:1000001",
          "tgn:7019674",
          "tgn:7012149",
          "tgn:7029392"
        ],
        "placetype": [
          "aat:300008706"
        ],
        "id": 2358886,
        "name:xx": "Granite Creek"
      }
    },
    {
      "geometry": {
        "type": "Point",
        "coordinates": [
          -112.5,
          34.4833
        ]
      },
      "type": "Feature",
      "properties": {
        "hierarchy": [
          "tgn:2358887",
          "tgn:1000001",
          "tgn:7006451",
          "tgn:7012149",
          "tgn:2000103",
          "tgn:7029392"
        ],
        "placetype": [
          "aat:300008706"
        ],
        "id": 2358887,
        "name:xx": "Granite Creek"
      }
    },
    {
      "geometry": {
        "type": "Point",
        "coordinates": [
          -118.5833,
          36.8667
        ]
      },
      "type": "Feature",
      "properties": {
        "hierarchy": [
          "tgn:2358888",
          "tgn:1000001",
          "tgn:7012149",
          "tgn:1002392",
          "tgn:7007157",
          "tgn:7029392"
        ],
        "placetype": [
          "aat:300008706"
        ],
        "id": 2358888,
        "name:xx": "Granite Creek"
      }
    },
    {
      "geometry": {
        "type": "Point",
        "coordinates": [
          -121.9833,
          37.05
        ]
      },
      "type": "Feature",
      "properties": {
        "hierarchy": [
          "tgn:2358889",
          "tgn:1000001",
          "tgn:7012149",
          "tgn:7007157",
          "tgn:1002869",
          "tgn:7029392"
        ],
        "placetype": [
          "aat:300008706"
        ],
        "id": 2358889,
        "name:xx": "Granite Creek"
      }
    }
  ]
}
