{
  "geometry": {
    "type": "Point",
    "coordinates": [
      29.1333,
      54.6667
    ]
  },
  "type": "Feature",
  "properties": {
    "hierarchy": [
      "tgn:1057709",
      "tgn:7011701",
      "tgn:1000003",
      "tgn:7006657",
      "tgn:7029392"
    ],
    "placetype": [
      "aat:300008347"
    ],
    "id": 1057709,
    "name:xx": "Novolukoml'"
  }
}
