{
  "geometry": {
    "type": "Point",
    "coordinates": [
      -110.0167,
      40.8333
    ]
  },
  "type": "Feature",
  "properties": {
    "hierarchy": [
      "tgn:2710520",
      "tgn:1000001",
      "tgn:7012149",
      "tgn:2002122",
      "tgn:7007827",
      "tgn:7029392"
    ],
    "placetype": [
      "aat:300008680"
    ],
    "id": 2710520,
    "name:xx": "Tamarack Lake"
  }
}
