{
  "geometry": {
    "type": "Point",
    "coordinates": [
      -69.205,
      18.452
    ]
  },
  "type": "Feature",
  "properties": {
    "hierarchy": [
      "tgn:1130142",
      "tgn:1000001",
      "tgn:7005388",
      "tgn:7029392"
    ],
    "placetype": [
      "aat:300008707"
    ],
    "id": 1130142,
    "name:xx": "Soco, Río"
  }
}
