{
  "type": "FeatureCollection",
  "features": [
    {
      "geometry": {
        "type": "Point",
        "coordinates": [
          29.9,
          0.3833
        ]
      },
      "type": "Feature",
      "properties": {
        "hierarchy": [
          "tgn:1109550",
          "tgn:7001242",
          "tgn:7029392"
        ],
        "placetype": [
          "aat:300386831"
        ],
        "id": 1109550,
        "name:xx": "Ruwenzori Range"
      }
    },
    {
      "geometry": {
        "type": "Point",
        "coordinates": [
          136.75,
          36.15
        ]
      },
      "type": "Feature",
      "properties": {
        "hierarchy": [
          "tgn:1109551",
          "tgn:7000895",
          "tgn:1000004",
          "tgn:1000120",
          "tgn:7029392"
        ],
        "placetype": [
          "aat:300008795"
        ],
        "id": 1109551,
        "name:xx": "Ryōhaku-sanchi"
      }
    },
    {
      "geometry": {
        "type": "Point",
        "coordinates": [
          25.8,
          42.5333
        ]
      },
      "type": "Feature",
      "properties": {
        "hierarchy": [
          "tgn:1109552",
          "tgn:7593873",
          "tgn:1000003",
          "tgn:7006413",
          "tgn:7029392"
        ],
        "placetype": [
          "aat:300386831"
        ],
        "id": 1109552,
        "name:xx": "Sŭrnena Gora"
      }
    },
    {
      "geometry": {
        "type": "Point",
        "coordinates": [
          9.366667,
          52.2
        ]
      },
      "type": "Feature",
      "properties": {
        "hierarchy": [
          "tgn:1109554",
          "tgn:1000003",
          "tgn:7003676",
          "tgn:7000084",
          "tgn:7029392"
        ],
        "placetype": [
          "aat:300008795"
        ],
        "id": 1109554,
        "name:xx": "Süntel"
      }
    },
    {
      "geometry": {
        "type": "Point",
        "coordinates": [
          25,
          -72
        ]
      },
      "type": "Feature",
      "properties": {
        "hierarchy": [
          "tgn:1109555",
          "tgn:1000007",
          "tgn:7029392"
        ],
        "placetype": [
          "aat:300008795"
        ],
        "id": 1109555,
        "name:xx": "Sør Rondane Mountains"
      }
    },
    {
      "geometry": {
        "type": "Point",
        "coordinates": [
          12.25,
          42.166667
        ]
      },
      "type": "Feature",
      "properties": {
        "hierarchy": [
          "tgn:1109556",
          "tgn:7003139",
          "tgn:1000003",
          "tgn:7003080",
          "tgn:1000080",
          "tgn:7029392"
        ],
        "placetype": [
          "aat:300008795"
        ],
        "id": 1109556,
        "name:xx": "Sabatini, Monti"
      }
    },
    {
      "geometry": {
        "type": "Point",
        "coordinates": [
          -105.75,
          33.1167
        ]
      },
      "type": "Feature",
      "properties": {
        "hierarchy": [
          "tgn:1109558",
          "tgn:1000001",
          "tgn:7012149",
          "tgn:7007566",
          "tgn:7029392"
        ],
        "placetype": [
          "aat:300008795"
        ],
        "id": 1109558,
        "name:xx": "Sacramento Mountains"
      }
    },
    {
      "geometry": {
        "type": "Point",
        "coordinates": [
          -119.55,
          46.8
        ]
      },
      "type": "Feature",
      "properties": {
        "hierarchy": [
          "tgn:1109559",
          "tgn:1000001",
          "tgn:7012149",
          "tgn:7007920",
          "tgn:7029392"
        ],
        "placetype": [
          "aat:300008795"
        ],
        "id": 1109559,
        "name:xx": "Saddle Mountains"
      }
    }
  ]
}
