{
  "type": "FeatureCollection",
  "features": [
    {
      "geometry": {
        "type": "Point",
        "coordinates": [
          -6.05,
          57.116667
        ]
      },
      "type": "Feature",
      "properties": {
        "hierarchy": [
          "tgn:7446631",
          "tgn:7002444",
          "tgn:1000003",
          "tgn:7008082",
          "tgn:7008591",
          "tgn:7029392"
        ],
        "placetype": [
          "aat:300132316"
        ],
        "name:en": "Slapin, Loch",
        "id": 7446631
      }
    },
    {
      "geometry": {
        "type": "Point",
        "coordinates": [
          -2.033333,
          54.9
        ]
      },
      "type": "Feature",
      "properties": {
        "hierarchy": [
          "tgn:7446633",
          "tgn:7002445",
          "tgn:1000003",
          "tgn:7008165",
          "tgn:7008591",
          "tgn:7029392"
        ],
        "placetype": [
          "aat:300008347"
        ],
        "name:en": "Slaley",
        "id": 7446633
      }
    },
    {
      "geometry": {
        "type": "Point",
        "coordinates": [
          -1.816667,
          57.416667
        ]
      },
      "type": "Feature",
      "properties": {
        "hierarchy": [
          "tgn:7446635",
          "tgn:5000432",
          "tgn:7002444",
          "tgn:1000003",
          "tgn:7008591",
          "tgn:7029392"
        ],
        "placetype": [
          "aat:300004792"
        ],
        "name:en": "Slains Castle",
        "id": 7446635
      }
    },
    {
      "geometry": {
        "type": "Point",
        "coordinates": [
          -4.35,
          58.466667
        ]
      },
      "type": "Feature",
      "properties": {
        "hierarchy": [
          "tgn:7446636",
          "tgn:7002444",
          "tgn:1000003",
          "tgn:7008082",
          "tgn:7008591",
          "tgn:7029392"
        ],
        "placetype": [
          "aat:300008680"
        ],
        "name:en": "Slaim, Loch",
        "id": 7446636
      }
    },
    {
      "geometry": {
        "type": "Point",
        "coordinates": [
          -2.5,
          54.85
        ]
      },
      "type": "Feature",
      "properties": {
        "hierarchy": [
          "tgn:7446638",
          "tgn:7002445",
          "tgn:1000003",
          "tgn:7008165",
          "tgn:7008591",
          "tgn:7029392"
        ],
        "placetype": [
          "aat:300008347"
        ],
        "name:en": "Slaggyford",
        "id": 7446638
      }
    },
    {
      "geometry": {
        "type": "Point",
        "coordinates": [
          -5.633333,
          57.883333
        ]
      },
      "type": "Feature",
      "properties": {
        "hierarchy": [
          "tgn:7446639",
          "tgn:7002444",
          "tgn:1000003",
          "tgn:7008082",
          "tgn:7008591",
          "tgn:7029392"
        ],
        "placetype": [
          "aat:300008347"
        ],
        "name:en": "Slaggan",
        "id": 7446639
      }
    }
  ]
}
