{
  "type": "FeatureCollection",
  "features": [
    {
      "geometry": {
        "type": "Point",
        "coordinates": [
          14.25,
          55.4667
        ]
      },
      "type": "Feature",
      "properties": {
        "hierarchy": [
          "tgn:4000261",
          "tgn:1000003",
          "tgn:7024622",
          "tgn:1000097",
          "tgn:7029392"
        ],
        "placetype": [
          "aat:300008347"
        ],
        "id": 4000261,
        "name:xx": "Östra Hoby"
      }
    },
    {
      "geometry": {
        "type": "Point",
        "coordinates": [
          14.1,
          55.5167
        ]
      },
      "type": "Feature",
      "properties": {
        "hierarchy": [
          "tgn:4000262",
          "tgn:1000003",
          "tgn:7024622",
          "tgn:1000097",
          "tgn:7029392"
        ],
        "placetype": [
          "aat:300008347"
        ],
        "id": 4000262,
        "name:xx": "Östra Ingelstad"
      }
    },
    {
      "geometry": {
        "type": "Point",
        "coordinates": [
          34.8667,
          38.6667
        ]
      },
      "type": "Feature",
      "properties": {
        "hierarchy": [
          "tgn:4000266",
          "tgn:1001451",
          "tgn:1000004",
          "tgn:7018453",
          "tgn:1000144",
          "tgn:7029392"
        ],
        "placetype": [
          "aat:300008347",
          "aat:300008375"
        ],
        "id": 4000266,
        "name:xx": "Çavuşin"
      }
    }
  ]
}
