{
  "geometry": {
    "type": "Point",
    "coordinates": [
      72.933179,
      27.614877
    ]
  },
  "type": "Feature",
  "properties": {
    "hierarchy": [
      "tgn:7583384",
      "tgn:1000004",
      "tgn:7000198",
      "tgn:7016788",
      "tgn:7029392"
    ],
    "placetype": [
      "aat:300008347"
    ],
    "name:en": "Lambāna Mūlvān",
    "id": 7583384
  }
}
