{
  "geometry": {
    "type": "Point",
    "coordinates": [
      31.786111,
      30.66
    ]
  },
  "type": "Feature",
  "properties": {
    "hierarchy": [
      "tgn:7520931",
      "tgn:7001242",
      "tgn:7016833",
      "tgn:1001113",
      "tgn:7029392"
    ],
    "placetype": [
      "aat:300008347"
    ],
    "name:en": "Al Khaţţārah aş Şughrá",
    "id": 7520931
  }
}
