{
  "geometry": {
    "type": "Point",
    "coordinates": [
      118.9667,
      28.9833
    ]
  },
  "type": "Feature",
  "properties": {
    "hierarchy": [
      "tgn:1131899",
      "tgn:1000004",
      "tgn:1000111",
      "tgn:7029392"
    ],
    "placetype": [
      "aat:300008707"
    ],
    "id": 1131899,
    "name:xx": "Wuxi Jiang"
  }
}
