{
  "geometry": {
    "type": "Point",
    "coordinates": [
      121.8439,
      24.5836
    ]
  },
  "type": "Feature",
  "properties": {
    "hierarchy": [
      "tgn:7478646",
      "tgn:1000004",
      "tgn:7489179",
      "tgn:1000141",
      "tgn:7029392"
    ],
    "placetype": [
      "aat:300007899"
    ],
    "id": 7478646,
    "name:xx": "Erhao Suidao"
  }
}
