{
  "geometry": {
    "type": "Point",
    "coordinates": [
      74.32656,
      32.998107
    ]
  },
  "type": "Feature",
  "properties": {
    "hierarchy": [
      "tgn:7591028",
      "tgn:1000004",
      "tgn:7000198",
      "tgn:7000799",
      "tgn:7029392"
    ],
    "placetype": [
      "aat:300008347"
    ],
    "name:en": "Māhāder",
    "id": 7591028
  }
}
