{
  "geometry": {
    "type": "Point",
    "coordinates": [
      24.8333,
      54.5167
    ]
  },
  "type": "Feature",
  "properties": {
    "hierarchy": [
      "tgn:1058796",
      "tgn:1000003",
      "tgn:7006613",
      "tgn:7006542",
      "tgn:7029392"
    ],
    "placetype": [
      "aat:300008347"
    ],
    "id": 1058796,
    "name:xx": "Rūdiškės"
  }
}
