{
  "geometry": {
    "type": "Point",
    "coordinates": [
      -75.3333,
      38.3667
    ]
  },
  "type": "Feature",
  "properties": {
    "hierarchy": [
      "tgn:2138961",
      "tgn:1000001",
      "tgn:1003023",
      "tgn:7012149",
      "tgn:7007516",
      "tgn:7029392"
    ],
    "placetype": [
      "aat:300008699"
    ],
    "id": 2138961,
    "name:xx": "Asherwood Branch"
  }
}
