{
  "geometry": {
    "type": "Point",
    "coordinates": [
      -119.3333,
      47.5833
    ]
  },
  "type": "Feature",
  "properties": {
    "hierarchy": [
      "tgn:2503933",
      "tgn:1000001",
      "tgn:7012149",
      "tgn:2002246",
      "tgn:7007920",
      "tgn:7029392"
    ],
    "placetype": [
      "aat:300008706"
    ],
    "id": 2503933,
    "name:xx": "Meadow Creek"
  }
}
