{
  "geometry": {
    "type": "Point",
    "coordinates": [
      -99.5333,
      34.5167
    ]
  },
  "type": "Feature",
  "properties": {
    "hierarchy": [
      "tgn:2083084",
      "tgn:1000001",
      "tgn:7012149",
      "tgn:2001655",
      "tgn:7007707",
      "tgn:7029392"
    ],
    "placetype": [
      "aat:300387016"
    ],
    "id": 2083084,
    "name:xx": "Creta"
  }
}
