{
  "geometry": {
    "type": "Point",
    "coordinates": [
      -81.45,
      38.6667
    ]
  },
  "type": "Feature",
  "properties": {
    "hierarchy": [
      "tgn:2624400",
      "tgn:1000001",
      "tgn:7012149",
      "tgn:2002293",
      "tgn:7013961",
      "tgn:7029392"
    ],
    "placetype": [
      "aat:300008699"
    ],
    "id": 2624400,
    "name:xx": "Rock Lick Branch"
  }
}
