{
  "geometry": {
    "type": "Point",
    "coordinates": [
      -79.0167,
      35.7333
    ]
  },
  "type": "Feature",
  "properties": {
    "hierarchy": [
      "tgn:2650120",
      "tgn:1000001",
      "tgn:2001480",
      "tgn:7012149",
      "tgn:7007709",
      "tgn:7029392"
    ],
    "placetype": [
      "aat:300008680"
    ],
    "id": 2650120,
    "name:xx": "Seaforth Lake"
  }
}
