{
  "geometry": {
    "type": "Point",
    "coordinates": [
      -90.85,
      36.45
    ]
  },
  "type": "Feature",
  "properties": {
    "hierarchy": [
      "tgn:2777589",
      "tgn:1000001",
      "tgn:7016172",
      "tgn:7012149",
      "tgn:2000165",
      "tgn:7029392"
    ],
    "placetype": [
      "aat:300008706"
    ],
    "id": 2777589,
    "name:xx": "Winningham Creek"
  }
}
