{
  "geometry": {
    "type": "Point",
    "coordinates": [
      -81.6167,
      36.6333
    ]
  },
  "type": "Feature",
  "properties": {
    "hierarchy": [
      "tgn:2212195",
      "tgn:1000001",
      "tgn:7012149",
      "tgn:7007919",
      "tgn:7029392"
    ],
    "placetype": [
      "aat:300008798"
    ],
    "id": 2212195,
    "name:xx": "Buzzard Rock"
  }
}
