{
  "type": "FeatureCollection",
  "features": [
    {
      "geometry": {
        "type": "Point",
        "coordinates": [
          -115.95,
          47.0667
        ]
      },
      "type": "Feature",
      "properties": {
        "hierarchy": [
          "tgn:2469650",
          "tgn:1000001",
          "tgn:7012149",
          "tgn:2000491",
          "tgn:7007250",
          "tgn:7029392"
        ],
        "placetype": [
          "aat:300008798"
        ],
        "id": 2469650,
        "name:xx": "Lookout Mountain"
      }
    },
    {
      "geometry": {
        "type": "Point",
        "coordinates": [
          -116.7667,
          48.7667
        ]
      },
      "type": "Feature",
      "properties": {
        "hierarchy": [
          "tgn:2469651",
          "tgn:1000001",
          "tgn:2000462",
          "tgn:7012149",
          "tgn:7007250",
          "tgn:7029392"
        ],
        "placetype": [
          "aat:300008798"
        ],
        "id": 2469651,
        "name:xx": "Lookout Mountain"
      }
    },
    {
      "geometry": {
        "type": "Point",
        "coordinates": [
          -95.1667,
          39.8833
        ]
      },
      "type": "Feature",
      "properties": {
        "hierarchy": [
          "tgn:2469652",
          "tgn:1000001",
          "tgn:2000681",
          "tgn:7012149",
          "tgn:7007254",
          "tgn:7029392"
        ],
        "placetype": [
          "aat:300008798"
        ],
        "id": 2469652,
        "name:xx": "Lookout Mountain"
      }
    },
    {
      "geometry": {
        "type": "Point",
        "coordinates": [
          -67.8667,
          44.5
        ]
      },
      "type": "Feature",
      "properties": {
        "hierarchy": [
          "tgn:2469653",
          "tgn:1000001",
          "tgn:7012149",
          "tgn:7014589",
          "tgn:7007515",
          "tgn:7029392"
        ],
        "placetype": [
          "aat:300008798"
        ],
        "id": 2469653,
        "name:xx": "Lookout Mountain"
      }
    },
    {
      "geometry": {
        "type": "Point",
        "coordinates": [
          -68.2667,
          45.3333
        ]
      },
      "type": "Feature",
      "properties": {
        "hierarchy": [
          "tgn:2469654",
          "tgn:1000001",
          "tgn:7012149",
          "tgn:2000927",
          "tgn:7007515",
          "tgn:7029392"
        ],
        "placetype": [
          "aat:300008798"
        ],
        "id": 2469654,
        "name:xx": "Lookout Mountain"
      }
    },
    {
      "geometry": {
        "type": "Point",
        "coordinates": [
          -95.6333,
          45.8167
        ]
      },
      "type": "Feature",
      "properties": {
        "hierarchy": [
          "tgn:2469655",
          "tgn:1000001",
          "tgn:2001019",
          "tgn:7012149",
          "tgn:7007521",
          "tgn:7029392"
        ],
        "placetype": [
          "aat:300008798"
        ],
        "id": 2469655,
        "name:xx": "Lookout Mountain"
      }
    },
    {
      "geometry": {
        "type": "Point",
        "coordinates": [
          -92.5333,
          47.5667
        ]
      },
      "type": "Feature",
      "properties": {
        "hierarchy": [
          "tgn:2469656",
          "tgn:1000001",
          "tgn:7012149",
          "tgn:2001067",
          "tgn:7007521",
          "tgn:7029392"
        ],
        "placetype": [
          "aat:300008798"
        ],
        "id": 2469656,
        "name:xx": "Lookout Mountain"
      }
    },
    {
      "geometry": {
        "type": "Point",
        "coordinates": [
          -91.25,
          39.6333
        ]
      },
      "type": "Feature",
      "properties": {
        "hierarchy": [
          "tgn:2469657",
          "tgn:1000001",
          "tgn:7012149",
          "tgn:1002817",
          "tgn:7007523",
          "tgn:7029392"
        ],
        "placetype": [
          "aat:300008798"
        ],
        "id": 2469657,
        "name:xx": "Lookout Mountain"
      }
    },
    {
      "geometry": {
        "type": "Point",
        "coordinates": [
          -110.2167,
          45.0833
        ]
      },
      "type": "Feature",
      "properties": {
        "hierarchy": [
          "tgn:2469659",
          "tgn:1000001",
          "tgn:7012149",
          "tgn:2001293",
          "tgn:7007524",
          "tgn:7029392"
        ],
        "placetype": [
          "aat:300008798"
        ],
        "id": 2469659,
        "name:xx": "Lookout Mountain"
      }
    }
  ]
}
