{
  "geometry": {
    "type": "Point",
    "coordinates": [
      5.65,
      62.3667
    ]
  },
  "type": "Feature",
  "properties": {
    "hierarchy": [
      "tgn:1048545",
      "tgn:7003647",
      "tgn:1000003",
      "tgn:1000088",
      "tgn:7029392"
    ],
    "placetype": [
      "aat:300008347"
    ],
    "id": 1048545,
    "name:xx": "Fosnavåg"
  }
}
