{
  "geometry": {
    "type": "Point",
    "coordinates": [
      -76.7333,
      38.9333
    ]
  },
  "type": "Feature",
  "properties": {
    "hierarchy": [
      "tgn:2512094",
      "tgn:1000001",
      "tgn:2124001",
      "tgn:7012149",
      "tgn:7007516",
      "tgn:7029392"
    ],
    "placetype": [
      "aat:300008699"
    ],
    "id": 2512094,
    "name:xx": "Mill Branch"
  }
}
