{
  "geometry": {
    "type": "Point",
    "coordinates": [
      -85.75,
      37.3667
    ]
  },
  "type": "Feature",
  "properties": {
    "hierarchy": [
      "tgn:2464039",
      "tgn:1000001",
      "tgn:7012149",
      "tgn:2000798",
      "tgn:7007255",
      "tgn:7029392"
    ],
    "placetype": [
      "aat:300008699"
    ],
    "id": 2464039,
    "name:xx": "Locust Branch"
  }
}
