{
  "geometry": {
    "type": "Point",
    "coordinates": [
      69.4833,
      40.2167
    ]
  },
  "type": "Feature",
  "properties": {
    "hierarchy": [
      "tgn:1124989",
      "tgn:1000004",
      "tgn:7029392"
    ],
    "placetype": [
      "aat:300008707"
    ],
    "id": 1124989,
    "name:xx": "Isfana"
  }
}
