{
  "geometry": {
    "type": "Point",
    "coordinates": [
      -89.7667,
      46.15
    ]
  },
  "type": "Feature",
  "properties": {
    "hierarchy": [
      "tgn:2433066",
      "tgn:1000001",
      "tgn:7012149",
      "tgn:2002359",
      "tgn:7007922",
      "tgn:7029392"
    ],
    "placetype": [
      "aat:300008791"
    ],
    "id": 2433066,
    "name:xx": "Keith Island"
  }
}
