{
  "geometry": {
    "type": "Point",
    "coordinates": [
      31.366667,
      30.816667
    ]
  },
  "type": "Feature",
  "properties": {
    "hierarchy": [
      "tgn:7528037",
      "tgn:7001242",
      "tgn:1001059",
      "tgn:7016833",
      "tgn:7029392"
    ],
    "placetype": [
      "aat:300005926"
    ],
    "name:en": "S카d카 'Abd al Kar카m Bin 'In훮n",
    "id": 7528037
  }
}
