{
  "geometry": {
    "type": "Point",
    "coordinates": [
      -71.633,
      18.816
    ]
  },
  "type": "Feature",
  "properties": {
    "hierarchy": [
      "tgn:7593395",
      "tgn:7005403",
      "tgn:1000001",
      "tgn:7005388",
      "tgn:7029392"
    ],
    "placetype": [
      "aat:300008347"
    ],
    "id": 7593395,
    "name:xx": "El Llano"
  }
}
