{
  "geometry": {
    "type": "Point",
    "coordinates": [
      -106.85,
      39.0333
    ]
  },
  "type": "Feature",
  "properties": {
    "hierarchy": [
      "tgn:2226064",
      "tgn:1000001",
      "tgn:7012149",
      "tgn:7007158",
      "tgn:2000240",
      "tgn:7029392"
    ],
    "placetype": [
      "aat:300008706"
    ],
    "id": 2226064,
    "name:xx": "Cataract Creek"
  }
}
