{
  "geometry": {
    "type": "Point",
    "coordinates": [
      -76.0833,
      43.2333
    ]
  },
  "type": "Feature",
  "properties": {
    "hierarchy": [
      "tgn:2656053",
      "tgn:1000001",
      "tgn:7012149",
      "tgn:1002758",
      "tgn:7007568",
      "tgn:7029392"
    ],
    "placetype": [
      "aat:300008850"
    ],
    "id": 2656053,
    "name:xx": "Shaw Point"
  }
}
