{
  "type": "FeatureCollection",
  "features": [
    {
      "geometry": {
        "type": "Point",
        "coordinates": [
          -80.3333,
          39.3667
        ]
      },
      "type": "Feature",
      "properties": {
        "hierarchy": [
          "tgn:2119030",
          "tgn:1000001",
          "tgn:7012149",
          "tgn:2002267",
          "tgn:7013961",
          "tgn:7029392"
        ],
        "placetype": [
          "aat:300008347"
        ],
        "id": 2119030,
        "name:xx": "Lumberport"
      }
    },
    {
      "geometry": {
        "type": "Point",
        "coordinates": [
          -81.7333,
          37.8
        ]
      },
      "type": "Feature",
      "properties": {
        "hierarchy": [
          "tgn:2119031",
          "tgn:1000001",
          "tgn:7012149",
          "tgn:2002273",
          "tgn:7013961",
          "tgn:7029392"
        ],
        "placetype": [
          "aat:300008347"
        ],
        "id": 2119031,
        "name:xx": "Lundale"
      }
    },
    {
      "geometry": {
        "type": "Point",
        "coordinates": [
          -81.9167,
          37.8
        ]
      },
      "type": "Feature",
      "properties": {
        "hierarchy": [
          "tgn:2119034",
          "tgn:1000001",
          "tgn:7012149",
          "tgn:2002273",
          "tgn:7013961",
          "tgn:7029392"
        ],
        "placetype": [
          "aat:300008347"
        ],
        "id": 2119034,
        "name:xx": "Lyburn"
      }
    },
    {
      "geometry": {
        "type": "Point",
        "coordinates": [
          -81.6667,
          37.6833
        ]
      },
      "type": "Feature",
      "properties": {
        "hierarchy": [
          "tgn:2119035",
          "tgn:1000001",
          "tgn:7012149",
          "tgn:2002304",
          "tgn:7013961",
          "tgn:7029392"
        ],
        "placetype": [
          "aat:300008347"
        ],
        "id": 2119035,
        "name:xx": "Lynco"
      }
    },
    {
      "geometry": {
        "type": "Point",
        "coordinates": [
          -82.15,
          37.6
        ]
      },
      "type": "Feature",
      "properties": {
        "hierarchy": [
          "tgn:2119036",
          "tgn:1000001",
          "tgn:7012149",
          "tgn:2002280",
          "tgn:7013961",
          "tgn:7029392"
        ],
        "placetype": [
          "aat:300008347"
        ],
        "id": 2119036,
        "name:xx": "Lynn"
      }
    },
    {
      "geometry": {
        "type": "Point",
        "coordinates": [
          -80.7,
          39.7667
        ]
      },
      "type": "Feature",
      "properties": {
        "hierarchy": [
          "tgn:2119037",
          "tgn:1000001",
          "tgn:7012149",
          "tgn:2002276",
          "tgn:7013961",
          "tgn:7029392"
        ],
        "placetype": [
          "aat:300008347"
        ],
        "id": 2119037,
        "name:xx": "Lynn Camp"
      }
    },
    {
      "geometry": {
        "type": "Point",
        "coordinates": [
          -81.2167,
          37.6667
        ]
      },
      "type": "Feature",
      "properties": {
        "hierarchy": [
          "tgn:2119038",
          "tgn:1000001",
          "tgn:7012149",
          "tgn:2002290",
          "tgn:7013961",
          "tgn:7029392"
        ],
        "placetype": [
          "aat:300008347",
          "aat:300387210"
        ],
        "id": 2119038,
        "name:xx": "Lynwinn"
      }
    },
    {
      "geometry": {
        "type": "Point",
        "coordinates": [
          -81.05,
          38.25
        ]
      },
      "type": "Feature",
      "properties": {
        "hierarchy": [
          "tgn:2119039",
          "tgn:1000001",
          "tgn:7012149",
          "tgn:2002284",
          "tgn:7013961",
          "tgn:7029392"
        ],
        "placetype": [
          "aat:300008347"
        ],
        "id": 2119039,
        "name:xx": "Lyonsville"
      }
    }
  ]
}
