{
  "geometry": {
    "type": "Point",
    "coordinates": [
      -91.5167,
      45.9167
    ]
  },
  "type": "Feature",
  "properties": {
    "hierarchy": [
      "tgn:2153305",
      "tgn:1000001",
      "tgn:7012149",
      "tgn:7007922",
      "tgn:7029392"
    ],
    "placetype": [
      "aat:300008699"
    ],
    "id": 2153305,
    "name:xx": "Bean Brook"
  }
}
