{
  "geometry": {
    "type": "Point",
    "coordinates": [
      -121.2667,
      37.1167
    ]
  },
  "type": "Feature",
  "properties": {
    "hierarchy": [
      "tgn:2533643",
      "tgn:1000001",
      "tgn:7012149",
      "tgn:7007157",
      "tgn:7014475",
      "tgn:7029392"
    ],
    "placetype": [
      "aat:300266640"
    ],
    "id": 2533643,
    "name:xx": "Mustang Ridge"
  }
}
