{
  "geometry": {
    "type": "Point",
    "coordinates": [
      -116.7667,
      34.1833
    ]
  },
  "type": "Feature",
  "properties": {
    "hierarchy": [
      "tgn:2771456",
      "tgn:1000001",
      "tgn:7012149",
      "tgn:7007157",
      "tgn:1002857",
      "tgn:7029392"
    ],
    "placetype": [
      "aat:300008706"
    ],
    "id": 2771456,
    "name:xx": "Wildhorse Creek"
  }
}
