{
  "geometry": {
    "type": "Point",
    "coordinates": [
      -81.3667,
      36.3333
    ]
  },
  "type": "Feature",
  "properties": {
    "hierarchy": [
      "tgn:2189969",
      "tgn:1000001",
      "tgn:7012149",
      "tgn:7007709",
      "tgn:7029392"
    ],
    "placetype": [
      "aat:300008706"
    ],
    "id": 2189969,
    "name:xx": "Bowlin Creek"
  }
}
