{
  "geometry": {
    "type": "Point",
    "coordinates": [
      44.1333,
      10.55
    ]
  },
  "type": "Feature",
  "properties": {
    "hierarchy": [
      "tgn:1092758",
      "tgn:7001242",
      "tgn:1001774",
      "tgn:1000192",
      "tgn:7029392"
    ],
    "placetype": [
      "aat:300008347"
    ],
    "id": 1092758,
    "name:xx": "Saba Wanak"
  }
}
