{
  "geometry": {
    "type": "Point",
    "coordinates": [
      -80.3333,
      37.0333
    ]
  },
  "type": "Feature",
  "properties": {
    "hierarchy": [
      "tgn:2150278",
      "tgn:1000001",
      "tgn:7012149",
      "tgn:2002174",
      "tgn:7007919",
      "tgn:7029392"
    ],
    "placetype": [
      "aat:300008347"
    ],
    "id": 2150278,
    "name:xx": "Basham"
  }
}
