{
  "geometry": {
    "type": "Point",
    "coordinates": [
      0.6333,
      52.0333
    ]
  },
  "type": "Feature",
  "properties": {
    "hierarchy": [
      "tgn:4001352",
      "tgn:7002445",
      "tgn:1000003",
      "tgn:7008131",
      "tgn:7008591",
      "tgn:7029392"
    ],
    "placetype": [
      "aat:300008347"
    ],
    "id": 4001352,
    "name:xx": "Belchamp Walter"
  }
}
