{
  "type": "FeatureCollection",
  "features": [
    {
      "geometry": {
        "type": "Point",
        "coordinates": [
          -4.016667,
          37.316667
        ]
      },
      "type": "Feature",
      "properties": {
        "hierarchy": [
          "tgn:7008091",
          "tgn:7002758",
          "tgn:7002821",
          "tgn:1000003",
          "tgn:1000095",
          "tgn:7029392"
        ],
        "placetype": [
          "aat:300008347"
        ],
        "id": 7008091,
        "name:xx": "Montefrío"
      }
    },
    {
      "geometry": {
        "type": "Point",
        "coordinates": [
          -4.3333,
          56.0833
        ]
      },
      "type": "Feature",
      "properties": {
        "hierarchy": [
          "tgn:7008092",
          "tgn:7002444",
          "tgn:1000003",
          "tgn:7008591",
          "tgn:7029392"
        ],
        "placetype": [
          "aat:300008631",
          "aat:300387302",
          "aat:300236112"
        ],
        "id": 7008092,
        "name:xx": "Central"
      }
    },
    {
      "geometry": {
        "type": "Point",
        "coordinates": [
          0.194091,
          41.913584
        ]
      },
      "type": "Feature",
      "properties": {
        "hierarchy": [
          "tgn:7008093",
          "tgn:7002759",
          "tgn:7008909",
          "tgn:1000003",
          "tgn:1000095",
          "tgn:7029392"
        ],
        "placetype": [
          "aat:300008347"
        ],
        "id": 7008093,
        "name:xx": "Monzón"
      }
    },
    {
      "geometry": {
        "type": "Point",
        "coordinates": [
          -7,
          57.6667
        ]
      },
      "type": "Feature",
      "properties": {
        "hierarchy": [
          "tgn:7008094",
          "tgn:7002444",
          "tgn:1000003",
          "tgn:7008591",
          "tgn:7029392"
        ],
        "placetype": [
          "aat:300387064",
          "aat:300387145",
          "aat:300386853",
          "aat:300387172",
          "aat:300236112",
          "aat:300387071"
        ],
        "name:en": "Eilean Siar",
        "id": 7008094
      }
    },
    {
      "geometry": {
        "type": "Point",
        "coordinates": [
          -3.766667,
          39.683333
        ]
      },
      "type": "Feature",
      "properties": {
        "hierarchy": [
          "tgn:7008097",
          "tgn:7002847",
          "tgn:1001647",
          "tgn:1000003",
          "tgn:1000095",
          "tgn:7029392"
        ],
        "placetype": [
          "aat:300008347"
        ],
        "id": 7008097,
        "name:xx": "Mora"
      }
    },
    {
      "geometry": {
        "type": "Point",
        "coordinates": [
          -3.7,
          42.7
        ]
      },
      "type": "Feature",
      "properties": {
        "hierarchy": [
          "tgn:7008098",
          "tgn:7002810",
          "tgn:7001158",
          "tgn:1000003",
          "tgn:1000095",
          "tgn:7029392"
        ],
        "placetype": [
          "aat:300008347"
        ],
        "id": 7008098,
        "name:xx": "Moradillo de Sedano"
      }
    }
  ]
}
