{
  "geometry": {
    "type": "Point",
    "coordinates": [
      -93.5333,
      34.75
    ]
  },
  "type": "Feature",
  "properties": {
    "hierarchy": [
      "tgn:2694933",
      "tgn:1000001",
      "tgn:7016172",
      "tgn:7012149",
      "tgn:2000179",
      "tgn:7029392"
    ],
    "placetype": [
      "aat:300008699"
    ],
    "id": 2694933,
    "name:xx": "Still Branch"
  }
}
