{
  "geometry": {
    "type": "Point",
    "coordinates": [
      -106.15,
      34.4333
    ]
  },
  "type": "Feature",
  "properties": {
    "hierarchy": [
      "tgn:2233986",
      "tgn:1000001",
      "tgn:7012149",
      "tgn:2001458",
      "tgn:7007566",
      "tgn:7029392"
    ],
    "placetype": [
      "aat:300008701"
    ],
    "id": 2233986,
    "name:xx": "Chaves Draw"
  }
}
