{
  "geometry": {
    "type": "Point",
    "coordinates": [
      78.383333,
      11.05
    ]
  },
  "type": "Feature",
  "properties": {
    "hierarchy": [
      "tgn:7546791",
      "tgn:1000004",
      "tgn:7000198",
      "tgn:7001797",
      "tgn:7029392"
    ],
    "placetype": [
      "aat:300008347"
    ],
    "name:en": "Appananallūr",
    "id": 7546791
  }
}
