{
  "geometry": {
    "type": "Point",
    "coordinates": [
      -83.0667,
      37.4833
    ]
  },
  "type": "Feature",
  "properties": {
    "hierarchy": [
      "tgn:2474978",
      "tgn:1000001",
      "tgn:7012149",
      "tgn:2000805",
      "tgn:7007255",
      "tgn:7029392"
    ],
    "placetype": [
      "aat:300008699"
    ],
    "id": 2474978,
    "name:xx": "Lower Whit Branch"
  }
}
