{
  "geometry": {
    "type": "Point",
    "coordinates": [
      -78.8333,
      34.7333
    ]
  },
  "type": "Feature",
  "properties": {
    "hierarchy": [
      "tgn:2201404",
      "tgn:1000001",
      "tgn:2001471",
      "tgn:7012149",
      "tgn:7007709",
      "tgn:7029392"
    ],
    "placetype": [
      "aat:300008699"
    ],
    "id": 2201404,
    "name:xx": "Buck Branch"
  }
}
