{
  "geometry": {
    "type": "Point",
    "coordinates": [
      9.65,
      54.15
    ]
  },
  "type": "Feature",
  "properties": {
    "hierarchy": [
      "tgn:7175983",
      "tgn:1000003",
      "tgn:7003688",
      "tgn:7000084",
      "tgn:7029392"
    ],
    "placetype": [
      "aat:300000206"
    ],
    "id": 7175983,
    "name:xx": "Grevensberg"
  }
}
