{
  "geometry": {
    "type": "Point",
    "coordinates": [
      -117.8333,
      48.35
    ]
  },
  "type": "Feature",
  "properties": {
    "hierarchy": [
      "tgn:2115193",
      "tgn:1000001",
      "tgn:7012149",
      "tgn:2002250",
      "tgn:7007920",
      "tgn:7029392"
    ],
    "placetype": [
      "aat:300008347"
    ],
    "id": 2115193,
    "name:xx": "Addy"
  }
}
