{
  "geometry": {
    "type": "Point",
    "coordinates": [
      -98.45,
      34.6833
    ]
  },
  "type": "Feature",
  "properties": {
    "hierarchy": [
      "tgn:2392059",
      "tgn:1000001",
      "tgn:2001638",
      "tgn:7012149",
      "tgn:7007707",
      "tgn:7029392"
    ],
    "placetype": [
      "aat:300008798"
    ],
    "id": 2392059,
    "name:xx": "Hinds, Mount"
  }
}
