{
  "geometry": {
    "type": "Point",
    "coordinates": [
      79.738178,
      22.213836
    ]
  },
  "type": "Feature",
  "properties": {
    "hierarchy": [
      "tgn:7575710",
      "tgn:1000004",
      "tgn:7000198",
      "tgn:1001894",
      "tgn:7029392"
    ],
    "placetype": [
      "aat:300008347"
    ],
    "name:en": "Kaniwāra",
    "id": 7575710
  }
}
