{
  "geometry": {
    "type": "Point",
    "coordinates": [
      -85.6667,
      35.5333
    ]
  },
  "type": "Feature",
  "properties": {
    "hierarchy": [
      "tgn:2404519",
      "tgn:1000001",
      "tgn:7012149",
      "tgn:2001925",
      "tgn:7007825",
      "tgn:7029392"
    ],
    "placetype": [
      "aat:300008746"
    ],
    "id": 2404519,
    "name:xx": "Hubbards Cave"
  }
}
