{
  "geometry": {
    "type": "Point",
    "coordinates": [
      13.9667,
      47.85
    ]
  },
  "type": "Feature",
  "properties": {
    "hierarchy": [
      "tgn:7003275",
      "tgn:7003026",
      "tgn:1000003",
      "tgn:1000062",
      "tgn:7029392"
    ],
    "placetype": [
      "aat:300008347"
    ],
    "id": 7003275,
    "name:xx": "Grünau"
  }
}
