{
  "geometry": {
    "type": "Point",
    "coordinates": [
      89.65,
      23.1833
    ]
  },
  "type": "Feature",
  "properties": {
    "hierarchy": [
      "tgn:1065794",
      "tgn:1000004",
      "tgn:7000190",
      "tgn:1000105",
      "tgn:7029392"
    ],
    "placetype": [
      "aat:300008347"
    ],
    "id": 1065794,
    "name:xx": "Lohāgara"
  }
}
