{
  "geometry": {
    "type": "Point",
    "coordinates": [
      75.701942,
      26.940032
    ]
  },
  "type": "Feature",
  "properties": {
    "hierarchy": [
      "tgn:7559926",
      "tgn:1000004",
      "tgn:7000198",
      "tgn:7016788",
      "tgn:7029392"
    ],
    "placetype": [
      "aat:300008347"
    ],
    "name:en": "P카th훮w훮s ki Dh훮ni",
    "id": 7559926
  }
}
