{
  "geometry": {
    "type": "Point",
    "coordinates": [
      12.933333,
      50.65
    ]
  },
  "type": "Feature",
  "properties": {
    "hierarchy": [
      "tgn:7071152",
      "tgn:1000003",
      "tgn:7003685",
      "tgn:7000084",
      "tgn:7029392"
    ],
    "placetype": [
      "aat:300008746"
    ],
    "id": 7071152,
    "name:xx": "Stülpnerhöhle"
  }
}
