{
  "geometry": {
    "type": "Point",
    "coordinates": [
      -80.6833,
      40.1667
    ]
  },
  "type": "Feature",
  "properties": {
    "hierarchy": [
      "tgn:2390332",
      "tgn:1000001",
      "tgn:7012149",
      "tgn:1002519",
      "tgn:7007706",
      "tgn:7029392"
    ],
    "placetype": [
      "aat:300008347"
    ],
    "id": 2390332,
    "name:xx": "Highland City"
  }
}
