{
  "geometry": {
    "type": "Point",
    "coordinates": [
      121.54925,
      24.3608
    ]
  },
  "type": "Feature",
  "properties": {
    "hierarchy": [
      "tgn:7472309",
      "tgn:1000004",
      "tgn:7489179",
      "tgn:1000141",
      "tgn:7029392"
    ],
    "placetype": [
      "aat:300008699"
    ],
    "id": 7472309,
    "name:xx": "Wulai Xi"
  }
}
