{
  "type": "FeatureCollection",
  "features": [
    {
      "geometry": {
        "type": "Point",
        "coordinates": [
          -107.133333,
          25.916667
        ]
      },
      "type": "Feature",
      "properties": {
        "hierarchy": [
          "tgn:7365911",
          "tgn:7005581",
          "tgn:1000001",
          "tgn:7005560",
          "tgn:7029392"
        ],
        "placetype": [
          "aat:300008347"
        ],
        "id": 7365911,
        "name:xx": "Galeana"
      }
    },
    {
      "geometry": {
        "type": "Point",
        "coordinates": [
          -104.4,
          24.55
        ]
      },
      "type": "Feature",
      "properties": {
        "hierarchy": [
          "tgn:7365914",
          "tgn:7005583",
          "tgn:1000001",
          "tgn:7005560",
          "tgn:7029392"
        ],
        "placetype": [
          "aat:300008347"
        ],
        "id": 7365914,
        "name:xx": "Galeana"
      }
    },
    {
      "geometry": {
        "type": "Point",
        "coordinates": [
          -102.483333,
          19.083333
        ]
      },
      "type": "Feature",
      "properties": {
        "hierarchy": [
          "tgn:7365915",
          "tgn:1000001",
          "tgn:7005590",
          "tgn:7005560",
          "tgn:7029392"
        ],
        "placetype": [
          "aat:300008347"
        ],
        "id": 7365915,
        "name:xx": "Galeana"
      }
    },
    {
      "geometry": {
        "type": "Point",
        "coordinates": [
          -101.566667,
          18.283333
        ]
      },
      "type": "Feature",
      "properties": {
        "hierarchy": [
          "tgn:7365916",
          "tgn:7005585",
          "tgn:1000001",
          "tgn:7005560",
          "tgn:7029392"
        ],
        "placetype": [
          "aat:300008347"
        ],
        "id": 7365916,
        "name:xx": "Galeana"
      }
    },
    {
      "geometry": {
        "type": "Point",
        "coordinates": [
          -90.866667,
          16.15
        ]
      },
      "type": "Feature",
      "properties": {
        "hierarchy": [
          "tgn:7365917",
          "tgn:7005580",
          "tgn:1000001",
          "tgn:7005560",
          "tgn:7029392"
        ],
        "placetype": [
          "aat:300008347"
        ],
        "id": 7365917,
        "name:xx": "Galaxia"
      }
    },
    {
      "geometry": {
        "type": "Point",
        "coordinates": [
          -93.733333,
          16.033333
        ]
      },
      "type": "Feature",
      "properties": {
        "hierarchy": [
          "tgn:7365918",
          "tgn:7005580",
          "tgn:1000001",
          "tgn:7005560",
          "tgn:7029392"
        ],
        "placetype": [
          "aat:300008347"
        ],
        "id": 7365918,
        "name:xx": "Galaor"
      }
    },
    {
      "geometry": {
        "type": "Point",
        "coordinates": [
          -101.183333,
          28.783333
        ]
      },
      "type": "Feature",
      "properties": {
        "hierarchy": [
          "tgn:7365919",
          "tgn:1001853",
          "tgn:1000001",
          "tgn:7005560",
          "tgn:7029392"
        ],
        "placetype": [
          "aat:300266554",
          "aat:300008699"
        ],
        "id": 7365919,
        "name:xx": "Galán, Arroyo"
      }
    }
  ]
}
