{
  "geometry": {
    "type": "Point",
    "coordinates": [
      -92.25,
      30.8667
    ]
  },
  "type": "Feature",
  "properties": {
    "hierarchy": [
      "tgn:2176610",
      "tgn:1000001",
      "tgn:2000873",
      "tgn:7012149",
      "tgn:7007256",
      "tgn:7029392"
    ],
    "placetype": [
      "aat:300008699"
    ],
    "id": 2176610,
    "name:xx": "Black Lake Bayou"
  }
}
