{
  "geometry": {
    "type": "Point",
    "coordinates": [
      -149.3833,
      61.2167
    ]
  },
  "type": "Feature",
  "properties": {
    "hierarchy": [
      "tgn:2377442",
      "tgn:2124017",
      "tgn:7006450",
      "tgn:1000001",
      "tgn:7012149",
      "tgn:7029392"
    ],
    "placetype": [
      "aat:300008798"
    ],
    "id": 2377442,
    "name:xx": "Harp Mountain"
  }
}
