{
  "geometry": {
    "type": "Point",
    "coordinates": [
      -104.1667,
      35.2167
    ]
  },
  "type": "Feature",
  "properties": {
    "hierarchy": [
      "tgn:2136176",
      "tgn:1000001",
      "tgn:7012149",
      "tgn:2001453",
      "tgn:7007566",
      "tgn:7029392"
    ],
    "placetype": [
      "aat:300008706"
    ],
    "id": 2136176,
    "name:xx": "Aragon Creek"
  }
}
