{
  "geometry": {
    "type": "Point",
    "coordinates": [
      -92.7167,
      31.35
    ]
  },
  "type": "Feature",
  "properties": {
    "hierarchy": [
      "tgn:2265454",
      "tgn:1000001",
      "tgn:7012149",
      "tgn:2000893",
      "tgn:7007256",
      "tgn:7029392"
    ],
    "placetype": [
      "aat:300008905"
    ],
    "id": 2265454,
    "name:xx": "Crane Lake"
  }
}
