{
  "geometry": {
    "type": "Point",
    "coordinates": [
      -79.45,
      37.5833
    ]
  },
  "type": "Feature",
  "properties": {
    "hierarchy": [
      "tgn:2702904",
      "tgn:1000001",
      "tgn:7012149",
      "tgn:2002186",
      "tgn:7007919",
      "tgn:7029392"
    ],
    "placetype": [
      "aat:300008761"
    ],
    "id": 2702904,
    "name:xx": "Sulphur Spring Hollow"
  }
}
