{
  "geometry": {
    "type": "Point",
    "coordinates": [
      -110.1667,
      34.0667
    ]
  },
  "type": "Feature",
  "properties": {
    "hierarchy": [
      "tgn:2390766",
      "tgn:1000001",
      "tgn:7006451",
      "tgn:7012149",
      "tgn:2000099",
      "tgn:7029392"
    ],
    "placetype": [
      "aat:300006191"
    ],
    "id": 2390766,
    "name:xx": "Highway Sixty Tank"
  }
}
