{
  "geometry": {
    "type": "Point",
    "coordinates": [
      -100.95,
      37.35
    ]
  },
  "type": "Feature",
  "properties": {
    "hierarchy": [
      "tgn:2518757",
      "tgn:1000001",
      "tgn:7012149",
      "tgn:2000747",
      "tgn:7007254",
      "tgn:7029392"
    ],
    "placetype": [
      "aat:300006191"
    ],
    "id": 2518757,
    "name:xx": "Mitchell Pond"
  }
}
