{
  "geometry": {
    "type": "Point",
    "coordinates": [
      -66.5167,
      18.05
    ]
  },
  "type": "Feature",
  "properties": {
    "hierarchy": [
      "tgn:1018967",
      "tgn:7017440",
      "tgn:1000001",
      "tgn:7004643",
      "tgn:7029392"
    ],
    "placetype": [
      "aat:300008347"
    ],
    "id": 1018967,
    "name:xx": "Juana Díaz"
  }
}
