{
  "geometry": {
    "type": "Point",
    "coordinates": [
      33.9333,
      -9.55
    ]
  },
  "type": "Feature",
  "properties": {
    "hierarchy": [
      "tgn:1140935",
      "tgn:7001242",
      "tgn:1001706",
      "tgn:1000203",
      "tgn:7029392"
    ],
    "placetype": [
      "aat:300008347"
    ],
    "id": 1140935,
    "name:xx": "Mwaya"
  }
}
