{
  "geometry": {
    "type": "Point",
    "coordinates": [
      22.75,
      -18.75
    ]
  },
  "type": "Feature",
  "properties": {
    "hierarchy": [
      "tgn:1111036",
      "tgn:7001242",
      "tgn:1000905",
      "tgn:1000150",
      "tgn:7029392"
    ],
    "placetype": [
      "aat:300008760"
    ],
    "id": 1111036,
    "name:xx": "Okavango Delta"
  }
}
