{
  "geometry": {
    "type": "Point",
    "coordinates": [
      -87.45,
      35.8167
    ]
  },
  "type": "Feature",
  "properties": {
    "hierarchy": [
      "tgn:2613197",
      "tgn:1000001",
      "tgn:7012149",
      "tgn:7015666",
      "tgn:7007825",
      "tgn:7029392"
    ],
    "placetype": [
      "aat:300008699"
    ],
    "id": 2613197,
    "name:xx": "Reece Branch"
  }
}
