{
  "geometry": {
    "type": "Point",
    "coordinates": [
      31.833611,
      31.414167
    ]
  },
  "type": "Feature",
  "properties": {
    "hierarchy": [
      "tgn:7535411",
      "tgn:7001242",
      "tgn:7016833",
      "tgn:1001225",
      "tgn:7029392"
    ],
    "placetype": [
      "aat:300008347"
    ],
    "name:en": "Ibrâhîm Ḥakîm",
    "id": 7535411
  }
}
