{
  "geometry": {
    "type": "Point",
    "coordinates": [
      -93.6667,
      44.9333
    ]
  },
  "type": "Feature",
  "properties": {
    "hierarchy": [
      "tgn:2482192",
      "tgn:1000001",
      "tgn:2001025",
      "tgn:7012149",
      "tgn:7007521",
      "tgn:7029392"
    ],
    "placetype": [
      "aat:300008680"
    ],
    "id": 2482192,
    "name:xx": "Langdon Lake"
  }
}
