{
  "type": "FeatureCollection",
  "features": [
    {
      "geometry": {
        "type": "Point",
        "coordinates": [
          -4.3,
          56.483333
        ]
      },
      "type": "Feature",
      "properties": {
        "hierarchy": [
          "tgn:1123450",
          "tgn:7002444",
          "tgn:1000003",
          "tgn:5000460",
          "tgn:7008591",
          "tgn:7029392"
        ],
        "placetype": [
          "aat:300008707",
          "aat:300008699"
        ],
        "name:en": "Dochart",
        "id": 1123450
      }
    },
    {
      "geometry": {
        "type": "Point",
        "coordinates": [
          -89.6167,
          48.85
        ]
      },
      "type": "Feature",
      "properties": {
        "hierarchy": [
          "tgn:1123452",
          "tgn:7005685",
          "tgn:1000001",
          "tgn:7013154",
          "tgn:7029392"
        ],
        "placetype": [
          "aat:300008707"
        ],
        "id": 1123452,
        "name:xx": "Dog"
      }
    },
    {
      "geometry": {
        "type": "Point",
        "coordinates": [
          6.15,
          53.3167
        ]
      },
      "type": "Feature",
      "properties": {
        "hierarchy": [
          "tgn:1123454",
          "tgn:1000003",
          "tgn:7016845",
          "tgn:7029392"
        ],
        "placetype": [
          "aat:300008707"
        ],
        "id": 1123454,
        "name:xx": "Dokkumer Ee"
      }
    },
    {
      "geometry": {
        "type": "Point",
        "coordinates": [
          4.7667,
          45.3
        ]
      },
      "type": "Feature",
      "properties": {
        "hierarchy": [
          "tgn:1123456",
          "tgn:1000003",
          "tgn:1000070",
          "tgn:7002897",
          "tgn:7029392"
        ],
        "placetype": [
          "aat:300008707"
        ],
        "id": 1123456,
        "name:xx": "Dolon"
      }
    },
    {
      "geometry": {
        "type": "Point",
        "coordinates": [
          125.4833,
          12.0333
        ]
      },
      "type": "Feature",
      "properties": {
        "hierarchy": [
          "tgn:1123458",
          "tgn:1000004",
          "tgn:1001231",
          "tgn:1000135",
          "tgn:7029392"
        ],
        "placetype": [
          "aat:300008707"
        ],
        "id": 1123458,
        "name:xx": "Dolores"
      }
    }
  ]
}
