{
  "geometry": {
    "type": "Point",
    "coordinates": [
      -104.65,
      39.0167
    ]
  },
  "type": "Feature",
  "properties": {
    "hierarchy": [
      "tgn:2746072",
      "tgn:1000001",
      "tgn:7012149",
      "tgn:7014097",
      "tgn:7007158",
      "tgn:7029392"
    ],
    "placetype": [
      "aat:300008798"
    ],
    "id": 2746072,
    "name:xx": "Vollmer Hill"
  }
}
