{
  "type": "FeatureCollection",
  "features": [
    {
      "geometry": {
        "type": "Point",
        "coordinates": [
          127.5667,
          36.3
        ]
      },
      "type": "Feature",
      "properties": {
        "hierarchy": [
          "tgn:1082320",
          "tgn:1001191",
          "tgn:1000004",
          "tgn:7000299",
          "tgn:7029392"
        ],
        "placetype": [
          "aat:300008347"
        ],
        "id": 1082320,
        "name:xx": "Okch'ŏn"
      }
    },
    {
      "geometry": {
        "type": "Point",
        "coordinates": [
          127.0667,
          37.15
        ]
      },
      "type": "Feature",
      "properties": {
        "hierarchy": [
          "tgn:1082321",
          "tgn:1000004",
          "tgn:1001370",
          "tgn:7000299",
          "tgn:7029392"
        ],
        "placetype": [
          "aat:300008347"
        ],
        "id": 1082321,
        "name:xx": "Osan"
      }
    },
    {
      "geometry": {
        "type": "Point",
        "coordinates": [
          127.3167,
          35.5333
        ]
      },
      "type": "Feature",
      "properties": {
        "hierarchy": [
          "tgn:1082322",
          "tgn:1001194",
          "tgn:1000004",
          "tgn:7000299",
          "tgn:7029392"
        ],
        "placetype": [
          "aat:300008347"
        ],
        "id": 1082322,
        "name:xx": "Osu-ri"
      }
    },
    {
      "geometry": {
        "type": "Point",
        "coordinates": [
          128.1833,
          37.7
        ]
      },
      "type": "Feature",
      "properties": {
        "hierarchy": [
          "tgn:1082324",
          "tgn:1001342",
          "tgn:1000004",
          "tgn:7000299",
          "tgn:7029392"
        ],
        "placetype": [
          "aat:300008347"
        ],
        "id": 1082324,
        "name:xx": "P'ungam-ni"
      }
    },
    {
      "geometry": {
        "type": "Point",
        "coordinates": [
          128.3833,
          37.3667
        ]
      },
      "type": "Feature",
      "properties": {
        "hierarchy": [
          "tgn:1082325",
          "tgn:1001342",
          "tgn:1000004",
          "tgn:7000299",
          "tgn:7029392"
        ],
        "placetype": [
          "aat:300008347"
        ],
        "id": 1082325,
        "name:xx": "P'yŏngch'ang"
      }
    },
    {
      "geometry": {
        "type": "Point",
        "coordinates": [
          128.0333,
          37.1333
        ]
      },
      "type": "Feature",
      "properties": {
        "hierarchy": [
          "tgn:1082326",
          "tgn:1001191",
          "tgn:1000004",
          "tgn:7000299",
          "tgn:7029392"
        ],
        "placetype": [
          "aat:300008347"
        ],
        "id": 1082326,
        "name:xx": "P'yŏngdong-ni"
      }
    },
    {
      "geometry": {
        "type": "Point",
        "coordinates": [
          127.0833,
          36.9833
        ]
      },
      "type": "Feature",
      "properties": {
        "hierarchy": [
          "tgn:1082327",
          "tgn:1000004",
          "tgn:1001370",
          "tgn:7000299",
          "tgn:7029392"
        ],
        "placetype": [
          "aat:300008347"
        ],
        "id": 1082327,
        "name:xx": "P'yŏngt'aek"
      }
    },
    {
      "geometry": {
        "type": "Point",
        "coordinates": [
          129.4333,
          36.7167
        ]
      },
      "type": "Feature",
      "properties": {
        "hierarchy": [
          "tgn:1082328",
          "tgn:1000004",
          "tgn:1001372",
          "tgn:7000299",
          "tgn:7029392"
        ],
        "placetype": [
          "aat:300008347"
        ],
        "id": 1082328,
        "name:xx": "P'yŏnghae"
      }
    },
    {
      "geometry": {
        "type": "Point",
        "coordinates": [
          127.3333,
          34.8333
        ]
      },
      "type": "Feature",
      "properties": {
        "hierarchy": [
          "tgn:1082329",
          "tgn:1001193",
          "tgn:1000004",
          "tgn:7000299",
          "tgn:7029392"
        ],
        "placetype": [
          "aat:300008347"
        ],
        "id": 1082329,
        "name:xx": "Pŏlgyo"
      }
    }
  ]
}
