{
  "geometry": {
    "type": "Point",
    "coordinates": [
      -80.85,
      39.5333
    ]
  },
  "type": "Feature",
  "properties": {
    "hierarchy": [
      "tgn:2246220",
      "tgn:1000001",
      "tgn:7012149",
      "tgn:2002297",
      "tgn:7013961",
      "tgn:7029392"
    ],
    "placetype": [
      "aat:300008699"
    ],
    "id": 2246220,
    "name:xx": "Coallick Run"
  }
}
