{
  "type": "FeatureCollection",
  "features": [
    {
      "geometry": {
        "type": "Point",
        "coordinates": [
          14.966667,
          36.883333
        ]
      },
      "type": "Feature",
      "properties": {
        "hierarchy": [
          "tgn:7040180",
          "tgn:1001622",
          "tgn:1000003",
          "tgn:7003122",
          "tgn:1000080",
          "tgn:7029392"
        ],
        "placetype": [
          "aat:300008347"
        ],
        "id": 7040180,
        "name:xx": "Savarino"
      }
    },
    {
      "geometry": {
        "type": "Point",
        "coordinates": [
          9.083333,
          40.833333
        ]
      },
      "type": "Feature",
      "properties": {
        "hierarchy": [
          "tgn:7040181",
          "tgn:7015163",
          "tgn:1000003",
          "tgn:7003121",
          "tgn:1000080",
          "tgn:7029392"
        ],
        "placetype": [
          "aat:300259572"
        ],
        "id": 7040181,
        "name:xx": "Sa Variante"
      }
    },
    {
      "geometry": {
        "type": "Point",
        "coordinates": [
          14.1,
          41.466667
        ]
      },
      "type": "Feature",
      "properties": {
        "hierarchy": [
          "tgn:7040183",
          "tgn:7003011",
          "tgn:7003005",
          "tgn:1000003",
          "tgn:1000080",
          "tgn:7029392"
        ],
        "placetype": [
          "aat:300008699"
        ],
        "id": 7040183,
        "name:xx": "Sava, Fiume"
      }
    },
    {
      "geometry": {
        "type": "Point",
        "coordinates": [
          6.883333,
          44.483333
        ]
      },
      "type": "Feature",
      "properties": {
        "hierarchy": [
          "tgn:7040187",
          "tgn:7005126",
          "tgn:1000003",
          "tgn:7003120",
          "tgn:1000080",
          "tgn:7029392"
        ],
        "placetype": [
          "aat:300008798"
        ],
        "id": 7040187,
        "name:xx": "Sautron, Tête de"
      }
    },
    {
      "geometry": {
        "type": "Point",
        "coordinates": [
          16.35,
          40.3
        ]
      },
      "type": "Feature",
      "properties": {
        "hierarchy": [
          "tgn:7040188",
          "tgn:1003489",
          "tgn:7004610",
          "tgn:1000003",
          "tgn:1000080",
          "tgn:7029392"
        ],
        "placetype": [
          "aat:300008699"
        ],
        "id": 7040188,
        "name:xx": "Sauro, Torrente"
      }
    },
    {
      "geometry": {
        "type": "Point",
        "coordinates": [
          12.679444,
          46.469167
        ]
      },
      "type": "Feature",
      "properties": {
        "hierarchy": [
          "tgn:7040189",
          "tgn:1003506",
          "tgn:1000003",
          "tgn:7002993",
          "tgn:1000080",
          "tgn:7029392"
        ],
        "placetype": [
          "aat:300008347"
        ],
        "id": 7040189,
        "name:xx": "Sauris di Sopra"
      }
    }
  ]
}
