{
  "geometry": {
    "type": "Point",
    "coordinates": [
      -74.0833,
      41.25
    ]
  },
  "type": "Feature",
  "properties": {
    "hierarchy": [
      "tgn:2480425",
      "tgn:1000001",
      "tgn:7012149",
      "tgn:7007568",
      "tgn:7029392"
    ],
    "placetype": [
      "aat:300008699"
    ],
    "id": 2480425,
    "name:xx": "Lake Tiorati Brook"
  }
}
