{
  "geometry": {
    "type": "Point",
    "coordinates": [
      -76.25,
      41.15
    ]
  },
  "type": "Feature",
  "properties": {
    "hierarchy": [
      "tgn:2438539",
      "tgn:1000001",
      "tgn:7012149",
      "tgn:1002612",
      "tgn:7007710",
      "tgn:7029392"
    ],
    "placetype": [
      "aat:300008699"
    ],
    "id": 2438539,
    "name:xx": "Kingsbury Brook"
  }
}
