{
  "geometry": {
    "type": "Point",
    "coordinates": [
      -105.9667,
      35.35
    ]
  },
  "type": "Feature",
  "properties": {
    "hierarchy": [
      "tgn:2474538",
      "tgn:1000001",
      "tgn:7012149",
      "tgn:2001454",
      "tgn:7007566",
      "tgn:7029392"
    ],
    "placetype": [
      "aat:300006191"
    ],
    "id": 2474538,
    "name:xx": "Lower Rock Tank"
  }
}
