{
  "geometry": {
    "type": "Point",
    "coordinates": [
      62.75,
      25.9167
    ]
  },
  "type": "Feature",
  "properties": {
    "hierarchy": [
      "tgn:7002275",
      "tgn:1000004",
      "tgn:7029392"
    ],
    "placetype": [
      "aat:300008707"
    ],
    "id": 7002275,
    "name:xx": "Nahang"
  }
}
