{
  "geometry": {
    "type": "Point",
    "coordinates": [
      -88.1667,
      37.05
    ]
  },
  "type": "Feature",
  "properties": {
    "hierarchy": [
      "tgn:2253483",
      "tgn:1000001",
      "tgn:7012149",
      "tgn:7007255",
      "tgn:7029392"
    ],
    "placetype": [
      "aat:300008706"
    ],
    "id": 2253483,
    "name:xx": "Cook Creek"
  }
}
