{
  "geometry": {
    "type": "Point",
    "coordinates": [
      -120.8333,
      44.2833
    ]
  },
  "type": "Feature",
  "properties": {
    "hierarchy": [
      "tgn:2599050",
      "tgn:1000001",
      "tgn:2001703",
      "tgn:7012149",
      "tgn:7007708",
      "tgn:7029392"
    ],
    "placetype": [
      "aat:300008761"
    ],
    "id": 2599050,
    "name:xx": "Prineville Valley"
  }
}
