{
  "geometry": {
    "type": "Point",
    "coordinates": [
      -105.4833,
      33.4167
    ]
  },
  "type": "Feature",
  "properties": {
    "hierarchy": [
      "tgn:2662962",
      "tgn:1000001",
      "tgn:7012149",
      "tgn:2001442",
      "tgn:7007566",
      "tgn:7029392"
    ],
    "placetype": [
      "aat:300006191"
    ],
    "id": 2662962,
    "name:xx": "Silva Tank"
  }
}
