{
  "type": "FeatureCollection",
  "features": [
    {
      "geometry": {
        "type": "Point",
        "coordinates": [
          12.05,
          42.4
        ]
      },
      "type": "Feature",
      "properties": {
        "hierarchy": [
          "tgn:7055180",
          "tgn:7003139",
          "tgn:1000003",
          "tgn:7003080",
          "tgn:1000080",
          "tgn:7029392"
        ],
        "placetype": [
          "aat:300008761"
        ],
        "id": 7055180,
        "name:xx": "Ospedale, Valle"
      }
    },
    {
      "geometry": {
        "type": "Point",
        "coordinates": [
          13.1,
          42.216667
        ]
      },
      "type": "Feature",
      "properties": {
        "hierarchy": [
          "tgn:7055181",
          "tgn:7003137",
          "tgn:1000003",
          "tgn:7003080",
          "tgn:1000080",
          "tgn:7029392"
        ],
        "placetype": [
          "aat:300008347"
        ],
        "id": 7055181,
        "name:xx": "Ospanesco"
      }
    },
    {
      "geometry": {
        "type": "Point",
        "coordinates": [
          13.433333,
          42.85
        ]
      },
      "type": "Feature",
      "properties": {
        "hierarchy": [
          "tgn:7055183",
          "tgn:1003432",
          "tgn:1000003",
          "tgn:7003240",
          "tgn:1000080",
          "tgn:7029392"
        ],
        "placetype": [
          "aat:300008347"
        ],
        "id": 7055183,
        "name:xx": "Osoli"
      }
    },
    {
      "geometry": {
        "type": "Point",
        "coordinates": [
          8.65,
          45.783333
        ]
      },
      "type": "Feature",
      "properties": {
        "hierarchy": [
          "tgn:7055185",
          "tgn:1000003",
          "tgn:1003508",
          "tgn:7003237",
          "tgn:1000080",
          "tgn:7029392"
        ],
        "placetype": [
          "aat:300008347"
        ],
        "id": 7055185,
        "name:xx": "Osmate Lentate"
      }
    },
    {
      "geometry": {
        "type": "Point",
        "coordinates": [
          13.614722,
          45.970833
        ]
      },
      "type": "Feature",
      "properties": {
        "hierarchy": [
          "tgn:7055186",
          "tgn:1003459",
          "tgn:1000003",
          "tgn:7002993",
          "tgn:1000080",
          "tgn:7029392"
        ],
        "placetype": [
          "aat:300008347"
        ],
        "id": 7055186,
        "name:xx": "Oslávia"
      }
    },
    {
      "geometry": {
        "type": "Point",
        "coordinates": [
          13.533333,
          43.483333
        ]
      },
      "type": "Feature",
      "properties": {
        "hierarchy": [
          "tgn:7055188",
          "tgn:1003429",
          "tgn:1000003",
          "tgn:7003240",
          "tgn:1000080",
          "tgn:7029392"
        ],
        "placetype": [
          "aat:300007783"
        ],
        "id": 7055188,
        "name:xx": "Stazione di Osimo"
      }
    }
  ]
}
