{
  "geometry": {
    "type": "Point",
    "coordinates": [
      -110.6333,
      32.2167
    ]
  },
  "type": "Feature",
  "properties": {
    "hierarchy": [
      "tgn:2722445",
      "tgn:1000001",
      "tgn:7006451",
      "tgn:7012149",
      "tgn:2000100",
      "tgn:7029392"
    ],
    "placetype": [
      "aat:300006191"
    ],
    "id": 2722445,
    "name:xx": "Tina Larga Tank"
  }
}
