{
  "geometry": {
    "type": "Point",
    "coordinates": [
      -105.3333,
      36.4333
    ]
  },
  "type": "Feature",
  "properties": {
    "hierarchy": [
      "tgn:2325196",
      "tgn:1000001",
      "tgn:7012149",
      "tgn:7007566",
      "tgn:7029392"
    ],
    "placetype": [
      "aat:300008706"
    ],
    "id": 2325196,
    "name:xx": "Fernando de Taos, Rio"
  }
}
