{
  "geometry": {
    "type": "Point",
    "coordinates": [
      -100.1833,
      48.95
    ]
  },
  "type": "Feature",
  "properties": {
    "hierarchy": [
      "tgn:2577610",
      "tgn:7020393",
      "tgn:1000001",
      "tgn:7012149",
      "tgn:7007705",
      "tgn:7029392"
    ],
    "placetype": [
      "aat:300008680"
    ],
    "id": 2577610,
    "name:xx": "Peterson Lake"
  }
}
