{
  "geometry": {
    "type": "Point",
    "coordinates": [
      79.966667,
      16.983333
    ]
  },
  "type": "Feature",
  "properties": {
    "hierarchy": [
      "tgn:7574882",
      "tgn:1001828",
      "tgn:1000004",
      "tgn:7000198",
      "tgn:7029392"
    ],
    "placetype": [
      "aat:300008347"
    ],
    "name:en": "Kodār",
    "id": 7574882
  }
}
