{
  "geometry": {
    "type": "Point",
    "coordinates": [
      -82.4333,
      35.8833
    ]
  },
  "type": "Feature",
  "properties": {
    "hierarchy": [
      "tgn:2591990",
      "tgn:1000001",
      "tgn:7012149",
      "tgn:2001516",
      "tgn:7007709",
      "tgn:7029392"
    ],
    "placetype": [
      "aat:300008706"
    ],
    "id": 2591990,
    "name:xx": "Ponder Creek"
  }
}
