{
  "type": "FeatureCollection",
  "features": [
    {
      "geometry": {
        "type": "Point",
        "coordinates": [
          44.202,
          33.353
        ]
      },
      "type": "Feature",
      "properties": {
        "hierarchy": [
          "tgn:7032894",
          "tgn:1000004",
          "tgn:1001130",
          "tgn:1000118",
          "tgn:7029392"
        ],
        "placetype": [
          "aat:300008347",
          "aat:300000810",
          "aat:300167671",
          "aat:300387218",
          "aat:300020634",
          "aat:300019828"
        ],
        "id": 7032894,
        "name:xx": "Aqar Quf"
      }
    },
    {
      "geometry": {
        "type": "Point",
        "coordinates": [
          13.677,
          45.9
        ]
      },
      "type": "Feature",
      "properties": {
        "hierarchy": [
          "tgn:7032895",
          "tgn:1000003",
          "tgn:7015085",
          "tgn:7006670",
          "tgn:7029392"
        ],
        "placetype": [
          "aat:300008347"
        ],
        "id": 7032895,
        "name:xx": "Bukovica"
      }
    },
    {
      "geometry": {
        "type": "Point",
        "coordinates": [
          48.525,
          32.016
        ]
      },
      "type": "Feature",
      "properties": {
        "hierarchy": [
          "tgn:7032896",
          "tgn:1000004",
          "tgn:7002147",
          "tgn:7000231",
          "tgn:7029392"
        ],
        "placetype": [
          "aat:300008347",
          "aat:300167671",
          "aat:300008389",
          "aat:300008057",
          "aat:300263063"
        ],
        "id": 7032896,
        "name:xx": "Tchogha Zanbil"
      }
    },
    {
      "geometry": {
        "type": "Point",
        "coordinates": [
          78.68906,
          27.693256
        ]
      },
      "type": "Feature",
      "properties": {
        "hierarchy": [
          "tgn:7032897",
          "tgn:1000004",
          "tgn:7000198",
          "tgn:7016722",
          "tgn:7029392"
        ],
        "placetype": [
          "aat:300008347",
          "aat:300000810",
          "aat:300167671",
          "aat:300008024",
          "aat:300387006"
        ],
        "id": 7032897,
        "name:xx": "Atranjikhera"
      }
    }
  ]
}
