{
  "geometry": {
    "type": "Point",
    "coordinates": [
      122.05,
      42.1833
    ]
  },
  "type": "Feature",
  "properties": {
    "hierarchy": [
      "tgn:1067708",
      "tgn:1000004",
      "tgn:1001390",
      "tgn:1000111",
      "tgn:7029392"
    ],
    "placetype": [
      "aat:300008347"
    ],
    "id": 1067708,
    "name:xx": "Digong"
  }
}
