{
  "geometry": {
    "type": "Point",
    "coordinates": [
      -68.95,
      44.3667
    ]
  },
  "type": "Feature",
  "properties": {
    "hierarchy": [
      "tgn:2433987",
      "tgn:1000001",
      "tgn:7012149",
      "tgn:2000931",
      "tgn:7007515",
      "tgn:7029392"
    ],
    "placetype": [
      "aat:300132316"
    ],
    "id": 2433987,
    "name:xx": "Kellys Cove"
  }
}
