{
  "geometry": {
    "type": "Point",
    "coordinates": [
      -0.5333,
      7.5167
    ]
  },
  "type": "Feature",
  "properties": {
    "hierarchy": [
      "tgn:1129843",
      "tgn:7001242",
      "tgn:1000166",
      "tgn:7029392"
    ],
    "placetype": [
      "aat:300008707"
    ],
    "id": 1129843,
    "name:xx": "Sene"
  }
}
