{
  "geometry": {
    "type": "Point",
    "coordinates": [
      -99.0667,
      30.8167
    ]
  },
  "type": "Feature",
  "properties": {
    "hierarchy": [
      "tgn:2734911",
      "tgn:1000001",
      "tgn:7012149",
      "tgn:2002037",
      "tgn:7007826",
      "tgn:7029392"
    ],
    "placetype": [
      "aat:300008706"
    ],
    "id": 2734911,
    "name:xx": "Twelvemile Creek"
  }
}
