{
  "geometry": {
    "type": "Point",
    "coordinates": [
      -82.7833,
      37.4167
    ]
  },
  "type": "Feature",
  "properties": {
    "hierarchy": [
      "tgn:2660664",
      "tgn:1000001",
      "tgn:7012149",
      "tgn:2000789",
      "tgn:7007255",
      "tgn:7029392"
    ],
    "placetype": [
      "aat:300008699"
    ],
    "id": 2660664,
    "name:xx": "Shop Branch"
  }
}
