{
  "geometry": {
    "type": "Point",
    "coordinates": [
      -84.55,
      33.6667
    ]
  },
  "type": "Feature",
  "properties": {
    "hierarchy": [
      "tgn:2743313",
      "tgn:1000001",
      "tgn:7012149",
      "tgn:2000351",
      "tgn:7007248",
      "tgn:7029392"
    ],
    "placetype": [
      "aat:300006191"
    ],
    "id": 2743313,
    "name:xx": "Vandivers Lake"
  }
}
