{
  "geometry": {
    "type": "Point",
    "coordinates": [
      -110.1333,
      38.0833
    ]
  },
  "type": "Feature",
  "properties": {
    "hierarchy": [
      "tgn:2678947",
      "tgn:1000001",
      "tgn:7012149",
      "tgn:7007827",
      "tgn:7029392"
    ],
    "placetype": [
      "aat:300008761"
    ],
    "id": 2678947,
    "name:xx": "South Fork Happy Canyon"
  }
}
