{
  "geometry": {
    "type": "Point",
    "coordinates": [
      119.5667,
      25.6833
    ]
  },
  "type": "Feature",
  "properties": {
    "hierarchy": [
      "tgn:1071980",
      "tgn:1000004",
      "tgn:7001796",
      "tgn:1000111",
      "tgn:7029392"
    ],
    "placetype": [
      "aat:300008347"
    ],
    "id": 1071980,
    "name:xx": "Songxia"
  }
}
