{
  "type": "FeatureCollection",
  "features": [
    {
      "geometry": {
        "type": "Point",
        "coordinates": [
          -109.2,
          45.1833
        ]
      },
      "type": "Feature",
      "properties": {
        "hierarchy": [
          "tgn:2242700",
          "tgn:1000001",
          "tgn:2001264",
          "tgn:7012149",
          "tgn:7007524",
          "tgn:7029392"
        ],
        "placetype": [
          "aat:300008706"
        ],
        "id": 2242700,
        "name:xx": "Clear Creek"
      }
    },
    {
      "geometry": {
        "type": "Point",
        "coordinates": [
          -113.05,
          46.0833
        ]
      },
      "type": "Feature",
      "properties": {
        "hierarchy": [
          "tgn:2242701",
          "tgn:1000001",
          "tgn:7012149",
          "tgn:7020792",
          "tgn:7007524",
          "tgn:7029392"
        ],
        "placetype": [
          "aat:300008706"
        ],
        "id": 2242701,
        "name:xx": "Clear Creek"
      }
    },
    {
      "geometry": {
        "type": "Point",
        "coordinates": [
          -111.35,
          46.5333
        ]
      },
      "type": "Feature",
      "properties": {
        "hierarchy": [
          "tgn:2242702",
          "tgn:1000001",
          "tgn:2001263",
          "tgn:7012149",
          "tgn:7007524",
          "tgn:7029392"
        ],
        "placetype": [
          "aat:300008706"
        ],
        "id": 2242702,
        "name:xx": "Clear Creek"
      }
    },
    {
      "geometry": {
        "type": "Point",
        "coordinates": [
          -114.6833,
          47.3833
        ]
      },
      "type": "Feature",
      "properties": {
        "hierarchy": [
          "tgn:2242703",
          "tgn:1000001",
          "tgn:7012149",
          "tgn:2001304",
          "tgn:7007524",
          "tgn:7029392"
        ],
        "placetype": [
          "aat:300008706"
        ],
        "id": 2242703,
        "name:xx": "Clear Creek"
      }
    },
    {
      "geometry": {
        "type": "Point",
        "coordinates": [
          -109.5,
          48.1167
        ]
      },
      "type": "Feature",
      "properties": {
        "hierarchy": [
          "tgn:2242704",
          "tgn:1000001",
          "tgn:2001262",
          "tgn:7012149",
          "tgn:7007524",
          "tgn:7029392"
        ],
        "placetype": [
          "aat:300008706"
        ],
        "id": 2242704,
        "name:xx": "Clear Creek"
      }
    },
    {
      "geometry": {
        "type": "Point",
        "coordinates": [
          -102.0167,
          41.35
        ]
      },
      "type": "Feature",
      "properties": {
        "hierarchy": [
          "tgn:2242705",
          "tgn:1000001",
          "tgn:2001366",
          "tgn:7012149",
          "tgn:7007525",
          "tgn:7029392"
        ],
        "placetype": [
          "aat:300008706"
        ],
        "id": 2242705,
        "name:xx": "Clear Creek"
      }
    },
    {
      "geometry": {
        "type": "Point",
        "coordinates": [
          -96.2,
          40.2167
        ]
      },
      "type": "Feature",
      "properties": {
        "hierarchy": [
          "tgn:2242706",
          "tgn:1000001",
          "tgn:7012149",
          "tgn:2001382",
          "tgn:7007525",
          "tgn:7029392"
        ],
        "placetype": [
          "aat:300008706"
        ],
        "id": 2242706,
        "name:xx": "Clear Creek"
      }
    },
    {
      "geometry": {
        "type": "Point",
        "coordinates": [
          -96.45,
          41.2333
        ]
      },
      "type": "Feature",
      "properties": {
        "hierarchy": [
          "tgn:2242707",
          "tgn:1000001",
          "tgn:7012149",
          "tgn:2001393",
          "tgn:7007525",
          "tgn:7029392"
        ],
        "placetype": [
          "aat:300008706"
        ],
        "id": 2242707,
        "name:xx": "Clear Creek"
      }
    },
    {
      "geometry": {
        "type": "Point",
        "coordinates": [
          -114.65,
          39.2
        ]
      },
      "type": "Feature",
      "properties": {
        "hierarchy": [
          "tgn:2242708",
          "tgn:1000001",
          "tgn:7012149",
          "tgn:2001420",
          "tgn:7007526",
          "tgn:7029392"
        ],
        "placetype": [
          "aat:300008706"
        ],
        "id": 2242708,
        "name:xx": "Clear Creek"
      }
    },
    {
      "geometry": {
        "type": "Point",
        "coordinates": [
          -116.5667,
          38.8167
        ]
      },
      "type": "Feature",
      "properties": {
        "hierarchy": [
          "tgn:2242709",
          "tgn:1000001",
          "tgn:2001418",
          "tgn:7012149",
          "tgn:7007526",
          "tgn:7029392"
        ],
        "placetype": [
          "aat:300008706"
        ],
        "id": 2242709,
        "name:xx": "Clear Creek"
      }
    }
  ]
}
