{
  "type": "FeatureCollection",
  "features": [
    {
      "geometry": {
        "type": "Point",
        "coordinates": [
          -77.3833,
          37.55
        ]
      },
      "type": "Feature",
      "properties": {
        "hierarchy": [
          "tgn:2113460",
          "tgn:1000001",
          "tgn:7012149",
          "tgn:1002467",
          "tgn:7007919",
          "tgn:7029392"
        ],
        "placetype": [
          "aat:300008347"
        ],
        "id": 2113460,
        "name:xx": "Oak Hill"
      }
    },
    {
      "geometry": {
        "type": "Point",
        "coordinates": [
          -79.1,
          36.7333
        ]
      },
      "type": "Feature",
      "properties": {
        "hierarchy": [
          "tgn:2113461",
          "tgn:1000001",
          "tgn:7012149",
          "tgn:2002166",
          "tgn:7007919",
          "tgn:7029392"
        ],
        "placetype": [
          "aat:300008347",
          "aat:300387210"
        ],
        "id": 2113461,
        "name:xx": "Oak Level"
      }
    },
    {
      "geometry": {
        "type": "Point",
        "coordinates": [
          -76.75,
          37.7667
        ]
      },
      "type": "Feature",
      "properties": {
        "hierarchy": [
          "tgn:2113463",
          "tgn:1000001",
          "tgn:7012149",
          "tgn:1002362",
          "tgn:7007919",
          "tgn:7029392"
        ],
        "placetype": [
          "aat:300008347",
          "aat:300387210"
        ],
        "id": 2113463,
        "name:xx": "Oakley"
      }
    },
    {
      "geometry": {
        "type": "Point",
        "coordinates": [
          -78.15,
          38.3667
        ]
      },
      "type": "Feature",
      "properties": {
        "hierarchy": [
          "tgn:2113464",
          "tgn:1000001",
          "tgn:7012149",
          "tgn:2002172",
          "tgn:7007919",
          "tgn:7029392"
        ],
        "placetype": [
          "aat:300008347"
        ],
        "id": 2113464,
        "name:xx": "Oakpark"
      }
    },
    {
      "geometry": {
        "type": "Point",
        "coordinates": [
          -77.95,
          38.5833
        ]
      },
      "type": "Feature",
      "properties": {
        "hierarchy": [
          "tgn:2113467",
          "tgn:1000001",
          "tgn:7012149",
          "tgn:2002155",
          "tgn:7007919",
          "tgn:7029392"
        ],
        "placetype": [
          "aat:300008347",
          "aat:300387210"
        ],
        "id": 2113467,
        "name:xx": "Oakshade"
      }
    },
    {
      "geometry": {
        "type": "Point",
        "coordinates": [
          -77.3,
          38.8667
        ]
      },
      "type": "Feature",
      "properties": {
        "hierarchy": [
          "tgn:2113469",
          "tgn:1000001",
          "tgn:7012149",
          "tgn:7014160",
          "tgn:7007919",
          "tgn:7029392"
        ],
        "placetype": [
          "aat:300008347"
        ],
        "id": 2113469,
        "name:xx": "Oakton"
      }
    }
  ]
}
