{
  "geometry": {
    "type": "Point",
    "coordinates": [
      23.5833,
      38.0333
    ]
  },
  "type": "Feature",
  "properties": {
    "hierarchy": [
      "tgn:1042180",
      "tgn:7002681",
      "tgn:7001395",
      "tgn:1000003",
      "tgn:1000074",
      "tgn:7029392"
    ],
    "placetype": [
      "aat:300008347"
    ],
    "id": 1042180,
    "name:xx": "Paralía Aspropírgos"
  }
}
