{
  "geometry": {
    "type": "Point",
    "coordinates": [
      -83.25,
      30.7833
    ]
  },
  "type": "Feature",
  "properties": {
    "hierarchy": [
      "tgn:2614313",
      "tgn:1000001",
      "tgn:7012149",
      "tgn:2000383",
      "tgn:7007248",
      "tgn:7029392"
    ],
    "placetype": [
      "aat:300008680"
    ],
    "id": 2614313,
    "name:xx": "Registers Pool"
  }
}
