{
  "geometry": {
    "type": "Point",
    "coordinates": [
      -75.8333,
      37.4167
    ]
  },
  "type": "Feature",
  "properties": {
    "hierarchy": [
      "tgn:2194109",
      "tgn:1000001",
      "tgn:7012149",
      "tgn:1002730",
      "tgn:7007919",
      "tgn:7029392"
    ],
    "placetype": [
      "aat:300008850"
    ],
    "id": 2194109,
    "name:xx": "Brickhouse Neck"
  }
}
