{
  "geometry": {
    "type": "Point",
    "coordinates": [
      -113.6333,
      41.7833
    ]
  },
  "type": "Feature",
  "properties": {
    "hierarchy": [
      "tgn:2275387",
      "tgn:1000001",
      "tgn:2002102",
      "tgn:7012149",
      "tgn:7007827",
      "tgn:7029392"
    ],
    "placetype": [
      "aat:300008761"
    ],
    "id": 2275387,
    "name:xx": "Danish Hollow"
  }
}
