{
  "geometry": {
    "type": "Point",
    "coordinates": [
      -121.95,
      37.0667
    ]
  },
  "type": "Feature",
  "properties": {
    "hierarchy": [
      "tgn:2523193",
      "tgn:1000001",
      "tgn:7012149",
      "tgn:7007157",
      "tgn:1002869",
      "tgn:7029392"
    ],
    "placetype": [
      "aat:300008761"
    ],
    "id": 2523193,
    "name:xx": "Moores Gulch"
  }
}
