{
  "type": "FeatureCollection",
  "features": [
    {
      "geometry": {
        "type": "Point",
        "coordinates": [
          -74.666667,
          -52.316667
        ]
      },
      "type": "Feature",
      "properties": {
        "hierarchy": [
          "tgn:7291650",
          "tgn:1001702",
          "tgn:1000049",
          "tgn:1000002",
          "tgn:7029392"
        ],
        "placetype": [
          "aat:300008804"
        ],
        "id": 7291650,
        "name:xx": "Entrada, Península"
      }
    },
    {
      "geometry": {
        "type": "Point",
        "coordinates": [
          -70.966667,
          -54.266667
        ]
      },
      "type": "Feature",
      "properties": {
        "hierarchy": [
          "tgn:7291651",
          "tgn:1001702",
          "tgn:1000049",
          "tgn:1000002",
          "tgn:7029392"
        ],
        "placetype": [
          "aat:300008791"
        ],
        "id": 7291651,
        "name:xx": "Entrada, Islotes"
      }
    },
    {
      "geometry": {
        "type": "Point",
        "coordinates": [
          -74.083333,
          -45.366667
        ]
      },
      "type": "Feature",
      "properties": {
        "hierarchy": [
          "tgn:7291652",
          "tgn:1001623",
          "tgn:1000049",
          "tgn:1000002",
          "tgn:7029392"
        ],
        "placetype": [
          "aat:300008791"
        ],
        "id": 7291652,
        "name:xx": "Entrada, Islotes"
      }
    },
    {
      "geometry": {
        "type": "Point",
        "coordinates": [
          -71.45,
          -54.7
        ]
      },
      "type": "Feature",
      "properties": {
        "hierarchy": [
          "tgn:7291653",
          "tgn:1001702",
          "tgn:1000049",
          "tgn:1000002",
          "tgn:7029392"
        ],
        "placetype": [
          "aat:300008791"
        ],
        "id": 7291653,
        "name:xx": "Entrada, Islote"
      }
    },
    {
      "geometry": {
        "type": "Point",
        "coordinates": [
          -73.466667,
          -52.966667
        ]
      },
      "type": "Feature",
      "properties": {
        "hierarchy": [
          "tgn:7291654",
          "tgn:1001702",
          "tgn:1000049",
          "tgn:1000002",
          "tgn:7029392"
        ],
        "placetype": [
          "aat:300008791"
        ],
        "id": 7291654,
        "name:xx": "Entrada, Islote"
      }
    },
    {
      "geometry": {
        "type": "Point",
        "coordinates": [
          -75.333333,
          -50.433333
        ]
      },
      "type": "Feature",
      "properties": {
        "hierarchy": [
          "tgn:7291655",
          "tgn:1001702",
          "tgn:1000049",
          "tgn:1000002",
          "tgn:7029392"
        ],
        "placetype": [
          "aat:300008791"
        ],
        "id": 7291655,
        "name:xx": "Entrada, Islote"
      }
    },
    {
      "geometry": {
        "type": "Point",
        "coordinates": [
          -73.866667,
          -46.533333
        ]
      },
      "type": "Feature",
      "properties": {
        "hierarchy": [
          "tgn:7291656",
          "tgn:1001623",
          "tgn:1000049",
          "tgn:1000002",
          "tgn:7029392"
        ],
        "placetype": [
          "aat:300008791"
        ],
        "id": 7291656,
        "name:xx": "Entrada, Islote"
      }
    },
    {
      "geometry": {
        "type": "Point",
        "coordinates": [
          -75.333333,
          -46.8
        ]
      },
      "type": "Feature",
      "properties": {
        "hierarchy": [
          "tgn:7291657",
          "tgn:1001623",
          "tgn:1000049",
          "tgn:1000002",
          "tgn:7029392"
        ],
        "placetype": [
          "aat:300008791"
        ],
        "id": 7291657,
        "name:xx": "Entrada, Islotes"
      }
    },
    {
      "geometry": {
        "type": "Point",
        "coordinates": [
          -68.333333,
          -54.916667
        ]
      },
      "type": "Feature",
      "properties": {
        "hierarchy": [
          "tgn:7291658",
          "tgn:1001702",
          "tgn:1000049",
          "tgn:1000002",
          "tgn:7029392"
        ],
        "placetype": [
          "aat:300008791"
        ],
        "id": 7291658,
        "name:xx": "Entrada, Isla"
      }
    },
    {
      "geometry": {
        "type": "Point",
        "coordinates": [
          -72.316667,
          -54.05
        ]
      },
      "type": "Feature",
      "properties": {
        "hierarchy": [
          "tgn:7291659",
          "tgn:1001702",
          "tgn:1000049",
          "tgn:1000002",
          "tgn:7029392"
        ],
        "placetype": [
          "aat:300008791"
        ],
        "id": 7291659,
        "name:xx": "Entrada, Isla"
      }
    }
  ]
}
