{
  "geometry": {
    "type": "Point",
    "coordinates": [
      -89.65,
      45.8667
    ]
  },
  "type": "Feature",
  "properties": {
    "hierarchy": [
      "tgn:2385241",
      "tgn:1000001",
      "tgn:7012149",
      "tgn:2002342",
      "tgn:7007922",
      "tgn:7029392"
    ],
    "placetype": [
      "aat:300008680"
    ],
    "id": 2385241,
    "name:xx": "Hemlock Lake"
  }
}
