{
  "geometry": {
    "type": "Point",
    "coordinates": [
      -107.6667,
      34.5833
    ]
  },
  "type": "Feature",
  "properties": {
    "hierarchy": [
      "tgn:2774694",
      "tgn:1000001",
      "tgn:2001431",
      "tgn:7012149",
      "tgn:7007566",
      "tgn:7029392"
    ],
    "placetype": [
      "aat:300008697"
    ],
    "id": 2774694,
    "name:xx": "Willow Spring"
  }
}
