{
  "geometry": {
    "type": "Point",
    "coordinates": [
      -95.8167,
      31.2667
    ]
  },
  "type": "Feature",
  "properties": {
    "hierarchy": [
      "tgn:2381910",
      "tgn:1000001",
      "tgn:7012149",
      "tgn:1002590",
      "tgn:7007826",
      "tgn:7029392"
    ],
    "placetype": [
      "aat:300008699"
    ],
    "id": 2381910,
    "name:xx": "Hayes Branch"
  }
}
