{
  "geometry": {
    "type": "Point",
    "coordinates": [
      24.6333,
      60.9167
    ]
  },
  "type": "Feature",
  "properties": {
    "hierarchy": [
      "tgn:1031585",
      "tgn:7024077",
      "tgn:1000003",
      "tgn:1000069",
      "tgn:7029392"
    ],
    "placetype": [
      "aat:300008347"
    ],
    "id": 1031585,
    "name:xx": "Turenki"
  }
}
