{
  "geometry": {
    "type": "Point",
    "coordinates": [
      145.75,
      -17.0167
    ]
  },
  "type": "Feature",
  "properties": {
    "hierarchy": [
      "tgn:1096821",
      "tgn:7000490",
      "tgn:1000006",
      "tgn:7001830",
      "tgn:7029392"
    ],
    "placetype": [
      "aat:300008347"
    ],
    "id": 1096821,
    "name:xx": "Edmonton"
  }
}
