{
  "geometry": {
    "type": "Point",
    "coordinates": [
      41.8833,
      3.9333
    ]
  },
  "type": "Feature",
  "properties": {
    "hierarchy": [
      "tgn:1090502",
      "tgn:7001242",
      "tgn:7593780",
      "tgn:1000169",
      "tgn:7029392"
    ],
    "placetype": [
      "aat:300008347"
    ],
    "id": 1090502,
    "name:xx": "Mandera"
  }
}
