{
  "geometry": {
    "type": "Point",
    "coordinates": [
      -85.4667,
      30.0167
    ]
  },
  "type": "Feature",
  "properties": {
    "hierarchy": [
      "tgn:2532820",
      "tgn:2000258",
      "tgn:1000001",
      "tgn:7012149",
      "tgn:7007240",
      "tgn:7029392"
    ],
    "placetype": [
      "aat:300132316"
    ],
    "id": 2532820,
    "name:xx": "Murray Bayou"
  }
}
