{
  "geometry": {
    "type": "Point",
    "coordinates": [
      -109.2833,
      48.1833
    ]
  },
  "type": "Feature",
  "properties": {
    "hierarchy": [
      "tgn:2344432",
      "tgn:1000001",
      "tgn:2001262",
      "tgn:7012149",
      "tgn:7007524",
      "tgn:7029392"
    ],
    "placetype": [
      "aat:300008706"
    ],
    "id": 2344432,
    "name:xx": "Gap Creek"
  }
}
