{
  "geometry": {
    "type": "Point",
    "coordinates": [
      -116.8833,
      40.9667
    ]
  },
  "type": "Feature",
  "properties": {
    "hierarchy": [
      "tgn:2628612",
      "tgn:1000001",
      "tgn:2001415",
      "tgn:7012149",
      "tgn:7007526",
      "tgn:7029392"
    ],
    "placetype": [
      "aat:300008798"
    ],
    "id": 2628612,
    "name:xx": "Roosters Comb"
  }
}
