{
  "geometry": {
    "type": "Point",
    "coordinates": [
      -97.15,
      34.8667
    ]
  },
  "type": "Feature",
  "properties": {
    "hierarchy": [
      "tgn:2218148",
      "tgn:1000001",
      "tgn:7012149",
      "tgn:2001666",
      "tgn:7007707",
      "tgn:7029392"
    ],
    "placetype": [
      "aat:300008706"
    ],
    "id": 2218148,
    "name:xx": "Canadian Sandy Creek"
  }
}
