{
  "geometry": {
    "type": "Point",
    "coordinates": [
      -113.4167,
      37.4167
    ]
  },
  "type": "Feature",
  "properties": {
    "hierarchy": [
      "tgn:2651070",
      "tgn:1000001",
      "tgn:7012149",
      "tgn:2002127",
      "tgn:7007827",
      "tgn:7029392"
    ],
    "placetype": [
      "aat:300008680"
    ],
    "id": 2651070,
    "name:xx": "Second Water"
  }
}
