{
  "geometry": {
    "type": "Point",
    "coordinates": [
      -97.9333,
      27.3667
    ]
  },
  "type": "Feature",
  "properties": {
    "hierarchy": [
      "tgn:2605079",
      "tgn:1000001",
      "tgn:7012149",
      "tgn:2002022",
      "tgn:7007826",
      "tgn:7029392"
    ],
    "placetype": [
      "aat:300008706"
    ],
    "id": 2605079,
    "name:xx": "Radicha Creek"
  }
}
