{
  "geometry": {
    "type": "Point",
    "coordinates": [
      -106.9167,
      40.0667
    ]
  },
  "type": "Feature",
  "properties": {
    "hierarchy": [
      "tgn:2329398",
      "tgn:1000001",
      "tgn:7012149",
      "tgn:7007158",
      "tgn:2000245",
      "tgn:7029392"
    ],
    "placetype": [
      "aat:300008706"
    ],
    "id": 2329398,
    "name:xx": "Five Pine Mesa Creek"
  }
}
