{
  "type": "FeatureCollection",
  "features": [
    {
      "geometry": {
        "type": "Point",
        "coordinates": [
          -85.25,
          34.1667
        ]
      },
      "type": "Feature",
      "properties": {
        "hierarchy": [
          "tgn:2426730",
          "tgn:1000001",
          "tgn:7012149",
          "tgn:2000348",
          "tgn:7007248",
          "tgn:7029392"
        ],
        "placetype": [
          "aat:300006191"
        ],
        "id": 2426730,
        "name:xx": "Jones Lakes"
      }
    },
    {
      "geometry": {
        "type": "Point",
        "coordinates": [
          -81.2,
          28.7
        ]
      },
      "type": "Feature",
      "properties": {
        "hierarchy": [
          "tgn:2426731",
          "tgn:1000001",
          "tgn:7012149",
          "tgn:1002881",
          "tgn:7007240",
          "tgn:7029392"
        ],
        "placetype": [
          "aat:300008347"
        ],
        "id": 2426731,
        "name:xx": "Jones Landing"
      }
    },
    {
      "geometry": {
        "type": "Point",
        "coordinates": [
          -91.7667,
          31.8667
        ]
      },
      "type": "Feature",
      "properties": {
        "hierarchy": [
          "tgn:2426732",
          "tgn:1000001",
          "tgn:7012149",
          "tgn:2000874",
          "tgn:7007256",
          "tgn:7029392"
        ],
        "placetype": [
          "aat:300008347"
        ],
        "id": 2426732,
        "name:xx": "Jones Landing"
      }
    },
    {
      "geometry": {
        "type": "Point",
        "coordinates": [
          -84.7333,
          38.2167
        ]
      },
      "type": "Feature",
      "properties": {
        "hierarchy": [
          "tgn:2426733",
          "tgn:1000001",
          "tgn:7012149",
          "tgn:1002382",
          "tgn:7007255",
          "tgn:7029392"
        ],
        "placetype": [
          "aat:300008699"
        ],
        "id": 2426733,
        "name:xx": "Jones Lane Branch"
      }
    },
    {
      "geometry": {
        "type": "Point",
        "coordinates": [
          -102.1667,
          38.1
        ]
      },
      "type": "Feature",
      "properties": {
        "hierarchy": [
          "tgn:2426734",
          "tgn:1000001",
          "tgn:7012149",
          "tgn:7007158",
          "tgn:2000241",
          "tgn:7029392"
        ],
        "placetype": [
          "aat:300006075"
        ],
        "id": 2426734,
        "name:xx": "Jones Lateral"
      }
    },
    {
      "geometry": {
        "type": "Point",
        "coordinates": [
          -112.4,
          43.0167
        ]
      },
      "type": "Feature",
      "properties": {
        "hierarchy": [
          "tgn:2426735",
          "tgn:1000001",
          "tgn:2000457",
          "tgn:7012149",
          "tgn:7007250",
          "tgn:7029392"
        ],
        "placetype": [
          "aat:300006075"
        ],
        "id": 2426735,
        "name:xx": "Jones Lateral"
      }
    },
    {
      "geometry": {
        "type": "Point",
        "coordinates": [
          -103.6,
          35.15
        ]
      },
      "type": "Feature",
      "properties": {
        "hierarchy": [
          "tgn:2426736",
          "tgn:1000001",
          "tgn:7012149",
          "tgn:2001448",
          "tgn:7007566",
          "tgn:7029392"
        ],
        "placetype": [
          "aat:300006075"
        ],
        "id": 2426736,
        "name:xx": "Jones Lateral"
      }
    },
    {
      "geometry": {
        "type": "Point",
        "coordinates": [
          -70.1833,
          43.7
        ]
      },
      "type": "Feature",
      "properties": {
        "hierarchy": [
          "tgn:2426738",
          "tgn:1000001",
          "tgn:2000920",
          "tgn:7012149",
          "tgn:7007515",
          "tgn:7029392"
        ],
        "placetype": [
          "aat:300132348"
        ],
        "id": 2426738,
        "name:xx": "Jones Ledge"
      }
    },
    {
      "geometry": {
        "type": "Point",
        "coordinates": [
          -106.1667,
          33.85
        ]
      },
      "type": "Feature",
      "properties": {
        "hierarchy": [
          "tgn:2426739",
          "tgn:1000001",
          "tgn:7012149",
          "tgn:2001456",
          "tgn:7007566",
          "tgn:7029392"
        ],
        "placetype": [
          "aat:300000390"
        ],
        "id": 2426739,
        "name:xx": "Jones Magnatite"
      }
    }
  ]
}
