{
  "geometry": {
    "type": "Point",
    "coordinates": [
      -104.35,
      34.0167
    ]
  },
  "type": "Feature",
  "properties": {
    "hierarchy": [
      "tgn:2309356",
      "tgn:1000001",
      "tgn:7019560",
      "tgn:7012149",
      "tgn:7007566",
      "tgn:7029392"
    ],
    "placetype": [
      "aat:300006191"
    ],
    "id": 2309356,
    "name:xx": "East Tank"
  }
}
