{
  "geometry": {
    "type": "Point",
    "coordinates": [
      74.6625,
      34.005556
    ]
  },
  "type": "Feature",
  "properties": {
    "hierarchy": [
      "tgn:7588205",
      "tgn:1000004",
      "tgn:7000198",
      "tgn:7000799",
      "tgn:7029392"
    ],
    "placetype": [
      "aat:300008347"
    ],
    "name:en": "Pāras",
    "id": 7588205
  }
}
