{
  "geometry": {
    "type": "Point",
    "coordinates": [
      -104.7667,
      40.4667
    ]
  },
  "type": "Feature",
  "properties": {
    "hierarchy": [
      "tgn:2394206",
      "tgn:1000001",
      "tgn:7012149",
      "tgn:7007158",
      "tgn:2000253",
      "tgn:7029392"
    ],
    "placetype": [
      "aat:300006191"
    ],
    "id": 2394206,
    "name:xx": "Hogarty Reservoir"
  }
}
