{
  "geometry": {
    "type": "Point",
    "coordinates": [
      -87.25,
      30.8667
    ]
  },
  "type": "Feature",
  "properties": {
    "hierarchy": [
      "tgn:2489747",
      "tgn:1000001",
      "tgn:7012149",
      "tgn:2000285",
      "tgn:7007240",
      "tgn:7029392"
    ],
    "placetype": [
      "aat:300008699"
    ],
    "id": 2489747,
    "name:xx": "Malone Hammock Branch"
  }
}
