{
  "geometry": {
    "type": "Point",
    "coordinates": [
      -85.1333,
      33.4667
    ]
  },
  "type": "Feature",
  "properties": {
    "hierarchy": [
      "tgn:2717782",
      "tgn:1000001",
      "tgn:2000313",
      "tgn:7012149",
      "tgn:7007248",
      "tgn:7029392"
    ],
    "placetype": [
      "aat:300006191"
    ],
    "id": 2717782,
    "name:xx": "Thomas Lake B"
  }
}
