{
  "geometry": {
    "type": "Point",
    "coordinates": [
      -71.25,
      42.65
    ]
  },
  "type": "Feature",
  "properties": {
    "hierarchy": [
      "tgn:2731678",
      "tgn:1000001",
      "tgn:1002665",
      "tgn:7012149",
      "tgn:7007517",
      "tgn:7029392"
    ],
    "placetype": [
      "aat:300008699"
    ],
    "id": 2731678,
    "name:xx": "Tull Brook"
  }
}
