{
  "geometry": {
    "type": "Point",
    "coordinates": [
      -103.1833,
      34.6167
    ]
  },
  "type": "Feature",
  "properties": {
    "hierarchy": [
      "tgn:2226254",
      "tgn:1000001",
      "tgn:7012149",
      "tgn:7029392"
    ],
    "placetype": [
      "aat:300008761"
    ],
    "id": 2226254,
    "name:xx": "Catfish Draw"
  }
}
