{
  "type": "FeatureCollection",
  "features": [
    {
      "geometry": {
        "type": "Point",
        "coordinates": [
          -6.466667,
          49.9
        ]
      },
      "type": "Feature",
      "properties": {
        "hierarchy": [
          "tgn:7456421",
          "tgn:7002445",
          "tgn:7008116",
          "tgn:1000003",
          "tgn:7008591",
          "tgn:7029392"
        ],
        "placetype": [
          "aat:300011692"
        ],
        "name:en": "Crim Rocks",
        "id": 7456421
      }
    },
    {
      "geometry": {
        "type": "Point",
        "coordinates": [
          -6.933333,
          54.4
        ]
      },
      "type": "Feature",
      "properties": {
        "hierarchy": [
          "tgn:7456423",
          "tgn:7002448",
          "tgn:7019203",
          "tgn:1000003",
          "tgn:7008591",
          "tgn:7029392"
        ],
        "placetype": [
          "aat:300008347"
        ],
        "name:en": "Crilly",
        "id": 7456423
      }
    },
    {
      "geometry": {
        "type": "Point",
        "coordinates": [
          -4.5,
          53.216667
        ]
      },
      "type": "Feature",
      "properties": {
        "hierarchy": [
          "tgn:7456424",
          "tgn:7008532",
          "tgn:7002443",
          "tgn:1000003",
          "tgn:7008591",
          "tgn:7029392"
        ],
        "placetype": [
          "aat:300132316"
        ],
        "name:en": "Crigyll Bay",
        "id": 7456424
      }
    },
    {
      "geometry": {
        "type": "Point",
        "coordinates": [
          -3.05,
          52.716667
        ]
      },
      "type": "Feature",
      "properties": {
        "hierarchy": [
          "tgn:7456426",
          "tgn:7002443",
          "tgn:1000003",
          "tgn:7008050",
          "tgn:7008591",
          "tgn:7029392"
        ],
        "placetype": [
          "aat:300008347"
        ],
        "name:en": "Criggion",
        "id": 7456426
      }
    },
    {
      "geometry": {
        "type": "Point",
        "coordinates": [
          -0.216667,
          51.55
        ]
      },
      "type": "Feature",
      "properties": {
        "hierarchy": [
          "tgn:7456429",
          "tgn:7002445",
          "tgn:7018909",
          "tgn:1000003",
          "tgn:7008136",
          "tgn:7008591",
          "tgn:7029392"
        ],
        "placetype": [
          "aat:300008347",
          "aat:300000745"
        ],
        "name:en": "Cricklewood",
        "id": 7456429
      }
    }
  ]
}
