{
  "geometry": {
    "type": "Point",
    "coordinates": [
      -114.0833,
      45.0333
    ]
  },
  "type": "Feature",
  "properties": {
    "hierarchy": [
      "tgn:2680408",
      "tgn:1000001",
      "tgn:7012149",
      "tgn:2000481",
      "tgn:7007250",
      "tgn:7029392"
    ],
    "placetype": [
      "aat:300008706"
    ],
    "id": 2680408,
    "name:xx": "South Fork Williams Creek"
  }
}
