{
  "type": "FeatureCollection",
  "features": [
    {
      "geometry": {
        "type": "Point",
        "coordinates": [
          -77.95,
          40.7
        ]
      },
      "type": "Feature",
      "properties": {
        "hierarchy": [
          "tgn:2688340",
          "tgn:1000001",
          "tgn:7012149",
          "tgn:7007710",
          "tgn:7029392"
        ],
        "placetype": [
          "aat:300008706"
        ],
        "id": 2688340,
        "name:xx": "Spruce Creek"
      }
    },
    {
      "geometry": {
        "type": "Point",
        "coordinates": [
          -85.6,
          35.3167
        ]
      },
      "type": "Feature",
      "properties": {
        "hierarchy": [
          "tgn:2688341",
          "tgn:1000001",
          "tgn:7012149",
          "tgn:2001867",
          "tgn:7007825",
          "tgn:7029392"
        ],
        "placetype": [
          "aat:300008706"
        ],
        "id": 2688341,
        "name:xx": "Spruce Creek"
      }
    },
    {
      "geometry": {
        "type": "Point",
        "coordinates": [
          -84.8,
          36.4833
        ]
      },
      "type": "Feature",
      "properties": {
        "hierarchy": [
          "tgn:2688342",
          "tgn:1000001",
          "tgn:7012149",
          "tgn:2001861",
          "tgn:7007825",
          "tgn:7029392"
        ],
        "placetype": [
          "aat:300008706"
        ],
        "id": 2688342,
        "name:xx": "Spruce Creek"
      }
    },
    {
      "geometry": {
        "type": "Point",
        "coordinates": [
          -109.4167,
          40.85
        ]
      },
      "type": "Feature",
      "properties": {
        "hierarchy": [
          "tgn:2688343",
          "tgn:1000001",
          "tgn:2002105",
          "tgn:7012149",
          "tgn:7007827",
          "tgn:7029392"
        ],
        "placetype": [
          "aat:300008706"
        ],
        "id": 2688343,
        "name:xx": "Spruce Creek"
      }
    },
    {
      "geometry": {
        "type": "Point",
        "coordinates": [
          -78.9333,
          37.9
        ]
      },
      "type": "Feature",
      "properties": {
        "hierarchy": [
          "tgn:2688344",
          "tgn:1000001",
          "tgn:7012149",
          "tgn:2002175",
          "tgn:7007919",
          "tgn:7029392"
        ],
        "placetype": [
          "aat:300008706"
        ],
        "id": 2688344,
        "name:xx": "Spruce Creek"
      }
    },
    {
      "geometry": {
        "type": "Point",
        "coordinates": [
          -121.1667,
          46.55
        ]
      },
      "type": "Feature",
      "properties": {
        "hierarchy": [
          "tgn:2688345",
          "tgn:1000001",
          "tgn:7012149",
          "tgn:1003042",
          "tgn:7007920",
          "tgn:7029392"
        ],
        "placetype": [
          "aat:300008706"
        ],
        "id": 2688345,
        "name:xx": "Spruce Creek"
      }
    },
    {
      "geometry": {
        "type": "Point",
        "coordinates": [
          -124.0833,
          47.8333
        ]
      },
      "type": "Feature",
      "properties": {
        "hierarchy": [
          "tgn:2688346",
          "tgn:1000001",
          "tgn:7012149",
          "tgn:1002521",
          "tgn:7007920",
          "tgn:7029392"
        ],
        "placetype": [
          "aat:300008706"
        ],
        "id": 2688346,
        "name:xx": "Spruce Creek"
      }
    },
    {
      "geometry": {
        "type": "Point",
        "coordinates": [
          -120.9667,
          48.25
        ]
      },
      "type": "Feature",
      "properties": {
        "hierarchy": [
          "tgn:2688347",
          "tgn:1000001",
          "tgn:7012149",
          "tgn:1002899",
          "tgn:7007920",
          "tgn:7029392"
        ],
        "placetype": [
          "aat:300008706"
        ],
        "id": 2688347,
        "name:xx": "Spruce Creek"
      }
    },
    {
      "geometry": {
        "type": "Point",
        "coordinates": [
          -124.05,
          47.85
        ]
      },
      "type": "Feature",
      "properties": {
        "hierarchy": [
          "tgn:2688348",
          "tgn:1000001",
          "tgn:7012149",
          "tgn:7007920",
          "tgn:7029392"
        ],
        "placetype": [
          "aat:300008706"
        ],
        "id": 2688348,
        "name:xx": "Spruce Creek"
      }
    },
    {
      "geometry": {
        "type": "Point",
        "coordinates": [
          -80.9333,
          39.0667
        ]
      },
      "type": "Feature",
      "properties": {
        "hierarchy": [
          "tgn:2688349",
          "tgn:1000001",
          "tgn:7012149",
          "tgn:2002292",
          "tgn:7013961",
          "tgn:7029392"
        ],
        "placetype": [
          "aat:300008706"
        ],
        "id": 2688349,
        "name:xx": "Spruce Creek"
      }
    }
  ]
}
