{
  "geometry": {
    "type": "Point",
    "coordinates": [
      -91.55,
      35.65
    ]
  },
  "type": "Feature",
  "properties": {
    "hierarchy": [
      "tgn:2536456",
      "tgn:1000001",
      "tgn:7016172",
      "tgn:7012149",
      "tgn:2000136",
      "tgn:7029392"
    ],
    "placetype": [
      "aat:300008798"
    ],
    "id": 2536456,
    "name:xx": "Neal Mountain"
  }
}
