{
  "geometry": {
    "type": "Point",
    "coordinates": [
      -90.8167,
      31.95
    ]
  },
  "type": "Feature",
  "properties": {
    "hierarchy": [
      "tgn:2187722",
      "tgn:1000001",
      "tgn:2001096",
      "tgn:7012149",
      "tgn:7007522",
      "tgn:7029392"
    ],
    "placetype": [
      "aat:300008706"
    ],
    "id": 2187722,
    "name:xx": "Booths Creek"
  }
}
