{
  "geometry": {
    "type": "Point",
    "coordinates": [
      59.85,
      54.8667
    ]
  },
  "type": "Feature",
  "properties": {
    "hierarchy": [
      "tgn:1137836",
      "tgn:6001314",
      "tgn:1000004",
      "tgn:7018214",
      "tgn:7002435",
      "tgn:7029392"
    ],
    "placetype": [
      "aat:300008347"
    ],
    "id": 1137836,
    "name:xx": "Leninsk"
  }
}
