{
  "geometry": {
    "type": "Point",
    "coordinates": [
      -85.15,
      33.05
    ]
  },
  "type": "Feature",
  "properties": {
    "hierarchy": [
      "tgn:2744318",
      "tgn:1000001",
      "tgn:7012149",
      "tgn:2000432",
      "tgn:7007248",
      "tgn:7029392"
    ],
    "placetype": [
      "aat:300008347"
    ],
    "id": 2744318,
    "name:xx": "Vernon"
  }
}
