{
  "geometry": {
    "type": "Point",
    "coordinates": [
      -115.75,
      41.0167
    ]
  },
  "type": "Feature",
  "properties": {
    "hierarchy": [
      "tgn:2305251",
      "tgn:1000001",
      "tgn:2001411",
      "tgn:7012149",
      "tgn:7007526",
      "tgn:7029392"
    ],
    "placetype": [
      "aat:300008706"
    ],
    "id": 2305251,
    "name:xx": "East Branch Sherman Creek"
  }
}
