{
  "geometry": {
    "type": "Point",
    "coordinates": [
      -76.2167,
      40.7833
    ]
  },
  "type": "Feature",
  "properties": {
    "hierarchy": [
      "tgn:2085962",
      "tgn:1000001",
      "tgn:7012149",
      "tgn:1002876",
      "tgn:7007710",
      "tgn:7029392"
    ],
    "placetype": [
      "aat:300008347"
    ],
    "id": 2085962,
    "name:xx": "Altamont"
  }
}
