{
  "type": "FeatureCollection",
  "features": [
    {
      "geometry": {
        "type": "Point",
        "coordinates": [
          -99.233333,
          16.766667
        ]
      },
      "type": "Feature",
      "properties": {
        "hierarchy": [
          "tgn:7356190",
          "tgn:7005585",
          "tgn:1000001",
          "tgn:7005560",
          "tgn:7029392"
        ],
        "placetype": [
          "aat:300008347"
        ],
        "id": 7356190,
        "name:xx": "Caridad"
      }
    },
    {
      "geometry": {
        "type": "Point",
        "coordinates": [
          -106.95,
          27.916667
        ]
      },
      "type": "Feature",
      "properties": {
        "hierarchy": [
          "tgn:7356191",
          "tgn:7005581",
          "tgn:1000001",
          "tgn:7005560",
          "tgn:7029392"
        ],
        "placetype": [
          "aat:300008795"
        ],
        "id": 7356191,
        "name:xx": "Carichic, Sierra"
      }
    },
    {
      "geometry": {
        "type": "Point",
        "coordinates": [
          -107.083333,
          27.833333
        ]
      },
      "type": "Feature",
      "properties": {
        "hierarchy": [
          "tgn:7356192",
          "tgn:7005581",
          "tgn:1000001",
          "tgn:7005560",
          "tgn:7029392"
        ],
        "placetype": [
          "aat:300008699"
        ],
        "id": 7356192,
        "name:xx": "Carichic, Río"
      }
    },
    {
      "geometry": {
        "type": "Point",
        "coordinates": [
          -107.616667,
          28.683333
        ]
      },
      "type": "Feature",
      "properties": {
        "hierarchy": [
          "tgn:7356193",
          "tgn:7005581",
          "tgn:1000001",
          "tgn:7005560",
          "tgn:7029392"
        ],
        "placetype": [
          "aat:300008347"
        ],
        "id": 7356193,
        "name:xx": "Carichic"
      }
    },
    {
      "geometry": {
        "type": "Point",
        "coordinates": [
          -107,
          28.066667
        ]
      },
      "type": "Feature",
      "properties": {
        "hierarchy": [
          "tgn:7356195",
          "tgn:7005581",
          "tgn:1000001",
          "tgn:7005560",
          "tgn:7029392"
        ],
        "placetype": [
          "aat:300008347"
        ],
        "id": 7356195,
        "name:xx": "Carichic"
      }
    },
    {
      "geometry": {
        "type": "Point",
        "coordinates": [
          -91.066667,
          16.3
        ]
      },
      "type": "Feature",
      "properties": {
        "hierarchy": [
          "tgn:7356197",
          "tgn:7005580",
          "tgn:1000001",
          "tgn:7005560",
          "tgn:7029392"
        ],
        "placetype": [
          "aat:300008795"
        ],
        "id": 7356197,
        "name:xx": "Caribe, Sierra"
      }
    },
    {
      "geometry": {
        "type": "Point",
        "coordinates": [
          -90.666667,
          18.333333
        ]
      },
      "type": "Feature",
      "properties": {
        "hierarchy": [
          "tgn:7356198",
          "tgn:7005578",
          "tgn:1000001",
          "tgn:7005560",
          "tgn:7029392"
        ],
        "placetype": [
          "aat:300008699"
        ],
        "id": 7356198,
        "name:xx": "Caribe, Río"
      }
    },
    {
      "geometry": {
        "type": "Point",
        "coordinates": [
          -91.166667,
          16.35
        ]
      },
      "type": "Feature",
      "properties": {
        "hierarchy": [
          "tgn:7356199",
          "tgn:7005580",
          "tgn:1000001",
          "tgn:7005560",
          "tgn:7029392"
        ],
        "placetype": [
          "aat:300008795"
        ],
        "id": 7356199,
        "name:xx": "Caribe, Cerro"
      }
    }
  ]
}
