{
  "geometry": {
    "type": "Point",
    "coordinates": [
      29.55,
      30.933333
    ]
  },
  "type": "Feature",
  "properties": {
    "hierarchy": [
      "tgn:7522321",
      "tgn:7001242",
      "tgn:7016833",
      "tgn:1001418",
      "tgn:7029392"
    ],
    "placetype": [
      "aat:300008347"
    ],
    "name:en": "Dawwār Siwākah",
    "id": 7522321
  }
}
