{
  "geometry": {
    "type": "Point",
    "coordinates": [
      72.6667,
      42.5333
    ]
  },
  "type": "Feature",
  "properties": {
    "hierarchy": [
      "tgn:1137217",
      "tgn:1000004",
      "tgn:7011478",
      "tgn:7006655",
      "tgn:7029392"
    ],
    "placetype": [
      "aat:300008347"
    ],
    "id": 1137217,
    "name:xx": "Aral"
  }
}
