{
  "geometry": {
    "type": "Point",
    "coordinates": [
      -169.7167,
      66.0167
    ]
  },
  "type": "Feature",
  "properties": {
    "hierarchy": [
      "tgn:1057329",
      "tgn:6001445",
      "tgn:1000004",
      "tgn:7018214",
      "tgn:7002435",
      "tgn:7029392"
    ],
    "placetype": [
      "aat:300008347"
    ],
    "id": 1057329,
    "name:xx": "Naukan"
  }
}
