{
  "type": "FeatureCollection",
  "features": [
    {
      "geometry": {
        "type": "Point",
        "coordinates": [
          -86.15,
          39.2667
        ]
      },
      "type": "Feature",
      "properties": {
        "hierarchy": [
          "tgn:2787110",
          "tgn:1000001",
          "tgn:7012149",
          "tgn:1002678",
          "tgn:7007252",
          "tgn:7029392"
        ],
        "placetype": [
          "aat:300008798"
        ],
        "id": 2787110,
        "name:xx": "Zion Hill"
      }
    },
    {
      "geometry": {
        "type": "Point",
        "coordinates": [
          -86.6667,
          37.1
        ]
      },
      "type": "Feature",
      "properties": {
        "hierarchy": [
          "tgn:2787111",
          "tgn:1000001",
          "tgn:2000775",
          "tgn:7012149",
          "tgn:7007255",
          "tgn:7029392"
        ],
        "placetype": [
          "aat:300008798"
        ],
        "id": 2787111,
        "name:xx": "Zion Hill"
      }
    },
    {
      "geometry": {
        "type": "Point",
        "coordinates": [
          -87.2333,
          37.65
        ]
      },
      "type": "Feature",
      "properties": {
        "hierarchy": [
          "tgn:2787112",
          "tgn:1000001",
          "tgn:7012149",
          "tgn:2000786",
          "tgn:7007255",
          "tgn:7029392"
        ],
        "placetype": [
          "aat:300008798"
        ],
        "id": 2787112,
        "name:xx": "Zion Hill"
      }
    },
    {
      "geometry": {
        "type": "Point",
        "coordinates": [
          -92.6333,
          32
        ]
      },
      "type": "Feature",
      "properties": {
        "hierarchy": [
          "tgn:2787113",
          "tgn:1000001",
          "tgn:7012149",
          "tgn:2000917",
          "tgn:7007256",
          "tgn:7029392"
        ],
        "placetype": [
          "aat:300008347"
        ],
        "id": 2787113,
        "name:xx": "Zion Hill"
      }
    },
    {
      "geometry": {
        "type": "Point",
        "coordinates": [
          -70.1,
          44.5667
        ]
      },
      "type": "Feature",
      "properties": {
        "hierarchy": [
          "tgn:2787114",
          "tgn:1000001",
          "tgn:2000921",
          "tgn:7012149",
          "tgn:7007515",
          "tgn:7029392"
        ],
        "placetype": [
          "aat:300008798"
        ],
        "id": 2787114,
        "name:xx": "Zion Hill"
      }
    },
    {
      "geometry": {
        "type": "Point",
        "coordinates": [
          -71.1667,
          42.45
        ]
      },
      "type": "Feature",
      "properties": {
        "hierarchy": [
          "tgn:2787115",
          "tgn:1000001",
          "tgn:1002665",
          "tgn:7012149",
          "tgn:7007517",
          "tgn:7029392"
        ],
        "placetype": [
          "aat:300008798"
        ],
        "id": 2787115,
        "name:xx": "Zion Hill"
      }
    },
    {
      "geometry": {
        "type": "Point",
        "coordinates": [
          -70.9,
          42.2
        ]
      },
      "type": "Feature",
      "properties": {
        "hierarchy": [
          "tgn:2787116",
          "tgn:1000001",
          "tgn:7014423",
          "tgn:7012149",
          "tgn:7007517",
          "tgn:7029392"
        ],
        "placetype": [
          "aat:300008798"
        ],
        "id": 2787116,
        "name:xx": "Zion Hill"
      }
    },
    {
      "geometry": {
        "type": "Point",
        "coordinates": [
          -90.8167,
          31.3
        ]
      },
      "type": "Feature",
      "properties": {
        "hierarchy": [
          "tgn:2787117",
          "tgn:2001088",
          "tgn:1000001",
          "tgn:7012149",
          "tgn:7007522",
          "tgn:7029392"
        ],
        "placetype": [
          "aat:300008347"
        ],
        "id": 2787117,
        "name:xx": "Zion Hill"
      }
    },
    {
      "geometry": {
        "type": "Point",
        "coordinates": [
          -89.5667,
          31.8333
        ]
      },
      "type": "Feature",
      "properties": {
        "hierarchy": [
          "tgn:2787118",
          "tgn:1000001",
          "tgn:7012149",
          "tgn:2001150",
          "tgn:7007522",
          "tgn:7029392"
        ],
        "placetype": [
          "aat:300008347"
        ],
        "id": 2787118,
        "name:xx": "Zion Hill"
      }
    },
    {
      "geometry": {
        "type": "Point",
        "coordinates": [
          -89.7833,
          31.9167
        ]
      },
      "type": "Feature",
      "properties": {
        "hierarchy": [
          "tgn:2787119",
          "tgn:1000001",
          "tgn:7012149",
          "tgn:2001149",
          "tgn:7007522",
          "tgn:7029392"
        ],
        "placetype": [
          "aat:300008347"
        ],
        "id": 2787119,
        "name:xx": "Zion Hill"
      }
    }
  ]
}
