{
  "geometry": {
    "type": "Point",
    "coordinates": [
      -112.6167,
      35.15
    ]
  },
  "type": "Feature",
  "properties": {
    "hierarchy": [
      "tgn:2670833",
      "tgn:1000001",
      "tgn:7006451",
      "tgn:7012149",
      "tgn:2000103",
      "tgn:7029392"
    ],
    "placetype": [
      "aat:300008798"
    ],
    "id": 2670833,
    "name:xx": "Smith Butte"
  }
}
