{
  "geometry": {
    "type": "Point",
    "coordinates": [
      -116.4167,
      43.8667
    ]
  },
  "type": "Feature",
  "properties": {
    "hierarchy": [
      "tgn:2579491",
      "tgn:1000001",
      "tgn:7012149",
      "tgn:2000474",
      "tgn:7007250",
      "tgn:7029392"
    ],
    "placetype": [
      "aat:300008761"
    ],
    "id": 2579491,
    "name:xx": "Picket Corral Canyon"
  }
}
