{
  "geometry": {
    "type": "Point",
    "coordinates": [
      -122.7167,
      44.6833
    ]
  },
  "type": "Feature",
  "properties": {
    "hierarchy": [
      "tgn:2627732",
      "tgn:1000001",
      "tgn:7012149",
      "tgn:2001717",
      "tgn:7007708",
      "tgn:7029392"
    ],
    "placetype": [
      "aat:300008798"
    ],
    "id": 2627732,
    "name:xx": "Rogers Mountain"
  }
}
