{
  "geometry": {
    "type": "Point",
    "coordinates": [
      -83.55,
      39.3333
    ]
  },
  "type": "Feature",
  "properties": {
    "hierarchy": [
      "tgn:2080330",
      "tgn:1000001",
      "tgn:7012149",
      "tgn:1002476",
      "tgn:7007706",
      "tgn:7029392"
    ],
    "placetype": [
      "aat:300008347"
    ],
    "id": 2080330,
    "name:xx": "Leesburg"
  }
}
