{
  "geometry": {
    "type": "Point",
    "coordinates": [
      -87.0833,
      41.4667
    ]
  },
  "type": "Feature",
  "properties": {
    "hierarchy": [
      "tgn:2492454",
      "tgn:1000001",
      "tgn:7012149",
      "tgn:1002798",
      "tgn:7007252",
      "tgn:7029392"
    ],
    "placetype": [
      "aat:300008347"
    ],
    "id": 2492454,
    "name:xx": "Marian Manor"
  }
}
