{
  "geometry": {
    "type": "Point",
    "coordinates": [
      -88.35,
      45.0833
    ]
  },
  "type": "Feature",
  "properties": {
    "hierarchy": [
      "tgn:2592100",
      "tgn:1000001",
      "tgn:7012149",
      "tgn:2002341",
      "tgn:7007922",
      "tgn:7029392"
    ],
    "placetype": [
      "aat:300008680"
    ],
    "id": 2592100,
    "name:xx": "Ponsegrau Lake"
  }
}
