{
  "geometry": {
    "type": "Point",
    "coordinates": [
      -119.6833,
      48.9333
    ]
  },
  "type": "Feature",
  "properties": {
    "hierarchy": [
      "tgn:2232106",
      "tgn:1000001",
      "tgn:7012149",
      "tgn:1002742",
      "tgn:7007920",
      "tgn:7029392"
    ],
    "placetype": [
      "aat:300008699"
    ],
    "id": 2232106,
    "name:xx": "Champneys Slough Stream"
  }
}
