{
  "geometry": {
    "type": "Point",
    "coordinates": [
      -90.3833,
      39.8667
    ]
  },
  "type": "Feature",
  "properties": {
    "hierarchy": [
      "tgn:2556717",
      "tgn:1000001",
      "tgn:1002241",
      "tgn:7012149",
      "tgn:7007251",
      "tgn:7029392"
    ],
    "placetype": [
      "aat:300008706"
    ],
    "id": 2556717,
    "name:xx": "Old Channel Mud Creek"
  }
}
