{
  "geometry": {
    "type": "Point",
    "coordinates": [
      3.35,
      46.5667
    ]
  },
  "type": "Feature",
  "properties": {
    "hierarchy": [
      "tgn:1036311",
      "tgn:7002871",
      "tgn:1000003",
      "tgn:1000070",
      "tgn:7029392"
    ],
    "placetype": [
      "aat:300008347"
    ],
    "id": 1036311,
    "name:xx": "Yzeure"
  }
}
