{
  "geometry": {
    "type": "Point",
    "coordinates": [
      -81.1167,
      28.5833
    ]
  },
  "type": "Feature",
  "properties": {
    "hierarchy": [
      "tgn:2480239",
      "tgn:1000001",
      "tgn:7012149",
      "tgn:1002749",
      "tgn:7007240",
      "tgn:7029392"
    ],
    "placetype": [
      "aat:300008347"
    ],
    "id": 2480239,
    "name:xx": "Lake Pickett"
  }
}
