{
  "geometry": {
    "type": "Point",
    "coordinates": [
      27.2333,
      49.0333
    ]
  },
  "type": "Feature",
  "properties": {
    "hierarchy": [
      "tgn:1061235",
      "tgn:1000003",
      "tgn:7016777",
      "tgn:7006660",
      "tgn:7029392"
    ],
    "placetype": [
      "aat:300008347"
    ],
    "id": 1061235,
    "name:xx": "Vin'kivtsi"
  }
}
