{
  "geometry": {
    "type": "Point",
    "coordinates": [
      -80.4667,
      40.1333
    ]
  },
  "type": "Feature",
  "properties": {
    "hierarchy": [
      "tgn:2302172",
      "tgn:1000001",
      "tgn:7012149",
      "tgn:1002995",
      "tgn:7007710",
      "tgn:7029392"
    ],
    "placetype": [
      "aat:300006191"
    ],
    "id": 2302172,
    "name:xx": "Dutch Fork Lake"
  }
}
