{
  "type": "FeatureCollection",
  "features": [
    {
      "geometry": {
        "type": "Point",
        "coordinates": [
          -118.9333,
          35.7
        ]
      },
      "type": "Feature",
      "properties": {
        "hierarchy": [
          "tgn:2463770",
          "tgn:1000001",
          "tgn:7012149",
          "tgn:1002545",
          "tgn:7007157",
          "tgn:7029392"
        ],
        "placetype": [
          "aat:300008761"
        ],
        "id": 2463770,
        "name:xx": "Locked Gate Gulch"
      }
    },
    {
      "geometry": {
        "type": "Point",
        "coordinates": [
          -108.2667,
          33.15
        ]
      },
      "type": "Feature",
      "properties": {
        "hierarchy": [
          "tgn:2463771",
          "tgn:1000001",
          "tgn:7012149",
          "tgn:2001437",
          "tgn:7007566",
          "tgn:7029392"
        ],
        "placetype": [
          "aat:300006191"
        ],
        "id": 2463771,
        "name:xx": "Locked Horns Tank"
      }
    },
    {
      "geometry": {
        "type": "Point",
        "coordinates": [
          -83.4333,
          38.1167
        ]
      },
      "type": "Feature",
      "properties": {
        "hierarchy": [
          "tgn:2463772",
          "tgn:1000001",
          "tgn:7012149",
          "tgn:1002837",
          "tgn:7007255",
          "tgn:7029392"
        ],
        "placetype": [
          "aat:300008699"
        ],
        "id": 2463772,
        "name:xx": "Lockegee Branch"
      }
    },
    {
      "geometry": {
        "type": "Point",
        "coordinates": [
          -83.4333,
          38.1167
        ]
      },
      "type": "Feature",
      "properties": {
        "hierarchy": [
          "tgn:2463773",
          "tgn:1000001",
          "tgn:7012149",
          "tgn:1002837",
          "tgn:7007255",
          "tgn:7029392"
        ],
        "placetype": [
          "aat:300008798"
        ],
        "id": 2463773,
        "name:xx": "Lockegee Rock"
      }
    },
    {
      "geometry": {
        "type": "Point",
        "coordinates": [
          -80.5,
          35.65
        ]
      },
      "type": "Feature",
      "properties": {
        "hierarchy": [
          "tgn:2463774",
          "tgn:1000001",
          "tgn:7012149",
          "tgn:2001536",
          "tgn:7007709",
          "tgn:7029392"
        ],
        "placetype": [
          "aat:300008347"
        ],
        "id": 2463774,
        "name:xx": "Lockeland"
      }
    },
    {
      "geometry": {
        "type": "Point",
        "coordinates": [
          -74.55,
          41.3167
        ]
      },
      "type": "Feature",
      "properties": {
        "hierarchy": [
          "tgn:2463775",
          "tgn:1000001",
          "tgn:7012149",
          "tgn:1002751",
          "tgn:7007568",
          "tgn:7029392"
        ],
        "placetype": [
          "aat:300008680"
        ],
        "id": 2463775,
        "name:xx": "Lockenhurst Pond"
      }
    },
    {
      "geometry": {
        "type": "Point",
        "coordinates": [
          -103.5167,
          31.3667
        ]
      },
      "type": "Feature",
      "properties": {
        "hierarchy": [
          "tgn:2463776",
          "tgn:1000001",
          "tgn:7012149",
          "tgn:2002062",
          "tgn:7007826",
          "tgn:7029392"
        ],
        "placetype": [
          "aat:300008347"
        ],
        "id": 2463776,
        "name:xx": "Locker"
      }
    },
    {
      "geometry": {
        "type": "Point",
        "coordinates": [
          -86.5833,
          35.1
        ]
      },
      "type": "Feature",
      "properties": {
        "hierarchy": [
          "tgn:2463777",
          "tgn:1000001",
          "tgn:7012149",
          "tgn:2001888",
          "tgn:7007825",
          "tgn:7029392"
        ],
        "placetype": [
          "aat:300008798"
        ],
        "id": 2463777,
        "name:xx": "Locker Hill"
      }
    },
    {
      "geometry": {
        "type": "Point",
        "coordinates": [
          -98.9,
          31.3667
        ]
      },
      "type": "Feature",
      "properties": {
        "hierarchy": [
          "tgn:2463778",
          "tgn:1000001",
          "tgn:7012149",
          "tgn:2002069",
          "tgn:7007826",
          "tgn:7029392"
        ],
        "placetype": [
          "aat:300008798"
        ],
        "id": 2463778,
        "name:xx": "Locker Hill"
      }
    },
    {
      "geometry": {
        "type": "Point",
        "coordinates": [
          -84.15,
          42.3
        ]
      },
      "type": "Feature",
      "properties": {
        "hierarchy": [
          "tgn:2463779",
          "tgn:1000001",
          "tgn:7012149",
          "tgn:1002509",
          "tgn:7007520",
          "tgn:7029392"
        ],
        "placetype": [
          "aat:300008680"
        ],
        "id": 2463779,
        "name:xx": "Locker Lake"
      }
    }
  ]
}
