{
  "geometry": {
    "type": "Point",
    "coordinates": [
      -136.35,
      57.8167
    ]
  },
  "type": "Feature",
  "properties": {
    "hierarchy": [
      "tgn:2593437",
      "tgn:7006450",
      "tgn:1000001",
      "tgn:7012149",
      "tgn:2124002",
      "tgn:7029392"
    ],
    "placetype": [
      "aat:300132316"
    ],
    "id": 2593437,
    "name:xx": "Porcupine Bay"
  }
}
