{
  "geometry": {
    "type": "Point",
    "coordinates": [
      -92.9167,
      37.25
    ]
  },
  "type": "Feature",
  "properties": {
    "hierarchy": [
      "tgn:2450070",
      "tgn:1000001",
      "tgn:7012149",
      "tgn:2001256",
      "tgn:7007523",
      "tgn:7029392"
    ],
    "placetype": [
      "aat:300008347"
    ],
    "id": 2450070,
    "name:xx": "Lindstrew Ford"
  }
}
