{
  "geometry": {
    "type": "Point",
    "coordinates": [
      -80.6333,
      39.8333
    ]
  },
  "type": "Feature",
  "properties": {
    "hierarchy": [
      "tgn:2118390",
      "tgn:1000001",
      "tgn:7012149",
      "tgn:2002276",
      "tgn:7013961",
      "tgn:7029392"
    ],
    "placetype": [
      "aat:300008347"
    ],
    "id": 2118390,
    "name:xx": "Glen Easton"
  }
}
