{
  "geometry": {
    "type": "Point",
    "coordinates": [
      -92.7167,
      42.85
    ]
  },
  "type": "Feature",
  "properties": {
    "hierarchy": [
      "tgn:2035420",
      "tgn:1000001",
      "tgn:2000572",
      "tgn:7012149",
      "tgn:7007253",
      "tgn:7029392"
    ],
    "placetype": [
      "aat:300008347"
    ],
    "id": 2035420,
    "name:xx": "Packard"
  }
}
