{
  "geometry": {
    "type": "Point",
    "coordinates": [
      -104.8333,
      44.5667
    ]
  },
  "type": "Feature",
  "properties": {
    "hierarchy": [
      "tgn:7019783",
      "tgn:1000001",
      "tgn:2002370",
      "tgn:7012149",
      "tgn:7007923",
      "tgn:7029392"
    ],
    "placetype": [
      "aat:300006191"
    ],
    "id": 7019783,
    "name:xx": "Basin Reservoir Number 2"
  }
}
