{
  "geometry": {
    "type": "Point",
    "coordinates": [
      -124.35,
      40.4333
    ]
  },
  "type": "Feature",
  "properties": {
    "hierarchy": [
      "tgn:2220558",
      "tgn:1000001",
      "tgn:7012149",
      "tgn:2000181",
      "tgn:7007157",
      "tgn:7029392"
    ],
    "placetype": [
      "aat:300266640"
    ],
    "id": 2220558,
    "name:xx": "Cape Ridge"
  }
}
