{
  "geometry": {
    "type": "Point",
    "coordinates": [
      -103.7667,
      37.4333
    ]
  },
  "type": "Feature",
  "properties": {
    "hierarchy": [
      "tgn:2278674",
      "tgn:1000001",
      "tgn:7012149",
      "tgn:2000227",
      "tgn:7007158",
      "tgn:7029392"
    ],
    "placetype": [
      "aat:300008761"
    ],
    "id": 2278674,
    "name:xx": "Dead Horse Canyon"
  }
}
