{
  "geometry": {
    "type": "Point",
    "coordinates": [
      87.898201,
      23.073019
    ]
  },
  "type": "Feature",
  "properties": {
    "hierarchy": [
      "tgn:1076727",
      "tgn:1000004",
      "tgn:7000198",
      "tgn:1001977",
      "tgn:7029392"
    ],
    "placetype": [
      "aat:300008347"
    ],
    "name:en": "Rāyna",
    "id": 1076727
  }
}
