{
  "geometry": {
    "type": "Point",
    "coordinates": [
      -108.8667,
      33.25
    ]
  },
  "type": "Feature",
  "properties": {
    "hierarchy": [
      "tgn:2341198",
      "tgn:1000001",
      "tgn:7012149",
      "tgn:7029392"
    ],
    "placetype": [
      "aat:300008761"
    ],
    "id": 2341198,
    "name:xx": "Frisco Canyon"
  }
}
