{
  "geometry": {
    "type": "Point",
    "coordinates": [
      -86.0167,
      35.7667
    ]
  },
  "type": "Feature",
  "properties": {
    "hierarchy": [
      "tgn:2781905",
      "tgn:1000001",
      "tgn:7012149",
      "tgn:2001844",
      "tgn:7007825",
      "tgn:7029392"
    ],
    "placetype": [
      "aat:300008761"
    ],
    "id": 2781905,
    "name:xx": "Woods Hollow"
  }
}
