{
  "geometry": {
    "type": "Point",
    "coordinates": [
      -154.6333,
      69.4167
    ]
  },
  "type": "Feature",
  "properties": {
    "hierarchy": [
      "tgn:2432144",
      "tgn:7006450",
      "tgn:1000001",
      "tgn:7012149",
      "tgn:2124005",
      "tgn:7029392"
    ],
    "placetype": [
      "aat:300008706"
    ],
    "id": 2432144,
    "name:xx": "Kay Creek"
  }
}
