{
  "type": "FeatureCollection",
  "features": [
    {
      "geometry": {
        "type": "Point",
        "coordinates": [
          -81.6667,
          39.0833
        ]
      },
      "type": "Feature",
      "properties": {
        "hierarchy": [
          "tgn:2468940",
          "tgn:1000001",
          "tgn:7012149",
          "tgn:2002303",
          "tgn:7013961",
          "tgn:7029392"
        ],
        "placetype": [
          "aat:300008699"
        ],
        "id": 2468940,
        "name:xx": "Long Run"
      }
    },
    {
      "geometry": {
        "type": "Point",
        "coordinates": [
          -79.55,
          39.15
        ]
      },
      "type": "Feature",
      "properties": {
        "hierarchy": [
          "tgn:2468941",
          "tgn:1000001",
          "tgn:7012149",
          "tgn:2002296",
          "tgn:7013961",
          "tgn:7029392"
        ],
        "placetype": [
          "aat:300008699"
        ],
        "id": 2468941,
        "name:xx": "Long Run"
      }
    },
    {
      "geometry": {
        "type": "Point",
        "coordinates": [
          -80.8,
          39.1167
        ]
      },
      "type": "Feature",
      "properties": {
        "hierarchy": [
          "tgn:2468942",
          "tgn:1000001",
          "tgn:2002260",
          "tgn:7012149",
          "tgn:7013961",
          "tgn:7029392"
        ],
        "placetype": [
          "aat:300008699"
        ],
        "id": 2468942,
        "name:xx": "Long Run"
      }
    },
    {
      "geometry": {
        "type": "Point",
        "coordinates": [
          -81.1833,
          39.2333
        ]
      },
      "type": "Feature",
      "properties": {
        "hierarchy": [
          "tgn:2468943",
          "tgn:1000001",
          "tgn:7012149",
          "tgn:2002292",
          "tgn:7013961",
          "tgn:7029392"
        ],
        "placetype": [
          "aat:300008699"
        ],
        "id": 2468943,
        "name:xx": "Long Run"
      }
    },
    {
      "geometry": {
        "type": "Point",
        "coordinates": [
          -80.0833,
          39.3
        ]
      },
      "type": "Feature",
      "properties": {
        "hierarchy": [
          "tgn:2468944",
          "tgn:1000001",
          "tgn:7012149",
          "tgn:2002295",
          "tgn:7013961",
          "tgn:7029392"
        ],
        "placetype": [
          "aat:300008699"
        ],
        "id": 2468944,
        "name:xx": "Long Run"
      }
    },
    {
      "geometry": {
        "type": "Point",
        "coordinates": [
          -81.15,
          39.3667
        ]
      },
      "type": "Feature",
      "properties": {
        "hierarchy": [
          "tgn:2468945",
          "tgn:1000001",
          "tgn:7012149",
          "tgn:2002286",
          "tgn:7013961",
          "tgn:7029392"
        ],
        "placetype": [
          "aat:300008699"
        ],
        "id": 2468945,
        "name:xx": "Long Run"
      }
    },
    {
      "geometry": {
        "type": "Point",
        "coordinates": [
          -78.7667,
          39.4
        ]
      },
      "type": "Feature",
      "properties": {
        "hierarchy": [
          "tgn:2468946",
          "tgn:1000001",
          "tgn:7012149",
          "tgn:2002265",
          "tgn:7013961",
          "tgn:7029392"
        ],
        "placetype": [
          "aat:300008699"
        ],
        "id": 2468946,
        "name:xx": "Long Run"
      }
    },
    {
      "geometry": {
        "type": "Point",
        "coordinates": [
          -80.05,
          39.4167
        ]
      },
      "type": "Feature",
      "properties": {
        "hierarchy": [
          "tgn:2468947",
          "tgn:1000001",
          "tgn:7012149",
          "tgn:2002275",
          "tgn:7013961",
          "tgn:7029392"
        ],
        "placetype": [
          "aat:300008699"
        ],
        "id": 2468947,
        "name:xx": "Long Run"
      }
    },
    {
      "geometry": {
        "type": "Point",
        "coordinates": [
          -80.9167,
          39.5333
        ]
      },
      "type": "Feature",
      "properties": {
        "hierarchy": [
          "tgn:2468948",
          "tgn:1000001",
          "tgn:7012149",
          "tgn:2002297",
          "tgn:7013961",
          "tgn:7029392"
        ],
        "placetype": [
          "aat:300008699"
        ],
        "id": 2468948,
        "name:xx": "Long Run"
      }
    },
    {
      "geometry": {
        "type": "Point",
        "coordinates": [
          -80.65,
          40.1167
        ]
      },
      "type": "Feature",
      "properties": {
        "hierarchy": [
          "tgn:2468949",
          "tgn:1000001",
          "tgn:7012149",
          "tgn:1002741",
          "tgn:7013961",
          "tgn:7029392"
        ],
        "placetype": [
          "aat:300008699"
        ],
        "id": 2468949,
        "name:xx": "Long Run"
      }
    }
  ]
}
