{
  "geometry": {
    "type": "Point",
    "coordinates": [
      -96.15,
      37.0167
    ]
  },
  "type": "Feature",
  "properties": {
    "hierarchy": [
      "tgn:2562036",
      "tgn:1000001",
      "tgn:2000669",
      "tgn:7012149",
      "tgn:7007254",
      "tgn:7029392"
    ],
    "placetype": [
      "aat:300008706"
    ],
    "id": 2562036,
    "name:xx": "Otter Creek"
  }
}
