{
  "geometry": {
    "type": "Point",
    "coordinates": [
      -89.05,
      35.1667
    ]
  },
  "type": "Feature",
  "properties": {
    "hierarchy": [
      "tgn:2673778",
      "tgn:1000001",
      "tgn:7012149",
      "tgn:2001871",
      "tgn:7007825",
      "tgn:7029392"
    ],
    "placetype": [
      "aat:300008706"
    ],
    "id": 2673778,
    "name:xx": "Snow Creek"
  }
}
