{
  "geometry": {
    "type": "Point",
    "coordinates": [
      -81.7333,
      33.85
    ]
  },
  "type": "Feature",
  "properties": {
    "hierarchy": [
      "tgn:2159837",
      "tgn:1000001",
      "tgn:7012149",
      "tgn:7007712",
      "tgn:7029392"
    ],
    "placetype": [
      "aat:300008706"
    ],
    "id": 2159837,
    "name:xx": "Beech Creek"
  }
}
