{
  "type": "FeatureCollection",
  "features": [
    {
      "geometry": {
        "type": "Point",
        "coordinates": [
          -88.6667,
          34.8667
        ]
      },
      "type": "Feature",
      "properties": {
        "hierarchy": [
          "tgn:2427070",
          "tgn:2001087",
          "tgn:1000001",
          "tgn:7012149",
          "tgn:7007522",
          "tgn:7029392"
        ],
        "placetype": [
          "aat:300008347"
        ],
        "id": 2427070,
        "name:xx": "Jonestown"
      }
    },
    {
      "geometry": {
        "type": "Point",
        "coordinates": [
          -90.8667,
          32.3167
        ]
      },
      "type": "Feature",
      "properties": {
        "hierarchy": [
          "tgn:2427071",
          "tgn:1000001",
          "tgn:7012149",
          "tgn:2001160",
          "tgn:7007522",
          "tgn:7029392"
        ],
        "placetype": [
          "aat:300008347"
        ],
        "id": 2427071,
        "name:xx": "Jonestown"
      }
    },
    {
      "geometry": {
        "type": "Point",
        "coordinates": [
          -80.3333,
          36.05
        ]
      },
      "type": "Feature",
      "properties": {
        "hierarchy": [
          "tgn:2427072",
          "tgn:1000001",
          "tgn:7012149",
          "tgn:2001494",
          "tgn:7007709",
          "tgn:7029392"
        ],
        "placetype": [
          "aat:300008347"
        ],
        "id": 2427072,
        "name:xx": "Jonestown"
      }
    },
    {
      "geometry": {
        "type": "Point",
        "coordinates": [
          -82.6167,
          39.0833
        ]
      },
      "type": "Feature",
      "properties": {
        "hierarchy": [
          "tgn:2427073",
          "tgn:1000001",
          "tgn:7012149",
          "tgn:2001614",
          "tgn:7007706",
          "tgn:7029392"
        ],
        "placetype": [
          "aat:300008347"
        ],
        "id": 2427073,
        "name:xx": "Jonestown"
      }
    },
    {
      "geometry": {
        "type": "Point",
        "coordinates": [
          -79.2333,
          33.9333
        ]
      },
      "type": "Feature",
      "properties": {
        "hierarchy": [
          "tgn:2427074",
          "tgn:1000001",
          "tgn:7012149",
          "tgn:2001750",
          "tgn:7007712",
          "tgn:7029392"
        ],
        "placetype": [
          "aat:300008347"
        ],
        "id": 2427074,
        "name:xx": "Jonestown"
      }
    },
    {
      "geometry": {
        "type": "Point",
        "coordinates": [
          -87.2,
          35.3833
        ]
      },
      "type": "Feature",
      "properties": {
        "hierarchy": [
          "tgn:2427075",
          "tgn:1000001",
          "tgn:7012149",
          "tgn:2001864",
          "tgn:7007825",
          "tgn:7029392"
        ],
        "placetype": [
          "aat:300008347"
        ],
        "id": 2427075,
        "name:xx": "Jonestown"
      }
    },
    {
      "geometry": {
        "type": "Point",
        "coordinates": [
          -82.9667,
          35.8833
        ]
      },
      "type": "Feature",
      "properties": {
        "hierarchy": [
          "tgn:2427076",
          "tgn:1000001",
          "tgn:7012149",
          "tgn:2001851",
          "tgn:7007825",
          "tgn:7029392"
        ],
        "placetype": [
          "aat:300008347"
        ],
        "id": 2427076,
        "name:xx": "Jonestown"
      }
    },
    {
      "geometry": {
        "type": "Point",
        "coordinates": [
          -79.2667,
          37.8833
        ]
      },
      "type": "Feature",
      "properties": {
        "hierarchy": [
          "tgn:2427077",
          "tgn:1000001",
          "tgn:7012149",
          "tgn:2002186",
          "tgn:7007919",
          "tgn:7029392"
        ],
        "placetype": [
          "aat:300008347"
        ],
        "id": 2427077,
        "name:xx": "Jonestown"
      }
    },
    {
      "geometry": {
        "type": "Point",
        "coordinates": [
          -86.2167,
          33.4333
        ]
      },
      "type": "Feature",
      "properties": {
        "hierarchy": [
          "tgn:2427078",
          "tgn:7002659",
          "tgn:1000001",
          "tgn:7012149",
          "tgn:2000060",
          "tgn:7029392"
        ],
        "placetype": [
          "aat:300008347"
        ],
        "id": 2427078,
        "name:xx": "Jonesview"
      }
    },
    {
      "geometry": {
        "type": "Point",
        "coordinates": [
          -85.9,
          31.8833
        ]
      },
      "type": "Feature",
      "properties": {
        "hierarchy": [
          "tgn:2427079",
          "tgn:7002659",
          "tgn:1000001",
          "tgn:7012149",
          "tgn:2000054",
          "tgn:7029392"
        ],
        "placetype": [
          "aat:300008347"
        ],
        "id": 2427079,
        "name:xx": "Jonesville"
      }
    }
  ]
}
