{
  "geometry": {
    "type": "Point",
    "coordinates": [
      26.35,
      -3.65
    ]
  },
  "type": "Feature",
  "properties": {
    "hierarchy": [
      "tgn:1089106",
      "tgn:7001242",
      "tgn:7016707",
      "tgn:1000159",
      "tgn:7029392"
    ],
    "placetype": [
      "aat:300008347"
    ],
    "id": 1089106,
    "name:xx": "Kayuyu"
  }
}
