{
  "geometry": {
    "type": "Point",
    "coordinates": [
      -83.5167,
      35.4167
    ]
  },
  "type": "Feature",
  "properties": {
    "hierarchy": [
      "tgn:2631719",
      "tgn:1000001",
      "tgn:7012149",
      "tgn:2001543",
      "tgn:7007709",
      "tgn:7029392"
    ],
    "placetype": [
      "aat:300008347"
    ],
    "id": 2631719,
    "name:xx": "Roundhill"
  }
}
