{
  "geometry": {
    "type": "Point",
    "coordinates": [
      -97.65,
      29.3833
    ]
  },
  "type": "Feature",
  "properties": {
    "hierarchy": [
      "tgn:2203244",
      "tgn:1000001",
      "tgn:7012149",
      "tgn:1002414",
      "tgn:7007826",
      "tgn:7029392"
    ],
    "placetype": [
      "aat:300008706"
    ],
    "id": 2203244,
    "name:xx": "Buckhorn Creek"
  }
}
