{
  "geometry": {
    "type": "Point",
    "coordinates": [
      -91.2667,
      40.0667
    ]
  },
  "type": "Feature",
  "properties": {
    "hierarchy": [
      "tgn:2741526",
      "tgn:1002134",
      "tgn:1000001",
      "tgn:7012149",
      "tgn:7007251",
      "tgn:7029392"
    ],
    "placetype": [
      "aat:300008706"
    ],
    "id": 2741526,
    "name:xx": "Ursa Creek"
  }
}
