{
  "geometry": {
    "type": "Point",
    "coordinates": [
      125.7167,
      10.7167
    ]
  },
  "type": "Feature",
  "properties": {
    "hierarchy": [
      "tgn:1084158",
      "tgn:1000004",
      "tgn:1007429",
      "tgn:1001231",
      "tgn:1000135",
      "tgn:7029392"
    ],
    "placetype": [
      "aat:300008347"
    ],
    "id": 1084158,
    "name:xx": "Culasi"
  }
}
