{
  "geometry": {
    "type": "Point",
    "coordinates": [
      26.532222,
      39.0275
    ]
  },
  "type": "Feature",
  "properties": {
    "hierarchy": [
      "tgn:7219933",
      "tgn:7011163",
      "tgn:7002674",
      "tgn:1000003",
      "tgn:1000074",
      "tgn:7029392"
    ],
    "placetype": [
      "aat:300132317"
    ],
    "id": 7219933,
    "name:xx": "Palaióloutros, Agkáli"
  }
}
