{
  "geometry": {
    "type": "Point",
    "coordinates": [
      79.8882,
      27.1148
    ]
  },
  "type": "Feature",
  "properties": {
    "hierarchy": [
      "tgn:7562300",
      "tgn:1000004",
      "tgn:7000198",
      "tgn:7016722",
      "tgn:7029392"
    ],
    "placetype": [
      "aat:300008347"
    ],
    "name:en": "Kachhiāpur",
    "id": 7562300
  }
}
