{
  "geometry": {
    "type": "Point",
    "coordinates": [
      -70.3667,
      43.7667
    ]
  },
  "type": "Feature",
  "properties": {
    "hierarchy": [
      "tgn:2426512",
      "tgn:1000001",
      "tgn:2000920",
      "tgn:7012149",
      "tgn:7007515",
      "tgn:7029392"
    ],
    "placetype": [
      "aat:300008798"
    ],
    "id": 2426512,
    "name:xx": "Jones Hill"
  }
}
