{
  "geometry": {
    "type": "Point",
    "coordinates": [
      36.7333,
      -6.6667
    ]
  },
  "type": "Feature",
  "properties": {
    "hierarchy": [
      "tgn:1140931",
      "tgn:7001242",
      "tgn:1001711",
      "tgn:1000203",
      "tgn:7029392"
    ],
    "placetype": [
      "aat:300008347"
    ],
    "id": 1140931,
    "name:xx": "Kidete"
  }
}
