{
  "type": "FeatureCollection",
  "features": [
    {
      "geometry": {
        "type": "Point",
        "coordinates": [
          0.9667,
          47.9
        ]
      },
      "type": "Feature",
      "properties": {
        "hierarchy": [
          "tgn:1031660",
          "tgn:1000003",
          "tgn:7002877",
          "tgn:1000070",
          "tgn:7029392"
        ],
        "placetype": [
          "aat:300008347"
        ],
        "id": 1031660,
        "name:xx": "Épuisay"
      }
    },
    {
      "geometry": {
        "type": "Point",
        "coordinates": [
          2.1,
          49.0167
        ]
      },
      "type": "Feature",
      "properties": {
        "hierarchy": [
          "tgn:1031662",
          "tgn:1000003",
          "tgn:7002883",
          "tgn:1000070",
          "tgn:7029392"
        ],
        "placetype": [
          "aat:300008347"
        ],
        "id": 1031662,
        "name:xx": "Éragny"
      }
    },
    {
      "geometry": {
        "type": "Point",
        "coordinates": [
          -2.8333,
          48.6167
        ]
      },
      "type": "Feature",
      "properties": {
        "hierarchy": [
          "tgn:1031663",
          "tgn:1000003",
          "tgn:7012216",
          "tgn:1000070",
          "tgn:7029392"
        ],
        "placetype": [
          "aat:300008347"
        ],
        "id": 1031663,
        "name:xx": "Étables"
      }
    },
    {
      "geometry": {
        "type": "Point",
        "coordinates": [
          5.6333,
          49.2167
        ]
      },
      "type": "Feature",
      "properties": {
        "hierarchy": [
          "tgn:1031664",
          "tgn:1000003",
          "tgn:7002888",
          "tgn:1000070",
          "tgn:7029392"
        ],
        "placetype": [
          "aat:300008347"
        ],
        "id": 1031664,
        "name:xx": "Étain"
      }
    },
    {
      "geometry": {
        "type": "Point",
        "coordinates": [
          2.4667,
          48.6333
        ]
      },
      "type": "Feature",
      "properties": {
        "hierarchy": [
          "tgn:1031667",
          "tgn:1000003",
          "tgn:7002883",
          "tgn:1000070",
          "tgn:7029392"
        ],
        "placetype": [
          "aat:300008347"
        ],
        "id": 1031667,
        "name:xx": "Étiolles"
      }
    },
    {
      "geometry": {
        "type": "Point",
        "coordinates": [
          1.6167,
          49.3167
        ]
      },
      "type": "Feature",
      "properties": {
        "hierarchy": [
          "tgn:1031669",
          "tgn:1000003",
          "tgn:7002882",
          "tgn:1000070",
          "tgn:7029392"
        ],
        "placetype": [
          "aat:300008347"
        ],
        "id": 1031669,
        "name:xx": "Étrépagny"
      }
    }
  ]
}
