{
  "geometry": {
    "type": "Point",
    "coordinates": [
      -61.2667,
      1.55
    ]
  },
  "type": "Feature",
  "properties": {
    "hierarchy": [
      "tgn:1121030",
      "tgn:1002001",
      "tgn:1000047",
      "tgn:7002456",
      "tgn:1000002",
      "tgn:7029392"
    ],
    "placetype": [
      "aat:300008707"
    ],
    "id": 1121030,
    "name:xx": "Ajarani"
  }
}
