{
  "type": "FeatureCollection",
  "features": [
    {
      "geometry": {
        "type": "Point",
        "coordinates": [
          -70.1667,
          -31.9833
        ]
      },
      "type": "Feature",
      "properties": {
        "hierarchy": [
          "tgn:1105613",
          "tgn:7006477",
          "tgn:1001519",
          "tgn:1000002",
          "tgn:7029392"
        ],
        "placetype": [
          "aat:300008795"
        ],
        "id": 1105613,
        "name:xx": "Mercedario, Cerro"
      }
    },
    {
      "geometry": {
        "type": "Point",
        "coordinates": [
          22.633333,
          37.5
        ]
      },
      "type": "Feature",
      "properties": {
        "hierarchy": [
          "tgn:1105614",
          "tgn:7002681",
          "tgn:7001395",
          "tgn:1000003",
          "tgn:1000074",
          "tgn:7029392"
        ],
        "placetype": [
          "aat:300008795"
        ],
        "id": 1105614,
        "name:xx": "Merkourovoúni"
      }
    },
    {
      "geometry": {
        "type": "Point",
        "coordinates": [
          35.4,
          32.9833
        ]
      },
      "type": "Feature",
      "properties": {
        "hierarchy": [
          "tgn:1105615",
          "tgn:7000249",
          "tgn:1000004",
          "tgn:1000119",
          "tgn:7029392"
        ],
        "placetype": [
          "aat:300008795"
        ],
        "id": 1105615,
        "name:xx": "Meron, Hare"
      }
    },
    {
      "geometry": {
        "type": "Point",
        "coordinates": [
          -4.466667,
          55.116667
        ]
      },
      "type": "Feature",
      "properties": {
        "hierarchy": [
          "tgn:1105616",
          "tgn:7002444",
          "tgn:7008074",
          "tgn:1000003",
          "tgn:7008591",
          "tgn:7029392"
        ],
        "placetype": [
          "aat:300008795"
        ],
        "name:en": "Merrick",
        "id": 1105616
      }
    },
    {
      "geometry": {
        "type": "Point",
        "coordinates": [
          -106.6333,
          37.9
        ]
      },
      "type": "Feature",
      "properties": {
        "hierarchy": [
          "tgn:1105618",
          "tgn:1000001",
          "tgn:7012149",
          "tgn:7007158",
          "tgn:2000246",
          "tgn:7029392"
        ],
        "placetype": [
          "aat:300008795"
        ],
        "id": 1105618,
        "name:xx": "Mesa Mountain"
      }
    },
    {
      "geometry": {
        "type": "Point",
        "coordinates": [
          -71.4833,
          -48.7667
        ]
      },
      "type": "Feature",
      "properties": {
        "hierarchy": [
          "tgn:1105619",
          "tgn:7006477",
          "tgn:1001522",
          "tgn:1000002",
          "tgn:7029392"
        ],
        "placetype": [
          "aat:300008795"
        ],
        "id": 1105619,
        "name:xx": "Mesa, Cerro"
      }
    }
  ]
}
