{
  "geometry": {
    "type": "Point",
    "coordinates": [
      -107.5333,
      42.8333
    ]
  },
  "type": "Feature",
  "properties": {
    "hierarchy": [
      "tgn:2414444",
      "tgn:1000001",
      "tgn:7012149",
      "tgn:2002371",
      "tgn:7007923",
      "tgn:7029392"
    ],
    "placetype": [
      "aat:300006191"
    ],
    "id": 2414444,
    "name:xx": "Iron Springs Reservoir"
  }
}
