{
  "geometry": {
    "type": "Point",
    "coordinates": [
      102.5333,
      18.4333
    ]
  },
  "type": "Feature",
  "properties": {
    "hierarchy": [
      "tgn:1082553",
      "tgn:1000004",
      "tgn:7000851",
      "tgn:1000125",
      "tgn:7029392"
    ],
    "placetype": [
      "aat:300008347"
    ],
    "id": 1082553,
    "name:xx": "Tourakom"
  }
}
