{
  "geometry": {
    "type": "Point",
    "coordinates": [
      -89.2667,
      45.4333
    ]
  },
  "type": "Feature",
  "properties": {
    "hierarchy": [
      "tgn:2519251",
      "tgn:1000001",
      "tgn:7012149",
      "tgn:2002333",
      "tgn:7007922",
      "tgn:7029392"
    ],
    "placetype": [
      "aat:300008680"
    ],
    "id": 2519251,
    "name:xx": "Moccasin Lake"
  }
}
