{
  "geometry": {
    "type": "Point",
    "coordinates": [
      -85.2833,
      33.65
    ]
  },
  "type": "Feature",
  "properties": {
    "hierarchy": [
      "tgn:2772565",
      "tgn:1000001",
      "tgn:7012149",
      "tgn:7029392"
    ],
    "placetype": [
      "aat:300008706"
    ],
    "id": 2772565,
    "name:xx": "Williams Creek"
  }
}
