{
  "geometry": {
    "type": "Point",
    "coordinates": [
      -116.4167,
      48.0667
    ]
  },
  "type": "Feature",
  "properties": {
    "hierarchy": [
      "tgn:2702404",
      "tgn:1000001",
      "tgn:2000460",
      "tgn:7012149",
      "tgn:7007250",
      "tgn:7029392"
    ],
    "placetype": [
      "aat:300008697"
    ],
    "id": 2702404,
    "name:xx": "Sullivan Spring"
  }
}
