{
  "geometry": {
    "type": "Point",
    "coordinates": [
      -120.7833,
      47.1167
    ]
  },
  "type": "Feature",
  "properties": {
    "hierarchy": [
      "tgn:2399254",
      "tgn:1000001",
      "tgn:7012149",
      "tgn:1002553",
      "tgn:7007920",
      "tgn:7029392"
    ],
    "placetype": [
      "aat:300008347"
    ],
    "id": 2399254,
    "name:xx": "Horlick"
  }
}
