{
  "geometry": {
    "type": "Point",
    "coordinates": [
      -82.3167,
      29.1833
    ]
  },
  "type": "Feature",
  "properties": {
    "hierarchy": [
      "tgn:2648099",
      "tgn:1000001",
      "tgn:7012149",
      "tgn:1002631",
      "tgn:7007240",
      "tgn:7029392"
    ],
    "placetype": [
      "aat:300008680"
    ],
    "id": 2648099,
    "name:xx": "Schoolhouse Pond"
  }
}
