{
  "geometry": {
    "type": "Point",
    "coordinates": [
      -92.35,
      38.0833
    ]
  },
  "type": "Feature",
  "properties": {
    "hierarchy": [
      "tgn:2182616",
      "tgn:1000001",
      "tgn:7012149",
      "tgn:1002671",
      "tgn:7007523",
      "tgn:7029392"
    ],
    "placetype": [
      "aat:300008697"
    ],
    "id": 2182616,
    "name:xx": "Blue Spring"
  }
}
