{
  "geometry": {
    "type": "Point",
    "coordinates": [
      88.25,
      22.9333
    ]
  },
  "type": "Feature",
  "properties": {
    "hierarchy": [
      "tgn:1076624",
      "tgn:1000004",
      "tgn:7000198",
      "tgn:1001977",
      "tgn:7029392"
    ],
    "placetype": [
      "aat:300008347"
    ],
    "id": 1076624,
    "name:xx": "Ponpāj"
  }
}
