{
  "geometry": {
    "type": "Point",
    "coordinates": [
      -84.7167,
      36.05
    ]
  },
  "type": "Feature",
  "properties": {
    "hierarchy": [
      "tgn:2288519",
      "tgn:1000001",
      "tgn:7012149",
      "tgn:2001901",
      "tgn:7007825",
      "tgn:7029392"
    ],
    "placetype": [
      "aat:300008699"
    ],
    "id": 2288519,
    "name:xx": "Dismal Branch"
  }
}
