{
  "geometry": {
    "type": "Point",
    "coordinates": [
      31.666667,
      31.233333
    ]
  },
  "type": "Feature",
  "properties": {
    "hierarchy": [
      "tgn:7527565",
      "tgn:7001242",
      "tgn:7016833",
      "tgn:1001225",
      "tgn:7029392"
    ],
    "placetype": [
      "aat:300005926"
    ],
    "name:en": "S카d카 Sir훮j Ab큰 Mash'al",
    "id": 7527565
  }
}
