{
  "geometry": {
    "type": "Point",
    "coordinates": [
      -95.25,
      38.8833
    ]
  },
  "type": "Feature",
  "properties": {
    "hierarchy": [
      "tgn:2655087",
      "tgn:1000001",
      "tgn:2000682",
      "tgn:7012149",
      "tgn:7007254",
      "tgn:7029392"
    ],
    "placetype": [
      "aat:300008798"
    ],
    "id": 2655087,
    "name:xx": "Shank Hill"
  }
}
