{
  "geometry": {
    "type": "Point",
    "coordinates": [
      21.0167,
      54.65
    ]
  },
  "type": "Feature",
  "properties": {
    "hierarchy": [
      "tgn:1054250",
      "tgn:1000004",
      "tgn:7011565",
      "tgn:7018214",
      "tgn:7002435",
      "tgn:7029392"
    ],
    "placetype": [
      "aat:300008347"
    ],
    "id": 1054250,
    "name:xx": "Gvardeysk"
  }
}
