{
  "geometry": {
    "type": "Point",
    "coordinates": [
      -85.8667,
      44.7667
    ]
  },
  "type": "Feature",
  "properties": {
    "hierarchy": [
      "tgn:2743500",
      "tgn:1000001",
      "tgn:7012149",
      "tgn:7007520",
      "tgn:7029392"
    ],
    "placetype": [
      "aat:300008798"
    ],
    "id": 2743500,
    "name:xx": "Varney Hill"
  }
}
