{
  "geometry": {
    "type": "Point",
    "coordinates": [
      -71.0667,
      42.8167
    ]
  },
  "type": "Feature",
  "properties": {
    "hierarchy": [
      "tgn:2707384",
      "tgn:1000001",
      "tgn:7014352",
      "tgn:7012149",
      "tgn:7007564",
      "tgn:7029392"
    ],
    "placetype": [
      "aat:300008798"
    ],
    "id": 2707384,
    "name:xx": "Sweet Hill"
  }
}
