{
  "geometry": {
    "type": "Point",
    "coordinates": [
      -111.65,
      41.4833
    ]
  },
  "type": "Feature",
  "properties": {
    "hierarchy": [
      "tgn:2516570",
      "tgn:1000001",
      "tgn:2002103",
      "tgn:7012149",
      "tgn:7007827",
      "tgn:7029392"
    ],
    "placetype": [
      "aat:300008850"
    ],
    "id": 2516570,
    "name:xx": "Mineral Point"
  }
}
