{
  "geometry": {
    "type": "Point",
    "coordinates": [
      -95.75,
      37.1667
    ]
  },
  "type": "Feature",
  "properties": {
    "hierarchy": [
      "tgn:2036085",
      "tgn:1000001",
      "tgn:7012149",
      "tgn:2000722",
      "tgn:7007254",
      "tgn:7029392"
    ],
    "placetype": [
      "aat:300387016"
    ],
    "id": 2036085,
    "name:xx": "Blake"
  }
}
