{
  "geometry": {
    "type": "Point",
    "coordinates": [
      126.0333,
      39.1333
    ]
  },
  "type": "Feature",
  "properties": {
    "hierarchy": [
      "tgn:1082024",
      "tgn:1000004",
      "tgn:1001477",
      "tgn:1000122",
      "tgn:7029392"
    ],
    "placetype": [
      "aat:300008347"
    ],
    "id": 1082024,
    "name:xx": "Kangdong-ŭp"
  }
}
