{
  "geometry": {
    "type": "Point",
    "coordinates": [
      -81.2167,
      34.8833
    ]
  },
  "type": "Feature",
  "properties": {
    "hierarchy": [
      "tgn:2216099",
      "tgn:1000001",
      "tgn:7012149",
      "tgn:2001770",
      "tgn:7007712",
      "tgn:7029392"
    ],
    "placetype": [
      "aat:300006191"
    ],
    "id": 2216099,
    "name:xx": "Cammeron Pond"
  }
}
