{
  "geometry": {
    "type": "Point",
    "coordinates": [
      -122.4667,
      48.6667
    ]
  },
  "type": "Feature",
  "properties": {
    "hierarchy": [
      "tgn:2563982",
      "tgn:1000001",
      "tgn:7012149",
      "tgn:7007920",
      "tgn:7029392"
    ],
    "placetype": [
      "aat:300008706"
    ],
    "id": 2563982,
    "name:xx": "Oyster Creek"
  }
}
