{
  "geometry": {
    "type": "Point",
    "coordinates": [
      -83.65,
      39.9667
    ]
  },
  "type": "Feature",
  "properties": {
    "hierarchy": [
      "tgn:2441046",
      "tgn:1000001",
      "tgn:1002274",
      "tgn:7012149",
      "tgn:7007706",
      "tgn:7029392"
    ],
    "placetype": [
      "aat:300008798"
    ],
    "id": 2441046,
    "name:xx": "Knobs, The"
  }
}
