{
  "geometry": {
    "type": "Point",
    "coordinates": [
      86.3333,
      27.9167
    ]
  },
  "type": "Feature",
  "properties": {
    "hierarchy": [
      "tgn:1104674",
      "tgn:1000004",
      "tgn:7029392"
    ],
    "placetype": [
      "aat:300008795"
    ],
    "id": 1104674,
    "name:xx": "Gauri Sankar"
  }
}
