{
  "type": "FeatureCollection",
  "features": [
    {
      "geometry": {
        "type": "Point",
        "coordinates": [
          -73.7333,
          40.8
        ]
      },
      "type": "Feature",
      "properties": {
        "hierarchy": [
          "tgn:1012793",
          "tgn:1000001",
          "tgn:7012149",
          "tgn:1002708",
          "tgn:7007568",
          "tgn:7029392"
        ],
        "placetype": [
          "aat:300008804"
        ],
        "id": 1012793,
        "name:xx": "Great Neck"
      }
    },
    {
      "geometry": {
        "type": "Point",
        "coordinates": [
          -95,
          76.6667
        ]
      },
      "type": "Feature",
      "properties": {
        "hierarchy": [
          "tgn:1012794",
          "tgn:1006952",
          "tgn:7005685",
          "tgn:1000001",
          "tgn:1010229",
          "tgn:7024197",
          "tgn:7029392"
        ],
        "placetype": [
          "aat:300008804"
        ],
        "id": 1012794,
        "name:xx": "Grinnell Peninsula"
      }
    },
    {
      "geometry": {
        "type": "Point",
        "coordinates": [
          -84.5833,
          21.95
        ]
      },
      "type": "Feature",
      "properties": {
        "hierarchy": [
          "tgn:1012795",
          "tgn:1001488",
          "tgn:1000001",
          "tgn:7004624",
          "tgn:7029392"
        ],
        "placetype": [
          "aat:300008804"
        ],
        "id": 1012795,
        "name:xx": "Guanahacabibes, Península de"
      }
    },
    {
      "geometry": {
        "type": "Point",
        "coordinates": [
          -148,
          -76.3
        ]
      },
      "type": "Feature",
      "properties": {
        "hierarchy": [
          "tgn:1012796",
          "tgn:1000007",
          "tgn:7029392"
        ],
        "placetype": [
          "aat:300008804"
        ],
        "id": 1012796,
        "name:xx": "Guest Peninsula"
      }
    },
    {
      "geometry": {
        "type": "Point",
        "coordinates": [
          79,
          70.8333
        ]
      },
      "type": "Feature",
      "properties": {
        "hierarchy": [
          "tgn:1012797",
          "tgn:1000004",
          "tgn:7013571",
          "tgn:7018214",
          "tgn:7002435",
          "tgn:7029392"
        ],
        "placetype": [
          "aat:300008804"
        ],
        "id": 1012797,
        "name:xx": "Gydanskiy poluostrov"
      }
    },
    {
      "geometry": {
        "type": "Point",
        "coordinates": [
          -66,
          63.5
        ]
      },
      "type": "Feature",
      "properties": {
        "hierarchy": [
          "tgn:1012798",
          "tgn:7013003",
          "tgn:7005685",
          "tgn:1000001",
          "tgn:7024197",
          "tgn:7029392"
        ],
        "placetype": [
          "aat:300008804"
        ],
        "id": 1012798,
        "name:xx": "Hall Peninsula"
      }
    },
    {
      "geometry": {
        "type": "Point",
        "coordinates": [
          8.8167,
          54.6
        ]
      },
      "type": "Feature",
      "properties": {
        "hierarchy": [
          "tgn:1012799",
          "tgn:1000003",
          "tgn:7003688",
          "tgn:7000084",
          "tgn:7029392"
        ],
        "placetype": [
          "aat:300008804"
        ],
        "id": 1012799,
        "name:xx": "Hamburger Hallig"
      }
    }
  ]
}
