{
  "geometry": {
    "type": "Point",
    "coordinates": [
      -78.1167,
      37.65
    ]
  },
  "type": "Feature",
  "properties": {
    "hierarchy": [
      "tgn:2373556",
      "tgn:1000001",
      "tgn:7012149",
      "tgn:2002156",
      "tgn:7007919",
      "tgn:7029392"
    ],
    "placetype": [
      "aat:300008347"
    ],
    "id": 2373556,
    "name:xx": "Hamilton"
  }
}
