{
  "geometry": {
    "type": "Point",
    "coordinates": [
      3.4667,
      46.8333
    ]
  },
  "type": "Feature",
  "properties": {
    "hierarchy": [
      "tgn:1032912",
      "tgn:1000003",
      "tgn:7002875",
      "tgn:1000070",
      "tgn:7029392"
    ],
    "placetype": [
      "aat:300008347"
    ],
    "id": 1032912,
    "name:xx": "Decize"
  }
}
