{
  "geometry": {
    "type": "Point",
    "coordinates": [
      -89.7167,
      44.35
    ]
  },
  "type": "Feature",
  "properties": {
    "hierarchy": [
      "tgn:2121504",
      "tgn:1000001",
      "tgn:7012149",
      "tgn:2002347",
      "tgn:7007922",
      "tgn:7029392"
    ],
    "placetype": [
      "aat:300008347"
    ],
    "id": 2121504,
    "name:xx": "Kellner"
  }
}
