{
  "geometry": {
    "type": "Point",
    "coordinates": [
      7.3333,
      43.8333
    ]
  },
  "type": "Feature",
  "properties": {
    "hierarchy": [
      "tgn:1032121",
      "tgn:1000003",
      "tgn:1000070",
      "tgn:7002895",
      "tgn:7029392"
    ],
    "placetype": [
      "aat:300008347"
    ],
    "id": 1032121,
    "name:xx": "Berre-des-Alpes"
  }
}
