{
  "geometry": {
    "type": "Point",
    "coordinates": [
      -83.05,
      35.7833
    ]
  },
  "type": "Feature",
  "properties": {
    "hierarchy": [
      "tgn:2321949",
      "tgn:1000001",
      "tgn:7012149",
      "tgn:2001851",
      "tgn:7007825",
      "tgn:7029392"
    ],
    "placetype": [
      "aat:300008699"
    ],
    "id": 2321949,
    "name:xx": "Fall Branch"
  }
}
