{
  "geometry": {
    "type": "Point",
    "coordinates": [
      -95.0167,
      30.6167
    ]
  },
  "type": "Feature",
  "properties": {
    "hierarchy": [
      "tgn:2463190",
      "tgn:1000001",
      "tgn:7012149",
      "tgn:7007826",
      "tgn:7029392"
    ],
    "placetype": [
      "aat:300006191"
    ],
    "id": 2463190,
    "name:xx": "Livingston, Lake"
  }
}
