{
  "geometry": {
    "type": "Point",
    "coordinates": [
      -4.4333,
      5.2333
    ]
  },
  "type": "Feature",
  "properties": {
    "hierarchy": [
      "tgn:1114699",
      "tgn:1000484",
      "tgn:7001242",
      "tgn:1000168",
      "tgn:7029392"
    ],
    "placetype": [
      "aat:300008679"
    ],
    "id": 1114699,
    "name:xx": "Ébrié, Lagune"
  }
}
