{
  "geometry": {
    "type": "Point",
    "coordinates": [
      -81.1667,
      34.1833
    ]
  },
  "type": "Feature",
  "properties": {
    "hierarchy": [
      "tgn:2096559",
      "tgn:1000001",
      "tgn:2001744",
      "tgn:7012149",
      "tgn:7007712",
      "tgn:7029392"
    ],
    "placetype": [
      "aat:300008347",
      "aat:300387210"
    ],
    "id": 2096559,
    "name:xx": "Richtex"
  }
}
