{
  "geometry": {
    "type": "Point",
    "coordinates": [
      -95.45,
      29.1833
    ]
  },
  "type": "Feature",
  "properties": {
    "hierarchy": [
      "tgn:1002198",
      "tgn:1000001",
      "tgn:7012149",
      "tgn:7007826",
      "tgn:7029392"
    ],
    "placetype": [
      "aat:300387145",
      "aat:300000771"
    ],
    "id": 1002198,
    "name:xx": "Brazoria"
  }
}
