{
  "geometry": {
    "type": "Point",
    "coordinates": [
      -93.3167,
      44.4667
    ]
  },
  "type": "Feature",
  "properties": {
    "hierarchy": [
      "tgn:2054875",
      "tgn:1000001",
      "tgn:7012149",
      "tgn:2001064",
      "tgn:7007521",
      "tgn:7029392"
    ],
    "placetype": [
      "aat:300008347",
      "aat:300387210"
    ],
    "id": 2054875,
    "name:xx": "Little Chicago"
  }
}
