{
  "geometry": {
    "type": "Point",
    "coordinates": [
      -71.35,
      -34.633333
    ]
  },
  "type": "Feature",
  "properties": {
    "hierarchy": [
      "tgn:7281303",
      "tgn:1001695",
      "tgn:1000049",
      "tgn:1000002",
      "tgn:7029392"
    ],
    "placetype": [
      "aat:300007783"
    ],
    "id": 7281303,
    "name:xx": "Estación Santa Cruz"
  }
}
