{
  "geometry": {
    "type": "Point",
    "coordinates": [
      30.25,
      30.666667
    ]
  },
  "type": "Feature",
  "properties": {
    "hierarchy": [
      "tgn:7537249",
      "tgn:7001242",
      "tgn:1001075",
      "tgn:7016833",
      "tgn:7029392"
    ],
    "placetype": [
      "aat:300008777"
    ],
    "name:en": "Shāmikh, Tallāt",
    "id": 7537249
  }
}
