{
  "geometry": {
    "type": "Point",
    "coordinates": [
      19.6833,
      49.8667
    ]
  },
  "type": "Feature",
  "properties": {
    "hierarchy": [
      "tgn:7007683",
      "tgn:1000003",
      "tgn:7024127",
      "tgn:7006366",
      "tgn:7029392"
    ],
    "placetype": [
      "aat:300008347"
    ],
    "id": 7007683,
    "name:xx": "Kalwaria Zebrzydowska"
  }
}
