{
  "geometry": {
    "type": "Point",
    "coordinates": [
      -91.75,
      38.4833
    ]
  },
  "type": "Feature",
  "properties": {
    "hierarchy": [
      "tgn:2547064",
      "tgn:1000001",
      "tgn:7012149",
      "tgn:1002755",
      "tgn:7007523",
      "tgn:7029392"
    ],
    "placetype": [
      "aat:300008706"
    ],
    "id": 2547064,
    "name:xx": "North Fork Pointers Creek"
  }
}
