{
  "geometry": {
    "type": "Point",
    "coordinates": [
      -114.4333,
      36.1833
    ]
  },
  "type": "Feature",
  "properties": {
    "hierarchy": [
      "tgn:2516695",
      "tgn:1000001",
      "tgn:2001410",
      "tgn:7012149",
      "tgn:7007526",
      "tgn:7029392"
    ],
    "placetype": [
      "aat:300132316"
    ],
    "id": 2516695,
    "name:xx": "Miners Cove"
  }
}
