{
  "geometry": {
    "type": "Point",
    "coordinates": [
      -84.1667,
      30.0833
    ]
  },
  "type": "Feature",
  "properties": {
    "hierarchy": [
      "tgn:2574401",
      "tgn:1000001",
      "tgn:7012149",
      "tgn:2000289",
      "tgn:7007240",
      "tgn:7029392"
    ],
    "placetype": [
      "aat:300008850"
    ],
    "id": 2574401,
    "name:xx": "Pelican Point"
  }
}
