{
  "geometry": {
    "type": "Point",
    "coordinates": [
      -85.7667,
      45.4667
    ]
  },
  "type": "Feature",
  "properties": {
    "hierarchy": [
      "tgn:2547883",
      "tgn:1000001",
      "tgn:7012149",
      "tgn:2000971",
      "tgn:7007520",
      "tgn:7029392"
    ],
    "placetype": [
      "aat:300008791"
    ],
    "id": 2547883,
    "name:xx": "North Fox Island"
  }
}
