{
  "geometry": {
    "type": "Point",
    "coordinates": [
      -83.85,
      38.8333
    ]
  },
  "type": "Feature",
  "properties": {
    "hierarchy": [
      "tgn:2391492",
      "tgn:1000001",
      "tgn:1002210",
      "tgn:7012149",
      "tgn:7007706",
      "tgn:7029392"
    ],
    "placetype": [
      "aat:300266640"
    ],
    "id": 2391492,
    "name:xx": "Hillman Ridge"
  }
}
