{
  "geometry": {
    "type": "Point",
    "coordinates": [
      -101.1333,
      37.35
    ]
  },
  "type": "Feature",
  "properties": {
    "hierarchy": [
      "tgn:2036163",
      "tgn:1000001",
      "tgn:7012149",
      "tgn:2000754",
      "tgn:7007254",
      "tgn:7029392"
    ],
    "placetype": [
      "aat:300008347",
      "aat:300387210"
    ],
    "id": 2036163,
    "name:xx": "Cave"
  }
}
