{
  "geometry": {
    "type": "Point",
    "coordinates": [
      -78.0833,
      43.25
    ]
  },
  "type": "Feature",
  "properties": {
    "hierarchy": [
      "tgn:2068214",
      "tgn:1000001",
      "tgn:7012149",
      "tgn:1002752",
      "tgn:7007568",
      "tgn:7029392"
    ],
    "placetype": [
      "aat:300008347"
    ],
    "id": 2068214,
    "name:xx": "Brockville"
  }
}
