{
  "geometry": {
    "type": "Point",
    "coordinates": [
      32.4167,
      51.1167
    ]
  },
  "type": "Feature",
  "properties": {
    "hierarchy": [
      "tgn:1058448",
      "tgn:7012002",
      "tgn:1000003",
      "tgn:7006660",
      "tgn:7029392"
    ],
    "placetype": [
      "aat:300008347"
    ],
    "id": 1058448,
    "name:xx": "Pliski"
  }
}
