{
  "geometry": {
    "type": "Point",
    "coordinates": [
      -111.6667,
      35.3333
    ]
  },
  "type": "Feature",
  "properties": {
    "hierarchy": [
      "tgn:2156099",
      "tgn:1000001",
      "tgn:7006451",
      "tgn:2000092",
      "tgn:7012149",
      "tgn:7029392"
    ],
    "placetype": [
      "aat:300008761"
    ],
    "id": 2156099,
    "name:xx": "Beard Canyon"
  }
}
