{
  "geometry": {
    "type": "Point",
    "coordinates": [
      -85.9667,
      35.2167
    ]
  },
  "type": "Feature",
  "properties": {
    "hierarchy": [
      "tgn:2481876",
      "tgn:1000001",
      "tgn:7012149",
      "tgn:2001852",
      "tgn:7007825",
      "tgn:7029392"
    ],
    "placetype": [
      "aat:300266640"
    ],
    "id": 2481876,
    "name:xx": "Lands End Ridge"
  }
}
