{
  "geometry": {
    "type": "Point",
    "coordinates": [
      13.05,
      51.916667
    ]
  },
  "type": "Feature",
  "properties": {
    "hierarchy": [
      "tgn:7151448",
      "tgn:7000096",
      "tgn:1000003",
      "tgn:7000084",
      "tgn:7029392"
    ],
    "placetype": [
      "aat:300055621"
    ],
    "id": 7151448,
    "name:xx": "Wüste Mark Kähnsdorf"
  }
}
