{
  "geometry": {
    "type": "Point",
    "coordinates": [
      -84.4167,
      35.35
    ]
  },
  "type": "Feature",
  "properties": {
    "hierarchy": [
      "tgn:2504580",
      "tgn:1000001",
      "tgn:7012149",
      "tgn:7022542",
      "tgn:7007825",
      "tgn:7029392"
    ],
    "placetype": [
      "aat:300008347"
    ],
    "id": 2504580,
    "name:xx": "Mecca"
  }
}
