{
  "type": "FeatureCollection",
  "features": [
    {
      "geometry": {
        "type": "Point",
        "coordinates": [
          -114.9,
          39.0667
        ]
      },
      "type": "Feature",
      "properties": {
        "hierarchy": [
          "tgn:2373510",
          "tgn:1000001",
          "tgn:7012149",
          "tgn:2001420",
          "tgn:7007526",
          "tgn:7029392"
        ],
        "placetype": [
          "aat:300008798"
        ],
        "id": 2373510,
        "name:xx": "Hamels Peak"
      }
    },
    {
      "geometry": {
        "type": "Point",
        "coordinates": [
          -121.3333,
          42.7833
        ]
      },
      "type": "Feature",
      "properties": {
        "hierarchy": [
          "tgn:2373511",
          "tgn:1000001",
          "tgn:7012149",
          "tgn:7007708",
          "tgn:7029392"
        ],
        "placetype": [
          "aat:300008798"
        ],
        "id": 2373511,
        "name:xx": "Hamelton Butte"
      }
    },
    {
      "geometry": {
        "type": "Point",
        "coordinates": [
          -110.7,
          46.3
        ]
      },
      "type": "Feature",
      "properties": {
        "hierarchy": [
          "tgn:2373512",
          "tgn:1000001",
          "tgn:7012149",
          "tgn:2001289",
          "tgn:7007524",
          "tgn:7029392"
        ],
        "placetype": [
          "aat:300008347"
        ],
        "id": 2373512,
        "name:xx": "Hamen"
      }
    },
    {
      "geometry": {
        "type": "Point",
        "coordinates": [
          -110.7,
          46.3
        ]
      },
      "type": "Feature",
      "properties": {
        "hierarchy": [
          "tgn:2373513",
          "tgn:1000001",
          "tgn:7012149",
          "tgn:2001289",
          "tgn:7007524",
          "tgn:7029392"
        ],
        "placetype": [
          "aat:300006191"
        ],
        "id": 2373513,
        "name:xx": "Hamen Reservoir"
      }
    },
    {
      "geometry": {
        "type": "Point",
        "coordinates": [
          -81.2,
          32.0833
        ]
      },
      "type": "Feature",
      "properties": {
        "hierarchy": [
          "tgn:2373514",
          "tgn:1000001",
          "tgn:2000316",
          "tgn:7012149",
          "tgn:7007248",
          "tgn:7029392"
        ],
        "placetype": [
          "aat:300008347"
        ],
        "id": 2373514,
        "name:xx": "Hamer"
      }
    },
    {
      "geometry": {
        "type": "Point",
        "coordinates": [
          -84.4,
          41.6167
        ]
      },
      "type": "Feature",
      "properties": {
        "hierarchy": [
          "tgn:2373515",
          "tgn:1000001",
          "tgn:7012149",
          "tgn:1003025",
          "tgn:7007706",
          "tgn:7029392"
        ],
        "placetype": [
          "aat:300008347"
        ],
        "id": 2373515,
        "name:xx": "Hamer"
      }
    },
    {
      "geometry": {
        "type": "Point",
        "coordinates": [
          -90.8,
          32.2333
        ]
      },
      "type": "Feature",
      "properties": {
        "hierarchy": [
          "tgn:2373516",
          "tgn:1000001",
          "tgn:7012149",
          "tgn:2001160",
          "tgn:7007522",
          "tgn:7029392"
        ],
        "placetype": [
          "aat:300008699"
        ],
        "id": 2373516,
        "name:xx": "Hamer Bayou"
      }
    },
    {
      "geometry": {
        "type": "Point",
        "coordinates": [
          -79.7167,
          35.1667
        ]
      },
      "type": "Feature",
      "properties": {
        "hierarchy": [
          "tgn:2373517",
          "tgn:1000001",
          "tgn:7012149",
          "tgn:2001533",
          "tgn:7007709",
          "tgn:7029392"
        ],
        "placetype": [
          "aat:300008699"
        ],
        "id": 2373517,
        "name:xx": "Hamer Branch"
      }
    },
    {
      "geometry": {
        "type": "Point",
        "coordinates": [
          -60.9667,
          38.7333
        ]
      },
      "type": "Feature",
      "properties": {
        "hierarchy": [
          "tgn:2373518",
          "tgn:1000001",
          "tgn:7012149",
          "tgn:1002579",
          "tgn:7007252",
          "tgn:7029392"
        ],
        "placetype": [
          "aat:300008746"
        ],
        "id": 2373518,
        "name:xx": "Hamer Cave"
      }
    },
    {
      "geometry": {
        "type": "Point",
        "coordinates": [
          -79.9833,
          35.2167
        ]
      },
      "type": "Feature",
      "properties": {
        "hierarchy": [
          "tgn:2373519",
          "tgn:1000001",
          "tgn:7012149",
          "tgn:7007709",
          "tgn:7029392"
        ],
        "placetype": [
          "aat:300008706"
        ],
        "id": 2373519,
        "name:xx": "Hamer Creek"
      }
    }
  ]
}
