{
  "type": "FeatureCollection",
  "features": [
    {
      "geometry": {
        "type": "Point",
        "coordinates": [
          -95.1167,
          38.3667
        ]
      },
      "type": "Feature",
      "properties": {
        "hierarchy": [
          "tgn:2036440",
          "tgn:2000661",
          "tgn:1000001",
          "tgn:7012149",
          "tgn:7007254",
          "tgn:7029392"
        ],
        "placetype": [
          "aat:300008347"
        ],
        "id": 2036440,
        "name:xx": "Greeley"
      }
    },
    {
      "geometry": {
        "type": "Point",
        "coordinates": [
          -97,
          39.4167
        ]
      },
      "type": "Feature",
      "properties": {
        "hierarchy": [
          "tgn:2036441",
          "tgn:1000001",
          "tgn:2000673",
          "tgn:7012149",
          "tgn:7007254",
          "tgn:7029392"
        ],
        "placetype": [
          "aat:300008347"
        ],
        "id": 2036441,
        "name:xx": "Green"
      }
    },
    {
      "geometry": {
        "type": "Point",
        "coordinates": [
          -94.9833,
          37.5
        ]
      },
      "type": "Feature",
      "properties": {
        "hierarchy": [
          "tgn:2036442",
          "tgn:1000001",
          "tgn:2000678",
          "tgn:7012149",
          "tgn:7007254",
          "tgn:7029392"
        ],
        "placetype": [
          "aat:300008347",
          "aat:300387210"
        ],
        "id": 2036442,
        "name:xx": "Greenbush"
      }
    },
    {
      "geometry": {
        "type": "Point",
        "coordinates": [
          -96.9667,
          39.7167
        ]
      },
      "type": "Feature",
      "properties": {
        "hierarchy": [
          "tgn:2036443",
          "tgn:1000001",
          "tgn:7012149",
          "tgn:2000760",
          "tgn:7007254",
          "tgn:7029392"
        ],
        "placetype": [
          "aat:300008347"
        ],
        "id": 2036443,
        "name:xx": "Greenleaf"
      }
    },
    {
      "geometry": {
        "type": "Point",
        "coordinates": [
          -99.2833,
          37.6
        ]
      },
      "type": "Feature",
      "properties": {
        "hierarchy": [
          "tgn:2036444",
          "tgn:1000001",
          "tgn:7012149",
          "tgn:2000708",
          "tgn:7007254",
          "tgn:7029392"
        ],
        "placetype": [
          "aat:300008347"
        ],
        "id": 2036444,
        "name:xx": "Greensburg"
      }
    },
    {
      "geometry": {
        "type": "Point",
        "coordinates": [
          -97.2,
          37.7667
        ]
      },
      "type": "Feature",
      "properties": {
        "hierarchy": [
          "tgn:2036445",
          "tgn:1000001",
          "tgn:7012149",
          "tgn:2000746",
          "tgn:7007254",
          "tgn:7029392"
        ],
        "placetype": [
          "aat:300008347"
        ],
        "id": 2036445,
        "name:xx": "Greenwich"
      }
    },
    {
      "geometry": {
        "type": "Point",
        "coordinates": [
          -97.2,
          37.65
        ]
      },
      "type": "Feature",
      "properties": {
        "hierarchy": [
          "tgn:2036446",
          "tgn:1000001",
          "tgn:7012149",
          "tgn:2000746",
          "tgn:7007254",
          "tgn:7029392"
        ],
        "placetype": [
          "aat:300008347"
        ],
        "id": 2036446,
        "name:xx": "Greenwich Heights"
      }
    },
    {
      "geometry": {
        "type": "Point",
        "coordinates": [
          -96.45,
          37.3333
        ]
      },
      "type": "Feature",
      "properties": {
        "hierarchy": [
          "tgn:2036447",
          "tgn:1000001",
          "tgn:2000684",
          "tgn:7012149",
          "tgn:7007254",
          "tgn:7029392"
        ],
        "placetype": [
          "aat:300008347"
        ],
        "id": 2036447,
        "name:xx": "Grenola"
      }
    },
    {
      "geometry": {
        "type": "Point",
        "coordinates": [
          -99.2,
          39.75
        ]
      },
      "type": "Feature",
      "properties": {
        "hierarchy": [
          "tgn:2036448",
          "tgn:1000001",
          "tgn:7012149",
          "tgn:2000733",
          "tgn:7007254",
          "tgn:7029392"
        ],
        "placetype": [
          "aat:300008347",
          "aat:300387210"
        ],
        "id": 2036448,
        "name:xx": "Gretna"
      }
    },
    {
      "geometry": {
        "type": "Point",
        "coordinates": [
          -95.8833,
          38.0833
        ]
      },
      "type": "Feature",
      "properties": {
        "hierarchy": [
          "tgn:2036449",
          "tgn:1000001",
          "tgn:2000675",
          "tgn:7012149",
          "tgn:7007254",
          "tgn:7029392"
        ],
        "placetype": [
          "aat:300008347"
        ],
        "id": 2036449,
        "name:xx": "Gridley"
      }
    }
  ]
}
