{
  "geometry": {
    "type": "Point",
    "coordinates": [
      -86.2833,
      46.25
    ]
  },
  "type": "Feature",
  "properties": {
    "hierarchy": [
      "tgn:2651306",
      "tgn:1000001",
      "tgn:7012149",
      "tgn:2000996",
      "tgn:7007520",
      "tgn:7029392"
    ],
    "placetype": [
      "aat:300008706"
    ],
    "id": 2651306,
    "name:xx": "Section Nineteen Creek"
  }
}
