{
  "geometry": {
    "type": "Point",
    "coordinates": [
      -81.3833,
      38.55
    ]
  },
  "type": "Feature",
  "properties": {
    "hierarchy": [
      "tgn:2217589",
      "tgn:1000001",
      "tgn:7012149",
      "tgn:2002293",
      "tgn:7013961",
      "tgn:7029392"
    ],
    "placetype": [
      "aat:300008798"
    ],
    "id": 2217589,
    "name:xx": "Campbell Hill"
  }
}
