{
  "type": "FeatureCollection",
  "features": [
    {
      "geometry": {
        "type": "Point",
        "coordinates": [
          7.616667,
          51.15
        ]
      },
      "type": "Feature",
      "properties": {
        "hierarchy": [
          "tgn:7090880",
          "tgn:1000003",
          "tgn:7003677",
          "tgn:7000084",
          "tgn:7029392"
        ],
        "placetype": [
          "aat:300000206"
        ],
        "id": 7090880,
        "name:xx": "Vorth"
      }
    },
    {
      "geometry": {
        "type": "Point",
        "coordinates": [
          9.787222,
          49.263333
        ]
      },
      "type": "Feature",
      "properties": {
        "hierarchy": [
          "tgn:7090881",
          "tgn:7003692",
          "tgn:1000003",
          "tgn:7000084",
          "tgn:7029392"
        ],
        "placetype": [
          "aat:300008347"
        ],
        "id": 7090881,
        "name:xx": "Vogelsberg"
      }
    },
    {
      "geometry": {
        "type": "Point",
        "coordinates": [
          7.916667,
          51.283333
        ]
      },
      "type": "Feature",
      "properties": {
        "hierarchy": [
          "tgn:7090883",
          "tgn:1000003",
          "tgn:7003677",
          "tgn:7000084",
          "tgn:7029392"
        ],
        "placetype": [
          "aat:300008777"
        ],
        "id": 7090883,
        "name:xx": "Vogels-Berg"
      }
    },
    {
      "geometry": {
        "type": "Point",
        "coordinates": [
          6.1,
          51.216667
        ]
      },
      "type": "Feature",
      "properties": {
        "hierarchy": [
          "tgn:7090884",
          "tgn:1000003",
          "tgn:7003677",
          "tgn:7000084",
          "tgn:7029392"
        ],
        "placetype": [
          "aat:300008777"
        ],
        "id": 7090884,
        "name:xx": "Vogels Berg"
      }
    },
    {
      "geometry": {
        "type": "Point",
        "coordinates": [
          9.766667,
          50.983333
        ]
      },
      "type": "Feature",
      "properties": {
        "hierarchy": [
          "tgn:7090885",
          "tgn:1000003",
          "tgn:7003678",
          "tgn:7000084",
          "tgn:7029392"
        ],
        "placetype": [
          "aat:300008777"
        ],
        "id": 7090885,
        "name:xx": "Vogels-Berg"
      }
    },
    {
      "geometry": {
        "type": "Point",
        "coordinates": [
          10.366667,
          50.766667
        ]
      },
      "type": "Feature",
      "properties": {
        "hierarchy": [
          "tgn:7090886",
          "tgn:1000003",
          "tgn:7003689",
          "tgn:7000084",
          "tgn:7029392"
        ],
        "placetype": [
          "aat:300008777"
        ],
        "id": 7090886,
        "name:xx": "Vogels-Berg"
      }
    },
    {
      "geometry": {
        "type": "Point",
        "coordinates": [
          7.25,
          49.65
        ]
      },
      "type": "Feature",
      "properties": {
        "hierarchy": [
          "tgn:7090888",
          "tgn:1000003",
          "tgn:7003682",
          "tgn:7000084",
          "tgn:7029392"
        ],
        "placetype": [
          "aat:300008777"
        ],
        "id": 7090888,
        "name:xx": "Vogels-Berg"
      }
    },
    {
      "geometry": {
        "type": "Point",
        "coordinates": [
          7.8,
          51.333333
        ]
      },
      "type": "Feature",
      "properties": {
        "hierarchy": [
          "tgn:7090889",
          "tgn:1000003",
          "tgn:7003677",
          "tgn:7000084",
          "tgn:7029392"
        ],
        "placetype": [
          "aat:300000206"
        ],
        "id": 7090889,
        "name:xx": "Vogelsberg"
      }
    }
  ]
}
