{
  "geometry": {
    "type": "Point",
    "coordinates": [
      -85.45,
      44.8167
    ]
  },
  "type": "Feature",
  "properties": {
    "hierarchy": [
      "tgn:2053797",
      "tgn:1000001",
      "tgn:7012149",
      "tgn:2000961",
      "tgn:7007520",
      "tgn:7029392"
    ],
    "placetype": [
      "aat:300008347",
      "aat:300387210"
    ],
    "id": 2053797,
    "name:xx": "Yuba"
  }
}
