{
  "geometry": {
    "type": "Point",
    "coordinates": [
      -117.7833,
      40.9833
    ]
  },
  "type": "Feature",
  "properties": {
    "hierarchy": [
      "tgn:2738923",
      "tgn:1000001",
      "tgn:2001414",
      "tgn:7012149",
      "tgn:7007526",
      "tgn:7029392"
    ],
    "placetype": [
      "aat:300000390"
    ],
    "id": 2738923,
    "name:xx": "Union Series Mine"
  }
}
