{
  "geometry": {
    "type": "Point",
    "coordinates": [
      -92.3833,
      40.2167
    ]
  },
  "type": "Feature",
  "properties": {
    "hierarchy": [
      "tgn:2393433",
      "tgn:1002133",
      "tgn:1000001",
      "tgn:7012149",
      "tgn:7007523",
      "tgn:7029392"
    ],
    "placetype": [
      "aat:300008699"
    ],
    "id": 2393433,
    "name:xx": "Hog Branch"
  }
}
