{
  "geometry": {
    "type": "Point",
    "coordinates": [
      117.5167,
      24.5667
    ]
  },
  "type": "Feature",
  "properties": {
    "hierarchy": [
      "tgn:1069296",
      "tgn:1000004",
      "tgn:7001796",
      "tgn:1000111",
      "tgn:7029392"
    ],
    "placetype": [
      "aat:300008347"
    ],
    "id": 1069296,
    "name:xx": "Jingcheng"
  }
}
