{
  "geometry": {
    "type": "Point",
    "coordinates": [
      -83.45,
      37.9833
    ]
  },
  "type": "Feature",
  "properties": {
    "hierarchy": [
      "tgn:2605412",
      "tgn:1000001",
      "tgn:7012149",
      "tgn:2000831",
      "tgn:7007255",
      "tgn:7029392"
    ],
    "placetype": [
      "aat:300008699"
    ],
    "id": 2605412,
    "name:xx": "Ragstand Branch"
  }
}
