{
  "geometry": {
    "type": "Point",
    "coordinates": [
      79.506013,
      30.075651
    ]
  },
  "type": "Feature",
  "properties": {
    "hierarchy": [
      "tgn:7580208",
      "tgn:1000004",
      "tgn:7000198",
      "tgn:7031786",
      "tgn:7029392"
    ],
    "placetype": [
      "aat:300008347"
    ],
    "name:en": "Tharāli",
    "id": 7580208
  }
}
