{
  "geometry": {
    "type": "Point",
    "coordinates": [
      10.6667,
      4.35
    ]
  },
  "type": "Feature",
  "properties": {
    "hierarchy": [
      "tgn:1088256",
      "tgn:1001394",
      "tgn:7001242",
      "tgn:1000153",
      "tgn:7029392"
    ],
    "placetype": [
      "aat:300008347"
    ],
    "id": 1088256,
    "name:xx": "Ngambé"
  }
}
