{
  "geometry": {
    "type": "Point",
    "coordinates": [
      -113.1167,
      38.5333
    ]
  },
  "type": "Feature",
  "properties": {
    "hierarchy": [
      "tgn:2177473",
      "tgn:2002101",
      "tgn:1000001",
      "tgn:7012149",
      "tgn:7007827",
      "tgn:7029392"
    ],
    "placetype": [
      "aat:300000390"
    ],
    "id": 2177473,
    "name:xx": "Black Rock Mine"
  }
}
