{
  "geometry": {
    "type": "Point",
    "coordinates": [
      -110.4333,
      43.6333
    ]
  },
  "type": "Feature",
  "properties": {
    "hierarchy": [
      "tgn:2402155",
      "tgn:1000001",
      "tgn:7012149",
      "tgn:2002384",
      "tgn:7007923",
      "tgn:7029392"
    ],
    "placetype": [
      "aat:300008706"
    ],
    "id": 2402155,
    "name:xx": "Horsetail Creek"
  }
}
