{
  "geometry": {
    "type": "Point",
    "coordinates": [
      -116.2167,
      44.3167
    ]
  },
  "type": "Feature",
  "properties": {
    "hierarchy": [
      "tgn:2654634",
      "tgn:1000001",
      "tgn:7012149",
      "tgn:2000474",
      "tgn:7007250",
      "tgn:7029392"
    ],
    "placetype": [
      "aat:300008761"
    ],
    "id": 2654634,
    "name:xx": "Shake Gulch"
  }
}
