{
  "geometry": {
    "type": "Point",
    "coordinates": [
      -97.4833,
      30.1333
    ]
  },
  "type": "Feature",
  "properties": {
    "hierarchy": [
      "tgn:2365166",
      "tgn:1000001",
      "tgn:1002168",
      "tgn:7012149",
      "tgn:7007826",
      "tgn:7029392"
    ],
    "placetype": [
      "aat:300008706"
    ],
    "id": 2365166,
    "name:xx": "Greens Creek"
  }
}
