{
  "type": "FeatureCollection",
  "features": [
    {
      "geometry": {
        "type": "Point",
        "coordinates": [
          30.491743,
          29.445763
        ]
      },
      "type": "Feature",
      "properties": {
        "hierarchy": [
          "tgn:7520250",
          "tgn:7001242",
          "tgn:7001105",
          "tgn:7016833",
          "tgn:7029392"
        ],
        "placetype": [
          "aat:300386846"
        ],
        "name:en": "'Abd al 'Āl, Khashm",
        "id": 7520250
      }
    },
    {
      "geometry": {
        "type": "Point",
        "coordinates": [
          31.901264,
          31.470468
        ]
      },
      "type": "Feature",
      "properties": {
        "hierarchy": [
          "tgn:7520251",
          "tgn:7001242",
          "tgn:7016833",
          "tgn:1001080",
          "tgn:7029392"
        ],
        "placetype": [
          "aat:300008713"
        ],
        "name:en": "'Abd ad Dā'im, Ḩalq",
        "id": 7520251
      }
    },
    {
      "geometry": {
        "type": "Point",
        "coordinates": [
          31.618359,
          29.083067
        ]
      },
      "type": "Feature",
      "properties": {
        "hierarchy": [
          "tgn:7520253",
          "tgn:7001242",
          "tgn:7016833",
          "tgn:7029392"
        ],
        "placetype": [
          "aat:300379998"
        ],
        "name:en": "'Abd, Wâdi el",
        "id": 7520253
      }
    },
    {
      "geometry": {
        "type": "Point",
        "coordinates": [
          30.8893,
          24.623115
        ]
      },
      "type": "Feature",
      "properties": {
        "hierarchy": [
          "tgn:7520254",
          "tgn:7001242",
          "tgn:7016833",
          "tgn:7001334",
          "tgn:7029392"
        ],
        "placetype": [
          "aat:300379998"
        ],
        "name:en": "'Abd, Wādī al",
        "id": 7520254
      }
    },
    {
      "geometry": {
        "type": "Point",
        "coordinates": [
          33.94308,
          26.929119
        ]
      },
      "type": "Feature",
      "properties": {
        "hierarchy": [
          "tgn:7520255",
          "tgn:7001242",
          "tgn:7001311",
          "tgn:7016833",
          "tgn:7029392"
        ],
        "placetype": [
          "aat:300386968"
        ],
        "name:en": "Sharm al 'Abd",
        "id": 7520255
      }
    },
    {
      "geometry": {
        "type": "Point",
        "coordinates": [
          32.783333,
          23.783333
        ]
      },
      "type": "Feature",
      "properties": {
        "hierarchy": [
          "tgn:7520256",
          "tgn:7001242",
          "tgn:7016833",
          "tgn:7000122",
          "tgn:7029392"
        ],
        "placetype": [
          "aat:300008795"
        ],
        "name:en": "'Abd, Ras el",
        "id": 7520256
      }
    },
    {
      "geometry": {
        "type": "Point",
        "coordinates": [
          29.870552,
          30.232237
        ]
      },
      "type": "Feature",
      "properties": {
        "hierarchy": [
          "tgn:7520258",
          "tgn:7001242",
          "tgn:1001075",
          "tgn:7016833",
          "tgn:7029392"
        ],
        "placetype": [
          "aat:300008777"
        ],
        "name:en": "'Abd, Quwayrāt al",
        "id": 7520258
      }
    },
    {
      "geometry": {
        "type": "Point",
        "coordinates": [
          28.758679,
          30.619974
        ]
      },
      "type": "Feature",
      "properties": {
        "hierarchy": [
          "tgn:7520259",
          "tgn:7001242",
          "tgn:7016833",
          "tgn:1001418",
          "tgn:7029392"
        ],
        "placetype": [
          "aat:300008777"
        ],
        "name:en": "'Abd, Qārat al",
        "id": 7520259
      }
    }
  ]
}
