{
  "geometry": {
    "type": "Point",
    "coordinates": [
      -82.7333,
      41.5167
    ]
  },
  "type": "Feature",
  "properties": {
    "hierarchy": [
      "tgn:2492007",
      "tgn:1000001",
      "tgn:7012149",
      "tgn:1002761",
      "tgn:7007706",
      "tgn:7029392"
    ],
    "placetype": [
      "aat:300000390"
    ],
    "id": 2492007,
    "name:xx": "Marblehead Quarry"
  }
}
