{
  "geometry": {
    "type": "Point",
    "coordinates": [
      -121.25,
      48.9333
    ]
  },
  "type": "Feature",
  "properties": {
    "hierarchy": [
      "tgn:2617933",
      "tgn:1000001",
      "tgn:7012149",
      "tgn:1003020",
      "tgn:7007920",
      "tgn:7029392"
    ],
    "placetype": [
      "aat:300266640"
    ],
    "id": 2617933,
    "name:xx": "Ridge of Gendarmes"
  }
}
