{
  "geometry": {
    "type": "Point",
    "coordinates": [
      -104.15,
      40.3167
    ]
  },
  "type": "Feature",
  "properties": {
    "hierarchy": [
      "tgn:2417933",
      "tgn:1000001",
      "tgn:7012149",
      "tgn:7007158",
      "tgn:7029392"
    ],
    "placetype": [
      "aat:300006075"
    ],
    "id": 2417933,
    "name:xx": "Jackson Lake Inlet"
  }
}
