{
  "geometry": {
    "type": "Point",
    "coordinates": [
      -84.3833,
      37.9167
    ]
  },
  "type": "Feature",
  "properties": {
    "hierarchy": [
      "tgn:2314469",
      "tgn:1000001",
      "tgn:7012149",
      "tgn:1002371",
      "tgn:7007255",
      "tgn:7029392"
    ],
    "placetype": [
      "aat:300008706"
    ],
    "id": 2314469,
    "name:xx": "Elk Lick Creek"
  }
}
