{
  "geometry": {
    "type": "Point",
    "coordinates": [
      -104.7167,
      34.2167
    ]
  },
  "type": "Feature",
  "properties": {
    "hierarchy": [
      "tgn:2170170",
      "tgn:1000001",
      "tgn:7019560",
      "tgn:7012149",
      "tgn:7007566",
      "tgn:7029392"
    ],
    "placetype": [
      "aat:300006191"
    ],
    "id": 2170170,
    "name:xx": "Big Ragland Tank"
  }
}
