{
  "geometry": {
    "type": "Point",
    "coordinates": [
      -79.2833,
      39.3167
    ]
  },
  "type": "Feature",
  "properties": {
    "hierarchy": [
      "tgn:2694788",
      "tgn:1000001",
      "tgn:2000935",
      "tgn:7012149",
      "tgn:7007516",
      "tgn:7029392"
    ],
    "placetype": [
      "aat:300008699"
    ],
    "id": 2694788,
    "name:xx": "Steyer Run"
  }
}
