{
  "geometry": {
    "type": "Point",
    "coordinates": [
      30.8333,
      48.5833
    ]
  },
  "type": "Feature",
  "properties": {
    "hierarchy": [
      "tgn:1057629",
      "tgn:1000003",
      "tgn:7011662",
      "tgn:7006660",
      "tgn:7029392"
    ],
    "placetype": [
      "aat:300008347"
    ],
    "id": 1057629,
    "name:xx": "Novoarkhangelsk"
  }
}
