{
  "geometry": {
    "type": "Point",
    "coordinates": [
      -81.6667,
      35.65
    ]
  },
  "type": "Feature",
  "properties": {
    "hierarchy": [
      "tgn:2176032",
      "tgn:1000001",
      "tgn:2001474",
      "tgn:7012149",
      "tgn:7007709",
      "tgn:7029392"
    ],
    "placetype": [
      "aat:300266640"
    ],
    "id": 2176032,
    "name:xx": "Black Fox Ridge"
  }
}
