{
  "geometry": {
    "type": "Point",
    "coordinates": [
      -122.9333,
      39.2333
    ]
  },
  "type": "Feature",
  "properties": {
    "hierarchy": [
      "tgn:2740246",
      "tgn:1000001",
      "tgn:7012149",
      "tgn:7007157",
      "tgn:1002566",
      "tgn:7029392"
    ],
    "placetype": [
      "aat:300055621"
    ],
    "id": 2740246,
    "name:xx": "Upper Lake"
  }
}
