{
  "geometry": {
    "type": "Point",
    "coordinates": [
      31.883333,
      31.35
    ]
  },
  "type": "Feature",
  "properties": {
    "hierarchy": [
      "tgn:7544247",
      "tgn:7001242",
      "tgn:1001059",
      "tgn:7016833",
      "tgn:7029392"
    ],
    "placetype": [
      "aat:300006075"
    ],
    "name:en": "Qanāt al 'Inābīyah",
    "id": 7544247
  }
}
