{
  "geometry": {
    "type": "Point",
    "coordinates": [
      -111.45,
      42.0833
    ]
  },
  "type": "Feature",
  "properties": {
    "hierarchy": [
      "tgn:2268986",
      "tgn:2000455",
      "tgn:1000001",
      "tgn:7012149",
      "tgn:7007250",
      "tgn:7029392"
    ],
    "placetype": [
      "aat:300008761"
    ],
    "id": 2268986,
    "name:xx": "Crossley Hollow"
  }
}
