{
  "geometry": {
    "type": "Point",
    "coordinates": [
      -94.1667,
      32.3667
    ]
  },
  "type": "Feature",
  "properties": {
    "hierarchy": [
      "tgn:2104055",
      "tgn:1000001",
      "tgn:7012149",
      "tgn:1002460",
      "tgn:7007826",
      "tgn:7029392"
    ],
    "placetype": [
      "aat:300008347"
    ],
    "id": 2104055,
    "name:xx": "Elysian Fields"
  }
}
