{
  "geometry": {
    "type": "Point",
    "coordinates": [
      -103.9667,
      39.15
    ]
  },
  "type": "Feature",
  "properties": {
    "hierarchy": [
      "tgn:2170728",
      "tgn:1000001",
      "tgn:7012149",
      "tgn:2000211",
      "tgn:7007158",
      "tgn:7029392"
    ],
    "placetype": [
      "aat:300006191"
    ],
    "id": 2170728,
    "name:xx": "Big Sandy Creek Watershed S-23 Reservoir"
  }
}
