{
  "geometry": {
    "type": "Point",
    "coordinates": [
      73.966667,
      34.619444
    ]
  },
  "type": "Feature",
  "properties": {
    "hierarchy": [
      "tgn:7589846",
      "tgn:1000004",
      "tgn:7000198",
      "tgn:7000799",
      "tgn:7029392"
    ],
    "placetype": [
      "aat:300008863"
    ],
    "name:en": "Kunjiwāla Forest",
    "id": 7589846
  }
}
