{
  "geometry": {
    "type": "Point",
    "coordinates": [
      -84.4167,
      35.9167
    ]
  },
  "type": "Feature",
  "properties": {
    "hierarchy": [
      "tgn:2192729",
      "tgn:1000001",
      "tgn:7012149",
      "tgn:2001909",
      "tgn:7007825",
      "tgn:7029392"
    ],
    "placetype": [
      "aat:300132348"
    ],
    "id": 2192729,
    "name:xx": "Brashears Shoals"
  }
}
