{
  "geometry": {
    "type": "Point",
    "coordinates": [
      -96.4167,
      48.9333
    ]
  },
  "type": "Feature",
  "properties": {
    "hierarchy": [
      "tgn:2691959",
      "tgn:1000001",
      "tgn:7012149",
      "tgn:2001033",
      "tgn:7007521",
      "tgn:7029392"
    ],
    "placetype": [
      "aat:300006075"
    ],
    "id": 2691959,
    "name:xx": "State Ditch Number Fiftyone"
  }
}
