{
  "geometry": {
    "type": "Point",
    "coordinates": [
      -89.8833,
      41.8833
    ]
  },
  "type": "Feature",
  "properties": {
    "hierarchy": [
      "tgn:2766836",
      "tgn:1000001",
      "tgn:7012149",
      "tgn:2000538",
      "tgn:7007251",
      "tgn:7029392"
    ],
    "placetype": [
      "aat:300008347"
    ],
    "id": 2766836,
    "name:xx": "White Pigeon"
  }
}
