{
  "type": "FeatureCollection",
  "features": [
    {
      "geometry": {
        "type": "Point",
        "coordinates": [
          11.9,
          42.966667
        ]
      },
      "type": "Feature",
      "properties": {
        "hierarchy": [
          "tgn:7006341",
          "tgn:7003168",
          "tgn:1000003",
          "tgn:7009760",
          "tgn:1000080",
          "tgn:7029392"
        ],
        "placetype": [
          "aat:300008347"
        ],
        "id": 7006341,
        "name:xx": "Cetona"
      }
    },
    {
      "geometry": {
        "type": "Point",
        "coordinates": [
          11.95,
          43.016667
        ]
      },
      "type": "Feature",
      "properties": {
        "hierarchy": [
          "tgn:7006344",
          "tgn:7003168",
          "tgn:1000003",
          "tgn:7009760",
          "tgn:1000080",
          "tgn:7029392"
        ],
        "placetype": [
          "aat:300008347",
          "aat:300000810",
          "aat:300387235",
          "aat:300008375"
        ],
        "id": 7006344,
        "name:xx": "Chiusi"
      }
    },
    {
      "geometry": {
        "type": "Point",
        "coordinates": [
          11.783333,
          43.083333
        ]
      },
      "type": "Feature",
      "properties": {
        "hierarchy": [
          "tgn:7006345",
          "tgn:7003168",
          "tgn:1000003",
          "tgn:7009760",
          "tgn:1000080",
          "tgn:7029392"
        ],
        "placetype": [
          "aat:300008347"
        ],
        "id": 7006345,
        "name:xx": "Montepulciano"
      }
    },
    {
      "geometry": {
        "type": "Point",
        "coordinates": [
          11.8833,
          42.8667
        ]
      },
      "type": "Feature",
      "properties": {
        "hierarchy": [
          "tgn:7006346",
          "tgn:7003168",
          "tgn:1000003",
          "tgn:7009760",
          "tgn:1000080",
          "tgn:7029392"
        ],
        "placetype": [
          "aat:300008347"
        ],
        "id": 7006346,
        "name:xx": "Rapolano Terme"
      }
    },
    {
      "geometry": {
        "type": "Point",
        "coordinates": [
          -67,
          -40
        ]
      },
      "type": "Feature",
      "properties": {
        "hierarchy": [
          "tgn:7006348",
          "tgn:7006477",
          "tgn:1000002",
          "tgn:7029392"
        ],
        "placetype": [
          "aat:300387064",
          "aat:300000774"
        ],
        "id": 7006348,
        "name:xx": "Río Negro"
      }
    },
    {
      "geometry": {
        "type": "Point",
        "coordinates": [
          18.1,
          46
        ]
      },
      "type": "Feature",
      "properties": {
        "hierarchy": [
          "tgn:7006349",
          "tgn:1000003",
          "tgn:7006278",
          "tgn:7029392"
        ],
        "placetype": [
          "aat:300387064",
          "aat:300000771"
        ],
        "id": 7006349,
        "name:xx": "Baranya"
      }
    }
  ]
}
