{
  "geometry": {
    "type": "Point",
    "coordinates": [
      -121.9667,
      44.4167
    ]
  },
  "type": "Feature",
  "properties": {
    "hierarchy": [
      "tgn:2646430",
      "tgn:1000001",
      "tgn:7012149",
      "tgn:2001717",
      "tgn:7007708",
      "tgn:7029392"
    ],
    "placetype": [
      "aat:300008746"
    ],
    "id": 2646430,
    "name:xx": "Sawyers Cave"
  }
}
