{
  "geometry": {
    "type": "Point",
    "coordinates": [
      27.355,
      58.004
    ]
  },
  "type": "Feature",
  "properties": {
    "hierarchy": [
      "tgn:1061173",
      "tgn:7006639",
      "tgn:1000003",
      "tgn:7006540",
      "tgn:7029392"
    ],
    "placetype": [
      "aat:300008347"
    ],
    "name:en": "Veriora",
    "id": 1061173
  }
}
