{
  "geometry": {
    "type": "Point",
    "coordinates": [
      -91.8667,
      31.6667
    ]
  },
  "type": "Feature",
  "properties": {
    "hierarchy": [
      "tgn:2000866",
      "tgn:1000001",
      "tgn:7012149",
      "tgn:7007256",
      "tgn:7029392"
    ],
    "placetype": [
      "aat:300387145",
      "aat:300387092"
    ],
    "id": 2000866,
    "name:xx": "Catahoula"
  }
}
