{
  "type": "FeatureCollection",
  "features": [
    {
      "geometry": {
        "type": "Point",
        "coordinates": [
          -70.05,
          12.5333
        ]
      },
      "type": "Feature",
      "properties": {
        "hierarchy": [
          "tgn:1012622",
          "tgn:7004548",
          "tgn:1000001",
          "tgn:7029392"
        ],
        "placetype": [
          "aat:300386846"
        ],
        "id": 1012622,
        "name:xx": "Westpunt"
      }
    },
    {
      "geometry": {
        "type": "Point",
        "coordinates": [
          -84.95,
          46.7667
        ]
      },
      "type": "Feature",
      "properties": {
        "hierarchy": [
          "tgn:1012623",
          "tgn:1000001",
          "tgn:2000952",
          "tgn:7012149",
          "tgn:7007520",
          "tgn:7029392"
        ],
        "placetype": [
          "aat:300386846"
        ],
        "id": 1012623,
        "name:xx": "Whitefish Point"
      }
    },
    {
      "geometry": {
        "type": "Point",
        "coordinates": [
          -122.75,
          48.1333
        ]
      },
      "type": "Feature",
      "properties": {
        "hierarchy": [
          "tgn:1012626",
          "tgn:1000001",
          "tgn:7012149",
          "tgn:1002521",
          "tgn:7007920",
          "tgn:7029392"
        ],
        "placetype": [
          "aat:300386846"
        ],
        "id": 1012626,
        "name:xx": "Wilson, Point"
      }
    },
    {
      "geometry": {
        "type": "Point",
        "coordinates": [
          -82.9167,
          42.35
        ]
      },
      "type": "Feature",
      "properties": {
        "hierarchy": [
          "tgn:1012628",
          "tgn:1000001",
          "tgn:7012149",
          "tgn:1003005",
          "tgn:7007520",
          "tgn:7029392"
        ],
        "placetype": [
          "aat:300386846"
        ],
        "id": 1012628,
        "name:xx": "Windmill Point"
      }
    },
    {
      "geometry": {
        "type": "Point",
        "coordinates": [
          -76.2667,
          37.6
        ]
      },
      "type": "Feature",
      "properties": {
        "hierarchy": [
          "tgn:1012629",
          "tgn:1000001",
          "tgn:7012149",
          "tgn:1002575",
          "tgn:7007919",
          "tgn:7029392"
        ],
        "placetype": [
          "aat:300386846"
        ],
        "id": 1012629,
        "name:xx": "Windmill Point"
      }
    }
  ]
}
