{
  "geometry": {
    "type": "Point",
    "coordinates": [
      -81.3667,
      29.85
    ]
  },
  "type": "Feature",
  "properties": {
    "hierarchy": [
      "tgn:2526838",
      "tgn:1000001",
      "tgn:7012149",
      "tgn:2000283",
      "tgn:7007240",
      "tgn:7029392"
    ],
    "placetype": [
      "aat:300008706"
    ],
    "id": 2526838,
    "name:xx": "Moultrie Creek"
  }
}
