{
  "type": "FeatureCollection",
  "features": [
    {
      "geometry": {
        "type": "Point",
        "coordinates": [
          14.133333,
          52.25
        ]
      },
      "type": "Feature",
      "properties": {
        "hierarchy": [
          "tgn:7200371",
          "tgn:7000096",
          "tgn:1000003",
          "tgn:7000084",
          "tgn:7029392"
        ],
        "placetype": [
          "aat:300008777"
        ],
        "id": 7200371,
        "name:xx": "Eich-Berg"
      }
    },
    {
      "geometry": {
        "type": "Point",
        "coordinates": [
          13.533333,
          52.166667
        ]
      },
      "type": "Feature",
      "properties": {
        "hierarchy": [
          "tgn:7200372",
          "tgn:7000096",
          "tgn:1000003",
          "tgn:7000084",
          "tgn:7029392"
        ],
        "placetype": [
          "aat:300008777"
        ],
        "id": 7200372,
        "name:xx": "Eich-Berg"
      }
    },
    {
      "geometry": {
        "type": "Point",
        "coordinates": [
          9.45,
          52.116667
        ]
      },
      "type": "Feature",
      "properties": {
        "hierarchy": [
          "tgn:7200373",
          "tgn:1000003",
          "tgn:7003676",
          "tgn:7000084",
          "tgn:7029392"
        ],
        "placetype": [
          "aat:300008777"
        ],
        "id": 7200373,
        "name:xx": "Eich-Berg"
      }
    },
    {
      "geometry": {
        "type": "Point",
        "coordinates": [
          14.066667,
          52.05
        ]
      },
      "type": "Feature",
      "properties": {
        "hierarchy": [
          "tgn:7200374",
          "tgn:7000096",
          "tgn:1000003",
          "tgn:7000084",
          "tgn:7029392"
        ],
        "placetype": [
          "aat:300008777"
        ],
        "id": 7200374,
        "name:xx": "Eich-Berg"
      }
    },
    {
      "geometry": {
        "type": "Point",
        "coordinates": [
          13.283333,
          52.016667
        ]
      },
      "type": "Feature",
      "properties": {
        "hierarchy": [
          "tgn:7200375",
          "tgn:7000096",
          "tgn:1000003",
          "tgn:7000084",
          "tgn:7029392"
        ],
        "placetype": [
          "aat:300008777"
        ],
        "id": 7200375,
        "name:xx": "Eich-Berg"
      }
    },
    {
      "geometry": {
        "type": "Point",
        "coordinates": [
          9.466667,
          52.016667
        ]
      },
      "type": "Feature",
      "properties": {
        "hierarchy": [
          "tgn:7200376",
          "tgn:1000003",
          "tgn:7003676",
          "tgn:7000084",
          "tgn:7029392"
        ],
        "placetype": [
          "aat:300008777"
        ],
        "id": 7200376,
        "name:xx": "Eich-Berg"
      }
    },
    {
      "geometry": {
        "type": "Point",
        "coordinates": [
          14.666667,
          51.916667
        ]
      },
      "type": "Feature",
      "properties": {
        "hierarchy": [
          "tgn:7200377",
          "tgn:7000096",
          "tgn:1000003",
          "tgn:7000084",
          "tgn:7029392"
        ],
        "placetype": [
          "aat:300008777"
        ],
        "id": 7200377,
        "name:xx": "Eich-Berg"
      }
    },
    {
      "geometry": {
        "type": "Point",
        "coordinates": [
          11.216667,
          51.566667
        ]
      },
      "type": "Feature",
      "properties": {
        "hierarchy": [
          "tgn:7200379",
          "tgn:1000003",
          "tgn:7003687",
          "tgn:7000084",
          "tgn:7029392"
        ],
        "placetype": [
          "aat:300008777"
        ],
        "id": 7200379,
        "name:xx": "Eich-Berg"
      }
    }
  ]
}
