{
  "geometry": {
    "type": "Point",
    "coordinates": [
      -98.0167,
      32.6167
    ]
  },
  "type": "Feature",
  "properties": {
    "hierarchy": [
      "tgn:2595475",
      "tgn:1000001",
      "tgn:7012149",
      "tgn:1002771",
      "tgn:7007826",
      "tgn:7029392"
    ],
    "placetype": [
      "aat:300008798"
    ],
    "id": 2595475,
    "name:xx": "Potato Hill"
  }
}
