{
  "geometry": {
    "type": "Point",
    "coordinates": [
      -116.1333,
      33.9833
    ]
  },
  "type": "Feature",
  "properties": {
    "hierarchy": [
      "tgn:2634938",
      "tgn:1000001",
      "tgn:7012149",
      "tgn:7007157",
      "tgn:1002828",
      "tgn:7029392"
    ],
    "placetype": [
      "aat:300008798"
    ],
    "id": 2634938,
    "name:xx": "Ryan Mountain"
  }
}
