{
  "geometry": {
    "type": "Point",
    "coordinates": [
      -122.2333,
      44.3333
    ]
  },
  "type": "Feature",
  "properties": {
    "hierarchy": [
      "tgn:1107794",
      "tgn:1000001",
      "tgn:7012149",
      "tgn:2001717",
      "tgn:7007708",
      "tgn:7029392"
    ],
    "placetype": [
      "aat:300008744"
    ],
    "id": 1107794,
    "name:xx": "Twin Buttes"
  }
}
