{
  "geometry": {
    "type": "Point",
    "coordinates": [
      -93.9833,
      37.7667
    ]
  },
  "type": "Feature",
  "properties": {
    "hierarchy": [
      "tgn:2234638",
      "tgn:1000001",
      "tgn:2001183",
      "tgn:7012149",
      "tgn:7007523",
      "tgn:7029392"
    ],
    "placetype": [
      "aat:300008699"
    ],
    "id": 2234638,
    "name:xx": "Cherry Branch"
  }
}
