{
  "geometry": {
    "type": "Point",
    "coordinates": [
      -85.6333,
      37.9167
    ]
  },
  "type": "Feature",
  "properties": {
    "hierarchy": [
      "tgn:2593136",
      "tgn:1000001",
      "tgn:2000774",
      "tgn:7012149",
      "tgn:7007255",
      "tgn:7029392"
    ],
    "placetype": [
      "aat:300008347"
    ],
    "id": 2593136,
    "name:xx": "Poplar Level"
  }
}
