{
  "type": "FeatureCollection",
  "features": [
    {
      "geometry": {
        "type": "Point",
        "coordinates": [
          -71.966667,
          -37.816667
        ]
      },
      "type": "Feature",
      "properties": {
        "hierarchy": [
          "tgn:7282480",
          "tgn:1001637",
          "tgn:1000049",
          "tgn:1000002",
          "tgn:7029392"
        ],
        "placetype": [
          "aat:300008795"
        ],
        "id": 7282480,
        "name:xx": "Peuco, Loma del"
      }
    },
    {
      "geometry": {
        "type": "Point",
        "coordinates": [
          -73.316667,
          -39.95
        ]
      },
      "type": "Feature",
      "properties": {
        "hierarchy": [
          "tgn:7282481",
          "tgn:1001699",
          "tgn:1000049",
          "tgn:1000002",
          "tgn:7029392"
        ],
        "placetype": [
          "aat:300008699"
        ],
        "id": 7282481,
        "name:xx": "Peuco, Estero del"
      }
    },
    {
      "geometry": {
        "type": "Point",
        "coordinates": [
          -70.716667,
          -33.95
        ]
      },
      "type": "Feature",
      "properties": {
        "hierarchy": [
          "tgn:7282482",
          "tgn:1001708",
          "tgn:1000049",
          "tgn:1000002",
          "tgn:7029392"
        ],
        "placetype": [
          "aat:300008699"
        ],
        "id": 7282482,
        "name:xx": "Peuco, Estero del"
      }
    },
    {
      "geometry": {
        "type": "Point",
        "coordinates": [
          -70.45,
          -33.95
        ]
      },
      "type": "Feature",
      "properties": {
        "hierarchy": [
          "tgn:7282483",
          "tgn:1001695",
          "tgn:1000049",
          "tgn:1000002",
          "tgn:7029392"
        ],
        "placetype": [
          "aat:300008795"
        ],
        "id": 7282483,
        "name:xx": "Peuco, Cerros de"
      }
    },
    {
      "geometry": {
        "type": "Point",
        "coordinates": [
          -70.833333,
          -33.083333
        ]
      },
      "type": "Feature",
      "properties": {
        "hierarchy": [
          "tgn:7282484",
          "tgn:1001708",
          "tgn:1000049",
          "tgn:1000002",
          "tgn:7029392"
        ],
        "placetype": [
          "aat:300008795"
        ],
        "id": 7282484,
        "name:xx": "Peuco, Cerro"
      }
    },
    {
      "geometry": {
        "type": "Point",
        "coordinates": [
          -70.65,
          -33.95
        ]
      },
      "type": "Feature",
      "properties": {
        "hierarchy": [
          "tgn:7282485",
          "tgn:1001695",
          "tgn:1000049",
          "tgn:1000002",
          "tgn:7029392"
        ],
        "placetype": [
          "aat:300000206"
        ],
        "id": 7282485,
        "name:xx": "Peuco"
      }
    },
    {
      "geometry": {
        "type": "Point",
        "coordinates": [
          -74.062222,
          -44.032222
        ]
      },
      "type": "Feature",
      "properties": {
        "hierarchy": [
          "tgn:7282486",
          "tgn:1001623",
          "tgn:1000049",
          "tgn:1000002",
          "tgn:7029392"
        ],
        "placetype": [
          "aat:300011692"
        ],
        "id": 7282486,
        "name:xx": "Petún, Roca"
      }
    },
    {
      "geometry": {
        "type": "Point",
        "coordinates": [
          -75.316667,
          -49.233333
        ]
      },
      "type": "Feature",
      "properties": {
        "hierarchy": [
          "tgn:7282487",
          "tgn:1001702",
          "tgn:1000049",
          "tgn:1000002",
          "tgn:7029392"
        ],
        "placetype": [
          "aat:300008791"
        ],
        "id": 7282487,
        "name:xx": "Petters, Isla"
      }
    },
    {
      "geometry": {
        "type": "Point",
        "coordinates": [
          -71.266667,
          -37.483333
        ]
      },
      "type": "Feature",
      "properties": {
        "hierarchy": [
          "tgn:7282488",
          "tgn:1001637",
          "tgn:1000049",
          "tgn:1000002",
          "tgn:7029392"
        ],
        "placetype": [
          "aat:300008699"
        ],
        "id": 7282488,
        "name:xx": "Petronquines, Estero"
      }
    },
    {
      "geometry": {
        "type": "Point",
        "coordinates": [
          -71.416667,
          -37.516667
        ]
      },
      "type": "Feature",
      "properties": {
        "hierarchy": [
          "tgn:7282489",
          "tgn:1001637",
          "tgn:1000049",
          "tgn:1000002",
          "tgn:7029392"
        ],
        "placetype": [
          "aat:300008795"
        ],
        "id": 7282489,
        "name:xx": "Petronquines, Cordón"
      }
    }
  ]
}
