{
  "geometry": {
    "type": "Point",
    "coordinates": [
      -94.8833,
      32.1167
    ]
  },
  "type": "Feature",
  "properties": {
    "hierarchy": [
      "tgn:2568791",
      "tgn:1000001",
      "tgn:7012149",
      "tgn:1002839",
      "tgn:7007826",
      "tgn:7029392"
    ],
    "placetype": [
      "aat:300008706"
    ],
    "id": 2568791,
    "name:xx": "Parker Creek"
  }
}
