{
  "type": "FeatureCollection",
  "features": [
    {
      "geometry": {
        "type": "Point",
        "coordinates": [
          -121,
          38.8833
        ]
      },
      "type": "Feature",
      "properties": {
        "hierarchy": [
          "tgn:2010832",
          "tgn:1000001",
          "tgn:7012149",
          "tgn:1002350",
          "tgn:7007157",
          "tgn:7029392"
        ],
        "placetype": [
          "aat:300008347"
        ],
        "id": 2010832,
        "name:xx": "Cool"
      }
    },
    {
      "geometry": {
        "type": "Point",
        "coordinates": [
          -121.7,
          36.7
        ]
      },
      "type": "Feature",
      "properties": {
        "hierarchy": [
          "tgn:2010834",
          "tgn:1000001",
          "tgn:7012149",
          "tgn:7007157",
          "tgn:1002684",
          "tgn:7029392"
        ],
        "placetype": [
          "aat:300387016"
        ],
        "id": 2010834,
        "name:xx": "Cooper"
      }
    },
    {
      "geometry": {
        "type": "Point",
        "coordinates": [
          -120.5333,
          37.7333
        ]
      },
      "type": "Feature",
      "properties": {
        "hierarchy": [
          "tgn:2010836",
          "tgn:1000001",
          "tgn:7012149",
          "tgn:7007157",
          "tgn:1002915",
          "tgn:7029392"
        ],
        "placetype": [
          "aat:300387016"
        ],
        "id": 2010836,
        "name:xx": "Cooperstown"
      }
    },
    {
      "geometry": {
        "type": "Point",
        "coordinates": [
          -122.35,
          41.9833
        ]
      },
      "type": "Feature",
      "properties": {
        "hierarchy": [
          "tgn:2010837",
          "tgn:1000001",
          "tgn:7012149",
          "tgn:7007157",
          "tgn:2000189",
          "tgn:7029392"
        ],
        "placetype": [
          "aat:300008347"
        ],
        "id": 2010837,
        "name:xx": "Copco"
      }
    },
    {
      "geometry": {
        "type": "Point",
        "coordinates": [
          -121.3333,
          41.85
        ]
      },
      "type": "Feature",
      "properties": {
        "hierarchy": [
          "tgn:2010838",
          "tgn:1000001",
          "tgn:7012149",
          "tgn:7007157",
          "tgn:2000186",
          "tgn:7029392"
        ],
        "placetype": [
          "aat:300387016"
        ],
        "id": 2010838,
        "name:xx": "Copic"
      }
    },
    {
      "geometry": {
        "type": "Point",
        "coordinates": [
          -120.6333,
          37.9667
        ]
      },
      "type": "Feature",
      "properties": {
        "hierarchy": [
          "tgn:2010839",
          "tgn:1000001",
          "tgn:1002219",
          "tgn:7012149",
          "tgn:7007157",
          "tgn:7029392"
        ],
        "placetype": [
          "aat:300008347"
        ],
        "id": 2010839,
        "name:xx": "Copperopolis"
      }
    }
  ]
}
