{
  "geometry": {
    "type": "Point",
    "coordinates": [
      113.8833,
      35.7667
    ]
  },
  "type": "Feature",
  "properties": {
    "hierarchy": [
      "tgn:1139257",
      "tgn:1000004",
      "tgn:7016672",
      "tgn:1000111",
      "tgn:7029392"
    ],
    "placetype": [
      "aat:300008347"
    ],
    "id": 1139257,
    "name:xx": "Linqi"
  }
}
