{
  "geometry": {
    "type": "Point",
    "coordinates": [
      -96.0167,
      41.7333
    ]
  },
  "type": "Feature",
  "properties": {
    "hierarchy": [
      "tgn:2630795",
      "tgn:1000001",
      "tgn:2000603",
      "tgn:7012149",
      "tgn:7007253",
      "tgn:7029392"
    ],
    "placetype": [
      "aat:300006191"
    ],
    "id": 2630795,
    "name:xx": "Round Lake"
  }
}
