{
  "geometry": {
    "type": "Point",
    "coordinates": [
      139.1167,
      35.3167
    ]
  },
  "type": "Feature",
  "properties": {
    "hierarchy": [
      "tgn:1080786",
      "tgn:7016696",
      "tgn:1000004",
      "tgn:7000894",
      "tgn:1000120",
      "tgn:7029392"
    ],
    "placetype": [
      "aat:300008347"
    ],
    "id": 1080786,
    "name:xx": "Minamiashigara"
  }
}
