{
  "geometry": {
    "type": "Point",
    "coordinates": [
      -87.3167,
      35.5667
    ]
  },
  "type": "Feature",
  "properties": {
    "hierarchy": [
      "tgn:2347477",
      "tgn:1000001",
      "tgn:7012149",
      "tgn:2001896",
      "tgn:7007825",
      "tgn:7029392"
    ],
    "placetype": [
      "aat:300008761"
    ],
    "id": 2347477,
    "name:xx": "George Pogue Hollow"
  }
}
