{
  "geometry": {
    "type": "Point",
    "coordinates": [
      6.0333,
      62.3667
    ]
  },
  "type": "Feature",
  "properties": {
    "hierarchy": [
      "tgn:1048566",
      "tgn:7003647",
      "tgn:1000003",
      "tgn:1000088",
      "tgn:7029392"
    ],
    "placetype": [
      "aat:300008347"
    ],
    "id": 1048566,
    "name:xx": "Hareid"
  }
}
