{
  "geometry": {
    "type": "Point",
    "coordinates": [
      -94.85,
      32.5667
    ]
  },
  "type": "Feature",
  "properties": {
    "hierarchy": [
      "tgn:2659287",
      "tgn:1000001",
      "tgn:7012149",
      "tgn:1002427",
      "tgn:7007826",
      "tgn:7029392"
    ],
    "placetype": [
      "aat:300008347"
    ],
    "id": 2659287,
    "name:xx": "Shiloh"
  }
}
