{
  "geometry": {
    "type": "Point",
    "coordinates": [
      -94.75,
      31.9833
    ]
  },
  "type": "Feature",
  "properties": {
    "hierarchy": [
      "tgn:2426716",
      "tgn:1000001",
      "tgn:7012149",
      "tgn:1002839",
      "tgn:7007826",
      "tgn:7029392"
    ],
    "placetype": [
      "aat:300006191"
    ],
    "id": 2426716,
    "name:xx": "Jones Lake"
  }
}
