{
  "geometry": {
    "type": "Point",
    "coordinates": [
      -82.7667,
      30.4333
    ]
  },
  "type": "Feature",
  "properties": {
    "hierarchy": [
      "tgn:2592429",
      "tgn:1000001",
      "tgn:2000271",
      "tgn:7012149",
      "tgn:7007240",
      "tgn:7029392"
    ],
    "placetype": [
      "aat:300008680"
    ],
    "id": 2592429,
    "name:xx": "Poole Pond"
  }
}
