{
  "geometry": {
    "type": "Point",
    "coordinates": [
      -81.3833,
      38.4167
    ]
  },
  "type": "Feature",
  "properties": {
    "hierarchy": [
      "tgn:2741142",
      "tgn:1000001",
      "tgn:7012149",
      "tgn:2002270",
      "tgn:7013961",
      "tgn:7029392"
    ],
    "placetype": [
      "aat:300008699"
    ],
    "id": 2741142,
    "name:xx": "Upper Threemile Fork"
  }
}
