{
  "geometry": {
    "type": "Point",
    "coordinates": [
      -80.5333,
      43.4667
    ]
  },
  "type": "Feature",
  "properties": {
    "hierarchy": [
      "tgn:7013137",
      "tgn:7005685",
      "tgn:1000001",
      "tgn:7013154",
      "tgn:7029392"
    ],
    "placetype": [
      "aat:300008347"
    ],
    "id": 7013137,
    "name:xx": "Waterloo"
  }
}
