{
  "geometry": {
    "type": "Point",
    "coordinates": [
      -75.7167,
      40.9833
    ]
  },
  "type": "Feature",
  "properties": {
    "hierarchy": [
      "tgn:2445864",
      "tgn:1000001",
      "tgn:1002233",
      "tgn:7012149",
      "tgn:7007710",
      "tgn:7029392"
    ],
    "placetype": [
      "aat:300008347"
    ],
    "id": 2445864,
    "name:xx": "Leslie Run"
  }
}
