{
  "geometry": {
    "type": "Point",
    "coordinates": [
      -113.8167,
      48.1667
    ]
  },
  "type": "Feature",
  "properties": {
    "hierarchy": [
      "tgn:2572935",
      "tgn:1000001",
      "tgn:7012149",
      "tgn:2001274",
      "tgn:7007524",
      "tgn:7029392"
    ],
    "placetype": [
      "aat:300008706"
    ],
    "id": 2572935,
    "name:xx": "Pearl Creek"
  }
}
