{
  "geometry": {
    "type": "Point",
    "coordinates": [
      -116.85,
      45.9833
    ]
  },
  "type": "Feature",
  "properties": {
    "hierarchy": [
      "tgn:2167317",
      "tgn:1000001",
      "tgn:7012149",
      "tgn:2000486",
      "tgn:7007250",
      "tgn:7029392"
    ],
    "placetype": [
      "aat:300008706"
    ],
    "id": 2167317,
    "name:xx": "Big Cougar Creek"
  }
}
