{
  "type": "FeatureCollection",
  "features": [
    {
      "geometry": {
        "type": "Point",
        "coordinates": [
          -84.1,
          40.7333
        ]
      },
      "type": "Feature",
      "properties": {
        "hierarchy": [
          "tgn:7013890",
          "tgn:1002144",
          "tgn:1000001",
          "tgn:7012149",
          "tgn:7007706",
          "tgn:7029392"
        ],
        "placetype": [
          "aat:300008347"
        ],
        "id": 7013890,
        "name:xx": "Lima"
      }
    },
    {
      "geometry": {
        "type": "Point",
        "coordinates": [
          -71.3,
          42.4167
        ]
      },
      "type": "Feature",
      "properties": {
        "hierarchy": [
          "tgn:7013891",
          "tgn:1000001",
          "tgn:1002665",
          "tgn:7012149",
          "tgn:7007517",
          "tgn:7029392"
        ],
        "placetype": [
          "aat:300008347"
        ],
        "id": 7013891,
        "name:xx": "Lincoln"
      }
    },
    {
      "geometry": {
        "type": "Point",
        "coordinates": [
          -96.6667,
          40.8
        ]
      },
      "type": "Feature",
      "properties": {
        "hierarchy": [
          "tgn:7013892",
          "tgn:1000001",
          "tgn:2001370",
          "tgn:7012149",
          "tgn:7007525",
          "tgn:7029392"
        ],
        "placetype": [
          "aat:300387277",
          "aat:300008347",
          "aat:300008416",
          "aat:300008389",
          "aat:300387308",
          "aat:300387512",
          "aat:300387221",
          "aat:300387270",
          "aat:300387296"
        ],
        "id": 7013892,
        "name:xx": "Lincoln"
      }
    },
    {
      "geometry": {
        "type": "Point",
        "coordinates": [
          -73.1833,
          41.7333
        ]
      },
      "type": "Feature",
      "properties": {
        "hierarchy": [
          "tgn:7013894",
          "tgn:1000001",
          "tgn:1002601",
          "tgn:7012149",
          "tgn:7007159",
          "tgn:7029392"
        ],
        "placetype": [
          "aat:300008347"
        ],
        "id": 7013894,
        "name:xx": "Litchfield"
      }
    },
    {
      "geometry": {
        "type": "Point",
        "coordinates": [
          -92.2833,
          34.7333
        ]
      },
      "type": "Feature",
      "properties": {
        "hierarchy": [
          "tgn:7013897",
          "tgn:1000001",
          "tgn:7016172",
          "tgn:7012149",
          "tgn:2000164",
          "tgn:7029392"
        ],
        "placetype": [
          "aat:300008347",
          "aat:300008416",
          "aat:300387255",
          "aat:300008389",
          "aat:300387308",
          "aat:300387304",
          "aat:300005135",
          "aat:300264742",
          "aat:300387305",
          "aat:300387221",
          "aat:300387302"
        ],
        "id": 7013897,
        "name:xx": "Little Rock"
      }
    },
    {
      "geometry": {
        "type": "Point",
        "coordinates": [
          -105,
          39.6
        ]
      },
      "type": "Feature",
      "properties": {
        "hierarchy": [
          "tgn:7013898",
          "tgn:2000194",
          "tgn:1000001",
          "tgn:7012149",
          "tgn:7007158",
          "tgn:7029392"
        ],
        "placetype": [
          "aat:300008347"
        ],
        "id": 7013898,
        "name:xx": "Littleton"
      }
    }
  ]
}
