{
  "geometry": {
    "type": "Point",
    "coordinates": [
      -61.5833,
      16.1833
    ]
  },
  "type": "Feature",
  "properties": {
    "hierarchy": [
      "tgn:1012391",
      "tgn:7018312",
      "tgn:1006440",
      "tgn:1000001",
      "tgn:7004545",
      "tgn:7029392"
    ],
    "placetype": [
      "aat:300386846"
    ],
    "id": 1012391,
    "name:xx": "Rivière à Goyaves, Pointe de la"
  }
}
