{
  "geometry": {
    "type": "Point",
    "coordinates": [
      -87.85,
      31.2333
    ]
  },
  "type": "Feature",
  "properties": {
    "hierarchy": [
      "tgn:2162852",
      "tgn:7002659",
      "tgn:1000001",
      "tgn:2000012",
      "tgn:7012149",
      "tgn:7029392"
    ],
    "placetype": [
      "aat:300008680"
    ],
    "id": 2162852,
    "name:xx": "Bengy Lake"
  }
}
