{
  "geometry": {
    "type": "Point",
    "coordinates": [
      -123.3833,
      39.15
    ]
  },
  "type": "Feature",
  "properties": {
    "hierarchy": [
      "tgn:2499125",
      "tgn:1000001",
      "tgn:7012149",
      "tgn:7007157",
      "tgn:2000185",
      "tgn:7029392"
    ],
    "placetype": [
      "aat:300008706"
    ],
    "id": 2499125,
    "name:xx": "McCarvey Creek"
  }
}
