{
  "geometry": {
    "type": "Point",
    "coordinates": [
      91.16903,
      26.601945
    ]
  },
  "type": "Feature",
  "properties": {
    "hierarchy": [
      "tgn:7559003",
      "tgn:1000004",
      "tgn:1001832",
      "tgn:7000198",
      "tgn:7029392"
    ],
    "placetype": [
      "aat:300008347"
    ],
    "name:en": "Rihābāri",
    "id": 7559003
  }
}
