{
  "geometry": {
    "type": "Point",
    "coordinates": [
      -59.3167,
      -34.7167
    ]
  },
  "type": "Feature",
  "properties": {
    "hierarchy": [
      "tgn:1020102",
      "tgn:1001160",
      "tgn:7006477",
      "tgn:1000002",
      "tgn:7029392"
    ],
    "placetype": [
      "aat:300008347"
    ],
    "id": 1020102,
    "name:xx": "Tomás Jofré"
  }
}
