{
  "geometry": {
    "type": "Point",
    "coordinates": [
      -105.7333,
      38.2167
    ]
  },
  "type": "Feature",
  "properties": {
    "hierarchy": [
      "tgn:2548361",
      "tgn:1000001",
      "tgn:7012149",
      "tgn:2000205",
      "tgn:7007158",
      "tgn:7029392"
    ],
    "placetype": [
      "aat:300008706"
    ],
    "id": 2548361,
    "name:xx": "North Lake Creek"
  }
}
