{
  "geometry": {
    "type": "Point",
    "coordinates": [
      87.1667,
      52.25
    ]
  },
  "type": "Feature",
  "properties": {
    "hierarchy": [
      "tgn:1060530",
      "tgn:7011495",
      "tgn:1000004",
      "tgn:7002435",
      "tgn:7029392"
    ],
    "placetype": [
      "aat:300008347"
    ],
    "id": 1060530,
    "name:xx": "Turochak"
  }
}
