{
  "geometry": {
    "type": "Point",
    "coordinates": [
      -110.5333,
      34.2833
    ]
  },
  "type": "Feature",
  "properties": {
    "hierarchy": [
      "tgn:2579094",
      "tgn:1000001",
      "tgn:7006451",
      "tgn:7012149",
      "tgn:2000099",
      "tgn:7029392"
    ],
    "placetype": [
      "aat:300008699"
    ],
    "id": 2579094,
    "name:xx": "Phoenix Park Wash"
  }
}
