{
  "geometry": {
    "type": "Point",
    "coordinates": [
      -122.1333,
      45.2667
    ]
  },
  "type": "Feature",
  "properties": {
    "hierarchy": [
      "tgn:2283468",
      "tgn:1000001",
      "tgn:1002270",
      "tgn:7012149",
      "tgn:7007708",
      "tgn:7029392"
    ],
    "placetype": [
      "aat:300008706"
    ],
    "id": 2283468,
    "name:xx": "Delph Creek"
  }
}
