{
  "geometry": {
    "type": "Point",
    "coordinates": [
      -82.4333,
      38.7667
    ]
  },
  "type": "Feature",
  "properties": {
    "hierarchy": [
      "tgn:2078692",
      "tgn:1000001",
      "tgn:7012149",
      "tgn:2001612",
      "tgn:7007706",
      "tgn:7029392"
    ],
    "placetype": [
      "aat:300008347"
    ],
    "id": 2078692,
    "name:xx": "Cadmus"
  }
}
