{
  "geometry": {
    "type": "Point",
    "coordinates": [
      102.25,
      19.9667
    ]
  },
  "type": "Feature",
  "properties": {
    "hierarchy": [
      "tgn:1131952",
      "tgn:1000004",
      "tgn:1000125",
      "tgn:7029392"
    ],
    "placetype": [
      "aat:300008707"
    ],
    "id": 1131952,
    "name:xx": "Xuang, Houay"
  }
}
