{
  "geometry": {
    "type": "Point",
    "coordinates": [
      79.23804,
      24.658153
    ]
  },
  "type": "Feature",
  "properties": {
    "hierarchy": [
      "tgn:7566091",
      "tgn:1000004",
      "tgn:7000198",
      "tgn:1001894",
      "tgn:7029392"
    ],
    "placetype": [
      "aat:300008699"
    ],
    "name:en": "Jurauniya Nāla",
    "id": 7566091
  }
}
