{
  "geometry": {
    "type": "Point",
    "coordinates": [
      -95.2167,
      32.0333
    ]
  },
  "type": "Feature",
  "properties": {
    "hierarchy": [
      "tgn:2173675",
      "tgn:1000001",
      "tgn:7012149",
      "tgn:1002263",
      "tgn:7007826",
      "tgn:7029392"
    ],
    "placetype": [
      "aat:300008706"
    ],
    "id": 2173675,
    "name:xx": "Birches Creek"
  }
}
