{
  "geometry": {
    "type": "Point",
    "coordinates": [
      -78.8667,
      42.25
    ]
  },
  "type": "Feature",
  "properties": {
    "hierarchy": [
      "tgn:2753521",
      "tgn:1000001",
      "tgn:1002245",
      "tgn:7012149",
      "tgn:7007568",
      "tgn:7029392"
    ],
    "placetype": [
      "aat:300008905"
    ],
    "id": 2753521,
    "name:xx": "Waterman Swamp"
  }
}
