{
  "geometry": {
    "type": "Point",
    "coordinates": [
      -108.0167,
      36.8167
    ]
  },
  "type": "Feature",
  "properties": {
    "hierarchy": [
      "tgn:2323323",
      "tgn:1000001",
      "tgn:7012149",
      "tgn:2001452",
      "tgn:7007566",
      "tgn:7029392"
    ],
    "placetype": [
      "aat:300006075"
    ],
    "id": 2323323,
    "name:xx": "Farmers Ditch"
  }
}
