{
  "geometry": {
    "type": "Point",
    "coordinates": [
      -80.0667,
      40.0833
    ]
  },
  "type": "Feature",
  "properties": {
    "hierarchy": [
      "tgn:2587946",
      "tgn:1000001",
      "tgn:7012149",
      "tgn:1002995",
      "tgn:7007710",
      "tgn:7029392"
    ],
    "placetype": [
      "aat:300008347"
    ],
    "id": 2587946,
    "name:xx": "Pleasant View Heights"
  }
}
