{
  "geometry": {
    "type": "Point",
    "coordinates": [
      -69.533333,
      -21.65
    ]
  },
  "type": "Feature",
  "properties": {
    "hierarchy": [
      "tgn:7284572",
      "tgn:7016598",
      "tgn:1000049",
      "tgn:1000002",
      "tgn:7029392"
    ],
    "placetype": [
      "aat:300007783"
    ],
    "id": 7284572,
    "name:xx": "Estación Quillagua"
  }
}
