{
  "type": "FeatureCollection",
  "features": [
    {
      "geometry": {
        "type": "Point",
        "coordinates": [
          73.4333,
          40.65
        ]
      },
      "type": "Feature",
      "properties": {
        "hierarchy": [
          "tgn:1125430",
          "tgn:7011476",
          "tgn:1000004",
          "tgn:7006655",
          "tgn:7029392"
        ],
        "placetype": [
          "aat:300008707"
        ],
        "id": 1125430,
        "name:xx": "Kara-Kul'dzha"
      }
    },
    {
      "geometry": {
        "type": "Point",
        "coordinates": [
          172.1,
          -41.266667
        ]
      },
      "type": "Feature",
      "properties": {
        "hierarchy": [
          "tgn:1125432",
          "tgn:1009227",
          "tgn:1000226",
          "tgn:1000006",
          "tgn:7016850",
          "tgn:7029392"
        ],
        "placetype": [
          "aat:300008707",
          "aat:300008699"
        ],
        "id": 1125432,
        "name:xx": "Karamea"
      }
    },
    {
      "geometry": {
        "type": "Point",
        "coordinates": [
          45,
          51.3333
        ]
      },
      "type": "Feature",
      "properties": {
        "hierarchy": [
          "tgn:1125433",
          "tgn:1000004",
          "tgn:7002435",
          "tgn:7029392"
        ],
        "placetype": [
          "aat:300008707"
        ],
        "id": 1125433,
        "name:xx": "Karamysh"
      }
    },
    {
      "geometry": {
        "type": "Point",
        "coordinates": [
          139.1667,
          36.2667
        ]
      },
      "type": "Feature",
      "properties": {
        "hierarchy": [
          "tgn:1125434",
          "tgn:1000004",
          "tgn:7000894",
          "tgn:1000120",
          "tgn:7029392"
        ],
        "placetype": [
          "aat:300008707"
        ],
        "id": 1125434,
        "name:xx": "Karasu-gawa"
      }
    },
    {
      "geometry": {
        "type": "Point",
        "coordinates": [
          77.1667,
          46.4167
        ]
      },
      "type": "Feature",
      "properties": {
        "hierarchy": [
          "tgn:1125437",
          "tgn:1000004",
          "tgn:1003416",
          "tgn:7014786",
          "tgn:7029392"
        ],
        "placetype": [
          "aat:300008707"
        ],
        "id": 1125437,
        "name:xx": "Karatal"
      }
    },
    {
      "geometry": {
        "type": "Point",
        "coordinates": [
          89.5833,
          24.25
        ]
      },
      "type": "Feature",
      "properties": {
        "hierarchy": [
          "tgn:1125438",
          "tgn:1000004",
          "tgn:7029392"
        ],
        "placetype": [
          "aat:300008707"
        ],
        "id": 1125438,
        "name:xx": "Karatoya"
      }
    },
    {
      "geometry": {
        "type": "Point",
        "coordinates": [
          72.3333,
          40.9
        ]
      },
      "type": "Feature",
      "properties": {
        "hierarchy": [
          "tgn:1125439",
          "tgn:7011476",
          "tgn:1000004",
          "tgn:7006655",
          "tgn:7029392"
        ],
        "placetype": [
          "aat:300008707"
        ],
        "id": 1125439,
        "name:xx": "Karaunkyur"
      }
    }
  ]
}
