{
  "type": "FeatureCollection",
  "features": [
    {
      "geometry": {
        "type": "Point",
        "coordinates": [
          -109.7167,
          45.0833
        ]
      },
      "type": "Feature",
      "properties": {
        "hierarchy": [
          "tgn:2703520",
          "tgn:1000001",
          "tgn:2001264",
          "tgn:7012149",
          "tgn:7007524",
          "tgn:7029392"
        ],
        "placetype": [
          "aat:300008798"
        ],
        "id": 2703520,
        "name:xx": "Summit Mountain"
      }
    },
    {
      "geometry": {
        "type": "Point",
        "coordinates": [
          -113.3667,
          48.35
        ]
      },
      "type": "Feature",
      "properties": {
        "hierarchy": [
          "tgn:2703521",
          "tgn:1000001",
          "tgn:7012149",
          "tgn:7007524",
          "tgn:7029392"
        ],
        "placetype": [
          "aat:300008798"
        ],
        "id": 2703521,
        "name:xx": "Summit Mountain"
      }
    },
    {
      "geometry": {
        "type": "Point",
        "coordinates": [
          -74.9167,
          43.9833
        ]
      },
      "type": "Feature",
      "properties": {
        "hierarchy": [
          "tgn:2703522",
          "tgn:1000001",
          "tgn:7012149",
          "tgn:1002472",
          "tgn:7007568",
          "tgn:7029392"
        ],
        "placetype": [
          "aat:300008798"
        ],
        "id": 2703522,
        "name:xx": "Summit Mountain"
      }
    },
    {
      "geometry": {
        "type": "Point",
        "coordinates": [
          -124.3833,
          42.8667
        ]
      },
      "type": "Feature",
      "properties": {
        "hierarchy": [
          "tgn:2703523",
          "tgn:1000001",
          "tgn:2001704",
          "tgn:7012149",
          "tgn:7007708",
          "tgn:7029392"
        ],
        "placetype": [
          "aat:300008798"
        ],
        "id": 2703523,
        "name:xx": "Summit Mountain"
      }
    },
    {
      "geometry": {
        "type": "Point",
        "coordinates": [
          -118.1333,
          48.95
        ]
      },
      "type": "Feature",
      "properties": {
        "hierarchy": [
          "tgn:2703524",
          "tgn:1000001",
          "tgn:7012149",
          "tgn:2002250",
          "tgn:7007920",
          "tgn:7029392"
        ],
        "placetype": [
          "aat:300008798"
        ],
        "id": 2703524,
        "name:xx": "Summit Mountain"
      }
    },
    {
      "geometry": {
        "type": "Point",
        "coordinates": [
          -108.9833,
          32.8667
        ]
      },
      "type": "Feature",
      "properties": {
        "hierarchy": [
          "tgn:2703525",
          "tgn:1000001",
          "tgn:7012149",
          "tgn:2001437",
          "tgn:7007566",
          "tgn:7029392"
        ],
        "placetype": [
          "aat:300386831"
        ],
        "id": 2703525,
        "name:xx": "Summit Mountains"
      }
    },
    {
      "geometry": {
        "type": "Point",
        "coordinates": [
          -76.6667,
          39.3667
        ]
      },
      "type": "Feature",
      "properties": {
        "hierarchy": [
          "tgn:2703526",
          "tgn:7016099",
          "tgn:1000001",
          "tgn:7012149",
          "tgn:7007516",
          "tgn:7029392"
        ],
        "placetype": [
          "aat:300008347"
        ],
        "id": 2703526,
        "name:xx": "Summit Park"
      }
    },
    {
      "geometry": {
        "type": "Point",
        "coordinates": [
          -111.6,
          40.7333
        ]
      },
      "type": "Feature",
      "properties": {
        "hierarchy": [
          "tgn:2703527",
          "tgn:1000001",
          "tgn:7012149",
          "tgn:2002122",
          "tgn:7007827",
          "tgn:7029392"
        ],
        "placetype": [
          "aat:300008347"
        ],
        "id": 2703527,
        "name:xx": "Summit Park"
      }
    },
    {
      "geometry": {
        "type": "Point",
        "coordinates": [
          -115.8,
          39.8
        ]
      },
      "type": "Feature",
      "properties": {
        "hierarchy": [
          "tgn:2703528",
          "tgn:1000001",
          "tgn:7012149",
          "tgn:7007526",
          "tgn:7029392"
        ],
        "placetype": [
          "aat:300008798"
        ],
        "id": 2703528,
        "name:xx": "Summit Peak"
      }
    },
    {
      "geometry": {
        "type": "Point",
        "coordinates": [
          -108.9833,
          32.8667
        ]
      },
      "type": "Feature",
      "properties": {
        "hierarchy": [
          "tgn:2703529",
          "tgn:1000001",
          "tgn:7012149",
          "tgn:2001437",
          "tgn:7007566",
          "tgn:7029392"
        ],
        "placetype": [
          "aat:300008798"
        ],
        "id": 2703529,
        "name:xx": "Summit Peak"
      }
    }
  ]
}
