{
  "geometry": {
    "type": "Point",
    "coordinates": [
      -72.8667,
      42.5333
    ]
  },
  "type": "Feature",
  "properties": {
    "hierarchy": [
      "tgn:2754299",
      "tgn:1000001",
      "tgn:7013942",
      "tgn:7012149",
      "tgn:7007517",
      "tgn:7029392"
    ],
    "placetype": [
      "aat:300006191"
    ],
    "id": 2754299,
    "name:xx": "Wauban Pond"
  }
}
