{
  "type": "FeatureCollection",
  "features": [
    {
      "geometry": {
        "type": "Point",
        "coordinates": [
          -120.4667,
          39.5667
        ]
      },
      "type": "Feature",
      "properties": {
        "hierarchy": [
          "tgn:2449540",
          "tgn:1000001",
          "tgn:7012149",
          "tgn:7007157",
          "tgn:1002894",
          "tgn:7029392"
        ],
        "placetype": [
          "aat:300008706"
        ],
        "id": 2449540,
        "name:xx": "Lincoln Creek"
      }
    },
    {
      "geometry": {
        "type": "Point",
        "coordinates": [
          -106.6167,
          39
        ]
      },
      "type": "Feature",
      "properties": {
        "hierarchy": [
          "tgn:2449541",
          "tgn:1000001",
          "tgn:7012149",
          "tgn:7007158",
          "tgn:2000240",
          "tgn:7029392"
        ],
        "placetype": [
          "aat:300008706"
        ],
        "id": 2449541,
        "name:xx": "Lincoln Creek"
      }
    },
    {
      "geometry": {
        "type": "Point",
        "coordinates": [
          -81.2167,
          31.7667
        ]
      },
      "type": "Feature",
      "properties": {
        "hierarchy": [
          "tgn:2449542",
          "tgn:1000001",
          "tgn:2000306",
          "tgn:7012149",
          "tgn:7007248",
          "tgn:7029392"
        ],
        "placetype": [
          "aat:300008706"
        ],
        "id": 2449542,
        "name:xx": "Lincoln Creek"
      }
    },
    {
      "geometry": {
        "type": "Point",
        "coordinates": [
          -115.2667,
          44.55
        ]
      },
      "type": "Feature",
      "properties": {
        "hierarchy": [
          "tgn:2449543",
          "tgn:1000001",
          "tgn:2000470",
          "tgn:7012149",
          "tgn:7007250",
          "tgn:7029392"
        ],
        "placetype": [
          "aat:300008706"
        ],
        "id": 2449543,
        "name:xx": "Lincoln Creek"
      }
    },
    {
      "geometry": {
        "type": "Point",
        "coordinates": [
          -115.3,
          43.65
        ]
      },
      "type": "Feature",
      "properties": {
        "hierarchy": [
          "tgn:2449544",
          "tgn:1000001",
          "tgn:7012149",
          "tgn:2000471",
          "tgn:7007250",
          "tgn:7029392"
        ],
        "placetype": [
          "aat:300008706"
        ],
        "id": 2449544,
        "name:xx": "Lincoln Creek"
      }
    },
    {
      "geometry": {
        "type": "Point",
        "coordinates": [
          -112.05,
          43.1
        ]
      },
      "type": "Feature",
      "properties": {
        "hierarchy": [
          "tgn:2449545",
          "tgn:1000001",
          "tgn:2000457",
          "tgn:7012149",
          "tgn:7007250",
          "tgn:7029392"
        ],
        "placetype": [
          "aat:300008706"
        ],
        "id": 2449545,
        "name:xx": "Lincoln Creek"
      }
    },
    {
      "geometry": {
        "type": "Point",
        "coordinates": [
          -86.3167,
          39.8167
        ]
      },
      "type": "Feature",
      "properties": {
        "hierarchy": [
          "tgn:2449546",
          "tgn:1000001",
          "tgn:7012149",
          "tgn:7007252",
          "tgn:7029392"
        ],
        "placetype": [
          "aat:300008706"
        ],
        "id": 2449546,
        "name:xx": "Lincoln Creek"
      }
    },
    {
      "geometry": {
        "type": "Point",
        "coordinates": [
          -97,
          39.4167
        ]
      },
      "type": "Feature",
      "properties": {
        "hierarchy": [
          "tgn:2449547",
          "tgn:1000001",
          "tgn:2000673",
          "tgn:7012149",
          "tgn:7007254",
          "tgn:7029392"
        ],
        "placetype": [
          "aat:300008706"
        ],
        "id": 2449547,
        "name:xx": "Lincoln Creek"
      }
    },
    {
      "geometry": {
        "type": "Point",
        "coordinates": [
          -84.6167,
          36.8
        ]
      },
      "type": "Feature",
      "properties": {
        "hierarchy": [
          "tgn:2449548",
          "tgn:1000001",
          "tgn:7012149",
          "tgn:2000850",
          "tgn:7007255",
          "tgn:7029392"
        ],
        "placetype": [
          "aat:300008706"
        ],
        "id": 2449548,
        "name:xx": "Lincoln Creek"
      }
    },
    {
      "geometry": {
        "type": "Point",
        "coordinates": [
          -85.4333,
          43.9333
        ]
      },
      "type": "Feature",
      "properties": {
        "hierarchy": [
          "tgn:2449549",
          "tgn:1000001",
          "tgn:7012149",
          "tgn:2000987",
          "tgn:7007520",
          "tgn:7029392"
        ],
        "placetype": [
          "aat:300008706"
        ],
        "id": 2449549,
        "name:xx": "Lincoln Creek"
      }
    }
  ]
}
