{
  "geometry": {
    "type": "Point",
    "coordinates": [
      31.437359,
      30.433476
    ]
  },
  "type": "Feature",
  "properties": {
    "hierarchy": [
      "tgn:1095235",
      "tgn:7001242",
      "tgn:7016833",
      "tgn:1001113",
      "tgn:7029392"
    ],
    "placetype": [
      "aat:300008347"
    ],
    "name:en": "Al Balāshūn",
    "id": 1095235
  }
}
