{
  "geometry": {
    "type": "Point",
    "coordinates": [
      25.322778,
      37.0675
    ]
  },
  "type": "Feature",
  "properties": {
    "hierarchy": [
      "tgn:7218901",
      "tgn:7011270",
      "tgn:7002674",
      "tgn:1000003",
      "tgn:1000074",
      "tgn:7029392"
    ],
    "placetype": [
      "aat:300011692"
    ],
    "id": 7218901,
    "name:xx": "Kalypsó, Vráchos"
  }
}
