{
  "geometry": {
    "type": "Point",
    "coordinates": [
      -83.8667,
      32.05
    ]
  },
  "type": "Feature",
  "properties": {
    "hierarchy": [
      "tgn:2149789",
      "tgn:1000001",
      "tgn:7012149",
      "tgn:2000337",
      "tgn:7007248",
      "tgn:7029392"
    ],
    "placetype": [
      "aat:300006191"
    ],
    "id": 2149789,
    "name:xx": "Bartenfeld Lake"
  }
}
