{
  "geometry": {
    "type": "Point",
    "coordinates": [
      31.813368,
      26.574766
    ]
  },
  "type": "Feature",
  "properties": {
    "hierarchy": [
      "tgn:7521596",
      "tgn:7001242",
      "tgn:7001311",
      "tgn:7016833",
      "tgn:7029392"
    ],
    "placetype": [
      "aat:300379998"
    ],
    "name:en": "Ab큰 Jilb훮nah, W훮d카",
    "id": 7521596
  }
}
