{
  "geometry": {
    "type": "Point",
    "coordinates": [
      -70.5167,
      41.9167
    ]
  },
  "type": "Feature",
  "properties": {
    "hierarchy": [
      "tgn:2495179",
      "tgn:1000001",
      "tgn:7014423",
      "tgn:7012149",
      "tgn:7007517",
      "tgn:7029392"
    ],
    "placetype": [
      "aat:300132348"
    ],
    "id": 2495179,
    "name:xx": "Mary Ann Rocks"
  }
}
