{
  "geometry": {
    "type": "Point",
    "coordinates": [
      -110.95,
      40.4167
    ]
  },
  "type": "Feature",
  "properties": {
    "hierarchy": [
      "tgn:2307008",
      "tgn:1000001",
      "tgn:7012149",
      "tgn:2002126",
      "tgn:7007827",
      "tgn:7029392"
    ],
    "placetype": [
      "aat:300008706"
    ],
    "id": 2307008,
    "name:xx": "East Fork Little Sand Creek"
  }
}
