{
  "geometry": {
    "type": "Point",
    "coordinates": [
      31.266667,
      29.35
    ]
  },
  "type": "Feature",
  "properties": {
    "hierarchy": [
      "tgn:7526430",
      "tgn:7001242",
      "tgn:7016833",
      "tgn:1001083",
      "tgn:7029392"
    ],
    "placetype": [
      "aat:300005926"
    ],
    "name:en": "S카d카 Khal카l al Ghan훮'im",
    "id": 7526430
  }
}
