{
  "type": "FeatureCollection",
  "features": [
    {
      "geometry": {
        "type": "Point",
        "coordinates": [
          6.583333,
          50.083333
        ]
      },
      "type": "Feature",
      "properties": {
        "hierarchy": [
          "tgn:7204000",
          "tgn:1000003",
          "tgn:7003682",
          "tgn:7000084",
          "tgn:7029392"
        ],
        "placetype": [
          "aat:300008347"
        ],
        "id": 7204000,
        "name:xx": "Bruderholz"
      }
    },
    {
      "geometry": {
        "type": "Point",
        "coordinates": [
          14.7,
          52
        ]
      },
      "type": "Feature",
      "properties": {
        "hierarchy": [
          "tgn:7204001",
          "tgn:7000096",
          "tgn:1000003",
          "tgn:7000084",
          "tgn:7029392"
        ],
        "placetype": [
          "aat:300008347"
        ],
        "id": 7204001,
        "name:xx": "Bresinchen"
      }
    },
    {
      "geometry": {
        "type": "Point",
        "coordinates": [
          14.7,
          51.483333
        ]
      },
      "type": "Feature",
      "properties": {
        "hierarchy": [
          "tgn:7204002",
          "tgn:1000003",
          "tgn:7003685",
          "tgn:7000084",
          "tgn:7029392"
        ],
        "placetype": [
          "aat:300008347"
        ],
        "id": 7204002,
        "name:xx": "Brězyna"
      }
    },
    {
      "geometry": {
        "type": "Point",
        "coordinates": [
          9.166667,
          54.35
        ]
      },
      "type": "Feature",
      "properties": {
        "hierarchy": [
          "tgn:7204003",
          "tgn:1000003",
          "tgn:7003688",
          "tgn:7000084",
          "tgn:7029392"
        ],
        "placetype": [
          "aat:300000206"
        ],
        "id": 7204003,
        "name:xx": "Breshöft"
      }
    },
    {
      "geometry": {
        "type": "Point",
        "coordinates": [
          13.516667,
          53.7
        ]
      },
      "type": "Feature",
      "properties": {
        "hierarchy": [
          "tgn:7204005",
          "tgn:1000003",
          "tgn:7000094",
          "tgn:7000084",
          "tgn:7029392"
        ],
        "placetype": [
          "aat:300008347"
        ],
        "id": 7204005,
        "name:xx": "Bresewitz"
      }
    },
    {
      "geometry": {
        "type": "Point",
        "coordinates": [
          12,
          53.65
        ]
      },
      "type": "Feature",
      "properties": {
        "hierarchy": [
          "tgn:7204006",
          "tgn:1000003",
          "tgn:7000094",
          "tgn:7000084",
          "tgn:7029392"
        ],
        "placetype": [
          "aat:300008699"
        ],
        "id": 7204006,
        "name:xx": "Bresenitz"
      }
    },
    {
      "geometry": {
        "type": "Point",
        "coordinates": [
          11.066667,
          53.033333
        ]
      },
      "type": "Feature",
      "properties": {
        "hierarchy": [
          "tgn:7204007",
          "tgn:1000003",
          "tgn:7003676",
          "tgn:7000084",
          "tgn:7029392"
        ],
        "placetype": [
          "aat:300008347"
        ],
        "id": 7204007,
        "name:xx": "Breselenz"
      }
    },
    {
      "geometry": {
        "type": "Point",
        "coordinates": [
          12.6,
          49.383333
        ]
      },
      "type": "Feature",
      "properties": {
        "hierarchy": [
          "tgn:7204008",
          "tgn:7003669",
          "tgn:1000003",
          "tgn:7000084",
          "tgn:7029392"
        ],
        "placetype": [
          "aat:300008777"
        ],
        "id": 7204008,
        "name:xx": "Bresel-Berg"
      }
    },
    {
      "geometry": {
        "type": "Point",
        "coordinates": [
          11.3,
          53.35
        ]
      },
      "type": "Feature",
      "properties": {
        "hierarchy": [
          "tgn:7204009",
          "tgn:1000003",
          "tgn:7000094",
          "tgn:7000084",
          "tgn:7029392"
        ],
        "placetype": [
          "aat:300008347"
        ],
        "id": 7204009,
        "name:xx": "Bresegard"
      }
    }
  ]
}
