{
  "geometry": {
    "type": "Point",
    "coordinates": [
      -78.1833,
      33.9167
    ]
  },
  "type": "Feature",
  "properties": {
    "hierarchy": [
      "tgn:2585164",
      "tgn:1000001",
      "tgn:2001472",
      "tgn:7012149",
      "tgn:7007709",
      "tgn:7029392"
    ],
    "placetype": [
      "aat:300008850"
    ],
    "id": 2585164,
    "name:xx": "Pinner Point"
  }
}
