{
  "geometry": {
    "type": "Point",
    "coordinates": [
      -39.75,
      -15.1833
    ]
  },
  "type": "Feature",
  "properties": {
    "hierarchy": [
      "tgn:1122973",
      "tgn:1001834",
      "tgn:1000047",
      "tgn:7002455",
      "tgn:1000002",
      "tgn:7029392"
    ],
    "placetype": [
      "aat:300008707"
    ],
    "id": 1122973,
    "name:xx": "Colônia"
  }
}
