{
  "geometry": {
    "type": "Point",
    "coordinates": [
      -76.8333,
      37.85
    ]
  },
  "type": "Feature",
  "properties": {
    "hierarchy": [
      "tgn:2319122",
      "tgn:1000001",
      "tgn:7012149",
      "tgn:1002362",
      "tgn:7007919",
      "tgn:7029392"
    ],
    "placetype": [
      "aat:300006191"
    ],
    "id": 2319122,
    "name:xx": "Essex Millpond"
  }
}
