{
  "geometry": {
    "type": "Point",
    "coordinates": [
      75.566667,
      11.966667
    ]
  },
  "type": "Feature",
  "properties": {
    "hierarchy": [
      "tgn:7573540",
      "tgn:1000004",
      "tgn:7000198",
      "tgn:1001886",
      "tgn:7029392"
    ],
    "placetype": [
      "aat:300008347"
    ],
    "name:en": "Irikkūr",
    "id": 7573540
  }
}
