{
  "geometry": {
    "type": "Point",
    "coordinates": [
      33.085663,
      23.298947
    ]
  },
  "type": "Feature",
  "properties": {
    "hierarchy": [
      "tgn:7539092",
      "tgn:7001242",
      "tgn:7016833",
      "tgn:7000122",
      "tgn:7029392"
    ],
    "placetype": [
      "aat:300379998"
    ],
    "name:en": "M훮r카yah, W훮d카",
    "id": 7539092
  }
}
