{
  "type": "FeatureCollection",
  "features": [
    {
      "geometry": {
        "type": "Point",
        "coordinates": [
          -81.3,
          37.4167
        ]
      },
      "type": "Feature",
      "properties": {
        "hierarchy": [
          "tgn:2584960",
          "tgn:1000001",
          "tgn:7012149",
          "tgn:2002304",
          "tgn:7013961",
          "tgn:7029392"
        ],
        "placetype": [
          "aat:300008706"
        ],
        "id": 2584960,
        "name:xx": "Pinnacle Creek"
      }
    },
    {
      "geometry": {
        "type": "Point",
        "coordinates": [
          -108.8167,
          41.4667
        ]
      },
      "type": "Feature",
      "properties": {
        "hierarchy": [
          "tgn:2584961",
          "tgn:1000001",
          "tgn:7012149",
          "tgn:2002383",
          "tgn:7007923",
          "tgn:7029392"
        ],
        "placetype": [
          "aat:300008761"
        ],
        "id": 2584961,
        "name:xx": "Pinnacle Draw"
      }
    },
    {
      "geometry": {
        "type": "Point",
        "coordinates": [
          -140.3167,
          60.1333
        ]
      },
      "type": "Feature",
      "properties": {
        "hierarchy": [
          "tgn:2584962",
          "tgn:7006450",
          "tgn:1000001",
          "tgn:7012149",
          "tgn:7030574",
          "tgn:7029392"
        ],
        "placetype": [
          "aat:300008835"
        ],
        "id": 2584962,
        "name:xx": "Pinnacle Glacier"
      }
    },
    {
      "geometry": {
        "type": "Point",
        "coordinates": [
          -121.5167,
          46.2
        ]
      },
      "type": "Feature",
      "properties": {
        "hierarchy": [
          "tgn:2584963",
          "tgn:1000001",
          "tgn:7012149",
          "tgn:7007920",
          "tgn:7029392"
        ],
        "placetype": [
          "aat:300008835"
        ],
        "id": 2584963,
        "name:xx": "Pinnacle Glacier"
      }
    },
    {
      "geometry": {
        "type": "Point",
        "coordinates": [
          -121.7167,
          46.75
        ]
      },
      "type": "Feature",
      "properties": {
        "hierarchy": [
          "tgn:2584964",
          "tgn:1000001",
          "tgn:7012149",
          "tgn:1002594",
          "tgn:7007920",
          "tgn:7029392"
        ],
        "placetype": [
          "aat:300008835"
        ],
        "id": 2584964,
        "name:xx": "Pinnacle Glacier"
      }
    },
    {
      "geometry": {
        "type": "Point",
        "coordinates": [
          -166.2,
          65.9167
        ]
      },
      "type": "Feature",
      "properties": {
        "hierarchy": [
          "tgn:2584965",
          "tgn:7006450",
          "tgn:1000001",
          "tgn:7012149",
          "tgn:2000079",
          "tgn:7029392"
        ],
        "placetype": [
          "aat:300008761"
        ],
        "id": 2584965,
        "name:xx": "Pinnacle Gulch"
      }
    },
    {
      "geometry": {
        "type": "Point",
        "coordinates": [
          -82.0167,
          34.9667
        ]
      },
      "type": "Feature",
      "properties": {
        "hierarchy": [
          "tgn:2584966",
          "tgn:1000001",
          "tgn:7012149",
          "tgn:2001766",
          "tgn:7007712",
          "tgn:7029392"
        ],
        "placetype": [
          "aat:300008347"
        ],
        "id": 2584966,
        "name:xx": "Pinnacle Heights"
      }
    },
    {
      "geometry": {
        "type": "Point",
        "coordinates": [
          -70.6667,
          41.9
        ]
      },
      "type": "Feature",
      "properties": {
        "hierarchy": [
          "tgn:2584967",
          "tgn:1000001",
          "tgn:7014423",
          "tgn:7012149",
          "tgn:7007517",
          "tgn:7029392"
        ],
        "placetype": [
          "aat:300008798"
        ],
        "id": 2584967,
        "name:xx": "Pinnacle Hill"
      }
    },
    {
      "geometry": {
        "type": "Point",
        "coordinates": [
          -71.2,
          42.6167
        ]
      },
      "type": "Feature",
      "properties": {
        "hierarchy": [
          "tgn:2584968",
          "tgn:1000001",
          "tgn:1002665",
          "tgn:7012149",
          "tgn:7007517",
          "tgn:7029392"
        ],
        "placetype": [
          "aat:300008798"
        ],
        "id": 2584968,
        "name:xx": "Pinnacle Hill"
      }
    }
  ]
}
