{
  "geometry": {
    "type": "Point",
    "coordinates": [
      -105.1333,
      38.1833
    ]
  },
  "type": "Feature",
  "properties": {
    "hierarchy": [
      "tgn:2590064",
      "tgn:1000001",
      "tgn:7012149",
      "tgn:2000205",
      "tgn:7007158",
      "tgn:7029392"
    ],
    "placetype": [
      "aat:300008761"
    ],
    "id": 2590064,
    "name:xx": "Poison Gulch"
  }
}
