{
  "geometry": {
    "type": "Point",
    "coordinates": [
      135.8167,
      35.3833
    ]
  },
  "type": "Feature",
  "properties": {
    "hierarchy": [
      "tgn:1105002",
      "tgn:7016674",
      "tgn:1000004",
      "tgn:1000120",
      "tgn:7029392"
    ],
    "placetype": [
      "aat:300008795"
    ],
    "id": 1105002,
    "name:xx": "Hyakuri-ga-dake"
  }
}
