{
  "geometry": {
    "type": "Point",
    "coordinates": [
      105.0833,
      43.0833
    ]
  },
  "type": "Feature",
  "properties": {
    "hierarchy": [
      "tgn:1103377",
      "tgn:1000004",
      "tgn:7029392"
    ],
    "placetype": [
      "aat:300008916"
    ],
    "id": 1103377,
    "name:xx": "Gobi"
  }
}
