{
  "geometry": {
    "type": "Point",
    "coordinates": [
      -83.5167,
      32.8333
    ]
  },
  "type": "Feature",
  "properties": {
    "hierarchy": [
      "tgn:2372509",
      "tgn:1000001",
      "tgn:2000302",
      "tgn:7012149",
      "tgn:7007248",
      "tgn:7029392"
    ],
    "placetype": [
      "aat:300008699"
    ],
    "id": 2372509,
    "name:xx": "Hall Branch"
  }
}
