{
  "type": "FeatureCollection",
  "features": [
    {
      "geometry": {
        "type": "Point",
        "coordinates": [
          -105.25,
          40.55
        ]
      },
      "type": "Feature",
      "properties": {
        "hierarchy": [
          "tgn:2375841",
          "tgn:1000001",
          "tgn:7012149",
          "tgn:2000226",
          "tgn:7007158",
          "tgn:7029392"
        ],
        "placetype": [
          "aat:300008761"
        ],
        "id": 2375841,
        "name:xx": "Happy Hollow Gulch"
      }
    },
    {
      "geometry": {
        "type": "Point",
        "coordinates": [
          -107.9333,
          38.8833
        ]
      },
      "type": "Feature",
      "properties": {
        "hierarchy": [
          "tgn:2375842",
          "tgn:1000001",
          "tgn:7012149",
          "tgn:2000206",
          "tgn:7007158",
          "tgn:7029392"
        ],
        "placetype": [
          "aat:300008761"
        ],
        "id": 2375842,
        "name:xx": "Happy Hollow Gulch"
      }
    },
    {
      "geometry": {
        "type": "Point",
        "coordinates": [
          -86.1,
          39.15
        ]
      },
      "type": "Feature",
      "properties": {
        "hierarchy": [
          "tgn:2375843",
          "tgn:1000001",
          "tgn:1002209",
          "tgn:7012149",
          "tgn:7007252",
          "tgn:7029392"
        ],
        "placetype": [
          "aat:300006191"
        ],
        "id": 2375843,
        "name:xx": "Happy Hollow Lake"
      }
    },
    {
      "geometry": {
        "type": "Point",
        "coordinates": [
          -95.0333,
          39.3333
        ]
      },
      "type": "Feature",
      "properties": {
        "hierarchy": [
          "tgn:2375844",
          "tgn:1000001",
          "tgn:7012149",
          "tgn:2000711",
          "tgn:7007254",
          "tgn:7029392"
        ],
        "placetype": [
          "aat:300006191"
        ],
        "id": 2375844,
        "name:xx": "Happy Hollow Lake"
      }
    },
    {
      "geometry": {
        "type": "Point",
        "coordinates": [
          -94.8167,
          39.2833
        ]
      },
      "type": "Feature",
      "properties": {
        "hierarchy": [
          "tgn:2375845",
          "tgn:1000001",
          "tgn:7012149",
          "tgn:2001231",
          "tgn:7007523",
          "tgn:7029392"
        ],
        "placetype": [
          "aat:300006191"
        ],
        "id": 2375845,
        "name:xx": "Happy Hollow Lake"
      }
    },
    {
      "geometry": {
        "type": "Point",
        "coordinates": [
          -95.4667,
          40.3167
        ]
      },
      "type": "Feature",
      "properties": {
        "hierarchy": [
          "tgn:2375846",
          "tgn:2001169",
          "tgn:1000001",
          "tgn:7012149",
          "tgn:7007523",
          "tgn:7029392"
        ],
        "placetype": [
          "aat:300006191"
        ],
        "id": 2375846,
        "name:xx": "Happy Hollow Lake"
      }
    },
    {
      "geometry": {
        "type": "Point",
        "coordinates": [
          -94.3833,
          37.8
        ]
      },
      "type": "Feature",
      "properties": {
        "hierarchy": [
          "tgn:2375847",
          "tgn:1000001",
          "tgn:7012149",
          "tgn:2001253",
          "tgn:7007523",
          "tgn:7029392"
        ],
        "placetype": [
          "aat:300006191"
        ],
        "id": 2375847,
        "name:xx": "Happy Hollow Lake"
      }
    },
    {
      "geometry": {
        "type": "Point",
        "coordinates": [
          -78.9333,
          37.9833
        ]
      },
      "type": "Feature",
      "properties": {
        "hierarchy": [
          "tgn:2375848",
          "tgn:2002142",
          "tgn:1000001",
          "tgn:7012149",
          "tgn:7007919",
          "tgn:7029392"
        ],
        "placetype": [
          "aat:300006191"
        ],
        "id": 2375848,
        "name:xx": "Happy Hollow Lake"
      }
    },
    {
      "geometry": {
        "type": "Point",
        "coordinates": [
          -71.3833,
          41.9
        ]
      },
      "type": "Feature",
      "properties": {
        "hierarchy": [
          "tgn:2375849",
          "tgn:1002808",
          "tgn:1000001",
          "tgn:7012149",
          "tgn:7007711",
          "tgn:7029392"
        ],
        "placetype": [
          "aat:300006191"
        ],
        "id": 2375849,
        "name:xx": "Happy Hollow Pond"
      }
    }
  ]
}
