{
  "geometry": {
    "type": "Point",
    "coordinates": [
      -78.3167,
      38.65
    ]
  },
  "type": "Feature",
  "properties": {
    "hierarchy": [
      "tgn:2570123",
      "tgn:1000001",
      "tgn:7012149",
      "tgn:2002178",
      "tgn:7007919",
      "tgn:7029392"
    ],
    "placetype": [
      "aat:300008699"
    ],
    "id": 2570123,
    "name:xx": "Pass Run"
  }
}
