{
  "geometry": {
    "type": "Point",
    "coordinates": [
      -93.8167,
      34.3333
    ]
  },
  "type": "Feature",
  "properties": {
    "hierarchy": [
      "tgn:2394542",
      "tgn:1000001",
      "tgn:7016172",
      "tgn:7012149",
      "tgn:7029392"
    ],
    "placetype": [
      "aat:300008798"
    ],
    "id": 2394542,
    "name:xx": "Hogpen Mountain"
  }
}
