{
  "geometry": {
    "type": "Point",
    "coordinates": [
      -88.95,
      37.3333
    ]
  },
  "type": "Feature",
  "properties": {
    "hierarchy": [
      "tgn:2371494",
      "tgn:1000001",
      "tgn:7012149",
      "tgn:2000524",
      "tgn:7007251",
      "tgn:7029392"
    ],
    "placetype": [
      "aat:300008798"
    ],
    "id": 2371494,
    "name:xx": "Hairy Hill"
  }
}
