{
  "type": "FeatureCollection",
  "features": [
    {
      "geometry": {
        "type": "Point",
        "coordinates": [
          -74.416667,
          -49.216667
        ]
      },
      "type": "Feature",
      "properties": {
        "hierarchy": [
          "tgn:7319410",
          "tgn:1001702",
          "tgn:1000049",
          "tgn:1000002",
          "tgn:7029392"
        ],
        "placetype": [
          "aat:300386846"
        ],
        "id": 7319410,
        "name:xx": "Álvaro, Punta"
      }
    },
    {
      "geometry": {
        "type": "Point",
        "coordinates": [
          -74.6,
          -50.8
        ]
      },
      "type": "Feature",
      "properties": {
        "hierarchy": [
          "tgn:7319411",
          "tgn:1001702",
          "tgn:1000049",
          "tgn:1000002",
          "tgn:7029392"
        ],
        "placetype": [
          "aat:300386846"
        ],
        "id": 7319411,
        "name:xx": "Álvaro, Cabo"
      }
    },
    {
      "geometry": {
        "type": "Point",
        "coordinates": [
          -72.766667,
          -45.416667
        ]
      },
      "type": "Feature",
      "properties": {
        "hierarchy": [
          "tgn:7319412",
          "tgn:1001623",
          "tgn:1000049",
          "tgn:1000002",
          "tgn:7029392"
        ],
        "placetype": [
          "aat:300008699"
        ],
        "id": 7319412,
        "name:xx": "Álvarez, Río"
      }
    },
    {
      "geometry": {
        "type": "Point",
        "coordinates": [
          -73.766667,
          -48.116667
        ]
      },
      "type": "Feature",
      "properties": {
        "hierarchy": [
          "tgn:7319413",
          "tgn:1001623",
          "tgn:1000049",
          "tgn:1000002",
          "tgn:7029392"
        ],
        "placetype": [
          "aat:300132317"
        ],
        "id": 7319413,
        "name:xx": "Álvarez, Puerto"
      }
    },
    {
      "geometry": {
        "type": "Point",
        "coordinates": [
          -72.866667,
          -51.866667
        ]
      },
      "type": "Feature",
      "properties": {
        "hierarchy": [
          "tgn:7319414",
          "tgn:1001702",
          "tgn:1000049",
          "tgn:1000002",
          "tgn:7029392"
        ],
        "placetype": [
          "aat:300387036"
        ],
        "id": 7319414,
        "name:xx": "Álvarez, Bajo"
      }
    },
    {
      "geometry": {
        "type": "Point",
        "coordinates": [
          -69.95,
          -34.183333
        ]
      },
      "type": "Feature",
      "properties": {
        "hierarchy": [
          "tgn:7319415",
          "tgn:1001708",
          "tgn:1000049",
          "tgn:1000002",
          "tgn:7029392"
        ],
        "placetype": [
          "aat:300008699"
        ],
        "id": 7319415,
        "name:xx": "Alvarado, Río"
      }
    },
    {
      "geometry": {
        "type": "Point",
        "coordinates": [
          -70.666667,
          -32.083333
        ]
      },
      "type": "Feature",
      "properties": {
        "hierarchy": [
          "tgn:7319416",
          "tgn:1001657",
          "tgn:1000049",
          "tgn:1000002",
          "tgn:7029392"
        ],
        "placetype": [
          "aat:300008795"
        ],
        "id": 7319416,
        "name:xx": "Alvarado, Morro"
      }
    },
    {
      "geometry": {
        "type": "Point",
        "coordinates": [
          -73.55,
          -45.2
        ]
      },
      "type": "Feature",
      "properties": {
        "hierarchy": [
          "tgn:7319417",
          "tgn:1001623",
          "tgn:1000049",
          "tgn:1000002",
          "tgn:7029392"
        ],
        "placetype": [
          "aat:300008791"
        ],
        "id": 7319417,
        "name:xx": "Alvarado, Isla"
      }
    },
    {
      "geometry": {
        "type": "Point",
        "coordinates": [
          -75.266667,
          -48.15
        ]
      },
      "type": "Feature",
      "properties": {
        "hierarchy": [
          "tgn:7319418",
          "tgn:1001623",
          "tgn:1000049",
          "tgn:1000002",
          "tgn:7029392"
        ],
        "placetype": [
          "aat:300008676"
        ],
        "id": 7319418,
        "name:xx": "Alvarado, Fiordo"
      }
    },
    {
      "geometry": {
        "type": "Point",
        "coordinates": [
          -73.433333,
          -41.133333
        ]
      },
      "type": "Feature",
      "properties": {
        "hierarchy": [
          "tgn:7319419",
          "tgn:1001699",
          "tgn:1000049",
          "tgn:1000002",
          "tgn:7029392"
        ],
        "placetype": [
          "aat:300008699"
        ],
        "id": 7319419,
        "name:xx": "Alvarado, Estero"
      }
    }
  ]
}
