{
  "geometry": {
    "type": "Point",
    "coordinates": [
      124.1333,
      39.8667
    ]
  },
  "type": "Feature",
  "properties": {
    "hierarchy": [
      "tgn:1138915",
      "tgn:1000004",
      "tgn:1001390",
      "tgn:1000111",
      "tgn:7029392"
    ],
    "placetype": [
      "aat:300008347"
    ],
    "id": 1138915,
    "name:xx": "Donggou"
  }
}
