{
  "geometry": {
    "type": "Point",
    "coordinates": [
      -84.2167,
      33.6167
    ]
  },
  "type": "Feature",
  "properties": {
    "hierarchy": [
      "tgn:2494374",
      "tgn:1000001",
      "tgn:7012149",
      "tgn:2000366",
      "tgn:7007248",
      "tgn:7029392"
    ],
    "placetype": [
      "aat:300008706"
    ],
    "id": 2494374,
    "name:xx": "Martin Creek"
  }
}
