{
  "geometry": {
    "type": "Point",
    "coordinates": [
      71.4167,
      50.85
    ]
  },
  "type": "Feature",
  "properties": {
    "hierarchy": [
      "tgn:1058940",
      "tgn:7012935",
      "tgn:1000004",
      "tgn:7014786",
      "tgn:7029392"
    ],
    "placetype": [
      "aat:300008347"
    ],
    "id": 1058940,
    "name:xx": "Rozhdestvenka"
  }
}
