{
  "geometry": {
    "type": "Point",
    "coordinates": [
      -106.2667,
      39.3667
    ]
  },
  "type": "Feature",
  "properties": {
    "hierarchy": [
      "tgn:2584464",
      "tgn:1000001",
      "tgn:7012149",
      "tgn:2000210",
      "tgn:7007158",
      "tgn:7029392"
    ],
    "placetype": [
      "aat:300008761"
    ],
    "id": 2584464,
    "name:xx": "Piney Gulch"
  }
}
