{
  "geometry": {
    "type": "Point",
    "coordinates": [
      41.6333,
      53.2333
    ]
  },
  "type": "Feature",
  "properties": {
    "hierarchy": [
      "tgn:1058087",
      "tgn:1000004",
      "tgn:1003417",
      "tgn:7018214",
      "tgn:7002435",
      "tgn:7029392"
    ],
    "placetype": [
      "aat:300008347"
    ],
    "id": 1058087,
    "name:xx": "Ot-yassy"
  }
}
