{
  "type": "FeatureCollection",
  "features": [
    {
      "geometry": {
        "type": "Point",
        "coordinates": [
          31.433333,
          30.983333
        ]
      },
      "type": "Feature",
      "properties": {
        "hierarchy": [
          "tgn:7533480",
          "tgn:7001242",
          "tgn:1001059",
          "tgn:7016833",
          "tgn:7029392"
        ],
        "placetype": [
          "aat:300008347"
        ],
        "name:en": "Jāliyah",
        "id": 7533480
      }
    },
    {
      "geometry": {
        "type": "Point",
        "coordinates": [
          30.283333,
          31.05
        ]
      },
      "type": "Feature",
      "properties": {
        "hierarchy": [
          "tgn:7533481",
          "tgn:7001242",
          "tgn:1001075",
          "tgn:7016833",
          "tgn:7029392"
        ],
        "placetype": [
          "aat:300000206"
        ],
        "name:en": "'Izbat Jalīlah",
        "id": 7533481
      }
    },
    {
      "geometry": {
        "type": "Point",
        "coordinates": [
          30.75,
          28.5
        ]
      },
      "type": "Feature",
      "properties": {
        "hierarchy": [
          "tgn:7533482",
          "tgn:7001242",
          "tgn:7016833",
          "tgn:1001087",
          "tgn:7029392"
        ],
        "placetype": [
          "aat:300007783"
        ],
        "name:en": "Jalf",
        "id": 7533482
      }
    },
    {
      "geometry": {
        "type": "Point",
        "coordinates": [
          31.638509,
          26.739809
        ]
      },
      "type": "Feature",
      "properties": {
        "hierarchy": [
          "tgn:7533483",
          "tgn:7001242",
          "tgn:7001311",
          "tgn:7016833",
          "tgn:7029392"
        ],
        "placetype": [
          "aat:300379998"
        ],
        "name:en": "Jalāwīyah, Wādī al",
        "id": 7533483
      }
    },
    {
      "geometry": {
        "type": "Point",
        "coordinates": [
          31.633333,
          26.75
        ]
      },
      "type": "Feature",
      "properties": {
        "hierarchy": [
          "tgn:7533484",
          "tgn:7001242",
          "tgn:7001311",
          "tgn:7016833",
          "tgn:7029392"
        ],
        "placetype": [
          "aat:300259572"
        ],
        "name:en": "Jalāwīyah, Naqb al",
        "id": 7533484
      }
    },
    {
      "geometry": {
        "type": "Point",
        "coordinates": [
          30.25,
          31.15
        ]
      },
      "type": "Feature",
      "properties": {
        "hierarchy": [
          "tgn:7533485",
          "tgn:7001242",
          "tgn:1001075",
          "tgn:7016833",
          "tgn:7029392"
        ],
        "placetype": [
          "aat:300000206"
        ],
        "name:en": "'Izbat Jalāmīs",
        "id": 7533485
      }
    },
    {
      "geometry": {
        "type": "Point",
        "coordinates": [
          30.166667,
          31.1
        ]
      },
      "type": "Feature",
      "properties": {
        "hierarchy": [
          "tgn:7533487",
          "tgn:7001242",
          "tgn:1001075",
          "tgn:7016833",
          "tgn:7029392"
        ],
        "placetype": [
          "aat:300000206"
        ],
        "name:en": "'Izbat Lūmbārdū",
        "id": 7533487
      }
    },
    {
      "geometry": {
        "type": "Point",
        "coordinates": [
          31.05,
          30.066667
        ]
      },
      "type": "Feature",
      "properties": {
        "hierarchy": [
          "tgn:7533488",
          "tgn:7001242",
          "tgn:7016833",
          "tgn:7029392"
        ],
        "placetype": [
          "aat:300379998"
        ],
        "id": 7533488,
        "name:xx": "Lu'lu', Wādī al"
      }
    },
    {
      "geometry": {
        "type": "Point",
        "coordinates": [
          32.420727,
          31.023841
        ]
      },
      "type": "Feature",
      "properties": {
        "hierarchy": [
          "tgn:7533489",
          "tgn:7001242",
          "tgn:7016833",
          "tgn:1001123",
          "tgn:7029392"
        ],
        "placetype": [
          "aat:300008777"
        ],
        "id": 7533489,
        "name:xx": "Lūlī, Tall al"
      }
    }
  ]
}
