{
  "geometry": {
    "type": "Point",
    "coordinates": [
      -111.35,
      48.8333
    ]
  },
  "type": "Feature",
  "properties": {
    "hierarchy": [
      "tgn:2656697",
      "tgn:1000001",
      "tgn:7012149",
      "tgn:2001310",
      "tgn:7007524",
      "tgn:7029392"
    ],
    "placetype": [
      "aat:300008706"
    ],
    "id": 2656697,
    "name:xx": "Sheep Creek"
  }
}
