{
  "type": "FeatureCollection",
  "features": [
    {
      "geometry": {
        "type": "Point",
        "coordinates": [
          -95.75,
          46.7
        ]
      },
      "type": "Feature",
      "properties": {
        "hierarchy": [
          "tgn:2329340",
          "tgn:1000001",
          "tgn:7012149",
          "tgn:2001054",
          "tgn:7007521",
          "tgn:7029392"
        ],
        "placetype": [
          "aat:300008680"
        ],
        "id": 2329340,
        "name:xx": "Five Lake"
      }
    },
    {
      "geometry": {
        "type": "Point",
        "coordinates": [
          -120.2333,
          39.1667
        ]
      },
      "type": "Feature",
      "properties": {
        "hierarchy": [
          "tgn:2329341",
          "tgn:1000001",
          "tgn:7012149",
          "tgn:7007157",
          "tgn:1002791",
          "tgn:7029392"
        ],
        "placetype": [
          "aat:300008680"
        ],
        "id": 2329341,
        "name:xx": "Five Lakes"
      }
    },
    {
      "geometry": {
        "type": "Point",
        "coordinates": [
          -93.55,
          29.9167
        ]
      },
      "type": "Feature",
      "properties": {
        "hierarchy": [
          "tgn:2329342",
          "tgn:1000001",
          "tgn:7020676",
          "tgn:7012149",
          "tgn:7007256",
          "tgn:7029392"
        ],
        "placetype": [
          "aat:300008680"
        ],
        "id": 2329342,
        "name:xx": "Five Lakes"
      }
    },
    {
      "geometry": {
        "type": "Point",
        "coordinates": [
          -83.2333,
          43.1333
        ]
      },
      "type": "Feature",
      "properties": {
        "hierarchy": [
          "tgn:2329343",
          "tgn:1000001",
          "tgn:7012149",
          "tgn:1002576",
          "tgn:7007520",
          "tgn:7029392"
        ],
        "placetype": [
          "aat:300008680"
        ],
        "id": 2329343,
        "name:xx": "Five Lakes"
      }
    },
    {
      "geometry": {
        "type": "Point",
        "coordinates": [
          -84.7,
          45.0333
        ]
      },
      "type": "Feature",
      "properties": {
        "hierarchy": [
          "tgn:2329344",
          "tgn:1000001",
          "tgn:7012149",
          "tgn:2000989",
          "tgn:7007520",
          "tgn:7029392"
        ],
        "placetype": [
          "aat:300008680"
        ],
        "id": 2329344,
        "name:xx": "Five Lakes"
      }
    },
    {
      "geometry": {
        "type": "Point",
        "coordinates": [
          -84.8,
          43.8667
        ]
      },
      "type": "Feature",
      "properties": {
        "hierarchy": [
          "tgn:2329345",
          "tgn:1000001",
          "tgn:2000953",
          "tgn:7012149",
          "tgn:7007520",
          "tgn:7029392"
        ],
        "placetype": [
          "aat:300008680"
        ],
        "id": 2329345,
        "name:xx": "Five Lakes"
      }
    },
    {
      "geometry": {
        "type": "Point",
        "coordinates": [
          -110.6833,
          45.1
        ]
      },
      "type": "Feature",
      "properties": {
        "hierarchy": [
          "tgn:2329346",
          "tgn:1000001",
          "tgn:7012149",
          "tgn:2001293",
          "tgn:7007524",
          "tgn:7029392"
        ],
        "placetype": [
          "aat:300008680"
        ],
        "id": 2329346,
        "name:xx": "Five Lakes"
      }
    },
    {
      "geometry": {
        "type": "Point",
        "coordinates": [
          -111.5333,
          38.05
        ]
      },
      "type": "Feature",
      "properties": {
        "hierarchy": [
          "tgn:2329347",
          "tgn:1000001",
          "tgn:2002109",
          "tgn:7012149",
          "tgn:7007827",
          "tgn:7029392"
        ],
        "placetype": [
          "aat:300008680"
        ],
        "id": 2329347,
        "name:xx": "Five Lakes"
      }
    },
    {
      "geometry": {
        "type": "Point",
        "coordinates": [
          -118.9167,
          48.0667
        ]
      },
      "type": "Feature",
      "properties": {
        "hierarchy": [
          "tgn:2329348",
          "tgn:1000001",
          "tgn:7012149",
          "tgn:1002742",
          "tgn:7007920",
          "tgn:7029392"
        ],
        "placetype": [
          "aat:300008680"
        ],
        "id": 2329348,
        "name:xx": "Five Lakes"
      }
    },
    {
      "geometry": {
        "type": "Point",
        "coordinates": [
          -120.55,
          39.4
        ]
      },
      "type": "Feature",
      "properties": {
        "hierarchy": [
          "tgn:2329349",
          "tgn:1000001",
          "tgn:7012149",
          "tgn:7007157",
          "tgn:1002710",
          "tgn:7029392"
        ],
        "placetype": [
          "aat:300386845"
        ],
        "id": 2329349,
        "name:xx": "Five Lakes Basin"
      }
    }
  ]
}
