{
  "geometry": {
    "type": "Point",
    "coordinates": [
      -82.0333,
      38.3667
    ]
  },
  "type": "Feature",
  "properties": {
    "hierarchy": [
      "tgn:2485681",
      "tgn:1000001",
      "tgn:7012149",
      "tgn:2002289",
      "tgn:7013961",
      "tgn:7029392"
    ],
    "placetype": [
      "aat:300008699"
    ],
    "id": 2485681,
    "name:xx": "Laywell Branch"
  }
}
