{
  "type": "FeatureCollection",
  "features": [
    {
      "geometry": {
        "type": "Point",
        "coordinates": [
          -5.616667,
          43.45
        ]
      },
      "type": "Feature",
      "properties": {
        "hierarchy": [
          "tgn:7328530",
          "tgn:7008911",
          "tgn:1000003",
          "tgn:7002763",
          "tgn:1000095",
          "tgn:7029392"
        ],
        "placetype": [
          "aat:300008347"
        ],
        "id": 7328530,
        "name:xx": "Quintana"
      }
    },
    {
      "geometry": {
        "type": "Point",
        "coordinates": [
          -4.85,
          43.416667
        ]
      },
      "type": "Feature",
      "properties": {
        "hierarchy": [
          "tgn:7328531",
          "tgn:7008911",
          "tgn:1000003",
          "tgn:7002763",
          "tgn:1000095",
          "tgn:7029392"
        ],
        "placetype": [
          "aat:300008347"
        ],
        "id": 7328531,
        "name:xx": "Quintana"
      }
    },
    {
      "geometry": {
        "type": "Point",
        "coordinates": [
          -6.3,
          43.266667
        ]
      },
      "type": "Feature",
      "properties": {
        "hierarchy": [
          "tgn:7328532",
          "tgn:7008911",
          "tgn:1000003",
          "tgn:7002763",
          "tgn:1000095",
          "tgn:7029392"
        ],
        "placetype": [
          "aat:300008347"
        ],
        "id": 7328532,
        "name:xx": "Quintana"
      }
    },
    {
      "geometry": {
        "type": "Point",
        "coordinates": [
          -3.983333,
          43.233333
        ]
      },
      "type": "Feature",
      "properties": {
        "hierarchy": [
          "tgn:7328533",
          "tgn:7002760",
          "tgn:1000003",
          "tgn:1000095",
          "tgn:7029392"
        ],
        "placetype": [
          "aat:300008347"
        ],
        "id": 7328533,
        "name:xx": "Quintana"
      }
    },
    {
      "geometry": {
        "type": "Point",
        "coordinates": [
          -4.05,
          43.016667
        ]
      },
      "type": "Feature",
      "properties": {
        "hierarchy": [
          "tgn:7328534",
          "tgn:7002760",
          "tgn:1000003",
          "tgn:1000095",
          "tgn:7029392"
        ],
        "placetype": [
          "aat:300008347"
        ],
        "id": 7328534,
        "name:xx": "Quintana"
      }
    },
    {
      "geometry": {
        "type": "Point",
        "coordinates": [
          -3.666667,
          42.7
        ]
      },
      "type": "Feature",
      "properties": {
        "hierarchy": [
          "tgn:7328535",
          "tgn:7002810",
          "tgn:7001158",
          "tgn:1000003",
          "tgn:1000095",
          "tgn:7029392"
        ],
        "placetype": [
          "aat:300008347"
        ],
        "id": 7328535,
        "name:xx": "Quintana"
      }
    },
    {
      "geometry": {
        "type": "Point",
        "coordinates": [
          -2.477205,
          42.658077
        ]
      },
      "type": "Feature",
      "properties": {
        "hierarchy": [
          "tgn:7328536",
          "tgn:7007088",
          "tgn:1000003",
          "tgn:7009604",
          "tgn:1000095",
          "tgn:7029392"
        ],
        "placetype": [
          "aat:300008347"
        ],
        "id": 7328536,
        "name:xx": "Quintana"
      }
    },
    {
      "geometry": {
        "type": "Point",
        "coordinates": [
          -3.05,
          42.416667
        ]
      },
      "type": "Feature",
      "properties": {
        "hierarchy": [
          "tgn:7328537",
          "tgn:7002827",
          "tgn:1000003",
          "tgn:7002789",
          "tgn:1000095",
          "tgn:7029392"
        ],
        "placetype": [
          "aat:300008347"
        ],
        "id": 7328537,
        "name:xx": "Quintana"
      }
    },
    {
      "geometry": {
        "type": "Point",
        "coordinates": [
          -3.516667,
          40.466667
        ]
      },
      "type": "Feature",
      "properties": {
        "hierarchy": [
          "tgn:7328538",
          "tgn:7010420",
          "tgn:1000003",
          "tgn:7002795",
          "tgn:1000095",
          "tgn:7029392"
        ],
        "placetype": [
          "aat:300008347"
        ],
        "id": 7328538,
        "name:xx": "Quintana"
      }
    },
    {
      "geometry": {
        "type": "Point",
        "coordinates": [
          -4.866667,
          37.7
        ]
      },
      "type": "Feature",
      "properties": {
        "hierarchy": [
          "tgn:7328539",
          "tgn:7002758",
          "tgn:7002817",
          "tgn:1000003",
          "tgn:1000095",
          "tgn:7029392"
        ],
        "placetype": [
          "aat:300008347"
        ],
        "id": 7328539,
        "name:xx": "Quintana"
      }
    }
  ]
}
