{
  "geometry": {
    "type": "Point",
    "coordinates": [
      54.7167,
      57.9333
    ]
  },
  "type": "Feature",
  "properties": {
    "hierarchy": [
      "tgn:1057868",
      "tgn:1000004",
      "tgn:7013412",
      "tgn:7018214",
      "tgn:7002435",
      "tgn:7029392"
    ],
    "placetype": [
      "aat:300008347"
    ],
    "id": 1057868,
    "name:xx": "Ocher"
  }
}
