{
  "geometry": {
    "type": "Point",
    "coordinates": [
      -105.7833,
      37.9667
    ]
  },
  "type": "Feature",
  "properties": {
    "hierarchy": [
      "tgn:2544969",
      "tgn:1000001",
      "tgn:7012149",
      "tgn:7007158",
      "tgn:2000246",
      "tgn:7029392"
    ],
    "placetype": [
      "aat:300006075"
    ],
    "id": 2544969,
    "name:xx": "North Crestone Ditch"
  }
}
