{
  "geometry": {
    "type": "Point",
    "coordinates": [
      -116.05,
      43.8333
    ]
  },
  "type": "Feature",
  "properties": {
    "hierarchy": [
      "tgn:2701992",
      "tgn:1000001",
      "tgn:2000459",
      "tgn:7012149",
      "tgn:7007250",
      "tgn:7029392"
    ],
    "placetype": [
      "aat:300008798"
    ],
    "id": 2701992,
    "name:xx": "Sugarloaf Rock"
  }
}
