{
  "type": "FeatureCollection",
  "features": [
    {
      "geometry": {
        "type": "Point",
        "coordinates": [
          4.333333,
          51.3
        ]
      },
      "type": "Feature",
      "properties": {
        "hierarchy": [
          "tgn:7250970",
          "tgn:7003456",
          "tgn:1000003",
          "tgn:1000063",
          "tgn:7018236",
          "tgn:7029392"
        ],
        "placetype": [
          "aat:300006909"
        ],
        "id": 7250970,
        "name:xx": "Schans van Oorderen"
      }
    },
    {
      "geometry": {
        "type": "Point",
        "coordinates": [
          4.366667,
          51.283333
        ]
      },
      "type": "Feature",
      "properties": {
        "hierarchy": [
          "tgn:7250971",
          "tgn:7003456",
          "tgn:1000003",
          "tgn:1000063",
          "tgn:7018236",
          "tgn:7029392"
        ],
        "placetype": [
          "aat:300008347"
        ],
        "id": 7250971,
        "name:xx": "Oorderen"
      }
    },
    {
      "geometry": {
        "type": "Point",
        "coordinates": [
          3.9,
          50.933333
        ]
      },
      "type": "Feature",
      "properties": {
        "hierarchy": [
          "tgn:7250972",
          "tgn:7003457",
          "tgn:1000003",
          "tgn:1000063",
          "tgn:7018236",
          "tgn:7029392"
        ],
        "placetype": [
          "aat:300008347"
        ],
        "id": 7250972,
        "name:xx": "Oordegemsestraat"
      }
    },
    {
      "geometry": {
        "type": "Point",
        "coordinates": [
          3.902011,
          50.957272
        ]
      },
      "type": "Feature",
      "properties": {
        "hierarchy": [
          "tgn:7250973",
          "tgn:7003457",
          "tgn:1000003",
          "tgn:1000063",
          "tgn:7018236",
          "tgn:7029392"
        ],
        "placetype": [
          "aat:300008347"
        ],
        "id": 7250973,
        "name:xx": "Oordegem"
      }
    },
    {
      "geometry": {
        "type": "Point",
        "coordinates": [
          4.896178,
          50.799373
        ]
      },
      "type": "Feature",
      "properties": {
        "hierarchy": [
          "tgn:7250975",
          "tgn:7018239",
          "tgn:1000003",
          "tgn:1000063",
          "tgn:7018236",
          "tgn:7029392"
        ],
        "placetype": [
          "aat:300008347"
        ],
        "id": 7250975,
        "name:xx": "Oorbeek"
      }
    },
    {
      "geometry": {
        "type": "Point",
        "coordinates": [
          3.941379,
          50.87784
        ]
      },
      "type": "Feature",
      "properties": {
        "hierarchy": [
          "tgn:7250979",
          "tgn:7003457",
          "tgn:1000003",
          "tgn:1000063",
          "tgn:7018236",
          "tgn:7029392"
        ],
        "placetype": [
          "aat:300008347"
        ],
        "id": 7250979,
        "name:xx": "Oom"
      }
    }
  ]
}
