{
  "geometry": {
    "type": "Point",
    "coordinates": [
      -86.3333,
      32.5667
    ]
  },
  "type": "Feature",
  "properties": {
    "hierarchy": [
      "tgn:2003342",
      "tgn:7002659",
      "tgn:1000001",
      "tgn:7012149",
      "tgn:2000025",
      "tgn:7029392"
    ],
    "placetype": [
      "aat:300006448"
    ],
    "id": 2003342,
    "name:xx": "Draper Correctional Center"
  }
}
