{
  "geometry": {
    "type": "Point",
    "coordinates": [
      -85.25,
      44.1333
    ]
  },
  "type": "Feature",
  "properties": {
    "hierarchy": [
      "tgn:2390289",
      "tgn:1000001",
      "tgn:7012149",
      "tgn:2000987",
      "tgn:7007520",
      "tgn:7029392"
    ],
    "placetype": [
      "aat:300008347"
    ],
    "id": 2390289,
    "name:xx": "Highland"
  }
}
