{
  "geometry": {
    "type": "Point",
    "coordinates": [
      34.4333,
      -18.1167
    ]
  },
  "type": "Feature",
  "properties": {
    "hierarchy": [
      "tgn:1091658",
      "tgn:7001242",
      "tgn:7000400",
      "tgn:1000180",
      "tgn:7029392"
    ],
    "placetype": [
      "aat:300008347"
    ],
    "id": 1091658,
    "name:xx": "Nhamacolomo"
  }
}
