{
  "geometry": {
    "type": "Point",
    "coordinates": [
      -110.4667,
      31.8667
    ]
  },
  "type": "Feature",
  "properties": {
    "hierarchy": [
      "tgn:2542777",
      "tgn:1000001",
      "tgn:7006451",
      "tgn:7012149",
      "tgn:2000098",
      "tgn:7029392"
    ],
    "placetype": [
      "aat:300008697"
    ],
    "id": 2542777,
    "name:xx": "Nogales Spring"
  }
}
