{
  "geometry": {
    "type": "Point",
    "coordinates": [
      -88.3833,
      40.5833
    ]
  },
  "type": "Feature",
  "properties": {
    "hierarchy": [
      "tgn:2662087",
      "tgn:1000001",
      "tgn:1002377",
      "tgn:7012149",
      "tgn:7007251",
      "tgn:7029392"
    ],
    "placetype": [
      "aat:300008680"
    ],
    "id": 2662087,
    "name:xx": "Sibley, Lake"
  }
}
