{
  "type": "FeatureCollection",
  "features": [
    {
      "geometry": {
        "type": "Point",
        "coordinates": [
          -0.1,
          47.55
        ]
      },
      "type": "Feature",
      "properties": {
        "hierarchy": [
          "tgn:4001281",
          "tgn:1000003",
          "tgn:7002893",
          "tgn:1000070",
          "tgn:7029392"
        ],
        "placetype": [
          "aat:300008347"
        ],
        "id": 4001281,
        "name:xx": "Baugé"
      }
    },
    {
      "geometry": {
        "type": "Point",
        "coordinates": [
          -6.8833,
          51.1333
        ]
      },
      "type": "Feature",
      "properties": {
        "hierarchy": [
          "tgn:4001283",
          "tgn:7003669",
          "tgn:1000003",
          "tgn:7000084",
          "tgn:7029392"
        ],
        "placetype": [
          "aat:300008347",
          "aat:300000641",
          "aat:300008375"
        ],
        "id": 4001283,
        "name:de": "Baumburg"
      }
    }
  ]
}
