{
  "geometry": {
    "type": "Point",
    "coordinates": [
      -69.0333,
      44.55
    ]
  },
  "type": "Feature",
  "properties": {
    "hierarchy": [
      "tgn:2154801",
      "tgn:1000001",
      "tgn:7012149",
      "tgn:2000931",
      "tgn:7007515",
      "tgn:7029392"
    ],
    "placetype": [
      "aat:300008798"
    ],
    "id": 2154801,
    "name:xx": "Bear Hill"
  }
}
