{
  "geometry": {
    "type": "Point",
    "coordinates": [
      -122.1833,
      47.5667
    ]
  },
  "type": "Feature",
  "properties": {
    "hierarchy": [
      "tgn:2116364",
      "tgn:1000001",
      "tgn:7012149",
      "tgn:7018871",
      "tgn:7007920",
      "tgn:7029392"
    ],
    "placetype": [
      "aat:300008347"
    ],
    "id": 2116364,
    "name:xx": "Newport Shores"
  }
}
