{
  "geometry": {
    "type": "Point",
    "coordinates": [
      -122.4833,
      47.3667
    ]
  },
  "type": "Feature",
  "properties": {
    "hierarchy": [
      "tgn:2376049",
      "tgn:1000001",
      "tgn:7012149",
      "tgn:7018871",
      "tgn:7007920",
      "tgn:7029392"
    ],
    "placetype": [
      "aat:300008347"
    ],
    "id": 2376049,
    "name:xx": "Harbor Heights"
  }
}
