{
  "type": "FeatureCollection",
  "features": [
    {
      "geometry": {
        "type": "Point",
        "coordinates": [
          -94.9667,
          32.5833
        ]
      },
      "type": "Feature",
      "properties": {
        "hierarchy": [
          "tgn:2398610",
          "tgn:1000001",
          "tgn:7012149",
          "tgn:1002966",
          "tgn:7007826",
          "tgn:7029392"
        ],
        "placetype": [
          "aat:300008699"
        ],
        "id": 2398610,
        "name:xx": "Hoover Spring Branch"
      }
    },
    {
      "geometry": {
        "type": "Point",
        "coordinates": [
          -121.55,
          37.2
        ]
      },
      "type": "Feature",
      "properties": {
        "hierarchy": [
          "tgn:2398611",
          "tgn:1000001",
          "tgn:7012149",
          "tgn:7007157",
          "tgn:7014475",
          "tgn:7029392"
        ],
        "placetype": [
          "aat:300008761"
        ],
        "id": 2398611,
        "name:xx": "Hoover Valley"
      }
    },
    {
      "geometry": {
        "type": "Point",
        "coordinates": [
          -95.1333,
          40.4167
        ]
      },
      "type": "Feature",
      "properties": {
        "hierarchy": [
          "tgn:2398612",
          "tgn:1000001",
          "tgn:7012149",
          "tgn:2001224",
          "tgn:7007523",
          "tgn:7029392"
        ],
        "placetype": [
          "aat:300006191"
        ],
        "id": 2398612,
        "name:xx": "Hoover-Frankum Watershed C-22 Lake"
      }
    },
    {
      "geometry": {
        "type": "Point",
        "coordinates": [
          -106.9167,
          39.4
        ]
      },
      "type": "Feature",
      "properties": {
        "hierarchy": [
          "tgn:2398613",
          "tgn:1000001",
          "tgn:7012149",
          "tgn:2000210",
          "tgn:7007158",
          "tgn:7029392"
        ],
        "placetype": [
          "aat:300008761"
        ],
        "id": 2398613,
        "name:xx": "Hoovers Bend Gulch"
      }
    },
    {
      "geometry": {
        "type": "Point",
        "coordinates": [
          -108.05,
          38.6
        ]
      },
      "type": "Feature",
      "properties": {
        "hierarchy": [
          "tgn:2398614",
          "tgn:1000001",
          "tgn:7012149",
          "tgn:2000234",
          "tgn:7007158",
          "tgn:7029392"
        ],
        "placetype": [
          "aat:300008347"
        ],
        "id": 2398614,
        "name:xx": "Hoovers Corner"
      }
    },
    {
      "geometry": {
        "type": "Point",
        "coordinates": [
          -84.3,
          43.1
        ]
      },
      "type": "Feature",
      "properties": {
        "hierarchy": [
          "tgn:2398615",
          "tgn:1000001",
          "tgn:7012149",
          "tgn:1002892",
          "tgn:7007520",
          "tgn:7029392"
        ],
        "placetype": [
          "aat:300008347"
        ],
        "id": 2398615,
        "name:xx": "Hoovers Corners"
      }
    },
    {
      "geometry": {
        "type": "Point",
        "coordinates": [
          -111.5167,
          40.4333
        ]
      },
      "type": "Feature",
      "properties": {
        "hierarchy": [
          "tgn:2398617",
          "tgn:1000001",
          "tgn:7012149",
          "tgn:2002126",
          "tgn:7007827",
          "tgn:7029392"
        ],
        "placetype": [
          "aat:300008761"
        ],
        "id": 2398617,
        "name:xx": "Hoovers Hollow"
      }
    },
    {
      "geometry": {
        "type": "Point",
        "coordinates": [
          -90.4,
          30.4333
        ]
      },
      "type": "Feature",
      "properties": {
        "hierarchy": [
          "tgn:2398619",
          "tgn:1000001",
          "tgn:7012149",
          "tgn:2000906",
          "tgn:7007256",
          "tgn:7029392"
        ],
        "placetype": [
          "aat:300006191"
        ],
        "id": 2398619,
        "name:xx": "Hoovers Pond"
      }
    }
  ]
}
