{
  "geometry": {
    "type": "Point",
    "coordinates": [
      -84.7833,
      30.4833
    ]
  },
  "type": "Feature",
  "properties": {
    "hierarchy": [
      "tgn:2555238",
      "tgn:1000001",
      "tgn:7012149",
      "tgn:7007240",
      "tgn:7029392"
    ],
    "placetype": [
      "aat:300008706"
    ],
    "id": 2555238,
    "name:xx": "Ocklawaha Creek"
  }
}
