{
  "geometry": {
    "type": "Point",
    "coordinates": [
      -87.8167,
      44.1167
    ]
  },
  "type": "Feature",
  "properties": {
    "hierarchy": [
      "tgn:2647237",
      "tgn:1000001",
      "tgn:7012149",
      "tgn:2002335",
      "tgn:7007922",
      "tgn:7029392"
    ],
    "placetype": [
      "aat:300008680"
    ],
    "id": 2647237,
    "name:xx": "Schisel Lake"
  }
}
