{
  "geometry": {
    "type": "Point",
    "coordinates": [
      -108.1833,
      36.9667
    ]
  },
  "type": "Feature",
  "properties": {
    "hierarchy": [
      "tgn:2524356",
      "tgn:1000001",
      "tgn:7012149",
      "tgn:2001452",
      "tgn:7007566",
      "tgn:7029392"
    ],
    "placetype": [
      "aat:300000390"
    ],
    "id": 2524356,
    "name:xx": "Morgan Mines"
  }
}
