{
  "geometry": {
    "type": "Point",
    "coordinates": [
      -91.2667,
      44.15
    ]
  },
  "type": "Feature",
  "properties": {
    "hierarchy": [
      "tgn:2157533",
      "tgn:1000001",
      "tgn:7012149",
      "tgn:2002357",
      "tgn:7007922",
      "tgn:7029392"
    ],
    "placetype": [
      "aat:300008706"
    ],
    "id": 2157533,
    "name:xx": "Beaver Creek"
  }
}
