{
  "type": "FeatureCollection",
  "features": [
    {
      "geometry": {
        "type": "Point",
        "coordinates": [
          -89.25,
          20.833333
        ]
      },
      "type": "Feature",
      "properties": {
        "hierarchy": [
          "tgn:7434031",
          "tgn:1000001",
          "tgn:7005600",
          "tgn:7005560",
          "tgn:7029392"
        ],
        "placetype": [
          "aat:300008347"
        ],
        "id": 7434031,
        "name:xx": "Xtabay"
      }
    },
    {
      "geometry": {
        "type": "Point",
        "coordinates": [
          -88.5,
          21.416667
        ]
      },
      "type": "Feature",
      "properties": {
        "hierarchy": [
          "tgn:7434032",
          "tgn:1000001",
          "tgn:7005600",
          "tgn:7005560",
          "tgn:7029392"
        ],
        "placetype": [
          "aat:300008347"
        ],
        "id": 7434032,
        "name:xx": "Xtab"
      }
    },
    {
      "geometry": {
        "type": "Point",
        "coordinates": [
          -90.483333,
          20.45
        ]
      },
      "type": "Feature",
      "properties": {
        "hierarchy": [
          "tgn:7434033",
          "tgn:7005578",
          "tgn:1000001",
          "tgn:7005560",
          "tgn:7029392"
        ],
        "placetype": [
          "aat:300386846"
        ],
        "id": 7434033,
        "name:xx": "Xpuq, Punta"
      }
    },
    {
      "geometry": {
        "type": "Point",
        "coordinates": [
          -89.4,
          18.5
        ]
      },
      "type": "Feature",
      "properties": {
        "hierarchy": [
          "tgn:7434034",
          "tgn:1000001",
          "tgn:1001937",
          "tgn:7005560",
          "tgn:7029392"
        ],
        "placetype": [
          "aat:300387007"
        ],
        "id": 7434034,
        "name:xx": "Xpujil"
      }
    },
    {
      "geometry": {
        "type": "Point",
        "coordinates": [
          -89.116667,
          20.583333
        ]
      },
      "type": "Feature",
      "properties": {
        "hierarchy": [
          "tgn:7434035",
          "tgn:1000001",
          "tgn:7005600",
          "tgn:7005560",
          "tgn:7029392"
        ],
        "placetype": [
          "aat:300008347"
        ],
        "id": 7434035,
        "name:xx": "Xplacam"
      }
    },
    {
      "geometry": {
        "type": "Point",
        "coordinates": [
          -88.3,
          21.35
        ]
      },
      "type": "Feature",
      "properties": {
        "hierarchy": [
          "tgn:7434037",
          "tgn:1000001",
          "tgn:7005600",
          "tgn:7005560",
          "tgn:7029392"
        ],
        "placetype": [
          "aat:300008347"
        ],
        "id": 7434037,
        "name:xx": "Xpalib"
      }
    },
    {
      "geometry": {
        "type": "Point",
        "coordinates": [
          -89.416667,
          20.55
        ]
      },
      "type": "Feature",
      "properties": {
        "hierarchy": [
          "tgn:7434038",
          "tgn:1000001",
          "tgn:7005600",
          "tgn:7005560",
          "tgn:7029392"
        ],
        "placetype": [
          "aat:300008347"
        ],
        "id": 7434038,
        "name:xx": "Xpacay"
      }
    },
    {
      "geometry": {
        "type": "Point",
        "coordinates": [
          -89.5,
          20.583333
        ]
      },
      "type": "Feature",
      "properties": {
        "hierarchy": [
          "tgn:7434039",
          "tgn:1000001",
          "tgn:7005600",
          "tgn:7005560",
          "tgn:7029392"
        ],
        "placetype": [
          "aat:300387007"
        ],
        "id": 7434039,
        "name:xx": "Xpac"
      }
    }
  ]
}
