{
  "geometry": {
    "type": "Point",
    "coordinates": [
      -113.4167,
      35.6667
    ]
  },
  "type": "Feature",
  "properties": {
    "hierarchy": [
      "tgn:2506911",
      "tgn:1000001",
      "tgn:7006451",
      "tgn:7012149",
      "tgn:2000098",
      "tgn:7029392"
    ],
    "placetype": [
      "aat:300008697"
    ],
    "id": 2506911,
    "name:xx": "Mesquite Spring"
  }
}
