{
  "geometry": {
    "type": "Point",
    "coordinates": [
      36.6833,
      14.3333
    ]
  },
  "type": "Feature",
  "properties": {
    "hierarchy": [
      "tgn:1089929",
      "tgn:7001242",
      "tgn:7017572",
      "tgn:7001658",
      "tgn:7029392"
    ],
    "placetype": [
      "aat:300008347"
    ],
    "id": 1089929,
    "name:xx": "Om Hājer"
  }
}
