{
  "geometry": {
    "type": "Point",
    "coordinates": [
      -119.7667,
      48.0833
    ]
  },
  "type": "Feature",
  "properties": {
    "hierarchy": [
      "tgn:2745667",
      "tgn:1000001",
      "tgn:7012149",
      "tgn:1002742",
      "tgn:7007920",
      "tgn:7029392"
    ],
    "placetype": [
      "aat:300008347"
    ],
    "id": 2745667,
    "name:xx": "Virginia City"
  }
}
