{
  "geometry": {
    "type": "Point",
    "coordinates": [
      -122.0667,
      45.7667
    ]
  },
  "type": "Feature",
  "properties": {
    "hierarchy": [
      "tgn:2469550",
      "tgn:1000001",
      "tgn:7012149",
      "tgn:1002897",
      "tgn:7007920",
      "tgn:7029392"
    ],
    "placetype": [
      "aat:300008706"
    ],
    "id": 2469550,
    "name:xx": "Lookout Creek"
  }
}
