{
  "geometry": {
    "type": "Point",
    "coordinates": [
      -119.45,
      48.0667
    ]
  },
  "type": "Feature",
  "properties": {
    "hierarchy": [
      "tgn:2190375",
      "tgn:1000001",
      "tgn:7012149",
      "tgn:7007920",
      "tgn:7029392"
    ],
    "placetype": [
      "aat:300008761"
    ],
    "id": 2190375,
    "name:xx": "Box Canyon"
  }
}
