{
  "geometry": {
    "type": "Point",
    "coordinates": [
      121.0167,
      30.8833
    ]
  },
  "type": "Feature",
  "properties": {
    "hierarchy": [
      "tgn:1068038",
      "tgn:1000004",
      "tgn:1000958",
      "tgn:1000111",
      "tgn:7029392"
    ],
    "placetype": [
      "aat:300008347"
    ],
    "id": 1068038,
    "name:xx": "Fengjingzhen"
  }
}
