{
  "geometry": {
    "type": "Point",
    "coordinates": [
      -109.5333,
      43.8667
    ]
  },
  "type": "Feature",
  "properties": {
    "hierarchy": [
      "tgn:2266882",
      "tgn:1000001",
      "tgn:7012149",
      "tgn:2002371",
      "tgn:7007923",
      "tgn:7029392"
    ],
    "placetype": [
      "aat:300008798"
    ],
    "id": 2266882,
    "name:xx": "Crescent Top"
  }
}
