{
  "type": "FeatureCollection",
  "features": [
    {
      "geometry": {
        "type": "Point",
        "coordinates": [
          -2.25,
          55.3
        ]
      },
      "type": "Feature",
      "properties": {
        "hierarchy": [
          "tgn:1136740",
          "tgn:7002445",
          "tgn:1000003",
          "tgn:7008165",
          "tgn:7008591",
          "tgn:7029392"
        ],
        "placetype": [
          "aat:300008347",
          "aat:300000810",
          "aat:300387238",
          "aat:300006909",
          "aat:300008372",
          "aat:300020533"
        ],
        "name:en": "Rochester",
        "id": 1136740
      }
    },
    {
      "geometry": {
        "type": "Point",
        "coordinates": [
          -1.483333,
          53.75
        ]
      },
      "type": "Feature",
      "properties": {
        "hierarchy": [
          "tgn:1136741",
          "tgn:7019038",
          "tgn:7002445",
          "tgn:1000003",
          "tgn:7029507",
          "tgn:7008591",
          "tgn:7029392"
        ],
        "placetype": [
          "aat:300008347",
          "aat:300008375"
        ],
        "name:en": "Rothwell",
        "id": 1136741
      }
    },
    {
      "geometry": {
        "type": "Point",
        "coordinates": [
          0.525,
          52.767
        ]
      },
      "type": "Feature",
      "properties": {
        "hierarchy": [
          "tgn:1136742",
          "tgn:7002445",
          "tgn:1000003",
          "tgn:7008160",
          "tgn:7008591",
          "tgn:7029392"
        ],
        "placetype": [
          "aat:300008347",
          "aat:300008372"
        ],
        "id": 1136742,
        "name:xx": "Roydon"
      }
    },
    {
      "geometry": {
        "type": "Point",
        "coordinates": [
          -0.218,
          53.9
        ]
      },
      "type": "Feature",
      "properties": {
        "hierarchy": [
          "tgn:1136747",
          "tgn:7002445",
          "tgn:1000003",
          "tgn:7019057",
          "tgn:7008591",
          "tgn:7029392"
        ],
        "placetype": [
          "aat:300008347",
          "aat:300008372"
        ],
        "id": 1136747,
        "name:xx": "Seaton"
      }
    },
    {
      "geometry": {
        "type": "Point",
        "coordinates": [
          -3.55,
          54.6833
        ]
      },
      "type": "Feature",
      "properties": {
        "hierarchy": [
          "tgn:1136748",
          "tgn:7002445",
          "tgn:1000003",
          "tgn:7008117",
          "tgn:7008591",
          "tgn:7029392"
        ],
        "placetype": [
          "aat:300008347"
        ],
        "id": 1136748,
        "name:xx": "Seaton"
      }
    },
    {
      "geometry": {
        "type": "Point",
        "coordinates": [
          -2.866667,
          54.7
        ]
      },
      "type": "Feature",
      "properties": {
        "hierarchy": [
          "tgn:1136749",
          "tgn:7002445",
          "tgn:1000003",
          "tgn:7008117",
          "tgn:7008591",
          "tgn:7029392"
        ],
        "placetype": [
          "aat:300008347"
        ],
        "name:en": "Skelton",
        "id": 1136749
      }
    }
  ]
}
