{
  "geometry": {
    "type": "Point",
    "coordinates": [
      16.3333,
      -17.4667
    ]
  },
  "type": "Feature",
  "properties": {
    "hierarchy": [
      "tgn:1093918",
      "tgn:7001242",
      "tgn:7030588",
      "tgn:1000198",
      "tgn:7029392"
    ],
    "placetype": [
      "aat:300008347"
    ],
    "id": 1093918,
    "name:xx": "Eenhana"
  }
}
