{
  "geometry": {
    "type": "Point",
    "coordinates": [
      103.65,
      27.3333
    ]
  },
  "type": "Feature",
  "properties": {
    "hierarchy": [
      "tgn:1073934",
      "tgn:1000004",
      "tgn:7018118",
      "tgn:1000111",
      "tgn:7029392"
    ],
    "placetype": [
      "aat:300008347"
    ],
    "id": 1073934,
    "name:xx": "Zhaotong"
  }
}
