{
  "geometry": {
    "type": "Point",
    "coordinates": [
      -109.9333,
      45.6667
    ]
  },
  "type": "Feature",
  "properties": {
    "hierarchy": [
      "tgn:2669623",
      "tgn:1000001",
      "tgn:7012149",
      "tgn:2001308",
      "tgn:7007524",
      "tgn:7029392"
    ],
    "placetype": [
      "aat:300008761"
    ],
    "id": 2669623,
    "name:xx": "Slide Rock Gulch"
  }
}
