{
  "geometry": {
    "type": "Point",
    "coordinates": [
      35.3333,
      -14.8333
    ]
  },
  "type": "Feature",
  "properties": {
    "hierarchy": [
      "tgn:1101677",
      "tgn:7001242",
      "tgn:1001542",
      "tgn:7000726",
      "tgn:7029392"
    ],
    "placetype": [
      "aat:300008189"
    ],
    "id": 1101677,
    "name:xx": "Liwonde National Park"
  }
}
