{
  "geometry": {
    "type": "Point",
    "coordinates": [
      -94.0333,
      32.9333
    ]
  },
  "type": "Feature",
  "properties": {
    "hierarchy": [
      "tgn:2108348",
      "tgn:1000001",
      "tgn:7012149",
      "tgn:1002244",
      "tgn:7007826",
      "tgn:7029392"
    ],
    "placetype": [
      "aat:300008347",
      "aat:300387210"
    ],
    "id": 2108348,
    "name:xx": "Walton"
  }
}
