{
  "geometry": {
    "type": "Point",
    "coordinates": [
      -106.7333,
      45.6833
    ]
  },
  "type": "Feature",
  "properties": {
    "hierarchy": [
      "tgn:2258886",
      "tgn:1000001",
      "tgn:7012149",
      "tgn:2001303",
      "tgn:7007524",
      "tgn:7029392"
    ],
    "placetype": [
      "aat:300008706"
    ],
    "id": 2258886,
    "name:xx": "Cottonwood Creek"
  }
}
