{
  "geometry": {
    "type": "Point",
    "coordinates": [
      -88.35,
      41.8667
    ]
  },
  "type": "Feature",
  "properties": {
    "hierarchy": [
      "tgn:2573626",
      "tgn:1000001",
      "tgn:7012149",
      "tgn:1002531",
      "tgn:7007251",
      "tgn:7029392"
    ],
    "placetype": [
      "aat:300008680"
    ],
    "id": 2573626,
    "name:xx": "Peck Lake"
  }
}
