{
  "geometry": {
    "type": "Point",
    "coordinates": [
      -122.8667,
      44.5667
    ]
  },
  "type": "Feature",
  "properties": {
    "hierarchy": [
      "tgn:2084444",
      "tgn:1000001",
      "tgn:7012149",
      "tgn:2001717",
      "tgn:7007708",
      "tgn:7029392"
    ],
    "placetype": [
      "aat:300387016"
    ],
    "id": 2084444,
    "name:xx": "Brewster"
  }
}
