{
  "geometry": {
    "type": "Point",
    "coordinates": [
      -86.7667,
      33.8667
    ]
  },
  "type": "Feature",
  "properties": {
    "hierarchy": [
      "tgn:2163615",
      "tgn:7002659",
      "tgn:1000001",
      "tgn:2000004",
      "tgn:7012149",
      "tgn:7029392"
    ],
    "placetype": [
      "aat:300008347"
    ],
    "id": 2163615,
    "name:xx": "Bent Tree"
  }
}
