{
  "geometry": {
    "type": "Point",
    "coordinates": [
      -1.7833,
      48.05
    ]
  },
  "type": "Feature",
  "properties": {
    "hierarchy": [
      "tgn:1127107",
      "tgn:1000003",
      "tgn:7012216",
      "tgn:1000070",
      "tgn:7029392"
    ],
    "placetype": [
      "aat:300008707"
    ],
    "id": 1127107,
    "name:xx": "Meu"
  }
}
