{
  "geometry": {
    "type": "Point",
    "coordinates": [
      -0.566667,
      39.95
    ]
  },
  "type": "Feature",
  "properties": {
    "hierarchy": [
      "tgn:7338404",
      "tgn:7002815",
      "tgn:1000003",
      "tgn:7002793",
      "tgn:1000095",
      "tgn:7029392"
    ],
    "placetype": [
      "aat:300008347"
    ],
    "id": 7338404,
    "name:xx": "Caudiel"
  }
}
