{
  "geometry": {
    "type": "Point",
    "coordinates": [
      -119.4667,
      40.8833
    ]
  },
  "type": "Feature",
  "properties": {
    "hierarchy": [
      "tgn:2747162",
      "tgn:1000001",
      "tgn:7012149",
      "tgn:1002999",
      "tgn:7007526",
      "tgn:7029392"
    ],
    "placetype": [
      "aat:300008697"
    ],
    "id": 2747162,
    "name:xx": "Wagon Tire Spring"
  }
}
