{
  "type": "FeatureCollection",
  "features": [
    {
      "geometry": {
        "type": "Point",
        "coordinates": [
          -111.3833,
          46.1167
        ]
      },
      "type": "Feature",
      "properties": {
        "hierarchy": [
          "tgn:2171090",
          "tgn:1000001",
          "tgn:2001263",
          "tgn:7012149",
          "tgn:7007524",
          "tgn:7029392"
        ],
        "placetype": [
          "aat:300008697"
        ],
        "id": 2171090,
        "name:xx": "Big Spring"
      }
    },
    {
      "geometry": {
        "type": "Point",
        "coordinates": [
          -116.2667,
          36.3667
        ]
      },
      "type": "Feature",
      "properties": {
        "hierarchy": [
          "tgn:2171091",
          "tgn:1000001",
          "tgn:2001418",
          "tgn:7012149",
          "tgn:7007526",
          "tgn:7029392"
        ],
        "placetype": [
          "aat:300008697"
        ],
        "id": 2171091,
        "name:xx": "Big Spring"
      }
    },
    {
      "geometry": {
        "type": "Point",
        "coordinates": [
          -114.0333,
          36.5167
        ]
      },
      "type": "Feature",
      "properties": {
        "hierarchy": [
          "tgn:2171092",
          "tgn:1000001",
          "tgn:2001410",
          "tgn:7012149",
          "tgn:7007526",
          "tgn:7029392"
        ],
        "placetype": [
          "aat:300008697"
        ],
        "id": 2171092,
        "name:xx": "Big Spring"
      }
    },
    {
      "geometry": {
        "type": "Point",
        "coordinates": [
          -114.35,
          37.5167
        ]
      },
      "type": "Feature",
      "properties": {
        "hierarchy": [
          "tgn:2171093",
          "tgn:1000001",
          "tgn:2001416",
          "tgn:7012149",
          "tgn:7007526",
          "tgn:7029392"
        ],
        "placetype": [
          "aat:300008697"
        ],
        "id": 2171093,
        "name:xx": "Big Spring"
      }
    },
    {
      "geometry": {
        "type": "Point",
        "coordinates": [
          -117.7833,
          37.6333
        ]
      },
      "type": "Feature",
      "properties": {
        "hierarchy": [
          "tgn:2171094",
          "tgn:1000001",
          "tgn:2001412",
          "tgn:7012149",
          "tgn:7007526",
          "tgn:7029392"
        ],
        "placetype": [
          "aat:300008697"
        ],
        "id": 2171094,
        "name:xx": "Big Spring"
      }
    },
    {
      "geometry": {
        "type": "Point",
        "coordinates": [
          -116.4833,
          40
        ]
      },
      "type": "Feature",
      "properties": {
        "hierarchy": [
          "tgn:2171095",
          "tgn:1000001",
          "tgn:2001413",
          "tgn:7012149",
          "tgn:7007526",
          "tgn:7029392"
        ],
        "placetype": [
          "aat:300008697"
        ],
        "id": 2171095,
        "name:xx": "Big Spring"
      }
    },
    {
      "geometry": {
        "type": "Point",
        "coordinates": [
          -115.5333,
          40.65
        ]
      },
      "type": "Feature",
      "properties": {
        "hierarchy": [
          "tgn:2171096",
          "tgn:1000001",
          "tgn:2001411",
          "tgn:7012149",
          "tgn:7007526",
          "tgn:7029392"
        ],
        "placetype": [
          "aat:300008697"
        ],
        "id": 2171096,
        "name:xx": "Big Spring"
      }
    },
    {
      "geometry": {
        "type": "Point",
        "coordinates": [
          -119.75,
          41.1833
        ]
      },
      "type": "Feature",
      "properties": {
        "hierarchy": [
          "tgn:2171097",
          "tgn:1000001",
          "tgn:7012149",
          "tgn:1002999",
          "tgn:7007526",
          "tgn:7029392"
        ],
        "placetype": [
          "aat:300008697"
        ],
        "id": 2171097,
        "name:xx": "Big Spring"
      }
    },
    {
      "geometry": {
        "type": "Point",
        "coordinates": [
          -119.15,
          41.9167
        ]
      },
      "type": "Feature",
      "properties": {
        "hierarchy": [
          "tgn:2171098",
          "tgn:1000001",
          "tgn:2001414",
          "tgn:7012149",
          "tgn:7007526",
          "tgn:7029392"
        ],
        "placetype": [
          "aat:300008697"
        ],
        "id": 2171098,
        "name:xx": "Big Spring"
      }
    },
    {
      "geometry": {
        "type": "Point",
        "coordinates": [
          -116.85,
          40.35
        ]
      },
      "type": "Feature",
      "properties": {
        "hierarchy": [
          "tgn:2171099",
          "tgn:1000001",
          "tgn:2001415",
          "tgn:7012149",
          "tgn:7007526",
          "tgn:7029392"
        ],
        "placetype": [
          "aat:300008697"
        ],
        "id": 2171099,
        "name:xx": "Big Spring"
      }
    }
  ]
}
