{
  "geometry": {
    "type": "Point",
    "coordinates": [
      -83.0667,
      38.6333
    ]
  },
  "type": "Feature",
  "properties": {
    "hierarchy": [
      "tgn:2487787",
      "tgn:1000001",
      "tgn:7012149",
      "tgn:1002591",
      "tgn:7007255",
      "tgn:7029392"
    ],
    "placetype": [
      "aat:300008706"
    ],
    "id": 2487787,
    "name:xx": "Left Fork Rock Creek"
  }
}
