{
  "geometry": {
    "type": "Point",
    "coordinates": [
      -111.1833,
      37.2333
    ]
  },
  "type": "Feature",
  "properties": {
    "hierarchy": [
      "tgn:2782519",
      "tgn:1000001",
      "tgn:7012149",
      "tgn:2002113",
      "tgn:7007827",
      "tgn:7029392"
    ],
    "placetype": [
      "aat:300386837"
    ],
    "id": 2782519,
    "name:xx": "Woolsey Arch"
  }
}
