{
  "type": "FeatureCollection",
  "features": [
    {
      "geometry": {
        "type": "Point",
        "coordinates": [
          12.1333,
          42.4833
        ]
      },
      "type": "Feature",
      "properties": {
        "hierarchy": [
          "tgn:5002435",
          "tgn:7003139",
          "tgn:1000003",
          "tgn:7003080",
          "tgn:1000080",
          "tgn:7029392"
        ],
        "placetype": [
          "aat:300008347"
        ],
        "id": 5002435,
        "name:xx": "Acquarossa"
      }
    },
    {
      "geometry": {
        "type": "Point",
        "coordinates": [
          12.066667,
          42.25
        ]
      },
      "type": "Feature",
      "properties": {
        "hierarchy": [
          "tgn:5002438",
          "tgn:7003139",
          "tgn:1000003",
          "tgn:7003080",
          "tgn:1000080",
          "tgn:7029392"
        ],
        "placetype": [
          "aat:300008347"
        ],
        "id": 5002438,
        "name:xx": "Barbarano Romano"
      }
    },
    {
      "geometry": {
        "type": "Point",
        "coordinates": [
          12.3167,
          42.466
        ]
      },
      "type": "Feature",
      "properties": {
        "hierarchy": [
          "tgn:5002439",
          "tgn:7003139",
          "tgn:1000003",
          "tgn:7003080",
          "tgn:1000080",
          "tgn:7029392"
        ],
        "placetype": [
          "aat:300008347"
        ],
        "id": 5002439,
        "name:xx": "Bassano in Teverina"
      }
    }
  ]
}
