{
  "type": "FeatureCollection",
  "features": [
    {
      "geometry": {
        "type": "Point",
        "coordinates": [
          121.833333,
          25.133333
        ]
      },
      "type": "Feature",
      "properties": {
        "hierarchy": [
          "tgn:7471980",
          "tgn:1000004",
          "tgn:1000454",
          "tgn:1000141",
          "tgn:7029392"
        ],
        "placetype": [
          "aat:300008347"
        ],
        "id": 7471980,
        "name:xx": "Caoshan"
      }
    },
    {
      "geometry": {
        "type": "Point",
        "coordinates": [
          120.638291,
          23.373717
        ]
      },
      "type": "Feature",
      "properties": {
        "hierarchy": [
          "tgn:7471981",
          "tgn:7468018",
          "tgn:1000004",
          "tgn:1000141",
          "tgn:7029392"
        ],
        "placetype": [
          "aat:300008347"
        ],
        "id": 7471981,
        "name:xx": "Caoshan"
      }
    },
    {
      "geometry": {
        "type": "Point",
        "coordinates": [
          120.433889,
          22.990278
        ]
      },
      "type": "Feature",
      "properties": {
        "hierarchy": [
          "tgn:7471982",
          "tgn:7001004",
          "tgn:1000004",
          "tgn:1000141",
          "tgn:7029392"
        ],
        "placetype": [
          "aat:300008347"
        ],
        "id": 7471982,
        "name:xx": "Caoshan"
      }
    },
    {
      "geometry": {
        "type": "Point",
        "coordinates": [
          120.633333,
          22.383333
        ]
      },
      "type": "Feature",
      "properties": {
        "hierarchy": [
          "tgn:7471983",
          "tgn:1000004",
          "tgn:7492971",
          "tgn:1000141",
          "tgn:7029392"
        ],
        "placetype": [
          "aat:300008795",
          "aat:300008798"
        ],
        "id": 7471983,
        "name:xx": "Cao Shan"
      }
    },
    {
      "geometry": {
        "type": "Point",
        "coordinates": [
          121.875716,
          25.093863
        ]
      },
      "type": "Feature",
      "properties": {
        "hierarchy": [
          "tgn:7471984",
          "tgn:1000004",
          "tgn:1000454",
          "tgn:1000141",
          "tgn:7029392"
        ],
        "placetype": [
          "aat:300008798"
        ],
        "id": 7471984,
        "name:xx": "Cao Shan"
      }
    },
    {
      "geometry": {
        "type": "Point",
        "coordinates": [
          120.658933,
          23.339566
        ]
      },
      "type": "Feature",
      "properties": {
        "hierarchy": [
          "tgn:7471985",
          "tgn:7468018",
          "tgn:1000004",
          "tgn:1000141",
          "tgn:7029392"
        ],
        "placetype": [
          "aat:300008795"
        ],
        "id": 7471985,
        "name:xx": "Cao Shan"
      }
    },
    {
      "geometry": {
        "type": "Point",
        "coordinates": [
          121.566111,
          22.063889
        ]
      },
      "type": "Feature",
      "properties": {
        "hierarchy": [
          "tgn:7471987",
          "tgn:1000004",
          "tgn:7491221",
          "tgn:1000141",
          "tgn:7029392"
        ],
        "placetype": [
          "aat:300008777"
        ],
        "id": 7471987,
        "name:xx": "Cao Shan"
      }
    },
    {
      "geometry": {
        "type": "Point",
        "coordinates": [
          121.603656,
          25.264846
        ]
      },
      "type": "Feature",
      "properties": {
        "hierarchy": [
          "tgn:7471988",
          "tgn:1000004",
          "tgn:1000454",
          "tgn:1000141",
          "tgn:7029392"
        ],
        "placetype": [
          "aat:300008347"
        ],
        "id": 7471988,
        "name:xx": "Caobuwei"
      }
    },
    {
      "geometry": {
        "type": "Point",
        "coordinates": [
          121.488798,
          25.226823
        ]
      },
      "type": "Feature",
      "properties": {
        "hierarchy": [
          "tgn:7471989",
          "tgn:1000004",
          "tgn:1000454",
          "tgn:1000141",
          "tgn:7029392"
        ],
        "placetype": [
          "aat:300008347"
        ],
        "id": 7471989,
        "name:xx": "Caobuwei"
      }
    }
  ]
}
