{
  "geometry": {
    "type": "Point",
    "coordinates": [
      159.5833,
      -8.45
    ]
  },
  "type": "Feature",
  "properties": {
    "hierarchy": [
      "tgn:1008960",
      "tgn:1001313",
      "tgn:1000233",
      "tgn:1000006",
      "tgn:7029392"
    ],
    "placetype": [
      "aat:300008791"
    ],
    "id": 1008960,
    "name:xx": "San Jorge Island"
  }
}
