{
  "geometry": {
    "type": "Point",
    "coordinates": [
      -84.3333,
      38.9833
    ]
  },
  "type": "Feature",
  "properties": {
    "hierarchy": [
      "tgn:2773717",
      "tgn:1000001",
      "tgn:1002231",
      "tgn:7012149",
      "tgn:7007255",
      "tgn:7029392"
    ],
    "placetype": [
      "aat:300008699"
    ],
    "id": 2773717,
    "name:xx": "Willow Branch"
  }
}
