{
  "geometry": {
    "type": "Point",
    "coordinates": [
      -109.95,
      33.6167
    ]
  },
  "type": "Feature",
  "properties": {
    "hierarchy": [
      "tgn:2625671",
      "tgn:1000001",
      "tgn:7006451",
      "tgn:7012149",
      "tgn:2000099",
      "tgn:7029392"
    ],
    "placetype": [
      "aat:300006191"
    ],
    "id": 2625671,
    "name:xx": "Rocky Basin Tank Number One"
  }
}
