{
  "type": "FeatureCollection",
  "features": [
    {
      "geometry": {
        "type": "Point",
        "coordinates": [
          8.85,
          51.45
        ]
      },
      "type": "Feature",
      "properties": {
        "hierarchy": [
          "tgn:7013252",
          "tgn:1000003",
          "tgn:7003677",
          "tgn:7000084",
          "tgn:7029392"
        ],
        "placetype": [
          "aat:300008347"
        ],
        "id": 7013252,
        "name:xx": "Marsberg"
      }
    },
    {
      "geometry": {
        "type": "Point",
        "coordinates": [
          7.7,
          49.766667
        ]
      },
      "type": "Feature",
      "properties": {
        "hierarchy": [
          "tgn:7013253",
          "tgn:1000003",
          "tgn:7003682",
          "tgn:7000084",
          "tgn:7029392"
        ],
        "placetype": [
          "aat:300008347",
          "aat:300008375"
        ],
        "id": 7013253,
        "name:xx": "Odernheim"
      }
    },
    {
      "geometry": {
        "type": "Point",
        "coordinates": [
          8.45,
          48.066667
        ]
      },
      "type": "Feature",
      "properties": {
        "hierarchy": [
          "tgn:7013257",
          "tgn:7003692",
          "tgn:1000003",
          "tgn:7000084",
          "tgn:7029392"
        ],
        "placetype": [
          "aat:300008347",
          "aat:300008389",
          "aat:300387308"
        ],
        "name:en": "Villingen-Schwenningen",
        "id": 7013257,
        "name:de": "Villingen-Schwenningen"
      }
    },
    {
      "geometry": {
        "type": "Point",
        "coordinates": [
          9,
          47.866667
        ]
      },
      "type": "Feature",
      "properties": {
        "hierarchy": [
          "tgn:7013259",
          "tgn:7003692",
          "tgn:1000003",
          "tgn:7000084",
          "tgn:7029392"
        ],
        "placetype": [
          "aat:300008347"
        ],
        "id": 7013259,
        "name:xx": "Zizenhausen"
      }
    }
  ]
}
