{
  "geometry": {
    "type": "Point",
    "coordinates": [
      -82.7167,
      35.5167
    ]
  },
  "type": "Feature",
  "properties": {
    "hierarchy": [
      "tgn:2584521",
      "tgn:1000001",
      "tgn:2001473",
      "tgn:7012149",
      "tgn:7007709",
      "tgn:7029392"
    ],
    "placetype": [
      "aat:300008798"
    ],
    "id": 2584521,
    "name:xx": "Piney Mountain"
  }
}
