{
  "geometry": {
    "type": "Point",
    "coordinates": [
      -82.0333,
      29.8167
    ]
  },
  "type": "Feature",
  "properties": {
    "hierarchy": [
      "tgn:2270352",
      "tgn:1000001",
      "tgn:2000261",
      "tgn:7012149",
      "tgn:7007240",
      "tgn:7029392"
    ],
    "placetype": [
      "aat:300008680"
    ],
    "id": 2270352,
    "name:xx": "Crystal Lake"
  }
}
