{
  "geometry": {
    "type": "Point",
    "coordinates": [
      -115.4333,
      39.15
    ]
  },
  "type": "Feature",
  "properties": {
    "hierarchy": [
      "tgn:2481524",
      "tgn:1000001",
      "tgn:7012149",
      "tgn:2001420",
      "tgn:7007526",
      "tgn:7029392"
    ],
    "placetype": [
      "aat:300008761"
    ],
    "id": 2481524,
    "name:xx": "Lampson Canyon"
  }
}
