{
  "geometry": {
    "type": "Point",
    "coordinates": [
      -100.35,
      44.4167
    ]
  },
  "type": "Feature",
  "properties": {
    "hierarchy": [
      "tgn:2390947",
      "tgn:1000001",
      "tgn:2001802",
      "tgn:7012149",
      "tgn:7007713",
      "tgn:7029392"
    ],
    "placetype": [
      "aat:300008761"
    ],
    "id": 2390947,
    "name:xx": "Hilgers Gulch"
  }
}
