{
  "geometry": {
    "type": "Point",
    "coordinates": [
      14.1833,
      26.35
    ]
  },
  "type": "Feature",
  "properties": {
    "hierarchy": [
      "tgn:1111541",
      "tgn:7001242",
      "tgn:7000613",
      "tgn:1000172",
      "tgn:7029392"
    ],
    "placetype": [
      "aat:300008773"
    ],
    "id": 1111541,
    "name:xx": "Nashūʻ, Wādī an"
  }
}
