{
  "geometry": {
    "type": "Point",
    "coordinates": [
      -16.3667,
      13.8833
    ]
  },
  "type": "Feature",
  "properties": {
    "hierarchy": [
      "tgn:1092546",
      "tgn:7016459",
      "tgn:7001242",
      "tgn:1000189",
      "tgn:7029392"
    ],
    "placetype": [
      "aat:300008347"
    ],
    "id": 1092546,
    "name:xx": "Sokone"
  }
}
