{
  "geometry": {
    "type": "Point",
    "coordinates": [
      45.5333,
      -25.55
    ]
  },
  "type": "Feature",
  "properties": {
    "hierarchy": [
      "tgn:1090888",
      "tgn:7001242",
      "tgn:1001575",
      "tgn:1000173",
      "tgn:7029392"
    ],
    "placetype": [
      "aat:300008347"
    ],
    "id": 1090888,
    "name:xx": "Faux-Cap"
  }
}
