{
  "geometry": {
    "type": "Point",
    "coordinates": [
      -122.8667,
      41.95
    ]
  },
  "type": "Feature",
  "properties": {
    "hierarchy": [
      "tgn:2240058",
      "tgn:1000001",
      "tgn:7012149",
      "tgn:7007157",
      "tgn:2000189",
      "tgn:7029392"
    ],
    "placetype": [
      "aat:300000390"
    ],
    "id": 2240058,
    "name:xx": "Cinnabar Mine"
  }
}
