{
  "geometry": {
    "type": "Point",
    "coordinates": [
      -107.0833,
      36.8667
    ]
  },
  "type": "Feature",
  "properties": {
    "hierarchy": [
      "tgn:2600420",
      "tgn:1000001",
      "tgn:7012149",
      "tgn:2001449",
      "tgn:7007566",
      "tgn:7029392"
    ],
    "placetype": [
      "aat:300008697"
    ],
    "id": 2600420,
    "name:xx": "Puerto Spring"
  }
}
