{
  "geometry": {
    "type": "Point",
    "coordinates": [
      113.8167,
      29.65
    ]
  },
  "type": "Feature",
  "properties": {
    "hierarchy": [
      "tgn:1067020",
      "tgn:1000004",
      "tgn:7002078",
      "tgn:1000111",
      "tgn:7029392"
    ],
    "placetype": [
      "aat:300008347"
    ],
    "id": 1067020,
    "name:xx": "Chaanling"
  }
}
