{
  "geometry": {
    "type": "Point",
    "coordinates": [
      -43.7333,
      -6.4833
    ]
  },
  "type": "Feature",
  "properties": {
    "hierarchy": [
      "tgn:1022820",
      "tgn:7006246",
      "tgn:1000047",
      "tgn:7002455",
      "tgn:1000002",
      "tgn:7029392"
    ],
    "placetype": [
      "aat:300008347"
    ],
    "id": 1022820,
    "name:xx": "São João dos Patos"
  }
}
