{
  "geometry": {
    "type": "Point",
    "coordinates": [
      -55.7333,
      -15.3333
    ]
  },
  "type": "Feature",
  "properties": {
    "hierarchy": [
      "tgn:1021157",
      "tgn:7006260",
      "tgn:7002454",
      "tgn:1000047",
      "tgn:1000002",
      "tgn:7029392"
    ],
    "placetype": [
      "aat:300008347"
    ],
    "id": 1021157,
    "name:xx": "Chapada dos Guimarães"
  }
}
