{
  "geometry": {
    "type": "Point",
    "coordinates": [
      -136.5833,
      59.7167
    ]
  },
  "type": "Feature",
  "properties": {
    "hierarchy": [
      "tgn:1108365",
      "tgn:7005735",
      "tgn:7005685",
      "tgn:1000001",
      "tgn:7029392"
    ],
    "placetype": [
      "aat:300259572"
    ],
    "id": 1108365,
    "name:xx": "Chilkat Pass"
  }
}
