{
  "geometry": {
    "type": "Point",
    "coordinates": [
      -88.0667,
      34.7667
    ]
  },
  "type": "Feature",
  "properties": {
    "hierarchy": [
      "tgn:2004380",
      "tgn:7002659",
      "tgn:1000001",
      "tgn:2000016",
      "tgn:7012149",
      "tgn:7029392"
    ],
    "placetype": [
      "aat:300008347"
    ],
    "id": 2004380,
    "name:xx": "Margerum"
  }
}
