{
  "geometry": {
    "type": "Point",
    "coordinates": [
      -84.9833,
      32.65
    ]
  },
  "type": "Feature",
  "properties": {
    "hierarchy": [
      "tgn:2224910",
      "tgn:1000001",
      "tgn:7012149",
      "tgn:2000363",
      "tgn:7007248",
      "tgn:7029392"
    ],
    "placetype": [
      "aat:300006191"
    ],
    "id": 2224910,
    "name:xx": "Casselberry Lake"
  }
}
