{
  "geometry": {
    "type": "Point",
    "coordinates": [
      -113.15,
      35.5667
    ]
  },
  "type": "Feature",
  "properties": {
    "hierarchy": [
      "tgn:2483526",
      "tgn:1000001",
      "tgn:7006451",
      "tgn:2000092",
      "tgn:7012149",
      "tgn:7029392"
    ],
    "placetype": [
      "aat:300006191"
    ],
    "id": 2483526,
    "name:xx": "Last Chance Tank"
  }
}
