{
  "geometry": {
    "type": "Point",
    "coordinates": [
      -82.6333,
      42.65
    ]
  },
  "type": "Feature",
  "properties": {
    "hierarchy": [
      "tgn:1112712",
      "tgn:1000001",
      "tgn:7012149",
      "tgn:7016056",
      "tgn:7007520",
      "tgn:7029392"
    ],
    "placetype": [
      "aat:300132316"
    ],
    "id": 1112712,
    "name:xx": "Bouvier Bay"
  }
}
