{
  "geometry": {
    "type": "Point",
    "coordinates": [
      -75.8833,
      36.5833
    ]
  },
  "type": "Feature",
  "properties": {
    "hierarchy": [
      "tgn:2263103",
      "tgn:1000001",
      "tgn:7012149",
      "tgn:7022218",
      "tgn:7007919",
      "tgn:7029392"
    ],
    "placetype": [
      "aat:300132316"
    ],
    "id": 2263103,
    "name:xx": "Cowpen Cove"
  }
}
