{
  "geometry": {
    "type": "Point",
    "coordinates": [
      -96.4667,
      36.5667
    ]
  },
  "type": "Feature",
  "properties": {
    "hierarchy": [
      "tgn:2291650",
      "tgn:1000001",
      "tgn:7012149",
      "tgn:2001679",
      "tgn:7007707",
      "tgn:7029392"
    ],
    "placetype": [
      "aat:300008761"
    ],
    "id": 2291650,
    "name:xx": "Dollie Hollow"
  }
}
