{
  "geometry": {
    "type": "Point",
    "coordinates": [
      31.346317,
      29.393673
    ]
  },
  "type": "Feature",
  "properties": {
    "hierarchy": [
      "tgn:7533739",
      "tgn:7001242",
      "tgn:7016833",
      "tgn:7029392"
    ],
    "placetype": [
      "aat:300379998"
    ],
    "name:en": "Jarr훮r카yah, W훮d카",
    "id": 7533739
  }
}
