{
  "geometry": {
    "type": "Point",
    "coordinates": [
      -107.4333,
      36.4667
    ]
  },
  "type": "Feature",
  "properties": {
    "hierarchy": [
      "tgn:2318137",
      "tgn:1000001",
      "tgn:7012149",
      "tgn:7007566",
      "tgn:7029392"
    ],
    "placetype": [
      "aat:300008798"
    ],
    "id": 2318137,
    "name:xx": "Ensenada Mesa"
  }
}
