{
  "geometry": {
    "type": "Point",
    "coordinates": [
      -81.2333,
      40.7333
    ]
  },
  "type": "Feature",
  "properties": {
    "hierarchy": [
      "tgn:2080573",
      "tgn:1000001",
      "tgn:7012149",
      "tgn:1002917",
      "tgn:7007706",
      "tgn:7029392"
    ],
    "placetype": [
      "aat:300008347"
    ],
    "id": 2080573,
    "name:xx": "Mapleton"
  }
}
