{
  "geometry": {
    "type": "Point",
    "coordinates": [
      -41.3667,
      -12.9833
    ]
  },
  "type": "Feature",
  "properties": {
    "hierarchy": [
      "tgn:1022170",
      "tgn:1001834",
      "tgn:1000047",
      "tgn:7002455",
      "tgn:1000002",
      "tgn:7029392"
    ],
    "placetype": [
      "aat:300008347"
    ],
    "id": 1022170,
    "name:xx": "Mucugê"
  }
}
