{
  "type": "FeatureCollection",
  "features": [
    {
      "geometry": {
        "type": "Point",
        "coordinates": [
          -112.6,
          37.8667
        ]
      },
      "type": "Feature",
      "properties": {
        "hierarchy": [
          "tgn:2727530",
          "tgn:1000001",
          "tgn:7012149",
          "tgn:2002111",
          "tgn:7007827",
          "tgn:7029392"
        ],
        "placetype": [
          "aat:300008706"
        ],
        "id": 2727530,
        "name:xx": "Trail Creek"
      }
    },
    {
      "geometry": {
        "type": "Point",
        "coordinates": [
          -110.6833,
          40.85
        ]
      },
      "type": "Feature",
      "properties": {
        "hierarchy": [
          "tgn:2727531",
          "tgn:1000001",
          "tgn:7012149",
          "tgn:2002122",
          "tgn:7007827",
          "tgn:7029392"
        ],
        "placetype": [
          "aat:300008706"
        ],
        "id": 2727531,
        "name:xx": "Trail Creek"
      }
    },
    {
      "geometry": {
        "type": "Point",
        "coordinates": [
          -109.5,
          40.8667
        ]
      },
      "type": "Feature",
      "properties": {
        "hierarchy": [
          "tgn:2727532",
          "tgn:1000001",
          "tgn:2002105",
          "tgn:7012149",
          "tgn:7007827",
          "tgn:7029392"
        ],
        "placetype": [
          "aat:300008706"
        ],
        "id": 2727532,
        "name:xx": "Trail Creek"
      }
    },
    {
      "geometry": {
        "type": "Point",
        "coordinates": [
          -111.5167,
          38.4
        ]
      },
      "type": "Feature",
      "properties": {
        "hierarchy": [
          "tgn:2727533",
          "tgn:1000001",
          "tgn:7012149",
          "tgn:2002128",
          "tgn:7007827",
          "tgn:7029392"
        ],
        "placetype": [
          "aat:300008706"
        ],
        "id": 2727533,
        "name:xx": "Trail Creek"
      }
    },
    {
      "geometry": {
        "type": "Point",
        "coordinates": [
          -120.5667,
          48.9667
        ]
      },
      "type": "Feature",
      "properties": {
        "hierarchy": [
          "tgn:2727534",
          "tgn:1000001",
          "tgn:7012149",
          "tgn:1002742",
          "tgn:7007920",
          "tgn:7029392"
        ],
        "placetype": [
          "aat:300008706"
        ],
        "id": 2727534,
        "name:xx": "Trail Creek"
      }
    },
    {
      "geometry": {
        "type": "Point",
        "coordinates": [
          -124.1667,
          47.9833
        ]
      },
      "type": "Feature",
      "properties": {
        "hierarchy": [
          "tgn:2727535",
          "tgn:1000001",
          "tgn:1002271",
          "tgn:7012149",
          "tgn:7007920",
          "tgn:7029392"
        ],
        "placetype": [
          "aat:300008706"
        ],
        "id": 2727535,
        "name:xx": "Trail Creek"
      }
    },
    {
      "geometry": {
        "type": "Point",
        "coordinates": [
          -120.3,
          47.1333
        ]
      },
      "type": "Feature",
      "properties": {
        "hierarchy": [
          "tgn:2727536",
          "tgn:1000001",
          "tgn:7012149",
          "tgn:1002553",
          "tgn:7007920",
          "tgn:7029392"
        ],
        "placetype": [
          "aat:300008706"
        ],
        "id": 2727536,
        "name:xx": "Trail Creek"
      }
    },
    {
      "geometry": {
        "type": "Point",
        "coordinates": [
          -121.1,
          47.5167
        ]
      },
      "type": "Feature",
      "properties": {
        "hierarchy": [
          "tgn:2727537",
          "tgn:1000001",
          "tgn:7012149",
          "tgn:7007920",
          "tgn:7029392"
        ],
        "placetype": [
          "aat:300008706"
        ],
        "id": 2727537,
        "name:xx": "Trail Creek"
      }
    },
    {
      "geometry": {
        "type": "Point",
        "coordinates": [
          -124.1833,
          47.5
        ]
      },
      "type": "Feature",
      "properties": {
        "hierarchy": [
          "tgn:2727538",
          "tgn:1000001",
          "tgn:7012149",
          "tgn:1002418",
          "tgn:7007920",
          "tgn:7029392"
        ],
        "placetype": [
          "aat:300008706"
        ],
        "id": 2727538,
        "name:xx": "Trail Creek"
      }
    },
    {
      "geometry": {
        "type": "Point",
        "coordinates": [
          -105.35,
          41.8167
        ]
      },
      "type": "Feature",
      "properties": {
        "hierarchy": [
          "tgn:2727539",
          "tgn:2002365",
          "tgn:1000001",
          "tgn:7012149",
          "tgn:7007923",
          "tgn:7029392"
        ],
        "placetype": [
          "aat:300008706"
        ],
        "id": 2727539,
        "name:xx": "Trail Creek"
      }
    }
  ]
}
