{
  "geometry": {
    "type": "Point",
    "coordinates": [
      -120.9167,
      39.2667
    ]
  },
  "type": "Feature",
  "properties": {
    "hierarchy": [
      "tgn:1120448",
      "tgn:1000001",
      "tgn:7012149",
      "tgn:7007157",
      "tgn:1002710",
      "tgn:7029392"
    ],
    "placetype": [
      "aat:300006191"
    ],
    "id": 1120448,
    "name:xx": "Scotts Flat Reservoir"
  }
}
