{
  "type": "FeatureCollection",
  "features": [
    {
      "geometry": {
        "type": "Point",
        "coordinates": [
          30.667984,
          31.026182
        ]
      },
      "type": "Feature",
      "properties": {
        "hierarchy": [
          "tgn:7532730",
          "tgn:7001242",
          "tgn:1001075",
          "tgn:7016833",
          "tgn:7029392"
        ],
        "placetype": [
          "aat:300008347"
        ],
        "name:en": "'Izbat Abū Fāţimah",
        "id": 7532730
      }
    },
    {
      "geometry": {
        "type": "Point",
        "coordinates": [
          30.67224,
          31.02088
        ]
      },
      "type": "Feature",
      "properties": {
        "hierarchy": [
          "tgn:7532731",
          "tgn:7001242",
          "tgn:1001075",
          "tgn:7016833",
          "tgn:7029392"
        ],
        "placetype": [
          "aat:300008347"
        ],
        "name:en": "'Izbat Sulaymān Shalabī",
        "id": 7532731
      }
    },
    {
      "geometry": {
        "type": "Point",
        "coordinates": [
          30.667016,
          31.015701
        ]
      },
      "type": "Feature",
      "properties": {
        "hierarchy": [
          "tgn:7532732",
          "tgn:7001242",
          "tgn:1001075",
          "tgn:7016833",
          "tgn:7029392"
        ],
        "placetype": [
          "aat:300008347"
        ],
        "name:en": "'Izbat aş Şanādīdī al Qiblīyah",
        "id": 7532732
      }
    },
    {
      "geometry": {
        "type": "Point",
        "coordinates": [
          30.676343,
          31.001724
        ]
      },
      "type": "Feature",
      "properties": {
        "hierarchy": [
          "tgn:7532733",
          "tgn:7001242",
          "tgn:1001075",
          "tgn:7016833",
          "tgn:7029392"
        ],
        "placetype": [
          "aat:300000206"
        ],
        "name:en": "'Izbat Abū Ḩannā",
        "id": 7532733
      }
    },
    {
      "geometry": {
        "type": "Point",
        "coordinates": [
          30.672524,
          31.007998
        ]
      },
      "type": "Feature",
      "properties": {
        "hierarchy": [
          "tgn:7532734",
          "tgn:7001242",
          "tgn:1001075",
          "tgn:7016833",
          "tgn:7029392"
        ],
        "placetype": [
          "aat:300008347"
        ],
        "name:en": "'Izbat Abū Dāwūd",
        "id": 7532734
      }
    },
    {
      "geometry": {
        "type": "Point",
        "coordinates": [
          30.657401,
          31.012335
        ]
      },
      "type": "Feature",
      "properties": {
        "hierarchy": [
          "tgn:7532735",
          "tgn:7001242",
          "tgn:1001075",
          "tgn:7016833",
          "tgn:7029392"
        ],
        "placetype": [
          "aat:300008347"
        ],
        "name:en": "Al Jarāyisah",
        "id": 7532735
      }
    },
    {
      "geometry": {
        "type": "Point",
        "coordinates": [
          30.659738,
          31.015582
        ]
      },
      "type": "Feature",
      "properties": {
        "hierarchy": [
          "tgn:7532736",
          "tgn:7001242",
          "tgn:1001075",
          "tgn:7016833",
          "tgn:7029392"
        ],
        "placetype": [
          "aat:300008347"
        ],
        "name:en": "'Izbat 'Abbās",
        "id": 7532736
      }
    },
    {
      "geometry": {
        "type": "Point",
        "coordinates": [
          30.648333,
          31.019444
        ]
      },
      "type": "Feature",
      "properties": {
        "hierarchy": [
          "tgn:7532737",
          "tgn:7001242",
          "tgn:1001075",
          "tgn:7016833",
          "tgn:7029392"
        ],
        "placetype": [
          "aat:300000206"
        ],
        "name:en": "'Izbat 'Umar",
        "id": 7532737
      }
    },
    {
      "geometry": {
        "type": "Point",
        "coordinates": [
          30.648521,
          31.019827
        ]
      },
      "type": "Feature",
      "properties": {
        "hierarchy": [
          "tgn:7532738",
          "tgn:7001242",
          "tgn:1001075",
          "tgn:7016833",
          "tgn:7029392"
        ],
        "placetype": [
          "aat:300008347"
        ],
        "name:en": "'Izbat 'Umar",
        "id": 7532738
      }
    },
    {
      "geometry": {
        "type": "Point",
        "coordinates": [
          30.636944,
          31.009167
        ]
      },
      "type": "Feature",
      "properties": {
        "hierarchy": [
          "tgn:7532739",
          "tgn:7001242",
          "tgn:1001075",
          "tgn:7016833",
          "tgn:7029392"
        ],
        "placetype": [
          "aat:300008347"
        ],
        "name:en": "'Izbat 'Uthmān Bayk",
        "id": 7532739
      }
    }
  ]
}
