{
  "geometry": {
    "type": "Point",
    "coordinates": [
      15.316,
      46.75
    ]
  },
  "type": "Feature",
  "properties": {
    "hierarchy": [
      "tgn:7030577",
      "tgn:7003028",
      "tgn:1000003",
      "tgn:1000062",
      "tgn:7029392"
    ],
    "placetype": [
      "aat:300008347"
    ],
    "id": 7030577,
    "name:xx": "Brunn"
  }
}
