{
  "geometry": {
    "type": "Point",
    "coordinates": [
      17.3667,
      -21.0167
    ]
  },
  "type": "Feature",
  "properties": {
    "hierarchy": [
      "tgn:1093990",
      "tgn:7001242",
      "tgn:7030594",
      "tgn:1000198",
      "tgn:7029392"
    ],
    "placetype": [
      "aat:300008347",
      "aat:300000206"
    ],
    "id": 1093990,
    "name:xx": "Osire Süd"
  }
}
