{
  "geometry": {
    "type": "Point",
    "coordinates": [
      74.852064,
      31.17935
    ]
  },
  "type": "Feature",
  "properties": {
    "hierarchy": [
      "tgn:7579217",
      "tgn:1000004",
      "tgn:7000198",
      "tgn:7016883",
      "tgn:7029392"
    ],
    "placetype": [
      "aat:300008347"
    ],
    "name:en": "Sobrāon",
    "id": 7579217
  }
}
