{
  "geometry": {
    "type": "Point",
    "coordinates": [
      -109.2833,
      34.0167
    ]
  },
  "type": "Feature",
  "properties": {
    "hierarchy": [
      "tgn:2477642",
      "tgn:2000090",
      "tgn:1000001",
      "tgn:7006451",
      "tgn:7012149",
      "tgn:7029392"
    ],
    "placetype": [
      "aat:300006191"
    ],
    "id": 2477642,
    "name:xx": "MVC Tank Number One"
  }
}
