{
  "geometry": {
    "type": "Point",
    "coordinates": [
      -105.9333,
      45.2167
    ]
  },
  "type": "Feature",
  "properties": {
    "hierarchy": [
      "tgn:2134926",
      "tgn:1000001",
      "tgn:7012149",
      "tgn:2001297",
      "tgn:7007524",
      "tgn:7029392"
    ],
    "placetype": [
      "aat:300006191"
    ],
    "id": 2134926,
    "name:xx": "Antelope Reservoir"
  }
}
