{
  "type": "FeatureCollection",
  "features": [
    {
      "geometry": {
        "type": "Point",
        "coordinates": [
          -103.7167,
          47.4667
        ]
      },
      "type": "Feature",
      "properties": {
        "hierarchy": [
          "tgn:2340280",
          "tgn:1000001",
          "tgn:2001583",
          "tgn:7012149",
          "tgn:7007705",
          "tgn:7029392"
        ],
        "placetype": [
          "aat:300008706"
        ],
        "id": 2340280,
        "name:xx": "French Creek"
      }
    },
    {
      "geometry": {
        "type": "Point",
        "coordinates": [
          -123.0333,
          42.8333
        ]
      },
      "type": "Feature",
      "properties": {
        "hierarchy": [
          "tgn:2340281",
          "tgn:1000001",
          "tgn:7012149",
          "tgn:2001706",
          "tgn:7007708",
          "tgn:7029392"
        ],
        "placetype": [
          "aat:300008706"
        ],
        "id": 2340281,
        "name:xx": "French Creek"
      }
    },
    {
      "geometry": {
        "type": "Point",
        "coordinates": [
          -117.4667,
          44.5167
        ]
      },
      "type": "Feature",
      "properties": {
        "hierarchy": [
          "tgn:2340282",
          "tgn:7013349",
          "tgn:1000001",
          "tgn:7012149",
          "tgn:7007708",
          "tgn:7029392"
        ],
        "placetype": [
          "aat:300008706"
        ],
        "id": 2340282,
        "name:xx": "French Creek"
      }
    },
    {
      "geometry": {
        "type": "Point",
        "coordinates": [
          -117.3167,
          45.1
        ]
      },
      "type": "Feature",
      "properties": {
        "hierarchy": [
          "tgn:2340283",
          "tgn:1000001",
          "tgn:7012149",
          "tgn:2001721",
          "tgn:7007708",
          "tgn:7029392"
        ],
        "placetype": [
          "aat:300008706"
        ],
        "id": 2340283,
        "name:xx": "French Creek"
      }
    },
    {
      "geometry": {
        "type": "Point",
        "coordinates": [
          -122.2167,
          44.7667
        ]
      },
      "type": "Feature",
      "properties": {
        "hierarchy": [
          "tgn:2340284",
          "tgn:1000001",
          "tgn:7012149",
          "tgn:1002636",
          "tgn:7007708",
          "tgn:7029392"
        ],
        "placetype": [
          "aat:300008706"
        ],
        "id": 2340284,
        "name:xx": "French Creek"
      }
    },
    {
      "geometry": {
        "type": "Point",
        "coordinates": [
          -117.3667,
          45.2667
        ]
      },
      "type": "Feature",
      "properties": {
        "hierarchy": [
          "tgn:2340285",
          "tgn:1000001",
          "tgn:7012149",
          "tgn:2001722",
          "tgn:7007708",
          "tgn:7029392"
        ],
        "placetype": [
          "aat:300008706"
        ],
        "id": 2340285,
        "name:xx": "French Creek"
      }
    },
    {
      "geometry": {
        "type": "Point",
        "coordinates": [
          -123.6667,
          45.6333
        ]
      },
      "type": "Feature",
      "properties": {
        "hierarchy": [
          "tgn:2340286",
          "tgn:1000001",
          "tgn:7012149",
          "tgn:1002943",
          "tgn:7007708",
          "tgn:7029392"
        ],
        "placetype": [
          "aat:300008706"
        ],
        "id": 2340286,
        "name:xx": "French Creek"
      }
    },
    {
      "geometry": {
        "type": "Point",
        "coordinates": [
          -118.75,
          42.1833
        ]
      },
      "type": "Feature",
      "properties": {
        "hierarchy": [
          "tgn:2340287",
          "tgn:1000001",
          "tgn:7012149",
          "tgn:2001709",
          "tgn:7007708",
          "tgn:7029392"
        ],
        "placetype": [
          "aat:300008706"
        ],
        "id": 2340287,
        "name:xx": "French Creek"
      }
    },
    {
      "geometry": {
        "type": "Point",
        "coordinates": [
          -76.4,
          41.6
        ]
      },
      "type": "Feature",
      "properties": {
        "hierarchy": [
          "tgn:2340288",
          "tgn:1000001",
          "tgn:1002194",
          "tgn:7012149",
          "tgn:7007710",
          "tgn:7029392"
        ],
        "placetype": [
          "aat:300008706"
        ],
        "id": 2340288,
        "name:xx": "French Creek"
      }
    },
    {
      "geometry": {
        "type": "Point",
        "coordinates": [
          -100.15,
          29.4
        ]
      },
      "type": "Feature",
      "properties": {
        "hierarchy": [
          "tgn:2340289",
          "tgn:1000001",
          "tgn:7012149",
          "tgn:2002021",
          "tgn:7007826",
          "tgn:7029392"
        ],
        "placetype": [
          "aat:300008706"
        ],
        "id": 2340289,
        "name:xx": "French Creek"
      }
    }
  ]
}
