{
  "geometry": {
    "type": "Point",
    "coordinates": [
      -77.4667,
      41.6667
    ]
  },
  "type": "Feature",
  "properties": {
    "hierarchy": [
      "tgn:2400906",
      "tgn:1000001",
      "tgn:7012149",
      "tgn:1002945",
      "tgn:7007710",
      "tgn:7029392"
    ],
    "placetype": [
      "aat:300008699"
    ],
    "id": 2400906,
    "name:xx": "Horse Run"
  }
}
