{
  "geometry": {
    "type": "Point",
    "coordinates": [
      -72.2167,
      41.65
    ]
  },
  "type": "Feature",
  "properties": {
    "hierarchy": [
      "tgn:2382632",
      "tgn:1000001",
      "tgn:1002714",
      "tgn:7012149",
      "tgn:7007159",
      "tgn:7029392"
    ],
    "placetype": [
      "aat:300006191"
    ],
    "id": 2382632,
    "name:xx": "Hayward Pond"
  }
}
