{
  "geometry": {
    "type": "Point",
    "coordinates": [
      -96.15,
      42.6833
    ]
  },
  "type": "Feature",
  "properties": {
    "hierarchy": [
      "tgn:2517283",
      "tgn:1000001",
      "tgn:7012149",
      "tgn:2000635",
      "tgn:7007253",
      "tgn:7029392"
    ],
    "placetype": [
      "aat:300008699"
    ],
    "id": 2517283,
    "name:xx": "Minnie Brook"
  }
}
