{
  "geometry": {
    "type": "Point",
    "coordinates": [
      -71.4333,
      41.7833
    ]
  },
  "type": "Feature",
  "properties": {
    "hierarchy": [
      "tgn:2495651",
      "tgn:1002808",
      "tgn:1000001",
      "tgn:7012149",
      "tgn:7007711",
      "tgn:7029392"
    ],
    "placetype": [
      "aat:300008699"
    ],
    "id": 2495651,
    "name:xx": "Mashapaug Brook"
  }
}
