{
  "geometry": {
    "type": "Point",
    "coordinates": [
      17.8833,
      59.95
    ]
  },
  "type": "Feature",
  "properties": {
    "hierarchy": [
      "tgn:1063500",
      "tgn:1000003",
      "tgn:1000462",
      "tgn:1000097",
      "tgn:7029392"
    ],
    "placetype": [
      "aat:300008347"
    ],
    "id": 1063500,
    "name:xx": "Rasbo"
  }
}
