{
  "geometry": {
    "type": "Point",
    "coordinates": [
      -83.0667,
      36.1667
    ]
  },
  "type": "Feature",
  "properties": {
    "hierarchy": [
      "tgn:2101546",
      "tgn:1000001",
      "tgn:7012149",
      "tgn:2001866",
      "tgn:7007825",
      "tgn:7029392"
    ],
    "placetype": [
      "aat:300008347",
      "aat:300387210"
    ],
    "id": 2101546,
    "name:xx": "Skinner Crossroad"
  }
}
