{
  "geometry": {
    "type": "Point",
    "coordinates": [
      -3.85,
      39.95
    ]
  },
  "type": "Feature",
  "properties": {
    "hierarchy": [
      "tgn:7347767",
      "tgn:7002847",
      "tgn:1001647",
      "tgn:1000003",
      "tgn:1000095",
      "tgn:7029392"
    ],
    "placetype": [
      "aat:300008347"
    ],
    "id": 7347767,
    "name:xx": "Aceca"
  }
}
