{
  "geometry": {
    "type": "Point",
    "coordinates": [
      -92.9167,
      37.5333
    ]
  },
  "type": "Feature",
  "properties": {
    "hierarchy": [
      "tgn:2748190",
      "tgn:1000001",
      "tgn:7012149",
      "tgn:2001192",
      "tgn:7007523",
      "tgn:7029392"
    ],
    "placetype": [
      "aat:300008699"
    ],
    "id": 2748190,
    "name:xx": "Walker Branch"
  }
}
