{
  "geometry": {
    "type": "Point",
    "coordinates": [
      -78.1333,
      38.4333
    ]
  },
  "type": "Feature",
  "properties": {
    "hierarchy": [
      "tgn:2112661",
      "tgn:1000001",
      "tgn:7012149",
      "tgn:2002178",
      "tgn:7007919",
      "tgn:7029392"
    ],
    "placetype": [
      "aat:300008347"
    ],
    "id": 2112661,
    "name:xx": "Leon"
  }
}
