{
  "geometry": {
    "type": "Point",
    "coordinates": [
      121.0958,
      22.7979
    ]
  },
  "type": "Feature",
  "properties": {
    "hierarchy": [
      "tgn:7498753",
      "tgn:1000004",
      "tgn:7491221",
      "tgn:1000141",
      "tgn:7029392"
    ],
    "placetype": [
      "aat:300006156"
    ],
    "id": 7498753,
    "name:xx": "Taiping Zuoti"
  }
}
