{
  "geometry": {
    "type": "Point",
    "coordinates": [
      -76.6333,
      35.3167
    ]
  },
  "type": "Feature",
  "properties": {
    "hierarchy": [
      "tgn:2711662",
      "tgn:1000001",
      "tgn:7013368",
      "tgn:7012149",
      "tgn:7007709",
      "tgn:7029392"
    ],
    "placetype": [
      "aat:300008699"
    ],
    "id": 2711662,
    "name:xx": "Tar Landing Gut"
  }
}
