{
  "geometry": {
    "type": "Point",
    "coordinates": [
      -115.9333,
      47.8667
    ]
  },
  "type": "Feature",
  "properties": {
    "hierarchy": [
      "tgn:2188557",
      "tgn:1000001",
      "tgn:7012149",
      "tgn:7029392"
    ],
    "placetype": [
      "aat:300008798"
    ],
    "id": 2188557,
    "name:xx": "Bottle Point"
  }
}
