{
  "geometry": {
    "type": "Point",
    "coordinates": [
      -81.4833,
      31.3667
    ]
  },
  "type": "Feature",
  "properties": {
    "hierarchy": [
      "tgn:2215648",
      "tgn:1000001",
      "tgn:7012149",
      "tgn:2000386",
      "tgn:7007248",
      "tgn:7029392"
    ],
    "placetype": [
      "aat:300008791"
    ],
    "id": 2215648,
    "name:xx": "Cambers Island"
  }
}
