{
  "geometry": {
    "type": "Point",
    "coordinates": [
      -96.3333,
      39.3667
    ]
  },
  "type": "Feature",
  "properties": {
    "hierarchy": [
      "tgn:2199426",
      "tgn:1000001",
      "tgn:7012149",
      "tgn:2000734",
      "tgn:7007254",
      "tgn:7029392"
    ],
    "placetype": [
      "aat:300008706"
    ],
    "id": 2199426,
    "name:xx": "Brush Creek"
  }
}
