{
  "geometry": {
    "type": "Point",
    "coordinates": [
      -106.75,
      40.8833
    ]
  },
  "type": "Feature",
  "properties": {
    "hierarchy": [
      "tgn:2640931",
      "tgn:1000001",
      "tgn:7012149",
      "tgn:2000220",
      "tgn:7007158",
      "tgn:7029392"
    ],
    "placetype": [
      "aat:300008680"
    ],
    "id": 2640931,
    "name:xx": "Sanchez Lakes"
  }
}
