{
  "type": "FeatureCollection",
  "features": [
    {
      "geometry": {
        "type": "Point",
        "coordinates": [
          -105.283333,
          24.05
        ]
      },
      "type": "Feature",
      "properties": {
        "hierarchy": [
          "tgn:7351230",
          "tgn:7005583",
          "tgn:1000001",
          "tgn:7005560",
          "tgn:7029392"
        ],
        "placetype": [
          "aat:300008347"
        ],
        "id": 7351230,
        "name:xx": "Cachanas"
      }
    },
    {
      "geometry": {
        "type": "Point",
        "coordinates": [
          -98.366667,
          16.716667
        ]
      },
      "type": "Feature",
      "properties": {
        "hierarchy": [
          "tgn:7351232",
          "tgn:7005585",
          "tgn:1000001",
          "tgn:7005560",
          "tgn:7029392"
        ],
        "placetype": [
          "aat:300008347"
        ],
        "id": 7351232,
        "name:xx": "Cachalapa"
      }
    },
    {
      "geometry": {
        "type": "Point",
        "coordinates": [
          -92.45,
          15.066667
        ]
      },
      "type": "Feature",
      "properties": {
        "hierarchy": [
          "tgn:7351233",
          "tgn:7005580",
          "tgn:1000001",
          "tgn:7005560",
          "tgn:7029392"
        ],
        "placetype": [
          "aat:300008699"
        ],
        "id": 7351233,
        "name:xx": "Cacee, Arroyo del"
      }
    },
    {
      "geometry": {
        "type": "Point",
        "coordinates": [
          -110.366667,
          30.5
        ]
      },
      "type": "Feature",
      "properties": {
        "hierarchy": [
          "tgn:7351234",
          "tgn:1000001",
          "tgn:1001960",
          "tgn:7005560",
          "tgn:7029392"
        ],
        "placetype": [
          "aat:300008795"
        ],
        "id": 7351234,
        "name:xx": "Cacaxtle, Cerro"
      }
    },
    {
      "geometry": {
        "type": "Point",
        "coordinates": [
          -92.833333,
          16.866667
        ]
      },
      "type": "Feature",
      "properties": {
        "hierarchy": [
          "tgn:7351235",
          "tgn:7005580",
          "tgn:1000001",
          "tgn:7005560",
          "tgn:7029392"
        ],
        "placetype": [
          "aat:300008347"
        ],
        "id": 7351235,
        "name:xx": "Cacate"
      }
    },
    {
      "geometry": {
        "type": "Point",
        "coordinates": [
          -107.083333,
          26.2
        ]
      },
      "type": "Feature",
      "properties": {
        "hierarchy": [
          "tgn:7351236",
          "tgn:7005581",
          "tgn:1000001",
          "tgn:7005560",
          "tgn:7029392"
        ],
        "placetype": [
          "aat:300000241"
        ],
        "id": 7351236,
        "name:xx": "Rancho Cacaste"
      }
    },
    {
      "geometry": {
        "type": "Point",
        "coordinates": [
          -104.85,
          24.3
        ]
      },
      "type": "Feature",
      "properties": {
        "hierarchy": [
          "tgn:7351237",
          "tgn:7005583",
          "tgn:1000001",
          "tgn:7005560",
          "tgn:7029392"
        ],
        "placetype": [
          "aat:300008777"
        ],
        "id": 7351237,
        "name:xx": "Cacaria, Sierra de"
      }
    },
    {
      "geometry": {
        "type": "Point",
        "coordinates": [
          -104.733333,
          24.4
        ]
      },
      "type": "Feature",
      "properties": {
        "hierarchy": [
          "tgn:7351238",
          "tgn:7005583",
          "tgn:1000001",
          "tgn:7005560",
          "tgn:7029392"
        ],
        "placetype": [
          "aat:300007783"
        ],
        "id": 7351238,
        "name:xx": "Cacaria"
      }
    },
    {
      "geometry": {
        "type": "Point",
        "coordinates": [
          -104.75,
          24.4
        ]
      },
      "type": "Feature",
      "properties": {
        "hierarchy": [
          "tgn:7351239",
          "tgn:7005583",
          "tgn:1000001",
          "tgn:7005560",
          "tgn:7029392"
        ],
        "placetype": [
          "aat:300008347"
        ],
        "id": 7351239,
        "name:xx": "Cacaria"
      }
    }
  ]
}
