{
  "geometry": {
    "type": "Point",
    "coordinates": [
      -87.9667,
      38.15
    ]
  },
  "type": "Feature",
  "properties": {
    "hierarchy": [
      "tgn:2593182",
      "tgn:1000001",
      "tgn:7012149",
      "tgn:2000537",
      "tgn:7007251",
      "tgn:7029392"
    ],
    "placetype": [
      "aat:300266640"
    ],
    "id": 2593182,
    "name:xx": "Poplar Ridge"
  }
}
