{
  "geometry": {
    "type": "Point",
    "coordinates": [
      -74.7667,
      43.2667
    ]
  },
  "type": "Feature",
  "properties": {
    "hierarchy": [
      "tgn:2372869",
      "tgn:1000001",
      "tgn:7012149",
      "tgn:1002472",
      "tgn:7007568",
      "tgn:7029392"
    ],
    "placetype": [
      "aat:300008905"
    ],
    "id": 2372869,
    "name:xx": "Hall Vly"
  }
}
