{
  "geometry": {
    "type": "Point",
    "coordinates": [
      -68.4167,
      44.45
    ]
  },
  "type": "Feature",
  "properties": {
    "hierarchy": [
      "tgn:2183491",
      "tgn:1000001",
      "tgn:2000922",
      "tgn:7012149",
      "tgn:7007515",
      "tgn:7029392"
    ],
    "placetype": [
      "aat:300008850"
    ],
    "id": 2183491,
    "name:xx": "Bluff Point"
  }
}
