{
  "geometry": {
    "type": "Point",
    "coordinates": [
      -76.55,
      37.9667
    ]
  },
  "type": "Feature",
  "properties": {
    "hierarchy": [
      "tgn:2110914",
      "tgn:1000001",
      "tgn:7012149",
      "tgn:1002733",
      "tgn:7007919",
      "tgn:7029392"
    ],
    "placetype": [
      "aat:300008347"
    ],
    "id": 2110914,
    "name:xx": "Callao"
  }
}
