{
  "geometry": {
    "type": "Point",
    "coordinates": [
      31.630501,
      29.701687
    ]
  },
  "type": "Feature",
  "properties": {
    "hierarchy": [
      "tgn:7534105",
      "tgn:7001242",
      "tgn:7016833",
      "tgn:7029392"
    ],
    "placetype": [
      "aat:300379998"
    ],
    "name:en": "Ḩasanī, Wādī",
    "id": 7534105
  }
}
