{
  "geometry": {
    "type": "Point",
    "coordinates": [
      -132.7333,
      54.8333
    ]
  },
  "type": "Feature",
  "properties": {
    "hierarchy": [
      "tgn:2185935",
      "tgn:7006450",
      "tgn:1000001",
      "tgn:7012149",
      "tgn:2000082",
      "tgn:7029392"
    ],
    "placetype": [
      "aat:300132316"
    ],
    "id": 2185935,
    "name:xx": "Bolles Inlet"
  }
}
