{
  "geometry": {
    "type": "Point",
    "coordinates": [
      81.257121,
      20.78945
    ]
  },
  "type": "Feature",
  "properties": {
    "hierarchy": [
      "tgn:7576612",
      "tgn:1000004",
      "tgn:7031781",
      "tgn:7000198",
      "tgn:7029392"
    ],
    "placetype": [
      "aat:300008347"
    ],
    "name:en": "Lātābor",
    "id": 7576612
  }
}
