{
  "geometry": {
    "type": "Point",
    "coordinates": [
      90.0167,
      25.0167
    ]
  },
  "type": "Feature",
  "properties": {
    "hierarchy": [
      "tgn:1138731",
      "tgn:7000189",
      "tgn:1000004",
      "tgn:1000105",
      "tgn:7029392"
    ],
    "placetype": [
      "aat:300008347"
    ],
    "id": 1138731,
    "name:xx": "Sherpur"
  }
}
