{
  "geometry": {
    "type": "Point",
    "coordinates": [
      75.1167,
      35.05
    ]
  },
  "type": "Feature",
  "properties": {
    "hierarchy": [
      "tgn:1083402",
      "tgn:7000367",
      "tgn:1000004",
      "tgn:1000133",
      "tgn:7029392"
    ],
    "placetype": [
      "aat:300008347"
    ],
    "id": 1083402,
    "name:xx": "Chilam"
  }
}
