{
  "type": "FeatureCollection",
  "features": [
    {
      "geometry": {
        "type": "Point",
        "coordinates": [
          -107.4833,
          37.6
        ]
      },
      "type": "Feature",
      "properties": {
        "hierarchy": [
          "tgn:2577330",
          "tgn:1000001",
          "tgn:7012149",
          "tgn:2000225",
          "tgn:7007158",
          "tgn:7029392"
        ],
        "placetype": [
          "aat:300008798"
        ],
        "id": 2577330,
        "name:xx": "Peters Peak"
      }
    },
    {
      "geometry": {
        "type": "Point",
        "coordinates": [
          -83.1833,
          37.25
        ]
      },
      "type": "Feature",
      "properties": {
        "hierarchy": [
          "tgn:2577331",
          "tgn:1000001",
          "tgn:7012149",
          "tgn:2000836",
          "tgn:7007255",
          "tgn:7029392"
        ],
        "placetype": [
          "aat:300008798"
        ],
        "id": 2577331,
        "name:xx": "Peters Peak"
      }
    },
    {
      "geometry": {
        "type": "Point",
        "coordinates": [
          -155.1,
          59.3833
        ]
      },
      "type": "Feature",
      "properties": {
        "hierarchy": [
          "tgn:2577332",
          "tgn:7006450",
          "tgn:1000001",
          "tgn:7030517",
          "tgn:7012149",
          "tgn:7029392"
        ],
        "placetype": [
          "aat:300008798"
        ],
        "id": 2577332,
        "name:xx": "Peters Plug"
      }
    },
    {
      "geometry": {
        "type": "Point",
        "coordinates": [
          -113.4833,
          36.0833
        ]
      },
      "type": "Feature",
      "properties": {
        "hierarchy": [
          "tgn:2577333",
          "tgn:1000001",
          "tgn:7006451",
          "tgn:7012149",
          "tgn:2000098",
          "tgn:7029392"
        ],
        "placetype": [
          "aat:300008680"
        ],
        "id": 2577333,
        "name:xx": "Peters Pocket"
      }
    },
    {
      "geometry": {
        "type": "Point",
        "coordinates": [
          -94.0333,
          35.65
        ]
      },
      "type": "Feature",
      "properties": {
        "hierarchy": [
          "tgn:2577334",
          "tgn:1000001",
          "tgn:7016172",
          "tgn:7012149",
          "tgn:2000128",
          "tgn:7029392"
        ],
        "placetype": [
          "aat:300008798"
        ],
        "id": 2577334,
        "name:xx": "Peters Point"
      }
    },
    {
      "geometry": {
        "type": "Point",
        "coordinates": [
          -116.7,
          43.0667
        ]
      },
      "type": "Feature",
      "properties": {
        "hierarchy": [
          "tgn:2577335",
          "tgn:1000001",
          "tgn:7012149",
          "tgn:2000488",
          "tgn:7007250",
          "tgn:7029392"
        ],
        "placetype": [
          "aat:300266640"
        ],
        "id": 2577335,
        "name:xx": "Peters Point"
      }
    },
    {
      "geometry": {
        "type": "Point",
        "coordinates": [
          -68.5667,
          44.4
        ]
      },
      "type": "Feature",
      "properties": {
        "hierarchy": [
          "tgn:2577336",
          "tgn:1000001",
          "tgn:2000922",
          "tgn:7012149",
          "tgn:7007515",
          "tgn:7029392"
        ],
        "placetype": [
          "aat:300008850"
        ],
        "id": 2577336,
        "name:xx": "Peters Point"
      }
    },
    {
      "geometry": {
        "type": "Point",
        "coordinates": [
          -71.1,
          41.8167
        ]
      },
      "type": "Feature",
      "properties": {
        "hierarchy": [
          "tgn:2577337",
          "tgn:1002201",
          "tgn:1000001",
          "tgn:7012149",
          "tgn:7007517",
          "tgn:7029392"
        ],
        "placetype": [
          "aat:300008850"
        ],
        "id": 2577337,
        "name:xx": "Peters Point"
      }
    },
    {
      "geometry": {
        "type": "Point",
        "coordinates": [
          -70.9,
          42.5333
        ]
      },
      "type": "Feature",
      "properties": {
        "hierarchy": [
          "tgn:2577338",
          "tgn:1000001",
          "tgn:1002359",
          "tgn:7012149",
          "tgn:7007517",
          "tgn:7029392"
        ],
        "placetype": [
          "aat:300008850"
        ],
        "id": 2577338,
        "name:xx": "Peters Point"
      }
    },
    {
      "geometry": {
        "type": "Point",
        "coordinates": [
          -77.9167,
          33.9833
        ]
      },
      "type": "Feature",
      "properties": {
        "hierarchy": [
          "tgn:2577339",
          "tgn:1000001",
          "tgn:7012149",
          "tgn:2001523",
          "tgn:7007709",
          "tgn:7029392"
        ],
        "placetype": [
          "aat:300008850"
        ],
        "id": 2577339,
        "name:xx": "Peters Point"
      }
    }
  ]
}
