{
  "geometry": {
    "type": "Point",
    "coordinates": [
      -93.5833,
      36.4333
    ]
  },
  "type": "Feature",
  "properties": {
    "hierarchy": [
      "tgn:2342373",
      "tgn:1000001",
      "tgn:7016172",
      "tgn:2000112",
      "tgn:7012149",
      "tgn:7029392"
    ],
    "placetype": [
      "aat:300006191"
    ],
    "id": 2342373,
    "name:xx": "Fuller Lake"
  }
}
