{
  "geometry": {
    "type": "Point",
    "coordinates": [
      -123.8667,
      43.75
    ]
  },
  "type": "Feature",
  "properties": {
    "hierarchy": [
      "tgn:2712775",
      "tgn:1000001",
      "tgn:7012149",
      "tgn:2001706",
      "tgn:7007708",
      "tgn:7029392"
    ],
    "placetype": [
      "aat:300008706"
    ],
    "id": 2712775,
    "name:xx": "Taylor Creek"
  }
}
