{
  "type": "FeatureCollection",
  "features": [
    {
      "geometry": {
        "type": "Point",
        "coordinates": [
          -3.6,
          52.25
        ]
      },
      "type": "Feature",
      "properties": {
        "hierarchy": [
          "tgn:1122891",
          "tgn:7002443",
          "tgn:1000003",
          "tgn:7008050",
          "tgn:7008591",
          "tgn:7029392"
        ],
        "placetype": [
          "aat:300008707",
          "aat:300008699"
        ],
        "name:en": "Claerwen",
        "id": 1122891
      }
    },
    {
      "geometry": {
        "type": "Point",
        "coordinates": [
          2.75,
          48.1167
        ]
      },
      "type": "Feature",
      "properties": {
        "hierarchy": [
          "tgn:1122893",
          "tgn:1000003",
          "tgn:1000070",
          "tgn:7029392"
        ],
        "placetype": [
          "aat:300008707"
        ],
        "id": 1122893,
        "name:xx": "Clairis"
      }
    },
    {
      "geometry": {
        "type": "Point",
        "coordinates": [
          -85.4,
          44.25
        ]
      },
      "type": "Feature",
      "properties": {
        "hierarchy": [
          "tgn:1122894",
          "tgn:1000001",
          "tgn:7012149",
          "tgn:7007520",
          "tgn:7029392"
        ],
        "placetype": [
          "aat:300008707"
        ],
        "id": 1122894,
        "name:xx": "Clam"
      }
    },
    {
      "geometry": {
        "type": "Point",
        "coordinates": [
          -92.25,
          45.55
        ]
      },
      "type": "Feature",
      "properties": {
        "hierarchy": [
          "tgn:1122895",
          "tgn:1000001",
          "tgn:7012149",
          "tgn:7007922",
          "tgn:7029392"
        ],
        "placetype": [
          "aat:300008707"
        ],
        "id": 1122895,
        "name:xx": "Clam"
      }
    },
    {
      "geometry": {
        "type": "Point",
        "coordinates": [
          -77.2833,
          44.4667
        ]
      },
      "type": "Feature",
      "properties": {
        "hierarchy": [
          "tgn:1122898",
          "tgn:7005685",
          "tgn:1000001",
          "tgn:7013154",
          "tgn:7029392"
        ],
        "placetype": [
          "aat:300008707"
        ],
        "id": 1122898,
        "name:xx": "Clare"
      }
    },
    {
      "geometry": {
        "type": "Point",
        "coordinates": [
          -9.05,
          53.3333
        ]
      },
      "type": "Feature",
      "properties": {
        "hierarchy": [
          "tgn:1122899",
          "tgn:7003479",
          "tgn:7001198",
          "tgn:1000003",
          "tgn:1000078",
          "tgn:7029392"
        ],
        "placetype": [
          "aat:300008707"
        ],
        "id": 1122899,
        "name:xx": "Clare"
      }
    }
  ]
}
