{
  "geometry": {
    "type": "Point",
    "coordinates": [
      -82.8167,
      40.35
    ]
  },
  "type": "Feature",
  "properties": {
    "hierarchy": [
      "tgn:2081287",
      "tgn:1000001",
      "tgn:7012149",
      "tgn:1002697",
      "tgn:7007706",
      "tgn:7029392"
    ],
    "placetype": [
      "aat:300008347"
    ],
    "id": 2081287,
    "name:xx": "Pagetown"
  }
}
