{
  "geometry": {
    "type": "Point",
    "coordinates": [
      -80.2167,
      37.3333
    ]
  },
  "type": "Feature",
  "properties": {
    "hierarchy": [
      "tgn:2618003",
      "tgn:1000001",
      "tgn:7012149",
      "tgn:7014344",
      "tgn:7007919",
      "tgn:7029392"
    ],
    "placetype": [
      "aat:300266640"
    ],
    "id": 2618003,
    "name:xx": "Ridges, The"
  }
}
