{
  "geometry": {
    "type": "Point",
    "coordinates": [
      -101.9167,
      40.4833
    ]
  },
  "type": "Feature",
  "properties": {
    "hierarchy": [
      "tgn:2491819",
      "tgn:1000001",
      "tgn:2001330",
      "tgn:7012149",
      "tgn:7007525",
      "tgn:7029392"
    ],
    "placetype": [
      "aat:300006075"
    ],
    "id": 2491819,
    "name:xx": "Maranville Canal"
  }
}
