{
  "geometry": {
    "type": "Point",
    "coordinates": [
      -145.6833,
      64.7833
    ]
  },
  "type": "Feature",
  "properties": {
    "hierarchy": [
      "tgn:2211239",
      "tgn:7006450",
      "tgn:1000001",
      "tgn:7019674",
      "tgn:7012149",
      "tgn:7029392"
    ],
    "placetype": [
      "aat:300008706"
    ],
    "id": 2211239,
    "name:xx": "Butte Creek"
  }
}
