{
  "geometry": {
    "type": "Point",
    "coordinates": [
      -90.85,
      33.5833
    ]
  },
  "type": "Feature",
  "properties": {
    "hierarchy": [
      "tgn:2155101",
      "tgn:1000001",
      "tgn:7012149",
      "tgn:7007522",
      "tgn:7029392"
    ],
    "placetype": [
      "aat:300008699"
    ],
    "id": 2155101,
    "name:xx": "Bear Lake"
  }
}
