{
  "type": "FeatureCollection",
  "features": [
    {
      "geometry": {
        "type": "Point",
        "coordinates": [
          -96.8,
          32.85
        ]
      },
      "type": "Feature",
      "properties": {
        "hierarchy": [
          "tgn:2108180",
          "tgn:1000001",
          "tgn:7012149",
          "tgn:1002315",
          "tgn:7007826",
          "tgn:7029392"
        ],
        "placetype": [
          "aat:300008347"
        ],
        "id": 2108180,
        "name:xx": "University Park"
      }
    },
    {
      "geometry": {
        "type": "Point",
        "coordinates": [
          -97.3333,
          28.9167
        ]
      },
      "type": "Feature",
      "properties": {
        "hierarchy": [
          "tgn:2108184",
          "tgn:1000001",
          "tgn:7012149",
          "tgn:7021746",
          "tgn:7007826",
          "tgn:7029392"
        ],
        "placetype": [
          "aat:300008347",
          "aat:300387210"
        ],
        "id": 2108184,
        "name:xx": "Upper Meyersville"
      }
    },
    {
      "geometry": {
        "type": "Point",
        "coordinates": [
          -97.25,
          30
        ]
      },
      "type": "Feature",
      "properties": {
        "hierarchy": [
          "tgn:2108186",
          "tgn:1000001",
          "tgn:1002168",
          "tgn:7012149",
          "tgn:7007826",
          "tgn:7029392"
        ],
        "placetype": [
          "aat:300008347",
          "aat:300387210"
        ],
        "id": 2108186,
        "name:xx": "Upton"
      }
    },
    {
      "geometry": {
        "type": "Point",
        "coordinates": [
          -94.95,
          30.55
        ]
      },
      "type": "Feature",
      "properties": {
        "hierarchy": [
          "tgn:2108187",
          "tgn:1000001",
          "tgn:7012149",
          "tgn:1002860",
          "tgn:7007826",
          "tgn:7029392"
        ],
        "placetype": [
          "aat:300008347",
          "aat:300387210"
        ],
        "id": 2108187,
        "name:xx": "Urbana"
      }
    },
    {
      "geometry": {
        "type": "Point",
        "coordinates": [
          -97.4167,
          30.1667
        ]
      },
      "type": "Feature",
      "properties": {
        "hierarchy": [
          "tgn:2108188",
          "tgn:1000001",
          "tgn:1002168",
          "tgn:7012149",
          "tgn:7007826",
          "tgn:7029392"
        ],
        "placetype": [
          "aat:300008347",
          "aat:300387210"
        ],
        "id": 2108188,
        "name:xx": "Utley"
      }
    },
    {
      "geometry": {
        "type": "Point",
        "coordinates": [
          -99.5167,
          29.6
        ]
      },
      "type": "Feature",
      "properties": {
        "hierarchy": [
          "tgn:2108189",
          "tgn:1000001",
          "tgn:7012149",
          "tgn:2002087",
          "tgn:7007826",
          "tgn:7029392"
        ],
        "placetype": [
          "aat:300008347"
        ],
        "id": 2108189,
        "name:xx": "Utopia"
      }
    }
  ]
}
