{
  "geometry": {
    "type": "Point",
    "coordinates": [
      -105.4667,
      47.0667
    ]
  },
  "type": "Feature",
  "properties": {
    "hierarchy": [
      "tgn:2199320",
      "tgn:1000001",
      "tgn:7012149",
      "tgn:2001299",
      "tgn:7007524",
      "tgn:7029392"
    ],
    "placetype": [
      "aat:300008761"
    ],
    "id": 2199320,
    "name:xx": "Brush Coulee"
  }
}
