{
  "geometry": {
    "type": "Point",
    "coordinates": [
      -86.0333,
      44.0167
    ]
  },
  "type": "Feature",
  "properties": {
    "hierarchy": [
      "tgn:2265098",
      "tgn:1000001",
      "tgn:7012149",
      "tgn:2000976",
      "tgn:7007520",
      "tgn:7029392"
    ],
    "placetype": [
      "aat:300008680"
    ],
    "id": 2265098,
    "name:xx": "Cranberry Lake"
  }
}
