{
  "geometry": {
    "type": "Point",
    "coordinates": [
      81.3167,
      29.6167
    ]
  },
  "type": "Feature",
  "properties": {
    "hierarchy": [
      "tgn:1083320",
      "tgn:7001433",
      "tgn:7001420",
      "tgn:1000004",
      "tgn:1000132",
      "tgn:7029392"
    ],
    "placetype": [
      "aat:300008347"
    ],
    "id": 1083320,
    "name:xx": "Tālkot"
  }
}
