{
  "geometry": {
    "type": "Point",
    "coordinates": [
      32.979012,
      31.015843
    ]
  },
  "type": "Feature",
  "properties": {
    "hierarchy": [
      "tgn:7531778",
      "tgn:7001242",
      "tgn:7016833",
      "tgn:7001335",
      "tgn:7029392"
    ],
    "placetype": [
      "aat:300387498"
    ],
    "id": 7531778,
    "name:xx": "Abu Nafil, Ḥôḍ"
  }
}
