{
  "geometry": {
    "type": "Point",
    "coordinates": [
      -86.5667,
      34.7167
    ]
  },
  "type": "Feature",
  "properties": {
    "hierarchy": [
      "tgn:2310703",
      "tgn:7002659",
      "tgn:1000001",
      "tgn:7012149",
      "tgn:2000044",
      "tgn:7029392"
    ],
    "placetype": [
      "aat:300008347"
    ],
    "id": 2310703,
    "name:xx": "Echols Hill"
  }
}
