{
  "geometry": {
    "type": "Point",
    "coordinates": [
      -87.05,
      36.7167
    ]
  },
  "type": "Feature",
  "properties": {
    "hierarchy": [
      "tgn:2037467",
      "tgn:1000001",
      "tgn:7012149",
      "tgn:2000845",
      "tgn:7007255",
      "tgn:7029392"
    ],
    "placetype": [
      "aat:300008347"
    ],
    "id": 2037467,
    "name:xx": "Allensville"
  }
}
