{
  "geometry": {
    "type": "Point",
    "coordinates": [
      -118.8667,
      38.2833
    ]
  },
  "type": "Feature",
  "properties": {
    "hierarchy": [
      "tgn:2235366",
      "tgn:1000001",
      "tgn:2001417",
      "tgn:7012149",
      "tgn:7007526",
      "tgn:7029392"
    ],
    "placetype": [
      "aat:300000390"
    ],
    "id": 2235366,
    "name:xx": "Chesco Mine"
  }
}
