{
  "geometry": {
    "type": "Point",
    "coordinates": [
      51.2167,
      35.8167
    ]
  },
  "type": "Feature",
  "properties": {
    "hierarchy": [
      "tgn:1079164",
      "tgn:1000004",
      "tgn:7002004",
      "tgn:7000231",
      "tgn:7029392"
    ],
    "placetype": [
      "aat:300008347"
    ],
    "id": 1079164,
    "name:xx": "Kishar Bāla"
  }
}
