{
  "geometry": {
    "type": "Point",
    "coordinates": [
      -44.2167,
      -21.4833
    ]
  },
  "type": "Feature",
  "properties": {
    "hierarchy": [
      "tgn:1132732",
      "tgn:7006237",
      "tgn:1000047",
      "tgn:7002457",
      "tgn:1000002",
      "tgn:7029392"
    ],
    "placetype": [
      "aat:300008706"
    ],
    "id": 1132732,
    "name:xx": "Cavalos, Ribeirão dos"
  }
}
