{
  "geometry": {
    "type": "Point",
    "coordinates": [
      -151.55,
      59.65
    ]
  },
  "type": "Feature",
  "properties": {
    "hierarchy": [
      "tgn:2286444",
      "tgn:7006450",
      "tgn:1000001",
      "tgn:7019698",
      "tgn:7012149",
      "tgn:7029392"
    ],
    "placetype": [
      "aat:300008706"
    ],
    "id": 2286444,
    "name:xx": "Diamond Creek"
  }
}
