{
  "geometry": {
    "type": "Point",
    "coordinates": [
      108.3667,
      -7.1833
    ]
  },
  "type": "Feature",
  "properties": {
    "hierarchy": [
      "tgn:1077817",
      "tgn:1001321",
      "tgn:1000004",
      "tgn:1000116",
      "tgn:7029392"
    ],
    "placetype": [
      "aat:300008347"
    ],
    "id": 1077817,
    "name:xx": "Kawali"
  }
}
