{
  "type": "FeatureCollection",
  "features": [
    {
      "geometry": {
        "type": "Point",
        "coordinates": [
          -85.4167,
          41.2333
        ]
      },
      "type": "Feature",
      "properties": {
        "hierarchy": [
          "tgn:2718800",
          "tgn:1000001",
          "tgn:7012149",
          "tgn:1003022",
          "tgn:7007252",
          "tgn:7029392"
        ],
        "placetype": [
          "aat:300008706"
        ],
        "id": 2718800,
        "name:xx": "Thorn Creek"
      }
    },
    {
      "geometry": {
        "type": "Point",
        "coordinates": [
          -85.1833,
          43.8333
        ]
      },
      "type": "Feature",
      "properties": {
        "hierarchy": [
          "tgn:2718801",
          "tgn:1000001",
          "tgn:7012149",
          "tgn:2000987",
          "tgn:7007520",
          "tgn:7029392"
        ],
        "placetype": [
          "aat:300008706"
        ],
        "id": 2718801,
        "name:xx": "Thorn Creek"
      }
    },
    {
      "geometry": {
        "type": "Point",
        "coordinates": [
          -122.3833,
          43.3
        ]
      },
      "type": "Feature",
      "properties": {
        "hierarchy": [
          "tgn:2718802",
          "tgn:1000001",
          "tgn:7012149",
          "tgn:2001706",
          "tgn:7007708",
          "tgn:7029392"
        ],
        "placetype": [
          "aat:300008706"
        ],
        "id": 2718802,
        "name:xx": "Thorn Creek"
      }
    },
    {
      "geometry": {
        "type": "Point",
        "coordinates": [
          -116.75,
          45.4833
        ]
      },
      "type": "Feature",
      "properties": {
        "hierarchy": [
          "tgn:2718803",
          "tgn:1000001",
          "tgn:7012149",
          "tgn:2001722",
          "tgn:7007708",
          "tgn:7029392"
        ],
        "placetype": [
          "aat:300008706"
        ],
        "id": 2718803,
        "name:xx": "Thorn Creek"
      }
    },
    {
      "geometry": {
        "type": "Point",
        "coordinates": [
          -119,
          43.9667
        ]
      },
      "type": "Feature",
      "properties": {
        "hierarchy": [
          "tgn:2718804",
          "tgn:1000001",
          "tgn:7012149",
          "tgn:2001708",
          "tgn:7007708",
          "tgn:7029392"
        ],
        "placetype": [
          "aat:300008706"
        ],
        "id": 2718804,
        "name:xx": "Thorn Creek"
      }
    },
    {
      "geometry": {
        "type": "Point",
        "coordinates": [
          -117.65,
          44.1667
        ]
      },
      "type": "Feature",
      "properties": {
        "hierarchy": [
          "tgn:2718805",
          "tgn:1000001",
          "tgn:7012149",
          "tgn:2001718",
          "tgn:7007708",
          "tgn:7029392"
        ],
        "placetype": [
          "aat:300008706"
        ],
        "id": 2718805,
        "name:xx": "Thorn Creek"
      }
    },
    {
      "geometry": {
        "type": "Point",
        "coordinates": [
          -120.4,
          44.3667
        ]
      },
      "type": "Feature",
      "properties": {
        "hierarchy": [
          "tgn:2718806",
          "tgn:1000001",
          "tgn:2001703",
          "tgn:7012149",
          "tgn:7007708",
          "tgn:7029392"
        ],
        "placetype": [
          "aat:300008706"
        ],
        "id": 2718806,
        "name:xx": "Thorn Creek"
      }
    },
    {
      "geometry": {
        "type": "Point",
        "coordinates": [
          -117.7,
          45.05
        ]
      },
      "type": "Feature",
      "properties": {
        "hierarchy": [
          "tgn:2718807",
          "tgn:1000001",
          "tgn:7012149",
          "tgn:2001721",
          "tgn:7007708",
          "tgn:7029392"
        ],
        "placetype": [
          "aat:300008706"
        ],
        "id": 2718807,
        "name:xx": "Thorn Creek"
      }
    },
    {
      "geometry": {
        "type": "Point",
        "coordinates": [
          -119.4333,
          45.1167
        ]
      },
      "type": "Feature",
      "properties": {
        "hierarchy": [
          "tgn:2718808",
          "tgn:1000001",
          "tgn:7012149",
          "tgn:2001719",
          "tgn:7007708",
          "tgn:7029392"
        ],
        "placetype": [
          "aat:300008706"
        ],
        "id": 2718808,
        "name:xx": "Thorn Creek"
      }
    },
    {
      "geometry": {
        "type": "Point",
        "coordinates": [
          -123.5167,
          45.25
        ]
      },
      "type": "Feature",
      "properties": {
        "hierarchy": [
          "tgn:2718809",
          "tgn:1000001",
          "tgn:7012149",
          "tgn:1002943",
          "tgn:7007708",
          "tgn:7029392"
        ],
        "placetype": [
          "aat:300008706"
        ],
        "id": 2718809,
        "name:xx": "Thorn Creek"
      }
    }
  ]
}
