{
  "geometry": {
    "type": "Point",
    "coordinates": [
      -81.8667,
      39.8833
    ]
  },
  "type": "Feature",
  "properties": {
    "hierarchy": [
      "tgn:2485501",
      "tgn:1000001",
      "tgn:7012149",
      "tgn:1002701",
      "tgn:7007706",
      "tgn:7029392"
    ],
    "placetype": [
      "aat:300008347"
    ],
    "id": 2485501,
    "name:xx": "Lawton"
  }
}
