{
  "geometry": {
    "type": "Point",
    "coordinates": [
      31.824785,
      29.03597
    ]
  },
  "type": "Feature",
  "properties": {
    "hierarchy": [
      "tgn:7537568",
      "tgn:7001242",
      "tgn:7016833",
      "tgn:7029392"
    ],
    "placetype": [
      "aat:300379998"
    ],
    "name:en": "Nâshât el-Kheima, Wâdi",
    "id": 7537568
  }
}
