{
  "geometry": {
    "type": "Point",
    "coordinates": [
      -108.85,
      42.8333
    ]
  },
  "type": "Feature",
  "properties": {
    "hierarchy": [
      "tgn:2610371",
      "tgn:1000001",
      "tgn:7012149",
      "tgn:2002371",
      "tgn:7007923",
      "tgn:7029392"
    ],
    "placetype": [
      "aat:300008798"
    ],
    "id": 2610371,
    "name:xx": "Red Butte"
  }
}
