{
  "geometry": {
    "type": "Point",
    "coordinates": [
      -72.25,
      -53.15
    ]
  },
  "type": "Feature",
  "properties": {
    "hierarchy": [
      "tgn:7288341",
      "tgn:1001702",
      "tgn:1000049",
      "tgn:1000002",
      "tgn:7029392"
    ],
    "placetype": [
      "aat:300386846"
    ],
    "id": 7288341,
    "name:xx": "Jofré, Punta"
  }
}
