{
  "geometry": {
    "type": "Point",
    "coordinates": [
      110.0667,
      23.3333
    ]
  },
  "type": "Feature",
  "properties": {
    "hierarchy": [
      "tgn:1068455",
      "tgn:1000004",
      "tgn:1001678",
      "tgn:1000111",
      "tgn:7029392"
    ],
    "placetype": [
      "aat:300008347"
    ],
    "id": 1068455,
    "name:xx": "Guiping"
  }
}
