{
  "geometry": {
    "type": "Point",
    "coordinates": [
      -82.5833,
      38.15
    ]
  },
  "type": "Feature",
  "properties": {
    "hierarchy": [
      "tgn:2770656",
      "tgn:1000001",
      "tgn:7012149",
      "tgn:2002299",
      "tgn:7013961",
      "tgn:7029392"
    ],
    "placetype": [
      "aat:300008699"
    ],
    "id": 2770656,
    "name:xx": "Wildcat Branch"
  }
}
