{
  "type": "FeatureCollection",
  "features": [
    {
      "geometry": {
        "type": "Point",
        "coordinates": [
          -84.8167,
          36.9
        ]
      },
      "type": "Feature",
      "properties": {
        "hierarchy": [
          "tgn:2322070",
          "tgn:1000001",
          "tgn:7012149",
          "tgn:2000850",
          "tgn:7007255",
          "tgn:7029392"
        ],
        "placetype": [
          "aat:300008706"
        ],
        "id": 2322070,
        "name:xx": "Fall Creek"
      }
    },
    {
      "geometry": {
        "type": "Point",
        "coordinates": [
          -84.3,
          36.9833
        ]
      },
      "type": "Feature",
      "properties": {
        "hierarchy": [
          "tgn:2322071",
          "tgn:1000001",
          "tgn:7012149",
          "tgn:2000839",
          "tgn:7007255",
          "tgn:7029392"
        ],
        "placetype": [
          "aat:300008706"
        ],
        "id": 2322071,
        "name:xx": "Fall Creek"
      }
    },
    {
      "geometry": {
        "type": "Point",
        "coordinates": [
          -85.3333,
          42.55
        ]
      },
      "type": "Feature",
      "properties": {
        "hierarchy": [
          "tgn:2322072",
          "tgn:1002166",
          "tgn:1000001",
          "tgn:7012149",
          "tgn:7007520",
          "tgn:7029392"
        ],
        "placetype": [
          "aat:300008706"
        ],
        "id": 2322072,
        "name:xx": "Fall Creek"
      }
    },
    {
      "geometry": {
        "type": "Point",
        "coordinates": [
          -83.4833,
          45.15
        ]
      },
      "type": "Feature",
      "properties": {
        "hierarchy": [
          "tgn:2322073",
          "tgn:2000944",
          "tgn:1000001",
          "tgn:7012149",
          "tgn:7007520",
          "tgn:7029392"
        ],
        "placetype": [
          "aat:300008706"
        ],
        "id": 2322073,
        "name:xx": "Fall Creek"
      }
    },
    {
      "geometry": {
        "type": "Point",
        "coordinates": [
          -93.3,
          36.6667
        ]
      },
      "type": "Feature",
      "properties": {
        "hierarchy": [
          "tgn:2322074",
          "tgn:1000001",
          "tgn:7012149",
          "tgn:7007523",
          "tgn:7029392"
        ],
        "placetype": [
          "aat:300008706"
        ],
        "id": 2322074,
        "name:xx": "Fall Creek"
      }
    },
    {
      "geometry": {
        "type": "Point",
        "coordinates": [
          -91.3333,
          39.6833
        ]
      },
      "type": "Feature",
      "properties": {
        "hierarchy": [
          "tgn:2322075",
          "tgn:1000001",
          "tgn:7012149",
          "tgn:1002634",
          "tgn:7007523",
          "tgn:7029392"
        ],
        "placetype": [
          "aat:300008706"
        ],
        "id": 2322075,
        "name:xx": "Fall Creek"
      }
    },
    {
      "geometry": {
        "type": "Point",
        "coordinates": [
          -110.45,
          47.4167
        ]
      },
      "type": "Feature",
      "properties": {
        "hierarchy": [
          "tgn:2322077",
          "tgn:1000001",
          "tgn:7012149",
          "tgn:7007524",
          "tgn:7029392"
        ],
        "placetype": [
          "aat:300008706"
        ],
        "id": 2322077,
        "name:xx": "Fall Creek"
      }
    },
    {
      "geometry": {
        "type": "Point",
        "coordinates": [
          -115.3667,
          41.8
        ]
      },
      "type": "Feature",
      "properties": {
        "hierarchy": [
          "tgn:2322078",
          "tgn:1000001",
          "tgn:2001411",
          "tgn:7012149",
          "tgn:7007526",
          "tgn:7029392"
        ],
        "placetype": [
          "aat:300008706"
        ],
        "id": 2322078,
        "name:xx": "Fall Creek"
      }
    },
    {
      "geometry": {
        "type": "Point",
        "coordinates": [
          -74.15,
          42.3333
        ]
      },
      "type": "Feature",
      "properties": {
        "hierarchy": [
          "tgn:2322079",
          "tgn:1000001",
          "tgn:7012149",
          "tgn:1002423",
          "tgn:7007568",
          "tgn:7029392"
        ],
        "placetype": [
          "aat:300008706"
        ],
        "id": 2322079,
        "name:xx": "Fall Creek"
      }
    }
  ]
}
