{
  "geometry": {
    "type": "Point",
    "coordinates": [
      -88.2333,
      32.85
    ]
  },
  "type": "Feature",
  "properties": {
    "hierarchy": [
      "tgn:7021500",
      "tgn:7002659",
      "tgn:1000001",
      "tgn:7012149",
      "tgn:2000059",
      "tgn:7029392"
    ],
    "placetype": [
      "aat:300006191"
    ],
    "id": 7021500,
    "name:xx": "Barns Pond"
  }
}
