{
  "geometry": {
    "type": "Point",
    "coordinates": [
      30.553776,
      25.043131
    ]
  },
  "type": "Feature",
  "properties": {
    "hierarchy": [
      "tgn:7533618",
      "tgn:7001242",
      "tgn:7016833",
      "tgn:7001334",
      "tgn:7029392"
    ],
    "placetype": [
      "aat:300008697"
    ],
    "name:en": "Jarmashīn, 'Ayn",
    "id": 7533618
  }
}
