{
  "type": "FeatureCollection",
  "features": [
    {
      "geometry": {
        "type": "Point",
        "coordinates": [
          -83.65,
          35.9
        ]
      },
      "type": "Feature",
      "properties": {
        "hierarchy": [
          "tgn:2214690",
          "tgn:1000001",
          "tgn:7012149",
          "tgn:2001914",
          "tgn:7007825",
          "tgn:7029392"
        ],
        "placetype": [
          "aat:300008699"
        ],
        "id": 2214690,
        "name:xx": "Calf Branch"
      }
    },
    {
      "geometry": {
        "type": "Point",
        "coordinates": [
          -82.2833,
          38.2333
        ]
      },
      "type": "Feature",
      "properties": {
        "hierarchy": [
          "tgn:2214691",
          "tgn:1000001",
          "tgn:7012149",
          "tgn:2002299",
          "tgn:7013961",
          "tgn:7029392"
        ],
        "placetype": [
          "aat:300008699"
        ],
        "id": 2214691,
        "name:xx": "Calf Branch"
      }
    },
    {
      "geometry": {
        "type": "Point",
        "coordinates": [
          -120.5167,
          35.4167
        ]
      },
      "type": "Feature",
      "properties": {
        "hierarchy": [
          "tgn:2214692",
          "tgn:1000001",
          "tgn:7012149",
          "tgn:7007157",
          "tgn:1002863",
          "tgn:7029392"
        ],
        "placetype": [
          "aat:300008761"
        ],
        "id": 2214692,
        "name:xx": "Calf Canyon"
      }
    },
    {
      "geometry": {
        "type": "Point",
        "coordinates": [
          -108.6833,
          39.8667
        ]
      },
      "type": "Feature",
      "properties": {
        "hierarchy": [
          "tgn:2214693",
          "tgn:1000001",
          "tgn:7012149",
          "tgn:7007158",
          "tgn:2000243",
          "tgn:7029392"
        ],
        "placetype": [
          "aat:300008761"
        ],
        "id": 2214693,
        "name:xx": "Calf Canyon"
      }
    },
    {
      "geometry": {
        "type": "Point",
        "coordinates": [
          -108.8833,
          39.65
        ]
      },
      "type": "Feature",
      "properties": {
        "hierarchy": [
          "tgn:2214694",
          "tgn:1000001",
          "tgn:7012149",
          "tgn:7007158",
          "tgn:7029392"
        ],
        "placetype": [
          "aat:300008761"
        ],
        "id": 2214694,
        "name:xx": "Calf Canyon"
      }
    },
    {
      "geometry": {
        "type": "Point",
        "coordinates": [
          -108.7333,
          39.5833
        ]
      },
      "type": "Feature",
      "properties": {
        "hierarchy": [
          "tgn:2214695",
          "tgn:1000001",
          "tgn:7012149",
          "tgn:2000214",
          "tgn:7007158",
          "tgn:7029392"
        ],
        "placetype": [
          "aat:300008761"
        ],
        "id": 2214695,
        "name:xx": "Calf Canyon"
      }
    },
    {
      "geometry": {
        "type": "Point",
        "coordinates": [
          -103.6167,
          37.45
        ]
      },
      "type": "Feature",
      "properties": {
        "hierarchy": [
          "tgn:2214696",
          "tgn:1000001",
          "tgn:7012149",
          "tgn:2000227",
          "tgn:7007158",
          "tgn:7029392"
        ],
        "placetype": [
          "aat:300008761"
        ],
        "id": 2214696,
        "name:xx": "Calf Canyon"
      }
    },
    {
      "geometry": {
        "type": "Point",
        "coordinates": [
          -114.8667,
          40.2
        ]
      },
      "type": "Feature",
      "properties": {
        "hierarchy": [
          "tgn:2214697",
          "tgn:1000001",
          "tgn:2001411",
          "tgn:7012149",
          "tgn:7007526",
          "tgn:7029392"
        ],
        "placetype": [
          "aat:300008761"
        ],
        "id": 2214697,
        "name:xx": "Calf Canyon"
      }
    },
    {
      "geometry": {
        "type": "Point",
        "coordinates": [
          -104.9167,
          32.1167
        ]
      },
      "type": "Feature",
      "properties": {
        "hierarchy": [
          "tgn:2214698",
          "tgn:1000001",
          "tgn:7012149",
          "tgn:2001447",
          "tgn:7007566",
          "tgn:7029392"
        ],
        "placetype": [
          "aat:300008761"
        ],
        "id": 2214698,
        "name:xx": "Calf Canyon"
      }
    },
    {
      "geometry": {
        "type": "Point",
        "coordinates": [
          -105.5167,
          35.7
        ]
      },
      "type": "Feature",
      "properties": {
        "hierarchy": [
          "tgn:2214699",
          "tgn:1000001",
          "tgn:7012149",
          "tgn:2001453",
          "tgn:7007566",
          "tgn:7029392"
        ],
        "placetype": [
          "aat:300008761"
        ],
        "id": 2214699,
        "name:xx": "Calf Canyon"
      }
    }
  ]
}
