{
  "geometry": {
    "type": "Point",
    "coordinates": [
      -110.5333,
      36.2167
    ]
  },
  "type": "Feature",
  "properties": {
    "hierarchy": [
      "tgn:2169751",
      "tgn:1000001",
      "tgn:7006451",
      "tgn:7012149",
      "tgn:2000099",
      "tgn:7029392"
    ],
    "placetype": [
      "aat:300008697"
    ],
    "id": 2169751,
    "name:xx": "Big Mountain Ruin Spring"
  }
}
