{
  "geometry": {
    "type": "Point",
    "coordinates": [
      -83.05,
      39.0333
    ]
  },
  "type": "Feature",
  "properties": {
    "hierarchy": [
      "tgn:2419673",
      "tgn:1000001",
      "tgn:7012149",
      "tgn:1002788",
      "tgn:7007706",
      "tgn:7029392"
    ],
    "placetype": [
      "aat:300008798"
    ],
    "id": 2419673,
    "name:xx": "Jasper Knob"
  }
}
