{
  "geometry": {
    "type": "Point",
    "coordinates": [
      -9.258,
      39.091
    ]
  },
  "type": "Feature",
  "properties": {
    "hierarchy": [
      "tgn:7011097",
      "tgn:1000882",
      "tgn:1000003",
      "tgn:1000090",
      "tgn:7029392"
    ],
    "placetype": [
      "aat:300008347"
    ],
    "id": 7011097,
    "name:xx": "Torres Vedras"
  }
}
