{
  "geometry": {
    "type": "Point",
    "coordinates": [
      -70.7667,
      44.1833
    ]
  },
  "type": "Feature",
  "properties": {
    "hierarchy": [
      "tgn:2363278",
      "tgn:1000001",
      "tgn:7012149",
      "tgn:2000926",
      "tgn:7007515",
      "tgn:7029392"
    ],
    "placetype": [
      "aat:300008699"
    ],
    "id": 2363278,
    "name:xx": "Green Brook"
  }
}
