{
  "geometry": {
    "type": "Point",
    "coordinates": [
      -107.3333,
      39.6833
    ]
  },
  "type": "Feature",
  "properties": {
    "hierarchy": [
      "tgn:2298008",
      "tgn:1000001",
      "tgn:7012149",
      "tgn:2000214",
      "tgn:7007158",
      "tgn:7029392"
    ],
    "placetype": [
      "aat:300008680"
    ],
    "id": 2298008,
    "name:xx": "Dry Lake"
  }
}
