{
  "geometry": {
    "type": "Point",
    "coordinates": [
      -57.9167,
      -34.4167
    ]
  },
  "type": "Feature",
  "properties": {
    "hierarchy": [
      "tgn:1010045",
      "tgn:1000574",
      "tgn:1000002",
      "tgn:1000058",
      "tgn:7029392"
    ],
    "placetype": [
      "aat:300386853"
    ],
    "id": 1010045,
    "name:xx": "Hornos, Islas de"
  }
}
