{
  "geometry": {
    "type": "Point",
    "coordinates": [
      -111.85,
      33.9167
    ]
  },
  "type": "Feature",
  "properties": {
    "hierarchy": [
      "tgn:2383018",
      "tgn:1000001",
      "tgn:7006451",
      "tgn:7012149",
      "tgn:2000097",
      "tgn:7029392"
    ],
    "placetype": [
      "aat:300008697"
    ],
    "id": 2383018,
    "name:xx": "Head of Cottonwood Spring"
  }
}
