{
  "geometry": {
    "type": "Point",
    "coordinates": [
      -122.6333,
      39.0833
    ]
  },
  "type": "Feature",
  "properties": {
    "hierarchy": [
      "tgn:2779228",
      "tgn:1000001",
      "tgn:7012149",
      "tgn:7007157",
      "tgn:1002566",
      "tgn:7029392"
    ],
    "placetype": [
      "aat:300266640"
    ],
    "id": 2779228,
    "name:xx": "Wolf Creek Ridge"
  }
}
