{
  "geometry": {
    "type": "Point",
    "coordinates": [
      -116.9667,
      32.65
    ]
  },
  "type": "Feature",
  "properties": {
    "hierarchy": [
      "tgn:2770489",
      "tgn:1000001",
      "tgn:7012149",
      "tgn:7007157",
      "tgn:1002858",
      "tgn:7029392"
    ],
    "placetype": [
      "aat:300008761"
    ],
    "id": 2770489,
    "name:xx": "Wild Mans Canyon"
  }
}
