{
  "geometry": {
    "type": "Point",
    "coordinates": [
      -107.3667,
      43.3333
    ]
  },
  "type": "Feature",
  "properties": {
    "hierarchy": [
      "tgn:2706049",
      "tgn:1000001",
      "tgn:7012149",
      "tgn:2002377",
      "tgn:7007923",
      "tgn:7029392"
    ],
    "placetype": [
      "aat:300008347"
    ],
    "id": 2706049,
    "name:xx": "Swaim Place"
  }
}
