{
  "geometry": {
    "type": "Point",
    "coordinates": [
      -96.75,
      34.0333
    ]
  },
  "type": "Feature",
  "properties": {
    "hierarchy": [
      "tgn:2455588",
      "tgn:1000001",
      "tgn:7012149",
      "tgn:2001670",
      "tgn:7007707",
      "tgn:7029392"
    ],
    "placetype": [
      "aat:300008706"
    ],
    "id": 2455588,
    "name:xx": "Little Glasses Creek"
  }
}
