{
  "geometry": {
    "type": "Point",
    "coordinates": [
      -85.2333,
      41.2167
    ]
  },
  "type": "Feature",
  "properties": {
    "hierarchy": [
      "tgn:2660165",
      "tgn:1002143",
      "tgn:1000001",
      "tgn:7012149",
      "tgn:7007252",
      "tgn:7029392"
    ],
    "placetype": [
      "aat:300006075"
    ],
    "id": 2660165,
    "name:xx": "Shoaff Dawson Ditch"
  }
}
