{
  "geometry": {
    "type": "Point",
    "coordinates": [
      -118.45,
      33.4333
    ]
  },
  "type": "Feature",
  "properties": {
    "hierarchy": [
      "tgn:2171418",
      "tgn:1000001",
      "tgn:7012149",
      "tgn:7007157",
      "tgn:1002608",
      "tgn:1008999",
      "tgn:7029392"
    ],
    "placetype": [
      "aat:300006191"
    ],
    "id": 2171418,
    "name:xx": "Big Springs Reservoir"
  }
}
