{
  "geometry": {
    "type": "Point",
    "coordinates": [
      -78.8667,
      37.6833
    ]
  },
  "type": "Feature",
  "properties": {
    "hierarchy": [
      "tgn:2538171",
      "tgn:1000001",
      "tgn:7012149",
      "tgn:2002175",
      "tgn:7007919",
      "tgn:7029392"
    ],
    "placetype": [
      "aat:300006191"
    ],
    "id": 2538171,
    "name:xx": "Nelson Lake"
  }
}
