{
  "geometry": {
    "type": "Point",
    "coordinates": [
      -113.5667,
      46.6333
    ]
  },
  "type": "Feature",
  "properties": {
    "hierarchy": [
      "tgn:2257442",
      "tgn:1000001",
      "tgn:7012149",
      "tgn:2001279",
      "tgn:7007524",
      "tgn:7029392"
    ],
    "placetype": [
      "aat:300008761"
    ],
    "id": 2257442,
    "name:xx": "Corona Gulch"
  }
}
