{
  "geometry": {
    "type": "Point",
    "coordinates": [
      -100.5833,
      30.8167
    ]
  },
  "type": "Feature",
  "properties": {
    "hierarchy": [
      "tgn:2549926",
      "tgn:1000001",
      "tgn:7012149",
      "tgn:7007826",
      "tgn:7029392"
    ],
    "placetype": [
      "aat:300008699"
    ],
    "id": 2549926,
    "name:xx": "North Valley Prong"
  }
}
