{
  "geometry": {
    "type": "Point",
    "coordinates": [
      141.2833,
      -36.55
    ]
  },
  "type": "Feature",
  "properties": {
    "hierarchy": [
      "tgn:1097219",
      "tgn:7000490",
      "tgn:1000006",
      "tgn:7006238",
      "tgn:7029392"
    ],
    "placetype": [
      "aat:300008347"
    ],
    "id": 1097219,
    "name:xx": "Kaniva"
  }
}
