{
  "geometry": {
    "type": "Point",
    "coordinates": [
      31.116667,
      28.266667
    ]
  },
  "type": "Feature",
  "properties": {
    "hierarchy": [
      "tgn:7534613",
      "tgn:7001242",
      "tgn:7001311",
      "tgn:7016833",
      "tgn:7029392"
    ],
    "placetype": [
      "aat:300008777"
    ],
    "name:en": "Jurūn, 'Alāwī",
    "id": 7534613
  }
}
