{
  "type": "FeatureCollection",
  "features": [
    {
      "geometry": {
        "type": "Point",
        "coordinates": [
          10.916667,
          51.033333
        ]
      },
      "type": "Feature",
      "properties": {
        "hierarchy": [
          "tgn:7182510",
          "tgn:1000003",
          "tgn:7003689",
          "tgn:7000084",
          "tgn:7029392"
        ],
        "placetype": [
          "aat:300008777"
        ],
        "id": 7182510,
        "name:xx": "Geiers-Berg"
      }
    },
    {
      "geometry": {
        "type": "Point",
        "coordinates": [
          11.066667,
          50.933333
        ]
      },
      "type": "Feature",
      "properties": {
        "hierarchy": [
          "tgn:7182511",
          "tgn:1000003",
          "tgn:7003689",
          "tgn:7000084",
          "tgn:7029392"
        ],
        "placetype": [
          "aat:300008777"
        ],
        "id": 7182511,
        "name:xx": "Geiers-Berg"
      }
    },
    {
      "geometry": {
        "type": "Point",
        "coordinates": [
          13.65,
          50.9
        ]
      },
      "type": "Feature",
      "properties": {
        "hierarchy": [
          "tgn:7182512",
          "tgn:1000003",
          "tgn:7003685",
          "tgn:7000084",
          "tgn:7029392"
        ],
        "placetype": [
          "aat:300008777"
        ],
        "id": 7182512,
        "name:xx": "Geiers Berg"
      }
    },
    {
      "geometry": {
        "type": "Point",
        "coordinates": [
          10.633333,
          50.866667
        ]
      },
      "type": "Feature",
      "properties": {
        "hierarchy": [
          "tgn:7182513",
          "tgn:1000003",
          "tgn:7003689",
          "tgn:7000084",
          "tgn:7029392"
        ],
        "placetype": [
          "aat:300008777"
        ],
        "id": 7182513,
        "name:xx": "Geiers-Berg"
      }
    },
    {
      "geometry": {
        "type": "Point",
        "coordinates": [
          11.3,
          50.816667
        ]
      },
      "type": "Feature",
      "properties": {
        "hierarchy": [
          "tgn:7182514",
          "tgn:1000003",
          "tgn:7003689",
          "tgn:7000084",
          "tgn:7029392"
        ],
        "placetype": [
          "aat:300008777"
        ],
        "id": 7182514,
        "name:xx": "Geiers-Berg"
      }
    },
    {
      "geometry": {
        "type": "Point",
        "coordinates": [
          12.95,
          50.75
        ]
      },
      "type": "Feature",
      "properties": {
        "hierarchy": [
          "tgn:7182515",
          "tgn:1000003",
          "tgn:7003685",
          "tgn:7000084",
          "tgn:7029392"
        ],
        "placetype": [
          "aat:300008777"
        ],
        "id": 7182515,
        "name:xx": "Geiers-Berg"
      }
    },
    {
      "geometry": {
        "type": "Point",
        "coordinates": [
          8.716667,
          50.716667
        ]
      },
      "type": "Feature",
      "properties": {
        "hierarchy": [
          "tgn:7182516",
          "tgn:1000003",
          "tgn:7003678",
          "tgn:7000084",
          "tgn:7029392"
        ],
        "placetype": [
          "aat:300008777"
        ],
        "id": 7182516,
        "name:xx": "Geiers-Berg"
      }
    },
    {
      "geometry": {
        "type": "Point",
        "coordinates": [
          11.133333,
          50.65
        ]
      },
      "type": "Feature",
      "properties": {
        "hierarchy": [
          "tgn:7182517",
          "tgn:1000003",
          "tgn:7003689",
          "tgn:7000084",
          "tgn:7029392"
        ],
        "placetype": [
          "aat:300008777"
        ],
        "id": 7182517,
        "name:xx": "Geiers-Berg"
      }
    },
    {
      "geometry": {
        "type": "Point",
        "coordinates": [
          12.533333,
          50.616667
        ]
      },
      "type": "Feature",
      "properties": {
        "hierarchy": [
          "tgn:7182518",
          "tgn:1000003",
          "tgn:7003685",
          "tgn:7000084",
          "tgn:7029392"
        ],
        "placetype": [
          "aat:300008777"
        ],
        "id": 7182518,
        "name:xx": "Geiers-Berg"
      }
    },
    {
      "geometry": {
        "type": "Point",
        "coordinates": [
          11.533333,
          50.616667
        ]
      },
      "type": "Feature",
      "properties": {
        "hierarchy": [
          "tgn:7182519",
          "tgn:1000003",
          "tgn:7003689",
          "tgn:7000084",
          "tgn:7029392"
        ],
        "placetype": [
          "aat:300008777"
        ],
        "id": 7182519,
        "name:xx": "Geiers-Berg"
      }
    }
  ]
}
