{
  "geometry": {
    "type": "Point",
    "coordinates": [
      -121.7167,
      44.55
    ]
  },
  "type": "Feature",
  "properties": {
    "hierarchy": [
      "tgn:2124574",
      "tgn:1000001",
      "tgn:7012149",
      "tgn:2001712",
      "tgn:7007708",
      "tgn:7029392"
    ],
    "placetype": [
      "aat:300008697"
    ],
    "id": 2124574,
    "name:xx": "Abbot Butte Spring"
  }
}
