{
  "type": "FeatureCollection",
  "features": [
    {
      "geometry": {
        "type": "Point",
        "coordinates": [
          -77.5333,
          41.1833
        ]
      },
      "type": "Feature",
      "properties": {
        "hierarchy": [
          "tgn:2358060",
          "tgn:1000001",
          "tgn:1002286",
          "tgn:7012149",
          "tgn:7007710",
          "tgn:7029392"
        ],
        "placetype": [
          "aat:300008699"
        ],
        "id": 2358060,
        "name:xx": "Graham Run"
      }
    },
    {
      "geometry": {
        "type": "Point",
        "coordinates": [
          -104.7,
          40.4667
        ]
      },
      "type": "Feature",
      "properties": {
        "hierarchy": [
          "tgn:2358061",
          "tgn:1000001",
          "tgn:7012149",
          "tgn:7007158",
          "tgn:2000253",
          "tgn:7029392"
        ],
        "placetype": [
          "aat:300006075"
        ],
        "id": 2358061,
        "name:xx": "Graham Seep"
      }
    },
    {
      "geometry": {
        "type": "Point",
        "coordinates": [
          -111.3833,
          43.7333
        ]
      },
      "type": "Feature",
      "properties": {
        "hierarchy": [
          "tgn:2358062",
          "tgn:1000001",
          "tgn:7012149",
          "tgn:2000492",
          "tgn:7007250",
          "tgn:7029392"
        ],
        "placetype": [
          "aat:300008697"
        ],
        "id": 2358062,
        "name:xx": "Graham Spring"
      }
    },
    {
      "geometry": {
        "type": "Point",
        "coordinates": [
          -91.4333,
          36.7667
        ]
      },
      "type": "Feature",
      "properties": {
        "hierarchy": [
          "tgn:2358063",
          "tgn:1000001",
          "tgn:7012149",
          "tgn:2001225",
          "tgn:7007523",
          "tgn:7029392"
        ],
        "placetype": [
          "aat:300008697"
        ],
        "id": 2358063,
        "name:xx": "Graham Spring"
      }
    },
    {
      "geometry": {
        "type": "Point",
        "coordinates": [
          -111.7,
          46.4333
        ]
      },
      "type": "Feature",
      "properties": {
        "hierarchy": [
          "tgn:2358065",
          "tgn:1000001",
          "tgn:2001263",
          "tgn:7012149",
          "tgn:7007524",
          "tgn:7029392"
        ],
        "placetype": [
          "aat:300008697"
        ],
        "id": 2358065,
        "name:xx": "Graham Spring"
      }
    },
    {
      "geometry": {
        "type": "Point",
        "coordinates": [
          -114.7167,
          38.65
        ]
      },
      "type": "Feature",
      "properties": {
        "hierarchy": [
          "tgn:2358066",
          "tgn:1000001",
          "tgn:2001416",
          "tgn:7012149",
          "tgn:7007526",
          "tgn:7029392"
        ],
        "placetype": [
          "aat:300008697"
        ],
        "id": 2358066,
        "name:xx": "Graham Spring"
      }
    },
    {
      "geometry": {
        "type": "Point",
        "coordinates": [
          -103.8167,
          33.2667
        ]
      },
      "type": "Feature",
      "properties": {
        "hierarchy": [
          "tgn:2358067",
          "tgn:1000001",
          "tgn:2001430",
          "tgn:7012149",
          "tgn:7007566",
          "tgn:7029392"
        ],
        "placetype": [
          "aat:300008697"
        ],
        "id": 2358067,
        "name:xx": "Graham Spring"
      }
    },
    {
      "geometry": {
        "type": "Point",
        "coordinates": [
          -121.55,
          45.5333
        ]
      },
      "type": "Feature",
      "properties": {
        "hierarchy": [
          "tgn:2358068",
          "tgn:1000001",
          "tgn:7012149",
          "tgn:2001710",
          "tgn:7007708",
          "tgn:7029392"
        ],
        "placetype": [
          "aat:300008697"
        ],
        "id": 2358068,
        "name:xx": "Graham Spring"
      }
    }
  ]
}
