{
  "geometry": {
    "type": "Point",
    "coordinates": [
      -105.5667,
      42.35
    ]
  },
  "type": "Feature",
  "properties": {
    "hierarchy": [
      "tgn:2600524",
      "tgn:1000001",
      "tgn:2002369",
      "tgn:7012149",
      "tgn:7007923",
      "tgn:7029392"
    ],
    "placetype": [
      "aat:300008761"
    ],
    "id": 2600524,
    "name:xx": "Pugilist Gulch"
  }
}
