{
  "geometry": {
    "type": "Point",
    "coordinates": [
      -83.2667,
      42.7167
    ]
  },
  "type": "Feature",
  "properties": {
    "hierarchy": [
      "tgn:2729952",
      "tgn:1000001",
      "tgn:7012149",
      "tgn:1002737",
      "tgn:7007520",
      "tgn:7029392"
    ],
    "placetype": [
      "aat:300008706"
    ],
    "id": 2729952,
    "name:xx": "Trout Creek"
  }
}
