{
  "geometry": {
    "type": "Point",
    "coordinates": [
      -98.75,
      23.75
    ]
  },
  "type": "Feature",
  "properties": {
    "hierarchy": [
      "tgn:7381080",
      "tgn:1000001",
      "tgn:7005597",
      "tgn:7005560",
      "tgn:7029392"
    ],
    "placetype": [
      "aat:300008811"
    ],
    "id": 7381080,
    "name:xx": "Loma Prieta, Mesa"
  }
}
