{
  "geometry": {
    "type": "Point",
    "coordinates": [
      -4.2667,
      48.45
    ]
  },
  "type": "Feature",
  "properties": {
    "hierarchy": [
      "tgn:1033773",
      "tgn:1000003",
      "tgn:7012216",
      "tgn:1000070",
      "tgn:7029392"
    ],
    "placetype": [
      "aat:300008347"
    ],
    "id": 1033773,
    "name:xx": "Landerneau"
  }
}
