{
  "geometry": {
    "type": "Point",
    "coordinates": [
      -66.7833,
      -34.2167
    ]
  },
  "type": "Feature",
  "properties": {
    "hierarchy": [
      "tgn:1123385",
      "tgn:7006477",
      "tgn:1000002",
      "tgn:7029392"
    ],
    "placetype": [
      "aat:300008707"
    ],
    "id": 1123385,
    "name:xx": "Desaguadero, Río"
  }
}
