{
  "type": "FeatureCollection",
  "features": [
    {
      "geometry": {
        "type": "Point",
        "coordinates": [
          8.766667,
          51.566667
        ]
      },
      "type": "Feature",
      "properties": {
        "hierarchy": [
          "tgn:7090630",
          "tgn:1000003",
          "tgn:7003677",
          "tgn:7000084",
          "tgn:7029392"
        ],
        "placetype": [
          "aat:300008777"
        ],
        "id": 7090630,
        "name:xx": "Voß-Berg"
      }
    },
    {
      "geometry": {
        "type": "Point",
        "coordinates": [
          8.45,
          51.383333
        ]
      },
      "type": "Feature",
      "properties": {
        "hierarchy": [
          "tgn:7090631",
          "tgn:1000003",
          "tgn:7003677",
          "tgn:7000084",
          "tgn:7029392"
        ],
        "placetype": [
          "aat:300008777"
        ],
        "id": 7090631,
        "name:xx": "Voß-Berg"
      }
    },
    {
      "geometry": {
        "type": "Point",
        "coordinates": [
          10.65,
          53.65
        ]
      },
      "type": "Feature",
      "properties": {
        "hierarchy": [
          "tgn:7090632",
          "tgn:1000003",
          "tgn:7003688",
          "tgn:7000084",
          "tgn:7029392"
        ],
        "placetype": [
          "aat:300008863"
        ],
        "id": 7090632,
        "name:xx": "Voßberg"
      }
    },
    {
      "geometry": {
        "type": "Point",
        "coordinates": [
          9.133333,
          54.466667
        ]
      },
      "type": "Feature",
      "properties": {
        "hierarchy": [
          "tgn:7090633",
          "tgn:1000003",
          "tgn:7003688",
          "tgn:7000084",
          "tgn:7029392"
        ],
        "placetype": [
          "aat:300000206"
        ],
        "id": 7090633,
        "name:xx": "Voßberg"
      }
    },
    {
      "geometry": {
        "type": "Point",
        "coordinates": [
          10.016667,
          54.416667
        ]
      },
      "type": "Feature",
      "properties": {
        "hierarchy": [
          "tgn:7090634",
          "tgn:1000003",
          "tgn:7003688",
          "tgn:7000084",
          "tgn:7029392"
        ],
        "placetype": [
          "aat:300000206"
        ],
        "id": 7090634,
        "name:xx": "Voßberg"
      }
    },
    {
      "geometry": {
        "type": "Point",
        "coordinates": [
          10.316667,
          54.3
        ]
      },
      "type": "Feature",
      "properties": {
        "hierarchy": [
          "tgn:7090635",
          "tgn:1000003",
          "tgn:7003688",
          "tgn:7000084",
          "tgn:7029392"
        ],
        "placetype": [
          "aat:300000206"
        ],
        "id": 7090635,
        "name:xx": "Voßberg"
      }
    },
    {
      "geometry": {
        "type": "Point",
        "coordinates": [
          9.616667,
          54.2
        ]
      },
      "type": "Feature",
      "properties": {
        "hierarchy": [
          "tgn:7090636",
          "tgn:1000003",
          "tgn:7003688",
          "tgn:7000084",
          "tgn:7029392"
        ],
        "placetype": [
          "aat:300000206"
        ],
        "id": 7090636,
        "name:xx": "Voßberg"
      }
    },
    {
      "geometry": {
        "type": "Point",
        "coordinates": [
          10.783333,
          54.066667
        ]
      },
      "type": "Feature",
      "properties": {
        "hierarchy": [
          "tgn:7090637",
          "tgn:1000003",
          "tgn:7003688",
          "tgn:7000084",
          "tgn:7029392"
        ],
        "placetype": [
          "aat:300000206"
        ],
        "id": 7090637,
        "name:xx": "Vossberg"
      }
    },
    {
      "geometry": {
        "type": "Point",
        "coordinates": [
          9.733333,
          53.716667
        ]
      },
      "type": "Feature",
      "properties": {
        "hierarchy": [
          "tgn:7090638",
          "tgn:1000003",
          "tgn:7003688",
          "tgn:7000084",
          "tgn:7029392"
        ],
        "placetype": [
          "aat:300000206"
        ],
        "id": 7090638,
        "name:xx": "Voßberg"
      }
    },
    {
      "geometry": {
        "type": "Point",
        "coordinates": [
          12.116667,
          53.15
        ]
      },
      "type": "Feature",
      "properties": {
        "hierarchy": [
          "tgn:7090639",
          "tgn:7000096",
          "tgn:1000003",
          "tgn:7000084",
          "tgn:7029392"
        ],
        "placetype": [
          "aat:300000206"
        ],
        "id": 7090639,
        "name:xx": "Voßberg"
      }
    }
  ]
}
