{
  "geometry": {
    "type": "Point",
    "coordinates": [
      -72.3333,
      43.45
    ]
  },
  "type": "Feature",
  "properties": {
    "hierarchy": [
      "tgn:2435203",
      "tgn:1000001",
      "tgn:2001427",
      "tgn:7012149",
      "tgn:7007564",
      "tgn:7029392"
    ],
    "placetype": [
      "aat:300008798"
    ],
    "id": 2435203,
    "name:xx": "Kenyon Hill"
  }
}
