{
  "geometry": {
    "type": "Point",
    "coordinates": [
      79.26638,
      27.791374
    ]
  },
  "type": "Feature",
  "properties": {
    "hierarchy": [
      "tgn:7562875",
      "tgn:1000004",
      "tgn:7000198",
      "tgn:7016722",
      "tgn:7029392"
    ],
    "placetype": [
      "aat:300008347"
    ],
    "name:en": "Chīrāni",
    "id": 7562875
  }
}
