{
  "type": "FeatureCollection",
  "features": [
    {
      "geometry": {
        "type": "Point",
        "coordinates": [
          -100.5,
          27.616667
        ]
      },
      "type": "Feature",
      "properties": {
        "hierarchy": [
          "tgn:7350800",
          "tgn:1001853",
          "tgn:1000001",
          "tgn:7005560",
          "tgn:7029392"
        ],
        "placetype": [
          "aat:300006191"
        ],
        "id": 7350800,
        "name:xx": "Tanque Cabezas"
      }
    },
    {
      "geometry": {
        "type": "Point",
        "coordinates": [
          -104.283333,
          22.216667
        ]
      },
      "type": "Feature",
      "properties": {
        "hierarchy": [
          "tgn:7350801",
          "tgn:7005586",
          "tgn:1000001",
          "tgn:7005560",
          "tgn:7029392"
        ],
        "placetype": [
          "aat:300008777"
        ],
        "id": 7350801,
        "name:xx": "Cabezas, Cerro de las"
      }
    },
    {
      "geometry": {
        "type": "Point",
        "coordinates": [
          -108.15,
          25.566667
        ]
      },
      "type": "Feature",
      "properties": {
        "hierarchy": [
          "tgn:7350802",
          "tgn:1000001",
          "tgn:7005595",
          "tgn:7005560",
          "tgn:7029392"
        ],
        "placetype": [
          "aat:300008347"
        ],
        "id": 7350802,
        "name:xx": "Cabezas"
      }
    },
    {
      "geometry": {
        "type": "Point",
        "coordinates": [
          -99.3,
          21.85
        ]
      },
      "type": "Feature",
      "properties": {
        "hierarchy": [
          "tgn:7350803",
          "tgn:1000001",
          "tgn:7005594",
          "tgn:7005560",
          "tgn:7029392"
        ],
        "placetype": [
          "aat:300008347"
        ],
        "id": 7350803,
        "name:xx": "Cabezas"
      }
    },
    {
      "geometry": {
        "type": "Point",
        "coordinates": [
          -103.716667,
          18.6
        ]
      },
      "type": "Feature",
      "properties": {
        "hierarchy": [
          "tgn:7350804",
          "tgn:1000001",
          "tgn:7005590",
          "tgn:7005560",
          "tgn:7029392"
        ],
        "placetype": [
          "aat:300387499"
        ],
        "id": 7350804,
        "name:xx": "Cabeza Negra, Punta"
      }
    },
    {
      "geometry": {
        "type": "Point",
        "coordinates": [
          -100.366667,
          26.8
        ]
      },
      "type": "Feature",
      "properties": {
        "hierarchy": [
          "tgn:7350805",
          "tgn:1000001",
          "tgn:7005589",
          "tgn:7005560",
          "tgn:7029392"
        ],
        "placetype": [
          "aat:300008795"
        ],
        "id": 7350805,
        "name:xx": "Cabeza de Víbora, Cerro"
      }
    },
    {
      "geometry": {
        "type": "Point",
        "coordinates": [
          -106.283333,
          26.55
        ]
      },
      "type": "Feature",
      "properties": {
        "hierarchy": [
          "tgn:7350806",
          "tgn:7005581",
          "tgn:1000001",
          "tgn:7005560",
          "tgn:7029392"
        ],
        "placetype": [
          "aat:300008795"
        ],
        "id": 7350806,
        "name:xx": "Cabeza de Venado, Cerro"
      }
    },
    {
      "geometry": {
        "type": "Point",
        "coordinates": [
          -100.25,
          17.5
        ]
      },
      "type": "Feature",
      "properties": {
        "hierarchy": [
          "tgn:7350807",
          "tgn:7005585",
          "tgn:1000001",
          "tgn:7005560",
          "tgn:7029392"
        ],
        "placetype": [
          "aat:300008795"
        ],
        "id": 7350807,
        "name:xx": "Cabeza de Venado, Cerro"
      }
    },
    {
      "geometry": {
        "type": "Point",
        "coordinates": [
          -108.9,
          28.316667
        ]
      },
      "type": "Feature",
      "properties": {
        "hierarchy": [
          "tgn:7350808",
          "tgn:1000001",
          "tgn:1001960",
          "tgn:7005560",
          "tgn:7029392"
        ],
        "placetype": [
          "aat:300008795"
        ],
        "id": 7350808,
        "name:xx": "Cabeza de Vaca, Cerro"
      }
    },
    {
      "geometry": {
        "type": "Point",
        "coordinates": [
          -108.883333,
          28.3
        ]
      },
      "type": "Feature",
      "properties": {
        "hierarchy": [
          "tgn:7350809",
          "tgn:7005581",
          "tgn:1000001",
          "tgn:7005560",
          "tgn:7029392"
        ],
        "placetype": [
          "aat:300387007"
        ],
        "id": 7350809,
        "name:xx": "Cabeza de Vaca"
      }
    }
  ]
}
