{
  "geometry": {
    "type": "Point",
    "coordinates": [
      -76.05,
      39.9667
    ]
  },
  "type": "Feature",
  "properties": {
    "hierarchy": [
      "tgn:2403432",
      "tgn:1000001",
      "tgn:7012149",
      "tgn:7013867",
      "tgn:7007710",
      "tgn:7029392"
    ],
    "placetype": [
      "aat:300008699"
    ],
    "id": 2403432,
    "name:xx": "Houston Run"
  }
}
