{
  "geometry": {
    "type": "Point",
    "coordinates": [
      -79.25,
      39.4167
    ]
  },
  "type": "Feature",
  "properties": {
    "hierarchy": [
      "tgn:2770562",
      "tgn:1000001",
      "tgn:2000935",
      "tgn:7012149",
      "tgn:7007516",
      "tgn:7029392"
    ],
    "placetype": [
      "aat:300008798"
    ],
    "id": 2770562,
    "name:xx": "Wild Turkey Rock"
  }
}
