{
  "geometry": {
    "type": "Point",
    "coordinates": [
      -119.3333,
      38.1833
    ]
  },
  "type": "Feature",
  "properties": {
    "hierarchy": [
      "tgn:2444206",
      "tgn:1000001",
      "tgn:7012149",
      "tgn:7007157",
      "tgn:1002675",
      "tgn:7029392"
    ],
    "placetype": [
      "aat:300008706"
    ],
    "id": 2444206,
    "name:xx": "Labrosse Creek"
  }
}
