{
  "geometry": {
    "type": "Point",
    "coordinates": [
      -118.8667,
      44.2167
    ]
  },
  "type": "Feature",
  "properties": {
    "hierarchy": [
      "tgn:2266102",
      "tgn:1000001",
      "tgn:7012149",
      "tgn:2001708",
      "tgn:7007708",
      "tgn:7029392"
    ],
    "placetype": [
      "aat:300008761"
    ],
    "id": 2266102,
    "name:xx": "Crawford Gulch"
  }
}
