{
  "geometry": {
    "type": "Point",
    "coordinates": [
      79.8213,
      27.0883
    ]
  },
  "type": "Feature",
  "properties": {
    "hierarchy": [
      "tgn:7562557",
      "tgn:1000004",
      "tgn:7000198",
      "tgn:7016722",
      "tgn:7029392"
    ],
    "placetype": [
      "aat:300008347"
    ],
    "name:en": "Pahla",
    "id": 7562557
  }
}
