{
  "type": "FeatureCollection",
  "features": [
    {
      "geometry": {
        "type": "Point",
        "coordinates": [
          -71.35,
          -37.383333
        ]
      },
      "type": "Feature",
      "properties": {
        "hierarchy": [
          "tgn:7292240",
          "tgn:1001637",
          "tgn:1000049",
          "tgn:1000002",
          "tgn:7029392"
        ],
        "placetype": [
          "aat:300387200"
        ],
        "id": 7292240,
        "name:xx": "El Escorial"
      }
    },
    {
      "geometry": {
        "type": "Point",
        "coordinates": [
          -70.933333,
          -33.216667
        ]
      },
      "type": "Feature",
      "properties": {
        "hierarchy": [
          "tgn:7292241",
          "tgn:1001708",
          "tgn:1000049",
          "tgn:1000002",
          "tgn:7029392"
        ],
        "placetype": [
          "aat:300387200"
        ],
        "id": 7292241,
        "name:xx": "El Escorial"
      }
    },
    {
      "geometry": {
        "type": "Point",
        "coordinates": [
          -70.6,
          -33.85
        ]
      },
      "type": "Feature",
      "properties": {
        "hierarchy": [
          "tgn:7292242",
          "tgn:1001708",
          "tgn:1000049",
          "tgn:1000002",
          "tgn:7029392"
        ],
        "placetype": [
          "aat:300000206"
        ],
        "id": 7292242,
        "name:xx": "El Escorial"
      }
    },
    {
      "geometry": {
        "type": "Point",
        "coordinates": [
          -71.816667,
          -32.75
        ]
      },
      "type": "Feature",
      "properties": {
        "hierarchy": [
          "tgn:7292243",
          "tgn:1001768",
          "tgn:1000049",
          "tgn:1000002",
          "tgn:7029392"
        ],
        "placetype": [
          "aat:300000206"
        ],
        "id": 7292243,
        "name:xx": "El Escorial"
      }
    },
    {
      "geometry": {
        "type": "Point",
        "coordinates": [
          -71.05,
          -33.916667
        ]
      },
      "type": "Feature",
      "properties": {
        "hierarchy": [
          "tgn:7292244",
          "tgn:1001708",
          "tgn:1000049",
          "tgn:1000002",
          "tgn:7029392"
        ],
        "placetype": [
          "aat:300008795"
        ],
        "id": 7292244,
        "name:xx": "El Escarpe, Cerro"
      }
    },
    {
      "geometry": {
        "type": "Point",
        "coordinates": [
          -71.316667,
          -29.633333
        ]
      },
      "type": "Feature",
      "properties": {
        "hierarchy": [
          "tgn:7292245",
          "tgn:1001657",
          "tgn:1000049",
          "tgn:1000002",
          "tgn:7029392"
        ],
        "placetype": [
          "aat:300386846"
        ],
        "id": 7292245,
        "name:xx": "Elés, Punta"
      }
    },
    {
      "geometry": {
        "type": "Point",
        "coordinates": [
          -69.666667,
          -26.666667
        ]
      },
      "type": "Feature",
      "properties": {
        "hierarchy": [
          "tgn:7292246",
          "tgn:1001630",
          "tgn:1000049",
          "tgn:1000002",
          "tgn:7029392"
        ],
        "placetype": [
          "aat:300266554",
          "aat:300008699"
        ],
        "id": 7292246,
        "name:xx": "El Ermitaño, Quebrada"
      }
    },
    {
      "geometry": {
        "type": "Point",
        "coordinates": [
          -71.4,
          -33.633333
        ]
      },
      "type": "Feature",
      "properties": {
        "hierarchy": [
          "tgn:7292247",
          "tgn:1001708",
          "tgn:1000049",
          "tgn:1000002",
          "tgn:7029392"
        ],
        "placetype": [
          "aat:300008777"
        ],
        "id": 7292247,
        "name:xx": "El Ermitaño, Loma"
      }
    },
    {
      "geometry": {
        "type": "Point",
        "coordinates": [
          -70.783333,
          -34.666667
        ]
      },
      "type": "Feature",
      "properties": {
        "hierarchy": [
          "tgn:7292248",
          "tgn:1001695",
          "tgn:1000049",
          "tgn:1000002",
          "tgn:7029392"
        ],
        "placetype": [
          "aat:300008795"
        ],
        "id": 7292248,
        "name:xx": "El Ermitaño, Cerro"
      }
    },
    {
      "geometry": {
        "type": "Point",
        "coordinates": [
          -69.616667,
          -26.633333
        ]
      },
      "type": "Feature",
      "properties": {
        "hierarchy": [
          "tgn:7292249",
          "tgn:1001630",
          "tgn:1000049",
          "tgn:1000002",
          "tgn:7029392"
        ],
        "placetype": [
          "aat:300008697"
        ],
        "id": 7292249,
        "name:xx": "El Ermitaño"
      }
    }
  ]
}
