{
  "geometry": {
    "type": "Point",
    "coordinates": [
      -83.85,
      32.4833
    ]
  },
  "type": "Feature",
  "properties": {
    "hierarchy": [
      "tgn:2475848",
      "tgn:1000001",
      "tgn:7012149",
      "tgn:2000402",
      "tgn:7007248",
      "tgn:7029392"
    ],
    "placetype": [
      "aat:300006191"
    ],
    "id": 2475848,
    "name:xx": "Lucy Giles Lake"
  }
}
