{
  "type": "FeatureCollection",
  "features": [
    {
      "geometry": {
        "type": "Point",
        "coordinates": [
          -79.9667,
          33.9167
        ]
      },
      "type": "Feature",
      "properties": {
        "hierarchy": [
          "tgn:2399800",
          "tgn:1000001",
          "tgn:2001738",
          "tgn:7012149",
          "tgn:7007712",
          "tgn:7029392"
        ],
        "placetype": [
          "aat:300008699"
        ],
        "id": 2399800,
        "name:xx": "Horse Branch"
      }
    },
    {
      "geometry": {
        "type": "Point",
        "coordinates": [
          -80.9833,
          34.35
        ]
      },
      "type": "Feature",
      "properties": {
        "hierarchy": [
          "tgn:2399801",
          "tgn:1000001",
          "tgn:2001744",
          "tgn:7012149",
          "tgn:7007712",
          "tgn:7029392"
        ],
        "placetype": [
          "aat:300008699"
        ],
        "id": 2399801,
        "name:xx": "Horse Branch"
      }
    },
    {
      "geometry": {
        "type": "Point",
        "coordinates": [
          -84.6833,
          35.2833
        ]
      },
      "type": "Feature",
      "properties": {
        "hierarchy": [
          "tgn:2399802",
          "tgn:1000001",
          "tgn:7012149",
          "tgn:7022542",
          "tgn:7007825",
          "tgn:7029392"
        ],
        "placetype": [
          "aat:300008699"
        ],
        "id": 2399802,
        "name:xx": "Horse Branch"
      }
    },
    {
      "geometry": {
        "type": "Point",
        "coordinates": [
          -87.4167,
          35.6167
        ]
      },
      "type": "Feature",
      "properties": {
        "hierarchy": [
          "tgn:2399803",
          "tgn:1000001",
          "tgn:7012149",
          "tgn:7015666",
          "tgn:7007825",
          "tgn:7029392"
        ],
        "placetype": [
          "aat:300008699"
        ],
        "id": 2399803,
        "name:xx": "Horse Branch"
      }
    },
    {
      "geometry": {
        "type": "Point",
        "coordinates": [
          -83.4833,
          35.7333
        ]
      },
      "type": "Feature",
      "properties": {
        "hierarchy": [
          "tgn:2399804",
          "tgn:1000001",
          "tgn:7012149",
          "tgn:2001914",
          "tgn:7007825",
          "tgn:7029392"
        ],
        "placetype": [
          "aat:300008699"
        ],
        "id": 2399804,
        "name:xx": "Horse Branch"
      }
    },
    {
      "geometry": {
        "type": "Point",
        "coordinates": [
          -98.8333,
          32.8
        ]
      },
      "type": "Feature",
      "properties": {
        "hierarchy": [
          "tgn:2399805",
          "tgn:1000001",
          "tgn:7012149",
          "tgn:2002076",
          "tgn:7007826",
          "tgn:7029392"
        ],
        "placetype": [
          "aat:300008699"
        ],
        "id": 2399805,
        "name:xx": "Horse Branch"
      }
    },
    {
      "geometry": {
        "type": "Point",
        "coordinates": [
          -95.5333,
          30.7167
        ]
      },
      "type": "Feature",
      "properties": {
        "hierarchy": [
          "tgn:2399806",
          "tgn:1000001",
          "tgn:7012149",
          "tgn:1002980",
          "tgn:7007826",
          "tgn:7029392"
        ],
        "placetype": [
          "aat:300008699"
        ],
        "id": 2399806,
        "name:xx": "Horse Branch"
      }
    },
    {
      "geometry": {
        "type": "Point",
        "coordinates": [
          -82.05,
          37.4167
        ]
      },
      "type": "Feature",
      "properties": {
        "hierarchy": [
          "tgn:2399807",
          "tgn:1000001",
          "tgn:2002148",
          "tgn:7012149",
          "tgn:7007919",
          "tgn:7029392"
        ],
        "placetype": [
          "aat:300008699"
        ],
        "id": 2399807,
        "name:xx": "Horse Branch"
      }
    },
    {
      "geometry": {
        "type": "Point",
        "coordinates": [
          -78.7,
          37.55
        ]
      },
      "type": "Feature",
      "properties": {
        "hierarchy": [
          "tgn:2399808",
          "tgn:1000001",
          "tgn:2002149",
          "tgn:7012149",
          "tgn:7007919",
          "tgn:7029392"
        ],
        "placetype": [
          "aat:300008699"
        ],
        "id": 2399808,
        "name:xx": "Horse Branch"
      }
    },
    {
      "geometry": {
        "type": "Point",
        "coordinates": [
          -81.6,
          38.0333
        ]
      },
      "type": "Feature",
      "properties": {
        "hierarchy": [
          "tgn:2399809",
          "tgn:1000001",
          "tgn:2002255",
          "tgn:7012149",
          "tgn:7013961",
          "tgn:7029392"
        ],
        "placetype": [
          "aat:300008699"
        ],
        "id": 2399809,
        "name:xx": "Horse Branch"
      }
    }
  ]
}
