{
  "type": "FeatureCollection",
  "features": [
    {
      "geometry": {
        "type": "Point",
        "coordinates": [
          -154.45,
          57.5667
        ]
      },
      "type": "Feature",
      "properties": {
        "hierarchy": [
          "tgn:2006160",
          "tgn:7006450",
          "tgn:1000001",
          "tgn:2124012",
          "tgn:7012149",
          "tgn:7019710",
          "tgn:7029392"
        ],
        "placetype": [
          "aat:300008347"
        ],
        "id": 2006160,
        "name:xx": "Karluk"
      }
    },
    {
      "geometry": {
        "type": "Point",
        "coordinates": [
          -132.4,
          55.5333
        ]
      },
      "type": "Feature",
      "properties": {
        "hierarchy": [
          "tgn:2006161",
          "tgn:7006450",
          "tgn:1000001",
          "tgn:7012149",
          "tgn:2000082",
          "tgn:7019648",
          "tgn:7029392"
        ],
        "placetype": [
          "aat:300008347"
        ],
        "id": 2006161,
        "name:xx": "Kasaan"
      }
    },
    {
      "geometry": {
        "type": "Point",
        "coordinates": [
          -157.8333,
          60.85
        ]
      },
      "type": "Feature",
      "properties": {
        "hierarchy": [
          "tgn:2006162",
          "tgn:7006450",
          "tgn:2000069",
          "tgn:1000001",
          "tgn:7012149",
          "tgn:7029392"
        ],
        "placetype": [
          "aat:300008347",
          "aat:300387210"
        ],
        "id": 2006162,
        "name:xx": "Kashegelok"
      }
    },
    {
      "geometry": {
        "type": "Point",
        "coordinates": [
          -162.5167,
          60.8833
        ]
      },
      "type": "Feature",
      "properties": {
        "hierarchy": [
          "tgn:2006164",
          "tgn:7006450",
          "tgn:2000069",
          "tgn:1000001",
          "tgn:7012149",
          "tgn:7029392"
        ],
        "placetype": [
          "aat:300008347"
        ],
        "id": 2006164,
        "name:xx": "Kasigluk"
      }
    }
  ]
}
