{
  "geometry": {
    "type": "Point",
    "coordinates": [
      -112.55,
      34.5833
    ]
  },
  "type": "Feature",
  "properties": {
    "hierarchy": [
      "tgn:2737111",
      "tgn:1000001",
      "tgn:7006451",
      "tgn:7012149",
      "tgn:2000103",
      "tgn:7029392"
    ],
    "placetype": [
      "aat:300008798"
    ],
    "id": 2737111,
    "name:xx": "Two Rock Mountain"
  }
}
