{
  "geometry": {
    "type": "Point",
    "coordinates": [
      12.85,
      53.85
    ]
  },
  "type": "Feature",
  "properties": {
    "hierarchy": [
      "tgn:7173923",
      "tgn:1000003",
      "tgn:7000094",
      "tgn:7000084",
      "tgn:7029392"
    ],
    "placetype": [
      "aat:300008876"
    ],
    "id": 7173923,
    "name:xx": "Große Rosinwiesen"
  }
}
