{
  "geometry": {
    "type": "Point",
    "coordinates": [
      -112.2333,
      34.3333
    ]
  },
  "type": "Feature",
  "properties": {
    "hierarchy": [
      "tgn:2181047",
      "tgn:1000001",
      "tgn:7006451",
      "tgn:7012149",
      "tgn:2000103",
      "tgn:7029392"
    ],
    "placetype": [
      "aat:300000390"
    ],
    "id": 2181047,
    "name:xx": "Blue Bell Mine"
  }
}
