{
  "type": "FeatureCollection",
  "features": [
    {
      "geometry": {
        "type": "Point",
        "coordinates": [
          48.4167,
          29.9167
        ]
      },
      "type": "Feature",
      "properties": {
        "hierarchy": [
          "tgn:1114060",
          "tgn:1000004",
          "tgn:7029392"
        ],
        "placetype": [
          "aat:300008713"
        ],
        "id": 1114060,
        "name:xx": "Khawr ʻAbd Allāh"
      }
    },
    {
      "geometry": {
        "type": "Point",
        "coordinates": [
          -76.9167,
          44.0833
        ]
      },
      "type": "Feature",
      "properties": {
        "hierarchy": [
          "tgn:1114061",
          "tgn:7005685",
          "tgn:1000001",
          "tgn:7013154",
          "tgn:7029392"
        ],
        "placetype": [
          "aat:300008713"
        ],
        "id": 1114061,
        "name:xx": "Adolphus Reach"
      }
    },
    {
      "geometry": {
        "type": "Point",
        "coordinates": [
          -156.5,
          20.5833
        ]
      },
      "type": "Feature",
      "properties": {
        "hierarchy": [
          "tgn:1114063",
          "tgn:1002648",
          "tgn:1000001",
          "tgn:7012149",
          "tgn:7007249",
          "tgn:7029392"
        ],
        "placetype": [
          "aat:300008713"
        ],
        "id": 1114063,
        "name:xx": "Alalakeiki Channel"
      }
    },
    {
      "geometry": {
        "type": "Point",
        "coordinates": [
          -156,
          20.4333
        ]
      },
      "type": "Feature",
      "properties": {
        "hierarchy": [
          "tgn:1114064",
          "tgn:1000001",
          "tgn:7012149",
          "tgn:7007249",
          "tgn:7029392"
        ],
        "placetype": [
          "aat:300008713"
        ],
        "id": 1114064,
        "name:xx": "Alenuihaha Channel"
      }
    },
    {
      "geometry": {
        "type": "Point",
        "coordinates": [
          -73.9833,
          40.5167
        ]
      },
      "type": "Feature",
      "properties": {
        "hierarchy": [
          "tgn:1114065",
          "tgn:1000001",
          "tgn:7012149",
          "tgn:7029392"
        ],
        "placetype": [
          "aat:300008713"
        ],
        "id": 1114065,
        "name:xx": "Ambrose Channel"
      }
    },
    {
      "geometry": {
        "type": "Point",
        "coordinates": [
          -172,
          52.45
        ]
      },
      "type": "Feature",
      "properties": {
        "hierarchy": [
          "tgn:1114067",
          "tgn:7030516",
          "tgn:7006450",
          "tgn:1000001",
          "tgn:7012149",
          "tgn:7029392"
        ],
        "placetype": [
          "aat:300008713"
        ],
        "id": 1114067,
        "name:xx": "Amukta Pass"
      }
    },
    {
      "geometry": {
        "type": "Point",
        "coordinates": [
          -74.383333,
          -49.9
        ]
      },
      "type": "Feature",
      "properties": {
        "hierarchy": [
          "tgn:1114068",
          "tgn:1001702",
          "tgn:1000049",
          "tgn:1000002",
          "tgn:7029392"
        ],
        "placetype": [
          "aat:300387026",
          "aat:300008713"
        ],
        "id": 1114068,
        "name:xx": "Wide, Canal"
      }
    },
    {
      "geometry": {
        "type": "Point",
        "coordinates": [
          16.333333,
          69.166667
        ]
      },
      "type": "Feature",
      "properties": {
        "hierarchy": [
          "tgn:1114069",
          "tgn:1000003",
          "tgn:1000088",
          "tgn:7029392"
        ],
        "placetype": [
          "aat:300008713"
        ],
        "id": 1114069,
        "name:xx": "Andfjorden"
      }
    }
  ]
}
