{
  "geometry": {
    "type": "Point",
    "coordinates": [
      -78.05,
      39.3167
    ]
  },
  "type": "Feature",
  "properties": {
    "hierarchy": [
      "tgn:2485883",
      "tgn:1000001",
      "tgn:2002254",
      "tgn:7012149",
      "tgn:7013961",
      "tgn:7029392"
    ],
    "placetype": [
      "aat:300008697"
    ],
    "id": 2485883,
    "name:xx": "LeFevre Spring"
  }
}
