{
  "geometry": {
    "type": "Point",
    "coordinates": [
      120.0333,
      -4.15
    ]
  },
  "type": "Feature",
  "properties": {
    "hierarchy": [
      "tgn:1078588",
      "tgn:1000004",
      "tgn:1001547",
      "tgn:1000116",
      "tgn:7029392"
    ],
    "placetype": [
      "aat:300008347"
    ],
    "id": 1078588,
    "name:xx": "Singkang"
  }
}
