{
  "geometry": {
    "type": "Point",
    "coordinates": [
      114.3667,
      22.3333
    ]
  },
  "type": "Feature",
  "properties": {
    "hierarchy": [
      "tgn:1007137",
      "tgn:7018487",
      "tgn:1000004",
      "tgn:7004542",
      "tgn:1000111",
      "tgn:7029392"
    ],
    "placetype": [
      "aat:300008791"
    ],
    "id": 1007137,
    "name:xx": "Fu Tau Pun Chau"
  }
}
