{
  "geometry": {
    "type": "Point",
    "coordinates": [
      -93.9833,
      33.4833
    ]
  },
  "type": "Feature",
  "properties": {
    "hierarchy": [
      "tgn:2746830",
      "tgn:1000001",
      "tgn:7016172",
      "tgn:7012149",
      "tgn:2000150",
      "tgn:7029392"
    ],
    "placetype": [
      "aat:300006191"
    ],
    "id": 2746830,
    "name:xx": "Wadley Lake"
  }
}
