{
  "geometry": {
    "type": "Point",
    "coordinates": [
      -134.2667,
      58.1833
    ]
  },
  "type": "Feature",
  "properties": {
    "hierarchy": [
      "tgn:2409308",
      "tgn:7006450",
      "tgn:1000001",
      "tgn:2124089",
      "tgn:7012149",
      "tgn:7029392"
    ],
    "placetype": [
      "aat:300008850"
    ],
    "id": 2409308,
    "name:xx": "Icy Point"
  }
}
