{
  "geometry": {
    "type": "Point",
    "coordinates": [
      -76.4333,
      43.4833
    ]
  },
  "type": "Feature",
  "properties": {
    "hierarchy": [
      "tgn:2748140",
      "tgn:1000001",
      "tgn:7012149",
      "tgn:1002758",
      "tgn:7007568",
      "tgn:7029392"
    ],
    "placetype": [
      "aat:300008347"
    ],
    "id": 2748140,
    "name:xx": "Walker"
  }
}
