{
  "type": "FeatureCollection",
  "features": [
    {
      "geometry": {
        "type": "Point",
        "coordinates": [
          -79.8667,
          44.3333
        ]
      },
      "type": "Feature",
      "properties": {
        "hierarchy": [
          "tgn:1128640",
          "tgn:7005685",
          "tgn:1000001",
          "tgn:7013154",
          "tgn:7029392"
        ],
        "placetype": [
          "aat:300008707"
        ],
        "id": 1128640,
        "name:xx": "Pine"
      }
    },
    {
      "geometry": {
        "type": "Point",
        "coordinates": [
          -71.0167,
          42.4333
        ]
      },
      "type": "Feature",
      "properties": {
        "hierarchy": [
          "tgn:1128642",
          "tgn:1000001",
          "tgn:7012149",
          "tgn:7007517",
          "tgn:7029392"
        ],
        "placetype": [
          "aat:300008707"
        ],
        "id": 1128642,
        "name:xx": "Pines"
      }
    },
    {
      "geometry": {
        "type": "Point",
        "coordinates": [
          -84.9,
          35.6833
        ]
      },
      "type": "Feature",
      "properties": {
        "hierarchy": [
          "tgn:1128643",
          "tgn:1000001",
          "tgn:7012149",
          "tgn:2001908",
          "tgn:7007825",
          "tgn:7029392"
        ],
        "placetype": [
          "aat:300008707"
        ],
        "id": 1128643,
        "name:xx": "Piney"
      }
    },
    {
      "geometry": {
        "type": "Point",
        "coordinates": [
          115.1167,
          25.9833
        ]
      },
      "type": "Feature",
      "properties": {
        "hierarchy": [
          "tgn:1128644",
          "tgn:1000004",
          "tgn:7002082",
          "tgn:1000111",
          "tgn:7029392"
        ],
        "placetype": [
          "aat:300008707"
        ],
        "id": 1128644,
        "name:xx": "Ping"
      }
    },
    {
      "geometry": {
        "type": "Point",
        "coordinates": [
          116.6,
          24.4167
        ]
      },
      "type": "Feature",
      "properties": {
        "hierarchy": [
          "tgn:1128646",
          "tgn:1000004",
          "tgn:7005232",
          "tgn:1000111",
          "tgn:7029392"
        ],
        "placetype": [
          "aat:300008707"
        ],
        "id": 1128646,
        "name:xx": "Pinghe"
      }
    },
    {
      "geometry": {
        "type": "Point",
        "coordinates": [
          -46.7,
          -22.7
        ]
      },
      "type": "Feature",
      "properties": {
        "hierarchy": [
          "tgn:1128647",
          "tgn:1001945",
          "tgn:1000047",
          "tgn:7002457",
          "tgn:1000002",
          "tgn:7029392"
        ],
        "placetype": [
          "aat:300008707"
        ],
        "id": 1128647,
        "name:xx": "Pinhal, Ribeirão do"
      }
    },
    {
      "geometry": {
        "type": "Point",
        "coordinates": [
          -46.7333,
          -23.5333
        ]
      },
      "type": "Feature",
      "properties": {
        "hierarchy": [
          "tgn:1128648",
          "tgn:1001945",
          "tgn:1000047",
          "tgn:7002457",
          "tgn:1000002",
          "tgn:7029392"
        ],
        "placetype": [
          "aat:300008707"
        ],
        "id": 1128648,
        "name:xx": "Pinheiros"
      }
    },
    {
      "geometry": {
        "type": "Point",
        "coordinates": [
          -65,
          -6.35
        ]
      },
      "type": "Feature",
      "properties": {
        "hierarchy": [
          "tgn:1128649",
          "tgn:1001826",
          "tgn:1000047",
          "tgn:7002456",
          "tgn:1000002",
          "tgn:7029392"
        ],
        "placetype": [
          "aat:300008707"
        ],
        "id": 1128649,
        "name:xx": "Pinhuã"
      }
    }
  ]
}
