{
  "geometry": {
    "type": "Point",
    "coordinates": [
      -70.2167,
      44.1667
    ]
  },
  "type": "Feature",
  "properties": {
    "hierarchy": [
      "tgn:2140123",
      "tgn:2000918",
      "tgn:1000001",
      "tgn:7012149",
      "tgn:7007515",
      "tgn:7029392"
    ],
    "placetype": [
      "aat:300008347"
    ],
    "id": 2140123,
    "name:xx": "Auburn Plains"
  }
}
