{
  "geometry": {
    "type": "Point",
    "coordinates": [
      -79.6833,
      36.7333
    ]
  },
  "type": "Feature",
  "properties": {
    "hierarchy": [
      "tgn:2490601",
      "tgn:1000001",
      "tgn:7012149",
      "tgn:7007919",
      "tgn:7029392"
    ],
    "placetype": [
      "aat:300008706"
    ],
    "id": 2490601,
    "name:xx": "Mann Creek"
  }
}
