{
  "type": "FeatureCollection",
  "features": [
    {
      "geometry": {
        "type": "Point",
        "coordinates": [
          9.083333,
          52.466667
        ]
      },
      "type": "Feature",
      "properties": {
        "hierarchy": [
          "tgn:7123480",
          "tgn:1000003",
          "tgn:7003677",
          "tgn:7000084",
          "tgn:7029392"
        ],
        "placetype": [
          "aat:300000206"
        ],
        "id": 7123480,
        "name:xx": "Neuhof"
      }
    },
    {
      "geometry": {
        "type": "Point",
        "coordinates": [
          14.133333,
          51.533333
        ]
      },
      "type": "Feature",
      "properties": {
        "hierarchy": [
          "tgn:7123481",
          "tgn:1000003",
          "tgn:7003685",
          "tgn:7000084",
          "tgn:7029392"
        ],
        "placetype": [
          "aat:300000206"
        ],
        "id": 7123481,
        "name:xx": "Neuhof"
      }
    },
    {
      "geometry": {
        "type": "Point",
        "coordinates": [
          14.416667,
          51.366667
        ]
      },
      "type": "Feature",
      "properties": {
        "hierarchy": [
          "tgn:7123482",
          "tgn:1000003",
          "tgn:7003685",
          "tgn:7000084",
          "tgn:7029392"
        ],
        "placetype": [
          "aat:300000206"
        ],
        "id": 7123482,
        "name:xx": "Neuhof"
      }
    },
    {
      "geometry": {
        "type": "Point",
        "coordinates": [
          6.6,
          51.233333
        ]
      },
      "type": "Feature",
      "properties": {
        "hierarchy": [
          "tgn:7123483",
          "tgn:1000003",
          "tgn:7003677",
          "tgn:7000084",
          "tgn:7029392"
        ],
        "placetype": [
          "aat:300000206"
        ],
        "id": 7123483,
        "name:xx": "Neuhof"
      }
    },
    {
      "geometry": {
        "type": "Point",
        "coordinates": [
          6.733333,
          50.95
        ]
      },
      "type": "Feature",
      "properties": {
        "hierarchy": [
          "tgn:7123484",
          "tgn:1000003",
          "tgn:7003677",
          "tgn:7000084",
          "tgn:7029392"
        ],
        "placetype": [
          "aat:300000206"
        ],
        "id": 7123484,
        "name:xx": "Neuhof"
      }
    },
    {
      "geometry": {
        "type": "Point",
        "coordinates": [
          7.85,
          50.65
        ]
      },
      "type": "Feature",
      "properties": {
        "hierarchy": [
          "tgn:7123485",
          "tgn:1000003",
          "tgn:7003682",
          "tgn:7000084",
          "tgn:7029392"
        ],
        "placetype": [
          "aat:300000206"
        ],
        "id": 7123485,
        "name:xx": "Neuhof"
      }
    },
    {
      "geometry": {
        "type": "Point",
        "coordinates": [
          8.683333,
          50.5
        ]
      },
      "type": "Feature",
      "properties": {
        "hierarchy": [
          "tgn:7123486",
          "tgn:1000003",
          "tgn:7003678",
          "tgn:7000084",
          "tgn:7029392"
        ],
        "placetype": [
          "aat:300000206"
        ],
        "id": 7123486,
        "name:xx": "Neuhof"
      }
    },
    {
      "geometry": {
        "type": "Point",
        "coordinates": [
          6.383333,
          50.416667
        ]
      },
      "type": "Feature",
      "properties": {
        "hierarchy": [
          "tgn:7123487",
          "tgn:1000003",
          "tgn:7003677",
          "tgn:7000084",
          "tgn:7029392"
        ],
        "placetype": [
          "aat:300000206"
        ],
        "id": 7123487,
        "name:xx": "Neuhof"
      }
    },
    {
      "geometry": {
        "type": "Point",
        "coordinates": [
          6.75,
          50.383333
        ]
      },
      "type": "Feature",
      "properties": {
        "hierarchy": [
          "tgn:7123488",
          "tgn:1000003",
          "tgn:7003677",
          "tgn:7000084",
          "tgn:7029392"
        ],
        "placetype": [
          "aat:300000206"
        ],
        "id": 7123488,
        "name:xx": "Neuhof"
      }
    },
    {
      "geometry": {
        "type": "Point",
        "coordinates": [
          7.35,
          50.216667
        ]
      },
      "type": "Feature",
      "properties": {
        "hierarchy": [
          "tgn:7123489",
          "tgn:1000003",
          "tgn:7003682",
          "tgn:7000084",
          "tgn:7029392"
        ],
        "placetype": [
          "aat:300000206"
        ],
        "id": 7123489,
        "name:xx": "Neuhof"
      }
    }
  ]
}
