{
  "type": "FeatureCollection",
  "features": [
    {
      "geometry": {
        "type": "Point",
        "coordinates": [
          8.8,
          51.416667
        ]
      },
      "type": "Feature",
      "properties": {
        "hierarchy": [
          "tgn:7167920",
          "tgn:1000003",
          "tgn:7003677",
          "tgn:7000084",
          "tgn:7029392"
        ],
        "placetype": [
          "aat:300008777"
        ],
        "id": 7167920,
        "name:xx": "Heim-Berg"
      }
    },
    {
      "geometry": {
        "type": "Point",
        "coordinates": [
          8.633333,
          51.4
        ]
      },
      "type": "Feature",
      "properties": {
        "hierarchy": [
          "tgn:7167921",
          "tgn:1000003",
          "tgn:7003677",
          "tgn:7000084",
          "tgn:7029392"
        ],
        "placetype": [
          "aat:300008777"
        ],
        "id": 7167921,
        "name:xx": "Heim-Berg"
      }
    },
    {
      "geometry": {
        "type": "Point",
        "coordinates": [
          8.266667,
          51.35
        ]
      },
      "type": "Feature",
      "properties": {
        "hierarchy": [
          "tgn:7167922",
          "tgn:1000003",
          "tgn:7003677",
          "tgn:7000084",
          "tgn:7029392"
        ],
        "placetype": [
          "aat:300008777"
        ],
        "id": 7167922,
        "name:xx": "Heim-Berg"
      }
    },
    {
      "geometry": {
        "type": "Point",
        "coordinates": [
          8.383333,
          51.316667
        ]
      },
      "type": "Feature",
      "properties": {
        "hierarchy": [
          "tgn:7167923",
          "tgn:1000003",
          "tgn:7003677",
          "tgn:7000084",
          "tgn:7029392"
        ],
        "placetype": [
          "aat:300008777"
        ],
        "id": 7167923,
        "name:xx": "Heim-Berg"
      }
    },
    {
      "geometry": {
        "type": "Point",
        "coordinates": [
          8.716667,
          51.233333
        ]
      },
      "type": "Feature",
      "properties": {
        "hierarchy": [
          "tgn:7167924",
          "tgn:1000003",
          "tgn:7003678",
          "tgn:7000084",
          "tgn:7029392"
        ],
        "placetype": [
          "aat:300008777"
        ],
        "id": 7167924,
        "name:xx": "Heim-Berg"
      }
    },
    {
      "geometry": {
        "type": "Point",
        "coordinates": [
          8.2,
          51.2
        ]
      },
      "type": "Feature",
      "properties": {
        "hierarchy": [
          "tgn:7167926",
          "tgn:1000003",
          "tgn:7003677",
          "tgn:7000084",
          "tgn:7029392"
        ],
        "placetype": [
          "aat:300008777"
        ],
        "id": 7167926,
        "name:xx": "Heim-Berg"
      }
    },
    {
      "geometry": {
        "type": "Point",
        "coordinates": [
          7.733333,
          49.8
        ]
      },
      "type": "Feature",
      "properties": {
        "hierarchy": [
          "tgn:7167927",
          "tgn:1000003",
          "tgn:7003682",
          "tgn:7000084",
          "tgn:7029392"
        ],
        "placetype": [
          "aat:300008777"
        ],
        "id": 7167927,
        "name:xx": "Heimberg"
      }
    },
    {
      "geometry": {
        "type": "Point",
        "coordinates": [
          11.733333,
          49.183333
        ]
      },
      "type": "Feature",
      "properties": {
        "hierarchy": [
          "tgn:7167928",
          "tgn:7003669",
          "tgn:1000003",
          "tgn:7000084",
          "tgn:7029392"
        ],
        "placetype": [
          "aat:300008777"
        ],
        "id": 7167928,
        "name:xx": "Heimberg"
      }
    },
    {
      "geometry": {
        "type": "Point",
        "coordinates": [
          9.45,
          49.133333
        ]
      },
      "type": "Feature",
      "properties": {
        "hierarchy": [
          "tgn:7167929",
          "tgn:7003692",
          "tgn:1000003",
          "tgn:7000084",
          "tgn:7029392"
        ],
        "placetype": [
          "aat:300008777"
        ],
        "id": 7167929,
        "name:xx": "Heimberg"
      }
    }
  ]
}
