{
  "geometry": {
    "type": "Point",
    "coordinates": [
      -109.3833,
      32.2167
    ]
  },
  "type": "Feature",
  "properties": {
    "hierarchy": [
      "tgn:2287396",
      "tgn:1000001",
      "tgn:7006451",
      "tgn:2000091",
      "tgn:7012149",
      "tgn:7029392"
    ],
    "placetype": [
      "aat:300006191"
    ],
    "id": 2287396,
    "name:xx": "Dickson Tank"
  }
}
