{
  "geometry": {
    "type": "Point",
    "coordinates": [
      -87.2667,
      45.9333
    ]
  },
  "type": "Feature",
  "properties": {
    "hierarchy": [
      "tgn:2216502",
      "tgn:1000001",
      "tgn:2000955",
      "tgn:7012149",
      "tgn:7007520",
      "tgn:7029392"
    ],
    "placetype": [
      "aat:300008706"
    ],
    "id": 2216502,
    "name:xx": "Camp Creek"
  }
}
