{
  "type": "FeatureCollection",
  "features": [
    {
      "geometry": {
        "type": "Point",
        "coordinates": [
          -8.332,
          40.354
        ]
      },
      "type": "Feature",
      "properties": {
        "hierarchy": [
          "tgn:4008530",
          "tgn:7003820",
          "tgn:1000003",
          "tgn:1000090",
          "tgn:7029392"
        ],
        "placetype": [
          "aat:300008347"
        ],
        "id": 4008530,
        "name:xx": "Pendurada"
      }
    },
    {
      "geometry": {
        "type": "Point",
        "coordinates": [
          -9.201,
          39.066
        ]
      },
      "type": "Feature",
      "properties": {
        "hierarchy": [
          "tgn:4008531",
          "tgn:1000882",
          "tgn:1000003",
          "tgn:1000090",
          "tgn:7029392"
        ],
        "placetype": [
          "aat:300008347"
        ],
        "id": 4008531,
        "name:xx": "Penedo"
      }
    },
    {
      "geometry": {
        "type": "Point",
        "coordinates": [
          41.95,
          37.45
        ]
      },
      "type": "Feature",
      "properties": {
        "hierarchy": [
          "tgn:4008532",
          "tgn:1001509",
          "tgn:1000004",
          "tgn:7018456",
          "tgn:1000144",
          "tgn:7029392"
        ],
        "placetype": [
          "aat:300008347",
          "aat:300008375"
        ],
        "id": 4008532,
        "name:xx": "Penek"
      }
    },
    {
      "geometry": {
        "type": "Point",
        "coordinates": [
          -4.05,
          53.3
        ]
      },
      "type": "Feature",
      "properties": {
        "hierarchy": [
          "tgn:4008537",
          "tgn:7008532",
          "tgn:7002443",
          "tgn:1000003",
          "tgn:7008591",
          "tgn:7029392"
        ],
        "placetype": [
          "aat:300008347"
        ],
        "name:en": "Penmon",
        "id": 4008537
      }
    }
  ]
}
