{
  "geometry": {
    "type": "Point",
    "coordinates": [
      -103.4667,
      37.2667
    ]
  },
  "type": "Feature",
  "properties": {
    "hierarchy": [
      "tgn:2588510",
      "tgn:1000001",
      "tgn:7012149",
      "tgn:2000227",
      "tgn:7007158",
      "tgn:7029392"
    ],
    "placetype": [
      "aat:300008761"
    ],
    "id": 2588510,
    "name:xx": "Plum Valley"
  }
}
