{
  "geometry": {
    "type": "Point",
    "coordinates": [
      30.933889,
      30.933889
    ]
  },
  "type": "Feature",
  "properties": {
    "hierarchy": [
      "tgn:7527417",
      "tgn:7001242",
      "tgn:7016833",
      "tgn:1001113",
      "tgn:7029392"
    ],
    "placetype": [
      "aat:300008777"
    ],
    "name:en": "Jazīrat az Zuwaylīn, Tall",
    "id": 7527417
  }
}
