{
  "type": "FeatureCollection",
  "features": [
    {
      "geometry": {
        "type": "Point",
        "coordinates": [
          117.85,
          24.4
        ]
      },
      "type": "Feature",
      "properties": {
        "hierarchy": [
          "tgn:1068530",
          "tgn:1000004",
          "tgn:7001796",
          "tgn:1000111",
          "tgn:7029392"
        ],
        "placetype": [
          "aat:300008347"
        ],
        "id": 1068530,
        "name:xx": "Haicheng"
      }
    },
    {
      "geometry": {
        "type": "Point",
        "coordinates": [
          116.3,
          39.9667
        ]
      },
      "type": "Feature",
      "properties": {
        "hierarchy": [
          "tgn:1068531",
          "tgn:1000956",
          "tgn:1000004",
          "tgn:1000111",
          "tgn:7029392"
        ],
        "placetype": [
          "aat:300008347"
        ],
        "id": 1068531,
        "name:xx": "Haidian"
      }
    },
    {
      "geometry": {
        "type": "Point",
        "coordinates": [
          121.8167,
          29.6
        ]
      },
      "type": "Feature",
      "properties": {
        "hierarchy": [
          "tgn:1068532",
          "tgn:1000004",
          "tgn:7002076",
          "tgn:1000111",
          "tgn:7029392"
        ],
        "placetype": [
          "aat:300008347"
        ],
        "id": 1068532,
        "name:xx": "Haidun"
      }
    },
    {
      "geometry": {
        "type": "Point",
        "coordinates": [
          115.3167,
          22.9333
        ]
      },
      "type": "Feature",
      "properties": {
        "hierarchy": [
          "tgn:1068533",
          "tgn:1000004",
          "tgn:7005232",
          "tgn:1000111",
          "tgn:7029392"
        ],
        "placetype": [
          "aat:300008347"
        ],
        "id": 1068533,
        "name:xx": "Haifeng"
      }
    },
    {
      "geometry": {
        "type": "Point",
        "coordinates": [
          121.7667,
          31.8833
        ]
      },
      "type": "Feature",
      "properties": {
        "hierarchy": [
          "tgn:1068534",
          "tgn:1000004",
          "tgn:7002081",
          "tgn:1000111",
          "tgn:7029392"
        ],
        "placetype": [
          "aat:300008347"
        ],
        "id": 1068534,
        "name:xx": "Haifengzheng"
      }
    },
    {
      "geometry": {
        "type": "Point",
        "coordinates": [
          121.7,
          31.9833
        ]
      },
      "type": "Feature",
      "properties": {
        "hierarchy": [
          "tgn:1068535",
          "tgn:1000004",
          "tgn:7002081",
          "tgn:1000111",
          "tgn:7029392"
        ],
        "placetype": [
          "aat:300008347"
        ],
        "id": 1068535,
        "name:xx": "Haifuzhen"
      }
    },
    {
      "geometry": {
        "type": "Point",
        "coordinates": [
          120.0333,
          33.7333
        ]
      },
      "type": "Feature",
      "properties": {
        "hierarchy": [
          "tgn:1068536",
          "tgn:1000004",
          "tgn:7002081",
          "tgn:1000111",
          "tgn:7029392"
        ],
        "placetype": [
          "aat:300008347"
        ],
        "id": 1068536,
        "name:xx": "Haihezhen"
      }
    },
    {
      "geometry": {
        "type": "Point",
        "coordinates": [
          110.0833,
          20.9
        ]
      },
      "type": "Feature",
      "properties": {
        "hierarchy": [
          "tgn:1068537",
          "tgn:1000004",
          "tgn:7005232",
          "tgn:1000111",
          "tgn:7029392"
        ],
        "placetype": [
          "aat:300008347"
        ],
        "id": 1068537,
        "name:xx": "Haikang"
      }
    },
    {
      "geometry": {
        "type": "Point",
        "coordinates": [
          110.4167,
          20.0833
        ]
      },
      "type": "Feature",
      "properties": {
        "hierarchy": [
          "tgn:1068538",
          "tgn:1000004",
          "tgn:7001800",
          "tgn:1000111",
          "tgn:7029392"
        ],
        "placetype": [
          "aat:300008347",
          "aat:300387223",
          "aat:300008375",
          "aat:300120599"
        ],
        "id": 1068538,
        "name:xx": "Haikou"
      }
    }
  ]
}
