{
  "geometry": {
    "type": "Point",
    "coordinates": [
      -81.35,
      40.1833
    ]
  },
  "type": "Feature",
  "properties": {
    "hierarchy": [
      "tgn:2670300",
      "tgn:1000001",
      "tgn:7012149",
      "tgn:7007706",
      "tgn:7029392"
    ],
    "placetype": [
      "aat:300008706"
    ],
    "id": 2670300,
    "name:xx": "Small Atkinson Creek"
  }
}
