{
  "geometry": {
    "type": "Point",
    "coordinates": [
      -90.9333,
      33.9333
    ]
  },
  "type": "Feature",
  "properties": {
    "hierarchy": [
      "tgn:2056561",
      "tgn:1000001",
      "tgn:2001091",
      "tgn:7012149",
      "tgn:7007522",
      "tgn:7029392"
    ],
    "placetype": [
      "aat:300008347"
    ],
    "id": 2056561,
    "name:xx": "Gunnison"
  }
}
