{
  "type": "FeatureCollection",
  "features": [
    {
      "geometry": {
        "type": "Point",
        "coordinates": [
          10.983333,
          49.483333
        ]
      },
      "type": "Feature",
      "properties": {
        "hierarchy": [
          "tgn:1128500",
          "tgn:7003669",
          "tgn:1000003",
          "tgn:7000084",
          "tgn:7029392"
        ],
        "placetype": [
          "aat:300008707",
          "aat:300008699"
        ],
        "id": 1128500,
        "name:xx": "Pegnitz"
      }
    },
    {
      "geometry": {
        "type": "Point",
        "coordinates": [
          121.173985,
          22.756931
        ]
      },
      "type": "Feature",
      "properties": {
        "hierarchy": [
          "tgn:1128504",
          "tgn:1000004",
          "tgn:7491221",
          "tgn:1000141",
          "tgn:7029392"
        ],
        "placetype": [
          "aat:300008707",
          "aat:300008699"
        ],
        "id": 1128504,
        "name:xx": "Beinan Daxi"
      }
    },
    {
      "geometry": {
        "type": "Point",
        "coordinates": [
          -50.85,
          -14.1
        ]
      },
      "type": "Feature",
      "properties": {
        "hierarchy": [
          "tgn:1128505",
          "tgn:1001945",
          "tgn:1000047",
          "tgn:7002457",
          "tgn:1000002",
          "tgn:7029392"
        ],
        "placetype": [
          "aat:300008707"
        ],
        "id": 1128505,
        "name:xx": "Peixe, Rio do"
      }
    },
    {
      "geometry": {
        "type": "Point",
        "coordinates": [
          -57.9333,
          -10.7
        ]
      },
      "type": "Feature",
      "properties": {
        "hierarchy": [
          "tgn:1128506",
          "tgn:7006260",
          "tgn:7002454",
          "tgn:1000047",
          "tgn:1000002",
          "tgn:7029392"
        ],
        "placetype": [
          "aat:300008707"
        ],
        "id": 1128506,
        "name:xx": "Peixes, Rio dos"
      }
    },
    {
      "geometry": {
        "type": "Point",
        "coordinates": [
          -55.5167,
          -10.1
        ]
      },
      "type": "Feature",
      "properties": {
        "hierarchy": [
          "tgn:1128507",
          "tgn:7006260",
          "tgn:7002454",
          "tgn:1000047",
          "tgn:1000002",
          "tgn:7029392"
        ],
        "placetype": [
          "aat:300008707"
        ],
        "id": 1128507,
        "name:xx": "Peixoto de Azevedo"
      }
    },
    {
      "geometry": {
        "type": "Point",
        "coordinates": [
          21.5833,
          44.75
        ]
      },
      "type": "Feature",
      "properties": {
        "hierarchy": [
          "tgn:1128508",
          "tgn:1000003",
          "tgn:7006669",
          "tgn:7029392"
        ],
        "placetype": [
          "aat:300008707"
        ],
        "id": 1128508,
        "name:xx": "Pek"
      }
    }
  ]
}
