{
  "type": "FeatureCollection",
  "features": [
    {
      "geometry": {
        "type": "Point",
        "coordinates": [
          -54.2,
          -24.0333
        ]
      },
      "type": "Feature",
      "properties": {
        "hierarchy": [
          "tgn:1101860",
          "tgn:1000047",
          "tgn:1000002",
          "tgn:7029392"
        ],
        "placetype": [
          "aat:300008189"
        ],
        "id": 1101860,
        "name:xx": "Sete Quedas, Parque Nacional de"
      }
    },
    {
      "geometry": {
        "type": "Point",
        "coordinates": [
          134,
          34.3333
        ]
      },
      "type": "Feature",
      "properties": {
        "hierarchy": [
          "tgn:1101861",
          "tgn:1000004",
          "tgn:1000120",
          "tgn:7029392"
        ],
        "placetype": [
          "aat:300008189"
        ],
        "id": 1101861,
        "name:xx": "Setonaikai Kokuritsukōen"
      }
    },
    {
      "geometry": {
        "type": "Point",
        "coordinates": [
          150.7667,
          -34.8167
        ]
      },
      "type": "Feature",
      "properties": {
        "hierarchy": [
          "tgn:1101862",
          "tgn:7000490",
          "tgn:1000006",
          "tgn:7001828",
          "tgn:7029392"
        ],
        "placetype": [
          "aat:300008189"
        ],
        "id": 1101862,
        "name:xx": "Seven Mile Beach National Park"
      }
    },
    {
      "geometry": {
        "type": "Point",
        "coordinates": [
          141,
          42.7833
        ]
      },
      "type": "Feature",
      "properties": {
        "hierarchy": [
          "tgn:1101864",
          "tgn:1000985",
          "tgn:7016529",
          "tgn:7016531",
          "tgn:1000004",
          "tgn:1000120",
          "tgn:7029392"
        ],
        "placetype": [
          "aat:300008189"
        ],
        "id": 1101864,
        "name:xx": "Shikotsu-Tōya-kokuritsu-kōen"
      }
    },
    {
      "geometry": {
        "type": "Point",
        "coordinates": [
          145.1667,
          44.1333
        ]
      },
      "type": "Feature",
      "properties": {
        "hierarchy": [
          "tgn:1101865",
          "tgn:1000985",
          "tgn:7016529",
          "tgn:7016531",
          "tgn:1000004",
          "tgn:1000120",
          "tgn:7029392"
        ],
        "placetype": [
          "aat:300008189"
        ],
        "id": 1101865,
        "name:xx": "Shiretoko-kokuritsu-kōen"
      }
    },
    {
      "geometry": {
        "type": "Point",
        "coordinates": [
          133.1333,
          33.75
        ]
      },
      "type": "Feature",
      "properties": {
        "hierarchy": [
          "tgn:1101866",
          "tgn:7004473",
          "tgn:1000004",
          "tgn:7000903",
          "tgn:1000120",
          "tgn:7029392"
        ],
        "placetype": [
          "aat:300008189"
        ],
        "id": 1101866,
        "name:xx": "Shizuchi-kokutei-kōen"
      }
    },
    {
      "geometry": {
        "type": "Point",
        "coordinates": [
          136.5,
          45.2
        ]
      },
      "type": "Feature",
      "properties": {
        "hierarchy": [
          "tgn:1101867",
          "tgn:1000004",
          "tgn:7011539",
          "tgn:7018214",
          "tgn:7002435",
          "tgn:7029392"
        ],
        "placetype": [
          "aat:300008189"
        ],
        "id": 1101867,
        "name:xx": "Sikhote-Alin'skiy Zapovednik"
      }
    },
    {
      "geometry": {
        "type": "Point",
        "coordinates": [
          -70.8333,
          8.6
        ]
      },
      "type": "Feature",
      "properties": {
        "hierarchy": [
          "tgn:1101868",
          "tgn:1001837",
          "tgn:1000002",
          "tgn:1000059",
          "tgn:7029392"
        ],
        "placetype": [
          "aat:300008189"
        ],
        "id": 1101868,
        "name:xx": "Sierra Nevada, Parque Nacional"
      }
    },
    {
      "geometry": {
        "type": "Point",
        "coordinates": [
          -115.5,
          31
        ]
      },
      "type": "Feature",
      "properties": {
        "hierarchy": [
          "tgn:1101869",
          "tgn:1001835",
          "tgn:1000001",
          "tgn:7005560",
          "tgn:7029392"
        ],
        "placetype": [
          "aat:300008189"
        ],
        "id": 1101869,
        "name:xx": "Sierra San Pedro Mártir, Parque Nacional"
      }
    }
  ]
}
