{
  "geometry": {
    "type": "Point",
    "coordinates": [
      -121.1333,
      47.6167
    ]
  },
  "type": "Feature",
  "properties": {
    "hierarchy": [
      "tgn:2274271",
      "tgn:1000001",
      "tgn:7012149",
      "tgn:7018871",
      "tgn:7007920",
      "tgn:7029392"
    ],
    "placetype": [
      "aat:300008680"
    ],
    "id": 2274271,
    "name:xx": "Daisy Lake"
  }
}
