{
  "geometry": {
    "type": "Point",
    "coordinates": [
      26.526006,
      29.161045
    ]
  },
  "type": "Feature",
  "properties": {
    "hierarchy": [
      "tgn:7533398",
      "tgn:7001242",
      "tgn:7016833",
      "tgn:1001418",
      "tgn:7029392"
    ],
    "placetype": [
      "aat:300379998"
    ],
    "name:en": "Ḩāmid, Wādī",
    "id": 7533398
  }
}
