{
  "geometry": {
    "type": "Point",
    "coordinates": [
      -109.4667,
      40.85
    ]
  },
  "type": "Feature",
  "properties": {
    "hierarchy": [
      "tgn:2236485",
      "tgn:1000001",
      "tgn:2002105",
      "tgn:7012149",
      "tgn:7007827",
      "tgn:7029392"
    ],
    "placetype": [
      "aat:300008697"
    ],
    "id": 2236485,
    "name:xx": "Chicken Spring"
  }
}
