{
  "type": "FeatureCollection",
  "features": [
    {
      "geometry": {
        "type": "Point",
        "coordinates": [
          -61.6833,
          49.1333
        ]
      },
      "type": "Feature",
      "properties": {
        "hierarchy": [
          "tgn:1011860",
          "tgn:1006302",
          "tgn:7005685",
          "tgn:1000001",
          "tgn:7005804",
          "tgn:7029392"
        ],
        "placetype": [
          "aat:300386846"
        ],
        "id": 1011860,
        "name:xx": "Est, Pointe de l'"
      }
    },
    {
      "geometry": {
        "type": "Point",
        "coordinates": [
          -7.7,
          43.766667
        ]
      },
      "type": "Feature",
      "properties": {
        "hierarchy": [
          "tgn:1011861",
          "tgn:7002824",
          "tgn:1000003",
          "tgn:7002786",
          "tgn:1000095",
          "tgn:7029392"
        ],
        "placetype": [
          "aat:300386846"
        ],
        "id": 1011861,
        "name:xx": "Estaca de Bares, Punta de la"
      }
    },
    {
      "geometry": {
        "type": "Point",
        "coordinates": [
          -65.3167,
          18.15
        ]
      },
      "type": "Feature",
      "properties": {
        "hierarchy": [
          "tgn:1011862",
          "tgn:7017442",
          "tgn:1009641",
          "tgn:1000001",
          "tgn:7004643",
          "tgn:7029392"
        ],
        "placetype": [
          "aat:300386846"
        ],
        "id": 1011862,
        "name:xx": "Este, Punta"
      }
    },
    {
      "geometry": {
        "type": "Point",
        "coordinates": [
          -114.7,
          30.9
        ]
      },
      "type": "Feature",
      "properties": {
        "hierarchy": [
          "tgn:1011863",
          "tgn:1001835",
          "tgn:1000001",
          "tgn:7005560",
          "tgn:7029392"
        ],
        "placetype": [
          "aat:300386846"
        ],
        "id": 1011863,
        "name:xx": "Estrella, Punta"
      }
    },
    {
      "geometry": {
        "type": "Point",
        "coordinates": [
          -115.083333,
          27.833333
        ]
      },
      "type": "Feature",
      "properties": {
        "hierarchy": [
          "tgn:1011864",
          "tgn:1001836",
          "tgn:1000001",
          "tgn:7005560",
          "tgn:7029392"
        ],
        "placetype": [
          "aat:300386846"
        ],
        "id": 1011864,
        "name:xx": "Eugenia, Punta"
      }
    },
    {
      "geometry": {
        "type": "Point",
        "coordinates": [
          -72.0833,
          63.4
        ]
      },
      "type": "Feature",
      "properties": {
        "hierarchy": [
          "tgn:1011868",
          "tgn:7013003",
          "tgn:7005685",
          "tgn:1000001",
          "tgn:7024197",
          "tgn:7029392"
        ],
        "placetype": [
          "aat:300386846"
        ],
        "id": 1011868,
        "name:xx": "Fair Ness"
      }
    },
    {
      "geometry": {
        "type": "Point",
        "coordinates": [
          -70.0833,
          -21.4167
        ]
      },
      "type": "Feature",
      "properties": {
        "hierarchy": [
          "tgn:1011869",
          "tgn:7002464",
          "tgn:1000049",
          "tgn:1000002",
          "tgn:7029392"
        ],
        "placetype": [
          "aat:300386846"
        ],
        "id": 1011869,
        "name:xx": "Falsa Chipana, Punta"
      }
    }
  ]
}
