{
  "type": "FeatureCollection",
  "features": [
    {
      "geometry": {
        "type": "Point",
        "coordinates": [
          9.783333,
          52.8
        ]
      },
      "type": "Feature",
      "properties": {
        "hierarchy": [
          "tgn:7077370",
          "tgn:1000003",
          "tgn:7003676",
          "tgn:7000084",
          "tgn:7029392"
        ],
        "placetype": [
          "aat:300008777"
        ],
        "id": 7077370,
        "name:xx": "Ziegen-Berg"
      }
    },
    {
      "geometry": {
        "type": "Point",
        "coordinates": [
          11.116667,
          52.383333
        ]
      },
      "type": "Feature",
      "properties": {
        "hierarchy": [
          "tgn:7077371",
          "tgn:1000003",
          "tgn:7003687",
          "tgn:7000084",
          "tgn:7029392"
        ],
        "placetype": [
          "aat:300008777"
        ],
        "id": 7077371,
        "name:xx": "Ziegen-Berg"
      }
    },
    {
      "geometry": {
        "type": "Point",
        "coordinates": [
          10.016667,
          52.05
        ]
      },
      "type": "Feature",
      "properties": {
        "hierarchy": [
          "tgn:7077372",
          "tgn:1000003",
          "tgn:7003676",
          "tgn:7000084",
          "tgn:7029392"
        ],
        "placetype": [
          "aat:300008777"
        ],
        "id": 7077372,
        "name:xx": "Ziegen-Berg"
      }
    },
    {
      "geometry": {
        "type": "Point",
        "coordinates": [
          10.75,
          51.833333
        ]
      },
      "type": "Feature",
      "properties": {
        "hierarchy": [
          "tgn:7077373",
          "tgn:1000003",
          "tgn:7003687",
          "tgn:7000084",
          "tgn:7029392"
        ],
        "placetype": [
          "aat:300008777"
        ],
        "id": 7077373,
        "name:xx": "Ziegen-Berg"
      }
    },
    {
      "geometry": {
        "type": "Point",
        "coordinates": [
          10.133333,
          51.766667
        ]
      },
      "type": "Feature",
      "properties": {
        "hierarchy": [
          "tgn:7077374",
          "tgn:1000003",
          "tgn:7003676",
          "tgn:7000084",
          "tgn:7029392"
        ],
        "placetype": [
          "aat:300008777"
        ],
        "id": 7077374,
        "name:xx": "Ziegen-Berg"
      }
    },
    {
      "geometry": {
        "type": "Point",
        "coordinates": [
          10.9,
          51.816667
        ]
      },
      "type": "Feature",
      "properties": {
        "hierarchy": [
          "tgn:7077375",
          "tgn:1000003",
          "tgn:7003687",
          "tgn:7000084",
          "tgn:7029392"
        ],
        "placetype": [
          "aat:300008777"
        ],
        "id": 7077375,
        "name:xx": "Ziegen-Berg"
      }
    },
    {
      "geometry": {
        "type": "Point",
        "coordinates": [
          9.366667,
          51.766667
        ]
      },
      "type": "Feature",
      "properties": {
        "hierarchy": [
          "tgn:7077377",
          "tgn:1000003",
          "tgn:7003677",
          "tgn:7000084",
          "tgn:7029392"
        ],
        "placetype": [
          "aat:300008777"
        ],
        "id": 7077377,
        "name:xx": "Ziegen-Berg"
      }
    },
    {
      "geometry": {
        "type": "Point",
        "coordinates": [
          8.85,
          51.75
        ]
      },
      "type": "Feature",
      "properties": {
        "hierarchy": [
          "tgn:7077378",
          "tgn:1000003",
          "tgn:7003677",
          "tgn:7000084",
          "tgn:7029392"
        ],
        "placetype": [
          "aat:300008777"
        ],
        "id": 7077378,
        "name:xx": "Ziegen-Berg"
      }
    },
    {
      "geometry": {
        "type": "Point",
        "coordinates": [
          9.916667,
          51.7
        ]
      },
      "type": "Feature",
      "properties": {
        "hierarchy": [
          "tgn:7077379",
          "tgn:1000003",
          "tgn:7003676",
          "tgn:7000084",
          "tgn:7029392"
        ],
        "placetype": [
          "aat:300008777"
        ],
        "id": 7077379,
        "name:xx": "Ziegen-Berg"
      }
    }
  ]
}
