{
  "type": "FeatureCollection",
  "features": [
    {
      "geometry": {
        "type": "Point",
        "coordinates": [
          85.415314,
          25.032792
        ]
      },
      "type": "Feature",
      "properties": {
        "hierarchy": [
          "tgn:7556220",
          "tgn:1000004",
          "tgn:1001842",
          "tgn:7000198",
          "tgn:7029392"
        ],
        "placetype": [
          "aat:300007783"
        ],
        "name:en": "Rājgīr Kund",
        "id": 7556220
      }
    },
    {
      "geometry": {
        "type": "Point",
        "coordinates": [
          85.401262,
          25.001928
        ]
      },
      "type": "Feature",
      "properties": {
        "hierarchy": [
          "tgn:7556221",
          "tgn:1000004",
          "tgn:1001842",
          "tgn:7000198",
          "tgn:7029392"
        ],
        "placetype": [
          "aat:300008777"
        ],
        "name:en": "Rājgīr Hills",
        "id": 7556221
      }
    },
    {
      "geometry": {
        "type": "Point",
        "coordinates": [
          78.35,
          28.25
        ]
      },
      "type": "Feature",
      "properties": {
        "hierarchy": [
          "tgn:7556223",
          "tgn:1000004",
          "tgn:7000198",
          "tgn:7016722",
          "tgn:7029392"
        ],
        "placetype": [
          "aat:300007783"
        ],
        "name:en": "Rājghāt Naraura",
        "id": 7556223
      }
    },
    {
      "geometry": {
        "type": "Point",
        "coordinates": [
          77.299093,
          30.851453
        ]
      },
      "type": "Feature",
      "properties": {
        "hierarchy": [
          "tgn:7556225",
          "tgn:1000004",
          "tgn:7000198",
          "tgn:1001996",
          "tgn:7029392"
        ],
        "placetype": [
          "aat:300008347"
        ],
        "name:en": "Rājgarh",
        "id": 7556225
      }
    },
    {
      "geometry": {
        "type": "Point",
        "coordinates": [
          74.620143,
          26.301471
        ]
      },
      "type": "Feature",
      "properties": {
        "hierarchy": [
          "tgn:7556228",
          "tgn:1000004",
          "tgn:7000198",
          "tgn:7016788",
          "tgn:7029392"
        ],
        "placetype": [
          "aat:300008347"
        ],
        "name:en": "Rājgarh",
        "id": 7556228
      }
    },
    {
      "geometry": {
        "type": "Point",
        "coordinates": [
          77.955198,
          25.469484
        ]
      },
      "type": "Feature",
      "properties": {
        "hierarchy": [
          "tgn:7556229",
          "tgn:1000004",
          "tgn:7000198",
          "tgn:1001894",
          "tgn:7029392"
        ],
        "placetype": [
          "aat:300008347"
        ],
        "name:en": "Rājgarh",
        "id": 7556229
      }
    }
  ]
}
