{
  "geometry": {
    "type": "Point",
    "coordinates": [
      -78.3167,
      40.8167
    ]
  },
  "type": "Feature",
  "properties": {
    "hierarchy": [
      "tgn:2357006",
      "tgn:1000001",
      "tgn:1002278",
      "tgn:7012149",
      "tgn:7007710",
      "tgn:7029392"
    ],
    "placetype": [
      "aat:300008347"
    ],
    "id": 2357006,
    "name:xx": "Goss Run Junction"
  }
}
