{
  "geometry": {
    "type": "Point",
    "coordinates": [
      -76.9167,
      38.1333
    ]
  },
  "type": "Feature",
  "properties": {
    "hierarchy": [
      "tgn:7021935",
      "tgn:1000001",
      "tgn:7012149",
      "tgn:7007919",
      "tgn:7029392"
    ],
    "placetype": [
      "aat:300008699"
    ],
    "id": 7021935,
    "name:xx": "Big Swamp, The"
  }
}
