{
  "type": "FeatureCollection",
  "features": [
    {
      "geometry": {
        "type": "Point",
        "coordinates": [
          -95.2833,
          46.2
        ]
      },
      "type": "Feature",
      "properties": {
        "hierarchy": [
          "tgn:2272450",
          "tgn:1000001",
          "tgn:7012149",
          "tgn:2001054",
          "tgn:7007521",
          "tgn:7029392"
        ],
        "placetype": [
          "aat:300008680"
        ],
        "id": 2272450,
        "name:xx": "Curtis Lake"
      }
    },
    {
      "geometry": {
        "type": "Point",
        "coordinates": [
          -95.4333,
          48
        ]
      },
      "type": "Feature",
      "properties": {
        "hierarchy": [
          "tgn:2272451",
          "tgn:1000001",
          "tgn:2001013",
          "tgn:7012149",
          "tgn:7007521",
          "tgn:7029392"
        ],
        "placetype": [
          "aat:300008680"
        ],
        "id": 2272451,
        "name:xx": "Curtis Lake"
      }
    },
    {
      "geometry": {
        "type": "Point",
        "coordinates": [
          -89.1,
          34.7667
        ]
      },
      "type": "Feature",
      "properties": {
        "hierarchy": [
          "tgn:2272452",
          "tgn:2001090",
          "tgn:1000001",
          "tgn:7012149",
          "tgn:7007522",
          "tgn:7029392"
        ],
        "placetype": [
          "aat:300006191"
        ],
        "id": 2272452,
        "name:xx": "Curtis Lake"
      }
    },
    {
      "geometry": {
        "type": "Point",
        "coordinates": [
          -74.95,
          43.3333
        ]
      },
      "type": "Feature",
      "properties": {
        "hierarchy": [
          "tgn:2272453",
          "tgn:1000001",
          "tgn:7012149",
          "tgn:1002472",
          "tgn:7007568",
          "tgn:7029392"
        ],
        "placetype": [
          "aat:300008680"
        ],
        "id": 2272453,
        "name:xx": "Curtis Lake"
      }
    },
    {
      "geometry": {
        "type": "Point",
        "coordinates": [
          -117.2833,
          45.0667
        ]
      },
      "type": "Feature",
      "properties": {
        "hierarchy": [
          "tgn:2272454",
          "tgn:7013349",
          "tgn:1000001",
          "tgn:7012149",
          "tgn:7007708",
          "tgn:7029392"
        ],
        "placetype": [
          "aat:300008680"
        ],
        "id": 2272454,
        "name:xx": "Curtis Lake"
      }
    },
    {
      "geometry": {
        "type": "Point",
        "coordinates": [
          -74.7833,
          40.1833
        ]
      },
      "type": "Feature",
      "properties": {
        "hierarchy": [
          "tgn:2272455",
          "tgn:1000001",
          "tgn:1002213",
          "tgn:7012149",
          "tgn:7007710",
          "tgn:7029392"
        ],
        "placetype": [
          "aat:300008680"
        ],
        "id": 2272455,
        "name:xx": "Curtis Lake"
      }
    },
    {
      "geometry": {
        "type": "Point",
        "coordinates": [
          -122.7333,
          45.7167
        ]
      },
      "type": "Feature",
      "properties": {
        "hierarchy": [
          "tgn:2272456",
          "tgn:1000001",
          "tgn:1002275",
          "tgn:7012149",
          "tgn:7007920",
          "tgn:7029392"
        ],
        "placetype": [
          "aat:300008680"
        ],
        "id": 2272456,
        "name:xx": "Curtis Lake"
      }
    },
    {
      "geometry": {
        "type": "Point",
        "coordinates": [
          -122.05,
          46.2667
        ]
      },
      "type": "Feature",
      "properties": {
        "hierarchy": [
          "tgn:2272457",
          "tgn:1000001",
          "tgn:7012149",
          "tgn:1002897",
          "tgn:7007920",
          "tgn:7029392"
        ],
        "placetype": [
          "aat:300008680"
        ],
        "id": 2272457,
        "name:xx": "Curtis Lake"
      }
    },
    {
      "geometry": {
        "type": "Point",
        "coordinates": [
          -89.4167,
          44
        ]
      },
      "type": "Feature",
      "properties": {
        "hierarchy": [
          "tgn:2272458",
          "tgn:1000001",
          "tgn:7012149",
          "tgn:2002362",
          "tgn:7007922",
          "tgn:7029392"
        ],
        "placetype": [
          "aat:300008680"
        ],
        "id": 2272458,
        "name:xx": "Curtis Lake"
      }
    },
    {
      "geometry": {
        "type": "Point",
        "coordinates": [
          -89.7667,
          45.8833
        ]
      },
      "type": "Feature",
      "properties": {
        "hierarchy": [
          "tgn:2272459",
          "tgn:1000001",
          "tgn:7012149",
          "tgn:2002342",
          "tgn:7007922",
          "tgn:7029392"
        ],
        "placetype": [
          "aat:300008680"
        ],
        "id": 2272459,
        "name:xx": "Curtis Lake"
      }
    }
  ]
}
