{
  "geometry": {
    "type": "Point",
    "coordinates": [
      30.733333,
      29.15
    ]
  },
  "type": "Feature",
  "properties": {
    "hierarchy": [
      "tgn:7535097",
      "tgn:7001242",
      "tgn:7001105",
      "tgn:7016833",
      "tgn:7029392"
    ],
    "placetype": [
      "aat:300008057"
    ],
    "name:en": "Āthār Kawm Dānyāl",
    "id": 7535097
  }
}
