{
  "geometry": {
    "type": "Point",
    "coordinates": [
      75.245,
      13.688
    ]
  },
  "type": "Feature",
  "properties": {
    "hierarchy": [
      "tgn:1077111",
      "tgn:1000004",
      "tgn:7000198",
      "tgn:1001882",
      "tgn:7029392"
    ],
    "placetype": [
      "aat:300008347"
    ],
    "name:en": "Tīrthahalli",
    "id": 1077111
  }
}
