{
  "geometry": {
    "type": "Point",
    "coordinates": [
      -92.9833,
      35.4667
    ]
  },
  "type": "Feature",
  "properties": {
    "hierarchy": [
      "tgn:2185625",
      "tgn:1000001",
      "tgn:7016172",
      "tgn:7012149",
      "tgn:2000162",
      "tgn:7029392"
    ],
    "placetype": [
      "aat:300008347"
    ],
    "id": 2185625,
    "name:xx": "Boiling Springs"
  }
}
