{
  "geometry": {
    "type": "Point",
    "coordinates": [
      -75.15,
      41.2333
    ]
  },
  "type": "Feature",
  "properties": {
    "hierarchy": [
      "tgn:2567331",
      "tgn:1000001",
      "tgn:7012149",
      "tgn:1002682",
      "tgn:7007710",
      "tgn:7029392"
    ],
    "placetype": [
      "aat:300008905"
    ],
    "id": 2567331,
    "name:xx": "Panther Swamp"
  }
}
