{
  "geometry": {
    "type": "Point",
    "coordinates": [
      -75.7167,
      38.7667
    ]
  },
  "type": "Feature",
  "properties": {
    "hierarchy": [
      "tgn:7020716",
      "tgn:1002234",
      "tgn:1000001",
      "tgn:7012149",
      "tgn:7007516",
      "tgn:7029392"
    ],
    "placetype": [
      "aat:300006191"
    ],
    "id": 7020716,
    "name:xx": "Smithville Lake"
  }
}
