{
  "geometry": {
    "type": "Point",
    "coordinates": [
      -75.1333,
      9.7167
    ]
  },
  "type": "Feature",
  "properties": {
    "hierarchy": [
      "tgn:1023792",
      "tgn:1000529",
      "tgn:1000050",
      "tgn:1000002",
      "tgn:7029392"
    ],
    "placetype": [
      "aat:300008347"
    ],
    "id": 1023792,
    "name:xx": "El Carmen de Bolívar"
  }
}
