{
  "geometry": {
    "type": "Point",
    "coordinates": [
      -74.7833,
      43.7667
    ]
  },
  "type": "Feature",
  "properties": {
    "hierarchy": [
      "tgn:2626671",
      "tgn:1000001",
      "tgn:7012149",
      "tgn:1002440",
      "tgn:7007568",
      "tgn:7029392"
    ],
    "placetype": [
      "aat:300008798"
    ],
    "id": 2626671,
    "name:xx": "Rocky Mountain"
  }
}
