{
  "geometry": {
    "type": "Point",
    "coordinates": [
      -99.6833,
      27.6833
    ]
  },
  "type": "Feature",
  "properties": {
    "hierarchy": [
      "tgn:2607034",
      "tgn:1000001",
      "tgn:7012149",
      "tgn:2002090",
      "tgn:7007826",
      "tgn:7029392"
    ],
    "placetype": [
      "aat:300006191"
    ],
    "id": 2607034,
    "name:xx": "Ranchita Tank"
  }
}
