{
  "type": "FeatureCollection",
  "features": [
    {
      "geometry": {
        "type": "Point",
        "coordinates": [
          -82.7667,
          35.3667
        ]
      },
      "type": "Feature",
      "properties": {
        "hierarchy": [
          "tgn:2148770",
          "tgn:1000001",
          "tgn:7012149",
          "tgn:2001544",
          "tgn:7007709",
          "tgn:7029392"
        ],
        "placetype": [
          "aat:300008699"
        ],
        "id": 2148770,
        "name:xx": "Barnett Branch"
      }
    },
    {
      "geometry": {
        "type": "Point",
        "coordinates": [
          -82.4167,
          36.0333
        ]
      },
      "type": "Feature",
      "properties": {
        "hierarchy": [
          "tgn:2148771",
          "tgn:1000001",
          "tgn:7012149",
          "tgn:7029392"
        ],
        "placetype": [
          "aat:300008699"
        ],
        "id": 2148771,
        "name:xx": "Barnett Branch"
      }
    },
    {
      "geometry": {
        "type": "Point",
        "coordinates": [
          -87.5667,
          35.3167
        ]
      },
      "type": "Feature",
      "properties": {
        "hierarchy": [
          "tgn:2148772",
          "tgn:1000001",
          "tgn:7012149",
          "tgn:2001927",
          "tgn:7007825",
          "tgn:7029392"
        ],
        "placetype": [
          "aat:300008699"
        ],
        "id": 2148772,
        "name:xx": "Barnett Branch"
      }
    },
    {
      "geometry": {
        "type": "Point",
        "coordinates": [
          -88.8833,
          35.8667
        ]
      },
      "type": "Feature",
      "properties": {
        "hierarchy": [
          "tgn:2148773",
          "tgn:1000001",
          "tgn:7012149",
          "tgn:2001863",
          "tgn:7007825",
          "tgn:7029392"
        ],
        "placetype": [
          "aat:300008699"
        ],
        "id": 2148773,
        "name:xx": "Barnett Branch"
      }
    },
    {
      "geometry": {
        "type": "Point",
        "coordinates": [
          -99.2,
          30.1667
        ]
      },
      "type": "Feature",
      "properties": {
        "hierarchy": [
          "tgn:2148774",
          "tgn:1000001",
          "tgn:7012149",
          "tgn:2001990",
          "tgn:7007826",
          "tgn:7029392"
        ],
        "placetype": [
          "aat:300008699"
        ],
        "id": 2148774,
        "name:xx": "Barnett Branch"
      }
    },
    {
      "geometry": {
        "type": "Point",
        "coordinates": [
          -98.5833,
          30.5833
        ]
      },
      "type": "Feature",
      "properties": {
        "hierarchy": [
          "tgn:2148775",
          "tgn:1000001",
          "tgn:7012149",
          "tgn:2002030",
          "tgn:7007826",
          "tgn:7029392"
        ],
        "placetype": [
          "aat:300008699"
        ],
        "id": 2148775,
        "name:xx": "Barnett Branch"
      }
    },
    {
      "geometry": {
        "type": "Point",
        "coordinates": [
          -82.0333,
          38.5833
        ]
      },
      "type": "Feature",
      "properties": {
        "hierarchy": [
          "tgn:2148776",
          "tgn:1000001",
          "tgn:7012149",
          "tgn:2002289",
          "tgn:7013961",
          "tgn:7029392"
        ],
        "placetype": [
          "aat:300008699"
        ],
        "id": 2148776,
        "name:xx": "Barnett Branch"
      }
    },
    {
      "geometry": {
        "type": "Point",
        "coordinates": [
          -92.3,
          38.05
        ]
      },
      "type": "Feature",
      "properties": {
        "hierarchy": [
          "tgn:2148777",
          "tgn:1000001",
          "tgn:7012149",
          "tgn:1002671",
          "tgn:7007523",
          "tgn:7029392"
        ],
        "placetype": [
          "aat:300008746"
        ],
        "id": 2148777,
        "name:xx": "Barnett Cave"
      }
    },
    {
      "geometry": {
        "type": "Point",
        "coordinates": [
          -80,
          38.2833
        ]
      },
      "type": "Feature",
      "properties": {
        "hierarchy": [
          "tgn:2148778",
          "tgn:1000001",
          "tgn:7012149",
          "tgn:2002287",
          "tgn:7013961",
          "tgn:7029392"
        ],
        "placetype": [
          "aat:300008746"
        ],
        "id": 2148778,
        "name:xx": "Barnett Caves"
      }
    },
    {
      "geometry": {
        "type": "Point",
        "coordinates": [
          -91.5833,
          35.9333
        ]
      },
      "type": "Feature",
      "properties": {
        "hierarchy": [
          "tgn:2148779",
          "tgn:1000001",
          "tgn:7016172",
          "tgn:7012149",
          "tgn:7029392"
        ],
        "placetype": [
          "aat:300008706"
        ],
        "id": 2148779,
        "name:xx": "Barnett Creek"
      }
    }
  ]
}
