{
  "geometry": {
    "type": "Point",
    "coordinates": [
      -107.7167,
      32.9167
    ]
  },
  "type": "Feature",
  "properties": {
    "hierarchy": [
      "tgn:2739050",
      "tgn:1000001",
      "tgn:7012149",
      "tgn:2001455",
      "tgn:7007566",
      "tgn:7029392"
    ],
    "placetype": [
      "aat:300000390"
    ],
    "id": 2739050,
    "name:xx": "United States and Illinois"
  }
}
