{
  "geometry": {
    "type": "Point",
    "coordinates": [
      79.9786,
      27.1675
    ]
  },
  "type": "Feature",
  "properties": {
    "hierarchy": [
      "tgn:7562034",
      "tgn:1000004",
      "tgn:7000198",
      "tgn:7016722",
      "tgn:7029392"
    ],
    "placetype": [
      "aat:300008347"
    ],
    "name:en": "Birni",
    "id": 7562034
  }
}
