{
  "type": "FeatureCollection",
  "features": [
    {
      "geometry": {
        "type": "Point",
        "coordinates": [
          -101,
          29.016667
        ]
      },
      "type": "Feature",
      "properties": {
        "hierarchy": [
          "tgn:7367380",
          "tgn:1001853",
          "tgn:1000001",
          "tgn:7005560",
          "tgn:7029392"
        ],
        "placetype": [
          "aat:300008347"
        ],
        "id": 7367380,
        "name:xx": "El Tule"
      }
    },
    {
      "geometry": {
        "type": "Point",
        "coordinates": [
          -106.166667,
          27.316667
        ]
      },
      "type": "Feature",
      "properties": {
        "hierarchy": [
          "tgn:7367381",
          "tgn:7005581",
          "tgn:1000001",
          "tgn:7005560",
          "tgn:7029392"
        ],
        "placetype": [
          "aat:300008347"
        ],
        "id": 7367381,
        "name:xx": "El Tule"
      }
    },
    {
      "geometry": {
        "type": "Point",
        "coordinates": [
          -106.266667,
          27.05
        ]
      },
      "type": "Feature",
      "properties": {
        "hierarchy": [
          "tgn:7367382",
          "tgn:7005581",
          "tgn:1000001",
          "tgn:7005560",
          "tgn:7029392"
        ],
        "placetype": [
          "aat:300008347"
        ],
        "id": 7367382,
        "name:xx": "El Tule"
      }
    },
    {
      "geometry": {
        "type": "Point",
        "coordinates": [
          -105.666667,
          26.133333
        ]
      },
      "type": "Feature",
      "properties": {
        "hierarchy": [
          "tgn:7367383",
          "tgn:7005583",
          "tgn:1000001",
          "tgn:7005560",
          "tgn:7029392"
        ],
        "placetype": [
          "aat:300008347"
        ],
        "id": 7367383,
        "name:xx": "El Tule"
      }
    },
    {
      "geometry": {
        "type": "Point",
        "coordinates": [
          -106.966667,
          26.016667
        ]
      },
      "type": "Feature",
      "properties": {
        "hierarchy": [
          "tgn:7367384",
          "tgn:7005581",
          "tgn:1000001",
          "tgn:7005560",
          "tgn:7029392"
        ],
        "placetype": [
          "aat:300008347"
        ],
        "id": 7367384,
        "name:xx": "El Tule"
      }
    },
    {
      "geometry": {
        "type": "Point",
        "coordinates": [
          -97.333333,
          25.9
        ]
      },
      "type": "Feature",
      "properties": {
        "hierarchy": [
          "tgn:7367385",
          "tgn:1000001",
          "tgn:7005597",
          "tgn:7005560",
          "tgn:7029392"
        ],
        "placetype": [
          "aat:300008347"
        ],
        "id": 7367385,
        "name:xx": "El Tule"
      }
    },
    {
      "geometry": {
        "type": "Point",
        "coordinates": [
          -109.216667,
          25.833333
        ]
      },
      "type": "Feature",
      "properties": {
        "hierarchy": [
          "tgn:7367386",
          "tgn:1000001",
          "tgn:7005595",
          "tgn:7005560",
          "tgn:7029392"
        ],
        "placetype": [
          "aat:300008347"
        ],
        "id": 7367386,
        "name:xx": "El Tule"
      }
    },
    {
      "geometry": {
        "type": "Point",
        "coordinates": [
          -98.05,
          25.733333
        ]
      },
      "type": "Feature",
      "properties": {
        "hierarchy": [
          "tgn:7367387",
          "tgn:1000001",
          "tgn:7005597",
          "tgn:7005560",
          "tgn:7029392"
        ],
        "placetype": [
          "aat:300008347"
        ],
        "id": 7367387,
        "name:xx": "El Tule"
      }
    },
    {
      "geometry": {
        "type": "Point",
        "coordinates": [
          -106.733333,
          25.833333
        ]
      },
      "type": "Feature",
      "properties": {
        "hierarchy": [
          "tgn:7367388",
          "tgn:7005581",
          "tgn:1000001",
          "tgn:7005560",
          "tgn:7029392"
        ],
        "placetype": [
          "aat:300008347"
        ],
        "id": 7367388,
        "name:xx": "El Porvenir"
      }
    },
    {
      "geometry": {
        "type": "Point",
        "coordinates": [
          -99.7,
          25.05
        ]
      },
      "type": "Feature",
      "properties": {
        "hierarchy": [
          "tgn:7367389",
          "tgn:1000001",
          "tgn:7005589",
          "tgn:7005560",
          "tgn:7029392"
        ],
        "placetype": [
          "aat:300008347"
        ],
        "id": 7367389,
        "name:xx": "El Porvenir"
      }
    }
  ]
}
