{
  "geometry": {
    "type": "Point",
    "coordinates": [
      -63.75,
      -21.6667
    ]
  },
  "type": "Feature",
  "properties": {
    "hierarchy": [
      "tgn:1020420",
      "tgn:1000776",
      "tgn:1000046",
      "tgn:1000002",
      "tgn:7029392"
    ],
    "placetype": [
      "aat:300008347"
    ],
    "id": 1020420,
    "name:xx": "Sanandita"
  }
}
