{
  "geometry": {
    "type": "Point",
    "coordinates": [
      -107.65,
      45.0167
    ]
  },
  "type": "Feature",
  "properties": {
    "hierarchy": [
      "tgn:2372279",
      "tgn:1000001",
      "tgn:7012149",
      "tgn:7029392"
    ],
    "placetype": [
      "aat:300008761"
    ],
    "id": 2372279,
    "name:xx": "Halfway Canyon"
  }
}
