{
  "geometry": {
    "type": "Point",
    "coordinates": [
      -135.3167,
      57.0333
    ]
  },
  "type": "Feature",
  "properties": {
    "hierarchy": [
      "tgn:2443069",
      "tgn:7006450",
      "tgn:1000001",
      "tgn:7012149",
      "tgn:2124002",
      "tgn:7029392"
    ],
    "placetype": [
      "aat:300008791"
    ],
    "id": 2443069,
    "name:xx": "Kutkan Island"
  }
}
