{
  "geometry": {
    "type": "Point",
    "coordinates": [
      -93.25,
      35.8667
    ]
  },
  "type": "Feature",
  "properties": {
    "hierarchy": [
      "tgn:2773424",
      "tgn:1000001",
      "tgn:7016172",
      "tgn:7012149",
      "tgn:2000155",
      "tgn:7029392"
    ],
    "placetype": [
      "aat:300008699"
    ],
    "id": 2773424,
    "name:xx": "Willis Branch"
  }
}
