{
  "geometry": {
    "type": "Point",
    "coordinates": [
      -121.1833,
      45.2333
    ]
  },
  "type": "Feature",
  "properties": {
    "hierarchy": [
      "tgn:2737551",
      "tgn:1000001",
      "tgn:7012149",
      "tgn:1002990",
      "tgn:7007708",
      "tgn:7029392"
    ],
    "placetype": [
      "aat:300006191"
    ],
    "id": 2737551,
    "name:xx": "Tygh Valley Storage Pond"
  }
}
