{
  "geometry": {
    "type": "Point",
    "coordinates": [
      -123.7167,
      44.3667
    ]
  },
  "type": "Feature",
  "properties": {
    "hierarchy": [
      "tgn:2454627",
      "tgn:1000001",
      "tgn:7012149",
      "tgn:7007708",
      "tgn:7029392"
    ],
    "placetype": [
      "aat:300008798"
    ],
    "id": 2454627,
    "name:xx": "Little Digger Mountain"
  }
}
