{
  "geometry": {
    "type": "Point",
    "coordinates": [
      -105.8667,
      43.2167
    ]
  },
  "type": "Feature",
  "properties": {
    "hierarchy": [
      "tgn:2545349",
      "tgn:1000001",
      "tgn:2002369",
      "tgn:7012149",
      "tgn:7007923",
      "tgn:7029392"
    ],
    "placetype": [
      "aat:300008706"
    ],
    "id": 2545349,
    "name:xx": "North Fork Bear Creek"
  }
}
