{
  "type": "FeatureCollection",
  "features": [
    {
      "geometry": {
        "type": "Point",
        "coordinates": [
          -85.6667,
          46.65
        ]
      },
      "type": "Feature",
      "properties": {
        "hierarchy": [
          "tgn:2729950",
          "tgn:1000001",
          "tgn:7012149",
          "tgn:2000972",
          "tgn:7007520",
          "tgn:7029392"
        ],
        "placetype": [
          "aat:300008706"
        ],
        "id": 2729950,
        "name:xx": "Trout Creek"
      }
    },
    {
      "geometry": {
        "type": "Point",
        "coordinates": [
          -89.0333,
          46.3833
        ]
      },
      "type": "Feature",
      "properties": {
        "hierarchy": [
          "tgn:2729951",
          "tgn:1000001",
          "tgn:7012149",
          "tgn:7007520",
          "tgn:7029392"
        ],
        "placetype": [
          "aat:300008706"
        ],
        "id": 2729951,
        "name:xx": "Trout Creek"
      }
    },
    {
      "geometry": {
        "type": "Point",
        "coordinates": [
          -83.2667,
          42.7167
        ]
      },
      "type": "Feature",
      "properties": {
        "hierarchy": [
          "tgn:2729952",
          "tgn:1000001",
          "tgn:7012149",
          "tgn:1002737",
          "tgn:7007520",
          "tgn:7029392"
        ],
        "placetype": [
          "aat:300008706"
        ],
        "id": 2729952,
        "name:xx": "Trout Creek"
      }
    },
    {
      "geometry": {
        "type": "Point",
        "coordinates": [
          -91.9167,
          44.1167
        ]
      },
      "type": "Feature",
      "properties": {
        "hierarchy": [
          "tgn:2729953",
          "tgn:1000001",
          "tgn:7012149",
          "tgn:7007521",
          "tgn:7029392"
        ],
        "placetype": [
          "aat:300008706"
        ],
        "id": 2729953,
        "name:xx": "Trout Creek"
      }
    },
    {
      "geometry": {
        "type": "Point",
        "coordinates": [
          -94.8667,
          45.8667
        ]
      },
      "type": "Feature",
      "properties": {
        "hierarchy": [
          "tgn:2729954",
          "tgn:1000001",
          "tgn:7012149",
          "tgn:2001075",
          "tgn:7007521",
          "tgn:7029392"
        ],
        "placetype": [
          "aat:300008706"
        ],
        "id": 2729954,
        "name:xx": "Trout Creek"
      }
    },
    {
      "geometry": {
        "type": "Point",
        "coordinates": [
          -93.3833,
          47.25
        ]
      },
      "type": "Feature",
      "properties": {
        "hierarchy": [
          "tgn:2729955",
          "tgn:1000001",
          "tgn:7012149",
          "tgn:2001029",
          "tgn:7007521",
          "tgn:7029392"
        ],
        "placetype": [
          "aat:300008706"
        ],
        "id": 2729955,
        "name:xx": "Trout Creek"
      }
    },
    {
      "geometry": {
        "type": "Point",
        "coordinates": [
          -111.8833,
          47.25
        ]
      },
      "type": "Feature",
      "properties": {
        "hierarchy": [
          "tgn:2729956",
          "tgn:1000001",
          "tgn:2001266",
          "tgn:7012149",
          "tgn:7007524",
          "tgn:7029392"
        ],
        "placetype": [
          "aat:300008706"
        ],
        "id": 2729956,
        "name:xx": "Trout Creek"
      }
    },
    {
      "geometry": {
        "type": "Point",
        "coordinates": [
          -111.5,
          44.85
        ]
      },
      "type": "Feature",
      "properties": {
        "hierarchy": [
          "tgn:2729957",
          "tgn:1000001",
          "tgn:7012149",
          "tgn:2001288",
          "tgn:7007524",
          "tgn:7029392"
        ],
        "placetype": [
          "aat:300008706"
        ],
        "id": 2729957,
        "name:xx": "Trout Creek"
      }
    },
    {
      "geometry": {
        "type": "Point",
        "coordinates": [
          -112.8667,
          45.3667
        ]
      },
      "type": "Feature",
      "properties": {
        "hierarchy": [
          "tgn:2729958",
          "tgn:1000001",
          "tgn:2001260",
          "tgn:7012149",
          "tgn:7007524",
          "tgn:7029392"
        ],
        "placetype": [
          "aat:300008706"
        ],
        "id": 2729958,
        "name:xx": "Trout Creek"
      }
    },
    {
      "geometry": {
        "type": "Point",
        "coordinates": [
          -113.3,
          45.9833
        ]
      },
      "type": "Feature",
      "properties": {
        "hierarchy": [
          "tgn:2729959",
          "tgn:1000001",
          "tgn:7012149",
          "tgn:7020792",
          "tgn:7007524",
          "tgn:7029392"
        ],
        "placetype": [
          "aat:300008706"
        ],
        "id": 2729959,
        "name:xx": "Trout Creek"
      }
    }
  ]
}
