{
  "geometry": {
    "type": "Point",
    "coordinates": [
      79.497859,
      26.0483
    ]
  },
  "type": "Feature",
  "properties": {
    "hierarchy": [
      "tgn:7566118",
      "tgn:1000004",
      "tgn:7000198",
      "tgn:7016722",
      "tgn:7029392"
    ],
    "placetype": [
      "aat:300008347"
    ],
    "name:en": "Jalālpur Chirgawān",
    "id": 7566118
  }
}
