{
  "type": "FeatureCollection",
  "features": [
    {
      "geometry": {
        "type": "Point",
        "coordinates": [
          -13.666667,
          29.1
        ]
      },
      "type": "Feature",
      "properties": {
        "hierarchy": [
          "tgn:7307440",
          "tgn:7002825",
          "tgn:7016622",
          "tgn:1000003",
          "tgn:1000095",
          "tgn:7029392"
        ],
        "placetype": [
          "aat:300386846"
        ],
        "id": 7307440,
        "name:xx": "Los Lajares"
      }
    },
    {
      "geometry": {
        "type": "Point",
        "coordinates": [
          -5.766667,
          37.783333
        ]
      },
      "type": "Feature",
      "properties": {
        "hierarchy": [
          "tgn:7307441",
          "tgn:7002758",
          "tgn:7002841",
          "tgn:1000003",
          "tgn:1000095",
          "tgn:7029392"
        ],
        "placetype": [
          "aat:300007783"
        ],
        "id": 7307441,
        "name:xx": "Apartadero de Los Labrados"
      }
    },
    {
      "geometry": {
        "type": "Point",
        "coordinates": [
          -16.333333,
          28.4
        ]
      },
      "type": "Feature",
      "properties": {
        "hierarchy": [
          "tgn:7307443",
          "tgn:7002836",
          "tgn:7016622",
          "tgn:1000003",
          "tgn:1000095",
          "tgn:7029392"
        ],
        "placetype": [
          "aat:300266554",
          "aat:300008699"
        ],
        "id": 7307443,
        "name:xx": "Los Juncos, Barranco"
      }
    },
    {
      "geometry": {
        "type": "Point",
        "coordinates": [
          -16.333333,
          28.4
        ]
      },
      "type": "Feature",
      "properties": {
        "hierarchy": [
          "tgn:7307444",
          "tgn:7002836",
          "tgn:7016622",
          "tgn:1000003",
          "tgn:1000095",
          "tgn:7029392"
        ],
        "placetype": [
          "aat:300008347"
        ],
        "id": 7307444,
        "name:xx": "Los Juncos"
      }
    },
    {
      "geometry": {
        "type": "Point",
        "coordinates": [
          -1.8,
          37.75
        ]
      },
      "type": "Feature",
      "properties": {
        "hierarchy": [
          "tgn:7307445",
          "tgn:1001439",
          "tgn:1000003",
          "tgn:7002797",
          "tgn:1000095",
          "tgn:7029392"
        ],
        "placetype": [
          "aat:300008347"
        ],
        "id": 7307445,
        "name:xx": "Los Juanetes"
      }
    },
    {
      "geometry": {
        "type": "Point",
        "coordinates": [
          -1.683333,
          37.55
        ]
      },
      "type": "Feature",
      "properties": {
        "hierarchy": [
          "tgn:7307446",
          "tgn:1001439",
          "tgn:1000003",
          "tgn:7002797",
          "tgn:1000095",
          "tgn:7029392"
        ],
        "placetype": [
          "aat:300008347"
        ],
        "id": 7307446,
        "name:xx": "Los Jopos"
      }
    },
    {
      "geometry": {
        "type": "Point",
        "coordinates": [
          -2.133333,
          37.216667
        ]
      },
      "type": "Feature",
      "properties": {
        "hierarchy": [
          "tgn:7307447",
          "tgn:7002805",
          "tgn:7002758",
          "tgn:1000003",
          "tgn:1000095",
          "tgn:7029392"
        ],
        "placetype": [
          "aat:300008347"
        ],
        "id": 7307447,
        "name:xx": "Los Jarales"
      }
    },
    {
      "geometry": {
        "type": "Point",
        "coordinates": [
          -13.9,
          28.666667
        ]
      },
      "type": "Feature",
      "properties": {
        "hierarchy": [
          "tgn:7307448",
          "tgn:7002825",
          "tgn:7016622",
          "tgn:1000003",
          "tgn:1000095",
          "tgn:7029392"
        ],
        "placetype": [
          "aat:300008750"
        ],
        "id": 7307448,
        "name:xx": "Los Jablitos"
      }
    },
    {
      "geometry": {
        "type": "Point",
        "coordinates": [
          -5.616667,
          36.916667
        ]
      },
      "type": "Feature",
      "properties": {
        "hierarchy": [
          "tgn:7307449",
          "tgn:7002813",
          "tgn:7002758",
          "tgn:1000003",
          "tgn:1000095",
          "tgn:7029392"
        ],
        "placetype": [
          "aat:300008347"
        ],
        "id": 7307449,
        "name:xx": "Los Izquierdos"
      }
    }
  ]
}
