{
  "geometry": {
    "type": "Point",
    "coordinates": [
      84.184022,
      25.470139
    ]
  },
  "type": "Feature",
  "properties": {
    "hierarchy": [
      "tgn:7574704",
      "tgn:1000004",
      "tgn:1001842",
      "tgn:7000198",
      "tgn:7029392"
    ],
    "placetype": [
      "aat:300008347"
    ],
    "name:en": "Kurān Sarāi",
    "id": 7574704
  }
}
