{
  "geometry": {
    "type": "Point",
    "coordinates": [
      -92.7333,
      36.65
    ]
  },
  "type": "Feature",
  "properties": {
    "hierarchy": [
      "tgn:2306152",
      "tgn:1000001",
      "tgn:7012149",
      "tgn:7007523",
      "tgn:7029392"
    ],
    "placetype": [
      "aat:300008706"
    ],
    "id": 2306152,
    "name:xx": "East Fork Big Creek"
  }
}
