{
  "type": "FeatureCollection",
  "features": [
    {
      "geometry": {
        "type": "Point",
        "coordinates": [
          -111.7,
          28.866667
        ]
      },
      "type": "Feature",
      "properties": {
        "hierarchy": [
          "tgn:7384740",
          "tgn:1000001",
          "tgn:1001960",
          "tgn:7005560",
          "tgn:7029392"
        ],
        "placetype": [
          "aat:300008347"
        ],
        "id": 7384740,
        "name:xx": "Navolatos"
      }
    },
    {
      "geometry": {
        "type": "Point",
        "coordinates": [
          -109.566667,
          27.033333
        ]
      },
      "type": "Feature",
      "properties": {
        "hierarchy": [
          "tgn:7384741",
          "tgn:1000001",
          "tgn:1001960",
          "tgn:7005560",
          "tgn:7029392"
        ],
        "placetype": [
          "aat:300008347"
        ],
        "id": 7384741,
        "name:xx": "Navolato"
      }
    },
    {
      "geometry": {
        "type": "Point",
        "coordinates": [
          -109.633333,
          26.85
        ]
      },
      "type": "Feature",
      "properties": {
        "hierarchy": [
          "tgn:7384743",
          "tgn:1000001",
          "tgn:1001960",
          "tgn:7005560",
          "tgn:7029392"
        ],
        "placetype": [
          "aat:300006075"
        ],
        "id": 7384743,
        "name:xx": "Canal de Navojoa"
      }
    },
    {
      "geometry": {
        "type": "Point",
        "coordinates": [
          -108.6,
          25.816667
        ]
      },
      "type": "Feature",
      "properties": {
        "hierarchy": [
          "tgn:7384745",
          "tgn:1000001",
          "tgn:7005595",
          "tgn:7005560",
          "tgn:7029392"
        ],
        "placetype": [
          "aat:300000241"
        ],
        "id": 7384745,
        "name:xx": "Rancho Navobampo"
      }
    },
    {
      "geometry": {
        "type": "Point",
        "coordinates": [
          -107.341111,
          24.342778
        ]
      },
      "type": "Feature",
      "properties": {
        "hierarchy": [
          "tgn:7384746",
          "tgn:1000001",
          "tgn:7005595",
          "tgn:7005560",
          "tgn:7029392"
        ],
        "placetype": [
          "aat:300008347"
        ],
        "id": 7384746,
        "name:xx": "Navito"
      }
    },
    {
      "geometry": {
        "type": "Point",
        "coordinates": [
          -105.066667,
          23.9
        ]
      },
      "type": "Feature",
      "properties": {
        "hierarchy": [
          "tgn:7384748",
          "tgn:7005583",
          "tgn:1000001",
          "tgn:7005560",
          "tgn:7029392"
        ],
        "placetype": [
          "aat:300008347"
        ],
        "id": 7384748,
        "name:xx": "Navíos"
      }
    },
    {
      "geometry": {
        "type": "Point",
        "coordinates": [
          -113.566667,
          29.566667
        ]
      },
      "type": "Feature",
      "properties": {
        "hierarchy": [
          "tgn:7384749",
          "tgn:1001835",
          "tgn:1000001",
          "tgn:7005560",
          "tgn:7029392"
        ],
        "placetype": [
          "aat:300008791"
        ],
        "id": 7384749,
        "name:xx": "Vela, Isla de la"
      }
    }
  ]
}
