{
  "geometry": {
    "type": "Point",
    "coordinates": [
      -116.05,
      42.0833
    ]
  },
  "type": "Feature",
  "properties": {
    "hierarchy": [
      "tgn:2719547",
      "tgn:1000001",
      "tgn:7012149",
      "tgn:2000488",
      "tgn:7007250",
      "tgn:7029392"
    ],
    "placetype": [
      "aat:300008697"
    ],
    "id": 2719547,
    "name:xx": "Three Forks Summit Springs"
  }
}
