{
  "geometry": {
    "type": "Point",
    "coordinates": [
      -112.3167,
      34.15
    ]
  },
  "type": "Feature",
  "properties": {
    "hierarchy": [
      "tgn:2406037",
      "tgn:1000001",
      "tgn:7006451",
      "tgn:7012149",
      "tgn:2000103",
      "tgn:7029392"
    ],
    "placetype": [
      "aat:300008706"
    ],
    "id": 2406037,
    "name:xx": "Humbug Creek"
  }
}
