{
  "type": "FeatureCollection",
  "features": [
    {
      "geometry": {
        "type": "Point",
        "coordinates": [
          -70.25,
          -12
        ]
      },
      "type": "Feature",
      "properties": {
        "hierarchy": [
          "tgn:1000680",
          "tgn:1000002",
          "tgn:1000056",
          "tgn:7029392"
        ],
        "placetype": [
          "aat:300387064",
          "aat:300000772",
          "aat:300236112"
        ],
        "id": 1000680,
        "name:xx": "Madre de Dios"
      }
    },
    {
      "geometry": {
        "type": "Point",
        "coordinates": [
          -86.4167,
          13.5
        ]
      },
      "type": "Feature",
      "properties": {
        "hierarchy": [
          "tgn:1000681",
          "tgn:1000001",
          "tgn:7005562",
          "tgn:7029392"
        ],
        "placetype": [
          "aat:300387064",
          "aat:300000772"
        ],
        "id": 1000681,
        "name:xx": "Madriz"
      }
    },
    {
      "geometry": {
        "type": "Point",
        "coordinates": [
          -74.5,
          10
        ]
      },
      "type": "Feature",
      "properties": {
        "hierarchy": [
          "tgn:1000682",
          "tgn:1000050",
          "tgn:1000002",
          "tgn:7029392"
        ],
        "placetype": [
          "aat:300387064",
          "aat:300000772"
        ],
        "id": 1000682,
        "name:xx": "Magdalena"
      }
    },
    {
      "geometry": {
        "type": "Point",
        "coordinates": [
          -7.4167,
          7.3333
        ]
      },
      "type": "Feature",
      "properties": {
        "hierarchy": [
          "tgn:1000684",
          "tgn:7001242",
          "tgn:1000168",
          "tgn:7029392"
        ],
        "placetype": [
          "aat:300387064",
          "aat:300000772"
        ],
        "id": 1000684,
        "name:xx": "Man, Département de"
      }
    },
    {
      "geometry": {
        "type": "Point",
        "coordinates": [
          -86.4167,
          12
        ]
      },
      "type": "Feature",
      "properties": {
        "hierarchy": [
          "tgn:1000685",
          "tgn:1000001",
          "tgn:7005562",
          "tgn:7029392"
        ],
        "placetype": [
          "aat:300387064",
          "aat:300000772"
        ],
        "id": 1000685,
        "name:xx": "Managua"
      }
    },
    {
      "geometry": {
        "type": "Point",
        "coordinates": [
          -6,
          8.3333
        ]
      },
      "type": "Feature",
      "properties": {
        "hierarchy": [
          "tgn:1000687",
          "tgn:7001242",
          "tgn:1000168",
          "tgn:7029392"
        ],
        "placetype": [
          "aat:300387064",
          "aat:300000772"
        ],
        "id": 1000687,
        "name:xx": "Mankono, Département de"
      }
    },
    {
      "geometry": {
        "type": "Point",
        "coordinates": [
          7,
          14
        ]
      },
      "type": "Feature",
      "properties": {
        "hierarchy": [
          "tgn:1000688",
          "tgn:7001242",
          "tgn:1000181",
          "tgn:7029392"
        ],
        "placetype": [
          "aat:300387064",
          "aat:300000772"
        ],
        "id": 1000688,
        "name:xx": "Maradi"
      }
    }
  ]
}
