{
  "geometry": {
    "type": "Point",
    "coordinates": [
      -111.0333,
      42.9667
    ]
  },
  "type": "Feature",
  "properties": {
    "hierarchy": [
      "tgn:7020167",
      "tgn:1000001",
      "tgn:7012149",
      "tgn:2002376",
      "tgn:7007923",
      "tgn:7029392"
    ],
    "placetype": [
      "aat:300008347"
    ],
    "id": 7020167,
    "name:xx": "Freedom"
  }
}
