{
  "geometry": {
    "type": "Point",
    "coordinates": [
      -79.5833,
      38.3333
    ]
  },
  "type": "Feature",
  "properties": {
    "hierarchy": [
      "tgn:2416733",
      "tgn:1000001",
      "tgn:7012149",
      "tgn:7029392"
    ],
    "placetype": [
      "aat:300386831"
    ],
    "id": 2416733,
    "name:xx": "Jack Mountain"
  }
}
