{
  "geometry": {
    "type": "Point",
    "coordinates": [
      22.75,
      50.8333
    ]
  },
  "type": "Feature",
  "properties": {
    "hierarchy": [
      "tgn:1049557",
      "tgn:1000003",
      "tgn:7024128",
      "tgn:7006366",
      "tgn:7029392"
    ],
    "placetype": [
      "aat:300008347"
    ],
    "id": 1049557,
    "name:xx": "Turobin"
  }
}
