{
  "type": "FeatureCollection",
  "features": [
    {
      "geometry": {
        "type": "Point",
        "coordinates": [
          177.2167,
          51.8667
        ]
      },
      "type": "Feature",
      "properties": {
        "hierarchy": [
          "tgn:2275760",
          "tgn:7030516",
          "tgn:7006450",
          "tgn:1000001",
          "tgn:7012149",
          "tgn:7029392"
        ],
        "placetype": [
          "aat:300132316"
        ],
        "id": 2275760,
        "name:xx": "Dark Cove"
      }
    },
    {
      "geometry": {
        "type": "Point",
        "coordinates": [
          -67.95,
          45.1833
        ]
      },
      "type": "Feature",
      "properties": {
        "hierarchy": [
          "tgn:2275761",
          "tgn:1000001",
          "tgn:7012149",
          "tgn:7014589",
          "tgn:7007515",
          "tgn:7029392"
        ],
        "placetype": [
          "aat:300132316"
        ],
        "id": 2275761,
        "name:xx": "Dark Cove"
      }
    },
    {
      "geometry": {
        "type": "Point",
        "coordinates": [
          -67.85,
          45.7167
        ]
      },
      "type": "Feature",
      "properties": {
        "hierarchy": [
          "tgn:2275762",
          "tgn:2000919",
          "tgn:1000001",
          "tgn:7012149",
          "tgn:7007515",
          "tgn:7029392"
        ],
        "placetype": [
          "aat:300132316"
        ],
        "id": 2275762,
        "name:xx": "Dark Cove"
      }
    },
    {
      "geometry": {
        "type": "Point",
        "coordinates": [
          -83.6833,
          35.05
        ]
      },
      "type": "Feature",
      "properties": {
        "hierarchy": [
          "tgn:2275763",
          "tgn:1000001",
          "tgn:2001483",
          "tgn:7012149",
          "tgn:7007709",
          "tgn:7029392"
        ],
        "placetype": [
          "aat:300008761"
        ],
        "id": 2275763,
        "name:xx": "Dark Cove"
      }
    },
    {
      "geometry": {
        "type": "Point",
        "coordinates": [
          -82.5333,
          35.2167
        ]
      },
      "type": "Feature",
      "properties": {
        "hierarchy": [
          "tgn:2275764",
          "tgn:1000001",
          "tgn:7012149",
          "tgn:2001504",
          "tgn:7007709",
          "tgn:7029392"
        ],
        "placetype": [
          "aat:300008761"
        ],
        "id": 2275764,
        "name:xx": "Dark Cove"
      }
    },
    {
      "geometry": {
        "type": "Point",
        "coordinates": [
          -67.9333,
          45.1833
        ]
      },
      "type": "Feature",
      "properties": {
        "hierarchy": [
          "tgn:2275765",
          "tgn:1000001",
          "tgn:7012149",
          "tgn:7014589",
          "tgn:7007515",
          "tgn:7029392"
        ],
        "placetype": [
          "aat:300008798"
        ],
        "id": 2275765,
        "name:xx": "Dark Cove Mountain"
      }
    },
    {
      "geometry": {
        "type": "Point",
        "coordinates": [
          -81.3167,
          31.4333
        ]
      },
      "type": "Feature",
      "properties": {
        "hierarchy": [
          "tgn:2275766",
          "tgn:1000001",
          "tgn:7012149",
          "tgn:2000386",
          "tgn:7007248",
          "tgn:7029392"
        ],
        "placetype": [
          "aat:300008706"
        ],
        "id": 2275766,
        "name:xx": "Dark Creek"
      }
    },
    {
      "geometry": {
        "type": "Point",
        "coordinates": [
          -92.55,
          39.6
        ]
      },
      "type": "Feature",
      "properties": {
        "hierarchy": [
          "tgn:2275767",
          "tgn:1000001",
          "tgn:7012149",
          "tgn:1002819",
          "tgn:7007523",
          "tgn:7029392"
        ],
        "placetype": [
          "aat:300008706"
        ],
        "id": 2275767,
        "name:xx": "Dark Creek"
      }
    },
    {
      "geometry": {
        "type": "Point",
        "coordinates": [
          -115.5833,
          48.7
        ]
      },
      "type": "Feature",
      "properties": {
        "hierarchy": [
          "tgn:2275768",
          "tgn:1000001",
          "tgn:7012149",
          "tgn:2001286",
          "tgn:7007524",
          "tgn:7029392"
        ],
        "placetype": [
          "aat:300008706"
        ],
        "id": 2275768,
        "name:xx": "Dark Creek"
      }
    },
    {
      "geometry": {
        "type": "Point",
        "coordinates": [
          -123.1833,
          42.85
        ]
      },
      "type": "Feature",
      "properties": {
        "hierarchy": [
          "tgn:2275769",
          "tgn:1000001",
          "tgn:7012149",
          "tgn:2001706",
          "tgn:7007708",
          "tgn:7029392"
        ],
        "placetype": [
          "aat:300008706"
        ],
        "id": 2275769,
        "name:xx": "Dark Creek"
      }
    }
  ]
}
