{
  "type": "FeatureCollection",
  "features": [
    {
      "geometry": {
        "type": "Point",
        "coordinates": [
          -5.3,
          57.266667
        ]
      },
      "type": "Feature",
      "properties": {
        "hierarchy": [
          "tgn:7449373",
          "tgn:7002444",
          "tgn:1000003",
          "tgn:7008082",
          "tgn:7008591",
          "tgn:7029392"
        ],
        "placetype": [
          "aat:300008736"
        ],
        "name:en": "Glomach, Fall of",
        "id": 7449373
      }
    },
    {
      "geometry": {
        "type": "Point",
        "coordinates": [
          -4.6,
          51.95
        ]
      },
      "type": "Feature",
      "properties": {
        "hierarchy": [
          "tgn:7449374",
          "tgn:7002443",
          "tgn:1000003",
          "tgn:7018993",
          "tgn:7008591",
          "tgn:7029392"
        ],
        "placetype": [
          "aat:300007783"
        ],
        "name:en": "Glogue Station",
        "id": 7449374
      }
    },
    {
      "geometry": {
        "type": "Point",
        "coordinates": [
          -2.916667,
          58.883333
        ]
      },
      "type": "Feature",
      "properties": {
        "hierarchy": [
          "tgn:7449376",
          "tgn:7002444",
          "tgn:1000003",
          "tgn:7009907",
          "tgn:7008591",
          "tgn:7029392"
        ],
        "placetype": [
          "aat:300008791"
        ],
        "name:en": "Glims Holm",
        "id": 7449376
      }
    },
    {
      "geometry": {
        "type": "Point",
        "coordinates": [
          -3.866667,
          55.533333
        ]
      },
      "type": "Feature",
      "properties": {
        "hierarchy": [
          "tgn:7449377",
          "tgn:7002444",
          "tgn:1000003",
          "tgn:7019090",
          "tgn:7008591",
          "tgn:7029392"
        ],
        "placetype": [
          "aat:300008699"
        ],
        "name:en": "Glespin Burn",
        "id": 7449377
      }
    },
    {
      "geometry": {
        "type": "Point",
        "coordinates": [
          -5.25,
          57.083333
        ]
      },
      "type": "Feature",
      "properties": {
        "hierarchy": [
          "tgn:7449378",
          "tgn:7002444",
          "tgn:1000003",
          "tgn:7008082",
          "tgn:7008591",
          "tgn:7029392"
        ],
        "placetype": [
          "aat:300008795"
        ],
        "name:en": "Gleouraich",
        "id": 7449378
      }
    },
    {
      "geometry": {
        "type": "Point",
        "coordinates": [
          -2.966667,
          55.033333
        ]
      },
      "type": "Feature",
      "properties": {
        "hierarchy": [
          "tgn:7449379",
          "tgn:7002445",
          "tgn:1000003",
          "tgn:7008117",
          "tgn:7008591",
          "tgn:7029392"
        ],
        "placetype": [
          "aat:300008699"
        ],
        "name:en": "Glenzier Burn",
        "id": 7449379
      }
    }
  ]
}
