{
  "type": "FeatureCollection",
  "features": [
    {
      "geometry": {
        "type": "Point",
        "coordinates": [
          -82.45,
          37.1833
        ]
      },
      "type": "Feature",
      "properties": {
        "hierarchy": [
          "tgn:2112411",
          "tgn:1000001",
          "tgn:7012149",
          "tgn:2002157",
          "tgn:7007919",
          "tgn:7029392"
        ],
        "placetype": [
          "aat:300008347",
          "aat:300387210"
        ],
        "id": 2112411,
        "name:xx": "Isom"
      }
    },
    {
      "geometry": {
        "type": "Point",
        "coordinates": [
          -77.4,
          38.7833
        ]
      },
      "type": "Feature",
      "properties": {
        "hierarchy": [
          "tgn:2112412",
          "tgn:1000001",
          "tgn:7012149",
          "tgn:7014160",
          "tgn:7007919",
          "tgn:7029392"
        ],
        "placetype": [
          "aat:300008347",
          "aat:300387210"
        ],
        "id": 2112412,
        "name:xx": "Ivakota"
      }
    },
    {
      "geometry": {
        "type": "Point",
        "coordinates": [
          -80.9667,
          36.8333
        ]
      },
      "type": "Feature",
      "properties": {
        "hierarchy": [
          "tgn:2112413",
          "tgn:1000001",
          "tgn:7012149",
          "tgn:2002196",
          "tgn:7007919",
          "tgn:7029392"
        ],
        "placetype": [
          "aat:300008347"
        ],
        "id": 2112413,
        "name:xx": "Ivanhoe"
      }
    },
    {
      "geometry": {
        "type": "Point",
        "coordinates": [
          -76.6667,
          37.85
        ]
      },
      "type": "Feature",
      "properties": {
        "hierarchy": [
          "tgn:2112414",
          "tgn:1000001",
          "tgn:7012149",
          "tgn:7014334",
          "tgn:7007919",
          "tgn:7029392"
        ],
        "placetype": [
          "aat:300008347",
          "aat:300387210"
        ],
        "id": 2112414,
        "name:xx": "Ivondale"
      }
    },
    {
      "geometry": {
        "type": "Point",
        "coordinates": [
          -76.9,
          36.9
        ]
      },
      "type": "Feature",
      "properties": {
        "hierarchy": [
          "tgn:2112415",
          "tgn:1000001",
          "tgn:7012149",
          "tgn:1002911",
          "tgn:7007919",
          "tgn:7029392"
        ],
        "placetype": [
          "aat:300008347"
        ],
        "id": 2112415,
        "name:xx": "Ivor"
      }
    },
    {
      "geometry": {
        "type": "Point",
        "coordinates": [
          -78.5833,
          38.05
        ]
      },
      "type": "Feature",
      "properties": {
        "hierarchy": [
          "tgn:2112416",
          "tgn:2002137",
          "tgn:1000001",
          "tgn:7012149",
          "tgn:7007919",
          "tgn:7029392"
        ],
        "placetype": [
          "aat:300008347"
        ],
        "id": 2112416,
        "name:xx": "Ivy"
      }
    },
    {
      "geometry": {
        "type": "Point",
        "coordinates": [
          -76.6833,
          37.7
        ]
      },
      "type": "Feature",
      "properties": {
        "hierarchy": [
          "tgn:2112418",
          "tgn:1000001",
          "tgn:7012149",
          "tgn:1002667",
          "tgn:7007919",
          "tgn:7029392"
        ],
        "placetype": [
          "aat:300008347"
        ],
        "id": 2112418,
        "name:xx": "Jamaica"
      }
    }
  ]
}
