{
  "type": "FeatureCollection",
  "features": [
    {
      "geometry": {
        "type": "Point",
        "coordinates": [
          -79.65,
          39.2833
        ]
      },
      "type": "Feature",
      "properties": {
        "hierarchy": [
          "tgn:2156610",
          "tgn:1000001",
          "tgn:7012149",
          "tgn:2002288",
          "tgn:7013961",
          "tgn:7029392"
        ],
        "placetype": [
          "aat:300266640"
        ],
        "id": 2156610,
        "name:xx": "Bearwallow Ridge"
      }
    },
    {
      "geometry": {
        "type": "Point",
        "coordinates": [
          -81.4,
          37.6167
        ]
      },
      "type": "Feature",
      "properties": {
        "hierarchy": [
          "tgn:2156611",
          "tgn:1000001",
          "tgn:7012149",
          "tgn:2002304",
          "tgn:7013961",
          "tgn:7029392"
        ],
        "placetype": [
          "aat:300266640"
        ],
        "id": 2156611,
        "name:xx": "Bearwallow Ridge"
      }
    },
    {
      "geometry": {
        "type": "Point",
        "coordinates": [
          -80.85,
          39.8333
        ]
      },
      "type": "Feature",
      "properties": {
        "hierarchy": [
          "tgn:2156612",
          "tgn:1000001",
          "tgn:7012149",
          "tgn:2001617",
          "tgn:7007706",
          "tgn:7029392"
        ],
        "placetype": [
          "aat:300008699"
        ],
        "id": 2156612,
        "name:xx": "Bearwallow Run"
      }
    },
    {
      "geometry": {
        "type": "Point",
        "coordinates": [
          -76.5167,
          41.2833
        ]
      },
      "type": "Feature",
      "properties": {
        "hierarchy": [
          "tgn:2156613",
          "tgn:1000001",
          "tgn:7012149",
          "tgn:1002927",
          "tgn:7007710",
          "tgn:7029392"
        ],
        "placetype": [
          "aat:300008699"
        ],
        "id": 2156613,
        "name:xx": "Bearwallow Run"
      }
    },
    {
      "geometry": {
        "type": "Point",
        "coordinates": [
          -78.6667,
          38.2833
        ]
      },
      "type": "Feature",
      "properties": {
        "hierarchy": [
          "tgn:2156614",
          "tgn:1000001",
          "tgn:7012149",
          "tgn:2002187",
          "tgn:7007919",
          "tgn:7029392"
        ],
        "placetype": [
          "aat:300008699"
        ],
        "id": 2156614,
        "name:xx": "Bearwallow Run"
      }
    },
    {
      "geometry": {
        "type": "Point",
        "coordinates": [
          -79.65,
          38.55
        ]
      },
      "type": "Feature",
      "properties": {
        "hierarchy": [
          "tgn:2156615",
          "tgn:1000001",
          "tgn:7012149",
          "tgn:2002168",
          "tgn:7007919",
          "tgn:7029392"
        ],
        "placetype": [
          "aat:300008699"
        ],
        "id": 2156615,
        "name:xx": "Bearwallow Run"
      }
    },
    {
      "geometry": {
        "type": "Point",
        "coordinates": [
          -79.7167,
          38.6
        ]
      },
      "type": "Feature",
      "properties": {
        "hierarchy": [
          "tgn:2156616",
          "tgn:1000001",
          "tgn:7012149",
          "tgn:2002287",
          "tgn:7013961",
          "tgn:7029392"
        ],
        "placetype": [
          "aat:300008699"
        ],
        "id": 2156616,
        "name:xx": "Bearwallow Run"
      }
    },
    {
      "geometry": {
        "type": "Point",
        "coordinates": [
          -79.7333,
          39.2167
        ]
      },
      "type": "Feature",
      "properties": {
        "hierarchy": [
          "tgn:2156618",
          "tgn:1000001",
          "tgn:7012149",
          "tgn:2002296",
          "tgn:7013961",
          "tgn:7029392"
        ],
        "placetype": [
          "aat:300008699"
        ],
        "id": 2156618,
        "name:xx": "Bearwallow Run"
      }
    },
    {
      "geometry": {
        "type": "Point",
        "coordinates": [
          -79.6667,
          39.3667
        ]
      },
      "type": "Feature",
      "properties": {
        "hierarchy": [
          "tgn:2156619",
          "tgn:1000001",
          "tgn:7012149",
          "tgn:2002288",
          "tgn:7013961",
          "tgn:7029392"
        ],
        "placetype": [
          "aat:300008699"
        ],
        "id": 2156619,
        "name:xx": "Bearwallow Run"
      }
    }
  ]
}
