{
  "geometry": {
    "type": "Point",
    "coordinates": [
      -72.8833,
      43.8167
    ]
  },
  "type": "Feature",
  "properties": {
    "hierarchy": [
      "tgn:2423068",
      "tgn:1000001",
      "tgn:1002840",
      "tgn:7012149",
      "tgn:7007828",
      "tgn:7029392"
    ],
    "placetype": [
      "aat:300008699"
    ],
    "id": 2423068,
    "name:xx": "Joe Smith Brook"
  }
}
