{
  "geometry": {
    "type": "Point",
    "coordinates": [
      -71.2333,
      43.2833
    ]
  },
  "type": "Feature",
  "properties": {
    "hierarchy": [
      "tgn:2268385",
      "tgn:1000001",
      "tgn:7012149",
      "tgn:7007564",
      "tgn:7029392"
    ],
    "placetype": [
      "aat:300008699"
    ],
    "id": 2268385,
    "name:xx": "Crooked Run"
  }
}
