{
  "type": "FeatureCollection",
  "features": [
    {
      "geometry": {
        "type": "Point",
        "coordinates": [
          10.5,
          53.683333
        ]
      },
      "type": "Feature",
      "properties": {
        "hierarchy": [
          "tgn:1041020",
          "tgn:1000003",
          "tgn:7003688",
          "tgn:7000084",
          "tgn:7029392"
        ],
        "placetype": [
          "aat:300008347"
        ],
        "id": 1041020,
        "name:xx": "Sandesneben"
      }
    },
    {
      "geometry": {
        "type": "Point",
        "coordinates": [
          7.5,
          53.483333
        ]
      },
      "type": "Feature",
      "properties": {
        "hierarchy": [
          "tgn:1041021",
          "tgn:1000003",
          "tgn:7003676",
          "tgn:7000084",
          "tgn:7029392"
        ],
        "placetype": [
          "aat:300008347"
        ],
        "id": 1041021,
        "name:xx": "Sandhorst"
      }
    },
    {
      "geometry": {
        "type": "Point",
        "coordinates": [
          8.533333,
          53.366667
        ]
      },
      "type": "Feature",
      "properties": {
        "hierarchy": [
          "tgn:1041022",
          "tgn:1000003",
          "tgn:7003676",
          "tgn:7000084",
          "tgn:7029392"
        ],
        "placetype": [
          "aat:300008347"
        ],
        "id": 1041022,
        "name:xx": "Sandstedt"
      }
    },
    {
      "geometry": {
        "type": "Point",
        "coordinates": [
          7.183333,
          50.766667
        ]
      },
      "type": "Feature",
      "properties": {
        "hierarchy": [
          "tgn:1041024",
          "tgn:1000003",
          "tgn:7003677",
          "tgn:7000084",
          "tgn:7029392"
        ],
        "placetype": [
          "aat:300008347",
          "aat:300008389"
        ],
        "id": 1041024,
        "name:xx": "Sankt Augustin"
      }
    },
    {
      "geometry": {
        "type": "Point",
        "coordinates": [
          7.8,
          47.983333
        ]
      },
      "type": "Feature",
      "properties": {
        "hierarchy": [
          "tgn:1041026",
          "tgn:7003692",
          "tgn:1000003",
          "tgn:7000084",
          "tgn:7029392"
        ],
        "placetype": [
          "aat:300008347",
          "aat:300008375"
        ],
        "name:en": "Sankt Georgen",
        "id": 1041026,
        "name:de": "Sankt Georgen"
      }
    },
    {
      "geometry": {
        "type": "Point",
        "coordinates": [
          7.733333,
          50.15
        ]
      },
      "type": "Feature",
      "properties": {
        "hierarchy": [
          "tgn:1041028",
          "tgn:1000003",
          "tgn:7003682",
          "tgn:7000084",
          "tgn:7029392"
        ],
        "placetype": [
          "aat:300008347"
        ],
        "id": 1041028,
        "name:xx": "Sankt Goarshausen"
      }
    },
    {
      "geometry": {
        "type": "Point",
        "coordinates": [
          6.45,
          51.383333
        ]
      },
      "type": "Feature",
      "properties": {
        "hierarchy": [
          "tgn:1041029",
          "tgn:1000003",
          "tgn:7003677",
          "tgn:7000084",
          "tgn:7029392"
        ],
        "placetype": [
          "aat:300008347"
        ],
        "id": 1041029,
        "name:xx": "Sankt Hubert"
      }
    }
  ]
}
