{
  "geometry": {
    "type": "Point",
    "coordinates": [
      -83.55,
      38.7333
    ]
  },
  "type": "Feature",
  "properties": {
    "hierarchy": [
      "tgn:2523255",
      "tgn:1002136",
      "tgn:1000001",
      "tgn:7012149",
      "tgn:7007706",
      "tgn:7029392"
    ],
    "placetype": [
      "aat:300008699"
    ],
    "id": 2523255,
    "name:xx": "Moores Run"
  }
}
