{
  "geometry": {
    "type": "Point",
    "coordinates": [
      -100.175,
      20.175
    ]
  },
  "type": "Feature",
  "properties": {
    "hierarchy": [
      "tgn:7399291",
      "tgn:1000001",
      "tgn:7005593",
      "tgn:7005560",
      "tgn:7029392"
    ],
    "placetype": [
      "aat:300008347"
    ],
    "id": 7399291,
    "name:xx": "San Juan Dehedo"
  }
}
