{
  "geometry": {
    "type": "Point",
    "coordinates": [
      -99.8333,
      37.2167
    ]
  },
  "type": "Feature",
  "properties": {
    "hierarchy": [
      "tgn:2612784",
      "tgn:1000001",
      "tgn:2000672",
      "tgn:7012149",
      "tgn:7007254",
      "tgn:7029392"
    ],
    "placetype": [
      "aat:300008706"
    ],
    "id": 2612784,
    "name:xx": "Redhole Creek"
  }
}
