{
  "type": "FeatureCollection",
  "features": [
    {
      "geometry": {
        "type": "Point",
        "coordinates": [
          -120.3333,
          47.0167
        ]
      },
      "type": "Feature",
      "properties": {
        "hierarchy": [
          "tgn:1136020",
          "tgn:1000001",
          "tgn:7012149",
          "tgn:1002553",
          "tgn:7007920",
          "tgn:7029392"
        ],
        "placetype": [
          "aat:300006075"
        ],
        "id": 1136020,
        "name:xx": "North Branch Canal"
      }
    },
    {
      "geometry": {
        "type": "Point",
        "coordinates": [
          -80.5167,
          26.3167
        ]
      },
      "type": "Feature",
      "properties": {
        "hierarchy": [
          "tgn:1136021",
          "tgn:1000001",
          "tgn:7012149",
          "tgn:7007240",
          "tgn:7029392"
        ],
        "placetype": [
          "aat:300006075"
        ],
        "id": 1136021,
        "name:xx": "North New River Canal"
      }
    },
    {
      "geometry": {
        "type": "Point",
        "coordinates": [
          -87.7,
          42.0333
        ]
      },
      "type": "Feature",
      "properties": {
        "hierarchy": [
          "tgn:1136022",
          "tgn:1000001",
          "tgn:7013649",
          "tgn:7012149",
          "tgn:7007251",
          "tgn:7029392"
        ],
        "placetype": [
          "aat:300006075"
        ],
        "id": 1136022,
        "name:xx": "North Shore Channel"
      }
    },
    {
      "geometry": {
        "type": "Point",
        "coordinates": [
          -57.3,
          -36.1833
        ]
      },
      "type": "Feature",
      "properties": {
        "hierarchy": [
          "tgn:1136023",
          "tgn:1001160",
          "tgn:7006477",
          "tgn:1000002",
          "tgn:7029392"
        ],
        "placetype": [
          "aat:300006075"
        ],
        "id": 1136023,
        "name:xx": "Nueve, Canal Numero"
      }
    },
    {
      "geometry": {
        "type": "Point",
        "coordinates": [
          14.033333,
          52.866667
        ]
      },
      "type": "Feature",
      "properties": {
        "hierarchy": [
          "tgn:1136024",
          "tgn:7000096",
          "tgn:1000003",
          "tgn:7000084",
          "tgn:7029392"
        ],
        "placetype": [
          "aat:300006075"
        ],
        "id": 1136024,
        "name:xx": "Oder-Havel-Kanal"
      }
    },
    {
      "geometry": {
        "type": "Point",
        "coordinates": [
          13.6833,
          52.3833
        ]
      },
      "type": "Feature",
      "properties": {
        "hierarchy": [
          "tgn:1136025",
          "tgn:1000003",
          "tgn:7000084",
          "tgn:7029392"
        ],
        "placetype": [
          "aat:300006075"
        ],
        "id": 1136025,
        "name:xx": "Oder-Spree-Kanal"
      }
    },
    {
      "geometry": {
        "type": "Point",
        "coordinates": [
          -3.7,
          40.5333
        ]
      },
      "type": "Feature",
      "properties": {
        "hierarchy": [
          "tgn:1136026",
          "tgn:7010420",
          "tgn:1000003",
          "tgn:7002795",
          "tgn:1000095",
          "tgn:7029392"
        ],
        "placetype": [
          "aat:300006075"
        ],
        "id": 1136026,
        "name:xx": "Oeste, Canal del"
      }
    },
    {
      "geometry": {
        "type": "Point",
        "coordinates": [
          -81.4,
          40.4167
        ]
      },
      "type": "Feature",
      "properties": {
        "hierarchy": [
          "tgn:1136027",
          "tgn:1000001",
          "tgn:7012149",
          "tgn:7007706",
          "tgn:7029392"
        ],
        "placetype": [
          "aat:300006075"
        ],
        "id": 1136027,
        "name:xx": "Ohio Canal"
      }
    },
    {
      "geometry": {
        "type": "Point",
        "coordinates": [
          -58.6,
          -36.15
        ]
      },
      "type": "Feature",
      "properties": {
        "hierarchy": [
          "tgn:1136029",
          "tgn:1001160",
          "tgn:7006477",
          "tgn:1000002",
          "tgn:7029392"
        ],
        "placetype": [
          "aat:300006075"
        ],
        "id": 1136029,
        "name:xx": "Once, Canal Numero"
      }
    }
  ]
}
