{
  "geometry": {
    "type": "Point",
    "coordinates": [
      -139.0667,
      -9.9667
    ]
  },
  "type": "Feature",
  "properties": {
    "hierarchy": [
      "tgn:1098722",
      "tgn:7006215",
      "tgn:1009344",
      "tgn:1000216",
      "tgn:1000006",
      "tgn:7029392"
    ],
    "placetype": [
      "aat:300008347"
    ],
    "id": 1098722,
    "name:xx": "Hanatetena"
  }
}
