{
  "geometry": {
    "type": "Point",
    "coordinates": [
      -83.65,
      38.65
    ]
  },
  "type": "Feature",
  "properties": {
    "hierarchy": [
      "tgn:2350298",
      "tgn:1002136",
      "tgn:1000001",
      "tgn:7012149",
      "tgn:7007706",
      "tgn:7029392"
    ],
    "placetype": [
      "aat:300266640"
    ],
    "id": 2350298,
    "name:xx": "Ginger Ridge"
  }
}
