{
  "geometry": {
    "type": "Point",
    "coordinates": [
      -106.6667,
      38.8167
    ]
  },
  "type": "Feature",
  "properties": {
    "hierarchy": [
      "tgn:2741679",
      "tgn:1000001",
      "tgn:7012149",
      "tgn:2000217",
      "tgn:7007158",
      "tgn:7029392"
    ],
    "placetype": [
      "aat:300008761"
    ],
    "id": 2741679,
    "name:xx": "Ute Gulch"
  }
}
