{
  "geometry": {
    "type": "Point",
    "coordinates": [
      -2.95,
      42.15
    ]
  },
  "type": "Feature",
  "properties": {
    "hierarchy": [
      "tgn:7336676",
      "tgn:7002827",
      "tgn:1000003",
      "tgn:7002789",
      "tgn:1000095",
      "tgn:7029392"
    ],
    "placetype": [
      "aat:300008699"
    ],
    "id": 7336676,
    "name:xx": "Gatón, Río"
  }
}
