{
  "geometry": {
    "type": "Point",
    "coordinates": [
      -121.25,
      42.0667
    ]
  },
  "type": "Feature",
  "properties": {
    "hierarchy": [
      "tgn:2758408",
      "tgn:1000001",
      "tgn:7012149",
      "tgn:2001714",
      "tgn:7007708",
      "tgn:7029392"
    ],
    "placetype": [
      "aat:300006075"
    ],
    "id": 2758408,
    "name:xx": "West Canal"
  }
}
