{
  "geometry": {
    "type": "Point",
    "coordinates": [
      -122.6667,
      47.8333
    ]
  },
  "type": "Feature",
  "properties": {
    "hierarchy": [
      "tgn:2224527",
      "tgn:1000001",
      "tgn:7012149",
      "tgn:1002521",
      "tgn:7007920",
      "tgn:7029392"
    ],
    "placetype": [
      "aat:300132348"
    ],
    "id": 2224527,
    "name:xx": "Case Shoal"
  }
}
