{
  "geometry": {
    "type": "Point",
    "coordinates": [
      -74.8833,
      42.2667
    ]
  },
  "type": "Feature",
  "properties": {
    "hierarchy": [
      "tgn:2723976",
      "tgn:1000001",
      "tgn:1002328",
      "tgn:7012149",
      "tgn:7007568",
      "tgn:7029392"
    ],
    "placetype": [
      "aat:300008699"
    ],
    "id": 2723976,
    "name:xx": "Toll Gate Brook"
  }
}
