{
  "type": "FeatureCollection",
  "features": [
    {
      "geometry": {
        "type": "Point",
        "coordinates": [
          12.05,
          43.066667
        ]
      },
      "type": "Feature",
      "properties": {
        "hierarchy": [
          "tgn:7041830",
          "tgn:7003170",
          "tgn:1000003",
          "tgn:7003125",
          "tgn:1000080",
          "tgn:7029392"
        ],
        "placetype": [
          "aat:300008347"
        ],
        "id": 7041830,
        "name:xx": "Sanfatucchio"
      }
    },
    {
      "geometry": {
        "type": "Point",
        "coordinates": [
          15.083333,
          41.25
        ]
      },
      "type": "Feature",
      "properties": {
        "hierarchy": [
          "tgn:7041831",
          "tgn:7003005",
          "tgn:1000003",
          "tgn:1000080",
          "tgn:7029392"
        ],
        "placetype": [
          "aat:300387200"
        ],
        "id": 7041831,
        "name:xx": "Contrada San Eleuterio"
      }
    },
    {
      "geometry": {
        "type": "Point",
        "coordinates": [
          13.833333,
          45.6
        ]
      },
      "type": "Feature",
      "properties": {
        "hierarchy": [
          "tgn:7041834",
          "tgn:1003505",
          "tgn:1000003",
          "tgn:7002993",
          "tgn:1000080",
          "tgn:7029392"
        ],
        "placetype": [
          "aat:300387198",
          "aat:300265612"
        ],
        "id": 7041834,
        "name:xx": "San Dorligo della Valle"
      }
    },
    {
      "geometry": {
        "type": "Point",
        "coordinates": [
          10.966667,
          44.583333
        ]
      },
      "type": "Feature",
      "properties": {
        "hierarchy": [
          "tgn:7041835",
          "tgn:7004597",
          "tgn:1000003",
          "tgn:7008516",
          "tgn:1000080",
          "tgn:7029392"
        ],
        "placetype": [
          "aat:300008347"
        ],
        "id": 7041835,
        "name:xx": "San Donnino della Nizzola"
      }
    },
    {
      "geometry": {
        "type": "Point",
        "coordinates": [
          11.3,
          44.666667
        ]
      },
      "type": "Feature",
      "properties": {
        "hierarchy": [
          "tgn:7041837",
          "tgn:7003127",
          "tgn:1000003",
          "tgn:7008516",
          "tgn:1000080",
          "tgn:7029392"
        ],
        "placetype": [
          "aat:300008347"
        ],
        "id": 7041837,
        "name:xx": "San Donino"
      }
    }
  ]
}
