{
  "type": "FeatureCollection",
  "features": [
    {
      "geometry": {
        "type": "Point",
        "coordinates": [
          173.133333,
          -41.3
        ]
      },
      "type": "Feature",
      "properties": {
        "hierarchy": [
          "tgn:7509170",
          "tgn:1009227",
          "tgn:1000226",
          "tgn:7016729",
          "tgn:1000006",
          "tgn:7029392"
        ],
        "placetype": [
          "aat:300008699"
        ],
        "name:en": "Waimea River",
        "id": 7509170
      }
    },
    {
      "geometry": {
        "type": "Point",
        "coordinates": [
          168.583333,
          -45.833333
        ]
      },
      "type": "Feature",
      "properties": {
        "hierarchy": [
          "tgn:7509171",
          "tgn:1009227",
          "tgn:1000226",
          "tgn:7016822",
          "tgn:1000006",
          "tgn:7029392"
        ],
        "placetype": [
          "aat:300008805"
        ],
        "name:en": "Waimea Plains",
        "id": 7509171
      }
    },
    {
      "geometry": {
        "type": "Point",
        "coordinates": [
          168.7,
          -45.983333
        ]
      },
      "type": "Feature",
      "properties": {
        "hierarchy": [
          "tgn:7509172",
          "tgn:1009227",
          "tgn:1000226",
          "tgn:7016822",
          "tgn:1000006",
          "tgn:7029392"
        ],
        "placetype": [
          "aat:300008795"
        ],
        "name:en": "Waimea Hill",
        "id": 7509172
      }
    },
    {
      "geometry": {
        "type": "Point",
        "coordinates": [
          171.066667,
          -42.633333
        ]
      },
      "type": "Feature",
      "properties": {
        "hierarchy": [
          "tgn:7509173",
          "tgn:1009227",
          "tgn:1000226",
          "tgn:1000006",
          "tgn:7016850",
          "tgn:7029392"
        ],
        "placetype": [
          "aat:300008699"
        ],
        "name:en": "Waimea Creek",
        "id": 7509173
      }
    },
    {
      "geometry": {
        "type": "Point",
        "coordinates": [
          177.75,
          -39.066667
        ]
      },
      "type": "Feature",
      "properties": {
        "hierarchy": [
          "tgn:7509175",
          "tgn:7016670",
          "tgn:1008380",
          "tgn:1000226",
          "tgn:1000006",
          "tgn:7029392"
        ],
        "placetype": [
          "aat:300008699"
        ],
        "name:en": "Waimaunu Stream",
        "id": 7509175
      }
    },
    {
      "geometry": {
        "type": "Point",
        "coordinates": [
          171.7,
          -42.233333
        ]
      },
      "type": "Feature",
      "properties": {
        "hierarchy": [
          "tgn:7509176",
          "tgn:1009227",
          "tgn:1000226",
          "tgn:1000006",
          "tgn:7016850",
          "tgn:7029392"
        ],
        "placetype": [
          "aat:300008347"
        ],
        "name:en": "Waimaunga",
        "id": 7509176
      }
    },
    {
      "geometry": {
        "type": "Point",
        "coordinates": [
          174.5,
          -36.75
        ]
      },
      "type": "Feature",
      "properties": {
        "hierarchy": [
          "tgn:7509177",
          "tgn:7000508",
          "tgn:1008380",
          "tgn:1000226",
          "tgn:1000006",
          "tgn:7029392"
        ],
        "placetype": [
          "aat:300008347"
        ],
        "name:en": "Waimauku",
        "id": 7509177
      }
    },
    {
      "geometry": {
        "type": "Point",
        "coordinates": [
          168.166667,
          -46.366667
        ]
      },
      "type": "Feature",
      "properties": {
        "hierarchy": [
          "tgn:7509178",
          "tgn:1009227",
          "tgn:1000226",
          "tgn:7016822",
          "tgn:1000006",
          "tgn:7029392"
        ],
        "placetype": [
          "aat:300008699"
        ],
        "name:en": "Waimatuku Stream",
        "id": 7509178
      }
    },
    {
      "geometry": {
        "type": "Point",
        "coordinates": [
          168.166667,
          -46.3
        ]
      },
      "type": "Feature",
      "properties": {
        "hierarchy": [
          "tgn:7509179",
          "tgn:1009227",
          "tgn:1000226",
          "tgn:7016822",
          "tgn:1000006",
          "tgn:7029392"
        ],
        "placetype": [
          "aat:300008347"
        ],
        "name:en": "Waimatuku",
        "id": 7509179
      }
    }
  ]
}
