{
  "geometry": {
    "type": "Point",
    "coordinates": [
      -73.4833,
      41.7667
    ]
  },
  "type": "Feature",
  "properties": {
    "hierarchy": [
      "tgn:1102374",
      "tgn:1000001",
      "tgn:1002601",
      "tgn:7012149",
      "tgn:7007159",
      "tgn:7029392"
    ],
    "placetype": [
      "aat:300008192"
    ],
    "id": 1102374,
    "name:xx": "Macedonia Brook State Park"
  }
}
