{
  "type": "FeatureCollection",
  "features": [
    {
      "geometry": {
        "type": "Point",
        "coordinates": [
          7.766667,
          49.066667
        ]
      },
      "type": "Feature",
      "properties": {
        "hierarchy": [
          "tgn:7097790",
          "tgn:1000003",
          "tgn:7003682",
          "tgn:7000084",
          "tgn:7029392"
        ],
        "placetype": [
          "aat:300008795"
        ],
        "id": 7097790,
        "name:xx": "Sindels Berg"
      }
    },
    {
      "geometry": {
        "type": "Point",
        "coordinates": [
          7.9,
          49.433333
        ]
      },
      "type": "Feature",
      "properties": {
        "hierarchy": [
          "tgn:7097791",
          "tgn:1000003",
          "tgn:7003682",
          "tgn:7000084",
          "tgn:7029392"
        ],
        "placetype": [
          "aat:300008777"
        ],
        "id": 7097791,
        "name:xx": "Sindelsberg"
      }
    },
    {
      "geometry": {
        "type": "Point",
        "coordinates": [
          11.216667,
          47.9
        ]
      },
      "type": "Feature",
      "properties": {
        "hierarchy": [
          "tgn:7097792",
          "tgn:7003669",
          "tgn:1000003",
          "tgn:7000084",
          "tgn:7029392"
        ],
        "placetype": [
          "aat:300008777"
        ],
        "id": 7097792,
        "name:xx": "Sindels Berg"
      }
    },
    {
      "geometry": {
        "type": "Point",
        "coordinates": [
          12.2,
          49.383333
        ]
      },
      "type": "Feature",
      "properties": {
        "hierarchy": [
          "tgn:7097793",
          "tgn:7003669",
          "tgn:1000003",
          "tgn:7000084",
          "tgn:7029392"
        ],
        "placetype": [
          "aat:300000206"
        ],
        "id": 7097793,
        "name:xx": "Sindelsberg"
      }
    },
    {
      "geometry": {
        "type": "Point",
        "coordinates": [
          11.366667,
          47.7
        ]
      },
      "type": "Feature",
      "properties": {
        "hierarchy": [
          "tgn:7097794",
          "tgn:7003669",
          "tgn:1000003",
          "tgn:7000084",
          "tgn:7029392"
        ],
        "placetype": [
          "aat:300008699"
        ],
        "id": 7097794,
        "name:xx": "Sindels-Bach"
      }
    },
    {
      "geometry": {
        "type": "Point",
        "coordinates": [
          9.616667,
          49.35
        ]
      },
      "type": "Feature",
      "properties": {
        "hierarchy": [
          "tgn:7097796",
          "tgn:7003692",
          "tgn:1000003",
          "tgn:7000084",
          "tgn:7029392"
        ],
        "placetype": [
          "aat:300008347"
        ],
        "id": 7097796,
        "name:xx": "Sindeldorf"
      }
    },
    {
      "geometry": {
        "type": "Point",
        "coordinates": [
          9.6,
          49.366667
        ]
      },
      "type": "Feature",
      "properties": {
        "hierarchy": [
          "tgn:7097797",
          "tgn:7003692",
          "tgn:1000003",
          "tgn:7000084",
          "tgn:7029392"
        ],
        "placetype": [
          "aat:300008699"
        ],
        "id": 7097797,
        "name:xx": "Sindelbach"
      }
    },
    {
      "geometry": {
        "type": "Point",
        "coordinates": [
          9.15,
          48.733333
        ]
      },
      "type": "Feature",
      "properties": {
        "hierarchy": [
          "tgn:7097798",
          "tgn:7003692",
          "tgn:1000003",
          "tgn:7000084",
          "tgn:7029392"
        ],
        "placetype": [
          "aat:300008699"
        ],
        "id": 7097798,
        "name:xx": "Sindelbach"
      }
    },
    {
      "geometry": {
        "type": "Point",
        "coordinates": [
          10.383333,
          49.066667
        ]
      },
      "type": "Feature",
      "properties": {
        "hierarchy": [
          "tgn:7097799",
          "tgn:7003669",
          "tgn:1000003",
          "tgn:7000084",
          "tgn:7029392"
        ],
        "placetype": [
          "aat:300008347"
        ],
        "id": 7097799,
        "name:xx": "Sinbronn"
      }
    }
  ]
}
