{
  "type": "FeatureCollection",
  "features": [
    {
      "geometry": {
        "type": "Point",
        "coordinates": [
          -0.3,
          53.25
        ]
      },
      "type": "Feature",
      "properties": {
        "hierarchy": [
          "tgn:7463070",
          "tgn:7002445",
          "tgn:1000003",
          "tgn:7008157",
          "tgn:7008591",
          "tgn:7029392"
        ],
        "placetype": [
          "aat:300008347"
        ],
        "name:en": "Kingthorpe",
        "id": 7463070
      }
    },
    {
      "geometry": {
        "type": "Point",
        "coordinates": [
          -0.25,
          51.316667
        ]
      },
      "type": "Feature",
      "properties": {
        "hierarchy": [
          "tgn:7463072",
          "tgn:7002445",
          "tgn:1000003",
          "tgn:7008175",
          "tgn:7008591",
          "tgn:7029392"
        ],
        "placetype": [
          "aat:300008347"
        ],
        "name:en": "Kingswood Warren",
        "id": 7463072
      }
    },
    {
      "geometry": {
        "type": "Point",
        "coordinates": [
          -0.2,
          51.266667
        ]
      },
      "type": "Feature",
      "properties": {
        "hierarchy": [
          "tgn:7463073",
          "tgn:7002445",
          "tgn:1000003",
          "tgn:7008175",
          "tgn:7008591",
          "tgn:7029392"
        ],
        "placetype": [
          "aat:300008347"
        ],
        "name:en": "Kingswood Manor",
        "id": 7463073
      }
    },
    {
      "geometry": {
        "type": "Point",
        "coordinates": [
          -1.716667,
          52.333333
        ]
      },
      "type": "Feature",
      "properties": {
        "hierarchy": [
          "tgn:7463074",
          "tgn:7002445",
          "tgn:1000003",
          "tgn:7008178",
          "tgn:7008591",
          "tgn:7029392"
        ],
        "placetype": [
          "aat:300008347"
        ],
        "name:en": "Kingswood",
        "id": 7463074
      }
    },
    {
      "geometry": {
        "type": "Point",
        "coordinates": [
          -2.367222,
          51.625833
        ]
      },
      "type": "Feature",
      "properties": {
        "hierarchy": [
          "tgn:7463075",
          "tgn:7002445",
          "tgn:1000003",
          "tgn:7008132",
          "tgn:7008591",
          "tgn:7029392"
        ],
        "placetype": [
          "aat:300008347"
        ],
        "name:en": "Kingswood",
        "id": 7463075
      }
    },
    {
      "geometry": {
        "type": "Point",
        "coordinates": [
          -2.508333,
          51.452778
        ]
      },
      "type": "Feature",
      "properties": {
        "hierarchy": [
          "tgn:7463076",
          "tgn:7002445",
          "tgn:1000003",
          "tgn:7019020",
          "tgn:7008591",
          "tgn:7029392"
        ],
        "placetype": [
          "aat:300008347"
        ],
        "name:en": "Kingswood",
        "id": 7463076
      }
    }
  ]
}
