{
  "geometry": {
    "type": "Point",
    "coordinates": [
      77.591624,
      30.9485
    ]
  },
  "type": "Feature",
  "properties": {
    "hierarchy": [
      "tgn:7551061",
      "tgn:1000004",
      "tgn:7000198",
      "tgn:1001996",
      "tgn:7029392"
    ],
    "placetype": [
      "aat:300008347"
    ],
    "name:en": "Chaupāl",
    "id": 7551061
  }
}
