{
  "geometry": {
    "type": "Point",
    "coordinates": [
      -111.5833,
      47.3333
    ]
  },
  "type": "Feature",
  "properties": {
    "hierarchy": [
      "tgn:2538120",
      "tgn:1000001",
      "tgn:2001266",
      "tgn:7012149",
      "tgn:7007524",
      "tgn:7029392"
    ],
    "placetype": [
      "aat:300008791"
    ],
    "id": 2538120,
    "name:xx": "Nelson Island"
  }
}
