{
  "geometry": {
    "type": "Point",
    "coordinates": [
      -80.85,
      36.2667
    ]
  },
  "type": "Feature",
  "properties": {
    "hierarchy": [
      "tgn:2314955",
      "tgn:1000001",
      "tgn:7012149",
      "tgn:2001542",
      "tgn:7007709",
      "tgn:7029392"
    ],
    "placetype": [
      "aat:300008347"
    ],
    "id": 2314955,
    "name:xx": "Elkin Valley"
  }
}
