{
  "geometry": {
    "type": "Point",
    "coordinates": [
      -121.9667,
      47.5333
    ]
  },
  "type": "Feature",
  "properties": {
    "hierarchy": [
      "tgn:2358430",
      "tgn:1000001",
      "tgn:7012149",
      "tgn:7018871",
      "tgn:7007920",
      "tgn:7029392"
    ],
    "placetype": [
      "aat:300266640"
    ],
    "id": 2358430,
    "name:xx": "Grand Ridge"
  }
}
