{
  "geometry": {
    "type": "Point",
    "coordinates": [
      -78.45,
      35.15
    ]
  },
  "type": "Feature",
  "properties": {
    "hierarchy": [
      "tgn:2665273",
      "tgn:1000001",
      "tgn:7012149",
      "tgn:2001538",
      "tgn:7007709",
      "tgn:7029392"
    ],
    "placetype": [
      "aat:300006191"
    ],
    "id": 2665273,
    "name:xx": "Sinclair Lake"
  }
}
