{
  "geometry": {
    "type": "Point",
    "coordinates": [
      12.65,
      37.7167
    ]
  },
  "type": "Feature",
  "properties": {
    "hierarchy": [
      "tgn:1043560",
      "tgn:1000003",
      "tgn:7003122",
      "tgn:1001762",
      "tgn:1000080",
      "tgn:7029392"
    ],
    "placetype": [
      "aat:300008347"
    ],
    "id": 1043560,
    "name:xx": "Borgata Costiera"
  }
}
