{
  "geometry": {
    "type": "Point",
    "coordinates": [
      13.35,
      48.55
    ]
  },
  "type": "Feature",
  "properties": {
    "hierarchy": [
      "tgn:7213618",
      "tgn:7003669",
      "tgn:1000003",
      "tgn:7000084",
      "tgn:7029392"
    ],
    "placetype": [
      "aat:300000206"
    ],
    "id": 7213618,
    "name:xx": "Bölln"
  }
}
