{
  "geometry": {
    "type": "Point",
    "coordinates": [
      69.740833,
      21.684167
    ]
  },
  "type": "Feature",
  "properties": {
    "hierarchy": [
      "tgn:7557440",
      "tgn:1000004",
      "tgn:1001869",
      "tgn:7000198",
      "tgn:7029392"
    ],
    "placetype": [
      "aat:300008347"
    ],
    "name:en": "Rānāvāv",
    "id": 7557440
  }
}
