{
  "geometry": {
    "type": "Point",
    "coordinates": [
      72.55,
      21.666667
    ]
  },
  "type": "Feature",
  "properties": {
    "hierarchy": [
      "tgn:7577849",
      "tgn:1000004",
      "tgn:1001869",
      "tgn:7000198",
      "tgn:7029392"
    ],
    "placetype": [
      "aat:300008347"
    ],
    "name:en": "Luhāra",
    "id": 7577849
  }
}
