{
  "geometry": {
    "type": "Point",
    "coordinates": [
      -84.0333,
      34.3833
    ]
  },
  "type": "Feature",
  "properties": {
    "hierarchy": [
      "tgn:2170763",
      "tgn:1000001",
      "tgn:7012149",
      "tgn:2000333",
      "tgn:7007248",
      "tgn:7029392"
    ],
    "placetype": [
      "aat:300008761"
    ],
    "id": 2170763,
    "name:xx": "Big Savannah"
  }
}
