{
  "geometry": {
    "type": "Point",
    "coordinates": [
      -117.05,
      48.5167
    ]
  },
  "type": "Feature",
  "properties": {
    "hierarchy": [
      "tgn:2483491",
      "tgn:1000001",
      "tgn:7012149",
      "tgn:2002248",
      "tgn:7007920",
      "tgn:7029392"
    ],
    "placetype": [
      "aat:300000390"
    ],
    "id": 2483491,
    "name:xx": "Last Chance Mine"
  }
}
