{
  "geometry": {
    "type": "Point",
    "coordinates": [
      -106.0667,
      39.3333
    ]
  },
  "type": "Feature",
  "properties": {
    "hierarchy": [
      "tgn:2603359",
      "tgn:1000001",
      "tgn:7012149",
      "tgn:2000238",
      "tgn:7007158",
      "tgn:7029392"
    ],
    "placetype": [
      "aat:300008347"
    ],
    "id": 2603359,
    "name:xx": "Quartzville"
  }
}
