{
  "geometry": {
    "type": "Point",
    "coordinates": [
      -108.7833,
      41.3333
    ]
  },
  "type": "Feature",
  "properties": {
    "hierarchy": [
      "tgn:2228689",
      "tgn:1000001",
      "tgn:7012149",
      "tgn:2002383",
      "tgn:7007923",
      "tgn:7029392"
    ],
    "placetype": [
      "aat:300008761"
    ],
    "id": 2228689,
    "name:xx": "Cedar Draw"
  }
}
