{
  "geometry": {
    "type": "Point",
    "coordinates": [
      134.45,
      16.2667
    ]
  },
  "type": "Feature",
  "properties": {
    "hierarchy": [
      "tgn:7024401",
      "tgn:7000490",
      "tgn:1000006",
      "tgn:7001829",
      "tgn:7029392"
    ],
    "placetype": [
      "aat:300008706"
    ],
    "id": 7024401,
    "name:xx": "Jiberu Creek"
  }
}
