{
  "geometry": {
    "type": "Point",
    "coordinates": [
      -68.3333,
      44.1833
    ]
  },
  "type": "Feature",
  "properties": {
    "hierarchy": [
      "tgn:2413114",
      "tgn:1000001",
      "tgn:2000922",
      "tgn:7012149",
      "tgn:7007515",
      "tgn:7029392"
    ],
    "placetype": [
      "aat:300132348"
    ],
    "id": 2413114,
    "name:xx": "Inner Dawes Ledge"
  }
}
