{
  "type": "FeatureCollection",
  "features": [
    {
      "geometry": {
        "type": "Point",
        "coordinates": [
          7.783333,
          52.066667
        ]
      },
      "type": "Feature",
      "properties": {
        "hierarchy": [
          "tgn:7203120",
          "tgn:1000003",
          "tgn:7003677",
          "tgn:7000084",
          "tgn:7029392"
        ],
        "placetype": [
          "aat:300387200"
        ],
        "id": 7203120,
        "name:xx": "Brock"
      }
    },
    {
      "geometry": {
        "type": "Point",
        "coordinates": [
          7.483333,
          51.9
        ]
      },
      "type": "Feature",
      "properties": {
        "hierarchy": [
          "tgn:7203121",
          "tgn:1000003",
          "tgn:7003677",
          "tgn:7000084",
          "tgn:7029392"
        ],
        "placetype": [
          "aat:300387200"
        ],
        "id": 7203121,
        "name:xx": "Brock"
      }
    },
    {
      "geometry": {
        "type": "Point",
        "coordinates": [
          8.233333,
          51.866667
        ]
      },
      "type": "Feature",
      "properties": {
        "hierarchy": [
          "tgn:7203123",
          "tgn:1000003",
          "tgn:7003677",
          "tgn:7000084",
          "tgn:7029392"
        ],
        "placetype": [
          "aat:300387200"
        ],
        "id": 7203123,
        "name:xx": "Brock"
      }
    },
    {
      "geometry": {
        "type": "Point",
        "coordinates": [
          7.783333,
          51.833333
        ]
      },
      "type": "Feature",
      "properties": {
        "hierarchy": [
          "tgn:7203124",
          "tgn:1000003",
          "tgn:7003677",
          "tgn:7000084",
          "tgn:7029392"
        ],
        "placetype": [
          "aat:300387200"
        ],
        "id": 7203124,
        "name:xx": "Brock"
      }
    },
    {
      "geometry": {
        "type": "Point",
        "coordinates": [
          7.866667,
          52.066667
        ]
      },
      "type": "Feature",
      "properties": {
        "hierarchy": [
          "tgn:7203125",
          "tgn:1000003",
          "tgn:7003677",
          "tgn:7000084",
          "tgn:7029392"
        ],
        "placetype": [
          "aat:300008347"
        ],
        "id": 7203125,
        "name:xx": "Brock"
      }
    },
    {
      "geometry": {
        "type": "Point",
        "coordinates": [
          7.2,
          52.05
        ]
      },
      "type": "Feature",
      "properties": {
        "hierarchy": [
          "tgn:7203126",
          "tgn:1000003",
          "tgn:7003677",
          "tgn:7000084",
          "tgn:7029392"
        ],
        "placetype": [
          "aat:300008347"
        ],
        "id": 7203126,
        "name:xx": "Brock"
      }
    },
    {
      "geometry": {
        "type": "Point",
        "coordinates": [
          9.883333,
          52.95
        ]
      },
      "type": "Feature",
      "properties": {
        "hierarchy": [
          "tgn:7203127",
          "tgn:1000003",
          "tgn:7003676",
          "tgn:7000084",
          "tgn:7029392"
        ],
        "placetype": [
          "aat:300055621"
        ],
        "id": 7203127,
        "name:xx": "Brock"
      }
    },
    {
      "geometry": {
        "type": "Point",
        "coordinates": [
          7.516667,
          51.766667
        ]
      },
      "type": "Feature",
      "properties": {
        "hierarchy": [
          "tgn:7203128",
          "tgn:1000003",
          "tgn:7003677",
          "tgn:7000084",
          "tgn:7029392"
        ],
        "placetype": [
          "aat:300387200"
        ],
        "id": 7203128,
        "name:xx": "Brochtrup"
      }
    },
    {
      "geometry": {
        "type": "Point",
        "coordinates": [
          7.533333,
          51.783333
        ]
      },
      "type": "Feature",
      "properties": {
        "hierarchy": [
          "tgn:7203129",
          "tgn:1000003",
          "tgn:7003677",
          "tgn:7000084",
          "tgn:7029392"
        ],
        "placetype": [
          "aat:300000206"
        ],
        "id": 7203129,
        "name:xx": "Brochtrup"
      }
    }
  ]
}
