{
  "geometry": {
    "type": "Point",
    "coordinates": [
      34.7333,
      30.4333
    ]
  },
  "type": "Feature",
  "properties": {
    "hierarchy": [
      "tgn:1103602",
      "tgn:1000861",
      "tgn:1000004",
      "tgn:1000119",
      "tgn:7029392"
    ],
    "placetype": [
      "aat:300008795"
    ],
    "id": 1103602,
    "name:xx": "ʻArif, Har"
  }
}
