{
  "geometry": {
    "type": "Point",
    "coordinates": [
      -82.4667,
      35.7667
    ]
  },
  "type": "Feature",
  "properties": {
    "hierarchy": [
      "tgn:2203659",
      "tgn:1000001",
      "tgn:2001473",
      "tgn:7012149",
      "tgn:7007709",
      "tgn:7029392"
    ],
    "placetype": [
      "aat:300008699"
    ],
    "id": 2203659,
    "name:xx": "Buckner Branch"
  }
}
