{
  "geometry": {
    "type": "Point",
    "coordinates": [
      114.2167,
      -26.4167
    ]
  },
  "type": "Feature",
  "properties": {
    "hierarchy": [
      "tgn:1097065",
      "tgn:7000490",
      "tgn:1000006",
      "tgn:7001834",
      "tgn:7029392"
    ],
    "placetype": [
      "aat:300008347"
    ],
    "id": 1097065,
    "name:xx": "Hamelin Pool"
  }
}
