{
  "geometry": {
    "type": "Point",
    "coordinates": [
      -91.1167,
      37.7333
    ]
  },
  "type": "Feature",
  "properties": {
    "hierarchy": [
      "tgn:2660211",
      "tgn:1000001",
      "tgn:7012149",
      "tgn:2001190",
      "tgn:7007523",
      "tgn:7029392"
    ],
    "placetype": [
      "aat:300008706"
    ],
    "id": 2660211,
    "name:xx": "Shoal Creek"
  }
}
