{
  "geometry": {
    "type": "Point",
    "coordinates": [
      -124.1333,
      41.65
    ]
  },
  "type": "Feature",
  "properties": {
    "hierarchy": [
      "tgn:2665993",
      "tgn:1000001",
      "tgn:7012149",
      "tgn:2000180",
      "tgn:7007157",
      "tgn:7029392"
    ],
    "placetype": [
      "aat:300008791"
    ],
    "id": 2665993,
    "name:xx": "Sister Rocks"
  }
}
