{
  "geometry": {
    "type": "Point",
    "coordinates": [
      37.6833,
      12.9667
    ]
  },
  "type": "Feature",
  "properties": {
    "hierarchy": [
      "tgn:1089764",
      "tgn:7001242",
      "tgn:1001267",
      "tgn:7000489",
      "tgn:7029392"
    ],
    "placetype": [
      "aat:300008347"
    ],
    "id": 1089764,
    "name:xx": "Dabat"
  }
}
