{
  "geometry": {
    "type": "Point",
    "coordinates": [
      -71.55,
      42.6167
    ]
  },
  "type": "Feature",
  "properties": {
    "hierarchy": [
      "tgn:2235642",
      "tgn:1000001",
      "tgn:1002665",
      "tgn:7012149",
      "tgn:7007517",
      "tgn:7029392"
    ],
    "placetype": [
      "aat:300008798"
    ],
    "id": 2235642,
    "name:xx": "Chestnut Hills"
  }
}
