{
  "geometry": {
    "type": "Point",
    "coordinates": [
      28.4667,
      53.6667
    ]
  },
  "type": "Feature",
  "properties": {
    "hierarchy": [
      "tgn:1051338",
      "tgn:1003391",
      "tgn:1000003",
      "tgn:7006657",
      "tgn:7029392"
    ],
    "placetype": [
      "aat:300008347"
    ],
    "id": 1051338,
    "name:xx": "Cherven"
  }
}
