{
  "geometry": {
    "type": "Point",
    "coordinates": [
      9.25,
      41.4833
    ]
  },
  "type": "Feature",
  "properties": {
    "hierarchy": [
      "tgn:1108327",
      "tgn:1000003",
      "tgn:7029392"
    ],
    "placetype": [
      "aat:300259572"
    ],
    "id": 1108327,
    "name:it": "Aresia, Col d'"
  }
}
