{
  "geometry": {
    "type": "Point",
    "coordinates": [
      -74.35,
      44.5333
    ]
  },
  "type": "Feature",
  "properties": {
    "hierarchy": [
      "tgn:2456715",
      "tgn:1000001",
      "tgn:7012149",
      "tgn:7013941",
      "tgn:7007568",
      "tgn:7029392"
    ],
    "placetype": [
      "aat:300008798"
    ],
    "id": 2456715,
    "name:xx": "Little Jennings Mountain"
  }
}
