{
  "geometry": {
    "type": "Point",
    "coordinates": [
      -37.5333,
      -11.7833
    ]
  },
  "type": "Feature",
  "properties": {
    "hierarchy": [
      "tgn:1125026",
      "tgn:1001834",
      "tgn:1000047",
      "tgn:7002455",
      "tgn:1000002",
      "tgn:7029392"
    ],
    "placetype": [
      "aat:300008707"
    ],
    "id": 1125026,
    "name:xx": "Itapicuru"
  }
}
