{
  "geometry": {
    "type": "Point",
    "coordinates": [
      -71.0167,
      41.8667
    ]
  },
  "type": "Feature",
  "properties": {
    "hierarchy": [
      "tgn:2617492",
      "tgn:1002201",
      "tgn:1000001",
      "tgn:7012149",
      "tgn:7007517",
      "tgn:7029392"
    ],
    "placetype": [
      "aat:300008680"
    ],
    "id": 2617492,
    "name:xx": "Richmond Pond"
  }
}
