{
  "geometry": {
    "type": "Point",
    "coordinates": [
      -87.1833,
      34.1667
    ]
  },
  "type": "Feature",
  "properties": {
    "hierarchy": [
      "tgn:2208600",
      "tgn:7002659",
      "tgn:1000001",
      "tgn:7012149",
      "tgn:2000066",
      "tgn:7029392"
    ],
    "placetype": [
      "aat:300008699"
    ],
    "id": 2208600,
    "name:xx": "Burns Branch"
  }
}
