{
  "geometry": {
    "type": "Point",
    "coordinates": [
      -5.35,
      36.1333
    ]
  },
  "type": "Feature",
  "properties": {
    "name:en": "Gibraltar",
    "name:xx": "Jabal Ṭāriq",
    "hierarchy": [
      "tgn:7005233",
      "tgn:1000003",
      "tgn:7029392"
    ],
    "placetype": [
      "aat:300387054",
      "aat:300235115",
      "aat:300387176",
      "aat:300008804"
    ],
    "name:it": "Gibilterra",
    "id": 7005233
  }
}
