{
  "geometry": {
    "type": "Point",
    "coordinates": [
      11.6833,
      -4.4167
    ]
  },
  "type": "Feature",
  "properties": {
    "hierarchy": [
      "tgn:1088648",
      "tgn:7001242",
      "tgn:1000996",
      "tgn:1000158",
      "tgn:7029392"
    ],
    "placetype": [
      "aat:300008347"
    ],
    "id": 1088648,
    "name:xx": "Kayes"
  }
}
