{
  "geometry": {
    "type": "Point",
    "coordinates": [
      -89.6333,
      46.35
    ]
  },
  "type": "Feature",
  "properties": {
    "hierarchy": [
      "tgn:2574558",
      "tgn:1000001",
      "tgn:7012149",
      "tgn:2000960",
      "tgn:7007520",
      "tgn:7029392"
    ],
    "placetype": [
      "aat:300008707"
    ],
    "id": 2574558,
    "name:xx": "Pelton River"
  }
}
