{
  "geometry": {
    "type": "Point",
    "coordinates": [
      -81.5833,
      36.0833
    ]
  },
  "type": "Feature",
  "properties": {
    "hierarchy": [
      "tgn:2272437",
      "tgn:1000001",
      "tgn:2001476",
      "tgn:7012149",
      "tgn:7007709",
      "tgn:7029392"
    ],
    "placetype": [
      "aat:300008798"
    ],
    "id": 2272437,
    "name:xx": "Curtis Knob"
  }
}
