{
  "geometry": {
    "type": "Point",
    "coordinates": [
      -7.841,
      37.028
    ]
  },
  "type": "Feature",
  "properties": {
    "hierarchy": [
      "tgn:7010977",
      "tgn:1000852",
      "tgn:1000003",
      "tgn:1000090",
      "tgn:7029392"
    ],
    "placetype": [
      "aat:300008347",
      "aat:300387218"
    ],
    "id": 7010977,
    "name:xx": "Olhão"
  }
}
