{
  "geometry": {
    "type": "Point",
    "coordinates": [
      -155.3833,
      60.7833
    ]
  },
  "type": "Feature",
  "properties": {
    "hierarchy": [
      "tgn:2703351",
      "tgn:7006450",
      "tgn:1000001",
      "tgn:7030517",
      "tgn:7012149",
      "tgn:7029392"
    ],
    "placetype": [
      "aat:300008706"
    ],
    "id": 2703351,
    "name:xx": "Summit Creek"
  }
}
