{
  "geometry": {
    "type": "Point",
    "coordinates": [
      -94.1167,
      46.9167
    ]
  },
  "type": "Feature",
  "properties": {
    "hierarchy": [
      "tgn:2183001",
      "tgn:1000001",
      "tgn:2001009",
      "tgn:7012149",
      "tgn:7007521",
      "tgn:7029392"
    ],
    "placetype": [
      "aat:300008680"
    ],
    "id": 2183001,
    "name:xx": "Blueberry Lake"
  }
}
