{
  "geometry": {
    "type": "Point",
    "coordinates": [
      -90.8667,
      46.3167
    ]
  },
  "type": "Feature",
  "properties": {
    "hierarchy": [
      "tgn:2746536",
      "tgn:2002306",
      "tgn:1000001",
      "tgn:7012149",
      "tgn:7007922",
      "tgn:7029392"
    ],
    "placetype": [
      "aat:300008706"
    ],
    "id": 2746536,
    "name:xx": "Waboo Creek"
  }
}
