{
  "geometry": {
    "type": "Point",
    "coordinates": [
      -116.7833,
      43.0333
    ]
  },
  "type": "Feature",
  "properties": {
    "hierarchy": [
      "tgn:2714994",
      "tgn:1000001",
      "tgn:7012149",
      "tgn:2000488",
      "tgn:7007250",
      "tgn:7029392"
    ],
    "placetype": [
      "aat:300008761"
    ],
    "id": 2714994,
    "name:xx": "Tennessee Gulch"
  }
}
