{
  "geometry": {
    "type": "Point",
    "coordinates": [
      19.2667,
      47.6167
    ]
  },
  "type": "Feature",
  "properties": {
    "hierarchy": [
      "tgn:1110466",
      "tgn:1000003",
      "tgn:1000431",
      "tgn:7006278",
      "tgn:7029392"
    ],
    "placetype": [
      "aat:300008777"
    ],
    "id": 1110466,
    "name:xx": "Gödöllői Dombság"
  }
}
