{
  "geometry": {
    "type": "Point",
    "coordinates": [
      -79.15,
      37.95
    ]
  },
  "type": "Feature",
  "properties": {
    "hierarchy": [
      "tgn:2440016",
      "tgn:2002142",
      "tgn:1000001",
      "tgn:7012149",
      "tgn:7007919",
      "tgn:7029392"
    ],
    "placetype": [
      "aat:300006191"
    ],
    "id": 2440016,
    "name:xx": "Kiwanis Lake"
  }
}
