{
  "type": "FeatureCollection",
  "features": [
    {
      "geometry": {
        "type": "Point",
        "coordinates": [
          -113.05,
          46.35
        ]
      },
      "type": "Feature",
      "properties": {
        "hierarchy": [
          "tgn:2358920",
          "tgn:1000001",
          "tgn:7012149",
          "tgn:2001279",
          "tgn:7007524",
          "tgn:7029392"
        ],
        "placetype": [
          "aat:300008706"
        ],
        "id": 2358920,
        "name:xx": "Granite Creek"
      }
    },
    {
      "geometry": {
        "type": "Point",
        "coordinates": [
          -113.3167,
          48.2167
        ]
      },
      "type": "Feature",
      "properties": {
        "hierarchy": [
          "tgn:2358921",
          "tgn:1000001",
          "tgn:7012149",
          "tgn:2001274",
          "tgn:7007524",
          "tgn:7029392"
        ],
        "placetype": [
          "aat:300008706"
        ],
        "id": 2358921,
        "name:xx": "Granite Creek"
      }
    },
    {
      "geometry": {
        "type": "Point",
        "coordinates": [
          -114.6333,
          46.65
        ]
      },
      "type": "Feature",
      "properties": {
        "hierarchy": [
          "tgn:2358922",
          "tgn:1000001",
          "tgn:7012149",
          "tgn:2001291",
          "tgn:7007524",
          "tgn:7029392"
        ],
        "placetype": [
          "aat:300008706"
        ],
        "id": 2358922,
        "name:xx": "Granite Creek"
      }
    },
    {
      "geometry": {
        "type": "Point",
        "coordinates": [
          -119.3667,
          40.7833
        ]
      },
      "type": "Feature",
      "properties": {
        "hierarchy": [
          "tgn:2358923",
          "tgn:1000001",
          "tgn:7012149",
          "tgn:7007526",
          "tgn:7029392"
        ],
        "placetype": [
          "aat:300008706"
        ],
        "id": 2358923,
        "name:xx": "Granite Creek"
      }
    },
    {
      "geometry": {
        "type": "Point",
        "coordinates": [
          -116.3,
          41.5167
        ]
      },
      "type": "Feature",
      "properties": {
        "hierarchy": [
          "tgn:2358924",
          "tgn:1000001",
          "tgn:2001411",
          "tgn:7012149",
          "tgn:7007526",
          "tgn:7029392"
        ],
        "placetype": [
          "aat:300008706"
        ],
        "id": 2358924,
        "name:xx": "Granite Creek"
      }
    },
    {
      "geometry": {
        "type": "Point",
        "coordinates": [
          -117.3,
          41.15
        ]
      },
      "type": "Feature",
      "properties": {
        "hierarchy": [
          "tgn:2358925",
          "tgn:1000001",
          "tgn:2001414",
          "tgn:7012149",
          "tgn:7007526",
          "tgn:7029392"
        ],
        "placetype": [
          "aat:300008706"
        ],
        "id": 2358925,
        "name:xx": "Granite Creek"
      }
    },
    {
      "geometry": {
        "type": "Point",
        "coordinates": [
          -123.7333,
          42.4167
        ]
      },
      "type": "Feature",
      "properties": {
        "hierarchy": [
          "tgn:2358926",
          "tgn:1000001",
          "tgn:7012149",
          "tgn:2001713",
          "tgn:7007708",
          "tgn:7029392"
        ],
        "placetype": [
          "aat:300008706"
        ],
        "id": 2358926,
        "name:xx": "Granite Creek"
      }
    },
    {
      "geometry": {
        "type": "Point",
        "coordinates": [
          -124.15,
          42.75
        ]
      },
      "type": "Feature",
      "properties": {
        "hierarchy": [
          "tgn:2358927",
          "tgn:1000001",
          "tgn:2001702",
          "tgn:7012149",
          "tgn:7007708",
          "tgn:7029392"
        ],
        "placetype": [
          "aat:300008706"
        ],
        "id": 2358927,
        "name:xx": "Granite Creek"
      }
    },
    {
      "geometry": {
        "type": "Point",
        "coordinates": [
          -122.9667,
          42.8167
        ]
      },
      "type": "Feature",
      "properties": {
        "hierarchy": [
          "tgn:2358928",
          "tgn:1000001",
          "tgn:7012149",
          "tgn:2001706",
          "tgn:7007708",
          "tgn:7029392"
        ],
        "placetype": [
          "aat:300008706"
        ],
        "id": 2358928,
        "name:xx": "Granite Creek"
      }
    },
    {
      "geometry": {
        "type": "Point",
        "coordinates": [
          -117.7333,
          42.9667
        ]
      },
      "type": "Feature",
      "properties": {
        "hierarchy": [
          "tgn:2358929",
          "tgn:1000001",
          "tgn:7012149",
          "tgn:2001718",
          "tgn:7007708",
          "tgn:7029392"
        ],
        "placetype": [
          "aat:300008706"
        ],
        "id": 2358929,
        "name:xx": "Granite Creek"
      }
    }
  ]
}
