{
  "geometry": {
    "type": "Point",
    "coordinates": [
      -90.7167,
      41.2333
    ]
  },
  "type": "Feature",
  "properties": {
    "hierarchy": [
      "tgn:2030308",
      "tgn:1000001",
      "tgn:7012149",
      "tgn:2000520",
      "tgn:7007251",
      "tgn:7029392"
    ],
    "placetype": [
      "aat:300008347",
      "aat:300387210"
    ],
    "id": 2030308,
    "name:xx": "Sugar Grove"
  }
}
