{
  "geometry": {
    "type": "Point",
    "coordinates": [
      -115.3833,
      35.2667
    ]
  },
  "type": "Feature",
  "properties": {
    "hierarchy": [
      "tgn:2635834",
      "tgn:1000001",
      "tgn:7012149",
      "tgn:7007157",
      "tgn:1002857",
      "tgn:7029392"
    ],
    "placetype": [
      "aat:300008697"
    ],
    "id": 2635834,
    "name:xx": "Sacaton Spring"
  }
}
