{
  "geometry": {
    "type": "Point",
    "coordinates": [
      74.526883,
      24.25617
    ]
  },
  "type": "Feature",
  "properties": {
    "hierarchy": [
      "tgn:7578967",
      "tgn:1000004",
      "tgn:7000198",
      "tgn:7016788",
      "tgn:7029392"
    ],
    "placetype": [
      "aat:300008347"
    ],
    "name:en": "Sītāmāta",
    "id": 7578967
  }
}
