{
  "geometry": {
    "type": "Point",
    "coordinates": [
      -69.0667,
      45.4833
    ]
  },
  "type": "Feature",
  "properties": {
    "hierarchy": [
      "tgn:2141760",
      "tgn:1000001",
      "tgn:7012149",
      "tgn:2000928",
      "tgn:7007515",
      "tgn:7029392"
    ],
    "placetype": [
      "aat:300008699"
    ],
    "id": 2141760,
    "name:xx": "Babel Brook"
  }
}
