{
  "geometry": {
    "type": "Point",
    "coordinates": [
      -105.6167,
      40.7667
    ]
  },
  "type": "Feature",
  "properties": {
    "hierarchy": [
      "tgn:7019211",
      "tgn:1000001",
      "tgn:7012149",
      "tgn:2000226",
      "tgn:7007158",
      "tgn:7029392"
    ],
    "placetype": [
      "aat:300008680",
      "aat:300006191"
    ],
    "id": 7019211,
    "name:xx": "Bellaire Lake"
  }
}
