{
  "geometry": {
    "type": "Point",
    "coordinates": [
      -97.7667,
      27.7833
    ]
  },
  "type": "Feature",
  "properties": {
    "hierarchy": [
      "tgn:1134170",
      "tgn:1000001",
      "tgn:7012149",
      "tgn:7007826",
      "tgn:7029392"
    ],
    "placetype": [
      "aat:300008706"
    ],
    "id": 1134170,
    "name:xx": "Petronila Creek"
  }
}
