{
  "geometry": {
    "type": "Point",
    "coordinates": [
      29.5667,
      2.9167
    ]
  },
  "type": "Feature",
  "properties": {
    "hierarchy": [
      "tgn:1088938",
      "tgn:7001242",
      "tgn:7016755",
      "tgn:1000159",
      "tgn:7029392"
    ],
    "placetype": [
      "aat:300008347"
    ],
    "id": 1088938,
    "name:xx": "Dubele"
  }
}
