{
  "geometry": {
    "type": "Point",
    "coordinates": [
      -94.7333,
      33.2667
    ]
  },
  "type": "Feature",
  "properties": {
    "hierarchy": [
      "tgn:2301255",
      "tgn:1000001",
      "tgn:7012149",
      "tgn:1002696",
      "tgn:7007826",
      "tgn:7029392"
    ],
    "placetype": [
      "aat:300008680"
    ],
    "id": 2301255,
    "name:xx": "Dunlap Lake"
  }
}
