{
  "geometry": {
    "type": "Point",
    "coordinates": [
      -86.2667,
      43.4833
    ]
  },
  "type": "Feature",
  "properties": {
    "hierarchy": [
      "tgn:2333344",
      "tgn:1000001",
      "tgn:7012149",
      "tgn:2000984",
      "tgn:7007520",
      "tgn:7029392"
    ],
    "placetype": [
      "aat:300008680"
    ],
    "id": 2333344,
    "name:xx": "Fogg Lake"
  }
}
