{
  "geometry": {
    "type": "Point",
    "coordinates": [
      -114.35,
      36.4833
    ]
  },
  "type": "Feature",
  "properties": {
    "hierarchy": [
      "tgn:2470838",
      "tgn:1000001",
      "tgn:2001410",
      "tgn:7012149",
      "tgn:7007526",
      "tgn:7029392"
    ],
    "placetype": [
      "aat:300132316"
    ],
    "id": 2470838,
    "name:xx": "Lost City Cove"
  }
}
