{
  "geometry": {
    "type": "Point",
    "coordinates": [
      -82.8167,
      35.3167
    ]
  },
  "type": "Feature",
  "properties": {
    "hierarchy": [
      "tgn:2235785",
      "tgn:1000001",
      "tgn:7012149",
      "tgn:7007709",
      "tgn:7029392"
    ],
    "placetype": [
      "aat:300266640"
    ],
    "id": 2235785,
    "name:xx": "Chestnut Ridge"
  }
}
