{
  "geometry": {
    "type": "Point",
    "coordinates": [
      -91.5667,
      37.4333
    ]
  },
  "type": "Feature",
  "properties": {
    "hierarchy": [
      "tgn:2548124",
      "tgn:1000001",
      "tgn:7012149",
      "tgn:7007523",
      "tgn:7029392"
    ],
    "placetype": [
      "aat:300008761"
    ],
    "id": 2548124,
    "name:xx": "North Hollow"
  }
}
