{
  "geometry": {
    "type": "Point",
    "coordinates": [
      -84.3167,
      36.35
    ]
  },
  "type": "Feature",
  "properties": {
    "hierarchy": [
      "tgn:2279963",
      "tgn:1000001",
      "tgn:7012149",
      "tgn:2001912",
      "tgn:7007825",
      "tgn:7029392"
    ],
    "placetype": [
      "aat:300000390"
    ],
    "id": 2279963,
    "name:xx": "Dean Mine"
  }
}
