{
  "geometry": {
    "type": "Point",
    "coordinates": [
      -124.0667,
      44.4333
    ]
  },
  "type": "Feature",
  "properties": {
    "hierarchy": [
      "tgn:2472106",
      "tgn:1000001",
      "tgn:7012149",
      "tgn:1002599",
      "tgn:7007708",
      "tgn:7029392"
    ],
    "placetype": [
      "aat:300008680"
    ],
    "id": 2472106,
    "name:xx": "Lotus Lake"
  }
}
