{
  "geometry": {
    "type": "Point",
    "coordinates": [
      177.75,
      -39.05
    ]
  },
  "type": "Feature",
  "properties": {
    "hierarchy": [
      "tgn:1099106",
      "tgn:7016670",
      "tgn:1008380",
      "tgn:1000226",
      "tgn:1000006",
      "tgn:7029392"
    ],
    "placetype": [
      "aat:300008347"
    ],
    "name:en": "Nuhaka",
    "id": 1099106
  }
}
