{
  "geometry": {
    "type": "Point",
    "coordinates": [
      41.6667,
      40.8167
    ]
  },
  "type": "Feature",
  "properties": {
    "hierarchy": [
      "tgn:1128083",
      "tgn:1000004",
      "tgn:1000144",
      "tgn:7029392"
    ],
    "placetype": [
      "aat:300008707"
    ],
    "id": 1128083,
    "name:xx": "Oltu Çayı"
  }
}
