{
  "geometry": {
    "type": "Point",
    "coordinates": [
      17.5333,
      -0.7167
    ]
  },
  "type": "Feature",
  "properties": {
    "hierarchy": [
      "tgn:1088671",
      "tgn:7001242",
      "tgn:1001001",
      "tgn:1000158",
      "tgn:7029392"
    ],
    "placetype": [
      "aat:300008347"
    ],
    "id": 1088671,
    "name:xx": "Liranga"
  }
}
