{
  "geometry": {
    "type": "Point",
    "coordinates": [
      28.003656,
      28.682428
    ]
  },
  "type": "Feature",
  "properties": {
    "hierarchy": [
      "tgn:7526308",
      "tgn:7001242",
      "tgn:7016833",
      "tgn:1001418",
      "tgn:7029392"
    ],
    "placetype": [
      "aat:300008749"
    ],
    "name:en": "Ţawīl, Al Minqār aţ",
    "id": 7526308
  }
}
