{
  "geometry": {
    "type": "Point",
    "coordinates": [
      -79.15,
      35.7667
    ]
  },
  "type": "Feature",
  "properties": {
    "hierarchy": [
      "tgn:2555365",
      "tgn:1000001",
      "tgn:2001480",
      "tgn:7012149",
      "tgn:7007709",
      "tgn:7029392"
    ],
    "placetype": [
      "aat:300006191"
    ],
    "id": 2555365,
    "name:xx": "Odell Pond"
  }
}
