{
  "geometry": {
    "type": "Point",
    "coordinates": [
      -96.2333,
      42.7167
    ]
  },
  "type": "Feature",
  "properties": {
    "hierarchy": [
      "tgn:2035235",
      "tgn:1000001",
      "tgn:7012149",
      "tgn:2000635",
      "tgn:7007253",
      "tgn:7029392"
    ],
    "placetype": [
      "aat:300008347"
    ],
    "id": 2035235,
    "name:xx": "Merrill"
  }
}
