{
  "geometry": {
    "type": "Point",
    "coordinates": [
      -111.0667,
      41.6833
    ]
  },
  "type": "Feature",
  "properties": {
    "hierarchy": [
      "tgn:2162910",
      "tgn:1000001",
      "tgn:7012149",
      "tgn:2002117",
      "tgn:7007827",
      "tgn:7029392"
    ],
    "placetype": [
      "aat:300000390"
    ],
    "id": 2162910,
    "name:xx": "Benjamin Mine"
  }
}
