{
  "geometry": {
    "type": "Point",
    "coordinates": [
      -71.3833,
      43.9833
    ]
  },
  "type": "Feature",
  "properties": {
    "hierarchy": [
      "tgn:2127972",
      "tgn:1000001",
      "tgn:7012149",
      "tgn:7007564",
      "tgn:7029392"
    ],
    "placetype": [
      "aat:300008761"
    ],
    "id": 2127972,
    "name:xx": "Albany Intervale"
  }
}
