{
  "geometry": {
    "type": "Point",
    "coordinates": [
      106.5833,
      10.75
    ]
  },
  "type": "Feature",
  "properties": {
    "hierarchy": [
      "tgn:1087040",
      "tgn:1000004",
      "tgn:7001063",
      "tgn:1000145",
      "tgn:7029392"
    ],
    "placetype": [
      "aat:300008347"
    ],
    "id": 1087040,
    "name:xx": "Ấp Tân Hòa"
  }
}
