{
  "geometry": {
    "type": "Point",
    "coordinates": [
      -105.2667,
      48.7833
    ]
  },
  "type": "Feature",
  "properties": {
    "hierarchy": [
      "tgn:2490962",
      "tgn:1000001",
      "tgn:2001269",
      "tgn:7012149",
      "tgn:7007524",
      "tgn:7029392"
    ],
    "placetype": [
      "aat:300008761"
    ],
    "id": 2490962,
    "name:xx": "Manternach Coulee"
  }
}
