{
  "geometry": {
    "type": "Point",
    "coordinates": [
      -76.6667,
      37.1833
    ]
  },
  "type": "Feature",
  "properties": {
    "hierarchy": [
      "tgn:2397121",
      "tgn:1000001",
      "tgn:7012149",
      "tgn:1002931",
      "tgn:7007919",
      "tgn:7029392"
    ],
    "placetype": [
      "aat:300008706"
    ],
    "id": 2397121,
    "name:xx": "Homewood Creek"
  }
}
