{
  "geometry": {
    "type": "Point",
    "coordinates": [
      25.7667,
      52.9833
    ]
  },
  "type": "Feature",
  "properties": {
    "hierarchy": [
      "tgn:1056403",
      "tgn:1003357",
      "tgn:1000003",
      "tgn:7006657",
      "tgn:7029392"
    ],
    "placetype": [
      "aat:300008347"
    ],
    "id": 1056403,
    "name:xx": "Lesnaya"
  }
}
