{
  "geometry": {
    "type": "Point",
    "coordinates": [
      -83.8333,
      30.8333
    ]
  },
  "type": "Feature",
  "properties": {
    "hierarchy": [
      "tgn:2143170",
      "tgn:1000001",
      "tgn:7012149",
      "tgn:7014371",
      "tgn:7007248",
      "tgn:7029392"
    ],
    "placetype": [
      "aat:300008699"
    ],
    "id": 2143170,
    "name:xx": "Bailey Branch"
  }
}
