{
  "type": "FeatureCollection",
  "features": [
    {
      "geometry": {
        "type": "Point",
        "coordinates": [
          7.8,
          47.833333
        ]
      },
      "type": "Feature",
      "properties": {
        "hierarchy": [
          "tgn:7123750",
          "tgn:7003692",
          "tgn:1000003",
          "tgn:7000084",
          "tgn:7029392"
        ],
        "placetype": [
          "aat:300008347"
        ],
        "id": 7123750,
        "name:xx": "Neuh채user"
      }
    },
    {
      "geometry": {
        "type": "Point",
        "coordinates": [
          12.466667,
          51.75
        ]
      },
      "type": "Feature",
      "properties": {
        "hierarchy": [
          "tgn:7123751",
          "tgn:1000003",
          "tgn:7003687",
          "tgn:7000084",
          "tgn:7029392"
        ],
        "placetype": [
          "aat:300000206"
        ],
        "id": 7123751,
        "name:xx": "Neuh채user"
      }
    },
    {
      "geometry": {
        "type": "Point",
        "coordinates": [
          12.066667,
          50.583333
        ]
      },
      "type": "Feature",
      "properties": {
        "hierarchy": [
          "tgn:7123752",
          "tgn:1000003",
          "tgn:7003689",
          "tgn:7000084",
          "tgn:7029392"
        ],
        "placetype": [
          "aat:300000206"
        ],
        "id": 7123752,
        "name:xx": "Neuh채user"
      }
    },
    {
      "geometry": {
        "type": "Point",
        "coordinates": [
          9.766667,
          48
        ]
      },
      "type": "Feature",
      "properties": {
        "hierarchy": [
          "tgn:7123753",
          "tgn:7003692",
          "tgn:1000003",
          "tgn:7000084",
          "tgn:7029392"
        ],
        "placetype": [
          "aat:300000206"
        ],
        "id": 7123753,
        "name:xx": "Neuhauser"
      }
    },
    {
      "geometry": {
        "type": "Point",
        "coordinates": [
          10.033333,
          47.983333
        ]
      },
      "type": "Feature",
      "properties": {
        "hierarchy": [
          "tgn:7123754",
          "tgn:7003692",
          "tgn:1000003",
          "tgn:7000084",
          "tgn:7029392"
        ],
        "placetype": [
          "aat:300000206"
        ],
        "id": 7123754,
        "name:xx": "Neuhauser"
      }
    },
    {
      "geometry": {
        "type": "Point",
        "coordinates": [
          9.883333,
          47.85
        ]
      },
      "type": "Feature",
      "properties": {
        "hierarchy": [
          "tgn:7123755",
          "tgn:7003692",
          "tgn:1000003",
          "tgn:7000084",
          "tgn:7029392"
        ],
        "placetype": [
          "aat:300000206"
        ],
        "id": 7123755,
        "name:xx": "Neuhauser"
      }
    },
    {
      "geometry": {
        "type": "Point",
        "coordinates": [
          9.433333,
          47.666667
        ]
      },
      "type": "Feature",
      "properties": {
        "hierarchy": [
          "tgn:7123756",
          "tgn:7003692",
          "tgn:1000003",
          "tgn:7000084",
          "tgn:7029392"
        ],
        "placetype": [
          "aat:300000206"
        ],
        "id": 7123756,
        "name:xx": "Neuh채user"
      }
    },
    {
      "geometry": {
        "type": "Point",
        "coordinates": [
          8.933333,
          47.966667
        ]
      },
      "type": "Feature",
      "properties": {
        "hierarchy": [
          "tgn:7123757",
          "tgn:7003692",
          "tgn:1000003",
          "tgn:7000084",
          "tgn:7029392"
        ],
        "placetype": [
          "aat:300008347"
        ],
        "id": 7123757,
        "name:xx": "Neuhausen"
      }
    },
    {
      "geometry": {
        "type": "Point",
        "coordinates": [
          9.283333,
          48.683333
        ]
      },
      "type": "Feature",
      "properties": {
        "hierarchy": [
          "tgn:7123758",
          "tgn:7003692",
          "tgn:1000003",
          "tgn:7000084",
          "tgn:7029392"
        ],
        "placetype": [
          "aat:300008347"
        ],
        "id": 7123758,
        "name:xx": "Neuhausen"
      }
    },
    {
      "geometry": {
        "type": "Point",
        "coordinates": [
          9.3,
          48.533333
        ]
      },
      "type": "Feature",
      "properties": {
        "hierarchy": [
          "tgn:7123759",
          "tgn:7003692",
          "tgn:1000003",
          "tgn:7000084",
          "tgn:7029392"
        ],
        "placetype": [
          "aat:300008347"
        ],
        "id": 7123759,
        "name:xx": "Neuhausen"
      }
    }
  ]
}
