{
  "geometry": {
    "type": "Point",
    "coordinates": [
      -76.45,
      44.3667
    ]
  },
  "type": "Feature",
  "properties": {
    "hierarchy": [
      "tgn:1115953",
      "tgn:7005685",
      "tgn:1000001",
      "tgn:7013154",
      "tgn:7029392"
    ],
    "placetype": [
      "aat:300008680"
    ],
    "id": 1115953,
    "name:xx": "Collins Lake"
  }
}
