{
  "geometry": {
    "type": "Point",
    "coordinates": [
      17.2833,
      49.4333
    ]
  },
  "type": "Feature",
  "properties": {
    "hierarchy": [
      "tgn:4011311",
      "tgn:7593917",
      "tgn:1000003",
      "tgn:1001780",
      "tgn:7029392"
    ],
    "placetype": [
      "aat:300008347"
    ],
    "id": 4011311,
    "name:xx": "Tovačov"
  }
}
