{
  "type": "FeatureCollection",
  "features": [
    {
      "geometry": {
        "type": "Point",
        "coordinates": [
          -99.8167,
          40.1333
        ]
      },
      "type": "Feature",
      "properties": {
        "hierarchy": [
          "tgn:2061942",
          "tgn:1000001",
          "tgn:2001348",
          "tgn:7012149",
          "tgn:7007525",
          "tgn:7029392"
        ],
        "placetype": [
          "aat:300008347"
        ],
        "id": 2061942,
        "name:xx": "Beaver City"
      }
    },
    {
      "geometry": {
        "type": "Point",
        "coordinates": [
          -97.2667,
          40.7667
        ]
      },
      "type": "Feature",
      "properties": {
        "hierarchy": [
          "tgn:2061943",
          "tgn:1000001",
          "tgn:7012149",
          "tgn:2001395",
          "tgn:7007525",
          "tgn:7029392"
        ],
        "placetype": [
          "aat:300008347"
        ],
        "id": 2061943,
        "name:xx": "Beaver Crossing"
      }
    },
    {
      "geometry": {
        "type": "Point",
        "coordinates": [
          -100.6833,
          41.1333
        ]
      },
      "type": "Feature",
      "properties": {
        "hierarchy": [
          "tgn:2061944",
          "tgn:1000001",
          "tgn:7012149",
          "tgn:2001371",
          "tgn:7007525",
          "tgn:7029392"
        ],
        "placetype": [
          "aat:300387016"
        ],
        "id": 2061944,
        "name:xx": "Beck"
      }
    },
    {
      "geometry": {
        "type": "Point",
        "coordinates": [
          -97.05,
          41
        ]
      },
      "type": "Feature",
      "properties": {
        "hierarchy": [
          "tgn:2061945",
          "tgn:1000001",
          "tgn:7012149",
          "tgn:2001395",
          "tgn:7007525",
          "tgn:7029392"
        ],
        "placetype": [
          "aat:300008347"
        ],
        "id": 2061945,
        "name:xx": "Bee"
      }
    },
    {
      "geometry": {
        "type": "Point",
        "coordinates": [
          -96.8,
          41.9167
        ]
      },
      "type": "Feature",
      "properties": {
        "hierarchy": [
          "tgn:2061946",
          "tgn:1000001",
          "tgn:2001335",
          "tgn:7012149",
          "tgn:7007525",
          "tgn:7029392"
        ],
        "placetype": [
          "aat:300008347"
        ],
        "id": 2061946,
        "name:xx": "Beemer"
      }
    },
    {
      "geometry": {
        "type": "Point",
        "coordinates": [
          -97.2,
          42.4
        ]
      },
      "type": "Feature",
      "properties": {
        "hierarchy": [
          "tgn:2061948",
          "tgn:1000001",
          "tgn:2001329",
          "tgn:7012149",
          "tgn:7007525",
          "tgn:7029392"
        ],
        "placetype": [
          "aat:300008347"
        ],
        "id": 2061948,
        "name:xx": "Belden"
      }
    },
    {
      "geometry": {
        "type": "Point",
        "coordinates": [
          -98.0667,
          41.4667
        ]
      },
      "type": "Feature",
      "properties": {
        "hierarchy": [
          "tgn:2061949",
          "tgn:1000001",
          "tgn:7012149",
          "tgn:2001378",
          "tgn:7007525",
          "tgn:7029392"
        ],
        "placetype": [
          "aat:300008347"
        ],
        "id": 2061949,
        "name:xx": "Belgrade"
      }
    }
  ]
}
