{
  "type": "FeatureCollection",
  "features": [
    {
      "geometry": {
        "type": "Point",
        "coordinates": [
          -70.816667,
          -34.6
        ]
      },
      "type": "Feature",
      "properties": {
        "hierarchy": [
          "tgn:7311650",
          "tgn:1001695",
          "tgn:1000049",
          "tgn:1000002",
          "tgn:7029392"
        ],
        "placetype": [
          "aat:300008795"
        ],
        "id": 7311650,
        "name:xx": "Las Placillas, Alto"
      }
    },
    {
      "geometry": {
        "type": "Point",
        "coordinates": [
          -71.616667,
          -37.95
        ]
      },
      "type": "Feature",
      "properties": {
        "hierarchy": [
          "tgn:7311651",
          "tgn:1001637",
          "tgn:1000049",
          "tgn:1000002",
          "tgn:7029392"
        ],
        "placetype": [
          "aat:300008795"
        ],
        "id": 7311651,
        "name:xx": "Las Placetas, Cordillera"
      }
    },
    {
      "geometry": {
        "type": "Point",
        "coordinates": [
          -71.666667,
          -35.266667
        ]
      },
      "type": "Feature",
      "properties": {
        "hierarchy": [
          "tgn:7311652",
          "tgn:1001705",
          "tgn:1000049",
          "tgn:1000002",
          "tgn:7029392"
        ],
        "placetype": [
          "aat:300008795"
        ],
        "id": 7311652,
        "name:xx": "Las Placetas, Cerro"
      }
    },
    {
      "geometry": {
        "type": "Point",
        "coordinates": [
          -69.8,
          -28.883333
        ]
      },
      "type": "Feature",
      "properties": {
        "hierarchy": [
          "tgn:7311653",
          "tgn:1001630",
          "tgn:1000049",
          "tgn:1000002",
          "tgn:7029392"
        ],
        "placetype": [
          "aat:300008795"
        ],
        "id": 7311653,
        "name:xx": "Las Placetas, Cerro"
      }
    },
    {
      "geometry": {
        "type": "Point",
        "coordinates": [
          -70.483333,
          -34.85
        ]
      },
      "type": "Feature",
      "properties": {
        "hierarchy": [
          "tgn:7311654",
          "tgn:1001695",
          "tgn:1000049",
          "tgn:1000002",
          "tgn:7029392"
        ],
        "placetype": [
          "aat:300008795"
        ],
        "id": 7311654,
        "name:xx": "Las Placetas, Alto de"
      }
    },
    {
      "geometry": {
        "type": "Point",
        "coordinates": [
          -71,
          -33.15
        ]
      },
      "type": "Feature",
      "properties": {
        "hierarchy": [
          "tgn:7311655",
          "tgn:1001708",
          "tgn:1000049",
          "tgn:1000002",
          "tgn:7029392"
        ],
        "placetype": [
          "aat:300387002"
        ],
        "id": 7311655,
        "name:xx": "Las Placetas"
      }
    },
    {
      "geometry": {
        "type": "Point",
        "coordinates": [
          -71.633333,
          -30.983333
        ]
      },
      "type": "Feature",
      "properties": {
        "hierarchy": [
          "tgn:7311656",
          "tgn:1001657",
          "tgn:1000049",
          "tgn:1000002",
          "tgn:7029392"
        ],
        "placetype": [
          "aat:300008347"
        ],
        "id": 7311656,
        "name:xx": "Las Placetas"
      }
    },
    {
      "geometry": {
        "type": "Point",
        "coordinates": [
          -71.083333,
          -34.683333
        ]
      },
      "type": "Feature",
      "properties": {
        "hierarchy": [
          "tgn:7311657",
          "tgn:1001695",
          "tgn:1000049",
          "tgn:1000002",
          "tgn:7029392"
        ],
        "placetype": [
          "aat:300387200"
        ],
        "id": 7311657,
        "name:xx": "Las Placetas"
      }
    },
    {
      "geometry": {
        "type": "Point",
        "coordinates": [
          -71.083333,
          -32.966667
        ]
      },
      "type": "Feature",
      "properties": {
        "hierarchy": [
          "tgn:7311658",
          "tgn:1001768",
          "tgn:1000049",
          "tgn:1000002",
          "tgn:7029392"
        ],
        "placetype": [
          "aat:300387200"
        ],
        "id": 7311658,
        "name:xx": "Las Placetas"
      }
    },
    {
      "geometry": {
        "type": "Point",
        "coordinates": [
          -70.666667,
          -33.083333
        ]
      },
      "type": "Feature",
      "properties": {
        "hierarchy": [
          "tgn:7311659",
          "tgn:1001708",
          "tgn:1000049",
          "tgn:1000002",
          "tgn:7029392"
        ],
        "placetype": [
          "aat:300008777"
        ],
        "id": 7311659,
        "name:xx": "Las Placetas"
      }
    }
  ]
}
