{
  "geometry": {
    "type": "Point",
    "coordinates": [
      -93.6833,
      43.8667
    ]
  },
  "type": "Feature",
  "properties": {
    "hierarchy": [
      "tgn:2260535",
      "tgn:1000001",
      "tgn:7012149",
      "tgn:2001079",
      "tgn:7007521",
      "tgn:7029392"
    ],
    "placetype": [
      "aat:300006075"
    ],
    "id": 2260535,
    "name:xx": "County Ditch Number Forty"
  }
}
