{
  "geometry": {
    "type": "Point",
    "coordinates": [
      -80.5167,
      36.5333
    ]
  },
  "type": "Feature",
  "properties": {
    "hierarchy": [
      "tgn:2293525",
      "tgn:1000001",
      "tgn:7012149",
      "tgn:7029392"
    ],
    "placetype": [
      "aat:300008699"
    ],
    "id": 2293525,
    "name:xx": "Double Spring Branch"
  }
}
