{
  "geometry": {
    "type": "Point",
    "coordinates": [
      -80.5833,
      27.1833
    ]
  },
  "type": "Feature",
  "properties": {
    "hierarchy": [
      "tgn:2018656",
      "tgn:1000001",
      "tgn:7012149",
      "tgn:1002641",
      "tgn:7007240",
      "tgn:7029392"
    ],
    "placetype": [
      "aat:300387016"
    ],
    "id": 2018656,
    "name:xx": "Bluefield"
  }
}
