{
  "geometry": {
    "type": "Point",
    "coordinates": [
      -77.1167,
      39.2667
    ]
  },
  "type": "Feature",
  "properties": {
    "hierarchy": [
      "tgn:2046006",
      "tgn:1000001",
      "tgn:1002488",
      "tgn:7012149",
      "tgn:7007516",
      "tgn:7029392"
    ],
    "placetype": [
      "aat:300008347",
      "aat:300387210"
    ],
    "id": 2046006,
    "name:xx": "Annapolis Rock"
  }
}
