{
  "geometry": {
    "type": "Point",
    "coordinates": [
      9.7667,
      -2.5333
    ]
  },
  "type": "Feature",
  "properties": {
    "hierarchy": [
      "tgn:1090057",
      "tgn:7001242",
      "tgn:1001729",
      "tgn:1000164",
      "tgn:7029392"
    ],
    "placetype": [
      "aat:300008347"
    ],
    "id": 1090057,
    "name:xx": "Setté Cama"
  }
}
