{
  "geometry": {
    "type": "Point",
    "coordinates": [
      -88.15,
      42.3333
    ]
  },
  "type": "Feature",
  "properties": {
    "hierarchy": [
      "tgn:2327919",
      "tgn:1000001",
      "tgn:7012149",
      "tgn:7013855",
      "tgn:7007251",
      "tgn:7029392"
    ],
    "placetype": [
      "aat:300008680"
    ],
    "id": 2327919,
    "name:xx": "Fish Lake"
  }
}
