{
  "geometry": {
    "type": "Point",
    "coordinates": [
      33.983674,
      28.347171
    ]
  },
  "type": "Feature",
  "properties": {
    "hierarchy": [
      "tgn:7543936",
      "tgn:7001242",
      "tgn:7016833",
      "tgn:7001336",
      "tgn:7029392"
    ],
    "placetype": [
      "aat:300379998"
    ],
    "name:en": "Rimḩān, Wādī",
    "id": 7543936
  }
}
