{
  "geometry": {
    "type": "Point",
    "coordinates": [
      -111.8167,
      40.7667
    ]
  },
  "type": "Feature",
  "properties": {
    "hierarchy": [
      "tgn:2230943",
      "tgn:1000001",
      "tgn:7012149",
      "tgn:2002118",
      "tgn:7007827",
      "tgn:7029392"
    ],
    "placetype": [
      "aat:300008761"
    ],
    "id": 2230943,
    "name:xx": "Cephalopod Gulch"
  }
}
