{
  "geometry": {
    "type": "Point",
    "coordinates": [
      -94.25,
      30.7833
    ]
  },
  "type": "Feature",
  "properties": {
    "hierarchy": [
      "tgn:2607933",
      "tgn:1000001",
      "tgn:7012149",
      "tgn:1002959",
      "tgn:7007826",
      "tgn:7029392"
    ],
    "placetype": [
      "aat:300008699"
    ],
    "id": 2607933,
    "name:xx": "Ratcliff Branch"
  }
}
