{
  "geometry": {
    "type": "Point",
    "coordinates": [
      -75.1167,
      39.8667
    ]
  },
  "type": "Feature",
  "properties": {
    "hierarchy": [
      "tgn:2064214",
      "tgn:1002227",
      "tgn:1000001",
      "tgn:7012149",
      "tgn:7007565",
      "tgn:7029392"
    ],
    "placetype": [
      "aat:300008347"
    ],
    "id": 2064214,
    "name:xx": "Brooklawn"
  }
}
