{
  "type": "FeatureCollection",
  "features": [
    {
      "geometry": {
        "type": "Point",
        "coordinates": [
          -85.35,
          31.4333
        ]
      },
      "type": "Feature",
      "properties": {
        "hierarchy": [
          "tgn:2216160",
          "tgn:7002659",
          "tgn:1000001",
          "tgn:7012149",
          "tgn:7029392"
        ],
        "placetype": [
          "aat:300008699"
        ],
        "id": 2216160,
        "name:xx": "Camp Branch"
      }
    },
    {
      "geometry": {
        "type": "Point",
        "coordinates": [
          -87.1833,
          32.75
        ]
      },
      "type": "Feature",
      "properties": {
        "hierarchy": [
          "tgn:2216161",
          "tgn:7002659",
          "tgn:1000001",
          "tgn:7012149",
          "tgn:2000052",
          "tgn:7029392"
        ],
        "placetype": [
          "aat:300008699"
        ],
        "id": 2216161,
        "name:xx": "Camp Branch"
      }
    },
    {
      "geometry": {
        "type": "Point",
        "coordinates": [
          -86.4833,
          33
        ]
      },
      "type": "Feature",
      "properties": {
        "hierarchy": [
          "tgn:2216162",
          "tgn:7002659",
          "tgn:1000001",
          "tgn:2000018",
          "tgn:7012149",
          "tgn:7029392"
        ],
        "placetype": [
          "aat:300008699"
        ],
        "id": 2216162,
        "name:xx": "Camp Branch"
      }
    },
    {
      "geometry": {
        "type": "Point",
        "coordinates": [
          -86.7333,
          33.2333
        ]
      },
      "type": "Feature",
      "properties": {
        "hierarchy": [
          "tgn:2216163",
          "tgn:7002659",
          "tgn:1000001",
          "tgn:7012149",
          "tgn:2000058",
          "tgn:7029392"
        ],
        "placetype": [
          "aat:300008699"
        ],
        "id": 2216163,
        "name:xx": "Camp Branch"
      }
    },
    {
      "geometry": {
        "type": "Point",
        "coordinates": [
          -88,
          33.9833
        ]
      },
      "type": "Feature",
      "properties": {
        "hierarchy": [
          "tgn:2216164",
          "tgn:7002659",
          "tgn:1000001",
          "tgn:7012149",
          "tgn:2000037",
          "tgn:7029392"
        ],
        "placetype": [
          "aat:300008699"
        ],
        "id": 2216164,
        "name:xx": "Camp Branch"
      }
    },
    {
      "geometry": {
        "type": "Point",
        "coordinates": [
          -85.8667,
          31.5667
        ]
      },
      "type": "Feature",
      "properties": {
        "hierarchy": [
          "tgn:2216165",
          "tgn:7002659",
          "tgn:1000001",
          "tgn:2000015",
          "tgn:7012149",
          "tgn:7029392"
        ],
        "placetype": [
          "aat:300008699"
        ],
        "id": 2216165,
        "name:xx": "Camp Branch"
      }
    },
    {
      "geometry": {
        "type": "Point",
        "coordinates": [
          -87.0167,
          32.8667
        ]
      },
      "type": "Feature",
      "properties": {
        "hierarchy": [
          "tgn:2216166",
          "tgn:7002659",
          "tgn:1000001",
          "tgn:2000003",
          "tgn:7012149",
          "tgn:7029392"
        ],
        "placetype": [
          "aat:300008699"
        ],
        "id": 2216166,
        "name:xx": "Camp Branch"
      }
    },
    {
      "geometry": {
        "type": "Point",
        "coordinates": [
          -86.75,
          33.2
        ]
      },
      "type": "Feature",
      "properties": {
        "hierarchy": [
          "tgn:2216167",
          "tgn:7002659",
          "tgn:1000001",
          "tgn:7012149",
          "tgn:2000058",
          "tgn:7029392"
        ],
        "placetype": [
          "aat:300008347"
        ],
        "id": 2216167,
        "name:xx": "Camp Branch"
      }
    },
    {
      "geometry": {
        "type": "Point",
        "coordinates": [
          -91.9333,
          35.4167
        ]
      },
      "type": "Feature",
      "properties": {
        "hierarchy": [
          "tgn:2216168",
          "tgn:1000001",
          "tgn:7016172",
          "tgn:2000116",
          "tgn:7012149",
          "tgn:7029392"
        ],
        "placetype": [
          "aat:300008699"
        ],
        "id": 2216168,
        "name:xx": "Camp Branch"
      }
    },
    {
      "geometry": {
        "type": "Point",
        "coordinates": [
          -91.3333,
          36.1667
        ]
      },
      "type": "Feature",
      "properties": {
        "hierarchy": [
          "tgn:2216169",
          "tgn:1000001",
          "tgn:7016172",
          "tgn:7012149",
          "tgn:2000142",
          "tgn:7029392"
        ],
        "placetype": [
          "aat:300008699"
        ],
        "id": 2216169,
        "name:xx": "Camp Branch"
      }
    }
  ]
}
