{
  "geometry": {
    "type": "Point",
    "coordinates": [
      -114.9833,
      47.0333
    ]
  },
  "type": "Feature",
  "properties": {
    "hierarchy": [
      "tgn:2301361",
      "tgn:1000001",
      "tgn:7012149",
      "tgn:2001290",
      "tgn:7007524",
      "tgn:7029392"
    ],
    "placetype": [
      "aat:300008706"
    ],
    "id": 2301361,
    "name:xx": "Dunn Creek"
  }
}
