{
  "type": "FeatureCollection",
  "features": [
    {
      "geometry": {
        "type": "Point",
        "coordinates": [
          7.45,
          50.9
        ]
      },
      "type": "Feature",
      "properties": {
        "hierarchy": [
          "tgn:7117580",
          "tgn:1000003",
          "tgn:7003677",
          "tgn:7000084",
          "tgn:7029392"
        ],
        "placetype": [
          "aat:300000206"
        ],
        "id": 7117580,
        "name:xx": "Ophausen"
      }
    },
    {
      "geometry": {
        "type": "Point",
        "coordinates": [
          7.6,
          51.716667
        ]
      },
      "type": "Feature",
      "properties": {
        "hierarchy": [
          "tgn:7117581",
          "tgn:1000003",
          "tgn:7003677",
          "tgn:7000084",
          "tgn:7029392"
        ],
        "placetype": [
          "aat:300000206"
        ],
        "id": 7117581,
        "name:xx": "Ophaus"
      }
    },
    {
      "geometry": {
        "type": "Point",
        "coordinates": [
          9.8,
          48.283333
        ]
      },
      "type": "Feature",
      "properties": {
        "hierarchy": [
          "tgn:7117582",
          "tgn:7003692",
          "tgn:1000003",
          "tgn:7000084",
          "tgn:7029392"
        ],
        "placetype": [
          "aat:300008347"
        ],
        "id": 7117582,
        "name:xx": "Öpfingen"
      }
    },
    {
      "geometry": {
        "type": "Point",
        "coordinates": [
          7.716667,
          48
        ]
      },
      "type": "Feature",
      "properties": {
        "hierarchy": [
          "tgn:7117583",
          "tgn:7003692",
          "tgn:1000003",
          "tgn:7000084",
          "tgn:7029392"
        ],
        "placetype": [
          "aat:300008347"
        ],
        "id": 7117583,
        "name:xx": "Opfingen"
      }
    },
    {
      "geometry": {
        "type": "Point",
        "coordinates": [
          10.183333,
          48.416667
        ]
      },
      "type": "Feature",
      "properties": {
        "hierarchy": [
          "tgn:7117584",
          "tgn:7003669",
          "tgn:1000003",
          "tgn:7000084",
          "tgn:7029392"
        ],
        "placetype": [
          "aat:300008347"
        ],
        "id": 7117584,
        "name:xx": "Opferstetten"
      }
    },
    {
      "geometry": {
        "type": "Point",
        "coordinates": [
          8.716667,
          51.083333
        ]
      },
      "type": "Feature",
      "properties": {
        "hierarchy": [
          "tgn:7117585",
          "tgn:1000003",
          "tgn:7003678",
          "tgn:7000084",
          "tgn:7029392"
        ],
        "placetype": [
          "aat:300008777"
        ],
        "id": 7117585,
        "name:xx": "Opfermanns Kopf"
      }
    },
    {
      "geometry": {
        "type": "Point",
        "coordinates": [
          8.5,
          47.866667
        ]
      },
      "type": "Feature",
      "properties": {
        "hierarchy": [
          "tgn:7117586",
          "tgn:7003692",
          "tgn:1000003",
          "tgn:7000084",
          "tgn:7029392"
        ],
        "placetype": [
          "aat:300008347"
        ],
        "id": 7117586,
        "name:xx": "Opferdingen"
      }
    },
    {
      "geometry": {
        "type": "Point",
        "coordinates": [
          9.1,
          51.283333
        ]
      },
      "type": "Feature",
      "properties": {
        "hierarchy": [
          "tgn:7117587",
          "tgn:1000003",
          "tgn:7003678",
          "tgn:7000084",
          "tgn:7029392"
        ],
        "placetype": [
          "aat:300008777"
        ],
        "id": 7117587,
        "name:xx": "Opfer-Berg"
      }
    },
    {
      "geometry": {
        "type": "Point",
        "coordinates": [
          10.066667,
          49.933333
        ]
      },
      "type": "Feature",
      "properties": {
        "hierarchy": [
          "tgn:7117588",
          "tgn:7003669",
          "tgn:1000003",
          "tgn:7000084",
          "tgn:7029392"
        ],
        "placetype": [
          "aat:300008347"
        ],
        "id": 7117588,
        "name:xx": "Opferbaum"
      }
    },
    {
      "geometry": {
        "type": "Point",
        "coordinates": [
          10.583333,
          49.05
        ]
      },
      "type": "Feature",
      "properties": {
        "hierarchy": [
          "tgn:7117589",
          "tgn:7003669",
          "tgn:1000003",
          "tgn:7000084",
          "tgn:7029392"
        ],
        "placetype": [
          "aat:300008347"
        ],
        "id": 7117589,
        "name:xx": "Opfenried"
      }
    }
  ]
}
