{
  "geometry": {
    "type": "Point",
    "coordinates": [
      -75.8167,
      42.0833
    ]
  },
  "type": "Feature",
  "properties": {
    "hierarchy": [
      "tgn:2069202",
      "tgn:1000001",
      "tgn:1002206",
      "tgn:7012149",
      "tgn:7007568",
      "tgn:7029392"
    ],
    "placetype": [
      "aat:300008347"
    ],
    "id": 2069202,
    "name:xx": "Fivemile Point"
  }
}
