{
  "geometry": {
    "type": "Point",
    "coordinates": [
      79.53115,
      26.861977
    ]
  },
  "type": "Feature",
  "properties": {
    "hierarchy": [
      "tgn:7564952",
      "tgn:1000004",
      "tgn:7000198",
      "tgn:7016722",
      "tgn:7029392"
    ],
    "placetype": [
      "aat:300008347"
    ],
    "name:en": "Sabhād",
    "id": 7564952
  }
}
