{
  "geometry": {
    "type": "Point",
    "coordinates": [
      -79.1667,
      41.45
    ]
  },
  "type": "Feature",
  "properties": {
    "hierarchy": [
      "tgn:2772411",
      "tgn:1000001",
      "tgn:7012149",
      "tgn:1002378",
      "tgn:7007710",
      "tgn:7029392"
    ],
    "placetype": [
      "aat:300008347"
    ],
    "id": 2772411,
    "name:xx": "Williams"
  }
}
