{
  "type": "FeatureCollection",
  "features": [
    {
      "geometry": {
        "type": "Point",
        "coordinates": [
          -77.5333,
          38.7167
        ]
      },
      "type": "Feature",
      "properties": {
        "hierarchy": [
          "tgn:2110806",
          "tgn:1000001",
          "tgn:7012149",
          "tgn:7015778",
          "tgn:7007919",
          "tgn:7029392"
        ],
        "placetype": [
          "aat:300008347"
        ],
        "id": 2110806,
        "name:xx": "Bristow"
      }
    },
    {
      "geometry": {
        "type": "Point",
        "coordinates": [
          -77.6833,
          39.25
        ]
      },
      "type": "Feature",
      "properties": {
        "hierarchy": [
          "tgn:2110807",
          "tgn:1000001",
          "tgn:7012149",
          "tgn:7015770",
          "tgn:7007919",
          "tgn:7029392"
        ],
        "placetype": [
          "aat:300008347",
          "aat:300387210"
        ],
        "id": 2110807,
        "name:xx": "Britain"
      }
    },
    {
      "geometry": {
        "type": "Point",
        "coordinates": [
          -81.6667,
          36.9167
        ]
      },
      "type": "Feature",
      "properties": {
        "hierarchy": [
          "tgn:2110809",
          "tgn:1000001",
          "tgn:7012149",
          "tgn:2002191",
          "tgn:7007919",
          "tgn:7029392"
        ],
        "placetype": [
          "aat:300008347"
        ],
        "id": 2110809,
        "name:xx": "Broadford"
      }
    }
  ]
}
