{
  "geometry": {
    "type": "Point",
    "coordinates": [
      105.2333,
      15.2333
    ]
  },
  "type": "Feature",
  "properties": {
    "hierarchy": [
      "tgn:1085633",
      "tgn:7005193",
      "tgn:1000004",
      "tgn:7000974",
      "tgn:1000142",
      "tgn:7029392"
    ],
    "placetype": [
      "aat:300008347"
    ],
    "id": 1085633,
    "name:xx": "Phibun Mangsahan"
  }
}
