{
  "geometry": {
    "type": "Point",
    "coordinates": [
      -109.7333,
      44.3667
    ]
  },
  "type": "Feature",
  "properties": {
    "hierarchy": [
      "tgn:2154749",
      "tgn:1000001",
      "tgn:7012149",
      "tgn:2002379",
      "tgn:7007923",
      "tgn:7029392"
    ],
    "placetype": [
      "aat:300008761"
    ],
    "id": 2154749,
    "name:xx": "Bear Gulch"
  }
}
