{
  "geometry": {
    "type": "Point",
    "coordinates": [
      -81.4667,
      34.45
    ]
  },
  "type": "Feature",
  "properties": {
    "hierarchy": [
      "tgn:2700374",
      "tgn:1000001",
      "tgn:7012149",
      "tgn:2001760",
      "tgn:7007712",
      "tgn:7029392"
    ],
    "placetype": [
      "aat:300008706"
    ],
    "id": 2700374,
    "name:xx": "Subers Creek"
  }
}
