{
  "geometry": {
    "type": "Point",
    "coordinates": [
      -81.0833,
      39.3833
    ]
  },
  "type": "Feature",
  "properties": {
    "hierarchy": [
      "tgn:2324293",
      "tgn:1000001",
      "tgn:7012149",
      "tgn:2002286",
      "tgn:7013961",
      "tgn:7029392"
    ],
    "placetype": [
      "aat:300266640"
    ],
    "id": 2324293,
    "name:xx": "Federal Ridge"
  }
}
