{
  "geometry": {
    "type": "Point",
    "coordinates": [
      -94.2167,
      30.9333
    ]
  },
  "type": "Feature",
  "properties": {
    "hierarchy": [
      "tgn:2730832",
      "tgn:1000001",
      "tgn:7012149",
      "tgn:2002009",
      "tgn:7007826",
      "tgn:7029392"
    ],
    "placetype": [
      "aat:300008680"
    ],
    "id": 2730832,
    "name:xx": "Tub Lake"
  }
}
