{
  "geometry": {
    "type": "Point",
    "coordinates": [
      -88.3833,
      35.5333
    ]
  },
  "type": "Feature",
  "properties": {
    "hierarchy": [
      "tgn:2230485",
      "tgn:1000001",
      "tgn:7012149",
      "tgn:2001875",
      "tgn:7007825",
      "tgn:7029392"
    ],
    "placetype": [
      "aat:300008347"
    ],
    "id": 2230485,
    "name:xx": "Center Hill"
  }
}
