{
  "geometry": {
    "type": "Point",
    "coordinates": [
      34.681944,
      29.710833
    ]
  },
  "type": "Feature",
  "properties": {
    "hierarchy": [
      "tgn:7522187",
      "tgn:7001242",
      "tgn:7016833",
      "tgn:7001335",
      "tgn:7029392"
    ],
    "placetype": [
      "aat:300379998"
    ],
    "name:en": "Abū Rumaythá, Wādī",
    "id": 7522187
  }
}
