{
  "geometry": {
    "type": "Point",
    "coordinates": [
      19.962,
      42.906
    ]
  },
  "type": "Feature",
  "properties": {
    "hierarchy": [
      "tgn:7593975",
      "tgn:1000003",
      "tgn:7015657",
      "tgn:7029392"
    ],
    "placetype": [
      "aat:300387064",
      "aat:300265612"
    ],
    "id": 7593975,
    "name:xx": "Petnjica"
  }
}
