{
  "geometry": {
    "type": "Point",
    "coordinates": [
      9.15,
      52.983333
    ]
  },
  "type": "Feature",
  "properties": {
    "hierarchy": [
      "tgn:7191097",
      "tgn:1000003",
      "tgn:7003676",
      "tgn:7000084",
      "tgn:7029392"
    ],
    "placetype": [
      "aat:300000206"
    ],
    "id": 7191097,
    "name:xx": "Försten"
  }
}
