{
  "geometry": {
    "type": "Point",
    "coordinates": [
      -87.1333,
      41.5333
    ]
  },
  "type": "Feature",
  "properties": {
    "hierarchy": [
      "tgn:2033722",
      "tgn:1000001",
      "tgn:7012149",
      "tgn:1002798",
      "tgn:7007252",
      "tgn:7029392"
    ],
    "placetype": [
      "aat:300008347"
    ],
    "id": 2033722,
    "name:xx": "South Haven"
  }
}
