{
  "type": "FeatureCollection",
  "features": [
    {
      "geometry": {
        "type": "Point",
        "coordinates": [
          -85.0333,
          34.4
        ]
      },
      "type": "Feature",
      "properties": {
        "hierarchy": [
          "tgn:2023940",
          "tgn:1000001",
          "tgn:7012149",
          "tgn:2000355",
          "tgn:7007248",
          "tgn:7029392"
        ],
        "placetype": [
          "aat:300008347"
        ],
        "id": 2023940,
        "name:xx": "Plainville"
      }
    },
    {
      "geometry": {
        "type": "Point",
        "coordinates": [
          -84.4833,
          32.8
        ]
      },
      "type": "Feature",
      "properties": {
        "hierarchy": [
          "tgn:2023942",
          "tgn:1000001",
          "tgn:7012149",
          "tgn:2000421",
          "tgn:7007248",
          "tgn:7029392"
        ],
        "placetype": [
          "aat:300008347"
        ],
        "id": 2023942,
        "name:xx": "Pleasant Hill"
      }
    },
    {
      "geometry": {
        "type": "Point",
        "coordinates": [
          -84.1167,
          33.9333
        ]
      },
      "type": "Feature",
      "properties": {
        "hierarchy": [
          "tgn:2023943",
          "tgn:1000001",
          "tgn:7012149",
          "tgn:2000358",
          "tgn:7007248",
          "tgn:7029392"
        ],
        "placetype": [
          "aat:300008347"
        ],
        "id": 2023943,
        "name:xx": "Pleasant Hill"
      }
    },
    {
      "geometry": {
        "type": "Point",
        "coordinates": [
          -84.4,
          31.8667
        ]
      },
      "type": "Feature",
      "properties": {
        "hierarchy": [
          "tgn:2023944",
          "tgn:1000001",
          "tgn:7012149",
          "tgn:2000426",
          "tgn:7007248",
          "tgn:7029392"
        ],
        "placetype": [
          "aat:300008347",
          "aat:300387210"
        ],
        "id": 2023944,
        "name:xx": "Pleasant Hill"
      }
    },
    {
      "geometry": {
        "type": "Point",
        "coordinates": [
          -84.85,
          34.3333
        ]
      },
      "type": "Feature",
      "properties": {
        "hierarchy": [
          "tgn:2023945",
          "tgn:1000001",
          "tgn:2000299",
          "tgn:7012149",
          "tgn:7007248",
          "tgn:7029392"
        ],
        "placetype": [
          "aat:300008347",
          "aat:300387210"
        ],
        "id": 2023945,
        "name:xx": "Pleasant Valley"
      }
    },
    {
      "geometry": {
        "type": "Point",
        "coordinates": [
          -83.2833,
          34.1833
        ]
      },
      "type": "Feature",
      "properties": {
        "hierarchy": [
          "tgn:2023947",
          "tgn:1000001",
          "tgn:7012149",
          "tgn:2000388",
          "tgn:7007248",
          "tgn:7029392"
        ],
        "placetype": [
          "aat:300008347"
        ],
        "id": 2023947,
        "name:xx": "Pocataligo"
      }
    },
    {
      "geometry": {
        "type": "Point",
        "coordinates": [
          -83,
          33.9833
        ]
      },
      "type": "Feature",
      "properties": {
        "hierarchy": [
          "tgn:2023948",
          "tgn:1000001",
          "tgn:7012149",
          "tgn:2000400",
          "tgn:7007248",
          "tgn:7029392"
        ],
        "placetype": [
          "aat:300008347"
        ],
        "id": 2023948,
        "name:xx": "Point Peter"
      }
    }
  ]
}
