{
  "type": "FeatureCollection",
  "features": [
    {
      "geometry": {
        "type": "Point",
        "coordinates": [
          -70.733333,
          -27.4
        ]
      },
      "type": "Feature",
      "properties": {
        "hierarchy": [
          "tgn:7275830",
          "tgn:1001630",
          "tgn:1000049",
          "tgn:1000002",
          "tgn:7029392"
        ],
        "placetype": [
          "aat:300008777"
        ],
        "id": 7275830,
        "name:xx": "Totoralillo, Cerro"
      }
    },
    {
      "geometry": {
        "type": "Point",
        "coordinates": [
          -71.333333,
          -29.483333
        ]
      },
      "type": "Feature",
      "properties": {
        "hierarchy": [
          "tgn:7275831",
          "tgn:1001657",
          "tgn:1000049",
          "tgn:1000002",
          "tgn:7029392"
        ],
        "placetype": [
          "aat:300132316"
        ],
        "id": 7275831,
        "name:xx": "Totoralillo, Caleta"
      }
    },
    {
      "geometry": {
        "type": "Point",
        "coordinates": [
          -70.816667,
          -26.866667
        ]
      },
      "type": "Feature",
      "properties": {
        "hierarchy": [
          "tgn:7275832",
          "tgn:1001630",
          "tgn:1000049",
          "tgn:1000002",
          "tgn:7029392"
        ],
        "placetype": [
          "aat:300132316"
        ],
        "id": 7275832,
        "name:xx": "Totoralillo, Bahía"
      }
    },
    {
      "geometry": {
        "type": "Point",
        "coordinates": [
          -70.25,
          -27.6
        ]
      },
      "type": "Feature",
      "properties": {
        "hierarchy": [
          "tgn:7275833",
          "tgn:1001630",
          "tgn:1000049",
          "tgn:1000002",
          "tgn:7029392"
        ],
        "placetype": [
          "aat:300007783"
        ],
        "id": 7275833,
        "name:xx": "Totoralillo"
      }
    },
    {
      "geometry": {
        "type": "Point",
        "coordinates": [
          -71.533333,
          -32.033333
        ]
      },
      "type": "Feature",
      "properties": {
        "hierarchy": [
          "tgn:7275834",
          "tgn:1001657",
          "tgn:1000049",
          "tgn:1000002",
          "tgn:7029392"
        ],
        "placetype": [
          "aat:300008347"
        ],
        "id": 7275834,
        "name:xx": "Totoralillo"
      }
    },
    {
      "geometry": {
        "type": "Point",
        "coordinates": [
          -71.375,
          -30.066667
        ]
      },
      "type": "Feature",
      "properties": {
        "hierarchy": [
          "tgn:7275835",
          "tgn:1001657",
          "tgn:1000049",
          "tgn:1000002",
          "tgn:7029392"
        ],
        "placetype": [
          "aat:300008347"
        ],
        "id": 7275835,
        "name:xx": "Totoralillo"
      }
    },
    {
      "geometry": {
        "type": "Point",
        "coordinates": [
          -71.300278,
          -29.515
        ]
      },
      "type": "Feature",
      "properties": {
        "hierarchy": [
          "tgn:7275836",
          "tgn:1001657",
          "tgn:1000049",
          "tgn:1000002",
          "tgn:7029392"
        ],
        "placetype": [
          "aat:300008347"
        ],
        "id": 7275836,
        "name:xx": "Totoralillo"
      }
    },
    {
      "geometry": {
        "type": "Point",
        "coordinates": [
          -72.466667,
          -43.2
        ]
      },
      "type": "Feature",
      "properties": {
        "hierarchy": [
          "tgn:7275837",
          "tgn:1001699",
          "tgn:1000049",
          "tgn:1000002",
          "tgn:7029392"
        ],
        "placetype": [
          "aat:300387200"
        ],
        "id": 7275837,
        "name:xx": "Totorales"
      }
    },
    {
      "geometry": {
        "type": "Point",
        "coordinates": [
          -71.676389,
          -30.363056
        ]
      },
      "type": "Feature",
      "properties": {
        "hierarchy": [
          "tgn:7275838",
          "tgn:1001657",
          "tgn:1000049",
          "tgn:1000002",
          "tgn:7029392"
        ],
        "placetype": [
          "aat:300132316"
        ],
        "id": 7275838,
        "name:xx": "Totoral de Lengua de Vaca, Caleta"
      }
    },
    {
      "geometry": {
        "type": "Point",
        "coordinates": [
          -71.1,
          -27.816667
        ]
      },
      "type": "Feature",
      "properties": {
        "hierarchy": [
          "tgn:7275839",
          "tgn:1001630",
          "tgn:1000049",
          "tgn:1000002",
          "tgn:7029392"
        ],
        "placetype": [
          "aat:300132317"
        ],
        "id": 7275839,
        "name:xx": "Totoral Bajo, Caleta"
      }
    }
  ]
}
