{
  "geometry": {
    "type": "Point",
    "coordinates": [
      -83.5833,
      32.0833
    ]
  },
  "type": "Feature",
  "properties": {
    "hierarchy": [
      "tgn:2329429",
      "tgn:1000001",
      "tgn:7012149",
      "tgn:2000447",
      "tgn:7007248",
      "tgn:7029392"
    ],
    "placetype": [
      "aat:300008347"
    ],
    "id": 2329429,
    "name:xx": "Five Points"
  }
}
