{
  "geometry": {
    "type": "Point",
    "coordinates": [
      4.35,
      52.05
    ]
  },
  "type": "Feature",
  "properties": {
    "hierarchy": [
      "tgn:7267873",
      "tgn:1000003",
      "tgn:7003632",
      "tgn:7016845",
      "tgn:7029392"
    ],
    "placetype": [
      "aat:300006075"
    ],
    "name:nl": "Rijn-Schiekanaal",
    "id": 7267873
  }
}
