{
  "geometry": {
    "type": "Point",
    "coordinates": [
      79.2495,
      24.7526
    ]
  },
  "type": "Feature",
  "properties": {
    "hierarchy": [
      "tgn:7565352",
      "tgn:1000004",
      "tgn:7000198",
      "tgn:1001894",
      "tgn:7029392"
    ],
    "placetype": [
      "aat:300008347"
    ],
    "name:en": "Hīrāpur",
    "id": 7565352
  }
}
