{
  "geometry": {
    "type": "Point",
    "coordinates": [
      -105.5167,
      36.2333
    ]
  },
  "type": "Feature",
  "properties": {
    "hierarchy": [
      "tgn:2478850",
      "tgn:1000001",
      "tgn:7012149",
      "tgn:2001457",
      "tgn:7007566",
      "tgn:7029392"
    ],
    "placetype": [
      "aat:300266640"
    ],
    "id": 2478850,
    "name:xx": "Maestas Ridge"
  }
}
