{
  "geometry": {
    "type": "Point",
    "coordinates": [
      -95.45,
      33.6333
    ]
  },
  "type": "Feature",
  "properties": {
    "hierarchy": [
      "tgn:2460527",
      "tgn:1000001",
      "tgn:7012149",
      "tgn:2002024",
      "tgn:7007826",
      "tgn:7029392"
    ],
    "placetype": [
      "aat:300008706"
    ],
    "id": 2460527,
    "name:xx": "Little Sandy Creek"
  }
}
