{
  "geometry": {
    "type": "Point",
    "coordinates": [
      -89.6833,
      29.4833
    ]
  },
  "type": "Feature",
  "properties": {
    "hierarchy": [
      "tgn:2538564",
      "tgn:1000001",
      "tgn:7012149",
      "tgn:2000891",
      "tgn:7007256",
      "tgn:7029392"
    ],
    "placetype": [
      "aat:300006075"
    ],
    "id": 2538564,
    "name:xx": "Nestor Canal"
  }
}
