{
  "geometry": {
    "type": "Point",
    "coordinates": [
      33.550464,
      31.061598
    ]
  },
  "type": "Feature",
  "properties": {
    "hierarchy": [
      "tgn:7536313",
      "tgn:7001242",
      "tgn:7016833",
      "tgn:7001335",
      "tgn:7029392"
    ],
    "placetype": [
      "aat:300055621"
    ],
    "name:en": "Ghurfân el- Gimâl",
    "id": 7536313
  }
}
