{
  "type": "FeatureCollection",
  "features": [
    {
      "geometry": {
        "type": "Point",
        "coordinates": [
          -123.6667,
          42.9833
        ]
      },
      "type": "Feature",
      "properties": {
        "hierarchy": [
          "tgn:2277950",
          "tgn:1000001",
          "tgn:7012149",
          "tgn:2001706",
          "tgn:7007708",
          "tgn:7029392"
        ],
        "placetype": [
          "aat:300008706"
        ],
        "id": 2277950,
        "name:xx": "Day Creek"
      }
    },
    {
      "geometry": {
        "type": "Point",
        "coordinates": [
          -122.6333,
          43.5667
        ]
      },
      "type": "Feature",
      "properties": {
        "hierarchy": [
          "tgn:2277951",
          "tgn:1000001",
          "tgn:7012149",
          "tgn:2001716",
          "tgn:7007708",
          "tgn:7029392"
        ],
        "placetype": [
          "aat:300008706"
        ],
        "id": 2277951,
        "name:xx": "Day Creek"
      }
    },
    {
      "geometry": {
        "type": "Point",
        "coordinates": [
          -103.3167,
          43.1333
        ]
      },
      "type": "Feature",
      "properties": {
        "hierarchy": [
          "tgn:2277952",
          "tgn:1000001",
          "tgn:2001793",
          "tgn:7012149",
          "tgn:7007713",
          "tgn:7029392"
        ],
        "placetype": [
          "aat:300008706"
        ],
        "id": 2277952,
        "name:xx": "Day Creek"
      }
    },
    {
      "geometry": {
        "type": "Point",
        "coordinates": [
          -79.7833,
          37.4
        ]
      },
      "type": "Feature",
      "properties": {
        "hierarchy": [
          "tgn:2277953",
          "tgn:1000001",
          "tgn:2002144",
          "tgn:7012149",
          "tgn:7007919",
          "tgn:7029392"
        ],
        "placetype": [
          "aat:300008706"
        ],
        "id": 2277953,
        "name:xx": "Day Creek"
      }
    },
    {
      "geometry": {
        "type": "Point",
        "coordinates": [
          -118.5333,
          48.9333
        ]
      },
      "type": "Feature",
      "properties": {
        "hierarchy": [
          "tgn:2277954",
          "tgn:1000001",
          "tgn:2002243",
          "tgn:7012149",
          "tgn:7007920",
          "tgn:7029392"
        ],
        "placetype": [
          "aat:300008706"
        ],
        "id": 2277954,
        "name:xx": "Day Creek"
      }
    },
    {
      "geometry": {
        "type": "Point",
        "coordinates": [
          -122.5167,
          45.9833
        ]
      },
      "type": "Feature",
      "properties": {
        "hierarchy": [
          "tgn:2277955",
          "tgn:1000001",
          "tgn:1002305",
          "tgn:7012149",
          "tgn:7007920",
          "tgn:7029392"
        ],
        "placetype": [
          "aat:300008706"
        ],
        "id": 2277955,
        "name:xx": "Day Creek"
      }
    },
    {
      "geometry": {
        "type": "Point",
        "coordinates": [
          -121.35,
          48.5333
        ]
      },
      "type": "Feature",
      "properties": {
        "hierarchy": [
          "tgn:2277956",
          "tgn:1000001",
          "tgn:7012149",
          "tgn:7014510",
          "tgn:7007920",
          "tgn:7029392"
        ],
        "placetype": [
          "aat:300008706"
        ],
        "id": 2277956,
        "name:xx": "Day Creek"
      }
    },
    {
      "geometry": {
        "type": "Point",
        "coordinates": [
          -90.7,
          43.4167
        ]
      },
      "type": "Feature",
      "properties": {
        "hierarchy": [
          "tgn:2277957",
          "tgn:1000001",
          "tgn:7012149",
          "tgn:2002358",
          "tgn:7007922",
          "tgn:7029392"
        ],
        "placetype": [
          "aat:300008706"
        ],
        "id": 2277957,
        "name:xx": "Day Creek"
      }
    },
    {
      "geometry": {
        "type": "Point",
        "coordinates": [
          -113.0833,
          47
        ]
      },
      "type": "Feature",
      "properties": {
        "hierarchy": [
          "tgn:2277958",
          "tgn:1000001",
          "tgn:7012149",
          "tgn:2001298",
          "tgn:7007524",
          "tgn:7029392"
        ],
        "placetype": [
          "aat:300006075"
        ],
        "id": 2277958,
        "name:xx": "Day Ditch"
      }
    },
    {
      "geometry": {
        "type": "Point",
        "coordinates": [
          -124.0333,
          44.45
        ]
      },
      "type": "Feature",
      "properties": {
        "hierarchy": [
          "tgn:2277959",
          "tgn:1000001",
          "tgn:7012149",
          "tgn:1002599",
          "tgn:7007708",
          "tgn:7029392"
        ],
        "placetype": [
          "aat:300006075"
        ],
        "id": 2277959,
        "name:xx": "Day Drainage Ditch"
      }
    }
  ]
}
