{
  "type": "FeatureCollection",
  "features": [
    {
      "geometry": {
        "type": "Point",
        "coordinates": [
          -77.5,
          59.6333
        ]
      },
      "type": "Feature",
      "properties": {
        "hierarchy": [
          "tgn:1125651",
          "tgn:7005685",
          "tgn:1000001",
          "tgn:7005804",
          "tgn:7029392"
        ],
        "placetype": [
          "aat:300008707"
        ],
        "id": 1125651,
        "name:xx": "Kogaluc River"
      }
    },
    {
      "geometry": {
        "type": "Point",
        "coordinates": [
          -61.7333,
          56.2
        ]
      },
      "type": "Feature",
      "properties": {
        "hierarchy": [
          "tgn:1125652",
          "tgn:7005685",
          "tgn:1000001",
          "tgn:7005801",
          "tgn:7029392"
        ],
        "placetype": [
          "aat:300008707"
        ],
        "id": 1125652,
        "name:xx": "Kogaluk"
      }
    },
    {
      "geometry": {
        "type": "Point",
        "coordinates": [
          29.6667,
          45.8333
        ]
      },
      "type": "Feature",
      "properties": {
        "hierarchy": [
          "tgn:1125653",
          "tgn:1000003",
          "tgn:7029392"
        ],
        "placetype": [
          "aat:300008707"
        ],
        "name:ro": "Kogilnik",
        "id": 1125653,
        "name:xx": "Kogil'nik"
      }
    },
    {
      "geometry": {
        "type": "Point",
        "coordinates": [
          -14.7,
          11.0167
        ]
      },
      "type": "Feature",
      "properties": {
        "hierarchy": [
          "tgn:1125654",
          "tgn:7001242",
          "tgn:1000167",
          "tgn:7029392"
        ],
        "placetype": [
          "aat:300008707"
        ],
        "id": 1125654,
        "name:xx": "Kogon"
      }
    },
    {
      "geometry": {
        "type": "Point",
        "coordinates": [
          71.8,
          33.4
        ]
      },
      "type": "Feature",
      "properties": {
        "hierarchy": [
          "tgn:1125655",
          "tgn:1000004",
          "tgn:1000133",
          "tgn:7029392"
        ],
        "placetype": [
          "aat:300008707"
        ],
        "id": 1125655,
        "name:xx": "Kohāt Toi"
      }
    },
    {
      "geometry": {
        "type": "Point",
        "coordinates": [
          139.8667,
          35.35
        ]
      },
      "type": "Feature",
      "properties": {
        "hierarchy": [
          "tgn:1125656",
          "tgn:1000971",
          "tgn:1000004",
          "tgn:7000894",
          "tgn:1000120",
          "tgn:7029392"
        ],
        "placetype": [
          "aat:300008707"
        ],
        "id": 1125656,
        "name:xx": "Koito-gawa"
      }
    },
    {
      "geometry": {
        "type": "Point",
        "coordinates": [
          61.2167,
          25.5667
        ]
      },
      "type": "Feature",
      "properties": {
        "hierarchy": [
          "tgn:1125657",
          "tgn:1000004",
          "tgn:7002176",
          "tgn:7000231",
          "tgn:7029392"
        ],
        "placetype": [
          "aat:300008707"
        ],
        "id": 1125657,
        "name:xx": "Kojā"
      }
    },
    {
      "geometry": {
        "type": "Point",
        "coordinates": [
          140.1333,
          35.8667
        ]
      },
      "type": "Feature",
      "properties": {
        "hierarchy": [
          "tgn:1125659",
          "tgn:1000004",
          "tgn:7000894",
          "tgn:1000120",
          "tgn:7029392"
        ],
        "placetype": [
          "aat:300008707"
        ],
        "id": 1125659,
        "name:xx": "Kokai-gawa"
      }
    }
  ]
}
