{
  "type": "FeatureCollection",
  "features": [
    {
      "geometry": {
        "type": "Point",
        "coordinates": [
          -92.4333,
          45.4333
        ]
      },
      "type": "Feature",
      "properties": {
        "hierarchy": [
          "tgn:2513660",
          "tgn:1000001",
          "tgn:7012149",
          "tgn:2002346",
          "tgn:7007922",
          "tgn:7029392"
        ],
        "placetype": [
          "aat:300008680"
        ],
        "id": 2513660,
        "name:xx": "Mill Pond"
      }
    },
    {
      "geometry": {
        "type": "Point",
        "coordinates": [
          -91.9833,
          45.6333
        ]
      },
      "type": "Feature",
      "properties": {
        "hierarchy": [
          "tgn:2513661",
          "tgn:1000001",
          "tgn:7012149",
          "tgn:2002360",
          "tgn:7007922",
          "tgn:7029392"
        ],
        "placetype": [
          "aat:300008680"
        ],
        "id": 2513661,
        "name:xx": "Mill Pond"
      }
    },
    {
      "geometry": {
        "type": "Point",
        "coordinates": [
          -90.5333,
          45.9167
        ]
      },
      "type": "Feature",
      "properties": {
        "hierarchy": [
          "tgn:2513662",
          "tgn:1000001",
          "tgn:7012149",
          "tgn:2002348",
          "tgn:7007922",
          "tgn:7029392"
        ],
        "placetype": [
          "aat:300008680"
        ],
        "id": 2513662,
        "name:xx": "Mill Pond"
      }
    },
    {
      "geometry": {
        "type": "Point",
        "coordinates": [
          -89.1667,
          42.5
        ]
      },
      "type": "Feature",
      "properties": {
        "hierarchy": [
          "tgn:2513663",
          "tgn:1000001",
          "tgn:7012149",
          "tgn:7014350",
          "tgn:7007922",
          "tgn:7029392"
        ],
        "placetype": [
          "aat:300006191"
        ],
        "id": 2513663,
        "name:xx": "Mill Pond"
      }
    },
    {
      "geometry": {
        "type": "Point",
        "coordinates": [
          -89,
          43.3333
        ]
      },
      "type": "Feature",
      "properties": {
        "hierarchy": [
          "tgn:2513664",
          "tgn:1000001",
          "tgn:7012149",
          "tgn:7007922",
          "tgn:7029392"
        ],
        "placetype": [
          "aat:300006191"
        ],
        "id": 2513664,
        "name:xx": "Mill Pond"
      }
    },
    {
      "geometry": {
        "type": "Point",
        "coordinates": [
          -89,
          44.2167
        ]
      },
      "type": "Feature",
      "properties": {
        "hierarchy": [
          "tgn:2513665",
          "tgn:1000001",
          "tgn:7012149",
          "tgn:2002362",
          "tgn:7007922",
          "tgn:7029392"
        ],
        "placetype": [
          "aat:300006191"
        ],
        "id": 2513665,
        "name:xx": "Mill Pond"
      }
    },
    {
      "geometry": {
        "type": "Point",
        "coordinates": [
          -92.6667,
          45.0167
        ]
      },
      "type": "Feature",
      "properties": {
        "hierarchy": [
          "tgn:2513666",
          "tgn:1000001",
          "tgn:7012149",
          "tgn:2002351",
          "tgn:7007922",
          "tgn:7029392"
        ],
        "placetype": [
          "aat:300006191"
        ],
        "id": 2513666,
        "name:xx": "Mill Pond"
      }
    },
    {
      "geometry": {
        "type": "Point",
        "coordinates": [
          -91.6833,
          36.4
        ]
      },
      "type": "Feature",
      "properties": {
        "hierarchy": [
          "tgn:2513668",
          "tgn:1000001",
          "tgn:7016172",
          "tgn:7012149",
          "tgn:2000129",
          "tgn:7029392"
        ],
        "placetype": [
          "aat:300008699"
        ],
        "id": 2513668,
        "name:xx": "Mill Pond Branch"
      }
    },
    {
      "geometry": {
        "type": "Point",
        "coordinates": [
          -84.8167,
          30.3167
        ]
      },
      "type": "Feature",
      "properties": {
        "hierarchy": [
          "tgn:2513669",
          "tgn:1000001",
          "tgn:7012149",
          "tgn:2000278",
          "tgn:7007240",
          "tgn:7029392"
        ],
        "placetype": [
          "aat:300008699"
        ],
        "id": 2513669,
        "name:xx": "Mill Pond Branch"
      }
    }
  ]
}
