{
  "type": "FeatureCollection",
  "features": [
    {
      "geometry": {
        "type": "Point",
        "coordinates": [
          16.5833,
          47
        ]
      },
      "type": "Feature",
      "properties": {
        "hierarchy": [
          "tgn:1128651",
          "tgn:1000003",
          "tgn:7029392"
        ],
        "placetype": [
          "aat:300008707"
        ],
        "name:hu": "Pinka",
        "id": 1128651,
        "name:de": "Pinka"
      }
    },
    {
      "geometry": {
        "type": "Point",
        "coordinates": [
          -0.4833,
          51.5167
        ]
      },
      "type": "Feature",
      "properties": {
        "hierarchy": [
          "tgn:1128652",
          "tgn:7002445",
          "tgn:1000003",
          "tgn:7008136",
          "tgn:7008591",
          "tgn:7029392"
        ],
        "placetype": [
          "aat:300008707"
        ],
        "id": 1128652,
        "name:xx": "Pinn"
      }
    },
    {
      "geometry": {
        "type": "Point",
        "coordinates": [
          -50.2667,
          -13.55
        ]
      },
      "type": "Feature",
      "properties": {
        "hierarchy": [
          "tgn:1128654",
          "tgn:7012827",
          "tgn:7002454",
          "tgn:1000047",
          "tgn:1000002",
          "tgn:7029392"
        ],
        "placetype": [
          "aat:300008707"
        ],
        "id": 1128654,
        "name:xx": "Pintado"
      }
    },
    {
      "geometry": {
        "type": "Point",
        "coordinates": [
          -70.3,
          -46.5833
        ]
      },
      "type": "Feature",
      "properties": {
        "hierarchy": [
          "tgn:1128656",
          "tgn:7006477",
          "tgn:1001522",
          "tgn:1000002",
          "tgn:7029392"
        ],
        "placetype": [
          "aat:300008707"
        ],
        "id": 1128656,
        "name:xx": "Pinturas, Río"
      }
    },
    {
      "geometry": {
        "type": "Point",
        "coordinates": [
          -63.5,
          -3.3833
        ]
      },
      "type": "Feature",
      "properties": {
        "hierarchy": [
          "tgn:1128657",
          "tgn:1001826",
          "tgn:1000047",
          "tgn:7002456",
          "tgn:1000002",
          "tgn:7029392"
        ],
        "placetype": [
          "aat:300008707"
        ],
        "id": 1128657,
        "name:xx": "Piorini"
      }
    },
    {
      "geometry": {
        "type": "Point",
        "coordinates": [
          -100.75,
          49.7
        ]
      },
      "type": "Feature",
      "properties": {
        "hierarchy": [
          "tgn:1128658",
          "tgn:7005685",
          "tgn:1000001",
          "tgn:7013154",
          "tgn:7029392"
        ],
        "placetype": [
          "aat:300008707"
        ],
        "id": 1128658,
        "name:xx": "Pipestone Creek"
      }
    },
    {
      "geometry": {
        "type": "Point",
        "coordinates": [
          22.8,
          7.45
        ]
      },
      "type": "Feature",
      "properties": {
        "hierarchy": [
          "tgn:1128659",
          "tgn:7001242",
          "tgn:1000982",
          "tgn:1000155",
          "tgn:7029392"
        ],
        "placetype": [
          "aat:300008707"
        ],
        "id": 1128659,
        "name:xx": "Pipi"
      }
    }
  ]
}
