{
  "type": "FeatureCollection",
  "features": [
    {
      "geometry": {
        "type": "Point",
        "coordinates": [
          -119.55,
          37.1667
        ]
      },
      "type": "Feature",
      "properties": {
        "hierarchy": [
          "tgn:2327600",
          "tgn:1000001",
          "tgn:7012149",
          "tgn:7007157",
          "tgn:1002621",
          "tgn:7029392"
        ],
        "placetype": [
          "aat:300008706"
        ],
        "id": 2327600,
        "name:xx": "Fish Creek"
      }
    },
    {
      "geometry": {
        "type": "Point",
        "coordinates": [
          -118.85,
          34.6
        ]
      },
      "type": "Feature",
      "properties": {
        "hierarchy": [
          "tgn:2327601",
          "tgn:1000001",
          "tgn:7012149",
          "tgn:7007157",
          "tgn:1002972",
          "tgn:7029392"
        ],
        "placetype": [
          "aat:300008706"
        ],
        "id": 2327601,
        "name:xx": "Fish Creek"
      }
    },
    {
      "geometry": {
        "type": "Point",
        "coordinates": [
          -118.5,
          34.6833
        ]
      },
      "type": "Feature",
      "properties": {
        "hierarchy": [
          "tgn:2327602",
          "tgn:1000001",
          "tgn:7012149",
          "tgn:7007157",
          "tgn:1002608",
          "tgn:7029392"
        ],
        "placetype": [
          "aat:300008706"
        ],
        "id": 2327602,
        "name:xx": "Fish Creek"
      }
    },
    {
      "geometry": {
        "type": "Point",
        "coordinates": [
          -120.15,
          35.1
        ]
      },
      "type": "Feature",
      "properties": {
        "hierarchy": [
          "tgn:2327603",
          "tgn:1000001",
          "tgn:7012149",
          "tgn:7007157",
          "tgn:1002863",
          "tgn:7029392"
        ],
        "placetype": [
          "aat:300008706"
        ],
        "id": 2327603,
        "name:xx": "Fish Creek"
      }
    },
    {
      "geometry": {
        "type": "Point",
        "coordinates": [
          -116.7667,
          34.1
        ]
      },
      "type": "Feature",
      "properties": {
        "hierarchy": [
          "tgn:2327604",
          "tgn:1000001",
          "tgn:7012149",
          "tgn:7007157",
          "tgn:1002857",
          "tgn:7029392"
        ],
        "placetype": [
          "aat:300008706"
        ],
        "id": 2327604,
        "name:xx": "Fish Creek"
      }
    },
    {
      "geometry": {
        "type": "Point",
        "coordinates": [
          -118.5333,
          36.1667
        ]
      },
      "type": "Feature",
      "properties": {
        "hierarchy": [
          "tgn:2327605",
          "tgn:1000001",
          "tgn:7012149",
          "tgn:7007157",
          "tgn:1002956",
          "tgn:7029392"
        ],
        "placetype": [
          "aat:300008706"
        ],
        "id": 2327605,
        "name:xx": "Fish Creek"
      }
    },
    {
      "geometry": {
        "type": "Point",
        "coordinates": [
          -106.1167,
          40.9
        ]
      },
      "type": "Feature",
      "properties": {
        "hierarchy": [
          "tgn:2327606",
          "tgn:1000001",
          "tgn:7012149",
          "tgn:2000226",
          "tgn:7007158",
          "tgn:7029392"
        ],
        "placetype": [
          "aat:300008706"
        ],
        "id": 2327606,
        "name:xx": "Fish Creek"
      }
    },
    {
      "geometry": {
        "type": "Point",
        "coordinates": [
          -107.1333,
          40.5833
        ]
      },
      "type": "Feature",
      "properties": {
        "hierarchy": [
          "tgn:2327607",
          "tgn:1000001",
          "tgn:7012149",
          "tgn:7007158",
          "tgn:2000245",
          "tgn:7029392"
        ],
        "placetype": [
          "aat:300008706"
        ],
        "id": 2327607,
        "name:xx": "Fish Creek"
      }
    },
    {
      "geometry": {
        "type": "Point",
        "coordinates": [
          -107.1167,
          40.2
        ]
      },
      "type": "Feature",
      "properties": {
        "hierarchy": [
          "tgn:2327608",
          "tgn:1000001",
          "tgn:7012149",
          "tgn:7007158",
          "tgn:7029392"
        ],
        "placetype": [
          "aat:300008706"
        ],
        "id": 2327608,
        "name:xx": "Fish Creek"
      }
    },
    {
      "geometry": {
        "type": "Point",
        "coordinates": [
          -108.1,
          37.8333
        ]
      },
      "type": "Feature",
      "properties": {
        "hierarchy": [
          "tgn:2327609",
          "tgn:1000001",
          "tgn:7012149",
          "tgn:2000208",
          "tgn:7007158",
          "tgn:7029392"
        ],
        "placetype": [
          "aat:300008706"
        ],
        "id": 2327609,
        "name:xx": "Fish Creek"
      }
    }
  ]
}
