{
  "geometry": {
    "type": "Point",
    "coordinates": [
      -75.6333,
      44.05
    ]
  },
  "type": "Feature",
  "properties": {
    "hierarchy": [
      "tgn:2751873",
      "tgn:1000001",
      "tgn:7012149",
      "tgn:1002518",
      "tgn:7007568",
      "tgn:7029392"
    ],
    "placetype": [
      "aat:300008905"
    ],
    "id": 2751873,
    "name:xx": "Warren Swamp"
  }
}
