{
  "geometry": {
    "type": "Point",
    "coordinates": [
      -83.1833,
      36.0833
    ]
  },
  "type": "Feature",
  "properties": {
    "hierarchy": [
      "tgn:2440595",
      "tgn:1000001",
      "tgn:7012149",
      "tgn:7007825",
      "tgn:7029392"
    ],
    "placetype": [
      "aat:300008706"
    ],
    "id": 2440595,
    "name:xx": "Kneelas Creek"
  }
}
