{
  "geometry": {
    "type": "Point",
    "coordinates": [
      -79.2167,
      33.6667
    ]
  },
  "type": "Feature",
  "properties": {
    "hierarchy": [
      "tgn:2361205",
      "tgn:1000001",
      "tgn:2001746",
      "tgn:7012149",
      "tgn:7007712",
      "tgn:7029392"
    ],
    "placetype": [
      "aat:300008761"
    ],
    "id": 2361205,
    "name:xx": "Gravel Gully"
  }
}
