{
  "geometry": {
    "type": "Point",
    "coordinates": [
      -81.7167,
      30.1167
    ]
  },
  "type": "Feature",
  "properties": {
    "hierarchy": [
      "tgn:2512374",
      "tgn:1000001",
      "tgn:2000261",
      "tgn:7012149",
      "tgn:7007240",
      "tgn:7029392"
    ],
    "placetype": [
      "aat:300132316"
    ],
    "id": 2512374,
    "name:xx": "Mill Cove"
  }
}
