{
  "type": "FeatureCollection",
  "features": [
    {
      "geometry": {
        "type": "Point",
        "coordinates": [
          -69.933333,
          -23.15
        ]
      },
      "type": "Feature",
      "properties": {
        "hierarchy": [
          "tgn:7310290",
          "tgn:7016598",
          "tgn:1000049",
          "tgn:1000002",
          "tgn:7029392"
        ],
        "placetype": [
          "aat:300387033"
        ],
        "id": 7310290,
        "name:xx": "Mineral Valenzuela"
      }
    },
    {
      "geometry": {
        "type": "Point",
        "coordinates": [
          -69.433333,
          -26.5
        ]
      },
      "type": "Feature",
      "properties": {
        "hierarchy": [
          "tgn:7310291",
          "tgn:1001630",
          "tgn:1000049",
          "tgn:1000002",
          "tgn:7029392"
        ],
        "placetype": [
          "aat:300008347"
        ],
        "id": 7310291,
        "name:xx": "Mineral Potrerillos"
      }
    },
    {
      "geometry": {
        "type": "Point",
        "coordinates": [
          -69.6,
          -26.216667
        ]
      },
      "type": "Feature",
      "properties": {
        "hierarchy": [
          "tgn:7310292",
          "tgn:1001630",
          "tgn:1000049",
          "tgn:1000002",
          "tgn:7029392"
        ],
        "placetype": [
          "aat:300008347"
        ],
        "id": 7310292,
        "name:xx": "Mineral El Salvador"
      }
    },
    {
      "geometry": {
        "type": "Point",
        "coordinates": [
          -70.416667,
          -27.816667
        ]
      },
      "type": "Feature",
      "properties": {
        "hierarchy": [
          "tgn:7310293",
          "tgn:1001630",
          "tgn:1000049",
          "tgn:1000002",
          "tgn:7029392"
        ],
        "placetype": [
          "aat:300008057"
        ],
        "id": 7310293,
        "name:xx": "Mineral de Chañarcillo"
      }
    },
    {
      "geometry": {
        "type": "Point",
        "coordinates": [
          -70.983333,
          -28.8
        ]
      },
      "type": "Feature",
      "properties": {
        "hierarchy": [
          "tgn:7310294",
          "tgn:1001630",
          "tgn:1000049",
          "tgn:1000002",
          "tgn:7029392"
        ],
        "placetype": [
          "aat:300000517"
        ],
        "id": 7310294,
        "name:xx": "Campamento Mineral Algarrobo"
      }
    },
    {
      "geometry": {
        "type": "Point",
        "coordinates": [
          -74.466667,
          -49
        ]
      },
      "type": "Feature",
      "properties": {
        "hierarchy": [
          "tgn:7310295",
          "tgn:1001702",
          "tgn:1000049",
          "tgn:1000002",
          "tgn:7029392"
        ],
        "placetype": [
          "aat:300387036"
        ],
        "id": 7310295,
        "name:xx": "Mindful, Bajo"
      }
    },
    {
      "geometry": {
        "type": "Point",
        "coordinates": [
          -72.420556,
          -43.086389
        ]
      },
      "type": "Feature",
      "properties": {
        "hierarchy": [
          "tgn:7310297",
          "tgn:1001699",
          "tgn:1000049",
          "tgn:1000002",
          "tgn:7029392"
        ],
        "placetype": [
          "aat:300008699"
        ],
        "id": 7310297,
        "name:xx": "Minchinmávida, Río"
      }
    },
    {
      "geometry": {
        "type": "Point",
        "coordinates": [
          -71.45,
          -31.4
        ]
      },
      "type": "Feature",
      "properties": {
        "hierarchy": [
          "tgn:7310298",
          "tgn:1001657",
          "tgn:1000049",
          "tgn:1000002",
          "tgn:7029392"
        ],
        "placetype": [
          "aat:300008699"
        ],
        "id": 7310298,
        "name:xx": "Mincha, Quebrada"
      }
    },
    {
      "geometry": {
        "type": "Point",
        "coordinates": [
          -71.45,
          -31.583333
        ]
      },
      "type": "Feature",
      "properties": {
        "hierarchy": [
          "tgn:7310299",
          "tgn:1001657",
          "tgn:1000049",
          "tgn:1000002",
          "tgn:7029392"
        ],
        "placetype": [
          "aat:300008347"
        ],
        "id": 7310299,
        "name:xx": "Mincha"
      }
    }
  ]
}
