{
  "geometry": {
    "type": "Point",
    "coordinates": [
      -95.4333,
      30.1667
    ]
  },
  "type": "Feature",
  "properties": {
    "hierarchy": [
      "tgn:2107944",
      "tgn:1000001",
      "tgn:7012149",
      "tgn:1002691",
      "tgn:7007826",
      "tgn:7029392"
    ],
    "placetype": [
      "aat:300008347"
    ],
    "id": 2107944,
    "name:xx": "Tamina"
  }
}
