{
  "type": "FeatureCollection",
  "features": [
    {
      "geometry": {
        "type": "Point",
        "coordinates": [
          -95.5167,
          37.8667
        ]
      },
      "type": "Feature",
      "properties": {
        "hierarchy": [
          "tgn:2180580",
          "tgn:2000660",
          "tgn:1000001",
          "tgn:7012149",
          "tgn:7007254",
          "tgn:7029392"
        ],
        "placetype": [
          "aat:300008699"
        ],
        "id": 2180580,
        "name:xx": "Bloody Run"
      }
    },
    {
      "geometry": {
        "type": "Point",
        "coordinates": [
          -84.5,
          38.75
        ]
      },
      "type": "Feature",
      "properties": {
        "hierarchy": [
          "tgn:2180581",
          "tgn:1000001",
          "tgn:7012149",
          "tgn:1002778",
          "tgn:7007255",
          "tgn:7029392"
        ],
        "placetype": [
          "aat:300008699"
        ],
        "id": 2180581,
        "name:xx": "Bloody Run"
      }
    },
    {
      "geometry": {
        "type": "Point",
        "coordinates": [
          -96.5,
          40.2333
        ]
      },
      "type": "Feature",
      "properties": {
        "hierarchy": [
          "tgn:2180582",
          "tgn:1000001",
          "tgn:2001349",
          "tgn:7012149",
          "tgn:7007525",
          "tgn:7029392"
        ],
        "placetype": [
          "aat:300008699"
        ],
        "id": 2180582,
        "name:xx": "Bloody Run"
      }
    },
    {
      "geometry": {
        "type": "Point",
        "coordinates": [
          -83.1667,
          38.8833
        ]
      },
      "type": "Feature",
      "properties": {
        "hierarchy": [
          "tgn:2180583",
          "tgn:1000001",
          "tgn:7012149",
          "tgn:1002877",
          "tgn:7007706",
          "tgn:7029392"
        ],
        "placetype": [
          "aat:300008699"
        ],
        "id": 2180583,
        "name:xx": "Bloody Run"
      }
    },
    {
      "geometry": {
        "type": "Point",
        "coordinates": [
          -81.9833,
          39.5667
        ]
      },
      "type": "Feature",
      "properties": {
        "hierarchy": [
          "tgn:2180584",
          "tgn:1000001",
          "tgn:7012149",
          "tgn:2001618",
          "tgn:7007706",
          "tgn:7029392"
        ],
        "placetype": [
          "aat:300008699"
        ],
        "id": 2180584,
        "name:xx": "Bloody Run"
      }
    },
    {
      "geometry": {
        "type": "Point",
        "coordinates": [
          -82.5833,
          39.95
        ]
      },
      "type": "Feature",
      "properties": {
        "hierarchy": [
          "tgn:2180585",
          "tgn:1000001",
          "tgn:7012149",
          "tgn:1002596",
          "tgn:7007706",
          "tgn:7029392"
        ],
        "placetype": [
          "aat:300008699"
        ],
        "id": 2180585,
        "name:xx": "Bloody Run"
      }
    },
    {
      "geometry": {
        "type": "Point",
        "coordinates": [
          -78.3667,
          40.0167
        ]
      },
      "type": "Feature",
      "properties": {
        "hierarchy": [
          "tgn:2180587",
          "tgn:1002172",
          "tgn:1000001",
          "tgn:7012149",
          "tgn:7007710",
          "tgn:7029392"
        ],
        "placetype": [
          "aat:300008699"
        ],
        "id": 2180587,
        "name:xx": "Bloody Run"
      }
    },
    {
      "geometry": {
        "type": "Point",
        "coordinates": [
          -77.8667,
          41.1833
        ]
      },
      "type": "Feature",
      "properties": {
        "hierarchy": [
          "tgn:2180588",
          "tgn:1000001",
          "tgn:1002286",
          "tgn:7012149",
          "tgn:7007710",
          "tgn:7029392"
        ],
        "placetype": [
          "aat:300008699"
        ],
        "id": 2180588,
        "name:xx": "Bloody Run"
      }
    },
    {
      "geometry": {
        "type": "Point",
        "coordinates": [
          -76.4333,
          41.3333
        ]
      },
      "type": "Feature",
      "properties": {
        "hierarchy": [
          "tgn:2180589",
          "tgn:1000001",
          "tgn:7012149",
          "tgn:1002927",
          "tgn:7007710",
          "tgn:7029392"
        ],
        "placetype": [
          "aat:300008699"
        ],
        "id": 2180589,
        "name:xx": "Bloody Run"
      }
    }
  ]
}
