{
  "geometry": {
    "type": "Point",
    "coordinates": [
      -117.4167,
      48.1833
    ]
  },
  "type": "Feature",
  "properties": {
    "hierarchy": [
      "tgn:2678270",
      "tgn:1000001",
      "tgn:7012149",
      "tgn:2002248",
      "tgn:7007920",
      "tgn:7029392"
    ],
    "placetype": [
      "aat:300008706"
    ],
    "id": 2678270,
    "name:xx": "South Fork Calispell Creek"
  }
}
