{
  "type": "FeatureCollection",
  "features": [
    {
      "geometry": {
        "type": "Point",
        "coordinates": [
          80.06365,
          23.667686
        ]
      },
      "type": "Feature",
      "properties": {
        "hierarchy": [
          "tgn:7546130",
          "tgn:1000004",
          "tgn:7000198",
          "tgn:1001894",
          "tgn:7029392"
        ],
        "placetype": [
          "aat:300008347"
        ],
        "name:en": "Bahurīband",
        "id": 7546130
      }
    },
    {
      "geometry": {
        "type": "Point",
        "coordinates": [
          79.766667,
          11.8
        ]
      },
      "type": "Feature",
      "properties": {
        "hierarchy": [
          "tgn:7546131",
          "tgn:1000004",
          "tgn:7000198",
          "tgn:1002000",
          "tgn:7029392"
        ],
        "placetype": [
          "aat:300008347"
        ],
        "name:en": "Bahūr",
        "id": 7546131
      }
    },
    {
      "geometry": {
        "type": "Point",
        "coordinates": [
          75.705935,
          29.534011
        ]
      },
      "type": "Feature",
      "properties": {
        "hierarchy": [
          "tgn:7546132",
          "tgn:1000004",
          "tgn:1001871",
          "tgn:7000198",
          "tgn:7029392"
        ],
        "placetype": [
          "aat:300008347"
        ],
        "name:en": "Bahūna",
        "id": 7546132
      }
    },
    {
      "geometry": {
        "type": "Point",
        "coordinates": [
          76.05,
          14.4
        ]
      },
      "type": "Feature",
      "properties": {
        "hierarchy": [
          "tgn:7546133",
          "tgn:1000004",
          "tgn:7000198",
          "tgn:1001882",
          "tgn:7029392"
        ],
        "placetype": [
          "aat:300008347"
        ],
        "name:en": "Anagodu",
        "id": 7546133
      }
    },
    {
      "geometry": {
        "type": "Point",
        "coordinates": [
          72.653189,
          24.636939
        ]
      },
      "type": "Feature",
      "properties": {
        "hierarchy": [
          "tgn:7546134",
          "tgn:1000004",
          "tgn:7000198",
          "tgn:7016788",
          "tgn:7029392"
        ],
        "placetype": [
          "aat:300008347"
        ],
        "name:en": "Anādra",
        "id": 7546134
      }
    },
    {
      "geometry": {
        "type": "Point",
        "coordinates": [
          84.586904,
          26.73374
        ]
      },
      "type": "Feature",
      "properties": {
        "hierarchy": [
          "tgn:7546135",
          "tgn:1000004",
          "tgn:1001842",
          "tgn:7000198",
          "tgn:7029392"
        ],
        "placetype": [
          "aat:300008347"
        ],
        "name:en": "Amwa Majhār",
        "id": 7546135
      }
    },
    {
      "geometry": {
        "type": "Point",
        "coordinates": [
          76.1,
          14.483333
        ]
      },
      "type": "Feature",
      "properties": {
        "hierarchy": [
          "tgn:7546137",
          "tgn:1000004",
          "tgn:7000198",
          "tgn:1001882",
          "tgn:7029392"
        ],
        "placetype": [
          "aat:300008347"
        ],
        "name:en": "Anaji",
        "id": 7546137
      }
    },
    {
      "geometry": {
        "type": "Point",
        "coordinates": [
          77,
          10.3
        ]
      },
      "type": "Feature",
      "properties": {
        "hierarchy": [
          "tgn:7546139",
          "tgn:1000004",
          "tgn:7000198",
          "tgn:7001797",
          "tgn:7029392"
        ],
        "placetype": [
          "aat:300008777"
        ],
        "name:en": "Anaimalai Hills",
        "id": 7546139
      }
    }
  ]
}
