{
  "geometry": {
    "type": "Point",
    "coordinates": [
      -134.75,
      58.3833
    ]
  },
  "type": "Feature",
  "properties": {
    "hierarchy": [
      "tgn:2445308",
      "tgn:7006450",
      "tgn:1000001",
      "tgn:2124089",
      "tgn:7012149",
      "tgn:7029392"
    ],
    "placetype": [
      "aat:300132316"
    ],
    "id": 2445308,
    "name:xx": "Lena Cove"
  }
}
