{
  "geometry": {
    "type": "Point",
    "coordinates": [
      4.6333,
      51.7167
    ]
  },
  "type": "Feature",
  "properties": {
    "hierarchy": [
      "tgn:1123489",
      "tgn:1000003",
      "tgn:7016845",
      "tgn:7029392"
    ],
    "placetype": [
      "aat:300008707"
    ],
    "id": 1123489,
    "name:xx": "Dordtse Kil"
  }
}
