{
  "geometry": {
    "type": "Point",
    "coordinates": [
      -83.7333,
      41.75
    ]
  },
  "type": "Feature",
  "properties": {
    "hierarchy": [
      "tgn:2561912",
      "tgn:1000001",
      "tgn:7012149",
      "tgn:1002679",
      "tgn:7007520",
      "tgn:7029392"
    ],
    "placetype": [
      "aat:300008699"
    ],
    "id": 2561912,
    "name:xx": "Ottawa Lake Outlet"
  }
}
