{
  "geometry": {
    "type": "Point",
    "coordinates": [
      -96.3833,
      32.45
    ]
  },
  "type": "Feature",
  "properties": {
    "hierarchy": [
      "tgn:2170707",
      "tgn:1000001",
      "tgn:7012149",
      "tgn:1002535",
      "tgn:7007826",
      "tgn:7029392"
    ],
    "placetype": [
      "aat:300008706"
    ],
    "id": 2170707,
    "name:xx": "Big Sandy Creek"
  }
}
