{
  "geometry": {
    "type": "Point",
    "coordinates": [
      84.15,
      18.383333
    ]
  },
  "type": "Feature",
  "properties": {
    "hierarchy": [
      "tgn:7576917",
      "tgn:1001828",
      "tgn:1000004",
      "tgn:7000198",
      "tgn:7029392"
    ],
    "placetype": [
      "aat:300008347"
    ],
    "name:en": "Kottarāvupeta",
    "id": 7576917
  }
}
