{
  "geometry": {
    "type": "Point",
    "coordinates": [
      79.798,
      27.0479
    ]
  },
  "type": "Feature",
  "properties": {
    "hierarchy": [
      "tgn:7562721",
      "tgn:1000004",
      "tgn:7000198",
      "tgn:7016722",
      "tgn:7029392"
    ],
    "placetype": [
      "aat:300008347"
    ],
    "name:en": "Mawai Rahāyak",
    "id": 7562721
  }
}
