{
  "geometry": {
    "type": "Point",
    "coordinates": [
      -80.4167,
      41.7667
    ]
  },
  "type": "Feature",
  "properties": {
    "hierarchy": [
      "tgn:2266353",
      "tgn:1000001",
      "tgn:1002308",
      "tgn:7012149",
      "tgn:7007710",
      "tgn:7029392"
    ],
    "placetype": [
      "aat:300008699"
    ],
    "id": 2266353,
    "name:xx": "Crazy Run"
  }
}
