{
  "geometry": {
    "type": "Point",
    "coordinates": [
      -81.95,
      35.8833
    ]
  },
  "type": "Feature",
  "properties": {
    "hierarchy": [
      "tgn:2397611",
      "tgn:1000001",
      "tgn:7012149",
      "tgn:2001514",
      "tgn:7007709",
      "tgn:7029392"
    ],
    "placetype": [
      "aat:300008706"
    ],
    "id": 2397611,
    "name:xx": "Honeycutt Creek"
  }
}
