{
  "geometry": {
    "type": "Point",
    "coordinates": [
      7.25,
      50.85
    ]
  },
  "type": "Feature",
  "properties": {
    "hierarchy": [
      "tgn:7190180",
      "tgn:1000003",
      "tgn:7003677",
      "tgn:7000084",
      "tgn:7029392"
    ],
    "placetype": [
      "aat:300008347"
    ],
    "id": 7190180,
    "name:xx": "Ellhausen"
  }
}
