{
  "geometry": {
    "type": "Point",
    "coordinates": [
      75.2667,
      36.8333
    ]
  },
  "type": "Feature",
  "properties": {
    "hierarchy": [
      "tgn:7017970",
      "tgn:1000004",
      "tgn:7029392"
    ],
    "placetype": [
      "aat:300259572"
    ],
    "id": 7017970,
    "name:xx": "Kunjirap Daban"
  }
}
