{
  "geometry": {
    "type": "Point",
    "coordinates": [
      -94.5167,
      33.65
    ]
  },
  "type": "Feature",
  "properties": {
    "hierarchy": [
      "tgn:2193269",
      "tgn:1000001",
      "tgn:7012149",
      "tgn:2001667",
      "tgn:7007707",
      "tgn:7029392"
    ],
    "placetype": [
      "aat:300008680"
    ],
    "id": 2193269,
    "name:xx": "Breedlove Lake"
  }
}
