{
  "geometry": {
    "type": "Point",
    "coordinates": [
      -80.6833,
      32.3667
    ]
  },
  "type": "Feature",
  "properties": {
    "hierarchy": [
      "tgn:2096511",
      "tgn:2001731",
      "tgn:1000001",
      "tgn:7012149",
      "tgn:7007712",
      "tgn:7029392"
    ],
    "placetype": [
      "aat:300008347"
    ],
    "id": 2096511,
    "name:xx": "Port Royal"
  }
}
