{
  "geometry": {
    "type": "Point",
    "coordinates": [
      -122.4167,
      45.5167
    ]
  },
  "type": "Feature",
  "properties": {
    "hierarchy": [
      "tgn:2501228",
      "tgn:1000001",
      "tgn:7012149",
      "tgn:1002699",
      "tgn:7007708",
      "tgn:7029392"
    ],
    "placetype": [
      "aat:300006191"
    ],
    "id": 2501228,
    "name:xx": "McGill Reservoir"
  }
}
