{
  "geometry": {
    "type": "Point",
    "coordinates": [
      -91.3167,
      30.0333
    ]
  },
  "type": "Feature",
  "properties": {
    "hierarchy": [
      "tgn:2451509",
      "tgn:1000001",
      "tgn:7012149",
      "tgn:2000876",
      "tgn:7007256",
      "tgn:7029392"
    ],
    "placetype": [
      "aat:300008699"
    ],
    "id": 2451509,
    "name:xx": "Little Bayou Mallet"
  }
}
