{
  "geometry": {
    "type": "Point",
    "coordinates": [
      11.883333,
      48.75
    ]
  },
  "type": "Feature",
  "properties": {
    "hierarchy": [
      "tgn:7209129",
      "tgn:7003669",
      "tgn:1000003",
      "tgn:7000084",
      "tgn:7029392"
    ],
    "placetype": [
      "aat:300000206"
    ],
    "id": 7209129,
    "name:xx": "Beckerhof"
  }
}
