{
  "geometry": {
    "type": "Point",
    "coordinates": [
      -101.9667,
      48.4833
    ]
  },
  "type": "Feature",
  "properties": {
    "hierarchy": [
      "tgn:2190065",
      "tgn:1000001",
      "tgn:7012149",
      "tgn:2001607",
      "tgn:7007705",
      "tgn:7029392"
    ],
    "placetype": [
      "aat:300008761"
    ],
    "id": 2190065,
    "name:xx": "Bowman Coulee"
  }
}
