{
  "type": "FeatureCollection",
  "features": [
    {
      "geometry": {
        "type": "Point",
        "coordinates": [
          -71.466667,
          -30.3
        ]
      },
      "type": "Feature",
      "properties": {
        "hierarchy": [
          "tgn:7321420",
          "tgn:1001657",
          "tgn:1000049",
          "tgn:1000002",
          "tgn:7029392"
        ],
        "placetype": [
          "aat:300008699"
        ],
        "id": 7321420,
        "name:xx": "Camarones, Quebrada"
      }
    },
    {
      "geometry": {
        "type": "Point",
        "coordinates": [
          -70.45,
          -25.333333
        ]
      },
      "type": "Feature",
      "properties": {
        "hierarchy": [
          "tgn:7321421",
          "tgn:7016598",
          "tgn:1000049",
          "tgn:1000002",
          "tgn:7029392"
        ],
        "placetype": [
          "aat:300386846"
        ],
        "id": 7321421,
        "name:xx": "Camarones, Punta"
      }
    },
    {
      "geometry": {
        "type": "Point",
        "coordinates": [
          -70.283333,
          -19.216667
        ]
      },
      "type": "Feature",
      "properties": {
        "hierarchy": [
          "tgn:7321422",
          "tgn:7002464",
          "tgn:1000049",
          "tgn:1000002",
          "tgn:7029392"
        ],
        "placetype": [
          "aat:300386846"
        ],
        "id": 7321422,
        "name:xx": "Camarones, Punta"
      }
    },
    {
      "geometry": {
        "type": "Point",
        "coordinates": [
          -70.166667,
          -18.966667
        ]
      },
      "type": "Feature",
      "properties": {
        "hierarchy": [
          "tgn:7321423",
          "tgn:7002464",
          "tgn:1000049",
          "tgn:1000002",
          "tgn:7029392"
        ],
        "placetype": [
          "aat:300008805"
        ],
        "id": 7321423,
        "name:xx": "Camarones, Pampa de"
      }
    },
    {
      "geometry": {
        "type": "Point",
        "coordinates": [
          -69.866667,
          -19
        ]
      },
      "type": "Feature",
      "properties": {
        "hierarchy": [
          "tgn:7321424",
          "tgn:7002464",
          "tgn:1000049",
          "tgn:1000002",
          "tgn:7029392"
        ],
        "placetype": [
          "aat:300000206"
        ],
        "id": 7321424,
        "name:xx": "Hacienda Camarones"
      }
    },
    {
      "geometry": {
        "type": "Point",
        "coordinates": [
          -69.8,
          -19.033333
        ]
      },
      "type": "Feature",
      "properties": {
        "hierarchy": [
          "tgn:7321425",
          "tgn:7002464",
          "tgn:1000049",
          "tgn:1000002",
          "tgn:7029392"
        ],
        "placetype": [
          "aat:300008795"
        ],
        "id": 7321425,
        "name:xx": "Camarones, Cerro"
      }
    },
    {
      "geometry": {
        "type": "Point",
        "coordinates": [
          -70.283333,
          -19.2
        ]
      },
      "type": "Feature",
      "properties": {
        "hierarchy": [
          "tgn:7321426",
          "tgn:7002464",
          "tgn:1000049",
          "tgn:1000002",
          "tgn:7029392"
        ],
        "placetype": [
          "aat:300132317"
        ],
        "id": 7321426,
        "name:xx": "Camarones, Caleta"
      }
    },
    {
      "geometry": {
        "type": "Point",
        "coordinates": [
          -69.783333,
          -19.033333
        ]
      },
      "type": "Feature",
      "properties": {
        "hierarchy": [
          "tgn:7321427",
          "tgn:7002464",
          "tgn:1000049",
          "tgn:1000002",
          "tgn:7029392"
        ],
        "placetype": [
          "aat:300387033"
        ],
        "id": 7321427,
        "name:xx": "Camarones"
      }
    },
    {
      "geometry": {
        "type": "Point",
        "coordinates": [
          -70.65,
          -28.666667
        ]
      },
      "type": "Feature",
      "properties": {
        "hierarchy": [
          "tgn:7321428",
          "tgn:1001630",
          "tgn:1000049",
          "tgn:1000002",
          "tgn:7029392"
        ],
        "placetype": [
          "aat:300008347"
        ],
        "id": 7321428,
        "name:xx": "Camarones"
      }
    },
    {
      "geometry": {
        "type": "Point",
        "coordinates": [
          -69.866667,
          -19.016667
        ]
      },
      "type": "Feature",
      "properties": {
        "hierarchy": [
          "tgn:7321429",
          "tgn:7002464",
          "tgn:1000049",
          "tgn:1000002",
          "tgn:7029392"
        ],
        "placetype": [
          "aat:300008347"
        ],
        "id": 7321429,
        "name:xx": "Camarones"
      }
    }
  ]
}
