{
  "geometry": {
    "type": "Point",
    "coordinates": [
      34.8667,
      49.4167
    ]
  },
  "type": "Feature",
  "properties": {
    "hierarchy": [
      "tgn:1056631",
      "tgn:1000003",
      "tgn:7011666",
      "tgn:7006660",
      "tgn:7029392"
    ],
    "placetype": [
      "aat:300008347"
    ],
    "id": 1056631,
    "name:xx": "Mashevka"
  }
}
