{
  "geometry": {
    "type": "Point",
    "coordinates": [
      -101.25,
      32.9667
    ]
  },
  "type": "Feature",
  "properties": {
    "hierarchy": [
      "tgn:2610444",
      "tgn:1000001",
      "tgn:7012149",
      "tgn:7007826",
      "tgn:7029392"
    ],
    "placetype": [
      "aat:300008761"
    ],
    "id": 2610444,
    "name:xx": "Red Canyon"
  }
}
