{
  "geometry": {
    "type": "Point",
    "coordinates": [
      -76.9667,
      39.4833
    ]
  },
  "type": "Feature",
  "properties": {
    "hierarchy": [
      "tgn:2173842",
      "tgn:1002238",
      "tgn:1000001",
      "tgn:7012149",
      "tgn:7007516",
      "tgn:7029392"
    ],
    "placetype": [
      "aat:300008347"
    ],
    "id": 2173842,
    "name:xx": "Bird Hill"
  }
}
