{
  "geometry": {
    "type": "Point",
    "coordinates": [
      26.4167,
      49.85
    ]
  },
  "type": "Feature",
  "properties": {
    "hierarchy": [
      "tgn:1060242",
      "tgn:1000003",
      "tgn:7016777",
      "tgn:7006660",
      "tgn:7029392"
    ],
    "placetype": [
      "aat:300008347"
    ],
    "id": 1060242,
    "name:xx": "Teofilpol'"
  }
}
