{
  "type": "FeatureCollection",
  "features": [
    {
      "geometry": {
        "type": "Point",
        "coordinates": [
          13.6,
          42.483333
        ]
      },
      "type": "Feature",
      "properties": {
        "hierarchy": [
          "tgn:7047490",
          "tgn:7009084",
          "tgn:7003001",
          "tgn:1000003",
          "tgn:1000080",
          "tgn:7029392"
        ],
        "placetype": [
          "aat:300008347"
        ],
        "id": 7047490,
        "name:xx": "Fano a Corno"
      }
    },
    {
      "geometry": {
        "type": "Point",
        "coordinates": [
          12.883333,
          43.3
        ]
      },
      "type": "Feature",
      "properties": {
        "hierarchy": [
          "tgn:7047491",
          "tgn:1003429",
          "tgn:1000003",
          "tgn:7003240",
          "tgn:1000080",
          "tgn:7029392"
        ],
        "placetype": [
          "aat:300008795"
        ],
        "id": 7047491,
        "name:xx": "Fano, Monte"
      }
    },
    {
      "geometry": {
        "type": "Point",
        "coordinates": [
          8.483333,
          40.1
        ]
      },
      "type": "Feature",
      "properties": {
        "hierarchy": [
          "tgn:7047493",
          "tgn:1001730",
          "tgn:1000003",
          "tgn:7003121",
          "tgn:1000080",
          "tgn:7029392"
        ],
        "placetype": [
          "aat:300008699"
        ],
        "id": 7047493,
        "name:xx": "Fanni Scanu, Riu"
      }
    },
    {
      "geometry": {
        "type": "Point",
        "coordinates": [
          7.533333,
          43.883333
        ]
      },
      "type": "Feature",
      "properties": {
        "hierarchy": [
          "tgn:7047495",
          "tgn:1000003",
          "tgn:7003141",
          "tgn:7003236",
          "tgn:1000080",
          "tgn:7029392"
        ],
        "placetype": [
          "aat:300008347"
        ],
        "id": 7047495,
        "name:xx": "Fanghetto"
      }
    },
    {
      "geometry": {
        "type": "Point",
        "coordinates": [
          12.383333,
          42.983333
        ]
      },
      "type": "Feature",
      "properties": {
        "hierarchy": [
          "tgn:7047496",
          "tgn:7003170",
          "tgn:1000003",
          "tgn:7003125",
          "tgn:1000080",
          "tgn:7029392"
        ],
        "placetype": [
          "aat:300008347"
        ],
        "id": 7047496,
        "name:xx": "Fanciullata"
      }
    },
    {
      "geometry": {
        "type": "Point",
        "coordinates": [
          18.2,
          39.833333
        ]
      },
      "type": "Feature",
      "properties": {
        "hierarchy": [
          "tgn:7047497",
          "tgn:1003468",
          "tgn:1000003",
          "tgn:7010380",
          "tgn:1000080",
          "tgn:7029392"
        ],
        "placetype": [
          "aat:300008791"
        ],
        "id": 7047497,
        "name:xx": "Fanciulla, Isola"
      }
    },
    {
      "geometry": {
        "type": "Point",
        "coordinates": [
          12.15,
          43.916667
        ]
      },
      "type": "Feature",
      "properties": {
        "hierarchy": [
          "tgn:7047498",
          "tgn:7003129",
          "tgn:1000003",
          "tgn:7008516",
          "tgn:1000080",
          "tgn:7029392"
        ],
        "placetype": [
          "aat:300008699"
        ],
        "id": 7047498,
        "name:xx": "Fanante, Torrente"
      }
    }
  ]
}
