{
  "type": "FeatureCollection",
  "features": [
    {
      "geometry": {
        "type": "Point",
        "coordinates": [
          -83.3167,
          32.0833
        ]
      },
      "type": "Feature",
      "properties": {
        "hierarchy": [
          "tgn:2275330",
          "tgn:1000001",
          "tgn:7012149",
          "tgn:2000336",
          "tgn:7007248",
          "tgn:7029392"
        ],
        "placetype": [
          "aat:300006191"
        ],
        "id": 2275330,
        "name:xx": "Daniels Millpond"
      }
    },
    {
      "geometry": {
        "type": "Point",
        "coordinates": [
          -110.8667,
          31.7167
        ]
      },
      "type": "Feature",
      "properties": {
        "hierarchy": [
          "tgn:2275331",
          "tgn:1000001",
          "tgn:7006451",
          "tgn:7012149",
          "tgn:2000102",
          "tgn:7029392"
        ],
        "placetype": [
          "aat:300000390"
        ],
        "id": 2275331,
        "name:xx": "Daniels Mine"
      }
    },
    {
      "geometry": {
        "type": "Point",
        "coordinates": [
          -93.3167,
          35.9
        ]
      },
      "type": "Feature",
      "properties": {
        "hierarchy": [
          "tgn:2275332",
          "tgn:1000001",
          "tgn:7016172",
          "tgn:7012149",
          "tgn:2000155",
          "tgn:7029392"
        ],
        "placetype": [
          "aat:300008798"
        ],
        "id": 2275332,
        "name:xx": "Daniels Mountain"
      }
    },
    {
      "geometry": {
        "type": "Point",
        "coordinates": [
          -72.5,
          42.85
        ]
      },
      "type": "Feature",
      "properties": {
        "hierarchy": [
          "tgn:2275333",
          "tgn:7019618",
          "tgn:1000001",
          "tgn:7012149",
          "tgn:7007564",
          "tgn:7029392"
        ],
        "placetype": [
          "aat:300008798"
        ],
        "id": 2275333,
        "name:xx": "Daniels Mountain"
      }
    },
    {
      "geometry": {
        "type": "Point",
        "coordinates": [
          -78.5,
          38.3
        ]
      },
      "type": "Feature",
      "properties": {
        "hierarchy": [
          "tgn:2275335",
          "tgn:1000001",
          "tgn:7012149",
          "tgn:2002165",
          "tgn:7007919",
          "tgn:7029392"
        ],
        "placetype": [
          "aat:300008798"
        ],
        "id": 2275335,
        "name:xx": "Daniels Mountain"
      }
    },
    {
      "geometry": {
        "type": "Point",
        "coordinates": [
          -72.6,
          42.7
        ]
      },
      "type": "Feature",
      "properties": {
        "hierarchy": [
          "tgn:2275336",
          "tgn:1000001",
          "tgn:7013942",
          "tgn:7012149",
          "tgn:7007517",
          "tgn:7029392"
        ],
        "placetype": [
          "aat:300008798"
        ],
        "id": 2275336,
        "name:xx": "Daniels Peak"
      }
    },
    {
      "geometry": {
        "type": "Point",
        "coordinates": [
          -89.8,
          35.7667
        ]
      },
      "type": "Feature",
      "properties": {
        "hierarchy": [
          "tgn:2275337",
          "tgn:1000001",
          "tgn:7016172",
          "tgn:7012149",
          "tgn:2000151",
          "tgn:7029392"
        ],
        "placetype": [
          "aat:300008850"
        ],
        "id": 2275337,
        "name:xx": "Daniels Point"
      }
    },
    {
      "geometry": {
        "type": "Point",
        "coordinates": [
          -81.4667,
          25.8833
        ]
      },
      "type": "Feature",
      "properties": {
        "hierarchy": [
          "tgn:2275338",
          "tgn:1000001",
          "tgn:1002289",
          "tgn:7012149",
          "tgn:7007240",
          "tgn:7029392"
        ],
        "placetype": [
          "aat:300008850"
        ],
        "id": 2275338,
        "name:xx": "Daniels Point"
      }
    },
    {
      "geometry": {
        "type": "Point",
        "coordinates": [
          -106.2333,
          47.6333
        ]
      },
      "type": "Feature",
      "properties": {
        "hierarchy": [
          "tgn:2275339",
          "tgn:1000001",
          "tgn:7012149",
          "tgn:2001287",
          "tgn:7007524",
          "tgn:7029392"
        ],
        "placetype": [
          "aat:300008850"
        ],
        "id": 2275339,
        "name:xx": "Daniels Point"
      }
    }
  ]
}
