{
  "geometry": {
    "type": "Point",
    "coordinates": [
      -84.5667,
      42.8333
    ]
  },
  "type": "Feature",
  "properties": {
    "hierarchy": [
      "tgn:2347121",
      "tgn:1000001",
      "tgn:1002283",
      "tgn:7012149",
      "tgn:7007520",
      "tgn:7029392"
    ],
    "placetype": [
      "aat:300008680"
    ],
    "id": 2347121,
    "name:xx": "Geneva, Lake"
  }
}
