{
  "geometry": {
    "type": "Point",
    "coordinates": [
      76.372124,
      29.437226
    ]
  },
  "type": "Feature",
  "properties": {
    "hierarchy": [
      "tgn:7553694",
      "tgn:1000004",
      "tgn:1001871",
      "tgn:7000198",
      "tgn:7029392"
    ],
    "placetype": [
      "aat:300008347"
    ],
    "name:en": "Nikurān",
    "id": 7553694
  }
}
