{
  "geometry": {
    "type": "Point",
    "coordinates": [
      -73.65,
      43.5333
    ]
  },
  "type": "Feature",
  "properties": {
    "hierarchy": [
      "tgn:2707503",
      "tgn:1000001",
      "tgn:7012149",
      "tgn:1002986",
      "tgn:7007568",
      "tgn:7029392"
    ],
    "placetype": [
      "aat:300008791"
    ],
    "id": 2707503,
    "name:xx": "Sweetbriar Island"
  }
}
