{
  "geometry": {
    "type": "Point",
    "coordinates": [
      -77.3167,
      38.85
    ]
  },
  "type": "Feature",
  "properties": {
    "hierarchy": [
      "tgn:1132217",
      "tgn:1000001",
      "tgn:7012149",
      "tgn:7007919",
      "tgn:7029392"
    ],
    "placetype": [
      "aat:300008706"
    ],
    "id": 1132217,
    "name:xx": "Accotink Creek"
  }
}
