{
  "geometry": {
    "type": "Point",
    "coordinates": [
      18.3333,
      68.5833
    ]
  },
  "type": "Feature",
  "properties": {
    "hierarchy": [
      "tgn:1101927",
      "tgn:1000003",
      "tgn:1000097",
      "tgn:7029392"
    ],
    "placetype": [
      "aat:300008189"
    ],
    "id": 1101927,
    "name:xx": "Vadvetjåkko Nationalpark"
  }
}
