{
  "type": "FeatureCollection",
  "features": [
    {
      "geometry": {
        "type": "Point",
        "coordinates": [
          -116.9667,
          43.05
        ]
      },
      "type": "Feature",
      "properties": {
        "hierarchy": [
          "tgn:2129530",
          "tgn:1000001",
          "tgn:7012149",
          "tgn:2000488",
          "tgn:7007250",
          "tgn:7029392"
        ],
        "placetype": [
          "aat:300008761"
        ],
        "id": 2129530,
        "name:xx": "Alkali Draw"
      }
    },
    {
      "geometry": {
        "type": "Point",
        "coordinates": [
          -107.2667,
          47.05
        ]
      },
      "type": "Feature",
      "properties": {
        "hierarchy": [
          "tgn:2129531",
          "tgn:1000001",
          "tgn:7012149",
          "tgn:2001276",
          "tgn:7007524",
          "tgn:7029392"
        ],
        "placetype": [
          "aat:300008761"
        ],
        "id": 2129531,
        "name:xx": "Alkali Draw"
      }
    },
    {
      "geometry": {
        "type": "Point",
        "coordinates": [
          -104.4,
          33.8167
        ]
      },
      "type": "Feature",
      "properties": {
        "hierarchy": [
          "tgn:2129532",
          "tgn:1000001",
          "tgn:2001430",
          "tgn:7012149",
          "tgn:7007566",
          "tgn:7029392"
        ],
        "placetype": [
          "aat:300008761"
        ],
        "id": 2129532,
        "name:xx": "Alkali Draw"
      }
    },
    {
      "geometry": {
        "type": "Point",
        "coordinates": [
          -100.05,
          33
        ]
      },
      "type": "Feature",
      "properties": {
        "hierarchy": [
          "tgn:2129533",
          "tgn:1000001",
          "tgn:7012149",
          "tgn:2002078",
          "tgn:7007826",
          "tgn:7029392"
        ],
        "placetype": [
          "aat:300008761"
        ],
        "id": 2129533,
        "name:xx": "Alkali Draw"
      }
    },
    {
      "geometry": {
        "type": "Point",
        "coordinates": [
          -108.3667,
          43.7
        ]
      },
      "type": "Feature",
      "properties": {
        "hierarchy": [
          "tgn:2129534",
          "tgn:1000001",
          "tgn:7012149",
          "tgn:2002373",
          "tgn:7007923",
          "tgn:7029392"
        ],
        "placetype": [
          "aat:300008761"
        ],
        "id": 2129534,
        "name:xx": "Alkali Draw"
      }
    },
    {
      "geometry": {
        "type": "Point",
        "coordinates": [
          -109.15,
          42.3833
        ]
      },
      "type": "Feature",
      "properties": {
        "hierarchy": [
          "tgn:2129535",
          "tgn:1000001",
          "tgn:7012149",
          "tgn:2002382",
          "tgn:7007923",
          "tgn:7029392"
        ],
        "placetype": [
          "aat:300008761"
        ],
        "id": 2129535,
        "name:xx": "Alkali Draw"
      }
    },
    {
      "geometry": {
        "type": "Point",
        "coordinates": [
          -106.8333,
          43.8167
        ]
      },
      "type": "Feature",
      "properties": {
        "hierarchy": [
          "tgn:2129536",
          "tgn:1000001",
          "tgn:7012149",
          "tgn:2002374",
          "tgn:7007923",
          "tgn:7029392"
        ],
        "placetype": [
          "aat:300008761"
        ],
        "id": 2129536,
        "name:xx": "Alkali Draw"
      }
    },
    {
      "geometry": {
        "type": "Point",
        "coordinates": [
          -104.95,
          44.65
        ]
      },
      "type": "Feature",
      "properties": {
        "hierarchy": [
          "tgn:2129537",
          "tgn:1000001",
          "tgn:2002370",
          "tgn:7012149",
          "tgn:7007923",
          "tgn:7029392"
        ],
        "placetype": [
          "aat:300008761"
        ],
        "id": 2129537,
        "name:xx": "Alkali Draw"
      }
    },
    {
      "geometry": {
        "type": "Point",
        "coordinates": [
          -108.85,
          42
        ]
      },
      "type": "Feature",
      "properties": {
        "hierarchy": [
          "tgn:2129538",
          "tgn:1000001",
          "tgn:7012149",
          "tgn:2002383",
          "tgn:7007923",
          "tgn:7029392"
        ],
        "placetype": [
          "aat:300008761"
        ],
        "id": 2129538,
        "name:xx": "Alkali Draw"
      }
    },
    {
      "geometry": {
        "type": "Point",
        "coordinates": [
          -104.7667,
          44.0833
        ]
      },
      "type": "Feature",
      "properties": {
        "hierarchy": [
          "tgn:2129539",
          "tgn:1000001",
          "tgn:7012149",
          "tgn:2002387",
          "tgn:7007923",
          "tgn:7029392"
        ],
        "placetype": [
          "aat:300008761"
        ],
        "id": 2129539,
        "name:xx": "Alkali Draw"
      }
    }
  ]
}
