{
  "geometry": {
    "type": "Point",
    "coordinates": [
      -77.35,
      43.1667
    ]
  },
  "type": "Feature",
  "properties": {
    "hierarchy": [
      "tgn:2418343",
      "tgn:1000001",
      "tgn:7012149",
      "tgn:7014600",
      "tgn:7007568",
      "tgn:7029392"
    ],
    "placetype": [
      "aat:300008798"
    ],
    "id": 2418343,
    "name:xx": "Jacobs Hill"
  }
}
