{
  "geometry": {
    "type": "Point",
    "coordinates": [
      -87.1667,
      34.75
    ]
  },
  "type": "Feature",
  "properties": {
    "hierarchy": [
      "tgn:2160194",
      "tgn:7002659",
      "tgn:1000001",
      "tgn:7012149",
      "tgn:2000041",
      "tgn:7029392"
    ],
    "placetype": [
      "aat:300008347"
    ],
    "id": 2160194,
    "name:xx": "Beechwood Acres"
  }
}
