{
  "type": "FeatureCollection",
  "features": [
    {
      "geometry": {
        "type": "Point",
        "coordinates": [
          11.65,
          50.533333
        ]
      },
      "type": "Feature",
      "properties": {
        "hierarchy": [
          "tgn:1037580",
          "tgn:1000003",
          "tgn:7003689",
          "tgn:7000084",
          "tgn:7029392"
        ],
        "placetype": [
          "aat:300008347"
        ],
        "id": 1037580,
        "name:xx": "Remptendorf"
      }
    },
    {
      "geometry": {
        "type": "Point",
        "coordinates": [
          12.7,
          52.633333
        ]
      },
      "type": "Feature",
      "properties": {
        "hierarchy": [
          "tgn:1037581",
          "tgn:7000096",
          "tgn:1000003",
          "tgn:7000084",
          "tgn:7029392"
        ],
        "placetype": [
          "aat:300008347"
        ],
        "id": 1037581,
        "name:xx": "Retzow"
      }
    },
    {
      "geometry": {
        "type": "Point",
        "coordinates": [
          12.3,
          52.066667
        ]
      },
      "type": "Feature",
      "properties": {
        "hierarchy": [
          "tgn:1037582",
          "tgn:1000003",
          "tgn:7003687",
          "tgn:7000084",
          "tgn:7029392"
        ],
        "placetype": [
          "aat:300008347"
        ],
        "id": 1037582,
        "name:xx": "Reuden"
      }
    },
    {
      "geometry": {
        "type": "Point",
        "coordinates": [
          12.9,
          53.7
        ]
      },
      "type": "Feature",
      "properties": {
        "hierarchy": [
          "tgn:1037583",
          "tgn:1000003",
          "tgn:7000094",
          "tgn:7000084",
          "tgn:7029392"
        ],
        "placetype": [
          "aat:300008347"
        ],
        "id": 1037583,
        "name:xx": "Reuterstadt Stavenhagen"
      }
    },
    {
      "geometry": {
        "type": "Point",
        "coordinates": [
          12.333333,
          52.75
        ]
      },
      "type": "Feature",
      "properties": {
        "hierarchy": [
          "tgn:1037585",
          "tgn:7000096",
          "tgn:1000003",
          "tgn:7000084",
          "tgn:7029392"
        ],
        "placetype": [
          "aat:300008347"
        ],
        "id": 1037585,
        "name:xx": "Rhinow"
      }
    },
    {
      "geometry": {
        "type": "Point",
        "coordinates": [
          12.466667,
          54.25
        ]
      },
      "type": "Feature",
      "properties": {
        "hierarchy": [
          "tgn:1037586",
          "tgn:1000003",
          "tgn:7000094",
          "tgn:7000084",
          "tgn:7029392"
        ],
        "placetype": [
          "aat:300008347"
        ],
        "id": 1037586,
        "name:xx": "Ribnitz-Damgarten"
      }
    },
    {
      "geometry": {
        "type": "Point",
        "coordinates": [
          12.883333,
          54.2
        ]
      },
      "type": "Feature",
      "properties": {
        "hierarchy": [
          "tgn:1037587",
          "tgn:1000003",
          "tgn:7000094",
          "tgn:7000084",
          "tgn:7029392"
        ],
        "placetype": [
          "aat:300008347"
        ],
        "id": 1037587,
        "name:xx": "Richtenberg"
      }
    },
    {
      "geometry": {
        "type": "Point",
        "coordinates": [
          11.166667,
          51.733333
        ]
      },
      "type": "Feature",
      "properties": {
        "hierarchy": [
          "tgn:1037588",
          "tgn:1000003",
          "tgn:7003687",
          "tgn:7000084",
          "tgn:7029392"
        ],
        "placetype": [
          "aat:300008347"
        ],
        "id": 1037588,
        "name:xx": "Rieder"
      }
    }
  ]
}
