{
  "type": "FeatureCollection",
  "features": [
    {
      "geometry": {
        "type": "Point",
        "coordinates": [
          -113.45,
          47.75
        ]
      },
      "type": "Feature",
      "properties": {
        "hierarchy": [
          "tgn:2579821",
          "tgn:1000001",
          "tgn:7012149",
          "tgn:2001274",
          "tgn:7007524",
          "tgn:7029392"
        ],
        "placetype": [
          "aat:300008706"
        ],
        "id": 2579821,
        "name:xx": "Picture Creek"
      }
    },
    {
      "geometry": {
        "type": "Point",
        "coordinates": [
          -78.7333,
          36.1833
        ]
      },
      "type": "Feature",
      "properties": {
        "hierarchy": [
          "tgn:2579822",
          "tgn:1000001",
          "tgn:7012149",
          "tgn:7014128",
          "tgn:7007709",
          "tgn:7029392"
        ],
        "placetype": [
          "aat:300008706"
        ],
        "id": 2579822,
        "name:xx": "Picture Creek"
      }
    },
    {
      "geometry": {
        "type": "Point",
        "coordinates": [
          -120.25,
          37.6833
        ]
      },
      "type": "Feature",
      "properties": {
        "hierarchy": [
          "tgn:2579823",
          "tgn:1000001",
          "tgn:7012149",
          "tgn:7007157",
          "tgn:7014004",
          "tgn:7029392"
        ],
        "placetype": [
          "aat:300008761"
        ],
        "id": 2579823,
        "name:xx": "Picture Gallery Gulch"
      }
    },
    {
      "geometry": {
        "type": "Point",
        "coordinates": [
          -119.6167,
          44.5
        ]
      },
      "type": "Feature",
      "properties": {
        "hierarchy": [
          "tgn:2579824",
          "tgn:1000001",
          "tgn:7012149",
          "tgn:2001708",
          "tgn:7007708",
          "tgn:7029392"
        ],
        "placetype": [
          "aat:300008761"
        ],
        "id": 2579824,
        "name:xx": "Picture Gorge"
      }
    },
    {
      "geometry": {
        "type": "Point",
        "coordinates": [
          -106.7833,
          39.7833
        ]
      },
      "type": "Feature",
      "properties": {
        "hierarchy": [
          "tgn:2579825",
          "tgn:1000001",
          "tgn:7012149",
          "tgn:2000210",
          "tgn:7007158",
          "tgn:7029392"
        ],
        "placetype": [
          "aat:300008680"
        ],
        "id": 2579825,
        "name:xx": "Picture Lake"
      }
    },
    {
      "geometry": {
        "type": "Point",
        "coordinates": [
          -86.1333,
          42.3833
        ]
      },
      "type": "Feature",
      "properties": {
        "hierarchy": [
          "tgn:2579826",
          "tgn:1000001",
          "tgn:7012149",
          "tgn:1002967",
          "tgn:7007520",
          "tgn:7029392"
        ],
        "placetype": [
          "aat:300008680"
        ],
        "id": 2579826,
        "name:xx": "Picture Lake"
      }
    },
    {
      "geometry": {
        "type": "Point",
        "coordinates": [
          -113.9,
          47.3333
        ]
      },
      "type": "Feature",
      "properties": {
        "hierarchy": [
          "tgn:2579827",
          "tgn:1000001",
          "tgn:7012149",
          "tgn:2001283",
          "tgn:7007524",
          "tgn:7029392"
        ],
        "placetype": [
          "aat:300008680"
        ],
        "id": 2579827,
        "name:xx": "Picture Lake"
      }
    },
    {
      "geometry": {
        "type": "Point",
        "coordinates": [
          -113.45,
          47.7333
        ]
      },
      "type": "Feature",
      "properties": {
        "hierarchy": [
          "tgn:2579828",
          "tgn:1000001",
          "tgn:7012149",
          "tgn:2001274",
          "tgn:7007524",
          "tgn:7029392"
        ],
        "placetype": [
          "aat:300008680"
        ],
        "id": 2579828,
        "name:xx": "Picture Lake"
      }
    },
    {
      "geometry": {
        "type": "Point",
        "coordinates": [
          -110.6167,
          40.65
        ]
      },
      "type": "Feature",
      "properties": {
        "hierarchy": [
          "tgn:2579829",
          "tgn:1000001",
          "tgn:2002107",
          "tgn:7012149",
          "tgn:7007827",
          "tgn:7029392"
        ],
        "placetype": [
          "aat:300008680"
        ],
        "id": 2579829,
        "name:xx": "Picture Lake"
      }
    }
  ]
}
