{
  "geometry": {
    "type": "Point",
    "coordinates": [
      74.72486,
      34.174087
    ]
  },
  "type": "Feature",
  "properties": {
    "hierarchy": [
      "tgn:7587169",
      "tgn:1000004",
      "tgn:7000198",
      "tgn:7000799",
      "tgn:7029392"
    ],
    "placetype": [
      "aat:300008347"
    ],
    "name:en": "Chhandna Deh Nauābād",
    "id": 7587169
  }
}
