{
  "geometry": {
    "type": "Point",
    "coordinates": [
      -82.8667,
      35.1667
    ]
  },
  "type": "Feature",
  "properties": {
    "hierarchy": [
      "tgn:2216363",
      "tgn:1000001",
      "tgn:7012149",
      "tgn:2001544",
      "tgn:7007709",
      "tgn:7029392"
    ],
    "placetype": [
      "aat:300008699"
    ],
    "id": 2216363,
    "name:xx": "Camp Cove Branch"
  }
}
