{
  "type": "FeatureCollection",
  "features": [
    {
      "geometry": {
        "type": "Point",
        "coordinates": [
          31.333333,
          30.683333
        ]
      },
      "type": "Feature",
      "properties": {
        "hierarchy": [
          "tgn:7528010",
          "tgn:7001242",
          "tgn:1001059",
          "tgn:7016833",
          "tgn:7029392"
        ],
        "placetype": [
          "aat:300005926"
        ],
        "id": 7528010,
        "name:xx": "Manāmat Sīdī 'Abd Allāh al 'Irāqī"
      }
    },
    {
      "geometry": {
        "type": "Point",
        "coordinates": [
          31.3,
          30.8
        ]
      },
      "type": "Feature",
      "properties": {
        "hierarchy": [
          "tgn:7528011",
          "tgn:7001242",
          "tgn:1001059",
          "tgn:7016833",
          "tgn:7029392"
        ],
        "placetype": [
          "aat:300005926"
        ],
        "name:en": "Sīdī 'Abd Allāh al Ghunaymī",
        "id": 7528011
      }
    },
    {
      "geometry": {
        "type": "Point",
        "coordinates": [
          30.65,
          28.533333
        ]
      },
      "type": "Feature",
      "properties": {
        "hierarchy": [
          "tgn:7528012",
          "tgn:7001242",
          "tgn:7016833",
          "tgn:1001088",
          "tgn:7029392"
        ],
        "placetype": [
          "aat:300005926"
        ],
        "name:en": "Sīdī 'Abd Allāh ad Dakrūrī",
        "id": 7528012
      }
    },
    {
      "geometry": {
        "type": "Point",
        "coordinates": [
          31.966667,
          31.216667
        ]
      },
      "type": "Feature",
      "properties": {
        "hierarchy": [
          "tgn:7528013",
          "tgn:7001242",
          "tgn:1001059",
          "tgn:7016833",
          "tgn:7029392"
        ],
        "placetype": [
          "aat:300007544"
        ],
        "name:en": "Masjid Sīdī 'Abd Allāh",
        "id": 7528013
      }
    },
    {
      "geometry": {
        "type": "Point",
        "coordinates": [
          31.166667,
          29.166667
        ]
      },
      "type": "Feature",
      "properties": {
        "hierarchy": [
          "tgn:7528014",
          "tgn:7001242",
          "tgn:7001105",
          "tgn:7016833",
          "tgn:7029392"
        ],
        "placetype": [
          "aat:300005926"
        ],
        "name:en": "Manāmat Sīdī 'Abd Allāh",
        "id": 7528014
      }
    },
    {
      "geometry": {
        "type": "Point",
        "coordinates": [
          32.716667,
          25.766667
        ]
      },
      "type": "Feature",
      "properties": {
        "hierarchy": [
          "tgn:7528015",
          "tgn:7001242",
          "tgn:7016833",
          "tgn:7000123",
          "tgn:7029392"
        ],
        "placetype": [
          "aat:300005926"
        ],
        "name:en": "Manāmat Sīdī 'Abd Allāh",
        "id": 7528015
      }
    },
    {
      "geometry": {
        "type": "Point",
        "coordinates": [
          32.883333,
          24.516667
        ]
      },
      "type": "Feature",
      "properties": {
        "hierarchy": [
          "tgn:7528016",
          "tgn:7001242",
          "tgn:7016833",
          "tgn:7000122",
          "tgn:7029392"
        ],
        "placetype": [
          "aat:300005926"
        ],
        "name:en": "Manāmat Sīdī 'Abd Allāh",
        "id": 7528016
      }
    },
    {
      "geometry": {
        "type": "Point",
        "coordinates": [
          30.333333,
          30.85
        ]
      },
      "type": "Feature",
      "properties": {
        "hierarchy": [
          "tgn:7528017",
          "tgn:7001242",
          "tgn:1001075",
          "tgn:7016833",
          "tgn:7029392"
        ],
        "placetype": [
          "aat:300266755"
        ],
        "name:en": "Manāmat Sīdī 'Abd Allāh",
        "id": 7528017
      }
    },
    {
      "geometry": {
        "type": "Point",
        "coordinates": [
          31.733333,
          31.3
        ]
      },
      "type": "Feature",
      "properties": {
        "hierarchy": [
          "tgn:7528018",
          "tgn:7001242",
          "tgn:7016833",
          "tgn:1001225",
          "tgn:7029392"
        ],
        "placetype": [
          "aat:300005926"
        ],
        "name:en": "Sīdī 'Abd Allāh",
        "id": 7528018
      }
    },
    {
      "geometry": {
        "type": "Point",
        "coordinates": [
          31.033333,
          29.433333
        ]
      },
      "type": "Feature",
      "properties": {
        "hierarchy": [
          "tgn:7528019",
          "tgn:7001242",
          "tgn:7001105",
          "tgn:7016833",
          "tgn:7029392"
        ],
        "placetype": [
          "aat:300005926"
        ],
        "name:en": "Sīdī 'Abd Allāh",
        "id": 7528019
      }
    }
  ]
}
