{
  "geometry": {
    "type": "Point",
    "coordinates": [
      16.3333,
      63.9167
    ]
  },
  "type": "Feature",
  "properties": {
    "hierarchy": [
      "tgn:1063523",
      "tgn:1000003",
      "tgn:7003773",
      "tgn:1000097",
      "tgn:7029392"
    ],
    "placetype": [
      "aat:300008347"
    ],
    "id": 1063523,
    "name:xx": "Rossön"
  }
}
