{
  "geometry": {
    "type": "Point",
    "coordinates": [
      -78.8833,
      42.9667
    ]
  },
  "type": "Feature",
  "properties": {
    "hierarchy": [
      "tgn:1134928",
      "tgn:1000001",
      "tgn:7012149",
      "tgn:1002356",
      "tgn:7007568",
      "tgn:7029392"
    ],
    "placetype": [
      "aat:300008706"
    ],
    "id": 1134928,
    "name:xx": "Twomile Creek"
  }
}
