{
  "geometry": {
    "type": "Point",
    "coordinates": [
      -79.5667,
      43.6167
    ]
  },
  "type": "Feature",
  "properties": {
    "hierarchy": [
      "tgn:1133662",
      "tgn:7005685",
      "tgn:1000001",
      "tgn:7013154",
      "tgn:7029392"
    ],
    "placetype": [
      "aat:300008706"
    ],
    "id": 1133662,
    "name:xx": "Little Etobicoke Creek"
  }
}
