{
  "geometry": {
    "type": "Point",
    "coordinates": [
      16.6167,
      47.0167
    ]
  },
  "type": "Feature",
  "properties": {
    "hierarchy": [
      "tgn:1042362",
      "tgn:1000003",
      "tgn:1000468",
      "tgn:7006278",
      "tgn:7029392"
    ],
    "placetype": [
      "aat:300008347"
    ],
    "id": 1042362,
    "name:xx": "Körmend"
  }
}
