{
  "geometry": {
    "type": "Point",
    "coordinates": [
      -78.25,
      37.2167
    ]
  },
  "type": "Feature",
  "properties": {
    "hierarchy": [
      "tgn:2113088",
      "tgn:1000001",
      "tgn:7012149",
      "tgn:2002182",
      "tgn:7007919",
      "tgn:7029392"
    ],
    "placetype": [
      "aat:300008347",
      "aat:300387210"
    ],
    "id": 2113088,
    "name:xx": "Moran"
  }
}
