{
  "geometry": {
    "type": "Point",
    "coordinates": [
      -75.2667,
      40.55
    ]
  },
  "type": "Feature",
  "properties": {
    "hierarchy": [
      "tgn:2688130",
      "tgn:1000001",
      "tgn:1002213",
      "tgn:7012149",
      "tgn:7007710",
      "tgn:7029392"
    ],
    "placetype": [
      "aat:300008746"
    ],
    "id": 2688130,
    "name:xx": "Springtown Boulder Cave"
  }
}
