{
  "geometry": {
    "type": "Point",
    "coordinates": [
      -74.95,
      43.8667
    ]
  },
  "type": "Feature",
  "properties": {
    "hierarchy": [
      "tgn:2781955",
      "tgn:1000001",
      "tgn:7012149",
      "tgn:1002472",
      "tgn:7007568",
      "tgn:7029392"
    ],
    "placetype": [
      "aat:300008680"
    ],
    "id": 2781955,
    "name:xx": "Woods Lake"
  }
}
