{
  "geometry": {
    "type": "Point",
    "coordinates": [
      -116.1167,
      41.9833
    ]
  },
  "type": "Feature",
  "properties": {
    "hierarchy": [
      "tgn:2126687",
      "tgn:1000001",
      "tgn:7012149",
      "tgn:7029392"
    ],
    "placetype": [
      "aat:300006075"
    ],
    "id": 2126687,
    "name:xx": "Agency Canal"
  }
}
