{
  "geometry": {
    "type": "Point",
    "coordinates": [
      -96.05,
      33.3833
    ]
  },
  "type": "Feature",
  "properties": {
    "hierarchy": [
      "tgn:2510480",
      "tgn:1000001",
      "tgn:7012149",
      "tgn:7007826",
      "tgn:7029392"
    ],
    "placetype": [
      "aat:300008707"
    ],
    "id": 2510480,
    "name:xx": "Middle Sulphur River"
  }
}
