{
  "geometry": {
    "type": "Point",
    "coordinates": [
      -75.5167,
      38.2833
    ]
  },
  "type": "Feature",
  "properties": {
    "hierarchy": [
      "tgn:2515751",
      "tgn:1000001",
      "tgn:7012149",
      "tgn:7007516",
      "tgn:7029392"
    ],
    "placetype": [
      "aat:300008706"
    ],
    "id": 2515751,
    "name:xx": "Millville Creek"
  }
}
