{
  "geometry": {
    "type": "Point",
    "coordinates": [
      15.65,
      45.6833
    ]
  },
  "type": "Feature",
  "properties": {
    "hierarchy": [
      "tgn:1065036",
      "tgn:1000003",
      "tgn:7017290",
      "tgn:7006663",
      "tgn:7029392"
    ],
    "placetype": [
      "aat:300008347"
    ],
    "id": 1065036,
    "name:xx": "Jastrebarsko"
  }
}
