{
  "type": "FeatureCollection",
  "features": [
    {
      "geometry": {
        "type": "Point",
        "coordinates": [
          22.5,
          39.466667
        ]
      },
      "type": "Feature",
      "properties": {
        "hierarchy": [
          "tgn:7226490",
          "tgn:7002750",
          "tgn:7001399",
          "tgn:1000003",
          "tgn:1000074",
          "tgn:7029392"
        ],
        "placetype": [
          "aat:300008347"
        ],
        "id": 7226490,
        "name:xx": "Sofón"
      }
    },
    {
      "geometry": {
        "type": "Point",
        "coordinates": [
          24.3,
          35.316667
        ]
      },
      "type": "Feature",
      "properties": {
        "hierarchy": [
          "tgn:7226491",
          "tgn:7002690",
          "tgn:7012056",
          "tgn:1000003",
          "tgn:1000074",
          "tgn:7029392"
        ],
        "placetype": [
          "aat:300008699"
        ],
        "id": 7226491,
        "name:xx": "Sofoliá Réma"
      }
    },
    {
      "geometry": {
        "type": "Point",
        "coordinates": [
          23.144503,
          37.742366
        ]
      },
      "type": "Feature",
      "properties": {
        "hierarchy": [
          "tgn:7226492",
          "tgn:7002739",
          "tgn:7017076",
          "tgn:1000003",
          "tgn:1000074",
          "tgn:7029392"
        ],
        "placetype": [
          "aat:300132316"
        ],
        "id": 7226492,
        "name:xx": "Sofikoú, Órmos"
      }
    },
    {
      "geometry": {
        "type": "Point",
        "coordinates": [
          22.483333,
          38.033333
        ]
      },
      "type": "Feature",
      "properties": {
        "hierarchy": [
          "tgn:7226494",
          "tgn:7002741",
          "tgn:7017076",
          "tgn:1000003",
          "tgn:1000074",
          "tgn:7029392"
        ],
        "placetype": [
          "aat:300008347"
        ],
        "id": 7226494,
        "name:xx": "Sofianá"
      }
    },
    {
      "geometry": {
        "type": "Point",
        "coordinates": [
          22.25,
          39.2
        ]
      },
      "type": "Feature",
      "properties": {
        "hierarchy": [
          "tgn:7226495",
          "tgn:7002748",
          "tgn:7001399",
          "tgn:1000003",
          "tgn:1000074",
          "tgn:7029392"
        ],
        "placetype": [
          "aat:300008347"
        ],
        "id": 7226495,
        "name:xx": "Sofiádha"
      }
    },
    {
      "geometry": {
        "type": "Point",
        "coordinates": [
          21.0025,
          38.480833
        ]
      },
      "type": "Feature",
      "properties": {
        "hierarchy": [
          "tgn:7226496",
          "tgn:7011167",
          "tgn:7001338",
          "tgn:1000003",
          "tgn:1000074",
          "tgn:7029392"
        ],
        "placetype": [
          "aat:300008791"
        ],
        "id": 7226496,
        "name:xx": "Sofía, Nisída"
      }
    },
    {
      "geometry": {
        "type": "Point",
        "coordinates": [
          20.6,
          39.716667
        ]
      },
      "type": "Feature",
      "properties": {
        "hierarchy": [
          "tgn:7226499",
          "tgn:7002707",
          "tgn:7002705",
          "tgn:1000003",
          "tgn:1000074",
          "tgn:7029392"
        ],
        "placetype": [
          "aat:300008699"
        ],
        "id": 7226499,
        "name:xx": "Smólitsas Potamós"
      }
    }
  ]
}
