{
  "geometry": {
    "type": "Point",
    "coordinates": [
      -73.7833,
      40.8833
    ]
  },
  "type": "Feature",
  "properties": {
    "hierarchy": [
      "tgn:2538406",
      "tgn:1000001",
      "tgn:7012149",
      "tgn:7014612",
      "tgn:7007568",
      "tgn:7029392"
    ],
    "placetype": [
      "aat:300008791"
    ],
    "id": 2538406,
    "name:xx": "Neptune Island"
  }
}
