{
  "geometry": {
    "type": "Point",
    "coordinates": [
      -75.75,
      41.2167
    ]
  },
  "type": "Feature",
  "properties": {
    "hierarchy": [
      "tgn:2451648",
      "tgn:1000001",
      "tgn:7012149",
      "tgn:1002612",
      "tgn:7007710",
      "tgn:7029392"
    ],
    "placetype": [
      "aat:300008706"
    ],
    "id": 2451648,
    "name:xx": "Little Bear Creek"
  }
}
