{
  "geometry": {
    "type": "Point",
    "coordinates": [
      -113.4833,
      43.3667
    ]
  },
  "type": "Feature",
  "properties": {
    "hierarchy": [
      "tgn:2652606",
      "tgn:1000001",
      "tgn:2000463",
      "tgn:7012149",
      "tgn:7007250",
      "tgn:7029392"
    ],
    "placetype": [
      "aat:300008798"
    ],
    "id": 2652606,
    "name:xx": "Sentinel, The"
  }
}
