{
  "geometry": {
    "type": "Point",
    "coordinates": [
      -71.8167,
      43.2167
    ]
  },
  "type": "Feature",
  "properties": {
    "hierarchy": [
      "tgn:2249751",
      "tgn:1000001",
      "tgn:2001425",
      "tgn:7012149",
      "tgn:7007564",
      "tgn:7029392"
    ],
    "placetype": [
      "aat:300008680"
    ],
    "id": 2249751,
    "name:xx": "Colleague Pond"
  }
}
