{
  "geometry": {
    "type": "Point",
    "coordinates": [
      -88.0333,
      41.95
    ]
  },
  "type": "Feature",
  "properties": {
    "hierarchy": [
      "tgn:1135396",
      "tgn:1000001",
      "tgn:7019013",
      "tgn:7012149",
      "tgn:7007251",
      "tgn:7029392"
    ],
    "placetype": [
      "aat:300008703"
    ],
    "id": 1135396,
    "name:xx": "Spring Brook"
  }
}
