{
  "geometry": {
    "type": "Point",
    "coordinates": [
      -143.4167,
      60.9833
    ]
  },
  "type": "Feature",
  "properties": {
    "hierarchy": [
      "tgn:2690719",
      "tgn:7006450",
      "tgn:1000001",
      "tgn:7012149",
      "tgn:2000086",
      "tgn:7029392"
    ],
    "placetype": [
      "aat:300008706"
    ],
    "id": 2690719,
    "name:xx": "Standard Creek"
  }
}
