{
  "type": "FeatureCollection",
  "features": [
    {
      "geometry": {
        "type": "Point",
        "coordinates": [
          4.733333,
          50.45
        ]
      },
      "type": "Feature",
      "properties": {
        "hierarchy": [
          "tgn:7244080",
          "tgn:7003466",
          "tgn:1000003",
          "tgn:1000063",
          "tgn:4012014",
          "tgn:7029392"
        ],
        "placetype": [
          "aat:300008347"
        ],
        "id": 7244080,
        "name:xx": "Jodion"
      }
    },
    {
      "geometry": {
        "type": "Point",
        "coordinates": [
          5.616667,
          49.966667
        ]
      },
      "type": "Feature",
      "properties": {
        "hierarchy": [
          "tgn:7244081",
          "tgn:7003465",
          "tgn:1000003",
          "tgn:1000063",
          "tgn:4012014",
          "tgn:7029392"
        ],
        "placetype": [
          "aat:300008347"
        ],
        "id": 7244081,
        "name:xx": "Jodenville"
      }
    },
    {
      "geometry": {
        "type": "Point",
        "coordinates": [
          5.233333,
          50.933333
        ]
      },
      "type": "Feature",
      "properties": {
        "hierarchy": [
          "tgn:7244082",
          "tgn:7003461",
          "tgn:1000003",
          "tgn:1000063",
          "tgn:7018236",
          "tgn:7029392"
        ],
        "placetype": [
          "aat:300008347"
        ],
        "id": 7244082,
        "name:xx": "Jodenstraat"
      }
    },
    {
      "geometry": {
        "type": "Point",
        "coordinates": [
          2.75,
          51.1
        ]
      },
      "type": "Feature",
      "properties": {
        "hierarchy": [
          "tgn:7244083",
          "tgn:7003458",
          "tgn:1000003",
          "tgn:1000063",
          "tgn:7018236",
          "tgn:7029392"
        ],
        "placetype": [
          "aat:300000206"
        ],
        "id": 7244083,
        "name:xx": "Jockveld"
      }
    },
    {
      "geometry": {
        "type": "Point",
        "coordinates": [
          3.228303,
          51.025766
        ]
      },
      "type": "Feature",
      "properties": {
        "hierarchy": [
          "tgn:7244084",
          "tgn:7003458",
          "tgn:1000003",
          "tgn:1000063",
          "tgn:7018236",
          "tgn:7029392"
        ],
        "placetype": [
          "aat:300008347"
        ],
        "id": 7244084,
        "name:xx": "Jo"
      }
    },
    {
      "geometry": {
        "type": "Point",
        "coordinates": [
          4.7,
          50.933333
        ]
      },
      "type": "Feature",
      "properties": {
        "hierarchy": [
          "tgn:7244085",
          "tgn:7018239",
          "tgn:1000003",
          "tgn:1000063",
          "tgn:7018236",
          "tgn:7029392"
        ],
        "placetype": [
          "aat:300000206"
        ],
        "id": 7244085,
        "name:xx": "Jezuitenhof"
      }
    },
    {
      "geometry": {
        "type": "Point",
        "coordinates": [
          4.6,
          51.133333
        ]
      },
      "type": "Feature",
      "properties": {
        "hierarchy": [
          "tgn:7244086",
          "tgn:7003456",
          "tgn:1000003",
          "tgn:1000063",
          "tgn:7018236",
          "tgn:7029392"
        ],
        "placetype": [
          "aat:300000206"
        ],
        "id": 7244086,
        "name:xx": "Jezuitenhoeve"
      }
    },
    {
      "geometry": {
        "type": "Point",
        "coordinates": [
          5.8,
          50.516667
        ]
      },
      "type": "Feature",
      "properties": {
        "hierarchy": [
          "tgn:7244087",
          "tgn:7003460",
          "tgn:1000003",
          "tgn:1000063",
          "tgn:4012014",
          "tgn:7029392"
        ],
        "placetype": [
          "aat:300008347"
        ],
        "id": 7244087,
        "name:xx": "Jevoumont"
      }
    },
    {
      "geometry": {
        "type": "Point",
        "coordinates": [
          5.75,
          50.3
        ]
      },
      "type": "Feature",
      "properties": {
        "hierarchy": [
          "tgn:7244088",
          "tgn:7003460",
          "tgn:1000003",
          "tgn:1000063",
          "tgn:4012014",
          "tgn:7029392"
        ],
        "placetype": [
          "aat:300008347"
        ],
        "id": 7244088,
        "name:xx": "Jévigne"
      }
    },
    {
      "geometry": {
        "type": "Point",
        "coordinates": [
          4.433333,
          50.6
        ]
      },
      "type": "Feature",
      "properties": {
        "hierarchy": [
          "tgn:7244089",
          "tgn:7007877",
          "tgn:1000003",
          "tgn:1000063",
          "tgn:4012014",
          "tgn:7029392"
        ],
        "placetype": [
          "aat:300008347"
        ],
        "id": 7244089,
        "name:xx": "Jeune Pioul"
      }
    }
  ]
}
