{
  "type": "FeatureCollection",
  "features": [
    {
      "geometry": {
        "type": "Point",
        "coordinates": [
          -103.5,
          37.2
        ]
      },
      "type": "Feature",
      "properties": {
        "hierarchy": [
          "tgn:2588260",
          "tgn:1000001",
          "tgn:7012149",
          "tgn:2000227",
          "tgn:7007158",
          "tgn:7029392"
        ],
        "placetype": [
          "aat:300008706"
        ],
        "id": 2588260,
        "name:xx": "Plum Creek"
      }
    },
    {
      "geometry": {
        "type": "Point",
        "coordinates": [
          -102.9667,
          37.4
        ]
      },
      "type": "Feature",
      "properties": {
        "hierarchy": [
          "tgn:2588261",
          "tgn:2000196",
          "tgn:1000001",
          "tgn:7012149",
          "tgn:7007158",
          "tgn:7029392"
        ],
        "placetype": [
          "aat:300008706"
        ],
        "id": 2588261,
        "name:xx": "Plum Creek"
      }
    },
    {
      "geometry": {
        "type": "Point",
        "coordinates": [
          -89.6167,
          38.1833
        ]
      },
      "type": "Feature",
      "properties": {
        "hierarchy": [
          "tgn:2588262",
          "tgn:1000001",
          "tgn:7012149",
          "tgn:2000526",
          "tgn:7007251",
          "tgn:7029392"
        ],
        "placetype": [
          "aat:300008706"
        ],
        "id": 2588262,
        "name:xx": "Plum Creek"
      }
    },
    {
      "geometry": {
        "type": "Point",
        "coordinates": [
          -89.4833,
          38.3833
        ]
      },
      "type": "Feature",
      "properties": {
        "hierarchy": [
          "tgn:2588263",
          "tgn:1000001",
          "tgn:7012149",
          "tgn:1002991",
          "tgn:7007251",
          "tgn:7029392"
        ],
        "placetype": [
          "aat:300008706"
        ],
        "id": 2588263,
        "name:xx": "Plum Creek"
      }
    },
    {
      "geometry": {
        "type": "Point",
        "coordinates": [
          -90.3667,
          39.7
        ]
      },
      "type": "Feature",
      "properties": {
        "hierarchy": [
          "tgn:2588264",
          "tgn:1000001",
          "tgn:7012149",
          "tgn:1002878",
          "tgn:7007251",
          "tgn:7029392"
        ],
        "placetype": [
          "aat:300008706"
        ],
        "id": 2588264,
        "name:xx": "Plum Creek"
      }
    },
    {
      "geometry": {
        "type": "Point",
        "coordinates": [
          -89.5167,
          41.8833
        ]
      },
      "type": "Feature",
      "properties": {
        "hierarchy": [
          "tgn:2588265",
          "tgn:1000001",
          "tgn:7012149",
          "tgn:1002583",
          "tgn:7007251",
          "tgn:7029392"
        ],
        "placetype": [
          "aat:300008706"
        ],
        "id": 2588265,
        "name:xx": "Plum Creek"
      }
    },
    {
      "geometry": {
        "type": "Point",
        "coordinates": [
          -85,
          38.85
        ]
      },
      "type": "Feature",
      "properties": {
        "hierarchy": [
          "tgn:2588266",
          "tgn:1000001",
          "tgn:7012149",
          "tgn:1002938",
          "tgn:7007252",
          "tgn:7029392"
        ],
        "placetype": [
          "aat:300008706"
        ],
        "id": 2588266,
        "name:xx": "Plum Creek"
      }
    },
    {
      "geometry": {
        "type": "Point",
        "coordinates": [
          -85.3,
          39.1667
        ]
      },
      "type": "Feature",
      "properties": {
        "hierarchy": [
          "tgn:2588267",
          "tgn:1000001",
          "tgn:7012149",
          "tgn:1002827",
          "tgn:7007252",
          "tgn:7029392"
        ],
        "placetype": [
          "aat:300008706"
        ],
        "id": 2588267,
        "name:xx": "Plum Creek"
      }
    },
    {
      "geometry": {
        "type": "Point",
        "coordinates": [
          -86.3,
          39.2333
        ]
      },
      "type": "Feature",
      "properties": {
        "hierarchy": [
          "tgn:2588268",
          "tgn:1000001",
          "tgn:1002209",
          "tgn:7012149",
          "tgn:7007252",
          "tgn:7029392"
        ],
        "placetype": [
          "aat:300008706"
        ],
        "id": 2588268,
        "name:xx": "Plum Creek"
      }
    },
    {
      "geometry": {
        "type": "Point",
        "coordinates": [
          -86.6167,
          39.6333
        ]
      },
      "type": "Feature",
      "properties": {
        "hierarchy": [
          "tgn:2588269",
          "tgn:1000001",
          "tgn:7012149",
          "tgn:7007252",
          "tgn:7029392"
        ],
        "placetype": [
          "aat:300008706"
        ],
        "id": 2588269,
        "name:xx": "Plum Creek"
      }
    }
  ]
}
