{
  "type": "FeatureCollection",
  "features": [
    {
      "geometry": {
        "type": "Point",
        "coordinates": [
          -99.95,
          22.583333
        ]
      },
      "type": "Feature",
      "properties": {
        "hierarchy": [
          "tgn:7433410",
          "tgn:1000001",
          "tgn:7005594",
          "tgn:7005560",
          "tgn:7029392"
        ],
        "placetype": [
          "aat:300008347"
        ],
        "id": 7433410,
        "name:xx": "Viborilla"
      }
    },
    {
      "geometry": {
        "type": "Point",
        "coordinates": [
          -104.616667,
          29.8
        ]
      },
      "type": "Feature",
      "properties": {
        "hierarchy": [
          "tgn:7433411",
          "tgn:7005581",
          "tgn:1000001",
          "tgn:7005560",
          "tgn:7029392"
        ],
        "placetype": [
          "aat:300008347"
        ],
        "id": 7433411,
        "name:xx": "Viborero"
      }
    },
    {
      "geometry": {
        "type": "Point",
        "coordinates": [
          -101.966667,
          23.516667
        ]
      },
      "type": "Feature",
      "properties": {
        "hierarchy": [
          "tgn:7433412",
          "tgn:1000001",
          "tgn:7005601",
          "tgn:7005560",
          "tgn:7029392"
        ],
        "placetype": [
          "aat:300008680"
        ],
        "id": 7433412,
        "name:xx": "Víboras, Laguna"
      }
    },
    {
      "geometry": {
        "type": "Point",
        "coordinates": [
          -104.633333,
          20.2
        ]
      },
      "type": "Feature",
      "properties": {
        "hierarchy": [
          "tgn:7433413",
          "tgn:7005586",
          "tgn:1000001",
          "tgn:7005560",
          "tgn:7029392"
        ],
        "placetype": [
          "aat:300008795"
        ],
        "id": 7433413,
        "name:xx": "Viboras, Cerro las"
      }
    },
    {
      "geometry": {
        "type": "Point",
        "coordinates": [
          -107.45,
          31.383333
        ]
      },
      "type": "Feature",
      "properties": {
        "hierarchy": [
          "tgn:7433414",
          "tgn:7005581",
          "tgn:1000001",
          "tgn:7005560",
          "tgn:7029392"
        ],
        "placetype": [
          "aat:300008795"
        ],
        "id": 7433414,
        "name:xx": "Víboras, Cerro de las"
      }
    },
    {
      "geometry": {
        "type": "Point",
        "coordinates": [
          -109.666667,
          29.783333
        ]
      },
      "type": "Feature",
      "properties": {
        "hierarchy": [
          "tgn:7433415",
          "tgn:1000001",
          "tgn:1001960",
          "tgn:7005560",
          "tgn:7029392"
        ],
        "placetype": [
          "aat:300266554",
          "aat:300008699"
        ],
        "id": 7433415,
        "name:xx": "Viboras, Arroyo de las"
      }
    },
    {
      "geometry": {
        "type": "Point",
        "coordinates": [
          -99.933333,
          24.31
        ]
      },
      "type": "Feature",
      "properties": {
        "hierarchy": [
          "tgn:7433416",
          "tgn:1000001",
          "tgn:7005589",
          "tgn:7005560",
          "tgn:7029392"
        ],
        "placetype": [
          "aat:300266554",
          "aat:300008699"
        ],
        "id": 7433416,
        "name:xx": "Viboras, Arroyo de las"
      }
    },
    {
      "geometry": {
        "type": "Point",
        "coordinates": [
          -116.266667,
          32.233333
        ]
      },
      "type": "Feature",
      "properties": {
        "hierarchy": [
          "tgn:7433417",
          "tgn:1001835",
          "tgn:1000001",
          "tgn:7005560",
          "tgn:7029392"
        ],
        "placetype": [
          "aat:300008347"
        ],
        "id": 7433417,
        "name:xx": "Víboras"
      }
    },
    {
      "geometry": {
        "type": "Point",
        "coordinates": [
          -99.016667,
          20.083333
        ]
      },
      "type": "Feature",
      "properties": {
        "hierarchy": [
          "tgn:7433419",
          "tgn:7005587",
          "tgn:1000001",
          "tgn:7005560",
          "tgn:7029392"
        ],
        "placetype": [
          "aat:300008347"
        ],
        "id": 7433419,
        "name:xx": "Víboras"
      }
    }
  ]
}
