{
  "type": "FeatureCollection",
  "features": [
    {
      "geometry": {
        "type": "Point",
        "coordinates": [
          2.0833,
          44.0833
        ]
      },
      "type": "Feature",
      "properties": {
        "hierarchy": [
          "tgn:4007324",
          "tgn:1000003",
          "tgn:7002889",
          "tgn:1000070",
          "tgn:7029392"
        ],
        "placetype": [
          "aat:300008347"
        ],
        "id": 4007324,
        "name:xx": "Monestiès"
      }
    },
    {
      "geometry": {
        "type": "Point",
        "coordinates": [
          -0.716667,
          38.383333
        ]
      },
      "type": "Feature",
      "properties": {
        "hierarchy": [
          "tgn:4007328",
          "tgn:7002804",
          "tgn:1000003",
          "tgn:7002793",
          "tgn:1000095",
          "tgn:7029392"
        ],
        "placetype": [
          "aat:300008347"
        ],
        "id": 4007328,
        "name:xx": "Monforte del Cid"
      }
    }
  ]
}
