{
  "geometry": {
    "type": "Point",
    "coordinates": [
      -102.833333,
      25.25
    ]
  },
  "type": "Feature",
  "properties": {
    "hierarchy": [
      "tgn:7435389",
      "tgn:1001853",
      "tgn:1000001",
      "tgn:7005560",
      "tgn:7029392"
    ],
    "placetype": [
      "aat:300008763"
    ],
    "id": 7435389,
    "name:xx": "Víoora, Cañón de la"
  }
}
