{
  "geometry": {
    "type": "Point",
    "coordinates": [
      -147.9333,
      62.4667
    ]
  },
  "type": "Feature",
  "properties": {
    "hierarchy": [
      "tgn:2347315",
      "tgn:7006450",
      "tgn:1000001",
      "tgn:2124053",
      "tgn:7012149",
      "tgn:7029392"
    ],
    "placetype": [
      "aat:300008706"
    ],
    "id": 2347315,
    "name:xx": "George Creek"
  }
}
