{
  "geometry": {
    "type": "Point",
    "coordinates": [
      -88.4333,
      44.1833
    ]
  },
  "type": "Feature",
  "properties": {
    "hierarchy": [
      "tgn:2293115",
      "tgn:1000001",
      "tgn:7012149",
      "tgn:2002363",
      "tgn:7007922",
      "tgn:7029392"
    ],
    "placetype": [
      "aat:300008791"
    ],
    "id": 2293115,
    "name:xx": "Doty Island"
  }
}
