{
  "geometry": {
    "type": "Point",
    "coordinates": [
      33.5333,
      -21.05
    ]
  },
  "type": "Feature",
  "properties": {
    "hierarchy": [
      "tgn:1091641",
      "tgn:7001242",
      "tgn:1000891",
      "tgn:1000180",
      "tgn:7029392"
    ],
    "placetype": [
      "aat:300008347"
    ],
    "id": 1091641,
    "name:xx": "Mutanda"
  }
}
