{
  "geometry": {
    "type": "Point",
    "coordinates": [
      -91.8667,
      39.75
    ]
  },
  "type": "Feature",
  "properties": {
    "hierarchy": [
      "tgn:2658927",
      "tgn:1000001",
      "tgn:7012149",
      "tgn:7007523",
      "tgn:7029392"
    ],
    "placetype": [
      "aat:300008699"
    ],
    "id": 2658927,
    "name:xx": "Sherry Branch"
  }
}
