{
  "type": "FeatureCollection",
  "features": [
    {
      "geometry": {
        "type": "Point",
        "coordinates": [
          -86.5,
          39.4
        ]
      },
      "type": "Feature",
      "properties": {
        "hierarchy": [
          "tgn:2031210",
          "tgn:1000001",
          "tgn:7012149",
          "tgn:1002694",
          "tgn:7007252",
          "tgn:7029392"
        ],
        "placetype": [
          "aat:300008347"
        ],
        "id": 2031210,
        "name:xx": "Browns Crossing"
      }
    },
    {
      "geometry": {
        "type": "Point",
        "coordinates": [
          -86.0333,
          38.8667
        ]
      },
      "type": "Feature",
      "properties": {
        "hierarchy": [
          "tgn:2031212",
          "tgn:1000001",
          "tgn:7012149",
          "tgn:1002508",
          "tgn:7007252",
          "tgn:7029392"
        ],
        "placetype": [
          "aat:300008347"
        ],
        "id": 2031212,
        "name:xx": "Brownstown"
      }
    },
    {
      "geometry": {
        "type": "Point",
        "coordinates": [
          -86.9833,
          39.9
        ]
      },
      "type": "Feature",
      "properties": {
        "hierarchy": [
          "tgn:2031213",
          "tgn:1000001",
          "tgn:7012149",
          "tgn:2000547",
          "tgn:7007252",
          "tgn:7029392"
        ],
        "placetype": [
          "aat:300008347"
        ],
        "id": 2031213,
        "name:xx": "Browns Valley"
      }
    },
    {
      "geometry": {
        "type": "Point",
        "coordinates": [
          -85,
          39.65
        ]
      },
      "type": "Feature",
      "properties": {
        "hierarchy": [
          "tgn:2031214",
          "tgn:1000001",
          "tgn:7012149",
          "tgn:1002962",
          "tgn:7007252",
          "tgn:7029392"
        ],
        "placetype": [
          "aat:300008347"
        ],
        "id": 2031214,
        "name:xx": "Brownsville"
      }
    },
    {
      "geometry": {
        "type": "Point",
        "coordinates": [
          -87.4,
          38.75
        ]
      },
      "type": "Feature",
      "properties": {
        "hierarchy": [
          "tgn:2031216",
          "tgn:1000001",
          "tgn:7012149",
          "tgn:2000545",
          "tgn:7007252",
          "tgn:7029392"
        ],
        "placetype": [
          "aat:300008347"
        ],
        "id": 2031216,
        "name:xx": "Bruceville"
      }
    },
    {
      "geometry": {
        "type": "Point",
        "coordinates": [
          -87.0167,
          41.6167
        ]
      },
      "type": "Feature",
      "properties": {
        "hierarchy": [
          "tgn:2031217",
          "tgn:1000001",
          "tgn:7012149",
          "tgn:1002798",
          "tgn:7007252",
          "tgn:7029392"
        ],
        "placetype": [
          "aat:300008347"
        ],
        "id": 2031217,
        "name:xx": "Brummitt Acres"
      }
    },
    {
      "geometry": {
        "type": "Point",
        "coordinates": [
          -87.1167,
          39.1833
        ]
      },
      "type": "Feature",
      "properties": {
        "hierarchy": [
          "tgn:2031218",
          "tgn:1000001",
          "tgn:2000540",
          "tgn:7012149",
          "tgn:7007252",
          "tgn:7029392"
        ],
        "placetype": [
          "aat:300008347",
          "aat:300387210"
        ],
        "id": 2031218,
        "name:xx": "Brunswick"
      }
    },
    {
      "geometry": {
        "type": "Point",
        "coordinates": [
          -87.5,
          41.3667
        ]
      },
      "type": "Feature",
      "properties": {
        "hierarchy": [
          "tgn:2031219",
          "tgn:1000001",
          "tgn:7012149",
          "tgn:1002569",
          "tgn:7007252",
          "tgn:7029392"
        ],
        "placetype": [
          "aat:300008347"
        ],
        "id": 2031219,
        "name:xx": "Brunswick"
      }
    }
  ]
}
