{
  "geometry": {
    "type": "Point",
    "coordinates": [
      -81.0167,
      26.8667
    ]
  },
  "type": "Feature",
  "properties": {
    "hierarchy": [
      "tgn:2522490",
      "tgn:1000001",
      "tgn:1002408",
      "tgn:7012149",
      "tgn:7007240",
      "tgn:7029392"
    ],
    "placetype": [
      "aat:300132316"
    ],
    "id": 2522490,
    "name:xx": "Moonshine Bay"
  }
}
