{
  "type": "FeatureCollection",
  "features": [
    {
      "geometry": {
        "type": "Point",
        "coordinates": [
          -77.0333,
          42.6
        ]
      },
      "type": "Feature",
      "properties": {
        "hierarchy": [
          "tgn:2072210",
          "tgn:1000001",
          "tgn:7012149",
          "tgn:1003045",
          "tgn:7007568",
          "tgn:7029392"
        ],
        "placetype": [
          "aat:300008347",
          "aat:300387210"
        ],
        "id": 2072210,
        "name:xx": "Second Milo"
      }
    },
    {
      "geometry": {
        "type": "Point",
        "coordinates": [
          -76.8833,
          42
        ]
      },
      "type": "Feature",
      "properties": {
        "hierarchy": [
          "tgn:2072211",
          "tgn:1000001",
          "tgn:1002261",
          "tgn:7012149",
          "tgn:7007568",
          "tgn:7029392"
        ],
        "placetype": [
          "aat:300008347"
        ],
        "id": 2072211,
        "name:xx": "Seeley Creek"
      }
    },
    {
      "geometry": {
        "type": "Point",
        "coordinates": [
          -73.0333,
          40.85
        ]
      },
      "type": "Feature",
      "properties": {
        "hierarchy": [
          "tgn:2072212",
          "tgn:1000001",
          "tgn:7012149",
          "tgn:1002924",
          "tgn:7007568",
          "tgn:7029392"
        ],
        "placetype": [
          "aat:300008347"
        ],
        "id": 2072212,
        "name:xx": "Selden"
      }
    },
    {
      "geometry": {
        "type": "Point",
        "coordinates": [
          -73.7833,
          42.5167
        ]
      },
      "type": "Feature",
      "properties": {
        "hierarchy": [
          "tgn:2072216",
          "tgn:1002139",
          "tgn:1000001",
          "tgn:7012149",
          "tgn:7007568",
          "tgn:7029392"
        ],
        "placetype": [
          "aat:300008347"
        ],
        "id": 2072216,
        "name:xx": "Selkirk"
      }
    },
    {
      "geometry": {
        "type": "Point",
        "coordinates": [
          -74.9833,
          44.4833
        ]
      },
      "type": "Feature",
      "properties": {
        "hierarchy": [
          "tgn:2072218",
          "tgn:1000001",
          "tgn:7012149",
          "tgn:7016021",
          "tgn:7007568",
          "tgn:7029392"
        ],
        "placetype": [
          "aat:300008347",
          "aat:300387210"
        ],
        "id": 2072218,
        "name:xx": "Sellecks Corners"
      }
    },
    {
      "geometry": {
        "type": "Point",
        "coordinates": [
          -76.3,
          42.7167
        ]
      },
      "type": "Feature",
      "properties": {
        "hierarchy": [
          "tgn:2072219",
          "tgn:1000001",
          "tgn:1002246",
          "tgn:7012149",
          "tgn:7007568",
          "tgn:7029392"
        ],
        "placetype": [
          "aat:300008347"
        ],
        "id": 2072219,
        "name:xx": "Sempronius"
      }
    }
  ]
}
