{
  "geometry": {
    "type": "Point",
    "coordinates": [
      34.89847,
      23.377029
    ]
  },
  "type": "Feature",
  "properties": {
    "hierarchy": [
      "tgn:7520673",
      "tgn:7001242",
      "tgn:7001311",
      "tgn:7016833",
      "tgn:7029392"
    ],
    "placetype": [
      "aat:300379998"
    ],
    "name:en": "Abraq, Wâdi",
    "id": 7520673
  }
}
