{
  "geometry": {
    "type": "Point",
    "coordinates": [
      -102.65,
      21.8125
    ]
  },
  "type": "Feature",
  "properties": {
    "hierarchy": [
      "tgn:7421322",
      "tgn:7005579",
      "tgn:1000001",
      "tgn:7005560",
      "tgn:7029392"
    ],
    "placetype": [
      "aat:300008347"
    ],
    "id": 7421322,
    "name:xx": "La Loma"
  }
}
