{
  "geometry": {
    "type": "Point",
    "coordinates": [
      -121.1333,
      41.2667
    ]
  },
  "type": "Feature",
  "properties": {
    "hierarchy": [
      "tgn:2392125",
      "tgn:1000001",
      "tgn:7012149",
      "tgn:7007157",
      "tgn:2000186",
      "tgn:7029392"
    ],
    "placetype": [
      "aat:300006191"
    ],
    "id": 2392125,
    "name:xx": "Hines Reservoir"
  }
}
