{
  "geometry": {
    "type": "Point",
    "coordinates": [
      140.1333,
      35.8667
    ]
  },
  "type": "Feature",
  "properties": {
    "hierarchy": [
      "tgn:1125659",
      "tgn:1000004",
      "tgn:7000894",
      "tgn:1000120",
      "tgn:7029392"
    ],
    "placetype": [
      "aat:300008707"
    ],
    "id": 1125659,
    "name:xx": "Kokai-gawa"
  }
}
