{
  "geometry": {
    "type": "Point",
    "coordinates": [
      122.1667,
      42.5333
    ]
  },
  "type": "Feature",
  "properties": {
    "hierarchy": [
      "tgn:1069339",
      "tgn:1000004",
      "tgn:1001390",
      "tgn:1000111",
      "tgn:7029392"
    ],
    "placetype": [
      "aat:300008347"
    ],
    "id": 1069339,
    "name:xx": "Jinjiawopu"
  }
}
