{
  "geometry": {
    "type": "Point",
    "coordinates": [
      -87.6667,
      46.45
    ]
  },
  "type": "Feature",
  "properties": {
    "hierarchy": [
      "tgn:2052754",
      "tgn:1000001",
      "tgn:7012149",
      "tgn:2000975",
      "tgn:7007520",
      "tgn:7029392"
    ],
    "placetype": [
      "aat:300008347"
    ],
    "id": 2052754,
    "name:xx": "National Mine"
  }
}
