{
  "geometry": {
    "type": "Point",
    "coordinates": [
      -83.05,
      38.05
    ]
  },
  "type": "Feature",
  "properties": {
    "hierarchy": [
      "tgn:2039542",
      "tgn:1000001",
      "tgn:7012149",
      "tgn:1002354",
      "tgn:7007255",
      "tgn:7029392"
    ],
    "placetype": [
      "aat:300008347"
    ],
    "id": 2039542,
    "name:xx": "Isonville"
  }
}
