{
  "type": "FeatureCollection",
  "features": [
    {
      "geometry": {
        "type": "Point",
        "coordinates": [
          9.616667,
          45.966667
        ]
      },
      "type": "Feature",
      "properties": {
        "hierarchy": [
          "tgn:7046030",
          "tgn:7005023",
          "tgn:1000003",
          "tgn:7003237",
          "tgn:1000080",
          "tgn:7029392"
        ],
        "placetype": [
          "aat:300008347"
        ],
        "id": 7046030,
        "name:xx": "Cassiglio"
      }
    },
    {
      "geometry": {
        "type": "Point",
        "coordinates": [
          13.383333,
          43.566667
        ]
      },
      "type": "Feature",
      "properties": {
        "hierarchy": [
          "tgn:7046033",
          "tgn:1003429",
          "tgn:1000003",
          "tgn:7003240",
          "tgn:1000080",
          "tgn:7029392"
        ],
        "placetype": [
          "aat:300008347"
        ],
        "id": 7046033,
        "name:xx": "Cassero"
      }
    },
    {
      "geometry": {
        "type": "Point",
        "coordinates": [
          9.5,
          44.4
        ]
      },
      "type": "Feature",
      "properties": {
        "hierarchy": [
          "tgn:7046034",
          "tgn:1000003",
          "tgn:7003143",
          "tgn:7003236",
          "tgn:1000080",
          "tgn:7029392"
        ],
        "placetype": [
          "aat:300008347"
        ],
        "id": 7046034,
        "name:xx": "Cassego"
      }
    },
    {
      "geometry": {
        "type": "Point",
        "coordinates": [
          10.25,
          46.383333
        ]
      },
      "type": "Feature",
      "properties": {
        "hierarchy": [
          "tgn:7046035",
          "tgn:1000003",
          "tgn:7003152",
          "tgn:7003237",
          "tgn:1000080",
          "tgn:7029392"
        ],
        "placetype": [
          "aat:300008347"
        ],
        "id": 7046035,
        "name:xx": "Cassaurolo"
      }
    },
    {
      "geometry": {
        "type": "Point",
        "coordinates": [
          8.866667,
          44.766667
        ]
      },
      "type": "Feature",
      "properties": {
        "hierarchy": [
          "tgn:7046037",
          "tgn:1003428",
          "tgn:1000003",
          "tgn:7003120",
          "tgn:1000080",
          "tgn:7029392"
        ],
        "placetype": [
          "aat:300008347"
        ],
        "id": 7046037,
        "name:xx": "Cassano"
      }
    }
  ]
}
