{
  "type": "FeatureCollection",
  "features": [
    {
      "geometry": {
        "type": "Point",
        "coordinates": [
          -77.75,
          42.3167
        ]
      },
      "type": "Feature",
      "properties": {
        "hierarchy": [
          "tgn:2641640",
          "tgn:1002141",
          "tgn:1000001",
          "tgn:7012149",
          "tgn:7007568",
          "tgn:7029392"
        ],
        "placetype": [
          "aat:300008798"
        ],
        "id": 2641640,
        "name:xx": "Sand Hill"
      }
    },
    {
      "geometry": {
        "type": "Point",
        "coordinates": [
          -75,
          43.25
        ]
      },
      "type": "Feature",
      "properties": {
        "hierarchy": [
          "tgn:2641641",
          "tgn:1000001",
          "tgn:7012149",
          "tgn:1002472",
          "tgn:7007568",
          "tgn:7029392"
        ],
        "placetype": [
          "aat:300008798"
        ],
        "id": 2641641,
        "name:xx": "Sand Hill"
      }
    },
    {
      "geometry": {
        "type": "Point",
        "coordinates": [
          -78.5167,
          34.0833
        ]
      },
      "type": "Feature",
      "properties": {
        "hierarchy": [
          "tgn:2641642",
          "tgn:1000001",
          "tgn:2001472",
          "tgn:7012149",
          "tgn:7007709",
          "tgn:7029392"
        ],
        "placetype": [
          "aat:300008798"
        ],
        "id": 2641642,
        "name:xx": "Sand Hill"
      }
    },
    {
      "geometry": {
        "type": "Point",
        "coordinates": [
          -82.7333,
          39.6667
        ]
      },
      "type": "Feature",
      "properties": {
        "hierarchy": [
          "tgn:2641643",
          "tgn:1000001",
          "tgn:7012149",
          "tgn:2001611",
          "tgn:7007706",
          "tgn:7029392"
        ],
        "placetype": [
          "aat:300008798"
        ],
        "id": 2641643,
        "name:xx": "Sand Hill"
      }
    },
    {
      "geometry": {
        "type": "Point",
        "coordinates": [
          -82.6,
          38.6
        ]
      },
      "type": "Feature",
      "properties": {
        "hierarchy": [
          "tgn:2641644",
          "tgn:1000001",
          "tgn:7012149",
          "tgn:2001615",
          "tgn:7007706",
          "tgn:7029392"
        ],
        "placetype": [
          "aat:300008798"
        ],
        "id": 2641644,
        "name:xx": "Sand Hill"
      }
    },
    {
      "geometry": {
        "type": "Point",
        "coordinates": [
          -82.95,
          39
        ]
      },
      "type": "Feature",
      "properties": {
        "hierarchy": [
          "tgn:2641645",
          "tgn:1000001",
          "tgn:7012149",
          "tgn:1002788",
          "tgn:7007706",
          "tgn:7029392"
        ],
        "placetype": [
          "aat:300008798"
        ],
        "id": 2641645,
        "name:xx": "Sand Hill"
      }
    },
    {
      "geometry": {
        "type": "Point",
        "coordinates": [
          -82.9167,
          39.3833
        ]
      },
      "type": "Feature",
      "properties": {
        "hierarchy": [
          "tgn:2641646",
          "tgn:1000001",
          "tgn:7012149",
          "tgn:1002835",
          "tgn:7007706",
          "tgn:7029392"
        ],
        "placetype": [
          "aat:300008798"
        ],
        "id": 2641646,
        "name:xx": "Sand Hill"
      }
    },
    {
      "geometry": {
        "type": "Point",
        "coordinates": [
          -83.5667,
          41.7167
        ]
      },
      "type": "Feature",
      "properties": {
        "hierarchy": [
          "tgn:2641647",
          "tgn:1000001",
          "tgn:7012149",
          "tgn:1002611",
          "tgn:7007706",
          "tgn:7029392"
        ],
        "placetype": [
          "aat:300008798"
        ],
        "id": 2641647,
        "name:xx": "Sand Hill"
      }
    },
    {
      "geometry": {
        "type": "Point",
        "coordinates": [
          -81.2667,
          41.5167
        ]
      },
      "type": "Feature",
      "properties": {
        "hierarchy": [
          "tgn:2641648",
          "tgn:1000001",
          "tgn:7012149",
          "tgn:7021516",
          "tgn:7007706",
          "tgn:7029392"
        ],
        "placetype": [
          "aat:300008798"
        ],
        "id": 2641648,
        "name:xx": "Sand Hill"
      }
    },
    {
      "geometry": {
        "type": "Point",
        "coordinates": [
          -118.9667,
          43.6167
        ]
      },
      "type": "Feature",
      "properties": {
        "hierarchy": [
          "tgn:2641649",
          "tgn:1000001",
          "tgn:7012149",
          "tgn:2001709",
          "tgn:7007708",
          "tgn:7029392"
        ],
        "placetype": [
          "aat:300008798"
        ],
        "id": 2641649,
        "name:xx": "Sand Hill"
      }
    }
  ]
}
