{
  "geometry": {
    "type": "Point",
    "coordinates": [
      5.3667,
      46.2667
    ]
  },
  "type": "Feature",
  "properties": {
    "hierarchy": [
      "tgn:1035915",
      "tgn:1000003",
      "tgn:1000070",
      "tgn:7002897",
      "tgn:7029392"
    ],
    "placetype": [
      "aat:300008347"
    ],
    "id": 1035915,
    "name:xx": "Treffort"
  }
}
