{
  "geometry": {
    "type": "Point",
    "coordinates": [
      -102.3333,
      30.4833
    ]
  },
  "type": "Feature",
  "properties": {
    "hierarchy": [
      "tgn:2501844",
      "tgn:1000001",
      "tgn:7012149",
      "tgn:7007826",
      "tgn:7029392"
    ],
    "placetype": [
      "aat:300008706"
    ],
    "id": 2501844,
    "name:xx": "McKay Creek"
  }
}
