{
  "geometry": {
    "type": "Point",
    "coordinates": [
      -108.9667,
      32.9833
    ]
  },
  "type": "Feature",
  "properties": {
    "hierarchy": [
      "tgn:2135576",
      "tgn:1000001",
      "tgn:7012149",
      "tgn:7029392"
    ],
    "placetype": [
      "aat:300008706"
    ],
    "id": 2135576,
    "name:xx": "Apache Creek"
  }
}
