{
  "geometry": {
    "type": "Point",
    "coordinates": [
      6.433333,
      50.85
    ]
  },
  "type": "Feature",
  "properties": {
    "hierarchy": [
      "tgn:7129044",
      "tgn:1000003",
      "tgn:7003677",
      "tgn:7000084",
      "tgn:7029392"
    ],
    "placetype": [
      "aat:300000206"
    ],
    "id": 7129044,
    "name:xx": "Ober Köttenich"
  }
}
