{
  "geometry": {
    "type": "Point",
    "coordinates": [
      69.15,
      39.7667
    ]
  },
  "type": "Feature",
  "properties": {
    "hierarchy": [
      "tgn:1054905",
      "tgn:7011631",
      "tgn:1000004",
      "tgn:7014835",
      "tgn:7029392"
    ],
    "placetype": [
      "aat:300008347"
    ],
    "id": 1054905,
    "name:xx": "Kalininabad"
  }
}
