{
  "type": "FeatureCollection",
  "features": [
    {
      "geometry": {
        "type": "Point",
        "coordinates": [
          -123.5667,
          43.2333
        ]
      },
      "type": "Feature",
      "properties": {
        "hierarchy": [
          "tgn:2329660",
          "tgn:1000001",
          "tgn:7012149",
          "tgn:2001706",
          "tgn:7007708",
          "tgn:7029392"
        ],
        "placetype": [
          "aat:300008706"
        ],
        "id": 2329660,
        "name:xx": "Fivemile Creek"
      }
    },
    {
      "geometry": {
        "type": "Point",
        "coordinates": [
          -117.35,
          44.7667
        ]
      },
      "type": "Feature",
      "properties": {
        "hierarchy": [
          "tgn:2329661",
          "tgn:7013349",
          "tgn:1000001",
          "tgn:7012149",
          "tgn:7007708",
          "tgn:7029392"
        ],
        "placetype": [
          "aat:300008706"
        ],
        "id": 2329661,
        "name:xx": "Fivemile Creek"
      }
    },
    {
      "geometry": {
        "type": "Point",
        "coordinates": [
          -119.1833,
          45.1833
        ]
      },
      "type": "Feature",
      "properties": {
        "hierarchy": [
          "tgn:2329662",
          "tgn:1000001",
          "tgn:7012149",
          "tgn:7007708",
          "tgn:7029392"
        ],
        "placetype": [
          "aat:300008706"
        ],
        "id": 2329662,
        "name:xx": "Fivemile Creek"
      }
    },
    {
      "geometry": {
        "type": "Point",
        "coordinates": [
          -79.6167,
          41.75
        ]
      },
      "type": "Feature",
      "properties": {
        "hierarchy": [
          "tgn:2329663",
          "tgn:1000001",
          "tgn:1002308",
          "tgn:7012149",
          "tgn:7007710",
          "tgn:7029392"
        ],
        "placetype": [
          "aat:300008706"
        ],
        "id": 2329663,
        "name:xx": "Fivemile Creek"
      }
    },
    {
      "geometry": {
        "type": "Point",
        "coordinates": [
          -82.7,
          34.5167
        ]
      },
      "type": "Feature",
      "properties": {
        "hierarchy": [
          "tgn:2329664",
          "tgn:2001728",
          "tgn:1000001",
          "tgn:7012149",
          "tgn:7007712",
          "tgn:7029392"
        ],
        "placetype": [
          "aat:300008706"
        ],
        "id": 2329664,
        "name:xx": "Fivemile Creek"
      }
    },
    {
      "geometry": {
        "type": "Point",
        "coordinates": [
          -99,
          43.3833
        ]
      },
      "type": "Feature",
      "properties": {
        "hierarchy": [
          "tgn:2329665",
          "tgn:1000001",
          "tgn:2001781",
          "tgn:7012149",
          "tgn:7007713",
          "tgn:7029392"
        ],
        "placetype": [
          "aat:300008706"
        ],
        "id": 2329665,
        "name:xx": "Fivemile Creek"
      }
    },
    {
      "geometry": {
        "type": "Point",
        "coordinates": [
          -99.45,
          43.4667
        ]
      },
      "type": "Feature",
      "properties": {
        "hierarchy": [
          "tgn:2329666",
          "tgn:1000001",
          "tgn:7012149",
          "tgn:7007713",
          "tgn:7029392"
        ],
        "placetype": [
          "aat:300008706"
        ],
        "id": 2329666,
        "name:xx": "Fivemile Creek"
      }
    },
    {
      "geometry": {
        "type": "Point",
        "coordinates": [
          -102.9333,
          45.8167
        ]
      },
      "type": "Feature",
      "properties": {
        "hierarchy": [
          "tgn:2329667",
          "tgn:1000001",
          "tgn:7012149",
          "tgn:2001822",
          "tgn:7007713",
          "tgn:7029392"
        ],
        "placetype": [
          "aat:300008706"
        ],
        "id": 2329667,
        "name:xx": "Fivemile Creek"
      }
    },
    {
      "geometry": {
        "type": "Point",
        "coordinates": [
          -87.2333,
          36.1
        ]
      },
      "type": "Feature",
      "properties": {
        "hierarchy": [
          "tgn:2329668",
          "tgn:1000001",
          "tgn:7012149",
          "tgn:2001858",
          "tgn:7007825",
          "tgn:7029392"
        ],
        "placetype": [
          "aat:300008706"
        ],
        "id": 2329668,
        "name:xx": "Fivemile Creek"
      }
    },
    {
      "geometry": {
        "type": "Point",
        "coordinates": [
          -86.8,
          35.8167
        ]
      },
      "type": "Feature",
      "properties": {
        "hierarchy": [
          "tgn:2329669",
          "tgn:1000001",
          "tgn:7012149",
          "tgn:2001930",
          "tgn:7007825",
          "tgn:7029392"
        ],
        "placetype": [
          "aat:300008706"
        ],
        "id": 2329669,
        "name:xx": "Fivemile Creek"
      }
    }
  ]
}
