{
  "geometry": {
    "type": "Point",
    "coordinates": [
      58.45,
      48.55
    ]
  },
  "type": "Feature",
  "properties": {
    "hierarchy": [
      "tgn:1057197",
      "tgn:7011450",
      "tgn:1000004",
      "tgn:7014786",
      "tgn:7029392"
    ],
    "placetype": [
      "aat:300008347"
    ],
    "id": 1057197,
    "name:xx": "Mugodzharskaya"
  }
}
