{
  "geometry": {
    "type": "Point",
    "coordinates": [
      -100.0333,
      29.15
    ]
  },
  "type": "Feature",
  "properties": {
    "hierarchy": [
      "tgn:2346340",
      "tgn:1000001",
      "tgn:7012149",
      "tgn:2002087",
      "tgn:7007826",
      "tgn:7029392"
    ],
    "placetype": [
      "aat:300000390"
    ],
    "id": 2346340,
    "name:xx": "Gato Quarry"
  }
}
