{
  "geometry": {
    "type": "Point",
    "coordinates": [
      -54.3833,
      49.6333
    ]
  },
  "type": "Feature",
  "properties": {
    "hierarchy": [
      "tgn:1014174",
      "tgn:7005685",
      "tgn:7005807",
      "tgn:1000001",
      "tgn:7005801",
      "tgn:7029392"
    ],
    "placetype": [
      "aat:300008347"
    ],
    "id": 1014174,
    "name:xx": "Change Islands"
  }
}
