{
  "geometry": {
    "type": "Point",
    "coordinates": [
      -87.3167,
      35.35
    ]
  },
  "type": "Feature",
  "properties": {
    "hierarchy": [
      "tgn:2594918",
      "tgn:1000001",
      "tgn:7012149",
      "tgn:2001886",
      "tgn:7007825",
      "tgn:7029392"
    ],
    "placetype": [
      "aat:300008699"
    ],
    "id": 2594918,
    "name:xx": "Possumtrot Branch"
  }
}
