{
  "geometry": {
    "type": "Point",
    "coordinates": [
      -86.0833,
      44.0333
    ]
  },
  "type": "Feature",
  "properties": {
    "hierarchy": [
      "tgn:2208207",
      "tgn:1000001",
      "tgn:7012149",
      "tgn:2000976",
      "tgn:7007520",
      "tgn:7029392"
    ],
    "placetype": [
      "aat:300008905"
    ],
    "id": 2208207,
    "name:xx": "Burley Lake"
  }
}
