{
  "geometry": {
    "type": "Point",
    "coordinates": [
      -74.6667,
      39.3333
    ]
  },
  "type": "Feature",
  "properties": {
    "hierarchy": [
      "tgn:2064668",
      "tgn:1002157",
      "tgn:1000001",
      "tgn:7012149",
      "tgn:7007565",
      "tgn:7029392"
    ],
    "placetype": [
      "aat:300008347"
    ],
    "id": 2064668,
    "name:xx": "English Creek"
  }
}
