{
  "geometry": {
    "type": "Point",
    "coordinates": [
      121.5833,
      31.8333
    ]
  },
  "type": "Feature",
  "properties": {
    "hierarchy": [
      "tgn:1071360",
      "tgn:1000004",
      "tgn:7002081",
      "tgn:1000111",
      "tgn:7029392"
    ],
    "placetype": [
      "aat:300008347"
    ],
    "id": 1071360,
    "name:xx": "Sanxingzhen"
  }
}
