{
  "type": "FeatureCollection",
  "features": [
    {
      "geometry": {
        "type": "Point",
        "coordinates": [
          13.483333,
          54.066667
        ]
      },
      "type": "Feature",
      "properties": {
        "hierarchy": [
          "tgn:7182690",
          "tgn:1000003",
          "tgn:7000094",
          "tgn:7000084",
          "tgn:7029392"
        ],
        "placetype": [
          "aat:300008347"
        ],
        "id": 7182690,
        "name:xx": "Friedrichshagen"
      }
    },
    {
      "geometry": {
        "type": "Point",
        "coordinates": [
          11.283333,
          53.816667
        ]
      },
      "type": "Feature",
      "properties": {
        "hierarchy": [
          "tgn:7182691",
          "tgn:1000003",
          "tgn:7000094",
          "tgn:7000084",
          "tgn:7029392"
        ],
        "placetype": [
          "aat:300008347"
        ],
        "id": 7182691,
        "name:xx": "Friedrichshagen"
      }
    },
    {
      "geometry": {
        "type": "Point",
        "coordinates": [
          12.4,
          53.783333
        ]
      },
      "type": "Feature",
      "properties": {
        "hierarchy": [
          "tgn:7182692",
          "tgn:1000003",
          "tgn:7000094",
          "tgn:7000084",
          "tgn:7029392"
        ],
        "placetype": [
          "aat:300008347"
        ],
        "id": 7182692,
        "name:xx": "Friedrichshagen"
      }
    },
    {
      "geometry": {
        "type": "Point",
        "coordinates": [
          13.883333,
          53.633333
        ]
      },
      "type": "Feature",
      "properties": {
        "hierarchy": [
          "tgn:7182693",
          "tgn:1000003",
          "tgn:7000094",
          "tgn:7000084",
          "tgn:7029392"
        ],
        "placetype": [
          "aat:300008347"
        ],
        "id": 7182693,
        "name:xx": "Friedrichshagen"
      }
    },
    {
      "geometry": {
        "type": "Point",
        "coordinates": [
          9.233333,
          52.133333
        ]
      },
      "type": "Feature",
      "properties": {
        "hierarchy": [
          "tgn:7182694",
          "tgn:1000003",
          "tgn:7003676",
          "tgn:7000084",
          "tgn:7029392"
        ],
        "placetype": [
          "aat:300008347"
        ],
        "id": 7182694,
        "name:xx": "Friedrichshagen"
      }
    },
    {
      "geometry": {
        "type": "Point",
        "coordinates": [
          11,
          53.666667
        ]
      },
      "type": "Feature",
      "properties": {
        "hierarchy": [
          "tgn:7182695",
          "tgn:1000003",
          "tgn:7000094",
          "tgn:7000084",
          "tgn:7029392"
        ],
        "placetype": [
          "aat:300000206"
        ],
        "id": 7182695,
        "name:xx": "Friedrichshagen"
      }
    },
    {
      "geometry": {
        "type": "Point",
        "coordinates": [
          9.483333,
          47.633333
        ]
      },
      "type": "Feature",
      "properties": {
        "hierarchy": [
          "tgn:7182696",
          "tgn:7003692",
          "tgn:1000003",
          "tgn:7000084",
          "tgn:7029392"
        ],
        "placetype": [
          "aat:300132316"
        ],
        "id": 7182696,
        "name:xx": "Friedrichshafener Bucht"
      }
    },
    {
      "geometry": {
        "type": "Point",
        "coordinates": [
          12.566667,
          53.116667
        ]
      },
      "type": "Feature",
      "properties": {
        "hierarchy": [
          "tgn:7182698",
          "tgn:7000096",
          "tgn:1000003",
          "tgn:7000084",
          "tgn:7029392"
        ],
        "placetype": [
          "aat:300008347"
        ],
        "id": 7182698,
        "name:xx": "Friedrichsgüte"
      }
    },
    {
      "geometry": {
        "type": "Point",
        "coordinates": [
          8.8,
          51.55
        ]
      },
      "type": "Feature",
      "properties": {
        "hierarchy": [
          "tgn:7182699",
          "tgn:1000003",
          "tgn:7003677",
          "tgn:7000084",
          "tgn:7029392"
        ],
        "placetype": [
          "aat:300000206"
        ],
        "id": 7182699,
        "name:xx": "Gut Friedrichsgrund"
      }
    }
  ]
}
