{
  "geometry": {
    "type": "Point",
    "coordinates": [
      20.8667,
      48.9167
    ]
  },
  "type": "Feature",
  "properties": {
    "hierarchy": [
      "tgn:1027304",
      "tgn:7027133",
      "tgn:1000003",
      "tgn:7011765",
      "tgn:7029392"
    ],
    "placetype": [
      "aat:300008347"
    ],
    "id": 1027304,
    "name:xx": "Krompachy"
  }
}
