{
  "geometry": {
    "type": "Point",
    "coordinates": [
      121.8667,
      42.0333
    ]
  },
  "type": "Feature",
  "properties": {
    "hierarchy": [
      "tgn:1071816",
      "tgn:1000004",
      "tgn:1001390",
      "tgn:1000111",
      "tgn:7029392"
    ],
    "placetype": [
      "aat:300008347"
    ],
    "id": 1071816,
    "name:xx": "Shuangmiaozi"
  }
}
