{
  "geometry": {
    "type": "Point",
    "coordinates": [
      -94.9667,
      49.3333
    ]
  },
  "type": "Feature",
  "properties": {
    "hierarchy": [
      "tgn:2786210",
      "tgn:1000001",
      "tgn:7012149",
      "tgn:7021313",
      "tgn:7007521",
      "tgn:7029392"
    ],
    "placetype": [
      "aat:300132316"
    ],
    "id": 2786210,
    "name:xx": "Youngs Bay"
  }
}
