{
  "geometry": {
    "type": "Point",
    "coordinates": [
      -90.2333,
      29.8333
    ]
  },
  "type": "Feature",
  "properties": {
    "hierarchy": [
      "tgn:2226040",
      "tgn:1000001",
      "tgn:7012149",
      "tgn:2000898",
      "tgn:7007256",
      "tgn:7029392"
    ],
    "placetype": [
      "aat:300008680"
    ],
    "id": 2226040,
    "name:xx": "Cataouatche, Lake"
  }
}
