{
  "type": "FeatureCollection",
  "features": [
    {
      "geometry": {
        "type": "Point",
        "coordinates": [
          -84.6,
          36.75
        ]
      },
      "type": "Feature",
      "properties": {
        "hierarchy": [
          "tgn:2732110",
          "tgn:1000001",
          "tgn:7012149",
          "tgn:2000818",
          "tgn:7007255",
          "tgn:7029392"
        ],
        "placetype": [
          "aat:300008761"
        ],
        "id": 2732110,
        "name:xx": "Tunnel Hollow"
      }
    },
    {
      "geometry": {
        "type": "Point",
        "coordinates": [
          -78.4667,
          39.55
        ]
      },
      "type": "Feature",
      "properties": {
        "hierarchy": [
          "tgn:2732111",
          "tgn:2000934",
          "tgn:1000001",
          "tgn:7012149",
          "tgn:7007516",
          "tgn:7029392"
        ],
        "placetype": [
          "aat:300008761"
        ],
        "id": 2732111,
        "name:xx": "Tunnel Hollow"
      }
    },
    {
      "geometry": {
        "type": "Point",
        "coordinates": [
          -92.1167,
          37.7833
        ]
      },
      "type": "Feature",
      "properties": {
        "hierarchy": [
          "tgn:2732112",
          "tgn:1000001",
          "tgn:7012149",
          "tgn:2001233",
          "tgn:7007523",
          "tgn:7029392"
        ],
        "placetype": [
          "aat:300008761"
        ],
        "id": 2732112,
        "name:xx": "Tunnel Hollow"
      }
    },
    {
      "geometry": {
        "type": "Point",
        "coordinates": [
          -87.2167,
          35.75
        ]
      },
      "type": "Feature",
      "properties": {
        "hierarchy": [
          "tgn:2732113",
          "tgn:1000001",
          "tgn:7012149",
          "tgn:2001896",
          "tgn:7007825",
          "tgn:7029392"
        ],
        "placetype": [
          "aat:300008761"
        ],
        "id": 2732113,
        "name:xx": "Tunnel Hollow"
      }
    },
    {
      "geometry": {
        "type": "Point",
        "coordinates": [
          -84.2167,
          36.2667
        ]
      },
      "type": "Feature",
      "properties": {
        "hierarchy": [
          "tgn:2732114",
          "tgn:1000001",
          "tgn:7012149",
          "tgn:2001843",
          "tgn:7007825",
          "tgn:7029392"
        ],
        "placetype": [
          "aat:300008761"
        ],
        "id": 2732114,
        "name:xx": "Tunnel Hollow"
      }
    },
    {
      "geometry": {
        "type": "Point",
        "coordinates": [
          -84.5667,
          36.35
        ]
      },
      "type": "Feature",
      "properties": {
        "hierarchy": [
          "tgn:2732115",
          "tgn:1000001",
          "tgn:7012149",
          "tgn:2001912",
          "tgn:7007825",
          "tgn:7029392"
        ],
        "placetype": [
          "aat:300008761"
        ],
        "id": 2732115,
        "name:xx": "Tunnel Hollow"
      }
    },
    {
      "geometry": {
        "type": "Point",
        "coordinates": [
          -111.55,
          41
        ]
      },
      "type": "Feature",
      "properties": {
        "hierarchy": [
          "tgn:2732116",
          "tgn:1000001",
          "tgn:7012149",
          "tgn:2002115",
          "tgn:7007827",
          "tgn:7029392"
        ],
        "placetype": [
          "aat:300008761"
        ],
        "id": 2732116,
        "name:xx": "Tunnel Hollow"
      }
    },
    {
      "geometry": {
        "type": "Point",
        "coordinates": [
          -111.15,
          41.1667
        ]
      },
      "type": "Feature",
      "properties": {
        "hierarchy": [
          "tgn:2732117",
          "tgn:1000001",
          "tgn:7012149",
          "tgn:2002122",
          "tgn:7007827",
          "tgn:7029392"
        ],
        "placetype": [
          "aat:300008761"
        ],
        "id": 2732117,
        "name:xx": "Tunnel Hollow"
      }
    },
    {
      "geometry": {
        "type": "Point",
        "coordinates": [
          -80.8167,
          37.0167
        ]
      },
      "type": "Feature",
      "properties": {
        "hierarchy": [
          "tgn:2732118",
          "tgn:1000001",
          "tgn:7012149",
          "tgn:2002183",
          "tgn:7007919",
          "tgn:7029392"
        ],
        "placetype": [
          "aat:300008761"
        ],
        "id": 2732118,
        "name:xx": "Tunnel Hollow"
      }
    },
    {
      "geometry": {
        "type": "Point",
        "coordinates": [
          -79.1833,
          38.3167
        ]
      },
      "type": "Feature",
      "properties": {
        "hierarchy": [
          "tgn:2732119",
          "tgn:2002142",
          "tgn:1000001",
          "tgn:7012149",
          "tgn:7007919",
          "tgn:7029392"
        ],
        "placetype": [
          "aat:300008761"
        ],
        "id": 2732119,
        "name:xx": "Tunnel Hollow"
      }
    }
  ]
}
