{
  "geometry": {
    "type": "Point",
    "coordinates": [
      -114.05,
      35.45
    ]
  },
  "type": "Feature",
  "properties": {
    "hierarchy": [
      "tgn:2313589",
      "tgn:1000001",
      "tgn:7006451",
      "tgn:7012149",
      "tgn:2000098",
      "tgn:7029392"
    ],
    "placetype": [
      "aat:300008697"
    ],
    "id": 2313589,
    "name:xx": "Elements Spring"
  }
}
