{
  "geometry": {
    "type": "Point",
    "coordinates": [
      31.875,
      31.316667
    ]
  },
  "type": "Feature",
  "properties": {
    "hierarchy": [
      "tgn:7544240",
      "tgn:7001242",
      "tgn:1001059",
      "tgn:7016833",
      "tgn:7029392"
    ],
    "placetype": [
      "aat:300386885"
    ],
    "name:en": "Bitiltīsh, Barr",
    "id": 7544240
  }
}
