{
  "geometry": {
    "type": "Point",
    "coordinates": [
      75.216667,
      33.75
    ]
  },
  "type": "Feature",
  "properties": {
    "hierarchy": [
      "tgn:7553413",
      "tgn:1000004",
      "tgn:7000198",
      "tgn:7000799",
      "tgn:7029392"
    ],
    "placetype": [
      "aat:300008347"
    ],
    "name:en": "Mārtand",
    "id": 7553413
  }
}
