{
  "geometry": {
    "type": "Point",
    "coordinates": [
      -88.2833,
      36.35
    ]
  },
  "type": "Feature",
  "properties": {
    "hierarchy": [
      "tgn:2386324",
      "tgn:1000001",
      "tgn:7012149",
      "tgn:2001876",
      "tgn:7007825",
      "tgn:7029392"
    ],
    "placetype": [
      "aat:300008699"
    ],
    "id": 2386324,
    "name:xx": "Henson Branch"
  }
}
