{
  "geometry": {
    "type": "Point",
    "coordinates": [
      -111.45,
      41.4333
    ]
  },
  "type": "Feature",
  "properties": {
    "hierarchy": [
      "tgn:2706730",
      "tgn:1000001",
      "tgn:7012149",
      "tgn:2002117",
      "tgn:7007827",
      "tgn:7029392"
    ],
    "placetype": [
      "aat:300266640"
    ],
    "id": 2706730,
    "name:xx": "Swan Ridge"
  }
}
