{
  "type": "FeatureCollection",
  "features": [
    {
      "geometry": {
        "type": "Point",
        "coordinates": [
          -84.1333,
          37.0167
        ]
      },
      "type": "Feature",
      "properties": {
        "hierarchy": [
          "tgn:2705830",
          "tgn:1000001",
          "tgn:7012149",
          "tgn:2000808",
          "tgn:7007255",
          "tgn:7029392"
        ],
        "placetype": [
          "aat:300008699"
        ],
        "id": 2705830,
        "name:xx": "Sutton Branch"
      }
    },
    {
      "geometry": {
        "type": "Point",
        "coordinates": [
          -83.1,
          38.4
        ]
      },
      "type": "Feature",
      "properties": {
        "hierarchy": [
          "tgn:2705831",
          "tgn:1000001",
          "tgn:1002240",
          "tgn:7012149",
          "tgn:7007255",
          "tgn:7029392"
        ],
        "placetype": [
          "aat:300008699"
        ],
        "id": 2705831,
        "name:xx": "Sutton Branch"
      }
    },
    {
      "geometry": {
        "type": "Point",
        "coordinates": [
          -90.7667,
          37.4167
        ]
      },
      "type": "Feature",
      "properties": {
        "hierarchy": [
          "tgn:2705832",
          "tgn:1000001",
          "tgn:7012149",
          "tgn:2001236",
          "tgn:7007523",
          "tgn:7029392"
        ],
        "placetype": [
          "aat:300008699"
        ],
        "id": 2705832,
        "name:xx": "Sutton Branch"
      }
    },
    {
      "geometry": {
        "type": "Point",
        "coordinates": [
          -92.45,
          37.4833
        ]
      },
      "type": "Feature",
      "properties": {
        "hierarchy": [
          "tgn:2705833",
          "tgn:1000001",
          "tgn:7012149",
          "tgn:2001211",
          "tgn:7007523",
          "tgn:7029392"
        ],
        "placetype": [
          "aat:300008699"
        ],
        "id": 2705833,
        "name:xx": "Sutton Branch"
      }
    },
    {
      "geometry": {
        "type": "Point",
        "coordinates": [
          -77.7833,
          35.0833
        ]
      },
      "type": "Feature",
      "properties": {
        "hierarchy": [
          "tgn:2705834",
          "tgn:1000001",
          "tgn:7012149",
          "tgn:2001491",
          "tgn:7007709",
          "tgn:7029392"
        ],
        "placetype": [
          "aat:300008699"
        ],
        "id": 2705834,
        "name:xx": "Sutton Branch"
      }
    },
    {
      "geometry": {
        "type": "Point",
        "coordinates": [
          -83.2667,
          35.35
        ]
      },
      "type": "Feature",
      "properties": {
        "hierarchy": [
          "tgn:2705835",
          "tgn:1000001",
          "tgn:7012149",
          "tgn:2001508",
          "tgn:7007709",
          "tgn:7029392"
        ],
        "placetype": [
          "aat:300008699"
        ],
        "id": 2705835,
        "name:xx": "Sutton Branch"
      }
    },
    {
      "geometry": {
        "type": "Point",
        "coordinates": [
          -80.55,
          34.7
        ]
      },
      "type": "Feature",
      "properties": {
        "hierarchy": [
          "tgn:2705836",
          "tgn:1000001",
          "tgn:7012149",
          "tgn:2001753",
          "tgn:7007712",
          "tgn:7029392"
        ],
        "placetype": [
          "aat:300008699"
        ],
        "id": 2705836,
        "name:xx": "Sutton Branch"
      }
    },
    {
      "geometry": {
        "type": "Point",
        "coordinates": [
          -86.2333,
          35.6667
        ]
      },
      "type": "Feature",
      "properties": {
        "hierarchy": [
          "tgn:2705837",
          "tgn:1000001",
          "tgn:7012149",
          "tgn:2001852",
          "tgn:7007825",
          "tgn:7029392"
        ],
        "placetype": [
          "aat:300008699"
        ],
        "id": 2705837,
        "name:xx": "Sutton Branch"
      }
    },
    {
      "geometry": {
        "type": "Point",
        "coordinates": [
          -83.4167,
          36.5667
        ]
      },
      "type": "Feature",
      "properties": {
        "hierarchy": [
          "tgn:2705838",
          "tgn:1000001",
          "tgn:7012149",
          "tgn:7007825",
          "tgn:7029392"
        ],
        "placetype": [
          "aat:300008699"
        ],
        "id": 2705838,
        "name:xx": "Sutton Branch"
      }
    },
    {
      "geometry": {
        "type": "Point",
        "coordinates": [
          -72.1,
          44.3333
        ]
      },
      "type": "Feature",
      "properties": {
        "hierarchy": [
          "tgn:2705839",
          "tgn:2002131",
          "tgn:1000001",
          "tgn:7012149",
          "tgn:7007828",
          "tgn:7029392"
        ],
        "placetype": [
          "aat:300008699"
        ],
        "id": 2705839,
        "name:xx": "Sutton Brook"
      }
    }
  ]
}
