{
  "geometry": {
    "type": "Point",
    "coordinates": [
      -109.15,
      42.6833
    ]
  },
  "type": "Feature",
  "properties": {
    "hierarchy": [
      "tgn:2341839",
      "tgn:1000001",
      "tgn:7012149",
      "tgn:2002382",
      "tgn:7007923",
      "tgn:7029392"
    ],
    "placetype": [
      "aat:300008680"
    ],
    "id": 2341839,
    "name:xx": "Frozen Lakes"
  }
}
