{
  "geometry": {
    "type": "Point",
    "coordinates": [
      -91.6833,
      45.1667
    ]
  },
  "type": "Feature",
  "properties": {
    "hierarchy": [
      "tgn:2122332",
      "tgn:1000001",
      "tgn:2002319",
      "tgn:7012149",
      "tgn:7007922",
      "tgn:7029392"
    ],
    "placetype": [
      "aat:300008347"
    ],
    "id": 2122332,
    "name:xx": "Sand Creek"
  }
}
