{
  "geometry": {
    "type": "Point",
    "coordinates": [
      -79.0167,
      34.7167
    ]
  },
  "type": "Feature",
  "properties": {
    "hierarchy": [
      "tgn:2593172",
      "tgn:1000001",
      "tgn:7012149",
      "tgn:2001534",
      "tgn:7007709",
      "tgn:7029392"
    ],
    "placetype": [
      "aat:300008699"
    ],
    "id": 2593172,
    "name:xx": "Poplar Pole Branch"
  }
}
