{
  "geometry": {
    "type": "Point",
    "coordinates": [
      -121.8833,
      37.9333
    ]
  },
  "type": "Feature",
  "properties": {
    "hierarchy": [
      "tgn:2439387",
      "tgn:1000001",
      "tgn:7012149",
      "tgn:1002298",
      "tgn:7007157",
      "tgn:7029392"
    ],
    "placetype": [
      "aat:300008706"
    ],
    "id": 2439387,
    "name:xx": "Kirker Creek"
  }
}
