{
  "geometry": {
    "type": "Point",
    "coordinates": [
      -119.2167,
      39.9833
    ]
  },
  "type": "Feature",
  "properties": {
    "hierarchy": [
      "tgn:2419797",
      "tgn:1000001",
      "tgn:7012149",
      "tgn:1002999",
      "tgn:7007526",
      "tgn:7029392"
    ],
    "placetype": [
      "aat:300000390"
    ],
    "id": 2419797,
    "name:xx": "Jay Bird Mine"
  }
}
