{
  "type": "FeatureCollection",
  "features": [
    {
      "geometry": {
        "type": "Point",
        "coordinates": [
          -83.0167,
          36.6667
        ]
      },
      "type": "Feature",
      "properties": {
        "hierarchy": [
          "tgn:2142250",
          "tgn:1000001",
          "tgn:7012149",
          "tgn:2002169",
          "tgn:7007919",
          "tgn:7029392"
        ],
        "placetype": [
          "aat:300386845"
        ],
        "id": 2142250,
        "name:xx": "Back Valley"
      }
    },
    {
      "geometry": {
        "type": "Point",
        "coordinates": [
          -82.8167,
          36.7
        ]
      },
      "type": "Feature",
      "properties": {
        "hierarchy": [
          "tgn:2142251",
          "tgn:1000001",
          "tgn:7012149",
          "tgn:2002189",
          "tgn:7007919",
          "tgn:7029392"
        ],
        "placetype": [
          "aat:300386845"
        ],
        "id": 2142251,
        "name:xx": "Back Valley"
      }
    },
    {
      "geometry": {
        "type": "Point",
        "coordinates": [
          -82.1667,
          36.95
        ]
      },
      "type": "Feature",
      "properties": {
        "hierarchy": [
          "tgn:2142252",
          "tgn:1000001",
          "tgn:7012149",
          "tgn:2002188",
          "tgn:7007919",
          "tgn:7029392"
        ],
        "placetype": [
          "aat:300008761"
        ],
        "id": 2142252,
        "name:xx": "Back Valley"
      }
    },
    {
      "geometry": {
        "type": "Point",
        "coordinates": [
          -80.95,
          37.1833
        ]
      },
      "type": "Feature",
      "properties": {
        "hierarchy": [
          "tgn:2142253",
          "tgn:1000001",
          "tgn:2002145",
          "tgn:7012149",
          "tgn:7007919",
          "tgn:7029392"
        ],
        "placetype": [
          "aat:300008761"
        ],
        "id": 2142253,
        "name:xx": "Back Valley"
      }
    },
    {
      "geometry": {
        "type": "Point",
        "coordinates": [
          -82.5833,
          36.8167
        ]
      },
      "type": "Feature",
      "properties": {
        "hierarchy": [
          "tgn:2142254",
          "tgn:1000001",
          "tgn:7012149",
          "tgn:2002189",
          "tgn:7007919",
          "tgn:7029392"
        ],
        "placetype": [
          "aat:300008761"
        ],
        "id": 2142254,
        "name:xx": "Back Valley"
      }
    },
    {
      "geometry": {
        "type": "Point",
        "coordinates": [
          -80.3,
          37.5
        ]
      },
      "type": "Feature",
      "properties": {
        "hierarchy": [
          "tgn:2142255",
          "tgn:1000001",
          "tgn:7012149",
          "tgn:2002282",
          "tgn:7013961",
          "tgn:7029392"
        ],
        "placetype": [
          "aat:300008761"
        ],
        "id": 2142255,
        "name:xx": "Back Valley"
      }
    },
    {
      "geometry": {
        "type": "Point",
        "coordinates": [
          -85.4,
          34.8167
        ]
      },
      "type": "Feature",
      "properties": {
        "hierarchy": [
          "tgn:2142256",
          "tgn:1000001",
          "tgn:7012149",
          "tgn:2000437",
          "tgn:7007248",
          "tgn:7029392"
        ],
        "placetype": [
          "aat:300008706"
        ],
        "id": 2142256,
        "name:xx": "Back Valley Creek"
      }
    },
    {
      "geometry": {
        "type": "Point",
        "coordinates": [
          -145.6833,
          66.6167
        ]
      },
      "type": "Feature",
      "properties": {
        "hierarchy": [
          "tgn:2142259",
          "tgn:7006450",
          "tgn:1000001",
          "tgn:7012149",
          "tgn:2000089",
          "tgn:7029392"
        ],
        "placetype": [
          "aat:300008699"
        ],
        "id": 2142259,
        "name:xx": "Back Yukon Slough"
      }
    }
  ]
}
