{
  "type": "FeatureCollection",
  "features": [
    {
      "geometry": {
        "type": "Point",
        "coordinates": [
          -119.2333,
          35.7
        ]
      },
      "type": "Feature",
      "properties": {
        "hierarchy": [
          "tgn:2014820",
          "tgn:1000001",
          "tgn:7012149",
          "tgn:1002545",
          "tgn:7007157",
          "tgn:7029392"
        ],
        "placetype": [
          "aat:300387016"
        ],
        "id": 2014820,
        "name:xx": "Vinland"
      }
    },
    {
      "geometry": {
        "type": "Point",
        "coordinates": [
          -120.1667,
          39.8
        ]
      },
      "type": "Feature",
      "properties": {
        "hierarchy": [
          "tgn:2014821",
          "tgn:1000001",
          "tgn:7012149",
          "tgn:7007157",
          "tgn:2000187",
          "tgn:7029392"
        ],
        "placetype": [
          "aat:300008347"
        ],
        "id": 2014821,
        "name:xx": "Vinton"
      }
    },
    {
      "geometry": {
        "type": "Point",
        "coordinates": [
          -121.6667,
          40.5167
        ]
      },
      "type": "Feature",
      "properties": {
        "hierarchy": [
          "tgn:2014822",
          "tgn:1000001",
          "tgn:7012149",
          "tgn:7007157",
          "tgn:2000188",
          "tgn:7029392"
        ],
        "placetype": [
          "aat:300008347",
          "aat:300387210"
        ],
        "id": 2014822,
        "name:xx": "Viola"
      }
    },
    {
      "geometry": {
        "type": "Point",
        "coordinates": [
          -121.1,
          40.0167
        ]
      },
      "type": "Feature",
      "properties": {
        "hierarchy": [
          "tgn:2014823",
          "tgn:1000001",
          "tgn:7012149",
          "tgn:7007157",
          "tgn:2000187",
          "tgn:7029392"
        ],
        "placetype": [
          "aat:300387016"
        ],
        "id": 2014823,
        "name:xx": "Virgilia"
      }
    },
    {
      "geometry": {
        "type": "Point",
        "coordinates": [
          -118.85,
          34.2833
        ]
      },
      "type": "Feature",
      "properties": {
        "hierarchy": [
          "tgn:2014824",
          "tgn:1000001",
          "tgn:7012149",
          "tgn:7007157",
          "tgn:1002972",
          "tgn:7029392"
        ],
        "placetype": [
          "aat:300008347"
        ],
        "id": 2014824,
        "name:xx": "Virginia Colony"
      }
    },
    {
      "geometry": {
        "type": "Point",
        "coordinates": [
          -119.2833,
          36.3167
        ]
      },
      "type": "Feature",
      "properties": {
        "hierarchy": [
          "tgn:2014826",
          "tgn:1000001",
          "tgn:7012149",
          "tgn:7007157",
          "tgn:1002956",
          "tgn:7029392"
        ],
        "placetype": [
          "aat:300387277",
          "aat:300008347",
          "aat:300008416",
          "aat:300008389",
          "aat:300387308"
        ],
        "id": 2014826,
        "name:xx": "Visalia"
      }
    }
  ]
}
