{
  "geometry": {
    "type": "Point",
    "coordinates": [
      -69.85,
      45.3167
    ]
  },
  "type": "Feature",
  "properties": {
    "hierarchy": [
      "tgn:2209158",
      "tgn:1000001",
      "tgn:7012149",
      "tgn:2000930",
      "tgn:7007515",
      "tgn:7029392"
    ],
    "placetype": [
      "aat:300008791"
    ],
    "id": 2209158,
    "name:xx": "Burnt Jacket Island"
  }
}
