{
  "geometry": {
    "type": "Point",
    "coordinates": [
      71.233333,
      20.816667
    ]
  },
  "type": "Feature",
  "properties": {
    "hierarchy": [
      "tgn:7549678",
      "tgn:1000004",
      "tgn:1001869",
      "tgn:7000198",
      "tgn:7029392"
    ],
    "placetype": [
      "aat:300008347"
    ],
    "name:en": "Dhārābandar",
    "id": 7549678
  }
}
