{
  "type": "FeatureCollection",
  "features": [
    {
      "geometry": {
        "type": "Point",
        "coordinates": [
          -99.7333,
          32.1333
        ]
      },
      "type": "Feature",
      "properties": {
        "hierarchy": [
          "tgn:2105570",
          "tgn:1000001",
          "tgn:7012149",
          "tgn:2002081",
          "tgn:7007826",
          "tgn:7029392"
        ],
        "placetype": [
          "aat:300008347"
        ],
        "id": 2105570,
        "name:xx": "Lawn"
      }
    },
    {
      "geometry": {
        "type": "Point",
        "coordinates": [
          -96.3333,
          32.7333
        ]
      },
      "type": "Feature",
      "properties": {
        "hierarchy": [
          "tgn:2105571",
          "tgn:1000001",
          "tgn:7012149",
          "tgn:1002535",
          "tgn:7007826",
          "tgn:7029392"
        ],
        "placetype": [
          "aat:300008347"
        ],
        "id": 2105571,
        "name:xx": "Lawrence"
      }
    },
    {
      "geometry": {
        "type": "Point",
        "coordinates": [
          -95.7833,
          32.6333
        ]
      },
      "type": "Feature",
      "properties": {
        "hierarchy": [
          "tgn:2105572",
          "tgn:1000001",
          "tgn:7012149",
          "tgn:1002969",
          "tgn:7007826",
          "tgn:7029392"
        ],
        "placetype": [
          "aat:300008347",
          "aat:300387210"
        ],
        "id": 2105572,
        "name:xx": "Lawrence Springs"
      }
    },
    {
      "geometry": {
        "type": "Point",
        "coordinates": [
          -96.55,
          32.7
        ]
      },
      "type": "Feature",
      "properties": {
        "hierarchy": [
          "tgn:2105573",
          "tgn:1000001",
          "tgn:7012149",
          "tgn:1002315",
          "tgn:7007826",
          "tgn:7029392"
        ],
        "placetype": [
          "aat:300008347",
          "aat:300387210"
        ],
        "id": 2105573,
        "name:xx": "Lawson"
      }
    },
    {
      "geometry": {
        "type": "Point",
        "coordinates": [
          -102.6,
          34.3833
        ]
      },
      "type": "Feature",
      "properties": {
        "hierarchy": [
          "tgn:2105575",
          "tgn:1000001",
          "tgn:7012149",
          "tgn:2002054",
          "tgn:7007826",
          "tgn:7029392"
        ],
        "placetype": [
          "aat:300008347"
        ],
        "id": 2105575,
        "name:xx": "Lazbuddie"
      }
    },
    {
      "geometry": {
        "type": "Point",
        "coordinates": [
          -99.6667,
          31.5667
        ]
      },
      "type": "Feature",
      "properties": {
        "hierarchy": [
          "tgn:2105576",
          "tgn:1000001",
          "tgn:7012149",
          "tgn:2001959",
          "tgn:7007826",
          "tgn:7029392"
        ],
        "placetype": [
          "aat:300008347",
          "aat:300387210"
        ],
        "id": 2105576,
        "name:xx": "Leaday"
      }
    },
    {
      "geometry": {
        "type": "Point",
        "coordinates": [
          -95.0833,
          29.5
        ]
      },
      "type": "Feature",
      "properties": {
        "hierarchy": [
          "tgn:2105577",
          "tgn:1000001",
          "tgn:7012149",
          "tgn:1002401",
          "tgn:7007826",
          "tgn:7029392"
        ],
        "placetype": [
          "aat:300008347"
        ],
        "id": 2105577,
        "name:xx": "League City"
      }
    }
  ]
}
