{
  "geometry": {
    "type": "Point",
    "coordinates": [
      -119.5333,
      37.7167
    ]
  },
  "type": "Feature",
  "properties": {
    "hierarchy": [
      "tgn:2316822",
      "tgn:1000001",
      "tgn:7012149",
      "tgn:7007157",
      "tgn:7014004",
      "tgn:7029392"
    ],
    "placetype": [
      "aat:300008680"
    ],
    "id": 2316822,
    "name:xx": "Emerald Pool"
  }
}
