{
  "type": "FeatureCollection",
  "features": [
    {
      "geometry": {
        "type": "Point",
        "coordinates": [
          -86.8167,
          33.5667
        ]
      },
      "type": "Feature",
      "properties": {
        "hierarchy": [
          "tgn:2381980",
          "tgn:7002659",
          "tgn:1000001",
          "tgn:7012149",
          "tgn:2000036",
          "tgn:7029392"
        ],
        "placetype": [
          "aat:300008347"
        ],
        "id": 2381980,
        "name:xx": "Hayes Highland"
      }
    },
    {
      "geometry": {
        "type": "Point",
        "coordinates": [
          -87.4167,
          33.7
        ]
      },
      "type": "Feature",
      "properties": {
        "hierarchy": [
          "tgn:2381981",
          "tgn:7002659",
          "tgn:1000001",
          "tgn:7012149",
          "tgn:2000063",
          "tgn:7029392"
        ],
        "placetype": [
          "aat:300008798"
        ],
        "id": 2381981,
        "name:xx": "Hayes Hill"
      }
    },
    {
      "geometry": {
        "type": "Point",
        "coordinates": [
          -86.1833,
          38.0667
        ]
      },
      "type": "Feature",
      "properties": {
        "hierarchy": [
          "tgn:2381982",
          "tgn:1000001",
          "tgn:7012149",
          "tgn:1002457",
          "tgn:7007252",
          "tgn:7029392"
        ],
        "placetype": [
          "aat:300008798"
        ],
        "id": 2381982,
        "name:xx": "Hayes Hill"
      }
    },
    {
      "geometry": {
        "type": "Point",
        "coordinates": [
          -70.9833,
          43.1667
        ]
      },
      "type": "Feature",
      "properties": {
        "hierarchy": [
          "tgn:2381983",
          "tgn:1000001",
          "tgn:2001426",
          "tgn:7012149",
          "tgn:7007564",
          "tgn:7029392"
        ],
        "placetype": [
          "aat:300008798"
        ],
        "id": 2381983,
        "name:xx": "Hayes Hill"
      }
    },
    {
      "geometry": {
        "type": "Point",
        "coordinates": [
          -72.2,
          43.6667
        ]
      },
      "type": "Feature",
      "properties": {
        "hierarchy": [
          "tgn:2381984",
          "tgn:1000001",
          "tgn:2001424",
          "tgn:7012149",
          "tgn:7007564",
          "tgn:7029392"
        ],
        "placetype": [
          "aat:300008798"
        ],
        "id": 2381984,
        "name:xx": "Hayes Hill"
      }
    },
    {
      "geometry": {
        "type": "Point",
        "coordinates": [
          -123.5667,
          42.3167
        ]
      },
      "type": "Feature",
      "properties": {
        "hierarchy": [
          "tgn:2381985",
          "tgn:1000001",
          "tgn:7012149",
          "tgn:2001713",
          "tgn:7007708",
          "tgn:7029392"
        ],
        "placetype": [
          "aat:300008798"
        ],
        "id": 2381985,
        "name:xx": "Hayes Hill"
      }
    },
    {
      "geometry": {
        "type": "Point",
        "coordinates": [
          -123.4167,
          44.6167
        ]
      },
      "type": "Feature",
      "properties": {
        "hierarchy": [
          "tgn:2381986",
          "tgn:1000001",
          "tgn:2001701",
          "tgn:7012149",
          "tgn:7007708",
          "tgn:7029392"
        ],
        "placetype": [
          "aat:300008798"
        ],
        "id": 2381986,
        "name:xx": "Hayes Hill"
      }
    },
    {
      "geometry": {
        "type": "Point",
        "coordinates": [
          -81.75,
          34.8667
        ]
      },
      "type": "Feature",
      "properties": {
        "hierarchy": [
          "tgn:2381987",
          "tgn:1000001",
          "tgn:7012149",
          "tgn:2001766",
          "tgn:7007712",
          "tgn:7029392"
        ],
        "placetype": [
          "aat:300008798"
        ],
        "id": 2381987,
        "name:xx": "Hayes Hill"
      }
    },
    {
      "geometry": {
        "type": "Point",
        "coordinates": [
          -122.6667,
          47.05
        ]
      },
      "type": "Feature",
      "properties": {
        "hierarchy": [
          "tgn:2381988",
          "tgn:1000001",
          "tgn:7012149",
          "tgn:1002785",
          "tgn:7007920",
          "tgn:7029392"
        ],
        "placetype": [
          "aat:300008798"
        ],
        "id": 2381988,
        "name:xx": "Hayes Hill"
      }
    },
    {
      "geometry": {
        "type": "Point",
        "coordinates": [
          -123.5833,
          42.3167
        ]
      },
      "type": "Feature",
      "properties": {
        "hierarchy": [
          "tgn:2381989",
          "tgn:1000001",
          "tgn:7012149",
          "tgn:2001713",
          "tgn:7007708",
          "tgn:7029392"
        ],
        "placetype": [
          "aat:300008798"
        ],
        "id": 2381989,
        "name:xx": "Hayes Hill Summit"
      }
    }
  ]
}
