{
  "type": "FeatureCollection",
  "features": [
    {
      "geometry": {
        "type": "Point",
        "coordinates": [
          157.95,
          -45.8
        ]
      },
      "type": "Feature",
      "properties": {
        "hierarchy": [
          "tgn:7514160",
          "tgn:1009227",
          "tgn:1000226",
          "tgn:7016822",
          "tgn:1000006",
          "tgn:7029392"
        ],
        "placetype": [
          "aat:300008699"
        ],
        "name:en": "Elbow Creek",
        "id": 7514160
      }
    },
    {
      "geometry": {
        "type": "Point",
        "coordinates": [
          176.733333,
          -39.316667
        ]
      },
      "type": "Feature",
      "properties": {
        "hierarchy": [
          "tgn:7514161",
          "tgn:7016670",
          "tgn:1008380",
          "tgn:1000226",
          "tgn:1000006",
          "tgn:7029392"
        ],
        "placetype": [
          "aat:300000206"
        ],
        "name:en": "Eland",
        "id": 7514161
      }
    },
    {
      "geometry": {
        "type": "Point",
        "coordinates": [
          173.783333,
          -41.05
        ]
      },
      "type": "Feature",
      "properties": {
        "hierarchy": [
          "tgn:7514162",
          "tgn:1009227",
          "tgn:1000226",
          "tgn:7016729",
          "tgn:1000006",
          "tgn:7029392"
        ],
        "placetype": [
          "aat:300132316"
        ],
        "name:en": "Elaine Bay",
        "id": 7514162
      }
    },
    {
      "geometry": {
        "type": "Point",
        "coordinates": [
          173.033333,
          -41.4
        ]
      },
      "type": "Feature",
      "properties": {
        "hierarchy": [
          "tgn:7514165",
          "tgn:1009227",
          "tgn:1000226",
          "tgn:7520095",
          "tgn:1000006",
          "tgn:7029392"
        ],
        "placetype": [
          "aat:300008699"
        ],
        "name:en": "Eighty-eight Valley Stream",
        "id": 7514165
      }
    },
    {
      "geometry": {
        "type": "Point",
        "coordinates": [
          173.033333,
          -41.45
        ]
      },
      "type": "Feature",
      "properties": {
        "hierarchy": [
          "tgn:7514166",
          "tgn:1009227",
          "tgn:1000226",
          "tgn:7520095",
          "tgn:1000006",
          "tgn:7029392"
        ],
        "placetype": [
          "aat:300008767"
        ],
        "name:en": "Eighty-eight Valley",
        "id": 7514166
      }
    },
    {
      "geometry": {
        "type": "Point",
        "coordinates": [
          169.516667,
          -44.75
        ]
      },
      "type": "Feature",
      "properties": {
        "hierarchy": [
          "tgn:7514167",
          "tgn:1009227",
          "tgn:1000226",
          "tgn:7018437",
          "tgn:1000006",
          "tgn:7029392"
        ],
        "placetype": [
          "aat:300008699"
        ],
        "name:en": "Eight Mile Creek",
        "id": 7514167
      }
    },
    {
      "geometry": {
        "type": "Point",
        "coordinates": [
          171.3,
          -42.55
        ]
      },
      "type": "Feature",
      "properties": {
        "hierarchy": [
          "tgn:7514168",
          "tgn:1009227",
          "tgn:1000226",
          "tgn:1000006",
          "tgn:7016850",
          "tgn:7029392"
        ],
        "placetype": [
          "aat:300008699"
        ],
        "name:en": "Eight Mile Creek",
        "id": 7514168
      }
    },
    {
      "geometry": {
        "type": "Point",
        "coordinates": [
          172.316667,
          -41.9
        ]
      },
      "type": "Feature",
      "properties": {
        "hierarchy": [
          "tgn:7514169",
          "tgn:1009227",
          "tgn:1000226",
          "tgn:1000006",
          "tgn:7016850",
          "tgn:7029392"
        ],
        "placetype": [
          "aat:300008699"
        ],
        "name:en": "Eight Mile Creek",
        "id": 7514169
      }
    }
  ]
}
