{
  "geometry": {
    "type": "Point",
    "coordinates": [
      8.583,
      46.583
    ]
  },
  "type": "Feature",
  "properties": {
    "hierarchy": [
      "tgn:7544627",
      "tgn:1000003",
      "tgn:7011731",
      "tgn:7029392"
    ],
    "placetype": [
      "aat:300008795"
    ],
    "id": 7544627,
    "name:xx": "Saint Gotthard"
  }
}
