{
  "geometry": {
    "type": "Point",
    "coordinates": [
      -91.2833,
      35.4833
    ]
  },
  "type": "Feature",
  "properties": {
    "hierarchy": [
      "tgn:2396037",
      "tgn:1000001",
      "tgn:7016172",
      "tgn:7012149",
      "tgn:2000138",
      "tgn:7029392"
    ],
    "placetype": [
      "aat:300008905"
    ],
    "id": 2396037,
    "name:xx": "Holly Orchard Brake"
  }
}
