{
  "type": "FeatureCollection",
  "features": [
    {
      "geometry": {
        "type": "Point",
        "coordinates": [
          -90.1,
          17.9
        ]
      },
      "type": "Feature",
      "properties": {
        "hierarchy": [
          "tgn:7395840",
          "tgn:7005578",
          "tgn:1000001",
          "tgn:7005560",
          "tgn:7029392"
        ],
        "placetype": [
          "aat:300008347"
        ],
        "id": 7395840,
        "name:xx": "San Felipe"
      }
    },
    {
      "geometry": {
        "type": "Point",
        "coordinates": [
          -91.366667,
          17.7
        ]
      },
      "type": "Feature",
      "properties": {
        "hierarchy": [
          "tgn:7395841",
          "tgn:1000001",
          "tgn:7005596",
          "tgn:7005560",
          "tgn:7029392"
        ],
        "placetype": [
          "aat:300008347"
        ],
        "id": 7395841,
        "name:xx": "San Felipe"
      }
    },
    {
      "geometry": {
        "type": "Point",
        "coordinates": [
          -101.316667,
          17.666667
        ]
      },
      "type": "Feature",
      "properties": {
        "hierarchy": [
          "tgn:7395842",
          "tgn:7005585",
          "tgn:1000001",
          "tgn:7005560",
          "tgn:7029392"
        ],
        "placetype": [
          "aat:300008347"
        ],
        "id": 7395842,
        "name:xx": "San Felipe"
      }
    },
    {
      "geometry": {
        "type": "Point",
        "coordinates": [
          -92.666667,
          16.7
        ]
      },
      "type": "Feature",
      "properties": {
        "hierarchy": [
          "tgn:7395843",
          "tgn:7005580",
          "tgn:1000001",
          "tgn:7005560",
          "tgn:7029392"
        ],
        "placetype": [
          "aat:300008347"
        ],
        "id": 7395843,
        "name:xx": "San Felipe"
      }
    },
    {
      "geometry": {
        "type": "Point",
        "coordinates": [
          -93.966667,
          16.283333
        ]
      },
      "type": "Feature",
      "properties": {
        "hierarchy": [
          "tgn:7395844",
          "tgn:7005580",
          "tgn:1000001",
          "tgn:7005560",
          "tgn:7029392"
        ],
        "placetype": [
          "aat:300008347"
        ],
        "id": 7395844,
        "name:xx": "San Felipe"
      }
    },
    {
      "geometry": {
        "type": "Point",
        "coordinates": [
          -92.75,
          16.066667
        ]
      },
      "type": "Feature",
      "properties": {
        "hierarchy": [
          "tgn:7395845",
          "tgn:7005580",
          "tgn:1000001",
          "tgn:7005560",
          "tgn:7029392"
        ],
        "placetype": [
          "aat:300008347"
        ],
        "id": 7395845,
        "name:xx": "San Felipe"
      }
    },
    {
      "geometry": {
        "type": "Point",
        "coordinates": [
          -92.416667,
          15.95
        ]
      },
      "type": "Feature",
      "properties": {
        "hierarchy": [
          "tgn:7395846",
          "tgn:7005580",
          "tgn:1000001",
          "tgn:7005560",
          "tgn:7029392"
        ],
        "placetype": [
          "aat:300008347"
        ],
        "id": 7395846,
        "name:xx": "San Felipe"
      }
    },
    {
      "geometry": {
        "type": "Point",
        "coordinates": [
          -92.15,
          15.933333
        ]
      },
      "type": "Feature",
      "properties": {
        "hierarchy": [
          "tgn:7395847",
          "tgn:7005580",
          "tgn:1000001",
          "tgn:7005560",
          "tgn:7029392"
        ],
        "placetype": [
          "aat:300008347"
        ],
        "id": 7395847,
        "name:xx": "San Felipe"
      }
    },
    {
      "geometry": {
        "type": "Point",
        "coordinates": [
          -92.616667,
          15.283333
        ]
      },
      "type": "Feature",
      "properties": {
        "hierarchy": [
          "tgn:7395848",
          "tgn:7005580",
          "tgn:1000001",
          "tgn:7005560",
          "tgn:7029392"
        ],
        "placetype": [
          "aat:300008347"
        ],
        "id": 7395848,
        "name:xx": "San Felipe"
      }
    },
    {
      "geometry": {
        "type": "Point",
        "coordinates": [
          -109.883333,
          23.166667
        ]
      },
      "type": "Feature",
      "properties": {
        "hierarchy": [
          "tgn:7395849",
          "tgn:1001836",
          "tgn:1000001",
          "tgn:7005560",
          "tgn:7029392"
        ],
        "placetype": [
          "aat:300008795"
        ],
        "id": 7395849,
        "name:xx": "San Felipe"
      }
    }
  ]
}
