{
  "geometry": {
    "type": "Point",
    "coordinates": [
      -99.1167,
      19.3667
    ]
  },
  "type": "Feature",
  "properties": {
    "hierarchy": [
      "tgn:1004443",
      "tgn:7007227",
      "tgn:7005575",
      "tgn:1000001",
      "tgn:7005560",
      "tgn:7029392"
    ],
    "placetype": [
      "aat:300000745"
    ],
    "id": 1004443,
    "name:xx": "Escuadrón 201"
  }
}
