{
  "geometry": {
    "type": "Point",
    "coordinates": [
      6.5333,
      43.6833
    ]
  },
  "type": "Feature",
  "properties": {
    "hierarchy": [
      "tgn:1034426",
      "tgn:1000003",
      "tgn:1000070",
      "tgn:7002895",
      "tgn:7029392"
    ],
    "placetype": [
      "aat:300008347"
    ],
    "id": 1034426,
    "name:xx": "Mons"
  }
}
