{
  "geometry": {
    "type": "Point",
    "coordinates": [
      -77.4167,
      34.8167
    ]
  },
  "type": "Feature",
  "properties": {
    "hierarchy": [
      "tgn:2412341",
      "tgn:1000001",
      "tgn:7012149",
      "tgn:2001524",
      "tgn:7007709",
      "tgn:7029392"
    ],
    "placetype": [
      "aat:300008347"
    ],
    "id": 2412341,
    "name:xx": "Indian Springs"
  }
}
