{
  "geometry": {
    "type": "Point",
    "coordinates": [
      -83.0667,
      36.2833
    ]
  },
  "type": "Feature",
  "properties": {
    "hierarchy": [
      "tgn:2748212",
      "tgn:1000001",
      "tgn:7012149",
      "tgn:2001873",
      "tgn:7007825",
      "tgn:7029392"
    ],
    "placetype": [
      "aat:300008699"
    ],
    "id": 2748212,
    "name:xx": "Walker Branch"
  }
}
