{
  "geometry": {
    "type": "Point",
    "coordinates": [
      87.233333,
      26.35
    ]
  },
  "type": "Feature",
  "properties": {
    "hierarchy": [
      "tgn:7546266",
      "tgn:1000004",
      "tgn:1001842",
      "tgn:7000198",
      "tgn:7029392"
    ],
    "placetype": [
      "aat:300008347"
    ],
    "name:en": "Bathnāha",
    "id": 7546266
  }
}
