{
  "geometry": {
    "type": "Point",
    "coordinates": [
      -85.1333,
      43.4333
    ]
  },
  "type": "Feature",
  "properties": {
    "hierarchy": [
      "tgn:2327322",
      "tgn:1000001",
      "tgn:7012149",
      "tgn:2000981",
      "tgn:7007520",
      "tgn:7029392"
    ],
    "placetype": [
      "aat:300008680"
    ],
    "id": 2327322,
    "name:xx": "First Lake"
  }
}
