{
  "type": "FeatureCollection",
  "features": [
    {
      "geometry": {
        "type": "Point",
        "coordinates": [
          14.083333,
          51.1
        ]
      },
      "type": "Feature",
      "properties": {
        "hierarchy": [
          "tgn:7151120",
          "tgn:1000003",
          "tgn:7003685",
          "tgn:7000084",
          "tgn:7029392"
        ],
        "placetype": [
          "aat:300008777"
        ],
        "id": 7151120,
        "name:xx": "Kapellen-Berg"
      }
    },
    {
      "geometry": {
        "type": "Point",
        "coordinates": [
          12.733333,
          50.833333
        ]
      },
      "type": "Feature",
      "properties": {
        "hierarchy": [
          "tgn:7151121",
          "tgn:1000003",
          "tgn:7003685",
          "tgn:7000084",
          "tgn:7029392"
        ],
        "placetype": [
          "aat:300008777"
        ],
        "id": 7151121,
        "name:xx": "Kapellen-Berg"
      }
    },
    {
      "geometry": {
        "type": "Point",
        "coordinates": [
          10.666667,
          50.483333
        ]
      },
      "type": "Feature",
      "properties": {
        "hierarchy": [
          "tgn:7151122",
          "tgn:1000003",
          "tgn:7003689",
          "tgn:7000084",
          "tgn:7029392"
        ],
        "placetype": [
          "aat:300008777"
        ],
        "id": 7151122,
        "name:xx": "Kapellen-Berg"
      }
    },
    {
      "geometry": {
        "type": "Point",
        "coordinates": [
          12.3,
          50.183333
        ]
      },
      "type": "Feature",
      "properties": {
        "hierarchy": [
          "tgn:7151123",
          "tgn:1000003",
          "tgn:7003685",
          "tgn:7000084",
          "tgn:7029392"
        ],
        "placetype": [
          "aat:300008777"
        ],
        "id": 7151123,
        "name:xx": "Kapellen-Berg"
      }
    },
    {
      "geometry": {
        "type": "Point",
        "coordinates": [
          8.433333,
          50.1
        ]
      },
      "type": "Feature",
      "properties": {
        "hierarchy": [
          "tgn:7151124",
          "tgn:1000003",
          "tgn:7003678",
          "tgn:7000084",
          "tgn:7029392"
        ],
        "placetype": [
          "aat:300008777"
        ],
        "id": 7151124,
        "name:xx": "Kapellen-Berg"
      }
    },
    {
      "geometry": {
        "type": "Point",
        "coordinates": [
          6.15,
          50.033333
        ]
      },
      "type": "Feature",
      "properties": {
        "hierarchy": [
          "tgn:7151125",
          "tgn:1000003",
          "tgn:7003682",
          "tgn:7000084",
          "tgn:7029392"
        ],
        "placetype": [
          "aat:300008777"
        ],
        "id": 7151125,
        "name:xx": "Kapellen-Berg"
      }
    },
    {
      "geometry": {
        "type": "Point",
        "coordinates": [
          10.366667,
          49.9
        ]
      },
      "type": "Feature",
      "properties": {
        "hierarchy": [
          "tgn:7151126",
          "tgn:7003669",
          "tgn:1000003",
          "tgn:7000084",
          "tgn:7029392"
        ],
        "placetype": [
          "aat:300008777"
        ],
        "id": 7151126,
        "name:xx": "Kapellenberg"
      }
    },
    {
      "geometry": {
        "type": "Point",
        "coordinates": [
          8.083333,
          49.083333
        ]
      },
      "type": "Feature",
      "properties": {
        "hierarchy": [
          "tgn:7151127",
          "tgn:1000003",
          "tgn:7003682",
          "tgn:7000084",
          "tgn:7029392"
        ],
        "placetype": [
          "aat:300008777"
        ],
        "id": 7151127,
        "name:xx": "Kapellen-Berg"
      }
    },
    {
      "geometry": {
        "type": "Point",
        "coordinates": [
          10.033333,
          48.4
        ]
      },
      "type": "Feature",
      "properties": {
        "hierarchy": [
          "tgn:7151128",
          "tgn:7003669",
          "tgn:1000003",
          "tgn:7000084",
          "tgn:7029392"
        ],
        "placetype": [
          "aat:300008777"
        ],
        "id": 7151128,
        "name:xx": "Kapellenberg"
      }
    },
    {
      "geometry": {
        "type": "Point",
        "coordinates": [
          11.016667,
          48.116667
        ]
      },
      "type": "Feature",
      "properties": {
        "hierarchy": [
          "tgn:7151129",
          "tgn:7003669",
          "tgn:1000003",
          "tgn:7000084",
          "tgn:7029392"
        ],
        "placetype": [
          "aat:300008777"
        ],
        "id": 7151129,
        "name:xx": "Kapellen Berg"
      }
    }
  ]
}
