{
  "type": "FeatureCollection",
  "features": [
    {
      "geometry": {
        "type": "Point",
        "coordinates": [
          -75.3667,
          39.7833
        ]
      },
      "type": "Feature",
      "properties": {
        "hierarchy": [
          "tgn:2491690",
          "tgn:1000001",
          "tgn:1002410",
          "tgn:7012149",
          "tgn:7007565",
          "tgn:7029392"
        ],
        "placetype": [
          "aat:300008905"
        ],
        "id": 2491690,
        "name:xx": "Maple Swamp"
      }
    },
    {
      "geometry": {
        "type": "Point",
        "coordinates": [
          -72.6,
          40.8833
        ]
      },
      "type": "Feature",
      "properties": {
        "hierarchy": [
          "tgn:2491691",
          "tgn:1000001",
          "tgn:7012149",
          "tgn:1002924",
          "tgn:7007568",
          "tgn:7029392"
        ],
        "placetype": [
          "aat:300008905"
        ],
        "id": 2491691,
        "name:xx": "Maple Swamp"
      }
    },
    {
      "geometry": {
        "type": "Point",
        "coordinates": [
          -77.6167,
          36.0667
        ]
      },
      "type": "Feature",
      "properties": {
        "hierarchy": [
          "tgn:2491692",
          "tgn:1000001",
          "tgn:7012149",
          "tgn:2001493",
          "tgn:7007709",
          "tgn:7029392"
        ],
        "placetype": [
          "aat:300008699"
        ],
        "id": 2491692,
        "name:xx": "Maple Swamp"
      }
    },
    {
      "geometry": {
        "type": "Point",
        "coordinates": [
          -75.9167,
          36.3167
        ]
      },
      "type": "Feature",
      "properties": {
        "hierarchy": [
          "tgn:2491693",
          "tgn:1000001",
          "tgn:7012149",
          "tgn:1002312",
          "tgn:7007709",
          "tgn:7029392"
        ],
        "placetype": [
          "aat:300008905"
        ],
        "id": 2491693,
        "name:xx": "Maple Swamp"
      }
    },
    {
      "geometry": {
        "type": "Point",
        "coordinates": [
          -75.05,
          41.3
        ]
      },
      "type": "Feature",
      "properties": {
        "hierarchy": [
          "tgn:2491694",
          "tgn:1000001",
          "tgn:7012149",
          "tgn:1002789",
          "tgn:7007710",
          "tgn:7029392"
        ],
        "placetype": [
          "aat:300008905"
        ],
        "id": 2491694,
        "name:xx": "Maple Swamp"
      }
    },
    {
      "geometry": {
        "type": "Point",
        "coordinates": [
          -79.05,
          33.95
        ]
      },
      "type": "Feature",
      "properties": {
        "hierarchy": [
          "tgn:2491695",
          "tgn:1000001",
          "tgn:7012149",
          "tgn:2001750",
          "tgn:7007712",
          "tgn:7029392"
        ],
        "placetype": [
          "aat:300008699"
        ],
        "id": 2491695,
        "name:xx": "Maple Swamp"
      }
    },
    {
      "geometry": {
        "type": "Point",
        "coordinates": [
          -79.3833,
          34.4167
        ]
      },
      "type": "Feature",
      "properties": {
        "hierarchy": [
          "tgn:2491696",
          "tgn:1000001",
          "tgn:2001741",
          "tgn:7012149",
          "tgn:7007712",
          "tgn:7029392"
        ],
        "placetype": [
          "aat:300008699"
        ],
        "id": 2491696,
        "name:xx": "Maple Swamp"
      }
    },
    {
      "geometry": {
        "type": "Point",
        "coordinates": [
          -79.3667,
          33.9
        ]
      },
      "type": "Feature",
      "properties": {
        "hierarchy": [
          "tgn:2491697",
          "tgn:1000001",
          "tgn:7012149",
          "tgn:2001758",
          "tgn:7007712",
          "tgn:7029392"
        ],
        "placetype": [
          "aat:300008905"
        ],
        "id": 2491697,
        "name:xx": "Maple Swamp"
      }
    },
    {
      "geometry": {
        "type": "Point",
        "coordinates": [
          -77.55,
          38.0167
        ]
      },
      "type": "Feature",
      "properties": {
        "hierarchy": [
          "tgn:2491698",
          "tgn:1000001",
          "tgn:1002235",
          "tgn:7012149",
          "tgn:7007919",
          "tgn:7029392"
        ],
        "placetype": [
          "aat:300006191"
        ],
        "id": 2491698,
        "name:xx": "Maple Swamp"
      }
    },
    {
      "geometry": {
        "type": "Point",
        "coordinates": [
          -87.1667,
          34.8667
        ]
      },
      "type": "Feature",
      "properties": {
        "hierarchy": [
          "tgn:2491699",
          "tgn:7002659",
          "tgn:1000001",
          "tgn:7012149",
          "tgn:2000041",
          "tgn:7029392"
        ],
        "placetype": [
          "aat:300008699"
        ],
        "id": 2491699,
        "name:xx": "Maple Swamp Branch"
      }
    }
  ]
}
