{
  "geometry": {
    "type": "Point",
    "coordinates": [
      27.166,
      58.083
    ]
  },
  "type": "Feature",
  "properties": {
    "hierarchy": [
      "tgn:7006639",
      "tgn:1000003",
      "tgn:7006540",
      "tgn:7029392"
    ],
    "placetype": [
      "aat:300387064",
      "aat:300000771"
    ],
    "name:en": "Põlvamaa",
    "id": 7006639
  }
}
