{
  "geometry": {
    "type": "Point",
    "coordinates": [
      31.273144,
      30.008221
    ]
  },
  "type": "Feature",
  "properties": {
    "hierarchy": [
      "tgn:7526863",
      "tgn:7001242",
      "tgn:7016833",
      "tgn:1001091",
      "tgn:7029392"
    ],
    "placetype": [
      "aat:300266755"
    ],
    "id": 7526863,
    "name:xx": "Maqābir Sīdī 'Alī Abū al Wafā"
  }
}
