{
  "type": "FeatureCollection",
  "features": [
    {
      "geometry": {
        "type": "Point",
        "coordinates": [
          -82.5333,
          37.9167
        ]
      },
      "type": "Feature",
      "properties": {
        "hierarchy": [
          "tgn:2039601",
          "tgn:1000001",
          "tgn:7012149",
          "tgn:2000824",
          "tgn:7007255",
          "tgn:7029392"
        ],
        "placetype": [
          "aat:300008347"
        ],
        "id": 2039601,
        "name:xx": "Job"
      }
    },
    {
      "geometry": {
        "type": "Point",
        "coordinates": [
          -84.1833,
          37.4
        ]
      },
      "type": "Feature",
      "properties": {
        "hierarchy": [
          "tgn:2039603",
          "tgn:1000001",
          "tgn:7012149",
          "tgn:2000840",
          "tgn:7007255",
          "tgn:7029392"
        ],
        "placetype": [
          "aat:300008347"
        ],
        "id": 2039603,
        "name:xx": "Johnetta"
      }
    },
    {
      "geometry": {
        "type": "Point",
        "coordinates": [
          -82.7333,
          37.7333
        ]
      },
      "type": "Feature",
      "properties": {
        "hierarchy": [
          "tgn:2039606",
          "tgn:1000001",
          "tgn:7012149",
          "tgn:7594172",
          "tgn:7007255",
          "tgn:7029392"
        ],
        "placetype": [
          "aat:300387331"
        ],
        "id": 2039606,
        "name:xx": "Nero"
      }
    },
    {
      "geometry": {
        "type": "Point",
        "coordinates": [
          -82.9,
          38.2333
        ]
      },
      "type": "Feature",
      "properties": {
        "hierarchy": [
          "tgn:2039609",
          "tgn:1000001",
          "tgn:1002240",
          "tgn:7012149",
          "tgn:7007255",
          "tgn:7029392"
        ],
        "placetype": [
          "aat:300008347",
          "aat:300387210"
        ],
        "id": 2039609,
        "name:xx": "Johns Run"
      }
    }
  ]
}
