{
  "geometry": {
    "type": "Point",
    "coordinates": [
      -78.15,
      42.1333
    ]
  },
  "type": "Feature",
  "properties": {
    "hierarchy": [
      "tgn:2778094",
      "tgn:1002141",
      "tgn:1000001",
      "tgn:7012149",
      "tgn:7007568",
      "tgn:7029392"
    ],
    "placetype": [
      "aat:300008347"
    ],
    "id": 2778094,
    "name:xx": "Wirt"
  }
}
