{
  "geometry": {
    "type": "Point",
    "coordinates": [
      -78.9167,
      36.1833
    ]
  },
  "type": "Feature",
  "properties": {
    "hierarchy": [
      "tgn:2602681",
      "tgn:1000001",
      "tgn:7012149",
      "tgn:2001492",
      "tgn:7007709",
      "tgn:7029392"
    ],
    "placetype": [
      "aat:300006191"
    ],
    "id": 2602681,
    "name:xx": "Quail Roost Lake Number One"
  }
}
