{
  "geometry": {
    "type": "Point",
    "coordinates": [
      -87.9667,
      43.2833
    ]
  },
  "type": "Feature",
  "properties": {
    "hierarchy": [
      "tgn:2373558",
      "tgn:1000001",
      "tgn:7012149",
      "tgn:1002766",
      "tgn:7007922",
      "tgn:7029392"
    ],
    "placetype": [
      "aat:300008347"
    ],
    "id": 2373558,
    "name:xx": "Hamilton"
  }
}
