{
  "geometry": {
    "type": "Point",
    "coordinates": [
      -112.4667,
      35.3167
    ]
  },
  "type": "Feature",
  "properties": {
    "hierarchy": [
      "tgn:7022486",
      "tgn:1000001",
      "tgn:7006451",
      "tgn:7012149",
      "tgn:7029392"
    ],
    "placetype": [
      "aat:300006191"
    ],
    "id": 7022486,
    "name:xx": "Yellow Cow Tank"
  }
}
