{
  "geometry": {
    "type": "Point",
    "coordinates": [
      -87.05,
      33.2667
    ]
  },
  "type": "Feature",
  "properties": {
    "hierarchy": [
      "tgn:2711091",
      "tgn:7002659",
      "tgn:1000001",
      "tgn:7012149",
      "tgn:2000036",
      "tgn:7029392"
    ],
    "placetype": [
      "aat:300008347"
    ],
    "id": 2711091,
    "name:xx": "Tannehill Valley Estates"
  }
}
