{
  "type": "FeatureCollection",
  "features": [
    {
      "geometry": {
        "type": "Point",
        "coordinates": [
          -78.6167,
          41.5333
        ]
      },
      "type": "Feature",
      "properties": {
        "hierarchy": [
          "tgn:2089762",
          "tgn:1000001",
          "tgn:7012149",
          "tgn:1002352",
          "tgn:7007710",
          "tgn:7029392"
        ],
        "placetype": [
          "aat:300387016"
        ],
        "id": 2089762,
        "name:xx": "Ketner"
      }
    },
    {
      "geometry": {
        "type": "Point",
        "coordinates": [
          -76.5333,
          39.8667
        ]
      },
      "type": "Feature",
      "properties": {
        "hierarchy": [
          "tgn:2089763",
          "tgn:1000001",
          "tgn:7012149",
          "tgn:1003047",
          "tgn:7007710",
          "tgn:7029392"
        ],
        "placetype": [
          "aat:300008347"
        ],
        "id": 2089763,
        "name:xx": "Keys"
      }
    },
    {
      "geometry": {
        "type": "Point",
        "coordinates": [
          -78.9833,
          39.8
        ]
      },
      "type": "Feature",
      "properties": {
        "hierarchy": [
          "tgn:2089765",
          "tgn:1000001",
          "tgn:7012149",
          "tgn:1002904",
          "tgn:7007710",
          "tgn:7029392"
        ],
        "placetype": [
          "aat:300008347",
          "aat:300387210"
        ],
        "id": 2089765,
        "name:xx": "Keystone"
      }
    },
    {
      "geometry": {
        "type": "Point",
        "coordinates": [
          -79.7,
          40.2667
        ]
      },
      "type": "Feature",
      "properties": {
        "hierarchy": [
          "tgn:2089766",
          "tgn:1000001",
          "tgn:7012149",
          "tgn:1003017",
          "tgn:7007710",
          "tgn:7029392"
        ],
        "placetype": [
          "aat:300008347"
        ],
        "id": 2089766,
        "name:xx": "Keystone"
      }
    },
    {
      "geometry": {
        "type": "Point",
        "coordinates": [
          -75.7833,
          41.2667
        ]
      },
      "type": "Feature",
      "properties": {
        "hierarchy": [
          "tgn:2089767",
          "tgn:1000001",
          "tgn:7012149",
          "tgn:1002612",
          "tgn:7007710",
          "tgn:7029392"
        ],
        "placetype": [
          "aat:300008347"
        ],
        "id": 2089767,
        "name:xx": "Keystone"
      }
    },
    {
      "geometry": {
        "type": "Point",
        "coordinates": [
          -80.0333,
          39.8833
        ]
      },
      "type": "Feature",
      "properties": {
        "hierarchy": [
          "tgn:2089768",
          "tgn:1000001",
          "tgn:7012149",
          "tgn:2001724",
          "tgn:7007710",
          "tgn:7029392"
        ],
        "placetype": [
          "aat:300008347"
        ],
        "id": 2089768,
        "name:xx": "Khedive"
      }
    },
    {
      "geometry": {
        "type": "Point",
        "coordinates": [
          -80.1,
          40.5167
        ]
      },
      "type": "Feature",
      "properties": {
        "hierarchy": [
          "tgn:2089769",
          "tgn:7013272",
          "tgn:1000001",
          "tgn:7012149",
          "tgn:7007710",
          "tgn:7029392"
        ],
        "placetype": [
          "aat:300008347"
        ],
        "id": 2089769,
        "name:xx": "Kilbuck Township"
      }
    }
  ]
}
