{
  "type": "FeatureCollection",
  "features": [
    {
      "geometry": {
        "type": "Point",
        "coordinates": [
          -160.1667,
          55.7167
        ]
      },
      "type": "Feature",
      "properties": {
        "hierarchy": [
          "tgn:2693740",
          "tgn:7030515",
          "tgn:7006450",
          "tgn:1000001",
          "tgn:7012149",
          "tgn:7029392"
        ],
        "placetype": [
          "aat:300008798"
        ],
        "id": 2693740,
        "name:xx": "Stepo, Mount"
      }
    },
    {
      "geometry": {
        "type": "Point",
        "coordinates": [
          -159.8333,
          55.7167
        ]
      },
      "type": "Feature",
      "properties": {
        "hierarchy": [
          "tgn:2693741",
          "tgn:7006450",
          "tgn:1000001",
          "tgn:7012149",
          "tgn:7029392"
        ],
        "placetype": [
          "aat:300132316"
        ],
        "id": 2693741,
        "name:xx": "Stepovak Bay"
      }
    },
    {
      "geometry": {
        "type": "Point",
        "coordinates": [
          -82.35,
          35.5833
        ]
      },
      "type": "Feature",
      "properties": {
        "hierarchy": [
          "tgn:2693744",
          "tgn:1000001",
          "tgn:2001473",
          "tgn:7012149",
          "tgn:7007709",
          "tgn:7029392"
        ],
        "placetype": [
          "aat:300008699"
        ],
        "id": 2693744,
        "name:xx": "Stepp Branch"
      }
    },
    {
      "geometry": {
        "type": "Point",
        "coordinates": [
          -82.4,
          37.85
        ]
      },
      "type": "Feature",
      "properties": {
        "hierarchy": [
          "tgn:2693745",
          "tgn:1000001",
          "tgn:7012149",
          "tgn:2002299",
          "tgn:7013961",
          "tgn:7029392"
        ],
        "placetype": [
          "aat:300008699"
        ],
        "id": 2693745,
        "name:xx": "Stepp Branch"
      }
    },
    {
      "geometry": {
        "type": "Point",
        "coordinates": [
          -93.3,
          35.8333
        ]
      },
      "type": "Feature",
      "properties": {
        "hierarchy": [
          "tgn:2693746",
          "tgn:1000001",
          "tgn:7016172",
          "tgn:7012149",
          "tgn:2000155",
          "tgn:7029392"
        ],
        "placetype": [
          "aat:300008706"
        ],
        "id": 2693746,
        "name:xx": "Stepp Creek"
      }
    },
    {
      "geometry": {
        "type": "Point",
        "coordinates": [
          -110.55,
          42.3
        ]
      },
      "type": "Feature",
      "properties": {
        "hierarchy": [
          "tgn:2693747",
          "tgn:1000001",
          "tgn:7012149",
          "tgn:2002376",
          "tgn:7007923",
          "tgn:7029392"
        ],
        "placetype": [
          "aat:300008706"
        ],
        "id": 2693747,
        "name:xx": "Stepp Creek"
      }
    },
    {
      "geometry": {
        "type": "Point",
        "coordinates": [
          -85.7,
          35.5333
        ]
      },
      "type": "Feature",
      "properties": {
        "hierarchy": [
          "tgn:2693748",
          "tgn:1000001",
          "tgn:7012149",
          "tgn:2001925",
          "tgn:7007825",
          "tgn:7029392"
        ],
        "placetype": [
          "aat:300008798"
        ],
        "id": 2693748,
        "name:xx": "Stepp Knob"
      }
    },
    {
      "geometry": {
        "type": "Point",
        "coordinates": [
          -88.2667,
          33.15
        ]
      },
      "type": "Feature",
      "properties": {
        "hierarchy": [
          "tgn:2693749",
          "tgn:7002659",
          "tgn:1000001",
          "tgn:7012149",
          "tgn:2000053",
          "tgn:7029392"
        ],
        "placetype": [
          "aat:300008680"
        ],
        "id": 2693749,
        "name:xx": "Stepp Lake"
      }
    }
  ]
}
