{
  "geometry": {
    "type": "Point",
    "coordinates": [
      -87.0667,
      35.3667
    ]
  },
  "type": "Feature",
  "properties": {
    "hierarchy": [
      "tgn:2145929",
      "tgn:1000001",
      "tgn:7012149",
      "tgn:2001864",
      "tgn:7007825",
      "tgn:7029392"
    ],
    "placetype": [
      "aat:300008699"
    ],
    "id": 2145929,
    "name:xx": "Ball Branch"
  }
}
