{
  "geometry": {
    "type": "Point",
    "coordinates": [
      -120.8833,
      39.7167
    ]
  },
  "type": "Feature",
  "properties": {
    "hierarchy": [
      "tgn:2582469",
      "tgn:1000001",
      "tgn:7012149",
      "tgn:7007157",
      "tgn:1002894",
      "tgn:7029392"
    ],
    "placetype": [
      "aat:300008706"
    ],
    "id": 2582469,
    "name:xx": "Pine Grove Creek"
  }
}
