{
  "geometry": {
    "type": "Point",
    "coordinates": [
      -114.4333,
      48.5833
    ]
  },
  "type": "Feature",
  "properties": {
    "hierarchy": [
      "tgn:2237385",
      "tgn:1000001",
      "tgn:7012149",
      "tgn:2001274",
      "tgn:7007524",
      "tgn:7029392"
    ],
    "placetype": [
      "aat:300386845"
    ],
    "id": 2237385,
    "name:xx": "China Basin"
  }
}
