{
  "geometry": {
    "type": "Point",
    "coordinates": [
      -86.4667,
      32.3333
    ]
  },
  "type": "Feature",
  "properties": {
    "hierarchy": [
      "tgn:2634735",
      "tgn:7002659",
      "tgn:1000001",
      "tgn:7012149",
      "tgn:2000050",
      "tgn:7029392"
    ],
    "placetype": [
      "aat:300006191"
    ],
    "id": 2634735,
    "name:xx": "Rutland Lake"
  }
}
