{
  "geometry": {
    "type": "Point",
    "coordinates": [
      -144.3667,
      59.9333
    ]
  },
  "type": "Feature",
  "properties": {
    "hierarchy": [
      "tgn:2432179",
      "tgn:7006450",
      "tgn:1000001",
      "tgn:7012149",
      "tgn:2000086",
      "tgn:7029392"
    ],
    "placetype": [
      "aat:300008791"
    ],
    "id": 2432179,
    "name:xx": "Kayak Island"
  }
}
