{
  "geometry": {
    "type": "Point",
    "coordinates": [
      -85.2833,
      35.5667
    ]
  },
  "type": "Feature",
  "properties": {
    "hierarchy": [
      "tgn:2165775",
      "tgn:1000001",
      "tgn:2001840",
      "tgn:7012149",
      "tgn:7007825",
      "tgn:7029392"
    ],
    "placetype": [
      "aat:300000390"
    ],
    "id": 2165775,
    "name:xx": "Bickford Mines"
  }
}
