{
  "geometry": {
    "type": "Point",
    "coordinates": [
      -85.9833,
      39.7667
    ]
  },
  "type": "Feature",
  "properties": {
    "hierarchy": [
      "tgn:2525036",
      "tgn:1000001",
      "tgn:7012149",
      "tgn:7007252",
      "tgn:7029392"
    ],
    "placetype": [
      "aat:300006075"
    ],
    "id": 2525036,
    "name:xx": "Morris Ditch"
  }
}
