{
  "type": "FeatureCollection",
  "features": [
    {
      "geometry": {
        "type": "Point",
        "coordinates": [
          -120.9833,
          41
        ]
      },
      "type": "Feature",
      "properties": {
        "hierarchy": [
          "tgn:2533860",
          "tgn:1000001",
          "tgn:7012149",
          "tgn:7007157",
          "tgn:2000184",
          "tgn:7029392"
        ],
        "placetype": [
          "aat:300008697"
        ],
        "id": 2533860,
        "name:xx": "Myer Spring"
      }
    },
    {
      "geometry": {
        "type": "Point",
        "coordinates": [
          -116.0333,
          32.6667
        ]
      },
      "type": "Feature",
      "properties": {
        "hierarchy": [
          "tgn:2533861",
          "tgn:1000001",
          "tgn:7012149",
          "tgn:2000182",
          "tgn:7007157",
          "tgn:7029392"
        ],
        "placetype": [
          "aat:300008761"
        ],
        "id": 2533861,
        "name:xx": "Myer Valley"
      }
    },
    {
      "geometry": {
        "type": "Point",
        "coordinates": [
          -77.4667,
          40.6833
        ]
      },
      "type": "Feature",
      "properties": {
        "hierarchy": [
          "tgn:2533864",
          "tgn:1000001",
          "tgn:7012149",
          "tgn:1002669",
          "tgn:7007710",
          "tgn:7029392"
        ],
        "placetype": [
          "aat:300008746"
        ],
        "id": 2533864,
        "name:xx": "Myerly Spring Cave"
      }
    },
    {
      "geometry": {
        "type": "Point",
        "coordinates": [
          -105.2,
          35.4333
        ]
      },
      "type": "Feature",
      "properties": {
        "hierarchy": [
          "tgn:2533865",
          "tgn:1000001",
          "tgn:7012149",
          "tgn:2001453",
          "tgn:7007566",
          "tgn:7029392"
        ],
        "placetype": [
          "aat:300008347"
        ],
        "id": 2533865,
        "name:xx": "Myers"
      }
    },
    {
      "geometry": {
        "type": "Point",
        "coordinates": [
          -108.7167,
          35.55
        ]
      },
      "type": "Feature",
      "properties": {
        "hierarchy": [
          "tgn:2533866",
          "tgn:1000001",
          "tgn:7012149",
          "tgn:7019676",
          "tgn:7007566",
          "tgn:7029392"
        ],
        "placetype": [
          "aat:300000390"
        ],
        "id": 2533866,
        "name:xx": "Myers"
      }
    },
    {
      "geometry": {
        "type": "Point",
        "coordinates": [
          -81.1167,
          40.7667
        ]
      },
      "type": "Feature",
      "properties": {
        "hierarchy": [
          "tgn:2533867",
          "tgn:1000001",
          "tgn:7012149",
          "tgn:1002917",
          "tgn:7007706",
          "tgn:7029392"
        ],
        "placetype": [
          "aat:300008347"
        ],
        "id": 2533867,
        "name:xx": "Myers"
      }
    },
    {
      "geometry": {
        "type": "Point",
        "coordinates": [
          -82.6167,
          40.8333
        ]
      },
      "type": "Feature",
      "properties": {
        "hierarchy": [
          "tgn:2533868",
          "tgn:1000001",
          "tgn:7012149",
          "tgn:1002823",
          "tgn:7007706",
          "tgn:7029392"
        ],
        "placetype": [
          "aat:300008347"
        ],
        "id": 2533868,
        "name:xx": "Myers"
      }
    },
    {
      "geometry": {
        "type": "Point",
        "coordinates": [
          -83.5167,
          39.8833
        ]
      },
      "type": "Feature",
      "properties": {
        "hierarchy": [
          "tgn:2533869",
          "tgn:1000001",
          "tgn:7012149",
          "tgn:1002625",
          "tgn:7007706",
          "tgn:7029392"
        ],
        "placetype": [
          "aat:300008347"
        ],
        "id": 2533869,
        "name:xx": "Myers"
      }
    }
  ]
}
