{
  "geometry": {
    "type": "Point",
    "coordinates": [
      34.1667,
      50.75
    ]
  },
  "type": "Feature",
  "properties": {
    "hierarchy": [
      "tgn:1101703",
      "tgn:1000003",
      "tgn:1003410",
      "tgn:7006660",
      "tgn:7029392"
    ],
    "placetype": [
      "aat:300008189"
    ],
    "id": 1101703,
    "name:xx": "Michajlovskaja Celina, zapovednik"
  }
}
