{
  "geometry": {
    "type": "Point",
    "coordinates": [
      -81.0167,
      25.6667
    ]
  },
  "type": "Feature",
  "properties": {
    "hierarchy": [
      "tgn:2472003",
      "tgn:1000001",
      "tgn:2000275",
      "tgn:7012149",
      "tgn:7007240",
      "tgn:7029392"
    ],
    "placetype": [
      "aat:300132451"
    ],
    "id": 2472003,
    "name:xx": "Lostmans Pines"
  }
}
