{
  "geometry": {
    "type": "Point",
    "coordinates": [
      31.346224,
      30.030609
    ]
  },
  "type": "Feature",
  "properties": {
    "hierarchy": [
      "tgn:7531982",
      "tgn:7001242",
      "tgn:7016833",
      "tgn:1001091",
      "tgn:7029392"
    ],
    "placetype": [
      "aat:300000853"
    ],
    "id": 7531982,
    "name:xx": "Al Hay'ah al 'Āmmah lil Istithmār wa al Manāţiq al Ḩurrah"
  }
}
