{
  "geometry": {
    "type": "Point",
    "coordinates": [
      -98.2167,
      31.6833
    ]
  },
  "type": "Feature",
  "properties": {
    "hierarchy": [
      "tgn:2681078",
      "tgn:1000001",
      "tgn:7012149",
      "tgn:2001996",
      "tgn:7007826",
      "tgn:7029392"
    ],
    "placetype": [
      "aat:300008706"
    ],
    "id": 2681078,
    "name:xx": "South Mesquite Creek"
  }
}
