{
  "geometry": {
    "type": "Point",
    "coordinates": [
      -95.3333,
      42.9167
    ]
  },
  "type": "Feature",
  "properties": {
    "hierarchy": [
      "tgn:2035456",
      "tgn:1000001",
      "tgn:2000581",
      "tgn:7012149",
      "tgn:7007253",
      "tgn:7029392"
    ],
    "placetype": [
      "aat:300008347"
    ],
    "id": 2035456,
    "name:xx": "Peterson"
  }
}
