{
  "geometry": {
    "type": "Point",
    "coordinates": [
      -60.1667,
      -51.3333
    ]
  },
  "type": "Feature",
  "properties": {
    "hierarchy": [
      "tgn:1009044",
      "tgn:7005151",
      "tgn:7005152",
      "tgn:1000002",
      "tgn:7029392"
    ],
    "placetype": [
      "aat:300008791"
    ],
    "id": 1009044,
    "name:xx": "Saunders Island"
  }
}
