{
  "geometry": {
    "type": "Point",
    "coordinates": [
      -85.2167,
      30.8667
    ]
  },
  "type": "Feature",
  "properties": {
    "hierarchy": [
      "tgn:2400813",
      "tgn:1000001",
      "tgn:2000273",
      "tgn:7012149",
      "tgn:7007240",
      "tgn:7029392"
    ],
    "placetype": [
      "aat:300008680"
    ],
    "id": 2400813,
    "name:xx": "Horse Ponds"
  }
}
