{
  "type": "FeatureCollection",
  "features": [
    {
      "geometry": {
        "type": "Point",
        "coordinates": [
          -68.6,
          45.8
        ]
      },
      "type": "Feature",
      "properties": {
        "hierarchy": [
          "tgn:2733900",
          "tgn:1000001",
          "tgn:7012149",
          "tgn:2000927",
          "tgn:7007515",
          "tgn:7029392"
        ],
        "placetype": [
          "aat:300008905"
        ],
        "id": 2733900,
        "name:xx": "Turner Logan"
      }
    },
    {
      "geometry": {
        "type": "Point",
        "coordinates": [
          -91.7167,
          35.8833
        ]
      },
      "type": "Feature",
      "properties": {
        "hierarchy": [
          "tgn:2733901",
          "tgn:1000001",
          "tgn:7016172",
          "tgn:7012149",
          "tgn:2000136",
          "tgn:7029392"
        ],
        "placetype": [
          "aat:300000390"
        ],
        "id": 2733901,
        "name:xx": "Turner Mine"
      }
    },
    {
      "geometry": {
        "type": "Point",
        "coordinates": [
          -123.3333,
          41.7333
        ]
      },
      "type": "Feature",
      "properties": {
        "hierarchy": [
          "tgn:2733902",
          "tgn:1000001",
          "tgn:7012149",
          "tgn:7007157",
          "tgn:2000189",
          "tgn:7029392"
        ],
        "placetype": [
          "aat:300000390"
        ],
        "id": 2733902,
        "name:xx": "Turner Mine"
      }
    },
    {
      "geometry": {
        "type": "Point",
        "coordinates": [
          -104.8667,
          37.7
        ]
      },
      "type": "Feature",
      "properties": {
        "hierarchy": [
          "tgn:2733903",
          "tgn:1000001",
          "tgn:7012149",
          "tgn:2000219",
          "tgn:7007158",
          "tgn:7029392"
        ],
        "placetype": [
          "aat:300000390"
        ],
        "id": 2733903,
        "name:xx": "Turner Mine"
      }
    },
    {
      "geometry": {
        "type": "Point",
        "coordinates": [
          -117,
          39.5
        ]
      },
      "type": "Feature",
      "properties": {
        "hierarchy": [
          "tgn:2733905",
          "tgn:1000001",
          "tgn:2001415",
          "tgn:7012149",
          "tgn:7007526",
          "tgn:7029392"
        ],
        "placetype": [
          "aat:300000390"
        ],
        "id": 2733905,
        "name:xx": "Turner Mine"
      }
    },
    {
      "geometry": {
        "type": "Point",
        "coordinates": [
          -104.3333,
          36.95
        ]
      },
      "type": "Feature",
      "properties": {
        "hierarchy": [
          "tgn:2733906",
          "tgn:1000001",
          "tgn:2001432",
          "tgn:7012149",
          "tgn:7007566",
          "tgn:7029392"
        ],
        "placetype": [
          "aat:300000390"
        ],
        "id": 2733906,
        "name:xx": "Turner Mine Number Two"
      }
    },
    {
      "geometry": {
        "type": "Point",
        "coordinates": [
          -122.35,
          38.7333
        ]
      },
      "type": "Feature",
      "properties": {
        "hierarchy": [
          "tgn:2733907",
          "tgn:1000001",
          "tgn:7012149",
          "tgn:7007157",
          "tgn:1002706",
          "tgn:7029392"
        ],
        "placetype": [
          "aat:300008798"
        ],
        "id": 2733907,
        "name:xx": "Turner Mountain"
      }
    },
    {
      "geometry": {
        "type": "Point",
        "coordinates": [
          -121.6,
          40.2833
        ]
      },
      "type": "Feature",
      "properties": {
        "hierarchy": [
          "tgn:2733908",
          "tgn:1000001",
          "tgn:7012149",
          "tgn:7007157",
          "tgn:2000190",
          "tgn:7029392"
        ],
        "placetype": [
          "aat:300008798"
        ],
        "id": 2733908,
        "name:xx": "Turner Mountain"
      }
    },
    {
      "geometry": {
        "type": "Point",
        "coordinates": [
          -73.5167,
          41.5833
        ]
      },
      "type": "Feature",
      "properties": {
        "hierarchy": [
          "tgn:2733909",
          "tgn:1002366",
          "tgn:1000001",
          "tgn:7012149",
          "tgn:7007159",
          "tgn:7029392"
        ],
        "placetype": [
          "aat:300008798"
        ],
        "id": 2733909,
        "name:xx": "Turner Mountain"
      }
    }
  ]
}
