{
  "geometry": {
    "type": "Point",
    "coordinates": [
      -123.3167,
      44.9667
    ]
  },
  "type": "Feature",
  "properties": {
    "hierarchy": [
      "tgn:2261521",
      "tgn:1000001",
      "tgn:7012149",
      "tgn:1002794",
      "tgn:7007708",
      "tgn:7029392"
    ],
    "placetype": [
      "aat:300006191"
    ],
    "id": 2261521,
    "name:xx": "Couter Reservoir"
  }
}
