{
  "geometry": {
    "type": "Point",
    "coordinates": [
      -163.5333,
      67.2333
    ]
  },
  "type": "Feature",
  "properties": {
    "hierarchy": [
      "tgn:2312224",
      "tgn:7006450",
      "tgn:1000001",
      "tgn:7012149",
      "tgn:2124014",
      "tgn:7029392"
    ],
    "placetype": [
      "aat:300008798"
    ],
    "id": 2312224,
    "name:xx": "Eigaloruk"
  }
}
