{
  "geometry": {
    "type": "Point",
    "coordinates": [
      -85.4167,
      35.1833
    ]
  },
  "type": "Feature",
  "properties": {
    "hierarchy": [
      "tgn:2567099",
      "tgn:1000001",
      "tgn:7012149",
      "tgn:2001894",
      "tgn:7007825",
      "tgn:7029392"
    ],
    "placetype": [
      "aat:300000390"
    ],
    "id": 2567099,
    "name:xx": "Panther Creek Number 1 Mine"
  }
}
