{
  "geometry": {
    "type": "Point",
    "coordinates": [
      -113.7667,
      46.55
    ]
  },
  "type": "Feature",
  "properties": {
    "hierarchy": [
      "tgn:2240078",
      "tgn:1000001",
      "tgn:7012149",
      "tgn:2001279",
      "tgn:7007524",
      "tgn:7029392"
    ],
    "placetype": [
      "aat:300008798"
    ],
    "id": 2240078,
    "name:xx": "Cinnamon Bear Point"
  }
}
