{
  "type": "FeatureCollection",
  "features": [
    {
      "geometry": {
        "type": "Point",
        "coordinates": [
          45.067,
          32.908
        ]
      },
      "type": "Feature",
      "properties": {
        "hierarchy": [
          "tgn:7029580",
          "tgn:1000004",
          "tgn:1000118",
          "tgn:1001596",
          "tgn:7029392"
        ],
        "placetype": [
          "aat:300008347"
        ],
        "id": 7029580,
        "name:xx": "Aziziyah"
      }
    },
    {
      "geometry": {
        "type": "Point",
        "coordinates": [
          103,
          16
        ]
      },
      "type": "Feature",
      "properties": {
        "hierarchy": [
          "tgn:7029581",
          "tgn:7005193",
          "tgn:1000004",
          "tgn:7000932",
          "tgn:1000142",
          "tgn:7029392"
        ],
        "placetype": [
          "aat:300106738",
          "aat:300008347",
          "aat:300387007",
          "aat:300000810",
          "aat:300167671",
          "aat:300019278",
          "aat:300387004"
        ],
        "id": 7029581,
        "name:xx": "Noen U-Loke"
      }
    },
    {
      "geometry": {
        "type": "Point",
        "coordinates": [
          45.815,
          15.001
        ]
      },
      "type": "Feature",
      "properties": {
        "hierarchy": [
          "tgn:7029583",
          "tgn:1000139",
          "tgn:7004363",
          "tgn:1000004",
          "tgn:7000261",
          "tgn:7029392"
        ],
        "placetype": [
          "aat:300008347",
          "aat:300387007",
          "aat:300000810",
          "aat:300167671",
          "aat:300007148"
        ],
        "id": 7029583,
        "name:xx": "Timnaʻ"
      }
    },
    {
      "geometry": {
        "type": "Point",
        "coordinates": [
          43.643,
          36.263
        ]
      },
      "type": "Feature",
      "properties": {
        "hierarchy": [
          "tgn:7029584",
          "tgn:1001115",
          "tgn:1000004",
          "tgn:1000118",
          "tgn:7029392"
        ],
        "placetype": [
          "aat:300008347"
        ],
        "id": 7029584,
        "name:xx": "Aski Kalak"
      }
    },
    {
      "geometry": {
        "type": "Point",
        "coordinates": [
          31.8333,
          18.5
        ]
      },
      "type": "Feature",
      "properties": {
        "hierarchy": [
          "tgn:7029589",
          "tgn:7001242",
          "tgn:1001112",
          "tgn:1000201",
          "tgn:7029392"
        ],
        "placetype": [
          "aat:300387178",
          "aat:300008347",
          "aat:300387264",
          "aat:300387218"
        ],
        "id": 7029589,
        "name:xx": "Merowe"
      }
    }
  ]
}
