{
  "geometry": {
    "type": "Point",
    "coordinates": [
      -90.7667,
      46.2833
    ]
  },
  "type": "Feature",
  "properties": {
    "hierarchy": [
      "tgn:1110473",
      "tgn:1000001",
      "tgn:7012149",
      "tgn:7029392"
    ],
    "placetype": [
      "aat:300008777"
    ],
    "id": 1110473,
    "name:xx": "Gogebic Range"
  }
}
