{
  "geometry": {
    "type": "Point",
    "coordinates": [
      -99.55,
      28.7667
    ]
  },
  "type": "Feature",
  "properties": {
    "hierarchy": [
      "tgn:2210147",
      "tgn:1000001",
      "tgn:7012149",
      "tgn:2002100",
      "tgn:7007826",
      "tgn:7029392"
    ],
    "placetype": [
      "aat:300008706"
    ],
    "id": 2210147,
    "name:xx": "Burtrand Creek"
  }
}
