{
  "geometry": {
    "type": "Point",
    "coordinates": [
      118.05,
      32.9333
    ]
  },
  "type": "Feature",
  "properties": {
    "hierarchy": [
      "tgn:1117427",
      "tgn:7002075",
      "tgn:1000004",
      "tgn:1000111",
      "tgn:7029392"
    ],
    "placetype": [
      "aat:300008680"
    ],
    "id": 1117427,
    "name:xx": "Nüshan Hu"
  }
}
