{
  "geometry": {
    "type": "Point",
    "coordinates": [
      -97.694444,
      16.6875
    ]
  },
  "type": "Feature",
  "properties": {
    "hierarchy": [
      "tgn:7415782",
      "tgn:1000001",
      "tgn:7005591",
      "tgn:7005560",
      "tgn:7029392"
    ],
    "placetype": [
      "aat:300008699"
    ],
    "id": 7415782,
    "name:es": "Atoyaquillo, Río"
  }
}
