{
  "geometry": {
    "type": "Point",
    "coordinates": [
      -79.8833,
      42.0333
    ]
  },
  "type": "Feature",
  "properties": {
    "hierarchy": [
      "tgn:2091912",
      "tgn:1000001",
      "tgn:7012149",
      "tgn:1002358",
      "tgn:7007710",
      "tgn:7029392"
    ],
    "placetype": [
      "aat:300008347",
      "aat:300387210"
    ],
    "id": 2091912,
    "name:xx": "Phillipsville"
  }
}
