{
  "geometry": {
    "type": "Point",
    "coordinates": [
      -63.5833,
      -64.55
    ]
  },
  "type": "Feature",
  "properties": {
    "hierarchy": [
      "tgn:1006305",
      "tgn:1000007",
      "tgn:7029392"
    ],
    "placetype": [
      "aat:300008791"
    ],
    "id": 1006305,
    "name:xx": "Anvers Island"
  }
}
