{
  "geometry": {
    "type": "Point",
    "coordinates": [
      -87.8167,
      45.2833
    ]
  },
  "type": "Feature",
  "properties": {
    "hierarchy": [
      "tgn:2740155",
      "tgn:1000001",
      "tgn:7012149",
      "tgn:2002337",
      "tgn:7007922",
      "tgn:7029392"
    ],
    "placetype": [
      "aat:300008699"
    ],
    "id": 2740155,
    "name:xx": "Upper Inlet"
  }
}
