{
  "geometry": {
    "type": "Point",
    "coordinates": [
      86.130635,
      20.47954
    ]
  },
  "type": "Feature",
  "properties": {
    "hierarchy": [
      "tgn:7557221",
      "tgn:1000004",
      "tgn:7000198",
      "tgn:7016694",
      "tgn:7029392"
    ],
    "placetype": [
      "aat:300008347"
    ],
    "name:en": "Sālepur",
    "id": 7557221
  }
}
