{
  "geometry": {
    "type": "Point",
    "coordinates": [
      -91.7167,
      47.6167
    ]
  },
  "type": "Feature",
  "properties": {
    "hierarchy": [
      "tgn:2542007",
      "tgn:1000001",
      "tgn:7012149",
      "tgn:2001036",
      "tgn:7007521",
      "tgn:7029392"
    ],
    "placetype": [
      "aat:300008706"
    ],
    "id": 2542007,
    "name:xx": "Nip Creek"
  }
}
