{
  "geometry": {
    "type": "Point",
    "coordinates": [
      -80.8333,
      28.5167
    ]
  },
  "type": "Feature",
  "properties": {
    "hierarchy": [
      "tgn:2173952",
      "tgn:1000001",
      "tgn:1002200",
      "tgn:7012149",
      "tgn:7007240",
      "tgn:7029392"
    ],
    "placetype": [
      "aat:300008905"
    ],
    "id": 2173952,
    "name:xx": "Bird Lake"
  }
}
