{
  "geometry": {
    "type": "Point",
    "coordinates": [
      81.683333,
      21.35
    ]
  },
  "type": "Feature",
  "properties": {
    "hierarchy": [
      "tgn:7555505",
      "tgn:1000004",
      "tgn:7031781",
      "tgn:7000198",
      "tgn:7029392"
    ],
    "placetype": [
      "aat:300008347"
    ],
    "name:en": "Māndhar",
    "id": 7555505
  }
}
