{
  "geometry": {
    "type": "Point",
    "coordinates": [
      31.1667,
      2.6333
    ]
  },
  "type": "Feature",
  "properties": {
    "hierarchy": [
      "tgn:1095092",
      "tgn:7001242",
      "tgn:1000908",
      "tgn:1000206",
      "tgn:7029392"
    ],
    "placetype": [
      "aat:300008347"
    ],
    "id": 1095092,
    "name:xx": "Okollo"
  }
}
