{
  "geometry": {
    "type": "Point",
    "coordinates": [
      -102.3333,
      39.1667
    ]
  },
  "type": "Feature",
  "properties": {
    "hierarchy": [
      "tgn:2508013",
      "tgn:1000001",
      "tgn:7012149",
      "tgn:7029392"
    ],
    "placetype": [
      "aat:300008706"
    ],
    "id": 2508013,
    "name:xx": "Middle Beaver Creek"
  }
}
