{
  "geometry": {
    "type": "Point",
    "coordinates": [
      -85.2333,
      44.35
    ]
  },
  "type": "Feature",
  "properties": {
    "hierarchy": [
      "tgn:2355809",
      "tgn:1000001",
      "tgn:7012149",
      "tgn:2000980",
      "tgn:7007520",
      "tgn:7029392"
    ],
    "placetype": [
      "aat:300008680"
    ],
    "id": 2355809,
    "name:xx": "Goose Lake"
  }
}
