{
  "geometry": {
    "type": "Point",
    "coordinates": [
      -70.6833,
      41.8333
    ]
  },
  "type": "Feature",
  "properties": {
    "hierarchy": [
      "tgn:2634069",
      "tgn:1000001",
      "tgn:7014423",
      "tgn:7012149",
      "tgn:7007517",
      "tgn:7029392"
    ],
    "placetype": [
      "aat:300008905"
    ],
    "id": 2634069,
    "name:xx": "Russell Bogs"
  }
}
