{
  "geometry": {
    "type": "Point",
    "coordinates": [
      -105.0167,
      37.4167
    ]
  },
  "type": "Feature",
  "properties": {
    "hierarchy": [
      "tgn:2310663",
      "tgn:1000001",
      "tgn:7012149",
      "tgn:2000219",
      "tgn:7007158",
      "tgn:7029392"
    ],
    "placetype": [
      "aat:300266640"
    ],
    "id": 2310663,
    "name:xx": "Echo Ridge"
  }
}
