{
  "geometry": {
    "type": "Point",
    "coordinates": [
      -85.05,
      37.0167
    ]
  },
  "type": "Feature",
  "properties": {
    "hierarchy": [
      "tgn:2371921",
      "tgn:1000001",
      "tgn:7012149",
      "tgn:2000841",
      "tgn:7007255",
      "tgn:7029392"
    ],
    "placetype": [
      "aat:300266640"
    ],
    "id": 2371921,
    "name:xx": "Half Acre Ridge"
  }
}
