{
  "geometry": {
    "type": "Point",
    "coordinates": [
      -66.9667,
      44.8667
    ]
  },
  "type": "Feature",
  "properties": {
    "hierarchy": [
      "tgn:1101830",
      "tgn:1006698",
      "tgn:7005685",
      "tgn:1000001",
      "tgn:7005799",
      "tgn:7029392"
    ],
    "placetype": [
      "aat:300008189"
    ],
    "id": 1101830,
    "name:xx": "Roosevelt Campobello International Park"
  }
}
