{
  "geometry": {
    "type": "Point",
    "coordinates": [
      -91.2833,
      38.3167
    ]
  },
  "type": "Feature",
  "properties": {
    "hierarchy": [
      "tgn:2492531",
      "tgn:1000001",
      "tgn:7012149",
      "tgn:1002384",
      "tgn:7007523",
      "tgn:7029392"
    ],
    "placetype": [
      "aat:300006191"
    ],
    "id": 2492531,
    "name:xx": "Marie Otte Reservoir"
  }
}
