{
  "geometry": {
    "type": "Point",
    "coordinates": [
      -156.05,
      20.65
    ]
  },
  "type": "Feature",
  "properties": {
    "hierarchy": [
      "tgn:2141114",
      "tgn:1002648",
      "tgn:1000001",
      "tgn:7019158",
      "tgn:7012149",
      "tgn:7007249",
      "tgn:7029392"
    ],
    "placetype": [
      "aat:300132316"
    ],
    "id": 2141114,
    "name:xx": "Awapaewaa Bay"
  }
}
