{
  "geometry": {
    "type": "Point",
    "coordinates": [
      -85.1167,
      32.5667
    ]
  },
  "type": "Feature",
  "properties": {
    "hierarchy": [
      "tgn:2732506",
      "tgn:7002659",
      "tgn:1000001",
      "tgn:7012149",
      "tgn:2000040",
      "tgn:7029392"
    ],
    "placetype": [
      "aat:300008706"
    ],
    "id": 2732506,
    "name:xx": "Turkey Creek"
  }
}
