{
  "geometry": {
    "type": "Point",
    "coordinates": [
      30.743519,
      30.635443
    ]
  },
  "type": "Feature",
  "properties": {
    "hierarchy": [
      "tgn:7540795",
      "tgn:7001242",
      "tgn:1001075",
      "tgn:7016833",
      "tgn:7029392"
    ],
    "placetype": [
      "aat:300008347"
    ],
    "name:en": "Qaryat Khālid Ibn al Walīd",
    "id": 7540795
  }
}
