{
  "geometry": {
    "type": "Point",
    "coordinates": [
      -105.6667,
      36.2667
    ]
  },
  "type": "Feature",
  "properties": {
    "hierarchy": [
      "tgn:2740113",
      "tgn:1000001",
      "tgn:7012149",
      "tgn:2001457",
      "tgn:7007566",
      "tgn:7029392"
    ],
    "placetype": [
      "aat:300000390"
    ],
    "id": 2740113,
    "name:xx": "Upper Hondo Canyon Prospect"
  }
}
