{
  "geometry": {
    "type": "Point",
    "coordinates": [
      -85.75,
      31.5667
    ]
  },
  "type": "Feature",
  "properties": {
    "hierarchy": [
      "tgn:2711358",
      "tgn:7002659",
      "tgn:1000001",
      "tgn:7012149",
      "tgn:2000022",
      "tgn:7029392"
    ],
    "placetype": [
      "aat:300008699"
    ],
    "id": 2711358,
    "name:xx": "Tanyard Branch"
  }
}
