{
  "geometry": {
    "type": "Point",
    "coordinates": [
      -112.8667,
      33.4167
    ]
  },
  "type": "Feature",
  "properties": {
    "hierarchy": [
      "tgn:2777965",
      "tgn:1000001",
      "tgn:7006451",
      "tgn:7012149",
      "tgn:2000097",
      "tgn:7029392"
    ],
    "placetype": [
      "aat:300008347"
    ],
    "id": 2777965,
    "name:xx": "Wintersburg"
  }
}
