{
  "geometry": {
    "type": "Point",
    "coordinates": [
      8.35,
      48.75
    ]
  },
  "type": "Feature",
  "properties": {
    "hierarchy": [
      "tgn:7198266",
      "tgn:7003692",
      "tgn:1000003",
      "tgn:7000084",
      "tgn:7029392"
    ],
    "placetype": [
      "aat:300006891"
    ],
    "id": 7198266,
    "name:xx": "Schloß Eberstein"
  }
}
