{
  "geometry": {
    "type": "Point",
    "coordinates": [
      -120.0333,
      41.0167
    ]
  },
  "type": "Feature",
  "properties": {
    "hierarchy": [
      "tgn:7021306",
      "tgn:1000001",
      "tgn:7012149",
      "tgn:7029392"
    ],
    "placetype": [
      "aat:300386845",
      "aat:300008761"
    ],
    "id": 7021306,
    "name:xx": "Tuledad Valley"
  }
}
