{
  "geometry": {
    "type": "Point",
    "coordinates": [
      -113.2333,
      36.9167
    ]
  },
  "type": "Feature",
  "properties": {
    "hierarchy": [
      "tgn:2739318",
      "tgn:1000001",
      "tgn:7006451",
      "tgn:7012149",
      "tgn:2000098",
      "tgn:7029392"
    ],
    "placetype": [
      "aat:300008798"
    ],
    "id": 2739318,
    "name:xx": "Upper Antelope"
  }
}
