{
  "geometry": {
    "type": "Point",
    "coordinates": [
      -84.1333,
      35.9333
    ]
  },
  "type": "Feature",
  "properties": {
    "hierarchy": [
      "tgn:2588342",
      "tgn:1000001",
      "tgn:7012149",
      "tgn:2001883",
      "tgn:7007825",
      "tgn:7029392"
    ],
    "placetype": [
      "aat:300008347"
    ],
    "id": 2588342,
    "name:xx": "Plum Creek"
  }
}
