{
  "geometry": {
    "type": "Point",
    "coordinates": [
      167.9167,
      -29.0333
    ]
  },
  "type": "Feature",
  "properties": {
    "hierarchy": [
      "tgn:1100008",
      "tgn:7000430",
      "tgn:1000006",
      "tgn:7029392"
    ],
    "placetype": [
      "aat:300007466"
    ],
    "id": 1100008,
    "name:xx": "Saint Barnabas Chapel"
  }
}
