{
  "geometry": {
    "type": "Point",
    "coordinates": [
      -85.75,
      37.9333
    ]
  },
  "type": "Feature",
  "properties": {
    "hierarchy": [
      "tgn:2037663",
      "tgn:1000001",
      "tgn:2000774",
      "tgn:7012149",
      "tgn:7007255",
      "tgn:7029392"
    ],
    "placetype": [
      "aat:300008347",
      "aat:300387210"
    ],
    "id": 2037663,
    "name:xx": "Beech Grove"
  }
}
