{
  "geometry": {
    "type": "Point",
    "coordinates": [
      -111.3667,
      41.6667
    ]
  },
  "type": "Feature",
  "properties": {
    "hierarchy": [
      "tgn:2363501",
      "tgn:1000001",
      "tgn:7012149",
      "tgn:2002117",
      "tgn:7007827",
      "tgn:7029392"
    ],
    "placetype": [
      "aat:300006191"
    ],
    "id": 2363501,
    "name:xx": "Green Fork Reservoir"
  }
}
