{
  "geometry": {
    "type": "Point",
    "coordinates": [
      -118.9167,
      48.05
    ]
  },
  "type": "Feature",
  "properties": {
    "hierarchy": [
      "tgn:2609902",
      "tgn:1000001",
      "tgn:7012149",
      "tgn:1002742",
      "tgn:7007920",
      "tgn:7029392"
    ],
    "placetype": [
      "aat:300008680"
    ],
    "id": 2609902,
    "name:xx": "Rebecca Lake"
  }
}
