{
  "geometry": {
    "type": "Point",
    "coordinates": [
      -79.5833,
      40.4833
    ]
  },
  "type": "Feature",
  "properties": {
    "hierarchy": [
      "tgn:2590211",
      "tgn:1000001",
      "tgn:7012149",
      "tgn:1003017",
      "tgn:7007710",
      "tgn:7029392"
    ],
    "placetype": [
      "aat:300008347"
    ],
    "id": 2590211,
    "name:xx": "Poke Run"
  }
}
