{
  "geometry": {
    "type": "Point",
    "coordinates": [
      23.2833,
      43.8833
    ]
  },
  "type": "Feature",
  "properties": {
    "hierarchy": [
      "tgn:1050251",
      "tgn:1000003",
      "tgn:1000364",
      "tgn:1000091",
      "tgn:7029392"
    ],
    "placetype": [
      "aat:300008347"
    ],
    "id": 1050251,
    "name:xx": "Rast"
  }
}
