{
  "geometry": {
    "type": "Point",
    "coordinates": [
      -77.4667,
      39.3833
    ]
  },
  "type": "Feature",
  "properties": {
    "hierarchy": [
      "tgn:2047064",
      "tgn:1000001",
      "tgn:7016101",
      "tgn:7012149",
      "tgn:7007516",
      "tgn:7029392"
    ],
    "placetype": [
      "aat:300008347"
    ],
    "id": 2047064,
    "name:xx": "Feagaville"
  }
}
