{
  "type": "FeatureCollection",
  "features": [
    {
      "geometry": {
        "type": "Point",
        "coordinates": [
          -80.4333,
          32.45
        ]
      },
      "type": "Feature",
      "properties": {
        "hierarchy": [
          "tgn:1115040",
          "tgn:1000001",
          "tgn:7012149",
          "tgn:7007712",
          "tgn:7029392"
        ],
        "placetype": [
          "aat:300266558"
        ],
        "id": 1115040,
        "name:xx": "Saint Helena Sound"
      }
    },
    {
      "geometry": {
        "type": "Point",
        "coordinates": [
          -72.35,
          41.0333
        ]
      },
      "type": "Feature",
      "properties": {
        "hierarchy": [
          "tgn:1115041",
          "tgn:1000001",
          "tgn:7012149",
          "tgn:1002924",
          "tgn:7007568",
          "tgn:7029392"
        ],
        "placetype": [
          "aat:300266558"
        ],
        "id": 1115041,
        "name:xx": "Shelter Island Sound"
      }
    },
    {
      "geometry": {
        "type": "Point",
        "coordinates": [
          -6.4167,
          57.9
        ]
      },
      "type": "Feature",
      "properties": {
        "hierarchy": [
          "tgn:1115042",
          "tgn:7002444",
          "tgn:1000003",
          "tgn:7008094",
          "tgn:1007849",
          "tgn:7008591",
          "tgn:7029392"
        ],
        "placetype": [
          "aat:300266558"
        ],
        "id": 1115042,
        "name:xx": "Shiant, Sound of"
      }
    },
    {
      "geometry": {
        "type": "Point",
        "coordinates": [
          -135.4833,
          56.9667
        ]
      },
      "type": "Feature",
      "properties": {
        "hierarchy": [
          "tgn:1115043",
          "tgn:7006450",
          "tgn:1000001",
          "tgn:7012149",
          "tgn:2124002",
          "tgn:7029392"
        ],
        "placetype": [
          "aat:300266558"
        ],
        "id": 1115043,
        "name:xx": "Sitka Sound"
      }
    },
    {
      "geometry": {
        "type": "Point",
        "coordinates": [
          -72,
          -52.5833
        ]
      },
      "type": "Feature",
      "properties": {
        "hierarchy": [
          "tgn:1115045",
          "tgn:1001702",
          "tgn:1000049",
          "tgn:1000002",
          "tgn:7029392"
        ],
        "placetype": [
          "aat:300266558"
        ],
        "id": 1115045,
        "name:xx": "Skyring, Seno"
      }
    },
    {
      "geometry": {
        "type": "Point",
        "coordinates": [
          -5.8167,
          57.1
        ]
      },
      "type": "Feature",
      "properties": {
        "hierarchy": [
          "tgn:1115046",
          "tgn:7002444",
          "tgn:1000003",
          "tgn:7008082",
          "tgn:7008591",
          "tgn:7029392"
        ],
        "placetype": [
          "aat:300266558"
        ],
        "name:en": "Sleat, Sound of",
        "id": 1115046
      }
    },
    {
      "geometry": {
        "type": "Point",
        "coordinates": [
          -127.75,
          51.3
        ]
      },
      "type": "Feature",
      "properties": {
        "hierarchy": [
          "tgn:1115048",
          "tgn:7005735",
          "tgn:7005685",
          "tgn:1000001",
          "tgn:7029392"
        ],
        "placetype": [
          "aat:300266558"
        ],
        "id": 1115048,
        "name:xx": "Smith Sound"
      }
    },
    {
      "geometry": {
        "type": "Point",
        "coordinates": [
          -9.4667,
          53.0333
        ]
      },
      "type": "Feature",
      "properties": {
        "hierarchy": [
          "tgn:1115049",
          "tgn:7003496",
          "tgn:7001201",
          "tgn:1000003",
          "tgn:1000078",
          "tgn:7029392"
        ],
        "placetype": [
          "aat:300266558"
        ],
        "id": 1115049,
        "name:xx": "South Sound"
      }
    }
  ]
}
