{
  "geometry": {
    "type": "Point",
    "coordinates": [
      -115.4667,
      35.0667
    ]
  },
  "type": "Feature",
  "properties": {
    "hierarchy": [
      "tgn:2250895",
      "tgn:1000001",
      "tgn:7012149",
      "tgn:7007157",
      "tgn:1002857",
      "tgn:7029392"
    ],
    "placetype": [
      "aat:300000390"
    ],
    "id": 2250895,
    "name:xx": "Columbia Mine"
  }
}
