{
  "geometry": {
    "type": "Point",
    "coordinates": [
      2.6667,
      45.8667
    ]
  },
  "type": "Feature",
  "properties": {
    "hierarchy": [
      "tgn:1034936",
      "tgn:7002871",
      "tgn:1000003",
      "tgn:1000070",
      "tgn:7029392"
    ],
    "placetype": [
      "aat:300008347"
    ],
    "id": 1034936,
    "name:xx": "Pontaumur"
  }
}
