{
  "geometry": {
    "type": "Point",
    "coordinates": [
      -90.7833,
      34.15
    ]
  },
  "type": "Feature",
  "properties": {
    "hierarchy": [
      "tgn:2454974",
      "tgn:1000001",
      "tgn:2001099",
      "tgn:7012149",
      "tgn:7007522",
      "tgn:7029392"
    ],
    "placetype": [
      "aat:300008680"
    ],
    "id": 2454974,
    "name:xx": "Little Eddy Lake"
  }
}
