{
  "geometry": {
    "type": "Point",
    "coordinates": [
      88.157812,
      26.369966
    ]
  },
  "type": "Feature",
  "properties": {
    "hierarchy": [
      "tgn:7581623",
      "tgn:1000004",
      "tgn:1001842",
      "tgn:7000198",
      "tgn:7029392"
    ],
    "placetype": [
      "aat:300008347"
    ],
    "name:en": "Taiābpur",
    "id": 7581623
  }
}
