{
  "geometry": {
    "type": "Point",
    "coordinates": [
      -119.0833,
      37.3167
    ]
  },
  "type": "Feature",
  "properties": {
    "hierarchy": [
      "tgn:2715013",
      "tgn:1000001",
      "tgn:7012149",
      "tgn:1002392",
      "tgn:7007157",
      "tgn:7029392"
    ],
    "placetype": [
      "aat:300008798"
    ],
    "id": 2715013,
    "name:xx": "Tennessee Point"
  }
}
