{
  "geometry": {
    "type": "Point",
    "coordinates": [
      -57.1667,
      -34.3333
    ]
  },
  "type": "Feature",
  "properties": {
    "hierarchy": [
      "tgn:1110440",
      "tgn:1000574",
      "tgn:1000002",
      "tgn:1000058",
      "tgn:7029392"
    ],
    "placetype": [
      "aat:300008777"
    ],
    "id": 1110440,
    "name:xx": "Cufré, Cuchilla"
  }
}
