{
  "geometry": {
    "type": "Point",
    "coordinates": [
      -120.5167,
      34.8667
    ]
  },
  "type": "Feature",
  "properties": {
    "hierarchy": [
      "tgn:2014251",
      "tgn:1000001",
      "tgn:7012149",
      "tgn:7007157",
      "tgn:1002867",
      "tgn:7029392"
    ],
    "placetype": [
      "aat:300387016"
    ],
    "id": 2014251,
    "name:xx": "Shuman"
  }
}
