{
  "geometry": {
    "type": "Point",
    "coordinates": [
      6.762,
      43.633
    ]
  },
  "type": "Feature",
  "properties": {
    "hierarchy": [
      "tgn:7032149",
      "tgn:1000003",
      "tgn:1000070",
      "tgn:7002895",
      "tgn:7029392"
    ],
    "placetype": [
      "aat:300008347"
    ],
    "id": 7032149,
    "name:xx": "Callian"
  }
}
