{
  "type": "FeatureCollection",
  "features": [
    {
      "geometry": {
        "type": "Point",
        "coordinates": [
          11.766667,
          47.916667
        ]
      },
      "type": "Feature",
      "properties": {
        "hierarchy": [
          "tgn:7100010",
          "tgn:7003669",
          "tgn:1000003",
          "tgn:7000084",
          "tgn:7029392"
        ],
        "placetype": [
          "aat:300008347"
        ],
        "id": 7100010,
        "name:xx": "Sollach"
      }
    },
    {
      "geometry": {
        "type": "Point",
        "coordinates": [
          11.416667,
          49.35
        ]
      },
      "type": "Feature",
      "properties": {
        "hierarchy": [
          "tgn:7100011",
          "tgn:7003669",
          "tgn:1000003",
          "tgn:7000084",
          "tgn:7029392"
        ],
        "placetype": [
          "aat:300008863"
        ],
        "id": 7100011,
        "name:xx": "Sollach"
      }
    },
    {
      "geometry": {
        "type": "Point",
        "coordinates": [
          12.716667,
          48.933333
        ]
      },
      "type": "Feature",
      "properties": {
        "hierarchy": [
          "tgn:7100012",
          "tgn:7003669",
          "tgn:1000003",
          "tgn:7000084",
          "tgn:7029392"
        ],
        "placetype": [
          "aat:300000206"
        ],
        "id": 7100012,
        "name:xx": "Sollach"
      }
    },
    {
      "geometry": {
        "type": "Point",
        "coordinates": [
          12.15,
          47.766667
        ]
      },
      "type": "Feature",
      "properties": {
        "hierarchy": [
          "tgn:7100013",
          "tgn:7003669",
          "tgn:1000003",
          "tgn:7000084",
          "tgn:7029392"
        ],
        "placetype": [
          "aat:300000206"
        ],
        "id": 7100013,
        "name:xx": "Sollach"
      }
    },
    {
      "geometry": {
        "type": "Point",
        "coordinates": [
          13.3,
          48.816667
        ]
      },
      "type": "Feature",
      "properties": {
        "hierarchy": [
          "tgn:7100014",
          "tgn:7003669",
          "tgn:1000003",
          "tgn:7000084",
          "tgn:7029392"
        ],
        "placetype": [
          "aat:300008347"
        ],
        "id": 7100014,
        "name:xx": "Solla"
      }
    },
    {
      "geometry": {
        "type": "Point",
        "coordinates": [
          13.533333,
          48.8
        ]
      },
      "type": "Feature",
      "properties": {
        "hierarchy": [
          "tgn:7100015",
          "tgn:7003669",
          "tgn:1000003",
          "tgn:7000084",
          "tgn:7029392"
        ],
        "placetype": [
          "aat:300008347"
        ],
        "id": 7100015,
        "name:xx": "Solla"
      }
    },
    {
      "geometry": {
        "type": "Point",
        "coordinates": [
          13.65,
          48.766667
        ]
      },
      "type": "Feature",
      "properties": {
        "hierarchy": [
          "tgn:7100016",
          "tgn:7003669",
          "tgn:1000003",
          "tgn:7000084",
          "tgn:7029392"
        ],
        "placetype": [
          "aat:300008347"
        ],
        "id": 7100016,
        "name:xx": "Solla"
      }
    },
    {
      "geometry": {
        "type": "Point",
        "coordinates": [
          13.216667,
          48.666667
        ]
      },
      "type": "Feature",
      "properties": {
        "hierarchy": [
          "tgn:7100017",
          "tgn:7003669",
          "tgn:1000003",
          "tgn:7000084",
          "tgn:7029392"
        ],
        "placetype": [
          "aat:300008347"
        ],
        "id": 7100017,
        "name:xx": "Solla"
      }
    },
    {
      "geometry": {
        "type": "Point",
        "coordinates": [
          13.183333,
          48.683333
        ]
      },
      "type": "Feature",
      "properties": {
        "hierarchy": [
          "tgn:7100018",
          "tgn:7003669",
          "tgn:1000003",
          "tgn:7000084",
          "tgn:7029392"
        ],
        "placetype": [
          "aat:300000206"
        ],
        "id": 7100018,
        "name:xx": "Solla"
      }
    }
  ]
}
