{
  "geometry": {
    "type": "Point",
    "coordinates": [
      -118.7167,
      36.6833
    ]
  },
  "type": "Feature",
  "properties": {
    "hierarchy": [
      "tgn:2653657",
      "tgn:1000001",
      "tgn:7012149",
      "tgn:7007157",
      "tgn:1002956",
      "tgn:7029392"
    ],
    "placetype": [
      "aat:300008680"
    ],
    "id": 2653657,
    "name:xx": "Seville Lake"
  }
}
