{
  "geometry": {
    "type": "Point",
    "coordinates": [
      -71.95,
      44.85
    ]
  },
  "type": "Feature",
  "properties": {
    "hierarchy": [
      "tgn:2729280",
      "tgn:1000001",
      "tgn:1002753",
      "tgn:7012149",
      "tgn:7007828",
      "tgn:7029392"
    ],
    "placetype": [
      "aat:300008798"
    ],
    "id": 2729280,
    "name:xx": "Trip Hill"
  }
}
