{
  "geometry": {
    "type": "Point",
    "coordinates": [
      -110.7167,
      46.9167
    ]
  },
  "type": "Feature",
  "properties": {
    "hierarchy": [
      "tgn:7020406",
      "tgn:1000001",
      "tgn:2001266",
      "tgn:7012149",
      "tgn:7007524",
      "tgn:7029392"
    ],
    "placetype": [
      "aat:300000390"
    ],
    "id": 7020406,
    "name:xx": "Broadwater Mines"
  }
}
