{
  "geometry": {
    "type": "Point",
    "coordinates": [
      78.807439,
      25.226173
    ]
  },
  "type": "Feature",
  "properties": {
    "hierarchy": [
      "tgn:7583412",
      "tgn:1000004",
      "tgn:7000198",
      "tgn:1001894",
      "tgn:7029392"
    ],
    "placetype": [
      "aat:300008347"
    ],
    "name:en": "Chhāpar",
    "id": 7583412
  }
}
