{
  "geometry": {
    "type": "Point",
    "coordinates": [
      72.72306,
      24.60835
    ]
  },
  "type": "Feature",
  "properties": {
    "hierarchy": [
      "tgn:7551979",
      "tgn:1000004",
      "tgn:7000198",
      "tgn:7016788",
      "tgn:7029392"
    ],
    "placetype": [
      "aat:300008347"
    ],
    "name:en": "Delmāra",
    "id": 7551979
  }
}
