{
  "geometry": {
    "type": "Point",
    "coordinates": [
      -113.4667,
      41.8667
    ]
  },
  "type": "Feature",
  "properties": {
    "hierarchy": [
      "tgn:2297621",
      "tgn:1000001",
      "tgn:2002102",
      "tgn:7012149",
      "tgn:7007827",
      "tgn:7029392"
    ],
    "placetype": [
      "aat:300008701"
    ],
    "id": 2297621,
    "name:xx": "Dry Fork Pine Creek"
  }
}
