{
  "geometry": {
    "type": "Point",
    "coordinates": [
      -83.3333,
      34.9833
    ]
  },
  "type": "Feature",
  "properties": {
    "hierarchy": [
      "tgn:2024338",
      "tgn:1000001",
      "tgn:7012149",
      "tgn:2000410",
      "tgn:7007248",
      "tgn:7029392"
    ],
    "placetype": [
      "aat:300008347"
    ],
    "id": 2024338,
    "name:xx": "Sky Valley"
  }
}
