{
  "geometry": {
    "type": "Point",
    "coordinates": [
      79.3366,
      26.1451
    ]
  },
  "type": "Feature",
  "properties": {
    "hierarchy": [
      "tgn:1075536",
      "tgn:1000004",
      "tgn:7000198",
      "tgn:7016722",
      "tgn:7029392"
    ],
    "placetype": [
      "aat:300008347"
    ],
    "name:en": "Jālaun",
    "id": 1075536
  }
}
