{
  "geometry": {
    "type": "Point",
    "coordinates": [
      -8.519,
      41.408
    ]
  },
  "type": "Feature",
  "properties": {
    "hierarchy": [
      "tgn:1049974",
      "tgn:7010776",
      "tgn:1000003",
      "tgn:1000090",
      "tgn:7029392"
    ],
    "placetype": [
      "aat:300008347"
    ],
    "id": 1049974,
    "name:xx": "Vila Nova de Famalicão"
  }
}
