{
  "geometry": {
    "type": "Point",
    "coordinates": [
      33.5667,
      18.9333
    ]
  },
  "type": "Feature",
  "properties": {
    "hierarchy": [
      "tgn:1111417",
      "tgn:1001069",
      "tgn:7001242",
      "tgn:1000201",
      "tgn:7029392"
    ],
    "placetype": [
      "aat:300008773"
    ],
    "id": 1111417,
    "name:xx": "ʻAmūr, Wādī"
  }
}
