{
  "geometry": {
    "type": "Point",
    "coordinates": [
      -117.7167,
      44.7833
    ]
  },
  "type": "Feature",
  "properties": {
    "hierarchy": [
      "tgn:2604942",
      "tgn:7013349",
      "tgn:1000001",
      "tgn:7012149",
      "tgn:7007708",
      "tgn:7029392"
    ],
    "placetype": [
      "aat:300000390"
    ],
    "id": 2604942,
    "name:xx": "Rachel Mine"
  }
}
