{
  "geometry": {
    "type": "Point",
    "coordinates": [
      -106.0833,
      45.6667
    ]
  },
  "type": "Feature",
  "properties": {
    "hierarchy": [
      "tgn:2647200",
      "tgn:1000001",
      "tgn:7012149",
      "tgn:2001297",
      "tgn:7007524",
      "tgn:7029392"
    ],
    "placetype": [
      "aat:300008706"
    ],
    "id": 2647200,
    "name:xx": "Schiller Creek"
  }
}
