{
  "geometry": {
    "type": "Point",
    "coordinates": [
      30.95,
      29.233333
    ]
  },
  "type": "Feature",
  "properties": {
    "hierarchy": [
      "tgn:7540498",
      "tgn:7001242",
      "tgn:7001105",
      "tgn:7016833",
      "tgn:7029392"
    ],
    "placetype": [
      "aat:300008347"
    ],
    "name:en": "Minshāt Kamāl",
    "id": 7540498
  }
}
