{
  "geometry": {
    "type": "Point",
    "coordinates": [
      -2.0833,
      53.7667
    ]
  },
  "type": "Feature",
  "properties": {
    "hierarchy": [
      "tgn:1124616",
      "tgn:1003573",
      "tgn:7002445",
      "tgn:1000003",
      "tgn:7029507",
      "tgn:7008591",
      "tgn:7029392"
    ],
    "placetype": [
      "aat:300008707"
    ],
    "id": 1124616,
    "name:xx": "Heptonstall Moor"
  }
}
