{
  "geometry": {
    "type": "Point",
    "coordinates": [
      -104.8833,
      44.0167
    ]
  },
  "type": "Feature",
  "properties": {
    "hierarchy": [
      "tgn:2287163",
      "tgn:1000001",
      "tgn:7012149",
      "tgn:2002387",
      "tgn:7007923",
      "tgn:7029392"
    ],
    "placetype": [
      "aat:300008761"
    ],
    "id": 2287163,
    "name:xx": "Dickey Draw"
  }
}
