{
  "geometry": {
    "type": "Point",
    "coordinates": [
      -79.6167,
      38.1833
    ]
  },
  "type": "Feature",
  "properties": {
    "hierarchy": [
      "tgn:2208626",
      "tgn:2002143",
      "tgn:1000001",
      "tgn:7012149",
      "tgn:7007919",
      "tgn:7029392"
    ],
    "placetype": [
      "aat:300008746"
    ],
    "id": 2208626,
    "name:xx": "Burns Chesnut Ridge Cave"
  }
}
