{
  "geometry": {
    "type": "Point",
    "coordinates": [
      -88.3333,
      41.9833
    ]
  },
  "type": "Feature",
  "properties": {
    "hierarchy": [
      "tgn:2030832",
      "tgn:1000001",
      "tgn:7012149",
      "tgn:1002531",
      "tgn:7007251",
      "tgn:7029392"
    ],
    "placetype": [
      "aat:300387016"
    ],
    "id": 2030832,
    "name:xx": "Youngsdale"
  }
}
