{
  "geometry": {
    "type": "Point",
    "coordinates": [
      -92.3833,
      37.5833
    ]
  },
  "type": "Feature",
  "properties": {
    "hierarchy": [
      "tgn:2330071",
      "tgn:1000001",
      "tgn:7012149",
      "tgn:2001211",
      "tgn:7007523",
      "tgn:7029392"
    ],
    "placetype": [
      "aat:300008761"
    ],
    "id": 2330071,
    "name:xx": "Flagmire Hollow"
  }
}
