{
  "type": "FeatureCollection",
  "features": [
    {
      "geometry": {
        "type": "Point",
        "coordinates": [
          -73.4167,
          41.7667
        ]
      },
      "type": "Feature",
      "properties": {
        "hierarchy": [
          "tgn:2017224",
          "tgn:1000001",
          "tgn:1002601",
          "tgn:7012149",
          "tgn:7007159",
          "tgn:7029392"
        ],
        "placetype": [
          "aat:300008347"
        ],
        "id": 2017224,
        "name:xx": "North Kent"
      }
    },
    {
      "geometry": {
        "type": "Point",
        "coordinates": [
          -72.3167,
          41.4333
        ]
      },
      "type": "Feature",
      "properties": {
        "hierarchy": [
          "tgn:2017225",
          "tgn:1000001",
          "tgn:1002664",
          "tgn:7012149",
          "tgn:7007159",
          "tgn:7029392"
        ],
        "placetype": [
          "aat:300008347",
          "aat:300387210"
        ],
        "id": 2017225,
        "name:xx": "North Plain"
      }
    },
    {
      "geometry": {
        "type": "Point",
        "coordinates": [
          -71.8667,
          41.4333
        ]
      },
      "type": "Feature",
      "properties": {
        "hierarchy": [
          "tgn:2017227",
          "tgn:1000001",
          "tgn:1002714",
          "tgn:7012149",
          "tgn:7007159",
          "tgn:7029392"
        ],
        "placetype": [
          "aat:300008347"
        ],
        "id": 2017227,
        "name:xx": "North Stonington"
      }
    },
    {
      "geometry": {
        "type": "Point",
        "coordinates": [
          -73.3833,
          41.6167
        ]
      },
      "type": "Feature",
      "properties": {
        "hierarchy": [
          "tgn:2017228",
          "tgn:1000001",
          "tgn:1002601",
          "tgn:7012149",
          "tgn:7007159",
          "tgn:7029392"
        ],
        "placetype": [
          "aat:300008347"
        ],
        "id": 2017228,
        "name:xx": "Northville"
      }
    },
    {
      "geometry": {
        "type": "Point",
        "coordinates": [
          -72.4,
          41.5667
        ]
      },
      "type": "Feature",
      "properties": {
        "hierarchy": [
          "tgn:2017229",
          "tgn:1000001",
          "tgn:1002714",
          "tgn:7012149",
          "tgn:7007159",
          "tgn:7029392"
        ],
        "placetype": [
          "aat:300008347"
        ],
        "id": 2017229,
        "name:xx": "North Westchester"
      }
    }
  ]
}
