{
  "geometry": {
    "type": "Point",
    "coordinates": [
      89.716667,
      26.45
    ]
  },
  "type": "Feature",
  "properties": {
    "hierarchy": [
      "tgn:7557586",
      "tgn:1000004",
      "tgn:7000198",
      "tgn:1001977",
      "tgn:7029392"
    ],
    "placetype": [
      "aat:300008347"
    ],
    "name:en": "Pārokāta",
    "id": 7557586
  }
}
