{
  "geometry": {
    "type": "Point",
    "coordinates": [
      -94.1833,
      31.4667
    ]
  },
  "type": "Feature",
  "properties": {
    "hierarchy": [
      "tgn:2417073",
      "tgn:1000001",
      "tgn:7012149",
      "tgn:2002067",
      "tgn:7007826",
      "tgn:7029392"
    ],
    "placetype": [
      "aat:300008706"
    ],
    "id": 2417073,
    "name:xx": "Jacklot Creek"
  }
}
