{
  "geometry": {
    "type": "Point",
    "coordinates": [
      -99.35,
      29.8167
    ]
  },
  "type": "Feature",
  "properties": {
    "hierarchy": [
      "tgn:2616245",
      "tgn:1000001",
      "tgn:2001938",
      "tgn:7012149",
      "tgn:7007826",
      "tgn:7029392"
    ],
    "placetype": [
      "aat:300008706"
    ],
    "id": 2616245,
    "name:xx": "Rhyme Creek"
  }
}
