{
  "type": "FeatureCollection",
  "features": [
    {
      "geometry": {
        "type": "Point",
        "coordinates": [
          -99.65,
          18.566667
        ]
      },
      "type": "Feature",
      "properties": {
        "hierarchy": [
          "tgn:7351260",
          "tgn:7005585",
          "tgn:1000001",
          "tgn:7005560",
          "tgn:7029392"
        ],
        "placetype": [
          "aat:300008347"
        ],
        "id": 7351260,
        "name:xx": "Cacalotenango"
      }
    },
    {
      "geometry": {
        "type": "Point",
        "coordinates": [
          -107.016667,
          26.166667
        ]
      },
      "type": "Feature",
      "properties": {
        "hierarchy": [
          "tgn:7351261",
          "tgn:7005581",
          "tgn:1000001",
          "tgn:7005560",
          "tgn:7029392"
        ],
        "placetype": [
          "aat:300000241"
        ],
        "id": 7351261,
        "name:xx": "Rancho Cacalote Arriba"
      }
    },
    {
      "geometry": {
        "type": "Point",
        "coordinates": [
          -107,
          26.166667
        ]
      },
      "type": "Feature",
      "properties": {
        "hierarchy": [
          "tgn:7351262",
          "tgn:7005581",
          "tgn:1000001",
          "tgn:7005560",
          "tgn:7029392"
        ],
        "placetype": [
          "aat:300000241"
        ],
        "id": 7351262,
        "name:xx": "Rancho Cacalote Abajo"
      }
    },
    {
      "geometry": {
        "type": "Point",
        "coordinates": [
          -95.933333,
          16.05
        ]
      },
      "type": "Feature",
      "properties": {
        "hierarchy": [
          "tgn:7351263",
          "tgn:1000001",
          "tgn:7005591",
          "tgn:7005560",
          "tgn:7029392"
        ],
        "placetype": [
          "aat:300008795"
        ],
        "id": 7351263,
        "name:xx": "Cacalote, Cerro"
      }
    },
    {
      "geometry": {
        "type": "Point",
        "coordinates": [
          -103.116667,
          23.216667
        ]
      },
      "type": "Feature",
      "properties": {
        "hierarchy": [
          "tgn:7351264",
          "tgn:1000001",
          "tgn:7005601",
          "tgn:7005560",
          "tgn:7029392"
        ],
        "placetype": [
          "aat:300008777"
        ],
        "id": 7351264,
        "name:xx": "Cacalote, Cerro"
      }
    },
    {
      "geometry": {
        "type": "Point",
        "coordinates": [
          -100.783333,
          20.35
        ]
      },
      "type": "Feature",
      "properties": {
        "hierarchy": [
          "tgn:7351265",
          "tgn:7005584",
          "tgn:1000001",
          "tgn:7005560",
          "tgn:7029392"
        ],
        "placetype": [
          "aat:300007783"
        ],
        "id": 7351265,
        "name:xx": "Cacalote"
      }
    },
    {
      "geometry": {
        "type": "Point",
        "coordinates": [
          -106.183333,
          27.433333
        ]
      },
      "type": "Feature",
      "properties": {
        "hierarchy": [
          "tgn:7351266",
          "tgn:7005581",
          "tgn:1000001",
          "tgn:7005560",
          "tgn:7029392"
        ],
        "placetype": [
          "aat:300008347"
        ],
        "id": 7351266,
        "name:xx": "Cacalote"
      }
    },
    {
      "geometry": {
        "type": "Point",
        "coordinates": [
          -103.033333,
          20.45
        ]
      },
      "type": "Feature",
      "properties": {
        "hierarchy": [
          "tgn:7351267",
          "tgn:7005586",
          "tgn:1000001",
          "tgn:7005560",
          "tgn:7029392"
        ],
        "placetype": [
          "aat:300008347"
        ],
        "id": 7351267,
        "name:xx": "Cacalote"
      }
    },
    {
      "geometry": {
        "type": "Point",
        "coordinates": [
          -100.783333,
          20.35
        ]
      },
      "type": "Feature",
      "properties": {
        "hierarchy": [
          "tgn:7351268",
          "tgn:7005584",
          "tgn:1000001",
          "tgn:7005560",
          "tgn:7029392"
        ],
        "placetype": [
          "aat:300008347"
        ],
        "id": 7351268,
        "name:xx": "Cacalote"
      }
    },
    {
      "geometry": {
        "type": "Point",
        "coordinates": [
          -97.05,
          16.333333
        ]
      },
      "type": "Feature",
      "properties": {
        "hierarchy": [
          "tgn:7351269",
          "tgn:1000001",
          "tgn:7005591",
          "tgn:7005560",
          "tgn:7029392"
        ],
        "placetype": [
          "aat:300008347"
        ],
        "id": 7351269,
        "name:xx": "Cacalote"
      }
    }
  ]
}
