{
  "geometry": {
    "type": "Point",
    "coordinates": [
      -104.6833,
      32.45
    ]
  },
  "type": "Feature",
  "properties": {
    "hierarchy": [
      "tgn:2463503",
      "tgn:1000001",
      "tgn:2001436",
      "tgn:7012149",
      "tgn:7007566",
      "tgn:7029392"
    ],
    "placetype": [
      "aat:300006191"
    ],
    "id": 2463503,
    "name:xx": "Loafer Tank"
  }
}
