{
  "type": "FeatureCollection",
  "features": [
    {
      "geometry": {
        "type": "Point",
        "coordinates": [
          -101.35,
          28.416667
        ]
      },
      "type": "Feature",
      "properties": {
        "hierarchy": [
          "tgn:7356510",
          "tgn:1001853",
          "tgn:1000001",
          "tgn:7005560",
          "tgn:7029392"
        ],
        "placetype": [
          "aat:300008347"
        ],
        "id": 7356510,
        "name:xx": "Chilpitín"
      }
    },
    {
      "geometry": {
        "type": "Point",
        "coordinates": [
          -99.2,
          26.366667
        ]
      },
      "type": "Feature",
      "properties": {
        "hierarchy": [
          "tgn:7356511",
          "tgn:1000001",
          "tgn:7005597",
          "tgn:7005560",
          "tgn:7029392"
        ],
        "placetype": [
          "aat:300008347"
        ],
        "id": 7356511,
        "name:xx": "Chilpitín"
      }
    },
    {
      "geometry": {
        "type": "Point",
        "coordinates": [
          -99.6,
          25.9
        ]
      },
      "type": "Feature",
      "properties": {
        "hierarchy": [
          "tgn:7356512",
          "tgn:1000001",
          "tgn:7005589",
          "tgn:7005560",
          "tgn:7029392"
        ],
        "placetype": [
          "aat:300000241"
        ],
        "id": 7356512,
        "name:xx": "Rancho Chilpitenes"
      }
    },
    {
      "geometry": {
        "type": "Point",
        "coordinates": [
          -97.716667,
          21.016667
        ]
      },
      "type": "Feature",
      "properties": {
        "hierarchy": [
          "tgn:7356514",
          "tgn:1000001",
          "tgn:7005599",
          "tgn:7005560",
          "tgn:7029392"
        ],
        "placetype": [
          "aat:300008347"
        ],
        "id": 7356514,
        "name:xx": "Cerro Viejo"
      }
    },
    {
      "geometry": {
        "type": "Point",
        "coordinates": [
          -105.483333,
          23.983333
        ]
      },
      "type": "Feature",
      "properties": {
        "hierarchy": [
          "tgn:7356515",
          "tgn:7005583",
          "tgn:1000001",
          "tgn:7005560",
          "tgn:7029392"
        ],
        "placetype": [
          "aat:300008347"
        ],
        "id": 7356515,
        "name:xx": "Cerro Verde"
      }
    },
    {
      "geometry": {
        "type": "Point",
        "coordinates": [
          -105.983333,
          23.8
        ]
      },
      "type": "Feature",
      "properties": {
        "hierarchy": [
          "tgn:7356516",
          "tgn:1000001",
          "tgn:7005595",
          "tgn:7005560",
          "tgn:7029392"
        ],
        "placetype": [
          "aat:300008347"
        ],
        "id": 7356516,
        "name:xx": "Cerro Verde"
      }
    },
    {
      "geometry": {
        "type": "Point",
        "coordinates": [
          -97.866667,
          20.6
        ]
      },
      "type": "Feature",
      "properties": {
        "hierarchy": [
          "tgn:7356517",
          "tgn:1000001",
          "tgn:7005592",
          "tgn:7005560",
          "tgn:7029392"
        ],
        "placetype": [
          "aat:300008347"
        ],
        "id": 7356517,
        "name:xx": "Cerro Verde"
      }
    },
    {
      "geometry": {
        "type": "Point",
        "coordinates": [
          -97.75,
          20.35
        ]
      },
      "type": "Feature",
      "properties": {
        "hierarchy": [
          "tgn:7356518",
          "tgn:1000001",
          "tgn:7005592",
          "tgn:7005560",
          "tgn:7029392"
        ],
        "placetype": [
          "aat:300008347"
        ],
        "id": 7356518,
        "name:xx": "Cerro Verde"
      }
    },
    {
      "geometry": {
        "type": "Point",
        "coordinates": [
          -116.9,
          32.333333
        ]
      },
      "type": "Feature",
      "properties": {
        "hierarchy": [
          "tgn:7356519",
          "tgn:1001835",
          "tgn:1000001",
          "tgn:7005560",
          "tgn:7029392"
        ],
        "placetype": [
          "aat:300008347"
        ],
        "id": 7356519,
        "name:xx": "Cerro Veladero"
      }
    }
  ]
}
