{
  "geometry": {
    "type": "Point",
    "coordinates": [
      -99.2667,
      27.6833
    ]
  },
  "type": "Feature",
  "properties": {
    "hierarchy": [
      "tgn:2640287",
      "tgn:1000001",
      "tgn:7012149",
      "tgn:2002090",
      "tgn:7007826",
      "tgn:7029392"
    ],
    "placetype": [
      "aat:300008706"
    ],
    "id": 2640287,
    "name:xx": "San Carlos Creek"
  }
}
