{
  "geometry": {
    "type": "Point",
    "coordinates": [
      -105.3833,
      33.6167
    ]
  },
  "type": "Feature",
  "properties": {
    "hierarchy": [
      "tgn:2483252",
      "tgn:1000001",
      "tgn:7012149",
      "tgn:2001442",
      "tgn:7007566",
      "tgn:7029392"
    ],
    "placetype": [
      "aat:300008706"
    ],
    "id": 2483252,
    "name:xx": "Las Tablas Creek"
  }
}
