{
  "geometry": {
    "type": "Point",
    "coordinates": [
      -81.5667,
      26.6667
    ]
  },
  "type": "Feature",
  "properties": {
    "hierarchy": [
      "tgn:2437650",
      "tgn:1000001",
      "tgn:7012149",
      "tgn:1002582",
      "tgn:7007240",
      "tgn:7029392"
    ],
    "placetype": [
      "aat:300006075"
    ],
    "id": 2437650,
    "name:xx": "King Canal"
  }
}
