{
  "type": "FeatureCollection",
  "features": [
    {
      "geometry": {
        "type": "Point",
        "coordinates": [
          26.6,
          41.35
        ]
      },
      "type": "Feature",
      "properties": {
        "hierarchy": [
          "tgn:7222100",
          "tgn:7011163",
          "tgn:7002674",
          "tgn:1000003",
          "tgn:1000074",
          "tgn:7029392"
        ],
        "placetype": [
          "aat:300008347"
        ],
        "id": 7222100,
        "name:xx": "Mikrokhórion"
      }
    },
    {
      "geometry": {
        "type": "Point",
        "coordinates": [
          24.45,
          41.316667
        ]
      },
      "type": "Feature",
      "properties": {
        "hierarchy": [
          "tgn:7222101",
          "tgn:7011170",
          "tgn:7002715",
          "tgn:1000003",
          "tgn:1000074",
          "tgn:7029392"
        ],
        "placetype": [
          "aat:300008347"
        ],
        "id": 7222101,
        "name:xx": "Mikrokhórion"
      }
    },
    {
      "geometry": {
        "type": "Point",
        "coordinates": [
          24.183333,
          41.1
        ]
      },
      "type": "Feature",
      "properties": {
        "hierarchy": [
          "tgn:7222102",
          "tgn:7011170",
          "tgn:7002715",
          "tgn:1000003",
          "tgn:1000074",
          "tgn:7029392"
        ],
        "placetype": [
          "aat:300008347"
        ],
        "id": 7222102,
        "name:xx": "Mikrokhórion"
      }
    },
    {
      "geometry": {
        "type": "Point",
        "coordinates": [
          24.8,
          40.966667
        ]
      },
      "type": "Feature",
      "properties": {
        "hierarchy": [
          "tgn:7222103",
          "tgn:7011170",
          "tgn:7002715",
          "tgn:1000003",
          "tgn:1000074",
          "tgn:7029392"
        ],
        "placetype": [
          "aat:300008347"
        ],
        "id": 7222103,
        "name:xx": "Mikrokhórion"
      }
    },
    {
      "geometry": {
        "type": "Point",
        "coordinates": [
          20.615278,
          39.576111
        ]
      },
      "type": "Feature",
      "properties": {
        "hierarchy": [
          "tgn:7222104",
          "tgn:7002707",
          "tgn:7002705",
          "tgn:1000003",
          "tgn:1000074",
          "tgn:7029392"
        ],
        "placetype": [
          "aat:300008347"
        ],
        "id": 7222104,
        "name:xx": "Mikrochórion"
      }
    },
    {
      "geometry": {
        "type": "Point",
        "coordinates": [
          23.9,
          38.233333
        ]
      },
      "type": "Feature",
      "properties": {
        "hierarchy": [
          "tgn:7222105",
          "tgn:7002681",
          "tgn:7001395",
          "tgn:1000003",
          "tgn:1000074",
          "tgn:7029392"
        ],
        "placetype": [
          "aat:300008347"
        ],
        "id": 7222105,
        "name:xx": "Mikrokhórion"
      }
    },
    {
      "geometry": {
        "type": "Point",
        "coordinates": [
          21.933333,
          37.55
        ]
      },
      "type": "Feature",
      "properties": {
        "hierarchy": [
          "tgn:7222106",
          "tgn:7011369",
          "tgn:7017076",
          "tgn:1000003",
          "tgn:1000074",
          "tgn:7029392"
        ],
        "placetype": [
          "aat:300008347"
        ],
        "id": 7222106,
        "name:xx": "Mikrokhórion"
      }
    },
    {
      "geometry": {
        "type": "Point",
        "coordinates": [
          21.5,
          40.266667
        ]
      },
      "type": "Feature",
      "properties": {
        "hierarchy": [
          "tgn:7222107",
          "tgn:7002721",
          "tgn:7002715",
          "tgn:1000003",
          "tgn:1000074",
          "tgn:7029392"
        ],
        "placetype": [
          "aat:300008347"
        ],
        "id": 7222107,
        "name:xx": "Mikrókastron"
      }
    },
    {
      "geometry": {
        "type": "Point",
        "coordinates": [
          24,
          41.133333
        ]
      },
      "type": "Feature",
      "properties": {
        "hierarchy": [
          "tgn:7222108",
          "tgn:7011170",
          "tgn:7002715",
          "tgn:1000003",
          "tgn:1000074",
          "tgn:7029392"
        ],
        "placetype": [
          "aat:300008347"
        ],
        "id": 7222108,
        "name:xx": "Mikrókambos"
      }
    },
    {
      "geometry": {
        "type": "Point",
        "coordinates": [
          22.769722,
          40.838611
        ]
      },
      "type": "Feature",
      "properties": {
        "hierarchy": [
          "tgn:7222109",
          "tgn:7002725",
          "tgn:7002715",
          "tgn:1000003",
          "tgn:1000074",
          "tgn:7029392"
        ],
        "placetype": [
          "aat:300008347"
        ],
        "id": 7222109,
        "name:xx": "Mikrókampos"
      }
    }
  ]
}
