{
  "geometry": {
    "type": "Point",
    "coordinates": [
      -106.6333,
      44.4167
    ]
  },
  "type": "Feature",
  "properties": {
    "hierarchy": [
      "tgn:2371879",
      "tgn:1000001",
      "tgn:7012149",
      "tgn:2002374",
      "tgn:7007923",
      "tgn:7029392"
    ],
    "placetype": [
      "aat:300008761"
    ],
    "id": 2371879,
    "name:xx": "Haley Draw"
  }
}
