{
  "geometry": {
    "type": "Point",
    "coordinates": [
      119.35,
      30.8167
    ]
  },
  "type": "Feature",
  "properties": {
    "hierarchy": [
      "tgn:1067146",
      "tgn:7002075",
      "tgn:1000004",
      "tgn:1000111",
      "tgn:7029392"
    ],
    "placetype": [
      "aat:300008347"
    ],
    "id": 1067146,
    "name:xx": "Chayue"
  }
}
