{
  "geometry": {
    "type": "Point",
    "coordinates": [
      38.4667,
      48.05
    ]
  },
  "type": "Feature",
  "properties": {
    "hierarchy": [
      "tgn:1051512",
      "tgn:7012076",
      "tgn:1000003",
      "tgn:7006660",
      "tgn:7029392"
    ],
    "placetype": [
      "aat:300008347"
    ],
    "id": 1051512,
    "name:xx": "Shakhtars'k"
  }
}
