{
  "geometry": {
    "type": "Point",
    "coordinates": [
      115.2167,
      24.9167
    ]
  },
  "type": "Feature",
  "properties": {
    "hierarchy": [
      "tgn:1068751",
      "tgn:1000004",
      "tgn:7002082",
      "tgn:1000111",
      "tgn:7029392"
    ],
    "placetype": [
      "aat:300008347"
    ],
    "id": 1068751,
    "name:xx": "Hezixu"
  }
}
