{
  "geometry": {
    "type": "Point",
    "coordinates": [
      -91.9833,
      39.0833
    ]
  },
  "type": "Feature",
  "properties": {
    "hierarchy": [
      "tgn:2303062",
      "tgn:1002158",
      "tgn:1000001",
      "tgn:7012149",
      "tgn:7007523",
      "tgn:7029392"
    ],
    "placetype": [
      "aat:300006191"
    ],
    "id": 2303062,
    "name:xx": "E B Feutz Lake"
  }
}
