{
  "geometry": {
    "type": "Point",
    "coordinates": [
      -79.3667,
      35.7833
    ]
  },
  "type": "Feature",
  "properties": {
    "hierarchy": [
      "tgn:2715545",
      "tgn:1000001",
      "tgn:2001480",
      "tgn:7012149",
      "tgn:7007709",
      "tgn:7029392"
    ],
    "placetype": [
      "aat:300008706"
    ],
    "id": 2715545,
    "name:xx": "Terrells Creek"
  }
}
