{
  "geometry": {
    "type": "Point",
    "coordinates": [
      -74.2833,
      40.8167
    ]
  },
  "type": "Feature",
  "properties": {
    "hierarchy": [
      "tgn:2619047",
      "tgn:1000001",
      "tgn:1002360",
      "tgn:7012149",
      "tgn:7007565",
      "tgn:7029392"
    ],
    "placetype": [
      "aat:300008798"
    ],
    "id": 2619047,
    "name:xx": "Riker Hill"
  }
}
