{
  "geometry": {
    "type": "Point",
    "coordinates": [
      44.4333,
      38.45
    ]
  },
  "type": "Feature",
  "properties": {
    "hierarchy": [
      "tgn:1079251",
      "tgn:1001048",
      "tgn:1000004",
      "tgn:7000231",
      "tgn:7029392"
    ],
    "placetype": [
      "aat:300008347"
    ],
    "id": 1079251,
    "name:xx": "Qoṭūr"
  }
}
