{
  "geometry": {
    "type": "Point",
    "coordinates": [
      -95.0667,
      43.5333
    ]
  },
  "type": "Feature",
  "properties": {
    "hierarchy": [
      "tgn:2232261",
      "tgn:1000001",
      "tgn:7012149",
      "tgn:2001030",
      "tgn:7007521",
      "tgn:7029392"
    ],
    "placetype": [
      "aat:300008680"
    ],
    "id": 2232261,
    "name:xx": "Chandler Lake"
  }
}
