{
  "geometry": {
    "type": "Point",
    "coordinates": [
      -121.1833,
      48.1667
    ]
  },
  "type": "Feature",
  "properties": {
    "hierarchy": [
      "tgn:2448901",
      "tgn:1000001",
      "tgn:7012149",
      "tgn:1002899",
      "tgn:7007920",
      "tgn:7029392"
    ],
    "placetype": [
      "aat:300008706"
    ],
    "id": 2448901,
    "name:xx": "Lime Creek"
  }
}
