{
  "type": "FeatureCollection",
  "features": [
    {
      "geometry": {
        "type": "Point",
        "coordinates": [
          -82.2167,
          36.9333
        ]
      },
      "type": "Feature",
      "properties": {
        "hierarchy": [
          "tgn:2298510",
          "tgn:1000001",
          "tgn:7012149",
          "tgn:2002188",
          "tgn:7007919",
          "tgn:7029392"
        ],
        "placetype": [
          "aat:300008699"
        ],
        "id": 2298510,
        "name:xx": "Dry Run"
      }
    },
    {
      "geometry": {
        "type": "Point",
        "coordinates": [
          -79.7167,
          37.65
        ]
      },
      "type": "Feature",
      "properties": {
        "hierarchy": [
          "tgn:2298511",
          "tgn:1000001",
          "tgn:2002146",
          "tgn:7012149",
          "tgn:7007919",
          "tgn:7029392"
        ],
        "placetype": [
          "aat:300008699"
        ],
        "id": 2298511,
        "name:xx": "Dry Run"
      }
    },
    {
      "geometry": {
        "type": "Point",
        "coordinates": [
          -79.8167,
          37.8333
        ]
      },
      "type": "Feature",
      "properties": {
        "hierarchy": [
          "tgn:2298512",
          "tgn:2002138",
          "tgn:1000001",
          "tgn:7012149",
          "tgn:7007919",
          "tgn:7029392"
        ],
        "placetype": [
          "aat:300008699"
        ],
        "id": 2298512,
        "name:xx": "Dry Run"
      }
    },
    {
      "geometry": {
        "type": "Point",
        "coordinates": [
          -79.75,
          37.9167
        ]
      },
      "type": "Feature",
      "properties": {
        "hierarchy": [
          "tgn:2298513",
          "tgn:2002143",
          "tgn:1000001",
          "tgn:7012149",
          "tgn:7007919",
          "tgn:7029392"
        ],
        "placetype": [
          "aat:300008699"
        ],
        "id": 2298513,
        "name:xx": "Dry Run"
      }
    },
    {
      "geometry": {
        "type": "Point",
        "coordinates": [
          -77.9667,
          38.4333
        ]
      },
      "type": "Feature",
      "properties": {
        "hierarchy": [
          "tgn:2298514",
          "tgn:1000001",
          "tgn:7012149",
          "tgn:2002155",
          "tgn:7007919",
          "tgn:7029392"
        ],
        "placetype": [
          "aat:300008699"
        ],
        "id": 2298514,
        "name:xx": "Dry Run"
      }
    },
    {
      "geometry": {
        "type": "Point",
        "coordinates": [
          -78.3167,
          38.75
        ]
      },
      "type": "Feature",
      "properties": {
        "hierarchy": [
          "tgn:2298515",
          "tgn:1000001",
          "tgn:7012149",
          "tgn:2002178",
          "tgn:7007919",
          "tgn:7029392"
        ],
        "placetype": [
          "aat:300008699"
        ],
        "id": 2298515,
        "name:xx": "Dry Run"
      }
    },
    {
      "geometry": {
        "type": "Point",
        "coordinates": [
          -78.4167,
          38.85
        ]
      },
      "type": "Feature",
      "properties": {
        "hierarchy": [
          "tgn:2298516",
          "tgn:1000001",
          "tgn:7012149",
          "tgn:2002190",
          "tgn:7007919",
          "tgn:7029392"
        ],
        "placetype": [
          "aat:300008699"
        ],
        "id": 2298516,
        "name:xx": "Dry Run"
      }
    },
    {
      "geometry": {
        "type": "Point",
        "coordinates": [
          -78.0333,
          38.9667
        ]
      },
      "type": "Feature",
      "properties": {
        "hierarchy": [
          "tgn:2298517",
          "tgn:1000001",
          "tgn:7012149",
          "tgn:2002193",
          "tgn:7007919",
          "tgn:7029392"
        ],
        "placetype": [
          "aat:300008699"
        ],
        "id": 2298517,
        "name:xx": "Dry Run"
      }
    },
    {
      "geometry": {
        "type": "Point",
        "coordinates": [
          -80.35,
          37.3
        ]
      },
      "type": "Feature",
      "properties": {
        "hierarchy": [
          "tgn:2298518",
          "tgn:1000001",
          "tgn:7012149",
          "tgn:2002174",
          "tgn:7007919",
          "tgn:7029392"
        ],
        "placetype": [
          "aat:300008699"
        ],
        "id": 2298518,
        "name:xx": "Dry Run"
      }
    },
    {
      "geometry": {
        "type": "Point",
        "coordinates": [
          -78.5,
          38.4
        ]
      },
      "type": "Feature",
      "properties": {
        "hierarchy": [
          "tgn:2298519",
          "tgn:1000001",
          "tgn:7012149",
          "tgn:2002187",
          "tgn:7007919",
          "tgn:7029392"
        ],
        "placetype": [
          "aat:300008699"
        ],
        "id": 2298519,
        "name:xx": "Dry Run"
      }
    }
  ]
}
