{
  "geometry": {
    "type": "Point",
    "coordinates": [
      6.5167,
      46.6667
    ]
  },
  "type": "Feature",
  "properties": {
    "hierarchy": [
      "tgn:7007392",
      "tgn:1000003",
      "tgn:7003763",
      "tgn:7011731",
      "tgn:7029392"
    ],
    "placetype": [
      "aat:300008347"
    ],
    "id": 7007392,
    "name:xx": "La Sarraz"
  }
}
