{
  "geometry": {
    "type": "Point",
    "coordinates": [
      -80.2167,
      33.0167
    ]
  },
  "type": "Feature",
  "properties": {
    "hierarchy": [
      "tgn:2573495",
      "tgn:1000001",
      "tgn:2001742",
      "tgn:7012149",
      "tgn:7007712",
      "tgn:7029392"
    ],
    "placetype": [
      "aat:300008347"
    ],
    "id": 2573495,
    "name:xx": "Pecan Grove"
  }
}
