{
  "geometry": {
    "type": "Point",
    "coordinates": [
      75.25,
      20.383333
    ]
  },
  "type": "Feature",
  "properties": {
    "hierarchy": [
      "tgn:7554441",
      "tgn:1000004",
      "tgn:7000198",
      "tgn:1001895",
      "tgn:7029392"
    ],
    "placetype": [
      "aat:300008347"
    ],
    "name:en": "Nāgāpur",
    "id": 7554441
  }
}
