{
  "geometry": {
    "type": "Point",
    "coordinates": [
      -77.0833,
      41.5167
    ]
  },
  "type": "Feature",
  "properties": {
    "hierarchy": [
      "tgn:2621334",
      "tgn:1000001",
      "tgn:7012149",
      "tgn:7007710",
      "tgn:7029392"
    ],
    "placetype": [
      "aat:300008699"
    ],
    "id": 2621334,
    "name:xx": "Roaring Branch"
  }
}
