{
  "geometry": {
    "type": "Point",
    "coordinates": [
      -108.65,
      33.2833
    ]
  },
  "type": "Feature",
  "properties": {
    "hierarchy": [
      "tgn:2167964",
      "tgn:1000001",
      "tgn:7012149",
      "tgn:7007566",
      "tgn:7029392"
    ],
    "placetype": [
      "aat:300008706"
    ],
    "id": 2167964,
    "name:xx": "Big Dry Creek"
  }
}
