{
  "geometry": {
    "type": "Point",
    "coordinates": [
      85.58053,
      20.052811
    ]
  },
  "type": "Feature",
  "properties": {
    "hierarchy": [
      "tgn:7579002",
      "tgn:1000004",
      "tgn:7000198",
      "tgn:7016694",
      "tgn:7029392"
    ],
    "placetype": [
      "aat:300007783"
    ],
    "name:en": "Tāpang",
    "id": 7579002
  }
}
