{
  "geometry": {
    "type": "Point",
    "coordinates": [
      -82.7667,
      27.9667
    ]
  },
  "type": "Feature",
  "properties": {
    "hierarchy": [
      "tgn:2392681",
      "tgn:1000001",
      "tgn:7012149",
      "tgn:1002790",
      "tgn:7007240",
      "tgn:7029392"
    ],
    "placetype": [
      "aat:300008680"
    ],
    "id": 2392681,
    "name:xx": "Hobart Lake"
  }
}
