{
  "geometry": {
    "type": "Point",
    "coordinates": [
      -57.3333,
      -37.5833
    ]
  },
  "type": "Feature",
  "properties": {
    "hierarchy": [
      "tgn:1135878",
      "tgn:1001160",
      "tgn:7006477",
      "tgn:1000002",
      "tgn:7029392"
    ],
    "placetype": [
      "aat:300006075"
    ],
    "id": 1135878,
    "name:xx": "Cinco, Canal Numero"
  }
}
