{
  "geometry": {
    "type": "Point",
    "coordinates": [
      -98.25,
      33.55
    ]
  },
  "type": "Feature",
  "properties": {
    "hierarchy": [
      "tgn:2281817",
      "tgn:1000001",
      "tgn:7012149",
      "tgn:2001956",
      "tgn:7007826",
      "tgn:7029392"
    ],
    "placetype": [
      "aat:300008706"
    ],
    "id": 2281817,
    "name:xx": "Deer Creek"
  }
}
