{
  "geometry": {
    "type": "Point",
    "coordinates": [
      -90.3833,
      37.6167
    ]
  },
  "type": "Feature",
  "properties": {
    "hierarchy": [
      "tgn:2435635",
      "tgn:1000001",
      "tgn:7012149",
      "tgn:2001217",
      "tgn:7007523",
      "tgn:7029392"
    ],
    "placetype": [
      "aat:300008706"
    ],
    "id": 2435635,
    "name:xx": "Kessler Creek"
  }
}
