{
  "geometry": {
    "type": "Point",
    "coordinates": [
      12.4167,
      46.4167
    ]
  },
  "type": "Feature",
  "properties": {
    "hierarchy": [
      "tgn:1111648",
      "tgn:7003029",
      "tgn:1000003",
      "tgn:1000062",
      "tgn:7029392"
    ],
    "placetype": [
      "aat:300008761"
    ],
    "id": 1111648,
    "name:xx": "Defereggen"
  }
}
