{
  "geometry": {
    "type": "Point",
    "coordinates": [
      18.0667,
      45.4833
    ]
  },
  "type": "Feature",
  "properties": {
    "hierarchy": [
      "tgn:1065138",
      "tgn:7017302",
      "tgn:1000003",
      "tgn:7006663",
      "tgn:7029392"
    ],
    "placetype": [
      "aat:300008347"
    ],
    "id": 1065138,
    "name:xx": "Našice"
  }
}
