{
  "geometry": {
    "type": "Point",
    "coordinates": [
      31.376866,
      27.01736
    ]
  },
  "type": "Feature",
  "properties": {
    "hierarchy": [
      "tgn:7530731",
      "tgn:7001242",
      "tgn:7016833",
      "tgn:1001114",
      "tgn:7029392"
    ],
    "placetype": [
      "aat:300008347"
    ],
    "name:en": "Minshāt Hammām",
    "id": 7530731
  }
}
