{
  "geometry": {
    "type": "Point",
    "coordinates": [
      71.5833,
      32.8667
    ]
  },
  "type": "Feature",
  "properties": {
    "hierarchy": [
      "tgn:1083408",
      "tgn:1000004",
      "tgn:1001490",
      "tgn:1000133",
      "tgn:7029392"
    ],
    "placetype": [
      "aat:300008347"
    ],
    "id": 1083408,
    "name:xx": "Daud Khel"
  }
}
