{
  "geometry": {
    "type": "Point",
    "coordinates": [
      11.6833,
      52.2667
    ]
  },
  "type": "Feature",
  "properties": {
    "hierarchy": [
      "tgn:7012991",
      "tgn:1000003",
      "tgn:7000084",
      "tgn:7029392"
    ],
    "placetype": [
      "aat:300006075"
    ],
    "id": 7012991,
    "name:xx": "Mittellandkanal"
  }
}
