{
  "geometry": {
    "type": "Point",
    "coordinates": [
      -58.6833,
      -34.55
    ]
  },
  "type": "Feature",
  "properties": {
    "hierarchy": [
      "tgn:1136424",
      "tgn:1001160",
      "tgn:7006477",
      "tgn:1000002",
      "tgn:7029392"
    ],
    "placetype": [
      "aat:300008347"
    ],
    "id": 1136424,
    "name:xx": "Bella Vista"
  }
}
