{
  "geometry": {
    "type": "Point",
    "coordinates": [
      -94.05,
      33.45
    ]
  },
  "type": "Feature",
  "properties": {
    "hierarchy": [
      "tgn:2706362",
      "tgn:1000001",
      "tgn:2001944",
      "tgn:7012149",
      "tgn:7007826",
      "tgn:7029392"
    ],
    "placetype": [
      "aat:300008706"
    ],
    "id": 2706362,
    "name:xx": "Swampoodle Creek"
  }
}
