{
  "geometry": {
    "type": "Point",
    "coordinates": [
      -73.8333,
      -13.8667
    ]
  },
  "type": "Feature",
  "properties": {
    "hierarchy": [
      "tgn:1024715",
      "tgn:1000518",
      "tgn:1000002",
      "tgn:1000056",
      "tgn:7029392"
    ],
    "placetype": [
      "aat:300008347"
    ],
    "id": 1024715,
    "name:xx": "Querobamba"
  }
}
