{
  "type": "FeatureCollection",
  "features": [
    {
      "geometry": {
        "type": "Point",
        "coordinates": [
          -78.7333,
          37.8167
        ]
      },
      "type": "Feature",
      "properties": {
        "hierarchy": [
          "tgn:2111680",
          "tgn:1000001",
          "tgn:7012149",
          "tgn:2002175",
          "tgn:7007919",
          "tgn:7029392"
        ],
        "placetype": [
          "aat:300008347"
        ],
        "id": 2111680,
        "name:xx": "Faber"
      }
    },
    {
      "geometry": {
        "type": "Point",
        "coordinates": [
          -80.3167,
          37.1833
        ]
      },
      "type": "Feature",
      "properties": {
        "hierarchy": [
          "tgn:2111681",
          "tgn:1000001",
          "tgn:7012149",
          "tgn:2002174",
          "tgn:7007919",
          "tgn:7029392"
        ],
        "placetype": [
          "aat:300008347",
          "aat:300387210"
        ],
        "id": 2111681,
        "name:xx": "Fagg"
      }
    }
  ]
}
