{
  "geometry": {
    "type": "Point",
    "coordinates": [
      -96.9333,
      31.2667
    ]
  },
  "type": "Feature",
  "properties": {
    "hierarchy": [
      "tgn:1002367",
      "tgn:1000001",
      "tgn:7012149",
      "tgn:7007826",
      "tgn:7029392"
    ],
    "placetype": [
      "aat:300387145",
      "aat:300000771"
    ],
    "id": 1002367,
    "name:xx": "Falls"
  }
}
