{
  "geometry": {
    "type": "Point",
    "coordinates": [
      -88.9167,
      36.9167
    ]
  },
  "type": "Feature",
  "properties": {
    "hierarchy": [
      "tgn:2636997",
      "tgn:1000001",
      "tgn:2000778",
      "tgn:7012149",
      "tgn:7007255",
      "tgn:7029392"
    ],
    "placetype": [
      "aat:300008905"
    ],
    "id": 2636997,
    "name:xx": "Saint Arbor Slough"
  }
}
