{
  "geometry": {
    "type": "Point",
    "coordinates": [
      -88.3833,
      32.8333
    ]
  },
  "type": "Feature",
  "properties": {
    "hierarchy": [
      "tgn:2721113",
      "tgn:1000001",
      "tgn:7012149",
      "tgn:7029392"
    ],
    "placetype": [
      "aat:300008706"
    ],
    "id": 2721113,
    "name:xx": "Tifallili Creek"
  }
}
