{
  "geometry": {
    "type": "Point",
    "coordinates": [
      -101.1167,
      47.35
    ]
  },
  "type": "Feature",
  "properties": {
    "hierarchy": [
      "tgn:2245933",
      "tgn:1000001",
      "tgn:2001584",
      "tgn:7012149",
      "tgn:7007705",
      "tgn:7029392"
    ],
    "placetype": [
      "aat:300008699"
    ],
    "id": 2245933,
    "name:xx": "Coal Lake Coulee"
  }
}
