{
  "geometry": {
    "type": "Point",
    "coordinates": [
      -87.9167,
      46.8333
    ]
  },
  "type": "Feature",
  "properties": {
    "hierarchy": [
      "tgn:1110488",
      "tgn:1000001",
      "tgn:7012149",
      "tgn:2000975",
      "tgn:7007520",
      "tgn:7029392"
    ],
    "placetype": [
      "aat:300008777"
    ],
    "id": 1110488,
    "name:xx": "Huron Mountains"
  }
}
