{
  "type": "FeatureCollection",
  "features": [
    {
      "geometry": {
        "type": "Point",
        "coordinates": [
          14.033333,
          53.5
        ]
      },
      "type": "Feature",
      "properties": {
        "hierarchy": [
          "tgn:7118310",
          "tgn:1000003",
          "tgn:7000094",
          "tgn:7000084",
          "tgn:7029392"
        ],
        "placetype": [
          "aat:300000206"
        ],
        "id": 7118310,
        "name:xx": "Papenbeck"
      }
    },
    {
      "geometry": {
        "type": "Point",
        "coordinates": [
          9.6,
          54.116667
        ]
      },
      "type": "Feature",
      "properties": {
        "hierarchy": [
          "tgn:7118311",
          "tgn:1000003",
          "tgn:7003688",
          "tgn:7000084",
          "tgn:7029392"
        ],
        "placetype": [
          "aat:300008699"
        ],
        "id": 7118311,
        "name:xx": "Papenau"
      }
    },
    {
      "geometry": {
        "type": "Point",
        "coordinates": [
          9.633333,
          54.116667
        ]
      },
      "type": "Feature",
      "properties": {
        "hierarchy": [
          "tgn:7118312",
          "tgn:1000003",
          "tgn:7003688",
          "tgn:7000084",
          "tgn:7029392"
        ],
        "placetype": [
          "aat:300000206"
        ],
        "id": 7118312,
        "name:xx": "Papenau"
      }
    },
    {
      "geometry": {
        "type": "Point",
        "coordinates": [
          10.433333,
          53.3
        ]
      },
      "type": "Feature",
      "properties": {
        "hierarchy": [
          "tgn:7118313",
          "tgn:1000003",
          "tgn:7003676",
          "tgn:7000084",
          "tgn:7029392"
        ],
        "placetype": [
          "aat:300008777"
        ],
        "id": 7118313,
        "name:xx": "Papageien-Berg"
      }
    },
    {
      "geometry": {
        "type": "Point",
        "coordinates": [
          7.3,
          50.016667
        ]
      },
      "type": "Feature",
      "properties": {
        "hierarchy": [
          "tgn:7118314",
          "tgn:1000003",
          "tgn:7003682",
          "tgn:7000084",
          "tgn:7029392"
        ],
        "placetype": [
          "aat:300008347"
        ],
        "id": 7118314,
        "name:xx": "Panzweiler"
      }
    },
    {
      "geometry": {
        "type": "Point",
        "coordinates": [
          7.483333,
          49.9
        ]
      },
      "type": "Feature",
      "properties": {
        "hierarchy": [
          "tgn:7118315",
          "tgn:1000003",
          "tgn:7003682",
          "tgn:7000084",
          "tgn:7029392"
        ],
        "placetype": [
          "aat:300008347"
        ],
        "id": 7118315,
        "name:xx": "Panzweiler"
      }
    },
    {
      "geometry": {
        "type": "Point",
        "coordinates": [
          11.666667,
          54
        ]
      },
      "type": "Feature",
      "properties": {
        "hierarchy": [
          "tgn:7118316",
          "tgn:1000003",
          "tgn:7000094",
          "tgn:7000084",
          "tgn:7029392"
        ],
        "placetype": [
          "aat:300008347"
        ],
        "id": 7118316,
        "name:xx": "Panzow"
      }
    },
    {
      "geometry": {
        "type": "Point",
        "coordinates": [
          12.566667,
          48.433333
        ]
      },
      "type": "Feature",
      "properties": {
        "hierarchy": [
          "tgn:7118317",
          "tgn:7003669",
          "tgn:1000003",
          "tgn:7000084",
          "tgn:7029392"
        ],
        "placetype": [
          "aat:300008347"
        ],
        "id": 7118317,
        "name:xx": "Panzing"
      }
    },
    {
      "geometry": {
        "type": "Point",
        "coordinates": [
          12.383333,
          49.966667
        ]
      },
      "type": "Feature",
      "properties": {
        "hierarchy": [
          "tgn:7118318",
          "tgn:7003669",
          "tgn:1000003",
          "tgn:7000084",
          "tgn:7029392"
        ],
        "placetype": [
          "aat:300000206"
        ],
        "id": 7118318,
        "name:xx": "Panzen"
      }
    },
    {
      "geometry": {
        "type": "Point",
        "coordinates": [
          13.566667,
          54.383333
        ]
      },
      "type": "Feature",
      "properties": {
        "hierarchy": [
          "tgn:7118319",
          "tgn:1000003",
          "tgn:7000094",
          "tgn:7000084",
          "tgn:7029392"
        ],
        "placetype": [
          "aat:300008347"
        ],
        "id": 7118319,
        "name:xx": "Pantow"
      }
    }
  ]
}
