{
  "type": "FeatureCollection",
  "features": [
    {
      "geometry": {
        "type": "Point",
        "coordinates": [
          6.966667,
          52.7
        ]
      },
      "type": "Feature",
      "properties": {
        "hierarchy": [
          "tgn:7270660",
          "tgn:7003614",
          "tgn:1000003",
          "tgn:7016845",
          "tgn:7029392"
        ],
        "placetype": [
          "aat:300008347"
        ],
        "name:nl": "Schutwijk",
        "id": 7270660
      }
    },
    {
      "geometry": {
        "type": "Point",
        "coordinates": [
          5.983333,
          50.95
        ]
      },
      "type": "Feature",
      "properties": {
        "hierarchy": [
          "tgn:7270661",
          "tgn:1000003",
          "tgn:7003622",
          "tgn:7016845",
          "tgn:7029392"
        ],
        "placetype": [
          "aat:300000745"
        ],
        "name:nl": "Schuttersveld",
        "id": 7270661
      }
    },
    {
      "geometry": {
        "type": "Point",
        "coordinates": [
          5.983333,
          50.95
        ]
      },
      "type": "Feature",
      "properties": {
        "hierarchy": [
          "tgn:7270662",
          "tgn:1000003",
          "tgn:7003622",
          "tgn:7016845",
          "tgn:7029392"
        ],
        "placetype": [
          "aat:300008187"
        ],
        "name:nl": "Schutterspark",
        "id": 7270662
      }
    },
    {
      "geometry": {
        "type": "Point",
        "coordinates": [
          5.4,
          52.133333
        ]
      },
      "type": "Feature",
      "properties": {
        "hierarchy": [
          "tgn:7270663",
          "tgn:1000003",
          "tgn:7003627",
          "tgn:7016845",
          "tgn:7029392"
        ],
        "placetype": [
          "aat:300008347"
        ],
        "name:nl": "Schutterhoef",
        "id": 7270663
      }
    },
    {
      "geometry": {
        "type": "Point",
        "coordinates": [
          3.666667,
          51.566667
        ]
      },
      "type": "Feature",
      "properties": {
        "hierarchy": [
          "tgn:7270664",
          "tgn:1000003",
          "tgn:7003635",
          "tgn:7016845",
          "tgn:7029392"
        ],
        "placetype": [
          "aat:300008791"
        ],
        "name:nl": "Schutteplaat",
        "id": 7270664
      }
    },
    {
      "geometry": {
        "type": "Point",
        "coordinates": [
          5.533333,
          52.266667
        ]
      },
      "type": "Feature",
      "properties": {
        "hierarchy": [
          "tgn:7270665",
          "tgn:7003619",
          "tgn:1000003",
          "tgn:7016845",
          "tgn:7029392"
        ],
        "placetype": [
          "aat:300006075"
        ],
        "name:nl": "Schuttenbeek",
        "id": 7270665
      }
    },
    {
      "geometry": {
        "type": "Point",
        "coordinates": [
          6.483333,
          52.1
        ]
      },
      "type": "Feature",
      "properties": {
        "hierarchy": [
          "tgn:7270666",
          "tgn:7003619",
          "tgn:1000003",
          "tgn:7016845",
          "tgn:7029392"
        ],
        "placetype": [
          "aat:300007836"
        ],
        "name:nl": "Schuttelerbrug",
        "id": 7270666
      }
    },
    {
      "geometry": {
        "type": "Point",
        "coordinates": [
          4.533333,
          51.783333
        ]
      },
      "type": "Feature",
      "properties": {
        "hierarchy": [
          "tgn:7270667",
          "tgn:1000003",
          "tgn:7003632",
          "tgn:7016845",
          "tgn:7029392"
        ],
        "placetype": [
          "aat:300006163"
        ],
        "name:nl": "Sint-Anthoniepolder",
        "id": 7270667
      }
    },
    {
      "geometry": {
        "type": "Point",
        "coordinates": [
          6.616667,
          53.3
        ]
      },
      "type": "Feature",
      "properties": {
        "hierarchy": [
          "tgn:7270668",
          "tgn:1000003",
          "tgn:7003613",
          "tgn:7016845",
          "tgn:7029392"
        ],
        "placetype": [
          "aat:300008347"
        ],
        "name:nl": "Sint Annerhuisjes",
        "id": 7270668
      }
    },
    {
      "geometry": {
        "type": "Point",
        "coordinates": [
          6.666667,
          53.3
        ]
      },
      "type": "Feature",
      "properties": {
        "hierarchy": [
          "tgn:7270669",
          "tgn:1000003",
          "tgn:7003613",
          "tgn:7016845",
          "tgn:7029392"
        ],
        "placetype": [
          "aat:300008347"
        ],
        "name:nl": "Sint Annen",
        "id": 7270669
      }
    }
  ]
}
