{
  "geometry": {
    "type": "Point",
    "coordinates": [
      -82.4333,
      31.15
    ]
  },
  "type": "Feature",
  "properties": {
    "hierarchy": [
      "tgn:2435796",
      "tgn:1000001",
      "tgn:7012149",
      "tgn:2000439",
      "tgn:7007248",
      "tgn:7029392"
    ],
    "placetype": [
      "aat:300008706"
    ],
    "id": 2435796,
    "name:xx": "Kettle Creek"
  }
}
