{
  "geometry": {
    "type": "Point",
    "coordinates": [
      87.8333,
      22.1667
    ]
  },
  "type": "Feature",
  "properties": {
    "hierarchy": [
      "tgn:1125294",
      "tgn:1000004",
      "tgn:7000198",
      "tgn:1001977",
      "tgn:7029392"
    ],
    "placetype": [
      "aat:300008707"
    ],
    "id": 1125294,
    "name:xx": "Kāliāghaj"
  }
}
