{
  "geometry": {
    "type": "Point",
    "coordinates": [
      -83.4833,
      35.0667
    ]
  },
  "type": "Feature",
  "properties": {
    "hierarchy": [
      "tgn:2138638",
      "tgn:1000001",
      "tgn:7012149",
      "tgn:2001515",
      "tgn:7007709",
      "tgn:7029392"
    ],
    "placetype": [
      "aat:300008699"
    ],
    "id": 2138638,
    "name:xx": "Ash Flat Branch"
  }
}
