{
  "geometry": {
    "type": "Point",
    "coordinates": [
      -109.25,
      41.1667
    ]
  },
  "type": "Feature",
  "properties": {
    "hierarchy": [
      "tgn:2606845",
      "tgn:1000001",
      "tgn:7012149",
      "tgn:2002383",
      "tgn:7007923",
      "tgn:7029392"
    ],
    "placetype": [
      "aat:300008798"
    ],
    "id": 2606845,
    "name:xx": "Ramsey Peak"
  }
}
