{
  "geometry": {
    "type": "Point",
    "coordinates": [
      29.037242,
      28.486177
    ]
  },
  "type": "Feature",
  "properties": {
    "hierarchy": [
      "tgn:7536330",
      "tgn:7001242",
      "tgn:7016833",
      "tgn:7029392"
    ],
    "placetype": [
      "aat:300008777"
    ],
    "name:en": "Ghurābī, Jabal",
    "id": 7536330
  }
}
