{
  "geometry": {
    "type": "Point",
    "coordinates": [
      25.8333,
      62.2667
    ]
  },
  "type": "Feature",
  "properties": {
    "hierarchy": [
      "tgn:7009882",
      "tgn:7024077",
      "tgn:1000003",
      "tgn:1000069",
      "tgn:7029392"
    ],
    "placetype": [
      "aat:300008347",
      "aat:300264742",
      "aat:300387223",
      "aat:300008375"
    ],
    "id": 7009882,
    "name:xx": "Jyväskylä"
  }
}
