{
  "geometry": {
    "type": "Point",
    "coordinates": [
      -87.85,
      31.0833
    ]
  },
  "type": "Feature",
  "properties": {
    "hierarchy": [
      "tgn:2538179",
      "tgn:2000001",
      "tgn:7002659",
      "tgn:1000001",
      "tgn:7012149",
      "tgn:7029392"
    ],
    "placetype": [
      "aat:300008347"
    ],
    "id": 2538179,
    "name:xx": "Nelson Landing"
  }
}
