{
  "geometry": {
    "type": "Point",
    "coordinates": [
      -81.6667,
      39.75
    ]
  },
  "type": "Feature",
  "properties": {
    "hierarchy": [
      "tgn:2614942",
      "tgn:1000001",
      "tgn:7012149",
      "tgn:2001619",
      "tgn:7007706",
      "tgn:7029392"
    ],
    "placetype": [
      "aat:300008347"
    ],
    "id": 2614942,
    "name:xx": "Renrock"
  }
}
