{
  "geometry": {
    "type": "Point",
    "coordinates": [
      -96.2833,
      39.0167
    ]
  },
  "type": "Feature",
  "properties": {
    "hierarchy": [
      "tgn:2035974",
      "tgn:1000001",
      "tgn:7012149",
      "tgn:2000758",
      "tgn:7007254",
      "tgn:7029392"
    ],
    "placetype": [
      "aat:300008347"
    ],
    "id": 2035974,
    "name:xx": "Alma"
  }
}
