{
  "geometry": {
    "type": "Point",
    "coordinates": [
      -69.4833,
      44.4833
    ]
  },
  "type": "Feature",
  "properties": {
    "hierarchy": [
      "tgn:2302595",
      "tgn:1000001",
      "tgn:2000923",
      "tgn:7012149",
      "tgn:7007515",
      "tgn:7029392"
    ],
    "placetype": [
      "aat:300008680"
    ],
    "id": 2302595,
    "name:xx": "Dutton Pond"
  }
}
