{
  "type": "FeatureCollection",
  "features": [
    {
      "geometry": {
        "type": "Point",
        "coordinates": [
          7.816667,
          49.316667
        ]
      },
      "type": "Feature",
      "properties": {
        "hierarchy": [
          "tgn:7070213",
          "tgn:1000003",
          "tgn:7003682",
          "tgn:7000084",
          "tgn:7029392"
        ],
        "placetype": [
          "aat:300008777",
          "aat:300008795"
        ],
        "id": 7070213,
        "name:xx": "Stein Berg"
      }
    },
    {
      "geometry": {
        "type": "Point",
        "coordinates": [
          6.816667,
          49.383333
        ]
      },
      "type": "Feature",
      "properties": {
        "hierarchy": [
          "tgn:7070214",
          "tgn:1000003",
          "tgn:7003684",
          "tgn:7000084",
          "tgn:7029392"
        ],
        "placetype": [
          "aat:300008777"
        ],
        "id": 7070214,
        "name:xx": "Stein-Berg"
      }
    },
    {
      "geometry": {
        "type": "Point",
        "coordinates": [
          7.183333,
          49.35
        ]
      },
      "type": "Feature",
      "properties": {
        "hierarchy": [
          "tgn:7070215",
          "tgn:1000003",
          "tgn:7003684",
          "tgn:7000084",
          "tgn:7029392"
        ],
        "placetype": [
          "aat:300008777"
        ],
        "id": 7070215,
        "name:xx": "Stein-Berg"
      }
    },
    {
      "geometry": {
        "type": "Point",
        "coordinates": [
          10.35,
          49.3
        ]
      },
      "type": "Feature",
      "properties": {
        "hierarchy": [
          "tgn:7070216",
          "tgn:7003669",
          "tgn:1000003",
          "tgn:7000084",
          "tgn:7029392"
        ],
        "placetype": [
          "aat:300008777"
        ],
        "id": 7070216,
        "name:xx": "Steinberg"
      }
    },
    {
      "geometry": {
        "type": "Point",
        "coordinates": [
          11.516667,
          49.266667
        ]
      },
      "type": "Feature",
      "properties": {
        "hierarchy": [
          "tgn:7070217",
          "tgn:7003669",
          "tgn:1000003",
          "tgn:7000084",
          "tgn:7029392"
        ],
        "placetype": [
          "aat:300008777"
        ],
        "id": 7070217,
        "name:xx": "Steinberg"
      }
    },
    {
      "geometry": {
        "type": "Point",
        "coordinates": [
          11.85,
          49.25
        ]
      },
      "type": "Feature",
      "properties": {
        "hierarchy": [
          "tgn:7070218",
          "tgn:7003669",
          "tgn:1000003",
          "tgn:7000084",
          "tgn:7029392"
        ],
        "placetype": [
          "aat:300008777"
        ],
        "id": 7070218,
        "name:xx": "Stein Berg"
      }
    },
    {
      "geometry": {
        "type": "Point",
        "coordinates": [
          6.8,
          49.166667
        ]
      },
      "type": "Feature",
      "properties": {
        "hierarchy": [
          "tgn:7070219",
          "tgn:1000003",
          "tgn:7003684",
          "tgn:7000084",
          "tgn:7029392"
        ],
        "placetype": [
          "aat:300008777"
        ],
        "id": 7070219,
        "name:xx": "Stein Berg"
      }
    }
  ]
}
