{
  "geometry": {
    "type": "Point",
    "coordinates": [
      -120.85,
      38.2667
    ]
  },
  "type": "Feature",
  "properties": {
    "hierarchy": [
      "tgn:2543618",
      "tgn:1002146",
      "tgn:1000001",
      "tgn:7012149",
      "tgn:7007157",
      "tgn:7029392"
    ],
    "placetype": [
      "aat:300132316"
    ],
    "id": 2543618,
    "name:xx": "North Arm"
  }
}
