{
  "geometry": {
    "type": "Point",
    "coordinates": [
      -86.6667,
      38.05
    ]
  },
  "type": "Feature",
  "properties": {
    "hierarchy": [
      "tgn:2394131",
      "tgn:1000001",
      "tgn:7012149",
      "tgn:2000550",
      "tgn:7007252",
      "tgn:7029392"
    ],
    "placetype": [
      "aat:300008761"
    ],
    "id": 2394131,
    "name:xx": "Hogan Hollow"
  }
}
