{
  "geometry": {
    "type": "Point",
    "coordinates": [
      -81.5333,
      37.5167
    ]
  },
  "type": "Feature",
  "properties": {
    "hierarchy": [
      "tgn:2407838",
      "tgn:1000001",
      "tgn:7012149",
      "tgn:2002304",
      "tgn:7013961",
      "tgn:7029392"
    ],
    "placetype": [
      "aat:300008699"
    ],
    "id": 2407838,
    "name:xx": "Hurricane Branch"
  }
}
