{
  "geometry": {
    "type": "Point",
    "coordinates": [
      -96.7667,
      34.3167
    ]
  },
  "type": "Feature",
  "properties": {
    "hierarchy": [
      "tgn:2084113",
      "tgn:1000001",
      "tgn:7012149",
      "tgn:2001657",
      "tgn:7007707",
      "tgn:7029392"
    ],
    "placetype": [
      "aat:300008347"
    ],
    "id": 2084113,
    "name:xx": "Troy"
  }
}
