{
  "geometry": {
    "type": "Point",
    "coordinates": [
      79.6667,
      9.5333
    ]
  },
  "type": "Feature",
  "properties": {
    "hierarchy": [
      "tgn:1006943",
      "tgn:7000406",
      "tgn:1000004",
      "tgn:1000110",
      "tgn:7029392"
    ],
    "placetype": [
      "aat:300008791"
    ],
    "id": 1006943,
    "name:xx": "Delft Island"
  }
}
