{
  "geometry": {
    "type": "Point",
    "coordinates": [
      -157.7833,
      66.3667
    ]
  },
  "type": "Feature",
  "properties": {
    "hierarchy": [
      "tgn:2661498",
      "tgn:7006450",
      "tgn:1000001",
      "tgn:7012149",
      "tgn:2124014",
      "tgn:7029392"
    ],
    "placetype": [
      "aat:300008706"
    ],
    "id": 2661498,
    "name:xx": "Shovel Creek"
  }
}
