{
  "geometry": {
    "type": "Point",
    "coordinates": [
      16.65,
      -4.75
    ]
  },
  "type": "Feature",
  "properties": {
    "hierarchy": [
      "tgn:1089512",
      "tgn:1001143",
      "tgn:7001242",
      "tgn:1000159",
      "tgn:7029392"
    ],
    "placetype": [
      "aat:300008347"
    ],
    "id": 1089512,
    "name:xx": "Takundi"
  }
}
