{
  "geometry": {
    "type": "Point",
    "coordinates": [
      -81.5167,
      36.3333
    ]
  },
  "type": "Feature",
  "properties": {
    "hierarchy": [
      "tgn:2603517",
      "tgn:2001467",
      "tgn:1000001",
      "tgn:7012149",
      "tgn:7007709",
      "tgn:7029392"
    ],
    "placetype": [
      "aat:300266640"
    ],
    "id": 2603517,
    "name:xx": "Queen Ridge"
  }
}
