{
  "geometry": {
    "type": "Point",
    "coordinates": [
      140.4833,
      37.4167
    ]
  },
  "type": "Feature",
  "properties": {
    "hierarchy": [
      "tgn:6003875",
      "tgn:1000976",
      "tgn:1000004",
      "tgn:7000893",
      "tgn:1000120",
      "tgn:7029392"
    ],
    "placetype": [
      "aat:300008347"
    ],
    "id": 6003875,
    "name:xx": "Miharu"
  }
}
