{
  "type": "FeatureCollection",
  "features": [
    {
      "geometry": {
        "type": "Point",
        "coordinates": [
          11.766667,
          52.883333
        ]
      },
      "type": "Feature",
      "properties": {
        "hierarchy": [
          "tgn:1121880",
          "tgn:1000003",
          "tgn:7003687",
          "tgn:7000084",
          "tgn:7029392"
        ],
        "placetype": [
          "aat:300008707",
          "aat:300008699"
        ],
        "id": 1121880,
        "name:xx": "Biese"
      }
    },
    {
      "geometry": {
        "type": "Point",
        "coordinates": [
          15.033333,
          41.983333
        ]
      },
      "type": "Feature",
      "properties": {
        "hierarchy": [
          "tgn:1121881",
          "tgn:1000003",
          "tgn:7003241",
          "tgn:1000080",
          "tgn:7029392"
        ],
        "placetype": [
          "aat:300008707",
          "aat:300008699"
        ],
        "id": 1121881,
        "name:xx": "Biferno"
      }
    },
    {
      "geometry": {
        "type": "Point",
        "coordinates": [
          -152.4,
          60.75
        ]
      },
      "type": "Feature",
      "properties": {
        "hierarchy": [
          "tgn:1121882",
          "tgn:7006450",
          "tgn:1000001",
          "tgn:7019698",
          "tgn:7012149",
          "tgn:7029392"
        ],
        "placetype": [
          "aat:300008707"
        ],
        "id": 1121882,
        "name:xx": "Big"
      }
    },
    {
      "geometry": {
        "type": "Point",
        "coordinates": [
          -125.2333,
          72.5
        ]
      },
      "type": "Feature",
      "properties": {
        "hierarchy": [
          "tgn:1121884",
          "tgn:1006417",
          "tgn:7005685",
          "tgn:1000001",
          "tgn:1000296",
          "tgn:7029392"
        ],
        "placetype": [
          "aat:300008707"
        ],
        "id": 1121884,
        "name:xx": "Big"
      }
    },
    {
      "geometry": {
        "type": "Point",
        "coordinates": [
          -89.1167,
          33.6833
        ]
      },
      "type": "Feature",
      "properties": {
        "hierarchy": [
          "tgn:1121887",
          "tgn:1000001",
          "tgn:7012149",
          "tgn:7007522",
          "tgn:7029392"
        ],
        "placetype": [
          "aat:300008707"
        ],
        "id": 1121887,
        "name:xx": "Big Black"
      }
    },
    {
      "geometry": {
        "type": "Point",
        "coordinates": [
          -85.2667,
          40.0333
        ]
      },
      "type": "Feature",
      "properties": {
        "hierarchy": [
          "tgn:1121888",
          "tgn:1000001",
          "tgn:7012149",
          "tgn:7007252",
          "tgn:7029392"
        ],
        "placetype": [
          "aat:300008707"
        ],
        "id": 1121888,
        "name:xx": "Big Blue"
      }
    }
  ]
}
