{
  "geometry": {
    "type": "Point",
    "coordinates": [
      -86.4167,
      35.0833
    ]
  },
  "type": "Feature",
  "properties": {
    "hierarchy": [
      "tgn:2300360",
      "tgn:1000001",
      "tgn:7012149",
      "tgn:2001888",
      "tgn:7007825",
      "tgn:7029392"
    ],
    "placetype": [
      "aat:300008706"
    ],
    "id": 2300360,
    "name:xx": "Dukes Creek"
  }
}
