{
  "geometry": {
    "type": "Point",
    "coordinates": [
      -90.9333,
      43.7333
    ]
  },
  "type": "Feature",
  "properties": {
    "hierarchy": [
      "tgn:2347950",
      "tgn:1000001",
      "tgn:7012149",
      "tgn:7007922",
      "tgn:7029392"
    ],
    "placetype": [
      "aat:300008699"
    ],
    "id": 2347950,
    "name:xx": "German Coulee"
  }
}
