{
  "type": "FeatureCollection",
  "features": [
    {
      "geometry": {
        "type": "Point",
        "coordinates": [
          -69.7833,
          43.8333
        ]
      },
      "type": "Feature",
      "properties": {
        "hierarchy": [
          "tgn:2606410",
          "tgn:1000001",
          "tgn:7012149",
          "tgn:2000929",
          "tgn:7007515",
          "tgn:7029392"
        ],
        "placetype": [
          "aat:300008791"
        ],
        "id": 2606410,
        "name:xx": "Ram Island"
      }
    },
    {
      "geometry": {
        "type": "Point",
        "coordinates": [
          -69.3,
          43.9167
        ]
      },
      "type": "Feature",
      "properties": {
        "hierarchy": [
          "tgn:2606411",
          "tgn:1000001",
          "tgn:2000924",
          "tgn:7012149",
          "tgn:7007515",
          "tgn:7029392"
        ],
        "placetype": [
          "aat:300008791"
        ],
        "id": 2606411,
        "name:xx": "Ram Island"
      }
    },
    {
      "geometry": {
        "type": "Point",
        "coordinates": [
          -68.6,
          44.1333
        ]
      },
      "type": "Feature",
      "properties": {
        "hierarchy": [
          "tgn:2606412",
          "tgn:1000001",
          "tgn:2000922",
          "tgn:7012149",
          "tgn:7007515",
          "tgn:7029392"
        ],
        "placetype": [
          "aat:300008791"
        ],
        "id": 2606412,
        "name:xx": "Ram Island"
      }
    },
    {
      "geometry": {
        "type": "Point",
        "coordinates": [
          -70.1833,
          44.3167
        ]
      },
      "type": "Feature",
      "properties": {
        "hierarchy": [
          "tgn:2606413",
          "tgn:2000918",
          "tgn:1000001",
          "tgn:7012149",
          "tgn:7007515",
          "tgn:7029392"
        ],
        "placetype": [
          "aat:300008791"
        ],
        "id": 2606413,
        "name:xx": "Ram Island"
      }
    },
    {
      "geometry": {
        "type": "Point",
        "coordinates": [
          -68.9167,
          44.3333
        ]
      },
      "type": "Feature",
      "properties": {
        "hierarchy": [
          "tgn:2606414",
          "tgn:1000001",
          "tgn:7012149",
          "tgn:2000931",
          "tgn:7007515",
          "tgn:7029392"
        ],
        "placetype": [
          "aat:300008791"
        ],
        "id": 2606414,
        "name:xx": "Ram Island"
      }
    },
    {
      "geometry": {
        "type": "Point",
        "coordinates": [
          -67.6167,
          44.4833
        ]
      },
      "type": "Feature",
      "properties": {
        "hierarchy": [
          "tgn:2606415",
          "tgn:1000001",
          "tgn:7012149",
          "tgn:7014589",
          "tgn:7007515",
          "tgn:7029392"
        ],
        "placetype": [
          "aat:300008791"
        ],
        "id": 2606415,
        "name:xx": "Ram Island"
      }
    },
    {
      "geometry": {
        "type": "Point",
        "coordinates": [
          -69.7833,
          44.6
        ]
      },
      "type": "Feature",
      "properties": {
        "hierarchy": [
          "tgn:2606416",
          "tgn:1000001",
          "tgn:7012149",
          "tgn:2000930",
          "tgn:7007515",
          "tgn:7029392"
        ],
        "placetype": [
          "aat:300008791"
        ],
        "id": 2606416,
        "name:xx": "Ram Island"
      }
    },
    {
      "geometry": {
        "type": "Point",
        "coordinates": [
          -68.7667,
          44.9
        ]
      },
      "type": "Feature",
      "properties": {
        "hierarchy": [
          "tgn:2606417",
          "tgn:1000001",
          "tgn:7012149",
          "tgn:2000927",
          "tgn:7007515",
          "tgn:7029392"
        ],
        "placetype": [
          "aat:300008791"
        ],
        "id": 2606417,
        "name:xx": "Ram Island"
      }
    },
    {
      "geometry": {
        "type": "Point",
        "coordinates": [
          -69.2,
          45.25
        ]
      },
      "type": "Feature",
      "properties": {
        "hierarchy": [
          "tgn:2606418",
          "tgn:1000001",
          "tgn:7012149",
          "tgn:2000928",
          "tgn:7007515",
          "tgn:7029392"
        ],
        "placetype": [
          "aat:300008791"
        ],
        "id": 2606418,
        "name:xx": "Ram Island"
      }
    },
    {
      "geometry": {
        "type": "Point",
        "coordinates": [
          -70.8667,
          42.8167
        ]
      },
      "type": "Feature",
      "properties": {
        "hierarchy": [
          "tgn:2606419",
          "tgn:1000001",
          "tgn:1002359",
          "tgn:7012149",
          "tgn:7007517",
          "tgn:7029392"
        ],
        "placetype": [
          "aat:300008791"
        ],
        "id": 2606419,
        "name:xx": "Ram Island"
      }
    }
  ]
}
