{
  "geometry": {
    "type": "Point",
    "coordinates": [
      120.6664,
      23.8303
    ]
  },
  "type": "Feature",
  "properties": {
    "hierarchy": [
      "tgn:7475884",
      "tgn:7488858",
      "tgn:1000004",
      "tgn:1000141",
      "tgn:7029392"
    ],
    "placetype": [
      "aat:300008347"
    ],
    "id": 7475884,
    "name:xx": "Xiabu"
  }
}
