{
  "geometry": {
    "type": "Point",
    "coordinates": [
      -2.6667,
      53.3333
    ]
  },
  "type": "Feature",
  "properties": {
    "hierarchy": [
      "tgn:7010640",
      "tgn:7002445",
      "tgn:1000003",
      "tgn:1003600",
      "tgn:7008591",
      "tgn:7029392"
    ],
    "placetype": [
      "aat:300008347"
    ],
    "id": 7010640,
    "name:xx": "Norton"
  }
}
