{
  "geometry": {
    "type": "Point",
    "coordinates": [
      9.2333,
      45.6833
    ]
  },
  "type": "Feature",
  "properties": {
    "hierarchy": [
      "tgn:1047354",
      "tgn:7003150",
      "tgn:1000003",
      "tgn:7003237",
      "tgn:1000080",
      "tgn:7029392"
    ],
    "placetype": [
      "aat:300008347"
    ],
    "id": 1047354,
    "name:xx": "Verano Brianza"
  }
}
