{
  "geometry": {
    "type": "Point",
    "coordinates": [
      -82.15,
      27.85
    ]
  },
  "type": "Feature",
  "properties": {
    "hierarchy": [
      "tgn:2500426",
      "tgn:1000001",
      "tgn:1002479",
      "tgn:7012149",
      "tgn:7007240",
      "tgn:7029392"
    ],
    "placetype": [
      "aat:300008699"
    ],
    "id": 2500426,
    "name:xx": "McDonald Branch"
  }
}
