{
  "geometry": {
    "type": "Point",
    "coordinates": [
      -117.45,
      35.7833
    ]
  },
  "type": "Feature",
  "properties": {
    "hierarchy": [
      "tgn:2209714",
      "tgn:1000001",
      "tgn:7012149",
      "tgn:7007157",
      "tgn:7029392"
    ],
    "placetype": [
      "aat:300008761"
    ],
    "id": 2209714,
    "name:xx": "Burro Canyon"
  }
}
