{
  "geometry": {
    "type": "Point",
    "coordinates": [
      -91.75,
      33.9167
    ]
  },
  "type": "Feature",
  "properties": {
    "hierarchy": [
      "tgn:2218662",
      "tgn:1000001",
      "tgn:7016172",
      "tgn:7012149",
      "tgn:2000144",
      "tgn:7029392"
    ],
    "placetype": [
      "aat:300008680"
    ],
    "id": 2218662,
    "name:xx": "Cane Creek Lake"
  }
}
