{
  "geometry": {
    "type": "Point",
    "coordinates": [
      -80.5167,
      40.35
    ]
  },
  "type": "Feature",
  "properties": {
    "hierarchy": [
      "tgn:2504627",
      "tgn:1000001",
      "tgn:1002205",
      "tgn:7012149",
      "tgn:7013961",
      "tgn:7029392"
    ],
    "placetype": [
      "aat:300008699"
    ],
    "id": 2504627,
    "name:xx": "Mechling Run"
  }
}
