{
  "geometry": {
    "type": "Point",
    "coordinates": [
      2.3667,
      48.8333
    ]
  },
  "type": "Feature",
  "properties": {
    "hierarchy": [
      "tgn:1121862",
      "tgn:1000003",
      "tgn:7002883",
      "tgn:1000070",
      "tgn:7029392"
    ],
    "placetype": [
      "aat:300008707"
    ],
    "id": 1121862,
    "name:xx": "Bièvre"
  }
}
