{
  "geometry": {
    "type": "Point",
    "coordinates": [
      21.95,
      -16.2333
    ]
  },
  "type": "Feature",
  "properties": {
    "hierarchy": [
      "tgn:1087900",
      "tgn:7001242",
      "tgn:1000149",
      "tgn:1000833",
      "tgn:7029392"
    ],
    "placetype": [
      "aat:300008347"
    ],
    "id": 1087900,
    "name:xx": "Missão Santa Cruz"
  }
}
