{
  "geometry": {
    "type": "Point",
    "coordinates": [
      77.121158,
      29.82178
    ]
  },
  "type": "Feature",
  "properties": {
    "hierarchy": [
      "tgn:7590090",
      "tgn:1000004",
      "tgn:1001871",
      "tgn:7000198",
      "tgn:7029392"
    ],
    "placetype": [
      "aat:300008347"
    ],
    "name:en": "Blāni",
    "id": 7590090
  }
}
