{
  "type": "FeatureCollection",
  "features": [
    {
      "geometry": {
        "type": "Point",
        "coordinates": [
          -110.1833,
          48.9833
        ]
      },
      "type": "Feature",
      "properties": {
        "hierarchy": [
          "tgn:2360810",
          "tgn:1000001",
          "tgn:7012149",
          "tgn:2001280",
          "tgn:7007524",
          "tgn:7029392"
        ],
        "placetype": [
          "aat:300008680"
        ],
        "id": 2360810,
        "name:xx": "Grassy Lake"
      }
    },
    {
      "geometry": {
        "type": "Point",
        "coordinates": [
          -109.8,
          48.85
        ]
      },
      "type": "Feature",
      "properties": {
        "hierarchy": [
          "tgn:2360811",
          "tgn:1000001",
          "tgn:7012149",
          "tgn:2001280",
          "tgn:7007524",
          "tgn:7029392"
        ],
        "placetype": [
          "aat:300006191"
        ],
        "id": 2360811,
        "name:xx": "Grassy Lake"
      }
    },
    {
      "geometry": {
        "type": "Point",
        "coordinates": [
          -112.2,
          48.8667
        ]
      },
      "type": "Feature",
      "properties": {
        "hierarchy": [
          "tgn:2360812",
          "tgn:1000001",
          "tgn:7012149",
          "tgn:2001277",
          "tgn:7007524",
          "tgn:7029392"
        ],
        "placetype": [
          "aat:300008680"
        ],
        "id": 2360812,
        "name:xx": "Grassy Lake"
      }
    },
    {
      "geometry": {
        "type": "Point",
        "coordinates": [
          -111.8667,
          45.2333
        ]
      },
      "type": "Feature",
      "properties": {
        "hierarchy": [
          "tgn:2360813",
          "tgn:1000001",
          "tgn:7012149",
          "tgn:2001288",
          "tgn:7007524",
          "tgn:7029392"
        ],
        "placetype": [
          "aat:300008680"
        ],
        "id": 2360813,
        "name:xx": "Grassy Lake"
      }
    },
    {
      "geometry": {
        "type": "Point",
        "coordinates": [
          -94.7833,
          33.7667
        ]
      },
      "type": "Feature",
      "properties": {
        "hierarchy": [
          "tgn:2360814",
          "tgn:1000001",
          "tgn:7012149",
          "tgn:2001667",
          "tgn:7007707",
          "tgn:7029392"
        ],
        "placetype": [
          "aat:300008680"
        ],
        "id": 2360814,
        "name:xx": "Grassy Lake"
      }
    },
    {
      "geometry": {
        "type": "Point",
        "coordinates": [
          -96.0667,
          34.1667
        ]
      },
      "type": "Feature",
      "properties": {
        "hierarchy": [
          "tgn:2360815",
          "tgn:2001625",
          "tgn:1000001",
          "tgn:7012149",
          "tgn:7007707",
          "tgn:7029392"
        ],
        "placetype": [
          "aat:300008680"
        ],
        "id": 2360815,
        "name:xx": "Grassy Lake"
      }
    },
    {
      "geometry": {
        "type": "Point",
        "coordinates": [
          -94.5,
          33.6667
        ]
      },
      "type": "Feature",
      "properties": {
        "hierarchy": [
          "tgn:2360816",
          "tgn:1000001",
          "tgn:7012149",
          "tgn:2001667",
          "tgn:7007707",
          "tgn:7029392"
        ],
        "placetype": [
          "aat:300008905"
        ],
        "id": 2360816,
        "name:xx": "Grassy Lake"
      }
    },
    {
      "geometry": {
        "type": "Point",
        "coordinates": [
          -95.8167,
          34.0667
        ]
      },
      "type": "Feature",
      "properties": {
        "hierarchy": [
          "tgn:2360817",
          "tgn:1000001",
          "tgn:2001634",
          "tgn:7012149",
          "tgn:7007707",
          "tgn:7029392"
        ],
        "placetype": [
          "aat:300006191"
        ],
        "id": 2360817,
        "name:xx": "Grassy Lake"
      }
    },
    {
      "geometry": {
        "type": "Point",
        "coordinates": [
          -119.35,
          43.45
        ]
      },
      "type": "Feature",
      "properties": {
        "hierarchy": [
          "tgn:2360818",
          "tgn:1000001",
          "tgn:7012149",
          "tgn:2001709",
          "tgn:7007708",
          "tgn:7029392"
        ],
        "placetype": [
          "aat:300008680"
        ],
        "id": 2360818,
        "name:xx": "Grassy Lake"
      }
    },
    {
      "geometry": {
        "type": "Point",
        "coordinates": [
          -123.85,
          45.8167
        ]
      },
      "type": "Feature",
      "properties": {
        "hierarchy": [
          "tgn:2360819",
          "tgn:1000001",
          "tgn:1002276",
          "tgn:7012149",
          "tgn:7007708",
          "tgn:7029392"
        ],
        "placetype": [
          "aat:300008680"
        ],
        "id": 2360819,
        "name:xx": "Grassy Lake"
      }
    }
  ]
}
