{
  "geometry": {
    "type": "Point",
    "coordinates": [
      -107.0833,
      35.7333
    ]
  },
  "type": "Feature",
  "properties": {
    "hierarchy": [
      "tgn:2231007",
      "tgn:1000001",
      "tgn:7012149",
      "tgn:2001451",
      "tgn:7007566",
      "tgn:7029392"
    ],
    "placetype": [
      "aat:300006191"
    ],
    "id": 2231007,
    "name:xx": "Cerro Colorado Tank"
  }
}
