{
  "geometry": {
    "type": "Point",
    "coordinates": [
      -78.4833,
      40.85
    ]
  },
  "type": "Feature",
  "properties": {
    "hierarchy": [
      "tgn:2471796",
      "tgn:1000001",
      "tgn:1002278",
      "tgn:7012149",
      "tgn:7007710",
      "tgn:7029392"
    ],
    "placetype": [
      "aat:300008699"
    ],
    "id": 2471796,
    "name:xx": "Lost Run"
  }
}
