{
  "geometry": {
    "type": "Point",
    "coordinates": [
      -97.3333,
      32.3833
    ]
  },
  "type": "Feature",
  "properties": {
    "hierarchy": [
      "tgn:2463804",
      "tgn:1000001",
      "tgn:7012149",
      "tgn:1002526",
      "tgn:7007826",
      "tgn:7029392"
    ],
    "placetype": [
      "aat:300008699"
    ],
    "id": 2463804,
    "name:xx": "Lockett Branch"
  }
}
