{
  "geometry": {
    "type": "Point",
    "coordinates": [
      -122.1833,
      46.0333
    ]
  },
  "type": "Feature",
  "properties": {
    "hierarchy": [
      "tgn:2605703",
      "tgn:1000001",
      "tgn:7012149",
      "tgn:1002897",
      "tgn:7007920",
      "tgn:7029392"
    ],
    "placetype": [
      "aat:300008706"
    ],
    "id": 2605703,
    "name:xx": "Rain Creek"
  }
}
