{
  "geometry": {
    "type": "Point",
    "coordinates": [
      30.931667,
      30.661111
    ]
  },
  "type": "Feature",
  "properties": {
    "hierarchy": [
      "tgn:7525965",
      "tgn:7001242",
      "tgn:7016833",
      "tgn:1001087",
      "tgn:7029392"
    ],
    "placetype": [
      "aat:300005926"
    ],
    "name:en": "Sīdī Ḩassān",
    "id": 7525965
  }
}
