{
  "geometry": {
    "type": "Point",
    "coordinates": [
      -4.65,
      39.183333
    ]
  },
  "type": "Feature",
  "properties": {
    "hierarchy": [
      "tgn:7300306",
      "tgn:7002816",
      "tgn:1001647",
      "tgn:1000003",
      "tgn:1000095",
      "tgn:7029392"
    ],
    "placetype": [
      "aat:300008699"
    ],
    "id": 7300306,
    "name:xx": "Valdehornos, Río de"
  }
}
