{
  "geometry": {
    "type": "Point",
    "coordinates": [
      77.106944,
      31.24
    ]
  },
  "type": "Feature",
  "properties": {
    "hierarchy": [
      "tgn:7567852",
      "tgn:1000004",
      "tgn:7000198",
      "tgn:1001996",
      "tgn:7029392"
    ],
    "placetype": [
      "aat:300008347"
    ],
    "name:en": "Dwārsu",
    "id": 7567852
  }
}
