{
  "geometry": {
    "type": "Point",
    "coordinates": [
      77.381356,
      29.70576
    ]
  },
  "type": "Feature",
  "properties": {
    "hierarchy": [
      "tgn:7590350",
      "tgn:1000004",
      "tgn:7000198",
      "tgn:7016722",
      "tgn:7029392"
    ],
    "placetype": [
      "aat:300008347"
    ],
    "name:en": "Nūrpura",
    "id": 7590350
  }
}
