{
  "geometry": {
    "type": "Point",
    "coordinates": [
      -83.6667,
      42.2667
    ]
  },
  "type": "Feature",
  "properties": {
    "hierarchy": [
      "tgn:2346717",
      "tgn:1000001",
      "tgn:7012149",
      "tgn:1003000",
      "tgn:7007520",
      "tgn:7029392"
    ],
    "placetype": [
      "aat:300008347"
    ],
    "id": 2346717,
    "name:xx": "Geddes"
  }
}
