{
  "geometry": {
    "type": "Point",
    "coordinates": [
      -89.7833,
      46.2667
    ]
  },
  "type": "Feature",
  "properties": {
    "hierarchy": [
      "tgn:2523759",
      "tgn:1000001",
      "tgn:7012149",
      "tgn:7029392"
    ],
    "placetype": [
      "aat:300008680"
    ],
    "id": 2523759,
    "name:xx": "Moraine Lake"
  }
}
