{
  "geometry": {
    "type": "Point",
    "coordinates": [
      -75.0833,
      43.3333
    ]
  },
  "type": "Feature",
  "properties": {
    "hierarchy": [
      "tgn:2717848",
      "tgn:1000001",
      "tgn:7012149",
      "tgn:7014287",
      "tgn:7007568",
      "tgn:7029392"
    ],
    "placetype": [
      "aat:300008680"
    ],
    "id": 2717848,
    "name:xx": "Thomas Pond"
  }
}
