{
  "geometry": {
    "type": "Point",
    "coordinates": [
      -72.85,
      40.7333
    ]
  },
  "type": "Feature",
  "properties": {
    "hierarchy": [
      "tgn:2657340",
      "tgn:1000001",
      "tgn:7012149",
      "tgn:1002924",
      "tgn:7007568",
      "tgn:7029392"
    ],
    "placetype": [
      "aat:300008706"
    ],
    "id": 2657340,
    "name:xx": "Sheepen Creek"
  }
}
