{
  "geometry": {
    "type": "Point",
    "coordinates": [
      -96.3167,
      29.4833
    ]
  },
  "type": "Feature",
  "properties": {
    "hierarchy": [
      "tgn:2496730",
      "tgn:1000001",
      "tgn:7012149",
      "tgn:1002291",
      "tgn:7007826",
      "tgn:7029392"
    ],
    "placetype": [
      "aat:300008347"
    ],
    "id": 2496730,
    "name:xx": "Matthews"
  }
}
