{
  "geometry": {
    "type": "Point",
    "coordinates": [
      -91.0333,
      39.45
    ]
  },
  "type": "Feature",
  "properties": {
    "hierarchy": [
      "tgn:2029667",
      "tgn:1000001",
      "tgn:7012149",
      "tgn:1002786",
      "tgn:7007251",
      "tgn:7029392"
    ],
    "placetype": [
      "aat:300008347"
    ],
    "id": 2029667,
    "name:xx": "Pike"
  }
}
