{
  "geometry": {
    "type": "Point",
    "coordinates": [
      -76.6667,
      2.3333
    ]
  },
  "type": "Feature",
  "properties": {
    "hierarchy": [
      "tgn:1024038",
      "tgn:1000554",
      "tgn:1000050",
      "tgn:1000002",
      "tgn:7029392"
    ],
    "placetype": [
      "aat:300008347"
    ],
    "id": 1024038,
    "name:xx": "Timbío"
  }
}
