{
  "geometry": {
    "type": "Point",
    "coordinates": [
      -115.6333,
      34.7667
    ]
  },
  "type": "Feature",
  "properties": {
    "hierarchy": [
      "tgn:2765834",
      "tgn:1000001",
      "tgn:7012149",
      "tgn:7007157",
      "tgn:1002857",
      "tgn:7029392"
    ],
    "placetype": [
      "aat:300008798"
    ],
    "id": 2765834,
    "name:xx": "White Fang"
  }
}
