{
  "geometry": {
    "type": "Point",
    "coordinates": [
      -90.8333,
      37.7333
    ]
  },
  "type": "Feature",
  "properties": {
    "hierarchy": [
      "tgn:2600014",
      "tgn:1000001",
      "tgn:7012149",
      "tgn:2001254",
      "tgn:7007523",
      "tgn:7029392"
    ],
    "placetype": [
      "aat:300008798"
    ],
    "id": 2600014,
    "name:xx": "Pruitt Mountain"
  }
}
