{
  "geometry": {
    "type": "Point",
    "coordinates": [
      -78.5333,
      -6.6833
    ]
  },
  "type": "Feature",
  "properties": {
    "hierarchy": [
      "tgn:1024379",
      "tgn:1000547",
      "tgn:1000002",
      "tgn:1000056",
      "tgn:7029392"
    ],
    "placetype": [
      "aat:300008347"
    ],
    "id": 1024379,
    "name:xx": "Bambamarca"
  }
}
