{
  "geometry": {
    "type": "Point",
    "coordinates": [
      115.8333,
      51.6667
    ]
  },
  "type": "Feature",
  "properties": {
    "hierarchy": [
      "tgn:1128115",
      "tgn:1000004",
      "tgn:7029392"
    ],
    "placetype": [
      "aat:300008707"
    ],
    "id": 1128115,
    "name:xx": "Onon"
  }
}
