{
  "geometry": {
    "type": "Point",
    "coordinates": [
      10.05,
      52.05
    ]
  },
  "type": "Feature",
  "properties": {
    "hierarchy": [
      "tgn:7178679",
      "tgn:1000003",
      "tgn:7003676",
      "tgn:7000084",
      "tgn:7029392"
    ],
    "placetype": [
      "aat:300008777"
    ],
    "id": 7178679,
    "name:xx": "Hammersteins Höhe"
  }
}
