{
  "geometry": {
    "type": "Point",
    "coordinates": [
      -78.75,
      41.0833
    ]
  },
  "type": "Feature",
  "properties": {
    "hierarchy": [
      "tgn:2575422",
      "tgn:1000001",
      "tgn:1002278",
      "tgn:7012149",
      "tgn:7007710",
      "tgn:7029392"
    ],
    "placetype": [
      "aat:300008699"
    ],
    "id": 2575422,
    "name:xx": "Pentz Run"
  }
}
