{
  "geometry": {
    "type": "Point",
    "coordinates": [
      -76.05,
      35.9167
    ]
  },
  "type": "Feature",
  "properties": {
    "hierarchy": [
      "tgn:2624494",
      "tgn:1000001",
      "tgn:7012149",
      "tgn:2001545",
      "tgn:7007709",
      "tgn:7029392"
    ],
    "placetype": [
      "aat:300008850"
    ],
    "id": 2624494,
    "name:xx": "Rock Point"
  }
}
