{
  "geometry": {
    "type": "Point",
    "coordinates": [
      17.5667,
      53.2667
    ]
  },
  "type": "Feature",
  "properties": {
    "hierarchy": [
      "tgn:1049268",
      "tgn:7024116",
      "tgn:1000003",
      "tgn:7006366",
      "tgn:7029392"
    ],
    "placetype": [
      "aat:300008347"
    ],
    "id": 1049268,
    "name:xx": "Mrocza"
  }
}
