{
  "geometry": {
    "type": "Point",
    "coordinates": [
      -83.6667,
      37.9333
    ]
  },
  "type": "Feature",
  "properties": {
    "hierarchy": [
      "tgn:2380221",
      "tgn:1000001",
      "tgn:7012149",
      "tgn:2000826",
      "tgn:7007255",
      "tgn:7029392"
    ],
    "placetype": [
      "aat:300008706"
    ],
    "id": 2380221,
    "name:xx": "Hathaway Creek"
  }
}
