{
  "geometry": {
    "type": "Point",
    "coordinates": [
      -75.3167,
      39.5167
    ]
  },
  "type": "Feature",
  "properties": {
    "hierarchy": [
      "tgn:2246679",
      "tgn:1000001",
      "tgn:7014449",
      "tgn:7012149",
      "tgn:7007565",
      "tgn:7029392"
    ],
    "placetype": [
      "aat:300006191"
    ],
    "id": 2246679,
    "name:xx": "Cobbs Mill Lake"
  }
}
