{
  "type": "FeatureCollection",
  "features": [
    {
      "geometry": {
        "type": "Point",
        "coordinates": [
          -90.8667,
          48
        ]
      },
      "type": "Feature",
      "properties": {
        "hierarchy": [
          "tgn:2342660",
          "tgn:1000001",
          "tgn:2001014",
          "tgn:7012149",
          "tgn:7007521",
          "tgn:7029392"
        ],
        "placetype": [
          "aat:300008680"
        ],
        "id": 2342660,
        "name:xx": "Fungus Lake"
      }
    },
    {
      "geometry": {
        "type": "Point",
        "coordinates": [
          -90.7,
          37.3167
        ]
      },
      "type": "Feature",
      "properties": {
        "hierarchy": [
          "tgn:2342662",
          "tgn:1000001",
          "tgn:7012149",
          "tgn:7007523",
          "tgn:7029392"
        ],
        "placetype": [
          "aat:300008699"
        ],
        "id": 2342662,
        "name:xx": "Funk Branch"
      }
    },
    {
      "geometry": {
        "type": "Point",
        "coordinates": [
          -85.8833,
          41.0833
        ]
      },
      "type": "Feature",
      "properties": {
        "hierarchy": [
          "tgn:2342665",
          "tgn:1000001",
          "tgn:7012149",
          "tgn:1002557",
          "tgn:7007252",
          "tgn:7029392"
        ],
        "placetype": [
          "aat:300006075"
        ],
        "id": 2342665,
        "name:xx": "Funk Ditch"
      }
    },
    {
      "geometry": {
        "type": "Point",
        "coordinates": [
          -120.55,
          37.9667
        ]
      },
      "type": "Feature",
      "properties": {
        "hierarchy": [
          "tgn:2342666",
          "tgn:1000001",
          "tgn:1002219",
          "tgn:7012149",
          "tgn:7007157",
          "tgn:7029392"
        ],
        "placetype": [
          "aat:300008798"
        ],
        "id": 2342666,
        "name:xx": "Funk Hill"
      }
    },
    {
      "geometry": {
        "type": "Point",
        "coordinates": [
          -86.7,
          37.9833
        ]
      },
      "type": "Feature",
      "properties": {
        "hierarchy": [
          "tgn:2342667",
          "tgn:1000001",
          "tgn:7012149",
          "tgn:2000550",
          "tgn:7007252",
          "tgn:7029392"
        ],
        "placetype": [
          "aat:300008761"
        ],
        "id": 2342667,
        "name:xx": "Funk Hollow"
      }
    },
    {
      "geometry": {
        "type": "Point",
        "coordinates": [
          -88.25,
          45.05
        ]
      },
      "type": "Feature",
      "properties": {
        "hierarchy": [
          "tgn:2342668",
          "tgn:1000001",
          "tgn:7012149",
          "tgn:2002341",
          "tgn:7007922",
          "tgn:7029392"
        ],
        "placetype": [
          "aat:300008680"
        ],
        "id": 2342668,
        "name:xx": "Funk Lake"
      }
    },
    {
      "geometry": {
        "type": "Point",
        "coordinates": [
          -119.7333,
          48.6
        ]
      },
      "type": "Feature",
      "properties": {
        "hierarchy": [
          "tgn:2342669",
          "tgn:1000001",
          "tgn:7012149",
          "tgn:1002742",
          "tgn:7007920",
          "tgn:7029392"
        ],
        "placetype": [
          "aat:300008798"
        ],
        "id": 2342669,
        "name:xx": "Funk Mountain"
      }
    }
  ]
}
