{
  "geometry": {
    "type": "Point",
    "coordinates": [
      -116.8667,
      42.45
    ]
  },
  "type": "Feature",
  "properties": {
    "hierarchy": [
      "tgn:2717605",
      "tgn:1000001",
      "tgn:7012149",
      "tgn:2000488",
      "tgn:7007250",
      "tgn:7029392"
    ],
    "placetype": [
      "aat:300008706"
    ],
    "id": 2717605,
    "name:xx": "Thomas Creek"
  }
}
