{
  "geometry": {
    "type": "Point",
    "coordinates": [
      -134.1333,
      58.3833
    ]
  },
  "type": "Feature",
  "properties": {
    "hierarchy": [
      "tgn:2352074",
      "tgn:7006450",
      "tgn:1000001",
      "tgn:2124089",
      "tgn:7012149",
      "tgn:7029392"
    ],
    "placetype": [
      "aat:300008680"
    ],
    "id": 2352074,
    "name:xx": "Glory Lake"
  }
}
