{
  "type": "FeatureCollection",
  "features": [
    {
      "geometry": {
        "type": "Point",
        "coordinates": [
          0.4833,
          47
        ]
      },
      "type": "Feature",
      "properties": {
        "hierarchy": [
          "tgn:4001643",
          "tgn:1000003",
          "tgn:7002877",
          "tgn:1000070",
          "tgn:7029392"
        ],
        "placetype": [
          "aat:300008347"
        ],
        "id": 4001643,
        "name:xx": "Bois-Aubry"
      }
    },
    {
      "geometry": {
        "type": "Point",
        "coordinates": [
          4.133333,
          50.466667
        ]
      },
      "type": "Feature",
      "properties": {
        "hierarchy": [
          "tgn:4001645",
          "tgn:7007877",
          "tgn:1000003",
          "tgn:1000063",
          "tgn:4012014",
          "tgn:7029392"
        ],
        "placetype": [
          "aat:300008347"
        ],
        "id": 4001645,
        "name:xx": "Bois du Luc"
      }
    },
    {
      "geometry": {
        "type": "Point",
        "coordinates": [
          0.65,
          49.15
        ]
      },
      "type": "Feature",
      "properties": {
        "hierarchy": [
          "tgn:4001647",
          "tgn:1000003",
          "tgn:7002882",
          "tgn:1000070",
          "tgn:7029392"
        ],
        "placetype": [
          "aat:300008347"
        ],
        "id": 4001647,
        "name:xx": "Boisney"
      }
    },
    {
      "geometry": {
        "type": "Point",
        "coordinates": [
          23.266,
          42.65
        ]
      },
      "type": "Feature",
      "properties": {
        "hierarchy": [
          "tgn:4001648",
          "tgn:7018759",
          "tgn:1000003",
          "tgn:7006413",
          "tgn:7029392"
        ],
        "placetype": [
          "aat:300008347"
        ],
        "id": 4001648,
        "name:xx": "Boyana"
      }
    }
  ]
}
