{
  "geometry": {
    "type": "Point",
    "coordinates": [
      80.866667,
      23.116667
    ]
  },
  "type": "Feature",
  "properties": {
    "hierarchy": [
      "tgn:7580901",
      "tgn:1000004",
      "tgn:7000198",
      "tgn:1001894",
      "tgn:7029392"
    ],
    "placetype": [
      "aat:300008347"
    ],
    "name:en": "Tilwārāghāt",
    "id": 7580901
  }
}
