{
  "geometry": {
    "type": "Point",
    "coordinates": [
      -87.6167,
      39.15
    ]
  },
  "type": "Feature",
  "properties": {
    "hierarchy": [
      "tgn:2556704",
      "tgn:1000001",
      "tgn:7012149",
      "tgn:7029392"
    ],
    "placetype": [
      "aat:300008680"
    ],
    "id": 2556704,
    "name:xx": "Old Channel Lake"
  }
}
