{
  "geometry": {
    "type": "Point",
    "coordinates": [
      112.3167,
      36.5667
    ]
  },
  "type": "Feature",
  "properties": {
    "hierarchy": [
      "tgn:1071123",
      "tgn:1000004",
      "tgn:7002086",
      "tgn:1000111",
      "tgn:7029392"
    ],
    "placetype": [
      "aat:300008347"
    ],
    "id": 1071123,
    "name:xx": "Qinyuan"
  }
}
