{
  "geometry": {
    "type": "Point",
    "coordinates": [
      8.3333,
      47.4667
    ]
  },
  "type": "Feature",
  "properties": {
    "hierarchy": [
      "tgn:7007496",
      "tgn:7003739",
      "tgn:1000003",
      "tgn:7011731",
      "tgn:7029392"
    ],
    "placetype": [
      "aat:300008347"
    ],
    "id": 7007496,
    "name:xx": "Wettingen"
  }
}
