{
  "geometry": {
    "type": "Point",
    "coordinates": [
      21.05,
      40.75
    ]
  },
  "type": "Feature",
  "properties": {
    "hierarchy": [
      "tgn:7225159",
      "tgn:7002724",
      "tgn:7002715",
      "tgn:1000003",
      "tgn:1000074",
      "tgn:7029392"
    ],
    "placetype": [
      "aat:300266640"
    ],
    "id": 7225159,
    "name:xx": "Rámnitsa"
  }
}
