{
  "geometry": {
    "type": "Point",
    "coordinates": [
      -97.5667,
      41.65
    ]
  },
  "type": "Feature",
  "properties": {
    "hierarchy": [
      "tgn:2315938",
      "tgn:1000001",
      "tgn:7012149",
      "tgn:2001386",
      "tgn:7007525",
      "tgn:7029392"
    ],
    "placetype": [
      "aat:300008706"
    ],
    "id": 2315938,
    "name:xx": "Elm Creek"
  }
}
