{
  "geometry": {
    "type": "Point",
    "coordinates": [
      -89.0333,
      32.4333
    ]
  },
  "type": "Feature",
  "properties": {
    "hierarchy": [
      "tgn:2239296",
      "tgn:1000001",
      "tgn:7012149",
      "tgn:2001136",
      "tgn:7007522",
      "tgn:7029392"
    ],
    "placetype": [
      "aat:300006075"
    ],
    "id": 2239296,
    "name:xx": "Chunky Canal"
  }
}
