{
  "geometry": {
    "type": "Point",
    "coordinates": [
      91.7833,
      24.4833
    ]
  },
  "type": "Feature",
  "properties": {
    "hierarchy": [
      "tgn:1065818",
      "tgn:1000004",
      "tgn:7032097",
      "tgn:1000105",
      "tgn:7029392"
    ],
    "placetype": [
      "aat:300008347"
    ],
    "id": 1065818,
    "name:xx": "Maulvi Bāzār"
  }
}
