{
  "geometry": {
    "type": "Point",
    "coordinates": [
      -83.0667,
      36.9333
    ]
  },
  "type": "Feature",
  "properties": {
    "hierarchy": [
      "tgn:2415025",
      "tgn:1000001",
      "tgn:7012149",
      "tgn:2000797",
      "tgn:7007255",
      "tgn:7029392"
    ],
    "placetype": [
      "aat:300008699"
    ],
    "id": 2415025,
    "name:xx": "Island Branch"
  }
}
