{
  "geometry": {
    "type": "Point",
    "coordinates": [
      -81.0833,
      35.5667
    ]
  },
  "type": "Feature",
  "properties": {
    "hierarchy": [
      "tgn:2450336",
      "tgn:1000001",
      "tgn:2001479",
      "tgn:7012149",
      "tgn:7007709",
      "tgn:7029392"
    ],
    "placetype": [
      "aat:300008706"
    ],
    "id": 2450336,
    "name:xx": "Link Creek"
  }
}
