{
  "type": "FeatureCollection",
  "features": [
    {
      "geometry": {
        "type": "Point",
        "coordinates": [
          -106.65,
          28.883333
        ]
      },
      "type": "Feature",
      "properties": {
        "hierarchy": [
          "tgn:7430830",
          "tgn:7005581",
          "tgn:1000001",
          "tgn:7005560",
          "tgn:7029392"
        ],
        "placetype": [
          "aat:300008347"
        ],
        "id": 7430830,
        "name:xx": "Campo 46"
      }
    },
    {
      "geometry": {
        "type": "Point",
        "coordinates": [
          -106.75,
          28.9
        ]
      },
      "type": "Feature",
      "properties": {
        "hierarchy": [
          "tgn:7430832",
          "tgn:7005581",
          "tgn:1000001",
          "tgn:7005560",
          "tgn:7029392"
        ],
        "placetype": [
          "aat:300008347"
        ],
        "id": 7430832,
        "name:xx": "Campo 38"
      }
    },
    {
      "geometry": {
        "type": "Point",
        "coordinates": [
          -106.816667,
          28.833333
        ]
      },
      "type": "Feature",
      "properties": {
        "hierarchy": [
          "tgn:7430834",
          "tgn:7005581",
          "tgn:1000001",
          "tgn:7005560",
          "tgn:7029392"
        ],
        "placetype": [
          "aat:300008347"
        ],
        "id": 7430834,
        "name:xx": "Campo 36"
      }
    },
    {
      "geometry": {
        "type": "Point",
        "coordinates": [
          -106.9,
          28.466667
        ]
      },
      "type": "Feature",
      "properties": {
        "hierarchy": [
          "tgn:7430836",
          "tgn:7005581",
          "tgn:1000001",
          "tgn:7005560",
          "tgn:7029392"
        ],
        "placetype": [
          "aat:300008347"
        ],
        "id": 7430836,
        "name:xx": "Campo 2 A"
      }
    },
    {
      "geometry": {
        "type": "Point",
        "coordinates": [
          -107.083333,
          29.15
        ]
      },
      "type": "Feature",
      "properties": {
        "hierarchy": [
          "tgn:7430837",
          "tgn:7005581",
          "tgn:1000001",
          "tgn:7005560",
          "tgn:7029392"
        ],
        "placetype": [
          "aat:300008347"
        ],
        "id": 7430837,
        "name:xx": "Campo 261"
      }
    },
    {
      "geometry": {
        "type": "Point",
        "coordinates": [
          -107.116667,
          29.166667
        ]
      },
      "type": "Feature",
      "properties": {
        "hierarchy": [
          "tgn:7430838",
          "tgn:7005581",
          "tgn:1000001",
          "tgn:7005560",
          "tgn:7029392"
        ],
        "placetype": [
          "aat:300008347"
        ],
        "id": 7430838,
        "name:xx": "Campo 254"
      }
    },
    {
      "geometry": {
        "type": "Point",
        "coordinates": [
          -107.133333,
          29.183333
        ]
      },
      "type": "Feature",
      "properties": {
        "hierarchy": [
          "tgn:7430839",
          "tgn:7005581",
          "tgn:1000001",
          "tgn:7005560",
          "tgn:7029392"
        ],
        "placetype": [
          "aat:300008347"
        ],
        "id": 7430839,
        "name:xx": "Campo 253"
      }
    }
  ]
}
