{
  "geometry": {
    "type": "Point",
    "coordinates": [
      -77.4167,
      41.3833
    ]
  },
  "type": "Feature",
  "properties": {
    "hierarchy": [
      "tgn:2183248",
      "tgn:1000001",
      "tgn:7012149",
      "tgn:1002613",
      "tgn:7007710",
      "tgn:7029392"
    ],
    "placetype": [
      "aat:300008699"
    ],
    "id": 2183248,
    "name:xx": "Bluestone Run"
  }
}
