{
  "geometry": {
    "type": "Point",
    "coordinates": [
      -91.7667,
      35.8333
    ]
  },
  "type": "Feature",
  "properties": {
    "hierarchy": [
      "tgn:2298413",
      "tgn:1000001",
      "tgn:7016172",
      "tgn:7012149",
      "tgn:2000136",
      "tgn:7029392"
    ],
    "placetype": [
      "aat:300008699"
    ],
    "id": 2298413,
    "name:xx": "Dry Run"
  }
}
