{
  "geometry": {
    "type": "Point",
    "coordinates": [
      123.4333,
      8.65
    ]
  },
  "type": "Feature",
  "properties": {
    "hierarchy": [
      "tgn:1084172",
      "tgn:1000004",
      "tgn:1001610",
      "tgn:1000135",
      "tgn:7029392"
    ],
    "placetype": [
      "aat:300008347"
    ],
    "id": 1084172,
    "name:xx": "Dapitan"
  }
}
