{
  "geometry": {
    "type": "Point",
    "coordinates": [
      -107.3333,
      32.3333
    ]
  },
  "type": "Feature",
  "properties": {
    "hierarchy": [
      "tgn:2741792",
      "tgn:1000001",
      "tgn:7012149",
      "tgn:2001444",
      "tgn:7007566",
      "tgn:7029392"
    ],
    "placetype": [
      "aat:300008761"
    ],
    "id": 2741792,
    "name:xx": "Uvas Valley"
  }
}
