{
  "geometry": {
    "type": "Point",
    "coordinates": [
      77.328757,
      28.02798
    ]
  },
  "type": "Feature",
  "properties": {
    "hierarchy": [
      "tgn:7548241",
      "tgn:1000004",
      "tgn:1001871",
      "tgn:7000198",
      "tgn:7029392"
    ],
    "placetype": [
      "aat:300008347"
    ],
    "name:en": "Aurangābād",
    "id": 7548241
  }
}
