{
  "geometry": {
    "type": "Point",
    "coordinates": [
      62.7167,
      26.3667
    ]
  },
  "type": "Feature",
  "properties": {
    "hierarchy": [
      "tgn:1083690",
      "tgn:7000360",
      "tgn:1000004",
      "tgn:1000133",
      "tgn:7029392"
    ],
    "placetype": [
      "aat:300008347"
    ],
    "id": 1083690,
    "name:xx": "Nirwāno"
  }
}
