{
  "geometry": {
    "type": "Point",
    "coordinates": [
      40.1833,
      60.4167
    ]
  },
  "type": "Feature",
  "properties": {
    "hierarchy": [
      "tgn:1061272",
      "tgn:1000004",
      "tgn:7017317",
      "tgn:7018214",
      "tgn:7002435",
      "tgn:7029392"
    ],
    "placetype": [
      "aat:300008347"
    ],
    "id": 1061272,
    "name:xx": "Vozhega"
  }
}
