{
  "geometry": {
    "type": "Point",
    "coordinates": [
      -98.45,
      25.083333
    ]
  },
  "type": "Feature",
  "properties": {
    "hierarchy": [
      "tgn:7439896",
      "tgn:1000001",
      "tgn:7005597",
      "tgn:7005560",
      "tgn:7029392"
    ],
    "placetype": [
      "aat:300008347"
    ],
    "id": 7439896,
    "name:xx": "San Pedro de Gutiérrez"
  }
}
