{
  "geometry": {
    "type": "Point",
    "coordinates": [
      -105.0333,
      41.9333
    ]
  },
  "type": "Feature",
  "properties": {
    "hierarchy": [
      "tgn:2641479",
      "tgn:1000001",
      "tgn:7012149",
      "tgn:2002383",
      "tgn:7007923",
      "tgn:7029392"
    ],
    "placetype": [
      "aat:300008706"
    ],
    "id": 2641479,
    "name:xx": "Sand Creek"
  }
}
