{
  "geometry": {
    "type": "Point",
    "coordinates": [
      -86.25,
      38.4167
    ]
  },
  "type": "Feature",
  "properties": {
    "hierarchy": [
      "tgn:2397353",
      "tgn:1000001",
      "tgn:7012149",
      "tgn:1002750",
      "tgn:7007252",
      "tgn:7029392"
    ],
    "placetype": [
      "aat:300008706"
    ],
    "id": 2397353,
    "name:xx": "Honey Creek"
  }
}
