{
  "geometry": {
    "type": "Point",
    "coordinates": [
      -123.9167,
      45.45
    ]
  },
  "type": "Feature",
  "properties": {
    "hierarchy": [
      "tgn:2660981",
      "tgn:1000001",
      "tgn:7012149",
      "tgn:1002943",
      "tgn:7007708",
      "tgn:7029392"
    ],
    "placetype": [
      "aat:300008706"
    ],
    "id": 2660981,
    "name:xx": "Short Creek"
  }
}
