{
  "geometry": {
    "type": "Point",
    "coordinates": [
      -84.7833,
      35.6167
    ]
  },
  "type": "Feature",
  "properties": {
    "hierarchy": [
      "tgn:2584639",
      "tgn:1000001",
      "tgn:7012149",
      "tgn:7007825",
      "tgn:7029392"
    ],
    "placetype": [
      "aat:300132348"
    ],
    "id": 2584639,
    "name:xx": "Piney River Shoals"
  }
}
