{
  "geometry": {
    "type": "Point",
    "coordinates": [
      142.8333,
      -3.3333
    ]
  },
  "type": "Feature",
  "properties": {
    "hierarchy": [
      "tgn:1099580",
      "tgn:7006160",
      "tgn:1000947",
      "tgn:1000006",
      "tgn:7029392"
    ],
    "placetype": [
      "aat:300008347"
    ],
    "id": 1099580,
    "name:xx": "Suain"
  }
}
