{
  "geometry": {
    "type": "Point",
    "coordinates": [
      -97.65,
      32.1667
    ]
  },
  "type": "Feature",
  "properties": {
    "hierarchy": [
      "tgn:2104110",
      "tgn:1000001",
      "tgn:1002191",
      "tgn:7012149",
      "tgn:7007826",
      "tgn:7029392"
    ],
    "placetype": [
      "aat:300008347",
      "aat:300387210"
    ],
    "id": 2104110,
    "name:xx": "Eulogy"
  }
}
