{
  "geometry": {
    "type": "Point",
    "coordinates": [
      25.25,
      41.083333
    ]
  },
  "type": "Feature",
  "properties": {
    "hierarchy": [
      "tgn:7235547",
      "tgn:7011170",
      "tgn:7002715",
      "tgn:1000003",
      "tgn:1000074",
      "tgn:7029392"
    ],
    "placetype": [
      "aat:300008699"
    ],
    "id": 7235547,
    "name:xx": "Filalós Réma"
  }
}
