{
  "geometry": {
    "type": "Point",
    "coordinates": [
      -86.8333,
      36.55
    ]
  },
  "type": "Feature",
  "properties": {
    "hierarchy": [
      "tgn:2706365",
      "tgn:1000001",
      "tgn:7012149",
      "tgn:2001910",
      "tgn:7007825",
      "tgn:7029392"
    ],
    "placetype": [
      "aat:300008905"
    ],
    "id": 2706365,
    "name:xx": "Swamps, The"
  }
}
