{
  "geometry": {
    "type": "Point",
    "coordinates": [
      -85.5833,
      30.7167
    ]
  },
  "type": "Feature",
  "properties": {
    "hierarchy": [
      "tgn:2426910",
      "tgn:1000001",
      "tgn:7012149",
      "tgn:2000291",
      "tgn:7007240",
      "tgn:7029392"
    ],
    "placetype": [
      "aat:300008699"
    ],
    "id": 2426910,
    "name:xx": "Jones Rice Mill Branch"
  }
}
