{
  "type": "FeatureCollection",
  "features": [
    {
      "geometry": {
        "type": "Point",
        "coordinates": [
          3.463894,
          50.934224
        ]
      },
      "type": "Feature",
      "properties": {
        "hierarchy": [
          "tgn:7250690",
          "tgn:7003457",
          "tgn:1000003",
          "tgn:1000063",
          "tgn:7018236",
          "tgn:7029392"
        ],
        "placetype": [
          "aat:300008347"
        ],
        "id": 7250690,
        "name:xx": "Olsene"
      }
    },
    {
      "geometry": {
        "type": "Point",
        "coordinates": [
          5.75,
          50.583333
        ]
      },
      "type": "Feature",
      "properties": {
        "hierarchy": [
          "tgn:7250692",
          "tgn:7003460",
          "tgn:1000003",
          "tgn:1000063",
          "tgn:4012014",
          "tgn:7029392"
        ],
        "placetype": [
          "aat:300008347"
        ],
        "id": 7250692,
        "name:xx": "Olne"
      }
    },
    {
      "geometry": {
        "type": "Point",
        "coordinates": [
          3.266667,
          51.133333
        ]
      },
      "type": "Feature",
      "properties": {
        "hierarchy": [
          "tgn:7250693",
          "tgn:7003458",
          "tgn:1000003",
          "tgn:1000063",
          "tgn:7018236",
          "tgn:7029392"
        ],
        "placetype": [
          "aat:300008347"
        ],
        "id": 7250693,
        "name:xx": "Nachtegaal"
      }
    },
    {
      "geometry": {
        "type": "Point",
        "coordinates": [
          4.733333,
          51.05
        ]
      },
      "type": "Feature",
      "properties": {
        "hierarchy": [
          "tgn:7250694",
          "tgn:7003456",
          "tgn:1000003",
          "tgn:1000063",
          "tgn:7018236",
          "tgn:7029392"
        ],
        "placetype": [
          "aat:300008347"
        ],
        "id": 7250694,
        "name:xx": "Nachtegaal"
      }
    },
    {
      "geometry": {
        "type": "Point",
        "coordinates": [
          3.283796,
          51.011707
        ]
      },
      "type": "Feature",
      "properties": {
        "hierarchy": [
          "tgn:7250695",
          "tgn:7003458",
          "tgn:1000003",
          "tgn:1000063",
          "tgn:7018236",
          "tgn:7029392"
        ],
        "placetype": [
          "aat:300008347"
        ],
        "id": 7250695,
        "name:xx": "Nachtegaal"
      }
    },
    {
      "geometry": {
        "type": "Point",
        "coordinates": [
          2.901274,
          50.964402
        ]
      },
      "type": "Feature",
      "properties": {
        "hierarchy": [
          "tgn:7250696",
          "tgn:7003458",
          "tgn:1000003",
          "tgn:1000063",
          "tgn:7018236",
          "tgn:7029392"
        ],
        "placetype": [
          "aat:300008347"
        ],
        "id": 7250696,
        "name:xx": "Nachtegaal"
      }
    },
    {
      "geometry": {
        "type": "Point",
        "coordinates": [
          3.15,
          50.866667
        ]
      },
      "type": "Feature",
      "properties": {
        "hierarchy": [
          "tgn:7250697",
          "tgn:7003458",
          "tgn:1000003",
          "tgn:1000063",
          "tgn:7018236",
          "tgn:7029392"
        ],
        "placetype": [
          "aat:300008347"
        ],
        "id": 7250697,
        "name:xx": "Nachtegaal"
      }
    },
    {
      "geometry": {
        "type": "Point",
        "coordinates": [
          4.267512,
          50.73917
        ]
      },
      "type": "Feature",
      "properties": {
        "hierarchy": [
          "tgn:7250698",
          "tgn:7018239",
          "tgn:1000003",
          "tgn:1000063",
          "tgn:7018236",
          "tgn:7029392"
        ],
        "placetype": [
          "aat:300008347"
        ],
        "id": 7250698,
        "name:xx": "Nachtegaal"
      }
    },
    {
      "geometry": {
        "type": "Point",
        "coordinates": [
          4.45,
          51.133333
        ]
      },
      "type": "Feature",
      "properties": {
        "hierarchy": [
          "tgn:7250699",
          "tgn:7003456",
          "tgn:1000003",
          "tgn:1000063",
          "tgn:7018236",
          "tgn:7029392"
        ],
        "placetype": [
          "aat:300000206"
        ],
        "id": 7250699,
        "name:xx": "Nachtegaal"
      }
    }
  ]
}
