{
  "geometry": {
    "type": "Point",
    "coordinates": [
      -146.65,
      61.1167
    ]
  },
  "type": "Feature",
  "properties": {
    "hierarchy": [
      "tgn:2498506",
      "tgn:7006450",
      "tgn:1000001",
      "tgn:7012149",
      "tgn:2000086",
      "tgn:7029392"
    ],
    "placetype": [
      "aat:300008706"
    ],
    "id": 2498506,
    "name:xx": "McAllister Creek"
  }
}
