{
  "geometry": {
    "type": "Point",
    "coordinates": [
      113.2667,
      26.0833
    ]
  },
  "type": "Feature",
  "properties": {
    "hierarchy": [
      "tgn:1069794",
      "tgn:1000004",
      "tgn:7002079",
      "tgn:1000111",
      "tgn:7029392"
    ],
    "placetype": [
      "aat:300008347"
    ],
    "id": 1069794,
    "name:xx": "Liaojiangshi"
  }
}
