{
  "geometry": {
    "type": "Point",
    "coordinates": [
      -116.9833,
      38.6667
    ]
  },
  "type": "Feature",
  "properties": {
    "hierarchy": [
      "tgn:2276422",
      "tgn:1000001",
      "tgn:2001418",
      "tgn:7012149",
      "tgn:7007526",
      "tgn:7029392"
    ],
    "placetype": [
      "aat:300008761"
    ],
    "id": 2276422,
    "name:xx": "Davenport Canyon"
  }
}
