{
  "type": "FeatureCollection",
  "features": [
    {
      "geometry": {
        "type": "Point",
        "coordinates": [
          -104.7833,
          38.7667
        ]
      },
      "type": "Feature",
      "properties": {
        "hierarchy": [
          "tgn:2016361",
          "tgn:1000001",
          "tgn:7012149",
          "tgn:7014097",
          "tgn:7007158",
          "tgn:7029392"
        ],
        "placetype": [
          "aat:300008347"
        ],
        "id": 2016361,
        "name:xx": "Stratmoor Hills"
      }
    },
    {
      "geometry": {
        "type": "Point",
        "coordinates": [
          -102.6,
          39.3
        ]
      },
      "type": "Feature",
      "properties": {
        "hierarchy": [
          "tgn:2016362",
          "tgn:1000001",
          "tgn:7012149",
          "tgn:2000223",
          "tgn:7007158",
          "tgn:7029392"
        ],
        "placetype": [
          "aat:300008347"
        ],
        "id": 2016362,
        "name:xx": "Stratton"
      }
    },
    {
      "geometry": {
        "type": "Point",
        "coordinates": [
          -106.3167,
          39.2333
        ]
      },
      "type": "Feature",
      "properties": {
        "hierarchy": [
          "tgn:2016363",
          "tgn:1000001",
          "tgn:7012149",
          "tgn:2000224",
          "tgn:7007158",
          "tgn:7029392"
        ],
        "placetype": [
          "aat:300008347"
        ],
        "id": 2016363,
        "name:xx": "Stringtown"
      }
    },
    {
      "geometry": {
        "type": "Point",
        "coordinates": [
          -102.1833,
          38.4667
        ]
      },
      "type": "Feature",
      "properties": {
        "hierarchy": [
          "tgn:2016364",
          "tgn:1000001",
          "tgn:7012149",
          "tgn:2000222",
          "tgn:7007158",
          "tgn:7029392"
        ],
        "placetype": [
          "aat:300387016"
        ],
        "id": 2016364,
        "name:xx": "Stuart"
      }
    },
    {
      "geometry": {
        "type": "Point",
        "coordinates": [
          -103.65,
          38.2167
        ]
      },
      "type": "Feature",
      "properties": {
        "hierarchy": [
          "tgn:2016365",
          "tgn:1000001",
          "tgn:7012149",
          "tgn:2000204",
          "tgn:7007158",
          "tgn:7029392"
        ],
        "placetype": [
          "aat:300008347"
        ],
        "id": 2016365,
        "name:xx": "Sugar City"
      }
    },
    {
      "geometry": {
        "type": "Point",
        "coordinates": [
          -106.1,
          37.5667
        ]
      },
      "type": "Feature",
      "properties": {
        "hierarchy": [
          "tgn:2016367",
          "tgn:1000001",
          "tgn:7012149",
          "tgn:7007158",
          "tgn:2000244",
          "tgn:7029392"
        ],
        "placetype": [
          "aat:300387016"
        ],
        "id": 2016367,
        "name:xx": "Sugar Junction"
      }
    },
    {
      "geometry": {
        "type": "Point",
        "coordinates": [
          -105.4,
          40.0167
        ]
      },
      "type": "Feature",
      "properties": {
        "hierarchy": [
          "tgn:2016368",
          "tgn:1000001",
          "tgn:2000198",
          "tgn:7012149",
          "tgn:7007158",
          "tgn:7029392"
        ],
        "placetype": [
          "aat:300008347"
        ],
        "id": 2016368,
        "name:xx": "Sugarloaf"
      }
    }
  ]
}
