{
  "geometry": {
    "type": "Point",
    "coordinates": [
      12.8167,
      47.2333
    ]
  },
  "type": "Feature",
  "properties": {
    "hierarchy": [
      "tgn:1025554",
      "tgn:7003027",
      "tgn:1000003",
      "tgn:1000062",
      "tgn:7029392"
    ],
    "placetype": [
      "aat:300008347"
    ],
    "id": 1025554,
    "name:xx": "Fusch"
  }
}
