{
  "type": "FeatureCollection",
  "features": [
    {
      "geometry": {
        "type": "Point",
        "coordinates": [
          -62.8333,
          67
        ]
      },
      "type": "Feature",
      "properties": {
        "hierarchy": [
          "tgn:1008491",
          "tgn:7005685",
          "tgn:1000001",
          "tgn:1000296",
          "tgn:7029392"
        ],
        "placetype": [
          "aat:300008791"
        ],
        "id": 1008491,
        "name:xx": "Padloping Island"
      }
    },
    {
      "geometry": {
        "type": "Point",
        "coordinates": [
          15,
          44.5
        ]
      },
      "type": "Feature",
      "properties": {
        "hierarchy": [
          "tgn:1008494",
          "tgn:7017300",
          "tgn:1000003",
          "tgn:7006663",
          "tgn:7029392"
        ],
        "placetype": [
          "aat:300008791"
        ],
        "id": 1008494,
        "name:xx": "Pag"
      }
    },
    {
      "geometry": {
        "type": "Point",
        "coordinates": [
          121.7833,
          13.9
        ]
      },
      "type": "Feature",
      "properties": {
        "hierarchy": [
          "tgn:1008498",
          "tgn:1000004",
          "tgn:1001496",
          "tgn:1000135",
          "tgn:7029392"
        ],
        "placetype": [
          "aat:300008791"
        ],
        "id": 1008498,
        "name:xx": "Pagbilao Grande Island"
      }
    },
    {
      "geometry": {
        "type": "Point",
        "coordinates": [
          -43.0833,
          -22.9833
        ]
      },
      "type": "Feature",
      "properties": {
        "hierarchy": [
          "tgn:1008499",
          "tgn:1001942",
          "tgn:1000047",
          "tgn:7002457",
          "tgn:1000002",
          "tgn:7029392"
        ],
        "placetype": [
          "aat:300008791"
        ],
        "id": 1008499,
        "name:xx": "Pai, Ilha do"
      }
    }
  ]
}
