{
  "geometry": {
    "type": "Point",
    "coordinates": [
      -90.9833,
      42.6833
    ]
  },
  "type": "Feature",
  "properties": {
    "hierarchy": [
      "tgn:2278868",
      "tgn:1000001",
      "tgn:2000582",
      "tgn:7012149",
      "tgn:7007253",
      "tgn:7029392"
    ],
    "placetype": [
      "aat:300008680"
    ],
    "id": 2278868,
    "name:xx": "Dead Lake"
  }
}
