{
  "geometry": {
    "type": "Point",
    "coordinates": [
      -93.0833,
      48.3333
    ]
  },
  "type": "Feature",
  "properties": {
    "hierarchy": [
      "tgn:2457116",
      "tgn:1000001",
      "tgn:7012149",
      "tgn:7007521",
      "tgn:7029392"
    ],
    "placetype": [
      "aat:300008680"
    ],
    "id": 2457116,
    "name:xx": "Little Lake"
  }
}
