{
  "geometry": {
    "type": "Point",
    "coordinates": [
      10.966667,
      52.05
    ]
  },
  "type": "Feature",
  "properties": {
    "hierarchy": [
      "tgn:7175420",
      "tgn:1000003",
      "tgn:7594165",
      "tgn:7000084",
      "tgn:7029392"
    ],
    "placetype": [
      "aat:300055621"
    ],
    "id": 7175420,
    "name:xx": "Große Wiese"
  }
}
