{
  "geometry": {
    "type": "Point",
    "coordinates": [
      22.15,
      38.65
    ]
  },
  "type": "Feature",
  "properties": {
    "hierarchy": [
      "tgn:7228368",
      "tgn:4003773",
      "tgn:7001395",
      "tgn:1000003",
      "tgn:1000074",
      "tgn:7029392"
    ],
    "placetype": [
      "aat:300008795"
    ],
    "id": 7228368,
    "name:xx": "Kokkiniás"
  }
}
