{
  "type": "FeatureCollection",
  "features": [
    {
      "geometry": {
        "type": "Point",
        "coordinates": [
          -5.383333,
          56.95
        ]
      },
      "type": "Feature",
      "properties": {
        "hierarchy": [
          "tgn:7458040",
          "tgn:7002444",
          "tgn:1000003",
          "tgn:7008082",
          "tgn:7008591",
          "tgn:7029392"
        ],
        "placetype": [
          "aat:300008761"
        ],
        "name:en": "Pean, Glen",
        "id": 7458040
      }
    },
    {
      "geometry": {
        "type": "Point",
        "coordinates": [
          -0.266667,
          52.633333
        ]
      },
      "type": "Feature",
      "properties": {
        "hierarchy": [
          "tgn:7458041",
          "tgn:7002445",
          "tgn:1000003",
          "tgn:7026520",
          "tgn:7008591",
          "tgn:7029392"
        ],
        "placetype": [
          "aat:300008347"
        ],
        "name:en": "Peakirk",
        "id": 7458041
      }
    },
    {
      "geometry": {
        "type": "Point",
        "coordinates": [
          -1.866667,
          53.283333
        ]
      },
      "type": "Feature",
      "properties": {
        "hierarchy": [
          "tgn:7458042",
          "tgn:7002445",
          "tgn:1000003",
          "tgn:7008118",
          "tgn:7008591",
          "tgn:7029392"
        ],
        "placetype": [
          "aat:300007783"
        ],
        "name:en": "Peak Forest Station",
        "id": 7458042
      }
    },
    {
      "geometry": {
        "type": "Point",
        "coordinates": [
          -1.8,
          53.416667
        ]
      },
      "type": "Feature",
      "properties": {
        "hierarchy": [
          "tgn:7458045",
          "tgn:7002445",
          "tgn:1000003",
          "tgn:7008118",
          "tgn:7008591",
          "tgn:7029392"
        ],
        "placetype": [
          "aat:300055621"
        ],
        "name:en": "Peak District",
        "id": 7458045
      }
    },
    {
      "geometry": {
        "type": "Point",
        "coordinates": [
          -2.116667,
          55.766667
        ]
      },
      "type": "Feature",
      "properties": {
        "hierarchy": [
          "tgn:7458048",
          "tgn:7002444",
          "tgn:1000003",
          "tgn:7008072",
          "tgn:7008591",
          "tgn:7029392"
        ],
        "placetype": [
          "aat:300387502"
        ],
        "name:en": "Paxton House",
        "id": 7458048
      }
    },
    {
      "geometry": {
        "type": "Point",
        "coordinates": [
          -2.1,
          55.766667
        ]
      },
      "type": "Feature",
      "properties": {
        "hierarchy": [
          "tgn:7458049",
          "tgn:7002444",
          "tgn:1000003",
          "tgn:7008072",
          "tgn:7008591",
          "tgn:7029392"
        ],
        "placetype": [
          "aat:300008347"
        ],
        "name:en": "Paxton",
        "id": 7458049
      }
    }
  ]
}
