{
  "geometry": {
    "type": "Point",
    "coordinates": [
      -96.0667,
      30.5833
    ]
  },
  "type": "Feature",
  "properties": {
    "hierarchy": [
      "tgn:2103123",
      "tgn:1000001",
      "tgn:7012149",
      "tgn:1002429",
      "tgn:7007826",
      "tgn:7029392"
    ],
    "placetype": [
      "aat:300008347"
    ],
    "id": 2103123,
    "name:xx": "Carlos"
  }
}
