{
  "geometry": {
    "type": "Point",
    "coordinates": [
      -81.5667,
      29.7833
    ]
  },
  "type": "Feature",
  "properties": {
    "hierarchy": [
      "tgn:2332126",
      "tgn:1000001",
      "tgn:7012149",
      "tgn:2000282",
      "tgn:7007240",
      "tgn:7029392"
    ],
    "placetype": [
      "aat:300008850"
    ],
    "id": 2332126,
    "name:xx": "Flint Point"
  }
}
