{
  "type": "FeatureCollection",
  "features": [
    {
      "geometry": {
        "type": "Point",
        "coordinates": [
          4.8,
          51.966667
        ]
      },
      "type": "Feature",
      "properties": {
        "hierarchy": [
          "tgn:7271310",
          "tgn:1000003",
          "tgn:7003632",
          "tgn:7016845",
          "tgn:7029392"
        ],
        "placetype": [
          "aat:300008347"
        ],
        "name:nl": "Schoonouwen",
        "id": 7271310
      }
    },
    {
      "geometry": {
        "type": "Point",
        "coordinates": [
          6.75,
          52.85
        ]
      },
      "type": "Feature",
      "properties": {
        "hierarchy": [
          "tgn:7271311",
          "tgn:7003614",
          "tgn:1000003",
          "tgn:7016845",
          "tgn:7029392"
        ],
        "placetype": [
          "aat:300008347"
        ],
        "name:nl": "Schoonoord",
        "id": 7271311
      }
    },
    {
      "geometry": {
        "type": "Point",
        "coordinates": [
          6.7,
          52.883333
        ]
      },
      "type": "Feature",
      "properties": {
        "hierarchy": [
          "tgn:7271312",
          "tgn:7003614",
          "tgn:1000003",
          "tgn:7016845",
          "tgn:7029392"
        ],
        "placetype": [
          "aat:300008187"
        ],
        "name:nl": "Boswachterij Schoonloo",
        "id": 7271312
      }
    },
    {
      "geometry": {
        "type": "Point",
        "coordinates": [
          6.716667,
          52.883333
        ]
      },
      "type": "Feature",
      "properties": {
        "hierarchy": [
          "tgn:7271313",
          "tgn:7003614",
          "tgn:1000003",
          "tgn:7016845",
          "tgn:7029392"
        ],
        "placetype": [
          "aat:300387200"
        ],
        "name:nl": "Schoonloërveld",
        "id": 7271313
      }
    },
    {
      "geometry": {
        "type": "Point",
        "coordinates": [
          6.7,
          52.9
        ]
      },
      "type": "Feature",
      "properties": {
        "hierarchy": [
          "tgn:7271314",
          "tgn:7003614",
          "tgn:1000003",
          "tgn:7016845",
          "tgn:7029392"
        ],
        "placetype": [
          "aat:300008347"
        ],
        "name:nl": "Schoonlo",
        "id": 7271314
      }
    },
    {
      "geometry": {
        "type": "Point",
        "coordinates": [
          6.333333,
          52.366667
        ]
      },
      "type": "Feature",
      "properties": {
        "hierarchy": [
          "tgn:7271317",
          "tgn:1000003",
          "tgn:7003626",
          "tgn:7016845",
          "tgn:7029392"
        ],
        "placetype": [
          "aat:300386887"
        ],
        "name:nl": "Schoonheterheide",
        "id": 7271317
      }
    },
    {
      "geometry": {
        "type": "Point",
        "coordinates": [
          6.3,
          52.35
        ]
      },
      "type": "Feature",
      "properties": {
        "hierarchy": [
          "tgn:7271318",
          "tgn:1000003",
          "tgn:7003626",
          "tgn:7016845",
          "tgn:7029392"
        ],
        "placetype": [
          "aat:300008347"
        ],
        "name:nl": "Schoonheten",
        "id": 7271318
      }
    },
    {
      "geometry": {
        "type": "Point",
        "coordinates": [
          6.283333,
          52.35
        ]
      },
      "type": "Feature",
      "properties": {
        "hierarchy": [
          "tgn:7271319",
          "tgn:1000003",
          "tgn:7003626",
          "tgn:7016845",
          "tgn:7029392"
        ],
        "placetype": [
          "aat:300008863"
        ],
        "name:nl": "Schoonheten",
        "id": 7271319
      }
    }
  ]
}
