{
  "geometry": {
    "type": "Point",
    "coordinates": [
      -101.7167,
      41.7167
    ]
  },
  "type": "Feature",
  "properties": {
    "hierarchy": [
      "tgn:2392829",
      "tgn:2001318",
      "tgn:1000001",
      "tgn:7012149",
      "tgn:7007525",
      "tgn:7029392"
    ],
    "placetype": [
      "aat:300386845"
    ],
    "id": 2392829,
    "name:xx": "Hobin Valley"
  }
}
