{
  "geometry": {
    "type": "Point",
    "coordinates": [
      -71.7833,
      42.3667
    ]
  },
  "type": "Feature",
  "properties": {
    "hierarchy": [
      "tgn:2717498",
      "tgn:1000001",
      "tgn:7012149",
      "tgn:1003038",
      "tgn:7007517",
      "tgn:7029392"
    ],
    "placetype": [
      "aat:300132316"
    ],
    "id": 2717498,
    "name:xx": "Thomas Basin"
  }
}
