{
  "geometry": {
    "type": "Point",
    "coordinates": [
      -38.1667,
      -6.95
    ]
  },
  "type": "Feature",
  "properties": {
    "hierarchy": [
      "tgn:1022826",
      "tgn:7005439",
      "tgn:1000047",
      "tgn:7002455",
      "tgn:1000002",
      "tgn:7029392"
    ],
    "placetype": [
      "aat:300008347"
    ],
    "id": 1022826,
    "name:xx": "São José de Lagoa Tapada"
  }
}
