{
  "geometry": {
    "type": "Point",
    "coordinates": [
      75.2333,
      37.7833
    ]
  },
  "type": "Feature",
  "properties": {
    "hierarchy": [
      "tgn:7016633",
      "tgn:1000004",
      "tgn:7001745",
      "tgn:1000111",
      "tgn:7029392"
    ],
    "placetype": [
      "aat:300008347"
    ],
    "id": 7016633,
    "name:xx": "Taxkorgan"
  }
}
