{
  "geometry": {
    "type": "Point",
    "coordinates": [
      -108.233333,
      27.25
    ]
  },
  "type": "Feature",
  "properties": {
    "hierarchy": [
      "tgn:7428447",
      "tgn:7005581",
      "tgn:1000001",
      "tgn:7005560",
      "tgn:7029392"
    ],
    "placetype": [
      "aat:300007783"
    ],
    "id": 7428447,
    "name:xx": "Estación Temores"
  }
}
