{
  "geometry": {
    "type": "Point",
    "coordinates": [
      -81.4667,
      27.5833
    ]
  },
  "type": "Feature",
  "properties": {
    "hierarchy": [
      "tgn:2133937",
      "tgn:1000001",
      "tgn:1002477",
      "tgn:7012149",
      "tgn:7007240",
      "tgn:7029392"
    ],
    "placetype": [
      "aat:300008680"
    ],
    "id": 2133937,
    "name:xx": "Angelo, Lake"
  }
}
