{
  "geometry": {
    "type": "Point",
    "coordinates": [
      -97.35,
      33.4333
    ]
  },
  "type": "Feature",
  "properties": {
    "hierarchy": [
      "tgn:2142347",
      "tgn:1000001",
      "tgn:7012149",
      "tgn:2001964",
      "tgn:7007826",
      "tgn:7029392"
    ],
    "placetype": [
      "aat:300266640"
    ],
    "id": 2142347,
    "name:xx": "Backbone, The"
  }
}
