{
  "type": "FeatureCollection",
  "features": [
    {
      "geometry": {
        "type": "Point",
        "coordinates": [
          2.666,
          42.166
        ]
      },
      "type": "Feature",
      "properties": {
        "hierarchy": [
          "tgn:7002820",
          "tgn:7030216",
          "tgn:1000003",
          "tgn:1000095",
          "tgn:7029392"
        ],
        "placetype": [
          "aat:300387145",
          "aat:300000774"
        ],
        "id": 7002820,
        "name:xx": "Girona"
      }
    },
    {
      "geometry": {
        "type": "Point",
        "coordinates": [
          -3.25,
          37.25
        ]
      },
      "type": "Feature",
      "properties": {
        "hierarchy": [
          "tgn:7002821",
          "tgn:7002758",
          "tgn:1000003",
          "tgn:1000095",
          "tgn:7029392"
        ],
        "placetype": [
          "aat:300387145",
          "aat:300000774"
        ],
        "id": 7002821,
        "name:xx": "Granada"
      }
    },
    {
      "geometry": {
        "type": "Point",
        "coordinates": [
          -2.5,
          40.833
        ]
      },
      "type": "Feature",
      "properties": {
        "hierarchy": [
          "tgn:7002822",
          "tgn:1001647",
          "tgn:1000003",
          "tgn:1000095",
          "tgn:7029392"
        ],
        "placetype": [
          "aat:300387145",
          "aat:300000774"
        ],
        "id": 7002822,
        "name:xx": "Guadalajara"
      }
    },
    {
      "geometry": {
        "type": "Point",
        "coordinates": [
          -7,
          37.666
        ]
      },
      "type": "Feature",
      "properties": {
        "hierarchy": [
          "tgn:7002823",
          "tgn:7002758",
          "tgn:1000003",
          "tgn:1000095",
          "tgn:7029392"
        ],
        "placetype": [
          "aat:300387145",
          "aat:300000774"
        ],
        "id": 7002823,
        "name:xx": "Huelva"
      }
    },
    {
      "geometry": {
        "type": "Point",
        "coordinates": [
          -8.4,
          43.3667
        ]
      },
      "type": "Feature",
      "properties": {
        "hierarchy": [
          "tgn:7002824",
          "tgn:1000003",
          "tgn:7002786",
          "tgn:1000095",
          "tgn:7029392"
        ],
        "placetype": [
          "aat:300387145",
          "aat:300000774"
        ],
        "id": 7002824,
        "name:xx": "Coruña, A"
      }
    },
    {
      "geometry": {
        "type": "Point",
        "coordinates": [
          -14.25,
          28.4167
        ]
      },
      "type": "Feature",
      "properties": {
        "hierarchy": [
          "tgn:7002825",
          "tgn:7016622",
          "tgn:1000003",
          "tgn:1000095",
          "tgn:7029392"
        ],
        "placetype": [
          "aat:300387145",
          "aat:300000774"
        ],
        "id": 7002825,
        "name:xx": "Palmas, Las"
      }
    },
    {
      "geometry": {
        "type": "Point",
        "coordinates": [
          -6,
          42.666
        ]
      },
      "type": "Feature",
      "properties": {
        "hierarchy": [
          "tgn:7002826",
          "tgn:7001158",
          "tgn:1000003",
          "tgn:1000095",
          "tgn:7029392"
        ],
        "placetype": [
          "aat:300387145",
          "aat:300000774"
        ],
        "id": 7002826,
        "name:xx": "León"
      }
    },
    {
      "geometry": {
        "type": "Point",
        "coordinates": [
          -2.45,
          42.4667
        ]
      },
      "type": "Feature",
      "properties": {
        "hierarchy": [
          "tgn:7002827",
          "tgn:1000003",
          "tgn:7002789",
          "tgn:1000095",
          "tgn:7029392"
        ],
        "placetype": [
          "aat:300387145",
          "aat:300000774"
        ],
        "id": 7002827,
        "name:xx": "Rioja, La"
      }
    },
    {
      "geometry": {
        "type": "Point",
        "coordinates": [
          -7.5,
          43
        ]
      },
      "type": "Feature",
      "properties": {
        "hierarchy": [
          "tgn:7002829",
          "tgn:1000003",
          "tgn:7002786",
          "tgn:1000095",
          "tgn:7029392"
        ],
        "placetype": [
          "aat:300387145",
          "aat:300000774"
        ],
        "id": 7002829,
        "name:xx": "Lugo"
      }
    }
  ]
}
