{
  "geometry": {
    "type": "Point",
    "coordinates": [
      -112.3667,
      46.4333
    ]
  },
  "type": "Feature",
  "properties": {
    "hierarchy": [
      "tgn:2495167",
      "tgn:1000001",
      "tgn:7012149",
      "tgn:2001298",
      "tgn:7007524",
      "tgn:7029392"
    ],
    "placetype": [
      "aat:300008706"
    ],
    "id": 2495167,
    "name:xx": "Mary Ann Creek"
  }
}
