{
  "geometry": {
    "type": "Point",
    "coordinates": [
      41.7833,
      19.4667
    ]
  },
  "type": "Feature",
  "properties": {
    "hierarchy": [
      "tgn:1084906",
      "tgn:7000679",
      "tgn:7003866",
      "tgn:1000004",
      "tgn:1000137",
      "tgn:7029392"
    ],
    "placetype": [
      "aat:300008347"
    ],
    "id": 1084906,
    "name:xx": "Rawḥah"
  }
}
