{
  "type": "FeatureCollection",
  "features": [
    {
      "geometry": {
        "type": "Point",
        "coordinates": [
          -5.816667,
          41.116667
        ]
      },
      "type": "Feature",
      "properties": {
        "hierarchy": [
          "tgn:7339920",
          "tgn:7002835",
          "tgn:7001158",
          "tgn:1000003",
          "tgn:1000095",
          "tgn:7029392"
        ],
        "placetype": [
          "aat:300008347"
        ],
        "id": 7339920,
        "name:xx": "El Arco"
      }
    },
    {
      "geometry": {
        "type": "Point",
        "coordinates": [
          -6,
          37.483333
        ]
      },
      "type": "Feature",
      "properties": {
        "hierarchy": [
          "tgn:7339921",
          "tgn:7002758",
          "tgn:7002841",
          "tgn:1000003",
          "tgn:1000095",
          "tgn:7029392"
        ],
        "placetype": [
          "aat:300008347"
        ],
        "id": 7339921,
        "name:xx": "El Aral"
      }
    },
    {
      "geometry": {
        "type": "Point",
        "coordinates": [
          -5.35,
          42.7
        ]
      },
      "type": "Feature",
      "properties": {
        "hierarchy": [
          "tgn:7339923",
          "tgn:7002826",
          "tgn:7001158",
          "tgn:1000003",
          "tgn:1000095",
          "tgn:7029392"
        ],
        "placetype": [
          "aat:300008699"
        ],
        "id": 7339923,
        "name:xx": "Curueño, Río"
      }
    },
    {
      "geometry": {
        "type": "Point",
        "coordinates": [
          -5.983333,
          42.833333
        ]
      },
      "type": "Feature",
      "properties": {
        "hierarchy": [
          "tgn:7339924",
          "tgn:7002826",
          "tgn:7001158",
          "tgn:1000003",
          "tgn:1000095",
          "tgn:7029392"
        ],
        "placetype": [
          "aat:300008347"
        ],
        "id": 7339924,
        "name:xx": "Curueña"
      }
    },
    {
      "geometry": {
        "type": "Point",
        "coordinates": [
          -8.133333,
          43.133333
        ]
      },
      "type": "Feature",
      "properties": {
        "hierarchy": [
          "tgn:7339925",
          "tgn:7002824",
          "tgn:1000003",
          "tgn:7002786",
          "tgn:1000095",
          "tgn:7029392"
        ],
        "placetype": [
          "aat:300007783"
        ],
        "id": 7339925,
        "name:xx": "Estación de Curtis"
      }
    },
    {
      "geometry": {
        "type": "Point",
        "coordinates": [
          -1.6,
          40.233333
        ]
      },
      "type": "Feature",
      "properties": {
        "hierarchy": [
          "tgn:7339928",
          "tgn:7002759",
          "tgn:7002843",
          "tgn:1000003",
          "tgn:1000095",
          "tgn:7029392"
        ],
        "placetype": [
          "aat:300008699"
        ],
        "id": 7339928,
        "name:xx": "Currucán, Barranco del"
      }
    },
    {
      "geometry": {
        "type": "Point",
        "coordinates": [
          -7.166667,
          42.916667
        ]
      },
      "type": "Feature",
      "properties": {
        "hierarchy": [
          "tgn:7339929",
          "tgn:7002829",
          "tgn:1000003",
          "tgn:7002786",
          "tgn:1000095",
          "tgn:7029392"
        ],
        "placetype": [
          "aat:300008347"
        ],
        "id": 7339929,
        "name:xx": "Curro"
      }
    }
  ]
}
