{
  "geometry": {
    "type": "Point",
    "coordinates": [
      -94.6333,
      47.8833
    ]
  },
  "type": "Feature",
  "properties": {
    "hierarchy": [
      "tgn:2689294",
      "tgn:2001002",
      "tgn:1000001",
      "tgn:7012149",
      "tgn:7007521",
      "tgn:7029392"
    ],
    "placetype": [
      "aat:300008706"
    ],
    "id": 2689294,
    "name:xx": "Squaw Creek"
  }
}
