{
  "geometry": {
    "type": "Point",
    "coordinates": [
      26.8667,
      52.5833
    ]
  },
  "type": "Feature",
  "properties": {
    "hierarchy": [
      "tgn:1051431",
      "tgn:1003357",
      "tgn:1000003",
      "tgn:7006657",
      "tgn:7029392"
    ],
    "placetype": [
      "aat:300008347"
    ],
    "id": 1051431,
    "name:xx": "Čučeviči"
  }
}
