{
  "geometry": {
    "type": "Point",
    "coordinates": [
      -88.7167,
      37.4667
    ]
  },
  "type": "Feature",
  "properties": {
    "hierarchy": [
      "tgn:2425359",
      "tgn:1000001",
      "tgn:7012149",
      "tgn:2000523",
      "tgn:7007251",
      "tgn:7029392"
    ],
    "placetype": [
      "aat:300266640"
    ],
    "id": 2425359,
    "name:xx": "Johnson Ridge"
  }
}
