{
  "geometry": {
    "type": "Point",
    "coordinates": [
      26.7667,
      40.7667
    ]
  },
  "type": "Feature",
  "properties": {
    "hierarchy": [
      "tgn:1086515",
      "tgn:7001285",
      "tgn:1000004",
      "tgn:7018450",
      "tgn:1000144",
      "tgn:7029392"
    ],
    "placetype": [
      "aat:300008347"
    ],
    "id": 1086515,
    "name:xx": "Kadıköy"
  }
}
