{
  "geometry": {
    "type": "Point",
    "coordinates": [
      -109.4667,
      44.7333
    ]
  },
  "type": "Feature",
  "properties": {
    "hierarchy": [
      "tgn:2685933",
      "tgn:1000001",
      "tgn:7012149",
      "tgn:2002379",
      "tgn:7007923",
      "tgn:7029392"
    ],
    "placetype": [
      "aat:300008699"
    ],
    "id": 2685933,
    "name:xx": "Spring Branch"
  }
}
