{
  "geometry": {
    "type": "Point",
    "coordinates": [
      -108.2167,
      35.1167
    ]
  },
  "type": "Feature",
  "properties": {
    "hierarchy": [
      "tgn:2127851",
      "tgn:1000001",
      "tgn:2001431",
      "tgn:7012149",
      "tgn:7007566",
      "tgn:7029392"
    ],
    "placetype": [
      "aat:300008697"
    ],
    "id": 2127851,
    "name:xx": "Alamosa Spring"
  }
}
