{
  "geometry": {
    "type": "Point",
    "coordinates": [
      30.05,
      28.483333
    ]
  },
  "type": "Feature",
  "properties": {
    "hierarchy": [
      "tgn:7527796",
      "tgn:7001242",
      "tgn:7016833",
      "tgn:1001088",
      "tgn:7029392"
    ],
    "placetype": [
      "aat:300008777"
    ],
    "name:en": "Sîh el-Ghazâl",
    "id": 7527796
  }
}
