{
  "type": "FeatureCollection",
  "features": [
    {
      "geometry": {
        "type": "Point",
        "coordinates": [
          11.45,
          44.216667
        ]
      },
      "type": "Feature",
      "properties": {
        "hierarchy": [
          "tgn:7048620",
          "tgn:7003127",
          "tgn:1000003",
          "tgn:7008516",
          "tgn:1000080",
          "tgn:7029392"
        ],
        "placetype": [
          "aat:300008347"
        ],
        "id": 7048620,
        "name:xx": "Giugnola"
      }
    },
    {
      "geometry": {
        "type": "Point",
        "coordinates": [
          18.366667,
          40.083333
        ]
      },
      "type": "Feature",
      "properties": {
        "hierarchy": [
          "tgn:7048622",
          "tgn:1003468",
          "tgn:1000003",
          "tgn:7010380",
          "tgn:1000080",
          "tgn:7029392"
        ],
        "placetype": [
          "aat:300008347"
        ],
        "id": 7048622,
        "name:xx": "Giuggianello"
      }
    },
    {
      "geometry": {
        "type": "Point",
        "coordinates": [
          12.316667,
          45.433333
        ]
      },
      "type": "Feature",
      "properties": {
        "hierarchy": [
          "tgn:7048623",
          "tgn:7003006",
          "tgn:1000003",
          "tgn:7002997",
          "tgn:1000080",
          "tgn:7029392"
        ],
        "placetype": [
          "aat:300006075"
        ],
        "id": 7048623,
        "name:xx": "Canale della Giudecca"
      }
    },
    {
      "geometry": {
        "type": "Point",
        "coordinates": [
          9.3,
          41.016667
        ]
      },
      "type": "Feature",
      "properties": {
        "hierarchy": [
          "tgn:7048624",
          "tgn:7015163",
          "tgn:1000003",
          "tgn:7003121",
          "tgn:1000080",
          "tgn:7029392"
        ],
        "placetype": [
          "aat:300008795"
        ],
        "id": 7048624,
        "name:xx": "Giucantinu, Monte"
      }
    },
    {
      "geometry": {
        "type": "Point",
        "coordinates": [
          12.5,
          41.983333
        ]
      },
      "type": "Feature",
      "properties": {
        "hierarchy": [
          "tgn:7048625",
          "tgn:7003138",
          "tgn:1000003",
          "tgn:7003080",
          "tgn:1000080",
          "tgn:7029392"
        ],
        "placetype": [
          "aat:300004792"
        ],
        "id": 7048625,
        "name:xx": "Castel Giubileo"
      }
    },
    {
      "geometry": {
        "type": "Point",
        "coordinates": [
          15.2,
          37.166667
        ]
      },
      "type": "Feature",
      "properties": {
        "hierarchy": [
          "tgn:7048627",
          "tgn:1000003",
          "tgn:7003122",
          "tgn:1000080",
          "tgn:7029392"
        ],
        "placetype": [
          "aat:300386846"
        ],
        "id": 7048627,
        "name:xx": "Girotta, Punta"
      }
    },
    {
      "geometry": {
        "type": "Point",
        "coordinates": [
          11.25,
          43.85
        ]
      },
      "type": "Feature",
      "properties": {
        "hierarchy": [
          "tgn:7048628",
          "tgn:7003163",
          "tgn:1000003",
          "tgn:7009760",
          "tgn:1000080",
          "tgn:7029392"
        ],
        "placetype": [
          "aat:300008795"
        ],
        "id": 7048628,
        "name:xx": "Giro, Poggio del"
      }
    }
  ]
}
