{
  "geometry": {
    "type": "Point",
    "coordinates": [
      -113.3333,
      37.45
    ]
  },
  "type": "Feature",
  "properties": {
    "hierarchy": [
      "tgn:2706967",
      "tgn:1000001",
      "tgn:7012149",
      "tgn:7007827",
      "tgn:7029392"
    ],
    "placetype": [
      "aat:300008798"
    ],
    "id": 2706967,
    "name:xx": "Swasey Mountain"
  }
}
