{
  "geometry": {
    "type": "Point",
    "coordinates": [
      -93.9833,
      35.6667
    ]
  },
  "type": "Feature",
  "properties": {
    "hierarchy": [
      "tgn:2642282",
      "tgn:1000001",
      "tgn:7016172",
      "tgn:2000121",
      "tgn:7012149",
      "tgn:7029392"
    ],
    "placetype": [
      "aat:300008697"
    ],
    "id": 2642282,
    "name:xx": "Sand Spring"
  }
}
