{
  "geometry": {
    "type": "Point",
    "coordinates": [
      -72.3667,
      43.4333
    ]
  },
  "type": "Feature",
  "properties": {
    "hierarchy": [
      "tgn:2756596",
      "tgn:1000001",
      "tgn:2001427",
      "tgn:7012149",
      "tgn:7007564",
      "tgn:7029392"
    ],
    "placetype": [
      "aat:300008798"
    ],
    "id": 2756596,
    "name:xx": "Wellmans Hill"
  }
}
