{
  "geometry": {
    "type": "Point",
    "coordinates": [
      -109.6333,
      47.7333
    ]
  },
  "type": "Feature",
  "properties": {
    "hierarchy": [
      "tgn:2564182",
      "tgn:1000001",
      "tgn:7012149",
      "tgn:2001273",
      "tgn:7007524",
      "tgn:7029392"
    ],
    "placetype": [
      "aat:300008791"
    ],
    "id": 2564182,
    "name:xx": "PN Island"
  }
}
