{
  "geometry": {
    "type": "Point",
    "coordinates": [
      -112.8167,
      42.9833
    ]
  },
  "type": "Feature",
  "properties": {
    "hierarchy": [
      "tgn:2483699",
      "tgn:1000001",
      "tgn:2000457",
      "tgn:7012149",
      "tgn:7007250",
      "tgn:7029392"
    ],
    "placetype": [
      "aat:300006075"
    ],
    "id": 2483699,
    "name:xx": "Lateral I"
  }
}
