{
  "geometry": {
    "type": "Point",
    "coordinates": [
      11.7833,
      -4.0333
    ]
  },
  "type": "Feature",
  "properties": {
    "hierarchy": [
      "tgn:1088639",
      "tgn:7001242",
      "tgn:1000996",
      "tgn:1000158",
      "tgn:7029392"
    ],
    "placetype": [
      "aat:300008347"
    ],
    "id": 1088639,
    "name:xx": "Ikalou"
  }
}
