{
  "geometry": {
    "type": "Point",
    "coordinates": [
      -78.8833,
      39.5667
    ]
  },
  "type": "Feature",
  "properties": {
    "hierarchy": [
      "tgn:7020701",
      "tgn:2000934",
      "tgn:1000001",
      "tgn:7012149",
      "tgn:7007516",
      "tgn:7029392"
    ],
    "placetype": [
      "aat:300008798"
    ],
    "id": 7020701,
    "name:xx": "Dans Mountain"
  }
}
