{
  "type": "FeatureCollection",
  "features": [
    {
      "geometry": {
        "type": "Point",
        "coordinates": [
          -10.1333,
          29.25
        ]
      },
      "type": "Feature",
      "properties": {
        "hierarchy": [
          "tgn:1003760",
          "tgn:7001242",
          "tgn:1000179",
          "tgn:7593686",
          "tgn:7029392"
        ],
        "placetype": [
          "aat:300387346"
        ],
        "id": 1003760,
        "name:xx": "Ifni"
      }
    },
    {
      "geometry": {
        "type": "Point",
        "coordinates": [
          25.129,
          27.791
        ]
      },
      "type": "Feature",
      "properties": {
        "hierarchy": [
          "tgn:1003763",
          "tgn:7001242",
          "tgn:7017583",
          "tgn:1000193",
          "tgn:7029392"
        ],
        "placetype": [
          "aat:300000206"
        ],
        "id": 1003763,
        "name:xx": "Kaffraria"
      }
    },
    {
      "geometry": {
        "type": "Point",
        "coordinates": [
          8.783333,
          49.15
        ]
      },
      "type": "Feature",
      "properties": {
        "hierarchy": [
          "tgn:1003769",
          "tgn:7003692",
          "tgn:1000003",
          "tgn:7000084",
          "tgn:7029392"
        ],
        "placetype": [
          "aat:300387346"
        ],
        "id": 1003769,
        "name:xx": "Kraichgau"
      }
    }
  ]
}
