{
  "type": "FeatureCollection",
  "features": [
    {
      "geometry": {
        "type": "Point",
        "coordinates": [
          -75.0667,
          38.7
        ]
      },
      "type": "Feature",
      "properties": {
        "hierarchy": [
          "tgn:2017970",
          "tgn:1002933",
          "tgn:1000001",
          "tgn:7012149",
          "tgn:7007239",
          "tgn:7029392"
        ],
        "placetype": [
          "aat:300008347"
        ],
        "id": 2017970,
        "name:xx": "Killens Addition"
      }
    },
    {
      "geometry": {
        "type": "Point",
        "coordinates": [
          -75.6833,
          39.5667
        ]
      },
      "type": "Feature",
      "properties": {
        "hierarchy": [
          "tgn:2017971",
          "tgn:7014201",
          "tgn:1000001",
          "tgn:7012149",
          "tgn:7007239",
          "tgn:7029392"
        ],
        "placetype": [
          "aat:300008347"
        ],
        "id": 2017971,
        "name:xx": "Kirkwood"
      }
    },
    {
      "geometry": {
        "type": "Point",
        "coordinates": [
          -75.4,
          39.1
        ]
      },
      "type": "Feature",
      "properties": {
        "hierarchy": [
          "tgn:2017973",
          "tgn:1002538",
          "tgn:1000001",
          "tgn:7012149",
          "tgn:7007239",
          "tgn:7029392"
        ],
        "placetype": [
          "aat:300008347"
        ],
        "id": 2017973,
        "name:xx": "Kitts Hummock"
      }
    },
    {
      "geometry": {
        "type": "Point",
        "coordinates": [
          -75.5333,
          38.55
        ]
      },
      "type": "Feature",
      "properties": {
        "hierarchy": [
          "tgn:2017976",
          "tgn:1002933",
          "tgn:1000001",
          "tgn:7012149",
          "tgn:7007239",
          "tgn:7029392"
        ],
        "placetype": [
          "aat:300008347",
          "aat:300387210"
        ],
        "id": 2017976,
        "name:xx": "Lake Pines"
      }
    },
    {
      "geometry": {
        "type": "Point",
        "coordinates": [
          -75.4833,
          39.8167
        ]
      },
      "type": "Feature",
      "properties": {
        "hierarchy": [
          "tgn:2017978",
          "tgn:7014201",
          "tgn:1000001",
          "tgn:7012149",
          "tgn:7007239",
          "tgn:7029392"
        ],
        "placetype": [
          "aat:300008347"
        ],
        "id": 2017978,
        "name:xx": "Lancashire"
      }
    },
    {
      "geometry": {
        "type": "Point",
        "coordinates": [
          -75.6,
          39.75
        ]
      },
      "type": "Feature",
      "properties": {
        "hierarchy": [
          "tgn:2017979",
          "tgn:7014201",
          "tgn:1000001",
          "tgn:7012149",
          "tgn:7007239",
          "tgn:7029392"
        ],
        "placetype": [
          "aat:300008347"
        ],
        "id": 2017979,
        "name:xx": "Lancaster Court"
      }
    }
  ]
}
