{
  "geometry": {
    "type": "Point",
    "coordinates": [
      -89.7167,
      34.3667
    ]
  },
  "type": "Feature",
  "properties": {
    "hierarchy": [
      "tgn:2748975",
      "tgn:1000001",
      "tgn:7012149",
      "tgn:2001139",
      "tgn:7007522",
      "tgn:7029392"
    ],
    "placetype": [
      "aat:300008347"
    ],
    "id": 2748975,
    "name:xx": "Wallace"
  }
}
