{
  "type": "FeatureCollection",
  "features": [
    {
      "geometry": {
        "type": "Point",
        "coordinates": [
          -80.0167,
          36.8667
        ]
      },
      "type": "Feature",
      "properties": {
        "hierarchy": [
          "tgn:2197580",
          "tgn:1000001",
          "tgn:7012149",
          "tgn:2002160",
          "tgn:7007919",
          "tgn:7029392"
        ],
        "placetype": [
          "aat:300008798"
        ],
        "id": 2197580,
        "name:xx": "Brown Hill"
      }
    },
    {
      "geometry": {
        "type": "Point",
        "coordinates": [
          -115.95,
          48.1167
        ]
      },
      "type": "Feature",
      "properties": {
        "hierarchy": [
          "tgn:2197581",
          "tgn:1000001",
          "tgn:7012149",
          "tgn:2001304",
          "tgn:7007524",
          "tgn:7029392"
        ],
        "placetype": [
          "aat:300000390"
        ],
        "id": 2197581,
        "name:xx": "Brown Hill Mine"
      }
    },
    {
      "geometry": {
        "type": "Point",
        "coordinates": [
          -87.4667,
          33.7333
        ]
      },
      "type": "Feature",
      "properties": {
        "hierarchy": [
          "tgn:2197582",
          "tgn:7002659",
          "tgn:1000001",
          "tgn:7012149",
          "tgn:2000063",
          "tgn:7029392"
        ],
        "placetype": [
          "aat:300008761"
        ],
        "id": 2197582,
        "name:xx": "Brown Hollow"
      }
    },
    {
      "geometry": {
        "type": "Point",
        "coordinates": [
          -87.2,
          34.5667
        ]
      },
      "type": "Feature",
      "properties": {
        "hierarchy": [
          "tgn:2197583",
          "tgn:7002659",
          "tgn:1000001",
          "tgn:7012149",
          "tgn:2000039",
          "tgn:7029392"
        ],
        "placetype": [
          "aat:300008761"
        ],
        "id": 2197583,
        "name:xx": "Brown Hollow"
      }
    },
    {
      "geometry": {
        "type": "Point",
        "coordinates": [
          -94.0167,
          35.8167
        ]
      },
      "type": "Feature",
      "properties": {
        "hierarchy": [
          "tgn:2197584",
          "tgn:1000001",
          "tgn:7016172",
          "tgn:7012149",
          "tgn:2000176",
          "tgn:7029392"
        ],
        "placetype": [
          "aat:300008761"
        ],
        "id": 2197584,
        "name:xx": "Brown Hollow"
      }
    },
    {
      "geometry": {
        "type": "Point",
        "coordinates": [
          -92.05,
          35.8833
        ]
      },
      "type": "Feature",
      "properties": {
        "hierarchy": [
          "tgn:2197585",
          "tgn:1000001",
          "tgn:7016172",
          "tgn:7012149",
          "tgn:2000173",
          "tgn:7029392"
        ],
        "placetype": [
          "aat:300008761"
        ],
        "id": 2197585,
        "name:xx": "Brown Hollow"
      }
    },
    {
      "geometry": {
        "type": "Point",
        "coordinates": [
          -92.7167,
          35.9667
        ]
      },
      "type": "Feature",
      "properties": {
        "hierarchy": [
          "tgn:2197586",
          "tgn:1000001",
          "tgn:7016172",
          "tgn:7012149",
          "tgn:2000169",
          "tgn:7029392"
        ],
        "placetype": [
          "aat:300008761"
        ],
        "id": 2197586,
        "name:xx": "Brown Hollow"
      }
    },
    {
      "geometry": {
        "type": "Point",
        "coordinates": [
          -93.4333,
          36.15
        ]
      },
      "type": "Feature",
      "properties": {
        "hierarchy": [
          "tgn:2197587",
          "tgn:1000001",
          "tgn:7016172",
          "tgn:2000112",
          "tgn:7012149",
          "tgn:7029392"
        ],
        "placetype": [
          "aat:300008761"
        ],
        "id": 2197587,
        "name:xx": "Brown Hollow"
      }
    },
    {
      "geometry": {
        "type": "Point",
        "coordinates": [
          -91.4833,
          36.45
        ]
      },
      "type": "Feature",
      "properties": {
        "hierarchy": [
          "tgn:2197588",
          "tgn:1000001",
          "tgn:7016172",
          "tgn:7012149",
          "tgn:2000129",
          "tgn:7029392"
        ],
        "placetype": [
          "aat:300008761"
        ],
        "id": 2197588,
        "name:xx": "Brown Hollow"
      }
    },
    {
      "geometry": {
        "type": "Point",
        "coordinates": [
          -91.2667,
          36.3833
        ]
      },
      "type": "Feature",
      "properties": {
        "hierarchy": [
          "tgn:2197589",
          "tgn:1000001",
          "tgn:7016172",
          "tgn:7012149",
          "tgn:2000165",
          "tgn:7029392"
        ],
        "placetype": [
          "aat:300008761"
        ],
        "id": 2197589,
        "name:xx": "Brown Hollow"
      }
    }
  ]
}
