{
  "geometry": {
    "type": "Point",
    "coordinates": [
      30.516667,
      25.283333
    ]
  },
  "type": "Feature",
  "properties": {
    "hierarchy": [
      "tgn:7536614",
      "tgn:7001242",
      "tgn:7016833",
      "tgn:7001334",
      "tgn:7029392"
    ],
    "placetype": [
      "aat:300006207"
    ],
    "name:en": "Bîr Ginah 2",
    "id": 7536614
  }
}
