{
  "geometry": {
    "type": "Point",
    "coordinates": [
      10.9667,
      47.5667
    ]
  },
  "type": "Feature",
  "properties": {
    "hierarchy": [
      "tgn:7012578",
      "tgn:7003669",
      "tgn:1000003",
      "tgn:7000084",
      "tgn:7029392"
    ],
    "placetype": [
      "aat:300006891"
    ],
    "id": 7012578,
    "name:xx": "Linderhof"
  }
}
