{
  "geometry": {
    "type": "Point",
    "coordinates": [
      -99.9833,
      48.8833
    ]
  },
  "type": "Feature",
  "properties": {
    "hierarchy": [
      "tgn:2161672",
      "tgn:1000001",
      "tgn:2001596",
      "tgn:7012149",
      "tgn:7007705",
      "tgn:7029392"
    ],
    "placetype": [
      "aat:300008680"
    ],
    "id": 2161672,
    "name:xx": "Belle Lake"
  }
}
