{
  "geometry": {
    "type": "Point",
    "coordinates": [
      -84.85,
      36.7833
    ]
  },
  "type": "Feature",
  "properties": {
    "hierarchy": [
      "tgn:2042055",
      "tgn:1000001",
      "tgn:7012149",
      "tgn:2000850",
      "tgn:7007255",
      "tgn:7029392"
    ],
    "placetype": [
      "aat:300008347"
    ],
    "id": 2042055,
    "name:xx": "Wray Gap"
  }
}
