{
  "geometry": {
    "type": "Point",
    "coordinates": [
      -111.4167,
      41.7167
    ]
  },
  "type": "Feature",
  "properties": {
    "hierarchy": [
      "tgn:2464313",
      "tgn:1000001",
      "tgn:2002103",
      "tgn:7012149",
      "tgn:7007827",
      "tgn:7029392"
    ],
    "placetype": [
      "aat:300008761"
    ],
    "id": 2464313,
    "name:xx": "Lodgepole Canyon"
  }
}
