{
  "geometry": {
    "type": "Point",
    "coordinates": [
      100.4667,
      5.3667
    ]
  },
  "type": "Feature",
  "properties": {
    "hierarchy": [
      "tgn:1082712",
      "tgn:7000317",
      "tgn:1000004",
      "tgn:7018057",
      "tgn:1000128",
      "tgn:7029392"
    ],
    "placetype": [
      "aat:300008347"
    ],
    "id": 1082712,
    "name:xx": "Bukit Mertajam"
  }
}
