{
  "geometry": {
    "type": "Point",
    "coordinates": [
      -92.9167,
      41.0667
    ]
  },
  "type": "Feature",
  "properties": {
    "hierarchy": [
      "tgn:2392470",
      "tgn:1000001",
      "tgn:7012149",
      "tgn:2000628",
      "tgn:7007253",
      "tgn:7029392"
    ],
    "placetype": [
      "aat:300000390"
    ],
    "id": 2392470,
    "name:xx": "Hiteman Mine Number 10"
  }
}
