{
  "geometry": {
    "type": "Point",
    "coordinates": [
      -119.7833,
      39.4833
    ]
  },
  "type": "Feature",
  "properties": {
    "hierarchy": [
      "tgn:2246887",
      "tgn:1000001",
      "tgn:7012149",
      "tgn:1002999",
      "tgn:7007526",
      "tgn:7029392"
    ],
    "placetype": [
      "aat:300006075"
    ],
    "id": 2246887,
    "name:xx": "Cochran Ditch"
  }
}
