{
  "type": "FeatureCollection",
  "features": [
    {
      "geometry": {
        "type": "Point",
        "coordinates": [
          -93.05,
          16.816667
        ]
      },
      "type": "Feature",
      "properties": {
        "hierarchy": [
          "tgn:7368200",
          "tgn:7005580",
          "tgn:1000001",
          "tgn:7005560",
          "tgn:7029392"
        ],
        "placetype": [
          "aat:300008347"
        ],
        "id": 7368200,
        "name:xx": "Iglesia Vieja"
      }
    },
    {
      "geometry": {
        "type": "Point",
        "coordinates": [
          -102.85,
          28.1
        ]
      },
      "type": "Feature",
      "properties": {
        "hierarchy": [
          "tgn:7368201",
          "tgn:7005581",
          "tgn:1000001",
          "tgn:7005560",
          "tgn:7029392"
        ],
        "placetype": [
          "aat:300008795"
        ],
        "id": 7368201,
        "name:xx": "Iglesias, Sierra de las"
      }
    },
    {
      "geometry": {
        "type": "Point",
        "coordinates": [
          -101.666667,
          24.316667
        ]
      },
      "type": "Feature",
      "properties": {
        "hierarchy": [
          "tgn:7368202",
          "tgn:1000001",
          "tgn:7005601",
          "tgn:7005560",
          "tgn:7029392"
        ],
        "placetype": [
          "aat:300008795"
        ],
        "id": 7368202,
        "name:xx": "Iglesias, Sierra de las"
      }
    },
    {
      "geometry": {
        "type": "Point",
        "coordinates": [
          -104.816667,
          19.216667
        ]
      },
      "type": "Feature",
      "properties": {
        "hierarchy": [
          "tgn:7368203",
          "tgn:7005586",
          "tgn:1000001",
          "tgn:7005560",
          "tgn:7029392"
        ],
        "placetype": [
          "aat:300008791"
        ],
        "id": 7368203,
        "name:xx": "Iglesias, Isla"
      }
    },
    {
      "geometry": {
        "type": "Point",
        "coordinates": [
          -106.616667,
          26.25
        ]
      },
      "type": "Feature",
      "properties": {
        "hierarchy": [
          "tgn:7368204",
          "tgn:7005581",
          "tgn:1000001",
          "tgn:7005560",
          "tgn:7029392"
        ],
        "placetype": [
          "aat:300008795"
        ],
        "id": 7368204,
        "name:xx": "Iglesias, Cerro las"
      }
    },
    {
      "geometry": {
        "type": "Point",
        "coordinates": [
          -100,
          28.016667
        ]
      },
      "type": "Feature",
      "properties": {
        "hierarchy": [
          "tgn:7368205",
          "tgn:1001853",
          "tgn:1000001",
          "tgn:7005560",
          "tgn:7029392"
        ],
        "placetype": [
          "aat:300266554",
          "aat:300008699"
        ],
        "id": 7368205,
        "name:xx": "Iglesias, Arroyo de las"
      }
    },
    {
      "geometry": {
        "type": "Point",
        "coordinates": [
          -101.35,
          27.583333
        ]
      },
      "type": "Feature",
      "properties": {
        "hierarchy": [
          "tgn:7368206",
          "tgn:1001853",
          "tgn:1000001",
          "tgn:7005560",
          "tgn:7029392"
        ],
        "placetype": [
          "aat:300008347"
        ],
        "id": 7368206,
        "name:xx": "Iglesias"
      }
    },
    {
      "geometry": {
        "type": "Point",
        "coordinates": [
          -104.966667,
          25.233333
        ]
      },
      "type": "Feature",
      "properties": {
        "hierarchy": [
          "tgn:7368207",
          "tgn:7005583",
          "tgn:1000001",
          "tgn:7005560",
          "tgn:7029392"
        ],
        "placetype": [
          "aat:300008347"
        ],
        "id": 7368207,
        "name:xx": "Iglesias"
      }
    },
    {
      "geometry": {
        "type": "Point",
        "coordinates": [
          -106.316667,
          24.466667
        ]
      },
      "type": "Feature",
      "properties": {
        "hierarchy": [
          "tgn:7368208",
          "tgn:7005583",
          "tgn:1000001",
          "tgn:7005560",
          "tgn:7029392"
        ],
        "placetype": [
          "aat:300008347"
        ],
        "id": 7368208,
        "name:xx": "Iglesias"
      }
    },
    {
      "geometry": {
        "type": "Point",
        "coordinates": [
          -102.233333,
          22.8
        ]
      },
      "type": "Feature",
      "properties": {
        "hierarchy": [
          "tgn:7368209",
          "tgn:1000001",
          "tgn:7005601",
          "tgn:7005560",
          "tgn:7029392"
        ],
        "placetype": [
          "aat:300008347"
        ],
        "id": 7368209,
        "name:xx": "Iglesias"
      }
    }
  ]
}
