{
  "geometry": {
    "type": "Point",
    "coordinates": [
      6.0833,
      50.0167
    ]
  },
  "type": "Feature",
  "properties": {
    "hierarchy": [
      "tgn:1047561",
      "tgn:7003531",
      "tgn:1000003",
      "tgn:7003514",
      "tgn:7029392"
    ],
    "placetype": [
      "aat:300008347"
    ],
    "id": 1047561,
    "name:xx": "Hosingen"
  }
}
