{
  "geometry": {
    "type": "Point",
    "coordinates": [
      -119.1833,
      38.85
    ]
  },
  "type": "Feature",
  "properties": {
    "hierarchy": [
      "tgn:2762078",
      "tgn:1000001",
      "tgn:1002614",
      "tgn:7012149",
      "tgn:7007526",
      "tgn:7029392"
    ],
    "placetype": [
      "aat:300006075"
    ],
    "id": 2762078,
    "name:xx": "West Side Canal"
  }
}
