{
  "geometry": {
    "type": "Point",
    "coordinates": [
      85.3833,
      55.8833
    ]
  },
  "type": "Feature",
  "properties": {
    "hierarchy": [
      "tgn:1137529",
      "tgn:1000004",
      "tgn:6003034",
      "tgn:7018214",
      "tgn:7002435",
      "tgn:7029392"
    ],
    "placetype": [
      "aat:300008347"
    ],
    "id": 1137529,
    "name:xx": "Yashkino"
  }
}
