{
  "geometry": {
    "type": "Point",
    "coordinates": [
      15.0833,
      60.5833
    ]
  },
  "type": "Feature",
  "properties": {
    "hierarchy": [
      "tgn:1063005",
      "tgn:1000403",
      "tgn:1000003",
      "tgn:1000097",
      "tgn:7029392"
    ],
    "placetype": [
      "aat:300008347"
    ],
    "id": 1063005,
    "name:xx": "Gagnef"
  }
}
