{
  "geometry": {
    "type": "Point",
    "coordinates": [
      22.5833,
      60.6167
    ]
  },
  "type": "Feature",
  "properties": {
    "hierarchy": [
      "tgn:1031267",
      "tgn:7024077",
      "tgn:1000003",
      "tgn:1000069",
      "tgn:7029392"
    ],
    "placetype": [
      "aat:300008347"
    ],
    "id": 1031267,
    "name:xx": "Aura"
  }
}
