{
  "type": "FeatureCollection",
  "features": [
    {
      "geometry": {
        "type": "Point",
        "coordinates": [
          -55.1667,
          48.05
        ]
      },
      "type": "Feature",
      "properties": {
        "hierarchy": [
          "tgn:1116750",
          "tgn:7005685",
          "tgn:7005807",
          "tgn:1000001",
          "tgn:7005801",
          "tgn:7029392"
        ],
        "placetype": [
          "aat:300008680"
        ],
        "id": 1116750,
        "name:xx": "Jubilee Lake"
      }
    },
    {
      "geometry": {
        "type": "Point",
        "coordinates": [
          -81.8,
          28.1167
        ]
      },
      "type": "Feature",
      "properties": {
        "hierarchy": [
          "tgn:1116751",
          "tgn:1000001",
          "tgn:7012149",
          "tgn:1002793",
          "tgn:7007240",
          "tgn:7029392"
        ],
        "placetype": [
          "aat:300008680"
        ],
        "id": 1116751,
        "name:xx": "Juliana, Lake"
      }
    },
    {
      "geometry": {
        "type": "Point",
        "coordinates": [
          -76.1,
          -11.0333
        ]
      },
      "type": "Feature",
      "properties": {
        "hierarchy": [
          "tgn:1116752",
          "tgn:1000654",
          "tgn:1000002",
          "tgn:1000056",
          "tgn:7029392"
        ],
        "placetype": [
          "aat:300008680"
        ],
        "id": 1116752,
        "name:xx": "Junín, Lago de"
      }
    },
    {
      "geometry": {
        "type": "Point",
        "coordinates": [
          13.083333,
          52.416667
        ]
      },
      "type": "Feature",
      "properties": {
        "hierarchy": [
          "tgn:1116754",
          "tgn:7000096",
          "tgn:1000003",
          "tgn:7000084",
          "tgn:7029392"
        ],
        "placetype": [
          "aat:300008680"
        ],
        "id": 1116754,
        "name:xx": "Jungfern-See"
      }
    },
    {
      "geometry": {
        "type": "Point",
        "coordinates": [
          -40.3,
          -19.5833
        ]
      },
      "type": "Feature",
      "properties": {
        "hierarchy": [
          "tgn:1116756",
          "tgn:7006389",
          "tgn:1000047",
          "tgn:7002457",
          "tgn:1000002",
          "tgn:7029392"
        ],
        "placetype": [
          "aat:300008680"
        ],
        "id": 1116756,
        "name:xx": "Juparanã, Lagoa"
      }
    }
  ]
}
