{
  "geometry": {
    "type": "Point",
    "coordinates": [
      -75.25,
      40.8833
    ]
  },
  "type": "Feature",
  "properties": {
    "hierarchy": [
      "tgn:2629710",
      "tgn:1000001",
      "tgn:7012149",
      "tgn:1002682",
      "tgn:7007710",
      "tgn:7029392"
    ],
    "placetype": [
      "aat:300008706"
    ],
    "id": 2629710,
    "name:xx": "Ross Common Creek"
  }
}
