{
  "type": "FeatureCollection",
  "features": [
    {
      "geometry": {
        "type": "Point",
        "coordinates": [
          10.883333,
          47.966667
        ]
      },
      "type": "Feature",
      "properties": {
        "hierarchy": [
          "tgn:4007610",
          "tgn:7003669",
          "tgn:1000003",
          "tgn:7000084",
          "tgn:7029392"
        ],
        "placetype": [
          "aat:300008347"
        ],
        "id": 4007610,
        "name:xx": "Mundraching"
      }
    },
    {
      "geometry": {
        "type": "Point",
        "coordinates": [
          -2.846678,
          43.355067
        ]
      },
      "type": "Feature",
      "properties": {
        "hierarchy": [
          "tgn:4007611",
          "tgn:7002849",
          "tgn:1000003",
          "tgn:7009604",
          "tgn:1000095",
          "tgn:7029392"
        ],
        "placetype": [
          "aat:300008347"
        ],
        "id": 4007611,
        "name:xx": "Munguía"
      }
    },
    {
      "geometry": {
        "type": "Point",
        "coordinates": [
          9.566667,
          54.8
        ]
      },
      "type": "Feature",
      "properties": {
        "hierarchy": [
          "tgn:4007612",
          "tgn:1000003",
          "tgn:7003688",
          "tgn:7000084",
          "tgn:7029392"
        ],
        "placetype": [
          "aat:300008347"
        ],
        "id": 4007612,
        "name:xx": "Munkbrarup"
      }
    },
    {
      "geometry": {
        "type": "Point",
        "coordinates": [
          1.6,
          47.4167
        ]
      },
      "type": "Feature",
      "properties": {
        "hierarchy": [
          "tgn:4007613",
          "tgn:1000003",
          "tgn:7002877",
          "tgn:1000070",
          "tgn:7029392"
        ],
        "placetype": [
          "aat:300008347"
        ],
        "id": 4007613,
        "name:xx": "Mur-de-Sologne"
      }
    }
  ]
}
