{
  "type": "FeatureCollection",
  "features": [
    {
      "geometry": {
        "type": "Point",
        "coordinates": [
          -75.6167,
          39.3
        ]
      },
      "type": "Feature",
      "properties": {
        "hierarchy": [
          "tgn:2468520",
          "tgn:1002538",
          "tgn:1000001",
          "tgn:7012149",
          "tgn:7007239",
          "tgn:7029392"
        ],
        "placetype": [
          "aat:300008347"
        ],
        "id": 2468520,
        "name:xx": "Long Point Landing"
      }
    },
    {
      "geometry": {
        "type": "Point",
        "coordinates": [
          -81.6,
          27.2667
        ]
      },
      "type": "Feature",
      "properties": {
        "hierarchy": [
          "tgn:2468521",
          "tgn:1000001",
          "tgn:7021603",
          "tgn:7012149",
          "tgn:7007240",
          "tgn:7029392"
        ],
        "placetype": [
          "aat:300008905"
        ],
        "id": 2468521,
        "name:xx": "Long Point Marsh"
      }
    },
    {
      "geometry": {
        "type": "Point",
        "coordinates": [
          -76.5,
          38.9
        ]
      },
      "type": "Feature",
      "properties": {
        "hierarchy": [
          "tgn:2468522",
          "tgn:7014651",
          "tgn:1000001",
          "tgn:7012149",
          "tgn:7007516",
          "tgn:7029392"
        ],
        "placetype": [
          "aat:300008905"
        ],
        "id": 2468522,
        "name:xx": "Long Point Marsh"
      }
    },
    {
      "geometry": {
        "type": "Point",
        "coordinates": [
          -70.2,
          42.0333
        ]
      },
      "type": "Feature",
      "properties": {
        "hierarchy": [
          "tgn:2468523",
          "tgn:1002165",
          "tgn:1000001",
          "tgn:7012149",
          "tgn:7007517",
          "tgn:7029392"
        ],
        "placetype": [
          "aat:300008905"
        ],
        "id": 2468523,
        "name:xx": "Long Point Marshes"
      }
    },
    {
      "geometry": {
        "type": "Point",
        "coordinates": [
          -108.5833,
          38.55
        ]
      },
      "type": "Feature",
      "properties": {
        "hierarchy": [
          "tgn:2468524",
          "tgn:1000001",
          "tgn:7012149",
          "tgn:2000230",
          "tgn:7007158",
          "tgn:7029392"
        ],
        "placetype": [
          "aat:300008798"
        ],
        "id": 2468524,
        "name:xx": "Long Point Mountain"
      }
    },
    {
      "geometry": {
        "type": "Point",
        "coordinates": [
          -111.15,
          39.2
        ]
      },
      "type": "Feature",
      "properties": {
        "hierarchy": [
          "tgn:2468525",
          "tgn:1000001",
          "tgn:2002108",
          "tgn:7012149",
          "tgn:7007827",
          "tgn:7029392"
        ],
        "placetype": [
          "aat:300006191"
        ],
        "id": 2468525,
        "name:xx": "Long Point Number 3 Reservoir"
      }
    },
    {
      "geometry": {
        "type": "Point",
        "coordinates": [
          -75.85,
          36.3
        ]
      },
      "type": "Feature",
      "properties": {
        "hierarchy": [
          "tgn:2468526",
          "tgn:1000001",
          "tgn:7012149",
          "tgn:1002312",
          "tgn:7007709",
          "tgn:7029392"
        ],
        "placetype": [
          "aat:300008680"
        ],
        "id": 2468526,
        "name:xx": "Long Point Pond"
      }
    },
    {
      "geometry": {
        "type": "Point",
        "coordinates": [
          -88.4333,
          43.9167
        ]
      },
      "type": "Feature",
      "properties": {
        "hierarchy": [
          "tgn:2468528",
          "tgn:1000001",
          "tgn:7012149",
          "tgn:2002363",
          "tgn:7007922",
          "tgn:7029392"
        ],
        "placetype": [
          "aat:300132348"
        ],
        "id": 2468528,
        "name:xx": "Long Point Reef"
      }
    },
    {
      "geometry": {
        "type": "Point",
        "coordinates": [
          -110.5333,
          39.2333
        ]
      },
      "type": "Feature",
      "properties": {
        "hierarchy": [
          "tgn:2468529",
          "tgn:1000001",
          "tgn:2002108",
          "tgn:7012149",
          "tgn:7007827",
          "tgn:7029392"
        ],
        "placetype": [
          "aat:300266640"
        ],
        "id": 2468529,
        "name:xx": "Long Point Ridge"
      }
    }
  ]
}
