{
  "geometry": {
    "type": "Point",
    "coordinates": [
      -82.3833,
      35.6833
    ]
  },
  "type": "Feature",
  "properties": {
    "hierarchy": [
      "tgn:2156339",
      "tgn:1000001",
      "tgn:2001473",
      "tgn:7012149",
      "tgn:7007709",
      "tgn:7029392"
    ],
    "placetype": [
      "aat:300008798"
    ],
    "id": 2156339,
    "name:xx": "Bearpen Knob"
  }
}
