{
  "geometry": {
    "type": "Point",
    "coordinates": [
      40.9333,
      34.4833
    ]
  },
  "type": "Feature",
  "properties": {
    "hierarchy": [
      "tgn:1085042",
      "tgn:1002075",
      "tgn:1000004",
      "tgn:1000140",
      "tgn:7029392"
    ],
    "placetype": [
      "aat:300008347"
    ],
    "id": 1085042,
    "name:xx": "Abū Kamāl"
  }
}
