{
  "geometry": {
    "type": "Point",
    "coordinates": [
      -71.9333,
      41.7667
    ]
  },
  "type": "Feature",
  "properties": {
    "hierarchy": [
      "tgn:2248528",
      "tgn:1000001",
      "tgn:1003028",
      "tgn:7012149",
      "tgn:7007159",
      "tgn:7029392"
    ],
    "placetype": [
      "aat:300008699"
    ],
    "id": 2248528,
    "name:xx": "Cold Spring Brook"
  }
}
