{
  "geometry": {
    "type": "Point",
    "coordinates": [
      -77.55,
      36.9333
    ]
  },
  "type": "Feature",
  "properties": {
    "hierarchy": [
      "tgn:2378325",
      "tgn:1000001",
      "tgn:7012149",
      "tgn:7007919",
      "tgn:7029392"
    ],
    "placetype": [
      "aat:300008699"
    ],
    "id": 2378325,
    "name:xx": "Harris Swamp"
  }
}
