{
  "geometry": {
    "type": "Point",
    "coordinates": [
      -91.1833,
      46.4667
    ]
  },
  "type": "Feature",
  "properties": {
    "hierarchy": [
      "tgn:2185817",
      "tgn:2002308",
      "tgn:1000001",
      "tgn:7012149",
      "tgn:7007922",
      "tgn:7029392"
    ],
    "placetype": [
      "aat:300008706"
    ],
    "id": 2185817,
    "name:xx": "Bolen Creek"
  }
}
