{
  "geometry": {
    "type": "Point",
    "coordinates": [
      -68.0333,
      44.85
    ]
  },
  "type": "Feature",
  "properties": {
    "hierarchy": [
      "tgn:2660802",
      "tgn:1000001",
      "tgn:2000922",
      "tgn:7012149",
      "tgn:7007515",
      "tgn:7029392"
    ],
    "placetype": [
      "aat:300008699"
    ],
    "id": 2660802,
    "name:xx": "Shorey Brook"
  }
}
