{
  "type": "FeatureCollection",
  "features": [
    {
      "geometry": {
        "type": "Point",
        "coordinates": [
          -81.9333,
          36.2833
        ]
      },
      "type": "Feature",
      "properties": {
        "hierarchy": [
          "tgn:2582940",
          "tgn:1000001",
          "tgn:7012149",
          "tgn:2001882",
          "tgn:7007825",
          "tgn:7029392"
        ],
        "placetype": [
          "aat:300008798"
        ],
        "id": 2582940,
        "name:xx": "Pine Knob"
      }
    },
    {
      "geometry": {
        "type": "Point",
        "coordinates": [
          -79.0167,
          38.7833
        ]
      },
      "type": "Feature",
      "properties": {
        "hierarchy": [
          "tgn:2582941",
          "tgn:1000001",
          "tgn:7012149",
          "tgn:2002187",
          "tgn:7007919",
          "tgn:7029392"
        ],
        "placetype": [
          "aat:300008798"
        ],
        "id": 2582941,
        "name:xx": "Pine Knob"
      }
    },
    {
      "geometry": {
        "type": "Point",
        "coordinates": [
          -81.8,
          37.4167
        ]
      },
      "type": "Feature",
      "properties": {
        "hierarchy": [
          "tgn:2582942",
          "tgn:1000001",
          "tgn:7012149",
          "tgn:2002274",
          "tgn:7013961",
          "tgn:7029392"
        ],
        "placetype": [
          "aat:300008798"
        ],
        "id": 2582942,
        "name:xx": "Pine Knob"
      }
    },
    {
      "geometry": {
        "type": "Point",
        "coordinates": [
          -80.8667,
          38.7
        ]
      },
      "type": "Feature",
      "properties": {
        "hierarchy": [
          "tgn:2582943",
          "tgn:1000001",
          "tgn:2002256",
          "tgn:7012149",
          "tgn:7013961",
          "tgn:7029392"
        ],
        "placetype": [
          "aat:300008798"
        ],
        "id": 2582943,
        "name:xx": "Pine Knob"
      }
    },
    {
      "geometry": {
        "type": "Point",
        "coordinates": [
          -80.3833,
          38.9333
        ]
      },
      "type": "Feature",
      "properties": {
        "hierarchy": [
          "tgn:2582944",
          "tgn:1000001",
          "tgn:7012149",
          "tgn:2002271",
          "tgn:7013961",
          "tgn:7029392"
        ],
        "placetype": [
          "aat:300008798"
        ],
        "id": 2582944,
        "name:xx": "Pine Knob"
      }
    },
    {
      "geometry": {
        "type": "Point",
        "coordinates": [
          -79.0167,
          38.7833
        ]
      },
      "type": "Feature",
      "properties": {
        "hierarchy": [
          "tgn:2582945",
          "tgn:1000001",
          "tgn:7012149",
          "tgn:7029392"
        ],
        "placetype": [
          "aat:300008798"
        ],
        "id": 2582945,
        "name:xx": "Pine Knob"
      }
    },
    {
      "geometry": {
        "type": "Point",
        "coordinates": [
          -90.9,
          43.0167
        ]
      },
      "type": "Feature",
      "properties": {
        "hierarchy": [
          "tgn:2582946",
          "tgn:1000001",
          "tgn:2002324",
          "tgn:7012149",
          "tgn:7007922",
          "tgn:7029392"
        ],
        "placetype": [
          "aat:300008798"
        ],
        "id": 2582946,
        "name:xx": "Pine Knob"
      }
    },
    {
      "geometry": {
        "type": "Point",
        "coordinates": [
          -89.9,
          43.1
        ]
      },
      "type": "Feature",
      "properties": {
        "hierarchy": [
          "tgn:2582947",
          "tgn:1000001",
          "tgn:7012149",
          "tgn:2002326",
          "tgn:7007922",
          "tgn:7029392"
        ],
        "placetype": [
          "aat:300008798"
        ],
        "id": 2582947,
        "name:xx": "Pine Knob"
      }
    },
    {
      "geometry": {
        "type": "Point",
        "coordinates": [
          -89.9833,
          43.7
        ]
      },
      "type": "Feature",
      "properties": {
        "hierarchy": [
          "tgn:2582948",
          "tgn:1000001",
          "tgn:7012149",
          "tgn:2002329",
          "tgn:7007922",
          "tgn:7029392"
        ],
        "placetype": [
          "aat:300008798"
        ],
        "id": 2582948,
        "name:xx": "Pine Knob"
      }
    },
    {
      "geometry": {
        "type": "Point",
        "coordinates": [
          -90.3333,
          43.7333
        ]
      },
      "type": "Feature",
      "properties": {
        "hierarchy": [
          "tgn:2582949",
          "tgn:1000001",
          "tgn:7012149",
          "tgn:2002340",
          "tgn:7007922",
          "tgn:7029392"
        ],
        "placetype": [
          "aat:300008798"
        ],
        "id": 2582949,
        "name:xx": "Pine Knob"
      }
    }
  ]
}
