{
  "type": "FeatureCollection",
  "features": [
    {
      "geometry": {
        "type": "Point",
        "coordinates": [
          -92.4333,
          31.3167
        ]
      },
      "type": "Feature",
      "properties": {
        "hierarchy": [
          "tgn:2580290",
          "tgn:1000001",
          "tgn:7012149",
          "tgn:2000893",
          "tgn:7007256",
          "tgn:7029392"
        ],
        "placetype": [
          "aat:300008680"
        ],
        "id": 2580290,
        "name:xx": "Pierson Lake"
      }
    },
    {
      "geometry": {
        "type": "Point",
        "coordinates": [
          -92.9,
          31.5333
        ]
      },
      "type": "Feature",
      "properties": {
        "hierarchy": [
          "tgn:2580291",
          "tgn:1000001",
          "tgn:7012149",
          "tgn:2000888",
          "tgn:7007256",
          "tgn:7029392"
        ],
        "placetype": [
          "aat:300008905"
        ],
        "id": 2580291,
        "name:xx": "Pierson Lake"
      }
    },
    {
      "geometry": {
        "type": "Point",
        "coordinates": [
          -91.5,
          38.9
        ]
      },
      "type": "Feature",
      "properties": {
        "hierarchy": [
          "tgn:2580292",
          "tgn:1000001",
          "tgn:7012149",
          "tgn:1002687",
          "tgn:7007523",
          "tgn:7029392"
        ],
        "placetype": [
          "aat:300006191"
        ],
        "id": 2580292,
        "name:xx": "Pierson Lake"
      }
    },
    {
      "geometry": {
        "type": "Point",
        "coordinates": [
          -67.4,
          44.5833
        ]
      },
      "type": "Feature",
      "properties": {
        "hierarchy": [
          "tgn:2580293",
          "tgn:1000001",
          "tgn:7012149",
          "tgn:7014589",
          "tgn:7007515",
          "tgn:7029392"
        ],
        "placetype": [
          "aat:300008791"
        ],
        "id": 2580293,
        "name:xx": "Pierson Ledge"
      }
    },
    {
      "geometry": {
        "type": "Point",
        "coordinates": [
          -86.8,
          33.8
        ]
      },
      "type": "Feature",
      "properties": {
        "hierarchy": [
          "tgn:2580294",
          "tgn:7002659",
          "tgn:1000001",
          "tgn:7012149",
          "tgn:2000036",
          "tgn:7029392"
        ],
        "placetype": [
          "aat:300000390"
        ],
        "id": 2580294,
        "name:xx": "Pierson Mine"
      }
    },
    {
      "geometry": {
        "type": "Point",
        "coordinates": [
          -105.4667,
          40.3
        ]
      },
      "type": "Feature",
      "properties": {
        "hierarchy": [
          "tgn:2580295",
          "tgn:1000001",
          "tgn:7012149",
          "tgn:2000226",
          "tgn:7007158",
          "tgn:7029392"
        ],
        "placetype": [
          "aat:300008798"
        ],
        "id": 2580295,
        "name:xx": "Pierson Mountain"
      }
    },
    {
      "geometry": {
        "type": "Point",
        "coordinates": [
          -116.25,
          47.8833
        ]
      },
      "type": "Feature",
      "properties": {
        "hierarchy": [
          "tgn:2580296",
          "tgn:1000001",
          "tgn:7012149",
          "tgn:2000491",
          "tgn:7007250",
          "tgn:7029392"
        ],
        "placetype": [
          "aat:300008798"
        ],
        "id": 2580296,
        "name:xx": "Pierson Peak"
      }
    },
    {
      "geometry": {
        "type": "Point",
        "coordinates": [
          -72.5,
          43.4333
        ]
      },
      "type": "Feature",
      "properties": {
        "hierarchy": [
          "tgn:2580297",
          "tgn:1000001",
          "tgn:2002136",
          "tgn:7012149",
          "tgn:7007828",
          "tgn:7029392"
        ],
        "placetype": [
          "aat:300008798"
        ],
        "id": 2580297,
        "name:xx": "Pierson Peak"
      }
    },
    {
      "geometry": {
        "type": "Point",
        "coordinates": [
          -76.7667,
          34.9667
        ]
      },
      "type": "Feature",
      "properties": {
        "hierarchy": [
          "tgn:2580298",
          "tgn:1000001",
          "tgn:7012149",
          "tgn:2001526",
          "tgn:7007709",
          "tgn:7029392"
        ],
        "placetype": [
          "aat:300008850"
        ],
        "id": 2580298,
        "name:xx": "Pierson Point"
      }
    },
    {
      "geometry": {
        "type": "Point",
        "coordinates": [
          -123.05,
          45.45
        ]
      },
      "type": "Feature",
      "properties": {
        "hierarchy": [
          "tgn:2580299",
          "tgn:1000001",
          "tgn:7012149",
          "tgn:1002994",
          "tgn:7007708",
          "tgn:7029392"
        ],
        "placetype": [
          "aat:300006191"
        ],
        "id": 2580299,
        "name:xx": "Pierson Reservoir"
      }
    }
  ]
}
