{
  "geometry": {
    "type": "Point",
    "coordinates": [
      -107.3333,
      33.3667
    ]
  },
  "type": "Feature",
  "properties": {
    "hierarchy": [
      "tgn:2662443",
      "tgn:1000001",
      "tgn:7012149",
      "tgn:2001455",
      "tgn:7007566",
      "tgn:7029392"
    ],
    "placetype": [
      "aat:300008798"
    ],
    "id": 2662443,
    "name:xx": "Sierras Mediano"
  }
}
