{
  "geometry": {
    "type": "Point",
    "coordinates": [
      -107.65,
      35.6667
    ]
  },
  "type": "Feature",
  "properties": {
    "hierarchy": [
      "tgn:2179721",
      "tgn:1000001",
      "tgn:7012149",
      "tgn:7019676",
      "tgn:7007566",
      "tgn:7029392"
    ],
    "placetype": [
      "aat:300006191"
    ],
    "id": 2179721,
    "name:xx": "Blanton Tank"
  }
}
