{
  "geometry": {
    "type": "Point",
    "coordinates": [
      -120.2333,
      46.8833
    ]
  },
  "type": "Feature",
  "properties": {
    "hierarchy": [
      "tgn:2424691",
      "tgn:1000001",
      "tgn:7012149",
      "tgn:1002553",
      "tgn:7007920",
      "tgn:7029392"
    ],
    "placetype": [
      "aat:300008706"
    ],
    "id": 2424691,
    "name:xx": "Johnson Creek"
  }
}
