{
  "geometry": {
    "type": "Point",
    "coordinates": [
      79.1667,
      19.8333
    ]
  },
  "type": "Feature",
  "properties": {
    "hierarchy": [
      "tgn:1128525",
      "tgn:1000004",
      "tgn:7000198",
      "tgn:7029392"
    ],
    "placetype": [
      "aat:300008707"
    ],
    "id": 1128525,
    "name:xx": "Penganga"
  }
}
