{
  "geometry": {
    "type": "Point",
    "coordinates": [
      -110.4167,
      41.7167
    ]
  },
  "type": "Feature",
  "properties": {
    "hierarchy": [
      "tgn:2264143",
      "tgn:1000001",
      "tgn:7012149",
      "tgn:2002376",
      "tgn:7007923",
      "tgn:7029392"
    ],
    "placetype": [
      "aat:300008697"
    ],
    "id": 2264143,
    "name:xx": "Coyote Spring"
  }
}
