{
  "geometry": {
    "type": "Point",
    "coordinates": [
      86.67768,
      20.790664
    ]
  },
  "type": "Feature",
  "properties": {
    "hierarchy": [
      "tgn:7557247",
      "tgn:1000004",
      "tgn:7000198",
      "tgn:7016694",
      "tgn:7029392"
    ],
    "placetype": [
      "aat:300008699"
    ],
    "name:en": "Sālandi River",
    "id": 7557247
  }
}
