{
  "geometry": {
    "type": "Point",
    "coordinates": [
      -80.65,
      38.7833
    ]
  },
  "type": "Feature",
  "properties": {
    "hierarchy": [
      "tgn:2343116",
      "tgn:1000001",
      "tgn:2002256",
      "tgn:7012149",
      "tgn:7013961",
      "tgn:7029392"
    ],
    "placetype": [
      "aat:300008798"
    ],
    "id": 2343116,
    "name:xx": "Gabel Knob"
  }
}
