{
  "geometry": {
    "type": "Point",
    "coordinates": [
      -70.0833,
      45.5167
    ]
  },
  "type": "Feature",
  "properties": {
    "hierarchy": [
      "tgn:2480229",
      "tgn:1000001",
      "tgn:7012149",
      "tgn:2000930",
      "tgn:7007515",
      "tgn:7029392"
    ],
    "placetype": [
      "aat:300008347"
    ],
    "id": 2480229,
    "name:xx": "Lake Parlin"
  }
}
