{
  "geometry": {
    "type": "Point",
    "coordinates": [
      79.2341,
      24.0004
    ]
  },
  "type": "Feature",
  "properties": {
    "hierarchy": [
      "tgn:7566790",
      "tgn:1000004",
      "tgn:7000198",
      "tgn:1001894",
      "tgn:7029392"
    ],
    "placetype": [
      "aat:300008347"
    ],
    "name:en": "Kānkardo",
    "id": 7566790
  }
}
