{
  "type": "FeatureCollection",
  "features": [
    {
      "geometry": {
        "type": "Point",
        "coordinates": [
          -8.583333,
          42.25
        ]
      },
      "type": "Feature",
      "properties": {
        "hierarchy": [
          "tgn:5003494",
          "tgn:7001155",
          "tgn:1000003",
          "tgn:7002790",
          "tgn:1000095",
          "tgn:7029392"
        ],
        "placetype": [
          "aat:300008347"
        ],
        "id": 5003494,
        "name:xx": "San Martín"
      }
    },
    {
      "geometry": {
        "type": "Point",
        "coordinates": [
          -2.272852,
          42.551618
        ]
      },
      "type": "Feature",
      "properties": {
        "hierarchy": [
          "tgn:5003496",
          "tgn:7001155",
          "tgn:1000003",
          "tgn:7002790",
          "tgn:1000095",
          "tgn:7029392"
        ],
        "placetype": [
          "aat:300008347"
        ],
        "id": 5003496,
        "name:xx": "Torres del Río"
      }
    },
    {
      "geometry": {
        "type": "Point",
        "coordinates": [
          -1.5,
          42.5
        ]
      },
      "type": "Feature",
      "properties": {
        "hierarchy": [
          "tgn:5003498",
          "tgn:7001155",
          "tgn:1000003",
          "tgn:7002790",
          "tgn:1000095",
          "tgn:7029392"
        ],
        "placetype": [
          "aat:300008347"
        ],
        "id": 5003498,
        "name:xx": "Ujué"
      }
    },
    {
      "geometry": {
        "type": "Point",
        "coordinates": [
          -1.983333,
          42.666667
        ]
      },
      "type": "Feature",
      "properties": {
        "hierarchy": [
          "tgn:5003499",
          "tgn:7001155",
          "tgn:1000003",
          "tgn:7002790",
          "tgn:1000095",
          "tgn:7029392"
        ],
        "placetype": [
          "aat:300008347"
        ],
        "id": 5003499,
        "name:xx": "Villatuerta"
      }
    }
  ]
}
