{
  "type": "FeatureCollection",
  "features": [
    {
      "geometry": {
        "type": "Point",
        "coordinates": [
          23,
          36.1
        ]
      },
      "type": "Feature",
      "properties": {
        "hierarchy": [
          "tgn:7234240",
          "tgn:7002745",
          "tgn:7017076",
          "tgn:1000003",
          "tgn:1000074",
          "tgn:7029392"
        ],
        "placetype": [
          "aat:300008791"
        ],
        "id": 7234240,
        "name:xx": "Avgó, Nisís"
      }
    },
    {
      "geometry": {
        "type": "Point",
        "coordinates": [
          25.573056,
          35.600556
        ]
      },
      "type": "Feature",
      "properties": {
        "hierarchy": [
          "tgn:7234241",
          "tgn:7002692",
          "tgn:7012056",
          "tgn:1000003",
          "tgn:1000074",
          "tgn:7029392"
        ],
        "placetype": [
          "aat:300008791"
        ],
        "id": 7234241,
        "name:xx": "Avgó, Nisída"
      }
    },
    {
      "geometry": {
        "type": "Point",
        "coordinates": [
          24.466667,
          41.433333
        ]
      },
      "type": "Feature",
      "properties": {
        "hierarchy": [
          "tgn:7234242",
          "tgn:7011170",
          "tgn:7002715",
          "tgn:1000003",
          "tgn:1000074",
          "tgn:7029392"
        ],
        "placetype": [
          "aat:300008347"
        ],
        "id": 7234242,
        "name:xx": "Avgó"
      }
    },
    {
      "geometry": {
        "type": "Point",
        "coordinates": [
          20.666667,
          38.216667
        ]
      },
      "type": "Feature",
      "properties": {
        "hierarchy": [
          "tgn:7234243",
          "tgn:7011167",
          "tgn:7001338",
          "tgn:1000003",
          "tgn:1000074",
          "tgn:7029392"
        ],
        "placetype": [
          "aat:300008798"
        ],
        "id": 7234243,
        "name:xx": "Avgó"
      }
    },
    {
      "geometry": {
        "type": "Point",
        "coordinates": [
          21.095556,
          39.925
        ]
      },
      "type": "Feature",
      "properties": {
        "hierarchy": [
          "tgn:7234244",
          "tgn:7002721",
          "tgn:7002715",
          "tgn:1000003",
          "tgn:1000074",
          "tgn:7029392"
        ],
        "placetype": [
          "aat:300008795"
        ],
        "id": 7234244,
        "name:xx": "Avgó"
      }
    },
    {
      "geometry": {
        "type": "Point",
        "coordinates": [
          21.383333,
          39.489444
        ]
      },
      "type": "Feature",
      "properties": {
        "hierarchy": [
          "tgn:7234245",
          "tgn:7002752",
          "tgn:7001399",
          "tgn:1000003",
          "tgn:1000074",
          "tgn:7029392"
        ],
        "placetype": [
          "aat:300008795"
        ],
        "id": 7234245,
        "name:xx": "Afgó"
      }
    },
    {
      "geometry": {
        "type": "Point",
        "coordinates": [
          22.183333,
          38
        ]
      },
      "type": "Feature",
      "properties": {
        "hierarchy": [
          "tgn:7234246",
          "tgn:7002741",
          "tgn:7017076",
          "tgn:1000003",
          "tgn:1000074",
          "tgn:7029392"
        ],
        "placetype": [
          "aat:300008795"
        ],
        "id": 7234246,
        "name:xx": "Avgó"
      }
    },
    {
      "geometry": {
        "type": "Point",
        "coordinates": [
          22.5,
          38.133333
        ]
      },
      "type": "Feature",
      "properties": {
        "hierarchy": [
          "tgn:7234247",
          "tgn:7002741",
          "tgn:7017076",
          "tgn:1000003",
          "tgn:1000074",
          "tgn:7029392"
        ],
        "placetype": [
          "aat:300008777"
        ],
        "id": 7234247,
        "name:xx": "Avgó"
      }
    },
    {
      "geometry": {
        "type": "Point",
        "coordinates": [
          23.183333,
          38.95
        ]
      },
      "type": "Feature",
      "properties": {
        "hierarchy": [
          "tgn:7234248",
          "tgn:7002751",
          "tgn:7001399",
          "tgn:1000003",
          "tgn:1000074",
          "tgn:7029392"
        ],
        "placetype": [
          "aat:300008347"
        ],
        "id": 7234248,
        "name:xx": "Avgariá"
      }
    },
    {
      "geometry": {
        "type": "Point",
        "coordinates": [
          24.433333,
          37.166667
        ]
      },
      "type": "Feature",
      "properties": {
        "hierarchy": [
          "tgn:7234249",
          "tgn:7011270",
          "tgn:7002674",
          "tgn:1000003",
          "tgn:1000074",
          "tgn:7029392"
        ],
        "placetype": [
          "aat:300132316"
        ],
        "id": 7234249,
        "name:xx": "Avesalós, Órmos"
      }
    }
  ]
}
