{
  "geometry": {
    "type": "Point",
    "coordinates": [
      137.7833,
      35.9333
    ]
  },
  "type": "Feature",
  "properties": {
    "hierarchy": [
      "tgn:1140456",
      "tgn:7000895",
      "tgn:1000004",
      "tgn:1001010",
      "tgn:1000120",
      "tgn:7029392"
    ],
    "placetype": [
      "aat:300008347"
    ],
    "id": 1140456,
    "name:xx": "Kiso"
  }
}
