{
  "type": "FeatureCollection",
  "features": [
    {
      "geometry": {
        "type": "Point",
        "coordinates": [
          -83.3,
          37.4333
        ]
      },
      "type": "Feature",
      "properties": {
        "hierarchy": [
          "tgn:2041851",
          "tgn:1000001",
          "tgn:2000772",
          "tgn:7012149",
          "tgn:7007255",
          "tgn:7029392"
        ],
        "placetype": [
          "aat:300008347",
          "aat:300387210"
        ],
        "id": 2041851,
        "name:xx": "Watts"
      }
    },
    {
      "geometry": {
        "type": "Point",
        "coordinates": [
          -87.8,
          37.7
        ]
      },
      "type": "Feature",
      "properties": {
        "hierarchy": [
          "tgn:2041853",
          "tgn:1000001",
          "tgn:7012149",
          "tgn:2000847",
          "tgn:7007255",
          "tgn:7029392"
        ],
        "placetype": [
          "aat:300008347"
        ],
        "id": 2041853,
        "name:xx": "Waverly"
      }
    },
    {
      "geometry": {
        "type": "Point",
        "coordinates": [
          -85.8333,
          38.1167
        ]
      },
      "type": "Feature",
      "properties": {
        "hierarchy": [
          "tgn:2041854",
          "tgn:1000001",
          "tgn:7012149",
          "tgn:1002516",
          "tgn:7007255",
          "tgn:7029392"
        ],
        "placetype": [
          "aat:300008347",
          "aat:300387210"
        ],
        "id": 2041854,
        "name:xx": "Waverly Hills"
      }
    },
    {
      "geometry": {
        "type": "Point",
        "coordinates": [
          -86.1167,
          37.35
        ]
      },
      "type": "Feature",
      "properties": {
        "hierarchy": [
          "tgn:2041855",
          "tgn:1000001",
          "tgn:7012149",
          "tgn:2000793",
          "tgn:7007255",
          "tgn:7029392"
        ],
        "placetype": [
          "aat:300008347"
        ],
        "id": 2041855,
        "name:xx": "Wax"
      }
    },
    {
      "geometry": {
        "type": "Point",
        "coordinates": [
          -82.8,
          37.4333
        ]
      },
      "type": "Feature",
      "properties": {
        "hierarchy": [
          "tgn:2041856",
          "tgn:1000001",
          "tgn:7012149",
          "tgn:2000789",
          "tgn:7007255",
          "tgn:7029392"
        ],
        "placetype": [
          "aat:300008347"
        ],
        "id": 2041856,
        "name:xx": "Wayland"
      }
    },
    {
      "geometry": {
        "type": "Point",
        "coordinates": [
          -84.6667,
          37.3167
        ]
      },
      "type": "Feature",
      "properties": {
        "hierarchy": [
          "tgn:2041857",
          "tgn:1000001",
          "tgn:7012149",
          "tgn:2000813",
          "tgn:7007255",
          "tgn:7029392"
        ],
        "placetype": [
          "aat:300008347"
        ],
        "id": 2041857,
        "name:xx": "Waynesburg"
      }
    },
    {
      "geometry": {
        "type": "Point",
        "coordinates": [
          -85.6,
          37.25
        ]
      },
      "type": "Feature",
      "properties": {
        "hierarchy": [
          "tgn:2041858",
          "tgn:1000001",
          "tgn:7012149",
          "tgn:2000794",
          "tgn:7007255",
          "tgn:7029392"
        ],
        "placetype": [
          "aat:300008347",
          "aat:300387210"
        ],
        "id": 2041858,
        "name:xx": "Webbs"
      }
    },
    {
      "geometry": {
        "type": "Point",
        "coordinates": [
          -85.05,
          37.1
        ]
      },
      "type": "Feature",
      "properties": {
        "hierarchy": [
          "tgn:2041859",
          "tgn:1000001",
          "tgn:7012149",
          "tgn:2000841",
          "tgn:7007255",
          "tgn:7029392"
        ],
        "placetype": [
          "aat:300008347"
        ],
        "id": 2041859,
        "name:xx": "Webbs Cross Roads"
      }
    }
  ]
}
