{
  "type": "FeatureCollection",
  "features": [
    {
      "geometry": {
        "type": "Point",
        "coordinates": [
          -83.7833,
          32.0833
        ]
      },
      "type": "Feature",
      "properties": {
        "hierarchy": [
          "tgn:2024620",
          "tgn:1000001",
          "tgn:7012149",
          "tgn:2000337",
          "tgn:7007248",
          "tgn:7029392"
        ],
        "placetype": [
          "aat:300008347"
        ],
        "id": 2024620,
        "name:xx": "Vienna"
      }
    },
    {
      "geometry": {
        "type": "Point",
        "coordinates": [
          -83.6,
          34.5167
        ]
      },
      "type": "Feature",
      "properties": {
        "hierarchy": [
          "tgn:2024621",
          "tgn:1000001",
          "tgn:7012149",
          "tgn:2000359",
          "tgn:7007248",
          "tgn:7029392"
        ],
        "placetype": [
          "aat:300008347",
          "aat:300387210"
        ],
        "id": 2024621,
        "name:xx": "View"
      }
    },
    {
      "geometry": {
        "type": "Point",
        "coordinates": [
          -85.1,
          34.6667
        ]
      },
      "type": "Feature",
      "properties": {
        "hierarchy": [
          "tgn:2024622",
          "tgn:1000001",
          "tgn:7012149",
          "tgn:2000437",
          "tgn:7007248",
          "tgn:7029392"
        ],
        "placetype": [
          "aat:300008347"
        ],
        "id": 2024622,
        "name:xx": "Villanow"
      }
    },
    {
      "geometry": {
        "type": "Point",
        "coordinates": [
          -84.9167,
          33.7167
        ]
      },
      "type": "Feature",
      "properties": {
        "hierarchy": [
          "tgn:2024623",
          "tgn:1000001",
          "tgn:2000313",
          "tgn:7012149",
          "tgn:7007248",
          "tgn:7029392"
        ],
        "placetype": [
          "aat:300008347"
        ],
        "id": 2024623,
        "name:xx": "Villa Rica"
      }
    },
    {
      "geometry": {
        "type": "Point",
        "coordinates": [
          -84.45,
          33.85
        ]
      },
      "type": "Feature",
      "properties": {
        "hierarchy": [
          "tgn:2024625",
          "tgn:1000001",
          "tgn:2000324",
          "tgn:7012149",
          "tgn:7007248",
          "tgn:7029392"
        ],
        "placetype": [
          "aat:300008347"
        ],
        "id": 2024625,
        "name:xx": "Vinings"
      }
    }
  ]
}
