{
  "geometry": {
    "type": "Point",
    "coordinates": [
      36.35,
      31.0167
    ]
  },
  "type": "Feature",
  "properties": {
    "hierarchy": [
      "tgn:1103617",
      "tgn:1000004",
      "tgn:1000121",
      "tgn:1002092",
      "tgn:7029392"
    ],
    "placetype": [
      "aat:300008795"
    ],
    "id": 1103617,
    "name:xx": "Ṣakhrīyāt, Jabal aṣ-"
  }
}
