{
  "geometry": {
    "type": "Point",
    "coordinates": [
      -124.4167,
      42.4167
    ]
  },
  "type": "Feature",
  "properties": {
    "hierarchy": [
      "tgn:2294568",
      "tgn:1000001",
      "tgn:2001704",
      "tgn:7012149",
      "tgn:7007708",
      "tgn:7029392"
    ],
    "placetype": [
      "aat:300008850"
    ],
    "id": 2294568,
    "name:xx": "Doyle Point"
  }
}
