{
  "geometry": {
    "type": "Point",
    "coordinates": [
      31.051513,
      29.089809
    ]
  },
  "type": "Feature",
  "properties": {
    "hierarchy": [
      "tgn:7525680",
      "tgn:7001242",
      "tgn:7016833",
      "tgn:1001142",
      "tgn:7029392"
    ],
    "placetype": [
      "aat:300008347"
    ],
    "name:en": "Banī 'Affān",
    "id": 7525680
  }
}
