{
  "geometry": {
    "type": "Point",
    "coordinates": [
      74.877967,
      32.60371
    ]
  },
  "type": "Feature",
  "properties": {
    "hierarchy": [
      "tgn:7591371",
      "tgn:1000004",
      "tgn:7000198",
      "tgn:7000799",
      "tgn:7029392"
    ],
    "placetype": [
      "aat:300008347"
    ],
    "name:en": "Phatwāl",
    "id": 7591371
  }
}
