{
  "geometry": {
    "type": "Point",
    "coordinates": [
      102.1333,
      5.8333
    ]
  },
  "type": "Feature",
  "properties": {
    "hierarchy": [
      "tgn:1140681",
      "tgn:7000317",
      "tgn:1001885",
      "tgn:1000004",
      "tgn:1000128",
      "tgn:7029392"
    ],
    "placetype": [
      "aat:300008347"
    ],
    "id": 1140681,
    "name:xx": "Tanah Merah"
  }
}
