{
  "geometry": {
    "type": "Point",
    "coordinates": [
      -87.3333,
      34.4333
    ]
  },
  "type": "Feature",
  "properties": {
    "hierarchy": [
      "tgn:2669069",
      "tgn:7002659",
      "tgn:1000001",
      "tgn:7012149",
      "tgn:2000039",
      "tgn:7029392"
    ],
    "placetype": [
      "aat:300008706"
    ],
    "id": 2669069,
    "name:xx": "Sledge Creek"
  }
}
