{
  "geometry": {
    "type": "Point",
    "coordinates": [
      -107.25,
      38.0333
    ]
  },
  "type": "Feature",
  "properties": {
    "hierarchy": [
      "tgn:2568336",
      "tgn:1000001",
      "tgn:7012149",
      "tgn:2000218",
      "tgn:7007158",
      "tgn:7029392"
    ],
    "placetype": [
      "aat:300008706"
    ],
    "id": 2568336,
    "name:xx": "Park Creek"
  }
}
