{
  "type": "FeatureCollection",
  "features": [
    {
      "geometry": {
        "type": "Point",
        "coordinates": [
          39.85,
          -16.3333
        ]
      },
      "type": "Feature",
      "properties": {
        "hierarchy": [
          "tgn:1006290",
          "tgn:7001242",
          "tgn:1000902",
          "tgn:1000180",
          "tgn:7029392"
        ],
        "placetype": [
          "aat:300008791"
        ],
        "id": 1006290,
        "name:xx": "Angoche, Ilha"
      }
    },
    {
      "geometry": {
        "type": "Point",
        "coordinates": [
          169.5833,
          -19.2667
        ]
      },
      "type": "Feature",
      "properties": {
        "hierarchy": [
          "tgn:1006293",
          "tgn:1002120",
          "tgn:1000225",
          "tgn:1000006",
          "tgn:7029392"
        ],
        "placetype": [
          "aat:300008791"
        ],
        "id": 1006293,
        "name:xx": "Aniwa"
      }
    },
    {
      "geometry": {
        "type": "Point",
        "coordinates": [
          -82.7167,
          27.5
        ]
      },
      "type": "Feature",
      "properties": {
        "hierarchy": [
          "tgn:1006296",
          "tgn:1000001",
          "tgn:7012149",
          "tgn:1002628",
          "tgn:7007240",
          "tgn:7029392"
        ],
        "placetype": [
          "aat:300008791"
        ],
        "id": 1006296,
        "name:xx": "Anna Maria Island"
      }
    },
    {
      "geometry": {
        "type": "Point",
        "coordinates": [
          -6.37136,
          49.895745
        ]
      },
      "type": "Feature",
      "properties": {
        "hierarchy": [
          "tgn:1006298",
          "tgn:7002445",
          "tgn:7008116",
          "tgn:1000003",
          "tgn:7011368",
          "tgn:7008591",
          "tgn:7029392"
        ],
        "placetype": [
          "aat:300008791"
        ],
        "name:en": "Annet",
        "id": 1006298
      }
    },
    {
      "geometry": {
        "type": "Point",
        "coordinates": [
          -131.4667,
          55.1333
        ]
      },
      "type": "Feature",
      "properties": {
        "hierarchy": [
          "tgn:1006299",
          "tgn:7006450",
          "tgn:1000001",
          "tgn:7012149",
          "tgn:2000082",
          "tgn:7029392"
        ],
        "placetype": [
          "aat:300008791"
        ],
        "id": 1006299,
        "name:xx": "Annette Island"
      }
    }
  ]
}
