{
  "geometry": {
    "type": "Point",
    "coordinates": [
      -90.2833,
      38.9333
    ]
  },
  "type": "Feature",
  "properties": {
    "hierarchy": [
      "tgn:2028818",
      "tgn:1000001",
      "tgn:7012149",
      "tgn:1002524",
      "tgn:7007251",
      "tgn:7029392"
    ],
    "placetype": [
      "aat:300008347",
      "aat:300387210"
    ],
    "id": 2028818,
    "name:xx": "Lockhaven"
  }
}
