{
  "geometry": {
    "type": "Point",
    "coordinates": [
      16.15,
      11.35
    ]
  },
  "type": "Feature",
  "properties": {
    "hierarchy": [
      "tgn:1088541",
      "tgn:7001242",
      "tgn:1000970",
      "tgn:1000156",
      "tgn:7029392"
    ],
    "placetype": [
      "aat:300008347"
    ],
    "id": 1088541,
    "name:xx": "Massénya"
  }
}
