{
  "geometry": {
    "type": "Point",
    "coordinates": [
      -92.35,
      36.2833
    ]
  },
  "type": "Feature",
  "properties": {
    "hierarchy": [
      "tgn:2008480",
      "tgn:2000107",
      "tgn:1000001",
      "tgn:7016172",
      "tgn:7012149",
      "tgn:7029392"
    ],
    "placetype": [
      "aat:300008347"
    ],
    "id": 2008480,
    "name:xx": "Heritage Estates"
  }
}
