{
  "geometry": {
    "type": "Point",
    "coordinates": [
      -159.8333,
      59.7167
    ]
  },
  "type": "Feature",
  "properties": {
    "hierarchy": [
      "tgn:2139924",
      "tgn:7006450",
      "tgn:1000001",
      "tgn:2000071",
      "tgn:7012149",
      "tgn:7029392"
    ],
    "placetype": [
      "aat:300008798"
    ],
    "id": 2139924,
    "name:xx": "Atshichlut Mountain"
  }
}
