{
  "geometry": {
    "type": "Point",
    "coordinates": [
      -108.1333,
      37.4833
    ]
  },
  "type": "Feature",
  "properties": {
    "hierarchy": [
      "tgn:2270218",
      "tgn:1000001",
      "tgn:7012149",
      "tgn:2000233",
      "tgn:7007158",
      "tgn:7029392"
    ],
    "placetype": [
      "aat:300008706"
    ],
    "id": 2270218,
    "name:xx": "Crystal Creek"
  }
}
