{
  "type": "FeatureCollection",
  "features": [
    {
      "geometry": {
        "type": "Point",
        "coordinates": [
          7.25,
          50.883333
        ]
      },
      "type": "Feature",
      "properties": {
        "hierarchy": [
          "tgn:7133840",
          "tgn:1000003",
          "tgn:7003677",
          "tgn:7000084",
          "tgn:7029392"
        ],
        "placetype": [
          "aat:300008347"
        ],
        "id": 7133840,
        "name:xx": "Münchhof"
      }
    },
    {
      "geometry": {
        "type": "Point",
        "coordinates": [
          12.316667,
          50.8
        ]
      },
      "type": "Feature",
      "properties": {
        "hierarchy": [
          "tgn:7133841",
          "tgn:1000003",
          "tgn:7003685",
          "tgn:7000084",
          "tgn:7029392"
        ],
        "placetype": [
          "aat:300008347"
        ],
        "id": 7133841,
        "name:xx": "Mönchhof"
      }
    },
    {
      "geometry": {
        "type": "Point",
        "coordinates": [
          7.9,
          49.433333
        ]
      },
      "type": "Feature",
      "properties": {
        "hierarchy": [
          "tgn:7133842",
          "tgn:1000003",
          "tgn:7003682",
          "tgn:7000084",
          "tgn:7029392"
        ],
        "placetype": [
          "aat:300008347"
        ],
        "id": 7133842,
        "name:xx": "Münchhof"
      }
    },
    {
      "geometry": {
        "type": "Point",
        "coordinates": [
          8.95,
          47.883333
        ]
      },
      "type": "Feature",
      "properties": {
        "hierarchy": [
          "tgn:7133843",
          "tgn:7003692",
          "tgn:1000003",
          "tgn:7000084",
          "tgn:7029392"
        ],
        "placetype": [
          "aat:300008347"
        ],
        "id": 7133843,
        "name:xx": "Münchhöf"
      }
    },
    {
      "geometry": {
        "type": "Point",
        "coordinates": [
          13.166667,
          51.183333
        ]
      },
      "type": "Feature",
      "properties": {
        "hierarchy": [
          "tgn:7133844",
          "tgn:1000003",
          "tgn:7003685",
          "tgn:7000084",
          "tgn:7029392"
        ],
        "placetype": [
          "aat:300000206"
        ],
        "id": 7133844,
        "name:xx": "Münchhof"
      }
    },
    {
      "geometry": {
        "type": "Point",
        "coordinates": [
          7.316667,
          50.516667
        ]
      },
      "type": "Feature",
      "properties": {
        "hierarchy": [
          "tgn:7133845",
          "tgn:1000003",
          "tgn:7003682",
          "tgn:7000084",
          "tgn:7029392"
        ],
        "placetype": [
          "aat:300000206"
        ],
        "id": 7133845,
        "name:xx": "Münchhof"
      }
    },
    {
      "geometry": {
        "type": "Point",
        "coordinates": [
          9.2,
          50.016667
        ]
      },
      "type": "Feature",
      "properties": {
        "hierarchy": [
          "tgn:7133846",
          "tgn:7003669",
          "tgn:1000003",
          "tgn:7000084",
          "tgn:7029392"
        ],
        "placetype": [
          "aat:300000206"
        ],
        "id": 7133846,
        "name:xx": "Münchhof"
      }
    },
    {
      "geometry": {
        "type": "Point",
        "coordinates": [
          8.316667,
          49.416667
        ]
      },
      "type": "Feature",
      "properties": {
        "hierarchy": [
          "tgn:7133847",
          "tgn:1000003",
          "tgn:7003682",
          "tgn:7000084",
          "tgn:7029392"
        ],
        "placetype": [
          "aat:300000206"
        ],
        "id": 7133847,
        "name:xx": "Münchhof"
      }
    },
    {
      "geometry": {
        "type": "Point",
        "coordinates": [
          8.116667,
          48.666667
        ]
      },
      "type": "Feature",
      "properties": {
        "hierarchy": [
          "tgn:7133848",
          "tgn:7003692",
          "tgn:1000003",
          "tgn:7000084",
          "tgn:7029392"
        ],
        "placetype": [
          "aat:300000206"
        ],
        "id": 7133848,
        "name:xx": "Münchhof"
      }
    },
    {
      "geometry": {
        "type": "Point",
        "coordinates": [
          6.516667,
          51.266667
        ]
      },
      "type": "Feature",
      "properties": {
        "hierarchy": [
          "tgn:7133849",
          "tgn:1000003",
          "tgn:7003677",
          "tgn:7000084",
          "tgn:7029392"
        ],
        "placetype": [
          "aat:300008347"
        ],
        "id": 7133849,
        "name:xx": "Münchheide"
      }
    }
  ]
}
