{
  "geometry": {
    "type": "Point",
    "coordinates": [
      31.318906,
      30.09793
    ]
  },
  "type": "Feature",
  "properties": {
    "hierarchy": [
      "tgn:7529528",
      "tgn:7001242",
      "tgn:7016833",
      "tgn:1001091",
      "tgn:7029392"
    ],
    "placetype": [
      "aat:300008187"
    ],
    "id": 7529528,
    "name:xx": "Ḩadīqat al Mayrīlānd"
  }
}
