{
  "type": "FeatureCollection",
  "features": [
    {
      "geometry": {
        "type": "Point",
        "coordinates": [
          -91.45,
          31.7667
        ]
      },
      "type": "Feature",
      "properties": {
        "hierarchy": [
          "tgn:2475520",
          "tgn:1000001",
          "tgn:7012149",
          "tgn:2000907",
          "tgn:7007256",
          "tgn:7029392"
        ],
        "placetype": [
          "aat:300008347"
        ],
        "id": 2475520,
        "name:xx": "Luckett"
      }
    },
    {
      "geometry": {
        "type": "Point",
        "coordinates": [
          -89.75,
          32.7
        ]
      },
      "type": "Feature",
      "properties": {
        "hierarchy": [
          "tgn:2475521",
          "tgn:1000001",
          "tgn:7012149",
          "tgn:2001130",
          "tgn:7007522",
          "tgn:7029392"
        ],
        "placetype": [
          "aat:300008706"
        ],
        "id": 2475521,
        "name:xx": "Luckett Creek"
      }
    },
    {
      "geometry": {
        "type": "Point",
        "coordinates": [
          -90.0333,
          32.6667
        ]
      },
      "type": "Feature",
      "properties": {
        "hierarchy": [
          "tgn:2475522",
          "tgn:1000001",
          "tgn:7012149",
          "tgn:2001130",
          "tgn:7007522",
          "tgn:7029392"
        ],
        "placetype": [
          "aat:300006075"
        ],
        "id": 2475522,
        "name:xx": "Luckett Ditch"
      }
    },
    {
      "geometry": {
        "type": "Point",
        "coordinates": [
          -104.5,
          31.35
        ]
      },
      "type": "Feature",
      "properties": {
        "hierarchy": [
          "tgn:2475523",
          "tgn:1000001",
          "tgn:7012149",
          "tgn:2001969",
          "tgn:7007826",
          "tgn:7029392"
        ],
        "placetype": [
          "aat:300008761"
        ],
        "id": 2475523,
        "name:xx": "Luckett Draw"
      }
    },
    {
      "geometry": {
        "type": "Point",
        "coordinates": [
          -86.9,
          36.8
        ]
      },
      "type": "Feature",
      "properties": {
        "hierarchy": [
          "tgn:2475524",
          "tgn:1000001",
          "tgn:7012149",
          "tgn:2000815",
          "tgn:7007255",
          "tgn:7029392"
        ],
        "placetype": [
          "aat:300008798"
        ],
        "id": 2475524,
        "name:xx": "Luckett Knob"
      }
    },
    {
      "geometry": {
        "type": "Point",
        "coordinates": [
          -91.3,
          34.55
        ]
      },
      "type": "Feature",
      "properties": {
        "hierarchy": [
          "tgn:2475525",
          "tgn:2000105",
          "tgn:1000001",
          "tgn:7016172",
          "tgn:7012149",
          "tgn:7029392"
        ],
        "placetype": [
          "aat:300008680"
        ],
        "id": 2475525,
        "name:xx": "Luckett Lake"
      }
    },
    {
      "geometry": {
        "type": "Point",
        "coordinates": [
          -119.1833,
          36.8
        ]
      },
      "type": "Feature",
      "properties": {
        "hierarchy": [
          "tgn:2475526",
          "tgn:1000001",
          "tgn:7012149",
          "tgn:1002392",
          "tgn:7007157",
          "tgn:7029392"
        ],
        "placetype": [
          "aat:300008798"
        ],
        "id": 2475526,
        "name:xx": "Luckett Mountain"
      }
    },
    {
      "geometry": {
        "type": "Point",
        "coordinates": [
          -90.8167,
          39.1
        ]
      },
      "type": "Feature",
      "properties": {
        "hierarchy": [
          "tgn:2475527",
          "tgn:1000001",
          "tgn:7012149",
          "tgn:1002598",
          "tgn:7007523",
          "tgn:7029392"
        ],
        "placetype": [
          "aat:300266640"
        ],
        "id": 2475527,
        "name:xx": "Luckett Ridge"
      }
    },
    {
      "geometry": {
        "type": "Point",
        "coordinates": [
          -104.4833,
          31.3333
        ]
      },
      "type": "Feature",
      "properties": {
        "hierarchy": [
          "tgn:2475528",
          "tgn:1000001",
          "tgn:7012149",
          "tgn:2001969",
          "tgn:7007826",
          "tgn:7029392"
        ],
        "placetype": [
          "aat:300006191"
        ],
        "id": 2475528,
        "name:xx": "Luckett Tank"
      }
    },
    {
      "geometry": {
        "type": "Point",
        "coordinates": [
          -99.6833,
          42.7667
        ]
      },
      "type": "Feature",
      "properties": {
        "hierarchy": [
          "tgn:2475529",
          "tgn:1000001",
          "tgn:2001367",
          "tgn:7012149",
          "tgn:7007525",
          "tgn:7029392"
        ],
        "placetype": [
          "aat:300008706"
        ],
        "id": 2475529,
        "name:xx": "Luckey Creek"
      }
    }
  ]
}
