{
  "geometry": {
    "type": "Point",
    "coordinates": [
      -70.7333,
      41.85
    ]
  },
  "type": "Feature",
  "properties": {
    "hierarchy": [
      "tgn:2265311",
      "tgn:1000001",
      "tgn:7014423",
      "tgn:7012149",
      "tgn:7007517",
      "tgn:7029392"
    ],
    "placetype": [
      "aat:300006191"
    ],
    "id": 2265311,
    "name:xx": "Crane Brook Reservoir"
  }
}
