{
  "type": "FeatureCollection",
  "features": [
    {
      "geometry": {
        "type": "Point",
        "coordinates": [
          -118.9,
          46.0833
        ]
      },
      "type": "Feature",
      "properties": {
        "hierarchy": [
          "tgn:2117071",
          "tgn:1000001",
          "tgn:7012149",
          "tgn:2002251",
          "tgn:7007920",
          "tgn:7029392"
        ],
        "placetype": [
          "aat:300008347"
        ],
        "id": 2117071,
        "name:xx": "Wallula"
      }
    },
    {
      "geometry": {
        "type": "Point",
        "coordinates": [
          -122.5833,
          45.6667
        ]
      },
      "type": "Feature",
      "properties": {
        "hierarchy": [
          "tgn:2117075",
          "tgn:1000001",
          "tgn:1002275",
          "tgn:7012149",
          "tgn:7007920",
          "tgn:7029392"
        ],
        "placetype": [
          "aat:300008347"
        ],
        "id": 2117075,
        "name:xx": "Walnut Grove"
      }
    },
    {
      "geometry": {
        "type": "Point",
        "coordinates": [
          -117.1,
          47.0333
        ]
      },
      "type": "Feature",
      "properties": {
        "hierarchy": [
          "tgn:2117076",
          "tgn:1000001",
          "tgn:7012149",
          "tgn:2002252",
          "tgn:7007920",
          "tgn:7029392"
        ],
        "placetype": [
          "aat:300387016"
        ],
        "id": 2117076,
        "name:xx": "Walters"
      }
    },
    {
      "geometry": {
        "type": "Point",
        "coordinates": [
          -119.9333,
          46.85
        ]
      },
      "type": "Feature",
      "properties": {
        "hierarchy": [
          "tgn:2117077",
          "tgn:1000001",
          "tgn:7012149",
          "tgn:2002246",
          "tgn:7007920",
          "tgn:7029392"
        ],
        "placetype": [
          "aat:300008347"
        ],
        "id": 2117077,
        "name:xx": "Wanapum Village"
      }
    },
    {
      "geometry": {
        "type": "Point",
        "coordinates": [
          -120.4167,
          46.4333
        ]
      },
      "type": "Feature",
      "properties": {
        "hierarchy": [
          "tgn:2117078",
          "tgn:1000001",
          "tgn:7012149",
          "tgn:1003042",
          "tgn:7007920",
          "tgn:7029392"
        ],
        "placetype": [
          "aat:300008347"
        ],
        "id": 2117078,
        "name:xx": "Wapato"
      }
    },
    {
      "geometry": {
        "type": "Point",
        "coordinates": [
          -119.0333,
          46.9667
        ]
      },
      "type": "Feature",
      "properties": {
        "hierarchy": [
          "tgn:2117079",
          "tgn:1000001",
          "tgn:7012149",
          "tgn:2002246",
          "tgn:7007920",
          "tgn:7029392"
        ],
        "placetype": [
          "aat:300008347"
        ],
        "id": 2117079,
        "name:xx": "Warden"
      }
    }
  ]
}
