{
  "geometry": {
    "type": "Point",
    "coordinates": [
      16.3167,
      48.25
    ]
  },
  "type": "Feature",
  "properties": {
    "hierarchy": [
      "tgn:1005296",
      "tgn:7003321",
      "tgn:7003030",
      "tgn:1000003",
      "tgn:1000062",
      "tgn:7029392"
    ],
    "placetype": [
      "aat:300000874"
    ],
    "id": 1005296,
    "name:xx": "Pötzleinsdorf"
  }
}
