{
  "geometry": {
    "type": "Point",
    "coordinates": [
      150.1667,
      -35.0167
    ]
  },
  "type": "Feature",
  "properties": {
    "hierarchy": [
      "tgn:1104305",
      "tgn:7000490",
      "tgn:1000006",
      "tgn:7001828",
      "tgn:7029392"
    ],
    "placetype": [
      "aat:300008795"
    ],
    "id": 1104305,
    "name:xx": "Coolumburra Hill"
  }
}
