{
  "geometry": {
    "type": "Point",
    "coordinates": [
      -108.4333,
      34.1833
    ]
  },
  "type": "Feature",
  "properties": {
    "hierarchy": [
      "tgn:2318837",
      "tgn:1000001",
      "tgn:2001429",
      "tgn:7012149",
      "tgn:7007566",
      "tgn:7029392"
    ],
    "placetype": [
      "aat:300008706"
    ],
    "id": 2318837,
    "name:xx": "Escondido Creek"
  }
}
