{
  "geometry": {
    "type": "Point",
    "coordinates": [
      -82.4667,
      35.2833
    ]
  },
  "type": "Feature",
  "properties": {
    "hierarchy": [
      "tgn:2658417",
      "tgn:1000001",
      "tgn:7012149",
      "tgn:2001504",
      "tgn:7007709",
      "tgn:7029392"
    ],
    "placetype": [
      "aat:300008706"
    ],
    "id": 2658417,
    "name:xx": "Shepherd Creek"
  }
}
