{
  "geometry": {
    "type": "Point",
    "coordinates": [
      -87.35,
      35.65
    ]
  },
  "type": "Feature",
  "properties": {
    "hierarchy": [
      "tgn:2785815",
      "tgn:1000001",
      "tgn:7012149",
      "tgn:7029392"
    ],
    "placetype": [
      "aat:300008761"
    ],
    "id": 2785815,
    "name:xx": "York Hollow"
  }
}
