{
  "geometry": {
    "type": "Point",
    "coordinates": [
      -113.6833,
      35.6667
    ]
  },
  "type": "Feature",
  "properties": {
    "hierarchy": [
      "tgn:2376469",
      "tgn:1000001",
      "tgn:7006451",
      "tgn:7012149",
      "tgn:2000098",
      "tgn:7029392"
    ],
    "placetype": [
      "aat:300008697"
    ],
    "id": 2376469,
    "name:xx": "Harding Spring"
  }
}
