{
  "geometry": {
    "type": "Point",
    "coordinates": [
      103.9667,
      30.3167
    ]
  },
  "type": "Feature",
  "properties": {
    "hierarchy": [
      "tgn:1068918",
      "tgn:1000004",
      "tgn:7002087",
      "tgn:1000111",
      "tgn:7029392"
    ],
    "placetype": [
      "aat:300008347"
    ],
    "id": 1068918,
    "name:xx": "Huanglongxi"
  }
}
