{
  "type": "FeatureCollection",
  "features": [
    {
      "geometry": {
        "type": "Point",
        "coordinates": [
          -5.833333,
          57.733333
        ]
      },
      "type": "Feature",
      "properties": {
        "hierarchy": [
          "tgn:7463640",
          "tgn:7002444",
          "tgn:1000003",
          "tgn:7008082",
          "tgn:7008591",
          "tgn:7029392"
        ],
        "placetype": [
          "aat:300008791"
        ],
        "name:en": "Longa Island",
        "id": 7463640
      }
    },
    {
      "geometry": {
        "type": "Point",
        "coordinates": [
          -2.8,
          57.7
        ]
      },
      "type": "Feature",
      "properties": {
        "hierarchy": [
          "tgn:7463641",
          "tgn:5000432",
          "tgn:7002444",
          "tgn:1000003",
          "tgn:7008591",
          "tgn:7029392"
        ],
        "placetype": [
          "aat:300132316"
        ],
        "name:en": "Long, Port",
        "id": 7463641
      }
    },
    {
      "geometry": {
        "type": "Point",
        "coordinates": [
          -5.5,
          57.3
        ]
      },
      "type": "Feature",
      "properties": {
        "hierarchy": [
          "tgn:7463642",
          "tgn:7002444",
          "tgn:1000003",
          "tgn:7008082",
          "tgn:7008591",
          "tgn:7029392"
        ],
        "placetype": [
          "aat:300132316"
        ],
        "name:en": "Long, Loch",
        "id": 7463642
      }
    },
    {
      "geometry": {
        "type": "Point",
        "coordinates": [
          -4.883333,
          58.333333
        ]
      },
      "type": "Feature",
      "properties": {
        "hierarchy": [
          "tgn:7463644",
          "tgn:7002444",
          "tgn:1000003",
          "tgn:7008082",
          "tgn:7008591",
          "tgn:7029392"
        ],
        "placetype": [
          "aat:300008347"
        ],
        "name:en": "Lone",
        "id": 7463644
      }
    },
    {
      "geometry": {
        "type": "Point",
        "coordinates": [
          -2.233333,
          53.483333
        ]
      },
      "type": "Feature",
      "properties": {
        "hierarchy": [
          "tgn:7463645",
          "tgn:7002445",
          "tgn:7027477",
          "tgn:1000003",
          "tgn:7026570",
          "tgn:7008591",
          "tgn:7029392"
        ],
        "placetype": [
          "aat:300007783"
        ],
        "name:en": "London Road Station",
        "id": 7463645
      }
    },
    {
      "geometry": {
        "type": "Point",
        "coordinates": [
          -7.333333,
          55
        ]
      },
      "type": "Feature",
      "properties": {
        "hierarchy": [
          "tgn:7463646",
          "tgn:7002448",
          "tgn:7008699",
          "tgn:1000003",
          "tgn:7008591",
          "tgn:7029392"
        ],
        "placetype": [
          "aat:300000745"
        ],
        "name:en": "Londonderry County Borough",
        "id": 7463646
      }
    },
    {
      "geometry": {
        "type": "Point",
        "coordinates": [
          -6.916667,
          54.916667
        ]
      },
      "type": "Feature",
      "properties": {
        "hierarchy": [
          "tgn:7463647",
          "tgn:7002448",
          "tgn:7019215",
          "tgn:1000003",
          "tgn:7008591",
          "tgn:7029392"
        ],
        "placetype": [
          "aat:300387346"
        ],
        "name:en": "Londonderry, County",
        "id": 7463647
      }
    }
  ]
}
