{
  "geometry": {
    "type": "Point",
    "coordinates": [
      -37.75,
      -4.5333
    ]
  },
  "type": "Feature",
  "properties": {
    "hierarchy": [
      "tgn:1020653",
      "tgn:7006064",
      "tgn:1000047",
      "tgn:7002455",
      "tgn:1000002",
      "tgn:7029392"
    ],
    "placetype": [
      "aat:300008347"
    ],
    "id": 1020653,
    "name:xx": "Aracati"
  }
}
