{
  "geometry": {
    "type": "Point",
    "coordinates": [
      -88.1833,
      41.3667
    ]
  },
  "type": "Feature",
  "properties": {
    "hierarchy": [
      "tgn:2026622",
      "tgn:1000001",
      "tgn:7012149",
      "tgn:1003024",
      "tgn:7007251",
      "tgn:7029392"
    ],
    "placetype": [
      "aat:300387016"
    ],
    "id": 2026622,
    "name:xx": "Blodgett"
  }
}
