{
  "geometry": {
    "type": "Point",
    "coordinates": [
      -123.0667,
      44.9167
    ]
  },
  "type": "Feature",
  "properties": {
    "hierarchy": [
      "tgn:2777624",
      "tgn:1000001",
      "tgn:7012149",
      "tgn:1002794",
      "tgn:7007708",
      "tgn:7029392"
    ],
    "placetype": [
      "aat:300008347"
    ],
    "id": 2777624,
    "name:xx": "Winona"
  }
}
