{
  "geometry": {
    "type": "Point",
    "coordinates": [
      78.325254,
      24.81543
    ]
  },
  "type": "Feature",
  "properties": {
    "hierarchy": [
      "tgn:7582357",
      "tgn:1000004",
      "tgn:7000198",
      "tgn:7016722",
      "tgn:7029392"
    ],
    "placetype": [
      "aat:300008699"
    ],
    "name:en": "Lera Nāla",
    "id": 7582357
  }
}
