{
  "geometry": {
    "type": "Point",
    "coordinates": [
      -92.9167,
      37.15
    ]
  },
  "type": "Feature",
  "properties": {
    "hierarchy": [
      "tgn:2715292",
      "tgn:1000001",
      "tgn:7012149",
      "tgn:2001256",
      "tgn:7007523",
      "tgn:7029392"
    ],
    "placetype": [
      "aat:300008699"
    ],
    "id": 2715292,
    "name:xx": "Terell Branch"
  }
}
