{
  "geometry": {
    "type": "Point",
    "coordinates": [
      -78.2167,
      40.8833
    ]
  },
  "type": "Feature",
  "properties": {
    "hierarchy": [
      "tgn:2093221",
      "tgn:1000001",
      "tgn:1002249",
      "tgn:7012149",
      "tgn:7007710",
      "tgn:7029392"
    ],
    "placetype": [
      "aat:300008347"
    ],
    "id": 2093221,
    "name:xx": "South Philipsburg"
  }
}
