{
  "geometry": {
    "type": "Point",
    "coordinates": [
      -105.85,
      36.0333
    ]
  },
  "type": "Feature",
  "properties": {
    "hierarchy": [
      "tgn:2271154",
      "tgn:1000001",
      "tgn:7012149",
      "tgn:2001449",
      "tgn:7007566",
      "tgn:7029392"
    ],
    "placetype": [
      "aat:300008699"
    ],
    "id": 2271154,
    "name:xx": "Cuesta Colorada, Arroyo"
  }
}
