{
  "geometry": {
    "type": "Point",
    "coordinates": [
      -107.8333,
      41.1833
    ]
  },
  "type": "Feature",
  "properties": {
    "hierarchy": [
      "tgn:2331233",
      "tgn:1000001",
      "tgn:2002368",
      "tgn:7012149",
      "tgn:7007923",
      "tgn:7029392"
    ],
    "placetype": [
      "aat:300008798"
    ],
    "id": 2331233,
    "name:xx": "Flat Top Mountain"
  }
}
