{
  "geometry": {
    "type": "Point",
    "coordinates": [
      -161.3833,
      65.3167
    ]
  },
  "type": "Feature",
  "properties": {
    "hierarchy": [
      "tgn:2155208",
      "tgn:7006450",
      "tgn:1000001",
      "tgn:7012149",
      "tgn:2124014",
      "tgn:7029392"
    ],
    "placetype": [
      "aat:300008798"
    ],
    "id": 2155208,
    "name:xx": "Bear Mountain"
  }
}
