{
  "type": "FeatureCollection",
  "features": [
    {
      "geometry": {
        "type": "Point",
        "coordinates": [
          -84.5167,
          35
        ]
      },
      "type": "Feature",
      "properties": {
        "hierarchy": [
          "tgn:2237360",
          "tgn:1000001",
          "tgn:7012149",
          "tgn:2001906",
          "tgn:7007825",
          "tgn:7029392"
        ],
        "placetype": [
          "aat:300008798"
        ],
        "id": 2237360,
        "name:xx": "Chimneytop"
      }
    },
    {
      "geometry": {
        "type": "Point",
        "coordinates": [
          -82.7,
          36.4
        ]
      },
      "type": "Feature",
      "properties": {
        "hierarchy": [
          "tgn:2237361",
          "tgn:1000001",
          "tgn:7012149",
          "tgn:7007825",
          "tgn:7029392"
        ],
        "placetype": [
          "aat:300008798"
        ],
        "id": 2237361,
        "name:xx": "Chimneytop"
      }
    },
    {
      "geometry": {
        "type": "Point",
        "coordinates": [
          -82.75,
          36.4
        ]
      },
      "type": "Feature",
      "properties": {
        "hierarchy": [
          "tgn:2237362",
          "tgn:1000001",
          "tgn:7012149",
          "tgn:2001873",
          "tgn:7007825",
          "tgn:7029392"
        ],
        "placetype": [
          "aat:300008347"
        ],
        "id": 2237362,
        "name:xx": "Chimneytop"
      }
    },
    {
      "geometry": {
        "type": "Point",
        "coordinates": [
          -83.8167,
          34.8667
        ]
      },
      "type": "Feature",
      "properties": {
        "hierarchy": [
          "tgn:2237363",
          "tgn:1000001",
          "tgn:7012149",
          "tgn:2000435",
          "tgn:7007248",
          "tgn:7029392"
        ],
        "placetype": [
          "aat:300008798"
        ],
        "id": 2237363,
        "name:xx": "Chimneytop Mountain"
      }
    },
    {
      "geometry": {
        "type": "Point",
        "coordinates": [
          -83.05,
          35.1
        ]
      },
      "type": "Feature",
      "properties": {
        "hierarchy": [
          "tgn:2237364",
          "tgn:1000001",
          "tgn:7012149",
          "tgn:2001508",
          "tgn:7007709",
          "tgn:7029392"
        ],
        "placetype": [
          "aat:300008798"
        ],
        "id": 2237364,
        "name:xx": "Chimneytop Mountain"
      }
    },
    {
      "geometry": {
        "type": "Point",
        "coordinates": [
          -82.7,
          36.4
        ]
      },
      "type": "Feature",
      "properties": {
        "hierarchy": [
          "tgn:2237365",
          "tgn:1000001",
          "tgn:7012149",
          "tgn:7007825",
          "tgn:7029392"
        ],
        "placetype": [
          "aat:300008798"
        ],
        "id": 2237365,
        "name:xx": "Chimneytop Mountain"
      }
    },
    {
      "geometry": {
        "type": "Point",
        "coordinates": [
          -73.3667,
          41.0667
        ]
      },
      "type": "Feature",
      "properties": {
        "hierarchy": [
          "tgn:2237366",
          "tgn:1002366",
          "tgn:1000001",
          "tgn:7012149",
          "tgn:7007159",
          "tgn:7029392"
        ],
        "placetype": [
          "aat:300008791"
        ],
        "id": 2237366,
        "name:xx": "Chimon Rock"
      }
    },
    {
      "geometry": {
        "type": "Point",
        "coordinates": [
          -114.4167,
          39.9833
        ]
      },
      "type": "Feature",
      "properties": {
        "hierarchy": [
          "tgn:2237367",
          "tgn:1000001",
          "tgn:7012149",
          "tgn:2001420",
          "tgn:7007526",
          "tgn:7029392"
        ],
        "placetype": [
          "aat:300008706"
        ],
        "id": 2237367,
        "name:xx": "Chin Creek"
      }
    },
    {
      "geometry": {
        "type": "Point",
        "coordinates": [
          -114.3,
          40.0167
        ]
      },
      "type": "Feature",
      "properties": {
        "hierarchy": [
          "tgn:2237368",
          "tgn:1000001",
          "tgn:7012149",
          "tgn:2001420",
          "tgn:7007526",
          "tgn:7029392"
        ],
        "placetype": [
          "aat:300006075"
        ],
        "id": 2237368,
        "name:xx": "Chin Creek Ditch"
      }
    },
    {
      "geometry": {
        "type": "Point",
        "coordinates": [
          -114.35,
          40.0167
        ]
      },
      "type": "Feature",
      "properties": {
        "hierarchy": [
          "tgn:2237369",
          "tgn:1000001",
          "tgn:7012149",
          "tgn:2001420",
          "tgn:7007526",
          "tgn:7029392"
        ],
        "placetype": [
          "aat:300006191"
        ],
        "id": 2237369,
        "name:xx": "Chin Creek Reservoir"
      }
    }
  ]
}
