{
  "geometry": {
    "type": "Point",
    "coordinates": [
      -116.15,
      32.8167
    ]
  },
  "type": "Feature",
  "properties": {
    "hierarchy": [
      "tgn:2542974",
      "tgn:1000001",
      "tgn:7012149",
      "tgn:7007157",
      "tgn:1002858",
      "tgn:7029392"
    ],
    "placetype": [
      "aat:300008761"
    ],
    "id": 2542974,
    "name:xx": "Nombre, Canyon"
  }
}
