{
  "geometry": {
    "type": "Point",
    "coordinates": [
      -73.7667,
      40.8833
    ]
  },
  "type": "Feature",
  "properties": {
    "hierarchy": [
      "tgn:2684613",
      "tgn:1000001",
      "tgn:7012149",
      "tgn:7014612",
      "tgn:7007568",
      "tgn:7029392"
    ],
    "placetype": [
      "aat:300132348"
    ],
    "id": 2684613,
    "name:xx": "Spindle Rock"
  }
}
