{
  "type": "FeatureCollection",
  "features": [
    {
      "geometry": {
        "type": "Point",
        "coordinates": [
          -74.45,
          41.7667
        ]
      },
      "type": "Feature",
      "properties": {
        "hierarchy": [
          "tgn:2192440",
          "tgn:1000001",
          "tgn:7012149",
          "tgn:1002961",
          "tgn:7007568",
          "tgn:7029392"
        ],
        "placetype": [
          "aat:300008699"
        ],
        "id": 2192440,
        "name:xx": "Brandy Brook"
      }
    },
    {
      "geometry": {
        "type": "Point",
        "coordinates": [
          -74.35,
          44.2833
        ]
      },
      "type": "Feature",
      "properties": {
        "hierarchy": [
          "tgn:2192441",
          "tgn:1000001",
          "tgn:7012149",
          "tgn:7013941",
          "tgn:7007568",
          "tgn:7029392"
        ],
        "placetype": [
          "aat:300008699"
        ],
        "id": 2192441,
        "name:xx": "Brandy Brook"
      }
    },
    {
      "geometry": {
        "type": "Point",
        "coordinates": [
          -74.6833,
          44.4167
        ]
      },
      "type": "Feature",
      "properties": {
        "hierarchy": [
          "tgn:2192442",
          "tgn:1000001",
          "tgn:7012149",
          "tgn:7016021",
          "tgn:7007568",
          "tgn:7029392"
        ],
        "placetype": [
          "aat:300008699"
        ],
        "id": 2192442,
        "name:xx": "Brandy Brook"
      }
    },
    {
      "geometry": {
        "type": "Point",
        "coordinates": [
          -73.9,
          44.7
        ]
      },
      "type": "Feature",
      "properties": {
        "hierarchy": [
          "tgn:2192443",
          "tgn:1000001",
          "tgn:1002284",
          "tgn:7012149",
          "tgn:7007568",
          "tgn:7029392"
        ],
        "placetype": [
          "aat:300008699"
        ],
        "id": 2192443,
        "name:xx": "Brandy Brook"
      }
    },
    {
      "geometry": {
        "type": "Point",
        "coordinates": [
          -75.5667,
          43.15
        ]
      },
      "type": "Feature",
      "properties": {
        "hierarchy": [
          "tgn:2192444",
          "tgn:1000001",
          "tgn:7012149",
          "tgn:7007568",
          "tgn:7029392"
        ],
        "placetype": [
          "aat:300008699"
        ],
        "id": 2192444,
        "name:xx": "Brandy Brook"
      }
    },
    {
      "geometry": {
        "type": "Point",
        "coordinates": [
          -75.4833,
          43.25
        ]
      },
      "type": "Feature",
      "properties": {
        "hierarchy": [
          "tgn:2192445",
          "tgn:1000001",
          "tgn:7012149",
          "tgn:7014287",
          "tgn:7007568",
          "tgn:7029392"
        ],
        "placetype": [
          "aat:300008699"
        ],
        "id": 2192445,
        "name:xx": "Brandy Brook"
      }
    },
    {
      "geometry": {
        "type": "Point",
        "coordinates": [
          -74.6667,
          43.25
        ]
      },
      "type": "Feature",
      "properties": {
        "hierarchy": [
          "tgn:2192446",
          "tgn:1000001",
          "tgn:7012149",
          "tgn:1002397",
          "tgn:7007568",
          "tgn:7029392"
        ],
        "placetype": [
          "aat:300008699"
        ],
        "id": 2192446,
        "name:xx": "Brandy Brook"
      }
    },
    {
      "geometry": {
        "type": "Point",
        "coordinates": [
          -73.5333,
          44.1
        ]
      },
      "type": "Feature",
      "properties": {
        "hierarchy": [
          "tgn:2192447",
          "tgn:1000001",
          "tgn:7012149",
          "tgn:2001461",
          "tgn:7007568",
          "tgn:7029392"
        ],
        "placetype": [
          "aat:300008699"
        ],
        "id": 2192447,
        "name:xx": "Brandy Brook"
      }
    },
    {
      "geometry": {
        "type": "Point",
        "coordinates": [
          -71.5667,
          41.8
        ]
      },
      "type": "Feature",
      "properties": {
        "hierarchy": [
          "tgn:2192448",
          "tgn:1002808",
          "tgn:1000001",
          "tgn:7012149",
          "tgn:7007711",
          "tgn:7029392"
        ],
        "placetype": [
          "aat:300008699"
        ],
        "id": 2192448,
        "name:xx": "Brandy Brook"
      }
    },
    {
      "geometry": {
        "type": "Point",
        "coordinates": [
          -72.95,
          43.95
        ]
      },
      "type": "Feature",
      "properties": {
        "hierarchy": [
          "tgn:2192449",
          "tgn:2002130",
          "tgn:1000001",
          "tgn:7012149",
          "tgn:7007828",
          "tgn:7029392"
        ],
        "placetype": [
          "aat:300008699"
        ],
        "id": 2192449,
        "name:xx": "Brandy Brook"
      }
    }
  ]
}
