{
  "geometry": {
    "type": "Point",
    "coordinates": [
      -71.9667,
      41.3833
    ]
  },
  "type": "Feature",
  "properties": {
    "hierarchy": [
      "tgn:2208475",
      "tgn:1000001",
      "tgn:1002714",
      "tgn:7012149",
      "tgn:7007159",
      "tgn:7029392"
    ],
    "placetype": [
      "aat:300008347"
    ],
    "id": 2208475,
    "name:xx": "Burnetts Corner"
  }
}
