{
  "geometry": {
    "type": "Point",
    "coordinates": [
      -79.9167,
      41.8667
    ]
  },
  "type": "Feature",
  "properties": {
    "hierarchy": [
      "tgn:2091260",
      "tgn:1000001",
      "tgn:7012149",
      "tgn:1002358",
      "tgn:7007710",
      "tgn:7029392"
    ],
    "placetype": [
      "aat:300008347"
    ],
    "id": 2091260,
    "name:xx": "New Ireland"
  }
}
