{
  "geometry": {
    "type": "Point",
    "coordinates": [
      -122.5167,
      37.85
    ]
  },
  "type": "Feature",
  "properties": {
    "hierarchy": [
      "tgn:1102038",
      "tgn:1000001",
      "tgn:7012149",
      "tgn:7007157",
      "tgn:7014005",
      "tgn:7029392"
    ],
    "placetype": [
      "aat:300000510"
    ],
    "id": 1102038,
    "name:xx": "Golden Gate National Recreation Area"
  }
}
