{
  "geometry": {
    "type": "Point",
    "coordinates": [
      -115.5333,
      40.15
    ]
  },
  "type": "Feature",
  "properties": {
    "hierarchy": [
      "tgn:2471245",
      "tgn:1000001",
      "tgn:2001411",
      "tgn:7012149",
      "tgn:7007526",
      "tgn:7029392"
    ],
    "placetype": [
      "aat:300008746"
    ],
    "id": 2471245,
    "name:xx": "Lost Hope Cave"
  }
}
