{
  "geometry": {
    "type": "Point",
    "coordinates": [
      -85.2833,
      36.2333
    ]
  },
  "type": "Feature",
  "properties": {
    "hierarchy": [
      "tgn:2706153",
      "tgn:1000001",
      "tgn:7012149",
      "tgn:2001903",
      "tgn:7007825",
      "tgn:7029392"
    ],
    "placetype": [
      "aat:300008746"
    ],
    "id": 2706153,
    "name:xx": "Swallows Hole"
  }
}
