{
  "geometry": {
    "type": "Point",
    "coordinates": [
      -69.3167,
      45.5833
    ]
  },
  "type": "Feature",
  "properties": {
    "hierarchy": [
      "tgn:2169503",
      "tgn:1000001",
      "tgn:7012149",
      "tgn:2000928",
      "tgn:7007515",
      "tgn:7029392"
    ],
    "placetype": [
      "aat:300006191"
    ],
    "id": 2169503,
    "name:xx": "Big Lyford Pond"
  }
}
