{
  "geometry": {
    "type": "Point",
    "coordinates": [
      -97.9667,
      39.2667
    ]
  },
  "type": "Feature",
  "properties": {
    "hierarchy": [
      "tgn:2650790",
      "tgn:1000001",
      "tgn:7012149",
      "tgn:7007254",
      "tgn:7029392"
    ],
    "placetype": [
      "aat:300008706"
    ],
    "id": 2650790,
    "name:xx": "Second Creek"
  }
}
