{
  "geometry": {
    "type": "Point",
    "coordinates": [
      30.469496,
      29.415527
    ]
  },
  "type": "Feature",
  "properties": {
    "hierarchy": [
      "tgn:7540897",
      "tgn:7001242",
      "tgn:7001105",
      "tgn:7016833",
      "tgn:7029392"
    ],
    "placetype": [
      "aat:300008347"
    ],
    "name:en": "Qaryat at Ta'mīr as Siyāḩīyah",
    "id": 7540897
  }
}
