{
  "type": "FeatureCollection",
  "features": [
    {
      "geometry": {
        "type": "Point",
        "coordinates": [
          -79.0833,
          33.9667
        ]
      },
      "type": "Feature",
      "properties": {
        "hierarchy": [
          "tgn:2096530",
          "tgn:1000001",
          "tgn:7012149",
          "tgn:2001750",
          "tgn:7007712",
          "tgn:7029392"
        ],
        "placetype": [
          "aat:300008347",
          "aat:300387210"
        ],
        "id": 2096530,
        "name:xx": "Rabon Crossroads"
      }
    },
    {
      "geometry": {
        "type": "Point",
        "coordinates": [
          -79.3,
          34.0833
        ]
      },
      "type": "Feature",
      "properties": {
        "hierarchy": [
          "tgn:2096531",
          "tgn:1000001",
          "tgn:7012149",
          "tgn:2001758",
          "tgn:7007712",
          "tgn:7029392"
        ],
        "placetype": [
          "aat:300008347"
        ],
        "id": 2096531,
        "name:xx": "Rains"
      }
    },
    {
      "geometry": {
        "type": "Point",
        "coordinates": [
          -80.1333,
          32.7667
        ]
      },
      "type": "Feature",
      "properties": {
        "hierarchy": [
          "tgn:2096532",
          "tgn:1000001",
          "tgn:2001734",
          "tgn:7012149",
          "tgn:7007712",
          "tgn:7029392"
        ],
        "placetype": [
          "aat:300008347"
        ],
        "id": 2096532,
        "name:xx": "Rantowles"
      }
    },
    {
      "geometry": {
        "type": "Point",
        "coordinates": [
          -80.25,
          32.75
        ]
      },
      "type": "Feature",
      "properties": {
        "hierarchy": [
          "tgn:2096533",
          "tgn:1000001",
          "tgn:2001734",
          "tgn:7012149",
          "tgn:7007712",
          "tgn:7029392"
        ],
        "placetype": [
          "aat:300008347"
        ],
        "id": 2096533,
        "name:xx": "Ravenel"
      }
    },
    {
      "geometry": {
        "type": "Point",
        "coordinates": [
          -81.2333,
          33.9167
        ]
      },
      "type": "Feature",
      "properties": {
        "hierarchy": [
          "tgn:2096535",
          "tgn:1000001",
          "tgn:7012149",
          "tgn:2001756",
          "tgn:7007712",
          "tgn:7029392"
        ],
        "placetype": [
          "aat:300008347"
        ],
        "id": 2096535,
        "name:xx": "Red Bank"
      }
    },
    {
      "geometry": {
        "type": "Point",
        "coordinates": [
          -78.8333,
          33.9
        ]
      },
      "type": "Feature",
      "properties": {
        "hierarchy": [
          "tgn:2096536",
          "tgn:1000001",
          "tgn:7012149",
          "tgn:2001750",
          "tgn:7007712",
          "tgn:7029392"
        ],
        "placetype": [
          "aat:300008347"
        ],
        "id": 2096536,
        "name:xx": "Red Bluff Crossroads"
      }
    },
    {
      "geometry": {
        "type": "Point",
        "coordinates": [
          -80.4,
          34.1667
        ]
      },
      "type": "Feature",
      "properties": {
        "hierarchy": [
          "tgn:2096537",
          "tgn:1000001",
          "tgn:7012149",
          "tgn:2001755",
          "tgn:7007712",
          "tgn:7029392"
        ],
        "placetype": [
          "aat:300008347",
          "aat:300387210"
        ],
        "id": 2096537,
        "name:xx": "Red Hill"
      }
    }
  ]
}
