{
  "type": "FeatureCollection",
  "features": [
    {
      "geometry": {
        "type": "Point",
        "coordinates": [
          -71.8333,
          -13.4167
        ]
      },
      "type": "Feature",
      "properties": {
        "hierarchy": [
          "tgn:1099870",
          "tgn:1000584",
          "tgn:1000002",
          "tgn:1000056",
          "tgn:7029392"
        ],
        "placetype": [
          "aat:300008347"
        ],
        "id": 1099870,
        "name:xx": "Pisac"
      }
    },
    {
      "geometry": {
        "type": "Point",
        "coordinates": [
          12.2667,
          41.7667
        ]
      },
      "type": "Feature",
      "properties": {
        "hierarchy": [
          "tgn:1099873",
          "tgn:7003138",
          "tgn:1000003",
          "tgn:7003080",
          "tgn:1000080",
          "tgn:7029392"
        ],
        "placetype": [
          "aat:300387004",
          "aat:300000372",
          "aat:300008057"
        ],
        "id": 1099873,
        "name:xx": "Porto di Traiano, Necropoli del"
      }
    },
    {
      "geometry": {
        "type": "Point",
        "coordinates": [
          24,
          37.6667
        ]
      },
      "type": "Feature",
      "properties": {
        "hierarchy": [
          "tgn:1099874",
          "tgn:7002681",
          "tgn:7001395",
          "tgn:1000003",
          "tgn:1000074",
          "tgn:7029392"
        ],
        "placetype": [
          "aat:300008347",
          "aat:300167671"
        ],
        "id": 1099874,
        "name:xx": "Possidhonia"
      }
    },
    {
      "geometry": {
        "type": "Point",
        "coordinates": [
          16.5667,
          41.2
        ]
      },
      "type": "Feature",
      "properties": {
        "hierarchy": [
          "tgn:1099876",
          "tgn:7003248",
          "tgn:1000003",
          "tgn:7010380",
          "tgn:1000080",
          "tgn:7029392"
        ],
        "placetype": [
          "aat:300008347",
          "aat:300167671"
        ],
        "id": 1099876,
        "name:xx": "Pulo"
      }
    },
    {
      "geometry": {
        "type": "Point",
        "coordinates": [
          36.5833,
          31.8
        ]
      },
      "type": "Feature",
      "properties": {
        "hierarchy": [
          "tgn:1099878",
          "tgn:1002055",
          "tgn:1000004",
          "tgn:1000121",
          "tgn:7029392"
        ],
        "placetype": [
          "aat:300008347",
          "aat:300167671"
        ],
        "id": 1099878,
        "name:xx": "Qusayr ʻAmra"
      }
    },
    {
      "geometry": {
        "type": "Point",
        "coordinates": [
          36.05,
          31.5833
        ]
      },
      "type": "Feature",
      "properties": {
        "hierarchy": [
          "tgn:1099879",
          "tgn:1002055",
          "tgn:1000004",
          "tgn:1000121",
          "tgn:7029392"
        ],
        "placetype": [
          "aat:300008347",
          "aat:300167671"
        ],
        "id": 1099879,
        "name:xx": "Qaṣr Ḍabʻah"
      }
    }
  ]
}
