{
  "geometry": {
    "type": "Point",
    "coordinates": [
      -105.9667,
      38.75
    ]
  },
  "type": "Feature",
  "properties": {
    "hierarchy": [
      "tgn:2453688",
      "tgn:1000001",
      "tgn:2000199",
      "tgn:7012149",
      "tgn:7007158",
      "tgn:7029392"
    ],
    "placetype": [
      "aat:300008706"
    ],
    "id": 2453688,
    "name:xx": "Little Cottonwood Creek"
  }
}
