{
  "geometry": {
    "type": "Point",
    "coordinates": [
      -94.75,
      38.0833
    ]
  },
  "type": "Feature",
  "properties": {
    "hierarchy": [
      "tgn:2761058",
      "tgn:1000001",
      "tgn:7012149",
      "tgn:7007254",
      "tgn:7029392"
    ],
    "placetype": [
      "aat:300008706"
    ],
    "id": 2761058,
    "name:xx": "West Laberdie Creek"
  }
}
