{
  "geometry": {
    "type": "Point",
    "coordinates": [
      -90.05,
      48.05
    ]
  },
  "type": "Feature",
  "properties": {
    "hierarchy": [
      "tgn:2456810",
      "tgn:1000001",
      "tgn:2001014",
      "tgn:7012149",
      "tgn:7007521",
      "tgn:7029392"
    ],
    "placetype": [
      "aat:300008680"
    ],
    "id": 2456810,
    "name:xx": "Little John Lake"
  }
}
