{
  "geometry": {
    "type": "Point",
    "coordinates": [
      -84.99,
      11.172
    ]
  },
  "type": "Feature",
  "properties": {
    "hierarchy": [
      "tgn:1010306",
      "tgn:1000738",
      "tgn:1000001",
      "tgn:7005562",
      "tgn:7029392"
    ],
    "placetype": [
      "aat:300386854"
    ],
    "id": 1010306,
    "name:xx": "Solentiname, Archipiélago de"
  }
}
