{
  "geometry": {
    "type": "Point",
    "coordinates": [
      -122.05,
      46.1833
    ]
  },
  "type": "Feature",
  "properties": {
    "hierarchy": [
      "tgn:2265476",
      "tgn:1000001",
      "tgn:7012149",
      "tgn:1002897",
      "tgn:7007920",
      "tgn:7029392"
    ],
    "placetype": [
      "aat:300008680"
    ],
    "id": 2265476,
    "name:xx": "Crane Lake"
  }
}
