{
  "geometry": {
    "type": "Point",
    "coordinates": [
      -81.7667,
      40.6833
    ]
  },
  "type": "Feature",
  "properties": {
    "hierarchy": [
      "tgn:2461392",
      "tgn:1000001",
      "tgn:7012149",
      "tgn:1003007",
      "tgn:7007706",
      "tgn:7029392"
    ],
    "placetype": [
      "aat:300008706"
    ],
    "id": 2461392,
    "name:xx": "Little Sugar Creek"
  }
}
