{
  "geometry": {
    "type": "Point",
    "coordinates": [
      -88.9833,
      35.1167
    ]
  },
  "type": "Feature",
  "properties": {
    "hierarchy": [
      "tgn:2261949",
      "tgn:1000001",
      "tgn:7012149",
      "tgn:2001871",
      "tgn:7007825",
      "tgn:7029392"
    ],
    "placetype": [
      "aat:300008699"
    ],
    "id": 2261949,
    "name:xx": "Covington Branch"
  }
}
