{
  "geometry": {
    "type": "Point",
    "coordinates": [
      -166.95,
      53.4167
    ]
  },
  "type": "Feature",
  "properties": {
    "hierarchy": [
      "tgn:2444162",
      "tgn:7030516",
      "tgn:7006450",
      "tgn:1000001",
      "tgn:7012149",
      "tgn:7029392"
    ],
    "placetype": [
      "aat:300132348"
    ],
    "id": 2444162,
    "name:xx": "Label Reef"
  }
}
