{
  "geometry": {
    "type": "Point",
    "coordinates": [
      14.4333,
      36.8667
    ]
  },
  "type": "Feature",
  "properties": {
    "hierarchy": [
      "tgn:1124944",
      "tgn:1000003",
      "tgn:7003122",
      "tgn:1001737",
      "tgn:1000080",
      "tgn:7029392"
    ],
    "placetype": [
      "aat:300008707"
    ],
    "id": 1124944,
    "name:xx": "Ippari"
  }
}
