{
  "geometry": {
    "type": "Point",
    "coordinates": [
      -106.4667,
      38.65
    ]
  },
  "type": "Feature",
  "properties": {
    "hierarchy": [
      "tgn:2488639",
      "tgn:1000001",
      "tgn:7012149",
      "tgn:2000217",
      "tgn:7007158",
      "tgn:7029392"
    ],
    "placetype": [
      "aat:300008680"
    ],
    "id": 2488639,
    "name:xx": "Maid Lake"
  }
}
