{
  "geometry": {
    "type": "Point",
    "coordinates": [
      74.47681,
      32.806863
    ]
  },
  "type": "Feature",
  "properties": {
    "hierarchy": [
      "tgn:7591263",
      "tgn:1000004",
      "tgn:7000198",
      "tgn:7000799",
      "tgn:7029392"
    ],
    "placetype": [
      "aat:300008347"
    ],
    "name:en": "Budwāl",
    "id": 7591263
  }
}
