{
  "geometry": {
    "type": "Point",
    "coordinates": [
      -107.1833,
      39.3333
    ]
  },
  "type": "Feature",
  "properties": {
    "hierarchy": [
      "tgn:2446463",
      "tgn:1000001",
      "tgn:7012149",
      "tgn:7007158",
      "tgn:2000240",
      "tgn:7029392"
    ],
    "placetype": [
      "aat:300008680"
    ],
    "id": 2446463,
    "name:xx": "Lewis Lake"
  }
}
