{
  "geometry": {
    "type": "Point",
    "coordinates": [
      -88.3667,
      33.3333
    ]
  },
  "type": "Feature",
  "properties": {
    "hierarchy": [
      "tgn:2182490",
      "tgn:1000001",
      "tgn:7012149",
      "tgn:2001129",
      "tgn:7007522",
      "tgn:7029392"
    ],
    "placetype": [
      "aat:300132348"
    ],
    "id": 2182490,
    "name:xx": "Blue Rock"
  }
}
