{
  "geometry": {
    "type": "Point",
    "coordinates": [
      -90.7667,
      36.0833
    ]
  },
  "type": "Feature",
  "properties": {
    "hierarchy": [
      "tgn:2537365",
      "tgn:1000001",
      "tgn:7016172",
      "tgn:7012149",
      "tgn:2000132",
      "tgn:7029392"
    ],
    "placetype": [
      "aat:300008699"
    ],
    "id": 2537365,
    "name:xx": "Negro Head Slough"
  }
}
