{
  "geometry": {
    "type": "Point",
    "coordinates": [
      -80.25,
      39.3667
    ]
  },
  "type": "Feature",
  "properties": {
    "hierarchy": [
      "tgn:2119492",
      "tgn:1000001",
      "tgn:7012149",
      "tgn:2002267",
      "tgn:7013961",
      "tgn:7029392"
    ],
    "placetype": [
      "aat:300008347"
    ],
    "id": 2119492,
    "name:xx": "Owings"
  }
}
