{
  "geometry": {
    "type": "Point",
    "coordinates": [
      -112.4833,
      36.9167
    ]
  },
  "type": "Feature",
  "properties": {
    "hierarchy": [
      "tgn:2425384",
      "tgn:1000001",
      "tgn:7006451",
      "tgn:2000092",
      "tgn:7012149",
      "tgn:7029392"
    ],
    "placetype": [
      "aat:300008701"
    ],
    "id": 2425384,
    "name:xx": "Johnson Run"
  }
}
