{
  "type": "FeatureCollection",
  "features": [
    {
      "geometry": {
        "type": "Point",
        "coordinates": [
          22.966667,
          36.2
        ]
      },
      "type": "Feature",
      "properties": {
        "hierarchy": [
          "tgn:7231730",
          "tgn:7002745",
          "tgn:7017076",
          "tgn:1000003",
          "tgn:1000074",
          "tgn:7029392"
        ],
        "placetype": [
          "aat:300008347"
        ],
        "id": 7231730,
        "name:xx": "Kalisperiánika"
      }
    },
    {
      "geometry": {
        "type": "Point",
        "coordinates": [
          24.383333,
          35.233333
        ]
      },
      "type": "Feature",
      "properties": {
        "hierarchy": [
          "tgn:7231731",
          "tgn:7002690",
          "tgn:7012056",
          "tgn:1000003",
          "tgn:1000074",
          "tgn:7029392"
        ],
        "placetype": [
          "aat:300008347"
        ],
        "id": 7231731,
        "name:xx": "Kalí Sikéa"
      }
    },
    {
      "geometry": {
        "type": "Point",
        "coordinates": [
          23.7,
          39.15
        ]
      },
      "type": "Feature",
      "properties": {
        "hierarchy": [
          "tgn:7231732",
          "tgn:7002751",
          "tgn:7001399",
          "tgn:1000003",
          "tgn:1000074",
          "tgn:7029392"
        ],
        "placetype": [
          "aat:300008850"
        ],
        "id": 7231732,
        "name:xx": "Kalís, Kávos"
      }
    },
    {
      "geometry": {
        "type": "Point",
        "coordinates": [
          21.283333,
          40.083333
        ]
      },
      "type": "Feature",
      "properties": {
        "hierarchy": [
          "tgn:7231733",
          "tgn:7002721",
          "tgn:7002715",
          "tgn:1000003",
          "tgn:1000074",
          "tgn:7029392"
        ],
        "placetype": [
          "aat:300008347"
        ],
        "id": 7231733,
        "name:xx": "Kalirákhi"
      }
    },
    {
      "geometry": {
        "type": "Point",
        "coordinates": [
          20.833333,
          37.8
        ]
      },
      "type": "Feature",
      "properties": {
        "hierarchy": [
          "tgn:7231734",
          "tgn:7011167",
          "tgn:7001338",
          "tgn:1000003",
          "tgn:1000074",
          "tgn:7029392"
        ],
        "placetype": [
          "aat:300008347"
        ],
        "id": 7231734,
        "name:xx": "Kalipádhon"
      }
    },
    {
      "geometry": {
        "type": "Point",
        "coordinates": [
          21.7,
          36.816667
        ]
      },
      "type": "Feature",
      "properties": {
        "hierarchy": [
          "tgn:7231735",
          "tgn:7011369",
          "tgn:7017076",
          "tgn:1000003",
          "tgn:1000074",
          "tgn:7029392"
        ],
        "placetype": [
          "aat:300008791"
        ],
        "id": 7231735,
        "name:xx": "Kalióra, Nisís"
      }
    },
    {
      "geometry": {
        "type": "Point",
        "coordinates": [
          22.794444,
          41.115556
        ]
      },
      "type": "Feature",
      "properties": {
        "hierarchy": [
          "tgn:7231736",
          "tgn:7002725",
          "tgn:7002715",
          "tgn:1000003",
          "tgn:1000074",
          "tgn:7029392"
        ],
        "placetype": [
          "aat:300008347"
        ],
        "id": 7231736,
        "name:xx": "Kalíndria"
      }
    },
    {
      "geometry": {
        "type": "Point",
        "coordinates": [
          26.995556,
          36.943056
        ]
      },
      "type": "Feature",
      "properties": {
        "hierarchy": [
          "tgn:7231737",
          "tgn:7011330",
          "tgn:7002674",
          "tgn:1000003",
          "tgn:1000074",
          "tgn:7029392"
        ],
        "placetype": [
          "aat:300132316"
        ],
        "id": 7231737,
        "name:xx": "Kalýmnou, Órmos"
      }
    }
  ]
}
