{
  "geometry": {
    "type": "Point",
    "coordinates": [
      6.8667,
      46.1833
    ]
  },
  "type": "Feature",
  "properties": {
    "hierarchy": [
      "tgn:1063984",
      "tgn:1000003",
      "tgn:7003762",
      "tgn:7011731",
      "tgn:7029392"
    ],
    "placetype": [
      "aat:300008347"
    ],
    "id": 1063984,
    "name:xx": "Champéry"
  }
}
