{
  "geometry": {
    "type": "Point",
    "coordinates": [
      -90.5167,
      43.7333
    ]
  },
  "type": "Feature",
  "properties": {
    "hierarchy": [
      "tgn:2193782",
      "tgn:1000001",
      "tgn:7012149",
      "tgn:7007922",
      "tgn:7029392"
    ],
    "placetype": [
      "aat:300008761"
    ],
    "id": 2193782,
    "name:xx": "Brey Valley"
  }
}
