{
  "type": "FeatureCollection",
  "features": [
    {
      "geometry": {
        "type": "Point",
        "coordinates": [
          -115.8333,
          46.5833
        ]
      },
      "type": "Feature",
      "properties": {
        "hierarchy": [
          "tgn:2603190",
          "tgn:1000001",
          "tgn:2000469",
          "tgn:7012149",
          "tgn:7007250",
          "tgn:7029392"
        ],
        "placetype": [
          "aat:300008706"
        ],
        "id": 2603190,
        "name:xx": "Quartz Creek"
      }
    },
    {
      "geometry": {
        "type": "Point",
        "coordinates": [
          -115.3833,
          47.25
        ]
      },
      "type": "Feature",
      "properties": {
        "hierarchy": [
          "tgn:2603191",
          "tgn:1000001",
          "tgn:7012149",
          "tgn:2000491",
          "tgn:7007250",
          "tgn:7029392"
        ],
        "placetype": [
          "aat:300008706"
        ],
        "id": 2603191,
        "name:xx": "Quartz Creek"
      }
    },
    {
      "geometry": {
        "type": "Point",
        "coordinates": [
          -115.15,
          47.5167
        ]
      },
      "type": "Feature",
      "properties": {
        "hierarchy": [
          "tgn:2603192",
          "tgn:1000001",
          "tgn:7012149",
          "tgn:2001304",
          "tgn:7007524",
          "tgn:7029392"
        ],
        "placetype": [
          "aat:300008706"
        ],
        "id": 2603192,
        "name:xx": "Quartz Creek"
      }
    },
    {
      "geometry": {
        "type": "Point",
        "coordinates": [
          -112.1333,
          46.4
        ]
      },
      "type": "Feature",
      "properties": {
        "hierarchy": [
          "tgn:2603193",
          "tgn:1000001",
          "tgn:7012149",
          "tgn:2001281",
          "tgn:7007524",
          "tgn:7029392"
        ],
        "placetype": [
          "aat:300008706"
        ],
        "id": 2603193,
        "name:xx": "Quartz Creek"
      }
    },
    {
      "geometry": {
        "type": "Point",
        "coordinates": [
          -114.8833,
          46.9833
        ]
      },
      "type": "Feature",
      "properties": {
        "hierarchy": [
          "tgn:2603194",
          "tgn:1000001",
          "tgn:7012149",
          "tgn:2001290",
          "tgn:7007524",
          "tgn:7029392"
        ],
        "placetype": [
          "aat:300008706"
        ],
        "id": 2603194,
        "name:xx": "Quartz Creek"
      }
    },
    {
      "geometry": {
        "type": "Point",
        "coordinates": [
          -114,
          48.8333
        ]
      },
      "type": "Feature",
      "properties": {
        "hierarchy": [
          "tgn:2603195",
          "tgn:1000001",
          "tgn:7012149",
          "tgn:2001274",
          "tgn:7007524",
          "tgn:7029392"
        ],
        "placetype": [
          "aat:300008706"
        ],
        "id": 2603195,
        "name:xx": "Quartz Creek"
      }
    },
    {
      "geometry": {
        "type": "Point",
        "coordinates": [
          -112.0333,
          45.5
        ]
      },
      "type": "Feature",
      "properties": {
        "hierarchy": [
          "tgn:2603196",
          "tgn:1000001",
          "tgn:7012149",
          "tgn:2001288",
          "tgn:7007524",
          "tgn:7029392"
        ],
        "placetype": [
          "aat:300008706"
        ],
        "id": 2603196,
        "name:xx": "Quartz Creek"
      }
    },
    {
      "geometry": {
        "type": "Point",
        "coordinates": [
          -115.6833,
          48.5667
        ]
      },
      "type": "Feature",
      "properties": {
        "hierarchy": [
          "tgn:2603197",
          "tgn:1000001",
          "tgn:7012149",
          "tgn:2001286",
          "tgn:7007524",
          "tgn:7029392"
        ],
        "placetype": [
          "aat:300008706"
        ],
        "id": 2603197,
        "name:xx": "Quartz Creek"
      }
    },
    {
      "geometry": {
        "type": "Point",
        "coordinates": [
          -120.7833,
          42.3333
        ]
      },
      "type": "Feature",
      "properties": {
        "hierarchy": [
          "tgn:2603198",
          "tgn:1000001",
          "tgn:7012149",
          "tgn:2001715",
          "tgn:7007708",
          "tgn:7029392"
        ],
        "placetype": [
          "aat:300008706"
        ],
        "id": 2603198,
        "name:xx": "Quartz Creek"
      }
    },
    {
      "geometry": {
        "type": "Point",
        "coordinates": [
          -123.4667,
          42.6
        ]
      },
      "type": "Feature",
      "properties": {
        "hierarchy": [
          "tgn:2603199",
          "tgn:1000001",
          "tgn:7012149",
          "tgn:2001713",
          "tgn:7007708",
          "tgn:7029392"
        ],
        "placetype": [
          "aat:300008706"
        ],
        "id": 2603199,
        "name:xx": "Quartz Creek"
      }
    }
  ]
}
