{
  "geometry": {
    "type": "Point",
    "coordinates": [
      14.1167,
      5.55
    ]
  },
  "type": "Feature",
  "properties": {
    "hierarchy": [
      "tgn:1088168",
      "tgn:1001245",
      "tgn:7001242",
      "tgn:1000153",
      "tgn:7029392"
    ],
    "placetype": [
      "aat:300008347"
    ],
    "id": 1088168,
    "name:xx": "Bétaré Oya"
  }
}
