{
  "geometry": {
    "type": "Point",
    "coordinates": [
      -84.3333,
      36.0833
    ]
  },
  "type": "Feature",
  "properties": {
    "hierarchy": [
      "tgn:2436304",
      "tgn:2001837",
      "tgn:1000001",
      "tgn:7012149",
      "tgn:7007825",
      "tgn:7029392"
    ],
    "placetype": [
      "aat:300008761"
    ],
    "id": 2436304,
    "name:xx": "Khotan Hollow"
  }
}
