{
  "type": "FeatureCollection",
  "features": [
    {
      "geometry": {
        "type": "Point",
        "coordinates": [
          12.716667,
          51.85
        ]
      },
      "type": "Feature",
      "properties": {
        "hierarchy": [
          "tgn:7160030",
          "tgn:1000003",
          "tgn:7003687",
          "tgn:7000084",
          "tgn:7029392"
        ],
        "placetype": [
          "aat:300008347"
        ],
        "id": 7160030,
        "name:xx": "Hohndorf"
      }
    },
    {
      "geometry": {
        "type": "Point",
        "coordinates": [
          12.916667,
          51.7
        ]
      },
      "type": "Feature",
      "properties": {
        "hierarchy": [
          "tgn:7160031",
          "tgn:1000003",
          "tgn:7003687",
          "tgn:7000084",
          "tgn:7029392"
        ],
        "placetype": [
          "aat:300008347"
        ],
        "id": 7160031,
        "name:xx": "Hohndorf"
      }
    },
    {
      "geometry": {
        "type": "Point",
        "coordinates": [
          13.6,
          51.25
        ]
      },
      "type": "Feature",
      "properties": {
        "hierarchy": [
          "tgn:7160032",
          "tgn:1000003",
          "tgn:7003685",
          "tgn:7000084",
          "tgn:7029392"
        ],
        "placetype": [
          "aat:300008347"
        ],
        "id": 7160032,
        "name:xx": "Hohndorf"
      }
    },
    {
      "geometry": {
        "type": "Point",
        "coordinates": [
          11.65,
          51.15
        ]
      },
      "type": "Feature",
      "properties": {
        "hierarchy": [
          "tgn:7160033",
          "tgn:1000003",
          "tgn:7003687",
          "tgn:7000084",
          "tgn:7029392"
        ],
        "placetype": [
          "aat:300008347"
        ],
        "id": 7160033,
        "name:xx": "Hohndorf"
      }
    },
    {
      "geometry": {
        "type": "Point",
        "coordinates": [
          13.083333,
          50.716667
        ]
      },
      "type": "Feature",
      "properties": {
        "hierarchy": [
          "tgn:7160035",
          "tgn:1000003",
          "tgn:7003685",
          "tgn:7000084",
          "tgn:7029392"
        ],
        "placetype": [
          "aat:300008347"
        ],
        "id": 7160035,
        "name:xx": "Hohndorf"
      }
    },
    {
      "geometry": {
        "type": "Point",
        "coordinates": [
          12.133333,
          50.616667
        ]
      },
      "type": "Feature",
      "properties": {
        "hierarchy": [
          "tgn:7160036",
          "tgn:1000003",
          "tgn:7003689",
          "tgn:7000084",
          "tgn:7029392"
        ],
        "placetype": [
          "aat:300008347"
        ],
        "id": 7160036,
        "name:xx": "Hohndorf"
      }
    },
    {
      "geometry": {
        "type": "Point",
        "coordinates": [
          10.416667,
          50.8
        ]
      },
      "type": "Feature",
      "properties": {
        "hierarchy": [
          "tgn:7160037",
          "tgn:1000003",
          "tgn:7003689",
          "tgn:7000084",
          "tgn:7029392"
        ],
        "placetype": [
          "aat:300008777"
        ],
        "id": 7160037,
        "name:xx": "Höhn-Berge"
      }
    },
    {
      "geometry": {
        "type": "Point",
        "coordinates": [
          10.666667,
          50.45
        ]
      },
      "type": "Feature",
      "properties": {
        "hierarchy": [
          "tgn:7160038",
          "tgn:1000003",
          "tgn:7003689",
          "tgn:7000084",
          "tgn:7029392"
        ],
        "placetype": [
          "aat:300008777"
        ],
        "id": 7160038,
        "name:xx": "Höhn-Berg"
      }
    },
    {
      "geometry": {
        "type": "Point",
        "coordinates": [
          12.783333,
          51.116667
        ]
      },
      "type": "Feature",
      "properties": {
        "hierarchy": [
          "tgn:7160039",
          "tgn:1000003",
          "tgn:7003685",
          "tgn:7000084",
          "tgn:7029392"
        ],
        "placetype": [
          "aat:300008347"
        ],
        "id": 7160039,
        "name:xx": "Hohnbach"
      }
    }
  ]
}
