{
  "geometry": {
    "type": "Point",
    "coordinates": [
      -97.7333,
      27.6667
    ]
  },
  "type": "Feature",
  "properties": {
    "hierarchy": [
      "tgn:2103872",
      "tgn:1000001",
      "tgn:7012149",
      "tgn:2002049",
      "tgn:7007826",
      "tgn:7029392"
    ],
    "placetype": [
      "aat:300008347"
    ],
    "id": 2103872,
    "name:xx": "Driscoll"
  }
}
