{
  "type": "FeatureCollection",
  "features": [
    {
      "geometry": {
        "type": "Point",
        "coordinates": [
          -90.95,
          43.0833
        ]
      },
      "type": "Feature",
      "properties": {
        "hierarchy": [
          "tgn:2436430",
          "tgn:1000001",
          "tgn:2002316",
          "tgn:7012149",
          "tgn:7007922",
          "tgn:7029392"
        ],
        "placetype": [
          "aat:300008746"
        ],
        "id": 2436430,
        "name:xx": "Kickapoo Indian Caverns"
      }
    },
    {
      "geometry": {
        "type": "Point",
        "coordinates": [
          -94.9167,
          39.3833
        ]
      },
      "type": "Feature",
      "properties": {
        "hierarchy": [
          "tgn:2436431",
          "tgn:1000001",
          "tgn:7012149",
          "tgn:2000711",
          "tgn:7007254",
          "tgn:7029392"
        ],
        "placetype": [
          "aat:300008791"
        ],
        "id": 2436431,
        "name:xx": "Kickapoo Island"
      }
    },
    {
      "geometry": {
        "type": "Point",
        "coordinates": [
          -90.7333,
          39.1833
        ]
      },
      "type": "Feature",
      "properties": {
        "hierarchy": [
          "tgn:2436432",
          "tgn:1000001",
          "tgn:7012149",
          "tgn:1002598",
          "tgn:7007523",
          "tgn:7029392"
        ],
        "placetype": [
          "aat:300008791"
        ],
        "id": 2436432,
        "name:xx": "Kickapoo Island"
      }
    },
    {
      "geometry": {
        "type": "Point",
        "coordinates": [
          -94.9167,
          39.3833
        ]
      },
      "type": "Feature",
      "properties": {
        "hierarchy": [
          "tgn:2436433",
          "tgn:1000001",
          "tgn:7012149",
          "tgn:2001231",
          "tgn:7007523",
          "tgn:7029392"
        ],
        "placetype": [
          "aat:300008791"
        ],
        "id": 2436433,
        "name:xx": "Kickapoo Island"
      }
    },
    {
      "geometry": {
        "type": "Point",
        "coordinates": [
          -89.4833,
          46.2167
        ]
      },
      "type": "Feature",
      "properties": {
        "hierarchy": [
          "tgn:2436434",
          "tgn:1000001",
          "tgn:7012149",
          "tgn:2000960",
          "tgn:7007520",
          "tgn:7029392"
        ],
        "placetype": [
          "aat:300008680"
        ],
        "id": 2436434,
        "name:xx": "Kickapoo Lake"
      }
    },
    {
      "geometry": {
        "type": "Point",
        "coordinates": [
          -90.3333,
          32.4
        ]
      },
      "type": "Feature",
      "properties": {
        "hierarchy": [
          "tgn:2436435",
          "tgn:1000001",
          "tgn:7012149",
          "tgn:2001110",
          "tgn:7007522",
          "tgn:7029392"
        ],
        "placetype": [
          "aat:300006191"
        ],
        "id": 2436435,
        "name:xx": "Kickapoo Lake"
      }
    },
    {
      "geometry": {
        "type": "Point",
        "coordinates": [
          -96.2,
          31.0667
        ]
      },
      "type": "Feature",
      "properties": {
        "hierarchy": [
          "tgn:2436436",
          "tgn:1000001",
          "tgn:7012149",
          "tgn:1002590",
          "tgn:7007826",
          "tgn:7029392"
        ],
        "placetype": [
          "aat:300006191"
        ],
        "id": 2436436,
        "name:xx": "Kickapoo Lake"
      }
    },
    {
      "geometry": {
        "type": "Point",
        "coordinates": [
          -100.3333,
          31.9667
        ]
      },
      "type": "Feature",
      "properties": {
        "hierarchy": [
          "tgn:2436437",
          "tgn:1000001",
          "tgn:7012149",
          "tgn:2001958",
          "tgn:7007826",
          "tgn:7029392"
        ],
        "placetype": [
          "aat:300008798"
        ],
        "id": 2436437,
        "name:xx": "Kickapoo Mountain"
      }
    },
    {
      "geometry": {
        "type": "Point",
        "coordinates": [
          -95.4667,
          32.0167
        ]
      },
      "type": "Feature",
      "properties": {
        "hierarchy": [
          "tgn:2436438",
          "tgn:1002148",
          "tgn:1000001",
          "tgn:7012149",
          "tgn:7007826",
          "tgn:7029392"
        ],
        "placetype": [
          "aat:300008798"
        ],
        "id": 2436438,
        "name:xx": "Kickapoo Mountain"
      }
    }
  ]
}
