{
  "geometry": {
    "type": "Point",
    "coordinates": [
      -80.3833,
      34.1167
    ]
  },
  "type": "Feature",
  "properties": {
    "hierarchy": [
      "tgn:2263149",
      "tgn:1000001",
      "tgn:7012149",
      "tgn:7007712",
      "tgn:7029392"
    ],
    "placetype": [
      "aat:300008699"
    ],
    "id": 2263149,
    "name:xx": "Cowpen Swamp"
  }
}
