{
  "geometry": {
    "type": "Point",
    "coordinates": [
      30.90046,
      28.707335
    ]
  },
  "type": "Feature",
  "properties": {
    "hierarchy": [
      "tgn:1095765",
      "tgn:7001242",
      "tgn:7016833",
      "tgn:1001088",
      "tgn:7029392"
    ],
    "placetype": [
      "aat:300008347"
    ],
    "id": 1095765,
    "name:xx": "Zāwiyat al Judhāmī"
  }
}
