{
  "geometry": {
    "type": "Point",
    "coordinates": [
      -99.5667,
      29.8833
    ]
  },
  "type": "Feature",
  "properties": {
    "hierarchy": [
      "tgn:2341155",
      "tgn:1000001",
      "tgn:7012149",
      "tgn:7007826",
      "tgn:7029392"
    ],
    "placetype": [
      "aat:300008761"
    ],
    "id": 2341155,
    "name:xx": "Frio Draw"
  }
}
