{
  "geometry": {
    "type": "Point",
    "coordinates": [
      -114.45,
      48.4667
    ]
  },
  "type": "Feature",
  "properties": {
    "hierarchy": [
      "tgn:2191150",
      "tgn:1000001",
      "tgn:7012149",
      "tgn:2001274",
      "tgn:7007524",
      "tgn:7029392"
    ],
    "placetype": [
      "aat:300008680"
    ],
    "id": 2191150,
    "name:xx": "Boyle Lake"
  }
}
