{
  "geometry": {
    "type": "Point",
    "coordinates": [
      -157.6167,
      66.3167
    ]
  },
  "type": "Feature",
  "properties": {
    "hierarchy": [
      "tgn:2172921",
      "tgn:7006450",
      "tgn:1000001",
      "tgn:7012149",
      "tgn:2000089",
      "tgn:7029392"
    ],
    "placetype": [
      "aat:300008706"
    ],
    "id": 2172921,
    "name:xx": "Billy Hawk Creek"
  }
}
