{
  "geometry": {
    "type": "Point",
    "coordinates": [
      114.2667,
      22.2167
    ]
  },
  "type": "Feature",
  "properties": {
    "hierarchy": [
      "tgn:1011427",
      "tgn:7018484",
      "tgn:7004543",
      "tgn:1000004",
      "tgn:7004542",
      "tgn:1000111",
      "tgn:7029392"
    ],
    "placetype": [
      "aat:300387499"
    ],
    "id": 1011427,
    "name:xx": "Hok Tsui"
  }
}
