{
  "geometry": {
    "type": "Point",
    "coordinates": [
      131.7833,
      34.3333
    ]
  },
  "type": "Feature",
  "properties": {
    "hierarchy": [
      "tgn:1103810",
      "tgn:7000897",
      "tgn:1001040",
      "tgn:1000004",
      "tgn:1000120",
      "tgn:7029392"
    ],
    "placetype": [
      "aat:300008795"
    ],
    "id": 1103810,
    "name:xx": "Azamiga-dake"
  }
}
