{
  "geometry": {
    "type": "Point",
    "coordinates": [
      -82.85,
      36.4667
    ]
  },
  "type": "Feature",
  "properties": {
    "hierarchy": [
      "tgn:2101733",
      "tgn:1000001",
      "tgn:7012149",
      "tgn:2001873",
      "tgn:7007825",
      "tgn:7029392"
    ],
    "placetype": [
      "aat:300008347"
    ],
    "id": 2101733,
    "name:xx": "Surgoinsville"
  }
}
