{
  "geometry": {
    "type": "Point",
    "coordinates": [
      -78.85,
      42.0833
    ]
  },
  "type": "Feature",
  "properties": {
    "hierarchy": [
      "tgn:2248416",
      "tgn:1000001",
      "tgn:1002245",
      "tgn:7012149",
      "tgn:7007568",
      "tgn:7029392"
    ],
    "placetype": [
      "aat:300008347"
    ],
    "id": 2248416,
    "name:xx": "Cold Spring"
  }
}
