{
  "geometry": {
    "type": "Point",
    "coordinates": [
      -111.9333,
      39.4167
    ]
  },
  "type": "Feature",
  "properties": {
    "hierarchy": [
      "tgn:2238682",
      "tgn:1000001",
      "tgn:7012149",
      "tgn:2002112",
      "tgn:7007827",
      "tgn:7029392"
    ],
    "placetype": [
      "aat:300008706"
    ],
    "id": 2238682,
    "name:xx": "Chriss Creek"
  }
}
