{
  "geometry": {
    "type": "Point",
    "coordinates": [
      -91.6333,
      37.9833
    ]
  },
  "type": "Feature",
  "properties": {
    "hierarchy": [
      "tgn:2622654",
      "tgn:1000001",
      "tgn:7012149",
      "tgn:2001230",
      "tgn:7007523",
      "tgn:7029392"
    ],
    "placetype": [
      "aat:300008706"
    ],
    "id": 2622654,
    "name:xx": "Robinson Creek"
  }
}
