{
  "type": "FeatureCollection",
  "features": [
    {
      "geometry": {
        "type": "Point",
        "coordinates": [
          3.983333,
          51.816667
        ]
      },
      "type": "Feature",
      "properties": {
        "hierarchy": [
          "tgn:7032126",
          "tgn:1000003",
          "tgn:7003632",
          "tgn:7016845",
          "tgn:7029392"
        ],
        "placetype": [
          "aat:300008347"
        ],
        "name:nl": "Goedereede",
        "id": 7032126
      }
    },
    {
      "geometry": {
        "type": "Point",
        "coordinates": [
          3.933333,
          51.816667
        ]
      },
      "type": "Feature",
      "properties": {
        "hierarchy": [
          "tgn:7032128",
          "tgn:1000003",
          "tgn:7003632",
          "tgn:7032127",
          "tgn:7016845",
          "tgn:7029392"
        ],
        "placetype": [
          "aat:300055621"
        ],
        "name:nl": "Goeree",
        "id": 7032128
      }
    },
    {
      "geometry": {
        "type": "Point",
        "coordinates": [
          9.266667,
          50.983333
        ]
      },
      "type": "Feature",
      "properties": {
        "hierarchy": [
          "tgn:7032129",
          "tgn:1000003",
          "tgn:7003678",
          "tgn:7000084",
          "tgn:7029392"
        ],
        "placetype": [
          "aat:300008347"
        ],
        "id": 7032129,
        "name:xx": "Neuenhain"
      }
    }
  ]
}
