{
  "geometry": {
    "type": "Point",
    "coordinates": [
      -97.4667,
      53.1667
    ]
  },
  "type": "Feature",
  "properties": {
    "hierarchy": [
      "tgn:1127440",
      "tgn:7005685",
      "tgn:1000001",
      "tgn:7005734",
      "tgn:7029392"
    ],
    "placetype": [
      "aat:300008707"
    ],
    "id": 1127440,
    "name:xx": "Mukutawa River"
  }
}
