{
  "geometry": {
    "type": "Point",
    "coordinates": [
      -86.3333,
      39.7167
    ]
  },
  "type": "Feature",
  "properties": {
    "hierarchy": [
      "tgn:2440330",
      "tgn:1000001",
      "tgn:7012149",
      "tgn:7007252",
      "tgn:7029392"
    ],
    "placetype": [
      "aat:300008706"
    ],
    "id": 2440330,
    "name:xx": "Klondike Creek"
  }
}
