{
  "geometry": {
    "type": "Point",
    "coordinates": [
      -111.2833,
      46.4833
    ]
  },
  "type": "Feature",
  "properties": {
    "hierarchy": [
      "tgn:2339197",
      "tgn:1000001",
      "tgn:2001263",
      "tgn:7012149",
      "tgn:7007524",
      "tgn:7029392"
    ],
    "placetype": [
      "aat:300008697"
    ],
    "id": 2339197,
    "name:xx": "Franks Spring"
  }
}
