{
  "geometry": {
    "type": "Point",
    "coordinates": [
      -85.7167,
      40.5833
    ]
  },
  "type": "Feature",
  "properties": {
    "hierarchy": [
      "tgn:2223447",
      "tgn:1000001",
      "tgn:7012149",
      "tgn:7007252",
      "tgn:7029392"
    ],
    "placetype": [
      "aat:300008706"
    ],
    "id": 2223447,
    "name:xx": "Cart Creek"
  }
}
