{
  "geometry": {
    "type": "Point",
    "coordinates": [
      -120.8333,
      37.55
    ]
  },
  "type": "Feature",
  "properties": {
    "hierarchy": [
      "tgn:2740293",
      "tgn:1000001",
      "tgn:7012149",
      "tgn:7007157",
      "tgn:1002915",
      "tgn:7029392"
    ],
    "placetype": [
      "aat:300006075"
    ],
    "id": 2740293,
    "name:xx": "Upper Lateral Number Two And One Half"
  }
}
