{
  "geometry": {
    "type": "Point",
    "coordinates": [
      -79.05,
      -43.0833
    ]
  },
  "type": "Feature",
  "properties": {
    "hierarchy": [
      "tgn:1004278",
      "tgn:7005685",
      "tgn:1000001",
      "tgn:7013154",
      "tgn:7029392"
    ],
    "placetype": [
      "aat:300008347"
    ],
    "id": 1004278,
    "name:xx": "Chippawa"
  }
}
