{
  "geometry": {
    "type": "Point",
    "coordinates": [
      -117.5833,
      46.3667
    ]
  },
  "type": "Feature",
  "properties": {
    "hierarchy": [
      "tgn:2712269",
      "tgn:1000001",
      "tgn:2002245",
      "tgn:7012149",
      "tgn:7007920",
      "tgn:7029392"
    ],
    "placetype": [
      "aat:300008798"
    ],
    "id": 2712269,
    "name:xx": "Tatman Mountain"
  }
}
