{
  "geometry": {
    "type": "Point",
    "coordinates": [
      -147.1667,
      68.55
    ]
  },
  "type": "Feature",
  "properties": {
    "hierarchy": [
      "tgn:2429630",
      "tgn:7006450",
      "tgn:1000001",
      "tgn:7012149",
      "tgn:7029392"
    ],
    "placetype": [
      "aat:300008707"
    ],
    "id": 2429630,
    "name:xx": "Junjik River"
  }
}
