{
  "geometry": {
    "type": "Point",
    "coordinates": [
      -98.7167,
      31.8667
    ]
  },
  "type": "Feature",
  "properties": {
    "hierarchy": [
      "tgn:2707699",
      "tgn:1000001",
      "tgn:7012149",
      "tgn:2001962",
      "tgn:7007826",
      "tgn:7029392"
    ],
    "placetype": [
      "aat:300008706"
    ],
    "id": 2707699,
    "name:xx": "Sweetwater Creek"
  }
}
