{
  "geometry": {
    "type": "Point",
    "coordinates": [
      -88.8667,
      46.3667
    ]
  },
  "type": "Feature",
  "properties": {
    "hierarchy": [
      "tgn:2715179",
      "tgn:1000001",
      "tgn:7012149",
      "tgn:2000966",
      "tgn:7007520",
      "tgn:7029392"
    ],
    "placetype": [
      "aat:300008706"
    ],
    "id": 2715179,
    "name:xx": "Tepee Creek"
  }
}
