{
  "type": "FeatureCollection",
  "features": [
    {
      "geometry": {
        "type": "Point",
        "coordinates": [
          -108.65,
          27.016667
        ]
      },
      "type": "Feature",
      "properties": {
        "hierarchy": [
          "tgn:7360330",
          "tgn:1000001",
          "tgn:1001960",
          "tgn:7005560",
          "tgn:7029392"
        ],
        "placetype": [
          "aat:300008795"
        ],
        "id": 7360330,
        "name:xx": "Cobre, Cerro"
      }
    },
    {
      "geometry": {
        "type": "Point",
        "coordinates": [
          -107.766667,
          27.516667
        ]
      },
      "type": "Feature",
      "properties": {
        "hierarchy": [
          "tgn:7360331",
          "tgn:7005581",
          "tgn:1000001",
          "tgn:7005560",
          "tgn:7029392"
        ],
        "placetype": [
          "aat:300008763"
        ],
        "id": 7360331,
        "name:xx": "Cobre, Barranca del"
      }
    },
    {
      "geometry": {
        "type": "Point",
        "coordinates": [
          -104.083333,
          25.266667
        ]
      },
      "type": "Feature",
      "properties": {
        "hierarchy": [
          "tgn:7360332",
          "tgn:7005583",
          "tgn:1000001",
          "tgn:7005560",
          "tgn:7029392"
        ],
        "placetype": [
          "aat:300008699"
        ],
        "id": 7360332,
        "name:xx": "Cobre, Arroyo del"
      }
    },
    {
      "geometry": {
        "type": "Point",
        "coordinates": [
          -105.916667,
          24.55
        ]
      },
      "type": "Feature",
      "properties": {
        "hierarchy": [
          "tgn:7360333",
          "tgn:7005583",
          "tgn:1000001",
          "tgn:7005560",
          "tgn:7029392"
        ],
        "placetype": [
          "aat:300008347"
        ],
        "id": 7360333,
        "name:xx": "Cobre"
      }
    },
    {
      "geometry": {
        "type": "Point",
        "coordinates": [
          -103.216667,
          18.85
        ]
      },
      "type": "Feature",
      "properties": {
        "hierarchy": [
          "tgn:7360334",
          "tgn:1000001",
          "tgn:7005590",
          "tgn:7005560",
          "tgn:7029392"
        ],
        "placetype": [
          "aat:300008347"
        ],
        "id": 7360334,
        "name:xx": "Cobre"
      }
    },
    {
      "geometry": {
        "type": "Point",
        "coordinates": [
          -101.55,
          17.933333
        ]
      },
      "type": "Feature",
      "properties": {
        "hierarchy": [
          "tgn:7360335",
          "tgn:7005585",
          "tgn:1000001",
          "tgn:7005560",
          "tgn:7029392"
        ],
        "placetype": [
          "aat:300008347"
        ],
        "id": 7360335,
        "name:xx": "Cobre"
      }
    },
    {
      "geometry": {
        "type": "Point",
        "coordinates": [
          -112.083333,
          31.583333
        ]
      },
      "type": "Feature",
      "properties": {
        "hierarchy": [
          "tgn:7360337",
          "tgn:1000001",
          "tgn:1001960",
          "tgn:7005560",
          "tgn:7029392"
        ],
        "placetype": [
          "aat:300008795"
        ],
        "id": 7360337,
        "name:xx": "Cobota, Sierra del"
      }
    },
    {
      "geometry": {
        "type": "Point",
        "coordinates": [
          -112.083333,
          31.55
        ]
      },
      "type": "Feature",
      "properties": {
        "hierarchy": [
          "tgn:7360338",
          "tgn:1000001",
          "tgn:1001960",
          "tgn:7005560",
          "tgn:7029392"
        ],
        "placetype": [
          "aat:300008798"
        ],
        "id": 7360338,
        "name:xx": "Cobota, El Picacho de"
      }
    },
    {
      "geometry": {
        "type": "Point",
        "coordinates": [
          -112.116667,
          31.6
        ]
      },
      "type": "Feature",
      "properties": {
        "hierarchy": [
          "tgn:7360339",
          "tgn:1000001",
          "tgn:1001960",
          "tgn:7005560",
          "tgn:7029392"
        ],
        "placetype": [
          "aat:300008347"
        ],
        "id": 7360339,
        "name:xx": "Cobota"
      }
    }
  ]
}
