{
  "geometry": {
    "type": "Point",
    "coordinates": [
      76.0167,
      42.35
    ]
  },
  "type": "Feature",
  "properties": {
    "hierarchy": [
      "tgn:1058043",
      "tgn:1000004",
      "tgn:7011479",
      "tgn:7006655",
      "tgn:7029392"
    ],
    "placetype": [
      "aat:300008347"
    ],
    "id": 1058043,
    "name:xx": "Orto-Tokoj"
  }
}
