{
  "geometry": {
    "type": "Point",
    "coordinates": [
      5.95,
      52.65
    ]
  },
  "type": "Feature",
  "properties": {
    "hierarchy": [
      "tgn:7274503",
      "tgn:7003615",
      "tgn:1000003",
      "tgn:7016845",
      "tgn:7029392"
    ],
    "placetype": [
      "aat:300006075"
    ],
    "name:nl": "Zwartemeertocht",
    "id": 7274503
  }
}
