{
  "geometry": {
    "type": "Point",
    "coordinates": [
      -110.25,
      34.0167
    ]
  },
  "type": "Feature",
  "properties": {
    "hierarchy": [
      "tgn:2229297",
      "tgn:1000001",
      "tgn:7006451",
      "tgn:7012149",
      "tgn:2000099",
      "tgn:7029392"
    ],
    "placetype": [
      "aat:300006191"
    ],
    "id": 2229297,
    "name:xx": "Cedar Mesa Tanks"
  }
}
