{
  "geometry": {
    "type": "Point",
    "coordinates": [
      -86.2333,
      40.7167
    ]
  },
  "type": "Feature",
  "properties": {
    "hierarchy": [
      "tgn:2666311",
      "tgn:1000001",
      "tgn:1002242",
      "tgn:7012149",
      "tgn:7007252",
      "tgn:7029392"
    ],
    "placetype": [
      "aat:300006075"
    ],
    "id": 2666311,
    "name:xx": "Sixby Ditch"
  }
}
