{
  "geometry": {
    "type": "Point",
    "coordinates": [
      -113.4667,
      38.9833
    ]
  },
  "type": "Feature",
  "properties": {
    "hierarchy": [
      "tgn:2180136",
      "tgn:1000001",
      "tgn:7012149",
      "tgn:2002114",
      "tgn:7007827",
      "tgn:7029392"
    ],
    "placetype": [
      "aat:300008761"
    ],
    "id": 2180136,
    "name:xx": "Blind Valley"
  }
}
