{
  "geometry": {
    "type": "Point",
    "coordinates": [
      77.05,
      39.1333
    ]
  },
  "type": "Feature",
  "properties": {
    "hierarchy": [
      "tgn:1072098",
      "tgn:1000004",
      "tgn:7001745",
      "tgn:1000111",
      "tgn:7029392"
    ],
    "placetype": [
      "aat:300008347"
    ],
    "id": 1072098,
    "name:xx": "Talimuashili"
  }
}
