{
  "geometry": {
    "type": "Point",
    "coordinates": [
      -70.55,
      -33.766667
    ]
  },
  "type": "Feature",
  "properties": {
    "hierarchy": [
      "tgn:7318541",
      "tgn:1001708",
      "tgn:1000049",
      "tgn:1000002",
      "tgn:7029392"
    ],
    "placetype": [
      "aat:300008699"
    ],
    "id": 7318541,
    "name:xx": "Corazón, Quebrada del"
  }
}
