{
  "geometry": {
    "type": "Point",
    "coordinates": [
      -133.95,
      57.45
    ]
  },
  "type": "Feature",
  "properties": {
    "hierarchy": [
      "tgn:2533159",
      "tgn:7006450",
      "tgn:1000001",
      "tgn:7012149",
      "tgn:7019760",
      "tgn:7029392"
    ],
    "placetype": [
      "aat:300008791"
    ],
    "id": 2533159,
    "name:xx": "Muse Island"
  }
}
