{
  "geometry": {
    "type": "Point",
    "coordinates": [
      -100.4667,
      29.7667
    ]
  },
  "type": "Feature",
  "properties": {
    "hierarchy": [
      "tgn:2330601",
      "tgn:1000001",
      "tgn:7012149",
      "tgn:2001980",
      "tgn:7007826",
      "tgn:7029392"
    ],
    "placetype": [
      "aat:300008706"
    ],
    "id": 2330601,
    "name:xx": "Flat Creek"
  }
}
