{
  "geometry": {
    "type": "Point",
    "coordinates": [
      -79.4833,
      39.6167
    ]
  },
  "type": "Feature",
  "properties": {
    "hierarchy": [
      "tgn:2513825",
      "tgn:1000001",
      "tgn:7012149",
      "tgn:2002288",
      "tgn:7013961",
      "tgn:7029392"
    ],
    "placetype": [
      "aat:300008699"
    ],
    "id": 2513825,
    "name:xx": "Mill Run"
  }
}
