{
  "type": "FeatureCollection",
  "features": [
    {
      "geometry": {
        "type": "Point",
        "coordinates": [
          -68.766667,
          -26.533333
        ]
      },
      "type": "Feature",
      "properties": {
        "hierarchy": [
          "tgn:7287670",
          "tgn:1001630",
          "tgn:1000049",
          "tgn:1000002",
          "tgn:7029392"
        ],
        "placetype": [
          "aat:300008795"
        ],
        "id": 7287670,
        "name:xx": "Juncalito, Cerro del"
      }
    },
    {
      "geometry": {
        "type": "Point",
        "coordinates": [
          -69.583333,
          -26.65
        ]
      },
      "type": "Feature",
      "properties": {
        "hierarchy": [
          "tgn:7287671",
          "tgn:1001630",
          "tgn:1000049",
          "tgn:1000002",
          "tgn:7029392"
        ],
        "placetype": [
          "aat:300008697"
        ],
        "id": 7287671,
        "name:xx": "Juncalito"
      }
    },
    {
      "geometry": {
        "type": "Point",
        "coordinates": [
          -70.133333,
          -32.833333
        ]
      },
      "type": "Feature",
      "properties": {
        "hierarchy": [
          "tgn:7287673",
          "tgn:1001768",
          "tgn:1000049",
          "tgn:1000002",
          "tgn:7029392"
        ],
        "placetype": [
          "aat:300008699"
        ],
        "id": 7287673,
        "name:xx": "Juncalillo, Río"
      }
    },
    {
      "geometry": {
        "type": "Point",
        "coordinates": [
          -69.55,
          -25.783333
        ]
      },
      "type": "Feature",
      "properties": {
        "hierarchy": [
          "tgn:7287674",
          "tgn:1001630",
          "tgn:1000049",
          "tgn:1000002",
          "tgn:7029392"
        ],
        "placetype": [
          "aat:300266554",
          "aat:300008699"
        ],
        "id": 7287674,
        "name:xx": "Juncalillo, Quebrada de"
      }
    },
    {
      "geometry": {
        "type": "Point",
        "coordinates": [
          -70.15,
          -32.85
        ]
      },
      "type": "Feature",
      "properties": {
        "hierarchy": [
          "tgn:7287675",
          "tgn:1001768",
          "tgn:1000049",
          "tgn:1000002",
          "tgn:7029392"
        ],
        "placetype": [
          "aat:300008795"
        ],
        "id": 7287675,
        "name:xx": "Juncalillo, Cerro"
      }
    },
    {
      "geometry": {
        "type": "Point",
        "coordinates": [
          -69.466667,
          -25.783333
        ]
      },
      "type": "Feature",
      "properties": {
        "hierarchy": [
          "tgn:7287676",
          "tgn:1001630",
          "tgn:1000049",
          "tgn:1000002",
          "tgn:7029392"
        ],
        "placetype": [
          "aat:300004792"
        ],
        "id": 7287676,
        "name:xx": "Juncalillo"
      }
    },
    {
      "geometry": {
        "type": "Point",
        "coordinates": [
          -70.166667,
          -33.05
        ]
      },
      "type": "Feature",
      "properties": {
        "hierarchy": [
          "tgn:7287677",
          "tgn:1001768",
          "tgn:1000049",
          "tgn:1000002",
          "tgn:7029392"
        ],
        "placetype": [
          "aat:300008835"
        ],
        "id": 7287677,
        "name:xx": "Juncal, Ventisquero"
      }
    },
    {
      "geometry": {
        "type": "Point",
        "coordinates": [
          -69.4,
          -25.716667
        ]
      },
      "type": "Feature",
      "properties": {
        "hierarchy": [
          "tgn:7287678",
          "tgn:1001630",
          "tgn:1000049",
          "tgn:1000002",
          "tgn:7029392"
        ],
        "placetype": [
          "aat:300008686"
        ],
        "id": 7287678,
        "name:xx": "Juncal, Vegas de"
      }
    },
    {
      "geometry": {
        "type": "Point",
        "coordinates": [
          -69.4,
          -25.7
        ]
      },
      "type": "Feature",
      "properties": {
        "hierarchy": [
          "tgn:7287679",
          "tgn:1001630",
          "tgn:1000049",
          "tgn:1000002",
          "tgn:7029392"
        ],
        "placetype": [
          "aat:300008795"
        ],
        "id": 7287679,
        "name:xx": "Juncal, Sierra"
      }
    }
  ]
}
