{
  "type": "FeatureCollection",
  "features": [
    {
      "geometry": {
        "type": "Point",
        "coordinates": [
          -2.583333,
          52.3
        ]
      },
      "type": "Feature",
      "properties": {
        "hierarchy": [
          "tgn:1030850",
          "tgn:7002445",
          "tgn:1000003",
          "tgn:7012034",
          "tgn:7008591",
          "tgn:7029392"
        ],
        "placetype": [
          "aat:300008347"
        ],
        "name:en": "Tenbury",
        "id": 1030850
      }
    },
    {
      "geometry": {
        "type": "Point",
        "coordinates": [
          0.7,
          51.05
        ]
      },
      "type": "Feature",
      "properties": {
        "hierarchy": [
          "tgn:1030851",
          "tgn:7002445",
          "tgn:1000003",
          "tgn:7008153",
          "tgn:7008591",
          "tgn:7029392"
        ],
        "placetype": [
          "aat:300008347"
        ],
        "name:en": "Tenterden",
        "id": 1030851
      }
    },
    {
      "geometry": {
        "type": "Point",
        "coordinates": [
          0.3,
          52.75
        ]
      },
      "type": "Feature",
      "properties": {
        "hierarchy": [
          "tgn:1030852",
          "tgn:7002445",
          "tgn:1000003",
          "tgn:7008160",
          "tgn:7008591",
          "tgn:7029392"
        ],
        "placetype": [
          "aat:300008347",
          "aat:300008372"
        ],
        "id": 1030852,
        "name:xx": "Terrington Saint Clement"
      }
    },
    {
      "geometry": {
        "type": "Point",
        "coordinates": [
          0.4333,
          51.25
        ]
      },
      "type": "Feature",
      "properties": {
        "hierarchy": [
          "tgn:1030853",
          "tgn:7002445",
          "tgn:1000003",
          "tgn:7008153",
          "tgn:7008591",
          "tgn:7029392"
        ],
        "placetype": [
          "aat:300008347",
          "aat:300008372"
        ],
        "id": 1030853,
        "name:xx": "Teston"
      }
    },
    {
      "geometry": {
        "type": "Point",
        "coordinates": [
          -2.162222,
          51.639444
        ]
      },
      "type": "Feature",
      "properties": {
        "hierarchy": [
          "tgn:1030854",
          "tgn:7002445",
          "tgn:1000003",
          "tgn:7008132",
          "tgn:7008591",
          "tgn:7029392"
        ],
        "placetype": [
          "aat:300008347",
          "aat:300008375"
        ],
        "name:en": "Tetbury",
        "id": 1030854
      }
    },
    {
      "geometry": {
        "type": "Point",
        "coordinates": [
          -2.183333,
          52.6
        ]
      },
      "type": "Feature",
      "properties": {
        "hierarchy": [
          "tgn:1030855",
          "tgn:7002445",
          "tgn:7019032",
          "tgn:1000003",
          "tgn:7029506",
          "tgn:7008591",
          "tgn:7029392"
        ],
        "placetype": [
          "aat:300008347"
        ],
        "name:en": "Tettenhall",
        "id": 1030855
      }
    },
    {
      "geometry": {
        "type": "Point",
        "coordinates": [
          0.816667,
          51.333333
        ]
      },
      "type": "Feature",
      "properties": {
        "hierarchy": [
          "tgn:1030857",
          "tgn:7002445",
          "tgn:1000003",
          "tgn:7008153",
          "tgn:7008591",
          "tgn:7029392"
        ],
        "placetype": [
          "aat:300008347"
        ],
        "name:en": "Teynham",
        "id": 1030857
      }
    },
    {
      "geometry": {
        "type": "Point",
        "coordinates": [
          -0.333333,
          51.383333
        ]
      },
      "type": "Feature",
      "properties": {
        "hierarchy": [
          "tgn:1030859",
          "tgn:7002445",
          "tgn:1000003",
          "tgn:7008175",
          "tgn:7008591",
          "tgn:7029392"
        ],
        "placetype": [
          "aat:300008347"
        ],
        "name:en": "Thames Ditton",
        "id": 1030859
      }
    }
  ]
}
