{
  "geometry": {
    "type": "Point",
    "coordinates": [
      -74.65,
      5.7333
    ]
  },
  "type": "Feature",
  "properties": {
    "hierarchy": [
      "tgn:1127670",
      "tgn:1000583",
      "tgn:1000050",
      "tgn:1000002",
      "tgn:7029392"
    ],
    "placetype": [
      "aat:300008707"
    ],
    "id": 1127670,
    "name:xx": "Negro"
  }
}
