{
  "geometry": {
    "type": "Point",
    "coordinates": [
      -80.35,
      33.4667
    ]
  },
  "type": "Feature",
  "properties": {
    "hierarchy": [
      "tgn:2582843",
      "tgn:1000001",
      "tgn:2001738",
      "tgn:7012149",
      "tgn:7007712",
      "tgn:7029392"
    ],
    "placetype": [
      "aat:300008791"
    ],
    "id": 2582843,
    "name:xx": "Pine Island"
  }
}
