{
  "geometry": {
    "type": "Point",
    "coordinates": [
      -83.5667,
      30.6167
    ]
  },
  "type": "Feature",
  "properties": {
    "hierarchy": [
      "tgn:2020219",
      "tgn:1000001",
      "tgn:7012149",
      "tgn:2000279",
      "tgn:7007240",
      "tgn:7029392"
    ],
    "placetype": [
      "aat:300387016"
    ],
    "id": 2020219,
    "name:xx": "Lovett"
  }
}
