{
  "geometry": {
    "type": "Point",
    "coordinates": [
      -79.65,
      37.4833
    ]
  },
  "type": "Feature",
  "properties": {
    "hierarchy": [
      "tgn:2261737",
      "tgn:1000001",
      "tgn:2002146",
      "tgn:7012149",
      "tgn:7007919",
      "tgn:7029392"
    ],
    "placetype": [
      "aat:300008798"
    ],
    "id": 2261737,
    "name:xx": "Cove Mountain"
  }
}
