{
  "type": "FeatureCollection",
  "features": [
    {
      "geometry": {
        "type": "Point",
        "coordinates": [
          -87.5167,
          36
        ]
      },
      "type": "Feature",
      "properties": {
        "hierarchy": [
          "tgn:2156640",
          "tgn:1000001",
          "tgn:7012149",
          "tgn:2001858",
          "tgn:7007825",
          "tgn:7029392"
        ],
        "placetype": [
          "aat:300008347"
        ],
        "id": 2156640,
        "name:xx": "Beasley"
      }
    },
    {
      "geometry": {
        "type": "Point",
        "coordinates": [
          -75.8,
          36.2833
        ]
      },
      "type": "Feature",
      "properties": {
        "hierarchy": [
          "tgn:2156641",
          "tgn:1000001",
          "tgn:7012149",
          "tgn:1002312",
          "tgn:7007709",
          "tgn:7029392"
        ],
        "placetype": [
          "aat:300132316"
        ],
        "id": 2156641,
        "name:xx": "Beasley Bay"
      }
    },
    {
      "geometry": {
        "type": "Point",
        "coordinates": [
          -90.6167,
          33.2167
        ]
      },
      "type": "Feature",
      "properties": {
        "hierarchy": [
          "tgn:2156642",
          "tgn:1000001",
          "tgn:7012149",
          "tgn:2001112",
          "tgn:7007522",
          "tgn:7029392"
        ],
        "placetype": [
          "aat:300008699"
        ],
        "id": 2156642,
        "name:xx": "Beasley Bayou"
      }
    },
    {
      "geometry": {
        "type": "Point",
        "coordinates": [
          -85.7,
          31.5167
        ]
      },
      "type": "Feature",
      "properties": {
        "hierarchy": [
          "tgn:2156643",
          "tgn:7002659",
          "tgn:1000001",
          "tgn:7012149",
          "tgn:2000022",
          "tgn:7029392"
        ],
        "placetype": [
          "aat:300008699"
        ],
        "id": 2156643,
        "name:xx": "Beasley Branch"
      }
    },
    {
      "geometry": {
        "type": "Point",
        "coordinates": [
          -82.7,
          37.9333
        ]
      },
      "type": "Feature",
      "properties": {
        "hierarchy": [
          "tgn:2156644",
          "tgn:1000001",
          "tgn:7012149",
          "tgn:2000809",
          "tgn:7007255",
          "tgn:7029392"
        ],
        "placetype": [
          "aat:300008699"
        ],
        "id": 2156644,
        "name:xx": "Beasley Branch"
      }
    },
    {
      "geometry": {
        "type": "Point",
        "coordinates": [
          -79.5667,
          34.7833
        ]
      },
      "type": "Feature",
      "properties": {
        "hierarchy": [
          "tgn:2156645",
          "tgn:1000001",
          "tgn:7012149",
          "tgn:2001539",
          "tgn:7007709",
          "tgn:7029392"
        ],
        "placetype": [
          "aat:300008699"
        ],
        "id": 2156645,
        "name:xx": "Beasley Branch"
      }
    },
    {
      "geometry": {
        "type": "Point",
        "coordinates": [
          -82.8167,
          35.1833
        ]
      },
      "type": "Feature",
      "properties": {
        "hierarchy": [
          "tgn:2156646",
          "tgn:1000001",
          "tgn:7012149",
          "tgn:2001544",
          "tgn:7007709",
          "tgn:7029392"
        ],
        "placetype": [
          "aat:300008699"
        ],
        "id": 2156646,
        "name:xx": "Beasley Branch"
      }
    },
    {
      "geometry": {
        "type": "Point",
        "coordinates": [
          -76.8833,
          36.4667
        ]
      },
      "type": "Feature",
      "properties": {
        "hierarchy": [
          "tgn:2156647",
          "tgn:1000001",
          "tgn:7012149",
          "tgn:1002403",
          "tgn:7007709",
          "tgn:7029392"
        ],
        "placetype": [
          "aat:300008699"
        ],
        "id": 2156647,
        "name:xx": "Beasley Branch"
      }
    },
    {
      "geometry": {
        "type": "Point",
        "coordinates": [
          -86.9,
          35.05
        ]
      },
      "type": "Feature",
      "properties": {
        "hierarchy": [
          "tgn:2156648",
          "tgn:1000001",
          "tgn:7012149",
          "tgn:2001864",
          "tgn:7007825",
          "tgn:7029392"
        ],
        "placetype": [
          "aat:300008699"
        ],
        "id": 2156648,
        "name:xx": "Beasley Branch"
      }
    },
    {
      "geometry": {
        "type": "Point",
        "coordinates": [
          -88.05,
          36.1
        ]
      },
      "type": "Feature",
      "properties": {
        "hierarchy": [
          "tgn:2156649",
          "tgn:1000001",
          "tgn:2001839",
          "tgn:7012149",
          "tgn:7007825",
          "tgn:7029392"
        ],
        "placetype": [
          "aat:300008699"
        ],
        "id": 2156649,
        "name:xx": "Beasley Branch"
      }
    }
  ]
}
