{
  "geometry": {
    "type": "Point",
    "coordinates": [
      -112.4833,
      45.75
    ]
  },
  "type": "Feature",
  "properties": {
    "hierarchy": [
      "tgn:2216532",
      "tgn:1000001",
      "tgn:7012149",
      "tgn:7007524",
      "tgn:7029392"
    ],
    "placetype": [
      "aat:300008706"
    ],
    "id": 2216532,
    "name:xx": "Camp Creek"
  }
}
