{
  "type": "FeatureCollection",
  "features": [
    {
      "geometry": {
        "type": "Point",
        "coordinates": [
          -96.45,
          32.0333
        ]
      },
      "type": "Feature",
      "properties": {
        "hierarchy": [
          "tgn:2359690",
          "tgn:1000001",
          "tgn:7012149",
          "tgn:1002709",
          "tgn:7007826",
          "tgn:7029392"
        ],
        "placetype": [
          "aat:300008706"
        ],
        "id": 2359690,
        "name:xx": "Grape Creek"
      }
    },
    {
      "geometry": {
        "type": "Point",
        "coordinates": [
          -101.5333,
          32.8
        ]
      },
      "type": "Feature",
      "properties": {
        "hierarchy": [
          "tgn:2359691",
          "tgn:1000001",
          "tgn:2001943",
          "tgn:7012149",
          "tgn:7007826",
          "tgn:7029392"
        ],
        "placetype": [
          "aat:300008706"
        ],
        "id": 2359691,
        "name:xx": "Grape Creek"
      }
    },
    {
      "geometry": {
        "type": "Point",
        "coordinates": [
          -101.05,
          32.8667
        ]
      },
      "type": "Feature",
      "properties": {
        "hierarchy": [
          "tgn:2359692",
          "tgn:1000001",
          "tgn:7012149",
          "tgn:7007826",
          "tgn:7029392"
        ],
        "placetype": [
          "aat:300008706"
        ],
        "id": 2359692,
        "name:xx": "Grape Creek"
      }
    },
    {
      "geometry": {
        "type": "Point",
        "coordinates": [
          -98.7333,
          30.6167
        ]
      },
      "type": "Feature",
      "properties": {
        "hierarchy": [
          "tgn:2359693",
          "tgn:1000001",
          "tgn:7012149",
          "tgn:2002030",
          "tgn:7007826",
          "tgn:7029392"
        ],
        "placetype": [
          "aat:300008706"
        ],
        "id": 2359693,
        "name:xx": "Grape Creek"
      }
    },
    {
      "geometry": {
        "type": "Point",
        "coordinates": [
          -101.0667,
          33.6333
        ]
      },
      "type": "Feature",
      "properties": {
        "hierarchy": [
          "tgn:2359694",
          "tgn:1000001",
          "tgn:7012149",
          "tgn:2001968",
          "tgn:7007826",
          "tgn:7029392"
        ],
        "placetype": [
          "aat:300008706"
        ],
        "id": 2359694,
        "name:xx": "Grape Creek"
      }
    },
    {
      "geometry": {
        "type": "Point",
        "coordinates": [
          -100.5667,
          31.65
        ]
      },
      "type": "Feature",
      "properties": {
        "hierarchy": [
          "tgn:2359695",
          "tgn:1000001",
          "tgn:7012149",
          "tgn:2002085",
          "tgn:7007826",
          "tgn:7029392"
        ],
        "placetype": [
          "aat:300008706"
        ],
        "id": 2359695,
        "name:xx": "Grape Creek"
      }
    },
    {
      "geometry": {
        "type": "Point",
        "coordinates": [
          -85.9667,
          30.5333
        ]
      },
      "type": "Feature",
      "properties": {
        "hierarchy": [
          "tgn:2359697",
          "tgn:1000001",
          "tgn:7012149",
          "tgn:2000290",
          "tgn:7007240",
          "tgn:7029392"
        ],
        "placetype": [
          "aat:300008699"
        ],
        "id": 2359697,
        "name:xx": "Grape Head Branch"
      }
    },
    {
      "geometry": {
        "type": "Point",
        "coordinates": [
          -81.05,
          28.0833
        ]
      },
      "type": "Feature",
      "properties": {
        "hierarchy": [
          "tgn:2359698",
          "tgn:1000001",
          "tgn:7012149",
          "tgn:1002756",
          "tgn:7007240",
          "tgn:7029392"
        ],
        "placetype": [
          "aat:300008905"
        ],
        "id": 2359698,
        "name:xx": "Grape Head Pond"
      }
    },
    {
      "geometry": {
        "type": "Point",
        "coordinates": [
          -70.9,
          42.8833
        ]
      },
      "type": "Feature",
      "properties": {
        "hierarchy": [
          "tgn:2359699",
          "tgn:1000001",
          "tgn:7012149",
          "tgn:7029392"
        ],
        "placetype": [
          "aat:300008798"
        ],
        "id": 2359699,
        "name:xx": "Grape Hill"
      }
    }
  ]
}
