{
  "geometry": {
    "type": "Point",
    "coordinates": [
      -84.4833,
      41.8333
    ]
  },
  "type": "Feature",
  "properties": {
    "hierarchy": [
      "tgn:2551902",
      "tgn:1000001",
      "tgn:7012149",
      "tgn:1002481",
      "tgn:7007520",
      "tgn:7029392"
    ],
    "placetype": [
      "aat:300008680"
    ],
    "id": 2551902,
    "name:xx": "Number Eight, Lake"
  }
}
