{
  "type": "FeatureCollection",
  "features": [
    {
      "geometry": {
        "type": "Point",
        "coordinates": [
          -108.8,
          40.7833
        ]
      },
      "type": "Feature",
      "properties": {
        "hierarchy": [
          "tgn:2456750",
          "tgn:1000001",
          "tgn:7012149",
          "tgn:2000232",
          "tgn:7007158",
          "tgn:7029392"
        ],
        "placetype": [
          "aat:300386845"
        ],
        "id": 2456750,
        "name:xx": "Little Joe Basin"
      }
    },
    {
      "geometry": {
        "type": "Point",
        "coordinates": [
          -116,
          43.15
        ]
      },
      "type": "Feature",
      "properties": {
        "hierarchy": [
          "tgn:2456751",
          "tgn:2000452",
          "tgn:1000001",
          "tgn:7012149",
          "tgn:7007250",
          "tgn:7029392"
        ],
        "placetype": [
          "aat:300008798"
        ],
        "id": 2456751,
        "name:xx": "Little Joe Butte"
      }
    },
    {
      "geometry": {
        "type": "Point",
        "coordinates": [
          -109.7,
          48.15
        ]
      },
      "type": "Feature",
      "properties": {
        "hierarchy": [
          "tgn:2456752",
          "tgn:1000001",
          "tgn:7012149",
          "tgn:2001280",
          "tgn:7007524",
          "tgn:7029392"
        ],
        "placetype": [
          "aat:300008798"
        ],
        "id": 2456752,
        "name:xx": "Little Joe Butte"
      }
    },
    {
      "geometry": {
        "type": "Point",
        "coordinates": [
          -104.55,
          37.95
        ]
      },
      "type": "Feature",
      "properties": {
        "hierarchy": [
          "tgn:2456753",
          "tgn:1000001",
          "tgn:7012149",
          "tgn:7007158",
          "tgn:2000242",
          "tgn:7029392"
        ],
        "placetype": [
          "aat:300008761"
        ],
        "id": 2456753,
        "name:xx": "Little Joe Canyon"
      }
    },
    {
      "geometry": {
        "type": "Point",
        "coordinates": [
          -155.4,
          64.6167
        ]
      },
      "type": "Feature",
      "properties": {
        "hierarchy": [
          "tgn:2456754",
          "tgn:7006450",
          "tgn:1000001",
          "tgn:7012149",
          "tgn:2000089",
          "tgn:7029392"
        ],
        "placetype": [
          "aat:300008706"
        ],
        "id": 2456754,
        "name:xx": "Little Joe Creek"
      }
    },
    {
      "geometry": {
        "type": "Point",
        "coordinates": [
          -93.8,
          34.7167
        ]
      },
      "type": "Feature",
      "properties": {
        "hierarchy": [
          "tgn:2456755",
          "tgn:1000001",
          "tgn:7016172",
          "tgn:7012149",
          "tgn:2000168",
          "tgn:7029392"
        ],
        "placetype": [
          "aat:300008706"
        ],
        "id": 2456755,
        "name:xx": "Little Joe Creek"
      }
    },
    {
      "geometry": {
        "type": "Point",
        "coordinates": [
          -85.35,
          40.3833
        ]
      },
      "type": "Feature",
      "properties": {
        "hierarchy": [
          "tgn:2456756",
          "tgn:1000001",
          "tgn:1002184",
          "tgn:7012149",
          "tgn:7007252",
          "tgn:7029392"
        ],
        "placetype": [
          "aat:300008706"
        ],
        "id": 2456756,
        "name:xx": "Little Joe Creek"
      }
    },
    {
      "geometry": {
        "type": "Point",
        "coordinates": [
          -85.8667,
          38.6333
        ]
      },
      "type": "Feature",
      "properties": {
        "hierarchy": [
          "tgn:2456757",
          "tgn:1000001",
          "tgn:7012149",
          "tgn:1002879",
          "tgn:7007252",
          "tgn:7029392"
        ],
        "placetype": [
          "aat:300008706"
        ],
        "id": 2456757,
        "name:xx": "Little Joe Creek"
      }
    },
    {
      "geometry": {
        "type": "Point",
        "coordinates": [
          -88.8,
          36.7167
        ]
      },
      "type": "Feature",
      "properties": {
        "hierarchy": [
          "tgn:2456758",
          "tgn:1000001",
          "tgn:7012149",
          "tgn:7007255",
          "tgn:7029392"
        ],
        "placetype": [
          "aat:300008706"
        ],
        "id": 2456758,
        "name:xx": "Little Joe Creek"
      }
    },
    {
      "geometry": {
        "type": "Point",
        "coordinates": [
          -113.0167,
          45.55
        ]
      },
      "type": "Feature",
      "properties": {
        "hierarchy": [
          "tgn:2456759",
          "tgn:1000001",
          "tgn:2001260",
          "tgn:7012149",
          "tgn:7007524",
          "tgn:7029392"
        ],
        "placetype": [
          "aat:300008706"
        ],
        "id": 2456759,
        "name:xx": "Little Joe Creek"
      }
    }
  ]
}
