{
  "type": "FeatureCollection",
  "features": [
    {
      "geometry": {
        "type": "Point",
        "coordinates": [
          -75,
          41.0833
        ]
      },
      "type": "Feature",
      "properties": {
        "hierarchy": [
          "tgn:2086880",
          "tgn:1000001",
          "tgn:7012149",
          "tgn:1002789",
          "tgn:7007710",
          "tgn:7029392"
        ],
        "placetype": [
          "aat:300008347"
        ],
        "id": 2086880,
        "name:xx": "Bushkill"
      }
    },
    {
      "geometry": {
        "type": "Point",
        "coordinates": [
          -75.3167,
          40.7833
        ]
      },
      "type": "Feature",
      "properties": {
        "hierarchy": [
          "tgn:2086881",
          "tgn:1000001",
          "tgn:7012149",
          "tgn:1002729",
          "tgn:7007710",
          "tgn:7029392"
        ],
        "placetype": [
          "aat:300008347"
        ],
        "id": 2086881,
        "name:xx": "Bushkill Center"
      }
    },
    {
      "geometry": {
        "type": "Point",
        "coordinates": [
          -79.7,
          39.95
        ]
      },
      "type": "Feature",
      "properties": {
        "hierarchy": [
          "tgn:2086882",
          "tgn:1000001",
          "tgn:7012149",
          "tgn:7014185",
          "tgn:7007710",
          "tgn:7029392"
        ],
        "placetype": [
          "aat:300008347"
        ],
        "id": 2086882,
        "name:xx": "Bute"
      }
    },
    {
      "geometry": {
        "type": "Point",
        "coordinates": [
          -79.2833,
          40.25
        ]
      },
      "type": "Feature",
      "properties": {
        "hierarchy": [
          "tgn:2086889",
          "tgn:1000001",
          "tgn:7012149",
          "tgn:1003017",
          "tgn:7007710",
          "tgn:7029392"
        ],
        "placetype": [
          "aat:300008347",
          "aat:300387210"
        ],
        "id": 2086889,
        "name:xx": "Buttermilk Falls"
      }
    }
  ]
}
