{
  "type": "FeatureCollection",
  "features": [
    {
      "geometry": {
        "type": "Point",
        "coordinates": [
          -111.111111,
          25.358889
        ]
      },
      "type": "Feature",
      "properties": {
        "hierarchy": [
          "tgn:7395771",
          "tgn:1001836",
          "tgn:1000001",
          "tgn:7005560",
          "tgn:7029392"
        ],
        "placetype": [
          "aat:300008347"
        ],
        "id": 7395771,
        "name:xx": "San Antonio"
      }
    },
    {
      "geometry": {
        "type": "Point",
        "coordinates": [
          -108.233333,
          25.333333
        ]
      },
      "type": "Feature",
      "properties": {
        "hierarchy": [
          "tgn:7395772",
          "tgn:1000001",
          "tgn:7005595",
          "tgn:7005560",
          "tgn:7029392"
        ],
        "placetype": [
          "aat:300008347"
        ],
        "id": 7395772,
        "name:xx": "San Antonio"
      }
    },
    {
      "geometry": {
        "type": "Point",
        "coordinates": [
          -100.033333,
          25.333333
        ]
      },
      "type": "Feature",
      "properties": {
        "hierarchy": [
          "tgn:7395773",
          "tgn:1000001",
          "tgn:7005589",
          "tgn:7005560",
          "tgn:7029392"
        ],
        "placetype": [
          "aat:300008347"
        ],
        "id": 7395773,
        "name:xx": "San Antonio"
      }
    },
    {
      "geometry": {
        "type": "Point",
        "coordinates": [
          -101.516667,
          25.316667
        ]
      },
      "type": "Feature",
      "properties": {
        "hierarchy": [
          "tgn:7395775",
          "tgn:1001853",
          "tgn:1000001",
          "tgn:7005560",
          "tgn:7029392"
        ],
        "placetype": [
          "aat:300008347"
        ],
        "id": 7395775,
        "name:xx": "San Antonio"
      }
    },
    {
      "geometry": {
        "type": "Point",
        "coordinates": [
          -104.05,
          25.266667
        ]
      },
      "type": "Feature",
      "properties": {
        "hierarchy": [
          "tgn:7395776",
          "tgn:7005583",
          "tgn:1000001",
          "tgn:7005560",
          "tgn:7029392"
        ],
        "placetype": [
          "aat:300008347"
        ],
        "id": 7395776,
        "name:xx": "San Antonio"
      }
    },
    {
      "geometry": {
        "type": "Point",
        "coordinates": [
          -106.733333,
          25.233333
        ]
      },
      "type": "Feature",
      "properties": {
        "hierarchy": [
          "tgn:7395777",
          "tgn:7005583",
          "tgn:1000001",
          "tgn:7005560",
          "tgn:7029392"
        ],
        "placetype": [
          "aat:300008347"
        ],
        "id": 7395777,
        "name:xx": "San Antonio"
      }
    },
    {
      "geometry": {
        "type": "Point",
        "coordinates": [
          -105.95,
          25.2
        ]
      },
      "type": "Feature",
      "properties": {
        "hierarchy": [
          "tgn:7395778",
          "tgn:7005583",
          "tgn:1000001",
          "tgn:7005560",
          "tgn:7029392"
        ],
        "placetype": [
          "aat:300008347"
        ],
        "id": 7395778,
        "name:xx": "San Antonio"
      }
    },
    {
      "geometry": {
        "type": "Point",
        "coordinates": [
          -103.4,
          25.183333
        ]
      },
      "type": "Feature",
      "properties": {
        "hierarchy": [
          "tgn:7395779",
          "tgn:7005583",
          "tgn:1000001",
          "tgn:7005560",
          "tgn:7029392"
        ],
        "placetype": [
          "aat:300008347"
        ],
        "id": 7395779,
        "name:xx": "San Antonio"
      }
    }
  ]
}
