{
  "type": "FeatureCollection",
  "features": [
    {
      "geometry": {
        "type": "Point",
        "coordinates": [
          -93.366667,
          17.416667
        ]
      },
      "type": "Feature",
      "properties": {
        "hierarchy": [
          "tgn:7377410",
          "tgn:7005580",
          "tgn:1000001",
          "tgn:7005560",
          "tgn:7029392"
        ],
        "placetype": [
          "aat:300008347"
        ],
        "id": 7377410,
        "name:xx": "La Soledad"
      }
    },
    {
      "geometry": {
        "type": "Point",
        "coordinates": [
          -98.416667,
          16.733333
        ]
      },
      "type": "Feature",
      "properties": {
        "hierarchy": [
          "tgn:7377411",
          "tgn:7005585",
          "tgn:1000001",
          "tgn:7005560",
          "tgn:7029392"
        ],
        "placetype": [
          "aat:300008347"
        ],
        "id": 7377411,
        "name:xx": "La Soledad"
      }
    },
    {
      "geometry": {
        "type": "Point",
        "coordinates": [
          -91.433333,
          16.5
        ]
      },
      "type": "Feature",
      "properties": {
        "hierarchy": [
          "tgn:7377412",
          "tgn:7005580",
          "tgn:1000001",
          "tgn:7005560",
          "tgn:7029392"
        ],
        "placetype": [
          "aat:300008347"
        ],
        "id": 7377412,
        "name:xx": "La Soledad"
      }
    },
    {
      "geometry": {
        "type": "Point",
        "coordinates": [
          -96.633333,
          16.416667
        ]
      },
      "type": "Feature",
      "properties": {
        "hierarchy": [
          "tgn:7377413",
          "tgn:1000001",
          "tgn:7005591",
          "tgn:7005560",
          "tgn:7029392"
        ],
        "placetype": [
          "aat:300008347"
        ],
        "id": 7377413,
        "name:xx": "La Soledad"
      }
    },
    {
      "geometry": {
        "type": "Point",
        "coordinates": [
          -91.7,
          16.4
        ]
      },
      "type": "Feature",
      "properties": {
        "hierarchy": [
          "tgn:7377414",
          "tgn:7005580",
          "tgn:1000001",
          "tgn:7005560",
          "tgn:7029392"
        ],
        "placetype": [
          "aat:300008347"
        ],
        "id": 7377414,
        "name:xx": "La Soledad"
      }
    },
    {
      "geometry": {
        "type": "Point",
        "coordinates": [
          -93.966667,
          16.3
        ]
      },
      "type": "Feature",
      "properties": {
        "hierarchy": [
          "tgn:7377415",
          "tgn:7005580",
          "tgn:1000001",
          "tgn:7005560",
          "tgn:7029392"
        ],
        "placetype": [
          "aat:300008347"
        ],
        "id": 7377415,
        "name:xx": "La Soledad"
      }
    },
    {
      "geometry": {
        "type": "Point",
        "coordinates": [
          -94.15,
          16.083333
        ]
      },
      "type": "Feature",
      "properties": {
        "hierarchy": [
          "tgn:7377416",
          "tgn:1000001",
          "tgn:7005591",
          "tgn:7005560",
          "tgn:7029392"
        ],
        "placetype": [
          "aat:300008347"
        ],
        "id": 7377416,
        "name:xx": "La Soledad"
      }
    },
    {
      "geometry": {
        "type": "Point",
        "coordinates": [
          -92.483333,
          15.566667
        ]
      },
      "type": "Feature",
      "properties": {
        "hierarchy": [
          "tgn:7377417",
          "tgn:7005580",
          "tgn:1000001",
          "tgn:7005560",
          "tgn:7029392"
        ],
        "placetype": [
          "aat:300008347"
        ],
        "id": 7377417,
        "name:xx": "La Soledad"
      }
    },
    {
      "geometry": {
        "type": "Point",
        "coordinates": [
          -92.783333,
          15.283333
        ]
      },
      "type": "Feature",
      "properties": {
        "hierarchy": [
          "tgn:7377418",
          "tgn:7005580",
          "tgn:1000001",
          "tgn:7005560",
          "tgn:7029392"
        ],
        "placetype": [
          "aat:300008347"
        ],
        "id": 7377418,
        "name:xx": "La Soledad"
      }
    },
    {
      "geometry": {
        "type": "Point",
        "coordinates": [
          -106.616667,
          25.6
        ]
      },
      "type": "Feature",
      "properties": {
        "hierarchy": [
          "tgn:7377419",
          "tgn:7005583",
          "tgn:1000001",
          "tgn:7005560",
          "tgn:7029392"
        ],
        "placetype": [
          "aat:300000241"
        ],
        "id": 7377419,
        "name:xx": "Rancho La Sola"
      }
    }
  ]
}
