{
  "geometry": {
    "type": "Point",
    "coordinates": [
      -78.9667,
      36.3667
    ]
  },
  "type": "Feature",
  "properties": {
    "hierarchy": [
      "tgn:2493201",
      "tgn:1000001",
      "tgn:7012149",
      "tgn:2001529",
      "tgn:7007709",
      "tgn:7029392"
    ],
    "placetype": [
      "aat:300008706"
    ],
    "id": 2493201,
    "name:xx": "Marlowe Creek"
  }
}
