{
  "type": "FeatureCollection",
  "features": [
    {
      "geometry": {
        "type": "Point",
        "coordinates": [
          -75.7333,
          39.65
        ]
      },
      "type": "Feature",
      "properties": {
        "hierarchy": [
          "tgn:2017731",
          "tgn:7014201",
          "tgn:1000001",
          "tgn:7012149",
          "tgn:7007239",
          "tgn:7029392"
        ],
        "placetype": [
          "aat:300008347"
        ],
        "id": 2017731,
        "name:xx": "Catalina Gardens"
      }
    },
    {
      "geometry": {
        "type": "Point",
        "coordinates": [
          -75.3167,
          38.9167
        ]
      },
      "type": "Feature",
      "properties": {
        "hierarchy": [
          "tgn:2017732",
          "tgn:1002933",
          "tgn:1000001",
          "tgn:7012149",
          "tgn:7007239",
          "tgn:7029392"
        ],
        "placetype": [
          "aat:300008347",
          "aat:300387247"
        ],
        "id": 2017732,
        "name:xx": "Cedar Beach"
      }
    },
    {
      "geometry": {
        "type": "Point",
        "coordinates": [
          -75.6167,
          39.8167
        ]
      },
      "type": "Feature",
      "properties": {
        "hierarchy": [
          "tgn:2017733",
          "tgn:7014201",
          "tgn:1000001",
          "tgn:7012149",
          "tgn:7007239",
          "tgn:7029392"
        ],
        "placetype": [
          "aat:300008347"
        ],
        "id": 2017733,
        "name:xx": "Centerville"
      }
    },
    {
      "geometry": {
        "type": "Point",
        "coordinates": [
          -75.5167,
          39.8167
        ]
      },
      "type": "Feature",
      "properties": {
        "hierarchy": [
          "tgn:2017734",
          "tgn:7014201",
          "tgn:1000001",
          "tgn:7012149",
          "tgn:7007239",
          "tgn:7029392"
        ],
        "placetype": [
          "aat:300008347"
        ],
        "id": 2017734,
        "name:xx": "Chalfonte"
      }
    },
    {
      "geometry": {
        "type": "Point",
        "coordinates": [
          -75.7167,
          39.7
        ]
      },
      "type": "Feature",
      "properties": {
        "hierarchy": [
          "tgn:2017737",
          "tgn:7014201",
          "tgn:1000001",
          "tgn:7012149",
          "tgn:7007239",
          "tgn:7029392"
        ],
        "placetype": [
          "aat:300008347"
        ],
        "id": 2017737,
        "name:xx": "Chapel Hill"
      }
    }
  ]
}
