{
  "type": "FeatureCollection",
  "features": [
    {
      "geometry": {
        "type": "Point",
        "coordinates": [
          35.1,
          24.216667
        ]
      },
      "type": "Feature",
      "properties": {
        "hierarchy": [
          "tgn:7521000",
          "tgn:7001242",
          "tgn:7001311",
          "tgn:7016833",
          "tgn:7029392"
        ],
        "placetype": [
          "aat:300006207"
        ],
        "name:en": "Qalt Abu Amiri",
        "id": 7521000
      }
    },
    {
      "geometry": {
        "type": "Point",
        "coordinates": [
          32.133333,
          26.766667
        ]
      },
      "type": "Feature",
      "properties": {
        "hierarchy": [
          "tgn:7521001",
          "tgn:7001242",
          "tgn:7001311",
          "tgn:7016833",
          "tgn:7029392"
        ],
        "placetype": [
          "aat:300006207"
        ],
        "name:en": "Bi'r Abū 'Amīrī",
        "id": 7521001
      }
    },
    {
      "geometry": {
        "type": "Point",
        "coordinates": [
          32.533333,
          30.9
        ]
      },
      "type": "Feature",
      "properties": {
        "hierarchy": [
          "tgn:7521002",
          "tgn:7001242",
          "tgn:7016833",
          "tgn:1001080",
          "tgn:7029392"
        ],
        "placetype": [
          "aat:300006207"
        ],
        "name:en": "Bi'r Abū 'Āmir",
        "id": 7521002
      }
    },
    {
      "geometry": {
        "type": "Point",
        "coordinates": [
          30.15,
          31.066667
        ]
      },
      "type": "Feature",
      "properties": {
        "hierarchy": [
          "tgn:7521003",
          "tgn:7001242",
          "tgn:1001075",
          "tgn:7016833",
          "tgn:7029392"
        ],
        "placetype": [
          "aat:300000206"
        ],
        "name:en": "'Izbat 'Allām",
        "id": 7521003
      }
    },
    {
      "geometry": {
        "type": "Point",
        "coordinates": [
          27.333333,
          30.533333
        ]
      },
      "type": "Feature",
      "properties": {
        "hierarchy": [
          "tgn:7521004",
          "tgn:7001242",
          "tgn:7016833",
          "tgn:1001418",
          "tgn:7029392"
        ],
        "placetype": [
          "aat:300386860"
        ],
        "name:en": "'Allâm, Deir",
        "id": 7521004
      }
    },
    {
      "geometry": {
        "type": "Point",
        "coordinates": [
          30.898981,
          29.380662
        ]
      },
      "type": "Feature",
      "properties": {
        "hierarchy": [
          "tgn:7521005",
          "tgn:7001242",
          "tgn:7001105",
          "tgn:7016833",
          "tgn:7029392"
        ],
        "placetype": [
          "aat:300008699"
        ],
        "name:en": "'Allām, Baḩr",
        "id": 7521005
      }
    },
    {
      "geometry": {
        "type": "Point",
        "coordinates": [
          29.19936,
          28.672884
        ]
      },
      "type": "Feature",
      "properties": {
        "hierarchy": [
          "tgn:7521007",
          "tgn:7001242",
          "tgn:7016833",
          "tgn:7029392"
        ],
        "placetype": [
          "aat:300008777"
        ],
        "name:en": "'Allāfah, Qārat al",
        "id": 7521007
      }
    }
  ]
}
