{
  "geometry": {
    "type": "Point",
    "coordinates": [
      -71.7833,
      43.0833
    ]
  },
  "type": "Feature",
  "properties": {
    "hierarchy": [
      "tgn:2754701",
      "tgn:1000001",
      "tgn:1002480",
      "tgn:7012149",
      "tgn:7007564",
      "tgn:7029392"
    ],
    "placetype": [
      "aat:300008680"
    ],
    "id": 2754701,
    "name:xx": "Weare Reservoir"
  }
}
