{
  "geometry": {
    "type": "Point",
    "coordinates": [
      0.65,
      44.15
    ]
  },
  "type": "Feature",
  "properties": {
    "hierarchy": [
      "tgn:1124165",
      "tgn:1000003",
      "tgn:1000070",
      "tgn:7029392"
    ],
    "placetype": [
      "aat:300008707"
    ],
    "id": 1124165,
    "name:xx": "Gers"
  }
}
