{
  "geometry": {
    "type": "Point",
    "coordinates": [
      -111.9833,
      45.0667
    ]
  },
  "type": "Feature",
  "properties": {
    "hierarchy": [
      "tgn:2596478",
      "tgn:1000001",
      "tgn:7012149",
      "tgn:2001288",
      "tgn:7007524",
      "tgn:7029392"
    ],
    "placetype": [
      "aat:300008761"
    ],
    "id": 2596478,
    "name:xx": "Powder Gulch"
  }
}
