{
  "geometry": {
    "type": "Point",
    "coordinates": [
      -69.0333,
      45.7667
    ]
  },
  "type": "Feature",
  "properties": {
    "hierarchy": [
      "tgn:2516952",
      "tgn:1000001",
      "tgn:7012149",
      "tgn:2000928",
      "tgn:7007515",
      "tgn:7029392"
    ],
    "placetype": [
      "aat:300132316"
    ],
    "id": 2516952,
    "name:xx": "Minister Cove"
  }
}
