{
  "type": "FeatureCollection",
  "features": [
    {
      "geometry": {
        "type": "Point",
        "coordinates": [
          18.7,
          45.0833
        ]
      },
      "type": "Feature",
      "properties": {
        "hierarchy": [
          "tgn:1064891",
          "tgn:1000003",
          "tgn:7017307",
          "tgn:7006663",
          "tgn:7029392"
        ],
        "placetype": [
          "aat:300008347"
        ],
        "id": 1064891,
        "name:xx": "Županja"
      }
    },
    {
      "geometry": {
        "type": "Point",
        "coordinates": [
          20.4333,
          42.3667
        ]
      },
      "type": "Feature",
      "properties": {
        "hierarchy": [
          "tgn:1064892",
          "tgn:7015191",
          "tgn:7029392"
        ],
        "placetype": [
          "aat:300008347"
        ],
        "id": 1064892,
        "name:xx": "Đakovica"
      }
    },
    {
      "geometry": {
        "type": "Point",
        "coordinates": [
          18.4,
          45.3167
        ]
      },
      "type": "Feature",
      "properties": {
        "hierarchy": [
          "tgn:1064893",
          "tgn:7017305",
          "tgn:1000003",
          "tgn:7006663",
          "tgn:7029392"
        ],
        "placetype": [
          "aat:300008347"
        ],
        "id": 1064893,
        "name:xx": "Dakovo"
      }
    },
    {
      "geometry": {
        "type": "Point",
        "coordinates": [
          17.05,
          46.0333
        ]
      },
      "type": "Feature",
      "properties": {
        "hierarchy": [
          "tgn:1064894",
          "tgn:7017297",
          "tgn:1000003",
          "tgn:7006663",
          "tgn:7029392"
        ],
        "placetype": [
          "aat:300008347"
        ],
        "id": 1064894,
        "name:xx": "Durdevac"
      }
    },
    {
      "geometry": {
        "type": "Point",
        "coordinates": [
          20.15,
          45.8167
        ]
      },
      "type": "Feature",
      "properties": {
        "hierarchy": [
          "tgn:1064895",
          "tgn:1000003",
          "tgn:4011927",
          "tgn:7006669",
          "tgn:7029392"
        ],
        "placetype": [
          "aat:300008347"
        ],
        "id": 1064895,
        "name:xx": "Ada"
      }
    },
    {
      "geometry": {
        "type": "Point",
        "coordinates": [
          13.9,
          45.9
        ]
      },
      "type": "Feature",
      "properties": {
        "hierarchy": [
          "tgn:1064896",
          "tgn:7015087",
          "tgn:1000003",
          "tgn:7006670",
          "tgn:7029392"
        ],
        "placetype": [
          "aat:300008347",
          "aat:300387222",
          "aat:300008375"
        ],
        "id": 1064896,
        "name:xx": "Ajdovščina"
      }
    },
    {
      "geometry": {
        "type": "Point",
        "coordinates": [
          21.7,
          43.5167
        ]
      },
      "type": "Feature",
      "properties": {
        "hierarchy": [
          "tgn:1064897",
          "tgn:1000003",
          "tgn:7006669",
          "tgn:7029392"
        ],
        "placetype": [
          "aat:300008347",
          "aat:300000835",
          "aat:300008375"
        ],
        "id": 1064897,
        "name:xx": "Aleksinac"
      }
    },
    {
      "geometry": {
        "type": "Point",
        "coordinates": [
          20.9667,
          45.0833
        ]
      },
      "type": "Feature",
      "properties": {
        "hierarchy": [
          "tgn:1064898",
          "tgn:1000003",
          "tgn:4011927",
          "tgn:7006669",
          "tgn:7029392"
        ],
        "placetype": [
          "aat:300008347"
        ],
        "id": 1064898,
        "name:xx": "Alibunar"
      }
    },
    {
      "geometry": {
        "type": "Point",
        "coordinates": [
          19.8,
          42.7333
        ]
      },
      "type": "Feature",
      "properties": {
        "hierarchy": [
          "tgn:1064899",
          "tgn:7593962",
          "tgn:1000003",
          "tgn:7015657",
          "tgn:7029392"
        ],
        "placetype": [
          "aat:300008347"
        ],
        "id": 1064899,
        "name:xx": "Andrijevica"
      }
    }
  ]
}
