{
  "type": "FeatureCollection",
  "features": [
    {
      "geometry": {
        "type": "Point",
        "coordinates": [
          114.8,
          24.1333
        ]
      },
      "type": "Feature",
      "properties": {
        "hierarchy": [
          "tgn:1071890",
          "tgn:1000004",
          "tgn:7005232",
          "tgn:1000111",
          "tgn:7029392"
        ],
        "placetype": [
          "aat:300008347"
        ],
        "id": 1071890,
        "name:xx": "Shuntianhu"
      }
    },
    {
      "geometry": {
        "type": "Point",
        "coordinates": [
          116.6,
          40.15
        ]
      },
      "type": "Feature",
      "properties": {
        "hierarchy": [
          "tgn:1071891",
          "tgn:1000956",
          "tgn:1000004",
          "tgn:1000111",
          "tgn:7029392"
        ],
        "placetype": [
          "aat:300008347"
        ],
        "id": 1071891,
        "name:xx": "Shunyi"
      }
    },
    {
      "geometry": {
        "type": "Point",
        "coordinates": [
          95.7833,
          30.8
        ]
      },
      "type": "Feature",
      "properties": {
        "hierarchy": [
          "tgn:1071892",
          "tgn:1000004",
          "tgn:7001319",
          "tgn:1000111",
          "tgn:7029392"
        ],
        "placetype": [
          "aat:300008347"
        ],
        "id": 1071892,
        "name:xx": "Shuoduzong"
      }
    },
    {
      "geometry": {
        "type": "Point",
        "coordinates": [
          119.7333,
          33.7
        ]
      },
      "type": "Feature",
      "properties": {
        "hierarchy": [
          "tgn:1071893",
          "tgn:1000004",
          "tgn:7002081",
          "tgn:1000111",
          "tgn:7029392"
        ],
        "placetype": [
          "aat:300008347"
        ],
        "id": 1071893,
        "name:xx": "Shuojiaji"
      }
    },
    {
      "geometry": {
        "type": "Point",
        "coordinates": [
          104.7167,
          29.3167
        ]
      },
      "type": "Feature",
      "properties": {
        "hierarchy": [
          "tgn:1071894",
          "tgn:1000004",
          "tgn:7002087",
          "tgn:1000111",
          "tgn:7029392"
        ],
        "placetype": [
          "aat:300008347"
        ],
        "id": 1071894,
        "name:xx": "Shuping"
      }
    },
    {
      "geometry": {
        "type": "Point",
        "coordinates": [
          118.7667,
          34.1333
        ]
      },
      "type": "Feature",
      "properties": {
        "hierarchy": [
          "tgn:1071895",
          "tgn:1000004",
          "tgn:7002081",
          "tgn:1000111",
          "tgn:7029392"
        ],
        "placetype": [
          "aat:300008347"
        ],
        "id": 1071895,
        "name:xx": "Shuyang"
      }
    },
    {
      "geometry": {
        "type": "Point",
        "coordinates": [
          119.65,
          30.9
        ]
      },
      "type": "Feature",
      "properties": {
        "hierarchy": [
          "tgn:1071896",
          "tgn:1000004",
          "tgn:7002076",
          "tgn:1000111",
          "tgn:7029392"
        ],
        "placetype": [
          "aat:300008347"
        ],
        "id": 1071896,
        "name:xx": "Si'an"
      }
    },
    {
      "geometry": {
        "type": "Point",
        "coordinates": [
          120.75,
          40.8
        ]
      },
      "type": "Feature",
      "properties": {
        "hierarchy": [
          "tgn:1071897",
          "tgn:1000004",
          "tgn:1001390",
          "tgn:1000111",
          "tgn:7029392"
        ],
        "placetype": [
          "aat:300008347"
        ],
        "id": 1071897,
        "name:xx": "Si'erpu"
      }
    },
    {
      "geometry": {
        "type": "Point",
        "coordinates": [
          119.2167,
          33.0833
        ]
      },
      "type": "Feature",
      "properties": {
        "hierarchy": [
          "tgn:1071898",
          "tgn:1000004",
          "tgn:7002081",
          "tgn:1000111",
          "tgn:7029392"
        ],
        "placetype": [
          "aat:300008347"
        ],
        "id": 1071898,
        "name:xx": "Sianzhuang"
      }
    },
    {
      "geometry": {
        "type": "Point",
        "coordinates": [
          116.7,
          25.9167
        ]
      },
      "type": "Feature",
      "properties": {
        "hierarchy": [
          "tgn:1071899",
          "tgn:1000004",
          "tgn:7001796",
          "tgn:1000111",
          "tgn:7029392"
        ],
        "placetype": [
          "aat:300008347"
        ],
        "id": 1071899,
        "name:xx": "Sibao"
      }
    }
  ]
}
