{
  "geometry": {
    "type": "Point",
    "coordinates": [
      -123.9167,
      45.8167
    ]
  },
  "type": "Feature",
  "properties": {
    "hierarchy": [
      "tgn:2655350",
      "tgn:1000001",
      "tgn:1002276",
      "tgn:7012149",
      "tgn:7007708",
      "tgn:7029392"
    ],
    "placetype": [
      "aat:300008706"
    ],
    "id": 2655350,
    "name:xx": "Shark Creek"
  }
}
