{
  "type": "FeatureCollection",
  "features": [
    {
      "geometry": {
        "type": "Point",
        "coordinates": [
          -88.3667,
          46.4833
        ]
      },
      "type": "Feature",
      "properties": {
        "hierarchy": [
          "tgn:2519580",
          "tgn:2000947",
          "tgn:1000001",
          "tgn:7012149",
          "tgn:7007520",
          "tgn:7029392"
        ],
        "placetype": [
          "aat:300008680"
        ],
        "id": 2519580,
        "name:xx": "Mogans Lake"
      }
    },
    {
      "geometry": {
        "type": "Point",
        "coordinates": [
          -111.3,
          40
        ]
      },
      "type": "Feature",
      "properties": {
        "hierarchy": [
          "tgn:2519581",
          "tgn:1000001",
          "tgn:7012149",
          "tgn:2002125",
          "tgn:7007827",
          "tgn:7029392"
        ],
        "placetype": [
          "aat:300008697"
        ],
        "id": 2519581,
        "name:xx": "Mogbeck Spring"
      }
    },
    {
      "geometry": {
        "type": "Point",
        "coordinates": [
          -106.0667,
          32.8
        ]
      },
      "type": "Feature",
      "properties": {
        "hierarchy": [
          "tgn:2519582",
          "tgn:1000001",
          "tgn:7012149",
          "tgn:2001447",
          "tgn:7007566",
          "tgn:7029392"
        ],
        "placetype": [
          "aat:300006191"
        ],
        "id": 2519582,
        "name:xx": "Mogee Tank"
      }
    },
    {
      "geometry": {
        "type": "Point",
        "coordinates": [
          -75.3167,
          40.1
        ]
      },
      "type": "Feature",
      "properties": {
        "hierarchy": [
          "tgn:2519583",
          "tgn:1000001",
          "tgn:7012149",
          "tgn:1002690",
          "tgn:7007710",
          "tgn:7029392"
        ],
        "placetype": [
          "aat:300008347"
        ],
        "id": 2519583,
        "name:xx": "Mogees Station"
      }
    },
    {
      "geometry": {
        "type": "Point",
        "coordinates": [
          -113.7167,
          44.6667
        ]
      },
      "type": "Feature",
      "properties": {
        "hierarchy": [
          "tgn:2519584",
          "tgn:1000001",
          "tgn:7012149",
          "tgn:2000481",
          "tgn:7007250",
          "tgn:7029392"
        ],
        "placetype": [
          "aat:300008706"
        ],
        "id": 2519584,
        "name:xx": "Mogg Creek"
      }
    },
    {
      "geometry": {
        "type": "Point",
        "coordinates": [
          -113.7,
          44.6667
        ]
      },
      "type": "Feature",
      "properties": {
        "hierarchy": [
          "tgn:2519585",
          "tgn:1000001",
          "tgn:7012149",
          "tgn:2000481",
          "tgn:7007250",
          "tgn:7029392"
        ],
        "placetype": [
          "aat:300008798"
        ],
        "id": 2519585,
        "name:xx": "Mogg Mountain"
      }
    },
    {
      "geometry": {
        "type": "Point",
        "coordinates": [
          -171.6,
          63.4833
        ]
      },
      "type": "Feature",
      "properties": {
        "hierarchy": [
          "tgn:2519586",
          "tgn:7006450",
          "tgn:1000001",
          "tgn:7012149",
          "tgn:2000079",
          "tgn:7029392"
        ],
        "placetype": [
          "aat:300008707"
        ],
        "id": 2519586,
        "name:xx": "Moghoweyik River"
      }
    },
    {
      "geometry": {
        "type": "Point",
        "coordinates": [
          -92.2167,
          46.7667
        ]
      },
      "type": "Feature",
      "properties": {
        "hierarchy": [
          "tgn:2519587",
          "tgn:1000001",
          "tgn:7012149",
          "tgn:2001067",
          "tgn:7007521",
          "tgn:7029392"
        ],
        "placetype": [
          "aat:300008680"
        ],
        "id": 2519587,
        "name:xx": "Mogie Lake"
      }
    },
    {
      "geometry": {
        "type": "Point",
        "coordinates": [
          -135.3833,
          57.0333
        ]
      },
      "type": "Feature",
      "properties": {
        "hierarchy": [
          "tgn:2519588",
          "tgn:7006450",
          "tgn:1000001",
          "tgn:7012149",
          "tgn:2124002",
          "tgn:7029392"
        ],
        "placetype": [
          "aat:300008791"
        ],
        "id": 2519588,
        "name:xx": "Mogilnoi Island"
      }
    },
    {
      "geometry": {
        "type": "Point",
        "coordinates": [
          -110.5,
          34.4167
        ]
      },
      "type": "Feature",
      "properties": {
        "hierarchy": [
          "tgn:2519589",
          "tgn:1000001",
          "tgn:7006451",
          "tgn:7012149",
          "tgn:2000099",
          "tgn:7029392"
        ],
        "placetype": [
          "aat:300008805"
        ],
        "id": 2519589,
        "name:xx": "Mogo Uon Plateau"
      }
    }
  ]
}
