{
  "geometry": {
    "type": "Point",
    "coordinates": [
      -3.6275,
      43.470556
    ]
  },
  "type": "Feature",
  "properties": {
    "hierarchy": [
      "tgn:7296014",
      "tgn:7002760",
      "tgn:1000003",
      "tgn:1000095",
      "tgn:7029392"
    ],
    "placetype": [
      "aat:300008795"
    ],
    "id": 7296014,
    "name:xx": "Galizano, Monte"
  }
}
