{
  "geometry": {
    "type": "Point",
    "coordinates": [
      -104.7333,
      32.0333
    ]
  },
  "type": "Feature",
  "properties": {
    "hierarchy": [
      "tgn:2466228",
      "tgn:1000001",
      "tgn:2001436",
      "tgn:7012149",
      "tgn:7007566",
      "tgn:7029392"
    ],
    "placetype": [
      "aat:300266640"
    ],
    "id": 2466228,
    "name:xx": "Lonesome Ridge"
  }
}
