{
  "geometry": {
    "type": "Point",
    "coordinates": [
      -73.0333,
      41.3667
    ]
  },
  "type": "Feature",
  "properties": {
    "hierarchy": [
      "tgn:2175199",
      "tgn:1000001",
      "tgn:1002712",
      "tgn:7012149",
      "tgn:7007159",
      "tgn:7029392"
    ],
    "placetype": [
      "aat:300008699"
    ],
    "id": 2175199,
    "name:xx": "Black Brook"
  }
}
