{
  "geometry": {
    "type": "Point",
    "coordinates": [
      -83.3833,
      42.1167
    ]
  },
  "type": "Feature",
  "properties": {
    "hierarchy": [
      "tgn:2299913",
      "tgn:1000001",
      "tgn:7012149",
      "tgn:7007520",
      "tgn:7029392"
    ],
    "placetype": [
      "aat:300008699"
    ],
    "id": 2299913,
    "name:xx": "Duff Drain"
  }
}
