{
  "geometry": {
    "type": "Point",
    "coordinates": [
      -108.3167,
      41.05
    ]
  },
  "type": "Feature",
  "properties": {
    "hierarchy": [
      "tgn:2126814",
      "tgn:1000001",
      "tgn:7012149",
      "tgn:2002383",
      "tgn:7007923",
      "tgn:7029392"
    ],
    "placetype": [
      "aat:300006191"
    ],
    "id": 2126814,
    "name:xx": "Agropyron Reservoir"
  }
}
