{
  "geometry": {
    "type": "Point",
    "coordinates": [
      -118.4333,
      36.5667
    ]
  },
  "type": "Feature",
  "properties": {
    "hierarchy": [
      "tgn:2625527",
      "tgn:1000001",
      "tgn:7012149",
      "tgn:7007157",
      "tgn:1002621",
      "tgn:7029392"
    ],
    "placetype": [
      "aat:300008680"
    ],
    "id": 2625527,
    "name:xx": "Rockslide Lake"
  }
}
