{
  "type": "FeatureCollection",
  "features": [
    {
      "geometry": {
        "type": "Point",
        "coordinates": [
          9.233333,
          54.1
        ]
      },
      "type": "Feature",
      "properties": {
        "hierarchy": [
          "tgn:7073620",
          "tgn:1000003",
          "tgn:7003688",
          "tgn:7000084",
          "tgn:7029392"
        ],
        "placetype": [
          "aat:300386990"
        ],
        "id": 7073620,
        "name:xx": "Südermoor"
      }
    },
    {
      "geometry": {
        "type": "Point",
        "coordinates": [
          8.933333,
          53.766667
        ]
      },
      "type": "Feature",
      "properties": {
        "hierarchy": [
          "tgn:7073621",
          "tgn:1000003",
          "tgn:7003676",
          "tgn:7000084",
          "tgn:7029392"
        ],
        "placetype": [
          "aat:300387200"
        ],
        "id": 7073621,
        "name:xx": "Südermittelteil"
      }
    },
    {
      "geometry": {
        "type": "Point",
        "coordinates": [
          8.633333,
          54.5
        ]
      },
      "type": "Feature",
      "properties": {
        "hierarchy": [
          "tgn:7073622",
          "tgn:1000003",
          "tgn:7003688",
          "tgn:7000084",
          "tgn:7029392"
        ],
        "placetype": [
          "aat:300008347"
        ],
        "id": 7073622,
        "name:xx": "Südermitteldeich"
      }
    },
    {
      "geometry": {
        "type": "Point",
        "coordinates": [
          9.066667,
          54.1
        ]
      },
      "type": "Feature",
      "properties": {
        "hierarchy": [
          "tgn:7073623",
          "tgn:1000003",
          "tgn:7003688",
          "tgn:7000084",
          "tgn:7029392"
        ],
        "placetype": [
          "aat:300008699"
        ],
        "id": 7073623,
        "name:xx": "Süder Miele"
      }
    },
    {
      "geometry": {
        "type": "Point",
        "coordinates": [
          9.033333,
          54.45
        ]
      },
      "type": "Feature",
      "properties": {
        "hierarchy": [
          "tgn:7073624",
          "tgn:1000003",
          "tgn:7003688",
          "tgn:7000084",
          "tgn:7029392"
        ],
        "placetype": [
          "aat:300006163"
        ],
        "id": 7073624,
        "name:xx": "Südermarschkoog"
      }
    },
    {
      "geometry": {
        "type": "Point",
        "coordinates": [
          9.1,
          54.433333
        ]
      },
      "type": "Feature",
      "properties": {
        "hierarchy": [
          "tgn:7073625",
          "tgn:1000003",
          "tgn:7003688",
          "tgn:7000084",
          "tgn:7029392"
        ],
        "placetype": [
          "aat:300008903"
        ],
        "id": 7073625,
        "name:xx": "Süder Marsch"
      }
    },
    {
      "geometry": {
        "type": "Point",
        "coordinates": [
          8.8,
          54.333333
        ]
      },
      "type": "Feature",
      "properties": {
        "hierarchy": [
          "tgn:7073626",
          "tgn:1000003",
          "tgn:7003688",
          "tgn:7000084",
          "tgn:7029392"
        ],
        "placetype": [
          "aat:300008903"
        ],
        "id": 7073626,
        "name:xx": "Südermarsch"
      }
    },
    {
      "geometry": {
        "type": "Point",
        "coordinates": [
          9.083333,
          54.416667
        ]
      },
      "type": "Feature",
      "properties": {
        "hierarchy": [
          "tgn:7073627",
          "tgn:1000003",
          "tgn:7003688",
          "tgn:7000084",
          "tgn:7029392"
        ],
        "placetype": [
          "aat:300387173"
        ],
        "id": 7073627,
        "name:xx": "Südermarsch"
      }
    },
    {
      "geometry": {
        "type": "Point",
        "coordinates": [
          8.95,
          54.866667
        ]
      },
      "type": "Feature",
      "properties": {
        "hierarchy": [
          "tgn:7073628",
          "tgn:1000003",
          "tgn:7003688",
          "tgn:7000084",
          "tgn:7029392"
        ],
        "placetype": [
          "aat:300008863"
        ],
        "id": 7073628,
        "name:xx": "Süderlügum, Forst"
      }
    }
  ]
}
