{
  "geometry": {
    "type": "Point",
    "coordinates": [
      30.7167,
      55.3333
    ]
  },
  "type": "Feature",
  "properties": {
    "hierarchy": [
      "tgn:1054563",
      "tgn:7011701",
      "tgn:1000003",
      "tgn:7006657",
      "tgn:7029392"
    ],
    "placetype": [
      "aat:300008347"
    ],
    "id": 1054563,
    "name:xx": "Yanovichi"
  }
}
