{
  "type": "FeatureCollection",
  "features": [
    {
      "geometry": {
        "type": "Point",
        "coordinates": [
          -2.633333,
          55.283333
        ]
      },
      "type": "Feature",
      "properties": {
        "hierarchy": [
          "tgn:7458020",
          "tgn:7002444",
          "tgn:1000003",
          "tgn:7008072",
          "tgn:7008591",
          "tgn:7029392"
        ],
        "placetype": [
          "aat:300008699"
        ],
        "name:en": "Peel Burn",
        "id": 7458020
      }
    },
    {
      "geometry": {
        "type": "Point",
        "coordinates": [
          -3.25,
          55.75
        ]
      },
      "type": "Feature",
      "properties": {
        "hierarchy": [
          "tgn:7458021",
          "tgn:7002444",
          "tgn:1000003",
          "tgn:7008072",
          "tgn:7008591",
          "tgn:7029392"
        ],
        "placetype": [
          "aat:300387145"
        ],
        "name:en": "Peeblesshire",
        "id": 7458021
      }
    },
    {
      "geometry": {
        "type": "Point",
        "coordinates": [
          -5.65,
          50.866667
        ]
      },
      "type": "Feature",
      "properties": {
        "hierarchy": [
          "tgn:7458023",
          "tgn:7002445",
          "tgn:7008116",
          "tgn:1000003",
          "tgn:7008591",
          "tgn:7029392"
        ],
        "placetype": [
          "aat:300008749"
        ],
        "name:en": "Pedn-mên-an-mere",
        "id": 7458023
      }
    },
    {
      "geometry": {
        "type": "Point",
        "coordinates": [
          -2.133333,
          52.45
        ]
      },
      "type": "Feature",
      "properties": {
        "hierarchy": [
          "tgn:7458024",
          "tgn:7019030",
          "tgn:7002445",
          "tgn:1000003",
          "tgn:7029506",
          "tgn:7008591",
          "tgn:7029392"
        ],
        "placetype": [
          "aat:300008347"
        ],
        "name:en": "Pedmore",
        "id": 7458024
      }
    },
    {
      "geometry": {
        "type": "Point",
        "coordinates": [
          -3.666667,
          55.4
        ]
      },
      "type": "Feature",
      "properties": {
        "hierarchy": [
          "tgn:7458025",
          "tgn:7002444",
          "tgn:1000003",
          "tgn:7019090",
          "tgn:7008591",
          "tgn:7029392"
        ],
        "placetype": [
          "aat:300008699"
        ],
        "name:en": "Peden Burn",
        "id": 7458025
      }
    },
    {
      "geometry": {
        "type": "Point",
        "coordinates": [
          -1.8,
          52.116667
        ]
      },
      "type": "Feature",
      "properties": {
        "hierarchy": [
          "tgn:7458027",
          "tgn:7002445",
          "tgn:1000003",
          "tgn:5000227",
          "tgn:7008591",
          "tgn:7029392"
        ],
        "placetype": [
          "aat:300008347"
        ],
        "name:en": "Pebworth",
        "id": 7458027
      }
    }
  ]
}
