{
  "geometry": {
    "type": "Point",
    "coordinates": [
      -123.4667,
      43.2833
    ]
  },
  "type": "Feature",
  "properties": {
    "hierarchy": [
      "tgn:2290634",
      "tgn:1000001",
      "tgn:7012149",
      "tgn:2001706",
      "tgn:7007708",
      "tgn:7029392"
    ],
    "placetype": [
      "aat:300006191"
    ],
    "id": 2290634,
    "name:xx": "Doerner Reservoir"
  }
}
