{
  "geometry": {
    "type": "Point",
    "coordinates": [
      178.45,
      -37.65
    ]
  },
  "type": "Feature",
  "properties": {
    "hierarchy": [
      "tgn:7508293",
      "tgn:7520092",
      "tgn:1008380",
      "tgn:1000226",
      "tgn:1000006",
      "tgn:7029392"
    ],
    "placetype": [
      "aat:300008699"
    ],
    "name:en": "Oruatua Stream",
    "id": 7508293
  }
}
