{
  "geometry": {
    "type": "Point",
    "coordinates": [
      -84.5167,
      37.2167
    ]
  },
  "type": "Feature",
  "properties": {
    "hierarchy": [
      "tgn:2664814",
      "tgn:1000001",
      "tgn:7012149",
      "tgn:2000839",
      "tgn:7007255",
      "tgn:7029392"
    ],
    "placetype": [
      "aat:300008761"
    ],
    "id": 2664814,
    "name:xx": "Simon Hollow"
  }
}
