{
  "geometry": {
    "type": "Point",
    "coordinates": [
      -120.4167,
      38.4833
    ]
  },
  "type": "Feature",
  "properties": {
    "hierarchy": [
      "tgn:2281547",
      "tgn:1002146",
      "tgn:1000001",
      "tgn:7012149",
      "tgn:7007157",
      "tgn:7029392"
    ],
    "placetype": [
      "aat:300008706"
    ],
    "id": 2281547,
    "name:xx": "Deer Creek"
  }
}
