{
  "geometry": {
    "type": "Point",
    "coordinates": [
      -107.4333,
      32.5667
    ]
  },
  "type": "Feature",
  "properties": {
    "hierarchy": [
      "tgn:2067273",
      "tgn:1000001",
      "tgn:7012149",
      "tgn:2001444",
      "tgn:7007566",
      "tgn:7029392"
    ],
    "placetype": [
      "aat:300387016"
    ],
    "id": 2067273,
    "name:xx": "Nutt"
  }
}
