{
  "geometry": {
    "type": "Point",
    "coordinates": [
      15.4667,
      12.0167
    ]
  },
  "type": "Feature",
  "properties": {
    "hierarchy": [
      "tgn:1088484",
      "tgn:7001242",
      "tgn:1000970",
      "tgn:1000156",
      "tgn:7029392"
    ],
    "placetype": [
      "aat:300008347"
    ],
    "id": 1088484,
    "name:xx": "Bomboyo"
  }
}
