{
  "geometry": {
    "type": "Point",
    "coordinates": [
      79.447942,
      30.25631
    ]
  },
  "type": "Feature",
  "properties": {
    "hierarchy": [
      "tgn:7570675",
      "tgn:1000004",
      "tgn:7000198",
      "tgn:7031786",
      "tgn:7029392"
    ],
    "placetype": [
      "aat:300008347"
    ],
    "name:en": "Ghāt",
    "id": 7570675
  }
}
