{
  "geometry": {
    "type": "Point",
    "coordinates": [
      90.883692,
      26.50862
    ]
  },
  "type": "Feature",
  "properties": {
    "hierarchy": [
      "tgn:7588287",
      "tgn:1000004",
      "tgn:1001832",
      "tgn:7000198",
      "tgn:7029392"
    ],
    "placetype": [
      "aat:300008347"
    ],
    "name:en": "Ahompathār",
    "id": 7588287
  }
}
