{
  "geometry": {
    "type": "Point",
    "coordinates": [
      13.8833,
      46.2833
    ]
  },
  "type": "Feature",
  "properties": {
    "hierarchy": [
      "tgn:1065265",
      "tgn:1000003",
      "tgn:7015085",
      "tgn:7006670",
      "tgn:7029392"
    ],
    "placetype": [
      "aat:300008347"
    ],
    "id": 1065265,
    "name:xx": "Stara Fužina"
  }
}
