{
  "geometry": {
    "type": "Point",
    "coordinates": [
      -44.65,
      -22.75
    ]
  },
  "type": "Feature",
  "properties": {
    "hierarchy": [
      "tgn:1106749",
      "tgn:1001945",
      "tgn:1000047",
      "tgn:7002457",
      "tgn:1000002",
      "tgn:7029392"
    ],
    "placetype": [
      "aat:300008795"
    ],
    "id": 1106749,
    "name:xx": "Tira Chapéu, Morro"
  }
}
