{
  "geometry": {
    "type": "Point",
    "coordinates": [
      -109.9667,
      47.6333
    ]
  },
  "type": "Feature",
  "properties": {
    "hierarchy": [
      "tgn:2134641",
      "tgn:1000001",
      "tgn:2001267",
      "tgn:7012149",
      "tgn:7007524",
      "tgn:7029392"
    ],
    "placetype": [
      "aat:300008761"
    ],
    "id": 2134641,
    "name:xx": "Antelope Coulee"
  }
}
