{
  "geometry": {
    "type": "Point",
    "coordinates": [
      -82.0333,
      32.85
    ]
  },
  "type": "Feature",
  "properties": {
    "hierarchy": [
      "tgn:2454878",
      "tgn:1000001",
      "tgn:7012149",
      "tgn:2000373",
      "tgn:7007248",
      "tgn:7029392"
    ],
    "placetype": [
      "aat:300008680"
    ],
    "id": 2454878,
    "name:xx": "Little Dukes Pond"
  }
}
