{
  "geometry": {
    "type": "Point",
    "coordinates": [
      -81.75,
      39.0167
    ]
  },
  "type": "Feature",
  "properties": {
    "hierarchy": [
      "tgn:2119269",
      "tgn:1000001",
      "tgn:7012149",
      "tgn:2002268",
      "tgn:7013961",
      "tgn:7029392"
    ],
    "placetype": [
      "aat:300008347",
      "aat:300387210"
    ],
    "id": 2119269,
    "name:xx": "Morgan"
  }
}
