{
  "geometry": {
    "type": "Point",
    "coordinates": [
      -118.3667,
      45.25
    ]
  },
  "type": "Feature",
  "properties": {
    "hierarchy": [
      "tgn:2776192",
      "tgn:1000001",
      "tgn:7012149",
      "tgn:2001721",
      "tgn:7007708",
      "tgn:7029392"
    ],
    "placetype": [
      "aat:300008706"
    ],
    "id": 2776192,
    "name:xx": "Wilts Creek"
  }
}
