{
  "geometry": {
    "type": "Point",
    "coordinates": [
      -121.9667,
      41.15
    ]
  },
  "type": "Feature",
  "properties": {
    "hierarchy": [
      "tgn:2580457",
      "tgn:1000001",
      "tgn:7012149",
      "tgn:7007157",
      "tgn:2000188",
      "tgn:7029392"
    ],
    "placetype": [
      "aat:300008706"
    ],
    "id": 2580457,
    "name:xx": "Pigeon Creek"
  }
}
