{
  "geometry": {
    "type": "Point",
    "coordinates": [
      65.2667,
      54.05
    ]
  },
  "type": "Feature",
  "properties": {
    "hierarchy": [
      "tgn:1137848",
      "tgn:1000004",
      "tgn:7012922",
      "tgn:7014786",
      "tgn:7029392"
    ],
    "placetype": [
      "aat:300008347"
    ],
    "id": 1137848,
    "name:xx": "Leninskoye"
  }
}
