{
  "geometry": {
    "type": "Point",
    "coordinates": [
      -70.5333,
      45.25
    ]
  },
  "type": "Feature",
  "properties": {
    "hierarchy": [
      "tgn:2654871",
      "tgn:1000001",
      "tgn:2000921",
      "tgn:7012149",
      "tgn:7007515",
      "tgn:7029392"
    ],
    "placetype": [
      "aat:300008680"
    ],
    "id": 2654871,
    "name:xx": "Shallow Pond"
  }
}
