{
  "geometry": {
    "type": "Point",
    "coordinates": [
      77.453545,
      28.953708
    ]
  },
  "type": "Feature",
  "properties": {
    "hierarchy": [
      "tgn:7546676",
      "tgn:1000004",
      "tgn:7000198",
      "tgn:7016722",
      "tgn:7029392"
    ],
    "placetype": [
      "aat:300008347"
    ],
    "name:en": "Bāleni",
    "id": 7546676
  }
}
