{
  "geometry": {
    "type": "Point",
    "coordinates": [
      -73.65,
      44.4333
    ]
  },
  "type": "Feature",
  "properties": {
    "hierarchy": [
      "tgn:2367837",
      "tgn:1000001",
      "tgn:7012149",
      "tgn:2001461",
      "tgn:7007568",
      "tgn:7029392"
    ],
    "placetype": [
      "aat:300132451"
    ],
    "id": 2367837,
    "name:xx": "Grove, The"
  }
}
