{
  "geometry": {
    "type": "Point",
    "coordinates": [
      -122.2667,
      40.1833
    ]
  },
  "type": "Feature",
  "properties": {
    "hierarchy": [
      "tgn:2193702",
      "tgn:1000001",
      "tgn:7012149",
      "tgn:7007157",
      "tgn:2000190",
      "tgn:7029392"
    ],
    "placetype": [
      "aat:300008706"
    ],
    "id": 2193702,
    "name:xx": "Brewery Creek"
  }
}
