{
  "geometry": {
    "type": "Point",
    "coordinates": [
      -107.3167,
      38.8833
    ]
  },
  "type": "Feature",
  "properties": {
    "hierarchy": [
      "tgn:2297633",
      "tgn:1000001",
      "tgn:7012149",
      "tgn:2000217",
      "tgn:7007158",
      "tgn:7029392"
    ],
    "placetype": [
      "aat:300008706"
    ],
    "id": 2297633,
    "name:xx": "Dry Fork Snowshoe Creek"
  }
}
