{
  "geometry": {
    "type": "Point",
    "coordinates": [
      -4.25,
      5.8333
    ]
  },
  "type": "Feature",
  "properties": {
    "hierarchy": [
      "tgn:1000489",
      "tgn:7001242",
      "tgn:1000168",
      "tgn:7029392"
    ],
    "placetype": [
      "aat:300387064",
      "aat:300000772"
    ],
    "id": 1000489,
    "name:xx": "Agboville, Département d'"
  }
}
