{
  "geometry": {
    "type": "Point",
    "coordinates": [
      -115.95,
      30.933333
    ]
  },
  "type": "Feature",
  "properties": {
    "hierarchy": [
      "tgn:7437462",
      "tgn:1001835",
      "tgn:1000001",
      "tgn:7005560",
      "tgn:7029392"
    ],
    "placetype": [
      "aat:300008699"
    ],
    "id": 7437462,
    "name:xx": "San Telmo, Río"
  }
}
