{
  "geometry": {
    "type": "Point",
    "coordinates": [
      10.35,
      42.75
    ]
  },
  "type": "Feature",
  "properties": {
    "hierarchy": [
      "tgn:7036177",
      "tgn:7003164",
      "tgn:1000003",
      "tgn:7009760",
      "tgn:1000080",
      "tgn:7029392"
    ],
    "placetype": [
      "aat:300386846"
    ],
    "id": 7036177,
    "name:xx": "Zuccale, Punta di"
  }
}
