{
  "geometry": {
    "type": "Point",
    "coordinates": [
      -87.8667,
      36.0333
    ]
  },
  "type": "Feature",
  "properties": {
    "hierarchy": [
      "tgn:2690441",
      "tgn:1000001",
      "tgn:7012149",
      "tgn:2001879",
      "tgn:7007825",
      "tgn:7029392"
    ],
    "placetype": [
      "aat:300008798"
    ],
    "id": 2690441,
    "name:xx": "Stairstep Hill"
  }
}
