{
  "type": "FeatureCollection",
  "features": [
    {
      "geometry": {
        "type": "Point",
        "coordinates": [
          -61.1167,
          14.7
        ]
      },
      "type": "Feature",
      "properties": {
        "hierarchy": [
          "tgn:1107650",
          "tgn:7015035",
          "tgn:1000001",
          "tgn:7005870",
          "tgn:7029392"
        ],
        "placetype": [
          "aat:300008798"
        ],
        "id": 1107650,
        "name:xx": "Carbet, Pitons du"
      }
    },
    {
      "geometry": {
        "type": "Point",
        "coordinates": [
          -117.7,
          35.4667
        ]
      },
      "type": "Feature",
      "properties": {
        "hierarchy": [
          "tgn:1107651",
          "tgn:1000001",
          "tgn:7012149",
          "tgn:1002545",
          "tgn:7007157",
          "tgn:7029392"
        ],
        "placetype": [
          "aat:300008798"
        ],
        "id": 1107651,
        "name:xx": "El Paso Peaks"
      }
    },
    {
      "geometry": {
        "type": "Point",
        "coordinates": [
          -106.8,
          36.1167
        ]
      },
      "type": "Feature",
      "properties": {
        "hierarchy": [
          "tgn:1107652",
          "tgn:1000001",
          "tgn:7012149",
          "tgn:2001449",
          "tgn:7007566",
          "tgn:7029392"
        ],
        "placetype": [
          "aat:300008798"
        ],
        "id": 1107652,
        "name:xx": "San Pedro Peaks"
      }
    },
    {
      "geometry": {
        "type": "Point",
        "coordinates": [
          -128.1667,
          54.9667
        ]
      },
      "type": "Feature",
      "properties": {
        "hierarchy": [
          "tgn:1107653",
          "tgn:7005735",
          "tgn:7005685",
          "tgn:1000001",
          "tgn:7029392"
        ],
        "placetype": [
          "aat:300008798"
        ],
        "id": 1107653,
        "name:xx": "Seven Sisters Peaks"
      }
    },
    {
      "geometry": {
        "type": "Point",
        "coordinates": [
          64.6667,
          -69.7
        ]
      },
      "type": "Feature",
      "properties": {
        "hierarchy": [
          "tgn:1107654",
          "tgn:1000007",
          "tgn:7029392"
        ],
        "placetype": [
          "aat:300008798"
        ],
        "id": 1107654,
        "name:xx": "Stinear Nunataks"
      }
    },
    {
      "geometry": {
        "type": "Point",
        "coordinates": [
          -122.4333,
          37.75
        ]
      },
      "type": "Feature",
      "properties": {
        "hierarchy": [
          "tgn:1107656",
          "tgn:1000001",
          "tgn:7012149",
          "tgn:7007157",
          "tgn:1002859",
          "tgn:7029392"
        ],
        "placetype": [
          "aat:300008798"
        ],
        "id": 1107656,
        "name:xx": "Twin Peaks"
      }
    },
    {
      "geometry": {
        "type": "Point",
        "coordinates": [
          -114.4667,
          44.6
        ]
      },
      "type": "Feature",
      "properties": {
        "hierarchy": [
          "tgn:1107657",
          "tgn:1000001",
          "tgn:7012149",
          "tgn:7007250",
          "tgn:7029392"
        ],
        "placetype": [
          "aat:300008798"
        ],
        "id": 1107657,
        "name:xx": "Twin Peaks"
      }
    },
    {
      "geometry": {
        "type": "Point",
        "coordinates": [
          118.3333,
          9.3667
        ]
      },
      "type": "Feature",
      "properties": {
        "hierarchy": [
          "tgn:1107658",
          "tgn:1000004",
          "tgn:1001481",
          "tgn:1000135",
          "tgn:7029392"
        ],
        "placetype": [
          "aat:300008798"
        ],
        "id": 1107658,
        "name:xx": "Victoria Peaks"
      }
    },
    {
      "geometry": {
        "type": "Point",
        "coordinates": [
          -104.45,
          44.4667
        ]
      },
      "type": "Feature",
      "properties": {
        "hierarchy": [
          "tgn:1107659",
          "tgn:1000001",
          "tgn:2002370",
          "tgn:7012149",
          "tgn:7007923",
          "tgn:7029392"
        ],
        "placetype": [
          "aat:300008798"
        ],
        "id": 1107659,
        "name:xx": "Warren Peaks"
      }
    }
  ]
}
