{
  "type": "FeatureCollection",
  "features": [
    {
      "geometry": {
        "type": "Point",
        "coordinates": [
          -99.216667,
          20.2
        ]
      },
      "type": "Feature",
      "properties": {
        "hierarchy": [
          "tgn:1103550",
          "tgn:1000001",
          "tgn:7005601",
          "tgn:7005560",
          "tgn:7029392"
        ],
        "placetype": [
          "aat:300008795"
        ],
        "id": 1103550,
        "name:xx": "Ángel, Cerro"
      }
    },
    {
      "geometry": {
        "type": "Point",
        "coordinates": [
          -55.3167,
          -34.7667
        ]
      },
      "type": "Feature",
      "properties": {
        "hierarchy": [
          "tgn:1103551",
          "tgn:7002649",
          "tgn:1000002",
          "tgn:1000058",
          "tgn:7029392"
        ],
        "placetype": [
          "aat:300008795"
        ],
        "id": 1103551,
        "name:xx": "Cerro de las Ánimas"
      }
    },
    {
      "geometry": {
        "type": "Point",
        "coordinates": [
          6.3333,
          44.8333
        ]
      },
      "type": "Feature",
      "properties": {
        "hierarchy": [
          "tgn:1103553",
          "tgn:1000003",
          "tgn:1000070",
          "tgn:7029392"
        ],
        "placetype": [
          "aat:300008795"
        ],
        "id": 1103553,
        "name:xx": "Écrins, les"
      }
    },
    {
      "geometry": {
        "type": "Point",
        "coordinates": [
          23.816667,
          37.95
        ]
      },
      "type": "Feature",
      "properties": {
        "hierarchy": [
          "tgn:1103554",
          "tgn:7002681",
          "tgn:7001395",
          "tgn:1000003",
          "tgn:1000074",
          "tgn:7029392"
        ],
        "placetype": [
          "aat:300008795",
          "aat:300008798"
        ],
        "id": 1103554,
        "name:xx": "Évzonos"
      }
    },
    {
      "geometry": {
        "type": "Point",
        "coordinates": [
          24.75,
          35.25
        ]
      },
      "type": "Feature",
      "properties": {
        "hierarchy": [
          "tgn:1103555",
          "tgn:7002691",
          "tgn:7012056",
          "tgn:1000003",
          "tgn:1000074",
          "tgn:7029392"
        ],
        "placetype": [
          "aat:300008795"
        ],
        "name:en": "Mount Ida",
        "id": 1103555
      }
    },
    {
      "geometry": {
        "type": "Point",
        "coordinates": [
          39.7,
          40.5667
        ]
      },
      "type": "Feature",
      "properties": {
        "hierarchy": [
          "tgn:1103559",
          "tgn:1001256",
          "tgn:1000004",
          "tgn:7018454",
          "tgn:1000144",
          "tgn:7029392"
        ],
        "placetype": [
          "aat:300008795"
        ],
        "id": 1103559,
        "name:xx": "Cakirgol Dagi"
      }
    }
  ]
}
