{
  "geometry": {
    "type": "Point",
    "coordinates": [
      -57.5833,
      -19.0167
    ]
  },
  "type": "Feature",
  "properties": {
    "hierarchy": [
      "tgn:1021917",
      "tgn:1001898",
      "tgn:7002454",
      "tgn:1000047",
      "tgn:1000002",
      "tgn:7029392"
    ],
    "placetype": [
      "aat:300008347"
    ],
    "id": 1021917,
    "name:xx": "Ladário"
  }
}
