{
  "geometry": {
    "type": "Point",
    "coordinates": [
      79.08237,
      27.600636
    ]
  },
  "type": "Feature",
  "properties": {
    "hierarchy": [
      "tgn:7551299",
      "tgn:1000004",
      "tgn:7000198",
      "tgn:7016722",
      "tgn:7029392"
    ],
    "placetype": [
      "aat:300007783"
    ],
    "name:en": "Dariāoganj",
    "id": 7551299
  }
}
