{
  "geometry": {
    "type": "Point",
    "coordinates": [
      -78.8667,
      42.8333
    ]
  },
  "type": "Feature",
  "properties": {
    "hierarchy": [
      "tgn:2677870",
      "tgn:1000001",
      "tgn:7012149",
      "tgn:1002356",
      "tgn:7007568",
      "tgn:7029392"
    ],
    "placetype": [
      "aat:300006075"
    ],
    "id": 2677870,
    "name:xx": "South Entrance Outer Channel"
  }
}
