{
  "geometry": {
    "type": "Point",
    "coordinates": [
      -144.95,
      65.4833
    ]
  },
  "type": "Feature",
  "properties": {
    "hierarchy": [
      "tgn:2472207",
      "tgn:7006450",
      "tgn:1000001",
      "tgn:7012149",
      "tgn:2000089",
      "tgn:7029392"
    ],
    "placetype": [
      "aat:300008699"
    ],
    "id": 2472207,
    "name:xx": "Louie Pup"
  }
}
