{
  "geometry": {
    "type": "Point",
    "coordinates": [
      -77.7667,
      40.35
    ]
  },
  "type": "Feature",
  "properties": {
    "hierarchy": [
      "tgn:2348994",
      "tgn:1000001",
      "tgn:7012149",
      "tgn:1002494",
      "tgn:7007710",
      "tgn:7029392"
    ],
    "placetype": [
      "aat:300008761"
    ],
    "id": 2348994,
    "name:xx": "Gifford Hollow"
  }
}
