{
  "geometry": {
    "type": "Point",
    "coordinates": [
      120.422222,
      23.3375
    ]
  },
  "type": "Feature",
  "properties": {
    "hierarchy": [
      "tgn:7483744",
      "tgn:1000004",
      "tgn:7490934",
      "tgn:1000141",
      "tgn:7029392"
    ],
    "placetype": [
      "aat:300007836"
    ],
    "id": 7483744,
    "name:xx": "Cisheng Qiao"
  }
}
