{
  "geometry": {
    "type": "Point",
    "coordinates": [
      136.5333,
      -2.25
    ]
  },
  "type": "Feature",
  "properties": {
    "hierarchy": [
      "tgn:1077769",
      "tgn:1000004",
      "tgn:7003970",
      "tgn:1000116",
      "tgn:7029392"
    ],
    "placetype": [
      "aat:300008347"
    ],
    "id": 1077769,
    "name:xx": "Kai"
  }
}
