{
  "geometry": {
    "type": "Point",
    "coordinates": [
      -74.5667,
      41.9167
    ]
  },
  "type": "Feature",
  "properties": {
    "hierarchy": [
      "tgn:2068530",
      "tgn:1000001",
      "tgn:7012149",
      "tgn:1002926",
      "tgn:7007568",
      "tgn:7029392"
    ],
    "placetype": [
      "aat:300008347"
    ],
    "id": 2068530,
    "name:xx": "Claryville"
  }
}
