{
  "type": "FeatureCollection",
  "features": [
    {
      "geometry": {
        "type": "Point",
        "coordinates": [
          -78.1,
          35.6667
        ]
      },
      "type": "Feature",
      "properties": {
        "hierarchy": [
          "tgn:2392210",
          "tgn:1000001",
          "tgn:7012149",
          "tgn:2001554",
          "tgn:7007709",
          "tgn:7029392"
        ],
        "placetype": [
          "aat:300006191"
        ],
        "id": 2392210,
        "name:xx": "Hinnants Lake"
      }
    },
    {
      "geometry": {
        "type": "Point",
        "coordinates": [
          -75.85,
          40.3667
        ]
      },
      "type": "Feature",
      "properties": {
        "hierarchy": [
          "tgn:2392211",
          "tgn:1000001",
          "tgn:7013387",
          "tgn:7012149",
          "tgn:7007710",
          "tgn:7029392"
        ],
        "placetype": [
          "aat:300006191"
        ],
        "id": 2392211,
        "name:xx": "Hinnerskiz Basin"
      }
    },
    {
      "geometry": {
        "type": "Point",
        "coordinates": [
          -77.7833,
          36.4
        ]
      },
      "type": "Feature",
      "properties": {
        "hierarchy": [
          "tgn:2392212",
          "tgn:1000001",
          "tgn:7012149",
          "tgn:2001501",
          "tgn:7007709",
          "tgn:7029392"
        ],
        "placetype": [
          "aat:300008347"
        ],
        "id": 2392212,
        "name:xx": "Hinnes Crossroads"
      }
    },
    {
      "geometry": {
        "type": "Point",
        "coordinates": [
          -78.1,
          43.25
        ]
      },
      "type": "Feature",
      "properties": {
        "hierarchy": [
          "tgn:2392213",
          "tgn:1000001",
          "tgn:7012149",
          "tgn:1002752",
          "tgn:7007568",
          "tgn:7029392"
        ],
        "placetype": [
          "aat:300008347"
        ],
        "id": 2392213,
        "name:xx": "Hinsburg"
      }
    },
    {
      "geometry": {
        "type": "Point",
        "coordinates": [
          -121.7667,
          39
        ]
      },
      "type": "Feature",
      "properties": {
        "hierarchy": [
          "tgn:2392214",
          "tgn:1000001",
          "tgn:7012149",
          "tgn:7007157",
          "tgn:1002937",
          "tgn:7029392"
        ],
        "placetype": [
          "aat:300008347"
        ],
        "id": 2392214,
        "name:xx": "Hinsdale"
      }
    },
    {
      "geometry": {
        "type": "Point",
        "coordinates": [
          -92.1333,
          47.6
        ]
      },
      "type": "Feature",
      "properties": {
        "hierarchy": [
          "tgn:2392215",
          "tgn:1000001",
          "tgn:7012149",
          "tgn:2001067",
          "tgn:7007521",
          "tgn:7029392"
        ],
        "placetype": [
          "aat:300008347"
        ],
        "id": 2392215,
        "name:xx": "Hinsdale"
      }
    },
    {
      "geometry": {
        "type": "Point",
        "coordinates": [
          -76.1333,
          43.1
        ]
      },
      "type": "Feature",
      "properties": {
        "hierarchy": [
          "tgn:2392216",
          "tgn:1000001",
          "tgn:7012149",
          "tgn:1002746",
          "tgn:7007568",
          "tgn:7029392"
        ],
        "placetype": [
          "aat:300008347"
        ],
        "id": 2392216,
        "name:xx": "Hinsdale"
      }
    },
    {
      "geometry": {
        "type": "Point",
        "coordinates": [
          -72.6667,
          42.65
        ]
      },
      "type": "Feature",
      "properties": {
        "hierarchy": [
          "tgn:2392217",
          "tgn:1000001",
          "tgn:7013942",
          "tgn:7012149",
          "tgn:7007517",
          "tgn:7029392"
        ],
        "placetype": [
          "aat:300008699"
        ],
        "id": 2392217,
        "name:xx": "Hinsdale Brook"
      }
    },
    {
      "geometry": {
        "type": "Point",
        "coordinates": [
          -73.1,
          42.4
        ]
      },
      "type": "Feature",
      "properties": {
        "hierarchy": [
          "tgn:2392218",
          "tgn:7013388",
          "tgn:1000001",
          "tgn:7012149",
          "tgn:7007517",
          "tgn:7029392"
        ],
        "placetype": [
          "aat:300008178"
        ],
        "id": 2392218,
        "name:xx": "Hinsdale Flats Wildlife Management Area"
      }
    },
    {
      "geometry": {
        "type": "Point",
        "coordinates": [
          -92.45,
          47.9
        ]
      },
      "type": "Feature",
      "properties": {
        "hierarchy": [
          "tgn:2392219",
          "tgn:1000001",
          "tgn:7012149",
          "tgn:2001067",
          "tgn:7007521",
          "tgn:7029392"
        ],
        "placetype": [
          "aat:300008791"
        ],
        "id": 2392219,
        "name:xx": "Hinsdale Island"
      }
    }
  ]
}
