{
  "geometry": {
    "type": "Point",
    "coordinates": [
      37.4167,
      48.05
    ]
  },
  "type": "Feature",
  "properties": {
    "hierarchy": [
      "tgn:1056099",
      "tgn:7012076",
      "tgn:1000003",
      "tgn:7006660",
      "tgn:7029392"
    ],
    "placetype": [
      "aat:300008347"
    ],
    "id": 1056099,
    "name:xx": "Kurakhovka"
  }
}
