{
  "type": "FeatureCollection",
  "features": [
    {
      "geometry": {
        "type": "Point",
        "coordinates": [
          9.266667,
          54
        ]
      },
      "type": "Feature",
      "properties": {
        "hierarchy": [
          "tgn:7207361",
          "tgn:1000003",
          "tgn:7003688",
          "tgn:7000084",
          "tgn:7029392"
        ],
        "placetype": [
          "aat:300008347"
        ],
        "id": 7207361,
        "name:xx": "Burg"
      }
    },
    {
      "geometry": {
        "type": "Point",
        "coordinates": [
          9.333333,
          53.65
        ]
      },
      "type": "Feature",
      "properties": {
        "hierarchy": [
          "tgn:7207362",
          "tgn:1000003",
          "tgn:7003676",
          "tgn:7000084",
          "tgn:7029392"
        ],
        "placetype": [
          "aat:300008347"
        ],
        "id": 7207362,
        "name:xx": "Burg"
      }
    },
    {
      "geometry": {
        "type": "Point",
        "coordinates": [
          8.366667,
          53.533333
        ]
      },
      "type": "Feature",
      "properties": {
        "hierarchy": [
          "tgn:7207363",
          "tgn:1000003",
          "tgn:7003676",
          "tgn:7000084",
          "tgn:7029392"
        ],
        "placetype": [
          "aat:300008347"
        ],
        "id": 7207363,
        "name:xx": "Burg"
      }
    },
    {
      "geometry": {
        "type": "Point",
        "coordinates": [
          10.1,
          52.583333
        ]
      },
      "type": "Feature",
      "properties": {
        "hierarchy": [
          "tgn:7207364",
          "tgn:1000003",
          "tgn:7003676",
          "tgn:7000084",
          "tgn:7029392"
        ],
        "placetype": [
          "aat:300008347"
        ],
        "id": 7207364,
        "name:xx": "Burg"
      }
    },
    {
      "geometry": {
        "type": "Point",
        "coordinates": [
          14.35,
          51.466667
        ]
      },
      "type": "Feature",
      "properties": {
        "hierarchy": [
          "tgn:7207367",
          "tgn:1000003",
          "tgn:7003685",
          "tgn:7000084",
          "tgn:7029392"
        ],
        "placetype": [
          "aat:300008347"
        ],
        "id": 7207367,
        "name:xx": "Burg"
      }
    },
    {
      "geometry": {
        "type": "Point",
        "coordinates": [
          12.8,
          47.966667
        ]
      },
      "type": "Feature",
      "properties": {
        "hierarchy": [
          "tgn:7207368",
          "tgn:7003669",
          "tgn:1000003",
          "tgn:7000084",
          "tgn:7029392"
        ],
        "placetype": [
          "aat:300008863"
        ],
        "id": 7207368,
        "name:xx": "Buch-Holz"
      }
    },
    {
      "geometry": {
        "type": "Point",
        "coordinates": [
          9.85,
          54.55
        ]
      },
      "type": "Feature",
      "properties": {
        "hierarchy": [
          "tgn:7207369",
          "tgn:1000003",
          "tgn:7003688",
          "tgn:7000084",
          "tgn:7029392"
        ],
        "placetype": [
          "aat:300000206"
        ],
        "id": 7207369,
        "name:xx": "Buchholz"
      }
    }
  ]
}
