{
  "geometry": {
    "type": "Point",
    "coordinates": [
      -85.4667,
      36.55
    ]
  },
  "type": "Feature",
  "properties": {
    "hierarchy": [
      "tgn:2722684",
      "tgn:1000001",
      "tgn:7012149",
      "tgn:2001850",
      "tgn:7007825",
      "tgn:7029392"
    ],
    "placetype": [
      "aat:300008699"
    ],
    "id": 2722684,
    "name:xx": "Tinsley Branch"
  }
}
