{
  "geometry": {
    "type": "Point",
    "coordinates": [
      -75.4167,
      10.3333
    ]
  },
  "type": "Feature",
  "properties": {
    "hierarchy": [
      "tgn:1024048",
      "tgn:1000529",
      "tgn:1000050",
      "tgn:1000002",
      "tgn:7029392"
    ],
    "placetype": [
      "aat:300008347"
    ],
    "id": 1024048,
    "name:xx": "Turbaco"
  }
}
