{
  "type": "FeatureCollection",
  "features": [
    {
      "geometry": {
        "type": "Point",
        "coordinates": [
          5.333333,
          52.2
        ]
      },
      "type": "Feature",
      "properties": {
        "hierarchy": [
          "tgn:7274030",
          "tgn:1000003",
          "tgn:7003627",
          "tgn:7016845",
          "tgn:7029392"
        ],
        "placetype": [
          "aat:300006163"
        ],
        "name:nl": "Zeldert, Polder",
        "id": 7274030
      }
    },
    {
      "geometry": {
        "type": "Point",
        "coordinates": [
          5.366667,
          52.2
        ]
      },
      "type": "Feature",
      "properties": {
        "hierarchy": [
          "tgn:7274031",
          "tgn:1000003",
          "tgn:7003627",
          "tgn:7016845",
          "tgn:7029392"
        ],
        "placetype": [
          "aat:300008347"
        ],
        "name:nl": "Zeldert",
        "id": 7274031
      }
    },
    {
      "geometry": {
        "type": "Point",
        "coordinates": [
          6.016667,
          51.7
        ]
      },
      "type": "Feature",
      "properties": {
        "hierarchy": [
          "tgn:7274032",
          "tgn:1000003",
          "tgn:7003622",
          "tgn:7016845",
          "tgn:7029392"
        ],
        "placetype": [
          "aat:300008863"
        ],
        "name:nl": "Zelderse Driessen",
        "id": 7274032
      }
    },
    {
      "geometry": {
        "type": "Point",
        "coordinates": [
          6.016667,
          51.7
        ]
      },
      "type": "Feature",
      "properties": {
        "hierarchy": [
          "tgn:7274033",
          "tgn:1000003",
          "tgn:7003622",
          "tgn:7016845",
          "tgn:7029392"
        ],
        "placetype": [
          "aat:300008347"
        ],
        "name:nl": "Zelder",
        "id": 7274033
      }
    },
    {
      "geometry": {
        "type": "Point",
        "coordinates": [
          6.616667,
          52.25
        ]
      },
      "type": "Feature",
      "properties": {
        "hierarchy": [
          "tgn:7274034",
          "tgn:1000003",
          "tgn:7003626",
          "tgn:7016845",
          "tgn:7029392"
        ],
        "placetype": [
          "aat:300008347"
        ],
        "name:nl": "Zeldam",
        "id": 7274034
      }
    },
    {
      "geometry": {
        "type": "Point",
        "coordinates": [
          5.25,
          52.066667
        ]
      },
      "type": "Feature",
      "properties": {
        "hierarchy": [
          "tgn:7274035",
          "tgn:1000003",
          "tgn:7003627",
          "tgn:7016845",
          "tgn:7029392"
        ],
        "placetype": [
          "aat:300006075"
        ],
        "name:nl": "Zeistergrift",
        "id": 7274035
      }
    },
    {
      "geometry": {
        "type": "Point",
        "coordinates": [
          5.266667,
          52.083333
        ]
      },
      "type": "Feature",
      "properties": {
        "hierarchy": [
          "tgn:7274036",
          "tgn:1000003",
          "tgn:7003627",
          "tgn:7016845",
          "tgn:7029392"
        ],
        "placetype": [
          "aat:300008863"
        ],
        "name:nl": "Zeisterbos",
        "id": 7274036
      }
    },
    {
      "geometry": {
        "type": "Point",
        "coordinates": [
          5.816667,
          51.45
        ]
      },
      "type": "Feature",
      "properties": {
        "hierarchy": [
          "tgn:7274039",
          "tgn:1000003",
          "tgn:7003624",
          "tgn:7016845",
          "tgn:7029392"
        ],
        "placetype": [
          "aat:300000745"
        ],
        "name:nl": "Zeilberg",
        "id": 7274039
      }
    }
  ]
}
