{
  "geometry": {
    "type": "Point",
    "coordinates": [
      45.3333,
      46.5333
    ]
  },
  "type": "Feature",
  "properties": {
    "hierarchy": [
      "tgn:1137812",
      "tgn:1000004",
      "tgn:7011497",
      "tgn:7002435",
      "tgn:7029392"
    ],
    "placetype": [
      "aat:300008347"
    ],
    "id": 1137812,
    "name:xx": "Kuropatkino"
  }
}
