{
  "geometry": {
    "type": "Point",
    "coordinates": [
      -68.1167,
      45.7667
    ]
  },
  "type": "Feature",
  "properties": {
    "hierarchy": [
      "tgn:2351864",
      "tgn:2000919",
      "tgn:1000001",
      "tgn:7012149",
      "tgn:7007515",
      "tgn:7029392"
    ],
    "placetype": [
      "aat:300008347"
    ],
    "id": 2351864,
    "name:xx": "Glenwood"
  }
}
