{
  "geometry": {
    "type": "Point",
    "coordinates": [
      -109.5667,
      46.6833
    ]
  },
  "type": "Feature",
  "properties": {
    "hierarchy": [
      "tgn:2179215",
      "tgn:1000001",
      "tgn:7012149",
      "tgn:7007524",
      "tgn:7029392"
    ],
    "placetype": [
      "aat:300008706"
    ],
    "id": 2179215,
    "name:xx": "Blake Creek"
  }
}
