{
  "geometry": {
    "type": "Point",
    "coordinates": [
      -106.6333,
      32.95
    ]
  },
  "type": "Feature",
  "properties": {
    "hierarchy": [
      "tgn:2689725",
      "tgn:1000001",
      "tgn:7012149",
      "tgn:2001455",
      "tgn:7007566",
      "tgn:7029392"
    ],
    "placetype": [
      "aat:300008761"
    ],
    "id": 2689725,
    "name:xx": "Squaw Tit Canyon"
  }
}
