{
  "geometry": {
    "type": "Point",
    "coordinates": [
      -90.6167,
      29.55
    ]
  },
  "type": "Feature",
  "properties": {
    "hierarchy": [
      "tgn:2443486",
      "tgn:1000001",
      "tgn:7012149",
      "tgn:2000908",
      "tgn:7007256",
      "tgn:7029392"
    ],
    "placetype": [
      "aat:300008699"
    ],
    "id": 2443486,
    "name:xx": "La Cache, Bayou"
  }
}
