{
  "geometry": {
    "type": "Point",
    "coordinates": [
      14.75,
      8.75
    ]
  },
  "type": "Feature",
  "properties": {
    "hierarchy": [
      "tgn:1101425",
      "tgn:7001242",
      "tgn:1001455",
      "tgn:1000153",
      "tgn:7029392"
    ],
    "placetype": [
      "aat:300008189"
    ],
    "id": 1101425,
    "name:xx": "Boubandjida, Parc National de"
  }
}
