{
  "geometry": {
    "type": "Point",
    "coordinates": [
      8.4167,
      44.4833
    ]
  },
  "type": "Feature",
  "properties": {
    "hierarchy": [
      "tgn:1045390",
      "tgn:1000003",
      "tgn:7003236",
      "tgn:7003144",
      "tgn:1000080",
      "tgn:7029392"
    ],
    "placetype": [
      "aat:300008347"
    ],
    "id": 1045390,
    "name:xx": "Mioglia"
  }
}
