{
  "geometry": {
    "type": "Point",
    "coordinates": [
      -115.5167,
      33.1167
    ]
  },
  "type": "Feature",
  "properties": {
    "hierarchy": [
      "tgn:2212800",
      "tgn:1000001",
      "tgn:7012149",
      "tgn:2000182",
      "tgn:7007157",
      "tgn:7029392"
    ],
    "placetype": [
      "aat:300006075"
    ],
    "id": 2212800,
    "name:xx": "C Lateral West"
  }
}
