{
  "type": "FeatureCollection",
  "features": [
    {
      "geometry": {
        "type": "Point",
        "coordinates": [
          -74.95,
          39.5667
        ]
      },
      "type": "Feature",
      "properties": {
        "hierarchy": [
          "tgn:2539690",
          "tgn:1000001",
          "tgn:1002410",
          "tgn:7012149",
          "tgn:7007565",
          "tgn:7029392"
        ],
        "placetype": [
          "aat:300008699"
        ],
        "id": 2539690,
        "name:xx": "New Squankum Branch"
      }
    },
    {
      "geometry": {
        "type": "Point",
        "coordinates": [
          -114.0333,
          34.1167
        ]
      },
      "type": "Feature",
      "properties": {
        "hierarchy": [
          "tgn:2539692",
          "tgn:1000001",
          "tgn:7006451",
          "tgn:7012149",
          "tgn:2000104",
          "tgn:7029392"
        ],
        "placetype": [
          "aat:300000390"
        ],
        "id": 2539692,
        "name:xx": "New Standard Mine"
      }
    },
    {
      "geometry": {
        "type": "Point",
        "coordinates": [
          -112.0833,
          39.9
        ]
      },
      "type": "Feature",
      "properties": {
        "hierarchy": [
          "tgn:2539693",
          "tgn:1000001",
          "tgn:7012149",
          "tgn:2002112",
          "tgn:7007827",
          "tgn:7029392"
        ],
        "placetype": [
          "aat:300000390"
        ],
        "id": 2539693,
        "name:xx": "New State"
      }
    },
    {
      "geometry": {
        "type": "Point",
        "coordinates": [
          -95.6167,
          34.75
        ]
      },
      "type": "Feature",
      "properties": {
        "hierarchy": [
          "tgn:2539694",
          "tgn:1000001",
          "tgn:7012149",
          "tgn:2001683",
          "tgn:7007707",
          "tgn:7029392"
        ],
        "placetype": [
          "aat:300008798"
        ],
        "id": 2539694,
        "name:xx": "New State Mountain"
      }
    },
    {
      "geometry": {
        "type": "Point",
        "coordinates": [
          -67.6667,
          44.9667
        ]
      },
      "type": "Feature",
      "properties": {
        "hierarchy": [
          "tgn:2539695",
          "tgn:1000001",
          "tgn:7012149",
          "tgn:7014589",
          "tgn:7007515",
          "tgn:7029392"
        ],
        "placetype": [
          "aat:300008699"
        ],
        "id": 2539695,
        "name:xx": "New Stream"
      }
    },
    {
      "geometry": {
        "type": "Point",
        "coordinates": [
          -74.1833,
          40.9
        ]
      },
      "type": "Feature",
      "properties": {
        "hierarchy": [
          "tgn:2539696",
          "tgn:1000001",
          "tgn:1002775",
          "tgn:7012149",
          "tgn:7007565",
          "tgn:7029392"
        ],
        "placetype": [
          "aat:300006191"
        ],
        "id": 2539696,
        "name:xx": "New Street Reservoir"
      }
    },
    {
      "geometry": {
        "type": "Point",
        "coordinates": [
          -117,
          39.5
        ]
      },
      "type": "Feature",
      "properties": {
        "hierarchy": [
          "tgn:2539697",
          "tgn:1000001",
          "tgn:2001415",
          "tgn:7012149",
          "tgn:7007526",
          "tgn:7029392"
        ],
        "placetype": [
          "aat:300000390"
        ],
        "id": 2539697,
        "name:xx": "New Strike Mine"
      }
    },
    {
      "geometry": {
        "type": "Point",
        "coordinates": [
          -111.85,
          40.4
        ]
      },
      "type": "Feature",
      "properties": {
        "hierarchy": [
          "tgn:2539698",
          "tgn:1000001",
          "tgn:7012149",
          "tgn:2002125",
          "tgn:7007827",
          "tgn:7029392"
        ],
        "placetype": [
          "aat:300006075"
        ],
        "id": 2539698,
        "name:xx": "New Survey Ditch"
      }
    },
    {
      "geometry": {
        "type": "Point",
        "coordinates": [
          -94.1833,
          44.4
        ]
      },
      "type": "Feature",
      "properties": {
        "hierarchy": [
          "tgn:2539699",
          "tgn:1000001",
          "tgn:7012149",
          "tgn:2001050",
          "tgn:7007521",
          "tgn:7029392"
        ],
        "placetype": [
          "aat:300008347"
        ],
        "id": 2539699,
        "name:xx": "New Sweden"
      }
    }
  ]
}
