{
  "geometry": {
    "type": "Point",
    "coordinates": [
      -77.05,
      37.8167
    ]
  },
  "type": "Feature",
  "properties": {
    "hierarchy": [
      "tgn:2203982",
      "tgn:1000001",
      "tgn:7012149",
      "tgn:7007919",
      "tgn:7029392"
    ],
    "placetype": [
      "aat:300008699"
    ],
    "id": 2203982,
    "name:xx": "Buckyard Branch"
  }
}
