{
  "geometry": {
    "type": "Point",
    "coordinates": [
      121.6428,
      25.0018
    ]
  },
  "type": "Feature",
  "properties": {
    "hierarchy": [
      "tgn:7498612",
      "tgn:1000004",
      "tgn:1000454",
      "tgn:1000141",
      "tgn:7029392"
    ],
    "placetype": [
      "aat:300008798"
    ],
    "id": 7498612,
    "name:xx": "Fengzilin Shan"
  }
}
