{
  "geometry": {
    "type": "Point",
    "coordinates": [
      -156.05,
      19.75
    ]
  },
  "type": "Feature",
  "properties": {
    "hierarchy": [
      "tgn:2739229",
      "tgn:7023902",
      "tgn:1000001",
      "tgn:7012149",
      "tgn:7007249",
      "tgn:7029392"
    ],
    "placetype": [
      "aat:300008850"
    ],
    "id": 2739229,
    "name:xx": "Unualoha Point"
  }
}
