{
  "geometry": {
    "type": "Point",
    "coordinates": [
      -96.3667,
      32.5167
    ]
  },
  "type": "Feature",
  "properties": {
    "hierarchy": [
      "tgn:2107539",
      "tgn:1000001",
      "tgn:7012149",
      "tgn:1002535",
      "tgn:7007826",
      "tgn:7029392"
    ],
    "placetype": [
      "aat:300008347"
    ],
    "id": 2107539,
    "name:xx": "Scurry"
  }
}
