{
  "geometry": {
    "type": "Point",
    "coordinates": [
      -78.9333,
      36.45
    ]
  },
  "type": "Feature",
  "properties": {
    "hierarchy": [
      "tgn:2328789",
      "tgn:1000001",
      "tgn:7012149",
      "tgn:2001529",
      "tgn:7007709",
      "tgn:7029392"
    ],
    "placetype": [
      "aat:300008699"
    ],
    "id": 2328789,
    "name:xx": "Fishing Branch"
  }
}
