{
  "geometry": {
    "type": "Point",
    "coordinates": [
      151.1667,
      -33.8333
    ]
  },
  "type": "Feature",
  "properties": {
    "hierarchy": [
      "tgn:1097408",
      "tgn:7000490",
      "tgn:1000006",
      "tgn:7001828",
      "tgn:7029392"
    ],
    "placetype": [
      "aat:300008347"
    ],
    "id": 1097408,
    "name:xx": "Longueville"
  }
}
