{
  "type": "FeatureCollection",
  "features": [
    {
      "geometry": {
        "type": "Point",
        "coordinates": [
          12.466667,
          43.25
        ]
      },
      "type": "Feature",
      "properties": {
        "hierarchy": [
          "tgn:7037640",
          "tgn:7003170",
          "tgn:1000003",
          "tgn:7003125",
          "tgn:1000080",
          "tgn:7029392"
        ],
        "placetype": [
          "aat:300008699"
        ],
        "id": 7037640,
        "name:xx": "Valdobuccia, Rio"
      }
    },
    {
      "geometry": {
        "type": "Point",
        "coordinates": [
          13.166667,
          42.166667
        ]
      },
      "type": "Feature",
      "properties": {
        "hierarchy": [
          "tgn:7037643",
          "tgn:7003137",
          "tgn:1000003",
          "tgn:7003080",
          "tgn:1000080",
          "tgn:7029392"
        ],
        "placetype": [
          "aat:300008795"
        ],
        "id": 7037643,
        "name:xx": "Val di Varri, Monte"
      }
    },
    {
      "geometry": {
        "type": "Point",
        "coordinates": [
          10.1,
          44.383333
        ]
      },
      "type": "Feature",
      "properties": {
        "hierarchy": [
          "tgn:7037644",
          "tgn:7003131",
          "tgn:1000003",
          "tgn:7008516",
          "tgn:1000080",
          "tgn:7029392"
        ],
        "placetype": [
          "aat:300008347"
        ],
        "id": 7037644,
        "name:xx": "Valditacca"
      }
    },
    {
      "geometry": {
        "type": "Point",
        "coordinates": [
          11.1,
          44.983333
        ]
      },
      "type": "Feature",
      "properties": {
        "hierarchy": [
          "tgn:7037645",
          "tgn:7005880",
          "tgn:1000003",
          "tgn:7003237",
          "tgn:1000080",
          "tgn:7029392"
        ],
        "placetype": [
          "aat:300008347"
        ],
        "id": 7037645,
        "name:xx": "Valdirame"
      }
    },
    {
      "geometry": {
        "type": "Point",
        "coordinates": [
          11.366667,
          43.3
        ]
      },
      "type": "Feature",
      "properties": {
        "hierarchy": [
          "tgn:7037646",
          "tgn:7003168",
          "tgn:1000003",
          "tgn:7009760",
          "tgn:1000080",
          "tgn:7029392"
        ],
        "placetype": [
          "aat:300008347"
        ],
        "id": 7037646,
        "name:xx": "Val di Pugna"
      }
    },
    {
      "geometry": {
        "type": "Point",
        "coordinates": [
          10.5,
          43.416667
        ]
      },
      "type": "Feature",
      "properties": {
        "hierarchy": [
          "tgn:7037647",
          "tgn:7003166",
          "tgn:1000003",
          "tgn:7009760",
          "tgn:1000080",
          "tgn:7029392"
        ],
        "placetype": [
          "aat:300008347"
        ],
        "id": 7037647,
        "name:xx": "Val di Perga"
      }
    },
    {
      "geometry": {
        "type": "Point",
        "coordinates": [
          13.116667,
          43.3
        ]
      },
      "type": "Feature",
      "properties": {
        "hierarchy": [
          "tgn:7037648",
          "tgn:1003471",
          "tgn:1000003",
          "tgn:7003240",
          "tgn:1000080",
          "tgn:7029392"
        ],
        "placetype": [
          "aat:300008699"
        ],
        "id": 7037648,
        "name:xx": "Valdiola, Fosso"
      }
    },
    {
      "geometry": {
        "type": "Point",
        "coordinates": [
          12.104444,
          44.0625
        ]
      },
      "type": "Feature",
      "properties": {
        "hierarchy": [
          "tgn:7037649",
          "tgn:7003129",
          "tgn:1000003",
          "tgn:7008516",
          "tgn:1000080",
          "tgn:7029392"
        ],
        "placetype": [
          "aat:300008347"
        ],
        "id": 7037649,
        "name:xx": "Valdinoce"
      }
    }
  ]
}
