{
  "geometry": {
    "type": "Point",
    "coordinates": [
      -58.75,
      -34.65
    ]
  },
  "type": "Feature",
  "properties": {
    "hierarchy": [
      "tgn:1134859",
      "tgn:1001160",
      "tgn:7006477",
      "tgn:1000002",
      "tgn:7029392"
    ],
    "placetype": [
      "aat:300008706"
    ],
    "id": 1134859,
    "name:xx": "Torres, Arroyo"
  }
}
