{
  "geometry": {
    "type": "Point",
    "coordinates": [
      31.216735,
      30.640289
    ]
  },
  "type": "Feature",
  "properties": {
    "hierarchy": [
      "tgn:7533732",
      "tgn:7001242",
      "tgn:7016833",
      "tgn:7001312",
      "tgn:7029392"
    ],
    "placetype": [
      "aat:300008347"
    ],
    "name:en": "Kafr Ismā'īl",
    "id": 7533732
  }
}
