{
  "geometry": {
    "type": "Point",
    "coordinates": [
      -73.3167,
      -14.1667
    ]
  },
  "type": "Feature",
  "properties": {
    "hierarchy": [
      "tgn:1024776",
      "tgn:1000504",
      "tgn:1000002",
      "tgn:1000056",
      "tgn:7029392"
    ],
    "placetype": [
      "aat:300008347"
    ],
    "id": 1024776,
    "name:xx": "Soraya"
  }
}
