{
  "geometry": {
    "type": "Point",
    "coordinates": [
      -102.0667,
      44.6667
    ]
  },
  "type": "Feature",
  "properties": {
    "hierarchy": [
      "tgn:2445161",
      "tgn:1000001",
      "tgn:2001816",
      "tgn:7012149",
      "tgn:7007713",
      "tgn:7029392"
    ],
    "placetype": [
      "aat:300008706"
    ],
    "id": 2445161,
    "name:xx": "Lemmon Creek"
  }
}
