{
  "geometry": {
    "type": "Point",
    "coordinates": [
      -79.35,
      36.4667
    ]
  },
  "type": "Feature",
  "properties": {
    "hierarchy": [
      "tgn:2076219",
      "tgn:1000001",
      "tgn:7013557",
      "tgn:7012149",
      "tgn:7007709",
      "tgn:7029392"
    ],
    "placetype": [
      "aat:300008347"
    ],
    "id": 2076219,
    "name:xx": "Purley"
  }
}
