{
  "geometry": {
    "type": "Point",
    "coordinates": [
      -109.15,
      40.7167
    ]
  },
  "type": "Feature",
  "properties": {
    "hierarchy": [
      "tgn:2269160",
      "tgn:1000001",
      "tgn:2002105",
      "tgn:7012149",
      "tgn:7007827",
      "tgn:7029392"
    ],
    "placetype": [
      "aat:300008706"
    ],
    "id": 2269160,
    "name:xx": "Crouse Creek"
  }
}
