{
  "geometry": {
    "type": "Point",
    "coordinates": [
      -79.3833,
      41.3667
    ]
  },
  "type": "Feature",
  "properties": {
    "hierarchy": [
      "tgn:2608770",
      "tgn:1000001",
      "tgn:1002272",
      "tgn:7012149",
      "tgn:7007710",
      "tgn:7029392"
    ],
    "placetype": [
      "aat:300008699"
    ],
    "id": 2608770,
    "name:xx": "Rattlesnake Run"
  }
}
