{
  "geometry": {
    "type": "Point",
    "coordinates": [
      11.95,
      52.983333
    ]
  },
  "type": "Feature",
  "properties": {
    "hierarchy": [
      "tgn:7135882",
      "tgn:7000096",
      "tgn:1000003",
      "tgn:7000084",
      "tgn:7029392"
    ],
    "placetype": [
      "aat:300008863"
    ],
    "id": 7135882,
    "name:xx": "Mühlenholz"
  }
}
