{
  "geometry": {
    "type": "Point",
    "coordinates": [
      -82.05,
      35.8667
    ]
  },
  "type": "Feature",
  "properties": {
    "hierarchy": [
      "tgn:2654507",
      "tgn:1000001",
      "tgn:7012149",
      "tgn:2001519",
      "tgn:7007709",
      "tgn:7029392"
    ],
    "placetype": [
      "aat:300006191"
    ],
    "id": 2654507,
    "name:xx": "Shafords Lake"
  }
}
