{
  "geometry": {
    "type": "Point",
    "coordinates": [
      136.9167,
      35.3333
    ]
  },
  "type": "Feature",
  "properties": {
    "hierarchy": [
      "tgn:1079673",
      "tgn:7016579",
      "tgn:7000895",
      "tgn:1000004",
      "tgn:1000120",
      "tgn:7029392"
    ],
    "placetype": [
      "aat:300008347"
    ],
    "id": 1079673,
    "name:xx": "Ōguchi"
  }
}
