{
  "geometry": {
    "type": "Point",
    "coordinates": [
      -107.4833,
      37.6167
    ]
  },
  "type": "Feature",
  "properties": {
    "hierarchy": [
      "tgn:2204711",
      "tgn:1000001",
      "tgn:7012149",
      "tgn:2000225",
      "tgn:7007158",
      "tgn:7029392"
    ],
    "placetype": [
      "aat:300008798"
    ],
    "id": 2204711,
    "name:xx": "Buffalo Peak"
  }
}
