{
  "geometry": {
    "type": "Point",
    "coordinates": [
      127.9167,
      35.6833
    ]
  },
  "type": "Feature",
  "properties": {
    "hierarchy": [
      "tgn:1140673",
      "tgn:1000004",
      "tgn:1001371",
      "tgn:7000299",
      "tgn:7029392"
    ],
    "placetype": [
      "aat:300008347"
    ],
    "id": 1140673,
    "name:xx": "Kŏch'ang"
  }
}
