{
  "type": "FeatureCollection",
  "features": [
    {
      "geometry": {
        "type": "Point",
        "coordinates": [
          -83.9167,
          34.8833
        ]
      },
      "type": "Feature",
      "properties": {
        "hierarchy": [
          "tgn:2629920",
          "tgn:1000001",
          "tgn:7012149",
          "tgn:2000435",
          "tgn:7007248",
          "tgn:7029392"
        ],
        "placetype": [
          "aat:300266640"
        ],
        "id": 2629920,
        "name:xx": "Ross Ridge"
      }
    },
    {
      "geometry": {
        "type": "Point",
        "coordinates": [
          -82.0833,
          36.5
        ]
      },
      "type": "Feature",
      "properties": {
        "hierarchy": [
          "tgn:2629921",
          "tgn:1000001",
          "tgn:7012149",
          "tgn:2001918",
          "tgn:7007825",
          "tgn:7029392"
        ],
        "placetype": [
          "aat:300266640"
        ],
        "id": 2629921,
        "name:xx": "Ross Ridge"
      }
    },
    {
      "geometry": {
        "type": "Point",
        "coordinates": [
          -94.05,
          30.1167
        ]
      },
      "type": "Feature",
      "properties": {
        "hierarchy": [
          "tgn:2629922",
          "tgn:1000001",
          "tgn:7012149",
          "tgn:2002052",
          "tgn:7007826",
          "tgn:7029392"
        ],
        "placetype": [
          "aat:300266640"
        ],
        "id": 2629922,
        "name:xx": "Ross Ridge"
      }
    },
    {
      "geometry": {
        "type": "Point",
        "coordinates": [
          -109.9,
          42.5333
        ]
      },
      "type": "Feature",
      "properties": {
        "hierarchy": [
          "tgn:2629923",
          "tgn:1000001",
          "tgn:7012149",
          "tgn:2002382",
          "tgn:7007923",
          "tgn:7029392"
        ],
        "placetype": [
          "aat:300266640"
        ],
        "id": 2629923,
        "name:xx": "Ross Ridge"
      }
    },
    {
      "geometry": {
        "type": "Point",
        "coordinates": [
          -85.7,
          40.7833
        ]
      },
      "type": "Feature",
      "properties": {
        "hierarchy": [
          "tgn:2629924",
          "tgn:1000001",
          "tgn:7012149",
          "tgn:1002978",
          "tgn:7007252",
          "tgn:7029392"
        ],
        "placetype": [
          "aat:300008699"
        ],
        "id": 2629924,
        "name:xx": "Ross Run"
      }
    },
    {
      "geometry": {
        "type": "Point",
        "coordinates": [
          -83.9167,
          38.8333
        ]
      },
      "type": "Feature",
      "properties": {
        "hierarchy": [
          "tgn:2629925",
          "tgn:1000001",
          "tgn:1002210",
          "tgn:7012149",
          "tgn:7007706",
          "tgn:7029392"
        ],
        "placetype": [
          "aat:300008699"
        ],
        "id": 2629925,
        "name:xx": "Ross Run"
      }
    },
    {
      "geometry": {
        "type": "Point",
        "coordinates": [
          -81.8333,
          39.0167
        ]
      },
      "type": "Feature",
      "properties": {
        "hierarchy": [
          "tgn:2629926",
          "tgn:1000001",
          "tgn:7012149",
          "tgn:2001616",
          "tgn:7007706",
          "tgn:7029392"
        ],
        "placetype": [
          "aat:300008699"
        ],
        "id": 2629926,
        "name:xx": "Ross Run"
      }
    },
    {
      "geometry": {
        "type": "Point",
        "coordinates": [
          -80.95,
          40.1667
        ]
      },
      "type": "Feature",
      "properties": {
        "hierarchy": [
          "tgn:2629927",
          "tgn:1000001",
          "tgn:7012149",
          "tgn:1002459",
          "tgn:7007706",
          "tgn:7029392"
        ],
        "placetype": [
          "aat:300008699"
        ],
        "id": 2629927,
        "name:xx": "Ross Run"
      }
    },
    {
      "geometry": {
        "type": "Point",
        "coordinates": [
          -84.45,
          39.15
        ]
      },
      "type": "Feature",
      "properties": {
        "hierarchy": [
          "tgn:2629928",
          "tgn:1000001",
          "tgn:7012149",
          "tgn:1002441",
          "tgn:7007706",
          "tgn:7029392"
        ],
        "placetype": [
          "aat:300008699"
        ],
        "id": 2629928,
        "name:xx": "Ross Run"
      }
    },
    {
      "geometry": {
        "type": "Point",
        "coordinates": [
          -81.7333,
          39.2167
        ]
      },
      "type": "Feature",
      "properties": {
        "hierarchy": [
          "tgn:2629929",
          "tgn:2001610",
          "tgn:1000001",
          "tgn:7012149",
          "tgn:7007706",
          "tgn:7029392"
        ],
        "placetype": [
          "aat:300008699"
        ],
        "id": 2629929,
        "name:xx": "Ross Run"
      }
    }
  ]
}
