{
  "geometry": {
    "type": "Point",
    "coordinates": [
      -83.3833,
      42.3833
    ]
  },
  "type": "Feature",
  "properties": {
    "hierarchy": [
      "tgn:2570798",
      "tgn:1000001",
      "tgn:7012149",
      "tgn:1003005",
      "tgn:7007520",
      "tgn:7029392"
    ],
    "placetype": [
      "aat:300006075"
    ],
    "id": 2570798,
    "name:xx": "Patter Drain"
  }
}
