{
  "geometry": {
    "type": "Point",
    "coordinates": [
      -121.2167,
      40.4167
    ]
  },
  "type": "Feature",
  "properties": {
    "hierarchy": [
      "tgn:2287773",
      "tgn:1000001",
      "tgn:7012149",
      "tgn:7007157",
      "tgn:2000187",
      "tgn:7029392"
    ],
    "placetype": [
      "aat:300008706"
    ],
    "id": 2287773,
    "name:xx": "Dillon Creek"
  }
}
