{
  "type": "FeatureCollection",
  "features": [
    {
      "geometry": {
        "type": "Point",
        "coordinates": [
          -91.95,
          34.9333
        ]
      },
      "type": "Feature",
      "properties": {
        "hierarchy": [
          "tgn:2228940",
          "tgn:1000001",
          "tgn:7016172",
          "tgn:7012149",
          "tgn:2000147",
          "tgn:7029392"
        ],
        "placetype": [
          "aat:300008347"
        ],
        "id": 2228940,
        "name:xx": "Cedar Hills Estates"
      }
    },
    {
      "geometry": {
        "type": "Point",
        "coordinates": [
          -78.6167,
          35.85
        ]
      },
      "type": "Feature",
      "properties": {
        "hierarchy": [
          "tgn:2228941",
          "tgn:1000001",
          "tgn:7012149",
          "tgn:2001548",
          "tgn:7007709",
          "tgn:7029392"
        ],
        "placetype": [
          "aat:300008347"
        ],
        "id": 2228941,
        "name:xx": "Cedar Hills Estates"
      }
    },
    {
      "geometry": {
        "type": "Point",
        "coordinates": [
          -92.6,
          35.8167
        ]
      },
      "type": "Feature",
      "properties": {
        "hierarchy": [
          "tgn:2228943",
          "tgn:1000001",
          "tgn:7016172",
          "tgn:7012149",
          "tgn:2000169",
          "tgn:7029392"
        ],
        "placetype": [
          "aat:300008761"
        ],
        "id": 2228943,
        "name:xx": "Cedar Hollow"
      }
    },
    {
      "geometry": {
        "type": "Point",
        "coordinates": [
          -93.8333,
          35.9667
        ]
      },
      "type": "Feature",
      "properties": {
        "hierarchy": [
          "tgn:2228944",
          "tgn:1000001",
          "tgn:7016172",
          "tgn:7012149",
          "tgn:2000148",
          "tgn:7029392"
        ],
        "placetype": [
          "aat:300008761"
        ],
        "id": 2228944,
        "name:xx": "Cedar Hollow"
      }
    },
    {
      "geometry": {
        "type": "Point",
        "coordinates": [
          -92.7,
          36.3667
        ]
      },
      "type": "Feature",
      "properties": {
        "hierarchy": [
          "tgn:2228945",
          "tgn:1000001",
          "tgn:7016172",
          "tgn:7012149",
          "tgn:2000149",
          "tgn:7029392"
        ],
        "placetype": [
          "aat:300008761"
        ],
        "id": 2228945,
        "name:xx": "Cedar Hollow"
      }
    },
    {
      "geometry": {
        "type": "Point",
        "coordinates": [
          -93.15,
          35.6333
        ]
      },
      "type": "Feature",
      "properties": {
        "hierarchy": [
          "tgn:2228946",
          "tgn:1000001",
          "tgn:7016172",
          "tgn:7012149",
          "tgn:2000162",
          "tgn:7029392"
        ],
        "placetype": [
          "aat:300008761"
        ],
        "id": 2228946,
        "name:xx": "Cedar Hollow"
      }
    },
    {
      "geometry": {
        "type": "Point",
        "coordinates": [
          -111.75,
          42.5333
        ]
      },
      "type": "Feature",
      "properties": {
        "hierarchy": [
          "tgn:2228947",
          "tgn:1000001",
          "tgn:2000466",
          "tgn:7012149",
          "tgn:7007250",
          "tgn:7029392"
        ],
        "placetype": [
          "aat:300008761"
        ],
        "id": 2228947,
        "name:xx": "Cedar Hollow"
      }
    },
    {
      "geometry": {
        "type": "Point",
        "coordinates": [
          -111.5167,
          44.1167
        ]
      },
      "type": "Feature",
      "properties": {
        "hierarchy": [
          "tgn:2228948",
          "tgn:1000001",
          "tgn:7012149",
          "tgn:2000473",
          "tgn:7007250",
          "tgn:7029392"
        ],
        "placetype": [
          "aat:300008761"
        ],
        "id": 2228948,
        "name:xx": "Cedar Hollow"
      }
    },
    {
      "geometry": {
        "type": "Point",
        "coordinates": [
          -86.9,
          40.45
        ]
      },
      "type": "Feature",
      "properties": {
        "hierarchy": [
          "tgn:2228949",
          "tgn:1000001",
          "tgn:7012149",
          "tgn:1002946",
          "tgn:7007252",
          "tgn:7029392"
        ],
        "placetype": [
          "aat:300008761"
        ],
        "id": 2228949,
        "name:xx": "Cedar Hollow"
      }
    }
  ]
}
