{
  "geometry": {
    "type": "Point",
    "coordinates": [
      31.07,
      29.343
    ]
  },
  "type": "Feature",
  "properties": {
    "hierarchy": [
      "tgn:1095348",
      "tgn:7001242",
      "tgn:7016833",
      "tgn:1001418",
      "tgn:7029392"
    ],
    "placetype": [
      "aat:300007783"
    ],
    "name:en": "Maḩaţţat ar Ru'ūs",
    "id": 1095348
  }
}
