{
  "geometry": {
    "type": "Point",
    "coordinates": [
      25.4333,
      48.9667
    ]
  },
  "type": "Feature",
  "properties": {
    "hierarchy": [
      "tgn:7026337",
      "tgn:1000003",
      "tgn:7011664",
      "tgn:7006660",
      "tgn:7029392"
    ],
    "placetype": [
      "aat:300008347"
    ],
    "id": 7026337,
    "name:xx": "Pomortsy"
  }
}
