{
  "geometry": {
    "type": "Point",
    "coordinates": [
      -87.0333,
      34.9167
    ]
  },
  "type": "Feature",
  "properties": {
    "hierarchy": [
      "tgn:2684002",
      "tgn:7002659",
      "tgn:1000001",
      "tgn:7012149",
      "tgn:2000041",
      "tgn:7029392"
    ],
    "placetype": [
      "aat:300008746"
    ],
    "id": 2684002,
    "name:xx": "Spencer Cave"
  }
}
