{
  "geometry": {
    "type": "Point",
    "coordinates": [
      122.7667,
      14.25
    ]
  },
  "type": "Feature",
  "properties": {
    "hierarchy": [
      "tgn:1084544",
      "tgn:1000004",
      "tgn:1001174",
      "tgn:1000135",
      "tgn:7029392"
    ],
    "placetype": [
      "aat:300008347"
    ],
    "id": 1084544,
    "name:xx": "Paracale"
  }
}
