{
  "geometry": {
    "type": "Point",
    "coordinates": [
      -116.5333,
      33.0333
    ]
  },
  "type": "Feature",
  "properties": {
    "hierarchy": [
      "tgn:2248057",
      "tgn:1000001",
      "tgn:7012149",
      "tgn:7007157",
      "tgn:1002858",
      "tgn:7029392"
    ],
    "placetype": [
      "aat:300000390"
    ],
    "id": 2248057,
    "name:xx": "Cold Beef Mine"
  }
}
