{
  "geometry": {
    "type": "Point",
    "coordinates": [
      -85.3167,
      37.4167
    ]
  },
  "type": "Feature",
  "properties": {
    "hierarchy": [
      "tgn:2563310",
      "tgn:1000001",
      "tgn:7012149",
      "tgn:2000844",
      "tgn:7007255",
      "tgn:7029392"
    ],
    "placetype": [
      "aat:300008706"
    ],
    "id": 2563310,
    "name:xx": "Owl Creek"
  }
}
