{
  "geometry": {
    "type": "Point",
    "coordinates": [
      -77.9167,
      35.4667
    ]
  },
  "type": "Feature",
  "properties": {
    "hierarchy": [
      "tgn:2466652",
      "tgn:1000001",
      "tgn:7012149",
      "tgn:2001552",
      "tgn:7007709",
      "tgn:7029392"
    ],
    "placetype": [
      "aat:300008699"
    ],
    "id": 2466652,
    "name:xx": "Long Branch"
  }
}
