{
  "geometry": {
    "type": "Point",
    "coordinates": [
      -83.0167,
      37.3167
    ]
  },
  "type": "Feature",
  "properties": {
    "hierarchy": [
      "tgn:2038085",
      "tgn:1000001",
      "tgn:7012149",
      "tgn:2000805",
      "tgn:7007255",
      "tgn:7029392"
    ],
    "placetype": [
      "aat:300008347"
    ],
    "id": 2038085,
    "name:xx": "Carrie"
  }
}
