{
  "geometry": {
    "type": "Point",
    "coordinates": [
      112.6333,
      30.5167
    ]
  },
  "type": "Feature",
  "properties": {
    "hierarchy": [
      "tgn:1072721",
      "tgn:1000004",
      "tgn:7002078",
      "tgn:1000111",
      "tgn:7029392"
    ],
    "placetype": [
      "aat:300008347"
    ],
    "id": 1072721,
    "name:xx": "Xiabanghu"
  }
}
