{
  "geometry": {
    "type": "Point",
    "coordinates": [
      -82.5167,
      35.75
    ]
  },
  "type": "Feature",
  "properties": {
    "hierarchy": [
      "tgn:2347197",
      "tgn:1000001",
      "tgn:2001473",
      "tgn:7012149",
      "tgn:7007709",
      "tgn:7029392"
    ],
    "placetype": [
      "aat:300008699"
    ],
    "id": 2347197,
    "name:xx": "Gentry Branch"
  }
}
