{
  "geometry": {
    "type": "Point",
    "coordinates": [
      -97.4667,
      45.6667
    ]
  },
  "type": "Feature",
  "properties": {
    "hierarchy": [
      "tgn:2471493",
      "tgn:1000001",
      "tgn:2001815",
      "tgn:7012149",
      "tgn:7007713",
      "tgn:7029392"
    ],
    "placetype": [
      "aat:300008680"
    ],
    "id": 2471493,
    "name:xx": "Lost Lake"
  }
}
