{
  "geometry": {
    "type": "Point",
    "coordinates": [
      -93.1833,
      29.8167
    ]
  },
  "type": "Feature",
  "properties": {
    "hierarchy": [
      "tgn:2681620",
      "tgn:1000001",
      "tgn:7020676",
      "tgn:7012149",
      "tgn:7007256",
      "tgn:7029392"
    ],
    "placetype": [
      "aat:300008699"
    ],
    "id": 2681620,
    "name:xx": "South Prong of Grand Bayou"
  }
}
