{
  "geometry": {
    "type": "Point",
    "coordinates": [
      -5.95,
      43.35
    ]
  },
  "type": "Feature",
  "properties": {
    "hierarchy": [
      "tgn:7297629",
      "tgn:7008911",
      "tgn:1000003",
      "tgn:7002763",
      "tgn:1000095",
      "tgn:7029392"
    ],
    "placetype": [
      "aat:300008347"
    ],
    "id": 7297629,
    "name:xx": "Soto de Rey"
  }
}
