{
  "type": "FeatureCollection",
  "features": [
    {
      "geometry": {
        "type": "Point",
        "coordinates": [
          10.8,
          48.6
        ]
      },
      "type": "Feature",
      "properties": {
        "hierarchy": [
          "tgn:1040530",
          "tgn:7003669",
          "tgn:1000003",
          "tgn:7000084",
          "tgn:7029392"
        ],
        "placetype": [
          "aat:300008347"
        ],
        "id": 1040530,
        "name:xx": "Nordendorf"
      }
    },
    {
      "geometry": {
        "type": "Point",
        "coordinates": [
          8.483333,
          53.5
        ]
      },
      "type": "Feature",
      "properties": {
        "hierarchy": [
          "tgn:1040531",
          "tgn:1000003",
          "tgn:7003676",
          "tgn:7000084",
          "tgn:7029392"
        ],
        "placetype": [
          "aat:300008347"
        ],
        "id": 1040531,
        "name:xx": "Nordenham"
      }
    },
    {
      "geometry": {
        "type": "Point",
        "coordinates": [
          9.25,
          54.35
        ]
      },
      "type": "Feature",
      "properties": {
        "hierarchy": [
          "tgn:1040533",
          "tgn:1000003",
          "tgn:7003688",
          "tgn:7000084",
          "tgn:7029392"
        ],
        "placetype": [
          "aat:300008347"
        ],
        "id": 1040533,
        "name:xx": "Norderstapel"
      }
    },
    {
      "geometry": {
        "type": "Point",
        "coordinates": [
          10.016667,
          53.7
        ]
      },
      "type": "Feature",
      "properties": {
        "hierarchy": [
          "tgn:1040534",
          "tgn:1000003",
          "tgn:7003688",
          "tgn:7000084",
          "tgn:7029392"
        ],
        "placetype": [
          "aat:300008347",
          "aat:300008389"
        ],
        "id": 1040534,
        "name:xx": "Norderstedt"
      }
    },
    {
      "geometry": {
        "type": "Point",
        "coordinates": [
          11.2167,
          50.3667
        ]
      },
      "type": "Feature",
      "properties": {
        "hierarchy": [
          "tgn:1040535",
          "tgn:7003669",
          "tgn:1000003",
          "tgn:7000084",
          "tgn:7029392"
        ],
        "placetype": [
          "aat:300008347"
        ],
        "id": 1040535,
        "name:xx": "Nordhalben"
      }
    },
    {
      "geometry": {
        "type": "Point",
        "coordinates": [
          10.1833,
          50.4667
        ]
      },
      "type": "Feature",
      "properties": {
        "hierarchy": [
          "tgn:1040536",
          "tgn:7003669",
          "tgn:1000003",
          "tgn:7000084",
          "tgn:7029392"
        ],
        "placetype": [
          "aat:300008347"
        ],
        "id": 1040536,
        "name:xx": "Nordheim von der Rhön"
      }
    },
    {
      "geometry": {
        "type": "Point",
        "coordinates": [
          7.533333,
          51.733333
        ]
      },
      "type": "Feature",
      "properties": {
        "hierarchy": [
          "tgn:1040538",
          "tgn:1000003",
          "tgn:7003677",
          "tgn:7000084",
          "tgn:7029392"
        ],
        "placetype": [
          "aat:300008347"
        ],
        "id": 1040538,
        "name:xx": "Nordkirchen"
      }
    }
  ]
}
