{
  "geometry": {
    "type": "Point",
    "coordinates": [
      19.4167,
      54.1667
    ]
  },
  "type": "Feature",
  "properties": {
    "hierarchy": [
      "tgn:7007656",
      "tgn:1000003",
      "tgn:7024118",
      "tgn:7006366",
      "tgn:7029392"
    ],
    "placetype": [
      "aat:300008347",
      "aat:300008389",
      "aat:300387223",
      "aat:300387302"
    ],
    "id": 7007656,
    "name:xx": "ElblaÌœg"
  }
}
