{
  "geometry": {
    "type": "Point",
    "coordinates": [
      -145.1667,
      61.65
    ]
  },
  "type": "Feature",
  "properties": {
    "hierarchy": [
      "tgn:2006437",
      "tgn:7006450",
      "tgn:1000001",
      "tgn:7012149",
      "tgn:2000086",
      "tgn:7029392"
    ],
    "placetype": [
      "aat:300008347"
    ],
    "id": 2006437,
    "name:xx": "Tonsina"
  }
}
