{
  "type": "FeatureCollection",
  "features": [
    {
      "geometry": {
        "type": "Point",
        "coordinates": [
          -107.25,
          31.95
        ]
      },
      "type": "Feature",
      "properties": {
        "hierarchy": [
          "tgn:2176230",
          "tgn:1000001",
          "tgn:2001435",
          "tgn:7012149",
          "tgn:7007566",
          "tgn:7029392"
        ],
        "placetype": [
          "aat:300008798"
        ],
        "id": 2176230,
        "name:xx": "Black Hills"
      }
    },
    {
      "geometry": {
        "type": "Point",
        "coordinates": [
          -121.2167,
          42.5667
        ]
      },
      "type": "Feature",
      "properties": {
        "hierarchy": [
          "tgn:2176231",
          "tgn:1000001",
          "tgn:7012149",
          "tgn:2001714",
          "tgn:7007708",
          "tgn:7029392"
        ],
        "placetype": [
          "aat:300008798"
        ],
        "id": 2176231,
        "name:xx": "Black Hills"
      }
    },
    {
      "geometry": {
        "type": "Point",
        "coordinates": [
          -117.8167,
          42.6333
        ]
      },
      "type": "Feature",
      "properties": {
        "hierarchy": [
          "tgn:2176232",
          "tgn:1000001",
          "tgn:7012149",
          "tgn:2001718",
          "tgn:7007708",
          "tgn:7029392"
        ],
        "placetype": [
          "aat:300008798"
        ],
        "id": 2176232,
        "name:xx": "Black Hills"
      }
    },
    {
      "geometry": {
        "type": "Point",
        "coordinates": [
          -120.6667,
          43.1667
        ]
      },
      "type": "Feature",
      "properties": {
        "hierarchy": [
          "tgn:2176233",
          "tgn:1000001",
          "tgn:7012149",
          "tgn:2001715",
          "tgn:7007708",
          "tgn:7029392"
        ],
        "placetype": [
          "aat:300386831"
        ],
        "id": 2176233,
        "name:xx": "Black Hills"
      }
    },
    {
      "geometry": {
        "type": "Point",
        "coordinates": [
          -96.55,
          32.1
        ]
      },
      "type": "Feature",
      "properties": {
        "hierarchy": [
          "tgn:2176234",
          "tgn:1000001",
          "tgn:7012149",
          "tgn:1002709",
          "tgn:7007826",
          "tgn:7029392"
        ],
        "placetype": [
          "aat:300008798"
        ],
        "id": 2176234,
        "name:xx": "Black Hills"
      }
    },
    {
      "geometry": {
        "type": "Point",
        "coordinates": [
          -104.2333,
          30
        ]
      },
      "type": "Feature",
      "properties": {
        "hierarchy": [
          "tgn:2176235",
          "tgn:1000001",
          "tgn:7012149",
          "tgn:2002057",
          "tgn:7007826",
          "tgn:7029392"
        ],
        "placetype": [
          "aat:300008798"
        ],
        "id": 2176235,
        "name:xx": "Black Hills"
      }
    },
    {
      "geometry": {
        "type": "Point",
        "coordinates": [
          -102.9833,
          29.8167
        ]
      },
      "type": "Feature",
      "properties": {
        "hierarchy": [
          "tgn:2176236",
          "tgn:1000001",
          "tgn:2001945",
          "tgn:7012149",
          "tgn:7007826",
          "tgn:7029392"
        ],
        "placetype": [
          "aat:300008798"
        ],
        "id": 2176236,
        "name:xx": "Black Hills"
      }
    },
    {
      "geometry": {
        "type": "Point",
        "coordinates": [
          -113.5333,
          41.8167
        ]
      },
      "type": "Feature",
      "properties": {
        "hierarchy": [
          "tgn:2176237",
          "tgn:1000001",
          "tgn:2002102",
          "tgn:7012149",
          "tgn:7007827",
          "tgn:7029392"
        ],
        "placetype": [
          "aat:300008798"
        ],
        "id": 2176237,
        "name:xx": "Black Hills"
      }
    },
    {
      "geometry": {
        "type": "Point",
        "coordinates": [
          -113.75,
          37.5
        ]
      },
      "type": "Feature",
      "properties": {
        "hierarchy": [
          "tgn:2176238",
          "tgn:1000001",
          "tgn:7012149",
          "tgn:2002127",
          "tgn:7007827",
          "tgn:7029392"
        ],
        "placetype": [
          "aat:300008798"
        ],
        "id": 2176238,
        "name:xx": "Black Hills"
      }
    },
    {
      "geometry": {
        "type": "Point",
        "coordinates": [
          -113.3167,
          38.85
        ]
      },
      "type": "Feature",
      "properties": {
        "hierarchy": [
          "tgn:2176239",
          "tgn:1000001",
          "tgn:7012149",
          "tgn:2002114",
          "tgn:7007827",
          "tgn:7029392"
        ],
        "placetype": [
          "aat:300386831"
        ],
        "id": 2176239,
        "name:xx": "Black Hills"
      }
    }
  ]
}
