{
  "geometry": {
    "type": "Point",
    "coordinates": [
      -89.3833,
      39.65
    ]
  },
  "type": "Feature",
  "properties": {
    "hierarchy": [
      "tgn:2027652",
      "tgn:1000001",
      "tgn:1002268",
      "tgn:7012149",
      "tgn:7007251",
      "tgn:7029392"
    ],
    "placetype": [
      "aat:300008347"
    ],
    "id": 2027652,
    "name:xx": "Edinburg"
  }
}
