{
  "geometry": {
    "type": "Point",
    "coordinates": [
      -156.7167,
      65.3667
    ]
  },
  "type": "Feature",
  "properties": {
    "hierarchy": [
      "tgn:2380293",
      "tgn:7006450",
      "tgn:1000001",
      "tgn:7012149",
      "tgn:2000089",
      "tgn:7029392"
    ],
    "placetype": [
      "aat:300008680"
    ],
    "id": 2380293,
    "name:xx": "Hatseegatloth Lake"
  }
}
