{
  "geometry": {
    "type": "Point",
    "coordinates": [
      -77.15,
      40.75
    ]
  },
  "type": "Feature",
  "properties": {
    "hierarchy": [
      "tgn:2717878",
      "tgn:1000001",
      "tgn:7012149",
      "tgn:1002900",
      "tgn:7007710",
      "tgn:7029392"
    ],
    "placetype": [
      "aat:300266640"
    ],
    "id": 2717878,
    "name:xx": "Thomas Ridge"
  }
}
