{
  "geometry": {
    "type": "Point",
    "coordinates": [
      -94.95,
      35.9833
    ]
  },
  "type": "Feature",
  "properties": {
    "hierarchy": [
      "tgn:2293530",
      "tgn:1000001",
      "tgn:2001633",
      "tgn:7012149",
      "tgn:7007707",
      "tgn:7029392"
    ],
    "placetype": [
      "aat:300008706"
    ],
    "id": 2293530,
    "name:xx": "Double Spring Creek"
  }
}
