{
  "geometry": {
    "type": "Point",
    "coordinates": [
      8.2167,
      46.05
    ]
  },
  "type": "Feature",
  "properties": {
    "hierarchy": [
      "tgn:1044081",
      "tgn:1003478",
      "tgn:1000003",
      "tgn:7003120",
      "tgn:1000080",
      "tgn:7029392"
    ],
    "placetype": [
      "aat:300008347"
    ],
    "id": 1044081,
    "name:xx": "Castiglione d'Ossola"
  }
}
