{
  "geometry": {
    "type": "Point",
    "coordinates": [
      105.3833,
      29.15
    ]
  },
  "type": "Feature",
  "properties": {
    "hierarchy": [
      "tgn:1068102",
      "tgn:1000004",
      "tgn:7002087",
      "tgn:1000111",
      "tgn:7029392"
    ],
    "placetype": [
      "aat:300008347"
    ],
    "id": 1068102,
    "name:xx": "Fuji"
  }
}
