{
  "geometry": {
    "type": "Point",
    "coordinates": [
      -70.95,
      -33.05
    ]
  },
  "type": "Feature",
  "properties": {
    "hierarchy": [
      "tgn:7289415",
      "tgn:1001708",
      "tgn:1000049",
      "tgn:1000002",
      "tgn:7029392"
    ],
    "placetype": [
      "aat:300008347"
    ],
    "id": 7289415,
    "name:xx": "La Finca"
  }
}
