{
  "geometry": {
    "type": "Point",
    "coordinates": [
      -80.0167,
      35.3167
    ]
  },
  "type": "Feature",
  "properties": {
    "hierarchy": [
      "tgn:2741337",
      "tgn:1000001",
      "tgn:7012149",
      "tgn:2001520",
      "tgn:7007709",
      "tgn:7029392"
    ],
    "placetype": [
      "aat:300008699"
    ],
    "id": 2741337,
    "name:xx": "Upper Wood Run"
  }
}
