{
  "geometry": {
    "type": "Point",
    "coordinates": [
      33.55,
      -21.3333
    ]
  },
  "type": "Feature",
  "properties": {
    "hierarchy": [
      "tgn:1091507",
      "tgn:7001242",
      "tgn:1000891",
      "tgn:1000180",
      "tgn:7029392"
    ],
    "placetype": [
      "aat:300008347"
    ],
    "id": 1091507,
    "name:xx": "Chirape"
  }
}
