{
  "geometry": {
    "type": "Point",
    "coordinates": [
      -115.8167,
      40.7167
    ]
  },
  "type": "Feature",
  "properties": {
    "hierarchy": [
      "tgn:2678290",
      "tgn:1000001",
      "tgn:2001411",
      "tgn:7012149",
      "tgn:7007526",
      "tgn:7029392"
    ],
    "placetype": [
      "aat:300008761"
    ],
    "id": 2678290,
    "name:xx": "South Fork Canon"
  }
}
