{
  "geometry": {
    "type": "Point",
    "coordinates": [
      -85.2167,
      38.8167
    ]
  },
  "type": "Feature",
  "properties": {
    "hierarchy": [
      "tgn:2294237",
      "tgn:1000001",
      "tgn:7012149",
      "tgn:1002515",
      "tgn:7007252",
      "tgn:7029392"
    ],
    "placetype": [
      "aat:300266640"
    ],
    "id": 2294237,
    "name:xx": "Dow Ridge"
  }
}
