{
  "geometry": {
    "type": "Point",
    "coordinates": [
      4.3667,
      49.5167
    ]
  },
  "type": "Feature",
  "properties": {
    "hierarchy": [
      "tgn:7009464",
      "tgn:1000003",
      "tgn:7002880",
      "tgn:1000070",
      "tgn:7029392"
    ],
    "placetype": [
      "aat:300008347",
      "aat:300387330",
      "aat:300008375"
    ],
    "id": 7009464,
    "name:xx": "Rethel"
  }
}
