{
  "geometry": {
    "type": "Point",
    "coordinates": [
      -107.5333,
      46.2667
    ]
  },
  "type": "Feature",
  "properties": {
    "hierarchy": [
      "tgn:2483011",
      "tgn:1000001",
      "tgn:7012149",
      "tgn:2001311",
      "tgn:7007524",
      "tgn:7029392"
    ],
    "placetype": [
      "aat:300006191"
    ],
    "id": 2483011,
    "name:xx": "Larsens Reservoir"
  }
}
