{
  "geometry": {
    "type": "Point",
    "coordinates": [
      -74.7333,
      40.9667
    ]
  },
  "type": "Feature",
  "properties": {
    "hierarchy": [
      "tgn:2270878",
      "tgn:1000001",
      "tgn:1002934",
      "tgn:7012149",
      "tgn:7007565",
      "tgn:7029392"
    ],
    "placetype": [
      "aat:300008680"
    ],
    "id": 2270878,
    "name:xx": "Cub Lake"
  }
}
