{
  "geometry": {
    "type": "Point",
    "coordinates": [
      -76.6833,
      41.3667
    ]
  },
  "type": "Feature",
  "properties": {
    "hierarchy": [
      "tgn:2529518",
      "tgn:1000001",
      "tgn:7012149",
      "tgn:1002927",
      "tgn:7007710",
      "tgn:7029392"
    ],
    "placetype": [
      "aat:300008680"
    ],
    "id": 2529518,
    "name:xx": "Mud Lake"
  }
}
