{
  "type": "FeatureCollection",
  "features": [
    {
      "geometry": {
        "type": "Point",
        "coordinates": [
          -86.4833,
          37.2833
        ]
      },
      "type": "Feature",
      "properties": {
        "hierarchy": [
          "tgn:2486720",
          "tgn:1000001",
          "tgn:2000775",
          "tgn:7012149",
          "tgn:7007255",
          "tgn:7029392"
        ],
        "placetype": [
          "aat:300008347"
        ],
        "id": 2486720,
        "name:xx": "Lee"
      }
    },
    {
      "geometry": {
        "type": "Point",
        "coordinates": [
          -86.0833,
          42.45
        ]
      },
      "type": "Feature",
      "properties": {
        "hierarchy": [
          "tgn:2486721",
          "tgn:1002140",
          "tgn:1000001",
          "tgn:7012149",
          "tgn:7007520",
          "tgn:7029392"
        ],
        "placetype": [
          "aat:300008347"
        ],
        "id": 2486721,
        "name:xx": "Lee"
      }
    },
    {
      "geometry": {
        "type": "Point",
        "coordinates": [
          -73.4833,
          42.95
        ]
      },
      "type": "Feature",
      "properties": {
        "hierarchy": [
          "tgn:2486722",
          "tgn:1000001",
          "tgn:7012149",
          "tgn:1002993",
          "tgn:7007568",
          "tgn:7029392"
        ],
        "placetype": [
          "aat:300008347"
        ],
        "id": 2486722,
        "name:xx": "Lee"
      }
    },
    {
      "geometry": {
        "type": "Point",
        "coordinates": [
          -124.0667,
          43.1667
        ]
      },
      "type": "Feature",
      "properties": {
        "hierarchy": [
          "tgn:2486723",
          "tgn:1000001",
          "tgn:2001702",
          "tgn:7012149",
          "tgn:7007708",
          "tgn:7029392"
        ],
        "placetype": [
          "aat:300008347"
        ],
        "id": 2486723,
        "name:xx": "Lee"
      }
    },
    {
      "geometry": {
        "type": "Point",
        "coordinates": [
          -85.35,
          36.35
        ]
      },
      "type": "Feature",
      "properties": {
        "hierarchy": [
          "tgn:2486724",
          "tgn:1000001",
          "tgn:7012149",
          "tgn:2001903",
          "tgn:7007825",
          "tgn:7029392"
        ],
        "placetype": [
          "aat:300008347"
        ],
        "id": 2486724,
        "name:xx": "Lee"
      }
    },
    {
      "geometry": {
        "type": "Point",
        "coordinates": [
          -118.55,
          46.35
        ]
      },
      "type": "Feature",
      "properties": {
        "hierarchy": [
          "tgn:2486725",
          "tgn:1000001",
          "tgn:7012149",
          "tgn:2002251",
          "tgn:7007920",
          "tgn:7029392"
        ],
        "placetype": [
          "aat:300008347"
        ],
        "id": 2486725,
        "name:xx": "Lee"
      }
    },
    {
      "geometry": {
        "type": "Point",
        "coordinates": [
          -88.7167,
          34.2333
        ]
      },
      "type": "Feature",
      "properties": {
        "hierarchy": [
          "tgn:2486726",
          "tgn:1000001",
          "tgn:7012149",
          "tgn:2001126",
          "tgn:7007522",
          "tgn:7029392"
        ],
        "placetype": [
          "aat:300008347"
        ],
        "id": 2486726,
        "name:xx": "Lee Acres"
      }
    },
    {
      "geometry": {
        "type": "Point",
        "coordinates": [
          -106.6333,
          35.1333
        ]
      },
      "type": "Feature",
      "properties": {
        "hierarchy": [
          "tgn:2486727",
          "tgn:1000001",
          "tgn:2001428",
          "tgn:7012149",
          "tgn:7007566",
          "tgn:7029392"
        ],
        "placetype": [
          "aat:300008347"
        ],
        "id": 2486727,
        "name:xx": "Lee Acres"
      }
    },
    {
      "geometry": {
        "type": "Point",
        "coordinates": [
          -108.0333,
          36.6833
        ]
      },
      "type": "Feature",
      "properties": {
        "hierarchy": [
          "tgn:2486728",
          "tgn:1000001",
          "tgn:7012149",
          "tgn:2001452",
          "tgn:7007566",
          "tgn:7029392"
        ],
        "placetype": [
          "aat:300008347"
        ],
        "id": 2486728,
        "name:xx": "Lee Acres"
      }
    },
    {
      "geometry": {
        "type": "Point",
        "coordinates": [
          -79.4667,
          36.0833
        ]
      },
      "type": "Feature",
      "properties": {
        "hierarchy": [
          "tgn:2486729",
          "tgn:2001463",
          "tgn:1000001",
          "tgn:7012149",
          "tgn:7007709",
          "tgn:7029392"
        ],
        "placetype": [
          "aat:300008347"
        ],
        "id": 2486729,
        "name:xx": "Lee Acres"
      }
    }
  ]
}
