{
  "geometry": {
    "type": "Point",
    "coordinates": [
      -75.0667,
      38.5833
    ]
  },
  "type": "Feature",
  "properties": {
    "hierarchy": [
      "tgn:2196297",
      "tgn:1002933",
      "tgn:1000001",
      "tgn:7012149",
      "tgn:7007239",
      "tgn:7029392"
    ],
    "placetype": [
      "aat:300008905"
    ],
    "id": 2196297,
    "name:xx": "Broken Marshes"
  }
}
