{
  "geometry": {
    "type": "Point",
    "coordinates": [
      -88.7167,
      48.0167
    ]
  },
  "type": "Feature",
  "properties": {
    "hierarchy": [
      "tgn:2413282",
      "tgn:1000001",
      "tgn:7012149",
      "tgn:2000969",
      "tgn:7007520",
      "tgn:7029392"
    ],
    "placetype": [
      "aat:300008680"
    ],
    "id": 2413282,
    "name:xx": "Intermediate Lake"
  }
}
