{
  "geometry": {
    "type": "Point",
    "coordinates": [
      -116.3833,
      43.6167
    ]
  },
  "type": "Feature",
  "properties": {
    "hierarchy": [
      "tgn:2406992",
      "tgn:2000452",
      "tgn:1000001",
      "tgn:7012149",
      "tgn:7007250",
      "tgn:7029392"
    ],
    "placetype": [
      "aat:300006075"
    ],
    "id": 2406992,
    "name:xx": "Hunter Lateral"
  }
}
