{
  "geometry": {
    "type": "Point",
    "coordinates": [
      -75.0833,
      44.3667
    ]
  },
  "type": "Feature",
  "properties": {
    "hierarchy": [
      "tgn:2282925",
      "tgn:1000001",
      "tgn:7012149",
      "tgn:7016021",
      "tgn:7007568",
      "tgn:7029392"
    ],
    "placetype": [
      "aat:300008863"
    ],
    "id": 2282925,
    "name:xx": "Degrasse State Forest"
  }
}
