{
  "geometry": {
    "type": "Point",
    "coordinates": [
      -82.8333,
      35.3667
    ]
  },
  "type": "Feature",
  "properties": {
    "hierarchy": [
      "tgn:2424013",
      "tgn:1000001",
      "tgn:7012149",
      "tgn:2001503",
      "tgn:7007709",
      "tgn:7029392"
    ],
    "placetype": [
      "aat:300008761"
    ],
    "id": 2424013,
    "name:xx": "Johns Cove"
  }
}
