{
  "geometry": {
    "type": "Point",
    "coordinates": [
      -74.6833,
      41.0333
    ]
  },
  "type": "Feature",
  "properties": {
    "hierarchy": [
      "tgn:2698287",
      "tgn:1000001",
      "tgn:1002934",
      "tgn:7012149",
      "tgn:7007565",
      "tgn:7029392"
    ],
    "placetype": [
      "aat:300008680"
    ],
    "id": 2698287,
    "name:xx": "Straders Pond"
  }
}
