{
  "geometry": {
    "type": "Point",
    "coordinates": [
      -109.15,
      33.8833
    ]
  },
  "type": "Feature",
  "properties": {
    "hierarchy": [
      "tgn:2552664",
      "tgn:2000090",
      "tgn:1000001",
      "tgn:7006451",
      "tgn:7012149",
      "tgn:7029392"
    ],
    "placetype": [
      "aat:300008706"
    ],
    "id": 2552664,
    "name:xx": "Nutrioso Creek"
  }
}
