{
  "geometry": {
    "type": "Point",
    "coordinates": [
      -88.6333,
      42.9667
    ]
  },
  "type": "Feature",
  "properties": {
    "hierarchy": [
      "tgn:2122402",
      "tgn:1000001",
      "tgn:7012149",
      "tgn:1002522",
      "tgn:7007922",
      "tgn:7029392"
    ],
    "placetype": [
      "aat:300008347",
      "aat:300387210"
    ],
    "id": 2122402,
    "name:xx": "Slabtown"
  }
}
