{
  "geometry": {
    "type": "Point",
    "coordinates": [
      79.4502,
      24.8882
    ]
  },
  "type": "Feature",
  "properties": {
    "hierarchy": [
      "tgn:7564118",
      "tgn:1000004",
      "tgn:7000198",
      "tgn:1001894",
      "tgn:7029392"
    ],
    "placetype": [
      "aat:300008865"
    ],
    "name:en": "Panautha Protected Forest",
    "id": 7564118
  }
}
