{
  "geometry": {
    "type": "Point",
    "coordinates": [
      -80.55,
      39.9167
    ]
  },
  "type": "Feature",
  "properties": {
    "hierarchy": [
      "tgn:2235859",
      "tgn:1000001",
      "tgn:7012149",
      "tgn:2002276",
      "tgn:7013961",
      "tgn:7029392"
    ],
    "placetype": [
      "aat:300266640"
    ],
    "id": 2235859,
    "name:xx": "Chestnut Ridge"
  }
}
