{
  "geometry": {
    "type": "Point",
    "coordinates": [
      -101.2833,
      33.1167
    ]
  },
  "type": "Feature",
  "properties": {
    "hierarchy": [
      "tgn:2736896",
      "tgn:1000001",
      "tgn:7012149",
      "tgn:2001989",
      "tgn:7007826",
      "tgn:7029392"
    ],
    "placetype": [
      "aat:300008798"
    ],
    "id": 2736896,
    "name:xx": "Two Bush Knob"
  }
}
