{
  "type": "FeatureCollection",
  "features": [
    {
      "geometry": {
        "type": "Point",
        "coordinates": [
          -82.7167,
          37.1667
        ]
      },
      "type": "Feature",
      "properties": {
        "hierarchy": [
          "tgn:2163650",
          "tgn:1000001",
          "tgn:7012149",
          "tgn:2000812",
          "tgn:7007255",
          "tgn:7029392"
        ],
        "placetype": [
          "aat:300008761"
        ],
        "id": 2163650,
        "name:xx": "Bentley Hollow"
      }
    },
    {
      "geometry": {
        "type": "Point",
        "coordinates": [
          -73.2833,
          42.6167
        ]
      },
      "type": "Feature",
      "properties": {
        "hierarchy": [
          "tgn:2163651",
          "tgn:7013388",
          "tgn:1000001",
          "tgn:7012149",
          "tgn:7007517",
          "tgn:7029392"
        ],
        "placetype": [
          "aat:300008761"
        ],
        "id": 2163651,
        "name:xx": "Bentley Hollow"
      }
    },
    {
      "geometry": {
        "type": "Point",
        "coordinates": [
          -78,
          41.5333
        ]
      },
      "type": "Feature",
      "properties": {
        "hierarchy": [
          "tgn:2163652",
          "tgn:1000001",
          "tgn:7012149",
          "tgn:1002800",
          "tgn:7007710",
          "tgn:7029392"
        ],
        "placetype": [
          "aat:300008761"
        ],
        "id": 2163652,
        "name:xx": "Bentley Hollow"
      }
    },
    {
      "geometry": {
        "type": "Point",
        "coordinates": [
          -82.6667,
          36.9333
        ]
      },
      "type": "Feature",
      "properties": {
        "hierarchy": [
          "tgn:2163653",
          "tgn:1000001",
          "tgn:7012149",
          "tgn:2002195",
          "tgn:7007919",
          "tgn:7029392"
        ],
        "placetype": [
          "aat:300008761"
        ],
        "id": 2163653,
        "name:xx": "Bentley Hollow"
      }
    },
    {
      "geometry": {
        "type": "Point",
        "coordinates": [
          -147.6833,
          64.8333
        ]
      },
      "type": "Feature",
      "properties": {
        "hierarchy": [
          "tgn:2163654",
          "tgn:7006450",
          "tgn:1000001",
          "tgn:7019674",
          "tgn:7012149",
          "tgn:7029392"
        ],
        "placetype": [
          "aat:300008791"
        ],
        "id": 2163654,
        "name:xx": "Bentley Island"
      }
    },
    {
      "geometry": {
        "type": "Point",
        "coordinates": [
          -81.6,
          36.15
        ]
      },
      "type": "Feature",
      "properties": {
        "hierarchy": [
          "tgn:2163655",
          "tgn:1000001",
          "tgn:7012149",
          "tgn:2001551",
          "tgn:7007709",
          "tgn:7029392"
        ],
        "placetype": [
          "aat:300008798"
        ],
        "id": 2163655,
        "name:xx": "Bentley Knob"
      }
    },
    {
      "geometry": {
        "type": "Point",
        "coordinates": [
          -87.05,
          33.65
        ]
      },
      "type": "Feature",
      "properties": {
        "hierarchy": [
          "tgn:2163656",
          "tgn:7002659",
          "tgn:1000001",
          "tgn:7012149",
          "tgn:2000036",
          "tgn:7029392"
        ],
        "placetype": [
          "aat:300006191"
        ],
        "id": 2163656,
        "name:xx": "Bentley Lake"
      }
    },
    {
      "geometry": {
        "type": "Point",
        "coordinates": [
          -85.2667,
          33.9333
        ]
      },
      "type": "Feature",
      "properties": {
        "hierarchy": [
          "tgn:2163657",
          "tgn:1000001",
          "tgn:7012149",
          "tgn:2000406",
          "tgn:7007248",
          "tgn:7029392"
        ],
        "placetype": [
          "aat:300006191"
        ],
        "id": 2163657,
        "name:xx": "Bentley Lake"
      }
    },
    {
      "geometry": {
        "type": "Point",
        "coordinates": [
          -84.15,
          31.0667
        ]
      },
      "type": "Feature",
      "properties": {
        "hierarchy": [
          "tgn:2163658",
          "tgn:1000001",
          "tgn:7012149",
          "tgn:2000392",
          "tgn:7007248",
          "tgn:7029392"
        ],
        "placetype": [
          "aat:300006191"
        ],
        "id": 2163658,
        "name:xx": "Bentley Lake"
      }
    },
    {
      "geometry": {
        "type": "Point",
        "coordinates": [
          -84.6,
          31.7167
        ]
      },
      "type": "Feature",
      "properties": {
        "hierarchy": [
          "tgn:2163659",
          "tgn:1000001",
          "tgn:7012149",
          "tgn:2000411",
          "tgn:7007248",
          "tgn:7029392"
        ],
        "placetype": [
          "aat:300006191"
        ],
        "id": 2163659,
        "name:xx": "Bentley Lake"
      }
    }
  ]
}
