{
  "type": "FeatureCollection",
  "features": [
    {
      "geometry": {
        "type": "Point",
        "coordinates": [
          7.65,
          48.9667
        ]
      },
      "type": "Feature",
      "properties": {
        "hierarchy": [
          "tgn:1034664",
          "tgn:7002870",
          "tgn:1000003",
          "tgn:1000070",
          "tgn:7029392"
        ],
        "placetype": [
          "aat:300008347"
        ],
        "id": 1034664,
        "name:xx": "Niederbronn-Les-Bains"
      }
    },
    {
      "geometry": {
        "type": "Point",
        "coordinates": [
          2.8333,
          50.7
        ]
      },
      "type": "Feature",
      "properties": {
        "hierarchy": [
          "tgn:1034665",
          "tgn:1000003",
          "tgn:7001097",
          "tgn:1000070",
          "tgn:7029392"
        ],
        "placetype": [
          "aat:300008347"
        ],
        "id": 1034665,
        "name:xx": "Nieppe"
      }
    },
    {
      "geometry": {
        "type": "Point",
        "coordinates": [
          3.8667,
          47.6833
        ]
      },
      "type": "Feature",
      "properties": {
        "hierarchy": [
          "tgn:1034667",
          "tgn:1000003",
          "tgn:7002875",
          "tgn:1000070",
          "tgn:7029392"
        ],
        "placetype": [
          "aat:300008347"
        ],
        "id": 1034667,
        "name:xx": "Nitry"
      }
    },
    {
      "geometry": {
        "type": "Point",
        "coordinates": [
          2.15,
          49.4667
        ]
      },
      "type": "Feature",
      "properties": {
        "hierarchy": [
          "tgn:1034668",
          "tgn:1000003",
          "tgn:7002890",
          "tgn:1000070",
          "tgn:7029392"
        ],
        "placetype": [
          "aat:300008347"
        ],
        "id": 1034668,
        "name:xx": "Nivillers"
      }
    },
    {
      "geometry": {
        "type": "Point",
        "coordinates": [
          4.0667,
          49.5833
        ]
      },
      "type": "Feature",
      "properties": {
        "hierarchy": [
          "tgn:1034669",
          "tgn:1000003",
          "tgn:7002890",
          "tgn:1000070",
          "tgn:7029392"
        ],
        "placetype": [
          "aat:300008347"
        ],
        "id": 1034669,
        "name:xx": "Nizy-le-Comte"
      }
    }
  ]
}
