{
  "geometry": {
    "type": "Point",
    "coordinates": [
      53.1833,
      50.8833
    ]
  },
  "type": "Feature",
  "properties": {
    "hierarchy": [
      "tgn:1137141",
      "tgn:1000004",
      "tgn:7011457",
      "tgn:7014786",
      "tgn:7029392"
    ],
    "placetype": [
      "aat:300008347"
    ],
    "id": 1137141,
    "name:xx": "Aksu"
  }
}
