{
  "geometry": {
    "type": "Point",
    "coordinates": [
      -76.4833,
      37.5833
    ]
  },
  "type": "Feature",
  "properties": {
    "hierarchy": [
      "tgn:2768611",
      "tgn:1000001",
      "tgn:7012149",
      "tgn:1002667",
      "tgn:7007919",
      "tgn:7029392"
    ],
    "placetype": [
      "aat:300008706"
    ],
    "id": 2768611,
    "name:xx": "Whiting Creek"
  }
}
