{
  "geometry": {
    "type": "Point",
    "coordinates": [
      -120.1333,
      38.0667
    ]
  },
  "type": "Feature",
  "properties": {
    "hierarchy": [
      "tgn:2390130",
      "tgn:1000001",
      "tgn:7012149",
      "tgn:7007157",
      "tgn:1002957",
      "tgn:7029392"
    ],
    "placetype": [
      "aat:300008347"
    ],
    "id": 2390130,
    "name:xx": "High Sierra Park"
  }
}
