{
  "geometry": {
    "type": "Point",
    "coordinates": [
      120.4766,
      22.6662
    ]
  },
  "type": "Feature",
  "properties": {
    "hierarchy": [
      "tgn:7499636",
      "tgn:1000004",
      "tgn:7492971",
      "tgn:1000141",
      "tgn:7029392"
    ],
    "placetype": [
      "aat:300006495"
    ],
    "id": 7499636,
    "name:xx": "Datong Guoxiao"
  }
}
