{
  "type": "FeatureCollection",
  "features": [
    {
      "geometry": {
        "type": "Point",
        "coordinates": [
          -6.6,
          57.483333
        ]
      },
      "type": "Feature",
      "properties": {
        "hierarchy": [
          "tgn:7465550",
          "tgn:7002444",
          "tgn:1000003",
          "tgn:7008082",
          "tgn:7008591",
          "tgn:7029392"
        ],
        "placetype": [
          "aat:300008699"
        ],
        "name:en": "Bay River",
        "id": 7465550
      }
    },
    {
      "geometry": {
        "type": "Point",
        "coordinates": [
          -0.466667,
          51.1
        ]
      },
      "type": "Feature",
      "properties": {
        "hierarchy": [
          "tgn:7465551",
          "tgn:7002445",
          "tgn:1000003",
          "tgn:7008175",
          "tgn:7008591",
          "tgn:7029392"
        ],
        "placetype": [
          "aat:300007783"
        ],
        "name:en": "Baynards Station",
        "id": 7465551
      }
    },
    {
      "geometry": {
        "type": "Point",
        "coordinates": [
          1.066667,
          52.116667
        ]
      },
      "type": "Feature",
      "properties": {
        "hierarchy": [
          "tgn:7465552",
          "tgn:7002445",
          "tgn:1000003",
          "tgn:7008185",
          "tgn:7008591",
          "tgn:7029392"
        ],
        "placetype": [
          "aat:300008347"
        ],
        "name:en": "Baylham",
        "id": 7465552
      }
    },
    {
      "geometry": {
        "type": "Point",
        "coordinates": [
          -2.766667,
          53.966667
        ]
      },
      "type": "Feature",
      "properties": {
        "hierarchy": [
          "tgn:7465553",
          "tgn:7002445",
          "tgn:1000003",
          "tgn:7008154",
          "tgn:7008591",
          "tgn:7029392"
        ],
        "placetype": [
          "aat:300007783"
        ],
        "name:en": "Bay Horse Station",
        "id": 7465553
      }
    },
    {
      "geometry": {
        "type": "Point",
        "coordinates": [
          0.35,
          51.1
        ]
      },
      "type": "Feature",
      "properties": {
        "hierarchy": [
          "tgn:7465554",
          "tgn:7002445",
          "tgn:1000003",
          "tgn:7008153",
          "tgn:7008591",
          "tgn:7029392"
        ],
        "placetype": [
          "aat:300387502"
        ],
        "name:en": "Bayham Abbey",
        "id": 7465554
      }
    },
    {
      "geometry": {
        "type": "Point",
        "coordinates": [
          -4,
          57.733333
        ]
      },
      "type": "Feature",
      "properties": {
        "hierarchy": [
          "tgn:7465556",
          "tgn:7002444",
          "tgn:1000003",
          "tgn:7008082",
          "tgn:7008591",
          "tgn:7029392"
        ],
        "placetype": [
          "aat:300004792"
        ],
        "name:en": "Bayfield House",
        "id": 7465556
      }
    },
    {
      "geometry": {
        "type": "Point",
        "coordinates": [
          -1.6,
          51.483333
        ]
      },
      "type": "Feature",
      "properties": {
        "hierarchy": [
          "tgn:7465557",
          "tgn:7002445",
          "tgn:1000003",
          "tgn:7008180",
          "tgn:7008591",
          "tgn:7029392"
        ],
        "placetype": [
          "aat:300008347"
        ],
        "name:en": "Baydon",
        "id": 7465557
      }
    },
    {
      "geometry": {
        "type": "Point",
        "coordinates": [
          -3.083333,
          54.133333
        ]
      },
      "type": "Feature",
      "properties": {
        "hierarchy": [
          "tgn:7465558",
          "tgn:7002445",
          "tgn:1000003",
          "tgn:7008117",
          "tgn:7008591",
          "tgn:7029392"
        ],
        "placetype": [
          "aat:300008347"
        ],
        "name:en": "Baycliff",
        "id": 7465558
      }
    }
  ]
}
