{
  "geometry": {
    "type": "Point",
    "coordinates": [
      19.1167,
      50.2667
    ]
  },
  "type": "Feature",
  "properties": {
    "hierarchy": [
      "tgn:1049475",
      "tgn:1000003",
      "tgn:7024125",
      "tgn:7006366",
      "tgn:7029392"
    ],
    "placetype": [
      "aat:300008347",
      "aat:300008389",
      "aat:300387305",
      "aat:300387302"
    ],
    "id": 1049475,
    "name:xx": "Sosnowiec"
  }
}
