{
  "geometry": {
    "type": "Point",
    "coordinates": [
      -72.25,
      42.4333
    ]
  },
  "type": "Feature",
  "properties": {
    "hierarchy": [
      "tgn:2446038",
      "tgn:1000001",
      "tgn:7012149",
      "tgn:1003038",
      "tgn:7007517",
      "tgn:7029392"
    ],
    "placetype": [
      "aat:300008791"
    ],
    "id": 2446038,
    "name:xx": "Leveau Island"
  }
}
