{
  "geometry": {
    "type": "Point",
    "coordinates": [
      77.78795,
      30.437283
    ]
  },
  "type": "Feature",
  "properties": {
    "hierarchy": [
      "tgn:7591251",
      "tgn:1000004",
      "tgn:7000198",
      "tgn:7031786",
      "tgn:7029392"
    ],
    "placetype": [
      "aat:300008347"
    ],
    "name:en": "Lachhmīpur",
    "id": 7591251
  }
}
