{
  "geometry": {
    "type": "Point",
    "coordinates": [
      -83.5833,
      34.5833
    ]
  },
  "type": "Feature",
  "properties": {
    "hierarchy": [
      "tgn:2568138",
      "tgn:1000001",
      "tgn:7012149",
      "tgn:2000359",
      "tgn:7007248",
      "tgn:7029392"
    ],
    "placetype": [
      "aat:300008347"
    ],
    "id": 2568138,
    "name:xx": "Pardue Mill"
  }
}
