{
  "type": "FeatureCollection",
  "features": [
    {
      "geometry": {
        "type": "Point",
        "coordinates": [
          -120.9833,
          45.6333
        ]
      },
      "type": "Feature",
      "properties": {
        "hierarchy": [
          "tgn:2085256",
          "tgn:1000001",
          "tgn:7012149",
          "tgn:1002990",
          "tgn:7007708",
          "tgn:7029392"
        ],
        "placetype": [
          "aat:300387016"
        ],
        "id": 2085256,
        "name:xx": "Oregon Trunk Junction"
      }
    },
    {
      "geometry": {
        "type": "Point",
        "coordinates": [
          -122.9,
          45.5167
        ]
      },
      "type": "Feature",
      "properties": {
        "hierarchy": [
          "tgn:2085257",
          "tgn:1000001",
          "tgn:7012149",
          "tgn:1002994",
          "tgn:7007708",
          "tgn:7029392"
        ],
        "placetype": [
          "aat:300008347"
        ],
        "id": 2085257,
        "name:xx": "Orenco"
      }
    },
    {
      "geometry": {
        "type": "Point",
        "coordinates": [
          -123.95,
          45.15
        ]
      },
      "type": "Feature",
      "properties": {
        "hierarchy": [
          "tgn:2085258",
          "tgn:1000001",
          "tgn:7012149",
          "tgn:1002943",
          "tgn:7007708",
          "tgn:7029392"
        ],
        "placetype": [
          "aat:300008347",
          "aat:300387210"
        ],
        "id": 2085258,
        "name:xx": "Oretown"
      }
    },
    {
      "geometry": {
        "type": "Point",
        "coordinates": [
          -122.35,
          45.4667
        ]
      },
      "type": "Feature",
      "properties": {
        "hierarchy": [
          "tgn:2085259",
          "tgn:1000001",
          "tgn:7012149",
          "tgn:1002699",
          "tgn:7007708",
          "tgn:7029392"
        ],
        "placetype": [
          "aat:300008347"
        ],
        "id": 2085259,
        "name:xx": "Orient"
      }
    }
  ]
}
