{
  "geometry": {
    "type": "Point",
    "coordinates": [
      -84.9333,
      36.5833
    ]
  },
  "type": "Feature",
  "properties": {
    "hierarchy": [
      "tgn:7022897",
      "tgn:1000001",
      "tgn:7012149",
      "tgn:7007825",
      "tgn:7029392"
    ],
    "placetype": [
      "aat:300008707"
    ],
    "id": 7022897,
    "name:xx": "Rotten Fork Wolf River"
  }
}
