{
  "geometry": {
    "type": "Point",
    "coordinates": [
      -104.6167,
      37.1167
    ]
  },
  "type": "Feature",
  "properties": {
    "hierarchy": [
      "tgn:2478795",
      "tgn:1000001",
      "tgn:7012149",
      "tgn:2000227",
      "tgn:7007158",
      "tgn:7029392"
    ],
    "placetype": [
      "aat:300006191"
    ],
    "id": 2478795,
    "name:xx": "Madrid Reservoir"
  }
}
