{
  "geometry": {
    "type": "Point",
    "coordinates": [
      -107.5667,
      40.0167
    ]
  },
  "type": "Feature",
  "properties": {
    "hierarchy": [
      "tgn:2226785",
      "tgn:1000001",
      "tgn:7012149",
      "tgn:7007158",
      "tgn:2000243",
      "tgn:7029392"
    ],
    "placetype": [
      "aat:300008706"
    ],
    "id": 2226785,
    "name:xx": "Cattle Creek"
  }
}
