{
  "geometry": {
    "type": "Point",
    "coordinates": [
      -112.6167,
      34.5833
    ]
  },
  "type": "Feature",
  "properties": {
    "hierarchy": [
      "tgn:2606883",
      "tgn:1000001",
      "tgn:7006451",
      "tgn:7012149",
      "tgn:2000103",
      "tgn:7029392"
    ],
    "placetype": [
      "aat:300008697"
    ],
    "id": 2606883,
    "name:xx": "Ramsgate Spring"
  }
}
