{
  "geometry": {
    "type": "Point",
    "coordinates": [
      13.75,
      52.25
    ]
  },
  "type": "Feature",
  "properties": {
    "hierarchy": [
      "tgn:7197568",
      "tgn:7000096",
      "tgn:1000003",
      "tgn:7000084",
      "tgn:7029392"
    ],
    "placetype": [
      "aat:300008680"
    ],
    "id": 7197568,
    "name:xx": "Dolgen See"
  }
}
