{
  "geometry": {
    "type": "Point",
    "coordinates": [
      177.4667,
      -17.6167
    ]
  },
  "type": "Feature",
  "properties": {
    "hierarchy": [
      "tgn:1098693",
      "tgn:1000950",
      "tgn:7000493",
      "tgn:1000006",
      "tgn:7029392"
    ],
    "placetype": [
      "aat:300008347",
      "aat:300008375"
    ],
    "id": 1098693,
    "name:xx": "Lautoka"
  }
}
