{
  "geometry": {
    "type": "Point",
    "coordinates": [
      -105.9667,
      42.4833
    ]
  },
  "type": "Feature",
  "properties": {
    "hierarchy": [
      "tgn:2272256",
      "tgn:1000001",
      "tgn:2002369",
      "tgn:7012149",
      "tgn:7007923",
      "tgn:7029392"
    ],
    "placetype": [
      "aat:300008706"
    ],
    "id": 2272256,
    "name:xx": "Curry Creek"
  }
}
