{
  "geometry": {
    "type": "Point",
    "coordinates": [
      75.632978,
      26.9237
    ]
  },
  "type": "Feature",
  "properties": {
    "hierarchy": [
      "tgn:7560124",
      "tgn:1000004",
      "tgn:7000198",
      "tgn:7016788",
      "tgn:7029392"
    ],
    "placetype": [
      "aat:300008347"
    ],
    "name:en": "Sinwār",
    "id": 7560124
  }
}
