{
  "geometry": {
    "type": "Point",
    "coordinates": [
      -87.25,
      34.8167
    ]
  },
  "type": "Feature",
  "properties": {
    "hierarchy": [
      "tgn:2563427",
      "tgn:7002659",
      "tgn:1000001",
      "tgn:7012149",
      "tgn:2000038",
      "tgn:7029392"
    ],
    "placetype": [
      "aat:300008761"
    ],
    "id": 2563427,
    "name:xx": "Owl Hollow"
  }
}
