{
  "geometry": {
    "type": "Point",
    "coordinates": [
      -89.2667,
      35.7667
    ]
  },
  "type": "Feature",
  "properties": {
    "hierarchy": [
      "tgn:2552044",
      "tgn:1000001",
      "tgn:7012149",
      "tgn:2001853",
      "tgn:7007825",
      "tgn:7029392"
    ],
    "placetype": [
      "aat:300008791"
    ],
    "id": 2552044,
    "name:xx": "Number Nine Island"
  }
}
