{
  "type": "FeatureCollection",
  "features": [
    {
      "geometry": {
        "type": "Point",
        "coordinates": [
          5.303692,
          50.585515
        ]
      },
      "type": "Feature",
      "properties": {
        "hierarchy": [
          "tgn:7248720",
          "tgn:7003460",
          "tgn:1000003",
          "tgn:1000063",
          "tgn:4012014",
          "tgn:7029392"
        ],
        "placetype": [
          "aat:300008347"
        ],
        "id": 7248720,
        "name:xx": "Bodegnée"
      }
    },
    {
      "geometry": {
        "type": "Point",
        "coordinates": [
          5.7,
          49.85
        ]
      },
      "type": "Feature",
      "properties": {
        "hierarchy": [
          "tgn:7248721",
          "tgn:7003465",
          "tgn:1000003",
          "tgn:1000063",
          "tgn:4012014",
          "tgn:7029392"
        ],
        "placetype": [
          "aat:300008347"
        ],
        "id": 7248721,
        "name:xx": "Bodange"
      }
    },
    {
      "geometry": {
        "type": "Point",
        "coordinates": [
          5.666667,
          50.133333
        ]
      },
      "type": "Feature",
      "properties": {
        "hierarchy": [
          "tgn:7248722",
          "tgn:7003465",
          "tgn:1000003",
          "tgn:1000063",
          "tgn:4012014",
          "tgn:7029392"
        ],
        "placetype": [
          "aat:300008347"
        ],
        "id": 7248722,
        "name:xx": "Bodaimont"
      }
    },
    {
      "geometry": {
        "type": "Point",
        "coordinates": [
          5,
          50.366667
        ]
      },
      "type": "Feature",
      "properties": {
        "hierarchy": [
          "tgn:7248723",
          "tgn:7003466",
          "tgn:1000003",
          "tgn:1000063",
          "tgn:4012014",
          "tgn:7029392"
        ],
        "placetype": [
          "aat:300000206"
        ],
        "id": 7248723,
        "name:xx": "Cense du Bocq"
      }
    },
    {
      "geometry": {
        "type": "Point",
        "coordinates": [
          4.4,
          51.066667
        ]
      },
      "type": "Feature",
      "properties": {
        "hierarchy": [
          "tgn:7248725",
          "tgn:7003456",
          "tgn:1000003",
          "tgn:1000063",
          "tgn:7018236",
          "tgn:7029392"
        ],
        "placetype": [
          "aat:300008347"
        ],
        "id": 7248725,
        "name:xx": "Bocht"
      }
    },
    {
      "geometry": {
        "type": "Point",
        "coordinates": [
          3.580473,
          50.543521
        ]
      },
      "type": "Feature",
      "properties": {
        "hierarchy": [
          "tgn:7248728",
          "tgn:7007877",
          "tgn:1000003",
          "tgn:1000063",
          "tgn:4012014",
          "tgn:7029392"
        ],
        "placetype": [
          "aat:300008347"
        ],
        "id": 7248728,
        "name:xx": "Bocarmé"
      }
    },
    {
      "geometry": {
        "type": "Point",
        "coordinates": [
          4.266667,
          50.733333
        ]
      },
      "type": "Feature",
      "properties": {
        "hierarchy": [
          "tgn:7248729",
          "tgn:7018239",
          "tgn:1000003",
          "tgn:1000063",
          "tgn:7018236",
          "tgn:7029392"
        ],
        "placetype": [
          "aat:300000206"
        ],
        "id": 7248729,
        "name:xx": "Hof ten Bloten"
      }
    }
  ]
}
