{
  "geometry": {
    "type": "Point",
    "coordinates": [
      -87.9667,
      47.4667
    ]
  },
  "type": "Feature",
  "properties": {
    "hierarchy": [
      "tgn:2275467",
      "tgn:1000001",
      "tgn:7012149",
      "tgn:2000969",
      "tgn:7007520",
      "tgn:7029392"
    ],
    "placetype": [
      "aat:300008850"
    ],
    "id": 2275467,
    "name:xx": "Dans Point"
  }
}
