{
  "geometry": {
    "type": "Point",
    "coordinates": [
      -80.5167,
      38.15
    ]
  },
  "type": "Feature",
  "properties": {
    "hierarchy": [
      "tgn:2169738",
      "tgn:1000001",
      "tgn:7012149",
      "tgn:7013961",
      "tgn:7029392"
    ],
    "placetype": [
      "aat:300008798"
    ],
    "id": 2169738,
    "name:xx": "Big Mountain"
  }
}
