{
  "geometry": {
    "type": "Point",
    "coordinates": [
      -103.25,
      20.183333
    ]
  },
  "type": "Feature",
  "properties": {
    "hierarchy": [
      "tgn:7397549",
      "tgn:7005586",
      "tgn:1000001",
      "tgn:7005560",
      "tgn:7029392"
    ],
    "placetype": [
      "aat:300008347"
    ],
    "id": 7397549,
    "name:xx": "San Nicolás"
  }
}
