{
  "geometry": {
    "type": "Point",
    "coordinates": [
      -108.6333,
      38.55
    ]
  },
  "type": "Feature",
  "properties": {
    "hierarchy": [
      "tgn:2546140",
      "tgn:1000001",
      "tgn:7012149",
      "tgn:2000230",
      "tgn:7007158",
      "tgn:7029392"
    ],
    "placetype": [
      "aat:300008706"
    ],
    "id": 2546140,
    "name:xx": "North Fork Escalante Creek"
  }
}
