{
  "geometry": {
    "type": "Point",
    "coordinates": [
      -85.0667,
      38.6667
    ]
  },
  "type": "Feature",
  "properties": {
    "hierarchy": [
      "tgn:2038626",
      "tgn:1000001",
      "tgn:1002237",
      "tgn:7012149",
      "tgn:7007255",
      "tgn:7029392"
    ],
    "placetype": [
      "aat:300008347",
      "aat:300387210"
    ],
    "id": 2038626,
    "name:xx": "Easterday"
  }
}
