{
  "geometry": {
    "type": "Point",
    "coordinates": [
      -97.3833,
      29.8167
    ]
  },
  "type": "Feature",
  "properties": {
    "hierarchy": [
      "tgn:2103736",
      "tgn:1000001",
      "tgn:7012149",
      "tgn:1002220",
      "tgn:7007826",
      "tgn:7029392"
    ],
    "placetype": [
      "aat:300008347",
      "aat:300387210"
    ],
    "id": 2103736,
    "name:xx": "Delhi"
  }
}
