{
  "type": "FeatureCollection",
  "features": [
    {
      "geometry": {
        "type": "Point",
        "coordinates": [
          -105.0333,
          40.4333
        ]
      },
      "type": "Feature",
      "properties": {
        "hierarchy": [
          "tgn:2190920",
          "tgn:1000001",
          "tgn:7012149",
          "tgn:2000226",
          "tgn:7007158",
          "tgn:7029392"
        ],
        "placetype": [
          "aat:300006191"
        ],
        "id": 2190920,
        "name:xx": "Boyd Lake"
      }
    },
    {
      "geometry": {
        "type": "Point",
        "coordinates": [
          -81.55,
          29.1333
        ]
      },
      "type": "Feature",
      "properties": {
        "hierarchy": [
          "tgn:2190921",
          "tgn:1000001",
          "tgn:7012149",
          "tgn:1002567",
          "tgn:7007240",
          "tgn:7029392"
        ],
        "placetype": [
          "aat:300008680"
        ],
        "id": 2190921,
        "name:xx": "Boyd Lake"
      }
    },
    {
      "geometry": {
        "type": "Point",
        "coordinates": [
          -81.9333,
          33.1833
        ]
      },
      "type": "Feature",
      "properties": {
        "hierarchy": [
          "tgn:2190922",
          "tgn:1000001",
          "tgn:2000308",
          "tgn:7012149",
          "tgn:7007248",
          "tgn:7029392"
        ],
        "placetype": [
          "aat:300006191"
        ],
        "id": 2190922,
        "name:xx": "Boyd Lake"
      }
    },
    {
      "geometry": {
        "type": "Point",
        "coordinates": [
          -84.4167,
          31.75
        ]
      },
      "type": "Feature",
      "properties": {
        "hierarchy": [
          "tgn:2190923",
          "tgn:1000001",
          "tgn:7012149",
          "tgn:2000426",
          "tgn:7007248",
          "tgn:7029392"
        ],
        "placetype": [
          "aat:300006191"
        ],
        "id": 2190923,
        "name:xx": "Boyd Lake"
      }
    },
    {
      "geometry": {
        "type": "Point",
        "coordinates": [
          -114.5333,
          46.2667
        ]
      },
      "type": "Feature",
      "properties": {
        "hierarchy": [
          "tgn:2190924",
          "tgn:1000001",
          "tgn:7012149",
          "tgn:2000476",
          "tgn:7007250",
          "tgn:7029392"
        ],
        "placetype": [
          "aat:300008680"
        ],
        "id": 2190924,
        "name:xx": "Boyd Lake"
      }
    },
    {
      "geometry": {
        "type": "Point",
        "coordinates": [
          -86.1667,
          39.25
        ]
      },
      "type": "Feature",
      "properties": {
        "hierarchy": [
          "tgn:2190925",
          "tgn:1000001",
          "tgn:1002209",
          "tgn:7012149",
          "tgn:7007252",
          "tgn:7029392"
        ],
        "placetype": [
          "aat:300006191"
        ],
        "id": 2190925,
        "name:xx": "Boyd Lake"
      }
    },
    {
      "geometry": {
        "type": "Point",
        "coordinates": [
          -87.6333,
          36.8
        ]
      },
      "type": "Feature",
      "properties": {
        "hierarchy": [
          "tgn:2190926",
          "tgn:1000001",
          "tgn:2000780",
          "tgn:7012149",
          "tgn:7007255",
          "tgn:7029392"
        ],
        "placetype": [
          "aat:300008680"
        ],
        "id": 2190926,
        "name:xx": "Boyd Lake"
      }
    },
    {
      "geometry": {
        "type": "Point",
        "coordinates": [
          -68.9167,
          45.1667
        ]
      },
      "type": "Feature",
      "properties": {
        "hierarchy": [
          "tgn:2190927",
          "tgn:1000001",
          "tgn:7012149",
          "tgn:2000928",
          "tgn:7007515",
          "tgn:7029392"
        ],
        "placetype": [
          "aat:300008680"
        ],
        "id": 2190927,
        "name:xx": "Boyd Lake"
      }
    },
    {
      "geometry": {
        "type": "Point",
        "coordinates": [
          -68.8833,
          45.1833
        ]
      },
      "type": "Feature",
      "properties": {
        "hierarchy": [
          "tgn:2190928",
          "tgn:1000001",
          "tgn:7012149",
          "tgn:2000928",
          "tgn:7007515",
          "tgn:7029392"
        ],
        "placetype": [
          "aat:300008347"
        ],
        "id": 2190928,
        "name:xx": "Boyd Lake"
      }
    },
    {
      "geometry": {
        "type": "Point",
        "coordinates": [
          -85.2833,
          43.8167
        ]
      },
      "type": "Feature",
      "properties": {
        "hierarchy": [
          "tgn:2190929",
          "tgn:1000001",
          "tgn:7012149",
          "tgn:2000987",
          "tgn:7007520",
          "tgn:7029392"
        ],
        "placetype": [
          "aat:300008680"
        ],
        "id": 2190929,
        "name:xx": "Boyd Lake"
      }
    }
  ]
}
