{
  "type": "FeatureCollection",
  "features": [
    {
      "geometry": {
        "type": "Point",
        "coordinates": [
          13.9667,
          -21.7833
        ]
      },
      "type": "Feature",
      "properties": {
        "hierarchy": [
          "tgn:1010860",
          "tgn:7001242",
          "tgn:7030583",
          "tgn:1000198",
          "tgn:7029392"
        ],
        "placetype": [
          "aat:300008850"
        ],
        "id": 1010860,
        "name:xx": "Cross, Cape"
      }
    },
    {
      "geometry": {
        "type": "Point",
        "coordinates": [
          -154.8,
          19.5167
        ]
      },
      "type": "Feature",
      "properties": {
        "hierarchy": [
          "tgn:1010863",
          "tgn:7023902",
          "tgn:1000001",
          "tgn:7012149",
          "tgn:7007249",
          "tgn:7029392"
        ],
        "placetype": [
          "aat:300008850"
        ],
        "id": 1010863,
        "name:xx": "Kumukahi, Cape"
      }
    },
    {
      "geometry": {
        "type": "Point",
        "coordinates": [
          -156.8167,
          56.8833
        ]
      },
      "type": "Feature",
      "properties": {
        "hierarchy": [
          "tgn:1010865",
          "tgn:7006450",
          "tgn:1000001",
          "tgn:7030517",
          "tgn:7012149",
          "tgn:7029392"
        ],
        "placetype": [
          "aat:300008850"
        ],
        "id": 1010865,
        "name:xx": "Kuyuyukak, Cape"
      }
    },
    {
      "geometry": {
        "type": "Point",
        "coordinates": [
          135.2167,
          35.7667
        ]
      },
      "type": "Feature",
      "properties": {
        "hierarchy": [
          "tgn:1010866",
          "tgn:1000004",
          "tgn:1000998",
          "tgn:7000896",
          "tgn:1000120",
          "tgn:7029392"
        ],
        "placetype": [
          "aat:300008850"
        ],
        "id": 1010866,
        "name:xx": "Kyōga-misaki"
      }
    },
    {
      "geometry": {
        "type": "Point",
        "coordinates": [
          24.731111,
          34.923889
        ]
      },
      "type": "Feature",
      "properties": {
        "hierarchy": [
          "tgn:1010868",
          "tgn:7002690",
          "tgn:7012056",
          "tgn:1000003",
          "tgn:1000074",
          "tgn:7029392"
        ],
        "placetype": [
          "aat:300008850"
        ],
        "id": 1010868,
        "name:xx": "Líthinon, Ákra"
      }
    },
    {
      "geometry": {
        "type": "Point",
        "coordinates": [
          13.2,
          -9.7167
        ]
      },
      "type": "Feature",
      "properties": {
        "hierarchy": [
          "tgn:1010869",
          "tgn:1000811",
          "tgn:7001242",
          "tgn:1000149",
          "tgn:7029392"
        ],
        "placetype": [
          "aat:300008850"
        ],
        "id": 1010869,
        "name:xx": "Lêdo, Cabo"
      }
    }
  ]
}
