{
  "geometry": {
    "type": "Point",
    "coordinates": [
      1.3167,
      43.4667
    ]
  },
  "type": "Feature",
  "properties": {
    "hierarchy": [
      "tgn:7009385",
      "tgn:1000003",
      "tgn:7002889",
      "tgn:1000070",
      "tgn:7029392"
    ],
    "placetype": [
      "aat:300008347"
    ],
    "id": 7009385,
    "name:xx": "Muret"
  }
}
