{
  "geometry": {
    "type": "Point",
    "coordinates": [
      -90.7667,
      45.2333
    ]
  },
  "type": "Feature",
  "properties": {
    "hierarchy": [
      "tgn:2328562",
      "tgn:1000001",
      "tgn:7012149",
      "tgn:7007922",
      "tgn:7029392"
    ],
    "placetype": [
      "aat:300008707"
    ],
    "id": 2328562,
    "name:xx": "Fisher River"
  }
}
