{
  "geometry": {
    "type": "Point",
    "coordinates": [
      31.4757,
      31.142859
    ]
  },
  "type": "Feature",
  "properties": {
    "hierarchy": [
      "tgn:7536702",
      "tgn:7001242",
      "tgn:1001059",
      "tgn:7016833",
      "tgn:7029392"
    ],
    "placetype": [
      "aat:300008347"
    ],
    "name:en": "Kafr Badawāy al Qadīm",
    "id": 7536702
  }
}
