{
  "geometry": {
    "type": "Point",
    "coordinates": [
      26.4333,
      -19.9833
    ]
  },
  "type": "Feature",
  "properties": {
    "hierarchy": [
      "tgn:1126693",
      "tgn:7001242",
      "tgn:7029392"
    ],
    "placetype": [
      "aat:300008707"
    ],
    "id": 1126693,
    "name:xx": "Maitengwe"
  }
}
