{
  "geometry": {
    "type": "Point",
    "coordinates": [
      -73.6167,
      41.2167
    ]
  },
  "type": "Feature",
  "properties": {
    "hierarchy": [
      "tgn:2572130",
      "tgn:1000001",
      "tgn:7012149",
      "tgn:7014612",
      "tgn:7007568",
      "tgn:7029392"
    ],
    "placetype": [
      "aat:300008680"
    ],
    "id": 2572130,
    "name:xx": "Pea Pond"
  }
}
