{
  "geometry": {
    "type": "Point",
    "coordinates": [
      -94.45,
      32.1667
    ]
  },
  "type": "Feature",
  "properties": {
    "hierarchy": [
      "tgn:2370407",
      "tgn:1000001",
      "tgn:7012149",
      "tgn:1002769",
      "tgn:7007826",
      "tgn:7029392"
    ],
    "placetype": [
      "aat:300006191"
    ],
    "id": 2370407,
    "name:xx": "H and H Lake"
  }
}
