{
  "geometry": {
    "type": "Point",
    "coordinates": [
      -105.6667,
      44.75
    ]
  },
  "type": "Feature",
  "properties": {
    "hierarchy": [
      "tgn:1132496",
      "tgn:1000001",
      "tgn:7012149",
      "tgn:7029392"
    ],
    "placetype": [
      "aat:300008706"
    ],
    "id": 1132496,
    "name:xx": "Bitter Creek"
  }
}
