{
  "geometry": {
    "type": "Point",
    "coordinates": [
      -85.0667,
      29.7333
    ]
  },
  "type": "Feature",
  "properties": {
    "hierarchy": [
      "tgn:2721649",
      "tgn:1000001",
      "tgn:2000267",
      "tgn:7012149",
      "tgn:7007240",
      "tgn:7029392"
    ],
    "placetype": [
      "aat:300008347"
    ],
    "id": 2721649,
    "name:xx": "Tilton"
  }
}
