{
  "type": "FeatureCollection",
  "features": [
    {
      "geometry": {
        "type": "Point",
        "coordinates": [
          3.983333,
          51.466667
        ]
      },
      "type": "Feature",
      "properties": {
        "hierarchy": [
          "tgn:7270960",
          "tgn:1000003",
          "tgn:7003635",
          "tgn:7016845",
          "tgn:7029392"
        ],
        "placetype": [
          "aat:300387200"
        ],
        "name:nl": "Smokkelhoek",
        "id": 7270960
      }
    },
    {
      "geometry": {
        "type": "Point",
        "coordinates": [
          6.983333,
          52.283333
        ]
      },
      "type": "Feature",
      "properties": {
        "hierarchy": [
          "tgn:7270961",
          "tgn:1000003",
          "tgn:7003626",
          "tgn:7016845",
          "tgn:7029392"
        ],
        "placetype": [
          "aat:300008863"
        ],
        "name:nl": "Smoddebos",
        "id": 7270961
      }
    },
    {
      "geometry": {
        "type": "Point",
        "coordinates": [
          5.95,
          50.916667
        ]
      },
      "type": "Feature",
      "properties": {
        "hierarchy": [
          "tgn:7270962",
          "tgn:1000003",
          "tgn:7003622",
          "tgn:7016845",
          "tgn:7029392"
        ],
        "placetype": [
          "aat:300008347"
        ],
        "name:nl": "Smitzerveld",
        "id": 7270962
      }
    },
    {
      "geometry": {
        "type": "Point",
        "coordinates": [
          6.383333,
          52.8
        ]
      },
      "type": "Feature",
      "properties": {
        "hierarchy": [
          "tgn:7270963",
          "tgn:7003614",
          "tgn:1000003",
          "tgn:7016845",
          "tgn:7029392"
        ],
        "placetype": [
          "aat:300008688"
        ],
        "name:nl": "Smitsveen",
        "id": 7270963
      }
    },
    {
      "geometry": {
        "type": "Point",
        "coordinates": [
          5.9,
          52.333333
        ]
      },
      "type": "Feature",
      "properties": {
        "hierarchy": [
          "tgn:7270964",
          "tgn:7003619",
          "tgn:1000003",
          "tgn:7016845",
          "tgn:7029392"
        ],
        "placetype": [
          "aat:300386887"
        ],
        "name:nl": "Smitsveen",
        "id": 7270964
      }
    },
    {
      "geometry": {
        "type": "Point",
        "coordinates": [
          4.483333,
          51.866667
        ]
      },
      "type": "Feature",
      "properties": {
        "hierarchy": [
          "tgn:7270965",
          "tgn:1000003",
          "tgn:7003632",
          "tgn:7016845",
          "tgn:7029392"
        ],
        "placetype": [
          "aat:300008347"
        ],
        "name:nl": "Smitshoek",
        "id": 7270965
      }
    },
    {
      "geometry": {
        "type": "Point",
        "coordinates": [
          5.2,
          52.2
        ]
      },
      "type": "Feature",
      "properties": {
        "hierarchy": [
          "tgn:7270966",
          "tgn:1000003",
          "tgn:7006951",
          "tgn:7016845",
          "tgn:7029392"
        ],
        "placetype": [
          "aat:300008863"
        ],
        "name:nl": "Smithuyserbos",
        "id": 7270966
      }
    },
    {
      "geometry": {
        "type": "Point",
        "coordinates": [
          6.35,
          52.9
        ]
      },
      "type": "Feature",
      "properties": {
        "hierarchy": [
          "tgn:7270968",
          "tgn:7003614",
          "tgn:1000003",
          "tgn:7016845",
          "tgn:7029392"
        ],
        "placetype": [
          "aat:300008187"
        ],
        "name:nl": "Boswachterij Smilde",
        "id": 7270968
      }
    }
  ]
}
