{
  "geometry": {
    "type": "Point",
    "coordinates": [
      -79.9667,
      40.4167
    ]
  },
  "type": "Feature",
  "properties": {
    "hierarchy": [
      "tgn:2682730",
      "tgn:7013272",
      "tgn:1000001",
      "tgn:7012149",
      "tgn:7007710",
      "tgn:7029392"
    ],
    "placetype": [
      "aat:300008347"
    ],
    "id": 2682730,
    "name:xx": "Southside Slopes"
  }
}
