{
  "geometry": {
    "type": "Point",
    "coordinates": [
      -110.3833,
      34.3833
    ]
  },
  "type": "Feature",
  "properties": {
    "hierarchy": [
      "tgn:2143072",
      "tgn:1000001",
      "tgn:7006451",
      "tgn:7012149",
      "tgn:2000099",
      "tgn:7029392"
    ],
    "placetype": [
      "aat:300006191"
    ],
    "id": 2143072,
    "name:xx": "Bagnal Tank"
  }
}
