{
  "type": "FeatureCollection",
  "features": [
    {
      "geometry": {
        "type": "Point",
        "coordinates": [
          -161.9167,
          65.9
        ]
      },
      "type": "Feature",
      "properties": {
        "hierarchy": [
          "tgn:2005941",
          "tgn:7006450",
          "tgn:1000001",
          "tgn:7012149",
          "tgn:2124014",
          "tgn:7029392"
        ],
        "placetype": [
          "aat:300008347"
        ],
        "id": 2005941,
        "name:xx": "Candle"
      }
    },
    {
      "geometry": {
        "type": "Point",
        "coordinates": [
          -148.95,
          63.3833
        ]
      },
      "type": "Feature",
      "properties": {
        "hierarchy": [
          "tgn:2005942",
          "tgn:7006450",
          "tgn:1000001",
          "tgn:7030547",
          "tgn:7012149",
          "tgn:7029392"
        ],
        "placetype": [
          "aat:300008347"
        ],
        "id": 2005942,
        "name:xx": "Cantwell"
      }
    },
    {
      "geometry": {
        "type": "Point",
        "coordinates": [
          -133.7833,
          55.95
        ]
      },
      "type": "Feature",
      "properties": {
        "hierarchy": [
          "tgn:2005948",
          "tgn:7006450",
          "tgn:1000001",
          "tgn:7012149",
          "tgn:2000082",
          "tgn:7016045",
          "tgn:7029392"
        ],
        "placetype": [
          "aat:300008347"
        ],
        "id": 2005948,
        "name:xx": "Cape Pole"
      }
    }
  ]
}
