{
  "geometry": {
    "type": "Point",
    "coordinates": [
      -90.5167,
      45.9667
    ]
  },
  "type": "Feature",
  "properties": {
    "hierarchy": [
      "tgn:2211689",
      "tgn:1000001",
      "tgn:7012149",
      "tgn:2002348",
      "tgn:7007922",
      "tgn:7029392"
    ],
    "placetype": [
      "aat:300008680"
    ],
    "id": 2211689,
    "name:xx": "Butternut Lake"
  }
}
