{
  "geometry": {
    "type": "Point",
    "coordinates": [
      -75.1667,
      41.5333
    ]
  },
  "type": "Feature",
  "properties": {
    "hierarchy": [
      "tgn:2627015",
      "tgn:1000001",
      "tgn:7012149",
      "tgn:1003008",
      "tgn:7007710",
      "tgn:7029392"
    ],
    "placetype": [
      "aat:300008699"
    ],
    "id": 2627015,
    "name:xx": "Rocky Run"
  }
}
