{
  "geometry": {
    "type": "Point",
    "coordinates": [
      -74.0167,
      43.3167
    ]
  },
  "type": "Feature",
  "properties": {
    "hierarchy": [
      "tgn:2635202",
      "tgn:1000001",
      "tgn:7012149",
      "tgn:1002871",
      "tgn:7007568",
      "tgn:7029392"
    ],
    "placetype": [
      "aat:300008798"
    ],
    "id": 2635202,
    "name:xx": "Ryther Mountain"
  }
}
