{
  "geometry": {
    "type": "Point",
    "coordinates": [
      -78.5167,
      36.8833
    ]
  },
  "type": "Feature",
  "properties": {
    "hierarchy": [
      "tgn:2183236",
      "tgn:1000001",
      "tgn:7012149",
      "tgn:7007919",
      "tgn:7029392"
    ],
    "placetype": [
      "aat:300008706"
    ],
    "id": 2183236,
    "name:xx": "Bluestone Creek"
  }
}
