{
  "geometry": {
    "type": "Point",
    "coordinates": [
      -116.15,
      32.95
    ]
  },
  "type": "Feature",
  "properties": {
    "hierarchy": [
      "tgn:2215886",
      "tgn:1000001",
      "tgn:7012149",
      "tgn:7007157",
      "tgn:1002858",
      "tgn:7029392"
    ],
    "placetype": [
      "aat:300008699"
    ],
    "id": 2215886,
    "name:xx": "Camels Head Wash"
  }
}
