{
  "type": "FeatureCollection",
  "features": [
    {
      "geometry": {
        "type": "Point",
        "coordinates": [
          -116.3167,
          33.1167
        ]
      },
      "type": "Feature",
      "properties": {
        "hierarchy": [
          "tgn:2630520",
          "tgn:1000001",
          "tgn:7012149",
          "tgn:7007157",
          "tgn:1002858",
          "tgn:7029392"
        ],
        "placetype": [
          "aat:300008798"
        ],
        "id": 2630520,
        "name:xx": "Round Granite Hill"
      }
    },
    {
      "geometry": {
        "type": "Point",
        "coordinates": [
          -87.0167,
          40.5833
        ]
      },
      "type": "Feature",
      "properties": {
        "hierarchy": [
          "tgn:2630521",
          "tgn:1000001",
          "tgn:7012149",
          "tgn:1003021",
          "tgn:7007252",
          "tgn:7029392"
        ],
        "placetype": [
          "aat:300008347"
        ],
        "id": 2630521,
        "name:xx": "Round Grove"
      }
    },
    {
      "geometry": {
        "type": "Point",
        "coordinates": [
          -120.8833,
          42.3333
        ]
      },
      "type": "Feature",
      "properties": {
        "hierarchy": [
          "tgn:2630525",
          "tgn:1000001",
          "tgn:7012149",
          "tgn:2001714",
          "tgn:7007708",
          "tgn:7029392"
        ],
        "placetype": [
          "aat:300008905"
        ],
        "id": 2630525,
        "name:xx": "Round Grove"
      }
    },
    {
      "geometry": {
        "type": "Point",
        "coordinates": [
          -110.7,
          40.45
        ]
      },
      "type": "Feature",
      "properties": {
        "hierarchy": [
          "tgn:2630526",
          "tgn:1000001",
          "tgn:2002107",
          "tgn:7012149",
          "tgn:7007827",
          "tgn:7029392"
        ],
        "placetype": [
          "aat:300132451"
        ],
        "id": 2630526,
        "name:xx": "Round Grove"
      }
    },
    {
      "geometry": {
        "type": "Point",
        "coordinates": [
          -94.4667,
          39
        ]
      },
      "type": "Feature",
      "properties": {
        "hierarchy": [
          "tgn:2630527",
          "tgn:1000001",
          "tgn:7012149",
          "tgn:2001208",
          "tgn:7007523",
          "tgn:7029392"
        ],
        "placetype": [
          "aat:300008706"
        ],
        "id": 2630527,
        "name:xx": "Round Grove Creek"
      }
    },
    {
      "geometry": {
        "type": "Point",
        "coordinates": [
          -96.0167,
          40.1833
        ]
      },
      "type": "Feature",
      "properties": {
        "hierarchy": [
          "tgn:2630528",
          "tgn:1000001",
          "tgn:7012149",
          "tgn:7007525",
          "tgn:7029392"
        ],
        "placetype": [
          "aat:300008706"
        ],
        "id": 2630528,
        "name:xx": "Round Grove Creek"
      }
    },
    {
      "geometry": {
        "type": "Point",
        "coordinates": [
          -94.4833,
          44.7
        ]
      },
      "type": "Feature",
      "properties": {
        "hierarchy": [
          "tgn:2630529",
          "tgn:1000001",
          "tgn:7012149",
          "tgn:7007521",
          "tgn:7029392"
        ],
        "placetype": [
          "aat:300008680"
        ],
        "id": 2630529,
        "name:xx": "Round Grove Lake"
      }
    }
  ]
}
