{
  "geometry": {
    "type": "Point",
    "coordinates": [
      2.9833,
      49.15
    ]
  },
  "type": "Feature",
  "properties": {
    "hierarchy": [
      "tgn:1032134",
      "tgn:1000003",
      "tgn:7002890",
      "tgn:1000070",
      "tgn:7029392"
    ],
    "placetype": [
      "aat:300008347"
    ],
    "id": 1032134,
    "name:xx": "Betz"
  }
}
