{
  "geometry": {
    "type": "Point",
    "coordinates": [
      -109.15,
      40.55
    ]
  },
  "type": "Feature",
  "properties": {
    "hierarchy": [
      "tgn:2187464",
      "tgn:1000001",
      "tgn:7012149",
      "tgn:2002124",
      "tgn:7007827",
      "tgn:7029392"
    ],
    "placetype": [
      "aat:300266640"
    ],
    "id": 2187464,
    "name:xx": "Boone Ridge"
  }
}
