{
  "geometry": {
    "type": "Point",
    "coordinates": [
      -109.1833,
      32.5167
    ]
  },
  "type": "Feature",
  "properties": {
    "hierarchy": [
      "tgn:2552023",
      "tgn:1000001",
      "tgn:7006451",
      "tgn:2000095",
      "tgn:7012149",
      "tgn:7029392"
    ],
    "placetype": [
      "aat:300006191"
    ],
    "id": 2552023,
    "name:xx": "Number Four, Tank"
  }
}
