{
  "geometry": {
    "type": "Point",
    "coordinates": [
      76.300471,
      22.76989
    ]
  },
  "type": "Feature",
  "properties": {
    "hierarchy": [
      "tgn:1075428",
      "tgn:1000004",
      "tgn:7000198",
      "tgn:1001894",
      "tgn:7029392"
    ],
    "placetype": [
      "aat:300008347"
    ],
    "name:en": "Hāt Pīplia",
    "id": 1075428
  }
}
