{
  "type": "FeatureCollection",
  "features": [
    {
      "geometry": {
        "type": "Point",
        "coordinates": [
          7.5,
          51.45
        ]
      },
      "type": "Feature",
      "properties": {
        "hierarchy": [
          "tgn:1005922",
          "tgn:1000003",
          "tgn:7003677",
          "tgn:7000084",
          "tgn:7004982",
          "tgn:7029392"
        ],
        "placetype": [
          "aat:300000745",
          "aat:300387332"
        ],
        "id": 1005922,
        "name:xx": "Wichlinghofen"
      }
    },
    {
      "geometry": {
        "type": "Point",
        "coordinates": [
          7.6167,
          51.5333
        ]
      },
      "type": "Feature",
      "properties": {
        "hierarchy": [
          "tgn:1005923",
          "tgn:1000003",
          "tgn:7003677",
          "tgn:7000084",
          "tgn:7004982",
          "tgn:7029392"
        ],
        "placetype": [
          "aat:300000745",
          "aat:300387332"
        ],
        "id": 1005923,
        "name:xx": "Wickede"
      }
    },
    {
      "geometry": {
        "type": "Point",
        "coordinates": [
          7.0667,
          51.1333
        ]
      },
      "type": "Feature",
      "properties": {
        "hierarchy": [
          "tgn:1005924",
          "tgn:1000003",
          "tgn:7003677",
          "tgn:7000084",
          "tgn:7004940",
          "tgn:7029392"
        ],
        "placetype": [
          "aat:300000745",
          "aat:300387332"
        ],
        "id": 1005924,
        "name:xx": "Widdert"
      }
    },
    {
      "geometry": {
        "type": "Point",
        "coordinates": [
          7.216667,
          51.466667
        ]
      },
      "type": "Feature",
      "properties": {
        "hierarchy": [
          "tgn:1005925",
          "tgn:1000003",
          "tgn:7003677",
          "tgn:7000084",
          "tgn:7004904",
          "tgn:7029392"
        ],
        "placetype": [
          "aat:300000745",
          "aat:300387332"
        ],
        "id": 1005925,
        "name:xx": "Wiemelhausen"
      }
    },
    {
      "geometry": {
        "type": "Point",
        "coordinates": [
          6.9833,
          51.1333
        ]
      },
      "type": "Feature",
      "properties": {
        "hierarchy": [
          "tgn:1005926",
          "tgn:1000003",
          "tgn:7003677",
          "tgn:7000084",
          "tgn:7004940",
          "tgn:7029392"
        ],
        "placetype": [
          "aat:300000745",
          "aat:300387332"
        ],
        "id": 1005926,
        "name:xx": "Wiescheid"
      }
    },
    {
      "geometry": {
        "type": "Point",
        "coordinates": [
          -58.3167,
          -34.7
        ]
      },
      "type": "Feature",
      "properties": {
        "hierarchy": [
          "tgn:1005927",
          "tgn:1001160",
          "tgn:7006477",
          "tgn:1136422",
          "tgn:1000002",
          "tgn:7029392"
        ],
        "placetype": [
          "aat:300000745"
        ],
        "id": 1005927,
        "name:xx": "Wilde"
      }
    },
    {
      "geometry": {
        "type": "Point",
        "coordinates": [
          10,
          53.5
        ]
      },
      "type": "Feature",
      "properties": {
        "hierarchy": [
          "tgn:1005928",
          "tgn:1000003",
          "tgn:7003673",
          "tgn:7005289",
          "tgn:7000084",
          "tgn:7029392"
        ],
        "placetype": [
          "aat:300000745"
        ],
        "id": 1005928,
        "name:xx": "Wilhelmsburg"
      }
    },
    {
      "geometry": {
        "type": "Point",
        "coordinates": [
          13.2,
          52.516667
        ]
      },
      "type": "Feature",
      "properties": {
        "hierarchy": [
          "tgn:1005929",
          "tgn:7003712",
          "tgn:1005645",
          "tgn:7003670",
          "tgn:1000003",
          "tgn:7000084",
          "tgn:7029392"
        ],
        "placetype": [
          "aat:300000745",
          "aat:300387340"
        ],
        "id": 1005929,
        "name:xx": "Wilhelmstadt"
      }
    }
  ]
}
