{
  "type": "FeatureCollection",
  "features": [
    {
      "geometry": {
        "type": "Point",
        "coordinates": [
          -73.8,
          43.3833
        ]
      },
      "type": "Feature",
      "properties": {
        "hierarchy": [
          "tgn:2694630",
          "tgn:1000001",
          "tgn:7012149",
          "tgn:1002986",
          "tgn:7007568",
          "tgn:7029392"
        ],
        "placetype": [
          "aat:300008680"
        ],
        "id": 2694630,
        "name:xx": "Stewart Lake"
      }
    },
    {
      "geometry": {
        "type": "Point",
        "coordinates": [
          -97.2667,
          48.05
        ]
      },
      "type": "Feature",
      "properties": {
        "hierarchy": [
          "tgn:2694631",
          "tgn:1000001",
          "tgn:2001574",
          "tgn:7012149",
          "tgn:7007705",
          "tgn:7029392"
        ],
        "placetype": [
          "aat:300008680"
        ],
        "id": 2694631,
        "name:xx": "Stewart Lake"
      }
    },
    {
      "geometry": {
        "type": "Point",
        "coordinates": [
          -103.4333,
          46.3333
        ]
      },
      "type": "Feature",
      "properties": {
        "hierarchy": [
          "tgn:2694632",
          "tgn:1000001",
          "tgn:2001600",
          "tgn:7012149",
          "tgn:7007705",
          "tgn:7029392"
        ],
        "placetype": [
          "aat:300006191"
        ],
        "id": 2694632,
        "name:xx": "Stewart Lake"
      }
    },
    {
      "geometry": {
        "type": "Point",
        "coordinates": [
          -82.95,
          39.2167
        ]
      },
      "type": "Feature",
      "properties": {
        "hierarchy": [
          "tgn:2694633",
          "tgn:1000001",
          "tgn:7012149",
          "tgn:1002835",
          "tgn:7007706",
          "tgn:7029392"
        ],
        "placetype": [
          "aat:300008680"
        ],
        "id": 2694633,
        "name:xx": "Stewart Lake"
      }
    },
    {
      "geometry": {
        "type": "Point",
        "coordinates": [
          -119.4333,
          44.3833
        ]
      },
      "type": "Feature",
      "properties": {
        "hierarchy": [
          "tgn:2694634",
          "tgn:1000001",
          "tgn:7012149",
          "tgn:2001708",
          "tgn:7007708",
          "tgn:7029392"
        ],
        "placetype": [
          "aat:300008680"
        ],
        "id": 2694634,
        "name:xx": "Stewart Lake"
      }
    },
    {
      "geometry": {
        "type": "Point",
        "coordinates": [
          -123.2333,
          44.5833
        ]
      },
      "type": "Feature",
      "properties": {
        "hierarchy": [
          "tgn:2694635",
          "tgn:1000001",
          "tgn:2001701",
          "tgn:7012149",
          "tgn:7007708",
          "tgn:7029392"
        ],
        "placetype": [
          "aat:300008680"
        ],
        "id": 2694635,
        "name:xx": "Stewart Lake"
      }
    },
    {
      "geometry": {
        "type": "Point",
        "coordinates": [
          -98.2667,
          32.4667
        ]
      },
      "type": "Feature",
      "properties": {
        "hierarchy": [
          "tgn:2694636",
          "tgn:1000001",
          "tgn:7012149",
          "tgn:2001982",
          "tgn:7007826",
          "tgn:7029392"
        ],
        "placetype": [
          "aat:300006191"
        ],
        "id": 2694636,
        "name:xx": "Stewart Lake"
      }
    },
    {
      "geometry": {
        "type": "Point",
        "coordinates": [
          -95.5333,
          30.5833
        ]
      },
      "type": "Feature",
      "properties": {
        "hierarchy": [
          "tgn:2694637",
          "tgn:1000001",
          "tgn:7012149",
          "tgn:1002980",
          "tgn:7007826",
          "tgn:7029392"
        ],
        "placetype": [
          "aat:300008680"
        ],
        "id": 2694637,
        "name:xx": "Stewart Lake"
      }
    },
    {
      "geometry": {
        "type": "Point",
        "coordinates": [
          -96.15,
          30.65
        ]
      },
      "type": "Feature",
      "properties": {
        "hierarchy": [
          "tgn:2694638",
          "tgn:1000001",
          "tgn:7012149",
          "tgn:1002429",
          "tgn:7007826",
          "tgn:7029392"
        ],
        "placetype": [
          "aat:300008680"
        ],
        "id": 2694638,
        "name:xx": "Stewart Lake"
      }
    },
    {
      "geometry": {
        "type": "Point",
        "coordinates": [
          -95.6833,
          30.3667
        ]
      },
      "type": "Feature",
      "properties": {
        "hierarchy": [
          "tgn:2694639",
          "tgn:1000001",
          "tgn:7012149",
          "tgn:1002691",
          "tgn:7007826",
          "tgn:7029392"
        ],
        "placetype": [
          "aat:300006191"
        ],
        "id": 2694639,
        "name:xx": "Stewart Lake"
      }
    }
  ]
}
