{
  "geometry": {
    "type": "Point",
    "coordinates": [
      -77.25,
      41.2833
    ]
  },
  "type": "Feature",
  "properties": {
    "hierarchy": [
      "tgn:2601646",
      "tgn:1000001",
      "tgn:7012149",
      "tgn:1002613",
      "tgn:7007710",
      "tgn:7029392"
    ],
    "placetype": [
      "aat:300008798"
    ],
    "id": 2601646,
    "name:xx": "Puterbaugh Mountain"
  }
}
