{
  "geometry": {
    "type": "Point",
    "coordinates": [
      -104.6833,
      44.5833
    ]
  },
  "type": "Feature",
  "properties": {
    "hierarchy": [
      "tgn:2122894",
      "tgn:1000001",
      "tgn:2002370",
      "tgn:7012149",
      "tgn:7007923",
      "tgn:7029392"
    ],
    "placetype": [
      "aat:300008347"
    ],
    "id": 2122894,
    "name:xx": "Devils Tower"
  }
}
