{
  "geometry": {
    "type": "Point",
    "coordinates": [
      8.016667,
      52.25
    ]
  },
  "type": "Feature",
  "properties": {
    "hierarchy": [
      "tgn:7165304",
      "tgn:1000003",
      "tgn:7003676",
      "tgn:7000084",
      "tgn:7029392"
    ],
    "placetype": [
      "aat:300008863"
    ],
    "id": 7165304,
    "name:xx": "Hörter Bruch"
  }
}
