{
  "geometry": {
    "type": "Point",
    "coordinates": [
      -88.35,
      45.6333
    ]
  },
  "type": "Feature",
  "properties": {
    "hierarchy": [
      "tgn:2241300",
      "tgn:1000001",
      "tgn:7012149",
      "tgn:2002337",
      "tgn:7007922",
      "tgn:7029392"
    ],
    "placetype": [
      "aat:300008680"
    ],
    "id": 2241300,
    "name:xx": "Clark Lake"
  }
}
