{
  "geometry": {
    "type": "Point",
    "coordinates": [
      114.4333,
      32.2833
    ]
  },
  "type": "Feature",
  "properties": {
    "hierarchy": [
      "tgn:1129956",
      "tgn:1000004",
      "tgn:1000111",
      "tgn:7029392"
    ],
    "placetype": [
      "aat:300008707"
    ],
    "id": 1129956,
    "name:xx": "Shi He"
  }
}
