{
  "type": "FeatureCollection",
  "features": [
    {
      "geometry": {
        "type": "Point",
        "coordinates": [
          -111.9167,
          35.4333
        ]
      },
      "type": "Feature",
      "properties": {
        "hierarchy": [
          "tgn:2429540",
          "tgn:1000001",
          "tgn:7006451",
          "tgn:2000092",
          "tgn:7012149",
          "tgn:7029392"
        ],
        "placetype": [
          "aat:300266640"
        ],
        "id": 2429540,
        "name:xx": "Juniper Ridge"
      }
    },
    {
      "geometry": {
        "type": "Point",
        "coordinates": [
          -110.2,
          34.25
        ]
      },
      "type": "Feature",
      "properties": {
        "hierarchy": [
          "tgn:2429541",
          "tgn:1000001",
          "tgn:7006451",
          "tgn:7012149",
          "tgn:2000099",
          "tgn:7029392"
        ],
        "placetype": [
          "aat:300266640"
        ],
        "id": 2429541,
        "name:xx": "Juniper Ridge"
      }
    },
    {
      "geometry": {
        "type": "Point",
        "coordinates": [
          -120.65,
          41.8
        ]
      },
      "type": "Feature",
      "properties": {
        "hierarchy": [
          "tgn:2429542",
          "tgn:1000001",
          "tgn:7012149",
          "tgn:7007157",
          "tgn:2000186",
          "tgn:7029392"
        ],
        "placetype": [
          "aat:300266640"
        ],
        "id": 2429542,
        "name:xx": "Juniper Ridge"
      }
    },
    {
      "geometry": {
        "type": "Point",
        "coordinates": [
          -120.3333,
          40.8667
        ]
      },
      "type": "Feature",
      "properties": {
        "hierarchy": [
          "tgn:2429543",
          "tgn:1000001",
          "tgn:7012149",
          "tgn:7007157",
          "tgn:7029392"
        ],
        "placetype": [
          "aat:300266640"
        ],
        "id": 2429543,
        "name:xx": "Juniper Ridge"
      }
    },
    {
      "geometry": {
        "type": "Point",
        "coordinates": [
          -120.5333,
          36.1833
        ]
      },
      "type": "Feature",
      "properties": {
        "hierarchy": [
          "tgn:2429544",
          "tgn:1000001",
          "tgn:7012149",
          "tgn:1002392",
          "tgn:7007157",
          "tgn:7029392"
        ],
        "placetype": [
          "aat:300266640"
        ],
        "id": 2429544,
        "name:xx": "Juniper Ridge"
      }
    },
    {
      "geometry": {
        "type": "Point",
        "coordinates": [
          -117.5667,
          40.9333
        ]
      },
      "type": "Feature",
      "properties": {
        "hierarchy": [
          "tgn:2429545",
          "tgn:1000001",
          "tgn:2001414",
          "tgn:7012149",
          "tgn:7007526",
          "tgn:7029392"
        ],
        "placetype": [
          "aat:300266640"
        ],
        "id": 2429545,
        "name:xx": "Juniper Ridge"
      }
    },
    {
      "geometry": {
        "type": "Point",
        "coordinates": [
          -108.85,
          33.8167
        ]
      },
      "type": "Feature",
      "properties": {
        "hierarchy": [
          "tgn:2429546",
          "tgn:1000001",
          "tgn:2001429",
          "tgn:7012149",
          "tgn:7007566",
          "tgn:7029392"
        ],
        "placetype": [
          "aat:300266640"
        ],
        "id": 2429546,
        "name:xx": "Juniper Ridge"
      }
    },
    {
      "geometry": {
        "type": "Point",
        "coordinates": [
          -119.6167,
          42.95
        ]
      },
      "type": "Feature",
      "properties": {
        "hierarchy": [
          "tgn:2429547",
          "tgn:1000001",
          "tgn:7012149",
          "tgn:2001709",
          "tgn:7007708",
          "tgn:7029392"
        ],
        "placetype": [
          "aat:300266640"
        ],
        "id": 2429547,
        "name:xx": "Juniper Ridge"
      }
    },
    {
      "geometry": {
        "type": "Point",
        "coordinates": [
          -122.4,
          42.45
        ]
      },
      "type": "Feature",
      "properties": {
        "hierarchy": [
          "tgn:2429548",
          "tgn:1000001",
          "tgn:7012149",
          "tgn:2001711",
          "tgn:7007708",
          "tgn:7029392"
        ],
        "placetype": [
          "aat:300266640"
        ],
        "id": 2429548,
        "name:xx": "Juniper Ridge"
      }
    },
    {
      "geometry": {
        "type": "Point",
        "coordinates": [
          -117.2833,
          43.45
        ]
      },
      "type": "Feature",
      "properties": {
        "hierarchy": [
          "tgn:2429549",
          "tgn:1000001",
          "tgn:7012149",
          "tgn:2001718",
          "tgn:7007708",
          "tgn:7029392"
        ],
        "placetype": [
          "aat:300266640"
        ],
        "id": 2429549,
        "name:xx": "Juniper Ridge"
      }
    }
  ]
}
