{
  "type": "FeatureCollection",
  "features": [
    {
      "geometry": {
        "type": "Point",
        "coordinates": [
          7.45,
          49.183333
        ]
      },
      "type": "Feature",
      "properties": {
        "hierarchy": [
          "tgn:7032330",
          "tgn:1000003",
          "tgn:7003682",
          "tgn:7000084",
          "tgn:7029392"
        ],
        "placetype": [
          "aat:300008347",
          "aat:300008375"
        ],
        "id": 7032330,
        "name:de": "Riedelberg"
      }
    },
    {
      "geometry": {
        "type": "Point",
        "coordinates": [
          7.466667,
          49.2
        ]
      },
      "type": "Feature",
      "properties": {
        "hierarchy": [
          "tgn:7032331",
          "tgn:1000003",
          "tgn:7003682",
          "tgn:7000084",
          "tgn:7029392"
        ],
        "placetype": [
          "aat:300008347",
          "aat:300008375"
        ],
        "id": 7032331,
        "name:de": "Kleinsteinhausen"
      }
    },
    {
      "geometry": {
        "type": "Point",
        "coordinates": [
          3.338,
          32.583
        ]
      },
      "type": "Feature",
      "properties": {
        "hierarchy": [
          "tgn:7032334",
          "tgn:7001242",
          "tgn:7016752",
          "tgn:7593685",
          "tgn:7029392"
        ],
        "placetype": [
          "aat:300055621",
          "aat:300263063",
          "aat:300008761"
        ],
        "id": 7032334,
        "name:xx": "M'Zab"
      }
    },
    {
      "geometry": {
        "type": "Point",
        "coordinates": [
          3.067,
          36.783
        ]
      },
      "type": "Feature",
      "properties": {
        "hierarchy": [
          "tgn:7032335",
          "tgn:7001314",
          "tgn:1000598",
          "tgn:7001242",
          "tgn:7016752",
          "tgn:7029392"
        ],
        "placetype": [
          "aat:300387331",
          "aat:300263063"
        ],
        "id": 7032335,
        "name:xx": "Kasbah"
      }
    }
  ]
}
