{
  "geometry": {
    "type": "Point",
    "coordinates": [
      -110.7667,
      31.7167
    ]
  },
  "type": "Feature",
  "properties": {
    "hierarchy": [
      "tgn:2559552",
      "tgn:1000001",
      "tgn:7006451",
      "tgn:7012149",
      "tgn:2000102",
      "tgn:7029392"
    ],
    "placetype": [
      "aat:300008746"
    ],
    "id": 2559552,
    "name:xx": "Onyx Cave"
  }
}
