{
  "geometry": {
    "type": "Point",
    "coordinates": [
      61.8333,
      37.5833
    ]
  },
  "type": "Feature",
  "properties": {
    "hierarchy": [
      "tgn:7012225",
      "tgn:1000004",
      "tgn:7006659",
      "tgn:7029392"
    ],
    "placetype": [
      "aat:300006075"
    ],
    "name:en": "Karakum Canal",
    "id": 7012225
  }
}
