{
  "type": "FeatureCollection",
  "features": [
    {
      "geometry": {
        "type": "Point",
        "coordinates": [
          -93.7333,
          29.8667
        ]
      },
      "type": "Feature",
      "properties": {
        "hierarchy": [
          "tgn:2773690",
          "tgn:1000001",
          "tgn:7020676",
          "tgn:7012149",
          "tgn:7007256",
          "tgn:7029392"
        ],
        "placetype": [
          "aat:300008699"
        ],
        "id": 2773690,
        "name:xx": "Willow Bayou"
      }
    },
    {
      "geometry": {
        "type": "Point",
        "coordinates": [
          -92.5167,
          31.25
        ]
      },
      "type": "Feature",
      "properties": {
        "hierarchy": [
          "tgn:2773691",
          "tgn:1000001",
          "tgn:7012149",
          "tgn:2000893",
          "tgn:7007256",
          "tgn:7029392"
        ],
        "placetype": [
          "aat:300008699"
        ],
        "id": 2773691,
        "name:xx": "Willow Bayou"
      }
    },
    {
      "geometry": {
        "type": "Point",
        "coordinates": [
          -90.95,
          32.4
        ]
      },
      "type": "Feature",
      "properties": {
        "hierarchy": [
          "tgn:2773692",
          "tgn:1000001",
          "tgn:7012149",
          "tgn:2001160",
          "tgn:7007522",
          "tgn:7029392"
        ],
        "placetype": [
          "aat:300008905"
        ],
        "id": 2773692,
        "name:xx": "Willow Bayou"
      }
    },
    {
      "geometry": {
        "type": "Point",
        "coordinates": [
          -95.0667,
          29.3333
        ]
      },
      "type": "Feature",
      "properties": {
        "hierarchy": [
          "tgn:2773694",
          "tgn:1000001",
          "tgn:7012149",
          "tgn:7007826",
          "tgn:7029392"
        ],
        "placetype": [
          "aat:300008699"
        ],
        "id": 2773694,
        "name:xx": "Willow Bayou"
      }
    },
    {
      "geometry": {
        "type": "Point",
        "coordinates": [
          -93.7,
          29.8667
        ]
      },
      "type": "Feature",
      "properties": {
        "hierarchy": [
          "tgn:2773695",
          "tgn:1000001",
          "tgn:7020676",
          "tgn:7012149",
          "tgn:7007256",
          "tgn:7029392"
        ],
        "placetype": [
          "aat:300006075"
        ],
        "id": 2773695,
        "name:xx": "Willow Bayou Canal"
      }
    },
    {
      "geometry": {
        "type": "Point",
        "coordinates": [
          -77.5,
          42.7333
        ]
      },
      "type": "Feature",
      "properties": {
        "hierarchy": [
          "tgn:2773696",
          "tgn:1000001",
          "tgn:7012149",
          "tgn:1002747",
          "tgn:7007568",
          "tgn:7029392"
        ],
        "placetype": [
          "aat:300008347"
        ],
        "id": 2773696,
        "name:xx": "Willow Beach"
      }
    },
    {
      "geometry": {
        "type": "Point",
        "coordinates": [
          -83.4667,
          41.7
        ]
      },
      "type": "Feature",
      "properties": {
        "hierarchy": [
          "tgn:2773697",
          "tgn:1000001",
          "tgn:7012149",
          "tgn:1002611",
          "tgn:7007706",
          "tgn:7029392"
        ],
        "placetype": [
          "aat:300008347"
        ],
        "id": 2773697,
        "name:xx": "Willow Beach"
      }
    },
    {
      "geometry": {
        "type": "Point",
        "coordinates": [
          -92.1167,
          34.7
        ]
      },
      "type": "Feature",
      "properties": {
        "hierarchy": [
          "tgn:2773698",
          "tgn:1000001",
          "tgn:7016172",
          "tgn:7012149",
          "tgn:2000164",
          "tgn:7029392"
        ],
        "placetype": [
          "aat:300008680"
        ],
        "id": 2773698,
        "name:xx": "Willow Beach Lake"
      }
    },
    {
      "geometry": {
        "type": "Point",
        "coordinates": [
          -92.1333,
          34.7
        ]
      },
      "type": "Feature",
      "properties": {
        "hierarchy": [
          "tgn:2773699",
          "tgn:1000001",
          "tgn:7016172",
          "tgn:7012149",
          "tgn:2000164",
          "tgn:7029392"
        ],
        "placetype": [
          "aat:300006191"
        ],
        "id": 2773699,
        "name:xx": "Willow Beach Lake"
      }
    }
  ]
}
