{
  "geometry": {
    "type": "Point",
    "coordinates": [
      -99.2333,
      33.85
    ]
  },
  "type": "Feature",
  "properties": {
    "hierarchy": [
      "tgn:2508396",
      "tgn:1000001",
      "tgn:7012149",
      "tgn:7007826",
      "tgn:7029392"
    ],
    "placetype": [
      "aat:300008706"
    ],
    "id": 2508396,
    "name:xx": "Middle Coffee Creek"
  }
}
