{
  "geometry": {
    "type": "Point",
    "coordinates": [
      6.75,
      50.55
    ]
  },
  "type": "Feature",
  "properties": {
    "hierarchy": [
      "tgn:7176495",
      "tgn:1000003",
      "tgn:7003677",
      "tgn:7000084",
      "tgn:7029392"
    ],
    "placetype": [
      "aat:300008777"
    ],
    "id": 7176495,
    "name:xx": "Hähnchen"
  }
}
