{
  "type": "FeatureCollection",
  "features": [
    {
      "geometry": {
        "type": "Point",
        "coordinates": [
          -78.6833,
          34.9167
        ]
      },
      "type": "Feature",
      "properties": {
        "hierarchy": [
          "tgn:2378450",
          "tgn:1000001",
          "tgn:7012149",
          "tgn:7007709",
          "tgn:7029392"
        ],
        "placetype": [
          "aat:300008706"
        ],
        "id": 2378450,
        "name:xx": "Harrison Creek"
      }
    },
    {
      "geometry": {
        "type": "Point",
        "coordinates": [
          -83.3667,
          41.0667
        ]
      },
      "type": "Feature",
      "properties": {
        "hierarchy": [
          "tgn:2378451",
          "tgn:1000001",
          "tgn:7012149",
          "tgn:1002883",
          "tgn:7007706",
          "tgn:7029392"
        ],
        "placetype": [
          "aat:300008706"
        ],
        "id": 2378451,
        "name:xx": "Harrison Creek"
      }
    },
    {
      "geometry": {
        "type": "Point",
        "coordinates": [
          -120,
          44.5667
        ]
      },
      "type": "Feature",
      "properties": {
        "hierarchy": [
          "tgn:2378452",
          "tgn:1000001",
          "tgn:7012149",
          "tgn:2001723",
          "tgn:7007708",
          "tgn:7029392"
        ],
        "placetype": [
          "aat:300008706"
        ],
        "id": 2378452,
        "name:xx": "Harrison Creek"
      }
    },
    {
      "geometry": {
        "type": "Point",
        "coordinates": [
          -122.5667,
          42.3
        ]
      },
      "type": "Feature",
      "properties": {
        "hierarchy": [
          "tgn:2378453",
          "tgn:1000001",
          "tgn:7012149",
          "tgn:2001711",
          "tgn:7007708",
          "tgn:7029392"
        ],
        "placetype": [
          "aat:300008706"
        ],
        "id": 2378453,
        "name:xx": "Harrison Creek"
      }
    },
    {
      "geometry": {
        "type": "Point",
        "coordinates": [
          -89.9,
          35.1167
        ]
      },
      "type": "Feature",
      "properties": {
        "hierarchy": [
          "tgn:2378454",
          "tgn:1000001",
          "tgn:7012149",
          "tgn:2001915",
          "tgn:7007825",
          "tgn:7029392"
        ],
        "placetype": [
          "aat:300008706"
        ],
        "id": 2378454,
        "name:xx": "Harrison Creek"
      }
    },
    {
      "geometry": {
        "type": "Point",
        "coordinates": [
          -77.35,
          37.2
        ]
      },
      "type": "Feature",
      "properties": {
        "hierarchy": [
          "tgn:2378455",
          "tgn:1000001",
          "tgn:7012149",
          "tgn:1002805",
          "tgn:7007919",
          "tgn:7029392"
        ],
        "placetype": [
          "aat:300008706"
        ],
        "id": 2378455,
        "name:xx": "Harrison Creek"
      }
    },
    {
      "geometry": {
        "type": "Point",
        "coordinates": [
          -77,
          37.65
        ]
      },
      "type": "Feature",
      "properties": {
        "hierarchy": [
          "tgn:2378456",
          "tgn:1000001",
          "tgn:7012149",
          "tgn:1002548",
          "tgn:7007919",
          "tgn:7029392"
        ],
        "placetype": [
          "aat:300008706"
        ],
        "id": 2378456,
        "name:xx": "Harrison Creek"
      }
    },
    {
      "geometry": {
        "type": "Point",
        "coordinates": [
          -119.15,
          48.2333
        ]
      },
      "type": "Feature",
      "properties": {
        "hierarchy": [
          "tgn:2378457",
          "tgn:1000001",
          "tgn:7012149",
          "tgn:1002742",
          "tgn:7007920",
          "tgn:7029392"
        ],
        "placetype": [
          "aat:300008706"
        ],
        "id": 2378457,
        "name:xx": "Harrison Creek"
      }
    },
    {
      "geometry": {
        "type": "Point",
        "coordinates": [
          -122.3833,
          48.5833
        ]
      },
      "type": "Feature",
      "properties": {
        "hierarchy": [
          "tgn:2378458",
          "tgn:1000001",
          "tgn:7012149",
          "tgn:7014510",
          "tgn:7007920",
          "tgn:7029392"
        ],
        "placetype": [
          "aat:300008706"
        ],
        "id": 2378458,
        "name:xx": "Harrison Creek"
      }
    },
    {
      "geometry": {
        "type": "Point",
        "coordinates": [
          -120.4333,
          45.9333
        ]
      },
      "type": "Feature",
      "properties": {
        "hierarchy": [
          "tgn:2378459",
          "tgn:1000001",
          "tgn:7012149",
          "tgn:1002554",
          "tgn:7007920",
          "tgn:7029392"
        ],
        "placetype": [
          "aat:300008706"
        ],
        "id": 2378459,
        "name:xx": "Harrison Creek"
      }
    }
  ]
}
