{
  "geometry": {
    "type": "Point",
    "coordinates": [
      -90.3833,
      31.55
    ]
  },
  "type": "Feature",
  "properties": {
    "hierarchy": [
      "tgn:2056093",
      "tgn:1000001",
      "tgn:7012149",
      "tgn:2001128",
      "tgn:7007522",
      "tgn:7029392"
    ],
    "placetype": [
      "aat:300008347",
      "aat:300387210"
    ],
    "id": 2056093,
    "name:xx": "Cam"
  }
}
