{
  "geometry": {
    "type": "Point",
    "coordinates": [
      152.3667,
      -27.7333
    ]
  },
  "type": "Feature",
  "properties": {
    "hierarchy": [
      "tgn:1097688",
      "tgn:7000490",
      "tgn:1000006",
      "tgn:7001830",
      "tgn:7029392"
    ],
    "placetype": [
      "aat:300008347"
    ],
    "id": 1097688,
    "name:xx": "Mulgowie"
  }
}
