{
  "geometry": {
    "type": "Point",
    "coordinates": [
      -84.4333,
      42.4667
    ]
  },
  "type": "Feature",
  "properties": {
    "hierarchy": [
      "tgn:2713694",
      "tgn:1000001",
      "tgn:7012149",
      "tgn:1002502",
      "tgn:7007520",
      "tgn:7029392"
    ],
    "placetype": [
      "aat:300008798"
    ],
    "id": 2713694,
    "name:xx": "Teaspoon Hill"
  }
}
