{
  "type": "FeatureCollection",
  "features": [
    {
      "geometry": {
        "type": "Point",
        "coordinates": [
          -83.6,
          35.5
        ]
      },
      "type": "Feature",
      "properties": {
        "hierarchy": [
          "tgn:2380910",
          "tgn:1000001",
          "tgn:7012149",
          "tgn:2001543",
          "tgn:7007709",
          "tgn:7029392"
        ],
        "placetype": [
          "aat:300008699"
        ],
        "id": 2380910,
        "name:xx": "Hawk Ridge Branch"
      }
    },
    {
      "geometry": {
        "type": "Point",
        "coordinates": [
          -161,
          62.2167
        ]
      },
      "type": "Feature",
      "properties": {
        "hierarchy": [
          "tgn:2380911",
          "tgn:7006450",
          "tgn:1000001",
          "tgn:7012149",
          "tgn:7029392"
        ],
        "placetype": [
          "aat:300008707"
        ],
        "id": 2380911,
        "name:xx": "Hawk River"
      }
    },
    {
      "geometry": {
        "type": "Point",
        "coordinates": [
          -77.0333,
          40.3667
        ]
      },
      "type": "Feature",
      "properties": {
        "hierarchy": [
          "tgn:2380912",
          "tgn:1000001",
          "tgn:1002185",
          "tgn:7012149",
          "tgn:7007710",
          "tgn:7029392"
        ],
        "placetype": [
          "aat:300008798"
        ],
        "id": 2380912,
        "name:xx": "Hawk Rock"
      }
    },
    {
      "geometry": {
        "type": "Point",
        "coordinates": [
          -71.8833,
          44.7
        ]
      },
      "type": "Feature",
      "properties": {
        "hierarchy": [
          "tgn:2380913",
          "tgn:2002131",
          "tgn:1000001",
          "tgn:7012149",
          "tgn:7007828",
          "tgn:7029392"
        ],
        "placetype": [
          "aat:300008798"
        ],
        "id": 2380913,
        "name:xx": "Hawk Rock"
      }
    },
    {
      "geometry": {
        "type": "Point",
        "coordinates": [
          -86.85,
          38.2167
        ]
      },
      "type": "Feature",
      "properties": {
        "hierarchy": [
          "tgn:2380914",
          "tgn:1000001",
          "tgn:7012149",
          "tgn:7007252",
          "tgn:7029392"
        ],
        "placetype": [
          "aat:300008699"
        ],
        "id": 2380914,
        "name:xx": "Hawk Run"
      }
    },
    {
      "geometry": {
        "type": "Point",
        "coordinates": [
          -93.2667,
          41.3
        ]
      },
      "type": "Feature",
      "properties": {
        "hierarchy": [
          "tgn:2380915",
          "tgn:1000001",
          "tgn:7012149",
          "tgn:2000623",
          "tgn:7007253",
          "tgn:7029392"
        ],
        "placetype": [
          "aat:300008699"
        ],
        "id": 2380915,
        "name:xx": "Hawk Run"
      }
    },
    {
      "geometry": {
        "type": "Point",
        "coordinates": [
          -78.1667,
          40.8167
        ]
      },
      "type": "Feature",
      "properties": {
        "hierarchy": [
          "tgn:2380916",
          "tgn:1000001",
          "tgn:1002249",
          "tgn:7012149",
          "tgn:7007710",
          "tgn:7029392"
        ],
        "placetype": [
          "aat:300008699"
        ],
        "id": 2380916,
        "name:xx": "Hawk Run"
      }
    },
    {
      "geometry": {
        "type": "Point",
        "coordinates": [
          -78.2,
          40.95
        ]
      },
      "type": "Feature",
      "properties": {
        "hierarchy": [
          "tgn:2380917",
          "tgn:1000001",
          "tgn:1002278",
          "tgn:7012149",
          "tgn:7007710",
          "tgn:7029392"
        ],
        "placetype": [
          "aat:300008699"
        ],
        "id": 2380917,
        "name:xx": "Hawk Run"
      }
    },
    {
      "geometry": {
        "type": "Point",
        "coordinates": [
          -75.6167,
          41.0167
        ]
      },
      "type": "Feature",
      "properties": {
        "hierarchy": [
          "tgn:2380918",
          "tgn:1000001",
          "tgn:1002233",
          "tgn:7012149",
          "tgn:7007710",
          "tgn:7029392"
        ],
        "placetype": [
          "aat:300008699"
        ],
        "id": 2380918,
        "name:xx": "Hawk Run"
      }
    },
    {
      "geometry": {
        "type": "Point",
        "coordinates": [
          -76.8333,
          41.5833
        ]
      },
      "type": "Feature",
      "properties": {
        "hierarchy": [
          "tgn:2380919",
          "tgn:1000001",
          "tgn:7012149",
          "tgn:1002613",
          "tgn:7007710",
          "tgn:7029392"
        ],
        "placetype": [
          "aat:300008699"
        ],
        "id": 2380919,
        "name:xx": "Hawk Run"
      }
    }
  ]
}
