{
  "geometry": {
    "type": "Point",
    "coordinates": [
      -105.05,
      38.8167
    ]
  },
  "type": "Feature",
  "properties": {
    "hierarchy": [
      "tgn:7022372",
      "tgn:1000001",
      "tgn:7012149",
      "tgn:7014097",
      "tgn:7007158",
      "tgn:7029392"
    ],
    "placetype": [
      "aat:300006191"
    ],
    "id": 7022372,
    "name:xx": "Bighorn Reservoir"
  }
}
