{
  "geometry": {
    "type": "Point",
    "coordinates": [
      -80.8167,
      39.0333
    ]
  },
  "type": "Feature",
  "properties": {
    "hierarchy": [
      "tgn:2117903",
      "tgn:1000001",
      "tgn:2002262",
      "tgn:7012149",
      "tgn:7013961",
      "tgn:7029392"
    ],
    "placetype": [
      "aat:300008347"
    ],
    "id": 2117903,
    "name:xx": "Coxs Mills"
  }
}
