{
  "geometry": {
    "type": "Point",
    "coordinates": [
      -118.7333,
      48.6333
    ]
  },
  "type": "Feature",
  "properties": {
    "hierarchy": [
      "tgn:2116605",
      "tgn:1000001",
      "tgn:2002243",
      "tgn:7012149",
      "tgn:7007920",
      "tgn:7029392"
    ],
    "placetype": [
      "aat:300008347",
      "aat:300008416"
    ],
    "id": 2116605,
    "name:xx": "Republic"
  }
}
