{
  "geometry": {
    "type": "Point",
    "coordinates": [
      5.9167,
      49.1667
    ]
  },
  "type": "Feature",
  "properties": {
    "hierarchy": [
      "tgn:1033272",
      "tgn:1000003",
      "tgn:7002888",
      "tgn:1000070",
      "tgn:7029392"
    ],
    "placetype": [
      "aat:300008347"
    ],
    "id": 1033272,
    "name:xx": "Giraumont"
  }
}
