{
  "geometry": {
    "type": "Point",
    "coordinates": [
      79.585875,
      27.573418
    ]
  },
  "type": "Feature",
  "properties": {
    "hierarchy": [
      "tgn:7560864",
      "tgn:1000004",
      "tgn:7000198",
      "tgn:7016722",
      "tgn:7029392"
    ],
    "placetype": [
      "aat:300008347"
    ],
    "name:en": "Nawāda",
    "id": 7560864
  }
}
