{
  "type": "FeatureCollection",
  "features": [
    {
      "geometry": {
        "type": "Point",
        "coordinates": [
          -97.616667,
          20.716667
        ]
      },
      "type": "Feature",
      "properties": {
        "hierarchy": [
          "tgn:7389330",
          "tgn:1000001",
          "tgn:7005599",
          "tgn:7005560",
          "tgn:7029392"
        ],
        "placetype": [
          "aat:300008347"
        ],
        "id": 7389330,
        "name:xx": "Rancho Nuevo"
      }
    },
    {
      "geometry": {
        "type": "Point",
        "coordinates": [
          -100.733333,
          20.516667
        ]
      },
      "type": "Feature",
      "properties": {
        "hierarchy": [
          "tgn:7389331",
          "tgn:7005584",
          "tgn:1000001",
          "tgn:7005560",
          "tgn:7029392"
        ],
        "placetype": [
          "aat:300008347"
        ],
        "id": 7389331,
        "name:xx": "Rancho Nuevo"
      }
    },
    {
      "geometry": {
        "type": "Point",
        "coordinates": [
          -102.85,
          20.45
        ]
      },
      "type": "Feature",
      "properties": {
        "hierarchy": [
          "tgn:7389332",
          "tgn:7005586",
          "tgn:1000001",
          "tgn:7005560",
          "tgn:7029392"
        ],
        "placetype": [
          "aat:300008347"
        ],
        "id": 7389332,
        "name:xx": "La Soledad"
      }
    },
    {
      "geometry": {
        "type": "Point",
        "coordinates": [
          -96.533333,
          19.933333
        ]
      },
      "type": "Feature",
      "properties": {
        "hierarchy": [
          "tgn:7389333",
          "tgn:1000001",
          "tgn:7005599",
          "tgn:7005560",
          "tgn:7029392"
        ],
        "placetype": [
          "aat:300008347"
        ],
        "id": 7389333,
        "name:xx": "Rancho Nuevo"
      }
    },
    {
      "geometry": {
        "type": "Point",
        "coordinates": [
          -96.533333,
          19.45
        ]
      },
      "type": "Feature",
      "properties": {
        "hierarchy": [
          "tgn:7389334",
          "tgn:1000001",
          "tgn:7005599",
          "tgn:7005560",
          "tgn:7029392"
        ],
        "placetype": [
          "aat:300008347"
        ],
        "id": 7389334,
        "name:xx": "Rancho Nuevo"
      }
    },
    {
      "geometry": {
        "type": "Point",
        "coordinates": [
          -102.7,
          19.3
        ]
      },
      "type": "Feature",
      "properties": {
        "hierarchy": [
          "tgn:7389335",
          "tgn:7005586",
          "tgn:1000001",
          "tgn:7005560",
          "tgn:7029392"
        ],
        "placetype": [
          "aat:300008347"
        ],
        "id": 7389335,
        "name:xx": "Rancho Nuevo"
      }
    },
    {
      "geometry": {
        "type": "Point",
        "coordinates": [
          -102.233333,
          19.283333
        ]
      },
      "type": "Feature",
      "properties": {
        "hierarchy": [
          "tgn:7389336",
          "tgn:1000001",
          "tgn:7005590",
          "tgn:7005560",
          "tgn:7029392"
        ],
        "placetype": [
          "aat:300008347"
        ],
        "id": 7389336,
        "name:xx": "Rancho Nuevo"
      }
    },
    {
      "geometry": {
        "type": "Point",
        "coordinates": [
          -101.766667,
          19.066667
        ]
      },
      "type": "Feature",
      "properties": {
        "hierarchy": [
          "tgn:7389337",
          "tgn:1000001",
          "tgn:7005590",
          "tgn:7005560",
          "tgn:7029392"
        ],
        "placetype": [
          "aat:300008347"
        ],
        "id": 7389337,
        "name:xx": "Rancho Nuevo"
      }
    },
    {
      "geometry": {
        "type": "Point",
        "coordinates": [
          -97.45,
          18.9
        ]
      },
      "type": "Feature",
      "properties": {
        "hierarchy": [
          "tgn:7389338",
          "tgn:1000001",
          "tgn:7005592",
          "tgn:7005560",
          "tgn:7029392"
        ],
        "placetype": [
          "aat:300008347"
        ],
        "id": 7389338,
        "name:xx": "Rancho Nuevo"
      }
    },
    {
      "geometry": {
        "type": "Point",
        "coordinates": [
          -101.483333,
          18.166667
        ]
      },
      "type": "Feature",
      "properties": {
        "hierarchy": [
          "tgn:7389339",
          "tgn:7005585",
          "tgn:1000001",
          "tgn:7005560",
          "tgn:7029392"
        ],
        "placetype": [
          "aat:300008347"
        ],
        "id": 7389339,
        "name:xx": "Rancho Nuevo"
      }
    }
  ]
}
