{
  "type": "FeatureCollection",
  "features": [
    {
      "geometry": {
        "type": "Point",
        "coordinates": [
          9.716667,
          53.066667
        ]
      },
      "type": "Feature",
      "properties": {
        "hierarchy": [
          "tgn:7155980",
          "tgn:1000003",
          "tgn:7003676",
          "tgn:7000084",
          "tgn:7029392"
        ],
        "placetype": [
          "aat:300008347"
        ],
        "id": 7155980,
        "name:xx": "Kempen"
      }
    },
    {
      "geometry": {
        "type": "Point",
        "coordinates": [
          8.95,
          51.8
        ]
      },
      "type": "Feature",
      "properties": {
        "hierarchy": [
          "tgn:7155981",
          "tgn:1000003",
          "tgn:7003677",
          "tgn:7000084",
          "tgn:7029392"
        ],
        "placetype": [
          "aat:300008347"
        ],
        "id": 7155981,
        "name:xx": "Kempen"
      }
    },
    {
      "geometry": {
        "type": "Point",
        "coordinates": [
          7.05,
          51.116667
        ]
      },
      "type": "Feature",
      "properties": {
        "hierarchy": [
          "tgn:7155983",
          "tgn:1000003",
          "tgn:7003677",
          "tgn:7000084",
          "tgn:7029392"
        ],
        "placetype": [
          "aat:300008347"
        ],
        "id": 7155983,
        "name:xx": "Kempen"
      }
    },
    {
      "geometry": {
        "type": "Point",
        "coordinates": [
          6.1,
          51.083333
        ]
      },
      "type": "Feature",
      "properties": {
        "hierarchy": [
          "tgn:7155984",
          "tgn:1000003",
          "tgn:7003677",
          "tgn:7000084",
          "tgn:7029392"
        ],
        "placetype": [
          "aat:300008347"
        ],
        "id": 7155984,
        "name:xx": "Kempen"
      }
    },
    {
      "geometry": {
        "type": "Point",
        "coordinates": [
          9.866667,
          53.583333
        ]
      },
      "type": "Feature",
      "properties": {
        "hierarchy": [
          "tgn:7155985",
          "tgn:1000003",
          "tgn:7003673",
          "tgn:7000084",
          "tgn:7029392"
        ],
        "placetype": [
          "aat:300008777"
        ],
        "id": 7155985,
        "name:xx": "Kempel-Berg"
      }
    },
    {
      "geometry": {
        "type": "Point",
        "coordinates": [
          12.1,
          48.45
        ]
      },
      "type": "Feature",
      "properties": {
        "hierarchy": [
          "tgn:7155986",
          "tgn:7003669",
          "tgn:1000003",
          "tgn:7000084",
          "tgn:7029392"
        ],
        "placetype": [
          "aat:300008347"
        ],
        "id": 7155986,
        "name:xx": "Kemoden"
      }
    },
    {
      "geometry": {
        "type": "Point",
        "coordinates": [
          12.9,
          52.316667
        ]
      },
      "type": "Feature",
      "properties": {
        "hierarchy": [
          "tgn:7155987",
          "tgn:7000096",
          "tgn:1000003",
          "tgn:7000084",
          "tgn:7029392"
        ],
        "placetype": [
          "aat:300008347"
        ],
        "id": 7155987,
        "name:xx": "Kemnitzerheide"
      }
    },
    {
      "geometry": {
        "type": "Point",
        "coordinates": [
          13,
          52.15
        ]
      },
      "type": "Feature",
      "properties": {
        "hierarchy": [
          "tgn:7155988",
          "tgn:7000096",
          "tgn:1000003",
          "tgn:7000084",
          "tgn:7029392"
        ],
        "placetype": [
          "aat:300386887"
        ],
        "id": 7155988,
        "name:xx": "Kemnitzer Heide"
      }
    },
    {
      "geometry": {
        "type": "Point",
        "coordinates": [
          13.55,
          54.066667
        ]
      },
      "type": "Feature",
      "properties": {
        "hierarchy": [
          "tgn:7155989",
          "tgn:1000003",
          "tgn:7000094",
          "tgn:7000084",
          "tgn:7029392"
        ],
        "placetype": [
          "aat:300008347"
        ],
        "id": 7155989,
        "name:xx": "Kemnitzerhagen"
      }
    }
  ]
}
