{
  "geometry": {
    "type": "Point",
    "coordinates": [
      25.2833,
      60.8667
    ]
  },
  "type": "Feature",
  "properties": {
    "hierarchy": [
      "tgn:1031320",
      "tgn:7024077",
      "tgn:1000003",
      "tgn:1000069",
      "tgn:7029392"
    ],
    "placetype": [
      "aat:300008347"
    ],
    "id": 1031320,
    "name:xx": "Järvelä"
  }
}
