{
  "type": "FeatureCollection",
  "features": [
    {
      "geometry": {
        "type": "Point",
        "coordinates": [
          -82.3167,
          37.3833
        ]
      },
      "type": "Feature",
      "properties": {
        "hierarchy": [
          "tgn:2642540",
          "tgn:1000001",
          "tgn:7012149",
          "tgn:2000837",
          "tgn:7007255",
          "tgn:7029392"
        ],
        "placetype": [
          "aat:300008699"
        ],
        "id": 2642540,
        "name:xx": "Sanders Branch"
      }
    },
    {
      "geometry": {
        "type": "Point",
        "coordinates": [
          -90.7667,
          31.8333
        ]
      },
      "type": "Feature",
      "properties": {
        "hierarchy": [
          "tgn:2642541",
          "tgn:1000001",
          "tgn:2001096",
          "tgn:7012149",
          "tgn:7007522",
          "tgn:7029392"
        ],
        "placetype": [
          "aat:300008699"
        ],
        "id": 2642541,
        "name:xx": "Sanders Branch"
      }
    },
    {
      "geometry": {
        "type": "Point",
        "coordinates": [
          -90.1833,
          34.5333
        ]
      },
      "type": "Feature",
      "properties": {
        "hierarchy": [
          "tgn:2642542",
          "tgn:1000001",
          "tgn:7012149",
          "tgn:7007522",
          "tgn:7029392"
        ],
        "placetype": [
          "aat:300008699"
        ],
        "id": 2642542,
        "name:xx": "Sanders Branch"
      }
    },
    {
      "geometry": {
        "type": "Point",
        "coordinates": [
          -91.4,
          36.6667
        ]
      },
      "type": "Feature",
      "properties": {
        "hierarchy": [
          "tgn:2642543",
          "tgn:1000001",
          "tgn:7012149",
          "tgn:2001225",
          "tgn:7007523",
          "tgn:7029392"
        ],
        "placetype": [
          "aat:300008699"
        ],
        "id": 2642543,
        "name:xx": "Sanders Branch"
      }
    },
    {
      "geometry": {
        "type": "Point",
        "coordinates": [
          -91.75,
          37.15
        ]
      },
      "type": "Feature",
      "properties": {
        "hierarchy": [
          "tgn:2642544",
          "tgn:1000001",
          "tgn:7012149",
          "tgn:2001252",
          "tgn:7007523",
          "tgn:7029392"
        ],
        "placetype": [
          "aat:300008699"
        ],
        "id": 2642544,
        "name:xx": "Sanders Branch"
      }
    },
    {
      "geometry": {
        "type": "Point",
        "coordinates": [
          -81.05,
          32.8667
        ]
      },
      "type": "Feature",
      "properties": {
        "hierarchy": [
          "tgn:2642545",
          "tgn:1000001",
          "tgn:2001749",
          "tgn:7012149",
          "tgn:7007712",
          "tgn:7029392"
        ],
        "placetype": [
          "aat:300008699"
        ],
        "id": 2642545,
        "name:xx": "Sanders Branch"
      }
    },
    {
      "geometry": {
        "type": "Point",
        "coordinates": [
          -87.35,
          35.85
        ]
      },
      "type": "Feature",
      "properties": {
        "hierarchy": [
          "tgn:2642546",
          "tgn:1000001",
          "tgn:7012149",
          "tgn:7015666",
          "tgn:7007825",
          "tgn:7029392"
        ],
        "placetype": [
          "aat:300008699"
        ],
        "id": 2642546,
        "name:xx": "Sanders Branch"
      }
    },
    {
      "geometry": {
        "type": "Point",
        "coordinates": [
          -86.7333,
          36.5333
        ]
      },
      "type": "Feature",
      "properties": {
        "hierarchy": [
          "tgn:2642547",
          "tgn:1000001",
          "tgn:7012149",
          "tgn:2001910",
          "tgn:7007825",
          "tgn:7029392"
        ],
        "placetype": [
          "aat:300008699"
        ],
        "id": 2642547,
        "name:xx": "Sanders Branch"
      }
    },
    {
      "geometry": {
        "type": "Point",
        "coordinates": [
          -84.9,
          35.0667
        ]
      },
      "type": "Feature",
      "properties": {
        "hierarchy": [
          "tgn:2642548",
          "tgn:1000001",
          "tgn:2001842",
          "tgn:7012149",
          "tgn:7007825",
          "tgn:7029392"
        ],
        "placetype": [
          "aat:300008699"
        ],
        "id": 2642548,
        "name:xx": "Sanders Branch"
      }
    },
    {
      "geometry": {
        "type": "Point",
        "coordinates": [
          -94.95,
          31.9667
        ]
      },
      "type": "Feature",
      "properties": {
        "hierarchy": [
          "tgn:2642549",
          "tgn:1000001",
          "tgn:7012149",
          "tgn:1002839",
          "tgn:7007826",
          "tgn:7029392"
        ],
        "placetype": [
          "aat:300008699"
        ],
        "id": 2642549,
        "name:xx": "Sanders Branch"
      }
    }
  ]
}
