{
  "type": "FeatureCollection",
  "features": [
    {
      "geometry": {
        "type": "Point",
        "coordinates": [
          -112.8333,
          37.65
        ]
      },
      "type": "Feature",
      "properties": {
        "hierarchy": [
          "tgn:2125710",
          "tgn:1000001",
          "tgn:7012149",
          "tgn:2002111",
          "tgn:7007827",
          "tgn:7029392"
        ],
        "placetype": [
          "aat:300008761"
        ],
        "id": 2125710,
        "name:xx": "Adams Canyon"
      }
    },
    {
      "geometry": {
        "type": "Point",
        "coordinates": [
          -111.85,
          41.0667
        ]
      },
      "type": "Feature",
      "properties": {
        "hierarchy": [
          "tgn:2125711",
          "tgn:1000001",
          "tgn:2002106",
          "tgn:7012149",
          "tgn:7007827",
          "tgn:7029392"
        ],
        "placetype": [
          "aat:300008761"
        ],
        "id": 2125711,
        "name:xx": "Adams Canyon"
      }
    },
    {
      "geometry": {
        "type": "Point",
        "coordinates": [
          -110.95,
          43.4167
        ]
      },
      "type": "Feature",
      "properties": {
        "hierarchy": [
          "tgn:2125712",
          "tgn:1000001",
          "tgn:7012149",
          "tgn:2002384",
          "tgn:7007923",
          "tgn:7029392"
        ],
        "placetype": [
          "aat:300008761"
        ],
        "id": 2125712,
        "name:xx": "Adams Canyon"
      }
    },
    {
      "geometry": {
        "type": "Point",
        "coordinates": [
          -104.2667,
          44.2833
        ]
      },
      "type": "Feature",
      "properties": {
        "hierarchy": [
          "tgn:2125713",
          "tgn:1000001",
          "tgn:2002370",
          "tgn:7012149",
          "tgn:7007923",
          "tgn:7029392"
        ],
        "placetype": [
          "aat:300008761"
        ],
        "id": 2125713,
        "name:xx": "Adams Canyon"
      }
    },
    {
      "geometry": {
        "type": "Point",
        "coordinates": [
          -86.6167,
          34.5667
        ]
      },
      "type": "Feature",
      "properties": {
        "hierarchy": [
          "tgn:2125714",
          "tgn:7002659",
          "tgn:1000001",
          "tgn:7012149",
          "tgn:2000044",
          "tgn:7029392"
        ],
        "placetype": [
          "aat:300008746"
        ],
        "id": 2125714,
        "name:xx": "Adams Cave"
      }
    },
    {
      "geometry": {
        "type": "Point",
        "coordinates": [
          -85.0667,
          35.4167
        ]
      },
      "type": "Feature",
      "properties": {
        "hierarchy": [
          "tgn:2125715",
          "tgn:1000001",
          "tgn:7012149",
          "tgn:2001869",
          "tgn:7007825",
          "tgn:7029392"
        ],
        "placetype": [
          "aat:300008746"
        ],
        "id": 2125715,
        "name:xx": "Adams Cave"
      }
    },
    {
      "geometry": {
        "type": "Point",
        "coordinates": [
          -78.7667,
          38.8333
        ]
      },
      "type": "Feature",
      "properties": {
        "hierarchy": [
          "tgn:2125716",
          "tgn:1000001",
          "tgn:7012149",
          "tgn:2002190",
          "tgn:7007919",
          "tgn:7029392"
        ],
        "placetype": [
          "aat:300008746"
        ],
        "id": 2125716,
        "name:xx": "Adams Cave"
      }
    },
    {
      "geometry": {
        "type": "Point",
        "coordinates": [
          -82.9167,
          36.7667
        ]
      },
      "type": "Feature",
      "properties": {
        "hierarchy": [
          "tgn:2125717",
          "tgn:1000001",
          "tgn:7012149",
          "tgn:2002169",
          "tgn:7007919",
          "tgn:7029392"
        ],
        "placetype": [
          "aat:300008746"
        ],
        "id": 2125717,
        "name:xx": "Adams Cave"
      }
    },
    {
      "geometry": {
        "type": "Point",
        "coordinates": [
          -87.05,
          34.95
        ]
      },
      "type": "Feature",
      "properties": {
        "hierarchy": [
          "tgn:2125718",
          "tgn:7002659",
          "tgn:1000001",
          "tgn:7012149",
          "tgn:2000041",
          "tgn:7029392"
        ],
        "placetype": [
          "aat:300008746"
        ],
        "id": 2125718,
        "name:xx": "Adams Cool Crawl Cave"
      }
    },
    {
      "geometry": {
        "type": "Point",
        "coordinates": [
          -98.0833,
          38.05
        ]
      },
      "type": "Feature",
      "properties": {
        "hierarchy": [
          "tgn:2125719",
          "tgn:1000001",
          "tgn:7012149",
          "tgn:2000737",
          "tgn:7007254",
          "tgn:7029392"
        ],
        "placetype": [
          "aat:300008347"
        ],
        "id": 2125719,
        "name:xx": "Adams Corner"
      }
    }
  ]
}
