{
  "geometry": {
    "type": "Point",
    "coordinates": [
      179.45,
      51.3667
    ]
  },
  "type": "Feature",
  "properties": {
    "hierarchy": [
      "tgn:1010653",
      "tgn:7030516",
      "tgn:7006450",
      "tgn:1000001",
      "tgn:7012149",
      "tgn:7029392"
    ],
    "placetype": [
      "aat:300008850"
    ],
    "id": 1010653,
    "name:xx": "East Cape"
  }
}
