{
  "geometry": {
    "type": "Point",
    "coordinates": [
      37.7667,
      12.0667
    ]
  },
  "type": "Feature",
  "properties": {
    "hierarchy": [
      "tgn:1089983",
      "tgn:7001242",
      "tgn:1001267",
      "tgn:7000489",
      "tgn:7029392"
    ],
    "placetype": [
      "aat:300008347"
    ],
    "id": 1089983,
    "name:xx": "Yifag"
  }
}
