{
  "type": "FeatureCollection",
  "features": [
    {
      "geometry": {
        "type": "Point",
        "coordinates": [
          -91.3,
          30.7
        ]
      },
      "type": "Feature",
      "properties": {
        "hierarchy": [
          "tgn:2490660",
          "tgn:1000001",
          "tgn:7012149",
          "tgn:2000916",
          "tgn:7007256",
          "tgn:7029392"
        ],
        "placetype": [
          "aat:300008347"
        ],
        "id": 2490660,
        "name:xx": "Mannheim"
      }
    },
    {
      "geometry": {
        "type": "Point",
        "coordinates": [
          -106.1,
          32.4
        ]
      },
      "type": "Feature",
      "properties": {
        "hierarchy": [
          "tgn:2490661",
          "tgn:1000001",
          "tgn:7012149",
          "tgn:2001447",
          "tgn:7007566",
          "tgn:7029392"
        ],
        "placetype": [
          "aat:300000390"
        ],
        "id": 2490661,
        "name:xx": "Mannie Baird Mine"
      }
    },
    {
      "geometry": {
        "type": "Point",
        "coordinates": [
          -98.3667,
          47.7
        ]
      },
      "type": "Feature",
      "properties": {
        "hierarchy": [
          "tgn:2490662",
          "tgn:1000001",
          "tgn:2001588",
          "tgn:7012149",
          "tgn:7007705",
          "tgn:7029392"
        ],
        "placetype": [
          "aat:300008680"
        ],
        "id": 2490662,
        "name:xx": "Mannie Lake"
      }
    },
    {
      "geometry": {
        "type": "Point",
        "coordinates": [
          -82.1667,
          30.1667
        ]
      },
      "type": "Feature",
      "properties": {
        "hierarchy": [
          "tgn:2490663",
          "tgn:2000257",
          "tgn:1000001",
          "tgn:7012149",
          "tgn:7007240",
          "tgn:7029392"
        ],
        "placetype": [
          "aat:300008347"
        ],
        "id": 2490663,
        "name:xx": "Manning"
      }
    },
    {
      "geometry": {
        "type": "Point",
        "coordinates": [
          -82.7667,
          32.6
        ]
      },
      "type": "Feature",
      "properties": {
        "hierarchy": [
          "tgn:2490664",
          "tgn:1000001",
          "tgn:7012149",
          "tgn:2000378",
          "tgn:7007248",
          "tgn:7029392"
        ],
        "placetype": [
          "aat:300008347"
        ],
        "id": 2490664,
        "name:xx": "Manning"
      }
    },
    {
      "geometry": {
        "type": "Point",
        "coordinates": [
          -93.35,
          32.25
        ]
      },
      "type": "Feature",
      "properties": {
        "hierarchy": [
          "tgn:2490665",
          "tgn:1000001",
          "tgn:2000860",
          "tgn:7012149",
          "tgn:7007256",
          "tgn:7029392"
        ],
        "placetype": [
          "aat:300008347"
        ],
        "id": 2490665,
        "name:xx": "Manning"
      }
    },
    {
      "geometry": {
        "type": "Point",
        "coordinates": [
          -94.5333,
          31.1333
        ]
      },
      "type": "Feature",
      "properties": {
        "hierarchy": [
          "tgn:2490666",
          "tgn:1002149",
          "tgn:1000001",
          "tgn:7012149",
          "tgn:7007826",
          "tgn:7029392"
        ],
        "placetype": [
          "aat:300008347"
        ],
        "id": 2490666,
        "name:xx": "Manning"
      }
    },
    {
      "geometry": {
        "type": "Point",
        "coordinates": [
          -76.6333,
          36.7
        ]
      },
      "type": "Feature",
      "properties": {
        "hierarchy": [
          "tgn:2490667",
          "tgn:1000001",
          "tgn:7012149",
          "tgn:7022217",
          "tgn:7007919",
          "tgn:7029392"
        ],
        "placetype": [
          "aat:300008347"
        ],
        "id": 2490667,
        "name:xx": "Manning"
      }
    },
    {
      "geometry": {
        "type": "Point",
        "coordinates": [
          -117.4,
          46.9167
        ]
      },
      "type": "Feature",
      "properties": {
        "hierarchy": [
          "tgn:2490668",
          "tgn:1000001",
          "tgn:7012149",
          "tgn:2002252",
          "tgn:7007920",
          "tgn:7029392"
        ],
        "placetype": [
          "aat:300008347"
        ],
        "id": 2490668,
        "name:xx": "Manning"
      }
    },
    {
      "geometry": {
        "type": "Point",
        "coordinates": [
          -82.1833,
          34.9167
        ]
      },
      "type": "Feature",
      "properties": {
        "hierarchy": [
          "tgn:2490669",
          "tgn:1000001",
          "tgn:7012149",
          "tgn:2001766",
          "tgn:7007712",
          "tgn:7029392"
        ],
        "placetype": [
          "aat:300008347"
        ],
        "id": 2490669,
        "name:xx": "Manning Acres"
      }
    }
  ]
}
