{
  "geometry": {
    "type": "Point",
    "coordinates": [
      -103.3833,
      43.85
    ]
  },
  "type": "Feature",
  "properties": {
    "hierarchy": [
      "tgn:2480975",
      "tgn:1000001",
      "tgn:2001786",
      "tgn:7012149",
      "tgn:7007713",
      "tgn:7029392"
    ],
    "placetype": [
      "aat:300006191"
    ],
    "id": 2480975,
    "name:xx": "Lakota Lake"
  }
}
