{
  "geometry": {
    "type": "Point",
    "coordinates": [
      -115.4667,
      33.15
    ]
  },
  "type": "Feature",
  "properties": {
    "hierarchy": [
      "tgn:2408942",
      "tgn:1000001",
      "tgn:7012149",
      "tgn:2000182",
      "tgn:7007157",
      "tgn:7029392"
    ],
    "placetype": [
      "aat:300006075"
    ],
    "id": 2408942,
    "name:xx": "I Lateral"
  }
}
