{
  "geometry": {
    "type": "Point",
    "coordinates": [
      -106.1667,
      45.3833
    ]
  },
  "type": "Feature",
  "properties": {
    "hierarchy": [
      "tgn:2565108",
      "tgn:1000001",
      "tgn:7012149",
      "tgn:2001297",
      "tgn:7007524",
      "tgn:7029392"
    ],
    "placetype": [
      "aat:300006191"
    ],
    "id": 2565108,
    "name:xx": "Paget Reservoir Number Two"
  }
}
