{
  "geometry": {
    "type": "Point",
    "coordinates": [
      -78.5667,
      40.8833
    ]
  },
  "type": "Feature",
  "properties": {
    "hierarchy": [
      "tgn:2453486",
      "tgn:1000001",
      "tgn:1002278",
      "tgn:7012149",
      "tgn:7007710",
      "tgn:7029392"
    ],
    "placetype": [
      "aat:300008706"
    ],
    "id": 2453486,
    "name:xx": "Little Clearfield Creek"
  }
}
