{
  "type": "FeatureCollection",
  "features": [
    {
      "geometry": {
        "type": "Point",
        "coordinates": [
          -1.6,
          52.216667
        ]
      },
      "type": "Feature",
      "properties": {
        "hierarchy": [
          "tgn:7441870",
          "tgn:7002445",
          "tgn:1000003",
          "tgn:7008178",
          "tgn:7008591",
          "tgn:7029392"
        ],
        "placetype": [
          "aat:300008347"
        ],
        "name:en": "Wasperton",
        "id": 7441870
      }
    },
    {
      "geometry": {
        "type": "Point",
        "coordinates": [
          -1.916667,
          54.8
        ]
      },
      "type": "Feature",
      "properties": {
        "hierarchy": [
          "tgn:7441871",
          "tgn:7002445",
          "tgn:1000003",
          "tgn:7008127",
          "tgn:7008591",
          "tgn:7029392"
        ],
        "placetype": [
          "aat:300008347"
        ],
        "name:en": "Waskerley",
        "id": 7441871
      }
    },
    {
      "geometry": {
        "type": "Point",
        "coordinates": [
          -1.5,
          54.9
        ]
      },
      "type": "Feature",
      "properties": {
        "hierarchy": [
          "tgn:7441873",
          "tgn:7002445",
          "tgn:7019069",
          "tgn:1000003",
          "tgn:7012033",
          "tgn:7008591",
          "tgn:7029392"
        ],
        "placetype": [
          "aat:300007783"
        ],
        "name:en": "Washington Station",
        "id": 7441873
      }
    },
    {
      "geometry": {
        "type": "Point",
        "coordinates": [
          -3.683333,
          55.25
        ]
      },
      "type": "Feature",
      "properties": {
        "hierarchy": [
          "tgn:7441875",
          "tgn:7002444",
          "tgn:7008074",
          "tgn:1000003",
          "tgn:7008591",
          "tgn:7029392"
        ],
        "placetype": [
          "aat:300008680"
        ],
        "name:en": "Townfoot Loch",
        "id": 7441875
      }
    },
    {
      "geometry": {
        "type": "Point",
        "coordinates": [
          -3.033333,
          57.5
        ]
      },
      "type": "Feature",
      "properties": {
        "hierarchy": [
          "tgn:7441877",
          "tgn:7002444",
          "tgn:1000003",
          "tgn:5000451",
          "tgn:7008591",
          "tgn:7029392"
        ],
        "placetype": [
          "aat:300008795"
        ],
        "name:en": "Towie, Hill of",
        "id": 7441877
      }
    },
    {
      "geometry": {
        "type": "Point",
        "coordinates": [
          -2.933333,
          57.183333
        ]
      },
      "type": "Feature",
      "properties": {
        "hierarchy": [
          "tgn:7441878",
          "tgn:5000432",
          "tgn:7002444",
          "tgn:1000003",
          "tgn:7008591",
          "tgn:7029392"
        ],
        "placetype": [
          "aat:300008347"
        ],
        "name:en": "Towie",
        "id": 7441878
      }
    },
    {
      "geometry": {
        "type": "Point",
        "coordinates": [
          -4.3,
          50.683333
        ]
      },
      "type": "Feature",
      "properties": {
        "hierarchy": [
          "tgn:7441879",
          "tgn:7002445",
          "tgn:1000003",
          "tgn:7012077",
          "tgn:7008591",
          "tgn:7029392"
        ],
        "placetype": [
          "aat:300007783"
        ],
        "name:en": "Towerhill Station",
        "id": 7441879
      }
    }
  ]
}
