{
  "geometry": {
    "type": "Point",
    "coordinates": [
      -107.0667,
      37.0167
    ]
  },
  "type": "Feature",
  "properties": {
    "hierarchy": [
      "tgn:2619479",
      "tgn:2000195",
      "tgn:1000001",
      "tgn:7012149",
      "tgn:7007158",
      "tgn:7029392"
    ],
    "placetype": [
      "aat:300008761"
    ],
    "id": 2619479,
    "name:xx": "Rincon Bonito Canyon"
  }
}
