{
  "geometry": {
    "type": "Point",
    "coordinates": [
      -85.6333,
      31.7333
    ]
  },
  "type": "Feature",
  "properties": {
    "hierarchy": [
      "tgn:2418186",
      "tgn:2000002",
      "tgn:7002659",
      "tgn:1000001",
      "tgn:7012149",
      "tgn:7029392"
    ],
    "placetype": [
      "aat:300006191"
    ],
    "id": 2418186,
    "name:xx": "Jacksons Pond"
  }
}
