{
  "geometry": {
    "type": "Point",
    "coordinates": [
      -92.6833,
      38.2833
    ]
  },
  "type": "Feature",
  "properties": {
    "hierarchy": [
      "tgn:2182713",
      "tgn:1000001",
      "tgn:7012149",
      "tgn:1002671",
      "tgn:7007523",
      "tgn:7029392"
    ],
    "placetype": [
      "aat:300008706"
    ],
    "id": 2182713,
    "name:xx": "Blue Spring Creek"
  }
}
