{
  "geometry": {
    "type": "Point",
    "coordinates": [
      -112.0333,
      38.5167
    ]
  },
  "type": "Feature",
  "properties": {
    "hierarchy": [
      "tgn:2545491",
      "tgn:1000001",
      "tgn:7012149",
      "tgn:7007827",
      "tgn:7029392"
    ],
    "placetype": [
      "aat:300008706"
    ],
    "id": 2545491,
    "name:xx": "North Fork Box Creek"
  }
}
