{
  "geometry": {
    "type": "Point",
    "coordinates": [
      -106.95,
      44.7833
    ]
  },
  "type": "Feature",
  "properties": {
    "hierarchy": [
      "tgn:2123163",
      "tgn:1000001",
      "tgn:7012149",
      "tgn:2002381",
      "tgn:7007923",
      "tgn:7029392"
    ],
    "placetype": [
      "aat:300008347"
    ],
    "id": 2123163,
    "name:xx": "Sheridan"
  }
}
