{
  "geometry": {
    "type": "Point",
    "coordinates": [
      -79.6833,
      40.8667
    ]
  },
  "type": "Feature",
  "properties": {
    "hierarchy": [
      "tgn:2091336",
      "tgn:1002153",
      "tgn:1000001",
      "tgn:7012149",
      "tgn:7007710",
      "tgn:7029392"
    ],
    "placetype": [
      "aat:300008347",
      "aat:300387210"
    ],
    "id": 2091336,
    "name:xx": "Nichola"
  }
}
