{
  "geometry": {
    "type": "Point",
    "coordinates": [
      -107.2833,
      34.9833
    ]
  },
  "type": "Feature",
  "properties": {
    "hierarchy": [
      "tgn:2312869",
      "tgn:1000001",
      "tgn:2001431",
      "tgn:7012149",
      "tgn:7007566",
      "tgn:7029392"
    ],
    "placetype": [
      "aat:300008347"
    ],
    "id": 2312869,
    "name:xx": "El Rito"
  }
}
