{
  "geometry": {
    "type": "Point",
    "coordinates": [
      -80.5833,
      38.45
    ]
  },
  "type": "Feature",
  "properties": {
    "hierarchy": [
      "tgn:2562145",
      "tgn:1000001",
      "tgn:7012149",
      "tgn:2002300",
      "tgn:7013961",
      "tgn:7029392"
    ],
    "placetype": [
      "aat:300008761"
    ],
    "id": 2562145,
    "name:xx": "Otter Hole"
  }
}
