{
  "geometry": {
    "type": "Point",
    "coordinates": [
      -81.95,
      30.1833
    ]
  },
  "type": "Feature",
  "properties": {
    "hierarchy": [
      "tgn:2216172",
      "tgn:1000001",
      "tgn:7012149",
      "tgn:7007240",
      "tgn:7029392"
    ],
    "placetype": [
      "aat:300008699"
    ],
    "id": 2216172,
    "name:xx": "Camp Branch"
  }
}
