{
  "geometry": {
    "type": "Point",
    "coordinates": [
      -77.75,
      37.65
    ]
  },
  "type": "Feature",
  "properties": {
    "hierarchy": [
      "tgn:2342516",
      "tgn:1000001",
      "tgn:7012149",
      "tgn:2002163",
      "tgn:7007919",
      "tgn:7029392"
    ],
    "placetype": [
      "aat:300006191"
    ],
    "id": 2342516,
    "name:xx": "Fullstream, Lake"
  }
}
