{
  "geometry": {
    "type": "Point",
    "coordinates": [
      -111.5667,
      40.0167
    ]
  },
  "type": "Feature",
  "properties": {
    "hierarchy": [
      "tgn:2720581",
      "tgn:1000001",
      "tgn:7012149",
      "tgn:2002125",
      "tgn:7007827",
      "tgn:7029392"
    ],
    "placetype": [
      "aat:300266640"
    ],
    "id": 2720581,
    "name:xx": "Thurber Ridge"
  }
}
