{
  "type": "FeatureCollection",
  "features": [
    {
      "geometry": {
        "type": "Point",
        "coordinates": [
          -1.6,
          53.483333
        ]
      },
      "type": "Feature",
      "properties": {
        "hierarchy": [
          "tgn:1030750",
          "tgn:7002445",
          "tgn:7019047",
          "tgn:1000003",
          "tgn:7029505",
          "tgn:7008591",
          "tgn:7029392"
        ],
        "placetype": [
          "aat:300008347"
        ],
        "name:en": "Stocksbridge",
        "id": 1030750
      }
    },
    {
      "geometry": {
        "type": "Point",
        "coordinates": [
          -2.5667,
          53.3667
        ]
      },
      "type": "Feature",
      "properties": {
        "hierarchy": [
          "tgn:1030751",
          "tgn:7002445",
          "tgn:7008114",
          "tgn:1000003",
          "tgn:7008591",
          "tgn:7029392"
        ],
        "placetype": [
          "aat:300008347"
        ],
        "id": 1030751,
        "name:xx": "Stockton Heath"
      }
    },
    {
      "geometry": {
        "type": "Point",
        "coordinates": [
          0.616667,
          51.433333
        ]
      },
      "type": "Feature",
      "properties": {
        "hierarchy": [
          "tgn:1030753",
          "tgn:7002445",
          "tgn:1000003",
          "tgn:7008153",
          "tgn:7008591",
          "tgn:7029392"
        ],
        "placetype": [
          "aat:300008347",
          "aat:300008372"
        ],
        "name:en": "Stoke",
        "id": 1030753
      }
    },
    {
      "geometry": {
        "type": "Point",
        "coordinates": [
          -1.4,
          52.566667
        ]
      },
      "type": "Feature",
      "properties": {
        "hierarchy": [
          "tgn:1030755",
          "tgn:7002445",
          "tgn:1000003",
          "tgn:7008155",
          "tgn:7008591",
          "tgn:7029392"
        ],
        "placetype": [
          "aat:300008347"
        ],
        "name:en": "Stoke Golding",
        "id": 1030755
      }
    },
    {
      "geometry": {
        "type": "Point",
        "coordinates": [
          -0.9,
          51.65
        ]
      },
      "type": "Feature",
      "properties": {
        "hierarchy": [
          "tgn:1030758",
          "tgn:7002445",
          "tgn:7008104",
          "tgn:1000003",
          "tgn:7008591",
          "tgn:7029392"
        ],
        "placetype": [
          "aat:300008347"
        ],
        "name:en": "Stokenchurch",
        "id": 1030758
      }
    },
    {
      "geometry": {
        "type": "Point",
        "coordinates": [
          -1.2,
          54.466667
        ]
      },
      "type": "Feature",
      "properties": {
        "hierarchy": [
          "tgn:1030759",
          "tgn:7002445",
          "tgn:1000003",
          "tgn:7008166",
          "tgn:7008591",
          "tgn:7029392"
        ],
        "placetype": [
          "aat:300008347"
        ],
        "name:en": "Stokesley",
        "id": 1030759
      }
    }
  ]
}
