{
  "geometry": {
    "type": "Point",
    "coordinates": [
      -88.6833,
      36.5667
    ]
  },
  "type": "Feature",
  "properties": {
    "hierarchy": [
      "tgn:2148342",
      "tgn:1000001",
      "tgn:7012149",
      "tgn:2000792",
      "tgn:7007255",
      "tgn:7029392"
    ],
    "placetype": [
      "aat:300008706"
    ],
    "id": 2148342,
    "name:xx": "Barn Creek"
  }
}
