{
  "geometry": {
    "type": "Point",
    "coordinates": [
      -83.645,
      11.595
    ]
  },
  "type": "Feature",
  "properties": {
    "hierarchy": [
      "tgn:1012190",
      "tgn:7593359",
      "tgn:1000001",
      "tgn:7005562",
      "tgn:7029392"
    ],
    "placetype": [
      "aat:300386846"
    ],
    "id": 1012190,
    "name:xx": "Mono, Punta"
  }
}
