{
  "geometry": {
    "type": "Point",
    "coordinates": [
      -78.5667,
      42.4167
    ]
  },
  "type": "Feature",
  "properties": {
    "hierarchy": [
      "tgn:2410880",
      "tgn:1000001",
      "tgn:1002245",
      "tgn:7012149",
      "tgn:7007568",
      "tgn:7029392"
    ],
    "placetype": [
      "aat:300008706"
    ],
    "id": 2410880,
    "name:xx": "Indian Creek"
  }
}
