{
  "geometry": {
    "type": "Point",
    "coordinates": [
      -85.65,
      31.3167
    ]
  },
  "type": "Feature",
  "properties": {
    "hierarchy": [
      "tgn:2004100",
      "tgn:7002659",
      "tgn:1000001",
      "tgn:7012149",
      "tgn:2000022",
      "tgn:7029392"
    ],
    "placetype": [
      "aat:300008347"
    ],
    "id": 2004100,
    "name:xx": "Kelly"
  }
}
