{
  "geometry": {
    "type": "Point",
    "coordinates": [
      -83.5667,
      35.9667
    ]
  },
  "type": "Feature",
  "properties": {
    "hierarchy": [
      "tgn:2533777",
      "tgn:1000001",
      "tgn:7012149",
      "tgn:2001914",
      "tgn:7007825",
      "tgn:7029392"
    ],
    "placetype": [
      "aat:300008761"
    ],
    "id": 2533777,
    "name:xx": "Mutton Hollow"
  }
}
