{
  "geometry": {
    "type": "Point",
    "coordinates": [
      -135.0833,
      57.4667
    ]
  },
  "type": "Feature",
  "properties": {
    "hierarchy": [
      "tgn:2322735",
      "tgn:7006450",
      "tgn:1000001",
      "tgn:7012149",
      "tgn:2124002",
      "tgn:7029392"
    ],
    "placetype": [
      "aat:300008850"
    ],
    "id": 2322735,
    "name:xx": "False Lindenberg Head"
  }
}
