{
  "geometry": {
    "type": "Point",
    "coordinates": [
      25.9833,
      44.1833
    ]
  },
  "type": "Feature",
  "properties": {
    "hierarchy": [
      "tgn:1050063",
      "tgn:1000003",
      "tgn:7004276",
      "tgn:1000091",
      "tgn:7029392"
    ],
    "placetype": [
      "aat:300008347"
    ],
    "id": 1050063,
    "name:xx": "Călugăreni"
  }
}
