{
  "geometry": {
    "type": "Point",
    "coordinates": [
      -98.6667,
      33.4833
    ]
  },
  "type": "Feature",
  "properties": {
    "hierarchy": [
      "tgn:2291280",
      "tgn:2001934",
      "tgn:1000001",
      "tgn:7012149",
      "tgn:7007826",
      "tgn:7029392"
    ],
    "placetype": [
      "aat:300008706"
    ],
    "id": 2291280,
    "name:xx": "Dogwood Creek"
  }
}
