{
  "geometry": {
    "type": "Point",
    "coordinates": [
      13.4833,
      5.8667
    ]
  },
  "type": "Feature",
  "properties": {
    "hierarchy": [
      "tgn:1088182",
      "tgn:1001245",
      "tgn:7001242",
      "tgn:1000153",
      "tgn:7029392"
    ],
    "placetype": [
      "aat:300008347"
    ],
    "id": 1088182,
    "name:xx": "Djaouro Mbali"
  }
}
