{
  "geometry": {
    "type": "Point",
    "coordinates": [
      30.767033,
      29.38334
    ]
  },
  "type": "Feature",
  "properties": {
    "hierarchy": [
      "tgn:7535882",
      "tgn:7001242",
      "tgn:7001105",
      "tgn:7016833",
      "tgn:7029392"
    ],
    "placetype": [
      "aat:300000745"
    ],
    "name:en": "Fidīmīn al Qiblīyah",
    "id": 7535882
  }
}
