{
  "geometry": {
    "type": "Point",
    "coordinates": [
      -71.2667,
      41.6833
    ]
  },
  "type": "Feature",
  "properties": {
    "hierarchy": [
      "tgn:2663325",
      "tgn:1002202",
      "tgn:1000001",
      "tgn:7012149",
      "tgn:7007711",
      "tgn:7029392"
    ],
    "placetype": [
      "aat:300008706"
    ],
    "id": 2663325,
    "name:xx": "Silver Creek"
  }
}
