{
  "geometry": {
    "type": "Point",
    "coordinates": [
      75.151324,
      28.271844
    ]
  },
  "type": "Feature",
  "properties": {
    "hierarchy": [
      "tgn:7573421",
      "tgn:1000004",
      "tgn:7000198",
      "tgn:7016788",
      "tgn:7029392"
    ],
    "placetype": [
      "aat:300008347"
    ],
    "name:en": "Gāngīyāsar",
    "id": 7573421
  }
}
