{
  "geometry": {
    "type": "Point",
    "coordinates": [
      -118.5833,
      47.3333
    ]
  },
  "type": "Feature",
  "properties": {
    "hierarchy": [
      "tgn:2116354",
      "tgn:1000001",
      "tgn:7012149",
      "tgn:2002247",
      "tgn:7007920",
      "tgn:7029392"
    ],
    "placetype": [
      "aat:300387016"
    ],
    "id": 2116354,
    "name:xx": "Nemo"
  }
}
