{
  "geometry": {
    "type": "Point",
    "coordinates": [
      -78.5167,
      39.1833
    ]
  },
  "type": "Feature",
  "properties": {
    "hierarchy": [
      "tgn:2287815",
      "tgn:1000001",
      "tgn:7012149",
      "tgn:2002265",
      "tgn:7013961",
      "tgn:7029392"
    ],
    "placetype": [
      "aat:300008798"
    ],
    "id": 2287815,
    "name:xx": "Dillons Mountain"
  }
}
