{
  "type": "FeatureCollection",
  "features": [
    {
      "geometry": {
        "type": "Point",
        "coordinates": [
          -3.5,
          39.216667
        ]
      },
      "type": "Feature",
      "properties": {
        "hierarchy": [
          "tgn:4000802",
          "tgn:7002816",
          "tgn:1001647",
          "tgn:1000003",
          "tgn:1000095",
          "tgn:7029392"
        ],
        "placetype": [
          "aat:300008347"
        ],
        "id": 4000802,
        "name:xx": "Arenas de San Juan"
      }
    },
    {
      "geometry": {
        "type": "Point",
        "coordinates": [
          -2.486378,
          43.017238
        ]
      },
      "type": "Feature",
      "properties": {
        "hierarchy": [
          "tgn:4000803",
          "tgn:7007780",
          "tgn:1000003",
          "tgn:7009604",
          "tgn:1000095",
          "tgn:7029392"
        ],
        "placetype": [
          "aat:300008347"
        ],
        "id": 4000803,
        "name:xx": "Arenaza"
      }
    }
  ]
}
