{
  "geometry": {
    "type": "Point",
    "coordinates": [
      -75.7167,
      41.7333
    ]
  },
  "type": "Feature",
  "properties": {
    "hierarchy": [
      "tgn:2524254",
      "tgn:1000001",
      "tgn:7012149",
      "tgn:1002932",
      "tgn:7007710",
      "tgn:7029392"
    ],
    "placetype": [
      "aat:300008798"
    ],
    "id": 2524254,
    "name:xx": "Morgan Hill"
  }
}
