{
  "geometry": {
    "type": "Point",
    "coordinates": [
      -107.05,
      43.8167
    ]
  },
  "type": "Feature",
  "properties": {
    "hierarchy": [
      "tgn:7019822",
      "tgn:1000001",
      "tgn:7012149",
      "tgn:2002374",
      "tgn:7007923",
      "tgn:7029392"
    ],
    "placetype": [
      "aat:300008798"
    ],
    "id": 7019822,
    "name:xx": "Castle Rock, The"
  }
}
