{
  "geometry": {
    "type": "Point",
    "coordinates": [
      -147.9667,
      66.3667
    ]
  },
  "type": "Feature",
  "properties": {
    "hierarchy": [
      "tgn:2476040",
      "tgn:7006450",
      "tgn:1000001",
      "tgn:7012149",
      "tgn:2000089",
      "tgn:7029392"
    ],
    "placetype": [
      "aat:300008680"
    ],
    "id": 2476040,
    "name:xx": "Luke Lake"
  }
}
