{
  "geometry": {
    "type": "Point",
    "coordinates": [
      -112.9333,
      46.0833
    ]
  },
  "type": "Feature",
  "properties": {
    "hierarchy": [
      "tgn:2131049",
      "tgn:1000001",
      "tgn:7012149",
      "tgn:7020792",
      "tgn:7007524",
      "tgn:7029392"
    ],
    "placetype": [
      "aat:300000390"
    ],
    "id": 2131049,
    "name:xx": "Alpha Mine"
  }
}
