{
  "geometry": {
    "type": "Point",
    "coordinates": [
      -83.6333,
      36.2167
    ]
  },
  "type": "Feature",
  "properties": {
    "hierarchy": [
      "tgn:2390563",
      "tgn:1000001",
      "tgn:7012149",
      "tgn:2001865",
      "tgn:7007825",
      "tgn:7029392"
    ],
    "placetype": [
      "aat:300008347"
    ],
    "id": 2390563,
    "name:xx": "Highlands"
  }
}
