{
  "geometry": {
    "type": "Point",
    "coordinates": [
      28.3167,
      48.3667
    ]
  },
  "type": "Feature",
  "properties": {
    "hierarchy": [
      "tgn:1053809",
      "tgn:1000003",
      "tgn:7011999",
      "tgn:7006660",
      "tgn:7029392"
    ],
    "placetype": [
      "aat:300008347"
    ],
    "id": 1053809,
    "name:xx": "Dzyhivka"
  }
}
