{
  "geometry": {
    "type": "Point",
    "coordinates": [
      -83.6667,
      43.2667
    ]
  },
  "type": "Feature",
  "properties": {
    "hierarchy": [
      "tgn:2315297",
      "tgn:1000001",
      "tgn:7012149",
      "tgn:2000997",
      "tgn:7007520",
      "tgn:7029392"
    ],
    "placetype": [
      "aat:300008699"
    ],
    "id": 2315297,
    "name:xx": "Elliot Branch"
  }
}
