{
  "geometry": {
    "type": "Point",
    "coordinates": [
      -87.3667,
      35.7667
    ]
  },
  "type": "Feature",
  "properties": {
    "hierarchy": [
      "tgn:2504412",
      "tgn:1000001",
      "tgn:7012149",
      "tgn:7015666",
      "tgn:7007825",
      "tgn:7029392"
    ],
    "placetype": [
      "aat:300000390"
    ],
    "id": 2504412,
    "name:xx": "Meadows Mine"
  }
}
