{
  "geometry": {
    "type": "Point",
    "coordinates": [
      -90.05,
      36.4167
    ]
  },
  "type": "Feature",
  "properties": {
    "hierarchy": [
      "tgn:2394851",
      "tgn:1000001",
      "tgn:7012149",
      "tgn:2001197",
      "tgn:7007523",
      "tgn:7029392"
    ],
    "placetype": [
      "aat:300008791"
    ],
    "id": 2394851,
    "name:xx": "Holcomb Island"
  }
}
