{
  "geometry": {
    "type": "Point",
    "coordinates": [
      -115.5667,
      42.75
    ]
  },
  "type": "Feature",
  "properties": {
    "hierarchy": [
      "tgn:2574727",
      "tgn:1000001",
      "tgn:7012149",
      "tgn:2000488",
      "tgn:7007250",
      "tgn:7029392"
    ],
    "placetype": [
      "aat:300008798"
    ],
    "id": 2574727,
    "name:xx": "Pence Butte"
  }
}
