{
  "geometry": {
    "type": "Point",
    "coordinates": [
      -123.0667,
      38.6833
    ]
  },
  "type": "Feature",
  "properties": {
    "hierarchy": [
      "tgn:2653129",
      "tgn:1000001",
      "tgn:7012149",
      "tgn:7007157",
      "tgn:7014516",
      "tgn:7029392"
    ],
    "placetype": [
      "aat:300008706"
    ],
    "id": 2653129,
    "name:xx": "Seven Oaks Creek"
  }
}
