{
  "geometry": {
    "type": "Point",
    "coordinates": [
      -91.8833,
      31.05
    ]
  },
  "type": "Feature",
  "properties": {
    "hierarchy": [
      "tgn:2629269",
      "tgn:2000858",
      "tgn:1000001",
      "tgn:7012149",
      "tgn:7007256",
      "tgn:7029392"
    ],
    "placetype": [
      "aat:300008680"
    ],
    "id": 2629269,
    "name:xx": "Roseaux, Lac aux"
  }
}
