{
  "geometry": {
    "type": "Point",
    "coordinates": [
      -90.5667,
      34.5667
    ]
  },
  "type": "Feature",
  "properties": {
    "hierarchy": [
      "tgn:2597536",
      "tgn:1000001",
      "tgn:7016172",
      "tgn:7012149",
      "tgn:2000158",
      "tgn:7029392"
    ],
    "placetype": [
      "aat:300008850"
    ],
    "id": 2597536,
    "name:xx": "Prairie Point"
  }
}
