{
  "geometry": {
    "type": "Point",
    "coordinates": [
      -89.6167,
      36.0333
    ]
  },
  "type": "Feature",
  "properties": {
    "hierarchy": [
      "tgn:2468660",
      "tgn:1000001",
      "tgn:7012149",
      "tgn:2001859",
      "tgn:7007825",
      "tgn:7029392"
    ],
    "placetype": [
      "aat:300008905"
    ],
    "id": 2468660,
    "name:xx": "Long Pond"
  }
}
