{
  "type": "FeatureCollection",
  "features": [
    {
      "geometry": {
        "type": "Point",
        "coordinates": [
          -77.5,
          40
        ]
      },
      "type": "Feature",
      "properties": {
        "hierarchy": [
          "tgn:2090510",
          "tgn:1000001",
          "tgn:7012149",
          "tgn:1002387",
          "tgn:7007710",
          "tgn:7029392"
        ],
        "placetype": [
          "aat:300008347"
        ],
        "id": 2090510,
        "name:xx": "Mainsville"
      }
    },
    {
      "geometry": {
        "type": "Point",
        "coordinates": [
          -76.3667,
          40.9667
        ]
      },
      "type": "Feature",
      "properties": {
        "hierarchy": [
          "tgn:2090511",
          "tgn:1000001",
          "tgn:1002294",
          "tgn:7012149",
          "tgn:7007710",
          "tgn:7029392"
        ],
        "placetype": [
          "aat:300008347"
        ],
        "id": 2090511,
        "name:xx": "Mainville"
      }
    },
    {
      "geometry": {
        "type": "Point",
        "coordinates": [
          -77.5,
          40.6167
        ]
      },
      "type": "Feature",
      "properties": {
        "hierarchy": [
          "tgn:2090512",
          "tgn:1000001",
          "tgn:7012149",
          "tgn:1002669",
          "tgn:7007710",
          "tgn:7029392"
        ],
        "placetype": [
          "aat:300008347"
        ],
        "id": 2090512,
        "name:xx": "Maitland"
      }
    },
    {
      "geometry": {
        "type": "Point",
        "coordinates": [
          -76.9,
          40.6167
        ]
      },
      "type": "Feature",
      "properties": {
        "hierarchy": [
          "tgn:2090514",
          "tgn:1000001",
          "tgn:7012149",
          "tgn:1002732",
          "tgn:7007710",
          "tgn:7029392"
        ],
        "placetype": [
          "aat:300008347",
          "aat:300387210"
        ],
        "id": 2090514,
        "name:xx": "Malta"
      }
    },
    {
      "geometry": {
        "type": "Point",
        "coordinates": [
          -75.5,
          40.0333
        ]
      },
      "type": "Feature",
      "properties": {
        "hierarchy": [
          "tgn:2090515",
          "tgn:1000001",
          "tgn:1002266",
          "tgn:7012149",
          "tgn:7007710",
          "tgn:7029392"
        ],
        "placetype": [
          "aat:300008347"
        ],
        "id": 2090515,
        "name:xx": "Malvern"
      }
    },
    {
      "geometry": {
        "type": "Point",
        "coordinates": [
          -79.45,
          40.2
        ]
      },
      "type": "Feature",
      "properties": {
        "hierarchy": [
          "tgn:2090516",
          "tgn:1000001",
          "tgn:7012149",
          "tgn:1003017",
          "tgn:7007710",
          "tgn:7029392"
        ],
        "placetype": [
          "aat:300008347"
        ],
        "id": 2090516,
        "name:xx": "Mammoth"
      }
    },
    {
      "geometry": {
        "type": "Point",
        "coordinates": [
          -79.5833,
          40.4667
        ]
      },
      "type": "Feature",
      "properties": {
        "hierarchy": [
          "tgn:2090517",
          "tgn:1000001",
          "tgn:7012149",
          "tgn:1003017",
          "tgn:7007710",
          "tgn:7029392"
        ],
        "placetype": [
          "aat:300008347"
        ],
        "id": 2090517,
        "name:xx": "Mamont"
      }
    },
    {
      "geometry": {
        "type": "Point",
        "coordinates": [
          -76.7,
          40.3833
        ]
      },
      "type": "Feature",
      "properties": {
        "hierarchy": [
          "tgn:2090518",
          "tgn:1000001",
          "tgn:1002318",
          "tgn:7012149",
          "tgn:7007710",
          "tgn:7029392"
        ],
        "placetype": [
          "aat:300008347",
          "aat:300387210"
        ],
        "id": 2090518,
        "name:xx": "Manada Gap"
      }
    },
    {
      "geometry": {
        "type": "Point",
        "coordinates": [
          -75.7167,
          40.3833
        ]
      },
      "type": "Feature",
      "properties": {
        "hierarchy": [
          "tgn:2090519",
          "tgn:1000001",
          "tgn:7013387",
          "tgn:7012149",
          "tgn:7007710",
          "tgn:7029392"
        ],
        "placetype": [
          "aat:300008347"
        ],
        "id": 2090519,
        "name:xx": "Manatawny"
      }
    }
  ]
}
