{
  "geometry": {
    "type": "Point",
    "coordinates": [
      -82.2667,
      30.25
    ]
  },
  "type": "Feature",
  "properties": {
    "hierarchy": [
      "tgn:2021172",
      "tgn:2000257",
      "tgn:1000001",
      "tgn:7012149",
      "tgn:7007240",
      "tgn:7029392"
    ],
    "placetype": [
      "aat:300008347"
    ],
    "id": 2021172,
    "name:xx": "Sanderson"
  }
}
