{
  "geometry": {
    "type": "Point",
    "coordinates": [
      32.95,
      23.333333
    ]
  },
  "type": "Feature",
  "properties": {
    "hierarchy": [
      "tgn:7537427",
      "tgn:7001242",
      "tgn:7016833",
      "tgn:7000122",
      "tgn:7029392"
    ],
    "placetype": [
      "aat:300185707"
    ],
    "name:en": "Sharaf ad Dīn, Khawr",
    "id": 7537427
  }
}
