{
  "type": "FeatureCollection",
  "features": [
    {
      "geometry": {
        "type": "Point",
        "coordinates": [
          32.703889,
          29.593889
        ]
      },
      "type": "Feature",
      "properties": {
        "hierarchy": [
          "tgn:7528530",
          "tgn:7001242",
          "tgn:7016833",
          "tgn:7001336",
          "tgn:7029392"
        ],
        "placetype": [
          "aat:300000401"
        ],
        "name:en": "Sudr",
        "id": 7528530
      }
    },
    {
      "geometry": {
        "type": "Point",
        "coordinates": [
          30.65,
          31.383333
        ]
      },
      "type": "Feature",
      "properties": {
        "hierarchy": [
          "tgn:7528533",
          "tgn:7001242",
          "tgn:7016833",
          "tgn:1001335",
          "tgn:7029392"
        ],
        "placetype": [
          "aat:300008791"
        ],
        "name:en": "Suddah, Jazā'ir as",
        "id": 7528533
      }
    },
    {
      "geometry": {
        "type": "Point",
        "coordinates": [
          30.522222,
          31.417222
        ]
      },
      "type": "Feature",
      "properties": {
        "hierarchy": [
          "tgn:7528534",
          "tgn:7001242",
          "tgn:7016833",
          "tgn:1001335",
          "tgn:7029392"
        ],
        "placetype": [
          "aat:300008903"
        ],
        "name:en": "Suddah, Gharrāqat as",
        "id": 7528534
      }
    },
    {
      "geometry": {
        "type": "Point",
        "coordinates": [
          33.646933,
          25.970961
        ]
      },
      "type": "Feature",
      "properties": {
        "hierarchy": [
          "tgn:7528535",
          "tgn:7001242",
          "tgn:7001311",
          "tgn:7016833",
          "tgn:7029392"
        ],
        "placetype": [
          "aat:300006207"
        ],
        "name:en": "Bi'r as Sudd",
        "id": 7528535
      }
    },
    {
      "geometry": {
        "type": "Point",
        "coordinates": [
          29.644689,
          30.276404
        ]
      },
      "type": "Feature",
      "properties": {
        "hierarchy": [
          "tgn:7528536",
          "tgn:7001242",
          "tgn:1001075",
          "tgn:7016833",
          "tgn:7029392"
        ],
        "placetype": [
          "aat:300008777"
        ],
        "name:en": "Sūd, Al Quwayrāt as",
        "id": 7528536
      }
    },
    {
      "geometry": {
        "type": "Point",
        "coordinates": [
          32.579284,
          22.747167
        ]
      },
      "type": "Feature",
      "properties": {
        "hierarchy": [
          "tgn:7528537",
          "tgn:7001242",
          "tgn:7001311",
          "tgn:7016833",
          "tgn:7029392"
        ],
        "placetype": [
          "aat:300379998"
        ],
        "name:en": "Subū', Wādī as",
        "id": 7528537
      }
    },
    {
      "geometry": {
        "type": "Point",
        "coordinates": [
          32.732129,
          22.748297
        ]
      },
      "type": "Feature",
      "properties": {
        "hierarchy": [
          "tgn:7528538",
          "tgn:7001242",
          "tgn:7001311",
          "tgn:7016833",
          "tgn:7029392"
        ],
        "placetype": [
          "aat:300008777"
        ],
        "name:en": "Subū', Naşb as",
        "id": 7528538
      }
    },
    {
      "geometry": {
        "type": "Point",
        "coordinates": [
          32.894749,
          22.061834
        ]
      },
      "type": "Feature",
      "properties": {
        "hierarchy": [
          "tgn:7528539",
          "tgn:7001242",
          "tgn:7001311",
          "tgn:7016833",
          "tgn:7029392"
        ],
        "placetype": [
          "aat:300259572"
        ],
        "name:en": "Subū', Bāb as",
        "id": 7528539
      }
    }
  ]
}
