{
  "geometry": {
    "type": "Point",
    "coordinates": [
      34.5333,
      -19.5333
    ]
  },
  "type": "Feature",
  "properties": {
    "hierarchy": [
      "tgn:1091672",
      "tgn:7001242",
      "tgn:7000400",
      "tgn:1000180",
      "tgn:7029392"
    ],
    "placetype": [
      "aat:300008347"
    ],
    "id": 1091672,
    "name:xx": "Ponte do Pungue"
  }
}
