{
  "geometry": {
    "type": "Point",
    "coordinates": [
      74.08901,
      33.792784
    ]
  },
  "type": "Feature",
  "properties": {
    "hierarchy": [
      "tgn:7588673",
      "tgn:1000004",
      "tgn:7000198",
      "tgn:7000799",
      "tgn:7029392"
    ],
    "placetype": [
      "aat:300008347"
    ],
    "name:en": "Mangiāl",
    "id": 7588673
  }
}
