{
  "geometry": {
    "type": "Point",
    "coordinates": [
      -115.6833,
      48.9667
    ]
  },
  "type": "Feature",
  "properties": {
    "hierarchy": [
      "tgn:2441901",
      "tgn:1000001",
      "tgn:7012149",
      "tgn:2001286",
      "tgn:7007524",
      "tgn:7029392"
    ],
    "placetype": [
      "aat:300008706"
    ],
    "id": 2441901,
    "name:xx": "Koo Koo Creek"
  }
}
