{
  "geometry": {
    "type": "Point",
    "coordinates": [
      -88.45,
      44.1333
    ]
  },
  "type": "Feature",
  "properties": {
    "hierarchy": [
      "tgn:2490943",
      "tgn:1000001",
      "tgn:7012149",
      "tgn:2002363",
      "tgn:7007922",
      "tgn:7029392"
    ],
    "placetype": [
      "aat:300132316"
    ],
    "id": 2490943,
    "name:xx": "Mansur Bay"
  }
}
