{
  "geometry": {
    "type": "Point",
    "coordinates": [
      -89.0333,
      37.1667
    ]
  },
  "type": "Feature",
  "properties": {
    "hierarchy": [
      "tgn:2733087",
      "tgn:2000767",
      "tgn:1000001",
      "tgn:7012149",
      "tgn:7007255",
      "tgn:7029392"
    ],
    "placetype": [
      "aat:300006191"
    ],
    "id": 2733087,
    "name:xx": "Turkey Lake"
  }
}
