{
  "geometry": {
    "type": "Point",
    "coordinates": [
      -107.3167,
      44.8333
    ]
  },
  "type": "Feature",
  "properties": {
    "hierarchy": [
      "tgn:2725160",
      "tgn:1000001",
      "tgn:7012149",
      "tgn:2002381",
      "tgn:7007923",
      "tgn:7029392"
    ],
    "placetype": [
      "aat:300008746"
    ],
    "id": 2725160,
    "name:xx": "Tongue River Cave"
  }
}
