{
  "type": "FeatureCollection",
  "features": [
    {
      "geometry": {
        "type": "Point",
        "coordinates": [
          -3.8,
          55.983333
        ]
      },
      "type": "Feature",
      "properties": {
        "hierarchy": [
          "tgn:7444580",
          "tgn:7002444",
          "tgn:1000003",
          "tgn:7019106",
          "tgn:7008591",
          "tgn:7029392"
        ],
        "placetype": [
          "aat:300005433"
        ],
        "name:en": "Westerglen",
        "id": 7444580
      }
    },
    {
      "geometry": {
        "type": "Point",
        "coordinates": [
          -3.383333,
          57.2
        ]
      },
      "type": "Feature",
      "properties": {
        "hierarchy": [
          "tgn:7444582",
          "tgn:7002444",
          "tgn:1000003",
          "tgn:5000451",
          "tgn:7008591",
          "tgn:7029392"
        ],
        "placetype": [
          "aat:300008347"
        ],
        "name:en": "Wester Gaulrig",
        "id": 7444582
      }
    },
    {
      "geometry": {
        "type": "Point",
        "coordinates": [
          1.166667,
          52.083333
        ]
      },
      "type": "Feature",
      "properties": {
        "hierarchy": [
          "tgn:7444583",
          "tgn:7002445",
          "tgn:1000003",
          "tgn:7008185",
          "tgn:7008591",
          "tgn:7029392"
        ],
        "placetype": [
          "aat:300008347"
        ],
        "name:en": "Westerfield",
        "id": 7444583
      }
    },
    {
      "geometry": {
        "type": "Point",
        "coordinates": [
          -4.3,
          57.866667
        ]
      },
      "type": "Feature",
      "properties": {
        "hierarchy": [
          "tgn:7444584",
          "tgn:7002444",
          "tgn:1000003",
          "tgn:7008082",
          "tgn:7008591",
          "tgn:7029392"
        ],
        "placetype": [
          "aat:300386846"
        ],
        "name:en": "Wester Fearn Point",
        "id": 7444584
      }
    },
    {
      "geometry": {
        "type": "Point",
        "coordinates": [
          -4.3,
          57.85
        ]
      },
      "type": "Feature",
      "properties": {
        "hierarchy": [
          "tgn:7444585",
          "tgn:7002444",
          "tgn:1000003",
          "tgn:7008082",
          "tgn:7008591",
          "tgn:7029392"
        ],
        "placetype": [
          "aat:300008699"
        ],
        "name:en": "Wester Fearn Burn",
        "id": 7444585
      }
    },
    {
      "geometry": {
        "type": "Point",
        "coordinates": [
          -4.3,
          57.85
        ]
      },
      "type": "Feature",
      "properties": {
        "hierarchy": [
          "tgn:7444586",
          "tgn:7002444",
          "tgn:1000003",
          "tgn:7008082",
          "tgn:7008591",
          "tgn:7029392"
        ],
        "placetype": [
          "aat:300008347"
        ],
        "name:en": "Wester Fearn",
        "id": 7444586
      }
    },
    {
      "geometry": {
        "type": "Point",
        "coordinates": [
          -0.966667,
          54.433333
        ]
      },
      "type": "Feature",
      "properties": {
        "hierarchy": [
          "tgn:7444588",
          "tgn:7002445",
          "tgn:1000003",
          "tgn:7008166",
          "tgn:7008591",
          "tgn:7029392"
        ],
        "placetype": [
          "aat:300008347"
        ],
        "name:en": "Westerdale",
        "id": 7444588
      }
    },
    {
      "geometry": {
        "type": "Point",
        "coordinates": [
          -3.883333,
          58.033333
        ]
      },
      "type": "Feature",
      "properties": {
        "hierarchy": [
          "tgn:7444589",
          "tgn:7002444",
          "tgn:1000003",
          "tgn:7008082",
          "tgn:7008591",
          "tgn:7029392"
        ],
        "placetype": [
          "aat:300008347"
        ],
        "name:en": "Wester Clynekirkton",
        "id": 7444589
      }
    }
  ]
}
