{
  "type": "FeatureCollection",
  "features": [
    {
      "geometry": {
        "type": "Point",
        "coordinates": [
          -86.2667,
          39.7
        ]
      },
      "type": "Feature",
      "properties": {
        "hierarchy": [
          "tgn:2454700",
          "tgn:1000001",
          "tgn:7012149",
          "tgn:1002633",
          "tgn:7007252",
          "tgn:7029392"
        ],
        "placetype": [
          "aat:300008706"
        ],
        "id": 2454700,
        "name:xx": "Little Dollar Hide Creek"
      }
    },
    {
      "geometry": {
        "type": "Point",
        "coordinates": [
          -85.3,
          46.1833
        ]
      },
      "type": "Feature",
      "properties": {
        "hierarchy": [
          "tgn:2454701",
          "tgn:1000001",
          "tgn:7012149",
          "tgn:2000973",
          "tgn:7007520",
          "tgn:7029392"
        ],
        "placetype": [
          "aat:300008680"
        ],
        "id": 2454701,
        "name:xx": "Little Dollar Lake"
      }
    },
    {
      "geometry": {
        "type": "Point",
        "coordinates": [
          -111.5833,
          40.6167
        ]
      },
      "type": "Feature",
      "properties": {
        "hierarchy": [
          "tgn:2454702",
          "tgn:1000001",
          "tgn:7012149",
          "tgn:2002118",
          "tgn:7007827",
          "tgn:7029392"
        ],
        "placetype": [
          "aat:300000390"
        ],
        "id": 2454702,
        "name:xx": "Little Dollie Tunnel"
      }
    },
    {
      "geometry": {
        "type": "Point",
        "coordinates": [
          -82.7167,
          28.1
        ]
      },
      "type": "Feature",
      "properties": {
        "hierarchy": [
          "tgn:2454703",
          "tgn:1000001",
          "tgn:7012149",
          "tgn:1002790",
          "tgn:7007240",
          "tgn:7029392"
        ],
        "placetype": [
          "aat:300132316"
        ],
        "id": 2454703,
        "name:xx": "Little Dolly Bay"
      }
    },
    {
      "geometry": {
        "type": "Point",
        "coordinates": [
          -108.8,
          38.8667
        ]
      },
      "type": "Feature",
      "properties": {
        "hierarchy": [
          "tgn:2454704",
          "tgn:1000001",
          "tgn:7012149",
          "tgn:7029392"
        ],
        "placetype": [
          "aat:300008707"
        ],
        "id": 2454704,
        "name:xx": "Little Dolores River"
      }
    },
    {
      "geometry": {
        "type": "Point",
        "coordinates": [
          -104.45,
          37.5333
        ]
      },
      "type": "Feature",
      "properties": {
        "hierarchy": [
          "tgn:2454705",
          "tgn:1000001",
          "tgn:7012149",
          "tgn:2000227",
          "tgn:7007158",
          "tgn:7029392"
        ],
        "placetype": [
          "aat:300008798"
        ],
        "id": 2454705,
        "name:xx": "Little Dome"
      }
    },
    {
      "geometry": {
        "type": "Point",
        "coordinates": [
          -71.05,
          42.2333
        ]
      },
      "type": "Feature",
      "properties": {
        "hierarchy": [
          "tgn:2454706",
          "tgn:1000001",
          "tgn:1002724",
          "tgn:7012149",
          "tgn:7007517",
          "tgn:7029392"
        ],
        "placetype": [
          "aat:300008798"
        ],
        "id": 2454706,
        "name:xx": "Little Dome"
      }
    },
    {
      "geometry": {
        "type": "Point",
        "coordinates": [
          -108.85,
          43.4
        ]
      },
      "type": "Feature",
      "properties": {
        "hierarchy": [
          "tgn:2454707",
          "tgn:1000001",
          "tgn:7012149",
          "tgn:2002371",
          "tgn:7007923",
          "tgn:7029392"
        ],
        "placetype": [
          "aat:300008798"
        ],
        "id": 2454707,
        "name:xx": "Little Dome"
      }
    },
    {
      "geometry": {
        "type": "Point",
        "coordinates": [
          -155.3,
          64.25
        ]
      },
      "type": "Feature",
      "properties": {
        "hierarchy": [
          "tgn:2454708",
          "tgn:7006450",
          "tgn:1000001",
          "tgn:7012149",
          "tgn:2000089",
          "tgn:7029392"
        ],
        "placetype": [
          "aat:300008706"
        ],
        "id": 2454708,
        "name:xx": "Little Dome Creek"
      }
    },
    {
      "geometry": {
        "type": "Point",
        "coordinates": [
          -147.9833,
          64.8833
        ]
      },
      "type": "Feature",
      "properties": {
        "hierarchy": [
          "tgn:2454709",
          "tgn:7006450",
          "tgn:1000001",
          "tgn:7019674",
          "tgn:7012149",
          "tgn:7029392"
        ],
        "placetype": [
          "aat:300008706"
        ],
        "id": 2454709,
        "name:xx": "Little Dome Creek"
      }
    }
  ]
}
