{
  "geometry": {
    "type": "Point",
    "coordinates": [
      -85.6667,
      33.1833
    ]
  },
  "type": "Feature",
  "properties": {
    "hierarchy": [
      "tgn:2372589",
      "tgn:7002659",
      "tgn:1000001",
      "tgn:2000013",
      "tgn:7012149",
      "tgn:7029392"
    ],
    "placetype": [
      "aat:300008706"
    ],
    "id": 2372589,
    "name:xx": "Hall Creek"
  }
}
