{
  "geometry": {
    "type": "Point",
    "coordinates": [
      89.4333,
      23.8667
    ]
  },
  "type": "Feature",
  "properties": {
    "hierarchy": [
      "tgn:1065924",
      "tgn:1000004",
      "tgn:7000191",
      "tgn:1000105",
      "tgn:7029392"
    ],
    "placetype": [
      "aat:300008347"
    ],
    "id": 1065924,
    "name:xx": "Sātbāria"
  }
}
