{
  "geometry": {
    "type": "Point",
    "coordinates": [
      -86.1833,
      35.65
    ]
  },
  "type": "Feature",
  "properties": {
    "hierarchy": [
      "tgn:2404142",
      "tgn:1000001",
      "tgn:7012149",
      "tgn:2001852",
      "tgn:7007825",
      "tgn:7029392"
    ],
    "placetype": [
      "aat:300008761"
    ],
    "id": 2404142,
    "name:xx": "Howland Hollow"
  }
}
