{
  "geometry": {
    "type": "Point",
    "coordinates": [
      -2.5667,
      50.95
    ]
  },
  "type": "Feature",
  "properties": {
    "hierarchy": [
      "tgn:7025871",
      "tgn:7002445",
      "tgn:1000003",
      "tgn:7011961",
      "tgn:7008591",
      "tgn:7029392"
    ],
    "placetype": [
      "aat:300008347"
    ],
    "id": 7025871,
    "name:ang": "Contone"
  }
}
