{
  "geometry": {
    "type": "Point",
    "coordinates": [
      -119.2833,
      44.1833
    ]
  },
  "type": "Feature",
  "properties": {
    "hierarchy": [
      "tgn:2785884",
      "tgn:1000001",
      "tgn:7012149",
      "tgn:2001708",
      "tgn:7007708",
      "tgn:7029392"
    ],
    "placetype": [
      "aat:300000390"
    ],
    "id": 2785884,
    "name:xx": "York and Rannels Mine"
  }
}
