{
  "geometry": {
    "type": "Point",
    "coordinates": [
      9.75,
      47.4667
    ]
  },
  "type": "Feature",
  "properties": {
    "hierarchy": [
      "tgn:1026247",
      "tgn:7018001",
      "tgn:1000003",
      "tgn:1000062",
      "tgn:7029392"
    ],
    "placetype": [
      "aat:300008347"
    ],
    "id": 1026247,
    "name:xx": "Wolfurt"
  }
}
