{
  "geometry": {
    "type": "Point",
    "coordinates": [
      -89.2833,
      45.05
    ]
  },
  "type": "Feature",
  "properties": {
    "hierarchy": [
      "tgn:2673372",
      "tgn:1000001",
      "tgn:7012149",
      "tgn:2002336",
      "tgn:7007922",
      "tgn:7029392"
    ],
    "placetype": [
      "aat:300008347"
    ],
    "id": 2673372,
    "name:xx": "Snell"
  }
}
