{
  "geometry": {
    "type": "Point",
    "coordinates": [
      30.916667,
      28.733333
    ]
  },
  "type": "Feature",
  "properties": {
    "hierarchy": [
      "tgn:7522260",
      "tgn:7001242",
      "tgn:7001311",
      "tgn:7016833",
      "tgn:7029392"
    ],
    "placetype": [
      "aat:300008777"
    ],
    "name:en": "Al Ḩarā'ib",
    "id": 7522260
  }
}
