{
  "geometry": {
    "type": "Point",
    "coordinates": [
      -112.4833,
      42.7333
    ]
  },
  "type": "Feature",
  "properties": {
    "hierarchy": [
      "tgn:2590481",
      "tgn:1000001",
      "tgn:7012149",
      "tgn:7007250",
      "tgn:7029392"
    ],
    "placetype": [
      "aat:300008761"
    ],
    "id": 2590481,
    "name:xx": "Pole Canyon"
  }
}
