{
  "type": "FeatureCollection",
  "features": [
    {
      "geometry": {
        "type": "Point",
        "coordinates": [
          -105.2833,
          33.2
        ]
      },
      "type": "Feature",
      "properties": {
        "hierarchy": [
          "tgn:2281170",
          "tgn:1000001",
          "tgn:7012149",
          "tgn:2001442",
          "tgn:7007566",
          "tgn:7029392"
        ],
        "placetype": [
          "aat:300008680"
        ],
        "id": 2281170,
        "name:xx": "Deep Lake"
      }
    },
    {
      "geometry": {
        "type": "Point",
        "coordinates": [
          -104.8333,
          33.2333
        ]
      },
      "type": "Feature",
      "properties": {
        "hierarchy": [
          "tgn:2281171",
          "tgn:1000001",
          "tgn:2001430",
          "tgn:7012149",
          "tgn:7007566",
          "tgn:7029392"
        ],
        "placetype": [
          "aat:300008680"
        ],
        "id": 2281171,
        "name:xx": "Deep Lake"
      }
    },
    {
      "geometry": {
        "type": "Point",
        "coordinates": [
          -105.1167,
          36.25
        ]
      },
      "type": "Feature",
      "properties": {
        "hierarchy": [
          "tgn:2281172",
          "tgn:1000001",
          "tgn:2001432",
          "tgn:7012149",
          "tgn:7007566",
          "tgn:7029392"
        ],
        "placetype": [
          "aat:300008680"
        ],
        "id": 2281172,
        "name:xx": "Deep Lake"
      }
    },
    {
      "geometry": {
        "type": "Point",
        "coordinates": [
          -106.3333,
          36.45
        ]
      },
      "type": "Feature",
      "properties": {
        "hierarchy": [
          "tgn:2281173",
          "tgn:1000001",
          "tgn:7012149",
          "tgn:2001449",
          "tgn:7007566",
          "tgn:7029392"
        ],
        "placetype": [
          "aat:300008680"
        ],
        "id": 2281173,
        "name:xx": "Deep Lake"
      }
    },
    {
      "geometry": {
        "type": "Point",
        "coordinates": [
          -75.0667,
          43.4333
        ]
      },
      "type": "Feature",
      "properties": {
        "hierarchy": [
          "tgn:2281174",
          "tgn:1000001",
          "tgn:7012149",
          "tgn:1002472",
          "tgn:7007568",
          "tgn:7029392"
        ],
        "placetype": [
          "aat:300008680"
        ],
        "id": 2281174,
        "name:xx": "Deep Lake"
      }
    },
    {
      "geometry": {
        "type": "Point",
        "coordinates": [
          -74.65,
          43.6167
        ]
      },
      "type": "Feature",
      "properties": {
        "hierarchy": [
          "tgn:2281175",
          "tgn:1000001",
          "tgn:7012149",
          "tgn:1002440",
          "tgn:7007568",
          "tgn:7029392"
        ],
        "placetype": [
          "aat:300008680"
        ],
        "id": 2281175,
        "name:xx": "Deep Lake"
      }
    },
    {
      "geometry": {
        "type": "Point",
        "coordinates": [
          -100.2667,
          48.9167
        ]
      },
      "type": "Feature",
      "properties": {
        "hierarchy": [
          "tgn:2281176",
          "tgn:7020393",
          "tgn:1000001",
          "tgn:7012149",
          "tgn:7007705",
          "tgn:7029392"
        ],
        "placetype": [
          "aat:300008680"
        ],
        "id": 2281176,
        "name:xx": "Deep Lake"
      }
    },
    {
      "geometry": {
        "type": "Point",
        "coordinates": [
          -122.1833,
          42.5667
        ]
      },
      "type": "Feature",
      "properties": {
        "hierarchy": [
          "tgn:2281177",
          "tgn:1000001",
          "tgn:7012149",
          "tgn:2001714",
          "tgn:7007708",
          "tgn:7029392"
        ],
        "placetype": [
          "aat:300008680"
        ],
        "id": 2281177,
        "name:xx": "Deep Lake"
      }
    },
    {
      "geometry": {
        "type": "Point",
        "coordinates": [
          -123,
          45.0667
        ]
      },
      "type": "Feature",
      "properties": {
        "hierarchy": [
          "tgn:2281178",
          "tgn:1000001",
          "tgn:7012149",
          "tgn:1002636",
          "tgn:7007708",
          "tgn:7029392"
        ],
        "placetype": [
          "aat:300008680"
        ],
        "id": 2281178,
        "name:xx": "Deep Lake"
      }
    },
    {
      "geometry": {
        "type": "Point",
        "coordinates": [
          -122.7833,
          45.8333
        ]
      },
      "type": "Feature",
      "properties": {
        "hierarchy": [
          "tgn:2281179",
          "tgn:1000001",
          "tgn:1002293",
          "tgn:7012149",
          "tgn:7007708",
          "tgn:7029392"
        ],
        "placetype": [
          "aat:300008680"
        ],
        "id": 2281179,
        "name:xx": "Deep Lake"
      }
    }
  ]
}
