{
  "geometry": {
    "type": "Point",
    "coordinates": [
      -149.6167,
      59.5667
    ]
  },
  "type": "Feature",
  "properties": {
    "hierarchy": [
      "tgn:2465768",
      "tgn:7006450",
      "tgn:1000001",
      "tgn:7019698",
      "tgn:7012149",
      "tgn:7029392"
    ],
    "placetype": [
      "aat:300008791"
    ],
    "id": 2465768,
    "name:xx": "Lone Rock"
  }
}
