{
  "geometry": {
    "type": "Point",
    "coordinates": [
      -100.1667,
      53.25
    ]
  },
  "type": "Feature",
  "properties": {
    "hierarchy": [
      "tgn:1119574",
      "tgn:7005685",
      "tgn:1000001",
      "tgn:7005734",
      "tgn:7029392"
    ],
    "placetype": [
      "aat:300006191"
    ],
    "id": 1119574,
    "name:xx": "Cedar Lake"
  }
}
