{
  "type": "FeatureCollection",
  "features": [
    {
      "geometry": {
        "type": "Point",
        "coordinates": [
          -148.05,
          63.8667
        ]
      },
      "type": "Feature",
      "properties": {
        "hierarchy": [
          "tgn:2255820",
          "tgn:7006450",
          "tgn:1000001",
          "tgn:7030547",
          "tgn:7012149",
          "tgn:7029392"
        ],
        "placetype": [
          "aat:300008706"
        ],
        "id": 2255820,
        "name:xx": "Copper Creek"
      }
    },
    {
      "geometry": {
        "type": "Point",
        "coordinates": [
          -110.4667,
          32.75
        ]
      },
      "type": "Feature",
      "properties": {
        "hierarchy": [
          "tgn:2255821",
          "tgn:1000001",
          "tgn:7006451",
          "tgn:7012149",
          "tgn:2000101",
          "tgn:7029392"
        ],
        "placetype": [
          "aat:300008347"
        ],
        "id": 2255821,
        "name:xx": "Copper Creek"
      }
    },
    {
      "geometry": {
        "type": "Point",
        "coordinates": [
          -113.9,
          34.8667
        ]
      },
      "type": "Feature",
      "properties": {
        "hierarchy": [
          "tgn:2255822",
          "tgn:1000001",
          "tgn:7006451",
          "tgn:7012149",
          "tgn:2000098",
          "tgn:7029392"
        ],
        "placetype": [
          "aat:300008706"
        ],
        "id": 2255822,
        "name:xx": "Copper Creek"
      }
    },
    {
      "geometry": {
        "type": "Point",
        "coordinates": [
          -110.9667,
          32.55
        ]
      },
      "type": "Feature",
      "properties": {
        "hierarchy": [
          "tgn:2255823",
          "tgn:1000001",
          "tgn:7006451",
          "tgn:7012149",
          "tgn:2000101",
          "tgn:7029392"
        ],
        "placetype": [
          "aat:300008706"
        ],
        "id": 2255823,
        "name:xx": "Copper Creek"
      }
    },
    {
      "geometry": {
        "type": "Point",
        "coordinates": [
          -112.5333,
          34.4833
        ]
      },
      "type": "Feature",
      "properties": {
        "hierarchy": [
          "tgn:2255824",
          "tgn:1000001",
          "tgn:7006451",
          "tgn:7012149",
          "tgn:2000103",
          "tgn:7029392"
        ],
        "placetype": [
          "aat:300008706"
        ],
        "id": 2255824,
        "name:xx": "Copper Creek"
      }
    },
    {
      "geometry": {
        "type": "Point",
        "coordinates": [
          -110.4,
          32.7333
        ]
      },
      "type": "Feature",
      "properties": {
        "hierarchy": [
          "tgn:2255825",
          "tgn:1000001",
          "tgn:7006451",
          "tgn:7012149",
          "tgn:7029392"
        ],
        "placetype": [
          "aat:300008706"
        ],
        "id": 2255825,
        "name:xx": "Copper Creek"
      }
    },
    {
      "geometry": {
        "type": "Point",
        "coordinates": [
          -118.5667,
          36.8667
        ]
      },
      "type": "Feature",
      "properties": {
        "hierarchy": [
          "tgn:2255826",
          "tgn:1000001",
          "tgn:7012149",
          "tgn:1002392",
          "tgn:7007157",
          "tgn:7029392"
        ],
        "placetype": [
          "aat:300008706"
        ],
        "id": 2255826,
        "name:xx": "Copper Creek"
      }
    },
    {
      "geometry": {
        "type": "Point",
        "coordinates": [
          -120.8667,
          38.3333
        ]
      },
      "type": "Feature",
      "properties": {
        "hierarchy": [
          "tgn:2255827",
          "tgn:1002146",
          "tgn:1000001",
          "tgn:7012149",
          "tgn:7007157",
          "tgn:7029392"
        ],
        "placetype": [
          "aat:300008706"
        ],
        "id": 2255827,
        "name:xx": "Copper Creek"
      }
    },
    {
      "geometry": {
        "type": "Point",
        "coordinates": [
          -122.6333,
          41.0667
        ]
      },
      "type": "Feature",
      "properties": {
        "hierarchy": [
          "tgn:2255828",
          "tgn:1000001",
          "tgn:7012149",
          "tgn:7007157",
          "tgn:2000191",
          "tgn:7029392"
        ],
        "placetype": [
          "aat:300008706"
        ],
        "id": 2255828,
        "name:xx": "Copper Creek"
      }
    },
    {
      "geometry": {
        "type": "Point",
        "coordinates": [
          -123.65,
          41.5333
        ]
      },
      "type": "Feature",
      "properties": {
        "hierarchy": [
          "tgn:2255829",
          "tgn:1000001",
          "tgn:7012149",
          "tgn:7007157",
          "tgn:2000189",
          "tgn:7029392"
        ],
        "placetype": [
          "aat:300008706"
        ],
        "id": 2255829,
        "name:xx": "Copper Creek"
      }
    }
  ]
}
