{
  "geometry": {
    "type": "Point",
    "coordinates": [
      7.05,
      51.25
    ]
  },
  "type": "Feature",
  "properties": {
    "hierarchy": [
      "tgn:7064267",
      "tgn:1000003",
      "tgn:7003677",
      "tgn:7000084",
      "tgn:7029392"
    ],
    "placetype": [
      "aat:300387200"
    ],
    "id": 7064267,
    "name:xx": "Unterdüssel"
  }
}
