{
  "geometry": {
    "type": "Point",
    "coordinates": [
      121.5833,
      30.9167
    ]
  },
  "type": "Feature",
  "properties": {
    "hierarchy": [
      "tgn:1071056",
      "tgn:1000004",
      "tgn:1000958",
      "tgn:1000111",
      "tgn:7029392"
    ],
    "placetype": [
      "aat:300008347"
    ],
    "id": 1071056,
    "name:xx": "Qingcun"
  }
}
