{
  "geometry": {
    "type": "Point",
    "coordinates": [
      116.0833,
      39.9167
    ]
  },
  "type": "Feature",
  "properties": {
    "hierarchy": [
      "tgn:1070449",
      "tgn:1000956",
      "tgn:1000004",
      "tgn:1000111",
      "tgn:7029392"
    ],
    "placetype": [
      "aat:300008347"
    ],
    "id": 1070449,
    "name:xx": "Mentougou"
  }
}
