{
  "geometry": {
    "type": "Point",
    "coordinates": [
      74.825365,
      28.16037
    ]
  },
  "type": "Feature",
  "properties": {
    "hierarchy": [
      "tgn:7564317",
      "tgn:1000004",
      "tgn:7000198",
      "tgn:7016788",
      "tgn:7029392"
    ],
    "placetype": [
      "aat:300008347"
    ],
    "name:en": "Bīkān ki Dhāni",
    "id": 7564317
  }
}
