{
  "geometry": {
    "type": "Point",
    "coordinates": [
      79.511275,
      26.279022
    ]
  },
  "type": "Feature",
  "properties": {
    "hierarchy": [
      "tgn:7565503",
      "tgn:1000004",
      "tgn:7000198",
      "tgn:7016722",
      "tgn:7029392"
    ],
    "placetype": [
      "aat:300008699"
    ],
    "name:en": "Bhitāri Nāla",
    "id": 7565503
  }
}
