{
  "type": "FeatureCollection",
  "features": [
    {
      "geometry": {
        "type": "Point",
        "coordinates": [
          17.25,
          40.4667
        ]
      },
      "type": "Feature",
      "properties": {
        "hierarchy": [
          "tgn:4012830",
          "tgn:1003500",
          "tgn:1000003",
          "tgn:7010380",
          "tgn:1000080",
          "tgn:7029392"
        ],
        "placetype": [
          "aat:300008347",
          "aat:300000745"
        ],
        "id": 4012830,
        "name:xx": "Città Nuova"
      }
    },
    {
      "geometry": {
        "type": "Point",
        "coordinates": [
          12.155278,
          45.530556
        ]
      },
      "type": "Feature",
      "properties": {
        "hierarchy": [
          "tgn:4012833",
          "tgn:7003006",
          "tgn:1000003",
          "tgn:7002997",
          "tgn:1000080",
          "tgn:7018159",
          "tgn:7029392"
        ],
        "placetype": [
          "aat:300008347",
          "aat:300387335"
        ],
        "id": 4012833,
        "name:xx": "Rialto"
      }
    },
    {
      "geometry": {
        "type": "Point",
        "coordinates": [
          12.35,
          45.45
        ]
      },
      "type": "Feature",
      "properties": {
        "hierarchy": [
          "tgn:4012834",
          "tgn:7003006",
          "tgn:1000003",
          "tgn:7002997",
          "tgn:1000080",
          "tgn:7018159",
          "tgn:7029392"
        ],
        "placetype": [
          "aat:300000745",
          "aat:300387335"
        ],
        "id": 4012834,
        "name:xx": "Sestière di Cannaregio"
      }
    },
    {
      "geometry": {
        "type": "Point",
        "coordinates": [
          9.916667,
          52.05
        ]
      },
      "type": "Feature",
      "properties": {
        "hierarchy": [
          "tgn:4012836",
          "tgn:1000003",
          "tgn:7003676",
          "tgn:7000084",
          "tgn:7029392"
        ],
        "placetype": [
          "aat:300008347"
        ],
        "id": 4012836,
        "name:xx": "Westfeld"
      }
    }
  ]
}
