{
  "geometry": {
    "type": "Point",
    "coordinates": [
      136.4167,
      51.45
    ]
  },
  "type": "Feature",
  "properties": {
    "hierarchy": [
      "tgn:1116249",
      "tgn:1000004",
      "tgn:7014474",
      "tgn:7018214",
      "tgn:7002435",
      "tgn:7029392"
    ],
    "placetype": [
      "aat:300008680"
    ],
    "id": 1116249,
    "name:xx": "Evoron, Ozero"
  }
}
