{
  "geometry": {
    "type": "Point",
    "coordinates": [
      166.4833,
      -21.9167
    ]
  },
  "type": "Feature",
  "properties": {
    "hierarchy": [
      "tgn:1104988",
      "tgn:7000665",
      "tgn:1000223",
      "tgn:1000006",
      "tgn:7029392"
    ],
    "placetype": [
      "aat:300008795"
    ],
    "id": 1104988,
    "name:xx": "Humboldt, Mont"
  }
}
