{
  "geometry": {
    "type": "Point",
    "coordinates": [
      -80.8667,
      40.3167
    ]
  },
  "type": "Feature",
  "properties": {
    "hierarchy": [
      "tgn:2377704",
      "tgn:1000001",
      "tgn:7012149",
      "tgn:7007706",
      "tgn:7029392"
    ],
    "placetype": [
      "aat:300008699"
    ],
    "id": 2377704,
    "name:xx": "Harrah Run"
  }
}
