{
  "geometry": {
    "type": "Point",
    "coordinates": [
      -79.1167,
      37.8833
    ]
  },
  "type": "Feature",
  "properties": {
    "hierarchy": [
      "tgn:2688945",
      "tgn:2002142",
      "tgn:1000001",
      "tgn:7012149",
      "tgn:7007919",
      "tgn:7029392"
    ],
    "placetype": [
      "aat:300008699"
    ],
    "id": 2688945,
    "name:xx": "Spy Run"
  }
}
