{
  "geometry": {
    "type": "Point",
    "coordinates": [
      -105.4333,
      31.9333
    ]
  },
  "type": "Feature",
  "properties": {
    "hierarchy": [
      "tgn:2572271",
      "tgn:1000001",
      "tgn:7012149",
      "tgn:2002005",
      "tgn:7007826",
      "tgn:7029392"
    ],
    "placetype": [
      "aat:300006191"
    ],
    "id": 2572271,
    "name:xx": "Peace Tank"
  }
}
