{
  "geometry": {
    "type": "Point",
    "coordinates": [
      -71.15,
      42.2667
    ]
  },
  "type": "Feature",
  "properties": {
    "hierarchy": [
      "tgn:7015008",
      "tgn:7013445",
      "tgn:1000001",
      "tgn:1002923",
      "tgn:7012149",
      "tgn:7007517",
      "tgn:7029392"
    ],
    "placetype": [
      "aat:300000745"
    ],
    "id": 7015008,
    "name:xx": "West Roxbury"
  }
}
