{
  "geometry": {
    "type": "Point",
    "coordinates": [
      20.783333,
      38.65
    ]
  },
  "type": "Feature",
  "properties": {
    "hierarchy": [
      "tgn:7233668",
      "tgn:7002680",
      "tgn:7001395",
      "tgn:1000003",
      "tgn:1000074",
      "tgn:7029392"
    ],
    "placetype": [
      "aat:300132316"
    ],
    "id": 7233668,
    "name:xx": "Dhikháli, Órmos"
  }
}
