{
  "geometry": {
    "type": "Point",
    "coordinates": [
      23.7667,
      61.3833
    ]
  },
  "type": "Feature",
  "properties": {
    "hierarchy": [
      "tgn:1031403",
      "tgn:7024077",
      "tgn:1000003",
      "tgn:1000069",
      "tgn:7029392"
    ],
    "placetype": [
      "aat:300008347"
    ],
    "id": 1031403,
    "name:xx": "Kulju"
  }
}
