{
  "type": "FeatureCollection",
  "features": [
    {
      "geometry": {
        "type": "Point",
        "coordinates": [
          -110.8167,
          34.0333
        ]
      },
      "type": "Feature",
      "properties": {
        "hierarchy": [
          "tgn:2775450",
          "tgn:1000001",
          "tgn:7006451",
          "tgn:2000093",
          "tgn:7012149",
          "tgn:7029392"
        ],
        "placetype": [
          "aat:300008706"
        ],
        "id": 2775450,
        "name:xx": "Wilson Creek"
      }
    },
    {
      "geometry": {
        "type": "Point",
        "coordinates": [
          -94.3,
          34.1167
        ]
      },
      "type": "Feature",
      "properties": {
        "hierarchy": [
          "tgn:2775451",
          "tgn:1000001",
          "tgn:7016172",
          "tgn:7012149",
          "tgn:2000171",
          "tgn:7029392"
        ],
        "placetype": [
          "aat:300008706"
        ],
        "id": 2775451,
        "name:xx": "Wilson Creek"
      }
    },
    {
      "geometry": {
        "type": "Point",
        "coordinates": [
          -93.5667,
          34.4667
        ]
      },
      "type": "Feature",
      "properties": {
        "hierarchy": [
          "tgn:2775452",
          "tgn:1000001",
          "tgn:7016172",
          "tgn:7012149",
          "tgn:2000153",
          "tgn:7029392"
        ],
        "placetype": [
          "aat:300008706"
        ],
        "id": 2775452,
        "name:xx": "Wilson Creek"
      }
    },
    {
      "geometry": {
        "type": "Point",
        "coordinates": [
          -93.1333,
          35.4333
        ]
      },
      "type": "Feature",
      "properties": {
        "hierarchy": [
          "tgn:2775453",
          "tgn:1000001",
          "tgn:7016172",
          "tgn:7012149",
          "tgn:2000162",
          "tgn:7029392"
        ],
        "placetype": [
          "aat:300008706"
        ],
        "id": 2775453,
        "name:xx": "Wilson Creek"
      }
    },
    {
      "geometry": {
        "type": "Point",
        "coordinates": [
          -91.8833,
          35.95
        ]
      },
      "type": "Feature",
      "properties": {
        "hierarchy": [
          "tgn:2775454",
          "tgn:1000001",
          "tgn:7016172",
          "tgn:7012149",
          "tgn:2000137",
          "tgn:7029392"
        ],
        "placetype": [
          "aat:300008706"
        ],
        "id": 2775454,
        "name:xx": "Wilson Creek"
      }
    },
    {
      "geometry": {
        "type": "Point",
        "coordinates": [
          -93.4167,
          33.85
        ]
      },
      "type": "Feature",
      "properties": {
        "hierarchy": [
          "tgn:2775455",
          "tgn:1000001",
          "tgn:7016172",
          "tgn:7012149",
          "tgn:7029392"
        ],
        "placetype": [
          "aat:300008706"
        ],
        "id": 2775455,
        "name:xx": "Wilson Creek"
      }
    },
    {
      "geometry": {
        "type": "Point",
        "coordinates": [
          -92.7,
          35.6
        ]
      },
      "type": "Feature",
      "properties": {
        "hierarchy": [
          "tgn:2775456",
          "tgn:1000001",
          "tgn:7016172",
          "tgn:7012149",
          "tgn:2000175",
          "tgn:7029392"
        ],
        "placetype": [
          "aat:300008706"
        ],
        "id": 2775456,
        "name:xx": "Wilson Creek"
      }
    },
    {
      "geometry": {
        "type": "Point",
        "coordinates": [
          -92.5,
          35.8333
        ]
      },
      "type": "Feature",
      "properties": {
        "hierarchy": [
          "tgn:2775457",
          "tgn:1000001",
          "tgn:7016172",
          "tgn:7012149",
          "tgn:2000169",
          "tgn:7029392"
        ],
        "placetype": [
          "aat:300008706"
        ],
        "id": 2775457,
        "name:xx": "Wilson Creek"
      }
    },
    {
      "geometry": {
        "type": "Point",
        "coordinates": [
          -119.4167,
          38.05
        ]
      },
      "type": "Feature",
      "properties": {
        "hierarchy": [
          "tgn:2775458",
          "tgn:1000001",
          "tgn:7012149",
          "tgn:7007157",
          "tgn:1002957",
          "tgn:7029392"
        ],
        "placetype": [
          "aat:300008706"
        ],
        "id": 2775458,
        "name:xx": "Wilson Creek"
      }
    },
    {
      "geometry": {
        "type": "Point",
        "coordinates": [
          -123.6333,
          39.8333
        ]
      },
      "type": "Feature",
      "properties": {
        "hierarchy": [
          "tgn:2775459",
          "tgn:1000001",
          "tgn:7012149",
          "tgn:7007157",
          "tgn:2000185",
          "tgn:7029392"
        ],
        "placetype": [
          "aat:300008706"
        ],
        "id": 2775459,
        "name:xx": "Wilson Creek"
      }
    }
  ]
}
