{
  "geometry": {
    "type": "Point",
    "coordinates": [
      -83.8333,
      37.0667
    ]
  },
  "type": "Feature",
  "properties": {
    "hierarchy": [
      "tgn:2628678",
      "tgn:1000001",
      "tgn:2000782",
      "tgn:7012149",
      "tgn:7007255",
      "tgn:7029392"
    ],
    "placetype": [
      "aat:300008699"
    ],
    "id": 2628678,
    "name:xx": "Roots Branch"
  }
}
