{
  "geometry": {
    "type": "Point",
    "coordinates": [
      -95.5833,
      47.1833
    ]
  },
  "type": "Feature",
  "properties": {
    "hierarchy": [
      "tgn:2455001",
      "tgn:1000001",
      "tgn:7012149",
      "tgn:2001042",
      "tgn:7007521",
      "tgn:7029392"
    ],
    "placetype": [
      "aat:300008680"
    ],
    "id": 2455001,
    "name:xx": "Little Elbow Lake"
  }
}
