{
  "geometry": {
    "type": "Point",
    "coordinates": [
      -93.7833,
      44.7667
    ]
  },
  "type": "Feature",
  "properties": {
    "hierarchy": [
      "tgn:2163739",
      "tgn:1000001",
      "tgn:2001008",
      "tgn:7012149",
      "tgn:7007521",
      "tgn:7029392"
    ],
    "placetype": [
      "aat:300008680"
    ],
    "id": 2163739,
    "name:xx": "Benton Lake"
  }
}
