{
  "geometry": {
    "type": "Point",
    "coordinates": [
      -71.8167,
      44.9667
    ]
  },
  "type": "Feature",
  "properties": {
    "hierarchy": [
      "tgn:2525905",
      "tgn:1000001",
      "tgn:1002361",
      "tgn:7012149",
      "tgn:7007828",
      "tgn:7029392"
    ],
    "placetype": [
      "aat:300008699"
    ],
    "id": 2525905,
    "name:xx": "Mosher Meadow Brook"
  }
}
