{
  "geometry": {
    "type": "Point",
    "coordinates": [
      -83.6667,
      41.55
    ]
  },
  "type": "Feature",
  "properties": {
    "hierarchy": [
      "tgn:2663823",
      "tgn:1000001",
      "tgn:7012149",
      "tgn:1002611",
      "tgn:7007706",
      "tgn:7029392"
    ],
    "placetype": [
      "aat:300008680"
    ],
    "id": 2663823,
    "name:xx": "Silver Lake"
  }
}
