{
  "geometry": {
    "type": "Point",
    "coordinates": [
      -95.866667,
      17.75
    ]
  },
  "type": "Feature",
  "properties": {
    "hierarchy": [
      "tgn:7432635",
      "tgn:1000001",
      "tgn:7005599",
      "tgn:7005560",
      "tgn:7029392"
    ],
    "placetype": [
      "aat:300008347"
    ],
    "id": 7432635,
    "name:xx": "Tomate Río Manso"
  }
}
