{
  "geometry": {
    "type": "Point",
    "coordinates": [
      44.2667,
      -23.8833
    ]
  },
  "type": "Feature",
  "properties": {
    "hierarchy": [
      "tgn:1091039",
      "tgn:7001242",
      "tgn:1001575",
      "tgn:1000173",
      "tgn:7029392"
    ],
    "placetype": [
      "aat:300008347"
    ],
    "id": 1091039,
    "name:xx": "Vohitsora"
  }
}
