{
  "geometry": {
    "type": "Point",
    "coordinates": [
      -107.2667,
      38.85
    ]
  },
  "type": "Feature",
  "properties": {
    "hierarchy": [
      "tgn:2757453",
      "tgn:1000001",
      "tgn:7012149",
      "tgn:2000217",
      "tgn:7007158",
      "tgn:7029392"
    ],
    "placetype": [
      "aat:300008798"
    ],
    "id": 2757453,
    "name:xx": "West Beckwith Mountain"
  }
}
