{
  "geometry": {
    "type": "Point",
    "coordinates": [
      -74.9333,
      41.6167
    ]
  },
  "type": "Feature",
  "properties": {
    "hierarchy": [
      "tgn:2540782",
      "tgn:1000001",
      "tgn:7012149",
      "tgn:1002926",
      "tgn:7007568",
      "tgn:7029392"
    ],
    "placetype": [
      "aat:300008680"
    ],
    "id": 2540782,
    "name:xx": "Nianque, Lake"
  }
}
