{
  "geometry": {
    "type": "Point",
    "coordinates": [
      -90.5833,
      31.15
    ]
  },
  "type": "Feature",
  "properties": {
    "hierarchy": [
      "tgn:2720877",
      "tgn:1000001",
      "tgn:7012149",
      "tgn:7029392"
    ],
    "placetype": [
      "aat:300008707"
    ],
    "id": 2720877,
    "name:xx": "Tickfaw River"
  }
}
