{
  "type": "FeatureCollection",
  "features": [
    {
      "geometry": {
        "type": "Point",
        "coordinates": [
          -105.65,
          40.3333
        ]
      },
      "type": "Feature",
      "properties": {
        "hierarchy": [
          "tgn:2592401",
          "tgn:1000001",
          "tgn:7012149",
          "tgn:2000226",
          "tgn:7007158",
          "tgn:7029392"
        ],
        "placetype": [
          "aat:300008680"
        ],
        "id": 2592401,
        "name:xx": "Pool, The"
      }
    },
    {
      "geometry": {
        "type": "Point",
        "coordinates": [
          -67.0833,
          44.75
        ]
      },
      "type": "Feature",
      "properties": {
        "hierarchy": [
          "tgn:2592402",
          "tgn:1000001",
          "tgn:7012149",
          "tgn:7014589",
          "tgn:7007515",
          "tgn:7029392"
        ],
        "placetype": [
          "aat:300132316"
        ],
        "id": 2592402,
        "name:xx": "Pool, The"
      }
    },
    {
      "geometry": {
        "type": "Point",
        "coordinates": [
          -69.2667,
          44.3167
        ]
      },
      "type": "Feature",
      "properties": {
        "hierarchy": [
          "tgn:2592403",
          "tgn:1000001",
          "tgn:2000924",
          "tgn:7012149",
          "tgn:7007515",
          "tgn:7029392"
        ],
        "placetype": [
          "aat:300008680"
        ],
        "id": 2592403,
        "name:xx": "Pool, The"
      }
    },
    {
      "geometry": {
        "type": "Point",
        "coordinates": [
          -70.35,
          43.4333
        ]
      },
      "type": "Feature",
      "properties": {
        "hierarchy": [
          "tgn:2592404",
          "tgn:1000001",
          "tgn:7012149",
          "tgn:2000933",
          "tgn:7007515",
          "tgn:7029392"
        ],
        "placetype": [
          "aat:300132316"
        ],
        "id": 2592404,
        "name:xx": "Pool, The"
      }
    },
    {
      "geometry": {
        "type": "Point",
        "coordinates": [
          -68.25,
          44.2333
        ]
      },
      "type": "Feature",
      "properties": {
        "hierarchy": [
          "tgn:2592405",
          "tgn:1000001",
          "tgn:2000922",
          "tgn:7012149",
          "tgn:7007515",
          "tgn:7029392"
        ],
        "placetype": [
          "aat:300132316"
        ],
        "id": 2592405,
        "name:xx": "Pool, The"
      }
    },
    {
      "geometry": {
        "type": "Point",
        "coordinates": [
          -71.6667,
          44.1
        ]
      },
      "type": "Feature",
      "properties": {
        "hierarchy": [
          "tgn:2592406",
          "tgn:1000001",
          "tgn:2001424",
          "tgn:7012149",
          "tgn:7007564",
          "tgn:7029392"
        ],
        "placetype": [
          "aat:300008680"
        ],
        "id": 2592406,
        "name:xx": "Pool, The"
      }
    },
    {
      "geometry": {
        "type": "Point",
        "coordinates": [
          -73.95,
          40.7833
        ]
      },
      "type": "Feature",
      "properties": {
        "hierarchy": [
          "tgn:2592407",
          "tgn:1000001",
          "tgn:7012149",
          "tgn:1002715",
          "tgn:7007568",
          "tgn:7029392"
        ],
        "placetype": [
          "aat:300008680"
        ],
        "id": 2592407,
        "name:xx": "Pool, The"
      }
    },
    {
      "geometry": {
        "type": "Point",
        "coordinates": [
          -157.2833,
          21.15
        ]
      },
      "type": "Feature",
      "properties": {
        "hierarchy": [
          "tgn:2592408",
          "tgn:1002648",
          "tgn:1000001",
          "tgn:1008191",
          "tgn:7012149",
          "tgn:7007249",
          "tgn:7029392"
        ],
        "placetype": [
          "aat:300008850"
        ],
        "id": 2592408,
        "name:xx": "Poolau"
      }
    },
    {
      "geometry": {
        "type": "Point",
        "coordinates": [
          -157.25,
          21.1333
        ]
      },
      "type": "Feature",
      "properties": {
        "hierarchy": [
          "tgn:2592409",
          "tgn:1002648",
          "tgn:1000001",
          "tgn:1008191",
          "tgn:7012149",
          "tgn:7007249",
          "tgn:7029392"
        ],
        "placetype": [
          "aat:300008761"
        ],
        "id": 2592409,
        "name:xx": "Poolau Gulch"
      }
    }
  ]
}
