{
  "geometry": {
    "type": "Point",
    "coordinates": [
      -80.0833,
      26.1833
    ]
  },
  "type": "Feature",
  "properties": {
    "hierarchy": [
      "tgn:2227732",
      "tgn:1000001",
      "tgn:1002207",
      "tgn:7012149",
      "tgn:7007240",
      "tgn:7029392"
    ],
    "placetype": [
      "aat:300008680"
    ],
    "id": 2227732,
    "name:xx": "Cayuga, Lake"
  }
}
