{
  "geometry": {
    "type": "Point",
    "coordinates": [
      -111.2167,
      37.4167
    ]
  },
  "type": "Feature",
  "properties": {
    "hierarchy": [
      "tgn:2168795",
      "tgn:1000001",
      "tgn:7012149",
      "tgn:2002113",
      "tgn:7007827",
      "tgn:7029392"
    ],
    "placetype": [
      "aat:300008761"
    ],
    "id": 2168795,
    "name:xx": "Big Hollow Wash"
  }
}
