{
  "type": "FeatureCollection",
  "features": [
    {
      "geometry": {
        "type": "Point",
        "coordinates": [
          12.333333,
          48.5
        ]
      },
      "type": "Feature",
      "properties": {
        "hierarchy": [
          "tgn:7082430",
          "tgn:7003669",
          "tgn:1000003",
          "tgn:7000084",
          "tgn:7029392"
        ],
        "placetype": [
          "aat:300000206"
        ],
        "id": 7082430,
        "name:xx": "Wimm"
      }
    },
    {
      "geometry": {
        "type": "Point",
        "coordinates": [
          13.2,
          48.533333
        ]
      },
      "type": "Feature",
      "properties": {
        "hierarchy": [
          "tgn:7082431",
          "tgn:7003669",
          "tgn:1000003",
          "tgn:7000084",
          "tgn:7029392"
        ],
        "placetype": [
          "aat:300000206"
        ],
        "id": 7082431,
        "name:xx": "Wimm"
      }
    },
    {
      "geometry": {
        "type": "Point",
        "coordinates": [
          12.933333,
          48.5
        ]
      },
      "type": "Feature",
      "properties": {
        "hierarchy": [
          "tgn:7082432",
          "tgn:7003669",
          "tgn:1000003",
          "tgn:7000084",
          "tgn:7029392"
        ],
        "placetype": [
          "aat:300000206"
        ],
        "id": 7082432,
        "name:xx": "Wimm"
      }
    },
    {
      "geometry": {
        "type": "Point",
        "coordinates": [
          12.65,
          48.316667
        ]
      },
      "type": "Feature",
      "properties": {
        "hierarchy": [
          "tgn:7082434",
          "tgn:7003669",
          "tgn:1000003",
          "tgn:7000084",
          "tgn:7029392"
        ],
        "placetype": [
          "aat:300000206"
        ],
        "id": 7082434,
        "name:xx": "Wimm"
      }
    },
    {
      "geometry": {
        "type": "Point",
        "coordinates": [
          12.333333,
          48.216667
        ]
      },
      "type": "Feature",
      "properties": {
        "hierarchy": [
          "tgn:7082435",
          "tgn:7003669",
          "tgn:1000003",
          "tgn:7000084",
          "tgn:7029392"
        ],
        "placetype": [
          "aat:300000206"
        ],
        "id": 7082435,
        "name:xx": "Wimm"
      }
    },
    {
      "geometry": {
        "type": "Point",
        "coordinates": [
          12.483333,
          48.166667
        ]
      },
      "type": "Feature",
      "properties": {
        "hierarchy": [
          "tgn:7082436",
          "tgn:7003669",
          "tgn:1000003",
          "tgn:7000084",
          "tgn:7029392"
        ],
        "placetype": [
          "aat:300000206"
        ],
        "id": 7082436,
        "name:xx": "Wimm"
      }
    },
    {
      "geometry": {
        "type": "Point",
        "coordinates": [
          12.75,
          48.15
        ]
      },
      "type": "Feature",
      "properties": {
        "hierarchy": [
          "tgn:7082437",
          "tgn:7003669",
          "tgn:1000003",
          "tgn:7000084",
          "tgn:7029392"
        ],
        "placetype": [
          "aat:300000206"
        ],
        "id": 7082437,
        "name:xx": "Wimm"
      }
    },
    {
      "geometry": {
        "type": "Point",
        "coordinates": [
          12.333333,
          48.116667
        ]
      },
      "type": "Feature",
      "properties": {
        "hierarchy": [
          "tgn:7082438",
          "tgn:7003669",
          "tgn:1000003",
          "tgn:7000084",
          "tgn:7029392"
        ],
        "placetype": [
          "aat:300000206"
        ],
        "id": 7082438,
        "name:xx": "Wimm"
      }
    },
    {
      "geometry": {
        "type": "Point",
        "coordinates": [
          12.4,
          47.966667
        ]
      },
      "type": "Feature",
      "properties": {
        "hierarchy": [
          "tgn:7082439",
          "tgn:7003669",
          "tgn:1000003",
          "tgn:7000084",
          "tgn:7029392"
        ],
        "placetype": [
          "aat:300000206"
        ],
        "id": 7082439,
        "name:xx": "Wimm"
      }
    }
  ]
}
