{
  "geometry": {
    "type": "Point",
    "coordinates": [
      -120.1333,
      38.4833
    ]
  },
  "type": "Feature",
  "properties": {
    "hierarchy": [
      "tgn:2181627",
      "tgn:1000001",
      "tgn:7012149",
      "tgn:7007157",
      "tgn:7029392"
    ],
    "placetype": [
      "aat:300008680"
    ],
    "id": 2181627,
    "name:xx": "Blue Hole"
  }
}
