{
  "geometry": {
    "type": "Point",
    "coordinates": [
      -80.0333,
      33.4833
    ]
  },
  "type": "Feature",
  "properties": {
    "hierarchy": [
      "tgn:2461037",
      "tgn:2001732",
      "tgn:1000001",
      "tgn:7012149",
      "tgn:7007712",
      "tgn:7029392"
    ],
    "placetype": [
      "aat:300008905"
    ],
    "id": 2461037,
    "name:xx": "Little Solomon Lake"
  }
}
