{
  "type": "FeatureCollection",
  "features": [
    {
      "geometry": {
        "type": "Point",
        "coordinates": [
          -88.7167,
          34.5
        ]
      },
      "type": "Feature",
      "properties": {
        "hierarchy": [
          "tgn:1100750",
          "tgn:1000001",
          "tgn:7012149",
          "tgn:2001126",
          "tgn:7007522",
          "tgn:7029392"
        ],
        "placetype": [
          "aat:300000835",
          "aat:300000833"
        ],
        "id": 1100750,
        "name:xx": "Brices Cross Roads National Battlefield Site"
      }
    },
    {
      "geometry": {
        "type": "Point",
        "coordinates": [
          -86.4333,
          35.8667
        ]
      },
      "type": "Feature",
      "properties": {
        "hierarchy": [
          "tgn:1100752",
          "tgn:1000001",
          "tgn:7012149",
          "tgn:2001911",
          "tgn:7007825",
          "tgn:7029392"
        ],
        "placetype": [
          "aat:300000835",
          "aat:300000833"
        ],
        "id": 1100752,
        "name:xx": "Stones River National Battlefield"
      }
    },
    {
      "geometry": {
        "type": "Point",
        "coordinates": [
          -88.7333,
          34.25
        ]
      },
      "type": "Feature",
      "properties": {
        "hierarchy": [
          "tgn:1100753",
          "tgn:1000001",
          "tgn:7012149",
          "tgn:2001126",
          "tgn:7007522",
          "tgn:7029392"
        ],
        "placetype": [
          "aat:300000835",
          "aat:300000833"
        ],
        "id": 1100753,
        "name:xx": "Tupelo National Battlefield"
      }
    }
  ]
}
