{
  "geometry": {
    "type": "Point",
    "coordinates": [
      86.390834,
      24.542066
    ]
  },
  "type": "Feature",
  "properties": {
    "hierarchy": [
      "tgn:7549299",
      "tgn:1000004",
      "tgn:1001842",
      "tgn:7000198",
      "tgn:7029392"
    ],
    "placetype": [
      "aat:300008347"
    ],
    "name:en": "Chākāi",
    "id": 7549299
  }
}
