{
  "geometry": {
    "type": "Point",
    "coordinates": [
      -72.2667,
      48.5167
    ]
  },
  "type": "Feature",
  "properties": {
    "hierarchy": [
      "tgn:1015596",
      "tgn:7005685",
      "tgn:1000001",
      "tgn:7005804",
      "tgn:7029392"
    ],
    "placetype": [
      "aat:300008347"
    ],
    "id": 1015596,
    "name:xx": "Roberval"
  }
}
