{
  "type": "FeatureCollection",
  "features": [
    {
      "geometry": {
        "type": "Point",
        "coordinates": [
          -2.8,
          54.633333
        ]
      },
      "type": "Feature",
      "properties": {
        "hierarchy": [
          "tgn:7461270",
          "tgn:7002445",
          "tgn:1000003",
          "tgn:7008117",
          "tgn:7008591",
          "tgn:7029392"
        ],
        "placetype": [
          "aat:300008347"
        ],
        "name:en": "Keldhead",
        "id": 7461270
      }
    },
    {
      "geometry": {
        "type": "Point",
        "coordinates": [
          -0.666667,
          54.516667
        ]
      },
      "type": "Feature",
      "properties": {
        "hierarchy": [
          "tgn:7461271",
          "tgn:7002445",
          "tgn:1000003",
          "tgn:7008166",
          "tgn:7008591",
          "tgn:7029392"
        ],
        "placetype": [
          "aat:300386918"
        ],
        "name:en": "Kelder Steel",
        "id": 7461271
      }
    },
    {
      "geometry": {
        "type": "Point",
        "coordinates": [
          -2.166667,
          54.4
        ]
      },
      "type": "Feature",
      "properties": {
        "hierarchy": [
          "tgn:7461272",
          "tgn:7002445",
          "tgn:1000003",
          "tgn:7008166",
          "tgn:7008591",
          "tgn:7029392"
        ],
        "placetype": [
          "aat:300008347"
        ],
        "name:en": "Keld",
        "id": 7461272
      }
    },
    {
      "geometry": {
        "type": "Point",
        "coordinates": [
          -4.85,
          55.766667
        ]
      },
      "type": "Feature",
      "properties": {
        "hierarchy": [
          "tgn:7461274",
          "tgn:7002444",
          "tgn:1000003",
          "tgn:7019091",
          "tgn:7008591",
          "tgn:7029392"
        ],
        "placetype": [
          "aat:300387502"
        ],
        "name:en": "Kelburn",
        "id": 7461274
      }
    },
    {
      "geometry": {
        "type": "Point",
        "coordinates": [
          -1.766667,
          57.5
        ]
      },
      "type": "Feature",
      "properties": {
        "hierarchy": [
          "tgn:7461276",
          "tgn:5000432",
          "tgn:7002444",
          "tgn:1000003",
          "tgn:7008591",
          "tgn:7029392"
        ],
        "placetype": [
          "aat:300008791"
        ],
        "name:en": "Keith Inch",
        "id": 7461276
      }
    },
    {
      "geometry": {
        "type": "Point",
        "coordinates": [
          -2.35,
          57.5
        ]
      },
      "type": "Feature",
      "properties": {
        "hierarchy": [
          "tgn:7461277",
          "tgn:5000432",
          "tgn:7002444",
          "tgn:1000003",
          "tgn:7008591",
          "tgn:7029392"
        ],
        "placetype": [
          "aat:300008347"
        ],
        "name:en": "Keithan",
        "id": 7461277
      }
    },
    {
      "geometry": {
        "type": "Point",
        "coordinates": [
          -3.1,
          58.533333
        ]
      },
      "type": "Feature",
      "properties": {
        "hierarchy": [
          "tgn:7461279",
          "tgn:7002444",
          "tgn:1000003",
          "tgn:7008082",
          "tgn:7008591",
          "tgn:7029392"
        ],
        "placetype": [
          "aat:300008057"
        ],
        "name:en": "Keiss Castle",
        "id": 7461279
      }
    }
  ]
}
