{
  "geometry": {
    "type": "Point",
    "coordinates": [
      -116.4167,
      47.1833
    ]
  },
  "type": "Feature",
  "properties": {
    "hierarchy": [
      "tgn:2274005",
      "tgn:2000456",
      "tgn:1000001",
      "tgn:7012149",
      "tgn:7007250",
      "tgn:7029392"
    ],
    "placetype": [
      "aat:300008706"
    ],
    "id": 2274005,
    "name:xx": "Dago Creek"
  }
}
