{
  "geometry": {
    "type": "Point",
    "coordinates": [
      -82.7333,
      32.85
    ]
  },
  "type": "Feature",
  "properties": {
    "hierarchy": [
      "tgn:2366354",
      "tgn:1000001",
      "tgn:7012149",
      "tgn:2000441",
      "tgn:7007248",
      "tgn:7029392"
    ],
    "placetype": [
      "aat:300008699"
    ],
    "id": 2366354,
    "name:xx": "Griffith Branch"
  }
}
