{
  "type": "FeatureCollection",
  "features": [
    {
      "geometry": {
        "type": "Point",
        "coordinates": [
          7.1,
          50.633333
        ]
      },
      "type": "Feature",
      "properties": {
        "hierarchy": [
          "tgn:7089690",
          "tgn:1000003",
          "tgn:7003677",
          "tgn:7000084",
          "tgn:7029392"
        ],
        "placetype": [
          "aat:300008347"
        ],
        "id": 7089690,
        "name:xx": "Wachtberg"
      }
    },
    {
      "geometry": {
        "type": "Point",
        "coordinates": [
          14.2,
          53.25
        ]
      },
      "type": "Feature",
      "properties": {
        "hierarchy": [
          "tgn:7089691",
          "tgn:7000096",
          "tgn:1000003",
          "tgn:7000084",
          "tgn:7029392"
        ],
        "placetype": [
          "aat:300008777"
        ],
        "id": 7089691,
        "name:xx": "Wacht-Berg"
      }
    },
    {
      "geometry": {
        "type": "Point",
        "coordinates": [
          10.65,
          53.05
        ]
      },
      "type": "Feature",
      "properties": {
        "hierarchy": [
          "tgn:7089692",
          "tgn:1000003",
          "tgn:7003676",
          "tgn:7000084",
          "tgn:7029392"
        ],
        "placetype": [
          "aat:300008777"
        ],
        "id": 7089692,
        "name:xx": "Wacht-Berg"
      }
    },
    {
      "geometry": {
        "type": "Point",
        "coordinates": [
          10.783333,
          53
        ]
      },
      "type": "Feature",
      "properties": {
        "hierarchy": [
          "tgn:7089693",
          "tgn:1000003",
          "tgn:7003676",
          "tgn:7000084",
          "tgn:7029392"
        ],
        "placetype": [
          "aat:300008777"
        ],
        "id": 7089693,
        "name:xx": "Wacht-Berg"
      }
    },
    {
      "geometry": {
        "type": "Point",
        "coordinates": [
          10.95,
          52.2
        ]
      },
      "type": "Feature",
      "properties": {
        "hierarchy": [
          "tgn:7089694",
          "tgn:1000003",
          "tgn:7003676",
          "tgn:7000084",
          "tgn:7029392"
        ],
        "placetype": [
          "aat:300008777"
        ],
        "id": 7089694,
        "name:xx": "Wacht-Berg"
      }
    },
    {
      "geometry": {
        "type": "Point",
        "coordinates": [
          12.516667,
          51.4
        ]
      },
      "type": "Feature",
      "properties": {
        "hierarchy": [
          "tgn:7089695",
          "tgn:1000003",
          "tgn:7003685",
          "tgn:7000084",
          "tgn:7029392"
        ],
        "placetype": [
          "aat:300008777"
        ],
        "id": 7089695,
        "name:xx": "Wacht-Berg"
      }
    },
    {
      "geometry": {
        "type": "Point",
        "coordinates": [
          14.466667,
          51.05
        ]
      },
      "type": "Feature",
      "properties": {
        "hierarchy": [
          "tgn:7089696",
          "tgn:1000003",
          "tgn:7003685",
          "tgn:7000084",
          "tgn:7029392"
        ],
        "placetype": [
          "aat:300008777"
        ],
        "id": 7089696,
        "name:xx": "Wacht-Berg"
      }
    },
    {
      "geometry": {
        "type": "Point",
        "coordinates": [
          8.583333,
          51.15
        ]
      },
      "type": "Feature",
      "properties": {
        "hierarchy": [
          "tgn:7089697",
          "tgn:1000003",
          "tgn:7003677",
          "tgn:7000084",
          "tgn:7029392"
        ],
        "placetype": [
          "aat:300008795"
        ],
        "id": 7089697,
        "name:xx": "Wacht"
      }
    },
    {
      "geometry": {
        "type": "Point",
        "coordinates": [
          8.1,
          50.45
        ]
      },
      "type": "Feature",
      "properties": {
        "hierarchy": [
          "tgn:7089698",
          "tgn:1000003",
          "tgn:7003678",
          "tgn:7000084",
          "tgn:7029392"
        ],
        "placetype": [
          "aat:300008777"
        ],
        "id": 7089698,
        "name:xx": "Wacht"
      }
    },
    {
      "geometry": {
        "type": "Point",
        "coordinates": [
          7.366667,
          51.35
        ]
      },
      "type": "Feature",
      "properties": {
        "hierarchy": [
          "tgn:7089699",
          "tgn:1000003",
          "tgn:7003677",
          "tgn:7000084",
          "tgn:7029392"
        ],
        "placetype": [
          "aat:300000206"
        ],
        "id": 7089699,
        "name:xx": "Wacht"
      }
    }
  ]
}
