{
  "type": "FeatureCollection",
  "features": [
    {
      "geometry": {
        "type": "Point",
        "coordinates": [
          106.9167,
          50.3
        ]
      },
      "type": "Feature",
      "properties": {
        "hierarchy": [
          "tgn:1051370",
          "tgn:1000004",
          "tgn:7011500",
          "tgn:7002435",
          "tgn:7029392"
        ],
        "placetype": [
          "aat:300008347"
        ],
        "id": 1051370,
        "name:xx": "Chikoy"
      }
    },
    {
      "geometry": {
        "type": "Point",
        "coordinates": [
          43.9,
          43.2
        ]
      },
      "type": "Feature",
      "properties": {
        "hierarchy": [
          "tgn:1051371",
          "tgn:1000004",
          "tgn:7014987",
          "tgn:7002435",
          "tgn:7029392"
        ],
        "placetype": [
          "aat:300008347"
        ],
        "id": 1051371,
        "name:xx": "Chikola"
      }
    },
    {
      "geometry": {
        "type": "Point",
        "coordinates": [
          70.65,
          40.1667
        ]
      },
      "type": "Feature",
      "properties": {
        "hierarchy": [
          "tgn:1051372",
          "tgn:1000004",
          "tgn:7011628",
          "tgn:7014835",
          "tgn:7029392"
        ],
        "placetype": [
          "aat:300008347"
        ],
        "id": 1051372,
        "name:xx": "Čil'gazi"
      }
    },
    {
      "geometry": {
        "type": "Point",
        "coordinates": [
          43.5,
          47.8333
        ]
      },
      "type": "Feature",
      "properties": {
        "hierarchy": [
          "tgn:1051373",
          "tgn:1000004",
          "tgn:7013207",
          "tgn:7018214",
          "tgn:7002435",
          "tgn:7029392"
        ],
        "placetype": [
          "aat:300008347"
        ],
        "id": 1051373,
        "name:xx": "Chilekovo"
      }
    },
    {
      "geometry": {
        "type": "Point",
        "coordinates": [
          78.2333,
          43.6
        ]
      },
      "type": "Feature",
      "properties": {
        "hierarchy": [
          "tgn:1051374",
          "tgn:1003353",
          "tgn:1000004",
          "tgn:7014786",
          "tgn:7029392"
        ],
        "placetype": [
          "aat:300008347"
        ],
        "id": 1051374,
        "name:xx": "Chilik"
      }
    },
    {
      "geometry": {
        "type": "Point",
        "coordinates": [
          59.7667,
          42.9333
        ]
      },
      "type": "Feature",
      "properties": {
        "hierarchy": [
          "tgn:1051375",
          "tgn:1000004",
          "tgn:7011673",
          "tgn:7006661",
          "tgn:7029392"
        ],
        "placetype": [
          "aat:300008347"
        ],
        "id": 1051375,
        "name:xx": "Chimbay"
      }
    },
    {
      "geometry": {
        "type": "Point",
        "coordinates": [
          28.8333,
          46.5
        ]
      },
      "type": "Feature",
      "properties": {
        "hierarchy": [
          "tgn:1051376",
          "tgn:7017344",
          "tgn:1000003",
          "tgn:7006656",
          "tgn:7029392"
        ],
        "placetype": [
          "aat:300008347"
        ],
        "id": 1051376,
        "name:xx": "Cimișlia"
      }
    },
    {
      "geometry": {
        "type": "Point",
        "coordinates": [
          71.5,
          40.3333
        ]
      },
      "type": "Feature",
      "properties": {
        "hierarchy": [
          "tgn:1051377",
          "tgn:7012251",
          "tgn:1000004",
          "tgn:7006661",
          "tgn:7029392"
        ],
        "placetype": [
          "aat:300008347"
        ],
        "id": 1051377,
        "name:xx": "Chimion"
      }
    },
    {
      "geometry": {
        "type": "Point",
        "coordinates": [
          75.5,
          42.8333
        ]
      },
      "type": "Feature",
      "properties": {
        "hierarchy": [
          "tgn:1051379",
          "tgn:7011475",
          "tgn:1000004",
          "tgn:7006655",
          "tgn:7029392"
        ],
        "placetype": [
          "aat:300008347"
        ],
        "id": 1051379,
        "name:xx": "Chimkorgon"
      }
    }
  ]
}
