{
  "geometry": {
    "type": "Point",
    "coordinates": [
      45.1833,
      41.7167
    ]
  },
  "type": "Feature",
  "properties": {
    "hierarchy": [
      "tgn:1059206",
      "tgn:1000004",
      "tgn:7012215",
      "tgn:7006653",
      "tgn:7029392"
    ],
    "placetype": [
      "aat:300008347"
    ],
    "id": 1059206,
    "name:xx": "Sartichala"
  }
}
