{
  "geometry": {
    "type": "Point",
    "coordinates": [
      -79.2167,
      40.05
    ]
  },
  "type": "Feature",
  "properties": {
    "hierarchy": [
      "tgn:2441971",
      "tgn:1000001",
      "tgn:7012149",
      "tgn:1002904",
      "tgn:7007710",
      "tgn:7029392"
    ],
    "placetype": [
      "aat:300006191"
    ],
    "id": 2441971,
    "name:xx": "Kooser Lake"
  }
}
