{
  "geometry": {
    "type": "Point",
    "coordinates": [
      -87.8667,
      32.75
    ]
  },
  "type": "Feature",
  "properties": {
    "hierarchy": [
      "tgn:2712974",
      "tgn:7002659",
      "tgn:1000001",
      "tgn:7012149",
      "tgn:2000031",
      "tgn:7029392"
    ],
    "placetype": [
      "aat:300006191"
    ],
    "id": 2712974,
    "name:xx": "Taylor Lake"
  }
}
