{
  "geometry": {
    "type": "Point",
    "coordinates": [
      -6.85,
      37.85
    ]
  },
  "type": "Feature",
  "properties": {
    "hierarchy": [
      "tgn:7333445",
      "tgn:7002758",
      "tgn:7002823",
      "tgn:1000003",
      "tgn:1000095",
      "tgn:7029392"
    ],
    "placetype": [
      "aat:300008347"
    ],
    "id": 7333445,
    "name:xx": "Estación de Gil Márquez"
  }
}
