{
  "geometry": {
    "type": "Point",
    "coordinates": [
      75.833333,
      11.45
    ]
  },
  "type": "Feature",
  "properties": {
    "hierarchy": [
      "tgn:7546956",
      "tgn:1000004",
      "tgn:7000198",
      "tgn:1001886",
      "tgn:7029392"
    ],
    "placetype": [
      "aat:300008347"
    ],
    "name:en": "Bālūssheri",
    "id": 7546956
  }
}
