{
  "geometry": {
    "type": "Point",
    "coordinates": [
      -124.3167,
      42.4833
    ]
  },
  "type": "Feature",
  "properties": {
    "hierarchy": [
      "tgn:2605355",
      "tgn:1000001",
      "tgn:2001704",
      "tgn:7012149",
      "tgn:7007708",
      "tgn:7029392"
    ],
    "placetype": [
      "aat:300008347"
    ],
    "id": 2605355,
    "name:xx": "Ragic"
  }
}
