{
  "geometry": {
    "type": "Point",
    "coordinates": [
      -115.35,
      43.2167
    ]
  },
  "type": "Feature",
  "properties": {
    "hierarchy": [
      "tgn:2256851",
      "tgn:1000001",
      "tgn:7012149",
      "tgn:2000471",
      "tgn:7007250",
      "tgn:7029392"
    ],
    "placetype": [
      "aat:300008706"
    ],
    "id": 2256851,
    "name:xx": "Corker Creek"
  }
}
