{
  "geometry": {
    "type": "Point",
    "coordinates": [
      -2.083333,
      39.15
    ]
  },
  "type": "Feature",
  "properties": {
    "hierarchy": [
      "tgn:7330127",
      "tgn:7002803",
      "tgn:1001647",
      "tgn:1000003",
      "tgn:1000095",
      "tgn:7029392"
    ],
    "placetype": [
      "aat:300007783"
    ],
    "id": 7330127,
    "name:xx": "Estación Hoya del Pozo"
  }
}
