{
  "geometry": {
    "type": "Point",
    "coordinates": [
      -113.5333,
      43.4167
    ]
  },
  "type": "Feature",
  "properties": {
    "hierarchy": [
      "tgn:2204336",
      "tgn:1000001",
      "tgn:2000463",
      "tgn:7012149",
      "tgn:7007250",
      "tgn:7029392"
    ],
    "placetype": [
      "aat:300008746"
    ],
    "id": 2204336,
    "name:xx": "Buffalo Caves"
  }
}
