{
  "geometry": {
    "type": "Point",
    "coordinates": [
      -83.6167,
      38.1667
    ]
  },
  "type": "Feature",
  "properties": {
    "hierarchy": [
      "tgn:2040354",
      "tgn:1002169",
      "tgn:1000001",
      "tgn:7012149",
      "tgn:7007255",
      "tgn:7029392"
    ],
    "placetype": [
      "aat:300008347"
    ],
    "id": 2040354,
    "name:xx": "Moores Ferry"
  }
}
