{
  "geometry": {
    "type": "Point",
    "coordinates": [
      -72.7667,
      41.9167
    ]
  },
  "type": "Feature",
  "properties": {
    "hierarchy": [
      "tgn:2579345",
      "tgn:1000001",
      "tgn:1002461",
      "tgn:7012149",
      "tgn:7007159",
      "tgn:7029392"
    ],
    "placetype": [
      "aat:300132316"
    ],
    "id": 2579345,
    "name:xx": "Pickerel Cove"
  }
}
