{
  "geometry": {
    "type": "Point",
    "coordinates": [
      -98.8833,
      29.7333
    ]
  },
  "type": "Feature",
  "properties": {
    "hierarchy": [
      "tgn:2220267",
      "tgn:1000001",
      "tgn:2001938",
      "tgn:7012149",
      "tgn:7007826",
      "tgn:7029392"
    ],
    "placetype": [
      "aat:300008798"
    ],
    "id": 2220267,
    "name:xx": "Cap Mountain"
  }
}
