{
  "type": "FeatureCollection",
  "features": [
    {
      "geometry": {
        "type": "Point",
        "coordinates": [
          -88.8,
          37.7333
        ]
      },
      "type": "Feature",
      "properties": {
        "hierarchy": [
          "tgn:2147340",
          "tgn:1000001",
          "tgn:7012149",
          "tgn:2000539",
          "tgn:7007251",
          "tgn:7029392"
        ],
        "placetype": [
          "aat:300000390"
        ],
        "id": 2147340,
        "name:xx": "Barbara Kay Mine"
      }
    },
    {
      "geometry": {
        "type": "Point",
        "coordinates": [
          -150.2167,
          60.8333
        ]
      },
      "type": "Feature",
      "properties": {
        "hierarchy": [
          "tgn:2147341",
          "tgn:7006450",
          "tgn:1000001",
          "tgn:7019698",
          "tgn:7012149",
          "tgn:7029392"
        ],
        "placetype": [
          "aat:300008680"
        ],
        "id": 2147341,
        "name:xx": "Barbara Lake"
      }
    },
    {
      "geometry": {
        "type": "Point",
        "coordinates": [
          -82.7,
          30.2833
        ]
      },
      "type": "Feature",
      "properties": {
        "hierarchy": [
          "tgn:2147342",
          "tgn:1000001",
          "tgn:2000262",
          "tgn:7012149",
          "tgn:7007240",
          "tgn:7029392"
        ],
        "placetype": [
          "aat:300008680"
        ],
        "id": 2147342,
        "name:xx": "Barbara Lake"
      }
    },
    {
      "geometry": {
        "type": "Point",
        "coordinates": [
          -109.6667,
          43.0167
        ]
      },
      "type": "Feature",
      "properties": {
        "hierarchy": [
          "tgn:2147343",
          "tgn:1000001",
          "tgn:7012149",
          "tgn:2002382",
          "tgn:7007923",
          "tgn:7029392"
        ],
        "placetype": [
          "aat:300008680"
        ],
        "id": 2147343,
        "name:xx": "Barbara Lake"
      }
    },
    {
      "geometry": {
        "type": "Point",
        "coordinates": [
          -93.2667,
          47.3333
        ]
      },
      "type": "Feature",
      "properties": {
        "hierarchy": [
          "tgn:2147344",
          "tgn:1000001",
          "tgn:7012149",
          "tgn:2001029",
          "tgn:7007521",
          "tgn:7029392"
        ],
        "placetype": [
          "aat:300000390"
        ],
        "id": 2147344,
        "name:xx": "Barbara Mine"
      }
    },
    {
      "geometry": {
        "type": "Point",
        "coordinates": [
          -78.2667,
          40.4
        ]
      },
      "type": "Feature",
      "properties": {
        "hierarchy": [
          "tgn:2147345",
          "tgn:1000001",
          "tgn:1002185",
          "tgn:7012149",
          "tgn:7007710",
          "tgn:7029392"
        ],
        "placetype": [
          "aat:300000390"
        ],
        "id": 2147345,
        "name:xx": "Barbara Mines"
      }
    },
    {
      "geometry": {
        "type": "Point",
        "coordinates": [
          -154,
          57.2833
        ]
      },
      "type": "Feature",
      "properties": {
        "hierarchy": [
          "tgn:2147346",
          "tgn:7006450",
          "tgn:1000001",
          "tgn:2124012",
          "tgn:7012149",
          "tgn:7029392"
        ],
        "placetype": [
          "aat:300008850"
        ],
        "id": 2147346,
        "name:xx": "Barbara Point"
      }
    },
    {
      "geometry": {
        "type": "Point",
        "coordinates": [
          -132.4833,
          54.8833
        ]
      },
      "type": "Feature",
      "properties": {
        "hierarchy": [
          "tgn:2147347",
          "tgn:7006450",
          "tgn:1000001",
          "tgn:7012149",
          "tgn:2000082",
          "tgn:7029392"
        ],
        "placetype": [
          "aat:300008791"
        ],
        "id": 2147347,
        "name:xx": "Barbara Rock"
      }
    },
    {
      "geometry": {
        "type": "Point",
        "coordinates": [
          -83.1667,
          38.7
        ]
      },
      "type": "Feature",
      "properties": {
        "hierarchy": [
          "tgn:2147348",
          "tgn:1000001",
          "tgn:7012149",
          "tgn:1002877",
          "tgn:7007706",
          "tgn:7029392"
        ],
        "placetype": [
          "aat:300008699"
        ],
        "id": 2147348,
        "name:xx": "Barbara Run"
      }
    },
    {
      "geometry": {
        "type": "Point",
        "coordinates": [
          -111.8667,
          34.1
        ]
      },
      "type": "Feature",
      "properties": {
        "hierarchy": [
          "tgn:2147349",
          "tgn:1000001",
          "tgn:7006451",
          "tgn:7012149",
          "tgn:2000103",
          "tgn:7029392"
        ],
        "placetype": [
          "aat:300008697"
        ],
        "id": 2147349,
        "name:xx": "Barbara Spring"
      }
    }
  ]
}
