{
  "type": "FeatureCollection",
  "features": [
    {
      "geometry": {
        "type": "Point",
        "coordinates": [
          -0.366667,
          52.55
        ]
      },
      "type": "Feature",
      "properties": {
        "hierarchy": [
          "tgn:4012071",
          "tgn:7002445",
          "tgn:7011980",
          "tgn:1000003",
          "tgn:7008591",
          "tgn:7029392"
        ],
        "placetype": [
          "aat:300008347",
          "aat:300387007",
          "aat:300008372"
        ],
        "id": 4012071,
        "name:ang": "Newetone"
      }
    },
    {
      "geometry": {
        "type": "Point",
        "coordinates": [
          5.533333,
          51
        ]
      },
      "type": "Feature",
      "properties": {
        "hierarchy": [
          "tgn:4012078",
          "tgn:7003461",
          "tgn:1000003",
          "tgn:1000063",
          "tgn:7018236",
          "tgn:7029392"
        ],
        "placetype": [
          "aat:300008347"
        ],
        "id": 4012078,
        "name:xx": "Waterschei"
      }
    }
  ]
}
