{
  "geometry": {
    "type": "Point",
    "coordinates": [
      87.538604,
      23.626032
    ]
  },
  "type": "Feature",
  "properties": {
    "hierarchy": [
      "tgn:1075516",
      "tgn:1000004",
      "tgn:7000198",
      "tgn:1001977",
      "tgn:7029392"
    ],
    "placetype": [
      "aat:300008347"
    ],
    "name:en": "Ilām Bāzār",
    "id": 1075516
  }
}
