{
  "geometry": {
    "type": "Point",
    "coordinates": [
      -107.95,
      43.45
    ]
  },
  "type": "Feature",
  "properties": {
    "hierarchy": [
      "tgn:1132261",
      "tgn:1000001",
      "tgn:7012149",
      "tgn:7007923",
      "tgn:7029392"
    ],
    "placetype": [
      "aat:300008706"
    ],
    "id": 1132261,
    "name:xx": "Antelope Creek"
  }
}
