{
  "geometry": {
    "type": "Point",
    "coordinates": [
      -75.4167,
      42.1333
    ]
  },
  "type": "Feature",
  "properties": {
    "hierarchy": [
      "tgn:2213176",
      "tgn:1000001",
      "tgn:7012149",
      "tgn:7007568",
      "tgn:7029392"
    ],
    "placetype": [
      "aat:300008699"
    ],
    "id": 2213176,
    "name:xx": "Cabin Brook"
  }
}
