{
  "geometry": {
    "type": "Point",
    "coordinates": [
      23.533333,
      39.15
    ]
  },
  "type": "Feature",
  "properties": {
    "hierarchy": [
      "tgn:7225115",
      "tgn:7002751",
      "tgn:7001399",
      "tgn:1000003",
      "tgn:1000074",
      "tgn:7029392"
    ],
    "placetype": [
      "aat:300008791"
    ],
    "id": 7225115,
    "name:xx": "Répion, Nisís"
  }
}
