{
  "geometry": {
    "type": "Point",
    "coordinates": [
      -78.2667,
      41.9333
    ]
  },
  "type": "Feature",
  "properties": {
    "hierarchy": [
      "tgn:2540118",
      "tgn:1000001",
      "tgn:7012149",
      "tgn:7016020",
      "tgn:7007710",
      "tgn:7029392"
    ],
    "placetype": [
      "aat:300008706"
    ],
    "id": 2540118,
    "name:xx": "Newell Creek"
  }
}
