{
  "geometry": {
    "type": "Point",
    "coordinates": [
      -122.2333,
      37.3667
    ]
  },
  "type": "Feature",
  "properties": {
    "hierarchy": [
      "tgn:2206010",
      "tgn:1000001",
      "tgn:7012149",
      "tgn:7007157",
      "tgn:1002864",
      "tgn:7029392"
    ],
    "placetype": [
      "aat:300008706"
    ],
    "id": 2206010,
    "name:xx": "Bull Run Creek"
  }
}
