{
  "geometry": {
    "type": "Point",
    "coordinates": [
      -80.9833,
      27.25
    ]
  },
  "type": "Feature",
  "properties": {
    "hierarchy": [
      "tgn:2491579",
      "tgn:1000001",
      "tgn:1002477",
      "tgn:7012149",
      "tgn:7007240",
      "tgn:7029392"
    ],
    "placetype": [
      "aat:300008707"
    ],
    "id": 2491579,
    "name:xx": "Maple River"
  }
}
