{
  "geometry": {
    "type": "Point",
    "coordinates": [
      -116.6167,
      48.3667
    ]
  },
  "type": "Feature",
  "properties": {
    "hierarchy": [
      "tgn:2247976",
      "tgn:1000001",
      "tgn:2000460",
      "tgn:7012149",
      "tgn:7007250",
      "tgn:7029392"
    ],
    "placetype": [
      "aat:300008680"
    ],
    "id": 2247976,
    "name:xx": "Colburn Lake"
  }
}
