{
  "type": "FeatureCollection",
  "features": [
    {
      "geometry": {
        "type": "Point",
        "coordinates": [
          -77.05,
          40.5
        ]
      },
      "type": "Feature",
      "properties": {
        "hierarchy": [
          "tgn:1110640",
          "tgn:1000001",
          "tgn:7012149",
          "tgn:1002779",
          "tgn:7007710",
          "tgn:7029392"
        ],
        "placetype": [
          "aat:300266640"
        ],
        "id": 1110640,
        "name:xx": "Berry Mountain"
      }
    },
    {
      "geometry": {
        "type": "Point",
        "coordinates": [
          -82.8833,
          36.9
        ]
      },
      "type": "Feature",
      "properties": {
        "hierarchy": [
          "tgn:1110641",
          "tgn:1000001",
          "tgn:7012149",
          "tgn:7029392"
        ],
        "placetype": [
          "aat:300266640"
        ],
        "id": 1110641,
        "name:xx": "Black Mountain"
      }
    },
    {
      "geometry": {
        "type": "Point",
        "coordinates": [
          -46.65,
          -23.4167
        ]
      },
      "type": "Feature",
      "properties": {
        "hierarchy": [
          "tgn:1110644",
          "tgn:1001945",
          "tgn:1000047",
          "tgn:7002457",
          "tgn:1000002",
          "tgn:7029392"
        ],
        "placetype": [
          "aat:300266640"
        ],
        "id": 1110644,
        "name:xx": "Cantareira, Serra da"
      }
    },
    {
      "geometry": {
        "type": "Point",
        "coordinates": [
          -44.3,
          -22.7833
        ]
      },
      "type": "Feature",
      "properties": {
        "hierarchy": [
          "tgn:1110645",
          "tgn:1001945",
          "tgn:1000047",
          "tgn:7002457",
          "tgn:1000002",
          "tgn:7029392"
        ],
        "placetype": [
          "aat:300266640"
        ],
        "id": 1110645,
        "name:xx": "Carioca, Serra da"
      }
    },
    {
      "geometry": {
        "type": "Point",
        "coordinates": [
          -46.1167,
          -22.1
        ]
      },
      "type": "Feature",
      "properties": {
        "hierarchy": [
          "tgn:1110647",
          "tgn:7006237",
          "tgn:1000047",
          "tgn:7002457",
          "tgn:1000002",
          "tgn:7029392"
        ],
        "placetype": [
          "aat:300266640"
        ],
        "id": 1110647,
        "name:xx": "Cervo, Serra do"
      }
    },
    {
      "geometry": {
        "type": "Point",
        "coordinates": [
          13.1667,
          -16
        ]
      },
      "type": "Feature",
      "properties": {
        "hierarchy": [
          "tgn:1110648",
          "tgn:7001242",
          "tgn:1000149",
          "tgn:1000867",
          "tgn:7029392"
        ],
        "placetype": [
          "aat:300266640"
        ],
        "id": 1110648,
        "name:xx": "Chela, Serra da"
      }
    }
  ]
}
