{
  "geometry": {
    "type": "Point",
    "coordinates": [
      29.6667,
      51.6667
    ]
  },
  "type": "Feature",
  "properties": {
    "hierarchy": [
      "tgn:1130104",
      "tgn:1000003",
      "tgn:7029392"
    ],
    "placetype": [
      "aat:300008707"
    ],
    "id": 1130104,
    "name:be": "Slovechna"
  }
}
