{
  "type": "FeatureCollection",
  "features": [
    {
      "geometry": {
        "type": "Point",
        "coordinates": [
          6.983333,
          44.466667
        ]
      },
      "type": "Feature",
      "properties": {
        "hierarchy": [
          "tgn:7054850",
          "tgn:7005126",
          "tgn:1000003",
          "tgn:7003120",
          "tgn:1000080",
          "tgn:7029392"
        ],
        "placetype": [
          "aat:300008699"
        ],
        "id": 7054850,
        "name:xx": "Mollasco, Rio"
      }
    },
    {
      "geometry": {
        "type": "Point",
        "coordinates": [
          13.783333,
          41.633333
        ]
      },
      "type": "Feature",
      "properties": {
        "hierarchy": [
          "tgn:7054851",
          "tgn:7003135",
          "tgn:1000003",
          "tgn:7003080",
          "tgn:1000080",
          "tgn:7029392"
        ],
        "placetype": [
          "aat:300008699"
        ],
        "id": 7054851,
        "name:xx": "Mollarino, Fiume"
      }
    },
    {
      "geometry": {
        "type": "Point",
        "coordinates": [
          13.866667,
          37.083333
        ]
      },
      "type": "Feature",
      "properties": {
        "hierarchy": [
          "tgn:7054852",
          "tgn:1000003",
          "tgn:7003122",
          "tgn:1000080",
          "tgn:7029392"
        ],
        "placetype": [
          "aat:300011692"
        ],
        "id": 7054852,
        "name:xx": "Mollachella, Rocca"
      }
    },
    {
      "geometry": {
        "type": "Point",
        "coordinates": [
          8.266667,
          41.1
        ]
      },
      "type": "Feature",
      "properties": {
        "hierarchy": [
          "tgn:7054853",
          "tgn:7015163",
          "tgn:1000003",
          "tgn:7003121",
          "tgn:1000080",
          "tgn:7029392"
        ],
        "placetype": [
          "aat:300008850",
          "aat:300386846"
        ],
        "id": 7054853,
        "name:xx": "Molla, Capo"
      }
    },
    {
      "geometry": {
        "type": "Point",
        "coordinates": [
          11.05,
          42.8
        ]
      },
      "type": "Feature",
      "properties": {
        "hierarchy": [
          "tgn:7054855",
          "tgn:1003460",
          "tgn:1000003",
          "tgn:7009760",
          "tgn:1000080",
          "tgn:7029392"
        ],
        "placetype": [
          "aat:300006075"
        ],
        "id": 7054855,
        "name:xx": "Canale Molla"
      }
    },
    {
      "geometry": {
        "type": "Point",
        "coordinates": [
          13.35,
          43.633333
        ]
      },
      "type": "Feature",
      "properties": {
        "hierarchy": [
          "tgn:7054859",
          "tgn:1003429",
          "tgn:1000003",
          "tgn:7003240",
          "tgn:1000080",
          "tgn:7029392"
        ],
        "placetype": [
          "aat:300008347"
        ],
        "id": 7054859,
        "name:xx": "Molino Santinelli"
      }
    }
  ]
}
