{
  "geometry": {
    "type": "Point",
    "coordinates": [
      26.6167,
      40.8667
    ]
  },
  "type": "Feature",
  "properties": {
    "hierarchy": [
      "tgn:1086585",
      "tgn:1001232",
      "tgn:1000004",
      "tgn:7018450",
      "tgn:1000144",
      "tgn:7029392"
    ],
    "placetype": [
      "aat:300008347"
    ],
    "id": 1086585,
    "name:xx": "Kesan"
  }
}
