{
  "geometry": {
    "type": "Point",
    "coordinates": [
      1.3333,
      49.9167
    ]
  },
  "type": "Feature",
  "properties": {
    "hierarchy": [
      "tgn:1033024",
      "tgn:1000003",
      "tgn:7002882",
      "tgn:1000070",
      "tgn:7029392"
    ],
    "placetype": [
      "aat:300008347"
    ],
    "id": 1033024,
    "name:xx": "Envermeu"
  }
}
