{
  "geometry": {
    "type": "Point",
    "coordinates": [
      -85.1833,
      43.3667
    ]
  },
  "type": "Feature",
  "properties": {
    "hierarchy": [
      "tgn:2521075",
      "tgn:1000001",
      "tgn:7012149",
      "tgn:2000981",
      "tgn:7007520",
      "tgn:7029392"
    ],
    "placetype": [
      "aat:300008680"
    ],
    "id": 2521075,
    "name:xx": "Montcalm, Lake"
  }
}
