{
  "geometry": {
    "type": "Point",
    "coordinates": [
      79.46527,
      27.99996
    ]
  },
  "type": "Feature",
  "properties": {
    "hierarchy": [
      "tgn:7561981",
      "tgn:1000004",
      "tgn:7000198",
      "tgn:7016722",
      "tgn:7029392"
    ],
    "placetype": [
      "aat:300008347"
    ],
    "name:en": "Gauntia",
    "id": 7561981
  }
}
