{
  "geometry": {
    "type": "Point",
    "coordinates": [
      44.0667,
      55.5833
    ]
  },
  "type": "Feature",
  "properties": {
    "hierarchy": [
      "tgn:1055960",
      "tgn:1000004",
      "tgn:7011585",
      "tgn:7018214",
      "tgn:7002435",
      "tgn:7029392"
    ],
    "placetype": [
      "aat:300008347"
    ],
    "id": 1055960,
    "name:xx": "Krutoj Majdan"
  }
}
