{
  "geometry": {
    "type": "Point",
    "coordinates": [
      79.724699,
      26.97192
    ]
  },
  "type": "Feature",
  "properties": {
    "hierarchy": [
      "tgn:7564399",
      "tgn:1000004",
      "tgn:7000198",
      "tgn:7016722",
      "tgn:7029392"
    ],
    "placetype": [
      "aat:300008347"
    ],
    "name:en": "Ratnāpur",
    "id": 7564399
  }
}
