{
  "geometry": {
    "type": "Point",
    "coordinates": [
      30.934828,
      30.95304
    ]
  },
  "type": "Feature",
  "properties": {
    "hierarchy": [
      "tgn:7527762",
      "tgn:7001242",
      "tgn:7016833",
      "tgn:7001312",
      "tgn:7029392"
    ],
    "placetype": [
      "aat:300008347"
    ],
    "name:en": "Shubr훮 Bil큰lah as Sakh훮w카yah",
    "id": 7527762
  }
}
