{
  "geometry": {
    "type": "Point",
    "coordinates": [
      31.238382,
      30.120601
    ]
  },
  "type": "Feature",
  "properties": {
    "hierarchy": [
      "tgn:7532366",
      "tgn:7001242",
      "tgn:7016833",
      "tgn:1001092",
      "tgn:7029392"
    ],
    "placetype": [
      "aat:300004792"
    ],
    "id": 7532366,
    "name:xx": "Ash Shirkah al Mişrīyah lil Inshā'āt al Ma'dinīyah"
  }
}
