{
  "geometry": {
    "type": "Point",
    "coordinates": [
      -109.6333,
      37.6667
    ]
  },
  "type": "Feature",
  "properties": {
    "hierarchy": [
      "tgn:2412498",
      "tgn:1000001",
      "tgn:7012149",
      "tgn:2002119",
      "tgn:7007827",
      "tgn:7029392"
    ],
    "placetype": [
      "aat:300008347"
    ],
    "id": 2412498,
    "name:xx": "Indian Village"
  }
}
