{
  "geometry": {
    "type": "Point",
    "coordinates": [
      -92.6833,
      39.1333
    ]
  },
  "type": "Feature",
  "properties": {
    "hierarchy": [
      "tgn:2058748",
      "tgn:1000001",
      "tgn:7012149",
      "tgn:2001205",
      "tgn:7007523",
      "tgn:7029392"
    ],
    "placetype": [
      "aat:300008347"
    ],
    "id": 2058748,
    "name:xx": "Fayette"
  }
}
