{
  "geometry": {
    "type": "Point",
    "coordinates": [
      -75.6167,
      42.4833
    ]
  },
  "type": "Feature",
  "properties": {
    "hierarchy": [
      "tgn:2710579",
      "tgn:1000001",
      "tgn:1002262",
      "tgn:7012149",
      "tgn:7007568",
      "tgn:7029392"
    ],
    "placetype": [
      "aat:300008905"
    ],
    "id": 2710579,
    "name:xx": "Tamarack Swamp"
  }
}
