{
  "type": "FeatureCollection",
  "features": [
    {
      "geometry": {
        "type": "Point",
        "coordinates": [
          15.406776,
          52.735748
        ]
      },
      "type": "Feature",
      "properties": {
        "hierarchy": [
          "tgn:1127922",
          "tgn:1000003",
          "tgn:7006366",
          "tgn:7029392"
        ],
        "placetype": [
          "aat:300008707"
        ],
        "id": 1127922,
        "name:xx": "Noteć"
      }
    },
    {
      "geometry": {
        "type": "Point",
        "coordinates": [
          -117.1167,
          57.2833
        ]
      },
      "type": "Feature",
      "properties": {
        "hierarchy": [
          "tgn:1127923",
          "tgn:7005694",
          "tgn:7005685",
          "tgn:1000001",
          "tgn:7029392"
        ],
        "placetype": [
          "aat:300008707"
        ],
        "id": 1127923,
        "name:xx": "Notikewin"
      }
    },
    {
      "geometry": {
        "type": "Point",
        "coordinates": [
          2.6,
          47.6833
        ]
      },
      "type": "Feature",
      "properties": {
        "hierarchy": [
          "tgn:1127924",
          "tgn:1000003",
          "tgn:7002877",
          "tgn:1000070",
          "tgn:7029392"
        ],
        "placetype": [
          "aat:300008707"
        ],
        "id": 1127924,
        "name:xx": "Notreure"
      }
    },
    {
      "geometry": {
        "type": "Point",
        "coordinates": [
          -80,
          44.5333
        ]
      },
      "type": "Feature",
      "properties": {
        "hierarchy": [
          "tgn:1127925",
          "tgn:7005685",
          "tgn:1000001",
          "tgn:7013154",
          "tgn:7029392"
        ],
        "placetype": [
          "aat:300008707"
        ],
        "id": 1127925,
        "name:xx": "Nottawasaga"
      }
    },
    {
      "geometry": {
        "type": "Point",
        "coordinates": [
          11.1,
          4.9167
        ]
      },
      "type": "Feature",
      "properties": {
        "hierarchy": [
          "tgn:1127928",
          "tgn:7001242",
          "tgn:1000153",
          "tgn:7029392"
        ],
        "placetype": [
          "aat:300008707"
        ],
        "id": 1127928,
        "name:xx": "Noun"
      }
    }
  ]
}
