{
  "geometry": {
    "type": "Point",
    "coordinates": [
      -73.6667,
      43.9833
    ]
  },
  "type": "Feature",
  "properties": {
    "hierarchy": [
      "tgn:2231654",
      "tgn:1000001",
      "tgn:7012149",
      "tgn:2001461",
      "tgn:7007568",
      "tgn:7029392"
    ],
    "placetype": [
      "aat:300008680"
    ],
    "id": 2231654,
    "name:xx": "Challis Pond"
  }
}
