{
  "geometry": {
    "type": "Point",
    "coordinates": [
      -74.7167,
      41.45
    ]
  },
  "type": "Feature",
  "properties": {
    "hierarchy": [
      "tgn:2659551",
      "tgn:1000001",
      "tgn:7012149",
      "tgn:1002751",
      "tgn:7007568",
      "tgn:7029392"
    ],
    "placetype": [
      "aat:300008699"
    ],
    "id": 2659551,
    "name:xx": "Shingle Kill"
  }
}
