{
  "geometry": {
    "type": "Point",
    "coordinates": [
      6.2167,
      60.3833
    ]
  },
  "type": "Feature",
  "properties": {
    "hierarchy": [
      "tgn:1048438",
      "tgn:7003646",
      "tgn:1000003",
      "tgn:1000088",
      "tgn:7029392"
    ],
    "placetype": [
      "aat:300008347"
    ],
    "id": 1048438,
    "name:xx": "Øystese"
  }
}
