{
  "geometry": {
    "type": "Point",
    "coordinates": [
      -74.0333,
      41.2833
    ]
  },
  "type": "Feature",
  "properties": {
    "hierarchy": [
      "tgn:2695308",
      "tgn:1000001",
      "tgn:7012149",
      "tgn:1002833",
      "tgn:7007568",
      "tgn:7029392"
    ],
    "placetype": [
      "aat:300008699"
    ],
    "id": 2695308,
    "name:xx": "Stillwater Brook"
  }
}
