{
  "geometry": {
    "type": "Point",
    "coordinates": [
      120.4075,
      22.830278
    ]
  },
  "type": "Feature",
  "properties": {
    "hierarchy": [
      "tgn:7492034",
      "tgn:7001004",
      "tgn:1000004",
      "tgn:1000141",
      "tgn:7029392"
    ],
    "placetype": [
      "aat:300008347"
    ],
    "id": 7492034,
    "name:xx": "Shuiwatan"
  }
}
