{
  "type": "FeatureCollection",
  "features": [
    {
      "geometry": {
        "type": "Point",
        "coordinates": [
          -72.666667,
          -53.35
        ]
      },
      "type": "Feature",
      "properties": {
        "hierarchy": [
          "tgn:7293190",
          "tgn:1001702",
          "tgn:1000049",
          "tgn:1000002",
          "tgn:7029392"
        ],
        "placetype": [
          "aat:300386846"
        ],
        "id": 7293190,
        "name:xx": "Espolón, Punta"
      }
    },
    {
      "geometry": {
        "type": "Point",
        "coordinates": [
          -70.333333,
          -52.933333
        ]
      },
      "type": "Feature",
      "properties": {
        "hierarchy": [
          "tgn:7293191",
          "tgn:1001702",
          "tgn:1000049",
          "tgn:1000002",
          "tgn:7029392"
        ],
        "placetype": [
          "aat:300386846"
        ],
        "id": 7293191,
        "name:xx": "Espolón, Punta"
      }
    },
    {
      "geometry": {
        "type": "Point",
        "coordinates": [
          -71.2,
          -52.816667
        ]
      },
      "type": "Feature",
      "properties": {
        "hierarchy": [
          "tgn:7293192",
          "tgn:1001702",
          "tgn:1000049",
          "tgn:1000002",
          "tgn:7029392"
        ],
        "placetype": [
          "aat:300386846"
        ],
        "id": 7293192,
        "name:xx": "Espolón, Punta"
      }
    },
    {
      "geometry": {
        "type": "Point",
        "coordinates": [
          -72.933333,
          -51.883333
        ]
      },
      "type": "Feature",
      "properties": {
        "hierarchy": [
          "tgn:7293193",
          "tgn:1001702",
          "tgn:1000049",
          "tgn:1000002",
          "tgn:7029392"
        ],
        "placetype": [
          "aat:300386846"
        ],
        "id": 7293193,
        "name:xx": "Espolón, Punta"
      }
    },
    {
      "geometry": {
        "type": "Point",
        "coordinates": [
          -75.345556,
          -50.095278
        ]
      },
      "type": "Feature",
      "properties": {
        "hierarchy": [
          "tgn:7293194",
          "tgn:1001702",
          "tgn:1000049",
          "tgn:1000002",
          "tgn:7029392"
        ],
        "placetype": [
          "aat:300386846"
        ],
        "id": 7293194,
        "name:xx": "Espolón, Punta"
      }
    },
    {
      "geometry": {
        "type": "Point",
        "coordinates": [
          -73.483333,
          -37.033333
        ]
      },
      "type": "Feature",
      "properties": {
        "hierarchy": [
          "tgn:7293195",
          "tgn:1001637",
          "tgn:1000049",
          "tgn:1000002",
          "tgn:7029392"
        ],
        "placetype": [
          "aat:300386846"
        ],
        "id": 7293195,
        "name:xx": "Espolón, Punta"
      }
    },
    {
      "geometry": {
        "type": "Point",
        "coordinates": [
          -109.433333,
          -27.116667
        ]
      },
      "type": "Feature",
      "properties": {
        "hierarchy": [
          "tgn:7293196",
          "tgn:1001768",
          "tgn:1000049",
          "tgn:1000002",
          "tgn:7029392"
        ],
        "placetype": [
          "aat:300386846"
        ],
        "id": 7293196,
        "name:xx": "Espolón, Punta"
      }
    },
    {
      "geometry": {
        "type": "Point",
        "coordinates": [
          -71.833333,
          -34.25
        ]
      },
      "type": "Feature",
      "properties": {
        "hierarchy": [
          "tgn:7293197",
          "tgn:1001695",
          "tgn:1000049",
          "tgn:1000002",
          "tgn:7029392"
        ],
        "placetype": [
          "aat:300008777"
        ],
        "id": 7293197,
        "name:xx": "Esplanada"
      }
    },
    {
      "geometry": {
        "type": "Point",
        "coordinates": [
          -71.466667,
          -31.233333
        ]
      },
      "type": "Feature",
      "properties": {
        "hierarchy": [
          "tgn:7293198",
          "tgn:1001657",
          "tgn:1000049",
          "tgn:1000002",
          "tgn:7029392"
        ],
        "placetype": [
          "aat:300008699"
        ],
        "id": 7293198,
        "name:xx": "Espíritu Santo, Quebrada"
      }
    },
    {
      "geometry": {
        "type": "Point",
        "coordinates": [
          -71.1,
          -34.116667
        ]
      },
      "type": "Feature",
      "properties": {
        "hierarchy": [
          "tgn:7293199",
          "tgn:1001708",
          "tgn:1000049",
          "tgn:1000002",
          "tgn:7029392"
        ],
        "placetype": [
          "aat:300008699"
        ],
        "id": 7293199,
        "name:xx": "Espinoza, Quebrada de"
      }
    }
  ]
}
