{
  "geometry": {
    "type": "Point",
    "coordinates": [
      15.2833,
      -9.2667
    ]
  },
  "type": "Feature",
  "properties": {
    "hierarchy": [
      "tgn:1087856",
      "tgn:7001242",
      "tgn:1000149",
      "tgn:1000834",
      "tgn:7029392"
    ],
    "placetype": [
      "aat:300008347"
    ],
    "id": 1087856,
    "name:xx": "Lucala"
  }
}
