{
  "geometry": {
    "type": "Point",
    "coordinates": [
      -105.8833,
      37.35
    ]
  },
  "type": "Feature",
  "properties": {
    "hierarchy": [
      "tgn:2697992",
      "tgn:1000001",
      "tgn:7012149",
      "tgn:2000213",
      "tgn:7007158",
      "tgn:7029392"
    ],
    "placetype": [
      "aat:300008680"
    ],
    "id": 2697992,
    "name:xx": "Stout Creek Lakes"
  }
}
