{
  "geometry": {
    "type": "Point",
    "coordinates": [
      40.1333,
      49.35
    ]
  },
  "type": "Feature",
  "properties": {
    "hierarchy": [
      "tgn:1056936",
      "tgn:1000003",
      "tgn:7012067",
      "tgn:7006660",
      "tgn:7029392"
    ],
    "placetype": [
      "aat:300008347"
    ],
    "id": 1056936,
    "name:xx": "Melovoye"
  }
}
