{
  "geometry": {
    "type": "Point",
    "coordinates": [
      -84.3667,
      33.7333
    ]
  },
  "type": "Feature",
  "properties": {
    "hierarchy": [
      "tgn:2213102",
      "tgn:1000001",
      "tgn:7012149",
      "tgn:2000351",
      "tgn:7007248",
      "tgn:7029392"
    ],
    "placetype": [
      "aat:300008347"
    ],
    "id": 2213102,
    "name:xx": "Cabbage Town"
  }
}
