{
  "geometry": {
    "type": "Point",
    "coordinates": [
      -88.7333,
      45.8167
    ]
  },
  "type": "Feature",
  "properties": {
    "hierarchy": [
      "tgn:2151074",
      "tgn:1000001",
      "tgn:2002323",
      "tgn:7012149",
      "tgn:7007922",
      "tgn:7029392"
    ],
    "placetype": [
      "aat:300008680"
    ],
    "id": 2151074,
    "name:xx": "Bastile Lake"
  }
}
