{
  "type": "FeatureCollection",
  "features": [
    {
      "geometry": {
        "type": "Point",
        "coordinates": [
          -83.4833,
          37.2333
        ]
      },
      "type": "Feature",
      "properties": {
        "hierarchy": [
          "tgn:2633700",
          "tgn:1000001",
          "tgn:7012149",
          "tgn:2000811",
          "tgn:7007255",
          "tgn:7029392"
        ],
        "placetype": [
          "aat:300008706"
        ],
        "id": 2633700,
        "name:xx": "Rush Creek"
      }
    },
    {
      "geometry": {
        "type": "Point",
        "coordinates": [
          -87.8833,
          46.8833
        ]
      },
      "type": "Feature",
      "properties": {
        "hierarchy": [
          "tgn:2633701",
          "tgn:1000001",
          "tgn:7012149",
          "tgn:2000975",
          "tgn:7007520",
          "tgn:7029392"
        ],
        "placetype": [
          "aat:300008706"
        ],
        "id": 2633701,
        "name:xx": "Rush Creek"
      }
    },
    {
      "geometry": {
        "type": "Point",
        "coordinates": [
          -85.9333,
          42.8833
        ]
      },
      "type": "Feature",
      "properties": {
        "hierarchy": [
          "tgn:2633702",
          "tgn:1000001",
          "tgn:7012149",
          "tgn:7007520",
          "tgn:7029392"
        ],
        "placetype": [
          "aat:300008706"
        ],
        "id": 2633702,
        "name:xx": "Rush Creek"
      }
    },
    {
      "geometry": {
        "type": "Point",
        "coordinates": [
          -83.95,
          42.9667
        ]
      },
      "type": "Feature",
      "properties": {
        "hierarchy": [
          "tgn:2633703",
          "tgn:1000001",
          "tgn:7012149",
          "tgn:1002892",
          "tgn:7007520",
          "tgn:7029392"
        ],
        "placetype": [
          "aat:300008706"
        ],
        "id": 2633703,
        "name:xx": "Rush Creek"
      }
    },
    {
      "geometry": {
        "type": "Point",
        "coordinates": [
          -91.9667,
          43.9333
        ]
      },
      "type": "Feature",
      "properties": {
        "hierarchy": [
          "tgn:2633704",
          "tgn:1000001",
          "tgn:7012149",
          "tgn:7007521",
          "tgn:7029392"
        ],
        "placetype": [
          "aat:300008706"
        ],
        "id": 2633704,
        "name:xx": "Rush Creek"
      }
    },
    {
      "geometry": {
        "type": "Point",
        "coordinates": [
          -93.6333,
          45.0833
        ]
      },
      "type": "Feature",
      "properties": {
        "hierarchy": [
          "tgn:2633705",
          "tgn:1000001",
          "tgn:2001025",
          "tgn:7012149",
          "tgn:7007521",
          "tgn:7029392"
        ],
        "placetype": [
          "aat:300008706"
        ],
        "id": 2633705,
        "name:xx": "Rush Creek"
      }
    },
    {
      "geometry": {
        "type": "Point",
        "coordinates": [
          -93.0167,
          45.6667
        ]
      },
      "type": "Feature",
      "properties": {
        "hierarchy": [
          "tgn:2633706",
          "tgn:1000001",
          "tgn:2001011",
          "tgn:7012149",
          "tgn:7007521",
          "tgn:7029392"
        ],
        "placetype": [
          "aat:300008706"
        ],
        "id": 2633706,
        "name:xx": "Rush Creek"
      }
    },
    {
      "geometry": {
        "type": "Point",
        "coordinates": [
          -91.1167,
          36.5833
        ]
      },
      "type": "Feature",
      "properties": {
        "hierarchy": [
          "tgn:2633707",
          "tgn:1000001",
          "tgn:7012149",
          "tgn:2001225",
          "tgn:7007523",
          "tgn:7029392"
        ],
        "placetype": [
          "aat:300008706"
        ],
        "id": 2633707,
        "name:xx": "Rush Creek"
      }
    },
    {
      "geometry": {
        "type": "Point",
        "coordinates": [
          -94.3833,
          39.2833
        ]
      },
      "type": "Feature",
      "properties": {
        "hierarchy": [
          "tgn:2633708",
          "tgn:1000001",
          "tgn:2001187",
          "tgn:7012149",
          "tgn:7007523",
          "tgn:7029392"
        ],
        "placetype": [
          "aat:300008706"
        ],
        "id": 2633708,
        "name:xx": "Rush Creek"
      }
    }
  ]
}
