{
  "type": "FeatureCollection",
  "features": [
    {
      "geometry": {
        "type": "Point",
        "coordinates": [
          0.7,
          46.9667
        ]
      },
      "type": "Feature",
      "properties": {
        "hierarchy": [
          "tgn:1032920",
          "tgn:1000003",
          "tgn:7002877",
          "tgn:1000070",
          "tgn:7029392"
        ],
        "placetype": [
          "aat:300008347"
        ],
        "id": 1032920,
        "name:xx": "Descartes"
      }
    },
    {
      "geometry": {
        "type": "Point",
        "coordinates": [
          7.4667,
          48.7667
        ]
      },
      "type": "Feature",
      "properties": {
        "hierarchy": [
          "tgn:1032922",
          "tgn:7002870",
          "tgn:1000003",
          "tgn:1000070",
          "tgn:7029392"
        ],
        "placetype": [
          "aat:300008347"
        ],
        "id": 1032922,
        "name:xx": "Dettwiller"
      }
    },
    {
      "geometry": {
        "type": "Point",
        "coordinates": [
          4.7,
          49.8833
        ]
      },
      "type": "Feature",
      "properties": {
        "hierarchy": [
          "tgn:1032924",
          "tgn:1000003",
          "tgn:7002880",
          "tgn:1000070",
          "tgn:7029392"
        ],
        "placetype": [
          "aat:300008347"
        ],
        "id": 1032924,
        "name:xx": "Deville"
      }
    },
    {
      "geometry": {
        "type": "Point",
        "coordinates": [
          5.0667,
          44.5167
        ]
      },
      "type": "Feature",
      "properties": {
        "hierarchy": [
          "tgn:1032928",
          "tgn:1000003",
          "tgn:1000070",
          "tgn:7002897",
          "tgn:7029392"
        ],
        "placetype": [
          "aat:300008347"
        ],
        "id": 1032928,
        "name:xx": "Dieulefit"
      }
    },
    {
      "geometry": {
        "type": "Point",
        "coordinates": [
          6.0833,
          48.8667
        ]
      },
      "type": "Feature",
      "properties": {
        "hierarchy": [
          "tgn:1032929",
          "tgn:1000003",
          "tgn:7002888",
          "tgn:1000070",
          "tgn:7029392"
        ],
        "placetype": [
          "aat:300008347"
        ],
        "id": 1032929,
        "name:xx": "Dieulouard"
      }
    }
  ]
}
