{
  "geometry": {
    "type": "Point",
    "coordinates": [
      -113.6333,
      48.7667
    ]
  },
  "type": "Feature",
  "properties": {
    "hierarchy": [
      "tgn:2673929",
      "tgn:1000001",
      "tgn:7012149",
      "tgn:2001277",
      "tgn:7007524",
      "tgn:7029392"
    ],
    "placetype": [
      "aat:300008680"
    ],
    "id": 2673929,
    "name:xx": "Snow Moon Lake"
  }
}
