{
  "geometry": {
    "type": "Point",
    "coordinates": [
      -101.6667,
      54.9667
    ]
  },
  "type": "Feature",
  "properties": {
    "hierarchy": [
      "tgn:1116866",
      "tgn:7005685",
      "tgn:1000001",
      "tgn:7029392"
    ],
    "placetype": [
      "aat:300008680"
    ],
    "id": 1116866,
    "name:xx": "Kisseynew Lake"
  }
}
