{
  "geometry": {
    "type": "Point",
    "coordinates": [
      -119.85,
      48.5167
    ]
  },
  "type": "Feature",
  "properties": {
    "hierarchy": [
      "tgn:2634548",
      "tgn:1000001",
      "tgn:7012149",
      "tgn:1002742",
      "tgn:7007920",
      "tgn:7029392"
    ],
    "placetype": [
      "aat:300008706"
    ],
    "id": 2634548,
    "name:xx": "Rusty Creek"
  }
}
