{
  "geometry": {
    "type": "Point",
    "coordinates": [
      75.95,
      28.65
    ]
  },
  "type": "Feature",
  "properties": {
    "hierarchy": [
      "tgn:7573183",
      "tgn:1000004",
      "tgn:1001871",
      "tgn:7000198",
      "tgn:7029392"
    ],
    "placetype": [
      "aat:300008347"
    ],
    "name:en": "Jui",
    "id": 7573183
  }
}
