{
  "geometry": {
    "type": "Point",
    "coordinates": [
      -93.35,
      29.8833
    ]
  },
  "type": "Feature",
  "properties": {
    "hierarchy": [
      "tgn:2758599",
      "tgn:1000001",
      "tgn:7020676",
      "tgn:7012149",
      "tgn:7007256",
      "tgn:7029392"
    ],
    "placetype": [
      "aat:300006075"
    ],
    "id": 2758599,
    "name:xx": "West Cove Canal"
  }
}
