{
  "geometry": {
    "type": "Point",
    "coordinates": [
      30.65,
      25.75
    ]
  },
  "type": "Feature",
  "properties": {
    "hierarchy": [
      "tgn:7535625",
      "tgn:7001242",
      "tgn:7016833",
      "tgn:7001334",
      "tgn:7029392"
    ],
    "placetype": [
      "aat:300008697"
    ],
    "name:en": "Ghazāl al Mustajiddah, 'Ayn",
    "id": 7535625
  }
}
