{
  "geometry": {
    "type": "Point",
    "coordinates": [
      71.900288,
      26.667003
    ]
  },
  "type": "Feature",
  "properties": {
    "hierarchy": [
      "tgn:7588709",
      "tgn:1000004",
      "tgn:7000198",
      "tgn:7016788",
      "tgn:7029392"
    ],
    "placetype": [
      "aat:300008688"
    ],
    "name:en": "Birmāri Talāi",
    "id": 7588709
  }
}
