{
  "type": "FeatureCollection",
  "features": [
    {
      "geometry": {
        "type": "Point",
        "coordinates": [
          -179.5,
          71
        ]
      },
      "type": "Feature",
      "properties": {
        "hierarchy": [
          "tgn:1009670",
          "tgn:6001445",
          "tgn:1000004",
          "tgn:7018214",
          "tgn:7002435",
          "tgn:7029392"
        ],
        "placetype": [
          "aat:300008791"
        ],
        "id": 1009670,
        "name:xx": "Vrangelya, Ostrov"
      }
    },
    {
      "geometry": {
        "type": "Point",
        "coordinates": [
          -178.9,
          -18.8667
        ]
      },
      "type": "Feature",
      "properties": {
        "hierarchy": [
          "tgn:1009671",
          "tgn:1000849",
          "tgn:1010095",
          "tgn:7000493",
          "tgn:1000006",
          "tgn:7029392"
        ],
        "placetype": [
          "aat:300008791"
        ],
        "id": 1009671,
        "name:xx": "Vuanggava Island"
      }
    },
    {
      "geometry": {
        "type": "Point",
        "coordinates": [
          14.966667,
          38.4
        ]
      },
      "type": "Feature",
      "properties": {
        "hierarchy": [
          "tgn:1009672",
          "tgn:1000003",
          "tgn:7008315",
          "tgn:7003122",
          "tgn:7003157",
          "tgn:1000080",
          "tgn:7029392"
        ],
        "placetype": [
          "aat:300008791"
        ],
        "id": 1009672,
        "name:xx": "Vulcano, Isola"
      }
    },
    {
      "geometry": {
        "type": "Point",
        "coordinates": [
          35.162,
          24.666212
        ]
      },
      "type": "Feature",
      "properties": {
        "hierarchy": [
          "tgn:1009673",
          "tgn:7001242",
          "tgn:7001311",
          "tgn:7016833",
          "tgn:7029392"
        ],
        "placetype": [
          "aat:300008791"
        ],
        "name:en": "W훮d카 Jim훮l, Jaz카rat",
        "id": 1009673
      }
    },
    {
      "geometry": {
        "type": "Point",
        "coordinates": [
          175.1,
          -36.8
        ]
      },
      "type": "Feature",
      "properties": {
        "hierarchy": [
          "tgn:1009678",
          "tgn:7000508",
          "tgn:1008380",
          "tgn:1000226",
          "tgn:1000006",
          "tgn:7029392"
        ],
        "placetype": [
          "aat:300008791"
        ],
        "name:en": "Waiheke Island",
        "id": 1009678
      }
    },
    {
      "geometry": {
        "type": "Point",
        "coordinates": [
          3.5833,
          51.55
        ]
      },
      "type": "Feature",
      "properties": {
        "hierarchy": [
          "tgn:1009679",
          "tgn:1000003",
          "tgn:7003635",
          "tgn:7016845",
          "tgn:7029392"
        ],
        "placetype": [
          "aat:300008791"
        ],
        "id": 1009679,
        "name:xx": "Walcheren"
      }
    }
  ]
}
