{
  "geometry": {
    "type": "Point",
    "coordinates": [
      -111.0667,
      33.7667
    ]
  },
  "type": "Feature",
  "properties": {
    "hierarchy": [
      "tgn:2230604",
      "tgn:1000001",
      "tgn:7006451",
      "tgn:2000093",
      "tgn:7012149",
      "tgn:7029392"
    ],
    "placetype": [
      "aat:300006191"
    ],
    "id": 2230604,
    "name:xx": "Center Ridge Tank"
  }
}
