{
  "geometry": {
    "type": "Point",
    "coordinates": [
      90.4833,
      23.45
    ]
  },
  "type": "Feature",
  "properties": {
    "hierarchy": [
      "tgn:1065581",
      "tgn:7000189",
      "tgn:1000004",
      "tgn:1000105",
      "tgn:7029392"
    ],
    "placetype": [
      "aat:300008347"
    ],
    "id": 1065581,
    "name:xx": "Bāghia"
  }
}
