{
  "type": "FeatureCollection",
  "features": [
    {
      "geometry": {
        "type": "Point",
        "coordinates": [
          69.25,
          39.5833
        ]
      },
      "type": "Feature",
      "properties": {
        "hierarchy": [
          "tgn:1110211",
          "tgn:1000004",
          "tgn:7029392"
        ],
        "placetype": [
          "aat:300386831"
        ],
        "id": 1110211,
        "name:xx": "Turkestanskiy Khrebet"
      }
    },
    {
      "geometry": {
        "type": "Point",
        "coordinates": [
          170.716667,
          -43.75
        ]
      },
      "type": "Feature",
      "properties": {
        "hierarchy": [
          "tgn:1110212",
          "tgn:1009227",
          "tgn:7001866",
          "tgn:1000226",
          "tgn:1000006",
          "tgn:7029392"
        ],
        "placetype": [
          "aat:300386831",
          "aat:300008795"
        ],
        "name:en": "Two Thumb Range",
        "id": 1110212
      }
    },
    {
      "geometry": {
        "type": "Point",
        "coordinates": [
          70.3333,
          42
        ]
      },
      "type": "Feature",
      "properties": {
        "hierarchy": [
          "tgn:1110214",
          "tgn:1000004",
          "tgn:7029392"
        ],
        "placetype": [
          "aat:300386831"
        ],
        "id": 1110214,
        "name:xx": "Ugamskij chrebet"
      }
    },
    {
      "geometry": {
        "type": "Point",
        "coordinates": [
          69.75,
          38.5333
        ]
      },
      "type": "Feature",
      "properties": {
        "hierarchy": [
          "tgn:1110216",
          "tgn:7011631",
          "tgn:1000004",
          "tgn:7014835",
          "tgn:7029392"
        ],
        "placetype": [
          "aat:300386831"
        ],
        "id": 1110216,
        "name:xx": "Vakhshskiy Khrebet"
      }
    },
    {
      "geometry": {
        "type": "Point",
        "coordinates": [
          -125.5,
          49.5
        ]
      },
      "type": "Feature",
      "properties": {
        "hierarchy": [
          "tgn:1110217",
          "tgn:7005735",
          "tgn:7005685",
          "tgn:1000001",
          "tgn:7013409",
          "tgn:7029392"
        ],
        "placetype": [
          "aat:300386831"
        ],
        "id": 1110217,
        "name:xx": "Vancouver Island Ranges"
      }
    },
    {
      "geometry": {
        "type": "Point",
        "coordinates": [
          45.4167,
          39.9667
        ]
      },
      "type": "Feature",
      "properties": {
        "hierarchy": [
          "tgn:1110218",
          "tgn:1000004",
          "tgn:7029392"
        ],
        "placetype": [
          "aat:300386831"
        ],
        "id": 1110218,
        "name:xx": "Vardenisskiy Khrebet"
      }
    }
  ]
}
