{
  "type": "FeatureCollection",
  "features": [
    {
      "geometry": {
        "type": "Point",
        "coordinates": [
          -106.85,
          38.9
        ]
      },
      "type": "Feature",
      "properties": {
        "hierarchy": [
          "tgn:2199370",
          "tgn:1000001",
          "tgn:7012149",
          "tgn:2000217",
          "tgn:7007158",
          "tgn:7029392"
        ],
        "placetype": [
          "aat:300008706"
        ],
        "id": 2199370,
        "name:xx": "Brush Creek"
      }
    },
    {
      "geometry": {
        "type": "Point",
        "coordinates": [
          -106.3667,
          38.4
        ]
      },
      "type": "Feature",
      "properties": {
        "hierarchy": [
          "tgn:2199371",
          "tgn:1000001",
          "tgn:7012149",
          "tgn:7007158",
          "tgn:2000246",
          "tgn:7029392"
        ],
        "placetype": [
          "aat:300008706"
        ],
        "id": 2199371,
        "name:xx": "Brush Creek"
      }
    },
    {
      "geometry": {
        "type": "Point",
        "coordinates": [
          -105.6,
          38.2333
        ]
      },
      "type": "Feature",
      "properties": {
        "hierarchy": [
          "tgn:2199372",
          "tgn:1000001",
          "tgn:7012149",
          "tgn:2000205",
          "tgn:7007158",
          "tgn:7029392"
        ],
        "placetype": [
          "aat:300008706"
        ],
        "id": 2199372,
        "name:xx": "Brush Creek"
      }
    },
    {
      "geometry": {
        "type": "Point",
        "coordinates": [
          -104.4333,
          37.0333
        ]
      },
      "type": "Feature",
      "properties": {
        "hierarchy": [
          "tgn:2199373",
          "tgn:1000001",
          "tgn:7012149",
          "tgn:2000227",
          "tgn:7007158",
          "tgn:7029392"
        ],
        "placetype": [
          "aat:300008706"
        ],
        "id": 2199373,
        "name:xx": "Brush Creek"
      }
    },
    {
      "geometry": {
        "type": "Point",
        "coordinates": [
          -81.9833,
          30.7167
        ]
      },
      "type": "Feature",
      "properties": {
        "hierarchy": [
          "tgn:2199374",
          "tgn:1000001",
          "tgn:7012149",
          "tgn:2000280",
          "tgn:7007240",
          "tgn:7029392"
        ],
        "placetype": [
          "aat:300008706"
        ],
        "id": 2199374,
        "name:xx": "Brush Creek"
      }
    },
    {
      "geometry": {
        "type": "Point",
        "coordinates": [
          -82.9167,
          33.1
        ]
      },
      "type": "Feature",
      "properties": {
        "hierarchy": [
          "tgn:2199375",
          "tgn:1000001",
          "tgn:7012149",
          "tgn:2000441",
          "tgn:7007248",
          "tgn:7029392"
        ],
        "placetype": [
          "aat:300008706"
        ],
        "id": 2199375,
        "name:xx": "Brush Creek"
      }
    },
    {
      "geometry": {
        "type": "Point",
        "coordinates": [
          -85.2,
          33.2167
        ]
      },
      "type": "Feature",
      "properties": {
        "hierarchy": [
          "tgn:2199376",
          "tgn:1000001",
          "tgn:7012149",
          "tgn:2000365",
          "tgn:7007248",
          "tgn:7029392"
        ],
        "placetype": [
          "aat:300008706"
        ],
        "id": 2199376,
        "name:xx": "Brush Creek"
      }
    },
    {
      "geometry": {
        "type": "Point",
        "coordinates": [
          -84.25,
          33.55
        ]
      },
      "type": "Feature",
      "properties": {
        "hierarchy": [
          "tgn:2199377",
          "tgn:1000001",
          "tgn:7012149",
          "tgn:2000366",
          "tgn:7007248",
          "tgn:7029392"
        ],
        "placetype": [
          "aat:300008706"
        ],
        "id": 2199377,
        "name:xx": "Brush Creek"
      }
    },
    {
      "geometry": {
        "type": "Point",
        "coordinates": [
          -83.3167,
          34.1
        ]
      },
      "type": "Feature",
      "properties": {
        "hierarchy": [
          "tgn:2199378",
          "tgn:1000001",
          "tgn:7012149",
          "tgn:2000388",
          "tgn:7007248",
          "tgn:7029392"
        ],
        "placetype": [
          "aat:300008706"
        ],
        "id": 2199378,
        "name:xx": "Brush Creek"
      }
    },
    {
      "geometry": {
        "type": "Point",
        "coordinates": [
          -112.0333,
          42.4833
        ]
      },
      "type": "Feature",
      "properties": {
        "hierarchy": [
          "tgn:2199379",
          "tgn:2000454",
          "tgn:1000001",
          "tgn:7012149",
          "tgn:7007250",
          "tgn:7029392"
        ],
        "placetype": [
          "aat:300008706"
        ],
        "id": 2199379,
        "name:xx": "Brush Creek"
      }
    }
  ]
}
