{
  "geometry": {
    "type": "Point",
    "coordinates": [
      21.441389,
      39.49
    ]
  },
  "type": "Feature",
  "properties": {
    "hierarchy": [
      "tgn:7232986",
      "tgn:7002752",
      "tgn:7001399",
      "tgn:1000003",
      "tgn:1000074",
      "tgn:7029392"
    ],
    "placetype": [
      "aat:300008795"
    ],
    "id": 7232986,
    "name:xx": "Lápata"
  }
}
