{
  "geometry": {
    "type": "Point",
    "coordinates": [
      32.45,
      25.566667
    ]
  },
  "type": "Feature",
  "properties": {
    "hierarchy": [
      "tgn:7529000",
      "tgn:7001242",
      "tgn:7016833",
      "tgn:7000123",
      "tgn:7029392"
    ],
    "placetype": [
      "aat:300005926"
    ],
    "name:en": "Sīdī 'Alī",
    "id": 7529000
  }
}
