{
  "type": "FeatureCollection",
  "features": [
    {
      "geometry": {
        "type": "Point",
        "coordinates": [
          -155.7833,
          20.2167
        ]
      },
      "type": "Feature",
      "properties": {
        "hierarchy": [
          "tgn:2024850",
          "tgn:7023902",
          "tgn:1000001",
          "tgn:7012149",
          "tgn:7007249",
          "tgn:7029392"
        ],
        "placetype": [
          "aat:300008347"
        ],
        "id": 2024850,
        "name:xx": "Halaula"
      }
    },
    {
      "geometry": {
        "type": "Point",
        "coordinates": [
          -155.7667,
          20.2
        ]
      },
      "type": "Feature",
      "properties": {
        "hierarchy": [
          "tgn:2024851",
          "tgn:7023902",
          "tgn:1000001",
          "tgn:7012149",
          "tgn:7007249",
          "tgn:7029392"
        ],
        "placetype": [
          "aat:300008347"
        ],
        "id": 2024851,
        "name:xx": "Halawa"
      }
    },
    {
      "geometry": {
        "type": "Point",
        "coordinates": [
          -156.7333,
          21.15
        ]
      },
      "type": "Feature",
      "properties": {
        "hierarchy": [
          "tgn:2024852",
          "tgn:1002648",
          "tgn:1000001",
          "tgn:7012149",
          "tgn:7007249",
          "tgn:7029392"
        ],
        "placetype": [
          "aat:300008347",
          "aat:300387210"
        ],
        "id": 2024852,
        "name:xx": "Halawa"
      }
    },
    {
      "geometry": {
        "type": "Point",
        "coordinates": [
          -157.9167,
          21.3667
        ]
      },
      "type": "Feature",
      "properties": {
        "hierarchy": [
          "tgn:2024853",
          "tgn:1002483",
          "tgn:7019080",
          "tgn:1000001",
          "tgn:7012149",
          "tgn:7007249",
          "tgn:7029392"
        ],
        "placetype": [
          "aat:300008347"
        ],
        "id": 2024853,
        "name:xx": "Halawa Heights"
      }
    },
    {
      "geometry": {
        "type": "Point",
        "coordinates": [
          -158.1,
          21.5833
        ]
      },
      "type": "Feature",
      "properties": {
        "hierarchy": [
          "tgn:2024857",
          "tgn:1002483",
          "tgn:7019080",
          "tgn:1000001",
          "tgn:7012149",
          "tgn:7007249",
          "tgn:7029392"
        ],
        "placetype": [
          "aat:300008347"
        ],
        "id": 2024857,
        "name:xx": "Haleiwa"
      }
    },
    {
      "geometry": {
        "type": "Point",
        "coordinates": [
          -156.8,
          20.8333
        ]
      },
      "type": "Feature",
      "properties": {
        "hierarchy": [
          "tgn:2024858",
          "tgn:1002648",
          "tgn:1000001",
          "tgn:1007799",
          "tgn:7012149",
          "tgn:7007249",
          "tgn:7029392"
        ],
        "placetype": [
          "aat:300008347",
          "aat:300387210"
        ],
        "id": 2024858,
        "name:xx": "Halepalaoa Landing"
      }
    },
    {
      "geometry": {
        "type": "Point",
        "coordinates": [
          -156.35,
          20.8667
        ]
      },
      "type": "Feature",
      "properties": {
        "hierarchy": [
          "tgn:2024859",
          "tgn:1002648",
          "tgn:1000001",
          "tgn:7019158",
          "tgn:7012149",
          "tgn:7007249",
          "tgn:7029392"
        ],
        "placetype": [
          "aat:300008347"
        ],
        "id": 2024859,
        "name:xx": "Haliimaile"
      }
    }
  ]
}
