{
  "type": "FeatureCollection",
  "features": [
    {
      "geometry": {
        "type": "Point",
        "coordinates": [
          140.5667,
          36
        ]
      },
      "type": "Feature",
      "properties": {
        "hierarchy": [
          "tgn:1116870",
          "tgn:1000987",
          "tgn:1000004",
          "tgn:7000894",
          "tgn:1000120",
          "tgn:7029392"
        ],
        "placetype": [
          "aat:300008680"
        ],
        "id": 1116870,
        "name:xx": "Kita-ura"
      }
    },
    {
      "geometry": {
        "type": "Point",
        "coordinates": [
          -127.7833,
          53.1167
        ]
      },
      "type": "Feature",
      "properties": {
        "hierarchy": [
          "tgn:1116872",
          "tgn:7005735",
          "tgn:7005685",
          "tgn:1000001",
          "tgn:7029392"
        ],
        "placetype": [
          "aat:300008680"
        ],
        "id": 1116872,
        "name:xx": "Kitlope Lake"
      }
    },
    {
      "geometry": {
        "type": "Point",
        "coordinates": [
          29.1667,
          -2
        ]
      },
      "type": "Feature",
      "properties": {
        "hierarchy": [
          "tgn:1116874",
          "tgn:7001242",
          "tgn:7029392"
        ],
        "placetype": [
          "aat:300008680"
        ],
        "id": 1116874,
        "name:xx": "Kivu, Lac"
      }
    },
    {
      "geometry": {
        "type": "Point",
        "coordinates": [
          -108.8833,
          51.6167
        ]
      },
      "type": "Feature",
      "properties": {
        "hierarchy": [
          "tgn:1116875",
          "tgn:7005685",
          "tgn:1000001",
          "tgn:7005805",
          "tgn:7029392"
        ],
        "placetype": [
          "aat:300008680"
        ],
        "id": 1116875,
        "name:xx": "Kiyiu Lake"
      }
    },
    {
      "geometry": {
        "type": "Point",
        "coordinates": [
          13.166667,
          52.416667
        ]
      },
      "type": "Feature",
      "properties": {
        "hierarchy": [
          "tgn:1116878",
          "tgn:7003712",
          "tgn:7003670",
          "tgn:1000003",
          "tgn:7000084",
          "tgn:7029392"
        ],
        "placetype": [
          "aat:300008680"
        ],
        "id": 1116878,
        "name:xx": "Kleiner Wannsee"
      }
    },
    {
      "geometry": {
        "type": "Point",
        "coordinates": [
          12.9,
          52.433333
        ]
      },
      "type": "Feature",
      "properties": {
        "hierarchy": [
          "tgn:1116879",
          "tgn:7000096",
          "tgn:1000003",
          "tgn:7000084",
          "tgn:7029392"
        ],
        "placetype": [
          "aat:300008680"
        ],
        "id": 1116879,
        "name:xx": "Kleiner Zern-See"
      }
    }
  ]
}
