{
  "geometry": {
    "type": "Point",
    "coordinates": [
      -83.2667,
      37.1833
    ]
  },
  "type": "Feature",
  "properties": {
    "hierarchy": [
      "tgn:2477818",
      "tgn:1000001",
      "tgn:7012149",
      "tgn:2000811",
      "tgn:7007255",
      "tgn:7029392"
    ],
    "placetype": [
      "aat:300008706"
    ],
    "id": 2477818,
    "name:xx": "MacIntosh Creek"
  }
}
