{
  "geometry": {
    "type": "Point",
    "coordinates": [
      -119.05,
      37.65
    ]
  },
  "type": "Feature",
  "properties": {
    "hierarchy": [
      "tgn:2516030",
      "tgn:1000001",
      "tgn:7012149",
      "tgn:7007157",
      "tgn:7029392"
    ],
    "placetype": [
      "aat:300008798"
    ],
    "id": 2516030,
    "name:xx": "Minaret Summit"
  }
}
