{
  "geometry": {
    "type": "Point",
    "coordinates": [
      -111.4667,
      41.9833
    ]
  },
  "type": "Feature",
  "properties": {
    "hierarchy": [
      "tgn:2706669",
      "tgn:1000001",
      "tgn:7012149",
      "tgn:2002117",
      "tgn:7007827",
      "tgn:7029392"
    ],
    "placetype": [
      "aat:300008680"
    ],
    "id": 2706669,
    "name:xx": "Swan Peak Pond"
  }
}
