{
  "geometry": {
    "type": "Point",
    "coordinates": [
      -92.55,
      34.0667
    ]
  },
  "type": "Feature",
  "properties": {
    "hierarchy": [
      "tgn:2007911",
      "tgn:1000001",
      "tgn:7016172",
      "tgn:7012149",
      "tgn:2000124",
      "tgn:7029392"
    ],
    "placetype": [
      "aat:300008347"
    ],
    "id": 2007911,
    "name:xx": "Carthage"
  }
}
