{
  "geometry": {
    "type": "Point",
    "coordinates": [
      -112.8833,
      39.1667
    ]
  },
  "type": "Feature",
  "properties": {
    "hierarchy": [
      "tgn:2626603",
      "tgn:1000001",
      "tgn:7012149",
      "tgn:2002114",
      "tgn:7007827",
      "tgn:7029392"
    ],
    "placetype": [
      "aat:300008798"
    ],
    "id": 2626603,
    "name:xx": "Rocky Knoll"
  }
}
