{
  "geometry": {
    "type": "Point",
    "coordinates": [
      -109.8333,
      33.9333
    ]
  },
  "type": "Feature",
  "properties": {
    "hierarchy": [
      "tgn:2782533",
      "tgn:2000090",
      "tgn:1000001",
      "tgn:7006451",
      "tgn:7012149",
      "tgn:7029392"
    ],
    "placetype": [
      "aat:300008905"
    ],
    "id": 2782533,
    "name:xx": "Woolsey Lake"
  }
}
