{
  "type": "FeatureCollection",
  "features": [
    {
      "geometry": {
        "type": "Point",
        "coordinates": [
          -91.2,
          34.3833
        ]
      },
      "type": "Feature",
      "properties": {
        "hierarchy": [
          "tgn:2711890",
          "tgn:2000105",
          "tgn:1000001",
          "tgn:7016172",
          "tgn:7012149",
          "tgn:7029392"
        ],
        "placetype": [
          "aat:300006075"
        ],
        "id": 2711890,
        "name:xx": "Tarleton Ditch"
      }
    },
    {
      "geometry": {
        "type": "Point",
        "coordinates": [
          -79.7833,
          34.15
        ]
      },
      "type": "Feature",
      "properties": {
        "hierarchy": [
          "tgn:2711891",
          "tgn:1000001",
          "tgn:2001745",
          "tgn:7012149",
          "tgn:7007712",
          "tgn:7029392"
        ],
        "placetype": [
          "aat:300008347"
        ],
        "id": 2711891,
        "name:xx": "Tarleton Estates"
      }
    },
    {
      "geometry": {
        "type": "Point",
        "coordinates": [
          -71.95,
          43.9667
        ]
      },
      "type": "Feature",
      "properties": {
        "hierarchy": [
          "tgn:2711892",
          "tgn:1000001",
          "tgn:2001424",
          "tgn:7012149",
          "tgn:7007564",
          "tgn:7029392"
        ],
        "placetype": [
          "aat:300008680"
        ],
        "id": 2711892,
        "name:xx": "Tarleton, Lake"
      }
    },
    {
      "geometry": {
        "type": "Point",
        "coordinates": [
          -89.2,
          32.2333
        ]
      },
      "type": "Feature",
      "properties": {
        "hierarchy": [
          "tgn:2711893",
          "tgn:1000001",
          "tgn:7012149",
          "tgn:2001136",
          "tgn:7007522",
          "tgn:7029392"
        ],
        "placetype": [
          "aat:300008706"
        ],
        "id": 2711893,
        "name:xx": "Tarlow Creek"
      }
    },
    {
      "geometry": {
        "type": "Point",
        "coordinates": [
          -82.7167,
          35.9667
        ]
      },
      "type": "Feature",
      "properties": {
        "hierarchy": [
          "tgn:2711894",
          "tgn:1000001",
          "tgn:7012149",
          "tgn:2001516",
          "tgn:7007709",
          "tgn:7029392"
        ],
        "placetype": [
          "aat:300008699"
        ],
        "id": 2711894,
        "name:xx": "Tarlton Branch"
      }
    },
    {
      "geometry": {
        "type": "Point",
        "coordinates": [
          -136.15,
          58
        ]
      },
      "type": "Feature",
      "properties": {
        "hierarchy": [
          "tgn:2711896",
          "tgn:7006450",
          "tgn:1000001",
          "tgn:7012149",
          "tgn:7019760",
          "tgn:7029392"
        ],
        "placetype": [
          "aat:300008798"
        ],
        "id": 2711896,
        "name:xx": "Tarn Mountain"
      }
    },
    {
      "geometry": {
        "type": "Point",
        "coordinates": [
          -146.2833,
          63.15
        ]
      },
      "type": "Feature",
      "properties": {
        "hierarchy": [
          "tgn:2711897",
          "tgn:7006450",
          "tgn:1000001",
          "tgn:7012149",
          "tgn:7029392"
        ],
        "placetype": [
          "aat:300008761"
        ],
        "id": 2711897,
        "name:xx": "Tarn Valley"
      }
    },
    {
      "geometry": {
        "type": "Point",
        "coordinates": [
          -68.2,
          44.35
        ]
      },
      "type": "Feature",
      "properties": {
        "hierarchy": [
          "tgn:2711898",
          "tgn:1000001",
          "tgn:2000922",
          "tgn:7012149",
          "tgn:7007515",
          "tgn:7029392"
        ],
        "placetype": [
          "aat:300008680"
        ],
        "id": 2711898,
        "name:xx": "Tarn, The"
      }
    },
    {
      "geometry": {
        "type": "Point",
        "coordinates": [
          -74.4333,
          40.9
        ]
      },
      "type": "Feature",
      "properties": {
        "hierarchy": [
          "tgn:2711899",
          "tgn:1000001",
          "tgn:1002695",
          "tgn:7012149",
          "tgn:7007565",
          "tgn:7029392"
        ],
        "placetype": [
          "aat:300008680"
        ],
        "id": 2711899,
        "name:xx": "Tarn, The"
      }
    }
  ]
}
