{
  "geometry": {
    "type": "Point",
    "coordinates": [
      -63.5167,
      50.5333
    ]
  },
  "type": "Feature",
  "properties": {
    "hierarchy": [
      "tgn:1115389",
      "tgn:7005685",
      "tgn:1000001",
      "tgn:7005804",
      "tgn:7029392"
    ],
    "placetype": [
      "aat:300008680"
    ],
    "id": 1115389,
    "name:xx": "Allard, Lac"
  }
}
