{
  "geometry": {
    "type": "Point",
    "coordinates": [
      -72.6167,
      43.5833
    ]
  },
  "type": "Feature",
  "properties": {
    "hierarchy": [
      "tgn:2109476",
      "tgn:1000001",
      "tgn:2002136",
      "tgn:7012149",
      "tgn:7007828",
      "tgn:7029392"
    ],
    "placetype": [
      "aat:300008347"
    ],
    "id": 2109476,
    "name:xx": "Bridgewater"
  }
}
