{
  "geometry": {
    "type": "Point",
    "coordinates": [
      -71.25,
      8.5667
    ]
  },
  "type": "Feature",
  "properties": {
    "hierarchy": [
      "tgn:1025093",
      "tgn:1001892",
      "tgn:1000002",
      "tgn:1000059",
      "tgn:7029392"
    ],
    "placetype": [
      "aat:300008347"
    ],
    "id": 1025093,
    "name:xx": "Ejido"
  }
}
