{
  "geometry": {
    "type": "Point",
    "coordinates": [
      -1.7833,
      43.3667
    ]
  },
  "type": "Feature",
  "properties": {
    "hierarchy": [
      "tgn:1121875",
      "tgn:1000003",
      "tgn:7029392"
    ],
    "placetype": [
      "aat:300008707"
    ],
    "name:fr": "Bidassoa",
    "id": 1121875,
    "name:eu": "Bidasoa, Río"
  }
}
