{
  "geometry": {
    "type": "Point",
    "coordinates": [
      -50.1333,
      -16.7833
    ]
  },
  "type": "Feature",
  "properties": {
    "hierarchy": [
      "tgn:1022319",
      "tgn:7012827",
      "tgn:7002454",
      "tgn:1000047",
      "tgn:1000002",
      "tgn:7029392"
    ],
    "placetype": [
      "aat:300008347"
    ],
    "id": 1022319,
    "name:xx": "Palminópolis"
  }
}
