{
  "geometry": {
    "type": "Point",
    "coordinates": [
      131.4333,
      -13.4833
    ]
  },
  "type": "Feature",
  "properties": {
    "hierarchy": [
      "tgn:1096385",
      "tgn:7000490",
      "tgn:1000006",
      "tgn:7001829",
      "tgn:7029392"
    ],
    "placetype": [
      "aat:300008347"
    ],
    "id": 1096385,
    "name:xx": "Brocks Creek"
  }
}
