{
  "geometry": {
    "type": "Point",
    "coordinates": [
      -91.0667,
      40.85
    ]
  },
  "type": "Feature",
  "properties": {
    "hierarchy": [
      "tgn:2300480",
      "tgn:1000001",
      "tgn:2000589",
      "tgn:7012149",
      "tgn:7007253",
      "tgn:7029392"
    ],
    "placetype": [
      "aat:300008680"
    ],
    "id": 2300480,
    "name:xx": "Dumbbell Lake"
  }
}
