{
  "geometry": {
    "type": "Point",
    "coordinates": [
      -81.75,
      38.7833
    ]
  },
  "type": "Feature",
  "properties": {
    "hierarchy": [
      "tgn:2168845",
      "tgn:1000001",
      "tgn:7012149",
      "tgn:2002268",
      "tgn:7013961",
      "tgn:7029392"
    ],
    "placetype": [
      "aat:300006191"
    ],
    "id": 2168845,
    "name:xx": "Big Horse Lake"
  }
}
