{
  "geometry": {
    "type": "Point",
    "coordinates": [
      11.25,
      53.766667
    ]
  },
  "type": "Feature",
  "properties": {
    "hierarchy": [
      "tgn:1037249",
      "tgn:1000003",
      "tgn:7000094",
      "tgn:7000084",
      "tgn:7029392"
    ],
    "placetype": [
      "aat:300008347"
    ],
    "id": 1037249,
    "name:xx": "Mühlen Eichsen"
  }
}
