{
  "geometry": {
    "type": "Point",
    "coordinates": [
      -95.0833,
      33.65
    ]
  },
  "type": "Feature",
  "properties": {
    "hierarchy": [
      "tgn:2185196",
      "tgn:1000001",
      "tgn:7012149",
      "tgn:2002061",
      "tgn:7007826",
      "tgn:7029392"
    ],
    "placetype": [
      "aat:300008706"
    ],
    "id": 2185196,
    "name:xx": "Boggy Creek"
  }
}
