{
  "type": "FeatureCollection",
  "features": [
    {
      "geometry": {
        "type": "Point",
        "coordinates": [
          -120.75,
          48.5667
        ]
      },
      "type": "Feature",
      "properties": {
        "hierarchy": [
          "tgn:2376810",
          "tgn:1000001",
          "tgn:7012149",
          "tgn:7007920",
          "tgn:7029392"
        ],
        "placetype": [
          "aat:300008798"
        ],
        "id": 2376810,
        "name:xx": "Hardy, Mount"
      }
    },
    {
      "geometry": {
        "type": "Point",
        "coordinates": [
          -113.0833,
          34.7333
        ]
      },
      "type": "Feature",
      "properties": {
        "hierarchy": [
          "tgn:2376811",
          "tgn:1000001",
          "tgn:7006451",
          "tgn:7012149",
          "tgn:2000103",
          "tgn:7029392"
        ],
        "placetype": [
          "aat:300006191"
        ],
        "id": 2376811,
        "name:xx": "Hardy-Schell Tank"
      }
    },
    {
      "geometry": {
        "type": "Point",
        "coordinates": [
          -83.7667,
          33.4
        ]
      },
      "type": "Feature",
      "properties": {
        "hierarchy": [
          "tgn:2376812",
          "tgn:1000001",
          "tgn:7012149",
          "tgn:2000370",
          "tgn:7007248",
          "tgn:7029392"
        ],
        "placetype": [
          "aat:300008706"
        ],
        "id": 2376812,
        "name:xx": "Hardys Creek"
      }
    },
    {
      "geometry": {
        "type": "Point",
        "coordinates": [
          -79.6,
          36.6167
        ]
      },
      "type": "Feature",
      "properties": {
        "hierarchy": [
          "tgn:2376813",
          "tgn:1000001",
          "tgn:7012149",
          "tgn:2002180",
          "tgn:7007919",
          "tgn:7029392"
        ],
        "placetype": [
          "aat:300008706"
        ],
        "id": 2376813,
        "name:xx": "Hardys Creek"
      }
    },
    {
      "geometry": {
        "type": "Point",
        "coordinates": [
          -83.8,
          33.3667
        ]
      },
      "type": "Feature",
      "properties": {
        "hierarchy": [
          "tgn:2376814",
          "tgn:1000001",
          "tgn:7012149",
          "tgn:2000370",
          "tgn:7007248",
          "tgn:7029392"
        ],
        "placetype": [
          "aat:300008347"
        ],
        "id": 2376814,
        "name:xx": "Hardys Crossroads"
      }
    },
    {
      "geometry": {
        "type": "Point",
        "coordinates": [
          -71.3,
          42.45
        ]
      },
      "type": "Feature",
      "properties": {
        "hierarchy": [
          "tgn:2376815",
          "tgn:1000001",
          "tgn:1002665",
          "tgn:7012149",
          "tgn:7007517",
          "tgn:7029392"
        ],
        "placetype": [
          "aat:300008798"
        ],
        "id": 2376815,
        "name:xx": "Hardys Hill"
      }
    },
    {
      "geometry": {
        "type": "Point",
        "coordinates": [
          -82.1333,
          33.5667
        ]
      },
      "type": "Feature",
      "properties": {
        "hierarchy": [
          "tgn:2376816",
          "tgn:1000001",
          "tgn:2000327",
          "tgn:7012149",
          "tgn:7007248",
          "tgn:7029392"
        ],
        "placetype": [
          "aat:300006191"
        ],
        "id": 2376816,
        "name:xx": "Hardys Lake"
      }
    },
    {
      "geometry": {
        "type": "Point",
        "coordinates": [
          -86.4833,
          41.4833
        ]
      },
      "type": "Feature",
      "properties": {
        "hierarchy": [
          "tgn:2376817",
          "tgn:1000001",
          "tgn:7012149",
          "tgn:7014366",
          "tgn:7007252",
          "tgn:7029392"
        ],
        "placetype": [
          "aat:300008680"
        ],
        "id": 2376817,
        "name:xx": "Hardys Lake"
      }
    },
    {
      "geometry": {
        "type": "Point",
        "coordinates": [
          -90.4,
          38.1167
        ]
      },
      "type": "Feature",
      "properties": {
        "hierarchy": [
          "tgn:2376818",
          "tgn:1000001",
          "tgn:7012149",
          "tgn:1002517",
          "tgn:7007523",
          "tgn:7029392"
        ],
        "placetype": [
          "aat:300008680"
        ],
        "id": 2376818,
        "name:xx": "Hardys Lake"
      }
    },
    {
      "geometry": {
        "type": "Point",
        "coordinates": [
          -79.7,
          36.1667
        ]
      },
      "type": "Feature",
      "properties": {
        "hierarchy": [
          "tgn:2376819",
          "tgn:1000001",
          "tgn:7012149",
          "tgn:2001500",
          "tgn:7007709",
          "tgn:7029392"
        ],
        "placetype": [
          "aat:300006191"
        ],
        "id": 2376819,
        "name:xx": "Hardys Mill Pond"
      }
    }
  ]
}
