{
  "geometry": {
    "type": "Point",
    "coordinates": [
      120.1721,
      23.3814
    ]
  },
  "type": "Feature",
  "properties": {
    "hierarchy": [
      "tgn:7480672",
      "tgn:7468018",
      "tgn:1000004",
      "tgn:1000141",
      "tgn:7029392"
    ],
    "placetype": [
      "aat:300006495"
    ],
    "id": 7480672,
    "name:xx": "Budai Guoxiao"
  }
}
