{
  "geometry": {
    "type": "Point",
    "coordinates": [
      -92.8125,
      17.475
    ]
  },
  "type": "Feature",
  "properties": {
    "hierarchy": [
      "tgn:7412993",
      "tgn:1000001",
      "tgn:7005596",
      "tgn:7005560",
      "tgn:7029392"
    ],
    "placetype": [
      "aat:300008347"
    ],
    "id": 7412993,
    "name:es": "Zunu y Patastal"
  }
}
