{
  "geometry": {
    "type": "Point",
    "coordinates": [
      34.09288,
      27.790564
    ]
  },
  "type": "Feature",
  "properties": {
    "hierarchy": [
      "tgn:7539409",
      "tgn:7001242",
      "tgn:7016833",
      "tgn:7001336",
      "tgn:7029392"
    ],
    "placetype": [
      "aat:300008808"
    ],
    "name:en": "Qad Ibn Haddān",
    "id": 7539409
  }
}
