{
  "geometry": {
    "type": "Point",
    "coordinates": [
      -88.8167,
      45.0333
    ]
  },
  "type": "Feature",
  "properties": {
    "hierarchy": [
      "tgn:2339471",
      "tgn:1000001",
      "tgn:7012149",
      "tgn:2002339",
      "tgn:7007922",
      "tgn:7029392"
    ],
    "placetype": [
      "aat:300008680"
    ],
    "id": 2339471,
    "name:xx": "Frechette Lake"
  }
}
