{
  "geometry": {
    "type": "Point",
    "coordinates": [
      -81.25,
      29.0333
    ]
  },
  "type": "Feature",
  "properties": {
    "hierarchy": [
      "tgn:2568448",
      "tgn:1000001",
      "tgn:7012149",
      "tgn:1002977",
      "tgn:7007240",
      "tgn:7029392"
    ],
    "placetype": [
      "aat:300008680"
    ],
    "id": 2568448,
    "name:xx": "Park Lake"
  }
}
