{
  "geometry": {
    "type": "Point",
    "coordinates": [
      -104.8833,
      34.9167
    ]
  },
  "type": "Feature",
  "properties": {
    "hierarchy": [
      "tgn:2585340",
      "tgn:1000001",
      "tgn:7012149",
      "tgn:2001438",
      "tgn:7007566",
      "tgn:7029392"
    ],
    "placetype": [
      "aat:300000390"
    ],
    "id": 2585340,
    "name:xx": "Pintada Mine"
  }
}
