{
  "geometry": {
    "type": "Point",
    "coordinates": [
      -114.6333,
      44.1167
    ]
  },
  "type": "Feature",
  "properties": {
    "hierarchy": [
      "tgn:2555081",
      "tgn:1000001",
      "tgn:2000470",
      "tgn:7012149",
      "tgn:7007250",
      "tgn:7029392"
    ],
    "placetype": [
      "aat:300008680"
    ],
    "id": 2555081,
    "name:xx": "Ocalkens Lake"
  }
}
