{
  "geometry": {
    "type": "Point",
    "coordinates": [
      -83.8667,
      36.95
    ]
  },
  "type": "Feature",
  "properties": {
    "hierarchy": [
      "tgn:2250142",
      "tgn:1000001",
      "tgn:7012149",
      "tgn:7007255",
      "tgn:7029392"
    ],
    "placetype": [
      "aat:300008699"
    ],
    "id": 2250142,
    "name:xx": "Collins Fork"
  }
}
