{
  "geometry": {
    "type": "Point",
    "coordinates": [
      -80.65,
      28.3667
    ]
  },
  "type": "Feature",
  "properties": {
    "hierarchy": [
      "tgn:2511735",
      "tgn:1000001",
      "tgn:1002200",
      "tgn:7012149",
      "tgn:7007240",
      "tgn:7029392"
    ],
    "placetype": [
      "aat:300008850"
    ],
    "id": 2511735,
    "name:xx": "Milford Point"
  }
}
