{
  "type": "FeatureCollection",
  "features": [
    {
      "geometry": {
        "type": "Point",
        "coordinates": [
          8.3167,
          41.1167
        ]
      },
      "type": "Feature",
      "properties": {
        "hierarchy": [
          "tgn:1012462",
          "tgn:7015163",
          "tgn:1000003",
          "tgn:7003121",
          "tgn:1000080",
          "tgn:7029392"
        ],
        "placetype": [
          "aat:300386846"
        ],
        "id": 1012462,
        "name:xx": "Scorno, Punta di"
      }
    },
    {
      "geometry": {
        "type": "Point",
        "coordinates": [
          -7.516667,
          57.066667
        ]
      },
      "type": "Feature",
      "properties": {
        "hierarchy": [
          "tgn:1012463",
          "tgn:7002444",
          "tgn:1006430",
          "tgn:1000003",
          "tgn:7008094",
          "tgn:7008591",
          "tgn:7029392"
        ],
        "placetype": [
          "aat:300386846"
        ],
        "name:en": "Scurrival Point",
        "id": 1012463
      }
    },
    {
      "geometry": {
        "type": "Point",
        "coordinates": [
          -80.1667,
          63.75
        ]
      },
      "type": "Feature",
      "properties": {
        "hierarchy": [
          "tgn:1012464",
          "tgn:7005685",
          "tgn:1000001",
          "tgn:1009239",
          "tgn:7024197",
          "tgn:7029392"
        ],
        "placetype": [
          "aat:300386846"
        ],
        "id": 1012464,
        "name:xx": "Seahorse Point"
      }
    },
    {
      "geometry": {
        "type": "Point",
        "coordinates": [
          -74.1833,
          40.5
        ]
      },
      "type": "Feature",
      "properties": {
        "hierarchy": [
          "tgn:1012465",
          "tgn:1000001",
          "tgn:7012149",
          "tgn:7015817",
          "tgn:7007568",
          "tgn:7029392"
        ],
        "placetype": [
          "aat:300386846"
        ],
        "id": 1012465,
        "name:xx": "Seguine Point"
      }
    },
    {
      "geometry": {
        "type": "Point",
        "coordinates": [
          -45.45,
          -23.9
        ]
      },
      "type": "Feature",
      "properties": {
        "hierarchy": [
          "tgn:1012467",
          "tgn:1001945",
          "tgn:1000047",
          "tgn:7002457",
          "tgn:1000002",
          "tgn:1008853",
          "tgn:7029392"
        ],
        "placetype": [
          "aat:300386846"
        ],
        "id": 1012467,
        "name:xx": "Sela, Ponta da"
      }
    },
    {
      "geometry": {
        "type": "Point",
        "coordinates": [
          173,
          -40.783333
        ]
      },
      "type": "Feature",
      "properties": {
        "hierarchy": [
          "tgn:1012468",
          "tgn:1009227",
          "tgn:1000226",
          "tgn:7520095",
          "tgn:1000006",
          "tgn:7029392"
        ],
        "placetype": [
          "aat:300386846"
        ],
        "name:en": "Separation Point",
        "id": 1012468
      }
    },
    {
      "geometry": {
        "type": "Point",
        "coordinates": [
          -43.45,
          -23.0333
        ]
      },
      "type": "Feature",
      "properties": {
        "hierarchy": [
          "tgn:1012469",
          "tgn:1001942",
          "tgn:1000047",
          "tgn:7002457",
          "tgn:1000002",
          "tgn:7017095",
          "tgn:7029392"
        ],
        "placetype": [
          "aat:300386846"
        ],
        "id": 1012469,
        "name:xx": "Sernambitiba, Pontal de"
      }
    }
  ]
}
