{
  "geometry": {
    "type": "Point",
    "coordinates": [
      -73.583333,
      -37.15
    ]
  },
  "type": "Feature",
  "properties": {
    "hierarchy": [
      "tgn:1012084",
      "tgn:1001637",
      "tgn:1000049",
      "tgn:1000002",
      "tgn:7029392"
    ],
    "placetype": [
      "aat:300386846"
    ],
    "id": 1012084,
    "name:xx": "Lavapié, Punta"
  }
}
