{
  "geometry": {
    "type": "Point",
    "coordinates": [
      -71.8667,
      41.35
    ]
  },
  "type": "Feature",
  "properties": {
    "hierarchy": [
      "tgn:2757074",
      "tgn:1000001",
      "tgn:1002714",
      "tgn:7012149",
      "tgn:7007159",
      "tgn:7029392"
    ],
    "placetype": [
      "aat:300008680"
    ],
    "id": 2757074,
    "name:xx": "Wequetequock Pond"
  }
}
