{
  "geometry": {
    "type": "Point",
    "coordinates": [
      -136.0833,
      57.55
    ]
  },
  "type": "Feature",
  "properties": {
    "hierarchy": [
      "tgn:2606640",
      "tgn:7006450",
      "tgn:1000001",
      "tgn:7012149",
      "tgn:2124002",
      "tgn:7029392"
    ],
    "placetype": [
      "aat:300008791"
    ],
    "id": 2606640,
    "name:xx": "Ramp Island"
  }
}
