{
  "type": "FeatureCollection",
  "features": [
    {
      "geometry": {
        "type": "Point",
        "coordinates": [
          39.8333,
          52.9167
        ]
      },
      "type": "Feature",
      "properties": {
        "hierarchy": [
          "tgn:1137571",
          "tgn:1000004",
          "tgn:7011575",
          "tgn:7018214",
          "tgn:7002435",
          "tgn:7029392"
        ],
        "placetype": [
          "aat:300008347"
        ],
        "id": 1137571,
        "name:xx": "Kalikino"
      }
    },
    {
      "geometry": {
        "type": "Point",
        "coordinates": [
          39,
          45.1167
        ]
      },
      "type": "Feature",
      "properties": {
        "hierarchy": [
          "tgn:1137573",
          "tgn:1000004",
          "tgn:7011531",
          "tgn:7018214",
          "tgn:7002435",
          "tgn:7029392"
        ],
        "placetype": [
          "aat:300008347"
        ],
        "id": 1137573,
        "name:xx": "Kalinino"
      }
    },
    {
      "geometry": {
        "type": "Point",
        "coordinates": [
          48.9333,
          46.3333
        ]
      },
      "type": "Feature",
      "properties": {
        "hierarchy": [
          "tgn:1137574",
          "tgn:7011552",
          "tgn:1000004",
          "tgn:7018214",
          "tgn:7002435",
          "tgn:7029392"
        ],
        "placetype": [
          "aat:300008347"
        ],
        "id": 1137574,
        "name:xx": "Kalinino"
      }
    },
    {
      "geometry": {
        "type": "Point",
        "coordinates": [
          37.4667,
          47.45
        ]
      },
      "type": "Feature",
      "properties": {
        "hierarchy": [
          "tgn:1137575",
          "tgn:7012076",
          "tgn:1000003",
          "tgn:7006660",
          "tgn:7029392"
        ],
        "placetype": [
          "aat:300008347"
        ],
        "id": 1137575,
        "name:xx": "Kalinino"
      }
    },
    {
      "geometry": {
        "type": "Point",
        "coordinates": [
          129.3,
          49.4
        ]
      },
      "type": "Feature",
      "properties": {
        "hierarchy": [
          "tgn:1137576",
          "tgn:1003354",
          "tgn:1000004",
          "tgn:7018214",
          "tgn:7002435",
          "tgn:7029392"
        ],
        "placetype": [
          "aat:300008347"
        ],
        "id": 1137576,
        "name:xx": "Kalinino"
      }
    },
    {
      "geometry": {
        "type": "Point",
        "coordinates": [
          56.3,
          57.3
        ]
      },
      "type": "Feature",
      "properties": {
        "hierarchy": [
          "tgn:1137577",
          "tgn:1000004",
          "tgn:7013412",
          "tgn:7018214",
          "tgn:7002435",
          "tgn:7029392"
        ],
        "placetype": [
          "aat:300008347"
        ],
        "id": 1137577,
        "name:xx": "Kalinino"
      }
    },
    {
      "geometry": {
        "type": "Point",
        "coordinates": [
          44.4833,
          51.5333
        ]
      },
      "type": "Feature",
      "properties": {
        "hierarchy": [
          "tgn:1137578",
          "tgn:1000004",
          "tgn:1003408",
          "tgn:7018214",
          "tgn:7002435",
          "tgn:7029392"
        ],
        "placetype": [
          "aat:300008347"
        ],
        "id": 1137578,
        "name:xx": "Kalininsk"
      }
    },
    {
      "geometry": {
        "type": "Point",
        "coordinates": [
          42.2,
          47.8667
        ]
      },
      "type": "Feature",
      "properties": {
        "hierarchy": [
          "tgn:1137579",
          "tgn:1000004",
          "tgn:1003405",
          "tgn:7018214",
          "tgn:7002435",
          "tgn:7029392"
        ],
        "placetype": [
          "aat:300008347"
        ],
        "id": 1137579,
        "name:xx": "Kalininskaya"
      }
    }
  ]
}
