{
  "geometry": {
    "type": "Point",
    "coordinates": [
      -74.4333,
      41.7333
    ]
  },
  "type": "Feature",
  "properties": {
    "hierarchy": [
      "tgn:2220549",
      "tgn:1000001",
      "tgn:7012149",
      "tgn:1002961",
      "tgn:7007568",
      "tgn:7029392"
    ],
    "placetype": [
      "aat:300006191"
    ],
    "id": 2220549,
    "name:xx": "Cape Pond"
  }
}
