{
  "type": "FeatureCollection",
  "features": [
    {
      "geometry": {
        "type": "Point",
        "coordinates": [
          -84.3,
          36.9667
        ]
      },
      "type": "Feature",
      "properties": {
        "hierarchy": [
          "tgn:2628880",
          "tgn:1000001",
          "tgn:7012149",
          "tgn:2000808",
          "tgn:7007255",
          "tgn:7029392"
        ],
        "placetype": [
          "aat:300008699"
        ],
        "id": 2628880,
        "name:xx": "Rose Branch"
      }
    },
    {
      "geometry": {
        "type": "Point",
        "coordinates": [
          -83.3167,
          37.5167
        ]
      },
      "type": "Feature",
      "properties": {
        "hierarchy": [
          "tgn:2628881",
          "tgn:1000001",
          "tgn:2000772",
          "tgn:7012149",
          "tgn:7007255",
          "tgn:7029392"
        ],
        "placetype": [
          "aat:300008699"
        ],
        "id": 2628881,
        "name:xx": "Rose Branch"
      }
    },
    {
      "geometry": {
        "type": "Point",
        "coordinates": [
          -83.0833,
          37.7
        ]
      },
      "type": "Feature",
      "properties": {
        "hierarchy": [
          "tgn:2628882",
          "tgn:1000001",
          "tgn:7012149",
          "tgn:2000821",
          "tgn:7007255",
          "tgn:7029392"
        ],
        "placetype": [
          "aat:300008699"
        ],
        "id": 2628882,
        "name:xx": "Rose Branch"
      }
    },
    {
      "geometry": {
        "type": "Point",
        "coordinates": [
          -94.3,
          39.2667
        ]
      },
      "type": "Feature",
      "properties": {
        "hierarchy": [
          "tgn:2628883",
          "tgn:1000001",
          "tgn:2001187",
          "tgn:7012149",
          "tgn:7007523",
          "tgn:7029392"
        ],
        "placetype": [
          "aat:300008699"
        ],
        "id": 2628883,
        "name:xx": "Rose Branch"
      }
    },
    {
      "geometry": {
        "type": "Point",
        "coordinates": [
          -82.1667,
          35.9833
        ]
      },
      "type": "Feature",
      "properties": {
        "hierarchy": [
          "tgn:2628885",
          "tgn:1000001",
          "tgn:7012149",
          "tgn:7007709",
          "tgn:7029392"
        ],
        "placetype": [
          "aat:300008699"
        ],
        "id": 2628885,
        "name:xx": "Rose Branch"
      }
    },
    {
      "geometry": {
        "type": "Point",
        "coordinates": [
          -80.0833,
          34.1333
        ]
      },
      "type": "Feature",
      "properties": {
        "hierarchy": [
          "tgn:2628886",
          "tgn:1000001",
          "tgn:2001740",
          "tgn:7012149",
          "tgn:7007712",
          "tgn:7029392"
        ],
        "placetype": [
          "aat:300008699"
        ],
        "id": 2628886,
        "name:xx": "Rose Branch"
      }
    },
    {
      "geometry": {
        "type": "Point",
        "coordinates": [
          -85.8833,
          35.1833
        ]
      },
      "type": "Feature",
      "properties": {
        "hierarchy": [
          "tgn:2628887",
          "tgn:1000001",
          "tgn:7012149",
          "tgn:2001852",
          "tgn:7007825",
          "tgn:7029392"
        ],
        "placetype": [
          "aat:300008699"
        ],
        "id": 2628887,
        "name:xx": "Rose Branch"
      }
    },
    {
      "geometry": {
        "type": "Point",
        "coordinates": [
          -87.8167,
          35.3167
        ]
      },
      "type": "Feature",
      "properties": {
        "hierarchy": [
          "tgn:2628888",
          "tgn:1000001",
          "tgn:7012149",
          "tgn:2001927",
          "tgn:7007825",
          "tgn:7029392"
        ],
        "placetype": [
          "aat:300008699"
        ],
        "id": 2628888,
        "name:xx": "Rose Branch"
      }
    },
    {
      "geometry": {
        "type": "Point",
        "coordinates": [
          -87.1333,
          35.3167
        ]
      },
      "type": "Feature",
      "properties": {
        "hierarchy": [
          "tgn:2628889",
          "tgn:1000001",
          "tgn:7012149",
          "tgn:2001864",
          "tgn:7007825",
          "tgn:7029392"
        ],
        "placetype": [
          "aat:300008699"
        ],
        "id": 2628889,
        "name:xx": "Rose Branch"
      }
    }
  ]
}
