{
  "geometry": {
    "type": "Point",
    "coordinates": [
      -111.6333,
      38.9333
    ]
  },
  "type": "Feature",
  "properties": {
    "hierarchy": [
      "tgn:2131604",
      "tgn:1000001",
      "tgn:7012149",
      "tgn:2002121",
      "tgn:7007827",
      "tgn:7029392"
    ],
    "placetype": [
      "aat:300008761"
    ],
    "id": 2131604,
    "name:xx": "Alumbed Hollow"
  }
}
