{
  "type": "FeatureCollection",
  "features": [
    {
      "geometry": {
        "type": "Point",
        "coordinates": [
          -94.35,
          43.55
        ]
      },
      "type": "Feature",
      "properties": {
        "hierarchy": [
          "tgn:2054332",
          "tgn:1000001",
          "tgn:7012149",
          "tgn:2001044",
          "tgn:7007521",
          "tgn:7029392"
        ],
        "placetype": [
          "aat:300008347"
        ],
        "id": 2054332,
        "name:xx": "East Chain"
      }
    },
    {
      "geometry": {
        "type": "Point",
        "coordinates": [
          -97.0167,
          47.9167
        ]
      },
      "type": "Feature",
      "properties": {
        "hierarchy": [
          "tgn:2054333",
          "tgn:1000001",
          "tgn:7012149",
          "tgn:2001058",
          "tgn:7007521",
          "tgn:7029392"
        ],
        "placetype": [
          "aat:300008347"
        ],
        "id": 2054333,
        "name:xx": "East Grand Forks"
      }
    },
    {
      "geometry": {
        "type": "Point",
        "coordinates": [
          -94.35,
          46.4
        ]
      },
      "type": "Feature",
      "properties": {
        "hierarchy": [
          "tgn:2054334",
          "tgn:1000001",
          "tgn:2001009",
          "tgn:7012149",
          "tgn:7007521",
          "tgn:7029392"
        ],
        "placetype": [
          "aat:300008347"
        ],
        "id": 2054334,
        "name:xx": "East Gull Lake"
      }
    },
    {
      "geometry": {
        "type": "Point",
        "coordinates": [
          -93.2833,
          46.5333
        ]
      },
      "type": "Feature",
      "properties": {
        "hierarchy": [
          "tgn:2054335",
          "tgn:2000999",
          "tgn:1000001",
          "tgn:7012149",
          "tgn:7007521",
          "tgn:7029392"
        ],
        "placetype": [
          "aat:300008347"
        ],
        "id": 2054335,
        "name:xx": "East Lake"
      }
    },
    {
      "geometry": {
        "type": "Point",
        "coordinates": [
          -93.3167,
          45.5
        ]
      },
      "type": "Feature",
      "properties": {
        "hierarchy": [
          "tgn:2054336",
          "tgn:1000001",
          "tgn:7012149",
          "tgn:2001028",
          "tgn:7007521",
          "tgn:7029392"
        ],
        "placetype": [
          "aat:300008347"
        ],
        "id": 2054336,
        "name:xx": "East Lake Francis Shores"
      }
    },
    {
      "geometry": {
        "type": "Point",
        "coordinates": [
          -93.9,
          43.75
        ]
      },
      "type": "Feature",
      "properties": {
        "hierarchy": [
          "tgn:2054337",
          "tgn:1000001",
          "tgn:2001020",
          "tgn:7012149",
          "tgn:7007521",
          "tgn:7029392"
        ],
        "placetype": [
          "aat:300008347"
        ],
        "id": 2054337,
        "name:xx": "Easton"
      }
    },
    {
      "geometry": {
        "type": "Point",
        "coordinates": [
          -93.6667,
          44.7167
        ]
      },
      "type": "Feature",
      "properties": {
        "hierarchy": [
          "tgn:2054339",
          "tgn:1000001",
          "tgn:2001008",
          "tgn:7012149",
          "tgn:7007521",
          "tgn:7029392"
        ],
        "placetype": [
          "aat:300008347"
        ],
        "id": 2054339,
        "name:xx": "East Union"
      }
    }
  ]
}
