{
  "geometry": {
    "type": "Point",
    "coordinates": [
      -90.3833,
      29.6667
    ]
  },
  "type": "Feature",
  "properties": {
    "hierarchy": [
      "tgn:2496353",
      "tgn:1000001",
      "tgn:7012149",
      "tgn:2000882",
      "tgn:7007256",
      "tgn:7029392"
    ],
    "placetype": [
      "aat:300008699"
    ],
    "id": 2496353,
    "name:xx": "Matherne, Bayou"
  }
}
