{
  "geometry": {
    "type": "Point",
    "coordinates": [
      -75.2333,
      38.0833
    ]
  },
  "type": "Feature",
  "properties": {
    "hierarchy": [
      "tgn:2586000",
      "tgn:1000001",
      "tgn:1003037",
      "tgn:7012149",
      "tgn:7007516",
      "tgn:7029392"
    ],
    "placetype": [
      "aat:300386853"
    ],
    "id": 2586000,
    "name:xx": "Pirate Islands"
  }
}
