{
  "geometry": {
    "type": "Point",
    "coordinates": [
      -92.5833,
      38.3167
    ]
  },
  "type": "Feature",
  "properties": {
    "hierarchy": [
      "tgn:2057942",
      "tgn:1000001",
      "tgn:7012149",
      "tgn:1002671",
      "tgn:7007523",
      "tgn:7029392"
    ],
    "placetype": [
      "aat:300008347"
    ],
    "id": 2057942,
    "name:xx": "Aurora Springs"
  }
}
