{
  "geometry": {
    "type": "Point",
    "coordinates": [
      -79.8833,
      39.8333
    ]
  },
  "type": "Feature",
  "properties": {
    "hierarchy": [
      "tgn:2625504",
      "tgn:1000001",
      "tgn:7012149",
      "tgn:7014185",
      "tgn:7007710",
      "tgn:7029392"
    ],
    "placetype": [
      "aat:300008347"
    ],
    "id": 2625504,
    "name:xx": "Rocks Works"
  }
}
