{
  "geometry": {
    "type": "Point",
    "coordinates": [
      78.733333,
      11.483333
    ]
  },
  "type": "Feature",
  "properties": {
    "hierarchy": [
      "tgn:7578163",
      "tgn:1000004",
      "tgn:7000198",
      "tgn:7001797",
      "tgn:7029392"
    ],
    "placetype": [
      "aat:300008347"
    ],
    "name:en": "Vīraganūr",
    "id": 7578163
  }
}
