{
  "geometry": {
    "type": "Point",
    "coordinates": [
      -96.1333,
      30.8667
    ]
  },
  "type": "Feature",
  "properties": {
    "hierarchy": [
      "tgn:2643133",
      "tgn:1000001",
      "tgn:7012149",
      "tgn:1002626",
      "tgn:7007826",
      "tgn:7029392"
    ],
    "placetype": [
      "aat:300008699"
    ],
    "id": 2643133,
    "name:xx": "Sandy Branch"
  }
}
