{
  "geometry": {
    "type": "Point",
    "coordinates": [
      -90.8667,
      48.2333
    ]
  },
  "type": "Feature",
  "properties": {
    "hierarchy": [
      "tgn:2561568",
      "tgn:1000001",
      "tgn:2001014",
      "tgn:7012149",
      "tgn:7007521",
      "tgn:7029392"
    ],
    "placetype": [
      "aat:300008791"
    ],
    "id": 2561568,
    "name:xx": "Oskenonton Island"
  }
}
