{
  "geometry": {
    "type": "Point",
    "coordinates": [
      -79.3667,
      43.1667
    ]
  },
  "type": "Feature",
  "properties": {
    "hierarchy": [
      "tgn:1134922",
      "tgn:7005685",
      "tgn:1000001",
      "tgn:7013154",
      "tgn:7029392"
    ],
    "placetype": [
      "aat:300008706"
    ],
    "id": 1134922,
    "name:xx": "Twenty Mile Creek"
  }
}
