{
  "geometry": {
    "type": "Point",
    "coordinates": [
      -73.95,
      44.6333
    ]
  },
  "type": "Feature",
  "properties": {
    "hierarchy": [
      "tgn:2550642",
      "tgn:1000001",
      "tgn:7012149",
      "tgn:7013941",
      "tgn:7007568",
      "tgn:7029392"
    ],
    "placetype": [
      "aat:300008798"
    ],
    "id": 2550642,
    "name:xx": "Norton Peak"
  }
}
