{
  "geometry": {
    "type": "Point",
    "coordinates": [
      -85.9333,
      40.8167
    ]
  },
  "type": "Feature",
  "properties": {
    "hierarchy": [
      "tgn:2317774",
      "tgn:1000001",
      "tgn:7012149",
      "tgn:1002978",
      "tgn:7007252",
      "tgn:7029392"
    ],
    "placetype": [
      "aat:300008706"
    ],
    "id": 2317774,
    "name:xx": "Engleman Creek"
  }
}
