{
  "geometry": {
    "type": "Point",
    "coordinates": [
      -78.0333,
      42.0667
    ]
  },
  "type": "Feature",
  "properties": {
    "hierarchy": [
      "tgn:2393468",
      "tgn:1002141",
      "tgn:1000001",
      "tgn:7012149",
      "tgn:7007568",
      "tgn:7029392"
    ],
    "placetype": [
      "aat:300008699"
    ],
    "id": 2393468,
    "name:xx": "Hog Brook"
  }
}
