{
  "geometry": {
    "type": "Point",
    "coordinates": [
      23.7833,
      -29.0667
    ]
  },
  "type": "Feature",
  "properties": {
    "hierarchy": [
      "tgn:1093025",
      "tgn:7001242",
      "tgn:7017582",
      "tgn:1000193",
      "tgn:7029392"
    ],
    "placetype": [
      "aat:300008347"
    ],
    "id": 1093025,
    "name:xx": "Douglas"
  }
}
