{
  "geometry": {
    "type": "Point",
    "coordinates": [
      31.868478,
      30.899721
    ]
  },
  "type": "Feature",
  "properties": {
    "hierarchy": [
      "tgn:7538337",
      "tgn:7001242",
      "tgn:7016833",
      "tgn:1001113",
      "tgn:7029392"
    ],
    "placetype": [
      "aat:300008777"
    ],
    "name:en": "Rimāl, Jazīrat ar",
    "id": 7538337
  }
}
