{
  "geometry": {
    "type": "Point",
    "coordinates": [
      -99.46,
      25.445833
    ]
  },
  "type": "Feature",
  "properties": {
    "hierarchy": [
      "tgn:7421233",
      "tgn:1000001",
      "tgn:7005589",
      "tgn:7005560",
      "tgn:7029392"
    ],
    "placetype": [
      "aat:300008699"
    ],
    "id": 7421233,
    "name:es": "Guzman, Río"
  }
}
