{
  "geometry": {
    "type": "Point",
    "coordinates": [
      -80.85,
      27.35
    ]
  },
  "type": "Feature",
  "properties": {
    "hierarchy": [
      "tgn:2303521",
      "tgn:1000001",
      "tgn:7012149",
      "tgn:1002743",
      "tgn:7007240",
      "tgn:7029392"
    ],
    "placetype": [
      "aat:300008791"
    ],
    "id": 2303521,
    "name:xx": "Eagle Island"
  }
}
