{
  "geometry": {
    "type": "Point",
    "coordinates": [
      -79.9333,
      35.7833
    ]
  },
  "type": "Feature",
  "properties": {
    "hierarchy": [
      "tgn:2216916",
      "tgn:1000001",
      "tgn:7012149",
      "tgn:2001532",
      "tgn:7007709",
      "tgn:7029392"
    ],
    "placetype": [
      "aat:300006191"
    ],
    "id": 2216916,
    "name:xx": "Camp Keyauwee Lake"
  }
}
