{
  "geometry": {
    "type": "Point",
    "coordinates": [
      -123.8667,
      46.2667
    ]
  },
  "type": "Feature",
  "properties": {
    "hierarchy": [
      "tgn:2237747",
      "tgn:1000001",
      "tgn:7012149",
      "tgn:1002767",
      "tgn:7007920",
      "tgn:7029392"
    ],
    "placetype": [
      "aat:300008707"
    ],
    "id": 2237747,
    "name:xx": "Chinook River"
  }
}
