{
  "geometry": {
    "type": "Point",
    "coordinates": [
      -111.0333,
      32.8667
    ]
  },
  "type": "Feature",
  "properties": {
    "hierarchy": [
      "tgn:2160345",
      "tgn:1000001",
      "tgn:7006451",
      "tgn:7012149",
      "tgn:2000101",
      "tgn:7029392"
    ],
    "placetype": [
      "aat:300006191"
    ],
    "id": 2160345,
    "name:xx": "Beehive Tank"
  }
}
