{
  "geometry": {
    "type": "Point",
    "coordinates": [
      72.975937,
      24.265771
    ]
  },
  "type": "Feature",
  "properties": {
    "hierarchy": [
      "tgn:7572156",
      "tgn:1000004",
      "tgn:1001869",
      "tgn:7000198",
      "tgn:7029392"
    ],
    "placetype": [
      "aat:300008347"
    ],
    "name:en": "Hadād",
    "id": 7572156
  }
}
