{
  "geometry": {
    "type": "Point",
    "coordinates": [
      28.2167,
      -25.6333
    ]
  },
  "type": "Feature",
  "properties": {
    "hierarchy": [
      "tgn:1092899",
      "tgn:7001242",
      "tgn:7017576",
      "tgn:1000193",
      "tgn:7029392"
    ],
    "placetype": [
      "aat:300008347"
    ],
    "id": 1092899,
    "name:xx": "Bon Accord"
  }
}
