{
  "geometry": {
    "type": "Point",
    "coordinates": [
      -97.6667,
      38.5667
    ]
  },
  "type": "Feature",
  "properties": {
    "hierarchy": [
      "tgn:2036708",
      "tgn:1000001",
      "tgn:7012149",
      "tgn:2000716",
      "tgn:7007254",
      "tgn:7029392"
    ],
    "placetype": [
      "aat:300008347"
    ],
    "id": 2036708,
    "name:xx": "Lindsborg"
  }
}
