{
  "geometry": {
    "type": "Point",
    "coordinates": [
      -102.4667,
      45.9667
    ]
  },
  "type": "Feature",
  "properties": {
    "hierarchy": [
      "tgn:2077699",
      "tgn:2001557",
      "tgn:1000001",
      "tgn:7012149",
      "tgn:7007705",
      "tgn:7029392"
    ],
    "placetype": [
      "aat:300008347"
    ],
    "id": 2077699,
    "name:xx": "Haynes"
  }
}
