{
  "type": "FeatureCollection",
  "features": [
    {
      "geometry": {
        "type": "Point",
        "coordinates": [
          -106.45,
          39
        ]
      },
      "type": "Feature",
      "properties": {
        "hierarchy": [
          "tgn:2365910",
          "tgn:1000001",
          "tgn:2000199",
          "tgn:7012149",
          "tgn:7007158",
          "tgn:7029392"
        ],
        "placetype": [
          "aat:300008706"
        ],
        "id": 2365910,
        "name:xx": "Grey Copper Creek"
      }
    },
    {
      "geometry": {
        "type": "Point",
        "coordinates": [
          -105.4,
          40.0333
        ]
      },
      "type": "Feature",
      "properties": {
        "hierarchy": [
          "tgn:2365911",
          "tgn:1000001",
          "tgn:2000198",
          "tgn:7012149",
          "tgn:7007158",
          "tgn:7029392"
        ],
        "placetype": [
          "aat:300000390"
        ],
        "id": 2365911,
        "name:xx": "Grey Copper Mine"
      }
    },
    {
      "geometry": {
        "type": "Point",
        "coordinates": [
          -87.4333,
          31.9
        ]
      },
      "type": "Feature",
      "properties": {
        "hierarchy": [
          "tgn:2365912",
          "tgn:7002659",
          "tgn:1000001",
          "tgn:7012149",
          "tgn:2000065",
          "tgn:7029392"
        ],
        "placetype": [
          "aat:300008706"
        ],
        "id": 2365912,
        "name:xx": "Grey Creek"
      }
    },
    {
      "geometry": {
        "type": "Point",
        "coordinates": [
          -84.8667,
          44.05
        ]
      },
      "type": "Feature",
      "properties": {
        "hierarchy": [
          "tgn:2365913",
          "tgn:1000001",
          "tgn:2000953",
          "tgn:7012149",
          "tgn:7007520",
          "tgn:7029392"
        ],
        "placetype": [
          "aat:300008706"
        ],
        "id": 2365913,
        "name:xx": "Grey Creek"
      }
    },
    {
      "geometry": {
        "type": "Point",
        "coordinates": [
          -83.5,
          44.5167
        ]
      },
      "type": "Feature",
      "properties": {
        "hierarchy": [
          "tgn:2365914",
          "tgn:2000942",
          "tgn:1000001",
          "tgn:7012149",
          "tgn:7007520",
          "tgn:7029392"
        ],
        "placetype": [
          "aat:300008706"
        ],
        "id": 2365914,
        "name:xx": "Grey Creek"
      }
    },
    {
      "geometry": {
        "type": "Point",
        "coordinates": [
          -121.25,
          46.5667
        ]
      },
      "type": "Feature",
      "properties": {
        "hierarchy": [
          "tgn:2365915",
          "tgn:1000001",
          "tgn:7012149",
          "tgn:1003042",
          "tgn:7007920",
          "tgn:7029392"
        ],
        "placetype": [
          "aat:300008706"
        ],
        "id": 2365915,
        "name:xx": "Grey Creek"
      }
    },
    {
      "geometry": {
        "type": "Point",
        "coordinates": [
          -75.6833,
          37.8167
        ]
      },
      "type": "Feature",
      "properties": {
        "hierarchy": [
          "tgn:2365916",
          "tgn:1002132",
          "tgn:1000001",
          "tgn:7012149",
          "tgn:7007919",
          "tgn:7029392"
        ],
        "placetype": [
          "aat:300006075"
        ],
        "id": 2365916,
        "name:xx": "Grey Ditch"
      }
    },
    {
      "geometry": {
        "type": "Point",
        "coordinates": [
          -114.6667,
          37.65
        ]
      },
      "type": "Feature",
      "properties": {
        "hierarchy": [
          "tgn:2365917",
          "tgn:1000001",
          "tgn:2001416",
          "tgn:7012149",
          "tgn:7007526",
          "tgn:7029392"
        ],
        "placetype": [
          "aat:300008798"
        ],
        "id": 2365917,
        "name:xx": "Grey Dome"
      }
    },
    {
      "geometry": {
        "type": "Point",
        "coordinates": [
          -108.5,
          45.75
        ]
      },
      "type": "Feature",
      "properties": {
        "hierarchy": [
          "tgn:2365918",
          "tgn:1000001",
          "tgn:7012149",
          "tgn:2001315",
          "tgn:7007524",
          "tgn:7029392"
        ],
        "placetype": [
          "aat:300006075"
        ],
        "id": 2365918,
        "name:xx": "Grey Eagle Ditch"
      }
    },
    {
      "geometry": {
        "type": "Point",
        "coordinates": [
          -120.7667,
          38.9
        ]
      },
      "type": "Feature",
      "properties": {
        "hierarchy": [
          "tgn:2365919",
          "tgn:1000001",
          "tgn:7012149",
          "tgn:1002350",
          "tgn:7007157",
          "tgn:7029392"
        ],
        "placetype": [
          "aat:300008798"
        ],
        "id": 2365919,
        "name:xx": "Grey Eagle Hill"
      }
    }
  ]
}
