{
  "geometry": {
    "type": "Point",
    "coordinates": [
      -91.7667,
      37.3833
    ]
  },
  "type": "Feature",
  "properties": {
    "hierarchy": [
      "tgn:2278747",
      "tgn:1000001",
      "tgn:7012149",
      "tgn:7007523",
      "tgn:7029392"
    ],
    "placetype": [
      "aat:300008761"
    ],
    "id": 2278747,
    "name:xx": "Dead Horse Hollow"
  }
}
