{
  "geometry": {
    "type": "Point",
    "coordinates": [
      5.8333,
      8.3333
    ]
  },
  "type": "Feature",
  "properties": {
    "hierarchy": [
      "tgn:1092068",
      "tgn:7001242",
      "tgn:7015047",
      "tgn:1000182",
      "tgn:7029392"
    ],
    "placetype": [
      "aat:300008347"
    ],
    "id": 1092068,
    "name:xx": "Isanlu Makutu"
  }
}
