{
  "geometry": {
    "type": "Point",
    "coordinates": [
      -74.8667,
      42.1833
    ]
  },
  "type": "Feature",
  "properties": {
    "hierarchy": [
      "tgn:2201064",
      "tgn:1000001",
      "tgn:1002328",
      "tgn:7012149",
      "tgn:7007568",
      "tgn:7029392"
    ],
    "placetype": [
      "aat:300008680"
    ],
    "id": 2201064,
    "name:xx": "Brydon Lake"
  }
}
