{
  "geometry": {
    "type": "Point",
    "coordinates": [
      88.377,
      22.641
    ]
  },
  "type": "Feature",
  "properties": {
    "hierarchy": [
      "tgn:1074656",
      "tgn:1000004",
      "tgn:7000198",
      "tgn:1001977",
      "tgn:7029392"
    ],
    "placetype": [
      "aat:300008347",
      "aat:300000745"
    ],
    "name:en": "Baranagar",
    "id": 1074656
  }
}
