{
  "geometry": {
    "type": "Point",
    "coordinates": [
      -108.8167,
      33.5333
    ]
  },
  "type": "Feature",
  "properties": {
    "hierarchy": [
      "tgn:2433601",
      "tgn:1000001",
      "tgn:2001429",
      "tgn:7012149",
      "tgn:7007566",
      "tgn:7029392"
    ],
    "placetype": [
      "aat:300008798"
    ],
    "id": 2433601,
    "name:xx": "Kelly Brushy"
  }
}
