{
  "geometry": {
    "type": "Point",
    "coordinates": [
      -80.5833,
      34.25
    ]
  },
  "type": "Feature",
  "properties": {
    "hierarchy": [
      "tgn:2193575",
      "tgn:1000001",
      "tgn:7012149",
      "tgn:2001752",
      "tgn:7007712",
      "tgn:7029392"
    ],
    "placetype": [
      "aat:300008697"
    ],
    "id": 2193575,
    "name:xx": "Brevards Spring"
  }
}
