{
  "geometry": {
    "type": "Point",
    "coordinates": [
      70.65,
      21.966667
    ]
  },
  "type": "Feature",
  "properties": {
    "hierarchy": [
      "tgn:7581959",
      "tgn:1000004",
      "tgn:1001869",
      "tgn:7000198",
      "tgn:7029392"
    ],
    "placetype": [
      "aat:300008347"
    ],
    "name:en": "Trākuda",
    "id": 7581959
  }
}
