{
  "geometry": {
    "type": "Point",
    "coordinates": [
      -131.5167,
      56.1833
    ]
  },
  "type": "Feature",
  "properties": {
    "hierarchy": [
      "tgn:2388744",
      "tgn:7006450",
      "tgn:1000001",
      "tgn:7012149",
      "tgn:2000082",
      "tgn:7029392"
    ],
    "placetype": [
      "aat:300008706"
    ],
    "id": 2388744,
    "name:xx": "Hidden Creek"
  }
}
