{
  "geometry": {
    "type": "Point",
    "coordinates": [
      -104.55,
      34.0333
    ]
  },
  "type": "Feature",
  "properties": {
    "hierarchy": [
      "tgn:2586171",
      "tgn:1000001",
      "tgn:7019560",
      "tgn:7012149",
      "tgn:7007566",
      "tgn:7029392"
    ],
    "placetype": [
      "aat:300006191"
    ],
    "id": 2586171,
    "name:xx": "Pisnel Tank"
  }
}
