{
  "geometry": {
    "type": "Point",
    "coordinates": [
      -84.1667,
      35.15
    ]
  },
  "type": "Feature",
  "properties": {
    "hierarchy": [
      "tgn:2392525",
      "tgn:1000001",
      "tgn:2001481",
      "tgn:7012149",
      "tgn:7007709",
      "tgn:7029392"
    ],
    "placetype": [
      "aat:300006191"
    ],
    "id": 2392525,
    "name:xx": "Hiwassee Lake"
  }
}
