{
  "type": "FeatureCollection",
  "features": [
    {
      "geometry": {
        "type": "Point",
        "coordinates": [
          -112.95,
          46.3833
        ]
      },
      "type": "Feature",
      "properties": {
        "hierarchy": [
          "tgn:2622740",
          "tgn:1000001",
          "tgn:7012149",
          "tgn:2001298",
          "tgn:7007524",
          "tgn:7029392"
        ],
        "placetype": [
          "aat:300008761"
        ],
        "id": 2622740,
        "name:xx": "Robinson Gulch"
      }
    },
    {
      "geometry": {
        "type": "Point",
        "coordinates": [
          -123.3,
          42.6833
        ]
      },
      "type": "Feature",
      "properties": {
        "hierarchy": [
          "tgn:2622741",
          "tgn:1000001",
          "tgn:7012149",
          "tgn:2001713",
          "tgn:7007708",
          "tgn:7029392"
        ],
        "placetype": [
          "aat:300008761"
        ],
        "id": 2622741,
        "name:xx": "Robinson Gulch"
      }
    },
    {
      "geometry": {
        "type": "Point",
        "coordinates": [
          -117.5333,
          44.4333
        ]
      },
      "type": "Feature",
      "properties": {
        "hierarchy": [
          "tgn:2622742",
          "tgn:7013349",
          "tgn:1000001",
          "tgn:7012149",
          "tgn:7007708",
          "tgn:7029392"
        ],
        "placetype": [
          "aat:300008761"
        ],
        "id": 2622742,
        "name:xx": "Robinson Gulch"
      }
    },
    {
      "geometry": {
        "type": "Point",
        "coordinates": [
          -116.6667,
          45.75
        ]
      },
      "type": "Feature",
      "properties": {
        "hierarchy": [
          "tgn:2622743",
          "tgn:1000001",
          "tgn:7012149",
          "tgn:2001722",
          "tgn:7007708",
          "tgn:7029392"
        ],
        "placetype": [
          "aat:300008761"
        ],
        "id": 2622743,
        "name:xx": "Robinson Gulch"
      }
    },
    {
      "geometry": {
        "type": "Point",
        "coordinates": [
          -110.95,
          39.7333
        ]
      },
      "type": "Feature",
      "properties": {
        "hierarchy": [
          "tgn:2622744",
          "tgn:1000001",
          "tgn:2002104",
          "tgn:7012149",
          "tgn:7007827",
          "tgn:7029392"
        ],
        "placetype": [
          "aat:300008761"
        ],
        "id": 2622744,
        "name:xx": "Robinson Gulch"
      }
    },
    {
      "geometry": {
        "type": "Point",
        "coordinates": [
          -117.4333,
          46.35
        ]
      },
      "type": "Feature",
      "properties": {
        "hierarchy": [
          "tgn:2622745",
          "tgn:1000001",
          "tgn:7012149",
          "tgn:7007920",
          "tgn:7029392"
        ],
        "placetype": [
          "aat:300008761"
        ],
        "id": 2622745,
        "name:xx": "Robinson Gulch"
      }
    },
    {
      "geometry": {
        "type": "Point",
        "coordinates": [
          -108.7,
          42.8
        ]
      },
      "type": "Feature",
      "properties": {
        "hierarchy": [
          "tgn:2622746",
          "tgn:1000001",
          "tgn:7012149",
          "tgn:2002371",
          "tgn:7007923",
          "tgn:7029392"
        ],
        "placetype": [
          "aat:300008761"
        ],
        "id": 2622746,
        "name:xx": "Robinson Gulch"
      }
    },
    {
      "geometry": {
        "type": "Point",
        "coordinates": [
          -95.2,
          30.1167
        ]
      },
      "type": "Feature",
      "properties": {
        "hierarchy": [
          "tgn:2622747",
          "tgn:1000001",
          "tgn:7012149",
          "tgn:1002691",
          "tgn:7007826",
          "tgn:7029392"
        ],
        "placetype": [
          "aat:300008761"
        ],
        "id": 2622747,
        "name:xx": "Robinson Gully"
      }
    },
    {
      "geometry": {
        "type": "Point",
        "coordinates": [
          -81.8667,
          31.2833
        ]
      },
      "type": "Feature",
      "properties": {
        "hierarchy": [
          "tgn:2622748",
          "tgn:1000001",
          "tgn:2000304",
          "tgn:7012149",
          "tgn:7007248",
          "tgn:7029392"
        ],
        "placetype": [
          "aat:300008791"
        ],
        "id": 2622748,
        "name:xx": "Robinson Hammock"
      }
    },
    {
      "geometry": {
        "type": "Point",
        "coordinates": [
          -82.3,
          29.6
        ]
      },
      "type": "Feature",
      "properties": {
        "hierarchy": [
          "tgn:2622749",
          "tgn:2000256",
          "tgn:1000001",
          "tgn:7012149",
          "tgn:7007240",
          "tgn:7029392"
        ],
        "placetype": [
          "aat:300008347"
        ],
        "id": 2622749,
        "name:xx": "Robinson Heights"
      }
    }
  ]
}
