{
  "geometry": {
    "type": "Point",
    "coordinates": [
      -93.7167,
      32.0167
    ]
  },
  "type": "Feature",
  "properties": {
    "hierarchy": [
      "tgn:2534639",
      "tgn:1000001",
      "tgn:7020680",
      "tgn:7012149",
      "tgn:7007256",
      "tgn:7029392"
    ],
    "placetype": [
      "aat:300008699"
    ],
    "id": 2534639,
    "name:xx": "Na Bonchasse, Bayou"
  }
}
