{
  "geometry": {
    "type": "Point",
    "coordinates": [
      -83.35,
      42.9333
    ]
  },
  "type": "Feature",
  "properties": {
    "hierarchy": [
      "tgn:2517150",
      "tgn:1000001",
      "tgn:7012149",
      "tgn:1002576",
      "tgn:7007520",
      "tgn:7029392"
    ],
    "placetype": [
      "aat:300006191"
    ],
    "id": 2517150,
    "name:xx": "Minnawanna, Lake"
  }
}
