{
  "geometry": {
    "type": "Point",
    "coordinates": [
      -88.35,
      39.15
    ]
  },
  "type": "Feature",
  "properties": {
    "hierarchy": [
      "tgn:2755455",
      "tgn:1000001",
      "tgn:7012149",
      "tgn:7007251",
      "tgn:7029392"
    ],
    "placetype": [
      "aat:300008699"
    ],
    "id": 2755455,
    "name:xx": "Webster Branch"
  }
}
