{
  "geometry": {
    "type": "Point",
    "coordinates": [
      121.3187,
      24.9896
    ]
  },
  "type": "Feature",
  "properties": {
    "hierarchy": [
      "tgn:7492742",
      "tgn:1000004",
      "tgn:7001013",
      "tgn:1000141",
      "tgn:7029392"
    ],
    "placetype": [
      "aat:300008347",
      "aat:300387220"
    ],
    "id": 7492742,
    "name:xx": "Taoyuan"
  }
}
