{
  "geometry": {
    "type": "Point",
    "coordinates": [
      33.75,
      50.8333
    ]
  },
  "type": "Feature",
  "properties": {
    "hierarchy": [
      "tgn:1055663",
      "tgn:1000003",
      "tgn:1003410",
      "tgn:7006660",
      "tgn:7029392"
    ],
    "placetype": [
      "aat:300008347"
    ],
    "id": 1055663,
    "name:xx": "Korovintsy"
  }
}
