{
  "geometry": {
    "type": "Point",
    "coordinates": [
      -116.8333,
      34.95
    ]
  },
  "type": "Feature",
  "properties": {
    "hierarchy": [
      "tgn:2442217",
      "tgn:1000001",
      "tgn:7012149",
      "tgn:7007157",
      "tgn:1002857",
      "tgn:7029392"
    ],
    "placetype": [
      "aat:300386837"
    ],
    "id": 2442217,
    "name:xx": "Kramer Arch"
  }
}
