{
  "geometry": {
    "type": "Point",
    "coordinates": [
      -87.2167,
      38.8833
    ]
  },
  "type": "Feature",
  "properties": {
    "hierarchy": [
      "tgn:2665323",
      "tgn:1000001",
      "tgn:7012149",
      "tgn:7007252",
      "tgn:7029392"
    ],
    "placetype": [
      "aat:300006075"
    ],
    "id": 2665323,
    "name:xx": "Singer Ditch"
  }
}
