{
  "geometry": {
    "type": "Point",
    "coordinates": [
      -109.7833,
      48.15
    ]
  },
  "type": "Feature",
  "properties": {
    "hierarchy": [
      "tgn:2556307",
      "tgn:1000001",
      "tgn:2001267",
      "tgn:7012149",
      "tgn:7007524",
      "tgn:7029392"
    ],
    "placetype": [
      "aat:300266640"
    ],
    "id": 2556307,
    "name:xx": "Okeyquaakkeo Ridge"
  }
}
