{
  "geometry": {
    "type": "Point",
    "coordinates": [
      -54.6667,
      49.4167
    ]
  },
  "type": "Feature",
  "properties": {
    "hierarchy": [
      "tgn:1014158",
      "tgn:7005685",
      "tgn:7005807",
      "tgn:1000001",
      "tgn:7005801",
      "tgn:7029392"
    ],
    "placetype": [
      "aat:300008347"
    ],
    "id": 1014158,
    "name:xx": "Boyds Cove"
  }
}
