{
  "geometry": {
    "type": "Point",
    "coordinates": [
      -111.9333,
      34.8167
    ]
  },
  "type": "Feature",
  "properties": {
    "hierarchy": [
      "tgn:2489848",
      "tgn:1000001",
      "tgn:7006451",
      "tgn:7012149",
      "tgn:2000103",
      "tgn:7029392"
    ],
    "placetype": [
      "aat:300006191"
    ],
    "id": 2489848,
    "name:xx": "Malpais Tank"
  }
}
