{
  "geometry": {
    "type": "Point",
    "coordinates": [
      -111.5167,
      32.4167
    ]
  },
  "type": "Feature",
  "properties": {
    "hierarchy": [
      "tgn:2603341",
      "tgn:1000001",
      "tgn:7006451",
      "tgn:7012149",
      "tgn:2000100",
      "tgn:7029392"
    ],
    "placetype": [
      "aat:300008798"
    ],
    "id": 2603341,
    "name:xx": "Quartzite Peak"
  }
}
