{
  "type": "FeatureCollection",
  "features": [
    {
      "geometry": {
        "type": "Point",
        "coordinates": [
          -87.6667,
          35.5
        ]
      },
      "type": "Feature",
      "properties": {
        "hierarchy": [
          "tgn:2137010",
          "tgn:1000001",
          "tgn:7012149",
          "tgn:2001887",
          "tgn:7007825",
          "tgn:7029392"
        ],
        "placetype": [
          "aat:300008699"
        ],
        "id": 2137010,
        "name:xx": "Arkansas Branch"
      }
    },
    {
      "geometry": {
        "type": "Point",
        "coordinates": [
          -82.35,
          38
        ]
      },
      "type": "Feature",
      "properties": {
        "hierarchy": [
          "tgn:2137011",
          "tgn:1000001",
          "tgn:7012149",
          "tgn:2002299",
          "tgn:7013961",
          "tgn:7029392"
        ],
        "placetype": [
          "aat:300008699"
        ],
        "id": 2137011,
        "name:xx": "Arkansas Branch"
      }
    },
    {
      "geometry": {
        "type": "Point",
        "coordinates": [
          -121.4,
          37.4667
        ]
      },
      "type": "Feature",
      "properties": {
        "hierarchy": [
          "tgn:2137012",
          "tgn:1000001",
          "tgn:7012149",
          "tgn:7007157",
          "tgn:1002915",
          "tgn:7029392"
        ],
        "placetype": [
          "aat:300008761"
        ],
        "id": 2137012,
        "name:xx": "Arkansas Canyon"
      }
    },
    {
      "geometry": {
        "type": "Point",
        "coordinates": [
          -116.5833,
          33.1333
        ]
      },
      "type": "Feature",
      "properties": {
        "hierarchy": [
          "tgn:2137013",
          "tgn:1000001",
          "tgn:7012149",
          "tgn:7007157",
          "tgn:1002858",
          "tgn:7029392"
        ],
        "placetype": [
          "aat:300008761"
        ],
        "id": 2137013,
        "name:xx": "Arkansas Canyon"
      }
    },
    {
      "geometry": {
        "type": "Point",
        "coordinates": [
          -116.2833,
          43.8667
        ]
      },
      "type": "Feature",
      "properties": {
        "hierarchy": [
          "tgn:2137014",
          "tgn:1000001",
          "tgn:7012149",
          "tgn:2000474",
          "tgn:7007250",
          "tgn:7029392"
        ],
        "placetype": [
          "aat:300008761"
        ],
        "id": 2137014,
        "name:xx": "Arkansas Canyon"
      }
    },
    {
      "geometry": {
        "type": "Point",
        "coordinates": [
          -105.7167,
          32.6167
        ]
      },
      "type": "Feature",
      "properties": {
        "hierarchy": [
          "tgn:2137015",
          "tgn:1000001",
          "tgn:7012149",
          "tgn:2001447",
          "tgn:7007566",
          "tgn:7029392"
        ],
        "placetype": [
          "aat:300008761"
        ],
        "id": 2137015,
        "name:xx": "Arkansas Canyon"
      }
    },
    {
      "geometry": {
        "type": "Point",
        "coordinates": [
          -98.4333,
          26.65
        ]
      },
      "type": "Feature",
      "properties": {
        "hierarchy": [
          "tgn:2137016",
          "tgn:1000001",
          "tgn:7012149",
          "tgn:2002075",
          "tgn:7007826",
          "tgn:7029392"
        ],
        "placetype": [
          "aat:300008347"
        ],
        "id": 2137016,
        "name:xx": "Arkansas City"
      }
    },
    {
      "geometry": {
        "type": "Point",
        "coordinates": [
          -141.0333,
          64.0667
        ]
      },
      "type": "Feature",
      "properties": {
        "hierarchy": [
          "tgn:2137017",
          "tgn:7006450",
          "tgn:1000001",
          "tgn:7012149",
          "tgn:2000085",
          "tgn:7029392"
        ],
        "placetype": [
          "aat:300008706"
        ],
        "id": 2137017,
        "name:xx": "Arkansas Creek"
      }
    },
    {
      "geometry": {
        "type": "Point",
        "coordinates": [
          -121.35,
          37.55
        ]
      },
      "type": "Feature",
      "properties": {
        "hierarchy": [
          "tgn:2137018",
          "tgn:1000001",
          "tgn:7012149",
          "tgn:7007157",
          "tgn:1002915",
          "tgn:7029392"
        ],
        "placetype": [
          "aat:300008706"
        ],
        "id": 2137018,
        "name:xx": "Arkansas Creek"
      }
    },
    {
      "geometry": {
        "type": "Point",
        "coordinates": [
          -120.9667,
          38.4667
        ]
      },
      "type": "Feature",
      "properties": {
        "hierarchy": [
          "tgn:2137019",
          "tgn:1000001",
          "tgn:7012149",
          "tgn:7007157",
          "tgn:7029392"
        ],
        "placetype": [
          "aat:300008706"
        ],
        "id": 2137019,
        "name:xx": "Arkansas Creek"
      }
    }
  ]
}
