{
  "geometry": {
    "type": "Point",
    "coordinates": [
      -70.75,
      43.4667
    ]
  },
  "type": "Feature",
  "properties": {
    "hierarchy": [
      "tgn:2727328",
      "tgn:1000001",
      "tgn:7012149",
      "tgn:2000933",
      "tgn:7007515",
      "tgn:7029392"
    ],
    "placetype": [
      "aat:300008699"
    ],
    "id": 2727328,
    "name:xx": "Trafton Brook"
  }
}
