{
  "type": "FeatureCollection",
  "features": [
    {
      "geometry": {
        "type": "Point",
        "coordinates": [
          8.6,
          45.9
        ]
      },
      "type": "Feature",
      "properties": {
        "hierarchy": [
          "tgn:1044170",
          "tgn:1000003",
          "tgn:1003508",
          "tgn:7003237",
          "tgn:1000080",
          "tgn:7029392"
        ],
        "placetype": [
          "aat:300008347"
        ],
        "id": 1044170,
        "name:xx": "Cerro"
      }
    },
    {
      "geometry": {
        "type": "Point",
        "coordinates": [
          16.35,
          40.05
        ]
      },
      "type": "Feature",
      "properties": {
        "hierarchy": [
          "tgn:1044171",
          "tgn:1003489",
          "tgn:7004610",
          "tgn:1000003",
          "tgn:1000080",
          "tgn:7029392"
        ],
        "placetype": [
          "aat:300008347"
        ],
        "id": 1044171,
        "name:xx": "Cersosimo"
      }
    },
    {
      "geometry": {
        "type": "Point",
        "coordinates": [
          10.9,
          46.7
        ]
      },
      "type": "Feature",
      "properties": {
        "hierarchy": [
          "tgn:1044173",
          "tgn:1003440",
          "tgn:1000003",
          "tgn:7003124",
          "tgn:1000080",
          "tgn:7029392"
        ],
        "placetype": [
          "aat:300008347"
        ],
        "id": 1044173,
        "name:xx": "Certosa"
      }
    },
    {
      "geometry": {
        "type": "Point",
        "coordinates": [
          10.333333,
          44.383333
        ]
      },
      "type": "Feature",
      "properties": {
        "hierarchy": [
          "tgn:1044175",
          "tgn:7003134",
          "tgn:1000003",
          "tgn:7008516",
          "tgn:1000080",
          "tgn:7029392"
        ],
        "placetype": [
          "aat:300008347"
        ],
        "id": 1044175,
        "name:xx": "Cervarezza"
      }
    },
    {
      "geometry": {
        "type": "Point",
        "coordinates": [
          13.9,
          41.483333
        ]
      },
      "type": "Feature",
      "properties": {
        "hierarchy": [
          "tgn:1044176",
          "tgn:7003135",
          "tgn:1000003",
          "tgn:7003080",
          "tgn:1000080",
          "tgn:7029392"
        ],
        "placetype": [
          "aat:300008347"
        ],
        "id": 1044176,
        "name:xx": "Cervaro"
      }
    },
    {
      "geometry": {
        "type": "Point",
        "coordinates": [
          13.338056,
          45.821111
        ]
      },
      "type": "Feature",
      "properties": {
        "hierarchy": [
          "tgn:1044179",
          "tgn:1003506",
          "tgn:1000003",
          "tgn:7002993",
          "tgn:1000080",
          "tgn:7029392"
        ],
        "placetype": [
          "aat:300008347"
        ],
        "id": 1044179,
        "name:xx": "Cervignano del Friuli"
      }
    }
  ]
}
