{
  "geometry": {
    "type": "Point",
    "coordinates": [
      -80.7667,
      35.0167
    ]
  },
  "type": "Feature",
  "properties": {
    "hierarchy": [
      "tgn:2614419",
      "tgn:1000001",
      "tgn:7012149",
      "tgn:2001546",
      "tgn:7007709",
      "tgn:7029392"
    ],
    "placetype": [
      "aat:300006191"
    ],
    "id": 2614419,
    "name:xx": "Reid Lake Number Two"
  }
}
