{
  "geometry": {
    "type": "Point",
    "coordinates": [
      124.05,
      13.05
    ]
  },
  "type": "Feature",
  "properties": {
    "hierarchy": [
      "tgn:1083971",
      "tgn:1000004",
      "tgn:1001540",
      "tgn:1000135",
      "tgn:7029392"
    ],
    "placetype": [
      "aat:300008347"
    ],
    "id": 1083971,
    "name:xx": "Bacon"
  }
}
