{
  "geometry": {
    "type": "Point",
    "coordinates": [
      -85.15,
      39.2667
    ]
  },
  "type": "Feature",
  "properties": {
    "hierarchy": [
      "tgn:2184446",
      "tgn:1000001",
      "tgn:7012149",
      "tgn:1002827",
      "tgn:7007252",
      "tgn:7029392"
    ],
    "placetype": [
      "aat:300008706"
    ],
    "id": 2184446,
    "name:xx": "Bobs Creek"
  }
}
