{
  "geometry": {
    "type": "Point",
    "coordinates": [
      -84.1167,
      30.3167
    ]
  },
  "type": "Feature",
  "properties": {
    "hierarchy": [
      "tgn:2399422",
      "tgn:1000001",
      "tgn:7012149",
      "tgn:2000277",
      "tgn:7007240",
      "tgn:7029392"
    ],
    "placetype": [
      "aat:300008697"
    ],
    "id": 2399422,
    "name:xx": "Horn Spring"
  }
}
