{
  "type": "FeatureCollection",
  "features": [
    {
      "geometry": {
        "type": "Point",
        "coordinates": [
          10.1,
          47.383333
        ]
      },
      "type": "Feature",
      "properties": {
        "hierarchy": [
          "tgn:7111730",
          "tgn:7003669",
          "tgn:1000003",
          "tgn:7000084",
          "tgn:7029392"
        ],
        "placetype": [
          "aat:300008795"
        ],
        "id": 7111730,
        "name:xx": "Roß Kopf"
      }
    },
    {
      "geometry": {
        "type": "Point",
        "coordinates": [
          10.583333,
          51.6
        ]
      },
      "type": "Feature",
      "properties": {
        "hierarchy": [
          "tgn:7111731",
          "tgn:1000003",
          "tgn:7003676",
          "tgn:7000084",
          "tgn:7029392"
        ],
        "placetype": [
          "aat:300008777"
        ],
        "id": 7111731,
        "name:xx": "Roßkopf"
      }
    },
    {
      "geometry": {
        "type": "Point",
        "coordinates": [
          9.916667,
          51.283333
        ]
      },
      "type": "Feature",
      "properties": {
        "hierarchy": [
          "tgn:7111732",
          "tgn:1000003",
          "tgn:7003678",
          "tgn:7000084",
          "tgn:7029392"
        ],
        "placetype": [
          "aat:300008777"
        ],
        "id": 7111732,
        "name:xx": "Roßkopf"
      }
    },
    {
      "geometry": {
        "type": "Point",
        "coordinates": [
          10.616667,
          50.75
        ]
      },
      "type": "Feature",
      "properties": {
        "hierarchy": [
          "tgn:7111733",
          "tgn:1000003",
          "tgn:7003689",
          "tgn:7000084",
          "tgn:7029392"
        ],
        "placetype": [
          "aat:300008777"
        ],
        "id": 7111733,
        "name:xx": "Roß-Kopf"
      }
    },
    {
      "geometry": {
        "type": "Point",
        "coordinates": [
          8.533333,
          50.25
        ]
      },
      "type": "Feature",
      "properties": {
        "hierarchy": [
          "tgn:7111735",
          "tgn:1000003",
          "tgn:7003678",
          "tgn:7000084",
          "tgn:7029392"
        ],
        "placetype": [
          "aat:300008777"
        ],
        "id": 7111735,
        "name:xx": "Roßkopf"
      }
    },
    {
      "geometry": {
        "type": "Point",
        "coordinates": [
          9.416667,
          50.2
        ]
      },
      "type": "Feature",
      "properties": {
        "hierarchy": [
          "tgn:7111736",
          "tgn:1000003",
          "tgn:7003678",
          "tgn:7000084",
          "tgn:7029392"
        ],
        "placetype": [
          "aat:300008777"
        ],
        "id": 7111736,
        "name:xx": "Roßkopf"
      }
    },
    {
      "geometry": {
        "type": "Point",
        "coordinates": [
          9.516667,
          50.166667
        ]
      },
      "type": "Feature",
      "properties": {
        "hierarchy": [
          "tgn:7111737",
          "tgn:1000003",
          "tgn:7003678",
          "tgn:7000084",
          "tgn:7029392"
        ],
        "placetype": [
          "aat:300008777"
        ],
        "id": 7111737,
        "name:xx": "Roßkopf"
      }
    },
    {
      "geometry": {
        "type": "Point",
        "coordinates": [
          8.133333,
          50.116667
        ]
      },
      "type": "Feature",
      "properties": {
        "hierarchy": [
          "tgn:7111738",
          "tgn:1000003",
          "tgn:7003678",
          "tgn:7000084",
          "tgn:7029392"
        ],
        "placetype": [
          "aat:300008777"
        ],
        "id": 7111738,
        "name:xx": "Roßkopf"
      }
    },
    {
      "geometry": {
        "type": "Point",
        "coordinates": [
          7.733333,
          49.983333
        ]
      },
      "type": "Feature",
      "properties": {
        "hierarchy": [
          "tgn:7111739",
          "tgn:1000003",
          "tgn:7003682",
          "tgn:7000084",
          "tgn:7029392"
        ],
        "placetype": [
          "aat:300008777"
        ],
        "id": 7111739,
        "name:xx": "Roß-Kopf"
      }
    }
  ]
}
