{
  "geometry": {
    "type": "Point",
    "coordinates": [
      31.05,
      31.45
    ]
  },
  "type": "Feature",
  "properties": {
    "hierarchy": [
      "tgn:7536582",
      "tgn:7001242",
      "tgn:7016833",
      "tgn:1001335",
      "tgn:7029392"
    ],
    "placetype": [
      "aat:300008750"
    ],
    "name:en": "Gûnet el- Maqât, Karâdîd",
    "id": 7536582
  }
}
