{
  "geometry": {
    "type": "Point",
    "coordinates": [
      39.7167,
      15.05
    ]
  },
  "type": "Feature",
  "properties": {
    "hierarchy": [
      "tgn:1089707",
      "tgn:7017569",
      "tgn:7001242",
      "tgn:7001658",
      "tgn:7029392"
    ],
    "placetype": [
      "aat:300008347"
    ],
    "id": 1089707,
    "name:xx": "Arafali"
  }
}
