{
  "geometry": {
    "type": "Point",
    "coordinates": [
      -5.95,
      43.016667
    ]
  },
  "type": "Feature",
  "properties": {
    "hierarchy": [
      "tgn:1107612",
      "tgn:7008911",
      "tgn:1000003",
      "tgn:7002763",
      "tgn:1000095",
      "tgn:7029392"
    ],
    "placetype": [
      "aat:300008798"
    ],
    "id": 1107612,
    "name:xx": "Ubiña, Peña"
  }
}
