{
  "geometry": {
    "type": "Point",
    "coordinates": [
      -105.2667,
      38.5833
    ]
  },
  "type": "Feature",
  "properties": {
    "hierarchy": [
      "tgn:2651738",
      "tgn:1000001",
      "tgn:7012149",
      "tgn:2000213",
      "tgn:7007158",
      "tgn:7029392"
    ],
    "placetype": [
      "aat:300008761"
    ],
    "id": 2651738,
    "name:xx": "Seep Springs Draw"
  }
}
