{
  "geometry": {
    "type": "Point",
    "coordinates": [
      31.284734,
      30.125992
    ]
  },
  "type": "Feature",
  "properties": {
    "hierarchy": [
      "tgn:7531671",
      "tgn:7001242",
      "tgn:7016833",
      "tgn:1001091",
      "tgn:7029392"
    ],
    "placetype": [
      "aat:300004792"
    ],
    "id": 7531671,
    "name:xx": "Shirkat an Nīl lil Zuyūt wa al Munaz̧z̧ifāt"
  }
}
