{
  "type": "FeatureCollection",
  "features": [
    {
      "geometry": {
        "type": "Point",
        "coordinates": [
          11.15,
          43.4
        ]
      },
      "type": "Feature",
      "properties": {
        "hierarchy": [
          "tgn:7039830",
          "tgn:7003168",
          "tgn:1000003",
          "tgn:7009760",
          "tgn:1000080",
          "tgn:7029392"
        ],
        "placetype": [
          "aat:300008805"
        ],
        "id": 7039830,
        "name:xx": "Senese, Piano"
      }
    },
    {
      "geometry": {
        "type": "Point",
        "coordinates": [
          9.65,
          40.483333
        ]
      },
      "type": "Feature",
      "properties": {
        "hierarchy": [
          "tgn:7039831",
          "tgn:1001724",
          "tgn:1000003",
          "tgn:7003121",
          "tgn:1000080",
          "tgn:7029392"
        ],
        "placetype": [
          "aat:300008795"
        ],
        "id": 7039831,
        "name:xx": "Senes, Monte"
      }
    },
    {
      "geometry": {
        "type": "Point",
        "coordinates": [
          12.216667,
          43.8
        ]
      },
      "type": "Feature",
      "properties": {
        "hierarchy": [
          "tgn:7039834",
          "tgn:1003483",
          "tgn:1000003",
          "tgn:7003240",
          "tgn:1000080",
          "tgn:7029392"
        ],
        "placetype": [
          "aat:300008699"
        ],
        "id": 7039834,
        "name:xx": "Senatello, Torrente"
      }
    },
    {
      "geometry": {
        "type": "Point",
        "coordinates": [
          11.333333,
          43.9
        ]
      },
      "type": "Feature",
      "properties": {
        "hierarchy": [
          "tgn:7039835",
          "tgn:7003163",
          "tgn:1000003",
          "tgn:7009760",
          "tgn:1000080",
          "tgn:7029392"
        ],
        "placetype": [
          "aat:300008795"
        ],
        "id": 7039835,
        "name:xx": "Senario, Monte"
      }
    },
    {
      "geometry": {
        "type": "Point",
        "coordinates": [
          9.116667,
          44.55
        ]
      },
      "type": "Feature",
      "properties": {
        "hierarchy": [
          "tgn:7039836",
          "tgn:1000003",
          "tgn:7003142",
          "tgn:7003236",
          "tgn:1000080",
          "tgn:7029392"
        ],
        "placetype": [
          "aat:300008347"
        ],
        "id": 7039836,
        "name:xx": "Senarega"
      }
    },
    {
      "geometry": {
        "type": "Point",
        "coordinates": [
          9.316667,
          40.7
        ]
      },
      "type": "Feature",
      "properties": {
        "hierarchy": [
          "tgn:7039837",
          "tgn:7015163",
          "tgn:1000003",
          "tgn:7003121",
          "tgn:1000080",
          "tgn:7029392"
        ],
        "placetype": [
          "aat:300008795"
        ],
        "id": 7039837,
        "name:xx": "Senalonga, Punta di"
      }
    },
    {
      "geometry": {
        "type": "Point",
        "coordinates": [
          10.883333,
          46.7
        ]
      },
      "type": "Feature",
      "properties": {
        "hierarchy": [
          "tgn:7039838",
          "tgn:1003440",
          "tgn:1000003",
          "tgn:7003124",
          "tgn:1000080",
          "tgn:7029392"
        ],
        "placetype": [
          "aat:300387198",
          "aat:300265612"
        ],
        "id": 7039838,
        "name:xx": "Comune di Senales"
      }
    }
  ]
}
