{
  "geometry": {
    "type": "Point",
    "coordinates": [
      6.15,
      51.25
    ]
  },
  "type": "Feature",
  "properties": {
    "hierarchy": [
      "tgn:7158419",
      "tgn:1000003",
      "tgn:7003677",
      "tgn:7000084",
      "tgn:7029392"
    ],
    "placetype": [
      "aat:300386887"
    ],
    "id": 7158419,
    "name:xx": "Holler Heide"
  }
}
