{
  "geometry": {
    "type": "Point",
    "coordinates": [
      74.51892,
      34.061674
    ]
  },
  "type": "Feature",
  "properties": {
    "hierarchy": [
      "tgn:7587942",
      "tgn:1000004",
      "tgn:7000198",
      "tgn:7000799",
      "tgn:7029392"
    ],
    "placetype": [
      "aat:300008347"
    ],
    "name:en": "Kārahom",
    "id": 7587942
  }
}
