{
  "geometry": {
    "type": "Point",
    "coordinates": [
      -106.5833,
      44.65
    ]
  },
  "type": "Feature",
  "properties": {
    "hierarchy": [
      "tgn:2747021",
      "tgn:1000001",
      "tgn:7012149",
      "tgn:2002381",
      "tgn:7007923",
      "tgn:7029392"
    ],
    "placetype": [
      "aat:300008706"
    ],
    "id": 2747021,
    "name:xx": "Wagner Prong Dutch Creek"
  }
}
