{
  "geometry": {
    "type": "Point",
    "coordinates": [
      -113.9333,
      42.8167
    ]
  },
  "type": "Feature",
  "properties": {
    "hierarchy": [
      "tgn:2521632",
      "tgn:1000001",
      "tgn:7012149",
      "tgn:2000483",
      "tgn:7007250",
      "tgn:7029392"
    ],
    "placetype": [
      "aat:300006191"
    ],
    "id": 2521632,
    "name:xx": "Montrose Reservoir"
  }
}
