{
  "geometry": {
    "type": "Point",
    "coordinates": [
      -91.5833,
      40.5333
    ]
  },
  "type": "Feature",
  "properties": {
    "hierarchy": [
      "tgn:2148199",
      "tgn:1000001",
      "tgn:7012149",
      "tgn:2000616",
      "tgn:7007253",
      "tgn:7029392"
    ],
    "placetype": [
      "aat:300008706"
    ],
    "id": 2148199,
    "name:xx": "Barlean Creek"
  }
}
