{
  "geometry": {
    "type": "Point",
    "coordinates": [
      -106.6667,
      37.5167
    ]
  },
  "type": "Feature",
  "properties": {
    "hierarchy": [
      "tgn:2633006",
      "tgn:1000001",
      "tgn:7012149",
      "tgn:7007158",
      "tgn:2000244",
      "tgn:7029392"
    ],
    "placetype": [
      "aat:300008680"
    ],
    "id": 2633006,
    "name:xx": "Rudifor Lake"
  }
}
