{
  "geometry": {
    "type": "Point",
    "coordinates": [
      -117.65,
      34.2333
    ]
  },
  "type": "Feature",
  "properties": {
    "hierarchy": [
      "tgn:2012854",
      "tgn:1000001",
      "tgn:7012149",
      "tgn:7007157",
      "tgn:1002857",
      "tgn:7029392"
    ],
    "placetype": [
      "aat:300008347"
    ],
    "id": 2012854,
    "name:xx": "Mount Baldy"
  }
}
