{
  "type": "FeatureCollection",
  "features": [
    {
      "geometry": {
        "type": "Point",
        "coordinates": [
          -108.6833,
          40.3167
        ]
      },
      "type": "Feature",
      "properties": {
        "hierarchy": [
          "tgn:2667610",
          "tgn:1000001",
          "tgn:7012149",
          "tgn:2000232",
          "tgn:7007158",
          "tgn:7029392"
        ],
        "placetype": [
          "aat:300008706"
        ],
        "id": 2667610,
        "name:xx": "Skull Creek"
      }
    },
    {
      "geometry": {
        "type": "Point",
        "coordinates": [
          -103.9167,
          38.95
        ]
      },
      "type": "Feature",
      "properties": {
        "hierarchy": [
          "tgn:2667611",
          "tgn:1000001",
          "tgn:7012149",
          "tgn:7007158",
          "tgn:7029392"
        ],
        "placetype": [
          "aat:300008706"
        ],
        "id": 2667611,
        "name:xx": "Skull Creek"
      }
    },
    {
      "geometry": {
        "type": "Point",
        "coordinates": [
          -115.8167,
          44.3167
        ]
      },
      "type": "Feature",
      "properties": {
        "hierarchy": [
          "tgn:2667612",
          "tgn:1000001",
          "tgn:7012149",
          "tgn:2000494",
          "tgn:7007250",
          "tgn:7029392"
        ],
        "placetype": [
          "aat:300008706"
        ],
        "id": 2667612,
        "name:xx": "Skull Creek"
      }
    },
    {
      "geometry": {
        "type": "Point",
        "coordinates": [
          -115.1167,
          45.4
        ]
      },
      "type": "Feature",
      "properties": {
        "hierarchy": [
          "tgn:2667613",
          "tgn:1000001",
          "tgn:7012149",
          "tgn:2000476",
          "tgn:7007250",
          "tgn:7029392"
        ],
        "placetype": [
          "aat:300008706"
        ],
        "id": 2667613,
        "name:xx": "Skull Creek"
      }
    },
    {
      "geometry": {
        "type": "Point",
        "coordinates": [
          -115.25,
          46.9
        ]
      },
      "type": "Feature",
      "properties": {
        "hierarchy": [
          "tgn:2667614",
          "tgn:1000001",
          "tgn:2000469",
          "tgn:7012149",
          "tgn:7007250",
          "tgn:7029392"
        ],
        "placetype": [
          "aat:300008706"
        ],
        "id": 2667614,
        "name:xx": "Skull Creek"
      }
    },
    {
      "geometry": {
        "type": "Point",
        "coordinates": [
          -116.0167,
          42
        ]
      },
      "type": "Feature",
      "properties": {
        "hierarchy": [
          "tgn:2667615",
          "tgn:1000001",
          "tgn:7012149",
          "tgn:7029392"
        ],
        "placetype": [
          "aat:300008706"
        ],
        "id": 2667615,
        "name:xx": "Skull Creek"
      }
    },
    {
      "geometry": {
        "type": "Point",
        "coordinates": [
          -88.65,
          39.4167
        ]
      },
      "type": "Feature",
      "properties": {
        "hierarchy": [
          "tgn:2667616",
          "tgn:1000001",
          "tgn:7012149",
          "tgn:1002885",
          "tgn:7007251",
          "tgn:7029392"
        ],
        "placetype": [
          "aat:300008706"
        ],
        "id": 2667616,
        "name:xx": "Skull Creek"
      }
    },
    {
      "geometry": {
        "type": "Point",
        "coordinates": [
          -96.5167,
          37.4333
        ]
      },
      "type": "Feature",
      "properties": {
        "hierarchy": [
          "tgn:2667617",
          "tgn:1000001",
          "tgn:2000677",
          "tgn:7012149",
          "tgn:7007254",
          "tgn:7029392"
        ],
        "placetype": [
          "aat:300008706"
        ],
        "id": 2667617,
        "name:xx": "Skull Creek"
      }
    },
    {
      "geometry": {
        "type": "Point",
        "coordinates": [
          -88.7333,
          31.2167
        ]
      },
      "type": "Feature",
      "properties": {
        "hierarchy": [
          "tgn:2667618",
          "tgn:1000001",
          "tgn:7012149",
          "tgn:2001106",
          "tgn:7007522",
          "tgn:7029392"
        ],
        "placetype": [
          "aat:300008706"
        ],
        "id": 2667618,
        "name:xx": "Skull Creek"
      }
    },
    {
      "geometry": {
        "type": "Point",
        "coordinates": [
          -92.95,
          38.8333
        ]
      },
      "type": "Feature",
      "properties": {
        "hierarchy": [
          "tgn:2667619",
          "tgn:1000001",
          "tgn:7012149",
          "tgn:2001189",
          "tgn:7007523",
          "tgn:7029392"
        ],
        "placetype": [
          "aat:300008706"
        ],
        "id": 2667619,
        "name:xx": "Skull Creek"
      }
    }
  ]
}
