{
  "type": "FeatureCollection",
  "features": [
    {
      "geometry": {
        "type": "Point",
        "coordinates": [
          138.9167,
          36.8667
        ]
      },
      "type": "Feature",
      "properties": {
        "hierarchy": [
          "tgn:1101340",
          "tgn:7000895",
          "tgn:1000004",
          "tgn:1001014",
          "tgn:1000120",
          "tgn:7029392"
        ],
        "placetype": [
          "aat:300007899"
        ],
        "id": 1101340,
        "name:xx": "Shimizu-tunnel"
      }
    },
    {
      "geometry": {
        "type": "Point",
        "coordinates": [
          8.0833,
          46.25
        ]
      },
      "type": "Feature",
      "properties": {
        "hierarchy": [
          "tgn:1101341",
          "tgn:1000003",
          "tgn:7029392"
        ],
        "placetype": [
          "aat:300007899"
        ],
        "name:en": "Simplon Tunnel",
        "id": 1101341
      }
    },
    {
      "geometry": {
        "type": "Point",
        "coordinates": [
          -2,
          53.5667
        ]
      },
      "type": "Feature",
      "properties": {
        "hierarchy": [
          "tgn:1101343",
          "tgn:7002445",
          "tgn:1000003",
          "tgn:7008591",
          "tgn:7029392"
        ],
        "placetype": [
          "aat:300007899"
        ],
        "id": 1101343,
        "name:xx": "Standedge Canal Tunnel"
      }
    },
    {
      "geometry": {
        "type": "Point",
        "coordinates": [
          -2,
          53.5667
        ]
      },
      "type": "Feature",
      "properties": {
        "hierarchy": [
          "tgn:1101344",
          "tgn:7002445",
          "tgn:1000003",
          "tgn:7008591",
          "tgn:7029392"
        ],
        "placetype": [
          "aat:300007899"
        ],
        "id": 1101344,
        "name:xx": "Standedge Railway Tunnel"
      }
    },
    {
      "geometry": {
        "type": "Point",
        "coordinates": [
          139.0667,
          35.1
        ]
      },
      "type": "Feature",
      "properties": {
        "hierarchy": [
          "tgn:1101345",
          "tgn:7000895",
          "tgn:1000004",
          "tgn:1001031",
          "tgn:1000120",
          "tgn:7029392"
        ],
        "placetype": [
          "aat:300007899"
        ],
        "id": 1101345,
        "name:xx": "Tanna-suidō"
      }
    },
    {
      "geometry": {
        "type": "Point",
        "coordinates": [
          7.5667,
          44.15
        ]
      },
      "type": "Feature",
      "properties": {
        "hierarchy": [
          "tgn:1101347",
          "tgn:1000003",
          "tgn:7029392"
        ],
        "placetype": [
          "aat:300007899"
        ],
        "name:fr": "Tende, Tunnel de",
        "id": 1101347
      }
    },
    {
      "geometry": {
        "type": "Point",
        "coordinates": [
          -79.25,
          42.95
        ]
      },
      "type": "Feature",
      "properties": {
        "hierarchy": [
          "tgn:1101348",
          "tgn:7005685",
          "tgn:1000001",
          "tgn:7013154",
          "tgn:7029392"
        ],
        "placetype": [
          "aat:300007899"
        ],
        "id": 1101348,
        "name:xx": "Townline Tunnel"
      }
    }
  ]
}
