{
  "geometry": {
    "type": "Point",
    "coordinates": [
      -51.5333,
      -28.2167
    ]
  },
  "type": "Feature",
  "properties": {
    "hierarchy": [
      "tgn:1021926",
      "tgn:1001941",
      "tgn:1000047",
      "tgn:7002458",
      "tgn:1000002",
      "tgn:7029392"
    ],
    "placetype": [
      "aat:300008347"
    ],
    "id": 1021926,
    "name:xx": "Lagoa Vermelha"
  }
}
