{
  "geometry": {
    "type": "Point",
    "coordinates": [
      -106.2333,
      35.65
    ]
  },
  "type": "Feature",
  "properties": {
    "hierarchy": [
      "tgn:2549149",
      "tgn:1000001",
      "tgn:7012149",
      "tgn:2001454",
      "tgn:7007566",
      "tgn:7029392"
    ],
    "placetype": [
      "aat:300000390"
    ],
    "id": 2549149,
    "name:xx": "North Red Bird"
  }
}
