{
  "geometry": {
    "type": "Point",
    "coordinates": [
      -74.6833,
      40.1833
    ]
  },
  "type": "Feature",
  "properties": {
    "hierarchy": [
      "tgn:2784445",
      "tgn:1000001",
      "tgn:1002657",
      "tgn:7012149",
      "tgn:7007565",
      "tgn:7029392"
    ],
    "placetype": [
      "aat:300008347"
    ],
    "id": 2784445,
    "name:xx": "Yardville Heights"
  }
}
