{
  "geometry": {
    "type": "Point",
    "coordinates": [
      -83.0167,
      39.1833
    ]
  },
  "type": "Feature",
  "properties": {
    "hierarchy": [
      "tgn:2523254",
      "tgn:1000001",
      "tgn:7012149",
      "tgn:7007706",
      "tgn:7029392"
    ],
    "placetype": [
      "aat:300008699"
    ],
    "id": 2523254,
    "name:xx": "Moores Run"
  }
}
