{
  "geometry": {
    "type": "Point",
    "coordinates": [
      78.85,
      9.683333
    ]
  },
  "type": "Feature",
  "properties": {
    "hierarchy": [
      "tgn:7574936",
      "tgn:1000004",
      "tgn:7000198",
      "tgn:7001797",
      "tgn:7029392"
    ],
    "placetype": [
      "aat:300008347"
    ],
    "name:en": "Kavvūr",
    "id": 7574936
  }
}
