{
  "geometry": {
    "type": "Point",
    "coordinates": [
      -78.8667,
      40.8833
    ]
  },
  "type": "Feature",
  "properties": {
    "hierarchy": [
      "tgn:2676735",
      "tgn:1000001",
      "tgn:7012149",
      "tgn:1002501",
      "tgn:7007710",
      "tgn:7029392"
    ],
    "placetype": [
      "aat:300008699"
    ],
    "id": 2676735,
    "name:xx": "South Branch Bear Run"
  }
}
