{
  "type": "FeatureCollection",
  "features": [
    {
      "geometry": {
        "type": "Point",
        "coordinates": [
          -97.95,
          40.15
        ]
      },
      "type": "Feature",
      "properties": {
        "hierarchy": [
          "tgn:2734310",
          "tgn:1000001",
          "tgn:7012149",
          "tgn:2001380",
          "tgn:7007525",
          "tgn:7029392"
        ],
        "placetype": [
          "aat:300008706"
        ],
        "id": 2734310,
        "name:xx": "Turtle Creek"
      }
    },
    {
      "geometry": {
        "type": "Point",
        "coordinates": [
          -96.4667,
          42.2333
        ]
      },
      "type": "Feature",
      "properties": {
        "hierarchy": [
          "tgn:2734311",
          "tgn:1000001",
          "tgn:7012149",
          "tgn:2001402",
          "tgn:7007525",
          "tgn:7029392"
        ],
        "placetype": [
          "aat:300008706"
        ],
        "id": 2734311,
        "name:xx": "Turtle Creek"
      }
    },
    {
      "geometry": {
        "type": "Point",
        "coordinates": [
          -74.4833,
          39.5833
        ]
      },
      "type": "Feature",
      "properties": {
        "hierarchy": [
          "tgn:2734312",
          "tgn:1002215",
          "tgn:1000001",
          "tgn:7012149",
          "tgn:7007565",
          "tgn:7029392"
        ],
        "placetype": [
          "aat:300008706"
        ],
        "id": 2734312,
        "name:xx": "Turtle Creek"
      }
    },
    {
      "geometry": {
        "type": "Point",
        "coordinates": [
          -100.9833,
          47.5833
        ]
      },
      "type": "Feature",
      "properties": {
        "hierarchy": [
          "tgn:2734313",
          "tgn:1000001",
          "tgn:2001584",
          "tgn:7012149",
          "tgn:7007705",
          "tgn:7029392"
        ],
        "placetype": [
          "aat:300008706"
        ],
        "id": 2734313,
        "name:xx": "Turtle Creek"
      }
    },
    {
      "geometry": {
        "type": "Point",
        "coordinates": [
          -101.9,
          45.95
        ]
      },
      "type": "Feature",
      "properties": {
        "hierarchy": [
          "tgn:2734314",
          "tgn:1000001",
          "tgn:7012149",
          "tgn:7007705",
          "tgn:7029392"
        ],
        "placetype": [
          "aat:300008706"
        ],
        "id": 2734314,
        "name:xx": "Turtle Creek"
      }
    },
    {
      "geometry": {
        "type": "Point",
        "coordinates": [
          -83.6667,
          39.2833
        ]
      },
      "type": "Feature",
      "properties": {
        "hierarchy": [
          "tgn:2734315",
          "tgn:1000001",
          "tgn:7012149",
          "tgn:1002476",
          "tgn:7007706",
          "tgn:7029392"
        ],
        "placetype": [
          "aat:300008706"
        ],
        "id": 2734315,
        "name:xx": "Turtle Creek"
      }
    },
    {
      "geometry": {
        "type": "Point",
        "coordinates": [
          -83.3,
          41.5667
        ]
      },
      "type": "Feature",
      "properties": {
        "hierarchy": [
          "tgn:2734316",
          "tgn:1000001",
          "tgn:7012149",
          "tgn:1002761",
          "tgn:7007706",
          "tgn:7029392"
        ],
        "placetype": [
          "aat:300008706"
        ],
        "id": 2734316,
        "name:xx": "Turtle Creek"
      }
    },
    {
      "geometry": {
        "type": "Point",
        "coordinates": [
          -84.1167,
          39.4333
        ]
      },
      "type": "Feature",
      "properties": {
        "hierarchy": [
          "tgn:2734317",
          "tgn:1000001",
          "tgn:7012149",
          "tgn:1002987",
          "tgn:7007706",
          "tgn:7029392"
        ],
        "placetype": [
          "aat:300008706"
        ],
        "id": 2734317,
        "name:xx": "Turtle Creek"
      }
    },
    {
      "geometry": {
        "type": "Point",
        "coordinates": [
          -84.25,
          40.25
        ]
      },
      "type": "Feature",
      "properties": {
        "hierarchy": [
          "tgn:2734318",
          "tgn:1000001",
          "tgn:7012149",
          "tgn:1002889",
          "tgn:7007706",
          "tgn:7029392"
        ],
        "placetype": [
          "aat:300008706"
        ],
        "id": 2734318,
        "name:xx": "Turtle Creek"
      }
    },
    {
      "geometry": {
        "type": "Point",
        "coordinates": [
          -97.9167,
          34.8833
        ]
      },
      "type": "Feature",
      "properties": {
        "hierarchy": [
          "tgn:2734319",
          "tgn:1000001",
          "tgn:2001648",
          "tgn:7012149",
          "tgn:7007707",
          "tgn:7029392"
        ],
        "placetype": [
          "aat:300008706"
        ],
        "id": 2734319,
        "name:xx": "Turtle Creek"
      }
    }
  ]
}
