{
  "geometry": {
    "type": "Point",
    "coordinates": [
      -83.8167,
      39.5833
    ]
  },
  "type": "Feature",
  "properties": {
    "hierarchy": [
      "tgn:2081294",
      "tgn:1000001",
      "tgn:7012149",
      "tgn:1002424",
      "tgn:7007706",
      "tgn:7029392"
    ],
    "placetype": [
      "aat:300008347"
    ],
    "id": 2081294,
    "name:xx": "Paintersville"
  }
}
