{
  "geometry": {
    "type": "Point",
    "coordinates": [
      -84.9167,
      34.5333
    ]
  },
  "type": "Feature",
  "properties": {
    "hierarchy": [
      "tgn:2196201",
      "tgn:1000001",
      "tgn:7012149",
      "tgn:2000355",
      "tgn:7007248",
      "tgn:7029392"
    ],
    "placetype": [
      "aat:300008798"
    ],
    "id": 2196201,
    "name:xx": "Brogdon Hill"
  }
}
