{
  "geometry": {
    "type": "Point",
    "coordinates": [
      -133.3667,
      58.4167
    ]
  },
  "type": "Feature",
  "properties": {
    "hierarchy": [
      "tgn:2555605",
      "tgn:7006450",
      "tgn:1000001",
      "tgn:2124089",
      "tgn:7012149",
      "tgn:7029392"
    ],
    "placetype": [
      "aat:300008798"
    ],
    "id": 2555605,
    "name:xx": "Ogden, Mount"
  }
}
