{
  "type": "FeatureCollection",
  "features": [
    {
      "geometry": {
        "type": "Point",
        "coordinates": [
          -80.5,
          33.4167
        ]
      },
      "type": "Feature",
      "properties": {
        "hierarchy": [
          "tgn:2416410",
          "tgn:1000001",
          "tgn:7012149",
          "tgn:2001762",
          "tgn:7007712",
          "tgn:7029392"
        ],
        "placetype": [
          "aat:300008699"
        ],
        "id": 2416410,
        "name:xx": "Jack Branch"
      }
    },
    {
      "geometry": {
        "type": "Point",
        "coordinates": [
          -87.8,
          35.5833
        ]
      },
      "type": "Feature",
      "properties": {
        "hierarchy": [
          "tgn:2416411",
          "tgn:1000001",
          "tgn:7012149",
          "tgn:2001904",
          "tgn:7007825",
          "tgn:7029392"
        ],
        "placetype": [
          "aat:300008699"
        ],
        "id": 2416411,
        "name:xx": "Jack Branch"
      }
    },
    {
      "geometry": {
        "type": "Point",
        "coordinates": [
          -85.3167,
          35.7
        ]
      },
      "type": "Feature",
      "properties": {
        "hierarchy": [
          "tgn:2416412",
          "tgn:1000001",
          "tgn:7012149",
          "tgn:7007825",
          "tgn:7029392"
        ],
        "placetype": [
          "aat:300008699"
        ],
        "id": 2416412,
        "name:xx": "Jack Branch"
      }
    },
    {
      "geometry": {
        "type": "Point",
        "coordinates": [
          -87.3167,
          35.7833
        ]
      },
      "type": "Feature",
      "properties": {
        "hierarchy": [
          "tgn:2416413",
          "tgn:1000001",
          "tgn:7012149",
          "tgn:7015666",
          "tgn:7007825",
          "tgn:7029392"
        ],
        "placetype": [
          "aat:300008699"
        ],
        "id": 2416413,
        "name:xx": "Jack Branch"
      }
    },
    {
      "geometry": {
        "type": "Point",
        "coordinates": [
          -84.2667,
          36.1833
        ]
      },
      "type": "Feature",
      "properties": {
        "hierarchy": [
          "tgn:2416414",
          "tgn:2001837",
          "tgn:1000001",
          "tgn:7012149",
          "tgn:7007825",
          "tgn:7029392"
        ],
        "placetype": [
          "aat:300008699"
        ],
        "id": 2416414,
        "name:xx": "Jack Branch"
      }
    },
    {
      "geometry": {
        "type": "Point",
        "coordinates": [
          -84.6167,
          35.0167
        ]
      },
      "type": "Feature",
      "properties": {
        "hierarchy": [
          "tgn:2416415",
          "tgn:1000001",
          "tgn:7012149",
          "tgn:2001906",
          "tgn:7007825",
          "tgn:7029392"
        ],
        "placetype": [
          "aat:300008699"
        ],
        "id": 2416415,
        "name:xx": "Jack Branch"
      }
    },
    {
      "geometry": {
        "type": "Point",
        "coordinates": [
          -87.8667,
          35.8667
        ]
      },
      "type": "Feature",
      "properties": {
        "hierarchy": [
          "tgn:2416416",
          "tgn:1000001",
          "tgn:7012149",
          "tgn:2001879",
          "tgn:7007825",
          "tgn:7029392"
        ],
        "placetype": [
          "aat:300008699"
        ],
        "id": 2416416,
        "name:xx": "Jack Branch"
      }
    },
    {
      "geometry": {
        "type": "Point",
        "coordinates": [
          -85.1167,
          36.1833
        ]
      },
      "type": "Feature",
      "properties": {
        "hierarchy": [
          "tgn:2416417",
          "tgn:1000001",
          "tgn:7012149",
          "tgn:2001903",
          "tgn:7007825",
          "tgn:7029392"
        ],
        "placetype": [
          "aat:300008699"
        ],
        "id": 2416417,
        "name:xx": "Jack Branch"
      }
    },
    {
      "geometry": {
        "type": "Point",
        "coordinates": [
          -96.5333,
          29.5667
        ]
      },
      "type": "Feature",
      "properties": {
        "hierarchy": [
          "tgn:2416418",
          "tgn:1000001",
          "tgn:7012149",
          "tgn:1002291",
          "tgn:7007826",
          "tgn:7029392"
        ],
        "placetype": [
          "aat:300008699"
        ],
        "id": 2416418,
        "name:xx": "Jack Branch"
      }
    },
    {
      "geometry": {
        "type": "Point",
        "coordinates": [
          -97.7333,
          31.7
        ]
      },
      "type": "Feature",
      "properties": {
        "hierarchy": [
          "tgn:2416419",
          "tgn:1000001",
          "tgn:7012149",
          "tgn:7007826",
          "tgn:7029392"
        ],
        "placetype": [
          "aat:300008699"
        ],
        "id": 2416419,
        "name:xx": "Jack Branch"
      }
    }
  ]
}
