{
  "type": "FeatureCollection",
  "features": [
    {
      "geometry": {
        "type": "Point",
        "coordinates": [
          -120.8167,
          42.2167
        ]
      },
      "type": "Feature",
      "properties": {
        "hierarchy": [
          "tgn:2468711",
          "tgn:1000001",
          "tgn:7012149",
          "tgn:2001715",
          "tgn:7007708",
          "tgn:7029392"
        ],
        "placetype": [
          "aat:300008905"
        ],
        "id": 2468711,
        "name:xx": "Long Prairie"
      }
    },
    {
      "geometry": {
        "type": "Point",
        "coordinates": [
          -124.3167,
          42.4167
        ]
      },
      "type": "Feature",
      "properties": {
        "hierarchy": [
          "tgn:2468712",
          "tgn:1000001",
          "tgn:2001704",
          "tgn:7012149",
          "tgn:7007708",
          "tgn:7029392"
        ],
        "placetype": [
          "aat:300055621"
        ],
        "id": 2468712,
        "name:xx": "Long Prairie"
      }
    },
    {
      "geometry": {
        "type": "Point",
        "coordinates": [
          -97.0333,
          30.1167
        ]
      },
      "type": "Feature",
      "properties": {
        "hierarchy": [
          "tgn:2468713",
          "tgn:1000001",
          "tgn:7012149",
          "tgn:7007826",
          "tgn:7029392"
        ],
        "placetype": [
          "aat:300008699"
        ],
        "id": 2468713,
        "name:xx": "Long Prairie Branch"
      }
    },
    {
      "geometry": {
        "type": "Point",
        "coordinates": [
          -94.4333,
          31.1667
        ]
      },
      "type": "Feature",
      "properties": {
        "hierarchy": [
          "tgn:2468714",
          "tgn:1002149",
          "tgn:1000001",
          "tgn:7012149",
          "tgn:7007826",
          "tgn:7029392"
        ],
        "placetype": [
          "aat:300008699"
        ],
        "id": 2468714,
        "name:xx": "Long Prairie Branch"
      }
    },
    {
      "geometry": {
        "type": "Point",
        "coordinates": [
          -123.85,
          40.9167
        ]
      },
      "type": "Feature",
      "properties": {
        "hierarchy": [
          "tgn:2468715",
          "tgn:1000001",
          "tgn:7012149",
          "tgn:2000181",
          "tgn:7007157",
          "tgn:7029392"
        ],
        "placetype": [
          "aat:300008706"
        ],
        "id": 2468715,
        "name:xx": "Long Prairie Creek"
      }
    },
    {
      "geometry": {
        "type": "Point",
        "coordinates": [
          -122.2167,
          42.1167
        ]
      },
      "type": "Feature",
      "properties": {
        "hierarchy": [
          "tgn:2468716",
          "tgn:1000001",
          "tgn:7012149",
          "tgn:7029392"
        ],
        "placetype": [
          "aat:300008706"
        ],
        "id": 2468716,
        "name:xx": "Long Prairie Creek"
      }
    },
    {
      "geometry": {
        "type": "Point",
        "coordinates": [
          -114.9833,
          45.9
        ]
      },
      "type": "Feature",
      "properties": {
        "hierarchy": [
          "tgn:2468717",
          "tgn:1000001",
          "tgn:7012149",
          "tgn:2000476",
          "tgn:7007250",
          "tgn:7029392"
        ],
        "placetype": [
          "aat:300008706"
        ],
        "id": 2468717,
        "name:xx": "Long Prairie Creek"
      }
    },
    {
      "geometry": {
        "type": "Point",
        "coordinates": [
          -84.6,
          40.75
        ]
      },
      "type": "Feature",
      "properties": {
        "hierarchy": [
          "tgn:2468718",
          "tgn:1000001",
          "tgn:7012149",
          "tgn:1002968",
          "tgn:7007706",
          "tgn:7029392"
        ],
        "placetype": [
          "aat:300008706"
        ],
        "id": 2468718,
        "name:xx": "Long Prairie Creek"
      }
    },
    {
      "geometry": {
        "type": "Point",
        "coordinates": [
          -123.7333,
          44.7
        ]
      },
      "type": "Feature",
      "properties": {
        "hierarchy": [
          "tgn:2468719",
          "tgn:1000001",
          "tgn:7012149",
          "tgn:1002599",
          "tgn:7007708",
          "tgn:7029392"
        ],
        "placetype": [
          "aat:300008706"
        ],
        "id": 2468719,
        "name:xx": "Long Prairie Creek"
      }
    }
  ]
}
