{
  "geometry": {
    "type": "Point",
    "coordinates": [
      -103.8333,
      35.0667
    ]
  },
  "type": "Feature",
  "properties": {
    "hierarchy": [
      "tgn:2183267",
      "tgn:1000001",
      "tgn:7012149",
      "tgn:2001448",
      "tgn:7007566",
      "tgn:7029392"
    ],
    "placetype": [
      "aat:300008706"
    ],
    "id": 2183267,
    "name:xx": "Bluewater Creek"
  }
}
