{
  "geometry": {
    "type": "Point",
    "coordinates": [
      -113.1167,
      44.8167
    ]
  },
  "type": "Feature",
  "properties": {
    "hierarchy": [
      "tgn:2479648",
      "tgn:1000001",
      "tgn:2001260",
      "tgn:7012149",
      "tgn:7007524",
      "tgn:7029392"
    ],
    "placetype": [
      "aat:300008761"
    ],
    "id": 2479648,
    "name:xx": "Lake Canyon"
  }
}
