{
  "type": "FeatureCollection",
  "features": [
    {
      "geometry": {
        "type": "Point",
        "coordinates": [
          -92.7,
          32.95
        ]
      },
      "type": "Feature",
      "properties": {
        "hierarchy": [
          "tgn:2165140",
          "tgn:1000001",
          "tgn:7012149",
          "tgn:2000909",
          "tgn:7007256",
          "tgn:7029392"
        ],
        "placetype": [
          "aat:300008347"
        ],
        "id": 2165140,
        "name:xx": "Bethel Springs"
      }
    },
    {
      "geometry": {
        "type": "Point",
        "coordinates": [
          -84.1667,
          36
        ]
      },
      "type": "Feature",
      "properties": {
        "hierarchy": [
          "tgn:2165141",
          "tgn:1000001",
          "tgn:7012149",
          "tgn:7007825",
          "tgn:7029392"
        ],
        "placetype": [
          "aat:300008761"
        ],
        "id": 2165141,
        "name:xx": "Bethel Valley"
      }
    },
    {
      "geometry": {
        "type": "Point",
        "coordinates": [
          -81.2,
          28.8333
        ]
      },
      "type": "Feature",
      "properties": {
        "hierarchy": [
          "tgn:2165142",
          "tgn:1000001",
          "tgn:7012149",
          "tgn:1002977",
          "tgn:7007240",
          "tgn:7029392"
        ],
        "placetype": [
          "aat:300008680"
        ],
        "id": 2165142,
        "name:xx": "Bethel, Lake"
      }
    },
    {
      "geometry": {
        "type": "Point",
        "coordinates": [
          -105.8667,
          39.7
        ]
      },
      "type": "Feature",
      "properties": {
        "hierarchy": [
          "tgn:2165143",
          "tgn:1000001",
          "tgn:2000201",
          "tgn:7012149",
          "tgn:7007158",
          "tgn:7029392"
        ],
        "placetype": [
          "aat:300008798"
        ],
        "id": 2165143,
        "name:xx": "Bethel, Mount"
      }
    },
    {
      "geometry": {
        "type": "Point",
        "coordinates": [
          -93.2,
          40.8333
        ]
      },
      "type": "Feature",
      "properties": {
        "hierarchy": [
          "tgn:2165144",
          "tgn:1000001",
          "tgn:7012149",
          "tgn:2000653",
          "tgn:7007253",
          "tgn:7029392"
        ],
        "placetype": [
          "aat:300008347"
        ],
        "id": 2165144,
        "name:xx": "Bethelhem"
      }
    },
    {
      "geometry": {
        "type": "Point",
        "coordinates": [
          -104.9667,
          34.2167
        ]
      },
      "type": "Feature",
      "properties": {
        "hierarchy": [
          "tgn:2165145",
          "tgn:1000001",
          "tgn:7012149",
          "tgn:2001442",
          "tgn:7007566",
          "tgn:7029392"
        ],
        "placetype": [
          "aat:300006191"
        ],
        "id": 2165145,
        "name:xx": "Bethell Tank"
      }
    },
    {
      "geometry": {
        "type": "Point",
        "coordinates": [
          -75.6833,
          39.1333
        ]
      },
      "type": "Feature",
      "properties": {
        "hierarchy": [
          "tgn:2165146",
          "tgn:1002538",
          "tgn:1000001",
          "tgn:7012149",
          "tgn:7007239",
          "tgn:7029392"
        ],
        "placetype": [
          "aat:300008347"
        ],
        "id": 2165146,
        "name:xx": "Bethesda"
      }
    },
    {
      "geometry": {
        "type": "Point",
        "coordinates": [
          -83,
          33.6333
        ]
      },
      "type": "Feature",
      "properties": {
        "hierarchy": [
          "tgn:2165147",
          "tgn:1000001",
          "tgn:7012149",
          "tgn:2000357",
          "tgn:7007248",
          "tgn:7029392"
        ],
        "placetype": [
          "aat:300008347"
        ],
        "id": 2165147,
        "name:xx": "Bethesda"
      }
    },
    {
      "geometry": {
        "type": "Point",
        "coordinates": [
          -95.0833,
          40.8333
        ]
      },
      "type": "Feature",
      "properties": {
        "hierarchy": [
          "tgn:2165148",
          "tgn:1000001",
          "tgn:7012149",
          "tgn:2000633",
          "tgn:7007253",
          "tgn:7029392"
        ],
        "placetype": [
          "aat:300008347"
        ],
        "id": 2165148,
        "name:xx": "Bethesda"
      }
    },
    {
      "geometry": {
        "type": "Point",
        "coordinates": [
          -90.3667,
          32.1333
        ]
      },
      "type": "Feature",
      "properties": {
        "hierarchy": [
          "tgn:2165149",
          "tgn:1000001",
          "tgn:7012149",
          "tgn:2001110",
          "tgn:7007522",
          "tgn:7029392"
        ],
        "placetype": [
          "aat:300008347"
        ],
        "id": 2165149,
        "name:xx": "Bethesda"
      }
    }
  ]
}
