{
  "geometry": {
    "type": "Point",
    "coordinates": [
      -82.9833,
      41.25
    ]
  },
  "type": "Feature",
  "properties": {
    "hierarchy": [
      "tgn:2343637",
      "tgn:1000001",
      "tgn:7012149",
      "tgn:1002865",
      "tgn:7007706",
      "tgn:7029392"
    ],
    "placetype": [
      "aat:300008347"
    ],
    "id": 2343637,
    "name:xx": "Galetown"
  }
}
