{
  "geometry": {
    "type": "Point",
    "coordinates": [
      -111.45,
      38.4333
    ]
  },
  "type": "Feature",
  "properties": {
    "hierarchy": [
      "tgn:2739738",
      "tgn:1000001",
      "tgn:7012149",
      "tgn:2002128",
      "tgn:7007827",
      "tgn:7029392"
    ],
    "placetype": [
      "aat:300008697"
    ],
    "id": 2739738,
    "name:xx": "Upper Deep Creek Spring"
  }
}
