{
  "geometry": {
    "type": "Point",
    "coordinates": [
      -74.8167,
      44.1333
    ]
  },
  "type": "Feature",
  "properties": {
    "hierarchy": [
      "tgn:2758919",
      "tgn:1000001",
      "tgn:7012149",
      "tgn:7016021",
      "tgn:7007568",
      "tgn:7029392"
    ],
    "placetype": [
      "aat:300132316"
    ],
    "id": 2758919,
    "name:xx": "West Flow"
  }
}
