{
  "geometry": {
    "type": "Point",
    "coordinates": [
      -115.4167,
      41.75
    ]
  },
  "type": "Feature",
  "properties": {
    "hierarchy": [
      "tgn:2216711",
      "tgn:1000001",
      "tgn:2001411",
      "tgn:7012149",
      "tgn:7007526",
      "tgn:7029392"
    ],
    "placetype": [
      "aat:300008761"
    ],
    "id": 2216711,
    "name:xx": "Camp Draw"
  }
}
