{
  "geometry": {
    "type": "Point",
    "coordinates": [
      167.75,
      -16.25
    ]
  },
  "type": "Feature",
  "properties": {
    "hierarchy": [
      "tgn:7024016",
      "tgn:1000225",
      "tgn:1000006",
      "tgn:7029392"
    ],
    "placetype": [
      "aat:300387064",
      "aat:300000774"
    ],
    "id": 7024016,
    "name:xx": "Malampa"
  }
}
