{
  "geometry": {
    "type": "Point",
    "coordinates": [
      76.31,
      -16.476
    ]
  },
  "type": "Feature",
  "properties": {
    "hierarchy": [
      "tgn:1077093",
      "tgn:1000004",
      "tgn:7000198",
      "tgn:1001882",
      "tgn:7029392"
    ],
    "placetype": [
      "aat:300008347"
    ],
    "name:en": "Tālīkota",
    "id": 1077093
  }
}
