{
  "geometry": {
    "type": "Point",
    "coordinates": [
      -74.6667,
      43.8333
    ]
  },
  "type": "Feature",
  "properties": {
    "hierarchy": [
      "tgn:2700570",
      "tgn:1000001",
      "tgn:7012149",
      "tgn:1002440",
      "tgn:7007568",
      "tgn:7029392"
    ],
    "placetype": [
      "aat:300132316"
    ],
    "id": 2700570,
    "name:xx": "Sucker Brook Bay"
  }
}
