{
  "geometry": {
    "type": "Point",
    "coordinates": [
      118.1833,
      29.5833
    ]
  },
  "type": "Feature",
  "properties": {
    "hierarchy": [
      "tgn:1139754",
      "tgn:7002075",
      "tgn:1000004",
      "tgn:1000111",
      "tgn:7029392"
    ],
    "placetype": [
      "aat:300008347"
    ],
    "id": 1139754,
    "name:xx": "Wucheng"
  }
}
