{
  "geometry": {
    "type": "Point",
    "coordinates": [
      -86.0333,
      37.7167
    ]
  },
  "type": "Feature",
  "properties": {
    "hierarchy": [
      "tgn:2576564",
      "tgn:1000001",
      "tgn:7012149",
      "tgn:2000796",
      "tgn:7007255",
      "tgn:7029392"
    ],
    "placetype": [
      "aat:300008347"
    ],
    "id": 2576564,
    "name:xx": "Perryville"
  }
}
