{
  "geometry": {
    "type": "Point",
    "coordinates": [
      79.08355,
      27.781503
    ]
  },
  "type": "Feature",
  "properties": {
    "hierarchy": [
      "tgn:7562147",
      "tgn:1000004",
      "tgn:7000198",
      "tgn:7016722",
      "tgn:7029392"
    ],
    "placetype": [
      "aat:300008347"
    ],
    "name:en": "Mahāula",
    "id": 7562147
  }
}
