{
  "geometry": {
    "type": "Point",
    "coordinates": [
      51.7833,
      57.1833
    ]
  },
  "type": "Feature",
  "properties": {
    "hierarchy": [
      "tgn:1058753",
      "tgn:1000004",
      "tgn:7002435",
      "tgn:7011526",
      "tgn:7029392"
    ],
    "placetype": [
      "aat:300008347"
    ],
    "id": 1058753,
    "name:xx": "Pumsi"
  }
}
