{
  "geometry": {
    "type": "Point",
    "coordinates": [
      -109.1833,
      34.0667
    ]
  },
  "type": "Feature",
  "properties": {
    "hierarchy": [
      "tgn:2519976",
      "tgn:2000090",
      "tgn:1000001",
      "tgn:7006451",
      "tgn:7012149",
      "tgn:7029392"
    ],
    "placetype": [
      "aat:300008697"
    ],
    "id": 2519976,
    "name:xx": "Molina Spring"
  }
}
