{
  "geometry": {
    "type": "Point",
    "coordinates": [
      -94.7667,
      37.75
    ]
  },
  "type": "Feature",
  "properties": {
    "hierarchy": [
      "tgn:2231812",
      "tgn:2000665",
      "tgn:1000001",
      "tgn:7012149",
      "tgn:7007254",
      "tgn:7029392"
    ],
    "placetype": [
      "aat:300008699"
    ],
    "id": 2231812,
    "name:xx": "Chambers Branch"
  }
}
