{
  "geometry": {
    "type": "Point",
    "coordinates": [
      -111.3667,
      41.2833
    ]
  },
  "type": "Feature",
  "properties": {
    "hierarchy": [
      "tgn:2182422",
      "tgn:1000001",
      "tgn:7012149",
      "tgn:2002115",
      "tgn:7007827",
      "tgn:7029392"
    ],
    "placetype": [
      "aat:300266640"
    ],
    "id": 2182422,
    "name:xx": "Blue Ridge"
  }
}
