{
  "geometry": {
    "type": "Point",
    "coordinates": [
      -122.7833,
      39.8833
    ]
  },
  "type": "Feature",
  "properties": {
    "hierarchy": [
      "tgn:2714220",
      "tgn:1000001",
      "tgn:7012149",
      "tgn:7007157",
      "tgn:2000190",
      "tgn:7029392"
    ],
    "placetype": [
      "aat:300266640"
    ],
    "id": 2714220,
    "name:xx": "Telephone Ridge"
  }
}
