{
  "geometry": {
    "type": "Point",
    "coordinates": [
      117.2667,
      38.8833
    ]
  },
  "type": "Feature",
  "properties": {
    "hierarchy": [
      "tgn:1072489",
      "tgn:1000004",
      "tgn:1000960",
      "tgn:1000111",
      "tgn:7029392"
    ],
    "placetype": [
      "aat:300008347"
    ],
    "id": 1072489,
    "name:xx": "Wangwenzhuang"
  }
}
