{
  "type": "FeatureCollection",
  "features": [
    {
      "geometry": {
        "type": "Point",
        "coordinates": [
          -84.6833,
          36.0667
        ]
      },
      "type": "Feature",
      "properties": {
        "hierarchy": [
          "tgn:2216260",
          "tgn:1000001",
          "tgn:7012149",
          "tgn:2001901",
          "tgn:7007825",
          "tgn:7029392"
        ],
        "placetype": [
          "aat:300008699"
        ],
        "id": 2216260,
        "name:xx": "Camp Branch"
      }
    },
    {
      "geometry": {
        "type": "Point",
        "coordinates": [
          -88.2,
          36.1833
        ]
      },
      "type": "Feature",
      "properties": {
        "hierarchy": [
          "tgn:2216261",
          "tgn:1000001",
          "tgn:7012149",
          "tgn:2001876",
          "tgn:7007825",
          "tgn:7029392"
        ],
        "placetype": [
          "aat:300008699"
        ],
        "id": 2216261,
        "name:xx": "Camp Branch"
      }
    },
    {
      "geometry": {
        "type": "Point",
        "coordinates": [
          -84.7167,
          36.4
        ]
      },
      "type": "Feature",
      "properties": {
        "hierarchy": [
          "tgn:2216262",
          "tgn:1000001",
          "tgn:7012149",
          "tgn:2001861",
          "tgn:7007825",
          "tgn:7029392"
        ],
        "placetype": [
          "aat:300008699"
        ],
        "id": 2216262,
        "name:xx": "Camp Branch"
      }
    },
    {
      "geometry": {
        "type": "Point",
        "coordinates": [
          -87.35,
          35.45
        ]
      },
      "type": "Feature",
      "properties": {
        "hierarchy": [
          "tgn:2216263",
          "tgn:1000001",
          "tgn:7012149",
          "tgn:7007825",
          "tgn:7029392"
        ],
        "placetype": [
          "aat:300008699"
        ],
        "id": 2216263,
        "name:xx": "Camp Branch"
      }
    },
    {
      "geometry": {
        "type": "Point",
        "coordinates": [
          -87.2833,
          35.55
        ]
      },
      "type": "Feature",
      "properties": {
        "hierarchy": [
          "tgn:2216264",
          "tgn:1000001",
          "tgn:7012149",
          "tgn:2001896",
          "tgn:7007825",
          "tgn:7029392"
        ],
        "placetype": [
          "aat:300008699"
        ],
        "id": 2216264,
        "name:xx": "Camp Branch"
      }
    },
    {
      "geometry": {
        "type": "Point",
        "coordinates": [
          -85.8667,
          35.9667
        ]
      },
      "type": "Feature",
      "properties": {
        "hierarchy": [
          "tgn:2216265",
          "tgn:1000001",
          "tgn:7012149",
          "tgn:7022246",
          "tgn:7007825",
          "tgn:7029392"
        ],
        "placetype": [
          "aat:300008699"
        ],
        "id": 2216265,
        "name:xx": "Camp Branch"
      }
    },
    {
      "geometry": {
        "type": "Point",
        "coordinates": [
          -97.9667,
          32.1
        ]
      },
      "type": "Feature",
      "properties": {
        "hierarchy": [
          "tgn:2216266",
          "tgn:1000001",
          "tgn:7012149",
          "tgn:7007826",
          "tgn:7029392"
        ],
        "placetype": [
          "aat:300008699"
        ],
        "id": 2216266,
        "name:xx": "Camp Branch"
      }
    },
    {
      "geometry": {
        "type": "Point",
        "coordinates": [
          -95.9833,
          32.5333
        ]
      },
      "type": "Feature",
      "properties": {
        "hierarchy": [
          "tgn:2216267",
          "tgn:1000001",
          "tgn:7012149",
          "tgn:1002969",
          "tgn:7007826",
          "tgn:7029392"
        ],
        "placetype": [
          "aat:300008699"
        ],
        "id": 2216267,
        "name:xx": "Camp Branch"
      }
    },
    {
      "geometry": {
        "type": "Point",
        "coordinates": [
          -95.0667,
          30.1333
        ]
      },
      "type": "Feature",
      "properties": {
        "hierarchy": [
          "tgn:2216268",
          "tgn:1000001",
          "tgn:7012149",
          "tgn:1002595",
          "tgn:7007826",
          "tgn:7029392"
        ],
        "placetype": [
          "aat:300008699"
        ],
        "id": 2216268,
        "name:xx": "Camp Branch"
      }
    },
    {
      "geometry": {
        "type": "Point",
        "coordinates": [
          -94.85,
          32.05
        ]
      },
      "type": "Feature",
      "properties": {
        "hierarchy": [
          "tgn:2216269",
          "tgn:1000001",
          "tgn:7012149",
          "tgn:1002839",
          "tgn:7007826",
          "tgn:7029392"
        ],
        "placetype": [
          "aat:300008699"
        ],
        "id": 2216269,
        "name:xx": "Camp Branch"
      }
    }
  ]
}
