{
  "type": "FeatureCollection",
  "features": [
    {
      "geometry": {
        "type": "Point",
        "coordinates": [
          0.766667,
          51.483333
        ]
      },
      "type": "Feature",
      "properties": {
        "hierarchy": [
          "tgn:7458073",
          "tgn:7002445",
          "tgn:1000003",
          "tgn:7008153",
          "tgn:7008591",
          "tgn:7029392"
        ],
        "placetype": [
          "aat:300387036"
        ],
        "name:en": "Nore Sand",
        "id": 7458073
      }
    },
    {
      "geometry": {
        "type": "Point",
        "coordinates": [
          -0.016667,
          51.3
        ]
      },
      "type": "Feature",
      "properties": {
        "hierarchy": [
          "tgn:7458074",
          "tgn:7002445",
          "tgn:1000003",
          "tgn:7008175",
          "tgn:7008591",
          "tgn:7029392"
        ],
        "placetype": [
          "aat:300008777"
        ],
        "name:en": "Nore Hill",
        "id": 7458074
      }
    },
    {
      "geometry": {
        "type": "Point",
        "coordinates": [
          0.3,
          52.583333
        ]
      },
      "type": "Feature",
      "properties": {
        "hierarchy": [
          "tgn:7458075",
          "tgn:7002445",
          "tgn:1000003",
          "tgn:7008160",
          "tgn:7008591",
          "tgn:7029392"
        ],
        "placetype": [
          "aat:300008347"
        ],
        "name:en": "Nordelph",
        "id": 7458075
      }
    },
    {
      "geometry": {
        "type": "Point",
        "coordinates": [
          -2.583333,
          53.316667
        ]
      },
      "type": "Feature",
      "properties": {
        "hierarchy": [
          "tgn:7458076",
          "tgn:7002445",
          "tgn:7008114",
          "tgn:1000003",
          "tgn:7008591",
          "tgn:7029392"
        ],
        "placetype": [
          "aat:300000206"
        ],
        "name:en": "Norcott Brook",
        "id": 7458076
      }
    },
    {
      "geometry": {
        "type": "Point",
        "coordinates": [
          -1.633333,
          60.3
        ]
      },
      "type": "Feature",
      "properties": {
        "hierarchy": [
          "tgn:7458077",
          "tgn:7002444",
          "tgn:1000003",
          "tgn:7029508",
          "tgn:7008591",
          "tgn:7029392"
        ],
        "placetype": [
          "aat:300386846"
        ],
        "name:en": "Norby, Neap of",
        "id": 7458077
      }
    },
    {
      "geometry": {
        "type": "Point",
        "coordinates": [
          -0.116667,
          51.416667
        ]
      },
      "type": "Feature",
      "properties": {
        "hierarchy": [
          "tgn:7458078",
          "tgn:7002445",
          "tgn:7026536",
          "tgn:1000003",
          "tgn:7008136",
          "tgn:7008591",
          "tgn:7029392"
        ],
        "placetype": [
          "aat:300000745"
        ],
        "name:en": "Norbury",
        "id": 7458078
      }
    }
  ]
}
