{
  "type": "FeatureCollection",
  "features": [
    {
      "geometry": {
        "type": "Point",
        "coordinates": [
          5.031238,
          50.261463
        ]
      },
      "type": "Feature",
      "properties": {
        "hierarchy": [
          "tgn:7242080",
          "tgn:7003466",
          "tgn:1000003",
          "tgn:1000063",
          "tgn:4012014",
          "tgn:7029392"
        ],
        "placetype": [
          "aat:300008347"
        ],
        "id": 7242080,
        "name:xx": "La Grande Agauche"
      }
    },
    {
      "geometry": {
        "type": "Point",
        "coordinates": [
          4.366667,
          50.7
        ]
      },
      "type": "Feature",
      "properties": {
        "hierarchy": [
          "tgn:7242081",
          "tgn:7018238",
          "tgn:1000003",
          "tgn:1000063",
          "tgn:4012014",
          "tgn:7029392"
        ],
        "placetype": [
          "aat:300000206"
        ],
        "id": 7242081,
        "name:xx": "La Graignette"
      }
    },
    {
      "geometry": {
        "type": "Point",
        "coordinates": [
          4.333333,
          50.65
        ]
      },
      "type": "Feature",
      "properties": {
        "hierarchy": [
          "tgn:7242082",
          "tgn:7007877",
          "tgn:1000003",
          "tgn:1000063",
          "tgn:4012014",
          "tgn:7029392"
        ],
        "placetype": [
          "aat:300000206"
        ],
        "id": 7242082,
        "name:xx": "La Goutte"
      }
    },
    {
      "geometry": {
        "type": "Point",
        "coordinates": [
          5.416667,
          50
        ]
      },
      "type": "Feature",
      "properties": {
        "hierarchy": [
          "tgn:7242083",
          "tgn:7003465",
          "tgn:1000003",
          "tgn:1000063",
          "tgn:4012014",
          "tgn:7029392"
        ],
        "placetype": [
          "aat:300008347"
        ],
        "id": 7242083,
        "name:xx": "La Gotte"
      }
    },
    {
      "geometry": {
        "type": "Point",
        "coordinates": [
          5.7,
          50.333333
        ]
      },
      "type": "Feature",
      "properties": {
        "hierarchy": [
          "tgn:7242084",
          "tgn:7003465",
          "tgn:1000003",
          "tgn:1000063",
          "tgn:4012014",
          "tgn:7029392"
        ],
        "placetype": [
          "aat:300008347"
        ],
        "id": 7242084,
        "name:xx": "La Gottale"
      }
    },
    {
      "geometry": {
        "type": "Point",
        "coordinates": [
          5.533333,
          50.05
        ]
      },
      "type": "Feature",
      "properties": {
        "hierarchy": [
          "tgn:7242085",
          "tgn:7003465",
          "tgn:1000003",
          "tgn:1000063",
          "tgn:4012014",
          "tgn:7029392"
        ],
        "placetype": [
          "aat:300008347"
        ],
        "id": 7242085,
        "name:xx": "La Gottale"
      }
    },
    {
      "geometry": {
        "type": "Point",
        "coordinates": [
          5.566667,
          50.5
        ]
      },
      "type": "Feature",
      "properties": {
        "hierarchy": [
          "tgn:7242086",
          "tgn:7003460",
          "tgn:1000003",
          "tgn:1000063",
          "tgn:4012014",
          "tgn:7029392"
        ],
        "placetype": [
          "aat:300008347"
        ],
        "id": 7242086,
        "name:xx": "La Gombe"
      }
    },
    {
      "geometry": {
        "type": "Point",
        "coordinates": [
          4.3,
          50.433333
        ]
      },
      "type": "Feature",
      "properties": {
        "hierarchy": [
          "tgn:7242087",
          "tgn:7007877",
          "tgn:1000003",
          "tgn:1000063",
          "tgn:4012014",
          "tgn:7029392"
        ],
        "placetype": [
          "aat:300008347"
        ],
        "id": 7242087,
        "name:xx": "La Gloriette"
      }
    },
    {
      "geometry": {
        "type": "Point",
        "coordinates": [
          4.15,
          50.65
        ]
      },
      "type": "Feature",
      "properties": {
        "hierarchy": [
          "tgn:7242088",
          "tgn:7007877",
          "tgn:1000003",
          "tgn:1000063",
          "tgn:4012014",
          "tgn:7029392"
        ],
        "placetype": [
          "aat:300000206"
        ],
        "id": 7242088,
        "name:xx": "La Gloriette"
      }
    }
  ]
}
