{
  "type": "FeatureCollection",
  "features": [
    {
      "geometry": {
        "type": "Point",
        "coordinates": [
          -75.1,
          43.5333
        ]
      },
      "type": "Feature",
      "properties": {
        "hierarchy": [
          "tgn:2222290",
          "tgn:1000001",
          "tgn:7012149",
          "tgn:7014287",
          "tgn:7007568",
          "tgn:7029392"
        ],
        "placetype": [
          "aat:300008706"
        ],
        "id": 2222290,
        "name:xx": "Caroline Creek"
      }
    },
    {
      "geometry": {
        "type": "Point",
        "coordinates": [
          -95.6,
          34.3167
        ]
      },
      "type": "Feature",
      "properties": {
        "hierarchy": [
          "tgn:2222291",
          "tgn:1000001",
          "tgn:7012149",
          "tgn:2001686",
          "tgn:7007707",
          "tgn:7029392"
        ],
        "placetype": [
          "aat:300008706"
        ],
        "id": 2222291,
        "name:xx": "Caroline Creek"
      }
    },
    {
      "geometry": {
        "type": "Point",
        "coordinates": [
          -96.1333,
          31.5833
        ]
      },
      "type": "Feature",
      "properties": {
        "hierarchy": [
          "tgn:2222292",
          "tgn:1000001",
          "tgn:7012149",
          "tgn:1002391",
          "tgn:7007826",
          "tgn:7029392"
        ],
        "placetype": [
          "aat:300008706"
        ],
        "id": 2222292,
        "name:xx": "Caroline Creek"
      }
    },
    {
      "geometry": {
        "type": "Point",
        "coordinates": [
          -76.4,
          42.3667
        ]
      },
      "type": "Feature",
      "properties": {
        "hierarchy": [
          "tgn:2222293",
          "tgn:1000001",
          "tgn:7012149",
          "tgn:1002950",
          "tgn:7007568",
          "tgn:7029392"
        ],
        "placetype": [
          "aat:300008347"
        ],
        "id": 2222293,
        "name:xx": "Caroline Depot"
      }
    },
    {
      "geometry": {
        "type": "Point",
        "coordinates": [
          -87.7667,
          36.2
        ]
      },
      "type": "Feature",
      "properties": {
        "hierarchy": [
          "tgn:2222294",
          "tgn:1000001",
          "tgn:7012149",
          "tgn:2001879",
          "tgn:7007825",
          "tgn:7029392"
        ],
        "placetype": [
          "aat:300008761"
        ],
        "id": 2222294,
        "name:xx": "Caroline Hollow"
      }
    },
    {
      "geometry": {
        "type": "Point",
        "coordinates": [
          -82.5833,
          33.2167
        ]
      },
      "type": "Feature",
      "properties": {
        "hierarchy": [
          "tgn:2222295",
          "tgn:1000001",
          "tgn:7012149",
          "tgn:2000353",
          "tgn:7007248",
          "tgn:7029392"
        ],
        "placetype": [
          "aat:300006191"
        ],
        "id": 2222295,
        "name:xx": "Caroline Lake"
      }
    },
    {
      "geometry": {
        "type": "Point",
        "coordinates": [
          -93.4167,
          47.8
        ]
      },
      "type": "Feature",
      "properties": {
        "hierarchy": [
          "tgn:2222296",
          "tgn:1000001",
          "tgn:7012149",
          "tgn:2001029",
          "tgn:7007521",
          "tgn:7029392"
        ],
        "placetype": [
          "aat:300008680"
        ],
        "id": 2222296,
        "name:xx": "Caroline Lake"
      }
    },
    {
      "geometry": {
        "type": "Point",
        "coordinates": [
          -88.6,
          32.5333
        ]
      },
      "type": "Feature",
      "properties": {
        "hierarchy": [
          "tgn:2222297",
          "tgn:1000001",
          "tgn:7012149",
          "tgn:2001123",
          "tgn:7007522",
          "tgn:7029392"
        ],
        "placetype": [
          "aat:300006191"
        ],
        "id": 2222297,
        "name:xx": "Caroline Lake"
      }
    },
    {
      "geometry": {
        "type": "Point",
        "coordinates": [
          -74.85,
          40.1667
        ]
      },
      "type": "Feature",
      "properties": {
        "hierarchy": [
          "tgn:2222298",
          "tgn:1000001",
          "tgn:1002213",
          "tgn:7012149",
          "tgn:7007710",
          "tgn:7029392"
        ],
        "placetype": [
          "aat:300008680"
        ],
        "id": 2222298,
        "name:xx": "Caroline Lake"
      }
    },
    {
      "geometry": {
        "type": "Point",
        "coordinates": [
          -90.55,
          46.2667
        ]
      },
      "type": "Feature",
      "properties": {
        "hierarchy": [
          "tgn:2222299",
          "tgn:1000001",
          "tgn:7012149",
          "tgn:7007922",
          "tgn:7029392"
        ],
        "placetype": [
          "aat:300008680"
        ],
        "id": 2222299,
        "name:xx": "Caroline Lake"
      }
    }
  ]
}
