{
  "geometry": {
    "type": "Point",
    "coordinates": [
      28.8333,
      48.9667
    ]
  },
  "type": "Feature",
  "properties": {
    "hierarchy": [
      "tgn:1057385",
      "tgn:1000003",
      "tgn:7011999",
      "tgn:7006660",
      "tgn:7029392"
    ],
    "placetype": [
      "aat:300008347"
    ],
    "id": 1057385,
    "name:xx": "Nemirov"
  }
}
