{
  "geometry": {
    "type": "Point",
    "coordinates": [
      -81.0833,
      44.95
    ]
  },
  "type": "Feature",
  "properties": {
    "hierarchy": [
      "tgn:1115000",
      "tgn:7005685",
      "tgn:1000001",
      "tgn:7013154",
      "tgn:7029392"
    ],
    "placetype": [
      "aat:300266558"
    ],
    "id": 1115000,
    "name:xx": "Melville Sound"
  }
}
