{
  "geometry": {
    "type": "Point",
    "coordinates": [
      -77.8333,
      41.8667
    ]
  },
  "type": "Feature",
  "properties": {
    "hierarchy": [
      "tgn:2088824",
      "tgn:1000001",
      "tgn:7012149",
      "tgn:1002800",
      "tgn:7007710",
      "tgn:7029392"
    ],
    "placetype": [
      "aat:300008347"
    ],
    "id": 2088824,
    "name:xx": "Gold"
  }
}
