{
  "geometry": {
    "type": "Point",
    "coordinates": [
      -105.8167,
      43.3667
    ]
  },
  "type": "Feature",
  "properties": {
    "hierarchy": [
      "tgn:2340909",
      "tgn:1000001",
      "tgn:2002369",
      "tgn:7012149",
      "tgn:7007923",
      "tgn:7029392"
    ],
    "placetype": [
      "aat:300008761"
    ],
    "id": 2340909,
    "name:xx": "Friday Draw"
  }
}
