{
  "geometry": {
    "type": "Point",
    "coordinates": [
      -98.5667,
      28.55
    ]
  },
  "type": "Feature",
  "properties": {
    "hierarchy": [
      "tgn:2198875",
      "tgn:1000001",
      "tgn:7012149",
      "tgn:2002035",
      "tgn:7007826",
      "tgn:7029392"
    ],
    "placetype": [
      "aat:300008699"
    ],
    "id": 2198875,
    "name:xx": "Bruce Branch"
  }
}
