{
  "geometry": {
    "type": "Point",
    "coordinates": [
      -83.3167,
      35.6833
    ]
  },
  "type": "Feature",
  "properties": {
    "hierarchy": [
      "tgn:2510164",
      "tgn:1000001",
      "tgn:7012149",
      "tgn:2001914",
      "tgn:7007825",
      "tgn:7029392"
    ],
    "placetype": [
      "aat:300008707"
    ],
    "id": 2510164,
    "name:xx": "Middle Prong Little Pigeon River"
  }
}
