{
  "geometry": {
    "type": "Point",
    "coordinates": [
      -115.9333,
      33.25
    ]
  },
  "type": "Feature",
  "properties": {
    "hierarchy": [
      "tgn:2689772",
      "tgn:1000001",
      "tgn:7012149",
      "tgn:2000182",
      "tgn:7007157",
      "tgn:7029392"
    ],
    "placetype": [
      "aat:300008697"
    ],
    "id": 2689772,
    "name:xx": "Squeaky Springs"
  }
}
