{
  "geometry": {
    "type": "Point",
    "coordinates": [
      31.203212,
      30.052201
    ]
  },
  "type": "Feature",
  "properties": {
    "hierarchy": [
      "tgn:7531235",
      "tgn:7001242",
      "tgn:7016833",
      "tgn:1001083",
      "tgn:7029392"
    ],
    "placetype": [
      "aat:300006676"
    ],
    "id": 7531235,
    "name:xx": "Mustashfá Muşţafá Maḩmūd"
  }
}
