{
  "geometry": {
    "type": "Point",
    "coordinates": [
      -74.6167,
      43.0833
    ]
  },
  "type": "Feature",
  "properties": {
    "hierarchy": [
      "tgn:2269926",
      "tgn:1000001",
      "tgn:7012149",
      "tgn:7007568",
      "tgn:7029392"
    ],
    "placetype": [
      "aat:300008706"
    ],
    "id": 2269926,
    "name:xx": "Crum Creek"
  }
}
