{
  "geometry": {
    "type": "Point",
    "coordinates": [
      30.782778,
      30.756389
    ]
  },
  "type": "Feature",
  "properties": {
    "hierarchy": [
      "tgn:7538692",
      "tgn:7001242",
      "tgn:1001075",
      "tgn:7016833",
      "tgn:7029392"
    ],
    "placetype": [
      "aat:300008791"
    ],
    "name:en": "Nitmā wa Kafr Gharīn, Jazīrat",
    "id": 7538692
  }
}
