{
  "geometry": {
    "type": "Point",
    "coordinates": [
      -107.3833,
      40.1833
    ]
  },
  "type": "Feature",
  "properties": {
    "hierarchy": [
      "tgn:2412096",
      "tgn:1000001",
      "tgn:7012149",
      "tgn:7007158",
      "tgn:7029392"
    ],
    "placetype": [
      "aat:300008699"
    ],
    "id": 2412096,
    "name:xx": "Indian Run"
  }
}
