{
  "geometry": {
    "type": "Point",
    "coordinates": [
      -120.7833,
      38.9667
    ]
  },
  "type": "Feature",
  "properties": {
    "hierarchy": [
      "tgn:2418748",
      "tgn:1000001",
      "tgn:7012149",
      "tgn:1002350",
      "tgn:7007157",
      "tgn:7029392"
    ],
    "placetype": [
      "aat:300008798"
    ],
    "id": 2418748,
    "name:xx": "Jakeys Hill"
  }
}
