{
  "type": "FeatureCollection",
  "features": [
    {
      "geometry": {
        "type": "Point",
        "coordinates": [
          -73.5,
          -41.216667
        ]
      },
      "type": "Feature",
      "properties": {
        "hierarchy": [
          "tgn:7283290",
          "tgn:1001699",
          "tgn:1000049",
          "tgn:1000002",
          "tgn:7029392"
        ],
        "placetype": [
          "aat:300008699"
        ],
        "id": 7283290,
        "name:xx": "Parga, Río"
      }
    },
    {
      "geometry": {
        "type": "Point",
        "coordinates": [
          -73.85,
          -41.45
        ]
      },
      "type": "Feature",
      "properties": {
        "hierarchy": [
          "tgn:7283291",
          "tgn:1001699",
          "tgn:1000049",
          "tgn:1000002",
          "tgn:7029392"
        ],
        "placetype": [
          "aat:300132317"
        ],
        "id": 7283291,
        "name:xx": "Parga, Caleta"
      }
    },
    {
      "geometry": {
        "type": "Point",
        "coordinates": [
          -73.5,
          -41.216667
        ]
      },
      "type": "Feature",
      "properties": {
        "hierarchy": [
          "tgn:7283292",
          "tgn:1001699",
          "tgn:1000049",
          "tgn:1000002",
          "tgn:7029392"
        ],
        "placetype": [
          "aat:300008347"
        ],
        "id": 7283292,
        "name:xx": "Parga"
      }
    },
    {
      "geometry": {
        "type": "Point",
        "coordinates": [
          -73.75,
          -45.35
        ]
      },
      "type": "Feature",
      "properties": {
        "hierarchy": [
          "tgn:7283293",
          "tgn:1001623",
          "tgn:1000049",
          "tgn:1000002",
          "tgn:7029392"
        ],
        "placetype": [
          "aat:300008791"
        ],
        "id": 7283293,
        "name:xx": "Parenti, Isla"
      }
    },
    {
      "geometry": {
        "type": "Point",
        "coordinates": [
          -73.55,
          -47.266667
        ]
      },
      "type": "Feature",
      "properties": {
        "hierarchy": [
          "tgn:7283294",
          "tgn:1001623",
          "tgn:1000049",
          "tgn:1000002",
          "tgn:7029392"
        ],
        "placetype": [
          "aat:300008795"
        ],
        "id": 7283294,
        "name:xx": "Pared Sur, Cerro"
      }
    },
    {
      "geometry": {
        "type": "Point",
        "coordinates": [
          -70.283333,
          -34.233333
        ]
      },
      "type": "Feature",
      "properties": {
        "hierarchy": [
          "tgn:7283295",
          "tgn:1001695",
          "tgn:1000049",
          "tgn:1000002",
          "tgn:7029392"
        ],
        "placetype": [
          "aat:300008699"
        ],
        "id": 7283295,
        "name:xx": "Paredones, Río"
      }
    },
    {
      "geometry": {
        "type": "Point",
        "coordinates": [
          -69.5,
          -27.6
        ]
      },
      "type": "Feature",
      "properties": {
        "hierarchy": [
          "tgn:7283296",
          "tgn:1001630",
          "tgn:1000049",
          "tgn:1000002",
          "tgn:7029392"
        ],
        "placetype": [
          "aat:300008699"
        ],
        "id": 7283296,
        "name:xx": "Paredones, Quebrada"
      }
    },
    {
      "geometry": {
        "type": "Point",
        "coordinates": [
          -69.333333,
          -27.516667
        ]
      },
      "type": "Feature",
      "properties": {
        "hierarchy": [
          "tgn:7283297",
          "tgn:1001630",
          "tgn:1000049",
          "tgn:1000002",
          "tgn:7029392"
        ],
        "placetype": [
          "aat:300259572"
        ],
        "id": 7283297,
        "name:xx": "Paredones, Portezuelo"
      }
    },
    {
      "geometry": {
        "type": "Point",
        "coordinates": [
          -72,
          -34.633333
        ]
      },
      "type": "Feature",
      "properties": {
        "hierarchy": [
          "tgn:7283298",
          "tgn:1001695",
          "tgn:1000049",
          "tgn:1000002",
          "tgn:7029392"
        ],
        "placetype": [
          "aat:300008699"
        ],
        "id": 7283298,
        "name:xx": "Paredones, Estero"
      }
    },
    {
      "geometry": {
        "type": "Point",
        "coordinates": [
          -69.333333,
          -27.5
        ]
      },
      "type": "Feature",
      "properties": {
        "hierarchy": [
          "tgn:7283299",
          "tgn:1001630",
          "tgn:1000049",
          "tgn:1000002",
          "tgn:7029392"
        ],
        "placetype": [
          "aat:300008795"
        ],
        "id": 7283299,
        "name:xx": "Paredones, Cerro"
      }
    }
  ]
}
