{
  "geometry": {
    "type": "Point",
    "coordinates": [
      22.4667,
      12.0333
    ]
  },
  "type": "Feature",
  "properties": {
    "hierarchy": [
      "tgn:7000425",
      "tgn:7001242",
      "tgn:7029392"
    ],
    "placetype": [
      "aat:300387091"
    ],
    "id": 7000425,
    "name:xx": "Kadja, Ouadi"
  }
}
