{
  "geometry": {
    "type": "Point",
    "coordinates": [
      -112.15,
      45.5667
    ]
  },
  "type": "Feature",
  "properties": {
    "hierarchy": [
      "tgn:2367605",
      "tgn:1000001",
      "tgn:7012149",
      "tgn:2001288",
      "tgn:7007524",
      "tgn:7029392"
    ],
    "placetype": [
      "aat:300000390"
    ],
    "id": 2367605,
    "name:xx": "Grouse Mine"
  }
}
