{
  "geometry": {
    "type": "Point",
    "coordinates": [
      79.7716,
      27.1907
    ]
  },
  "type": "Feature",
  "properties": {
    "hierarchy": [
      "tgn:7561402",
      "tgn:1000004",
      "tgn:7000198",
      "tgn:7016722",
      "tgn:7029392"
    ],
    "placetype": [
      "aat:300008347"
    ],
    "name:en": "Sadūpur Bāngar",
    "id": 7561402
  }
}
