{
  "geometry": {
    "type": "Point",
    "coordinates": [
      -68.1833,
      10.4833
    ]
  },
  "type": "Feature",
  "properties": {
    "hierarchy": [
      "tgn:1025211",
      "tgn:1001847",
      "tgn:1000002",
      "tgn:1000059",
      "tgn:7029392"
    ],
    "placetype": [
      "aat:300008347"
    ],
    "id": 1025211,
    "name:xx": "Morón"
  }
}
