{
  "geometry": {
    "type": "Point",
    "coordinates": [
      -7.798,
      41.101
    ]
  },
  "type": "Feature",
  "properties": {
    "hierarchy": [
      "tgn:7594313",
      "tgn:1000003",
      "tgn:1000090",
      "tgn:7029392"
    ],
    "placetype": [
      "aat:300387346",
      "aat:300263063"
    ],
    "id": 7594313,
    "name:xx": "Alto Douro Wine Region"
  }
}
