{
  "geometry": {
    "type": "Point",
    "coordinates": [
      29.61525,
      30.716653
    ]
  },
  "type": "Feature",
  "properties": {
    "hierarchy": [
      "tgn:7535948",
      "tgn:7001242",
      "tgn:7016833",
      "tgn:1001418",
      "tgn:7029392"
    ],
    "placetype": [
      "aat:300008777"
    ],
    "name:en": "Imbâyîh, 'Alam",
    "id": 7535948
  }
}
