{
  "geometry": {
    "type": "Point",
    "coordinates": [
      -82.7833,
      37.25
    ]
  },
  "type": "Feature",
  "properties": {
    "hierarchy": [
      "tgn:2601088",
      "tgn:1000001",
      "tgn:7012149",
      "tgn:2000805",
      "tgn:7007255",
      "tgn:7029392"
    ],
    "placetype": [
      "aat:300008699"
    ],
    "id": 2601088,
    "name:xx": "Puncheon Branch"
  }
}
