{
  "type": "FeatureCollection",
  "features": [
    {
      "geometry": {
        "type": "Point",
        "coordinates": [
          -77.3333,
          41.7333
        ]
      },
      "type": "Feature",
      "properties": {
        "hierarchy": [
          "tgn:2398510",
          "tgn:1000001",
          "tgn:7012149",
          "tgn:1002945",
          "tgn:7007710",
          "tgn:7029392"
        ],
        "placetype": [
          "aat:300008699"
        ],
        "id": 2398510,
        "name:xx": "Hoover Brook"
      }
    },
    {
      "geometry": {
        "type": "Point",
        "coordinates": [
          -81.9333,
          37.4
        ]
      },
      "type": "Feature",
      "properties": {
        "hierarchy": [
          "tgn:2398511",
          "tgn:1000001",
          "tgn:2002148",
          "tgn:7012149",
          "tgn:7007919",
          "tgn:7029392"
        ],
        "placetype": [
          "aat:300008699"
        ],
        "id": 2398511,
        "name:xx": "Hoover Camp Branch"
      }
    },
    {
      "geometry": {
        "type": "Point",
        "coordinates": [
          -116.55,
          33.1833
        ]
      },
      "type": "Feature",
      "properties": {
        "hierarchy": [
          "tgn:2398512",
          "tgn:1000001",
          "tgn:7012149",
          "tgn:7007157",
          "tgn:1002858",
          "tgn:7029392"
        ],
        "placetype": [
          "aat:300008761"
        ],
        "id": 2398512,
        "name:xx": "Hoover Canyon"
      }
    },
    {
      "geometry": {
        "type": "Point",
        "coordinates": [
          -120.9,
          46.7667
        ]
      },
      "type": "Feature",
      "properties": {
        "hierarchy": [
          "tgn:2398513",
          "tgn:1000001",
          "tgn:7012149",
          "tgn:1003042",
          "tgn:7007920",
          "tgn:7029392"
        ],
        "placetype": [
          "aat:300008761"
        ],
        "id": 2398513,
        "name:xx": "Hoover Canyon"
      }
    },
    {
      "geometry": {
        "type": "Point",
        "coordinates": [
          -93.95,
          34.65
        ]
      },
      "type": "Feature",
      "properties": {
        "hierarchy": [
          "tgn:2398514",
          "tgn:1000001",
          "tgn:7016172",
          "tgn:7012149",
          "tgn:2000161",
          "tgn:7029392"
        ],
        "placetype": [
          "aat:300008706"
        ],
        "id": 2398514,
        "name:xx": "Hoover Creek"
      }
    },
    {
      "geometry": {
        "type": "Point",
        "coordinates": [
          -121.55,
          37.2
        ]
      },
      "type": "Feature",
      "properties": {
        "hierarchy": [
          "tgn:2398515",
          "tgn:1000001",
          "tgn:7012149",
          "tgn:7007157",
          "tgn:7014475",
          "tgn:7029392"
        ],
        "placetype": [
          "aat:300008706"
        ],
        "id": 2398515,
        "name:xx": "Hoover Creek"
      }
    },
    {
      "geometry": {
        "type": "Point",
        "coordinates": [
          -119.4667,
          37.6
        ]
      },
      "type": "Feature",
      "properties": {
        "hierarchy": [
          "tgn:2398516",
          "tgn:1000001",
          "tgn:7012149",
          "tgn:7007157",
          "tgn:7029392"
        ],
        "placetype": [
          "aat:300008706"
        ],
        "id": 2398516,
        "name:xx": "Hoover Creek"
      }
    },
    {
      "geometry": {
        "type": "Point",
        "coordinates": [
          -123.5667,
          40.25
        ]
      },
      "type": "Feature",
      "properties": {
        "hierarchy": [
          "tgn:2398517",
          "tgn:1000001",
          "tgn:7012149",
          "tgn:2000181",
          "tgn:7007157",
          "tgn:7029392"
        ],
        "placetype": [
          "aat:300008706"
        ],
        "id": 2398517,
        "name:xx": "Hoover Creek"
      }
    },
    {
      "geometry": {
        "type": "Point",
        "coordinates": [
          -81.1833,
          31.9667
        ]
      },
      "type": "Feature",
      "properties": {
        "hierarchy": [
          "tgn:2398518",
          "tgn:1000001",
          "tgn:2000316",
          "tgn:7012149",
          "tgn:7007248",
          "tgn:7029392"
        ],
        "placetype": [
          "aat:300008706"
        ],
        "id": 2398518,
        "name:xx": "Hoover Creek"
      }
    },
    {
      "geometry": {
        "type": "Point",
        "coordinates": [
          -97.9167,
          38.5
        ]
      },
      "type": "Feature",
      "properties": {
        "hierarchy": [
          "tgn:2398519",
          "tgn:1000001",
          "tgn:7012149",
          "tgn:7007254",
          "tgn:7029392"
        ],
        "placetype": [
          "aat:300008706"
        ],
        "id": 2398519,
        "name:xx": "Hoover Creek"
      }
    }
  ]
}
