{
  "geometry": {
    "type": "Point",
    "coordinates": [
      -92.2167,
      29.8667
    ]
  },
  "type": "Feature",
  "properties": {
    "hierarchy": [
      "tgn:2514617",
      "tgn:1000001",
      "tgn:7012149",
      "tgn:2000910",
      "tgn:7007256",
      "tgn:7029392"
    ],
    "placetype": [
      "aat:300006075"
    ],
    "id": 2514617,
    "name:xx": "Miller Island Canal"
  }
}
