{
  "geometry": {
    "type": "Point",
    "coordinates": [
      -104.9833,
      41.4833
    ]
  },
  "type": "Feature",
  "properties": {
    "hierarchy": [
      "tgn:2451672",
      "tgn:1000001",
      "tgn:7012149",
      "tgn:7007923",
      "tgn:7029392"
    ],
    "placetype": [
      "aat:300008706"
    ],
    "id": 2451672,
    "name:xx": "Little Bear Creek"
  }
}
