{
  "type": "FeatureCollection",
  "features": [
    {
      "geometry": {
        "type": "Point",
        "coordinates": [
          -135.3667,
          56.8333
        ]
      },
      "type": "Feature",
      "properties": {
        "hierarchy": [
          "tgn:2265320",
          "tgn:7006450",
          "tgn:1000001",
          "tgn:7012149",
          "tgn:2124002",
          "tgn:7029392"
        ],
        "placetype": [
          "aat:300132316"
        ],
        "id": 2265320,
        "name:xx": "Crane Cove"
      }
    },
    {
      "geometry": {
        "type": "Point",
        "coordinates": [
          -75.8,
          38.05
        ]
      },
      "type": "Feature",
      "properties": {
        "hierarchy": [
          "tgn:2265321",
          "tgn:1000001",
          "tgn:1002902",
          "tgn:7012149",
          "tgn:7007516",
          "tgn:7029392"
        ],
        "placetype": [
          "aat:300132316"
        ],
        "id": 2265321,
        "name:xx": "Crane Cove"
      }
    },
    {
      "geometry": {
        "type": "Point",
        "coordinates": [
          -83.7167,
          42.8333
        ]
      },
      "type": "Feature",
      "properties": {
        "hierarchy": [
          "tgn:2265322",
          "tgn:1000001",
          "tgn:7012149",
          "tgn:1002406",
          "tgn:7007520",
          "tgn:7029392"
        ],
        "placetype": [
          "aat:300132316"
        ],
        "id": 2265322,
        "name:xx": "Crane Cove"
      }
    },
    {
      "geometry": {
        "type": "Point",
        "coordinates": [
          -88.05,
          33.5167
        ]
      },
      "type": "Feature",
      "properties": {
        "hierarchy": [
          "tgn:2265323",
          "tgn:7002659",
          "tgn:1000001",
          "tgn:7012149",
          "tgn:2000037",
          "tgn:7029392"
        ],
        "placetype": [
          "aat:300008706"
        ],
        "id": 2265323,
        "name:xx": "Crane Creek"
      }
    },
    {
      "geometry": {
        "type": "Point",
        "coordinates": [
          -133.9833,
          56.7
        ]
      },
      "type": "Feature",
      "properties": {
        "hierarchy": [
          "tgn:2265324",
          "tgn:7006450",
          "tgn:1000001",
          "tgn:7012149",
          "tgn:2000088",
          "tgn:7029392"
        ],
        "placetype": [
          "aat:300008706"
        ],
        "id": 2265324,
        "name:xx": "Crane Creek"
      }
    },
    {
      "geometry": {
        "type": "Point",
        "coordinates": [
          -147.25,
          65.0833
        ]
      },
      "type": "Feature",
      "properties": {
        "hierarchy": [
          "tgn:2265325",
          "tgn:7006450",
          "tgn:1000001",
          "tgn:7019674",
          "tgn:7012149",
          "tgn:7029392"
        ],
        "placetype": [
          "aat:300008706"
        ],
        "id": 2265325,
        "name:xx": "Crane Creek"
      }
    },
    {
      "geometry": {
        "type": "Point",
        "coordinates": [
          -92.6167,
          36.2833
        ]
      },
      "type": "Feature",
      "properties": {
        "hierarchy": [
          "tgn:2265326",
          "tgn:1000001",
          "tgn:7016172",
          "tgn:7012149",
          "tgn:2000149",
          "tgn:7029392"
        ],
        "placetype": [
          "aat:300008706"
        ],
        "id": 2265326,
        "name:xx": "Crane Creek"
      }
    },
    {
      "geometry": {
        "type": "Point",
        "coordinates": [
          -92.0667,
          33.6667
        ]
      },
      "type": "Feature",
      "properties": {
        "hierarchy": [
          "tgn:2265327",
          "tgn:1000001",
          "tgn:7016172",
          "tgn:2000110",
          "tgn:7012149",
          "tgn:7029392"
        ],
        "placetype": [
          "aat:300008706"
        ],
        "id": 2265327,
        "name:xx": "Crane Creek"
      }
    },
    {
      "geometry": {
        "type": "Point",
        "coordinates": [
          -92.8667,
          35.0167
        ]
      },
      "type": "Feature",
      "properties": {
        "hierarchy": [
          "tgn:2265328",
          "tgn:1000001",
          "tgn:7016172",
          "tgn:7012149",
          "tgn:2000157",
          "tgn:7029392"
        ],
        "placetype": [
          "aat:300008706"
        ],
        "id": 2265328,
        "name:xx": "Crane Creek"
      }
    },
    {
      "geometry": {
        "type": "Point",
        "coordinates": [
          -119.9333,
          37.9833
        ]
      },
      "type": "Feature",
      "properties": {
        "hierarchy": [
          "tgn:2265329",
          "tgn:1000001",
          "tgn:7012149",
          "tgn:7007157",
          "tgn:1002957",
          "tgn:7029392"
        ],
        "placetype": [
          "aat:300008706"
        ],
        "id": 2265329,
        "name:xx": "Crane Creek"
      }
    }
  ]
}
