{
  "geometry": {
    "type": "Point",
    "coordinates": [
      -94.7833,
      34.85
    ]
  },
  "type": "Feature",
  "properties": {
    "hierarchy": [
      "tgn:2765463",
      "tgn:1000001",
      "tgn:7012149",
      "tgn:2001662",
      "tgn:7007707",
      "tgn:7029392"
    ],
    "placetype": [
      "aat:300008699"
    ],
    "id": 2765463,
    "name:xx": "White Branch"
  }
}
