{
  "geometry": {
    "type": "Point",
    "coordinates": [
      -93.1833,
      30.2833
    ]
  },
  "type": "Feature",
  "properties": {
    "hierarchy": [
      "tgn:2173912",
      "tgn:1000001",
      "tgn:2000863",
      "tgn:7012149",
      "tgn:7007256",
      "tgn:7029392"
    ],
    "placetype": [
      "aat:300132316"
    ],
    "id": 2173912,
    "name:xx": "Bird Island Bay"
  }
}
