{
  "geometry": {
    "type": "Point",
    "coordinates": [
      6.65,
      53.05
    ]
  },
  "type": "Feature",
  "properties": {
    "hierarchy": [
      "tgn:7269336",
      "tgn:7003614",
      "tgn:1000003",
      "tgn:7016845",
      "tgn:7029392"
    ],
    "placetype": [
      "aat:300008347"
    ],
    "name:nl": "Oudemolen",
    "id": 7269336
  }
}
