{
  "geometry": {
    "type": "Point",
    "coordinates": [
      -78.05,
      36.4667
    ]
  },
  "type": "Feature",
  "properties": {
    "hierarchy": [
      "tgn:2427294",
      "tgn:1000001",
      "tgn:7012149",
      "tgn:2001549",
      "tgn:7007709",
      "tgn:7029392"
    ],
    "placetype": [
      "aat:300008706"
    ],
    "id": 2427294,
    "name:xx": "Jordan Creek"
  }
}
