{
  "geometry": {
    "type": "Point",
    "coordinates": [
      -97.2167,
      53.2167
    ]
  },
  "type": "Feature",
  "properties": {
    "hierarchy": [
      "tgn:1127590",
      "tgn:7005685",
      "tgn:1000001",
      "tgn:7005734",
      "tgn:7029392"
    ],
    "placetype": [
      "aat:300008707"
    ],
    "id": 1127590,
    "name:xx": "Nanowin"
  }
}
