{
  "geometry": {
    "type": "Point",
    "coordinates": [
      -159.9667,
      68.7167
    ]
  },
  "type": "Feature",
  "properties": {
    "hierarchy": [
      "tgn:2581343",
      "tgn:7006450",
      "tgn:1000001",
      "tgn:7012149",
      "tgn:2124005",
      "tgn:7029392"
    ],
    "placetype": [
      "aat:300008699"
    ],
    "id": 2581343,
    "name:xx": "Pilly Fork"
  }
}
