{
  "geometry": {
    "type": "Point",
    "coordinates": [
      -80.0333,
      40.25
    ]
  },
  "type": "Feature",
  "properties": {
    "hierarchy": [
      "tgn:2422555",
      "tgn:1000001",
      "tgn:7012149",
      "tgn:1002995",
      "tgn:7007710",
      "tgn:7029392"
    ],
    "placetype": [
      "aat:300006191"
    ],
    "id": 2422555,
    "name:xx": "Jo-ann, Lake"
  }
}
