{
  "geometry": {
    "type": "Point",
    "coordinates": [
      -73.25,
      43.35
    ]
  },
  "type": "Feature",
  "properties": {
    "hierarchy": [
      "tgn:2110182",
      "tgn:1000001",
      "tgn:1002840",
      "tgn:7012149",
      "tgn:7007828",
      "tgn:7029392"
    ],
    "placetype": [
      "aat:300008347"
    ],
    "id": 2110182,
    "name:xx": "West Pawlet"
  }
}
