{
  "type": "FeatureCollection",
  "features": [
    {
      "geometry": {
        "type": "Point",
        "coordinates": [
          -110.85,
          30.033333
        ]
      },
      "type": "Feature",
      "properties": {
        "hierarchy": [
          "tgn:7397580",
          "tgn:1000001",
          "tgn:1001960",
          "tgn:7005560",
          "tgn:7029392"
        ],
        "placetype": [
          "aat:300008347"
        ],
        "id": 7397580,
        "name:xx": "Santa Gertrudis"
      }
    },
    {
      "geometry": {
        "type": "Point",
        "coordinates": [
          -110.733333,
          29.233333
        ]
      },
      "type": "Feature",
      "properties": {
        "hierarchy": [
          "tgn:7397581",
          "tgn:1000001",
          "tgn:1001960",
          "tgn:7005560",
          "tgn:7029392"
        ],
        "placetype": [
          "aat:300008347"
        ],
        "id": 7397581,
        "name:xx": "Santa Gertrudis"
      }
    },
    {
      "geometry": {
        "type": "Point",
        "coordinates": [
          -107.25,
          29.166667
        ]
      },
      "type": "Feature",
      "properties": {
        "hierarchy": [
          "tgn:7397582",
          "tgn:7005581",
          "tgn:1000001",
          "tgn:7005560",
          "tgn:7029392"
        ],
        "placetype": [
          "aat:300008347"
        ],
        "id": 7397582,
        "name:xx": "Santa Gertrudis"
      }
    },
    {
      "geometry": {
        "type": "Point",
        "coordinates": [
          -100.633333,
          28.466667
        ]
      },
      "type": "Feature",
      "properties": {
        "hierarchy": [
          "tgn:7397583",
          "tgn:1001853",
          "tgn:1000001",
          "tgn:7005560",
          "tgn:7029392"
        ],
        "placetype": [
          "aat:300008347"
        ],
        "id": 7397583,
        "name:xx": "Santa Gertrudis"
      }
    },
    {
      "geometry": {
        "type": "Point",
        "coordinates": [
          -113.066667,
          28.083333
        ]
      },
      "type": "Feature",
      "properties": {
        "hierarchy": [
          "tgn:7397584",
          "tgn:1001835",
          "tgn:1000001",
          "tgn:7005560",
          "tgn:7029392"
        ],
        "placetype": [
          "aat:300008347"
        ],
        "id": 7397584,
        "name:xx": "Santa Gertrudis"
      }
    },
    {
      "geometry": {
        "type": "Point",
        "coordinates": [
          -105.716667,
          27.783333
        ]
      },
      "type": "Feature",
      "properties": {
        "hierarchy": [
          "tgn:7397585",
          "tgn:7005581",
          "tgn:1000001",
          "tgn:7005560",
          "tgn:7029392"
        ],
        "placetype": [
          "aat:300008347"
        ],
        "id": 7397585,
        "name:xx": "Santa Gertrudis"
      }
    },
    {
      "geometry": {
        "type": "Point",
        "coordinates": [
          -101.466667,
          27.816667
        ]
      },
      "type": "Feature",
      "properties": {
        "hierarchy": [
          "tgn:7397586",
          "tgn:1001853",
          "tgn:1000001",
          "tgn:7005560",
          "tgn:7029392"
        ],
        "placetype": [
          "aat:300008347"
        ],
        "id": 7397586,
        "name:xx": "Santa Gertrudis"
      }
    },
    {
      "geometry": {
        "type": "Point",
        "coordinates": [
          -101.533333,
          27.166667
        ]
      },
      "type": "Feature",
      "properties": {
        "hierarchy": [
          "tgn:7397588",
          "tgn:1001853",
          "tgn:1000001",
          "tgn:7005560",
          "tgn:7029392"
        ],
        "placetype": [
          "aat:300008347"
        ],
        "id": 7397588,
        "name:xx": "Santa Gertrudis"
      }
    },
    {
      "geometry": {
        "type": "Point",
        "coordinates": [
          -98,
          17.85
        ]
      },
      "type": "Feature",
      "properties": {
        "hierarchy": [
          "tgn:7397589",
          "tgn:1000001",
          "tgn:7005591",
          "tgn:7005560",
          "tgn:7029392"
        ],
        "placetype": [
          "aat:300008347"
        ],
        "id": 7397589,
        "name:xx": "San Simón Zahuatlán"
      }
    }
  ]
}
