{
  "geometry": {
    "type": "Point",
    "coordinates": [
      -92.2833,
      35.2333
    ]
  },
  "type": "Feature",
  "properties": {
    "hierarchy": [
      "tgn:2008840",
      "tgn:1000001",
      "tgn:7016172",
      "tgn:7012149",
      "tgn:2000127",
      "tgn:7029392"
    ],
    "placetype": [
      "aat:300008347",
      "aat:300387210"
    ],
    "id": 2008840,
    "name:xx": "McGintytown"
  }
}
