{
  "type": "FeatureCollection",
  "features": [
    {
      "geometry": {
        "type": "Point",
        "coordinates": [
          -91.116667,
          18.416667
        ]
      },
      "type": "Feature",
      "properties": {
        "hierarchy": [
          "tgn:7383800",
          "tgn:7005578",
          "tgn:1000001",
          "tgn:7005560",
          "tgn:7029392"
        ],
        "placetype": [
          "aat:300008347"
        ],
        "id": 7383800,
        "name:xx": "Paraíso"
      }
    },
    {
      "geometry": {
        "type": "Point",
        "coordinates": [
          -100.85,
          18.183333
        ]
      },
      "type": "Feature",
      "properties": {
        "hierarchy": [
          "tgn:7383802",
          "tgn:7005585",
          "tgn:1000001",
          "tgn:7005560",
          "tgn:7029392"
        ],
        "placetype": [
          "aat:300008347"
        ],
        "id": 7383802,
        "name:xx": "Paraíso"
      }
    },
    {
      "geometry": {
        "type": "Point",
        "coordinates": [
          -92.583333,
          17.75
        ]
      },
      "type": "Feature",
      "properties": {
        "hierarchy": [
          "tgn:7383803",
          "tgn:1000001",
          "tgn:7005596",
          "tgn:7005560",
          "tgn:7029392"
        ],
        "placetype": [
          "aat:300008347"
        ],
        "id": 7383803,
        "name:xx": "Paraíso"
      }
    },
    {
      "geometry": {
        "type": "Point",
        "coordinates": [
          -91.983333,
          16.85
        ]
      },
      "type": "Feature",
      "properties": {
        "hierarchy": [
          "tgn:7383804",
          "tgn:7005580",
          "tgn:1000001",
          "tgn:7005560",
          "tgn:7029392"
        ],
        "placetype": [
          "aat:300008347"
        ],
        "id": 7383804,
        "name:xx": "Paraíso"
      }
    },
    {
      "geometry": {
        "type": "Point",
        "coordinates": [
          -92.316667,
          15.666667
        ]
      },
      "type": "Feature",
      "properties": {
        "hierarchy": [
          "tgn:7383805",
          "tgn:7005580",
          "tgn:1000001",
          "tgn:7005560",
          "tgn:7029392"
        ],
        "placetype": [
          "aat:300008347"
        ],
        "id": 7383805,
        "name:xx": "Paraíso"
      }
    },
    {
      "geometry": {
        "type": "Point",
        "coordinates": [
          -88.483333,
          19.016667
        ]
      },
      "type": "Feature",
      "properties": {
        "hierarchy": [
          "tgn:7383806",
          "tgn:1000001",
          "tgn:1001937",
          "tgn:7005560",
          "tgn:7029392"
        ],
        "placetype": [
          "aat:300387007"
        ],
        "id": 7383806,
        "name:xx": "Paraíso"
      }
    },
    {
      "geometry": {
        "type": "Point",
        "coordinates": [
          -106.033333,
          28.183333
        ]
      },
      "type": "Feature",
      "properties": {
        "hierarchy": [
          "tgn:7383807",
          "tgn:7005581",
          "tgn:1000001",
          "tgn:7005560",
          "tgn:7029392"
        ],
        "placetype": [
          "aat:300008347"
        ],
        "id": 7383807,
        "name:xx": "Paraisito"
      }
    },
    {
      "geometry": {
        "type": "Point",
        "coordinates": [
          -100.1,
          27.383333
        ]
      },
      "type": "Feature",
      "properties": {
        "hierarchy": [
          "tgn:7383808",
          "tgn:1000001",
          "tgn:7005589",
          "tgn:7005560",
          "tgn:7029392"
        ],
        "placetype": [
          "aat:300006191"
        ],
        "id": 7383808,
        "name:xx": "Represa el Paragüe"
      }
    },
    {
      "geometry": {
        "type": "Point",
        "coordinates": [
          -108.466667,
          28.3
        ]
      },
      "type": "Feature",
      "properties": {
        "hierarchy": [
          "tgn:7383809",
          "tgn:7005581",
          "tgn:1000001",
          "tgn:7005560",
          "tgn:7029392"
        ],
        "placetype": [
          "aat:300008347"
        ],
        "id": 7383809,
        "name:xx": "Paragatos"
      }
    }
  ]
}
