{
  "type": "FeatureCollection",
  "features": [
    {
      "geometry": {
        "type": "Point",
        "coordinates": [
          16.416667,
          38.716667
        ]
      },
      "type": "Feature",
      "properties": {
        "hierarchy": [
          "tgn:7043481",
          "tgn:1003447",
          "tgn:7007850",
          "tgn:1000003",
          "tgn:1000080",
          "tgn:7029392"
        ],
        "placetype": [
          "aat:300008347"
        ],
        "id": 7043481,
        "name:xx": "Centrache"
      }
    },
    {
      "geometry": {
        "type": "Point",
        "coordinates": [
          9.716667,
          44.916667
        ]
      },
      "type": "Feature",
      "properties": {
        "hierarchy": [
          "tgn:7043482",
          "tgn:7003132",
          "tgn:1000003",
          "tgn:7008516",
          "tgn:1000080",
          "tgn:7029392"
        ],
        "placetype": [
          "aat:300008347"
        ],
        "id": 7043482,
        "name:xx": "Centovera"
      }
    },
    {
      "geometry": {
        "type": "Point",
        "coordinates": [
          11.933333,
          43.2
        ]
      },
      "type": "Feature",
      "properties": {
        "hierarchy": [
          "tgn:7043484",
          "tgn:7003162",
          "tgn:1000003",
          "tgn:7009760",
          "tgn:1000080",
          "tgn:7029392"
        ],
        "placetype": [
          "aat:300008347",
          "aat:300008372"
        ],
        "id": 7043484,
        "name:xx": "Centoia"
      }
    },
    {
      "geometry": {
        "type": "Point",
        "coordinates": [
          13.383333,
          43.433333
        ]
      },
      "type": "Feature",
      "properties": {
        "hierarchy": [
          "tgn:7043485",
          "tgn:1003429",
          "tgn:1000003",
          "tgn:7003240",
          "tgn:1000080",
          "tgn:7029392"
        ],
        "placetype": [
          "aat:300008347"
        ],
        "id": 7043485,
        "name:xx": "Centofinestre"
      }
    },
    {
      "geometry": {
        "type": "Point",
        "coordinates": [
          9.616667,
          44.416667
        ]
      },
      "type": "Feature",
      "properties": {
        "hierarchy": [
          "tgn:7043486",
          "tgn:7003131",
          "tgn:1000003",
          "tgn:7008516",
          "tgn:1000080",
          "tgn:7029392"
        ],
        "placetype": [
          "aat:300259572"
        ],
        "id": 7043486,
        "name:xx": "Cento Croci, Passo di"
      }
    }
  ]
}
