{
  "geometry": {
    "type": "Point",
    "coordinates": [
      -95.3333,
      44.6833
    ]
  },
  "type": "Feature",
  "properties": {
    "hierarchy": [
      "tgn:2415835",
      "tgn:1000001",
      "tgn:7012149",
      "tgn:2001062",
      "tgn:7007521",
      "tgn:7029392"
    ],
    "placetype": [
      "aat:300008680"
    ],
    "id": 2415835,
    "name:xx": "Iverson Lake"
  }
}
