{
  "type": "FeatureCollection",
  "features": [
    {
      "geometry": {
        "type": "Point",
        "coordinates": [
          -107.3833,
          38.8
        ]
      },
      "type": "Feature",
      "properties": {
        "hierarchy": [
          "tgn:2397930",
          "tgn:1000001",
          "tgn:7012149",
          "tgn:2000217",
          "tgn:7007158",
          "tgn:7029392"
        ],
        "placetype": [
          "aat:300008706"
        ],
        "id": 2397930,
        "name:xx": "Hoodoo Creek"
      }
    },
    {
      "geometry": {
        "type": "Point",
        "coordinates": [
          -114.6333,
          46.3167
        ]
      },
      "type": "Feature",
      "properties": {
        "hierarchy": [
          "tgn:2397931",
          "tgn:1000001",
          "tgn:7012149",
          "tgn:2000476",
          "tgn:7007250",
          "tgn:7029392"
        ],
        "placetype": [
          "aat:300008706"
        ],
        "id": 2397931,
        "name:xx": "Hoodoo Creek"
      }
    },
    {
      "geometry": {
        "type": "Point",
        "coordinates": [
          -114.5333,
          45.05
        ]
      },
      "type": "Feature",
      "properties": {
        "hierarchy": [
          "tgn:2397932",
          "tgn:1000001",
          "tgn:7012149",
          "tgn:2000481",
          "tgn:7007250",
          "tgn:7029392"
        ],
        "placetype": [
          "aat:300008706"
        ],
        "id": 2397932,
        "name:xx": "Hoodoo Creek"
      }
    },
    {
      "geometry": {
        "type": "Point",
        "coordinates": [
          -115.7167,
          43.8167
        ]
      },
      "type": "Feature",
      "properties": {
        "hierarchy": [
          "tgn:2397933",
          "tgn:1000001",
          "tgn:2000459",
          "tgn:7012149",
          "tgn:7007250",
          "tgn:7029392"
        ],
        "placetype": [
          "aat:300008706"
        ],
        "id": 2397933,
        "name:xx": "Hoodoo Creek"
      }
    },
    {
      "geometry": {
        "type": "Point",
        "coordinates": [
          -116.4833,
          47.75
        ]
      },
      "type": "Feature",
      "properties": {
        "hierarchy": [
          "tgn:2397934",
          "tgn:1000001",
          "tgn:7012149",
          "tgn:2000479",
          "tgn:7007250",
          "tgn:7029392"
        ],
        "placetype": [
          "aat:300008706"
        ],
        "id": 2397934,
        "name:xx": "Hoodoo Creek"
      }
    },
    {
      "geometry": {
        "type": "Point",
        "coordinates": [
          -116.7167,
          48.0167
        ]
      },
      "type": "Feature",
      "properties": {
        "hierarchy": [
          "tgn:2397935",
          "tgn:1000001",
          "tgn:2000460",
          "tgn:7012149",
          "tgn:7007250",
          "tgn:7029392"
        ],
        "placetype": [
          "aat:300008706"
        ],
        "id": 2397935,
        "name:xx": "Hoodoo Creek"
      }
    },
    {
      "geometry": {
        "type": "Point",
        "coordinates": [
          -92.7,
          47.9667
        ]
      },
      "type": "Feature",
      "properties": {
        "hierarchy": [
          "tgn:2397936",
          "tgn:1000001",
          "tgn:7012149",
          "tgn:2001067",
          "tgn:7007521",
          "tgn:7029392"
        ],
        "placetype": [
          "aat:300008706"
        ],
        "id": 2397936,
        "name:xx": "Hoodoo Creek"
      }
    },
    {
      "geometry": {
        "type": "Point",
        "coordinates": [
          -112.1833,
          46.35
        ]
      },
      "type": "Feature",
      "properties": {
        "hierarchy": [
          "tgn:2397937",
          "tgn:1000001",
          "tgn:7012149",
          "tgn:2001281",
          "tgn:7007524",
          "tgn:7029392"
        ],
        "placetype": [
          "aat:300008706"
        ],
        "id": 2397937,
        "name:xx": "Hoodoo Creek"
      }
    },
    {
      "geometry": {
        "type": "Point",
        "coordinates": [
          -115.4833,
          48.15
        ]
      },
      "type": "Feature",
      "properties": {
        "hierarchy": [
          "tgn:2397938",
          "tgn:1000001",
          "tgn:7012149",
          "tgn:2001286",
          "tgn:7007524",
          "tgn:7029392"
        ],
        "placetype": [
          "aat:300008706"
        ],
        "id": 2397938,
        "name:xx": "Hoodoo Creek"
      }
    },
    {
      "geometry": {
        "type": "Point",
        "coordinates": [
          -108.2,
          45.3
        ]
      },
      "type": "Feature",
      "properties": {
        "hierarchy": [
          "tgn:2397939",
          "tgn:1000001",
          "tgn:7012149",
          "tgn:7007524",
          "tgn:7029392"
        ],
        "placetype": [
          "aat:300008706"
        ],
        "id": 2397939,
        "name:xx": "Hoodoo Creek"
      }
    }
  ]
}
