{
  "geometry": {
    "type": "Point",
    "coordinates": [
      -115.5333,
      40.8167
    ]
  },
  "type": "Feature",
  "properties": {
    "hierarchy": [
      "tgn:2642726",
      "tgn:1000001",
      "tgn:2001411",
      "tgn:7012149",
      "tgn:7007526",
      "tgn:7029392"
    ],
    "placetype": [
      "aat:300008697"
    ],
    "id": 2642726,
    "name:xx": "Sandhill Spring"
  }
}
