{
  "type": "FeatureCollection",
  "features": [
    {
      "geometry": {
        "type": "Point",
        "coordinates": [
          119.6333,
          -4.05
        ]
      },
      "type": "Feature",
      "properties": {
        "hierarchy": [
          "tgn:1078560",
          "tgn:1000004",
          "tgn:1001547",
          "tgn:1000116",
          "tgn:7029392"
        ],
        "placetype": [
          "aat:300008347"
        ],
        "id": 1078560,
        "name:xx": "Sidenreng"
      }
    },
    {
      "geometry": {
        "type": "Point",
        "coordinates": [
          98.4167,
          2.7167
        ]
      },
      "type": "Feature",
      "properties": {
        "hierarchy": [
          "tgn:1078561",
          "tgn:1000004",
          "tgn:1001555",
          "tgn:1000116",
          "tgn:7029392"
        ],
        "placetype": [
          "aat:300008347"
        ],
        "id": 1078561,
        "name:xx": "Sidikalang"
      }
    },
    {
      "geometry": {
        "type": "Point",
        "coordinates": [
          120.2,
          0.3167
        ]
      },
      "type": "Feature",
      "properties": {
        "hierarchy": [
          "tgn:1078562",
          "tgn:1000004",
          "tgn:1001548",
          "tgn:1000116",
          "tgn:7029392"
        ],
        "placetype": [
          "aat:300008347"
        ],
        "id": 1078562,
        "name:xx": "Sidoan"
      }
    },
    {
      "geometry": {
        "type": "Point",
        "coordinates": [
          112.7,
          -7.45
        ]
      },
      "type": "Feature",
      "properties": {
        "hierarchy": [
          "tgn:1078563",
          "tgn:1000004",
          "tgn:1001323",
          "tgn:1000116",
          "tgn:7029392"
        ],
        "placetype": [
          "aat:300008347"
        ],
        "id": 1078563,
        "name:xx": "Sidoarjo"
      }
    },
    {
      "geometry": {
        "type": "Point",
        "coordinates": [
          97.35,
          1.5
        ]
      },
      "type": "Feature",
      "properties": {
        "hierarchy": [
          "tgn:1078564",
          "tgn:1000004",
          "tgn:1001555",
          "tgn:1008339",
          "tgn:1000116",
          "tgn:7029392"
        ],
        "placetype": [
          "aat:300008347"
        ],
        "id": 1078564,
        "name:xx": "Sifahandra"
      }
    },
    {
      "geometry": {
        "type": "Point",
        "coordinates": [
          98.8167,
          -1.0333
        ]
      },
      "type": "Feature",
      "properties": {
        "hierarchy": [
          "tgn:1078565",
          "tgn:1000004",
          "tgn:1009150",
          "tgn:1001553",
          "tgn:1000116",
          "tgn:7029392"
        ],
        "placetype": [
          "aat:300008347"
        ],
        "id": 1078565,
        "name:xx": "Sigep"
      }
    },
    {
      "geometry": {
        "type": "Point",
        "coordinates": [
          95.9333,
          5.35
        ]
      },
      "type": "Feature",
      "properties": {
        "hierarchy": [
          "tgn:1078566",
          "tgn:7016479",
          "tgn:1000004",
          "tgn:1000116",
          "tgn:7029392"
        ],
        "placetype": [
          "aat:300008347"
        ],
        "id": 1078566,
        "name:xx": "Sigli"
      }
    },
    {
      "geometry": {
        "type": "Point",
        "coordinates": [
          99.45,
          1.1
        ]
      },
      "type": "Feature",
      "properties": {
        "hierarchy": [
          "tgn:1078567",
          "tgn:1000004",
          "tgn:1001555",
          "tgn:1000116",
          "tgn:7029392"
        ],
        "placetype": [
          "aat:300008347"
        ],
        "id": 1078567,
        "name:xx": "Sihepeng"
      }
    },
    {
      "geometry": {
        "type": "Point",
        "coordinates": [
          101,
          -0.7
        ]
      },
      "type": "Feature",
      "properties": {
        "hierarchy": [
          "tgn:1078568",
          "tgn:1000004",
          "tgn:1001553",
          "tgn:1000116",
          "tgn:7029392"
        ],
        "placetype": [
          "aat:300008347"
        ],
        "id": 1078568,
        "name:xx": "Sijunjung"
      }
    },
    {
      "geometry": {
        "type": "Point",
        "coordinates": [
          122.2,
          -8.75
        ]
      },
      "type": "Feature",
      "properties": {
        "hierarchy": [
          "tgn:1078569",
          "tgn:7003974",
          "tgn:1000004",
          "tgn:1001467",
          "tgn:1000116",
          "tgn:7029392"
        ],
        "placetype": [
          "aat:300008347"
        ],
        "id": 1078569,
        "name:xx": "Sika"
      }
    }
  ]
}
