{
  "geometry": {
    "type": "Point",
    "coordinates": [
      -91.2333,
      36.2833
    ]
  },
  "type": "Feature",
  "properties": {
    "hierarchy": [
      "tgn:2554675",
      "tgn:1000001",
      "tgn:7016172",
      "tgn:7012149",
      "tgn:2000165",
      "tgn:7029392"
    ],
    "placetype": [
      "aat:300008798"
    ],
    "id": 2554675,
    "name:xx": "Oaks Hill"
  }
}
