{
  "geometry": {
    "type": "Point",
    "coordinates": [
      -113.7333,
      32.1833
    ]
  },
  "type": "Feature",
  "properties": {
    "hierarchy": [
      "tgn:2734599",
      "tgn:1000001",
      "tgn:7006451",
      "tgn:7012149",
      "tgn:2000104",
      "tgn:7029392"
    ],
    "placetype": [
      "aat:300006191"
    ],
    "id": 2734599,
    "name:xx": "Tuseral Tank"
  }
}
