{
  "geometry": {
    "type": "Point",
    "coordinates": [
      -80.9333,
      37.45
    ]
  },
  "type": "Feature",
  "properties": {
    "hierarchy": [
      "tgn:2370785",
      "tgn:1000001",
      "tgn:7012149",
      "tgn:2002278",
      "tgn:7013961",
      "tgn:7029392"
    ],
    "placetype": [
      "aat:300266640"
    ],
    "id": 2370785,
    "name:xx": "Hackett Ridge"
  }
}
