{
  "geometry": {
    "type": "Point",
    "coordinates": [
      32.933,
      34.766
    ]
  },
  "type": "Feature",
  "properties": {
    "hierarchy": [
      "tgn:7000838",
      "tgn:1000004",
      "tgn:1000112",
      "tgn:7029392"
    ],
    "placetype": [
      "aat:300387064",
      "aat:300387081"
    ],
    "id": 7000838,
    "name:xx": "Lemesós"
  }
}
