{
  "geometry": {
    "type": "Point",
    "coordinates": [
      -113.9167,
      43.6833
    ]
  },
  "type": "Feature",
  "properties": {
    "hierarchy": [
      "tgn:2691369",
      "tgn:1000001",
      "tgn:2000470",
      "tgn:7012149",
      "tgn:7007250",
      "tgn:7029392"
    ],
    "placetype": [
      "aat:300000390"
    ],
    "id": 2691369,
    "name:xx": "Star Hope Mine"
  }
}
