{
  "geometry": {
    "type": "Point",
    "coordinates": [
      -90.5167,
      37.8833
    ]
  },
  "type": "Feature",
  "properties": {
    "hierarchy": [
      "tgn:2291729",
      "tgn:1000001",
      "tgn:7012149",
      "tgn:2001241",
      "tgn:7007523",
      "tgn:7029392"
    ],
    "placetype": [
      "aat:300000390"
    ],
    "id": 2291729,
    "name:xx": "Dolomite Mines"
  }
}
