{
  "geometry": {
    "type": "Point",
    "coordinates": [
      -122.1167,
      45.5667
    ]
  },
  "type": "Feature",
  "properties": {
    "hierarchy": [
      "tgn:2323666",
      "tgn:1000001",
      "tgn:7012149",
      "tgn:1002699",
      "tgn:7007708",
      "tgn:7029392"
    ],
    "placetype": [
      "aat:300132348"
    ],
    "id": 2323666,
    "name:xx": "Fashion Reef"
  }
}
