{
  "geometry": {
    "type": "Point",
    "coordinates": [
      -70.85,
      42.95
    ]
  },
  "type": "Feature",
  "properties": {
    "hierarchy": [
      "tgn:2220987",
      "tgn:1000001",
      "tgn:7014352",
      "tgn:7012149",
      "tgn:7007564",
      "tgn:7029392"
    ],
    "placetype": [
      "aat:300008680"
    ],
    "id": 2220987,
    "name:xx": "Car Barn Pond"
  }
}
