{
  "type": "FeatureCollection",
  "features": [
    {
      "geometry": {
        "type": "Point",
        "coordinates": [
          11.825,
          55.874
        ]
      },
      "type": "Feature",
      "properties": {
        "hierarchy": [
          "tgn:1113180",
          "tgn:1000003",
          "tgn:1000066",
          "tgn:7029392"
        ],
        "placetype": [
          "aat:300132316"
        ],
        "id": 1113180,
        "name:xx": "Isefjord"
      }
    },
    {
      "geometry": {
        "type": "Point",
        "coordinates": [
          141,
          43.4167
        ]
      },
      "type": "Feature",
      "properties": {
        "hierarchy": [
          "tgn:1113181",
          "tgn:1000985",
          "tgn:7016531",
          "tgn:1000004",
          "tgn:1000120",
          "tgn:7029392"
        ],
        "placetype": [
          "aat:300132316"
        ],
        "id": 1113181,
        "name:xx": "Ishikari-wan"
      }
    },
    {
      "geometry": {
        "type": "Point",
        "coordinates": [
          118.1667,
          9.1
        ]
      },
      "type": "Feature",
      "properties": {
        "hierarchy": [
          "tgn:1113183",
          "tgn:1000004",
          "tgn:1001481",
          "tgn:1000135",
          "tgn:7029392"
        ],
        "placetype": [
          "aat:300132316"
        ],
        "id": 1113183,
        "name:xx": "Island Bay"
      }
    },
    {
      "geometry": {
        "type": "Point",
        "coordinates": [
          -58.25,
          49.1667
        ]
      },
      "type": "Feature",
      "properties": {
        "hierarchy": [
          "tgn:1113184",
          "tgn:7005685",
          "tgn:7005807",
          "tgn:1000001",
          "tgn:7005801",
          "tgn:7029392"
        ],
        "placetype": [
          "aat:300132316"
        ],
        "id": 1113184,
        "name:xx": "Islands, Bay of"
      }
    },
    {
      "geometry": {
        "type": "Point",
        "coordinates": [
          168.7,
          -43.966667
        ]
      },
      "type": "Feature",
      "properties": {
        "hierarchy": [
          "tgn:1113188",
          "tgn:1009227",
          "tgn:1000226",
          "tgn:1000006",
          "tgn:7016850",
          "tgn:7029392"
        ],
        "placetype": [
          "aat:300132316"
        ],
        "name:en": "Jackson Bay",
        "id": 1113188
      }
    }
  ]
}
