{
  "geometry": {
    "type": "Point",
    "coordinates": [
      -48.9167,
      -18.3167
    ]
  },
  "type": "Feature",
  "properties": {
    "hierarchy": [
      "tgn:1123077",
      "tgn:7012827",
      "tgn:7002454",
      "tgn:1000047",
      "tgn:1000002",
      "tgn:7029392"
    ],
    "placetype": [
      "aat:300008707"
    ],
    "id": 1123077,
    "name:xx": "Corumbá"
  }
}
