{
  "geometry": {
    "type": "Point",
    "coordinates": [
      58.2167,
      51.8667
    ]
  },
  "type": "Feature",
  "properties": {
    "hierarchy": [
      "tgn:1052011",
      "tgn:1000004",
      "tgn:7011498",
      "tgn:7002435",
      "tgn:7029392"
    ],
    "placetype": [
      "aat:300008347"
    ],
    "id": 1052011,
    "name:xx": "Akyar"
  }
}
