{
  "type": "FeatureCollection",
  "features": [
    {
      "geometry": {
        "type": "Point",
        "coordinates": [
          4.120853,
          50.757047
        ]
      },
      "type": "Feature",
      "properties": {
        "hierarchy": [
          "tgn:7246421",
          "tgn:7003457",
          "tgn:1000003",
          "tgn:1000063",
          "tgn:7018236",
          "tgn:7029392"
        ],
        "placetype": [
          "aat:300008699"
        ],
        "id": 7246421,
        "name:xx": "Bosbeek"
      }
    },
    {
      "geometry": {
        "type": "Point",
        "coordinates": [
          4.249693,
          50.942396
        ]
      },
      "type": "Feature",
      "properties": {
        "hierarchy": [
          "tgn:7246422",
          "tgn:7003456",
          "tgn:1000003",
          "tgn:1000063",
          "tgn:7018236",
          "tgn:7029392"
        ],
        "placetype": [
          "aat:300008347"
        ],
        "id": 7246422,
        "name:xx": "Bosbeek"
      }
    },
    {
      "geometry": {
        "type": "Point",
        "coordinates": [
          4.583333,
          50.766667
        ]
      },
      "type": "Feature",
      "properties": {
        "hierarchy": [
          "tgn:7246423",
          "tgn:7018239",
          "tgn:1000003",
          "tgn:1000063",
          "tgn:7018236",
          "tgn:7029392"
        ],
        "placetype": [
          "aat:300000206"
        ],
        "id": 7246423,
        "name:xx": "Hof ten Bos"
      }
    },
    {
      "geometry": {
        "type": "Point",
        "coordinates": [
          3.71661,
          50.777554
        ]
      },
      "type": "Feature",
      "properties": {
        "hierarchy": [
          "tgn:7246424",
          "tgn:7003457",
          "tgn:1000003",
          "tgn:1000063",
          "tgn:7018236",
          "tgn:7029392"
        ],
        "placetype": [
          "aat:300000206"
        ],
        "id": 7246424,
        "name:xx": "Hof ten Bos"
      }
    },
    {
      "geometry": {
        "type": "Point",
        "coordinates": [
          3.591033,
          51.143505
        ]
      },
      "type": "Feature",
      "properties": {
        "hierarchy": [
          "tgn:7246425",
          "tgn:7003457",
          "tgn:1000003",
          "tgn:1000063",
          "tgn:7018236",
          "tgn:7029392"
        ],
        "placetype": [
          "aat:300008347"
        ],
        "id": 7246425,
        "name:xx": "Bos"
      }
    },
    {
      "geometry": {
        "type": "Point",
        "coordinates": [
          5.683333,
          51.133333
        ]
      },
      "type": "Feature",
      "properties": {
        "hierarchy": [
          "tgn:7246426",
          "tgn:7003461",
          "tgn:1000003",
          "tgn:1000063",
          "tgn:7018236",
          "tgn:7029392"
        ],
        "placetype": [
          "aat:300008347"
        ],
        "id": 7246426,
        "name:xx": "Bos"
      }
    },
    {
      "geometry": {
        "type": "Point",
        "coordinates": [
          4.716667,
          51.066667
        ]
      },
      "type": "Feature",
      "properties": {
        "hierarchy": [
          "tgn:7246427",
          "tgn:7003456",
          "tgn:1000003",
          "tgn:1000063",
          "tgn:7018236",
          "tgn:7029392"
        ],
        "placetype": [
          "aat:300008347"
        ],
        "id": 7246427,
        "name:xx": "Bos"
      }
    },
    {
      "geometry": {
        "type": "Point",
        "coordinates": [
          4.003249,
          51.068911
        ]
      },
      "type": "Feature",
      "properties": {
        "hierarchy": [
          "tgn:7246428",
          "tgn:7003457",
          "tgn:1000003",
          "tgn:1000063",
          "tgn:7018236",
          "tgn:7029392"
        ],
        "placetype": [
          "aat:300008347"
        ],
        "id": 7246428,
        "name:xx": "Bos"
      }
    },
    {
      "geometry": {
        "type": "Point",
        "coordinates": [
          4.433333,
          50.983333
        ]
      },
      "type": "Feature",
      "properties": {
        "hierarchy": [
          "tgn:7246429",
          "tgn:7003456",
          "tgn:1000003",
          "tgn:1000063",
          "tgn:7018236",
          "tgn:7029392"
        ],
        "placetype": [
          "aat:300008347"
        ],
        "id": 7246429,
        "name:xx": "Bos"
      }
    }
  ]
}
