{
  "geometry": {
    "type": "Point",
    "coordinates": [
      -81.3167,
      35.15
    ]
  },
  "type": "Feature",
  "properties": {
    "hierarchy": [
      "tgn:2420732",
      "tgn:1000001",
      "tgn:7012149",
      "tgn:2001770",
      "tgn:7007712",
      "tgn:7029392"
    ],
    "placetype": [
      "aat:300008699"
    ],
    "id": 2420732,
    "name:xx": "Jennings Branch"
  }
}
