{
  "geometry": {
    "type": "Point",
    "coordinates": [
      -106.5833,
      39.0833
    ]
  },
  "type": "Feature",
  "properties": {
    "hierarchy": [
      "tgn:2410111",
      "tgn:1000001",
      "tgn:7012149",
      "tgn:7007158",
      "tgn:2000240",
      "tgn:7029392"
    ],
    "placetype": [
      "aat:300008706"
    ],
    "id": 2410111,
    "name:xx": "Independence Creek"
  }
}
