{
  "geometry": {
    "type": "Point",
    "coordinates": [
      78.3167,
      34.2833
    ]
  },
  "type": "Feature",
  "properties": {
    "hierarchy": [
      "tgn:1122680",
      "tgn:1000004",
      "tgn:7029392"
    ],
    "placetype": [
      "aat:300008707"
    ],
    "id": 1122680,
    "name:xx": "Chang Chenmo"
  }
}
