{
  "geometry": {
    "type": "Point",
    "coordinates": [
      -85.65,
      35.2833
    ]
  },
  "type": "Feature",
  "properties": {
    "hierarchy": [
      "tgn:2186563",
      "tgn:1000001",
      "tgn:7012149",
      "tgn:2001894",
      "tgn:7007825",
      "tgn:7029392"
    ],
    "placetype": [
      "aat:300266640"
    ],
    "id": 2186563,
    "name:xx": "Bone Ridge"
  }
}
