{
  "geometry": {
    "type": "Point",
    "coordinates": [
      -87.3333,
      32.3833
    ]
  },
  "type": "Feature",
  "properties": {
    "hierarchy": [
      "tgn:2756143",
      "tgn:7002659",
      "tgn:1000001",
      "tgn:7012149",
      "tgn:2000023",
      "tgn:7029392"
    ],
    "placetype": [
      "aat:300006191"
    ],
    "id": 2756143,
    "name:xx": "Weissinger Lakes"
  }
}
