{
  "geometry": {
    "type": "Point",
    "coordinates": [
      -108.0333,
      39.55
    ]
  },
  "type": "Feature",
  "properties": {
    "hierarchy": [
      "tgn:2323718",
      "tgn:1000001",
      "tgn:7012149",
      "tgn:7029392"
    ],
    "placetype": [
      "aat:300008761"
    ],
    "id": 2323718,
    "name:xx": "Fatty Canyon"
  }
}
