{
  "geometry": {
    "type": "Point",
    "coordinates": [
      -77.2167,
      34.8167
    ]
  },
  "type": "Feature",
  "properties": {
    "hierarchy": [
      "tgn:2525608",
      "tgn:1000001",
      "tgn:7012149",
      "tgn:2001524",
      "tgn:7007709",
      "tgn:7029392"
    ],
    "placetype": [
      "aat:300008347"
    ],
    "id": 2525608,
    "name:xx": "Morton Fork"
  }
}
