{
  "geometry": {
    "type": "Point",
    "coordinates": [
      -79.6833,
      33.1833
    ]
  },
  "type": "Feature",
  "properties": {
    "hierarchy": [
      "tgn:2148806",
      "tgn:2001732",
      "tgn:1000001",
      "tgn:7012149",
      "tgn:7007712",
      "tgn:7029392"
    ],
    "placetype": [
      "aat:300008791"
    ],
    "id": 2148806,
    "name:xx": "Barnett Island"
  }
}
