{
  "geometry": {
    "type": "Point",
    "coordinates": [
      -124.2667,
      43.3167
    ]
  },
  "type": "Feature",
  "properties": {
    "hierarchy": [
      "tgn:2785557",
      "tgn:1000001",
      "tgn:2001702",
      "tgn:7012149",
      "tgn:7007708",
      "tgn:7029392"
    ],
    "placetype": [
      "aat:300008798"
    ],
    "id": 2785557,
    "name:xx": "Yoakam Hill"
  }
}
