{
  "geometry": {
    "type": "Point",
    "coordinates": [
      17.0833,
      59.7333
    ]
  },
  "type": "Feature",
  "properties": {
    "hierarchy": [
      "tgn:1063064",
      "tgn:1000003",
      "tgn:1000462",
      "tgn:1000097",
      "tgn:7029392"
    ],
    "placetype": [
      "aat:300008347"
    ],
    "id": 1063064,
    "name:xx": "Härnevi"
  }
}
