{
  "geometry": {
    "type": "Point",
    "coordinates": [
      -80.8833,
      36.6167
    ]
  },
  "type": "Feature",
  "properties": {
    "hierarchy": [
      "tgn:2263439",
      "tgn:1000001",
      "tgn:7012149",
      "tgn:2002164",
      "tgn:7007919",
      "tgn:7029392"
    ],
    "placetype": [
      "aat:300008347"
    ],
    "id": 2263439,
    "name:xx": "Cox Mill"
  }
}
