{
  "geometry": {
    "type": "Point",
    "coordinates": [
      40.0333,
      48.35
    ]
  },
  "type": "Feature",
  "properties": {
    "hierarchy": [
      "tgn:1122070",
      "tgn:1000003",
      "tgn:7029392"
    ],
    "placetype": [
      "aat:300008707"
    ],
    "id": 1122070,
    "name:xx": "Velyka Kam-yanka"
  }
}
