{
  "geometry": {
    "type": "Point",
    "coordinates": [
      -96.95,
      38.5667
    ]
  },
  "type": "Feature",
  "properties": {
    "hierarchy": [
      "tgn:2441660",
      "tgn:1000001",
      "tgn:7012149",
      "tgn:7007254",
      "tgn:7029392"
    ],
    "placetype": [
      "aat:300008706"
    ],
    "id": 2441660,
    "name:xx": "Kohls Creek"
  }
}
