{
  "geometry": {
    "type": "Point",
    "coordinates": [
      -111.4833,
      36.9333
    ]
  },
  "type": "Feature",
  "properties": {
    "hierarchy": [
      "tgn:2596904",
      "tgn:1000001",
      "tgn:7012149",
      "tgn:7029392"
    ],
    "placetype": [
      "aat:300006191"
    ],
    "id": 2596904,
    "name:xx": "Powell, Lake"
  }
}
