{
  "geometry": {
    "type": "Point",
    "coordinates": [
      -121.15,
      41.3167
    ]
  },
  "type": "Feature",
  "properties": {
    "hierarchy": [
      "tgn:2292237",
      "tgn:1000001",
      "tgn:7012149",
      "tgn:7007157",
      "tgn:2000186",
      "tgn:7029392"
    ],
    "placetype": [
      "aat:300008798"
    ],
    "id": 2292237,
    "name:xx": "Donica Mountain"
  }
}
