{
  "geometry": {
    "type": "Point",
    "coordinates": [
      -114.6333,
      42.0333
    ]
  },
  "type": "Feature",
  "properties": {
    "hierarchy": [
      "tgn:7020976",
      "tgn:1000001",
      "tgn:7012149",
      "tgn:2000488",
      "tgn:7007250",
      "tgn:7029392"
    ],
    "placetype": [
      "aat:300008697"
    ],
    "id": 7020976,
    "name:xx": "Twin Springs"
  }
}
