{
  "geometry": {
    "type": "Point",
    "coordinates": [
      13.4833,
      48.0167
    ]
  },
  "type": "Feature",
  "properties": {
    "hierarchy": [
      "tgn:1026176",
      "tgn:7003026",
      "tgn:1000003",
      "tgn:1000062",
      "tgn:7029392"
    ],
    "placetype": [
      "aat:300008347"
    ],
    "id": 1026176,
    "name:xx": "Vöcklamarkt"
  }
}
