{
  "geometry": {
    "type": "Point",
    "coordinates": [
      74.832907,
      34.010065
    ]
  },
  "type": "Feature",
  "properties": {
    "hierarchy": [
      "tgn:7587881",
      "tgn:1000004",
      "tgn:7000198",
      "tgn:7000799",
      "tgn:7029392"
    ],
    "placetype": [
      "aat:300008347"
    ],
    "name:en": "Manganwār",
    "id": 7587881
  }
}
