{
  "type": "FeatureCollection",
  "features": [
    {
      "geometry": {
        "type": "Point",
        "coordinates": [
          -102.85,
          28.683333
        ]
      },
      "type": "Feature",
      "properties": {
        "hierarchy": [
          "tgn:7375200",
          "tgn:7005581",
          "tgn:1000001",
          "tgn:7005560",
          "tgn:7029392"
        ],
        "placetype": [
          "aat:300008347"
        ],
        "id": 7375200,
        "name:xx": "Las Delicias"
      }
    },
    {
      "geometry": {
        "type": "Point",
        "coordinates": [
          -108.183333,
          28.283333
        ]
      },
      "type": "Feature",
      "properties": {
        "hierarchy": [
          "tgn:7375201",
          "tgn:7005581",
          "tgn:1000001",
          "tgn:7005560",
          "tgn:7029392"
        ],
        "placetype": [
          "aat:300008347"
        ],
        "id": 7375201,
        "name:xx": "Las Delicias"
      }
    },
    {
      "geometry": {
        "type": "Point",
        "coordinates": [
          -106.466667,
          27.066667
        ]
      },
      "type": "Feature",
      "properties": {
        "hierarchy": [
          "tgn:7375203",
          "tgn:7005581",
          "tgn:1000001",
          "tgn:7005560",
          "tgn:7029392"
        ],
        "placetype": [
          "aat:300008347"
        ],
        "id": 7375203,
        "name:xx": "Las Delicias"
      }
    },
    {
      "geometry": {
        "type": "Point",
        "coordinates": [
          -112.083333,
          26.966667
        ]
      },
      "type": "Feature",
      "properties": {
        "hierarchy": [
          "tgn:7375204",
          "tgn:1001836",
          "tgn:1000001",
          "tgn:7005560",
          "tgn:7029392"
        ],
        "placetype": [
          "aat:300008347"
        ],
        "id": 7375204,
        "name:xx": "Las Delicias"
      }
    },
    {
      "geometry": {
        "type": "Point",
        "coordinates": [
          -101.633333,
          26.8
        ]
      },
      "type": "Feature",
      "properties": {
        "hierarchy": [
          "tgn:7375205",
          "tgn:1001853",
          "tgn:1000001",
          "tgn:7005560",
          "tgn:7029392"
        ],
        "placetype": [
          "aat:300008347"
        ],
        "id": 7375205,
        "name:xx": "Las Delicias"
      }
    },
    {
      "geometry": {
        "type": "Point",
        "coordinates": [
          -106.166667,
          26.716667
        ]
      },
      "type": "Feature",
      "properties": {
        "hierarchy": [
          "tgn:7375206",
          "tgn:7005583",
          "tgn:1000001",
          "tgn:7005560",
          "tgn:7029392"
        ],
        "placetype": [
          "aat:300008347"
        ],
        "id": 7375206,
        "name:xx": "Las Delicias"
      }
    },
    {
      "geometry": {
        "type": "Point",
        "coordinates": [
          -105.633333,
          26.3
        ]
      },
      "type": "Feature",
      "properties": {
        "hierarchy": [
          "tgn:7375207",
          "tgn:7005583",
          "tgn:1000001",
          "tgn:7005560",
          "tgn:7029392"
        ],
        "placetype": [
          "aat:300008347"
        ],
        "id": 7375207,
        "name:xx": "Las Delicias"
      }
    },
    {
      "geometry": {
        "type": "Point",
        "coordinates": [
          -102.783333,
          26.216667
        ]
      },
      "type": "Feature",
      "properties": {
        "hierarchy": [
          "tgn:7375208",
          "tgn:1001853",
          "tgn:1000001",
          "tgn:7005560",
          "tgn:7029392"
        ],
        "placetype": [
          "aat:300008347"
        ],
        "id": 7375208,
        "name:xx": "Las Delicias"
      }
    },
    {
      "geometry": {
        "type": "Point",
        "coordinates": [
          -102.333333,
          26.166667
        ]
      },
      "type": "Feature",
      "properties": {
        "hierarchy": [
          "tgn:7375209",
          "tgn:1001853",
          "tgn:1000001",
          "tgn:7005560",
          "tgn:7029392"
        ],
        "placetype": [
          "aat:300008347"
        ],
        "id": 7375209,
        "name:xx": "Las Delicias"
      }
    }
  ]
}
