{
  "geometry": {
    "type": "Point",
    "coordinates": [
      -80.85,
      36.9833
    ]
  },
  "type": "Feature",
  "properties": {
    "hierarchy": [
      "tgn:2197746",
      "tgn:1000001",
      "tgn:7012149",
      "tgn:2002196",
      "tgn:7007919",
      "tgn:7029392"
    ],
    "placetype": [
      "aat:300008699"
    ],
    "id": 2197746,
    "name:xx": "Brown Lick Branch"
  }
}
