{
  "geometry": {
    "type": "Point",
    "coordinates": [
      73.3333,
      40.25
    ]
  },
  "type": "Feature",
  "properties": {
    "hierarchy": [
      "tgn:1108309",
      "tgn:1000004",
      "tgn:7012212",
      "tgn:7006655",
      "tgn:7029392"
    ],
    "placetype": [
      "aat:300259572"
    ],
    "id": 1108309,
    "name:xx": "Čijirčik, pereval"
  }
}
