{
  "type": "FeatureCollection",
  "features": [
    {
      "geometry": {
        "type": "Point",
        "coordinates": [
          16.6333,
          -0.7333
        ]
      },
      "type": "Feature",
      "properties": {
        "hierarchy": [
          "tgn:1125730",
          "tgn:7001242",
          "tgn:1000972",
          "tgn:1000158",
          "tgn:7029392"
        ],
        "placetype": [
          "aat:300008707"
        ],
        "id": 1125730,
        "name:xx": "Kouyou"
      }
    },
    {
      "geometry": {
        "type": "Point",
        "coordinates": [
          69.4,
          37.15
        ]
      },
      "type": "Feature",
      "properties": {
        "hierarchy": [
          "tgn:1125733",
          "tgn:7016612",
          "tgn:1000004",
          "tgn:7029392"
        ],
        "placetype": [
          "aat:300008707"
        ],
        "id": 1125733,
        "name:xx": "Kowkcheh"
      }
    },
    {
      "geometry": {
        "type": "Point",
        "coordinates": [
          -163.2167,
          65.4167
        ]
      },
      "type": "Feature",
      "properties": {
        "hierarchy": [
          "tgn:1125735",
          "tgn:7006450",
          "tgn:1000001",
          "tgn:7012149",
          "tgn:2000079",
          "tgn:7029392"
        ],
        "placetype": [
          "aat:300008707"
        ],
        "id": 1125735,
        "name:xx": "Koyuk"
      }
    },
    {
      "geometry": {
        "type": "Point",
        "coordinates": [
          -151.0667,
          67.0333
        ]
      },
      "type": "Feature",
      "properties": {
        "hierarchy": [
          "tgn:1125736",
          "tgn:7006450",
          "tgn:1000001",
          "tgn:7012149",
          "tgn:2000089",
          "tgn:7029392"
        ],
        "placetype": [
          "aat:300008707"
        ],
        "id": 1125736,
        "name:xx": "Koyukuk River"
      }
    }
  ]
}
