{
  "geometry": {
    "type": "Point",
    "coordinates": [
      -110.05,
      43.7333
    ]
  },
  "type": "Feature",
  "properties": {
    "hierarchy": [
      "tgn:2776451",
      "tgn:1000001",
      "tgn:7012149",
      "tgn:7007923",
      "tgn:7029392"
    ],
    "placetype": [
      "aat:300008680"
    ],
    "id": 2776451,
    "name:xx": "Wind River Lake"
  }
}
