{
  "geometry": {
    "type": "Point",
    "coordinates": [
      -114.2667,
      42.3667
    ]
  },
  "type": "Feature",
  "properties": {
    "hierarchy": [
      "tgn:2135075",
      "tgn:1000001",
      "tgn:2000467",
      "tgn:7012149",
      "tgn:7007250",
      "tgn:7029392"
    ],
    "placetype": [
      "aat:300008761"
    ],
    "id": 2135075,
    "name:xx": "Antelope Valley"
  }
}
