{
  "geometry": {
    "type": "Point",
    "coordinates": [
      75.942195,
      28.6349
    ]
  },
  "type": "Feature",
  "properties": {
    "hierarchy": [
      "tgn:7573182",
      "tgn:1000004",
      "tgn:1001871",
      "tgn:7000198",
      "tgn:7029392"
    ],
    "placetype": [
      "aat:300008347"
    ],
    "name:en": "Jui Kalān",
    "id": 7573182
  }
}
