{
  "geometry": {
    "type": "Point",
    "coordinates": [
      -113.2333,
      34.8667
    ]
  },
  "type": "Feature",
  "properties": {
    "hierarchy": [
      "tgn:2154535",
      "tgn:1000001",
      "tgn:7006451",
      "tgn:7012149",
      "tgn:2000103",
      "tgn:7029392"
    ],
    "placetype": [
      "aat:300006191"
    ],
    "id": 2154535,
    "name:xx": "Bear Creek Tank"
  }
}
