{
  "geometry": {
    "type": "Point",
    "coordinates": [
      -81.8667,
      38.6667
    ]
  },
  "type": "Feature",
  "properties": {
    "hierarchy": [
      "tgn:2212054",
      "tgn:1000001",
      "tgn:7012149",
      "tgn:2002277",
      "tgn:7013961",
      "tgn:7029392"
    ],
    "placetype": [
      "aat:300008706"
    ],
    "id": 2212054,
    "name:xx": "Buzzard Creek"
  }
}
