{
  "type": "FeatureCollection",
  "features": [
    {
      "geometry": {
        "type": "Point",
        "coordinates": [
          -92.383333,
          15.9
        ]
      },
      "type": "Feature",
      "properties": {
        "hierarchy": [
          "tgn:7377400",
          "tgn:7005580",
          "tgn:1000001",
          "tgn:7005560",
          "tgn:7029392"
        ],
        "placetype": [
          "aat:300008347"
        ],
        "id": 7377400,
        "name:xx": "La Piedad"
      }
    },
    {
      "geometry": {
        "type": "Point",
        "coordinates": [
          -102.416667,
          19.383333
        ]
      },
      "type": "Feature",
      "properties": {
        "hierarchy": [
          "tgn:7377401",
          "tgn:1000001",
          "tgn:7005590",
          "tgn:7005560",
          "tgn:7029392"
        ],
        "placetype": [
          "aat:300008347"
        ],
        "id": 7377401,
        "name:xx": "La Soledad"
      }
    },
    {
      "geometry": {
        "type": "Point",
        "coordinates": [
          -102.266667,
          19.35
        ]
      },
      "type": "Feature",
      "properties": {
        "hierarchy": [
          "tgn:7377402",
          "tgn:1000001",
          "tgn:7005590",
          "tgn:7005560",
          "tgn:7029392"
        ],
        "placetype": [
          "aat:300008347"
        ],
        "id": 7377402,
        "name:xx": "La Soledad"
      }
    },
    {
      "geometry": {
        "type": "Point",
        "coordinates": [
          -102.783333,
          19.233333
        ]
      },
      "type": "Feature",
      "properties": {
        "hierarchy": [
          "tgn:7377403",
          "tgn:1000001",
          "tgn:7005590",
          "tgn:7005560",
          "tgn:7029392"
        ],
        "placetype": [
          "aat:300008347"
        ],
        "id": 7377403,
        "name:xx": "La Soledad"
      }
    },
    {
      "geometry": {
        "type": "Point",
        "coordinates": [
          -92.083333,
          18.283333
        ]
      },
      "type": "Feature",
      "properties": {
        "hierarchy": [
          "tgn:7377404",
          "tgn:7005578",
          "tgn:1000001",
          "tgn:7005560",
          "tgn:7029392"
        ],
        "placetype": [
          "aat:300008347"
        ],
        "id": 7377404,
        "name:xx": "La Soledad"
      }
    },
    {
      "geometry": {
        "type": "Point",
        "coordinates": [
          -95.716667,
          18.1
        ]
      },
      "type": "Feature",
      "properties": {
        "hierarchy": [
          "tgn:7377405",
          "tgn:1000001",
          "tgn:7005599",
          "tgn:7005560",
          "tgn:7029392"
        ],
        "placetype": [
          "aat:300008347"
        ],
        "id": 7377405,
        "name:xx": "La Soledad"
      }
    },
    {
      "geometry": {
        "type": "Point",
        "coordinates": [
          -101.716667,
          17.983333
        ]
      },
      "type": "Feature",
      "properties": {
        "hierarchy": [
          "tgn:7377406",
          "tgn:7005585",
          "tgn:1000001",
          "tgn:7005560",
          "tgn:7029392"
        ],
        "placetype": [
          "aat:300008347"
        ],
        "id": 7377406,
        "name:xx": "La Soledad"
      }
    },
    {
      "geometry": {
        "type": "Point",
        "coordinates": [
          -93.333333,
          17.983333
        ]
      },
      "type": "Feature",
      "properties": {
        "hierarchy": [
          "tgn:7377407",
          "tgn:7005580",
          "tgn:1000001",
          "tgn:7005560",
          "tgn:7029392"
        ],
        "placetype": [
          "aat:300008347"
        ],
        "id": 7377407,
        "name:xx": "La Soledad"
      }
    },
    {
      "geometry": {
        "type": "Point",
        "coordinates": [
          -101.233333,
          17.916667
        ]
      },
      "type": "Feature",
      "properties": {
        "hierarchy": [
          "tgn:7377408",
          "tgn:7005585",
          "tgn:1000001",
          "tgn:7005560",
          "tgn:7029392"
        ],
        "placetype": [
          "aat:300008347"
        ],
        "id": 7377408,
        "name:xx": "La Soledad"
      }
    },
    {
      "geometry": {
        "type": "Point",
        "coordinates": [
          -100.433333,
          17.783333
        ]
      },
      "type": "Feature",
      "properties": {
        "hierarchy": [
          "tgn:7377409",
          "tgn:7005585",
          "tgn:1000001",
          "tgn:7005560",
          "tgn:7029392"
        ],
        "placetype": [
          "aat:300008347"
        ],
        "id": 7377409,
        "name:xx": "La Soledad"
      }
    }
  ]
}
