{
  "type": "FeatureCollection",
  "features": [
    {
      "geometry": {
        "type": "Point",
        "coordinates": [
          -85.2667,
          46.5667
        ]
      },
      "type": "Feature",
      "properties": {
        "hierarchy": [
          "tgn:2778990",
          "tgn:1000001",
          "tgn:7012149",
          "tgn:2000972",
          "tgn:7007520",
          "tgn:7029392"
        ],
        "placetype": [
          "aat:300008706"
        ],
        "id": 2778990,
        "name:xx": "Wolf Creek"
      }
    },
    {
      "geometry": {
        "type": "Point",
        "coordinates": [
          -84.2667,
          43.35
        ]
      },
      "type": "Feature",
      "properties": {
        "hierarchy": [
          "tgn:2778991",
          "tgn:1000001",
          "tgn:7012149",
          "tgn:2000992",
          "tgn:7007520",
          "tgn:7029392"
        ],
        "placetype": [
          "aat:300008706"
        ],
        "id": 2778991,
        "name:xx": "Wolf Creek"
      }
    },
    {
      "geometry": {
        "type": "Point",
        "coordinates": [
          -84.7167,
          44.2167
        ]
      },
      "type": "Feature",
      "properties": {
        "hierarchy": [
          "tgn:2778992",
          "tgn:1000001",
          "tgn:7012149",
          "tgn:2000991",
          "tgn:7007520",
          "tgn:7029392"
        ],
        "placetype": [
          "aat:300008706"
        ],
        "id": 2778992,
        "name:xx": "Wolf Creek"
      }
    },
    {
      "geometry": {
        "type": "Point",
        "coordinates": [
          -84.1167,
          44.6
        ]
      },
      "type": "Feature",
      "properties": {
        "hierarchy": [
          "tgn:2778993",
          "tgn:1000001",
          "tgn:7012149",
          "tgn:2000988",
          "tgn:7007520",
          "tgn:7029392"
        ],
        "placetype": [
          "aat:300008706"
        ],
        "id": 2778993,
        "name:xx": "Wolf Creek"
      }
    },
    {
      "geometry": {
        "type": "Point",
        "coordinates": [
          -83.75,
          44.85
        ]
      },
      "type": "Feature",
      "properties": {
        "hierarchy": [
          "tgn:2778994",
          "tgn:2000944",
          "tgn:1000001",
          "tgn:7012149",
          "tgn:7007520",
          "tgn:7029392"
        ],
        "placetype": [
          "aat:300008706"
        ],
        "id": 2778994,
        "name:xx": "Wolf Creek"
      }
    },
    {
      "geometry": {
        "type": "Point",
        "coordinates": [
          -84.1833,
          42.05
        ]
      },
      "type": "Feature",
      "properties": {
        "hierarchy": [
          "tgn:2778995",
          "tgn:1000001",
          "tgn:7012149",
          "tgn:1002588",
          "tgn:7007520",
          "tgn:7029392"
        ],
        "placetype": [
          "aat:300008706"
        ],
        "id": 2778995,
        "name:xx": "Wolf Creek"
      }
    },
    {
      "geometry": {
        "type": "Point",
        "coordinates": [
          -84.15,
          42.7667
        ]
      },
      "type": "Feature",
      "properties": {
        "hierarchy": [
          "tgn:2778996",
          "tgn:1000001",
          "tgn:7012149",
          "tgn:7007520",
          "tgn:7029392"
        ],
        "placetype": [
          "aat:300008706"
        ],
        "id": 2778996,
        "name:xx": "Wolf Creek"
      }
    },
    {
      "geometry": {
        "type": "Point",
        "coordinates": [
          -89.2833,
          46.2833
        ]
      },
      "type": "Feature",
      "properties": {
        "hierarchy": [
          "tgn:2778997",
          "tgn:1000001",
          "tgn:7012149",
          "tgn:2000960",
          "tgn:7007520",
          "tgn:7029392"
        ],
        "placetype": [
          "aat:300008706"
        ],
        "id": 2778997,
        "name:xx": "Wolf Creek"
      }
    },
    {
      "geometry": {
        "type": "Point",
        "coordinates": [
          -92.85,
          46.1667
        ]
      },
      "type": "Feature",
      "properties": {
        "hierarchy": [
          "tgn:2778998",
          "tgn:1000001",
          "tgn:7012149",
          "tgn:2001056",
          "tgn:7007521",
          "tgn:7029392"
        ],
        "placetype": [
          "aat:300008706"
        ],
        "id": 2778998,
        "name:xx": "Wolf Creek"
      }
    },
    {
      "geometry": {
        "type": "Point",
        "coordinates": [
          -92.4167,
          47.9167
        ]
      },
      "type": "Feature",
      "properties": {
        "hierarchy": [
          "tgn:2778999",
          "tgn:1000001",
          "tgn:7012149",
          "tgn:2001067",
          "tgn:7007521",
          "tgn:7029392"
        ],
        "placetype": [
          "aat:300008706"
        ],
        "id": 2778999,
        "name:xx": "Wolf Creek"
      }
    }
  ]
}
