{
  "geometry": {
    "type": "Point",
    "coordinates": [
      -134.0667,
      57.2667
    ]
  },
  "type": "Feature",
  "properties": {
    "hierarchy": [
      "tgn:2682797",
      "tgn:7006450",
      "tgn:1000001",
      "tgn:7012149",
      "tgn:7019760",
      "tgn:7029392"
    ],
    "placetype": [
      "aat:300386853"
    ],
    "id": 2682797,
    "name:xx": "Southwest Islands"
  }
}
