{
  "geometry": {
    "type": "Point",
    "coordinates": [
      -90.5833,
      32.1667
    ]
  },
  "type": "Feature",
  "properties": {
    "hierarchy": [
      "tgn:2734892",
      "tgn:1000001",
      "tgn:7012149",
      "tgn:2001110",
      "tgn:7007522",
      "tgn:7029392"
    ],
    "placetype": [
      "aat:300008706"
    ],
    "id": 2734892,
    "name:xx": "Twelvemile Creek"
  }
}
