{
  "geometry": {
    "type": "Point",
    "coordinates": [
      12.2833,
      55.65
    ]
  },
  "type": "Feature",
  "properties": {
    "hierarchy": [
      "tgn:4004704",
      "tgn:7594005",
      "tgn:1000003",
      "tgn:1000066",
      "tgn:7029392"
    ],
    "placetype": [
      "aat:300008347"
    ],
    "id": 4004704,
    "name:xx": "Høje Tåstrup"
  }
}
