{
  "type": "FeatureCollection",
  "features": [
    {
      "geometry": {
        "type": "Point",
        "coordinates": [
          -0.2667,
          52.7833
        ]
      },
      "type": "Feature",
      "properties": {
        "hierarchy": [
          "tgn:1136201",
          "tgn:7002445",
          "tgn:1000003",
          "tgn:7008157",
          "tgn:7008591",
          "tgn:7029392"
        ],
        "placetype": [
          "aat:300006075",
          "aat:300006178"
        ],
        "name:en": "South Forty Foot Drain",
        "id": 1136201
      }
    },
    {
      "geometry": {
        "type": "Point",
        "coordinates": [
          106.8333,
          -6.1167
        ]
      },
      "type": "Feature",
      "properties": {
        "hierarchy": [
          "tgn:1136202",
          "tgn:7003695",
          "tgn:1000004",
          "tgn:1000116",
          "tgn:7029392"
        ],
        "placetype": [
          "aat:300006178"
        ],
        "id": 1136202,
        "name:xx": "Sunter, Kali"
      }
    },
    {
      "geometry": {
        "type": "Point",
        "coordinates": [
          -88.1667,
          40.45
        ]
      },
      "type": "Feature",
      "properties": {
        "hierarchy": [
          "tgn:1136203",
          "tgn:1000001",
          "tgn:7012149",
          "tgn:7007251",
          "tgn:7029392"
        ],
        "placetype": [
          "aat:300006178"
        ],
        "id": 1136203,
        "name:xx": "Wall Town Drainage Ditch"
      }
    },
    {
      "geometry": {
        "type": "Point",
        "coordinates": [
          -58.4667,
          -34.4667
        ]
      },
      "type": "Feature",
      "properties": {
        "hierarchy": [
          "tgn:1136206",
          "tgn:1001160",
          "tgn:7006477",
          "tgn:1000002",
          "tgn:7029392"
        ],
        "placetype": [
          "aat:300386965"
        ],
        "id": 1136206,
        "name:xx": "Costanero, Canal"
      }
    },
    {
      "geometry": {
        "type": "Point",
        "coordinates": [
          -122.6333,
          48.4
        ]
      },
      "type": "Feature",
      "properties": {
        "hierarchy": [
          "tgn:1136207",
          "tgn:1000001",
          "tgn:7012149",
          "tgn:7007920",
          "tgn:7029392"
        ],
        "placetype": [
          "aat:300386965"
        ],
        "id": 1136207,
        "name:xx": "Deception Pass"
      }
    }
  ]
}
