{
  "geometry": {
    "type": "Point",
    "coordinates": [
      -73.05,
      43.8667
    ]
  },
  "type": "Feature",
  "properties": {
    "hierarchy": [
      "tgn:2644908",
      "tgn:2002130",
      "tgn:1000001",
      "tgn:7012149",
      "tgn:7007828",
      "tgn:7029392"
    ],
    "placetype": [
      "aat:300008347"
    ],
    "id": 2644908,
    "name:xx": "Satans Kingdom"
  }
}
