{
  "type": "FeatureCollection",
  "features": [
    {
      "geometry": {
        "type": "Point",
        "coordinates": [
          -92.016667,
          17.916667
        ]
      },
      "type": "Feature",
      "properties": {
        "hierarchy": [
          "tgn:7393500",
          "tgn:1000001",
          "tgn:7005596",
          "tgn:7005560",
          "tgn:7029392"
        ],
        "placetype": [
          "aat:300008347"
        ],
        "id": 7393500,
        "name:xx": "San José"
      }
    },
    {
      "geometry": {
        "type": "Point",
        "coordinates": [
          -91.616667,
          17.883333
        ]
      },
      "type": "Feature",
      "properties": {
        "hierarchy": [
          "tgn:7393501",
          "tgn:1000001",
          "tgn:7005596",
          "tgn:7005560",
          "tgn:7029392"
        ],
        "placetype": [
          "aat:300008347"
        ],
        "id": 7393501,
        "name:xx": "San José"
      }
    },
    {
      "geometry": {
        "type": "Point",
        "coordinates": [
          -93.85,
          17.866667
        ]
      },
      "type": "Feature",
      "properties": {
        "hierarchy": [
          "tgn:7393502",
          "tgn:1000001",
          "tgn:7005596",
          "tgn:7005560",
          "tgn:7029392"
        ],
        "placetype": [
          "aat:300008347"
        ],
        "id": 7393502,
        "name:xx": "San José"
      }
    },
    {
      "geometry": {
        "type": "Point",
        "coordinates": [
          -93.366667,
          17.866667
        ]
      },
      "type": "Feature",
      "properties": {
        "hierarchy": [
          "tgn:7393503",
          "tgn:1000001",
          "tgn:7005596",
          "tgn:7005560",
          "tgn:7029392"
        ],
        "placetype": [
          "aat:300008347"
        ],
        "id": 7393503,
        "name:xx": "San José"
      }
    },
    {
      "geometry": {
        "type": "Point",
        "coordinates": [
          -91.566667,
          17.75
        ]
      },
      "type": "Feature",
      "properties": {
        "hierarchy": [
          "tgn:7393504",
          "tgn:1000001",
          "tgn:7005596",
          "tgn:7005560",
          "tgn:7029392"
        ],
        "placetype": [
          "aat:300008347"
        ],
        "id": 7393504,
        "name:xx": "San José"
      }
    },
    {
      "geometry": {
        "type": "Point",
        "coordinates": [
          -92.933333,
          17.7
        ]
      },
      "type": "Feature",
      "properties": {
        "hierarchy": [
          "tgn:7393505",
          "tgn:1000001",
          "tgn:7005596",
          "tgn:7005560",
          "tgn:7029392"
        ],
        "placetype": [
          "aat:300008347"
        ],
        "id": 7393505,
        "name:xx": "San José"
      }
    },
    {
      "geometry": {
        "type": "Point",
        "coordinates": [
          -101.233333,
          17.566667
        ]
      },
      "type": "Feature",
      "properties": {
        "hierarchy": [
          "tgn:7393506",
          "tgn:7005585",
          "tgn:1000001",
          "tgn:7005560",
          "tgn:7029392"
        ],
        "placetype": [
          "aat:300008347"
        ],
        "id": 7393506,
        "name:xx": "San Aparicio"
      }
    },
    {
      "geometry": {
        "type": "Point",
        "coordinates": [
          -98.783333,
          19.083333
        ]
      },
      "type": "Feature",
      "properties": {
        "hierarchy": [
          "tgn:7393507",
          "tgn:1000001",
          "tgn:1001893",
          "tgn:7005560",
          "tgn:7029392"
        ],
        "placetype": [
          "aat:300008347"
        ],
        "id": 7393507,
        "name:xx": "San Antonio Zoyatzingo"
      }
    },
    {
      "geometry": {
        "type": "Point",
        "coordinates": [
          -99,
          20.266667
        ]
      },
      "type": "Feature",
      "properties": {
        "hierarchy": [
          "tgn:7393509",
          "tgn:7005587",
          "tgn:1000001",
          "tgn:7005560",
          "tgn:7029392"
        ],
        "placetype": [
          "aat:300008347"
        ],
        "id": 7393509,
        "name:xx": "San Antonio Zaragoza"
      }
    }
  ]
}
