{
  "type": "FeatureCollection",
  "features": [
    {
      "geometry": {
        "type": "Point",
        "coordinates": [
          30.39524,
          31.209707
        ]
      },
      "type": "Feature",
      "properties": {
        "hierarchy": [
          "tgn:7531080",
          "tgn:7001242",
          "tgn:1001075",
          "tgn:7016833",
          "tgn:7029392"
        ],
        "placetype": [
          "aat:300008347"
        ],
        "name:en": "Al 'Aqarī al Baḩrīyah",
        "id": 7531080
      }
    },
    {
      "geometry": {
        "type": "Point",
        "coordinates": [
          30.412651,
          31.212159
        ]
      },
      "type": "Feature",
      "properties": {
        "hierarchy": [
          "tgn:7531081",
          "tgn:7001242",
          "tgn:1001075",
          "tgn:7016833",
          "tgn:7029392"
        ],
        "placetype": [
          "aat:300008347"
        ],
        "name:en": "'Izbat 10",
        "id": 7531081
      }
    },
    {
      "geometry": {
        "type": "Point",
        "coordinates": [
          30.402221,
          31.215664
        ]
      },
      "type": "Feature",
      "properties": {
        "hierarchy": [
          "tgn:7531082",
          "tgn:7001242",
          "tgn:1001075",
          "tgn:7016833",
          "tgn:7029392"
        ],
        "placetype": [
          "aat:300008347"
        ],
        "name:en": "'Izbat Balba'",
        "id": 7531082
      }
    },
    {
      "geometry": {
        "type": "Point",
        "coordinates": [
          30.435503,
          31.229161
        ]
      },
      "type": "Feature",
      "properties": {
        "hierarchy": [
          "tgn:7531083",
          "tgn:7001242",
          "tgn:1001075",
          "tgn:7016833",
          "tgn:7029392"
        ],
        "placetype": [
          "aat:300000206"
        ],
        "name:en": "'Izbat al Khalīj",
        "id": 7531083
      }
    },
    {
      "geometry": {
        "type": "Point",
        "coordinates": [
          30.458709,
          31.227589
        ]
      },
      "type": "Feature",
      "properties": {
        "hierarchy": [
          "tgn:7531084",
          "tgn:7001242",
          "tgn:1001075",
          "tgn:7016833",
          "tgn:7029392"
        ],
        "placetype": [
          "aat:300008347"
        ],
        "name:en": "'Izbat 16",
        "id": 7531084
      }
    },
    {
      "geometry": {
        "type": "Point",
        "coordinates": [
          30.478245,
          31.225545
        ]
      },
      "type": "Feature",
      "properties": {
        "hierarchy": [
          "tgn:7531085",
          "tgn:7001242",
          "tgn:1001075",
          "tgn:7016833",
          "tgn:7029392"
        ],
        "placetype": [
          "aat:300008347"
        ],
        "name:en": "'Izbat al Ḩajar",
        "id": 7531085
      }
    },
    {
      "geometry": {
        "type": "Point",
        "coordinates": [
          30.960833,
          30.598889
        ]
      },
      "type": "Feature",
      "properties": {
        "hierarchy": [
          "tgn:7531086",
          "tgn:7001242",
          "tgn:7016833",
          "tgn:1001087",
          "tgn:7029392"
        ],
        "placetype": [
          "aat:300006075"
        ],
        "name:en": "Jannābīyat Baḩr Sayf al Yumná",
        "id": 7531086
      }
    },
    {
      "geometry": {
        "type": "Point",
        "coordinates": [
          30.980624,
          30.561148
        ]
      },
      "type": "Feature",
      "properties": {
        "hierarchy": [
          "tgn:7531087",
          "tgn:7001242",
          "tgn:7016833",
          "tgn:7029392"
        ],
        "placetype": [
          "aat:300006075"
        ],
        "name:en": "Baḩr Sayf",
        "id": 7531087
      }
    },
    {
      "geometry": {
        "type": "Point",
        "coordinates": [
          30.484883,
          31.236279
        ]
      },
      "type": "Feature",
      "properties": {
        "hierarchy": [
          "tgn:7531088",
          "tgn:7001242",
          "tgn:1001075",
          "tgn:7016833",
          "tgn:7029392"
        ],
        "placetype": [
          "aat:300008347"
        ],
        "name:en": "'Izbat ash Shāfi'ī al Labbān",
        "id": 7531088
      }
    },
    {
      "geometry": {
        "type": "Point",
        "coordinates": [
          30.493611,
          31.248889
        ]
      },
      "type": "Feature",
      "properties": {
        "hierarchy": [
          "tgn:7531089",
          "tgn:7001242",
          "tgn:1001075",
          "tgn:7016833",
          "tgn:7029392"
        ],
        "placetype": [
          "aat:300000206"
        ],
        "name:en": "'Izbat al Minyāwī",
        "id": 7531089
      }
    }
  ]
}
