{
  "geometry": {
    "type": "Point",
    "coordinates": [
      -81.6667,
      36.0333
    ]
  },
  "type": "Feature",
  "properties": {
    "hierarchy": [
      "tgn:2660678",
      "tgn:1000001",
      "tgn:2001476",
      "tgn:7012149",
      "tgn:7007709",
      "tgn:7029392"
    ],
    "placetype": [
      "aat:300008699"
    ],
    "id": 2660678,
    "name:xx": "Shop Branch"
  }
}
