{
  "geometry": {
    "type": "Point",
    "coordinates": [
      -112.15,
      34.2333
    ]
  },
  "type": "Feature",
  "properties": {
    "hierarchy": [
      "tgn:2357450",
      "tgn:1000001",
      "tgn:7006451",
      "tgn:7012149",
      "tgn:2000103",
      "tgn:7029392"
    ],
    "placetype": [
      "aat:300008697"
    ],
    "id": 2357450,
    "name:xx": "Government Spring"
  }
}
