{
  "geometry": {
    "type": "Point",
    "coordinates": [
      125.3333,
      40.1667
    ]
  },
  "type": "Feature",
  "properties": {
    "hierarchy": [
      "tgn:1001478",
      "tgn:1000004",
      "tgn:1000122",
      "tgn:7029392"
    ],
    "placetype": [
      "aat:300387064",
      "aat:300000774"
    ],
    "name:en": "North P'yŏngan",
    "id": 1001478
  }
}
