{
  "geometry": {
    "type": "Point",
    "coordinates": [
      -82.8167,
      37.1667
    ]
  },
  "type": "Feature",
  "properties": {
    "hierarchy": [
      "tgn:2642770",
      "tgn:1000001",
      "tgn:7012149",
      "tgn:2000812",
      "tgn:7007255",
      "tgn:7029392"
    ],
    "placetype": [
      "aat:300008706"
    ],
    "id": 2642770,
    "name:xx": "Sandlick Creek"
  }
}
