{
  "geometry": {
    "type": "Point",
    "coordinates": [
      -122.4333,
      46.6833
    ]
  },
  "type": "Feature",
  "properties": {
    "hierarchy": [
      "tgn:1123388",
      "tgn:1000001",
      "tgn:7012149",
      "tgn:7007920",
      "tgn:7029392"
    ],
    "placetype": [
      "aat:300008707"
    ],
    "id": 1123388,
    "name:xx": "Deschutes"
  }
}
