{
  "geometry": {
    "type": "Point",
    "coordinates": [
      -105.95,
      45.25
    ]
  },
  "type": "Feature",
  "properties": {
    "hierarchy": [
      "tgn:2626247",
      "tgn:1000001",
      "tgn:7012149",
      "tgn:2001297",
      "tgn:7007524",
      "tgn:7029392"
    ],
    "placetype": [
      "aat:300006191"
    ],
    "id": 2626247,
    "name:xx": "Rocky Crossing Reservoir"
  }
}
