{
  "geometry": {
    "type": "Point",
    "coordinates": [
      -110.8167,
      46.35
    ]
  },
  "type": "Feature",
  "properties": {
    "hierarchy": [
      "tgn:2526226",
      "tgn:1000001",
      "tgn:7012149",
      "tgn:2001289",
      "tgn:7007524",
      "tgn:7029392"
    ],
    "placetype": [
      "aat:300008347"
    ],
    "id": 2526226,
    "name:xx": "Moss Agate"
  }
}
