{
  "type": "FeatureCollection",
  "features": [
    {
      "geometry": {
        "type": "Point",
        "coordinates": [
          10.683333,
          49.083333
        ]
      },
      "type": "Feature",
      "properties": {
        "hierarchy": [
          "tgn:7067020",
          "tgn:7003669",
          "tgn:1000003",
          "tgn:7000084",
          "tgn:7029392"
        ],
        "placetype": [
          "aat:300008347"
        ],
        "id": 7067020,
        "name:xx": "Stetten"
      }
    },
    {
      "geometry": {
        "type": "Point",
        "coordinates": [
          10,
          49.083333
        ]
      },
      "type": "Feature",
      "properties": {
        "hierarchy": [
          "tgn:7067021",
          "tgn:7003692",
          "tgn:1000003",
          "tgn:7000084",
          "tgn:7029392"
        ],
        "placetype": [
          "aat:300008347"
        ],
        "id": 7067021,
        "name:xx": "Stetten"
      }
    },
    {
      "geometry": {
        "type": "Point",
        "coordinates": [
          10.25,
          48.883333
        ]
      },
      "type": "Feature",
      "properties": {
        "hierarchy": [
          "tgn:7067022",
          "tgn:7003692",
          "tgn:1000003",
          "tgn:7000084",
          "tgn:7029392"
        ],
        "placetype": [
          "aat:300008347"
        ],
        "id": 7067022,
        "name:xx": "Stetten"
      }
    },
    {
      "geometry": {
        "type": "Point",
        "coordinates": [
          12.733333,
          48.8
        ]
      },
      "type": "Feature",
      "properties": {
        "hierarchy": [
          "tgn:7067023",
          "tgn:7003669",
          "tgn:1000003",
          "tgn:7000084",
          "tgn:7029392"
        ],
        "placetype": [
          "aat:300008347"
        ],
        "id": 7067023,
        "name:xx": "Stetten"
      }
    },
    {
      "geometry": {
        "type": "Point",
        "coordinates": [
          10.283333,
          48.766667
        ]
      },
      "type": "Feature",
      "properties": {
        "hierarchy": [
          "tgn:7067024",
          "tgn:7003692",
          "tgn:1000003",
          "tgn:7000084",
          "tgn:7029392"
        ],
        "placetype": [
          "aat:300008347"
        ],
        "id": 7067024,
        "name:xx": "Stetten"
      }
    },
    {
      "geometry": {
        "type": "Point",
        "coordinates": [
          12.416667,
          48.383333
        ]
      },
      "type": "Feature",
      "properties": {
        "hierarchy": [
          "tgn:7067025",
          "tgn:7003669",
          "tgn:1000003",
          "tgn:7000084",
          "tgn:7029392"
        ],
        "placetype": [
          "aat:300008347"
        ],
        "id": 7067025,
        "name:xx": "Stetten"
      }
    },
    {
      "geometry": {
        "type": "Point",
        "coordinates": [
          8.816667,
          48.35
        ]
      },
      "type": "Feature",
      "properties": {
        "hierarchy": [
          "tgn:7067026",
          "tgn:7003692",
          "tgn:1000003",
          "tgn:7000084",
          "tgn:7029392"
        ],
        "placetype": [
          "aat:300008347"
        ],
        "id": 7067026,
        "name:xx": "Stetten"
      }
    },
    {
      "geometry": {
        "type": "Point",
        "coordinates": [
          12.566667,
          48.316667
        ]
      },
      "type": "Feature",
      "properties": {
        "hierarchy": [
          "tgn:7067027",
          "tgn:7003669",
          "tgn:1000003",
          "tgn:7000084",
          "tgn:7029392"
        ],
        "placetype": [
          "aat:300008347"
        ],
        "id": 7067027,
        "name:xx": "Stetten"
      }
    },
    {
      "geometry": {
        "type": "Point",
        "coordinates": [
          11.383333,
          48.3
        ]
      },
      "type": "Feature",
      "properties": {
        "hierarchy": [
          "tgn:7067028",
          "tgn:7003669",
          "tgn:1000003",
          "tgn:7000084",
          "tgn:7029392"
        ],
        "placetype": [
          "aat:300008347"
        ],
        "id": 7067028,
        "name:xx": "Stetten"
      }
    },
    {
      "geometry": {
        "type": "Point",
        "coordinates": [
          9.9,
          48.283333
        ]
      },
      "type": "Feature",
      "properties": {
        "hierarchy": [
          "tgn:7067029",
          "tgn:7003692",
          "tgn:1000003",
          "tgn:7000084",
          "tgn:7029392"
        ],
        "placetype": [
          "aat:300008347"
        ],
        "id": 7067029,
        "name:xx": "Stetten"
      }
    }
  ]
}
