{
  "type": "FeatureCollection",
  "features": [
    {
      "geometry": {
        "type": "Point",
        "coordinates": [
          83.130256,
          24.447107
        ]
      },
      "type": "Feature",
      "properties": {
        "hierarchy": [
          "tgn:7576390",
          "tgn:1000004",
          "tgn:7000198",
          "tgn:7016722",
          "tgn:7029392"
        ],
        "placetype": [
          "aat:300008347"
        ],
        "name:en": "Kota",
        "id": 7576390
      }
    },
    {
      "geometry": {
        "type": "Point",
        "coordinates": [
          81.9,
          17.6
        ]
      },
      "type": "Feature",
      "properties": {
        "hierarchy": [
          "tgn:7576392",
          "tgn:1001828",
          "tgn:1000004",
          "tgn:7000198",
          "tgn:7029392"
        ],
        "placetype": [
          "aat:300008347"
        ],
        "name:en": "Kota",
        "id": 7576392
      }
    },
    {
      "geometry": {
        "type": "Point",
        "coordinates": [
          80.05,
          14.033333
        ]
      },
      "type": "Feature",
      "properties": {
        "hierarchy": [
          "tgn:7576393",
          "tgn:1001828",
          "tgn:1000004",
          "tgn:7000198",
          "tgn:7029392"
        ],
        "placetype": [
          "aat:300008347"
        ],
        "name:en": "Kota",
        "id": 7576393
      }
    },
    {
      "geometry": {
        "type": "Point",
        "coordinates": [
          74.695007,
          32.87393
        ]
      },
      "type": "Feature",
      "properties": {
        "hierarchy": [
          "tgn:7576395",
          "tgn:1000004",
          "tgn:7000198",
          "tgn:7000799",
          "tgn:7029392"
        ],
        "placetype": [
          "aat:300008347"
        ],
        "name:en": "Kot",
        "id": 7576395
      }
    },
    {
      "geometry": {
        "type": "Point",
        "coordinates": [
          77.228918,
          27.958907
        ]
      },
      "type": "Feature",
      "properties": {
        "hierarchy": [
          "tgn:7576396",
          "tgn:1000004",
          "tgn:1001871",
          "tgn:7000198",
          "tgn:7029392"
        ],
        "placetype": [
          "aat:300008347"
        ],
        "name:en": "Kot",
        "id": 7576396
      }
    },
    {
      "geometry": {
        "type": "Point",
        "coordinates": [
          73.702219,
          25.42609
        ]
      },
      "type": "Feature",
      "properties": {
        "hierarchy": [
          "tgn:7576397",
          "tgn:1000004",
          "tgn:7000198",
          "tgn:7016788",
          "tgn:7029392"
        ],
        "placetype": [
          "aat:300008347"
        ],
        "name:en": "Kot",
        "id": 7576397
      }
    },
    {
      "geometry": {
        "type": "Point",
        "coordinates": [
          82.533333,
          20.25
        ]
      },
      "type": "Feature",
      "properties": {
        "hierarchy": [
          "tgn:7576398",
          "tgn:1000004",
          "tgn:7031781",
          "tgn:7000198",
          "tgn:7029392"
        ],
        "placetype": [
          "aat:300008347"
        ],
        "name:en": "Kot",
        "id": 7576398
      }
    },
    {
      "geometry": {
        "type": "Point",
        "coordinates": [
          78.233333,
          8.866667
        ]
      },
      "type": "Feature",
      "properties": {
        "hierarchy": [
          "tgn:7576399",
          "tgn:1000004",
          "tgn:7000198",
          "tgn:7001797",
          "tgn:7029392"
        ],
        "placetype": [
          "aat:300008791"
        ],
        "name:en": "Koswari Island",
        "id": 7576399
      }
    }
  ]
}
