{
  "geometry": {
    "type": "Point",
    "coordinates": [
      75.693649,
      21.094687
    ]
  },
  "type": "Feature",
  "properties": {
    "hierarchy": [
      "tgn:7580443",
      "tgn:1000004",
      "tgn:7000198",
      "tgn:1001895",
      "tgn:7029392"
    ],
    "placetype": [
      "aat:300008699"
    ],
    "name:en": "Vāghur River",
    "id": 7580443
  }
}
