{
  "geometry": {
    "type": "Point",
    "coordinates": [
      -109.3167,
      33.95
    ]
  },
  "type": "Feature",
  "properties": {
    "hierarchy": [
      "tgn:2421538",
      "tgn:2000090",
      "tgn:1000001",
      "tgn:7006451",
      "tgn:7012149",
      "tgn:7029392"
    ],
    "placetype": [
      "aat:300008905"
    ],
    "id": 2421538,
    "name:xx": "Jessie Spring Marsh"
  }
}
