{
  "geometry": {
    "type": "Point",
    "coordinates": [
      -95.8667,
      28.9167
    ]
  },
  "type": "Feature",
  "properties": {
    "hierarchy": [
      "tgn:2578184",
      "tgn:1000001",
      "tgn:7012149",
      "tgn:1002646",
      "tgn:7007826",
      "tgn:7029392"
    ],
    "placetype": [
      "aat:300008706"
    ],
    "id": 2578184,
    "name:xx": "Peyton Creek"
  }
}
