{
  "geometry": {
    "type": "Point",
    "coordinates": [
      104.4667,
      12.5333
    ]
  },
  "type": "Feature",
  "properties": {
    "hierarchy": [
      "tgn:1129278",
      "tgn:1000004",
      "tgn:1000109",
      "tgn:7029392"
    ],
    "placetype": [
      "aat:300008707"
    ],
    "id": 1129278,
    "name:xx": "Sên, Stœng"
  }
}
