{
  "type": "FeatureCollection",
  "features": [
    {
      "geometry": {
        "type": "Point",
        "coordinates": [
          108.2333,
          15.8
        ]
      },
      "type": "Feature",
      "properties": {
        "hierarchy": [
          "tgn:6006044",
          "tgn:1000004",
          "tgn:7001056",
          "tgn:1000145",
          "tgn:7029392"
        ],
        "placetype": [
          "aat:300008347",
          "aat:300008375",
          "aat:300386830"
        ],
        "id": 6006044,
        "name:xx": "Trà Kiều Tây"
      }
    },
    {
      "geometry": {
        "type": "Point",
        "coordinates": [
          29.25,
          47.333333
        ]
      },
      "type": "Feature",
      "properties": {
        "hierarchy": [
          "tgn:6006048",
          "tgn:1000003",
          "tgn:7006656",
          "tgn:7029392"
        ],
        "placetype": [
          "aat:300387346"
        ],
        "id": 6006048,
        "name:xx": "Transnistria"
      }
    }
  ]
}
