{
  "geometry": {
    "type": "Point",
    "coordinates": [
      -123.6833,
      41.8833
    ]
  },
  "type": "Feature",
  "properties": {
    "hierarchy": [
      "tgn:2196313",
      "tgn:1000001",
      "tgn:7012149",
      "tgn:2000180",
      "tgn:7007157",
      "tgn:7029392"
    ],
    "placetype": [
      "aat:300008798"
    ],
    "id": 2196313,
    "name:xx": "Broken Rib Mountain"
  }
}
