{
  "geometry": {
    "type": "Point",
    "coordinates": [
      -103.05,
      44.5667
    ]
  },
  "type": "Feature",
  "properties": {
    "hierarchy": [
      "tgn:2317957",
      "tgn:1000001",
      "tgn:2001816",
      "tgn:7012149",
      "tgn:7007713",
      "tgn:7029392"
    ],
    "placetype": [
      "aat:300008798"
    ],
    "id": 2317957,
    "name:xx": "Englishman Butte"
  }
}
