{
  "geometry": {
    "type": "Point",
    "coordinates": [
      -71.1833,
      41.55
    ]
  },
  "type": "Feature",
  "properties": {
    "hierarchy": [
      "tgn:2543061",
      "tgn:1002716",
      "tgn:1000001",
      "tgn:7012149",
      "tgn:7007711",
      "tgn:7029392"
    ],
    "placetype": [
      "aat:300006191"
    ],
    "id": 2543061,
    "name:xx": "Nonquit Pond"
  }
}
