{
  "geometry": {
    "type": "Point",
    "coordinates": [
      -107.5333,
      34.7667
    ]
  },
  "type": "Feature",
  "properties": {
    "hierarchy": [
      "tgn:2170755",
      "tgn:1000001",
      "tgn:2001431",
      "tgn:7012149",
      "tgn:7007566",
      "tgn:7029392"
    ],
    "placetype": [
      "aat:300008699"
    ],
    "id": 2170755,
    "name:xx": "Big Sandy Wash"
  }
}
