{
  "geometry": {
    "type": "Point",
    "coordinates": [
      -101.7833,
      30.1333
    ]
  },
  "type": "Feature",
  "properties": {
    "hierarchy": [
      "tgn:2561581",
      "tgn:1000001",
      "tgn:7012149",
      "tgn:7007826",
      "tgn:7029392"
    ],
    "placetype": [
      "aat:300008761"
    ],
    "id": 2561581,
    "name:xx": "Osman Draw"
  }
}
