{
  "geometry": {
    "type": "Point",
    "coordinates": [
      -98.0333,
      32.8167
    ]
  },
  "type": "Feature",
  "properties": {
    "hierarchy": [
      "tgn:2516664",
      "tgn:1000001",
      "tgn:7012149",
      "tgn:1002771",
      "tgn:7007826",
      "tgn:7029392"
    ],
    "placetype": [
      "aat:300006191"
    ],
    "id": 2516664,
    "name:xx": "Mineral Wells, Lake"
  }
}
