{
  "geometry": {
    "type": "Point",
    "coordinates": [
      28.616,
      -18.766
    ]
  },
  "type": "Feature",
  "properties": {
    "hierarchy": [
      "tgn:1124504",
      "tgn:7001242",
      "tgn:1000185",
      "tgn:7029392"
    ],
    "placetype": [
      "aat:300008707"
    ],
    "id": 1124504,
    "name:xx": "Gweru"
  }
}
