{
  "geometry": {
    "type": "Point",
    "coordinates": [
      -111.55,
      35.4833
    ]
  },
  "type": "Feature",
  "properties": {
    "hierarchy": [
      "tgn:2580264",
      "tgn:1000001",
      "tgn:7006451",
      "tgn:2000092",
      "tgn:7012149",
      "tgn:7029392"
    ],
    "placetype": [
      "aat:300006191"
    ],
    "id": 2580264,
    "name:xx": "Pierre Tank"
  }
}
