{
  "geometry": {
    "type": "Point",
    "coordinates": [
      -154.0167,
      60.5167
    ]
  },
  "type": "Feature",
  "properties": {
    "hierarchy": [
      "tgn:2249767",
      "tgn:7006450",
      "tgn:1000001",
      "tgn:7030517",
      "tgn:7012149",
      "tgn:7029392"
    ],
    "placetype": [
      "aat:300008706"
    ],
    "id": 2249767,
    "name:xx": "College Creek"
  }
}
