{
  "geometry": {
    "type": "Point",
    "coordinates": [
      -75.9833,
      39.0333
    ]
  },
  "type": "Feature",
  "properties": {
    "hierarchy": [
      "tgn:2719341",
      "tgn:1000001",
      "tgn:2124025",
      "tgn:7012149",
      "tgn:7007516",
      "tgn:7029392"
    ],
    "placetype": [
      "aat:300008699"
    ],
    "id": 2719341,
    "name:xx": "Three Bridges Branch"
  }
}
