{
  "geometry": {
    "type": "Point",
    "coordinates": [
      -84.35,
      38.7333
    ]
  },
  "type": "Feature",
  "properties": {
    "hierarchy": [
      "tgn:2378039",
      "tgn:1000001",
      "tgn:7012149",
      "tgn:1002778",
      "tgn:7007255",
      "tgn:7029392"
    ],
    "placetype": [
      "aat:300008706"
    ],
    "id": 2378039,
    "name:xx": "Harris Creek"
  }
}
