{
  "type": "FeatureCollection",
  "features": [
    {
      "geometry": {
        "type": "Point",
        "coordinates": [
          -106.816667,
          29.05
        ]
      },
      "type": "Feature",
      "properties": {
        "hierarchy": [
          "tgn:7372060",
          "tgn:7005581",
          "tgn:1000001",
          "tgn:7005560",
          "tgn:7029392"
        ],
        "placetype": [
          "aat:300008347"
        ],
        "id": 7372060,
        "name:xx": "Lajas"
      }
    },
    {
      "geometry": {
        "type": "Point",
        "coordinates": [
          -106.25,
          25.616667
        ]
      },
      "type": "Feature",
      "properties": {
        "hierarchy": [
          "tgn:7372061",
          "tgn:7005583",
          "tgn:1000001",
          "tgn:7005560",
          "tgn:7029392"
        ],
        "placetype": [
          "aat:300008347"
        ],
        "id": 7372061,
        "name:xx": "Lajas"
      }
    },
    {
      "geometry": {
        "type": "Point",
        "coordinates": [
          -104.683333,
          24.9
        ]
      },
      "type": "Feature",
      "properties": {
        "hierarchy": [
          "tgn:7372062",
          "tgn:7005583",
          "tgn:1000001",
          "tgn:7005560",
          "tgn:7029392"
        ],
        "placetype": [
          "aat:300008347"
        ],
        "id": 7372062,
        "name:xx": "Lajas"
      }
    },
    {
      "geometry": {
        "type": "Point",
        "coordinates": [
          -104.966667,
          21.583333
        ]
      },
      "type": "Feature",
      "properties": {
        "hierarchy": [
          "tgn:7372064",
          "tgn:1000001",
          "tgn:1001906",
          "tgn:7005560",
          "tgn:7029392"
        ],
        "placetype": [
          "aat:300008347"
        ],
        "id": 7372064,
        "name:xx": "Lajas"
      }
    },
    {
      "geometry": {
        "type": "Point",
        "coordinates": [
          -105.033333,
          21.916667
        ]
      },
      "type": "Feature",
      "properties": {
        "hierarchy": [
          "tgn:7372065",
          "tgn:1000001",
          "tgn:1001906",
          "tgn:7005560",
          "tgn:7029392"
        ],
        "placetype": [
          "aat:300008347"
        ],
        "id": 7372065,
        "name:xx": "La Jarretadera"
      }
    },
    {
      "geometry": {
        "type": "Point",
        "coordinates": [
          -100.783333,
          28.95
        ]
      },
      "type": "Feature",
      "properties": {
        "hierarchy": [
          "tgn:7372066",
          "tgn:1001853",
          "tgn:1000001",
          "tgn:7005560",
          "tgn:7029392"
        ],
        "placetype": [
          "aat:300000241"
        ],
        "id": 7372066,
        "name:xx": "Rancho La Jarita"
      }
    },
    {
      "geometry": {
        "type": "Point",
        "coordinates": [
          -104.05,
          28.766667
        ]
      },
      "type": "Feature",
      "properties": {
        "hierarchy": [
          "tgn:7372067",
          "tgn:7005581",
          "tgn:1000001",
          "tgn:7005560",
          "tgn:7029392"
        ],
        "placetype": [
          "aat:300000241"
        ],
        "id": 7372067,
        "name:xx": "Rancho La Jarita"
      }
    },
    {
      "geometry": {
        "type": "Point",
        "coordinates": [
          -98.633333,
          26.1
        ]
      },
      "type": "Feature",
      "properties": {
        "hierarchy": [
          "tgn:7372068",
          "tgn:1000001",
          "tgn:7005597",
          "tgn:7005560",
          "tgn:7029392"
        ],
        "placetype": [
          "aat:300000241"
        ],
        "id": 7372068,
        "name:xx": "Rancho La Jarita"
      }
    },
    {
      "geometry": {
        "type": "Point",
        "coordinates": [
          -110.516667,
          29.4
        ]
      },
      "type": "Feature",
      "properties": {
        "hierarchy": [
          "tgn:7372069",
          "tgn:1000001",
          "tgn:1001960",
          "tgn:7005560",
          "tgn:7029392"
        ],
        "placetype": [
          "aat:300008347"
        ],
        "id": 7372069,
        "name:xx": "La Cañada"
      }
    }
  ]
}
