{
  "geometry": {
    "type": "Point",
    "coordinates": [
      -82.4333,
      31.7833
    ]
  },
  "type": "Feature",
  "properties": {
    "hierarchy": [
      "tgn:2177831",
      "tgn:2000292",
      "tgn:1000001",
      "tgn:7012149",
      "tgn:7007248",
      "tgn:7029392"
    ],
    "placetype": [
      "aat:300008706"
    ],
    "id": 2177831,
    "name:xx": "Black Water Creek"
  }
}
