{
  "type": "FeatureCollection",
  "features": [
    {
      "geometry": {
        "type": "Point",
        "coordinates": [
          -80.8167,
          25.85
        ]
      },
      "type": "Feature",
      "properties": {
        "hierarchy": [
          "tgn:2416450",
          "tgn:1000001",
          "tgn:7012149",
          "tgn:1002314",
          "tgn:7007240",
          "tgn:7029392"
        ],
        "placetype": [
          "aat:300008791"
        ],
        "id": 2416450,
        "name:xx": "Jack Clay Hammock"
      }
    },
    {
      "geometry": {
        "type": "Point",
        "coordinates": [
          -76.4167,
          37.65
        ]
      },
      "type": "Feature",
      "properties": {
        "hierarchy": [
          "tgn:2416451",
          "tgn:1000001",
          "tgn:7012149",
          "tgn:1002575",
          "tgn:7007919",
          "tgn:7029392"
        ],
        "placetype": [
          "aat:300132316"
        ],
        "id": 2416451,
        "name:xx": "Jack Cove"
      }
    },
    {
      "geometry": {
        "type": "Point",
        "coordinates": [
          -86.2667,
          32.9833
        ]
      },
      "type": "Feature",
      "properties": {
        "hierarchy": [
          "tgn:2416452",
          "tgn:7002659",
          "tgn:1000001",
          "tgn:2000018",
          "tgn:7012149",
          "tgn:7029392"
        ],
        "placetype": [
          "aat:300008706"
        ],
        "id": 2416452,
        "name:xx": "Jack Creek"
      }
    },
    {
      "geometry": {
        "type": "Point",
        "coordinates": [
          -85.3833,
          31.6167
        ]
      },
      "type": "Feature",
      "properties": {
        "hierarchy": [
          "tgn:2416453",
          "tgn:7002659",
          "tgn:1000001",
          "tgn:7012149",
          "tgn:2000033",
          "tgn:7029392"
        ],
        "placetype": [
          "aat:300008706"
        ],
        "id": 2416453,
        "name:xx": "Jack Creek"
      }
    },
    {
      "geometry": {
        "type": "Point",
        "coordinates": [
          -86.4667,
          32.1333
        ]
      },
      "type": "Feature",
      "properties": {
        "hierarchy": [
          "tgn:2416454",
          "tgn:7002659",
          "tgn:1000001",
          "tgn:7012149",
          "tgn:2000042",
          "tgn:7029392"
        ],
        "placetype": [
          "aat:300008706"
        ],
        "id": 2416454,
        "name:xx": "Jack Creek"
      }
    },
    {
      "geometry": {
        "type": "Point",
        "coordinates": [
          -160.2167,
          67.2167
        ]
      },
      "type": "Feature",
      "properties": {
        "hierarchy": [
          "tgn:2416455",
          "tgn:7006450",
          "tgn:1000001",
          "tgn:7012149",
          "tgn:2124014",
          "tgn:7029392"
        ],
        "placetype": [
          "aat:300008706"
        ],
        "id": 2416455,
        "name:xx": "Jack Creek"
      }
    },
    {
      "geometry": {
        "type": "Point",
        "coordinates": [
          -143.2333,
          62.5
        ]
      },
      "type": "Feature",
      "properties": {
        "hierarchy": [
          "tgn:2416456",
          "tgn:7006450",
          "tgn:1000001",
          "tgn:7012149",
          "tgn:2000086",
          "tgn:7029392"
        ],
        "placetype": [
          "aat:300008706"
        ],
        "id": 2416456,
        "name:xx": "Jack Creek"
      }
    },
    {
      "geometry": {
        "type": "Point",
        "coordinates": [
          -92.5333,
          34.4
        ]
      },
      "type": "Feature",
      "properties": {
        "hierarchy": [
          "tgn:2416457",
          "tgn:1000001",
          "tgn:7016172",
          "tgn:7012149",
          "tgn:2000131",
          "tgn:7029392"
        ],
        "placetype": [
          "aat:300008706"
        ],
        "id": 2416457,
        "name:xx": "Jack Creek"
      }
    },
    {
      "geometry": {
        "type": "Point",
        "coordinates": [
          -93.6,
          35.05
        ]
      },
      "type": "Feature",
      "properties": {
        "hierarchy": [
          "tgn:2416458",
          "tgn:1000001",
          "tgn:7016172",
          "tgn:7012149",
          "tgn:2000179",
          "tgn:7029392"
        ],
        "placetype": [
          "aat:300008706"
        ],
        "id": 2416458,
        "name:xx": "Jack Creek"
      }
    },
    {
      "geometry": {
        "type": "Point",
        "coordinates": [
          -91.2667,
          35.7333
        ]
      },
      "type": "Feature",
      "properties": {
        "hierarchy": [
          "tgn:2416459",
          "tgn:1000001",
          "tgn:7016172",
          "tgn:7012149",
          "tgn:2000138",
          "tgn:7029392"
        ],
        "placetype": [
          "aat:300008706"
        ],
        "id": 2416459,
        "name:xx": "Jack Creek"
      }
    }
  ]
}
