{
  "geometry": {
    "type": "Point",
    "coordinates": [
      -85.9167,
      34.15
    ]
  },
  "type": "Feature",
  "properties": {
    "hierarchy": [
      "tgn:2005440",
      "tgn:7002659",
      "tgn:1000001",
      "tgn:7012149",
      "tgn:2000027",
      "tgn:7029392"
    ],
    "placetype": [
      "aat:300008347",
      "aat:300387210"
    ],
    "id": 2005440,
    "name:xx": "Tabor"
  }
}
