{
  "geometry": {
    "type": "Point",
    "coordinates": [
      -101.55,
      44.5333
    ]
  },
  "type": "Feature",
  "properties": {
    "hierarchy": [
      "tgn:2160489",
      "tgn:1000001",
      "tgn:2001797",
      "tgn:7012149",
      "tgn:7007713",
      "tgn:7029392"
    ],
    "placetype": [
      "aat:300008697"
    ],
    "id": 2160489,
    "name:xx": "Beerwagon Spring"
  }
}
