{
  "type": "FeatureCollection",
  "features": [
    {
      "geometry": {
        "type": "Point",
        "coordinates": [
          135.6167,
          34.9167
        ]
      },
      "type": "Feature",
      "properties": {
        "hierarchy": [
          "tgn:1106090",
          "tgn:1000004",
          "tgn:1000998",
          "tgn:7000896",
          "tgn:1000120",
          "tgn:7029392"
        ],
        "placetype": [
          "aat:300008795"
        ],
        "id": 1106090,
        "name:xx": "Pompon-yama"
      }
    },
    {
      "geometry": {
        "type": "Point",
        "coordinates": [
          11.5833,
          49.4
        ]
      },
      "type": "Feature",
      "properties": {
        "hierarchy": [
          "tgn:1106094",
          "tgn:7003669",
          "tgn:1000003",
          "tgn:7000084",
          "tgn:7029392"
        ],
        "placetype": [
          "aat:300008795"
        ],
        "id": 1106094,
        "name:xx": "Poppberg"
      }
    },
    {
      "geometry": {
        "type": "Point",
        "coordinates": [
          -145.5167,
          65.5167
        ]
      },
      "type": "Feature",
      "properties": {
        "hierarchy": [
          "tgn:1106095",
          "tgn:7006450",
          "tgn:1000001",
          "tgn:7012149",
          "tgn:2000089",
          "tgn:7029392"
        ],
        "placetype": [
          "aat:300008795"
        ],
        "id": 1106095,
        "name:xx": "Porcupine Dome"
      }
    },
    {
      "geometry": {
        "type": "Point",
        "coordinates": [
          -79.45,
          38.9167
        ]
      },
      "type": "Feature",
      "properties": {
        "hierarchy": [
          "tgn:1106097",
          "tgn:1000001",
          "tgn:7012149",
          "tgn:7013961",
          "tgn:7029392"
        ],
        "placetype": [
          "aat:300008795"
        ],
        "id": 1106097,
        "name:xx": "Porte Crayon, Mount"
      }
    },
    {
      "geometry": {
        "type": "Point",
        "coordinates": [
          120.8,
          17.35
        ]
      },
      "type": "Feature",
      "properties": {
        "hierarchy": [
          "tgn:1106098",
          "tgn:1001057",
          "tgn:1000004",
          "tgn:1000135",
          "tgn:7029392"
        ],
        "placetype": [
          "aat:300008795"
        ],
        "id": 1106098,
        "name:xx": "Posooy, Mount"
      }
    },
    {
      "geometry": {
        "type": "Point",
        "coordinates": [
          -100.216667,
          24.866667
        ]
      },
      "type": "Feature",
      "properties": {
        "hierarchy": [
          "tgn:1106099",
          "tgn:1000001",
          "tgn:7005589",
          "tgn:7005560",
          "tgn:7029392"
        ],
        "placetype": [
          "aat:300008795"
        ],
        "id": 1106099,
        "name:xx": "Potosí, Cerro"
      }
    }
  ]
}
