{
  "geometry": {
    "type": "Point",
    "coordinates": [
      -96.7667,
      43.0833
    ]
  },
  "type": "Feature",
  "properties": {
    "hierarchy": [
      "tgn:2180026",
      "tgn:1000001",
      "tgn:7012149",
      "tgn:7007713",
      "tgn:7029392"
    ],
    "placetype": [
      "aat:300008706"
    ],
    "id": 2180026,
    "name:xx": "Blind Creek"
  }
}
