{
  "geometry": {
    "type": "Point",
    "coordinates": [
      -122.2333,
      44.9333
    ]
  },
  "type": "Feature",
  "properties": {
    "hierarchy": [
      "tgn:2427937",
      "tgn:1000001",
      "tgn:1002270",
      "tgn:7012149",
      "tgn:7007708",
      "tgn:7029392"
    ],
    "placetype": [
      "aat:300008680"
    ],
    "id": 2427937,
    "name:xx": "Joyce Lake"
  }
}
