{
  "geometry": {
    "type": "Point",
    "coordinates": [
      15.8667,
      49.5667
    ]
  },
  "type": "Feature",
  "properties": {
    "hierarchy": [
      "tgn:4009541",
      "tgn:1003530",
      "tgn:1000003",
      "tgn:1001780",
      "tgn:7029392"
    ],
    "placetype": [
      "aat:300008347"
    ],
    "id": 4009541,
    "name:xx": "Sázava"
  }
}
