{
  "geometry": {
    "type": "Point",
    "coordinates": [
      79.422888,
      24.88589
    ]
  },
  "type": "Feature",
  "properties": {
    "hierarchy": [
      "tgn:7564121",
      "tgn:1000004",
      "tgn:7000198",
      "tgn:1001894",
      "tgn:7029392"
    ],
    "placetype": [
      "aat:300008347"
    ],
    "name:en": "Pahārgaon",
    "id": 7564121
  }
}
