{
  "type": "FeatureCollection",
  "features": [
    {
      "geometry": {
        "type": "Point",
        "coordinates": [
          -98.183333,
          23.583333
        ]
      },
      "type": "Feature",
      "properties": {
        "hierarchy": [
          "tgn:7439330",
          "tgn:1000001",
          "tgn:7005597",
          "tgn:7005560",
          "tgn:7029392"
        ],
        "placetype": [
          "aat:300387033"
        ],
        "id": 7439330,
        "name:xx": "Tecolote"
      }
    },
    {
      "geometry": {
        "type": "Point",
        "coordinates": [
          -114.983333,
          32.583333
        ]
      },
      "type": "Feature",
      "properties": {
        "hierarchy": [
          "tgn:7439331",
          "tgn:1001835",
          "tgn:1000001",
          "tgn:7005560",
          "tgn:7029392"
        ],
        "placetype": [
          "aat:300007783"
        ],
        "id": 7439331,
        "name:xx": "Tecolote"
      }
    },
    {
      "geometry": {
        "type": "Point",
        "coordinates": [
          -111.566667,
          29.766667
        ]
      },
      "type": "Feature",
      "properties": {
        "hierarchy": [
          "tgn:7439332",
          "tgn:1000001",
          "tgn:1001960",
          "tgn:7005560",
          "tgn:7029392"
        ],
        "placetype": [
          "aat:300008347"
        ],
        "id": 7439332,
        "name:xx": "Tecolote"
      }
    },
    {
      "geometry": {
        "type": "Point",
        "coordinates": [
          -110.55,
          29.35
        ]
      },
      "type": "Feature",
      "properties": {
        "hierarchy": [
          "tgn:7439333",
          "tgn:1000001",
          "tgn:1001960",
          "tgn:7005560",
          "tgn:7029392"
        ],
        "placetype": [
          "aat:300008347"
        ],
        "id": 7439333,
        "name:xx": "Tecolote"
      }
    },
    {
      "geometry": {
        "type": "Point",
        "coordinates": [
          -105.866667,
          27.533333
        ]
      },
      "type": "Feature",
      "properties": {
        "hierarchy": [
          "tgn:7439334",
          "tgn:7005581",
          "tgn:1000001",
          "tgn:7005560",
          "tgn:7029392"
        ],
        "placetype": [
          "aat:300008347"
        ],
        "id": 7439334,
        "name:xx": "Tecolote"
      }
    },
    {
      "geometry": {
        "type": "Point",
        "coordinates": [
          -101.4,
          27.25
        ]
      },
      "type": "Feature",
      "properties": {
        "hierarchy": [
          "tgn:7439335",
          "tgn:1001853",
          "tgn:1000001",
          "tgn:7005560",
          "tgn:7029392"
        ],
        "placetype": [
          "aat:300008347"
        ],
        "id": 7439335,
        "name:xx": "Tecolote"
      }
    },
    {
      "geometry": {
        "type": "Point",
        "coordinates": [
          -101.433333,
          24.916667
        ]
      },
      "type": "Feature",
      "properties": {
        "hierarchy": [
          "tgn:7439336",
          "tgn:1001853",
          "tgn:1000001",
          "tgn:7005560",
          "tgn:7029392"
        ],
        "placetype": [
          "aat:300008347"
        ],
        "id": 7439336,
        "name:xx": "Tecolote"
      }
    },
    {
      "geometry": {
        "type": "Point",
        "coordinates": [
          -105.783333,
          24.433333
        ]
      },
      "type": "Feature",
      "properties": {
        "hierarchy": [
          "tgn:7439337",
          "tgn:7005583",
          "tgn:1000001",
          "tgn:7005560",
          "tgn:7029392"
        ],
        "placetype": [
          "aat:300008347"
        ],
        "id": 7439337,
        "name:xx": "Tecolote"
      }
    },
    {
      "geometry": {
        "type": "Point",
        "coordinates": [
          -100.35,
          22.116667
        ]
      },
      "type": "Feature",
      "properties": {
        "hierarchy": [
          "tgn:7439338",
          "tgn:1000001",
          "tgn:7005594",
          "tgn:7005560",
          "tgn:7029392"
        ],
        "placetype": [
          "aat:300008347"
        ],
        "id": 7439338,
        "name:xx": "Tecolote"
      }
    },
    {
      "geometry": {
        "type": "Point",
        "coordinates": [
          -98.883333,
          18.833333
        ]
      },
      "type": "Feature",
      "properties": {
        "hierarchy": [
          "tgn:7439339",
          "tgn:1000001",
          "tgn:7005588",
          "tgn:7005560",
          "tgn:7029392"
        ],
        "placetype": [
          "aat:300008347"
        ],
        "id": 7439339,
        "name:xx": "Tecolote"
      }
    }
  ]
}
