{
  "geometry": {
    "type": "Point",
    "coordinates": [
      -90.5333,
      38.45
    ]
  },
  "type": "Feature",
  "properties": {
    "hierarchy": [
      "tgn:2154210",
      "tgn:1000001",
      "tgn:7012149",
      "tgn:1002517",
      "tgn:7007523",
      "tgn:7029392"
    ],
    "placetype": [
      "aat:300008706"
    ],
    "id": 2154210,
    "name:xx": "Bear Creek"
  }
}
