{
  "geometry": {
    "type": "Point",
    "coordinates": [
      -95.1167,
      32.9833
    ]
  },
  "type": "Feature",
  "properties": {
    "hierarchy": [
      "tgn:2570854",
      "tgn:1000001",
      "tgn:7012149",
      "tgn:1002230",
      "tgn:7007826",
      "tgn:7029392"
    ],
    "placetype": [
      "aat:300008699"
    ],
    "id": 2570854,
    "name:xx": "Patterson Branch"
  }
}
