{
  "geometry": {
    "type": "Point",
    "coordinates": [
      88.5525,
      22.293889
    ]
  },
  "type": "Feature",
  "properties": {
    "hierarchy": [
      "tgn:7588413",
      "tgn:1000004",
      "tgn:7000198",
      "tgn:1001977",
      "tgn:7029392"
    ],
    "placetype": [
      "aat:300008347"
    ],
    "name:en": "Davis Abāo",
    "id": 7588413
  }
}
