{
  "geometry": {
    "type": "Point",
    "coordinates": [
      -83.0333,
      43.2333
    ]
  },
  "type": "Feature",
  "properties": {
    "hierarchy": [
      "tgn:2502160",
      "tgn:1000001",
      "tgn:7012149",
      "tgn:1002576",
      "tgn:7007520",
      "tgn:7029392"
    ],
    "placetype": [
      "aat:300006075"
    ],
    "id": 2502160,
    "name:xx": "McKimmon Drain"
  }
}
