{
  "geometry": {
    "type": "Point",
    "coordinates": [
      -91.9833,
      38.8333
    ]
  },
  "type": "Feature",
  "properties": {
    "hierarchy": [
      "tgn:2786256",
      "tgn:1000001",
      "tgn:1002223",
      "tgn:7012149",
      "tgn:7007523",
      "tgn:7029392"
    ],
    "placetype": [
      "aat:300008706"
    ],
    "id": 2786256,
    "name:xx": "Youngs Creek"
  }
}
