{
  "geometry": {
    "type": "Point",
    "coordinates": [
      25.35,
      29.25
    ]
  },
  "type": "Feature",
  "properties": {
    "hierarchy": [
      "tgn:7526485",
      "tgn:7001242",
      "tgn:7016833",
      "tgn:1001418",
      "tgn:7029392"
    ],
    "placetype": [
      "aat:300008697"
    ],
    "name:en": "Tāzţiftī, 'Ayn",
    "id": 7526485
  }
}
