{
  "geometry": {
    "type": "Point",
    "coordinates": [
      -116.4167,
      44.05
    ]
  },
  "type": "Feature",
  "properties": {
    "hierarchy": [
      "tgn:2623535",
      "tgn:1000001",
      "tgn:7012149",
      "tgn:2000474",
      "tgn:7007250",
      "tgn:7029392"
    ],
    "placetype": [
      "aat:300008706"
    ],
    "id": 2623535,
    "name:xx": "Rock Creek"
  }
}
