{
  "geometry": {
    "type": "Point",
    "coordinates": [
      -108.6667,
      44.8333
    ]
  },
  "type": "Feature",
  "properties": {
    "hierarchy": [
      "tgn:2491003",
      "tgn:1000001",
      "tgn:7012149",
      "tgn:7007923",
      "tgn:7029392"
    ],
    "placetype": [
      "aat:300008761"
    ],
    "id": 2491003,
    "name:xx": "Mantua Draw"
  }
}
