{
  "geometry": {
    "type": "Point",
    "coordinates": [
      -104.3833,
      44.5333
    ]
  },
  "type": "Feature",
  "properties": {
    "hierarchy": [
      "tgn:2549158",
      "tgn:1000001",
      "tgn:2002370",
      "tgn:7012149",
      "tgn:7007923",
      "tgn:7029392"
    ],
    "placetype": [
      "aat:300008706"
    ],
    "id": 2549158,
    "name:xx": "North Redwater Creek"
  }
}
