{
  "geometry": {
    "type": "Point",
    "coordinates": [
      -88.0667,
      33.4667
    ]
  },
  "type": "Feature",
  "properties": {
    "hierarchy": [
      "tgn:2236509",
      "tgn:7002659",
      "tgn:1000001",
      "tgn:7012149",
      "tgn:2000053",
      "tgn:7029392"
    ],
    "placetype": [
      "aat:300008699"
    ],
    "id": 2236509,
    "name:xx": "Chicken Swamp Branch"
  }
}
