{
  "geometry": {
    "type": "Point",
    "coordinates": [
      -123.3333,
      43.05
    ]
  },
  "type": "Feature",
  "properties": {
    "hierarchy": [
      "tgn:2632910",
      "tgn:1000001",
      "tgn:7012149",
      "tgn:2001706",
      "tgn:7007708",
      "tgn:7029392"
    ],
    "placetype": [
      "aat:300008347"
    ],
    "id": 2632910,
    "name:xx": "Ruckles"
  }
}
