{
  "geometry": {
    "type": "Point",
    "coordinates": [
      -103.7167,
      43.75
    ]
  },
  "type": "Feature",
  "properties": {
    "hierarchy": [
      "tgn:2751777",
      "tgn:1000001",
      "tgn:2001786",
      "tgn:7012149",
      "tgn:7007713",
      "tgn:7029392"
    ],
    "placetype": [
      "aat:300008697"
    ],
    "id": 2751777,
    "name:xx": "Warren Gulch Spring"
  }
}
