{
  "type": "FeatureCollection",
  "features": [
    {
      "geometry": {
        "type": "Point",
        "coordinates": [
          -95,
          32.55
        ]
      },
      "type": "Feature",
      "properties": {
        "hierarchy": [
          "tgn:2108544",
          "tgn:1000001",
          "tgn:7012149",
          "tgn:1002966",
          "tgn:7007826",
          "tgn:7029392"
        ],
        "placetype": [
          "aat:300008347"
        ],
        "id": 2108544,
        "name:xx": "Wilkins"
      }
    },
    {
      "geometry": {
        "type": "Point",
        "coordinates": [
          -94.95,
          33.3333
        ]
      },
      "type": "Feature",
      "properties": {
        "hierarchy": [
          "tgn:2108545",
          "tgn:1000001",
          "tgn:7012149",
          "tgn:1002948",
          "tgn:7007826",
          "tgn:7029392"
        ],
        "placetype": [
          "aat:300008347"
        ],
        "id": 2108545,
        "name:xx": "Wilkinson"
      }
    },
    {
      "geometry": {
        "type": "Point",
        "coordinates": [
          -97.7833,
          26.4333
        ]
      },
      "type": "Feature",
      "properties": {
        "hierarchy": [
          "tgn:2108546",
          "tgn:1000001",
          "tgn:7012149",
          "tgn:2002094",
          "tgn:7007826",
          "tgn:7029392"
        ],
        "placetype": [
          "aat:300008347"
        ],
        "id": 2108546,
        "name:xx": "Willacy County Housing Authority"
      }
    },
    {
      "geometry": {
        "type": "Point",
        "coordinates": [
          -97.6167,
          26.45
        ]
      },
      "type": "Feature",
      "properties": {
        "hierarchy": [
          "tgn:2108547",
          "tgn:1000001",
          "tgn:7012149",
          "tgn:2002094",
          "tgn:7007826",
          "tgn:7029392"
        ],
        "placetype": [
          "aat:300008347",
          "aat:300387210"
        ],
        "id": 2108547,
        "name:xx": "Willamar"
      }
    },
    {
      "geometry": {
        "type": "Point",
        "coordinates": [
          -96.2667,
          30.3
        ]
      },
      "type": "Feature",
      "properties": {
        "hierarchy": [
          "tgn:2108548",
          "tgn:1000001",
          "tgn:7012149",
          "tgn:1002997",
          "tgn:7007826",
          "tgn:7029392"
        ],
        "placetype": [
          "aat:300008347",
          "aat:300387210"
        ],
        "id": 2108548,
        "name:xx": "William Penn"
      }
    },
    {
      "geometry": {
        "type": "Point",
        "coordinates": [
          -99.0167,
          32.0167
        ]
      },
      "type": "Feature",
      "properties": {
        "hierarchy": [
          "tgn:2108549",
          "tgn:1000001",
          "tgn:2001948",
          "tgn:7012149",
          "tgn:7007826",
          "tgn:7029392"
        ],
        "placetype": [
          "aat:300008347",
          "aat:300387210"
        ],
        "id": 2108549,
        "name:xx": "Williams"
      }
    }
  ]
}
