{
  "geometry": {
    "type": "Point",
    "coordinates": [
      10.85,
      47.566667
    ]
  },
  "type": "Feature",
  "properties": {
    "hierarchy": [
      "tgn:7155758",
      "tgn:7003669",
      "tgn:1000003",
      "tgn:7000084",
      "tgn:7029392"
    ],
    "placetype": [
      "aat:300008795"
    ],
    "id": 7155758,
    "name:xx": "Kenzen-Köpfel"
  }
}
