{
  "geometry": {
    "type": "Point",
    "coordinates": [
      -80.6833,
      40.65
    ]
  },
  "type": "Feature",
  "properties": {
    "hierarchy": [
      "tgn:2079742",
      "tgn:1000001",
      "tgn:1002295",
      "tgn:7012149",
      "tgn:7007706",
      "tgn:7029392"
    ],
    "placetype": [
      "aat:300008347"
    ],
    "id": 2079742,
    "name:xx": "Glasgow"
  }
}
