{
  "geometry": {
    "type": "Point",
    "coordinates": [
      -74.3333,
      42.4333
    ]
  },
  "type": "Feature",
  "properties": {
    "hierarchy": [
      "tgn:2404458",
      "tgn:1000001",
      "tgn:7012149",
      "tgn:1002873",
      "tgn:7007568",
      "tgn:7029392"
    ],
    "placetype": [
      "aat:300008798"
    ],
    "id": 2404458,
    "name:xx": "Hubbard Hill"
  }
}
