{
  "geometry": {
    "type": "Point",
    "coordinates": [
      -94.1667,
      36.0833
    ]
  },
  "type": "Feature",
  "properties": {
    "hierarchy": [
      "tgn:2373535",
      "tgn:1000001",
      "tgn:7016172",
      "tgn:7012149",
      "tgn:2000176",
      "tgn:7029392"
    ],
    "placetype": [
      "aat:300008706"
    ],
    "id": 2373535,
    "name:xx": "Hamestring Creek"
  }
}
