{
  "type": "FeatureCollection",
  "features": [
    {
      "geometry": {
        "type": "Point",
        "coordinates": [
          12.916667,
          50.7
        ]
      },
      "type": "Feature",
      "properties": {
        "hierarchy": [
          "tgn:7069520",
          "tgn:1000003",
          "tgn:7003685",
          "tgn:7000084",
          "tgn:7029392"
        ],
        "placetype": [
          "aat:300008863"
        ],
        "id": 7069520,
        "name:xx": "Thum, Forst"
      }
    },
    {
      "geometry": {
        "type": "Point",
        "coordinates": [
          6.516667,
          50.7
        ]
      },
      "type": "Feature",
      "properties": {
        "hierarchy": [
          "tgn:7069521",
          "tgn:1000003",
          "tgn:7003677",
          "tgn:7000084",
          "tgn:7029392"
        ],
        "placetype": [
          "aat:300008347"
        ],
        "id": 7069521,
        "name:xx": "Thum"
      }
    },
    {
      "geometry": {
        "type": "Point",
        "coordinates": [
          7.9,
          52.933333
        ]
      },
      "type": "Feature",
      "properties": {
        "hierarchy": [
          "tgn:7069523",
          "tgn:1000003",
          "tgn:7003676",
          "tgn:7000084",
          "tgn:7029392"
        ],
        "placetype": [
          "aat:300008863"
        ],
        "id": 7069523,
        "name:xx": "Thülswald"
      }
    },
    {
      "geometry": {
        "type": "Point",
        "coordinates": [
          7.933333,
          52.933333
        ]
      },
      "type": "Feature",
      "properties": {
        "hierarchy": [
          "tgn:7069524",
          "tgn:1000003",
          "tgn:7003676",
          "tgn:7000084",
          "tgn:7029392"
        ],
        "placetype": [
          "aat:300006191"
        ],
        "id": 7069524,
        "name:xx": "Thülsfelder Stausee"
      }
    },
    {
      "geometry": {
        "type": "Point",
        "coordinates": [
          7.933333,
          52.933333
        ]
      },
      "type": "Feature",
      "properties": {
        "hierarchy": [
          "tgn:7069525",
          "tgn:1000003",
          "tgn:7003676",
          "tgn:7000084",
          "tgn:7029392"
        ],
        "placetype": [
          "aat:300008347"
        ],
        "id": 7069525,
        "name:xx": "Thülsfeld"
      }
    },
    {
      "geometry": {
        "type": "Point",
        "coordinates": [
          12.3,
          54.1
        ]
      },
      "type": "Feature",
      "properties": {
        "hierarchy": [
          "tgn:7069526",
          "tgn:1000003",
          "tgn:7000094",
          "tgn:7000084",
          "tgn:7029392"
        ],
        "placetype": [
          "aat:300008347"
        ],
        "id": 7069526,
        "name:xx": "Thulendorf"
      }
    },
    {
      "geometry": {
        "type": "Point",
        "coordinates": [
          8.65,
          51.416667
        ]
      },
      "type": "Feature",
      "properties": {
        "hierarchy": [
          "tgn:7069527",
          "tgn:1000003",
          "tgn:7003677",
          "tgn:7000084",
          "tgn:7029392"
        ],
        "placetype": [
          "aat:300008347"
        ],
        "id": 7069527,
        "name:xx": "Thülen"
      }
    },
    {
      "geometry": {
        "type": "Point",
        "coordinates": [
          8.583333,
          51.716667
        ]
      },
      "type": "Feature",
      "properties": {
        "hierarchy": [
          "tgn:7069528",
          "tgn:1000003",
          "tgn:7003677",
          "tgn:7000084",
          "tgn:7029392"
        ],
        "placetype": [
          "aat:300008347"
        ],
        "id": 7069528,
        "name:xx": "Thüle"
      }
    },
    {
      "geometry": {
        "type": "Point",
        "coordinates": [
          11.966667,
          48.516667
        ]
      },
      "type": "Feature",
      "properties": {
        "hierarchy": [
          "tgn:7069529",
          "tgn:7003669",
          "tgn:1000003",
          "tgn:7000084",
          "tgn:7029392"
        ],
        "placetype": [
          "aat:300008347"
        ],
        "id": 7069529,
        "name:xx": "Thulbach"
      }
    }
  ]
}
