{
  "geometry": {
    "type": "Point",
    "coordinates": [
      -99.3167,
      33.4833
    ]
  },
  "type": "Feature",
  "properties": {
    "hierarchy": [
      "tgn:2495480",
      "tgn:1000001",
      "tgn:2001939",
      "tgn:7012149",
      "tgn:7007826",
      "tgn:7029392"
    ],
    "placetype": [
      "aat:300008706"
    ],
    "id": 2495480,
    "name:xx": "Marys Creek"
  }
}
