{
  "geometry": {
    "type": "Point",
    "coordinates": [
      -88.75,
      45.15
    ]
  },
  "type": "Feature",
  "properties": {
    "hierarchy": [
      "tgn:2766237",
      "tgn:1000001",
      "tgn:7012149",
      "tgn:2002333",
      "tgn:7007922",
      "tgn:7029392"
    ],
    "placetype": [
      "aat:300008706"
    ],
    "id": 2766237,
    "name:xx": "White Lake Creek"
  }
}
