{
  "geometry": {
    "type": "Point",
    "coordinates": [
      -89.9167,
      39.0667
    ]
  },
  "type": "Feature",
  "properties": {
    "hierarchy": [
      "tgn:2564747",
      "tgn:1000001",
      "tgn:7012149",
      "tgn:7007251",
      "tgn:7029392"
    ],
    "placetype": [
      "aat:300008706"
    ],
    "id": 2564747,
    "name:xx": "Paddock Creek"
  }
}
