{
  "geometry": {
    "type": "Point",
    "coordinates": [
      -121.85,
      37.0167
    ]
  },
  "type": "Feature",
  "properties": {
    "hierarchy": [
      "tgn:2155888",
      "tgn:1000001",
      "tgn:7012149",
      "tgn:7007157",
      "tgn:1002869",
      "tgn:7029392"
    ],
    "placetype": [
      "aat:300008761"
    ],
    "id": 2155888,
    "name:xx": "Bear Valley"
  }
}
