{
  "type": "FeatureCollection",
  "features": [
    {
      "geometry": {
        "type": "Point",
        "coordinates": [
          168,
          -84
        ]
      },
      "type": "Feature",
      "properties": {
        "hierarchy": [
          "tgn:1110130",
          "tgn:1000007",
          "tgn:7029392"
        ],
        "placetype": [
          "aat:300386831"
        ],
        "id": 1110130,
        "name:xx": "Queen Alexandra Range"
      }
    },
    {
      "geometry": {
        "type": "Point",
        "coordinates": [
          43.5,
          42.5
        ]
      },
      "type": "Feature",
      "properties": {
        "hierarchy": [
          "tgn:1110131",
          "tgn:1000004",
          "tgn:7006653",
          "tgn:7029392"
        ],
        "placetype": [
          "aat:300386831"
        ],
        "id": 1110131,
        "name:xx": "Rachinskiy Khrebet"
      }
    },
    {
      "geometry": {
        "type": "Point",
        "coordinates": [
          178.033333,
          -37.783333
        ]
      },
      "type": "Feature",
      "properties": {
        "hierarchy": [
          "tgn:1110133",
          "tgn:1008380",
          "tgn:1000226",
          "tgn:1000006",
          "tgn:7029392"
        ],
        "placetype": [
          "aat:300386831",
          "aat:300008795"
        ],
        "name:en": "Raukumara Range",
        "id": 1110133
      }
    },
    {
      "geometry": {
        "type": "Point",
        "coordinates": [
          59.4167,
          33.5
        ]
      },
      "type": "Feature",
      "properties": {
        "hierarchy": [
          "tgn:1110135",
          "tgn:1000004",
          "tgn:7002004",
          "tgn:7000231",
          "tgn:7029392"
        ],
        "placetype": [
          "aat:300386831"
        ],
        "id": 1110135,
        "name:xx": "Razāq, Kūh-e"
      }
    },
    {
      "geometry": {
        "type": "Point",
        "coordinates": [
          170.633333,
          -43.866667
        ]
      },
      "type": "Feature",
      "properties": {
        "hierarchy": [
          "tgn:1110136",
          "tgn:1009227",
          "tgn:1000226",
          "tgn:1000006",
          "tgn:7029392"
        ],
        "placetype": [
          "aat:300386831",
          "aat:300008795"
        ],
        "name:en": "Richmond Range",
        "id": 1110136
      }
    }
  ]
}
