{
  "geometry": {
    "type": "Point",
    "coordinates": [
      -84.2833,
      31.45
    ]
  },
  "type": "Feature",
  "properties": {
    "hierarchy": [
      "tgn:2167755",
      "tgn:1000001",
      "tgn:7012149",
      "tgn:2000338",
      "tgn:7007248",
      "tgn:7029392"
    ],
    "placetype": [
      "aat:300008680"
    ],
    "id": 2167755,
    "name:xx": "Big Cypress Lake"
  }
}
