{
  "geometry": {
    "type": "Point",
    "coordinates": [
      -78.8333,
      38.7833
    ]
  },
  "type": "Feature",
  "properties": {
    "hierarchy": [
      "tgn:2697280",
      "tgn:1000001",
      "tgn:7012149",
      "tgn:2002190",
      "tgn:7007919",
      "tgn:7029392"
    ],
    "placetype": [
      "aat:300008706"
    ],
    "id": 2697280,
    "name:xx": "Stony Creek"
  }
}
