{
  "geometry": {
    "type": "Point",
    "coordinates": [
      8.6667,
      35.5833
    ]
  },
  "type": "Feature",
  "properties": {
    "hierarchy": [
      "tgn:1095010",
      "tgn:7001242",
      "tgn:1002089",
      "tgn:1000205",
      "tgn:7029392"
    ],
    "placetype": [
      "aat:300008347"
    ],
    "id": 1095010,
    "name:xx": "Thala"
  }
}
