{
  "geometry": {
    "type": "Point",
    "coordinates": [
      -84.5833,
      35.0667
    ]
  },
  "type": "Feature",
  "properties": {
    "hierarchy": [
      "tgn:2414266",
      "tgn:1000001",
      "tgn:7012149",
      "tgn:2001906",
      "tgn:7007825",
      "tgn:7029392"
    ],
    "placetype": [
      "aat:300008699"
    ],
    "id": 2414266,
    "name:xx": "Iron Ore Branch"
  }
}
