{
  "geometry": {
    "type": "Point",
    "coordinates": [
      -75.85,
      41.2167
    ]
  },
  "type": "Feature",
  "properties": {
    "hierarchy": [
      "tgn:2094583",
      "tgn:1000001",
      "tgn:7012149",
      "tgn:1002612",
      "tgn:7007710",
      "tgn:7029392"
    ],
    "placetype": [
      "aat:300008347"
    ],
    "id": 2094583,
    "name:xx": "Wilkes-Barre Township"
  }
}
