{
  "geometry": {
    "type": "Point",
    "coordinates": [
      -81.65,
      35.9833
    ]
  },
  "type": "Feature",
  "properties": {
    "hierarchy": [
      "tgn:2403095",
      "tgn:1000001",
      "tgn:2001476",
      "tgn:7012149",
      "tgn:7007709",
      "tgn:7029392"
    ],
    "placetype": [
      "aat:300008699"
    ],
    "id": 2403095,
    "name:xx": "House Branch"
  }
}
