{
  "geometry": {
    "type": "Point",
    "coordinates": [
      -78.2667,
      41.6333
    ]
  },
  "type": "Feature",
  "properties": {
    "hierarchy": [
      "tgn:7023502",
      "tgn:1000001",
      "tgn:7012149",
      "tgn:7007710",
      "tgn:7029392"
    ],
    "placetype": [
      "aat:300008761"
    ],
    "id": 7023502,
    "name:xx": "Stone Chimney Hollow"
  }
}
