{
  "geometry": {
    "type": "Point",
    "coordinates": [
      -93.85,
      36.5333
    ]
  },
  "type": "Feature",
  "properties": {
    "hierarchy": [
      "tgn:2652073",
      "tgn:2001170",
      "tgn:1000001",
      "tgn:7012149",
      "tgn:7007523",
      "tgn:7029392"
    ],
    "placetype": [
      "aat:300008761"
    ],
    "id": 2652073,
    "name:xx": "Seligman Hollow"
  }
}
