{
  "geometry": {
    "type": "Point",
    "coordinates": [
      -92.3167,
      40.45
    ]
  },
  "type": "Feature",
  "properties": {
    "hierarchy": [
      "tgn:2508678",
      "tgn:1000001",
      "tgn:7012149",
      "tgn:2001245",
      "tgn:7007523",
      "tgn:7029392"
    ],
    "placetype": [
      "aat:300008347"
    ],
    "id": 2508678,
    "name:xx": "Middle Fabius"
  }
}
