{
  "geometry": {
    "type": "Point",
    "coordinates": [
      -114.3833,
      48.4333
    ]
  },
  "type": "Feature",
  "properties": {
    "hierarchy": [
      "tgn:2157021",
      "tgn:1000001",
      "tgn:7012149",
      "tgn:2001274",
      "tgn:7007524",
      "tgn:7029392"
    ],
    "placetype": [
      "aat:300132316"
    ],
    "id": 2157021,
    "name:xx": "Beaver Bay"
  }
}
