{
  "geometry": {
    "type": "Point",
    "coordinates": [
      -92.3333,
      29.7333
    ]
  },
  "type": "Feature",
  "properties": {
    "hierarchy": [
      "tgn:2451710",
      "tgn:1000001",
      "tgn:7012149",
      "tgn:2000910",
      "tgn:7007256",
      "tgn:7029392"
    ],
    "placetype": [
      "aat:300008680"
    ],
    "id": 2451710,
    "name:xx": "Little Bear Lake"
  }
}
