{
  "geometry": {
    "type": "Point",
    "coordinates": [
      -85.1167,
      45.1833
    ]
  },
  "type": "Feature",
  "properties": {
    "hierarchy": [
      "tgn:2232173",
      "tgn:1000001",
      "tgn:2000950",
      "tgn:7012149",
      "tgn:7007520",
      "tgn:7029392"
    ],
    "placetype": [
      "aat:300008706"
    ],
    "id": 2232173,
    "name:xx": "Chanda Creek"
  }
}
