{
  "geometry": {
    "type": "Point",
    "coordinates": [
      -113.85,
      34.15
    ]
  },
  "type": "Feature",
  "properties": {
    "hierarchy": [
      "tgn:2536031",
      "tgn:1000001",
      "tgn:7006451",
      "tgn:7012149",
      "tgn:2000104",
      "tgn:7029392"
    ],
    "placetype": [
      "aat:300386837"
    ],
    "id": 2536031,
    "name:xx": "Natural Arch"
  }
}
