{
  "geometry": {
    "type": "Point",
    "coordinates": [
      -80.1667,
      42.0667
    ]
  },
  "type": "Feature",
  "properties": {
    "hierarchy": [
      "tgn:2138419",
      "tgn:1000001",
      "tgn:7012149",
      "tgn:1002358",
      "tgn:7007710",
      "tgn:7029392"
    ],
    "placetype": [
      "aat:300008347"
    ],
    "id": 2138419,
    "name:xx": "Asbury"
  }
}
