{
  "type": "FeatureCollection",
  "features": [
    {
      "geometry": {
        "type": "Point",
        "coordinates": [
          -115.0833,
          46.6667
        ]
      },
      "type": "Feature",
      "properties": {
        "hierarchy": [
          "tgn:2356750",
          "tgn:1000001",
          "tgn:2000469",
          "tgn:7012149",
          "tgn:7007250",
          "tgn:7029392"
        ],
        "placetype": [
          "aat:300008706"
        ],
        "id": 2356750,
        "name:xx": "Gorman Creek"
      }
    },
    {
      "geometry": {
        "type": "Point",
        "coordinates": [
          -90.25,
          30.8667
        ]
      },
      "type": "Feature",
      "properties": {
        "hierarchy": [
          "tgn:2356751",
          "tgn:1000001",
          "tgn:7012149",
          "tgn:7007256",
          "tgn:7029392"
        ],
        "placetype": [
          "aat:300008706"
        ],
        "id": 2356751,
        "name:xx": "Gorman Creek"
      }
    },
    {
      "geometry": {
        "type": "Point",
        "coordinates": [
          -92.0833,
          44.2333
        ]
      },
      "type": "Feature",
      "properties": {
        "hierarchy": [
          "tgn:2356752",
          "tgn:1000001",
          "tgn:7012149",
          "tgn:2001077",
          "tgn:7007521",
          "tgn:7029392"
        ],
        "placetype": [
          "aat:300008706"
        ],
        "id": 2356752,
        "name:xx": "Gorman Creek"
      }
    },
    {
      "geometry": {
        "type": "Point",
        "coordinates": [
          -113.1,
          45.5167
        ]
      },
      "type": "Feature",
      "properties": {
        "hierarchy": [
          "tgn:2356753",
          "tgn:1000001",
          "tgn:2001260",
          "tgn:7012149",
          "tgn:7007524",
          "tgn:7029392"
        ],
        "placetype": [
          "aat:300008706"
        ],
        "id": 2356753,
        "name:xx": "Gorman Creek"
      }
    },
    {
      "geometry": {
        "type": "Point",
        "coordinates": [
          -109.8333,
          48.2
        ]
      },
      "type": "Feature",
      "properties": {
        "hierarchy": [
          "tgn:2356754",
          "tgn:1000001",
          "tgn:2001267",
          "tgn:7012149",
          "tgn:7007524",
          "tgn:7029392"
        ],
        "placetype": [
          "aat:300008706"
        ],
        "id": 2356754,
        "name:xx": "Gorman Creek"
      }
    },
    {
      "geometry": {
        "type": "Point",
        "coordinates": [
          -118.45,
          43.5
        ]
      },
      "type": "Feature",
      "properties": {
        "hierarchy": [
          "tgn:2356755",
          "tgn:1000001",
          "tgn:7012149",
          "tgn:2001709",
          "tgn:7007708",
          "tgn:7029392"
        ],
        "placetype": [
          "aat:300008706"
        ],
        "id": 2356755,
        "name:xx": "Gorman Creek"
      }
    },
    {
      "geometry": {
        "type": "Point",
        "coordinates": [
          -98.5167,
          31.0167
        ]
      },
      "type": "Feature",
      "properties": {
        "hierarchy": [
          "tgn:2356756",
          "tgn:1000001",
          "tgn:7012149",
          "tgn:7007826",
          "tgn:7029392"
        ],
        "placetype": [
          "aat:300008706"
        ],
        "id": 2356756,
        "name:xx": "Gorman Creek"
      }
    },
    {
      "geometry": {
        "type": "Point",
        "coordinates": [
          -118.7833,
          34.7
        ]
      },
      "type": "Feature",
      "properties": {
        "hierarchy": [
          "tgn:2356757",
          "tgn:1000001",
          "tgn:7012149",
          "tgn:7007157",
          "tgn:1002608",
          "tgn:7029392"
        ],
        "placetype": [
          "aat:300006075"
        ],
        "id": 2356757,
        "name:xx": "Gorman Creek Siphon"
      }
    },
    {
      "geometry": {
        "type": "Point",
        "coordinates": [
          -77.3833,
          41.2833
        ]
      },
      "type": "Feature",
      "properties": {
        "hierarchy": [
          "tgn:2356758",
          "tgn:1000001",
          "tgn:7012149",
          "tgn:1002613",
          "tgn:7007710",
          "tgn:7029392"
        ],
        "placetype": [
          "aat:300008761"
        ],
        "id": 2356758,
        "name:xx": "Gorman Draft"
      }
    },
    {
      "geometry": {
        "type": "Point",
        "coordinates": [
          -99.8,
          30.6
        ]
      },
      "type": "Feature",
      "properties": {
        "hierarchy": [
          "tgn:2356759",
          "tgn:1000001",
          "tgn:7012149",
          "tgn:2002019",
          "tgn:7007826",
          "tgn:7029392"
        ],
        "placetype": [
          "aat:300008761"
        ],
        "id": 2356759,
        "name:xx": "Gorman Draw"
      }
    }
  ]
}
