{
  "geometry": {
    "type": "Point",
    "coordinates": [
      173.0167,
      52.95
    ]
  },
  "type": "Feature",
  "properties": {
    "hierarchy": [
      "tgn:2563187",
      "tgn:7030516",
      "tgn:7006450",
      "tgn:1000001",
      "tgn:7012149",
      "tgn:7029392"
    ],
    "placetype": [
      "aat:300266640"
    ],
    "id": 2563187,
    "name:xx": "Owens Ridge"
  }
}
