{
  "geometry": {
    "type": "Point",
    "coordinates": [
      53.4667,
      64.2333
    ]
  },
  "type": "Feature",
  "properties": {
    "hierarchy": [
      "tgn:1055212",
      "tgn:1000004",
      "tgn:6003149",
      "tgn:7002435",
      "tgn:7029392"
    ],
    "placetype": [
      "aat:300008347"
    ],
    "id": 1055212,
    "name:xx": "Kedva"
  }
}
