{
  "geometry": {
    "type": "Point",
    "coordinates": [
      87.5833,
      31.9167
    ]
  },
  "type": "Feature",
  "properties": {
    "hierarchy": [
      "tgn:1116066",
      "tgn:1000004",
      "tgn:7001319",
      "tgn:1000111",
      "tgn:7029392"
    ],
    "placetype": [
      "aat:300008680"
    ],
    "id": 1116066,
    "name:xx": "Dakecihu"
  }
}
