{
  "geometry": {
    "type": "Point",
    "coordinates": [
      -105.3667,
      41.6667
    ]
  },
  "type": "Feature",
  "properties": {
    "hierarchy": [
      "tgn:2219750",
      "tgn:2002365",
      "tgn:1000001",
      "tgn:7012149",
      "tgn:7007923",
      "tgn:7029392"
    ],
    "placetype": [
      "aat:300008706"
    ],
    "id": 2219750,
    "name:xx": "Canteen Creek"
  }
}
