{
  "type": "FeatureCollection",
  "features": [
    {
      "geometry": {
        "type": "Point",
        "coordinates": [
          -84.8,
          37.7
        ]
      },
      "type": "Feature",
      "properties": {
        "hierarchy": [
          "tgn:2261800",
          "tgn:1000001",
          "tgn:7012149",
          "tgn:2000827",
          "tgn:7007255",
          "tgn:7029392"
        ],
        "placetype": [
          "aat:300008697"
        ],
        "id": 2261800,
        "name:xx": "Cove Spring"
      }
    },
    {
      "geometry": {
        "type": "Point",
        "coordinates": [
          -93.7167,
          37.1667
        ]
      },
      "type": "Feature",
      "properties": {
        "hierarchy": [
          "tgn:2261801",
          "tgn:1000001",
          "tgn:7012149",
          "tgn:2001213",
          "tgn:7007523",
          "tgn:7029392"
        ],
        "placetype": [
          "aat:300008697"
        ],
        "id": 2261801,
        "name:xx": "Cove Spring"
      }
    },
    {
      "geometry": {
        "type": "Point",
        "coordinates": [
          -91.1667,
          37.1833
        ]
      },
      "type": "Feature",
      "properties": {
        "hierarchy": [
          "tgn:2261802",
          "tgn:1000001",
          "tgn:7012149",
          "tgn:2001247",
          "tgn:7007523",
          "tgn:7029392"
        ],
        "placetype": [
          "aat:300008697"
        ],
        "id": 2261802,
        "name:xx": "Cove Spring"
      }
    },
    {
      "geometry": {
        "type": "Point",
        "coordinates": [
          -90.9167,
          38.35
        ]
      },
      "type": "Feature",
      "properties": {
        "hierarchy": [
          "tgn:2261803",
          "tgn:1000001",
          "tgn:7012149",
          "tgn:1002384",
          "tgn:7007523",
          "tgn:7029392"
        ],
        "placetype": [
          "aat:300008697"
        ],
        "id": 2261803,
        "name:xx": "Cove Spring"
      }
    },
    {
      "geometry": {
        "type": "Point",
        "coordinates": [
          -118.8167,
          44
        ]
      },
      "type": "Feature",
      "properties": {
        "hierarchy": [
          "tgn:2261804",
          "tgn:1000001",
          "tgn:7012149",
          "tgn:2001708",
          "tgn:7007708",
          "tgn:7029392"
        ],
        "placetype": [
          "aat:300008697"
        ],
        "id": 2261804,
        "name:xx": "Cove Spring"
      }
    },
    {
      "geometry": {
        "type": "Point",
        "coordinates": [
          -113.5333,
          37.55
        ]
      },
      "type": "Feature",
      "properties": {
        "hierarchy": [
          "tgn:2261805",
          "tgn:1000001",
          "tgn:7012149",
          "tgn:2002127",
          "tgn:7007827",
          "tgn:7029392"
        ],
        "placetype": [
          "aat:300008697"
        ],
        "id": 2261805,
        "name:xx": "Cove Spring"
      }
    },
    {
      "geometry": {
        "type": "Point",
        "coordinates": [
          -112.7,
          37.75
        ]
      },
      "type": "Feature",
      "properties": {
        "hierarchy": [
          "tgn:2261806",
          "tgn:1000001",
          "tgn:7012149",
          "tgn:2002111",
          "tgn:7007827",
          "tgn:7029392"
        ],
        "placetype": [
          "aat:300008697"
        ],
        "id": 2261806,
        "name:xx": "Cove Spring"
      }
    },
    {
      "geometry": {
        "type": "Point",
        "coordinates": [
          -110.2333,
          37.9833
        ]
      },
      "type": "Feature",
      "properties": {
        "hierarchy": [
          "tgn:2261807",
          "tgn:1000001",
          "tgn:2002109",
          "tgn:7012149",
          "tgn:7007827",
          "tgn:7029392"
        ],
        "placetype": [
          "aat:300008697"
        ],
        "id": 2261807,
        "name:xx": "Cove Spring"
      }
    },
    {
      "geometry": {
        "type": "Point",
        "coordinates": [
          -112.85,
          38.65
        ]
      },
      "type": "Feature",
      "properties": {
        "hierarchy": [
          "tgn:2261808",
          "tgn:1000001",
          "tgn:7012149",
          "tgn:2002114",
          "tgn:7007827",
          "tgn:7029392"
        ],
        "placetype": [
          "aat:300008697"
        ],
        "id": 2261808,
        "name:xx": "Cove Spring"
      }
    },
    {
      "geometry": {
        "type": "Point",
        "coordinates": [
          -109.7833,
          40.5833
        ]
      },
      "type": "Feature",
      "properties": {
        "hierarchy": [
          "tgn:2261809",
          "tgn:1000001",
          "tgn:7012149",
          "tgn:2002124",
          "tgn:7007827",
          "tgn:7029392"
        ],
        "placetype": [
          "aat:300008697"
        ],
        "id": 2261809,
        "name:xx": "Cove Spring"
      }
    }
  ]
}
