{
  "geometry": {
    "type": "Point",
    "coordinates": [
      13.25,
      53.55
    ]
  },
  "type": "Feature",
  "properties": {
    "hierarchy": [
      "tgn:7103176",
      "tgn:1000003",
      "tgn:7000094",
      "tgn:7000084",
      "tgn:7029392"
    ],
    "placetype": [
      "aat:300008347"
    ],
    "id": 7103176,
    "name:xx": "Sankt Georg"
  }
}
