{
  "geometry": {
    "type": "Point",
    "coordinates": [
      -85.1667,
      36.4667
    ]
  },
  "type": "Feature",
  "properties": {
    "hierarchy": [
      "tgn:2168771",
      "tgn:1000001",
      "tgn:7012149",
      "tgn:7007825",
      "tgn:7029392"
    ],
    "placetype": [
      "aat:300008699"
    ],
    "id": 2168771,
    "name:xx": "Big Hollow Branch"
  }
}
