{
  "geometry": {
    "type": "Point",
    "coordinates": [
      -72.7167,
      41.6667
    ]
  },
  "type": "Feature",
  "properties": {
    "hierarchy": [
      "tgn:2625236",
      "tgn:1000001",
      "tgn:1002664",
      "tgn:7012149",
      "tgn:7007159",
      "tgn:7029392"
    ],
    "placetype": [
      "aat:300008699"
    ],
    "id": 2625236,
    "name:xx": "Rockhole Brook"
  }
}
