{
  "geometry": {
    "type": "Point",
    "coordinates": [
      31.75,
      58.3667
    ]
  },
  "type": "Feature",
  "properties": {
    "hierarchy": [
      "tgn:1058701",
      "tgn:1000004",
      "tgn:4008031",
      "tgn:7018214",
      "tgn:7002435",
      "tgn:7029392"
    ],
    "placetype": [
      "aat:300008347"
    ],
    "id": 1058701,
    "name:xx": "Proletariy"
  }
}
