{
  "geometry": {
    "type": "Point",
    "coordinates": [
      -89.95,
      43.0167
    ]
  },
  "type": "Feature",
  "properties": {
    "hierarchy": [
      "tgn:2413753",
      "tgn:1000001",
      "tgn:7012149",
      "tgn:2002326",
      "tgn:7007922",
      "tgn:7029392"
    ],
    "placetype": [
      "aat:300008706"
    ],
    "id": 2413753,
    "name:xx": "Irish Hollow Creek"
  }
}
