{
  "geometry": {
    "type": "Point",
    "coordinates": [
      20.8667,
      -11.8667
    ]
  },
  "type": "Feature",
  "properties": {
    "hierarchy": [
      "tgn:1087726",
      "tgn:7001242",
      "tgn:1000149",
      "tgn:1000899",
      "tgn:7029392"
    ],
    "placetype": [
      "aat:300008347"
    ],
    "id": 1087726,
    "name:xx": "Caxopa"
  }
}
