{
  "geometry": {
    "type": "Point",
    "coordinates": [
      -105.5167,
      40.9667
    ]
  },
  "type": "Feature",
  "properties": {
    "hierarchy": [
      "tgn:2512488",
      "tgn:1000001",
      "tgn:7012149",
      "tgn:2000226",
      "tgn:7007158",
      "tgn:7029392"
    ],
    "placetype": [
      "aat:300008706"
    ],
    "id": 2512488,
    "name:xx": "Mill Creek"
  }
}
