{
  "geometry": {
    "type": "Point",
    "coordinates": [
      -123.6667,
      47.8667
    ]
  },
  "type": "Feature",
  "properties": {
    "hierarchy": [
      "tgn:1109430",
      "tgn:1000001",
      "tgn:7012149",
      "tgn:7007920",
      "tgn:7029392"
    ],
    "placetype": [
      "aat:300008795"
    ],
    "id": 1109430,
    "name:xx": "Olympic Mountains"
  }
}
