{
  "geometry": {
    "type": "Point",
    "coordinates": [
      74.533333,
      16.85
    ]
  },
  "type": "Feature",
  "properties": {
    "hierarchy": [
      "tgn:7581068",
      "tgn:1000004",
      "tgn:7000198",
      "tgn:1001895",
      "tgn:7029392"
    ],
    "placetype": [
      "aat:300008699"
    ],
    "name:en": "Vārna River",
    "id": 7581068
  }
}
