{
  "geometry": {
    "type": "Point",
    "coordinates": [
      -109.7667,
      37.8667
    ]
  },
  "type": "Feature",
  "properties": {
    "hierarchy": [
      "tgn:2400667",
      "tgn:1000001",
      "tgn:7012149",
      "tgn:2002119",
      "tgn:7007827",
      "tgn:7029392"
    ],
    "placetype": [
      "aat:300008798"
    ],
    "id": 2400667,
    "name:xx": "Horse Mountain"
  }
}
