{
  "geometry": {
    "type": "Point",
    "coordinates": [
      16.3333,
      39.0333
    ]
  },
  "type": "Feature",
  "properties": {
    "hierarchy": [
      "tgn:1108317",
      "tgn:1003447",
      "tgn:7007850",
      "tgn:1000003",
      "tgn:1000080",
      "tgn:7029392"
    ],
    "placetype": [
      "aat:300259572"
    ],
    "id": 1108317,
    "name:xx": "Acquabona, Passo di"
  }
}
