{
  "geometry": {
    "type": "Point",
    "coordinates": [
      102.25,
      6.1167
    ]
  },
  "type": "Feature",
  "properties": {
    "hierarchy": [
      "tgn:1082802",
      "tgn:7000317",
      "tgn:1001885",
      "tgn:1000004",
      "tgn:1000128",
      "tgn:7029392"
    ],
    "placetype": [
      "aat:300008347",
      "aat:300387221",
      "aat:300008375",
      "aat:300387302"
    ],
    "id": 1082802,
    "name:xx": "Kota Baharu"
  }
}
