{
  "geometry": {
    "type": "Point",
    "coordinates": [
      -93.0167,
      45.25
    ]
  },
  "type": "Feature",
  "properties": {
    "hierarchy": [
      "tgn:2529410",
      "tgn:1000001",
      "tgn:7012149",
      "tgn:7007521",
      "tgn:7029392"
    ],
    "placetype": [
      "aat:300008680"
    ],
    "id": 2529410,
    "name:xx": "Mud Lake"
  }
}
