{
  "type": "FeatureCollection",
  "features": [
    {
      "geometry": {
        "type": "Point",
        "coordinates": [
          6.333333,
          50.15
        ]
      },
      "type": "Feature",
      "properties": {
        "hierarchy": [
          "tgn:1121100",
          "tgn:1000003",
          "tgn:7003682",
          "tgn:7000084",
          "tgn:7029392"
        ],
        "placetype": [
          "aat:300008707",
          "aat:300008699"
        ],
        "id": 1121100,
        "name:xx": "Alfbach"
      }
    },
    {
      "geometry": {
        "type": "Point",
        "coordinates": [
          3.291,
          11.933
        ]
      },
      "type": "Feature",
      "properties": {
        "hierarchy": [
          "tgn:1121106",
          "tgn:7001242",
          "tgn:1000160",
          "tgn:7029392"
        ],
        "placetype": [
          "aat:300008707",
          "aat:300008699"
        ],
        "id": 1121106,
        "name:xx": "Alibori"
      }
    },
    {
      "geometry": {
        "type": "Point",
        "coordinates": [
          16.6167,
          1.5833
        ]
      },
      "type": "Feature",
      "properties": {
        "hierarchy": [
          "tgn:1121108",
          "tgn:7001242",
          "tgn:1000158",
          "tgn:7029392"
        ],
        "placetype": [
          "aat:300008707"
        ],
        "id": 1121108,
        "name:xx": "Alima"
      }
    }
  ]
}
