{
  "type": "FeatureCollection",
  "features": [
    {
      "geometry": {
        "type": "Point",
        "coordinates": [
          -93.2333,
          39
        ]
      },
      "type": "Feature",
      "properties": {
        "hierarchy": [
          "tgn:2577600",
          "tgn:1000001",
          "tgn:7012149",
          "tgn:2001243",
          "tgn:7007523",
          "tgn:7029392"
        ],
        "placetype": [
          "aat:300006191"
        ],
        "id": 2577600,
        "name:xx": "Peterson Lake"
      }
    },
    {
      "geometry": {
        "type": "Point",
        "coordinates": [
          -94.6,
          39.8333
        ]
      },
      "type": "Feature",
      "properties": {
        "hierarchy": [
          "tgn:2577601",
          "tgn:2001168",
          "tgn:1000001",
          "tgn:7012149",
          "tgn:7007523",
          "tgn:7029392"
        ],
        "placetype": [
          "aat:300006191"
        ],
        "id": 2577601,
        "name:xx": "Peterson Lake"
      }
    },
    {
      "geometry": {
        "type": "Point",
        "coordinates": [
          -113.3,
          45.1667
        ]
      },
      "type": "Feature",
      "properties": {
        "hierarchy": [
          "tgn:2577602",
          "tgn:1000001",
          "tgn:2001260",
          "tgn:7012149",
          "tgn:7007524",
          "tgn:7029392"
        ],
        "placetype": [
          "aat:300008680"
        ],
        "id": 2577602,
        "name:xx": "Peterson Lake"
      }
    },
    {
      "geometry": {
        "type": "Point",
        "coordinates": [
          -114.2167,
          46.6333
        ]
      },
      "type": "Feature",
      "properties": {
        "hierarchy": [
          "tgn:2577603",
          "tgn:1000001",
          "tgn:7012149",
          "tgn:2001300",
          "tgn:7007524",
          "tgn:7029392"
        ],
        "placetype": [
          "aat:300008680"
        ],
        "id": 2577603,
        "name:xx": "Peterson Lake"
      }
    },
    {
      "geometry": {
        "type": "Point",
        "coordinates": [
          -114.05,
          48.1167
        ]
      },
      "type": "Feature",
      "properties": {
        "hierarchy": [
          "tgn:2577604",
          "tgn:1000001",
          "tgn:7012149",
          "tgn:2001274",
          "tgn:7007524",
          "tgn:7029392"
        ],
        "placetype": [
          "aat:300008680"
        ],
        "id": 2577604,
        "name:xx": "Peterson Lake"
      }
    },
    {
      "geometry": {
        "type": "Point",
        "coordinates": [
          -102.9,
          41.4833
        ]
      },
      "type": "Feature",
      "properties": {
        "hierarchy": [
          "tgn:2577605",
          "tgn:1000001",
          "tgn:7012149",
          "tgn:2001377",
          "tgn:7007525",
          "tgn:7029392"
        ],
        "placetype": [
          "aat:300008680"
        ],
        "id": 2577605,
        "name:xx": "Peterson Lake"
      }
    },
    {
      "geometry": {
        "type": "Point",
        "coordinates": [
          -102.6833,
          42.1333
        ]
      },
      "type": "Feature",
      "properties": {
        "hierarchy": [
          "tgn:2577606",
          "tgn:1000001",
          "tgn:7012149",
          "tgn:2001396",
          "tgn:7007525",
          "tgn:7029392"
        ],
        "placetype": [
          "aat:300008680"
        ],
        "id": 2577606,
        "name:xx": "Peterson Lake"
      }
    },
    {
      "geometry": {
        "type": "Point",
        "coordinates": [
          -99.4167,
          42.2667
        ]
      },
      "type": "Feature",
      "properties": {
        "hierarchy": [
          "tgn:2577607",
          "tgn:1000001",
          "tgn:7012149",
          "tgn:2001390",
          "tgn:7007525",
          "tgn:7029392"
        ],
        "placetype": [
          "aat:300008680"
        ],
        "id": 2577607,
        "name:xx": "Peterson Lake"
      }
    },
    {
      "geometry": {
        "type": "Point",
        "coordinates": [
          -77.1833,
          42.3
        ]
      },
      "type": "Feature",
      "properties": {
        "hierarchy": [
          "tgn:2577608",
          "tgn:1000001",
          "tgn:7012149",
          "tgn:1002920",
          "tgn:7007568",
          "tgn:7029392"
        ],
        "placetype": [
          "aat:300008680"
        ],
        "id": 2577608,
        "name:xx": "Peterson Lake"
      }
    },
    {
      "geometry": {
        "type": "Point",
        "coordinates": [
          -100.8,
          47.5167
        ]
      },
      "type": "Feature",
      "properties": {
        "hierarchy": [
          "tgn:2577609",
          "tgn:1000001",
          "tgn:2001584",
          "tgn:7012149",
          "tgn:7007705",
          "tgn:7029392"
        ],
        "placetype": [
          "aat:300008680"
        ],
        "id": 2577609,
        "name:xx": "Peterson Lake"
      }
    }
  ]
}
