{
  "geometry": {
    "type": "Point",
    "coordinates": [
      12.55,
      41.75
    ]
  },
  "type": "Feature",
  "properties": {
    "hierarchy": [
      "tgn:1004452",
      "tgn:7003138",
      "tgn:1000003",
      "tgn:7003080",
      "tgn:1000080",
      "tgn:7029392"
    ],
    "placetype": [
      "aat:300008347"
    ],
    "id": 1004452,
    "name:xx": "Falcognana di Sotto"
  }
}
