{
  "geometry": {
    "type": "Point",
    "coordinates": [
      -88.1167,
      38.6333
    ]
  },
  "type": "Feature",
  "properties": {
    "hierarchy": [
      "tgn:2313025",
      "tgn:1000001",
      "tgn:7012149",
      "tgn:2000527",
      "tgn:7007251",
      "tgn:7029392"
    ],
    "placetype": [
      "aat:300008347"
    ],
    "id": 2313025,
    "name:xx": "Elbow"
  }
}
