{
  "type": "FeatureCollection",
  "features": [
    {
      "geometry": {
        "type": "Point",
        "coordinates": [
          -117.9833,
          47.0167
        ]
      },
      "type": "Feature",
      "properties": {
        "hierarchy": [
          "tgn:2734410",
          "tgn:2002238",
          "tgn:1000001",
          "tgn:7012149",
          "tgn:7007920",
          "tgn:7029392"
        ],
        "placetype": [
          "aat:300008680"
        ],
        "id": 2734410,
        "name:xx": "Turtle Lake"
      }
    },
    {
      "geometry": {
        "type": "Point",
        "coordinates": [
          -118.0333,
          47.9333
        ]
      },
      "type": "Feature",
      "properties": {
        "hierarchy": [
          "tgn:2734411",
          "tgn:1000001",
          "tgn:7012149",
          "tgn:2002250",
          "tgn:7007920",
          "tgn:7029392"
        ],
        "placetype": [
          "aat:300008680"
        ],
        "id": 2734411,
        "name:xx": "Turtle Lake"
      }
    },
    {
      "geometry": {
        "type": "Point",
        "coordinates": [
          -119.55,
          48.6333
        ]
      },
      "type": "Feature",
      "properties": {
        "hierarchy": [
          "tgn:2734412",
          "tgn:1000001",
          "tgn:7012149",
          "tgn:1002742",
          "tgn:7007920",
          "tgn:7029392"
        ],
        "placetype": [
          "aat:300008680"
        ],
        "id": 2734412,
        "name:xx": "Turtle Lake"
      }
    },
    {
      "geometry": {
        "type": "Point",
        "coordinates": [
          -123.1333,
          47.25
        ]
      },
      "type": "Feature",
      "properties": {
        "hierarchy": [
          "tgn:2734413",
          "tgn:1000001",
          "tgn:7012149",
          "tgn:1002645",
          "tgn:7007920",
          "tgn:7029392"
        ],
        "placetype": [
          "aat:300008680"
        ],
        "id": 2734413,
        "name:xx": "Turtle Lake"
      }
    },
    {
      "geometry": {
        "type": "Point",
        "coordinates": [
          -88.6667,
          42.7167
        ]
      },
      "type": "Feature",
      "properties": {
        "hierarchy": [
          "tgn:2734414",
          "tgn:1000001",
          "tgn:7012149",
          "tgn:1002982",
          "tgn:7007922",
          "tgn:7029392"
        ],
        "placetype": [
          "aat:300008680"
        ],
        "id": 2734414,
        "name:xx": "Turtle Lake"
      }
    },
    {
      "geometry": {
        "type": "Point",
        "coordinates": [
          -89.3333,
          44.0833
        ]
      },
      "type": "Feature",
      "properties": {
        "hierarchy": [
          "tgn:2734415",
          "tgn:1000001",
          "tgn:7012149",
          "tgn:2002362",
          "tgn:7007922",
          "tgn:7029392"
        ],
        "placetype": [
          "aat:300008680"
        ],
        "id": 2734415,
        "name:xx": "Turtle Lake"
      }
    },
    {
      "geometry": {
        "type": "Point",
        "coordinates": [
          -89.2667,
          44.4667
        ]
      },
      "type": "Feature",
      "properties": {
        "hierarchy": [
          "tgn:2734416",
          "tgn:1000001",
          "tgn:7012149",
          "tgn:2002347",
          "tgn:7007922",
          "tgn:7029392"
        ],
        "placetype": [
          "aat:300008680"
        ],
        "id": 2734416,
        "name:xx": "Turtle Lake"
      }
    },
    {
      "geometry": {
        "type": "Point",
        "coordinates": [
          -89.3667,
          44.75
        ]
      },
      "type": "Feature",
      "properties": {
        "hierarchy": [
          "tgn:2734417",
          "tgn:1000001",
          "tgn:7012149",
          "tgn:2002336",
          "tgn:7007922",
          "tgn:7029392"
        ],
        "placetype": [
          "aat:300008680"
        ],
        "id": 2734417,
        "name:xx": "Turtle Lake"
      }
    },
    {
      "geometry": {
        "type": "Point",
        "coordinates": [
          -88.2667,
          45.0333
        ]
      },
      "type": "Feature",
      "properties": {
        "hierarchy": [
          "tgn:2734418",
          "tgn:1000001",
          "tgn:7012149",
          "tgn:2002341",
          "tgn:7007922",
          "tgn:7029392"
        ],
        "placetype": [
          "aat:300008680"
        ],
        "id": 2734418,
        "name:xx": "Turtle Lake"
      }
    },
    {
      "geometry": {
        "type": "Point",
        "coordinates": [
          -88.5333,
          45.1
        ]
      },
      "type": "Feature",
      "properties": {
        "hierarchy": [
          "tgn:2734419",
          "tgn:1000001",
          "tgn:7012149",
          "tgn:2002339",
          "tgn:7007922",
          "tgn:7029392"
        ],
        "placetype": [
          "aat:300008680"
        ],
        "id": 2734419,
        "name:xx": "Turtle Lake"
      }
    }
  ]
}
