{
  "geometry": {
    "type": "Point",
    "coordinates": [
      -113.1833,
      32.05
    ]
  },
  "type": "Feature",
  "properties": {
    "hierarchy": [
      "tgn:2126876",
      "tgn:1000001",
      "tgn:7006451",
      "tgn:7012149",
      "tgn:2000100",
      "tgn:7029392"
    ],
    "placetype": [
      "aat:300008798"
    ],
    "id": 2126876,
    "name:xx": "Agua Dulce Mountains"
  }
}
