{
  "type": "FeatureCollection",
  "features": [
    {
      "geometry": {
        "type": "Point",
        "coordinates": [
          -72.7333,
          43.6667
        ]
      },
      "type": "Feature",
      "properties": {
        "hierarchy": [
          "tgn:2697130",
          "tgn:1000001",
          "tgn:7012149",
          "tgn:7007828",
          "tgn:7029392"
        ],
        "placetype": [
          "aat:300008699"
        ],
        "id": 2697130,
        "name:xx": "Stony Brook"
      }
    },
    {
      "geometry": {
        "type": "Point",
        "coordinates": [
          -72.7333,
          44.1667
        ]
      },
      "type": "Feature",
      "properties": {
        "hierarchy": [
          "tgn:2697131",
          "tgn:1000001",
          "tgn:2002135",
          "tgn:7012149",
          "tgn:7007828",
          "tgn:7029392"
        ],
        "placetype": [
          "aat:300008699"
        ],
        "id": 2697131,
        "name:xx": "Stony Brook"
      }
    },
    {
      "geometry": {
        "type": "Point",
        "coordinates": [
          -71.7667,
          44.65
        ]
      },
      "type": "Feature",
      "properties": {
        "hierarchy": [
          "tgn:2697132",
          "tgn:1000001",
          "tgn:1002361",
          "tgn:7012149",
          "tgn:7007828",
          "tgn:7029392"
        ],
        "placetype": [
          "aat:300008699"
        ],
        "id": 2697132,
        "name:xx": "Stony Brook"
      }
    },
    {
      "geometry": {
        "type": "Point",
        "coordinates": [
          -72.2833,
          44.8667
        ]
      },
      "type": "Feature",
      "properties": {
        "hierarchy": [
          "tgn:2697133",
          "tgn:1000001",
          "tgn:1002753",
          "tgn:7012149",
          "tgn:7007828",
          "tgn:7029392"
        ],
        "placetype": [
          "aat:300008699"
        ],
        "id": 2697133,
        "name:xx": "Stony Brook"
      }
    },
    {
      "geometry": {
        "type": "Point",
        "coordinates": [
          -123.1,
          47.7333
        ]
      },
      "type": "Feature",
      "properties": {
        "hierarchy": [
          "tgn:2697134",
          "tgn:1000001",
          "tgn:7012149",
          "tgn:1002521",
          "tgn:7007920",
          "tgn:7029392"
        ],
        "placetype": [
          "aat:300008699"
        ],
        "id": 2697134,
        "name:xx": "Stony Brook"
      }
    },
    {
      "geometry": {
        "type": "Point",
        "coordinates": [
          -90.6333,
          45.65
        ]
      },
      "type": "Feature",
      "properties": {
        "hierarchy": [
          "tgn:2697135",
          "tgn:1000001",
          "tgn:7012149",
          "tgn:2002348",
          "tgn:7007922",
          "tgn:7029392"
        ],
        "placetype": [
          "aat:300008699"
        ],
        "id": 2697135,
        "name:xx": "Stony Brook"
      }
    },
    {
      "geometry": {
        "type": "Point",
        "coordinates": [
          -89,
          43.1167
        ]
      },
      "type": "Feature",
      "properties": {
        "hierarchy": [
          "tgn:2697136",
          "tgn:1000001",
          "tgn:7012149",
          "tgn:7007922",
          "tgn:7029392"
        ],
        "placetype": [
          "aat:300008699"
        ],
        "id": 2697136,
        "name:xx": "Stony Brook"
      }
    },
    {
      "geometry": {
        "type": "Point",
        "coordinates": [
          -88.25,
          44.05
        ]
      },
      "type": "Feature",
      "properties": {
        "hierarchy": [
          "tgn:2697137",
          "tgn:1000001",
          "tgn:2002312",
          "tgn:7012149",
          "tgn:7007922",
          "tgn:7029392"
        ],
        "placetype": [
          "aat:300008699"
        ],
        "id": 2697137,
        "name:xx": "Stony Brook"
      }
    },
    {
      "geometry": {
        "type": "Point",
        "coordinates": [
          -92.1,
          46.5333
        ]
      },
      "type": "Feature",
      "properties": {
        "hierarchy": [
          "tgn:2697138",
          "tgn:1000001",
          "tgn:2002318",
          "tgn:7012149",
          "tgn:7007922",
          "tgn:7029392"
        ],
        "placetype": [
          "aat:300008699"
        ],
        "id": 2697138,
        "name:xx": "Stony Brook"
      }
    },
    {
      "geometry": {
        "type": "Point",
        "coordinates": [
          -74.8,
          40.35
        ]
      },
      "type": "Feature",
      "properties": {
        "hierarchy": [
          "tgn:2697139",
          "tgn:1000001",
          "tgn:1002657",
          "tgn:7012149",
          "tgn:7007565",
          "tgn:7029392"
        ],
        "placetype": [
          "aat:300008699"
        ],
        "id": 2697139,
        "name:xx": "Stony Brook Branch"
      }
    }
  ]
}
