{
  "geometry": {
    "type": "Point",
    "coordinates": [
      -73.5333,
      45.4667
    ]
  },
  "type": "Feature",
  "properties": {
    "hierarchy": [
      "tgn:1015324",
      "tgn:7005685",
      "tgn:1000001",
      "tgn:7005804",
      "tgn:7029392"
    ],
    "placetype": [
      "aat:300008347",
      "aat:300008389",
      "aat:300387308",
      "aat:300265612"
    ],
    "id": 1015324,
    "name:xx": "Brossard"
  }
}
