{
  "type": "FeatureCollection",
  "features": [
    {
      "geometry": {
        "type": "Point",
        "coordinates": [
          -99.883333,
          20.05
        ]
      },
      "type": "Feature",
      "properties": {
        "hierarchy": [
          "tgn:7408500",
          "tgn:1000001",
          "tgn:1001893",
          "tgn:7005560",
          "tgn:7029392"
        ],
        "placetype": [
          "aat:300008347"
        ],
        "id": 7408500,
        "name:xx": "Los Ailes"
      }
    },
    {
      "geometry": {
        "type": "Point",
        "coordinates": [
          -99.975,
          20.033333
        ]
      },
      "type": "Feature",
      "properties": {
        "hierarchy": [
          "tgn:7408501",
          "tgn:1000001",
          "tgn:1001893",
          "tgn:7005560",
          "tgn:7029392"
        ],
        "placetype": [
          "aat:300008347"
        ],
        "id": 7408501,
        "name:xx": "Puentecillas"
      }
    },
    {
      "geometry": {
        "type": "Point",
        "coordinates": [
          -100,
          20.033333
        ]
      },
      "type": "Feature",
      "properties": {
        "hierarchy": [
          "tgn:7408502",
          "tgn:1000001",
          "tgn:1001893",
          "tgn:7005560",
          "tgn:7029392"
        ],
        "placetype": [
          "aat:300008347"
        ],
        "id": 7408502,
        "name:xx": "Juandó"
      }
    },
    {
      "geometry": {
        "type": "Point",
        "coordinates": [
          -100.033333,
          20.041667
        ]
      },
      "type": "Feature",
      "properties": {
        "hierarchy": [
          "tgn:7408503",
          "tgn:1000001",
          "tgn:1001893",
          "tgn:7005560",
          "tgn:7029392"
        ],
        "placetype": [
          "aat:300008347"
        ],
        "id": 7408503,
        "name:xx": "Los Charcos"
      }
    },
    {
      "geometry": {
        "type": "Point",
        "coordinates": [
          -100,
          20.05
        ]
      },
      "type": "Feature",
      "properties": {
        "hierarchy": [
          "tgn:7408504",
          "tgn:1000001",
          "tgn:1001893",
          "tgn:7005560",
          "tgn:7029392"
        ],
        "placetype": [
          "aat:300008347"
        ],
        "id": 7408504,
        "name:xx": "El Agostadero"
      }
    },
    {
      "geometry": {
        "type": "Point",
        "coordinates": [
          -100,
          20.075
        ]
      },
      "type": "Feature",
      "properties": {
        "hierarchy": [
          "tgn:7408505",
          "tgn:1000001",
          "tgn:1001893",
          "tgn:7005560",
          "tgn:7029392"
        ],
        "placetype": [
          "aat:300008347"
        ],
        "id": 7408505,
        "name:xx": "San Francisco Saxni"
      }
    },
    {
      "geometry": {
        "type": "Point",
        "coordinates": [
          -99.875,
          20.1
        ]
      },
      "type": "Feature",
      "properties": {
        "hierarchy": [
          "tgn:7408506",
          "tgn:1000001",
          "tgn:1001893",
          "tgn:7005560",
          "tgn:7029392"
        ],
        "placetype": [
          "aat:300008699"
        ],
        "id": 7408506,
        "name:xx": "Ñadó, Río"
      }
    },
    {
      "geometry": {
        "type": "Point",
        "coordinates": [
          -99.825,
          20.091667
        ]
      },
      "type": "Feature",
      "properties": {
        "hierarchy": [
          "tgn:7408507",
          "tgn:1000001",
          "tgn:1001893",
          "tgn:7005560",
          "tgn:7029392"
        ],
        "placetype": [
          "aat:300008347"
        ],
        "id": 7408507,
        "name:xx": "La Soledad"
      }
    },
    {
      "geometry": {
        "type": "Point",
        "coordinates": [
          -99.791667,
          20.1
        ]
      },
      "type": "Feature",
      "properties": {
        "hierarchy": [
          "tgn:7408508",
          "tgn:1000001",
          "tgn:1001893",
          "tgn:7005560",
          "tgn:7029392"
        ],
        "placetype": [
          "aat:300008347"
        ],
        "id": 7408508,
        "name:xx": "Santa María Nativitas"
      }
    },
    {
      "geometry": {
        "type": "Point",
        "coordinates": [
          -99.683333,
          20.1
        ]
      },
      "type": "Feature",
      "properties": {
        "hierarchy": [
          "tgn:7408509",
          "tgn:1000001",
          "tgn:1001893",
          "tgn:7005560",
          "tgn:7029392"
        ],
        "placetype": [
          "aat:300008347"
        ],
        "id": 7408509,
        "name:xx": "El Rosal"
      }
    }
  ]
}
