{
  "geometry": {
    "type": "Point",
    "coordinates": [
      -77.2333,
      37.3833
    ]
  },
  "type": "Feature",
  "properties": {
    "hierarchy": [
      "tgn:2489907",
      "tgn:1000001",
      "tgn:1002257",
      "tgn:7012149",
      "tgn:7007919",
      "tgn:7029392"
    ],
    "placetype": [
      "aat:300008798"
    ],
    "id": 2489907,
    "name:xx": "Malvern Hill"
  }
}
