{
  "geometry": {
    "type": "Point",
    "coordinates": [
      -100.35,
      34.4667
    ]
  },
  "type": "Feature",
  "properties": {
    "hierarchy": [
      "tgn:2236844",
      "tgn:1000001",
      "tgn:7012149",
      "tgn:2001955",
      "tgn:7007826",
      "tgn:7029392"
    ],
    "placetype": [
      "aat:300006191"
    ],
    "id": 2236844,
    "name:xx": "Childress, Lake"
  }
}
