{
  "geometry": {
    "type": "Point",
    "coordinates": [
      -99.8667,
      30.3167
    ]
  },
  "type": "Feature",
  "properties": {
    "hierarchy": [
      "tgn:2714069",
      "tgn:1000001",
      "tgn:7012149",
      "tgn:2002019",
      "tgn:7007826",
      "tgn:7029392"
    ],
    "placetype": [
      "aat:300008761"
    ],
    "id": 2714069,
    "name:xx": "Telegraph Canyon"
  }
}
