{
  "type": "FeatureCollection",
  "features": [
    {
      "geometry": {
        "type": "Point",
        "coordinates": [
          -4.683333,
          53.316667
        ]
      },
      "type": "Feature",
      "properties": {
        "hierarchy": [
          "tgn:7460633",
          "tgn:7008532",
          "tgn:7002443",
          "tgn:1000003",
          "tgn:7008591",
          "tgn:7029392"
        ],
        "placetype": [
          "aat:300008795"
        ],
        "name:en": "Holyhead Mountain",
        "id": 7460633
      }
    },
    {
      "geometry": {
        "type": "Point",
        "coordinates": [
          -2.15,
          54.616667
        ]
      },
      "type": "Feature",
      "properties": {
        "hierarchy": [
          "tgn:7460637",
          "tgn:7002445",
          "tgn:1000003",
          "tgn:7008127",
          "tgn:7008591",
          "tgn:7029392"
        ],
        "placetype": [
          "aat:300008347"
        ],
        "name:en": "Holwick",
        "id": 7460637
      }
    }
  ]
}
