{
  "geometry": {
    "type": "Point",
    "coordinates": [
      151.2167,
      -33.8833
    ]
  },
  "type": "Feature",
  "properties": {
    "hierarchy": [
      "tgn:1102874",
      "tgn:7000490",
      "tgn:1000006",
      "tgn:7001828",
      "tgn:7001923",
      "tgn:7029392"
    ],
    "placetype": [
      "aat:300008187"
    ],
    "id": 1102874,
    "name:xx": "Hyde Park"
  }
}
