{
  "geometry": {
    "type": "Point",
    "coordinates": [
      -74.4333,
      43.6333
    ]
  },
  "type": "Feature",
  "properties": {
    "hierarchy": [
      "tgn:2230099",
      "tgn:1000001",
      "tgn:7012149",
      "tgn:1002440",
      "tgn:7007568",
      "tgn:7029392"
    ],
    "placetype": [
      "aat:300008798"
    ],
    "id": 2230099,
    "name:xx": "Cellar Mountain"
  }
}
