{
  "geometry": {
    "type": "Point",
    "coordinates": [
      87.071829,
      22.913146
    ]
  },
  "type": "Feature",
  "properties": {
    "hierarchy": [
      "tgn:1076985",
      "tgn:1000004",
      "tgn:7000198",
      "tgn:1001977",
      "tgn:7029392"
    ],
    "placetype": [
      "aat:300008347"
    ],
    "name:en": "Simlāpāl",
    "id": 1076985
  }
}
