{
  "type": "FeatureCollection",
  "features": [
    {
      "geometry": {
        "type": "Point",
        "coordinates": [
          -104.5333,
          38.2167
        ]
      },
      "type": "Feature",
      "properties": {
        "hierarchy": [
          "tgn:2015910",
          "tgn:1000001",
          "tgn:7012149",
          "tgn:7007158",
          "tgn:2000242",
          "tgn:7029392"
        ],
        "placetype": [
          "aat:300008347"
        ],
        "id": 2015910,
        "name:xx": "Lombard Village"
      }
    },
    {
      "geometry": {
        "type": "Point",
        "coordinates": [
          -105.2333,
          39.5833
        ]
      },
      "type": "Feature",
      "properties": {
        "hierarchy": [
          "tgn:2015911",
          "tgn:1000001",
          "tgn:7012149",
          "tgn:2000221",
          "tgn:7007158",
          "tgn:7029392"
        ],
        "placetype": [
          "aat:300008347"
        ],
        "id": 2015911,
        "name:xx": "Lone Pine Estates"
      }
    },
    {
      "geometry": {
        "type": "Point",
        "coordinates": [
          -105.1,
          40.1667
        ]
      },
      "type": "Feature",
      "properties": {
        "hierarchy": [
          "tgn:2015912",
          "tgn:1000001",
          "tgn:2000198",
          "tgn:7012149",
          "tgn:7007158",
          "tgn:7029392"
        ],
        "placetype": [
          "aat:300008347"
        ],
        "id": 2015912,
        "name:xx": "Longmont"
      }
    },
    {
      "geometry": {
        "type": "Point",
        "coordinates": [
          -105.1833,
          39.4167
        ]
      },
      "type": "Feature",
      "properties": {
        "hierarchy": [
          "tgn:2015916",
          "tgn:1000001",
          "tgn:7012149",
          "tgn:2000221",
          "tgn:7007158",
          "tgn:7029392"
        ],
        "placetype": [
          "aat:300008347",
          "aat:300387247"
        ],
        "id": 2015916,
        "name:xx": "Longview"
      }
    },
    {
      "geometry": {
        "type": "Point",
        "coordinates": [
          -105.3667,
          37.1333
        ]
      },
      "type": "Feature",
      "properties": {
        "hierarchy": [
          "tgn:2015919",
          "tgn:1000001",
          "tgn:7012149",
          "tgn:2000203",
          "tgn:7007158",
          "tgn:7029392"
        ],
        "placetype": [
          "aat:300008347"
        ],
        "id": 2015919,
        "name:xx": "Los Fuertes"
      }
    }
  ]
}
