{
  "geometry": {
    "type": "Point",
    "coordinates": [
      25.5833,
      -25.6667
    ]
  },
  "type": "Feature",
  "properties": {
    "hierarchy": [
      "tgn:1088101",
      "tgn:7001242",
      "tgn:1000933",
      "tgn:1000150",
      "tgn:7029392"
    ],
    "placetype": [
      "aat:300008347"
    ],
    "id": 1088101,
    "name:xx": "Ramathlabama"
  }
}
