{
  "geometry": {
    "type": "Point",
    "coordinates": [
      -7.1667,
      53.7667
    ]
  },
  "type": "Feature",
  "properties": {
    "hierarchy": [
      "tgn:1042960",
      "tgn:7001199",
      "tgn:7003491",
      "tgn:1000003",
      "tgn:1000078",
      "tgn:7029392"
    ],
    "placetype": [
      "aat:300008347"
    ],
    "id": 1042960,
    "name:xx": "Oldcastle"
  }
}
