{
  "geometry": {
    "type": "Point",
    "coordinates": [
      27.8833,
      -28.8667
    ]
  },
  "type": "Feature",
  "properties": {
    "hierarchy": [
      "tgn:1093063",
      "tgn:7001242",
      "tgn:7016562",
      "tgn:1000193",
      "tgn:7029392"
    ],
    "placetype": [
      "aat:300008347"
    ],
    "id": 1093063,
    "name:xx": "Ficksburg"
  }
}
