{
  "geometry": {
    "type": "Point",
    "coordinates": [
      -64.146,
      10.82
    ]
  },
  "type": "Feature",
  "properties": {
    "hierarchy": [
      "tgn:7593347",
      "tgn:1006881",
      "tgn:1001914",
      "tgn:1000002",
      "tgn:1000059",
      "tgn:7029392"
    ],
    "placetype": [
      "aat:300000810"
    ],
    "id": 7593347,
    "name:xx": "Ruinas de Nueva Cádiz"
  }
}
