{
  "geometry": {
    "type": "Point",
    "coordinates": [
      -2.3833,
      47.9833
    ]
  },
  "type": "Feature",
  "properties": {
    "hierarchy": [
      "tgn:1132119",
      "tgn:1000003",
      "tgn:7012216",
      "tgn:1000070",
      "tgn:7029392"
    ],
    "placetype": [
      "aat:300008707"
    ],
    "id": 1132119,
    "name:xx": "Yvel"
  }
}
