{
  "type": "FeatureCollection",
  "features": [
    {
      "geometry": {
        "type": "Point",
        "coordinates": [
          -3.183333,
          51
        ]
      },
      "type": "Feature",
      "properties": {
        "hierarchy": [
          "tgn:7464652",
          "tgn:7002445",
          "tgn:1000003",
          "tgn:7012032",
          "tgn:7008591",
          "tgn:7029392"
        ],
        "placetype": [
          "aat:300008347"
        ],
        "name:en": "Bradford",
        "id": 7464652
      }
    },
    {
      "geometry": {
        "type": "Point",
        "coordinates": [
          0.8,
          52.2
        ]
      },
      "type": "Feature",
      "properties": {
        "hierarchy": [
          "tgn:7464653",
          "tgn:7002445",
          "tgn:1000003",
          "tgn:7008185",
          "tgn:7008591",
          "tgn:7029392"
        ],
        "placetype": [
          "aat:300008347"
        ],
        "name:en": "Bradfield Saint George",
        "id": 7464653
      }
    },
    {
      "geometry": {
        "type": "Point",
        "coordinates": [
          -1.6,
          53.416667
        ]
      },
      "type": "Feature",
      "properties": {
        "hierarchy": [
          "tgn:7464654",
          "tgn:7002445",
          "tgn:7019047",
          "tgn:1000003",
          "tgn:7029505",
          "tgn:7008591",
          "tgn:7029392"
        ],
        "placetype": [
          "aat:300008347"
        ],
        "name:en": "Bradfield",
        "id": 7464654
      }
    },
    {
      "geometry": {
        "type": "Point",
        "coordinates": [
          -7.166667,
          54.55
        ]
      },
      "type": "Feature",
      "properties": {
        "hierarchy": [
          "tgn:7464658",
          "tgn:7002448",
          "tgn:1000003",
          "tgn:7019206",
          "tgn:7008591",
          "tgn:7029392"
        ],
        "placetype": [
          "aat:300008347"
        ],
        "name:en": "Beragh",
        "id": 7464658
      }
    },
    {
      "geometry": {
        "type": "Point",
        "coordinates": [
          -0.783333,
          50.95
        ]
      },
      "type": "Feature",
      "properties": {
        "hierarchy": [
          "tgn:7464659",
          "tgn:7002445",
          "tgn:1000003",
          "tgn:7008134",
          "tgn:7008591",
          "tgn:7029392"
        ],
        "placetype": [
          "aat:300008347"
        ],
        "name:en": "Bepton",
        "id": 7464659
      }
    }
  ]
}
