{
  "geometry": {
    "type": "Point",
    "coordinates": [
      -122.35,
      41.1667
    ]
  },
  "type": "Feature",
  "properties": {
    "hierarchy": [
      "tgn:1102205",
      "tgn:1000001",
      "tgn:7012149",
      "tgn:7007157",
      "tgn:7029392"
    ],
    "placetype": [
      "aat:300008192"
    ],
    "id": 1102205,
    "name:xx": "Castle Crags State Park"
  }
}
