{
  "geometry": {
    "type": "Point",
    "coordinates": [
      -109.3167,
      33.6167
    ]
  },
  "type": "Feature",
  "properties": {
    "hierarchy": [
      "tgn:2359434",
      "tgn:1000001",
      "tgn:7006451",
      "tgn:2000095",
      "tgn:7012149",
      "tgn:7029392"
    ],
    "placetype": [
      "aat:300008706"
    ],
    "id": 2359434,
    "name:xx": "Grant Creek"
  }
}
