{
  "geometry": {
    "type": "Point",
    "coordinates": [
      41.6833,
      26.8167
    ]
  },
  "type": "Feature",
  "properties": {
    "hierarchy": [
      "tgn:1084800",
      "tgn:7000676",
      "tgn:1000004",
      "tgn:7003879",
      "tgn:1000137",
      "tgn:7029392"
    ],
    "placetype": [
      "aat:300008347"
    ],
    "id": 1084800,
    "name:xx": "Al-ʻAwsajīyah"
  }
}
