{
  "geometry": {
    "type": "Point",
    "coordinates": [
      -82.5833,
      35.8833
    ]
  },
  "type": "Feature",
  "properties": {
    "hierarchy": [
      "tgn:2137825",
      "tgn:1000001",
      "tgn:7012149",
      "tgn:2001516",
      "tgn:7007709",
      "tgn:7029392"
    ],
    "placetype": [
      "aat:300008699"
    ],
    "id": 2137825,
    "name:xx": "Arrington Branch"
  }
}
