{
  "geometry": {
    "type": "Point",
    "coordinates": [
      -75.2167,
      41.1667
    ]
  },
  "type": "Feature",
  "properties": {
    "hierarchy": [
      "tgn:2475740",
      "tgn:1000001",
      "tgn:7012149",
      "tgn:1002682",
      "tgn:7007710",
      "tgn:7029392"
    ],
    "placetype": [
      "aat:300008699"
    ],
    "id": 2475740,
    "name:xx": "Lucky Run"
  }
}
