{
  "type": "FeatureCollection",
  "features": [
    {
      "geometry": {
        "type": "Point",
        "coordinates": [
          -1.55,
          54.633333
        ]
      },
      "type": "Feature",
      "properties": {
        "hierarchy": [
          "tgn:7445030",
          "tgn:7002445",
          "tgn:1000003",
          "tgn:7008127",
          "tgn:7008591",
          "tgn:7029392"
        ],
        "placetype": [
          "aat:300008347"
        ],
        "name:en": "Woodham",
        "id": 7445030
      }
    },
    {
      "geometry": {
        "type": "Point",
        "coordinates": [
          -4.083333,
          54.983333
        ]
      },
      "type": "Feature",
      "properties": {
        "hierarchy": [
          "tgn:7445032",
          "tgn:7002444",
          "tgn:7008074",
          "tgn:1000003",
          "tgn:7008591",
          "tgn:7029392"
        ],
        "placetype": [
          "aat:300008680"
        ],
        "name:en": "Woodhall Loch",
        "id": 7445032
      }
    },
    {
      "geometry": {
        "type": "Point",
        "coordinates": [
          -7.448333,
          54.148611
        ]
      },
      "type": "Feature",
      "properties": {
        "hierarchy": [
          "tgn:7445034",
          "tgn:7002448",
          "tgn:7008700",
          "tgn:1000003",
          "tgn:7008591",
          "tgn:7029392"
        ],
        "placetype": [
          "aat:300008699"
        ],
        "name:en": "Woodford River",
        "id": 7445034
      }
    },
    {
      "geometry": {
        "type": "Point",
        "coordinates": [
          -1.833333,
          51.116667
        ]
      },
      "type": "Feature",
      "properties": {
        "hierarchy": [
          "tgn:7445039",
          "tgn:7002445",
          "tgn:1000003",
          "tgn:7008180",
          "tgn:7008591",
          "tgn:7029392"
        ],
        "placetype": [
          "aat:300008347"
        ],
        "name:en": "Woodford",
        "id": 7445039
      }
    }
  ]
}
