{
  "geometry": {
    "type": "Point",
    "coordinates": [
      25.344565,
      29.38472
    ]
  },
  "type": "Feature",
  "properties": {
    "hierarchy": [
      "tgn:7521850",
      "tgn:7001242",
      "tgn:7016833",
      "tgn:1001418",
      "tgn:7029392"
    ],
    "placetype": [
      "aat:300008777"
    ],
    "name:en": "Al Bayḑā'",
    "id": 7521850
  }
}
