{
  "geometry": {
    "type": "Point",
    "coordinates": [
      -94.05,
      41.0167
    ]
  },
  "type": "Feature",
  "properties": {
    "hierarchy": [
      "tgn:2716215",
      "tgn:1000001",
      "tgn:7012149",
      "tgn:2000648",
      "tgn:7007253",
      "tgn:7029392"
    ],
    "placetype": [
      "aat:300006191"
    ],
    "id": 2716215,
    "name:xx": "Thayer Lake"
  }
}
