{
  "geometry": {
    "type": "Point",
    "coordinates": [
      -105.8833,
      40.4167
    ]
  },
  "type": "Feature",
  "properties": {
    "hierarchy": [
      "tgn:2403716",
      "tgn:1000001",
      "tgn:7012149",
      "tgn:7007158",
      "tgn:7029392"
    ],
    "placetype": [
      "aat:300008798"
    ],
    "id": 2403716,
    "name:xx": "Howard Mountain"
  }
}
