{
  "geometry": {
    "type": "Point",
    "coordinates": [
      76.666667,
      25.25
    ]
  },
  "type": "Feature",
  "properties": {
    "hierarchy": [
      "tgn:7558679",
      "tgn:1000004",
      "tgn:7000198",
      "tgn:7016788",
      "tgn:7029392"
    ],
    "placetype": [
      "aat:300008347"
    ],
    "name:en": "Relāwan",
    "id": 7558679
  }
}
