{
  "geometry": {
    "type": "Point",
    "coordinates": [
      92.05,
      50.0333
    ]
  },
  "type": "Feature",
  "properties": {
    "hierarchy": [
      "tgn:1083084",
      "tgn:1000004",
      "tgn:1001589",
      "tgn:7029379",
      "tgn:7029392"
    ],
    "placetype": [
      "aat:300008347"
    ],
    "id": 1083084,
    "name:xx": "Candman'"
  }
}
