{
  "geometry": {
    "type": "Point",
    "coordinates": [
      -74.9167,
      38.9667
    ]
  },
  "type": "Feature",
  "properties": {
    "hierarchy": [
      "tgn:2191768",
      "tgn:1002232",
      "tgn:1000001",
      "tgn:7012149",
      "tgn:7007565",
      "tgn:7029392"
    ],
    "placetype": [
      "aat:300008699"
    ],
    "id": 2191768,
    "name:xx": "Bradley Run"
  }
}
