{
  "geometry": {
    "type": "Point",
    "coordinates": [
      -86.2333,
      32.65
    ]
  },
  "type": "Feature",
  "properties": {
    "hierarchy": [
      "tgn:2714558",
      "tgn:7002659",
      "tgn:1000001",
      "tgn:7012149",
      "tgn:2000025",
      "tgn:7029392"
    ],
    "placetype": [
      "aat:300008347"
    ],
    "id": 2714558,
    "name:xx": "Ten Cedars Estates"
  }
}
