{
  "geometry": {
    "type": "Point",
    "coordinates": [
      -106.1667,
      38.5833
    ]
  },
  "type": "Feature",
  "properties": {
    "hierarchy": [
      "tgn:2295692",
      "tgn:1000001",
      "tgn:2000199",
      "tgn:7012149",
      "tgn:7007158",
      "tgn:7029392"
    ],
    "placetype": [
      "aat:300008761"
    ],
    "id": 2295692,
    "name:xx": "Droney Gulch"
  }
}
