{
  "geometry": {
    "type": "Point",
    "coordinates": [
      73.25,
      19.466667
    ]
  },
  "type": "Feature",
  "properties": {
    "hierarchy": [
      "tgn:7554130",
      "tgn:1000004",
      "tgn:7000198",
      "tgn:1001895",
      "tgn:7029392"
    ],
    "placetype": [
      "aat:300008798"
    ],
    "name:en": "Māhuli",
    "id": 7554130
  }
}
