{
  "geometry": {
    "type": "Point",
    "coordinates": [
      -116.95,
      42.9167
    ]
  },
  "type": "Feature",
  "properties": {
    "hierarchy": [
      "tgn:2703610",
      "tgn:1000001",
      "tgn:7012149",
      "tgn:2000488",
      "tgn:7007250",
      "tgn:7029392"
    ],
    "placetype": [
      "aat:300008697"
    ],
    "id": 2703610,
    "name:xx": "Summit Spring Number One"
  }
}
