{
  "geometry": {
    "type": "Point",
    "coordinates": [
      -89.7333,
      29.4833
    ]
  },
  "type": "Feature",
  "properties": {
    "hierarchy": [
      "tgn:2674851",
      "tgn:1000001",
      "tgn:7012149",
      "tgn:2000891",
      "tgn:7007256",
      "tgn:7029392"
    ],
    "placetype": [
      "aat:300006075"
    ],
    "id": 2674851,
    "name:xx": "Socola Canal Number Two"
  }
}
