{
  "geometry": {
    "type": "Point",
    "coordinates": [
      179.5167,
      63.1167
    ]
  },
  "type": "Feature",
  "properties": {
    "hierarchy": [
      "tgn:1010485",
      "tgn:6001445",
      "tgn:1000004",
      "tgn:7018214",
      "tgn:7002435",
      "tgn:7029392"
    ],
    "placetype": [
      "aat:300008850"
    ],
    "id": 1010485,
    "name:xx": "Barykova, Mys"
  }
}
