{
  "geometry": {
    "type": "Point",
    "coordinates": [
      -96.2167,
      47.95
    ]
  },
  "type": "Feature",
  "properties": {
    "hierarchy": [
      "tgn:2198325",
      "tgn:1000001",
      "tgn:7012149",
      "tgn:2001061",
      "tgn:7007521",
      "tgn:7029392"
    ],
    "placetype": [
      "aat:300008706"
    ],
    "id": 2198325,
    "name:xx": "Browns Creek"
  }
}
