{
  "geometry": {
    "type": "Point",
    "coordinates": [
      51.1167,
      54.1333
    ]
  },
  "type": "Feature",
  "properties": {
    "hierarchy": [
      "tgn:1054416",
      "tgn:1000004",
      "tgn:1003407",
      "tgn:7018214",
      "tgn:7002435",
      "tgn:7029392"
    ],
    "placetype": [
      "aat:300008347"
    ],
    "id": 1054416,
    "name:xx": "Isakly"
  }
}
