{
  "geometry": {
    "type": "Point",
    "coordinates": [
      -95.4167,
      32.0167
    ]
  },
  "type": "Feature",
  "properties": {
    "hierarchy": [
      "tgn:2103565",
      "tgn:1000001",
      "tgn:7012149",
      "tgn:1002263",
      "tgn:7007826",
      "tgn:7029392"
    ],
    "placetype": [
      "aat:300008347"
    ],
    "id": 2103565,
    "name:xx": "Cuney"
  }
}
