{
  "geometry": {
    "type": "Point",
    "coordinates": [
      -76.75,
      34.8667
    ]
  },
  "type": "Feature",
  "properties": {
    "hierarchy": [
      "tgn:2265908",
      "tgn:1000001",
      "tgn:7012149",
      "tgn:2001486",
      "tgn:7007709",
      "tgn:7029392"
    ],
    "placetype": [
      "aat:300008347"
    ],
    "id": 2265908,
    "name:xx": "Craven Corner"
  }
}
