{
  "type": "FeatureCollection",
  "features": [
    {
      "geometry": {
        "type": "Point",
        "coordinates": [
          -84.3,
          39.2333
        ]
      },
      "type": "Feature",
      "properties": {
        "hierarchy": [
          "tgn:2414840",
          "tgn:1000001",
          "tgn:7012149",
          "tgn:1002441",
          "tgn:7007706",
          "tgn:7029392"
        ],
        "placetype": [
          "aat:300008680"
        ],
        "id": 2414840,
        "name:xx": "Isabella, Lake"
      }
    },
    {
      "geometry": {
        "type": "Point",
        "coordinates": [
          -121.6,
          47.6
        ]
      },
      "type": "Feature",
      "properties": {
        "hierarchy": [
          "tgn:2414842",
          "tgn:1000001",
          "tgn:7012149",
          "tgn:7018871",
          "tgn:7007920",
          "tgn:7029392"
        ],
        "placetype": [
          "aat:300008680"
        ],
        "id": 2414842,
        "name:xx": "Isabella, Lake"
      }
    },
    {
      "geometry": {
        "type": "Point",
        "coordinates": [
          -109.4667,
          42.9
        ]
      },
      "type": "Feature",
      "properties": {
        "hierarchy": [
          "tgn:2414843",
          "tgn:1000001",
          "tgn:7012149",
          "tgn:2002382",
          "tgn:7007923",
          "tgn:7029392"
        ],
        "placetype": [
          "aat:300008680"
        ],
        "id": 2414843,
        "name:xx": "Isabella, Lake"
      }
    },
    {
      "geometry": {
        "type": "Point",
        "coordinates": [
          -70.4,
          41.6167
        ]
      },
      "type": "Feature",
      "properties": {
        "hierarchy": [
          "tgn:2414844",
          "tgn:1002165",
          "tgn:1000001",
          "tgn:7012149",
          "tgn:7007517",
          "tgn:7029392"
        ],
        "placetype": [
          "aat:300008850"
        ],
        "id": 2414844,
        "name:xx": "Isabella, Point"
      }
    },
    {
      "geometry": {
        "type": "Point",
        "coordinates": [
          -86.9,
          33.8333
        ]
      },
      "type": "Feature",
      "properties": {
        "hierarchy": [
          "tgn:2414845",
          "tgn:7002659",
          "tgn:1000001",
          "tgn:7012149",
          "tgn:7029392"
        ],
        "placetype": [
          "aat:300008706"
        ],
        "id": 2414845,
        "name:xx": "Isabelle Creek"
      }
    },
    {
      "geometry": {
        "type": "Point",
        "coordinates": [
          -92.4667,
          44.7333
        ]
      },
      "type": "Feature",
      "properties": {
        "hierarchy": [
          "tgn:2414846",
          "tgn:1000001",
          "tgn:7012149",
          "tgn:2002345",
          "tgn:7007922",
          "tgn:7029392"
        ],
        "placetype": [
          "aat:300008706"
        ],
        "id": 2414846,
        "name:xx": "Isabelle Creek"
      }
    },
    {
      "geometry": {
        "type": "Point",
        "coordinates": [
          -105.6333,
          40.05
        ]
      },
      "type": "Feature",
      "properties": {
        "hierarchy": [
          "tgn:2414847",
          "tgn:1000001",
          "tgn:2000198",
          "tgn:7012149",
          "tgn:7007158",
          "tgn:7029392"
        ],
        "placetype": [
          "aat:300008835"
        ],
        "id": 2414847,
        "name:xx": "Isabelle Glacier"
      }
    }
  ]
}
