{
  "geometry": {
    "type": "Point",
    "coordinates": [
      -64.7667,
      -21.8667
    ]
  },
  "type": "Feature",
  "properties": {
    "hierarchy": [
      "tgn:1020352",
      "tgn:1000776",
      "tgn:1000046",
      "tgn:1000002",
      "tgn:7029392"
    ],
    "placetype": [
      "aat:300008347"
    ],
    "id": 1020352,
    "name:xx": "Padcaya"
  }
}
