{
  "geometry": {
    "type": "Point",
    "coordinates": [
      -111.2833,
      48.4667
    ]
  },
  "type": "Feature",
  "properties": {
    "hierarchy": [
      "tgn:2244241",
      "tgn:1000001",
      "tgn:7012149",
      "tgn:2001310",
      "tgn:7007524",
      "tgn:7029392"
    ],
    "placetype": [
      "aat:300008761"
    ],
    "id": 2244241,
    "name:xx": "Clift Coulee"
  }
}
