{
  "geometry": {
    "type": "Point",
    "coordinates": [
      117.45,
      40.3667
    ]
  },
  "type": "Feature",
  "properties": {
    "hierarchy": [
      "tgn:1069310",
      "tgn:1000004",
      "tgn:7002077",
      "tgn:1000111",
      "tgn:7029392"
    ],
    "placetype": [
      "aat:300008347"
    ],
    "id": 1069310,
    "name:xx": "Jinghuiling"
  }
}
