{
  "geometry": {
    "type": "Point",
    "coordinates": [
      -81.6667,
      29.45
    ]
  },
  "type": "Feature",
  "properties": {
    "hierarchy": [
      "tgn:2560167",
      "tgn:1000001",
      "tgn:7012149",
      "tgn:2000282",
      "tgn:7007240",
      "tgn:7029392"
    ],
    "placetype": [
      "aat:300008850"
    ],
    "id": 2560167,
    "name:xx": "Orange Point"
  }
}
