{
  "geometry": {
    "type": "Point",
    "coordinates": [
      -87.7333,
      34.6333
    ]
  },
  "type": "Feature",
  "properties": {
    "hierarchy": [
      "tgn:2285083",
      "tgn:7002659",
      "tgn:1000001",
      "tgn:2000016",
      "tgn:7012149",
      "tgn:7029392"
    ],
    "placetype": [
      "aat:300266640"
    ],
    "id": 2285083,
    "name:xx": "Devils Backbone"
  }
}
