{
  "geometry": {
    "type": "Point",
    "coordinates": [
      -108.0333,
      32.85
    ]
  },
  "type": "Feature",
  "properties": {
    "hierarchy": [
      "tgn:2373862",
      "tgn:1000001",
      "tgn:7012149",
      "tgn:2001437",
      "tgn:7007566",
      "tgn:7029392"
    ],
    "placetype": [
      "aat:300000390"
    ],
    "id": 2373862,
    "name:xx": "Hamlett Claims"
  }
}
