{
  "geometry": {
    "type": "Point",
    "coordinates": [
      5.20334,
      50.221738
    ]
  },
  "type": "Feature",
  "properties": {
    "hierarchy": [
      "tgn:7250257",
      "tgn:7003466",
      "tgn:1000003",
      "tgn:1000063",
      "tgn:4012014",
      "tgn:7029392"
    ],
    "placetype": [
      "aat:300008688"
    ],
    "id": 7250257,
    "name:xx": "Moulin, Étang du"
  }
}
