{
  "geometry": {
    "type": "Point",
    "coordinates": [
      74.8125,
      32.955556
    ]
  },
  "type": "Feature",
  "properties": {
    "hierarchy": [
      "tgn:7591823",
      "tgn:1000004",
      "tgn:7000198",
      "tgn:7000799",
      "tgn:7029392"
    ],
    "placetype": [
      "aat:300266554",
      "aat:300008699"
    ],
    "name:en": "Bāīwāli Khad",
    "id": 7591823
  }
}
