{
  "geometry": {
    "type": "Point",
    "coordinates": [
      -72.966667,
      -37.55
    ]
  },
  "type": "Feature",
  "properties": {
    "hierarchy": [
      "tgn:7285618",
      "tgn:1001637",
      "tgn:1000049",
      "tgn:1000002",
      "tgn:7029392"
    ],
    "placetype": [
      "aat:300008699"
    ],
    "id": 7285618,
    "name:xx": "Pichipehuén, Estero"
  }
}
