{
  "geometry": {
    "type": "Point",
    "coordinates": [
      -79.4167,
      33.5667
    ]
  },
  "type": "Feature",
  "properties": {
    "hierarchy": [
      "tgn:2611008",
      "tgn:1000001",
      "tgn:2001746",
      "tgn:7012149",
      "tgn:7007712",
      "tgn:7029392"
    ],
    "placetype": [
      "aat:300008347"
    ],
    "id": 2611008,
    "name:xx": "Red Hill"
  }
}
