{
  "geometry": {
    "type": "Point",
    "coordinates": [
      -114.9333,
      39.1333
    ]
  },
  "type": "Feature",
  "properties": {
    "hierarchy": [
      "tgn:2396507",
      "tgn:1000001",
      "tgn:7012149",
      "tgn:2001420",
      "tgn:7007526",
      "tgn:7029392"
    ],
    "placetype": [
      "aat:300008706"
    ],
    "id": 2396507,
    "name:xx": "Holt Creek"
  }
}
