{
  "geometry": {
    "type": "Point",
    "coordinates": [
      -67.8833,
      45.1667
    ]
  },
  "type": "Feature",
  "properties": {
    "hierarchy": [
      "tgn:2316417",
      "tgn:1000001",
      "tgn:7012149",
      "tgn:7014589",
      "tgn:7007515",
      "tgn:7029392"
    ],
    "placetype": [
      "aat:300008347"
    ],
    "id": 2316417,
    "name:xx": "Elsemore Landing"
  }
}
