{
  "type": "FeatureCollection",
  "features": [
    {
      "geometry": {
        "type": "Point",
        "coordinates": [
          -86.7667,
          45.4333
        ]
      },
      "type": "Feature",
      "properties": {
        "hierarchy": [
          "tgn:2637551",
          "tgn:1000001",
          "tgn:2000955",
          "tgn:7012149",
          "tgn:7007520",
          "tgn:7029392"
        ],
        "placetype": [
          "aat:300132348"
        ],
        "id": 2637551,
        "name:xx": "Saint Martin Island Shoals"
      }
    },
    {
      "geometry": {
        "type": "Point",
        "coordinates": [
          -84.6,
          45.9667
        ]
      },
      "type": "Feature",
      "properties": {
        "hierarchy": [
          "tgn:2637552",
          "tgn:1000001",
          "tgn:7012149",
          "tgn:2000973",
          "tgn:7007520",
          "tgn:7029392"
        ],
        "placetype": [
          "aat:300386853"
        ],
        "id": 2637552,
        "name:xx": "Saint Martin Islands"
      }
    },
    {
      "geometry": {
        "type": "Point",
        "coordinates": [
          -75.1167,
          38.4
        ]
      },
      "type": "Feature",
      "properties": {
        "hierarchy": [
          "tgn:2637553",
          "tgn:1000001",
          "tgn:1003037",
          "tgn:7012149",
          "tgn:7007516",
          "tgn:7029392"
        ],
        "placetype": [
          "aat:300008850"
        ],
        "id": 2637553,
        "name:xx": "Saint Martin Neck"
      }
    },
    {
      "geometry": {
        "type": "Point",
        "coordinates": [
          -84.5167,
          45.9667
        ]
      },
      "type": "Feature",
      "properties": {
        "hierarchy": [
          "tgn:2637554",
          "tgn:1000001",
          "tgn:7012149",
          "tgn:2000973",
          "tgn:7007520",
          "tgn:7029392"
        ],
        "placetype": [
          "aat:300008850"
        ],
        "id": 2637554,
        "name:xx": "Saint Martin Point"
      }
    },
    {
      "geometry": {
        "type": "Point",
        "coordinates": [
          -75.1667,
          38.4
        ]
      },
      "type": "Feature",
      "properties": {
        "hierarchy": [
          "tgn:2637555",
          "tgn:1000001",
          "tgn:1003037",
          "tgn:7012149",
          "tgn:7007516",
          "tgn:7029392"
        ],
        "placetype": [
          "aat:300008707"
        ],
        "id": 2637555,
        "name:xx": "Saint Martin River"
      }
    },
    {
      "geometry": {
        "type": "Point",
        "coordinates": [
          -84.8,
          44.6167
        ]
      },
      "type": "Feature",
      "properties": {
        "hierarchy": [
          "tgn:2637556",
          "tgn:1000001",
          "tgn:2000954",
          "tgn:7012149",
          "tgn:7007520",
          "tgn:7029392"
        ],
        "placetype": [
          "aat:300008798"
        ],
        "id": 2637556,
        "name:xx": "Saint Martin, Mont"
      }
    },
    {
      "geometry": {
        "type": "Point",
        "coordinates": [
          -75.1833,
          40.0667
        ]
      },
      "type": "Feature",
      "properties": {
        "hierarchy": [
          "tgn:2637557",
          "tgn:1000001",
          "tgn:7012149",
          "tgn:1002782",
          "tgn:7007710",
          "tgn:7029392"
        ],
        "placetype": [
          "aat:300008347"
        ],
        "id": 2637557,
        "name:xx": "Saint Martins"
      }
    },
    {
      "geometry": {
        "type": "Point",
        "coordinates": [
          -121.7833,
          45.7167
        ]
      },
      "type": "Feature",
      "properties": {
        "hierarchy": [
          "tgn:2637558",
          "tgn:1000001",
          "tgn:7012149",
          "tgn:1002897",
          "tgn:7007920",
          "tgn:7029392"
        ],
        "placetype": [
          "aat:300008347"
        ],
        "id": 2637558,
        "name:xx": "Saint Martins Hot Springs"
      }
    },
    {
      "geometry": {
        "type": "Point",
        "coordinates": [
          -121.7833,
          45.7167
        ]
      },
      "type": "Feature",
      "properties": {
        "hierarchy": [
          "tgn:2637559",
          "tgn:1000001",
          "tgn:7012149",
          "tgn:1002897",
          "tgn:7007920",
          "tgn:7029392"
        ],
        "placetype": [
          "aat:300008697"
        ],
        "id": 2637559,
        "name:xx": "Saint Martins Hot Springs"
      }
    }
  ]
}
