{
  "geometry": {
    "type": "Point",
    "coordinates": [
      -90.8167,
      37.4167
    ]
  },
  "type": "Feature",
  "properties": {
    "hierarchy": [
      "tgn:2756422",
      "tgn:1000001",
      "tgn:7012149",
      "tgn:2001236",
      "tgn:7007523",
      "tgn:7029392"
    ],
    "placetype": [
      "aat:300008746"
    ],
    "id": 2756422,
    "name:xx": "Well Cave"
  }
}
