{
  "type": "FeatureCollection",
  "features": [
    {
      "geometry": {
        "type": "Point",
        "coordinates": [
          109.8333,
          31.8
        ]
      },
      "type": "Feature",
      "properties": {
        "hierarchy": [
          "tgn:1068060",
          "tgn:1000004",
          "tgn:7002078",
          "tgn:1000111",
          "tgn:7029392"
        ],
        "placetype": [
          "aat:300008347"
        ],
        "id": 1068060,
        "name:xx": "Fengxi"
      }
    },
    {
      "geometry": {
        "type": "Point",
        "coordinates": [
          121.45,
          30.9167
        ]
      },
      "type": "Feature",
      "properties": {
        "hierarchy": [
          "tgn:1068061",
          "tgn:1000004",
          "tgn:1000958",
          "tgn:1000111",
          "tgn:7029392"
        ],
        "placetype": [
          "aat:300008347"
        ],
        "id": 1068061,
        "name:xx": "Fengxian"
      }
    },
    {
      "geometry": {
        "type": "Point",
        "coordinates": [
          115.3833,
          28.7
        ]
      },
      "type": "Feature",
      "properties": {
        "hierarchy": [
          "tgn:1068063",
          "tgn:1000004",
          "tgn:7002082",
          "tgn:1000111",
          "tgn:7029392"
        ],
        "placetype": [
          "aat:300008347"
        ],
        "id": 1068063,
        "name:xx": "Fengxin"
      }
    },
    {
      "geometry": {
        "type": "Point",
        "coordinates": [
          117.8833,
          24.8167
        ]
      },
      "type": "Feature",
      "properties": {
        "hierarchy": [
          "tgn:1068064",
          "tgn:1000004",
          "tgn:7001796",
          "tgn:1000111",
          "tgn:7029392"
        ],
        "placetype": [
          "aat:300008347"
        ],
        "id": 1068064,
        "name:xx": "Fengyang"
      }
    },
    {
      "geometry": {
        "type": "Point",
        "coordinates": [
          103.8667,
          31.6833
        ]
      },
      "type": "Feature",
      "properties": {
        "hierarchy": [
          "tgn:1068065",
          "tgn:1000004",
          "tgn:7002087",
          "tgn:1000111",
          "tgn:7029392"
        ],
        "placetype": [
          "aat:300008347"
        ],
        "id": 1068065,
        "name:xx": "Fengyi"
      }
    },
    {
      "geometry": {
        "type": "Point",
        "coordinates": [
          119.3,
          26.5167
        ]
      },
      "type": "Feature",
      "properties": {
        "hierarchy": [
          "tgn:1068066",
          "tgn:1000004",
          "tgn:7001796",
          "tgn:1000111",
          "tgn:7029392"
        ],
        "placetype": [
          "aat:300008347"
        ],
        "id": 1068066,
        "name:xx": "Fengyu"
      }
    },
    {
      "geometry": {
        "type": "Point",
        "coordinates": [
          113.1,
          40.4667
        ]
      },
      "type": "Feature",
      "properties": {
        "hierarchy": [
          "tgn:1068067",
          "tgn:1000004",
          "tgn:7001838",
          "tgn:1000111",
          "tgn:7029392"
        ],
        "placetype": [
          "aat:300008347"
        ],
        "id": 1068067,
        "name:xx": "Fengzhen"
      }
    },
    {
      "geometry": {
        "type": "Point",
        "coordinates": [
          113.8667,
          25.6833
        ]
      },
      "type": "Feature",
      "properties": {
        "hierarchy": [
          "tgn:1068068",
          "tgn:1000004",
          "tgn:7002079",
          "tgn:1000111",
          "tgn:7029392"
        ],
        "placetype": [
          "aat:300008347"
        ],
        "id": 1068068,
        "name:xx": "Fengzhou"
      }
    },
    {
      "geometry": {
        "type": "Point",
        "coordinates": [
          118.65,
          31
        ]
      },
      "type": "Feature",
      "properties": {
        "hierarchy": [
          "tgn:1068069",
          "tgn:7002075",
          "tgn:1000004",
          "tgn:1000111",
          "tgn:7029392"
        ],
        "placetype": [
          "aat:300008347"
        ],
        "id": 1068069,
        "name:xx": "Fengzhuangtou"
      }
    }
  ]
}
