{
  "type": "FeatureCollection",
  "features": [
    {
      "geometry": {
        "type": "Point",
        "coordinates": [
          -73.45,
          -37.366667
        ]
      },
      "type": "Feature",
      "properties": {
        "hierarchy": [
          "tgn:7317900",
          "tgn:1001637",
          "tgn:1000049",
          "tgn:1000002",
          "tgn:7029392"
        ],
        "placetype": [
          "aat:300008699"
        ],
        "id": 7317900,
        "name:xx": "Colorado, Río"
      }
    },
    {
      "geometry": {
        "type": "Point",
        "coordinates": [
          -71.016667,
          -35.266667
        ]
      },
      "type": "Feature",
      "properties": {
        "hierarchy": [
          "tgn:7317901",
          "tgn:1001705",
          "tgn:1000049",
          "tgn:1000002",
          "tgn:7029392"
        ],
        "placetype": [
          "aat:300008699"
        ],
        "id": 7317901,
        "name:xx": "Colorado, Río"
      }
    },
    {
      "geometry": {
        "type": "Point",
        "coordinates": [
          -70.383333,
          -33.6
        ]
      },
      "type": "Feature",
      "properties": {
        "hierarchy": [
          "tgn:7317902",
          "tgn:1001708",
          "tgn:1000049",
          "tgn:1000002",
          "tgn:7029392"
        ],
        "placetype": [
          "aat:300008699"
        ],
        "id": 7317902,
        "name:xx": "Colorado, Río"
      }
    },
    {
      "geometry": {
        "type": "Point",
        "coordinates": [
          -70.433333,
          -32.866667
        ]
      },
      "type": "Feature",
      "properties": {
        "hierarchy": [
          "tgn:7317903",
          "tgn:1001708",
          "tgn:1000049",
          "tgn:1000002",
          "tgn:7029392"
        ],
        "placetype": [
          "aat:300008699"
        ],
        "id": 7317903,
        "name:xx": "Colorado, Río"
      }
    },
    {
      "geometry": {
        "type": "Point",
        "coordinates": [
          -70.416667,
          -30.966667
        ]
      },
      "type": "Feature",
      "properties": {
        "hierarchy": [
          "tgn:7317905",
          "tgn:1001657",
          "tgn:1000049",
          "tgn:1000002",
          "tgn:7029392"
        ],
        "placetype": [
          "aat:300008699"
        ],
        "id": 7317905,
        "name:xx": "Colorado, Río"
      }
    },
    {
      "geometry": {
        "type": "Point",
        "coordinates": [
          -70.416667,
          -30.783333
        ]
      },
      "type": "Feature",
      "properties": {
        "hierarchy": [
          "tgn:7317906",
          "tgn:1001657",
          "tgn:1000049",
          "tgn:1000002",
          "tgn:7029392"
        ],
        "placetype": [
          "aat:300008699"
        ],
        "id": 7317906,
        "name:xx": "Colorado, Río"
      }
    },
    {
      "geometry": {
        "type": "Point",
        "coordinates": [
          -70.033333,
          -30.266667
        ]
      },
      "type": "Feature",
      "properties": {
        "hierarchy": [
          "tgn:7317907",
          "tgn:1001657",
          "tgn:1000049",
          "tgn:1000002",
          "tgn:7029392"
        ],
        "placetype": [
          "aat:300008699"
        ],
        "id": 7317907,
        "name:xx": "Colorado, Río"
      }
    },
    {
      "geometry": {
        "type": "Point",
        "coordinates": [
          -70.7,
          -32.416667
        ]
      },
      "type": "Feature",
      "properties": {
        "hierarchy": [
          "tgn:7317908",
          "tgn:1001768",
          "tgn:1000049",
          "tgn:1000002",
          "tgn:7029392"
        ],
        "placetype": [
          "aat:300008699"
        ],
        "id": 7317908,
        "name:xx": "Colorado, Quebrada del"
      }
    },
    {
      "geometry": {
        "type": "Point",
        "coordinates": [
          -69.55,
          -27.133333
        ]
      },
      "type": "Feature",
      "properties": {
        "hierarchy": [
          "tgn:7317909",
          "tgn:1001630",
          "tgn:1000049",
          "tgn:1000002",
          "tgn:7029392"
        ],
        "placetype": [
          "aat:300266554",
          "aat:300008699"
        ],
        "id": 7317909,
        "name:xx": "Colorado, Quebrada"
      }
    }
  ]
}
