{
  "geometry": {
    "type": "Point",
    "coordinates": [
      75.0167,
      36.8667
    ]
  },
  "type": "Feature",
  "properties": {
    "hierarchy": [
      "tgn:1083529",
      "tgn:7000367",
      "tgn:1000004",
      "tgn:1000133",
      "tgn:7029392"
    ],
    "placetype": [
      "aat:300008347"
    ],
    "id": 1083529,
    "name:xx": "Jun Kharchanai"
  }
}
