{
  "geometry": {
    "type": "Point",
    "coordinates": [
      -112.3667,
      34.9333
    ]
  },
  "type": "Feature",
  "properties": {
    "hierarchy": [
      "tgn:2458770",
      "tgn:1000001",
      "tgn:7006451",
      "tgn:7012149",
      "tgn:2000103",
      "tgn:7029392"
    ],
    "placetype": [
      "aat:300006191"
    ],
    "id": 2458770,
    "name:xx": "Little Page Tank"
  }
}
