{
  "geometry": {
    "type": "Point",
    "coordinates": [
      36.9167,
      62.3333
    ]
  },
  "type": "Feature",
  "properties": {
    "hierarchy": [
      "tgn:1118598",
      "tgn:1000004",
      "tgn:7011509",
      "tgn:7002435",
      "tgn:7029392"
    ],
    "placetype": [
      "aat:300008680"
    ],
    "id": 1118598,
    "name:xx": "Vodlozero, Ozero"
  }
}
