{
  "geometry": {
    "type": "Point",
    "coordinates": [
      -90.8333,
      43.4167
    ]
  },
  "type": "Feature",
  "properties": {
    "hierarchy": [
      "tgn:2425500",
      "tgn:1000001",
      "tgn:7012149",
      "tgn:7007922",
      "tgn:7029392"
    ],
    "placetype": [
      "aat:300008761"
    ],
    "id": 2425500,
    "name:xx": "Johnson Valley"
  }
}
