{
  "geometry": {
    "type": "Point",
    "coordinates": [
      -120.55,
      44.5167
    ]
  },
  "type": "Feature",
  "properties": {
    "hierarchy": [
      "tgn:2698123",
      "tgn:1000001",
      "tgn:2001703",
      "tgn:7012149",
      "tgn:7007708",
      "tgn:7029392"
    ],
    "placetype": [
      "aat:300008697"
    ],
    "id": 2698123,
    "name:xx": "Stove Spring"
  }
}
