{
  "type": "FeatureCollection",
  "features": [
    {
      "geometry": {
        "type": "Point",
        "coordinates": [
          -6.283333,
          55.633333
        ]
      },
      "type": "Feature",
      "properties": {
        "hierarchy": [
          "tgn:7456710",
          "tgn:7019094",
          "tgn:7002444",
          "tgn:1000003",
          "tgn:7008591",
          "tgn:7029392"
        ],
        "placetype": [
          "aat:300008804"
        ],
        "name:en": "Oa, The",
        "id": 7456710
      }
    },
    {
      "geometry": {
        "type": "Point",
        "coordinates": [
          -6.15,
          54.633333
        ]
      },
      "type": "Feature",
      "properties": {
        "hierarchy": [
          "tgn:7456714",
          "tgn:7008695",
          "tgn:7002448",
          "tgn:1000003",
          "tgn:7008591",
          "tgn:7029392"
        ],
        "placetype": [
          "aat:300008347"
        ],
        "name:en": "Nutts Corner",
        "id": 7456714
      }
    },
    {
      "geometry": {
        "type": "Point",
        "coordinates": [
          0.05,
          51.016667
        ]
      },
      "type": "Feature",
      "properties": {
        "hierarchy": [
          "tgn:7456716",
          "tgn:7002445",
          "tgn:1000003",
          "tgn:7008129",
          "tgn:7008591",
          "tgn:7029392"
        ],
        "placetype": [
          "aat:300008347"
        ],
        "name:en": "Nutley",
        "id": 7456716
      }
    },
    {
      "geometry": {
        "type": "Point",
        "coordinates": [
          -0.3,
          51
        ]
      },
      "type": "Feature",
      "properties": {
        "hierarchy": [
          "tgn:7456717",
          "tgn:7002445",
          "tgn:1000003",
          "tgn:7008134",
          "tgn:7008591",
          "tgn:7029392"
        ],
        "placetype": [
          "aat:300008347"
        ],
        "name:en": "Nuthurst",
        "id": 7456717
      }
    }
  ]
}
