{
  "geometry": {
    "type": "Point",
    "coordinates": [
      -113.0667,
      45.3333
    ]
  },
  "type": "Feature",
  "properties": {
    "hierarchy": [
      "tgn:2692729",
      "tgn:1000001",
      "tgn:2001260",
      "tgn:7012149",
      "tgn:7007524",
      "tgn:7029392"
    ],
    "placetype": [
      "aat:300008706"
    ],
    "id": 2692729,
    "name:xx": "Steel Creek"
  }
}
