{
  "geometry": {
    "type": "Point",
    "coordinates": [
      75.63067,
      21.169715
    ]
  },
  "type": "Feature",
  "properties": {
    "hierarchy": [
      "tgn:7556961",
      "tgn:1000004",
      "tgn:7000198",
      "tgn:1001895",
      "tgn:7029392"
    ],
    "placetype": [
      "aat:300008347"
    ],
    "name:en": "Sākli",
    "id": 7556961
  }
}
