{
  "type": "FeatureCollection",
  "features": [
    {
      "geometry": {
        "type": "Point",
        "coordinates": [
          -1.95,
          55.316667
        ]
      },
      "type": "Feature",
      "properties": {
        "hierarchy": [
          "tgn:7446360",
          "tgn:7002445",
          "tgn:1000003",
          "tgn:7008165",
          "tgn:7008591",
          "tgn:7029392"
        ],
        "placetype": [
          "aat:300008347"
        ],
        "name:en": "Snitter",
        "id": 7446360
      }
    },
    {
      "geometry": {
        "type": "Point",
        "coordinates": [
          -3.366667,
          58.833333
        ]
      },
      "type": "Feature",
      "properties": {
        "hierarchy": [
          "tgn:7446361",
          "tgn:7002444",
          "tgn:1000003",
          "tgn:7009907",
          "tgn:7008591",
          "tgn:7029392"
        ],
        "placetype": [
          "aat:300008850"
        ],
        "name:en": "Sneuk Head",
        "id": 7446361
      }
    },
    {
      "geometry": {
        "type": "Point",
        "coordinates": [
          -2.916667,
          59.3
        ]
      },
      "type": "Feature",
      "properties": {
        "hierarchy": [
          "tgn:7446362",
          "tgn:7002444",
          "tgn:1000003",
          "tgn:7009907",
          "tgn:7008591",
          "tgn:7029392"
        ],
        "placetype": [
          "aat:300008808"
        ],
        "name:en": "Sneuk",
        "id": 7446362
      }
    },
    {
      "geometry": {
        "type": "Point",
        "coordinates": [
          0.966667,
          52.466667
        ]
      },
      "type": "Feature",
      "properties": {
        "hierarchy": [
          "tgn:7446364",
          "tgn:7002445",
          "tgn:1000003",
          "tgn:7008160",
          "tgn:7008591",
          "tgn:7029392"
        ],
        "placetype": [
          "aat:300387502"
        ],
        "name:en": "Snetterton Heath",
        "id": 7446364
      }
    }
  ]
}
