{
  "type": "FeatureCollection",
  "features": [
    {
      "geometry": {
        "type": "Point",
        "coordinates": [
          -71.633333,
          -31.25
        ]
      },
      "type": "Feature",
      "properties": {
        "hierarchy": [
          "tgn:7311730",
          "tgn:1001657",
          "tgn:1000049",
          "tgn:1000002",
          "tgn:7029392"
        ],
        "placetype": [
          "aat:300008699"
        ],
        "id": 7311730,
        "name:xx": "Las Palmas, Quebrada"
      }
    },
    {
      "geometry": {
        "type": "Point",
        "coordinates": [
          -71.166667,
          -33.95
        ]
      },
      "type": "Feature",
      "properties": {
        "hierarchy": [
          "tgn:7311731",
          "tgn:1001708",
          "tgn:1000049",
          "tgn:1000002",
          "tgn:7029392"
        ],
        "placetype": [
          "aat:300008795"
        ],
        "id": 7311731,
        "name:xx": "Las Palmas, Morro"
      }
    },
    {
      "geometry": {
        "type": "Point",
        "coordinates": [
          -71.533333,
          -33.533333
        ]
      },
      "type": "Feature",
      "properties": {
        "hierarchy": [
          "tgn:7311732",
          "tgn:1001708",
          "tgn:1000049",
          "tgn:1000002",
          "tgn:7029392"
        ],
        "placetype": [
          "aat:300008699"
        ],
        "id": 7311732,
        "name:xx": "Las Palmas, Estero de"
      }
    },
    {
      "geometry": {
        "type": "Point",
        "coordinates": [
          -71.483333,
          -33.066667
        ]
      },
      "type": "Feature",
      "properties": {
        "hierarchy": [
          "tgn:7311733",
          "tgn:1001768",
          "tgn:1000049",
          "tgn:1000002",
          "tgn:7029392"
        ],
        "placetype": [
          "aat:300008699"
        ],
        "id": 7311733,
        "name:xx": "Las Palmas, Estero de"
      }
    },
    {
      "geometry": {
        "type": "Point",
        "coordinates": [
          -72.066667,
          -35.416667
        ]
      },
      "type": "Feature",
      "properties": {
        "hierarchy": [
          "tgn:7311734",
          "tgn:1001705",
          "tgn:1000049",
          "tgn:1000002",
          "tgn:7029392"
        ],
        "placetype": [
          "aat:300008699"
        ],
        "id": 7311734,
        "name:xx": "Las Palmas, Estero"
      }
    },
    {
      "geometry": {
        "type": "Point",
        "coordinates": [
          -71.783333,
          -35.283333
        ]
      },
      "type": "Feature",
      "properties": {
        "hierarchy": [
          "tgn:7311735",
          "tgn:1001705",
          "tgn:1000049",
          "tgn:1000002",
          "tgn:7029392"
        ],
        "placetype": [
          "aat:300008699"
        ],
        "id": 7311735,
        "name:xx": "Las Palmas, Estero"
      }
    },
    {
      "geometry": {
        "type": "Point",
        "coordinates": [
          -71.566667,
          -34.85
        ]
      },
      "type": "Feature",
      "properties": {
        "hierarchy": [
          "tgn:7311736",
          "tgn:1001695",
          "tgn:1000049",
          "tgn:1000002",
          "tgn:7029392"
        ],
        "placetype": [
          "aat:300008699"
        ],
        "id": 7311736,
        "name:xx": "Las Palmas, Estero"
      }
    },
    {
      "geometry": {
        "type": "Point",
        "coordinates": [
          -71.383333,
          -34.15
        ]
      },
      "type": "Feature",
      "properties": {
        "hierarchy": [
          "tgn:7311737",
          "tgn:1001708",
          "tgn:1000049",
          "tgn:1000002",
          "tgn:7029392"
        ],
        "placetype": [
          "aat:300008699"
        ],
        "id": 7311737,
        "name:xx": "Las Palmas, Estero"
      }
    },
    {
      "geometry": {
        "type": "Point",
        "coordinates": [
          -71.583333,
          -34.05
        ]
      },
      "type": "Feature",
      "properties": {
        "hierarchy": [
          "tgn:7311738",
          "tgn:1001708",
          "tgn:1000049",
          "tgn:1000002",
          "tgn:7029392"
        ],
        "placetype": [
          "aat:300008699"
        ],
        "id": 7311738,
        "name:xx": "Las Palmas, Estero"
      }
    },
    {
      "geometry": {
        "type": "Point",
        "coordinates": [
          -71.083333,
          -32.333333
        ]
      },
      "type": "Feature",
      "properties": {
        "hierarchy": [
          "tgn:7311739",
          "tgn:1001768",
          "tgn:1000049",
          "tgn:1000002",
          "tgn:7029392"
        ],
        "placetype": [
          "aat:300008699"
        ],
        "id": 7311739,
        "name:xx": "Las Palmas, Estero"
      }
    }
  ]
}
