{
  "geometry": {
    "type": "Point",
    "coordinates": [
      -104.6167,
      37.1333
    ]
  },
  "type": "Feature",
  "properties": {
    "hierarchy": [
      "tgn:2015347",
      "tgn:1000001",
      "tgn:7012149",
      "tgn:2000227",
      "tgn:7007158",
      "tgn:7029392"
    ],
    "placetype": [
      "aat:300008347"
    ],
    "id": 2015347,
    "name:xx": "Cokedale"
  }
}
