{
  "geometry": {
    "type": "Point",
    "coordinates": [
      22.083,
      45.083
    ]
  },
  "type": "Feature",
  "properties": {
    "hierarchy": [
      "tgn:7018684",
      "tgn:1000003",
      "tgn:1000091",
      "tgn:7029392"
    ],
    "placetype": [
      "aat:300008795"
    ],
    "id": 7018684,
    "name:xx": "Semenicului, Munţii"
  }
}
