{
  "geometry": {
    "type": "Point",
    "coordinates": [
      -100.5667,
      44.3667
    ]
  },
  "type": "Feature",
  "properties": {
    "hierarchy": [
      "tgn:2596734",
      "tgn:1000001",
      "tgn:7012149",
      "tgn:2001828",
      "tgn:7007713",
      "tgn:7029392"
    ],
    "placetype": [
      "aat:300008706"
    ],
    "id": 2596734,
    "name:xx": "Powell Creek"
  }
}
