{
  "geometry": {
    "type": "Point",
    "coordinates": [
      120.83,
      23.655
    ]
  },
  "type": "Feature",
  "properties": {
    "hierarchy": [
      "tgn:7500949",
      "tgn:7488858",
      "tgn:1000004",
      "tgn:1000141",
      "tgn:7029392"
    ],
    "placetype": [
      "aat:300008865"
    ],
    "id": 7500949,
    "name:xx": "Taida Shiyanlin"
  }
}
