{
  "geometry": {
    "type": "Point",
    "coordinates": [
      -149.1333,
      60.6667
    ]
  },
  "type": "Feature",
  "properties": {
    "hierarchy": [
      "tgn:2289055",
      "tgn:7006450",
      "tgn:1000001",
      "tgn:7019698",
      "tgn:7012149",
      "tgn:7029392"
    ],
    "placetype": [
      "aat:300008706"
    ],
    "id": 2289055,
    "name:xx": "Divide Creek"
  }
}
