{
  "geometry": {
    "type": "Point",
    "coordinates": [
      -80.85,
      27.2667
    ]
  },
  "type": "Feature",
  "properties": {
    "hierarchy": [
      "tgn:2151046",
      "tgn:1000001",
      "tgn:7012149",
      "tgn:1002743",
      "tgn:7007240",
      "tgn:7029392"
    ],
    "placetype": [
      "aat:300008347"
    ],
    "id": 2151046,
    "name:xx": "Basswood Estates"
  }
}
