{
  "type": "FeatureCollection",
  "features": [
    {
      "geometry": {
        "type": "Point",
        "coordinates": [
          -117.3167,
          34
        ]
      },
      "type": "Feature",
      "properties": {
        "hierarchy": [
          "tgn:2012210",
          "tgn:1000001",
          "tgn:7012149",
          "tgn:7007157",
          "tgn:1002828",
          "tgn:7029392"
        ],
        "placetype": [
          "aat:300387016"
        ],
        "id": 2012210,
        "name:xx": "Lily Cup"
      }
    },
    {
      "geometry": {
        "type": "Point",
        "coordinates": [
          -119.1167,
          34.3167
        ]
      },
      "type": "Feature",
      "properties": {
        "hierarchy": [
          "tgn:2012212",
          "tgn:1000001",
          "tgn:7012149",
          "tgn:7007157",
          "tgn:1002972",
          "tgn:7029392"
        ],
        "placetype": [
          "aat:300008347"
        ],
        "id": 2012212,
        "name:xx": "Limco"
      }
    },
    {
      "geometry": {
        "type": "Point",
        "coordinates": [
          -121.2833,
          38.8833
        ]
      },
      "type": "Feature",
      "properties": {
        "hierarchy": [
          "tgn:2012214",
          "tgn:1000001",
          "tgn:7012149",
          "tgn:7007157",
          "tgn:1002791",
          "tgn:7029392"
        ],
        "placetype": [
          "aat:300008347"
        ],
        "id": 2012214,
        "name:xx": "Lincoln"
      }
    },
    {
      "geometry": {
        "type": "Point",
        "coordinates": [
          -117.0667,
          32.6667
        ]
      },
      "type": "Feature",
      "properties": {
        "hierarchy": [
          "tgn:2012215",
          "tgn:1000001",
          "tgn:7012149",
          "tgn:7007157",
          "tgn:1002858",
          "tgn:7029392"
        ],
        "placetype": [
          "aat:300008347"
        ],
        "id": 2012215,
        "name:xx": "Lincoln Acres"
      }
    },
    {
      "geometry": {
        "type": "Point",
        "coordinates": [
          -121.3167,
          38
        ]
      },
      "type": "Feature",
      "properties": {
        "hierarchy": [
          "tgn:2012216",
          "tgn:1000001",
          "tgn:7012149",
          "tgn:7007157",
          "tgn:1002861",
          "tgn:7029392"
        ],
        "placetype": [
          "aat:300008347"
        ],
        "id": 2012216,
        "name:xx": "Lincoln Village"
      }
    },
    {
      "geometry": {
        "type": "Point",
        "coordinates": [
          -121.5333,
          39.1167
        ]
      },
      "type": "Feature",
      "properties": {
        "hierarchy": [
          "tgn:2012217",
          "tgn:1000001",
          "tgn:7012149",
          "tgn:7007157",
          "tgn:1003050",
          "tgn:7029392"
        ],
        "placetype": [
          "aat:300008347"
        ],
        "id": 2012217,
        "name:xx": "Linda"
      }
    }
  ]
}
