{
  "geometry": {
    "type": "Point",
    "coordinates": [
      -86.0667,
      35.0667
    ]
  },
  "type": "Feature",
  "properties": {
    "hierarchy": [
      "tgn:2388382",
      "tgn:1000001",
      "tgn:7012149",
      "tgn:2001862",
      "tgn:7007825",
      "tgn:7029392"
    ],
    "placetype": [
      "aat:300266640"
    ],
    "id": 2388382,
    "name:xx": "Hickory Ridge"
  }
}
