{
  "geometry": {
    "type": "Point",
    "coordinates": [
      -52.5167,
      -26.9333
    ]
  },
  "type": "Feature",
  "properties": {
    "hierarchy": [
      "tgn:1023360",
      "tgn:7006262",
      "tgn:1000047",
      "tgn:7002458",
      "tgn:1000002",
      "tgn:7029392"
    ],
    "placetype": [
      "aat:300008347"
    ],
    "id": 1023360,
    "name:xx": "Xaxim"
  }
}
