{
  "type": "FeatureCollection",
  "features": [
    {
      "geometry": {
        "type": "Point",
        "coordinates": [
          4.7,
          50.683333
        ]
      },
      "type": "Feature",
      "properties": {
        "hierarchy": [
          "tgn:7239921",
          "tgn:7018238",
          "tgn:1000003",
          "tgn:1000063",
          "tgn:4012014",
          "tgn:7029392"
        ],
        "placetype": [
          "aat:300008347"
        ],
        "id": 7239921,
        "name:xx": "Gistoux"
      }
    },
    {
      "geometry": {
        "type": "Point",
        "coordinates": [
          6.016667,
          50.7
        ]
      },
      "type": "Feature",
      "properties": {
        "hierarchy": [
          "tgn:7239924",
          "tgn:7003460",
          "tgn:1000003",
          "tgn:1000063",
          "tgn:4012014",
          "tgn:7029392"
        ],
        "placetype": [
          "aat:300000206"
        ],
        "id": 7239924,
        "name:xx": "Gippenhag"
      }
    },
    {
      "geometry": {
        "type": "Point",
        "coordinates": [
          3.353494,
          50.945669
        ]
      },
      "type": "Feature",
      "properties": {
        "hierarchy": [
          "tgn:7239925",
          "tgn:7003458",
          "tgn:1000003",
          "tgn:1000063",
          "tgn:7018236",
          "tgn:7029392"
        ],
        "placetype": [
          "aat:300008347"
        ],
        "id": 7239925,
        "name:xx": "Ginste"
      }
    },
    {
      "geometry": {
        "type": "Point",
        "coordinates": [
          3.783333,
          50.733333
        ]
      },
      "type": "Feature",
      "properties": {
        "hierarchy": [
          "tgn:7239926",
          "tgn:7007877",
          "tgn:1000003",
          "tgn:1000063",
          "tgn:4012014",
          "tgn:7029392"
        ],
        "placetype": [
          "aat:300008347"
        ],
        "id": 7239926,
        "name:xx": "Ginintreau"
      }
    },
    {
      "geometry": {
        "type": "Point",
        "coordinates": [
          4.866667,
          51.4
        ]
      },
      "type": "Feature",
      "properties": {
        "hierarchy": [
          "tgn:7239927",
          "tgn:7003456",
          "tgn:1000003",
          "tgn:1000063",
          "tgn:7018236",
          "tgn:7029392"
        ],
        "placetype": [
          "aat:300008347"
        ],
        "id": 7239927,
        "name:xx": "Ginhoven"
      }
    },
    {
      "geometry": {
        "type": "Point",
        "coordinates": [
          5.133157,
          50.749215
        ]
      },
      "type": "Feature",
      "properties": {
        "hierarchy": [
          "tgn:7239928",
          "tgn:7003461",
          "tgn:1000003",
          "tgn:1000063",
          "tgn:7018236",
          "tgn:7029392"
        ],
        "placetype": [
          "aat:300008347"
        ],
        "id": 7239928,
        "name:xx": "Gingelom"
      }
    }
  ]
}
