{
  "geometry": {
    "type": "Point",
    "coordinates": [
      -119.9833,
      38.9333
    ]
  },
  "type": "Feature",
  "properties": {
    "hierarchy": [
      "tgn:2730411",
      "tgn:1000001",
      "tgn:7012149",
      "tgn:1002350",
      "tgn:7007157",
      "tgn:7029392"
    ],
    "placetype": [
      "aat:300008905"
    ],
    "id": 2730411,
    "name:xx": "Truckee Marsh"
  }
}
