{
  "geometry": {
    "type": "Point",
    "coordinates": [
      126.0167,
      39.3833
    ]
  },
  "type": "Feature",
  "properties": {
    "hierarchy": [
      "tgn:7002229",
      "tgn:1000004",
      "tgn:1001477",
      "tgn:1000122",
      "tgn:7029392"
    ],
    "placetype": [
      "aat:300008347"
    ],
    "id": 7002229,
    "name:xx": "Unsan"
  }
}
