{
  "geometry": {
    "type": "Point",
    "coordinates": [
      -97.3667,
      45.35
    ]
  },
  "type": "Feature",
  "properties": {
    "hierarchy": [
      "tgn:2633841",
      "tgn:1000001",
      "tgn:2001788",
      "tgn:7012149",
      "tgn:7007713",
      "tgn:7029392"
    ],
    "placetype": [
      "aat:300008680"
    ],
    "id": 2633841,
    "name:xx": "Rush Lake"
  }
}
