{
  "geometry": {
    "type": "Point",
    "coordinates": [
      85.398026,
      21.972413
    ]
  },
  "type": "Feature",
  "properties": {
    "hierarchy": [
      "tgn:7550581",
      "tgn:1000004",
      "tgn:7000198",
      "tgn:7016694",
      "tgn:7029392"
    ],
    "placetype": [
      "aat:300008777"
    ],
    "name:en": "Dāl Pahār",
    "id": 7550581
  }
}
