{
  "type": "FeatureCollection",
  "features": [
    {
      "geometry": {
        "type": "Point",
        "coordinates": [
          -89.9667,
          32.8833
        ]
      },
      "type": "Feature",
      "properties": {
        "hierarchy": [
          "tgn:2057222",
          "tgn:1000001",
          "tgn:7012149",
          "tgn:2001111",
          "tgn:7007522",
          "tgn:7029392"
        ],
        "placetype": [
          "aat:300008347"
        ],
        "id": 2057222,
        "name:xx": "Pickens"
      }
    },
    {
      "geometry": {
        "type": "Point",
        "coordinates": [
          -89.8333,
          31.1333
        ]
      },
      "type": "Feature",
      "properties": {
        "hierarchy": [
          "tgn:2057223",
          "tgn:1000001",
          "tgn:7012149",
          "tgn:2001131",
          "tgn:7007522",
          "tgn:7029392"
        ],
        "placetype": [
          "aat:300008347",
          "aat:300387210"
        ],
        "id": 2057223,
        "name:xx": "Pickwick"
      }
    },
    {
      "geometry": {
        "type": "Point",
        "coordinates": [
          -89.6,
          32.6333
        ]
      },
      "type": "Feature",
      "properties": {
        "hierarchy": [
          "tgn:2057225",
          "tgn:1000001",
          "tgn:7012149",
          "tgn:2001125",
          "tgn:7007522",
          "tgn:7029392"
        ],
        "placetype": [
          "aat:300008347",
          "aat:300387210"
        ],
        "id": 2057225,
        "name:xx": "Piggtown"
      }
    },
    {
      "geometry": {
        "type": "Point",
        "coordinates": [
          -89.35,
          32.4833
        ]
      },
      "type": "Feature",
      "properties": {
        "hierarchy": [
          "tgn:2057226",
          "tgn:1000001",
          "tgn:7012149",
          "tgn:2001147",
          "tgn:7007522",
          "tgn:7029392"
        ],
        "placetype": [
          "aat:300008347",
          "aat:300387210"
        ],
        "id": 2057226,
        "name:xx": "Piketown"
      }
    },
    {
      "geometry": {
        "type": "Point",
        "coordinates": [
          -91.4667,
          31
        ]
      },
      "type": "Feature",
      "properties": {
        "hierarchy": [
          "tgn:2057228",
          "tgn:1000001",
          "tgn:7012149",
          "tgn:2001164",
          "tgn:7007522",
          "tgn:7029392"
        ],
        "placetype": [
          "aat:300008347",
          "aat:300387210"
        ],
        "id": 2057228,
        "name:xx": "Pinckneyville"
      }
    }
  ]
}
