{
  "geometry": {
    "type": "Point",
    "coordinates": [
      -107.6167,
      35.2833
    ]
  },
  "type": "Feature",
  "properties": {
    "hierarchy": [
      "tgn:2637975",
      "tgn:1000001",
      "tgn:2001431",
      "tgn:7012149",
      "tgn:7007566",
      "tgn:7029392"
    ],
    "placetype": [
      "aat:300006191"
    ],
    "id": 2637975,
    "name:xx": "Salazar Tank"
  }
}
