{
  "geometry": {
    "type": "Point",
    "coordinates": [
      -78.45,
      38.8833
    ]
  },
  "type": "Feature",
  "properties": {
    "hierarchy": [
      "tgn:2263481",
      "tgn:1000001",
      "tgn:7012149",
      "tgn:2002190",
      "tgn:7007919",
      "tgn:7029392"
    ],
    "placetype": [
      "aat:300266640"
    ],
    "id": 2263481,
    "name:xx": "Cox Ridge"
  }
}
