{
  "type": "FeatureCollection",
  "features": [
    {
      "geometry": {
        "type": "Point",
        "coordinates": [
          -97.3,
          44.2167
        ]
      },
      "type": "Feature",
      "properties": {
        "hierarchy": [
          "tgn:2097420",
          "tgn:1000001",
          "tgn:2001808",
          "tgn:7012149",
          "tgn:7007713",
          "tgn:7029392"
        ],
        "placetype": [
          "aat:300008347"
        ],
        "id": 2097420,
        "name:xx": "Oldham"
      }
    },
    {
      "geometry": {
        "type": "Point",
        "coordinates": [
          -97.6667,
          43.2333
        ]
      },
      "type": "Feature",
      "properties": {
        "hierarchy": [
          "tgn:2097421",
          "tgn:1000001",
          "tgn:2001803",
          "tgn:7012149",
          "tgn:7007713",
          "tgn:7029392"
        ],
        "placetype": [
          "aat:300008347"
        ],
        "id": 2097421,
        "name:xx": "Olivet"
      }
    },
    {
      "geometry": {
        "type": "Point",
        "coordinates": [
          -100.6,
          43.1167
        ]
      },
      "type": "Feature",
      "properties": {
        "hierarchy": [
          "tgn:2097422",
          "tgn:1000001",
          "tgn:7012149",
          "tgn:2001830",
          "tgn:7007713",
          "tgn:7029392"
        ],
        "placetype": [
          "aat:300008347",
          "aat:300387210"
        ],
        "id": 2097422,
        "name:xx": "Olsonville"
      }
    },
    {
      "geometry": {
        "type": "Point",
        "coordinates": [
          -99.45,
          45.1833
        ]
      },
      "type": "Feature",
      "properties": {
        "hierarchy": [
          "tgn:2097423",
          "tgn:1000001",
          "tgn:2001794",
          "tgn:7012149",
          "tgn:7007713",
          "tgn:7029392"
        ],
        "placetype": [
          "aat:300008347"
        ],
        "id": 2097423,
        "name:xx": "Onaka"
      }
    },
    {
      "geometry": {
        "type": "Point",
        "coordinates": [
          -100.05,
          44.7
        ]
      },
      "type": "Feature",
      "properties": {
        "hierarchy": [
          "tgn:2097424",
          "tgn:1000001",
          "tgn:7012149",
          "tgn:2001829",
          "tgn:7007713",
          "tgn:7029392"
        ],
        "placetype": [
          "aat:300008347"
        ],
        "id": 2097424,
        "name:xx": "Onida"
      }
    },
    {
      "geometry": {
        "type": "Point",
        "coordinates": [
          -102.45,
          44.8833
        ]
      },
      "type": "Feature",
      "properties": {
        "hierarchy": [
          "tgn:2097425",
          "tgn:1000001",
          "tgn:2001816",
          "tgn:7012149",
          "tgn:7007713",
          "tgn:7029392"
        ],
        "placetype": [
          "aat:300008347"
        ],
        "id": 2097425,
        "name:xx": "Opal"
      }
    },
    {
      "geometry": {
        "type": "Point",
        "coordinates": [
          -103.2667,
          43.4
        ]
      },
      "type": "Feature",
      "properties": {
        "hierarchy": [
          "tgn:2097426",
          "tgn:1000001",
          "tgn:2001793",
          "tgn:7012149",
          "tgn:7007713",
          "tgn:7029392"
        ],
        "placetype": [
          "aat:300008347"
        ],
        "id": 2097426,
        "name:xx": "Oral"
      }
    },
    {
      "geometry": {
        "type": "Point",
        "coordinates": [
          -98.4,
          45.5667
        ]
      },
      "type": "Feature",
      "properties": {
        "hierarchy": [
          "tgn:2097427",
          "tgn:1000001",
          "tgn:2001776",
          "tgn:7012149",
          "tgn:7007713",
          "tgn:7029392"
        ],
        "placetype": [
          "aat:300008347"
        ],
        "id": 2097427,
        "name:xx": "Ordway"
      }
    },
    {
      "geometry": {
        "type": "Point",
        "coordinates": [
          -99.0833,
          44.9
        ]
      },
      "type": "Feature",
      "properties": {
        "hierarchy": [
          "tgn:2097428",
          "tgn:1000001",
          "tgn:2001794",
          "tgn:7012149",
          "tgn:7007713",
          "tgn:7029392"
        ],
        "placetype": [
          "aat:300008347"
        ],
        "id": 2097428,
        "name:xx": "Orient"
      }
    },
    {
      "geometry": {
        "type": "Point",
        "coordinates": [
          -97.1833,
          43.8833
        ]
      },
      "type": "Feature",
      "properties": {
        "hierarchy": [
          "tgn:2097429",
          "tgn:1000001",
          "tgn:2001809",
          "tgn:7012149",
          "tgn:7007713",
          "tgn:7029392"
        ],
        "placetype": [
          "aat:300008347",
          "aat:300387210"
        ],
        "id": 2097429,
        "name:xx": "Orland"
      }
    }
  ]
}
