{
  "geometry": {
    "type": "Point",
    "coordinates": [
      -116.5667,
      40.1667
    ]
  },
  "type": "Feature",
  "properties": {
    "hierarchy": [
      "tgn:2357629",
      "tgn:1000001",
      "tgn:2001413",
      "tgn:7012149",
      "tgn:7007526",
      "tgn:7029392"
    ],
    "placetype": [
      "aat:300008697"
    ],
    "id": 2357629,
    "name:xx": "Goyeneche Spring Number Six"
  }
}
