{
  "geometry": {
    "type": "Point",
    "coordinates": [
      -83.8667,
      35.65
    ]
  },
  "type": "Feature",
  "properties": {
    "hierarchy": [
      "tgn:2218764",
      "tgn:1000001",
      "tgn:2001841",
      "tgn:7012149",
      "tgn:7007825",
      "tgn:7029392"
    ],
    "placetype": [
      "aat:300266640"
    ],
    "id": 2218764,
    "name:xx": "Cane Ridge"
  }
}
