{
  "geometry": {
    "type": "Point",
    "coordinates": [
      14.35,
      50.5833
    ]
  },
  "type": "Feature",
  "properties": {
    "hierarchy": [
      "tgn:1026994",
      "tgn:7593920",
      "tgn:1000003",
      "tgn:1001780",
      "tgn:7029392"
    ],
    "placetype": [
      "aat:300008347"
    ],
    "id": 1026994,
    "name:xx": "Úštěk"
  }
}
