{
  "geometry": {
    "type": "Point",
    "coordinates": [
      -110.0833,
      41.5667
    ]
  },
  "type": "Feature",
  "properties": {
    "hierarchy": [
      "tgn:2123216",
      "tgn:1000001",
      "tgn:7012149",
      "tgn:2002385",
      "tgn:7007923",
      "tgn:7029392"
    ],
    "placetype": [
      "aat:300387016"
    ],
    "id": 2123216,
    "name:xx": "Verne"
  }
}
