{
  "geometry": {
    "type": "Point",
    "coordinates": [
      -85.85,
      32.0833
    ]
  },
  "type": "Feature",
  "properties": {
    "hierarchy": [
      "tgn:2584754",
      "tgn:7002659",
      "tgn:1000001",
      "tgn:2000005",
      "tgn:7012149",
      "tgn:7029392"
    ],
    "placetype": [
      "aat:300008706"
    ],
    "id": 2584754,
    "name:xx": "Pinhook Creek"
  }
}
