{
  "geometry": {
    "type": "Point",
    "coordinates": [
      -88.8667,
      36.3667
    ]
  },
  "type": "Feature",
  "properties": {
    "hierarchy": [
      "tgn:2454395",
      "tgn:1000001",
      "tgn:7012149",
      "tgn:7007825",
      "tgn:7029392"
    ],
    "placetype": [
      "aat:300008706"
    ],
    "id": 2454395,
    "name:xx": "Little Cypress Creek"
  }
}
