{
  "type": "FeatureCollection",
  "features": [
    {
      "geometry": {
        "type": "Point",
        "coordinates": [
          -93.7167,
          30.9167
        ]
      },
      "type": "Feature",
      "properties": {
        "hierarchy": [
          "tgn:2105632",
          "tgn:1000001",
          "tgn:7012149",
          "tgn:2002047",
          "tgn:7007826",
          "tgn:7029392"
        ],
        "placetype": [
          "aat:300008347"
        ],
        "id": 2105632,
        "name:xx": "Liberty"
      }
    },
    {
      "geometry": {
        "type": "Point",
        "coordinates": [
          -101.7667,
          33.6833
        ]
      },
      "type": "Feature",
      "properties": {
        "hierarchy": [
          "tgn:2105633",
          "tgn:1000001",
          "tgn:7012149",
          "tgn:2002032",
          "tgn:7007826",
          "tgn:7029392"
        ],
        "placetype": [
          "aat:300008347",
          "aat:300387210"
        ],
        "id": 2105633,
        "name:xx": "Liberty"
      }
    },
    {
      "geometry": {
        "type": "Point",
        "coordinates": [
          -94.6,
          32.2167
        ]
      },
      "type": "Feature",
      "properties": {
        "hierarchy": [
          "tgn:2105634",
          "tgn:1000001",
          "tgn:7012149",
          "tgn:1002839",
          "tgn:7007826",
          "tgn:7029392"
        ],
        "placetype": [
          "aat:300008347",
          "aat:300387210"
        ],
        "id": 2105634,
        "name:xx": "Liberty"
      }
    },
    {
      "geometry": {
        "type": "Point",
        "coordinates": [
          -94.9333,
          32.4333
        ]
      },
      "type": "Feature",
      "properties": {
        "hierarchy": [
          "tgn:2105636",
          "tgn:1000001",
          "tgn:7012149",
          "tgn:1002427",
          "tgn:7007826",
          "tgn:7029392"
        ],
        "placetype": [
          "aat:300008347"
        ],
        "id": 2105636,
        "name:xx": "Liberty City"
      }
    },
    {
      "geometry": {
        "type": "Point",
        "coordinates": [
          -96.5167,
          32.95
        ]
      },
      "type": "Feature",
      "properties": {
        "hierarchy": [
          "tgn:2105637",
          "tgn:1000001",
          "tgn:7012149",
          "tgn:1002315",
          "tgn:7007826",
          "tgn:7029392"
        ],
        "placetype": [
          "aat:300008347"
        ],
        "id": 2105637,
        "name:xx": "Liberty Grove"
      }
    },
    {
      "geometry": {
        "type": "Point",
        "coordinates": [
          -95.2833,
          31.55
        ]
      },
      "type": "Feature",
      "properties": {
        "hierarchy": [
          "tgn:2105638",
          "tgn:1000001",
          "tgn:7012149",
          "tgn:1002486",
          "tgn:7007826",
          "tgn:7029392"
        ],
        "placetype": [
          "aat:300387210",
          "aat:300008798"
        ],
        "id": 2105638,
        "name:xx": "Liberty Hill"
      }
    },
    {
      "geometry": {
        "type": "Point",
        "coordinates": [
          -97.9167,
          30.65
        ]
      },
      "type": "Feature",
      "properties": {
        "hierarchy": [
          "tgn:2105639",
          "tgn:1000001",
          "tgn:7012149",
          "tgn:1003026",
          "tgn:7007826",
          "tgn:7029392"
        ],
        "placetype": [
          "aat:300008347"
        ],
        "id": 2105639,
        "name:xx": "Liberty Hill"
      }
    }
  ]
}
