{
  "type": "FeatureCollection",
  "features": [
    {
      "geometry": {
        "type": "Point",
        "coordinates": [
          4.000819,
          50.720047
        ]
      },
      "type": "Feature",
      "properties": {
        "hierarchy": [
          "tgn:7241130",
          "tgn:7003457",
          "tgn:1000003",
          "tgn:1000063",
          "tgn:7018236",
          "tgn:7029392"
        ],
        "placetype": [
          "aat:300008347"
        ],
        "id": 7241130,
        "name:xx": "Hellingen"
      }
    },
    {
      "geometry": {
        "type": "Point",
        "coordinates": [
          4.7,
          50.966667
        ]
      },
      "type": "Feature",
      "properties": {
        "hierarchy": [
          "tgn:7241131",
          "tgn:7003456",
          "tgn:1000003",
          "tgn:1000063",
          "tgn:7018236",
          "tgn:7029392"
        ],
        "placetype": [
          "aat:300008347"
        ],
        "id": 7241131,
        "name:xx": "Hellicht"
      }
    },
    {
      "geometry": {
        "type": "Point",
        "coordinates": [
          4.2,
          50.45
        ]
      },
      "type": "Feature",
      "properties": {
        "hierarchy": [
          "tgn:7241133",
          "tgn:7007877",
          "tgn:1000003",
          "tgn:1000063",
          "tgn:4012014",
          "tgn:7029392"
        ],
        "placetype": [
          "aat:300008347"
        ],
        "id": 7241133,
        "name:xx": "Haine-Saint-Pierre"
      }
    },
    {
      "geometry": {
        "type": "Point",
        "coordinates": [
          4.166667,
          50.45
        ]
      },
      "type": "Feature",
      "properties": {
        "hierarchy": [
          "tgn:7241135",
          "tgn:7007877",
          "tgn:1000003",
          "tgn:1000063",
          "tgn:4012014",
          "tgn:7029392"
        ],
        "placetype": [
          "aat:300008347"
        ],
        "id": 7241135,
        "name:xx": "Haine-Saint-Paul"
      }
    },
    {
      "geometry": {
        "type": "Point",
        "coordinates": [
          3.663291,
          50.449732
        ]
      },
      "type": "Feature",
      "properties": {
        "hierarchy": [
          "tgn:7241137",
          "tgn:7007877",
          "tgn:1000003",
          "tgn:1000063",
          "tgn:4012014",
          "tgn:7029392"
        ],
        "placetype": [
          "aat:300008699"
        ],
        "id": 7241137,
        "name:xx": "Haine"
      }
    },
    {
      "geometry": {
        "type": "Point",
        "coordinates": [
          3.783333,
          50.45
        ]
      },
      "type": "Feature",
      "properties": {
        "hierarchy": [
          "tgn:7241138",
          "tgn:7007877",
          "tgn:1000003",
          "tgn:1000063",
          "tgn:4012014",
          "tgn:7029392"
        ],
        "placetype": [
          "aat:300008347"
        ],
        "id": 7241138,
        "name:xx": "Haine"
      }
    }
  ]
}
