{
  "type": "FeatureCollection",
  "features": [
    {
      "geometry": {
        "type": "Point",
        "coordinates": [
          -90.6333,
          34.3167
        ]
      },
      "type": "Feature",
      "properties": {
        "hierarchy": [
          "tgn:2529450",
          "tgn:1000001",
          "tgn:2001099",
          "tgn:7012149",
          "tgn:7007522",
          "tgn:7029392"
        ],
        "placetype": [
          "aat:300008680",
          "aat:300387018"
        ],
        "id": 2529450,
        "name:xx": "Mud Lake"
      }
    },
    {
      "geometry": {
        "type": "Point",
        "coordinates": [
          -90.7,
          38.8833
        ]
      },
      "type": "Feature",
      "properties": {
        "hierarchy": [
          "tgn:2529451",
          "tgn:1000001",
          "tgn:7012149",
          "tgn:7016166",
          "tgn:7007523",
          "tgn:7029392"
        ],
        "placetype": [
          "aat:300008680"
        ],
        "id": 2529451,
        "name:xx": "Mud Lake"
      }
    },
    {
      "geometry": {
        "type": "Point",
        "coordinates": [
          -95.0667,
          39.55
        ]
      },
      "type": "Feature",
      "properties": {
        "hierarchy": [
          "tgn:2529452",
          "tgn:1000001",
          "tgn:2001175",
          "tgn:7012149",
          "tgn:7007523",
          "tgn:7029392"
        ],
        "placetype": [
          "aat:300008680"
        ],
        "id": 2529452,
        "name:xx": "Mud Lake"
      }
    },
    {
      "geometry": {
        "type": "Point",
        "coordinates": [
          -94.8667,
          39.3333
        ]
      },
      "type": "Feature",
      "properties": {
        "hierarchy": [
          "tgn:2529453",
          "tgn:1000001",
          "tgn:7012149",
          "tgn:2001231",
          "tgn:7007523",
          "tgn:7029392"
        ],
        "placetype": [
          "aat:300008680"
        ],
        "id": 2529453,
        "name:xx": "Mud Lake"
      }
    },
    {
      "geometry": {
        "type": "Point",
        "coordinates": [
          -107.5667,
          48.4667
        ]
      },
      "type": "Feature",
      "properties": {
        "hierarchy": [
          "tgn:2529454",
          "tgn:1000001",
          "tgn:7012149",
          "tgn:2001295",
          "tgn:7007524",
          "tgn:7029392"
        ],
        "placetype": [
          "aat:300008680"
        ],
        "id": 2529454,
        "name:xx": "Mud Lake"
      }
    },
    {
      "geometry": {
        "type": "Point",
        "coordinates": [
          -112.1667,
          44.6
        ]
      },
      "type": "Feature",
      "properties": {
        "hierarchy": [
          "tgn:2529455",
          "tgn:1000001",
          "tgn:2001260",
          "tgn:7012149",
          "tgn:7007524",
          "tgn:7029392"
        ],
        "placetype": [
          "aat:300008680"
        ],
        "id": 2529455,
        "name:xx": "Mud Lake"
      }
    },
    {
      "geometry": {
        "type": "Point",
        "coordinates": [
          -109.9,
          45.05
        ]
      },
      "type": "Feature",
      "properties": {
        "hierarchy": [
          "tgn:2529456",
          "tgn:1000001",
          "tgn:7012149",
          "tgn:2001293",
          "tgn:7007524",
          "tgn:7029392"
        ],
        "placetype": [
          "aat:300008680"
        ],
        "id": 2529456,
        "name:xx": "Mud Lake"
      }
    },
    {
      "geometry": {
        "type": "Point",
        "coordinates": [
          -112.8833,
          45.9167
        ]
      },
      "type": "Feature",
      "properties": {
        "hierarchy": [
          "tgn:2529457",
          "tgn:1000001",
          "tgn:7012149",
          "tgn:2001306",
          "tgn:7007524",
          "tgn:7029392"
        ],
        "placetype": [
          "aat:300008680"
        ],
        "id": 2529457,
        "name:xx": "Mud Lake"
      }
    },
    {
      "geometry": {
        "type": "Point",
        "coordinates": [
          -114.4667,
          46.15
        ]
      },
      "type": "Feature",
      "properties": {
        "hierarchy": [
          "tgn:2529458",
          "tgn:1000001",
          "tgn:7012149",
          "tgn:2001300",
          "tgn:7007524",
          "tgn:7029392"
        ],
        "placetype": [
          "aat:300008680"
        ],
        "id": 2529458,
        "name:xx": "Mud Lake"
      }
    },
    {
      "geometry": {
        "type": "Point",
        "coordinates": [
          -113.1,
          46.3167
        ]
      },
      "type": "Feature",
      "properties": {
        "hierarchy": [
          "tgn:2529459",
          "tgn:1000001",
          "tgn:7012149",
          "tgn:2001279",
          "tgn:7007524",
          "tgn:7029392"
        ],
        "placetype": [
          "aat:300008680"
        ],
        "id": 2529459,
        "name:xx": "Mud Lake"
      }
    }
  ]
}
