{
  "type": "FeatureCollection",
  "features": [
    {
      "geometry": {
        "type": "Point",
        "coordinates": [
          -70.4,
          43.9333
        ]
      },
      "type": "Feature",
      "properties": {
        "hierarchy": [
          "tgn:2352180",
          "tgn:1000001",
          "tgn:2000920",
          "tgn:7012149",
          "tgn:7007515",
          "tgn:7029392"
        ],
        "placetype": [
          "aat:300008798"
        ],
        "id": 2352180,
        "name:xx": "Glovers Wig"
      }
    },
    {
      "geometry": {
        "type": "Point",
        "coordinates": [
          -76.5667,
          36.85
        ]
      },
      "type": "Feature",
      "properties": {
        "hierarchy": [
          "tgn:2352181",
          "tgn:1000001",
          "tgn:7012149",
          "tgn:7022217",
          "tgn:7007919",
          "tgn:7029392"
        ],
        "placetype": [
          "aat:300008347"
        ],
        "id": 2352181,
        "name:xx": "Gloversville"
      }
    },
    {
      "geometry": {
        "type": "Point",
        "coordinates": [
          -84.8167,
          33.3833
        ]
      },
      "type": "Feature",
      "properties": {
        "hierarchy": [
          "tgn:2352182",
          "tgn:1000001",
          "tgn:7012149",
          "tgn:2000329",
          "tgn:7007248",
          "tgn:7029392"
        ],
        "placetype": [
          "aat:300008347"
        ],
        "id": 2352182,
        "name:xx": "Gloverton"
      }
    },
    {
      "geometry": {
        "type": "Point",
        "coordinates": [
          -80.4833,
          32.9
        ]
      },
      "type": "Feature",
      "properties": {
        "hierarchy": [
          "tgn:2352183",
          "tgn:1000001",
          "tgn:2001739",
          "tgn:7012149",
          "tgn:7007712",
          "tgn:7029392"
        ],
        "placetype": [
          "aat:300008347"
        ],
        "id": 2352183,
        "name:xx": "Gloverville"
      }
    },
    {
      "geometry": {
        "type": "Point",
        "coordinates": [
          -74.0667,
          43
        ]
      },
      "type": "Feature",
      "properties": {
        "hierarchy": [
          "tgn:2352184",
          "tgn:1000001",
          "tgn:7012149",
          "tgn:1002871",
          "tgn:7007568",
          "tgn:7029392"
        ],
        "placetype": [
          "aat:300008706"
        ],
        "id": 2352184,
        "name:xx": "Glowegee Creek"
      }
    },
    {
      "geometry": {
        "type": "Point",
        "coordinates": [
          -112.8,
          45.4167
        ]
      },
      "type": "Feature",
      "properties": {
        "hierarchy": [
          "tgn:2352185",
          "tgn:1000001",
          "tgn:2001260",
          "tgn:7012149",
          "tgn:7007524",
          "tgn:7029392"
        ],
        "placetype": [
          "aat:300000390"
        ],
        "id": 2352185,
        "name:xx": "Glowworm/Greenhorn Mine"
      }
    },
    {
      "geometry": {
        "type": "Point",
        "coordinates": [
          -101.8,
          35.35
        ]
      },
      "type": "Feature",
      "properties": {
        "hierarchy": [
          "tgn:2352186",
          "tgn:1000001",
          "tgn:7012149",
          "tgn:2002056",
          "tgn:7007826",
          "tgn:7029392"
        ],
        "placetype": [
          "aat:300008347"
        ],
        "id": 2352186,
        "name:xx": "Gluck"
      }
    },
    {
      "geometry": {
        "type": "Point",
        "coordinates": [
          -80.7833,
          38.9333
        ]
      },
      "type": "Feature",
      "properties": {
        "hierarchy": [
          "tgn:2352188",
          "tgn:1000001",
          "tgn:2002262",
          "tgn:7012149",
          "tgn:7013961",
          "tgn:7029392"
        ],
        "placetype": [
          "aat:300008699"
        ],
        "id": 2352188,
        "name:xx": "Gluck Run"
      }
    },
    {
      "geometry": {
        "type": "Point",
        "coordinates": [
          -71.2,
          42.0333
        ]
      },
      "type": "Feature",
      "properties": {
        "hierarchy": [
          "tgn:2352189",
          "tgn:1000001",
          "tgn:1002724",
          "tgn:7012149",
          "tgn:7007517",
          "tgn:7029392"
        ],
        "placetype": [
          "aat:300008680"
        ],
        "id": 2352189,
        "name:xx": "Glue Factory Pond"
      }
    }
  ]
}
