{
  "geometry": {
    "type": "Point",
    "coordinates": [
      -88.5833,
      44.3667
    ]
  },
  "type": "Feature",
  "properties": {
    "hierarchy": [
      "tgn:2122458",
      "tgn:1000001",
      "tgn:7012149",
      "tgn:2002343",
      "tgn:7007922",
      "tgn:7029392"
    ],
    "placetype": [
      "aat:300008347"
    ],
    "id": 2122458,
    "name:xx": "Stephensville"
  }
}
