{
  "type": "FeatureCollection",
  "features": [
    {
      "geometry": {
        "type": "Point",
        "coordinates": [
          -83.9833,
          42.4333
        ]
      },
      "type": "Feature",
      "properties": {
        "hierarchy": [
          "tgn:1128770",
          "tgn:1000001",
          "tgn:7012149",
          "tgn:7007520",
          "tgn:7029392"
        ],
        "placetype": [
          "aat:300008707"
        ],
        "id": 1128770,
        "name:xx": "Portage"
      }
    },
    {
      "geometry": {
        "type": "Point",
        "coordinates": [
          -83.5,
          41.35
        ]
      },
      "type": "Feature",
      "properties": {
        "hierarchy": [
          "tgn:1128771",
          "tgn:1000001",
          "tgn:7012149",
          "tgn:7007706",
          "tgn:7029392"
        ],
        "placetype": [
          "aat:300008707"
        ],
        "id": 1128771,
        "name:xx": "Portage"
      }
    },
    {
      "geometry": {
        "type": "Point",
        "coordinates": [
          -43.45,
          -23
        ]
      },
      "type": "Feature",
      "properties": {
        "hierarchy": [
          "tgn:1128776",
          "tgn:1001942",
          "tgn:1000047",
          "tgn:7002457",
          "tgn:1000002",
          "tgn:7017095",
          "tgn:7029392"
        ],
        "placetype": [
          "aat:300008707"
        ],
        "id": 1128776,
        "name:xx": "Portela"
      }
    },
    {
      "geometry": {
        "type": "Point",
        "coordinates": [
          -43.5833,
          -23.05
        ]
      },
      "type": "Feature",
      "properties": {
        "hierarchy": [
          "tgn:1128777",
          "tgn:1001942",
          "tgn:1000047",
          "tgn:7002457",
          "tgn:1000002",
          "tgn:7017095",
          "tgn:7029392"
        ],
        "placetype": [
          "aat:300008707"
        ],
        "id": 1128777,
        "name:xx": "Portinho, Rio do"
      }
    },
    {
      "geometry": {
        "type": "Point",
        "coordinates": [
          -112,
          43.1
        ]
      },
      "type": "Feature",
      "properties": {
        "hierarchy": [
          "tgn:1128778",
          "tgn:1000001",
          "tgn:7012149",
          "tgn:7007250",
          "tgn:7029392"
        ],
        "placetype": [
          "aat:300008707"
        ],
        "id": 1128778,
        "name:xx": "Portneuf"
      }
    }
  ]
}
