{
  "geometry": {
    "type": "Point",
    "coordinates": [
      27.067,
      58.06
    ]
  },
  "type": "Feature",
  "properties": {
    "hierarchy": [
      "tgn:1058134",
      "tgn:7006639",
      "tgn:1000003",
      "tgn:7006540",
      "tgn:7029392"
    ],
    "placetype": [
      "aat:300008347",
      "aat:300387222"
    ],
    "name:en": "Põlva",
    "id": 1058134
  }
}
