{
  "type": "FeatureCollection",
  "features": [
    {
      "geometry": {
        "type": "Point",
        "coordinates": [
          -97.7667,
          30.0833
        ]
      },
      "type": "Feature",
      "properties": {
        "hierarchy": [
          "tgn:2108130",
          "tgn:1000001",
          "tgn:7012149",
          "tgn:1002952",
          "tgn:7007826",
          "tgn:7029392"
        ],
        "placetype": [
          "aat:300008347",
          "aat:300387210"
        ],
        "id": 2108130,
        "name:xx": "Turnersville"
      }
    },
    {
      "geometry": {
        "type": "Point",
        "coordinates": [
          -97.7333,
          31.6167
        ]
      },
      "type": "Feature",
      "properties": {
        "hierarchy": [
          "tgn:2108131",
          "tgn:1000001",
          "tgn:7012149",
          "tgn:1002303",
          "tgn:7007826",
          "tgn:7029392"
        ],
        "placetype": [
          "aat:300008347"
        ],
        "id": 2108131,
        "name:xx": "Turnersville"
      }
    },
    {
      "geometry": {
        "type": "Point",
        "coordinates": [
          -95.1833,
          31.9
        ]
      },
      "type": "Feature",
      "properties": {
        "hierarchy": [
          "tgn:2108132",
          "tgn:1000001",
          "tgn:7012149",
          "tgn:1002263",
          "tgn:7007826",
          "tgn:7029392"
        ],
        "placetype": [
          "aat:300008347"
        ],
        "id": 2108132,
        "name:xx": "Turney"
      }
    },
    {
      "geometry": {
        "type": "Point",
        "coordinates": [
          -99.7833,
          32.2
        ]
      },
      "type": "Feature",
      "properties": {
        "hierarchy": [
          "tgn:2108134",
          "tgn:1000001",
          "tgn:7012149",
          "tgn:2002081",
          "tgn:7007826",
          "tgn:7029392"
        ],
        "placetype": [
          "aat:300008347"
        ],
        "id": 2108134,
        "name:xx": "Tuscola"
      }
    },
    {
      "geometry": {
        "type": "Point",
        "coordinates": [
          -99.95,
          32.9167
        ]
      },
      "type": "Feature",
      "properties": {
        "hierarchy": [
          "tgn:2108136",
          "tgn:1000001",
          "tgn:7012149",
          "tgn:2002014",
          "tgn:7007826",
          "tgn:7029392"
        ],
        "placetype": [
          "aat:300008347",
          "aat:300387210"
        ],
        "id": 2108136,
        "name:xx": "Tuxedo"
      }
    },
    {
      "geometry": {
        "type": "Point",
        "coordinates": [
          -100.7167,
          36.4333
        ]
      },
      "type": "Feature",
      "properties": {
        "hierarchy": [
          "tgn:2108137",
          "tgn:1000001",
          "tgn:7012149",
          "tgn:2002050",
          "tgn:7007826",
          "tgn:7029392"
        ],
        "placetype": [
          "aat:300387016"
        ],
        "id": 2108137,
        "name:xx": "Twichell"
      }
    }
  ]
}
