{
  "geometry": {
    "type": "Point",
    "coordinates": [
      77.0333,
      28.7167
    ]
  },
  "type": "Feature",
  "properties": {
    "hierarchy": [
      "tgn:1005011",
      "tgn:1000004",
      "tgn:7000201",
      "tgn:7000198",
      "tgn:7029392"
    ],
    "placetype": [
      "aat:300000745"
    ],
    "id": 1005011,
    "name:xx": "Madanpur Dabās"
  }
}
