{
  "geometry": {
    "type": "Point",
    "coordinates": [
      -82.2833,
      35.1833
    ]
  },
  "type": "Feature",
  "properties": {
    "hierarchy": [
      "tgn:2743641",
      "tgn:1000001",
      "tgn:7012149",
      "tgn:7029392"
    ],
    "placetype": [
      "aat:300008706"
    ],
    "id": 2743641,
    "name:xx": "Vaughn Creek"
  }
}
