{
  "geometry": {
    "type": "Point",
    "coordinates": [
      55.4833,
      -4.7167
    ]
  },
  "type": "Feature",
  "properties": {
    "hierarchy": [
      "tgn:7000588",
      "tgn:7001703",
      "tgn:7001242",
      "tgn:1007978",
      "tgn:1000190",
      "tgn:7029392"
    ],
    "placetype": [
      "aat:300008347"
    ],
    "id": 7000588,
    "name:xx": "Anse Boileau"
  }
}
