{
  "geometry": {
    "type": "Point",
    "coordinates": [
      -91.7833,
      30.8667
    ]
  },
  "type": "Feature",
  "properties": {
    "hierarchy": [
      "tgn:2500057",
      "tgn:1000001",
      "tgn:7012149",
      "tgn:2000892",
      "tgn:7007256",
      "tgn:7029392"
    ],
    "placetype": [
      "aat:300008680"
    ],
    "id": 2500057,
    "name:xx": "McCrea Lake"
  }
}
