{
  "geometry": {
    "type": "Point",
    "coordinates": [
      144.75,
      13.4667
    ]
  },
  "type": "Feature",
  "properties": {
    "hierarchy": [
      "tgn:1098767",
      "tgn:7000549",
      "tgn:7000550",
      "tgn:1000006",
      "tgn:7029392"
    ],
    "placetype": [
      "aat:300008347",
      "aat:300387218",
      "aat:300008375"
    ],
    "id": 1098767,
    "name:xx": "Hagåtña"
  }
}
