{
  "geometry": {
    "type": "Point",
    "coordinates": [
      149.9333,
      -10.5167
    ]
  },
  "type": "Feature",
  "properties": {
    "hierarchy": [
      "tgn:1099448",
      "tgn:7006160",
      "tgn:1000897",
      "tgn:1000006",
      "tgn:7029392"
    ],
    "placetype": [
      "aat:300008347"
    ],
    "id": 1099448,
    "name:xx": "Dahuni"
  }
}
