{
  "geometry": {
    "type": "Point",
    "coordinates": [
      -113.1667,
      45.4833
    ]
  },
  "type": "Feature",
  "properties": {
    "hierarchy": [
      "tgn:2155988",
      "tgn:1000001",
      "tgn:2001260",
      "tgn:7012149",
      "tgn:7007524",
      "tgn:7029392"
    ],
    "placetype": [
      "aat:300008706"
    ],
    "id": 2155988,
    "name:xx": "Bear Wallow Creek"
  }
}
