{
  "geometry": {
    "type": "Point",
    "coordinates": [
      -80.95,
      37.3333
    ]
  },
  "type": "Feature",
  "properties": {
    "hierarchy": [
      "tgn:2119440",
      "tgn:1000001",
      "tgn:7012149",
      "tgn:2002278",
      "tgn:7013961",
      "tgn:7029392"
    ],
    "placetype": [
      "aat:300008347"
    ],
    "id": 2119440,
    "name:xx": "Oakvale"
  }
}
