{
  "type": "FeatureCollection",
  "features": [
    {
      "geometry": {
        "type": "Point",
        "coordinates": [
          -82.0833,
          36.0833
        ]
      },
      "type": "Feature",
      "properties": {
        "hierarchy": [
          "tgn:2597030",
          "tgn:1000001",
          "tgn:7012149",
          "tgn:2001519",
          "tgn:7007709",
          "tgn:7029392"
        ],
        "placetype": [
          "aat:300008699"
        ],
        "id": 2597030,
        "name:xx": "Powers Branch"
      }
    },
    {
      "geometry": {
        "type": "Point",
        "coordinates": [
          -88.2,
          35.5833
        ]
      },
      "type": "Feature",
      "properties": {
        "hierarchy": [
          "tgn:2597031",
          "tgn:1000001",
          "tgn:7012149",
          "tgn:7007825",
          "tgn:7029392"
        ],
        "placetype": [
          "aat:300008699"
        ],
        "id": 2597031,
        "name:xx": "Powers Branch"
      }
    },
    {
      "geometry": {
        "type": "Point",
        "coordinates": [
          -88.25,
          35.5667
        ]
      },
      "type": "Feature",
      "properties": {
        "hierarchy": [
          "tgn:2597032",
          "tgn:1000001",
          "tgn:7012149",
          "tgn:2001875",
          "tgn:7007825",
          "tgn:7029392"
        ],
        "placetype": [
          "aat:300008699"
        ],
        "id": 2597032,
        "name:xx": "Powers Branch"
      }
    },
    {
      "geometry": {
        "type": "Point",
        "coordinates": [
          -96.9167,
          32.5167
        ]
      },
      "type": "Feature",
      "properties": {
        "hierarchy": [
          "tgn:2597033",
          "tgn:1000001",
          "tgn:7012149",
          "tgn:1002355",
          "tgn:7007826",
          "tgn:7029392"
        ],
        "placetype": [
          "aat:300008699"
        ],
        "id": 2597033,
        "name:xx": "Powers Branch"
      }
    },
    {
      "geometry": {
        "type": "Point",
        "coordinates": [
          -82.7833,
          36.6
        ]
      },
      "type": "Feature",
      "properties": {
        "hierarchy": [
          "tgn:2597034",
          "tgn:1000001",
          "tgn:7012149",
          "tgn:2002189",
          "tgn:7007919",
          "tgn:7029392"
        ],
        "placetype": [
          "aat:300008699"
        ],
        "id": 2597034,
        "name:xx": "Powers Branch"
      }
    },
    {
      "geometry": {
        "type": "Point",
        "coordinates": [
          -82.5,
          37.1
        ]
      },
      "type": "Feature",
      "properties": {
        "hierarchy": [
          "tgn:2597035",
          "tgn:1000001",
          "tgn:7012149",
          "tgn:2002157",
          "tgn:7007919",
          "tgn:7029392"
        ],
        "placetype": [
          "aat:300008699"
        ],
        "id": 2597035,
        "name:xx": "Powers Branch"
      }
    },
    {
      "geometry": {
        "type": "Point",
        "coordinates": [
          -70.7667,
          44.1333
        ]
      },
      "type": "Feature",
      "properties": {
        "hierarchy": [
          "tgn:2597036",
          "tgn:1000001",
          "tgn:7012149",
          "tgn:2000926",
          "tgn:7007515",
          "tgn:7029392"
        ],
        "placetype": [
          "aat:300008699"
        ],
        "id": 2597036,
        "name:xx": "Powers Brook"
      }
    },
    {
      "geometry": {
        "type": "Point",
        "coordinates": [
          -74.0167,
          43.85
        ]
      },
      "type": "Feature",
      "properties": {
        "hierarchy": [
          "tgn:2597037",
          "tgn:1000001",
          "tgn:7012149",
          "tgn:2001461",
          "tgn:7007568",
          "tgn:7029392"
        ],
        "placetype": [
          "aat:300008699"
        ],
        "id": 2597037,
        "name:xx": "Powers Brook"
      }
    },
    {
      "geometry": {
        "type": "Point",
        "coordinates": [
          -81.3833,
          41.2167
        ]
      },
      "type": "Feature",
      "properties": {
        "hierarchy": [
          "tgn:2597038",
          "tgn:1000001",
          "tgn:7012149",
          "tgn:1002928",
          "tgn:7007706",
          "tgn:7029392"
        ],
        "placetype": [
          "aat:300008699"
        ],
        "id": 2597038,
        "name:xx": "Powers Brook"
      }
    },
    {
      "geometry": {
        "type": "Point",
        "coordinates": [
          -106.8833,
          45.0167
        ]
      },
      "type": "Feature",
      "properties": {
        "hierarchy": [
          "tgn:2597039",
          "tgn:1000001",
          "tgn:2001261",
          "tgn:7012149",
          "tgn:7007524",
          "tgn:7029392"
        ],
        "placetype": [
          "aat:300006075"
        ],
        "id": 2597039,
        "name:xx": "Powers Brothers Ditch"
      }
    }
  ]
}
