{
  "geometry": {
    "type": "Point",
    "coordinates": [
      -81.4167,
      26.4167
    ]
  },
  "type": "Feature",
  "properties": {
    "hierarchy": [
      "tgn:2019690",
      "tgn:1000001",
      "tgn:1002289",
      "tgn:7012149",
      "tgn:7007240",
      "tgn:7029392"
    ],
    "placetype": [
      "aat:300008347"
    ],
    "id": 2019690,
    "name:xx": "Immokalee"
  }
}
