{
  "geometry": {
    "type": "Point",
    "coordinates": [
      -86.3333,
      34.9667
    ]
  },
  "type": "Feature",
  "properties": {
    "hierarchy": [
      "tgn:2183422",
      "tgn:7002659",
      "tgn:1000001",
      "tgn:7012149",
      "tgn:2000044",
      "tgn:7029392"
    ],
    "placetype": [
      "aat:300008761"
    ],
    "id": 2183422,
    "name:xx": "Bluff Hollow"
  }
}
