{
  "type": "FeatureCollection",
  "features": [
    {
      "geometry": {
        "type": "Point",
        "coordinates": [
          -95.9833,
          33.15
        ]
      },
      "type": "Feature",
      "properties": {
        "hierarchy": [
          "tgn:2753890",
          "tgn:1000001",
          "tgn:7012149",
          "tgn:1002492",
          "tgn:7007826",
          "tgn:7029392"
        ],
        "placetype": [
          "aat:300008699"
        ],
        "id": 2753890,
        "name:xx": "Watson Branch"
      }
    },
    {
      "geometry": {
        "type": "Point",
        "coordinates": [
          -95.1333,
          32.9667
        ]
      },
      "type": "Feature",
      "properties": {
        "hierarchy": [
          "tgn:2753891",
          "tgn:1000001",
          "tgn:7012149",
          "tgn:7007826",
          "tgn:7029392"
        ],
        "placetype": [
          "aat:300008699"
        ],
        "id": 2753891,
        "name:xx": "Watson Branch"
      }
    },
    {
      "geometry": {
        "type": "Point",
        "coordinates": [
          -94.9333,
          31.45
        ]
      },
      "type": "Feature",
      "properties": {
        "hierarchy": [
          "tgn:2753892",
          "tgn:1002149",
          "tgn:1000001",
          "tgn:7012149",
          "tgn:7007826",
          "tgn:7029392"
        ],
        "placetype": [
          "aat:300008699"
        ],
        "id": 2753892,
        "name:xx": "Watson Branch"
      }
    },
    {
      "geometry": {
        "type": "Point",
        "coordinates": [
          -94.4667,
          32.3333
        ]
      },
      "type": "Feature",
      "properties": {
        "hierarchy": [
          "tgn:2753893",
          "tgn:1000001",
          "tgn:7012149",
          "tgn:1002769",
          "tgn:7007826",
          "tgn:7029392"
        ],
        "placetype": [
          "aat:300008699"
        ],
        "id": 2753893,
        "name:xx": "Watson Branch"
      }
    },
    {
      "geometry": {
        "type": "Point",
        "coordinates": [
          -97.6167,
          33.3333
        ]
      },
      "type": "Feature",
      "properties": {
        "hierarchy": [
          "tgn:2753894",
          "tgn:1000001",
          "tgn:7012149",
          "tgn:1003031",
          "tgn:7007826",
          "tgn:7029392"
        ],
        "placetype": [
          "aat:300008699"
        ],
        "id": 2753894,
        "name:xx": "Watson Branch"
      }
    },
    {
      "geometry": {
        "type": "Point",
        "coordinates": [
          -81.45,
          38.2167
        ]
      },
      "type": "Feature",
      "properties": {
        "hierarchy": [
          "tgn:2753895",
          "tgn:1000001",
          "tgn:7012149",
          "tgn:2002270",
          "tgn:7013961",
          "tgn:7029392"
        ],
        "placetype": [
          "aat:300008699"
        ],
        "id": 2753895,
        "name:xx": "Watson Branch"
      }
    },
    {
      "geometry": {
        "type": "Point",
        "coordinates": [
          -87.65,
          37.3
        ]
      },
      "type": "Feature",
      "properties": {
        "hierarchy": [
          "tgn:2753896",
          "tgn:1000001",
          "tgn:7012149",
          "tgn:2000801",
          "tgn:7007255",
          "tgn:7029392"
        ],
        "placetype": [
          "aat:300000390"
        ],
        "id": 2753896,
        "name:xx": "Watson Bridge Mine"
      }
    },
    {
      "geometry": {
        "type": "Point",
        "coordinates": [
          -67.9333,
          45.75
        ]
      },
      "type": "Feature",
      "properties": {
        "hierarchy": [
          "tgn:2753897",
          "tgn:2000919",
          "tgn:1000001",
          "tgn:7012149",
          "tgn:7007515",
          "tgn:7029392"
        ],
        "placetype": [
          "aat:300008699"
        ],
        "id": 2753897,
        "name:xx": "Watson Brook"
      }
    },
    {
      "geometry": {
        "type": "Point",
        "coordinates": [
          -68.55,
          44.2667
        ]
      },
      "type": "Feature",
      "properties": {
        "hierarchy": [
          "tgn:2753898",
          "tgn:1000001",
          "tgn:2000922",
          "tgn:7012149",
          "tgn:7007515",
          "tgn:7029392"
        ],
        "placetype": [
          "aat:300008699"
        ],
        "id": 2753898,
        "name:xx": "Watson Brook"
      }
    },
    {
      "geometry": {
        "type": "Point",
        "coordinates": [
          -73.0167,
          42.1833
        ]
      },
      "type": "Feature",
      "properties": {
        "hierarchy": [
          "tgn:2753899",
          "tgn:1000001",
          "tgn:7019982",
          "tgn:7012149",
          "tgn:7007517",
          "tgn:7029392"
        ],
        "placetype": [
          "aat:300008699"
        ],
        "id": 2753899,
        "name:xx": "Watson Brook"
      }
    }
  ]
}
