{
  "geometry": {
    "type": "Point",
    "coordinates": [
      -80.6667,
      39.45
    ]
  },
  "type": "Feature",
  "properties": {
    "hierarchy": [
      "tgn:2584438",
      "tgn:1000001",
      "tgn:7012149",
      "tgn:2002301",
      "tgn:7013961",
      "tgn:7029392"
    ],
    "placetype": [
      "aat:300008699"
    ],
    "id": 2584438,
    "name:xx": "Piney Fork"
  }
}
