{
  "geometry": {
    "type": "Point",
    "coordinates": [
      -104.6667,
      35.8833
    ]
  },
  "type": "Feature",
  "properties": {
    "hierarchy": [
      "tgn:2342547",
      "tgn:1000001",
      "tgn:7012149",
      "tgn:2001446",
      "tgn:7007566",
      "tgn:7029392"
    ],
    "placetype": [
      "aat:300000390"
    ],
    "id": 2342547,
    "name:xx": "Fulton 1 Santa Fe"
  }
}
