{
  "geometry": {
    "type": "Point",
    "coordinates": [
      -95.9667,
      43.3667
    ]
  },
  "type": "Feature",
  "properties": {
    "hierarchy": [
      "tgn:2619827",
      "tgn:1000001",
      "tgn:7012149",
      "tgn:2000620",
      "tgn:7007253",
      "tgn:7029392"
    ],
    "placetype": [
      "aat:300008706"
    ],
    "id": 2619827,
    "name:xx": "Rio Grande Creek"
  }
}
