{
  "type": "FeatureCollection",
  "features": [
    {
      "geometry": {
        "type": "Point",
        "coordinates": [
          2.6,
          50.35
        ]
      },
      "type": "Feature",
      "properties": {
        "hierarchy": [
          "tgn:1031890",
          "tgn:1000003",
          "tgn:7001097",
          "tgn:1000070",
          "tgn:7029392"
        ],
        "placetype": [
          "aat:300008347"
        ],
        "id": 1031890,
        "name:xx": "Aubigny-en-Artois"
      }
    },
    {
      "geometry": {
        "type": "Point",
        "coordinates": [
          2.4333,
          47.4833
        ]
      },
      "type": "Feature",
      "properties": {
        "hierarchy": [
          "tgn:1031891",
          "tgn:1000003",
          "tgn:7002877",
          "tgn:1000070",
          "tgn:7029392"
        ],
        "placetype": [
          "aat:300008347"
        ],
        "id": 1031891,
        "name:xx": "Aubigny-sur-Nère"
      }
    },
    {
      "geometry": {
        "type": "Point",
        "coordinates": [
          2.2333,
          44.5333
        ]
      },
      "type": "Feature",
      "properties": {
        "hierarchy": [
          "tgn:1031892",
          "tgn:1000003",
          "tgn:7002889",
          "tgn:1000070",
          "tgn:7029392"
        ],
        "placetype": [
          "aat:300008347"
        ],
        "id": 1031892,
        "name:xx": "Aubin"
      }
    },
    {
      "geometry": {
        "type": "Point",
        "coordinates": [
          5.9667,
          49.2167
        ]
      },
      "type": "Feature",
      "properties": {
        "hierarchy": [
          "tgn:1031893",
          "tgn:1000003",
          "tgn:7002888",
          "tgn:1000070",
          "tgn:7029392"
        ],
        "placetype": [
          "aat:300008347"
        ],
        "id": 1031893,
        "name:xx": "Auboué"
      }
    },
    {
      "geometry": {
        "type": "Point",
        "coordinates": [
          4.7667,
          50.1
        ]
      },
      "type": "Feature",
      "properties": {
        "hierarchy": [
          "tgn:1031894",
          "tgn:1000003",
          "tgn:7002880",
          "tgn:1000070",
          "tgn:7029392"
        ],
        "placetype": [
          "aat:300008347"
        ],
        "id": 1031894,
        "name:xx": "Aubrives"
      }
    },
    {
      "geometry": {
        "type": "Point",
        "coordinates": [
          2.4833,
          50.5
        ]
      },
      "type": "Feature",
      "properties": {
        "hierarchy": [
          "tgn:1031897",
          "tgn:1000003",
          "tgn:7001097",
          "tgn:1000070",
          "tgn:7029392"
        ],
        "placetype": [
          "aat:300008347"
        ],
        "id": 1031897,
        "name:xx": "Auchel"
      }
    },
    {
      "geometry": {
        "type": "Point",
        "coordinates": [
          -1.0167,
          44.7
        ]
      },
      "type": "Feature",
      "properties": {
        "hierarchy": [
          "tgn:1031898",
          "tgn:7002878",
          "tgn:1000003",
          "tgn:1000070",
          "tgn:7029392"
        ],
        "placetype": [
          "aat:300008347"
        ],
        "id": 1031898,
        "name:xx": "Audenge"
      }
    },
    {
      "geometry": {
        "type": "Point",
        "coordinates": [
          5.8833,
          47.25
        ]
      },
      "type": "Feature",
      "properties": {
        "hierarchy": [
          "tgn:1031899",
          "tgn:1000003",
          "tgn:7002881",
          "tgn:1000070",
          "tgn:7029392"
        ],
        "placetype": [
          "aat:300008347"
        ],
        "id": 1031899,
        "name:xx": "Audeux"
      }
    }
  ]
}
