{
  "geometry": {
    "type": "Point",
    "coordinates": [
      -14.016667,
      28.65
    ]
  },
  "type": "Feature",
  "properties": {
    "hierarchy": [
      "tgn:7348263",
      "tgn:7002825",
      "tgn:7016622",
      "tgn:1000003",
      "tgn:1000095",
      "tgn:7029392"
    ],
    "placetype": [
      "aat:300008816"
    ],
    "id": 7348263,
    "name:xx": "Águila, Playa del"
  }
}
