{
  "geometry": {
    "type": "Point",
    "coordinates": [
      -77.7167,
      35.9333
    ]
  },
  "type": "Feature",
  "properties": {
    "hierarchy": [
      "tgn:2346537",
      "tgn:1000001",
      "tgn:7012149",
      "tgn:2001493",
      "tgn:7007709",
      "tgn:7029392"
    ],
    "placetype": [
      "aat:300008699"
    ],
    "id": 2346537,
    "name:xx": "Gay Branch"
  }
}
