{
  "geometry": {
    "type": "Point",
    "coordinates": [
      -58.7333,
      -34.4333
    ]
  },
  "type": "Feature",
  "properties": {
    "hierarchy": [
      "tgn:1019479",
      "tgn:1001160",
      "tgn:7006477",
      "tgn:1000002",
      "tgn:7029392"
    ],
    "placetype": [
      "aat:300008347"
    ],
    "id": 1019479,
    "name:xx": "Garín"
  }
}
