{
  "geometry": {
    "type": "Point",
    "coordinates": [
      -119.8167,
      48.9667
    ]
  },
  "type": "Feature",
  "properties": {
    "hierarchy": [
      "tgn:2556422",
      "tgn:1000001",
      "tgn:7012149",
      "tgn:1002742",
      "tgn:7007920",
      "tgn:7029392"
    ],
    "placetype": [
      "aat:300008706"
    ],
    "id": 2556422,
    "name:xx": "Olallie Creek"
  }
}
