{
  "geometry": {
    "type": "Point",
    "coordinates": [
      -96.5333,
      37.8167
    ]
  },
  "type": "Feature",
  "properties": {
    "hierarchy": [
      "tgn:2663220",
      "tgn:1000001",
      "tgn:2000696",
      "tgn:7012149",
      "tgn:7007254",
      "tgn:7029392"
    ],
    "placetype": [
      "aat:300008706"
    ],
    "id": 2663220,
    "name:xx": "Silver Creek"
  }
}
