{
  "geometry": {
    "type": "Point",
    "coordinates": [
      -83.3833,
      35.55
    ]
  },
  "type": "Feature",
  "properties": {
    "hierarchy": [
      "tgn:2467278",
      "tgn:1000001",
      "tgn:7012149",
      "tgn:2001543",
      "tgn:7007709",
      "tgn:7029392"
    ],
    "placetype": [
      "aat:300266640"
    ],
    "id": 2467278,
    "name:xx": "Long Drive Ridge"
  }
}
