{
  "geometry": {
    "type": "Point",
    "coordinates": [
      -111.3667,
      32.5833
    ]
  },
  "type": "Feature",
  "properties": {
    "hierarchy": [
      "tgn:2552317",
      "tgn:1000001",
      "tgn:7006451",
      "tgn:7012149",
      "tgn:2000101",
      "tgn:7029392"
    ],
    "placetype": [
      "aat:300006191"
    ],
    "id": 2552317,
    "name:xx": "Number Three Tank"
  }
}
