{
  "geometry": {
    "type": "Point",
    "coordinates": [
      34.6167,
      50.9667
    ]
  },
  "type": "Feature",
  "properties": {
    "hierarchy": [
      "tgn:1059825",
      "tgn:1000003",
      "tgn:1003410",
      "tgn:7006660",
      "tgn:7029392"
    ],
    "placetype": [
      "aat:300008347"
    ],
    "id": 1059825,
    "name:xx": "Stepanovka"
  }
}
