{
  "geometry": {
    "type": "Point",
    "coordinates": [
      -118.0667,
      45.3167
    ]
  },
  "type": "Feature",
  "properties": {
    "hierarchy": [
      "tgn:2212679",
      "tgn:1000001",
      "tgn:7012149",
      "tgn:2001721",
      "tgn:7007708",
      "tgn:7029392"
    ],
    "placetype": [
      "aat:300006191"
    ],
    "id": 2212679,
    "name:xx": "Byron Reservoir"
  }
}
