{
  "geometry": {
    "type": "Point",
    "coordinates": [
      -99.7833,
      33.55
    ]
  },
  "type": "Feature",
  "properties": {
    "hierarchy": [
      "tgn:2162924",
      "tgn:1000001",
      "tgn:7012149",
      "tgn:2002023",
      "tgn:7007826",
      "tgn:7029392"
    ],
    "placetype": [
      "aat:300006191"
    ],
    "id": 2162924,
    "name:xx": "Benjamin, Lake"
  }
}
