{
  "type": "FeatureCollection",
  "features": [
    {
      "geometry": {
        "type": "Point",
        "coordinates": [
          -134.0167,
          58.4833
        ]
      },
      "type": "Feature",
      "properties": {
        "hierarchy": [
          "tgn:2352630",
          "tgn:7006450",
          "tgn:1000001",
          "tgn:2124089",
          "tgn:7012149",
          "tgn:7029392"
        ],
        "placetype": [
          "aat:300266640"
        ],
        "id": 2352630,
        "name:xx": "Goat Ridge"
      }
    },
    {
      "geometry": {
        "type": "Point",
        "coordinates": [
          -134.05,
          58.5333
        ]
      },
      "type": "Feature",
      "properties": {
        "hierarchy": [
          "tgn:2352631",
          "tgn:7006450",
          "tgn:1000001",
          "tgn:2124089",
          "tgn:7012149",
          "tgn:7029392"
        ],
        "placetype": [
          "aat:300008798"
        ],
        "id": 2352631,
        "name:xx": "Goat Ridge"
      }
    },
    {
      "geometry": {
        "type": "Point",
        "coordinates": [
          -136.6167,
          58.6667
        ]
      },
      "type": "Feature",
      "properties": {
        "hierarchy": [
          "tgn:2352632",
          "tgn:7006450",
          "tgn:1000001",
          "tgn:7012149",
          "tgn:7019760",
          "tgn:7029392"
        ],
        "placetype": [
          "aat:300008798"
        ],
        "id": 2352632,
        "name:xx": "Goat Ridge"
      }
    },
    {
      "geometry": {
        "type": "Point",
        "coordinates": [
          -92.2667,
          36.2167
        ]
      },
      "type": "Feature",
      "properties": {
        "hierarchy": [
          "tgn:2352633",
          "tgn:2000107",
          "tgn:1000001",
          "tgn:7016172",
          "tgn:7012149",
          "tgn:7029392"
        ],
        "placetype": [
          "aat:300266640"
        ],
        "id": 2352633,
        "name:xx": "Goat Ridge"
      }
    },
    {
      "geometry": {
        "type": "Point",
        "coordinates": [
          -91.4333,
          36.2667
        ]
      },
      "type": "Feature",
      "properties": {
        "hierarchy": [
          "tgn:2352634",
          "tgn:1000001",
          "tgn:7016172",
          "tgn:7012149",
          "tgn:2000172",
          "tgn:7029392"
        ],
        "placetype": [
          "aat:300266640"
        ],
        "id": 2352634,
        "name:xx": "Goat Ridge"
      }
    },
    {
      "geometry": {
        "type": "Point",
        "coordinates": [
          -123.3,
          39.0833
        ]
      },
      "type": "Feature",
      "properties": {
        "hierarchy": [
          "tgn:2352635",
          "tgn:1000001",
          "tgn:7012149",
          "tgn:7007157",
          "tgn:2000185",
          "tgn:7029392"
        ],
        "placetype": [
          "aat:300266640"
        ],
        "id": 2352635,
        "name:xx": "Goat Ridge"
      }
    },
    {
      "geometry": {
        "type": "Point",
        "coordinates": [
          -114.9,
          45.9667
        ]
      },
      "type": "Feature",
      "properties": {
        "hierarchy": [
          "tgn:2352636",
          "tgn:1000001",
          "tgn:7012149",
          "tgn:7007250",
          "tgn:7029392"
        ],
        "placetype": [
          "aat:300266640"
        ],
        "id": 2352636,
        "name:xx": "Goat Ridge"
      }
    },
    {
      "geometry": {
        "type": "Point",
        "coordinates": [
          -116.6,
          45.3833
        ]
      },
      "type": "Feature",
      "properties": {
        "hierarchy": [
          "tgn:2352637",
          "tgn:1000001",
          "tgn:7012149",
          "tgn:2000476",
          "tgn:7007250",
          "tgn:7029392"
        ],
        "placetype": [
          "aat:300008798"
        ],
        "id": 2352637,
        "name:xx": "Goat Ridge"
      }
    },
    {
      "geometry": {
        "type": "Point",
        "coordinates": [
          -115.5833,
          47.9667
        ]
      },
      "type": "Feature",
      "properties": {
        "hierarchy": [
          "tgn:2352638",
          "tgn:1000001",
          "tgn:7012149",
          "tgn:2001304",
          "tgn:7007524",
          "tgn:7029392"
        ],
        "placetype": [
          "aat:300266640"
        ],
        "id": 2352638,
        "name:xx": "Goat Ridge"
      }
    },
    {
      "geometry": {
        "type": "Point",
        "coordinates": [
          -113,
          47.7667
        ]
      },
      "type": "Feature",
      "properties": {
        "hierarchy": [
          "tgn:2352639",
          "tgn:1000001",
          "tgn:7012149",
          "tgn:2001284",
          "tgn:7007524",
          "tgn:7029392"
        ],
        "placetype": [
          "aat:300266640"
        ],
        "id": 2352639,
        "name:xx": "Goat Ridge"
      }
    }
  ]
}
