{
  "geometry": {
    "type": "Point",
    "coordinates": [
      -94.0333,
      46.4667
    ]
  },
  "type": "Feature",
  "properties": {
    "hierarchy": [
      "tgn:2221823",
      "tgn:1000001",
      "tgn:2001016",
      "tgn:7012149",
      "tgn:7007521",
      "tgn:7029392"
    ],
    "placetype": [
      "aat:300000390"
    ],
    "id": 2221823,
    "name:xx": "Carlson Mine"
  }
}
