{
  "geometry": {
    "type": "Point",
    "coordinates": [
      14.9667,
      -9.8333
    ]
  },
  "type": "Feature",
  "properties": {
    "hierarchy": [
      "tgn:1087652",
      "tgn:7001242",
      "tgn:1000149",
      "tgn:1000835",
      "tgn:7029392"
    ],
    "placetype": [
      "aat:300008347"
    ],
    "id": 1087652,
    "name:xx": "Cabuta"
  }
}
