{
  "geometry": {
    "type": "Point",
    "coordinates": [
      -119.4167,
      37.6667
    ]
  },
  "type": "Feature",
  "properties": {
    "hierarchy": [
      "tgn:2361843",
      "tgn:1000001",
      "tgn:7012149",
      "tgn:7007157",
      "tgn:7014004",
      "tgn:7029392"
    ],
    "placetype": [
      "aat:300008706"
    ],
    "id": 2361843,
    "name:xx": "Gray Creek"
  }
}
