{
  "geometry": {
    "type": "Point",
    "coordinates": [
      -98.8667,
      35.8333
    ]
  },
  "type": "Feature",
  "properties": {
    "hierarchy": [
      "tgn:2630239",
      "tgn:1000001",
      "tgn:7012149",
      "tgn:7007707",
      "tgn:7029392"
    ],
    "placetype": [
      "aat:300008706"
    ],
    "id": 2630239,
    "name:xx": "Rough Creek"
  }
}
