{
  "geometry": {
    "type": "Point",
    "coordinates": [
      -104.4333,
      43.95
    ]
  },
  "type": "Feature",
  "properties": {
    "hierarchy": [
      "tgn:2306117",
      "tgn:1000001",
      "tgn:7012149",
      "tgn:2002387",
      "tgn:7007923",
      "tgn:7029392"
    ],
    "placetype": [
      "aat:300008706"
    ],
    "id": 2306117,
    "name:xx": "East Fork Beaver Creek"
  }
}
