{
  "geometry": {
    "type": "Point",
    "coordinates": [
      -80.4667,
      39.0167
    ]
  },
  "type": "Feature",
  "properties": {
    "hierarchy": [
      "tgn:2263524",
      "tgn:1000001",
      "tgn:7012149",
      "tgn:2002271",
      "tgn:7013961",
      "tgn:7029392"
    ],
    "placetype": [
      "aat:300008347"
    ],
    "id": 2263524,
    "name:xx": "Cox Town"
  }
}
