{
  "geometry": {
    "type": "Point",
    "coordinates": [
      -75.4833,
      42.9167
    ]
  },
  "type": "Feature",
  "properties": {
    "hierarchy": [
      "tgn:2477491",
      "tgn:1000001",
      "tgn:7012149",
      "tgn:1002624",
      "tgn:7007568",
      "tgn:7029392"
    ],
    "placetype": [
      "aat:300006191"
    ],
    "id": 2477491,
    "name:xx": "Lyons Pond"
  }
}
