{
  "geometry": {
    "type": "Point",
    "coordinates": [
      5.5167,
      59.7833
    ]
  },
  "type": "Feature",
  "properties": {
    "hierarchy": [
      "tgn:1048635",
      "tgn:7003646",
      "tgn:1000003",
      "tgn:1000088",
      "tgn:7029392"
    ],
    "placetype": [
      "aat:300008347"
    ],
    "id": 1048635,
    "name:xx": "Leirvik"
  }
}
