{
  "geometry": {
    "type": "Point",
    "coordinates": [
      -86.85,
      40.8333
    ]
  },
  "type": "Feature",
  "properties": {
    "hierarchy": [
      "tgn:2494473",
      "tgn:1000001",
      "tgn:7012149",
      "tgn:1003021",
      "tgn:7007252",
      "tgn:7029392"
    ],
    "placetype": [
      "aat:300006075"
    ],
    "id": 2494473,
    "name:xx": "Martin Ditch"
  }
}
