{
  "geometry": {
    "type": "Point",
    "coordinates": [
      -91.7333,
      47.5667
    ]
  },
  "type": "Feature",
  "properties": {
    "hierarchy": [
      "tgn:2549216",
      "tgn:1000001",
      "tgn:7012149",
      "tgn:7007521",
      "tgn:7029392"
    ],
    "placetype": [
      "aat:300008707"
    ],
    "id": 2549216,
    "name:xx": "North River"
  }
}
