{
  "geometry": {
    "type": "Point",
    "coordinates": [
      -81.35,
      25.8167
    ]
  },
  "type": "Feature",
  "properties": {
    "hierarchy": [
      "tgn:2238472",
      "tgn:1000001",
      "tgn:7012149",
      "tgn:7007240",
      "tgn:7029392"
    ],
    "placetype": [
      "aat:300132316"
    ],
    "id": 2238472,
    "name:xx": "Chokoloskee Bay"
  }
}
