{
  "geometry": {
    "type": "Point",
    "coordinates": [
      31.65,
      31.288011
    ]
  },
  "type": "Feature",
  "properties": {
    "hierarchy": [
      "tgn:7544109",
      "tgn:7001242",
      "tgn:7016833",
      "tgn:1001225",
      "tgn:7029392"
    ],
    "placetype": [
      "aat:300006075"
    ],
    "id": 7544109,
    "name:xx": "Tur'at ash Shirkah"
  }
}
