{
  "geometry": {
    "type": "Point",
    "coordinates": [
      -98.2333,
      45.7667
    ]
  },
  "type": "Feature",
  "properties": {
    "hierarchy": [
      "tgn:2529634",
      "tgn:1000001",
      "tgn:2001776",
      "tgn:7012149",
      "tgn:7007713",
      "tgn:7029392"
    ],
    "placetype": [
      "aat:300006191"
    ],
    "id": 2529634,
    "name:xx": "Mud Lake Reservoir"
  }
}
