{
  "geometry": {
    "type": "Point",
    "coordinates": [
      -80.5667,
      40.45
    ]
  },
  "type": "Feature",
  "properties": {
    "hierarchy": [
      "tgn:2733475",
      "tgn:1000001",
      "tgn:7012149",
      "tgn:1002449",
      "tgn:7013961",
      "tgn:7029392"
    ],
    "placetype": [
      "aat:300008699"
    ],
    "id": 2733475,
    "name:xx": "Turkeyfoot Run"
  }
}
