{
  "geometry": {
    "type": "Point",
    "coordinates": [
      121.7667,
      -3.8667
    ]
  },
  "type": "Feature",
  "properties": {
    "hierarchy": [
      "tgn:1078486",
      "tgn:1000004",
      "tgn:1001549",
      "tgn:1000116",
      "tgn:7029392"
    ],
    "placetype": [
      "aat:300008347"
    ],
    "id": 1078486,
    "name:xx": "Sanggona"
  }
}
