{
  "geometry": {
    "type": "Point",
    "coordinates": [
      -64.933,
      -15.216
    ]
  },
  "type": "Feature",
  "properties": {
    "hierarchy": [
      "tgn:1129266",
      "tgn:1000525",
      "tgn:1000046",
      "tgn:1000002",
      "tgn:7029392"
    ],
    "placetype": [
      "aat:300008707"
    ],
    "id": 1129266,
    "name:xx": "Sécure, Río"
  }
}
