{
  "geometry": {
    "type": "Point",
    "coordinates": [
      31.260769,
      27.191758
    ]
  },
  "type": "Feature",
  "properties": {
    "hierarchy": [
      "tgn:7525905",
      "tgn:7001242",
      "tgn:7001311",
      "tgn:7016833",
      "tgn:7029392"
    ],
    "placetype": [
      "aat:300008347"
    ],
    "name:en": "Al Kilābāt ash Sharqīyah",
    "id": 7525905
  }
}
