{
  "geometry": {
    "type": "Point",
    "coordinates": [
      -87.25,
      41.4833
    ]
  },
  "type": "Feature",
  "properties": {
    "hierarchy": [
      "tgn:2030857",
      "tgn:1000001",
      "tgn:7012149",
      "tgn:1002569",
      "tgn:7007252",
      "tgn:7029392"
    ],
    "placetype": [
      "aat:300008347"
    ],
    "id": 2030857,
    "name:xx": "Ainsworth"
  }
}
