{
  "type": "FeatureCollection",
  "features": [
    {
      "geometry": {
        "type": "Point",
        "coordinates": [
          -72.1,
          -36.383333
        ]
      },
      "type": "Feature",
      "properties": {
        "hierarchy": [
          "tgn:7280910",
          "tgn:1001637",
          "tgn:1000049",
          "tgn:1000002",
          "tgn:7029392"
        ],
        "placetype": [
          "aat:300008699"
        ],
        "id": 7280910,
        "name:xx": "San Javier, Estero"
      }
    },
    {
      "geometry": {
        "type": "Point",
        "coordinates": [
          -73.628611,
          -42.384444
        ]
      },
      "type": "Feature",
      "properties": {
        "hierarchy": [
          "tgn:7280911",
          "tgn:1001699",
          "tgn:1000049",
          "tgn:1000002",
          "tgn:7029392"
        ],
        "placetype": [
          "aat:300008347"
        ],
        "id": 7280911,
        "name:xx": "San Javier"
      }
    },
    {
      "geometry": {
        "type": "Point",
        "coordinates": [
          -72.2,
          -36.816667
        ]
      },
      "type": "Feature",
      "properties": {
        "hierarchy": [
          "tgn:7280912",
          "tgn:1001637",
          "tgn:1000049",
          "tgn:1000002",
          "tgn:7029392"
        ],
        "placetype": [
          "aat:300008347"
        ],
        "id": 7280912,
        "name:xx": "San Javier"
      }
    },
    {
      "geometry": {
        "type": "Point",
        "coordinates": [
          -71.75,
          -35.6
        ]
      },
      "type": "Feature",
      "properties": {
        "hierarchy": [
          "tgn:7280913",
          "tgn:1001705",
          "tgn:1000049",
          "tgn:1000002",
          "tgn:7029392"
        ],
        "placetype": [
          "aat:300008347"
        ],
        "id": 7280913,
        "name:xx": "San Javier"
      }
    },
    {
      "geometry": {
        "type": "Point",
        "coordinates": [
          -71.466667,
          -35.05
        ]
      },
      "type": "Feature",
      "properties": {
        "hierarchy": [
          "tgn:7280914",
          "tgn:1001705",
          "tgn:1000049",
          "tgn:1000002",
          "tgn:7029392"
        ],
        "placetype": [
          "aat:300008347"
        ],
        "id": 7280914,
        "name:xx": "San Javier"
      }
    },
    {
      "geometry": {
        "type": "Point",
        "coordinates": [
          -70.983333,
          -34.666667
        ]
      },
      "type": "Feature",
      "properties": {
        "hierarchy": [
          "tgn:7280915",
          "tgn:1001695",
          "tgn:1000049",
          "tgn:1000002",
          "tgn:7029392"
        ],
        "placetype": [
          "aat:300008347"
        ],
        "id": 7280915,
        "name:xx": "San Javier"
      }
    },
    {
      "geometry": {
        "type": "Point",
        "coordinates": [
          -70.883333,
          -33.633333
        ]
      },
      "type": "Feature",
      "properties": {
        "hierarchy": [
          "tgn:7280916",
          "tgn:1001708",
          "tgn:1000049",
          "tgn:1000002",
          "tgn:7029392"
        ],
        "placetype": [
          "aat:300008347"
        ],
        "id": 7280916,
        "name:xx": "San Javier"
      }
    },
    {
      "geometry": {
        "type": "Point",
        "coordinates": [
          -73,
          -39.766667
        ]
      },
      "type": "Feature",
      "properties": {
        "hierarchy": [
          "tgn:7280917",
          "tgn:1001699",
          "tgn:1000049",
          "tgn:1000002",
          "tgn:7029392"
        ],
        "placetype": [
          "aat:300387200"
        ],
        "id": 7280917,
        "name:xx": "San Javier"
      }
    },
    {
      "geometry": {
        "type": "Point",
        "coordinates": [
          -73.016667,
          -40.266667
        ]
      },
      "type": "Feature",
      "properties": {
        "hierarchy": [
          "tgn:7280918",
          "tgn:1001699",
          "tgn:1000049",
          "tgn:1000002",
          "tgn:7029392"
        ],
        "placetype": [
          "aat:300000206"
        ],
        "id": 7280918,
        "name:xx": "San Javier"
      }
    },
    {
      "geometry": {
        "type": "Point",
        "coordinates": [
          -72.35,
          -35.983333
        ]
      },
      "type": "Feature",
      "properties": {
        "hierarchy": [
          "tgn:7280919",
          "tgn:1001705",
          "tgn:1000049",
          "tgn:1000002",
          "tgn:7029392"
        ],
        "placetype": [
          "aat:300000206"
        ],
        "id": 7280919,
        "name:xx": "San Javier"
      }
    }
  ]
}
