{
  "geometry": {
    "type": "Point",
    "coordinates": [
      123.9667,
      40.6667
    ]
  },
  "type": "Feature",
  "properties": {
    "hierarchy": [
      "tgn:1139279",
      "tgn:1000004",
      "tgn:1001390",
      "tgn:1000111",
      "tgn:7029392"
    ],
    "placetype": [
      "aat:300008347"
    ],
    "id": 1139279,
    "name:xx": "Liujiahe"
  }
}
