{
  "geometry": {
    "type": "Point",
    "coordinates": [
      33.03,
      28.409
    ]
  },
  "type": "Feature",
  "properties": {
    "hierarchy": [
      "tgn:1111443",
      "tgn:7001242",
      "tgn:7001311",
      "tgn:7016833",
      "tgn:7029392"
    ],
    "placetype": [
      "aat:300008773",
      "aat:300379998"
    ],
    "id": 1111443,
    "name:xx": "Abū Ḥād, Wādī"
  }
}
