{
  "geometry": {
    "type": "Point",
    "coordinates": [
      -81.5833,
      35.8333
    ]
  },
  "type": "Feature",
  "properties": {
    "hierarchy": [
      "tgn:2726779",
      "tgn:1000001",
      "tgn:2001476",
      "tgn:7012149",
      "tgn:7007709",
      "tgn:7029392"
    ],
    "placetype": [
      "aat:300008347"
    ],
    "id": 2726779,
    "name:xx": "Town and Country"
  }
}
