{
  "type": "FeatureCollection",
  "features": [
    {
      "geometry": {
        "type": "Point",
        "coordinates": [
          -155.65,
          18.95
        ]
      },
      "type": "Feature",
      "properties": {
        "hierarchy": [
          "tgn:2589240",
          "tgn:7023902",
          "tgn:1000001",
          "tgn:7012149",
          "tgn:7007249",
          "tgn:7029392"
        ],
        "placetype": [
          "aat:300055621"
        ],
        "id": 2589240,
        "name:xx": "Pohokinikini"
      }
    },
    {
      "geometry": {
        "type": "Point",
        "coordinates": [
          -75.4667,
          40.9833
        ]
      },
      "type": "Feature",
      "properties": {
        "hierarchy": [
          "tgn:2589241",
          "tgn:1000001",
          "tgn:7012149",
          "tgn:7007710",
          "tgn:7029392"
        ],
        "placetype": [
          "aat:300008706"
        ],
        "id": 2589241,
        "name:xx": "Pohopoco Creek"
      }
    },
    {
      "geometry": {
        "type": "Point",
        "coordinates": [
          -75.4833,
          41
        ]
      },
      "type": "Feature",
      "properties": {
        "hierarchy": [
          "tgn:2589242",
          "tgn:1000001",
          "tgn:7012149",
          "tgn:7007710",
          "tgn:7029392"
        ],
        "placetype": [
          "aat:300008798"
        ],
        "id": 2589242,
        "name:xx": "Pohopoco Mountain"
      }
    },
    {
      "geometry": {
        "type": "Point",
        "coordinates": [
          -156.9167,
          20.8333
        ]
      },
      "type": "Feature",
      "properties": {
        "hierarchy": [
          "tgn:2589243",
          "tgn:1002648",
          "tgn:1000001",
          "tgn:1007799",
          "tgn:7012149",
          "tgn:7007249",
          "tgn:7029392"
        ],
        "placetype": [
          "aat:300008798"
        ],
        "id": 2589243,
        "name:xx": "Pohoula"
      }
    },
    {
      "geometry": {
        "type": "Point",
        "coordinates": [
          -155.5333,
          19.0833
        ]
      },
      "type": "Feature",
      "properties": {
        "hierarchy": [
          "tgn:2589245",
          "tgn:7023902",
          "tgn:1000001",
          "tgn:7012149",
          "tgn:7007249",
          "tgn:7029392"
        ],
        "placetype": [
          "aat:300008850"
        ],
        "id": 2589245,
        "name:xx": "Pohue, Lae"
      }
    },
    {
      "geometry": {
        "type": "Point",
        "coordinates": [
          -160.1,
          21.9167
        ]
      },
      "type": "Feature",
      "properties": {
        "hierarchy": [
          "tgn:2589246",
          "tgn:1002534",
          "tgn:1008345",
          "tgn:1000001",
          "tgn:7012149",
          "tgn:7007249",
          "tgn:7029392"
        ],
        "placetype": [
          "aat:300008761"
        ],
        "id": 2589246,
        "name:xx": "Pohueloa Valley"
      }
    },
    {
      "geometry": {
        "type": "Point",
        "coordinates": [
          -113.6,
          48.85
        ]
      },
      "type": "Feature",
      "properties": {
        "hierarchy": [
          "tgn:2589249",
          "tgn:1000001",
          "tgn:7012149",
          "tgn:2001277",
          "tgn:7007524",
          "tgn:7029392"
        ],
        "placetype": [
          "aat:300008680"
        ],
        "id": 2589249,
        "name:xx": "Poia Lake"
      }
    }
  ]
}
