{
  "geometry": {
    "type": "Point",
    "coordinates": [
      -103.7333,
      44.2833
    ]
  },
  "type": "Feature",
  "properties": {
    "hierarchy": [
      "tgn:2153768",
      "tgn:1000001",
      "tgn:7012149",
      "tgn:7007713",
      "tgn:7029392"
    ],
    "placetype": [
      "aat:300008706"
    ],
    "id": 2153768,
    "name:xx": "Bear Butte Creek"
  }
}
