{
  "geometry": {
    "type": "Point",
    "coordinates": [
      -83.6333,
      36.9167
    ]
  },
  "type": "Feature",
  "properties": {
    "hierarchy": [
      "tgn:2040310",
      "tgn:1000001",
      "tgn:7012149",
      "tgn:2000806",
      "tgn:7007255",
      "tgn:7029392"
    ],
    "placetype": [
      "aat:300008347"
    ],
    "id": 2040310,
    "name:xx": "Mills"
  }
}
