{
  "geometry": {
    "type": "Point",
    "coordinates": [
      79.87485,
      26.539991
    ]
  },
  "type": "Feature",
  "properties": {
    "hierarchy": [
      "tgn:7564201",
      "tgn:1000004",
      "tgn:7000198",
      "tgn:7016722",
      "tgn:7029392"
    ],
    "placetype": [
      "aat:300008347"
    ],
    "name:en": "Banīpāra Maharāj",
    "id": 7564201
  }
}
