{
  "geometry": {
    "type": "Point",
    "coordinates": [
      -2.5333,
      47.9667
    ]
  },
  "type": "Feature",
  "properties": {
    "hierarchy": [
      "tgn:7008261",
      "tgn:1000003",
      "tgn:7012216",
      "tgn:1000070",
      "tgn:7029392"
    ],
    "placetype": [
      "aat:300008347"
    ],
    "id": 7008261,
    "name:xx": "Josselin"
  }
}
