{
  "geometry": {
    "type": "Point",
    "coordinates": [
      -98.6833,
      47.5333
    ]
  },
  "type": "Feature",
  "properties": {
    "hierarchy": [
      "tgn:2697416",
      "tgn:1000001",
      "tgn:2001572",
      "tgn:7012149",
      "tgn:7007705",
      "tgn:7029392"
    ],
    "placetype": [
      "aat:300008680"
    ],
    "id": 2697416,
    "name:xx": "Stony Lake"
  }
}
