{
  "geometry": {
    "type": "Point",
    "coordinates": [
      -94.0333,
      46.3667
    ]
  },
  "type": "Feature",
  "properties": {
    "hierarchy": [
      "tgn:2735691",
      "tgn:1000001",
      "tgn:2001016",
      "tgn:7012149",
      "tgn:7007521",
      "tgn:7029392"
    ],
    "placetype": [
      "aat:300008680"
    ],
    "id": 2735691,
    "name:xx": "Twin Island Lake"
  }
}
