{
  "geometry": {
    "type": "Point",
    "coordinates": [
      -81.4833,
      39.3167
    ]
  },
  "type": "Feature",
  "properties": {
    "hierarchy": [
      "tgn:2170604",
      "tgn:1000001",
      "tgn:7012149",
      "tgn:2002303",
      "tgn:7013961",
      "tgn:7029392"
    ],
    "placetype": [
      "aat:300008699"
    ],
    "id": 2170604,
    "name:xx": "Big Run"
  }
}
