{
  "geometry": {
    "type": "Point",
    "coordinates": [
      -92.9333,
      40.7833
    ]
  },
  "type": "Feature",
  "properties": {
    "hierarchy": [
      "tgn:2534273",
      "tgn:7019177",
      "tgn:1000001",
      "tgn:7012149",
      "tgn:7007253",
      "tgn:7029392"
    ],
    "placetype": [
      "aat:300006191"
    ],
    "id": 2534273,
    "name:xx": "Mystic Reservoir"
  }
}
