{
  "type": "FeatureCollection",
  "features": [
    {
      "geometry": {
        "type": "Point",
        "coordinates": [
          -104.6,
          34.4333
        ]
      },
      "type": "Feature",
      "properties": {
        "hierarchy": [
          "tgn:2067700",
          "tgn:1000001",
          "tgn:7019560",
          "tgn:7012149",
          "tgn:7007566",
          "tgn:7029392"
        ],
        "placetype": [
          "aat:300008347"
        ],
        "id": 2067700,
        "name:xx": "Yeso"
      }
    },
    {
      "geometry": {
        "type": "Point",
        "coordinates": [
          -106.55,
          36.1833
        ]
      },
      "type": "Feature",
      "properties": {
        "hierarchy": [
          "tgn:2067702",
          "tgn:1000001",
          "tgn:7012149",
          "tgn:2001449",
          "tgn:7007566",
          "tgn:7029392"
        ],
        "placetype": [
          "aat:300008347"
        ],
        "id": 2067702,
        "name:xx": "Youngsville"
      }
    },
    {
      "geometry": {
        "type": "Point",
        "coordinates": [
          -106.35,
          35.1
        ]
      },
      "type": "Feature",
      "properties": {
        "hierarchy": [
          "tgn:2067703",
          "tgn:1000001",
          "tgn:2001428",
          "tgn:7012149",
          "tgn:7007566",
          "tgn:7029392"
        ],
        "placetype": [
          "aat:300008347",
          "aat:300387210"
        ],
        "id": 2067703,
        "name:xx": "Zamora"
      }
    },
    {
      "geometry": {
        "type": "Point",
        "coordinates": [
          -106.7167,
          35.5
        ]
      },
      "type": "Feature",
      "properties": {
        "hierarchy": [
          "tgn:2067705",
          "tgn:1000001",
          "tgn:7012149",
          "tgn:2001451",
          "tgn:7007566",
          "tgn:7029392"
        ],
        "placetype": [
          "aat:300008347"
        ],
        "id": 2067705,
        "name:xx": "Zia Pueblo"
      }
    }
  ]
}
