{
  "type": "FeatureCollection",
  "features": [
    {
      "geometry": {
        "type": "Point",
        "coordinates": [
          -106.75,
          48.6333
        ]
      },
      "type": "Feature",
      "properties": {
        "hierarchy": [
          "tgn:2303380",
          "tgn:1000001",
          "tgn:7012149",
          "tgn:2001312",
          "tgn:7007524",
          "tgn:7029392"
        ],
        "placetype": [
          "aat:300008706"
        ],
        "id": 2303380,
        "name:xx": "Eagle Creek"
      }
    },
    {
      "geometry": {
        "type": "Point",
        "coordinates": [
          -96.6833,
          42.4667
        ]
      },
      "type": "Feature",
      "properties": {
        "hierarchy": [
          "tgn:2303381",
          "tgn:1000001",
          "tgn:2001337",
          "tgn:7012149",
          "tgn:7007525",
          "tgn:7029392"
        ],
        "placetype": [
          "aat:300008706"
        ],
        "id": 2303381,
        "name:xx": "Eagle Creek"
      }
    },
    {
      "geometry": {
        "type": "Point",
        "coordinates": [
          -98.75,
          42.6333
        ]
      },
      "type": "Feature",
      "properties": {
        "hierarchy": [
          "tgn:2303382",
          "tgn:1000001",
          "tgn:2001360",
          "tgn:7012149",
          "tgn:7007525",
          "tgn:7029392"
        ],
        "placetype": [
          "aat:300008706"
        ],
        "id": 2303382,
        "name:xx": "Eagle Creek"
      }
    },
    {
      "geometry": {
        "type": "Point",
        "coordinates": [
          -117.6833,
          41.6167
        ]
      },
      "type": "Feature",
      "properties": {
        "hierarchy": [
          "tgn:2303383",
          "tgn:1000001",
          "tgn:2001414",
          "tgn:7012149",
          "tgn:7007526",
          "tgn:7029392"
        ],
        "placetype": [
          "aat:300008706"
        ],
        "id": 2303383,
        "name:xx": "Eagle Creek"
      }
    },
    {
      "geometry": {
        "type": "Point",
        "coordinates": [
          -105.3167,
          35.9333
        ]
      },
      "type": "Feature",
      "properties": {
        "hierarchy": [
          "tgn:2303384",
          "tgn:1000001",
          "tgn:7012149",
          "tgn:2001446",
          "tgn:7007566",
          "tgn:7029392"
        ],
        "placetype": [
          "aat:300008706"
        ],
        "id": 2303384,
        "name:xx": "Eagle Creek"
      }
    },
    {
      "geometry": {
        "type": "Point",
        "coordinates": [
          -105.7667,
          33.4
        ]
      },
      "type": "Feature",
      "properties": {
        "hierarchy": [
          "tgn:2303385",
          "tgn:1000001",
          "tgn:7012149",
          "tgn:2001442",
          "tgn:7007566",
          "tgn:7029392"
        ],
        "placetype": [
          "aat:300008706"
        ],
        "id": 2303385,
        "name:xx": "Eagle Creek"
      }
    },
    {
      "geometry": {
        "type": "Point",
        "coordinates": [
          -74.7333,
          43.7833
        ]
      },
      "type": "Feature",
      "properties": {
        "hierarchy": [
          "tgn:2303386",
          "tgn:1000001",
          "tgn:7012149",
          "tgn:7007568",
          "tgn:7029392"
        ],
        "placetype": [
          "aat:300008706"
        ],
        "id": 2303386,
        "name:xx": "Eagle Creek"
      }
    },
    {
      "geometry": {
        "type": "Point",
        "coordinates": [
          -83.75,
          35.5167
        ]
      },
      "type": "Feature",
      "properties": {
        "hierarchy": [
          "tgn:2303387",
          "tgn:1000001",
          "tgn:7012149",
          "tgn:2001543",
          "tgn:7007709",
          "tgn:7029392"
        ],
        "placetype": [
          "aat:300008706"
        ],
        "id": 2303387,
        "name:xx": "Eagle Creek"
      }
    },
    {
      "geometry": {
        "type": "Point",
        "coordinates": [
          -84.7667,
          41.6333
        ]
      },
      "type": "Feature",
      "properties": {
        "hierarchy": [
          "tgn:2303388",
          "tgn:1000001",
          "tgn:7012149",
          "tgn:1003025",
          "tgn:7007706",
          "tgn:7029392"
        ],
        "placetype": [
          "aat:300008706"
        ],
        "id": 2303388,
        "name:xx": "Eagle Creek"
      }
    },
    {
      "geometry": {
        "type": "Point",
        "coordinates": [
          -83.7,
          38.7833
        ]
      },
      "type": "Feature",
      "properties": {
        "hierarchy": [
          "tgn:2303389",
          "tgn:1000001",
          "tgn:1002210",
          "tgn:7012149",
          "tgn:7007706",
          "tgn:7029392"
        ],
        "placetype": [
          "aat:300008706"
        ],
        "id": 2303389,
        "name:xx": "Eagle Creek"
      }
    }
  ]
}
