{
  "geometry": {
    "type": "Point",
    "coordinates": [
      -65.6167,
      43.3833
    ]
  },
  "type": "Feature",
  "properties": {
    "hierarchy": [
      "tgn:1011132",
      "tgn:1006711",
      "tgn:7005685",
      "tgn:1000001",
      "tgn:7005802",
      "tgn:7029392"
    ],
    "placetype": [
      "aat:300008850"
    ],
    "id": 1011132,
    "name:xx": "Sable, Cape"
  }
}
