{
  "geometry": {
    "type": "Point",
    "coordinates": [
      -153.0833,
      59.95
    ]
  },
  "type": "Feature",
  "properties": {
    "hierarchy": [
      "tgn:2307881",
      "tgn:7006450",
      "tgn:1000001",
      "tgn:7019698",
      "tgn:7012149",
      "tgn:7029392"
    ],
    "placetype": [
      "aat:300008706"
    ],
    "id": 2307881,
    "name:xx": "East Glacier Creek"
  }
}
