{
  "geometry": {
    "type": "Point",
    "coordinates": [
      -77.8667,
      40.4667
    ]
  },
  "type": "Feature",
  "properties": {
    "hierarchy": [
      "tgn:2436522",
      "tgn:1000001",
      "tgn:7012149",
      "tgn:1002494",
      "tgn:7007710",
      "tgn:7029392"
    ],
    "placetype": [
      "aat:300008746"
    ],
    "id": 2436522,
    "name:xx": "Kidd Cave"
  }
}
