{
  "type": "FeatureCollection",
  "features": [
    {
      "geometry": {
        "type": "Point",
        "coordinates": [
          13.55,
          42.3
        ]
      },
      "type": "Feature",
      "properties": {
        "hierarchy": [
          "tgn:7040550",
          "tgn:7009084",
          "tgn:7004154",
          "tgn:1000003",
          "tgn:1000080",
          "tgn:7029392"
        ],
        "placetype": [
          "aat:300008347"
        ],
        "id": 7040550,
        "name:xx": "Santa Croce"
      }
    },
    {
      "geometry": {
        "type": "Point",
        "coordinates": [
          13.983333,
          41.183333
        ]
      },
      "type": "Feature",
      "properties": {
        "hierarchy": [
          "tgn:7040551",
          "tgn:7003011",
          "tgn:7003005",
          "tgn:1000003",
          "tgn:1000080",
          "tgn:7029392"
        ],
        "placetype": [
          "aat:300008347"
        ],
        "id": 7040551,
        "name:xx": "Santa Croce"
      }
    },
    {
      "geometry": {
        "type": "Point",
        "coordinates": [
          11.65,
          46.6
        ]
      },
      "type": "Feature",
      "properties": {
        "hierarchy": [
          "tgn:7040552",
          "tgn:1003440",
          "tgn:1000003",
          "tgn:7003124",
          "tgn:1000080",
          "tgn:7029392"
        ],
        "placetype": [
          "aat:300007466"
        ],
        "id": 7040552,
        "name:xx": "Santa Croce"
      }
    },
    {
      "geometry": {
        "type": "Point",
        "coordinates": [
          11.266667,
          43.766667
        ]
      },
      "type": "Feature",
      "properties": {
        "hierarchy": [
          "tgn:7040553",
          "tgn:7003163",
          "tgn:1000003",
          "tgn:7009760",
          "tgn:1000080",
          "tgn:7029392"
        ],
        "placetype": [
          "aat:300007466"
        ],
        "id": 7040553,
        "name:xx": "Santa Croce"
      }
    },
    {
      "geometry": {
        "type": "Point",
        "coordinates": [
          11.05,
          43.8
        ]
      },
      "type": "Feature",
      "properties": {
        "hierarchy": [
          "tgn:7040554",
          "tgn:7003163",
          "tgn:1000003",
          "tgn:7009760",
          "tgn:1000080",
          "tgn:7029392"
        ],
        "placetype": [
          "aat:300008347"
        ],
        "id": 7040554,
        "name:xx": "Santa Cristina in Prilli"
      }
    },
    {
      "geometry": {
        "type": "Point",
        "coordinates": [
          13.333333,
          37.983333
        ]
      },
      "type": "Feature",
      "properties": {
        "hierarchy": [
          "tgn:7040555",
          "tgn:1000003",
          "tgn:7003122",
          "tgn:1001732",
          "tgn:1000080",
          "tgn:7029392"
        ],
        "placetype": [
          "aat:300008347"
        ],
        "id": 7040555,
        "name:xx": "Santa Cristina Gela"
      }
    },
    {
      "geometry": {
        "type": "Point",
        "coordinates": [
          9.4,
          45.15
        ]
      },
      "type": "Feature",
      "properties": {
        "hierarchy": [
          "tgn:7040556",
          "tgn:7003132",
          "tgn:1000003",
          "tgn:7008516",
          "tgn:1000080",
          "tgn:7029392"
        ],
        "placetype": [
          "aat:300008347"
        ],
        "id": 7040556,
        "name:xx": "Santa Cristina e Bissone"
      }
    },
    {
      "geometry": {
        "type": "Point",
        "coordinates": [
          12.45,
          45.5
        ]
      },
      "type": "Feature",
      "properties": {
        "hierarchy": [
          "tgn:7040558",
          "tgn:7003006",
          "tgn:1000003",
          "tgn:7002997",
          "tgn:1000080",
          "tgn:7029392"
        ],
        "placetype": [
          "aat:300008791"
        ],
        "id": 7040558,
        "name:xx": "Santa Cristina, Isola"
      }
    }
  ]
}
