{
  "type": "FeatureCollection",
  "features": [
    {
      "geometry": {
        "type": "Point",
        "coordinates": [
          3.4667,
          46.8333
        ]
      },
      "type": "Feature",
      "properties": {
        "hierarchy": [
          "tgn:1032912",
          "tgn:1000003",
          "tgn:7002875",
          "tgn:1000070",
          "tgn:7029392"
        ],
        "placetype": [
          "aat:300008347"
        ],
        "id": 1032912,
        "name:xx": "Decize"
      }
    },
    {
      "geometry": {
        "type": "Point",
        "coordinates": [
          6.4,
          48.8833
        ]
      },
      "type": "Feature",
      "properties": {
        "hierarchy": [
          "tgn:1032914",
          "tgn:1000003",
          "tgn:7002888",
          "tgn:1000070",
          "tgn:7029392"
        ],
        "placetype": [
          "aat:300008347"
        ],
        "id": 1032914,
        "name:xx": "Delme"
      }
    },
    {
      "geometry": {
        "type": "Point",
        "coordinates": [
          1.9333,
          48.55
        ]
      },
      "type": "Feature",
      "properties": {
        "hierarchy": [
          "tgn:1032916",
          "tgn:1000003",
          "tgn:7002883",
          "tgn:1000070",
          "tgn:7029392"
        ],
        "placetype": [
          "aat:300008347"
        ],
        "id": 1032916,
        "name:xx": "Denisy"
      }
    },
    {
      "geometry": {
        "type": "Point",
        "coordinates": [
          1.7,
          49.0167
        ]
      },
      "type": "Feature",
      "properties": {
        "hierarchy": [
          "tgn:1032917",
          "tgn:1000003",
          "tgn:7002883",
          "tgn:1000070",
          "tgn:7029392"
        ],
        "placetype": [
          "aat:300008347"
        ],
        "id": 1032917,
        "name:xx": "Dennemont"
      }
    },
    {
      "geometry": {
        "type": "Point",
        "coordinates": [
          2.05,
          48.9667
        ]
      },
      "type": "Feature",
      "properties": {
        "hierarchy": [
          "tgn:1032918",
          "tgn:1000003",
          "tgn:7002883",
          "tgn:1000070",
          "tgn:7029392"
        ],
        "placetype": [
          "aat:300008347"
        ],
        "id": 1032918,
        "name:xx": "Denouval"
      }
    },
    {
      "geometry": {
        "type": "Point",
        "coordinates": [
          -1.6667,
          47.6667
        ]
      },
      "type": "Feature",
      "properties": {
        "hierarchy": [
          "tgn:1032919",
          "tgn:1000003",
          "tgn:7002893",
          "tgn:1000070",
          "tgn:7029392"
        ],
        "placetype": [
          "aat:300008347"
        ],
        "id": 1032919,
        "name:xx": "Derval"
      }
    }
  ]
}
