{
  "geometry": {
    "type": "Point",
    "coordinates": [
      24.0333,
      56.4167
    ]
  },
  "type": "Feature",
  "properties": {
    "hierarchy": [
      "tgn:4009511",
      "tgn:7012152",
      "tgn:1000003",
      "tgn:7006541",
      "tgn:7029392"
    ],
    "placetype": [
      "aat:300008347",
      "aat:300008375"
    ],
    "id": 4009511,
    "name:xx": "Rundale"
  }
}
