{
  "geometry": {
    "type": "Point",
    "coordinates": [
      -115.4667,
      46.1833
    ]
  },
  "type": "Feature",
  "properties": {
    "hierarchy": [
      "tgn:2699713",
      "tgn:1000001",
      "tgn:7012149",
      "tgn:2000476",
      "tgn:7007250",
      "tgn:7029392"
    ],
    "placetype": [
      "aat:300008706"
    ],
    "id": 2699713,
    "name:xx": "Stub Creek"
  }
}
