{
  "geometry": {
    "type": "Point",
    "coordinates": [
      -87.85,
      31.1833
    ]
  },
  "type": "Feature",
  "properties": {
    "hierarchy": [
      "tgn:2515964",
      "tgn:2000001",
      "tgn:7002659",
      "tgn:1000001",
      "tgn:7012149",
      "tgn:7029392"
    ],
    "placetype": [
      "aat:300008680"
    ],
    "id": 2515964,
    "name:xx": "Mimms Lake"
  }
}
