{
  "geometry": {
    "type": "Point",
    "coordinates": [
      -72.7333,
      42.3667
    ]
  },
  "type": "Feature",
  "properties": {
    "hierarchy": [
      "tgn:2739220",
      "tgn:1000001",
      "tgn:7013686",
      "tgn:7012149",
      "tgn:7007517",
      "tgn:7029392"
    ],
    "placetype": [
      "aat:300006191"
    ],
    "id": 2739220,
    "name:xx": "Unquomonk Reservoir"
  }
}
