{
  "type": "FeatureCollection",
  "features": [
    {
      "geometry": {
        "type": "Point",
        "coordinates": [
          -94.8,
          30.2833
        ]
      },
      "type": "Feature",
      "properties": {
        "hierarchy": [
          "tgn:2529540",
          "tgn:1000001",
          "tgn:7012149",
          "tgn:1002595",
          "tgn:7007826",
          "tgn:7029392"
        ],
        "placetype": [
          "aat:300008680"
        ],
        "id": 2529540,
        "name:xx": "Mud Lake"
      }
    },
    {
      "geometry": {
        "type": "Point",
        "coordinates": [
          -94.0833,
          30.3333
        ]
      },
      "type": "Feature",
      "properties": {
        "hierarchy": [
          "tgn:2529541",
          "tgn:1000001",
          "tgn:7012149",
          "tgn:1002454",
          "tgn:7007826",
          "tgn:7029392"
        ],
        "placetype": [
          "aat:300008680"
        ],
        "id": 2529541,
        "name:xx": "Mud Lake"
      }
    },
    {
      "geometry": {
        "type": "Point",
        "coordinates": [
          -96.2167,
          32.25
        ]
      },
      "type": "Feature",
      "properties": {
        "hierarchy": [
          "tgn:2529542",
          "tgn:1000001",
          "tgn:7012149",
          "tgn:1002464",
          "tgn:7007826",
          "tgn:7029392"
        ],
        "placetype": [
          "aat:300008680"
        ],
        "id": 2529542,
        "name:xx": "Mud Lake"
      }
    },
    {
      "geometry": {
        "type": "Point",
        "coordinates": [
          -94.8167,
          32.4667
        ]
      },
      "type": "Feature",
      "properties": {
        "hierarchy": [
          "tgn:2529543",
          "tgn:1000001",
          "tgn:7012149",
          "tgn:1002427",
          "tgn:7007826",
          "tgn:7029392"
        ],
        "placetype": [
          "aat:300008680"
        ],
        "id": 2529543,
        "name:xx": "Mud Lake"
      }
    },
    {
      "geometry": {
        "type": "Point",
        "coordinates": [
          -94.8167,
          30.2333
        ]
      },
      "type": "Feature",
      "properties": {
        "hierarchy": [
          "tgn:2529544",
          "tgn:1000001",
          "tgn:7012149",
          "tgn:1002595",
          "tgn:7007826",
          "tgn:7029392"
        ],
        "placetype": [
          "aat:300006191"
        ],
        "id": 2529544,
        "name:xx": "Mud Lake"
      }
    },
    {
      "geometry": {
        "type": "Point",
        "coordinates": [
          -96.6,
          28.5667
        ]
      },
      "type": "Feature",
      "properties": {
        "hierarchy": [
          "tgn:2529545",
          "tgn:1000001",
          "tgn:7012149",
          "tgn:2001950",
          "tgn:7007826",
          "tgn:7029392"
        ],
        "placetype": [
          "aat:300008680"
        ],
        "id": 2529545,
        "name:xx": "Mud Lake"
      }
    },
    {
      "geometry": {
        "type": "Point",
        "coordinates": [
          -96.2333,
          30.9667
        ]
      },
      "type": "Feature",
      "properties": {
        "hierarchy": [
          "tgn:2529546",
          "tgn:1000001",
          "tgn:7012149",
          "tgn:1002626",
          "tgn:7007826",
          "tgn:7029392"
        ],
        "placetype": [
          "aat:300008680"
        ],
        "id": 2529546,
        "name:xx": "Mud Lake"
      }
    },
    {
      "geometry": {
        "type": "Point",
        "coordinates": [
          -95.7,
          31.4333
        ]
      },
      "type": "Feature",
      "properties": {
        "hierarchy": [
          "tgn:2529547",
          "tgn:1000001",
          "tgn:7012149",
          "tgn:1002590",
          "tgn:7007826",
          "tgn:7029392"
        ],
        "placetype": [
          "aat:300008680"
        ],
        "id": 2529547,
        "name:xx": "Mud Lake"
      }
    },
    {
      "geometry": {
        "type": "Point",
        "coordinates": [
          -95.7833,
          31.6333
        ]
      },
      "type": "Feature",
      "properties": {
        "hierarchy": [
          "tgn:2529548",
          "tgn:1002148",
          "tgn:1000001",
          "tgn:7012149",
          "tgn:7007826",
          "tgn:7029392"
        ],
        "placetype": [
          "aat:300008680"
        ],
        "id": 2529548,
        "name:xx": "Mud Lake"
      }
    },
    {
      "geometry": {
        "type": "Point",
        "coordinates": [
          -95.2333,
          33.9
        ]
      },
      "type": "Feature",
      "properties": {
        "hierarchy": [
          "tgn:2529549",
          "tgn:1000001",
          "tgn:7012149",
          "tgn:2002061",
          "tgn:7007826",
          "tgn:7029392"
        ],
        "placetype": [
          "aat:300008680"
        ],
        "id": 2529549,
        "name:xx": "Mud Lake"
      }
    }
  ]
}
