{
  "geometry": {
    "type": "Point",
    "coordinates": [
      10.1667,
      47.5833
    ]
  },
  "type": "Feature",
  "properties": {
    "hierarchy": [
      "tgn:1111866",
      "tgn:1000003",
      "tgn:7000084",
      "tgn:7029392"
    ],
    "placetype": [
      "aat:300387346"
    ],
    "id": 1111866,
    "name:xx": "Allgäu"
  }
}
