{
  "geometry": {
    "type": "Point",
    "coordinates": [
      -111.7167,
      34.95
    ]
  },
  "type": "Feature",
  "properties": {
    "hierarchy": [
      "tgn:2266349",
      "tgn:1000001",
      "tgn:7006451",
      "tgn:2000092",
      "tgn:7012149",
      "tgn:7029392"
    ],
    "placetype": [
      "aat:300006191"
    ],
    "id": 2266349,
    "name:xx": "Crazy Park Tank"
  }
}
