{
  "geometry": {
    "type": "Point",
    "coordinates": [
      -94.9833,
      32.9667
    ]
  },
  "type": "Feature",
  "properties": {
    "hierarchy": [
      "tgn:2454198",
      "tgn:1000001",
      "tgn:7012149",
      "tgn:1002230",
      "tgn:7007826",
      "tgn:7029392"
    ],
    "placetype": [
      "aat:300008706"
    ],
    "id": 2454198,
    "name:xx": "Little Creek"
  }
}
