{
  "type": "FeatureCollection",
  "features": [
    {
      "geometry": {
        "type": "Point",
        "coordinates": [
          -81.8333,
          27.5667
        ]
      },
      "type": "Feature",
      "properties": {
        "hierarchy": [
          "tgn:2393410",
          "tgn:1000001",
          "tgn:1002452",
          "tgn:7012149",
          "tgn:7007240",
          "tgn:7029392"
        ],
        "placetype": [
          "aat:300008699"
        ],
        "id": 2393410,
        "name:xx": "Hog Branch"
      }
    },
    {
      "geometry": {
        "type": "Point",
        "coordinates": [
          -84.4667,
          32.0667
        ]
      },
      "type": "Feature",
      "properties": {
        "hierarchy": [
          "tgn:2393411",
          "tgn:1000001",
          "tgn:7012149",
          "tgn:2000443",
          "tgn:7007248",
          "tgn:7029392"
        ],
        "placetype": [
          "aat:300008699"
        ],
        "id": 2393411,
        "name:xx": "Hog Branch"
      }
    },
    {
      "geometry": {
        "type": "Point",
        "coordinates": [
          -83.2167,
          34.2167
        ]
      },
      "type": "Feature",
      "properties": {
        "hierarchy": [
          "tgn:2393412",
          "tgn:1000001",
          "tgn:7012149",
          "tgn:7007248",
          "tgn:7029392"
        ],
        "placetype": [
          "aat:300008699"
        ],
        "id": 2393412,
        "name:xx": "Hog Branch"
      }
    },
    {
      "geometry": {
        "type": "Point",
        "coordinates": [
          -87.9333,
          39.7167
        ]
      },
      "type": "Feature",
      "properties": {
        "hierarchy": [
          "tgn:2393413",
          "tgn:1000001",
          "tgn:7012149",
          "tgn:7007251",
          "tgn:7029392"
        ],
        "placetype": [
          "aat:300008699"
        ],
        "id": 2393413,
        "name:xx": "Hog Branch"
      }
    },
    {
      "geometry": {
        "type": "Point",
        "coordinates": [
          -87.15,
          38.3333
        ]
      },
      "type": "Feature",
      "properties": {
        "hierarchy": [
          "tgn:2393414",
          "tgn:1000001",
          "tgn:7012149",
          "tgn:2000551",
          "tgn:7007252",
          "tgn:7029392"
        ],
        "placetype": [
          "aat:300008699"
        ],
        "id": 2393414,
        "name:xx": "Hog Branch"
      }
    },
    {
      "geometry": {
        "type": "Point",
        "coordinates": [
          -94.4833,
          40.8
        ]
      },
      "type": "Feature",
      "properties": {
        "hierarchy": [
          "tgn:2393415",
          "tgn:1000001",
          "tgn:7012149",
          "tgn:2000647",
          "tgn:7007253",
          "tgn:7029392"
        ],
        "placetype": [
          "aat:300008699"
        ],
        "id": 2393415,
        "name:xx": "Hog Branch"
      }
    },
    {
      "geometry": {
        "type": "Point",
        "coordinates": [
          -94.6,
          38.3
        ]
      },
      "type": "Feature",
      "properties": {
        "hierarchy": [
          "tgn:2393416",
          "tgn:1000001",
          "tgn:7012149",
          "tgn:7029392"
        ],
        "placetype": [
          "aat:300008699"
        ],
        "id": 2393416,
        "name:xx": "Hog Branch"
      }
    },
    {
      "geometry": {
        "type": "Point",
        "coordinates": [
          -84.0167,
          37.3333
        ]
      },
      "type": "Feature",
      "properties": {
        "hierarchy": [
          "tgn:2393417",
          "tgn:1000001",
          "tgn:7012149",
          "tgn:2000802",
          "tgn:7007255",
          "tgn:7029392"
        ],
        "placetype": [
          "aat:300008699"
        ],
        "id": 2393417,
        "name:xx": "Hog Branch"
      }
    },
    {
      "geometry": {
        "type": "Point",
        "coordinates": [
          -83.05,
          37.9
        ]
      },
      "type": "Feature",
      "properties": {
        "hierarchy": [
          "tgn:2393418",
          "tgn:1000001",
          "tgn:7012149",
          "tgn:2000831",
          "tgn:7007255",
          "tgn:7029392"
        ],
        "placetype": [
          "aat:300008699"
        ],
        "id": 2393418,
        "name:xx": "Hog Branch"
      }
    },
    {
      "geometry": {
        "type": "Point",
        "coordinates": [
          -83.55,
          37.95
        ]
      },
      "type": "Feature",
      "properties": {
        "hierarchy": [
          "tgn:2393419",
          "tgn:1000001",
          "tgn:7012149",
          "tgn:2000826",
          "tgn:7007255",
          "tgn:7029392"
        ],
        "placetype": [
          "aat:300008699"
        ],
        "id": 2393419,
        "name:xx": "Hog Branch"
      }
    }
  ]
}
