{
  "geometry": {
    "type": "Point",
    "coordinates": [
      15.75,
      41.0167
    ]
  },
  "type": "Feature",
  "properties": {
    "hierarchy": [
      "tgn:1115341",
      "tgn:1003489",
      "tgn:7004610",
      "tgn:1000003",
      "tgn:1000080",
      "tgn:7029392"
    ],
    "placetype": [
      "aat:300008680"
    ],
    "id": 1115341,
    "name:xx": "Abate Alonia, Lago di"
  }
}
