{
  "geometry": {
    "type": "Point",
    "coordinates": [
      -3.65,
      35.25
    ]
  },
  "type": "Feature",
  "properties": {
    "hierarchy": [
      "tgn:1011078",
      "tgn:7001242",
      "tgn:1000179",
      "tgn:7593681",
      "tgn:7029392"
    ],
    "placetype": [
      "aat:300008850"
    ],
    "id": 1011078,
    "name:xx": "Quilates, Cap"
  }
}
