{
  "type": "FeatureCollection",
  "features": [
    {
      "geometry": {
        "type": "Point",
        "coordinates": [
          -81.7,
          28.6167
        ]
      },
      "type": "Feature",
      "properties": {
        "hierarchy": [
          "tgn:2019282",
          "tgn:1000001",
          "tgn:7012149",
          "tgn:1002567",
          "tgn:7007240",
          "tgn:7029392"
        ],
        "placetype": [
          "aat:300008347"
        ],
        "id": 2019282,
        "name:xx": "Ferndale"
      }
    },
    {
      "geometry": {
        "type": "Point",
        "coordinates": [
          -81.35,
          28.6333
        ]
      },
      "type": "Feature",
      "properties": {
        "hierarchy": [
          "tgn:2019283",
          "tgn:1000001",
          "tgn:7012149",
          "tgn:1002881",
          "tgn:7007240",
          "tgn:7029392"
        ],
        "placetype": [
          "aat:300008347"
        ],
        "id": 2019283,
        "name:xx": "Fern Park"
      }
    },
    {
      "geometry": {
        "type": "Point",
        "coordinates": [
          -87.2,
          30.5
        ]
      },
      "type": "Feature",
      "properties": {
        "hierarchy": [
          "tgn:2019285",
          "tgn:1000001",
          "tgn:2000265",
          "tgn:7012149",
          "tgn:7007240",
          "tgn:7029392"
        ],
        "placetype": [
          "aat:300008347"
        ],
        "id": 2019285,
        "name:xx": "Ferry Pass"
      }
    },
    {
      "geometry": {
        "type": "Point",
        "coordinates": [
          -83.9667,
          30.6
        ]
      },
      "type": "Feature",
      "properties": {
        "hierarchy": [
          "tgn:2019286",
          "tgn:1000001",
          "tgn:2000274",
          "tgn:7012149",
          "tgn:7007240",
          "tgn:7029392"
        ],
        "placetype": [
          "aat:300008347",
          "aat:300387210"
        ],
        "id": 2019286,
        "name:xx": "Festus"
      }
    },
    {
      "geometry": {
        "type": "Point",
        "coordinates": [
          -87.0167,
          30.9333
        ]
      },
      "type": "Feature",
      "properties": {
        "hierarchy": [
          "tgn:2019288",
          "tgn:1000001",
          "tgn:7012149",
          "tgn:2000285",
          "tgn:7007240",
          "tgn:7029392"
        ],
        "placetype": [
          "aat:300008347",
          "aat:300387210"
        ],
        "id": 2019288,
        "name:xx": "Fidelis"
      }
    }
  ]
}
