{
  "geometry": {
    "type": "Point",
    "coordinates": [
      -81.1167,
      41.7833
    ]
  },
  "type": "Feature",
  "properties": {
    "hierarchy": [
      "tgn:2136650",
      "tgn:1000001",
      "tgn:7012149",
      "tgn:1002570",
      "tgn:7007706",
      "tgn:7029392"
    ],
    "placetype": [
      "aat:300008706"
    ],
    "id": 2136650,
    "name:xx": "Arcola Creek"
  }
}
