{
  "geometry": {
    "type": "Point",
    "coordinates": [
      10.05,
      48.85
    ]
  },
  "type": "Feature",
  "properties": {
    "hierarchy": [
      "tgn:7178689",
      "tgn:7003692",
      "tgn:1000003",
      "tgn:7000084",
      "tgn:7029392"
    ],
    "placetype": [
      "aat:300008347"
    ],
    "id": 7178689,
    "name:xx": "Hammerstadt"
  }
}
