{
  "type": "FeatureCollection",
  "features": [
    {
      "geometry": {
        "type": "Point",
        "coordinates": [
          -94.8167,
          32.95
        ]
      },
      "type": "Feature",
      "properties": {
        "hierarchy": [
          "tgn:2103201",
          "tgn:1000001",
          "tgn:7012149",
          "tgn:1002230",
          "tgn:7007826",
          "tgn:7029392"
        ],
        "placetype": [
          "aat:300008347"
        ],
        "id": 2103201,
        "name:xx": "Center Point"
      }
    },
    {
      "geometry": {
        "type": "Point",
        "coordinates": [
          -99.0333,
          29.9333
        ]
      },
      "type": "Feature",
      "properties": {
        "hierarchy": [
          "tgn:2103203",
          "tgn:1000001",
          "tgn:7012149",
          "tgn:2002018",
          "tgn:7007826",
          "tgn:7029392"
        ],
        "placetype": [
          "aat:300008347"
        ],
        "id": 2103203,
        "name:xx": "Center Point"
      }
    },
    {
      "geometry": {
        "type": "Point",
        "coordinates": [
          -94.8833,
          33.1167
        ]
      },
      "type": "Feature",
      "properties": {
        "hierarchy": [
          "tgn:2103204",
          "tgn:1000001",
          "tgn:7012149",
          "tgn:1002948",
          "tgn:7007826",
          "tgn:7029392"
        ],
        "placetype": [
          "aat:300008347",
          "aat:300387210"
        ],
        "id": 2103204,
        "name:xx": "Center Point"
      }
    },
    {
      "geometry": {
        "type": "Point",
        "coordinates": [
          -97.7167,
          32.7333
        ]
      },
      "type": "Feature",
      "properties": {
        "hierarchy": [
          "tgn:2103206",
          "tgn:1000001",
          "tgn:7012149",
          "tgn:1002771",
          "tgn:7007826",
          "tgn:7029392"
        ],
        "placetype": [
          "aat:300008347",
          "aat:300387210"
        ],
        "id": 2103206,
        "name:xx": "Center Point"
      }
    },
    {
      "geometry": {
        "type": "Point",
        "coordinates": [
          -95.8,
          31.25
        ]
      },
      "type": "Feature",
      "properties": {
        "hierarchy": [
          "tgn:2103207",
          "tgn:1000001",
          "tgn:7012149",
          "tgn:1002590",
          "tgn:7007826",
          "tgn:7029392"
        ],
        "placetype": [
          "aat:300008347",
          "aat:300387210"
        ],
        "id": 2103207,
        "name:xx": "Centerview"
      }
    },
    {
      "geometry": {
        "type": "Point",
        "coordinates": [
          -95.0333,
          31.1667
        ]
      },
      "type": "Feature",
      "properties": {
        "hierarchy": [
          "tgn:2103208",
          "tgn:1000001",
          "tgn:7012149",
          "tgn:1002954",
          "tgn:7007826",
          "tgn:7029392"
        ],
        "placetype": [
          "aat:300008347",
          "aat:300387210"
        ],
        "id": 2103208,
        "name:xx": "Centerville"
      }
    },
    {
      "geometry": {
        "type": "Point",
        "coordinates": [
          -95.9667,
          31.25
        ]
      },
      "type": "Feature",
      "properties": {
        "hierarchy": [
          "tgn:2103209",
          "tgn:1000001",
          "tgn:7012149",
          "tgn:1002590",
          "tgn:7007826",
          "tgn:7029392"
        ],
        "placetype": [
          "aat:300008347"
        ],
        "id": 2103209,
        "name:xx": "Centerville"
      }
    }
  ]
}
