{
  "type": "FeatureCollection",
  "features": [
    {
      "geometry": {
        "type": "Point",
        "coordinates": [
          -85.8,
          33.3667
        ]
      },
      "type": "Feature",
      "properties": {
        "hierarchy": [
          "tgn:2337690",
          "tgn:7002659",
          "tgn:1000001",
          "tgn:7012149",
          "tgn:7029392"
        ],
        "placetype": [
          "aat:300008706"
        ],
        "id": 2337690,
        "name:xx": "Fox Creek"
      }
    },
    {
      "geometry": {
        "type": "Point",
        "coordinates": [
          -87.1333,
          34.5667
        ]
      },
      "type": "Feature",
      "properties": {
        "hierarchy": [
          "tgn:2337691",
          "tgn:7002659",
          "tgn:1000001",
          "tgn:7012149",
          "tgn:2000039",
          "tgn:7029392"
        ],
        "placetype": [
          "aat:300008706"
        ],
        "id": 2337691,
        "name:xx": "Fox Creek"
      }
    },
    {
      "geometry": {
        "type": "Point",
        "coordinates": [
          -136.2667,
          58.1667
        ]
      },
      "type": "Feature",
      "properties": {
        "hierarchy": [
          "tgn:2337692",
          "tgn:7006450",
          "tgn:1000001",
          "tgn:7012149",
          "tgn:7019760",
          "tgn:7029392"
        ],
        "placetype": [
          "aat:300008706"
        ],
        "id": 2337692,
        "name:xx": "Fox Creek"
      }
    },
    {
      "geometry": {
        "type": "Point",
        "coordinates": [
          -161.0833,
          59.3833
        ]
      },
      "type": "Feature",
      "properties": {
        "hierarchy": [
          "tgn:2337693",
          "tgn:7006450",
          "tgn:2000069",
          "tgn:1000001",
          "tgn:7012149",
          "tgn:7029392"
        ],
        "placetype": [
          "aat:300008706"
        ],
        "id": 2337693,
        "name:xx": "Fox Creek"
      }
    },
    {
      "geometry": {
        "type": "Point",
        "coordinates": [
          -150.95,
          59.9333
        ]
      },
      "type": "Feature",
      "properties": {
        "hierarchy": [
          "tgn:2337694",
          "tgn:7006450",
          "tgn:1000001",
          "tgn:7019698",
          "tgn:7012149",
          "tgn:7029392"
        ],
        "placetype": [
          "aat:300008706"
        ],
        "id": 2337694,
        "name:xx": "Fox Creek"
      }
    },
    {
      "geometry": {
        "type": "Point",
        "coordinates": [
          -151.0667,
          61.75
        ]
      },
      "type": "Feature",
      "properties": {
        "hierarchy": [
          "tgn:2337695",
          "tgn:7006450",
          "tgn:1000001",
          "tgn:2124053",
          "tgn:7012149",
          "tgn:7029392"
        ],
        "placetype": [
          "aat:300008706"
        ],
        "id": 2337695,
        "name:xx": "Fox Creek"
      }
    },
    {
      "geometry": {
        "type": "Point",
        "coordinates": [
          -148.8667,
          63.7833
        ]
      },
      "type": "Feature",
      "properties": {
        "hierarchy": [
          "tgn:2337696",
          "tgn:7006450",
          "tgn:1000001",
          "tgn:7030547",
          "tgn:7012149",
          "tgn:7029392"
        ],
        "placetype": [
          "aat:300008706"
        ],
        "id": 2337696,
        "name:xx": "Fox Creek"
      }
    },
    {
      "geometry": {
        "type": "Point",
        "coordinates": [
          -165.9667,
          64.6333
        ]
      },
      "type": "Feature",
      "properties": {
        "hierarchy": [
          "tgn:2337697",
          "tgn:7006450",
          "tgn:1000001",
          "tgn:7012149",
          "tgn:2000079",
          "tgn:7029392"
        ],
        "placetype": [
          "aat:300008706"
        ],
        "id": 2337697,
        "name:xx": "Fox Creek"
      }
    },
    {
      "geometry": {
        "type": "Point",
        "coordinates": [
          -141.5667,
          64.9667
        ]
      },
      "type": "Feature",
      "properties": {
        "hierarchy": [
          "tgn:2337698",
          "tgn:7006450",
          "tgn:1000001",
          "tgn:7012149",
          "tgn:2000085",
          "tgn:7029392"
        ],
        "placetype": [
          "aat:300008706"
        ],
        "id": 2337698,
        "name:xx": "Fox Creek"
      }
    },
    {
      "geometry": {
        "type": "Point",
        "coordinates": [
          -144.65,
          61.5167
        ]
      },
      "type": "Feature",
      "properties": {
        "hierarchy": [
          "tgn:2337699",
          "tgn:7006450",
          "tgn:1000001",
          "tgn:7012149",
          "tgn:2000086",
          "tgn:7029392"
        ],
        "placetype": [
          "aat:300008706"
        ],
        "id": 2337699,
        "name:xx": "Fox Creek"
      }
    }
  ]
}
