{
  "geometry": {
    "type": "Point",
    "coordinates": [
      26.1333,
      -17.4833
    ]
  },
  "type": "Feature",
  "properties": {
    "hierarchy": [
      "tgn:1095966",
      "tgn:7001242",
      "tgn:1001544",
      "tgn:1000209",
      "tgn:7029392"
    ],
    "placetype": [
      "aat:300008347"
    ],
    "id": 1095966,
    "name:xx": "Makoli"
  }
}
