{
  "type": "FeatureCollection",
  "features": [
    {
      "geometry": {
        "type": "Point",
        "coordinates": [
          -111.0667,
          34.85
        ]
      },
      "type": "Feature",
      "properties": {
        "hierarchy": [
          "tgn:2736700",
          "tgn:1000001",
          "tgn:7006451",
          "tgn:2000092",
          "tgn:7012149",
          "tgn:7029392"
        ],
        "placetype": [
          "aat:300006191"
        ],
        "id": 2736700,
        "name:xx": "Twin Tanks"
      }
    },
    {
      "geometry": {
        "type": "Point",
        "coordinates": [
          -112.8667,
          36.5167
        ]
      },
      "type": "Feature",
      "properties": {
        "hierarchy": [
          "tgn:2736701",
          "tgn:1000001",
          "tgn:7006451",
          "tgn:7012149",
          "tgn:2000098",
          "tgn:7029392"
        ],
        "placetype": [
          "aat:300006191"
        ],
        "id": 2736701,
        "name:xx": "Twin Tanks"
      }
    },
    {
      "geometry": {
        "type": "Point",
        "coordinates": [
          -116.0167,
          33.9833
        ]
      },
      "type": "Feature",
      "properties": {
        "hierarchy": [
          "tgn:2736702",
          "tgn:1000001",
          "tgn:7012149",
          "tgn:7007157",
          "tgn:1002828",
          "tgn:7029392"
        ],
        "placetype": [
          "aat:300006191"
        ],
        "id": 2736702,
        "name:xx": "Twin Tanks"
      }
    },
    {
      "geometry": {
        "type": "Point",
        "coordinates": [
          -107.3667,
          31.9167
        ]
      },
      "type": "Feature",
      "properties": {
        "hierarchy": [
          "tgn:2736703",
          "tgn:1000001",
          "tgn:7012149",
          "tgn:2001444",
          "tgn:7007566",
          "tgn:7029392"
        ],
        "placetype": [
          "aat:300006191"
        ],
        "id": 2736703,
        "name:xx": "Twin Tanks"
      }
    },
    {
      "geometry": {
        "type": "Point",
        "coordinates": [
          -106.7833,
          33.0833
        ]
      },
      "type": "Feature",
      "properties": {
        "hierarchy": [
          "tgn:2736704",
          "tgn:1000001",
          "tgn:7012149",
          "tgn:2001455",
          "tgn:7007566",
          "tgn:7029392"
        ],
        "placetype": [
          "aat:300006191"
        ],
        "id": 2736704,
        "name:xx": "Twin Tanks"
      }
    },
    {
      "geometry": {
        "type": "Point",
        "coordinates": [
          -106.0333,
          33.5333
        ]
      },
      "type": "Feature",
      "properties": {
        "hierarchy": [
          "tgn:2736705",
          "tgn:1000001",
          "tgn:7012149",
          "tgn:2001442",
          "tgn:7007566",
          "tgn:7029392"
        ],
        "placetype": [
          "aat:300006191"
        ],
        "id": 2736705,
        "name:xx": "Twin Tanks"
      }
    },
    {
      "geometry": {
        "type": "Point",
        "coordinates": [
          -104.8,
          33.8
        ]
      },
      "type": "Feature",
      "properties": {
        "hierarchy": [
          "tgn:2736706",
          "tgn:1000001",
          "tgn:2001430",
          "tgn:7012149",
          "tgn:7007566",
          "tgn:7029392"
        ],
        "placetype": [
          "aat:300006191"
        ],
        "id": 2736706,
        "name:xx": "Twin Tanks"
      }
    },
    {
      "geometry": {
        "type": "Point",
        "coordinates": [
          -104.0833,
          34.2833
        ]
      },
      "type": "Feature",
      "properties": {
        "hierarchy": [
          "tgn:2736707",
          "tgn:1000001",
          "tgn:7019560",
          "tgn:7012149",
          "tgn:7007566",
          "tgn:7029392"
        ],
        "placetype": [
          "aat:300006191"
        ],
        "id": 2736707,
        "name:xx": "Twin Tanks"
      }
    },
    {
      "geometry": {
        "type": "Point",
        "coordinates": [
          -104.0667,
          35.3667
        ]
      },
      "type": "Feature",
      "properties": {
        "hierarchy": [
          "tgn:2736708",
          "tgn:1000001",
          "tgn:7012149",
          "tgn:2001453",
          "tgn:7007566",
          "tgn:7029392"
        ],
        "placetype": [
          "aat:300006191"
        ],
        "id": 2736708,
        "name:xx": "Twin Tanks"
      }
    },
    {
      "geometry": {
        "type": "Point",
        "coordinates": [
          -103.5667,
          35.4167
        ]
      },
      "type": "Feature",
      "properties": {
        "hierarchy": [
          "tgn:2736709",
          "tgn:1000001",
          "tgn:7012149",
          "tgn:2001439",
          "tgn:7007566",
          "tgn:7029392"
        ],
        "placetype": [
          "aat:300006191"
        ],
        "id": 2736709,
        "name:xx": "Twin Tanks"
      }
    }
  ]
}
