{
  "geometry": {
    "type": "Point",
    "coordinates": [
      125.45,
      11.1167
    ]
  },
  "type": "Feature",
  "properties": {
    "hierarchy": [
      "tgn:1084224",
      "tgn:1000004",
      "tgn:1001231",
      "tgn:1000135",
      "tgn:7029392"
    ],
    "placetype": [
      "aat:300008347"
    ],
    "id": 1084224,
    "name:xx": "Giporlos"
  }
}
