{
  "type": "FeatureCollection",
  "features": [
    {
      "geometry": {
        "type": "Point",
        "coordinates": [
          -89.25,
          36.25
        ]
      },
      "type": "Feature",
      "properties": {
        "hierarchy": [
          "tgn:2099280",
          "tgn:1000001",
          "tgn:7012149",
          "tgn:2001902",
          "tgn:7007825",
          "tgn:7029392"
        ],
        "placetype": [
          "aat:300008347"
        ],
        "id": 2099280,
        "name:xx": "Glass"
      }
    },
    {
      "geometry": {
        "type": "Point",
        "coordinates": [
          -88.6,
          36.2
        ]
      },
      "type": "Feature",
      "properties": {
        "hierarchy": [
          "tgn:2099281",
          "tgn:1000001",
          "tgn:7012149",
          "tgn:2001928",
          "tgn:7007825",
          "tgn:7029392"
        ],
        "placetype": [
          "aat:300008347"
        ],
        "id": 2099281,
        "name:xx": "Gleason"
      }
    },
    {
      "geometry": {
        "type": "Point",
        "coordinates": [
          -85.9167,
          35.35
        ]
      },
      "type": "Feature",
      "properties": {
        "hierarchy": [
          "tgn:2099282",
          "tgn:1000001",
          "tgn:7012149",
          "tgn:2001852",
          "tgn:7007825",
          "tgn:7029392"
        ],
        "placetype": [
          "aat:300008347",
          "aat:300387210"
        ],
        "id": 2099282,
        "name:xx": "Glen"
      }
    },
    {
      "geometry": {
        "type": "Point",
        "coordinates": [
          -84.7333,
          35.8
        ]
      },
      "type": "Feature",
      "properties": {
        "hierarchy": [
          "tgn:2099283",
          "tgn:1000001",
          "tgn:7012149",
          "tgn:2001909",
          "tgn:7007825",
          "tgn:7029392"
        ],
        "placetype": [
          "aat:300008347"
        ],
        "id": 2099283,
        "name:xx": "Glen Alice"
      }
    },
    {
      "geometry": {
        "type": "Point",
        "coordinates": [
          -86.9833,
          35.5333
        ]
      },
      "type": "Feature",
      "properties": {
        "hierarchy": [
          "tgn:2099284",
          "tgn:1000001",
          "tgn:7012149",
          "tgn:2001896",
          "tgn:7007825",
          "tgn:7029392"
        ],
        "placetype": [
          "aat:300008347"
        ],
        "id": 2099284,
        "name:xx": "Glendale"
      }
    },
    {
      "geometry": {
        "type": "Point",
        "coordinates": [
          -84.2,
          35.7167
        ]
      },
      "type": "Feature",
      "properties": {
        "hierarchy": [
          "tgn:2099285",
          "tgn:1000001",
          "tgn:7012149",
          "tgn:2001889",
          "tgn:7007825",
          "tgn:7029392"
        ],
        "placetype": [
          "aat:300008347",
          "aat:300387210"
        ],
        "id": 2099285,
        "name:xx": "Glendale"
      }
    },
    {
      "geometry": {
        "type": "Point",
        "coordinates": [
          -87.3833,
          35.1
        ]
      },
      "type": "Feature",
      "properties": {
        "hierarchy": [
          "tgn:2099286",
          "tgn:1000001",
          "tgn:7012149",
          "tgn:2001886",
          "tgn:7007825",
          "tgn:7029392"
        ],
        "placetype": [
          "aat:300008347",
          "aat:300387210"
        ],
        "id": 2099286,
        "name:xx": "Glendale"
      }
    },
    {
      "geometry": {
        "type": "Point",
        "coordinates": [
          -87,
          35.1833
        ]
      },
      "type": "Feature",
      "properties": {
        "hierarchy": [
          "tgn:2099287",
          "tgn:1000001",
          "tgn:7012149",
          "tgn:2001864",
          "tgn:7007825",
          "tgn:7029392"
        ],
        "placetype": [
          "aat:300008347"
        ],
        "id": 2099287,
        "name:xx": "Glendale Estates"
      }
    }
  ]
}
