{
  "geometry": {
    "type": "Point",
    "coordinates": [
      -119.7667,
      34.4667
    ]
  },
  "type": "Feature",
  "properties": {
    "hierarchy": [
      "tgn:2307050",
      "tgn:1000001",
      "tgn:7012149",
      "tgn:7007157",
      "tgn:1002867",
      "tgn:7029392"
    ],
    "placetype": [
      "aat:300008706"
    ],
    "id": 2307050,
    "name:xx": "East Fork Maria Ygnacio Creek"
  }
}
