{
  "geometry": {
    "type": "Point",
    "coordinates": [
      -102.45,
      35.4833
    ]
  },
  "type": "Feature",
  "properties": {
    "hierarchy": [
      "tgn:2461829",
      "tgn:1000001",
      "tgn:7012149",
      "tgn:2002051",
      "tgn:7007826",
      "tgn:7029392"
    ],
    "placetype": [
      "aat:300008761"
    ],
    "id": 2461829,
    "name:xx": "Little Torrey Canyon"
  }
}
