{
  "type": "FeatureCollection",
  "features": [
    {
      "geometry": {
        "type": "Point",
        "coordinates": [
          -90.5167,
          40.35
        ]
      },
      "type": "Feature",
      "properties": {
        "hierarchy": [
          "tgn:2366660",
          "tgn:1000001",
          "tgn:7012149",
          "tgn:2000518",
          "tgn:7007251",
          "tgn:7029392"
        ],
        "placetype": [
          "aat:300008706"
        ],
        "id": 2366660,
        "name:xx": "Grindstone Creek"
      }
    },
    {
      "geometry": {
        "type": "Point",
        "coordinates": [
          -87.1,
          40.3
        ]
      },
      "type": "Feature",
      "properties": {
        "hierarchy": [
          "tgn:2366661",
          "tgn:1000001",
          "tgn:7012149",
          "tgn:1002380",
          "tgn:7007252",
          "tgn:7029392"
        ],
        "placetype": [
          "aat:300008706"
        ],
        "id": 2366661,
        "name:xx": "Grindstone Creek"
      }
    },
    {
      "geometry": {
        "type": "Point",
        "coordinates": [
          -94.9667,
          37.4833
        ]
      },
      "type": "Feature",
      "properties": {
        "hierarchy": [
          "tgn:2366662",
          "tgn:1000001",
          "tgn:2000678",
          "tgn:7012149",
          "tgn:7007254",
          "tgn:7029392"
        ],
        "placetype": [
          "aat:300008706"
        ],
        "id": 2366662,
        "name:xx": "Grindstone Creek"
      }
    },
    {
      "geometry": {
        "type": "Point",
        "coordinates": [
          -88.0833,
          36.55
        ]
      },
      "type": "Feature",
      "properties": {
        "hierarchy": [
          "tgn:2366663",
          "tgn:1000001",
          "tgn:2000777",
          "tgn:7012149",
          "tgn:7007255",
          "tgn:7029392"
        ],
        "placetype": [
          "aat:300008706"
        ],
        "id": 2366663,
        "name:xx": "Grindstone Creek"
      }
    },
    {
      "geometry": {
        "type": "Point",
        "coordinates": [
          -84.85,
          38.2333
        ]
      },
      "type": "Feature",
      "properties": {
        "hierarchy": [
          "tgn:2366664",
          "tgn:1000001",
          "tgn:7012149",
          "tgn:1002382",
          "tgn:7007255",
          "tgn:7029392"
        ],
        "placetype": [
          "aat:300008706"
        ],
        "id": 2366664,
        "name:xx": "Grindstone Creek"
      }
    },
    {
      "geometry": {
        "type": "Point",
        "coordinates": [
          -85.2,
          43.9833
        ]
      },
      "type": "Feature",
      "properties": {
        "hierarchy": [
          "tgn:2366665",
          "tgn:1000001",
          "tgn:7012149",
          "tgn:2000987",
          "tgn:7007520",
          "tgn:7029392"
        ],
        "placetype": [
          "aat:300008706"
        ],
        "id": 2366665,
        "name:xx": "Grindstone Creek"
      }
    },
    {
      "geometry": {
        "type": "Point",
        "coordinates": [
          -86.2333,
          46.15
        ]
      },
      "type": "Feature",
      "properties": {
        "hierarchy": [
          "tgn:2366666",
          "tgn:1000001",
          "tgn:7012149",
          "tgn:2000996",
          "tgn:7007520",
          "tgn:7029392"
        ],
        "placetype": [
          "aat:300008706"
        ],
        "id": 2366666,
        "name:xx": "Grindstone Creek"
      }
    },
    {
      "geometry": {
        "type": "Point",
        "coordinates": [
          -92.2833,
          38.9167
        ]
      },
      "type": "Feature",
      "properties": {
        "hierarchy": [
          "tgn:2366667",
          "tgn:1000001",
          "tgn:1002190",
          "tgn:7012149",
          "tgn:7007523",
          "tgn:7029392"
        ],
        "placetype": [
          "aat:300008706"
        ],
        "id": 2366667,
        "name:xx": "Grindstone Creek"
      }
    },
    {
      "geometry": {
        "type": "Point",
        "coordinates": [
          -94.3333,
          39.5333
        ]
      },
      "type": "Feature",
      "properties": {
        "hierarchy": [
          "tgn:2366668",
          "tgn:1000001",
          "tgn:7012149",
          "tgn:2001188",
          "tgn:7007523",
          "tgn:7029392"
        ],
        "placetype": [
          "aat:300008706"
        ],
        "id": 2366668,
        "name:xx": "Grindstone Creek"
      }
    },
    {
      "geometry": {
        "type": "Point",
        "coordinates": [
          -94.35,
          39.7167
        ]
      },
      "type": "Feature",
      "properties": {
        "hierarchy": [
          "tgn:2366669",
          "tgn:1000001",
          "tgn:7012149",
          "tgn:7007523",
          "tgn:7029392"
        ],
        "placetype": [
          "aat:300008706"
        ],
        "id": 2366669,
        "name:xx": "Grindstone Creek"
      }
    }
  ]
}
