{
  "geometry": {
    "type": "Point",
    "coordinates": [
      -83.6333,
      44.2333
    ]
  },
  "type": "Feature",
  "properties": {
    "hierarchy": [
      "tgn:2599436",
      "tgn:1000001",
      "tgn:7012149",
      "tgn:2000965",
      "tgn:7007520",
      "tgn:7029392"
    ],
    "placetype": [
      "aat:300008706"
    ],
    "id": 2599436,
    "name:xx": "Proper Creek"
  }
}
