{
  "geometry": {
    "type": "Point",
    "coordinates": [
      31.133333,
      29.183333
    ]
  },
  "type": "Feature",
  "properties": {
    "hierarchy": [
      "tgn:7529443",
      "tgn:7001242",
      "tgn:7001105",
      "tgn:7016833",
      "tgn:7029392"
    ],
    "placetype": [
      "aat:300005926"
    ],
    "name:en": "S카d카 ash Sh훮bb at T훮'ib",
    "id": 7529443
  }
}
