{
  "geometry": {
    "type": "Point",
    "coordinates": [
      -78.25,
      41.55
    ]
  },
  "type": "Feature",
  "properties": {
    "hierarchy": [
      "tgn:2149157",
      "tgn:1000001",
      "tgn:1002229",
      "tgn:7012149",
      "tgn:7007710",
      "tgn:7029392"
    ],
    "placetype": [
      "aat:300008699"
    ],
    "id": 2149157,
    "name:xx": "Barr Run"
  }
}
