{
  "geometry": {
    "type": "Point",
    "coordinates": [
      -85.05,
      32.4167
    ]
  },
  "type": "Feature",
  "properties": {
    "hierarchy": [
      "tgn:2653314",
      "tgn:7002659",
      "tgn:1000001",
      "tgn:7012149",
      "tgn:2000056",
      "tgn:7029392"
    ],
    "placetype": [
      "aat:300008706"
    ],
    "id": 2653314,
    "name:xx": "Sevenmile Creek"
  }
}
