{
  "geometry": {
    "type": "Point",
    "coordinates": [
      117.5833,
      26.2667
    ]
  },
  "type": "Feature",
  "properties": {
    "hierarchy": [
      "tgn:1071338",
      "tgn:1000004",
      "tgn:7001796",
      "tgn:1000111",
      "tgn:7029392"
    ],
    "placetype": [
      "aat:300008347"
    ],
    "id": 1071338,
    "name:xx": "Sanming"
  }
}
