{
  "geometry": {
    "type": "Point",
    "coordinates": [
      78.05,
      20.166667
    ]
  },
  "type": "Feature",
  "properties": {
    "hierarchy": [
      "tgn:7559514",
      "tgn:1000004",
      "tgn:7000198",
      "tgn:1001895",
      "tgn:7029392"
    ],
    "placetype": [
      "aat:300008347"
    ],
    "name:en": "Rui",
    "id": 7559514
  }
}
