{
  "geometry": {
    "type": "Point",
    "coordinates": [
      -60.9333,
      -27.6667
    ]
  },
  "type": "Feature",
  "properties": {
    "hierarchy": [
      "tgn:1019355",
      "tgn:1001195",
      "tgn:7006477",
      "tgn:1000002",
      "tgn:7029392"
    ],
    "placetype": [
      "aat:300008347"
    ],
    "id": 1019355,
    "name:xx": "Coronel Du Graty"
  }
}
