{
  "geometry": {
    "type": "Point",
    "coordinates": [
      28.3667,
      37.2167
    ]
  },
  "type": "Feature",
  "properties": {
    "hierarchy": [
      "tgn:1086700",
      "tgn:1001438",
      "tgn:1000004",
      "tgn:7018451",
      "tgn:1000144",
      "tgn:7029392"
    ],
    "placetype": [
      "aat:300008347",
      "aat:300008389",
      "aat:300387223",
      "aat:300387285"
    ],
    "id": 1086700,
    "name:xx": "Muğla"
  }
}
