{
  "geometry": {
    "type": "Point",
    "coordinates": [
      -75.9833,
      43.35
    ]
  },
  "type": "Feature",
  "properties": {
    "hierarchy": [
      "tgn:2233726",
      "tgn:1000001",
      "tgn:7012149",
      "tgn:1002758",
      "tgn:7007568",
      "tgn:7029392"
    ],
    "placetype": [
      "aat:300008680"
    ],
    "id": 2233726,
    "name:xx": "Chase Pond"
  }
}
