{
  "geometry": {
    "type": "Point",
    "coordinates": [
      104.4667,
      29.7667
    ]
  },
  "type": "Feature",
  "properties": {
    "hierarchy": [
      "tgn:1069779",
      "tgn:1000004",
      "tgn:7002087",
      "tgn:1000111",
      "tgn:7029392"
    ],
    "placetype": [
      "aat:300008347"
    ],
    "id": 1069779,
    "name:xx": "Lianjiechang"
  }
}
