{
  "geometry": {
    "type": "Point",
    "coordinates": [
      -115.75,
      44.1833
    ]
  },
  "type": "Feature",
  "properties": {
    "hierarchy": [
      "tgn:2648978",
      "tgn:1000001",
      "tgn:2000459",
      "tgn:7012149",
      "tgn:7007250",
      "tgn:7029392"
    ],
    "placetype": [
      "aat:300008706"
    ],
    "id": 2648978,
    "name:xx": "Scott Creek"
  }
}
