{
  "geometry": {
    "type": "Point",
    "coordinates": [
      -114.3833,
      44.45
    ]
  },
  "type": "Feature",
  "properties": {
    "hierarchy": [
      "tgn:2547989",
      "tgn:1000001",
      "tgn:2000470",
      "tgn:7012149",
      "tgn:7007250",
      "tgn:7029392"
    ],
    "placetype": [
      "aat:300008761"
    ],
    "id": 2547989,
    "name:xx": "North Gulch"
  }
}
