{
  "type": "FeatureCollection",
  "features": [
    {
      "geometry": {
        "type": "Point",
        "coordinates": [
          -117.6667,
          43.8333
        ]
      },
      "type": "Feature",
      "properties": {
        "hierarchy": [
          "tgn:2197880",
          "tgn:1000001",
          "tgn:7012149",
          "tgn:2001718",
          "tgn:7007708",
          "tgn:7029392"
        ],
        "placetype": [
          "aat:300006191"
        ],
        "id": 2197880,
        "name:xx": "Brown Reservoir"
      }
    },
    {
      "geometry": {
        "type": "Point",
        "coordinates": [
          -122.9667,
          42.1667
        ]
      },
      "type": "Feature",
      "properties": {
        "hierarchy": [
          "tgn:2197881",
          "tgn:1000001",
          "tgn:7012149",
          "tgn:2001711",
          "tgn:7007708",
          "tgn:7029392"
        ],
        "placetype": [
          "aat:300006191"
        ],
        "id": 2197881,
        "name:xx": "Brown Reservoir"
      }
    },
    {
      "geometry": {
        "type": "Point",
        "coordinates": [
          -104.6667,
          44.0833
        ]
      },
      "type": "Feature",
      "properties": {
        "hierarchy": [
          "tgn:2197882",
          "tgn:1000001",
          "tgn:7012149",
          "tgn:2002387",
          "tgn:7007923",
          "tgn:7029392"
        ],
        "placetype": [
          "aat:300006191"
        ],
        "id": 2197882,
        "name:xx": "Brown Reservoir"
      }
    },
    {
      "geometry": {
        "type": "Point",
        "coordinates": [
          -105.9333,
          43.7333
        ]
      },
      "type": "Feature",
      "properties": {
        "hierarchy": [
          "tgn:2197883",
          "tgn:1000001",
          "tgn:2002367",
          "tgn:7012149",
          "tgn:7007923",
          "tgn:7029392"
        ],
        "placetype": [
          "aat:300006191"
        ],
        "id": 2197883,
        "name:xx": "Brown Reservoir"
      }
    },
    {
      "geometry": {
        "type": "Point",
        "coordinates": [
          -87.3,
          33.45
        ]
      },
      "type": "Feature",
      "properties": {
        "hierarchy": [
          "tgn:2197884",
          "tgn:7002659",
          "tgn:1000001",
          "tgn:7012149",
          "tgn:2000036",
          "tgn:7029392"
        ],
        "placetype": [
          "aat:300266640"
        ],
        "id": 2197884,
        "name:xx": "Brown Ridge"
      }
    },
    {
      "geometry": {
        "type": "Point",
        "coordinates": [
          -109.4,
          36.45
        ]
      },
      "type": "Feature",
      "properties": {
        "hierarchy": [
          "tgn:2197885",
          "tgn:2000090",
          "tgn:1000001",
          "tgn:7006451",
          "tgn:7012149",
          "tgn:7029392"
        ],
        "placetype": [
          "aat:300266640"
        ],
        "id": 2197885,
        "name:xx": "Brown Ridge"
      }
    },
    {
      "geometry": {
        "type": "Point",
        "coordinates": [
          -84.9167,
          32.3667
        ]
      },
      "type": "Feature",
      "properties": {
        "hierarchy": [
          "tgn:2197886",
          "tgn:1000001",
          "tgn:2000317",
          "tgn:7012149",
          "tgn:7007248",
          "tgn:7029392"
        ],
        "placetype": [
          "aat:300266640"
        ],
        "id": 2197886,
        "name:xx": "Brown Ridge"
      }
    },
    {
      "geometry": {
        "type": "Point",
        "coordinates": [
          -86.4,
          39.1667
        ]
      },
      "type": "Feature",
      "properties": {
        "hierarchy": [
          "tgn:2197887",
          "tgn:1000001",
          "tgn:7012149",
          "tgn:1002678",
          "tgn:7007252",
          "tgn:7029392"
        ],
        "placetype": [
          "aat:300266640"
        ],
        "id": 2197887,
        "name:xx": "Brown Ridge"
      }
    },
    {
      "geometry": {
        "type": "Point",
        "coordinates": [
          -84.7833,
          36.6333
        ]
      },
      "type": "Feature",
      "properties": {
        "hierarchy": [
          "tgn:2197888",
          "tgn:1000001",
          "tgn:7012149",
          "tgn:2000850",
          "tgn:7007255",
          "tgn:7029392"
        ],
        "placetype": [
          "aat:300266640"
        ],
        "id": 2197888,
        "name:xx": "Brown Ridge"
      }
    },
    {
      "geometry": {
        "type": "Point",
        "coordinates": [
          -85.6,
          36.7
        ]
      },
      "type": "Feature",
      "properties": {
        "hierarchy": [
          "tgn:2197889",
          "tgn:1000001",
          "tgn:7012149",
          "tgn:2000829",
          "tgn:7007255",
          "tgn:7029392"
        ],
        "placetype": [
          "aat:300266640"
        ],
        "id": 2197889,
        "name:xx": "Brown Ridge"
      }
    }
  ]
}
