{
  "geometry": {
    "type": "Point",
    "coordinates": [
      79.354888,
      27.14389
    ]
  },
  "type": "Feature",
  "properties": {
    "hierarchy": [
      "tgn:7561509",
      "tgn:1000004",
      "tgn:7000198",
      "tgn:7016722",
      "tgn:7029392"
    ],
    "placetype": [
      "aat:300008347"
    ],
    "name:en": "Nagla Kalyānpur",
    "id": 7561509
  }
}
