{
  "geometry": {
    "type": "Point",
    "coordinates": [
      -81.7667,
      39.3833
    ]
  },
  "type": "Feature",
  "properties": {
    "hierarchy": [
      "tgn:2322549",
      "tgn:1000001",
      "tgn:7012149",
      "tgn:2001622",
      "tgn:7007706",
      "tgn:7029392"
    ],
    "placetype": [
      "aat:300008706"
    ],
    "id": 2322549,
    "name:xx": "Falls Creek"
  }
}
