{
  "geometry": {
    "type": "Point",
    "coordinates": [
      -87.7833,
      35.2333
    ]
  },
  "type": "Feature",
  "properties": {
    "hierarchy": [
      "tgn:2525781",
      "tgn:1000001",
      "tgn:7012149",
      "tgn:2001927",
      "tgn:7007825",
      "tgn:7029392"
    ],
    "placetype": [
      "aat:300008699"
    ],
    "id": 2525781,
    "name:xx": "Moser Branch"
  }
}
