{
  "geometry": {
    "type": "Point",
    "coordinates": [
      -80.95,
      33.7833
    ]
  },
  "type": "Feature",
  "properties": {
    "hierarchy": [
      "tgn:2643674",
      "tgn:1000001",
      "tgn:2001733",
      "tgn:7012149",
      "tgn:7007712",
      "tgn:7029392"
    ],
    "placetype": [
      "aat:300008347"
    ],
    "id": 2643674,
    "name:xx": "Sandy Run"
  }
}
