{
  "geometry": {
    "type": "Point",
    "coordinates": [
      -80.1833,
      41.2667
    ]
  },
  "type": "Feature",
  "properties": {
    "hierarchy": [
      "tgn:2480096",
      "tgn:1000001",
      "tgn:7012149",
      "tgn:1002659",
      "tgn:7007710",
      "tgn:7029392"
    ],
    "placetype": [
      "aat:300006191"
    ],
    "id": 2480096,
    "name:xx": "Lake Latonka"
  }
}
