{
  "geometry": {
    "type": "Point",
    "coordinates": [
      -70.8667,
      44.05
    ]
  },
  "type": "Feature",
  "properties": {
    "hierarchy": [
      "tgn:2223683",
      "tgn:1000001",
      "tgn:7012149",
      "tgn:2000926",
      "tgn:7007515",
      "tgn:7029392"
    ],
    "placetype": [
      "aat:300008798"
    ],
    "id": 2223683,
    "name:xx": "Carter Hill"
  }
}
