{
  "geometry": {
    "type": "Point",
    "coordinates": [
      75.658312,
      25.9108
    ]
  },
  "type": "Feature",
  "properties": {
    "hierarchy": [
      "tgn:7570194",
      "tgn:1000004",
      "tgn:7000198",
      "tgn:7016788",
      "tgn:7029392"
    ],
    "placetype": [
      "aat:300008347"
    ],
    "name:en": "Muglāni",
    "id": 7570194
  }
}
