{
  "geometry": {
    "type": "Point",
    "coordinates": [
      -119.9333,
      43.7667
    ]
  },
  "type": "Feature",
  "properties": {
    "hierarchy": [
      "tgn:2734956",
      "tgn:1000001",
      "tgn:2001703",
      "tgn:7012149",
      "tgn:7007708",
      "tgn:7029392"
    ],
    "placetype": [
      "aat:300006191"
    ],
    "id": 2734956,
    "name:xx": "Twelvemile Reservoir Number One"
  }
}
