{
  "geometry": {
    "type": "Point",
    "coordinates": [
      -90.1833,
      43.0667
    ]
  },
  "type": "Feature",
  "properties": {
    "hierarchy": [
      "tgn:2406957",
      "tgn:1000001",
      "tgn:7012149",
      "tgn:2002326",
      "tgn:7007922",
      "tgn:7029392"
    ],
    "placetype": [
      "aat:300008761"
    ],
    "id": 2406957,
    "name:xx": "Hunter Hollow"
  }
}
