{
  "geometry": {
    "type": "Point",
    "coordinates": [
      -74.35,
      41.95
    ]
  },
  "type": "Feature",
  "properties": {
    "hierarchy": [
      "tgn:2579487",
      "tgn:1000001",
      "tgn:7012149",
      "tgn:1002961",
      "tgn:7007568",
      "tgn:7029392"
    ],
    "placetype": [
      "aat:300008699"
    ],
    "id": 2579487,
    "name:xx": "Picket Brook"
  }
}
