{
  "geometry": {
    "type": "Point",
    "coordinates": [
      13.6833,
      52.3833
    ]
  },
  "type": "Feature",
  "properties": {
    "hierarchy": [
      "tgn:1136025",
      "tgn:1000003",
      "tgn:7000084",
      "tgn:7029392"
    ],
    "placetype": [
      "aat:300006075"
    ],
    "id": 1136025,
    "name:xx": "Oder-Spree-Kanal"
  }
}
