{
  "geometry": {
    "type": "Point",
    "coordinates": [
      -115.6167,
      45.9667
    ]
  },
  "type": "Feature",
  "properties": {
    "hierarchy": [
      "tgn:2605018",
      "tgn:1000001",
      "tgn:7012149",
      "tgn:2000476",
      "tgn:7007250",
      "tgn:7029392"
    ],
    "placetype": [
      "aat:300266640"
    ],
    "id": 2605018,
    "name:xx": "Radcliff Ridge"
  }
}
