{
  "geometry": {
    "type": "Point",
    "coordinates": [
      -74.65,
      42.65
    ]
  },
  "type": "Feature",
  "properties": {
    "hierarchy": [
      "tgn:7023097",
      "tgn:1000001",
      "tgn:7012149",
      "tgn:7007568",
      "tgn:7029392"
    ],
    "placetype": [
      "aat:300008706"
    ],
    "id": 7023097,
    "name:xx": "Schenevus Creek"
  }
}
