{
  "type": "FeatureCollection",
  "features": [
    {
      "geometry": {
        "type": "Point",
        "coordinates": [
          175.866667,
          -37.216667
        ]
      },
      "type": "Feature",
      "properties": {
        "hierarchy": [
          "tgn:7504440",
          "tgn:1008380",
          "tgn:1000226",
          "tgn:7018426",
          "tgn:1000006",
          "tgn:7029392"
        ],
        "placetype": [
          "aat:300008699"
        ],
        "name:en": "Wairoa Stream",
        "id": 7504440
      }
    },
    {
      "geometry": {
        "type": "Point",
        "coordinates": [
          173.116667,
          -41.35
        ]
      },
      "type": "Feature",
      "properties": {
        "hierarchy": [
          "tgn:7504441",
          "tgn:1009227",
          "tgn:1000226",
          "tgn:7016729",
          "tgn:1000006",
          "tgn:7029392"
        ],
        "placetype": [
          "aat:300008699"
        ],
        "name:en": "Wairoa River",
        "id": 7504441
      }
    },
    {
      "geometry": {
        "type": "Point",
        "coordinates": [
          172.583333,
          -40.616667
        ]
      },
      "type": "Feature",
      "properties": {
        "hierarchy": [
          "tgn:7504442",
          "tgn:1009227",
          "tgn:1000226",
          "tgn:7520095",
          "tgn:1000006",
          "tgn:7029392"
        ],
        "placetype": [
          "aat:300008699"
        ],
        "name:en": "Wairoa River",
        "id": 7504442
      }
    },
    {
      "geometry": {
        "type": "Point",
        "coordinates": [
          177.433333,
          -39.066667
        ]
      },
      "type": "Feature",
      "properties": {
        "hierarchy": [
          "tgn:7504443",
          "tgn:7016670",
          "tgn:1008380",
          "tgn:1000226",
          "tgn:1000006",
          "tgn:7029392"
        ],
        "placetype": [
          "aat:300008699"
        ],
        "name:en": "Wairoa River",
        "id": 7504443
      }
    },
    {
      "geometry": {
        "type": "Point",
        "coordinates": [
          175.083333,
          -36.933333
        ]
      },
      "type": "Feature",
      "properties": {
        "hierarchy": [
          "tgn:7504444",
          "tgn:7000508",
          "tgn:1008380",
          "tgn:1000226",
          "tgn:1000006",
          "tgn:7029392"
        ],
        "placetype": [
          "aat:300008699"
        ],
        "name:en": "Wairoa River",
        "id": 7504444
      }
    },
    {
      "geometry": {
        "type": "Point",
        "coordinates": [
          176.916667,
          -38.85
        ]
      },
      "type": "Feature",
      "properties": {
        "hierarchy": [
          "tgn:7504445",
          "tgn:7016670",
          "tgn:1008380",
          "tgn:1000226",
          "tgn:1000006",
          "tgn:7029392"
        ],
        "placetype": [
          "aat:300008699"
        ],
        "name:en": "Wairoa River",
        "id": 7504445
      }
    },
    {
      "geometry": {
        "type": "Point",
        "coordinates": [
          176.1,
          -37.683333
        ]
      },
      "type": "Feature",
      "properties": {
        "hierarchy": [
          "tgn:7504446",
          "tgn:1008380",
          "tgn:1000226",
          "tgn:7018426",
          "tgn:1000006",
          "tgn:7029392"
        ],
        "placetype": [
          "aat:300008699"
        ],
        "name:en": "Wairoa River",
        "id": 7504446
      }
    },
    {
      "geometry": {
        "type": "Point",
        "coordinates": [
          174.1,
          -35.166667
        ]
      },
      "type": "Feature",
      "properties": {
        "hierarchy": [
          "tgn:7504448",
          "tgn:1008380",
          "tgn:7000507",
          "tgn:1000226",
          "tgn:1000006",
          "tgn:7029392"
        ],
        "placetype": [
          "aat:300132316"
        ],
        "name:en": "Wairoa Bay",
        "id": 7504448
      }
    },
    {
      "geometry": {
        "type": "Point",
        "coordinates": [
          176.366667,
          -38.216667
        ]
      },
      "type": "Feature",
      "properties": {
        "hierarchy": [
          "tgn:7504449",
          "tgn:7000509",
          "tgn:1008380",
          "tgn:1000226",
          "tgn:1000006",
          "tgn:7029392"
        ],
        "placetype": [
          "aat:300387007"
        ],
        "name:en": "Wairoa",
        "id": 7504449
      }
    }
  ]
}
