{
  "geometry": {
    "type": "Point",
    "coordinates": [
      -90.3167,
      35.7167
    ]
  },
  "type": "Feature",
  "properties": {
    "hierarchy": [
      "tgn:2551627",
      "tgn:1000001",
      "tgn:7016172",
      "tgn:2000120",
      "tgn:7012149",
      "tgn:7029392"
    ],
    "placetype": [
      "aat:300006075"
    ],
    "id": 2551627,
    "name:xx": "Number 3, Ditch"
  }
}
