{
  "geometry": {
    "type": "Point",
    "coordinates": [
      -73.6667,
      42.55
    ]
  },
  "type": "Feature",
  "properties": {
    "hierarchy": [
      "tgn:2072177",
      "tgn:1000001",
      "tgn:7012149",
      "tgn:1002821",
      "tgn:7007568",
      "tgn:7029392"
    ],
    "placetype": [
      "aat:300008347"
    ],
    "id": 2072177,
    "name:xx": "Schodack Center"
  }
}
