{
  "geometry": {
    "type": "Point",
    "coordinates": [
      -87.4333,
      34.7833
    ]
  },
  "type": "Feature",
  "properties": {
    "hierarchy": [
      "tgn:2393732",
      "tgn:7002659",
      "tgn:1000001",
      "tgn:2000016",
      "tgn:7012149",
      "tgn:7029392"
    ],
    "placetype": [
      "aat:300386851",
      "aat:300008791"
    ],
    "id": 2393732,
    "name:xx": "Hog Island"
  }
}
