{
  "geometry": {
    "type": "Point",
    "coordinates": [
      -82.2833,
      36.1833
    ]
  },
  "type": "Feature",
  "properties": {
    "hierarchy": [
      "tgn:2199116",
      "tgn:1000001",
      "tgn:7012149",
      "tgn:2001922",
      "tgn:7007825",
      "tgn:7029392"
    ],
    "placetype": [
      "aat:300008761"
    ],
    "id": 2199116,
    "name:xx": "Brummett Hollow"
  }
}
