{
  "geometry": {
    "type": "Point",
    "coordinates": [
      -94.3833,
      40.4167
    ]
  },
  "type": "Feature",
  "properties": {
    "hierarchy": [
      "tgn:2573793",
      "tgn:1000001",
      "tgn:7012149",
      "tgn:7007523",
      "tgn:7029392"
    ],
    "placetype": [
      "aat:300008706"
    ],
    "id": 2573793,
    "name:xx": "Peddler Creek"
  }
}
