{
  "geometry": {
    "type": "Point",
    "coordinates": [
      -110.5833,
      34.5167
    ]
  },
  "type": "Feature",
  "properties": {
    "hierarchy": [
      "tgn:2611271",
      "tgn:1000001",
      "tgn:7006451",
      "tgn:7012149",
      "tgn:2000099",
      "tgn:7029392"
    ],
    "placetype": [
      "aat:300008798"
    ],
    "id": 2611271,
    "name:xx": "Red Knoll"
  }
}
