{
  "geometry": {
    "type": "Point",
    "coordinates": [
      -77.5167,
      41.4167
    ]
  },
  "type": "Feature",
  "properties": {
    "hierarchy": [
      "tgn:2551989",
      "tgn:1000001",
      "tgn:7012149",
      "tgn:1002613",
      "tgn:7007710",
      "tgn:7029392"
    ],
    "placetype": [
      "aat:300008761"
    ],
    "id": 2551989,
    "name:xx": "Number Four Hollow"
  }
}
