{
  "type": "FeatureCollection",
  "features": [
    {
      "geometry": {
        "type": "Point",
        "coordinates": [
          -80,
          81
        ]
      },
      "type": "Feature",
      "properties": {
        "hierarchy": [
          "tgn:1007030",
          "tgn:7005685",
          "tgn:1000001",
          "tgn:1010229",
          "tgn:7024197",
          "tgn:7029392"
        ],
        "placetype": [
          "aat:300008791"
        ],
        "id": 1007030,
        "name:xx": "Ellesmere Island"
      }
    },
    {
      "geometry": {
        "type": "Point",
        "coordinates": [
          -80.1833,
          25.4333
        ]
      },
      "type": "Feature",
      "properties": {
        "hierarchy": [
          "tgn:1007031",
          "tgn:1101415",
          "tgn:1000001",
          "tgn:7012149",
          "tgn:1002314",
          "tgn:7007240",
          "tgn:7029392"
        ],
        "placetype": [
          "aat:300008791"
        ],
        "id": 1007031,
        "name:xx": "Elliott Key"
      }
    },
    {
      "geometry": {
        "type": "Point",
        "coordinates": [
          6.05,
          53.45
        ]
      },
      "type": "Feature",
      "properties": {
        "hierarchy": [
          "tgn:1007037",
          "tgn:7003616",
          "tgn:1000003",
          "tgn:7016845",
          "tgn:7029392"
        ],
        "placetype": [
          "aat:300008791"
        ],
        "name:nl": "Engelsmanplaat",
        "id": 1007037
      }
    },
    {
      "geometry": {
        "type": "Point",
        "coordinates": [
          -43.1167,
          -22.8333
        ]
      },
      "type": "Feature",
      "properties": {
        "hierarchy": [
          "tgn:1007038",
          "tgn:1001942",
          "tgn:1000047",
          "tgn:7002457",
          "tgn:1000002",
          "tgn:7029392"
        ],
        "placetype": [
          "aat:300008791"
        ],
        "id": 1007038,
        "name:xx": "Engenho, Ilha do"
      }
    }
  ]
}
