{
  "geometry": {
    "type": "Point",
    "coordinates": [
      -80.8167,
      33.55
    ]
  },
  "type": "Feature",
  "properties": {
    "hierarchy": [
      "tgn:2452782",
      "tgn:1000001",
      "tgn:7012149",
      "tgn:2001762",
      "tgn:7007712",
      "tgn:7029392"
    ],
    "placetype": [
      "aat:300008706"
    ],
    "id": 2452782,
    "name:xx": "Little Bull Creek"
  }
}
