{
  "geometry": {
    "type": "Point",
    "coordinates": [
      109.7833,
      34.55
    ]
  },
  "type": "Feature",
  "properties": {
    "hierarchy": [
      "tgn:1139121",
      "tgn:1000004",
      "tgn:7002084",
      "tgn:1000111",
      "tgn:7029392"
    ],
    "placetype": [
      "aat:300008347"
    ],
    "id": 1139121,
    "name:xx": "Huaxian"
  }
}
