{
  "geometry": {
    "type": "Point",
    "coordinates": [
      -60.2167,
      -33.3167
    ]
  },
  "type": "Feature",
  "properties": {
    "hierarchy": [
      "tgn:1020021",
      "tgn:1001160",
      "tgn:7006477",
      "tgn:1000002",
      "tgn:7029392"
    ],
    "placetype": [
      "aat:300008347",
      "aat:300008389",
      "aat:300387302",
      "aat:300120599",
      "aat:300387286"
    ],
    "id": 1020021,
    "name:xx": "San Nicolás de los Arroyos"
  }
}
