{
  "geometry": {
    "type": "Point",
    "coordinates": [
      -83.25,
      31.8667
    ]
  },
  "type": "Feature",
  "properties": {
    "hierarchy": [
      "tgn:2212217",
      "tgn:1000001",
      "tgn:7012149",
      "tgn:2000447",
      "tgn:7007248",
      "tgn:7029392"
    ],
    "placetype": [
      "aat:300008905"
    ],
    "id": 2212217,
    "name:xx": "Buzzard Roost"
  }
}
