{
  "geometry": {
    "type": "Point",
    "coordinates": [
      16.2833,
      48.2333
    ]
  },
  "type": "Feature",
  "properties": {
    "hierarchy": [
      "tgn:7003320",
      "tgn:7003321",
      "tgn:7003030",
      "tgn:1000003",
      "tgn:1000062",
      "tgn:7029392"
    ],
    "placetype": [
      "aat:300000874"
    ],
    "id": 7003320,
    "name:xx": "Neuwaldegg"
  }
}
