{
  "geometry": {
    "type": "Point",
    "coordinates": [
      4.1333,
      43.6667
    ]
  },
  "type": "Feature",
  "properties": {
    "hierarchy": [
      "tgn:7017068",
      "tgn:1000003",
      "tgn:7002885",
      "tgn:1000070",
      "tgn:7029392"
    ],
    "placetype": [
      "aat:300008347"
    ],
    "id": 7017068,
    "name:xx": "Lunel"
  }
}
