{
  "geometry": {
    "type": "Point",
    "coordinates": [
      -81.5333,
      36.65
    ]
  },
  "type": "Feature",
  "properties": {
    "hierarchy": [
      "tgn:2509055",
      "tgn:1000001",
      "tgn:7012149",
      "tgn:2002164",
      "tgn:7007919",
      "tgn:7029392"
    ],
    "placetype": [
      "aat:300008706"
    ],
    "id": 2509055,
    "name:xx": "Middle Fork Helton Creek"
  }
}
