{
  "geometry": {
    "type": "Point",
    "coordinates": [
      106.35,
      30.05
    ]
  },
  "type": "Feature",
  "properties": {
    "hierarchy": [
      "tgn:1066670",
      "tgn:1000004",
      "tgn:7002087",
      "tgn:1000111",
      "tgn:7029392"
    ],
    "placetype": [
      "aat:300008347"
    ],
    "id": 1066670,
    "name:xx": "Baishaba"
  }
}
