{
  "type": "FeatureCollection",
  "features": [
    {
      "geometry": {
        "type": "Point",
        "coordinates": [
          10.466667,
          54.15
        ]
      },
      "type": "Feature",
      "properties": {
        "hierarchy": [
          "tgn:7158770",
          "tgn:1000003",
          "tgn:7003688",
          "tgn:7000084",
          "tgn:7029392"
        ],
        "placetype": [
          "aat:300008680"
        ],
        "id": 7158770,
        "name:xx": "Höftsee"
      }
    },
    {
      "geometry": {
        "type": "Point",
        "coordinates": [
          9.4,
          49.8
        ]
      },
      "type": "Feature",
      "properties": {
        "hierarchy": [
          "tgn:7158771",
          "tgn:7003669",
          "tgn:1000003",
          "tgn:7000084",
          "tgn:7029392"
        ],
        "placetype": [
          "aat:300008347"
        ],
        "id": 7158771,
        "name:xx": "Hofthiergarten"
      }
    },
    {
      "geometry": {
        "type": "Point",
        "coordinates": [
          12.533333,
          48.416667
        ]
      },
      "type": "Feature",
      "properties": {
        "hierarchy": [
          "tgn:7158772",
          "tgn:7003669",
          "tgn:1000003",
          "tgn:7000084",
          "tgn:7029392"
        ],
        "placetype": [
          "aat:300008347"
        ],
        "id": 7158772,
        "name:xx": "Hofthambach"
      }
    },
    {
      "geometry": {
        "type": "Point",
        "coordinates": [
          9.1,
          53.733333
        ]
      },
      "type": "Feature",
      "properties": {
        "hierarchy": [
          "tgn:7158773",
          "tgn:1000003",
          "tgn:7003676",
          "tgn:7000084",
          "tgn:7029392"
        ],
        "placetype": [
          "aat:300008347"
        ],
        "id": 7158773,
        "name:xx": "Höftgrube"
      }
    },
    {
      "geometry": {
        "type": "Point",
        "coordinates": [
          8,
          49.05
        ]
      },
      "type": "Feature",
      "properties": {
        "hierarchy": [
          "tgn:7158774",
          "tgn:1000003",
          "tgn:7003682",
          "tgn:7000084",
          "tgn:7029392"
        ],
        "placetype": [
          "aat:300000206"
        ],
        "id": 7158774,
        "name:xx": "Hoftelhof"
      }
    },
    {
      "geometry": {
        "type": "Point",
        "coordinates": [
          8.8,
          53.166667
        ]
      },
      "type": "Feature",
      "properties": {
        "hierarchy": [
          "tgn:7158775",
          "tgn:1000003",
          "tgn:7003676",
          "tgn:7000084",
          "tgn:7029392"
        ],
        "placetype": [
          "aat:300008347"
        ],
        "id": 7158775,
        "name:xx": "Höftdeich"
      }
    },
    {
      "geometry": {
        "type": "Point",
        "coordinates": [
          12,
          53.95
        ]
      },
      "type": "Feature",
      "properties": {
        "hierarchy": [
          "tgn:7158776",
          "tgn:1000003",
          "tgn:7000094",
          "tgn:7000084",
          "tgn:7029392"
        ],
        "placetype": [
          "aat:300008347"
        ],
        "id": 7158776,
        "name:xx": "Hof Tatschow"
      }
    },
    {
      "geometry": {
        "type": "Point",
        "coordinates": [
          8.25,
          53.533333
        ]
      },
      "type": "Feature",
      "properties": {
        "hierarchy": [
          "tgn:7158777",
          "tgn:1000003",
          "tgn:7003676",
          "tgn:7000084",
          "tgn:7029392"
        ],
        "placetype": [
          "aat:300000206"
        ],
        "id": 7158777,
        "name:xx": "Hofswürden"
      }
    },
    {
      "geometry": {
        "type": "Point",
        "coordinates": [
          6.283333,
          50.133333
        ]
      },
      "type": "Feature",
      "properties": {
        "hierarchy": [
          "tgn:7158778",
          "tgn:1000003",
          "tgn:7003682",
          "tgn:7000084",
          "tgn:7029392"
        ],
        "placetype": [
          "aat:300008863"
        ],
        "id": 7158778,
        "name:xx": "Hofswald"
      }
    },
    {
      "geometry": {
        "type": "Point",
        "coordinates": [
          6.283333,
          50.133333
        ]
      },
      "type": "Feature",
      "properties": {
        "hierarchy": [
          "tgn:7158779",
          "tgn:1000003",
          "tgn:7003682",
          "tgn:7000084",
          "tgn:7029392"
        ],
        "placetype": [
          "aat:300000206"
        ],
        "id": 7158779,
        "name:xx": "Hofswald"
      }
    }
  ]
}
