{
  "geometry": {
    "type": "Point",
    "coordinates": [
      -161.9333,
      55.5833
    ]
  },
  "type": "Feature",
  "properties": {
    "hierarchy": [
      "tgn:2692926",
      "tgn:7030515",
      "tgn:7006450",
      "tgn:1000001",
      "tgn:7012149",
      "tgn:7029392"
    ],
    "placetype": [
      "aat:300008706"
    ],
    "id": 2692926,
    "name:xx": "Steelhead Creek"
  }
}
