{
  "geometry": {
    "type": "Point",
    "coordinates": [
      -75.3833,
      38.6667
    ]
  },
  "type": "Feature",
  "properties": {
    "hierarchy": [
      "tgn:2501113",
      "tgn:1002933",
      "tgn:1000001",
      "tgn:7012149",
      "tgn:7007239",
      "tgn:7029392"
    ],
    "placetype": [
      "aat:300008699"
    ],
    "id": 2501113,
    "name:xx": "McGee Ditch"
  }
}
