{
  "geometry": {
    "type": "Point",
    "coordinates": [
      -117.4333,
      34.3333
    ]
  },
  "type": "Feature",
  "properties": {
    "hierarchy": [
      "tgn:1108357",
      "tgn:1000001",
      "tgn:7012149",
      "tgn:7007157",
      "tgn:1002857",
      "tgn:7029392"
    ],
    "placetype": [
      "aat:300259572"
    ],
    "id": 1108357,
    "name:xx": "Cajon Summit"
  }
}
