{
  "type": "FeatureCollection",
  "features": [
    {
      "geometry": {
        "type": "Point",
        "coordinates": [
          -72.0667,
          41.45
        ]
      },
      "type": "Feature",
      "properties": {
        "hierarchy": [
          "tgn:2017080",
          "tgn:1000001",
          "tgn:1002714",
          "tgn:7012149",
          "tgn:7007159",
          "tgn:7029392"
        ],
        "placetype": [
          "aat:300008347",
          "aat:300387210"
        ],
        "id": 2017080,
        "name:xx": "Massapeag"
      }
    },
    {
      "geometry": {
        "type": "Point",
        "coordinates": [
          -71.8833,
          41.9333
        ]
      },
      "type": "Feature",
      "properties": {
        "hierarchy": [
          "tgn:2017081",
          "tgn:1000001",
          "tgn:1003028",
          "tgn:7012149",
          "tgn:7007159",
          "tgn:7029392"
        ],
        "placetype": [
          "aat:300008347"
        ],
        "id": 2017081,
        "name:xx": "Mechanicsville"
      }
    },
    {
      "geometry": {
        "type": "Point",
        "coordinates": [
          -72.5167,
          41.9333
        ]
      },
      "type": "Feature",
      "properties": {
        "hierarchy": [
          "tgn:2017082",
          "tgn:1000001",
          "tgn:1002461",
          "tgn:7012149",
          "tgn:7007159",
          "tgn:7029392"
        ],
        "placetype": [
          "aat:300008347"
        ],
        "id": 2017082,
        "name:xx": "Melrose"
      }
    },
    {
      "geometry": {
        "type": "Point",
        "coordinates": [
          -72.8,
          41.5333
        ]
      },
      "type": "Feature",
      "properties": {
        "hierarchy": [
          "tgn:2017083",
          "tgn:1000001",
          "tgn:1002712",
          "tgn:7012149",
          "tgn:7007159",
          "tgn:7029392"
        ],
        "placetype": [
          "aat:300008347"
        ],
        "id": 2017083,
        "name:xx": "Meriden"
      }
    },
    {
      "geometry": {
        "type": "Point",
        "coordinates": [
          -72.3,
          41.8167
        ]
      },
      "type": "Feature",
      "properties": {
        "hierarchy": [
          "tgn:2017088",
          "tgn:1000001",
          "tgn:1002949",
          "tgn:7012149",
          "tgn:7007159",
          "tgn:7029392"
        ],
        "placetype": [
          "aat:300008347"
        ],
        "id": 2017088,
        "name:xx": "Merrow"
      }
    },
    {
      "geometry": {
        "type": "Point",
        "coordinates": [
          -73.1167,
          41.5167
        ]
      },
      "type": "Feature",
      "properties": {
        "hierarchy": [
          "tgn:2017089",
          "tgn:1000001",
          "tgn:1002712",
          "tgn:7012149",
          "tgn:7007159",
          "tgn:7029392"
        ],
        "placetype": [
          "aat:300008347"
        ],
        "id": 2017089,
        "name:xx": "Middlebury"
      }
    }
  ]
}
