{
  "geometry": {
    "type": "Point",
    "coordinates": [
      -81.7333,
      37.4833
    ]
  },
  "type": "Feature",
  "properties": {
    "hierarchy": [
      "tgn:2386300",
      "tgn:1000001",
      "tgn:7012149",
      "tgn:2002274",
      "tgn:7013961",
      "tgn:7029392"
    ],
    "placetype": [
      "aat:300008798"
    ],
    "id": 2386300,
    "name:xx": "Hensley Knob"
  }
}
