{
  "geometry": {
    "type": "Point",
    "coordinates": [
      -88.8833,
      30.85
    ]
  },
  "type": "Feature",
  "properties": {
    "hierarchy": [
      "tgn:2280585",
      "tgn:1000001",
      "tgn:7012149",
      "tgn:2001151",
      "tgn:7007522",
      "tgn:7029392"
    ],
    "placetype": [
      "aat:300008699"
    ],
    "id": 2280585,
    "name:xx": "Deep Branch"
  }
}
