{
  "type": "FeatureCollection",
  "features": [
    {
      "geometry": {
        "type": "Point",
        "coordinates": [
          -115.6833,
          43.2
        ]
      },
      "type": "Feature",
      "properties": {
        "hierarchy": [
          "tgn:2481270",
          "tgn:1000001",
          "tgn:7012149",
          "tgn:2000471",
          "tgn:7007250",
          "tgn:7029392"
        ],
        "placetype": [
          "aat:300006075"
        ],
        "id": 2481270,
        "name:xx": "Lamberton Canal"
      }
    },
    {
      "geometry": {
        "type": "Point",
        "coordinates": [
          -85.6167,
          43.0167
        ]
      },
      "type": "Feature",
      "properties": {
        "hierarchy": [
          "tgn:2481271",
          "tgn:1000001",
          "tgn:7012149",
          "tgn:1002540",
          "tgn:7007520",
          "tgn:7029392"
        ],
        "placetype": [
          "aat:300008706"
        ],
        "id": 2481271,
        "name:xx": "Lamberton Creek"
      }
    },
    {
      "geometry": {
        "type": "Point",
        "coordinates": [
          -85.6167,
          43.0167
        ]
      },
      "type": "Feature",
      "properties": {
        "hierarchy": [
          "tgn:2481272",
          "tgn:1000001",
          "tgn:7012149",
          "tgn:1002540",
          "tgn:7007520",
          "tgn:7029392"
        ],
        "placetype": [
          "aat:300008680"
        ],
        "id": 2481272,
        "name:xx": "Lamberton Lake"
      }
    },
    {
      "geometry": {
        "type": "Point",
        "coordinates": [
          -93,
          47.4333
        ]
      },
      "type": "Feature",
      "properties": {
        "hierarchy": [
          "tgn:2481273",
          "tgn:1000001",
          "tgn:7012149",
          "tgn:2001067",
          "tgn:7007521",
          "tgn:7029392"
        ],
        "placetype": [
          "aat:300000390"
        ],
        "id": 2481273,
        "name:xx": "Lamberton Mine"
      }
    },
    {
      "geometry": {
        "type": "Point",
        "coordinates": [
          -115.5667,
          43.1833
        ]
      },
      "type": "Feature",
      "properties": {
        "hierarchy": [
          "tgn:2481274",
          "tgn:1000001",
          "tgn:7012149",
          "tgn:2000471",
          "tgn:7007250",
          "tgn:7029392"
        ],
        "placetype": [
          "aat:300006191"
        ],
        "id": 2481274,
        "name:xx": "Lamberton Reservoir"
      }
    },
    {
      "geometry": {
        "type": "Point",
        "coordinates": [
          -91.9,
          34.2167
        ]
      },
      "type": "Feature",
      "properties": {
        "hierarchy": [
          "tgn:2481275",
          "tgn:1000001",
          "tgn:7016172",
          "tgn:7012149",
          "tgn:2000139",
          "tgn:7029392"
        ],
        "placetype": [
          "aat:300008347"
        ],
        "id": 2481275,
        "name:xx": "Lamberts"
      }
    },
    {
      "geometry": {
        "type": "Point",
        "coordinates": [
          -78.55,
          34.35
        ]
      },
      "type": "Feature",
      "properties": {
        "hierarchy": [
          "tgn:2481276",
          "tgn:1000001",
          "tgn:2001485",
          "tgn:7012149",
          "tgn:7007709",
          "tgn:7029392"
        ],
        "placetype": [
          "aat:300008905"
        ],
        "id": 2481276,
        "name:xx": "Lamberts Bay"
      }
    },
    {
      "geometry": {
        "type": "Point",
        "coordinates": [
          -122.95,
          47
        ]
      },
      "type": "Feature",
      "properties": {
        "hierarchy": [
          "tgn:2481277",
          "tgn:1000001",
          "tgn:7012149",
          "tgn:1002942",
          "tgn:7007920",
          "tgn:7029392"
        ],
        "placetype": [
          "aat:300008347"
        ],
        "id": 2481277,
        "name:xx": "Lamberts Corner"
      }
    },
    {
      "geometry": {
        "type": "Point",
        "coordinates": [
          -82.2333,
          32.8
        ]
      },
      "type": "Feature",
      "properties": {
        "hierarchy": [
          "tgn:2481279",
          "tgn:1000001",
          "tgn:2000308",
          "tgn:7012149",
          "tgn:7007248",
          "tgn:7029392"
        ],
        "placetype": [
          "aat:300008680"
        ],
        "id": 2481279,
        "name:xx": "Lamberts Lake"
      }
    }
  ]
}
