{
  "type": "FeatureCollection",
  "features": [
    {
      "geometry": {
        "type": "Point",
        "coordinates": [
          -69.1667,
          44.3833
        ]
      },
      "type": "Feature",
      "properties": {
        "hierarchy": [
          "tgn:2656920",
          "tgn:1000001",
          "tgn:7012149",
          "tgn:2000931",
          "tgn:7007515",
          "tgn:7029392"
        ],
        "placetype": [
          "aat:300008791"
        ],
        "id": 2656920,
        "name:xx": "Sheep Island"
      }
    },
    {
      "geometry": {
        "type": "Point",
        "coordinates": [
          -67.9,
          44.45
        ]
      },
      "type": "Feature",
      "properties": {
        "hierarchy": [
          "tgn:2656921",
          "tgn:1000001",
          "tgn:7012149",
          "tgn:7014589",
          "tgn:7007515",
          "tgn:7029392"
        ],
        "placetype": [
          "aat:300008791"
        ],
        "id": 2656921,
        "name:xx": "Sheep Island"
      }
    },
    {
      "geometry": {
        "type": "Point",
        "coordinates": [
          -71.5833,
          42.4833
        ]
      },
      "type": "Feature",
      "properties": {
        "hierarchy": [
          "tgn:2656922",
          "tgn:1000001",
          "tgn:7012149",
          "tgn:1003038",
          "tgn:7007517",
          "tgn:7029392"
        ],
        "placetype": [
          "aat:300008791"
        ],
        "id": 2656922,
        "name:xx": "Sheep Island"
      }
    },
    {
      "geometry": {
        "type": "Point",
        "coordinates": [
          -70.9167,
          42.2667
        ]
      },
      "type": "Feature",
      "properties": {
        "hierarchy": [
          "tgn:2656923",
          "tgn:1000001",
          "tgn:1002724",
          "tgn:7012149",
          "tgn:7007517",
          "tgn:7029392"
        ],
        "placetype": [
          "aat:300008791"
        ],
        "id": 2656923,
        "name:xx": "Sheep Island"
      }
    },
    {
      "geometry": {
        "type": "Point",
        "coordinates": [
          -96.9333,
          41.45
        ]
      },
      "type": "Feature",
      "properties": {
        "hierarchy": [
          "tgn:2656924",
          "tgn:1000001",
          "tgn:2001334",
          "tgn:7012149",
          "tgn:7007525",
          "tgn:7029392"
        ],
        "placetype": [
          "aat:300008791"
        ],
        "id": 2656924,
        "name:xx": "Sheep Island"
      }
    },
    {
      "geometry": {
        "type": "Point",
        "coordinates": [
          -71.5333,
          43.75
        ]
      },
      "type": "Feature",
      "properties": {
        "hierarchy": [
          "tgn:2656925",
          "tgn:1000001",
          "tgn:2001424",
          "tgn:7012149",
          "tgn:7007564",
          "tgn:7029392"
        ],
        "placetype": [
          "aat:300008791"
        ],
        "id": 2656925,
        "name:xx": "Sheep Island"
      }
    },
    {
      "geometry": {
        "type": "Point",
        "coordinates": [
          -78.2167,
          33.9167
        ]
      },
      "type": "Feature",
      "properties": {
        "hierarchy": [
          "tgn:2656926",
          "tgn:1000001",
          "tgn:2001472",
          "tgn:7012149",
          "tgn:7007709",
          "tgn:7029392"
        ],
        "placetype": [
          "aat:300008791"
        ],
        "id": 2656926,
        "name:xx": "Sheep Island"
      }
    },
    {
      "geometry": {
        "type": "Point",
        "coordinates": [
          -76.5167,
          34.65
        ]
      },
      "type": "Feature",
      "properties": {
        "hierarchy": [
          "tgn:2656927",
          "tgn:1000001",
          "tgn:2001477",
          "tgn:7012149",
          "tgn:7007709",
          "tgn:7029392"
        ],
        "placetype": [
          "aat:300008791"
        ],
        "id": 2656927,
        "name:xx": "Sheep Island"
      }
    },
    {
      "geometry": {
        "type": "Point",
        "coordinates": [
          -80.5667,
          32.3167
        ]
      },
      "type": "Feature",
      "properties": {
        "hierarchy": [
          "tgn:2656928",
          "tgn:2001731",
          "tgn:1000001",
          "tgn:7012149",
          "tgn:7007712",
          "tgn:7029392"
        ],
        "placetype": [
          "aat:300008791"
        ],
        "id": 2656928,
        "name:xx": "Sheep Island"
      }
    },
    {
      "geometry": {
        "type": "Point",
        "coordinates": [
          -76.35,
          37.15
        ]
      },
      "type": "Feature",
      "properties": {
        "hierarchy": [
          "tgn:2656929",
          "tgn:1000001",
          "tgn:7012149",
          "tgn:7022208",
          "tgn:7007919",
          "tgn:7029392"
        ],
        "placetype": [
          "aat:300008791"
        ],
        "id": 2656929,
        "name:xx": "Sheep Island"
      }
    }
  ]
}
