{
  "geometry": {
    "type": "Point",
    "coordinates": [
      113.5167,
      72.8667
    ]
  },
  "type": "Feature",
  "properties": {
    "hierarchy": [
      "tgn:1060681",
      "tgn:1000004",
      "tgn:7011528",
      "tgn:7002435",
      "tgn:7029392"
    ],
    "placetype": [
      "aat:300008347"
    ],
    "id": 1060681,
    "name:xx": "Uryung-Kyaya"
  }
}
