{
  "geometry": {
    "type": "Point",
    "coordinates": [
      -95.9167,
      28.75
    ]
  },
  "type": "Feature",
  "properties": {
    "hierarchy": [
      "tgn:2368606",
      "tgn:1000001",
      "tgn:7012149",
      "tgn:1002646",
      "tgn:7007826",
      "tgn:7029392"
    ],
    "placetype": [
      "aat:300008347"
    ],
    "id": 2368606,
    "name:xx": "Gulf Hill"
  }
}
