{
  "geometry": {
    "type": "Point",
    "coordinates": [
      -109.0667,
      33.5167
    ]
  },
  "type": "Feature",
  "properties": {
    "hierarchy": [
      "tgn:2746410",
      "tgn:1000001",
      "tgn:7006451",
      "tgn:2000095",
      "tgn:7012149",
      "tgn:7029392"
    ],
    "placetype": [
      "aat:300008798"
    ],
    "id": 2746410,
    "name:xx": "W S Mountain"
  }
}
