{
  "geometry": {
    "type": "Point",
    "coordinates": [
      27.8667,
      47.95
    ]
  },
  "type": "Feature",
  "properties": {
    "hierarchy": [
      "tgn:4010564",
      "tgn:7017348",
      "tgn:1000003",
      "tgn:7006656",
      "tgn:7029392"
    ],
    "placetype": [
      "aat:300008347",
      "aat:300008375"
    ],
    "id": 4010564,
    "name:xx": "Sofia"
  }
}
