{
  "geometry": {
    "type": "Point",
    "coordinates": [
      -100.0333,
      29.6833
    ]
  },
  "type": "Feature",
  "properties": {
    "hierarchy": [
      "tgn:2581104",
      "tgn:1000001",
      "tgn:7012149",
      "tgn:2001980",
      "tgn:7007826",
      "tgn:7029392"
    ],
    "placetype": [
      "aat:300008798"
    ],
    "id": 2581104,
    "name:xx": "Pikes Peak"
  }
}
