{
  "geometry": {
    "type": "Point",
    "coordinates": [
      7.15,
      9.4167
    ]
  },
  "type": "Feature",
  "properties": {
    "hierarchy": [
      "tgn:1090397",
      "tgn:7001242",
      "tgn:1000713",
      "tgn:1000168",
      "tgn:7029392"
    ],
    "placetype": [
      "aat:300008347"
    ],
    "id": 1090397,
    "name:xx": "Séguélon"
  }
}
