{
  "geometry": {
    "type": "Point",
    "coordinates": [
      -93.1833,
      30.4833
    ]
  },
  "type": "Feature",
  "properties": {
    "hierarchy": [
      "tgn:2493457",
      "tgn:1000001",
      "tgn:7012149",
      "tgn:7007256",
      "tgn:7029392"
    ],
    "placetype": [
      "aat:300008699"
    ],
    "id": 2493457,
    "name:xx": "Marsh Bayou"
  }
}
