{
  "geometry": {
    "type": "Point",
    "coordinates": [
      86.405078,
      20.62612
    ]
  },
  "type": "Feature",
  "properties": {
    "hierarchy": [
      "tgn:7550191",
      "tgn:1000004",
      "tgn:7000198",
      "tgn:7016694",
      "tgn:7029392"
    ],
    "placetype": [
      "aat:300008699"
    ],
    "name:en": "Birūpa River",
    "id": 7550191
  }
}
