{
  "type": "FeatureCollection",
  "features": [
    {
      "geometry": {
        "type": "Point",
        "coordinates": [
          -83.5833,
          37.25
        ]
      },
      "type": "Feature",
      "properties": {
        "hierarchy": [
          "tgn:2148320",
          "tgn:1000001",
          "tgn:2000782",
          "tgn:7012149",
          "tgn:7007255",
          "tgn:7029392"
        ],
        "placetype": [
          "aat:300008699"
        ],
        "id": 2148320,
        "name:xx": "Barn Branch"
      }
    },
    {
      "geometry": {
        "type": "Point",
        "coordinates": [
          -83.35,
          37.4167
        ]
      },
      "type": "Feature",
      "properties": {
        "hierarchy": [
          "tgn:2148321",
          "tgn:1000001",
          "tgn:2000772",
          "tgn:7012149",
          "tgn:7007255",
          "tgn:7029392"
        ],
        "placetype": [
          "aat:300008699"
        ],
        "id": 2148321,
        "name:xx": "Barn Branch"
      }
    },
    {
      "geometry": {
        "type": "Point",
        "coordinates": [
          -82.5167,
          37.5667
        ]
      },
      "type": "Feature",
      "properties": {
        "hierarchy": [
          "tgn:2148322",
          "tgn:1000001",
          "tgn:7012149",
          "tgn:2000837",
          "tgn:7007255",
          "tgn:7029392"
        ],
        "placetype": [
          "aat:300008699"
        ],
        "id": 2148322,
        "name:xx": "Barn Branch"
      }
    },
    {
      "geometry": {
        "type": "Point",
        "coordinates": [
          -83.3833,
          38.3667
        ]
      },
      "type": "Feature",
      "properties": {
        "hierarchy": [
          "tgn:2148323",
          "tgn:1000001",
          "tgn:7012149",
          "tgn:1002837",
          "tgn:7007255",
          "tgn:7029392"
        ],
        "placetype": [
          "aat:300008699"
        ],
        "id": 2148323,
        "name:xx": "Barn Branch"
      }
    },
    {
      "geometry": {
        "type": "Point",
        "coordinates": [
          -88.8167,
          36.8667
        ]
      },
      "type": "Feature",
      "properties": {
        "hierarchy": [
          "tgn:2148324",
          "tgn:1000001",
          "tgn:2000778",
          "tgn:7012149",
          "tgn:7007255",
          "tgn:7029392"
        ],
        "placetype": [
          "aat:300008699"
        ],
        "id": 2148324,
        "name:xx": "Barn Branch"
      }
    },
    {
      "geometry": {
        "type": "Point",
        "coordinates": [
          -83.75,
          35.4167
        ]
      },
      "type": "Feature",
      "properties": {
        "hierarchy": [
          "tgn:2148326",
          "tgn:1000001",
          "tgn:7012149",
          "tgn:2001497",
          "tgn:7007709",
          "tgn:7029392"
        ],
        "placetype": [
          "aat:300008699"
        ],
        "id": 2148326,
        "name:xx": "Barn Branch"
      }
    },
    {
      "geometry": {
        "type": "Point",
        "coordinates": [
          -82.8667,
          34.9667
        ]
      },
      "type": "Feature",
      "properties": {
        "hierarchy": [
          "tgn:2148327",
          "tgn:1000001",
          "tgn:7012149",
          "tgn:2001763",
          "tgn:7007712",
          "tgn:7029392"
        ],
        "placetype": [
          "aat:300008699"
        ],
        "id": 2148327,
        "name:xx": "Barn Branch"
      }
    },
    {
      "geometry": {
        "type": "Point",
        "coordinates": [
          -82.6,
          37.0667
        ]
      },
      "type": "Feature",
      "properties": {
        "hierarchy": [
          "tgn:2148328",
          "tgn:1000001",
          "tgn:7012149",
          "tgn:2002195",
          "tgn:7007919",
          "tgn:7029392"
        ],
        "placetype": [
          "aat:300008699"
        ],
        "id": 2148328,
        "name:xx": "Barn Branch"
      }
    },
    {
      "geometry": {
        "type": "Point",
        "coordinates": [
          -78.3833,
          38.0333
        ]
      },
      "type": "Feature",
      "properties": {
        "hierarchy": [
          "tgn:2148329",
          "tgn:2002137",
          "tgn:1000001",
          "tgn:7012149",
          "tgn:7007919",
          "tgn:7029392"
        ],
        "placetype": [
          "aat:300008699"
        ],
        "id": 2148329,
        "name:xx": "Barn Branch"
      }
    }
  ]
}
