{
  "geometry": {
    "type": "Point",
    "coordinates": [
      -90.6167,
      42.45
    ]
  },
  "type": "Feature",
  "properties": {
    "hierarchy": [
      "tgn:2414993",
      "tgn:1000001",
      "tgn:7012149",
      "tgn:2000514",
      "tgn:7007251",
      "tgn:7029392"
    ],
    "placetype": [
      "aat:300008791"
    ],
    "id": 2414993,
    "name:xx": "Island 228"
  }
}
