{
  "geometry": {
    "type": "Point",
    "coordinates": [
      -94.2167,
      44.2833
    ]
  },
  "type": "Feature",
  "properties": {
    "hierarchy": [
      "tgn:2541305",
      "tgn:1000001",
      "tgn:7012149",
      "tgn:2001050",
      "tgn:7007521",
      "tgn:7029392"
    ],
    "placetype": [
      "aat:300132316"
    ],
    "id": 2541305,
    "name:xx": "Nicollet Bay"
  }
}
