{
  "geometry": {
    "type": "Point",
    "coordinates": [
      -86.0333,
      43.6167
    ]
  },
  "type": "Feature",
  "properties": {
    "hierarchy": [
      "tgn:2439298",
      "tgn:1000001",
      "tgn:7012149",
      "tgn:7007520",
      "tgn:7029392"
    ],
    "placetype": [
      "aat:300008680"
    ],
    "id": 2439298,
    "name:xx": "Kirchner Lake"
  }
}
