{
  "geometry": {
    "type": "Point",
    "coordinates": [
      30.801306,
      31.452553
    ]
  },
  "type": "Feature",
  "properties": {
    "hierarchy": [
      "tgn:7523398",
      "tgn:7001242",
      "tgn:7016833",
      "tgn:1001335",
      "tgn:7029392"
    ],
    "placetype": [
      "aat:300008791"
    ],
    "name:en": "Bashārūsh, Jazīrat al",
    "id": 7523398
  }
}
