{
  "geometry": {
    "type": "Point",
    "coordinates": [
      -84.6667,
      32.65
    ]
  },
  "type": "Feature",
  "properties": {
    "hierarchy": [
      "tgn:2151991",
      "tgn:1000001",
      "tgn:7012149",
      "tgn:2000421",
      "tgn:7007248",
      "tgn:7029392"
    ],
    "placetype": [
      "aat:300008347"
    ],
    "id": 2151991,
    "name:xx": "Baughville"
  }
}
