{
  "type": "FeatureCollection",
  "features": [
    {
      "geometry": {
        "type": "Point",
        "coordinates": [
          -123.2167,
          42.6833
        ]
      },
      "type": "Feature",
      "properties": {
        "hierarchy": [
          "tgn:1105230",
          "tgn:1000001",
          "tgn:7012149",
          "tgn:7007708",
          "tgn:7029392"
        ],
        "placetype": [
          "aat:300008795"
        ],
        "id": 1105230,
        "name:xx": "King Mountain"
      }
    },
    {
      "geometry": {
        "type": "Point",
        "coordinates": [
          -128.9,
          58.2833
        ]
      },
      "type": "Feature",
      "properties": {
        "hierarchy": [
          "tgn:1105231",
          "tgn:7005735",
          "tgn:7005685",
          "tgn:1000001",
          "tgn:7029392"
        ],
        "placetype": [
          "aat:300008795"
        ],
        "id": 1105231,
        "name:xx": "King Mountain"
      }
    },
    {
      "geometry": {
        "type": "Point",
        "coordinates": [
          -75.8667,
          45.4833
        ]
      },
      "type": "Feature",
      "properties": {
        "hierarchy": [
          "tgn:1105232",
          "tgn:7005685",
          "tgn:1000001",
          "tgn:7005804",
          "tgn:7029392"
        ],
        "placetype": [
          "aat:300008795"
        ],
        "id": 1105232,
        "name:xx": "King, Mont"
      }
    },
    {
      "geometry": {
        "type": "Point",
        "coordinates": [
          138.35,
          38.1
        ]
      },
      "type": "Feature",
      "properties": {
        "hierarchy": [
          "tgn:1105234",
          "tgn:7000895",
          "tgn:1000004",
          "tgn:1001014",
          "tgn:7004244",
          "tgn:1000120",
          "tgn:7029392"
        ],
        "placetype": [
          "aat:300008795"
        ],
        "id": 1105234,
        "name:xx": "Kimpoku-san"
      }
    },
    {
      "geometry": {
        "type": "Point",
        "coordinates": [
          32.8667,
          3.4333
        ]
      },
      "type": "Feature",
      "properties": {
        "hierarchy": [
          "tgn:1105236",
          "tgn:7001242",
          "tgn:1001082",
          "tgn:7441551",
          "tgn:7029392"
        ],
        "placetype": [
          "aat:300008795"
        ],
        "id": 1105236,
        "name:xx": "Kinyeti"
      }
    },
    {
      "geometry": {
        "type": "Point",
        "coordinates": [
          -6.3333,
          53.1833
        ]
      },
      "type": "Feature",
      "properties": {
        "hierarchy": [
          "tgn:1105237",
          "tgn:7001199",
          "tgn:7003495",
          "tgn:1000003",
          "tgn:1000078",
          "tgn:7029392"
        ],
        "placetype": [
          "aat:300008795"
        ],
        "id": 1105237,
        "name:xx": "Kippure"
      }
    },
    {
      "geometry": {
        "type": "Point",
        "coordinates": [
          138.1667,
          36.1
        ]
      },
      "type": "Feature",
      "properties": {
        "hierarchy": [
          "tgn:1105238",
          "tgn:7000895",
          "tgn:1000004",
          "tgn:1001010",
          "tgn:1000120",
          "tgn:7029392"
        ],
        "placetype": [
          "aat:300008795"
        ],
        "id": 1105238,
        "name:xx": "Kirigamine"
      }
    },
    {
      "geometry": {
        "type": "Point",
        "coordinates": [
          80.75,
          6.8
        ]
      },
      "type": "Feature",
      "properties": {
        "hierarchy": [
          "tgn:1105239",
          "tgn:7000410",
          "tgn:1000004",
          "tgn:1000110",
          "tgn:7029392"
        ],
        "placetype": [
          "aat:300008795"
        ],
        "id": 1105239,
        "name:xx": "Kirigalpotta Mountain"
      }
    }
  ]
}
