{
  "geometry": {
    "type": "Point",
    "coordinates": [
      74.776546,
      32.8221
    ]
  },
  "type": "Feature",
  "properties": {
    "hierarchy": [
      "tgn:7592974",
      "tgn:1000004",
      "tgn:7000198",
      "tgn:7000799",
      "tgn:7029392"
    ],
    "placetype": [
      "aat:300008347"
    ],
    "name:en": "Assarwān",
    "id": 7592974
  }
}
