{
  "geometry": {
    "type": "Point",
    "coordinates": [
      -37.1833,
      -7.3667
    ]
  },
  "type": "Feature",
  "properties": {
    "hierarchy": [
      "tgn:1021742",
      "tgn:7005437",
      "tgn:1000047",
      "tgn:7002455",
      "tgn:1000002",
      "tgn:7029392"
    ],
    "placetype": [
      "aat:300008347"
    ],
    "id": 1021742,
    "name:xx": "Itapetim"
  }
}
