{
  "geometry": {
    "type": "Point",
    "coordinates": [
      -77.2333,
      35.8667
    ]
  },
  "type": "Feature",
  "properties": {
    "hierarchy": [
      "tgn:2074816",
      "tgn:1000001",
      "tgn:7012149",
      "tgn:2001517",
      "tgn:7007709",
      "tgn:7029392"
    ],
    "placetype": [
      "aat:300008347"
    ],
    "id": 2074816,
    "name:xx": "Gold Point"
  }
}
