{
  "geometry": {
    "type": "Point",
    "coordinates": [
      -71.5833,
      42.05
    ]
  },
  "type": "Feature",
  "properties": {
    "hierarchy": [
      "tgn:2694972",
      "tgn:1000001",
      "tgn:7012149",
      "tgn:1003038",
      "tgn:7007517",
      "tgn:7029392"
    ],
    "placetype": [
      "aat:300008699"
    ],
    "id": 2694972,
    "name:xx": "Still Corner Brook"
  }
}
