{
  "geometry": {
    "type": "Point",
    "coordinates": [
      -110.8333,
      31.7167
    ]
  },
  "type": "Feature",
  "properties": {
    "hierarchy": [
      "tgn:2137286",
      "tgn:1000001",
      "tgn:7006451",
      "tgn:7012149",
      "tgn:2000102",
      "tgn:7029392"
    ],
    "placetype": [
      "aat:300008697"
    ],
    "id": 2137286,
    "name:xx": "Armour Spring"
  }
}
