{
  "type": "FeatureCollection",
  "features": [
    {
      "geometry": {
        "type": "Point",
        "coordinates": [
          -0.05,
          40.116667
        ]
      },
      "type": "Feature",
      "properties": {
        "hierarchy": [
          "tgn:4011822",
          "tgn:7002815",
          "tgn:1000003",
          "tgn:7002793",
          "tgn:1000095",
          "tgn:7029392"
        ],
        "placetype": [
          "aat:300008347"
        ],
        "id": 4011822,
        "name:xx": "Villafamés"
      }
    },
    {
      "geometry": {
        "type": "Point",
        "coordinates": [
          11.533333,
          45.4
        ]
      },
      "type": "Feature",
      "properties": {
        "hierarchy": [
          "tgn:4011824",
          "tgn:7003008",
          "tgn:1000003",
          "tgn:7002997",
          "tgn:1000080",
          "tgn:7029392"
        ],
        "placetype": [
          "aat:300008347"
        ],
        "id": 4011824,
        "name:xx": "Villaga"
      }
    },
    {
      "geometry": {
        "type": "Point",
        "coordinates": [
          -5.2,
          41.783333
        ]
      },
      "type": "Feature",
      "properties": {
        "hierarchy": [
          "tgn:4011825",
          "tgn:7001158",
          "tgn:7002848",
          "tgn:1000003",
          "tgn:1000095",
          "tgn:7029392"
        ],
        "placetype": [
          "aat:300008347"
        ],
        "id": 4011825,
        "name:xx": "Villagarcía de Campos"
      }
    },
    {
      "geometry": {
        "type": "Point",
        "coordinates": [
          -4.45,
          42.383333
        ]
      },
      "type": "Feature",
      "properties": {
        "hierarchy": [
          "tgn:4011827",
          "tgn:7002832",
          "tgn:7001158",
          "tgn:1000003",
          "tgn:1000095",
          "tgn:7029392"
        ],
        "placetype": [
          "aat:300008347"
        ],
        "id": 4011827,
        "name:xx": "Villaherreros"
      }
    },
    {
      "geometry": {
        "type": "Point",
        "coordinates": [
          -3.266667,
          42.966667
        ]
      },
      "type": "Feature",
      "properties": {
        "hierarchy": [
          "tgn:4011828",
          "tgn:7002810",
          "tgn:7001158",
          "tgn:1000003",
          "tgn:1000095",
          "tgn:7029392"
        ],
        "placetype": [
          "aat:300008347"
        ],
        "id": 4011828,
        "name:xx": "Villaluenga"
      }
    },
    {
      "geometry": {
        "type": "Point",
        "coordinates": [
          -4.116667,
          40.3
        ]
      },
      "type": "Feature",
      "properties": {
        "hierarchy": [
          "tgn:4011829",
          "tgn:7010420",
          "tgn:1000003",
          "tgn:7002795",
          "tgn:1000095",
          "tgn:7029392"
        ],
        "placetype": [
          "aat:300008347"
        ],
        "id": 4011829,
        "name:xx": "Villamanta"
      }
    }
  ]
}
