{
  "geometry": {
    "type": "Point",
    "coordinates": [
      -75.8167,
      40.0667
    ]
  },
  "type": "Feature",
  "properties": {
    "hierarchy": [
      "tgn:2089489",
      "tgn:1000001",
      "tgn:1002266",
      "tgn:7012149",
      "tgn:7007710",
      "tgn:7029392"
    ],
    "placetype": [
      "aat:300008347",
      "aat:300387210"
    ],
    "id": 2089489,
    "name:xx": "Icedale"
  }
}
