{
  "geometry": {
    "type": "Point",
    "coordinates": [
      75.4673,
      28.1934
    ]
  },
  "type": "Feature",
  "properties": {
    "hierarchy": [
      "tgn:7585141",
      "tgn:1000004",
      "tgn:7000198",
      "tgn:7016788",
      "tgn:7029392"
    ],
    "placetype": [
      "aat:300008347"
    ],
    "name:en": "Limri ki Dhāni",
    "id": 7585141
  }
}
