{
  "geometry": {
    "type": "Point",
    "coordinates": [
      -116.8667,
      43.0667
    ]
  },
  "type": "Feature",
  "properties": {
    "hierarchy": [
      "tgn:2473758",
      "tgn:1000001",
      "tgn:7012149",
      "tgn:2000488",
      "tgn:7007250",
      "tgn:7029392"
    ],
    "placetype": [
      "aat:300008697"
    ],
    "id": 2473758,
    "name:xx": "Lower Flat Spring"
  }
}
