{
  "geometry": {
    "type": "Point",
    "coordinates": [
      -80.2167,
      41.5833
    ]
  },
  "type": "Feature",
  "properties": {
    "hierarchy": [
      "tgn:2094220",
      "tgn:1000001",
      "tgn:1002308",
      "tgn:7012149",
      "tgn:7007710",
      "tgn:7029392"
    ],
    "placetype": [
      "aat:300008347",
      "aat:300387210"
    ],
    "id": 2094220,
    "name:xx": "Watson Run"
  }
}
