{
  "geometry": {
    "type": "Point",
    "coordinates": [
      -98.65,
      46.15
    ]
  },
  "type": "Feature",
  "properties": {
    "hierarchy": [
      "tgn:2679342",
      "tgn:1000001",
      "tgn:2001567",
      "tgn:7012149",
      "tgn:7007705",
      "tgn:7029392"
    ],
    "placetype": [
      "aat:300008707"
    ],
    "id": 2679342,
    "name:xx": "South Fork Maple River"
  }
}
