{
  "type": "FeatureCollection",
  "features": [
    {
      "geometry": {
        "type": "Point",
        "coordinates": [
          4.5333,
          52.2667
        ]
      },
      "type": "Feature",
      "properties": {
        "hierarchy": [
          "tgn:1102902",
          "tgn:1000003",
          "tgn:7003632",
          "tgn:7016845",
          "tgn:7029392"
        ],
        "placetype": [
          "aat:300008187"
        ],
        "id": 1102902,
        "name:xx": "Keukenhof"
      }
    },
    {
      "geometry": {
        "type": "Point",
        "coordinates": [
          -0.3,
          51.4667
        ]
      },
      "type": "Feature",
      "properties": {
        "hierarchy": [
          "tgn:1102904",
          "tgn:7002445",
          "tgn:7018928",
          "tgn:1000003",
          "tgn:7008136",
          "tgn:7008591",
          "tgn:7029392"
        ],
        "placetype": [
          "aat:300008187"
        ],
        "id": 1102904,
        "name:xx": "Kew Gardens"
      }
    },
    {
      "geometry": {
        "type": "Point",
        "coordinates": [
          116.8167,
          -31.95
        ]
      },
      "type": "Feature",
      "properties": {
        "hierarchy": [
          "tgn:1102905",
          "tgn:7000490",
          "tgn:1000006",
          "tgn:7001834",
          "tgn:7029392"
        ],
        "placetype": [
          "aat:300008187"
        ],
        "id": 1102905,
        "name:xx": "Kings Park"
      }
    },
    {
      "geometry": {
        "type": "Point",
        "coordinates": [
          -2.85,
          53.45
        ]
      },
      "type": "Feature",
      "properties": {
        "hierarchy": [
          "tgn:1102907",
          "tgn:1004884",
          "tgn:7002445",
          "tgn:1000003",
          "tgn:7029504",
          "tgn:7008591",
          "tgn:7029392"
        ],
        "placetype": [
          "aat:300008187"
        ],
        "id": 1102907,
        "name:xx": "Knowsley Park"
      }
    },
    {
      "geometry": {
        "type": "Point",
        "coordinates": [
          7.0833,
          50.6667
        ]
      },
      "type": "Feature",
      "properties": {
        "hierarchy": [
          "tgn:1102908",
          "tgn:1000003",
          "tgn:7003682",
          "tgn:7000084",
          "tgn:7029392"
        ],
        "placetype": [
          "aat:300008187"
        ],
        "id": 1102908,
        "name:xx": "Kottenforst, Naturpark"
      }
    }
  ]
}
