{
  "geometry": {
    "type": "Point",
    "coordinates": [
      -88.2167,
      42.2667
    ]
  },
  "type": "Feature",
  "properties": {
    "hierarchy": [
      "tgn:2026808",
      "tgn:1000001",
      "tgn:7012149",
      "tgn:7019014",
      "tgn:7007251",
      "tgn:7029392"
    ],
    "placetype": [
      "aat:300008347"
    ],
    "id": 2026808,
    "name:xx": "Burtons Bridge"
  }
}
