{
  "geometry": {
    "type": "Point",
    "coordinates": [
      -86.9833,
      41.5833
    ]
  },
  "type": "Feature",
  "properties": {
    "hierarchy": [
      "tgn:2616523",
      "tgn:1000001",
      "tgn:7012149",
      "tgn:1002798",
      "tgn:7007252",
      "tgn:7029392"
    ],
    "placetype": [
      "aat:300006191"
    ],
    "id": 2616523,
    "name:xx": "Rice Lake"
  }
}
