{
  "geometry": {
    "type": "Point",
    "coordinates": [
      104.7667,
      34.9833
    ]
  },
  "type": "Feature",
  "properties": {
    "hierarchy": [
      "tgn:1139324",
      "tgn:1000004",
      "tgn:1001261",
      "tgn:1000111",
      "tgn:7029392"
    ],
    "placetype": [
      "aat:300008347"
    ],
    "id": 1139324,
    "name:xx": "Longxi"
  }
}
