{
  "geometry": {
    "type": "Point",
    "coordinates": [
      2.9333,
      45.7667
    ]
  },
  "type": "Feature",
  "properties": {
    "hierarchy": [
      "tgn:7017218",
      "tgn:7002871",
      "tgn:1000003",
      "tgn:1000070",
      "tgn:7029392"
    ],
    "placetype": [
      "aat:300008795"
    ],
    "id": 7017218,
    "name:xx": "Puy de Dôme"
  }
}
