{
  "geometry": {
    "type": "Point",
    "coordinates": [
      -112.15,
      46.3333
    ]
  },
  "type": "Feature",
  "properties": {
    "hierarchy": [
      "tgn:2502075",
      "tgn:1000001",
      "tgn:7012149",
      "tgn:2001281",
      "tgn:7007524",
      "tgn:7029392"
    ],
    "placetype": [
      "aat:300008761"
    ],
    "id": 2502075,
    "name:xx": "McKenzie Gulch"
  }
}
