{
  "type": "FeatureCollection",
  "features": [
    {
      "geometry": {
        "type": "Point",
        "coordinates": [
          -120.4,
          39.4167
        ]
      },
      "type": "Feature",
      "properties": {
        "hierarchy": [
          "tgn:1126262",
          "tgn:1000001",
          "tgn:7012149",
          "tgn:7007157",
          "tgn:7029392"
        ],
        "placetype": [
          "aat:300008707"
        ],
        "id": 1126262,
        "name:xx": "Little Truckee"
      }
    },
    {
      "geometry": {
        "type": "Point",
        "coordinates": [
          -92.6,
          48.7667
        ]
      },
      "type": "Feature",
      "properties": {
        "hierarchy": [
          "tgn:1126263",
          "tgn:7005685",
          "tgn:1000001",
          "tgn:7013154",
          "tgn:7029392"
        ],
        "placetype": [
          "aat:300008707"
        ],
        "id": 1126263,
        "name:xx": "Little Turtle"
      }
    },
    {
      "geometry": {
        "type": "Point",
        "coordinates": [
          -89.0833,
          41.6
        ]
      },
      "type": "Feature",
      "properties": {
        "hierarchy": [
          "tgn:1126264",
          "tgn:1000001",
          "tgn:7012149",
          "tgn:1002562",
          "tgn:7007251",
          "tgn:7029392"
        ],
        "placetype": [
          "aat:300008707"
        ],
        "id": 1126264,
        "name:xx": "Little Vermilion"
      }
    },
    {
      "geometry": {
        "type": "Point",
        "coordinates": [
          -98.25,
          34.95
        ]
      },
      "type": "Feature",
      "properties": {
        "hierarchy": [
          "tgn:1126266",
          "tgn:1000001",
          "tgn:7012149",
          "tgn:7007707",
          "tgn:7029392"
        ],
        "placetype": [
          "aat:300008707"
        ],
        "id": 1126266,
        "name:xx": "Little Washita"
      }
    },
    {
      "geometry": {
        "type": "Point",
        "coordinates": [
          -102.15,
          43.1833
        ]
      },
      "type": "Feature",
      "properties": {
        "hierarchy": [
          "tgn:1126267",
          "tgn:1000001",
          "tgn:7012149",
          "tgn:7007713",
          "tgn:7029392"
        ],
        "placetype": [
          "aat:300008707"
        ],
        "id": 1126267,
        "name:xx": "Little White"
      }
    },
    {
      "geometry": {
        "type": "Point",
        "coordinates": [
          -121.6,
          45.9167
        ]
      },
      "type": "Feature",
      "properties": {
        "hierarchy": [
          "tgn:1126268",
          "tgn:1000001",
          "tgn:7012149",
          "tgn:7007920",
          "tgn:7029392"
        ],
        "placetype": [
          "aat:300008707"
        ],
        "id": 1126268,
        "name:xx": "Little White Salmon"
      }
    },
    {
      "geometry": {
        "type": "Point",
        "coordinates": [
          -98.6167,
          33.65
        ]
      },
      "type": "Feature",
      "properties": {
        "hierarchy": [
          "tgn:1126269",
          "tgn:1000001",
          "tgn:7012149",
          "tgn:7007826",
          "tgn:7029392"
        ],
        "placetype": [
          "aat:300008707"
        ],
        "id": 1126269,
        "name:xx": "Little Wichita"
      }
    }
  ]
}
