{
  "geometry": {
    "type": "Point",
    "coordinates": [
      -119.35,
      45.1333
    ]
  },
  "type": "Feature",
  "properties": {
    "hierarchy": [
      "tgn:2494708",
      "tgn:1000001",
      "tgn:7012149",
      "tgn:2001719",
      "tgn:7007708",
      "tgn:7029392"
    ],
    "placetype": [
      "aat:300008697"
    ],
    "id": 2494708,
    "name:xx": "Martin Prairie Spring"
  }
}
