{
  "geometry": {
    "type": "Point",
    "coordinates": [
      -76.6333,
      36.8667
    ]
  },
  "type": "Feature",
  "properties": {
    "hierarchy": [
      "tgn:2616198",
      "tgn:1000001",
      "tgn:7012149",
      "tgn:1002506",
      "tgn:7007919",
      "tgn:7029392"
    ],
    "placetype": [
      "aat:300006191"
    ],
    "id": 2616198,
    "name:xx": "Rhodes, Lake"
  }
}
