{
  "type": "FeatureCollection",
  "features": [
    {
      "geometry": {
        "type": "Point",
        "coordinates": [
          -95.5333,
          32.5167
        ]
      },
      "type": "Feature",
      "properties": {
        "hierarchy": [
          "tgn:2104410",
          "tgn:1000001",
          "tgn:7012149",
          "tgn:1002898",
          "tgn:7007826",
          "tgn:7029392"
        ],
        "placetype": [
          "aat:300008347"
        ],
        "id": 2104410,
        "name:xx": "Garden Valley"
      }
    },
    {
      "geometry": {
        "type": "Point",
        "coordinates": [
          -97.65,
          29.0333
        ]
      },
      "type": "Feature",
      "properties": {
        "hierarchy": [
          "tgn:2104413",
          "tgn:1000001",
          "tgn:7012149",
          "tgn:7021746",
          "tgn:7007826",
          "tgn:7029392"
        ],
        "placetype": [
          "aat:300008347",
          "aat:300387210"
        ],
        "id": 2104413,
        "name:xx": "Garfield"
      }
    },
    {
      "geometry": {
        "type": "Point",
        "coordinates": [
          -97.55,
          30.1833
        ]
      },
      "type": "Feature",
      "properties": {
        "hierarchy": [
          "tgn:2104414",
          "tgn:1000001",
          "tgn:7012149",
          "tgn:1002952",
          "tgn:7007826",
          "tgn:7029392"
        ],
        "placetype": [
          "aat:300008347"
        ],
        "id": 2104414,
        "name:xx": "Garfield"
      }
    },
    {
      "geometry": {
        "type": "Point",
        "coordinates": [
          -94.6667,
          33.5
        ]
      },
      "type": "Feature",
      "properties": {
        "hierarchy": [
          "tgn:2104415",
          "tgn:1000001",
          "tgn:2001944",
          "tgn:7012149",
          "tgn:7007826",
          "tgn:7029392"
        ],
        "placetype": [
          "aat:300008347",
          "aat:300387210"
        ],
        "id": 2104415,
        "name:xx": "Garland"
      }
    },
    {
      "geometry": {
        "type": "Point",
        "coordinates": [
          -96.6333,
          32.9
        ]
      },
      "type": "Feature",
      "properties": {
        "hierarchy": [
          "tgn:2104417",
          "tgn:1000001",
          "tgn:7012149",
          "tgn:1002315",
          "tgn:7007826",
          "tgn:7029392"
        ],
        "placetype": [
          "aat:300008347"
        ],
        "id": 2104417,
        "name:xx": "Garland"
      }
    }
  ]
}
