{
  "geometry": {
    "type": "Point",
    "coordinates": [
      -78.2167,
      39.8333
    ]
  },
  "type": "Feature",
  "properties": {
    "hierarchy": [
      "tgn:2148858",
      "tgn:1000001",
      "tgn:7012149",
      "tgn:1002399",
      "tgn:7007710",
      "tgn:7029392"
    ],
    "placetype": [
      "aat:300008699"
    ],
    "id": 2148858,
    "name:xx": "Barnetts Run"
  }
}
