{
  "geometry": {
    "type": "Point",
    "coordinates": [
      -92.8833,
      40.4833
    ]
  },
  "type": "Feature",
  "properties": {
    "hierarchy": [
      "tgn:2460504",
      "tgn:1000001",
      "tgn:7012149",
      "tgn:2001234",
      "tgn:7007523",
      "tgn:7029392"
    ],
    "placetype": [
      "aat:300008706"
    ],
    "id": 2460504,
    "name:xx": "Little Sandy Creek"
  }
}
