{
  "geometry": {
    "type": "Point",
    "coordinates": [
      79.633333,
      21.25
    ]
  },
  "type": "Feature",
  "properties": {
    "hierarchy": [
      "tgn:7548071",
      "tgn:1000004",
      "tgn:7000198",
      "tgn:1001895",
      "tgn:7029392"
    ],
    "placetype": [
      "aat:300007783"
    ],
    "name:en": "Bhandāra Road",
    "id": 7548071
  }
}
