{
  "geometry": {
    "type": "Point",
    "coordinates": [
      -120.9167,
      38.6667
    ]
  },
  "type": "Feature",
  "properties": {
    "hierarchy": [
      "tgn:2714979",
      "tgn:1000001",
      "tgn:7012149",
      "tgn:1002350",
      "tgn:7007157",
      "tgn:7029392"
    ],
    "placetype": [
      "aat:300008706"
    ],
    "id": 2714979,
    "name:xx": "Tennessee Creek"
  }
}
