{
  "geometry": {
    "type": "Point",
    "coordinates": [
      -104.8333,
      32.9167
    ]
  },
  "type": "Feature",
  "properties": {
    "hierarchy": [
      "tgn:2756415",
      "tgn:1000001",
      "tgn:2001436",
      "tgn:7012149",
      "tgn:7007566",
      "tgn:7029392"
    ],
    "placetype": [
      "aat:300008761"
    ],
    "id": 2756415,
    "name:xx": "Well Canyon"
  }
}
