{
  "geometry": {
    "type": "Point",
    "coordinates": [
      -108.8667,
      38.2333
    ]
  },
  "type": "Feature",
  "properties": {
    "hierarchy": [
      "tgn:2686071",
      "tgn:1000001",
      "tgn:7012149",
      "tgn:2000234",
      "tgn:7007158",
      "tgn:7029392"
    ],
    "placetype": [
      "aat:300008761"
    ],
    "id": 2686071,
    "name:xx": "Spring Canyon"
  }
}
