{
  "geometry": {
    "type": "Point",
    "coordinates": [
      -109.1333,
      38.1833
    ]
  },
  "type": "Feature",
  "properties": {
    "hierarchy": [
      "tgn:2509858",
      "tgn:1000001",
      "tgn:7012149",
      "tgn:2002119",
      "tgn:7007827",
      "tgn:7029392"
    ],
    "placetype": [
      "aat:300008798"
    ],
    "id": 2509858,
    "name:xx": "Middle Mesa"
  }
}
