{
  "geometry": {
    "type": "Point",
    "coordinates": [
      137.6667,
      34.8333
    ]
  },
  "type": "Feature",
  "properties": {
    "hierarchy": [
      "tgn:1080233",
      "tgn:7000895",
      "tgn:1000004",
      "tgn:1001031",
      "tgn:1000120",
      "tgn:7029392"
    ],
    "placetype": [
      "aat:300008347"
    ],
    "id": 1080233,
    "name:xx": "Inasa"
  }
}
