{
  "geometry": {
    "type": "Point",
    "coordinates": [
      -148.0667,
      64.85
    ]
  },
  "type": "Feature",
  "properties": {
    "hierarchy": [
      "tgn:2523445",
      "tgn:7006450",
      "tgn:1000001",
      "tgn:7019674",
      "tgn:7012149",
      "tgn:7029392"
    ],
    "placetype": [
      "aat:300008761"
    ],
    "id": 2523445,
    "name:xx": "Moose Gulch"
  }
}
