{
  "geometry": {
    "type": "Point",
    "coordinates": [
      88.30083,
      23.688317
    ]
  },
  "type": "Feature",
  "properties": {
    "hierarchy": [
      "tgn:1075105",
      "tgn:1000004",
      "tgn:7000198",
      "tgn:1001977",
      "tgn:7029392"
    ],
    "placetype": [
      "aat:300008347"
    ],
    "name:en": "Debagrām",
    "id": 1075105
  }
}
