{
  "geometry": {
    "type": "Point",
    "coordinates": [
      -74.1167,
      42.8333
    ]
  },
  "type": "Feature",
  "properties": {
    "hierarchy": [
      "tgn:2677535",
      "tgn:1000001",
      "tgn:7012149",
      "tgn:7007568",
      "tgn:7029392"
    ],
    "placetype": [
      "aat:300008706"
    ],
    "id": 2677535,
    "name:xx": "South Chuctanunda Creek"
  }
}
