{
  "geometry": {
    "type": "Point",
    "coordinates": [
      -81.6167,
      30.4667
    ]
  },
  "type": "Feature",
  "properties": {
    "hierarchy": [
      "tgn:2778680",
      "tgn:1000001",
      "tgn:2000264",
      "tgn:7012149",
      "tgn:7007240",
      "tgn:7029392"
    ],
    "placetype": [
      "aat:300008905"
    ],
    "id": 2778680,
    "name:xx": "Wolf Bay"
  }
}
