{
  "type": "FeatureCollection",
  "features": [
    {
      "geometry": {
        "type": "Point",
        "coordinates": [
          30.678634,
          30.814156
        ]
      },
      "type": "Feature",
      "properties": {
        "hierarchy": [
          "tgn:7541940",
          "tgn:7001242",
          "tgn:1001075",
          "tgn:7016833",
          "tgn:7029392"
        ],
        "placetype": [
          "aat:300000206"
        ],
        "name:en": "'Izbat 'Abd as Salām Mişbāḩ",
        "id": 7541940
      }
    },
    {
      "geometry": {
        "type": "Point",
        "coordinates": [
          30.60421,
          30.81266
        ]
      },
      "type": "Feature",
      "properties": {
        "hierarchy": [
          "tgn:7541941",
          "tgn:7001242",
          "tgn:1001075",
          "tgn:7016833",
          "tgn:7029392"
        ],
        "placetype": [
          "aat:300000206"
        ],
        "name:en": "'Izbat al 'Azāyim",
        "id": 7541941
      }
    },
    {
      "geometry": {
        "type": "Point",
        "coordinates": [
          30.653606,
          30.818678
        ]
      },
      "type": "Feature",
      "properties": {
        "hierarchy": [
          "tgn:7541942",
          "tgn:7001242",
          "tgn:1001075",
          "tgn:7016833",
          "tgn:7029392"
        ],
        "placetype": [
          "aat:300000206"
        ],
        "name:en": "'Izbat Rāshid Rāshid",
        "id": 7541942
      }
    },
    {
      "geometry": {
        "type": "Point",
        "coordinates": [
          30.648035,
          30.830117
        ]
      },
      "type": "Feature",
      "properties": {
        "hierarchy": [
          "tgn:7541943",
          "tgn:7001242",
          "tgn:1001075",
          "tgn:7016833",
          "tgn:7029392"
        ],
        "placetype": [
          "aat:300000206"
        ],
        "name:en": "'Izbat Qāsim ash Shāyib",
        "id": 7541943
      }
    },
    {
      "geometry": {
        "type": "Point",
        "coordinates": [
          30.649826,
          30.813841
        ]
      },
      "type": "Feature",
      "properties": {
        "hierarchy": [
          "tgn:7541944",
          "tgn:7001242",
          "tgn:1001075",
          "tgn:7016833",
          "tgn:7029392"
        ],
        "placetype": [
          "aat:300008347"
        ],
        "name:en": "Qaryat Aḩmad Ţal'at",
        "id": 7541944
      }
    },
    {
      "geometry": {
        "type": "Point",
        "coordinates": [
          30.505016,
          30.968307
        ]
      },
      "type": "Feature",
      "properties": {
        "hierarchy": [
          "tgn:7541945",
          "tgn:7001242",
          "tgn:1001075",
          "tgn:7016833",
          "tgn:7029392"
        ],
        "placetype": [
          "aat:300000206"
        ],
        "name:en": "'Izbat 'Alī Sa'd",
        "id": 7541945
      }
    },
    {
      "geometry": {
        "type": "Point",
        "coordinates": [
          30.633698,
          30.824275
        ]
      },
      "type": "Feature",
      "properties": {
        "hierarchy": [
          "tgn:7541946",
          "tgn:7001242",
          "tgn:1001075",
          "tgn:7016833",
          "tgn:7029392"
        ],
        "placetype": [
          "aat:300000206"
        ],
        "name:en": "'Izbat 'Abd al Ghaffār",
        "id": 7541946
      }
    },
    {
      "geometry": {
        "type": "Point",
        "coordinates": [
          30.626043,
          30.827952
        ]
      },
      "type": "Feature",
      "properties": {
        "hierarchy": [
          "tgn:7541947",
          "tgn:7001242",
          "tgn:1001075",
          "tgn:7016833",
          "tgn:7029392"
        ],
        "placetype": [
          "aat:300000206"
        ],
        "name:en": "'Izbat 'Ilwānī",
        "id": 7541947
      }
    },
    {
      "geometry": {
        "type": "Point",
        "coordinates": [
          30.623611,
          30.827778
        ]
      },
      "type": "Feature",
      "properties": {
        "hierarchy": [
          "tgn:7541948",
          "tgn:7001242",
          "tgn:1001075",
          "tgn:7016833",
          "tgn:7029392"
        ],
        "placetype": [
          "aat:300000206"
        ],
        "name:en": "Kafr as Saqqā",
        "id": 7541948
      }
    },
    {
      "geometry": {
        "type": "Point",
        "coordinates": [
          30.596324,
          30.969677
        ]
      },
      "type": "Feature",
      "properties": {
        "hierarchy": [
          "tgn:7541949",
          "tgn:7001242",
          "tgn:1001075",
          "tgn:7016833",
          "tgn:7029392"
        ],
        "placetype": [
          "aat:300008347"
        ],
        "name:en": "'Izbat Amīn al Bahiyy",
        "id": 7541949
      }
    }
  ]
}
