{
  "geometry": {
    "type": "Point",
    "coordinates": [
      -84.45,
      44.35
    ]
  },
  "type": "Feature",
  "properties": {
    "hierarchy": [
      "tgn:2637220",
      "tgn:1000001",
      "tgn:7012149",
      "tgn:2000991",
      "tgn:7007520",
      "tgn:7029392"
    ],
    "placetype": [
      "aat:300008680"
    ],
    "id": 2637220,
    "name:xx": "Saint Helen, Lake"
  }
}
