{
  "geometry": {
    "type": "Point",
    "coordinates": [
      -108.1667,
      48.9667
    ]
  },
  "type": "Feature",
  "properties": {
    "hierarchy": [
      "tgn:2214495",
      "tgn:1000001",
      "tgn:7012149",
      "tgn:2001295",
      "tgn:7007524",
      "tgn:7029392"
    ],
    "placetype": [
      "aat:300008347"
    ],
    "id": 2214495,
    "name:xx": "Caldwell"
  }
}
