{
  "geometry": {
    "type": "Point",
    "coordinates": [
      -108.4667,
      34.1833
    ]
  },
  "type": "Feature",
  "properties": {
    "hierarchy": [
      "tgn:2445581",
      "tgn:1000001",
      "tgn:2001429",
      "tgn:7012149",
      "tgn:7007566",
      "tgn:7029392"
    ],
    "placetype": [
      "aat:300008761"
    ],
    "id": 2445581,
    "name:xx": "Leon, Cañon del"
  }
}
