{
  "geometry": {
    "type": "Point",
    "coordinates": [
      -121.6167,
      47.1833
    ]
  },
  "type": "Feature",
  "properties": {
    "hierarchy": [
      "tgn:2531535",
      "tgn:1000001",
      "tgn:7012149",
      "tgn:7018871",
      "tgn:7007920",
      "tgn:7029392"
    ],
    "placetype": [
      "aat:300008697"
    ],
    "id": 2531535,
    "name:xx": "Mule Spring"
  }
}
