{
  "geometry": {
    "type": "Point",
    "coordinates": [
      -89.6333,
      36.7333
    ]
  },
  "type": "Feature",
  "properties": {
    "hierarchy": [
      "tgn:2562338",
      "tgn:1000001",
      "tgn:7012149",
      "tgn:2001222",
      "tgn:7007523",
      "tgn:7029392"
    ],
    "placetype": [
      "aat:300006075"
    ],
    "id": 2562338,
    "name:xx": "Otter Slough Ditch"
  }
}
