{
  "geometry": {
    "type": "Point",
    "coordinates": [
      -88.2667,
      44.7833
    ]
  },
  "type": "Feature",
  "properties": {
    "hierarchy": [
      "tgn:2121328",
      "tgn:1000001",
      "tgn:7012149",
      "tgn:2002354",
      "tgn:7007922",
      "tgn:7029392"
    ],
    "placetype": [
      "aat:300008347"
    ],
    "id": 2121328,
    "name:xx": "Green Valley"
  }
}
