{
  "geometry": {
    "type": "Point",
    "coordinates": [
      -102.0167,
      46.4833
    ]
  },
  "type": "Feature",
  "properties": {
    "hierarchy": [
      "tgn:2134609",
      "tgn:1000001",
      "tgn:2001575",
      "tgn:7012149",
      "tgn:7007705",
      "tgn:7029392"
    ],
    "placetype": [
      "aat:300008798"
    ],
    "id": 2134609,
    "name:xx": "Antelope Butte"
  }
}
