{
  "type": "FeatureCollection",
  "features": [
    {
      "geometry": {
        "type": "Point",
        "coordinates": [
          135.1833,
          34.7167
        ]
      },
      "type": "Feature",
      "properties": {
        "hierarchy": [
          "tgn:1104641",
          "tgn:7016675",
          "tgn:1000004",
          "tgn:7000896",
          "tgn:1000120",
          "tgn:7029392"
        ],
        "placetype": [
          "aat:300008795"
        ],
        "id": 1104641,
        "name:xx": "Futatabi-yama"
      }
    },
    {
      "geometry": {
        "type": "Point",
        "coordinates": [
          119.8,
          45.8667
        ]
      },
      "type": "Feature",
      "properties": {
        "hierarchy": [
          "tgn:1104642",
          "tgn:1000004",
          "tgn:7001838",
          "tgn:1000111",
          "tgn:7029392"
        ],
        "placetype": [
          "aat:300008795"
        ],
        "id": 1104642,
        "name:xx": "Fuyouertuo Shan"
      }
    },
    {
      "geometry": {
        "type": "Point",
        "coordinates": [
          46.35,
          40.2667
        ]
      },
      "type": "Feature",
      "properties": {
        "hierarchy": [
          "tgn:1104643",
          "tgn:7011438",
          "tgn:1000004",
          "tgn:7006646",
          "tgn:7029392"
        ],
        "placetype": [
          "aat:300008795"
        ],
        "id": 1104643,
        "name:xx": "Gyamysh, Gora"
      }
    },
    {
      "geometry": {
        "type": "Point",
        "coordinates": [
          -86.224,
          12.628
        ]
      },
      "type": "Feature",
      "properties": {
        "hierarchy": [
          "tgn:1104646",
          "tgn:1000001",
          "tgn:7005562",
          "tgn:7029392"
        ],
        "placetype": [
          "aat:300008795",
          "aat:300266640"
        ],
        "id": 1104646,
        "name:xx": "Cordillera Güisisil"
      }
    },
    {
      "geometry": {
        "type": "Point",
        "coordinates": [
          42.2,
          39.7667
        ]
      },
      "type": "Feature",
      "properties": {
        "hierarchy": [
          "tgn:1104648",
          "tgn:7016655",
          "tgn:1000004",
          "tgn:7018455",
          "tgn:1000144",
          "tgn:7029392"
        ],
        "placetype": [
          "aat:300008795"
        ],
        "id": 1104648,
        "name:xx": "Gümüşkale Tepe"
      }
    },
    {
      "geometry": {
        "type": "Point",
        "coordinates": [
          -121.6667,
          54.5
        ]
      },
      "type": "Feature",
      "properties": {
        "hierarchy": [
          "tgn:1104649",
          "tgn:7005735",
          "tgn:7005685",
          "tgn:1000001",
          "tgn:7029392"
        ],
        "placetype": [
          "aat:300008795"
        ],
        "id": 1104649,
        "name:xx": "Gable Mountain"
      }
    }
  ]
}
