{
  "geometry": {
    "type": "Point",
    "coordinates": [
      -108.9833,
      43.7833
    ]
  },
  "type": "Feature",
  "properties": {
    "hierarchy": [
      "tgn:2181357",
      "tgn:1000001",
      "tgn:7012149",
      "tgn:2002373",
      "tgn:7007923",
      "tgn:7029392"
    ],
    "placetype": [
      "aat:300008706"
    ],
    "id": 2181357,
    "name:xx": "Blue Creek"
  }
}
