{
  "type": "FeatureCollection",
  "features": [
    {
      "geometry": {
        "type": "Point",
        "coordinates": [
          -119.9833,
          39.2667
        ]
      },
      "type": "Feature",
      "properties": {
        "hierarchy": [
          "tgn:2327190",
          "tgn:1000001",
          "tgn:7012149",
          "tgn:1002999",
          "tgn:7007526",
          "tgn:7029392"
        ],
        "placetype": [
          "aat:300008706"
        ],
        "id": 2327190,
        "name:xx": "First Creek"
      }
    },
    {
      "geometry": {
        "type": "Point",
        "coordinates": [
          -114.6667,
          39.55
        ]
      },
      "type": "Feature",
      "properties": {
        "hierarchy": [
          "tgn:2327191",
          "tgn:1000001",
          "tgn:7012149",
          "tgn:2001420",
          "tgn:7007526",
          "tgn:7029392"
        ],
        "placetype": [
          "aat:300008706"
        ],
        "id": 2327191,
        "name:xx": "First Creek"
      }
    },
    {
      "geometry": {
        "type": "Point",
        "coordinates": [
          -116.9833,
          41.3333
        ]
      },
      "type": "Feature",
      "properties": {
        "hierarchy": [
          "tgn:2327192",
          "tgn:1000001",
          "tgn:2001411",
          "tgn:7012149",
          "tgn:7007526",
          "tgn:7029392"
        ],
        "placetype": [
          "aat:300008706"
        ],
        "id": 2327192,
        "name:xx": "First Creek"
      }
    },
    {
      "geometry": {
        "type": "Point",
        "coordinates": [
          -75.35,
          44.0167
        ]
      },
      "type": "Feature",
      "properties": {
        "hierarchy": [
          "tgn:2327193",
          "tgn:1000001",
          "tgn:7012149",
          "tgn:1002593",
          "tgn:7007568",
          "tgn:7029392"
        ],
        "placetype": [
          "aat:300008706"
        ],
        "id": 2327193,
        "name:xx": "First Creek"
      }
    },
    {
      "geometry": {
        "type": "Point",
        "coordinates": [
          -77,
          43.2
        ]
      },
      "type": "Feature",
      "properties": {
        "hierarchy": [
          "tgn:2327194",
          "tgn:1000001",
          "tgn:7012149",
          "tgn:7014600",
          "tgn:7007568",
          "tgn:7029392"
        ],
        "placetype": [
          "aat:300008706"
        ],
        "id": 2327194,
        "name:xx": "First Creek"
      }
    },
    {
      "geometry": {
        "type": "Point",
        "coordinates": [
          -103.3,
          46.5
        ]
      },
      "type": "Feature",
      "properties": {
        "hierarchy": [
          "tgn:2327195",
          "tgn:1000001",
          "tgn:2001600",
          "tgn:7012149",
          "tgn:7007705",
          "tgn:7029392"
        ],
        "placetype": [
          "aat:300008706"
        ],
        "id": 2327195,
        "name:xx": "First Creek"
      }
    },
    {
      "geometry": {
        "type": "Point",
        "coordinates": [
          -84.0333,
          39.2667
        ]
      },
      "type": "Feature",
      "properties": {
        "hierarchy": [
          "tgn:2327196",
          "tgn:1000001",
          "tgn:7012149",
          "tgn:7007706",
          "tgn:7029392"
        ],
        "placetype": [
          "aat:300008706"
        ],
        "id": 2327196,
        "name:xx": "First Creek"
      }
    },
    {
      "geometry": {
        "type": "Point",
        "coordinates": [
          -124.2667,
          43.3667
        ]
      },
      "type": "Feature",
      "properties": {
        "hierarchy": [
          "tgn:2327197",
          "tgn:1000001",
          "tgn:2001702",
          "tgn:7012149",
          "tgn:7007708",
          "tgn:7029392"
        ],
        "placetype": [
          "aat:300008706"
        ],
        "id": 2327197,
        "name:xx": "First Creek"
      }
    },
    {
      "geometry": {
        "type": "Point",
        "coordinates": [
          -122.3833,
          43.7667
        ]
      },
      "type": "Feature",
      "properties": {
        "hierarchy": [
          "tgn:2327198",
          "tgn:1000001",
          "tgn:7012149",
          "tgn:2001716",
          "tgn:7007708",
          "tgn:7029392"
        ],
        "placetype": [
          "aat:300008706"
        ],
        "id": 2327198,
        "name:xx": "First Creek"
      }
    },
    {
      "geometry": {
        "type": "Point",
        "coordinates": [
          -119.8,
          44.4
        ]
      },
      "type": "Feature",
      "properties": {
        "hierarchy": [
          "tgn:2327199",
          "tgn:1000001",
          "tgn:7012149",
          "tgn:2001723",
          "tgn:7007708",
          "tgn:7029392"
        ],
        "placetype": [
          "aat:300008706"
        ],
        "id": 2327199,
        "name:xx": "First Creek"
      }
    }
  ]
}
