{
  "geometry": {
    "type": "Point",
    "coordinates": [
      -112.1833,
      32.9833
    ]
  },
  "type": "Feature",
  "properties": {
    "hierarchy": [
      "tgn:2389126",
      "tgn:1000001",
      "tgn:7006451",
      "tgn:7012149",
      "tgn:2000101",
      "tgn:7029392"
    ],
    "placetype": [
      "aat:300008761"
    ],
    "id": 2389126,
    "name:xx": "Hidden Valley"
  }
}
