{
  "geometry": {
    "type": "Point",
    "coordinates": [
      76.056944,
      12.765
    ]
  },
  "type": "Feature",
  "properties": {
    "hierarchy": [
      "tgn:7547154",
      "tgn:1000004",
      "tgn:7000198",
      "tgn:1001882",
      "tgn:7029392"
    ],
    "placetype": [
      "aat:300008347"
    ],
    "name:en": "Arkalgūd",
    "id": 7547154
  }
}
