{
  "geometry": {
    "type": "Point",
    "coordinates": [
      -109.1333,
      33.9667
    ]
  },
  "type": "Feature",
  "properties": {
    "hierarchy": [
      "tgn:2781793",
      "tgn:2000090",
      "tgn:1000001",
      "tgn:7006451",
      "tgn:7012149",
      "tgn:7029392"
    ],
    "placetype": [
      "aat:300008706"
    ],
    "id": 2781793,
    "name:xx": "Woods Creek"
  }
}
