{
  "type": "FeatureCollection",
  "features": [
    {
      "geometry": {
        "type": "Point",
        "coordinates": [
          -113.3833,
          39.85
        ]
      },
      "type": "Feature",
      "properties": {
        "hierarchy": [
          "tgn:2403270",
          "tgn:1000001",
          "tgn:7012149",
          "tgn:2002112",
          "tgn:7007827",
          "tgn:7029392"
        ],
        "placetype": [
          "aat:300008697"
        ],
        "id": 2403270,
        "name:xx": "House Springs"
      }
    },
    {
      "geometry": {
        "type": "Point",
        "coordinates": [
          -111.9,
          35.55
        ]
      },
      "type": "Feature",
      "properties": {
        "hierarchy": [
          "tgn:2403271",
          "tgn:1000001",
          "tgn:7006451",
          "tgn:2000092",
          "tgn:7012149",
          "tgn:7029392"
        ],
        "placetype": [
          "aat:300006191"
        ],
        "id": 2403271,
        "name:xx": "House Tank"
      }
    },
    {
      "geometry": {
        "type": "Point",
        "coordinates": [
          -110.15,
          32.4
        ]
      },
      "type": "Feature",
      "properties": {
        "hierarchy": [
          "tgn:2403272",
          "tgn:1000001",
          "tgn:7006451",
          "tgn:2000091",
          "tgn:7012149",
          "tgn:7029392"
        ],
        "placetype": [
          "aat:300006191"
        ],
        "id": 2403272,
        "name:xx": "House Tank"
      }
    },
    {
      "geometry": {
        "type": "Point",
        "coordinates": [
          -109.45,
          33.8333
        ]
      },
      "type": "Feature",
      "properties": {
        "hierarchy": [
          "tgn:2403273",
          "tgn:2000090",
          "tgn:1000001",
          "tgn:7006451",
          "tgn:7012149",
          "tgn:7029392"
        ],
        "placetype": [
          "aat:300006191"
        ],
        "id": 2403273,
        "name:xx": "House Tank"
      }
    },
    {
      "geometry": {
        "type": "Point",
        "coordinates": [
          -104.05,
          33.5833
        ]
      },
      "type": "Feature",
      "properties": {
        "hierarchy": [
          "tgn:2403274",
          "tgn:1000001",
          "tgn:2001430",
          "tgn:7012149",
          "tgn:7007566",
          "tgn:7029392"
        ],
        "placetype": [
          "aat:300006191"
        ],
        "id": 2403274,
        "name:xx": "House Tank"
      }
    },
    {
      "geometry": {
        "type": "Point",
        "coordinates": [
          -107.0833,
          34.7
        ]
      },
      "type": "Feature",
      "properties": {
        "hierarchy": [
          "tgn:2403275",
          "tgn:1000001",
          "tgn:7012149",
          "tgn:2001460",
          "tgn:7007566",
          "tgn:7029392"
        ],
        "placetype": [
          "aat:300006191"
        ],
        "id": 2403275,
        "name:xx": "House Tank"
      }
    },
    {
      "geometry": {
        "type": "Point",
        "coordinates": [
          -99.3,
          27.5833
        ]
      },
      "type": "Feature",
      "properties": {
        "hierarchy": [
          "tgn:2403276",
          "tgn:1000001",
          "tgn:7012149",
          "tgn:2002090",
          "tgn:7007826",
          "tgn:7029392"
        ],
        "placetype": [
          "aat:300006191"
        ],
        "id": 2403276,
        "name:xx": "House Tank"
      }
    },
    {
      "geometry": {
        "type": "Point",
        "coordinates": [
          -98.7167,
          28.1667
        ]
      },
      "type": "Feature",
      "properties": {
        "hierarchy": [
          "tgn:2403277",
          "tgn:1000001",
          "tgn:7012149",
          "tgn:2002035",
          "tgn:7007826",
          "tgn:7029392"
        ],
        "placetype": [
          "aat:300006191"
        ],
        "id": 2403277,
        "name:xx": "House Tank"
      }
    },
    {
      "geometry": {
        "type": "Point",
        "coordinates": [
          -105.65,
          31.9
        ]
      },
      "type": "Feature",
      "properties": {
        "hierarchy": [
          "tgn:2403278",
          "tgn:1000001",
          "tgn:7012149",
          "tgn:2002005",
          "tgn:7007826",
          "tgn:7029392"
        ],
        "placetype": [
          "aat:300006191"
        ],
        "id": 2403278,
        "name:xx": "House Tank"
      }
    },
    {
      "geometry": {
        "type": "Point",
        "coordinates": [
          -101.45,
          32.5333
        ]
      },
      "type": "Feature",
      "properties": {
        "hierarchy": [
          "tgn:2403279",
          "tgn:1000001",
          "tgn:2001943",
          "tgn:7012149",
          "tgn:7007826",
          "tgn:7029392"
        ],
        "placetype": [
          "aat:300006191"
        ],
        "id": 2403279,
        "name:xx": "House Tank"
      }
    }
  ]
}
