{
  "geometry": {
    "type": "Point",
    "coordinates": [
      -87.35,
      36.4667
    ]
  },
  "type": "Feature",
  "properties": {
    "hierarchy": [
      "tgn:2623188",
      "tgn:1000001",
      "tgn:7012149",
      "tgn:2001899",
      "tgn:7007825",
      "tgn:7029392"
    ],
    "placetype": [
      "aat:300132348"
    ],
    "id": 2623188,
    "name:xx": "Rock Bars"
  }
}
