{
  "geometry": {
    "type": "Point",
    "coordinates": [
      33.3167,
      35.3333
    ]
  },
  "type": "Feature",
  "properties": {
    "hierarchy": [
      "tgn:1074244",
      "tgn:7000836",
      "tgn:1000004",
      "tgn:1000112",
      "tgn:7029392"
    ],
    "placetype": [
      "aat:300008347",
      "aat:300387222",
      "aat:300008375",
      "aat:300120599"
    ],
    "id": 1074244,
    "name:xx": "Kirínia"
  }
}
