{
  "geometry": {
    "type": "Point",
    "coordinates": [
      -102.7333,
      48.6833
    ]
  },
  "type": "Feature",
  "properties": {
    "hierarchy": [
      "tgn:2367979",
      "tgn:2001563",
      "tgn:1000001",
      "tgn:7012149",
      "tgn:7007705",
      "tgn:7029392"
    ],
    "placetype": [
      "aat:300008680"
    ],
    "id": 2367979,
    "name:xx": "Grubb Lake"
  }
}
