{
  "geometry": {
    "type": "Point",
    "coordinates": [
      5.4167,
      52.75
    ]
  },
  "type": "Feature",
  "properties": {
    "hierarchy": [
      "tgn:7007041",
      "tgn:1000003",
      "tgn:7016845",
      "tgn:7029392"
    ],
    "placetype": [
      "aat:300008694"
    ],
    "id": 7007041,
    "name:xx": "IJsselmeer"
  }
}
