{
  "geometry": {
    "type": "Point",
    "coordinates": [
      -74.3333,
      39.4667
    ]
  },
  "type": "Feature",
  "properties": {
    "hierarchy": [
      "tgn:2639051",
      "tgn:1002157",
      "tgn:1000001",
      "tgn:7012149",
      "tgn:7007565",
      "tgn:7029392"
    ],
    "placetype": [
      "aat:300008791"
    ],
    "id": 2639051,
    "name:xx": "Salt Island"
  }
}
