{
  "geometry": {
    "type": "Point",
    "coordinates": [
      -109.7833,
      33.4833
    ]
  },
  "type": "Feature",
  "properties": {
    "hierarchy": [
      "tgn:2177329",
      "tgn:2000090",
      "tgn:1000001",
      "tgn:7006451",
      "tgn:7012149",
      "tgn:7029392"
    ],
    "placetype": [
      "aat:300006191"
    ],
    "id": 2177329,
    "name:xx": "Black River Number Two Tank"
  }
}
