{
  "geometry": {
    "type": "Point",
    "coordinates": [
      -77.6333,
      40.7167
    ]
  },
  "type": "Feature",
  "properties": {
    "hierarchy": [
      "tgn:2458146",
      "tgn:1000001",
      "tgn:7012149",
      "tgn:1002669",
      "tgn:7007710",
      "tgn:7029392"
    ],
    "placetype": [
      "aat:300008798"
    ],
    "id": 2458146,
    "name:xx": "Little Mountain"
  }
}
