{
  "geometry": {
    "type": "Point",
    "coordinates": [
      -66.35,
      -17.5667
    ]
  },
  "type": "Feature",
  "properties": {
    "hierarchy": [
      "tgn:1020323",
      "tgn:1000572",
      "tgn:1000046",
      "tgn:1000002",
      "tgn:7029392"
    ],
    "placetype": [
      "aat:300008347"
    ],
    "id": 1020323,
    "name:xx": "Itapaya"
  }
}
