{
  "geometry": {
    "type": "Point",
    "coordinates": [
      -109.7167,
      45.15
    ]
  },
  "type": "Feature",
  "properties": {
    "hierarchy": [
      "tgn:2473206",
      "tgn:1000001",
      "tgn:2001264",
      "tgn:7012149",
      "tgn:7007524",
      "tgn:7029392"
    ],
    "placetype": [
      "aat:300008680"
    ],
    "id": 2473206,
    "name:xx": "Lower Arch Lake"
  }
}
