{
  "geometry": {
    "type": "Point",
    "coordinates": [
      26.8833,
      56.7333
    ]
  },
  "type": "Feature",
  "properties": {
    "hierarchy": [
      "tgn:1126728",
      "tgn:1000003",
      "tgn:7006541",
      "tgn:7029392"
    ],
    "placetype": [
      "aat:300008707"
    ],
    "id": 1126728,
    "name:xx": "Malta"
  }
}
