{
  "geometry": {
    "type": "Point",
    "coordinates": [
      -83.4333,
      36.95
    ]
  },
  "type": "Feature",
  "properties": {
    "hierarchy": [
      "tgn:2201927",
      "tgn:1000001",
      "tgn:7012149",
      "tgn:2000811",
      "tgn:7007255",
      "tgn:7029392"
    ],
    "placetype": [
      "aat:300008761"
    ],
    "id": 2201927,
    "name:xx": "Buck Hollow"
  }
}
