{
  "geometry": {
    "type": "Point",
    "coordinates": [
      -122.9167,
      38.05
    ]
  },
  "type": "Feature",
  "properties": {
    "hierarchy": [
      "tgn:2396748",
      "tgn:1000001",
      "tgn:7012149",
      "tgn:7007157",
      "tgn:7014005",
      "tgn:7029392"
    ],
    "placetype": [
      "aat:300132316"
    ],
    "id": 2396748,
    "name:xx": "Home Bay"
  }
}
