{
  "geometry": {
    "type": "Point",
    "coordinates": [
      -84.8333,
      38.45
    ]
  },
  "type": "Feature",
  "properties": {
    "hierarchy": [
      "tgn:2189596",
      "tgn:1000001",
      "tgn:7012149",
      "tgn:1002763",
      "tgn:7007255",
      "tgn:7029392"
    ],
    "placetype": [
      "aat:300008699"
    ],
    "id": 2189596,
    "name:xx": "Bowen Branch"
  }
}
