{
  "geometry": {
    "type": "Point",
    "coordinates": [
      17.2833,
      69.2333
    ]
  },
  "type": "Feature",
  "properties": {
    "hierarchy": [
      "tgn:1101358",
      "tgn:7003655",
      "tgn:1000003",
      "tgn:1000088",
      "tgn:7029392"
    ],
    "placetype": [
      "aat:300008189"
    ],
    "id": 1101358,
    "name:xx": "Ånderdalen Nasjonalpark"
  }
}
