{
  "type": "FeatureCollection",
  "features": [
    {
      "geometry": {
        "type": "Point",
        "coordinates": [
          -80.8,
          34.1667
        ]
      },
      "type": "Feature",
      "properties": {
        "hierarchy": [
          "tgn:2583970",
          "tgn:1000001",
          "tgn:7012149",
          "tgn:2001752",
          "tgn:7007712",
          "tgn:7029392"
        ],
        "placetype": [
          "aat:300008347"
        ],
        "id": 2583970,
        "name:xx": "Pine Valley"
      }
    },
    {
      "geometry": {
        "type": "Point",
        "coordinates": [
          -81.9333,
          33.5167
        ]
      },
      "type": "Feature",
      "properties": {
        "hierarchy": [
          "tgn:2583971",
          "tgn:2001726",
          "tgn:1000001",
          "tgn:7012149",
          "tgn:7007712",
          "tgn:7029392"
        ],
        "placetype": [
          "aat:300008347"
        ],
        "id": 2583971,
        "name:xx": "Pine Valley"
      }
    },
    {
      "geometry": {
        "type": "Point",
        "coordinates": [
          -113.0667,
          37.35
        ]
      },
      "type": "Feature",
      "properties": {
        "hierarchy": [
          "tgn:2583972",
          "tgn:1000001",
          "tgn:7012149",
          "tgn:2002127",
          "tgn:7007827",
          "tgn:7029392"
        ],
        "placetype": [
          "aat:300008761"
        ],
        "id": 2583972,
        "name:xx": "Pine Valley"
      }
    },
    {
      "geometry": {
        "type": "Point",
        "coordinates": [
          -90.5833,
          43.4
        ]
      },
      "type": "Feature",
      "properties": {
        "hierarchy": [
          "tgn:2583973",
          "tgn:1000001",
          "tgn:7012149",
          "tgn:2002349",
          "tgn:7007922",
          "tgn:7029392"
        ],
        "placetype": [
          "aat:300008761"
        ],
        "id": 2583973,
        "name:xx": "Pine Valley"
      }
    },
    {
      "geometry": {
        "type": "Point",
        "coordinates": [
          -84.2667,
          33.0333
        ]
      },
      "type": "Feature",
      "properties": {
        "hierarchy": [
          "tgn:2583974",
          "tgn:1000001",
          "tgn:7012149",
          "tgn:2000405",
          "tgn:7007248",
          "tgn:7029392"
        ],
        "placetype": [
          "aat:300006191"
        ],
        "id": 2583974,
        "name:xx": "Pine Valley Camp Lake"
      }
    },
    {
      "geometry": {
        "type": "Point",
        "coordinates": [
          -116.5,
          32.9167
        ]
      },
      "type": "Feature",
      "properties": {
        "hierarchy": [
          "tgn:2583975",
          "tgn:1000001",
          "tgn:7012149",
          "tgn:7007157",
          "tgn:1002858",
          "tgn:7029392"
        ],
        "placetype": [
          "aat:300008706"
        ],
        "id": 2583975,
        "name:xx": "Pine Valley Creek"
      }
    },
    {
      "geometry": {
        "type": "Point",
        "coordinates": [
          -91.0167,
          37.1833
        ]
      },
      "type": "Feature",
      "properties": {
        "hierarchy": [
          "tgn:2583976",
          "tgn:1000001",
          "tgn:7012149",
          "tgn:7007523",
          "tgn:7029392"
        ],
        "placetype": [
          "aat:300008706"
        ],
        "id": 2583976,
        "name:xx": "Pine Valley Creek"
      }
    },
    {
      "geometry": {
        "type": "Point",
        "coordinates": [
          -79.5,
          41.9833
        ]
      },
      "type": "Feature",
      "properties": {
        "hierarchy": [
          "tgn:2583977",
          "tgn:1000001",
          "tgn:7012149",
          "tgn:7029392"
        ],
        "placetype": [
          "aat:300008706"
        ],
        "id": 2583977,
        "name:xx": "Pine Valley Creek"
      }
    },
    {
      "geometry": {
        "type": "Point",
        "coordinates": [
          -84.7333,
          33.8333
        ]
      },
      "type": "Feature",
      "properties": {
        "hierarchy": [
          "tgn:2583978",
          "tgn:1000001",
          "tgn:7012149",
          "tgn:2000401",
          "tgn:7007248",
          "tgn:7029392"
        ],
        "placetype": [
          "aat:300008347"
        ],
        "id": 2583978,
        "name:xx": "Pine Valley Estates"
      }
    },
    {
      "geometry": {
        "type": "Point",
        "coordinates": [
          -77.9,
          34.1833
        ]
      },
      "type": "Feature",
      "properties": {
        "hierarchy": [
          "tgn:2583979",
          "tgn:1000001",
          "tgn:7012149",
          "tgn:2001523",
          "tgn:7007709",
          "tgn:7029392"
        ],
        "placetype": [
          "aat:300008347"
        ],
        "id": 2583979,
        "name:xx": "Pine Valley Estates"
      }
    }
  ]
}
