{
  "geometry": {
    "type": "Point",
    "coordinates": [
      -116.5167,
      43.3167
    ]
  },
  "type": "Feature",
  "properties": {
    "hierarchy": [
      "tgn:2703655",
      "tgn:1000001",
      "tgn:7012149",
      "tgn:7007250",
      "tgn:7029392"
    ],
    "placetype": [
      "aat:300006075"
    ],
    "id": 2703655,
    "name:xx": "Summitt Lateral"
  }
}
