{
  "geometry": {
    "type": "Point",
    "coordinates": [
      -71.6833,
      42.5167
    ]
  },
  "type": "Feature",
  "properties": {
    "hierarchy": [
      "tgn:2461091",
      "tgn:1000001",
      "tgn:7012149",
      "tgn:1003038",
      "tgn:7007517",
      "tgn:7029392"
    ],
    "placetype": [
      "aat:300008680"
    ],
    "id": 2461091,
    "name:xx": "Little Spectacle Pond"
  }
}
