{
  "geometry": {
    "type": "Point",
    "coordinates": [
      31.306502,
      30.116198
    ]
  },
  "type": "Feature",
  "properties": {
    "hierarchy": [
      "tgn:7526623",
      "tgn:7001242",
      "tgn:7016833",
      "tgn:1001091",
      "tgn:7029392"
    ],
    "placetype": [
      "aat:300004792"
    ],
    "id": 7526623,
    "name:xx": "Shirkat Awt큰b카s훮t ad Dilt훮"
  }
}
