{
  "geometry": {
    "type": "Point",
    "coordinates": [
      127.5833,
      -17.8667
    ]
  },
  "type": "Feature",
  "properties": {
    "hierarchy": [
      "tgn:1098205",
      "tgn:7000490",
      "tgn:1000006",
      "tgn:7001834",
      "tgn:7029392"
    ],
    "placetype": [
      "aat:300008347"
    ],
    "id": 1098205,
    "name:xx": "Springvale"
  }
}
