{
  "geometry": {
    "type": "Point",
    "coordinates": [
      -84.25,
      40.4333
    ]
  },
  "type": "Feature",
  "properties": {
    "hierarchy": [
      "tgn:2080210",
      "tgn:1000001",
      "tgn:7012149",
      "tgn:1002889",
      "tgn:7007706",
      "tgn:7029392"
    ],
    "placetype": [
      "aat:300008347"
    ],
    "id": 2080210,
    "name:xx": "Kettlersville"
  }
}
