{
  "geometry": {
    "type": "Point",
    "coordinates": [
      127.3167,
      35.5333
    ]
  },
  "type": "Feature",
  "properties": {
    "hierarchy": [
      "tgn:1082322",
      "tgn:1001194",
      "tgn:1000004",
      "tgn:7000299",
      "tgn:7029392"
    ],
    "placetype": [
      "aat:300008347"
    ],
    "id": 1082322,
    "name:xx": "Osu-ri"
  }
}
