{
  "type": "FeatureCollection",
  "features": [
    {
      "geometry": {
        "type": "Point",
        "coordinates": [
          -92.7,
          34.5333
        ]
      },
      "type": "Feature",
      "properties": {
        "hierarchy": [
          "tgn:2440300",
          "tgn:1000001",
          "tgn:7016172",
          "tgn:7012149",
          "tgn:2000167",
          "tgn:7029392"
        ],
        "placetype": [
          "aat:300008347"
        ],
        "id": 2440300,
        "name:xx": "Klondike"
      }
    },
    {
      "geometry": {
        "type": "Point",
        "coordinates": [
          -83.7667,
          34.1833
        ]
      },
      "type": "Feature",
      "properties": {
        "hierarchy": [
          "tgn:2440301",
          "tgn:1000001",
          "tgn:7012149",
          "tgn:2000360",
          "tgn:7007248",
          "tgn:7029392"
        ],
        "placetype": [
          "aat:300008347"
        ],
        "id": 2440301,
        "name:xx": "Klondike"
      }
    },
    {
      "geometry": {
        "type": "Point",
        "coordinates": [
          -96.5167,
          43.3833
        ]
      },
      "type": "Feature",
      "properties": {
        "hierarchy": [
          "tgn:2440302",
          "tgn:1000001",
          "tgn:7012149",
          "tgn:2000620",
          "tgn:7007253",
          "tgn:7029392"
        ],
        "placetype": [
          "aat:300008347"
        ],
        "id": 2440302,
        "name:xx": "Klondike"
      }
    },
    {
      "geometry": {
        "type": "Point",
        "coordinates": [
          -94.5833,
          37.1333
        ]
      },
      "type": "Feature",
      "properties": {
        "hierarchy": [
          "tgn:2440303",
          "tgn:1000001",
          "tgn:7012149",
          "tgn:2001209",
          "tgn:7007523",
          "tgn:7029392"
        ],
        "placetype": [
          "aat:300008347"
        ],
        "id": 2440303,
        "name:xx": "Klondike"
      }
    },
    {
      "geometry": {
        "type": "Point",
        "coordinates": [
          -117.25,
          37.8833
        ]
      },
      "type": "Feature",
      "properties": {
        "hierarchy": [
          "tgn:2440304",
          "tgn:1000001",
          "tgn:2001412",
          "tgn:7012149",
          "tgn:7007526",
          "tgn:7029392"
        ],
        "placetype": [
          "aat:300008347"
        ],
        "id": 2440304,
        "name:xx": "Klondike"
      }
    },
    {
      "geometry": {
        "type": "Point",
        "coordinates": [
          -83.1333,
          40.2667
        ]
      },
      "type": "Feature",
      "properties": {
        "hierarchy": [
          "tgn:2440305",
          "tgn:1000001",
          "tgn:1002329",
          "tgn:7012149",
          "tgn:7007706",
          "tgn:7029392"
        ],
        "placetype": [
          "aat:300008347"
        ],
        "id": 2440305,
        "name:xx": "Klondike"
      }
    },
    {
      "geometry": {
        "type": "Point",
        "coordinates": [
          -120.6,
          45.5667
        ]
      },
      "type": "Feature",
      "properties": {
        "hierarchy": [
          "tgn:2440306",
          "tgn:1000001",
          "tgn:7012149",
          "tgn:1002891",
          "tgn:7007708",
          "tgn:7029392"
        ],
        "placetype": [
          "aat:300008347"
        ],
        "id": 2440306,
        "name:xx": "Klondike"
      }
    },
    {
      "geometry": {
        "type": "Point",
        "coordinates": [
          -77.1667,
          41.65
        ]
      },
      "type": "Feature",
      "properties": {
        "hierarchy": [
          "tgn:2440307",
          "tgn:1000001",
          "tgn:7012149",
          "tgn:1002945",
          "tgn:7007710",
          "tgn:7029392"
        ],
        "placetype": [
          "aat:300008347"
        ],
        "id": 2440307,
        "name:xx": "Klondike"
      }
    },
    {
      "geometry": {
        "type": "Point",
        "coordinates": [
          -79.1167,
          33.6833
        ]
      },
      "type": "Feature",
      "properties": {
        "hierarchy": [
          "tgn:2440308",
          "tgn:1000001",
          "tgn:7012149",
          "tgn:2001750",
          "tgn:7007712",
          "tgn:7029392"
        ],
        "placetype": [
          "aat:300008347"
        ],
        "id": 2440308,
        "name:xx": "Klondike"
      }
    },
    {
      "geometry": {
        "type": "Point",
        "coordinates": [
          -80.2833,
          39.6333
        ]
      },
      "type": "Feature",
      "properties": {
        "hierarchy": [
          "tgn:2440309",
          "tgn:1000001",
          "tgn:7012149",
          "tgn:2002281",
          "tgn:7013961",
          "tgn:7029392"
        ],
        "placetype": [
          "aat:300008347"
        ],
        "id": 2440309,
        "name:xx": "Klondike"
      }
    }
  ]
}
