{
  "geometry": {
    "type": "Point",
    "coordinates": [
      -92.4833,
      48.2833
    ]
  },
  "type": "Feature",
  "properties": {
    "hierarchy": [
      "tgn:2627988",
      "tgn:1000001",
      "tgn:7012149",
      "tgn:2001067",
      "tgn:7007521",
      "tgn:7029392"
    ],
    "placetype": [
      "aat:300132316"
    ],
    "id": 2627988,
    "name:xx": "Rollick Bay"
  }
}
