{
  "geometry": {
    "type": "Point",
    "coordinates": [
      -110.4167,
      32.7333
    ]
  },
  "type": "Feature",
  "properties": {
    "hierarchy": [
      "tgn:2492498",
      "tgn:1000001",
      "tgn:7006451",
      "tgn:7012149",
      "tgn:7029392"
    ],
    "placetype": [
      "aat:300008761"
    ],
    "id": 2492498,
    "name:xx": "Marics Canyon"
  }
}
