{
  "geometry": {
    "type": "Point",
    "coordinates": [
      -109.5833,
      48.0833
    ]
  },
  "type": "Feature",
  "properties": {
    "hierarchy": [
      "tgn:2625063",
      "tgn:1000001",
      "tgn:2001267",
      "tgn:7012149",
      "tgn:7007524",
      "tgn:7029392"
    ],
    "placetype": [
      "aat:300008798"
    ],
    "id": 2625063,
    "name:xx": "Rock, The"
  }
}
