{
  "geometry": {
    "type": "Point",
    "coordinates": [
      8.6667,
      56.3333
    ]
  },
  "type": "Feature",
  "properties": {
    "hierarchy": [
      "tgn:7003437",
      "tgn:1000003",
      "tgn:1000066",
      "tgn:7029392"
    ],
    "placetype": [
      "aat:300387179",
      "aat:300387064",
      "aat:300000771"
    ],
    "id": 7003437,
    "name:xx": "Ringkøbing"
  }
}
