{
  "geometry": {
    "type": "Point",
    "coordinates": [
      -100.0667,
      30.3167
    ]
  },
  "type": "Feature",
  "properties": {
    "hierarchy": [
      "tgn:2441445",
      "tgn:1000001",
      "tgn:7012149",
      "tgn:7007826",
      "tgn:7029392"
    ],
    "placetype": [
      "aat:300008761"
    ],
    "id": 2441445,
    "name:xx": "Knust Draw"
  }
}
