{
  "geometry": {
    "type": "Point",
    "coordinates": [
      -95.2667,
      36.95
    ]
  },
  "type": "Feature",
  "properties": {
    "hierarchy": [
      "tgn:2184985",
      "tgn:1000001",
      "tgn:2001640",
      "tgn:7012149",
      "tgn:7007707",
      "tgn:7029392"
    ],
    "placetype": [
      "aat:300008699"
    ],
    "id": 2184985,
    "name:xx": "Boggs Branch"
  }
}
