{
  "geometry": {
    "type": "Point",
    "coordinates": [
      -99.7333,
      44.8667
    ]
  },
  "type": "Feature",
  "properties": {
    "hierarchy": [
      "tgn:2696497",
      "tgn:1000001",
      "tgn:7012149",
      "tgn:2001829",
      "tgn:7007713",
      "tgn:7029392"
    ],
    "placetype": [
      "aat:300008680"
    ],
    "id": 2696497,
    "name:xx": "Stone Lake"
  }
}
