{
  "geometry": {
    "type": "Point",
    "coordinates": [
      -79.6667,
      39.5833
    ]
  },
  "type": "Feature",
  "properties": {
    "hierarchy": [
      "tgn:2569035",
      "tgn:1000001",
      "tgn:7012149",
      "tgn:2002288",
      "tgn:7013961",
      "tgn:7029392"
    ],
    "placetype": [
      "aat:300008699"
    ],
    "id": 2569035,
    "name:xx": "Parker Run"
  }
}
