{
  "geometry": {
    "type": "Point",
    "coordinates": [
      9.9833,
      55.2333
    ]
  },
  "type": "Feature",
  "properties": {
    "hierarchy": [
      "tgn:1027777",
      "tgn:1000003",
      "tgn:7594009",
      "tgn:1000066",
      "tgn:7029392"
    ],
    "placetype": [
      "aat:300008347"
    ],
    "id": 1027777,
    "name:xx": "Ebberup"
  }
}
