{
  "geometry": {
    "type": "Point",
    "coordinates": [
      -78.3167,
      41.25
    ]
  },
  "type": "Feature",
  "properties": {
    "hierarchy": [
      "tgn:2619956",
      "tgn:1000001",
      "tgn:7012149",
      "tgn:1002352",
      "tgn:7007710",
      "tgn:7029392"
    ],
    "placetype": [
      "aat:300008761"
    ],
    "id": 2619956,
    "name:xx": "Ripper Hollow"
  }
}
