{
  "geometry": {
    "type": "Point",
    "coordinates": [
      -137.6333,
      58.8333
    ]
  },
  "type": "Feature",
  "properties": {
    "hierarchy": [
      "tgn:2321776",
      "tgn:7006450",
      "tgn:1000001",
      "tgn:7012149",
      "tgn:7019760",
      "tgn:7029392"
    ],
    "placetype": [
      "aat:300008835"
    ],
    "id": 2321776,
    "name:xx": "Fairweather Glacier"
  }
}
