{
  "geometry": {
    "type": "Point",
    "coordinates": [
      126.0833,
      8.6333
    ]
  },
  "type": "Feature",
  "properties": {
    "hierarchy": [
      "tgn:1084352",
      "tgn:1000004",
      "tgn:1001557",
      "tgn:1000135",
      "tgn:7029392"
    ],
    "placetype": [
      "aat:300008347"
    ],
    "id": 1084352,
    "name:xx": "Lianga"
  }
}
