{
  "type": "FeatureCollection",
  "features": [
    {
      "geometry": {
        "type": "Point",
        "coordinates": [
          -119.1333,
          42.9167
        ]
      },
      "type": "Feature",
      "properties": {
        "hierarchy": [
          "tgn:2625990",
          "tgn:1000001",
          "tgn:7012149",
          "tgn:2001709",
          "tgn:7007708",
          "tgn:7029392"
        ],
        "placetype": [
          "aat:300008798"
        ],
        "id": 2625990,
        "name:xx": "Rocky Butte"
      }
    },
    {
      "geometry": {
        "type": "Point",
        "coordinates": [
          -117.1667,
          43.2833
        ]
      },
      "type": "Feature",
      "properties": {
        "hierarchy": [
          "tgn:2625991",
          "tgn:1000001",
          "tgn:7012149",
          "tgn:2001718",
          "tgn:7007708",
          "tgn:7029392"
        ],
        "placetype": [
          "aat:300008798"
        ],
        "id": 2625991,
        "name:xx": "Rocky Butte"
      }
    },
    {
      "geometry": {
        "type": "Point",
        "coordinates": [
          -121.5,
          45.25
        ]
      },
      "type": "Feature",
      "properties": {
        "hierarchy": [
          "tgn:2625992",
          "tgn:1000001",
          "tgn:7012149",
          "tgn:1002990",
          "tgn:7007708",
          "tgn:7029392"
        ],
        "placetype": [
          "aat:300008798"
        ],
        "id": 2625992,
        "name:xx": "Rocky Butte"
      }
    },
    {
      "geometry": {
        "type": "Point",
        "coordinates": [
          -122.55,
          45.5333
        ]
      },
      "type": "Feature",
      "properties": {
        "hierarchy": [
          "tgn:2625993",
          "tgn:1000001",
          "tgn:7012149",
          "tgn:1002699",
          "tgn:7007708",
          "tgn:7029392"
        ],
        "placetype": [
          "aat:300008798"
        ],
        "id": 2625993,
        "name:xx": "Rocky Butte"
      }
    },
    {
      "geometry": {
        "type": "Point",
        "coordinates": [
          -120.5833,
          43.0333
        ]
      },
      "type": "Feature",
      "properties": {
        "hierarchy": [
          "tgn:2625994",
          "tgn:1000001",
          "tgn:7012149",
          "tgn:2001715",
          "tgn:7007708",
          "tgn:7029392"
        ],
        "placetype": [
          "aat:300008798"
        ],
        "id": 2625994,
        "name:xx": "Rocky Butte"
      }
    },
    {
      "geometry": {
        "type": "Point",
        "coordinates": [
          -123.3667,
          44
        ]
      },
      "type": "Feature",
      "properties": {
        "hierarchy": [
          "tgn:2625995",
          "tgn:1000001",
          "tgn:7012149",
          "tgn:2001716",
          "tgn:7007708",
          "tgn:7029392"
        ],
        "placetype": [
          "aat:300008798"
        ],
        "id": 2625995,
        "name:xx": "Rocky Butte"
      }
    },
    {
      "geometry": {
        "type": "Point",
        "coordinates": [
          -102.7333,
          45.1833
        ]
      },
      "type": "Feature",
      "properties": {
        "hierarchy": [
          "tgn:2625996",
          "tgn:1000001",
          "tgn:7012149",
          "tgn:2001822",
          "tgn:7007713",
          "tgn:7029392"
        ],
        "placetype": [
          "aat:300008798"
        ],
        "id": 2625996,
        "name:xx": "Rocky Butte"
      }
    },
    {
      "geometry": {
        "type": "Point",
        "coordinates": [
          -117.5833,
          48.4
        ]
      },
      "type": "Feature",
      "properties": {
        "hierarchy": [
          "tgn:2625997",
          "tgn:1000001",
          "tgn:7012149",
          "tgn:2002250",
          "tgn:7007920",
          "tgn:7029392"
        ],
        "placetype": [
          "aat:300008798"
        ],
        "id": 2625997,
        "name:xx": "Rocky Butte"
      }
    },
    {
      "geometry": {
        "type": "Point",
        "coordinates": [
          -105.6,
          43.7333
        ]
      },
      "type": "Feature",
      "properties": {
        "hierarchy": [
          "tgn:2625998",
          "tgn:1000001",
          "tgn:2002367",
          "tgn:7012149",
          "tgn:7007923",
          "tgn:7029392"
        ],
        "placetype": [
          "aat:300008798"
        ],
        "id": 2625998,
        "name:xx": "Rocky Butte"
      }
    },
    {
      "geometry": {
        "type": "Point",
        "coordinates": [
          -105.6167,
          43.7333
        ]
      },
      "type": "Feature",
      "properties": {
        "hierarchy": [
          "tgn:2625999",
          "tgn:1000001",
          "tgn:2002367",
          "tgn:7012149",
          "tgn:7007923",
          "tgn:7029392"
        ],
        "placetype": [
          "aat:300008761"
        ],
        "id": 2625999,
        "name:xx": "Rocky Butte Gulch"
      }
    }
  ]
}
