{
  "type": "FeatureCollection",
  "features": [
    {
      "geometry": {
        "type": "Point",
        "coordinates": [
          -95.233333,
          16.333333
        ]
      },
      "type": "Feature",
      "properties": {
        "hierarchy": [
          "tgn:7438852",
          "tgn:1000001",
          "tgn:7005591",
          "tgn:7005560",
          "tgn:7029392"
        ],
        "placetype": [
          "aat:300007783"
        ],
        "id": 7438852,
        "name:xx": "Estación Tehuantepec"
      }
    },
    {
      "geometry": {
        "type": "Point",
        "coordinates": [
          -103.466667,
          20.083333
        ]
      },
      "type": "Feature",
      "properties": {
        "hierarchy": [
          "tgn:7438853",
          "tgn:7005586",
          "tgn:1000001",
          "tgn:7005560",
          "tgn:7029392"
        ],
        "placetype": [
          "aat:300008347"
        ],
        "id": 7438853,
        "name:xx": "Tehuantepec"
      }
    },
    {
      "geometry": {
        "type": "Point",
        "coordinates": [
          -105.575556,
          20.236667
        ]
      },
      "type": "Feature",
      "properties": {
        "hierarchy": [
          "tgn:7438855",
          "tgn:7005586",
          "tgn:1000001",
          "tgn:7005560",
          "tgn:7029392"
        ],
        "placetype": [
          "aat:300008347"
        ],
        "id": 7438855,
        "name:xx": "Tehualmixtle"
      }
    },
    {
      "geometry": {
        "type": "Point",
        "coordinates": [
          -110.366667,
          30.2
        ]
      },
      "type": "Feature",
      "properties": {
        "hierarchy": [
          "tgn:7438856",
          "tgn:1000001",
          "tgn:1001960",
          "tgn:7005560",
          "tgn:7029392"
        ],
        "placetype": [
          "aat:300008347"
        ],
        "id": 7438856,
        "name:xx": "Tehuachi"
      }
    },
    {
      "geometry": {
        "type": "Point",
        "coordinates": [
          -97.366667,
          18.466667
        ]
      },
      "type": "Feature",
      "properties": {
        "hierarchy": [
          "tgn:7438857",
          "tgn:1000001",
          "tgn:7005592",
          "tgn:7005560",
          "tgn:7029392"
        ],
        "placetype": [
          "aat:300008699"
        ],
        "id": 7438857,
        "name:xx": "Tehuacán, Río"
      }
    },
    {
      "geometry": {
        "type": "Point",
        "coordinates": [
          -107.116667,
          29.9
        ]
      },
      "type": "Feature",
      "properties": {
        "hierarchy": [
          "tgn:7438859",
          "tgn:7005581",
          "tgn:1000001",
          "tgn:7005560",
          "tgn:7029392"
        ],
        "placetype": [
          "aat:300008795"
        ],
        "id": 7438859,
        "name:xx": "Teguasalta, Cerro de"
      }
    }
  ]
}
