{
  "geometry": {
    "type": "Point",
    "coordinates": [
      -89.9667,
      39.4667
    ]
  },
  "type": "Feature",
  "properties": {
    "hierarchy": [
      "tgn:2029117",
      "tgn:1000001",
      "tgn:7012149",
      "tgn:1002620",
      "tgn:7007251",
      "tgn:7029392"
    ],
    "placetype": [
      "aat:300008347"
    ],
    "id": 2029117,
    "name:xx": "Modesto"
  }
}
