{
  "geometry": {
    "type": "Point",
    "coordinates": [
      -116.3833,
      35.8667
    ]
  },
  "type": "Feature",
  "properties": {
    "hierarchy": [
      "tgn:2350915",
      "tgn:1000001",
      "tgn:7012149",
      "tgn:2000183",
      "tgn:7007157",
      "tgn:7029392"
    ],
    "placetype": [
      "aat:300000390"
    ],
    "id": 2350915,
    "name:xx": "Gladstone Mine"
  }
}
