{
  "geometry": {
    "type": "Point",
    "coordinates": [
      -119.3667,
      37.5667
    ]
  },
  "type": "Feature",
  "properties": {
    "hierarchy": [
      "tgn:2325191",
      "tgn:1000001",
      "tgn:7012149",
      "tgn:7007157",
      "tgn:1002621",
      "tgn:7029392"
    ],
    "placetype": [
      "aat:300008680"
    ],
    "id": 2325191,
    "name:xx": "Fernandez Lakes"
  }
}
