{
  "geometry": {
    "type": "Point",
    "coordinates": [
      92.56553,
      22.678053
    ]
  },
  "type": "Feature",
  "properties": {
    "hierarchy": [
      "tgn:7553188",
      "tgn:1000004",
      "tgn:7000198",
      "tgn:1001998",
      "tgn:7029392"
    ],
    "placetype": [
      "aat:300008347"
    ],
    "name:en": "Mullianpui",
    "id": 7553188
  }
}
