{
  "type": "FeatureCollection",
  "features": [
    {
      "geometry": {
        "type": "Point",
        "coordinates": [
          -71.5833,
          42.9
        ]
      },
      "type": "Feature",
      "properties": {
        "hierarchy": [
          "tgn:2274830",
          "tgn:1000001",
          "tgn:1002480",
          "tgn:7012149",
          "tgn:7007564",
          "tgn:7029392"
        ],
        "placetype": [
          "aat:300008680"
        ],
        "id": 2274830,
        "name:xx": "Damon Pond"
      }
    },
    {
      "geometry": {
        "type": "Point",
        "coordinates": [
          -72.0667,
          42.7167
        ]
      },
      "type": "Feature",
      "properties": {
        "hierarchy": [
          "tgn:2274831",
          "tgn:7019618",
          "tgn:1000001",
          "tgn:7012149",
          "tgn:7007564",
          "tgn:7029392"
        ],
        "placetype": [
          "aat:300006191"
        ],
        "id": 2274831,
        "name:xx": "Damon Reservoirs"
      }
    },
    {
      "geometry": {
        "type": "Point",
        "coordinates": [
          -124.2,
          40.25
        ]
      },
      "type": "Feature",
      "properties": {
        "hierarchy": [
          "tgn:2274832",
          "tgn:1000001",
          "tgn:7012149",
          "tgn:2000181",
          "tgn:7007157",
          "tgn:7029392"
        ],
        "placetype": [
          "aat:300266640"
        ],
        "id": 2274832,
        "name:xx": "Damon Ridge"
      }
    },
    {
      "geometry": {
        "type": "Point",
        "coordinates": [
          -87.0667,
          41.5167
        ]
      },
      "type": "Feature",
      "properties": {
        "hierarchy": [
          "tgn:2274833",
          "tgn:1000001",
          "tgn:7012149",
          "tgn:1002798",
          "tgn:7007252",
          "tgn:7029392"
        ],
        "placetype": [
          "aat:300008699"
        ],
        "id": 2274833,
        "name:xx": "Damon Run"
      }
    },
    {
      "geometry": {
        "type": "Point",
        "coordinates": [
          -79.5167,
          41.9
        ]
      },
      "type": "Feature",
      "properties": {
        "hierarchy": [
          "tgn:2274834",
          "tgn:1000001",
          "tgn:7012149",
          "tgn:1002988",
          "tgn:7007710",
          "tgn:7029392"
        ],
        "placetype": [
          "aat:300008699"
        ],
        "id": 2274834,
        "name:xx": "Damon Run"
      }
    },
    {
      "geometry": {
        "type": "Point",
        "coordinates": [
          -116.0167,
          42.0333
        ]
      },
      "type": "Feature",
      "properties": {
        "hierarchy": [
          "tgn:2274835",
          "tgn:1000001",
          "tgn:7012149",
          "tgn:2000488",
          "tgn:7007250",
          "tgn:7029392"
        ],
        "placetype": [
          "aat:300008697"
        ],
        "id": 2274835,
        "name:xx": "Damon Springs"
      }
    },
    {
      "geometry": {
        "type": "Point",
        "coordinates": [
          -116.1,
          42.0667
        ]
      },
      "type": "Feature",
      "properties": {
        "hierarchy": [
          "tgn:2274836",
          "tgn:1000001",
          "tgn:7012149",
          "tgn:2000488",
          "tgn:7007250",
          "tgn:7029392"
        ],
        "placetype": [
          "aat:300008706"
        ],
        "id": 2274836,
        "name:xx": "Damon Trail Creek"
      }
    },
    {
      "geometry": {
        "type": "Point",
        "coordinates": [
          -81.5,
          27.6333
        ]
      },
      "type": "Feature",
      "properties": {
        "hierarchy": [
          "tgn:2274837",
          "tgn:1000001",
          "tgn:1002477",
          "tgn:7012149",
          "tgn:7007240",
          "tgn:7029392"
        ],
        "placetype": [
          "aat:300008680"
        ],
        "id": 2274837,
        "name:xx": "Damon, Lake"
      }
    },
    {
      "geometry": {
        "type": "Point",
        "coordinates": [
          -122.0833,
          37.2
        ]
      },
      "type": "Feature",
      "properties": {
        "hierarchy": [
          "tgn:2274838",
          "tgn:1000001",
          "tgn:7012149",
          "tgn:7007157",
          "tgn:1002869",
          "tgn:7029392"
        ],
        "placetype": [
          "aat:300266640"
        ],
        "id": 2274838,
        "name:xx": "Damond Ridge"
      }
    },
    {
      "geometry": {
        "type": "Point",
        "coordinates": [
          -121.1833,
          41.5167
        ]
      },
      "type": "Feature",
      "properties": {
        "hierarchy": [
          "tgn:2274839",
          "tgn:1000001",
          "tgn:7012149",
          "tgn:7007157",
          "tgn:2000186",
          "tgn:7029392"
        ],
        "placetype": [
          "aat:300008798"
        ],
        "id": 2274839,
        "name:xx": "Damons Butte"
      }
    }
  ]
}
