{
  "type": "FeatureCollection",
  "features": [
    {
      "geometry": {
        "type": "Point",
        "coordinates": [
          4.0167,
          49.7
        ]
      },
      "type": "Feature",
      "properties": {
        "hierarchy": [
          "tgn:1034461",
          "tgn:1000003",
          "tgn:7002890",
          "tgn:1000070",
          "tgn:7029392"
        ],
        "placetype": [
          "aat:300008347"
        ],
        "id": 1034461,
        "name:xx": "Montcornet"
      }
    },
    {
      "geometry": {
        "type": "Point",
        "coordinates": [
          -0.4167,
          45.3
        ]
      },
      "type": "Feature",
      "properties": {
        "hierarchy": [
          "tgn:1034463",
          "tgn:1000003",
          "tgn:7002892",
          "tgn:1000070",
          "tgn:7029392"
        ],
        "placetype": [
          "aat:300008347"
        ],
        "id": 1034463,
        "name:xx": "Montendre"
      }
    },
    {
      "geometry": {
        "type": "Point",
        "coordinates": [
          2.95,
          48.3833
        ]
      },
      "type": "Feature",
      "properties": {
        "hierarchy": [
          "tgn:1034465",
          "tgn:1000003",
          "tgn:7002883",
          "tgn:1000070",
          "tgn:7029392"
        ],
        "placetype": [
          "aat:300008347"
        ],
        "id": 1034465,
        "name:xx": "Montereau-Faut-Yonne"
      }
    },
    {
      "geometry": {
        "type": "Point",
        "coordinates": [
          2.6667,
          48.5833
        ]
      },
      "type": "Feature",
      "properties": {
        "hierarchy": [
          "tgn:1034466",
          "tgn:1000003",
          "tgn:7002883",
          "tgn:1000070",
          "tgn:7029392"
        ],
        "placetype": [
          "aat:300008347"
        ],
        "id": 1034466,
        "name:xx": "Montereau-sur-le-Jard"
      }
    },
    {
      "geometry": {
        "type": "Point",
        "coordinates": [
          2.15,
          48.9167
        ]
      },
      "type": "Feature",
      "properties": {
        "hierarchy": [
          "tgn:1034467",
          "tgn:1000003",
          "tgn:7002883",
          "tgn:1000070",
          "tgn:7029392"
        ],
        "placetype": [
          "aat:300008347"
        ],
        "id": 1034467,
        "name:xx": "Montesson"
      }
    },
    {
      "geometry": {
        "type": "Point",
        "coordinates": [
          5,
          44.0333
        ]
      },
      "type": "Feature",
      "properties": {
        "hierarchy": [
          "tgn:1034468",
          "tgn:1000003",
          "tgn:1000070",
          "tgn:7002895",
          "tgn:7029392"
        ],
        "placetype": [
          "aat:300008347"
        ],
        "id": 1034468,
        "name:xx": "Monteux"
      }
    },
    {
      "geometry": {
        "type": "Point",
        "coordinates": [
          4.3167,
          45.1833
        ]
      },
      "type": "Feature",
      "properties": {
        "hierarchy": [
          "tgn:1034469",
          "tgn:7002871",
          "tgn:1000003",
          "tgn:1000070",
          "tgn:7029392"
        ],
        "placetype": [
          "aat:300008347"
        ],
        "id": 1034469,
        "name:xx": "Montfaucon-en-Velay"
      }
    }
  ]
}
