{
  "geometry": {
    "type": "Point",
    "coordinates": [
      -108.7333,
      32.1333
    ]
  },
  "type": "Feature",
  "properties": {
    "hierarchy": [
      "tgn:2130165",
      "tgn:1000001",
      "tgn:7012149",
      "tgn:2001440",
      "tgn:7007566",
      "tgn:7029392"
    ],
    "placetype": [
      "aat:300000390"
    ],
    "id": 2130165,
    "name:xx": "Allen Mine"
  }
}
