{
  "type": "FeatureCollection",
  "features": [
    {
      "geometry": {
        "type": "Point",
        "coordinates": [
          73,
          10
        ]
      },
      "type": "Feature",
      "properties": {
        "hierarchy": [
          "tgn:1001890",
          "tgn:1000004",
          "tgn:7000198",
          "tgn:7029392"
        ],
        "placetype": [
          "aat:300387064",
          "aat:300387122"
        ],
        "id": 1001890,
        "name:xx": "Lakshadweep"
      }
    },
    {
      "geometry": {
        "type": "Point",
        "coordinates": [
          -69.8333,
          10.1667
        ]
      },
      "type": "Feature",
      "properties": {
        "hierarchy": [
          "tgn:1001891",
          "tgn:1000002",
          "tgn:1000059",
          "tgn:7029392"
        ],
        "placetype": [
          "aat:300008631",
          "aat:300387064",
          "aat:300000776"
        ],
        "id": 1001891,
        "name:xx": "Lara"
      }
    },
    {
      "geometry": {
        "type": "Point",
        "coordinates": [
          -71.1667,
          8.5
        ]
      },
      "type": "Feature",
      "properties": {
        "hierarchy": [
          "tgn:1001892",
          "tgn:1000002",
          "tgn:1000059",
          "tgn:7029392"
        ],
        "placetype": [
          "aat:300008631",
          "aat:300387064",
          "aat:300000776"
        ],
        "id": 1001892,
        "name:xx": "Mérida"
      }
    },
    {
      "geometry": {
        "type": "Point",
        "coordinates": [
          -99.5,
          19.333333
        ]
      },
      "type": "Feature",
      "properties": {
        "hierarchy": [
          "tgn:1001893",
          "tgn:1000001",
          "tgn:7005560",
          "tgn:7029392"
        ],
        "placetype": [
          "aat:300387064",
          "aat:300000776"
        ],
        "id": 1001893,
        "name:xx": "México"
      }
    },
    {
      "geometry": {
        "type": "Point",
        "coordinates": [
          79,
          22
        ]
      },
      "type": "Feature",
      "properties": {
        "hierarchy": [
          "tgn:1001894",
          "tgn:1000004",
          "tgn:7000198",
          "tgn:7029392"
        ],
        "placetype": [
          "aat:300387064",
          "aat:300000776"
        ],
        "id": 1001894,
        "name:xx": "Madhya Pradesh"
      }
    },
    {
      "geometry": {
        "type": "Point",
        "coordinates": [
          75,
          19.5
        ]
      },
      "type": "Feature",
      "properties": {
        "hierarchy": [
          "tgn:1001895",
          "tgn:1000004",
          "tgn:7000198",
          "tgn:7029392"
        ],
        "placetype": [
          "aat:300387064",
          "aat:300000776"
        ],
        "id": 1001895,
        "name:xx": "Mahārāshtra"
      }
    },
    {
      "geometry": {
        "type": "Point",
        "coordinates": [
          -55,
          -21
        ]
      },
      "type": "Feature",
      "properties": {
        "hierarchy": [
          "tgn:1001898",
          "tgn:7002454",
          "tgn:1000047",
          "tgn:1000002",
          "tgn:7029392"
        ],
        "placetype": [
          "aat:300008631",
          "aat:300387064",
          "aat:300387305",
          "aat:300000776"
        ],
        "id": 1001898,
        "name:xx": "Mato Grosso do Sul"
      }
    },
    {
      "geometry": {
        "type": "Point",
        "coordinates": [
          102.25,
          2.25
        ]
      },
      "type": "Feature",
      "properties": {
        "hierarchy": [
          "tgn:1001899",
          "tgn:7000317",
          "tgn:1000004",
          "tgn:1000128",
          "tgn:7029392"
        ],
        "placetype": [
          "aat:300235115",
          "aat:300387145",
          "aat:300000776"
        ],
        "id": 1001899,
        "name:xx": "Melaka"
      }
    }
  ]
}
