{
  "geometry": {
    "type": "Point",
    "coordinates": [
      -70.417,
      19.377
    ]
  },
  "type": "Feature",
  "properties": {
    "hierarchy": [
      "tgn:1016489",
      "tgn:7005415",
      "tgn:1000001",
      "tgn:7005388",
      "tgn:7029392"
    ],
    "placetype": [
      "aat:300008347",
      "aat:300387223",
      "aat:300008375"
    ],
    "id": 1016489,
    "name:xx": "Salcedo"
  }
}
