{
  "geometry": {
    "type": "Point",
    "coordinates": [
      -89.65,
      46.4333
    ]
  },
  "type": "Feature",
  "properties": {
    "hierarchy": [
      "tgn:2455541",
      "tgn:1000001",
      "tgn:7012149",
      "tgn:2000960",
      "tgn:7007520",
      "tgn:7029392"
    ],
    "placetype": [
      "aat:300008706"
    ],
    "id": 2455541,
    "name:xx": "Little Giant Creek"
  }
}
