{
  "geometry": {
    "type": "Point",
    "coordinates": [
      -113.7667,
      40.0833
    ]
  },
  "type": "Feature",
  "properties": {
    "hierarchy": [
      "tgn:2517192",
      "tgn:1000001",
      "tgn:7012149",
      "tgn:2002123",
      "tgn:7007827",
      "tgn:7029392"
    ],
    "placetype": [
      "aat:300008697"
    ],
    "id": 2517192,
    "name:xx": "Minnehaha Spring"
  }
}
