{
  "geometry": {
    "type": "Point",
    "coordinates": [
      -92.4833,
      45.4167
    ]
  },
  "type": "Feature",
  "properties": {
    "hierarchy": [
      "tgn:2451416",
      "tgn:1000001",
      "tgn:7012149",
      "tgn:2002346",
      "tgn:7007922",
      "tgn:7029392"
    ],
    "placetype": [
      "aat:300008680"
    ],
    "id": 2451416,
    "name:xx": "Little Bass Lake"
  }
}
