{
  "geometry": {
    "type": "Point",
    "coordinates": [
      -73.3167,
      44.55
    ]
  },
  "type": "Feature",
  "properties": {
    "hierarchy": [
      "tgn:2394314",
      "tgn:1000001",
      "tgn:2002132",
      "tgn:7012149",
      "tgn:7007828",
      "tgn:7029392"
    ],
    "placetype": [
      "aat:300132348"
    ],
    "id": 2394314,
    "name:xx": "Hogback Reef"
  }
}
