{
  "geometry": {
    "type": "Point",
    "coordinates": [
      28.5333,
      -21.4167
    ]
  },
  "type": "Feature",
  "properties": {
    "hierarchy": [
      "tgn:1092408",
      "tgn:7001242",
      "tgn:1001423",
      "tgn:1000185",
      "tgn:7029392"
    ],
    "placetype": [
      "aat:300008347"
    ],
    "id": 1092408,
    "name:xx": "Legion Mine"
  }
}
