{
  "geometry": {
    "type": "Point",
    "coordinates": [
      6.2833,
      46.3333
    ]
  },
  "type": "Feature",
  "properties": {
    "hierarchy": [
      "tgn:1032656",
      "tgn:1000003",
      "tgn:1000070",
      "tgn:7002897",
      "tgn:7029392"
    ],
    "placetype": [
      "aat:300008347"
    ],
    "id": 1032656,
    "name:xx": "Chens"
  }
}
