{
  "geometry": {
    "type": "Point",
    "coordinates": [
      75.644352,
      28.819379
    ]
  },
  "type": "Feature",
  "properties": {
    "hierarchy": [
      "tgn:7585428",
      "tgn:1000004",
      "tgn:1001871",
      "tgn:7000198",
      "tgn:7029392"
    ],
    "placetype": [
      "aat:300008688"
    ],
    "name:en": "Jauyānwāli Johri",
    "id": 7585428
  }
}
