{
  "geometry": {
    "type": "Point",
    "coordinates": [
      -80.6167,
      33.0333
    ]
  },
  "type": "Feature",
  "properties": {
    "hierarchy": [
      "tgn:2755808",
      "tgn:1000001",
      "tgn:2001739",
      "tgn:7012149",
      "tgn:7007712",
      "tgn:7029392"
    ],
    "placetype": [
      "aat:300008347"
    ],
    "id": 2755808,
    "name:xx": "Weeks"
  }
}
