{
  "geometry": {
    "type": "Point",
    "coordinates": [
      -82.3667,
      36.2167
    ]
  },
  "type": "Feature",
  "properties": {
    "hierarchy": [
      "tgn:2204700",
      "tgn:1000001",
      "tgn:7012149",
      "tgn:7007825",
      "tgn:7029392"
    ],
    "placetype": [
      "aat:300008798"
    ],
    "id": 2204700,
    "name:xx": "Buffalo Mountain"
  }
}
