{
  "geometry": {
    "type": "Point",
    "coordinates": [
      -89.6667,
      46.6333
    ]
  },
  "type": "Feature",
  "properties": {
    "hierarchy": [
      "tgn:2266283",
      "tgn:1000001",
      "tgn:7012149",
      "tgn:2000986",
      "tgn:7007520",
      "tgn:7029392"
    ],
    "placetype": [
      "aat:300008706"
    ],
    "id": 2266283,
    "name:xx": "Crazy Creek"
  }
}
