{
  "geometry": {
    "type": "Point",
    "coordinates": [
      -8.617,
      41.133
    ]
  },
  "type": "Feature",
  "properties": {
    "hierarchy": [
      "tgn:1049976",
      "tgn:7003826",
      "tgn:1000003",
      "tgn:1000090",
      "tgn:7029392"
    ],
    "placetype": [
      "aat:300008347"
    ],
    "id": 1049976,
    "name:xx": "Vila Nova de Gaia"
  }
}
