{
  "geometry": {
    "type": "Point",
    "coordinates": [
      -118.1167,
      35.5667
    ]
  },
  "type": "Feature",
  "properties": {
    "hierarchy": [
      "tgn:2667349",
      "tgn:1000001",
      "tgn:7012149",
      "tgn:1002545",
      "tgn:7007157",
      "tgn:7029392"
    ],
    "placetype": [
      "aat:300008798"
    ],
    "id": 2667349,
    "name:xx": "Skinner Peak"
  }
}
