{
  "geometry": {
    "type": "Point",
    "coordinates": [
      -111.7667,
      40.7667
    ]
  },
  "type": "Feature",
  "properties": {
    "hierarchy": [
      "tgn:2699493",
      "tgn:1000001",
      "tgn:7012149",
      "tgn:2002118",
      "tgn:7007827",
      "tgn:7029392"
    ],
    "placetype": [
      "aat:300008699"
    ],
    "id": 2699493,
    "name:xx": "Strongs Fork"
  }
}
