{
  "geometry": {
    "type": "Point",
    "coordinates": [
      -103.7333,
      34.8167
    ]
  },
  "type": "Feature",
  "properties": {
    "hierarchy": [
      "tgn:2605371",
      "tgn:1000001",
      "tgn:7012149",
      "tgn:2001448",
      "tgn:7007566",
      "tgn:7029392"
    ],
    "placetype": [
      "aat:300008798"
    ],
    "id": 2605371,
    "name:xx": "Ragland Hill"
  }
}
