{
  "geometry": {
    "type": "Point",
    "coordinates": [
      -96.2833,
      42.1833
    ]
  },
  "type": "Feature",
  "properties": {
    "hierarchy": [
      "tgn:2127986",
      "tgn:1000001",
      "tgn:7012149",
      "tgn:2000627",
      "tgn:7007253",
      "tgn:7029392"
    ],
    "placetype": [
      "aat:300008347"
    ],
    "id": 2127986,
    "name:xx": "Albaton"
  }
}
