{
  "geometry": {
    "type": "Point",
    "coordinates": [
      -71.0833,
      41.7333
    ]
  },
  "type": "Feature",
  "properties": {
    "hierarchy": [
      "tgn:2591964",
      "tgn:1002201",
      "tgn:1000001",
      "tgn:7012149",
      "tgn:7007517",
      "tgn:7029392"
    ],
    "placetype": [
      "aat:300008905"
    ],
    "id": 2591964,
    "name:xx": "Pond Swamp"
  }
}
