{
  "geometry": {
    "type": "Point",
    "coordinates": [
      -24.35,
      14.9333
    ]
  },
  "type": "Feature",
  "properties": {
    "hierarchy": [
      "tgn:1106044",
      "tgn:1007114",
      "tgn:7001635",
      "tgn:7001242",
      "tgn:7001632",
      "tgn:7029392"
    ],
    "placetype": [
      "aat:300008795"
    ],
    "id": 1106044,
    "name:xx": "Pico"
  }
}
