{
  "type": "FeatureCollection",
  "features": [
    {
      "geometry": {
        "type": "Point",
        "coordinates": [
          -112.9333,
          46.1667
        ]
      },
      "type": "Feature",
      "properties": {
        "hierarchy": [
          "tgn:2061010",
          "tgn:1000001",
          "tgn:7012149",
          "tgn:7020792",
          "tgn:7007524",
          "tgn:7029392"
        ],
        "placetype": [
          "aat:300008347"
        ],
        "id": 2061010,
        "name:xx": "Lost Creek"
      }
    },
    {
      "geometry": {
        "type": "Point",
        "coordinates": [
          -112.8167,
          46.1
        ]
      },
      "type": "Feature",
      "properties": {
        "hierarchy": [
          "tgn:2061013",
          "tgn:1000001",
          "tgn:7012149",
          "tgn:7020792",
          "tgn:7007524",
          "tgn:7029392"
        ],
        "placetype": [
          "aat:300008347"
        ],
        "id": 2061013,
        "name:xx": "Opportunity"
      }
    },
    {
      "geometry": {
        "type": "Point",
        "coordinates": [
          -113.2333,
          46.2
        ]
      },
      "type": "Feature",
      "properties": {
        "hierarchy": [
          "tgn:2061014",
          "tgn:1000001",
          "tgn:7012149",
          "tgn:7020792",
          "tgn:7007524",
          "tgn:7029392"
        ],
        "placetype": [
          "aat:300008347"
        ],
        "id": 2061014,
        "name:xx": "Southern Cross"
      }
    }
  ]
}
