{
  "geometry": {
    "type": "Point",
    "coordinates": [
      -80.7833,
      28.85
    ]
  },
  "type": "Feature",
  "properties": {
    "hierarchy": [
      "tgn:2509688",
      "tgn:1000001",
      "tgn:7012149",
      "tgn:1002977",
      "tgn:7007240",
      "tgn:7029392"
    ],
    "placetype": [
      "aat:300008791"
    ],
    "id": 2509688,
    "name:xx": "Middle Island"
  }
}
