{
  "type": "FeatureCollection",
  "features": [
    {
      "geometry": {
        "type": "Point",
        "coordinates": [
          -74.2167,
          43.05
        ]
      },
      "type": "Feature",
      "properties": {
        "hierarchy": [
          "tgn:2072840",
          "tgn:1000001",
          "tgn:7012149",
          "tgn:1002397",
          "tgn:7007568",
          "tgn:7029392"
        ],
        "placetype": [
          "aat:300008347"
        ],
        "id": 2072840,
        "name:xx": "Vail Mills"
      }
    },
    {
      "geometry": {
        "type": "Point",
        "coordinates": [
          -74.05,
          41.45
        ]
      },
      "type": "Feature",
      "properties": {
        "hierarchy": [
          "tgn:2072841",
          "tgn:1000001",
          "tgn:7012149",
          "tgn:1002751",
          "tgn:7007568",
          "tgn:7029392"
        ],
        "placetype": [
          "aat:300008347"
        ],
        "id": 2072841,
        "name:xx": "Vails Gate"
      }
    },
    {
      "geometry": {
        "type": "Point",
        "coordinates": [
          -73.6667,
          42.4
        ]
      },
      "type": "Feature",
      "properties": {
        "hierarchy": [
          "tgn:2072842",
          "tgn:1000001",
          "tgn:7013638",
          "tgn:7012149",
          "tgn:7007568",
          "tgn:7029392"
        ],
        "placetype": [
          "aat:300008347"
        ],
        "id": 2072842,
        "name:xx": "Valatie"
      }
    },
    {
      "geometry": {
        "type": "Point",
        "coordinates": [
          -73.4333,
          44.6
        ]
      },
      "type": "Feature",
      "properties": {
        "hierarchy": [
          "tgn:2072843",
          "tgn:1000001",
          "tgn:1002284",
          "tgn:7012149",
          "tgn:7007568",
          "tgn:7029392"
        ],
        "placetype": [
          "aat:300008347",
          "aat:300387210"
        ],
        "id": 2072843,
        "name:xx": "Valcour"
      }
    },
    {
      "geometry": {
        "type": "Point",
        "coordinates": [
          -73.7667,
          41.0667
        ]
      },
      "type": "Feature",
      "properties": {
        "hierarchy": [
          "tgn:2072844",
          "tgn:1000001",
          "tgn:7012149",
          "tgn:7014612",
          "tgn:7007568",
          "tgn:7029392"
        ],
        "placetype": [
          "aat:300008347"
        ],
        "id": 2072844,
        "name:xx": "Valhalla"
      }
    },
    {
      "geometry": {
        "type": "Point",
        "coordinates": [
          -73.95,
          41.1167
        ]
      },
      "type": "Feature",
      "properties": {
        "hierarchy": [
          "tgn:2072845",
          "tgn:1000001",
          "tgn:7012149",
          "tgn:1002833",
          "tgn:7007568",
          "tgn:7029392"
        ],
        "placetype": [
          "aat:300008347"
        ],
        "id": 2072845,
        "name:xx": "Valley Cottage"
      }
    }
  ]
}
