{
  "geometry": {
    "type": "Point",
    "coordinates": [
      -81.3667,
      37.5667
    ]
  },
  "type": "Feature",
  "properties": {
    "hierarchy": [
      "tgn:2119331",
      "tgn:1000001",
      "tgn:7012149",
      "tgn:2002304",
      "tgn:7013961",
      "tgn:7029392"
    ],
    "placetype": [
      "aat:300008347"
    ],
    "id": 2119331,
    "name:xx": "Mullens"
  }
}
