{
  "geometry": {
    "type": "Point",
    "coordinates": [
      -80.65,
      34.5167
    ]
  },
  "type": "Feature",
  "properties": {
    "hierarchy": [
      "tgn:2302770",
      "tgn:1000001",
      "tgn:7012149",
      "tgn:2001752",
      "tgn:7007712",
      "tgn:7029392"
    ],
    "placetype": [
      "aat:300008699"
    ],
    "id": 2302770,
    "name:xx": "Dye Mill Branch"
  }
}
