{
  "geometry": {
    "type": "Point",
    "coordinates": [
      -72.35,
      41.3167
    ]
  },
  "type": "Feature",
  "properties": {
    "hierarchy": [
      "tgn:2215536",
      "tgn:1000001",
      "tgn:1002714",
      "tgn:7012149",
      "tgn:7007159",
      "tgn:7029392"
    ],
    "placetype": [
      "aat:300132348"
    ],
    "id": 2215536,
    "name:xx": "Calves Island Bar"
  }
}
