{
  "geometry": {
    "type": "Point",
    "coordinates": [
      -87.6667,
      45.5333
    ]
  },
  "type": "Feature",
  "properties": {
    "hierarchy": [
      "tgn:2460703",
      "tgn:1000001",
      "tgn:7012149",
      "tgn:2000978",
      "tgn:7007520",
      "tgn:7029392"
    ],
    "placetype": [
      "aat:300008706"
    ],
    "id": 2460703,
    "name:xx": "Little Shakey Creek"
  }
}
