{
  "geometry": {
    "type": "Point",
    "coordinates": [
      85.70144,
      25.36354
    ]
  },
  "type": "Feature",
  "properties": {
    "hierarchy": [
      "tgn:7557273",
      "tgn:1000004",
      "tgn:1001842",
      "tgn:7000198",
      "tgn:7029392"
    ],
    "placetype": [
      "aat:300008347"
    ],
    "name:en": "Saksohāra",
    "id": 7557273
  }
}
