{
  "geometry": {
    "type": "Point",
    "coordinates": [
      -104.1833,
      36.7333
    ]
  },
  "type": "Feature",
  "properties": {
    "hierarchy": [
      "tgn:2730370",
      "tgn:1000001",
      "tgn:2001432",
      "tgn:7012149",
      "tgn:7007566",
      "tgn:7029392"
    ],
    "placetype": [
      "aat:300008798"
    ],
    "id": 2730370,
    "name:xx": "Troyburg Mesa"
  }
}
