{
  "geometry": {
    "type": "Point",
    "coordinates": [
      -83.2833,
      38.7833
    ]
  },
  "type": "Feature",
  "properties": {
    "hierarchy": [
      "tgn:2748668",
      "tgn:1002136",
      "tgn:1000001",
      "tgn:7012149",
      "tgn:7007706",
      "tgn:7029392"
    ],
    "placetype": [
      "aat:300008699"
    ],
    "id": 2748668,
    "name:xx": "Walker Run"
  }
}
