{
  "type": "FeatureCollection",
  "features": [
    {
      "geometry": {
        "type": "Point",
        "coordinates": [
          -85.35,
          43.6167
        ]
      },
      "type": "Feature",
      "properties": {
        "hierarchy": [
          "tgn:2687500",
          "tgn:1000001",
          "tgn:7012149",
          "tgn:2000977",
          "tgn:7007520",
          "tgn:7029392"
        ],
        "placetype": [
          "aat:300008680"
        ],
        "id": 2687500,
        "name:xx": "Spring Lakes"
      }
    },
    {
      "geometry": {
        "type": "Point",
        "coordinates": [
          -89.45,
          32.1167
        ]
      },
      "type": "Feature",
      "properties": {
        "hierarchy": [
          "tgn:2687501",
          "tgn:1000001",
          "tgn:7012149",
          "tgn:2001150",
          "tgn:7007522",
          "tgn:7029392"
        ],
        "placetype": [
          "aat:300006191"
        ],
        "id": 2687501,
        "name:xx": "Spring Lakes"
      }
    },
    {
      "geometry": {
        "type": "Point",
        "coordinates": [
          -114.6833,
          48.65
        ]
      },
      "type": "Feature",
      "properties": {
        "hierarchy": [
          "tgn:2687503",
          "tgn:1000001",
          "tgn:7012149",
          "tgn:2001274",
          "tgn:7007524",
          "tgn:7029392"
        ],
        "placetype": [
          "aat:300008680"
        ],
        "id": 2687503,
        "name:xx": "Spring Lakes"
      }
    },
    {
      "geometry": {
        "type": "Point",
        "coordinates": [
          -73.8,
          42.0167
        ]
      },
      "type": "Feature",
      "properties": {
        "hierarchy": [
          "tgn:2687504",
          "tgn:1000001",
          "tgn:1002347",
          "tgn:7012149",
          "tgn:7007568",
          "tgn:7029392"
        ],
        "placetype": [
          "aat:300008680"
        ],
        "id": 2687504,
        "name:xx": "Spring Lakes"
      }
    },
    {
      "geometry": {
        "type": "Point",
        "coordinates": [
          -82.9333,
          39.9333
        ]
      },
      "type": "Feature",
      "properties": {
        "hierarchy": [
          "tgn:2687505",
          "tgn:1000001",
          "tgn:7012149",
          "tgn:1002386",
          "tgn:7007706",
          "tgn:7029392"
        ],
        "placetype": [
          "aat:300006191"
        ],
        "id": 2687505,
        "name:xx": "Spring Lakes"
      }
    },
    {
      "geometry": {
        "type": "Point",
        "coordinates": [
          -119.9333,
          47.1167
        ]
      },
      "type": "Feature",
      "properties": {
        "hierarchy": [
          "tgn:2687506",
          "tgn:1000001",
          "tgn:7012149",
          "tgn:2002246",
          "tgn:7007920",
          "tgn:7029392"
        ],
        "placetype": [
          "aat:300008680"
        ],
        "id": 2687506,
        "name:xx": "Spring Lakes"
      }
    },
    {
      "geometry": {
        "type": "Point",
        "coordinates": [
          -111.8333,
          40.65
        ]
      },
      "type": "Feature",
      "properties": {
        "hierarchy": [
          "tgn:2687507",
          "tgn:1000001",
          "tgn:7012149",
          "tgn:2002118",
          "tgn:7007827",
          "tgn:7029392"
        ],
        "placetype": [
          "aat:300008347"
        ],
        "id": 2687507,
        "name:xx": "Spring Lane Condominium"
      }
    },
    {
      "geometry": {
        "type": "Point",
        "coordinates": [
          -78.3667,
          39.6833
        ]
      },
      "type": "Feature",
      "properties": {
        "hierarchy": [
          "tgn:2687508",
          "tgn:2000934",
          "tgn:1000001",
          "tgn:7012149",
          "tgn:7007516",
          "tgn:7029392"
        ],
        "placetype": [
          "aat:300008761"
        ],
        "id": 2687508,
        "name:xx": "Spring Lick Hollow"
      }
    },
    {
      "geometry": {
        "type": "Point",
        "coordinates": [
          -79.2,
          39.5
        ]
      },
      "type": "Feature",
      "properties": {
        "hierarchy": [
          "tgn:2687509",
          "tgn:1000001",
          "tgn:2000935",
          "tgn:7012149",
          "tgn:7007516",
          "tgn:7029392"
        ],
        "placetype": [
          "aat:300008699"
        ],
        "id": 2687509,
        "name:xx": "Spring Lick Run"
      }
    }
  ]
}
