{
  "geometry": {
    "type": "Point",
    "coordinates": [
      -94.4333,
      46.3667
    ]
  },
  "type": "Feature",
  "properties": {
    "hierarchy": [
      "tgn:2700014",
      "tgn:1000001",
      "tgn:2001009",
      "tgn:7012149",
      "tgn:7007521",
      "tgn:7029392"
    ],
    "placetype": [
      "aat:300008680"
    ],
    "id": 2700014,
    "name:xx": "Stump Lake"
  }
}
