{
  "geometry": {
    "type": "Point",
    "coordinates": [
      77.95,
      11.65
    ]
  },
  "type": "Feature",
  "properties": {
    "hierarchy": [
      "tgn:7557323",
      "tgn:1000004",
      "tgn:7000198",
      "tgn:7001797",
      "tgn:7029392"
    ],
    "placetype": [
      "aat:300008347"
    ],
    "name:en": "Pāppambādi",
    "id": 7557323
  }
}
