{
  "geometry": {
    "type": "Point",
    "coordinates": [
      -118.2667,
      44.8667
    ]
  },
  "type": "Feature",
  "properties": {
    "hierarchy": [
      "tgn:2463477",
      "tgn:1000001",
      "tgn:7012149",
      "tgn:2001708",
      "tgn:7007708",
      "tgn:7029392"
    ],
    "placetype": [
      "aat:300000390"
    ],
    "id": 2463477,
    "name:xx": "Loa Mae Mine"
  }
}
