{
  "geometry": {
    "type": "Point",
    "coordinates": [
      31.44533,
      29.502238
    ]
  },
  "type": "Feature",
  "properties": {
    "hierarchy": [
      "tgn:7520540",
      "tgn:7001242",
      "tgn:7016833",
      "tgn:7029392"
    ],
    "placetype": [
      "aat:300379998"
    ],
    "name:en": "Abū Ţurayfī, Wādī",
    "id": 7520540
  }
}
