{
  "geometry": {
    "type": "Point",
    "coordinates": [
      -91.6167,
      47.85
    ]
  },
  "type": "Feature",
  "properties": {
    "hierarchy": [
      "tgn:2455473",
      "tgn:1000001",
      "tgn:7012149",
      "tgn:2001036",
      "tgn:7007521",
      "tgn:7029392"
    ],
    "placetype": [
      "aat:300006191"
    ],
    "id": 2455473,
    "name:xx": "Little Gabbro Lake"
  }
}
