{
  "geometry": {
    "type": "Point",
    "coordinates": [
      -107.95,
      39.0167
    ]
  },
  "type": "Feature",
  "properties": {
    "hierarchy": [
      "tgn:2258815",
      "tgn:1000001",
      "tgn:7012149",
      "tgn:2000206",
      "tgn:7007158",
      "tgn:7029392"
    ],
    "placetype": [
      "aat:300008706"
    ],
    "id": 2258815,
    "name:xx": "Cottonwood Creek"
  }
}
