{
  "geometry": {
    "type": "Point",
    "coordinates": [
      -84.438,
      14.633
    ]
  },
  "type": "Feature",
  "properties": {
    "hierarchy": [
      "tgn:1131649",
      "tgn:7593358",
      "tgn:1000001",
      "tgn:7005562",
      "tgn:7029392"
    ],
    "placetype": [
      "aat:300008707"
    ],
    "id": 1131649,
    "name:xx": "Waspuk, Río"
  }
}
