{
  "geometry": {
    "type": "Point",
    "coordinates": [
      -99.25,
      28.8167
    ]
  },
  "type": "Feature",
  "properties": {
    "hierarchy": [
      "tgn:2528564",
      "tgn:1000001",
      "tgn:7012149",
      "tgn:2001987",
      "tgn:7007826",
      "tgn:7029392"
    ],
    "placetype": [
      "aat:300006191"
    ],
    "id": 2528564,
    "name:xx": "Muchacho Tank"
  }
}
