{
  "geometry": {
    "type": "Point",
    "coordinates": [
      -82.6333,
      35.1667
    ]
  },
  "type": "Feature",
  "properties": {
    "hierarchy": [
      "tgn:2201812",
      "tgn:1000001",
      "tgn:7012149",
      "tgn:2001544",
      "tgn:7007709",
      "tgn:7029392"
    ],
    "placetype": [
      "aat:300055621"
    ],
    "id": 2201812,
    "name:xx": "Buck Forest"
  }
}
