{
  "geometry": {
    "type": "Point",
    "coordinates": [
      -147.7667,
      64.8833
    ]
  },
  "type": "Feature",
  "properties": {
    "hierarchy": [
      "tgn:2614535",
      "tgn:7006450",
      "tgn:1000001",
      "tgn:7019674",
      "tgn:7012149",
      "tgn:7029392"
    ],
    "placetype": [
      "aat:300008680"
    ],
    "id": 2614535,
    "name:xx": "Reindeer Lake"
  }
}
