{
  "type": "FeatureCollection",
  "features": [
    {
      "geometry": {
        "type": "Point",
        "coordinates": [
          9.983333,
          51.283333
        ]
      },
      "type": "Feature",
      "properties": {
        "hierarchy": [
          "tgn:1038382",
          "tgn:1000003",
          "tgn:7003678",
          "tgn:7000084",
          "tgn:7029392"
        ],
        "placetype": [
          "aat:300008347"
        ],
        "id": 1038382,
        "name:xx": "Bad Sooden-Allendorf"
      }
    },
    {
      "geometry": {
        "type": "Point",
        "coordinates": [
          11.65,
          50.366667
        ]
      },
      "type": "Feature",
      "properties": {
        "hierarchy": [
          "tgn:1038383",
          "tgn:7003669",
          "tgn:1000003",
          "tgn:7000084",
          "tgn:7029392"
        ],
        "placetype": [
          "aat:300008347"
        ],
        "id": 1038383,
        "name:xx": "Bad Steben"
      }
    },
    {
      "geometry": {
        "type": "Point",
        "coordinates": [
          8.6833,
          48.7
        ]
      },
      "type": "Feature",
      "properties": {
        "hierarchy": [
          "tgn:1038385",
          "tgn:7003692",
          "tgn:1000003",
          "tgn:7000084",
          "tgn:7029392"
        ],
        "placetype": [
          "aat:300008347"
        ],
        "id": 1038385,
        "name:xx": "Bad Teinach"
      }
    },
    {
      "geometry": {
        "type": "Point",
        "coordinates": [
          9.4,
          48.5
        ]
      },
      "type": "Feature",
      "properties": {
        "hierarchy": [
          "tgn:1038386",
          "tgn:7003692",
          "tgn:1000003",
          "tgn:7000084",
          "tgn:7029392"
        ],
        "placetype": [
          "aat:300008347"
        ],
        "id": 1038386,
        "name:xx": "Bad Urach"
      }
    },
    {
      "geometry": {
        "type": "Point",
        "coordinates": [
          8.75,
          50.183333
        ]
      },
      "type": "Feature",
      "properties": {
        "hierarchy": [
          "tgn:1038387",
          "tgn:1000003",
          "tgn:7003678",
          "tgn:7000084",
          "tgn:7029392"
        ],
        "placetype": [
          "aat:300008347"
        ],
        "id": 1038387,
        "name:xx": "Bad Vilbel"
      }
    },
    {
      "geometry": {
        "type": "Point",
        "coordinates": [
          10.6,
          48.016667
        ]
      },
      "type": "Feature",
      "properties": {
        "hierarchy": [
          "tgn:1038388",
          "tgn:7003669",
          "tgn:1000003",
          "tgn:7000084",
          "tgn:7029392"
        ],
        "placetype": [
          "aat:300008347"
        ],
        "id": 1038388,
        "name:xx": "Bad Wörishofen"
      }
    },
    {
      "geometry": {
        "type": "Point",
        "coordinates": [
          9.766667,
          47.916667
        ]
      },
      "type": "Feature",
      "properties": {
        "hierarchy": [
          "tgn:1038389",
          "tgn:7003692",
          "tgn:1000003",
          "tgn:7000084",
          "tgn:7029392"
        ],
        "placetype": [
          "aat:300008347"
        ],
        "id": 1038389,
        "name:xx": "Bad Waldsee"
      }
    }
  ]
}
