{
  "geometry": {
    "type": "Point",
    "coordinates": [
      -90.3833,
      43.1833
    ]
  },
  "type": "Feature",
  "properties": {
    "hierarchy": [
      "tgn:2468103",
      "tgn:1000001",
      "tgn:7012149",
      "tgn:2002326",
      "tgn:7007922",
      "tgn:7029392"
    ],
    "placetype": [
      "aat:300008680"
    ],
    "id": 2468103,
    "name:xx": "Long Lake"
  }
}
