{
  "geometry": {
    "type": "Point",
    "coordinates": [
      -111.9833,
      42.1167
    ]
  },
  "type": "Feature",
  "properties": {
    "hierarchy": [
      "tgn:2736119",
      "tgn:1000001",
      "tgn:7012149",
      "tgn:2000472",
      "tgn:7007250",
      "tgn:7029392"
    ],
    "placetype": [
      "aat:300006075"
    ],
    "id": 2736119,
    "name:xx": "Twin Lakes Canal West Lateral"
  }
}
