{
  "geometry": {
    "type": "Point",
    "coordinates": [
      -109.35,
      33.3333
    ]
  },
  "type": "Feature",
  "properties": {
    "hierarchy": [
      "tgn:2727732",
      "tgn:1000001",
      "tgn:7006451",
      "tgn:2000095",
      "tgn:7012149",
      "tgn:7029392"
    ],
    "placetype": [
      "aat:300006191"
    ],
    "id": 2727732,
    "name:xx": "Trail Tank"
  }
}
