{
  "geometry": {
    "type": "Point",
    "coordinates": [
      -78.3667,
      38.05
    ]
  },
  "type": "Feature",
  "properties": {
    "hierarchy": [
      "tgn:2701957",
      "tgn:2002137",
      "tgn:1000001",
      "tgn:7012149",
      "tgn:7007919",
      "tgn:7029392"
    ],
    "placetype": [
      "aat:300008798"
    ],
    "id": 2701957,
    "name:xx": "Sugarloaf Mountain"
  }
}
