{
  "geometry": {
    "type": "Point",
    "coordinates": [
      -71.85,
      45.3667
    ]
  },
  "type": "Feature",
  "properties": {
    "hierarchy": [
      "tgn:1015483",
      "tgn:7005685",
      "tgn:1000001",
      "tgn:7005804",
      "tgn:7029392"
    ],
    "placetype": [
      "aat:300008347"
    ],
    "id": 1015483,
    "name:xx": "Lennoxville"
  }
}
