{
  "geometry": {
    "type": "Point",
    "coordinates": [
      -76.1333,
      39.0167
    ]
  },
  "type": "Feature",
  "properties": {
    "hierarchy": [
      "tgn:2721491",
      "tgn:1000001",
      "tgn:2124025",
      "tgn:7012149",
      "tgn:7007516",
      "tgn:7029392"
    ],
    "placetype": [
      "aat:300008706"
    ],
    "id": 2721491,
    "name:xx": "Tilghman Creek"
  }
}
