{
  "geometry": {
    "type": "Point",
    "coordinates": [
      -82.75,
      8.7667
    ]
  },
  "type": "Feature",
  "properties": {
    "hierarchy": [
      "tgn:1018878",
      "tgn:1001201",
      "tgn:1000001",
      "tgn:7005565",
      "tgn:7029392"
    ],
    "placetype": [
      "aat:300008347"
    ],
    "id": 1018878,
    "name:xx": "Caisán"
  }
}
