{
  "geometry": {
    "type": "Point",
    "coordinates": [
      117.1333,
      25.7333
    ]
  },
  "type": "Feature",
  "properties": {
    "hierarchy": [
      "tgn:1072886",
      "tgn:1000004",
      "tgn:7001796",
      "tgn:1000111",
      "tgn:7029392"
    ],
    "placetype": [
      "aat:300008347"
    ],
    "id": 1072886,
    "name:xx": "Xiaotao"
  }
}
