{
  "geometry": {
    "type": "Point",
    "coordinates": [
      -88.85,
      39.7333
    ]
  },
  "type": "Feature",
  "properties": {
    "hierarchy": [
      "tgn:2167475",
      "tgn:1000001",
      "tgn:7012149",
      "tgn:1002618",
      "tgn:7007251",
      "tgn:7029392"
    ],
    "placetype": [
      "aat:300008706"
    ],
    "id": 2167475,
    "name:xx": "Big Creek"
  }
}
