{
  "geometry": {
    "type": "Point",
    "coordinates": [
      -86.8333,
      30.9167
    ]
  },
  "type": "Feature",
  "properties": {
    "hierarchy": [
      "tgn:2228282",
      "tgn:1000001",
      "tgn:7012149",
      "tgn:2000285",
      "tgn:7007240",
      "tgn:7029392"
    ],
    "placetype": [
      "aat:300008706"
    ],
    "id": 2228282,
    "name:xx": "Cedar Creek"
  }
}
